{
  "type": "Feature",
  "properties": {
    "addr:full":"2 Queens Road Chislehurst Kent BR7 5AZ",
    "addr:housenumber":"2",
    "addr:postcode":"br7 5az",
    "addr:street":"Queens Road",
    "iso:country":"GB",
    "sg:address":"2 Queens Road",
    "sg:city":"Chislehurst",
    "sg:classifiers":[
        {
            "category":"Shopping",
            "subcategory":"Musical Instruments",
            "type":"Retail Goods"
        },
        {
            "category":"Manufacturing",
            "subcategory":"Furniture",
            "type":"Manufacturing & Wholesale Goods"
        }
    ],
    "sg:phone":"+44 20 8295 3505",
    "sg:postcode":"BR7 5AZ",
    "sg:province":"Kent",
    "sg:tags":[
        "polishing",
        "french"
    ],
    "wof:name":"Oakleigh French Polishers",
    "wof:placetype":"venue"
},
  "geometry": {"coordinates":[0.068482,51.418636],"type":"Point"}
}