{
  "type": "Feature",
  "properties": {
    "addr:full":"Helenslee Road Dumbarton Argyll and Bute G82 4AQ",
    "addr:postcode":"g82 4aq",
    "addr:street":"Helenslee Road",
    "iso:country":"GB",
    "sg:address":"Helenslee Road",
    "sg:city":"Dumbarton",
    "sg:classifiers":[
        {
            "category":"Arena",
            "subcategory":"Sports Club",
            "type":"Entertainment"
        }
    ],
    "sg:phone":"+44 1389 732855",
    "sg:postcode":"G82 4AQ",
    "sg:province":"Argyll and Bute",
    "wof:name":"Dixon Bowling Club",
    "wof:placetype":"venue"
},
  "geometry": {"coordinates":[-4.5815639496,55.9434738159],"type":"Point"}
}