{
  "type": "Feature",
  "properties": {
    "addr:full":"310 Clipsley Lane, Haydock St Helens Lancashire WA11 0JQ",
    "addr:housenumber":"310",
    "addr:postcode":"wa11 0jq",
    "addr:street":"Clipsley Lane Haydock",
    "iso:country":"GB",
    "sg:address":"310 Clipsley Lane, Haydock",
    "sg:city":"St Helens",
    "sg:classifiers":[
        {
            "category":"Personal",
            "subcategory":"Beauty Salon",
            "type":"Services"
        }
    ],
    "sg:phone":"+44 1744 28869",
    "sg:postcode":"WA11 0JQ",
    "sg:province":"Lancashire",
    "sg:tags":[
        "unisex",
        "hairdresser"
    ],
    "wof:name":"Nutters",
    "wof:placetype":"venue"
},
  "geometry": {"coordinates":[-2.6770000458,53.4667358398],"type":"Point"}
}