{
  "type": "Feature",
  "properties": {
    "addr:full":"58 Gurney Avenue Hereford Herefordshire HR1 1XW",
    "addr:housenumber":"58",
    "addr:postcode":"hr1 1xw",
    "addr:street":"Gurney Avenue",
    "iso:country":"GB",
    "sg:address":"58 Gurney Avenue",
    "sg:city":"Hereford",
    "sg:classifiers":[
        {
            "category":"Health Services",
            "subcategory":"Health Practitioner",
            "type":"Services"
        }
    ],
    "sg:postcode":"HR1 1XW",
    "sg:province":"Herefordshire",
    "sg:tags":[
        "psychotherapist"
    ],
    "wof:name":"Psychotherapy & Hypnotherapy",
    "wof:placetype":"venue"
},
  "geometry": {"coordinates":[-2.677076,52.050808],"type":"Point"}
}