{
  "type": "Feature",
  "properties": {
    "iso:country":"GB",
    "sg:address":"Ronald Court, The Street, Bramley",
    "sg:city":"Tadley",
    "sg:classifiers":[
        {
            "category":"Professional",
            "subcategory":"Business Services",
            "type":"Services"
        }
    ],
    "sg:phone":"+44 1256 882118",
    "sg:postcode":"RG26 5BT",
    "sg:province":"Berkshire",
    "sg:tags":[
        "shop",
        "cleaning"
    ],
    "wof:name":"Fresh & Clean Services",
    "wof:placetype":"venue"
},
  "geometry": {"coordinates":[-1.0618189573,51.3303909302],"type":"Point"}
}