{
  "type": "Feature",
  "properties": {
    "iso:country":"GB",
    "sg:address":"Couper Street",
    "sg:city":"Glasgow",
    "sg:classifiers":[
        {
            "category":"Manufacturing",
            "subcategory":"Tools & Machinery",
            "type":"Manufacturing & Wholesale Goods"
        },
        {
            "category":"Autos & Motor Vehicles",
            "subcategory":"Auto Supplies",
            "type":"Retail Goods"
        }
    ],
    "sg:phone":"+44 141 552 5591",
    "sg:postcode":"G4 0DL",
    "sg:province":"Glasgow City",
    "sg:tags":[
        "car",
        "part",
        "power",
        "accessory"
    ],
    "wof:name":"MAXIM POWER TOOLS (SCOTLAND) LTD",
    "wof:placetype":"venue"
},
  "geometry": {"coordinates":[-4.245898,55.867271],"type":"Point"}
}