{
  "type": "Feature",
  "properties": {
    "iso:country":"GB",
    "sg:address":"Attleborough Road",
    "sg:city":"Nuneaton",
    "sg:classifiers":[
        {
            "category":"Health Services",
            "subcategory":"Nursing And Care Facility",
            "type":"Services"
        },
        {
            "category":"Social Services",
            "subcategory":"Retirement Home",
            "type":"Services"
        }
    ],
    "sg:phone":"+44 24 7638 3543",
    "sg:postcode":"CV11 4JN",
    "sg:province":"Leicestershire",
    "sg:tags":[
        "residential"
    ],
    "wof:name":"Attleborough Grange",
    "wof:placetype":"venue"
},
  "geometry": {"coordinates":[-1.461329,52.5201],"type":"Point"}
}