{
  "type": "Feature",
  "properties": {
    "addr:full":"28 Keirby Walk Burnley Lancashire BB11 2DE",
    "addr:housenumber":"28",
    "addr:postcode":"bb11 2de",
    "addr:street":"Keirby Walk",
    "iso:country":"GB",
    "sg:address":"28 Keirby Walk",
    "sg:city":"Burnley",
    "sg:classifiers":[
        {
            "category":"Personal",
            "subcategory":"Beauty Salon",
            "type":"Services"
        }
    ],
    "sg:postcode":"BB11 2DE",
    "sg:province":"Lancashire",
    "sg:tags":[
        "unisex",
        "hairdresser"
    ],
    "wof:name":"Alexander,Pierre,",
    "wof:placetype":"venue"
},
  "geometry": {"coordinates":[-2.23961,53.789787],"type":"Point"}
}