{
  "type": "Feature",
  "properties": {
    "iso:country":"GB",
    "sg:address":"27-31 The Esplanade, Knott-end-on-sea",
    "sg:city":"Poulton-le-fylde",
    "sg:classifiers":[
        {
            "category":"Health Services",
            "subcategory":"Nursing And Care Facility",
            "type":"Services"
        },
        {
            "category":"Social Services",
            "subcategory":"Retirement Home",
            "type":"Services"
        }
    ],
    "sg:phone":"+44 1253 810888",
    "sg:postcode":"FY6 0AD",
    "sg:province":"Lancashire",
    "sg:tags":[
        "residential"
    ],
    "wof:name":"Sea Bank House",
    "wof:placetype":"venue"
},
  "geometry": {"coordinates":[-2.9914999008,53.9283485413],"type":"Point"}
}