{
  "type": "Feature",
  "properties": {
    "addr:full":"The Old Post Office, 38 South Riding St Albans Hertfordshire AL2 3NE",
    "addr:housenumber":"38",
    "addr:postcode":"al2 3ne",
    "addr:street":"South Riding",
    "iso:country":"GB",
    "sg:address":"The Old Post Office, 38 South Riding",
    "sg:city":"St Albans",
    "sg:classifiers":[
        {
            "category":"Professional",
            "subcategory":"Computer Services",
            "type":"Services"
        }
    ],
    "sg:phone":"+44 1923 661440",
    "sg:postcode":"AL2 3NE",
    "sg:province":"Hertfordshire",
    "sg:tags":[
        "consultant"
    ],
    "wof:name":"Computer Services Ltd",
    "wof:placetype":"venue"
},
  "geometry": {"coordinates":[-0.36638,51.70742],"type":"Point"}
}