{
  "type": "Feature",
  "properties": {
    "addr:full":"7 Hawks Road Hailsham East Sussex BN27 3BL",
    "addr:housenumber":"7",
    "addr:postcode":"bn27 3bl",
    "addr:street":"Hawks Road",
    "iso:country":"GB",
    "sg:address":"7 Hawks Road",
    "sg:city":"Hailsham",
    "sg:classifiers":[
        {
            "category":"Home & Garden",
            "subcategory":"Carpets & Floor Coverings",
            "type":"Retail Goods"
        }
    ],
    "sg:phone":"+44 1323 843715",
    "sg:postcode":"BN27 3BL",
    "sg:province":"East Sussex",
    "sg:tags":[
        "carpets",
        "rug",
        "matting"
    ],
    "wof:name":"Soft Floors",
    "wof:placetype":"venue"
},
  "geometry": {"coordinates":[0.251283,50.871143],"type":"Point"}
}