{
  "type": "Feature",
  "properties": {
    "iso:country":"GB",
    "sg:address":"Granby Buildings, 37 Granby Street",
    "sg:city":"Leicester",
    "sg:classifiers":[
        {
            "category":"Shopping",
            "subcategory":"Thrift Store",
            "type":"Retail Goods"
        },
        {
            "category":"Organizations",
            "subcategory":"Community Association",
            "type":"Services"
        },
        {
            "category":"Organizations",
            "subcategory":"Non-profit Organization",
            "type":"Services"
        }
    ],
    "sg:phone":"+44 116 247 0272",
    "sg:postcode":"LE1 6EH",
    "sg:province":"Leicestershire",
    "sg:tags":[
        "shop",
        "voluntary",
        "club",
        "organisation",
        "social",
        "charity"
    ],
    "wof:name":"BARNARDO'S",
    "wof:placetype":"venue"
},
  "geometry": {"coordinates":[-1.1307799816,52.6337509155],"type":"Point"}
}