{
  "type": "Feature",
  "properties": {
    "iso:country":"GB",
    "sg:address":"1a Barker Street, Langley",
    "sg:city":"Smethwick",
    "sg:classifiers":[
        {
            "category":"Retail",
            "subcategory":"Auto Repair",
            "type":"Services"
        }
    ],
    "sg:phone":"+44 121 552 3196",
    "sg:postcode":"B68 9UQ",
    "sg:province":"West Midlands",
    "sg:tags":[
        "body",
        "car",
        "repairer"
    ],
    "wof:name":"Charles Hamilton Motors",
    "wof:placetype":"venue"
},
  "geometry": {"coordinates":[-1.9986200333,52.4958610535],"type":"Point"}
}