{
  "type": "Feature",
  "properties": {
    "addr:full":"Wildings Lane Lytham St Annes Lancashire FY8 3RJ",
    "addr:postcode":"fy8 3rj",
    "addr:street":"Wildings Lane",
    "iso:country":"GB",
    "sg:address":"Wildings Lane",
    "sg:city":"Lytham St Annes",
    "sg:classifiers":[
        {
            "category":"Transit Center",
            "subcategory":"Passenger",
            "type":"Transportation"
        },
        {
            "category":"Retail",
            "subcategory":"Pet Boarding",
            "type":"Services"
        }
    ],
    "sg:postcode":"FY8 3RJ",
    "sg:province":"Lancashire",
    "sg:tags":[
        "kennel",
        "catteries"
    ],
    "wof:name":"Valentines Boarding Kennels & Cattery",
    "wof:placetype":"venue"
},
  "geometry": {"coordinates":[-3.0037500858,53.7586364746],"type":"Point"}
}