{
  "type": "Feature",
  "properties": {
    "addr:full":"195 High Street Lincoln Lincolnshire LN5 7AL",
    "addr:housenumber":"195",
    "addr:postcode":"ln5 7al",
    "addr:street":"High Street",
    "iso:country":"GB",
    "sg:address":"195 High Street",
    "sg:city":"Lincoln",
    "sg:classifiers":[
        {
            "category":"Shopping",
            "subcategory":"Music",
            "type":"Retail Goods"
        }
    ],
    "sg:phone":"+44 1522 539761",
    "sg:postcode":"LN5 7AL",
    "sg:province":"Lincolnshire",
    "sg:tags":[
        "record",
        "tape",
        "cd"
    ],
    "wof:name":"Our Price Windows (East)",
    "wof:placetype":"venue"
},
  "geometry": {"coordinates":[-0.541103,53.227505],"type":"Point"}
}