{
  "type": "Feature",
  "properties": {
    "addr:full":"32 Chapel St, Wem Shrewsbury Shropshire SY4 5ER",
    "addr:housenumber":"32",
    "addr:postcode":"sy4 5er",
    "addr:street":"Chapel St",
    "iso:country":"GB",
    "sg:address":"32 Chapel St, Wem",
    "sg:city":"Shrewsbury",
    "sg:classifiers":[
        {
            "category":"Professional",
            "subcategory":"Detective & Security Services",
            "type":"Services"
        }
    ],
    "sg:phone":"+44 1939 235333",
    "sg:postcode":"SY4 5ER",
    "sg:province":"Shropshire",
    "wof:name":"Sogedex (U K) Ltd",
    "wof:placetype":"venue"
},
  "geometry": {"coordinates":[-2.72422,52.854027],"type":"Point"}
}