{
  "type": "Feature",
  "properties": {
    "addr:full":"495 Rooley La Bradford West Yorkshire BD4 7SB",
    "addr:housenumber":"495",
    "addr:postcode":"bd4 7sb",
    "addr:street":"Rooley La Bradford West",
    "iso:country":"GB",
    "sg:address":"495 Rooley La",
    "sg:city":"Bradford",
    "sg:classifiers":[
        {
            "category":"Building & Trades",
            "subcategory":"Construction",
            "type":"Services"
        }
    ],
    "sg:phone":"+44 1274 725895",
    "sg:postcode":"BD4 7SB",
    "sg:province":"West Yorkshire",
    "sg:tags":[
        "glazier"
    ],
    "wof:name":"Bradford Glass & Glazing",
    "wof:placetype":"venue"
},
  "geometry": {"coordinates":[-1.729321003,53.7748908997],"type":"Point"}
}