{
  "type": "Feature",
  "properties": {
    "iso:country":"GB",
    "sg:address":"39 Windsor Terrace",
    "sg:city":"Sunderland",
    "sg:classifiers":[
        {
            "category":"Personal",
            "subcategory":"Beauty Salon",
            "type":"Services"
        }
    ],
    "sg:postcode":"SR2 9QF",
    "sg:province":"Tyne and Wear",
    "sg:tags":[
        "unisex",
        "hairdresser"
    ],
    "wof:name":"Rosina's",
    "wof:placetype":"venue"
},
  "geometry": {"coordinates":[-1.414395,54.952065],"type":"Point"}
}