{
  "type": "Feature",
  "properties": {
    "iso:country":"GB",
    "sg:address":"26 Willowside Way",
    "sg:city":"Royston",
    "sg:classifiers":[
        {
            "category":"Banks & Credit Unions",
            "subcategory":"Bank",
            "type":"Services"
        }
    ],
    "sg:phone":"+44 70 0590 5081",
    "sg:postcode":"SG8 5ET",
    "sg:province":"Bedfordshire",
    "sg:tags":[
        "broker",
        "mortgage"
    ],
    "wof:name":"Direct Contact Mortgage Co",
    "wof:placetype":"venue"
},
  "geometry": {"coordinates":[-0.028771,52.0574874878],"type":"Point"}
}