{
  "type": "Feature",
  "properties": {
    "addr:full":"Jarrow Road London Greater London N17 9PP",
    "addr:postcode":"n17 9pp",
    "addr:street":"Jarrow Road",
    "iso:country":"GB",
    "sg:address":"Jarrow Road",
    "sg:city":"London",
    "sg:classifiers":[
        {
            "category":"Education",
            "subcategory":"School",
            "type":"Public Place"
        }
    ],
    "sg:phone":"+44 20 8801 5233",
    "sg:postcode":"N17 9PP",
    "sg:province":"Greater London",
    "sg:tags":[
        "local",
        "authority"
    ],
    "wof:name":"Ferry Lane Primary School",
    "wof:placetype":"venue"
},
  "geometry": {"coordinates":[-0.058118999,51.5859832764],"type":"Point"}
}