{
  "type": "Feature",
  "properties": {
    "iso:country":"GB",
    "sg:address":"Slington Ho, Rankine Rd",
    "sg:city":"Basingstoke",
    "sg:classifiers":[
        {
            "category":"Social Services",
            "subcategory":"Adult Care",
            "type":"Services"
        }
    ],
    "sg:phone":"+44 1256 333355",
    "sg:postcode":"RG24 8PH",
    "sg:province":"Hampshire",
    "sg:tags":[
        "domestic",
        "cleaning"
    ],
    "wof:name":"Houseproud",
    "wof:placetype":"venue"
},
  "geometry": {"coordinates":[-1.07268,51.277111],"type":"Point"}
}