{
  "type": "Feature",
  "properties": {
    "addr:full":"33 Rushworth St London Greater London SE1 0RB",
    "addr:housenumber":"33",
    "addr:postcode":"se1 0rb",
    "addr:street":"Rushworth St",
    "iso:country":"GB",
    "sg:address":"33 Rushworth St",
    "sg:city":"London",
    "sg:classifiers":[
        {
            "category":"Professional",
            "subcategory":"Engineering",
            "type":"Services"
        }
    ],
    "sg:phone":"+44 20 7401 2224",
    "sg:postcode":"SE1 0RB",
    "sg:province":"Greater London",
    "sg:tags":[
        "consulting",
        "engineer"
    ],
    "wof:name":"Leonard Michael Genery & Associates",
    "wof:placetype":"venue"
},
  "geometry": {"coordinates":[-0.1023370028,51.5014343262],"type":"Point"}
}