{
  "type": "Feature",
  "properties": {
    "iso:country":"GB",
    "sg:address":"78 Katherine Rd",
    "sg:city":"East Ham",
    "sg:classifiers":[
        {
            "category":"Shopping",
            "subcategory":"Clothing, Apparel, & Fashions",
            "type":"Retail Goods"
        }
    ],
    "sg:phone":"+44 20 8470 0054",
    "sg:postcode":"E6 1EN",
    "sg:province":"Greater London",
    "sg:tags":[
        "clothing",
        "fabric"
    ],
    "wof:name":"Apsara Manufacturing",
    "wof:placetype":"venue"
},
  "geometry": {"coordinates":[0.0467029996,51.5345230103],"type":"Point"}
}