{
  "type": "Feature",
  "properties": {
    "iso:country":"GB",
    "sg:address":"Craigshaw Road West, West Tullos Industrial Estate",
    "sg:city":"Aberdeen",
    "sg:classifiers":[
        {
            "category":"Professional",
            "type":"Services"
        },
        {
            "category":"Shopping",
            "subcategory":"Bicycles & Sporting Goods",
            "type":"Retail Goods"
        }
    ],
    "sg:phone":"+44 1224 872085",
    "sg:postcode":"AB12 3AP",
    "sg:province":"Aberdeen City",
    "sg:tags":[
        "equipment",
        "marine",
        "supply"
    ],
    "wof:name":"Racal Decca Marine",
    "wof:placetype":"venue"
},
  "geometry": {"coordinates":[-2.088819,57.12228],"type":"Point"}
}