{
  "type": "Feature",
  "properties": {
    "addr:full":"12 Station Road Chertsey Surrey KT16  8BE",
    "addr:housenumber":"12",
    "addr:postcode":"kt16 8be",
    "addr:street":"Station Road",
    "iso:country":"GB",
    "sg:address":"12 Station Road",
    "sg:city":"Chertsey",
    "sg:classifiers":[
        {
            "category":"Communications",
            "type":"Services"
        }
    ],
    "sg:phone":"+44 1932 704000",
    "sg:postcode":"KT16  8BE",
    "sg:province":"Surrey",
    "sg:tags":[
        "telecommunication"
    ],
    "wof:name":"Stappard Howes",
    "wof:placetype":"venue"
},
  "geometry": {"coordinates":[-0.5074359775,51.3869476318],"type":"Point"}
}