{
  "type": "Feature",
  "properties": {
    "addr:full":"Unit E2 Bolsover Busines Pk, Station Rd, Bolsover Chesterfield Derbyshire S44 6BD",
    "addr:housenumber":"e2",
    "addr:postcode":"s44 6bd",
    "addr:street":"Busines Pk Station Rd",
    "iso:country":"GB",
    "sg:address":"Unit E2 Bolsover Busines Pk, Station Rd, Bolsover",
    "sg:city":"Chesterfield",
    "sg:classifiers":[
        {
            "category":"Retail",
            "subcategory":"Auto Repair",
            "type":"Services"
        }
    ],
    "sg:postcode":"S44 6BD",
    "sg:province":"Derbyshire",
    "sg:tags":[
        "body",
        "car"
    ],
    "wof:name":"R M Bodyline",
    "wof:placetype":"venue"
},
  "geometry": {"coordinates":[-1.31053,53.233204],"type":"Point"}
}