{
  "type": "Feature",
  "properties": {
    "iso:country":"GB",
    "sg:address":"24 Station Road, Nassington",
    "sg:city":"Peterborough",
    "sg:classifiers":[
        {
            "category":"Food & Beverages",
            "subcategory":"Liquor & Beverages",
            "type":"Retail Goods"
        }
    ],
    "sg:phone":"+44 1780 783102",
    "sg:postcode":"PE8 6QB",
    "sg:province":"Cambridgeshire",
    "sg:tags":[
        "beer",
        "wine",
        "spirit",
        "wines"
    ],
    "wof:name":"The Winesmith Ltd",
    "wof:placetype":"venue"
},
  "geometry": {"coordinates":[-0.426129,52.554581],"type":"Point"}
}