{
  "type": "Feature",
  "properties": {
    "iso:country":"GB",
    "sg:address":"Cathnor Road",
    "sg:city":"London",
    "sg:classifiers":[
        {
            "category":"Farming",
            "subcategory":"Nursery",
            "type":"Manufacturing & Wholesale Goods"
        },
        {
            "category":"Education",
            "subcategory":"Preschool",
            "type":"Public Place"
        },
        {
            "category":"Government",
            "subcategory":"Office",
            "type":"Public Place"
        }
    ],
    "sg:phone":"+44 20 8743 8196",
    "sg:postcode":"W12 9JA",
    "sg:province":"Greater London",
    "sg:tags":[
        "local",
        "school",
        "creche"
    ],
    "wof:name":"Vanessa Nursery School",
    "wof:placetype":"venue"
},
  "geometry": {"coordinates":[-0.23516,51.502918],"type":"Point"}
}