{
  "type": "Feature",
  "properties": {
    "addr:full":"Meadow Cottage, Pool Quay Welshpool Shropshire SY21 9LB",
    "addr:postcode":"sy21 9lb",
    "addr:street":"Pool Quay",
    "iso:country":"GB",
    "sg:address":"Meadow Cottage, Pool Quay",
    "sg:city":"Welshpool",
    "sg:classifiers":[
        {
            "category":"Farming",
            "subcategory":"Livestock Farm",
            "type":"Manufacturing & Wholesale Goods"
        },
        {
            "category":"Farming",
            "subcategory":"Farm",
            "type":"Manufacturing & Wholesale Goods"
        }
    ],
    "sg:postcode":"SY21 9LB",
    "sg:province":"Shropshire",
    "sg:tags":[
        "mixed",
        "crop",
        "others"
    ],
    "wof:name":"Gittins,David Llewellen,",
    "wof:placetype":"venue"
},
  "geometry": {"coordinates":[-3.1452031136,52.661190033],"type":"Point"}
}