{
  "type": "Feature",
  "properties": {
    "addr:full":"62 Waggon Road Barnet Hertfordshire EN4 0PP",
    "addr:housenumber":"62",
    "addr:postcode":"en4 0pp",
    "addr:street":"Waggon Road",
    "iso:country":"GB",
    "sg:address":"62 Waggon Road",
    "sg:city":"Barnet",
    "sg:classifiers":[
        {
            "category":"Shopping",
            "subcategory":"Stationery & Office Supplies",
            "type":"Retail Goods"
        }
    ],
    "sg:phone":"+44 20 8449 5522",
    "sg:postcode":"EN4 0PP",
    "sg:province":"Hertfordshire",
    "sg:tags":[
        "item",
        "promotional"
    ],
    "wof:name":"Soundscan Ltd.",
    "wof:placetype":"venue"
},
  "geometry": {"coordinates":[-0.166979,51.671928],"type":"Point"}
}