{
  "type": "Feature",
  "properties": {
    "addr:full":"Trout Road, Yiewsley West Drayton Greater London UB7 7RU",
    "addr:postcode":"ub7 7ru",
    "addr:street":"Trout Road",
    "iso:country":"GB",
    "sg:address":"Trout Road, Yiewsley",
    "sg:city":"West Drayton",
    "sg:classifiers":[
        {
            "category":"Professional",
            "subcategory":"Engineering",
            "type":"Services"
        }
    ],
    "sg:phone":"+44 1895 443168",
    "sg:postcode":"UB7 7RU",
    "sg:province":"Greater London",
    "sg:tags":[
        "precision",
        "engineer"
    ],
    "wof:name":"Metalmatics Ltd.",
    "wof:placetype":"venue"
},
  "geometry": {"coordinates":[-0.4739899933,51.5091171265],"type":"Point"}
}