{
  "type": "Feature",
  "properties": {
    "addr:full":"47 Westwood Avenue Lowestoft Suffolk NR33 9RW",
    "addr:housenumber":"47",
    "addr:postcode":"nr33 9rw",
    "addr:street":"Westwood Avenue",
    "iso:country":"GB",
    "sg:address":"47 Westwood Avenue",
    "sg:city":"Lowestoft",
    "sg:classifiers":[
        {
            "category":"Health Services",
            "subcategory":"Clinic",
            "type":"Services"
        }
    ],
    "sg:phone":"+44 1502 588854",
    "sg:postcode":"NR33 9RW",
    "sg:province":"Suffolk",
    "sg:tags":[
        "nh"
    ],
    "wof:name":"Westwood Surgery",
    "wof:placetype":"venue"
},
  "geometry": {"coordinates":[1.711384058,52.4652366638],"type":"Point"}
}