{
  "type": "Feature",
  "properties": {
    "iso:country":"GB",
    "sg:address":"2 Yazor Road, Whitecross",
    "sg:city":"Hereford",
    "sg:classifiers":[
        {
            "category":"Shopping",
            "subcategory":"News",
            "type":"Retail Goods"
        }
    ],
    "sg:phone":"+44 1432 273668",
    "sg:postcode":"HR4 0LY",
    "sg:province":"Herefordshire",
    "sg:tags":[
        "newsagent"
    ],
    "wof:name":"Forbuoys",
    "wof:placetype":"venue"
},
  "geometry": {"coordinates":[-2.740213,52.062176],"type":"Point"}
}