{
  "type": "Feature",
  "properties": {
    "addr:full":"5a Sun Street Hitchin Bedfordshire SG5 1AE",
    "addr:housenumber":"5a",
    "addr:postcode":"sg5 1ae",
    "addr:street":"Sun Street",
    "iso:country":"GB",
    "sg:address":"5a Sun Street",
    "sg:city":"Hitchin",
    "sg:classifiers":[
        {
            "category":"Professional",
            "subcategory":"Printing & Photocopies",
            "type":"Services"
        }
    ],
    "sg:postcode":"SG5 1AE",
    "sg:province":"Bedfordshire",
    "sg:tags":[
        "printer"
    ],
    "wof:name":"Osprey Print Services",
    "wof:placetype":"venue"
},
  "geometry": {"coordinates":[-0.278486,51.946583],"type":"Point"}
}