{
  "type": "Feature",
  "properties": {
    "iso:country":"GB",
    "sg:address":"Longleat Estate, Longleat",
    "sg:city":"Warminster",
    "sg:classifiers":[
        {
            "category":"Bars & Pubs",
            "subcategory":"Nightclub",
            "type":"Food & Drink"
        }
    ],
    "sg:phone":"+44 1985 844440",
    "sg:postcode":"BA12 7NL",
    "sg:province":"Somerset",
    "sg:tags":[
        "club",
        "night"
    ],
    "wof:name":"Oscars Night Club",
    "wof:placetype":"venue"
},
  "geometry": {"coordinates":[-2.278118,51.194511],"type":"Point"}
}