{
  "type": "Feature",
  "properties": {
    "iso:country":"GB",
    "sg:address":"Nelson Farm, Nelson Farm Lane, Hart Station",
    "sg:city":"Hartlepool",
    "sg:classifiers":[
        {
            "category":"Farming",
            "subcategory":"Livestock Farm",
            "type":"Manufacturing & Wholesale Goods"
        }
    ],
    "sg:phone":"+44 1429 267632",
    "sg:postcode":"TS27 3AE",
    "sg:province":"Durham",
    "sg:tags":[
        "others"
    ],
    "wof:name":"M R Ford",
    "wof:placetype":"venue"
},
  "geometry": {"coordinates":[-1.2705060244,54.7075614929],"type":"Point"}
}