{
  "type": "Feature",
  "properties": {
    "addr:full":"32-34 Westgate Street Gloucester Gloucestershire GL1 2NG",
    "addr:housenumber":"32-34",
    "addr:postcode":"gl1 2ng",
    "addr:street":"Westgate Street",
    "iso:country":"GB",
    "sg:address":"32-34 Westgate Street",
    "sg:city":"Gloucester",
    "sg:classifiers":[
        {
            "category":"Shopping",
            "subcategory":"Discount & Variety Stores",
            "type":"Retail Goods"
        }
    ],
    "sg:phone":"+44 1452 416413",
    "sg:postcode":"GL1 2NG",
    "sg:province":"Gloucestershire",
    "sg:tags":[
        "centre"
    ],
    "wof:name":"Poundstretcher Ltd",
    "wof:placetype":"venue"
},
  "geometry": {"coordinates":[-2.246901989,51.8661079407],"type":"Point"}
}