{
  "type": "Feature",
  "properties": {
    "addr:full":"Holly Dene, Rathmell Settle North Yorkshire BD24 0AJ",
    "addr:postcode":"bd24 0aj",
    "addr:street":"Dene",
    "iso:country":"GB",
    "sg:address":"Holly Dene, Rathmell",
    "sg:city":"Settle",
    "sg:classifiers":[
        {
            "category":"Farming",
            "subcategory":"Dairy Farm",
            "type":"Manufacturing & Wholesale Goods"
        }
    ],
    "sg:phone":"+44 1729 822538",
    "sg:postcode":"BD24 0AJ",
    "sg:province":"North Yorkshire",
    "wof:name":"A Bradley",
    "wof:placetype":"venue"
},
  "geometry": {"coordinates":[-2.300469,54.034763],"type":"Point"}
}