{
  "type": "Feature",
  "properties": {
    "addr:full":"213 Church Road Hayes Greater London UB3 2LG",
    "addr:housenumber":"213",
    "addr:postcode":"ub3 2lg",
    "addr:street":"Church Road",
    "iso:country":"GB",
    "sg:address":"213 Church Road",
    "sg:city":"Hayes",
    "sg:classifiers":[
        {
            "category":"Wholesale",
            "subcategory":"Machinery & Supplies",
            "type":"Manufacturing & Wholesale Goods"
        }
    ],
    "sg:postcode":"UB3 2LG",
    "sg:province":"Greater London",
    "sg:tags":[
        "industrial",
        "commercial"
    ],
    "wof:name":"Equipment Trading Co. Inc",
    "wof:placetype":"venue"
},
  "geometry": {"coordinates":[-0.4194900095,51.5163383484],"type":"Point"}
}