{
  "type": "Feature",
  "properties": {
    "addr:full":"Wentworth Rd Barnsley South Yorkshire S75 6DZ",
    "addr:postcode":"s75 6dz",
    "addr:street":"Wentworth Rd;Yorkshire",
    "iso:country":"GB",
    "sg:address":"Wentworth Rd",
    "sg:city":"Barnsley",
    "sg:classifiers":[
        {
            "category":"Parking",
            "type":"Transportation"
        }
    ],
    "sg:phone":"+44 1226 386424",
    "sg:postcode":"S75 6DZ",
    "sg:province":"South Yorkshire",
    "sg:tags":[
        "car",
        "valet"
    ],
    "wof:name":"S A Valeting",
    "wof:placetype":"venue"
},
  "geometry": {"coordinates":[-1.496174,53.582947],"type":"Point"}
}