{
  "type": "Feature",
  "properties": {
    "iso:country":"GB",
    "sg:address":"London Road",
    "sg:city":"Chalfont St Giles",
    "sg:classifiers":[
        {
            "category":"Restaurant",
            "type":"Food & Drink"
        }
    ],
    "sg:phone":"+44 1494 870200",
    "sg:postcode":"HP8 4NJ",
    "sg:province":"Buckinghamshire",
    "sg:tags":[
        "-",
        "chinese"
    ],
    "wof:name":"Mr Poons",
    "wof:placetype":"venue"
},
  "geometry": {"coordinates":[-0.565845,51.632767],"type":"Point"}
}