{
  "type": "Feature",
  "properties": {
    "addr:full":"399 New Cross Road London Greater London SE14 6LA",
    "addr:housenumber":"399",
    "addr:postcode":"se14 6la",
    "addr:street":"New Cross Road",
    "iso:country":"GB",
    "sg:address":"399 New Cross Road",
    "sg:city":"London",
    "sg:classifiers":[
        {
            "category":"Cafe",
            "type":"Food & Drink"
        }
    ],
    "sg:phone":"+44 20 8692 6149",
    "sg:postcode":"SE14 6LA",
    "sg:province":"Greater London",
    "sg:tags":[
        "tea",
        "room"
    ],
    "wof:name":"U Beyzade",
    "wof:placetype":"venue"
},
  "geometry": {"coordinates":[-0.033534,51.475994],"type":"Point"}
}