{
  "type": "Feature",
  "properties": {
    "addr:full":"30 Little London, Long Sutton Spalding Cambridgeshire PE12 9LE",
    "addr:housenumber":"30",
    "addr:postcode":"pe12 9le",
    "addr:street":"Little London;Spalding",
    "iso:country":"GB",
    "sg:address":"30 Little London, Long Sutton",
    "sg:city":"Spalding",
    "sg:classifiers":[
        {
            "category":"Building & Trades",
            "subcategory":"Plumbing",
            "type":"Services"
        },
        {
            "category":"Building & Trades",
            "subcategory":"Construction",
            "type":"Services"
        }
    ],
    "sg:phone":"+44 1406 362157",
    "sg:postcode":"PE12 9LE",
    "sg:province":"Cambridgeshire",
    "sg:tags":[
        "plumber",
        "heating",
        "contractor"
    ],
    "wof:name":"Trevor Waters",
    "wof:placetype":"venue"
},
  "geometry": {"coordinates":[0.1294129938,52.7898406982],"type":"Point"}
}