{
  "type": "Feature",
  "properties": {
    "addr:full":"Little Hook Haverfordwest Pembrokeshire SA62 5QX",
    "addr:postcode":"sa62 5qx",
    "addr:street":"Little Hook",
    "iso:country":"GB",
    "sg:address":"Little Hook",
    "sg:city":"Haverfordwest",
    "sg:classifiers":[
        {
            "category":"Farming",
            "subcategory":"Dairy Farm",
            "type":"Manufacturing & Wholesale Goods"
        }
    ],
    "sg:phone":"+44 1437 741677",
    "sg:postcode":"SA62 5QX",
    "sg:province":"Pembrokeshire",
    "wof:name":"Little Hook Dairy",
    "wof:placetype":"venue"
},
  "geometry": {"coordinates":[-4.9992890358,51.9263305664],"type":"Point"}
}