{
  "type": "Feature",
  "properties": {
    "iso:country":"GB",
    "sg:address":"54 Lombard Street",
    "sg:city":"London",
    "sg:classifiers":[
        {
            "category":"Banks & Credit Unions",
            "subcategory":"Bank",
            "type":"Services"
        }
    ],
    "sg:phone":"+44 20 7699 5000",
    "sg:postcode":"EC3P 3AH",
    "sg:province":"Greater London",
    "wof:name":"Barclays Financial Services Ltd.",
    "wof:placetype":"venue"
},
  "geometry": {"coordinates":[-0.085449,51.512142],"type":"Point"}
}