{
  "type": "Feature",
  "properties": {
    "iso:country":"GB",
    "sg:address":"60 Winster Avenue, Dorridge",
    "sg:city":"Solihull",
    "sg:classifiers":[
        {
            "category":"Professional",
            "subcategory":"Accounting & Tax Preparation",
            "type":"Services"
        }
    ],
    "sg:phone":"+44 1564 776981",
    "sg:postcode":"B93 8ST",
    "sg:province":"Warwickshire",
    "sg:tags":[
        "accountant"
    ],
    "wof:name":"FRITH & CO",
    "wof:placetype":"venue"
},
  "geometry": {"coordinates":[-1.7604290247,52.3779716492],"type":"Point"}
}