{
  "type": "Feature",
  "properties": {
    "addr:full":"83 Fetter Lane London Greater London EC4A 1EQ",
    "addr:housenumber":"83",
    "addr:postcode":"ec4a 1eq",
    "addr:street":"Fetter Lane",
    "iso:country":"GB",
    "sg:address":"83 Fetter Lane",
    "sg:city":"London",
    "sg:classifiers":[
        {
            "category":"Cafe",
            "type":"Food & Drink"
        }
    ],
    "sg:phone":"+44 20 7405 3088",
    "sg:postcode":"EC4A 1EQ",
    "sg:province":"Greater London",
    "sg:tags":[
        "tea",
        "room"
    ],
    "wof:name":"Tuckers",
    "wof:placetype":"venue"
},
  "geometry": {"coordinates":[-0.1091729999,51.5156288147],"type":"Point"}
}