{
  "type": "Feature",
  "properties": {
    "iso:country":"GB",
    "sg:address":"Oakwood, Oak Hill Road, Stapleford Abbotts",
    "sg:city":"Romford",
    "sg:classifiers":[
        {
            "category":"Retail",
            "subcategory":"Repair Shop",
            "type":"Services"
        }
    ],
    "sg:phone":"+44 1708 342587",
    "sg:postcode":"RM4 1JH",
    "sg:province":"Essex",
    "sg:tags":[
        "maintenance"
    ],
    "wof:name":"John Seabright",
    "wof:placetype":"venue"
},
  "geometry": {"coordinates":[0.16912,51.63644],"type":"Point"}
}