{
  "type": "Feature",
  "properties": {
    "addr:full":"St Aidans Vicarage, Moor Park Gardens Leigh On Sea Essex SS9 4PY",
    "addr:postcode":"ss9 4py",
    "addr:street":"St;Moor Park Gardens;Sea",
    "iso:country":"GB",
    "sg:address":"St Aidans Vicarage, Moor Park Gardens",
    "sg:city":"Leigh On Sea",
    "sg:classifiers":[
        {
            "category":"Place Of Worship",
            "type":"Public Place"
        }
    ],
    "sg:phone":"+44 1702 512531",
    "sg:postcode":"SS9 4PY",
    "sg:province":"Essex",
    "wof:name":"St Aidans C Of E Church",
    "wof:placetype":"venue"
},
  "geometry": {"coordinates":[0.6509950161,51.5484809875],"type":"Point"}
}