{
  "type": "Feature",
  "properties": {
    "iso:country":"GB",
    "sg:address":"3 Muirhall Road",
    "sg:city":"Larbert",
    "sg:classifiers":[
        {
            "category":"Home & Garden",
            "subcategory":"Home Furnishings",
            "type":"Retail Goods"
        }
    ],
    "sg:postcode":"FK5 4RF",
    "sg:province":"Falkirk",
    "sg:tags":[
        "furnishers",
        "planner",
        "kitchen"
    ],
    "wof:name":"Macdowell Design",
    "wof:placetype":"venue"
},
  "geometry": {"coordinates":[-3.830052,56.027042],"type":"Point"}
}