{
  "type": "Feature",
  "properties": {
    "addr:full":"17-19 Marsworth Road Leighton Buzzard Bedfordshire LU7 9AT",
    "addr:housenumber":"17-19",
    "addr:postcode":"lu7 9at",
    "addr:street":"Marsworth Road",
    "iso:country":"GB",
    "sg:address":"17-19 Marsworth Road",
    "sg:city":"Leighton Buzzard",
    "sg:classifiers":[
        {
            "category":"Restaurant",
            "type":"Food & Drink"
        }
    ],
    "sg:phone":"+44 1296 661969",
    "sg:postcode":"LU7 9AT",
    "sg:province":"Bedfordshire",
    "sg:tags":[
        "chinese"
    ],
    "wof:name":"May Fu Peking Restaurant",
    "wof:placetype":"venue"
},
  "geometry": {"coordinates":[-0.641505,51.832939],"type":"Point"}
}