{
  "type": "Feature",
  "properties": {
    "addr:full":"25 Church St Ilkley North Yorkshire LS29 9DR",
    "addr:housenumber":"25",
    "addr:postcode":"ls29 9dr",
    "addr:street":"Church St",
    "iso:country":"GB",
    "sg:address":"25 Church St",
    "sg:city":"Ilkley",
    "sg:classifiers":[
        {
            "category":"Professional",
            "subcategory":"Business Services",
            "type":"Services"
        }
    ],
    "sg:postcode":"LS29 9DR",
    "sg:province":"North Yorkshire",
    "sg:tags":[
        "import",
        "export",
        "agent"
    ],
    "wof:name":"Jonathan Shaw Fine Art",
    "wof:placetype":"venue"
},
  "geometry": {"coordinates":[-1.8245780468,53.9261283875],"type":"Point"}
}