{
  "type": "Feature",
  "properties": {
    "iso:country":"GB",
    "sg:address":"32-36 High View",
    "sg:city":"Hatfield",
    "sg:classifiers":[
        {
            "category":"Food & Beverages",
            "subcategory":"Groceries & Convenience Stores",
            "type":"Retail Goods"
        }
    ],
    "sg:phone":"+44 1707 262048",
    "sg:postcode":"AL10 8HZ",
    "sg:province":"Hertfordshire",
    "wof:name":"M & W Ltd",
    "wof:placetype":"venue"
},
  "geometry": {"coordinates":[-0.233871,51.748043],"type":"Point"}
}