{
  "type": "Feature",
  "properties": {
    "addr:full":"12 Malton Drive, Oadby Leicester Leicestershire LE2 4NG",
    "addr:housenumber":"12",
    "addr:postcode":"le2 4ng",
    "addr:street":"Malton Drive",
    "iso:country":"GB",
    "sg:address":"12 Malton Drive, Oadby",
    "sg:city":"Leicester",
    "sg:classifiers":[
        {
            "category":"Professional",
            "subcategory":"Computer Services",
            "type":"Services"
        }
    ],
    "sg:phone":"+44 116 271 6864",
    "sg:postcode":"LE2 4NG",
    "sg:province":"Leicestershire",
    "sg:tags":[
        "system",
        "software"
    ],
    "wof:name":"Advice Centre Year 2000",
    "wof:placetype":"venue"
},
  "geometry": {"coordinates":[-1.066624999,52.5995788574],"type":"Point"}
}