{
  "type": "Feature",
  "properties": {
    "addr:full":"99 Attercliffe Road, Attercliffe Sheffield South Yorkshire S4 7WW",
    "addr:housenumber":"99",
    "addr:postcode":"s4 7ww",
    "addr:street":"Attercliffe Road",
    "iso:country":"GB",
    "sg:address":"99 Attercliffe Road, Attercliffe",
    "sg:city":"Sheffield",
    "sg:classifiers":[
        {
            "category":"Retail",
            "subcategory":"Auto Repair",
            "type":"Services"
        }
    ],
    "sg:phone":"+44 114 272 8681",
    "sg:postcode":"S4 7WW",
    "sg:province":"South Yorkshire",
    "sg:tags":[
        "modification",
        "garage"
    ],
    "wof:name":"Pinco 1555 Ltd.",
    "wof:placetype":"venue"
},
  "geometry": {"coordinates":[-1.44807899,53.3902702332],"type":"Point"}
}