{
  "type": "Feature",
  "properties": {
    "addr:full":"Unit 10, Lakeside Industrial Estate, Stanton Harcourt Witney Oxfordshire OX29 5SL",
    "addr:housenumber":"unit 10;estate",
    "addr:postcode":"ox29 5sl",
    "addr:street":"Lakeside Industrial",
    "iso:country":"GB",
    "sg:address":"Unit 10, Lakeside Industrial Estate, Stanton Harcourt",
    "sg:city":"Witney",
    "sg:classifiers":[
        {
            "category":"Manufacturing",
            "subcategory":"Building Materials",
            "type":"Manufacturing & Wholesale Goods"
        }
    ],
    "sg:phone":"+44 1865 880404",
    "sg:postcode":"OX29 5SL",
    "sg:province":"Oxfordshire",
    "sg:tags":[
        "stonemason"
    ],
    "wof:name":"Davidson Masonry Ltd",
    "wof:placetype":"venue"
},
  "geometry": {"coordinates":[-1.408849,51.74715],"type":"Point"}
}