{
  "type": "Feature",
  "properties": {
    "addr:full":"Apex House, 4a West Street Epsom Surrey KT18 7RG",
    "addr:housenumber":"4a",
    "addr:postcode":"kt18 7rg",
    "addr:street":"West Street",
    "iso:country":"GB",
    "sg:address":"Apex House, 4a West Street",
    "sg:city":"Epsom",
    "sg:classifiers":[
        {
            "category":"Professional",
            "subcategory":"Computer Services",
            "type":"Services"
        }
    ],
    "sg:postcode":"KT18 7RG",
    "sg:province":"Surrey",
    "sg:tags":[
        "system",
        "software"
    ],
    "wof:name":"Axent Technologies Ltd.",
    "wof:placetype":"venue"
},
  "geometry": {"coordinates":[-0.2719939947,51.3333053589],"type":"Point"}
}