{
  "type": "Feature",
  "properties": {
    "addr:full":"180 Swan La Coventry Warwickshire CV2 4GB",
    "addr:housenumber":"180",
    "addr:postcode":"cv2 4gb",
    "addr:street":"Swan La",
    "iso:country":"GB",
    "sg:address":"180 Swan La",
    "sg:city":"Coventry",
    "sg:classifiers":[
        {
            "category":"Building & Trades",
            "subcategory":"Equipment Rental",
            "type":"Services"
        }
    ],
    "sg:phone":"+44 24 7625 6557",
    "sg:postcode":"CV2 4GB",
    "sg:province":"Warwickshire",
    "sg:tags":[
        "plant",
        "machinery"
    ],
    "wof:name":"Vraitch Construction & Plant Hire",
    "wof:placetype":"venue"
},
  "geometry": {"coordinates":[-1.488047,52.41309],"type":"Point"}
}