{
  "type": "Feature",
  "properties": {
    "iso:country":"GB",
    "sg:address":"School House, School Lane, North Benfleet",
    "sg:city":"Wickford",
    "sg:classifiers":[
        {
            "category":"Professional",
            "type":"Services"
        }
    ],
    "sg:phone":"+44 1268 727781",
    "sg:postcode":"SS12 9JL",
    "sg:province":"Essex",
    "sg:tags":[
        "caterer"
    ],
    "wof:name":"Essex Catering Fine Cuisine",
    "wof:placetype":"venue"
},
  "geometry": {"coordinates":[0.544753015,51.5871620178],"type":"Point"}
}