{
  "type": "Feature",
  "properties": {
    "addr:full":"13 Leigh Avenue Ilford Essex IG4 5PH",
    "addr:housenumber":"13",
    "addr:postcode":"ig4 5ph",
    "addr:street":"Leigh Avenue Ilford",
    "iso:country":"GB",
    "sg:address":"13 Leigh Avenue",
    "sg:city":"Ilford",
    "sg:classifiers":[
        {
            "category":"Manufacturing",
            "subcategory":"Metals",
            "type":"Manufacturing & Wholesale Goods"
        }
    ],
    "sg:postcode":"IG4 5PH",
    "sg:province":"Essex",
    "sg:tags":[
        "steel",
        "fabricator",
        "erectors"
    ],
    "wof:name":"Haydon Metalwork",
    "wof:placetype":"venue"
},
  "geometry": {"coordinates":[0.045113001,51.5832443237],"type":"Point"}
}