{
  "type": "Feature",
  "properties": {
    "addr:full":"93 Havant Road, Emsworth Havant Hampshire PO10 7LF",
    "addr:housenumber":"93",
    "addr:postcode":"po10 7lf",
    "addr:street":"Havant Road",
    "iso:country":"GB",
    "sg:address":"93 Havant Road, Emsworth",
    "sg:city":"Havant",
    "sg:classifiers":[
        {
            "category":"Travel",
            "subcategory":"Hotels & Motels",
            "type":"Entertainment"
        }
    ],
    "sg:phone":"+44 1243 373363",
    "sg:postcode":"PO10 7LF",
    "sg:province":"Hampshire",
    "sg:website":"http://www.brookfieldhotel.co.uk",
    "wof:name":"Brookfields Hotel",
    "wof:placetype":"venue"
},
  "geometry": {"coordinates":[-0.9543420076,50.8488121033],"type":"Point"}
}