{
  "type": "Feature",
  "properties": {
    "addr:full":"202 Cutlers Place Wimborne Dorset BH21 2HZ",
    "addr:housenumber":"202",
    "addr:postcode":"bh21 2hz",
    "addr:street":"Cutlers Place",
    "iso:country":"GB",
    "sg:address":"202 Cutlers Place",
    "sg:city":"Wimborne",
    "sg:classifiers":[
        {
            "category":"Real Estate",
            "subcategory":"Architect",
            "type":"Services"
        }
    ],
    "sg:phone":"+44 1202 884005",
    "sg:postcode":"BH21 2HZ",
    "sg:province":"Dorset",
    "sg:tags":[
        "technician",
        "technologist",
        "architectural"
    ],
    "wof:name":"Richard Woodward Associates",
    "wof:placetype":"venue"
},
  "geometry": {"coordinates":[-1.949409008,50.8039474487],"type":"Point"}
}