{
  "type": "Feature",
  "properties": {
    "addr:full":"Fountain Business Centre, Ellis Street Coatbridge North Lanarkshire ML5 3AA",
    "addr:postcode":"ml5 3aa",
    "addr:street":"Ellis Street",
    "iso:country":"GB",
    "sg:address":"Fountain Business Centre, Ellis Street",
    "sg:city":"Coatbridge",
    "sg:classifiers":[
        {
            "category":"Professional",
            "subcategory":"Accounting & Tax Preparation",
            "type":"Services"
        }
    ],
    "sg:phone":"+44 1236 423144",
    "sg:postcode":"ML5 3AA",
    "sg:province":"North Lanarkshire",
    "sg:tags":[
        "accountant"
    ],
    "wof:name":"P K F",
    "wof:placetype":"venue"
},
  "geometry": {"coordinates":[-4.035839,55.858753],"type":"Point"}
}