{
  "type": "Feature",
  "properties": {
    "iso:country":"GB",
    "sg:address":"Bethnal Green Training Centre, Deal, Hanbury Street",
    "sg:city":"London",
    "sg:classifiers":[
        {
            "category":"Education",
            "subcategory":"Special Training",
            "type":"Public Place"
        }
    ],
    "sg:phone":"+44 20 7247 4682",
    "sg:postcode":"E1 5HZ",
    "sg:province":"Greater London",
    "sg:tags":[
        "product",
        "centre"
    ],
    "wof:name":"East London Advanced Technology Training",
    "wof:placetype":"venue"
},
  "geometry": {"coordinates":[-0.06682,51.519829],"type":"Point"}
}