{
  "type": "Feature",
  "properties": {
    "iso:country":"GB",
    "sg:address":"16 Riverside Walk",
    "sg:city":"Skipton",
    "sg:classifiers":[
        {
            "category":"Organizations",
            "subcategory":"Community Association",
            "type":"Services"
        }
    ],
    "sg:phone":"+44 1729 830255",
    "sg:postcode":"BD23 4AF",
    "sg:province":"Lancashire",
    "sg:tags":[
        "relation",
        "public"
    ],
    "wof:name":"Randal Coe",
    "wof:placetype":"venue"
},
  "geometry": {"coordinates":[-2.148883,54.029469],"type":"Point"}
}