{
  "type": "Feature",
  "properties": {
    "addr:full":"78 Spring Road Bournemouth Dorset BH1 4PT",
    "addr:housenumber":"78",
    "addr:postcode":"bh1 4pt",
    "addr:street":"Spring Road",
    "iso:country":"GB",
    "sg:address":"78 Spring Road",
    "sg:city":"Bournemouth",
    "sg:classifiers":[
        {
            "category":"Real Estate",
            "subcategory":"Real Estate Agent",
            "type":"Services"
        }
    ],
    "sg:postcode":"BH1 4PT",
    "sg:province":"Dorset",
    "wof:name":"Southcote Property Company Limited",
    "wof:placetype":"venue"
},
  "geometry": {"coordinates":[-1.8523980379,50.7297439575],"type":"Point"}
}