{
  "type": "Feature",
  "properties": {
    "addr:full":"180 Friargate Preston Lancashire PR1 2EJ",
    "addr:housenumber":"180",
    "addr:postcode":"pr1 2ej",
    "addr:street":"Friargate Preston",
    "iso:country":"GB",
    "sg:address":"180 Friargate",
    "sg:city":"Preston",
    "sg:classifiers":[
        {
            "category":"Shopping",
            "subcategory":"Antiques",
            "type":"Retail Goods"
        },
        {
            "category":"Shopping",
            "subcategory":"Comic Books",
            "type":"Retail Goods"
        }
    ],
    "sg:phone":"+44 1772 258744",
    "sg:postcode":"PR1 2EJ",
    "sg:province":"Lancashire",
    "sg:tags":[
        "jeweller",
        "valuer",
        "jewellery"
    ],
    "wof:name":"Sovereign Jewellers",
    "wof:placetype":"venue"
},
  "geometry": {"coordinates":[-2.699917078,53.7595596313],"type":"Point"}
}