{
  "type": "Feature",
  "properties": {
    "iso:country":"GB",
    "sg:address":"Stevens Farm, Martinstown",
    "sg:city":"Dorchester",
    "sg:classifiers":[
        {
            "category":"Farming",
            "subcategory":"Livestock Farm",
            "type":"Manufacturing & Wholesale Goods"
        }
    ],
    "sg:postcode":"DT2 9JR",
    "sg:province":"Dorset",
    "sg:tags":[
        "others"
    ],
    "wof:name":"E J & N J Barnes",
    "wof:placetype":"venue"
},
  "geometry": {"coordinates":[-2.501534,50.699257],"type":"Point"}
}