{
  "type": "Feature",
  "properties": {
    "addr:full":"Owen Road Lancaster Lancashire LA1 2LL",
    "addr:postcode":"la1 2ll",
    "addr:street":"Owen Road",
    "iso:country":"GB",
    "sg:address":"Owen Road",
    "sg:city":"Lancaster",
    "sg:classifiers":[
        {
            "category":"Autos & Motor Vehicles",
            "subcategory":"Fuel & Gas Station",
            "type":"Retail Goods"
        }
    ],
    "sg:phone":"+44 1524 67816",
    "sg:postcode":"LA1 2LL",
    "sg:province":"Lancashire",
    "sg:tags":[
        "petrol",
        "filling"
    ],
    "wof:name":"Save Service Station",
    "wof:placetype":"venue"
},
  "geometry": {"coordinates":[-2.8012061119,54.0600814819],"type":"Point"}
}