{
  "type": "Feature",
  "properties": {
    "addr:full":"21c Station Road, Knowle Solihull Warwickshire B93 0HL",
    "addr:housenumber":"21c",
    "addr:postcode":"b93 0hl",
    "addr:street":"Station Road",
    "iso:country":"GB",
    "sg:address":"21c Station Road, Knowle",
    "sg:city":"Solihull",
    "sg:classifiers":[
        {
            "category":"Organizations",
            "subcategory":"Professional Association",
            "type":"Services"
        }
    ],
    "sg:phone":"+44 1564 778991",
    "sg:postcode":"B93 0HL",
    "sg:province":"Warwickshire",
    "sg:tags":[
        "institute"
    ],
    "wof:name":"The British Institute of Embalmers",
    "wof:placetype":"venue"
},
  "geometry": {"coordinates":[-1.735098,52.38665],"type":"Point"}
}