{
  "type": "Feature",
  "properties": {
    "addr:full":"Taurus Business Centre, 1 Vicarage Hill Wrexham Wrexham LL13 7HN",
    "addr:housenumber":"1",
    "addr:postcode":"ll13 7hn",
    "addr:street":"Vicarage Hill",
    "iso:country":"GB",
    "sg:address":"Taurus Business Centre, 1 Vicarage Hill",
    "sg:city":"Wrexham",
    "sg:classifiers":[
        {
            "category":"Shopping",
            "subcategory":"Computers & Home Electronics",
            "type":"Retail Goods"
        }
    ],
    "sg:postcode":"LL13 7HN",
    "sg:province":"Wrexham",
    "wof:name":"Taurus Computers (U K)",
    "wof:placetype":"venue"
},
  "geometry": {"coordinates":[-2.9971289635,53.0419540405],"type":"Point"}
}