{
  "type": "Feature",
  "properties": {
    "addr:full":"United Downs Industrial Estate, United Downs, St Day Redruth Cornwall TR16 5HP",
    "addr:postcode":"tr16 5hp",
    "addr:street":"Industrial Estate United Downs St",
    "iso:country":"GB",
    "sg:address":"United Downs Industrial Estate, United Downs, St Day",
    "sg:city":"Redruth",
    "sg:classifiers":[
        {
            "category":"Wholesale",
            "subcategory":"Scrap",
            "type":"Manufacturing & Wholesale Goods"
        }
    ],
    "sg:phone":"+44 1209 820282",
    "sg:postcode":"TR16 5HP",
    "sg:province":"Cornwall",
    "sg:tags":[
        "waste",
        "metal"
    ],
    "wof:name":"Malcolm Drew Ltd.",
    "wof:placetype":"venue"
},
  "geometry": {"coordinates":[-5.162519,50.230766],"type":"Point"}
}