{
  "type": "Feature",
  "properties": {
    "addr:full":"Harcombe Cross Newton Abbot Devon TQ13 0DF",
    "addr:housenumber":"abbot",
    "addr:postcode":"tq13 0df",
    "addr:street":"Harcombe Cross",
    "iso:country":"GB",
    "sg:address":"Harcombe Cross",
    "sg:city":"Newton Abbot",
    "sg:classifiers":[
        {
            "category":"Autos & Motor Vehicles",
            "subcategory":"Automobile Sales",
            "type":"Retail Goods"
        }
    ],
    "sg:phone":"+44 1626 854456",
    "sg:postcode":"TQ13 0DF",
    "sg:province":"Devon",
    "sg:tags":[
        "car"
    ],
    "wof:name":"Kybels Car Centre",
    "wof:placetype":"venue"
},
  "geometry": {"coordinates":[-3.5821299553,50.6235809326],"type":"Point"}
}