{
  "type": "Feature",
  "properties": {
    "iso:country":"GB",
    "sg:address":"57 Marlowes",
    "sg:city":"Hemel Hempstead",
    "sg:classifiers":[
        {
            "category":"Real Estate",
            "subcategory":"Surveying",
            "type":"Services"
        }
    ],
    "sg:phone":"+44 1442 242726",
    "sg:postcode":"HP1 1LE",
    "sg:province":"Hertfordshire",
    "sg:tags":[
        "surveyor",
        "valuer"
    ],
    "wof:name":"Rothesay Court Management Co. Ltd.",
    "wof:placetype":"venue"
},
  "geometry": {"coordinates":[-0.472689,51.75502],"type":"Point"}
}