{
  "type": "Feature",
  "properties": {
    "addr:full":"Po Box 457 Sheffield South Yorkshire S9 3UU",
    "addr:housenumber":"po",
    "addr:postcode":"s9 3uu",
    "addr:street":"Box 457",
    "iso:country":"GB",
    "sg:address":"Po Box 457",
    "sg:city":"Sheffield",
    "sg:classifiers":[
        {
            "category":"Manufacturing",
            "subcategory":"Tools & Machinery",
            "type":"Manufacturing & Wholesale Goods"
        }
    ],
    "sg:phone":"+44 114 243 7296",
    "sg:postcode":"S9 3UU",
    "sg:province":"South Yorkshire",
    "sg:tags":[
        "power"
    ],
    "wof:name":"M E I Unitech Ltd.",
    "wof:placetype":"venue"
},
  "geometry": {"coordinates":[-1.42673,53.389801],"type":"Point"}
}