{
  "type": "Feature",
  "properties": {
    "addr:full":"20 The Fairways, New River Trading Estate Waltham Cross Essex EN8 0NL",
    "addr:housenumber":"20",
    "addr:postcode":"en8 0nl",
    "addr:street":"The Fairways;Waltham Cross",
    "iso:country":"GB",
    "sg:address":"20 The Fairways, New River Trading Estate",
    "sg:city":"Waltham Cross",
    "sg:classifiers":[
        {
            "category":"Professional",
            "subcategory":"Printing & Photocopies",
            "type":"Services"
        }
    ],
    "sg:phone":"+44 1992 630766",
    "sg:postcode":"EN8 0NL",
    "sg:province":"Essex",
    "sg:tags":[
        "duplicating",
        "copying"
    ],
    "wof:name":"Rentokil Office Machine Maintenance",
    "wof:placetype":"venue"
},
  "geometry": {"coordinates":[-0.0338140018,51.6905097961],"type":"Point"}
}