{
  "type": "Feature",
  "properties": {
    "iso:country":"GB",
    "sg:address":"7 Southey Hill",
    "sg:city":"Sheffield",
    "sg:classifiers":[
        {
            "category":"Cafe",
            "type":"Food & Drink"
        }
    ],
    "sg:postcode":"S5 8BA",
    "sg:province":"South Yorkshire",
    "sg:tags":[
        "tea",
        "room"
    ],
    "wof:name":"The Oven Bottom",
    "wof:placetype":"venue"
},
  "geometry": {"coordinates":[-1.480405,53.418869],"type":"Point"}
}