{
  "type": "Feature",
  "properties": {
    "iso:country":"GB",
    "sg:address":"High Street, South Normanton",
    "sg:city":"Alfreton",
    "sg:classifiers":[
        {
            "category":"Retail",
            "subcategory":"Funeral Services",
            "type":"Services"
        }
    ],
    "sg:phone":"+44 1773 834973",
    "sg:postcode":"DE55 2BP",
    "sg:province":"Derbyshire",
    "sg:tags":[
        "cemetery",
        "crematorium"
    ],
    "wof:name":"G B Davies & Sons",
    "wof:placetype":"venue"
},
  "geometry": {"coordinates":[-1.3411389589,53.1076850891],"type":"Point"}
}