{
  "type": "Feature",
  "properties": {
    "addr:full":"5 Madrid Road Guildford Surrey GU2 7NU",
    "addr:housenumber":"5",
    "addr:postcode":"gu2 7nu",
    "addr:street":"Madrid Road",
    "iso:country":"GB",
    "sg:address":"5 Madrid Road",
    "sg:city":"Guildford",
    "sg:classifiers":[
        {
            "category":"Shopping",
            "subcategory":"Pharmacy",
            "type":"Retail Goods"
        }
    ],
    "sg:phone":"+44 1483 504461",
    "sg:postcode":"GU2 7NU",
    "sg:province":"Surrey",
    "sg:tags":[
        "pharmacist",
        "chemist"
    ],
    "wof:name":"Direct Pharmacy",
    "wof:placetype":"venue"
},
  "geometry": {"coordinates":[-0.586647,51.237614],"type":"Point"}
}