{
  "type": "Feature",
  "properties": {
    "addr:full":"37 Second Avenue Dagenham Essex RM10 9DX",
    "addr:housenumber":"37",
    "addr:postcode":"rm10 9dx",
    "addr:street":"Second Avenue",
    "iso:country":"GB",
    "sg:address":"37 Second Avenue",
    "sg:city":"Dagenham",
    "sg:classifiers":[
        {
            "category":"Building & Trades",
            "subcategory":"Construction",
            "type":"Services"
        }
    ],
    "sg:postcode":"RM10 9DX",
    "sg:province":"Essex",
    "sg:tags":[
        "roofing"
    ],
    "wof:name":"S S Roofing",
    "wof:placetype":"venue"
},
  "geometry": {"coordinates":[0.158307,51.530449],"type":"Point"}
}