{
  "type": "Feature",
  "properties": {
    "addr:full":"4 The Ridgeway, Parklands Estate Chichester West Sussex PO19 3LA",
    "addr:housenumber":"4",
    "addr:postcode":"po19 3la",
    "addr:street":"The Ridgeway;Estate",
    "iso:country":"GB",
    "sg:address":"4 The Ridgeway, Parklands Estate",
    "sg:city":"Chichester",
    "sg:classifiers":[
        {
            "category":"Shopping",
            "subcategory":"News",
            "type":"Retail Goods"
        }
    ],
    "sg:phone":"+44 1243 784112",
    "sg:postcode":"PO19 3LA",
    "sg:province":"West Sussex",
    "sg:tags":[
        "newsagent"
    ],
    "wof:name":"Parklands Stores",
    "wof:placetype":"venue"
},
  "geometry": {"coordinates":[-0.7754290104,50.8361663818],"type":"Point"}
}