{
  "type": "Feature",
  "properties": {
    "addr:full":"Grearshill Road, Kingstown Industrial Estate Carlisle Cumbria CA3 0ET",
    "addr:housenumber":"estate",
    "addr:postcode":"ca3 0et",
    "addr:street":"Grearshill Road;Industrial",
    "iso:country":"GB",
    "sg:address":"Grearshill Road, Kingstown Industrial Estate",
    "sg:city":"Carlisle",
    "sg:classifiers":[
        {
            "category":"Autos & Motor Vehicles",
            "subcategory":"Auto Supplies",
            "type":"Retail Goods"
        }
    ],
    "sg:phone":"+44 1228 591819",
    "sg:postcode":"CA3 0ET",
    "sg:province":"Cumbria",
    "sg:tags":[
        "component"
    ],
    "wof:name":"Roadspring Services",
    "wof:placetype":"venue"
},
  "geometry": {"coordinates":[-2.946567,54.925545],"type":"Point"}
}