{
  "type": "Feature",
  "properties": {
    "addr:full":"Chatsworth Road London Greater London NW2 4BL",
    "addr:postcode":"nw2 4bl",
    "addr:street":"Chatsworth Road",
    "iso:country":"GB",
    "sg:address":"Chatsworth Road",
    "sg:city":"London",
    "sg:classifiers":[
        {
            "category":"Arena",
            "subcategory":"Sports Club",
            "type":"Entertainment"
        }
    ],
    "sg:phone":"+44 20 8459 2517",
    "sg:postcode":"NW2 4BL",
    "sg:province":"Greater London",
    "wof:name":"Bromdesbury Bowling Club Ltd.",
    "wof:placetype":"venue"
},
  "geometry": {"coordinates":[-0.213284,51.547085],"type":"Point"}
}