{
  "type": "Feature",
  "properties": {
    "addr:full":"Treetops, Turncroft Road Darwen Lancashire BB3 2BW",
    "addr:postcode":"bb3 2bw",
    "addr:street":"Turncroft Road",
    "iso:country":"GB",
    "sg:address":"Treetops, Turncroft Road",
    "sg:city":"Darwen",
    "sg:classifiers":[
        {
            "category":"Transit Center",
            "subcategory":"Passenger",
            "type":"Transportation"
        },
        {
            "category":"Building & Trades",
            "subcategory":"Construction",
            "type":"Services"
        }
    ],
    "sg:phone":"+44 1254 773187",
    "sg:postcode":"BB3 2BW",
    "sg:province":"Lancashire",
    "sg:tags":[
        "boarding",
        "conversion",
        "loft",
        "kennel",
        "catteries"
    ],
    "wof:name":"Airtax",
    "wof:placetype":"venue"
},
  "geometry": {"coordinates":[-2.4575409889,53.6913490295],"type":"Point"}
}