{
  "type": "Feature",
  "properties": {
    "addr:full":"95 Hatton Garden London Greater London EC1N 8NX",
    "addr:housenumber":"95",
    "addr:postcode":"ec1n 8nx",
    "addr:street":"Hatton Garden",
    "iso:country":"GB",
    "sg:address":"95 Hatton Garden",
    "sg:city":"London",
    "sg:classifiers":[
        {
            "category":"Shopping",
            "subcategory":"Comic Books",
            "type":"Retail Goods"
        }
    ],
    "sg:phone":"+44 20 7419 9013",
    "sg:postcode":"EC1N 8NX",
    "sg:province":"Greater London",
    "sg:tags":[
        "jeweller"
    ],
    "wof:name":"J & A Jewellers",
    "wof:placetype":"venue"
},
  "geometry": {"coordinates":[-0.108269,51.519135],"type":"Point"}
}