{
  "type": "Feature",
  "properties": {
    "addr:full":"Unit 3b Maguire Industrial Estat, E 219 Torrington Coventry Warwickshire CV4 9HN",
    "addr:housenumber":"unit 3b;219",
    "addr:postcode":"cv4 9hn",
    "addr:street":"Maguire Industrial Estat E",
    "iso:country":"GB",
    "sg:address":"Unit 3b Maguire Industrial Estat, E 219 Torrington",
    "sg:city":"Coventry",
    "sg:classifiers":[
        {
            "category":"Manufacturing",
            "subcategory":"Motor Vehicles & Parts",
            "type":"Manufacturing & Wholesale Goods"
        },
        {
            "category":"Autos & Motor Vehicles",
            "subcategory":"Auto Supplies",
            "type":"Retail Goods"
        }
    ],
    "sg:phone":"+44 24 7646 7960",
    "sg:postcode":"CV4 9HN",
    "sg:province":"Warwickshire",
    "sg:tags":[
        "electric",
        "servicing",
        "sales"
    ],
    "wof:name":"Coventry Rewinds Ltd",
    "wof:placetype":"venue"
},
  "geometry": {"coordinates":[-1.5805599689,52.3979492188],"type":"Point"}
}