{
  "type": "Feature",
  "properties": {
    "iso:country":"GB",
    "sg:address":"Acre House",
    "sg:city":"London",
    "sg:classifiers":[
        {
            "category":"Professional",
            "type":"Services"
        }
    ],
    "sg:postcode":"NW1 3ER",
    "sg:province":"Greater London",
    "sg:tags":[
        "interior",
        "furnishers",
        "designer"
    ],
    "wof:name":"Shed Productions (Fw) Ltd.",
    "wof:placetype":"venue"
},
  "geometry": {"coordinates":[-0.087914,51.50737],"type":"Point"}
}