{
  "type": "Feature",
  "properties": {
    "addr:full":"Cardiff Road Cowbridge The Vale of Glamorgan CF71 7EP",
    "addr:postcode":"cf71 7ep",
    "addr:street":"Cardiff Road;Vale",
    "iso:country":"GB",
    "sg:address":"Cardiff Road",
    "sg:city":"Cowbridge",
    "sg:classifiers":[
        {
            "category":"Bars & Pubs",
            "type":"Food & Drink"
        },
        {
            "category":"Community Center",
            "subcategory":"Social",
            "type":"Public Place"
        }
    ],
    "sg:phone":"+44 1446 773192",
    "sg:postcode":"CF71 7EP",
    "sg:province":"The Vale of Glamorgan",
    "sg:tags":[
        "pubs",
        "house",
        "inn",
        "activity"
    ],
    "wof:name":"Edmondes Arms",
    "wof:placetype":"venue"
},
  "geometry": {"coordinates":[-3.4414250851,51.4589767456],"type":"Point"}
}