{
  "type": "Feature",
  "properties": {
    "addr:full":"1 Badsley Street Rotherham South Yorkshire S65 2PN",
    "addr:housenumber":"1",
    "addr:postcode":"s65 2pn",
    "addr:street":"Badsley Street",
    "iso:country":"GB",
    "sg:address":"1 Badsley Street",
    "sg:city":"Rotherham",
    "sg:classifiers":[
        {
            "category":"Health Services",
            "subcategory":"Dentist",
            "type":"Services"
        }
    ],
    "sg:phone":"+44 1709 371423",
    "sg:postcode":"S65 2PN",
    "sg:province":"South Yorkshire",
    "sg:tags":[
        "technician",
        "dental"
    ],
    "wof:name":"Easeholm Dental Laboratories Ltd",
    "wof:placetype":"venue"
},
  "geometry": {"coordinates":[-1.3420799971,53.4274902344],"type":"Point"}
}