{
  "type": "Feature",
  "properties": {
    "addr:full":"Post Office House, 1 Elliott Street Crook Durham DL15 8QH",
    "addr:housenumber":"1",
    "addr:postcode":"dl15 8qh",
    "addr:street":"Elliott Street",
    "iso:country":"GB",
    "sg:address":"Post Office House, 1 Elliott Street",
    "sg:city":"Crook",
    "sg:classifiers":[
        {
            "category":"Professional",
            "subcategory":"Lawyer & Legal Services",
            "type":"Services"
        }
    ],
    "sg:phone":"+44 1388 762466",
    "sg:postcode":"DL15 8QH",
    "sg:province":"Durham",
    "sg:tags":[
        "solicitor"
    ],
    "wof:name":"Marquis Penna",
    "wof:placetype":"venue"
},
  "geometry": {"coordinates":[-1.7462099791,54.7141036987],"type":"Point"}
}