{
  "type": "Feature",
  "properties": {
    "addr:full":"44 Scarrots Lane Newport Isle of Wight PO30 1JD",
    "addr:housenumber":"44",
    "addr:postcode":"po30 1jd",
    "addr:street":"Scarrots Lane",
    "iso:country":"GB",
    "sg:address":"44 Scarrots Lane",
    "sg:city":"Newport",
    "sg:classifiers":[
        {
            "category":"Food & Beverages",
            "subcategory":"Bakery",
            "type":"Retail Goods"
        }
    ],
    "sg:phone":"+44 1985 521187",
    "sg:postcode":"PO30 1JD",
    "sg:province":"Isle of Wight",
    "sg:tags":[
        "shop",
        "baker"
    ],
    "wof:name":"Market Bakery",
    "wof:placetype":"venue"
},
  "geometry": {"coordinates":[-1.2963570356,50.6987991333],"type":"Point"}
}