{
  "type": "Feature",
  "properties": {
    "iso:country":"GB",
    "sg:address":"21 Hilltop Rd, Bishop Meadows, Bearpark",
    "sg:city":"Durham",
    "sg:classifiers":[
        {
            "category":"Health Services",
            "subcategory":"Nursing And Care Facility",
            "type":"Services"
        }
    ],
    "sg:phone":"+44 191 373 6791",
    "sg:postcode":"DH7 7TA",
    "sg:province":"Durham",
    "sg:tags":[
        "agency"
    ],
    "wof:name":"Perri Homecare",
    "wof:placetype":"venue"
},
  "geometry": {"coordinates":[-1.632009,54.78307],"type":"Point"}
}