{
  "type": "Feature",
  "properties": {
    "iso:country":"GB",
    "sg:address":"17 Dutton Street",
    "sg:city":"Accrington",
    "sg:classifiers":[
        {
            "category":"Shopping",
            "subcategory":"Optical Goods",
            "type":"Retail Goods"
        },
        {
            "category":"Health Services",
            "subcategory":"Optometrist",
            "type":"Services"
        },
        {
            "category":"Shopping",
            "subcategory":"Optician",
            "type":"Retail Goods"
        }
    ],
    "sg:phone":"+44 1254 233817",
    "sg:postcode":"BB5 1JT",
    "sg:province":"Lancashire",
    "sg:tags":[
        "medical",
        "ophthalmic"
    ],
    "sg:website":"http://www.swallen.co.uk",
    "wof:name":"S W Allen Ltd",
    "wof:placetype":"venue"
},
  "geometry": {"coordinates":[-2.365238905,53.7526817322],"type":"Point"}
}