{
  "type": "Feature",
  "properties": {
    "iso:country":"GB",
    "sg:address":"Francis Ho, Francis St",
    "sg:city":"London",
    "sg:classifiers":[
        {
            "category":"Organizations",
            "subcategory":"Membership Organization",
            "type":"Services"
        }
    ],
    "sg:postcode":"SW1P 1DE",
    "sg:province":"Greater London",
    "sg:tags":[
        "club"
    ],
    "wof:name":"N F M S Enterprises Ltd",
    "wof:placetype":"venue"
},
  "geometry": {"coordinates":[-0.136949,51.496201],"type":"Point"}
}