{
  "type": "Feature",
  "properties": {
    "iso:country":"GB",
    "sg:address":"92 Water Lane",
    "sg:city":"Wilmslow",
    "sg:classifiers":[
        {
            "category":"Shopping",
            "subcategory":"Clothing, Apparel, & Fashions",
            "type":"Retail Goods"
        },
        {
            "category":"Shopping",
            "subcategory":"Baby Store",
            "type":"Retail Goods"
        }
    ],
    "sg:phone":"+44 1625 525164",
    "sg:postcode":"SK9 5BB",
    "sg:province":"Cheshire",
    "sg:tags":[
        "child",
        "childrens",
        "babywear"
    ],
    "wof:name":"Nought To Sixteen",
    "wof:placetype":"venue"
},
  "geometry": {"coordinates":[-2.237558,53.326859],"type":"Point"}
}