{
  "type": "Feature",
  "properties": {
    "iso:country":"GB",
    "sg:address":"105 Bushley Mill Crescent",
    "sg:city":"Watford",
    "sg:classifiers":[
        {
            "category":"Home & Garden",
            "subcategory":"Household Appliances",
            "type":"Retail Goods"
        }
    ],
    "sg:phone":"+44 1923 818474",
    "sg:postcode":"WD24 7RB",
    "sg:province":"Hertfordshire",
    "sg:tags":[
        "electrical"
    ],
    "wof:name":"A B Appliances",
    "wof:placetype":"venue"
},
  "geometry": {"coordinates":[-0.392957,51.678516],"type":"Point"}
}