{
  "type": "Feature",
  "properties": {
    "iso:country":"GB",
    "sg:address":"1 Tilbury Close, Philadelphia",
    "sg:city":"Houghton-le-spring",
    "sg:classifiers":[
        {
            "category":"Retail",
            "subcategory":"Repair Shop",
            "type":"Services"
        }
    ],
    "sg:phone":"+44 191 584 4447",
    "sg:postcode":"DH4 4XD",
    "sg:province":"Durham",
    "sg:tags":[
        "upholstering",
        "upholsterer"
    ],
    "wof:name":"1st Choice Upholstery",
    "wof:placetype":"venue"
},
  "geometry": {"coordinates":[-1.487262,54.862392],"type":"Point"}
}