{
  "type": "Feature",
  "properties": {
    "iso:country":"GB",
    "sg:address":"Alban House, Brownfields",
    "sg:city":"Welwyn Garden City",
    "sg:classifiers":[
        {
            "category":"Building & Trades",
            "subcategory":"Equipment Rental",
            "type":"Services"
        }
    ],
    "sg:phone":"+44 1707 371858",
    "sg:postcode":"AL7 1BE",
    "sg:province":"Hertfordshire",
    "sg:tags":[
        "plant",
        "machinery"
    ],
    "wof:name":"Miskin Plant & Tool Hire Co. Ltd.",
    "wof:placetype":"venue"
},
  "geometry": {"coordinates":[-0.189307,51.804302],"type":"Point"}
}