{
  "type": "Feature",
  "properties": {
    "addr:full":"7 Deysbrook Lane Liverpool Merseyside L12 8RE",
    "addr:housenumber":"7",
    "addr:postcode":"l12 8re",
    "addr:street":"Deysbrook Lane",
    "iso:country":"GB",
    "sg:address":"7 Deysbrook Lane",
    "sg:city":"Liverpool",
    "sg:classifiers":[
        {
            "category":"Food & Beverages",
            "subcategory":"Fruits & Vegetables",
            "type":"Retail Goods"
        }
    ],
    "sg:phone":"+44 151 228 9687",
    "sg:postcode":"L12 8RE",
    "sg:province":"Merseyside",
    "sg:tags":[
        "greengrocer"
    ],
    "wof:name":"Moss's",
    "wof:placetype":"venue"
},
  "geometry": {"coordinates":[-2.899572,53.429497],"type":"Point"}
}