{
  "type": "Feature",
  "properties": {
    "addr:full":"39 Boughton Chester Cheshire CH3 5AF",
    "addr:housenumber":"39",
    "addr:postcode":"ch3 5af",
    "addr:street":"Boughton Chester",
    "iso:country":"GB",
    "sg:address":"39 Boughton",
    "sg:city":"Chester",
    "sg:classifiers":[
        {
            "category":"Personal",
            "subcategory":"Beauty Salon",
            "type":"Services"
        },
        {
            "category":"Personal",
            "subcategory":"Barber",
            "type":"Services"
        }
    ],
    "sg:phone":"+44 1244 350432",
    "sg:postcode":"CH3 5AF",
    "sg:province":"Cheshire",
    "sg:tags":[
        "unisex",
        "hairdresser"
    ],
    "wof:name":"Hair Craft Studio",
    "wof:placetype":"venue"
},
  "geometry": {"coordinates":[-2.8789620399,53.1925392151],"type":"Point"}
}