{
  "type": "Feature",
  "properties": {
    "addr:full":"5a South Street Bourne Lincolnshire PE10 9LY",
    "addr:housenumber":"5a",
    "addr:postcode":"pe10 9ly",
    "addr:street":"South Street",
    "iso:country":"GB",
    "sg:address":"5a South Street",
    "sg:city":"Bourne",
    "sg:classifiers":[
        {
            "category":"Shopping",
            "subcategory":"Hobbies, Toys, & Games",
            "type":"Retail Goods"
        },
        {
            "category":"Shopping",
            "subcategory":"Music",
            "type":"Retail Goods"
        }
    ],
    "sg:phone":"+44 1778 426898",
    "sg:postcode":"PE10 9LY",
    "sg:province":"Lincolnshire",
    "sg:tags":[
        "shop",
        "toy",
        "sale"
    ],
    "wof:name":"Teddy Bears & Friends Of Bourne",
    "wof:placetype":"venue"
},
  "geometry": {"coordinates":[-0.3773300052,52.7675285339],"type":"Point"}
}