{
  "type": "Feature",
  "properties": {
    "iso:country":"GB",
    "sg:address":"Abererch Sands Holiday Centre, Abererch",
    "sg:city":"Pwllheli",
    "sg:classifiers":[
        {
            "category":"Recreation",
            "subcategory":"Campground",
            "type":"Entertainment"
        }
    ],
    "sg:phone":"+44 1758 612327",
    "sg:postcode":"LL53 6PJ",
    "sg:province":"Gwynedd",
    "sg:tags":[
        "caravan",
        "park"
    ],
    "wof:name":"Abererch Sands Holiday Centre Ltd.",
    "wof:placetype":"venue"
},
  "geometry": {"coordinates":[-4.381459,52.904003],"type":"Point"}
}