{
  "type": "Feature",
  "properties": {
    "addr:full":"4 Nelson Road Sheringham Norfolk NR26 8BU",
    "addr:housenumber":"4",
    "addr:postcode":"nr26 8bu",
    "addr:street":"Nelson Road",
    "iso:country":"GB",
    "sg:address":"4 Nelson Road",
    "sg:city":"Sheringham",
    "sg:classifiers":[
        {
            "category":"Shopping",
            "subcategory":"Pharmacy",
            "type":"Retail Goods"
        }
    ],
    "sg:postcode":"NR26 8BU",
    "sg:province":"Norfolk",
    "sg:tags":[
        "medicine",
        "therapy"
    ],
    "wof:name":"The Homoeopathic Supply Co.",
    "wof:placetype":"venue"
},
  "geometry": {"coordinates":[1.219887,52.943127],"type":"Point"}
}