{
  "type": "Feature",
  "properties": {
    "iso:country":"GB",
    "sg:address":"113 Balaam St",
    "sg:city":"Plaistow",
    "sg:classifiers":[
        {
            "category":"Health Services",
            "subcategory":"Clinic",
            "type":"Services"
        }
    ],
    "sg:phone":"+44 20 8218 7400",
    "sg:postcode":"E13 8AF",
    "sg:province":"Greater London",
    "sg:tags":[
        "nh"
    ],
    "wof:name":"Balaam Park Health Centre",
    "wof:placetype":"venue"
},
  "geometry": {"coordinates":[0.024017,51.525726],"type":"Point"}
}