{
  "type": "Feature",
  "properties": {
    "addr:full":"33 Cottall Avenue Chatham Kent ME4 6HG",
    "addr:housenumber":"33",
    "addr:postcode":"me4 6hg",
    "addr:street":"Cottall Avenue",
    "iso:country":"GB",
    "sg:address":"33 Cottall Avenue",
    "sg:city":"Chatham",
    "sg:classifiers":[
        {
            "category":"Personal",
            "subcategory":"Beauty Salon",
            "type":"Services"
        }
    ],
    "sg:postcode":"ME4 6HG",
    "sg:province":"Kent",
    "sg:tags":[
        "unisex",
        "hairdresser"
    ],
    "wof:name":"Avenue Hair Fashions",
    "wof:placetype":"venue"
},
  "geometry": {"coordinates":[0.523689,51.371975],"type":"Point"}
}