{
  "type": "Feature",
  "properties": {
    "iso:country":"GB",
    "sg:address":"16 Welbeck Road, Bolsover",
    "sg:city":"Chesterfield",
    "sg:classifiers":[
        {
            "category":"Personal",
            "subcategory":"Beauty Salon",
            "type":"Services"
        }
    ],
    "sg:phone":"+44 1246 822266",
    "sg:postcode":"S44 6DE",
    "sg:province":"Derbyshire",
    "sg:tags":[
        "unisex",
        "hairdresser"
    ],
    "wof:name":"Monicas Unisex Hair Fashions",
    "wof:placetype":"venue"
},
  "geometry": {"coordinates":[-1.2887860537,53.2300682068],"type":"Point"}
}