{
  "type": "Feature",
  "properties": {
    "iso:country":"GB",
    "sg:address":"43 Northfield Road",
    "sg:city":"Peterborough",
    "sg:classifiers":[
        {
            "category":"Building & Trades",
            "subcategory":"Plumbing",
            "type":"Services"
        }
    ],
    "sg:phone":"+44 1733 263662",
    "sg:postcode":"PE1 3QG",
    "sg:province":"Cambridgeshire",
    "sg:tags":[
        "heating"
    ],
    "wof:name":"A P S Plumbing & Heating",
    "wof:placetype":"venue"
},
  "geometry": {"coordinates":[-0.2473080009,52.5909042358],"type":"Point"}
}