{
  "type": "Feature",
  "properties": {
    "addr:full":"10 Rossett Avenue Harrogate North Yorkshire HG2 9NA",
    "addr:housenumber":"10",
    "addr:postcode":"hg2 9na",
    "addr:street":"Rossett Avenue",
    "iso:country":"GB",
    "sg:address":"10 Rossett Avenue",
    "sg:city":"Harrogate",
    "sg:classifiers":[
        {
            "category":"Professional",
            "subcategory":"Engineering",
            "type":"Services"
        }
    ],
    "sg:phone":"+44 1423 872149",
    "sg:postcode":"HG2 9NA",
    "sg:province":"North Yorkshire",
    "sg:tags":[
        "civil",
        "engineer"
    ],
    "wof:name":"Ickringill & Norton Ltd.",
    "wof:placetype":"venue"
},
  "geometry": {"coordinates":[-1.548571,53.973785],"type":"Point"}
}