{
  "type": "Feature",
  "properties": {
    "addr:full":"18-22 Bank Street Alloa Clackmannanshire FK10 1HP",
    "addr:housenumber":"18-22",
    "addr:postcode":"fk10 1hp",
    "addr:street":"Bank Street",
    "iso:country":"GB",
    "sg:address":"18-22 Bank Street",
    "sg:city":"Alloa",
    "sg:classifiers":[
        {
            "category":"Professional",
            "subcategory":"Lawyer & Legal Services",
            "type":"Services"
        }
    ],
    "sg:phone":"+44 1259 724411",
    "sg:postcode":"FK10 1HP",
    "sg:province":"Clackmannanshire",
    "sg:tags":[
        "solicitor"
    ],
    "wof:name":"Jardine Donaldson",
    "wof:placetype":"venue"
},
  "geometry": {"coordinates":[-3.7935380936,56.1141395569],"type":"Point"}
}