{
  "type": "Feature",
  "properties": {
    "addr:full":"Kirkland Road Kilbirnie North Ayrshire KA25 6HT",
    "addr:postcode":"ka25 6ht",
    "addr:street":"Kirkland Road",
    "iso:country":"GB",
    "sg:address":"Kirkland Road",
    "sg:city":"Kilbirnie",
    "sg:classifiers":[
        {
            "category":"Arena",
            "subcategory":"Stadium",
            "type":"Entertainment"
        },
        {
            "category":"Arena",
            "subcategory":"Sports Club",
            "type":"Entertainment"
        }
    ],
    "sg:phone":"+44 1505 683667",
    "sg:postcode":"KA25 6HT",
    "sg:province":"North Ayrshire",
    "sg:tags":[
        "ground"
    ],
    "wof:name":"Ladeside Pavilion",
    "wof:placetype":"venue"
},
  "geometry": {"coordinates":[-4.683959,55.745338],"type":"Point"}
}