{
  "type": "Feature",
  "properties": {
    "addr:full":"Unit 5 Newchase Business Park, Shaftesbury Street Derby Derbyshire DE23 8YB",
    "addr:housenumber":"unit 5",
    "addr:postcode":"de23 8yb",
    "addr:street":"Newchase Business Park Shaftesbury Street",
    "iso:country":"GB",
    "sg:address":"Unit 5 Newchase Business Park, Shaftesbury Street",
    "sg:city":"Derby",
    "sg:classifiers":[
        {
            "category":"Social Services",
            "type":"Services"
        },
        {
            "category":"Manufacturing",
            "subcategory":"Tobacco Products",
            "type":"Manufacturing & Wholesale Goods"
        }
    ],
    "sg:phone":"+44 1332 295821",
    "sg:postcode":"DE23 8YB",
    "sg:province":"Derbyshire",
    "sg:tags":[
        "equipment",
        "suppliers",
        "disability",
        "manufacturers"
    ],
    "wof:name":"Midequip Ltd",
    "wof:placetype":"venue"
},
  "geometry": {"coordinates":[-1.46681,52.904339],"type":"Point"}
}