{
  "type": "Feature",
  "properties": {
    "addr:full":"10 Oxford Street High Wycombe Buckinghamshire HP11 2DG",
    "addr:housenumber":"10",
    "addr:postcode":"hp11 2dg",
    "addr:street":"Oxford Street",
    "iso:country":"GB",
    "sg:address":"10 Oxford Street",
    "sg:city":"High Wycombe",
    "sg:classifiers":[
        {
            "category":"Fast Food",
            "type":"Food & Drink"
        }
    ],
    "sg:phone":"+44 1494 463340",
    "sg:postcode":"HP11 2DG",
    "sg:province":"Buckinghamshire",
    "sg:tags":[
        "away",
        "take"
    ],
    "wof:name":"Demmis Kebab Centre",
    "wof:placetype":"venue"
},
  "geometry": {"coordinates":[-0.7534329891,51.6307487488],"type":"Point"}
}