{
  "type": "Feature",
  "properties": {
    "iso:country":"GB",
    "sg:address":"393 Hertford Road",
    "sg:city":"Enfield",
    "sg:classifiers":[
        {
            "category":"Sports & Exercise",
            "subcategory":"Gym",
            "type":"Entertainment"
        }
    ],
    "sg:postcode":"EN3 5PP",
    "sg:province":"Greater London",
    "sg:tags":[
        "fitness",
        "health",
        "centre"
    ],
    "wof:name":"Four Seasons",
    "wof:placetype":"venue"
},
  "geometry": {"coordinates":[-0.044612,51.663818],"type":"Point"}
}