{
  "type": "Feature",
  "properties": {
    "addr:full":"19 Church Street Southport Lancashire PR9 0QT",
    "addr:housenumber":"19",
    "addr:postcode":"pr9 0qt",
    "addr:street":"Church Street",
    "iso:country":"GB",
    "sg:address":"19 Church Street",
    "sg:city":"Southport",
    "sg:classifiers":[
        {
            "category":"Retail",
            "subcategory":"Veterinary Services",
            "type":"Services"
        }
    ],
    "sg:postcode":"PR9 0QT",
    "sg:province":"Lancashire",
    "sg:tags":[
        "surgeon"
    ],
    "wof:name":"Alder Veterinary Center",
    "wof:placetype":"venue"
},
  "geometry": {"coordinates":[-2.9962251186,53.6485748291],"type":"Point"}
}