{
  "type": "Feature",
  "properties": {
    "addr:full":"Units 19-20 Aztec Ctre Queensway, Fforestfach Swansea Swansea SA5 4DH",
    "addr:housenumber":"units 19-20",
    "addr:postcode":"sa5 4dh",
    "addr:street":"Aztec Ctre Queensway Fforestfach",
    "iso:country":"GB",
    "sg:address":"Units 19-20 Aztec Ctre Queensway, Fforestfach",
    "sg:city":"Swansea",
    "sg:classifiers":[
        {
            "category":"Ice Cream",
            "type":"Food & Drink"
        }
    ],
    "sg:postcode":"SA5 4DH",
    "sg:province":"Swansea",
    "wof:name":"D & D Icecream Supplies",
    "wof:placetype":"venue"
},
  "geometry": {"coordinates":[-3.9890189171,51.6455116272],"type":"Point"}
}