{
  "type": "Feature",
  "properties": {
    "iso:country":"GB",
    "sg:address":"22 Coed Onn Rd",
    "sg:city":"Flint",
    "sg:classifiers":[
        {
            "category":"Professional",
            "subcategory":"Employment Agencies",
            "type":"Services"
        }
    ],
    "sg:phone":"+44 1352 730160",
    "sg:postcode":"CH6 5NE",
    "sg:province":"Flintshire",
    "sg:tags":[
        "consultant"
    ],
    "wof:name":"Pyramid Consultancy",
    "wof:placetype":"venue"
},
  "geometry": {"coordinates":[-3.135974,53.242817],"type":"Point"}
}