{
  "type": "Feature",
  "properties": {
    "iso:country":"GB",
    "sg:address":"Keepers Cottage, Stocking Lane, Bayford",
    "sg:city":"Hertford",
    "sg:classifiers":[
        {
            "category":"Professional",
            "type":"Services"
        }
    ],
    "sg:phone":"+44 1992 511444",
    "sg:postcode":"SG13 8PJ",
    "sg:province":"Hertfordshire",
    "sg:tags":[
        "aircraft",
        "maintenance"
    ],
    "wof:name":"Technical Resources International Ltd.",
    "wof:placetype":"venue"
},
  "geometry": {"coordinates":[-0.102728,51.759243],"type":"Point"}
}