{
  "type": "Feature",
  "properties": {
    "addr:full":"1 Mornington Avenue Rochford Essex SS4 1DW",
    "addr:housenumber":"1",
    "addr:postcode":"ss4 1dw",
    "addr:street":"Mornington Avenue",
    "iso:country":"GB",
    "sg:address":"1 Mornington Avenue",
    "sg:city":"Rochford",
    "sg:classifiers":[
        {
            "category":"Retail",
            "subcategory":"Auto Repair",
            "type":"Services"
        }
    ],
    "sg:postcode":"SS4 1DW",
    "sg:province":"Essex",
    "sg:tags":[
        "engine",
        "car",
        "specialist"
    ],
    "wof:name":"Mobile Computer Tune",
    "wof:placetype":"venue"
},
  "geometry": {"coordinates":[0.714509,51.585423],"type":"Point"}
}