{
  "type": "Feature",
  "properties": {
    "addr:full":"42 White Horse Hill Chislehurst Kent BR7 6DL",
    "addr:housenumber":"42",
    "addr:postcode":"br7 6dl",
    "addr:street":"White Horse Hill",
    "iso:country":"GB",
    "sg:address":"42 White Horse Hill",
    "sg:city":"Chislehurst",
    "sg:classifiers":[
        {
            "category":"Food & Beverages",
            "subcategory":"Meat & Fish",
            "type":"Retail Goods"
        }
    ],
    "sg:postcode":"BR7 6DL",
    "sg:province":"Kent",
    "sg:tags":[
        "butcher"
    ],
    "wof:name":"Eastlake Butchers",
    "wof:placetype":"venue"
},
  "geometry": {"coordinates":[0.0606059991,51.4232368469],"type":"Point"}
}