{
  "type": "Feature",
  "properties": {
    "addr:full":"Chapel La, Preston Lancashire PR4 5EB",
    "addr:postcode":"pr4 5eb",
    "iso:country":"GB",
    "sg:address":"Chapel La,",
    "sg:city":"Preston",
    "sg:classifiers":[
        {
            "category":"Autos & Motor Vehicles",
            "subcategory":"Automobile Sales",
            "type":"Retail Goods"
        }
    ],
    "sg:postcode":"PR4 5EB",
    "sg:province":"Lancashire",
    "sg:tags":[
        "car"
    ],
    "wof:name":"Suthers,John,& Sons Car Sales",
    "wof:placetype":"venue"
},
  "geometry": {"coordinates":[-2.777744,53.726589],"type":"Point"}
}