{
  "type": "Feature",
  "properties": {
    "addr:full":"Unit 11 Culvert House, Culvert Road London Greater London SW11 5AP",
    "addr:housenumber":"unit 11 culvert house",
    "addr:postcode":"sw11 5ap",
    "addr:street":"Culvert Road",
    "iso:country":"GB",
    "sg:address":"Unit 11 Culvert House, Culvert Road",
    "sg:city":"London",
    "sg:classifiers":[
        {
            "category":"Organizations",
            "subcategory":"Non-profit Organization",
            "type":"Services"
        }
    ],
    "sg:phone":"+44 20 7498 8878",
    "sg:postcode":"SW11 5AP",
    "sg:province":"Greater London",
    "sg:tags":[
        "organisation",
        "voluntary",
        "charity"
    ],
    "wof:name":"Sir Walter St.Johns Educational Charity",
    "wof:placetype":"venue"
},
  "geometry": {"coordinates":[-0.1600899994,51.4735794067],"type":"Point"}
}