{
  "type": "Feature",
  "properties": {
    "addr:full":"9 Market Centre Hayes Road Southall Greater London UB2 5XJ",
    "addr:housenumber":"9",
    "addr:postcode":"ub2 5xj",
    "addr:street":"Market Centre Hayes Road",
    "iso:country":"GB",
    "sg:address":"9 Market Centre Hayes Road",
    "sg:city":"Southall",
    "sg:classifiers":[
        {
            "category":"Professional",
            "subcategory":"Business Services",
            "type":"Services"
        }
    ],
    "sg:postcode":"UB2 5XJ",
    "sg:province":"Greater London",
    "sg:tags":[
        "import",
        "export",
        "agent"
    ],
    "wof:name":"Florian Ltd",
    "wof:placetype":"venue"
},
  "geometry": {"coordinates":[-0.40311,51.495941],"type":"Point"}
}