{
  "type": "Feature",
  "properties": {
    "iso:country":"GB",
    "sg:address":"153 Alder Road",
    "sg:city":"Poole",
    "sg:classifiers":[
        {
            "category":"Food & Beverages",
            "subcategory":"Fruits & Vegetables",
            "type":"Retail Goods"
        }
    ],
    "sg:phone":"+44 1202 740978",
    "sg:postcode":"BH12 4AA",
    "sg:province":"Dorset",
    "sg:tags":[
        "greengrocer"
    ],
    "wof:name":"Copsons Fruiters",
    "wof:placetype":"venue"
},
  "geometry": {"coordinates":[-1.919515,50.735889],"type":"Point"}
}