{
  "type": "Feature",
  "properties": {
    "addr:full":"1617 London Road Leigh-on-sea Essex SS9 2SQ",
    "addr:housenumber":"1617",
    "addr:postcode":"ss9 2sq",
    "addr:street":"London Road",
    "iso:country":"GB",
    "sg:address":"1617 London Road",
    "sg:city":"Leigh-on-sea",
    "sg:classifiers":[
        {
            "category":"Banks & Credit Unions",
            "subcategory":"Financial Services",
            "type":"Services"
        }
    ],
    "sg:phone":"+44 1702 470707",
    "sg:postcode":"SS9 2SQ",
    "sg:province":"Essex",
    "sg:tags":[
        "adviser"
    ],
    "wof:name":"Alexander Stronghold Insurance Services Ltd.",
    "wof:placetype":"venue"
},
  "geometry": {"coordinates":[0.637451,51.54792],"type":"Point"}
}