{
  "type": "Feature",
  "properties": {
    "iso:country":"GB",
    "sg:address":"Dane Farm, Stone Street, Petham",
    "sg:city":"Canterbury",
    "sg:classifiers":[
        {
            "category":"Shopping",
            "type":"Retail Goods"
        }
    ],
    "sg:phone":"+44 1227 700275",
    "sg:postcode":"CT4 5PP",
    "sg:province":"Kent",
    "sg:tags":[
        "merchant"
    ],
    "wof:name":"John Bourne & Co (Newenden)",
    "wof:placetype":"venue"
},
  "geometry": {"coordinates":[1.046144,51.223419],"type":"Point"}
}