{
  "type": "Feature",
  "properties": {
    "addr:full":"2-3 Pavilion Buildings Brighton East Sussex BN1 1EE",
    "addr:housenumber":"2-3",
    "addr:postcode":"bn1 1ee",
    "addr:street":"Pavilion Buildings",
    "iso:country":"GB",
    "sg:address":"2-3 Pavilion Buildings",
    "sg:city":"Brighton",
    "sg:classifiers":[
        {
            "category":"Professional",
            "subcategory":"Accounting & Tax Preparation",
            "type":"Services"
        }
    ],
    "sg:phone":"+44 1273 747847",
    "sg:postcode":"BN1 1EE",
    "sg:province":"East Sussex",
    "sg:tags":[
        "accountant"
    ],
    "wof:name":"Leonard Curtis & Associates",
    "wof:placetype":"venue"
},
  "geometry": {"coordinates":[-0.1386560053,50.8219718933],"type":"Point"}
}