{
  "type": "Feature",
  "properties": {
    "addr:full":"Castell Farm, Rhosesmor Road, Northop Mold Denbighshire CH7 6AG",
    "addr:postcode":"ch7 6ag",
    "addr:street":"Rhosesmor Road",
    "iso:country":"GB",
    "sg:address":"Castell Farm, Rhosesmor Road, Northop",
    "sg:city":"Mold",
    "sg:classifiers":[
        {
            "category":"Farming",
            "subcategory":"Dairy Farm",
            "type":"Manufacturing & Wholesale Goods"
        }
    ],
    "sg:phone":"+44 1352 840856",
    "sg:postcode":"CH7 6AG",
    "sg:province":"Denbighshire",
    "wof:name":"D M Roberts",
    "wof:placetype":"venue"
},
  "geometry": {"coordinates":[-3.1313490868,53.2069168091],"type":"Point"}
}