{
  "type": "Feature",
  "properties": {
    "addr:full":"9 Holmwood Close East Molesey Surrey KT24 6SS",
    "addr:housenumber":"9",
    "addr:postcode":"kt24 6ss",
    "addr:street":"Holmwood Close",
    "iso:country":"GB",
    "sg:address":"9 Holmwood Close",
    "sg:city":"East Molesey",
    "sg:classifiers":[
        {
            "category":"Real Estate",
            "subcategory":"Developer",
            "type":"Services"
        }
    ],
    "sg:postcode":"KT24 6SS",
    "sg:province":"Surrey",
    "sg:tags":[
        "property"
    ],
    "wof:name":"W & P Robinson Ltd.",
    "wof:placetype":"venue"
},
  "geometry": {"coordinates":[-0.433559,51.265434],"type":"Point"}
}