{
  "type": "Feature",
  "properties": {
    "iso:country":"GB",
    "sg:address":"Unit 21/23, Avenue One",
    "sg:city":"Witney",
    "sg:classifiers":[
        {
            "category":"Wholesale",
            "subcategory":"Vending Machines",
            "type":"Manufacturing & Wholesale Goods"
        }
    ],
    "sg:phone":"+44 1993 774601",
    "sg:postcode":"OX28 4BU",
    "sg:province":"Oxfordshire",
    "sg:tags":[
        "sale"
    ],
    "wof:name":"Polyvend Ltd.",
    "wof:placetype":"venue"
},
  "geometry": {"coordinates":[-1.489573,51.776833],"type":"Point"}
}