{
  "type": "Feature",
  "properties": {
    "iso:country":"GB",
    "sg:address":"3 Westbourne Avenue, Hodge Hill",
    "sg:city":"Birmingham",
    "sg:classifiers":[
        {
            "category":"Building & Trades",
            "subcategory":"Construction",
            "type":"Services"
        }
    ],
    "sg:phone":"+44 121 784 3070",
    "sg:postcode":"B34 6AN",
    "sg:province":"West Midlands",
    "sg:tags":[
        "decorator",
        "painter"
    ],
    "wof:name":"Flexible Decor",
    "wof:placetype":"venue"
},
  "geometry": {"coordinates":[-1.809504,52.495125],"type":"Point"}
}