{
  "type": "Feature",
  "properties": {
    "addr:full":"Church Road Keith Moray AB55 5BR",
    "addr:postcode":"ab55 5br",
    "addr:street":"Church Road",
    "iso:country":"GB",
    "sg:address":"Church Road",
    "sg:city":"Keith",
    "sg:classifiers":[
        {
            "category":"Organizations",
            "subcategory":"Community Association",
            "type":"Services"
        },
        {
            "category":"Organizations",
            "subcategory":"Membership Organization",
            "type":"Services"
        }
    ],
    "sg:phone":"+44 1542 887452",
    "sg:postcode":"AB55 5BR",
    "sg:province":"Moray",
    "sg:tags":[
        "club",
        "social"
    ],
    "wof:name":"Keith Bowling Club",
    "wof:placetype":"venue"
},
  "geometry": {"coordinates":[-2.952469,57.54348],"type":"Point"}
}