{
  "type": "Feature",
  "properties": {
    "iso:country":"GB",
    "sg:address":"226 Briercliffe Road",
    "sg:city":"Burnley",
    "sg:classifiers":[
        {
            "category":"Personal",
            "subcategory":"Beauty Salon",
            "type":"Services"
        },
        {
            "category":"Personal",
            "subcategory":"Barber",
            "type":"Services"
        }
    ],
    "sg:phone":"+44 1282 421955",
    "sg:postcode":"BB10 2NZ",
    "sg:province":"Lancashire",
    "sg:tags":[
        "unisex",
        "lady",
        "hairdresser"
    ],
    "wof:name":"Salon 226",
    "wof:placetype":"venue"
},
  "geometry": {"coordinates":[-2.221389,53.80991],"type":"Point"}
}