{
  "type": "Feature",
  "properties": {
    "addr:full":"Clarendon Ho, Hyde St Winchester Hampshire SO23 7DX",
    "addr:postcode":"so23 7dx",
    "addr:street":"Hyde St",
    "iso:country":"GB",
    "sg:address":"Clarendon Ho, Hyde St",
    "sg:city":"Winchester",
    "sg:classifiers":[
        {
            "category":"Professional",
            "subcategory":"Business Services",
            "type":"Services"
        }
    ],
    "sg:postcode":"SO23 7DX",
    "sg:province":"Hampshire",
    "sg:tags":[
        "holding"
    ],
    "wof:name":"Hart,David,Co Ltd",
    "wof:placetype":"venue"
},
  "geometry": {"coordinates":[-1.3168090582,51.0630683899],"type":"Point"}
}