{
  "type": "Feature",
  "properties": {
    "addr:full":"29 Warner Street Accrington Lancashire BB5 1HN",
    "addr:housenumber":"29",
    "addr:postcode":"bb5 1hn",
    "addr:street":"Warner Street",
    "iso:country":"GB",
    "sg:address":"29 Warner Street",
    "sg:city":"Accrington",
    "sg:classifiers":[
        {
            "category":"Personal",
            "subcategory":"Beauty Salon",
            "type":"Services"
        },
        {
            "category":"Personal",
            "subcategory":"Barber",
            "type":"Services"
        }
    ],
    "sg:phone":"+44 1254 383346",
    "sg:postcode":"BB5 1HN",
    "sg:province":"Lancashire",
    "sg:tags":[
        "unisex",
        "hairdresser"
    ],
    "wof:name":"James Hairshop",
    "wof:placetype":"venue"
},
  "geometry": {"coordinates":[-2.363027,53.751846],"type":"Point"}
}