{
  "type": "Feature",
  "properties": {
    "addr:full":"Oak House, Furze View, Slinfold Horsham West Sussex RH13 0RH",
    "addr:postcode":"rh13 0rh",
    "addr:street":"Furze View",
    "iso:country":"GB",
    "sg:address":"Oak House, Furze View, Slinfold",
    "sg:city":"Horsham",
    "sg:classifiers":[
        {
            "category":"Building & Trades",
            "subcategory":"Construction",
            "type":"Services"
        }
    ],
    "sg:postcode":"RH13 0RH",
    "sg:province":"West Sussex",
    "sg:tags":[
        "roofing"
    ],
    "wof:name":"Swift Contractors",
    "wof:placetype":"venue"
},
  "geometry": {"coordinates":[-0.4053319991,51.0700149536],"type":"Point"}
}