{
  "type": "Feature",
  "properties": {
    "addr:full":"7 Station Road Marlow Berkshire SL7 1NG",
    "addr:housenumber":"7",
    "addr:postcode":"sl7 1ng",
    "addr:street":"Station Road",
    "iso:country":"GB",
    "sg:address":"7 Station Road",
    "sg:city":"Marlow",
    "sg:classifiers":[
        {
            "category":"Transit Center",
            "subcategory":"Freight",
            "type":"Transportation"
        }
    ],
    "sg:phone":"+44 1628 487900",
    "sg:postcode":"SL7 1NG",
    "sg:province":"Berkshire",
    "sg:tags":[
        "shop",
        "craft",
        "centre"
    ],
    "wof:name":"Mulberry Crafts",
    "wof:placetype":"venue"
},
  "geometry": {"coordinates":[-0.77376,51.569355],"type":"Point"}
}