{
  "type": "Feature",
  "properties": {
    "addr:full":"225 Lozells Road, Lozells Birmingham West Midlands B19 1RJ",
    "addr:housenumber":"225",
    "addr:postcode":"b19 1rj",
    "addr:street":"Lozells Road",
    "iso:country":"GB",
    "sg:address":"225 Lozells Road, Lozells",
    "sg:city":"Birmingham",
    "sg:classifiers":[
        {
            "category":"Wholesale",
            "subcategory":"Machinery & Supplies",
            "type":"Manufacturing & Wholesale Goods"
        },
        {
            "category":"Shopping",
            "subcategory":"Crafts & Fabrics",
            "type":"Retail Goods"
        }
    ],
    "sg:phone":"+44 121 554 5073",
    "sg:postcode":"B19 1RJ",
    "sg:province":"West Midlands",
    "sg:tags":[
        "machine",
        "supplier",
        "sewing",
        "knitting"
    ],
    "wof:name":"Industrial Sewing Services Birmingham Ltd",
    "wof:placetype":"venue"
},
  "geometry": {"coordinates":[-1.914094,52.503124],"type":"Point"}
}