{
  "type": "Feature",
  "properties": {
    "iso:country":"GB",
    "sg:address":"Church Walk, Rear Of Fulwood Row",
    "sg:city":"Preston",
    "sg:classifiers":[
        {
            "category":"Autos & Motor Vehicles",
            "subcategory":"Auto Supplies",
            "type":"Retail Goods"
        }
    ],
    "sg:phone":"+44 1772 700713",
    "sg:postcode":"PR2 6SL",
    "sg:province":"Lancashire",
    "sg:tags":[
        "towing",
        "eqpt",
        "trailer"
    ],
    "wof:name":"Delta Engineering Co.",
    "wof:placetype":"venue"
},
  "geometry": {"coordinates":[-2.677049,53.778801],"type":"Point"}
}