{
  "type": "Feature",
  "properties": {
    "iso:country":"GB",
    "sg:address":"Maylite Trading Estate",
    "sg:city":"Worcester",
    "sg:classifiers":[
        {
            "category":"Home & Garden",
            "subcategory":"Kitchen Supply",
            "type":"Retail Goods"
        }
    ],
    "sg:phone":"+44 1886 888050",
    "sg:postcode":"WR6 6PQ",
    "sg:province":"Herefordshire",
    "sg:tags":[
        "measuring",
        "scale"
    ],
    "wof:name":"Euroweigh Ltd.",
    "wof:placetype":"venue"
},
  "geometry": {"coordinates":[-2.36808,52.230431],"type":"Point"}
}