{
  "type": "Feature",
  "properties": {
    "iso:country":"GB",
    "sg:address":"74 Carlton Avenue East",
    "sg:city":"Wembley",
    "sg:classifiers":[
        {
            "category":"Retail",
            "subcategory":"Driving School",
            "type":"Services"
        }
    ],
    "sg:phone":"+44 20 8723 8868",
    "sg:postcode":"HA9 8LY",
    "sg:province":"Greater London",
    "wof:name":"Anthony School of Motoring",
    "wof:placetype":"venue"
},
  "geometry": {"coordinates":[-0.289885,51.567909],"type":"Point"}
}