{
  "type": "Feature",
  "properties": {
    "addr:full":"192a Hard Lane St Helens Merseyside WA10 6PH",
    "addr:housenumber":"192a",
    "addr:postcode":"wa10 6ph",
    "addr:street":"Hard Lane",
    "iso:country":"GB",
    "sg:address":"192a Hard Lane",
    "sg:city":"St Helens",
    "sg:classifiers":[
        {
            "category":"Food & Beverages",
            "subcategory":"Liquor & Beverages",
            "type":"Retail Goods"
        }
    ],
    "sg:phone":"+44 1744 732353",
    "sg:postcode":"WA10 6PH",
    "sg:province":"Merseyside",
    "sg:tags":[
        "beer",
        "spirit",
        "wines"
    ],
    "wof:name":"Schooner Wines",
    "wof:placetype":"venue"
},
  "geometry": {"coordinates":[-2.745079,53.46796],"type":"Point"}
}