{
  "type": "Feature",
  "properties": {
    "addr:full":"Stowsdon Farm, Langdon Launceston Cornwall PL15 8NL",
    "addr:postcode":"pl15 8nl",
    "iso:country":"GB",
    "sg:address":"Stowsdon Farm, Langdon",
    "sg:city":"Launceston",
    "sg:classifiers":[
        {
            "category":"Farming",
            "subcategory":"Livestock Farm",
            "type":"Manufacturing & Wholesale Goods"
        }
    ],
    "sg:phone":"+44 1566 785347",
    "sg:postcode":"PL15 8NL",
    "sg:province":"Cornwall",
    "sg:tags":[
        "others"
    ],
    "wof:name":"T G Dingle",
    "wof:placetype":"venue"
},
  "geometry": {"coordinates":[-4.3633441925,50.6367073059],"type":"Point"}
}