{
  "type": "Feature",
  "properties": {
    "iso:country":"GB",
    "sg:address":"45-49 Chorley New Road",
    "sg:city":"Bolton",
    "sg:classifiers":[
        {
            "category":"Professional",
            "subcategory":"Testing Lab",
            "type":"Services"
        }
    ],
    "sg:phone":"+44 161 789 8990",
    "sg:postcode":"BL1 4QR",
    "sg:province":"Lancashire",
    "sg:tags":[
        "inspection",
        "calibration"
    ],
    "wof:name":"Servicecal Ltd",
    "wof:placetype":"venue"
},
  "geometry": {"coordinates":[-2.442818,53.581852],"type":"Point"}
}