{
  "type": "Feature",
  "properties": {
    "addr:full":"Nicholson Court, Priory Road Eastbourne East Sussex BN23 7AR",
    "addr:postcode":"bn23 7ar",
    "addr:street":"Nicholson;Priory Road",
    "iso:country":"GB",
    "sg:address":"Nicholson Court, Priory Road",
    "sg:city":"Eastbourne",
    "sg:classifiers":[
        {
            "category":"Organizations",
            "subcategory":"Community Association",
            "type":"Services"
        }
    ],
    "sg:phone":"+44 1323 764556",
    "sg:postcode":"BN23 7AR",
    "sg:province":"East Sussex",
    "sg:tags":[
        "society",
        "housing"
    ],
    "wof:name":"Housing 21",
    "wof:placetype":"venue"
},
  "geometry": {"coordinates":[0.315225,50.807224],"type":"Point"}
}