{
  "type": "Feature",
  "properties": {
    "iso:country":"GB",
    "sg:address":"37 Museum St",
    "sg:city":"Bloomsbury",
    "sg:classifiers":[
        {
            "category":"Shopping",
            "subcategory":"Books",
            "type":"Retail Goods"
        }
    ],
    "sg:phone":"+44 20 7430 0159",
    "sg:postcode":"WC1A 1LP",
    "sg:province":"Greater London",
    "sg:tags":[
        "second-hand"
    ],
    "wof:name":"The Print Room",
    "wof:placetype":"venue"
},
  "geometry": {"coordinates":[-0.1257990003,51.5179100037],"type":"Point"}
}