{
  "type": "Feature",
  "properties": {
    "addr:full":"Iron Hill, Hollycombe Liphook Hampshire GU30 7LP",
    "addr:postcode":"gu30 7lp",
    "addr:street":"Iron Hill Hollycombe",
    "iso:country":"GB",
    "sg:address":"Iron Hill, Hollycombe",
    "sg:city":"Liphook",
    "sg:classifiers":[
        {
            "category":"Shopping",
            "subcategory":"Pets & Pet Supplies",
            "type":"Retail Goods"
        }
    ],
    "sg:phone":"+44 1428 725137",
    "sg:postcode":"GU30 7LP",
    "sg:province":"Hampshire",
    "sg:tags":[
        "food",
        "feed",
        "animal"
    ],
    "wof:name":"Dene Country Stores",
    "wof:placetype":"venue"
},
  "geometry": {"coordinates":[-0.7991999984,51.0776405334],"type":"Point"}
}