{
  "type": "Feature",
  "properties": {
    "addr:full":"9 Burhley Ave Borehamwood Hertfordshire WD6 2JG",
    "addr:housenumber":"9",
    "addr:postcode":"wd6 2jg",
    "addr:street":"Burhley Ave",
    "iso:country":"GB",
    "sg:address":"9 Burhley Ave",
    "sg:city":"Borehamwood",
    "sg:classifiers":[
        {
            "category":"Building & Trades",
            "subcategory":"Construction",
            "type":"Services"
        }
    ],
    "sg:postcode":"WD6 2JG",
    "sg:province":"Hertfordshire",
    "sg:tags":[
        "roofing",
        "joiner",
        "carpenter"
    ],
    "wof:name":"Ratcliffe,Stephen,",
    "wof:placetype":"venue"
},
  "geometry": {"coordinates":[-0.2617610097,51.6485214233],"type":"Point"}
}