{
  "type": "Feature",
  "properties": {
    "addr:full":"15 Belmont Road Hemel Hempstead Hertfordshire HP3 9NZ",
    "addr:housenumber":"15",
    "addr:postcode":"hp3 9nz",
    "addr:street":"Belmont Road",
    "iso:country":"GB",
    "sg:address":"15 Belmont Road",
    "sg:city":"Hemel Hempstead",
    "sg:classifiers":[
        {
            "category":"Professional",
            "subcategory":"Art Services",
            "type":"Services"
        }
    ],
    "sg:postcode":"HP3 9NZ",
    "sg:province":"Hertfordshire",
    "sg:tags":[
        "photographer"
    ],
    "wof:name":"Nigel Wickens",
    "wof:placetype":"venue"
},
  "geometry": {"coordinates":[-0.46148,51.738773],"type":"Point"}
}