{
  "type": "Feature",
  "properties": {
    "iso:country":"GB",
    "sg:address":"Mount Pleasant",
    "sg:city":"Tonbridge",
    "sg:classifiers":[
        {
            "category":"Place Of Worship",
            "type":"Public Place"
        }
    ],
    "sg:phone":"+44 1892 833699",
    "sg:postcode":"TN12 6AG",
    "sg:province":"Kent",
    "wof:name":"St Justus R C Church",
    "wof:placetype":"venue"
},
  "geometry": {"coordinates":[0.382025,51.18037],"type":"Point"}
}