{
  "type": "Feature",
  "properties": {
    "addr:full":"Flat 5 Lily Marriott House, Gilmorton Close Leicester Leicestershire LE2 9GX",
    "addr:postcode":"le2 9gx",
    "addr:street":"Gilmorton Close",
    "iso:country":"GB",
    "sg:address":"Flat 5 Lily Marriott House, Gilmorton Close",
    "sg:city":"Leicester",
    "sg:classifiers":[
        {
            "category":"Retail",
            "subcategory":"Driving School",
            "type":"Services"
        }
    ],
    "sg:postcode":"LE2 9GX",
    "sg:province":"Leicestershire",
    "wof:name":"Ted Clarke",
    "wof:placetype":"venue"
},
  "geometry": {"coordinates":[-1.1646100283,52.5946006775],"type":"Point"}
}