{
  "type": "Feature",
  "properties": {
    "addr:full":"7 Kirklands Sale Cheshire M33 3SG",
    "addr:housenumber":"7",
    "addr:postcode":"m33 3sg",
    "addr:street":"Kirklands Sale Cheshire",
    "iso:country":"GB",
    "sg:address":"7 Kirklands",
    "sg:city":"Sale",
    "sg:classifiers":[
        {
            "category":"Shopping",
            "subcategory":"Stationery & Office Supplies",
            "type":"Retail Goods"
        }
    ],
    "sg:phone":"+44 161 962 7823",
    "sg:postcode":"M33 3SG",
    "sg:province":"Cheshire",
    "wof:name":"R & D Packaging & Print Supplies Ltd.",
    "wof:placetype":"venue"
},
  "geometry": {"coordinates":[-2.326392,53.415379],"type":"Point"}
}