{
  "type": "Feature",
  "properties": {
    "iso:country":"GB",
    "sg:address":"West Command Headquarters, 4 Barr Street",
    "sg:city":"Ardrossan",
    "sg:classifiers":[
        {
            "category":"Government",
            "subcategory":"Fire Station",
            "type":"Public Place"
        }
    ],
    "sg:phone":"+44 1294 607000",
    "sg:postcode":"KA22 8HD",
    "sg:province":"North Ayrshire",
    "wof:name":"Strathclyde Fire Brigade",
    "wof:placetype":"venue"
},
  "geometry": {"coordinates":[-4.813243866,55.6436424255],"type":"Point"}
}