{
  "type": "Feature",
  "properties": {
    "addr:full":"6 Upper Oak St Windermere Cumbria LA23 2LB",
    "addr:housenumber":"6",
    "addr:postcode":"la23 2lb",
    "addr:street":"Upper Oak St",
    "iso:country":"GB",
    "sg:address":"6 Upper Oak St",
    "sg:city":"Windermere",
    "sg:classifiers":[
        {
            "category":"Retail",
            "subcategory":"Storage",
            "type":"Services"
        }
    ],
    "sg:phone":"+44 15394 43323",
    "sg:postcode":"LA23 2LB",
    "sg:province":"Cumbria",
    "sg:tags":[
        "household",
        "removal"
    ],
    "wof:name":"W & J Martindale",
    "wof:placetype":"venue"
},
  "geometry": {"coordinates":[-2.9027760029,54.3761062622],"type":"Point"}
}