{
  "type": "Feature",
  "properties": {
    "iso:country":"GB",
    "sg:address":"Broomloan House, 170 Edmiston Drive",
    "sg:city":"Glasgow",
    "sg:classifiers":[
        {
            "category":"Professional",
            "subcategory":"Detective & Security Services",
            "type":"Services"
        }
    ],
    "sg:phone":"+44 141 419 9559",
    "sg:postcode":"G51 2YS",
    "sg:province":"Glasgow City",
    "wof:name":"Rock Steady Security",
    "wof:placetype":"venue"
},
  "geometry": {"coordinates":[-4.3079981804,55.8523521423],"type":"Point"}
}