{
  "type": "Feature",
  "properties": {
    "addr:full":"14 Erleigh Court Gardens, Earley Reading Berkshire RG6 1EH",
    "addr:housenumber":"14",
    "addr:postcode":"rg6 1eh",
    "addr:street":"Erleigh Court Gardens",
    "iso:country":"GB",
    "sg:address":"14 Erleigh Court Gardens, Earley",
    "sg:city":"Reading",
    "sg:classifiers":[
        {
            "category":"Building & Trades",
            "subcategory":"Plumbing",
            "type":"Services"
        }
    ],
    "sg:phone":"+44 118 926 2313",
    "sg:postcode":"RG6 1EH",
    "sg:province":"Berkshire",
    "sg:tags":[
        "central",
        "heating"
    ],
    "wof:name":"B J Heating",
    "wof:placetype":"venue"
},
  "geometry": {"coordinates":[-0.934941,51.454617],"type":"Point"}
}