{
  "type": "Feature",
  "properties": {
    "iso:country":"GB",
    "sg:address":"Stortford Rd",
    "sg:city":"Dunmow",
    "sg:classifiers":[
        {
            "category":"Autos & Motor Vehicles",
            "subcategory":"Fuel & Gas Station",
            "type":"Retail Goods"
        }
    ],
    "sg:postcode":"CM6 1TA",
    "sg:province":"Essex",
    "sg:tags":[
        "petrol",
        "filling"
    ],
    "wof:name":"Canfield Service Station",
    "wof:placetype":"venue"
},
  "geometry": {"coordinates":[0.358995,51.873085],"type":"Point"}
}