{
  "type": "Feature",
  "properties": {
    "addr:full":"Unit 13b Moore Rd Broadstone Dorset BH18 8AZ",
    "addr:housenumber":"unit 13b",
    "addr:postcode":"bh18 8az",
    "addr:street":"Moore Rd",
    "iso:country":"GB",
    "sg:address":"Unit 13b Moore Rd",
    "sg:city":"Broadstone",
    "sg:classifiers":[
        {
            "category":"Professional",
            "type":"Services"
        }
    ],
    "sg:postcode":"BH18 8AZ",
    "sg:province":"Dorset",
    "sg:tags":[
        "repair",
        "tech",
        "maintenance"
    ],
    "wof:name":"My-Teck Computer Services",
    "wof:placetype":"venue"
},
  "geometry": {"coordinates":[-1.9898439646,50.7646598816],"type":"Point"}
}