{
  "type": "Feature",
  "properties": {
    "iso:country":"GB",
    "sg:address":"Devauden Grn",
    "sg:city":"Chepstow",
    "sg:classifiers":[
        {
            "category":"Home & Garden",
            "subcategory":"Kitchen Supply",
            "type":"Retail Goods"
        }
    ],
    "sg:phone":"+44 1291 650738",
    "sg:postcode":"NP16 6PL",
    "sg:province":"Gloucestershire",
    "sg:tags":[
        "ware"
    ],
    "wof:name":"Brass & Traditional Sinks Ltd.",
    "wof:placetype":"venue"
},
  "geometry": {"coordinates":[-2.748532,51.687435],"type":"Point"}
}