{
  "type": "Feature",
  "properties": {
    "iso:country":"GB",
    "sg:address":"Safeguard House, 29-31 Drake Street",
    "sg:city":"Rochdale",
    "sg:classifiers":[
        {
            "category":"Insurance",
            "subcategory":"Insurance Agent",
            "type":"Services"
        }
    ],
    "sg:phone":"+44 1706 656314",
    "sg:postcode":"OL16 1RX",
    "sg:province":"Lancashire",
    "wof:name":"Safeguard Investment & Insurance",
    "wof:placetype":"venue"
},
  "geometry": {"coordinates":[-2.1554689407,53.6164245605],"type":"Point"}
}