{
  "type": "Feature",
  "properties": {
    "addr:full":"165 Cambridge Road St Helens Merseyside WA10 4HA",
    "addr:housenumber":"165",
    "addr:postcode":"wa10 4ha",
    "addr:street":"Cambridge Road",
    "iso:country":"GB",
    "sg:address":"165 Cambridge Road",
    "sg:city":"St Helens",
    "sg:classifiers":[
        {
            "category":"Shopping",
            "subcategory":"Gifts & Souvenirs",
            "type":"Retail Goods"
        }
    ],
    "sg:phone":"+44 1744 28840",
    "sg:postcode":"WA10 4HA",
    "sg:province":"Merseyside",
    "sg:tags":[
        "poster",
        "card"
    ],
    "wof:name":"Pack of Cards",
    "wof:placetype":"venue"
},
  "geometry": {"coordinates":[-2.752684,53.453266],"type":"Point"}
}