{
  "type": "Feature",
  "properties": {
    "addr:full":"Unit 16 Brentnall St Middlesbrough North Yorkshire TS1 5AP",
    "addr:housenumber":"unit 16",
    "addr:postcode":"ts1 5ap",
    "addr:street":"Brentnall St",
    "iso:country":"GB",
    "sg:address":"Unit 16 Brentnall St",
    "sg:city":"Middlesbrough",
    "sg:classifiers":[
        {
            "category":"Professional",
            "subcategory":"Computer Services",
            "type":"Services"
        }
    ],
    "sg:phone":"+44 1642 242668",
    "sg:postcode":"TS1 5AP",
    "sg:province":"North Yorkshire",
    "sg:tags":[
        "system",
        "software"
    ],
    "wof:name":"Effective Solutions Ltd",
    "wof:placetype":"venue"
},
  "geometry": {"coordinates":[-1.2412140369,54.5754737854],"type":"Point"}
}