{
  "type": "Feature",
  "properties": {
    "addr:full":"69-71 Birmingham Rd West Bromwich West Midlands B70 6PY",
    "addr:housenumber":"69-71",
    "addr:postcode":"b70 6py",
    "addr:street":"Birmingham Rd West",
    "iso:country":"GB",
    "sg:address":"69-71 Birmingham Rd",
    "sg:city":"West Bromwich",
    "sg:classifiers":[
        {
            "category":"Real Estate",
            "subcategory":"Architect",
            "type":"Services"
        }
    ],
    "sg:phone":"+44 121 500 5800",
    "sg:postcode":"B70 6PY",
    "sg:province":"West Midlands",
    "wof:name":"Francis Associates",
    "wof:placetype":"venue"
},
  "geometry": {"coordinates":[-1.980842948,52.51222229],"type":"Point"}
}