{
  "type": "Feature",
  "properties": {
    "iso:country":"GB",
    "sg:address":"58 Camden Square",
    "sg:city":"London",
    "sg:classifiers":[
        {
            "category":"Professional",
            "subcategory":"Business Services",
            "type":"Services"
        },
        {
            "category":"Organizations",
            "subcategory":"Membership Organization",
            "type":"Services"
        }
    ],
    "sg:phone":"+44 20 7267 0882",
    "sg:postcode":"NW1 9XE",
    "sg:province":"Greater London",
    "sg:tags":[
        "distributor",
        "club",
        "film"
    ],
    "wof:name":"Harcourt Films Ltd.",
    "wof:placetype":"venue"
},
  "geometry": {"coordinates":[-0.1325940043,51.5437850952],"type":"Point"}
}