{
  "type": "Feature",
  "properties": {
    "addr:full":"26 Regent Parade Harrogate North Yorkshire HG1 5AZ",
    "addr:housenumber":"26",
    "addr:postcode":"hg1 5az",
    "addr:street":"Regent Parade",
    "iso:country":"GB",
    "sg:address":"26 Regent Parade",
    "sg:city":"Harrogate",
    "sg:classifiers":[
        {
            "category":"Shopping",
            "subcategory":"Florist",
            "type":"Retail Goods"
        }
    ],
    "sg:phone":"+44 1423 501877",
    "sg:postcode":"HG1 5AZ",
    "sg:province":"North Yorkshire",
    "wof:name":"Francis & Pam Hammett",
    "wof:placetype":"venue"
},
  "geometry": {"coordinates":[-1.529665,53.997799],"type":"Point"}
}