{
  "type": "Feature",
  "properties": {
    "addr:full":"Bag La Manchester Greater Manchester M46 0JY",
    "addr:postcode":"m46 0jy",
    "iso:country":"GB",
    "sg:address":"Bag La",
    "sg:city":"Manchester",
    "sg:classifiers":[
        {
            "category":"Social Services",
            "subcategory":"Retirement Home",
            "type":"Services"
        }
    ],
    "sg:phone":"+44 1942 878266",
    "sg:postcode":"M46 0JY",
    "sg:province":"Greater Manchester",
    "sg:tags":[
        "residential",
        "care"
    ],
    "wof:name":"C L S Homes Ltd",
    "wof:placetype":"venue"
},
  "geometry": {"coordinates":[-2.5014879704,53.5281257629],"type":"Point"}
}