{
  "type": "Feature",
  "properties": {
    "addr:full":"126 Westmount Road, Eltham London Greater London SE9 1UT",
    "addr:housenumber":"126",
    "addr:postcode":"se9 1ut",
    "addr:street":"Westmount Road",
    "iso:country":"GB",
    "sg:address":"126 Westmount Road, Eltham",
    "sg:city":"London",
    "sg:classifiers":[
        {
            "category":"Shopping",
            "subcategory":"Florist",
            "type":"Retail Goods"
        }
    ],
    "sg:phone":"+44 20 8859 5338",
    "sg:postcode":"SE9 1UT",
    "sg:province":"Greater London",
    "wof:name":"Westmount Flowers",
    "wof:placetype":"venue"
},
  "geometry": {"coordinates":[0.05898,51.457409],"type":"Point"}
}