{
  "type": "Feature",
  "properties": {
    "addr:full":"8 Barn Rd Carmarthen Carmarthenshire SA31 1DE",
    "addr:housenumber":"8",
    "addr:postcode":"sa31 1de",
    "addr:street":"Barn Rd",
    "iso:country":"GB",
    "sg:address":"8 Barn Rd",
    "sg:city":"Carmarthen",
    "sg:classifiers":[
        {
            "category":"Home & Garden",
            "subcategory":"Household Appliances",
            "type":"Retail Goods"
        }
    ],
    "sg:postcode":"SA31 1DE",
    "sg:province":"Carmarthenshire",
    "sg:tags":[
        "cleaner",
        "domestic",
        "vacuum"
    ],
    "wof:name":"Myrddin Home Care Ltd",
    "wof:placetype":"venue"
},
  "geometry": {"coordinates":[-4.3079910278,51.858669281],"type":"Point"}
}