{
  "type": "Feature",
  "properties": {
    "addr:full":"10 Bellmaine Avenue, Corringham Stanford-le-hope Essex SS17 7TB",
    "addr:housenumber":"10",
    "addr:postcode":"ss17 7tb",
    "addr:street":"Bellmaine Avenue",
    "iso:country":"GB",
    "sg:address":"10 Bellmaine Avenue, Corringham",
    "sg:city":"Stanford-le-hope",
    "sg:classifiers":[
        {
            "category":"Health Services",
            "subcategory":"Health Practitioner",
            "type":"Services"
        }
    ],
    "sg:phone":"+44 1375 678810",
    "sg:postcode":"SS17 7TB",
    "sg:province":"Essex",
    "sg:tags":[
        "hypnotherapists"
    ],
    "wof:name":"Susan Jones",
    "wof:placetype":"venue"
},
  "geometry": {"coordinates":[0.445881,51.527809],"type":"Point"}
}