{
  "type": "Feature",
  "properties": {
    "addr:full":"5 Arnhem Road Bognor Regis West Sussex PO21 5LB",
    "addr:housenumber":"5",
    "addr:postcode":"po21 5lb",
    "addr:street":"Arnhem Road",
    "iso:country":"GB",
    "sg:address":"5 Arnhem Road",
    "sg:city":"Bognor Regis",
    "sg:classifiers":[
        {
            "category":"Personal",
            "type":"Services"
        }
    ],
    "sg:phone":"+44 1243 823105",
    "sg:postcode":"PO21 5LB",
    "sg:province":"West Sussex",
    "sg:tags":[
        "wedding"
    ],
    "wof:name":"Photography by Dennis Mann",
    "wof:placetype":"venue"
},
  "geometry": {"coordinates":[-0.6860970259,50.7947731018],"type":"Point"}
}