{
  "type": "Feature",
  "properties": {
    "addr:full":"16 Burchfield, Fatfield Washington Durham NE38 8SW",
    "addr:housenumber":"16",
    "addr:postcode":"ne38 8sw",
    "addr:street":"Burchfield Fatfield",
    "iso:country":"GB",
    "sg:address":"16 Burchfield, Fatfield",
    "sg:city":"Washington",
    "sg:classifiers":[
        {
            "category":"Shopping",
            "subcategory":"News",
            "type":"Retail Goods"
        }
    ],
    "sg:phone":"+44 191 417 0528",
    "sg:postcode":"NE38 8SW",
    "sg:province":"Durham",
    "sg:tags":[
        "newsagent"
    ],
    "wof:name":"M & E Edwards",
    "wof:placetype":"venue"
},
  "geometry": {"coordinates":[-1.502128005,54.8897743225],"type":"Point"}
}