{
  "type": "Feature",
  "properties": {
    "iso:country":"GB",
    "sg:address":"43 Russell St",
    "sg:city":"Salisbury",
    "sg:classifiers":[
        {
            "category":"Government",
            "subcategory":"Police Station",
            "type":"Public Place"
        }
    ],
    "sg:phone":"+44 1722 742101",
    "sg:postcode":"SP2 0BG",
    "sg:province":"Wiltshire",
    "sg:tags":[
        "support"
    ],
    "wof:name":"Wiltshire Constabulary",
    "wof:placetype":"venue"
},
  "geometry": {"coordinates":[-1.8611949682,51.0797271729],"type":"Point"}
}