{
  "type": "Feature",
  "properties": {
    "iso:country":"GB",
    "sg:address":"Glenkingie Street, Caol",
    "sg:city":"Fort William",
    "sg:classifiers":[
        {
            "category":"Social Services",
            "type":"Services"
        },
        {
            "category":"Community Center",
            "type":"Public Place"
        }
    ],
    "sg:phone":"+44 1397 708476",
    "sg:postcode":"PH33 7DS",
    "sg:province":"Highland",
    "sg:tags":[
        "ds",
        "centre"
    ],
    "wof:name":"Caol Community Centre",
    "wof:placetype":"venue"
},
  "geometry": {"coordinates":[-5.108208,56.839905],"type":"Point"}
}