{
  "type": "Feature",
  "properties": {
    "addr:full":"Mill Street Ulverston Cumbria LA12 7EB",
    "addr:postcode":"la12 7eb",
    "addr:street":"Mill Street",
    "iso:country":"GB",
    "sg:address":"Mill Street",
    "sg:city":"Ulverston",
    "sg:classifiers":[
        {
            "category":"Place Of Worship",
            "type":"Public Place"
        }
    ],
    "sg:phone":"+44 1229 586136",
    "sg:postcode":"LA12 7EB",
    "sg:province":"Cumbria",
    "wof:name":"Emmanuel Christian Centre",
    "wof:placetype":"venue"
},
  "geometry": {"coordinates":[-3.096139,54.197174],"type":"Point"}
}