{
  "type": "Feature",
  "properties": {
    "addr:full":"20 Cowley Lane, Gnosall Stafford Staffordshire ST20 0DS",
    "addr:housenumber":"20",
    "addr:postcode":"st20 0ds",
    "addr:street":"Cowley Lane",
    "iso:country":"GB",
    "sg:address":"20 Cowley Lane, Gnosall",
    "sg:city":"Stafford",
    "sg:classifiers":[
        {
            "category":"Building & Trades",
            "subcategory":"Construction",
            "type":"Services"
        }
    ],
    "sg:postcode":"ST20 0DS",
    "sg:province":"Staffordshire",
    "sg:tags":[
        "roofing"
    ],
    "wof:name":"Hipower Electrical Ltd",
    "wof:placetype":"venue"
},
  "geometry": {"coordinates":[-2.2582280636,52.7800865173],"type":"Point"}
}