{
  "type": "Feature",
  "properties": {
    "addr:full":"Stewards Yard, Wakering Rd Southend On Sea Essex SS3 9TR",
    "addr:postcode":"ss3 9tr",
    "addr:street":"Wakering Rd",
    "iso:country":"GB",
    "sg:address":"Stewards Yard, Wakering Rd",
    "sg:city":"Southend On Sea",
    "sg:classifiers":[
        {
            "category":"Building & Trades",
            "subcategory":"Landscaping Services",
            "type":"Services"
        }
    ],
    "sg:phone":"+44 1702 216766",
    "sg:postcode":"SS3 9TR",
    "sg:province":"Essex",
    "sg:tags":[
        "forestry",
        "tree"
    ],
    "wof:name":"Jonathan Steward",
    "wof:placetype":"venue"
},
  "geometry": {"coordinates":[0.80518,51.5429],"type":"Point"}
}