{
  "type": "Feature",
  "properties": {
    "addr:full":"4 Ednam Road Dudley West Midlands DY1 1HL",
    "addr:housenumber":"4",
    "addr:postcode":"dy1 1hl",
    "addr:street":"Ednam Road",
    "iso:country":"GB",
    "sg:address":"4 Ednam Road",
    "sg:city":"Dudley",
    "sg:classifiers":[
        {
            "category":"Professional",
            "type":"Services"
        },
        {
            "category":"Government",
            "subcategory":"Office",
            "type":"Public Place"
        }
    ],
    "sg:phone":"+44 1384 815261",
    "sg:postcode":"DY1 1HL",
    "sg:province":"West Midlands",
    "sg:tags":[
        "local",
        "caterer"
    ],
    "wof:name":"Civic Cuisine",
    "wof:placetype":"venue"
},
  "geometry": {"coordinates":[-2.0848400593,52.512512207],"type":"Point"}
}