{
  "type": "Feature",
  "properties": {
    "iso:country":"GB",
    "sg:address":"88b Cavendish Road",
    "sg:city":"London",
    "sg:classifiers":[
        {
            "category":"Place Of Worship",
            "type":"Public Place"
        },
        {
            "category":"Organizations",
            "subcategory":"Non-profit Organization",
            "type":"Services"
        }
    ],
    "sg:phone":"+44 20 8341 7496",
    "sg:postcode":"N4 1RS",
    "sg:province":"Greater London",
    "sg:tags":[
        "charitable",
        "organisation",
        "charity"
    ],
    "wof:name":"HARINGEY SEVENTH DAY ADVENTIST CHURCH",
    "wof:placetype":"venue"
},
  "geometry": {"coordinates":[-0.099619,51.578629],"type":"Point"}
}