{
  "type": "Feature",
  "properties": {
    "addr:full":"Fosse Way Industrial Estate, Stratford Road Moreton-in-marsh Gloucestershire GL56 9NQ",
    "addr:housenumber":"estate",
    "addr:postcode":"gl56 9nq",
    "addr:street":"Fosse Way Industrial;Stratford Road",
    "iso:country":"GB",
    "sg:address":"Fosse Way Industrial Estate, Stratford Road",
    "sg:city":"Moreton-in-marsh",
    "sg:classifiers":[
        {
            "category":"Professional",
            "subcategory":"Engineering",
            "type":"Services"
        }
    ],
    "sg:phone":"+44 1608 652893",
    "sg:postcode":"GL56 9NQ",
    "sg:province":"Gloucestershire",
    "sg:tags":[
        "consulting",
        "engineer"
    ],
    "wof:name":"Forest Movement Europe",
    "wof:placetype":"venue"
},
  "geometry": {"coordinates":[-1.703281,51.989727],"type":"Point"}
}