{
  "type": "Feature",
  "properties": {
    "addr:full":"18 Quarry Hill Godalming Surrey GU7 2NW",
    "addr:housenumber":"18",
    "addr:postcode":"gu7 2nw",
    "addr:street":"Quarry Hill",
    "iso:country":"GB",
    "sg:address":"18 Quarry Hill",
    "sg:city":"Godalming",
    "sg:classifiers":[
        {
            "category":"Bars & Pubs",
            "type":"Food & Drink"
        }
    ],
    "sg:phone":"+44 1483 421467",
    "sg:postcode":"GU7 2NW",
    "sg:province":"Surrey",
    "sg:tags":[
        "pubs",
        "inn"
    ],
    "wof:name":"King Alfred",
    "wof:placetype":"venue"
},
  "geometry": {"coordinates":[-0.630214,51.180569],"type":"Point"}
}