{
  "type": "Feature",
  "properties": {
    "addr:full":"Yarnton Nurseries, Sandy Lane, Yarnton Kidlington Buckinghamshire OX5 1PA",
    "addr:postcode":"ox5 1pa",
    "addr:street":"Sandy Lane",
    "iso:country":"GB",
    "sg:address":"Yarnton Nurseries, Sandy Lane, Yarnton",
    "sg:city":"Kidlington",
    "sg:classifiers":[
        {
            "category":"Shopping",
            "subcategory":"Florist",
            "type":"Retail Goods"
        }
    ],
    "sg:postcode":"OX5 1PA",
    "sg:province":"Buckinghamshire",
    "wof:name":"Anemone",
    "wof:placetype":"venue"
},
  "geometry": {"coordinates":[-1.309754,51.809246],"type":"Point"}
}