{
  "type": "Feature",
  "properties": {
    "addr:full":"Upper A Milburn House Dean Street Newcastle-upon-tyne Tyne and Wear NE1 1LF",
    "addr:postcode":"ne1 1lf",
    "addr:street":"Upper A Milburn House Dean Street",
    "iso:country":"GB",
    "sg:address":"Upper A Milburn House Dean Street",
    "sg:city":"Newcastle-upon-tyne",
    "sg:classifiers":[
        {
            "category":"Arts & Performance",
            "subcategory":"Theater",
            "type":"Entertainment"
        }
    ],
    "sg:phone":"+44 191 221 2490",
    "sg:postcode":"NE1 1LF",
    "sg:province":"Tyne and Wear",
    "sg:tags":[
        "theatrical",
        "agency"
    ],
    "wof:name":"Janet Plater Management Ltd.",
    "wof:placetype":"venue"
},
  "geometry": {"coordinates":[-1.6099560261,54.9703674316],"type":"Point"}
}