{
  "type": "Feature",
  "properties": {
    "addr:full":"Laroch, Post Office Lane, North Mundham Chichester West Sussex PO20 1JY",
    "addr:postcode":"po20 1jy",
    "addr:street":"Office Lane",
    "iso:country":"GB",
    "sg:address":"Laroch, Post Office Lane, North Mundham",
    "sg:city":"Chichester",
    "sg:classifiers":[
        {
            "category":"Professional",
            "subcategory":"Detective & Security Services",
            "type":"Services"
        }
    ],
    "sg:phone":"+44 1243 778383",
    "sg:postcode":"PO20 1JY",
    "sg:province":"West Sussex",
    "sg:tags":[
        "alarm",
        "burglar",
        "system"
    ],
    "wof:name":"Alarms Protection & Communications Ltd.",
    "wof:placetype":"venue"
},
  "geometry": {"coordinates":[-0.762443,50.81419],"type":"Point"}
}