{
  "type": "Feature",
  "properties": {
    "addr:full":"3 Selborne Close Petersfield Hampshire GU32 2JB",
    "addr:housenumber":"3",
    "addr:postcode":"gu32 2jb",
    "addr:street":"Selborne Close",
    "iso:country":"GB",
    "sg:address":"3 Selborne Close",
    "sg:city":"Petersfield",
    "sg:classifiers":[
        {
            "category":"Health Services",
            "subcategory":"Health Practitioner",
            "type":"Services"
        }
    ],
    "sg:phone":"+44 1730 261256",
    "sg:postcode":"GU32 2JB",
    "sg:province":"Hampshire",
    "sg:tags":[
        "physiotherapist"
    ],
    "wof:name":"Naomi Elia",
    "wof:placetype":"venue"
},
  "geometry": {"coordinates":[-0.9313989878,51.0133285522],"type":"Point"}
}