{
  "type": "Feature",
  "properties": {
    "iso:country":"GB",
    "sg:address":"71 Helix Rd",
    "sg:city":"London",
    "sg:classifiers":[
        {
            "category":"Professional",
            "subcategory":"Printing & Photocopies",
            "type":"Services"
        }
    ],
    "sg:phone":"+44 20 8671 8886",
    "sg:postcode":"SW2 2JR",
    "sg:province":"Greater London",
    "sg:tags":[
        "duplicating",
        "copying"
    ],
    "wof:name":"City Copier Services Ltd",
    "wof:placetype":"venue"
},
  "geometry": {"coordinates":[-0.1162350029,51.4523658752],"type":"Point"}
}