{
  "type": "Feature",
  "properties": {
    "iso:country":"GB",
    "sg:address":"Canal Bank",
    "sg:city":"Scunthorpe",
    "sg:classifiers":[
        {
            "category":"Social Services",
            "subcategory":"Job Training",
            "type":"Services"
        }
    ],
    "sg:phone":"+44 1724 782302",
    "sg:postcode":"DN17 3ED",
    "sg:province":"Lincolnshire",
    "sg:tags":[
        "engineering",
        "marine"
    ],
    "wof:name":"Keadby Marine Engineering Co",
    "wof:placetype":"venue"
},
  "geometry": {"coordinates":[-0.751148,53.575935],"type":"Point"}
}