{
  "type": "Feature",
  "properties": {
    "addr:full":"12 Upper Northgate Street Chester Cheshire CH1 4EE",
    "addr:housenumber":"12",
    "addr:postcode":"ch1 4ee",
    "addr:street":"Upper Northgate Street",
    "iso:country":"GB",
    "sg:address":"12 Upper Northgate Street",
    "sg:city":"Chester",
    "sg:classifiers":[
        {
            "category":"Shopping",
            "subcategory":"Pharmacy",
            "type":"Retail Goods"
        }
    ],
    "sg:phone":"+44 1244 379268",
    "sg:postcode":"CH1 4EE",
    "sg:province":"Cheshire",
    "sg:tags":[
        "pharmacist",
        "chemist"
    ],
    "wof:name":"Royal House Late Night Pharmacy",
    "wof:placetype":"venue"
},
  "geometry": {"coordinates":[-2.893393,53.194565],"type":"Point"}
}