{
  "type": "Feature",
  "properties": {
    "addr:full":"Dottery Bridport Dorset DT6 5HR",
    "addr:postcode":"dt6 5hr",
    "iso:country":"GB",
    "sg:address":"Dottery",
    "sg:city":"Bridport",
    "sg:classifiers":[
        {
            "category":"Farming",
            "subcategory":"Livestock Farm",
            "type":"Manufacturing & Wholesale Goods"
        }
    ],
    "sg:phone":"+44 1308 867474",
    "sg:postcode":"DT6 5HR",
    "sg:province":"Dorset",
    "sg:tags":[
        "others"
    ],
    "wof:name":"C G Rabbetts",
    "wof:placetype":"venue"
},
  "geometry": {"coordinates":[-2.7699000835,50.7499313354],"type":"Point"}
}