{
  "type": "Feature",
  "properties": {
    "addr:full":"Greville Ho, High St Solihull Warwickshire B93 0LN",
    "addr:postcode":"b93 0ln",
    "addr:street":"High St",
    "iso:country":"GB",
    "sg:address":"Greville Ho, High St",
    "sg:city":"Solihull",
    "sg:classifiers":[
        {
            "category":"Utilities",
            "type":"Services"
        }
    ],
    "sg:phone":"+44 121 745 5055",
    "sg:postcode":"B93 0LN",
    "sg:province":"Warwickshire",
    "sg:tags":[
        "internet"
    ],
    "wof:name":"WWW Dot",
    "wof:placetype":"venue"
},
  "geometry": {"coordinates":[-1.7347099781,52.3889312744],"type":"Point"}
}