{
  "type": "Feature",
  "properties": {
    "iso:country":"GB",
    "sg:address":"Basing View",
    "sg:city":"Basingstoke",
    "sg:classifiers":[
        {
            "category":"Banks & Credit Unions",
            "subcategory":"Financial Services",
            "type":"Services"
        }
    ],
    "sg:phone":"+44 1256 841414",
    "sg:postcode":"RG21 4DZ",
    "sg:province":"Hampshire",
    "sg:tags":[
        "consultant"
    ],
    "wof:name":"Sun Life of Canada Nominees Ltd.",
    "wof:placetype":"venue"
},
  "geometry": {"coordinates":[-1.073542,51.268841],"type":"Point"}
}