{
  "type": "Feature",
  "properties": {
    "addr:full":"West Mead, 4 Tavistock Rd Notting Hill Greater London W11 1BA",
    "addr:housenumber":"4",
    "addr:postcode":"w11 1ba",
    "addr:street":"West Mead;Tavistock Rd",
    "iso:country":"GB",
    "sg:address":"West Mead, 4 Tavistock Rd",
    "sg:city":"Notting Hill",
    "sg:classifiers":[
        {
            "category":"Social Services",
            "type":"Services"
        }
    ],
    "sg:phone":"+44 20 7641 4561",
    "sg:postcode":"W11 1BA",
    "sg:province":"Greater London",
    "wof:name":"Peddington Personal Care Services",
    "wof:placetype":"venue"
},
  "geometry": {"coordinates":[-0.2014199942,51.5202598572],"type":"Point"}
}