{
  "type": "Feature",
  "properties": {
    "iso:country":"GB",
    "sg:address":"10 Chesilton Road",
    "sg:city":"Fulham",
    "sg:classifiers":[
        {
            "category":"Professional",
            "subcategory":"Accounting & Tax Preparation",
            "type":"Services"
        }
    ],
    "sg:postcode":"SW6 5AB",
    "sg:province":"Greater London",
    "sg:tags":[
        "accountant"
    ],
    "wof:name":"Nelson Corporation Ltd",
    "wof:placetype":"venue"
},
  "geometry": {"coordinates":[-0.206283,51.476101],"type":"Point"}
}