{
  "type": "Feature",
  "properties": {
    "iso:country":"GB",
    "sg:address":"149 Tiverton Street",
    "sg:city":"Cleethorpes",
    "sg:classifiers":[
        {
            "category":"Recreation",
            "subcategory":"Fishing",
            "type":"Entertainment"
        }
    ],
    "sg:phone":"+44 1472 695050",
    "sg:postcode":"DN35 7EF",
    "sg:province":"Lincolnshire",
    "sg:tags":[
        "angling"
    ],
    "wof:name":"Tiverton Street Fisheries",
    "wof:placetype":"venue"
},
  "geometry": {"coordinates":[-0.051285,53.568031],"type":"Point"}
}