{
  "type": "Feature",
  "properties": {
    "addr:full":"2 Young Street Inverness Highland IV3 5BL",
    "addr:housenumber":"2",
    "addr:postcode":"iv3 5bl",
    "addr:street":"Young Street",
    "iso:country":"GB",
    "sg:address":"2 Young Street",
    "sg:city":"Inverness",
    "sg:classifiers":[
        {
            "category":"Bars & Pubs",
            "type":"Food & Drink"
        },
        {
            "category":"Community Center",
            "subcategory":"Social",
            "type":"Public Place"
        }
    ],
    "sg:phone":"+44 1463 231637",
    "sg:postcode":"IV3 5BL",
    "sg:province":"Highland",
    "sg:tags":[
        "pubs",
        "house",
        "inn",
        "activity"
    ],
    "wof:name":"Glenalbyn Bar",
    "wof:placetype":"venue"
},
  "geometry": {"coordinates":[-4.2283592224,57.4767990112],"type":"Point"}
}