{
  "type": "Feature",
  "properties": {
    "addr:full":"36 Meadow La, Cononley Keighley North Yorkshire BD20 8NB",
    "addr:housenumber":"36",
    "addr:postcode":"bd20 8nb",
    "addr:street":"Meadow La Cononley",
    "iso:country":"GB",
    "sg:address":"36 Meadow La, Cononley",
    "sg:city":"Keighley",
    "sg:classifiers":[
        {
            "category":"Social Services",
            "subcategory":"Adult Care",
            "type":"Services"
        }
    ],
    "sg:postcode":"BD20 8NB",
    "sg:province":"North Yorkshire",
    "sg:tags":[
        "housing",
        "sheltered"
    ],
    "wof:name":"Meadow Lane Sheltered Housing",
    "wof:placetype":"venue"
},
  "geometry": {"coordinates":[-2.018643,53.919605],"type":"Point"}
}