{
  "type": "Feature",
  "properties": {
    "addr:full":"30 Beechwood Avenue Wakefield West Yorkshire WF2 9JZ",
    "addr:housenumber":"30",
    "addr:postcode":"wf2 9jz",
    "addr:street":"Beechwood Avenue",
    "iso:country":"GB",
    "sg:address":"30 Beechwood Avenue",
    "sg:city":"Wakefield",
    "sg:classifiers":[
        {
            "category":"Professional",
            "subcategory":"Management & Consulting",
            "type":"Services"
        }
    ],
    "sg:phone":"+44 1924 386615",
    "sg:postcode":"WF2 9JZ",
    "sg:province":"West Yorkshire",
    "sg:tags":[
        "consultant",
        "investigation",
        "site"
    ],
    "wof:name":"M.D Atkinson",
    "wof:placetype":"venue"
},
  "geometry": {"coordinates":[-1.532572,53.681541],"type":"Point"}
}