{
  "type": "Feature",
  "properties": {
    "iso:country":"GB",
    "sg:address":"15 Woodgate, Rothley",
    "sg:city":"Leicester",
    "sg:classifiers":[
        {
            "category":"Banks & Credit Unions",
            "subcategory":"Bank",
            "type":"Services"
        }
    ],
    "sg:postcode":"LE7 7LL",
    "sg:province":"Leicestershire",
    "sg:tags":[
        "broker",
        "mortgage"
    ],
    "wof:name":"M & P Financial Consultants Llp",
    "wof:placetype":"venue"
},
  "geometry": {"coordinates":[-1.1382360458,52.7092132568],"type":"Point"}
}