{
  "type": "Feature",
  "properties": {
    "addr:full":"Craven Walk London Greater London N16 6BL",
    "addr:postcode":"n16 6bl",
    "addr:street":"Craven Walk",
    "iso:country":"GB",
    "sg:address":"Craven Walk",
    "sg:city":"London",
    "sg:classifiers":[
        {
            "category":"Food & Beverages",
            "subcategory":"Meat & Fish",
            "type":"Retail Goods"
        }
    ],
    "sg:phone":"+44 20 8880 1112",
    "sg:postcode":"N16 6BL",
    "sg:province":"Greater London",
    "sg:tags":[
        "butcher"
    ],
    "wof:name":"Mehadrin Meat",
    "wof:placetype":"venue"
},
  "geometry": {"coordinates":[-0.060679,51.57515],"type":"Point"}
}