{
  "type": "Feature",
  "properties": {
    "iso:country":"GB",
    "sg:address":"Unit 10, Shield Road",
    "sg:city":"Ashford",
    "sg:classifiers":[
        {
            "category":"Government",
            "subcategory":"Post Office",
            "type":"Public Place"
        }
    ],
    "sg:phone":"+44 1784 420466",
    "sg:postcode":"TW15 1AU",
    "sg:province":"Greater London",
    "sg:tags":[
        "messenger",
        "courier"
    ],
    "wof:name":"P D P Courier Services Ltd.",
    "wof:placetype":"venue"
},
  "geometry": {"coordinates":[-0.442529,51.435535],"type":"Point"}
}