{
  "type": "Feature",
  "properties": {
    "iso:country":"GB",
    "sg:address":"Reema Road",
    "sg:city":"Bellshill",
    "sg:classifiers":[
        {
            "category":"Building & Trades",
            "subcategory":"Construction",
            "type":"Services"
        }
    ],
    "sg:phone":"+44 1698 503503",
    "sg:postcode":"ML4 1RT",
    "sg:province":"North Lanarkshire",
    "sg:tags":[
        "contractor"
    ],
    "wof:name":"Balfour Beatty Construction",
    "wof:placetype":"venue"
},
  "geometry": {"coordinates":[-4.0183539391,55.8221893311],"type":"Point"}
}