{
  "type": "Feature",
  "properties": {
    "addr:full":"Second Floor, Allied Dunbar House, 1 Meadow Road Tunbridge Wells Kent TN1 2YG",
    "addr:housenumber":"second;1",
    "addr:postcode":"tn1 2yg",
    "addr:street":"Meadow Road",
    "iso:country":"GB",
    "sg:address":"Second Floor, Allied Dunbar House, 1 Meadow Road",
    "sg:city":"Tunbridge Wells",
    "sg:classifiers":[
        {
            "category":"Banks & Credit Unions",
            "subcategory":"Investment Brokerage",
            "type":"Services"
        }
    ],
    "sg:phone":"+44 1892 523346",
    "sg:postcode":"TN1 2YG",
    "sg:province":"Kent",
    "sg:tags":[
        "stockbroker"
    ],
    "wof:name":"Lawshare Ltd.",
    "wof:placetype":"venue"
},
  "geometry": {"coordinates":[0.2642680109,51.1359596252],"type":"Point"}
}