{
  "type": "Feature",
  "properties": {
    "iso:country":"GB",
    "sg:address":"2a Branksome Hill Road, College Town",
    "sg:city":"Camberley",
    "sg:classifiers":[
        {
            "category":"Retail",
            "subcategory":"Auto Repair",
            "type":"Services"
        }
    ],
    "sg:phone":"+44 1276 600140",
    "sg:postcode":"GU15 4QE",
    "sg:province":"Berkshire",
    "sg:tags":[
        "body",
        "car"
    ],
    "wof:name":"S & J Motors",
    "wof:placetype":"venue"
},
  "geometry": {"coordinates":[-0.74417,51.352692],"type":"Point"}
}