{
  "type": "Feature",
  "properties": {
    "addr:full":"Cairndhu House, Rhu Road Lower Helensburgh Argyll and Bute G84 8PL",
    "addr:postcode":"g84 8pl",
    "addr:street":"Rhu Road Lower Helensburgh",
    "iso:country":"GB",
    "sg:address":"Cairndhu House, Rhu Road Lower",
    "sg:city":"Helensburgh",
    "sg:classifiers":[
        {
            "category":"Health Services",
            "subcategory":"Nursing And Care Facility",
            "type":"Services"
        }
    ],
    "sg:phone":"+44 1436 679230",
    "sg:postcode":"G84 8PL",
    "sg:province":"Argyll and Bute",
    "sg:tags":[
        "home"
    ],
    "wof:name":"Cairndhu House Ltd.",
    "wof:placetype":"venue"
},
  "geometry": {"coordinates":[-4.732149,56.006584],"type":"Point"}
}