{
  "type": "Feature",
  "properties": {
    "iso:country":"GB",
    "sg:address":"Central Chambers 227 London Road, Hadleigh",
    "sg:city":"Benfleet",
    "sg:classifiers":[
        {
            "category":"Professional",
            "subcategory":"Lawyer & Legal Services",
            "type":"Services"
        }
    ],
    "sg:phone":"+44 1702 558286",
    "sg:postcode":"SS7 2RF",
    "sg:province":"Essex",
    "sg:tags":[
        "solicitor"
    ],
    "wof:name":"Andrew Hurrell",
    "wof:placetype":"venue"
},
  "geometry": {"coordinates":[0.6140750051,51.5513114929],"type":"Point"}
}