{
  "type": "Feature",
  "properties": {
    "addr:full":"Unit 4, Hattersley Industrial Estate, Stockport Road Hyde Cheshire SK14 3QJ",
    "addr:housenumber":"unit 4",
    "addr:postcode":"sk14 3qj",
    "addr:street":"Hattersley Industrial Estate Stockport Road",
    "iso:country":"GB",
    "sg:address":"Unit 4, Hattersley Industrial Estate, Stockport Road",
    "sg:city":"Hyde",
    "sg:classifiers":[
        {
            "category":"Home & Garden",
            "subcategory":"Carpets & Floor Coverings",
            "type":"Retail Goods"
        }
    ],
    "sg:phone":"+44 161 368 9755",
    "sg:postcode":"SK14 3QJ",
    "sg:province":"Cheshire",
    "sg:tags":[
        "rubber",
        "plastic"
    ],
    "wof:name":"John & Lorraine Elliott",
    "wof:placetype":"venue"
},
  "geometry": {"coordinates":[-2.031126976,53.4441261292],"type":"Point"}
}