{
  "type": "Feature",
  "properties": {
    "addr:full":"Brookside, East Hanney Wantage Berkshire OX12 0JL",
    "addr:postcode":"ox12 0jl",
    "addr:street":"Brookside East",
    "iso:country":"GB",
    "sg:address":"Brookside, East Hanney",
    "sg:city":"Wantage",
    "sg:classifiers":[
        {
            "category":"Government",
            "subcategory":"City Hall",
            "type":"Public Place"
        },
        {
            "category":"Real Estate",
            "subcategory":"Real Estate Operator",
            "type":"Services"
        }
    ],
    "sg:phone":"+44 1235 868502",
    "sg:postcode":"OX12 0JL",
    "sg:province":"Berkshire",
    "sg:tags":[
        "property",
        "leasing"
    ],
    "wof:name":"HANNEY WAR MEMORIAL HALL",
    "wof:placetype":"venue"
},
  "geometry": {"coordinates":[-1.397185,51.631672],"type":"Point"}
}