{
  "type": "Feature",
  "properties": {
    "iso:country":"GB",
    "sg:address":"233 Queensway, Bletchley",
    "sg:city":"Milton Keynes",
    "sg:classifiers":[
        {
            "category":"Shopping",
            "subcategory":"Optician",
            "type":"Retail Goods"
        }
    ],
    "sg:phone":"+44 1908 366882",
    "sg:postcode":"MK2 2EH",
    "sg:province":"Buckinghamshire",
    "sg:tags":[
        "dispensing"
    ],
    "wof:name":"Contact Lens Clinic",
    "wof:placetype":"venue"
},
  "geometry": {"coordinates":[-0.7231040001,51.9961700439],"type":"Point"}
}