{
  "type": "Feature",
  "properties": {
    "addr:full":"The Green, Clifton Manchester Greater Manchester M27 8QL",
    "addr:postcode":"m27 8ql",
    "addr:street":"Green",
    "iso:country":"GB",
    "sg:address":"The Green, Clifton",
    "sg:city":"Manchester",
    "sg:classifiers":[
        {
            "category":"Community Center",
            "subcategory":"Youth",
            "type":"Public Place"
        }
    ],
    "sg:phone":"+44 161 794 4321",
    "sg:postcode":"M27 8QL",
    "sg:province":"Greater Manchester",
    "sg:tags":[
        "organisation",
        "centre"
    ],
    "wof:name":"Clifton Youth Centre",
    "wof:placetype":"venue"
},
  "geometry": {"coordinates":[-2.322852,53.520798],"type":"Point"}
}