{
  "type": "Feature",
  "properties": {
    "addr:full":"4 Lind Road Sutton Surrey SM1 4PJ",
    "addr:housenumber":"4",
    "addr:postcode":"sm1 4pj",
    "addr:street":"Lind Road",
    "iso:country":"GB",
    "sg:address":"4 Lind Road",
    "sg:city":"Sutton",
    "sg:classifiers":[
        {
            "category":"Building & Trades",
            "subcategory":"Cleaning & Sanitation",
            "type":"Services"
        },
        {
            "category":"Social Services",
            "subcategory":"Adult Care",
            "type":"Services"
        }
    ],
    "sg:phone":"+44 20 8661 7717",
    "sg:postcode":"SM1 4PJ",
    "sg:province":"Surrey",
    "sg:tags":[
        "contracting",
        "domestic"
    ],
    "wof:name":"The Maids",
    "wof:placetype":"venue"
},
  "geometry": {"coordinates":[-0.185108,51.363094],"type":"Point"}
}