{
  "type": "Feature",
  "properties": {
    "iso:country":"GB",
    "sg:address":"2 Beech Farm Drive, Coopers Green Lane",
    "sg:city":"St Albans",
    "sg:classifiers":[
        {
            "category":"Building & Trades",
            "subcategory":"Construction",
            "type":"Services"
        }
    ],
    "sg:postcode":"AL4 9HW",
    "sg:province":"Hertfordshire",
    "sg:tags":[
        "joiner",
        "carpenter"
    ],
    "wof:name":"Norman Day",
    "wof:placetype":"venue"
},
  "geometry": {"coordinates":[-0.27869,51.767242],"type":"Point"}
}