{
  "type": "Feature",
  "properties": {
    "addr:full":"Grovenor House, Central Park Telford Shropshire TF2 9TW",
    "addr:postcode":"tf2 9tw",
    "iso:country":"GB",
    "sg:address":"Grovenor House, Central Park",
    "sg:city":"Telford",
    "sg:classifiers":[
        {
            "category":"Real Estate",
            "subcategory":"Surveying",
            "type":"Services"
        }
    ],
    "sg:phone":"+44 1952 521000",
    "sg:postcode":"TF2 9TW",
    "sg:province":"Shropshire",
    "sg:tags":[
        "surveyor",
        "valuer"
    ],
    "wof:name":"Andrew Dixon Estate Agents Ltd.",
    "wof:placetype":"venue"
},
  "geometry": {"coordinates":[-2.4447820187,52.6783981323],"type":"Point"}
}