{
  "type": "Feature",
  "properties": {
    "addr:full":"41 Fambridge Drive Wickford Essex SS12 9HR",
    "addr:housenumber":"41",
    "addr:postcode":"ss12 9hr",
    "addr:street":"Fambridge Drive",
    "iso:country":"GB",
    "sg:address":"41 Fambridge Drive",
    "sg:city":"Wickford",
    "sg:classifiers":[
        {
            "category":"Freight",
            "type":"Transportation"
        }
    ],
    "sg:phone":"+44 1268 560492",
    "sg:postcode":"SS12 9HR",
    "sg:province":"Essex",
    "sg:tags":[
        "haulage",
        "road"
    ],
    "wof:name":"Stevens Transport",
    "wof:placetype":"venue"
},
  "geometry": {"coordinates":[0.5280399919,51.605758667],"type":"Point"}
}