{
  "type": "Feature",
  "properties": {
    "addr:full":"74 Pensby Rd Wirral Merseyside CH60 7RE",
    "addr:housenumber":"74",
    "addr:postcode":"ch60 7re",
    "addr:street":"Pensby Rd",
    "iso:country":"GB",
    "sg:address":"74 Pensby Rd",
    "sg:city":"Wirral",
    "sg:classifiers":[
        {
            "category":"Shopping",
            "subcategory":"Optician",
            "type":"Retail Goods"
        }
    ],
    "sg:phone":"+44 151 342 6179",
    "sg:postcode":"CH60 7RE",
    "sg:province":"Merseyside",
    "wof:name":"Focus Optical Services",
    "wof:placetype":"venue"
},
  "geometry": {"coordinates":[-3.097542,53.330338],"type":"Point"}
}