{
  "type": "Feature",
  "properties": {
    "addr:full":"69 The Acorn Centre, Barry St Oldham Lancashire OL1 3NE",
    "addr:housenumber":"69",
    "addr:postcode":"ol1 3ne",
    "addr:street":"The;Barry St",
    "iso:country":"GB",
    "sg:address":"69 The Acorn Centre, Barry St",
    "sg:city":"Oldham",
    "sg:classifiers":[
        {
            "category":"Food & Beverages",
            "subcategory":"Supermarket",
            "type":"Retail Goods"
        }
    ],
    "sg:phone":"+44 161 627 2027",
    "sg:postcode":"OL1 3NE",
    "sg:province":"Lancashire",
    "sg:tags":[
        "frozen"
    ],
    "wof:name":"Seasoners Fine Food Ltd",
    "wof:placetype":"venue"
},
  "geometry": {"coordinates":[-2.095757,53.547592],"type":"Point"}
}