{
  "type": "Feature",
  "properties": {
    "addr:full":"217a Field End Rd Pinner Greater London HA5 1QZ",
    "addr:housenumber":"217a",
    "addr:postcode":"ha5 1qz",
    "addr:street":"Field End Rd",
    "iso:country":"GB",
    "sg:address":"217a Field End Rd",
    "sg:city":"Pinner",
    "sg:classifiers":[
        {
            "category":"Wholesale",
            "subcategory":"Music Publishers",
            "type":"Manufacturing & Wholesale Goods"
        }
    ],
    "sg:phone":"+44 20 8868 2917",
    "sg:postcode":"HA5 1QZ",
    "sg:province":"Greater London",
    "sg:tags":[
        "record"
    ],
    "wof:name":"Octopus Records",
    "wof:placetype":"venue"
},
  "geometry": {"coordinates":[-0.398349,51.5774],"type":"Point"}
}