{
  "type": "Feature",
  "properties": {
    "addr:full":"Tilland Farm, Tideford Saltash Cornwall PL12 5JE",
    "addr:postcode":"pl12 5je",
    "addr:street":"Tideford",
    "iso:country":"GB",
    "sg:address":"Tilland Farm, Tideford",
    "sg:city":"Saltash",
    "sg:classifiers":[
        {
            "category":"Travel",
            "subcategory":"Hotels & Motels",
            "type":"Entertainment"
        }
    ],
    "sg:phone":"+44 1752 851393",
    "sg:postcode":"PL12 5JE",
    "sg:province":"Cornwall",
    "sg:tags":[
        "house",
        "guest"
    ],
    "wof:name":"Tilland Farmers Accommodation",
    "wof:placetype":"venue"
},
  "geometry": {"coordinates":[-4.3273630142,50.4138526917],"type":"Point"}
}