{
  "type": "Feature",
  "properties": {
    "addr:full":"Suite C 80 Clifton Hill London Greater London NW8 0JT",
    "addr:housenumber":"suite c 80",
    "addr:postcode":"nw8 0jt",
    "addr:street":"Clifton Hill",
    "iso:country":"GB",
    "sg:address":"Suite C 80 Clifton Hill",
    "sg:city":"London",
    "sg:classifiers":[
        {
            "category":"Real Estate",
            "subcategory":"Real Estate Agent",
            "type":"Services"
        }
    ],
    "sg:postcode":"NW8 0JT",
    "sg:province":"Greater London",
    "wof:name":"Luxury Home Management Service (Internat",
    "wof:placetype":"venue"
},
  "geometry": {"coordinates":[-0.1852499992,51.5357818604],"type":"Point"}
}