{
  "type": "Feature",
  "properties": {
    "iso:country":"GB",
    "sg:address":"Mayo Courtyard, Rear Of 64 Main Street",
    "sg:city":"Cockermouth",
    "sg:classifiers":[
        {
            "category":"Sports & Exercise",
            "subcategory":"Gym",
            "type":"Entertainment"
        }
    ],
    "sg:phone":"+44 1900 827973",
    "sg:postcode":"CA13 9LU",
    "sg:province":"Cumbria",
    "sg:tags":[
        "fitness",
        "health",
        "centre"
    ],
    "wof:name":"Lifestyle & Shapers Fitness Centre",
    "wof:placetype":"venue"
},
  "geometry": {"coordinates":[-3.3659520149,54.663646698],"type":"Point"}
}