{
  "type": "Feature",
  "properties": {
    "iso:country":"GB",
    "sg:address":"12 Riverside Industrial Estate, 27 Thames Road",
    "sg:city":"Barking",
    "sg:classifiers":[
        {
            "category":"Professional",
            "subcategory":"Advertising",
            "type":"Services"
        },
        {
            "category":"Manufacturing",
            "subcategory":"Signs",
            "type":"Manufacturing & Wholesale Goods"
        }
    ],
    "sg:phone":"+44 20 8507 9385",
    "sg:postcode":"IG11 0ND",
    "sg:province":"Essex",
    "sg:tags":[
        "writer",
        "signwriters"
    ],
    "wof:name":"The Sign Emporium",
    "wof:placetype":"venue"
},
  "geometry": {"coordinates":[0.0811149999,51.539100647],"type":"Point"}
}