{
  "type": "Feature",
  "properties": {
    "iso:country":"GB",
    "sg:address":"36 Howe Lane, Nafforton",
    "sg:city":"Driffield",
    "sg:classifiers":[
        {
            "category":"Building & Trades",
            "subcategory":"Construction",
            "type":"Services"
        }
    ],
    "sg:postcode":"YO25 4JU",
    "sg:province":"East Riding of Yorkshire",
    "sg:tags":[
        "builder"
    ],
    "wof:name":"Raines,S,Builders",
    "wof:placetype":"venue"
},
  "geometry": {"coordinates":[-0.3874680102,54.0169487],"type":"Point"}
}