{
  "type": "Feature",
  "properties": {
    "addr:full":"Torrs Park Ilfracombe Devon EX34 8AZ",
    "addr:postcode":"ex34 8az",
    "iso:country":"GB",
    "sg:address":"Torrs Park",
    "sg:city":"Ilfracombe",
    "sg:classifiers":[
        {
            "category":"Travel",
            "subcategory":"Hotels & Motels",
            "type":"Entertainment"
        }
    ],
    "sg:postcode":"EX34 8AZ",
    "sg:province":"Devon",
    "wof:name":"Southcliffe Hotel",
    "wof:placetype":"venue"
},
  "geometry": {"coordinates":[-4.1280422211,51.2085876465],"type":"Point"}
}