{
  "type": "Feature",
  "properties": {
    "iso:country":"GB",
    "sg:address":"Leazes Lane, Whitley Chapel, Steel",
    "sg:city":"Hexham",
    "sg:classifiers":[
        {
            "category":"Education",
            "subcategory":"School",
            "type":"Public Place"
        }
    ],
    "sg:phone":"+44 1434 673294",
    "sg:postcode":"NE47 0HB",
    "sg:province":"Northumberland",
    "sg:tags":[
        "local",
        "authority"
    ],
    "wof:name":"Whitley Chapel C Of E First School",
    "wof:placetype":"venue"
},
  "geometry": {"coordinates":[-2.138274,54.868183],"type":"Point"}
}