{
  "type": "Feature",
  "properties": {
    "addr:full":"18a Hythe Street Dartford Kent DA1 1BX",
    "addr:housenumber":"18a",
    "addr:postcode":"da1 1bx",
    "addr:street":"Hythe Street",
    "iso:country":"GB",
    "sg:address":"18a Hythe Street",
    "sg:city":"Dartford",
    "sg:classifiers":[
        {
            "category":"Taxi",
            "type":"Transportation"
        }
    ],
    "sg:phone":"+44 1322 292121",
    "sg:postcode":"DA1 1BX",
    "sg:province":"Kent",
    "sg:tags":[
        "mini",
        "cab"
    ],
    "wof:name":"Beeline Taxis",
    "wof:placetype":"venue"
},
  "geometry": {"coordinates":[0.216219,51.445499],"type":"Point"}
}