{
  "type": "Feature",
  "properties": {
    "iso:country":"GB",
    "sg:address":"99 Dunkeld Road",
    "sg:city":"Perth",
    "sg:classifiers":[
        {
            "category":"Shopping",
            "subcategory":"Discount & Variety Stores",
            "type":"Retail Goods"
        },
        {
            "category":"Food & Beverages",
            "subcategory":"Groceries & Convenience Stores",
            "type":"Retail Goods"
        }
    ],
    "sg:phone":"+44 1738 633899",
    "sg:postcode":"PH1 5BS",
    "sg:province":"Perth and Kinross",
    "sg:tags":[
        "centre"
    ],
    "wof:name":"Supersavers",
    "wof:placetype":"venue"
},
  "geometry": {"coordinates":[-3.447644949,56.4075813293],"type":"Point"}
}