{
  "type": "Feature",
  "properties": {
    "iso:country":"GB",
    "sg:address":"203 Station Lane",
    "sg:city":"Hornchurch",
    "sg:classifiers":[
        {
            "category":"Insurance",
            "subcategory":"Insurance Agent",
            "type":"Services"
        }
    ],
    "sg:phone":"+44 1708 707016",
    "sg:postcode":"RM12 6LL",
    "sg:province":"Essex",
    "wof:name":"Fairshare Insurance Consultants",
    "wof:placetype":"venue"
},
  "geometry": {"coordinates":[0.219522,51.554199],"type":"Point"}
}