{
  "type": "Feature",
  "properties": {
    "addr:full":"78 Waterloo Road, Shirley Southampton Hampshire SO15 3BE",
    "addr:housenumber":"78",
    "addr:postcode":"so15 3be",
    "addr:street":"Waterloo Road",
    "iso:country":"GB",
    "sg:address":"78 Waterloo Road, Shirley",
    "sg:city":"Southampton",
    "sg:classifiers":[
        {
            "category":"Social Services",
            "subcategory":"Retirement Home",
            "type":"Services"
        }
    ],
    "sg:postcode":"SO15 3BE",
    "sg:province":"Hampshire",
    "sg:tags":[
        "rest"
    ],
    "wof:name":"Trinidad House Rest Home",
    "wof:placetype":"venue"
},
  "geometry": {"coordinates":[-1.4255609512,50.9108543396],"type":"Point"}
}