{
  "type": "Feature",
  "properties": {
    "addr:full":"175 North End Croydon Surrey CR0 1TP",
    "addr:housenumber":"175",
    "addr:postcode":"cr0 1tp",
    "addr:street":"North End",
    "iso:country":"GB",
    "sg:address":"175 North End",
    "sg:city":"Croydon",
    "sg:classifiers":[
        {
            "category":"Shopping",
            "subcategory":"Books",
            "type":"Retail Goods"
        }
    ],
    "sg:phone":"+44 20 8688 7190",
    "sg:postcode":"CR0 1TP",
    "sg:province":"Surrey",
    "sg:tags":[
        "bookseller"
    ],
    "wof:name":"Forbidden Planet",
    "wof:placetype":"venue"
},
  "geometry": {"coordinates":[-0.102888003,51.3780937195],"type":"Point"}
}