{
  "type": "Feature",
  "properties": {
    "iso:country":"GB",
    "sg:address":"Fox Gro, Old Basford",
    "sg:city":"Nottingham",
    "sg:classifiers":[
        {
            "category":"Building & Trades",
            "subcategory":"Cleaning & Sanitation",
            "type":"Services"
        }
    ],
    "sg:phone":"+44 115 978 9371",
    "sg:postcode":"NG5 1JT",
    "sg:province":"Nottinghamshire",
    "sg:tags":[
        "commercial"
    ],
    "wof:name":"Johnsons Powermaster",
    "wof:placetype":"venue"
},
  "geometry": {"coordinates":[-1.1759200096,52.9828987122],"type":"Point"}
}