{
  "type": "Feature",
  "properties": {
    "iso:country":"GB",
    "sg:address":"Unit 7, 62-70 Fowler Road",
    "sg:city":"Ilford",
    "sg:classifiers":[
        {
            "category":"Building & Trades",
            "subcategory":"Equipment Rental",
            "type":"Services"
        }
    ],
    "sg:phone":"+44 20 8501 0022",
    "sg:postcode":"IG6 3UT",
    "sg:province":"Essex",
    "sg:tags":[
        "plant",
        "machinery"
    ],
    "wof:name":"Broughton Plant Hire Ltd.",
    "wof:placetype":"venue"
},
  "geometry": {"coordinates":[0.12306,51.608433],"type":"Point"}
}