{
  "type": "Feature",
  "properties": {
    "addr:full":"19 Cobham Road London Greater London E17 4ED",
    "addr:housenumber":"19",
    "addr:postcode":"e17 4ed",
    "addr:street":"Cobham Road",
    "iso:country":"GB",
    "sg:address":"19 Cobham Road",
    "sg:city":"London",
    "sg:classifiers":[
        {
            "category":"Retail",
            "subcategory":"Driving School",
            "type":"Services"
        }
    ],
    "sg:phone":"+44 20 8531 5601",
    "sg:postcode":"E17 4ED",
    "sg:province":"Greater London",
    "wof:name":"Seventeen Plus School of Motoring",
    "wof:placetype":"venue"
},
  "geometry": {"coordinates":[-0.002967,51.598133],"type":"Point"}
}