{
  "type": "Feature",
  "properties": {
    "addr:full":"1 Brooklyn Gdn(s) Cheltenham Gloucestershire GL51 8LP",
    "addr:housenumber":"1",
    "addr:postcode":"gl51 8lp",
    "addr:street":"Brooklyn Gdn S",
    "iso:country":"GB",
    "sg:address":"1 Brooklyn Gdn(s)",
    "sg:city":"Cheltenham",
    "sg:classifiers":[
        {
            "category":"Personal",
            "subcategory":"Tanning Parlor",
            "type":"Services"
        }
    ],
    "sg:postcode":"GL51 8LP",
    "sg:province":"Gloucestershire",
    "sg:tags":[
        "sunbeds"
    ],
    "wof:name":"Aztec Sunbeds",
    "wof:placetype":"venue"
},
  "geometry": {"coordinates":[-2.100191,51.909222],"type":"Point"}
}