{
  "type": "Feature",
  "properties": {
    "iso:country":"GB",
    "sg:address":"83 Port Street",
    "sg:city":"Evesham",
    "sg:classifiers":[
        {
            "category":"Professional",
            "subcategory":"Art Services",
            "type":"Services"
        }
    ],
    "sg:postcode":"WR11 3LF",
    "sg:province":"Gloucestershire",
    "sg:tags":[
        "framing"
    ],
    "wof:name":"Anderson Gallery Framing",
    "wof:placetype":"venue"
},
  "geometry": {"coordinates":[-1.9382660389,52.0905914307],"type":"Point"}
}