{
  "type": "Feature",
  "properties": {
    "addr:full":"Linton House, Upper Green, Inkpen Hungerford Berkshire RG17 9PZ",
    "addr:postcode":"rg17 9pz",
    "addr:street":"Upper Green",
    "iso:country":"GB",
    "sg:address":"Linton House, Upper Green, Inkpen",
    "sg:city":"Hungerford",
    "sg:classifiers":[
        {
            "category":"Banks & Credit Unions",
            "subcategory":"Financial Services",
            "type":"Services"
        }
    ],
    "sg:phone":"+44 1488 668861",
    "sg:postcode":"RG17 9PZ",
    "sg:province":"Berkshire",
    "sg:tags":[
        "consultant"
    ],
    "wof:name":"Economy Leasing Ltd",
    "wof:placetype":"venue"
},
  "geometry": {"coordinates":[-1.4665440321,51.375213623],"type":"Point"}
}