{
  "type": "Feature",
  "properties": {
    "addr:full":"23 St Peters Street Bedford Bedfordshire MK40 2PN",
    "addr:housenumber":"23",
    "addr:postcode":"mk40 2pn",
    "addr:street":"St Peters Street",
    "iso:country":"GB",
    "sg:address":"23 St Peters Street",
    "sg:city":"Bedford",
    "sg:classifiers":[
        {
            "category":"Personal",
            "subcategory":"Beauty Salon",
            "type":"Services"
        }
    ],
    "sg:phone":"+44 1234 212666",
    "sg:postcode":"MK40 2PN",
    "sg:province":"Bedfordshire",
    "sg:tags":[
        "unisex",
        "hairdresser"
    ],
    "wof:name":"Hair by Vincenzo",
    "wof:placetype":"venue"
},
  "geometry": {"coordinates":[-0.4649539888,52.138835907],"type":"Point"}
}