{
  "type": "Feature",
  "properties": {
    "iso:country":"GB",
    "sg:address":"98 High Blantyre Road, Burnbank",
    "sg:city":"Hamilton",
    "sg:classifiers":[
        {
            "category":"Place Of Worship",
            "type":"Public Place"
        }
    ],
    "sg:phone":"+44 1698 823105",
    "sg:postcode":"ML3 9HW",
    "sg:province":"South Lanarkshire",
    "wof:name":"St.Cuthbert S",
    "wof:placetype":"venue"
},
  "geometry": {"coordinates":[-4.07639,55.781773],"type":"Point"}
}