{
  "type": "Feature",
  "properties": {
    "addr:full":"51 Market Place Uttoxeter Derbyshire ST14 8HF",
    "addr:housenumber":"51",
    "addr:postcode":"st14 8hf",
    "addr:street":"Market Place",
    "iso:country":"GB",
    "sg:address":"51 Market Place",
    "sg:city":"Uttoxeter",
    "sg:classifiers":[
        {
            "category":"Deli",
            "type":"Food & Drink"
        }
    ],
    "sg:phone":"+44 1889 569900",
    "sg:postcode":"ST14 8HF",
    "sg:province":"Derbyshire",
    "sg:tags":[
        "delivery",
        "sandwich"
    ],
    "wof:name":"Snack Attack",
    "wof:placetype":"venue"
},
  "geometry": {"coordinates":[-1.864796,52.898258],"type":"Point"}
}