{
  "type": "Feature",
  "properties": {
    "addr:full":"Dugard Ho, Peartree Rd, Stanway Colchester Essex CO3 5UL",
    "addr:postcode":"co3 5ul",
    "addr:street":"Peartree Rd",
    "iso:country":"GB",
    "sg:address":"Dugard Ho, Peartree Rd, Stanway",
    "sg:city":"Colchester",
    "sg:classifiers":[
        {
            "category":"Home & Garden",
            "subcategory":"Home Furnishings",
            "type":"Retail Goods"
        }
    ],
    "sg:phone":"+44 1206 760111",
    "sg:postcode":"CO3 5UL",
    "sg:province":"Essex",
    "sg:tags":[
        "racking",
        "shelving",
        "diy"
    ],
    "wof:name":"L W Interiors Ltd",
    "wof:placetype":"venue"
},
  "geometry": {"coordinates":[0.8428599834,51.8835983276],"type":"Point"}
}