{
  "type": "Feature",
  "properties": {
    "iso:country":"GB",
    "sg:address":"Unit 21 Chanters Industrial Estate, Tyldesley Old Road, Atherton",
    "sg:city":"Manchester",
    "sg:classifiers":[
        {
            "category":"Building & Trades",
            "subcategory":"Construction",
            "type":"Services"
        }
    ],
    "sg:phone":"+44 1942 886888",
    "sg:postcode":"M46 9BE",
    "sg:province":"Greater Manchester",
    "sg:tags":[
        "excavation",
        "groundwork",
        "contractor"
    ],
    "wof:name":"Fitfield Ltd.",
    "wof:placetype":"venue"
},
  "geometry": {"coordinates":[-2.4791460037,53.5202217102],"type":"Point"}
}