{
  "type": "Feature",
  "properties": {
    "addr:full":"31 The Green Burton-on-trent Derbyshire DE13 8JD",
    "addr:housenumber":"31",
    "addr:postcode":"de13 8jd",
    "addr:street":"The Green",
    "iso:country":"GB",
    "sg:address":"31 The Green",
    "sg:city":"Burton-on-trent",
    "sg:classifiers":[
        {
            "category":"Shopping",
            "subcategory":"Department Store",
            "type":"Retail Goods"
        }
    ],
    "sg:postcode":"DE13 8JD",
    "sg:province":"Derbyshire",
    "wof:name":"Barton Green Stores",
    "wof:placetype":"venue"
},
  "geometry": {"coordinates":[-1.7295670509,52.7599220276],"type":"Point"}
}