{
  "type": "Feature",
  "properties": {
    "iso:country":"GB",
    "sg:address":"5a Cluntergate, Horbury",
    "sg:city":"Wakefield",
    "sg:classifiers":[
        {
            "category":"Professional",
            "subcategory":"Accounting & Tax Preparation",
            "type":"Services"
        }
    ],
    "sg:phone":"+44 1924 280124",
    "sg:postcode":"WF4 5AF",
    "sg:province":"West Yorkshire",
    "sg:tags":[
        "accountant"
    ],
    "wof:name":"M K Blundell & Co. Ltd.",
    "wof:placetype":"venue"
},
  "geometry": {"coordinates":[-1.553187,53.659454],"type":"Point"}
}