{
  "type": "Feature",
  "properties": {
    "iso:country":"GB",
    "sg:address":"29a Green Drive",
    "sg:city":"Inverness",
    "sg:classifiers":[
        {
            "category":"Building & Trades",
            "subcategory":"Plumbing",
            "type":"Services"
        }
    ],
    "sg:phone":"+44 1463 242291",
    "sg:postcode":"IV2 4EU",
    "sg:province":"Highland",
    "sg:tags":[
        "plumber",
        "heating"
    ],
    "wof:name":"M J Craigen",
    "wof:placetype":"venue"
},
  "geometry": {"coordinates":[-4.223016,57.454861],"type":"Point"}
}