{
  "type": "Feature",
  "properties": {
    "addr:full":"21 Church Street, Milnathort Kinross Clackmannanshire KY13 9XE",
    "addr:housenumber":"21",
    "addr:postcode":"ky13 9xe",
    "addr:street":"Church Street",
    "iso:country":"GB",
    "sg:address":"21 Church Street, Milnathort",
    "sg:city":"Kinross",
    "sg:classifiers":[
        {
            "category":"Government",
            "subcategory":"Office",
            "type":"Public Place"
        }
    ],
    "sg:postcode":"KY13 9XE",
    "sg:province":"Clackmannanshire",
    "sg:tags":[
        "marriage",
        "death",
        "births"
    ],
    "wof:name":"Registration of Births Deaths & Marriages",
    "wof:placetype":"venue"
},
  "geometry": {"coordinates":[-3.4210879803,56.2262611389],"type":"Point"}
}