{
  "type": "Feature",
  "properties": {
    "addr:full":"3 Highfield Lane Maidenhead Berkshire SL6 3AN",
    "addr:housenumber":"3",
    "addr:postcode":"sl6 3an",
    "addr:street":"Highfield Lane",
    "iso:country":"GB",
    "sg:address":"3 Highfield Lane",
    "sg:city":"Maidenhead",
    "sg:classifiers":[
        {
            "category":"Professional",
            "subcategory":"Management & Consulting",
            "type":"Services"
        }
    ],
    "sg:phone":"+44 1628 635499",
    "sg:postcode":"SL6 3AN",
    "sg:province":"Berkshire",
    "sg:tags":[
        "consultant",
        "business"
    ],
    "wof:name":"International Training & Development Services",
    "wof:placetype":"venue"
},
  "geometry": {"coordinates":[-0.751735,51.506115],"type":"Point"}
}