{
  "type": "Feature",
  "properties": {
    "addr:full":"Unit 27 Scot Road Industrial Estate, Sundow Park Luton Bedfordshire LU3 3BF",
    "addr:housenumber":"unit 27",
    "addr:postcode":"lu3 3bf",
    "addr:street":"Scot Road Industrial Estate Sundow Park",
    "iso:country":"GB",
    "sg:address":"Unit 27 Scot Road Industrial Estate, Sundow Park",
    "sg:city":"Luton",
    "sg:classifiers":[
        {
            "category":"Manufacturing",
            "subcategory":"Petroleum Products",
            "type":"Manufacturing & Wholesale Goods"
        }
    ],
    "sg:phone":"+44 1582 585500",
    "sg:postcode":"LU3 3BF",
    "sg:province":"Bedfordshire",
    "sg:tags":[
        "double",
        "glazing"
    ],
    "wof:name":"Weatherbreak Windows Ltd.",
    "wof:placetype":"venue"
},
  "geometry": {"coordinates":[-0.4728139937,51.9170608521],"type":"Point"}
}