{
  "type": "Feature",
  "properties": {
    "iso:country":"GB",
    "sg:address":"Thames Rd",
    "sg:city":"Dartford",
    "sg:classifiers":[
        {
            "category":"Professional",
            "type":"Services"
        }
    ],
    "sg:phone":"+44 1322 552888",
    "sg:postcode":"DA1 4QJ",
    "sg:province":"Kent",
    "sg:tags":[
        "specialist",
        "coating"
    ],
    "wof:name":"Burmah Castrol",
    "wof:placetype":"venue"
},
  "geometry": {"coordinates":[0.199223,51.456097],"type":"Point"}
}