{
  "type": "Feature",
  "properties": {
    "addr:full":"2 Shoreditch High Street London Greater London E1 6PG",
    "addr:housenumber":"2",
    "addr:postcode":"e1 6pg",
    "addr:street":"Shoreditch High Street",
    "iso:country":"GB",
    "sg:address":"2 Shoreditch High Street",
    "sg:city":"London",
    "sg:classifiers":[
        {
            "category":"Professional",
            "subcategory":"Employment Agencies",
            "type":"Services"
        }
    ],
    "sg:phone":"+44 20 7377 1352",
    "sg:postcode":"E1 6PG",
    "sg:province":"Greater London",
    "sg:tags":[
        "consultant"
    ],
    "wof:name":"Mayday Group Ltd.",
    "wof:placetype":"venue"
},
  "geometry": {"coordinates":[-0.0781230032,51.5217018127],"type":"Point"}
}