{
  "type": "Feature",
  "properties": {
    "addr:full":"41 High Street Dalkeith City of Edinburgh EH22 1JB",
    "addr:housenumber":"41",
    "addr:postcode":"eh22 1jb",
    "addr:street":"High Street",
    "iso:country":"GB",
    "sg:address":"41 High Street",
    "sg:city":"Dalkeith",
    "sg:classifiers":[
        {
            "category":"Health Services",
            "subcategory":"Optometrist",
            "type":"Services"
        }
    ],
    "sg:phone":"+44 131 663 2548",
    "sg:postcode":"EH22 1JB",
    "sg:province":"City of Edinburgh",
    "sg:tags":[
        "optician"
    ],
    "wof:name":"Roberts & Gillanders Ltd.",
    "wof:placetype":"venue"
},
  "geometry": {"coordinates":[-3.0715670586,55.8939857483],"type":"Point"}
}