{
  "type": "Feature",
  "properties": {
    "addr:full":"490-494 Greenford Road Greenford Greater London UB6 8SH",
    "addr:housenumber":"490-494",
    "addr:postcode":"ub6 8sh",
    "addr:street":"Greenford Road",
    "iso:country":"GB",
    "sg:address":"490-494 Greenford Road",
    "sg:city":"Greenford",
    "sg:classifiers":[
        {
            "category":"Home & Garden",
            "subcategory":"Home Furnishings",
            "type":"Retail Goods"
        },
        {
            "category":"Manufacturing",
            "subcategory":"Textiles",
            "type":"Manufacturing & Wholesale Goods"
        }
    ],
    "sg:phone":"+44 20 8578 2883",
    "sg:postcode":"UB6 8SH",
    "sg:province":"Greater London",
    "sg:tags":[
        "made-up",
        "beds",
        "bedding",
        "blanket"
    ],
    "wof:name":"Brooks Gibbs Ltd.",
    "wof:placetype":"venue"
},
  "geometry": {"coordinates":[-0.351645,51.528812],"type":"Point"}
}