{
  "type": "Feature",
  "properties": {
    "addr:full":"Leofric Ho, 18b Binley Rd Coventry Warwickshire CV3 1JN",
    "addr:housenumber":"18b",
    "addr:postcode":"cv3 1jn",
    "addr:street":"Binley Rd",
    "iso:country":"GB",
    "sg:address":"Leofric Ho, 18b Binley Rd",
    "sg:city":"Coventry",
    "sg:classifiers":[
        {
            "category":"Home & Garden",
            "subcategory":"Building Materials",
            "type":"Retail Goods"
        }
    ],
    "sg:phone":"+44 24 7644 7128",
    "sg:postcode":"CV3 1JN",
    "sg:province":"Warwickshire",
    "sg:tags":[
        "insulation",
        "installers"
    ],
    "wof:name":"New World Insulations Ltd",
    "wof:placetype":"venue"
},
  "geometry": {"coordinates":[-1.49092,52.407681],"type":"Point"}
}