{
  "type": "Feature",
  "properties": {
    "iso:country":"GB",
    "sg:address":"5 Allen Farm Close, Godmanchester",
    "sg:city":"Huntingdon",
    "sg:classifiers":[
        {
            "category":"Building & Trades",
            "subcategory":"Construction",
            "type":"Services"
        }
    ],
    "sg:phone":"+44 1480 394424",
    "sg:postcode":"PE29 2LT",
    "sg:province":"Cambridgeshire",
    "sg:tags":[
        "builder"
    ],
    "wof:name":"Rma Services",
    "wof:placetype":"venue"
},
  "geometry": {"coordinates":[-0.175341,52.315472],"type":"Point"}
}