{
  "type": "Feature",
  "properties": {
    "iso:country":"GB",
    "sg:address":"Shefford Rd",
    "sg:city":"Shefford",
    "sg:classifiers":[
        {
            "category":"Professional",
            "subcategory":"Lawyer & Legal Services",
            "type":"Services"
        }
    ],
    "sg:phone":"+44 1462 814228",
    "sg:postcode":"SG17 5QS",
    "sg:province":"Bedfordshire",
    "sg:tags":[
        "advice",
        "counselling"
    ],
    "wof:name":"South East Beds Action Point",
    "wof:placetype":"venue"
},
  "geometry": {"coordinates":[-0.316181,52.037651],"type":"Point"}
}