{
  "type": "Feature",
  "properties": {
    "addr:full":"24 New Bank Road Blackburn Lancashire BB2 6JW",
    "addr:housenumber":"24",
    "addr:postcode":"bb2 6jw",
    "addr:street":"New Bank Road",
    "iso:country":"GB",
    "sg:address":"24 New Bank Road",
    "sg:city":"Blackburn",
    "sg:classifiers":[
        {
            "category":"Shopping",
            "subcategory":"News",
            "type":"Retail Goods"
        }
    ],
    "sg:phone":"+44 1254 661234",
    "sg:postcode":"BB2 6JW",
    "sg:province":"Lancashire",
    "sg:tags":[
        "newsagent"
    ],
    "wof:name":"NEW BANK NEWSAGENTS",
    "wof:placetype":"venue"
},
  "geometry": {"coordinates":[-2.5026800632,53.7518234253],"type":"Point"}
}