{
  "type": "Feature",
  "properties": {
    "addr:full":"The Old House, Rilla Mill Callington Cornwall PL17 7NT",
    "addr:postcode":"pl17 7nt",
    "addr:street":"Rilla Mill",
    "iso:country":"GB",
    "sg:address":"The Old House, Rilla Mill",
    "sg:city":"Callington",
    "sg:classifiers":[
        {
            "category":"Organizations",
            "subcategory":"Non-profit Organization",
            "type":"Services"
        }
    ],
    "sg:phone":"+44 1579 363545",
    "sg:postcode":"PL17 7NT",
    "sg:province":"Cornwall",
    "sg:tags":[
        "charitable",
        "organisation",
        "voluntary",
        "charity"
    ],
    "wof:name":"Arthritis Research Campaign",
    "wof:placetype":"venue"
},
  "geometry": {"coordinates":[-4.330329,50.50563],"type":"Point"}
}