{
  "type": "Feature",
  "properties": {
    "iso:country":"GB",
    "sg:address":"Unit 9 Reaymer Close",
    "sg:city":"Walsall",
    "sg:classifiers":[
        {
            "category":"Home & Garden",
            "subcategory":"Home Furnishings",
            "type":"Retail Goods"
        }
    ],
    "sg:phone":"+44 1922 400991",
    "sg:postcode":"WS2 7QZ",
    "sg:province":"West Midlands",
    "sg:tags":[
        "merchant",
        "diy",
        "decorators'"
    ],
    "wof:name":"Leyland Paint Co",
    "wof:placetype":"venue"
},
  "geometry": {"coordinates":[-2.007615,52.606033],"type":"Point"}
}