{
  "type": "Feature",
  "properties": {
    "addr:full":"Hessley Lane, Rathmell Settle North Yorkshire BD24 0LA",
    "addr:postcode":"bd24 0la",
    "addr:street":"Hessley Lane",
    "iso:country":"GB",
    "sg:address":"Hessley Lane, Rathmell",
    "sg:city":"Settle",
    "sg:classifiers":[
        {
            "category":"Education",
            "subcategory":"School",
            "type":"Public Place"
        },
        {
            "category":"Government",
            "subcategory":"Office",
            "type":"Public Place"
        }
    ],
    "sg:phone":"+44 1729 840360",
    "sg:postcode":"BD24 0LA",
    "sg:province":"North Yorkshire",
    "sg:tags":[
        "local",
        "authority"
    ],
    "wof:name":"Rathmell C O E Primary School",
    "wof:placetype":"venue"
},
  "geometry": {"coordinates":[-2.304826,54.035255],"type":"Point"}
}