{
  "type": "Feature",
  "properties": {
    "addr:full":"Mill Road Cambridge Cambridgeshire CB1 3DF",
    "addr:postcode":"cb1 3df",
    "addr:street":"Mill Road",
    "iso:country":"GB",
    "sg:address":"Mill Road",
    "sg:city":"Cambridge",
    "sg:classifiers":[
        {
            "category":"Autos & Motor Vehicles",
            "subcategory":"Automobile Sales",
            "type":"Retail Goods"
        },
        {
            "category":"Retail",
            "subcategory":"Auto Repair",
            "type":"Services"
        }
    ],
    "sg:phone":"+44 1223 242222",
    "sg:postcode":"CB1 3DF",
    "sg:province":"Cambridgeshire",
    "sg:tags":[
        "modification",
        "garage",
        "car"
    ],
    "wof:name":"Herbert Robinson Ltd.",
    "wof:placetype":"venue"
},
  "geometry": {"coordinates":[0.14242,52.198223],"type":"Point"}
}