{
  "type": "Feature",
  "properties": {
    "iso:country":"GB",
    "sg:address":"Sidmouth Road, Rousdon",
    "sg:city":"Lyme Regis",
    "sg:classifiers":[
        {
            "category":"Travel",
            "subcategory":"Hotels & Motels",
            "type":"Entertainment"
        }
    ],
    "sg:phone":"+44 1297 22055",
    "sg:postcode":"DT7 3RD",
    "sg:province":"Devon",
    "sg:tags":[
        "self",
        "catering"
    ],
    "wof:name":"Pinewood Homes",
    "wof:placetype":"venue"
},
  "geometry": {"coordinates":[-2.943626,50.727894],"type":"Point"}
}