{
  "type": "Feature",
  "properties": {
    "iso:country":"GB",
    "sg:address":"32 Bryn Hyfryd, Coedpoeth",
    "sg:city":"Wrexham",
    "sg:classifiers":[
        {
            "category":"Professional",
            "subcategory":"Engineering",
            "type":"Services"
        },
        {
            "category":"Building & Trades",
            "subcategory":"Electrical",
            "type":"Services"
        }
    ],
    "sg:phone":"+44 1978 757989",
    "sg:postcode":"LL11 3YB",
    "sg:province":"Wrexham",
    "sg:tags":[
        "engineer",
        "electrician",
        "contractor"
    ],
    "wof:name":"I Ashcroft",
    "wof:placetype":"venue"
},
  "geometry": {"coordinates":[-3.076677,53.058086],"type":"Point"}
}