{
  "type": "Feature",
  "properties": {
    "addr:full":"309 High St Gateshead Tyne and Wear NE8 1EQ",
    "addr:housenumber":"309",
    "addr:postcode":"ne8 1eq",
    "addr:street":"High St",
    "iso:country":"GB",
    "sg:address":"309 High St",
    "sg:city":"Gateshead",
    "sg:classifiers":[
        {
            "category":"Shopping",
            "subcategory":"Comic Books",
            "type":"Retail Goods"
        }
    ],
    "sg:phone":"+44 191 478 6696",
    "sg:postcode":"NE8 1EQ",
    "sg:province":"Tyne and Wear",
    "sg:tags":[
        "jeweller"
    ],
    "wof:name":"J E B Jewellers",
    "wof:placetype":"venue"
},
  "geometry": {"coordinates":[-1.5997159481,54.9606437683],"type":"Point"}
}