{
  "type": "Feature",
  "properties": {
    "addr:full":"Lakeside Weston Avenue Grays Essex RM20 3FJ",
    "addr:postcode":"rm20 3fj",
    "addr:street":"Weston Avenue",
    "iso:country":"GB",
    "sg:address":"Lakeside Weston Avenue",
    "sg:city":"Grays",
    "sg:classifiers":[
        {
            "category":"Autos & Motor Vehicles",
            "subcategory":"Automobile Sales",
            "type":"Retail Goods"
        }
    ],
    "sg:phone":"+44 1708 686300",
    "sg:postcode":"RM20 3FJ",
    "sg:province":"Essex",
    "sg:tags":[
        "car"
    ],
    "wof:name":"Carland",
    "wof:placetype":"venue"
},
  "geometry": {"coordinates":[0.2698200047,51.4783706665],"type":"Point"}
}