{
  "type": "Feature",
  "properties": {
    "addr:full":"30 New Road Birmingham West Midlands B45 9HU",
    "addr:housenumber":"30",
    "addr:postcode":"b45 9hu",
    "addr:street":"New Road",
    "iso:country":"GB",
    "sg:address":"30 New Road",
    "sg:city":"Birmingham",
    "sg:classifiers":[
        {
            "category":"Professional",
            "subcategory":"Management & Consulting",
            "type":"Services"
        },
        {
            "category":"Government",
            "subcategory":"Fire Station",
            "type":"Public Place"
        }
    ],
    "sg:phone":"+44 121 457 8484",
    "sg:postcode":"B45 9HU",
    "sg:province":"West Midlands",
    "sg:tags":[
        "consultant",
        "security",
        "protection"
    ],
    "wof:name":"Brookside Fire Services",
    "wof:placetype":"venue"
},
  "geometry": {"coordinates":[-2.025235,52.391472],"type":"Point"}
}