{
  "type": "Feature",
  "properties": {
    "iso:country":"GB",
    "sg:address":"3 Dunsborough Cottage, Dunsborough Park",
    "sg:city":"Woking",
    "sg:classifiers":[
        {
            "category":"Communications",
            "subcategory":"Film & Video Production",
            "type":"Services"
        }
    ],
    "sg:phone":"+44 1483 222600",
    "sg:postcode":"GU23 6AL",
    "sg:province":"Surrey",
    "sg:tags":[
        "recording",
        "studio"
    ],
    "wof:name":"Black Barn Studios The",
    "wof:placetype":"venue"
},
  "geometry": {"coordinates":[-0.49113,51.307758],"type":"Point"}
}