{
  "type": "Feature",
  "properties": {
    "iso:country":"GB",
    "sg:address":"81 High Street East",
    "sg:city":"Redcar",
    "sg:classifiers":[
        {
            "category":"Home & Garden",
            "subcategory":"Home Furnishings",
            "type":"Retail Goods"
        }
    ],
    "sg:phone":"+44 1642 492471",
    "sg:postcode":"TS10 3DE",
    "sg:province":"North Yorkshire",
    "sg:tags":[
        "patio",
        "furniture"
    ],
    "wof:name":"Wilkinson Group of Companies",
    "wof:placetype":"venue"
},
  "geometry": {"coordinates":[-1.063055,54.617935],"type":"Point"}
}