{
  "type": "Feature",
  "properties": {
    "addr:full":"Carne House, 16 Parsons Lane Bury Lancashire BL9 0JT",
    "addr:housenumber":"16",
    "addr:postcode":"bl9 0jt",
    "addr:street":"Parsons Lane",
    "iso:country":"GB",
    "sg:address":"Carne House, 16 Parsons Lane",
    "sg:city":"Bury",
    "sg:classifiers":[
        {
            "category":"Real Estate",
            "subcategory":"Real Estate Agent",
            "type":"Services"
        }
    ],
    "sg:phone":"+44 161 763 9000",
    "sg:postcode":"BL9 0JT",
    "sg:province":"Lancashire",
    "wof:name":"Dillons Estate Agents",
    "wof:placetype":"venue"
},
  "geometry": {"coordinates":[-2.294809103,53.5949707031],"type":"Point"}
}