{
  "type": "Feature",
  "properties": {
    "iso:country":"GB",
    "sg:address":"88-89 Portland Road, South Norwood",
    "sg:city":"London",
    "sg:classifiers":[
        {
            "category":"Home & Garden",
            "subcategory":"Household Appliances",
            "type":"Retail Goods"
        }
    ],
    "sg:phone":"+44 20 8654 8465",
    "sg:postcode":"SE25 4UN",
    "sg:province":"Greater London",
    "sg:tags":[
        "gas"
    ],
    "wof:name":"Sullivans Gas Appliances",
    "wof:placetype":"venue"
},
  "geometry": {"coordinates":[-0.0699129999,51.3965187073],"type":"Point"}
}