{
  "type": "Feature",
  "properties": {
    "addr:full":"Briar Cottage, Tithill Lane Taunton Devon TA4 3LY",
    "addr:postcode":"ta4 3ly",
    "addr:street":"Tithill Lane",
    "iso:country":"GB",
    "sg:address":"Briar Cottage, Tithill Lane",
    "sg:city":"Taunton",
    "sg:classifiers":[
        {
            "category":"Building & Trades",
            "subcategory":"Construction",
            "type":"Services"
        }
    ],
    "sg:postcode":"TA4 3LY",
    "sg:province":"Devon",
    "sg:tags":[
        "glazier",
        "decorator",
        "painter"
    ],
    "wof:name":"R F L Hicks",
    "wof:placetype":"venue"
},
  "geometry": {"coordinates":[-3.19153,51.044842],"type":"Point"}
}