{
  "type": "Feature",
  "properties": {
    "addr:full":"6 Kings Chambers, Queens Road Coventry West Midlands CV1 3EH",
    "addr:housenumber":"6",
    "addr:postcode":"cv1 3eh",
    "addr:street":"Kings Chambers Queens Road",
    "iso:country":"GB",
    "sg:address":"6 Kings Chambers, Queens Road",
    "sg:city":"Coventry",
    "sg:classifiers":[
        {
            "category":"Professional",
            "subcategory":"Management & Consulting",
            "type":"Services"
        },
        {
            "category":"Organizations",
            "subcategory":"Community Association",
            "type":"Services"
        }
    ],
    "sg:phone":"+44 24 7622 8881",
    "sg:postcode":"CV1 3EH",
    "sg:province":"West Midlands",
    "sg:tags":[
        "consultant",
        "relation",
        "public"
    ],
    "sg:website":"http://www.centurypr.com",
    "wof:name":"Century P R",
    "wof:placetype":"venue"
},
  "geometry": {"coordinates":[-1.51793,52.405285],"type":"Point"}
}