{
  "type": "Feature",
  "properties": {
    "iso:country":"GB",
    "sg:address":"Green Road",
    "sg:city":"Wick",
    "sg:classifiers":[
        {
            "category":"Wholesale",
            "subcategory":"Meat",
            "type":"Manufacturing & Wholesale Goods"
        }
    ],
    "sg:phone":"+44 1955 605472",
    "sg:postcode":"KW1 4DA",
    "sg:province":"Highland",
    "sg:tags":[
        "abattoir"
    ],
    "wof:name":"Wick Slaughterhouse Co",
    "wof:placetype":"venue"
},
  "geometry": {"coordinates":[-3.093739,58.445316],"type":"Point"}
}