{
  "type": "Feature",
  "properties": {
    "iso:country":"GB",
    "sg:address":"Workshop 1, Castle Clo, New Rd",
    "sg:city":"Crook",
    "sg:classifiers":[
        {
            "category":"Home & Garden",
            "subcategory":"Building Materials",
            "type":"Retail Goods"
        }
    ],
    "sg:phone":"+44 1388 768117",
    "sg:postcode":"DL15 8JZ",
    "sg:province":"Durham",
    "sg:tags":[
        "fencing"
    ],
    "wof:name":"Wear Valley Fencing Ltd",
    "wof:placetype":"venue"
},
  "geometry": {"coordinates":[-1.7487939596,54.7143630981],"type":"Point"}
}