{
  "type": "Feature",
  "properties": {
    "addr:full":"Unit 3 Pennant Park, Standard Way Fareham Hampshire PO16 8XU",
    "addr:housenumber":"unit 3 pennant",
    "addr:postcode":"po16 8xu",
    "addr:street":"Park Standard Way",
    "iso:country":"GB",
    "sg:address":"Unit 3 Pennant Park, Standard Way",
    "sg:city":"Fareham",
    "sg:classifiers":[
        {
            "category":"Manufacturing",
            "subcategory":"Metals",
            "type":"Manufacturing & Wholesale Goods"
        }
    ],
    "sg:phone":"+44 1329 826456",
    "sg:postcode":"PO16 8XU",
    "sg:province":"Hampshire",
    "sg:tags":[
        "work",
        "sheet"
    ],
    "wof:name":"Super Flex Portsmouth Specialised Welding Ltd",
    "wof:placetype":"venue"
},
  "geometry": {"coordinates":[-1.1740989685,50.8527336121],"type":"Point"}
}