{
  "type": "Feature",
  "properties": {
    "addr:full":"12 Kinsale Rd Bristol City of Bristol BS14 9HB",
    "addr:housenumber":"12",
    "addr:postcode":"bs14 9hb",
    "addr:street":"Kinsale Rd",
    "iso:country":"GB",
    "sg:address":"12 Kinsale Rd",
    "sg:city":"Bristol",
    "sg:classifiers":[
        {
            "category":"Food & Beverages",
            "subcategory":"Supermarket",
            "type":"Retail Goods"
        }
    ],
    "sg:postcode":"BS14 9HB",
    "sg:province":"City of Bristol",
    "wof:name":"Brown,Nigel,",
    "wof:placetype":"venue"
},
  "geometry": {"coordinates":[-2.5593850613,51.4225769043],"type":"Point"}
}