{
  "type": "Feature",
  "properties": {
    "addr:full":"38 Unity Road Enfield Greater London EN3 6PB",
    "addr:housenumber":"38",
    "addr:postcode":"en3 6pb",
    "addr:street":"Unity Road",
    "iso:country":"GB",
    "sg:address":"38 Unity Road",
    "sg:city":"Enfield",
    "sg:classifiers":[
        {
            "category":"Professional",
            "subcategory":"Detective & Security Services",
            "type":"Services"
        }
    ],
    "sg:phone":"+44 20 8482 0892",
    "sg:postcode":"EN3 6PB",
    "sg:province":"Greater London",
    "sg:tags":[
        "alarm",
        "burglar",
        "system"
    ],
    "wof:name":"Flipps Electrical Services",
    "wof:placetype":"venue"
},
  "geometry": {"coordinates":[-0.0418060012,51.6726455688],"type":"Point"}
}