{
  "type": "Feature",
  "properties": {
    "addr:full":"157 Craigmillar Castle Avenue Edinburgh City of Edinburgh EH16 4DN",
    "addr:housenumber":"157",
    "addr:postcode":"eh16 4dn",
    "addr:street":"Craigmillar Castle Avenue Edinburgh",
    "iso:country":"GB",
    "sg:address":"157 Craigmillar Castle Avenue",
    "sg:city":"Edinburgh",
    "sg:classifiers":[
        {
            "category":"Building & Trades",
            "subcategory":"Cleaning & Sanitation",
            "type":"Services"
        }
    ],
    "sg:postcode":"EH16 4DN",
    "sg:province":"City of Edinburgh",
    "sg:tags":[
        "commercial"
    ],
    "wof:name":"Housework",
    "wof:placetype":"venue"
},
  "geometry": {"coordinates":[-3.134723,55.931179],"type":"Point"}
}