{
  "type": "Feature",
  "properties": {
    "addr:full":"Circus Farm, Reading Road, Aldermaston Reading Berkshire RG7 4PP",
    "addr:postcode":"rg7 4pp",
    "addr:street":"Circus;Reading Road",
    "iso:country":"GB",
    "sg:address":"Circus Farm, Reading Road, Aldermaston",
    "sg:city":"Reading",
    "sg:classifiers":[
        {
            "category":"Freight",
            "type":"Transportation"
        }
    ],
    "sg:phone":"+44 118 981 2578",
    "sg:postcode":"RG7 4PP",
    "sg:province":"Berkshire",
    "sg:tags":[
        "haulage",
        "road"
    ],
    "wof:name":"Raymer Bros",
    "wof:placetype":"venue"
},
  "geometry": {"coordinates":[-1.1525789499,51.3829345703],"type":"Point"}
}