{
  "type": "Feature",
  "properties": {
    "addr:full":"Eastleigh Manor, Eastleigh Bideford Devon EX39 4PA",
    "addr:postcode":"ex39 4pa",
    "iso:country":"GB",
    "sg:address":"Eastleigh Manor, Eastleigh",
    "sg:city":"Bideford",
    "sg:classifiers":[
        {
            "category":"Farming",
            "subcategory":"Farm",
            "type":"Manufacturing & Wholesale Goods"
        }
    ],
    "sg:phone":"+44 1271 860418",
    "sg:postcode":"EX39 4PA",
    "sg:province":"Devon",
    "sg:tags":[
        "mixed",
        "crop"
    ],
    "wof:name":"David J Grigg",
    "wof:placetype":"venue"
},
  "geometry": {"coordinates":[-4.157688,51.03059],"type":"Point"}
}