{
  "type": "Feature",
  "properties": {
    "addr:full":"Unit 1 Avon Village Centre Bristol City of Bristol BS4 4WW",
    "addr:housenumber":"unit 1",
    "addr:postcode":"bs4 4ww",
    "addr:street":"Avon Village",
    "iso:country":"GB",
    "sg:address":"Unit 1 Avon Village Centre",
    "sg:city":"Bristol",
    "sg:classifiers":[
        {
            "category":"Shopping",
            "subcategory":"Bicycles & Sporting Goods",
            "type":"Retail Goods"
        }
    ],
    "sg:phone":"+44 117 977 6227",
    "sg:postcode":"BS4 4WW",
    "sg:province":"City of Bristol",
    "sg:tags":[
        "equipment",
        "leisure"
    ],
    "wof:name":"Mike's Waterfront Warehouse",
    "wof:placetype":"venue"
},
  "geometry": {"coordinates":[-2.541529,51.446651],"type":"Point"}
}