{
  "type": "Feature",
  "properties": {
    "addr:full":"164 Balham High Road, Balham London Greater London SW12 9BW",
    "addr:housenumber":"164",
    "addr:postcode":"sw12 9bw",
    "addr:street":"Balham High Road",
    "iso:country":"GB",
    "sg:address":"164 Balham High Road, Balham",
    "sg:city":"London",
    "sg:classifiers":[
        {
            "category":"Health Services",
            "subcategory":"Optometrist",
            "type":"Services"
        }
    ],
    "sg:phone":"+44 20 8675 6007",
    "sg:postcode":"SW12 9BW",
    "sg:province":"Greater London",
    "sg:tags":[
        "optician"
    ],
    "wof:name":"Balham Eyecare Centre",
    "wof:placetype":"venue"
},
  "geometry": {"coordinates":[-0.1521379948,51.4445114136],"type":"Point"}
}