{
  "type": "Feature",
  "properties": {
    "addr:full":"30 Oak Avenue Christchurch Dorset BH23 2QE",
    "addr:housenumber":"30",
    "addr:postcode":"bh23 2qe",
    "addr:street":"Oak Avenue",
    "iso:country":"GB",
    "sg:address":"30 Oak Avenue",
    "sg:city":"Christchurch",
    "sg:classifiers":[
        {
            "category":"Autos & Motor Vehicles",
            "subcategory":"Motorcycle Sales",
            "type":"Retail Goods"
        }
    ],
    "sg:phone":"+44 1202 483397",
    "sg:postcode":"BH23 2QE",
    "sg:province":"Dorset",
    "sg:tags":[
        "chauffeur",
        "driven",
        "car"
    ],
    "wof:name":"Priory White Cars",
    "wof:placetype":"venue"
},
  "geometry": {"coordinates":[-1.803374,50.744755],"type":"Point"}
}