{
  "type": "Feature",
  "properties": {
    "iso:country":"GB",
    "sg:address":"2 Bonemill Lane",
    "sg:city":"Washington",
    "sg:classifiers":[
        {
            "category":"Taxi",
            "type":"Transportation"
        },
        {
            "category":"Military Area",
            "subcategory":"Air Force Base",
            "type":"Public Place"
        }
    ],
    "sg:phone":"+44 191 416 7808",
    "sg:postcode":"NE38 8AJ",
    "sg:province":"Durham",
    "sg:tags":[
        "mini",
        "hire",
        "private",
        "cab"
    ],
    "wof:name":"Riverside Taxis",
    "wof:placetype":"venue"
},
  "geometry": {"coordinates":[-1.5258840322,54.879070282],"type":"Point"}
}