{
  "type": "Feature",
  "properties": {
    "addr:full":"Slamannan Road Falkirk Falkirk FK1 5LX",
    "addr:postcode":"fk1 5lx",
    "addr:street":"Slamannan Road",
    "iso:country":"GB",
    "sg:address":"Slamannan Road",
    "sg:city":"Falkirk",
    "sg:classifiers":[
        {
            "category":"Real Estate",
            "subcategory":"Real Estate Agent",
            "type":"Services"
        }
    ],
    "sg:postcode":"FK1 5LX",
    "sg:province":"Falkirk",
    "wof:name":"Bell Ingram Ltd.",
    "wof:placetype":"venue"
},
  "geometry": {"coordinates":[-3.7895240784,55.9916343689],"type":"Point"}
}