{
  "type": "Feature",
  "properties": {
    "addr:full":"Heapham Road South Gainsborough Lincolnshire DN21 1XY",
    "addr:postcode":"dn21 1xy",
    "addr:street":"Heapham Road South",
    "iso:country":"GB",
    "sg:address":"Heapham Road South",
    "sg:city":"Gainsborough",
    "sg:classifiers":[
        {
            "category":"Food & Beverages",
            "subcategory":"Supermarket",
            "type":"Retail Goods"
        }
    ],
    "sg:phone":"+44 1427 615522",
    "sg:postcode":"DN21 1XY",
    "sg:province":"Lincolnshire",
    "wof:name":"W M Morrison Supermarkets Plc",
    "wof:placetype":"venue"
},
  "geometry": {"coordinates":[-0.7540839911,53.3949737549],"type":"Point"}
}