{
  "type": "Feature",
  "properties": {
    "iso:country":"GB",
    "sg:address":"1 Goodsway",
    "sg:city":"London",
    "sg:classifiers":[
        {
            "category":"Professional",
            "type":"Services"
        }
    ],
    "sg:phone":"+44 20 7278 5567",
    "sg:postcode":"NW1 1UR",
    "sg:province":"Greater London",
    "sg:tags":[
        "interior",
        "furnishers",
        "designer"
    ],
    "wof:name":"Jam",
    "wof:placetype":"venue"
},
  "geometry": {"coordinates":[-0.1279439926,51.5325813293],"type":"Point"}
}