{
  "type": "Feature",
  "properties": {
    "iso:country":"GB",
    "sg:address":"Spittal Of Glenshee",
    "sg:city":"Blairgowrie",
    "sg:classifiers":[
        {
            "category":"Sports & Exercise",
            "subcategory":"Winter Sports",
            "type":"Entertainment"
        }
    ],
    "sg:phone":"+44 1250 885216",
    "sg:postcode":"PH10 7QE",
    "sg:province":"Perth and Kinross",
    "sg:tags":[
        "skiing"
    ],
    "wof:name":"Glenshee Ski School",
    "wof:placetype":"venue"
},
  "geometry": {"coordinates":[-3.4609310627,56.8141479492],"type":"Point"}
}