{
  "type": "Feature",
  "properties": {
    "addr:full":"32-34 London Road Southampton Hampshire SO15 2TB",
    "addr:housenumber":"32-34",
    "addr:postcode":"so15 2tb",
    "addr:street":"London Road",
    "iso:country":"GB",
    "sg:address":"32-34 London Road",
    "sg:city":"Southampton",
    "sg:classifiers":[
        {
            "category":"Real Estate",
            "subcategory":"Real Estate Agent",
            "type":"Services"
        }
    ],
    "sg:phone":"+44 23 8033 8066",
    "sg:postcode":"SO15 2TB",
    "sg:province":"Hampshire",
    "wof:name":"Fox & Sons (South) Ltd.",
    "wof:placetype":"venue"
},
  "geometry": {"coordinates":[-1.403957963,50.9115638733],"type":"Point"}
}