{
  "type": "Feature",
  "properties": {
    "addr:full":"104 Allerton Rd, Mossley Hill Liverpool Merseyside L18 2DG",
    "addr:housenumber":"104",
    "addr:postcode":"l18 2dg",
    "addr:street":"Allerton Rd",
    "iso:country":"GB",
    "sg:address":"104 Allerton Rd, Mossley Hill",
    "sg:city":"Liverpool",
    "sg:classifiers":[
        {
            "category":"Home & Garden",
            "subcategory":"Household Appliances",
            "type":"Retail Goods"
        }
    ],
    "sg:phone":"+44 151 733 5395",
    "sg:postcode":"L18 2DG",
    "sg:province":"Merseyside",
    "sg:tags":[
        "gas"
    ],
    "wof:name":"British Gas Energy Centre",
    "wof:placetype":"venue"
},
  "geometry": {"coordinates":[-2.9096689224,53.387008667],"type":"Point"}
}