{
  "type": "Feature",
  "properties": {
    "addr:full":"Unit 6 Miners Hill, Brassington Matlock Derbyshire DE4 4HA",
    "addr:housenumber":"unit 6",
    "addr:postcode":"de4 4ha",
    "addr:street":"Miners Hill",
    "iso:country":"GB",
    "sg:address":"Unit 6 Miners Hill, Brassington",
    "sg:city":"Matlock",
    "sg:classifiers":[
        {
            "category":"Building & Trades",
            "subcategory":"Construction",
            "type":"Services"
        }
    ],
    "sg:postcode":"DE4 4HA",
    "sg:province":"Derbyshire",
    "sg:tags":[
        "joinery"
    ],
    "wof:name":"P R Dickinson Joinery Services",
    "wof:placetype":"venue"
},
  "geometry": {"coordinates":[-1.6558829546,53.0855484009],"type":"Point"}
}