{
  "type": "Feature",
  "properties": {
    "iso:country":"GB",
    "sg:address":"Low Thornber, Wigglesworth",
    "sg:city":"Skipton",
    "sg:classifiers":[
        {
            "category":"Farming",
            "subcategory":"Dairy Farm",
            "type":"Manufacturing & Wholesale Goods"
        },
        {
            "category":"Farming",
            "subcategory":"Livestock Farm",
            "type":"Manufacturing & Wholesale Goods"
        }
    ],
    "sg:phone":"+44 1729 850225",
    "sg:postcode":"BD23 4RS",
    "sg:province":"Lancashire",
    "sg:tags":[
        "others",
        "farmer"
    ],
    "wof:name":"J R & M J Moon",
    "wof:placetype":"venue"
},
  "geometry": {"coordinates":[-2.2923328876,54.0078048706],"type":"Point"}
}