{
  "type": "Feature",
  "properties": {
    "addr:full":"5-7 South Street Epsom Surrey KT19 8BH",
    "addr:housenumber":"5-7",
    "addr:postcode":"kt19 8bh",
    "addr:street":"South Street",
    "iso:country":"GB",
    "sg:address":"5-7 South Street",
    "sg:city":"Epsom",
    "sg:classifiers":[
        {
            "category":"Shopping",
            "subcategory":"Musical Instruments",
            "type":"Retail Goods"
        }
    ],
    "sg:postcode":"KT19 8BH",
    "sg:province":"Surrey",
    "sg:tags":[
        "music",
        "sheet"
    ],
    "wof:name":"Bootleg Musical Instruments",
    "wof:placetype":"venue"
},
  "geometry": {"coordinates":[-0.2704890072,51.3326950073],"type":"Point"}
}