{
  "type": "Feature",
  "properties": {
    "addr:full":"23a Station Rd Burgess Hill East Sussex RH15 9DE",
    "addr:housenumber":"23a",
    "addr:postcode":"rh15 9de",
    "addr:street":"Station Rd",
    "iso:country":"GB",
    "sg:address":"23a Station Rd",
    "sg:city":"Burgess Hill",
    "sg:classifiers":[
        {
            "category":"Real Estate",
            "subcategory":"Surveying",
            "type":"Services"
        }
    ],
    "sg:postcode":"RH15 9DE",
    "sg:province":"East Sussex",
    "sg:tags":[
        "surveyor",
        "valuer"
    ],
    "wof:name":"Walter,David A,",
    "wof:placetype":"venue"
},
  "geometry": {"coordinates":[-0.1283400059,50.9543418884],"type":"Point"}
}