{
  "type": "Feature",
  "properties": {
    "addr:full":"Meadoway, Steeple Claydon Buckingham Buckinghamshire MK18 2PA",
    "addr:postcode":"mk18 2pa",
    "addr:street":"Meadoway Steeple",
    "iso:country":"GB",
    "sg:address":"Meadoway, Steeple Claydon",
    "sg:city":"Buckingham",
    "sg:classifiers":[
        {
            "category":"Education",
            "subcategory":"School",
            "type":"Public Place"
        }
    ],
    "sg:postcode":"MK18 2PA",
    "sg:province":"Buckinghamshire",
    "sg:tags":[
        "local",
        "authority"
    ],
    "wof:name":"Allan Shaw Combined School",
    "wof:placetype":"venue"
},
  "geometry": {"coordinates":[-0.9809859991,51.9361572266],"type":"Point"}
}