{
  "type": "Feature",
  "properties": {
    "addr:full":"Warick House, 76 Summer Lane Birmingham West Midlands B19 3NG",
    "addr:housenumber":"76",
    "addr:postcode":"b19 3ng",
    "addr:street":"Summer Lane",
    "iso:country":"GB",
    "sg:address":"Warick House, 76 Summer Lane",
    "sg:city":"Birmingham",
    "sg:classifiers":[
        {
            "category":"Professional",
            "subcategory":"Engineering",
            "type":"Services"
        },
        {
            "category":"Building & Trades",
            "subcategory":"Electrical",
            "type":"Services"
        }
    ],
    "sg:phone":"+44 121 248 1400",
    "sg:postcode":"B19 3NG",
    "sg:province":"West Midlands",
    "sg:tags":[
        "engineer",
        "electrician",
        "contractor"
    ],
    "wof:name":"Countrywide Electrical Services Ltd.",
    "wof:placetype":"venue"
},
  "geometry": {"coordinates":[-1.8989219666,52.491268158],"type":"Point"}
}