{
  "type": "Feature",
  "properties": {
    "addr:full":"22 Burton Road, Withington Manchester Greater Manchester M20 3ED",
    "addr:housenumber":"22",
    "addr:postcode":"m20 3ed",
    "addr:street":"Burton Road",
    "iso:country":"GB",
    "sg:address":"22 Burton Road, Withington",
    "sg:city":"Manchester",
    "sg:classifiers":[
        {
            "category":"Home & Garden",
            "subcategory":"Hardware",
            "type":"Retail Goods"
        }
    ],
    "sg:phone":"+44 161 445 1137",
    "sg:postcode":"M20 3ED",
    "sg:province":"Greater Manchester",
    "sg:tags":[
        "shop",
        "retailer",
        "diy"
    ],
    "wof:name":"P Walsh & Co",
    "wof:placetype":"venue"
},
  "geometry": {"coordinates":[-2.231599,53.433285],"type":"Point"}
}