{
  "type": "Feature",
  "properties": {
    "addr:full":"24 Rectory Road Benfleet Essex SS7 2ND",
    "addr:housenumber":"24",
    "addr:postcode":"ss7 2nd",
    "addr:street":"Rectory Road",
    "iso:country":"GB",
    "sg:address":"24 Rectory Road",
    "sg:city":"Benfleet",
    "sg:classifiers":[
        {
            "category":"Manufacturing",
            "subcategory":"Building Materials",
            "type":"Manufacturing & Wholesale Goods"
        }
    ],
    "sg:phone":"+44 1702 554881",
    "sg:postcode":"SS7 2ND",
    "sg:province":"Essex",
    "sg:tags":[
        "tile",
        "mnfrs"
    ],
    "wof:name":"Hadleigh Tiles & D I Y",
    "wof:placetype":"venue"
},
  "geometry": {"coordinates":[0.610653,51.554035],"type":"Point"}
}