{
  "type": "Feature",
  "properties": {
    "addr:full":"9 East Street, Titchfield Fareham Hampshire PO14 4AD",
    "addr:housenumber":"9",
    "addr:postcode":"po14 4ad",
    "addr:street":"East Street",
    "iso:country":"GB",
    "sg:address":"9 East Street, Titchfield",
    "sg:city":"Fareham",
    "sg:classifiers":[
        {
            "category":"Professional",
            "subcategory":"Management & Consulting",
            "type":"Services"
        }
    ],
    "sg:postcode":"PO14 4AD",
    "sg:province":"Hampshire",
    "sg:tags":[
        "consultant",
        "training"
    ],
    "wof:name":"Harold Straker Communications",
    "wof:placetype":"venue"
},
  "geometry": {"coordinates":[-1.2328909636,50.8506202698],"type":"Point"}
}