{
  "type": "Feature",
  "properties": {
    "addr:full":"28 Thames Road, Milnrow Rochdale Lancashire OL16 3UB",
    "addr:housenumber":"28",
    "addr:postcode":"ol16 3ub",
    "addr:street":"Thames Road;Rochdale",
    "iso:country":"GB",
    "sg:address":"28 Thames Road, Milnrow",
    "sg:city":"Rochdale",
    "sg:classifiers":[
        {
            "category":"Retail",
            "subcategory":"Driving School",
            "type":"Services"
        }
    ],
    "sg:phone":"+44 1706 341785",
    "sg:postcode":"OL16 3UB",
    "sg:province":"Lancashire",
    "wof:name":"Thames School of Motoring",
    "wof:placetype":"venue"
},
  "geometry": {"coordinates":[-2.099424,53.611149],"type":"Point"}
}