{
  "type": "Feature",
  "properties": {
    "addr:full":"3 Milldale Crescent Honiton Devon EX14 1RB",
    "addr:housenumber":"3",
    "addr:postcode":"ex14 1rb",
    "addr:street":"Milldale Crescent",
    "iso:country":"GB",
    "sg:address":"3 Milldale Crescent",
    "sg:city":"Honiton",
    "sg:classifiers":[
        {
            "category":"Building & Trades",
            "subcategory":"Construction",
            "type":"Services"
        }
    ],
    "sg:phone":"+44 1404 42059",
    "sg:postcode":"EX14 1RB",
    "sg:province":"Devon",
    "sg:tags":[
        "glazier"
    ],
    "wof:name":"Max Pulman",
    "wof:placetype":"venue"
},
  "geometry": {"coordinates":[-3.1978199482,50.7954826355],"type":"Point"}
}