{
  "type": "Feature",
  "properties": {
    "iso:country":"GB",
    "sg:address":"78a South Street, Ponders End",
    "sg:city":"Enfield",
    "sg:classifiers":[
        {
            "category":"Manufacturing",
            "subcategory":"Paper Products",
            "type":"Manufacturing & Wholesale Goods"
        }
    ],
    "sg:phone":"+44 20 8804 6764",
    "sg:postcode":"EN3 4LW",
    "sg:province":"Greater London",
    "sg:tags":[
        "merchant",
        "waste"
    ],
    "wof:name":"G & C Wastepaper Co. Ltd.",
    "wof:placetype":"venue"
},
  "geometry": {"coordinates":[-0.041918,51.643757],"type":"Point"}
}