{
  "type": "Feature",
  "properties": {
    "addr:full":"17 Coton Lane, Erdington Birmingham West Midlands B23 6TP",
    "addr:housenumber":"17",
    "addr:postcode":"b23 6tp",
    "addr:street":"Coton Lane",
    "iso:country":"GB",
    "sg:address":"17 Coton Lane, Erdington",
    "sg:city":"Birmingham",
    "sg:classifiers":[
        {
            "category":"Insurance",
            "subcategory":"Insurance Agent",
            "type":"Services"
        }
    ],
    "sg:postcode":"B23 6TP",
    "sg:province":"West Midlands",
    "sg:tags":[
        "broker"
    ],
    "wof:name":"Antelope Insurance Services Ltd.",
    "wof:placetype":"venue"
},
  "geometry": {"coordinates":[-1.842837,52.522984],"type":"Point"}
}