{
  "type": "Feature",
  "properties": {
    "iso:country":"GB",
    "sg:address":"Unit 3, Croydon Street",
    "sg:city":"Leeds",
    "sg:classifiers":[
        {
            "category":"Manufacturing",
            "subcategory":"Metals",
            "type":"Manufacturing & Wholesale Goods"
        }
    ],
    "sg:phone":"+44 113 244 6975",
    "sg:postcode":"LS11 5RT",
    "sg:province":"West Yorkshire",
    "wof:name":"Spartan Metal Polishing Co. Ltd.",
    "wof:placetype":"venue"
},
  "geometry": {"coordinates":[-1.564892,53.788113],"type":"Point"}
}