{
  "type": "Feature",
  "properties": {
    "iso:country":"GB",
    "sg:address":"252 Haydn Rd, Sherwood",
    "sg:city":"Nottingham",
    "sg:classifiers":[
        {
            "category":"Professional",
            "subcategory":"Business Services",
            "type":"Services"
        }
    ],
    "sg:phone":"+44 115 911 6022",
    "sg:postcode":"NG5 2LG",
    "sg:province":"Nottinghamshire",
    "sg:tags":[
        "bookmaker"
    ],
    "wof:name":"Sutherland Bookmakers",
    "wof:placetype":"venue"
},
  "geometry": {"coordinates":[-1.156803,52.979694],"type":"Point"}
}