{
  "type": "Feature",
  "properties": {
    "iso:country":"GB",
    "sg:address":"39 Nicholsons Walk",
    "sg:city":"Maidenhead",
    "sg:classifiers":[
        {
            "category":"Shopping",
            "subcategory":"Comic Books",
            "type":"Retail Goods"
        }
    ],
    "sg:phone":"+44 1628 670164",
    "sg:postcode":"SL6 1LB",
    "sg:province":"Berkshire",
    "sg:tags":[
        "jeweller"
    ],
    "wof:name":"H Samuel",
    "wof:placetype":"venue"
},
  "geometry": {"coordinates":[-0.7235890031,51.5220184326],"type":"Point"}
}