{
  "type": "Feature",
  "properties": {
    "addr:full":"Folly Farm, Manor Farm Estate, North Waltham Basingstoke Hampshire RG25 2BS",
    "addr:housenumber":"estate",
    "addr:postcode":"rg25 2bs",
    "addr:street":"Manor",
    "iso:country":"GB",
    "sg:address":"Folly Farm, Manor Farm Estate, North Waltham",
    "sg:city":"Basingstoke",
    "sg:classifiers":[
        {
            "category":"Home & Garden",
            "subcategory":"Home Furnishings",
            "type":"Retail Goods"
        }
    ],
    "sg:phone":"+44 1256 397983",
    "sg:postcode":"RG25 2BS",
    "sg:province":"Hampshire",
    "sg:tags":[
        "furnishers",
        "planner",
        "kitchen"
    ],
    "wof:name":"Phillip Stx James Joinery",
    "wof:placetype":"venue"
},
  "geometry": {"coordinates":[-1.196104,51.212318],"type":"Point"}
}