{
  "type": "Feature",
  "properties": {
    "iso:country":"GB",
    "sg:address":"30 Mill Street",
    "sg:city":"Macclesfield",
    "sg:classifiers":[
        {
            "category":"Shopping",
            "subcategory":"Baby Store",
            "type":"Retail Goods"
        }
    ],
    "sg:phone":"+44 1625 611552",
    "sg:postcode":"SK11 6LT",
    "sg:province":"Cheshire",
    "sg:tags":[
        "nursery",
        "accessory"
    ],
    "wof:name":"Mothercare Uk",
    "wof:placetype":"venue"
},
  "geometry": {"coordinates":[-2.1258831024,53.2593078613],"type":"Point"}
}