{
  "type": "Feature",
  "properties": {
    "addr:full":"5 Bath Road Swindon Wiltshire SN1 4AS",
    "addr:housenumber":"5",
    "addr:postcode":"sn1 4as",
    "addr:street":"Bath Road",
    "iso:country":"GB",
    "sg:address":"5 Bath Road",
    "sg:city":"Swindon",
    "sg:classifiers":[
        {
            "category":"Food & Beverages",
            "subcategory":"Bakery",
            "type":"Retail Goods"
        }
    ],
    "sg:phone":"+44 1793 484300",
    "sg:postcode":"SN1 4AS",
    "sg:province":"Wiltshire",
    "sg:tags":[
        "pizza"
    ],
    "wof:name":"Pizzaexpress (Soho)",
    "wof:placetype":"venue"
},
  "geometry": {"coordinates":[-1.777236,51.552475],"type":"Point"}
}