{
  "type": "Feature",
  "properties": {
    "iso:country":"GB",
    "sg:address":"43-45 Market St",
    "sg:city":"Aberdeen",
    "sg:classifiers":[
        {
            "category":"Travel",
            "subcategory":"Hotels & Motels",
            "type":"Entertainment"
        }
    ],
    "sg:phone":"+44 1224 582255",
    "sg:postcode":"AB11 5EL",
    "sg:province":"Aberdeen City",
    "wof:name":"Jarvis Aberdeen City Hotel",
    "wof:placetype":"venue"
},
  "geometry": {"coordinates":[-2.096099,57.14579],"type":"Point"}
}