{
  "type": "Feature",
  "properties": {
    "addr:full":"The Sawmills, Frith Street Wigan Lancashire WN5 0XQ",
    "addr:postcode":"wn5 0xq",
    "addr:street":"Frith Street",
    "iso:country":"GB",
    "sg:address":"The Sawmills, Frith Street",
    "sg:city":"Wigan",
    "sg:classifiers":[
        {
            "category":"Shopping",
            "type":"Retail Goods"
        }
    ],
    "sg:phone":"+44 1942 255535",
    "sg:postcode":"WN5 0XQ",
    "sg:province":"Lancashire",
    "sg:tags":[
        "part",
        "accessory"
    ],
    "wof:name":"Coverdale Carpets",
    "wof:placetype":"venue"
},
  "geometry": {"coordinates":[-2.6478600502,53.5437011719],"type":"Point"}
}