{
  "type": "Feature",
  "properties": {
    "addr:full":"64 Espedair Street Paisley East Renfrewshire PA2 6RW",
    "addr:housenumber":"64",
    "addr:postcode":"pa2 6rw",
    "addr:street":"Espedair Street",
    "iso:country":"GB",
    "sg:address":"64 Espedair Street",
    "sg:city":"Paisley",
    "sg:classifiers":[
        {
            "category":"Social Services",
            "type":"Services"
        },
        {
            "category":"Organizations",
            "subcategory":"Community Association",
            "type":"Services"
        }
    ],
    "sg:phone":"+44 141 889 7105",
    "sg:postcode":"PA2 6RW",
    "sg:province":"East Renfrewshire",
    "sg:tags":[
        "housing",
        "disability",
        "co-operatives",
        "society",
        "need",
        "trust",
        "special"
    ],
    "sg:website":"http://www.psha.org.uk",
    "wof:name":"Paisley South Housing Association Ltd",
    "wof:placetype":"venue"
},
  "geometry": {"coordinates":[-4.4217228889,55.8345718384],"type":"Point"}
}