{
  "type": "Feature",
  "properties": {
    "addr:full":"Building 1, The Moorings, Dockings Holt Spalding Cambridgeshire PE12 9HL",
    "addr:postcode":"pe12 9hl",
    "addr:street":"The;Dockings Holt Spalding",
    "iso:country":"GB",
    "sg:address":"Building 1, The Moorings, Dockings Holt",
    "sg:city":"Spalding",
    "sg:classifiers":[
        {
            "category":"Shopping",
            "type":"Retail Goods"
        }
    ],
    "sg:phone":"+44 1406 365663",
    "sg:postcode":"PE12 9HL",
    "sg:province":"Cambridgeshire",
    "sg:tags":[
        "part",
        "accessory"
    ],
    "wof:name":"Long Sutton Motor Spares",
    "wof:placetype":"venue"
},
  "geometry": {"coordinates":[0.118623,52.788265],"type":"Point"}
}