{
  "type": "Feature",
  "properties": {
    "addr:full":"Reading Road Basingstoke Hampshire RG24 8LN",
    "addr:postcode":"rg24 8ln",
    "addr:street":"Reading Road",
    "iso:country":"GB",
    "sg:address":"Reading Road",
    "sg:city":"Basingstoke",
    "sg:classifiers":[
        {
            "category":"Home & Garden",
            "subcategory":"Furniture",
            "type":"Retail Goods"
        }
    ],
    "sg:phone":"+44 1256 469156",
    "sg:postcode":"RG24 8LN",
    "sg:province":"Hampshire",
    "wof:name":"M F I Furniture Centres Ltd.",
    "wof:placetype":"venue"
},
  "geometry": {"coordinates":[-1.073531,51.279404],"type":"Point"}
}