{
  "type": "Feature",
  "properties": {
    "addr:full":"32 Queen Street Maidenhead Berkshire SL6 1JD",
    "addr:housenumber":"32",
    "addr:postcode":"sl6 1jd",
    "addr:street":"Queen Street",
    "iso:country":"GB",
    "sg:address":"32 Queen Street",
    "sg:city":"Maidenhead",
    "sg:classifiers":[
        {
            "category":"Real Estate",
            "subcategory":"Surveying",
            "type":"Services"
        }
    ],
    "sg:postcode":"SL6 1JD",
    "sg:province":"Berkshire",
    "sg:tags":[
        "surveyor",
        "valuer"
    ],
    "wof:name":"Dudley Clifton & Son",
    "wof:placetype":"venue"
},
  "geometry": {"coordinates":[-0.720344007,51.5219841003],"type":"Point"}
}