{
  "type": "Feature",
  "properties": {
    "addr:full":"1 Britannia Road Bedford Bedfordshire MK42 9HD",
    "addr:housenumber":"1",
    "addr:postcode":"mk42 9hd",
    "addr:street":"Britannia Road",
    "iso:country":"GB",
    "sg:address":"1 Britannia Road",
    "sg:city":"Bedford",
    "sg:classifiers":[
        {
            "category":"Bars & Pubs",
            "type":"Food & Drink"
        }
    ],
    "sg:phone":"+44 1234 360649",
    "sg:postcode":"MK42 9HD",
    "sg:province":"Bedfordshire",
    "sg:tags":[
        "pubs",
        "inn"
    ],
    "wof:name":"The Crown",
    "wof:placetype":"venue"
},
  "geometry": {"coordinates":[-0.471149,52.12923],"type":"Point"}
}