{
  "type": "Feature",
  "properties": {
    "addr:full":"32 Shaw Lane Markfield Leicestershire LE67 9PU",
    "addr:housenumber":"32",
    "addr:postcode":"le67 9pu",
    "addr:street":"Shaw Lane",
    "iso:country":"GB",
    "sg:address":"32 Shaw Lane",
    "sg:city":"Markfield",
    "sg:classifiers":[
        {
            "category":"Autos & Motor Vehicles",
            "subcategory":"Fuel & Gas Station",
            "type":"Retail Goods"
        }
    ],
    "sg:phone":"+44 1530 249849",
    "sg:postcode":"LE67 9PU",
    "sg:province":"Leicestershire",
    "sg:tags":[
        "petrol",
        "filling"
    ],
    "wof:name":"Browns Blue Service Station",
    "wof:placetype":"venue"
},
  "geometry": {"coordinates":[-1.3117959499,52.7015724182],"type":"Point"}
}