{
  "type": "Feature",
  "properties": {
    "addr:full":"Cross O'th Hill Malpas Cheshire SY14 8DH",
    "addr:postcode":"sy14 8dh",
    "addr:street":"Cheshire",
    "iso:country":"GB",
    "sg:address":"Cross O'th Hill",
    "sg:city":"Malpas",
    "sg:classifiers":[
        {
            "category":"Communications",
            "subcategory":"Film & Video Production",
            "type":"Services"
        },
        {
            "category":"Food & Beverages",
            "subcategory":"Specialty",
            "type":"Retail Goods"
        }
    ],
    "sg:phone":"+44 1948 860213",
    "sg:postcode":"SY14 8DH",
    "sg:province":"Cheshire",
    "sg:tags":[
        "organic",
        "supply"
    ],
    "wof:name":"Oakcroft Organic Gardens",
    "wof:placetype":"venue"
},
  "geometry": {"coordinates":[-2.7448499203,53.0239715576],"type":"Point"}
}