{
  "type": "Feature",
  "properties": {
    "addr:full":"103 St Mary Street Southampton Hampshire SO14 1PF",
    "addr:housenumber":"103",
    "addr:postcode":"so14 1pf",
    "addr:street":"St Mary Street",
    "iso:country":"GB",
    "sg:address":"103 St Mary Street",
    "sg:city":"Southampton",
    "sg:classifiers":[
        {
            "category":"Shopping",
            "subcategory":"Books",
            "type":"Retail Goods"
        }
    ],
    "sg:phone":"+44 23 8063 2257",
    "sg:postcode":"SO14 1PF",
    "sg:province":"Hampshire",
    "sg:tags":[
        "bookseller"
    ],
    "wof:name":"The Private Lines",
    "wof:placetype":"venue"
},
  "geometry": {"coordinates":[-1.396759,50.905708],"type":"Point"}
}