{
  "type": "Feature",
  "properties": {
    "iso:country":"GB",
    "sg:address":"25 Commercial Road",
    "sg:city":"Swindon",
    "sg:classifiers":[
        {
            "category":"Banks & Credit Unions",
            "subcategory":"Bank",
            "type":"Services"
        }
    ],
    "sg:phone":"+44 1793 511570",
    "sg:postcode":"SN1 5NS",
    "sg:province":"Wiltshire",
    "sg:tags":[
        "broker",
        "mortgage"
    ],
    "wof:name":"W Crowley",
    "wof:placetype":"venue"
},
  "geometry": {"coordinates":[-1.784084,51.558655],"type":"Point"}
}