{
  "type": "Feature",
  "properties": {
    "addr:full":"P O Box 69 Malvern Herefordshire WR14 3YU",
    "addr:housenumber":"box 69",
    "addr:postcode":"wr14 3yu",
    "addr:street":"P O",
    "iso:country":"GB",
    "sg:address":"P O Box 69",
    "sg:city":"Malvern",
    "sg:classifiers":[
        {
            "category":"Professional",
            "subcategory":"Accounting & Tax Preparation",
            "type":"Services"
        },
        {
            "category":"Professional",
            "subcategory":"Credit Reporting & Collection",
            "type":"Services"
        }
    ],
    "sg:phone":"+44 1684 893686",
    "sg:postcode":"WR14 3YU",
    "sg:province":"Herefordshire",
    "sg:tags":[
        "collecting",
        "accountant",
        "agency"
    ],
    "wof:name":"Abbey Legal Services",
    "wof:placetype":"venue"
},
  "geometry": {"coordinates":[-2.3100800514,52.104221344],"type":"Point"}
}