{
  "type": "Feature",
  "properties": {
    "iso:country":"GB",
    "sg:address":"The Hoading Bay, Poppleton Hill, Engine Lane",
    "sg:city":"Wakefield",
    "sg:classifiers":[
        {
            "category":"Building & Trades",
            "subcategory":"Cleaning & Sanitation",
            "type":"Services"
        }
    ],
    "sg:phone":"+44 1924 265844",
    "sg:postcode":"WF4 5NH",
    "sg:province":"West Yorkshire",
    "sg:tags":[
        "blast"
    ],
    "wof:name":"Phoenix Cars & Commercials Ltd.",
    "wof:placetype":"venue"
},
  "geometry": {"coordinates":[-1.56685,53.657791],"type":"Point"}
}