{
  "type": "Feature",
  "properties": {
    "addr:full":"68 Margravine Gardens, Barrons Court London Greater London W6 8RJ",
    "addr:housenumber":"68",
    "addr:postcode":"w6 8rj",
    "addr:street":"Margravine Gardens Barrons Court",
    "iso:country":"GB",
    "sg:address":"68 Margravine Gardens, Barrons Court",
    "sg:city":"London",
    "sg:classifiers":[
        {
            "category":"Professional",
            "subcategory":"Accounting & Tax Preparation",
            "type":"Services"
        }
    ],
    "sg:postcode":"W6 8RJ",
    "sg:province":"Greater London",
    "sg:tags":[
        "accountant"
    ],
    "wof:name":"Seagram Advisers Ltd",
    "wof:placetype":"venue"
},
  "geometry": {"coordinates":[-0.2184789926,51.489692688],"type":"Point"}
}