{
  "type": "Feature",
  "properties": {
    "iso:country":"GB",
    "sg:address":"Bushey Hall Drive",
    "sg:city":"Bushey",
    "sg:classifiers":[
        {
            "category":"Shopping",
            "subcategory":"Stationery & Office Supplies",
            "type":"Retail Goods"
        }
    ],
    "sg:phone":"+44 1923 241862",
    "sg:postcode":"WD23 2QF",
    "sg:province":"Hertfordshire",
    "sg:tags":[
        "printers'"
    ],
    "wof:name":"Inplant Print Supplies Ltd.",
    "wof:placetype":"venue"
},
  "geometry": {"coordinates":[-0.3754040003,51.6546707153],"type":"Point"}
}