{
  "type": "Feature",
  "properties": {
    "addr:full":"Higher Shaftesbury Road Blandford Forum Dorset DT11 8ST",
    "addr:postcode":"dt11 8st",
    "addr:street":"Shaftesbury Road",
    "iso:country":"GB",
    "sg:address":"Higher Shaftesbury Road",
    "sg:city":"Blandford Forum",
    "sg:classifiers":[
        {
            "category":"Manufacturing",
            "subcategory":"Tools & Machinery",
            "type":"Manufacturing & Wholesale Goods"
        }
    ],
    "sg:phone":"+44 1258 454220",
    "sg:postcode":"DT11 8ST",
    "sg:province":"Dorset",
    "wof:name":"Blandford Tools Ltd.",
    "wof:placetype":"venue"
},
  "geometry": {"coordinates":[-2.158749,50.907349],"type":"Point"}
}