{
  "type": "Feature",
  "properties": {
    "addr:full":"93 Flemming Avenue Leigh-on-sea Essex SS9 3AU",
    "addr:housenumber":"93",
    "addr:postcode":"ss9 3au",
    "addr:street":"Flemming Avenue",
    "iso:country":"GB",
    "sg:address":"93 Flemming Avenue",
    "sg:city":"Leigh-on-sea",
    "sg:classifiers":[
        {
            "category":"Building & Trades",
            "subcategory":"Construction",
            "type":"Services"
        }
    ],
    "sg:phone":"+44 1702 475574",
    "sg:postcode":"SS9 3AU",
    "sg:province":"Essex",
    "sg:tags":[
        "valve"
    ],
    "wof:name":"Kingland",
    "wof:placetype":"venue"
},
  "geometry": {"coordinates":[0.6489340067,51.5531463623],"type":"Point"}
}