{
  "type": "Feature",
  "properties": {
    "addr:full":"7 Carlton Avenue Greenhithe Kent DA9 9DR",
    "addr:housenumber":"7",
    "addr:postcode":"da9 9dr",
    "addr:street":"Carlton Avenue",
    "iso:country":"GB",
    "sg:address":"7 Carlton Avenue",
    "sg:city":"Greenhithe",
    "sg:classifiers":[
        {
            "category":"Building & Trades",
            "subcategory":"Landscaping Services",
            "type":"Services"
        },
        {
            "category":"Retail",
            "subcategory":"Repair Shop",
            "type":"Services"
        },
        {
            "category":"Building & Trades",
            "subcategory":"Construction",
            "type":"Services"
        }
    ],
    "sg:phone":"+44 1322 386381",
    "sg:postcode":"DA9 9DR",
    "sg:province":"Kent",
    "sg:tags":[
        "builder",
        "landscape",
        "maintenance",
        "contractor"
    ],
    "wof:name":"Duncans & Co",
    "wof:placetype":"venue"
},
  "geometry": {"coordinates":[0.262831986,51.4456596375],"type":"Point"}
}