{
  "type": "Feature",
  "properties": {
    "iso:country":"GB",
    "sg:address":"Unit 3 Daniel Business Park, Llanddaniel",
    "sg:city":"Gaerwen",
    "sg:classifiers":[
        {
            "category":"Shopping",
            "subcategory":"Discount & Variety Stores",
            "type":"Retail Goods"
        }
    ],
    "sg:phone":"+44 1248 422111",
    "sg:postcode":"LL60 6EE",
    "sg:province":"Isle of Anglesey",
    "sg:tags":[
        "cleaning",
        "supply"
    ],
    "wof:name":"D L S Wholesale Ltd.",
    "wof:placetype":"venue"
},
  "geometry": {"coordinates":[-4.2764987946,53.2228240967],"type":"Point"}
}