{
  "type": "Feature",
  "properties": {
    "addr:full":"1a The Babbages Barnstaple Devon EX31 2LL",
    "addr:housenumber":"1a",
    "addr:postcode":"ex31 2ll",
    "addr:street":"The Babbages",
    "iso:country":"GB",
    "sg:address":"1a The Babbages",
    "sg:city":"Barnstaple",
    "sg:classifiers":[
        {
            "category":"Shopping",
            "subcategory":"Department Store",
            "type":"Retail Goods"
        }
    ],
    "sg:phone":"+44 1271 326080",
    "sg:postcode":"EX31 2LL",
    "sg:province":"Devon",
    "wof:name":"Bickington General Stores & Post Office",
    "wof:placetype":"venue"
},
  "geometry": {"coordinates":[-4.0991940498,51.0735588074],"type":"Point"}
}