{
  "type": "Feature",
  "properties": {
    "iso:country":"GB",
    "sg:address":"Elmdene, 106 Shutt Lane",
    "sg:city":"Solihull",
    "sg:classifiers":[
        {
            "category":"Professional",
            "subcategory":"Accounting & Tax Preparation",
            "type":"Services"
        }
    ],
    "sg:postcode":"B94 6DA",
    "sg:province":"Warwickshire",
    "sg:tags":[
        "accountant"
    ],
    "wof:name":"M T  Manley & Co.  Ltd.",
    "wof:placetype":"venue"
},
  "geometry": {"coordinates":[-1.828780055,52.365070343],"type":"Point"}
}