{
  "type": "Feature",
  "properties": {
    "addr:full":"Cwmyrhiewdre, Dolfor Newtown Powys SY16 4BW",
    "addr:postcode":"sy16 4bw",
    "addr:street":"Dolfor",
    "iso:country":"GB",
    "sg:address":"Cwmyrhiewdre, Dolfor",
    "sg:city":"Newtown",
    "sg:classifiers":[
        {
            "category":"Farming",
            "subcategory":"Farm",
            "type":"Manufacturing & Wholesale Goods"
        }
    ],
    "sg:phone":"+44 1686 626835",
    "sg:postcode":"SY16 4BW",
    "sg:province":"Powys",
    "sg:tags":[
        "mixed",
        "crop"
    ],
    "wof:name":"W G & A Vaughan",
    "wof:placetype":"venue"
},
  "geometry": {"coordinates":[-3.317497,52.473904],"type":"Point"}
}