{
  "type": "Feature",
  "properties": {
    "addr:full":"Unit 1 Fishburn Industrial Estate, Fishburn Stockton-on-tees Durham TS21 4AJ",
    "addr:housenumber":"unit 1",
    "addr:postcode":"ts21 4aj",
    "addr:street":"Industrial Estate",
    "iso:country":"GB",
    "sg:address":"Unit 1 Fishburn Industrial Estate, Fishburn",
    "sg:city":"Stockton-on-tees",
    "sg:classifiers":[
        {
            "category":"Communications",
            "subcategory":"Film & Video Production",
            "type":"Services"
        }
    ],
    "sg:phone":"+44 1740 620646",
    "sg:postcode":"TS21 4AJ",
    "sg:province":"Durham",
    "sg:tags":[
        "mnfr",
        "coating",
        "powder"
    ],
    "wof:name":"R & D Baker",
    "wof:placetype":"venue"
},
  "geometry": {"coordinates":[-1.4422990084,54.6831817627],"type":"Point"}
}