{
  "type": "Feature",
  "properties": {
    "addr:full":"3b & C Castle Close Industrial Estate Crook Durham DL15 8LU",
    "addr:postcode":"dl15 8lu",
    "addr:street":"Castle Close Industrial Estate",
    "iso:country":"GB",
    "sg:address":"3b & C Castle Close Industrial Estate",
    "sg:city":"Crook",
    "sg:classifiers":[
        {
            "category":"Retail",
            "subcategory":"Auto Repair",
            "type":"Services"
        }
    ],
    "sg:phone":"+44 7970 228426",
    "sg:postcode":"DL15 8LU",
    "sg:province":"Durham",
    "sg:tags":[
        "engine",
        "specialist",
        "garage",
        "modification",
        "car"
    ],
    "wof:name":"Car Van Truck & Bus Diesel Engine Services",
    "wof:placetype":"venue"
},
  "geometry": {"coordinates":[-1.7506300211,54.7090797424],"type":"Point"}
}