{
  "type": "Feature",
  "properties": {
    "addr:full":"Shawfield Farm, Shaw Lane Harrogate North Yorkshire HG3 1RA",
    "addr:postcode":"hg3 1ra",
    "addr:street":"Shawfield;Shaw Lane",
    "iso:country":"GB",
    "sg:address":"Shawfield Farm, Shaw Lane",
    "sg:city":"Harrogate",
    "sg:classifiers":[
        {
            "category":"Professional",
            "type":"Services"
        }
    ],
    "sg:postcode":"HG3 1RA",
    "sg:province":"North Yorkshire",
    "sg:tags":[
        "writer"
    ],
    "wof:name":"Shawfield Motors",
    "wof:placetype":"venue"
},
  "geometry": {"coordinates":[-1.5921100378,53.9673500061],"type":"Point"}
}