{
  "type": "Feature",
  "properties": {
    "addr:full":"Drumlan Hall Farm, Newton Lane, Tattenhall Chester Cheshire CH3 9NE",
    "addr:postcode":"ch3 9ne",
    "addr:street":"Newton Lane",
    "iso:country":"GB",
    "sg:address":"Drumlan Hall Farm, Newton Lane, Tattenhall",
    "sg:city":"Chester",
    "sg:classifiers":[
        {
            "category":"Farming",
            "subcategory":"Dairy Farm",
            "type":"Manufacturing & Wholesale Goods"
        },
        {
            "category":"Farming",
            "subcategory":"Livestock Farm",
            "type":"Manufacturing & Wholesale Goods"
        }
    ],
    "sg:phone":"+44 1829 771161",
    "sg:postcode":"CH3 9NE",
    "sg:province":"Cheshire",
    "sg:tags":[
        "others"
    ],
    "wof:name":"T L & M A Fell",
    "wof:placetype":"venue"
},
  "geometry": {"coordinates":[-2.772879,53.119156],"type":"Point"}
}