{
  "type": "Feature",
  "properties": {
    "addr:full":", Fulham Fulham Greater London SW6 1QJ",
    "addr:postcode":"sw6 1qj",
    "iso:country":"GB",
    "sg:address":", Fulham",
    "sg:city":"Fulham",
    "sg:classifiers":[
        {
            "category":"Building & Trades",
            "subcategory":"Cleaning & Sanitation",
            "type":"Services"
        }
    ],
    "sg:phone":"+44 20 7381 0334",
    "sg:postcode":"SW6 1QJ",
    "sg:province":"Greater London",
    "sg:tags":[
        "commercial"
    ],
    "wof:name":"Silver Clean Machine Ltd",
    "wof:placetype":"venue"
},
  "geometry": {"coordinates":[-0.197319001,51.4804153442],"type":"Point"}
}