{
  "type": "Feature",
  "properties": {
    "iso:country":"GB",
    "sg:address":"15 Lead Lane",
    "sg:city":"Ripon",
    "sg:classifiers":[
        {
            "category":"Government",
            "subcategory":"Post Office",
            "type":"Public Place"
        }
    ],
    "sg:phone":"+44 1765 603546",
    "sg:postcode":"HG4 2PF",
    "sg:province":"North Yorkshire",
    "wof:name":"Lead Lane Post Office",
    "wof:placetype":"venue"
},
  "geometry": {"coordinates":[-1.5276939869,54.1259918213],"type":"Point"}
}