{
  "type": "Feature",
  "properties": {
    "addr:full":"62 Kennarck St Leicester Leicestershire LE4 9HR",
    "addr:housenumber":"62",
    "addr:postcode":"le4 9hr",
    "addr:street":"Kennarck St",
    "iso:country":"GB",
    "sg:address":"62 Kennarck St",
    "sg:city":"Leicester",
    "sg:classifiers":[
        {
            "category":"Manufacturing",
            "subcategory":"Rubber & Plastics",
            "type":"Manufacturing & Wholesale Goods"
        }
    ],
    "sg:phone":"+44 116 251 1245",
    "sg:postcode":"LE4 9HR",
    "sg:province":"Leicestershire",
    "sg:tags":[
        "injection",
        "moulding"
    ],
    "wof:name":"Ash Polyurethane Moulders",
    "wof:placetype":"venue"
},
  "geometry": {"coordinates":[-1.0803699493,52.6630897522],"type":"Point"}
}