{
  "type": "Feature",
  "properties": {
    "addr:full":"Hasler House, High St Dunmow Essex CM6 1AP",
    "addr:postcode":"cm6 1ap",
    "addr:street":"High St",
    "iso:country":"GB",
    "sg:address":"Hasler House, High St",
    "sg:city":"Dunmow",
    "sg:classifiers":[
        {
            "category":"Professional",
            "subcategory":"Engineering",
            "type":"Services"
        }
    ],
    "sg:phone":"+44 1371 876274",
    "sg:postcode":"CM6 1AP",
    "sg:province":"Essex",
    "sg:tags":[
        "contractor",
        "electrical",
        "engineer"
    ],
    "wof:name":"MPA Electrical",
    "wof:placetype":"venue"
},
  "geometry": {"coordinates":[0.36284,51.872463],"type":"Point"}
}