{
  "type": "Feature",
  "properties": {
    "addr:full":"Mac Ho, Abbey St Market Harborough Leicestershire LE16 9AA",
    "addr:postcode":"le16 9aa",
    "addr:street":"Abbey",
    "iso:country":"GB",
    "sg:address":"Mac Ho, Abbey St",
    "sg:city":"Market Harborough",
    "sg:classifiers":[
        {
            "category":"Professional",
            "subcategory":"Advertising",
            "type":"Services"
        }
    ],
    "sg:phone":"+44 1858 466441",
    "sg:postcode":"LE16 9AA",
    "sg:province":"Leicestershire",
    "sg:tags":[
        "agency"
    ],
    "wof:name":"McIntosh,Noel,",
    "wof:placetype":"venue"
},
  "geometry": {"coordinates":[-0.922579,52.479397],"type":"Point"}
}