{
  "type": "Feature",
  "properties": {
    "addr:full":"High Park Works, Ballast Quay Road Singringhoe Colchester Essex CO5 7DB",
    "addr:postcode":"co5 7db",
    "addr:street":"Ballast Quay Road Singringhoe Colchester",
    "iso:country":"GB",
    "sg:address":"High Park Works, Ballast Quay Road Singringhoe",
    "sg:city":"Colchester",
    "sg:classifiers":[
        {
            "category":"Professional",
            "subcategory":"Engineering",
            "type":"Services"
        }
    ],
    "sg:phone":"+44 1206 729227",
    "sg:postcode":"CO5 7DB",
    "sg:province":"Essex",
    "wof:name":"Chris Rowe Engineering",
    "wof:placetype":"venue"
},
  "geometry": {"coordinates":[0.948655,51.85672],"type":"Point"}
}