{
  "type": "Feature",
  "properties": {
    "addr:full":"50 Rivers Street Bath Bath and North East Somerset BA1 2QA",
    "addr:housenumber":"50",
    "addr:postcode":"ba1 2qa",
    "addr:street":"Rivers Street",
    "iso:country":"GB",
    "sg:address":"50 Rivers Street",
    "sg:city":"Bath",
    "sg:classifiers":[
        {
            "category":"Bars & Pubs",
            "type":"Food & Drink"
        },
        {
            "category":"Community Center",
            "subcategory":"Social",
            "type":"Public Place"
        }
    ],
    "sg:phone":"+44 1225 360017",
    "sg:postcode":"BA1 2QA",
    "sg:province":"Bath and North East Somerset",
    "sg:tags":[
        "pubs",
        "house",
        "inn",
        "activity"
    ],
    "wof:name":"The Chequers Inn",
    "wof:placetype":"venue"
},
  "geometry": {"coordinates":[-2.365023,51.387535],"type":"Point"}
}