{
  "type": "Feature",
  "properties": {
    "addr:full":"Valley View, Beverley Road, Blacko Nelson Lancashire BB9 6LX",
    "addr:postcode":"bb9 6lx",
    "addr:street":"Valley View Beverley Road",
    "iso:country":"GB",
    "sg:address":"Valley View, Beverley Road, Blacko",
    "sg:city":"Nelson",
    "sg:classifiers":[
        {
            "category":"Professional",
            "subcategory":"Accounting & Tax Preparation",
            "type":"Services"
        }
    ],
    "sg:phone":"+44 1282 612440",
    "sg:postcode":"BB9 6LX",
    "sg:province":"Lancashire",
    "sg:tags":[
        "payroll"
    ],
    "wof:name":"Datapaye Information Systems Ltd",
    "wof:placetype":"venue"
},
  "geometry": {"coordinates":[-2.214138031,53.8668251038],"type":"Point"}
}