{
  "type": "Feature",
  "properties": {
    "iso:country":"GB",
    "sg:address":"77-79 Great Eastern Street",
    "sg:city":"London",
    "sg:classifiers":[
        {
            "category":"Recreation",
            "subcategory":"Gun Range",
            "type":"Entertainment"
        }
    ],
    "sg:phone":"+44 20 7739 5415",
    "sg:postcode":"EC2A 3HU",
    "sg:province":"Greater London",
    "sg:tags":[
        "operator",
        "tour"
    ],
    "wof:name":"Windstar Cruises",
    "wof:placetype":"venue"
},
  "geometry": {"coordinates":[-0.08237,51.525391],"type":"Point"}
}