{
  "type": "Feature",
  "properties": {
    "addr:full":"The Clinic, Hants Lane Ormskirk Lancashire L39 1PX",
    "addr:postcode":"l39 1px",
    "addr:street":"Hants Lane",
    "iso:country":"GB",
    "sg:address":"The Clinic, Hants Lane",
    "sg:city":"Ormskirk",
    "sg:classifiers":[
        {
            "category":"Health Services",
            "subcategory":"Nursing And Care Facility",
            "type":"Services"
        }
    ],
    "sg:phone":"+44 1695 570579",
    "sg:postcode":"L39 1PX",
    "sg:province":"Lancashire",
    "sg:tags":[
        "home"
    ],
    "wof:name":"District Nurses",
    "wof:placetype":"venue"
},
  "geometry": {"coordinates":[-2.886300087,53.5662765503],"type":"Point"}
}