{
  "type": "Feature",
  "properties": {
    "addr:full":"14 Bishopsmead Parade, East Horsley Leatherhead Surrey KT24 6RT",
    "addr:housenumber":"14",
    "addr:postcode":"kt24 6rt",
    "addr:street":"Bishopsmead Parade",
    "iso:country":"GB",
    "sg:address":"14 Bishopsmead Parade, East Horsley",
    "sg:city":"Leatherhead",
    "sg:classifiers":[
        {
            "category":"Professional",
            "type":"Services"
        }
    ],
    "sg:phone":"+44 1483 285122",
    "sg:postcode":"KT24 6RT",
    "sg:province":"Surrey",
    "sg:tags":[
        "interior",
        "furnishers",
        "designer"
    ],
    "wof:name":"The Interior",
    "wof:placetype":"venue"
},
  "geometry": {"coordinates":[-0.43216,51.26524],"type":"Point"}
}