{
  "type": "Feature",
  "properties": {
    "addr:full":"24 Eastbury Avenue Northwood Greater London HA6 3LN",
    "addr:housenumber":"24",
    "addr:postcode":"ha6 3ln",
    "addr:street":"Eastbury Avenue",
    "iso:country":"GB",
    "sg:address":"24 Eastbury Avenue",
    "sg:city":"Northwood",
    "sg:classifiers":[
        {
            "category":"Health Services",
            "subcategory":"Nursing And Care Facility",
            "type":"Services"
        }
    ],
    "sg:phone":"+44 1923 826807",
    "sg:postcode":"HA6 3LN",
    "sg:province":"Greater London",
    "sg:tags":[
        "home"
    ],
    "wof:name":"Northwood Nursing Home",
    "wof:placetype":"venue"
},
  "geometry": {"coordinates":[-0.41644,51.617115],"type":"Point"}
}