{
  "type": "Feature",
  "properties": {
    "addr:full":"2 Seaward Ho, The Parade, Parkgate Ellesmere Port Cheshire CH64 6SA",
    "addr:housenumber":"2",
    "addr:postcode":"ch64 6sa",
    "addr:street":"Seaward Ho The Parade Parkgate",
    "iso:country":"GB",
    "sg:address":"2 Seaward Ho, The Parade, Parkgate",
    "sg:city":"Ellesmere Port",
    "sg:classifiers":[
        {
            "category":"Professional",
            "subcategory":"Art Services",
            "type":"Services"
        }
    ],
    "sg:phone":"+44 151 353 1709",
    "sg:postcode":"CH64 6SA",
    "sg:province":"Cheshire",
    "sg:tags":[
        "graphic",
        "designer"
    ],
    "wof:name":"Deeside Marketing Ltd",
    "wof:placetype":"venue"
},
  "geometry": {"coordinates":[-3.0855491161,53.2978096008],"type":"Point"}
}