{
  "type": "Feature",
  "properties": {
    "addr:full":"6 Egerton Dr Greenwich Greater London SE10 8JS",
    "addr:housenumber":"6",
    "addr:postcode":"se10 8js",
    "addr:street":"Egerton Dr",
    "iso:country":"GB",
    "sg:address":"6 Egerton Dr",
    "sg:city":"Greenwich",
    "sg:classifiers":[
        {
            "category":"Professional",
            "type":"Services"
        }
    ],
    "sg:phone":"+44 20 8265 2567",
    "sg:postcode":"SE10 8JS",
    "sg:province":"Greater London",
    "sg:tags":[
        "entertainer"
    ],
    "wof:name":"Punch & Judy Magic",
    "wof:placetype":"venue"
},
  "geometry": {"coordinates":[-0.0179820005,51.4742431641],"type":"Point"}
}