{
  "type": "Feature",
  "properties": {
    "addr:full":"101 Middleton Park Rd Leeds West Yorkshire LS10 4LS",
    "addr:housenumber":"101",
    "addr:postcode":"ls10 4ls",
    "addr:street":"Middleton Park Rd",
    "iso:country":"GB",
    "sg:address":"101 Middleton Park Rd",
    "sg:city":"Leeds",
    "sg:classifiers":[
        {
            "category":"Manufacturing",
            "subcategory":"Tools & Machinery",
            "type":"Manufacturing & Wholesale Goods"
        }
    ],
    "sg:phone":"+44 113 271 7744",
    "sg:postcode":"LS10 4LS",
    "sg:province":"West Yorkshire",
    "sg:tags":[
        "society",
        "friendly"
    ],
    "wof:name":"Hill House Hammond Ltd",
    "wof:placetype":"venue"
},
  "geometry": {"coordinates":[-1.549071,53.748161],"type":"Point"}
}