{
  "type": "Feature",
  "properties": {
    "iso:country":"GB",
    "sg:address":"3 Welfare Crescent South, South Hetton",
    "sg:city":"Durham",
    "sg:classifiers":[
        {
            "category":"Food & Beverages",
            "subcategory":"Meat & Fish",
            "type":"Retail Goods"
        }
    ],
    "sg:postcode":"DH6 2RN",
    "sg:province":"Durham",
    "sg:tags":[
        "butcher"
    ],
    "wof:name":"Hall,S G,",
    "wof:placetype":"venue"
},
  "geometry": {"coordinates":[-1.399054,54.797459],"type":"Point"}
}