{
  "type": "Feature",
  "properties": {
    "addr:full":"112/114 Great Portland St London Greater London W1W 6PH",
    "addr:housenumber":"112 / 114",
    "addr:postcode":"w1w 6ph",
    "addr:street":"Great Portland St",
    "iso:country":"GB",
    "sg:address":"112/114 Great Portland St",
    "sg:city":"London",
    "sg:classifiers":[
        {
            "category":"Shopping",
            "subcategory":"Books",
            "type":"Retail Goods"
        },
        {
            "category":"Wholesale",
            "subcategory":"Books, Periodicals, & Newspapers",
            "type":"Manufacturing & Wholesale Goods"
        }
    ],
    "sg:postcode":"W1W 6PH",
    "sg:province":"Greater London",
    "sg:tags":[
        "publishing"
    ],
    "wof:name":"European Publishing Ltd",
    "wof:placetype":"venue"
},
  "geometry": {"coordinates":[-0.1422020048,51.519443512],"type":"Point"}
}