{
  "type": "Feature",
  "properties": {
    "iso:country":"GB",
    "sg:address":"South Point House, Harcourt Way",
    "sg:city":"Leicester",
    "sg:classifiers":[
        {
            "category":"Insurance",
            "subcategory":"Insurance Agent",
            "type":"Services"
        }
    ],
    "sg:phone":"+44 116 282 7667",
    "sg:postcode":"LE3 2WN",
    "sg:province":"Leicestershire",
    "wof:name":"The Scottish Amicable Life Assurance Society",
    "wof:placetype":"venue"
},
  "geometry": {"coordinates":[-1.1900290251,52.6017341614],"type":"Point"}
}