{
  "type": "Feature",
  "properties": {
    "iso:country":"GB",
    "sg:address":"Unit 4, Brook St East",
    "sg:city":"Ashton-under-lyne",
    "sg:classifiers":[
        {
            "category":"Shopping",
            "subcategory":"Clothing, Apparel, & Fashions",
            "type":"Retail Goods"
        },
        {
            "category":"Home & Garden",
            "subcategory":"Hardware",
            "type":"Retail Goods"
        }
    ],
    "sg:phone":"+44 161 339 5560",
    "sg:postcode":"OL6 7SU",
    "sg:province":"Greater Manchester",
    "sg:tags":[
        "device",
        "fixing",
        "fastener",
        "haberdasher"
    ],
    "wof:name":"B V S Fasteners Ltd",
    "wof:placetype":"venue"
},
  "geometry": {"coordinates":[-2.101891,53.486465],"type":"Point"}
}