{
  "type": "Feature",
  "properties": {
    "addr:full":"86 Firbeck Road, Wollaton Nottingham Nottinghamshire NG8 2FB",
    "addr:housenumber":"86",
    "addr:postcode":"ng8 2fb",
    "addr:street":"Firbeck Road",
    "iso:country":"GB",
    "sg:address":"86 Firbeck Road, Wollaton",
    "sg:city":"Nottingham",
    "sg:classifiers":[
        {
            "category":"Personal",
            "type":"Services"
        }
    ],
    "sg:phone":"+44 115 928 7532",
    "sg:postcode":"NG8 2FB",
    "sg:province":"Nottinghamshire",
    "sg:tags":[
        "kiss-o-grams"
    ],
    "wof:name":"Fantasy Kissograms",
    "wof:placetype":"venue"
},
  "geometry": {"coordinates":[-1.2385549545,52.952709198],"type":"Point"}
}