{
  "type": "Feature",
  "properties": {
    "iso:country":"GB",
    "sg:address":"Venture House, Crofton Road",
    "sg:city":"Lincoln",
    "sg:classifiers":[
        {
            "category":"Professional",
            "subcategory":"Employment Agencies",
            "type":"Services"
        }
    ],
    "sg:phone":"+44 1522 567300",
    "sg:postcode":"LN3 4NL",
    "sg:province":"Lincolnshire",
    "sg:tags":[
        "consultant"
    ],
    "wof:name":"Euronational & Technical Ltd.",
    "wof:placetype":"venue"
},
  "geometry": {"coordinates":[-0.506474,53.232368],"type":"Point"}
}