{
  "type": "Feature",
  "properties": {
    "addr:full":"22 Easington Rd Ware Hertfordshire SG12 0LX",
    "addr:housenumber":"22",
    "addr:postcode":"sg12 0lx",
    "addr:street":"Easington Rd",
    "iso:country":"GB",
    "sg:address":"22 Easington Rd",
    "sg:city":"Ware",
    "sg:classifiers":[
        {
            "category":"Shopping",
            "subcategory":"Clothing, Apparel, & Fashions",
            "type":"Retail Goods"
        }
    ],
    "sg:phone":"+44 1992 582363",
    "sg:postcode":"SG12 0LX",
    "sg:province":"Hertfordshire",
    "sg:tags":[
        "dresswear"
    ],
    "wof:name":"Belle Robe At Gravesons",
    "wof:placetype":"venue"
},
  "geometry": {"coordinates":[-0.06576,51.876259],"type":"Point"}
}