{
  "type": "Feature",
  "properties": {
    "addr:full":"34 Pulteney Rd Bath Somerset BA2 4EZ",
    "addr:housenumber":"34",
    "addr:postcode":"ba2 4ez",
    "addr:street":"Pulteney Rd",
    "iso:country":"GB",
    "sg:address":"34 Pulteney Rd",
    "sg:city":"Bath",
    "sg:classifiers":[
        {
            "category":"Organizations",
            "subcategory":"Religious Organization",
            "type":"Services"
        }
    ],
    "sg:phone":"+44 1225 469405",
    "sg:postcode":"BA2 4EZ",
    "sg:province":"Somerset",
    "sg:tags":[
        "organisation"
    ],
    "wof:name":"L S U Office",
    "wof:placetype":"venue"
},
  "geometry": {"coordinates":[-2.3514859676,51.3814430237],"type":"Point"}
}