{
  "type": "Feature",
  "properties": {
    "addr:full":"Croftdown Road Birmingham West Midlands B17 8RD",
    "addr:postcode":"b17 8rd",
    "addr:street":"Croftdown Road",
    "iso:country":"GB",
    "sg:address":"Croftdown Road",
    "sg:city":"Birmingham",
    "sg:classifiers":[
        {
            "category":"Organizations",
            "subcategory":"Membership Organization",
            "type":"Services"
        }
    ],
    "sg:phone":"+44 121 428 2406",
    "sg:postcode":"B17 8RD",
    "sg:province":"West Midlands",
    "sg:tags":[
        "club"
    ],
    "wof:name":"Heathercroft Bridge Club",
    "wof:placetype":"venue"
},
  "geometry": {"coordinates":[-1.9673199654,52.4639854431],"type":"Point"}
}