{
  "type": "Feature",
  "properties": {
    "iso:country":"GB",
    "sg:address":"Park Pl",
    "sg:city":"Weston-super-mare",
    "sg:classifiers":[
        {
            "category":"Travel",
            "subcategory":"Hotels & Motels",
            "type":"Entertainment"
        }
    ],
    "sg:postcode":"BS23 2BA",
    "sg:province":"Somerset",
    "wof:name":"Richmond Hotel",
    "wof:placetype":"venue"
},
  "geometry": {"coordinates":[-2.982724,51.352684],"type":"Point"}
}