{
  "type": "Feature",
  "properties": {
    "addr:full":"Second Floor, Kingsgate House Redhill Surrey RH1 1SG",
    "addr:housenumber":"second",
    "addr:postcode":"rh1 1sg",
    "addr:street":"Kingsgate;Redhill",
    "iso:country":"GB",
    "sg:address":"Second Floor, Kingsgate House",
    "sg:city":"Redhill",
    "sg:classifiers":[
        {
            "category":"Professional",
            "subcategory":"Employment Agencies",
            "type":"Services"
        }
    ],
    "sg:phone":"+44 1737 778282",
    "sg:postcode":"RH1 1SG",
    "sg:province":"Surrey",
    "sg:tags":[
        "consultant"
    ],
    "wof:name":"Reflex Computer Recruitment Ltd.",
    "wof:placetype":"venue"
},
  "geometry": {"coordinates":[-0.1688790023,51.2381782532],"type":"Point"}
}