{
  "type": "Feature",
  "properties": {
    "iso:country":"GB",
    "sg:address":"International Ferry Terminal, Royal Quays",
    "sg:city":"North Shields",
    "sg:classifiers":[
        {
            "category":"Ferry",
            "type":"Transportation"
        }
    ],
    "sg:phone":"+44 191 293 6262",
    "sg:postcode":"NE29 6EE",
    "sg:province":"Tyne and Wear",
    "wof:name":"Scandinavian Seaways",
    "wof:placetype":"venue"
},
  "geometry": {"coordinates":[-1.45166,54.99258],"type":"Point"}
}