{
  "type": "Feature",
  "properties": {
    "addr:full":"49 Stuart St Millport North Ayrshire KA28 0AG",
    "addr:housenumber":"49",
    "addr:postcode":"ka28 0ag",
    "addr:street":"Stuart St",
    "iso:country":"GB",
    "sg:address":"49 Stuart St",
    "sg:city":"Millport",
    "sg:classifiers":[
        {
            "category":"Travel",
            "subcategory":"Hotels & Motels",
            "type":"Entertainment"
        }
    ],
    "sg:phone":"+44 1475 530094",
    "sg:postcode":"KA28 0AG",
    "sg:province":"North Ayrshire",
    "sg:tags":[
        "self",
        "catering"
    ],
    "wof:name":"Cumbrae Holidays Apartments Ltd",
    "wof:placetype":"venue"
},
  "geometry": {"coordinates":[-4.9316849709,55.7521705627],"type":"Point"}
}