{
  "type": "Feature",
  "properties": {
    "addr:full":"Paramount House, 77 Mutley Plain Lane Plymouth Devon PL4 7DS",
    "addr:housenumber":"77",
    "addr:postcode":"pl4 7ds",
    "addr:street":"Mutley Plain Lane",
    "iso:country":"GB",
    "sg:address":"Paramount House, 77 Mutley Plain Lane",
    "sg:city":"Plymouth",
    "sg:classifiers":[
        {
            "category":"Professional",
            "subcategory":"Employment Agencies",
            "type":"Services"
        }
    ],
    "sg:phone":"+44 1752 204333",
    "sg:postcode":"PL4 7DS",
    "sg:province":"Devon",
    "sg:tags":[
        "consultant"
    ],
    "wof:name":"A Y S Recruitment Ltd.",
    "wof:placetype":"venue"
},
  "geometry": {"coordinates":[-4.133742,50.383385],"type":"Point"}
}