{
  "type": "Feature",
  "properties": {
    "iso:country":"GB",
    "sg:address":"Wroughton Place",
    "sg:city":"Cardiff",
    "sg:classifiers":[
        {
            "category":"Government",
            "subcategory":"Fire Station",
            "type":"Public Place"
        },
        {
            "category":"Home & Garden",
            "subcategory":"Hardware",
            "type":"Retail Goods"
        }
    ],
    "sg:postcode":"CF5 4AR",
    "sg:province":"Cardiff",
    "sg:tags":[
        "w'sale",
        "lighting",
        "retailer"
    ],
    "wof:name":"B C Lighting",
    "wof:placetype":"venue"
},
  "geometry": {"coordinates":[-3.233269,51.484772],"type":"Point"}
}