{
  "type": "Feature",
  "properties": {
    "addr:full":"Caberfeidh Avenue Dingwall Highland IV15 9TD",
    "addr:postcode":"iv15 9td",
    "addr:street":"Caberfeidh Avenue",
    "iso:country":"GB",
    "sg:address":"Caberfeidh Avenue",
    "sg:city":"Dingwall",
    "sg:classifiers":[
        {
            "category":"Military Area",
            "subcategory":"Air Force Base",
            "type":"Public Place"
        }
    ],
    "sg:phone":"+44 1349 862412",
    "sg:postcode":"IV15 9TD",
    "sg:province":"Highland",
    "sg:tags":[
        "taxi",
        "hire",
        "private"
    ],
    "wof:name":"C & E Taxis",
    "wof:placetype":"venue"
},
  "geometry": {"coordinates":[-4.432709,57.594906],"type":"Point"}
}