{
  "type": "Feature",
  "properties": {
    "iso:country":"GB",
    "sg:address":"Pembroke Road",
    "sg:city":"Bristol",
    "sg:classifiers":[
        {
            "category":"Retail",
            "subcategory":"Auto Repair",
            "type":"Services"
        }
    ],
    "sg:postcode":"BS11 9SB",
    "sg:province":"City of Bristol",
    "sg:tags":[
        "modification",
        "garage"
    ],
    "wof:name":"Pembroke Road Garage",
    "wof:placetype":"venue"
},
  "geometry": {"coordinates":[-2.677177,51.489098],"type":"Point"}
}