{
  "type": "Feature",
  "properties": {
    "iso:country":"GB",
    "sg:address":"377 Durnsford Rd",
    "sg:city":"Wimbledon",
    "sg:classifiers":[
        {
            "category":"Home & Garden",
            "subcategory":"Carpets & Floor Coverings",
            "type":"Retail Goods"
        }
    ],
    "sg:phone":"+44 20 8241 2125",
    "sg:postcode":"SW19 8EF",
    "sg:province":"Greater London",
    "sg:tags":[
        "textile",
        "floorcoverings"
    ],
    "wof:name":"Designer Floorings Ltd",
    "wof:placetype":"venue"
},
  "geometry": {"coordinates":[-0.197123006,51.4389038086],"type":"Point"}
}