{
  "type": "Feature",
  "properties": {
    "addr:full":"54 Hollowood Avenue, Littleover Derby Derbyshire DE23 6JD",
    "addr:housenumber":"54",
    "addr:postcode":"de23 6jd",
    "addr:street":"Hollowood Avenue",
    "iso:country":"GB",
    "sg:address":"54 Hollowood Avenue, Littleover",
    "sg:city":"Derby",
    "sg:classifiers":[
        {
            "category":"Building & Trades",
            "subcategory":"Plumbing",
            "type":"Services"
        }
    ],
    "sg:postcode":"DE23 6JD",
    "sg:province":"Derbyshire",
    "sg:tags":[
        "heating"
    ],
    "wof:name":"Godfrey J R Plumbing and Heating Engineer",
    "wof:placetype":"venue"
},
  "geometry": {"coordinates":[-1.507869,52.900112],"type":"Point"}
}