{
  "type": "Feature",
  "properties": {
    "addr:full":"Bowhill House, Dunsford Rd Exeter Devon EX4 1LQ",
    "addr:housenumber":"bowhill",
    "addr:postcode":"ex4 1lq",
    "addr:street":"Dunsford Rd",
    "iso:country":"GB",
    "sg:address":"Bowhill House, Dunsford Rd",
    "sg:city":"Exeter",
    "sg:classifiers":[
        {
            "category":"Community Center",
            "type":"Public Place"
        }
    ],
    "sg:phone":"+44 1392 252461",
    "sg:postcode":"EX4 1LQ",
    "sg:province":"Devon",
    "sg:tags":[
        "conference",
        "room",
        "centre"
    ],
    "wof:name":"The Devonshire Association",
    "wof:placetype":"venue"
},
  "geometry": {"coordinates":[-3.548814,50.714207],"type":"Point"}
}