{
  "type": "Feature",
  "properties": {
    "addr:full":"109 Dudley Road Grantham Lincolnshire NG31 9AD",
    "addr:housenumber":"109",
    "addr:postcode":"ng31 9ad",
    "addr:street":"Dudley Road",
    "iso:country":"GB",
    "sg:address":"109 Dudley Road",
    "sg:city":"Grantham",
    "sg:classifiers":[
        {
            "category":"Retail",
            "subcategory":"Repair Shop",
            "type":"Services"
        }
    ],
    "sg:phone":"+44 1476 590098",
    "sg:postcode":"NG31 9AD",
    "sg:province":"Lincolnshire",
    "sg:tags":[
        "clocks",
        "watch",
        "sale",
        "clock"
    ],
    "wof:name":"Ruby Clocks",
    "wof:placetype":"venue"
},
  "geometry": {"coordinates":[-0.6332520247,52.9061927795],"type":"Point"}
}