{
  "type": "Feature",
  "properties": {
    "addr:full":"29 Castlesteads Drive Carlisle Cumbria CA2 7XE",
    "addr:housenumber":"29",
    "addr:postcode":"ca2 7xe",
    "addr:street":"Castlesteads Drive",
    "iso:country":"GB",
    "sg:address":"29 Castlesteads Drive",
    "sg:city":"Carlisle",
    "sg:classifiers":[
        {
            "category":"Utilities",
            "subcategory":"Mobile Phone",
            "type":"Services"
        },
        {
            "category":"Shopping",
            "subcategory":"Computers & Home Electronics",
            "type":"Retail Goods"
        }
    ],
    "sg:phone":"+44 1228 545246",
    "sg:postcode":"CA2 7XE",
    "sg:province":"Cumbria",
    "sg:tags":[
        "sound",
        "equipment",
        "rental",
        "installation"
    ],
    "wof:name":"Atkinson Sound Repairs",
    "wof:placetype":"venue"
},
  "geometry": {"coordinates":[-2.9884400368,54.8922805786],"type":"Point"}
}