{
  "type": "Feature",
  "properties": {
    "iso:country":"GB",
    "sg:address":"77-79 Great Eastern St",
    "sg:city":"London",
    "sg:classifiers":[
        {
            "category":"Travel",
            "subcategory":"Chalets",
            "type":"Entertainment"
        }
    ],
    "sg:postcode":"EC2A 3HU",
    "sg:province":"Greater London",
    "sg:tags":[
        "cruiselines"
    ],
    "wof:name":"Equity Cruises Ltd",
    "wof:placetype":"venue"
},
  "geometry": {"coordinates":[-0.08237,51.525391],"type":"Point"}
}