{
  "type": "Feature",
  "properties": {
    "addr:full":"8 Radcliffe Road, Milnsbridge Huddersfield West Yorkshire HD3 4LX",
    "addr:housenumber":"8",
    "addr:postcode":"hd3 4lx",
    "addr:street":"Radcliffe Road;West",
    "iso:country":"GB",
    "sg:address":"8 Radcliffe Road, Milnsbridge",
    "sg:city":"Huddersfield",
    "sg:classifiers":[
        {
            "category":"Education",
            "subcategory":"Dance Studio",
            "type":"Public Place"
        }
    ],
    "sg:phone":"+44 1484 643120",
    "sg:postcode":"HD3 4LX",
    "sg:province":"West Yorkshire",
    "sg:tags":[
        "school",
        "dancing"
    ],
    "wof:name":"York Dance Studios",
    "wof:placetype":"venue"
},
  "geometry": {"coordinates":[-1.823312,53.638008],"type":"Point"}
}