{
  "type": "Feature",
  "properties": {
    "iso:country":"GB",
    "sg:address":"Toronto Place",
    "sg:city":"Gosport",
    "sg:classifiers":[
        {
            "category":"Wholesale",
            "subcategory":"Scrap",
            "type":"Manufacturing & Wholesale Goods"
        }
    ],
    "sg:phone":"+44 23 9250 1511",
    "sg:postcode":"PO12 4UZ",
    "sg:province":"Hampshire",
    "sg:tags":[
        "breaker",
        "dismantlers"
    ],
    "wof:name":"Car Components (Gosport) Ltd.",
    "wof:placetype":"venue"
},
  "geometry": {"coordinates":[-1.138848,50.797729],"type":"Point"}
}