{
  "type": "Feature",
  "properties": {
    "addr:full":"54-57 Moorbridge Rd Maidenhead Berkshire SL6 8BN",
    "addr:housenumber":"54-57",
    "addr:postcode":"sl6 8bn",
    "addr:street":"Moorbridge Rd",
    "iso:country":"GB",
    "sg:address":"54-57 Moorbridge Rd",
    "sg:city":"Maidenhead",
    "sg:classifiers":[
        {
            "category":"Home & Garden",
            "subcategory":"Home Furnishings",
            "type":"Retail Goods"
        }
    ],
    "sg:phone":"+44 1628 580162",
    "sg:postcode":"SL6 8BN",
    "sg:province":"Berkshire",
    "sg:tags":[
        "beds",
        "bedding",
        "blanket"
    ],
    "wof:name":"Maidenhead Bedding Centre",
    "wof:placetype":"venue"
},
  "geometry": {"coordinates":[-0.7145159841,51.5232582092],"type":"Point"}
}