{
  "type": "Feature",
  "properties": {
    "addr:full":"Enterprise Workshops, Lower Trostre Road Llanelli Carmarthenshire SA15 2EA",
    "addr:postcode":"sa15 2ea",
    "addr:street":"Lower Trostre Road",
    "iso:country":"GB",
    "sg:address":"Enterprise Workshops, Lower Trostre Road",
    "sg:city":"Llanelli",
    "sg:classifiers":[
        {
            "category":"Manufacturing",
            "subcategory":"Buildings",
            "type":"Manufacturing & Wholesale Goods"
        }
    ],
    "sg:phone":"+44 1554 759472",
    "sg:postcode":"SA15 2EA",
    "sg:province":"Carmarthenshire",
    "sg:tags":[
        "shed",
        "greenhouse"
    ],
    "wof:name":"Sheds & Chalets",
    "wof:placetype":"venue"
},
  "geometry": {"coordinates":[-4.1342988014,51.6826820374],"type":"Point"}
}