{
  "type": "Feature",
  "properties": {
    "iso:country":"GB",
    "sg:address":"423 Fulwwod Road",
    "sg:city":"Sheffield",
    "sg:classifiers":[
        {
            "category":"Autos & Motor Vehicles",
            "subcategory":"Automobile Sales",
            "type":"Retail Goods"
        }
    ],
    "sg:phone":"+44 114 230 9500",
    "sg:postcode":"S10 3GF",
    "sg:province":"South Yorkshire",
    "sg:tags":[
        "car"
    ],
    "wof:name":"Gregory & Dench Ltd.",
    "wof:placetype":"venue"
},
  "geometry": {"coordinates":[-1.52816,53.368317],"type":"Point"}
}