{
  "type": "Feature",
  "properties": {
    "iso:country":"GB",
    "sg:address":"47 Western Avenue, Woodley",
    "sg:city":"Reading",
    "sg:classifiers":[
        {
            "category":"Personal",
            "subcategory":"Beauty Salon",
            "type":"Services"
        }
    ],
    "sg:phone":"+44 118 969 9944",
    "sg:postcode":"RG5 3BJ",
    "sg:province":"Berkshire",
    "sg:tags":[
        "unisex",
        "hairdresser"
    ],
    "wof:name":"Cut Above (Hairdressers)",
    "wof:placetype":"venue"
},
  "geometry": {"coordinates":[-0.9086310267,51.4591026306],"type":"Point"}
}