{
  "type": "Feature",
  "properties": {
    "iso:country":"GB",
    "sg:address":"9 Green Street",
    "sg:city":"Warrington",
    "sg:classifiers":[
        {
            "category":"Professional",
            "subcategory":"Detective & Security Services",
            "type":"Services"
        }
    ],
    "sg:phone":"+44 1925 571519",
    "sg:postcode":"WA5 1TW",
    "sg:province":"Cheshire",
    "sg:tags":[
        "car"
    ],
    "wof:name":"Cass (Gb) Ltd.",
    "wof:placetype":"venue"
},
  "geometry": {"coordinates":[-2.6086900234,53.3891448975],"type":"Point"}
}