{
  "type": "Feature",
  "properties": {
    "addr:full":"47 Maiden Erlegh Avenue Bexley Kent DA5 3PF",
    "addr:housenumber":"47",
    "addr:postcode":"da5 3pf",
    "addr:street":"Avenue",
    "iso:country":"GB",
    "sg:address":"47 Maiden Erlegh Avenue",
    "sg:city":"Bexley",
    "sg:classifiers":[
        {
            "category":"Recreation",
            "subcategory":"Dog Park",
            "type":"Entertainment"
        },
        {
            "category":"Retail",
            "subcategory":"Animal Services",
            "type":"Services"
        }
    ],
    "sg:phone":"+44 1322 527294",
    "sg:postcode":"DA5 3PF",
    "sg:province":"Kent",
    "sg:tags":[
        "grooming",
        "clipping"
    ],
    "wof:name":"Mobile Grooming for Dogs & Cats",
    "wof:placetype":"venue"
},
  "geometry": {"coordinates":[0.1328430027,51.440120697],"type":"Point"}
}