{
  "type": "Feature",
  "properties": {
    "addr:full":"34 King St Port Talbot Neath Port Talbot SA13 1AY",
    "addr:housenumber":"34",
    "addr:postcode":"sa13 1ay",
    "addr:street":"King St",
    "iso:country":"GB",
    "sg:address":"34 King St",
    "sg:city":"Port Talbot",
    "sg:classifiers":[
        {
            "category":"Shopping",
            "subcategory":"Antiques",
            "type":"Retail Goods"
        }
    ],
    "sg:phone":"+44 1639 888105",
    "sg:postcode":"SA13 1AY",
    "sg:province":"Neath Port Talbot",
    "wof:name":"The Furniture Warehouse",
    "wof:placetype":"venue"
},
  "geometry": {"coordinates":[-3.777097,51.595982],"type":"Point"}
}