{
  "type": "Feature",
  "properties": {
    "addr:full":"121 Eyre Street Sheffield South Yorkshire S1 4QW",
    "addr:housenumber":"121",
    "addr:postcode":"s1 4qw",
    "addr:street":"Eyre Street",
    "iso:country":"GB",
    "sg:address":"121 Eyre Street",
    "sg:city":"Sheffield",
    "sg:classifiers":[
        {
            "category":"Professional",
            "subcategory":"Lawyer & Legal Services",
            "type":"Services"
        }
    ],
    "sg:postcode":"S1 4QW",
    "sg:province":"South Yorkshire",
    "sg:tags":[
        "advice",
        "counselling"
    ],
    "wof:name":"Sheffield Area Bereavement Forum",
    "wof:placetype":"venue"
},
  "geometry": {"coordinates":[-1.470868,53.376755],"type":"Point"}
}