{
  "type": "Feature",
  "properties": {
    "addr:full":"177 Holyhead Road Birmingham West Midlands B21 0BD",
    "addr:housenumber":"177",
    "addr:postcode":"b21 0bd",
    "addr:street":"Holyhead Road",
    "iso:country":"GB",
    "sg:address":"177 Holyhead Road",
    "sg:city":"Birmingham",
    "sg:classifiers":[
        {
            "category":"Government",
            "subcategory":"Post Office",
            "type":"Public Place"
        }
    ],
    "sg:phone":"+44 121 554 5520",
    "sg:postcode":"B21 0BD",
    "sg:province":"West Midlands",
    "wof:name":"Wattville Road Post Office",
    "wof:placetype":"venue"
},
  "geometry": {"coordinates":[-1.9533159733,52.5078277588],"type":"Point"}
}