{
  "type": "Feature",
  "properties": {
    "addr:full":"82 Church Lane Great Yarmouth Norfolk NR31 7BJ",
    "addr:housenumber":"82",
    "addr:postcode":"nr31 7bj",
    "addr:street":"Church Lane",
    "iso:country":"GB",
    "sg:address":"82 Church Lane",
    "sg:city":"Great Yarmouth",
    "sg:classifiers":[
        {
            "category":"Food & Beverages",
            "subcategory":"Meat & Fish",
            "type":"Retail Goods"
        }
    ],
    "sg:phone":"+44 1493 667432",
    "sg:postcode":"NR31 7BJ",
    "sg:province":"Norfolk",
    "sg:tags":[
        "chip"
    ],
    "wof:name":"Fry Rite",
    "wof:placetype":"venue"
},
  "geometry": {"coordinates":[1.7187730074,52.5790367126],"type":"Point"}
}