{
  "type": "Feature",
  "properties": {
    "addr:full":"Mancetter Road, Hartshill Nuneaton Leicestershire CV10 0RT",
    "addr:postcode":"cv10 0rt",
    "addr:street":"Mancetter Road",
    "iso:country":"GB",
    "sg:address":"Mancetter Road, Hartshill",
    "sg:city":"Nuneaton",
    "sg:classifiers":[
        {
            "category":"Bars & Pubs",
            "type":"Food & Drink"
        }
    ],
    "sg:postcode":"CV10 0RT",
    "sg:province":"Leicestershire",
    "sg:tags":[
        "pubs",
        "inn"
    ],
    "wof:name":"The Anchor Inn",
    "wof:placetype":"venue"
},
  "geometry": {"coordinates":[-1.5025000572,52.5391311646],"type":"Point"}
}