{
  "type": "Feature",
  "properties": {
    "addr:full":"Wath Rd, Elsecar Barnsley South Yorkshire S74 8HW",
    "addr:postcode":"s74 8hw",
    "addr:street":"Wath Rd;Yorkshire",
    "iso:country":"GB",
    "sg:address":"Wath Rd, Elsecar",
    "sg:city":"Barnsley",
    "sg:classifiers":[
        {
            "category":"Professional",
            "subcategory":"Testing Lab",
            "type":"Services"
        }
    ],
    "sg:postcode":"S74 8HW",
    "sg:province":"South Yorkshire",
    "sg:tags":[
        "mot"
    ],
    "wof:name":"M.O.T Elsecar & Fast Fit Service Centre",
    "wof:placetype":"venue"
},
  "geometry": {"coordinates":[-1.4186500311,53.4962348938],"type":"Point"}
}