{
  "type": "Feature",
  "properties": {
    "addr:full":"Darley Drive, West Derby Liverpool Merseyside L12 8QN",
    "addr:postcode":"l12 8qn",
    "addr:street":"Darley Drive West Derby",
    "iso:country":"GB",
    "sg:address":"Darley Drive, West Derby",
    "sg:city":"Liverpool",
    "sg:classifiers":[
        {
            "category":"Food & Beverages",
            "subcategory":"Supermarket",
            "type":"Retail Goods"
        }
    ],
    "sg:phone":"+44 151 228 6906",
    "sg:postcode":"L12 8QN",
    "sg:province":"Merseyside",
    "wof:name":"Crs",
    "wof:placetype":"venue"
},
  "geometry": {"coordinates":[-2.901934,53.428635],"type":"Point"}
}