{
  "type": "Feature",
  "properties": {
    "iso:country":"GB",
    "sg:address":"Burleigh House, Chapel Oak",
    "sg:city":"Evesham",
    "sg:classifiers":[
        {
            "category":"Professional",
            "type":"Services"
        },
        {
            "category":"Professional",
            "subcategory":"Computer Services",
            "type":"Services"
        }
    ],
    "sg:postcode":"WR11 8SP",
    "sg:province":"Gloucestershire",
    "sg:tags":[
        "repair",
        "tech",
        "system",
        "maintenance",
        "software"
    ],
    "wof:name":"Gl Settle Ltd.",
    "wof:placetype":"venue"
},
  "geometry": {"coordinates":[-1.9439690113,52.1063919067],"type":"Point"}
}