{
  "type": "Feature",
  "properties": {
    "addr:full":"223-225 Ilderton Road London Greater London SE15 1NS",
    "addr:housenumber":"223-225",
    "addr:postcode":"se15 1ns",
    "addr:street":"Ilderton Road",
    "iso:country":"GB",
    "sg:address":"223-225 Ilderton Road",
    "sg:city":"London",
    "sg:classifiers":[
        {
            "category":"Shopping",
            "subcategory":"Discount & Variety Stores",
            "type":"Retail Goods"
        }
    ],
    "sg:phone":"+44 20 7732 0191",
    "sg:postcode":"SE15 1NS",
    "sg:province":"Greater London",
    "sg:tags":[
        "cleaning",
        "supply"
    ],
    "wof:name":"Lamco Ltd.",
    "wof:placetype":"venue"
},
  "geometry": {"coordinates":[-0.053506,51.483727],"type":"Point"}
}