{
  "type": "Feature",
  "properties": {
    "addr:full":"143 St Marychurch Road Torquay Devon TQ1 3HW",
    "addr:housenumber":"143",
    "addr:postcode":"tq1 3hw",
    "addr:street":"St Marychurch Road",
    "iso:country":"GB",
    "sg:address":"143 St Marychurch Road",
    "sg:city":"Torquay",
    "sg:classifiers":[
        {
            "category":"Fast Food",
            "type":"Food & Drink"
        },
        {
            "category":"Food & Beverages",
            "subcategory":"Meat & Fish",
            "type":"Retail Goods"
        }
    ],
    "sg:phone":"+44 1803 327944",
    "sg:postcode":"TQ1 3HW",
    "sg:province":"Devon",
    "sg:tags":[
        "shop",
        "chip"
    ],
    "wof:name":"Plainmoor Fish Bar Ltd",
    "wof:placetype":"venue"
},
  "geometry": {"coordinates":[-3.52665,50.477585],"type":"Point"}
}