{
  "type": "Feature",
  "properties": {
    "addr:full":"Loreburn Shopping Centre, Unit 32 High Street Dumfries Dumfries and Galloway DG1 2BL",
    "addr:housenumber":"unit 32",
    "addr:postcode":"dg1 2bl",
    "addr:street":"High Street",
    "iso:country":"GB",
    "sg:address":"Loreburn Shopping Centre, Unit 32 High Street",
    "sg:city":"Dumfries",
    "sg:classifiers":[
        {
            "category":"Shopping",
            "subcategory":"Shoes",
            "type":"Retail Goods"
        }
    ],
    "sg:phone":"+44 1387 247563",
    "sg:postcode":"DG1 2BL",
    "sg:province":"Dumfries and Galloway",
    "sg:tags":[
        "shop"
    ],
    "wof:name":"Shoe Express",
    "wof:placetype":"venue"
},
  "geometry": {"coordinates":[-3.6160740852,55.0694999695],"type":"Point"}
}