{
  "type": "Feature",
  "properties": {
    "iso:country":"GB",
    "sg:address":"C/o Mycock Allatson & Co, 139 Middleton Boulevard",
    "sg:city":"Nottingham",
    "sg:classifiers":[
        {
            "category":"Professional",
            "subcategory":"Testing Lab",
            "type":"Services"
        }
    ],
    "sg:postcode":"NG8 1FW",
    "sg:province":"Nottinghamshire",
    "sg:tags":[
        "inspection",
        "calibration"
    ],
    "wof:name":"Ellen,Ted,Ltd",
    "wof:placetype":"venue"
},
  "geometry": {"coordinates":[-1.1926629543,52.9547309875],"type":"Point"}
}