{
  "type": "Feature",
  "properties": {
    "addr:full":"408 Blurton Rd Stoke On Trent Staffordshire ST3 3AJ",
    "addr:housenumber":"408",
    "addr:postcode":"st3 3aj",
    "addr:street":"Blurton Rd",
    "iso:country":"GB",
    "sg:address":"408 Blurton Rd",
    "sg:city":"Stoke On Trent",
    "sg:classifiers":[
        {
            "category":"Home & Garden",
            "subcategory":"Building Materials",
            "type":"Retail Goods"
        }
    ],
    "sg:phone":"+44 1782 598698",
    "sg:postcode":"ST3 3AJ",
    "sg:province":"Staffordshire",
    "sg:tags":[
        "furnishers",
        "bathroom",
        "planner"
    ],
    "wof:name":"Graham Bathroom Centre",
    "wof:placetype":"venue"
},
  "geometry": {"coordinates":[-2.1535029411,52.9799537659],"type":"Point"}
}