{
  "type": "Feature",
  "properties": {
    "iso:country":"GB",
    "sg:address":"23 Benwell Rd",
    "sg:city":"London",
    "sg:classifiers":[
        {
            "category":"Communications",
            "type":"Services"
        }
    ],
    "sg:phone":"+44 20 7686 0044",
    "sg:postcode":"N7 7BL",
    "sg:province":"Greater London",
    "sg:tags":[
        "data",
        "network"
    ],
    "wof:name":"Flintworks Ltd",
    "wof:placetype":"venue"
},
  "geometry": {"coordinates":[-0.108991,51.55204],"type":"Point"}
}