{
  "type": "Feature",
  "properties": {
    "iso:country":"GB",
    "sg:address":"110 Victoria Road East",
    "sg:city":"Thornton-cleveleys",
    "sg:classifiers":[
        {
            "category":"Social Services",
            "subcategory":"Retirement Home",
            "type":"Services"
        }
    ],
    "sg:postcode":"FY5 3SZ",
    "sg:province":"Lancashire",
    "sg:tags":[
        "residential",
        "care"
    ],
    "wof:name":"Alexandra Court Appartments With Care",
    "wof:placetype":"venue"
},
  "geometry": {"coordinates":[-3.012635,53.872482],"type":"Point"}
}