{
  "type": "Feature",
  "properties": {
    "addr:full":"End Unit 299 Gander Green Lane Sutton Surrey SM3 9QE",
    "addr:housenumber":"unit 299",
    "addr:postcode":"sm3 9qe",
    "addr:street":"Gander Green Lane",
    "iso:country":"GB",
    "sg:address":"End Unit 299 Gander Green Lane",
    "sg:city":"Sutton",
    "sg:classifiers":[
        {
            "category":"Home & Garden",
            "subcategory":"Building Materials",
            "type":"Retail Goods"
        }
    ],
    "sg:phone":"+44 20 8641 4488",
    "sg:postcode":"SM3 9QE",
    "sg:province":"Surrey",
    "sg:tags":[
        "window",
        "frame"
    ],
    "wof:name":"Panoramic Installations Ltd.",
    "wof:placetype":"venue"
},
  "geometry": {"coordinates":[-0.2089799941,51.3717384338],"type":"Point"}
}