{
  "type": "Feature",
  "properties": {
    "iso:country":"GB",
    "sg:address":"Main Road, Lea",
    "sg:city":"Matlock",
    "sg:classifiers":[
        {
            "category":"Bars & Pubs",
            "type":"Food & Drink"
        },
        {
            "category":"Community Center",
            "subcategory":"Social",
            "type":"Public Place"
        }
    ],
    "sg:phone":"+44 1629 534232",
    "sg:postcode":"DE4 5GJ",
    "sg:province":"Derbyshire",
    "sg:tags":[
        "pubs",
        "house",
        "inn",
        "activity"
    ],
    "wof:name":"Jug & Glass Inn",
    "wof:placetype":"venue"
},
  "geometry": {"coordinates":[-1.498315,53.083218],"type":"Point"}
}