{
  "type": "Feature",
  "properties": {
    "addr:full":"Foundry Street Rotherham South Yorkshire S62 6EH",
    "addr:postcode":"s62 6eh",
    "addr:street":"Foundry Street",
    "iso:country":"GB",
    "sg:address":"Foundry Street",
    "sg:city":"Rotherham",
    "sg:classifiers":[
        {
            "category":"Retail",
            "subcategory":"Auto Repair",
            "type":"Services"
        }
    ],
    "sg:phone":"+44 1709 522421",
    "sg:postcode":"S62 6EH",
    "sg:province":"South Yorkshire",
    "sg:tags":[
        "modification",
        "garage"
    ],
    "wof:name":"Foundry Garage",
    "wof:placetype":"venue"
},
  "geometry": {"coordinates":[-1.3447790146,53.4512062073],"type":"Point"}
}