{
  "type": "Feature",
  "properties": {
    "addr:full":"Old Harbour House, 24 Trinity Road Weymouth Dorset DT4 8TJ",
    "addr:housenumber":"24",
    "addr:postcode":"dt4 8tj",
    "addr:street":"Trinity Road",
    "iso:country":"GB",
    "sg:address":"Old Harbour House, 24 Trinity Road",
    "sg:city":"Weymouth",
    "sg:classifiers":[
        {
            "category":"Recreation",
            "subcategory":"Fishing",
            "type":"Entertainment"
        }
    ],
    "sg:phone":"+44 1305 777771",
    "sg:postcode":"DT4 8TJ",
    "sg:province":"Dorset",
    "sg:tags":[
        "angling"
    ],
    "wof:name":"Weymouth Angling Centre",
    "wof:placetype":"venue"
},
  "geometry": {"coordinates":[-2.455702,50.606831],"type":"Point"}
}