{
  "type": "Feature",
  "properties": {
    "iso:country":"GB",
    "sg:address":"Spanish City",
    "sg:city":"Mablethorpe",
    "sg:classifiers":[
        {
            "category":"Cafe",
            "type":"Food & Drink"
        }
    ],
    "sg:postcode":"LN12 1AL",
    "sg:province":"Lincolnshire",
    "sg:tags":[
        "tea",
        "room"
    ],
    "wof:name":"Expresso Coffee Bar",
    "wof:placetype":"venue"
},
  "geometry": {"coordinates":[0.258197,53.340668],"type":"Point"}
}