{
  "type": "Feature",
  "properties": {
    "addr:full":"Pioneer Park, 200 Ampthill Road Bedford Bedfordshire MK42 9BW",
    "addr:housenumber":"200",
    "addr:postcode":"mk42 9bw",
    "addr:street":"Ampthill Road",
    "iso:country":"GB",
    "sg:address":"Pioneer Park, 200 Ampthill Road",
    "sg:city":"Bedford",
    "sg:classifiers":[
        {
            "category":"Autos & Motor Vehicles",
            "subcategory":"Automobile Sales",
            "type":"Retail Goods"
        }
    ],
    "sg:phone":"+44 1234 328522",
    "sg:postcode":"MK42 9BW",
    "sg:province":"Bedfordshire",
    "sg:tags":[
        "car"
    ],
    "wof:name":"Herbert Robinson",
    "wof:placetype":"venue"
},
  "geometry": {"coordinates":[-0.47349,52.12104],"type":"Point"}
}