{
  "type": "Feature",
  "properties": {
    "addr:full":"Unit 4, Church Street Lutterworth Leicestershire LE17 4AW",
    "addr:housenumber":"unit 4",
    "addr:postcode":"le17 4aw",
    "addr:street":"Church Street",
    "iso:country":"GB",
    "sg:address":"Unit 4, Church Street",
    "sg:city":"Lutterworth",
    "sg:classifiers":[
        {
            "category":"Food & Beverages",
            "subcategory":"Bakery",
            "type":"Retail Goods"
        }
    ],
    "sg:postcode":"LE17 4AW",
    "sg:province":"Leicestershire",
    "sg:tags":[
        "baker"
    ],
    "wof:name":"Mighty Bite",
    "wof:placetype":"venue"
},
  "geometry": {"coordinates":[-1.200691,52.455578],"type":"Point"}
}