{
  "type": "Feature",
  "properties": {
    "addr:full":"Unit 3, 123a Gorton Road, Reddish Stockport Cheshire SK5 6EE",
    "addr:housenumber":"unit;123a",
    "addr:postcode":"sk5 6ee",
    "addr:street":"Gorton Road",
    "iso:country":"GB",
    "sg:address":"Unit 3, 123a Gorton Road, Reddish",
    "sg:city":"Stockport",
    "sg:classifiers":[
        {
            "category":"Mining & Drilling",
            "type":"Manufacturing & Wholesale Goods"
        }
    ],
    "sg:phone":"+44 161 443 2822",
    "sg:postcode":"SK5 6EE",
    "sg:province":"Cheshire",
    "sg:tags":[
        "contractor"
    ],
    "wof:name":"National Drilling Services Ltd.",
    "wof:placetype":"venue"
},
  "geometry": {"coordinates":[-2.158689,53.441563],"type":"Point"}
}