{
  "type": "Feature",
  "properties": {
    "addr:full":"6 Burgess Mews Wimbledon Greater London SW19 1UF",
    "addr:housenumber":"6",
    "addr:postcode":"sw19 1uf",
    "addr:street":"Burgess Mews",
    "iso:country":"GB",
    "sg:address":"6 Burgess Mews",
    "sg:city":"Wimbledon",
    "sg:classifiers":[
        {
            "category":"Communications",
            "subcategory":"Newspaper",
            "type":"Services"
        }
    ],
    "sg:phone":"+44 1291 430861",
    "sg:postcode":"SW19 1UF",
    "sg:province":"Greater London",
    "sg:tags":[
        "magazine"
    ],
    "wof:name":"French Property News",
    "wof:placetype":"venue"
},
  "geometry": {"coordinates":[-0.1910690069,51.4205093384],"type":"Point"}
}