{
  "type": "Feature",
  "properties": {
    "iso:country":"GB",
    "sg:address":"37 High St",
    "sg:city":"Neath",
    "sg:classifiers":[
        {
            "category":"Building & Trades",
            "subcategory":"Landscaping Services",
            "type":"Services"
        }
    ],
    "sg:phone":"+44 1639 720611",
    "sg:postcode":"SA11 5BS",
    "sg:province":"Neath Port Talbot",
    "sg:tags":[
        "landscape",
        "contractor"
    ],
    "wof:name":"Ian Smith",
    "wof:placetype":"venue"
},
  "geometry": {"coordinates":[-3.622222,51.746376],"type":"Point"}
}