{
  "type": "Feature",
  "properties": {
    "addr:full":"42 Branscombe Road Tiverton Devon EX16 4AB",
    "addr:housenumber":"42",
    "addr:postcode":"ex16 4ab",
    "addr:street":"Branscombe Road",
    "iso:country":"GB",
    "sg:address":"42 Branscombe Road",
    "sg:city":"Tiverton",
    "sg:classifiers":[
        {
            "category":"Personal",
            "type":"Services"
        }
    ],
    "sg:postcode":"EX16 4AB",
    "sg:province":"Devon",
    "sg:tags":[
        "wedding"
    ],
    "wof:name":"Shadow Hire Rolls Royce & Limousine Service",
    "wof:placetype":"venue"
},
  "geometry": {"coordinates":[-3.4684491158,50.9042930603],"type":"Point"}
}