{
  "type": "Feature",
  "properties": {
    "iso:country":"GB",
    "sg:address":"33 Main Street, Bentham",
    "sg:city":"Lancaster",
    "sg:classifiers":[
        {
            "category":"Professional",
            "subcategory":"Accounting & Tax Preparation",
            "type":"Services"
        }
    ],
    "sg:phone":"+44 15242 61879",
    "sg:postcode":"LA2 7HQ",
    "sg:province":"Lancashire",
    "sg:tags":[
        "accountant"
    ],
    "wof:name":"Taylor Robertson & Willett",
    "wof:placetype":"venue"
},
  "geometry": {"coordinates":[-2.511419,54.118042],"type":"Point"}
}