{
  "type": "Feature",
  "properties": {
    "iso:country":"GB",
    "sg:address":"18 Thorpe Rd",
    "sg:city":"Hockley",
    "sg:classifiers":[
        {
            "category":"Shopping",
            "subcategory":"Hobbies, Toys, & Games",
            "type":"Retail Goods"
        }
    ],
    "sg:phone":"+44 1702 207060",
    "sg:postcode":"SS5 4EP",
    "sg:province":"Essex",
    "sg:tags":[
        "toy"
    ],
    "wof:name":"Hoots",
    "wof:placetype":"venue"
},
  "geometry": {"coordinates":[0.666621,51.592842],"type":"Point"}
}