{
  "type": "Feature",
  "properties": {
    "iso:country":"GB",
    "sg:address":"67 Charlotte Street",
    "sg:city":"London",
    "sg:classifiers":[
        {
            "category":"Restaurant",
            "type":"Food & Drink"
        }
    ],
    "sg:phone":"+44 20 7637 7713",
    "sg:postcode":"W1T 4PF",
    "sg:province":"Greater London",
    "wof:name":"Navarro's Restaurant",
    "wof:placetype":"venue"
},
  "geometry": {"coordinates":[-0.136451,51.520004],"type":"Point"}
}