{
  "type": "Feature",
  "properties": {
    "iso:country":"GB",
    "sg:address":"King Edward House, 9 Finsley Gate",
    "sg:city":"Burnley",
    "sg:classifiers":[
        {
            "category":"Professional",
            "subcategory":"Lawyer & Legal Services",
            "type":"Services"
        }
    ],
    "sg:phone":"+44 1282 855400",
    "sg:postcode":"BB11 2FS",
    "sg:province":"Lancashire",
    "sg:tags":[
        "solicitor"
    ],
    "wof:name":"FARNWORTHS",
    "wof:placetype":"venue"
},
  "geometry": {"coordinates":[-2.242864,53.785549],"type":"Point"}
}