{
  "type": "Feature",
  "properties": {
    "addr:full":"Unit 14 Darin Court, Crown Hill Milton Keynes Buckinghamshire MK8 0AD",
    "addr:housenumber":"unit 14",
    "addr:postcode":"mk8 0ad",
    "addr:street":"Darin Court",
    "iso:country":"GB",
    "sg:address":"Unit 14 Darin Court, Crown Hill",
    "sg:city":"Milton Keynes",
    "sg:classifiers":[
        {
            "category":"Manufacturing",
            "subcategory":"Electronics",
            "type":"Manufacturing & Wholesale Goods"
        }
    ],
    "sg:phone":"+44 1908 567433",
    "sg:postcode":"MK8 0AD",
    "sg:province":"Buckinghamshire",
    "sg:tags":[
        "printed",
        "circuit"
    ],
    "wof:name":"Circuit Solve Ltd.",
    "wof:placetype":"venue"
},
  "geometry": {"coordinates":[-0.798892,52.030907],"type":"Point"}
}