{
  "type": "Feature",
  "properties": {
    "iso:country":"GB",
    "sg:address":"23 Wilcox Clo",
    "sg:city":"Sheffield",
    "sg:classifiers":[
        {
            "category":"Autos & Motor Vehicles",
            "subcategory":"Auto Supplies",
            "type":"Retail Goods"
        }
    ],
    "sg:phone":"+44 114 233 5658",
    "sg:postcode":"S13 9BU",
    "sg:province":"South Yorkshire",
    "sg:tags":[
        "car",
        "audio"
    ],
    "wof:name":"C.B. Security",
    "wof:placetype":"venue"
},
  "geometry": {"coordinates":[-1.493682,53.427013],"type":"Point"}
}