{
  "type": "Feature",
  "properties": {
    "addr:full":"13 Bewick Road Gateshead Tyne and Wear NE8 4DP",
    "addr:housenumber":"13",
    "addr:postcode":"ne8 4dp",
    "addr:street":"Bewick Road",
    "iso:country":"GB",
    "sg:address":"13 Bewick Road",
    "sg:city":"Gateshead",
    "sg:classifiers":[
        {
            "category":"Shopping",
            "subcategory":"Pharmacy",
            "type":"Retail Goods"
        }
    ],
    "sg:phone":"+44 191 477 4456",
    "sg:postcode":"NE8 4DP",
    "sg:province":"Tyne and Wear",
    "sg:tags":[
        "pharmacist",
        "dispensing",
        "chemist"
    ],
    "wof:name":"Lloyds Pharmacy",
    "wof:placetype":"venue"
},
  "geometry": {"coordinates":[-1.602097,54.956299],"type":"Point"}
}