{
  "type": "Feature",
  "properties": {
    "iso:country":"GB",
    "sg:address":"25-39 Yarrow Road",
    "sg:city":"Poole",
    "sg:classifiers":[
        {
            "category":"Home & Garden",
            "subcategory":"Furniture",
            "type":"Retail Goods"
        }
    ],
    "sg:phone":"+44 1202 718327",
    "sg:postcode":"BH17 7NY",
    "sg:province":"Dorset",
    "wof:name":"Sharps Bedroom Design",
    "wof:placetype":"venue"
},
  "geometry": {"coordinates":[-1.9572319984,50.7407989502],"type":"Point"}
}