{
  "type": "Feature",
  "properties": {
    "addr:full":"Graigievar House, Craigmount Brae Edinburgh City of Edinburgh EH12 8YL",
    "addr:postcode":"eh12 8yl",
    "addr:street":"Craigmount Brae",
    "iso:country":"GB",
    "sg:address":"Graigievar House, Craigmount Brae",
    "sg:city":"Edinburgh",
    "sg:classifiers":[
        {
            "category":"Professional",
            "subcategory":"Computer Services",
            "type":"Services"
        }
    ],
    "sg:phone":"+44 131 339 9600",
    "sg:postcode":"EH12 8YL",
    "sg:province":"City of Edinburgh",
    "sg:tags":[
        "information"
    ],
    "wof:name":"Navigation Technologies Ltd.",
    "wof:placetype":"venue"
},
  "geometry": {"coordinates":[-3.3009738922,55.9528465271],"type":"Point"}
}