{
  "type": "Feature",
  "properties": {
    "iso:country":"GB",
    "sg:address":"8 St Johns Parade, Alinora Crescent",
    "sg:city":"Worthing",
    "sg:classifiers":[
        {
            "category":"Food & Beverages",
            "subcategory":"Candy",
            "type":"Retail Goods"
        }
    ],
    "sg:phone":"+44 1903 245534",
    "sg:postcode":"BN12 4HJ",
    "sg:province":"West Sussex",
    "sg:tags":[
        "confectioner"
    ],
    "wof:name":"J K & V J Koria Sub Post Office",
    "wof:placetype":"venue"
},
  "geometry": {"coordinates":[-0.416925,50.807236],"type":"Point"}
}