{
  "type": "Feature",
  "properties": {
    "addr:full":"Clare House, Melrose Gardens Gosport Hampshire PO12 3BZ",
    "addr:postcode":"po12 3bz",
    "addr:street":"Melrose Gardens",
    "iso:country":"GB",
    "sg:address":"Clare House, Melrose Gardens",
    "sg:city":"Gosport",
    "sg:classifiers":[
        {
            "category":"Health Services",
            "subcategory":"Nursing And Care Facility",
            "type":"Services"
        },
        {
            "category":"Social Services",
            "subcategory":"Adult Care",
            "type":"Services"
        },
        {
            "category":"Organizations",
            "subcategory":"Community Association",
            "type":"Services"
        },
        {
            "category":"Organizations",
            "subcategory":"Non-profit Organization",
            "type":"Services"
        }
    ],
    "sg:phone":"+44 23 9251 0028",
    "sg:postcode":"PO12 3BZ",
    "sg:province":"Hampshire",
    "sg:tags":[
        "society",
        "housing",
        "charitable",
        "sheltered",
        "home",
        "organisation",
        "charity"
    ],
    "wof:name":"Thorngate Almshouse Trust",
    "wof:placetype":"venue"
},
  "geometry": {"coordinates":[-1.1537840366,50.8058166504],"type":"Point"}
}