{
  "type": "Feature",
  "properties": {
    "addr:full":"London Road, Davenham Northwich Cheshire CW9 8LL",
    "addr:postcode":"cw9 8ll",
    "addr:street":"London Road",
    "iso:country":"GB",
    "sg:address":"London Road, Davenham",
    "sg:city":"Northwich",
    "sg:classifiers":[
        {
            "category":"Health Services",
            "subcategory":"Nursing And Care Facility",
            "type":"Services"
        }
    ],
    "sg:phone":"+44 1606 354320",
    "sg:postcode":"CW9 8LL",
    "sg:province":"Cheshire",
    "sg:tags":[
        "home"
    ],
    "wof:name":"DAVENHAM HALL",
    "wof:placetype":"venue"
},
  "geometry": {"coordinates":[-2.513289,53.25457],"type":"Point"}
}