{
  "type": "Feature",
  "properties": {
    "addr:full":"7 High St Welwyn Hertfordshire AL6 9EE",
    "addr:housenumber":"7",
    "addr:postcode":"al6 9ee",
    "addr:street":"High St",
    "iso:country":"GB",
    "sg:address":"7 High St",
    "sg:city":"Welwyn",
    "sg:classifiers":[
        {
            "category":"Shopping",
            "subcategory":"Jewelry",
            "type":"Retail Goods"
        }
    ],
    "sg:postcode":"AL6 9EE",
    "sg:province":"Hertfordshire",
    "sg:tags":[
        "gold",
        "silversmith"
    ],
    "wof:name":"Treasures",
    "wof:placetype":"venue"
},
  "geometry": {"coordinates":[-0.215402,51.830906],"type":"Point"}
}