{
  "type": "Feature",
  "properties": {
    "addr:full":"15 Bloomsbury Street, Nechells Birmingham West Midlands B7 5BX",
    "addr:housenumber":"15",
    "addr:postcode":"b7 5bx",
    "addr:street":"Bloomsbury Street",
    "iso:country":"GB",
    "sg:address":"15 Bloomsbury Street, Nechells",
    "sg:city":"Birmingham",
    "sg:classifiers":[
        {
            "category":"Professional",
            "subcategory":"Business Services",
            "type":"Services"
        },
        {
            "category":"Casinos & Gambling",
            "type":"Entertainment"
        }
    ],
    "sg:phone":"+44 121 359 2501",
    "sg:postcode":"B7 5BX",
    "sg:province":"West Midlands",
    "sg:tags":[
        "turf",
        "accountant",
        "bookmaker"
    ],
    "wof:name":"Tom Currigan Ltd",
    "wof:placetype":"venue"
},
  "geometry": {"coordinates":[-1.871942997,52.4940490723],"type":"Point"}
}