{
  "type": "Feature",
  "properties": {
    "addr:full":"466 Bury Old Road, Prestwich Manchester Greater Manchester M25 1NL",
    "addr:housenumber":"466",
    "addr:postcode":"m25 1nl",
    "addr:street":"Bury Old Road",
    "iso:country":"GB",
    "sg:address":"466 Bury Old Road, Prestwich",
    "sg:city":"Manchester",
    "sg:classifiers":[
        {
            "category":"Shopping",
            "subcategory":"News",
            "type":"Retail Goods"
        }
    ],
    "sg:phone":"+44 161 773 5755",
    "sg:postcode":"M25 1NL",
    "sg:province":"Greater Manchester",
    "sg:tags":[
        "newsagent"
    ],
    "wof:name":"Akhtar News",
    "wof:placetype":"venue"
},
  "geometry": {"coordinates":[-2.275662899,53.5376052856],"type":"Point"}
}