{
  "type": "Feature",
  "properties": {
    "addr:full":"Fine Jewelry Room London Greater London SW1X 7XL",
    "addr:postcode":"sw1x 7xl",
    "iso:country":"GB",
    "sg:address":"Fine Jewelry Room",
    "sg:city":"London",
    "sg:classifiers":[
        {
            "category":"Shopping",
            "subcategory":"Comic Books",
            "type":"Retail Goods"
        }
    ],
    "sg:postcode":"SW1X 7XL",
    "sg:province":"Greater London",
    "sg:tags":[
        "jeweller"
    ],
    "wof:name":"van Cleef & Arpels Ltd.",
    "wof:placetype":"venue"
},
  "geometry": {"coordinates":[-0.1556199938,51.5011291504],"type":"Point"}
}