{
  "type": "Feature",
  "properties": {
    "iso:country":"GB",
    "sg:address":"Unit 58 & 59, Greenheyes Business Centre, 10 Penfold Way",
    "sg:city":"Manchester",
    "sg:classifiers":[
        {
            "category":"Professional",
            "subcategory":"Computer Services",
            "type":"Services"
        }
    ],
    "sg:phone":"+44 161 288 2188",
    "sg:postcode":"M15 6JJ",
    "sg:province":"Cheshire",
    "sg:tags":[
        "system",
        "software"
    ],
    "wof:name":"P A S Ltd.",
    "wof:placetype":"venue"
},
  "geometry": {"coordinates":[-2.23709,53.46225],"type":"Point"}
}