{
  "type": "Feature",
  "properties": {
    "addr:full":"37b New Cavendish Street London Greater London W1G 8JR",
    "addr:housenumber":"37b",
    "addr:postcode":"w1g 8jr",
    "addr:street":"New Cavendish Street",
    "iso:country":"GB",
    "sg:address":"37b New Cavendish Street",
    "sg:city":"London",
    "sg:classifiers":[
        {
            "category":"Health Services",
            "subcategory":"Doctor",
            "type":"Services"
        }
    ],
    "sg:postcode":"W1G 8JR",
    "sg:province":"Greater London",
    "sg:tags":[
        "practitioners"
    ],
    "wof:name":"Premier Medical Services Ltd",
    "wof:placetype":"venue"
},
  "geometry": {"coordinates":[-0.149574995,51.5189743042],"type":"Point"}
}