{
  "type": "Feature",
  "properties": {
    "addr:full":"Unit 6 Faraday Close, Pattinson North Industrial Estate, District 15 Washington Durham NE38 8QA",
    "addr:housenumber":"unit 6",
    "addr:postcode":"ne38 8qa",
    "addr:street":"Faraday Close;Estate",
    "iso:country":"GB",
    "sg:address":"Unit 6 Faraday Close, Pattinson North Industrial Estate, District 15",
    "sg:city":"Washington",
    "sg:classifiers":[
        {
            "category":"Home & Garden",
            "subcategory":"Hardware",
            "type":"Retail Goods"
        }
    ],
    "sg:phone":"+44 191 416 5551",
    "sg:postcode":"NE38 8QA",
    "sg:province":"Durham",
    "sg:tags":[
        "paint"
    ],
    "wof:name":"Morrells Woodfinishes (North East) Ltd.",
    "wof:placetype":"venue"
},
  "geometry": {"coordinates":[-1.531789,54.898144],"type":"Point"}
}