{
  "type": "Feature",
  "properties": {
    "addr:full":"8 Market Place Camelford Cornwall PL32 9PB",
    "addr:housenumber":"8",
    "addr:postcode":"pl32 9pb",
    "addr:street":"Market Place",
    "iso:country":"GB",
    "sg:address":"8 Market Place",
    "sg:city":"Camelford",
    "sg:classifiers":[
        {
            "category":"Restaurant",
            "type":"Food & Drink"
        }
    ],
    "sg:postcode":"PL32 9PB",
    "sg:province":"Cornwall",
    "wof:name":"The Oscars",
    "wof:placetype":"venue"
},
  "geometry": {"coordinates":[-4.6787619591,50.6232223511],"type":"Point"}
}