{
  "type": "Feature",
  "properties": {
    "iso:country":"GB",
    "sg:address":"20 Grosvenor Pl",
    "sg:city":"Westminster",
    "sg:classifiers":[
        {
            "category":"Professional",
            "subcategory":"Business Services",
            "type":"Services"
        }
    ],
    "sg:phone":"+44 20 7838 9400",
    "sg:postcode":"SW1X 7HN",
    "sg:province":"Greater London",
    "sg:tags":[
        "trade"
    ],
    "wof:name":"World Travel & Tourism Council",
    "wof:placetype":"venue"
},
  "geometry": {"coordinates":[-0.149432,51.500271],"type":"Point"}
}