{
  "type": "Feature",
  "properties": {
    "iso:country":"GB",
    "sg:address":"12-14 Cedar Way Industrial Estat, E Cedar Way",
    "sg:city":"London",
    "sg:classifiers":[
        {
            "category":"Farming",
            "subcategory":"Fish & Marine Products",
            "type":"Manufacturing & Wholesale Goods"
        }
    ],
    "sg:phone":"+44 20 7383 3771",
    "sg:postcode":"NW1 0PD",
    "sg:province":"Greater London",
    "sg:tags":[
        "fishmonger"
    ],
    "wof:name":"Daily Fish Supplies Ltd.",
    "wof:placetype":"venue"
},
  "geometry": {"coordinates":[-0.1317699999,51.5404205322],"type":"Point"}
}