{
  "type": "Feature",
  "properties": {
    "iso:country":"GB",
    "sg:address":"Farrer St",
    "sg:city":"Stockton On Tees",
    "sg:classifiers":[
        {
            "category":"Health Services",
            "subcategory":"Clinic",
            "type":"Services"
        }
    ],
    "sg:phone":"+44 1642 615488",
    "sg:postcode":"TS18 2AG",
    "sg:province":"Durham",
    "sg:tags":[
        "nh"
    ],
    "wof:name":"The Link Centre",
    "wof:placetype":"venue"
},
  "geometry": {"coordinates":[-1.313609,54.56918],"type":"Point"}
}