{
  "type": "Feature",
  "properties": {
    "iso:country":"GB",
    "sg:address":"6-8 The Homend",
    "sg:city":"Ledbury",
    "sg:classifiers":[
        {
            "category":"Shopping",
            "subcategory":"Department Store",
            "type":"Retail Goods"
        }
    ],
    "sg:phone":"+44 1531 632834",
    "sg:postcode":"HR8 1BT",
    "sg:province":"Gloucestershire",
    "sg:tags":[
        "departmental"
    ],
    "wof:name":"Woolworths Plc",
    "wof:placetype":"venue"
},
  "geometry": {"coordinates":[-2.4234330654,52.037322998],"type":"Point"}
}