{
  "type": "Feature",
  "properties": {
    "addr:full":"Holly Road Uttoxeter Derbyshire ST14 7LY",
    "addr:postcode":"st14 7ly",
    "addr:street":"Holly Road",
    "iso:country":"GB",
    "sg:address":"Holly Road",
    "sg:city":"Uttoxeter",
    "sg:classifiers":[
        {
            "category":"Retail",
            "subcategory":"Laundry & Dry Cleaning",
            "type":"Services"
        }
    ],
    "sg:phone":"+44 1889 562173",
    "sg:postcode":"ST14 7LY",
    "sg:province":"Derbyshire",
    "sg:tags":[
        "launderette"
    ],
    "wof:name":"Apparelmaster U K Ltd.",
    "wof:placetype":"venue"
},
  "geometry": {"coordinates":[-1.872444,52.906681],"type":"Point"}
}