{
  "type": "Feature",
  "properties": {
    "addr:full":"73 High Street, Colton Rugeley Staffordshire WS15 3LG",
    "addr:housenumber":"73",
    "addr:postcode":"ws15 3lg",
    "addr:street":"High Street",
    "iso:country":"GB",
    "sg:address":"73 High Street, Colton",
    "sg:city":"Rugeley",
    "sg:classifiers":[
        {
            "category":"Bars & Pubs",
            "type":"Food & Drink"
        }
    ],
    "sg:phone":"+44 1889 584026",
    "sg:postcode":"WS15 3LG",
    "sg:province":"Staffordshire",
    "sg:tags":[
        "pubs",
        "inn"
    ],
    "wof:name":"Ye Olde Dun Cow Ltd.",
    "wof:placetype":"venue"
},
  "geometry": {"coordinates":[-1.921204,52.786533],"type":"Point"}
}