{
  "type": "Feature",
  "properties": {
    "addr:full":"2 Melton St, Radcliffe Manchester Greater Manchester M26 4BR",
    "addr:housenumber":"2",
    "addr:postcode":"m26 4br",
    "addr:street":"Melton St",
    "iso:country":"GB",
    "sg:address":"2 Melton St, Radcliffe",
    "sg:city":"Manchester",
    "sg:classifiers":[
        {
            "category":"Building & Trades",
            "subcategory":"Cleaning & Sanitation",
            "type":"Services"
        }
    ],
    "sg:phone":"+44 161 724 8051",
    "sg:postcode":"M26 4BR",
    "sg:province":"Greater Manchester",
    "sg:tags":[
        "steam"
    ],
    "wof:name":"P.D.S Steam Cleaner Repairs",
    "wof:placetype":"venue"
},
  "geometry": {"coordinates":[-2.334737,53.564014],"type":"Point"}
}