{
  "type": "Feature",
  "properties": {
    "iso:country":"GB",
    "sg:address":"Unit 5a Avon Gorge Industrial Centre, Portview Rd",
    "sg:city":"Bristol",
    "sg:classifiers":[
        {
            "category":"Wholesale",
            "subcategory":"Books, Periodicals, & Newspapers",
            "type":"Manufacturing & Wholesale Goods"
        }
    ],
    "sg:phone":"+44 117 982 1952",
    "sg:postcode":"BS11 9LQ",
    "sg:province":"City of Bristol",
    "sg:tags":[
        "newsagent"
    ],
    "wof:name":"Mags Express",
    "wof:placetype":"venue"
},
  "geometry": {"coordinates":[-2.692614,51.491402],"type":"Point"}
}