{
  "type": "Feature",
  "properties": {
    "iso:country":"GB",
    "sg:address":"42 Teign Street",
    "sg:city":"Teignmouth",
    "sg:classifiers":[
        {
            "category":"Shopping",
            "subcategory":"Shoes",
            "type":"Retail Goods"
        }
    ],
    "sg:postcode":"TQ14 8EA",
    "sg:province":"Devon",
    "sg:tags":[
        "shop"
    ],
    "wof:name":"Chuckle Shoes",
    "wof:placetype":"venue"
},
  "geometry": {"coordinates":[-3.49765,50.546257],"type":"Point"}
}