{
  "type": "Feature",
  "properties": {
    "addr:full":"The Studios, 22 Sutherland Gr London Greater London SW18 5PU",
    "addr:housenumber":"22",
    "addr:postcode":"sw18 5pu",
    "addr:street":"Sutherland Gr",
    "iso:country":"GB",
    "sg:address":"The Studios, 22 Sutherland Gr",
    "sg:city":"London",
    "sg:classifiers":[
        {
            "category":"Professional",
            "subcategory":"Advertising",
            "type":"Services"
        }
    ],
    "sg:phone":"+44 20 8780 5936",
    "sg:postcode":"SW18 5PU",
    "sg:province":"Greater London",
    "sg:tags":[
        "agency"
    ],
    "wof:name":"Anthony Lydekker Photographer",
    "wof:placetype":"venue"
},
  "geometry": {"coordinates":[-0.2074300051,51.4461402893],"type":"Point"}
}