{
  "type": "Feature",
  "properties": {
    "addr:full":"Bridge House, 12 Mornington Grove Bow Greater London E3 4NS",
    "addr:housenumber":"12",
    "addr:postcode":"e3 4ns",
    "addr:street":"Mornington Grove",
    "iso:country":"GB",
    "sg:address":"Bridge House, 12 Mornington Grove",
    "sg:city":"Bow",
    "sg:classifiers":[
        {
            "category":"Organizations",
            "subcategory":"Community Association",
            "type":"Services"
        }
    ],
    "sg:phone":"+44 20 8980 9942",
    "sg:postcode":"E3 4NS",
    "sg:province":"Greater London",
    "sg:tags":[
        "society",
        "housing"
    ],
    "wof:name":"Spitalfields Crypt Trust",
    "wof:placetype":"venue"
},
  "geometry": {"coordinates":[-0.023762,51.526035],"type":"Point"}
}