{
  "type": "Feature",
  "properties": {
    "iso:country":"GB",
    "sg:address":"8 Station Parade",
    "sg:city":"Barking",
    "sg:classifiers":[
        {
            "category":"Retail",
            "subcategory":"Laundry & Dry Cleaning",
            "type":"Services"
        }
    ],
    "sg:phone":"+44 20 8594 1666",
    "sg:postcode":"IG11 8DN",
    "sg:province":"Essex",
    "sg:tags":[
        "alteration"
    ],
    "wof:name":"Valet Dry Cleaning Services",
    "wof:placetype":"venue"
},
  "geometry": {"coordinates":[0.080047,51.538086],"type":"Point"}
}