{
  "type": "Feature",
  "properties": {
    "addr:full":"Upper Farm, Bell Lane, Brookmans Park Hatfield Hertfordshire AL9 7AY",
    "addr:postcode":"al9 7ay",
    "addr:street":"Upper;Bell Lane Brookmans Park",
    "iso:country":"GB",
    "sg:address":"Upper Farm, Bell Lane, Brookmans Park",
    "sg:city":"Hatfield",
    "sg:classifiers":[
        {
            "category":"Professional",
            "subcategory":"Engineering",
            "type":"Services"
        }
    ],
    "sg:phone":"+44 1707 644550",
    "sg:postcode":"AL9 7AY",
    "sg:province":"Hertfordshire",
    "sg:tags":[
        "civil",
        "engineer"
    ],
    "wof:name":"Honeybell Ltd",
    "wof:placetype":"venue"
},
  "geometry": {"coordinates":[-0.1868900061,51.7311401367],"type":"Point"}
}