{
  "type": "Feature",
  "properties": {
    "addr:full":"25 Park Rd Cannock Staffordshire WS11 1JN",
    "addr:housenumber":"25",
    "addr:postcode":"ws11 1jn",
    "addr:street":"Park Rd",
    "iso:country":"GB",
    "sg:address":"25 Park Rd",
    "sg:city":"Cannock",
    "sg:classifiers":[
        {
            "category":"Professional",
            "subcategory":"Lawyer & Legal Services",
            "type":"Services"
        }
    ],
    "sg:phone":"+44 1543 467235",
    "sg:postcode":"WS11 1JN",
    "sg:province":"Staffordshire",
    "sg:tags":[
        "advice",
        "counselling"
    ],
    "wof:name":"Cannock Drug Line",
    "wof:placetype":"venue"
},
  "geometry": {"coordinates":[-2.0333940983,52.6910705566],"type":"Point"}
}