{
  "type": "Feature",
  "properties": {
    "iso:country":"GB",
    "sg:address":"Allsaints House, Barton Bendish",
    "sg:city":"King's Lynn",
    "sg:classifiers":[
        {
            "category":"Real Estate",
            "subcategory":"Architect",
            "type":"Services"
        }
    ],
    "sg:phone":"+44 1366 347733",
    "sg:postcode":"PE33 9DP",
    "sg:province":"Norfolk",
    "sg:tags":[
        "architectural"
    ],
    "wof:name":"The Parsons Partnership",
    "wof:placetype":"venue"
},
  "geometry": {"coordinates":[0.52965,52.621868],"type":"Point"}
}