{
  "type": "Feature",
  "properties": {
    "iso:country":"GB",
    "sg:address":"149 Wallasey Village",
    "sg:city":"Wallasey",
    "sg:classifiers":[
        {
            "category":"Manufacturing",
            "subcategory":"Petroleum Products",
            "type":"Manufacturing & Wholesale Goods"
        }
    ],
    "sg:phone":"+44 151 630 7331",
    "sg:postcode":"L45 3LF",
    "sg:province":"Merseyside",
    "sg:tags":[
        "double",
        "glazing"
    ],
    "wof:name":"Glass Shop The",
    "wof:placetype":"venue"
},
  "geometry": {"coordinates":[-3.0659,53.424587],"type":"Point"}
}