{
  "type": "Feature",
  "properties": {
    "addr:full":"5 Motcomb Street London Greater London SW1X 8JU",
    "addr:housenumber":"5",
    "addr:postcode":"sw1x 8ju",
    "addr:street":"Motcomb Street",
    "iso:country":"GB",
    "sg:address":"5 Motcomb Street",
    "sg:city":"London",
    "sg:classifiers":[
        {
            "category":"Personal",
            "subcategory":"Beauty Salon",
            "type":"Services"
        }
    ],
    "sg:postcode":"SW1X 8JU",
    "sg:province":"Greater London",
    "sg:tags":[
        "unisex",
        "hairdresser"
    ],
    "wof:name":"Christian",
    "wof:placetype":"venue"
},
  "geometry": {"coordinates":[-0.1564729959,51.4993247986],"type":"Point"}
}