{
  "type": "Feature",
  "properties": {
    "addr:full":"157 High St Norwich Norfolk NR12 9BB",
    "addr:housenumber":"157",
    "addr:postcode":"nr12 9bb",
    "addr:street":"High St",
    "iso:country":"GB",
    "sg:address":"157 High St",
    "sg:city":"Norwich",
    "sg:classifiers":[
        {
            "category":"Cafe",
            "type":"Food & Drink"
        }
    ],
    "sg:phone":"+44 1692 581362",
    "sg:postcode":"NR12 9BB",
    "sg:province":"Norfolk",
    "sg:tags":[
        "tea",
        "room"
    ],
    "wof:name":"T.C'S Cafe",
    "wof:placetype":"venue"
},
  "geometry": {"coordinates":[1.51773,52.771324],"type":"Point"}
}