{
  "type": "Feature",
  "properties": {
    "addr:full":"Nine Lock Works, Mill Street Dudley West Midlands DY5 2SX",
    "addr:postcode":"dy5 2sx",
    "addr:street":"Mill Street",
    "iso:country":"GB",
    "sg:address":"Nine Lock Works, Mill Street",
    "sg:city":"Dudley",
    "sg:classifiers":[
        {
            "category":"Manufacturing",
            "subcategory":"Metals",
            "type":"Manufacturing & Wholesale Goods"
        },
        {
            "category":"Home & Garden",
            "subcategory":"Home Furnishings",
            "type":"Retail Goods"
        }
    ],
    "sg:phone":"+44 1384 487600",
    "sg:postcode":"DY5 2SX",
    "sg:province":"West Midlands",
    "sg:tags":[
        "steel",
        "tube",
        "fitting",
        "stockist",
        "stockholder"
    ],
    "wof:name":"Van Leeuwen Wheeler Ltd",
    "wof:placetype":"venue"
},
  "geometry": {"coordinates":[-2.1184399128,52.4795303345],"type":"Point"}
}