{
  "type": "Feature",
  "properties": {
    "addr:full":"5 Lavender Sweep Battersea Greater London SW11 1DY",
    "addr:housenumber":"5",
    "addr:postcode":"sw11 1dy",
    "addr:street":"Lavender Sweep",
    "iso:country":"GB",
    "sg:address":"5 Lavender Sweep",
    "sg:city":"Battersea",
    "sg:classifiers":[
        {
            "category":"Food & Beverages",
            "subcategory":"Liquor & Beverages",
            "type":"Retail Goods"
        }
    ],
    "sg:phone":"+44 20 7924 1029",
    "sg:postcode":"SW11 1DY",
    "sg:province":"Greater London",
    "sg:tags":[
        "beer",
        "spirit",
        "wines"
    ],
    "wof:name":"Victoria Wine",
    "wof:placetype":"venue"
},
  "geometry": {"coordinates":[-0.1646929979,51.4639587402],"type":"Point"}
}