{
  "type": "Feature",
  "properties": {
    "addr:full":"Batley Hall, Old Hall Road Batley West Yorkshire WF17 0AX",
    "addr:postcode":"wf17 0ax",
    "addr:street":"Old Hall Road",
    "iso:country":"GB",
    "sg:address":"Batley Hall, Old Hall Road",
    "sg:city":"Batley",
    "sg:classifiers":[
        {
            "category":"Health Services",
            "subcategory":"Nursing And Care Facility",
            "type":"Services"
        }
    ],
    "sg:phone":"+44 1924 472063",
    "sg:postcode":"WF17 0AX",
    "sg:province":"West Yorkshire",
    "sg:tags":[
        "home"
    ],
    "wof:name":"Impalance Ltd.",
    "wof:placetype":"venue"
},
  "geometry": {"coordinates":[-1.654499,53.726421],"type":"Point"}
}