{
  "type": "Feature",
  "properties": {
    "addr:full":"5 Dolver Clo Corby Northamptonshire NN18 8NB",
    "addr:housenumber":"5",
    "addr:postcode":"nn18 8nb",
    "addr:street":"Dolver Clo",
    "iso:country":"GB",
    "sg:address":"5 Dolver Clo",
    "sg:city":"Corby",
    "sg:classifiers":[
        {
            "category":"Building & Trades",
            "subcategory":"Construction",
            "type":"Services"
        }
    ],
    "sg:phone":"+44 1536 742937",
    "sg:postcode":"NN18 8NB",
    "sg:province":"Northamptonshire",
    "sg:tags":[
        "builder"
    ],
    "wof:name":"L D L Builders",
    "wof:placetype":"venue"
},
  "geometry": {"coordinates":[-0.7175400257,52.4702148438],"type":"Point"}
}