{
  "type": "Feature",
  "properties": {
    "addr:full":"20 Rich Indstrl Estate, Crimscott Street London Greater London SE1 5TF",
    "addr:housenumber":"20",
    "addr:postcode":"se1 5tf",
    "addr:street":"Rich Indstrl Estate Crimscott Street",
    "iso:country":"GB",
    "sg:address":"20 Rich Indstrl Estate, Crimscott Street",
    "sg:city":"London",
    "sg:classifiers":[
        {
            "category":"Professional",
            "subcategory":"Printing & Photocopies",
            "type":"Services"
        }
    ],
    "sg:phone":"+44 20 7206 1000",
    "sg:postcode":"SE1 5TF",
    "sg:province":"Greater London",
    "sg:tags":[
        "duplicating",
        "copying"
    ],
    "wof:name":"F E Burman Ltd.",
    "wof:placetype":"venue"
},
  "geometry": {"coordinates":[-0.0794579983,51.4950180054],"type":"Point"}
}