{
  "type": "Feature",
  "properties": {
    "addr:full":"Po Box 139 Fleet Hampshire GU51 3GP",
    "addr:housenumber":"po",
    "addr:postcode":"gu51 3gp",
    "addr:street":"Box 139",
    "iso:country":"GB",
    "sg:address":"Po Box 139",
    "sg:city":"Fleet",
    "sg:classifiers":[
        {
            "category":"Personal",
            "type":"Services"
        }
    ],
    "sg:postcode":"GU51 3GP",
    "sg:province":"Hampshire",
    "sg:tags":[
        "dating",
        "friendship",
        "agency"
    ],
    "wof:name":"The Friendship Bureau",
    "wof:placetype":"venue"
},
  "geometry": {"coordinates":[-0.8304100037,51.2811012268],"type":"Point"}
}