{
  "type": "Feature",
  "properties": {
    "iso:country":"GB",
    "sg:address":"20 Lynmoor Rd",
    "sg:city":"Weymouth",
    "sg:classifiers":[
        {
            "category":"Insurance",
            "subcategory":"Insurance Agent",
            "type":"Services"
        }
    ],
    "sg:phone":"+44 1305 783364",
    "sg:postcode":"DT4 7TW",
    "sg:province":"Dorset",
    "wof:name":"Camlin & Co",
    "wof:placetype":"venue"
},
  "geometry": {"coordinates":[-2.450498,50.624626],"type":"Point"}
}