{
  "type": "Feature",
  "properties": {
    "iso:country":"GB",
    "sg:address":"11-12 Half Moon Court, Bartholemew Close",
    "sg:city":"London",
    "sg:classifiers":[
        {
            "category":"Building & Trades",
            "subcategory":"Construction",
            "type":"Services"
        }
    ],
    "sg:phone":"+44 20 7606 3706",
    "sg:postcode":"EC1A 7LB",
    "sg:province":"Greater London",
    "sg:tags":[
        "joinery"
    ],
    "wof:name":"Lister Joinery Ltd.",
    "wof:placetype":"venue"
},
  "geometry": {"coordinates":[-0.098222,51.519012],"type":"Point"}
}