{
  "type": "Feature",
  "properties": {
    "addr:full":"Royal Terrace Edinburgh City of Edinburgh EH7 5AB",
    "addr:postcode":"eh7 5ab",
    "addr:street":"Royal Terrace",
    "iso:country":"GB",
    "sg:address":"Royal Terrace",
    "sg:city":"Edinburgh",
    "sg:classifiers":[
        {
            "category":"Place Of Worship",
            "type":"Public Place"
        }
    ],
    "sg:phone":"+44 131 556 5588",
    "sg:postcode":"EH7 5AB",
    "sg:province":"City of Edinburgh",
    "wof:name":"Greenside Parish Church",
    "wof:placetype":"venue"
},
  "geometry": {"coordinates":[-3.1767990589,55.9568901062],"type":"Point"}
}