{
  "type": "Feature",
  "properties": {
    "addr:full":"Unit 2, Byker Development Centre, Albion Row Newcastle-upon-tyne Tyne and Wear NE6 1LQ",
    "addr:housenumber":"unit 2;development",
    "addr:postcode":"ne6 1lq",
    "addr:street":"Byker;Albion Row",
    "iso:country":"GB",
    "sg:address":"Unit 2, Byker Development Centre, Albion Row",
    "sg:city":"Newcastle-upon-tyne",
    "sg:classifiers":[
        {
            "category":"Shopping",
            "subcategory":"Computers & Home Electronics",
            "type":"Retail Goods"
        }
    ],
    "sg:phone":"+44 191 276 4219",
    "sg:postcode":"NE6 1LQ",
    "sg:province":"Tyne and Wear",
    "wof:name":"J C Furniture",
    "wof:placetype":"venue"
},
  "geometry": {"coordinates":[-1.5842100382,54.973400116],"type":"Point"}
}