{
  "type": "Feature",
  "properties": {
    "addr:full":"20 Theydon Gro Epping Essex CM16 4PY",
    "addr:housenumber":"20",
    "addr:postcode":"cm16 4py",
    "addr:street":"Theydon Gro",
    "iso:country":"GB",
    "sg:address":"20 Theydon Gro",
    "sg:city":"Epping",
    "sg:classifiers":[
        {
            "category":"Manufacturing",
            "subcategory":"Signs",
            "type":"Manufacturing & Wholesale Goods"
        }
    ],
    "sg:phone":"+44 1992 573520",
    "sg:postcode":"CM16 4PY",
    "sg:province":"Essex",
    "sg:tags":[
        "writer"
    ],
    "wof:name":"J L Gregg Signs",
    "wof:placetype":"venue"
},
  "geometry": {"coordinates":[0.1169459969,51.7003860474],"type":"Point"}
}