{
  "type": "Feature",
  "properties": {
    "iso:country":"GB",
    "sg:address":"59 Mount Crescent, Warley",
    "sg:city":"Brentwood",
    "sg:classifiers":[
        {
            "category":"Professional",
            "subcategory":"Management & Consulting",
            "type":"Services"
        },
        {
            "category":"Building & Trades",
            "subcategory":"Electrical",
            "type":"Services"
        }
    ],
    "sg:phone":"+44 1277 210893",
    "sg:postcode":"CM14 5DD",
    "sg:province":"Essex",
    "sg:tags":[
        "fire",
        "consultant",
        "protection",
        "electrician",
        "contractor"
    ],
    "wof:name":"ELECTROPLAN CONTRACTING LTD",
    "wof:placetype":"venue"
},
  "geometry": {"coordinates":[0.3080460131,51.6116676331],"type":"Point"}
}