{
  "type": "Feature",
  "properties": {
    "iso:country":"GB",
    "sg:address":"Knowles Springs Industrial Estate",
    "sg:city":"Keighley",
    "sg:classifiers":[
        {
            "category":"Sports & Exercise",
            "subcategory":"Tennis Court",
            "type":"Entertainment"
        }
    ],
    "sg:phone":"+44 1535 606817",
    "sg:postcode":"BD21 1AQ",
    "sg:province":"West Yorkshire",
    "sg:tags":[
        "breakdown",
        "recovery"
    ],
    "wof:name":"K Petty",
    "wof:placetype":"venue"
},
  "geometry": {"coordinates":[-1.909674,53.866364],"type":"Point"}
}