{
  "type": "Feature",
  "properties": {
    "iso:country":"GB",
    "sg:address":"119 London Road",
    "sg:city":"Leicester",
    "sg:classifiers":[
        {
            "category":"Professional",
            "subcategory":"Lawyer & Legal Services",
            "type":"Services"
        }
    ],
    "sg:phone":"+44 116 254 1609",
    "sg:postcode":"LE2 0QT",
    "sg:province":"Leicestershire",
    "sg:tags":[
        "solicitor"
    ],
    "wof:name":"Michael Hill Partnership",
    "wof:placetype":"venue"
},
  "geometry": {"coordinates":[-1.121648,52.628357],"type":"Point"}
}