{
  "type": "Feature",
  "properties": {
    "addr:full":"1a Wellington Road Dereham Norfolk NR19 2BP",
    "addr:housenumber":"1a",
    "addr:postcode":"nr19 2bp",
    "addr:street":"Wellington Road",
    "iso:country":"GB",
    "sg:address":"1a Wellington Road",
    "sg:city":"Dereham",
    "sg:classifiers":[
        {
            "category":"Professional",
            "subcategory":"Lawyer & Legal Services",
            "type":"Services"
        }
    ],
    "sg:phone":"+44 1362 690960",
    "sg:postcode":"NR19 2BP",
    "sg:province":"Norfolk",
    "sg:tags":[
        "solicitor"
    ],
    "wof:name":"Jeremy Whigham",
    "wof:placetype":"venue"
},
  "geometry": {"coordinates":[0.9410600066,52.68227005],"type":"Point"}
}