{
  "type": "Feature",
  "properties": {
    "addr:full":"37a Market Place Cirencester Gloucestershire GL7 2NX",
    "addr:housenumber":"37a",
    "addr:postcode":"gl7 2nx",
    "addr:street":"Market Place",
    "iso:country":"GB",
    "sg:address":"37a Market Place",
    "sg:city":"Cirencester",
    "sg:classifiers":[
        {
            "category":"Professional",
            "subcategory":"Art Services",
            "type":"Services"
        }
    ],
    "sg:phone":"+44 1285 666425",
    "sg:postcode":"GL7 2NX",
    "sg:province":"Gloucestershire",
    "sg:tags":[
        "consultant",
        "design"
    ],
    "wof:name":"The Saffron House Consultancy Ltd.",
    "wof:placetype":"venue"
},
  "geometry": {"coordinates":[-1.966327,51.717083],"type":"Point"}
}