{
  "type": "Feature",
  "properties": {
    "iso:country":"GB",
    "sg:address":"73 West Bars",
    "sg:city":"Chesterfield",
    "sg:classifiers":[
        {
            "category":"Health Services",
            "subcategory":"Optometrist",
            "type":"Services"
        }
    ],
    "sg:postcode":"S40 1BA",
    "sg:province":"Derbyshire",
    "sg:tags":[
        "optician"
    ],
    "wof:name":"B Davies Opticians",
    "wof:placetype":"venue"
},
  "geometry": {"coordinates":[-1.436673,53.23576],"type":"Point"}
}