{
  "type": "Feature",
  "properties": {
    "iso:country":"GB",
    "sg:address":"2 Upper Bridge Street, Wye",
    "sg:city":"Ashford",
    "sg:classifiers":[
        {
            "category":"Real Estate",
            "subcategory":"Architect",
            "type":"Services"
        }
    ],
    "sg:phone":"+44 1233 812841",
    "sg:postcode":"TN25 5AF",
    "sg:province":"Kent",
    "wof:name":"Patrick Keegan Architects",
    "wof:placetype":"venue"
},
  "geometry": {"coordinates":[0.93802,51.182201],"type":"Point"}
}