{
  "type": "Feature",
  "properties": {
    "addr:full":"92 Southampton Row London Greater London WC1B 4BH",
    "addr:housenumber":"92",
    "addr:postcode":"wc1b 4bh",
    "addr:street":"Southampton Row",
    "iso:country":"GB",
    "sg:address":"92 Southampton Row",
    "sg:city":"London",
    "sg:classifiers":[
        {
            "category":"Travel",
            "subcategory":"Hotels & Motels",
            "type":"Entertainment"
        }
    ],
    "sg:phone":"+44 20 7242 2828",
    "sg:postcode":"WC1B 4BH",
    "sg:province":"Greater London",
    "wof:name":"Bonnington Hotels Ltd.",
    "wof:placetype":"venue"
},
  "geometry": {"coordinates":[-0.1220460013,51.5198745728],"type":"Point"}
}