{
  "type": "Feature",
  "properties": {
    "addr:full":"195 Manford Way Chigwell Essex IG7 4DJ",
    "addr:housenumber":"195",
    "addr:postcode":"ig7 4dj",
    "addr:street":"Manford Way",
    "iso:country":"GB",
    "sg:address":"195 Manford Way",
    "sg:city":"Chigwell",
    "sg:classifiers":[
        {
            "category":"Cinema",
            "subcategory":"Movie Rental",
            "type":"Entertainment"
        }
    ],
    "sg:phone":"+44 20 8500 4718",
    "sg:postcode":"IG7 4DJ",
    "sg:province":"Essex",
    "sg:tags":[
        "video",
        "library"
    ],
    "wof:name":"Capital Video",
    "wof:placetype":"venue"
},
  "geometry": {"coordinates":[0.106717,51.608356],"type":"Point"}
}