{
  "type": "Feature",
  "properties": {
    "iso:country":"GB",
    "sg:address":"Marston Ferry Road",
    "sg:city":"Oxford",
    "sg:classifiers":[
        {
            "category":"Education",
            "subcategory":"School",
            "type":"Public Place"
        },
        {
            "category":"Government",
            "subcategory":"Office",
            "type":"Public Place"
        }
    ],
    "sg:phone":"+44 1865 558719",
    "sg:postcode":"OX2 7EE",
    "sg:province":"Oxfordshire",
    "sg:tags":[
        "local",
        "authority"
    ],
    "wof:name":"Cherwell Upper School",
    "wof:placetype":"venue"
},
  "geometry": {"coordinates":[-1.262619,51.774361],"type":"Point"}
}