{
  "type": "Feature",
  "properties": {
    "iso:country":"GB",
    "sg:address":"72 Shortmead Street",
    "sg:city":"Biggleswade",
    "sg:classifiers":[
        {
            "category":"Cinema",
            "subcategory":"Movie Rental",
            "type":"Entertainment"
        }
    ],
    "sg:phone":"+44 1767 318966",
    "sg:postcode":"SG18 0AP",
    "sg:province":"Bedfordshire",
    "sg:tags":[
        "video",
        "library"
    ],
    "wof:name":"Video Direct",
    "wof:placetype":"venue"
},
  "geometry": {"coordinates":[-0.267023,52.08886],"type":"Point"}
}