{
  "type": "Feature",
  "properties": {
    "addr:full":"Slad Mills, Lansdown Stroud Gloucestershire GL5 1BX",
    "addr:postcode":"gl5 1bx",
    "addr:street":"Lansdown",
    "iso:country":"GB",
    "sg:address":"Slad Mills, Lansdown",
    "sg:city":"Stroud",
    "sg:classifiers":[
        {
            "category":"Home & Garden",
            "subcategory":"Building Materials",
            "type":"Retail Goods"
        }
    ],
    "sg:phone":"+44 1453 758300",
    "sg:postcode":"GL5 1BX",
    "sg:province":"Gloucestershire",
    "sg:tags":[
        "tanks",
        "cistern",
        "vat"
    ],
    "wof:name":"Dipsticks",
    "wof:placetype":"venue"
},
  "geometry": {"coordinates":[-2.193062067,51.7488975525],"type":"Point"}
}