{
  "type": "Feature",
  "properties": {
    "iso:country":"GB",
    "sg:address":"477 Otley Road",
    "sg:city":"Leeds",
    "sg:classifiers":[
        {
            "category":"Shopping",
            "subcategory":"Crafts & Fabrics",
            "type":"Retail Goods"
        },
        {
            "category":"Wholesale",
            "subcategory":"Vending Machines",
            "type":"Manufacturing & Wholesale Goods"
        }
    ],
    "sg:phone":"+44 113 267 4710",
    "sg:postcode":"LS16 7NR",
    "sg:province":"West Yorkshire",
    "sg:tags":[
        "knitting",
        "sewing",
        "commercial"
    ],
    "wof:name":"F D Duckett & Co",
    "wof:placetype":"venue"
},
  "geometry": {"coordinates":[-1.591534,53.854542],"type":"Point"}
}