{
  "type": "Feature",
  "properties": {
    "addr:full":"Clockbarn House, Hambledon Road Godalming Surrey GU8 4AY",
    "addr:postcode":"gu8 4ay",
    "addr:street":"Hambledon Road",
    "iso:country":"GB",
    "sg:address":"Clockbarn House, Hambledon Road",
    "sg:city":"Godalming",
    "sg:classifiers":[
        {
            "category":"Shopping",
            "type":"Retail Goods"
        }
    ],
    "sg:phone":"+44 1483 419779",
    "sg:postcode":"GU8 4AY",
    "sg:province":"Surrey",
    "sg:tags":[
        "part",
        "accessory"
    ],
    "wof:name":"Kam Differentials Ltd.",
    "wof:placetype":"venue"
},
  "geometry": {"coordinates":[-0.6186090112,51.1446151733],"type":"Point"}
}