{
  "type": "Feature",
  "properties": {
    "iso:country":"GB",
    "sg:address":"Firtree Cot, Ockwells Rd",
    "sg:city":"Maidenhead",
    "sg:classifiers":[
        {
            "category":"Utilities",
            "subcategory":"Refuse",
            "type":"Services"
        }
    ],
    "sg:phone":"+44 1628 770225",
    "sg:postcode":"SL6 3AA",
    "sg:province":"Berkshire",
    "sg:tags":[
        "skip",
        "hire"
    ],
    "wof:name":"W L G Waste Contractors",
    "wof:placetype":"venue"
},
  "geometry": {"coordinates":[-0.727257,51.522373],"type":"Point"}
}