{
  "type": "Feature",
  "properties": {
    "addr:full":"347 Portobello Road London Greater London W10 5SA",
    "addr:housenumber":"347",
    "addr:postcode":"w10 5sa",
    "addr:street":"Portobello Road",
    "iso:country":"GB",
    "sg:address":"347 Portobello Road",
    "sg:city":"London",
    "sg:classifiers":[
        {
            "category":"Manufacturing",
            "subcategory":"Textiles",
            "type":"Manufacturing & Wholesale Goods"
        }
    ],
    "sg:phone":"+44 20 8932 1816",
    "sg:postcode":"W10 5SA",
    "sg:province":"Greater London",
    "sg:tags":[
        "designer"
    ],
    "wof:name":"Beckford Silk Interiors",
    "wof:placetype":"venue"
},
  "geometry": {"coordinates":[-0.2104959935,51.5214004517],"type":"Point"}
}