{
  "type": "Feature",
  "properties": {
    "iso:country":"GB",
    "sg:address":"1 Market Place",
    "sg:city":"Pickering",
    "sg:classifiers":[
        {
            "category":"Arts & Performance",
            "subcategory":"Art Gallery",
            "type":"Entertainment"
        }
    ],
    "sg:phone":"+44 1751 477510",
    "sg:postcode":"YO18 7AA",
    "sg:province":"North Yorkshire",
    "wof:name":"K K Gallery",
    "wof:placetype":"venue"
},
  "geometry": {"coordinates":[-0.7786599994,54.2460594177],"type":"Point"}
}