{
  "type": "Feature",
  "properties": {
    "iso:country":"GB",
    "sg:address":"27 Pickhurst Rise",
    "sg:city":"West Wickham",
    "sg:classifiers":[
        {
            "category":"Social Services",
            "subcategory":"Job Training",
            "type":"Services"
        }
    ],
    "sg:postcode":"BR4 0AB",
    "sg:province":"Kent",
    "sg:tags":[
        "translator",
        "interpreter"
    ],
    "wof:name":"J Clay",
    "wof:placetype":"venue"
},
  "geometry": {"coordinates":[-0.009727,51.379986],"type":"Point"}
}