{
  "type": "Feature",
  "properties": {
    "iso:country":"GB",
    "sg:address":"124 Whateley Crescent",
    "sg:city":"Birmingham",
    "sg:classifiers":[
        {
            "category":"Building & Trades",
            "subcategory":"Plumbing",
            "type":"Services"
        },
        {
            "category":"Organizations",
            "subcategory":"Membership Organization",
            "type":"Services"
        }
    ],
    "sg:phone":"+44 121 747 6024",
    "sg:postcode":"B36 0DP",
    "sg:province":"West Midlands",
    "sg:tags":[
        "clearance",
        "drain",
        "sewer"
    ],
    "wof:name":"W E T & Co",
    "wof:placetype":"venue"
},
  "geometry": {"coordinates":[-1.766587,52.504574],"type":"Point"}
}