{
  "type": "Feature",
  "properties": {
    "iso:country":"GB",
    "sg:address":"8 Rawlinson Rd",
    "sg:city":"Leamington Spa",
    "sg:classifiers":[
        {
            "category":"Professional",
            "subcategory":"Printing & Photocopies",
            "type":"Services"
        }
    ],
    "sg:phone":"+44 1926 831759",
    "sg:postcode":"CV32 7QS",
    "sg:province":"Warwickshire",
    "sg:tags":[
        "process",
        "screen",
        "printer"
    ],
    "wof:name":"Screenart",
    "wof:placetype":"venue"
},
  "geometry": {"coordinates":[-1.521312,52.297192],"type":"Point"}
}