{
  "type": "Feature",
  "properties": {
    "addr:full":"The Spinney, Tangier Park Basingstoke Hampshire RG23 8PH",
    "addr:postcode":"rg23 8ph",
    "addr:street":"The;Tangier Park",
    "iso:country":"GB",
    "sg:address":"The Spinney, Tangier Park",
    "sg:city":"Basingstoke",
    "sg:classifiers":[
        {
            "category":"Building & Trades",
            "subcategory":"Construction",
            "type":"Services"
        }
    ],
    "sg:phone":"+44 1256 780674",
    "sg:postcode":"RG23 8PH",
    "sg:province":"Hampshire",
    "sg:tags":[
        "builder"
    ],
    "wof:name":"J B P Building Contractors",
    "wof:placetype":"venue"
},
  "geometry": {"coordinates":[-1.1674799919,51.2745895386],"type":"Point"}
}