{
  "type": "Feature",
  "properties": {
    "iso:country":"GB",
    "sg:address":"The Spinney, Tangier Park",
    "sg:city":"Basingstoke",
    "sg:classifiers":[
        {
            "category":"Building & Trades",
            "subcategory":"Construction",
            "type":"Services"
        }
    ],
    "sg:phone":"+44 1256 780674",
    "sg:postcode":"RG23 8PH",
    "sg:province":"Hampshire",
    "sg:tags":[
        "builder"
    ],
    "wof:name":"J B P Building Contractors",
    "wof:placetype":"venue"
},
  "geometry": {"coordinates":[-1.1674799919,51.2745895386],"type":"Point"}
}