{
  "type": "Feature",
  "properties": {
    "addr:full":"27 James Street London Greater London W1U 1DX",
    "addr:housenumber":"27",
    "addr:postcode":"w1u 1dx",
    "addr:street":"James Street",
    "iso:country":"GB",
    "sg:address":"27 James Street",
    "sg:city":"London",
    "sg:classifiers":[
        {
            "category":"Shopping",
            "subcategory":"Shoes",
            "type":"Retail Goods"
        }
    ],
    "sg:phone":"+44 20 7224 1921",
    "sg:postcode":"W1U 1DX",
    "sg:province":"Greater London",
    "sg:tags":[
        "shop"
    ],
    "wof:name":"Scarpe Diem Ltd.",
    "wof:placetype":"venue"
},
  "geometry": {"coordinates":[-0.150896,51.515244],"type":"Point"}
}