{
  "type": "Feature",
  "properties": {
    "iso:country":"GB",
    "sg:address":"44a Station Road, Padgate",
    "sg:city":"Warrington",
    "sg:classifiers":[
        {
            "category":"Retail",
            "subcategory":"Auto Repair",
            "type":"Services"
        }
    ],
    "sg:phone":"+44 1925 826683",
    "sg:postcode":"WA2 0QJ",
    "sg:province":"Cheshire",
    "sg:tags":[
        "modification",
        "garage"
    ],
    "wof:name":"Fearnhead Auto Centre",
    "wof:placetype":"venue"
},
  "geometry": {"coordinates":[-2.555909,53.407822],"type":"Point"}
}