{
  "type": "Feature",
  "properties": {
    "iso:country":"GB",
    "sg:address":"Woodlands Lane",
    "sg:city":"Chichester",
    "sg:classifiers":[
        {
            "category":"Education",
            "subcategory":"School",
            "type":"Public Place"
        }
    ],
    "sg:phone":"+44 1243 785965",
    "sg:postcode":"PO19 5PA",
    "sg:province":"West Sussex",
    "sg:tags":[
        "local",
        "authority"
    ],
    "sg:website":"http://www.st-anthonys.w-sussex.sch.uk",
    "wof:name":"St Anthony'S Special School",
    "wof:placetype":"venue"
},
  "geometry": {"coordinates":[-0.783704,50.844959],"type":"Point"}
}