{
  "type": "Feature",
  "properties": {
    "addr:full":"Hawkins Farm, Mendlesham Green Stowmarket Suffolk IP14 5RB",
    "addr:postcode":"ip14 5rb",
    "addr:street":"Hawkins;Mendlesham Green",
    "iso:country":"GB",
    "sg:address":"Hawkins Farm, Mendlesham Green",
    "sg:city":"Stowmarket",
    "sg:classifiers":[
        {
            "category":"Sports & Exercise",
            "subcategory":"Stables",
            "type":"Entertainment"
        },
        {
            "category":"Personal",
            "subcategory":"Adult",
            "type":"Services"
        }
    ],
    "sg:phone":"+44 1449 766264",
    "sg:postcode":"IP14 5RB",
    "sg:province":"Suffolk",
    "sg:tags":[
        "schools",
        "riding",
        "livery",
        "equestrian",
        "centre"
    ],
    "wof:name":"Hawkins Farm Riding Stables",
    "wof:placetype":"venue"
},
  "geometry": {"coordinates":[1.082645,52.2505],"type":"Point"}
}