{
  "type": "Feature",
  "properties": {
    "addr:full":"75 Crawthorne Road Peterborough Cambridgeshire PE1 4AE",
    "addr:housenumber":"75",
    "addr:postcode":"pe1 4ae",
    "addr:street":"Crawthorne Road",
    "iso:country":"GB",
    "sg:address":"75 Crawthorne Road",
    "sg:city":"Peterborough",
    "sg:classifiers":[
        {
            "category":"Personal",
            "subcategory":"Beauty Salon",
            "type":"Services"
        }
    ],
    "sg:phone":"+44 1733 566160",
    "sg:postcode":"PE1 4AE",
    "sg:province":"Cambridgeshire",
    "sg:tags":[
        "ladies",
        "lady",
        "hairdresser"
    ],
    "wof:name":"Betty Berry",
    "wof:placetype":"venue"
},
  "geometry": {"coordinates":[-0.236919,52.577972],"type":"Point"}
}