{
  "type": "Feature",
  "properties": {
    "addr:full":"44 The Avenue Watford Hertfordshire WD17 4NS",
    "addr:housenumber":"44",
    "addr:postcode":"wd17 4ns",
    "addr:street":"The Avenue",
    "iso:country":"GB",
    "sg:address":"44 The Avenue",
    "sg:city":"Watford",
    "sg:classifiers":[
        {
            "category":"Social Services",
            "subcategory":"Retirement Home",
            "type":"Services"
        }
    ],
    "sg:phone":"+44 1923 226946",
    "sg:postcode":"WD17 4NS",
    "sg:province":"Hertfordshire",
    "sg:tags":[
        "residential",
        "care"
    ],
    "wof:name":"Caretech Community Services Ltd.",
    "wof:placetype":"venue"
},
  "geometry": {"coordinates":[-0.404873,51.6619],"type":"Point"}
}