{
  "type": "Feature",
  "properties": {
    "iso:country":"GB",
    "sg:address":"Highview Farm, Dane End",
    "sg:city":"Ware",
    "sg:classifiers":[
        {
            "category":"Farming",
            "subcategory":"Livestock Farm",
            "type":"Manufacturing & Wholesale Goods"
        }
    ],
    "sg:postcode":"SG12 0NY",
    "sg:province":"Hertfordshire",
    "sg:tags":[
        "others"
    ],
    "wof:name":"William Ives",
    "wof:placetype":"venue"
},
  "geometry": {"coordinates":[-0.035126999,51.8163375854],"type":"Point"}
}