{
  "type": "Feature",
  "properties": {
    "iso:country":"GB",
    "sg:address":"21 Highfield Road",
    "sg:city":"Dartford",
    "sg:classifiers":[
        {
            "category":"Real Estate",
            "subcategory":"Surveying",
            "type":"Services"
        }
    ],
    "sg:phone":"+44 1322 223827",
    "sg:postcode":"DA1 2JS",
    "sg:province":"Kent",
    "sg:tags":[
        "surveyor",
        "valuer"
    ],
    "wof:name":"Campbell Clarke Surveyors & Valuers",
    "wof:placetype":"venue"
},
  "geometry": {"coordinates":[0.212216,51.44334],"type":"Point"}
}