{
  "type": "Feature",
  "properties": {
    "addr:full":"6 Arkwright Rd Reading Berkshire RG2 0LU",
    "addr:housenumber":"6",
    "addr:postcode":"rg2 0lu",
    "addr:street":"Arkwright Rd",
    "iso:country":"GB",
    "sg:address":"6 Arkwright Rd",
    "sg:city":"Reading",
    "sg:classifiers":[
        {
            "category":"Organizations",
            "subcategory":"Non-profit Organization",
            "type":"Services"
        }
    ],
    "sg:phone":"+44 118 975 2994",
    "sg:postcode":"RG2 0LU",
    "sg:province":"Berkshire",
    "sg:tags":[
        "organisation",
        "voluntary",
        "charity"
    ],
    "wof:name":"Bicycle Helmet Initiative Trust",
    "wof:placetype":"venue"
},
  "geometry": {"coordinates":[-0.970537,51.43771],"type":"Point"}
}