{
  "type": "Feature",
  "properties": {
    "addr:full":"24 New Kirk Road, Bearsden Glasgow East Dunbartonshire G61 3SL",
    "addr:housenumber":"24",
    "addr:postcode":"g61 3sl",
    "addr:street":"New Kirk Road",
    "iso:country":"GB",
    "sg:address":"24 New Kirk Road, Bearsden",
    "sg:city":"Glasgow",
    "sg:classifiers":[
        {
            "category":"Real Estate",
            "subcategory":"Architect",
            "type":"Services"
        }
    ],
    "sg:phone":"+44 141 942 3025",
    "sg:postcode":"G61 3SL",
    "sg:province":"East Dunbartonshire",
    "sg:tags":[
        "architectural"
    ],
    "wof:name":"LILIAN AND CHRISTOPHER JOHNSTONE",
    "wof:placetype":"venue"
},
  "geometry": {"coordinates":[-4.332698822,55.920791626],"type":"Point"}
}