{
  "type": "Feature",
  "properties": {
    "addr:full":"St Pauls Road Stockport Cheshire SK4 4RY",
    "addr:postcode":"sk4 4ry",
    "addr:street":"St Pauls Road",
    "iso:country":"GB",
    "sg:address":"St Pauls Road",
    "sg:city":"Stockport",
    "sg:classifiers":[
        {
            "category":"Farming",
            "subcategory":"Nursery",
            "type":"Manufacturing & Wholesale Goods"
        }
    ],
    "sg:phone":"+44 161 442 7767",
    "sg:postcode":"SK4 4RY",
    "sg:province":"Cheshire",
    "sg:tags":[
        "creche"
    ],
    "wof:name":"The Charnwood Trust",
    "wof:placetype":"venue"
},
  "geometry": {"coordinates":[-2.1862668991,53.4222106934],"type":"Point"}
}