{
  "type": "Feature",
  "properties": {
    "addr:full":"Fourth Way, Avonmouth Bristol City of Bristol BS11 8DX",
    "addr:postcode":"bs11 8dx",
    "addr:street":"Fourth Way",
    "iso:country":"GB",
    "sg:address":"Fourth Way, Avonmouth",
    "sg:city":"Bristol",
    "sg:classifiers":[
        {
            "category":"Wholesale",
            "subcategory":"Machinery & Supplies",
            "type":"Manufacturing & Wholesale Goods"
        }
    ],
    "sg:phone":"+44 117 982 0600",
    "sg:postcode":"BS11 8DX",
    "sg:province":"City of Bristol",
    "sg:tags":[
        "industrial",
        "commercial"
    ],
    "wof:name":"Finning (U K) Ltd.",
    "wof:placetype":"venue"
},
  "geometry": {"coordinates":[-2.678245,51.501419],"type":"Point"}
}