{
  "type": "Feature",
  "properties": {
    "addr:full":"26 College Crescent London Greater London NW3 5LH",
    "addr:housenumber":"26",
    "addr:postcode":"nw3 5lh",
    "addr:street":"College Crescent",
    "iso:country":"GB",
    "sg:address":"26 College Crescent",
    "sg:city":"London",
    "sg:classifiers":[
        {
            "category":"Professional",
            "subcategory":"Employment Agencies",
            "type":"Services"
        }
    ],
    "sg:phone":"+44 20 7387 9245",
    "sg:postcode":"NW3 5LH",
    "sg:province":"Greater London",
    "sg:tags":[
        "modelling"
    ],
    "wof:name":"Lookalikes",
    "wof:placetype":"venue"
},
  "geometry": {"coordinates":[-0.175494,51.545753],"type":"Point"}
}