{
  "type": "Feature",
  "properties": {
    "iso:country":"GB",
    "sg:address":"The Bungalow, Daisy Bank",
    "sg:city":"Lancaster",
    "sg:classifiers":[
        {
            "category":"Transit Center",
            "subcategory":"Passenger",
            "type":"Transportation"
        }
    ],
    "sg:phone":"+44 1524 35493",
    "sg:postcode":"LA1 3JN",
    "sg:province":"Lancashire",
    "sg:tags":[
        "boarding",
        "kennel",
        "catteries"
    ],
    "wof:name":"Daisybank Cattery",
    "wof:placetype":"venue"
},
  "geometry": {"coordinates":[-2.799029,54.044537],"type":"Point"}
}