{
  "type": "Feature",
  "properties": {
    "iso:country":"GB",
    "sg:address":"42 Ware Road",
    "sg:city":"Hoddesdon",
    "sg:classifiers":[
        {
            "category":"Home & Garden",
            "subcategory":"Furniture",
            "type":"Retail Goods"
        }
    ],
    "sg:phone":"+44 1992 420400",
    "sg:postcode":"EN11 9DU",
    "sg:province":"Essex",
    "wof:name":"Rob Stock & Furniture",
    "wof:placetype":"venue"
},
  "geometry": {"coordinates":[-0.012274,51.7672],"type":"Point"}
}