{
  "type": "Feature",
  "properties": {
    "iso:country":"GB",
    "sg:address":"3-5 Brockwell Road, Kingstanding",
    "sg:city":"Birmingham",
    "sg:classifiers":[
        {
            "category":"Shopping",
            "subcategory":"Discount & Variety Stores",
            "type":"Retail Goods"
        }
    ],
    "sg:phone":"+44 121 360 7350",
    "sg:postcode":"B44 9PF",
    "sg:province":"West Midlands",
    "sg:tags":[
        "shop",
        "model"
    ],
    "wof:name":"Mikes Models",
    "wof:placetype":"venue"
},
  "geometry": {"coordinates":[-1.892176,52.558327],"type":"Point"}
}