{
  "type": "Feature",
  "properties": {
    "addr:full":"2 Christopher Road Leeds West Yorkshire LS6 2JX",
    "addr:housenumber":"2",
    "addr:postcode":"ls6 2jx",
    "addr:street":"Christopher Road",
    "iso:country":"GB",
    "sg:address":"2 Christopher Road",
    "sg:city":"Leeds",
    "sg:classifiers":[
        {
            "category":"Professional",
            "subcategory":"Printing & Photocopies",
            "type":"Services"
        }
    ],
    "sg:phone":"+44 113 244 2265",
    "sg:postcode":"LS6 2JX",
    "sg:province":"West Yorkshire",
    "sg:tags":[
        "printer"
    ],
    "wof:name":"Bansal Printers",
    "wof:placetype":"venue"
},
  "geometry": {"coordinates":[-1.5534540415,53.8143005371],"type":"Point"}
}