{
  "type": "Feature",
  "properties": {
    "addr:full":"9 Branksome Wood Rd Bournemouth Dorset BH2 6BT",
    "addr:housenumber":"9",
    "addr:postcode":"bh2 6bt",
    "addr:street":"Branksome Wood Rd",
    "iso:country":"GB",
    "sg:address":"9 Branksome Wood Rd",
    "sg:city":"Bournemouth",
    "sg:classifiers":[
        {
            "category":"Health Services",
            "subcategory":"Nursing And Care Facility",
            "type":"Services"
        }
    ],
    "sg:phone":"+44 1202 290695",
    "sg:postcode":"BH2 6BT",
    "sg:province":"Dorset",
    "sg:tags":[
        "home"
    ],
    "wof:name":"The Seward Nursing Home",
    "wof:placetype":"venue"
},
  "geometry": {"coordinates":[-1.886979,50.724232],"type":"Point"}
}