{
  "type": "Feature",
  "properties": {
    "addr:full":"Van Garage, The Van Llanidloes Powys SY18 6NP",
    "addr:postcode":"sy18 6np",
    "addr:street":"The;Llanidloes",
    "iso:country":"GB",
    "sg:address":"Van Garage, The Van",
    "sg:city":"Llanidloes",
    "sg:classifiers":[
        {
            "category":"Retail",
            "subcategory":"Auto Repair",
            "type":"Services"
        }
    ],
    "sg:postcode":"SY18 6NP",
    "sg:province":"Powys",
    "sg:tags":[
        "modification",
        "garage"
    ],
    "wof:name":"J M Bavistock",
    "wof:placetype":"venue"
},
  "geometry": {"coordinates":[-3.540166,52.445915],"type":"Point"}
}