{
  "type": "Feature",
  "properties": {
    "iso:country":"GB",
    "sg:address":"3 The Drive, Ponsbourne Park, Newgate Street",
    "sg:city":"Hertford",
    "sg:classifiers":[
        {
            "category":"Professional",
            "subcategory":"Engineering",
            "type":"Services"
        },
        {
            "category":"Real Estate",
            "subcategory":"Architect",
            "type":"Services"
        }
    ],
    "sg:phone":"+44 1707 874636",
    "sg:postcode":"SG13 8QS",
    "sg:province":"Hertfordshire",
    "sg:tags":[
        "consultant",
        "structural"
    ],
    "wof:name":"Subsidence Investigation & Advisory Services",
    "wof:placetype":"venue"
},
  "geometry": {"coordinates":[-0.115759,51.72847],"type":"Point"}
}