{
  "type": "Feature",
  "properties": {
    "iso:country":"GB",
    "sg:address":"108 Depot Road",
    "sg:city":"Horsham",
    "sg:classifiers":[
        {
            "category":"Professional",
            "subcategory":"Engineering",
            "type":"Services"
        },
        {
            "category":"Building & Trades",
            "subcategory":"Electrical",
            "type":"Services"
        }
    ],
    "sg:phone":"+44 1403 261688",
    "sg:postcode":"RH13 5HP",
    "sg:province":"West Sussex",
    "sg:tags":[
        "engineer",
        "electrician",
        "contractor"
    ],
    "wof:name":"Brian Moore",
    "wof:placetype":"venue"
},
  "geometry": {"coordinates":[-0.306554,51.064075],"type":"Point"}
}