{
  "type": "Feature",
  "properties": {
    "addr:full":"48 Vicarage Farm Road Hounslow Greater London TW5 0AB",
    "addr:housenumber":"48",
    "addr:postcode":"tw5 0ab",
    "addr:street":"Vicarage Farm Road",
    "iso:country":"GB",
    "sg:address":"48 Vicarage Farm Road",
    "sg:city":"Hounslow",
    "sg:classifiers":[
        {
            "category":"Shopping",
            "subcategory":"Pharmacy",
            "type":"Retail Goods"
        }
    ],
    "sg:phone":"+44 20 8570 1796",
    "sg:postcode":"TW5 0AB",
    "sg:province":"Greater London",
    "sg:tags":[
        "pharmacist",
        "dispensing",
        "chemist"
    ],
    "wof:name":"Bhogal Chemist",
    "wof:placetype":"venue"
},
  "geometry": {"coordinates":[-0.3842589855,51.4767723083],"type":"Point"}
}