{
  "type": "Feature",
  "properties": {
    "iso:country":"GB",
    "sg:address":"130-132 Nantwich Road",
    "sg:city":"Crewe",
    "sg:classifiers":[
        {
            "category":"Manufacturing",
            "subcategory":"Chemicals & Compounds",
            "type":"Manufacturing & Wholesale Goods"
        }
    ],
    "sg:postcode":"CW2 6AZ",
    "sg:province":"Cheshire",
    "sg:tags":[
        "pesticide"
    ],
    "wof:name":"Hawthorn Applied Technology Limited",
    "wof:placetype":"venue"
},
  "geometry": {"coordinates":[-2.44197,53.088032],"type":"Point"}
}