{
  "type": "Feature",
  "properties": {
    "addr:full":"20 Mount Gro Birkenhead Merseyside L41 2UJ",
    "addr:housenumber":"20",
    "addr:postcode":"l41 2uj",
    "addr:street":"Mount Gro",
    "iso:country":"GB",
    "sg:address":"20 Mount Gro",
    "sg:city":"Birkenhead",
    "sg:classifiers":[
        {
            "category":"Retail",
            "subcategory":"Driving School",
            "type":"Services"
        }
    ],
    "sg:phone":"+44 151 652 1176",
    "sg:postcode":"L41 2UJ",
    "sg:province":"Merseyside",
    "wof:name":"A & A Driving School",
    "wof:placetype":"venue"
},
  "geometry": {"coordinates":[-3.033905983,53.3849334717],"type":"Point"}
}