{
  "type": "Feature",
  "properties": {
    "iso:country":"GB",
    "sg:address":"Shulbrede Priory, Linchmere",
    "sg:city":"Haslemere",
    "sg:classifiers":[
        {
            "category":"Professional",
            "subcategory":"Engineering",
            "type":"Services"
        }
    ],
    "sg:postcode":"GU27 3NQ",
    "sg:province":"Hampshire",
    "sg:tags":[
        "consultant",
        "structural"
    ],
    "wof:name":"Ian Russell",
    "wof:placetype":"venue"
},
  "geometry": {"coordinates":[-0.759396,51.066841],"type":"Point"}
}