{
  "type": "Feature",
  "properties": {
    "addr:full":"12 Honeyberry Drive, Ratrey Blairgowrie Perth and Kinross PH10 7RB",
    "addr:housenumber":"12",
    "addr:postcode":"ph10 7rb",
    "addr:street":"Honeyberry Drive;Blairgowrie",
    "iso:country":"GB",
    "sg:address":"12 Honeyberry Drive, Ratrey",
    "sg:city":"Blairgowrie",
    "sg:classifiers":[
        {
            "category":"Retail",
            "subcategory":"Driving School",
            "type":"Services"
        }
    ],
    "sg:phone":"+44 1250 875525",
    "sg:postcode":"PH10 7RB",
    "sg:province":"Perth and Kinross",
    "wof:name":"McLeod School of Motoring",
    "wof:placetype":"venue"
},
  "geometry": {"coordinates":[-3.324816,56.594662],"type":"Point"}
}