{
  "type": "Feature",
  "properties": {
    "addr:full":"138 Coldharbour Lane Hayes Greater London UB3 3HG",
    "addr:housenumber":"138",
    "addr:postcode":"ub3 3hg",
    "addr:street":"Coldharbour Lane",
    "iso:country":"GB",
    "sg:address":"138 Coldharbour Lane",
    "sg:city":"Hayes",
    "sg:classifiers":[
        {
            "category":"Health Services",
            "subcategory":"Dentist",
            "type":"Services"
        }
    ],
    "sg:phone":"+44 20 8573 7624",
    "sg:postcode":"UB3 3HG",
    "sg:province":"Greater London",
    "wof:name":"Turlough P O'Brien",
    "wof:placetype":"venue"
},
  "geometry": {"coordinates":[-0.412342,51.511894],"type":"Point"}
}