{
  "type": "Feature",
  "properties": {
    "addr:full":"Dreason, Bodwin Road Bodmin Cornwall PL30 4AZ",
    "addr:postcode":"pl30 4az",
    "addr:street":"Bodwin Road",
    "iso:country":"GB",
    "sg:address":"Dreason, Bodwin Road",
    "sg:city":"Bodmin",
    "sg:classifiers":[
        {
            "category":"Wholesale",
            "subcategory":"Construction Materials",
            "type":"Manufacturing & Wholesale Goods"
        }
    ],
    "sg:phone":"+44 1208 72238",
    "sg:postcode":"PL30 4AZ",
    "sg:province":"Cornwall",
    "sg:tags":[
        "sawdust",
        "sawmills",
        "shaving"
    ],
    "wof:name":"J Toms & Sons",
    "wof:placetype":"venue"
},
  "geometry": {"coordinates":[-4.66737,50.449348],"type":"Point"}
}