{
  "type": "Feature",
  "properties": {
    "iso:country":"GB",
    "sg:address":"23 Clifton Street, Milnrow",
    "sg:city":"Rochdale",
    "sg:classifiers":[
        {
            "category":"Farming",
            "subcategory":"Nursery",
            "type":"Manufacturing & Wholesale Goods"
        },
        {
            "category":"Social Services",
            "subcategory":"Child Care",
            "type":"Services"
        }
    ],
    "sg:phone":"+44 1706 869243",
    "sg:postcode":"OL16 4HP",
    "sg:province":"Lancashire",
    "sg:tags":[
        "creche"
    ],
    "wof:name":"Genesis Day Nursery",
    "wof:placetype":"venue"
},
  "geometry": {"coordinates":[-2.111806,53.610153],"type":"Point"}
}