{
  "type": "Feature",
  "properties": {
    "iso:country":"GB",
    "sg:address":"Upper Hill Farm, Ulcombe",
    "sg:city":"Maidstone",
    "sg:classifiers":[
        {
            "category":"Home & Garden",
            "subcategory":"Garden Supply",
            "type":"Retail Goods"
        },
        {
            "category":"Farming",
            "subcategory":"Livestock Farm",
            "type":"Manufacturing & Wholesale Goods"
        }
    ],
    "sg:phone":"+44 1622 858962",
    "sg:postcode":"ME17 1ER",
    "sg:province":"Kent",
    "sg:tags":[
        "bulb",
        "grower",
        "others"
    ],
    "wof:name":"R A Maddocks",
    "wof:placetype":"venue"
},
  "geometry": {"coordinates":[0.642209,51.26701],"type":"Point"}
}