{
  "type": "Feature",
  "properties": {
    "addr:full":"The Hillocks Farm, Kingennie, Broughty Ferry Dundee Angus DD5 3NZ",
    "addr:postcode":"dd5 3nz",
    "addr:street":"Kingennie",
    "iso:country":"GB",
    "sg:address":"The Hillocks Farm, Kingennie, Broughty Ferry",
    "sg:city":"Dundee",
    "sg:classifiers":[
        {
            "category":"Farming",
            "subcategory":"Livestock Farm",
            "type":"Manufacturing & Wholesale Goods"
        }
    ],
    "sg:postcode":"DD5 3NZ",
    "sg:province":"Angus",
    "sg:tags":[
        "others"
    ],
    "wof:name":"Duncan Kerr",
    "wof:placetype":"venue"
},
  "geometry": {"coordinates":[-2.8550899029,56.5009498596],"type":"Point"}
}