{
  "type": "Feature",
  "properties": {
    "addr:full":"Cherry Trees, Wains Lane, Staxton Scarborough North Yorkshire YO12 4SF",
    "addr:postcode":"yo12 4sf",
    "addr:street":"Wains Lane",
    "iso:country":"GB",
    "sg:address":"Cherry Trees, Wains Lane, Staxton",
    "sg:city":"Scarborough",
    "sg:classifiers":[
        {
            "category":"Professional",
            "type":"Services"
        },
        {
            "category":"Banks & Credit Unions",
            "subcategory":"Investment Brokerage",
            "type":"Services"
        }
    ],
    "sg:phone":"+44 1944 710366",
    "sg:postcode":"YO12 4SF",
    "sg:province":"North Yorkshire",
    "sg:tags":[
        "farm",
        "agricultural",
        "contractor"
    ],
    "wof:name":"John N Napthine",
    "wof:placetype":"venue"
},
  "geometry": {"coordinates":[-0.443338,54.196819],"type":"Point"}
}