{
  "type": "Feature",
  "properties": {
    "iso:country":"GB",
    "sg:address":"20 The Glebe",
    "sg:city":"Stevenage",
    "sg:classifiers":[
        {
            "category":"Restaurant",
            "type":"Food & Drink"
        }
    ],
    "sg:phone":"+44 1438 360297",
    "sg:postcode":"SG2 0DJ",
    "sg:province":"Hertfordshire",
    "sg:tags":[
        "indian"
    ],
    "wof:name":"The Gate of India",
    "wof:placetype":"venue"
},
  "geometry": {"coordinates":[-0.171074,51.90955],"type":"Point"}
}