{
  "type": "Feature",
  "properties": {
    "addr:full":"Lakeland Lodge, Weston Road, Edith Weston Oakham Leicestershire LE15 8HQ",
    "addr:postcode":"le15 8hq",
    "addr:street":"Weston Road",
    "iso:country":"GB",
    "sg:address":"Lakeland Lodge, Weston Road, Edith Weston",
    "sg:city":"Oakham",
    "sg:classifiers":[
        {
            "category":"Real Estate",
            "subcategory":"Developer",
            "type":"Services"
        }
    ],
    "sg:postcode":"LE15 8HQ",
    "sg:province":"Leicestershire",
    "sg:tags":[
        "property"
    ],
    "wof:name":"Lakeland Estates",
    "wof:placetype":"venue"
},
  "geometry": {"coordinates":[-0.634399,52.635921],"type":"Point"}
}