{
  "type": "Feature",
  "properties": {
    "iso:country":"GB",
    "sg:address":"124-130 Seymour Place",
    "sg:city":"London",
    "sg:classifiers":[
        {
            "category":"Professional",
            "subcategory":"Accounting & Tax Preparation",
            "type":"Services"
        }
    ],
    "sg:postcode":"W1H 1BG",
    "sg:province":"Greater London",
    "sg:tags":[
        "accountant"
    ],
    "wof:name":"Bright Grahame Murray Service Co. Ltd.",
    "wof:placetype":"venue"
},
  "geometry": {"coordinates":[-0.163451,51.520321],"type":"Point"}
}