{
  "type": "Feature",
  "properties": {
    "addr:full":"5 Bull Bridge Mead, Halstock Yeovil Dorset BA22 9RL",
    "addr:housenumber":"5",
    "addr:postcode":"ba22 9rl",
    "addr:street":"Bull Bridge Mead",
    "iso:country":"GB",
    "sg:address":"5 Bull Bridge Mead, Halstock",
    "sg:city":"Yeovil",
    "sg:classifiers":[
        {
            "category":"Professional",
            "type":"Services"
        },
        {
            "category":"Banks & Credit Unions",
            "subcategory":"Investment Brokerage",
            "type":"Services"
        }
    ],
    "sg:phone":"+44 1935 891488",
    "sg:postcode":"BA22 9RL",
    "sg:province":"Dorset",
    "sg:tags":[
        "farm",
        "agricultural",
        "contractor"
    ],
    "wof:name":"P A  & L E Frampton",
    "wof:placetype":"venue"
},
  "geometry": {"coordinates":[-2.6562559605,50.8673934937],"type":"Point"}
}