{
  "type": "Feature",
  "properties": {
    "addr:full":"17 Spring Hill Ventnor Isle of Wight PO38 1PF",
    "addr:housenumber":"17",
    "addr:postcode":"po38 1pf",
    "addr:street":"Spring",
    "iso:country":"GB",
    "sg:address":"17 Spring Hill",
    "sg:city":"Ventnor",
    "sg:classifiers":[
        {
            "category":"Building & Trades",
            "subcategory":"Construction",
            "type":"Services"
        }
    ],
    "sg:phone":"+44 1983 853703",
    "sg:postcode":"PO38 1PF",
    "sg:province":"Isle of Wight",
    "sg:tags":[
        "builder"
    ],
    "wof:name":"M W Gee & Son",
    "wof:placetype":"venue"
},
  "geometry": {"coordinates":[-1.2036720514,50.596370697],"type":"Point"}
}