{
  "type": "Feature",
  "properties": {
    "iso:country":"GB",
    "sg:address":"7 Rectory Close, Dowlais",
    "sg:city":"Merthyr Tydfil",
    "sg:classifiers":[
        {
            "category":"Organizations",
            "subcategory":"Non-profit Organization",
            "type":"Services"
        }
    ],
    "sg:phone":"+44 1685 377166",
    "sg:postcode":"CF48 3RD",
    "sg:province":"Caerphilly",
    "sg:tags":[
        "charitable",
        "organisation",
        "voluntary",
        "charity"
    ],
    "wof:name":"WALES EPILEPSY ASSOCIATION CYF.",
    "wof:placetype":"venue"
},
  "geometry": {"coordinates":[-3.349749,51.763206],"type":"Point"}
}