{
  "type": "Feature",
  "properties": {
    "addr:full":"Parys Road Amlwch Isle of Anglesey LL68 9EA",
    "addr:postcode":"ll68 9ea",
    "addr:street":"Parys Road",
    "iso:country":"GB",
    "sg:address":"Parys Road",
    "sg:city":"Amlwch",
    "sg:classifiers":[
        {
            "category":"Education",
            "subcategory":"Library",
            "type":"Public Place"
        }
    ],
    "sg:phone":"+44 1407 830145",
    "sg:postcode":"LL68 9EA",
    "sg:province":"Isle of Anglesey",
    "sg:tags":[
        "book"
    ],
    "wof:name":"Amlwch Library",
    "wof:placetype":"venue"
},
  "geometry": {"coordinates":[-4.340744,53.411812],"type":"Point"}
}