{
  "type": "Feature",
  "properties": {
    "addr:full":"Sudbury Heights Avenue Greenford Greater London UB6 0LX",
    "addr:postcode":"ub6 0lx",
    "addr:street":"Sudbury Heights Avenue",
    "iso:country":"GB",
    "sg:address":"Sudbury Heights Avenue",
    "sg:city":"Greenford",
    "sg:classifiers":[
        {
            "category":"Bars & Pubs",
            "type":"Food & Drink"
        }
    ],
    "sg:phone":"+44 20 8902 5026",
    "sg:postcode":"UB6 0LX",
    "sg:province":"Greater London",
    "sg:tags":[
        "pubs",
        "inn"
    ],
    "wof:name":"The Sudbury Arms",
    "wof:placetype":"venue"
},
  "geometry": {"coordinates":[-0.330509007,51.5553245544],"type":"Point"}
}