{
  "type": "Feature",
  "properties": {
    "iso:country":"GB",
    "sg:address":"44 London Rd",
    "sg:city":"Northampton",
    "sg:classifiers":[
        {
            "category":"Building & Trades",
            "subcategory":"Construction",
            "type":"Services"
        }
    ],
    "sg:phone":"+44 1604 862144",
    "sg:postcode":"NN7 2PL",
    "sg:province":"Buckinghamshire",
    "sg:tags":[
        "dry",
        "plastering",
        "plasterers",
        "lining",
        "related",
        "screeders"
    ],
    "wof:name":"S M Summerling",
    "wof:placetype":"venue"
},
  "geometry": {"coordinates":[-0.8979420066,52.1612663269],"type":"Point"}
}