{
  "type": "Feature",
  "properties": {
    "addr:full":"25 Brinsworth Lane, Brinsworth Rotherham South Yorkshire S60 5BS",
    "addr:housenumber":"25",
    "addr:postcode":"s60 5bs",
    "addr:street":"Brinsworth Lane",
    "iso:country":"GB",
    "sg:address":"25 Brinsworth Lane, Brinsworth",
    "sg:city":"Rotherham",
    "sg:classifiers":[
        {
            "category":"Insurance",
            "subcategory":"Insurance Agent",
            "type":"Services"
        }
    ],
    "sg:phone":"+44 1709 363159",
    "sg:postcode":"S60 5BS",
    "sg:province":"South Yorkshire",
    "wof:name":"Trendlord Financial Ltd.",
    "wof:placetype":"venue"
},
  "geometry": {"coordinates":[-1.3752139807,53.4038772583],"type":"Point"}
}