{
  "type": "Feature",
  "properties": {
    "addr:full":"62 Bampfylde Road Torquay Devon TQ2 5AY",
    "addr:housenumber":"62",
    "addr:postcode":"tq2 5ay",
    "addr:street":"Bampfylde Road",
    "iso:country":"GB",
    "sg:address":"62 Bampfylde Road",
    "sg:city":"Torquay",
    "sg:classifiers":[
        {
            "category":"Travel",
            "subcategory":"Hotels & Motels",
            "type":"Entertainment"
        }
    ],
    "sg:phone":"+44 1803 213167",
    "sg:postcode":"TQ2 5AY",
    "sg:province":"Devon",
    "wof:name":"Melba House Hotel",
    "wof:placetype":"venue"
},
  "geometry": {"coordinates":[-3.542462,50.466141],"type":"Point"}
}