{
  "type": "Feature",
  "properties": {
    "iso:country":"GB",
    "sg:address":"Unit C Bridewell Indust Estate, Bridewel, Clare",
    "sg:city":"Sudbury",
    "sg:classifiers":[
        {
            "category":"Professional",
            "subcategory":"Engineering",
            "type":"Services"
        }
    ],
    "sg:postcode":"CO10 8QD",
    "sg:province":"Essex",
    "sg:tags":[
        "contractor",
        "electrical",
        "engineer"
    ],
    "wof:name":"Quinney,Dave,",
    "wof:placetype":"venue"
},
  "geometry": {"coordinates":[0.581251,52.080494],"type":"Point"}
}