{
  "type": "Feature",
  "properties": {
    "addr:full":"256 St Albans Rd Watford Hertfordshire WD2 4AX",
    "addr:housenumber":"256",
    "addr:postcode":"wd2 4ax",
    "addr:street":"St Albans Rd",
    "iso:country":"GB",
    "sg:address":"256 St Albans Rd",
    "sg:city":"Watford",
    "sg:classifiers":[
        {
            "category":"Home & Garden",
            "subcategory":"Household Appliances",
            "type":"Retail Goods"
        }
    ],
    "sg:phone":"+44 1923 241523",
    "sg:postcode":"WD2 4AX",
    "sg:province":"Hertfordshire",
    "sg:tags":[
        "electrical"
    ],
    "wof:name":"Home Services (Watford)",
    "wof:placetype":"venue"
},
  "geometry": {"coordinates":[-0.3960820138,51.6721572876],"type":"Point"}
}