{
  "type": "Feature",
  "properties": {
    "iso:country":"GB",
    "sg:address":"2 Highmoor Cres",
    "sg:city":"Brighouse",
    "sg:classifiers":[
        {
            "category":"Social Services",
            "subcategory":"Adult Care",
            "type":"Services"
        }
    ],
    "sg:phone":"+44 1484 714679",
    "sg:postcode":"HD6 4HZ",
    "sg:province":"West Yorkshire",
    "sg:tags":[
        "housing",
        "sheltered"
    ],
    "wof:name":"Highmoor Crescent",
    "wof:placetype":"venue"
},
  "geometry": {"coordinates":[-1.761369,53.70525],"type":"Point"}
}