{
  "type": "Feature",
  "properties": {
    "iso:country":"GB",
    "sg:address":"Adam Ho, Players Ct, Player St, Radford",
    "sg:city":"Nottingham",
    "sg:classifiers":[
        {
            "category":"Organizations",
            "subcategory":"Non-profit Organization",
            "type":"Services"
        }
    ],
    "sg:postcode":"NG7 5LZ",
    "sg:province":"Nottinghamshire",
    "sg:tags":[
        "organisation",
        "voluntary",
        "charity"
    ],
    "wof:name":"Mencap Ltd",
    "wof:placetype":"venue"
},
  "geometry": {"coordinates":[-1.176614,52.960789],"type":"Point"}
}