{
  "type": "Feature",
  "properties": {
    "iso:country":"GB",
    "sg:address":"1 The Avenue",
    "sg:city":"Newton Abbot",
    "sg:classifiers":[
        {
            "category":"Retail",
            "subcategory":"Auto Rental",
            "type":"Services"
        }
    ],
    "sg:phone":"+44 1626 330300",
    "sg:postcode":"TQ12 2BZ",
    "sg:province":"Devon",
    "sg:tags":[
        "car"
    ],
    "wof:name":"Enterprise Rent-A-Car",
    "wof:placetype":"venue"
},
  "geometry": {"coordinates":[-3.6031570435,50.5320587158],"type":"Point"}
}