{
  "type": "Feature",
  "properties": {
    "addr:full":"36 Smugglers Walk Worthing West Sussex BN12 4DP",
    "addr:housenumber":"36",
    "addr:postcode":"bn12 4dp",
    "addr:street":"Smugglers Walk",
    "iso:country":"GB",
    "sg:address":"36 Smugglers Walk",
    "sg:city":"Worthing",
    "sg:classifiers":[
        {
            "category":"Professional",
            "subcategory":"Business Services",
            "type":"Services"
        }
    ],
    "sg:postcode":"BN12 4DP",
    "sg:province":"West Sussex",
    "sg:tags":[
        "holding"
    ],
    "wof:name":"Silpro Ltd.",
    "wof:placetype":"venue"
},
  "geometry": {"coordinates":[-0.409367,50.807178],"type":"Point"}
}