{
  "type": "Feature",
  "properties": {
    "addr:full":"Station Rd, Stainforth Doncaster South Yorkshire DN7 5QB",
    "addr:postcode":"dn7 5qb",
    "addr:street":"Station Rd",
    "iso:country":"GB",
    "sg:address":"Station Rd, Stainforth",
    "sg:city":"Doncaster",
    "sg:classifiers":[
        {
            "category":"Bars & Pubs",
            "type":"Food & Drink"
        }
    ],
    "sg:postcode":"DN7 5QB",
    "sg:province":"South Yorkshire",
    "sg:tags":[
        "pubs",
        "inn"
    ],
    "wof:name":"Palmer,Bernie,",
    "wof:placetype":"venue"
},
  "geometry": {"coordinates":[-1.028071,53.590454],"type":"Point"}
}