{
  "type": "Feature",
  "properties": {
    "iso:country":"GB",
    "sg:address":"Unit 2",
    "sg:city":"Dundee",
    "sg:classifiers":[
        {
            "category":"Home & Garden",
            "subcategory":"Home Furnishings",
            "type":"Retail Goods"
        }
    ],
    "sg:phone":"+44 1382 504029",
    "sg:postcode":"DD4 8JT",
    "sg:province":"Dundee City",
    "sg:tags":[
        "beds",
        "bedding",
        "blanket"
    ],
    "wof:name":"Bensons Bed Centres (Northern)",
    "wof:placetype":"venue"
},
  "geometry": {"coordinates":[-2.889814,56.480228],"type":"Point"}
}