{
  "type": "Feature",
  "properties": {
    "addr:full":"Hi Point, Thomas Street Taunton Somerset TA2 6HB",
    "addr:postcode":"ta2 6hb",
    "addr:street":"Hi;Thomas Street",
    "iso:country":"GB",
    "sg:address":"Hi Point, Thomas Street",
    "sg:city":"Taunton",
    "sg:classifiers":[
        {
            "category":"Manufacturing",
            "subcategory":"Building Materials",
            "type":"Manufacturing & Wholesale Goods"
        }
    ],
    "sg:postcode":"TA2 6HB",
    "sg:province":"Somerset",
    "sg:tags":[
        "concrete",
        "product"
    ],
    "wof:name":"Fencast Ltd",
    "wof:placetype":"venue"
},
  "geometry": {"coordinates":[-3.10502,51.023849],"type":"Point"}
}