{
  "type": "Feature",
  "properties": {
    "addr:full":"18 High Street East Linton East Lothian EH40 3AB",
    "addr:housenumber":"18",
    "addr:postcode":"eh40 3ab",
    "addr:street":"High Street",
    "iso:country":"GB",
    "sg:address":"18 High Street",
    "sg:city":"East Linton",
    "sg:classifiers":[
        {
            "category":"Education",
            "subcategory":"Library",
            "type":"Public Place"
        },
        {
            "category":"Government",
            "subcategory":"Office",
            "type":"Public Place"
        }
    ],
    "sg:phone":"+44 1620 860015",
    "sg:postcode":"EH40 3AB",
    "sg:province":"East Lothian",
    "sg:tags":[
        "book",
        "local"
    ],
    "wof:name":"East Linton Library",
    "wof:placetype":"venue"
},
  "geometry": {"coordinates":[-2.6561369896,55.9874191284],"type":"Point"}
}