{
  "type": "Feature",
  "properties": {
    "iso:country":"GB",
    "sg:address":"2 Stonewell",
    "sg:city":"Lancaster",
    "sg:classifiers":[
        {
            "category":"Retail",
            "subcategory":"Laundry & Dry Cleaning",
            "type":"Services"
        }
    ],
    "sg:phone":"+44 1524 844210",
    "sg:postcode":"LA1 1NJ",
    "sg:province":"Lancashire",
    "sg:tags":[
        "launderette"
    ],
    "wof:name":"Stonewell Launderette",
    "wof:placetype":"venue"
},
  "geometry": {"coordinates":[-2.798169,54.049603],"type":"Point"}
}