{
  "type": "Feature",
  "properties": {
    "addr:full":"Unit 24, Ogmore Crescent, Bridgend Industrial Estate Bridgend Bridgend CF31 3TE",
    "addr:housenumber":"unit 24",
    "addr:postcode":"cf31 3te",
    "addr:street":"Ogmore Crescent;Industrial Estate",
    "iso:country":"GB",
    "sg:address":"Unit 24, Ogmore Crescent, Bridgend Industrial Estate",
    "sg:city":"Bridgend",
    "sg:classifiers":[
        {
            "category":"Professional",
            "subcategory":"Engineering",
            "type":"Services"
        }
    ],
    "sg:phone":"+44 1656 657067",
    "sg:postcode":"CF31 3TE",
    "sg:province":"Bridgend",
    "sg:tags":[
        "precision",
        "engineer"
    ],
    "wof:name":"Pressrite Engineering Ltd.",
    "wof:placetype":"venue"
},
  "geometry": {"coordinates":[-3.5648341179,51.501121521],"type":"Point"}
}