{
  "type": "Feature",
  "properties": {
    "iso:country":"GB",
    "sg:address":"Beech House, Winskill",
    "sg:city":"Penrith",
    "sg:classifiers":[
        {
            "category":"Professional",
            "subcategory":"Business Services",
            "type":"Services"
        },
        {
            "category":"Farming",
            "subcategory":"Farm",
            "type":"Manufacturing & Wholesale Goods"
        }
    ],
    "sg:phone":"+44 1768 881881",
    "sg:postcode":"CA10 1PD",
    "sg:province":"Cumbria",
    "sg:tags":[
        "merchant",
        "agricultural",
        "mixed",
        "crop"
    ],
    "wof:name":"Jim Peet (Agriculture)",
    "wof:placetype":"venue"
},
  "geometry": {"coordinates":[-2.652144,54.707867],"type":"Point"}
}