{
  "type": "Feature",
  "properties": {
    "iso:country":"GB",
    "sg:address":"Waterville Rd",
    "sg:city":"North Shields",
    "sg:classifiers":[
        {
            "category":"Professional",
            "subcategory":"Engineering",
            "type":"Services"
        }
    ],
    "sg:phone":"+44 191 257 9837",
    "sg:postcode":"NE29 6UA",
    "sg:province":"Tyne and Wear",
    "sg:tags":[
        "consulting",
        "engineer"
    ],
    "wof:name":"Douglas Horn Ltd",
    "wof:placetype":"venue"
},
  "geometry": {"coordinates":[-1.4586399794,55.0035400391],"type":"Point"}
}