{
  "type": "Feature",
  "properties": {
    "addr:full":"176 Towngate Leyland Lancashire PR25 2TE",
    "addr:housenumber":"176",
    "addr:postcode":"pr25 2te",
    "addr:street":"Towngate Leyland",
    "iso:country":"GB",
    "sg:address":"176 Towngate",
    "sg:city":"Leyland",
    "sg:classifiers":[
        {
            "category":"Shopping",
            "subcategory":"Mobile Phones",
            "type":"Retail Goods"
        }
    ],
    "sg:postcode":"PR25 2TE",
    "sg:province":"Lancashire",
    "wof:name":"Ashurst,George,",
    "wof:placetype":"venue"
},
  "geometry": {"coordinates":[-2.696099,53.693722],"type":"Point"}
}