{
  "type": "Feature",
  "properties": {
    "iso:country":"GB",
    "sg:address":"Foxham Road",
    "sg:city":"London",
    "sg:classifiers":[
        {
            "category":"Education",
            "subcategory":"School",
            "type":"Public Place"
        }
    ],
    "sg:phone":"+44 20 7272 6580",
    "sg:postcode":"N19 4RR",
    "sg:province":"Greater London",
    "sg:tags":[
        "local",
        "authority"
    ],
    "wof:name":"Yerbury Primary School",
    "wof:placetype":"venue"
},
  "geometry": {"coordinates":[-0.1317439973,51.5598526001],"type":"Point"}
}