{
  "type": "Feature",
  "properties": {
    "addr:full":"New Sweden, Randolphs Lane, Iden Rye East Sussex TN31 7PR",
    "addr:postcode":"tn31 7pr",
    "addr:street":"Randolphs Lane",
    "iso:country":"GB",
    "sg:address":"New Sweden, Randolphs Lane, Iden",
    "sg:city":"Rye",
    "sg:classifiers":[
        {
            "category":"Building & Trades",
            "subcategory":"Construction",
            "type":"Services"
        }
    ],
    "sg:phone":"+44 1797 280308",
    "sg:postcode":"TN31 7PR",
    "sg:province":"East Sussex",
    "sg:tags":[
        "decorator",
        "painter"
    ],
    "wof:name":"Custom Paint Co",
    "wof:placetype":"venue"
},
  "geometry": {"coordinates":[0.730905,50.982143],"type":"Point"}
}