{
  "type": "Feature",
  "properties": {
    "iso:country":"GB",
    "sg:address":"21 Market Place",
    "sg:city":"Inverurie",
    "sg:classifiers":[
        {
            "category":"Banks & Credit Unions",
            "subcategory":"Bank",
            "type":"Services"
        }
    ],
    "sg:phone":"+44 1467 620425",
    "sg:postcode":"AB51 9PU",
    "sg:province":"Aberdeenshire",
    "wof:name":"The Royal Bank of Scotland Plc",
    "wof:placetype":"venue"
},
  "geometry": {"coordinates":[-2.374546051,57.283782959],"type":"Point"}
}