{
  "type": "Feature",
  "properties": {
    "addr:full":"Alma Court, Hornbuckle Close Harrow Greater London HA2 0YE",
    "addr:postcode":"ha2 0ye",
    "addr:street":"Alma Court Hornbuckle Close",
    "iso:country":"GB",
    "sg:address":"Alma Court, Hornbuckle Close",
    "sg:city":"Harrow",
    "sg:classifiers":[
        {
            "category":"Social Services",
            "subcategory":"Adult Care",
            "type":"Services"
        },
        {
            "category":"Social Services",
            "subcategory":"Retirement Home",
            "type":"Services"
        }
    ],
    "sg:phone":"+44 20 8864 4001",
    "sg:postcode":"HA2 0YE",
    "sg:province":"Greater London",
    "sg:tags":[
        "housing",
        "sheltered",
        "accommodation"
    ],
    "wof:name":"Alma Court",
    "wof:placetype":"venue"
},
  "geometry": {"coordinates":[-0.347419,51.56736],"type":"Point"}
}