{
  "type": "Feature",
  "properties": {
    "addr:full":"Long Acre, Bingham Nottingham Leicestershire NG13 8BG",
    "addr:postcode":"ng13 8bg",
    "addr:street":"Long Acre",
    "iso:country":"GB",
    "sg:address":"Long Acre, Bingham",
    "sg:city":"Nottingham",
    "sg:classifiers":[
        {
            "category":"Shopping",
            "subcategory":"Antiques",
            "type":"Retail Goods"
        }
    ],
    "sg:postcode":"NG13 8BG",
    "sg:province":"Leicestershire",
    "wof:name":"Long Acre Studios",
    "wof:placetype":"venue"
},
  "geometry": {"coordinates":[-0.956487,52.9503173828],"type":"Point"}
}