{
  "type": "Feature",
  "properties": {
    "addr:full":"Edmunds Road Banbury Oxfordshire OX16 0PP",
    "addr:postcode":"ox16 0pp",
    "addr:street":"Edmunds Road",
    "iso:country":"GB",
    "sg:address":"Edmunds Road",
    "sg:city":"Banbury",
    "sg:classifiers":[
        {
            "category":"Place Of Worship",
            "type":"Public Place"
        }
    ],
    "sg:phone":"+44 1295 264661",
    "sg:postcode":"OX16 0PP",
    "sg:province":"Oxfordshire",
    "wof:name":"St.Joseph's R C Church",
    "wof:placetype":"venue"
},
  "geometry": {"coordinates":[-1.3635590076,52.0614051819],"type":"Point"}
}