{
  "type": "Feature",
  "properties": {
    "iso:country":"GB",
    "sg:address":"P O Box 4",
    "sg:city":"Louth",
    "sg:classifiers":[
        {
            "category":"Home & Garden",
            "subcategory":"Garden Supply",
            "type":"Retail Goods"
        }
    ],
    "sg:phone":"+44 1507 600444",
    "sg:postcode":"LN11 0NW",
    "sg:province":"Lincolnshire",
    "sg:tags":[
        "sand",
        "gravel"
    ],
    "wof:name":"Enterprise Europa",
    "wof:placetype":"venue"
},
  "geometry": {"coordinates":[-0.018189,53.388081],"type":"Point"}
}