{
  "type": "Feature",
  "properties": {
    "addr:full":"New Street, Fressingfield Diss Norfolk IP21 5PJ",
    "addr:postcode":"ip21 5pj",
    "addr:street":"New Street",
    "iso:country":"GB",
    "sg:address":"New Street, Fressingfield",
    "sg:city":"Diss",
    "sg:classifiers":[
        {
            "category":"Health Services",
            "subcategory":"Doctor",
            "type":"Services"
        },
        {
            "category":"Health Services",
            "subcategory":"Clinic",
            "type":"Services"
        }
    ],
    "sg:postcode":"IP21 5PJ",
    "sg:province":"Norfolk",
    "sg:tags":[
        "nh",
        "practitioners"
    ],
    "wof:name":"Fressingfield Medical Centre",
    "wof:placetype":"venue"
},
  "geometry": {"coordinates":[1.318783,52.347141],"type":"Point"}
}