{
  "type": "Feature",
  "properties": {
    "addr:full":"Unit 1, Island Square, Island Street Salcombe Devon TQ8 8DP",
    "addr:housenumber":"unit 1",
    "addr:postcode":"tq8 8dp",
    "addr:street":"Island Square Island Street",
    "iso:country":"GB",
    "sg:address":"Unit 1, Island Square, Island Street",
    "sg:city":"Salcombe",
    "sg:classifiers":[
        {
            "category":"Food & Beverages",
            "subcategory":"Candy",
            "type":"Retail Goods"
        }
    ],
    "sg:postcode":"TQ8 8DP",
    "sg:province":"Devon",
    "sg:tags":[
        "confectionery"
    ],
    "wof:name":"Coton's Continental Chocolate",
    "wof:placetype":"venue"
},
  "geometry": {"coordinates":[-3.7686181068,50.2398834229],"type":"Point"}
}