{
  "type": "Feature",
  "properties": {
    "addr:full":"7 Redwood Avenue, Woodley Reading Berkshire RG5 4DS",
    "addr:housenumber":"7",
    "addr:postcode":"rg5 4ds",
    "addr:street":"Redwood Avenue",
    "iso:country":"GB",
    "sg:address":"7 Redwood Avenue, Woodley",
    "sg:city":"Reading",
    "sg:classifiers":[
        {
            "category":"Bus Charters",
            "type":"Transportation"
        }
    ],
    "sg:phone":"+44 118 969 1062",
    "sg:postcode":"RG5 4DS",
    "sg:province":"Berkshire",
    "sg:tags":[
        "hire",
        "coach"
    ],
    "wof:name":"Rightway Mini Coaches",
    "wof:placetype":"venue"
},
  "geometry": {"coordinates":[-0.8881239891,51.4459991455],"type":"Point"}
}