{
  "type": "Feature",
  "properties": {
    "addr:full":"Woodland View House, 675 Leeds Road Huddersfield West Yorkshire HD2 1YY",
    "addr:housenumber":"675",
    "addr:postcode":"hd2 1yy",
    "addr:street":"Leeds Road",
    "iso:country":"GB",
    "sg:address":"Woodland View House, 675 Leeds Road",
    "sg:city":"Huddersfield",
    "sg:classifiers":[
        {
            "category":"Professional",
            "subcategory":"Engineering",
            "type":"Services"
        }
    ],
    "sg:postcode":"HD2 1YY",
    "sg:province":"West Yorkshire",
    "sg:tags":[
        "contractor",
        "electrical",
        "engineer"
    ],
    "wof:name":"N.S.E. Electrical Services Ltd",
    "wof:placetype":"venue"
},
  "geometry": {"coordinates":[-1.7552410364,53.6633415222],"type":"Point"}
}