{
  "type": "Feature",
  "properties": {
    "iso:country":"GB",
    "sg:address":"24 Greenbrow Road",
    "sg:city":"Manchester",
    "sg:classifiers":[
        {
            "category":"Personal",
            "subcategory":"Beauty Salon",
            "type":"Services"
        },
        {
            "category":"Personal",
            "subcategory":"Barber",
            "type":"Services"
        }
    ],
    "sg:href":"http://api.simplegeo.com/1.0/features/SG_4SMku3xYjII1LpOnzTMepo_53.394291_-2.280119@1300740015.json",
    "sg:phone":"+44 161 946 0036",
    "sg:postcode":"M23 1EX",
    "sg:province":"Cheshire",
    "sg:tags":[
        "unisex",
        "hairdresser"
    ],
    "wof:name":"Dave's Crop Shop",
    "wof:placetype":"venue"
},
  "geometry": {"coordinates":[-2.280119,53.394291],"type":"Point"}
}