{
  "type": "Feature",
  "properties": {
    "iso:country":"GB",
    "sg:address":"14 Upper Brook Street",
    "sg:city":"Ipswich",
    "sg:classifiers":[
        {
            "category":"Fast Food",
            "type":"Food & Drink"
        }
    ],
    "sg:phone":"+44 1473 253562",
    "sg:postcode":"IP4 1EE",
    "sg:province":"Suffolk",
    "sg:tags":[
        "away",
        "take"
    ],
    "wof:name":"Bunters Sandwich Shop",
    "wof:placetype":"venue"
},
  "geometry": {"coordinates":[1.1560339928,52.0567626953],"type":"Point"}
}