{
  "type": "Feature",
  "properties": {
    "iso:country":"GB",
    "sg:address":"10 Bridge Street",
    "sg:city":"Congleton",
    "sg:classifiers":[
        {
            "category":"Communications",
            "subcategory":"Film & Video Production",
            "type":"Services"
        }
    ],
    "sg:phone":"+44 1260 273268",
    "sg:postcode":"CW12 1AY",
    "sg:province":"Cheshire",
    "sg:tags":[
        "tv"
    ],
    "wof:name":"Radio Rentals",
    "wof:placetype":"venue"
},
  "geometry": {"coordinates":[-2.213257,53.163059],"type":"Point"}
}