{
  "type": "Feature",
  "properties": {
    "addr:full":"56 Ashley Drive, Tylers Grn High Wycombe Buckinghamshire HP10 8AZ",
    "addr:housenumber":"56",
    "addr:postcode":"hp10 8az",
    "addr:street":"Ashley Drive Tylers Grn",
    "iso:country":"GB",
    "sg:address":"56 Ashley Drive, Tylers Grn",
    "sg:city":"High Wycombe",
    "sg:classifiers":[
        {
            "category":"Building & Trades",
            "subcategory":"Construction",
            "type":"Services"
        }
    ],
    "sg:phone":"+44 1494 813040",
    "sg:postcode":"HP10 8AZ",
    "sg:province":"Buckinghamshire",
    "sg:tags":[
        "roofing"
    ],
    "wof:name":"Penn Roofing",
    "wof:placetype":"venue"
},
  "geometry": {"coordinates":[-0.698184,51.640663],"type":"Point"}
}