{
  "type": "Feature",
  "properties": {
    "iso:country":"GB",
    "sg:address":"Rowley Hall Hospital, Rowley Park",
    "sg:city":"Stafford",
    "sg:classifiers":[
        {
            "category":"Health Services",
            "subcategory":"Hospital",
            "type":"Services"
        }
    ],
    "sg:phone":"+44 1785 223203",
    "sg:postcode":"ST17 9AQ",
    "sg:province":"Staffordshire",
    "wof:name":"Rowley Hall Hospital Ltd.",
    "wof:placetype":"venue"
},
  "geometry": {"coordinates":[-2.1265900135,52.794921875],"type":"Point"}
}