{
  "type": "Feature",
  "properties": {
    "iso:country":"GB",
    "sg:address":"176 Werrington Rd, Bucknall",
    "sg:city":"Stoke On Trent",
    "sg:classifiers":[
        {
            "category":"Professional",
            "subcategory":"Art Services",
            "type":"Services"
        }
    ],
    "sg:phone":"+44 1782 285984",
    "sg:postcode":"ST2 9AW",
    "sg:province":"Staffordshire",
    "sg:tags":[
        "picture",
        "restoration"
    ],
    "wof:name":"Castle Crafts",
    "wof:placetype":"venue"
},
  "geometry": {"coordinates":[-2.142056942,53.0252151489],"type":"Point"}
}