{
  "type": "Feature",
  "properties": {
    "iso:country":"GB",
    "sg:address":"262 High Street",
    "sg:city":"Perth",
    "sg:classifiers":[
        {
            "category":"Manufacturing",
            "subcategory":"Jewelry",
            "type":"Manufacturing & Wholesale Goods"
        }
    ],
    "sg:phone":"+44 1738 638232",
    "sg:postcode":"PH1 5QJ",
    "sg:province":"Perth and Kinross",
    "sg:tags":[
        "manufacture",
        "repair",
        "jewellery"
    ],
    "wof:name":"Jewellery Workshop",
    "wof:placetype":"venue"
},
  "geometry": {"coordinates":[-3.436183,56.396881],"type":"Point"}
}