{
  "type": "Feature",
  "properties": {
    "iso:country":"GB",
    "sg:address":"Bramley Hedge Farm, Red Hill Rd",
    "sg:city":"Cobham",
    "sg:classifiers":[
        {
            "category":"Personal",
            "subcategory":"Adult",
            "type":"Services"
        }
    ],
    "sg:phone":"+44 1932 865858",
    "sg:postcode":"KT11 1EQ",
    "sg:province":"Surrey",
    "sg:tags":[
        "equestrian"
    ],
    "wof:name":"Silvermere Equestrian Centre",
    "wof:placetype":"venue"
},
  "geometry": {"coordinates":[-0.410454,51.328117],"type":"Point"}
}