{
  "type": "Feature",
  "properties": {
    "iso:country":"GB",
    "sg:address":"60 Princes Street",
    "sg:city":"Yeovil",
    "sg:classifiers":[
        {
            "category":"Building & Trades",
            "subcategory":"Cleaning & Sanitation",
            "type":"Services"
        }
    ],
    "sg:postcode":"BA20 1HL",
    "sg:province":"Somerset",
    "sg:tags":[
        "blast"
    ],
    "wof:name":"Blast Cleaning Services Ltd",
    "wof:placetype":"venue"
},
  "geometry": {"coordinates":[-2.633544,50.942627],"type":"Point"}
}