{
  "type": "Feature",
  "properties": {
    "addr:full":"35 Lynn Road, Snettisham King's Lynn Norfolk PE31 7LR",
    "addr:housenumber":"35",
    "addr:postcode":"pe31 7lr",
    "addr:street":"Lynn Road;Lynn",
    "iso:country":"GB",
    "sg:address":"35 Lynn Road, Snettisham",
    "sg:city":"King's Lynn",
    "sg:classifiers":[
        {
            "category":"Organizations",
            "subcategory":"Professional Association",
            "type":"Services"
        }
    ],
    "sg:phone":"+44 1485 544500",
    "sg:postcode":"PE31 7LR",
    "sg:province":"Norfolk",
    "sg:tags":[
        "organisation",
        "motoring"
    ],
    "wof:name":"Ferrari Owners' Club Ltd.",
    "wof:placetype":"venue"
},
  "geometry": {"coordinates":[0.50257,52.879181],"type":"Point"}
}