{
  "type": "Feature",
  "properties": {
    "iso:country":"GB",
    "sg:address":"406 Richmond Rd, Ham",
    "sg:city":"Kingston Upon Thames",
    "sg:classifiers":[
        {
            "category":"Real Estate",
            "subcategory":"Real Estate Agent",
            "type":"Services"
        }
    ],
    "sg:phone":"+44 20 8546 6688",
    "sg:postcode":"KT2 5PU",
    "sg:province":"Greater London",
    "wof:name":"Lords Estate Agents",
    "wof:placetype":"venue"
},
  "geometry": {"coordinates":[-0.3068270087,51.4294624329],"type":"Point"}
}