{
  "type": "Feature",
  "properties": {
    "iso:country":"GB",
    "sg:address":"Climate House, Somers Rd",
    "sg:city":"Rugby",
    "sg:classifiers":[
        {
            "category":"Home & Garden",
            "subcategory":"Household Appliances",
            "type":"Retail Goods"
        }
    ],
    "sg:phone":"+44 1788 544197",
    "sg:postcode":"CV22 7DG",
    "sg:province":"Warwickshire",
    "sg:tags":[
        "equipment",
        "air conditioning"
    ],
    "wof:name":"Auriga",
    "wof:placetype":"venue"
},
  "geometry": {"coordinates":[-1.281863,52.373371],"type":"Point"}
}