{
  "type": "Feature",
  "properties": {
    "addr:full":"Seafire Clo York East Riding of Yorkshire YO3 4UU",
    "addr:postcode":"yo3 4uu",
    "iso:country":"GB",
    "sg:address":"Seafire Clo",
    "sg:city":"York",
    "sg:classifiers":[
        {
            "category":"Wholesale",
            "subcategory":"Construction Materials",
            "type":"Manufacturing & Wholesale Goods"
        }
    ],
    "sg:phone":"+44 1904 690830",
    "sg:postcode":"YO3 4UU",
    "sg:province":"East Riding of Yorkshire",
    "sg:tags":[
        "merchant",
        "glass"
    ],
    "wof:name":"Solaglas",
    "wof:placetype":"venue"
},
  "geometry": {"coordinates":[-1.093944,53.991619],"type":"Point"}
}