{
  "type": "Feature",
  "properties": {
    "addr:full":"Katherine Low Settlement, 108 Battersea High St Battersea Greater London SW11 3HP",
    "addr:housenumber":"108",
    "addr:postcode":"greater;sw11 3hp",
    "addr:street":"Settlement;Battersea High St",
    "iso:country":"GB",
    "sg:address":"Katherine Low Settlement, 108 Battersea High St",
    "sg:city":"Battersea",
    "sg:classifiers":[
        {
            "category":"Organizations",
            "subcategory":"Non-profit Organization",
            "type":"Services"
        }
    ],
    "sg:phone":"+44 20 7228 2566",
    "sg:postcode":"SW11 3HP",
    "sg:province":"Greater London",
    "sg:tags":[
        "organisation",
        "voluntary",
        "charity"
    ],
    "wof:name":"Wandsworth Young Carers Project",
    "wof:placetype":"venue"
},
  "geometry": {"coordinates":[-0.162839,51.467464],"type":"Point"}
}