{
  "type": "Feature",
  "properties": {
    "addr:full":"Penmore House, Hasland Road Chesterfield Derbyshire S41 0SJ",
    "addr:postcode":"s41 0sj",
    "addr:street":"Hasland Road",
    "iso:country":"GB",
    "sg:address":"Penmore House, Hasland Road",
    "sg:city":"Chesterfield",
    "sg:classifiers":[
        {
            "category":"Real Estate",
            "subcategory":"Architect",
            "type":"Services"
        }
    ],
    "sg:phone":"+44 1246 233255",
    "sg:postcode":"S41 0SJ",
    "sg:province":"Derbyshire",
    "wof:name":"Frank Shaw Associates Ltd.",
    "wof:placetype":"venue"
},
  "geometry": {"coordinates":[-1.418976,53.228607],"type":"Point"}
}