{
  "type": "Feature",
  "properties": {
    "addr:full":"2 Dunsham Court, Havelock St Aylesbury Buckinghamshire HP20 2NX",
    "addr:housenumber":"2",
    "addr:postcode":"hp20 2nx",
    "addr:street":"Dunsham Court Havelock St",
    "iso:country":"GB",
    "sg:address":"2 Dunsham Court, Havelock St",
    "sg:city":"Aylesbury",
    "sg:classifiers":[
        {
            "category":"Professional",
            "subcategory":"Computer Services",
            "type":"Services"
        }
    ],
    "sg:phone":"+44 1296 435648",
    "sg:postcode":"HP20 2NX",
    "sg:province":"Buckinghamshire",
    "sg:tags":[
        "consultant"
    ],
    "wof:name":"Bug Busters",
    "wof:placetype":"venue"
},
  "geometry": {"coordinates":[-0.807454,51.826702],"type":"Point"}
}