{
  "type": "Feature",
  "properties": {
    "addr:full":"415 Durham Rd Gateshead Tyne and Wear NE9 5AN",
    "addr:housenumber":"415",
    "addr:postcode":"ne9 5an",
    "addr:street":"Durham Rd",
    "iso:country":"GB",
    "sg:address":"415 Durham Rd",
    "sg:city":"Gateshead",
    "sg:classifiers":[
        {
            "category":"Bus Charters",
            "type":"Transportation"
        }
    ],
    "sg:phone":"+44 191 491 1111",
    "sg:postcode":"NE9 5AN",
    "sg:province":"Tyne and Wear",
    "sg:tags":[
        "hire",
        "coach"
    ],
    "wof:name":"Deans Mini Bus",
    "wof:placetype":"venue"
},
  "geometry": {"coordinates":[-1.5995329618,54.9378013611],"type":"Point"}
}