{
  "type": "Feature",
  "properties": {
    "addr:full":"Ladywood Road Birmingham West Midlands B16 8SZ",
    "addr:postcode":"b16 8sz",
    "addr:street":"Ladywood Road",
    "iso:country":"GB",
    "sg:address":"Ladywood Road",
    "sg:city":"Birmingham",
    "sg:classifiers":[
        {
            "category":"Organizations",
            "subcategory":"Non-profit Organization",
            "type":"Services"
        }
    ],
    "sg:phone":"+44 121 246 6100",
    "sg:postcode":"B16 8SZ",
    "sg:province":"West Midlands",
    "sg:tags":[
        "charitable",
        "organisation",
        "voluntary",
        "charity"
    ],
    "wof:name":"Birmingham Institute for the Deaf",
    "wof:placetype":"venue"
},
  "geometry": {"coordinates":[-1.926928997,52.4760742188],"type":"Point"}
}