{
  "type": "Feature",
  "properties": {
    "addr:full":"The Clifton Practice, 8/10 Whiteladies Road Bristol City of Bristol BS8 1PD",
    "addr:housenumber":"8 / 10",
    "addr:postcode":"bs8 1pd",
    "addr:street":"Whiteladies Road",
    "iso:country":"GB",
    "sg:address":"The Clifton Practice, 8/10 Whiteladies Road",
    "sg:city":"Bristol",
    "sg:classifiers":[
        {
            "category":"Health Services",
            "subcategory":"Health Practitioner",
            "type":"Services"
        }
    ],
    "sg:postcode":"BS8 1PD",
    "sg:province":"City of Bristol",
    "sg:tags":[
        "hypnotherapists"
    ],
    "wof:name":"David Newton",
    "wof:placetype":"venue"
},
  "geometry": {"coordinates":[-2.60892,51.45929],"type":"Point"}
}