{
  "type": "Feature",
  "properties": {
    "addr:full":"36 Bent Street Brierley Hill West Midlands DY5 1RB",
    "addr:housenumber":"36",
    "addr:postcode":"dy5 1rb",
    "addr:street":"Bent Street",
    "iso:country":"GB",
    "sg:address":"36 Bent Street",
    "sg:city":"Brierley Hill",
    "sg:classifiers":[
        {
            "category":"Utilities",
            "subcategory":"Fuel Oil & Lpg",
            "type":"Services"
        }
    ],
    "sg:phone":"+44 1384 78405",
    "sg:postcode":"DY5 1RB",
    "sg:province":"West Midlands",
    "sg:tags":[
        "merchant",
        "coal",
        "smokeless"
    ],
    "wof:name":"Joseph Warr",
    "wof:placetype":"venue"
},
  "geometry": {"coordinates":[-2.1230831146,52.4861335754],"type":"Point"}
}