{
  "type": "Feature",
  "properties": {
    "addr:full":"Urban Road, Kirkby-in-ashfield Nottingham Nottinghamshire NG17 8DA",
    "addr:postcode":"ng17 8da",
    "addr:street":"Urban Road",
    "iso:country":"GB",
    "sg:address":"Urban Road, Kirkby-in-ashfield",
    "sg:city":"Nottingham",
    "sg:classifiers":[
        {
            "category":"Retail",
            "subcategory":"Event Space",
            "type":"Services"
        },
        {
            "category":"Government",
            "subcategory":"Office",
            "type":"Public Place"
        }
    ],
    "sg:phone":"+44 1623 756884",
    "sg:postcode":"NG17 8DA",
    "sg:province":"Nottinghamshire",
    "sg:tags":[
        "function",
        "local",
        "room"
    ],
    "wof:name":"Ashfield District Council",
    "wof:placetype":"venue"
},
  "geometry": {"coordinates":[-1.2508640289,53.0998191833],"type":"Point"}
}