{
  "type": "Feature",
  "properties": {
    "iso:country":"GB",
    "sg:address":"203 Seven Sisters Road",
    "sg:city":"London",
    "sg:classifiers":[
        {
            "category":"Shopping",
            "subcategory":"Clothing, Apparel, & Fashions",
            "type":"Retail Goods"
        }
    ],
    "sg:postcode":"N4 3NG",
    "sg:province":"Greater London",
    "sg:tags":[
        "shop"
    ],
    "wof:name":"Le Mistral",
    "wof:placetype":"venue"
},
  "geometry": {"coordinates":[-0.1088289991,51.5628890991],"type":"Point"}
}