{
  "type": "Feature",
  "properties": {
    "iso:country":"GB",
    "sg:address":"10 Rawcliffe St",
    "sg:city":"Blackpool",
    "sg:classifiers":[
        {
            "category":"Retail",
            "subcategory":"Auto Repair",
            "type":"Services"
        }
    ],
    "sg:phone":"+44 1253 342182",
    "sg:postcode":"FY4 1BX",
    "sg:province":"Lancashire",
    "sg:tags":[
        "modification",
        "garage"
    ],
    "wof:name":"Pyper,T J,& Co Ltd",
    "wof:placetype":"venue"
},
  "geometry": {"coordinates":[-3.054328,53.797737],"type":"Point"}
}