{
  "type": "Feature",
  "properties": {
    "iso:country":"GB",
    "sg:address":"West Woodfoot Farm, Slaley",
    "sg:city":"Hexham",
    "sg:classifiers":[
        {
            "category":"Professional",
            "subcategory":"Management & Consulting",
            "type":"Services"
        }
    ],
    "sg:phone":"+44 1434 673385",
    "sg:postcode":"NE47 0DF",
    "sg:province":"Northumberland",
    "sg:tags":[
        "consultant",
        "business"
    ],
    "wof:name":"R E P I M",
    "wof:placetype":"venue"
},
  "geometry": {"coordinates":[-2.0399401188,54.9144248962],"type":"Point"}
}