{
  "type": "Feature",
  "properties": {
    "addr:full":"Unit 9 Denmark Street Newcastle-upon-tyne Tyne and Wear NE6 2XF",
    "addr:housenumber":"unit 9",
    "addr:postcode":"ne6 2xf",
    "addr:street":"Denmark Street",
    "iso:country":"GB",
    "sg:address":"Unit 9 Denmark Street",
    "sg:city":"Newcastle-upon-tyne",
    "sg:classifiers":[
        {
            "category":"Food & Beverages",
            "subcategory":"Meat & Fish",
            "type":"Retail Goods"
        }
    ],
    "sg:phone":"+44 191 276 4428",
    "sg:postcode":"NE6 2XF",
    "sg:province":"Tyne and Wear",
    "sg:tags":[
        "merchant"
    ],
    "wof:name":"Joe's Fish Net",
    "wof:placetype":"venue"
},
  "geometry": {"coordinates":[-1.5786240101,54.9790496826],"type":"Point"}
}