{
  "type": "Feature",
  "properties": {
    "addr:full":"1 Rugby Road Dagenham Essex RM9 4AL",
    "addr:housenumber":"1",
    "addr:postcode":"rm9 4al",
    "addr:street":"Rugby Road",
    "iso:country":"GB",
    "sg:address":"1 Rugby Road",
    "sg:city":"Dagenham",
    "sg:classifiers":[
        {
            "category":"Food & Beverages",
            "subcategory":"Liquor & Beverages",
            "type":"Retail Goods"
        }
    ],
    "sg:phone":"+44 20 8592 1818",
    "sg:postcode":"RM9 4AL",
    "sg:province":"Essex",
    "sg:tags":[
        "beer",
        "spirit",
        "wines"
    ],
    "wof:name":"Sooa Wines",
    "wof:placetype":"venue"
},
  "geometry": {"coordinates":[0.127157,51.541355],"type":"Point"}
}