{
  "type": "Feature",
  "properties": {
    "addr:full":"67 Charminster Rd, Charminster Bournemouth Dorset BH8 8UE",
    "addr:housenumber":"67",
    "addr:postcode":"bh8 8ue",
    "addr:street":"Charminster Rd",
    "iso:country":"GB",
    "sg:address":"67 Charminster Rd, Charminster",
    "sg:city":"Bournemouth",
    "sg:classifiers":[
        {
            "category":"Building & Trades",
            "subcategory":"Construction",
            "type":"Services"
        }
    ],
    "sg:phone":"+44 1202 241332",
    "sg:postcode":"BH8 8UE",
    "sg:province":"Dorset",
    "sg:tags":[
        "decorator",
        "painter"
    ],
    "wof:name":"Evertex",
    "wof:placetype":"venue"
},
  "geometry": {"coordinates":[-1.867886,50.735313],"type":"Point"}
}