{
  "type": "Feature",
  "properties": {
    "iso:country":"GB",
    "sg:address":"29 Cameron Toll Shopping Ctr, Lady Road",
    "sg:city":"Edinburgh",
    "sg:classifiers":[
        {
            "category":"Shopping",
            "subcategory":"Clothing, Apparel, & Fashions",
            "type":"Retail Goods"
        }
    ],
    "sg:phone":"+44 131 664 8921",
    "sg:postcode":"EH16 5PB",
    "sg:province":"City of Edinburgh",
    "sg:tags":[
        "shop"
    ],
    "wof:name":"Mackays Stores Ltd.",
    "wof:placetype":"venue"
},
  "geometry": {"coordinates":[-3.1643500328,55.9277992249],"type":"Point"}
}