{
  "type": "Feature",
  "properties": {
    "iso:country":"GB",
    "sg:address":"1 Kirton Rd, Drayton",
    "sg:city":"Portsmouth",
    "sg:classifiers":[
        {
            "category":"Building & Trades",
            "subcategory":"Construction",
            "type":"Services"
        }
    ],
    "sg:phone":"+44 23 9238 0509",
    "sg:postcode":"PO6 2ES",
    "sg:province":"Hampshire",
    "sg:tags":[
        "builder"
    ],
    "wof:name":"Gray & West",
    "wof:placetype":"venue"
},
  "geometry": {"coordinates":[-1.0493099689,50.8425445557],"type":"Point"}
}