{
  "type": "Feature",
  "properties": {
    "addr:full":"39 Randolph Street Cowdenbeath Fife KY4 8NL",
    "addr:housenumber":"39",
    "addr:postcode":"ky4 8nl",
    "addr:street":"Randolph Street",
    "iso:country":"GB",
    "sg:address":"39 Randolph Street",
    "sg:city":"Cowdenbeath",
    "sg:classifiers":[
        {
            "category":"Travel",
            "subcategory":"Hotels & Motels",
            "type":"Entertainment"
        }
    ],
    "sg:postcode":"KY4 8NL",
    "sg:province":"Fife",
    "sg:tags":[
        "house",
        "guest"
    ],
    "wof:name":"Brenlin Cottage",
    "wof:placetype":"venue"
},
  "geometry": {"coordinates":[-3.3367440701,56.1076927185],"type":"Point"}
}