{
  "type": "Feature",
  "properties": {
    "addr:full":"111 High Street Blackwood Caerphilly NP12 1AD",
    "addr:housenumber":"111",
    "addr:postcode":"np12 1ad",
    "addr:street":"High Street",
    "iso:country":"GB",
    "sg:address":"111 High Street",
    "sg:city":"Blackwood",
    "sg:classifiers":[
        {
            "category":"Shopping",
            "subcategory":"Clothing, Apparel, & Fashions",
            "type":"Retail Goods"
        }
    ],
    "sg:postcode":"NP12 1AD",
    "sg:province":"Caerphilly",
    "sg:tags":[
        "menswear"
    ],
    "wof:name":"D59A63 Ltd.",
    "wof:placetype":"venue"
},
  "geometry": {"coordinates":[-3.1954319477,51.6673774719],"type":"Point"}
}