{
  "type": "Feature",
  "properties": {
    "addr:full":"Friar's Crag, Wycollar Dr Blackburn Lancashire BB2 7AG",
    "addr:postcode":"bb2 7ag",
    "addr:street":"Dr",
    "iso:country":"GB",
    "sg:address":"Friar's Crag, Wycollar Dr",
    "sg:city":"Blackburn",
    "sg:classifiers":[
        {
            "category":"Real Estate",
            "subcategory":"Architect",
            "type":"Services"
        }
    ],
    "sg:phone":"+44 1254 692537",
    "sg:postcode":"BB2 7AG",
    "sg:province":"Lancashire",
    "wof:name":"J T Property Design Management",
    "wof:placetype":"venue"
},
  "geometry": {"coordinates":[-2.5109400749,53.7556114197],"type":"Point"}
}