{
  "type": "Feature",
  "properties": {
    "addr:full":"Unit 10, Cedar Trade Park Ferndown Dorset BH21 7SD",
    "addr:housenumber":"unit 10",
    "addr:postcode":"bh21 7sd",
    "addr:street":"Cedar Trade Park",
    "iso:country":"GB",
    "sg:address":"Unit 10, Cedar Trade Park",
    "sg:city":"Ferndown",
    "sg:classifiers":[
        {
            "category":"Professional",
            "subcategory":"Printing & Photocopies",
            "type":"Services"
        }
    ],
    "sg:postcode":"BH21 7SD",
    "sg:province":"Dorset",
    "sg:tags":[
        "print",
        "finisher"
    ],
    "wof:name":"Southern Counties Print Finishers",
    "wof:placetype":"venue"
},
  "geometry": {"coordinates":[-1.945208,50.827141],"type":"Point"}
}