{
  "type": "Feature",
  "properties": {
    "iso:country":"GB",
    "sg:address":"Grange Lane North",
    "sg:city":"Scunthorpe",
    "sg:classifiers":[
        {
            "category":"Manufacturing",
            "subcategory":"Metals",
            "type":"Manufacturing & Wholesale Goods"
        }
    ],
    "sg:phone":"+44 1724 861420",
    "sg:postcode":"DN16 1BN",
    "sg:province":"Lincolnshire",
    "sg:tags":[
        "work",
        "sheet"
    ],
    "wof:name":"Reginald A Bromby",
    "wof:placetype":"venue"
},
  "geometry": {"coordinates":[-0.6283490062,53.57213974],"type":"Point"}
}