{
  "type": "Feature",
  "properties": {
    "addr:full":"Unit 5 Indoor Market, Trinity Square Gateshead Tyne and Wear NE8 1AW",
    "addr:housenumber":"unit",
    "addr:postcode":"ne8 1aw",
    "addr:street":"Trinity Square",
    "iso:country":"GB",
    "sg:address":"Unit 5 Indoor Market, Trinity Square",
    "sg:city":"Gateshead",
    "sg:classifiers":[
        {
            "category":"Food & Beverages",
            "subcategory":"Bakery",
            "type":"Retail Goods"
        }
    ],
    "sg:phone":"+44 191 477 9317",
    "sg:postcode":"NE8 1AW",
    "sg:province":"Tyne and Wear",
    "sg:tags":[
        "baker"
    ],
    "wof:name":"The Bakers Oven",
    "wof:placetype":"venue"
},
  "geometry": {"coordinates":[-1.6020460129,54.9610404968],"type":"Point"}
}