{
  "type": "Feature",
  "properties": {
    "addr:full":"Exeter St Plymouth Devon PL4 0PD",
    "addr:postcode":"pl4 0pd",
    "addr:street":"Exeter St",
    "iso:country":"GB",
    "sg:address":"Exeter St",
    "sg:city":"Plymouth",
    "sg:classifiers":[
        {
            "category":"Autos & Motor Vehicles",
            "subcategory":"Auto Supplies",
            "type":"Retail Goods"
        }
    ],
    "sg:postcode":"PL4 0PD",
    "sg:province":"Devon",
    "sg:tags":[
        "component"
    ],
    "wof:name":"Edmunds Walker & Co",
    "wof:placetype":"venue"
},
  "geometry": {"coordinates":[-4.133895874,50.3716545105],"type":"Point"}
}