{
  "type": "Feature",
  "properties": {
    "addr:full":"Ashdown Farm, Aston Tirrold Didcot Oxfordshire OX11 9DR",
    "addr:housenumber":"ashdown farm",
    "addr:postcode":"ox11 9dr",
    "iso:country":"GB",
    "sg:address":"Ashdown Farm, Aston Tirrold",
    "sg:city":"Didcot",
    "sg:classifiers":[
        {
            "category":"Home & Garden",
            "subcategory":"Garden Supply",
            "type":"Retail Goods"
        },
        {
            "category":"Farming",
            "subcategory":"Livestock Farm",
            "type":"Manufacturing & Wholesale Goods"
        }
    ],
    "sg:postcode":"OX11 9DR",
    "sg:province":"Oxfordshire",
    "sg:tags":[
        "bulb",
        "grower",
        "others"
    ],
    "wof:name":"P B & J E Backhouse",
    "wof:placetype":"venue"
},
  "geometry": {"coordinates":[-1.2006839514,51.5698852539],"type":"Point"}
}