{
  "type": "Feature",
  "properties": {
    "addr:full":"61 Kingsway Banbury Oxfordshire OX16 9NX",
    "addr:housenumber":"61",
    "addr:postcode":"ox16 9nx",
    "addr:street":"Kingsway",
    "iso:country":"GB",
    "sg:address":"61 Kingsway",
    "sg:city":"Banbury",
    "sg:classifiers":[
        {
            "category":"Home & Garden",
            "subcategory":"Home Furnishings",
            "type":"Retail Goods"
        },
        {
            "category":"Building & Trades",
            "subcategory":"Construction",
            "type":"Services"
        },
        {
            "category":"Home & Garden",
            "subcategory":"Carpets & Floor Coverings",
            "type":"Retail Goods"
        }
    ],
    "sg:phone":"+44 1295 264954",
    "sg:postcode":"OX16 9NX",
    "sg:province":"Oxfordshire",
    "sg:tags":[
        "rug",
        "contractor",
        "fitting",
        "tiling",
        "matting",
        "carpets"
    ],
    "wof:name":"DAVID JOHN BURN",
    "wof:placetype":"venue"
},
  "geometry": {"coordinates":[-1.347918,52.05587],"type":"Point"}
}