{
  "type": "Feature",
  "properties": {
    "addr:full":"Unit 509, The Workstation, Paternoster Row Sheffield South Yorkshire S1 2BX",
    "addr:housenumber":"509",
    "addr:postcode":"s1 2bx",
    "addr:street":"The Workstation Paternoster Row",
    "iso:country":"GB",
    "sg:address":"Unit 509, The Workstation, Paternoster Row",
    "sg:city":"Sheffield",
    "sg:classifiers":[
        {
            "category":"Professional",
            "subcategory":"Computer Services",
            "type":"Services"
        }
    ],
    "sg:phone":"+44 114 221 0391",
    "sg:postcode":"S1 2BX",
    "sg:province":"South Yorkshire",
    "sg:tags":[
        "system",
        "software"
    ],
    "wof:name":"Windmill",
    "wof:placetype":"venue"
},
  "geometry": {"coordinates":[-1.464544,53.38311],"type":"Point"}
}