{
  "type": "Feature",
  "properties": {
    "iso:country":"GB",
    "sg:address":"Black Lion, 23 Mill Rd",
    "sg:city":"Gillingham",
    "sg:classifiers":[
        {
            "category":"Community Center",
            "subcategory":"Youth",
            "type":"Public Place"
        }
    ],
    "sg:phone":"+44 1634 684694",
    "sg:postcode":"ME7 1HL",
    "sg:province":"Kent",
    "sg:tags":[
        "organisation",
        "centre"
    ],
    "wof:name":"Medway 18 Plus Group",
    "wof:placetype":"venue"
},
  "geometry": {"coordinates":[0.5495430231,51.3864593506],"type":"Point"}
}