{
  "type": "Feature",
  "properties": {
    "addr:full":"15 Eastergate Close, Goring Worthing West Sussex BN12 5DH",
    "addr:housenumber":"15",
    "addr:postcode":"bn12 5dh",
    "addr:street":"Eastergate Close",
    "iso:country":"GB",
    "sg:address":"15 Eastergate Close, Goring",
    "sg:city":"Worthing",
    "sg:classifiers":[
        {
            "category":"Professional",
            "subcategory":"Engineering",
            "type":"Services"
        }
    ],
    "sg:postcode":"BN12 5DH",
    "sg:province":"West Sussex",
    "sg:tags":[
        "contractor",
        "electrical",
        "engineer"
    ],
    "wof:name":"David Draper Electrician",
    "wof:placetype":"venue"
},
  "geometry": {"coordinates":[-0.43967399,50.8163146973],"type":"Point"}
}