{
  "type": "Feature",
  "properties": {
    "addr:full":"283 Green Lanes London Greater London N13 4XS",
    "addr:housenumber":"283",
    "addr:postcode":"n13 4xs",
    "addr:street":"Green Lanes",
    "iso:country":"GB",
    "sg:address":"283 Green Lanes",
    "sg:city":"London",
    "sg:classifiers":[
        {
            "category":"Communications",
            "type":"Services"
        }
    ],
    "sg:postcode":"N13 4XS",
    "sg:province":"Greater London",
    "sg:tags":[
        "data",
        "network"
    ],
    "wof:name":"Mythos Media Services Ltd",
    "wof:placetype":"venue"
},
  "geometry": {"coordinates":[-0.109436,51.61705],"type":"Point"}
}