{
  "type": "Feature",
  "properties": {
    "iso:country":"GB",
    "sg:address":"Bower Mount Surgery, Lees Road, Yalding",
    "sg:city":"Maidstone",
    "sg:classifiers":[
        {
            "category":"Health Services",
            "subcategory":"Doctor",
            "type":"Services"
        }
    ],
    "sg:phone":"+44 1622 814373",
    "sg:postcode":"ME18 6HB",
    "sg:province":"Kent",
    "sg:tags":[
        "practitioners"
    ],
    "wof:name":"J C Virden",
    "wof:placetype":"venue"
},
  "geometry": {"coordinates":[0.438452,51.224354],"type":"Point"}
}