{
  "type": "Feature",
  "properties": {
    "iso:country":"GB",
    "sg:address":"30 Central Drive",
    "sg:city":"Chesterfield",
    "sg:classifiers":[
        {
            "category":"Building & Trades",
            "subcategory":"Landscaping Services",
            "type":"Services"
        }
    ],
    "sg:phone":"+44 1246 279277",
    "sg:postcode":"S42 6QL",
    "sg:province":"Derbyshire",
    "sg:tags":[
        "forestry",
        "tree"
    ],
    "wof:name":"Wingerworth Home & Garden Services",
    "wof:placetype":"venue"
},
  "geometry": {"coordinates":[-1.433557,53.200558],"type":"Point"}
}