{
  "type": "Feature",
  "properties": {
    "addr:full":"Highbank, Woodhouse Road Thornton-cleveleys Lancashire FY5 5LQ",
    "addr:postcode":"fy5 5lq",
    "addr:street":"Woodhouse Road",
    "iso:country":"GB",
    "sg:address":"Highbank, Woodhouse Road",
    "sg:city":"Thornton-cleveleys",
    "sg:classifiers":[
        {
            "category":"Real Estate",
            "subcategory":"Architect",
            "type":"Services"
        }
    ],
    "sg:postcode":"FY5 5LQ",
    "sg:province":"Lancashire",
    "wof:name":"Eric Forster Chartered Architect",
    "wof:placetype":"venue"
},
  "geometry": {"coordinates":[-2.987352,53.866024],"type":"Point"}
}