{
  "type": "Feature",
  "properties": {
    "addr:full":"9 Westcliffe Rd Southport Lancashire PR8 2BW",
    "addr:housenumber":"9",
    "addr:postcode":"pr8 2bw",
    "addr:street":"Westcliffe Rd",
    "iso:country":"GB",
    "sg:address":"9 Westcliffe Rd",
    "sg:city":"Southport",
    "sg:classifiers":[
        {
            "category":"Social Services",
            "subcategory":"Retirement Home",
            "type":"Services"
        }
    ],
    "sg:phone":"+44 1704 569947",
    "sg:postcode":"PR8 2BW",
    "sg:province":"Lancashire",
    "sg:tags":[
        "rest"
    ],
    "wof:name":"Gables The",
    "wof:placetype":"venue"
},
  "geometry": {"coordinates":[-3.0191230774,53.6408233643],"type":"Point"}
}