{
  "type": "Feature",
  "properties": {
    "iso:country":"GB",
    "sg:address":"Blair Lane Farm, Blairlogie",
    "sg:city":"Stirling",
    "sg:classifiers":[
        {
            "category":"Farming",
            "subcategory":"Dairy Farm",
            "type":"Manufacturing & Wholesale Goods"
        }
    ],
    "sg:postcode":"FK9 5QA",
    "sg:province":"Clackmannanshire",
    "wof:name":"A Logan & Sons",
    "wof:placetype":"venue"
},
  "geometry": {"coordinates":[-3.886337,56.149055],"type":"Point"}
}