{
  "type": "Feature",
  "properties": {
    "iso:country":"GB",
    "sg:address":"Main Rd, Galgate",
    "sg:city":"Lancaster",
    "sg:classifiers":[
        {
            "category":"Bars & Pubs",
            "type":"Food & Drink"
        },
        {
            "category":"Community Center",
            "subcategory":"Social",
            "type":"Public Place"
        }
    ],
    "sg:phone":"+44 1524 751337",
    "sg:postcode":"LA2 0LQ",
    "sg:province":"Lancashire",
    "sg:tags":[
        "pubs",
        "house",
        "inn",
        "activity"
    ],
    "wof:name":"Plough Inn",
    "wof:placetype":"venue"
},
  "geometry": {"coordinates":[-2.789866,53.989929],"type":"Point"}
}