{
  "type": "Feature",
  "properties": {
    "iso:country":"GB",
    "sg:address":"94 Chorlton Rd, Old Trafford",
    "sg:city":"Manchester",
    "sg:classifiers":[
        {
            "category":"Home & Garden",
            "subcategory":"Hardware",
            "type":"Retail Goods"
        },
        {
            "category":"Manufacturing",
            "subcategory":"Building Materials",
            "type":"Manufacturing & Wholesale Goods"
        }
    ],
    "sg:phone":"+44 161 226 3929",
    "sg:postcode":"M15 4AN",
    "sg:province":"Cheshire",
    "sg:tags":[
        "shop",
        "tile",
        "diy",
        "mnfrs"
    ],
    "sg:website":"http://www.almurad.co.uk",
    "wof:name":"Al Murad DIY Ltd",
    "wof:placetype":"venue"
},
  "geometry": {"coordinates":[-2.2575700283,53.4661254883],"type":"Point"}
}