{
  "type": "Feature",
  "properties": {
    "addr:full":"20 Monument Close Wellington Devon TA21 9AL",
    "addr:housenumber":"20",
    "addr:postcode":"ta21 9al",
    "addr:street":"Monument Close",
    "iso:country":"GB",
    "sg:address":"20 Monument Close",
    "sg:city":"Wellington",
    "sg:classifiers":[
        {
            "category":"Manufacturing",
            "subcategory":"Petroleum Products",
            "type":"Manufacturing & Wholesale Goods"
        },
        {
            "category":"Building & Trades",
            "subcategory":"Construction",
            "type":"Services"
        }
    ],
    "sg:phone":"+44 1823 665368",
    "sg:postcode":"TA21 9AL",
    "sg:province":"Devon",
    "sg:tags":[
        "double",
        "glazing",
        "installers"
    ],
    "wof:name":"Classy Glass",
    "wof:placetype":"venue"
},
  "geometry": {"coordinates":[-3.2230329514,50.9708175659],"type":"Point"}
}