{
  "type": "Feature",
  "properties": {
    "addr:full":"Tunstall Health Centre, Dunning St Stoke On Trent Staffordshire ST6 5AP",
    "addr:postcode":"st6 5ap",
    "addr:street":"St",
    "iso:country":"GB",
    "sg:address":"Tunstall Health Centre, Dunning St",
    "sg:city":"Stoke On Trent",
    "sg:classifiers":[
        {
            "category":"Health Services",
            "subcategory":"Doctor",
            "type":"Services"
        }
    ],
    "sg:phone":"+44 1782 425839",
    "sg:postcode":"ST6 5AP",
    "sg:province":"Staffordshire",
    "sg:tags":[
        "practitioners"
    ],
    "wof:name":"Singh, A K",
    "wof:placetype":"venue"
},
  "geometry": {"coordinates":[-2.21184,53.060219],"type":"Point"}
}