{
  "type": "Feature",
  "properties": {
    "iso:country":"GB",
    "sg:address":"19 Stafford Road",
    "sg:city":"Wallington",
    "sg:classifiers":[
        {
            "category":"Travel",
            "subcategory":"Hotels & Motels",
            "type":"Entertainment"
        }
    ],
    "sg:postcode":"SM6 9AN",
    "sg:province":"Surrey",
    "sg:tags":[
        "house",
        "guest"
    ],
    "wof:name":"J P's Bed & Breakfast",
    "wof:placetype":"venue"
},
  "geometry": {"coordinates":[-0.146254,51.357971],"type":"Point"}
}