{
  "type": "Feature",
  "properties": {
    "iso:country":"GB",
    "sg:address":"9 Denbigh Rd",
    "sg:city":"Northampton",
    "sg:classifiers":[
        {
            "category":"Professional",
            "subcategory":"Accounting & Tax Preparation",
            "type":"Services"
        }
    ],
    "sg:phone":"+44 1604 631020",
    "sg:postcode":"NN3 3HF",
    "sg:province":"Northamptonshire",
    "sg:tags":[
        "accountant"
    ],
    "wof:name":"Abacus",
    "wof:placetype":"venue"
},
  "geometry": {"coordinates":[-0.848545,52.240242],"type":"Point"}
}