{
  "type": "Feature",
  "properties": {
    "addr:full":"Lixwm Road, Brynford Holywell Denbighshire CH8 8LR",
    "addr:postcode":"ch8 8lr",
    "addr:street":"Lixwm Road",
    "iso:country":"GB",
    "sg:address":"Lixwm Road, Brynford",
    "sg:city":"Holywell",
    "sg:classifiers":[
        {
            "category":"Farming",
            "subcategory":"Livestock Farm",
            "type":"Manufacturing & Wholesale Goods"
        }
    ],
    "sg:phone":"+44 1352 712028",
    "sg:postcode":"CH8 8LR",
    "sg:province":"Denbighshire",
    "sg:tags":[
        "others"
    ],
    "wof:name":"J P Hooson",
    "wof:placetype":"venue"
},
  "geometry": {"coordinates":[-3.234544,53.25861],"type":"Point"}
}