{
  "type": "Feature",
  "properties": {
    "addr:full":"Cavendish Lodge, Turret Lane Ipswich Suffolk IP4 1DL",
    "addr:postcode":"ip4 1dl",
    "addr:street":"Turret Lane",
    "iso:country":"GB",
    "sg:address":"Cavendish Lodge, Turret Lane",
    "sg:city":"Ipswich",
    "sg:classifiers":[
        {
            "category":"Travel",
            "subcategory":"Hostel",
            "type":"Entertainment"
        }
    ],
    "sg:phone":"+44 1473 219155",
    "sg:postcode":"IP4 1DL",
    "sg:province":"Suffolk",
    "wof:name":"St.Matthew Housing",
    "wof:placetype":"venue"
},
  "geometry": {"coordinates":[1.15484,52.054668],"type":"Point"}
}