{
  "type": "Feature",
  "properties": {
    "iso:country":"GB",
    "sg:address":"96 Station Road",
    "sg:city":"Brierley Hill",
    "sg:classifiers":[
        {
            "category":"Transit Center",
            "subcategory":"Passenger",
            "type":"Transportation"
        },
        {
            "category":"Farming",
            "subcategory":"Livestock Farm",
            "type":"Manufacturing & Wholesale Goods"
        }
    ],
    "sg:phone":"+44 1384 78215",
    "sg:postcode":"DY5 3HR",
    "sg:province":"West Midlands",
    "sg:tags":[
        "boarding",
        "kennel",
        "catteries"
    ],
    "wof:name":"Brockmoor Boarding Cattery",
    "wof:placetype":"venue"
},
  "geometry": {"coordinates":[-2.126902,52.484406],"type":"Point"}
}