{
  "type": "Feature",
  "properties": {
    "iso:country":"GB",
    "sg:address":"Waterfall Rd, Southgate",
    "sg:city":"Southgate",
    "sg:classifiers":[
        {
            "category":"Arena",
            "subcategory":"Sports Club",
            "type":"Entertainment"
        }
    ],
    "sg:phone":"+44 20 8886 8381",
    "sg:postcode":"N14 7JS",
    "sg:province":"Greater London",
    "wof:name":"Southgate Cricket & Squash Clubs",
    "wof:placetype":"venue"
},
  "geometry": {"coordinates":[-0.132161,51.624287],"type":"Point"}
}