{
  "type": "Feature",
  "properties": {
    "addr:full":"41 High Street Billericay Essex CM12 9AZ",
    "addr:housenumber":"41",
    "addr:postcode":"cm12 9az",
    "addr:street":"High Street",
    "iso:country":"GB",
    "sg:address":"41 High Street",
    "sg:city":"Billericay",
    "sg:classifiers":[
        {
            "category":"Banks & Credit Unions",
            "subcategory":"Bank",
            "type":"Services"
        }
    ],
    "sg:phone":"+44 20 8804 4892",
    "sg:postcode":"CM12 9AZ",
    "sg:province":"Essex",
    "sg:tags":[
        "financial",
        "institution"
    ],
    "wof:name":"NATIONAL WESTMINSTER BANK PLC",
    "wof:placetype":"venue"
},
  "geometry": {"coordinates":[0.4184910059,51.6268806458],"type":"Point"}
}