{
  "type": "Feature",
  "properties": {
    "addr:full":"Dam Park Statium Ayr South Ayrshire KA8 0ET",
    "addr:postcode":"ka8 0et",
    "addr:street":"Dam;Statium",
    "iso:country":"GB",
    "sg:address":"Dam Park Statium",
    "sg:city":"Ayr",
    "sg:classifiers":[
        {
            "category":"Government",
            "subcategory":"Office",
            "type":"Public Place"
        }
    ],
    "sg:phone":"+44 1292 619595",
    "sg:postcode":"KA8 0ET",
    "sg:province":"South Ayrshire",
    "sg:tags":[
        "local"
    ],
    "wof:name":"South Ayrshire Council",
    "wof:placetype":"venue"
},
  "geometry": {"coordinates":[-4.6199197769,55.4609298706],"type":"Point"}
}