{
  "type": "Feature",
  "properties": {
    "iso:country":"GB",
    "sg:address":"50 Castle Road",
    "sg:city":"Newport",
    "sg:classifiers":[
        {
            "category":"Health Services",
            "subcategory":"Hospital",
            "type":"Services"
        }
    ],
    "sg:phone":"+44 1983 821037",
    "sg:postcode":"PO30 1DT",
    "sg:province":"Isle of Wight",
    "wof:name":"The Kestrals",
    "wof:placetype":"venue"
},
  "geometry": {"coordinates":[-1.306331,50.692719],"type":"Point"}
}