{
  "type": "Feature",
  "properties": {
    "iso:country":"GB",
    "sg:address":"10 Higher Street",
    "sg:city":"Merriott",
    "sg:classifiers":[
        {
            "category":"Building & Trades",
            "subcategory":"Construction",
            "type":"Services"
        }
    ],
    "sg:phone":"+44 1460 73287",
    "sg:postcode":"TA16 5PJ",
    "sg:province":"Somerset",
    "sg:tags":[
        "decorator",
        "painter"
    ],
    "wof:name":"B V Mildenberger",
    "wof:placetype":"venue"
},
  "geometry": {"coordinates":[-2.789287,50.913635],"type":"Point"}
}