{
  "type": "Feature",
  "properties": {
    "addr:full":"Paddock House Farm, Scagglethorpe Malton North Yorkshire YO17 8EA",
    "addr:housenumber":"scagglethorpe",
    "addr:postcode":"yo17 8ea",
    "iso:country":"GB",
    "sg:address":"Paddock House Farm, Scagglethorpe",
    "sg:city":"Malton",
    "sg:classifiers":[
        {
            "category":"Food & Beverages",
            "subcategory":"Farmers Market",
            "type":"Retail Goods"
        }
    ],
    "sg:postcode":"YO17 8EA",
    "sg:province":"North Yorkshire",
    "sg:tags":[
        "farm",
        "shop",
        "pyo"
    ],
    "wof:name":"K H & S N Stonehouse",
    "wof:placetype":"venue"
},
  "geometry": {"coordinates":[-0.7230520248,54.1413116455],"type":"Point"}
}