{
  "type": "Feature",
  "properties": {
    "addr:full":"Unit 3 Crossways, 175 Station Road, West Moors Ferndown Dorset BH22 0HT",
    "addr:housenumber":"unit 3;175",
    "addr:postcode":"bh22 0ht",
    "addr:street":"Crossways;Station Road West",
    "iso:country":"GB",
    "sg:address":"Unit 3 Crossways, 175 Station Road, West Moors",
    "sg:city":"Ferndown",
    "sg:classifiers":[
        {
            "category":"Health Services",
            "subcategory":"Chiropractor",
            "type":"Services"
        }
    ],
    "sg:phone":"+44 1202 870852",
    "sg:postcode":"BH22 0HT",
    "sg:province":"Dorset",
    "wof:name":"West Moors Chiropractic Clinic",
    "wof:placetype":"venue"
},
  "geometry": {"coordinates":[-1.8890140057,50.8249511719],"type":"Point"}
}