{
  "type": "Feature",
  "properties": {
    "addr:full":"9 Lansdowne Terrace, Gosforth Newcastle-upon-tyne Tyne and Wear NE3 1HN",
    "addr:housenumber":"9",
    "addr:postcode":"ne3 1hn",
    "addr:street":"Lansdowne Terrace",
    "iso:country":"GB",
    "sg:address":"9 Lansdowne Terrace, Gosforth",
    "sg:city":"Newcastle-upon-tyne",
    "sg:classifiers":[
        {
            "category":"Retail",
            "subcategory":"Funeral Services",
            "type":"Services"
        }
    ],
    "sg:phone":"+44 191 285 8376",
    "sg:postcode":"NE3 1HN",
    "sg:province":"Tyne and Wear",
    "sg:tags":[
        "director"
    ],
    "wof:name":"W S Harrison & Son",
    "wof:placetype":"venue"
},
  "geometry": {"coordinates":[-1.6204990149,55.0101242065],"type":"Point"}
}