{
  "type": "Feature",
  "properties": {
    "iso:country":"GB",
    "sg:address":"16 George Street",
    "sg:city":"Huntingdon",
    "sg:classifiers":[
        {
            "category":"Travel",
            "subcategory":"Hotels & Motels",
            "type":"Entertainment"
        }
    ],
    "sg:phone":"+44 1480 458484",
    "sg:postcode":"PE29 3BD",
    "sg:province":"Cambridgeshire",
    "sg:tags":[
        "house",
        "guest"
    ],
    "wof:name":"Sandwich Villas Guest House",
    "wof:placetype":"venue"
},
  "geometry": {"coordinates":[-0.187619,52.329983],"type":"Point"}
}