{
  "type": "Feature",
  "properties": {
    "addr:full":"72 Brooksbys Walk London Greater London E9 6DA",
    "addr:housenumber":"72",
    "addr:postcode":"e9 6da",
    "addr:street":"Brooksbys Walk",
    "iso:country":"GB",
    "sg:address":"72 Brooksbys Walk",
    "sg:city":"London",
    "sg:classifiers":[
        {
            "category":"Manufacturing",
            "subcategory":"Apparel",
            "type":"Manufacturing & Wholesale Goods"
        }
    ],
    "sg:postcode":"E9 6DA",
    "sg:province":"Greater London",
    "sg:tags":[
        "mnfr",
        "footwear"
    ],
    "wof:name":"Tonys Closers",
    "wof:placetype":"venue"
},
  "geometry": {"coordinates":[-0.04332,51.551109],"type":"Point"}
}