{
  "type": "Feature",
  "properties": {
    "iso:country":"GB",
    "sg:address":"Broadview Farm, Drayton Beauchamp",
    "sg:city":"Aylesbury",
    "sg:classifiers":[
        {
            "category":"Farming",
            "subcategory":"Livestock Farm",
            "type":"Manufacturing & Wholesale Goods"
        }
    ],
    "sg:phone":"+44 1442 826280",
    "sg:postcode":"HP22 5LU",
    "sg:province":"Buckinghamshire",
    "sg:tags":[
        "others"
    ],
    "wof:name":"P E Slough",
    "wof:placetype":"venue"
},
  "geometry": {"coordinates":[-0.6907669902,51.7977638245],"type":"Point"}
}