{
  "type": "Feature",
  "properties": {
    "addr:full":"146 Duke Street St Helens Merseyside WA10 2JL",
    "addr:housenumber":"146",
    "addr:postcode":"wa10 2jl",
    "addr:street":"Duke Street",
    "iso:country":"GB",
    "sg:address":"146 Duke Street",
    "sg:city":"St Helens",
    "sg:classifiers":[
        {
            "category":"Manufacturing",
            "subcategory":"Petroleum Products",
            "type":"Manufacturing & Wholesale Goods"
        }
    ],
    "sg:postcode":"WA10 2JL",
    "sg:province":"Merseyside",
    "sg:tags":[
        "double",
        "glazing"
    ],
    "wof:name":"Majestic Windows Ltd.",
    "wof:placetype":"venue"
},
  "geometry": {"coordinates":[-2.7440838814,53.4568634033],"type":"Point"}
}