{
  "type": "Feature",
  "properties": {
    "addr:full":"8 Park Road London Greater London N8 8TD",
    "addr:housenumber":"8",
    "addr:postcode":"n8 8td",
    "addr:street":"Park Road",
    "iso:country":"GB",
    "sg:address":"8 Park Road",
    "sg:city":"London",
    "sg:classifiers":[
        {
            "category":"Fast Food",
            "type":"Food & Drink"
        }
    ],
    "sg:phone":"+44 20 8348 6904",
    "sg:postcode":"N8 8TD",
    "sg:province":"Greater London",
    "sg:tags":[
        "away",
        "meal",
        "outlet",
        "take"
    ],
    "wof:name":"Dragon Chinese",
    "wof:placetype":"venue"
},
  "geometry": {"coordinates":[-0.12865,51.58326],"type":"Point"}
}