{
  "type": "Feature",
  "properties": {
    "addr:full":"Unit 13, Calder Trading Estate, Bradford Road Brighouse West Yorkshire HD6 4DJ",
    "addr:housenumber":"unit 13",
    "addr:postcode":"hd6 4dj",
    "addr:street":"Calder Trading Estate Bradford Road",
    "iso:country":"GB",
    "sg:address":"Unit 13, Calder Trading Estate, Bradford Road",
    "sg:city":"Brighouse",
    "sg:classifiers":[
        {
            "category":"Building & Trades",
            "subcategory":"Construction",
            "type":"Services"
        }
    ],
    "sg:phone":"+44 1484 400952",
    "sg:postcode":"HD6 4DJ",
    "sg:province":"West Yorkshire",
    "sg:tags":[
        "joiner",
        "carpenter"
    ],
    "wof:name":"Bailiff Bridge Joinery",
    "wof:placetype":"venue"
},
  "geometry": {"coordinates":[-1.7737369537,53.7021942139],"type":"Point"}
}