{
  "type": "Feature",
  "properties": {
    "iso:country":"GB",
    "sg:address":"76a Montague Street",
    "sg:city":"Worthing",
    "sg:classifiers":[
        {
            "category":"Shopping",
            "subcategory":"Clothing, Apparel, & Fashions",
            "type":"Retail Goods"
        }
    ],
    "sg:phone":"+44 1903 217826",
    "sg:postcode":"BN11 3HE",
    "sg:province":"West Sussex",
    "sg:tags":[
        "ladieswear"
    ],
    "wof:name":"Elvi",
    "wof:placetype":"venue"
},
  "geometry": {"coordinates":[-0.376259,50.809959],"type":"Point"}
}