{
  "type": "Feature",
  "properties": {
    "iso:country":"GB",
    "sg:address":"5 Southgate Street",
    "sg:city":"Gloucester",
    "sg:classifiers":[
        {
            "category":"Shopping",
            "subcategory":"Comic Books",
            "type":"Retail Goods"
        }
    ],
    "sg:phone":"+44 1452 522926",
    "sg:postcode":"GL1 1TG",
    "sg:province":"Gloucestershire",
    "sg:tags":[
        "jeweller"
    ],
    "wof:name":"G A Baker & Son",
    "wof:placetype":"venue"
},
  "geometry": {"coordinates":[-2.245954,51.86507],"type":"Point"}
}