{
  "type": "Feature",
  "properties": {
    "iso:country":"GB",
    "sg:address":"Coventry Lodge, Sleight Lane, Corfe Mullen",
    "sg:city":"Wimborne",
    "sg:classifiers":[
        {
            "category":"Building & Trades",
            "subcategory":"Construction",
            "type":"Services"
        }
    ],
    "sg:postcode":"BH21 3HL",
    "sg:province":"Dorset",
    "sg:tags":[
        "builder"
    ],
    "wof:name":"Design & Construction",
    "wof:placetype":"venue"
},
  "geometry": {"coordinates":[-2.0151538849,50.7770462036],"type":"Point"}
}