{
  "type": "Feature",
  "properties": {
    "addr:full":"69-71 Poplar Road Redditch Warwickshire B97 6NY",
    "addr:housenumber":"69-71",
    "addr:postcode":"b97 6ny",
    "addr:street":"Poplar Road",
    "iso:country":"GB",
    "sg:address":"69-71 Poplar Road",
    "sg:city":"Redditch",
    "sg:classifiers":[
        {
            "category":"Fast Food",
            "type":"Food & Drink"
        }
    ],
    "sg:phone":"+44 1527 64190",
    "sg:postcode":"B97 6NY",
    "sg:province":"Warwickshire",
    "sg:tags":[
        "away",
        "meal",
        "outlet",
        "take"
    ],
    "wof:name":"Eastern Star",
    "wof:placetype":"venue"
},
  "geometry": {"coordinates":[-1.9663820267,52.3048439026],"type":"Point"}
}