{
  "type": "Feature",
  "properties": {
    "iso:country":"GB",
    "sg:address":"8 Mardol Head",
    "sg:city":"Shrewsbury",
    "sg:classifiers":[
        {
            "category":"Banks & Credit Unions",
            "subcategory":"Bank",
            "type":"Services"
        }
    ],
    "sg:phone":"+44 1743 367601",
    "sg:postcode":"SY1 1HE",
    "sg:province":"Shropshire",
    "wof:name":"NatWest",
    "wof:placetype":"venue"
},
  "geometry": {"coordinates":[-2.7546360493,52.707950592],"type":"Point"}
}