{
  "type": "Feature",
  "properties": {
    "iso:country":"GB",
    "sg:address":"23 Linley Avenue, Shepshed",
    "sg:city":"Loughborough",
    "sg:classifiers":[
        {
            "category":"Manufacturing",
            "subcategory":"Building Materials",
            "type":"Manufacturing & Wholesale Goods"
        }
    ],
    "sg:phone":"+44 1276 854200",
    "sg:postcode":"LE12 9HJ",
    "sg:province":"Leicestershire",
    "sg:tags":[
        "tube",
        "manipulator",
        "bender"
    ],
    "wof:name":"Alpha Tubes Ltd.",
    "wof:placetype":"venue"
},
  "geometry": {"coordinates":[-1.285306,52.764439],"type":"Point"}
}