{
  "type": "Feature",
  "properties": {
    "addr:full":"Kersewell, Backmuir Of Pitfirrane Dunfermline Fife KY12 8QR",
    "addr:postcode":"ky12 8qr",
    "iso:country":"GB",
    "sg:address":"Kersewell, Backmuir Of Pitfirrane",
    "sg:city":"Dunfermline",
    "sg:classifiers":[
        {
            "category":"Retail",
            "subcategory":"Auto Repair",
            "type":"Services"
        }
    ],
    "sg:phone":"+44 1383 736241",
    "sg:postcode":"KY12 8QR",
    "sg:province":"Fife",
    "sg:tags":[
        "modification",
        "garage",
        "related"
    ],
    "wof:name":"Keavil Autos",
    "wof:placetype":"venue"
},
  "geometry": {"coordinates":[-3.5445311069,56.0597267151],"type":"Point"}
}