{
  "type": "Feature",
  "properties": {
    "addr:full":"141 High Street Elgin Moray IV30 1DS",
    "addr:housenumber":"141",
    "addr:postcode":"iv30 1ds",
    "addr:street":"High Street",
    "iso:country":"GB",
    "sg:address":"141 High Street",
    "sg:city":"Elgin",
    "sg:classifiers":[
        {
            "category":"Professional",
            "subcategory":"Lawyer & Legal Services",
            "type":"Services"
        }
    ],
    "sg:phone":"+44 1343 544971",
    "sg:postcode":"IV30 1DS",
    "sg:province":"Moray",
    "sg:tags":[
        "solicitor"
    ],
    "wof:name":"Inchstelly Farms Ltd.",
    "wof:placetype":"venue"
},
  "geometry": {"coordinates":[-3.3159680367,57.6488838196],"type":"Point"}
}