{
  "type": "Feature",
  "properties": {
    "addr:full":"Rocky Road, Dowlais Merthyr Tydfil Caerphilly CF48 3BT",
    "addr:postcode":"cf48 3bt",
    "addr:street":"Rocky Road",
    "iso:country":"GB",
    "sg:address":"Rocky Road, Dowlais",
    "sg:city":"Merthyr Tydfil",
    "sg:classifiers":[
        {
            "category":"Place Of Worship",
            "type":"Public Place"
        },
        {
            "category":"Education",
            "subcategory":"School",
            "type":"Public Place"
        }
    ],
    "sg:phone":"+44 1685 722235",
    "sg:postcode":"CF48 3BT",
    "sg:province":"Caerphilly",
    "sg:tags":[
        "local",
        "authority"
    ],
    "wof:name":"St Illtyds R C Primary School",
    "wof:placetype":"venue"
},
  "geometry": {"coordinates":[-3.3608899117,51.7611198425],"type":"Point"}
}