{
  "type": "Feature",
  "properties": {
    "iso:country":"GB",
    "sg:address":"1 Great West Road",
    "sg:city":"Hounslow",
    "sg:classifiers":[
        {
            "category":"Autos & Motor Vehicles",
            "subcategory":"Fuel & Gas Station",
            "type":"Retail Goods"
        }
    ],
    "sg:phone":"+44 20 8577 2270",
    "sg:postcode":"TW5 9AN",
    "sg:province":"Greater London",
    "sg:tags":[
        "petrol",
        "filling"
    ],
    "wof:name":"Star Service Stations Ltd",
    "wof:placetype":"venue"
},
  "geometry": {"coordinates":[-0.392548,51.47514],"type":"Point"}
}