{
  "type": "Feature",
  "properties": {
    "iso:country":"GB",
    "sg:address":"61 Dugard Avenue",
    "sg:city":"Colchester",
    "sg:classifiers":[
        {
            "category":"Communications",
            "subcategory":"Film & Video Production",
            "type":"Services"
        }
    ],
    "sg:phone":"+44 1206 562155",
    "sg:postcode":"CO3 9EL",
    "sg:province":"Essex",
    "sg:tags":[
        "recording",
        "studio"
    ],
    "wof:name":"Garden Studios",
    "wof:placetype":"venue"
},
  "geometry": {"coordinates":[0.8507300019,51.8777809143],"type":"Point"}
}