{
  "type": "Feature",
  "properties": {
    "addr:full":"95a Chancery La London Greater London WC2A 2JG",
    "addr:housenumber":"95a",
    "addr:postcode":"wc2a 2jg",
    "addr:street":"Chancery La",
    "iso:country":"GB",
    "sg:address":"95a Chancery La",
    "sg:city":"London",
    "sg:classifiers":[
        {
            "category":"Banks & Credit Unions",
            "subcategory":"Financial Services",
            "type":"Services"
        }
    ],
    "sg:postcode":"WC2A 2JG",
    "sg:province":"Greater London",
    "sg:tags":[
        "adviser"
    ],
    "wof:name":"Murray Noble Ltd",
    "wof:placetype":"venue"
},
  "geometry": {"coordinates":[-0.1114490032,51.5153694153],"type":"Point"}
}