{
  "type": "Feature",
  "properties": {
    "iso:country":"GB",
    "sg:address":"Unit 9, 3 Knightswick Centre",
    "sg:city":"Canvey Island",
    "sg:classifiers":[
        {
            "category":"Sports & Exercise",
            "subcategory":"Sports Center",
            "type":"Entertainment"
        }
    ],
    "sg:phone":"+44 1268 515155",
    "sg:postcode":"SS8 7AD",
    "sg:province":"Essex",
    "sg:tags":[
        "shop",
        "good"
    ],
    "wof:name":"Penn Sports Ltd.",
    "wof:placetype":"venue"
},
  "geometry": {"coordinates":[0.59112,51.520374],"type":"Point"}
}