{
  "type": "Feature",
  "properties": {
    "iso:country":"GB",
    "sg:address":"65 Queens Gate Mews",
    "sg:city":"London",
    "sg:classifiers":[
        {
            "category":"Retail",
            "subcategory":"Photofinishing",
            "type":"Services"
        }
    ],
    "sg:phone":"+44 20 7589 5759",
    "sg:postcode":"SW7 5QN",
    "sg:province":"Greater London",
    "sg:tags":[
        "photographic",
        "processor"
    ],
    "wof:name":"Ceta Services Ltd.",
    "wof:placetype":"venue"
},
  "geometry": {"coordinates":[-0.183485,51.499046],"type":"Point"}
}