{
  "type": "Feature",
  "properties": {
    "iso:country":"GB",
    "sg:address":"14 Market Street, Charlbury",
    "sg:city":"Chipping Norton",
    "sg:classifiers":[
        {
            "category":"Personal",
            "subcategory":"Barber",
            "type":"Services"
        }
    ],
    "sg:phone":"+44 1608 810630",
    "sg:postcode":"OX7 3PN",
    "sg:province":"Gloucestershire",
    "sg:tags":[
        "men's",
        "hairdresser"
    ],
    "wof:name":"Peters Hairdressers",
    "wof:placetype":"venue"
},
  "geometry": {"coordinates":[-1.4832359552,51.8734893799],"type":"Point"}
}