{
  "type": "Feature",
  "properties": {
    "iso:country":"GB",
    "sg:address":"West Street, Lilley",
    "sg:city":"Luton",
    "sg:classifiers":[
        {
            "category":"Bars & Pubs",
            "type":"Food & Drink"
        }
    ],
    "sg:phone":"+44 1462 768386",
    "sg:postcode":"LU2 8LH",
    "sg:province":"Bedfordshire",
    "sg:tags":[
        "pubs",
        "inn"
    ],
    "wof:name":"A & M Ringe",
    "wof:placetype":"venue"
},
  "geometry": {"coordinates":[-0.374682,51.924862],"type":"Point"}
}