{
  "type": "Feature",
  "properties": {
    "iso:country":"GB",
    "sg:address":"46 Broadwick Street",
    "sg:city":"London",
    "sg:classifiers":[
        {
            "category":"Communications",
            "subcategory":"Film & Video Production",
            "type":"Services"
        },
        {
            "category":"Communications",
            "type":"Services"
        }
    ],
    "sg:phone":"+44 20 7734 8100",
    "sg:postcode":"W1F 7AF",
    "sg:province":"Greater London",
    "sg:tags":[
        "tv",
        "studio",
        "audio-visual"
    ],
    "wof:name":"Genesis Television Ltd.",
    "wof:placetype":"venue"
},
  "geometry": {"coordinates":[-0.13647,51.513485],"type":"Point"}
}