{
  "type": "Feature",
  "properties": {
    "iso:country":"GB",
    "sg:address":"56 Aire Street",
    "sg:city":"Goole",
    "sg:classifiers":[
        {
            "category":"Home & Garden",
            "subcategory":"Carpets & Floor Coverings",
            "type":"Retail Goods"
        }
    ],
    "sg:phone":"+44 1405 768887",
    "sg:postcode":"DN14 5QE",
    "sg:province":"East Riding of Yorkshire",
    "sg:tags":[
        "carpets",
        "retailer",
        "rug",
        "matting"
    ],
    "wof:name":"Kingsway Carpets",
    "wof:placetype":"venue"
},
  "geometry": {"coordinates":[-0.870823,53.702579],"type":"Point"}
}