{
  "type": "Feature",
  "properties": {
    "addr:full":"Lower Street Pulborough West Sussex RH20 2BH",
    "addr:postcode":"rh20 2bh",
    "addr:street":"Lower Street",
    "iso:country":"GB",
    "sg:address":"Lower Street",
    "sg:city":"Pulborough",
    "sg:classifiers":[
        {
            "category":"Personal",
            "subcategory":"Beauty Salon",
            "type":"Services"
        }
    ],
    "sg:phone":"+44 1798 872455",
    "sg:postcode":"RH20 2BH",
    "sg:province":"West Sussex",
    "sg:tags":[
        "unisex",
        "hairdresser"
    ],
    "wof:name":"Looking Beyond Hair Studio",
    "wof:placetype":"venue"
},
  "geometry": {"coordinates":[-0.505184,50.957439],"type":"Point"}
}