{
  "type": "Feature",
  "properties": {
    "addr:full":"Nailford House, Brewery Lane, Bridge Canterbury Kent CT4 5LF",
    "addr:postcode":"ct4 5lf",
    "addr:street":"Brewery Lane Bridge",
    "iso:country":"GB",
    "sg:address":"Nailford House, Brewery Lane, Bridge",
    "sg:city":"Canterbury",
    "sg:classifiers":[
        {
            "category":"Manufacturing",
            "subcategory":"Signs",
            "type":"Manufacturing & Wholesale Goods"
        }
    ],
    "sg:phone":"+44 1227 831044",
    "sg:postcode":"CT4 5LF",
    "sg:province":"Kent",
    "sg:tags":[
        "nameplate"
    ],
    "wof:name":"B D S C Ltd.",
    "wof:placetype":"venue"
},
  "geometry": {"coordinates":[1.1256430149,51.2448883057],"type":"Point"}
}