{
  "type": "Feature",
  "properties": {
    "addr:full":"226 High Road, Whaplode Spalding Cambridgeshire PE12 6TJ",
    "addr:housenumber":"226",
    "addr:postcode":"pe12 6tj",
    "addr:street":"High Road;Spalding",
    "iso:country":"GB",
    "sg:address":"226 High Road, Whaplode",
    "sg:city":"Spalding",
    "sg:classifiers":[
        {
            "category":"Bars & Pubs",
            "type":"Food & Drink"
        },
        {
            "category":"Community Center",
            "subcategory":"Social",
            "type":"Public Place"
        }
    ],
    "sg:phone":"+44 1406 370414",
    "sg:postcode":"PE12 6TJ",
    "sg:province":"Cambridgeshire",
    "sg:tags":[
        "pubs",
        "house",
        "inn",
        "activity"
    ],
    "wof:name":"Lamb & Flag",
    "wof:placetype":"venue"
},
  "geometry": {"coordinates":[-0.070671998,52.8063964844],"type":"Point"}
}