{
  "type": "Feature",
  "properties": {
    "addr:full":"Unit 9 Kiln Workshops, Pilcot Road, Crookham Village Fleet Hampshire GU51 5RY",
    "addr:housenumber":"unit 9",
    "addr:postcode":"gu51 5ry",
    "addr:street":"Pilcot Road",
    "iso:country":"GB",
    "sg:address":"Unit 9 Kiln Workshops, Pilcot Road, Crookham Village",
    "sg:city":"Fleet",
    "sg:classifiers":[
        {
            "category":"Professional",
            "subcategory":"Art Services",
            "type":"Services"
        }
    ],
    "sg:phone":"+44 1252 622272",
    "sg:postcode":"GU51 5RY",
    "sg:province":"Hampshire",
    "sg:tags":[
        "consultant",
        "design"
    ],
    "wof:name":"Juliet Robson Textile Design",
    "wof:placetype":"venue"
},
  "geometry": {"coordinates":[-0.8645799756,51.2660598755],"type":"Point"}
}