{
  "type": "Feature",
  "properties": {
    "iso:country":"GB",
    "sg:address":"Avenue Road, Carstairs",
    "sg:city":"Lanark",
    "sg:classifiers":[
        {
            "category":"Education",
            "subcategory":"School",
            "type":"Public Place"
        },
        {
            "category":"Government",
            "subcategory":"Office",
            "type":"Public Place"
        }
    ],
    "sg:phone":"+44 1555 870462",
    "sg:postcode":"ML11 8QE",
    "sg:province":"South Lanarkshire",
    "sg:tags":[
        "local",
        "authority"
    ],
    "wof:name":"Carstairs Primary School",
    "wof:placetype":"venue"
},
  "geometry": {"coordinates":[-3.6912889481,55.6926231384],"type":"Point"}
}