{
  "type": "Feature",
  "properties": {
    "addr:full":"Terminal 2 North Moss Lane, Stallingborough Grimsby Lincolnshire DN41 8DD",
    "addr:postcode":"dn41 8dd",
    "addr:street":"North Moss Lane",
    "iso:country":"GB",
    "sg:address":"Terminal 2 North Moss Lane, Stallingborough",
    "sg:city":"Grimsby",
    "sg:classifiers":[
        {
            "category":"Building & Trades",
            "subcategory":"Cleaning & Sanitation",
            "type":"Services"
        }
    ],
    "sg:phone":"+44 1469 574300",
    "sg:postcode":"DN41 8DD",
    "sg:province":"Lincolnshire",
    "sg:tags":[
        "commercial"
    ],
    "wof:name":"Renvac Ltd.",
    "wof:placetype":"venue"
},
  "geometry": {"coordinates":[-0.188119,53.585716],"type":"Point"}
}