{
  "type": "Feature",
  "properties": {
    "iso:country":"GB",
    "sg:address":"6b Wellington Street",
    "sg:city":"Teignmouth",
    "sg:classifiers":[
        {
            "category":"Shopping",
            "subcategory":"Gifts & Souvenirs",
            "type":"Retail Goods"
        }
    ],
    "sg:postcode":"TQ14 8HH",
    "sg:province":"Devon",
    "sg:tags":[
        "shop"
    ],
    "wof:name":"Teignmouth Gifts",
    "wof:placetype":"venue"
},
  "geometry": {"coordinates":[-3.4951100349,50.5463104248],"type":"Point"}
}