{
  "type": "Feature",
  "properties": {
    "iso:country":"GB",
    "sg:address":"100-108 Carrington Business Park",
    "sg:city":"Manchester",
    "sg:classifiers":[
        {
            "category":"Professional",
            "subcategory":"Computer Services",
            "type":"Services"
        }
    ],
    "sg:phone":"+44 161 776 4802",
    "sg:postcode":"M31 4QQ",
    "sg:province":"Cheshire",
    "sg:tags":[
        "system",
        "software"
    ],
    "wof:name":"Computer Design Group Plc",
    "wof:placetype":"venue"
},
  "geometry": {"coordinates":[-2.425879,53.420078],"type":"Point"}
}