{
  "type": "Feature",
  "properties": {
    "iso:country":"GB",
    "sg:address":"2 River Street",
    "sg:city":"Truro",
    "sg:classifiers":[
        {
            "category":"Shopping",
            "subcategory":"Clothing, Apparel, & Fashions",
            "type":"Retail Goods"
        }
    ],
    "sg:phone":"+44 1872 225150",
    "sg:postcode":"TR1 2SQ",
    "sg:province":"Cornwall",
    "sg:tags":[
        "shop"
    ],
    "wof:name":"Harvey Rothschild Clothing",
    "wof:placetype":"venue"
},
  "geometry": {"coordinates":[-5.053449,50.263168],"type":"Point"}
}