{
  "type": "Feature",
  "properties": {
    "iso:country":"GB",
    "sg:address":"32 Station Road, Queensferry",
    "sg:city":"Deeside",
    "sg:classifiers":[
        {
            "category":"Professional",
            "subcategory":"Advertising",
            "type":"Services"
        }
    ],
    "sg:postcode":"CH5 1SU",
    "sg:province":"Flintshire",
    "sg:tags":[
        "agency"
    ],
    "wof:name":"Farinovelli Internationale",
    "wof:placetype":"venue"
},
  "geometry": {"coordinates":[-3.022754,53.206646],"type":"Point"}
}