{
  "type": "Feature",
  "properties": {
    "iso:country":"GB",
    "sg:address":"Hungerford Road Surgery Hungerford Rd",
    "sg:city":"Crewe",
    "sg:classifiers":[
        {
            "category":"Health Services",
            "subcategory":"Doctor",
            "type":"Services"
        }
    ],
    "sg:phone":"+44 1270 582589",
    "sg:postcode":"CW1 1EQ",
    "sg:province":"Cheshire",
    "sg:tags":[
        "practitioners"
    ],
    "wof:name":"Wilson, M",
    "wof:placetype":"venue"
},
  "geometry": {"coordinates":[-2.446105,53.100578],"type":"Point"}
}