{
  "type": "Feature",
  "properties": {
    "addr:full":"Ty Canol Farm, Sun Bank Llangollen Denbighshire LL20 7UL",
    "addr:postcode":"ll20 7ul",
    "addr:street":"Ty Canol",
    "iso:country":"GB",
    "sg:address":"Ty Canol Farm, Sun Bank",
    "sg:city":"Llangollen",
    "sg:classifiers":[
        {
            "category":"Manufacturing",
            "subcategory":"Wood Products",
            "type":"Manufacturing & Wholesale Goods"
        }
    ],
    "sg:phone":"+44 1978 860392",
    "sg:postcode":"LL20 7UL",
    "sg:province":"Denbighshire",
    "sg:tags":[
        "maker",
        "cabinet"
    ],
    "wof:name":"Ian Ashcroft",
    "wof:placetype":"venue"
},
  "geometry": {"coordinates":[-3.1702270508,52.9689025879],"type":"Point"}
}