{
  "type": "Feature",
  "properties": {
    "addr:full":"2 Balgeddie Clo, Balgeddie Way Glenrothes Fife KY6 3QA",
    "addr:housenumber":"2",
    "addr:postcode":"ky6 3qa",
    "addr:street":"Balgeddie Clo Balgeddie Way",
    "iso:country":"GB",
    "sg:address":"2 Balgeddie Clo, Balgeddie Way",
    "sg:city":"Glenrothes",
    "sg:classifiers":[
        {
            "category":"Retail",
            "subcategory":"Driving School",
            "type":"Services"
        }
    ],
    "sg:postcode":"KY6 3QA",
    "sg:province":"Fife",
    "wof:name":"D R M Driver Training Centre",
    "wof:placetype":"venue"
},
  "geometry": {"coordinates":[-3.1962521076,56.2125473022],"type":"Point"}
}