{
  "type": "Feature",
  "properties": {
    "iso:country":"GB",
    "sg:address":"3 Banks Court",
    "sg:city":"Blaydon On Tyne",
    "sg:classifiers":[
        {
            "category":"Food & Beverages",
            "subcategory":"Meat & Fish",
            "type":"Retail Goods"
        }
    ],
    "sg:phone":"+44 191 414 0774",
    "sg:postcode":"NE21 5NH",
    "sg:province":"Tyne and Wear",
    "sg:tags":[
        "merchant"
    ],
    "wof:name":"Tyne Valley Ltd",
    "wof:placetype":"venue"
},
  "geometry": {"coordinates":[-1.683142,54.946735],"type":"Point"}
}