{
  "type": "Feature",
  "properties": {
    "iso:country":"GB",
    "sg:address":"65-67 Long Street",
    "sg:city":"Atherstone",
    "sg:classifiers":[
        {
            "category":"Home & Garden",
            "subcategory":"Household Appliances",
            "type":"Retail Goods"
        }
    ],
    "sg:phone":"+44 1827 716222",
    "sg:postcode":"CV9 1AZ",
    "sg:province":"Leicestershire",
    "sg:tags":[
        "electrical",
        "domestic"
    ],
    "wof:name":"Foster & Swain Electrical Ltd.",
    "wof:placetype":"venue"
},
  "geometry": {"coordinates":[-1.5482590199,52.5776824951],"type":"Point"}
}