{
  "type": "Feature",
  "properties": {
    "iso:country":"GB",
    "sg:address":"174 Bridge Road, Sarisbury Grn",
    "sg:city":"Southampton",
    "sg:classifiers":[
        {
            "category":"Home & Garden",
            "subcategory":"Building Materials",
            "type":"Retail Goods"
        }
    ],
    "sg:phone":"+44 1489 583573",
    "sg:postcode":"SO31 7EH",
    "sg:province":"Hampshire",
    "sg:tags":[
        "insulation",
        "installers"
    ],
    "wof:name":"Sovereign Insulation Services Ltd.",
    "wof:placetype":"venue"
},
  "geometry": {"coordinates":[-1.2880619764,50.8763160706],"type":"Point"}
}