{
  "type": "Feature",
  "properties": {
    "addr:full":"Alexandra Street, Farnworth Bolton Lancashire BL4 9JT",
    "addr:postcode":"bl4 9jt",
    "addr:street":"Alexandra Street",
    "iso:country":"GB",
    "sg:address":"Alexandra Street, Farnworth",
    "sg:city":"Bolton",
    "sg:classifiers":[
        {
            "category":"Education",
            "subcategory":"School",
            "type":"Public Place"
        },
        {
            "category":"Government",
            "subcategory":"Office",
            "type":"Public Place"
        }
    ],
    "sg:phone":"+44 1204 571554",
    "sg:postcode":"BL4 9JT",
    "sg:province":"Lancashire",
    "sg:tags":[
        "local",
        "authority"
    ],
    "wof:name":"St Peter C of E Primary School",
    "wof:placetype":"venue"
},
  "geometry": {"coordinates":[-2.3954889774,53.5431365967],"type":"Point"}
}