{
  "type": "Feature",
  "properties": {
    "addr:full":"Langdyke Farm, Carrutherstown Road Dumfries Dumfries and Galloway DG1 4JX",
    "addr:postcode":"dg1 4jx",
    "addr:street":"Carrutherstown Road",
    "iso:country":"GB",
    "sg:address":"Langdyke Farm, Carrutherstown Road",
    "sg:city":"Dumfries",
    "sg:classifiers":[
        {
            "category":"Banks & Credit Unions",
            "subcategory":"Investment Brokerage",
            "type":"Services"
        }
    ],
    "sg:postcode":"DG1 4JX",
    "sg:province":"Dumfries and Galloway",
    "sg:tags":[
        "contractor"
    ],
    "wof:name":"Gavin Brown & Sons",
    "wof:placetype":"venue"
},
  "geometry": {"coordinates":[-3.406149,55.033615],"type":"Point"}
}