{
  "type": "Feature",
  "properties": {
    "addr:full":"Unit G1, Narvik Way North Shields Tyne and Wear NE29 7XJ",
    "addr:postcode":"ne29 7xj",
    "addr:street":"Narvik Way",
    "iso:country":"GB",
    "sg:address":"Unit G1, Narvik Way",
    "sg:city":"North Shields",
    "sg:classifiers":[
        {
            "category":"Home & Garden",
            "subcategory":"Building Materials",
            "type":"Retail Goods"
        },
        {
            "category":"Organizations",
            "subcategory":"Community Association",
            "type":"Services"
        }
    ],
    "sg:phone":"+44 191 257 5566",
    "sg:postcode":"NE29 7XJ",
    "sg:province":"Tyne and Wear",
    "sg:tags":[
        "product",
        "based",
        "frame",
        "pvc",
        "window",
        "supplier",
        "manufacturer"
    ],
    "wof:name":"Gofor Trade Windows Ltd",
    "wof:placetype":"venue"
},
  "geometry": {"coordinates":[-1.490614,55.007286],"type":"Point"}
}