{
  "type": "Feature",
  "properties": {
    "addr:full":"69-73, James Road Camberley Berkshire GU15 2RH",
    "addr:housenumber":"69-73",
    "addr:postcode":"gu15 2rh",
    "addr:street":"James Road",
    "iso:country":"GB",
    "sg:address":"69-73, James Road",
    "sg:city":"Camberley",
    "sg:classifiers":[
        {
            "category":"Building & Trades",
            "subcategory":"Construction",
            "type":"Services"
        }
    ],
    "sg:phone":"+44 1276 678001",
    "sg:postcode":"GU15 2RH",
    "sg:province":"Berkshire",
    "sg:tags":[
        "concrete"
    ],
    "wof:name":"BUILDSPAN",
    "wof:placetype":"venue"
},
  "geometry": {"coordinates":[-0.752702,51.319817],"type":"Point"}
}