{
  "type": "Feature",
  "properties": {
    "iso:country":"GB",
    "sg:address":"14 Swanstand",
    "sg:city":"Letchworth",
    "sg:classifiers":[
        {
            "category":"Manufacturing",
            "subcategory":"Tools & Machinery",
            "type":"Manufacturing & Wholesale Goods"
        }
    ],
    "sg:postcode":"SG6 2QJ",
    "sg:province":"Hertfordshire",
    "wof:name":"Garden City Tools",
    "wof:placetype":"venue"
},
  "geometry": {"coordinates":[-0.201530993,51.9696426392],"type":"Point"}
}