{
  "type": "Feature",
  "properties": {
    "addr:full":"18 Guildhall Shopping Centre, Queen Street Exeter Devon EX4 3HW",
    "addr:housenumber":"18",
    "addr:postcode":"ex4 3hw",
    "addr:street":"Guildhall Shopping Centre Queen Street",
    "iso:country":"GB",
    "sg:address":"18 Guildhall Shopping Centre, Queen Street",
    "sg:city":"Exeter",
    "sg:classifiers":[
        {
            "category":"Food & Beverages",
            "subcategory":"Bakery",
            "type":"Retail Goods"
        }
    ],
    "sg:phone":"+44 1392 436502",
    "sg:postcode":"EX4 3HW",
    "sg:province":"Devon",
    "sg:tags":[
        "baker"
    ],
    "wof:name":"The Cornish Oggie Oggie Pasty Co. Ltd.",
    "wof:placetype":"venue"
},
  "geometry": {"coordinates":[-3.5322790146,50.7231292725],"type":"Point"}
}