{
  "type": "Feature",
  "properties": {
    "iso:country":"GB",
    "sg:address":"10 Briarwood",
    "sg:city":"Wilmslow",
    "sg:classifiers":[
        {
            "category":"Parking",
            "type":"Transportation"
        }
    ],
    "sg:phone":"+44 1625 539140",
    "sg:postcode":"SK9 2DH",
    "sg:province":"Cheshire",
    "sg:tags":[
        "car",
        "valet"
    ],
    "wof:name":"V.i.p. Valeting",
    "wof:placetype":"venue"
},
  "geometry": {"coordinates":[-2.222247,53.329159],"type":"Point"}
}