{
  "type": "Feature",
  "properties": {
    "addr:full":"7-8 Horton Place, Bradshaw Halifax West Yorkshire HX2 9UY",
    "addr:housenumber":"7-8",
    "addr:postcode":"hx2 9uy",
    "addr:street":"Horton Place",
    "iso:country":"GB",
    "sg:address":"7-8 Horton Place, Bradshaw",
    "sg:city":"Halifax",
    "sg:classifiers":[
        {
            "category":"Government",
            "subcategory":"Post Office",
            "type":"Public Place"
        }
    ],
    "sg:postcode":"HX2 9UY",
    "sg:province":"West Yorkshire",
    "wof:name":"Bradshaw Sub-Post Office",
    "wof:placetype":"venue"
},
  "geometry": {"coordinates":[-1.8854689598,53.7656860352],"type":"Point"}
}