{
  "type": "Feature",
  "properties": {
    "addr:full":"Wern Rd Goodwick Pembrokeshire SA64 0AA",
    "addr:postcode":"sa64 0aa",
    "addr:street":"Wern Rd",
    "iso:country":"GB",
    "sg:address":"Wern Rd",
    "sg:city":"Goodwick",
    "sg:classifiers":[
        {
            "category":"Arena",
            "subcategory":"Sports Club",
            "type":"Entertainment"
        }
    ],
    "sg:phone":"+44 1348 873071",
    "sg:postcode":"SA64 0AA",
    "sg:province":"Pembrokeshire",
    "wof:name":"Fishguard & Goodwick Sports Club",
    "wof:placetype":"venue"
},
  "geometry": {"coordinates":[-4.9954791069,52.0023422241],"type":"Point"}
}