{
  "type": "Feature",
  "properties": {
    "iso:country":"GB",
    "sg:address":"Unit 5, 1 Davy Road",
    "sg:city":"Clacton-on-sea",
    "sg:classifiers":[
        {
            "category":"Arts & Performance",
            "subcategory":"Music",
            "type":"Entertainment"
        }
    ],
    "sg:phone":"+44 1255 436986",
    "sg:postcode":"CO15 4XD",
    "sg:province":"Essex",
    "sg:tags":[
        "mobile",
        "disco"
    ],
    "wof:name":"Classic",
    "wof:placetype":"venue"
},
  "geometry": {"coordinates":[1.1763850451,51.8168792725],"type":"Point"}
}