{
  "type": "Feature",
  "properties": {
    "addr:full":"24-32 North Mall, Lower Edmonton London Greater London N9 0EZ",
    "addr:housenumber":"24-32",
    "addr:postcode":"n9 0ez",
    "addr:street":"North Mall",
    "iso:country":"GB",
    "sg:address":"24-32 North Mall, Lower Edmonton",
    "sg:city":"London",
    "sg:classifiers":[
        {
            "category":"Shopping",
            "subcategory":"Department Store",
            "type":"Retail Goods"
        }
    ],
    "sg:phone":"+44 20 8807 2048",
    "sg:postcode":"N9 0EZ",
    "sg:province":"Greater London",
    "sg:tags":[
        "departmental"
    ],
    "wof:name":"Woolworths plc",
    "wof:placetype":"venue"
},
  "geometry": {"coordinates":[-0.055193,51.626068],"type":"Point"}
}