{
  "type": "Feature",
  "properties": {
    "addr:full":"37 Regal Drive, Soham Ely Cambridgeshire CB7 5BE",
    "addr:housenumber":"37",
    "addr:postcode":"cb7 5be",
    "addr:street":"Regal Drive",
    "iso:country":"GB",
    "sg:address":"37 Regal Drive, Soham",
    "sg:city":"Ely",
    "sg:classifiers":[
        {
            "category":"Home & Garden",
            "subcategory":"Carpets & Floor Coverings",
            "type":"Retail Goods"
        }
    ],
    "sg:phone":"+44 1353 624677",
    "sg:postcode":"CB7 5BE",
    "sg:province":"Cambridgeshire",
    "sg:tags":[
        "rubber",
        "plastic"
    ],
    "wof:name":"G S E Lining Technology Ltd.",
    "wof:placetype":"venue"
},
  "geometry": {"coordinates":[0.350546,52.326214],"type":"Point"}
}