{
  "type": "Feature",
  "properties": {
    "addr:full":"59 Loampit Hill London Greater London SE13 7SZ",
    "addr:housenumber":"59",
    "addr:postcode":"se13 7sz",
    "addr:street":"Loampit Hill",
    "iso:country":"GB",
    "sg:address":"59 Loampit Hill",
    "sg:city":"London",
    "sg:classifiers":[
        {
            "category":"Shopping",
            "subcategory":"Stationery & Office Supplies",
            "type":"Retail Goods"
        },
        {
            "category":"Government",
            "subcategory":"Post Office",
            "type":"Public Place"
        }
    ],
    "sg:phone":"+44 20 8692 6824",
    "sg:postcode":"SE13 7SZ",
    "sg:province":"Greater London",
    "wof:name":"Lewisham St John Post Office",
    "wof:placetype":"venue"
},
  "geometry": {"coordinates":[-0.023026,51.4674],"type":"Point"}
}