{
  "type": "Feature",
  "properties": {
    "addr:full":"Unit 7 Ely Enterprise Centre, Caldicot Road, Ely Cardiff Cardiff CF5 5EH",
    "addr:housenumber":"unit 7;enterprise centre",
    "addr:postcode":"cf5 5eh",
    "addr:street":"Caldicot Road",
    "iso:country":"GB",
    "sg:address":"Unit 7 Ely Enterprise Centre, Caldicot Road, Ely",
    "sg:city":"Cardiff",
    "sg:classifiers":[
        {
            "category":"Professional",
            "subcategory":"Business Services",
            "type":"Services"
        }
    ],
    "sg:phone":"+44 29 2059 9111",
    "sg:postcode":"CF5 5EH",
    "sg:province":"Cardiff",
    "sg:tags":[
        "import",
        "export",
        "agent"
    ],
    "wof:name":"Off the Mark Ltd.",
    "wof:placetype":"venue"
},
  "geometry": {"coordinates":[-3.245,51.473438],"type":"Point"}
}