{
  "type": "Feature",
  "properties": {
    "addr:full":"Stuart House, The Back Chepstow Gloucestershire NP16 5HH",
    "addr:housenumber":"the",
    "addr:postcode":"np16 5hh",
    "iso:country":"GB",
    "sg:address":"Stuart House, The Back",
    "sg:city":"Chepstow",
    "sg:classifiers":[
        {
            "category":"Building & Trades",
            "subcategory":"Construction",
            "type":"Services"
        }
    ],
    "sg:phone":"+44 1291 626323",
    "sg:postcode":"NP16 5HH",
    "sg:province":"Gloucestershire",
    "sg:tags":[
        "roofing"
    ],
    "wof:name":"Hightex Ltd.",
    "wof:placetype":"venue"
},
  "geometry": {"coordinates":[-2.6697490215,51.6448707581],"type":"Point"}
}