{
  "type": "Feature",
  "properties": {
    "addr:full":"Thornfield Court, Bruntcliffe Road, Morley Leeds West Yorkshire LS27 0QG",
    "addr:postcode":"ls27 0qg",
    "addr:street":"Thornfield;Bruntcliffe Road",
    "iso:country":"GB",
    "sg:address":"Thornfield Court, Bruntcliffe Road, Morley",
    "sg:city":"Leeds",
    "sg:classifiers":[
        {
            "category":"Communications",
            "subcategory":"Film & Video Production",
            "type":"Services"
        }
    ],
    "sg:phone":"+44 113 238 3000",
    "sg:postcode":"LS27 0QG",
    "sg:province":"West Yorkshire",
    "sg:tags":[
        "tv",
        "studio"
    ],
    "wof:name":"Inside-Out Branding Ltd.",
    "wof:placetype":"venue"
},
  "geometry": {"coordinates":[-1.6232589483,53.7442703247],"type":"Point"}
}