{
  "type": "Feature",
  "properties": {
    "addr:full":"85 Skelcher Road, Shirley Solihull West Midlands B90 2EY",
    "addr:housenumber":"85",
    "addr:postcode":"b90 2ey",
    "addr:street":"Skelcher Road",
    "iso:country":"GB",
    "sg:address":"85 Skelcher Road, Shirley",
    "sg:city":"Solihull",
    "sg:classifiers":[
        {
            "category":"Professional",
            "subcategory":"Accounting & Tax Preparation",
            "type":"Services"
        }
    ],
    "sg:phone":"+44 121 733 1167",
    "sg:postcode":"B90 2EY",
    "sg:province":"West Midlands",
    "sg:tags":[
        "accountant"
    ],
    "wof:name":"Hancox & Co",
    "wof:placetype":"venue"
},
  "geometry": {"coordinates":[-1.839779,52.41399],"type":"Point"}
}