{
  "type": "Feature",
  "properties": {
    "iso:country":"GB",
    "sg:address":"22 Barns Close, Kirby Muxloe",
    "sg:city":"Leicester",
    "sg:classifiers":[
        {
            "category":"Building & Trades",
            "subcategory":"Plumbing",
            "type":"Services"
        }
    ],
    "sg:phone":"+44 116 238 7555",
    "sg:postcode":"LE9 2BA",
    "sg:province":"Leicestershire",
    "sg:tags":[
        "heating"
    ],
    "wof:name":"P.C Bates",
    "wof:placetype":"venue"
},
  "geometry": {"coordinates":[-1.241839,52.635609],"type":"Point"}
}