{
  "type": "Feature",
  "properties": {
    "addr:full":"40a Market St, Kidsgrove Stoke-on-trent Cheshire ST7 4AB",
    "addr:housenumber":"40a",
    "addr:postcode":"st7 4ab",
    "addr:street":"Market St",
    "iso:country":"GB",
    "sg:address":"40a Market St, Kidsgrove",
    "sg:city":"Stoke-on-trent",
    "sg:classifiers":[
        {
            "category":"Shopping",
            "subcategory":"Gifts & Souvenirs",
            "type":"Retail Goods"
        }
    ],
    "sg:phone":"+44 1782 331084",
    "sg:postcode":"ST7 4AB",
    "sg:province":"Cheshire",
    "sg:tags":[
        "poster",
        "card"
    ],
    "wof:name":"Special Days Ltd",
    "wof:placetype":"venue"
},
  "geometry": {"coordinates":[-2.238611,53.087002],"type":"Point"}
}