{
  "type": "Feature",
  "properties": {
    "iso:country":"GB",
    "sg:address":"18-20 Windsor Street",
    "sg:city":"Uxbridge",
    "sg:classifiers":[
        {
            "category":"Sports & Exercise",
            "subcategory":"Golf",
            "type":"Entertainment"
        }
    ],
    "sg:postcode":"UB8 1AB",
    "sg:province":"Buckinghamshire",
    "sg:tags":[
        "equipment"
    ],
    "wof:name":"U S A Golf Ltd.",
    "wof:placetype":"venue"
},
  "geometry": {"coordinates":[-0.4801209867,51.5453834534],"type":"Point"}
}