{
  "type": "Feature",
  "properties": {
    "iso:country":"GB",
    "sg:address":"25 King St",
    "sg:city":"Worthing",
    "sg:classifiers":[
        {
            "category":"Health Services",
            "subcategory":"Health Practitioner",
            "type":"Services"
        }
    ],
    "sg:phone":"+44 1903 206575",
    "sg:postcode":"BN14 7BN",
    "sg:province":"West Sussex",
    "sg:tags":[
        "homoeopathic"
    ],
    "wof:name":"Susan J Merriott",
    "wof:placetype":"venue"
},
  "geometry": {"coordinates":[-0.375399,50.822796],"type":"Point"}
}