{
  "type": "Feature",
  "properties": {
    "addr:full":"Daisy Nook House, Bamburgh Drive Ashton-under-lyne Greater Manchester OL6 7DD",
    "addr:postcode":"ashton-under-lyne;ol6 7dd",
    "addr:street":"Bamburgh Drive",
    "iso:country":"GB",
    "sg:address":"Daisy Nook House, Bamburgh Drive",
    "sg:city":"Ashton-under-lyne",
    "sg:classifiers":[
        {
            "category":"Health Services",
            "subcategory":"Nursing And Care Facility",
            "type":"Services"
        },
        {
            "category":"Social Services",
            "subcategory":"Retirement Home",
            "type":"Services"
        }
    ],
    "sg:postcode":"OL6 7DD",
    "sg:province":"Greater Manchester",
    "sg:tags":[
        "rest"
    ],
    "wof:name":"Daisy Nook Home",
    "wof:placetype":"venue"
},
  "geometry": {"coordinates":[-2.115438,53.497314],"type":"Point"}
}