{
  "type": "Feature",
  "properties": {
    "addr:full":"Unit 56 South Nelson Industrial Estate Cramlington Northumberland NE23 1WF",
    "addr:housenumber":"unit 56",
    "addr:postcode":"ne23 1wf",
    "addr:street":"South Nelson Industrial Estate;Northumberland",
    "iso:country":"GB",
    "sg:address":"Unit 56 South Nelson Industrial Estate",
    "sg:city":"Cramlington",
    "sg:classifiers":[
        {
            "category":"Banks & Credit Unions",
            "subcategory":"Investment Brokerage",
            "type":"Services"
        },
        {
            "category":"Home & Garden",
            "subcategory":"Hardware",
            "type":"Retail Goods"
        }
    ],
    "sg:phone":"+44 1670 590300",
    "sg:postcode":"NE23 1WF",
    "sg:province":"Northumberland",
    "sg:tags":[
        "equipment",
        "sale",
        "generator",
        "welding"
    ],
    "wof:name":"Mosa Welding Products",
    "wof:placetype":"venue"
},
  "geometry": {"coordinates":[-1.604249,55.094452],"type":"Point"}
}