{
  "type": "Feature",
  "properties": {
    "iso:country":"GB",
    "sg:address":"117 Plumstead High Street",
    "sg:city":"London",
    "sg:classifiers":[
        {
            "category":"Personal",
            "subcategory":"Beauty Salon",
            "type":"Services"
        }
    ],
    "sg:phone":"+44 20 8317 1721",
    "sg:postcode":"SE18 1SE",
    "sg:province":"Greater London",
    "wof:name":"Ardanz Health & Beauty",
    "wof:placetype":"venue"
},
  "geometry": {"coordinates":[0.09233,51.487587],"type":"Point"}
}