{
  "type": "Feature",
  "properties": {
    "addr:full":"19 Wilton Avenue, Hampden Park Eastbourne East Sussex BN22 9HS",
    "addr:housenumber":"19",
    "addr:postcode":"bn22 9hs",
    "addr:street":"Wilton Avenue",
    "iso:country":"GB",
    "sg:address":"19 Wilton Avenue, Hampden Park",
    "sg:city":"Eastbourne",
    "sg:classifiers":[
        {
            "category":"Manufacturing",
            "subcategory":"Petroleum Products",
            "type":"Manufacturing & Wholesale Goods"
        }
    ],
    "sg:phone":"+44 1323 509127",
    "sg:postcode":"BN22 9HS",
    "sg:province":"East Sussex",
    "sg:tags":[
        "double",
        "glazing"
    ],
    "wof:name":"Eternal Windows",
    "wof:placetype":"venue"
},
  "geometry": {"coordinates":[0.28085199,50.8027229309],"type":"Point"}
}