{
  "type": "Feature",
  "properties": {
    "iso:country":"GB",
    "sg:address":"Denmark Villas, Station App",
    "sg:city":"Hove",
    "sg:classifiers":[
        {
            "category":"Autos & Motor Vehicles",
            "subcategory":"Fuel & Gas Station",
            "type":"Retail Goods"
        }
    ],
    "sg:phone":"+44 1273 733652",
    "sg:postcode":"BN3 3TJ",
    "sg:province":"East Sussex",
    "sg:tags":[
        "hr",
        "petrol"
    ],
    "wof:name":"Hove Service Station",
    "wof:placetype":"venue"
},
  "geometry": {"coordinates":[-0.170984,50.831036],"type":"Point"}
}