{
  "type": "Feature",
  "properties": {
    "addr:full":"37 Red Lane Coventry Warwickshire CV6 5EE",
    "addr:housenumber":"37",
    "addr:postcode":"cv6 5ee",
    "addr:street":"Red Lane",
    "iso:country":"GB",
    "sg:address":"37 Red Lane",
    "sg:city":"Coventry",
    "sg:classifiers":[
        {
            "category":"Building & Trades",
            "subcategory":"Plumbing",
            "type":"Services"
        }
    ],
    "sg:phone":"+44 24 7668 0200",
    "sg:postcode":"CV6 5EE",
    "sg:province":"Warwickshire",
    "sg:tags":[
        "merchant",
        "plumbers'"
    ],
    "wof:name":"Gilbert & Shropshire Ltd.",
    "wof:placetype":"venue"
},
  "geometry": {"coordinates":[-1.493739,52.420433],"type":"Point"}
}