{
  "type": "Feature",
  "properties": {
    "iso:country":"GB",
    "sg:address":"26-28 High Street, Silverdale",
    "sg:city":"Newcastle",
    "sg:classifiers":[
        {
            "category":"Autos & Motor Vehicles",
            "subcategory":"Automobile Sales",
            "type":"Retail Goods"
        }
    ],
    "sg:phone":"+44 1782 631960",
    "sg:postcode":"ST5 6NG",
    "sg:province":"Staffordshire",
    "sg:tags":[
        "car"
    ],
    "wof:name":"Village Car Sales",
    "wof:placetype":"venue"
},
  "geometry": {"coordinates":[-2.264444,53.015144],"type":"Point"}
}