{
  "type": "Feature",
  "properties": {
    "iso:country":"GB",
    "sg:address":"38 George Rd",
    "sg:city":"Birmingham",
    "sg:classifiers":[
        {
            "category":"Government",
            "subcategory":"Office",
            "type":"Public Place"
        }
    ],
    "sg:phone":"+44 121 455 7515",
    "sg:postcode":"B15 1PL",
    "sg:province":"West Midlands",
    "sg:tags":[
        "central"
    ],
    "wof:name":"P A C E",
    "wof:placetype":"venue"
},
  "geometry": {"coordinates":[-1.9145740271,52.4704246521],"type":"Point"}
}