{
  "type": "Feature",
  "properties": {
    "addr:full":"1 Port Henry Pier Peterhead Aberdeenshire AB42 1ZY",
    "addr:housenumber":"1",
    "addr:postcode":"ab42 1zy",
    "addr:street":"Port",
    "iso:country":"GB",
    "sg:address":"1 Port Henry Pier",
    "sg:city":"Peterhead",
    "sg:classifiers":[
        {
            "category":"Food & Beverages",
            "subcategory":"Farmers Market",
            "type":"Retail Goods"
        }
    ],
    "sg:phone":"+44 1779 479402",
    "sg:postcode":"AB42 1ZY",
    "sg:province":"Aberdeenshire",
    "sg:tags":[
        "consultant",
        "fisheries'"
    ],
    "wof:name":"Scot-Caught Sea Fishing Ltd.",
    "wof:placetype":"venue"
},
  "geometry": {"coordinates":[-1.7746249437,57.5074157715],"type":"Point"}
}