{
  "type": "Feature",
  "properties": {
    "iso:country":"GB",
    "sg:address":"165a Toller Lane",
    "sg:city":"Bradford",
    "sg:classifiers":[
        {
            "category":"Retail",
            "subcategory":"Auto Rental",
            "type":"Services"
        }
    ],
    "sg:phone":"+44 1274 545700",
    "sg:postcode":"BD8 9HW",
    "sg:province":"West Yorkshire",
    "sg:tags":[
        "car",
        "hire",
        "truck"
    ],
    "wof:name":"Custom Fleet Ltd.",
    "wof:placetype":"venue"
},
  "geometry": {"coordinates":[-1.786108,53.806107],"type":"Point"}
}