{
  "type": "Feature",
  "properties": {
    "addr:full":"18a North Street Leatherhead Surrey KT22 7AW",
    "addr:housenumber":"18a",
    "addr:postcode":"kt22 7aw",
    "addr:street":"North Street",
    "iso:country":"GB",
    "sg:address":"18a North Street",
    "sg:city":"Leatherhead",
    "sg:classifiers":[
        {
            "category":"Professional",
            "subcategory":"Business Services",
            "type":"Services"
        }
    ],
    "sg:phone":"+44 1372 224100",
    "sg:postcode":"KT22 7AW",
    "sg:province":"Surrey",
    "sg:tags":[
        "distribution"
    ],
    "wof:name":"M B S Group",
    "wof:placetype":"venue"
},
  "geometry": {"coordinates":[-0.329925,51.295654],"type":"Point"}
}