{
  "type": "Feature",
  "properties": {
    "iso:country":"GB",
    "sg:address":"2-3 Taylor Buildings",
    "sg:city":"Blackburn",
    "sg:classifiers":[
        {
            "category":"Shopping",
            "subcategory":"News",
            "type":"Retail Goods"
        }
    ],
    "sg:phone":"+44 1254 247627",
    "sg:postcode":"BB6 8DB",
    "sg:province":"Lancashire",
    "sg:tags":[
        "newsagent"
    ],
    "wof:name":"L Adams & S Mather",
    "wof:placetype":"venue"
},
  "geometry": {"coordinates":[-2.494813,53.723866],"type":"Point"}
}