{
  "type": "Feature",
  "properties": {
    "addr:full":"60 Falloch Rd, Milngavie Glasgow East Dunbartonshire G62 7RR",
    "addr:housenumber":"60",
    "addr:postcode":"g62 7rr",
    "addr:street":"Falloch Rd",
    "iso:country":"GB",
    "sg:address":"60 Falloch Rd, Milngavie",
    "sg:city":"Glasgow",
    "sg:classifiers":[
        {
            "category":"Manufacturing",
            "subcategory":"Building Materials",
            "type":"Manufacturing & Wholesale Goods"
        }
    ],
    "sg:phone":"+44 141 956 3436",
    "sg:postcode":"G62 7RR",
    "sg:province":"East Dunbartonshire",
    "sg:tags":[
        "adhesive",
        "tape"
    ],
    "wof:name":"A Fraser",
    "wof:placetype":"venue"
},
  "geometry": {"coordinates":[-4.340057,55.945747],"type":"Point"}
}