{
  "type": "Feature",
  "properties": {
    "addr:full":"5 Northampton Road Enfield Greater London EN3 7UL",
    "addr:housenumber":"5",
    "addr:postcode":"en3 7ul",
    "addr:street":"Northampton Road",
    "iso:country":"GB",
    "sg:address":"5 Northampton Road",
    "sg:city":"Enfield",
    "sg:classifiers":[
        {
            "category":"Food & Beverages",
            "subcategory":"Bakery",
            "type":"Retail Goods"
        }
    ],
    "sg:phone":"+44 20 8805 3066",
    "sg:postcode":"EN3 7UL",
    "sg:province":"Greater London",
    "sg:tags":[
        "baker"
    ],
    "wof:name":"Greggs",
    "wof:placetype":"venue"
},
  "geometry": {"coordinates":[-0.0303390007,51.6463317871],"type":"Point"}
}