{
  "type": "Feature",
  "properties": {
    "iso:country":"GB",
    "sg:address":"No 9merthyr Industrial Park",
    "sg:city":"Merthyr Tydfil",
    "sg:classifiers":[
        {
            "category":"Shopping",
            "subcategory":"Computers & Home Electronics",
            "type":"Retail Goods"
        }
    ],
    "sg:postcode":"CF48 4DR",
    "sg:province":"Caerphilly",
    "sg:tags":[
        "electrical"
    ],
    "wof:name":"City Electrical Factors Ltd.",
    "wof:placetype":"venue"
},
  "geometry": {"coordinates":[-3.3555700779,51.7198982239],"type":"Point"}
}