{
  "type": "Feature",
  "properties": {
    "addr:full":"D Squadran, 243 The Wessex Field Hospital Portsmouth Hampshire PO6 2SR",
    "addr:housenumber":"243",
    "addr:postcode":"po6 2sr",
    "addr:street":"The Wessex",
    "iso:country":"GB",
    "sg:address":"D Squadran, 243 The Wessex Field Hospital",
    "sg:city":"Portsmouth",
    "sg:classifiers":[
        {
            "category":"Military Area",
            "subcategory":"Coast Guard Base",
            "type":"Public Place"
        },
        {
            "category":"Government",
            "subcategory":"Office",
            "type":"Public Place"
        }
    ],
    "sg:phone":"+44 23 9237 5456",
    "sg:postcode":"PO6 2SR",
    "sg:province":"Hampshire",
    "sg:tags":[
        "force",
        "armed",
        "reserve"
    ],
    "wof:name":"Territorial Army",
    "wof:placetype":"venue"
},
  "geometry": {"coordinates":[-1.06702,50.837688],"type":"Point"}
}