{
  "type": "Feature",
  "properties": {
    "addr:full":"93 Mitchell Street Glasgow Glasgow City G1 3LN",
    "addr:housenumber":"93",
    "addr:postcode":"g1 3ln",
    "addr:street":"Mitchell Street",
    "iso:country":"GB",
    "sg:address":"93 Mitchell Street",
    "sg:city":"Glasgow",
    "sg:classifiers":[
        {
            "category":"Food & Beverages",
            "subcategory":"Liquor & Beverages",
            "type":"Retail Goods"
        }
    ],
    "sg:phone":"+44 141 221 4760",
    "sg:postcode":"G1 3LN",
    "sg:province":"Glasgow City",
    "sg:tags":[
        "beer",
        "wine",
        "spirit",
        "wines"
    ],
    "sg:website":"http://www.oddbins.com",
    "wof:name":"Oddbins Ltd",
    "wof:placetype":"venue"
},
  "geometry": {"coordinates":[-4.2558469772,55.8602752686],"type":"Point"}
}