{
  "type": "Feature",
  "properties": {
    "iso:country":"GB",
    "sg:address":"Usk Road",
    "sg:city":"Bargoed",
    "sg:classifiers":[
        {
            "category":"Education",
            "subcategory":"School",
            "type":"Public Place"
        }
    ],
    "sg:phone":"+44 1443 875513",
    "sg:postcode":"CF81 8RJ",
    "sg:province":"Caerphilly",
    "sg:tags":[
        "local",
        "authority"
    ],
    "wof:name":"Bargoed Infant School",
    "wof:placetype":"venue"
},
  "geometry": {"coordinates":[-3.232739,51.693653],"type":"Point"}
}