{
  "type": "Feature",
  "properties": {
    "iso:country":"GB",
    "sg:address":"5a West St, Wiveliscombe",
    "sg:city":"Taunton",
    "sg:classifiers":[
        {
            "category":"Social Services",
            "subcategory":"Retirement Home",
            "type":"Services"
        }
    ],
    "sg:phone":"+44 1984 623637",
    "sg:postcode":"TA4 2JP",
    "sg:province":"Devon",
    "sg:tags":[
        "residential",
        "care"
    ],
    "wof:name":"The Croft",
    "wof:placetype":"venue"
},
  "geometry": {"coordinates":[-3.3134961128,51.0422210693],"type":"Point"}
}