{
  "type": "Feature",
  "properties": {
    "iso:country":"GB",
    "sg:address":"Technical Training Centre, Unit G1 Northway Trading Estate",
    "sg:city":"Tewkesbury",
    "sg:classifiers":[
        {
            "category":"Wholesale",
            "subcategory":"Electrical",
            "type":"Manufacturing & Wholesale Goods"
        },
        {
            "category":"Shopping",
            "subcategory":"Computers & Home Electronics",
            "type":"Retail Goods"
        }
    ],
    "sg:phone":"+44 1684 274767",
    "sg:postcode":"GL20 8JH",
    "sg:province":"Gloucestershire",
    "sg:tags":[
        "wholesaler"
    ],
    "wof:name":"Lockwell Lectrics Ltd.",
    "wof:placetype":"venue"
},
  "geometry": {"coordinates":[-2.1038041115,51.9978027344],"type":"Point"}
}