{
  "type": "Feature",
  "properties": {
    "iso:country":"GB",
    "sg:address":"Catering Department",
    "sg:city":"Lancing",
    "sg:classifiers":[
        {
            "category":"Education",
            "subcategory":"School",
            "type":"Public Place"
        }
    ],
    "sg:phone":"+44 1273 452213",
    "sg:postcode":"BN15 0RW",
    "sg:province":"West Sussex",
    "sg:tags":[
        "independent",
        "preparatory"
    ],
    "wof:name":"Lancing College",
    "wof:placetype":"venue"
},
  "geometry": {"coordinates":[-0.318039,50.821899],"type":"Point"}
}