{
  "type": "Feature",
  "properties": {
    "addr:full":"69 High Street Market Harborough Leicestershire LE16 7AF",
    "addr:housenumber":"69",
    "addr:postcode":"le16 7af",
    "addr:street":"High Street",
    "iso:country":"GB",
    "sg:address":"69 High Street",
    "sg:city":"Market Harborough",
    "sg:classifiers":[
        {
            "category":"Shopping",
            "subcategory":"Gifts & Souvenirs",
            "type":"Retail Goods"
        }
    ],
    "sg:phone":"+44 1858 461473",
    "sg:postcode":"LE16 7AF",
    "sg:province":"Leicestershire",
    "sg:tags":[
        "shop"
    ],
    "wof:name":"Chinatown",
    "wof:placetype":"venue"
},
  "geometry": {"coordinates":[-0.9218710065,52.4786682129],"type":"Point"}
}