{
  "type": "Feature",
  "properties": {
    "iso:country":"GB",
    "sg:address":"Stephenson Av",
    "sg:city":"Spalding",
    "sg:classifiers":[
        {
            "category":"Retail",
            "subcategory":"Auto Repair",
            "type":"Services"
        }
    ],
    "sg:phone":"+44 1775 722789",
    "sg:postcode":"PE11 1HH",
    "sg:province":"Lincolnshire",
    "sg:tags":[
        "body",
        "car"
    ],
    "wof:name":"A S Whitaker & Sons",
    "wof:placetype":"venue"
},
  "geometry": {"coordinates":[-0.151488,52.788342],"type":"Point"}
}