{
  "type": "Feature",
  "properties": {
    "addr:full":"1 School Lane Colne Lancashire BB8 7JB",
    "addr:housenumber":"1",
    "addr:postcode":"bb8 7jb",
    "addr:street":"School Lane",
    "iso:country":"GB",
    "sg:address":"1 School Lane",
    "sg:city":"Colne",
    "sg:classifiers":[
        {
            "category":"Government",
            "subcategory":"Post Office",
            "type":"Public Place"
        }
    ],
    "sg:postcode":"BB8 7JB",
    "sg:province":"Lancashire",
    "wof:name":"Bennett,Valerie,",
    "wof:placetype":"venue"
},
  "geometry": {"coordinates":[-2.1193621159,53.8625602722],"type":"Point"}
}