{
  "type": "Feature",
  "properties": {
    "addr:full":"9-10 Pool Valley Brighton East Sussex BN1 1NJ",
    "addr:housenumber":"9-10",
    "addr:postcode":"bn1 1nj",
    "addr:street":"Pool Valley",
    "iso:country":"GB",
    "sg:address":"9-10 Pool Valley",
    "sg:city":"Brighton",
    "sg:classifiers":[
        {
            "category":"Cafe",
            "type":"Food & Drink"
        }
    ],
    "sg:phone":"+44 1273 324367",
    "sg:postcode":"BN1 1NJ",
    "sg:province":"East Sussex",
    "sg:tags":[
        "tea",
        "room"
    ],
    "wof:name":"The Continental Cafe",
    "wof:placetype":"venue"
},
  "geometry": {"coordinates":[-0.1384489983,50.8200302124],"type":"Point"}
}