{
  "type": "Feature",
  "properties": {
    "addr:full":"Walton Stone Staffordshire ST15 0HH",
    "addr:postcode":"st15 0hh",
    "iso:country":"GB",
    "sg:address":"Walton",
    "sg:city":"Stone",
    "sg:classifiers":[
        {
            "category":"Autos & Motor Vehicles",
            "subcategory":"Fuel & Gas Station",
            "type":"Retail Goods"
        }
    ],
    "sg:phone":"+44 1785 812260",
    "sg:postcode":"ST15 0HH",
    "sg:province":"Staffordshire",
    "sg:tags":[
        "hr",
        "petrol"
    ],
    "wof:name":"Shell Stone",
    "wof:placetype":"venue"
},
  "geometry": {"coordinates":[-2.1463649273,52.8968048096],"type":"Point"}
}