{
  "type": "Feature",
  "properties": {
    "iso:country":"GB",
    "sg:address":"Valtone, Old Salisbury Road, Abbotts Ann",
    "sg:city":"Andover",
    "sg:classifiers":[
        {
            "category":"Building & Trades",
            "subcategory":"Construction",
            "type":"Services"
        }
    ],
    "sg:postcode":"SP11 7NH",
    "sg:province":"Hampshire",
    "sg:tags":[
        "builder"
    ],
    "wof:name":"A F Baker Builder",
    "wof:placetype":"venue"
},
  "geometry": {"coordinates":[-1.531108,51.191257],"type":"Point"}
}