{
  "type": "Feature",
  "properties": {
    "addr:full":"Unit 5 Letts Road Northampton Northamptonshire NN4 8HQ",
    "addr:housenumber":"unit 5",
    "addr:postcode":"nn4 8hq",
    "addr:street":"Letts Road",
    "iso:country":"GB",
    "sg:address":"Unit 5 Letts Road",
    "sg:city":"Northampton",
    "sg:classifiers":[
        {
            "category":"Sports & Exercise",
            "subcategory":"Golf",
            "type":"Entertainment"
        }
    ],
    "sg:phone":"+44 1604 768176",
    "sg:postcode":"NN4 8HQ",
    "sg:province":"Northamptonshire",
    "sg:tags":[
        "greeting",
        "card"
    ],
    "wof:name":"B & T Greetings Cards",
    "wof:placetype":"venue"
},
  "geometry": {"coordinates":[-0.9078140259,52.2276191711],"type":"Point"}
}