{
  "type": "Feature",
  "properties": {
    "iso:country":"GB",
    "sg:address":"77 Courtland Avenue",
    "sg:city":"Coventry",
    "sg:classifiers":[
        {
            "category":"Food & Beverages",
            "subcategory":"Supermarket",
            "type":"Retail Goods"
        }
    ],
    "sg:phone":"+44 24 7659 1445",
    "sg:postcode":"CV6 1GU",
    "sg:province":"Warwickshire",
    "wof:name":"Pricelow Supersave",
    "wof:placetype":"venue"
},
  "geometry": {"coordinates":[-1.5382369757,52.420665741],"type":"Point"}
}