{
  "type": "Feature",
  "properties": {
    "iso:country":"GB",
    "sg:address":"Lincoln Road, Fulbeck",
    "sg:city":"Grantham",
    "sg:classifiers":[
        {
            "category":"Cafe",
            "type":"Food & Drink"
        }
    ],
    "sg:postcode":"NG32 3JN",
    "sg:province":"Leicestershire",
    "sg:tags":[
        "tea",
        "room"
    ],
    "wof:name":"Fulbeck Tea Rooms",
    "wof:placetype":"venue"
},
  "geometry": {"coordinates":[-0.58561,53.040405],"type":"Point"}
}