{
  "type": "Feature",
  "properties": {
    "iso:country":"GB",
    "sg:address":"17 High Street, Northfleet",
    "sg:city":"Gravesend",
    "sg:classifiers":[
        {
            "category":"Manufacturing",
            "subcategory":"Tools & Machinery",
            "type":"Manufacturing & Wholesale Goods"
        },
        {
            "category":"Professional",
            "subcategory":"Business Services",
            "type":"Services"
        }
    ],
    "sg:phone":"+44 1474 560551",
    "sg:postcode":"DA11 9EZ",
    "sg:province":"Kent",
    "sg:tags":[
        "import",
        "export",
        "agent",
        "power"
    ],
    "wof:name":"E K P Caravans",
    "wof:placetype":"venue"
},
  "geometry": {"coordinates":[0.332495,51.444599],"type":"Point"}
}