{
  "type": "Feature",
  "properties": {
    "iso:country":"GB",
    "sg:address":"Cooks Road, Bow",
    "sg:city":"London",
    "sg:classifiers":[
        {
            "category":"Home & Garden",
            "subcategory":"Home Furnishings",
            "type":"Retail Goods"
        }
    ],
    "sg:phone":"+44 20 8519 9191",
    "sg:postcode":"E15 2PL",
    "sg:province":"Greater London",
    "sg:tags":[
        "homefurnishings"
    ],
    "wof:name":"Continenta Ltd.",
    "wof:placetype":"venue"
},
  "geometry": {"coordinates":[-0.014497,51.531242],"type":"Point"}
}