{
  "type": "Feature",
  "properties": {
    "addr:full":"26a Chatsworth Place Harrogate North Yorkshire HG1 5HR",
    "addr:housenumber":"26a",
    "addr:postcode":"hg1 5hr",
    "addr:street":"Chatsworth Place",
    "iso:country":"GB",
    "sg:address":"26a Chatsworth Place",
    "sg:city":"Harrogate",
    "sg:classifiers":[
        {
            "category":"Professional",
            "subcategory":"Printing & Photocopies",
            "type":"Services"
        }
    ],
    "sg:phone":"+44 1423 508550",
    "sg:postcode":"HG1 5HR",
    "sg:province":"North Yorkshire",
    "sg:tags":[
        "photocopier"
    ],
    "wof:name":"Copytech",
    "wof:placetype":"venue"
},
  "geometry": {"coordinates":[-1.5359660387,54.0012283325],"type":"Point"}
}