{
  "type": "Feature",
  "properties": {
    "iso:country":"GB",
    "sg:address":"Kingstanding Rd",
    "sg:city":"Birmingham",
    "sg:classifiers":[
        {
            "category":"Bars & Pubs",
            "type":"Food & Drink"
        }
    ],
    "sg:phone":"+44 121 331 2951",
    "sg:postcode":"B44 8JR",
    "sg:province":"West Midlands",
    "sg:tags":[
        "pubs",
        "inn"
    ],
    "wof:name":"Golden Hind The",
    "wof:placetype":"venue"
},
  "geometry": {"coordinates":[-1.8862890005,52.5402565002],"type":"Point"}
}