{
  "type": "Feature",
  "properties": {
    "addr:full":"Country Garden Centre, Bognor Rd Chichester West Sussex PO20 6EG",
    "addr:postcode":"po20 6eg",
    "addr:street":"Bognor Rd",
    "iso:country":"GB",
    "sg:address":"Country Garden Centre, Bognor Rd",
    "sg:city":"Chichester",
    "sg:classifiers":[
        {
            "category":"Education",
            "subcategory":"Music School",
            "type":"Public Place"
        }
    ],
    "sg:phone":"+44 1243 839111",
    "sg:postcode":"PO20 6EG",
    "sg:province":"West Sussex",
    "sg:tags":[
        "conservatory"
    ],
    "wof:name":"Frameline",
    "wof:placetype":"venue"
},
  "geometry": {"coordinates":[-0.7754300237,50.8361587524],"type":"Point"}
}