{
  "type": "Feature",
  "properties": {
    "addr:full":"Dunsdale Haugh Selkirk Scottish Borders TD7 5EF",
    "addr:postcode":"td7 5ef",
    "addr:street":"Haugh",
    "iso:country":"GB",
    "sg:address":"Dunsdale Haugh",
    "sg:city":"Selkirk",
    "sg:classifiers":[
        {
            "category":"Manufacturing",
            "subcategory":"Glass & Minerals",
            "type":"Manufacturing & Wholesale Goods"
        }
    ],
    "sg:phone":"+44 1750 20954",
    "sg:postcode":"TD7 5EF",
    "sg:province":"Scottish Borders",
    "sg:tags":[
        "product"
    ],
    "wof:name":"Selkirk Glass Ltd.",
    "wof:placetype":"venue"
},
  "geometry": {"coordinates":[-2.8321750164,55.5604820251],"type":"Point"}
}