{
  "type": "Feature",
  "properties": {
    "addr:full":"30 North St Ashford Kent TN24 8JR",
    "addr:housenumber":"30",
    "addr:postcode":"tn24 8jr",
    "addr:street":"North St",
    "iso:country":"GB",
    "sg:address":"30 North St",
    "sg:city":"Ashford",
    "sg:classifiers":[
        {
            "category":"Shopping",
            "subcategory":"Books",
            "type":"Retail Goods"
        }
    ],
    "sg:postcode":"TN24 8JR",
    "sg:province":"Kent",
    "sg:tags":[
        "bookseller"
    ],
    "wof:name":"Ashford Bookshop",
    "wof:placetype":"venue"
},
  "geometry": {"coordinates":[0.8734160066,51.149684906],"type":"Point"}
}