{
  "type": "Feature",
  "properties": {
    "iso:country":"GB",
    "sg:address":"Hill House, 1 Little New Street",
    "sg:city":"London",
    "sg:classifiers":[
        {
            "category":"Education",
            "subcategory":"Library",
            "type":"Public Place"
        },
        {
            "category":"Government",
            "subcategory":"Office",
            "type":"Public Place"
        }
    ],
    "sg:phone":"+44 20 7583 7178",
    "sg:postcode":"EC4A 3JR",
    "sg:province":"Greater London",
    "sg:tags":[
        "book",
        "local"
    ],
    "wof:name":"Shoe Lane Library",
    "wof:placetype":"venue"
},
  "geometry": {"coordinates":[-0.10638,51.51572],"type":"Point"}
}