{
  "type": "Feature",
  "properties": {
    "addr:full":"17 Rigby Clo, Heathcote Indstl Est Warwick Warwickshire CV34 6TH",
    "addr:housenumber":"17",
    "addr:postcode":"cv34 6th",
    "addr:street":"Rigby Clo Heathcote Indstl Est",
    "iso:country":"GB",
    "sg:address":"17 Rigby Clo, Heathcote Indstl Est",
    "sg:city":"Warwick",
    "sg:classifiers":[
        {
            "category":"Professional",
            "subcategory":"Detective & Security Services",
            "type":"Services"
        }
    ],
    "sg:postcode":"CV34 6TH",
    "sg:province":"Warwickshire",
    "sg:tags":[
        "car"
    ],
    "wof:name":"Duff,G J,",
    "wof:placetype":"venue"
},
  "geometry": {"coordinates":[-1.552013,52.272732],"type":"Point"}
}