{
  "type": "Feature",
  "properties": {
    "addr:full":", Merton Okehampton Devon EX20 3DN",
    "addr:postcode":"ex20 3dn",
    "iso:country":"GB",
    "sg:address":", Merton",
    "sg:city":"Okehampton",
    "sg:classifiers":[
        {
            "category":"Education",
            "subcategory":"Special Training",
            "type":"Public Place"
        }
    ],
    "sg:phone":"+44 1805 603368",
    "sg:postcode":"EX20 3DN",
    "sg:province":"Devon",
    "sg:tags":[
        "product",
        "centre"
    ],
    "wof:name":"Great Potheridge House",
    "wof:placetype":"venue"
},
  "geometry": {"coordinates":[-4.093414,50.890713],"type":"Point"}
}