{
  "type": "Feature",
  "properties": {
    "addr:full":"281 Church Street Blackpool Lancashire FY1 3PB",
    "addr:housenumber":"281",
    "addr:postcode":"fy1 3pb",
    "addr:street":"Church Street",
    "iso:country":"GB",
    "sg:address":"281 Church Street",
    "sg:city":"Blackpool",
    "sg:classifiers":[
        {
            "category":"Building & Trades",
            "subcategory":"Construction",
            "type":"Services"
        }
    ],
    "sg:phone":"+44 1253 290666",
    "sg:postcode":"FY1 3PB",
    "sg:province":"Lancashire",
    "sg:tags":[
        "ceiling",
        "contractor"
    ],
    "wof:name":"Contex Building",
    "wof:placetype":"venue"
},
  "geometry": {"coordinates":[-3.040168,53.818569],"type":"Point"}
}