{
  "type": "Feature",
  "properties": {
    "iso:country":"GB",
    "sg:address":"97 Longfleet Road",
    "sg:city":"Poole",
    "sg:classifiers":[
        {
            "category":"Travel",
            "subcategory":"Hotels & Motels",
            "type":"Entertainment"
        }
    ],
    "sg:phone":"+44 1202 677839",
    "sg:postcode":"BH15 2HP",
    "sg:province":"Dorset",
    "sg:tags":[
        "house",
        "guest"
    ],
    "wof:name":"Holly House",
    "wof:placetype":"venue"
},
  "geometry": {"coordinates":[-1.973609,50.722221],"type":"Point"}
}