{
  "type": "Feature",
  "properties": {
    "addr:full":"39 Swainsea La Pickering North Yorkshire YO18 8NE",
    "addr:housenumber":"39",
    "addr:postcode":"yo18 8ne",
    "addr:street":"Swainsea La Pickering",
    "iso:country":"GB",
    "sg:address":"39 Swainsea La",
    "sg:city":"Pickering",
    "sg:classifiers":[
        {
            "category":"Building & Trades",
            "subcategory":"Construction",
            "type":"Services"
        }
    ],
    "sg:phone":"+44 1751 473108",
    "sg:postcode":"YO18 8NE",
    "sg:province":"North Yorkshire",
    "sg:tags":[
        "decorator",
        "painter"
    ],
    "wof:name":"Smith & Wardell",
    "wof:placetype":"venue"
},
  "geometry": {"coordinates":[-0.785705,54.250988],"type":"Point"}
}