{
  "type": "Feature",
  "properties": {
    "addr:full":"90 West St Farnham Surrey GU9 7EN",
    "addr:housenumber":"90",
    "addr:postcode":"gu9 7en",
    "addr:street":"West St",
    "iso:country":"GB",
    "sg:address":"90 West St",
    "sg:city":"Farnham",
    "sg:classifiers":[
        {
            "category":"Shopping",
            "subcategory":"Antiques",
            "type":"Retail Goods"
        }
    ],
    "sg:postcode":"GU9 7EN",
    "sg:province":"Surrey",
    "wof:name":"Clark,Patrica,",
    "wof:placetype":"venue"
},
  "geometry": {"coordinates":[-0.8034729958,51.2137832642],"type":"Point"}
}