{
  "type": "Feature",
  "properties": {
    "iso:country":"GB",
    "sg:address":"4 Parsonage Street",
    "sg:city":"Halstead",
    "sg:classifiers":[
        {
            "category":"Home & Garden",
            "subcategory":"Household Appliances",
            "type":"Retail Goods"
        }
    ],
    "sg:phone":"+44 1787 473596",
    "sg:postcode":"CO9 2LD",
    "sg:province":"Essex",
    "sg:tags":[
        "electrical"
    ],
    "wof:name":"R B Electrics",
    "wof:placetype":"venue"
},
  "geometry": {"coordinates":[0.639093,51.945057],"type":"Point"}
}