{
  "type": "Feature",
  "properties": {
    "addr:full":"24 Wellgate Rotherham South Yorkshire S60 2LR",
    "addr:housenumber":"24",
    "addr:postcode":"s60 2lr",
    "addr:street":"Wellgate Rotherham South",
    "iso:country":"GB",
    "sg:address":"24 Wellgate",
    "sg:city":"Rotherham",
    "sg:classifiers":[
        {
            "category":"Shopping",
            "subcategory":"Clothing, Apparel, & Fashions",
            "type":"Retail Goods"
        }
    ],
    "sg:phone":"+44 1709 513506",
    "sg:postcode":"S60 2LR",
    "sg:province":"South Yorkshire",
    "sg:tags":[
        "ladieswear"
    ],
    "wof:name":"K S",
    "wof:placetype":"venue"
},
  "geometry": {"coordinates":[-1.3545039892,53.4299087524],"type":"Point"}
}