{
  "type": "Feature",
  "properties": {
    "iso:country":"GB",
    "sg:address":"119-123 Cross Street, Sale",
    "sg:city":"Manchester",
    "sg:classifiers":[
        {
            "category":"Autos & Motor Vehicles",
            "subcategory":"Auto Supplies",
            "type":"Retail Goods"
        }
    ],
    "sg:phone":"+44 161 969 9655",
    "sg:postcode":"M33 7JN",
    "sg:province":"Cheshire",
    "sg:tags":[
        "exhaust",
        "absorber",
        "shock"
    ],
    "wof:name":"Kwik-Fit",
    "wof:placetype":"venue"
},
  "geometry": {"coordinates":[-2.3215720654,53.4291114807],"type":"Point"}
}