{
  "type": "Feature",
  "properties": {
    "addr:full":"College Farm, Hailey Lane, Hailey Hertford Hertfordshire SG13 7NX",
    "addr:postcode":"sg13 7nx",
    "addr:street":"Hailey Lane",
    "iso:country":"GB",
    "sg:address":"College Farm, Hailey Lane, Hailey",
    "sg:city":"Hertford",
    "sg:classifiers":[
        {
            "category":"Farming",
            "subcategory":"Livestock Farm",
            "type":"Manufacturing & Wholesale Goods"
        }
    ],
    "sg:phone":"+44 1992 462110",
    "sg:postcode":"SG13 7NX",
    "sg:province":"Hertfordshire",
    "sg:tags":[
        "others"
    ],
    "wof:name":"Evan C Smith",
    "wof:placetype":"venue"
},
  "geometry": {"coordinates":[-0.045925,51.782917],"type":"Point"}
}