{
  "type": "Feature",
  "properties": {
    "addr:full":"53 Mottingham Rd Eltham Greater London SE9 4QZ",
    "addr:housenumber":"53",
    "addr:postcode":"se9 4qz",
    "addr:street":"Mottingham Rd",
    "iso:country":"GB",
    "sg:address":"53 Mottingham Rd",
    "sg:city":"Eltham",
    "sg:classifiers":[
        {
            "category":"Building & Trades",
            "subcategory":"Cleaning & Sanitation",
            "type":"Services"
        }
    ],
    "sg:phone":"+44 20 8857 9388",
    "sg:postcode":"SE9 4QZ",
    "sg:province":"Greater London",
    "sg:tags":[
        "janitorial"
    ],
    "wof:name":"City & Kent Janitorial Supplies",
    "wof:placetype":"venue"
},
  "geometry": {"coordinates":[0.04521,51.436298],"type":"Point"}
}