{
  "type": "Feature",
  "properties": {
    "addr:full":"101 High Street Biggar Dumfries and Galloway ML12 6DL",
    "addr:housenumber":"101",
    "addr:postcode":"ml12 6dl",
    "addr:street":"High Street",
    "iso:country":"GB",
    "sg:address":"101 High Street",
    "sg:city":"Biggar",
    "sg:classifiers":[
        {
            "category":"Restaurant",
            "type":"Food & Drink"
        }
    ],
    "sg:phone":"+44 1899 220801",
    "sg:postcode":"ML12 6DL",
    "sg:province":"Dumfries and Galloway",
    "sg:tags":[
        "indian",
        "-"
    ],
    "wof:name":"Taj Mahal",
    "wof:placetype":"venue"
},
  "geometry": {"coordinates":[-3.5232920647,55.6245002747],"type":"Point"}
}