{
  "type": "Feature",
  "properties": {
    "iso:country":"GB",
    "sg:address":"4 Granville Road",
    "sg:city":"Colchester",
    "sg:classifiers":[
        {
            "category":"Personal",
            "subcategory":"Beauty Salon",
            "type":"Services"
        }
    ],
    "sg:postcode":"CO1 2EE",
    "sg:province":"Essex",
    "sg:tags":[
        "unisex",
        "hairdresser"
    ],
    "wof:name":"Sally Chapman",
    "wof:placetype":"venue"
},
  "geometry": {"coordinates":[0.912207,51.881508],"type":"Point"}
}