{
  "type": "Feature",
  "properties": {
    "addr:full":"Bryhan Court, Great Ellingham Attleborough Norfolk NR17 1JB",
    "addr:postcode":"nr17 1jb",
    "addr:street":"Court",
    "iso:country":"GB",
    "sg:address":"Bryhan Court, Great Ellingham",
    "sg:city":"Attleborough",
    "sg:classifiers":[
        {
            "category":"Manufacturing",
            "subcategory":"Electronics",
            "type":"Manufacturing & Wholesale Goods"
        }
    ],
    "sg:phone":"+44 1953 457800",
    "sg:postcode":"NR17 1JB",
    "sg:province":"Norfolk",
    "sg:tags":[
        "control",
        "component",
        "-",
        "electronic"
    ],
    "wof:name":"D C P Microdevelopments Ltd.",
    "wof:placetype":"venue"
},
  "geometry": {"coordinates":[1.009945035,52.5222587585],"type":"Point"}
}