{
  "type": "Feature",
  "properties": {
    "iso:country":"GB",
    "sg:address":"11 Birch Dr",
    "sg:city":"Oldham",
    "sg:classifiers":[
        {
            "category":"Fast Food",
            "type":"Food & Drink"
        }
    ],
    "sg:phone":"+44 161 620 1785",
    "sg:postcode":"OL4 5DX",
    "sg:province":"Lancashire",
    "sg:tags":[
        "away",
        "take"
    ],
    "wof:name":"Tastefully Yours",
    "wof:placetype":"venue"
},
  "geometry": {"coordinates":[-2.069537,53.535271],"type":"Point"}
}