{
  "type": "Feature",
  "properties": {
    "addr:full":"Clydeway Centre, 45 Finnieston St Glasgow Glasgow City G3 8JU",
    "addr:housenumber":"45",
    "addr:postcode":"g3 8ju",
    "addr:street":"Finnieston St",
    "iso:country":"GB",
    "sg:address":"Clydeway Centre, 45 Finnieston St",
    "sg:city":"Glasgow",
    "sg:classifiers":[
        {
            "category":"Shopping",
            "subcategory":"Clothing, Apparel, & Fashions",
            "type":"Retail Goods"
        }
    ],
    "sg:phone":"+44 141 564 3500",
    "sg:postcode":"G3 8JU",
    "sg:province":"Glasgow City",
    "sg:tags":[
        "clothing"
    ],
    "wof:name":"Gilt Edged Corporate Wear",
    "wof:placetype":"venue"
},
  "geometry": {"coordinates":[-4.2807,55.86253],"type":"Point"}
}