{
  "type": "Feature",
  "properties": {
    "iso:country":"GB",
    "sg:address":"29 Drygate Street",
    "sg:city":"Larkhall",
    "sg:classifiers":[
        {
            "category":"Food & Beverages",
            "subcategory":"Fruits & Vegetables",
            "type":"Retail Goods"
        },
        {
            "category":"Food & Beverages",
            "subcategory":"Groceries & Convenience Stores",
            "type":"Retail Goods"
        }
    ],
    "sg:phone":"+44 1698 881449",
    "sg:postcode":"ML9 2DA",
    "sg:province":"South Lanarkshire",
    "sg:tags":[
        "greengrocer"
    ],
    "wof:name":"DRYGATE GROCERY STORE",
    "wof:placetype":"venue"
},
  "geometry": {"coordinates":[-3.9700660706,55.743396759],"type":"Point"}
}