{
  "type": "Feature",
  "properties": {
    "iso:country":"GB",
    "sg:address":"26 Stanley Road",
    "sg:city":"Eastbourne",
    "sg:classifiers":[
        {
            "category":"Shopping",
            "subcategory":"Gifts & Souvenirs",
            "type":"Retail Goods"
        }
    ],
    "sg:postcode":"BN22 8JP",
    "sg:province":"East Sussex",
    "sg:tags":[
        "poster",
        "card"
    ],
    "wof:name":"Whitley Road Post Office",
    "wof:placetype":"venue"
},
  "geometry": {"coordinates":[0.2935220003,50.7766036987],"type":"Point"}
}