{
  "type": "Feature",
  "properties": {
    "addr:full":"12 Brig-y-nant Llangefni Gwynedd LL77 7QD",
    "addr:housenumber":"12",
    "addr:postcode":"ll77 7qd",
    "addr:street":"Brig-Y-Nant Llangefni",
    "iso:country":"GB",
    "sg:address":"12 Brig-y-nant",
    "sg:city":"Llangefni",
    "sg:classifiers":[
        {
            "category":"Building & Trades",
            "subcategory":"Construction",
            "type":"Services"
        }
    ],
    "sg:phone":"+44 1248 722660",
    "sg:postcode":"LL77 7QD",
    "sg:province":"Gwynedd",
    "sg:tags":[
        "joiner",
        "carpenter"
    ],
    "wof:name":"A.R Thomas",
    "wof:placetype":"venue"
},
  "geometry": {"coordinates":[-4.3198289871,53.2588500977],"type":"Point"}
}