{
  "type": "Feature",
  "properties": {
    "addr:full":"Calderwood Road Glasgow South Lanarkshire G74 4JB",
    "addr:postcode":"g74 4jb",
    "addr:street":"Calderwood Road",
    "iso:country":"GB",
    "sg:address":"Calderwood Road",
    "sg:city":"Glasgow",
    "sg:classifiers":[
        {
            "category":"Community Center",
            "type":"Public Place"
        },
        {
            "category":"Government",
            "subcategory":"Office",
            "type":"Public Place"
        }
    ],
    "sg:phone":"+44 1355 227124",
    "sg:postcode":"G74 4JB",
    "sg:province":"South Lanarkshire",
    "sg:tags":[
        "recreation",
        "local",
        "leisure",
        "centre"
    ],
    "wof:name":"Whitemoss Bowling Club",
    "wof:placetype":"venue"
},
  "geometry": {"coordinates":[-4.28611,55.816952],"type":"Point"}
}