{
  "type": "Feature",
  "properties": {
    "addr:full":"Cruse Ho, 40 Clydesdale St Hamilton South Lanarkshire ML3 0DA",
    "addr:housenumber":"40",
    "addr:postcode":"ml3 0da",
    "addr:street":"Clydesdale St",
    "iso:country":"GB",
    "sg:address":"Cruse Ho, 40 Clydesdale St",
    "sg:city":"Hamilton",
    "sg:classifiers":[
        {
            "category":"Professional",
            "subcategory":"Lawyer & Legal Services",
            "type":"Services"
        }
    ],
    "sg:phone":"+44 1698 303099",
    "sg:postcode":"ML3 0DA",
    "sg:province":"South Lanarkshire",
    "sg:tags":[
        "advice",
        "counselling"
    ],
    "wof:name":"CRUSE Bereavement Care",
    "wof:placetype":"venue"
},
  "geometry": {"coordinates":[-4.0533800125,55.7790298462],"type":"Point"}
}