{
  "type": "Feature",
  "properties": {
    "iso:country":"GB",
    "sg:address":"68 Pall Mall",
    "sg:city":"London",
    "sg:classifiers":[
        {
            "category":"Professional",
            "subcategory":"Lawyer & Legal Services",
            "type":"Services"
        }
    ],
    "sg:phone":"+44 20 7321 0477",
    "sg:postcode":"SW1Y 5ES",
    "sg:province":"Greater London",
    "wof:name":"Kilpatrick Stockton",
    "wof:placetype":"venue"
},
  "geometry": {"coordinates":[-0.1371649951,51.5054321289],"type":"Point"}
}