{
  "type": "Feature",
  "properties": {
    "addr:full":"Springfields Retail Park, Newcastle Road Stoke-on-trent Staffordshire ST4 6PD",
    "addr:postcode":"st4 6pd",
    "addr:street":"Springfields Retail Park Newcastle Road",
    "iso:country":"GB",
    "sg:address":"Springfields Retail Park, Newcastle Road",
    "sg:city":"Stoke-on-trent",
    "sg:classifiers":[
        {
            "category":"Fast Food",
            "type":"Food & Drink"
        }
    ],
    "sg:phone":"+44 1782 714243",
    "sg:postcode":"ST4 6PD",
    "sg:province":"Staffordshire",
    "sg:tags":[
        "away",
        "take"
    ],
    "wof:name":"McDonalds Restaurants Ltd.",
    "wof:placetype":"venue"
},
  "geometry": {"coordinates":[-2.208219,52.994846],"type":"Point"}
}