{
  "type": "Feature",
  "properties": {
    "addr:full":"133 Canterbury Road Margate Kent CT9 5BD",
    "addr:housenumber":"133",
    "addr:postcode":"ct9 5bd",
    "addr:street":"Canterbury Road",
    "iso:country":"GB",
    "sg:address":"133 Canterbury Road",
    "sg:city":"Margate",
    "sg:classifiers":[
        {
            "category":"Fast Food",
            "type":"Food & Drink"
        }
    ],
    "sg:phone":"+44 1843 295993",
    "sg:postcode":"CT9 5BD",
    "sg:province":"Kent",
    "sg:tags":[
        "away",
        "take"
    ],
    "wof:name":"Man Lin Chinese Take Away",
    "wof:placetype":"venue"
},
  "geometry": {"coordinates":[1.371055007,51.3863716125],"type":"Point"}
}