{
  "type": "Feature",
  "properties": {
    "addr:full":"17 Evan Street Stonehaven Aberdeenshire AB39 2EQ",
    "addr:housenumber":"17",
    "addr:postcode":"ab39 2eq",
    "addr:street":"Evan Street",
    "iso:country":"GB",
    "sg:address":"17 Evan Street",
    "sg:city":"Stonehaven",
    "sg:classifiers":[
        {
            "category":"Shopping",
            "subcategory":"Shoes",
            "type":"Retail Goods"
        }
    ],
    "sg:postcode":"AB39 2EQ",
    "sg:province":"Aberdeenshire",
    "sg:tags":[
        "shop"
    ],
    "wof:name":"D E Shoe Service",
    "wof:placetype":"venue"
},
  "geometry": {"coordinates":[-2.209977,56.963863],"type":"Point"}
}