{
  "type": "Feature",
  "properties": {
    "addr:full":"Gildingwells Road, Woodsetts Worksop Nottinghamshire S81 8QB",
    "addr:postcode":"s81 8qb",
    "addr:street":"Gildingwells Road",
    "iso:country":"GB",
    "sg:address":"Gildingwells Road, Woodsetts",
    "sg:city":"Worksop",
    "sg:classifiers":[
        {
            "category":"Education",
            "subcategory":"School",
            "type":"Public Place"
        },
        {
            "category":"Government",
            "subcategory":"Office",
            "type":"Public Place"
        }
    ],
    "sg:postcode":"S81 8QB",
    "sg:province":"Nottinghamshire",
    "sg:tags":[
        "local",
        "authority"
    ],
    "wof:name":"Rotherham Metropolitan Borough Council",
    "wof:placetype":"venue"
},
  "geometry": {"coordinates":[-1.1634030342,53.3627662659],"type":"Point"}
}