{
  "type": "Feature",
  "properties": {
    "addr:full":"Omega Maltings, 8 Star St Ware Hertfordshire SG12 7AA",
    "addr:housenumber":"8",
    "addr:postcode":"sg12 7aa",
    "addr:street":"Maltings;Star St",
    "iso:country":"GB",
    "sg:address":"Omega Maltings, 8 Star St",
    "sg:city":"Ware",
    "sg:classifiers":[
        {
            "category":"Shopping",
            "subcategory":"Clothing, Apparel, & Fashions",
            "type":"Retail Goods"
        },
        {
            "category":"Manufacturing",
            "subcategory":"Apparel",
            "type":"Manufacturing & Wholesale Goods"
        }
    ],
    "sg:postcode":"SG12 7AA",
    "sg:province":"Hertfordshire",
    "sg:tags":[
        "clothing",
        "shirt",
        "maker"
    ],
    "wof:name":"Roberto Carlo Ltd",
    "wof:placetype":"venue"
},
  "geometry": {"coordinates":[0.0240390003,51.8215560913],"type":"Point"}
}