{
  "type": "Feature",
  "properties": {
    "addr:full":"83 Efford Lane, Efford Plymouth Devon PL3 6LT",
    "addr:housenumber":"83",
    "addr:postcode":"pl3 6lt",
    "addr:street":"Efford Lane",
    "iso:country":"GB",
    "sg:address":"83 Efford Lane, Efford",
    "sg:city":"Plymouth",
    "sg:classifiers":[
        {
            "category":"Building & Trades",
            "subcategory":"Plumbing",
            "type":"Services"
        }
    ],
    "sg:phone":"+44 1752 265672",
    "sg:postcode":"PL3 6LT",
    "sg:province":"Devon",
    "sg:tags":[
        "drain",
        "clearance",
        "sewer"
    ],
    "wof:name":"Drain Doctor (South West) Ltd.",
    "wof:placetype":"venue"
},
  "geometry": {"coordinates":[-4.1115579605,50.3864974976],"type":"Point"}
}