{
  "type": "Feature",
  "properties": {
    "addr:full":"High Street, Handcross Haywards Heath East Sussex RH17 6BL",
    "addr:postcode":"rh17 6bl",
    "addr:street":"High Street",
    "iso:country":"GB",
    "sg:address":"High Street, Handcross",
    "sg:city":"Haywards Heath",
    "sg:classifiers":[
        {
            "category":"Home & Garden",
            "subcategory":"Home Furnishings",
            "type":"Retail Goods"
        }
    ],
    "sg:phone":"+44 1444 401277",
    "sg:postcode":"RH17 6BL",
    "sg:province":"East Sussex",
    "sg:tags":[
        "furnishers",
        "planner",
        "kitchen"
    ],
    "wof:name":"Christians of Handcross",
    "wof:placetype":"venue"
},
  "geometry": {"coordinates":[-0.157523,51.073483],"type":"Point"}
}