{
  "type": "Feature",
  "properties": {
    "addr:full":"Hopwood Hall, 2 Hopwood Lane Halifax West Yorkshire HX1 5HW",
    "addr:housenumber":"2",
    "addr:postcode":"hx1 5hw",
    "addr:street":"Hopwood Lane",
    "iso:country":"GB",
    "sg:address":"Hopwood Hall, 2 Hopwood Lane",
    "sg:city":"Halifax",
    "sg:classifiers":[
        {
            "category":"Organizations",
            "subcategory":"Professional Association",
            "type":"Services"
        }
    ],
    "sg:postcode":"HX1 5HW",
    "sg:province":"West Yorkshire",
    "sg:tags":[
        "union",
        "trade"
    ],
    "wof:name":"Natwest Staff Association",
    "wof:placetype":"venue"
},
  "geometry": {"coordinates":[-1.862224,53.721233],"type":"Point"}
}