{
  "type": "Feature",
  "properties": {
    "addr:full":"122 High Street Lowestoft Suffolk NR32 1HN",
    "addr:housenumber":"122",
    "addr:postcode":"nr32 1hn",
    "addr:street":"High Street",
    "iso:country":"GB",
    "sg:address":"122 High Street",
    "sg:city":"Lowestoft",
    "sg:classifiers":[
        {
            "category":"Shopping",
            "subcategory":"Tobacco",
            "type":"Retail Goods"
        },
        {
            "category":"Retail",
            "subcategory":"Event Space",
            "type":"Services"
        }
    ],
    "sg:phone":"+44 1502 567503",
    "sg:postcode":"NR32 1HN",
    "sg:province":"Suffolk",
    "sg:tags":[
        "product",
        "tobacconist",
        "sale"
    ],
    "wof:name":"Waveney News",
    "wof:placetype":"venue"
},
  "geometry": {"coordinates":[1.755494,52.479996],"type":"Point"}
}