{
  "type": "Feature",
  "properties": {
    "addr:full":"21 Dovecote Drive, Denton Northampton Buckinghamshire NN7 1ED",
    "addr:housenumber":"21",
    "addr:postcode":"nn7 1ed",
    "addr:street":"Dovecote Drive",
    "iso:country":"GB",
    "sg:address":"21 Dovecote Drive, Denton",
    "sg:city":"Northampton",
    "sg:classifiers":[
        {
            "category":"Building & Trades",
            "subcategory":"Construction",
            "type":"Services"
        }
    ],
    "sg:postcode":"NN7 1ED",
    "sg:province":"Buckinghamshire",
    "sg:tags":[
        "builder"
    ],
    "wof:name":"Ptb Formwork Ltd",
    "wof:placetype":"venue"
},
  "geometry": {"coordinates":[-0.777956,52.214573],"type":"Point"}
}