{
  "type": "Feature",
  "properties": {
    "iso:country":"GB",
    "sg:address":"Priors Crescent, Dunvant",
    "sg:city":"Swansea",
    "sg:classifiers":[
        {
            "category":"Education",
            "subcategory":"School",
            "type":"Public Place"
        }
    ],
    "sg:phone":"+44 1792 203728",
    "sg:postcode":"SA2 7UF",
    "sg:province":"Swansea",
    "sg:tags":[
        "local",
        "authority"
    ],
    "wof:name":"Pen Y Fro Primary School",
    "wof:placetype":"venue"
},
  "geometry": {"coordinates":[-4.0378050804,51.6260147095],"type":"Point"}
}