{
  "type": "Feature",
  "properties": {
    "iso:country":"GB",
    "sg:address":"1206 Tollcross Road",
    "sg:city":"Glasgow",
    "sg:classifiers":[
        {
            "category":"Fast Food",
            "type":"Food & Drink"
        }
    ],
    "sg:postcode":"G32 8HH",
    "sg:province":"Glasgow City",
    "sg:tags":[
        "away",
        "take"
    ],
    "wof:name":"Exceptchoice Limited",
    "wof:placetype":"venue"
},
  "geometry": {"coordinates":[-4.1667628288,55.8426818848],"type":"Point"}
}