{
  "type": "Feature",
  "properties": {
    "iso:country":"GB",
    "sg:address":"1a Royston Rd, Crayford",
    "sg:city":"Dartford",
    "sg:classifiers":[
        {
            "category":"Building & Trades",
            "subcategory":"Construction",
            "type":"Services"
        }
    ],
    "sg:phone":"+44 1322 521152",
    "sg:postcode":"DA1 3QH",
    "sg:province":"Kent",
    "sg:tags":[
        "builder"
    ],
    "wof:name":"Turrell Bros. Builders",
    "wof:placetype":"venue"
},
  "geometry": {"coordinates":[0.180083,51.446342],"type":"Point"}
}