{
  "type": "Feature",
  "properties": {
    "addr:full":"110 Junction Road London Greater London N19 5LB",
    "addr:housenumber":"110",
    "addr:postcode":"n19 5lb",
    "addr:street":"Junction Road",
    "iso:country":"GB",
    "sg:address":"110 Junction Road",
    "sg:city":"London",
    "sg:classifiers":[
        {
            "category":"Restaurant",
            "type":"Food & Drink"
        }
    ],
    "sg:phone":"+44 20 7263 1410",
    "sg:postcode":"N19 5LB",
    "sg:province":"Greater London",
    "wof:name":"Charuwan",
    "wof:placetype":"venue"
},
  "geometry": {"coordinates":[-0.1369629949,51.5612220764],"type":"Point"}
}