{
  "type": "Feature",
  "properties": {
    "addr:full":"Llynlloedd Machynlleth Ceredigion SY20 8EX",
    "addr:postcode":"sy20 8ex",
    "iso:country":"GB",
    "sg:address":"Llynlloedd",
    "sg:city":"Machynlleth",
    "sg:classifiers":[
        {
            "category":"Farming",
            "subcategory":"Livestock Farm",
            "type":"Manufacturing & Wholesale Goods"
        }
    ],
    "sg:postcode":"SY20 8EX",
    "sg:province":"Ceredigion",
    "sg:tags":[
        "others"
    ],
    "wof:name":"J C E Fenwick",
    "wof:placetype":"venue"
},
  "geometry": {"coordinates":[-3.846723,52.590961],"type":"Point"}
}