{
  "type": "Feature",
  "properties": {
    "addr:full":"122 Golders Green Road London Greater London NW11 8HB",
    "addr:housenumber":"122",
    "addr:postcode":"nw11 8hb",
    "addr:street":"Golders Green Road",
    "iso:country":"GB",
    "sg:address":"122 Golders Green Road",
    "sg:city":"London",
    "sg:classifiers":[
        {
            "category":"Farming",
            "subcategory":"Fish & Marine Products",
            "type":"Manufacturing & Wholesale Goods"
        }
    ],
    "sg:postcode":"NW11 8HB",
    "sg:province":"Greater London",
    "sg:tags":[
        "kosher",
        "food"
    ],
    "wof:name":"Cafe on the Green",
    "wof:placetype":"venue"
},
  "geometry": {"coordinates":[-0.2005569935,51.5738677979],"type":"Point"}
}