{
  "type": "Feature",
  "properties": {
    "addr:full":"Westpole Avenue, Cockfosters Barnet Hertfordshire EN4 0BN",
    "addr:postcode":"en4 0bn",
    "addr:street":"Avenue",
    "iso:country":"GB",
    "sg:address":"Westpole Avenue, Cockfosters",
    "sg:city":"Barnet",
    "sg:classifiers":[
        {
            "category":"Retail",
            "subcategory":"Auto Repair",
            "type":"Services"
        }
    ],
    "sg:phone":"+44 20 8441 4600",
    "sg:postcode":"EN4 0BN",
    "sg:province":"Hertfordshire",
    "sg:tags":[
        "modification",
        "garage"
    ],
    "wof:name":"Highfield Garage (Winchmore Hill) Ltd.",
    "wof:placetype":"venue"
},
  "geometry": {"coordinates":[-0.1575639993,51.6674041748],"type":"Point"}
}