{
  "type": "Feature",
  "properties": {
    "iso:country":"GB",
    "sg:address":"Unit 4, St. Marys Business Park, Albany Rd",
    "sg:city":"Market Harborough",
    "sg:classifiers":[
        {
            "category":"Professional",
            "subcategory":"Testing Lab",
            "type":"Services"
        }
    ],
    "sg:phone":"+44 1858 433100",
    "sg:postcode":"LE16 7QG",
    "sg:province":"Leicestershire",
    "sg:tags":[
        "laboratory"
    ],
    "wof:name":"Pyro Therm Equipment Co",
    "wof:placetype":"venue"
},
  "geometry": {"coordinates":[-0.922579,52.479397],"type":"Point"}
}