{
  "type": "Feature",
  "properties": {
    "iso:country":"GB",
    "sg:address":"2 Sandwood Close, Sparcells",
    "sg:city":"Swindon",
    "sg:classifiers":[
        {
            "category":"Building & Trades",
            "subcategory":"Construction",
            "type":"Services"
        }
    ],
    "sg:postcode":"SN5 5FA",
    "sg:province":"Wiltshire",
    "sg:tags":[
        "tiling",
        "contractor"
    ],
    "wof:name":"Phil Matthams Tiling",
    "wof:placetype":"venue"
},
  "geometry": {"coordinates":[-1.82918,51.578022],"type":"Point"}
}