{
  "type": "Feature",
  "properties": {
    "addr:full":"82 Bedford Road Bedford Bedfordshire MK42 8BB",
    "addr:housenumber":"82",
    "addr:postcode":"mk42 8bb",
    "addr:street":"Bedford Road",
    "iso:country":"GB",
    "sg:address":"82 Bedford Road",
    "sg:city":"Bedford",
    "sg:classifiers":[
        {
            "category":"Autos & Motor Vehicles",
            "subcategory":"Automobile Sales",
            "type":"Retail Goods"
        }
    ],
    "sg:phone":"+44 1234 855033",
    "sg:postcode":"MK42 8BB",
    "sg:province":"Bedfordshire",
    "sg:tags":[
        "car"
    ],
    "wof:name":"Kempston Car Sales",
    "wof:placetype":"venue"
},
  "geometry": {"coordinates":[-0.4876869917,52.1217956543],"type":"Point"}
}