{
  "type": "Feature",
  "properties": {
    "addr:full":"5 High Street Johnstone Renfrewshire PA5 8JZ",
    "addr:housenumber":"5",
    "addr:postcode":"pa5 8jz",
    "addr:street":"High Street",
    "iso:country":"GB",
    "sg:address":"5 High Street",
    "sg:city":"Johnstone",
    "sg:classifiers":[
        {
            "category":"Professional",
            "subcategory":"Art Services",
            "type":"Services"
        }
    ],
    "sg:phone":"+44 1505 327272",
    "sg:postcode":"PA5 8JZ",
    "sg:province":"Renfrewshire",
    "sg:tags":[
        "framing"
    ],
    "wof:name":"The Frame Shop",
    "wof:placetype":"venue"
},
  "geometry": {"coordinates":[-4.5072860718,55.8358001709],"type":"Point"}
}