{
  "type": "Feature",
  "properties": {
    "addr:full":"284 Totnes Road Paignton Devon TQ4 7HB",
    "addr:housenumber":"284",
    "addr:postcode":"tq4 7hb",
    "addr:street":"Totnes Road",
    "iso:country":"GB",
    "sg:address":"284 Totnes Road",
    "sg:city":"Paignton",
    "sg:classifiers":[
        {
            "category":"Autos & Motor Vehicles",
            "subcategory":"Automobile Sales",
            "type":"Retail Goods"
        }
    ],
    "sg:postcode":"TQ4 7HB",
    "sg:province":"Devon",
    "sg:tags":[
        "car"
    ],
    "wof:name":"Motor House the",
    "wof:placetype":"venue"
},
  "geometry": {"coordinates":[-3.5889289379,50.4286308289],"type":"Point"}
}