{
  "type": "Feature",
  "properties": {
    "addr:full":"Polstain Farm, Zelah Truro Cornwall TR4 9HY",
    "addr:postcode":"tr4 9hy",
    "addr:street":"Zelah",
    "iso:country":"GB",
    "sg:address":"Polstain Farm, Zelah",
    "sg:city":"Truro",
    "sg:classifiers":[
        {
            "category":"Farming",
            "subcategory":"Farm",
            "type":"Manufacturing & Wholesale Goods"
        }
    ],
    "sg:postcode":"TR4 9HY",
    "sg:province":"Cornwall",
    "sg:tags":[
        "mixed",
        "crop"
    ],
    "wof:name":"M C Whitford",
    "wof:placetype":"venue"
},
  "geometry": {"coordinates":[-5.0770192146,50.3249473572],"type":"Point"}
}