{
  "type": "Feature",
  "properties": {
    "iso:country":"GB",
    "sg:address":"46 Bickerdike Terrace, Kippax",
    "sg:city":"Leeds",
    "sg:classifiers":[
        {
            "category":"Building & Trades",
            "subcategory":"Landscaping Services",
            "type":"Services"
        }
    ],
    "sg:postcode":"LS25 7JY",
    "sg:province":"North Yorkshire",
    "sg:tags":[
        "landscape",
        "contractor"
    ],
    "wof:name":"A R B Landscapes",
    "wof:placetype":"venue"
},
  "geometry": {"coordinates":[-1.374504,53.764969],"type":"Point"}
}