{
  "type": "Feature",
  "properties": {
    "addr:full":"Nether Row, Hesket Newmarket Wigton Cumbria CA7 8LA",
    "addr:postcode":"ca7 8la",
    "addr:street":"Nether Row",
    "iso:country":"GB",
    "sg:address":"Nether Row, Hesket Newmarket",
    "sg:city":"Wigton",
    "sg:classifiers":[
        {
            "category":"Professional",
            "subcategory":"Art Services",
            "type":"Services"
        }
    ],
    "sg:phone":"+44 16974 78286",
    "sg:postcode":"CA7 8LA",
    "sg:province":"Cumbria",
    "sg:tags":[
        "photographer"
    ],
    "wof:name":"C J S Bonington",
    "wof:placetype":"venue"
},
  "geometry": {"coordinates":[-3.05078,54.730099],"type":"Point"}
}