{
  "type": "Feature",
  "properties": {
    "iso:country":"GB",
    "sg:address":"15 Middle Park Way",
    "sg:city":"Havant",
    "sg:classifiers":[
        {
            "category":"Health Services",
            "subcategory":"Clinic",
            "type":"Services"
        }
    ],
    "sg:phone":"+44 23 9261 1055",
    "sg:postcode":"PO9 4AB",
    "sg:province":"Hampshire",
    "sg:tags":[
        "nh"
    ],
    "wof:name":"Middle Park Medical Centre",
    "wof:placetype":"venue"
},
  "geometry": {"coordinates":[-0.999742,50.86499],"type":"Point"}
}