{
  "type": "Feature",
  "properties": {
    "addr:full":"21 York Road Maidenhead Berkshire SL6 1SQ",
    "addr:housenumber":"21",
    "addr:postcode":"sl6 1sq",
    "addr:street":"York Road",
    "iso:country":"GB",
    "sg:address":"21 York Road",
    "sg:city":"Maidenhead",
    "sg:classifiers":[
        {
            "category":"Building & Trades",
            "subcategory":"Construction",
            "type":"Services"
        }
    ],
    "sg:postcode":"SL6 1SQ",
    "sg:province":"Berkshire",
    "sg:tags":[
        "builder"
    ],
    "wof:name":"Charta Construction (Beaconsfield) Ltd.",
    "wof:placetype":"venue"
},
  "geometry": {"coordinates":[-0.7193880081,51.520778656],"type":"Point"}
}