{
  "type": "Feature",
  "properties": {
    "addr:full":"Derby Road Business Park, Derby Road, Clay Cross Chesterfield Derbyshire S45 9AG",
    "addr:postcode":"s45 9ag",
    "addr:street":"Derby Road Business Park Derby Road",
    "iso:country":"GB",
    "sg:address":"Derby Road Business Park, Derby Road, Clay Cross",
    "sg:city":"Chesterfield",
    "sg:classifiers":[
        {
            "category":"Building & Trades",
            "subcategory":"Construction",
            "type":"Services"
        }
    ],
    "sg:phone":"+44 1246 860799",
    "sg:postcode":"S45 9AG",
    "sg:province":"Derbyshire",
    "sg:tags":[
        "flooring"
    ],
    "wof:name":"Chryso U K Ltd.",
    "wof:placetype":"venue"
},
  "geometry": {"coordinates":[-1.4157170057,53.1657905579],"type":"Point"}
}