{
  "type": "Feature",
  "properties": {
    "iso:country":"GB",
    "sg:address":"17 High Street",
    "sg:city":"Merthyr Tydfil",
    "sg:classifiers":[
        {
            "category":"Fast Food",
            "type":"Food & Drink"
        }
    ],
    "sg:postcode":"CF47 8UB",
    "sg:province":"Merthyr Tydfil",
    "sg:tags":[
        "away",
        "take"
    ],
    "wof:name":"Taj Balti",
    "wof:placetype":"venue"
},
  "geometry": {"coordinates":[-3.378244,51.747849],"type":"Point"}
}