{
  "type": "Feature",
  "properties": {
    "addr:full":"Unit 6 Birchills Trading Estate, Emery Road Bristol City of Bristol BS4 5PF",
    "addr:housenumber":"unit 6;estate",
    "addr:postcode":"bs4 5pf",
    "addr:street":"Trading;Emery Road",
    "iso:country":"GB",
    "sg:address":"Unit 6 Birchills Trading Estate, Emery Road",
    "sg:city":"Bristol",
    "sg:classifiers":[
        {
            "category":"Building & Trades",
            "subcategory":"Cleaning & Sanitation",
            "type":"Services"
        }
    ],
    "sg:phone":"+44 117 971 3126",
    "sg:postcode":"BS4 5PF",
    "sg:province":"City of Bristol",
    "sg:tags":[
        "commercial"
    ],
    "wof:name":"Hygiene Group Ltd.",
    "wof:placetype":"venue"
},
  "geometry": {"coordinates":[-2.535223,51.436138],"type":"Point"}
}