{
  "type": "Feature",
  "properties": {
    "iso:country":"GB",
    "sg:address":"70 Jesmond Road West",
    "sg:city":"Newcastle-upon-tyne",
    "sg:classifiers":[
        {
            "category":"Professional",
            "subcategory":"Computer Services",
            "type":"Services"
        }
    ],
    "sg:postcode":"NE2 4QD",
    "sg:province":"Tyne and Wear",
    "sg:tags":[
        "system",
        "software"
    ],
    "wof:name":"Applied Client Server Ltd.",
    "wof:placetype":"venue"
},
  "geometry": {"coordinates":[-1.608277,54.981373],"type":"Point"}
}