{
  "type": "Feature",
  "properties": {
    "addr:full":"175 West Acre Drive Norwich Norfolk NR6 7HX",
    "addr:housenumber":"175",
    "addr:postcode":"nr6 7hx",
    "addr:street":"West Acre Drive",
    "iso:country":"GB",
    "sg:address":"175 West Acre Drive",
    "sg:city":"Norwich",
    "sg:classifiers":[
        {
            "category":"Professional",
            "type":"Services"
        }
    ],
    "sg:phone":"+44 1603 404464",
    "sg:postcode":"NR6 7HX",
    "sg:province":"Norfolk",
    "sg:tags":[
        "hire",
        "agency",
        "driver"
    ],
    "wof:name":"V I P Travel",
    "wof:placetype":"venue"
},
  "geometry": {"coordinates":[1.302645,52.671429],"type":"Point"}
}