{
  "type": "Feature",
  "properties": {
    "addr:full":"16 St Helens Place London Greater London EC3A 6DP",
    "addr:housenumber":"16",
    "addr:postcode":"ec3a 6dp",
    "addr:street":"St Helens Place",
    "iso:country":"GB",
    "sg:address":"16 St Helens Place",
    "sg:city":"London",
    "sg:classifiers":[
        {
            "category":"Professional",
            "subcategory":"Employment Agencies",
            "type":"Services"
        }
    ],
    "sg:phone":"+44 20 7588 5888",
    "sg:postcode":"EC3A 6DP",
    "sg:province":"Greater London",
    "sg:tags":[
        "consultant"
    ],
    "wof:name":"Centre Point Group",
    "wof:placetype":"venue"
},
  "geometry": {"coordinates":[-0.081977,51.51535],"type":"Point"}
}