{
  "type": "Feature",
  "properties": {
    "iso:country":"GB",
    "sg:address":"Model Farm, 144 Cock Bank, Whittlesey",
    "sg:city":"Peterborough",
    "sg:classifiers":[
        {
            "category":"Farming",
            "subcategory":"Livestock Farm",
            "type":"Manufacturing & Wholesale Goods"
        }
    ],
    "sg:phone":"+44 1733 840415",
    "sg:postcode":"PE7 2HN",
    "sg:province":"Cambridgeshire",
    "sg:tags":[
        "others"
    ],
    "wof:name":"E.C Brown & Son",
    "wof:placetype":"venue"
},
  "geometry": {"coordinates":[-0.13155,52.558418],"type":"Point"}
}