{
  "type": "Feature",
  "properties": {
    "addr:full":"Cavendish Ho, 128-134 Cleveland St West End Hampshire W1P 5DN",
    "addr:housenumber":"128-134",
    "addr:postcode":"w1p 5dn",
    "addr:street":"Cleveland St",
    "iso:country":"GB",
    "sg:address":"Cavendish Ho, 128-134 Cleveland St",
    "sg:city":"West End",
    "sg:classifiers":[
        {
            "category":"Communications",
            "type":"Services"
        }
    ],
    "sg:phone":"+44 20 7388 7700",
    "sg:postcode":"W1P 5DN",
    "sg:province":"Hampshire",
    "sg:tags":[
        "audio-visual"
    ],
    "wof:name":"Clark Television Productions",
    "wof:placetype":"venue"
},
  "geometry": {"coordinates":[-0.1389899999,51.5075798035],"type":"Point"}
}