{
  "type": "Feature",
  "properties": {
    "addr:full":"162 Cobblers Lane Pontefract North Yorkshire WF8 2LL",
    "addr:housenumber":"162",
    "addr:postcode":"wf8 2ll",
    "addr:street":"Cobblers Lane",
    "iso:country":"GB",
    "sg:address":"162 Cobblers Lane",
    "sg:city":"Pontefract",
    "sg:classifiers":[
        {
            "category":"Retail",
            "subcategory":"Storage",
            "type":"Services"
        }
    ],
    "sg:phone":"+44 1977 602245",
    "sg:postcode":"WF8 2LL",
    "sg:province":"North Yorkshire",
    "sg:tags":[
        "household",
        "removal"
    ],
    "wof:name":"James Valentine Removals",
    "wof:placetype":"venue"
},
  "geometry": {"coordinates":[-1.291977,53.698601],"type":"Point"}
}