{
  "type": "Feature",
  "properties": {
    "iso:country":"GB",
    "sg:address":"77 Priory Road",
    "sg:city":"Linlithgow",
    "sg:classifiers":[
        {
            "category":"Banks & Credit Unions",
            "subcategory":"Bank",
            "type":"Services"
        }
    ],
    "sg:postcode":"EH49 6BP",
    "sg:province":"Falkirk",
    "sg:tags":[
        "broker",
        "mortgage"
    ],
    "wof:name":"Nish Wendy",
    "wof:placetype":"venue"
},
  "geometry": {"coordinates":[-3.6042,55.971901],"type":"Point"}
}