{
  "type": "Feature",
  "properties": {
    "addr:full":"Unit B8, Marquis Court, Team Valley Trading Estate Gateshead Tyne and Wear NE11 0RU",
    "addr:postcode":"ne11 0ru",
    "addr:street":"Marquis Court Team",
    "iso:country":"GB",
    "sg:address":"Unit B8, Marquis Court, Team Valley Trading Estate",
    "sg:city":"Gateshead",
    "sg:classifiers":[
        {
            "category":"Building & Trades",
            "subcategory":"Cleaning & Sanitation",
            "type":"Services"
        }
    ],
    "sg:phone":"+44 191 491 4940",
    "sg:postcode":"NE11 0RU",
    "sg:province":"Tyne and Wear",
    "sg:tags":[
        "facility"
    ],
    "wof:name":"Pedus Ltd",
    "wof:placetype":"venue"
},
  "geometry": {"coordinates":[-1.6203989983,54.9331130981],"type":"Point"}
}