{
  "type": "Feature",
  "properties": {
    "iso:country":"GB",
    "sg:address":"Isobel Cottage, Parkhill",
    "sg:city":"Aberdeen",
    "sg:classifiers":[
        {
            "category":"Government",
            "subcategory":"Department Of Motor Vehicles",
            "type":"Public Place"
        }
    ],
    "sg:phone":"+44 1224 723897",
    "sg:postcode":"AB21 7XA",
    "sg:province":"Aberdeen City",
    "sg:tags":[
        "drawn",
        "horse",
        "hire"
    ],
    "wof:name":"Red Moss Clydedales",
    "wof:placetype":"venue"
},
  "geometry": {"coordinates":[-2.1616399288,57.2258491516],"type":"Point"}
}