{
  "type": "Feature",
  "properties": {
    "addr:full":"3-11 Dod St Poplar Greater London E14 7EQ",
    "addr:housenumber":"3-11",
    "addr:postcode":"e14 7eq",
    "addr:street":"Dod St",
    "iso:country":"GB",
    "sg:address":"3-11 Dod St",
    "sg:city":"Poplar",
    "sg:classifiers":[
        {
            "category":"Shopping",
            "subcategory":"Clothing, Apparel, & Fashions",
            "type":"Retail Goods"
        }
    ],
    "sg:phone":"+44 20 7515 3138",
    "sg:postcode":"E14 7EQ",
    "sg:province":"Greater London",
    "sg:tags":[
        "clothing",
        "fabric"
    ],
    "wof:name":"Burntex Ltd",
    "wof:placetype":"venue"
},
  "geometry": {"coordinates":[-0.02651,51.514],"type":"Point"}
}