{
  "type": "Feature",
  "properties": {
    "addr:full":"32 Market St Galashiels Scottish Borders TD1 3AA",
    "addr:housenumber":"32",
    "addr:postcode":"td1 3aa",
    "addr:street":"Market St",
    "iso:country":"GB",
    "sg:address":"32 Market St",
    "sg:city":"Galashiels",
    "sg:classifiers":[
        {
            "category":"Professional",
            "subcategory":"Business Services",
            "type":"Services"
        }
    ],
    "sg:postcode":"TD1 3AA",
    "sg:province":"Scottish Borders",
    "sg:tags":[
        "bookmaker"
    ],
    "wof:name":"Henderson,J,",
    "wof:placetype":"venue"
},
  "geometry": {"coordinates":[-2.8063070774,55.6153640747],"type":"Point"}
}