{
  "type": "Feature",
  "properties": {
    "iso:country":"GB",
    "sg:address":"8 Stanlane Pl",
    "sg:city":"Largs",
    "sg:classifiers":[
        {
            "category":"Shopping",
            "subcategory":"Department Store",
            "type":"Retail Goods"
        }
    ],
    "sg:postcode":"KA30 8DA",
    "sg:province":"North Ayrshire",
    "wof:name":"Livingstone,Ian,",
    "wof:placetype":"venue"
},
  "geometry": {"coordinates":[-4.869052887,55.7935943604],"type":"Point"}
}