{
  "type": "Feature",
  "properties": {
    "addr:full":"16 Melrose Place, Horsforth Leeds West Yorkshire LS18 4BY",
    "addr:housenumber":"16",
    "addr:postcode":"ls18 4by",
    "addr:street":"Melrose Place",
    "iso:country":"GB",
    "sg:address":"16 Melrose Place, Horsforth",
    "sg:city":"Leeds",
    "sg:classifiers":[
        {
            "category":"Professional",
            "subcategory":"Business Services",
            "type":"Services"
        }
    ],
    "sg:phone":"+44 113 258 2457",
    "sg:postcode":"LS18 4BY",
    "sg:province":"West Yorkshire",
    "sg:tags":[
        "shop",
        "cleaning"
    ],
    "wof:name":"Ace Service Cleaning Co.",
    "wof:placetype":"venue"
},
  "geometry": {"coordinates":[-1.623559,53.837189],"type":"Point"}
}