{
  "type": "Feature",
  "properties": {
    "addr:full":"Fullerton Road, Queensway Industrial Estate Glenrothes Fife KY7 5QR",
    "addr:postcode":"ky7 5qr",
    "addr:street":"Fullerton Road Queensway Industrial Estate",
    "iso:country":"GB",
    "sg:address":"Fullerton Road, Queensway Industrial Estate",
    "sg:city":"Glenrothes",
    "sg:classifiers":[
        {
            "category":"Autos & Motor Vehicles",
            "subcategory":"Auto Supplies",
            "type":"Retail Goods"
        }
    ],
    "sg:phone":"+44 1592 753839",
    "sg:postcode":"KY7 5QR",
    "sg:province":"Fife",
    "sg:tags":[
        "exhaust",
        "absorber",
        "shock"
    ],
    "wof:name":"Kwik-Fit",
    "wof:placetype":"venue"
},
  "geometry": {"coordinates":[-3.1739211082,56.1989631653],"type":"Point"}
}