{
  "type": "Feature",
  "properties": {
    "iso:country":"GB",
    "sg:address":"44 Stall Street",
    "sg:city":"Bath",
    "sg:classifiers":[
        {
            "category":"Banks & Credit Unions",
            "subcategory":"Bank",
            "type":"Services"
        }
    ],
    "sg:phone":"+44 845 765 4321",
    "sg:postcode":"BA1 1QH",
    "sg:province":"Bath and North East Somerset",
    "wof:name":"Abbey National Plc",
    "wof:placetype":"venue"
},
  "geometry": {"coordinates":[-2.36054,51.381413],"type":"Point"}
}