{
  "type": "Feature",
  "properties": {
    "addr:full":"120 High Street Hythe Kent CT21 5LE",
    "addr:housenumber":"120",
    "addr:postcode":"ct21 5le",
    "addr:street":"High Street",
    "iso:country":"GB",
    "sg:address":"120 High Street",
    "sg:city":"Hythe",
    "sg:classifiers":[
        {
            "category":"Personal",
            "subcategory":"Beauty Salon",
            "type":"Services"
        },
        {
            "category":"Personal",
            "subcategory":"Barber",
            "type":"Services"
        }
    ],
    "sg:phone":"+44 1303 261944",
    "sg:postcode":"CT21 5LE",
    "sg:province":"Kent",
    "sg:tags":[
        "unisex",
        "hairdresser"
    ],
    "sg:website":"http://www.oakshair.com",
    "wof:name":"Oaks Hair Design",
    "wof:placetype":"venue"
},
  "geometry": {"coordinates":[1.085859,51.07148],"type":"Point"}
}