{
  "type": "Feature",
  "properties": {
    "addr:full":"North Lodge, Landmark Rd Salcombe Devon TQ8 8NY",
    "addr:postcode":"tq8 8ny",
    "addr:street":"Landmark Rd",
    "iso:country":"GB",
    "sg:address":"North Lodge, Landmark Rd",
    "sg:city":"Salcombe",
    "sg:classifiers":[
        {
            "category":"Ferry",
            "type":"Transportation"
        }
    ],
    "sg:phone":"+44 1548 842061",
    "sg:postcode":"TQ8 8NY",
    "sg:province":"Devon",
    "wof:name":"Salcombe Ferry",
    "wof:placetype":"venue"
},
  "geometry": {"coordinates":[-3.774799,50.237865],"type":"Point"}
}