{
  "type": "Feature",
  "properties": {
    "iso:country":"GB",
    "sg:address":"The Chestnuts, Munderfield",
    "sg:city":"Bromyard",
    "sg:classifiers":[
        {
            "category":"Professional",
            "subcategory":"Computer Services",
            "type":"Services"
        }
    ],
    "sg:phone":"+44 1885 490480",
    "sg:postcode":"HR7 4JT",
    "sg:province":"Herefordshire",
    "sg:tags":[
        "development",
        "system",
        "software"
    ],
    "wof:name":"Diamond People Ltd",
    "wof:placetype":"venue"
},
  "geometry": {"coordinates":[-2.510399,52.189098],"type":"Point"}
}