{
  "type": "Feature",
  "properties": {
    "addr:full":"36-38 Empress Drive Blackpool Lancashire FY2 9SD",
    "addr:housenumber":"36-38",
    "addr:postcode":"fy2 9sd",
    "addr:street":"Empress Drive",
    "iso:country":"GB",
    "sg:address":"36-38 Empress Drive",
    "sg:city":"Blackpool",
    "sg:classifiers":[
        {
            "category":"Travel",
            "subcategory":"Hotels & Motels",
            "type":"Entertainment"
        }
    ],
    "sg:phone":"+44 1253 500150",
    "sg:postcode":"FY2 9SD",
    "sg:province":"Lancashire",
    "sg:tags":[
        "self",
        "catering"
    ],
    "wof:name":"Stratford Holiday Flats",
    "wof:placetype":"venue"
},
  "geometry": {"coordinates":[-3.0512330532,53.836265564],"type":"Point"}
}