{
  "type": "Feature",
  "properties": {
    "iso:country":"GB",
    "sg:address":"1 Julius Way, Lydfield Grn",
    "sg:city":"Lydney",
    "sg:classifiers":[
        {
            "category":"Shopping",
            "subcategory":"Jewelry",
            "type":"Retail Goods"
        }
    ],
    "sg:phone":"+44 1594 842288",
    "sg:postcode":"GL15 5QS",
    "sg:province":"Gloucestershire",
    "sg:tags":[
        "diamond"
    ],
    "wof:name":"Utilities Supplies Ltd.",
    "wof:placetype":"venue"
},
  "geometry": {"coordinates":[-2.5267410278,51.7311592102],"type":"Point"}
}