{
  "type": "Feature",
  "properties": {
    "addr:full":"99 Riverview, Chadwell St Mary Grays Essex RM16 4BD",
    "addr:housenumber":"99",
    "addr:postcode":"rm16 4bd",
    "addr:street":"Riverview",
    "iso:country":"GB",
    "sg:address":"99 Riverview, Chadwell St Mary",
    "sg:city":"Grays",
    "sg:classifiers":[
        {
            "category":"Health Services",
            "subcategory":"Clinic",
            "type":"Services"
        },
        {
            "category":"Autos & Motor Vehicles",
            "subcategory":"Auto Supplies",
            "type":"Retail Goods"
        }
    ],
    "sg:phone":"+44 1375 846696",
    "sg:postcode":"RM16 4BD",
    "sg:province":"Essex",
    "sg:tags":[
        "nh",
        "towbars"
    ],
    "wof:name":"Chadwell Trailers",
    "wof:placetype":"venue"
},
  "geometry": {"coordinates":[0.36312,51.481441],"type":"Point"}
}