{
  "type": "Feature",
  "properties": {
    "addr:full":"Brockholes Industrial Park, Rock Mill Rd Huddersfield West Yorkshire HD7 7BN",
    "addr:postcode":"hd7 7bn",
    "addr:street":"Rock Mill Rd",
    "iso:country":"GB",
    "sg:address":"Brockholes Industrial Park, Rock Mill Rd",
    "sg:city":"Huddersfield",
    "sg:classifiers":[
        {
            "category":"Professional",
            "subcategory":"Employment Agencies",
            "type":"Services"
        }
    ],
    "sg:phone":"+44 1484 664400",
    "sg:postcode":"HD7 7BN",
    "sg:province":"West Yorkshire",
    "sg:tags":[
        "recr",
        "hire",
        "driver"
    ],
    "wof:name":"Pennine Professional Drivers",
    "wof:placetype":"venue"
},
  "geometry": {"coordinates":[-1.78268,53.64695],"type":"Point"}
}