{
  "type": "Feature",
  "properties": {
    "iso:country":"GB",
    "sg:address":"18 Manor Road",
    "sg:city":"Aylesbury",
    "sg:classifiers":[
        {
            "category":"Health Services",
            "subcategory":"Podiatrist",
            "type":"Services"
        }
    ],
    "sg:postcode":"HP20 1JD",
    "sg:province":"Buckinghamshire",
    "sg:tags":[
        "podiatrists",
        "chiropodist"
    ],
    "wof:name":"R A Guy Srch",
    "wof:placetype":"venue"
},
  "geometry": {"coordinates":[-0.806514,51.822083],"type":"Point"}
}