{
  "type": "Feature",
  "properties": {
    "addr:full":"9 Beaufort Sq Chepstow Gloucestershire NP6 5EP",
    "addr:housenumber":"9",
    "addr:postcode":"np6 5ep",
    "addr:street":"Beaufort Sq",
    "iso:country":"GB",
    "sg:address":"9 Beaufort Sq",
    "sg:city":"Chepstow",
    "sg:classifiers":[
        {
            "category":"Food & Beverages",
            "subcategory":"Liquor & Beverages",
            "type":"Retail Goods"
        }
    ],
    "sg:phone":"+44 1291 626217",
    "sg:postcode":"NP6 5EP",
    "sg:province":"Gloucestershire",
    "sg:tags":[
        "beer",
        "spirit",
        "wines"
    ],
    "wof:name":"Victoria Wine",
    "wof:placetype":"venue"
},
  "geometry": {"coordinates":[-2.6748828888,51.6420097351],"type":"Point"}
}