{
  "type": "Feature",
  "properties": {
    "addr:full":"44 High St Barry The Vale of Glamorgan CF62 7EB",
    "addr:housenumber":"44",
    "addr:postcode":"cf62 7eb",
    "addr:street":"High St;Vale",
    "iso:country":"GB",
    "sg:address":"44 High St",
    "sg:city":"Barry",
    "sg:classifiers":[
        {
            "category":"Restaurant",
            "type":"Food & Drink"
        }
    ],
    "sg:phone":"+44 1446 746865",
    "sg:postcode":"CF62 7EB",
    "sg:province":"The Vale of Glamorgan",
    "sg:tags":[
        "indian"
    ],
    "wof:name":"Rajdoot Tandoori Restaurant",
    "wof:placetype":"venue"
},
  "geometry": {"coordinates":[-3.282118082,51.4008827209],"type":"Point"}
}