{
  "type": "Feature",
  "properties": {
    "iso:country":"GB",
    "sg:address":"Elder Way",
    "sg:city":"Chesterfield",
    "sg:classifiers":[
        {
            "category":"Place Of Worship",
            "type":"Public Place"
        }
    ],
    "sg:phone":"+44 1246 559407",
    "sg:postcode":"S40 1UR",
    "sg:province":"Derbyshire",
    "wof:name":"Elder Yard Unitarian Chapel",
    "wof:placetype":"venue"
},
  "geometry": {"coordinates":[-1.42784,53.23687],"type":"Point"}
}