{
  "type": "Feature",
  "properties": {
    "iso:country":"GB",
    "sg:address":"2282 Coventry Road, Sheldon",
    "sg:city":"Birmingham",
    "sg:classifiers":[
        {
            "category":"Shopping",
            "subcategory":"Stationery & Office Supplies",
            "type":"Retail Goods"
        }
    ],
    "sg:phone":"+44 121 742 6562",
    "sg:postcode":"B26 3JR",
    "sg:province":"West Midlands",
    "wof:name":"Osborne Office",
    "wof:placetype":"venue"
},
  "geometry": {"coordinates":[-1.776959,52.451614],"type":"Point"}
}