{
  "type": "Feature",
  "properties": {
    "addr:full":"Imberhorne Lane East Grinstead East Sussex RH19 1RG",
    "addr:postcode":"rh19 1rg",
    "addr:street":"Imberhorne Lane",
    "iso:country":"GB",
    "sg:address":"Imberhorne Lane",
    "sg:city":"East Grinstead",
    "sg:classifiers":[
        {
            "category":"Professional",
            "subcategory":"Engineering",
            "type":"Services"
        }
    ],
    "sg:phone":"+44 1342 300303",
    "sg:postcode":"RH19 1RG",
    "sg:province":"East Sussex",
    "sg:tags":[
        "precision",
        "engineer"
    ],
    "wof:name":"J D K Precision Ltd.",
    "wof:placetype":"venue"
},
  "geometry": {"coordinates":[-0.0332820006,51.1333885193],"type":"Point"}
}