{
  "type": "Feature",
  "properties": {
    "addr:full":"The Dovetails, Bridge-of-cally Blairgowrie Perth and Kinross PH10 7JL",
    "addr:postcode":"ph10 7jl",
    "iso:country":"GB",
    "sg:address":"The Dovetails, Bridge-of-cally",
    "sg:city":"Blairgowrie",
    "sg:classifiers":[
        {
            "category":"Manufacturing",
            "subcategory":"Wood Products",
            "type":"Manufacturing & Wholesale Goods"
        }
    ],
    "sg:postcode":"PH10 7JL",
    "sg:province":"Perth and Kinross",
    "sg:tags":[
        "maker",
        "cabinet"
    ],
    "wof:name":"Warren Workshops",
    "wof:placetype":"venue"
},
  "geometry": {"coordinates":[-3.4011230469,56.6491508484],"type":"Point"}
}