{
  "type": "Feature",
  "properties": {
    "addr:full":"Brighton Road, Salfords Redhill Surrey RH1 5ED",
    "addr:postcode":"rh1 5ed",
    "addr:street":"Brighton Road;Redhill",
    "iso:country":"GB",
    "sg:address":"Brighton Road, Salfords",
    "sg:city":"Redhill",
    "sg:classifiers":[
        {
            "category":"Autos & Motor Vehicles",
            "subcategory":"Automobile Sales",
            "type":"Retail Goods"
        }
    ],
    "sg:postcode":"RH1 5ED",
    "sg:province":"Surrey",
    "sg:tags":[
        "car"
    ],
    "wof:name":"Cronk Holdings (Garages) Ltd.",
    "wof:placetype":"venue"
},
  "geometry": {"coordinates":[-0.1657579988,51.1982498169],"type":"Point"}
}