{
  "type": "Feature",
  "properties": {
    "addr:full":"72 Yardley Road, Acocks Green Birmingham West Midlands B27 6LG",
    "addr:housenumber":"72",
    "addr:postcode":"b27 6lg",
    "addr:street":"Yardley Road",
    "iso:country":"GB",
    "sg:address":"72 Yardley Road, Acocks Green",
    "sg:city":"Birmingham",
    "sg:classifiers":[
        {
            "category":"Personal",
            "subcategory":"Tanning Parlor",
            "type":"Services"
        },
        {
            "category":"Personal",
            "subcategory":"Beauty Salon",
            "type":"Services"
        }
    ],
    "sg:phone":"+44 121 707 0711",
    "sg:postcode":"B27 6LG",
    "sg:province":"West Midlands",
    "sg:tags":[
        "sunbeds"
    ],
    "wof:name":"Sun & Health",
    "wof:placetype":"venue"
},
  "geometry": {"coordinates":[-1.818048,52.452061],"type":"Point"}
}