{
  "type": "Feature",
  "properties": {
    "addr:full":"5 Johnston Street Paisley Renfrewshire PA1 1XQ",
    "addr:housenumber":"5",
    "addr:postcode":"pa1 1xq",
    "addr:street":"Johnston Street",
    "iso:country":"GB",
    "sg:address":"5 Johnston Street",
    "sg:city":"Paisley",
    "sg:classifiers":[
        {
            "category":"Shopping",
            "subcategory":"News",
            "type":"Retail Goods"
        }
    ],
    "sg:phone":"+44 141 887 2308",
    "sg:postcode":"PA1 1XQ",
    "sg:province":"Renfrewshire",
    "sg:tags":[
        "newsagent"
    ],
    "wof:name":"B & I TRADING CO",
    "wof:placetype":"venue"
},
  "geometry": {"coordinates":[-4.4234538078,55.8425941467],"type":"Point"}
}