{
  "type": "Feature",
  "properties": {
    "addr:full":"White Chapel Road, Bream Lydney Gloucestershire GL15 6LR",
    "addr:postcode":"gl15 6lr",
    "addr:street":"White Chapel Road",
    "iso:country":"GB",
    "sg:address":"White Chapel Road, Bream",
    "sg:city":"Lydney",
    "sg:classifiers":[
        {
            "category":"Community Center",
            "type":"Public Place"
        },
        {
            "category":"Organizations",
            "subcategory":"Community Association",
            "type":"Services"
        }
    ],
    "sg:phone":"+44 1594 562985",
    "sg:postcode":"GL15 6LR",
    "sg:province":"Gloucestershire",
    "sg:tags":[
        "associations",
        "centre",
        "housing",
        "co-operatives",
        "trust",
        "societies"
    ],
    "wof:name":"THE EAVES CHRISTIAN CENTRE",
    "wof:placetype":"venue"
},
  "geometry": {"coordinates":[-2.5744891167,51.7505874634],"type":"Point"}
}