{
  "type": "Feature",
  "properties": {
    "iso:country":"GB",
    "sg:address":"92 Brookfield Road",
    "sg:city":"Bedford",
    "sg:classifiers":[
        {
            "category":"Social Services",
            "subcategory":"Retirement Home",
            "type":"Services"
        }
    ],
    "sg:phone":"+44 1234 344448",
    "sg:postcode":"MK41 9LJ",
    "sg:province":"Bedfordshire",
    "sg:tags":[
        "residential",
        "care"
    ],
    "wof:name":"Orchard House Residential Care Home",
    "wof:placetype":"venue"
},
  "geometry": {"coordinates":[-0.439532,52.14447],"type":"Point"}
}