{
  "type": "Feature",
  "properties": {
    "addr:full":"Swindon Road Marlborough Berkshire SN8 1TA",
    "addr:postcode":"sn8 1ta",
    "addr:street":"Swindon Road",
    "iso:country":"GB",
    "sg:address":"Swindon Road",
    "sg:city":"Marlborough",
    "sg:classifiers":[
        {
            "category":"Transit Center",
            "subcategory":"Passenger",
            "type":"Transportation"
        }
    ],
    "sg:postcode":"SN8 1TA",
    "sg:province":"Berkshire",
    "sg:tags":[
        "boarding",
        "kennel",
        "catteries"
    ],
    "wof:name":"Dukesmead Boarding Kennel & Cattery",
    "wof:placetype":"venue"
},
  "geometry": {"coordinates":[-1.7298890352,51.421333313],"type":"Point"}
}