{
  "type": "Feature",
  "properties": {
    "iso:country":"GB",
    "sg:address":"181 Cambuslang Road",
    "sg:city":"Glasgow",
    "sg:classifiers":[
        {
            "category":"Retail",
            "subcategory":"Auto Repair",
            "type":"Services"
        }
    ],
    "sg:phone":"+44 141 613 2077",
    "sg:postcode":"G73 1PX",
    "sg:province":"Glasgow City",
    "sg:tags":[
        "modification",
        "garage"
    ],
    "wof:name":"D C Tuning Centre",
    "wof:placetype":"venue"
},
  "geometry": {"coordinates":[-4.197028,55.829418],"type":"Point"}
}