{
  "type": "Feature",
  "properties": {
    "iso:country":"GB",
    "sg:address":"92 Station Road",
    "sg:city":"West Wickham",
    "sg:classifiers":[
        {
            "category":"Government",
            "subcategory":"Post Office",
            "type":"Public Place"
        }
    ],
    "sg:phone":"+44 20 8777 1959",
    "sg:postcode":"BR4 0QE",
    "sg:province":"Kent",
    "wof:name":"Post Office Counters Ltd.",
    "wof:placetype":"venue"
},
  "geometry": {"coordinates":[-0.014796,51.3760375977],"type":"Point"}
}