{
  "type": "Feature",
  "properties": {
    "addr:full":"17 Cedric Street Llanelli Carmarthenshire SA15 1LP",
    "addr:housenumber":"17",
    "addr:postcode":"sa15 1lp",
    "addr:street":"Cedric Street",
    "iso:country":"GB",
    "sg:address":"17 Cedric Street",
    "sg:city":"Llanelli",
    "sg:classifiers":[
        {
            "category":"Food & Beverages",
            "subcategory":"Meat & Fish",
            "type":"Retail Goods"
        }
    ],
    "sg:phone":"+44 1554 773075",
    "sg:postcode":"SA15 1LP",
    "sg:province":"Carmarthenshire",
    "sg:tags":[
        "chip"
    ],
    "wof:name":"Dill's Corner",
    "wof:placetype":"venue"
},
  "geometry": {"coordinates":[-4.1517009735,51.6796302795],"type":"Point"}
}