{
  "type": "Feature",
  "properties": {
    "addr:full":"42 Central Rd Morden Surrey SM4 5RT",
    "addr:housenumber":"42",
    "addr:postcode":"sm4 5rt",
    "addr:street":"Central Rd",
    "iso:country":"GB",
    "sg:address":"42 Central Rd",
    "sg:city":"Morden",
    "sg:classifiers":[
        {
            "category":"Health Services",
            "subcategory":"Doctor",
            "type":"Services"
        }
    ],
    "sg:phone":"+44 20 8648 9126",
    "sg:postcode":"SM4 5RT",
    "sg:province":"Surrey",
    "sg:tags":[
        "practitioners"
    ],
    "wof:name":"Jethwa, N K",
    "wof:placetype":"venue"
},
  "geometry": {"coordinates":[-0.189403,51.397793],"type":"Point"}
}