{
  "type": "Feature",
  "properties": {
    "addr:full":"Northfield Avenue West, Ealing London Greater London W13 9PR",
    "addr:postcode":"w13 9pr",
    "addr:street":"Northfield Avenue West",
    "iso:country":"GB",
    "sg:address":"Northfield Avenue West, Ealing",
    "sg:city":"London",
    "sg:classifiers":[
        {
            "category":"Place Of Worship",
            "type":"Public Place"
        }
    ],
    "sg:phone":"+44 20 8566 2182",
    "sg:postcode":"W13 9PR",
    "sg:province":"Greater London",
    "wof:name":"Kingsdown Methodist Church Hall",
    "wof:placetype":"venue"
},
  "geometry": {"coordinates":[-0.319619,51.50605],"type":"Point"}
}