{
  "type": "Feature",
  "properties": {
    "iso:country":"GB",
    "sg:address":"Burton Rd, Heckington",
    "sg:city":"Sleaford",
    "sg:classifiers":[
        {
            "category":"Sports & Exercise",
            "subcategory":"Stables",
            "type":"Entertainment"
        }
    ],
    "sg:phone":"+44 1529 461887",
    "sg:postcode":"NG34 9QS",
    "sg:province":"Lincolnshire",
    "sg:tags":[
        "education",
        "equestrian"
    ],
    "wof:name":"Mill View Farm",
    "wof:placetype":"venue"
},
  "geometry": {"coordinates":[-0.3399649858,52.9834365845],"type":"Point"}
}