{
  "type": "Feature",
  "properties": {
    "addr:full":"140 Wightman Rd Hornsey Greater London N8 0BD",
    "addr:housenumber":"140",
    "addr:postcode":"n8 0bd",
    "addr:street":"Wightman Rd",
    "iso:country":"GB",
    "sg:address":"140 Wightman Rd",
    "sg:city":"Hornsey",
    "sg:classifiers":[
        {
            "category":"Retail",
            "subcategory":"Animal Services",
            "type":"Services"
        }
    ],
    "sg:phone":"+44 20 8348 1273",
    "sg:postcode":"N8 0BD",
    "sg:province":"Greater London",
    "sg:tags":[
        "pet"
    ],
    "wof:name":"Debora's Cat Sitting Service",
    "wof:placetype":"venue"
},
  "geometry": {"coordinates":[-0.1058000028,51.581073761],"type":"Point"}
}