{
  "type": "Feature",
  "properties": {
    "addr:full":"Unit 10 The Vanguard Centre, Sir William Lyons Road Coventry Warwickshire CV4 7EZ",
    "addr:housenumber":"unit 10",
    "addr:postcode":"cv4 7ez",
    "addr:street":"The;Lyons Road",
    "iso:country":"GB",
    "sg:address":"Unit 10 The Vanguard Centre, Sir William Lyons Road",
    "sg:city":"Coventry",
    "sg:classifiers":[
        {
            "category":"Professional",
            "subcategory":"Engineering",
            "type":"Services"
        }
    ],
    "sg:phone":"+44 24 7632 3600",
    "sg:postcode":"CV4 7EZ",
    "sg:province":"Warwickshire",
    "sg:tags":[
        "consulting",
        "engineer"
    ],
    "wof:name":"Altair Engineering Ltd.",
    "wof:placetype":"venue"
},
  "geometry": {"coordinates":[-1.5579940081,52.3859558105],"type":"Point"}
}