{
  "type": "Feature",
  "properties": {
    "iso:country":"GB",
    "sg:address":"770 Barking Road, Plaistow",
    "sg:city":"London",
    "sg:classifiers":[
        {
            "category":"Fast Food",
            "type":"Food & Drink"
        }
    ],
    "sg:phone":"+44 20 8472 2614",
    "sg:postcode":"E13 9PJ",
    "sg:province":"Greater London",
    "sg:tags":[
        "away",
        "meal",
        "outlet",
        "take"
    ],
    "wof:name":"Oriental Kitchen",
    "wof:placetype":"venue"
},
  "geometry": {"coordinates":[0.0367030017,51.5300254822],"type":"Point"}
}