{
  "type": "Feature",
  "properties": {
    "addr:full":"85 Moorhill Crescent, Newton Mearns Glasgow East Ayrshire G77 6BQ",
    "addr:housenumber":"85",
    "addr:postcode":"g77 6bq",
    "addr:street":"Moorhill Crescent",
    "iso:country":"GB",
    "sg:address":"85 Moorhill Crescent, Newton Mearns",
    "sg:city":"Glasgow",
    "sg:classifiers":[
        {
            "category":"Building & Trades",
            "subcategory":"Landscaping Services",
            "type":"Services"
        }
    ],
    "sg:postcode":"G77 6BQ",
    "sg:province":"East Ayrshire",
    "sg:tags":[
        "gardening"
    ],
    "wof:name":"Steven Spellacy",
    "wof:placetype":"venue"
},
  "geometry": {"coordinates":[-4.3388900757,55.7702827454],"type":"Point"}
}