{
  "type": "Feature",
  "properties": {
    "iso:country":"GB",
    "sg:address":"42 Dorking Road, Bookham",
    "sg:city":"Leatherhead",
    "sg:classifiers":[
        {
            "category":"Building & Trades",
            "subcategory":"Construction",
            "type":"Services"
        }
    ],
    "sg:postcode":"KT23 4LX",
    "sg:province":"Surrey",
    "sg:tags":[
        "decorator",
        "painter"
    ],
    "wof:name":"E Palmer",
    "wof:placetype":"venue"
},
  "geometry": {"coordinates":[-0.3696480095,51.2750167847],"type":"Point"}
}