{
  "type": "Feature",
  "properties": {
    "addr:full":"Garden Ct, Hervines Rd Amersham Buckinghamshire HP6 5HS",
    "addr:postcode":"hp6 5hs",
    "addr:street":"Garden Ct Hervines Rd",
    "iso:country":"GB",
    "sg:address":"Garden Ct, Hervines Rd",
    "sg:city":"Amersham",
    "sg:classifiers":[
        {
            "category":"Health Services",
            "subcategory":"Dentist",
            "type":"Services"
        }
    ],
    "sg:phone":"+44 1494 726267",
    "sg:postcode":"HP6 5HS",
    "sg:province":"Buckinghamshire",
    "wof:name":"Patterson C.S. Dental Surgery",
    "wof:placetype":"venue"
},
  "geometry": {"coordinates":[-0.6084290147,51.6776008606],"type":"Point"}
}