{
  "type": "Feature",
  "properties": {
    "addr:full":"Cranfield Road, North Crawley Newport Pagnell Buckinghamshire MK16 9HP",
    "addr:postcode":"mk16 9hp",
    "addr:street":"Cranfield Road",
    "iso:country":"GB",
    "sg:address":"Cranfield Road, North Crawley",
    "sg:city":"Newport Pagnell",
    "sg:classifiers":[
        {
            "category":"Sports & Exercise",
            "subcategory":"Stables",
            "type":"Entertainment"
        }
    ],
    "sg:phone":"+44 1234 751200",
    "sg:postcode":"MK16 9HP",
    "sg:province":"Buckinghamshire",
    "sg:tags":[
        "education",
        "equestrian"
    ],
    "wof:name":"Ringcroft Farm Livery Yard",
    "wof:placetype":"venue"
},
  "geometry": {"coordinates":[-0.599279,52.103226],"type":"Point"}
}