{
  "type": "Feature",
  "properties": {
    "addr:full":"183 London Hertfordshire HP3 9SQ",
    "addr:housenumber":"183",
    "addr:postcode":"hp3 9sq",
    "addr:street":"London",
    "iso:country":"GB",
    "sg:address":"183",
    "sg:city":"London",
    "sg:classifiers":[
        {
            "category":"Autos & Motor Vehicles",
            "subcategory":"Automobile Sales",
            "type":"Retail Goods"
        }
    ],
    "sg:postcode":"HP3 9SQ",
    "sg:province":"Hertfordshire",
    "sg:tags":[
        "commercial"
    ],
    "wof:name":"Sunshine Cab Co  Ltd",
    "wof:placetype":"venue"
},
  "geometry": {"coordinates":[-0.470216,51.737701],"type":"Point"}
}