{
  "type": "Feature",
  "properties": {
    "iso:country":"GB",
    "sg:address":"Unit 14 Eastern Av",
    "sg:city":"Port Talbot",
    "sg:classifiers":[
        {
            "category":"Bus Charters",
            "type":"Transportation"
        }
    ],
    "sg:phone":"+44 1639 850338",
    "sg:postcode":"SA13 3PB",
    "sg:province":"Neath Port Talbot",
    "sg:tags":[
        "hire",
        "coach"
    ],
    "wof:name":"Wilkins Bros (Cymmer) Ltd",
    "wof:placetype":"venue"
},
  "geometry": {"coordinates":[-3.638064,51.647251],"type":"Point"}
}