{
  "type": "Feature",
  "properties": {
    "addr:full":"25 Oxford St London Greater London W1D 2AA",
    "addr:housenumber":"25",
    "addr:postcode":"w1d 2aa",
    "addr:street":"Oxford St",
    "iso:country":"GB",
    "sg:address":"25 Oxford St",
    "sg:city":"London",
    "sg:classifiers":[
        {
            "category":"Travel",
            "subcategory":"Travel Agent",
            "type":"Entertainment"
        }
    ],
    "sg:phone":"+44 20 7287 2287",
    "sg:postcode":"W1D 2AA",
    "sg:province":"Greater London",
    "wof:name":"Comet Travel (Oxford Street) Ltd",
    "wof:placetype":"venue"
},
  "geometry": {"coordinates":[-0.1327289939,51.516254425],"type":"Point"}
}