{
  "type": "Feature",
  "properties": {
    "addr:full":"298 Yardley Wood Rd, Moseley Birmingham West Midlands B13 9JW",
    "addr:housenumber":"298",
    "addr:postcode":"b13 9jw",
    "addr:street":"Yardley Wood Rd",
    "iso:country":"GB",
    "sg:address":"298 Yardley Wood Rd, Moseley",
    "sg:city":"Birmingham",
    "sg:classifiers":[
        {
            "category":"Restaurant",
            "type":"Food & Drink"
        }
    ],
    "sg:phone":"+44 121 442 0911",
    "sg:postcode":"B13 9JW",
    "sg:province":"West Midlands",
    "wof:name":"The Covered Wagon",
    "wof:placetype":"venue"
},
  "geometry": {"coordinates":[-1.8708959818,52.4385871887],"type":"Point"}
}