{
  "type": "Feature",
  "properties": {
    "iso:country":"GB",
    "sg:address":"26 Overton Road",
    "sg:city":"Leicester",
    "sg:classifiers":[
        {
            "category":"Building & Trades",
            "subcategory":"Construction",
            "type":"Services"
        },
        {
            "category":"Home & Garden",
            "subcategory":"Carpets & Floor Coverings",
            "type":"Retail Goods"
        }
    ],
    "sg:phone":"+44 116 276 0723",
    "sg:postcode":"LE5 0JA",
    "sg:province":"Leicestershire",
    "sg:tags":[
        "resurfacing",
        "laying",
        "refinishing",
        "flooring"
    ],
    "wof:name":"J & S Flooring",
    "wof:placetype":"venue"
},
  "geometry": {"coordinates":[-1.102173,52.64312],"type":"Point"}
}