{
  "type": "Feature",
  "properties": {
    "addr:full":"9 Church Walk, Oaterham Caterham Surrey CR3 6RT",
    "addr:housenumber":"9",
    "addr:postcode":"cr3 6rt",
    "addr:street":"Church Walk Oaterham",
    "iso:country":"GB",
    "sg:address":"9 Church Walk, Oaterham",
    "sg:city":"Caterham",
    "sg:classifiers":[
        {
            "category":"Shopping",
            "subcategory":"Pharmacy",
            "type":"Retail Goods"
        }
    ],
    "sg:phone":"+44 1883 347920",
    "sg:postcode":"CR3 6RT",
    "sg:province":"Surrey",
    "sg:tags":[
        "store",
        "drug"
    ],
    "wof:name":"Superdrug Stores Plc",
    "wof:placetype":"venue"
},
  "geometry": {"coordinates":[-0.076936,51.281578],"type":"Point"}
}