{
  "type": "Feature",
  "properties": {
    "addr:full":"Unit 5 Centre One, Old Sarum Park, Lysander Way Salisbury Hampshire SP4 6BU",
    "addr:housenumber":"unit 5 centre",
    "addr:postcode":"sp4 6bu",
    "addr:street":"Lysander Way",
    "iso:country":"GB",
    "sg:address":"Unit 5 Centre One, Old Sarum Park, Lysander Way",
    "sg:city":"Salisbury",
    "sg:classifiers":[
        {
            "category":"Shopping",
            "type":"Retail Goods"
        }
    ],
    "sg:phone":"+44 1722 410203",
    "sg:postcode":"SP4 6BU",
    "sg:province":"Hampshire",
    "sg:tags":[
        "part",
        "accessory"
    ],
    "wof:name":"Autotorano (Alloy Wheels) Ltd",
    "wof:placetype":"venue"
},
  "geometry": {"coordinates":[-1.7819900513,51.1022987366],"type":"Point"}
}