{
  "type": "Feature",
  "properties": {
    "addr:full":"7a Yspitty Road Llanelli Carmarthenshire SA14 9TD",
    "addr:housenumber":"7a",
    "addr:postcode":"sa14 9td",
    "addr:street":"Yspitty Road",
    "iso:country":"GB",
    "sg:address":"7a Yspitty Road",
    "sg:city":"Llanelli",
    "sg:classifiers":[
        {
            "category":"Manufacturing",
            "subcategory":"Motor Vehicles & Parts",
            "type":"Manufacturing & Wholesale Goods"
        },
        {
            "category":"Autos & Motor Vehicles",
            "subcategory":"Auto Supplies",
            "type":"Retail Goods"
        }
    ],
    "sg:phone":"+44 1554 773102",
    "sg:postcode":"SA14 9TD",
    "sg:province":"Carmarthenshire",
    "sg:tags":[
        "electric",
        "servicing",
        "sales"
    ],
    "wof:name":"Rees Electrical Repairs",
    "wof:placetype":"venue"
},
  "geometry": {"coordinates":[-4.0904741287,51.6668243408],"type":"Point"}
}