{
  "type": "Feature",
  "properties": {
    "addr:full":"Holbeach St Marks Spalding Cambridgeshire PE12 8DZ",
    "addr:postcode":"pe12 8dz",
    "addr:street":"Holbeach;Spalding",
    "iso:country":"GB",
    "sg:address":"Holbeach St Marks",
    "sg:city":"Spalding",
    "sg:classifiers":[
        {
            "category":"Education",
            "subcategory":"School",
            "type":"Public Place"
        },
        {
            "category":"Government",
            "subcategory":"Office",
            "type":"Public Place"
        }
    ],
    "sg:phone":"+44 1406 701266",
    "sg:postcode":"PE12 8DZ",
    "sg:province":"Cambridgeshire",
    "sg:tags":[
        "local",
        "authority"
    ],
    "wof:name":"Holbeach St Mark's C Of E Primary School",
    "wof:placetype":"venue"
},
  "geometry": {"coordinates":[0.035504,52.860893],"type":"Point"}
}