{
  "type": "Feature",
  "properties": {
    "iso:country":"GB",
    "sg:address":"The Smithy, Llanfor",
    "sg:city":"Bala",
    "sg:classifiers":[
        {
            "category":"Real Estate",
            "subcategory":"Architect",
            "type":"Services"
        }
    ],
    "sg:phone":"+44 1678 520362",
    "sg:postcode":"LL23 7DW",
    "sg:province":"Gwynedd",
    "wof:name":"R Lloyd & Son",
    "wof:placetype":"venue"
},
  "geometry": {"coordinates":[-3.595467,52.912148],"type":"Point"}
}