{
  "type": "Feature",
  "properties": {
    "iso:country":"GB",
    "sg:address":"Clun Rd",
    "sg:city":"Littlehampton",
    "sg:classifiers":[
        {
            "category":"Place Of Worship",
            "type":"Public Place"
        }
    ],
    "sg:phone":"+44 1903 731796",
    "sg:postcode":"BN17 7DZ",
    "sg:province":"West Sussex",
    "wof:name":"Wickbourne Chapel",
    "wof:placetype":"venue"
},
  "geometry": {"coordinates":[-0.5546690226,50.8184547424],"type":"Point"}
}