{
  "type": "Feature",
  "properties": {
    "addr:full":"Unit 3 Warstone Ct, Warstone La Birmingham West Midlands B18 6JQ",
    "addr:housenumber":"unit 3",
    "addr:postcode":"b18 6jq",
    "addr:street":"Warstone Ct Warstone La Birmingham",
    "iso:country":"GB",
    "sg:address":"Unit 3 Warstone Ct, Warstone La",
    "sg:city":"Birmingham",
    "sg:classifiers":[
        {
            "category":"Organizations",
            "subcategory":"Membership Organization",
            "type":"Services"
        }
    ],
    "sg:phone":"+44 121 242 4545",
    "sg:postcode":"B18 6JQ",
    "sg:province":"West Midlands",
    "sg:tags":[
        "club"
    ],
    "wof:name":"Eric Knowles Antiques Club",
    "wof:placetype":"venue"
},
  "geometry": {"coordinates":[-1.915169,52.487068],"type":"Point"}
}