{
  "type": "Feature",
  "properties": {
    "addr:full":"164 Windermere Avenue Southampton Hampshire SO16 9GA",
    "addr:housenumber":"164",
    "addr:postcode":"so16 9ga",
    "addr:street":"Windermere Avenue",
    "iso:country":"GB",
    "sg:address":"164 Windermere Avenue",
    "sg:city":"Southampton",
    "sg:classifiers":[
        {
            "category":"Shopping",
            "subcategory":"News",
            "type":"Retail Goods"
        }
    ],
    "sg:phone":"+44 23 8077 6280",
    "sg:postcode":"SO16 9GA",
    "sg:province":"Hampshire",
    "sg:tags":[
        "newsagent"
    ],
    "wof:name":"Thompson News",
    "wof:placetype":"venue"
},
  "geometry": {"coordinates":[-1.4587659836,50.9303131104],"type":"Point"}
}