{
  "type": "Feature",
  "properties": {
    "addr:full":"6 St Anthonys Drive Newcastle Staffordshire ST5 2JE",
    "addr:housenumber":"6",
    "addr:postcode":"st5 2je",
    "addr:street":"St Anthonys Drive",
    "iso:country":"GB",
    "sg:address":"6 St Anthonys Drive",
    "sg:city":"Newcastle",
    "sg:classifiers":[
        {
            "category":"Professional",
            "subcategory":"Management & Consulting",
            "type":"Services"
        }
    ],
    "sg:postcode":"ST5 2JE",
    "sg:province":"Staffordshire",
    "sg:tags":[
        "consultant",
        "business"
    ],
    "wof:name":"J. Topping Site Consultants Ltd",
    "wof:placetype":"venue"
},
  "geometry": {"coordinates":[-2.2400250435,53.0029563904],"type":"Point"}
}