{
  "type": "Feature",
  "properties": {
    "iso:country":"GB",
    "sg:address":"15 High St",
    "sg:city":"Bath",
    "sg:classifiers":[
        {
            "category":"Banks & Credit Unions",
            "subcategory":"Bank",
            "type":"Services"
        }
    ],
    "sg:phone":"+44 1225 443443",
    "sg:postcode":"BA1 5AH",
    "sg:province":"Bath and North East Somerset",
    "wof:name":"NatWest",
    "wof:placetype":"venue"
},
  "geometry": {"coordinates":[-2.359318018,51.3819694519],"type":"Point"}
}