{
  "type": "Feature",
  "properties": {
    "addr:full":"4 The Crescent, Croxley Grn Rickmansworth Hertfordshire WD3 3DU",
    "addr:housenumber":"4",
    "addr:postcode":"wd3 3du",
    "addr:street":"The Crescent Croxley Grn",
    "iso:country":"GB",
    "sg:address":"4 The Crescent, Croxley Grn",
    "sg:city":"Rickmansworth",
    "sg:classifiers":[
        {
            "category":"Manufacturing",
            "subcategory":"Signs",
            "type":"Manufacturing & Wholesale Goods"
        }
    ],
    "sg:phone":"+44 1923 770504",
    "sg:postcode":"WD3 3DU",
    "sg:province":"Hertfordshire",
    "sg:tags":[
        "writer"
    ],
    "wof:name":"Michael Woodward",
    "wof:placetype":"venue"
},
  "geometry": {"coordinates":[-0.4449949861,51.6470375061],"type":"Point"}
}