{
  "type": "Feature",
  "properties": {
    "iso:country":"GB",
    "sg:address":"6 Dene View, Luddendenfoot",
    "sg:city":"Halifax",
    "sg:classifiers":[
        {
            "category":"Organizations",
            "subcategory":"Non-profit Organization",
            "type":"Services"
        }
    ],
    "sg:postcode":"HX2 6PB",
    "sg:province":"West Yorkshire",
    "sg:tags":[
        "organisation",
        "voluntary",
        "charity"
    ],
    "wof:name":"Muscular Dystrophy Group",
    "wof:placetype":"venue"
},
  "geometry": {"coordinates":[-1.942004,53.727112],"type":"Point"}
}