{
  "type": "Feature",
  "properties": {
    "addr:full":"14 Dragon Dr Prescot Cheshire L35 3QW",
    "addr:housenumber":"14",
    "addr:postcode":"l35 3qw",
    "addr:street":"Dragon",
    "iso:country":"GB",
    "sg:address":"14 Dragon Dr",
    "sg:city":"Prescot",
    "sg:classifiers":[
        {
            "category":"Home & Garden",
            "subcategory":"Carpets & Floor Coverings",
            "type":"Retail Goods"
        }
    ],
    "sg:postcode":"L35 3QW",
    "sg:province":"Cheshire",
    "sg:tags":[
        "carpets",
        "rug",
        "matting"
    ],
    "wof:name":"Whiston Carpet Centre",
    "wof:placetype":"venue"
},
  "geometry": {"coordinates":[-2.797629118,53.4151115417],"type":"Point"}
}