{
  "type": "Feature",
  "properties": {
    "addr:full":"36 High Street, Bridge Canterbury Kent CT4 5JZ",
    "addr:housenumber":"36",
    "addr:postcode":"ct4 5jz",
    "addr:street":"High Street Bridge",
    "iso:country":"GB",
    "sg:address":"36 High Street, Bridge",
    "sg:city":"Canterbury",
    "sg:classifiers":[
        {
            "category":"Retail",
            "subcategory":"Auto Repair",
            "type":"Services"
        }
    ],
    "sg:phone":"+44 1227 830348",
    "sg:postcode":"CT4 5JZ",
    "sg:province":"Kent",
    "sg:tags":[
        "modification",
        "garage"
    ],
    "wof:name":"Rogers Garage",
    "wof:placetype":"venue"
},
  "geometry": {"coordinates":[1.124412,51.246731],"type":"Point"}
}