{
  "type": "Feature",
  "properties": {
    "iso:country":"GB",
    "sg:address":"24 Hulme Ct, Linby St",
    "sg:city":"Manchester",
    "sg:classifiers":[
        {
            "category":"Professional",
            "subcategory":"Computer Services",
            "type":"Services"
        }
    ],
    "sg:phone":"+44 161 226 2912",
    "sg:postcode":"M15 5AR",
    "sg:province":"Cheshire",
    "sg:tags":[
        "system",
        "software"
    ],
    "wof:name":"Savant Programming Services Ltd",
    "wof:placetype":"venue"
},
  "geometry": {"coordinates":[-2.25768,53.47057],"type":"Point"}
}