{
  "type": "Feature",
  "properties": {
    "addr:full":"Craig Arden Studio, Buchanan Castle Glasgow Argyll and Bute G63 0HX",
    "addr:postcode":"g63 0hx",
    "addr:street":"Craig",
    "iso:country":"GB",
    "sg:address":"Craig Arden Studio, Buchanan Castle",
    "sg:city":"Glasgow",
    "sg:classifiers":[
        {
            "category":"Real Estate",
            "subcategory":"Architect",
            "type":"Services"
        }
    ],
    "sg:phone":"+44 1360 660681",
    "sg:postcode":"G63 0HX",
    "sg:province":"Argyll and Bute",
    "wof:name":"Alan Dunlop",
    "wof:placetype":"venue"
},
  "geometry": {"coordinates":[-4.3747692108,56.0735282898],"type":"Point"}
}