{
  "type": "Feature",
  "properties": {
    "iso:country":"GB",
    "sg:address":"37 Auckland Road",
    "sg:city":"Reading",
    "sg:classifiers":[
        {
            "category":"Bars & Pubs",
            "type":"Food & Drink"
        }
    ],
    "sg:phone":"+44 118 926 2226",
    "sg:postcode":"RG6 1NY",
    "sg:province":"Berkshire",
    "sg:tags":[
        "pubs",
        "inn"
    ],
    "wof:name":"The Roebuck Public House",
    "wof:placetype":"venue"
},
  "geometry": {"coordinates":[-0.932806015,51.4478645325],"type":"Point"}
}