{
  "type": "Feature",
  "properties": {
    "iso:country":"GB",
    "sg:address":", Cilmery",
    "sg:city":"Builth Wells",
    "sg:classifiers":[
        {
            "category":"Bars & Pubs",
            "type":"Food & Drink"
        }
    ],
    "sg:phone":"+44 1982 552694",
    "sg:postcode":"LD2 3NU",
    "sg:province":"Powys",
    "sg:tags":[
        "pubs",
        "inn"
    ],
    "wof:name":"Prince Llewelyn Inn",
    "wof:placetype":"venue"
},
  "geometry": {"coordinates":[-3.4030599594,52.148273468],"type":"Point"}
}