{
  "type": "Feature",
  "properties": {
    "addr:full":"7 Court Farm Lane, Branston Burton On Trent Derbyshire DE14 3HA",
    "addr:housenumber":"7",
    "addr:postcode":"de14 3ha",
    "addr:street":"Court Farm Lane",
    "iso:country":"GB",
    "sg:address":"7 Court Farm Lane, Branston",
    "sg:city":"Burton On Trent",
    "sg:classifiers":[
        {
            "category":"Home & Garden",
            "subcategory":"Building Materials",
            "type":"Retail Goods"
        }
    ],
    "sg:phone":"+44 1283 535303",
    "sg:postcode":"DE14 3HA",
    "sg:province":"Derbyshire",
    "sg:tags":[
        "roofing",
        "rafter",
        "beams"
    ],
    "wof:name":"Branston Spindles",
    "wof:placetype":"venue"
},
  "geometry": {"coordinates":[-1.6737769842,52.7873191833],"type":"Point"}
}