{
  "type": "Feature",
  "properties": {
    "iso:country":"GB",
    "sg:address":"220 Camden High Street",
    "sg:city":"London",
    "sg:classifiers":[
        {
            "category":"Shopping",
            "subcategory":"Clothing, Apparel, & Fashions",
            "type":"Retail Goods"
        }
    ],
    "sg:postcode":"NW1 8QR",
    "sg:province":"Greater London",
    "sg:tags":[
        "t-shirt",
        "shop"
    ],
    "wof:name":"Tipsy",
    "wof:placetype":"venue"
},
  "geometry": {"coordinates":[-0.14388,51.540657],"type":"Point"}
}