{
  "type": "Feature",
  "properties": {
    "addr:full":"6 Southwestern Terrace Yeovil Somerset BA20 1NB",
    "addr:housenumber":"6",
    "addr:postcode":"ba20 1nb",
    "addr:street":"Southwestern Terrace",
    "iso:country":"GB",
    "sg:address":"6 Southwestern Terrace",
    "sg:city":"Yeovil",
    "sg:classifiers":[
        {
            "category":"Personal",
            "subcategory":"Beauty Salon",
            "type":"Services"
        }
    ],
    "sg:phone":"+44 1935 410946",
    "sg:postcode":"BA20 1NB",
    "sg:province":"Somerset",
    "sg:tags":[
        "unisex",
        "hairdresser"
    ],
    "wof:name":"The Yeovil Hair & Beauty Clinic",
    "wof:placetype":"venue"
},
  "geometry": {"coordinates":[-2.624974966,50.9413032532],"type":"Point"}
}