{
  "type": "Feature",
  "properties": {
    "addr:full":"42 Narborough Rd Leicester Leicestershire LE3 0BQ",
    "addr:housenumber":"42",
    "addr:postcode":"le3 0bq",
    "addr:street":"Narborough Rd",
    "iso:country":"GB",
    "sg:address":"42 Narborough Rd",
    "sg:city":"Leicester",
    "sg:classifiers":[
        {
            "category":"Shopping",
            "subcategory":"Used Merchandise",
            "type":"Retail Goods"
        }
    ],
    "sg:phone":"+44 116 233 8344",
    "sg:postcode":"LE3 0BQ",
    "sg:province":"Leicestershire",
    "sg:tags":[
        "shop",
        "second-hand"
    ],
    "wof:name":"Secondhand Stuff",
    "wof:placetype":"venue"
},
  "geometry": {"coordinates":[-1.1479250193,52.630241394],"type":"Point"}
}