{
  "type": "Feature",
  "properties": {
    "iso:country":"GB",
    "sg:address":"Treadwell House, High St, Bloxham",
    "sg:city":"Banbury",
    "sg:classifiers":[
        {
            "category":"Banks & Credit Unions",
            "subcategory":"Financial Services",
            "type":"Services"
        }
    ],
    "sg:phone":"+44 1295 722072",
    "sg:postcode":"OX15 4LT",
    "sg:province":"Oxfordshire",
    "sg:tags":[
        "consultant"
    ],
    "wof:name":"Chase Financial",
    "wof:placetype":"venue"
},
  "geometry": {"coordinates":[-1.3743590117,52.0200042725],"type":"Point"}
}