{
  "type": "Feature",
  "properties": {
    "addr:full":"797 Wandsworth Rd South Lambeth Greater London SW8 3JH",
    "addr:housenumber":"797",
    "addr:postcode":"sw8 3jh",
    "addr:street":"Wandsworth Rd",
    "iso:country":"GB",
    "sg:address":"797 Wandsworth Rd",
    "sg:city":"South Lambeth",
    "sg:classifiers":[
        {
            "category":"Cinema",
            "subcategory":"Movie Rental",
            "type":"Entertainment"
        }
    ],
    "sg:phone":"+44 20 7564 6777",
    "sg:postcode":"SW8 3JH",
    "sg:province":"Greater London",
    "sg:tags":[
        "video",
        "library"
    ],
    "wof:name":"Ol'top Entertainment Centre",
    "wof:placetype":"venue"
},
  "geometry": {"coordinates":[-0.1482229978,51.4665908813],"type":"Point"}
}