{
  "type": "Feature",
  "properties": {
    "iso:country":"GB",
    "sg:address":"12 Trearddur Rd, Trearddur Bay",
    "sg:city":"Holyhead",
    "sg:classifiers":[
        {
            "category":"Freight",
            "type":"Transportation"
        },
        {
            "category":"Professional",
            "subcategory":"Business Services",
            "type":"Services"
        }
    ],
    "sg:phone":"+44 1407 860931",
    "sg:postcode":"LL65 2UE",
    "sg:province":"Isle of Anglesey",
    "sg:tags":[
        "import",
        "export",
        "agent",
        "forwarders"
    ],
    "wof:name":"Holyhead Port Services",
    "wof:placetype":"venue"
},
  "geometry": {"coordinates":[-4.616924,53.283653],"type":"Point"}
}