{
  "type": "Feature",
  "properties": {
    "addr:full":"New Central Garage, Exford Minehead Somerset TA24 7PY",
    "addr:postcode":"ta24 7py",
    "iso:country":"GB",
    "sg:address":"New Central Garage, Exford",
    "sg:city":"Minehead",
    "sg:classifiers":[
        {
            "category":"Professional",
            "subcategory":"Engineering",
            "type":"Services"
        }
    ],
    "sg:postcode":"TA24 7PY",
    "sg:province":"Somerset",
    "wof:name":"Dunkery Services",
    "wof:placetype":"venue"
},
  "geometry": {"coordinates":[-3.6408429146,51.1330490112],"type":"Point"}
}