{
  "type": "Feature",
  "properties": {
    "addr:full":"119 George Lane London Greater London E18 1AN",
    "addr:housenumber":"119",
    "addr:postcode":"e18 1an",
    "addr:street":"George Lane",
    "iso:country":"GB",
    "sg:address":"119 George Lane",
    "sg:city":"London",
    "sg:classifiers":[
        {
            "category":"Personal",
            "subcategory":"Barber",
            "type":"Services"
        }
    ],
    "sg:phone":"+44 20 8518 8363",
    "sg:postcode":"E18 1AN",
    "sg:province":"Greater London",
    "sg:tags":[
        "men's",
        "hairdresser"
    ],
    "wof:name":"Cut for Gents",
    "wof:placetype":"venue"
},
  "geometry": {"coordinates":[0.026304,51.592861],"type":"Point"}
}