{
  "type": "Feature",
  "properties": {
    "addr:full":"Units 4b & 5b, Gatehouse Trading Estate Lichfield Road, Brownhills Walsall Staffordshire WS8 6JZ",
    "addr:housenumber":"units;estate",
    "addr:postcode":"ws8 6jz",
    "addr:street":"&;Trading;Lichfield Road",
    "iso:country":"GB",
    "sg:address":"Units 4b & 5b, Gatehouse Trading Estate Lichfield Road, Brownhills",
    "sg:city":"Walsall",
    "sg:classifiers":[
        {
            "category":"Wholesale",
            "subcategory":"Meat",
            "type":"Manufacturing & Wholesale Goods"
        }
    ],
    "sg:phone":"+44 1543 452796",
    "sg:postcode":"WS8 6JZ",
    "sg:province":"Staffordshire",
    "sg:tags":[
        "-"
    ],
    "wof:name":"A E Poxon",
    "wof:placetype":"venue"
},
  "geometry": {"coordinates":[-1.92019,52.652359],"type":"Point"}
}