{
  "type": "Feature",
  "properties": {
    "addr:full":"Cavendish Court, Lawkholme Lane Keighley West Yorkshire BD21 3DY",
    "addr:postcode":"bd21 3dy",
    "addr:street":"Cavendish;Lawkholme Lane",
    "iso:country":"GB",
    "sg:address":"Cavendish Court, Lawkholme Lane",
    "sg:city":"Keighley",
    "sg:classifiers":[
        {
            "category":"Home & Garden",
            "subcategory":"Home Furnishings",
            "type":"Retail Goods"
        }
    ],
    "sg:phone":"+44 1535 691919",
    "sg:postcode":"BD21 3DY",
    "sg:province":"West Yorkshire",
    "sg:tags":[
        "blind",
        "curtain",
        "fitting"
    ],
    "wof:name":"Manor Blinds & Curtains",
    "wof:placetype":"venue"
},
  "geometry": {"coordinates":[-1.903274,53.874416],"type":"Point"}
}