{
  "type": "Feature",
  "properties": {
    "iso:country":"GB",
    "sg:address":"55 High Street, Brant Broughton",
    "sg:city":"Lincoln",
    "sg:classifiers":[
        {
            "category":"Government",
            "subcategory":"Post Office",
            "type":"Public Place"
        }
    ],
    "sg:phone":"+44 1400 272289",
    "sg:postcode":"LN5 0SL",
    "sg:province":"Lincolnshire",
    "wof:name":"Brant Broughton Post Office",
    "wof:placetype":"venue"
},
  "geometry": {"coordinates":[-0.633096993,53.0769577026],"type":"Point"}
}