{
  "type": "Feature",
  "properties": {
    "addr:full":"Bashley Road, Bashley New Milton Hampshire BH25 5RY",
    "addr:postcode":"bh25 5ry",
    "addr:street":"Bashley Road",
    "iso:country":"GB",
    "sg:address":"Bashley Road, Bashley",
    "sg:city":"New Milton",
    "sg:classifiers":[
        {
            "category":"Building & Trades",
            "subcategory":"Landscaping Services",
            "type":"Services"
        }
    ],
    "sg:phone":"+44 1425 614210",
    "sg:postcode":"BH25 5RY",
    "sg:province":"Hampshire",
    "sg:tags":[
        "landscape",
        "contractor"
    ],
    "wof:name":"Redcliffe Gardners",
    "wof:placetype":"venue"
},
  "geometry": {"coordinates":[-1.6579890251,50.7721977234],"type":"Point"}
}