{
  "type": "Feature",
  "properties": {
    "iso:country":"GB",
    "sg:address":"Pound Lane",
    "sg:city":"Teignmouth",
    "sg:classifiers":[
        {
            "category":"Retail",
            "subcategory":"Auto Repair",
            "type":"Services"
        }
    ],
    "sg:phone":"+44 1626 772171",
    "sg:postcode":"TQ14 8SP",
    "sg:province":"Devon",
    "sg:tags":[
        "modification",
        "garage"
    ],
    "wof:name":"Courtenay Garage",
    "wof:placetype":"venue"
},
  "geometry": {"coordinates":[-3.493629,50.54723],"type":"Point"}
}