{
  "type": "Feature",
  "properties": {
    "addr:full":"104 Angel Street, Hadleigh Ipswich Suffolk IP7 5BZ",
    "addr:housenumber":"104",
    "addr:postcode":"ip7 5bz",
    "addr:street":"Angel Street",
    "iso:country":"GB",
    "sg:address":"104 Angel Street, Hadleigh",
    "sg:city":"Ipswich",
    "sg:classifiers":[
        {
            "category":"Professional",
            "subcategory":"Engineering",
            "type":"Services"
        },
        {
            "category":"Building & Trades",
            "subcategory":"Electrical",
            "type":"Services"
        }
    ],
    "sg:phone":"+44 1473 823179",
    "sg:postcode":"IP7 5BZ",
    "sg:province":"Suffolk",
    "sg:tags":[
        "engineer",
        "electrician",
        "contractor"
    ],
    "wof:name":"S Cowle Electrical Ltd",
    "wof:placetype":"venue"
},
  "geometry": {"coordinates":[0.9598929882,52.0472717285],"type":"Point"}
}