{
  "type": "Feature",
  "properties": {
    "addr:full":"Rossway Retreat, Little Bushey Lane Bushey Hertfordshire WD23 3RY",
    "addr:postcode":"wd23 3ry",
    "addr:street":"Little Bushey Lane",
    "iso:country":"GB",
    "sg:address":"Rossway Retreat, Little Bushey Lane",
    "sg:city":"Bushey",
    "sg:classifiers":[
        {
            "category":"Wholesale",
            "subcategory":"Scrap",
            "type":"Manufacturing & Wholesale Goods"
        }
    ],
    "sg:postcode":"WD23 3RY",
    "sg:province":"Hertfordshire",
    "sg:tags":[
        "breaker",
        "dismantlers"
    ],
    "wof:name":"Scavengers",
    "wof:placetype":"venue"
},
  "geometry": {"coordinates":[-0.3630689979,51.6443405151],"type":"Point"}
}