{
  "type": "Feature",
  "properties": {
    "addr:full":"51 Roper Street Whitehaven Cumbria CA28 7AR",
    "addr:housenumber":"51",
    "addr:postcode":"ca28 7ar",
    "addr:street":"Roper Street",
    "iso:country":"GB",
    "sg:address":"51 Roper Street",
    "sg:city":"Whitehaven",
    "sg:classifiers":[
        {
            "category":"Home & Garden",
            "subcategory":"Hardware",
            "type":"Retail Goods"
        }
    ],
    "sg:phone":"+44 1946 692569",
    "sg:postcode":"CA28 7AR",
    "sg:province":"Cumbria",
    "sg:tags":[
        "retailer",
        "lighting"
    ],
    "wof:name":"Reginald J Mason",
    "wof:placetype":"venue"
},
  "geometry": {"coordinates":[-3.590114,54.547245],"type":"Point"}
}