{
  "type": "Feature",
  "properties": {
    "addr:full":"4 Herbrand Street London Greater London WC1N 1HX",
    "addr:housenumber":"4",
    "addr:postcode":"wc1n 1hx",
    "addr:street":"Herbrand Street",
    "iso:country":"GB",
    "sg:address":"4 Herbrand Street",
    "sg:city":"London",
    "sg:classifiers":[
        {
            "category":"Bars & Pubs",
            "type":"Food & Drink"
        }
    ],
    "sg:phone":"+44 20 7837 5524",
    "sg:postcode":"WC1N 1HX",
    "sg:province":"Greater London",
    "sg:tags":[
        "pubs",
        "inn"
    ],
    "wof:name":"The Friend At Hand",
    "wof:placetype":"venue"
},
  "geometry": {"coordinates":[-0.12634,51.524712],"type":"Point"}
}