{
  "type": "Feature",
  "properties": {
    "addr:full":"29-31 Gurney Road Norwich Norfolk NR5 0HE",
    "addr:housenumber":"29-31",
    "addr:postcode":"nr5 0he",
    "addr:street":"Gurney Road Norwich Norfolk",
    "iso:country":"GB",
    "sg:address":"29-31 Gurney Road",
    "sg:city":"Norwich",
    "sg:classifiers":[
        {
            "category":"Health Services",
            "subcategory":"Dentist",
            "type":"Services"
        }
    ],
    "sg:phone":"+44 1603 745399",
    "sg:postcode":"NR5 0HE",
    "sg:province":"Norfolk",
    "wof:name":"Cotessey Dental Clinic",
    "wof:placetype":"venue"
},
  "geometry": {"coordinates":[1.2294950485,52.6449432373],"type":"Point"}
}