{
  "type": "Feature",
  "properties": {
    "addr:full":"49 Britannia Way Lichfield Staffordshire WS14 9UY",
    "addr:housenumber":"49",
    "addr:postcode":"ws14 9uy",
    "addr:street":"Britannia Way",
    "iso:country":"GB",
    "sg:address":"49 Britannia Way",
    "sg:city":"Lichfield",
    "sg:classifiers":[
        {
            "category":"Shopping",
            "subcategory":"Clothing, Apparel, & Fashions",
            "type":"Retail Goods"
        }
    ],
    "sg:postcode":"WS14 9UY",
    "sg:province":"Staffordshire",
    "sg:tags":[
        "accessory"
    ],
    "wof:name":"Jenclare Brands",
    "wof:placetype":"venue"
},
  "geometry": {"coordinates":[-1.8021130562,52.685218811],"type":"Point"}
}