{
  "type": "Feature",
  "properties": {
    "iso:country":"GB",
    "sg:address":"Pond House, Weston Green",
    "sg:city":"Thames Ditton",
    "sg:classifiers":[
        {
            "category":"Real Estate",
            "subcategory":"Real Estate Agent",
            "type":"Services"
        },
        {
            "category":"Organizations",
            "subcategory":"Membership Organization",
            "type":"Services"
        }
    ],
    "sg:postcode":"KT7 0JX",
    "sg:province":"Surrey",
    "wof:name":"Hampton Gardens Maintenance Limited",
    "wof:placetype":"venue"
},
  "geometry": {"coordinates":[-0.344464,51.386574],"type":"Point"}
}