{
  "type": "Feature",
  "properties": {
    "iso:country":"GB",
    "sg:address":"6-8 Northgate",
    "sg:city":"Peebles",
    "sg:classifiers":[
        {
            "category":"Bars & Pubs",
            "type":"Food & Drink"
        }
    ],
    "sg:phone":"+44 1721 724111",
    "sg:postcode":"EH45 8RS",
    "sg:province":"Scottish Borders",
    "sg:tags":[
        "pubs",
        "inn"
    ],
    "wof:name":"The Central Bar",
    "wof:placetype":"venue"
},
  "geometry": {"coordinates":[-3.1888000965,55.6525382996],"type":"Point"}
}