{
  "type": "Feature",
  "properties": {
    "addr:full":"Ashbys, Tytherington Warminster Somerset BA12 7AE",
    "addr:postcode":"ba12 7ae",
    "addr:street":"Ashbys",
    "iso:country":"GB",
    "sg:address":"Ashbys, Tytherington",
    "sg:city":"Warminster",
    "sg:classifiers":[
        {
            "category":"Farming",
            "subcategory":"Livestock Farm",
            "type":"Manufacturing & Wholesale Goods"
        }
    ],
    "sg:postcode":"BA12 7AE",
    "sg:province":"Somerset",
    "sg:tags":[
        "others"
    ],
    "wof:name":"G W & G A Giddings",
    "wof:placetype":"venue"
},
  "geometry": {"coordinates":[-2.1193389893,51.1710968018],"type":"Point"}
}