{
  "type": "Feature",
  "properties": {
    "addr:full":"Needwood, Salt Box Lane, Oldwood Tenbury Wells Herefordshire WR15 8TD",
    "addr:postcode":"wr15 8td",
    "addr:street":"Box Lane",
    "iso:country":"GB",
    "sg:address":"Needwood, Salt Box Lane, Oldwood",
    "sg:city":"Tenbury Wells",
    "sg:classifiers":[
        {
            "category":"Freight",
            "type":"Transportation"
        }
    ],
    "sg:phone":"+44 1584 810279",
    "sg:postcode":"WR15 8TD",
    "sg:province":"Herefordshire",
    "sg:tags":[
        "haulage",
        "road"
    ],
    "wof:name":"M.R Hill & Son",
    "wof:placetype":"venue"
},
  "geometry": {"coordinates":[-2.594179,52.312584],"type":"Point"}
}