{
  "type": "Feature",
  "properties": {
    "iso:country":"GB",
    "sg:address":"34 West Avenue, Ramsey",
    "sg:city":"Huntingdon",
    "sg:classifiers":[
        {
            "category":"Building & Trades",
            "subcategory":"Construction",
            "type":"Services"
        }
    ],
    "sg:phone":"+44 1487 815155",
    "sg:postcode":"PE26 1AZ",
    "sg:province":"Cambridgeshire",
    "sg:tags":[
        "glazier"
    ],
    "wof:name":"Victor Royston Spencer",
    "wof:placetype":"venue"
},
  "geometry": {"coordinates":[-0.117853,52.447346],"type":"Point"}
}