{
  "type": "Feature",
  "properties": {
    "iso:country":"GB",
    "sg:address":"42 Southover",
    "sg:city":"Wells",
    "sg:classifiers":[
        {
            "category":"Bars & Pubs",
            "type":"Food & Drink"
        }
    ],
    "sg:phone":"+44 1749 675792",
    "sg:postcode":"BA5 1UH",
    "sg:province":"Somerset",
    "sg:tags":[
        "pubs",
        "inn"
    ],
    "wof:name":"Punch Pub Co. (Ib) Ltd.",
    "wof:placetype":"venue"
},
  "geometry": {"coordinates":[-2.648253,51.205566],"type":"Point"}
}