{
  "type": "Feature",
  "properties": {
    "addr:full":"Carlisle Road Bradford West Yorkshire BD8 8DB",
    "addr:postcode":"bd8 8db",
    "addr:street":"Carlisle Road",
    "iso:country":"GB",
    "sg:address":"Carlisle Road",
    "sg:city":"Bradford",
    "sg:classifiers":[
        {
            "category":"Community Center",
            "type":"Public Place"
        },
        {
            "category":"Government",
            "subcategory":"Office",
            "type":"Public Place"
        }
    ],
    "sg:phone":"+44 1274 494927",
    "sg:postcode":"BD8 8DB",
    "sg:province":"West Yorkshire",
    "sg:tags":[
        "recreation",
        "local",
        "leisure",
        "centre"
    ],
    "wof:name":"Manningham Sports Centre",
    "wof:placetype":"venue"
},
  "geometry": {"coordinates":[-1.7718260288,53.8055992126],"type":"Point"}
}