{
  "type": "Feature",
  "properties": {
    "addr:full":"55 Mead Road, Leckhampton Cheltenham Gloucestershire GL53 7DY",
    "addr:housenumber":"55",
    "addr:postcode":"gl53 7dy",
    "addr:street":"Mead Road",
    "iso:country":"GB",
    "sg:address":"55 Mead Road, Leckhampton",
    "sg:city":"Cheltenham",
    "sg:classifiers":[
        {
            "category":"Building & Trades",
            "subcategory":"Construction",
            "type":"Services"
        }
    ],
    "sg:phone":"+44 1242 571473",
    "sg:postcode":"GL53 7DY",
    "sg:province":"Gloucestershire",
    "sg:tags":[
        "decorator",
        "painter"
    ],
    "wof:name":"P & S Decorators (Cheltenham) Ltd.",
    "wof:placetype":"venue"
},
  "geometry": {"coordinates":[-2.073877,51.882851],"type":"Point"}
}