{
  "type": "Feature",
  "properties": {
    "iso:country":"GB",
    "sg:address":"Church Lane",
    "sg:city":"Mold",
    "sg:classifiers":[
        {
            "category":"Manufacturing",
            "subcategory":"Metals",
            "type":"Manufacturing & Wholesale Goods"
        }
    ],
    "sg:postcode":"CH7 1BW",
    "sg:province":"Denbighshire",
    "wof:name":"Treasure Detecting Products",
    "wof:placetype":"venue"
},
  "geometry": {"coordinates":[-3.142909,53.168606],"type":"Point"}
}