{
  "type": "Feature",
  "properties": {
    "iso:country":"GB",
    "sg:address":"73 Lowfield Street",
    "sg:city":"Dartford",
    "sg:classifiers":[
        {
            "category":"Taxi",
            "type":"Transportation"
        }
    ],
    "sg:phone":"+44 1322 223344",
    "sg:postcode":"DA1 1HP",
    "sg:province":"Kent",
    "sg:tags":[
        "mini",
        "cab"
    ],
    "wof:name":"Linda Chandler",
    "wof:placetype":"venue"
},
  "geometry": {"coordinates":[0.2157109976,51.4420852661],"type":"Point"}
}