{
  "type": "Feature",
  "properties": {
    "addr:full":"1 Southbourne Street, Seedley Salford Greater Manchester M6 5GN",
    "addr:housenumber":"1",
    "addr:postcode":"m6 5gn",
    "addr:street":"Southbourne Street",
    "iso:country":"GB",
    "sg:address":"1 Southbourne Street, Seedley",
    "sg:city":"Salford",
    "sg:classifiers":[
        {
            "category":"Building & Trades",
            "subcategory":"Construction",
            "type":"Services"
        }
    ],
    "sg:phone":"+44 161 737 4372",
    "sg:postcode":"M6 5GN",
    "sg:province":"Greater Manchester",
    "sg:tags":[
        "decorator",
        "painter"
    ],
    "wof:name":"Paul Pickford",
    "wof:placetype":"venue"
},
  "geometry": {"coordinates":[-2.2990028858,53.4828948975],"type":"Point"}
}