{
  "type": "Feature",
  "properties": {
    "addr:full":"Flat 4 24 Saffrons Rd Eastbourne East Sussex BN21 1DU",
    "addr:housenumber":"24",
    "addr:postcode":"bn21 1du",
    "addr:street":"Saffrons Rd",
    "iso:country":"GB",
    "sg:address":"Flat 4 24 Saffrons Rd",
    "sg:city":"Eastbourne",
    "sg:classifiers":[
        {
            "category":"Manufacturing",
            "subcategory":"Apparel",
            "type":"Manufacturing & Wholesale Goods"
        }
    ],
    "sg:phone":"+44 1323 638869",
    "sg:postcode":"BN21 1DU",
    "sg:province":"East Sussex",
    "sg:tags":[
        "mnfr",
        "footwear"
    ],
    "wof:name":"Roberts Bespoke Footwear",
    "wof:placetype":"venue"
},
  "geometry": {"coordinates":[0.28535,50.766911],"type":"Point"}
}