{
  "type": "Feature",
  "properties": {
    "addr:full":"330 West Barnes Lane New Malden Surrey KT3 6NB",
    "addr:housenumber":"330",
    "addr:postcode":"kt3 6nb",
    "addr:street":"West Barnes Lane",
    "iso:country":"GB",
    "sg:address":"330 West Barnes Lane",
    "sg:city":"New Malden",
    "sg:classifiers":[
        {
            "category":"Retail",
            "subcategory":"Laundry & Dry Cleaning",
            "type":"Services"
        }
    ],
    "sg:phone":"+44 20 8296 0870",
    "sg:postcode":"KT3 6NB",
    "sg:province":"Surrey",
    "sg:tags":[
        "alteration"
    ],
    "wof:name":"Bourjois Dry Cleaners",
    "wof:placetype":"venue"
},
  "geometry": {"coordinates":[-0.2386360019,51.3943328857],"type":"Point"}
}