{
  "type": "Feature",
  "properties": {
    "addr:full":"4 Bellevue Mews, Bellevue Road Friern Barnet London Greater London N11 3HF",
    "addr:housenumber":"4",
    "addr:postcode":"n11 3hf",
    "addr:street":"Bellevue Mews Bellevue Road",
    "iso:country":"GB",
    "sg:address":"4 Bellevue Mews, Bellevue Road Friern Barnet",
    "sg:city":"London",
    "sg:classifiers":[
        {
            "category":"Professional",
            "subcategory":"Management & Consulting",
            "type":"Services"
        }
    ],
    "sg:postcode":"N11 3HF",
    "sg:province":"Greater London",
    "sg:tags":[
        "consultant",
        "business"
    ],
    "wof:name":"Kewcroft Ltd",
    "wof:placetype":"venue"
},
  "geometry": {"coordinates":[-0.148575,51.614815],"type":"Point"}
}