{
  "type": "Feature",
  "properties": {
    "iso:country":"GB",
    "sg:address":"63 Foregate Street",
    "sg:city":"Worcester",
    "sg:classifiers":[
        {
            "category":"Banks & Credit Unions",
            "subcategory":"Investment Brokerage",
            "type":"Services"
        }
    ],
    "sg:phone":"+44 1905 619499",
    "sg:postcode":"WR1 1DX",
    "sg:province":"Worcestershire",
    "sg:tags":[
        "stockbroker"
    ],
    "wof:name":"Harris Allday Lea & Brooks",
    "wof:placetype":"venue"
},
  "geometry": {"coordinates":[-2.2219409943,52.1945648193],"type":"Point"}
}