{
  "type": "Feature",
  "properties": {
    "addr:full":"37 Brewer Street London Greater London W1F 0RU",
    "addr:housenumber":"37",
    "addr:postcode":"w1f 0ru",
    "addr:street":"Brewer Street",
    "iso:country":"GB",
    "sg:address":"37 Brewer Street",
    "sg:city":"London",
    "sg:classifiers":[
        {
            "category":"Bars & Pubs",
            "type":"Food & Drink"
        }
    ],
    "sg:phone":"+44 20 7437 6819",
    "sg:postcode":"W1F 0RU",
    "sg:province":"Greater London",
    "sg:tags":[
        "pubs",
        "inn"
    ],
    "wof:name":"The Duke of Argyll",
    "wof:placetype":"venue"
},
  "geometry": {"coordinates":[-0.13471,51.511822],"type":"Point"}
}