{
  "type": "Feature",
  "properties": {
    "addr:full":"7 The Corridor Bath Bath and North East Somerset BA1 5AP",
    "addr:housenumber":"7",
    "addr:postcode":"ba1 5ap",
    "iso:country":"GB",
    "sg:address":"7 The Corridor",
    "sg:city":"Bath",
    "sg:classifiers":[
        {
            "category":"Shopping",
            "subcategory":"Music",
            "type":"Retail Goods"
        }
    ],
    "sg:phone":"+44 1225 460945",
    "sg:postcode":"BA1 5AP",
    "sg:province":"Bath and North East Somerset",
    "sg:tags":[
        "record",
        "tape",
        "cd"
    ],
    "wof:name":"Onyx Music Ltd.",
    "wof:placetype":"venue"
},
  "geometry": {"coordinates":[-2.361166954,51.3850708008],"type":"Point"}
}