{
  "type": "Feature",
  "properties": {
    "addr:full":"Frogmore Farm, Toller Porcorum Dorchester Dorset DT2 0DL",
    "addr:housenumber":"toller porcorum dorchester",
    "addr:postcode":"dt2 0dl",
    "addr:street":"Dorset",
    "iso:country":"GB",
    "sg:address":"Frogmore Farm, Toller Porcorum",
    "sg:city":"Dorchester",
    "sg:classifiers":[
        {
            "category":"Professional",
            "subcategory":"Management & Consulting",
            "type":"Services"
        }
    ],
    "sg:phone":"+44 1300 320541",
    "sg:postcode":"DT2 0DL",
    "sg:province":"Dorset",
    "sg:tags":[
        "marketing",
        "consultant"
    ],
    "wof:name":"A P Gower",
    "wof:placetype":"venue"
},
  "geometry": {"coordinates":[-2.6211299896,50.7799301147],"type":"Point"}
}