{
  "type": "Feature",
  "properties": {
    "addr:full":"2fnd Floor, Empress Mill Empress Street Manchester Cheshire M16 9EN",
    "addr:housenumber":"2fnd floor",
    "addr:postcode":"m16 9en",
    "addr:street":"Empress Mill Empress Street",
    "iso:country":"GB",
    "sg:address":"2fnd Floor, Empress Mill Empress Street",
    "sg:city":"Manchester",
    "sg:classifiers":[
        {
            "category":"Shopping",
            "subcategory":"Clothing, Apparel, & Fashions",
            "type":"Retail Goods"
        }
    ],
    "sg:phone":"+44 161 237 3080",
    "sg:postcode":"M16 9EN",
    "sg:province":"Cheshire",
    "sg:tags":[
        "clothing",
        "fabric"
    ],
    "wof:name":"Fashionpulse Ltd.",
    "wof:placetype":"venue"
},
  "geometry": {"coordinates":[-2.2692101002,53.4660491943],"type":"Point"}
}