{
  "type": "Feature",
  "properties": {
    "addr:full":"25 Commerical St Crook Durham DL15 0AD",
    "addr:housenumber":"25",
    "addr:postcode":"dl15 0ad",
    "addr:street":"Commerical St",
    "iso:country":"GB",
    "sg:address":"25 Commerical St",
    "sg:city":"Crook",
    "sg:classifiers":[
        {
            "category":"Retail",
            "subcategory":"Funeral Services",
            "type":"Services"
        }
    ],
    "sg:phone":"+44 1388 746288",
    "sg:postcode":"DL15 0AD",
    "sg:province":"Durham",
    "wof:name":"North Eastern Co-Operative",
    "wof:placetype":"venue"
},
  "geometry": {"coordinates":[-1.7487939596,54.7143630981],"type":"Point"}
}