{
  "type": "Feature",
  "properties": {
    "iso:country":"GB",
    "sg:address":"12-20 Regent St",
    "sg:city":"Weston Super Mare",
    "sg:classifiers":[
        {
            "category":"Recreation",
            "subcategory":"Amusement Park",
            "type":"Entertainment"
        }
    ],
    "sg:phone":"+44 1934 629683",
    "sg:postcode":"BS23 1SQ",
    "sg:province":"Somerset",
    "sg:tags":[
        "arcade"
    ],
    "wof:name":"Mr B'S Amusements",
    "wof:placetype":"venue"
},
  "geometry": {"coordinates":[-2.9799220562,51.3474845886],"type":"Point"}
}