{
  "type": "Feature",
  "properties": {
    "iso:country":"GB",
    "sg:address":"Densham Farm, Bishops Down",
    "sg:city":"Sherborne",
    "sg:classifiers":[
        {
            "category":"Health Services",
            "subcategory":"Medical Lab",
            "type":"Services"
        },
        {
            "category":"Professional",
            "subcategory":"Employment Agencies",
            "type":"Services"
        }
    ],
    "sg:phone":"+44 1963 23197",
    "sg:postcode":"DT9 5PN",
    "sg:province":"Dorset",
    "sg:tags":[
        "based",
        "advice",
        "activity",
        "research",
        "agricultural",
        "laboratory"
    ],
    "wof:name":"J PERRY & SON",
    "wof:placetype":"venue"
},
  "geometry": {"coordinates":[-2.463219,50.90913],"type":"Point"}
}