{
  "type": "Feature",
  "properties": {
    "iso:country":"GB",
    "sg:address":"North Road",
    "sg:city":"Hertford",
    "sg:classifiers":[
        {
            "category":"Communications",
            "type":"Services"
        }
    ],
    "sg:phone":"+44 1992 505001",
    "sg:postcode":"SG14 2BU",
    "sg:province":"Hertfordshire",
    "sg:tags":[
        "audio-visual"
    ],
    "wof:name":"Novasonics Studio",
    "wof:placetype":"venue"
},
  "geometry": {"coordinates":[-0.095144,51.813141],"type":"Point"}
}