{
  "type": "Feature",
  "properties": {
    "addr:full":"Larksmead, Slapton Kingsbridge Devon TQ7 2PY",
    "addr:postcode":"tq7 2py",
    "addr:street":"Slapton",
    "iso:country":"GB",
    "sg:address":"Larksmead, Slapton",
    "sg:city":"Kingsbridge",
    "sg:classifiers":[
        {
            "category":"Building & Trades",
            "subcategory":"Construction",
            "type":"Services"
        }
    ],
    "sg:postcode":"TQ7 2PY",
    "sg:province":"Devon",
    "sg:tags":[
        "glazier"
    ],
    "wof:name":"John W Wheeler",
    "wof:placetype":"venue"
},
  "geometry": {"coordinates":[-3.6566419601,50.2919082642],"type":"Point"}
}