{
  "type": "Feature",
  "properties": {
    "iso:country":"GB",
    "sg:address":"23 East Street",
    "sg:city":"Newquay",
    "sg:classifiers":[
        {
            "category":"Food & Beverages",
            "subcategory":"Bakery",
            "type":"Retail Goods"
        }
    ],
    "sg:phone":"+44 1637 850635",
    "sg:postcode":"TR7 1DN",
    "sg:province":"Cornwall",
    "sg:tags":[
        "shop",
        "baker"
    ],
    "sg:website":"http://www.saffronbypost.co.uk",
    "wof:name":"Warrens",
    "wof:placetype":"venue"
},
  "geometry": {"coordinates":[-5.080998,50.414124],"type":"Point"}
}