{
  "type": "Feature",
  "properties": {
    "addr:full":"Bourton Road, Bourton Buckingham Buckinghamshire MK18 7DL",
    "addr:postcode":"mk18 7dl",
    "addr:street":"Bourton Road",
    "iso:country":"GB",
    "sg:address":"Bourton Road, Bourton",
    "sg:city":"Buckingham",
    "sg:classifiers":[
        {
            "category":"Sports & Exercise",
            "subcategory":"Gym",
            "type":"Entertainment"
        }
    ],
    "sg:phone":"+44 1280 823423",
    "sg:postcode":"MK18 7DL",
    "sg:province":"Buckinghamshire",
    "sg:tags":[
        "fitness",
        "health",
        "centre"
    ],
    "wof:name":"Bourton Mill Health & Leisure Club Ltd.",
    "wof:placetype":"venue"
},
  "geometry": {"coordinates":[-0.97621,51.995888],"type":"Point"}
}