{
  "type": "Feature",
  "properties": {
    "iso:country":"GB",
    "sg:address":"Seven Sisters, Seven Sisters Rd",
    "sg:city":"Ventnor",
    "sg:classifiers":[
        {
            "category":"Building & Trades",
            "subcategory":"Landscaping Services",
            "type":"Services"
        }
    ],
    "sg:phone":"+44 1983 855488",
    "sg:postcode":"PO38 1UY",
    "sg:province":"Isle of Wight",
    "sg:tags":[
        "gardening"
    ],
    "wof:name":"S J Services",
    "wof:placetype":"venue"
},
  "geometry": {"coordinates":[-1.2499769926,50.585521698],"type":"Point"}
}