{
  "type": "Feature",
  "properties": {
    "iso:country":"GB",
    "sg:address":"Stoke St Gregory",
    "sg:city":"Taunton",
    "sg:classifiers":[
        {
            "category":"Place Of Worship",
            "type":"Public Place"
        },
        {
            "category":"Government",
            "subcategory":"Post Office",
            "type":"Public Place"
        }
    ],
    "sg:phone":"+44 1823 490246",
    "sg:postcode":"TA3 6JG",
    "sg:province":"Devon",
    "wof:name":"Stoke St.Gregory Post Office",
    "wof:placetype":"venue"
},
  "geometry": {"coordinates":[-2.93639,51.04285],"type":"Point"}
}