{
  "type": "Feature",
  "properties": {
    "addr:full":"217-219 Cowley Road Oxford Oxfordshire OX4 1XG",
    "addr:housenumber":"217-219",
    "addr:postcode":"ox4 1xg",
    "addr:street":"Cowley Road",
    "iso:country":"GB",
    "sg:address":"217-219 Cowley Road",
    "sg:city":"Oxford",
    "sg:classifiers":[
        {
            "category":"Government",
            "subcategory":"Post Office",
            "type":"Public Place"
        },
        {
            "category":"Food & Beverages",
            "subcategory":"Groceries & Convenience Stores",
            "type":"Retail Goods"
        }
    ],
    "sg:phone":"+44 1865 241513",
    "sg:postcode":"OX4 1XG",
    "sg:province":"Oxfordshire",
    "wof:name":"Londis",
    "wof:placetype":"venue"
},
  "geometry": {"coordinates":[-1.2313729525,51.7458000183],"type":"Point"}
}