{
  "type": "Feature",
  "properties": {
    "addr:full":"12 Strathmore Gardens London Greater London N3 2HL",
    "addr:housenumber":"12",
    "addr:postcode":"n3 2hl",
    "addr:street":"Strathmore Gardens",
    "iso:country":"GB",
    "sg:address":"12 Strathmore Gardens",
    "sg:city":"London",
    "sg:classifiers":[
        {
            "category":"Social Services",
            "type":"Services"
        },
        {
            "category":"Organizations",
            "subcategory":"Non-profit Organization",
            "type":"Services"
        }
    ],
    "sg:phone":"+44 20 8349 0614",
    "sg:postcode":"N3 2HL",
    "sg:province":"Greater London",
    "sg:tags":[
        "organisation",
        "disability",
        "voluntary",
        "charity"
    ],
    "wof:name":"Disabled Drivers' Motor Club",
    "wof:placetype":"venue"
},
  "geometry": {"coordinates":[-0.1868699938,51.5995826721],"type":"Point"}
}