{
  "type": "Feature",
  "properties": {
    "addr:full":"231 Lytham Road Blackpool Lancashire FY1 6ET",
    "addr:housenumber":"231",
    "addr:postcode":"fy1 6et",
    "addr:street":"Lytham Road",
    "iso:country":"GB",
    "sg:address":"231 Lytham Road",
    "sg:city":"Blackpool",
    "sg:classifiers":[
        {
            "category":"Shopping",
            "subcategory":"Baby Store",
            "type":"Retail Goods"
        }
    ],
    "sg:postcode":"FY1 6ET",
    "sg:province":"Lancashire",
    "sg:tags":[
        "nursery",
        "accessory"
    ],
    "wof:name":"R Blundell",
    "wof:placetype":"venue"
},
  "geometry": {"coordinates":[-3.0509989262,53.8000907898],"type":"Point"}
}