{
  "type": "Feature",
  "properties": {
    "addr:full":"Grampian House, Grampian Drive Peterlee Durham SR8 2LR",
    "addr:postcode":"sr8 2lr",
    "addr:street":"Grampian Drive",
    "iso:country":"GB",
    "sg:address":"Grampian House, Grampian Drive",
    "sg:city":"Peterlee",
    "sg:classifiers":[
        {
            "category":"Social Services",
            "subcategory":"Retirement Home",
            "type":"Services"
        }
    ],
    "sg:phone":"+44 191 586 4833",
    "sg:postcode":"SR8 2LR",
    "sg:province":"Durham",
    "sg:tags":[
        "residential",
        "care"
    ],
    "wof:name":"Grampian Residential Home",
    "wof:placetype":"venue"
},
  "geometry": {"coordinates":[-1.344938,54.756935],"type":"Point"}
}