{
  "type": "Feature",
  "properties": {
    "iso:country":"GB",
    "sg:address":"61 High Street",
    "sg:city":"Arbroath",
    "sg:classifiers":[
        {
            "category":"Organizations",
            "subcategory":"Non-profit Organization",
            "type":"Services"
        }
    ],
    "sg:phone":"+44 1241 430349",
    "sg:postcode":"DD11 1AN",
    "sg:province":"Angus",
    "sg:tags":[
        "charitable",
        "organisation",
        "voluntary",
        "charity"
    ],
    "sg:website":"http://www.aavo.org.uk",
    "wof:name":"Angus Association Of Voluntary Organisations",
    "wof:placetype":"venue"
},
  "geometry": {"coordinates":[-2.5807259083,56.5578575134],"type":"Point"}
}