{
  "type": "Feature",
  "properties": {
    "addr:full":"New Farm, Nether Poppleton York North Yorkshire YO26 6HU",
    "addr:postcode":"yo26 6hu",
    "addr:street":"New Farm",
    "iso:country":"GB",
    "sg:address":"New Farm, Nether Poppleton",
    "sg:city":"York",
    "sg:classifiers":[
        {
            "category":"Home & Garden",
            "subcategory":"Garden Supply",
            "type":"Retail Goods"
        }
    ],
    "sg:postcode":"YO26 6HU",
    "sg:province":"North Yorkshire",
    "sg:tags":[
        "bulb",
        "grower"
    ],
    "wof:name":"Douglas M Frazer & Son",
    "wof:placetype":"venue"
},
  "geometry": {"coordinates":[-1.145807,53.980755],"type":"Point"}
}