{
  "type": "Feature",
  "properties": {
    "addr:full":"249 Nottingham Rd Derby Derbyshire DE21 6AP",
    "addr:housenumber":"249",
    "addr:postcode":"de21 6ap",
    "addr:street":"Nottingham Rd",
    "iso:country":"GB",
    "sg:address":"249 Nottingham Rd",
    "sg:city":"Derby",
    "sg:classifiers":[
        {
            "category":"Shopping",
            "subcategory":"Used Merchandise",
            "type":"Retail Goods"
        }
    ],
    "sg:postcode":"DE21 6AP",
    "sg:province":"Derbyshire",
    "sg:tags":[
        "shop",
        "second-hand"
    ],
    "wof:name":"Greensmith,A H,",
    "wof:placetype":"venue"
},
  "geometry": {"coordinates":[-1.454285,52.926083],"type":"Point"}
}