{
  "type": "Feature",
  "properties": {
    "addr:full":"2 Honey Hill Bury St Edmunds Suffolk IP33 1RT",
    "addr:housenumber":"2",
    "addr:postcode":"ip33 1rt",
    "addr:street":"Honey Hill",
    "iso:country":"GB",
    "sg:address":"2 Honey Hill",
    "sg:city":"Bury St Edmunds",
    "sg:classifiers":[
        {
            "category":"Real Estate",
            "subcategory":"Architect",
            "type":"Services"
        }
    ],
    "sg:postcode":"IP33 1RT",
    "sg:province":"Suffolk",
    "wof:name":"Warren Technology",
    "wof:placetype":"venue"
},
  "geometry": {"coordinates":[0.7183009982,52.2424621582],"type":"Point"}
}