{
  "type": "Feature",
  "properties": {
    "addr:full":"Caernarvon Road Y Felinheli Gwynedd LL56 4RZ",
    "addr:postcode":"ll56 4rz",
    "addr:street":"Caernarvon Road",
    "iso:country":"GB",
    "sg:address":"Caernarvon Road",
    "sg:city":"Y Felinheli",
    "sg:classifiers":[
        {
            "category":"Retail",
            "subcategory":"Auto Repair",
            "type":"Services"
        }
    ],
    "sg:phone":"+44 1248 670882",
    "sg:postcode":"LL56 4RZ",
    "sg:province":"Gwynedd",
    "sg:tags":[
        "modification",
        "garage"
    ],
    "wof:name":"Menai Garage",
    "wof:placetype":"venue"
},
  "geometry": {"coordinates":[-4.2096090317,53.1836547852],"type":"Point"}
}