{
  "type": "Feature",
  "properties": {
    "iso:country":"GB",
    "sg:address":"3 Lever St",
    "sg:city":"Clerkenwell",
    "sg:classifiers":[
        {
            "category":"Professional",
            "subcategory":"Art Services",
            "type":"Services"
        }
    ],
    "sg:phone":"+44 20 7608 1083",
    "sg:postcode":"EC1V 3QU",
    "sg:province":"Greater London",
    "sg:tags":[
        "photographer"
    ],
    "wof:name":"Steve Teague",
    "wof:placetype":"venue"
},
  "geometry": {"coordinates":[-0.099759,51.526459],"type":"Point"}
}