{
  "type": "Feature",
  "properties": {
    "addr:full":"53 Vicarage Road, Redfield Bristol City of Bristol BS5 9AQ",
    "addr:housenumber":"53",
    "addr:postcode":"bs5 9aq",
    "addr:street":"Vicarage Road",
    "iso:country":"GB",
    "sg:address":"53 Vicarage Road, Redfield",
    "sg:city":"Bristol",
    "sg:classifiers":[
        {
            "category":"Social Services",
            "subcategory":"Adult Care",
            "type":"Services"
        }
    ],
    "sg:phone":"+44 117 904 1152",
    "sg:postcode":"BS5 9AQ",
    "sg:province":"City of Bristol",
    "sg:tags":[
        "domestic",
        "cleaning"
    ],
    "wof:name":"J Reed",
    "wof:placetype":"venue"
},
  "geometry": {"coordinates":[-2.559209,51.462585],"type":"Point"}
}