{
  "type": "Feature",
  "properties": {
    "addr:full":"High Street, Blagdon Bristol Somerset BS40 7RA",
    "addr:postcode":"bs40 7ra",
    "addr:street":"High Street",
    "iso:country":"GB",
    "sg:address":"High Street, Blagdon",
    "sg:city":"Bristol",
    "sg:classifiers":[
        {
            "category":"Bars & Pubs",
            "type":"Food & Drink"
        }
    ],
    "sg:phone":"+44 1761 462573",
    "sg:postcode":"BS40 7RA",
    "sg:province":"Somerset",
    "sg:tags":[
        "pubs",
        "inn"
    ],
    "wof:name":"The Queen Adelaide",
    "wof:placetype":"venue"
},
  "geometry": {"coordinates":[-2.715264082,51.3258018494],"type":"Point"}
}