{
  "type": "Feature",
  "properties": {
    "addr:full":"18 High Street, Eagle Lincoln Lincolnshire LN6 9DH",
    "addr:housenumber":"18",
    "addr:postcode":"ln6 9dh",
    "addr:street":"High Street",
    "iso:country":"GB",
    "sg:address":"18 High Street, Eagle",
    "sg:city":"Lincoln",
    "sg:classifiers":[
        {
            "category":"Building & Trades",
            "subcategory":"Construction",
            "type":"Services"
        }
    ],
    "sg:phone":"+44 1522 868310",
    "sg:postcode":"LN6 9DH",
    "sg:province":"Lincolnshire",
    "sg:tags":[
        "builder"
    ],
    "wof:name":"Anthony Dawson Builders",
    "wof:placetype":"venue"
},
  "geometry": {"coordinates":[-0.689728,53.192116],"type":"Point"}
}