{
  "type": "Feature",
  "properties": {
    "addr:full":"33 Bath Road Slough Berkshire SL1 4DX",
    "addr:housenumber":"33",
    "addr:postcode":"sl1 4dx",
    "addr:street":"Bath Road",
    "iso:country":"GB",
    "sg:address":"33 Bath Road",
    "sg:city":"Slough",
    "sg:classifiers":[
        {
            "category":"Professional",
            "subcategory":"Business Services",
            "type":"Services"
        }
    ],
    "sg:phone":"+44 1753 495000",
    "sg:postcode":"SL1 4DX",
    "sg:province":"Berkshire",
    "sg:tags":[
        "distribution"
    ],
    "wof:name":"Lego Park Holding U K Ltd.",
    "wof:placetype":"venue"
},
  "geometry": {"coordinates":[-0.617539,51.513451],"type":"Point"}
}