{
  "type": "Feature",
  "properties": {
    "iso:country":"GB",
    "sg:address":"Coroners Ct, 50 Newton St",
    "sg:city":"Birmingham",
    "sg:classifiers":[
        {
            "category":"Government",
            "subcategory":"Court House",
            "type":"Public Place"
        }
    ],
    "sg:phone":"+44 121 303 3920",
    "sg:postcode":"B4 6NE",
    "sg:province":"West Midlands",
    "wof:name":"Coroners Office The",
    "wof:placetype":"venue"
},
  "geometry": {"coordinates":[-1.8945599794,52.4832992554],"type":"Point"}
}