{
  "type": "Feature",
  "properties": {
    "iso:country":"GB",
    "sg:address":"209 Beam Hill Rd",
    "sg:city":"Burton On Trent",
    "sg:classifiers":[
        {
            "category":"Building & Trades",
            "subcategory":"Landscaping Services",
            "type":"Services"
        }
    ],
    "sg:phone":"+44 1283 812578",
    "sg:postcode":"DE13 9QW",
    "sg:province":"Derbyshire",
    "sg:tags":[
        "forestry",
        "tree"
    ],
    "wof:name":"Reed Landscape Services",
    "wof:placetype":"venue"
},
  "geometry": {"coordinates":[-1.671385,52.829533],"type":"Point"}
}