{
  "type": "Feature",
  "properties": {
    "iso:country":"GB",
    "sg:address":"4 Tait Walk, Crossford",
    "sg:city":"Carluke",
    "sg:classifiers":[
        {
            "category":"Professional",
            "subcategory":"Engineering",
            "type":"Services"
        }
    ],
    "sg:phone":"+44 1555 860600",
    "sg:postcode":"ML8 5NR",
    "sg:province":"South Lanarkshire",
    "sg:tags":[
        "consulting",
        "design",
        "engineer"
    ],
    "wof:name":"Robert J Leggett Associates",
    "wof:placetype":"venue"
},
  "geometry": {"coordinates":[-3.8699328899,55.6994476318],"type":"Point"}
}