{
  "type": "Feature",
  "properties": {
    "addr:full":"Wellington Gate, 7-9 Church Road Tunbridge Wells Kent TN1 1HT",
    "addr:housenumber":"7-9",
    "addr:postcode":"tn1 1ht",
    "addr:street":"Wellington Gate;Church Road",
    "iso:country":"GB",
    "sg:address":"Wellington Gate, 7-9 Church Road",
    "sg:city":"Tunbridge Wells",
    "sg:classifiers":[
        {
            "category":"Travel",
            "subcategory":"Hotels & Motels",
            "type":"Entertainment"
        }
    ],
    "sg:postcode":"TN1 1HT",
    "sg:province":"Kent",
    "sg:tags":[
        "self",
        "catering"
    ],
    "wof:name":"Exclusive Villas Ltd",
    "wof:placetype":"venue"
},
  "geometry": {"coordinates":[0.26355,51.133373],"type":"Point"}
}