{
  "type": "Feature",
  "properties": {
    "addr:full":"Avenue One, Station Lane Indstl Est Witney Oxfordshire OX28 4XX",
    "addr:postcode":"ox28 4xx",
    "addr:street":"Avenue One Station Lane Indstl Est",
    "iso:country":"GB",
    "sg:address":"Avenue One, Station Lane Indstl Est",
    "sg:city":"Witney",
    "sg:classifiers":[
        {
            "category":"Manufacturing",
            "subcategory":"Signs",
            "type":"Manufacturing & Wholesale Goods"
        }
    ],
    "sg:postcode":"OX28 4XX",
    "sg:province":"Oxfordshire",
    "sg:tags":[
        "nameplate"
    ],
    "wof:name":"British Industrial Graphics Ltd",
    "wof:placetype":"venue"
},
  "geometry": {"coordinates":[-1.489573,51.776833],"type":"Point"}
}