{
  "type": "Feature",
  "properties": {
    "iso:country":"GB",
    "sg:address":"10 Somerton Road",
    "sg:city":"London",
    "sg:classifiers":[
        {
            "category":"Utilities",
            "subcategory":"Fuel Oil & Lpg",
            "type":"Services"
        }
    ],
    "sg:phone":"+44 20 7263 9889",
    "sg:postcode":"NW2 1SA",
    "sg:province":"Greater London",
    "sg:tags":[
        "gas"
    ],
    "wof:name":"Subsea Ltd.",
    "wof:placetype":"venue"
},
  "geometry": {"coordinates":[-0.2100200057,51.5619544983],"type":"Point"}
}