{
  "type": "Feature",
  "properties": {
    "addr:full":"Coneygarth, Tunstall Carnforth Cumbria LA6 2QP",
    "addr:postcode":"la6 2qp",
    "iso:country":"GB",
    "sg:address":"Coneygarth, Tunstall",
    "sg:city":"Carnforth",
    "sg:classifiers":[
        {
            "category":"Professional",
            "subcategory":"Business Services",
            "type":"Services"
        }
    ],
    "sg:phone":"+44 1224 871015",
    "sg:postcode":"LA6 2QP",
    "sg:province":"Cumbria",
    "sg:tags":[
        "holding"
    ],
    "wof:name":"Can Holdings Ltd",
    "wof:placetype":"venue"
},
  "geometry": {"coordinates":[-2.6009819508,54.1564445496],"type":"Point"}
}