{
  "type": "Feature",
  "properties": {
    "iso:country":"GB",
    "sg:address":"59 High Street",
    "sg:city":"West Bromwich",
    "sg:classifiers":[
        {
            "category":"Shopping",
            "subcategory":"Department Store",
            "type":"Retail Goods"
        }
    ],
    "sg:phone":"+44 121 525 9899",
    "sg:postcode":"B70 6NZ",
    "sg:province":"West Midlands",
    "wof:name":"Punjab Food Store",
    "wof:placetype":"venue"
},
  "geometry": {"coordinates":[-1.987123,52.514793],"type":"Point"}
}