{
  "type": "Feature",
  "properties": {
    "addr:full":"36-38 Finkle Street Workington Cumbria CA14 2BB",
    "addr:housenumber":"36-38",
    "addr:postcode":"ca14 2bb",
    "addr:street":"Finkle Street",
    "iso:country":"GB",
    "sg:address":"36-38 Finkle Street",
    "sg:city":"Workington",
    "sg:classifiers":[
        {
            "category":"Travel",
            "subcategory":"Travel Agent",
            "type":"Entertainment"
        }
    ],
    "sg:phone":"+44 1900 64916",
    "sg:postcode":"CA14 2BB",
    "sg:province":"Cumbria",
    "wof:name":"Craig Travel",
    "wof:placetype":"venue"
},
  "geometry": {"coordinates":[-3.5477340221,54.645072937],"type":"Point"}
}