{
  "type": "Feature",
  "properties": {
    "iso:country":"GB",
    "sg:address":"1 Norbury Road",
    "sg:city":"Reigate",
    "sg:classifiers":[
        {
            "category":"Professional",
            "subcategory":"Testing Lab",
            "type":"Services"
        },
        {
            "category":"Professional",
            "subcategory":"Research",
            "type":"Services"
        }
    ],
    "sg:phone":"+44 1737 226662",
    "sg:postcode":"RH2 9BY",
    "sg:province":"Surrey",
    "sg:tags":[
        "laboratory",
        "based",
        "activity"
    ],
    "wof:name":"Mycoplasma Experience Ltd",
    "wof:placetype":"venue"
},
  "geometry": {"coordinates":[-0.2137700021,51.2394104004],"type":"Point"}
}