{
  "type": "Feature",
  "properties": {
    "addr:full":"4 River Terrace Ayr South Ayrshire KA8 0BJ",
    "addr:housenumber":"4",
    "addr:postcode":"ka8 0bj",
    "addr:street":"River Terrace",
    "iso:country":"GB",
    "sg:address":"4 River Terrace",
    "sg:city":"Ayr",
    "sg:classifiers":[
        {
            "category":"Restaurant",
            "type":"Food & Drink"
        }
    ],
    "sg:phone":"+44 1292 282087",
    "sg:postcode":"KA8 0BJ",
    "sg:province":"South Ayrshire",
    "sg:tags":[
        "french"
    ],
    "wof:name":"The Kirkton In Town",
    "wof:placetype":"venue"
},
  "geometry": {"coordinates":[-4.62864,55.46489],"type":"Point"}
}