{
  "type": "Feature",
  "properties": {
    "addr:full":"15 County Pl Perth Perth and Kinross PH2 8EE",
    "addr:housenumber":"15",
    "addr:postcode":"ph2 8ee",
    "addr:street":"County Pl",
    "iso:country":"GB",
    "sg:address":"15 County Pl",
    "sg:city":"Perth",
    "sg:classifiers":[
        {
            "category":"Fast Food",
            "type":"Food & Drink"
        }
    ],
    "sg:phone":"+44 1738 629616",
    "sg:postcode":"PH2 8EE",
    "sg:province":"Perth and Kinross",
    "sg:tags":[
        "away",
        "take"
    ],
    "wof:name":"Wing Sing Chip Shop & Chinese Curryhouse",
    "wof:placetype":"venue"
},
  "geometry": {"coordinates":[-3.4281079769,56.3830871582],"type":"Point"}
}