{
  "type": "Feature",
  "properties": {
    "addr:full":"8 Lion Mills, 394-396 Hackney Road London Greater London E2 7ST",
    "addr:housenumber":"8;394-396",
    "addr:postcode":"e2 7st",
    "addr:street":"Lion Mills;Hackney Road",
    "iso:country":"GB",
    "sg:address":"8 Lion Mills, 394-396 Hackney Road",
    "sg:city":"London",
    "sg:classifiers":[
        {
            "category":"Professional",
            "subcategory":"Management & Consulting",
            "type":"Services"
        }
    ],
    "sg:postcode":"E2 7ST",
    "sg:province":"Greater London",
    "sg:tags":[
        "consultant",
        "business"
    ],
    "wof:name":"Up in the Sky Enterprises Ltd",
    "wof:placetype":"venue"
},
  "geometry": {"coordinates":[-0.06292,51.531059],"type":"Point"}
}