{
  "type": "Feature",
  "properties": {
    "addr:full":"64 Bishopgate Norwich Norfolk NR1 4AA",
    "addr:housenumber":"64",
    "addr:postcode":"nr1 4aa",
    "addr:street":"Bishopgate Norwich Norfolk",
    "iso:country":"GB",
    "sg:address":"64 Bishopgate",
    "sg:city":"Norwich",
    "sg:classifiers":[
        {
            "category":"Real Estate",
            "subcategory":"Architect",
            "type":"Services"
        }
    ],
    "sg:phone":"+44 1603 622056",
    "sg:postcode":"NR1 4AA",
    "sg:province":"Norfolk",
    "wof:name":"Nicholas Warns Architects Ltd",
    "wof:placetype":"venue"
},
  "geometry": {"coordinates":[1.307773,52.632347],"type":"Point"}
}