{
  "type": "Feature",
  "properties": {
    "addr:full":"11 Town Square, Syston Leicester Leicestershire LE7 1GZ",
    "addr:housenumber":"11",
    "addr:postcode":"le7 1gz",
    "addr:street":"Town Square",
    "iso:country":"GB",
    "sg:address":"11 Town Square, Syston",
    "sg:city":"Leicester",
    "sg:classifiers":[
        {
            "category":"Shopping",
            "subcategory":"News",
            "type":"Retail Goods"
        }
    ],
    "sg:postcode":"LE7 1GZ",
    "sg:province":"Leicestershire",
    "sg:tags":[
        "newsagent"
    ],
    "wof:name":"Square News",
    "wof:placetype":"venue"
},
  "geometry": {"coordinates":[-1.0737400055,52.6993484497],"type":"Point"}
}