{
  "type": "Feature",
  "properties": {
    "iso:country":"GB",
    "sg:address":"18 Springfield Road",
    "sg:city":"Crawley",
    "sg:classifiers":[
        {
            "category":"Shopping",
            "subcategory":"Computers & Home Electronics",
            "type":"Retail Goods"
        }
    ],
    "sg:phone":"+44 1293 412662",
    "sg:postcode":"RH11 8AD",
    "sg:province":"West Sussex",
    "wof:name":"Abacus Maintenance Services Ltd.",
    "wof:placetype":"venue"
},
  "geometry": {"coordinates":[-0.191952005,51.1125335693],"type":"Point"}
}