{
  "type": "Feature",
  "properties": {
    "iso:country":"GB",
    "sg:address":"Hilton Hotel, Neville Street",
    "sg:city":"Leeds",
    "sg:classifiers":[
        {
            "category":"Sports & Exercise",
            "subcategory":"Gym",
            "type":"Entertainment"
        }
    ],
    "sg:phone":"+44 113 244 5443",
    "sg:postcode":"LS1 4BX",
    "sg:province":"West Yorkshire",
    "sg:tags":[
        "fitness",
        "health",
        "centre"
    ],
    "wof:name":"Livingwell Health Club",
    "wof:placetype":"venue"
},
  "geometry": {"coordinates":[-1.547699,53.793419],"type":"Point"}
}