{
  "type": "Feature",
  "properties": {
    "addr:full":"Chester Works, Chester Avenue Luton Bedfordshire LU4 9SF",
    "addr:postcode":"lu4 9sf",
    "addr:street":"Chester Avenue",
    "iso:country":"GB",
    "sg:address":"Chester Works, Chester Avenue",
    "sg:city":"Luton",
    "sg:classifiers":[
        {
            "category":"Professional",
            "subcategory":"Engineering",
            "type":"Services"
        }
    ],
    "sg:phone":"+44 1582 581309",
    "sg:postcode":"LU4 9SF",
    "sg:province":"Bedfordshire",
    "sg:tags":[
        "gas",
        "engineer"
    ],
    "wof:name":"Marpen",
    "wof:placetype":"venue"
},
  "geometry": {"coordinates":[-0.4560259879,51.8959732056],"type":"Point"}
}