{
  "type": "Feature",
  "properties": {
    "iso:country":"GB",
    "sg:address":"Summerlands Farm, Avon Weir Lane, Christian Malford",
    "sg:city":"Chippenham",
    "sg:classifiers":[
        {
            "category":"Building & Trades",
            "subcategory":"Landscaping Services",
            "type":"Services"
        },
        {
            "category":"Banks & Credit Unions",
            "subcategory":"Investment Brokerage",
            "type":"Services"
        }
    ],
    "sg:phone":"+44 1249 720073",
    "sg:postcode":"SN15 4AY",
    "sg:province":"Wiltshire",
    "sg:tags":[
        "contractor",
        "drainage"
    ],
    "wof:name":"C Pitman & Son",
    "wof:placetype":"venue"
},
  "geometry": {"coordinates":[-2.052589,51.508251],"type":"Point"}
}