{
  "type": "Feature",
  "properties": {
    "addr:full":"107 Barkby Road Leicester Leicestershire LE4 9LG",
    "addr:housenumber":"107",
    "addr:postcode":"le4 9lg",
    "addr:street":"Barkby Road",
    "iso:country":"GB",
    "sg:address":"107 Barkby Road",
    "sg:city":"Leicester",
    "sg:classifiers":[
        {
            "category":"Shopping",
            "subcategory":"Clothing, Apparel, & Fashions",
            "type":"Retail Goods"
        }
    ],
    "sg:phone":"+44 116 276 5858",
    "sg:postcode":"LE4 9LG",
    "sg:province":"Leicestershire",
    "sg:tags":[
        "haberdasher"
    ],
    "wof:name":"Leicester Thread & Trimming Manufacturers Ltd.",
    "wof:placetype":"venue"
},
  "geometry": {"coordinates":[-1.0963619947,52.6580467224],"type":"Point"}
}