{
  "type": "Feature",
  "properties": {
    "iso:country":"GB",
    "sg:address":"2 Wine Street",
    "sg:city":"Devizes",
    "sg:classifiers":[
        {
            "category":"Insurance",
            "subcategory":"Insurance Agent",
            "type":"Services"
        }
    ],
    "sg:phone":"+44 1380 729550",
    "sg:postcode":"SN10 1AP",
    "sg:province":"Wiltshire",
    "sg:tags":[
        "broker"
    ],
    "wof:name":"Kennet Insurance Brokers",
    "wof:placetype":"venue"
},
  "geometry": {"coordinates":[-1.995183,51.35183],"type":"Point"}
}