{
  "type": "Feature",
  "properties": {
    "iso:country":"GB",
    "sg:address":"Coast Road, Blackhall Rocks",
    "sg:city":"Hartlepool",
    "sg:classifiers":[
        {
            "category":"Recreation",
            "subcategory":"Campground",
            "type":"Entertainment"
        }
    ],
    "sg:phone":"+44 191 586 0963",
    "sg:postcode":"TS27 4BL",
    "sg:province":"Durham",
    "sg:tags":[
        "caravan",
        "park"
    ],
    "wof:name":"Denemouth Caravan Park",
    "wof:placetype":"venue"
},
  "geometry": {"coordinates":[-1.276761,54.740417],"type":"Point"}
}