{
  "type": "Feature",
  "properties": {
    "addr:full":"Knowles House, Cromwell Road Redhill Surrey RH1 1RT",
    "addr:postcode":"rh1 1rt",
    "addr:street":"Cromwell Road",
    "iso:country":"GB",
    "sg:address":"Knowles House, Cromwell Road",
    "sg:city":"Redhill",
    "sg:classifiers":[
        {
            "category":"Utilities",
            "subcategory":"Fuel Oil & Lpg",
            "type":"Services"
        }
    ],
    "sg:postcode":"RH1 1RT",
    "sg:province":"Surrey",
    "sg:tags":[
        "gas"
    ],
    "wof:name":"A B B Lummus Global Ltd.",
    "wof:placetype":"venue"
},
  "geometry": {"coordinates":[-0.16959,51.239128],"type":"Point"}
}