{
  "type": "Feature",
  "properties": {
    "addr:full":"Lane End, Loscombe Lane, Four Lanes Redruth Cornwall TR16 6LP",
    "addr:postcode":"tr16 6lp",
    "addr:street":"Loscombe Lane",
    "iso:country":"GB",
    "sg:address":"Lane End, Loscombe Lane, Four Lanes",
    "sg:city":"Redruth",
    "sg:classifiers":[
        {
            "category":"Professional",
            "subcategory":"Art Services",
            "type":"Services"
        }
    ],
    "sg:phone":"+44 1209 214452",
    "sg:postcode":"TR16 6LP",
    "sg:province":"Cornwall",
    "sg:tags":[
        "photographer"
    ],
    "wof:name":"Michael St.James Photography",
    "wof:placetype":"venue"
},
  "geometry": {"coordinates":[-5.2377138138,50.202911377],"type":"Point"}
}