{
  "type": "Feature",
  "properties": {
    "addr:full":"93 St Georges Place Cheltenham Gloucestershire GL50 3QB",
    "addr:housenumber":"93",
    "addr:postcode":"gl50 3qb",
    "addr:street":"St Georges Place",
    "iso:country":"GB",
    "sg:address":"93 St Georges Place",
    "sg:city":"Cheltenham",
    "sg:classifiers":[
        {
            "category":"Professional",
            "subcategory":"Secretarial Services",
            "type":"Services"
        },
        {
            "category":"Professional",
            "subcategory":"Printing & Photocopies",
            "type":"Services"
        }
    ],
    "sg:phone":"+44 1242 528906",
    "sg:postcode":"GL50 3QB",
    "sg:province":"Gloucestershire",
    "sg:tags":[
        "printer"
    ],
    "wof:name":"Top Flight Business Services",
    "wof:placetype":"venue"
},
  "geometry": {"coordinates":[-2.0803520679,51.8995742798],"type":"Point"}
}