{
  "type": "Feature",
  "properties": {
    "addr:full":"71-75 Main Street, Forth, Carnwath Lanark South Lanarkshire ML11 8HH",
    "addr:housenumber":"71-75",
    "addr:postcode":"ml11 8hh",
    "addr:street":"Main Street",
    "iso:country":"GB",
    "sg:address":"71-75 Main Street, Forth, Carnwath",
    "sg:city":"Lanark",
    "sg:classifiers":[
        {
            "category":"Organizations",
            "subcategory":"Membership Organization",
            "type":"Services"
        }
    ],
    "sg:phone":"+44 1555 811627",
    "sg:postcode":"ML11 8HH",
    "sg:province":"South Lanarkshire",
    "sg:tags":[
        "club"
    ],
    "wof:name":"Masonic Lodge",
    "wof:placetype":"venue"
},
  "geometry": {"coordinates":[-3.626308918,55.7004051208],"type":"Point"}
}