{
  "type": "Feature",
  "properties": {
    "addr:full":"City Pool, Northumberland Road Newcastle-upon-tyne Tyne and Wear NE1 8SE",
    "addr:postcode":"ne1 8se",
    "addr:street":"Northumberland Road",
    "iso:country":"GB",
    "sg:address":"City Pool, Northumberland Road",
    "sg:city":"Newcastle-upon-tyne",
    "sg:classifiers":[
        {
            "category":"Health Services",
            "subcategory":"Health Practitioner",
            "type":"Services"
        }
    ],
    "sg:phone":"+44 191 233 0500",
    "sg:postcode":"NE1 8SE",
    "sg:province":"Tyne and Wear",
    "sg:tags":[
        "physiotherapist"
    ],
    "wof:name":"The Sports Injury Clinic",
    "wof:placetype":"venue"
},
  "geometry": {"coordinates":[-1.6073590517,54.9775352478],"type":"Point"}
}