{
  "type": "Feature",
  "properties": {
    "addr:full":"Wellington Ho, Sweet St Leeds West Yorkshire LS11 9DB",
    "addr:postcode":"ls11 9db",
    "addr:street":"St;West",
    "iso:country":"GB",
    "sg:address":"Wellington Ho, Sweet St",
    "sg:city":"Leeds",
    "sg:classifiers":[
        {
            "category":"Professional",
            "subcategory":"Engineering",
            "type":"Services"
        }
    ],
    "sg:phone":"+44 113 243 4780",
    "sg:postcode":"LS11 9DB",
    "sg:province":"West Yorkshire",
    "sg:tags":[
        "engineer",
        "mechanical"
    ],
    "wof:name":"Crown House Engineering",
    "wof:placetype":"venue"
},
  "geometry": {"coordinates":[-1.5480639935,53.7961502075],"type":"Point"}
}