{
  "type": "Feature",
  "properties": {
    "iso:country":"GB",
    "sg:address":"Station Rd",
    "sg:city":"Kendal",
    "sg:classifiers":[
        {
            "category":"Shopping",
            "subcategory":"Discount & Variety Stores",
            "type":"Retail Goods"
        }
    ],
    "sg:phone":"+44 1539 720299",
    "sg:postcode":"LA9 6BT",
    "sg:province":"Cumbria",
    "sg:tags":[
        "cleaning",
        "supply"
    ],
    "wof:name":"Alpha Supplies Ltd",
    "wof:placetype":"venue"
},
  "geometry": {"coordinates":[-2.741605,54.331707],"type":"Point"}
}