{
  "type": "Feature",
  "properties": {
    "iso:country":"GB",
    "sg:address":"240 Dalston Lane",
    "sg:city":"London",
    "sg:classifiers":[
        {
            "category":"Personal",
            "subcategory":"Beauty Salon",
            "type":"Services"
        }
    ],
    "sg:phone":"+44 20 8986 9878",
    "sg:postcode":"E8 1JG",
    "sg:province":"Greater London",
    "sg:tags":[
        "ladies",
        "lady",
        "hairdresser"
    ],
    "wof:name":"MAYS HAIRDRESSERS",
    "wof:placetype":"venue"
},
  "geometry": {"coordinates":[-0.059273,51.549397],"type":"Point"}
}