{
  "type": "Feature",
  "properties": {
    "iso:country":"GB",
    "sg:address":"10 Greenfield Terrace, Cefn Pennar",
    "sg:city":"Mountain Ash",
    "sg:classifiers":[
        {
            "category":"Taxi",
            "type":"Transportation"
        }
    ],
    "sg:phone":"+44 1443 479314",
    "sg:postcode":"CF45 4EB",
    "sg:province":"Rhondda, Cynon, Taff",
    "sg:tags":[
        "mini",
        "cab"
    ],
    "wof:name":"Pete's Cars",
    "wof:placetype":"venue"
},
  "geometry": {"coordinates":[-3.323813,51.649395],"type":"Point"}
}