{
  "type": "Feature",
  "properties": {
    "addr:full":"83 Foregate Street Chester Cheshire CH1 1HE",
    "addr:housenumber":"83",
    "addr:postcode":"ch1 1he",
    "addr:street":"Foregate Street",
    "iso:country":"GB",
    "sg:address":"83 Foregate Street",
    "sg:city":"Chester",
    "sg:classifiers":[
        {
            "category":"Food & Beverages",
            "subcategory":"Bakery",
            "type":"Retail Goods"
        }
    ],
    "sg:phone":"+44 1244 346991",
    "sg:postcode":"CH1 1HE",
    "sg:province":"Cheshire",
    "sg:tags":[
        "pizza"
    ],
    "wof:name":"Pizza Hut",
    "wof:placetype":"venue"
},
  "geometry": {"coordinates":[-2.885493,53.191555],"type":"Point"}
}