{
  "type": "Feature",
  "properties": {
    "addr:full":"Corner House, Station Road Tidworth Hampshire SP9 7NW",
    "addr:postcode":"sp9 7nw",
    "addr:street":"Station Road",
    "iso:country":"GB",
    "sg:address":"Corner House, Station Road",
    "sg:city":"Tidworth",
    "sg:classifiers":[
        {
            "category":"Organizations",
            "subcategory":"Non-profit Organization",
            "type":"Services"
        }
    ],
    "sg:postcode":"SP9 7NW",
    "sg:province":"Hampshire",
    "sg:tags":[
        "organisation",
        "animal",
        "welfare"
    ],
    "wof:name":"The Veterinary Hospital",
    "wof:placetype":"venue"
},
  "geometry": {"coordinates":[-1.659516,51.234459],"type":"Point"}
}