{
  "type": "Feature",
  "properties": {
    "addr:full":"1-3 York Street Manchester Greater Manchester M1 7DE",
    "addr:housenumber":"1-3",
    "addr:postcode":"m1 7de",
    "addr:street":"York Street",
    "iso:country":"GB",
    "sg:address":"1-3 York Street",
    "sg:city":"Manchester",
    "sg:classifiers":[
        {
            "category":"Organizations",
            "subcategory":"Religious Organization",
            "type":"Services"
        }
    ],
    "sg:phone":"+44 161 273 8894",
    "sg:postcode":"M1 7DE",
    "sg:province":"Greater Manchester",
    "sg:tags":[
        "organisation",
        "place",
        "worship"
    ],
    "wof:name":"Christian Action",
    "wof:placetype":"venue"
},
  "geometry": {"coordinates":[-2.239685,53.474182],"type":"Point"}
}