{
  "type": "Feature",
  "properties": {
    "addr:full":"47 Hathaway Road Liverpool Merseyside L25 4ST",
    "addr:housenumber":"47",
    "addr:postcode":"l25 4st",
    "addr:street":"Hathaway Road",
    "iso:country":"GB",
    "sg:address":"47 Hathaway Road",
    "sg:city":"Liverpool",
    "sg:classifiers":[
        {
            "category":"Education",
            "subcategory":"University",
            "type":"Public Place"
        }
    ],
    "sg:phone":"+44 151 428 4679",
    "sg:postcode":"L25 4ST",
    "sg:province":"Merseyside",
    "sg:tags":[
        "higher"
    ],
    "wof:name":"I O Roberts",
    "wof:placetype":"venue"
},
  "geometry": {"coordinates":[-2.867585,53.390327],"type":"Point"}
}