{
  "type": "Feature",
  "properties": {
    "addr:full":"181 Headstone Lane Harrow Greater London HA2 6LX",
    "addr:housenumber":"181",
    "addr:postcode":"ha2 6lx",
    "addr:street":"Headstone Lane",
    "iso:country":"GB",
    "sg:address":"181 Headstone Lane",
    "sg:city":"Harrow",
    "sg:classifiers":[
        {
            "category":"Manufacturing",
            "subcategory":"Petroleum Products",
            "type":"Manufacturing & Wholesale Goods"
        }
    ],
    "sg:phone":"+44 20 8428 9612",
    "sg:postcode":"HA2 6LX",
    "sg:province":"Greater London",
    "sg:tags":[
        "double",
        "glazing"
    ],
    "wof:name":"D G Installations",
    "wof:placetype":"venue"
},
  "geometry": {"coordinates":[-0.355595,51.600765],"type":"Point"}
}