{
  "type": "Feature",
  "properties": {
    "addr:full":"Lauda Lane, Roundswell Barnstaple Devon EX31 3TA",
    "addr:postcode":"ex31 3ta",
    "addr:street":"Lauda Lane",
    "iso:country":"GB",
    "sg:address":"Lauda Lane, Roundswell",
    "sg:city":"Barnstaple",
    "sg:classifiers":[
        {
            "category":"Shopping",
            "type":"Retail Goods"
        }
    ],
    "sg:phone":"+44 1271 327442",
    "sg:postcode":"EX31 3TA",
    "sg:province":"Devon",
    "sg:tags":[
        "part",
        "accessory"
    ],
    "wof:name":"Pat Williams Ltd.",
    "wof:placetype":"venue"
},
  "geometry": {"coordinates":[-4.082881,51.064312],"type":"Point"}
}