{
  "type": "Feature",
  "properties": {
    "addr:full":"38 St Giles Street Northampton Northamptonshire NN1 1JW",
    "addr:housenumber":"38",
    "addr:postcode":"nn1 1jw",
    "addr:street":"St Giles Street",
    "iso:country":"GB",
    "sg:address":"38 St Giles Street",
    "sg:city":"Northampton",
    "sg:classifiers":[
        {
            "category":"Travel",
            "subcategory":"Travel Agent",
            "type":"Entertainment"
        }
    ],
    "sg:phone":"+44 1604 630261",
    "sg:postcode":"NN1 1JW",
    "sg:province":"Northamptonshire",
    "wof:name":"Yorks Travel Agents",
    "wof:placetype":"venue"
},
  "geometry": {"coordinates":[-0.890829,52.237621],"type":"Point"}
}