{
  "type": "Feature",
  "properties": {
    "iso:country":"GB",
    "sg:address":"517 Foleshill Road",
    "sg:city":"Coventry",
    "sg:classifiers":[
        {
            "category":"Professional",
            "subcategory":"Art Services",
            "type":"Services"
        }
    ],
    "sg:postcode":"CV6 5AU",
    "sg:province":"Warwickshire",
    "sg:tags":[
        "photographer"
    ],
    "wof:name":"B S V Photography",
    "wof:placetype":"venue"
},
  "geometry": {"coordinates":[-1.499203,52.42873],"type":"Point"}
}