{
  "type": "Feature",
  "properties": {
    "addr:full":"127 Commercial Rd Whitechapel Greater London E1 1PU",
    "addr:housenumber":"127",
    "addr:postcode":"e1 1pu",
    "addr:street":"Commercial Rd",
    "iso:country":"GB",
    "sg:address":"127 Commercial Rd",
    "sg:city":"Whitechapel",
    "sg:classifiers":[
        {
            "category":"Personal",
            "subcategory":"Skin Care",
            "type":"Services"
        }
    ],
    "sg:phone":"+44 20 7377 9324",
    "sg:postcode":"E1 1PU",
    "sg:province":"Greater London",
    "sg:tags":[
        "leather",
        "merchant"
    ],
    "wof:name":"Leather World",
    "wof:placetype":"venue"
},
  "geometry": {"coordinates":[-0.062865,51.51482],"type":"Point"}
}