{
  "type": "Feature",
  "properties": {
    "addr:full":"124 Brook St Erith Kent DA8 1JF",
    "addr:housenumber":"124",
    "addr:postcode":"da8 1jf",
    "addr:street":"Brook St",
    "iso:country":"GB",
    "sg:address":"124 Brook St",
    "sg:city":"Erith",
    "sg:classifiers":[
        {
            "category":"Farming",
            "subcategory":"Fish & Marine Products",
            "type":"Manufacturing & Wholesale Goods"
        },
        {
            "category":"Food & Beverages",
            "subcategory":"Meat & Fish",
            "type":"Retail Goods"
        }
    ],
    "sg:postcode":"DA8 1JF",
    "sg:province":"Kent",
    "sg:tags":[
        "fishmonger",
        "butcher"
    ],
    "wof:name":"Still,Fred,",
    "wof:placetype":"venue"
},
  "geometry": {"coordinates":[0.157654,51.474461],"type":"Point"}
}