{
  "type": "Feature",
  "properties": {
    "iso:country":"GB",
    "sg:address":"Tregenna Hill",
    "sg:city":"St Ives",
    "sg:classifiers":[
        {
            "category":"Place Of Worship",
            "type":"Public Place"
        }
    ],
    "sg:postcode":"TR26 1SE",
    "sg:province":"Cornwall",
    "wof:name":"Sacred Heart R C Church",
    "wof:placetype":"venue"
},
  "geometry": {"coordinates":[-5.4805822372,50.2110481262],"type":"Point"}
}