{
  "type": "Feature",
  "properties": {
    "addr:full":"1 Hartill St Stoke On Trent Staffordshire ST4 2AT",
    "addr:housenumber":"1",
    "addr:postcode":"st4 2at",
    "addr:street":"Hartill St",
    "iso:country":"GB",
    "sg:address":"1 Hartill St",
    "sg:city":"Stoke On Trent",
    "sg:classifiers":[
        {
            "category":"Food & Beverages",
            "subcategory":"Groceries & Convenience Stores",
            "type":"Retail Goods"
        }
    ],
    "sg:phone":"+44 1782 744750",
    "sg:postcode":"ST4 2AT",
    "sg:province":"Staffordshire",
    "wof:name":"Sunny Stores",
    "wof:placetype":"venue"
},
  "geometry": {"coordinates":[-2.1783699989,53.0072975159],"type":"Point"}
}