{
  "type": "Feature",
  "properties": {
    "addr:full":"116 Salmon Lane London Greater London E14 7PQ",
    "addr:housenumber":"116",
    "addr:postcode":"e14 7pq",
    "addr:street":"Salmon Lane",
    "iso:country":"GB",
    "sg:address":"116 Salmon Lane",
    "sg:city":"London",
    "sg:classifiers":[
        {
            "category":"Fast Food",
            "type":"Food & Drink"
        }
    ],
    "sg:phone":"+44 20 7515 3822",
    "sg:postcode":"E14 7PQ",
    "sg:province":"Greater London",
    "sg:tags":[
        "away",
        "take"
    ],
    "wof:name":"May Moon Takeaway",
    "wof:placetype":"venue"
},
  "geometry": {"coordinates":[-0.033969,51.5138816833],"type":"Point"}
}