{
  "type": "Feature",
  "properties": {
    "iso:country":"GB",
    "sg:address":"Hortonwood",
    "sg:city":"Telford",
    "sg:classifiers":[
        {
            "category":"Shopping",
            "subcategory":"Computers & Home Electronics",
            "type":"Retail Goods"
        }
    ],
    "sg:phone":"+44 1952 677899",
    "sg:postcode":"TF1 7FS",
    "sg:province":"Shropshire",
    "sg:tags":[
        "electrical"
    ],
    "wof:name":"Ashley & Rock Ltd.",
    "wof:placetype":"venue"
},
  "geometry": {"coordinates":[-2.456299,52.716648],"type":"Point"}
}