{
  "type": "Feature",
  "properties": {
    "addr:full":"17 Craven Ct, Winwick Quay Warrington Cheshire WA2 8QU",
    "addr:housenumber":"17",
    "addr:postcode":"wa2 8qu",
    "addr:street":"Craven Ct",
    "iso:country":"GB",
    "sg:address":"17 Craven Ct, Winwick Quay",
    "sg:city":"Warrington",
    "sg:classifiers":[
        {
            "category":"Professional",
            "type":"Services"
        }
    ],
    "sg:postcode":"WA2 8QU",
    "sg:province":"Cheshire",
    "sg:tags":[
        "caterer"
    ],
    "wof:name":"Stevenson,Brian,",
    "wof:placetype":"venue"
},
  "geometry": {"coordinates":[-2.608266,53.420822],"type":"Point"}
}