{
  "type": "Feature",
  "properties": {
    "iso:country":"GB",
    "sg:address":"Quayside",
    "sg:city":"Newcastle-upon-tyne",
    "sg:classifiers":[
        {
            "category":"Restaurant",
            "type":"Food & Drink"
        }
    ],
    "sg:phone":"+44 191 222 1701",
    "sg:postcode":"NE1 3DE",
    "sg:province":"Tyne and Wear",
    "wof:name":"Heartbreak Soup",
    "wof:placetype":"venue"
},
  "geometry": {"coordinates":[-1.60422,54.969269],"type":"Point"}
}