{
  "type": "Feature",
  "properties": {
    "iso:country":"GB",
    "sg:address":"544 London Road",
    "sg:city":"Isleworth",
    "sg:classifiers":[
        {
            "category":"Taxi",
            "type":"Transportation"
        },
        {
            "category":"Retail",
            "subcategory":"Auto Rental",
            "type":"Services"
        },
        {
            "category":"Government",
            "subcategory":"Post Office",
            "type":"Public Place"
        }
    ],
    "sg:phone":"+44 20 8847 0505",
    "sg:postcode":"TW7 4EP",
    "sg:province":"Greater London",
    "sg:tags":[
        "chauffeur",
        "mini",
        "hire",
        "courier",
        "car",
        "driven",
        "messenger",
        "cab"
    ],
    "wof:name":"CENTRAL CARS",
    "wof:placetype":"venue"
},
  "geometry": {"coordinates":[-0.344048,51.474522],"type":"Point"}
}