{
  "type": "Feature",
  "properties": {
    "addr:full":"254 King Street Castle Douglas Dumfries and Galloway DG7 1HA",
    "addr:housenumber":"254",
    "addr:postcode":"dg7 1ha",
    "addr:street":"King Street",
    "iso:country":"GB",
    "sg:address":"254 King Street",
    "sg:city":"Castle Douglas",
    "sg:classifiers":[
        {
            "category":"Food & Beverages",
            "subcategory":"Meat & Fish",
            "type":"Retail Goods"
        }
    ],
    "sg:postcode":"DG7 1HA",
    "sg:province":"Dumfries and Galloway",
    "sg:tags":[
        "chip"
    ],
    "wof:name":"W & M Moore & Sons",
    "wof:placetype":"venue"
},
  "geometry": {"coordinates":[-3.933604,54.938065],"type":"Point"}
}