{
  "type": "Feature",
  "properties": {
    "iso:country":"GB",
    "sg:address":"Market Place",
    "sg:city":"Alston",
    "sg:classifiers":[
        {
            "category":"Home & Garden",
            "subcategory":"Carpets & Floor Coverings",
            "type":"Retail Goods"
        }
    ],
    "sg:phone":"+44 1434 381452",
    "sg:postcode":"CA9 3HS",
    "sg:province":"Cumbria",
    "sg:tags":[
        "carpets",
        "rug",
        "matting"
    ],
    "wof:name":"Camelot Carpets",
    "wof:placetype":"venue"
},
  "geometry": {"coordinates":[-2.438751936,54.8123817444],"type":"Point"}
}