{
  "type": "Feature",
  "properties": {
    "addr:full":"5 Old School Lane, Blakesley Towcester Buckinghamshire NN12 8RS",
    "addr:housenumber":"5",
    "addr:postcode":"nn12 8rs",
    "addr:street":"Old School Lane",
    "iso:country":"GB",
    "sg:address":"5 Old School Lane, Blakesley",
    "sg:city":"Towcester",
    "sg:classifiers":[
        {
            "category":"Professional",
            "subcategory":"Engineering",
            "type":"Services"
        }
    ],
    "sg:postcode":"NN12 8RS",
    "sg:province":"Buckinghamshire",
    "wof:name":"Penny Mechanical Services Ltd.",
    "wof:placetype":"venue"
},
  "geometry": {"coordinates":[-1.089317,52.145317],"type":"Point"}
}