{
  "type": "Feature",
  "properties": {
    "addr:full":"Lonsdale House, 52 Blucher St Birmingham West Midlands B1 1QU",
    "addr:housenumber":"52",
    "addr:postcode":"b1 1qu",
    "addr:street":"Blucher St",
    "iso:country":"GB",
    "sg:address":"Lonsdale House, 52 Blucher St",
    "sg:city":"Birmingham",
    "sg:classifiers":[
        {
            "category":"Building & Trades",
            "subcategory":"Plumbing",
            "type":"Services"
        }
    ],
    "sg:phone":"+44 24 7622 9221",
    "sg:postcode":"B1 1QU",
    "sg:province":"West Midlands",
    "sg:tags":[
        "heating"
    ],
    "wof:name":"AJB Plumbing",
    "wof:placetype":"venue"
},
  "geometry": {"coordinates":[-1.903481,52.474751],"type":"Point"}
}