{
  "type": "Feature",
  "properties": {
    "iso:country":"GB",
    "sg:address":"365 Watling Street",
    "sg:city":"Tamworth",
    "sg:classifiers":[
        {
            "category":"Autos & Motor Vehicles",
            "subcategory":"Automobile Sales",
            "type":"Retail Goods"
        }
    ],
    "sg:phone":"+44 1827 261690",
    "sg:postcode":"B77 5AD",
    "sg:province":"Staffordshire",
    "sg:tags":[
        "commercial"
    ],
    "wof:name":"Mercia Car Centre",
    "wof:placetype":"venue"
},
  "geometry": {"coordinates":[-1.678974,52.610901],"type":"Point"}
}