{
  "type": "Feature",
  "properties": {
    "addr:full":"32a Floyd Road London Greater London SE7 8AN",
    "addr:housenumber":"32a",
    "addr:postcode":"se7 8an",
    "addr:street":"Floyd Road",
    "iso:country":"GB",
    "sg:address":"32a Floyd Road",
    "sg:city":"London",
    "sg:classifiers":[
        {
            "category":"Building & Trades",
            "subcategory":"Construction",
            "type":"Services"
        }
    ],
    "sg:phone":"+44 20 8858 7820",
    "sg:postcode":"SE7 8AN",
    "sg:province":"Greater London",
    "sg:tags":[
        "decorator",
        "painter"
    ],
    "wof:name":"Moorsby Decorators",
    "wof:placetype":"venue"
},
  "geometry": {"coordinates":[0.033533,51.486603],"type":"Point"}
}