{
  "type": "Feature",
  "properties": {
    "addr:full":"31 High Street, Tunstall Stoke-on-trent Staffordshire ST6 5TD",
    "addr:housenumber":"31",
    "addr:postcode":"staffordshire st6 5td",
    "addr:street":"High Street",
    "iso:country":"GB",
    "sg:address":"31 High Street, Tunstall",
    "sg:city":"Stoke-on-trent",
    "sg:classifiers":[
        {
            "category":"Real Estate",
            "subcategory":"Real Estate Agent",
            "type":"Services"
        }
    ],
    "sg:postcode":"ST6 5TD",
    "sg:province":"Staffordshire",
    "wof:name":"Prime Property & Mortgage Services",
    "wof:placetype":"venue"
},
  "geometry": {"coordinates":[-2.2107610703,53.0557365417],"type":"Point"}
}