{
  "type": "Feature",
  "properties": {
    "addr:full":"52 High Street Evesham Gloucestershire WR11 4HG",
    "addr:housenumber":"52",
    "addr:postcode":"wr11 4hg",
    "addr:street":"High Street",
    "iso:country":"GB",
    "sg:address":"52 High Street",
    "sg:city":"Evesham",
    "sg:classifiers":[
        {
            "category":"Personal",
            "subcategory":"Beauty Salon",
            "type":"Services"
        }
    ],
    "sg:phone":"+44 1386 442241",
    "sg:postcode":"WR11 4HG",
    "sg:province":"Gloucestershire",
    "sg:tags":[
        "unisex",
        "hairdresser"
    ],
    "wof:name":"Shirleys",
    "wof:placetype":"venue"
},
  "geometry": {"coordinates":[-1.9465919733,52.0938568115],"type":"Point"}
}