{
  "type": "Feature",
  "properties": {
    "iso:country":"GB",
    "sg:address":"13 Woodbury Rd",
    "sg:city":"Bridgwater",
    "sg:classifiers":[
        {
            "category":"Building & Trades",
            "subcategory":"Construction",
            "type":"Services"
        }
    ],
    "sg:phone":"+44 1278 426395",
    "sg:postcode":"TA6 7LQ",
    "sg:province":"Somerset",
    "sg:tags":[
        "joiner",
        "carpenter"
    ],
    "wof:name":"W G Wardle",
    "wof:placetype":"venue"
},
  "geometry": {"coordinates":[-3.02078,51.123463],"type":"Point"}
}