{
  "type": "Feature",
  "properties": {
    "addr:full":"1 Walton House, Grove Road Surbiton Surrey KT6 4DB",
    "addr:housenumber":"1",
    "addr:postcode":"kt6 4db",
    "addr:street":"House Grove Road",
    "iso:country":"GB",
    "sg:address":"1 Walton House, Grove Road",
    "sg:city":"Surbiton",
    "sg:classifiers":[
        {
            "category":"Professional",
            "subcategory":"Accounting & Tax Preparation",
            "type":"Services"
        }
    ],
    "sg:postcode":"KT6 4DB",
    "sg:province":"Surrey",
    "sg:tags":[
        "accountant"
    ],
    "wof:name":"Armstrong & Co",
    "wof:placetype":"venue"
},
  "geometry": {"coordinates":[-0.306949,51.392059],"type":"Point"}
}