{
  "type": "Feature",
  "properties": {
    "iso:country":"GB",
    "sg:address":"138 Preston Road, Grimsargh",
    "sg:city":"Preston",
    "sg:classifiers":[
        {
            "category":"Food & Beverages",
            "subcategory":"Meat & Fish",
            "type":"Retail Goods"
        }
    ],
    "sg:phone":"+44 1772 651331",
    "sg:postcode":"PR2 5JQ",
    "sg:province":"Lancashire",
    "sg:tags":[
        "chip"
    ],
    "wof:name":"New World Takeway",
    "wof:placetype":"venue"
},
  "geometry": {"coordinates":[-2.6324460506,53.8043785095],"type":"Point"}
}