{
  "type": "Feature",
  "properties": {
    "iso:country":"GB",
    "sg:address":"370-372 King Street",
    "sg:city":"London",
    "sg:classifiers":[
        {
            "category":"Food & Beverages",
            "subcategory":"Liquor & Beverages",
            "type":"Retail Goods"
        }
    ],
    "sg:phone":"+44 20 8748 2916",
    "sg:postcode":"W6 0RX",
    "sg:province":"Greater London",
    "sg:tags":[
        "beer",
        "spirit",
        "wines"
    ],
    "wof:name":"Fuller Smith & Turner Plc",
    "wof:placetype":"venue"
},
  "geometry": {"coordinates":[-0.244508,51.493553],"type":"Point"}
}