{
  "type": "Feature",
  "properties": {
    "addr:full":"52 Albemarle Gate Cheltenham Gloucestershire GL50 4PJ",
    "addr:housenumber":"52",
    "addr:postcode":"gl50 4pj",
    "addr:street":"Albemarle Gate",
    "iso:country":"GB",
    "sg:address":"52 Albemarle Gate",
    "sg:city":"Cheltenham",
    "sg:classifiers":[
        {
            "category":"Banks & Credit Unions",
            "subcategory":"Bank",
            "type":"Services"
        }
    ],
    "sg:phone":"+44 1242 524822",
    "sg:postcode":"GL50 4PJ",
    "sg:province":"Gloucestershire",
    "sg:tags":[
        "stocktaking",
        "inventory"
    ],
    "wof:name":"Maurice Bird",
    "wof:placetype":"venue"
},
  "geometry": {"coordinates":[-2.0736269951,51.9117622375],"type":"Point"}
}