{
  "type": "Feature",
  "properties": {
    "addr:full":"25 Broughton Street Edinburgh City of Edinburgh EH1 3JU",
    "addr:housenumber":"25",
    "addr:postcode":"eh1 3ju",
    "addr:street":"Broughton Street",
    "iso:country":"GB",
    "sg:address":"25 Broughton Street",
    "sg:city":"Edinburgh",
    "sg:classifiers":[
        {
            "category":"Bars & Pubs",
            "type":"Food & Drink"
        }
    ],
    "sg:phone":"+44 131 556 6754",
    "sg:postcode":"EH1 3JU",
    "sg:province":"City of Edinburgh",
    "sg:tags":[
        "pubs",
        "inn"
    ],
    "wof:name":"Mathers Bar",
    "wof:placetype":"venue"
},
  "geometry": {"coordinates":[-3.1878559589,55.9570388794],"type":"Point"}
}