{
  "type": "Feature",
  "properties": {
    "addr:full":"3 Studley St Birmingham West Midlands B12 8JB",
    "addr:housenumber":"3",
    "addr:postcode":"b12 8jb",
    "addr:street":"Studley St",
    "iso:country":"GB",
    "sg:address":"3 Studley St",
    "sg:city":"Birmingham",
    "sg:classifiers":[
        {
            "category":"Retail",
            "subcategory":"Storage",
            "type":"Services"
        }
    ],
    "sg:phone":"+44 121 773 1313",
    "sg:postcode":"B12 8JB",
    "sg:province":"West Midlands",
    "sg:tags":[
        "household",
        "removal"
    ],
    "wof:name":"Interfreight Worldwide Ltd",
    "wof:placetype":"venue"
},
  "geometry": {"coordinates":[-1.875564,52.458179],"type":"Point"}
}