{
  "type": "Feature",
  "properties": {
    "iso:country":"GB",
    "sg:address":"97 Wood Road",
    "sg:city":"Maldon",
    "sg:classifiers":[
        {
            "category":"Food & Beverages",
            "subcategory":"Fruits & Vegetables",
            "type":"Retail Goods"
        }
    ],
    "sg:phone":"+44 1621 853110",
    "sg:postcode":"CM9 4AS",
    "sg:province":"Essex",
    "sg:tags":[
        "greengrocer"
    ],
    "wof:name":"G G Cox",
    "wof:placetype":"venue"
},
  "geometry": {"coordinates":[0.694537,51.746635],"type":"Point"}
}