{
  "type": "Feature",
  "properties": {
    "addr:full":"70 Hadley Road Barnet Hertfordshire EN5 5QS",
    "addr:housenumber":"70",
    "addr:postcode":"en5 5qs",
    "addr:street":"Hadley Road",
    "iso:country":"GB",
    "sg:address":"70 Hadley Road",
    "sg:city":"Barnet",
    "sg:classifiers":[
        {
            "category":"Professional",
            "subcategory":"Art Services",
            "type":"Services"
        }
    ],
    "sg:phone":"+44 20 8449 2025",
    "sg:postcode":"EN5 5QS",
    "sg:province":"Hertfordshire",
    "sg:tags":[
        "consultant",
        "design"
    ],
    "wof:name":"Bruce Fazan & Co",
    "wof:placetype":"venue"
},
  "geometry": {"coordinates":[-0.1829659939,51.6545829773],"type":"Point"}
}