{
  "type": "Feature",
  "properties": {
    "addr:full":"88 Liverpool Road, Irlam Manchester Greater Manchester M44 6FN",
    "addr:housenumber":"88",
    "addr:postcode":"m44 6fn",
    "addr:street":"Liverpool Road",
    "iso:country":"GB",
    "sg:address":"88 Liverpool Road, Irlam",
    "sg:city":"Manchester",
    "sg:classifiers":[
        {
            "category":"Food & Beverages",
            "subcategory":"Groceries & Convenience Stores",
            "type":"Retail Goods"
        }
    ],
    "sg:phone":"+44 161 775 2411",
    "sg:postcode":"M44 6FN",
    "sg:province":"Greater Manchester",
    "wof:name":"Greenalls Food Store",
    "wof:placetype":"venue"
},
  "geometry": {"coordinates":[-2.410723,53.452618],"type":"Point"}
}