{
  "type": "Feature",
  "properties": {
    "iso:country":"GB",
    "sg:address":"91 Langdale Way",
    "sg:city":"East Boldon",
    "sg:classifiers":[
        {
            "category":"Professional",
            "subcategory":"Engineering",
            "type":"Services"
        }
    ],
    "sg:phone":"+44 191 519 3721",
    "sg:postcode":"NE36 0UE",
    "sg:province":"Tyne and Wear",
    "sg:tags":[
        "contractor",
        "electrical",
        "engineer"
    ],
    "wof:name":"K Giles",
    "wof:placetype":"venue"
},
  "geometry": {"coordinates":[-1.439023,54.947124],"type":"Point"}
}