{
  "type": "Feature",
  "properties": {
    "addr:full":"8 Commonside Sheffield South Yorkshire S10 1GB",
    "addr:housenumber":"8",
    "addr:postcode":"s10 1gb",
    "addr:street":"Commonside",
    "iso:country":"GB",
    "sg:address":"8 Commonside",
    "sg:city":"Sheffield",
    "sg:classifiers":[
        {
            "category":"Professional",
            "subcategory":"Detective & Security Services",
            "type":"Services"
        }
    ],
    "sg:phone":"+44 114 266 4332",
    "sg:postcode":"S10 1GB",
    "sg:province":"South Yorkshire",
    "wof:name":"Ingerpam Ltd.",
    "wof:placetype":"venue"
},
  "geometry": {"coordinates":[-1.4979389906,53.3875389099],"type":"Point"}
}