{
  "type": "Feature",
  "properties": {
    "addr:full":"Great North Road, Alconbury Huntingdon Bedfordshire PE28 4EX",
    "addr:postcode":"pe28 4ex",
    "addr:street":"Great North Road",
    "iso:country":"GB",
    "sg:address":"Great North Road, Alconbury",
    "sg:city":"Huntingdon",
    "sg:classifiers":[
        {
            "category":"Building & Trades",
            "subcategory":"Construction",
            "type":"Services"
        }
    ],
    "sg:phone":"+44 1480 891458",
    "sg:postcode":"PE28 4EX",
    "sg:province":"Bedfordshire",
    "sg:tags":[
        "contractor",
        "paving",
        "driveway"
    ],
    "wof:name":"Alconbury Paving",
    "wof:placetype":"venue"
},
  "geometry": {"coordinates":[-0.2611840069,52.3662796021],"type":"Point"}
}