{
  "type": "Feature",
  "properties": {
    "addr:full":"52 Coxwell Road Faringdon Oxfordshire SN7 7JX",
    "addr:housenumber":"52",
    "addr:postcode":"sn7 7jx",
    "addr:street":"Coxwell Road",
    "iso:country":"GB",
    "sg:address":"52 Coxwell Road",
    "sg:city":"Faringdon",
    "sg:classifiers":[
        {
            "category":"Building & Trades",
            "subcategory":"Construction",
            "type":"Services"
        }
    ],
    "sg:phone":"+44 1367 244509",
    "sg:postcode":"SN7 7JX",
    "sg:province":"Oxfordshire",
    "sg:tags":[
        "contractor",
        "paving",
        "driveway"
    ],
    "wof:name":"D O'Sullivan",
    "wof:placetype":"venue"
},
  "geometry": {"coordinates":[-1.592343,51.650875],"type":"Point"}
}