{
  "type": "Feature",
  "properties": {
    "addr:full":"23 Eskbank Road Dalkeith City of Edinburgh EH22 1HG",
    "addr:housenumber":"23",
    "addr:postcode":"eh22 1hg",
    "addr:street":"Eskbank Road",
    "iso:country":"GB",
    "sg:address":"23 Eskbank Road",
    "sg:city":"Dalkeith",
    "sg:classifiers":[
        {
            "category":"Organizations",
            "subcategory":"Non-profit Organization",
            "type":"Services"
        }
    ],
    "sg:phone":"+44 131 663 9827",
    "sg:postcode":"EH22 1HG",
    "sg:province":"City of Edinburgh",
    "sg:tags":[
        "charitable",
        "organisation",
        "voluntary",
        "charity"
    ],
    "wof:name":"Midlothian Womens Aid",
    "wof:placetype":"venue"
},
  "geometry": {"coordinates":[-3.072961092,55.8925361633],"type":"Point"}
}