{
  "type": "Feature",
  "properties": {
    "iso:country":"GB",
    "sg:address":"The Views, Hillside Of Dendoldrum, Inverbervie",
    "sg:city":"Montrose",
    "sg:classifiers":[
        {
            "category":"Education",
            "subcategory":"Music School",
            "type":"Public Place"
        }
    ],
    "sg:phone":"+44 1561 361665",
    "sg:postcode":"DD10 0PG",
    "sg:province":"Aberdeenshire",
    "sg:tags":[
        "conservatory"
    ],
    "wof:name":"Atlas Windows & Conservatories Ltd",
    "wof:placetype":"venue"
},
  "geometry": {"coordinates":[-2.2805979252,56.8441848755],"type":"Point"}
}