{
  "type": "Feature",
  "properties": {
    "iso:country":"GB",
    "sg:address":"Goodman Street",
    "sg:city":"Leeds",
    "sg:classifiers":[
        {
            "category":"Building & Trades",
            "subcategory":"Construction",
            "type":"Services"
        }
    ],
    "sg:phone":"+44 113 271 0200",
    "sg:postcode":"LS10 1NY",
    "sg:province":"West Yorkshire",
    "sg:tags":[
        "contractor"
    ],
    "wof:name":"C B M Construction Group Ltd.",
    "wof:placetype":"venue"
},
  "geometry": {"coordinates":[-1.524324,53.784554],"type":"Point"}
}