{
  "type": "Feature",
  "properties": {
    "addr:full":"58 Telford Avenue London Greater London SW2 4XF",
    "addr:housenumber":"58",
    "addr:postcode":"sw2 4xf",
    "addr:street":"Telford Avenue",
    "iso:country":"GB",
    "sg:address":"58 Telford Avenue",
    "sg:city":"London",
    "sg:classifiers":[
        {
            "category":"Professional",
            "subcategory":"Management & Consulting",
            "type":"Services"
        }
    ],
    "sg:postcode":"SW2 4XF",
    "sg:province":"Greater London",
    "sg:tags":[
        "consultant",
        "business"
    ],
    "wof:name":"S Viggiani Management Consultants",
    "wof:placetype":"venue"
},
  "geometry": {"coordinates":[-0.130738005,51.4420013428],"type":"Point"}
}