{
  "type": "Feature",
  "properties": {
    "iso:country":"GB",
    "sg:address":"High Street",
    "sg:city":"Moreton-in-marsh",
    "sg:classifiers":[
        {
            "category":"Shopping",
            "subcategory":"Gifts & Souvenirs",
            "type":"Retail Goods"
        }
    ],
    "sg:phone":"+44 1608 650309",
    "sg:postcode":"GL56 0BB",
    "sg:province":"Gloucestershire",
    "sg:tags":[
        "shop"
    ],
    "wof:name":"THE CORN EXCHANGE",
    "wof:placetype":"venue"
},
  "geometry": {"coordinates":[-1.7031639814,51.9901008606],"type":"Point"}
}