{
  "type": "Feature",
  "properties": {
    "iso:country":"GB",
    "sg:address":"42 Claremont Park",
    "sg:city":"Finchley Central",
    "sg:classifiers":[
        {
            "category":"Museum",
            "subcategory":"Art Museum",
            "type":"Entertainment"
        }
    ],
    "sg:phone":"+44 20 8343 3488",
    "sg:postcode":"N3 1TH",
    "sg:province":"Greater London",
    "sg:tags":[
        "gallery"
    ],
    "wof:name":"Epsilon Fine Art",
    "wof:placetype":"venue"
},
  "geometry": {"coordinates":[-0.2063879967,51.6019134521],"type":"Point"}
}