{
  "type": "Feature",
  "properties": {
    "addr:full":"62 Castle Street Salisbury Wiltshire SP1 3TS",
    "addr:housenumber":"62",
    "addr:postcode":"sp1 3ts",
    "addr:street":"Castle Street",
    "iso:country":"GB",
    "sg:address":"62 Castle Street",
    "sg:city":"Salisbury",
    "sg:classifiers":[
        {
            "category":"Banks & Credit Unions",
            "subcategory":"Bank",
            "type":"Services"
        }
    ],
    "sg:phone":"+44 1722 333473",
    "sg:postcode":"SP1 3TS",
    "sg:province":"Wiltshire",
    "sg:tags":[
        "broker",
        "mortgage"
    ],
    "wof:name":"D R E Whelan & Co.",
    "wof:placetype":"venue"
},
  "geometry": {"coordinates":[-1.79607,51.071651],"type":"Point"}
}