{
  "type": "Feature",
  "properties": {
    "addr:full":"2 Hendham Road London Greater London SW17 7DQ",
    "addr:housenumber":"2",
    "addr:postcode":"sw17 7dq",
    "addr:street":"Hendham Road",
    "iso:country":"GB",
    "sg:address":"2 Hendham Road",
    "sg:city":"London",
    "sg:classifiers":[
        {
            "category":"Communications",
            "subcategory":"Film & Video Production",
            "type":"Services"
        }
    ],
    "sg:postcode":"SW17 7DQ",
    "sg:province":"Greater London",
    "sg:tags":[
        "tv",
        "studio"
    ],
    "wof:name":"Paraadox Pictures",
    "wof:placetype":"venue"
},
  "geometry": {"coordinates":[-0.1679169983,51.4389648438],"type":"Point"}
}