{
  "type": "Feature",
  "properties": {
    "addr:full":"86 Royal Hill, Greenwich Greenwich Greater London SE10 8RT",
    "addr:housenumber":"86",
    "addr:postcode":"se10 8rt",
    "addr:street":"Royal Hill",
    "iso:country":"GB",
    "sg:address":"86 Royal Hill, Greenwich",
    "sg:city":"Greenwich",
    "sg:classifiers":[
        {
            "category":"Food & Beverages",
            "subcategory":"Specialty",
            "type":"Retail Goods"
        }
    ],
    "sg:phone":"+44 20 8488 6764",
    "sg:postcode":"SE10 8RT",
    "sg:province":"Greater London",
    "sg:tags":[
        "product",
        "health"
    ],
    "wof:name":"All Things Nice",
    "wof:placetype":"venue"
},
  "geometry": {"coordinates":[-0.0103280004,51.4759864807],"type":"Point"}
}