{
  "type": "Feature",
  "properties": {
    "addr:full":"26 Plymouth St Swindon Wiltshire SN1 2LA",
    "addr:housenumber":"26",
    "addr:postcode":"sn1 2la",
    "addr:street":"Plymouth St",
    "iso:country":"GB",
    "sg:address":"26 Plymouth St",
    "sg:city":"Swindon",
    "sg:classifiers":[
        {
            "category":"Building & Trades",
            "subcategory":"Construction",
            "type":"Services"
        }
    ],
    "sg:phone":"+44 1793 430311",
    "sg:postcode":"SN1 2LA",
    "sg:province":"Wiltshire",
    "sg:tags":[
        "decorator",
        "painter"
    ],
    "wof:name":"Brush Strokes",
    "wof:placetype":"venue"
},
  "geometry": {"coordinates":[-1.7713220119,51.561466217],"type":"Point"}
}