{
  "type": "Feature",
  "properties": {
    "iso:country":"GB",
    "sg:address":"151 High Street, Southgate",
    "sg:city":"London",
    "sg:classifiers":[
        {
            "category":"Professional",
            "subcategory":"Employment Agencies",
            "type":"Services"
        }
    ],
    "sg:phone":"+44 20 8882 6363",
    "sg:postcode":"N14 6PQ",
    "sg:province":"Greater London",
    "sg:tags":[
        "consultant"
    ],
    "wof:name":"Health Care Corporation of America International Ltd.",
    "wof:placetype":"venue"
},
  "geometry": {"coordinates":[-0.128023,51.63089],"type":"Point"}
}