{
  "type": "Feature",
  "properties": {
    "addr:full":"Storey House, Storey Square Barrow-in-furness Cumbria LA14 2HU",
    "addr:postcode":"la14 2hu",
    "addr:street":"Storey Square",
    "iso:country":"GB",
    "sg:address":"Storey House, Storey Square",
    "sg:city":"Barrow-in-furness",
    "sg:classifiers":[
        {
            "category":"Organizations",
            "subcategory":"Non-profit Organization",
            "type":"Services"
        }
    ],
    "sg:phone":"+44 1229 822822",
    "sg:postcode":"LA14 2HU",
    "sg:province":"Cumbria",
    "sg:tags":[
        "charitable",
        "organisation",
        "voluntary",
        "charity"
    ],
    "wof:name":"CARERS FURNESS CARERS ASSOCIATION",
    "wof:placetype":"venue"
},
  "geometry": {"coordinates":[-3.220784,54.111416],"type":"Point"}
}