{
  "type": "Feature",
  "properties": {
    "addr:full":"64-66 St. Pauls Churchyard St Paul's Greater London EC4M 8AA",
    "addr:housenumber":"64-66",
    "addr:postcode":"ec4m 8aa",
    "addr:street":"St. Pauls Churchyard St",
    "iso:country":"GB",
    "sg:address":"64-66 St. Pauls Churchyard",
    "sg:city":"St Paul's",
    "sg:classifiers":[
        {
            "category":"Shopping",
            "subcategory":"Books",
            "type":"Retail Goods"
        }
    ],
    "sg:phone":"+44 20 7248 4956",
    "sg:postcode":"EC4M 8AA",
    "sg:province":"Greater London",
    "sg:tags":[
        "bookseller"
    ],
    "wof:name":"Books Nippon",
    "wof:placetype":"venue"
},
  "geometry": {"coordinates":[-0.094041,51.536476],"type":"Point"}
}