{
  "type": "Feature",
  "properties": {
    "addr:full":"10 Old Bond Street London Greater London W1S 4PL",
    "addr:housenumber":"10",
    "addr:postcode":"w1s 4pl",
    "addr:street":"Old Bond Street",
    "iso:country":"GB",
    "sg:address":"10 Old Bond Street",
    "sg:city":"London",
    "sg:classifiers":[
        {
            "category":"Shopping",
            "subcategory":"Clothing, Apparel, & Fashions",
            "type":"Retail Goods"
        }
    ],
    "sg:phone":"+44 20 7409 4000",
    "sg:postcode":"W1S 4PL",
    "sg:province":"Greater London",
    "sg:tags":[
        "clothing"
    ],
    "wof:name":"Daks Ltd.",
    "wof:placetype":"venue"
},
  "geometry": {"coordinates":[-0.1403950006,51.5086975098],"type":"Point"}
}