{
  "type": "Feature",
  "properties": {
    "addr:full":"Canongate Jedburgh Scottish Borders TD8 6ER",
    "addr:postcode":"td8 6er",
    "addr:street":"Canongate",
    "iso:country":"GB",
    "sg:address":"Canongate",
    "sg:city":"Jedburgh",
    "sg:classifiers":[
        {
            "category":"Social Services",
            "subcategory":"Child Care",
            "type":"Services"
        },
        {
            "category":"Social Services",
            "subcategory":"Adult Care",
            "type":"Services"
        },
        {
            "category":"Government",
            "subcategory":"Office",
            "type":"Public Place"
        }
    ],
    "sg:phone":"+44 1835 862885",
    "sg:postcode":"TD8 6ER",
    "sg:province":"Scottish Borders",
    "sg:tags":[
        "local",
        "day",
        "centre"
    ],
    "wof:name":"Jedburgh Day Centre",
    "wof:placetype":"venue"
},
  "geometry": {"coordinates":[-2.5535390377,55.4776954651],"type":"Point"}
}