{
  "type": "Feature",
  "properties": {
    "addr:full":"35 Towy Terrace, Ffairfach Llandeilo Carmarthenshire SA19 6ST",
    "addr:housenumber":"35",
    "addr:postcode":"sa19 6st",
    "addr:street":"Towy Terrace Ffairfach;Carmarthenshire",
    "iso:country":"GB",
    "sg:address":"35 Towy Terrace, Ffairfach",
    "sg:city":"Llandeilo",
    "sg:classifiers":[
        {
            "category":"Government",
            "subcategory":"Post Office",
            "type":"Public Place"
        }
    ],
    "sg:phone":"+44 1558 823226",
    "sg:postcode":"SA19 6ST",
    "sg:province":"Carmarthenshire",
    "wof:name":"Ffairfach Post Office",
    "wof:placetype":"venue"
},
  "geometry": {"coordinates":[-3.991857,51.884136],"type":"Point"}
}