{
  "type": "Feature",
  "properties": {
    "iso:country":"GB",
    "sg:address":"Market Parade, Sidcup High Street",
    "sg:city":"Sidcup",
    "sg:classifiers":[
        {
            "category":"Home & Garden",
            "subcategory":"Carpets & Floor Coverings",
            "type":"Retail Goods"
        }
    ],
    "sg:phone":"+44 20 8302 7430",
    "sg:postcode":"DA14 6EP",
    "sg:province":"Kent",
    "sg:tags":[
        "carpets",
        "retailer",
        "rug",
        "matting"
    ],
    "wof:name":"J R Carpets",
    "wof:placetype":"venue"
},
  "geometry": {"coordinates":[0.103945,51.425919],"type":"Point"}
}