{
  "type": "Feature",
  "properties": {
    "iso:country":"GB",
    "sg:address":"Dukes Ho, 32-38 Dukes Pl",
    "sg:city":"Monument",
    "sg:classifiers":[
        {
            "category":"Manufacturing",
            "subcategory":"Tools & Machinery",
            "type":"Manufacturing & Wholesale Goods"
        }
    ],
    "sg:phone":"+44 20 7623 1900",
    "sg:postcode":"EC3A 7LP",
    "sg:province":"Greater London",
    "sg:tags":[
        "society",
        "friendly"
    ],
    "wof:name":"Citadel Insurance Services Ltd",
    "wof:placetype":"venue"
},
  "geometry": {"coordinates":[-0.07769,51.51437],"type":"Point"}
}