{
  "type": "Feature",
  "properties": {
    "iso:country":"GB",
    "sg:address":"47 Yardley Green Road, Bordesley Green",
    "sg:city":"Birmingham",
    "sg:classifiers":[
        {
            "category":"Shopping",
            "subcategory":"Pharmacy",
            "type":"Retail Goods"
        }
    ],
    "sg:phone":"+44 121 772 0025",
    "sg:postcode":"B9 5PU",
    "sg:province":"West Midlands",
    "sg:tags":[
        "pharmacist",
        "dispensing",
        "chemist"
    ],
    "wof:name":"Shelley Chemist",
    "wof:placetype":"venue"
},
  "geometry": {"coordinates":[-1.8405640125,52.4759559631],"type":"Point"}
}