{
  "type": "Feature",
  "properties": {
    "addr:full":"Shire Oak Quarry, Chester Road, Walsall Wood Walsall Staffordshire WS9 9PB",
    "addr:postcode":"ws9 9pb",
    "addr:street":"Shire Oak Quarry Chester Road",
    "iso:country":"GB",
    "sg:address":"Shire Oak Quarry, Chester Road, Walsall Wood",
    "sg:city":"Walsall",
    "sg:classifiers":[
        {
            "category":"Manufacturing",
            "subcategory":"Glass & Minerals",
            "type":"Manufacturing & Wholesale Goods"
        }
    ],
    "sg:phone":"+44 1543 373253",
    "sg:postcode":"WS9 9PB",
    "sg:province":"Staffordshire",
    "sg:tags":[
        "chalk",
        "stone",
        "slate"
    ],
    "wof:name":"Tarmac Ltd.",
    "wof:placetype":"venue"
},
  "geometry": {"coordinates":[-1.9229290485,52.6323661804],"type":"Point"}
}