{
  "type": "Feature",
  "properties": {
    "addr:full":"Berkhamsted Ho, 121 High St Berkhamsted Bedfordshire HP4 2DJ",
    "addr:housenumber":"121",
    "addr:postcode":"hp4 2dj",
    "addr:street":"High St",
    "iso:country":"GB",
    "sg:address":"Berkhamsted Ho, 121 High St",
    "sg:city":"Berkhamsted",
    "sg:classifiers":[
        {
            "category":"Professional",
            "subcategory":"Computer Services",
            "type":"Services"
        }
    ],
    "sg:postcode":"HP4 2DJ",
    "sg:province":"Bedfordshire",
    "sg:tags":[
        "system",
        "software"
    ],
    "wof:name":"Touchstone Europe Ltd",
    "wof:placetype":"venue"
},
  "geometry": {"coordinates":[-0.564559,51.760414],"type":"Point"}
}