{
  "type": "Feature",
  "properties": {
    "addr:full":"36 Hillside Av Keith Moray AB55 4AG",
    "addr:housenumber":"36",
    "addr:postcode":"ab55 4ag",
    "addr:street":"Hillside Av Keith",
    "iso:country":"GB",
    "sg:address":"36 Hillside Av",
    "sg:city":"Keith",
    "sg:classifiers":[
        {
            "category":"Military Area",
            "subcategory":"Air Force Base",
            "type":"Public Place"
        }
    ],
    "sg:phone":"+44 1340 820718",
    "sg:postcode":"AB55 4AG",
    "sg:province":"Moray",
    "sg:tags":[
        "taxi",
        "hire",
        "private"
    ],
    "wof:name":"Benaigen Private Hire",
    "wof:placetype":"venue"
},
  "geometry": {"coordinates":[-3.135218,57.445503],"type":"Point"}
}