{
  "type": "Feature",
  "properties": {
    "iso:country":"GB",
    "sg:address":"Manor Drive North",
    "sg:city":"New Malden",
    "sg:classifiers":[
        {
            "category":"Retail",
            "subcategory":"Auto Repair",
            "type":"Services"
        }
    ],
    "sg:phone":"+44 20 8337 7468",
    "sg:postcode":"KT3 5PN",
    "sg:province":"Surrey",
    "sg:tags":[
        "modification",
        "garage"
    ],
    "wof:name":"Manor Service Station",
    "wof:placetype":"venue"
},
  "geometry": {"coordinates":[-0.2659929991,51.3876266479],"type":"Point"}
}