{
  "type": "Feature",
  "properties": {
    "iso:country":"GB",
    "sg:address":"Brentwood Cathedral, Ingrave Rd",
    "sg:city":"Brentwood",
    "sg:classifiers":[
        {
            "category":"Place Of Worship",
            "type":"Public Place"
        }
    ],
    "sg:phone":"+44 1277 232266",
    "sg:postcode":"CM15 8AT",
    "sg:province":"Essex",
    "wof:name":"Cathedral House",
    "wof:placetype":"venue"
},
  "geometry": {"coordinates":[0.30573,51.620708],"type":"Point"}
}