{
  "type": "Feature",
  "properties": {
    "addr:full":"49a Links Road Poole Dorset BH14 9QS",
    "addr:housenumber":"49a",
    "addr:postcode":"bh14 9qs",
    "addr:street":"Links Road",
    "iso:country":"GB",
    "sg:address":"49a Links Road",
    "sg:city":"Poole",
    "sg:classifiers":[
        {
            "category":"Wholesale",
            "subcategory":"Sporting Goods",
            "type":"Manufacturing & Wholesale Goods"
        },
        {
            "category":"Sports & Exercise",
            "subcategory":"Golf",
            "type":"Entertainment"
        }
    ],
    "sg:phone":"+44 1202 707138",
    "sg:postcode":"BH14 9QS",
    "sg:province":"Dorset",
    "sg:tags":[
        "club",
        "mnfr",
        "course",
        "equipment"
    ],
    "wof:name":"PARKSTONE GOLF CLUB",
    "wof:placetype":"venue"
},
  "geometry": {"coordinates":[-1.934503,50.715942],"type":"Point"}
}