{
  "type": "Feature",
  "properties": {
    "addr:full":"63 Outram Street Sutton-in-ashfield Nottinghamshire NG17 4BG",
    "addr:housenumber":"63",
    "addr:postcode":"ng17 4bg",
    "addr:street":"Outram Street",
    "iso:country":"GB",
    "sg:address":"63 Outram Street",
    "sg:city":"Sutton-in-ashfield",
    "sg:classifiers":[
        {
            "category":"Organizations",
            "subcategory":"Non-profit Organization",
            "type":"Services"
        }
    ],
    "sg:phone":"+44 1623 464006",
    "sg:postcode":"NG17 4BG",
    "sg:province":"Nottinghamshire",
    "sg:tags":[
        "organisation",
        "voluntary",
        "charity"
    ],
    "wof:name":"Ashfield Homeless Support Group",
    "wof:placetype":"venue"
},
  "geometry": {"coordinates":[-1.257344,53.127964],"type":"Point"}
}