{
  "type": "Feature",
  "properties": {
    "addr:full":"9 Upper Mills, Slaithwaite Huddersfield West Yorkshire HD7 5HA",
    "addr:housenumber":"9",
    "addr:postcode":"hd7 5ha",
    "addr:street":"Upper Mills",
    "iso:country":"GB",
    "sg:address":"9 Upper Mills, Slaithwaite",
    "sg:city":"Huddersfield",
    "sg:classifiers":[
        {
            "category":"Autos & Motor Vehicles",
            "subcategory":"Auto Supplies",
            "type":"Retail Goods"
        }
    ],
    "sg:phone":"+44 1484 841666",
    "sg:postcode":"HD7 5HA",
    "sg:province":"West Yorkshire",
    "sg:tags":[
        "car",
        "part",
        "accessory"
    ],
    "wof:name":"Light Year",
    "wof:placetype":"venue"
},
  "geometry": {"coordinates":[-1.870396018,53.6224212646],"type":"Point"}
}