{
  "type": "Feature",
  "properties": {
    "addr:full":"Po Box 1 Wavertree Liverpool Merseyside L15 0HZ",
    "addr:housenumber":"po;1",
    "addr:postcode":"l15 0hz",
    "addr:street":"Box",
    "iso:country":"GB",
    "sg:address":"Po Box 1 Wavertree",
    "sg:city":"Liverpool",
    "sg:classifiers":[
        {
            "category":"Manufacturing",
            "subcategory":"Textiles",
            "type":"Manufacturing & Wholesale Goods"
        }
    ],
    "sg:phone":"+44 151 733 4080",
    "sg:postcode":"L15 0HZ",
    "sg:province":"Merseyside",
    "sg:tags":[
        "merchant",
        "agent"
    ],
    "wof:name":"Rexmore Ltd.",
    "wof:placetype":"venue"
},
  "geometry": {"coordinates":[-2.9784810543,53.4097747803],"type":"Point"}
}