{
  "type": "Feature",
  "properties": {
    "addr:full":"Cefn-uchaf-nantyr, Glyn Ceiriog Llangollen Denbighshire LL20 7DF",
    "addr:postcode":"ll20 7df",
    "iso:country":"GB",
    "sg:address":"Cefn-uchaf-nantyr, Glyn Ceiriog",
    "sg:city":"Llangollen",
    "sg:classifiers":[
        {
            "category":"Farming",
            "subcategory":"Farm",
            "type":"Manufacturing & Wholesale Goods"
        }
    ],
    "sg:phone":"+44 1691 718268",
    "sg:postcode":"LL20 7DF",
    "sg:province":"Denbighshire",
    "sg:tags":[
        "mixed",
        "crop"
    ],
    "wof:name":"R J & G E Newbrook & Son",
    "wof:placetype":"venue"
},
  "geometry": {"coordinates":[-3.189499,52.93087],"type":"Point"}
}