{
  "type": "Feature",
  "properties": {
    "addr:full":"18 Grange Lane, New Rossington Doncaster South Yorkshire DN11 0LN",
    "addr:housenumber":"18",
    "addr:postcode":"dn11 0ln",
    "addr:street":"Grange Lane",
    "iso:country":"GB",
    "sg:address":"18 Grange Lane, New Rossington",
    "sg:city":"Doncaster",
    "sg:classifiers":[
        {
            "category":"Building & Trades",
            "subcategory":"Construction",
            "type":"Services"
        }
    ],
    "sg:phone":"+44 1302 864694",
    "sg:postcode":"DN11 0LN",
    "sg:province":"South Yorkshire",
    "sg:tags":[
        "roofing"
    ],
    "wof:name":"Andrew Jackson",
    "wof:placetype":"venue"
},
  "geometry": {"coordinates":[-1.079664,53.473568],"type":"Point"}
}