{
  "type": "Feature",
  "properties": {
    "addr:full":"15 Muskham Peterborough Cambridgeshire PE3 9XU",
    "addr:housenumber":"15",
    "addr:postcode":"pe3 9xu",
    "addr:street":"Muskham Peterborough",
    "iso:country":"GB",
    "sg:address":"15 Muskham",
    "sg:city":"Peterborough",
    "sg:classifiers":[
        {
            "category":"Building & Trades",
            "subcategory":"Plumbing",
            "type":"Services"
        }
    ],
    "sg:postcode":"PE3 9XU",
    "sg:province":"Cambridgeshire",
    "sg:tags":[
        "heating"
    ],
    "wof:name":"Marigold Plumbing & Heating",
    "wof:placetype":"venue"
},
  "geometry": {"coordinates":[-0.289208,52.583656],"type":"Point"}
}