{
  "type": "Feature",
  "properties": {
    "iso:country":"GB",
    "sg:address":"7-9 Fore Street",
    "sg:city":"Dulverton",
    "sg:classifiers":[
        {
            "category":"Landmark",
            "subcategory":"Tourist Information",
            "type":"Public Place"
        }
    ],
    "sg:phone":"+44 1398 323841",
    "sg:postcode":"TA22 9EX",
    "sg:province":"Devon",
    "wof:name":"Dulverton Visitor's Centre",
    "wof:placetype":"venue"
},
  "geometry": {"coordinates":[-3.5510809422,51.0399856567],"type":"Point"}
}