{
  "type": "Feature",
  "properties": {
    "addr:full":"Well House Mills, Main Street Bradford West Yorkshire BD15 0JW",
    "addr:postcode":"bd15 0jw",
    "addr:street":"Mills Main Street",
    "iso:country":"GB",
    "sg:address":"Well House Mills, Main Street",
    "sg:city":"Bradford",
    "sg:classifiers":[
        {
            "category":"Wholesale",
            "subcategory":"Furniture",
            "type":"Manufacturing & Wholesale Goods"
        }
    ],
    "sg:phone":"+44 1535 271426",
    "sg:postcode":"BD15 0JW",
    "sg:province":"West Yorkshire",
    "sg:tags":[
        "shop",
        "fitting"
    ],
    "wof:name":"Birch Engineering Design",
    "wof:placetype":"venue"
},
  "geometry": {"coordinates":[-1.7583060265,53.7957382202],"type":"Point"}
}