{
  "type": "Feature",
  "properties": {
    "iso:country":"GB",
    "sg:address":"Unit 5a Lyon Road, Hersham Industrial Estate",
    "sg:city":"Walton-on-thames",
    "sg:classifiers":[
        {
            "category":"Retail",
            "subcategory":"Auto Repair",
            "type":"Services"
        }
    ],
    "sg:phone":"+44 1932 253825",
    "sg:postcode":"KT12 3PU",
    "sg:province":"Surrey",
    "sg:tags":[
        "body",
        "car",
        "commercial",
        "vehicle"
    ],
    "wof:name":"Claremont Coachworks",
    "wof:placetype":"venue"
},
  "geometry": {"coordinates":[-0.386587,51.378899],"type":"Point"}
}