{
  "type": "Feature",
  "properties": {
    "iso:country":"GB",
    "sg:address":"6 Franklin Close",
    "sg:city":"Worcester",
    "sg:classifiers":[
        {
            "category":"Banks & Credit Unions",
            "subcategory":"Financial Services",
            "type":"Services"
        }
    ],
    "sg:phone":"+44 1905 748498",
    "sg:postcode":"WR2 4DX",
    "sg:province":"Worcestershire",
    "sg:tags":[
        "adviser"
    ],
    "wof:name":"Personal Financial Management",
    "wof:placetype":"venue"
},
  "geometry": {"coordinates":[-2.238747,52.174751],"type":"Point"}
}