{
  "type": "Feature",
  "properties": {
    "iso:country":"GB",
    "sg:address":"41 Tudor Rd, St. Pauls",
    "sg:city":"Bristol",
    "sg:classifiers":[
        {
            "category":"Social Services",
            "subcategory":"Job Training",
            "type":"Services"
        }
    ],
    "sg:phone":"+44 117 909 6506",
    "sg:postcode":"BS2 9LW",
    "sg:province":"City of Bristol",
    "sg:tags":[
        "translator",
        "interpreter"
    ],
    "wof:name":"Swedish Translations",
    "wof:placetype":"venue"
},
  "geometry": {"coordinates":[-2.577786,51.465385],"type":"Point"}
}