{
  "type": "Feature",
  "properties": {
    "iso:country":"GB",
    "sg:address":"4 Holmes Holdings",
    "sg:city":"Broxburn",
    "sg:classifiers":[
        {
            "category":"Retail",
            "subcategory":"Storage",
            "type":"Services"
        }
    ],
    "sg:phone":"+44 1506 855732",
    "sg:postcode":"EH52 5NY",
    "sg:province":"City of Edinburgh",
    "sg:tags":[
        "household",
        "removal"
    ],
    "wof:name":"Sutton Bros Livingston",
    "wof:placetype":"venue"
},
  "geometry": {"coordinates":[-3.477939,55.933102],"type":"Point"}
}