{
  "type": "Feature",
  "properties": {
    "iso:country":"GB",
    "sg:address":"Berkeley, Pimperne",
    "sg:city":"Blandford Forum",
    "sg:classifiers":[
        {
            "category":"Autos & Motor Vehicles",
            "subcategory":"Automobile Sales",
            "type":"Retail Goods"
        }
    ],
    "sg:phone":"+44 1258 455477",
    "sg:postcode":"DT11 8TX",
    "sg:province":"Dorset",
    "sg:tags":[
        "commercial"
    ],
    "wof:name":"K L Commercials",
    "wof:placetype":"venue"
},
  "geometry": {"coordinates":[-2.1194889545,50.8693885803],"type":"Point"}
}