{
  "type": "Feature",
  "properties": {
    "addr:full":"147 Skipton Rd Keighley West Yorkshire BD21 3BG",
    "addr:housenumber":"147",
    "addr:postcode":"bd21 3bg",
    "addr:street":"Skipton Rd",
    "iso:country":"GB",
    "sg:address":"147 Skipton Rd",
    "sg:city":"Keighley",
    "sg:classifiers":[
        {
            "category":"Social Services",
            "subcategory":"Child Care",
            "type":"Services"
        },
        {
            "category":"Social Services",
            "subcategory":"Adult Care",
            "type":"Services"
        }
    ],
    "sg:phone":"+44 1535 607139",
    "sg:postcode":"BD21 3BG",
    "sg:province":"West Yorkshire",
    "sg:tags":[
        "day",
        "centre"
    ],
    "wof:name":"Skipton Road Community Mental Health Services",
    "wof:placetype":"venue"
},
  "geometry": {"coordinates":[-1.9096039534,53.8716964722],"type":"Point"}
}