{
  "type": "Feature",
  "properties": {
    "addr:full":"144 High St Smethwick West Midlands B66 3AP",
    "addr:housenumber":"144",
    "addr:postcode":"b66 3ap",
    "addr:street":"High St",
    "iso:country":"GB",
    "sg:address":"144 High St",
    "sg:city":"Smethwick",
    "sg:classifiers":[
        {
            "category":"Bars & Pubs",
            "type":"Food & Drink"
        }
    ],
    "sg:phone":"+44 121 558 3385",
    "sg:postcode":"B66 3AP",
    "sg:province":"West Midlands",
    "sg:tags":[
        "pubs",
        "inn"
    ],
    "wof:name":"Old Talbot",
    "wof:placetype":"venue"
},
  "geometry": {"coordinates":[-1.970929,52.495575],"type":"Point"}
}