{
  "type": "Feature",
  "properties": {
    "iso:country":"GB",
    "sg:address":"Unit 2, Gelders Hall Rd, Shepshed",
    "sg:city":"Loughborough",
    "sg:classifiers":[
        {
            "category":"Shopping",
            "subcategory":"Clothing, Apparel, & Fashions",
            "type":"Retail Goods"
        },
        {
            "category":"Shopping",
            "subcategory":"Jewelry",
            "type":"Retail Goods"
        }
    ],
    "sg:phone":"+44 1509 501000",
    "sg:postcode":"LE12 9NH",
    "sg:province":"Leicestershire",
    "sg:tags":[
        "accessory",
        "gold",
        "silversmith"
    ],
    "wof:name":"Inca Hair Accessories",
    "wof:placetype":"venue"
},
  "geometry": {"coordinates":[-1.298299,52.761318],"type":"Point"}
}