{
  "type": "Feature",
  "properties": {
    "iso:country":"GB",
    "sg:address":"109 Foxhole Road",
    "sg:city":"Paignton",
    "sg:classifiers":[
        {
            "category":"Food & Beverages",
            "subcategory":"Candy",
            "type":"Retail Goods"
        }
    ],
    "sg:postcode":"TQ3 3SU",
    "sg:province":"Devon",
    "sg:tags":[
        "confectioner"
    ],
    "wof:name":"Foxhole Sweetshop",
    "wof:placetype":"venue"
},
  "geometry": {"coordinates":[-3.584611,50.439861],"type":"Point"}
}