{
  "type": "Feature",
  "properties": {
    "addr:full":"Suite 1c Tannery Court, Stratton Way Abingdon Oxfordshire OX14 5TS",
    "addr:housenumber":"suite 1c",
    "addr:postcode":"ox14 5ts",
    "addr:street":"Tannery Court Stratton Way",
    "iso:country":"GB",
    "sg:address":"Suite 1c Tannery Court, Stratton Way",
    "sg:city":"Abingdon",
    "sg:classifiers":[
        {
            "category":"Insurance",
            "subcategory":"Insurance Agent",
            "type":"Services"
        }
    ],
    "sg:postcode":"OX14 5TS",
    "sg:province":"Oxfordshire",
    "sg:tags":[
        "broker"
    ],
    "wof:name":"Jequier Newitt Insurance Brokers",
    "wof:placetype":"venue"
},
  "geometry": {"coordinates":[-1.2824139595,51.6726722717],"type":"Point"}
}