{
  "type": "Feature",
  "properties": {
    "addr:full":"The Orchard, 8 Sherburn Street Selby East Riding of Yorkshire YO8 3SS",
    "addr:housenumber":"8",
    "addr:postcode":"yo8 3ss",
    "addr:street":"Sherburn Street",
    "iso:country":"GB",
    "sg:address":"The Orchard, 8 Sherburn Street",
    "sg:city":"Selby",
    "sg:classifiers":[
        {
            "category":"Shopping",
            "subcategory":"Antiques",
            "type":"Retail Goods"
        }
    ],
    "sg:postcode":"YO8 3SS",
    "sg:province":"East Riding of Yorkshire",
    "wof:name":"Cawood Antiques",
    "wof:placetype":"venue"
},
  "geometry": {"coordinates":[-1.0703459978,53.783908844],"type":"Point"}
}