{
  "type": "Feature",
  "properties": {
    "addr:full":"10 Brentford Business Centre, Commerce Road Brentford Greater London TW8 8LG",
    "addr:housenumber":"10",
    "addr:postcode":"tw8 8lg",
    "addr:street":"Brentford Business Centre Commerce Road",
    "iso:country":"GB",
    "sg:address":"10 Brentford Business Centre, Commerce Road",
    "sg:city":"Brentford",
    "sg:classifiers":[
        {
            "category":"Shopping",
            "subcategory":"Luggage & Leather Goods",
            "type":"Retail Goods"
        }
    ],
    "sg:phone":"+44 20 8560 7050",
    "sg:postcode":"TW8 8LG",
    "sg:province":"Greater London",
    "sg:tags":[
        "mnfr",
        "cane",
        "basketware"
    ],
    "wof:name":"Voodoo Blue Ltd.",
    "wof:placetype":"venue"
},
  "geometry": {"coordinates":[-0.3148359954,51.4841499329],"type":"Point"}
}