{
  "type": "Feature",
  "properties": {
    "addr:full":"Nivingston Cntry Htl & Rst'rant, Cleish Kinross Clackmannanshire KY13 0LS",
    "addr:postcode":"ky13 0ls",
    "iso:country":"GB",
    "sg:address":"Nivingston Cntry Htl & Rst'rant, Cleish",
    "sg:city":"Kinross",
    "sg:classifiers":[
        {
            "category":"Travel",
            "subcategory":"Hotels & Motels",
            "type":"Entertainment"
        }
    ],
    "sg:postcode":"KY13 0LS",
    "sg:province":"Clackmannanshire",
    "wof:name":"Nivingston House Hotel",
    "wof:placetype":"venue"
},
  "geometry": {"coordinates":[-3.4433400631,56.1638717651],"type":"Point"}
}