{
  "type": "Feature",
  "properties": {
    "addr:full":"24 Sandy Lane, Prestwich Manchester Greater Manchester M25 9RY",
    "addr:housenumber":"24",
    "addr:postcode":"m25 9ry",
    "addr:street":"Sandy Lane",
    "iso:country":"GB",
    "sg:address":"24 Sandy Lane, Prestwich",
    "sg:city":"Manchester",
    "sg:classifiers":[
        {
            "category":"Shopping",
            "subcategory":"News",
            "type":"Retail Goods"
        }
    ],
    "sg:phone":"+44 161 773 2021",
    "sg:postcode":"M25 9RY",
    "sg:province":"Greater Manchester",
    "sg:tags":[
        "newsagent"
    ],
    "wof:name":"Prestwich News",
    "wof:placetype":"venue"
},
  "geometry": {"coordinates":[-2.285128,53.521427],"type":"Point"}
}