{
  "type": "Feature",
  "properties": {
    "addr:full":"Shern House, 16 Melbourne Road Bushey Hertfordshire WD23 3LN",
    "addr:housenumber":"16",
    "addr:postcode":"wd23 3ln",
    "addr:street":"Melbourne Road",
    "iso:country":"GB",
    "sg:address":"Shern House, 16 Melbourne Road",
    "sg:city":"Bushey",
    "sg:classifiers":[
        {
            "category":"Banks & Credit Unions",
            "subcategory":"Investment Brokerage",
            "type":"Services"
        },
        {
            "category":"Retail",
            "subcategory":"Auto Rental",
            "type":"Services"
        }
    ],
    "sg:postcode":"WD23 3LN",
    "sg:province":"Hertfordshire",
    "sg:tags":[
        "moneylender",
        "hire",
        "truck",
        "car"
    ],
    "wof:name":"Colindale Finance Corporation Ltd.",
    "wof:placetype":"venue"
},
  "geometry": {"coordinates":[-0.360053,51.642944],"type":"Point"}
}