{
  "type": "Feature",
  "properties": {
    "addr:full":"48 South Pde, Mollison Way Edgware Greater London HA8 5QL",
    "addr:housenumber":"48",
    "addr:postcode":"ha8 5ql",
    "addr:street":"South Pde Mollison Way",
    "iso:country":"GB",
    "sg:address":"48 South Pde, Mollison Way",
    "sg:city":"Edgware",
    "sg:classifiers":[
        {
            "category":"Cafe",
            "type":"Food & Drink"
        }
    ],
    "sg:phone":"+44 20 8952 1587",
    "sg:postcode":"HA8 5QL",
    "sg:province":"Greater London",
    "sg:tags":[
        "tea",
        "room"
    ],
    "wof:name":"Corner Cafe The",
    "wof:placetype":"venue"
},
  "geometry": {"coordinates":[-0.277564,51.612083],"type":"Point"}
}