{
  "type": "Feature",
  "properties": {
    "iso:country":"GB",
    "sg:address":"374 Gallowgate",
    "sg:city":"Glasgow",
    "sg:classifiers":[
        {
            "category":"Bars & Pubs",
            "type":"Food & Drink"
        },
        {
            "category":"Community Center",
            "subcategory":"Social",
            "type":"Public Place"
        }
    ],
    "sg:phone":"+44 141 552 0753",
    "sg:postcode":"G4 0TX",
    "sg:province":"Glasgow City",
    "sg:tags":[
        "pubs",
        "house",
        "inn",
        "activity"
    ],
    "wof:name":"Hielan Jessie",
    "wof:placetype":"venue"
},
  "geometry": {"coordinates":[-4.2331647873,55.8555603027],"type":"Point"}
}