{
  "type": "Feature",
  "properties": {
    "iso:country":"GB",
    "sg:address":"83 Moorside Rd",
    "sg:city":"Huddersfield",
    "sg:classifiers":[
        {
            "category":"Arts & Performance",
            "subcategory":"Music",
            "type":"Entertainment"
        }
    ],
    "sg:phone":"+44 1484 303466",
    "sg:postcode":"HD5 0LR",
    "sg:province":"West Yorkshire",
    "sg:tags":[
        "mobile",
        "disco"
    ],
    "wof:name":"D J Daz",
    "wof:placetype":"venue"
},
  "geometry": {"coordinates":[-1.727514,53.663692],"type":"Point"}
}