{
  "type": "Feature",
  "properties": {
    "iso:country":"GB",
    "sg:address":"35 Common Lane, Culcheth",
    "sg:city":"Warrington",
    "sg:classifiers":[
        {
            "category":"Bars & Pubs",
            "type":"Food & Drink"
        }
    ],
    "sg:phone":"+44 1925 762624",
    "sg:postcode":"WA3 4EX",
    "sg:province":"Cheshire",
    "sg:tags":[
        "pubs",
        "inn"
    ],
    "wof:name":"Punch Retail (Holdings) Ltd.",
    "wof:placetype":"venue"
},
  "geometry": {"coordinates":[-2.522103,53.453274],"type":"Point"}
}