{
  "type": "Feature",
  "properties": {
    "addr:full":"23 Dugdale Street Nuneaton Leicestershire CV11 5QJ",
    "addr:housenumber":"23",
    "addr:postcode":"cv11 5qj",
    "addr:street":"Dugdale Street",
    "iso:country":"GB",
    "sg:address":"23 Dugdale Street",
    "sg:city":"Nuneaton",
    "sg:classifiers":[
        {
            "category":"Organizations",
            "subcategory":"Community Association",
            "type":"Services"
        },
        {
            "category":"Organizations",
            "subcategory":"Membership Organization",
            "type":"Services"
        }
    ],
    "sg:phone":"+44 24 7638 2041",
    "sg:postcode":"CV11 5QJ",
    "sg:province":"Leicestershire",
    "sg:tags":[
        "club",
        "social"
    ],
    "wof:name":"Nuneaton Co-Operative Sports & Social Club",
    "wof:placetype":"venue"
},
  "geometry": {"coordinates":[-1.470269,52.521511],"type":"Point"}
}