{
  "type": "Feature",
  "properties": {
    "addr:full":"243-247 Cricklewood Bdwy London Greater London NW2 6NX",
    "addr:housenumber":"243-247",
    "addr:postcode":"nw2 6nx",
    "addr:street":"Cricklewood Bdwy",
    "iso:country":"GB",
    "sg:address":"243-247 Cricklewood Bdwy",
    "sg:city":"London",
    "sg:classifiers":[
        {
            "category":"Health Services",
            "subcategory":"Doctor",
            "type":"Services"
        }
    ],
    "sg:phone":"+44 20 8452 1232",
    "sg:postcode":"NW2 6NX",
    "sg:province":"Greater London",
    "sg:tags":[
        "practitioners"
    ],
    "wof:name":"Medsupport Ltd.",
    "wof:placetype":"venue"
},
  "geometry": {"coordinates":[-0.2178049982,51.5585403442],"type":"Point"}
}