{
  "type": "Feature",
  "properties": {
    "addr:full":"Unit 3, Stanford House Tilbury Essex RM18 8YP",
    "addr:housenumber":"unit 3",
    "addr:postcode":"rm18 8yp",
    "addr:street":"Stanford;Tilbury",
    "iso:country":"GB",
    "sg:address":"Unit 3, Stanford House",
    "sg:city":"Tilbury",
    "sg:classifiers":[
        {
            "category":"Food & Beverages",
            "subcategory":"Fruits & Vegetables",
            "type":"Retail Goods"
        }
    ],
    "sg:phone":"+44 1375 858555",
    "sg:postcode":"RM18 8YP",
    "sg:province":"Essex",
    "sg:tags":[
        "greengrocer"
    ],
    "wof:name":"Kenny & Sons",
    "wof:placetype":"venue"
},
  "geometry": {"coordinates":[0.3851700127,51.472038269],"type":"Point"}
}