{
  "type": "Feature",
  "properties": {
    "addr:full":"118 Woodville Road Cardiff Cardiff CF24 4EE",
    "addr:housenumber":"118",
    "addr:postcode":"cf24 4ee",
    "addr:street":"Woodville Road",
    "iso:country":"GB",
    "sg:address":"118 Woodville Road",
    "sg:city":"Cardiff",
    "sg:classifiers":[
        {
            "category":"Professional",
            "subcategory":"Printing & Photocopies",
            "type":"Services"
        }
    ],
    "sg:postcode":"CF24 4EE",
    "sg:province":"Cardiff",
    "sg:tags":[
        "printer"
    ],
    "wof:name":"Walter Rogers (Printers) Ltd.",
    "wof:placetype":"venue"
},
  "geometry": {"coordinates":[-3.177066,51.49353],"type":"Point"}
}