{
  "type": "Feature",
  "properties": {
    "iso:country":"GB",
    "sg:address":"7 Moor Park Avenue",
    "sg:city":"Preston",
    "sg:classifiers":[
        {
            "category":"Health Services",
            "subcategory":"Doctor",
            "type":"Services"
        }
    ],
    "sg:phone":"+44 1772 204710",
    "sg:postcode":"PR1 6AS",
    "sg:province":"Lancashire",
    "sg:tags":[
        "practitioners"
    ],
    "wof:name":"James Christopher Faux",
    "wof:placetype":"venue"
},
  "geometry": {"coordinates":[-2.704472,53.771435],"type":"Point"}
}