{
  "type": "Feature",
  "properties": {
    "iso:country":"GB",
    "sg:address":"Head Office, 8 Norwich Rd",
    "sg:city":"Greenford",
    "sg:classifiers":[
        {
            "category":"Shopping",
            "subcategory":"Clothing, Apparel, & Fashions",
            "type":"Retail Goods"
        }
    ],
    "sg:phone":"+44 181 575 6827",
    "sg:postcode":"UB6 8UB",
    "sg:province":"Greater London",
    "sg:tags":[
        "shop"
    ],
    "wof:name":"Altered Image",
    "wof:placetype":"venue"
},
  "geometry": {"coordinates":[-0.3399,51.549271],"type":"Point"}
}