{
  "type": "Feature",
  "properties": {
    "addr:full":"51 Falcon Rd Battersea Greater London SW11 2PH",
    "addr:housenumber":"51",
    "addr:postcode":"sw11 2ph",
    "addr:street":"Falcon Rd",
    "iso:country":"GB",
    "sg:address":"51 Falcon Rd",
    "sg:city":"Battersea",
    "sg:classifiers":[
        {
            "category":"Health Services",
            "subcategory":"Dentist",
            "type":"Services"
        }
    ],
    "sg:phone":"+44 20 7228 3435",
    "sg:postcode":"SW11 2PH",
    "sg:province":"Greater London",
    "wof:name":"Bramlands Dental Surgery",
    "wof:placetype":"venue"
},
  "geometry": {"coordinates":[-0.170642,51.46854],"type":"Point"}
}