{
  "type": "Feature",
  "properties": {
    "addr:full":"13-15 High Street, Keynsham Bristol City of Bristol BS31 1DP",
    "addr:housenumber":"13-15",
    "addr:postcode":"bs31 1dp",
    "addr:street":"High Street",
    "iso:country":"GB",
    "sg:address":"13-15 High Street, Keynsham",
    "sg:city":"Bristol",
    "sg:classifiers":[
        {
            "category":"Banks & Credit Unions",
            "subcategory":"Bank",
            "type":"Services"
        }
    ],
    "sg:phone":"+44 117 986 5219",
    "sg:postcode":"BS31 1DP",
    "sg:province":"City of Bristol",
    "wof:name":"Lloyds Tsb Bank Plc",
    "wof:placetype":"venue"
},
  "geometry": {"coordinates":[-2.498821,51.416862],"type":"Point"}
}