{
  "type": "Feature",
  "properties": {
    "addr:full":"22-22a Hawthorn Road Eastbourne East Sussex BN23 6QA",
    "addr:housenumber":"22-22a",
    "addr:postcode":"bn23 6qa",
    "addr:street":"Hawthorn Road",
    "iso:country":"GB",
    "sg:address":"22-22a Hawthorn Road",
    "sg:city":"Eastbourne",
    "sg:classifiers":[
        {
            "category":"Wholesale",
            "subcategory":"Construction Materials",
            "type":"Manufacturing & Wholesale Goods"
        }
    ],
    "sg:phone":"+44 1323 646925",
    "sg:postcode":"BN23 6QA",
    "sg:province":"East Sussex",
    "sg:tags":[
        "lift"
    ],
    "wof:name":"Euroweb (S W) Ltd.",
    "wof:placetype":"venue"
},
  "geometry": {"coordinates":[0.299838,50.790264],"type":"Point"}
}