{
  "type": "Feature",
  "properties": {
    "addr:full":"Sunnyside Place Frome Somerset BA11 1LH",
    "addr:postcode":"ba11 1lh",
    "addr:street":"Sunnyside Place",
    "iso:country":"GB",
    "sg:address":"Sunnyside Place",
    "sg:city":"Frome",
    "sg:classifiers":[
        {
            "category":"Social Services",
            "subcategory":"Adult Care",
            "type":"Services"
        },
        {
            "category":"Social Services",
            "subcategory":"Retirement Home",
            "type":"Services"
        }
    ],
    "sg:phone":"+44 1373 463742",
    "sg:postcode":"BA11 1LH",
    "sg:province":"Somerset",
    "sg:tags":[
        "housing",
        "sheltered",
        "accommodation"
    ],
    "wof:name":"Sunnyside Place Sheltered Housing",
    "wof:placetype":"venue"
},
  "geometry": {"coordinates":[-2.3204689026,51.2233695984],"type":"Point"}
}