{
  "type": "Feature",
  "properties": {
    "iso:country":"GB",
    "sg:address":"12 Clarendon Pl",
    "sg:city":"Leamington Spa",
    "sg:classifiers":[
        {
            "category":"Farming",
            "subcategory":"Dairy Farm",
            "type":"Manufacturing & Wholesale Goods"
        }
    ],
    "sg:phone":"+44 1926 312637",
    "sg:postcode":"CV32 5QW",
    "sg:province":"Warwickshire",
    "wof:name":"Clarendon Food & Dairy Equipment Ltd",
    "wof:placetype":"venue"
},
  "geometry": {"coordinates":[-1.540089,52.292027],"type":"Point"}
}