{
  "type": "Feature",
  "properties": {
    "iso:country":"GB",
    "sg:address":"Halton Moor Avenue",
    "sg:city":"Leeds",
    "sg:classifiers":[
        {
            "category":"Education",
            "subcategory":"School",
            "type":"Public Place"
        },
        {
            "category":"Organizations",
            "subcategory":"Membership Organization",
            "type":"Services"
        }
    ],
    "sg:phone":"+44 113 248 3127",
    "sg:postcode":"LS9 0HB",
    "sg:province":"West Yorkshire",
    "sg:tags":[
        "club",
        "local",
        "authority",
        "social"
    ],
    "wof:name":"Corpus Christie Catholics Men Club",
    "wof:placetype":"venue"
},
  "geometry": {"coordinates":[-1.483099,53.798943],"type":"Point"}
}