{
  "type": "Feature",
  "properties": {
    "addr:full":"16 Victoria Road, Keelby Grimsby Lincolnshire DN41 8EH",
    "addr:housenumber":"16",
    "addr:postcode":"dn41 8eh",
    "addr:street":"Victoria Road",
    "iso:country":"GB",
    "sg:address":"16 Victoria Road, Keelby",
    "sg:city":"Grimsby",
    "sg:classifiers":[
        {
            "category":"Food & Beverages",
            "subcategory":"Meat & Fish",
            "type":"Retail Goods"
        }
    ],
    "sg:phone":"+44 1469 561147",
    "sg:postcode":"DN41 8EH",
    "sg:province":"Lincolnshire",
    "sg:tags":[
        "chip"
    ],
    "wof:name":"The Chip Inn",
    "wof:placetype":"venue"
},
  "geometry": {"coordinates":[-0.2443079948,53.5729026794],"type":"Point"}
}