{
  "type": "Feature",
  "properties": {
    "iso:country":"GB",
    "sg:address":"183 Elliott Street, Tyldesley",
    "sg:city":"Manchester",
    "sg:classifiers":[
        {
            "category":"Shopping",
            "subcategory":"Pets & Pet Supplies",
            "type":"Retail Goods"
        },
        {
            "category":"Food & Beverages",
            "subcategory":"Fruits & Vegetables",
            "type":"Retail Goods"
        }
    ],
    "sg:phone":"+44 1942 882756",
    "sg:postcode":"M29 8DR",
    "sg:province":"Greater Manchester",
    "sg:tags":[
        "shop",
        "greengrocer"
    ],
    "wof:name":"H G Hudson",
    "wof:placetype":"venue"
},
  "geometry": {"coordinates":[-2.466771,53.514153],"type":"Point"}
}