{
  "type": "Feature",
  "properties": {
    "iso:country":"GB",
    "sg:address":"62 High Street",
    "sg:city":"Caterham",
    "sg:classifiers":[
        {
            "category":"Shopping",
            "subcategory":"Comic Books",
            "type":"Retail Goods"
        }
    ],
    "sg:postcode":"CR3 5UB",
    "sg:province":"Surrey",
    "sg:tags":[
        "jeweller"
    ],
    "wof:name":"The Village Jewellers",
    "wof:placetype":"venue"
},
  "geometry": {"coordinates":[-0.088354,51.285294],"type":"Point"}
}