{
  "type": "Feature",
  "properties": {
    "addr:full":"Neptune House, Holmwood Villas Woolwich Rd Charlton Greater London SE7 7RH",
    "addr:postcode":"se7 7rh",
    "addr:street":"Woolwich Rd",
    "iso:country":"GB",
    "sg:address":"Neptune House, Holmwood Villas Woolwich Rd",
    "sg:city":"Charlton",
    "sg:classifiers":[
        {
            "category":"Professional",
            "subcategory":"Printing & Photocopies",
            "type":"Services"
        }
    ],
    "sg:phone":"+44 20 8293 5310",
    "sg:postcode":"SE7 7RH",
    "sg:province":"Greater London",
    "sg:tags":[
        "print",
        "finisher"
    ],
    "wof:name":"Busy Fingers",
    "wof:placetype":"venue"
},
  "geometry": {"coordinates":[0.0216499995,51.4867248535],"type":"Point"}
}