{
  "type": "Feature",
  "properties": {
    "iso:country":"GB",
    "sg:address":"Mill Green Rd, Pinchbeck",
    "sg:city":"Spalding",
    "sg:classifiers":[
        {
            "category":"Building & Trades",
            "subcategory":"Construction",
            "type":"Services"
        }
    ],
    "sg:phone":"+44 1775 722255",
    "sg:postcode":"PE11 3PU",
    "sg:province":"Lincolnshire",
    "sg:tags":[
        "builder"
    ],
    "wof:name":"Parker,David,Homes Ltd",
    "wof:placetype":"venue"
},
  "geometry": {"coordinates":[-0.161251,52.816528],"type":"Point"}
}