{
  "type": "Feature",
  "properties": {
    "addr:full":"4 Highbrook Suite, Delta House, Bridge Road Haywards Heath East Sussex RH16 1UA",
    "addr:housenumber":"4;suite",
    "addr:postcode":"rh16 1ua",
    "addr:street":"Highbrook;Bridge Road",
    "iso:country":"GB",
    "sg:address":"4 Highbrook Suite, Delta House, Bridge Road",
    "sg:city":"Haywards Heath",
    "sg:classifiers":[
        {
            "category":"Professional",
            "subcategory":"Management & Consulting",
            "type":"Services"
        }
    ],
    "sg:postcode":"RH16 1UA",
    "sg:province":"East Sussex",
    "sg:tags":[
        "consultant",
        "business"
    ],
    "wof:name":"Apex Management Consultants Ltd.",
    "wof:placetype":"venue"
},
  "geometry": {"coordinates":[-0.1020469964,50.9966583252],"type":"Point"}
}