{
  "type": "Feature",
  "properties": {
    "addr:full":"Spey Valley Smokehouse, Achnagonlin Grantown-on-spey Highland PH26 3TA",
    "addr:postcode":"ph26 3ta",
    "iso:country":"GB",
    "sg:address":"Spey Valley Smokehouse, Achnagonlin",
    "sg:city":"Grantown-on-spey",
    "sg:classifiers":[
        {
            "category":"Food & Beverages",
            "subcategory":"Meat & Fish",
            "type":"Retail Goods"
        }
    ],
    "sg:phone":"+44 1479 873078",
    "sg:postcode":"PH26 3TA",
    "sg:province":"Highland",
    "sg:tags":[
        "merchant"
    ],
    "wof:name":"Strathaird Salmon",
    "wof:placetype":"venue"
},
  "geometry": {"coordinates":[-3.6067790985,57.3320007324],"type":"Point"}
}