{
  "type": "Feature",
  "properties": {
    "addr:full":"Mitchell Street, Low Walker Newcastle-upon-tyne Tyne and Wear NE6 3PR",
    "addr:postcode":"ne6 3pr",
    "addr:street":"Mitchell Street;Walker",
    "iso:country":"GB",
    "sg:address":"Mitchell Street, Low Walker",
    "sg:city":"Newcastle-upon-tyne",
    "sg:classifiers":[
        {
            "category":"Bars & Pubs",
            "type":"Food & Drink"
        },
        {
            "category":"Community Center",
            "subcategory":"Social",
            "type":"Public Place"
        }
    ],
    "sg:phone":"+44 191 262 3010",
    "sg:postcode":"NE6 3PR",
    "sg:province":"Tyne and Wear",
    "sg:tags":[
        "pubs",
        "house",
        "inn",
        "activity"
    ],
    "wof:name":"Wincomblee Hotel",
    "wof:placetype":"venue"
},
  "geometry": {"coordinates":[-1.5393279791,54.9741363525],"type":"Point"}
}