{
  "type": "Feature",
  "properties": {
    "iso:country":"GB",
    "sg:address":"Alvana, Rocky Park Road, Plymstock",
    "sg:city":"Plymouth",
    "sg:classifiers":[
        {
            "category":"Retail",
            "subcategory":"Repair Shop",
            "type":"Services"
        },
        {
            "category":"Building & Trades",
            "subcategory":"Construction",
            "type":"Services"
        }
    ],
    "sg:phone":"+44 1752 481576",
    "sg:postcode":"PL9 7DQ",
    "sg:province":"Devon",
    "sg:tags":[
        "builder",
        "maintenance",
        "contractor"
    ],
    "wof:name":"Imperial Construction",
    "wof:placetype":"venue"
},
  "geometry": {"coordinates":[-4.094705,50.36338],"type":"Point"}
}