{
  "type": "Feature",
  "properties": {
    "addr:full":"Britannia House, High Street, Bream Lydney Gloucestershire GL15 6JS",
    "addr:postcode":"gl15 6js",
    "addr:street":"High Street",
    "iso:country":"GB",
    "sg:address":"Britannia House, High Street, Bream",
    "sg:city":"Lydney",
    "sg:classifiers":[
        {
            "category":"Manufacturing",
            "subcategory":"Tools & Machinery",
            "type":"Manufacturing & Wholesale Goods"
        },
        {
            "category":"Insurance",
            "subcategory":"Insurance Agent",
            "type":"Services"
        }
    ],
    "sg:phone":"+44 1594 563288",
    "sg:postcode":"GL15 6JS",
    "sg:province":"Gloucestershire",
    "sg:tags":[
        "society",
        "broker",
        "friendly"
    ],
    "wof:name":"Farmer & Clark",
    "wof:placetype":"venue"
},
  "geometry": {"coordinates":[-2.553256,51.714771],"type":"Point"}
}