{
  "type": "Feature",
  "properties": {
    "addr:full":"Wardens's House, 7 Lowry Close, Great Sankey Warrington Cheshire WA5 1EL",
    "addr:housenumber":"7",
    "addr:postcode":"wa5 1el",
    "addr:street":"Lowry Close",
    "iso:country":"GB",
    "sg:address":"Wardens's House, 7 Lowry Close, Great Sankey",
    "sg:city":"Warrington",
    "sg:classifiers":[
        {
            "category":"Social Services",
            "subcategory":"Adult Care",
            "type":"Services"
        }
    ],
    "sg:phone":"+44 1925 638282",
    "sg:postcode":"WA5 1EL",
    "sg:province":"Cheshire",
    "sg:tags":[
        "housing",
        "sheltered"
    ],
    "wof:name":"Warrington Housing Association Ltd.",
    "wof:placetype":"venue"
},
  "geometry": {"coordinates":[-2.6246669292,53.3948059082],"type":"Point"}
}