{
  "type": "Feature",
  "properties": {
    "addr:full":"10 Olrig Street Thurso Highland KW14 7BJ",
    "addr:housenumber":"10",
    "addr:postcode":"kw14 7bj",
    "addr:street":"Olrig Street",
    "iso:country":"GB",
    "sg:address":"10 Olrig Street",
    "sg:city":"Thurso",
    "sg:classifiers":[
        {
            "category":"Shopping",
            "subcategory":"Department Store",
            "type":"Retail Goods"
        }
    ],
    "sg:phone":"+44 1847 893344",
    "sg:postcode":"KW14 7BJ",
    "sg:province":"Highland",
    "wof:name":"Caithness Stationers Ltd.",
    "wof:placetype":"venue"
},
  "geometry": {"coordinates":[-3.5210690498,58.5949249268],"type":"Point"}
}