{
  "type": "Feature",
  "properties": {
    "addr:full":"5 Adelphi Road Paignton Devon TQ4 6AW",
    "addr:housenumber":"5",
    "addr:postcode":"tq4 6aw",
    "addr:street":"Adelphi Road",
    "iso:country":"GB",
    "sg:address":"5 Adelphi Road",
    "sg:city":"Paignton",
    "sg:classifiers":[
        {
            "category":"Travel",
            "subcategory":"Hotels & Motels",
            "type":"Entertainment"
        }
    ],
    "sg:phone":"+44 1803 551560",
    "sg:postcode":"TQ4 6AW",
    "sg:province":"Devon",
    "wof:name":"The Beresford Hotel",
    "wof:placetype":"venue"
},
  "geometry": {"coordinates":[-3.5611140728,50.4333839417],"type":"Point"}
}