{
  "type": "Feature",
  "properties": {
    "iso:country":"GB",
    "sg:address":"39 Sandpiper Crescent",
    "sg:city":"Malvern",
    "sg:classifiers":[
        {
            "category":"Recreation",
            "type":"Entertainment"
        }
    ],
    "sg:phone":"+44 1886 833828",
    "sg:postcode":"WR14 1UY",
    "sg:province":"Herefordshire",
    "sg:tags":[
        "outdoor",
        "pursuit"
    ],
    "wof:name":"Wyche Way Country Walks",
    "wof:placetype":"venue"
},
  "geometry": {"coordinates":[-2.338015,52.135567],"type":"Point"}
}