{
  "type": "Feature",
  "properties": {
    "iso:country":"GB",
    "sg:address":"Ranscombe Road",
    "sg:city":"Brixham",
    "sg:classifiers":[
        {
            "category":"Travel",
            "subcategory":"Hotels & Motels",
            "type":"Entertainment"
        }
    ],
    "sg:postcode":"TQ5 9UP",
    "sg:province":"Devon",
    "wof:name":"Ranscombe House Hotel",
    "wof:placetype":"venue"
},
  "geometry": {"coordinates":[-3.505774,50.393486],"type":"Point"}
}