{
  "type": "Feature",
  "properties": {
    "addr:full":"2 Frankfort Gate Plymouth Devon PL1 1QD",
    "addr:housenumber":"2",
    "addr:postcode":"pl1 1qd",
    "addr:street":"Frankfort Gate",
    "iso:country":"GB",
    "sg:address":"2 Frankfort Gate",
    "sg:city":"Plymouth",
    "sg:classifiers":[
        {
            "category":"Shopping",
            "subcategory":"Bicycles & Sporting Goods",
            "type":"Retail Goods"
        }
    ],
    "sg:phone":"+44 1752 664771",
    "sg:postcode":"PL1 1QD",
    "sg:province":"Devon",
    "sg:tags":[
        "cycle",
        "accessory"
    ],
    "wof:name":"Devon Cycles",
    "wof:placetype":"venue"
},
  "geometry": {"coordinates":[-4.147949,50.371841],"type":"Point"}
}