{
  "type": "Feature",
  "properties": {
    "iso:country":"GB",
    "sg:address":"11 Harben Parade, Finchley Road",
    "sg:city":"London",
    "sg:classifiers":[
        {
            "category":"Communications",
            "subcategory":"Film & Video Production",
            "type":"Services"
        }
    ],
    "sg:phone":"+44 20 7722 3016",
    "sg:postcode":"NW3 6JP",
    "sg:province":"Greater London",
    "sg:tags":[
        "tv"
    ],
    "wof:name":"Radio Rentals",
    "wof:placetype":"venue"
},
  "geometry": {"coordinates":[-0.17646,51.54464],"type":"Point"}
}