{
  "type": "Feature",
  "properties": {
    "iso:country":"GB",
    "sg:address":"2a/4a Araby Corner, High Street",
    "sg:city":"Shepperton",
    "sg:classifiers":[
        {
            "category":"Organizations",
            "subcategory":"Community Association",
            "type":"Services"
        }
    ],
    "sg:phone":"+44 1932 254110",
    "sg:postcode":"TW17 9AW",
    "sg:province":"Surrey",
    "sg:tags":[
        "relation",
        "public"
    ],
    "wof:name":"Adrian Barker Publicity",
    "wof:placetype":"venue"
},
  "geometry": {"coordinates":[-0.448547,51.394321],"type":"Point"}
}