{
  "type": "Feature",
  "properties": {
    "addr:full":"The Sq Emsworth Hampshire PO10 8UE",
    "addr:postcode":"po10 8ue",
    "addr:street":"The Sq",
    "iso:country":"GB",
    "sg:address":"The Sq",
    "sg:city":"Emsworth",
    "sg:classifiers":[
        {
            "category":"Farming",
            "subcategory":"Fish & Marine Products",
            "type":"Manufacturing & Wholesale Goods"
        }
    ],
    "sg:postcode":"PO10 8UE",
    "sg:province":"Hampshire",
    "sg:tags":[
        "fishmonger"
    ],
    "wof:name":"Treagust,Norman R,",
    "wof:placetype":"venue"
},
  "geometry": {"coordinates":[-0.925936,50.861595],"type":"Point"}
}