{
  "type": "Feature",
  "properties": {
    "iso:country":"GB",
    "sg:address":"12 Roper Street",
    "sg:city":"Whitehaven",
    "sg:classifiers":[
        {
            "category":"Personal",
            "subcategory":"Barber",
            "type":"Services"
        }
    ],
    "sg:phone":"+44 1946 694585",
    "sg:postcode":"CA28 7AU",
    "sg:province":"Cumbria",
    "sg:tags":[
        "men's",
        "hairdresser"
    ],
    "wof:name":"David's",
    "wof:placetype":"venue"
},
  "geometry": {"coordinates":[-3.589449,54.547226],"type":"Point"}
}