{
  "type": "Feature",
  "properties": {
    "addr:full":"26 Goldspink Lane Newcastle-upon-tyne Tyne and Wear NE2 1NR",
    "addr:housenumber":"26",
    "addr:postcode":"ne2 1nr",
    "addr:street":"Goldspink Lane",
    "iso:country":"GB",
    "sg:address":"26 Goldspink Lane",
    "sg:city":"Newcastle-upon-tyne",
    "sg:classifiers":[
        {
            "category":"Personal",
            "subcategory":"Beauty Salon",
            "type":"Services"
        },
        {
            "category":"Personal",
            "subcategory":"Barber",
            "type":"Services"
        }
    ],
    "sg:phone":"+44 191 232 3868",
    "sg:postcode":"NE2 1NR",
    "sg:province":"Tyne and Wear",
    "sg:tags":[
        "unisex",
        "hairdresser"
    ],
    "wof:name":"Glorious Hairdressing",
    "wof:placetype":"venue"
},
  "geometry": {"coordinates":[-1.5951319933,54.9826545715],"type":"Point"}
}