{
  "type": "Feature",
  "properties": {
    "iso:country":"GB",
    "sg:address":"294a Lymington Rd, Highcliffe",
    "sg:city":"Christchurch",
    "sg:classifiers":[
        {
            "category":"Building & Trades",
            "subcategory":"Construction",
            "type":"Services"
        }
    ],
    "sg:postcode":"BH23 5ET",
    "sg:province":"Dorset",
    "sg:tags":[
        "bricklaying"
    ],
    "wof:name":"Sunnyvale Developments Ltd",
    "wof:placetype":"venue"
},
  "geometry": {"coordinates":[-1.701107,50.741322],"type":"Point"}
}