{
  "type": "Feature",
  "properties": {
    "addr:full":"Lapworth Street, Lowsonford Solihull Warwickshire B95 5HJ",
    "addr:postcode":"b95 5hj",
    "addr:street":"Lapworth Street",
    "iso:country":"GB",
    "sg:address":"Lapworth Street, Lowsonford",
    "sg:city":"Solihull",
    "sg:classifiers":[
        {
            "category":"Bars & Pubs",
            "type":"Food & Drink"
        },
        {
            "category":"Community Center",
            "subcategory":"Social",
            "type":"Public Place"
        }
    ],
    "sg:phone":"+44 1564 782431",
    "sg:postcode":"B95 5HJ",
    "sg:province":"Warwickshire",
    "sg:tags":[
        "pubs",
        "house",
        "inn",
        "activity"
    ],
    "wof:name":"The Fleur De Lys Inn",
    "wof:placetype":"venue"
},
  "geometry": {"coordinates":[-1.717559,52.307816],"type":"Point"}
}