{
  "type": "Feature",
  "properties": {
    "addr:full":"St Margarets Vicarage, Gladstone Street Aberdare Neath Port Talbot CF44 6SA",
    "addr:postcode":"cf44 6sa",
    "addr:street":"Gladstone Street",
    "iso:country":"GB",
    "sg:address":"St Margarets Vicarage, Gladstone Street",
    "sg:city":"Aberdare",
    "sg:classifiers":[
        {
            "category":"Place Of Worship",
            "type":"Public Place"
        }
    ],
    "sg:phone":"+44 1685 872871",
    "sg:postcode":"CF44 6SA",
    "sg:province":"Neath Port Talbot",
    "wof:name":"St Margeret's Church",
    "wof:placetype":"venue"
},
  "geometry": {"coordinates":[-3.42468,51.698547],"type":"Point"}
}