{
  "type": "Feature",
  "properties": {
    "addr:full":"442 Thornton Road Bradford West Yorkshire BD8 9BS",
    "addr:housenumber":"442",
    "addr:postcode":"bd8 9bs",
    "addr:street":"Thornton Road",
    "iso:country":"GB",
    "sg:address":"442 Thornton Road",
    "sg:city":"Bradford",
    "sg:classifiers":[
        {
            "category":"Professional",
            "subcategory":"Accounting & Tax Preparation",
            "type":"Services"
        }
    ],
    "sg:phone":"+44 1274 824245",
    "sg:postcode":"BD8 9BS",
    "sg:province":"West Yorkshire",
    "sg:tags":[
        "accountant"
    ],
    "wof:name":"Flex Accountancy Services",
    "wof:placetype":"venue"
},
  "geometry": {"coordinates":[-1.783314,53.799252],"type":"Point"}
}