{
  "type": "Feature",
  "properties": {
    "iso:country":"GB",
    "sg:address":"50 Belhaven Terrace",
    "sg:city":"Wishaw",
    "sg:classifiers":[
        {
            "category":"Banks & Credit Unions",
            "subcategory":"Financial Services",
            "type":"Services"
        }
    ],
    "sg:phone":"+44 1698 307000",
    "sg:postcode":"ML2 7AY",
    "sg:province":"North Lanarkshire",
    "sg:tags":[
        "adviser"
    ],
    "wof:name":"Sal Financial Services",
    "wof:placetype":"venue"
},
  "geometry": {"coordinates":[-3.9254620075,55.7739944458],"type":"Point"}
}