{
  "type": "Feature",
  "properties": {
    "iso:country":"GB",
    "sg:address":"Donington Park, Castle Donington",
    "sg:city":"Derby",
    "sg:classifiers":[
        {
            "category":"Taxi",
            "type":"Transportation"
        },
        {
            "category":"Military Area",
            "subcategory":"Air Force Base",
            "type":"Public Place"
        }
    ],
    "sg:phone":"+44 1332 812009",
    "sg:postcode":"DE74 2RP",
    "sg:province":"Leicestershire",
    "sg:tags":[
        "hire",
        "private"
    ],
    "wof:name":"EAST MIDLAND AIRPORT TAXIS ASSOCIATION",
    "wof:placetype":"venue"
},
  "geometry": {"coordinates":[-1.3373839855,52.8448791504],"type":"Point"}
}