{
  "type": "Feature",
  "properties": {
    "addr:full":"Crown House, 217 Higher Hillgate Stockport Cheshire SK1 3RB",
    "addr:housenumber":"217",
    "addr:postcode":"sk1 3rb",
    "addr:street":"Higher Hillgate",
    "iso:country":"GB",
    "sg:address":"Crown House, 217 Higher Hillgate",
    "sg:city":"Stockport",
    "sg:classifiers":[
        {
            "category":"Professional",
            "subcategory":"Accounting & Tax Preparation",
            "type":"Services"
        }
    ],
    "sg:phone":"+44 161 476 5445",
    "sg:postcode":"SK1 3RB",
    "sg:province":"Cheshire",
    "sg:tags":[
        "accountant"
    ],
    "wof:name":"Simmonds & Co.",
    "wof:placetype":"venue"
},
  "geometry": {"coordinates":[-2.152723074,53.3986473083],"type":"Point"}
}