{
  "type": "Feature",
  "properties": {
    "iso:country":"GB",
    "sg:address":"Gwynfair Club, Ravenspoint Rd, Trearddur Bay",
    "sg:city":"Holyhead",
    "sg:classifiers":[
        {
            "category":"Organizations",
            "subcategory":"Membership Organization",
            "type":"Services"
        }
    ],
    "sg:phone":"+44 1407 861256",
    "sg:postcode":"LL65 2AX",
    "sg:province":"Isle of Anglesey",
    "sg:tags":[
        "club"
    ],
    "wof:name":"B Heywood",
    "wof:placetype":"venue"
},
  "geometry": {"coordinates":[-4.6307139397,53.3063697815],"type":"Point"}
}