{
  "type": "Feature",
  "properties": {
    "addr:full":"Guisborough Health Centre, Bow St Guisborough North Yorkshire TS14 7AA",
    "addr:postcode":"ts14 7aa",
    "addr:street":"Bow St",
    "iso:country":"GB",
    "sg:address":"Guisborough Health Centre, Bow St",
    "sg:city":"Guisborough",
    "sg:classifiers":[
        {
            "category":"Health Services",
            "subcategory":"Doctor",
            "type":"Services"
        }
    ],
    "sg:phone":"+44 1287 634171",
    "sg:postcode":"TS14 7AA",
    "sg:province":"North Yorkshire",
    "sg:tags":[
        "practitioners"
    ],
    "wof:name":"Halloway, A",
    "wof:placetype":"venue"
},
  "geometry": {"coordinates":[-1.0522840023,54.5356369019],"type":"Point"}
}