{
  "type": "Feature",
  "properties": {
    "iso:country":"GB",
    "sg:address":"43a The Avenue, Acocks Green",
    "sg:city":"Birmingham",
    "sg:classifiers":[
        {
            "category":"Wholesale",
            "subcategory":"Scrap",
            "type":"Manufacturing & Wholesale Goods"
        }
    ],
    "sg:phone":"+44 121 764 4091",
    "sg:postcode":"B27 6NG",
    "sg:province":"West Midlands",
    "sg:tags":[
        "waste",
        "metal"
    ],
    "wof:name":"Market & Shop Supplies Ltd",
    "wof:placetype":"venue"
},
  "geometry": {"coordinates":[-1.816118,52.449047],"type":"Point"}
}