{
  "type": "Feature",
  "properties": {
    "addr:full":"Penrith Methodist Church, Wordsworth St Penrith Cumbria CA11 7QY",
    "addr:postcode":"ca11 7qy",
    "addr:street":"Wordsworth St",
    "iso:country":"GB",
    "sg:address":"Penrith Methodist Church, Wordsworth St",
    "sg:city":"Penrith",
    "sg:classifiers":[
        {
            "category":"Organizations",
            "subcategory":"Religious Organization",
            "type":"Services"
        }
    ],
    "sg:phone":"+44 1768 891723",
    "sg:postcode":"CA11 7QY",
    "sg:province":"Cumbria",
    "sg:tags":[
        "organisation"
    ],
    "wof:name":"Cumbria Methodist District Mission Enabler",
    "wof:placetype":"venue"
},
  "geometry": {"coordinates":[-2.7574689388,54.6643028259],"type":"Point"}
}