{
  "type": "Feature",
  "properties": {
    "addr:full":"64 Cortworth Road Sheffield Derbyshire S11 9LP",
    "addr:housenumber":"64",
    "addr:postcode":"s11 9lp",
    "addr:street":"Cortworth Road",
    "iso:country":"GB",
    "sg:address":"64 Cortworth Road",
    "sg:city":"Sheffield",
    "sg:classifiers":[
        {
            "category":"Building & Trades",
            "subcategory":"Construction",
            "type":"Services"
        }
    ],
    "sg:postcode":"S11 9LP",
    "sg:province":"Derbyshire",
    "sg:tags":[
        "builder"
    ],
    "wof:name":"F J F Construction Ltd.",
    "wof:placetype":"venue"
},
  "geometry": {"coordinates":[-1.517363,53.35186],"type":"Point"}
}