{
  "type": "Feature",
  "properties": {
    "addr:full":"26 Bank View Road Derby Derbyshire DE22 1EJ",
    "addr:housenumber":"26",
    "addr:postcode":"de22 1ej",
    "addr:street":"Bank View Road",
    "iso:country":"GB",
    "sg:address":"26 Bank View Road",
    "sg:city":"Derby",
    "sg:classifiers":[
        {
            "category":"Professional",
            "subcategory":"Engineering",
            "type":"Services"
        }
    ],
    "sg:phone":"+44 1332 364474",
    "sg:postcode":"DE22 1EJ",
    "sg:province":"Derbyshire",
    "sg:tags":[
        "contractor",
        "electrical",
        "engineer"
    ],
    "wof:name":"M C Electrics",
    "wof:placetype":"venue"
},
  "geometry": {"coordinates":[-1.4822280407,52.9364547729],"type":"Point"}
}