{
  "type": "Feature",
  "properties": {
    "addr:full":"7 Oundle Rd Peterborough Cambridgeshire PE2 9AA",
    "addr:housenumber":"7",
    "addr:postcode":"pe2 9aa",
    "addr:street":"Oundle Rd",
    "iso:country":"GB",
    "sg:address":"7 Oundle Rd",
    "sg:city":"Peterborough",
    "sg:classifiers":[
        {
            "category":"Autos & Motor Vehicles",
            "subcategory":"Auto Supplies",
            "type":"Retail Goods"
        }
    ],
    "sg:postcode":"PE2 9AA",
    "sg:province":"Cambridgeshire",
    "sg:tags":[
        "component"
    ],
    "wof:name":"Express Factor of Peterborough",
    "wof:placetype":"venue"
},
  "geometry": {"coordinates":[-0.2448229939,52.5660247803],"type":"Point"}
}