{
  "type": "Feature",
  "properties": {
    "iso:country":"GB",
    "sg:address":"Cupernham Lane",
    "sg:city":"Romsey",
    "sg:classifiers":[
        {
            "category":"Home & Garden",
            "subcategory":"Hardware",
            "type":"Retail Goods"
        }
    ],
    "sg:phone":"+44 1794 521111",
    "sg:postcode":"SO51 7LF",
    "sg:province":"Hampshire",
    "sg:tags":[
        "sealant",
        "glue",
        "adhesives"
    ],
    "wof:name":"Wessex Resins & Adhesives Ltd.",
    "wof:placetype":"venue"
},
  "geometry": {"coordinates":[-1.4848940372,51.0040550232],"type":"Point"}
}