{
  "type": "Feature",
  "properties": {
    "iso:country":"GB",
    "sg:address":"4 Drumsheugh Place",
    "sg:city":"Edinburgh",
    "sg:classifiers":[
        {
            "category":"Shopping",
            "subcategory":"Thrift Store",
            "type":"Retail Goods"
        }
    ],
    "sg:phone":"+44 131 220 0802",
    "sg:postcode":"EH3 7PT",
    "sg:province":"City of Edinburgh",
    "sg:tags":[
        "shop",
        "charity"
    ],
    "wof:name":"The Kist",
    "wof:placetype":"venue"
},
  "geometry": {"coordinates":[-3.214397,55.950573],"type":"Point"}
}