{
  "type": "Feature",
  "properties": {
    "iso:country":"GB",
    "sg:address":"19 Sussex Drive",
    "sg:city":"Bognor Regis",
    "sg:classifiers":[
        {
            "category":"Communications",
            "type":"Services"
        },
        {
            "category":"Communications",
            "subcategory":"Television Station",
            "type":"Services"
        }
    ],
    "sg:phone":"+44 1243 262744",
    "sg:postcode":"PO21 4RW",
    "sg:province":"West Sussex",
    "sg:tags":[
        "satellite",
        "tv",
        "related",
        "equipment",
        "video",
        "radio"
    ],
    "wof:name":"D J Tellykings",
    "wof:placetype":"venue"
},
  "geometry": {"coordinates":[-0.735276,50.775898],"type":"Point"}
}