{
  "type": "Feature",
  "properties": {
    "addr:full":"4 Lichfield Street Wolverhampton West Midlands WV1 1DG",
    "addr:housenumber":"4",
    "addr:postcode":"wv1 1dg",
    "addr:street":"Lichfield Street",
    "iso:country":"GB",
    "sg:address":"4 Lichfield Street",
    "sg:city":"Wolverhampton",
    "sg:classifiers":[
        {
            "category":"Shopping",
            "subcategory":"Tobacco",
            "type":"Retail Goods"
        }
    ],
    "sg:phone":"+44 1902 423319",
    "sg:postcode":"WV1 1DG",
    "sg:province":"West Midlands",
    "sg:tags":[
        "tobacconist"
    ],
    "wof:name":"James Tobacconists",
    "wof:placetype":"venue"
},
  "geometry": {"coordinates":[-2.1269459724,52.58644104],"type":"Point"}
}