{
  "type": "Feature",
  "properties": {
    "addr:full":", Sandside Milnthorpe Cumbria LA7 7HW",
    "addr:postcode":"la7 7hw",
    "iso:country":"GB",
    "sg:address":", Sandside",
    "sg:city":"Milnthorpe",
    "sg:classifiers":[
        {
            "category":"Bars & Pubs",
            "type":"Food & Drink"
        }
    ],
    "sg:phone":"+44 15395 63113",
    "sg:postcode":"LA7 7HW",
    "sg:province":"Cumbria",
    "sg:tags":[
        "pubs",
        "inn"
    ],
    "wof:name":"Ship Inn",
    "wof:placetype":"venue"
},
  "geometry": {"coordinates":[-2.772592,54.226864],"type":"Point"}
}