{
  "type": "Feature",
  "properties": {
    "addr:full":"8a Parr Street Poole Dorset BH14 0JY",
    "addr:housenumber":"8a",
    "addr:postcode":"bh14 0jy",
    "addr:street":"Parr Street",
    "iso:country":"GB",
    "sg:address":"8a Parr Street",
    "sg:city":"Poole",
    "sg:classifiers":[
        {
            "category":"Recreation",
            "type":"Entertainment"
        }
    ],
    "sg:postcode":"BH14 0JY",
    "sg:province":"Dorset",
    "sg:tags":[
        "snooker",
        "billiards",
        "pool"
    ],
    "wof:name":"Ashley Cross Leisure Club",
    "wof:placetype":"venue"
},
  "geometry": {"coordinates":[-1.953489,50.723866],"type":"Point"}
}