{
  "type": "Feature",
  "properties": {
    "iso:country":"GB",
    "sg:address":"48a High Street",
    "sg:city":"Saffron Walden",
    "sg:classifiers":[
        {
            "category":"Sports & Exercise",
            "subcategory":"Gym",
            "type":"Entertainment"
        }
    ],
    "sg:phone":"+44 1799 513469",
    "sg:postcode":"CB10 1EE",
    "sg:province":"Cambridgeshire",
    "sg:tags":[
        "club",
        "fitness",
        "health",
        "centre"
    ],
    "sg:website":"http://www.wilburs.co.uk",
    "wof:name":"Wilburs Fitness & Gym",
    "wof:placetype":"venue"
},
  "geometry": {"coordinates":[0.2394379973,52.0223007202],"type":"Point"}
}