{
  "type": "Feature",
  "properties": {
    "iso:country":"GB",
    "sg:address":"9f West Bromwich Market",
    "sg:city":"West Bromwich",
    "sg:classifiers":[
        {
            "category":"Farming",
            "subcategory":"Farm",
            "type":"Manufacturing & Wholesale Goods"
        }
    ],
    "sg:postcode":"B71 4LD",
    "sg:province":"West Midlands",
    "sg:tags":[
        "egg",
        "producer"
    ],
    "wof:name":"J L Thomas & Sons",
    "wof:placetype":"venue"
},
  "geometry": {"coordinates":[-1.96686,52.508949],"type":"Point"}
}