{
  "type": "Feature",
  "properties": {
    "iso:country":"GB",
    "sg:address":"22 High St",
    "sg:city":"Burnham On Crouch",
    "sg:classifiers":[
        {
            "category":"Autos & Motor Vehicles",
            "subcategory":"Boat Sales",
            "type":"Retail Goods"
        }
    ],
    "sg:phone":"+44 1621 782237",
    "sg:postcode":"CM0 8AA",
    "sg:province":"Essex",
    "sg:tags":[
        "equipment"
    ],
    "wof:name":"Yacht Tests Ltd",
    "wof:placetype":"venue"
},
  "geometry": {"coordinates":[0.817837,51.625355],"type":"Point"}
}