{
  "type": "Feature",
  "properties": {
    "addr:full":"2 Wheatfield Road Ayr South Ayrshire KA7 2XB",
    "addr:housenumber":"2",
    "addr:postcode":"ka7 2xb",
    "addr:street":"Wheatfield Road",
    "iso:country":"GB",
    "sg:address":"2 Wheatfield Road",
    "sg:city":"Ayr",
    "sg:classifiers":[
        {
            "category":"Shopping",
            "subcategory":"Pharmacy",
            "type":"Retail Goods"
        }
    ],
    "sg:postcode":"KA7 2XB",
    "sg:province":"South Ayrshire",
    "sg:tags":[
        "medicine",
        "therapy"
    ],
    "wof:name":"Douglas W Bell",
    "wof:placetype":"venue"
},
  "geometry": {"coordinates":[-4.6379041672,55.4552116394],"type":"Point"}
}