{
  "type": "Feature",
  "properties": {
    "iso:country":"GB",
    "sg:address":"8 Maes Y Llan",
    "sg:city":"Meifod",
    "sg:classifiers":[
        {
            "category":"Professional",
            "subcategory":"Engineering",
            "type":"Services"
        }
    ],
    "sg:postcode":"SY22 6DE",
    "sg:province":"Shropshire",
    "sg:tags":[
        "contractor",
        "electrical",
        "engineer"
    ],
    "wof:name":"Tony Isaac",
    "wof:placetype":"venue"
},
  "geometry": {"coordinates":[-3.257929,52.710873],"type":"Point"}
}