{
  "type": "Feature",
  "properties": {
    "addr:full":"153 Queensway, Bletchley Milton Keynes Buckinghamshire MK2 2DY",
    "addr:housenumber":"153",
    "addr:postcode":"mk2 2dy",
    "addr:street":"Queensway",
    "iso:country":"GB",
    "sg:address":"153 Queensway, Bletchley",
    "sg:city":"Milton Keynes",
    "sg:classifiers":[
        {
            "category":"Cinema",
            "subcategory":"Movie Rental",
            "type":"Entertainment"
        }
    ],
    "sg:phone":"+44 1908 366694",
    "sg:postcode":"MK2 2DY",
    "sg:province":"Buckinghamshire",
    "sg:tags":[
        "video",
        "library"
    ],
    "wof:name":"Blockbuster Video",
    "wof:placetype":"venue"
},
  "geometry": {"coordinates":[-0.727428,51.995308],"type":"Point"}
}