{
  "type": "Feature",
  "properties": {
    "addr:full":"The Ford, Townsend Park Leominster Herefordshire HR6 0DZ",
    "addr:postcode":"hr6 0dz",
    "addr:street":"Townsend Park",
    "iso:country":"GB",
    "sg:address":"The Ford, Townsend Park",
    "sg:city":"Leominster",
    "sg:classifiers":[
        {
            "category":"Building & Trades",
            "subcategory":"Construction",
            "type":"Services"
        }
    ],
    "sg:phone":"+44 1568 615763",
    "sg:postcode":"HR6 0DZ",
    "sg:province":"Herefordshire",
    "sg:tags":[
        "builder"
    ],
    "wof:name":"Richard Byard",
    "wof:placetype":"venue"
},
  "geometry": {"coordinates":[-2.754969,52.266159],"type":"Point"}
}