{
  "type": "Feature",
  "properties": {
    "addr:full":"Manor Park, Manor Lane, Hawarden Deeside Flintshire CH5 3PP",
    "addr:postcode":"ch5 3pp",
    "addr:street":"Manor Park Manor Lane",
    "iso:country":"GB",
    "sg:address":"Manor Park, Manor Lane, Hawarden",
    "sg:city":"Deeside",
    "sg:classifiers":[
        {
            "category":"Building & Trades",
            "subcategory":"Construction",
            "type":"Services"
        }
    ],
    "sg:phone":"+44 1244 532420",
    "sg:postcode":"CH5 3PP",
    "sg:province":"Flintshire",
    "sg:tags":[
        "roofing"
    ],
    "wof:name":"H Pae & Son",
    "wof:placetype":"venue"
},
  "geometry": {"coordinates":[-2.994590044,53.1780052185],"type":"Point"}
}