{
  "type": "Feature",
  "properties": {
    "addr:full":"18 Jubilee Street Newquay Cornwall TR7 1LA",
    "addr:housenumber":"18",
    "addr:postcode":"tr7 1la",
    "addr:street":"Jubilee Street",
    "iso:country":"GB",
    "sg:address":"18 Jubilee Street",
    "sg:city":"Newquay",
    "sg:classifiers":[
        {
            "category":"Professional",
            "subcategory":"Engineering",
            "type":"Services"
        },
        {
            "category":"Building & Trades",
            "subcategory":"Electrical",
            "type":"Services"
        }
    ],
    "sg:phone":"+44 1637 872528",
    "sg:postcode":"TR7 1LA",
    "sg:province":"Cornwall",
    "sg:tags":[
        "engineer",
        "electrician",
        "contractor"
    ],
    "wof:name":"P G Randell Electrical",
    "wof:placetype":"venue"
},
  "geometry": {"coordinates":[-5.089737,50.414162],"type":"Point"}
}