{
  "type": "Feature",
  "properties": {
    "addr:full":"St Lukes Road, Pallion Industrial Estate Sunderland Tyne and Wear SR4 6RJ",
    "addr:housenumber":"estate",
    "addr:postcode":"sr4 6rj",
    "addr:street":"St Lukes Road;Industrial",
    "iso:country":"GB",
    "sg:address":"St Lukes Road, Pallion Industrial Estate",
    "sg:city":"Sunderland",
    "sg:classifiers":[
        {
            "category":"Utilities",
            "subcategory":"Natural Gas",
            "type":"Services"
        }
    ],
    "sg:phone":"+44 800 389 8229",
    "sg:postcode":"SR4 6RJ",
    "sg:province":"Tyne and Wear",
    "sg:tags":[
        "supplier"
    ],
    "wof:name":"Air Products",
    "wof:placetype":"venue"
},
  "geometry": {"coordinates":[-1.4156589508,54.9092750549],"type":"Point"}
}