{
  "type": "Feature",
  "properties": {
    "addr:full":"4 Regent Mews, Prince Regent Street Stockton-on-tees Durham TS18 1DD",
    "addr:housenumber":"4",
    "addr:postcode":"ts18 1dd",
    "addr:street":"Regent Mews;Regent Street",
    "iso:country":"GB",
    "sg:address":"4 Regent Mews, Prince Regent Street",
    "sg:city":"Stockton-on-tees",
    "sg:classifiers":[
        {
            "category":"Recreation",
            "subcategory":"Dog Park",
            "type":"Entertainment"
        }
    ],
    "sg:phone":"+44 1642 670396",
    "sg:postcode":"TS18 1DD",
    "sg:province":"Durham",
    "wof:name":"Petsworld",
    "wof:placetype":"venue"
},
  "geometry": {"coordinates":[-1.3130140305,54.5656204224],"type":"Point"}
}