{
  "type": "Feature",
  "properties": {
    "addr:full":"62 Mellish St, Isle Of Dogs London Greater London E14 8NS",
    "addr:housenumber":"62",
    "addr:postcode":"e14 8ns",
    "addr:street":"Mellish St",
    "iso:country":"GB",
    "sg:address":"62 Mellish St, Isle Of Dogs",
    "sg:city":"London",
    "sg:classifiers":[
        {
            "category":"Professional",
            "type":"Services"
        }
    ],
    "sg:phone":"+44 171 538 2438",
    "sg:postcode":"E14 8NS",
    "sg:province":"Greater London",
    "sg:tags":[
        "interior",
        "furnishers",
        "designer"
    ],
    "wof:name":"Work & Art Ltd",
    "wof:placetype":"venue"
},
  "geometry": {"coordinates":[-0.0229400005,51.4969596863],"type":"Point"}
}