{
  "type": "Feature",
  "properties": {
    "addr:full":"228 Gloucester Rd, Bishopston Bristol City of Bristol BS7 8NZ",
    "addr:housenumber":"228",
    "addr:postcode":"bs7 8nz",
    "addr:street":"Gloucester Rd",
    "iso:country":"GB",
    "sg:address":"228 Gloucester Rd, Bishopston",
    "sg:city":"Bristol",
    "sg:classifiers":[
        {
            "category":"Banks & Credit Unions",
            "subcategory":"Financial Services",
            "type":"Services"
        }
    ],
    "sg:postcode":"BS7 8NZ",
    "sg:province":"City of Bristol",
    "sg:tags":[
        "consultant"
    ],
    "wof:name":"Donisace,Nwaokobia,",
    "wof:placetype":"venue"
},
  "geometry": {"coordinates":[-2.593415,51.469959],"type":"Point"}
}