{
  "type": "Feature",
  "properties": {
    "iso:country":"GB",
    "sg:address":"9 Staverton Close",
    "sg:city":"Wokingham",
    "sg:classifiers":[
        {
            "category":"Building & Trades",
            "subcategory":"Plumbing",
            "type":"Services"
        }
    ],
    "sg:postcode":"RG11 1RR",
    "sg:province":"Berkshire",
    "sg:tags":[
        "heating"
    ],
    "wof:name":"Durham Plumbing & Heating",
    "wof:placetype":"venue"
},
  "geometry": {"coordinates":[-0.811221,51.413094],"type":"Point"}
}