{
  "type": "Feature",
  "properties": {
    "addr:full":"Chester Street, Brampton Chesterfield Derbyshire S40 1DW",
    "addr:postcode":"s40 1dw",
    "addr:street":"Chester Street",
    "iso:country":"GB",
    "sg:address":"Chester Street, Brampton",
    "sg:city":"Chesterfield",
    "sg:classifiers":[
        {
            "category":"Professional",
            "subcategory":"Business Services",
            "type":"Services"
        }
    ],
    "sg:postcode":"S40 1DW",
    "sg:province":"Derbyshire",
    "sg:tags":[
        "tile",
        "stockist"
    ],
    "wof:name":"The Tile Studio",
    "wof:placetype":"venue"
},
  "geometry": {"coordinates":[-1.445019,53.238895],"type":"Point"}
}