{
  "type": "Feature",
  "properties": {
    "addr:full":"27-28 Wholesale Market Precinct, Pershore Street Birmingham West Midlands B5 6UW",
    "addr:housenumber":"27-28",
    "addr:postcode":"b5 6uw",
    "addr:street":"Wholesale;Pershore Street",
    "iso:country":"GB",
    "sg:address":"27-28 Wholesale Market Precinct, Pershore Street",
    "sg:city":"Birmingham",
    "sg:classifiers":[
        {
            "category":"Shopping",
            "subcategory":"Florist",
            "type":"Retail Goods"
        }
    ],
    "sg:phone":"+44 121 622 6226",
    "sg:postcode":"B5 6UW",
    "sg:province":"West Midlands",
    "wof:name":"Geest Flowers Birmingham",
    "wof:placetype":"venue"
},
  "geometry": {"coordinates":[-1.89324,52.473122],"type":"Point"}
}