{
  "type": "Feature",
  "properties": {
    "addr:full":"Carousel, Beechenlea Lane Swanley Kent BR8 8DR",
    "addr:postcode":"br8 8dr",
    "addr:street":"Beechenlea Lane",
    "iso:country":"GB",
    "sg:address":"Carousel, Beechenlea Lane",
    "sg:city":"Swanley",
    "sg:classifiers":[
        {
            "category":"Retail",
            "subcategory":"Animal Services",
            "type":"Services"
        }
    ],
    "sg:phone":"+44 1322 664848",
    "sg:postcode":"BR8 8DR",
    "sg:province":"Kent",
    "sg:tags":[
        "box",
        "horse",
        "transporting"
    ],
    "wof:name":"Horseferry Transport Ltd.",
    "wof:placetype":"venue"
},
  "geometry": {"coordinates":[0.189459,51.392265],"type":"Point"}
}