{
  "type": "Feature",
  "properties": {
    "addr:full":"208 Barnett Wood Lane Ashtead Surrey KT21 2DB",
    "addr:housenumber":"208",
    "addr:postcode":"kt21 2db",
    "addr:street":"Barnett Wood Lane",
    "iso:country":"GB",
    "sg:address":"208 Barnett Wood Lane",
    "sg:city":"Ashtead",
    "sg:classifiers":[
        {
            "category":"Professional",
            "subcategory":"Management & Consulting",
            "type":"Services"
        }
    ],
    "sg:postcode":"KT21 2DB",
    "sg:province":"Surrey",
    "sg:tags":[
        "consultant",
        "business"
    ],
    "wof:name":"Beowulf Consulting Ltd",
    "wof:placetype":"venue"
},
  "geometry": {"coordinates":[-0.3103019893,51.3135070801],"type":"Point"}
}