{
  "type": "Feature",
  "properties": {
    "addr:full":"383 Preston Old Road Blackburn Lancashire BB2 5LL",
    "addr:housenumber":"383",
    "addr:postcode":"bb2 5ll",
    "addr:street":"Preston Old Road",
    "iso:country":"GB",
    "sg:address":"383 Preston Old Road",
    "sg:city":"Blackburn",
    "sg:classifiers":[
        {
            "category":"Retail",
            "subcategory":"Laundry & Dry Cleaning",
            "type":"Services"
        }
    ],
    "sg:phone":"+44 1254 208248",
    "sg:postcode":"BB2 5LL",
    "sg:province":"Lancashire",
    "sg:tags":[
        "cleaner",
        "alteration"
    ],
    "wof:name":"The Washbowl",
    "wof:placetype":"venue"
},
  "geometry": {"coordinates":[-2.518543005,53.7340164185],"type":"Point"}
}