{
  "type": "Feature",
  "properties": {
    "iso:country":"GB",
    "sg:address":"Warrington Road",
    "sg:city":"Northwich",
    "sg:classifiers":[
        {
            "category":"Restaurant",
            "type":"Food & Drink"
        }
    ],
    "sg:phone":"+44 1606 852310",
    "sg:postcode":"CW8 3QD",
    "sg:province":"Cheshire",
    "wof:name":"Rheingold Riverside Inn",
    "wof:placetype":"venue"
},
  "geometry": {"coordinates":[-2.596219,53.2738],"type":"Point"}
}