{
  "type": "Feature",
  "properties": {
    "addr:full":"1 Chapel Road Ilford Essex IG1 2AF",
    "addr:housenumber":"1",
    "addr:postcode":"ig1 2af",
    "addr:street":"Chapel Road",
    "iso:country":"GB",
    "sg:address":"1 Chapel Road",
    "sg:city":"Ilford",
    "sg:classifiers":[
        {
            "category":"Bars & Pubs",
            "type":"Food & Drink"
        },
        {
            "category":"Community Center",
            "subcategory":"Social",
            "type":"Public Place"
        }
    ],
    "sg:phone":"+44 20 8478 7060",
    "sg:postcode":"IG1 2AF",
    "sg:province":"Essex",
    "sg:tags":[
        "pubs",
        "house",
        "inn",
        "activity"
    ],
    "wof:name":"The Black Horse",
    "wof:placetype":"venue"
},
  "geometry": {"coordinates":[0.070016,51.557632],"type":"Point"}
}