{
  "type": "Feature",
  "properties": {
    "addr:full":"1 Howarth Close Bury Lancashire BL9 9SB",
    "addr:housenumber":"1",
    "addr:postcode":"bl9 9sb",
    "addr:street":"Howarth Close",
    "iso:country":"GB",
    "sg:address":"1 Howarth Close",
    "sg:city":"Bury",
    "sg:classifiers":[
        {
            "category":"Social Services",
            "type":"Services"
        },
        {
            "category":"Government",
            "subcategory":"Office",
            "type":"Public Place"
        }
    ],
    "sg:phone":"+44 161 764 9701",
    "sg:postcode":"BL9 9SB",
    "sg:province":"Lancashire",
    "sg:tags":[
        "local"
    ],
    "wof:name":"Howarth Close Hostel",
    "wof:placetype":"venue"
},
  "geometry": {"coordinates":[-2.28933,53.576637],"type":"Point"}
}