{
  "type": "Feature",
  "properties": {
    "addr:full":"2 Upper Teddington Road, Hampton Wick Kingston-upon-thames Greater London KT1 4DY",
    "addr:housenumber":"2",
    "addr:postcode":"kt1 4dy",
    "addr:street":"Upper Teddington Road",
    "iso:country":"GB",
    "sg:address":"2 Upper Teddington Road, Hampton Wick",
    "sg:city":"Kingston-upon-thames",
    "sg:classifiers":[
        {
            "category":"Real Estate",
            "subcategory":"Surveying",
            "type":"Services"
        }
    ],
    "sg:phone":"+44 20 8943 3937",
    "sg:postcode":"KT1 4DY",
    "sg:province":"Greater London",
    "sg:tags":[
        "surveyor",
        "quantity"
    ],
    "wof:name":"James Simler & Associates",
    "wof:placetype":"venue"
},
  "geometry": {"coordinates":[-0.3138380051,51.4161682129],"type":"Point"}
}