{
  "type": "Feature",
  "properties": {
    "addr:full":"207 Barkby Road Leicester Leicestershire LE4 9HZ",
    "addr:housenumber":"207",
    "addr:postcode":"le4 9hz",
    "addr:street":"Barkby Road",
    "iso:country":"GB",
    "sg:address":"207 Barkby Road",
    "sg:city":"Leicester",
    "sg:classifiers":[
        {
            "category":"Real Estate",
            "subcategory":"Developer",
            "type":"Services"
        }
    ],
    "sg:phone":"+44 116 276 7554",
    "sg:postcode":"LE4 9HZ",
    "sg:province":"Leicestershire",
    "sg:tags":[
        "property"
    ],
    "wof:name":"Sherriff Properties Ltd.",
    "wof:placetype":"venue"
},
  "geometry": {"coordinates":[-1.089040041,52.6615562439],"type":"Point"}
}