{
  "type": "Feature",
  "properties": {
    "iso:country":"GB",
    "sg:address":"40 Lee Grn",
    "sg:city":"Mirfield",
    "sg:classifiers":[
        {
            "category":"Military Area",
            "subcategory":"Air Force Base",
            "type":"Public Place"
        }
    ],
    "sg:postcode":"WF14 0AD",
    "sg:province":"West Yorkshire",
    "sg:tags":[
        "water",
        "treatment"
    ],
    "wof:name":"Mirfield Filter Co.",
    "wof:placetype":"venue"
},
  "geometry": {"coordinates":[-1.693207,53.684628],"type":"Point"}
}