{
  "type": "Feature",
  "properties": {
    "addr:full":"Murray Road Chertsey Surrey KT16 0HT",
    "addr:postcode":"kt16 0ht",
    "addr:street":"Murray Road",
    "iso:country":"GB",
    "sg:address":"Murray Road",
    "sg:city":"Chertsey",
    "sg:classifiers":[
        {
            "category":"Home & Garden",
            "subcategory":"Garden Supply",
            "type":"Retail Goods"
        }
    ],
    "sg:phone":"+44 1932 874875",
    "sg:postcode":"KT16 0HT",
    "sg:province":"Surrey",
    "sg:tags":[
        "nursery",
        "centre"
    ],
    "wof:name":"The Otter Plant Center",
    "wof:placetype":"venue"
},
  "geometry": {"coordinates":[-0.5284789801,51.3656463623],"type":"Point"}
}