{
  "type": "Feature",
  "properties": {
    "addr:full":"12 Otter Reach, Newton Poppleford Sidmouth Devon EX10 0ST",
    "addr:housenumber":"12",
    "addr:postcode":"ex10 0st",
    "addr:street":"Otter Reach",
    "iso:country":"GB",
    "sg:address":"12 Otter Reach, Newton Poppleford",
    "sg:city":"Sidmouth",
    "sg:classifiers":[
        {
            "category":"Social Services",
            "subcategory":"Job Training",
            "type":"Services"
        }
    ],
    "sg:postcode":"EX10 0ST",
    "sg:province":"Devon",
    "sg:tags":[
        "translator",
        "interpreter"
    ],
    "wof:name":"Warner Translations",
    "wof:placetype":"venue"
},
  "geometry": {"coordinates":[-3.2844719887,50.7222633362],"type":"Point"}
}