{
  "type": "Feature",
  "properties": {
    "iso:country":"GB",
    "sg:address":"3 Vicarage Hill, Flitwick",
    "sg:city":"Bedford",
    "sg:classifiers":[
        {
            "category":"Building & Trades",
            "subcategory":"Construction",
            "type":"Services"
        }
    ],
    "sg:postcode":"MK45 1HZ",
    "sg:province":"Bedfordshire",
    "sg:tags":[
        "window",
        "replacement"
    ],
    "wof:name":"Flitwick Glass",
    "wof:placetype":"venue"
},
  "geometry": {"coordinates":[-0.496317,51.997883],"type":"Point"}
}