{
  "type": "Feature",
  "properties": {
    "addr:full":"Unit 6, 233 Handsworth Road Sheffield South Yorkshire S13 9BL",
    "addr:housenumber":"unit 6",
    "addr:postcode":"233;s13 9bl",
    "addr:street":"Handsworth Road",
    "iso:country":"GB",
    "sg:address":"Unit 6, 233 Handsworth Road",
    "sg:city":"Sheffield",
    "sg:classifiers":[
        {
            "category":"Manufacturing",
            "subcategory":"Tools & Machinery",
            "type":"Manufacturing & Wholesale Goods"
        },
        {
            "category":"Wholesale",
            "subcategory":"Vending Machines",
            "type":"Manufacturing & Wholesale Goods"
        }
    ],
    "sg:phone":"+44 114 244 2907",
    "sg:postcode":"S13 9BL",
    "sg:province":"South Yorkshire",
    "sg:tags":[
        "design",
        "maker",
        "manufacturer"
    ],
    "wof:name":"G & J Cutting Tools",
    "wof:placetype":"venue"
},
  "geometry": {"coordinates":[-1.391479,53.374401],"type":"Point"}
}