{
  "type": "Feature",
  "properties": {
    "iso:country":"GB",
    "sg:address":"128 Silverwood House, Elsworth Close",
    "sg:city":"Doncaster",
    "sg:classifiers":[
        {
            "category":"Bus Charters",
            "type":"Transportation"
        }
    ],
    "sg:postcode":"DN1 3RW",
    "sg:province":"South Yorkshire",
    "sg:tags":[
        "mini",
        "hire",
        "leasing"
    ],
    "wof:name":"Silverwood Travel",
    "wof:placetype":"venue"
},
  "geometry": {"coordinates":[-1.1367880106,53.5154190063],"type":"Point"}
}