{
  "type": "Feature",
  "properties": {
    "iso:country":"GB",
    "sg:address":"2 Martins Building, Highfield Street",
    "sg:city":"Market Harborough",
    "sg:classifiers":[
        {
            "category":"Shopping",
            "subcategory":"Clothing, Apparel, & Fashions",
            "type":"Retail Goods"
        }
    ],
    "sg:phone":"+44 1858 431590",
    "sg:postcode":"LE16 9AN",
    "sg:province":"Leicestershire",
    "sg:tags":[
        "mnfr",
        "staff",
        "wear",
        "uniform"
    ],
    "wof:name":"J W Knitwear Ltd.",
    "wof:placetype":"venue"
},
  "geometry": {"coordinates":[-0.922579,52.479397],"type":"Point"}
}