{
  "type": "Feature",
  "properties": {
    "addr:full":"246 Woodway La Coventry Warwickshire CV2 2HX",
    "addr:housenumber":"246",
    "addr:postcode":"cv2 2hx",
    "addr:street":"Woodway La",
    "iso:country":"GB",
    "sg:address":"246 Woodway La",
    "sg:city":"Coventry",
    "sg:classifiers":[
        {
            "category":"Building & Trades",
            "subcategory":"Construction",
            "type":"Services"
        }
    ],
    "sg:phone":"+44 24 7661 9067",
    "sg:postcode":"CV2 2HX",
    "sg:province":"Warwickshire",
    "sg:tags":[
        "builder"
    ],
    "wof:name":"Advance Construction",
    "wof:placetype":"venue"
},
  "geometry": {"coordinates":[-1.4475929737,52.4300613403],"type":"Point"}
}