{
  "type": "Feature",
  "properties": {
    "iso:country":"GB",
    "sg:address":"3 Longfield, Starcross",
    "sg:city":"Exeter",
    "sg:classifiers":[
        {
            "category":"Professional",
            "subcategory":"Printing & Photocopies",
            "type":"Services"
        }
    ],
    "sg:phone":"+44 1626 890822",
    "sg:postcode":"EX6 8PW",
    "sg:province":"Devon",
    "sg:tags":[
        "printer"
    ],
    "wof:name":"Clerical Supplies",
    "wof:placetype":"venue"
},
  "geometry": {"coordinates":[-3.450759,50.629135],"type":"Point"}
}