{
  "type": "Feature",
  "properties": {
    "iso:country":"GB",
    "sg:address":"18 Manor Square",
    "sg:city":"Otley",
    "sg:classifiers":[
        {
            "category":"Real Estate",
            "subcategory":"Surveying",
            "type":"Services"
        }
    ],
    "sg:phone":"+44 1943 468068",
    "sg:postcode":"LS21 3AY",
    "sg:province":"North Yorkshire",
    "sg:tags":[
        "surveyor",
        "quantity"
    ],
    "wof:name":"Banks Smith Partnership",
    "wof:placetype":"venue"
},
  "geometry": {"coordinates":[-1.6949039698,53.9064712524],"type":"Point"}
}