{
  "type": "Feature",
  "properties": {
    "addr:full":"67 Rances Lane Wokingham Berkshire RG40 2LQ",
    "addr:housenumber":"67",
    "addr:postcode":"rg40 2lq",
    "addr:street":"Rances Lane",
    "iso:country":"GB",
    "sg:address":"67 Rances Lane",
    "sg:city":"Wokingham",
    "sg:classifiers":[
        {
            "category":"Personal",
            "subcategory":"Beauty Salon",
            "type":"Services"
        }
    ],
    "sg:phone":"+44 118 978 2249",
    "sg:postcode":"RG40 2LQ",
    "sg:province":"Berkshire",
    "sg:tags":[
        "unisex",
        "hairdresser"
    ],
    "wof:name":"Elizabeth Hairstylists",
    "wof:placetype":"venue"
},
  "geometry": {"coordinates":[-0.8178079724,51.4068374634],"type":"Point"}
}