{
  "type": "Feature",
  "properties": {
    "iso:country":"GB",
    "sg:address":"87 Junction Lane",
    "sg:city":"St Helens",
    "sg:classifiers":[
        {
            "category":"Professional",
            "type":"Services"
        }
    ],
    "sg:phone":"+44 1744 814316",
    "sg:postcode":"WA9 3JN",
    "sg:province":"Cheshire",
    "sg:tags":[
        "caterer"
    ],
    "wof:name":"Winstanleys",
    "wof:placetype":"venue"
},
  "geometry": {"coordinates":[-2.700481,53.434875],"type":"Point"}
}