{
  "type": "Feature",
  "properties": {
    "iso:country":"GB",
    "sg:address":"Carneddi",
    "sg:city":"Bangor",
    "sg:classifiers":[
        {
            "category":"Bars & Pubs",
            "type":"Food & Drink"
        }
    ],
    "sg:phone":"+44 1248 600015",
    "sg:postcode":"LL57 3RU",
    "sg:province":"Gwynedd",
    "sg:tags":[
        "pubs",
        "inn"
    ],
    "wof:name":"The George Inn",
    "wof:placetype":"venue"
},
  "geometry": {"coordinates":[-4.059134,53.1847],"type":"Point"}
}