{
  "type": "Feature",
  "properties": {
    "addr:full":"Springhead Mills, Oakworth Keighley North Yorkshire BD22 7RX",
    "addr:postcode":"bd22 7rx",
    "addr:street":"Springhead Mills",
    "iso:country":"GB",
    "sg:address":"Springhead Mills, Oakworth",
    "sg:city":"Keighley",
    "sg:classifiers":[
        {
            "category":"Manufacturing",
            "subcategory":"Textiles",
            "type":"Manufacturing & Wholesale Goods"
        }
    ],
    "sg:postcode":"BD22 7RX",
    "sg:province":"North Yorkshire",
    "sg:tags":[
        "knitwear"
    ],
    "wof:name":"Oakvale Fibres Ltd.",
    "wof:placetype":"venue"
},
  "geometry": {"coordinates":[-1.9477740526,53.8459472656],"type":"Point"}
}