{
  "type": "Feature",
  "properties": {
    "addr:full":"Unit 4 Greenway, Bedwas House Industrial Estate, Bedwas Caerphilly Caerphilly CF83 8DW",
    "addr:housenumber":"unit 4",
    "addr:postcode":"cf83 8dw",
    "addr:street":"Greenway;Industrial Estate",
    "iso:country":"GB",
    "sg:address":"Unit 4 Greenway, Bedwas House Industrial Estate, Bedwas",
    "sg:city":"Caerphilly",
    "sg:classifiers":[
        {
            "category":"Shopping",
            "subcategory":"Stationery & Office Supplies",
            "type":"Retail Goods"
        },
        {
            "category":"Professional",
            "subcategory":"Printing & Photocopies",
            "type":"Services"
        }
    ],
    "sg:phone":"+44 29 2086 0899",
    "sg:postcode":"CF83 8DW",
    "sg:province":"Caerphilly",
    "sg:tags":[
        "tag",
        "computer",
        "manufacturer",
        "label"
    ],
    "wof:name":"C P S",
    "wof:placetype":"venue"
},
  "geometry": {"coordinates":[-3.1898341179,51.5904693604],"type":"Point"}
}