{
  "type": "Feature",
  "properties": {
    "addr:full":"39 Highfield Drive Matlock Derbyshire DE4 3FZ",
    "addr:housenumber":"39",
    "addr:postcode":"de4 3fz",
    "addr:street":"Highfield Drive",
    "iso:country":"GB",
    "sg:address":"39 Highfield Drive",
    "sg:city":"Matlock",
    "sg:classifiers":[
        {
            "category":"Wholesale",
            "subcategory":"Electrical",
            "type":"Manufacturing & Wholesale Goods"
        }
    ],
    "sg:phone":"+44 1629 55772",
    "sg:postcode":"DE4 3FZ",
    "sg:province":"Derbyshire",
    "sg:tags":[
        "equipment",
        "refrigeration"
    ],
    "wof:name":"Wrights Refrigeration Engineering",
    "wof:placetype":"venue"
},
  "geometry": {"coordinates":[-1.5381640196,53.1450042725],"type":"Point"}
}