{
  "type": "Feature",
  "properties": {
    "addr:full":"Braeside, New Galloway Castle Douglas Dumfries and Galloway DG7 3RU",
    "addr:postcode":"dg7 3ru",
    "iso:country":"GB",
    "sg:address":"Braeside, New Galloway",
    "sg:city":"Castle Douglas",
    "sg:classifiers":[
        {
            "category":"Education",
            "subcategory":"School",
            "type":"Public Place"
        }
    ],
    "sg:phone":"+44 1644 420340",
    "sg:postcode":"DG7 3RU",
    "sg:province":"Dumfries and Galloway",
    "sg:tags":[
        "local",
        "authority"
    ],
    "wof:name":"Kells New Primary School",
    "wof:placetype":"venue"
},
  "geometry": {"coordinates":[-4.141488,55.07592],"type":"Point"}
}