{
  "type": "Feature",
  "properties": {
    "addr:full":"6 River Court, Chartham Canterbury Kent CT4 7JN",
    "addr:housenumber":"6",
    "addr:postcode":"ct4 7jn",
    "addr:street":"River Court",
    "iso:country":"GB",
    "sg:address":"6 River Court, Chartham",
    "sg:city":"Canterbury",
    "sg:classifiers":[
        {
            "category":"Education",
            "subcategory":"Special Training",
            "type":"Public Place"
        }
    ],
    "sg:postcode":"CT4 7JN",
    "sg:province":"Kent",
    "sg:tags":[
        "school",
        "language"
    ],
    "wof:name":"Rivercourt School of Languages",
    "wof:placetype":"venue"
},
  "geometry": {"coordinates":[1.017215,51.255524],"type":"Point"}
}