{
  "type": "Feature",
  "properties": {
    "iso:country":"GB",
    "sg:address":"Chessingham Park, Common Road, Dunnington",
    "sg:city":"York",
    "sg:classifiers":[
        {
            "category":"Wholesale",
            "subcategory":"Medical Equipment & Supplies",
            "type":"Manufacturing & Wholesale Goods"
        },
        {
            "category":"Retail",
            "subcategory":"Veterinary Services",
            "type":"Services"
        }
    ],
    "sg:phone":"+44 1904 489334",
    "sg:postcode":"YO19 5SE",
    "sg:province":"North Yorkshire",
    "sg:tags":[
        "manufacture",
        "laboratory",
        "pharmacy"
    ],
    "wof:name":"Trio Diagnostics Ltd.",
    "wof:placetype":"venue"
},
  "geometry": {"coordinates":[-0.9734489918,53.9576416016],"type":"Point"}
}