{
  "type": "Feature",
  "properties": {
    "iso:country":"GB",
    "sg:address":"Springvale Works, Shawclough Road",
    "sg:city":"Rossendale",
    "sg:classifiers":[
        {
            "category":"Manufacturing",
            "subcategory":"Textiles",
            "type":"Manufacturing & Wholesale Goods"
        }
    ],
    "sg:phone":"+44 1706 227549",
    "sg:postcode":"BB4 9JZ",
    "sg:province":"Lancashire",
    "sg:tags":[
        "dyer"
    ],
    "wof:name":"Campbell Hayward Ltd.",
    "wof:placetype":"venue"
},
  "geometry": {"coordinates":[-2.274823904,53.7089614868],"type":"Point"}
}