{
  "type": "Feature",
  "properties": {
    "iso:country":"GB",
    "sg:address":"Tees Bay Retail Park, Brenda Road",
    "sg:city":"Hartlepool",
    "sg:classifiers":[
        {
            "category":"Shopping",
            "type":"Retail Goods"
        }
    ],
    "sg:phone":"+44 1429 861528",
    "sg:postcode":"TS25 1XJ",
    "sg:province":"Durham",
    "sg:tags":[
        "part",
        "accessory"
    ],
    "wof:name":"Halfords Superstore",
    "wof:placetype":"venue"
},
  "geometry": {"coordinates":[-1.209073,54.6679],"type":"Point"}
}