{
  "type": "Feature",
  "properties": {
    "addr:full":"Flat 3 Ingram House, 227 Ingram Street Glasgow Glasgow City G1 1DA",
    "addr:housenumber":"227",
    "addr:postcode":"g1 1da",
    "addr:street":"Ingram Street",
    "iso:country":"GB",
    "sg:address":"Flat 3 Ingram House, 227 Ingram Street",
    "sg:city":"Glasgow",
    "sg:classifiers":[
        {
            "category":"Retail",
            "subcategory":"Event Space",
            "type":"Services"
        }
    ],
    "sg:phone":"+44 141 248 8060",
    "sg:postcode":"G1 1DA",
    "sg:province":"Glasgow City",
    "sg:tags":[
        "exhibition",
        "organiser"
    ],
    "wof:name":"Britannia Events Ltd.",
    "wof:placetype":"venue"
},
  "geometry": {"coordinates":[-4.2425107956,55.8578071594],"type":"Point"}
}