{
  "type": "Feature",
  "properties": {
    "addr:full":"8 Clifton Drive Blackpool Lancashire FY4 1NX",
    "addr:housenumber":"8",
    "addr:postcode":"fy4 1nx",
    "addr:street":"Clifton Drive",
    "iso:country":"GB",
    "sg:address":"8 Clifton Drive",
    "sg:city":"Blackpool",
    "sg:classifiers":[
        {
            "category":"Travel",
            "subcategory":"Hotels & Motels",
            "type":"Entertainment"
        }
    ],
    "sg:phone":"+44 1253 345283",
    "sg:postcode":"FY4 1NX",
    "sg:province":"Lancashire",
    "wof:name":"Hotel Sinatra",
    "wof:placetype":"venue"
},
  "geometry": {"coordinates":[-3.0564858913,53.787273407],"type":"Point"}
}