{
  "type": "Feature",
  "properties": {
    "addr:full":"135 Seymours Harlow Essex CM19 5NH",
    "addr:housenumber":"135",
    "addr:postcode":"cm19 5nh",
    "addr:street":"Seymours",
    "iso:country":"GB",
    "sg:address":"135 Seymours",
    "sg:city":"Harlow",
    "sg:classifiers":[
        {
            "category":"Building & Trades",
            "subcategory":"Landscaping Services",
            "type":"Services"
        }
    ],
    "sg:postcode":"CM19 5NH",
    "sg:province":"Essex",
    "sg:tags":[
        "gardening"
    ],
    "wof:name":"Lambert,Alan,Garden Services",
    "wof:placetype":"venue"
},
  "geometry": {"coordinates":[0.069731,51.755665],"type":"Point"}
}