{
  "type": "Feature",
  "properties": {
    "addr:full":"Unit 22/23 Calder Workshops, Gibbet Street Halifax West Yorkshire HX1 4JQ",
    "addr:housenumber":"unit 22 / 23",
    "addr:postcode":"hx1 4jq",
    "addr:street":"Gibbet Street",
    "iso:country":"GB",
    "sg:address":"Unit 22/23 Calder Workshops, Gibbet Street",
    "sg:city":"Halifax",
    "sg:classifiers":[
        {
            "category":"Manufacturing",
            "subcategory":"Metals",
            "type":"Manufacturing & Wholesale Goods"
        },
        {
            "category":"Professional",
            "type":"Services"
        }
    ],
    "sg:phone":"+44 1422 345404",
    "sg:postcode":"HX1 4JQ",
    "sg:province":"West Yorkshire",
    "sg:tags":[
        "polishing",
        "finishing"
    ],
    "wof:name":"Park Metal Polishing",
    "wof:placetype":"venue"
},
  "geometry": {"coordinates":[-1.862224,53.721233],"type":"Point"}
}