{
  "type": "Feature",
  "properties": {
    "addr:full":"Stamford Farm, Stamford Alnwick Northumberland NE66 3RY",
    "addr:postcode":"ne66 3ry",
    "iso:country":"GB",
    "sg:address":"Stamford Farm, Stamford",
    "sg:city":"Alnwick",
    "sg:classifiers":[
        {
            "category":"Farming",
            "subcategory":"Farm",
            "type":"Manufacturing & Wholesale Goods"
        }
    ],
    "sg:phone":"+44 1665 576253",
    "sg:postcode":"NE66 3RY",
    "sg:province":"Northumberland",
    "sg:tags":[
        "mixed",
        "crop"
    ],
    "wof:name":"G E Robertson & Co",
    "wof:placetype":"venue"
},
  "geometry": {"coordinates":[-1.645588994,55.4682998657],"type":"Point"}
}