{
  "type": "Feature",
  "properties": {
    "addr:full":"11 Fleetwood Way Watford Hertfordshire WD19 6NB",
    "addr:housenumber":"11",
    "addr:postcode":"wd19 6nb",
    "addr:street":"Fleetwood Way",
    "iso:country":"GB",
    "sg:address":"11 Fleetwood Way",
    "sg:city":"Watford",
    "sg:classifiers":[
        {
            "category":"Building & Trades",
            "subcategory":"Construction",
            "type":"Services"
        }
    ],
    "sg:phone":"+44 20 8421 0966",
    "sg:postcode":"WD19 6NB",
    "sg:province":"Hertfordshire",
    "sg:tags":[
        "decorator",
        "painter"
    ],
    "wof:name":"M T Sargant",
    "wof:placetype":"venue"
},
  "geometry": {"coordinates":[-0.394469,51.622261],"type":"Point"}
}