{
  "type": "Feature",
  "properties": {
    "addr:full":"Aboret Sevenoaks Kent TN15 9DD",
    "addr:postcode":"tn15 9dd",
    "addr:street":"Aboret",
    "iso:country":"GB",
    "sg:address":"Aboret",
    "sg:city":"Sevenoaks",
    "sg:classifiers":[
        {
            "category":"Social Services",
            "subcategory":"Child Care",
            "type":"Services"
        }
    ],
    "sg:phone":"+44 1732 887272",
    "sg:postcode":"TN15 9DD",
    "sg:province":"Kent",
    "sg:tags":[
        "agency",
        "nanny"
    ],
    "wof:name":"Alice Nannies Ltd.",
    "wof:placetype":"venue"
},
  "geometry": {"coordinates":[0.2813200057,51.2855415344],"type":"Point"}
}