{
  "type": "Feature",
  "properties": {
    "iso:country":"GB",
    "sg:address":"88 West Borough",
    "sg:city":"Wimborne",
    "sg:classifiers":[
        {
            "category":"Autos & Motor Vehicles",
            "subcategory":"Auto Supplies",
            "type":"Retail Goods"
        },
        {
            "category":"Shopping",
            "type":"Retail Goods"
        }
    ],
    "sg:phone":"+44 1202 884517",
    "sg:postcode":"BH21 1NH",
    "sg:province":"Dorset",
    "sg:tags":[
        "car",
        "part",
        "accessory"
    ],
    "sg:website":"http://www.phoenix-auto.fsnet.co.uk",
    "wof:name":"Phoenix Auto Spares",
    "wof:placetype":"venue"
},
  "geometry": {"coordinates":[-1.988738,50.803459],"type":"Point"}
}