{
  "type": "Feature",
  "properties": {
    "addr:full":"Dimlands Farm Riding School, Dimlands Road Llantwit Major The Vale of Glamorgan CF61 1YX",
    "addr:postcode":"cf61 1yx",
    "addr:street":"Dimlands Road;Vale",
    "iso:country":"GB",
    "sg:address":"Dimlands Farm Riding School, Dimlands Road",
    "sg:city":"Llantwit Major",
    "sg:classifiers":[
        {
            "category":"Sports & Exercise",
            "subcategory":"Stables",
            "type":"Entertainment"
        }
    ],
    "sg:phone":"+44 1446 794943",
    "sg:postcode":"CF61 1YX",
    "sg:province":"The Vale of Glamorgan",
    "sg:tags":[
        "equestrian",
        "centre",
        "livery",
        "schools",
        "riding",
        "education"
    ],
    "wof:name":"Dimlands Farm Riding School",
    "wof:placetype":"venue"
},
  "geometry": {"coordinates":[-3.492221117,51.4084892273],"type":"Point"}
}