{
  "type": "Feature",
  "properties": {
    "addr:full":"73 Earls Road Nuneaton Leicestershire CV11 5HS",
    "addr:housenumber":"73",
    "addr:postcode":"cv11 5hs",
    "addr:street":"Earls Road",
    "iso:country":"GB",
    "sg:address":"73 Earls Road",
    "sg:city":"Nuneaton",
    "sg:classifiers":[
        {
            "category":"Shopping",
            "subcategory":"Gifts & Souvenirs",
            "type":"Retail Goods"
        }
    ],
    "sg:phone":"+44 24 7635 3505",
    "sg:postcode":"CV11 5HS",
    "sg:province":"Leicestershire",
    "sg:tags":[
        "watch",
        "clock"
    ],
    "wof:name":"Ruskin Clocks & Mirrors",
    "wof:placetype":"venue"
},
  "geometry": {"coordinates":[-1.4809700251,52.5268554688],"type":"Point"}
}