{
  "type": "Feature",
  "properties": {
    "iso:country":"GB",
    "sg:address":"High Street, Stoney Middleton",
    "sg:city":"Hope Valley",
    "sg:classifiers":[
        {
            "category":"Farming",
            "subcategory":"Fish & Marine Products",
            "type":"Manufacturing & Wholesale Goods"
        }
    ],
    "sg:phone":"+44 1433 630571",
    "sg:postcode":"S32 4TL",
    "sg:province":"Derbyshire",
    "sg:tags":[
        "fishmonger"
    ],
    "wof:name":"L W Hancock & Son",
    "wof:placetype":"venue"
},
  "geometry": {"coordinates":[-1.6558820009,53.2752571106],"type":"Point"}
}