{
  "type": "Feature",
  "properties": {
    "iso:country":"GB",
    "sg:address":"27-29 Clarendon Avenue",
    "sg:city":"Leamington Spa",
    "sg:classifiers":[
        {
            "category":"Home & Garden",
            "subcategory":"Kitchen Supply",
            "type":"Retail Goods"
        }
    ],
    "sg:phone":"+44 1926 887476",
    "sg:postcode":"CV32 4SG",
    "sg:province":"Warwickshire",
    "sg:tags":[
        "equipment",
        "catering"
    ],
    "wof:name":"Crown Services",
    "wof:placetype":"venue"
},
  "geometry": {"coordinates":[-1.5331510305,52.2938461304],"type":"Point"}
}