{
  "type": "Feature",
  "properties": {
    "addr:full":"5-7 Ailsa Road, Irvine Industrial Estate Irvine North Ayrshire KA12 8LL",
    "addr:housenumber":"5-7",
    "addr:postcode":"ka12 8ll",
    "addr:street":"Ailsa Road;Industrial Estate",
    "iso:country":"GB",
    "sg:address":"5-7 Ailsa Road, Irvine Industrial Estate",
    "sg:city":"Irvine",
    "sg:classifiers":[
        {
            "category":"Wholesale",
            "subcategory":"Non-durable Goods",
            "type":"Manufacturing & Wholesale Goods"
        },
        {
            "category":"Wholesale",
            "subcategory":"Fruits & Vegetables",
            "type":"Manufacturing & Wholesale Goods"
        }
    ],
    "sg:phone":"+44 1294 279404",
    "sg:postcode":"KA12 8LL",
    "sg:province":"North Ayrshire",
    "sg:tags":[
        "carry",
        "cash"
    ],
    "wof:name":"Hugh McLellan",
    "wof:placetype":"venue"
},
  "geometry": {"coordinates":[-4.673879,55.600655],"type":"Point"}
}