{
  "type": "Feature",
  "properties": {
    "iso:country":"GB",
    "sg:address":"Bridge House",
    "sg:city":"Sheffield",
    "sg:classifiers":[
        {
            "category":"Fast Food",
            "type":"Food & Drink"
        }
    ],
    "sg:phone":"+44 114 276 6144",
    "sg:postcode":"S3 8NS",
    "sg:province":"South Yorkshire",
    "sg:tags":[
        "away",
        "take"
    ],
    "wof:name":"M A S Holdings Ltd.",
    "wof:placetype":"venue"
},
  "geometry": {"coordinates":[-1.467522,53.386761],"type":"Point"}
}