{
  "type": "Feature",
  "properties": {
    "addr:full":"Gracious Farm, High Street, Southill Biggleswade Bedfordshire SG18 9JB",
    "addr:postcode":"sg18 9jb",
    "addr:street":"High Street",
    "iso:country":"GB",
    "sg:address":"Gracious Farm, High Street, Southill",
    "sg:city":"Biggleswade",
    "sg:classifiers":[
        {
            "category":"Farming",
            "subcategory":"Livestock Farm",
            "type":"Manufacturing & Wholesale Goods"
        }
    ],
    "sg:postcode":"SG18 9JB",
    "sg:province":"Bedfordshire",
    "sg:tags":[
        "others"
    ],
    "wof:name":"N N Capon",
    "wof:placetype":"venue"
},
  "geometry": {"coordinates":[-0.324514,52.063904],"type":"Point"}
}