{
  "type": "Feature",
  "properties": {
    "iso:country":"GB",
    "sg:address":"176 Chorley Old Road",
    "sg:city":"Bolton",
    "sg:classifiers":[
        {
            "category":"Health Services",
            "subcategory":"Dentist",
            "type":"Services"
        }
    ],
    "sg:phone":"+44 1204 843891",
    "sg:postcode":"BL1 3BA",
    "sg:province":"Lancashire",
    "wof:name":"H R M Beattie",
    "wof:placetype":"venue"
},
  "geometry": {"coordinates":[-2.447764,53.584957],"type":"Point"}
}