{
  "type": "Feature",
  "properties": {
    "addr:full":"Sunrise Enterprise Park Sunderland Tyne and Wear SR5 3RX",
    "addr:postcode":"sr5 3rx",
    "iso:country":"GB",
    "sg:address":"Sunrise Enterprise Park",
    "sg:city":"Sunderland",
    "sg:classifiers":[
        {
            "category":"Professional",
            "subcategory":"Advertising",
            "type":"Services"
        }
    ],
    "sg:phone":"+44 191 514 3388",
    "sg:postcode":"SR5 3RX",
    "sg:province":"Tyne and Wear",
    "sg:tags":[
        "mail",
        "direct"
    ],
    "wof:name":"Reed Print Direct Mail Ltd.",
    "wof:placetype":"venue"
},
  "geometry": {"coordinates":[-1.4392080307,54.9139518738],"type":"Point"}
}