{
  "type": "Feature",
  "properties": {
    "iso:country":"GB",
    "sg:address":"99 Langley Place, Langley Road",
    "sg:city":"Watford",
    "sg:classifiers":[
        {
            "category":"Insurance",
            "subcategory":"Life Insurance",
            "type":"Services"
        }
    ],
    "sg:phone":"+44 1923 218280",
    "sg:postcode":"WD17 4BB",
    "sg:province":"Hertfordshire",
    "sg:tags":[
        "assurance"
    ],
    "wof:name":"Sun Life Group",
    "wof:placetype":"venue"
},
  "geometry": {"coordinates":[-0.4073530138,51.6679344177],"type":"Point"}
}