{
  "type": "Feature",
  "properties": {
    "addr:full":"161 Councillor Lane Cheadle Cheshire SK8 2JE",
    "addr:housenumber":"161",
    "addr:postcode":"sk8 2je",
    "addr:street":"Councillor Lane Cheadle",
    "iso:country":"GB",
    "sg:address":"161 Councillor Lane",
    "sg:city":"Cheadle",
    "sg:classifiers":[
        {
            "category":"Wholesale",
            "subcategory":"Sporting Goods",
            "type":"Manufacturing & Wholesale Goods"
        }
    ],
    "sg:postcode":"SK8 2JE",
    "sg:province":"Cheshire",
    "sg:tags":[
        "mnfr",
        "sport",
        "equipment"
    ],
    "wof:name":"The Golf Oasis",
    "wof:placetype":"venue"
},
  "geometry": {"coordinates":[-2.1940689087,53.3909072876],"type":"Point"}
}