{
  "type": "Feature",
  "properties": {
    "addr:full":"Oxford Arc Cardiff Cardiff CF1 2DT",
    "addr:postcode":"cf1 2dt",
    "iso:country":"GB",
    "sg:address":"Oxford Arc",
    "sg:city":"Cardiff",
    "sg:classifiers":[
        {
            "category":"Personal",
            "subcategory":"Beauty Salon",
            "type":"Services"
        }
    ],
    "sg:phone":"+44 29 2023 8474",
    "sg:postcode":"CF1 2DT",
    "sg:province":"Cardiff",
    "sg:tags":[
        "unisex",
        "hairdresser"
    ],
    "wof:name":"Hair Parade",
    "wof:placetype":"venue"
},
  "geometry": {"coordinates":[-3.164674,51.485809],"type":"Point"}
}