{
  "type": "Feature",
  "properties": {
    "iso:country":"GB",
    "sg:address":"33 Carlton Terr",
    "sg:city":"Brighton",
    "sg:classifiers":[
        {
            "category":"Retail",
            "subcategory":"Driving School",
            "type":"Services"
        }
    ],
    "sg:phone":"+44 1273 412777",
    "sg:postcode":"BN41 1XF",
    "sg:province":"East Sussex",
    "wof:name":"Southern Driving Centre",
    "wof:placetype":"venue"
},
  "geometry": {"coordinates":[-0.204638,50.83786],"type":"Point"}
}