{
  "type": "Feature",
  "properties": {
    "addr:full":"5a-5b King Street, Houghton Regis Dunstable Bedfordshire LU5 5DS",
    "addr:housenumber":"5a-5b",
    "addr:postcode":"lu5 5ds",
    "addr:street":"King Street",
    "iso:country":"GB",
    "sg:address":"5a-5b King Street, Houghton Regis",
    "sg:city":"Dunstable",
    "sg:classifiers":[
        {
            "category":"Shopping",
            "subcategory":"Computers & Home Electronics",
            "type":"Retail Goods"
        }
    ],
    "sg:postcode":"LU5 5DS",
    "sg:province":"Bedfordshire",
    "sg:tags":[
        "electrical"
    ],
    "wof:name":"M L Accessories Ltd.",
    "wof:placetype":"venue"
},
  "geometry": {"coordinates":[-0.5206689835,51.9034461975],"type":"Point"}
}