{
  "type": "Feature",
  "properties": {
    "addr:full":"30 Harcourt St West End Greater London W1H 2AA",
    "addr:housenumber":"30",
    "addr:postcode":"w1h 2aa",
    "addr:street":"Harcourt St",
    "iso:country":"GB",
    "sg:address":"30 Harcourt St",
    "sg:city":"West End",
    "sg:classifiers":[
        {
            "category":"Organizations",
            "subcategory":"Community Association",
            "type":"Services"
        }
    ],
    "sg:phone":"+44 20 7724 2399",
    "sg:postcode":"W1H 2AA",
    "sg:province":"Greater London",
    "sg:tags":[
        "relation",
        "public"
    ],
    "wof:name":"Creative Umbrella The",
    "wof:placetype":"venue"
},
  "geometry": {"coordinates":[-0.1607300043,51.5179901123],"type":"Point"}
}