{
  "type": "Feature",
  "properties": {
    "addr:full":"Lynton, 11 Mill Rd, Emneth Wisbech Cambridgeshire PE14 8AE",
    "addr:housenumber":"11",
    "addr:postcode":"pe14 8ae",
    "addr:street":"Mill Rd",
    "iso:country":"GB",
    "sg:address":"Lynton, 11 Mill Rd, Emneth",
    "sg:city":"Wisbech",
    "sg:classifiers":[
        {
            "category":"Professional",
            "subcategory":"Computer Services",
            "type":"Services"
        }
    ],
    "sg:phone":"+44 1945 463282",
    "sg:postcode":"PE14 8AE",
    "sg:province":"Cambridgeshire",
    "sg:tags":[
        "system",
        "software"
    ],
    "wof:name":"Horseshoe Enterprises Ltd",
    "wof:placetype":"venue"
},
  "geometry": {"coordinates":[0.2074050009,52.6427574158],"type":"Point"}
}