{
  "type": "Feature",
  "properties": {
    "addr:full":"Foleshill Road Coventry West Midlands CV1 4NR",
    "addr:postcode":"cv1 4nr",
    "addr:street":"Foleshill Road",
    "iso:country":"GB",
    "sg:address":"Foleshill Road",
    "sg:city":"Coventry",
    "sg:classifiers":[
        {
            "category":"Building & Trades",
            "subcategory":"Construction",
            "type":"Services"
        },
        {
            "category":"Shopping",
            "subcategory":"Computers & Home Electronics",
            "type":"Retail Goods"
        }
    ],
    "sg:phone":"+44 24 7622 7641",
    "sg:postcode":"CV1 4NR",
    "sg:province":"West Midlands",
    "sg:tags":[
        "joinery",
        "improvement"
    ],
    "sg:website":"http://www.magnet.co.uk",
    "wof:name":"Magnet Ltd.",
    "wof:placetype":"venue"
},
  "geometry": {"coordinates":[-1.506884,52.419605],"type":"Point"}
}