{
  "type": "Feature",
  "properties": {
    "iso:country":"GB",
    "sg:address":"1 Windmill Street",
    "sg:city":"Tunbridge Wells",
    "sg:classifiers":[
        {
            "category":"Shopping",
            "subcategory":"Department Store",
            "type":"Retail Goods"
        },
        {
            "category":"Government",
            "subcategory":"Post Office",
            "type":"Public Place"
        }
    ],
    "sg:phone":"+44 1892 527012",
    "sg:postcode":"TN2 4UU",
    "sg:province":"East Sussex",
    "wof:name":"Post Office Counters Ltd.",
    "wof:placetype":"venue"
},
  "geometry": {"coordinates":[0.2749199867,51.130115509],"type":"Point"}
}