{
  "type": "Feature",
  "properties": {
    "addr:full":"24 Garbutt Street Shildon Durham DL4 1AR",
    "addr:housenumber":"24",
    "addr:postcode":"dl4 1ar",
    "addr:street":"Garbutt Street",
    "iso:country":"GB",
    "sg:address":"24 Garbutt Street",
    "sg:city":"Shildon",
    "sg:classifiers":[
        {
            "category":"Retail",
            "subcategory":"Auto Repair",
            "type":"Services"
        }
    ],
    "sg:phone":"+44 1388 774174",
    "sg:postcode":"DL4 1AR",
    "sg:province":"Durham",
    "sg:tags":[
        "modification",
        "garage",
        "upholsterer",
        "car"
    ],
    "wof:name":"John R Richardson",
    "wof:placetype":"venue"
},
  "geometry": {"coordinates":[-1.6541090012,54.6333503723],"type":"Point"}
}