{
  "type": "Feature",
  "properties": {
    "addr:full":"Main Road, Stainforth Settle North Yorkshire BD24 9PB",
    "addr:postcode":"bd24 9pb",
    "addr:street":"Main Road",
    "iso:country":"GB",
    "sg:address":"Main Road, Stainforth",
    "sg:city":"Settle",
    "sg:classifiers":[
        {
            "category":"Travel",
            "subcategory":"Hotels & Motels",
            "type":"Entertainment"
        }
    ],
    "sg:phone":"+44 1729 822599",
    "sg:postcode":"BD24 9PB",
    "sg:province":"North Yorkshire",
    "wof:name":"Craven Heifer",
    "wof:placetype":"venue"
},
  "geometry": {"coordinates":[-2.2776060104,54.0697593689],"type":"Point"}
}