{
  "type": "Feature",
  "properties": {
    "iso:country":"GB",
    "sg:address":"76a York Road",
    "sg:city":"Clacton-on-sea",
    "sg:classifiers":[
        {
            "category":"Restaurant",
            "type":"Food & Drink"
        }
    ],
    "sg:phone":"+44 1255 812655",
    "sg:postcode":"CO15 5NW",
    "sg:province":"Essex",
    "sg:tags":[
        "-",
        "english"
    ],
    "wof:name":"Two Trees Restaurant",
    "wof:placetype":"venue"
},
  "geometry": {"coordinates":[1.1893470287,51.8051567078],"type":"Point"}
}