{
  "type": "Feature",
  "properties": {
    "addr:full":"Redlands Farm, East Coker Yeovil Dorset BA22 9HF",
    "addr:postcode":"ba22 9hf",
    "addr:street":"Coker",
    "iso:country":"GB",
    "sg:address":"Redlands Farm, East Coker",
    "sg:city":"Yeovil",
    "sg:classifiers":[
        {
            "category":"Farming",
            "subcategory":"Livestock Farm",
            "type":"Manufacturing & Wholesale Goods"
        },
        {
            "category":"Farming",
            "subcategory":"Farm",
            "type":"Manufacturing & Wholesale Goods"
        }
    ],
    "sg:phone":"+44 1935 862137",
    "sg:postcode":"BA22 9HF",
    "sg:province":"Dorset",
    "sg:tags":[
        "mixed",
        "crop",
        "others"
    ],
    "wof:name":"S Dening & Sons",
    "wof:placetype":"venue"
},
  "geometry": {"coordinates":[-2.6617,50.91415],"type":"Point"}
}