{
  "type": "Feature",
  "properties": {
    "addr:full":"40 Town Centre Hatfield Hertfordshire AL10 0JH",
    "addr:housenumber":"40",
    "addr:postcode":"al10 0jh",
    "addr:street":"Town",
    "iso:country":"GB",
    "sg:address":"40 Town Centre",
    "sg:city":"Hatfield",
    "sg:classifiers":[
        {
            "category":"Travel",
            "subcategory":"Travel Agent",
            "type":"Entertainment"
        }
    ],
    "sg:phone":"+44 1707 267592",
    "sg:postcode":"AL10 0JH",
    "sg:province":"Hertfordshire",
    "sg:tags":[
        "agency",
        "activity"
    ],
    "wof:name":"WHITES TRAVEL BUREAU LTD",
    "wof:placetype":"venue"
},
  "geometry": {"coordinates":[-0.2261479944,51.7648200989],"type":"Point"}
}