{
  "type": "Feature",
  "properties": {
    "iso:country":"GB",
    "sg:address":"21 Princes Mews",
    "sg:city":"Bayswater",
    "sg:classifiers":[
        {
            "category":"Fast Food",
            "type":"Food & Drink"
        }
    ],
    "sg:phone":"+44 20 7243 4725",
    "sg:postcode":"W2 4NX",
    "sg:province":"Greater London",
    "sg:tags":[
        "away",
        "take"
    ],
    "wof:name":"Souperdouper Ltd",
    "wof:placetype":"venue"
},
  "geometry": {"coordinates":[-0.193129,51.512428],"type":"Point"}
}