{
  "type": "Feature",
  "properties": {
    "addr:full":"21 Princes Mews Bayswater Greater London W2 4NX",
    "addr:housenumber":"21",
    "addr:postcode":"w2 4nx",
    "addr:street":"Princes Mews",
    "iso:country":"GB",
    "sg:address":"21 Princes Mews",
    "sg:city":"Bayswater",
    "sg:classifiers":[
        {
            "category":"Fast Food",
            "type":"Food & Drink"
        }
    ],
    "sg:phone":"+44 20 7243 4725",
    "sg:postcode":"W2 4NX",
    "sg:province":"Greater London",
    "sg:tags":[
        "away",
        "take"
    ],
    "wof:name":"Souperdouper Ltd",
    "wof:placetype":"venue"
},
  "geometry": {"coordinates":[-0.193129,51.512428],"type":"Point"}
}