{
  "type": "Feature",
  "properties": {
    "addr:full":"The Glasson Centre, 319 Oxford Road Reading Berkshire RG30 1AU",
    "addr:housenumber":"319",
    "addr:postcode":"rg30 1au",
    "addr:street":"Oxford Road",
    "iso:country":"GB",
    "sg:address":"The Glasson Centre, 319 Oxford Road",
    "sg:city":"Reading",
    "sg:classifiers":[
        {
            "category":"Government",
            "subcategory":"Police Station",
            "type":"Public Place"
        }
    ],
    "sg:phone":"+44 118 956 6322",
    "sg:postcode":"RG30 1AU",
    "sg:province":"Berkshire",
    "sg:tags":[
        "support"
    ],
    "wof:name":"Family Courts Welfare Service",
    "wof:placetype":"venue"
},
  "geometry": {"coordinates":[-0.9916800261,51.4559288025],"type":"Point"}
}