{
  "type": "Feature",
  "properties": {
    "iso:country":"GB",
    "sg:address":"80 St. Pauls Av",
    "sg:city":"Barry",
    "sg:classifiers":[
        {
            "category":"Shopping",
            "subcategory":"Crafts & Fabrics",
            "type":"Retail Goods"
        },
        {
            "category":"Shopping",
            "subcategory":"Computers & Home Electronics",
            "type":"Retail Goods"
        }
    ],
    "sg:phone":"+44 1446 420336",
    "sg:postcode":"CF62 8HT",
    "sg:province":"The Vale of Glamorgan",
    "sg:tags":[
        "television",
        "sewing",
        "sale",
        "centre"
    ],
    "wof:name":"Barry Sewing Centre",
    "wof:placetype":"venue"
},
  "geometry": {"coordinates":[-3.2767438889,51.4036941528],"type":"Point"}
}