{
  "type": "Feature",
  "properties": {
    "addr:full":"Start Hill Bishops Stortford Essex CM22 7TA",
    "addr:postcode":"cm22 7ta",
    "iso:country":"GB",
    "sg:address":"Start Hill",
    "sg:city":"Bishops Stortford",
    "sg:classifiers":[
        {
            "category":"Autos & Motor Vehicles",
            "subcategory":"Fuel & Gas Station",
            "type":"Retail Goods"
        }
    ],
    "sg:phone":"+44 1279 503959",
    "sg:postcode":"CM22 7TA",
    "sg:province":"Essex",
    "sg:tags":[
        "hr",
        "petrol"
    ],
    "wof:name":"Start Hill Service Station",
    "wof:placetype":"venue"
},
  "geometry": {"coordinates":[0.20663,51.871262],"type":"Point"}
}