{
  "type": "Feature",
  "properties": {
    "addr:full":"Cathedral Street Glasgow Glasgow City G1 2TG",
    "addr:postcode":"g1 2tg",
    "addr:street":"Cathedral Street",
    "iso:country":"GB",
    "sg:address":"Cathedral Street",
    "sg:city":"Glasgow",
    "sg:classifiers":[
        {
            "category":"Education",
            "subcategory":"College",
            "type":"Public Place"
        },
        {
            "category":"Education",
            "subcategory":"Special Training",
            "type":"Public Place"
        }
    ],
    "sg:phone":"+44 141 552 3751",
    "sg:postcode":"G1 2TG",
    "sg:province":"Glasgow City",
    "sg:tags":[
        "technical",
        "agricultural",
        "product",
        "centre"
    ],
    "wof:name":"G C F T Business Enterprises Ltd.",
    "wof:placetype":"venue"
},
  "geometry": {"coordinates":[-4.2488489151,55.8631095886],"type":"Point"}
}