{
  "type": "Feature",
  "properties": {
    "iso:country":"GB",
    "sg:address":"73 Sleetmoor Lane, Somercotes",
    "sg:city":"Alfreton",
    "sg:classifiers":[
        {
            "category":"Bars & Pubs",
            "type":"Food & Drink"
        }
    ],
    "sg:phone":"+44 1773 602537",
    "sg:postcode":"DE55 1RE",
    "sg:province":"Derbyshire",
    "sg:tags":[
        "pubs",
        "inn"
    ],
    "wof:name":"The Crown Inn",
    "wof:placetype":"venue"
},
  "geometry": {"coordinates":[-1.376954,53.080765],"type":"Point"}
}