{
  "type": "Feature",
  "properties": {
    "addr:full":"3 Springfield Road, Guiseley Leeds West Yorkshire LS20 8AL",
    "addr:housenumber":"3",
    "addr:postcode":"ls20 8al",
    "addr:street":"Springfield Road",
    "iso:country":"GB",
    "sg:address":"3 Springfield Road, Guiseley",
    "sg:city":"Leeds",
    "sg:classifiers":[
        {
            "category":"Food & Beverages",
            "subcategory":"Meat & Fish",
            "type":"Retail Goods"
        }
    ],
    "sg:phone":"+44 1943 876118",
    "sg:postcode":"LS20 8AL",
    "sg:province":"West Yorkshire",
    "sg:tags":[
        "chip"
    ],
    "wof:name":"Springfield Fisheries",
    "wof:placetype":"venue"
},
  "geometry": {"coordinates":[-1.710901022,53.8738441467],"type":"Point"}
}