{
  "type": "Feature",
  "properties": {
    "addr:full":"Tan Office Farm, Tan Office La Bury St Edmunds Suffolk IP29 5QZ",
    "addr:postcode":"ip29 5qz",
    "addr:street":"La",
    "iso:country":"GB",
    "sg:address":"Tan Office Farm, Tan Office La",
    "sg:city":"Bury St Edmunds",
    "sg:classifiers":[
        {
            "category":"Transit Center",
            "subcategory":"Passenger",
            "type":"Transportation"
        }
    ],
    "sg:phone":"+44 1284 850316",
    "sg:postcode":"IP29 5QZ",
    "sg:province":"Suffolk",
    "sg:tags":[
        "boarding",
        "kennel",
        "catteries"
    ],
    "wof:name":"V Budnik",
    "wof:placetype":"venue"
},
  "geometry": {"coordinates":[0.6065,52.198971],"type":"Point"}
}