{
  "type": "Feature",
  "properties": {
    "addr:full":"The Paddocks, Ross Road Abergavenny Herefordshire NP7 8NF",
    "addr:postcode":"np7 8nf",
    "addr:street":"Ross Road",
    "iso:country":"GB",
    "sg:address":"The Paddocks, Ross Road",
    "sg:city":"Abergavenny",
    "sg:classifiers":[
        {
            "category":"Building & Trades",
            "subcategory":"Plumbing",
            "type":"Services"
        }
    ],
    "sg:phone":"+44 1873 855976",
    "sg:postcode":"NP7 8NF",
    "sg:province":"Herefordshire",
    "sg:tags":[
        "plumber",
        "heating"
    ],
    "wof:name":"Roger Williams",
    "wof:placetype":"venue"
},
  "geometry": {"coordinates":[-3.02068,51.825008],"type":"Point"}
}