{
  "type": "Feature",
  "properties": {
    "addr:full":"11 The Soke Alresford Hampshire SO24 9DB",
    "addr:housenumber":"11",
    "addr:postcode":"so24 9db",
    "addr:street":"The Soke",
    "iso:country":"GB",
    "sg:address":"11 The Soke",
    "sg:city":"Alresford",
    "sg:classifiers":[
        {
            "category":"Health Services",
            "subcategory":"Health Practitioner",
            "type":"Services"
        }
    ],
    "sg:phone":"+44 1962 732449",
    "sg:postcode":"SO24 9DB",
    "sg:province":"Hampshire",
    "sg:tags":[
        "hypnotherapists"
    ],
    "wof:name":"Mr N Vickers",
    "wof:placetype":"venue"
},
  "geometry": {"coordinates":[-1.161659,51.092587],"type":"Point"}
}