{
  "type": "Feature",
  "properties": {
    "addr:full":"355 Bury Old Road, Prestwich Manchester Greater Manchester M25 1PY",
    "addr:housenumber":"355",
    "addr:postcode":"m25 1py",
    "addr:street":"Bury Old Road",
    "iso:country":"GB",
    "sg:address":"355 Bury Old Road, Prestwich",
    "sg:city":"Manchester",
    "sg:classifiers":[
        {
            "category":"Professional",
            "subcategory":"Accounting & Tax Preparation",
            "type":"Services"
        }
    ],
    "sg:phone":"+44 161 798 8400",
    "sg:postcode":"M25 1PY",
    "sg:province":"Greater Manchester",
    "sg:tags":[
        "accountant"
    ],
    "wof:name":"Anthony Stuart Daulby",
    "wof:placetype":"venue"
},
  "geometry": {"coordinates":[-2.2691879272,53.5353507996],"type":"Point"}
}