{
  "type": "Feature",
  "properties": {
    "addr:full":"Dornal Farm Cumnock East Ayrshire KA18 3LS",
    "addr:postcode":"ka18 3ls",
    "addr:street":"East",
    "iso:country":"GB",
    "sg:address":"Dornal Farm",
    "sg:city":"Cumnock",
    "sg:classifiers":[
        {
            "category":"Farming",
            "subcategory":"Livestock Farm",
            "type":"Manufacturing & Wholesale Goods"
        }
    ],
    "sg:postcode":"KA18 3LS",
    "sg:province":"East Ayrshire",
    "sg:tags":[
        "others"
    ],
    "wof:name":"Adam Gordon",
    "wof:placetype":"venue"
},
  "geometry": {"coordinates":[-4.2640991211,55.4532546997],"type":"Point"}
}