{
  "type": "Feature",
  "properties": {
    "iso:country":"GB",
    "sg:address":"12 Rutherford Walk, Tilehurst",
    "sg:city":"Reading",
    "sg:classifiers":[
        {
            "category":"Freight",
            "type":"Transportation"
        },
        {
            "category":"Military Area",
            "subcategory":"Air Force Base",
            "type":"Public Place"
        }
    ],
    "sg:phone":"+44 118 961 5500",
    "sg:postcode":"RG31 5ND",
    "sg:province":"Berkshire",
    "sg:tags":[
        "taxi",
        "haulage",
        "hire",
        "road",
        "private"
    ],
    "wof:name":"Village Taxis",
    "wof:placetype":"venue"
},
  "geometry": {"coordinates":[-1.036564,51.46077],"type":"Point"}
}