{
  "type": "Feature",
  "properties": {
    "addr:full":"Station Road Liphook Hampshire GU30 7DW",
    "addr:postcode":"gu30 7dw",
    "addr:street":"Station Road",
    "iso:country":"GB",
    "sg:address":"Station Road",
    "sg:city":"Liphook",
    "sg:classifiers":[
        {
            "category":"Travel",
            "subcategory":"Hotels & Motels",
            "type":"Entertainment"
        }
    ],
    "sg:phone":"+44 1428 722951",
    "sg:postcode":"GU30 7DW",
    "sg:province":"Hampshire",
    "wof:name":"William Wynne",
    "wof:placetype":"venue"
},
  "geometry": {"coordinates":[-0.8010690212,51.071521759],"type":"Point"}
}