{
  "type": "Feature",
  "properties": {
    "addr:full":"198 Speedwell Road, Hay Mills Birmingham West Midlands B25 8HH",
    "addr:housenumber":"198",
    "addr:postcode":"b25 8hh",
    "addr:street":"Speedwell Road",
    "iso:country":"GB",
    "sg:address":"198 Speedwell Road, Hay Mills",
    "sg:city":"Birmingham",
    "sg:classifiers":[
        {
            "category":"Manufacturing",
            "subcategory":"Tools & Machinery",
            "type":"Manufacturing & Wholesale Goods"
        }
    ],
    "sg:phone":"+44 121 771 4827",
    "sg:postcode":"B25 8HH",
    "sg:province":"West Midlands",
    "wof:name":"Harrex Equipment Ltd.",
    "wof:placetype":"venue"
},
  "geometry": {"coordinates":[-1.834566,52.460865],"type":"Point"}
}