{
  "type": "Feature",
  "properties": {
    "addr:full":"191 Kingston Road Epsom Surrey KT19 0AB",
    "addr:housenumber":"191",
    "addr:postcode":"kt19 0ab",
    "addr:street":"Kingston Road",
    "iso:country":"GB",
    "sg:address":"191 Kingston Road",
    "sg:city":"Epsom",
    "sg:classifiers":[
        {
            "category":"Retail",
            "subcategory":"Laundry & Dry Cleaning",
            "type":"Services"
        }
    ],
    "sg:phone":"+44 20 8393 8754",
    "sg:postcode":"KT19 0AB",
    "sg:province":"Surrey",
    "sg:tags":[
        "cleaner",
        "alteration"
    ],
    "wof:name":"Ewell Professional Dry Cleaners",
    "wof:placetype":"venue"
},
  "geometry": {"coordinates":[-0.254148,51.361046],"type":"Point"}
}