{
  "type": "Feature",
  "properties": {
    "addr:full":"Embercourt Road Thames Ditton Surrey KT7 0LQ",
    "addr:postcode":"kt7 0lq",
    "addr:street":"Embercourt Road",
    "iso:country":"GB",
    "sg:address":"Embercourt Road",
    "sg:city":"Thames Ditton",
    "sg:classifiers":[
        {
            "category":"Social Services",
            "subcategory":"Adult Care",
            "type":"Services"
        },
        {
            "category":"Government",
            "subcategory":"Office",
            "type":"Public Place"
        }
    ],
    "sg:phone":"+44 1372 474556",
    "sg:postcode":"KT7 0LQ",
    "sg:province":"Surrey",
    "sg:tags":[
        "local",
        "day",
        "centre"
    ],
    "wof:name":"Ember Day Centre",
    "wof:placetype":"venue"
},
  "geometry": {"coordinates":[-0.340623,51.389915],"type":"Point"}
}