{
  "type": "Feature",
  "properties": {
    "addr:full":"61 Wilson Street Middlesbrough North Yorkshire TS1 1SF",
    "addr:housenumber":"61",
    "addr:postcode":"ts1 1sf",
    "addr:street":"Wilson Street",
    "iso:country":"GB",
    "sg:address":"61 Wilson Street",
    "sg:city":"Middlesbrough",
    "sg:classifiers":[
        {
            "category":"Bars & Pubs",
            "type":"Food & Drink"
        }
    ],
    "sg:phone":"+44 1642 247708",
    "sg:postcode":"TS1 1SF",
    "sg:province":"North Yorkshire",
    "sg:tags":[
        "pubs",
        "inn"
    ],
    "wof:name":"The Isaac Wilson",
    "wof:placetype":"venue"
},
  "geometry": {"coordinates":[-1.2360589504,54.578163147],"type":"Point"}
}