{
  "type": "Feature",
  "properties": {
    "iso:country":"GB",
    "sg:address":"31 Church St",
    "sg:city":"Tetbury",
    "sg:classifiers":[
        {
            "category":"Shopping",
            "subcategory":"Bicycles & Sporting Goods",
            "type":"Retail Goods"
        }
    ],
    "sg:phone":"+44 1666 503599",
    "sg:postcode":"GL8 8JG",
    "sg:province":"Gloucestershire",
    "sg:tags":[
        "riding",
        "saddlery",
        "wear"
    ],
    "wof:name":"Alifam",
    "wof:placetype":"venue"
},
  "geometry": {"coordinates":[-2.1635930538,51.6374511719],"type":"Point"}
}