{
  "type": "Feature",
  "properties": {
    "iso:country":"GB",
    "sg:address":"Grove House, Grove Terrace",
    "sg:city":"Walsall",
    "sg:classifiers":[
        {
            "category":"Professional",
            "subcategory":"Accounting & Tax Preparation",
            "type":"Services"
        }
    ],
    "sg:phone":"+44 1922 624566",
    "sg:postcode":"WS1 2PP",
    "sg:province":"West Midlands",
    "sg:tags":[
        "accountant"
    ],
    "wof:name":"Ridsdale Cozens Purslow",
    "wof:placetype":"venue"
},
  "geometry": {"coordinates":[-1.9761,52.580395],"type":"Point"}
}