{
  "type": "Feature",
  "properties": {
    "iso:country":"GB",
    "sg:address":"14 Edinburgh Rd",
    "sg:city":"Dalkeith",
    "sg:classifiers":[
        {
            "category":"Building & Trades",
            "subcategory":"Construction",
            "type":"Services"
        }
    ],
    "sg:phone":"+44 131 660 5538",
    "sg:postcode":"EH22 1JZ",
    "sg:province":"City of Edinburgh",
    "sg:tags":[
        "glazier"
    ],
    "wof:name":"Grange Glass & Mirror Co",
    "wof:placetype":"venue"
},
  "geometry": {"coordinates":[-3.0968089104,55.9043502808],"type":"Point"}
}