{
  "type": "Feature",
  "properties": {
    "addr:full":"86 Regent Street Cambridge Cambridgeshire CB2 1DP",
    "addr:housenumber":"86",
    "addr:postcode":"cb2 1dp",
    "addr:street":"Regent Street",
    "iso:country":"GB",
    "sg:address":"86 Regent Street",
    "sg:city":"Cambridge",
    "sg:classifiers":[
        {
            "category":"Professional",
            "subcategory":"Printing & Photocopies",
            "type":"Services"
        }
    ],
    "sg:postcode":"CB2 1DP",
    "sg:province":"Cambridgeshire",
    "sg:tags":[
        "printer"
    ],
    "wof:name":"Presto Print",
    "wof:placetype":"venue"
},
  "geometry": {"coordinates":[0.1262850016,52.200176239],"type":"Point"}
}