{
  "type": "Feature",
  "properties": {
    "iso:country":"GB",
    "sg:address":"69 Briar, Amington",
    "sg:city":"Tamworth",
    "sg:classifiers":[
        {
            "category":"Home & Garden",
            "subcategory":"Home Furnishings",
            "type":"Retail Goods"
        }
    ],
    "sg:phone":"+44 1827 59136",
    "sg:postcode":"B77 4DY",
    "sg:province":"Staffordshire",
    "sg:tags":[
        "awning",
        "canopy",
        "blinds"
    ],
    "wof:name":"Albany Blinds",
    "wof:placetype":"venue"
},
  "geometry": {"coordinates":[-1.6590499878,52.6253013611],"type":"Point"}
}