{
  "type": "Feature",
  "properties": {
    "iso:country":"GB",
    "sg:address":"Tismans Common, Rudgwick",
    "sg:city":"Horsham",
    "sg:classifiers":[
        {
            "category":"Bars & Pubs",
            "type":"Food & Drink"
        }
    ],
    "sg:phone":"+44 1403 822300",
    "sg:postcode":"RH12 3BW",
    "sg:province":"West Sussex",
    "sg:tags":[
        "pubs",
        "inn"
    ],
    "wof:name":"Longman,Roger,",
    "wof:placetype":"venue"
},
  "geometry": {"coordinates":[-0.4484289885,51.0908241272],"type":"Point"}
}