{
  "type": "Feature",
  "properties": {
    "addr:full":"54 Bryn Glas, Aberporth Cardigan Ceredigion SA43 2EQ",
    "addr:housenumber":"54",
    "addr:postcode":"sa43 2eq",
    "addr:street":"Bryn Glas",
    "iso:country":"GB",
    "sg:address":"54 Bryn Glas, Aberporth",
    "sg:city":"Cardigan",
    "sg:classifiers":[
        {
            "category":"Organizations",
            "subcategory":"Non-profit Organization",
            "type":"Services"
        }
    ],
    "sg:postcode":"SA43 2EQ",
    "sg:province":"Ceredigion",
    "sg:tags":[
        "organisation",
        "voluntary",
        "charity"
    ],
    "wof:name":"The Cancer Research Campaign",
    "wof:placetype":"venue"
},
  "geometry": {"coordinates":[-4.543423,52.132504],"type":"Point"}
}