{
  "type": "Feature",
  "properties": {
    "addr:full":"Unit 18 Alexandra Centre, Rail Mill Way Rotherham South Yorkshire S62 6JE",
    "addr:housenumber":"unit 18",
    "addr:postcode":"s62 6je",
    "addr:street":"Alexandra Centre Rail Mill Way",
    "iso:country":"GB",
    "sg:address":"Unit 18 Alexandra Centre, Rail Mill Way",
    "sg:city":"Rotherham",
    "sg:classifiers":[
        {
            "category":"Professional",
            "subcategory":"Management & Consulting",
            "type":"Services"
        }
    ],
    "sg:phone":"+44 1709 780001",
    "sg:postcode":"S62 6JE",
    "sg:province":"South Yorkshire",
    "sg:tags":[
        "fire",
        "consultant",
        "protection"
    ],
    "wof:name":"Complete Fire & Safety",
    "wof:placetype":"venue"
},
  "geometry": {"coordinates":[-1.34337,53.448189],"type":"Point"}
}