{
  "type": "Feature",
  "properties": {
    "iso:country":"GB",
    "sg:address":"91 Northbrook Street",
    "sg:city":"Newbury",
    "sg:classifiers":[
        {
            "category":"Shopping",
            "subcategory":"Shoes",
            "type":"Retail Goods"
        }
    ],
    "sg:phone":"+44 1635 522714",
    "sg:postcode":"RG14 1AA",
    "sg:province":"Berkshire",
    "sg:tags":[
        "shop"
    ],
    "wof:name":"The Oliver Group",
    "wof:placetype":"venue"
},
  "geometry": {"coordinates":[-1.3246190548,51.4040718079],"type":"Point"}
}