{
  "type": "Feature",
  "properties": {
    "iso:country":"GB",
    "sg:address":"Red Roof Clinic Bar Lane, Waddington",
    "sg:city":"Lincoln",
    "sg:classifiers":[
        {
            "category":"Health Services",
            "subcategory":"Podiatrist",
            "type":"Services"
        }
    ],
    "sg:phone":"+44 1522 722595",
    "sg:postcode":"LN5 9SA",
    "sg:province":"Lincolnshire",
    "sg:tags":[
        "podiatrists",
        "chiropodist"
    ],
    "wof:name":"G Stewart",
    "wof:placetype":"venue"
},
  "geometry": {"coordinates":[-0.539114,53.168427],"type":"Point"}
}