{
  "type": "Feature",
  "properties": {
    "addr:full":"46 Embankment Road Plymouth Devon PL4 9HY",
    "addr:postcode":"pl4 9hy",
    "addr:street":"Embankment Road",
    "iso:country":"GB",
    "sg:address":"46 Embankment Road",
    "sg:city":"Plymouth",
    "sg:classifiers":[
        {
            "category":"Home & Garden",
            "subcategory":"Building Materials",
            "type":"Retail Goods"
        }
    ],
    "sg:phone":"+44 1752 222002",
    "sg:postcode":"PL4 9HY",
    "sg:province":"Devon",
    "sg:tags":[
        "plaster",
        "ware"
    ],
    "wof:name":"Abbey Mouldings",
    "wof:placetype":"venue"
},
  "geometry": {"coordinates":[-4.1217508316,50.3703384399],"type":"Point"}
}