{
  "type": "Feature",
  "properties": {
    "iso:country":"GB",
    "sg:address":"Carr Lane",
    "sg:city":"Gainsborough",
    "sg:classifiers":[
        {
            "category":"Manufacturing",
            "subcategory":"Food",
            "type":"Manufacturing & Wholesale Goods"
        }
    ],
    "sg:phone":"+44 1427 614161",
    "sg:postcode":"DN21 1LQ",
    "sg:province":"Lincolnshire",
    "sg:tags":[
        "miller",
        "mill"
    ],
    "wof:name":"Kerry Milling",
    "wof:placetype":"venue"
},
  "geometry": {"coordinates":[-0.776374,53.387501],"type":"Point"}
}