{
  "type": "Feature",
  "properties": {
    "iso:country":"GB",
    "sg:address":"Care Of Gk Group, Chatsworth Rd",
    "sg:city":"Chesterfield",
    "sg:classifiers":[
        {
            "category":"Retail",
            "subcategory":"Driving School",
            "type":"Services"
        }
    ],
    "sg:phone":"+44 1246 209999",
    "sg:postcode":"S40 2BJ",
    "sg:province":"Derbyshire",
    "wof:name":"Chesterfield & District Associations Of Driving Schools",
    "wof:placetype":"venue"
},
  "geometry": {"coordinates":[-1.44671,53.23354],"type":"Point"}
}