{
  "type": "Feature",
  "properties": {
    "addr:full":"10 Askern Rd Doncaster South Yorkshire DN5 0EA",
    "addr:housenumber":"10",
    "addr:postcode":"dn5 0ea",
    "addr:street":"Askern Rd",
    "iso:country":"GB",
    "sg:address":"10 Askern Rd",
    "sg:city":"Doncaster",
    "sg:classifiers":[
        {
            "category":"Food & Beverages",
            "subcategory":"Meat & Fish",
            "type":"Retail Goods"
        }
    ],
    "sg:postcode":"DN5 0EA",
    "sg:province":"South Yorkshire",
    "sg:tags":[
        "butcher"
    ],
    "wof:name":"Crundell,J R,",
    "wof:placetype":"venue"
},
  "geometry": {"coordinates":[-1.1456769705,53.547908783],"type":"Point"}
}