{
  "type": "Feature",
  "properties": {
    "addr:full":"Hightown Road Ringwood Dorset BH24 1NQ",
    "addr:postcode":"bh24 1nq",
    "addr:street":"Hightown Road",
    "iso:country":"GB",
    "sg:address":"Hightown Road",
    "sg:city":"Ringwood",
    "sg:classifiers":[
        {
            "category":"Bars & Pubs",
            "type":"Food & Drink"
        }
    ],
    "sg:phone":"+44 1425 473701",
    "sg:postcode":"BH24 1NQ",
    "sg:province":"Dorset",
    "sg:tags":[
        "pubs",
        "inn"
    ],
    "wof:name":"Railway Hotel",
    "wof:placetype":"venue"
},
  "geometry": {"coordinates":[-1.7733399868,50.8438644409],"type":"Point"}
}