{
  "type": "Feature",
  "properties": {
    "iso:country":"GB",
    "sg:address":"20 Blethin Close, Danescourt",
    "sg:city":"Cardiff",
    "sg:classifiers":[
        {
            "category":"Building & Trades",
            "subcategory":"Construction",
            "type":"Services"
        }
    ],
    "sg:phone":"+44 29 2055 3748",
    "sg:postcode":"CF5 2RR",
    "sg:province":"Cardiff",
    "sg:tags":[
        "builder"
    ],
    "wof:name":"S A S Building Contractors Ltd.",
    "wof:placetype":"venue"
},
  "geometry": {"coordinates":[-3.237305,51.504555],"type":"Point"}
}