{
  "type": "Feature",
  "properties": {
    "iso:country":"GB",
    "sg:address":"43 Charles St",
    "sg:city":"Cardiff",
    "sg:classifiers":[
        {
            "category":"Organizations",
            "subcategory":"Non-profit Organization",
            "type":"Services"
        }
    ],
    "sg:postcode":"CF10 2GB",
    "sg:province":"Cardiff",
    "sg:tags":[
        "organisation",
        "voluntary",
        "charity"
    ],
    "wof:name":"Innovate Trust Ltd",
    "wof:placetype":"venue"
},
  "geometry": {"coordinates":[-3.174589,51.482109],"type":"Point"}
}