{
  "type": "Feature",
  "properties": {
    "iso:country":"GB",
    "sg:address":"5 Broad Chalke Down",
    "sg:city":"Winchester",
    "sg:classifiers":[
        {
            "category":"Building & Trades",
            "subcategory":"Landscaping Services",
            "type":"Services"
        }
    ],
    "sg:phone":"+44 1962 841007",
    "sg:postcode":"SO22 4LR",
    "sg:province":"Hampshire",
    "sg:tags":[
        "designer",
        "architect",
        "landscape"
    ],
    "wof:name":"June Effemey",
    "wof:placetype":"venue"
},
  "geometry": {"coordinates":[-1.339955,51.049587],"type":"Point"}
}