{
  "type": "Feature",
  "properties": {
    "iso:country":"GB",
    "sg:address":"72 Downham Road",
    "sg:city":"London",
    "sg:classifiers":[
        {
            "category":"Professional",
            "subcategory":"Computer Services",
            "type":"Services"
        }
    ],
    "sg:phone":"+44 7956 119554",
    "sg:postcode":"N1 5BG",
    "sg:province":"Greater London",
    "sg:tags":[
        "system",
        "software"
    ],
    "wof:name":"Straight Path Ltd.",
    "wof:placetype":"venue"
},
  "geometry": {"coordinates":[-0.0831950009,51.5394363403],"type":"Point"}
}