{
  "type": "Feature",
  "properties": {
    "addr:full":"8 Westerham Avenue London Greater London E10 6DZ",
    "addr:housenumber":"8",
    "addr:postcode":"e10 6dz",
    "addr:street":"Westerham Avenue",
    "iso:country":"GB",
    "sg:address":"8 Westerham Avenue",
    "sg:city":"London",
    "sg:classifiers":[
        {
            "category":"Food & Beverages",
            "subcategory":"Meat & Fish",
            "type":"Retail Goods"
        }
    ],
    "sg:phone":"+44 20 8807 7315",
    "sg:postcode":"E10 6DZ",
    "sg:province":"Greater London",
    "sg:tags":[
        "butcher"
    ],
    "wof:name":"A Puntrello & Son",
    "wof:placetype":"venue"
},
  "geometry": {"coordinates":[-0.013404,51.574162],"type":"Point"}
}