{
  "type": "Feature",
  "properties": {
    "addr:full":"1-2 Adelaide Place Canterbury Kent CT1 2QA",
    "addr:housenumber":"1-2",
    "addr:postcode":"ct1 2qa",
    "addr:street":"Adelaide Place",
    "iso:country":"GB",
    "sg:address":"1-2 Adelaide Place",
    "sg:city":"Canterbury",
    "sg:classifiers":[
        {
            "category":"Restaurant",
            "type":"Food & Drink"
        }
    ],
    "sg:phone":"+44 1227 463447",
    "sg:postcode":"CT1 2QA",
    "sg:province":"Kent",
    "sg:tags":[
        "chinese"
    ],
    "wof:name":"Mandarin Chinese Restaurant",
    "wof:placetype":"venue"
},
  "geometry": {"coordinates":[1.07751,51.277199],"type":"Point"}
}