{
  "type": "Feature",
  "properties": {
    "iso:country":"GB",
    "sg:address":"55 London Road",
    "sg:city":"London",
    "sg:classifiers":[
        {
            "category":"Shopping",
            "subcategory":"Pets & Pet Supplies",
            "type":"Retail Goods"
        }
    ],
    "sg:phone":"+44 20 8648 3159",
    "sg:postcode":"SW17 9JR",
    "sg:province":"Greater London",
    "wof:name":"Manor Aquatics",
    "wof:placetype":"venue"
},
  "geometry": {"coordinates":[-0.161844,51.418816],"type":"Point"}
}