{
  "type": "Feature",
  "properties": {
    "addr:full":"Lovell Park Court Leeds West Yorkshire LS7 1DE",
    "addr:postcode":"ls7 1de",
    "addr:street":"Park Court",
    "iso:country":"GB",
    "sg:address":"Lovell Park Court",
    "sg:city":"Leeds",
    "sg:classifiers":[
        {
            "category":"Government",
            "subcategory":"Office",
            "type":"Public Place"
        }
    ],
    "sg:phone":"+44 113 245 2586",
    "sg:postcode":"LS7 1DE",
    "sg:province":"West Yorkshire",
    "sg:tags":[
        "local"
    ],
    "wof:name":"Leeds City Council",
    "wof:placetype":"venue"
},
  "geometry": {"coordinates":[-1.538654,53.804466],"type":"Point"}
}