{
  "type": "Feature",
  "properties": {
    "iso:country":"GB",
    "sg:address":"556 Green Lane, Small Heath",
    "sg:city":"Birmingham",
    "sg:classifiers":[
        {
            "category":"Communications",
            "subcategory":"Film & Video Production",
            "type":"Services"
        }
    ],
    "sg:phone":"+44 121 772 3877",
    "sg:postcode":"B9 5QG",
    "sg:province":"West Midlands",
    "sg:tags":[
        "tv"
    ],
    "wof:name":"Movie Zone",
    "wof:placetype":"venue"
},
  "geometry": {"coordinates":[-1.842895031,52.4756813049],"type":"Point"}
}