{
  "type": "Feature",
  "properties": {
    "addr:full":"Clive House Prospect Hill Redditch Warwickshire B97 4BG",
    "addr:postcode":"b97 4bg",
    "addr:street":"Prospect Hill",
    "iso:country":"GB",
    "sg:address":"Clive House Prospect Hill",
    "sg:city":"Redditch",
    "sg:classifiers":[
        {
            "category":"Wholesale",
            "subcategory":"Books, Periodicals, & Newspapers",
            "type":"Manufacturing & Wholesale Goods"
        }
    ],
    "sg:phone":"+44 1527 584500",
    "sg:postcode":"B97 4BG",
    "sg:province":"Warwickshire",
    "sg:tags":[
        "publishing"
    ],
    "wof:name":"I S T Travel Magazine",
    "wof:placetype":"venue"
},
  "geometry": {"coordinates":[-1.940794,52.310562],"type":"Point"}
}