{
  "type": "Feature",
  "properties": {
    "addr:full":"3 Cranleigh Gardens Bristol City of Bristol BS9 1HD",
    "addr:housenumber":"3",
    "addr:postcode":"bs9 1hd",
    "addr:street":"Cranleigh Gardens",
    "iso:country":"GB",
    "sg:address":"3 Cranleigh Gardens",
    "sg:city":"Bristol",
    "sg:classifiers":[
        {
            "category":"Professional",
            "subcategory":"Detective & Security Services",
            "type":"Services"
        }
    ],
    "sg:phone":"+44 117 962 6614",
    "sg:postcode":"BS9 1HD",
    "sg:province":"City of Bristol",
    "sg:tags":[
        "equipment"
    ],
    "wof:name":"Lace Safe",
    "wof:placetype":"venue"
},
  "geometry": {"coordinates":[-2.636779,51.477612],"type":"Point"}
}