{
  "type": "Feature",
  "properties": {
    "addr:full":"12 Main St, Sutton Bassett Market Harborough Leicestershire LE16 8HP",
    "addr:housenumber":"12",
    "addr:postcode":"le16 8hp",
    "addr:street":"Main St",
    "iso:country":"GB",
    "sg:address":"12 Main St, Sutton Bassett",
    "sg:city":"Market Harborough",
    "sg:classifiers":[
        {
            "category":"Real Estate",
            "subcategory":"Surveying",
            "type":"Services"
        }
    ],
    "sg:phone":"+44 1858 468026",
    "sg:postcode":"LE16 8HP",
    "sg:province":"Leicestershire",
    "sg:tags":[
        "surveyor",
        "land"
    ],
    "wof:name":"J.R Owen",
    "wof:placetype":"venue"
},
  "geometry": {"coordinates":[-0.832551,52.510548],"type":"Point"}
}