{
  "type": "Feature",
  "properties": {
    "addr:full":"14 Federick Place, Clifton Bristol City of Bristol BS8 1AS",
    "addr:housenumber":"14",
    "addr:postcode":"bs8 1as",
    "addr:street":"Federick Place",
    "iso:country":"GB",
    "sg:address":"14 Federick Place, Clifton",
    "sg:city":"Bristol",
    "sg:classifiers":[
        {
            "category":"Professional",
            "subcategory":"Art Services",
            "type":"Services"
        }
    ],
    "sg:phone":"+44 117 908 1390",
    "sg:postcode":"BS8 1AS",
    "sg:province":"City of Bristol",
    "sg:tags":[
        "graphic",
        "designer"
    ],
    "wof:name":"Juice Creative Communication",
    "wof:placetype":"venue"
},
  "geometry": {"coordinates":[-2.6103470325,51.4566993713],"type":"Point"}
}