{
  "type": "Feature",
  "properties": {
    "addr:full":"Unit 2 Gate Centre, Bredbury Park Way, Bredbury Park Industrial Estate Stockport Cheshire SK6 2SN",
    "addr:housenumber":"unit 2;estate",
    "addr:postcode":"sk6 2sn",
    "addr:street":"Gate;Bredbury Park Way Bredbury Park Industrial",
    "iso:country":"GB",
    "sg:address":"Unit 2 Gate Centre, Bredbury Park Way, Bredbury Park Industrial Estate",
    "sg:city":"Stockport",
    "sg:classifiers":[
        {
            "category":"Home & Garden",
            "subcategory":"Household Appliances",
            "type":"Retail Goods"
        },
        {
            "category":"Wholesale",
            "subcategory":"Electrical",
            "type":"Manufacturing & Wholesale Goods"
        }
    ],
    "sg:phone":"+44 161 336 9879",
    "sg:postcode":"SK6 2SN",
    "sg:province":"Cheshire",
    "sg:tags":[
        "equipment",
        "refrigeration",
        "air conditioning"
    ],
    "wof:name":"Tameside Refrigeration & Air Conditioning Ltd.",
    "wof:placetype":"venue"
},
  "geometry": {"coordinates":[-2.122762,53.42065],"type":"Point"}
}