{
  "type": "Feature",
  "properties": {
    "addr:full":"Dunkirk Drove, Somersham Huntingdon Bedfordshire PE28 3HN",
    "addr:postcode":"pe28 3hn",
    "addr:street":"Drove",
    "iso:country":"GB",
    "sg:address":"Dunkirk Drove, Somersham",
    "sg:city":"Huntingdon",
    "sg:classifiers":[
        {
            "category":"Recreation",
            "subcategory":"Dog Park",
            "type":"Entertainment"
        }
    ],
    "sg:postcode":"PE28 3HN",
    "sg:province":"Bedfordshire",
    "wof:name":"Razda Kennels",
    "wof:placetype":"venue"
},
  "geometry": {"coordinates":[-0.000226,52.382149],"type":"Point"}
}