{
  "type": "Feature",
  "properties": {
    "addr:full":"Cockermouth Business Centre, Factory Cockermouth Cumbria CA13 0NH",
    "addr:postcode":"ca13 0nh",
    "addr:street":"Cockermouth",
    "iso:country":"GB",
    "sg:address":"Cockermouth Business Centre, Factory",
    "sg:city":"Cockermouth",
    "sg:classifiers":[
        {
            "category":"Manufacturing",
            "subcategory":"Wood Products",
            "type":"Manufacturing & Wholesale Goods"
        }
    ],
    "sg:phone":"+44 1900 823555",
    "sg:postcode":"CA13 0NH",
    "sg:province":"Cumbria",
    "wof:name":"James Walker & Co",
    "wof:placetype":"venue"
},
  "geometry": {"coordinates":[-3.4118599892,54.6636505127],"type":"Point"}
}