{
  "type": "Feature",
  "properties": {
    "addr:full":"8 Church Street Kington Herefordshire HR5 3AZ",
    "addr:housenumber":"8",
    "addr:postcode":"hr5 3az",
    "addr:street":"Church Street",
    "iso:country":"GB",
    "sg:address":"8 Church Street",
    "sg:city":"Kington",
    "sg:classifiers":[
        {
            "category":"Professional",
            "subcategory":"Art Services",
            "type":"Services"
        }
    ],
    "sg:phone":"+44 1544 230623",
    "sg:postcode":"HR5 3AZ",
    "sg:province":"Herefordshire",
    "sg:tags":[
        "picture",
        "framing"
    ],
    "wof:name":"G R Maynard",
    "wof:placetype":"venue"
},
  "geometry": {"coordinates":[-3.0317618847,52.2037734985],"type":"Point"}
}