{
  "type": "Feature",
  "properties": {
    "addr:full":"7 High St Castle Cary Somerset BA7 7AN",
    "addr:housenumber":"7",
    "addr:postcode":"ba7 7an",
    "addr:street":"High St",
    "iso:country":"GB",
    "sg:address":"7 High St",
    "sg:city":"Castle Cary",
    "sg:classifiers":[
        {
            "category":"Real Estate",
            "subcategory":"Real Estate Agent",
            "type":"Services"
        }
    ],
    "sg:phone":"+44 1963 351352",
    "sg:postcode":"BA7 7AN",
    "sg:province":"Somerset",
    "wof:name":"Websters Estate Agents",
    "wof:placetype":"venue"
},
  "geometry": {"coordinates":[-2.5137081146,51.0897903442],"type":"Point"}
}