{
  "type": "Feature",
  "properties": {
    "iso:country":"GB",
    "sg:address":"Perrymans Hill, Furners Green",
    "sg:city":"Uckfield",
    "sg:classifiers":[
        {
            "category":"Transit Center",
            "subcategory":"Passenger",
            "type":"Transportation"
        }
    ],
    "sg:phone":"+44 1825 740287",
    "sg:postcode":"TN22 3RS",
    "sg:province":"East Sussex",
    "sg:tags":[
        "boarding",
        "kennel",
        "catteries"
    ],
    "wof:name":"Allins Farm Kennels",
    "wof:placetype":"venue"
},
  "geometry": {"coordinates":[0.007907,51.014942],"type":"Point"}
}