{
  "type": "Feature",
  "properties": {
    "addr:full":"Unit 24 Ashford Industrial Estate, Shield Road Ashford Greater London TW15 1AU",
    "addr:housenumber":"unit 24;estate",
    "addr:postcode":"tw15 1au",
    "addr:street":"Ashford Industrial;Shield Road",
    "iso:country":"GB",
    "sg:address":"Unit 24 Ashford Industrial Estate, Shield Road",
    "sg:city":"Ashford",
    "sg:classifiers":[
        {
            "category":"Freight",
            "type":"Transportation"
        }
    ],
    "sg:postcode":"TW15 1AU",
    "sg:province":"Greater London",
    "sg:tags":[
        "haulage",
        "road"
    ],
    "wof:name":"Rapid Logistics",
    "wof:placetype":"venue"
},
  "geometry": {"coordinates":[-0.462444,51.432976],"type":"Point"}
}