{
  "type": "Feature",
  "properties": {
    "iso:country":"GB",
    "sg:address":"Marvan, Cromwell Road",
    "sg:city":"Wisbech",
    "sg:classifiers":[
        {
            "category":"Retail",
            "subcategory":"Repair Shop",
            "type":"Services"
        },
        {
            "category":"Wholesale",
            "subcategory":"Machinery & Supplies",
            "type":"Manufacturing & Wholesale Goods"
        }
    ],
    "sg:phone":"+44 1945 464909",
    "sg:postcode":"PE14 0SD",
    "sg:province":"Cambridgeshire",
    "sg:tags":[
        "agricultural",
        "sale"
    ],
    "wof:name":"Stocks Ag Ltd.",
    "wof:placetype":"venue"
},
  "geometry": {"coordinates":[0.15057,52.657173],"type":"Point"}
}