{
  "type": "Feature",
  "properties": {
    "addr:full":"Oak Mount, Windmill La, Balsall Common Coventry Warwickshire CV7 7GY",
    "addr:postcode":"cv7 7gy",
    "addr:street":"Oak Mount;La Balsall",
    "iso:country":"GB",
    "sg:address":"Oak Mount, Windmill La, Balsall Common",
    "sg:city":"Coventry",
    "sg:classifiers":[
        {
            "category":"Building & Trades",
            "subcategory":"Construction",
            "type":"Services"
        },
        {
            "category":"Government",
            "subcategory":"Customs House",
            "type":"Public Place"
        }
    ],
    "sg:postcode":"CV7 7GY",
    "sg:province":"Warwickshire",
    "sg:tags":[
        "builder",
        "clearance"
    ],
    "wof:name":"Westmacott,V C,",
    "wof:placetype":"venue"
},
  "geometry": {"coordinates":[-1.6461340189,52.3858985901],"type":"Point"}
}