{
  "type": "Feature",
  "properties": {
    "iso:country":"GB",
    "sg:address":"Vancouver Drive",
    "sg:city":"Crawley",
    "sg:classifiers":[
        {
            "category":"Restaurant",
            "type":"Food & Drink"
        }
    ],
    "sg:phone":"+44 121 703 1900",
    "sg:postcode":"RH11 7UR",
    "sg:province":"West Sussex",
    "wof:name":"Jordans Toby Restaurant",
    "wof:placetype":"venue"
},
  "geometry": {"coordinates":[-0.189569,51.128891],"type":"Point"}
}