{
  "type": "Feature",
  "properties": {
    "addr:full":"34 Middle La, Whaplode Spalding Cambridgeshire PE12 6TW",
    "addr:housenumber":"34",
    "addr:postcode":"pe12 6tw",
    "addr:street":"Middle La Whaplode Spalding",
    "iso:country":"GB",
    "sg:address":"34 Middle La, Whaplode",
    "sg:city":"Spalding",
    "sg:classifiers":[
        {
            "category":"Organizations",
            "subcategory":"Membership Organization",
            "type":"Services"
        }
    ],
    "sg:postcode":"PE12 6TW",
    "sg:province":"Cambridgeshire",
    "sg:tags":[
        "club"
    ],
    "wof:name":"Spalding Chess Club",
    "wof:placetype":"venue"
},
  "geometry": {"coordinates":[-0.0369829983,52.8001785278],"type":"Point"}
}