{
  "type": "Feature",
  "properties": {
    "iso:country":"GB",
    "sg:address":"10 Knockbreck Street",
    "sg:city":"Tain",
    "sg:classifiers":[
        {
            "category":"Professional",
            "subcategory":"Art Services",
            "type":"Services"
        }
    ],
    "sg:postcode":"IV19 1BJ",
    "sg:province":"Highland",
    "sg:tags":[
        "graphic",
        "designer"
    ],
    "wof:name":"Arkle Information Systems Ltd.",
    "wof:placetype":"venue"
},
  "geometry": {"coordinates":[-4.050962925,57.8096542358],"type":"Point"}
}