{
  "type": "Feature",
  "properties": {
    "addr:full":"12 College Avenue Egham Surrey TW20 8NR",
    "addr:housenumber":"12",
    "addr:postcode":"tw20 8nr",
    "addr:street":"College Avenue",
    "iso:country":"GB",
    "sg:address":"12 College Avenue",
    "sg:city":"Egham",
    "sg:classifiers":[
        {
            "category":"Professional",
            "subcategory":"Management & Consulting",
            "type":"Services"
        }
    ],
    "sg:postcode":"TW20 8NR",
    "sg:province":"Surrey",
    "sg:tags":[
        "consultant",
        "business"
    ],
    "wof:name":"Spectre Consultancy Ltd.",
    "wof:placetype":"venue"
},
  "geometry": {"coordinates":[-0.5349550247,51.4277267456],"type":"Point"}
}