{
  "type": "Feature",
  "properties": {
    "iso:country":"GB",
    "sg:address":"9 Halesfield Rd",
    "sg:city":"Telford",
    "sg:classifiers":[
        {
            "category":"Shopping",
            "subcategory":"Mobile Phones",
            "type":"Retail Goods"
        }
    ],
    "sg:phone":"+44 1952 585859",
    "sg:postcode":"TF7 4ES",
    "sg:province":"Shropshire",
    "wof:name":"S S Electronics",
    "wof:placetype":"venue"
},
  "geometry": {"coordinates":[-2.4382939339,52.638710022],"type":"Point"}
}