{
  "type": "Feature",
  "properties": {
    "addr:full":"Hill Carr Farm, South Darley Matlock Derbyshire DE4 2LQ",
    "addr:postcode":"de4 2lq",
    "addr:street":"Hill Carr Farm South",
    "iso:country":"GB",
    "sg:address":"Hill Carr Farm, South Darley",
    "sg:city":"Matlock",
    "sg:classifiers":[
        {
            "category":"Farming",
            "subcategory":"Farm",
            "type":"Manufacturing & Wholesale Goods"
        }
    ],
    "sg:phone":"+44 1629 733542",
    "sg:postcode":"DE4 2LQ",
    "sg:province":"Derbyshire",
    "sg:tags":[
        "mixed",
        "crop"
    ],
    "wof:name":"J D & V Frith",
    "wof:placetype":"venue"
},
  "geometry": {"coordinates":[-1.548274,53.135616],"type":"Point"}
}