{
  "type": "Feature",
  "properties": {
    "addr:full":"Unit 5 Orion Trading Estate, Tenax Road Manchester Cheshire M17 1JT",
    "addr:housenumber":"unit 5",
    "addr:postcode":"m17 1jt",
    "addr:street":"Orion Trading Estate Tenax Road",
    "iso:country":"GB",
    "sg:address":"Unit 5 Orion Trading Estate, Tenax Road",
    "sg:city":"Manchester",
    "sg:classifiers":[
        {
            "category":"Professional",
            "subcategory":"Engineering",
            "type":"Services"
        }
    ],
    "sg:phone":"+44 161 848 0316",
    "sg:postcode":"M17 1JT",
    "sg:province":"Cheshire",
    "wof:name":"The Beamech Group Ltd.",
    "wof:placetype":"venue"
},
  "geometry": {"coordinates":[-2.3196790218,53.4674415588],"type":"Point"}
}