{
  "type": "Feature",
  "properties": {
    "addr:full":"2nd Floor Pensnett Ho, Pensnett Trading Est Kingswinford Staffordshire DY6 7PP",
    "addr:housenumber":"2nd floor",
    "addr:postcode":"dy6 7pp",
    "addr:street":"Pensnett Ho",
    "iso:country":"GB",
    "sg:address":"2nd Floor Pensnett Ho, Pensnett Trading Est",
    "sg:city":"Kingswinford",
    "sg:classifiers":[
        {
            "category":"Home & Garden",
            "subcategory":"Building Materials",
            "type":"Retail Goods"
        }
    ],
    "sg:phone":"+44 1384 402858",
    "sg:postcode":"DY6 7PP",
    "sg:province":"Staffordshire",
    "sg:tags":[
        "tanks",
        "cistern",
        "vat"
    ],
    "wof:name":"Horseley Bridge Tanks",
    "wof:placetype":"venue"
},
  "geometry": {"coordinates":[-2.167674,52.495804],"type":"Point"}
}