{
  "type": "Feature",
  "properties": {
    "iso:country":"GB",
    "sg:address":"Reliance House, 6 Theobald Street",
    "sg:city":"Borehamwood",
    "sg:classifiers":[
        {
            "category":"Professional",
            "subcategory":"Accounting & Tax Preparation",
            "type":"Services"
        }
    ],
    "sg:phone":"+44 20 8207 6929",
    "sg:postcode":"WD6 4SE",
    "sg:province":"Hertfordshire",
    "sg:tags":[
        "accountant"
    ],
    "wof:name":"Visana Chartered Accountants",
    "wof:placetype":"venue"
},
  "geometry": {"coordinates":[-0.27982,51.654331],"type":"Point"}
}