{
  "type": "Feature",
  "properties": {
    "addr:full":"36 Waver St Carlisle Cumbria CA5 4DG",
    "addr:housenumber":"36",
    "addr:postcode":"ca5 4dg",
    "addr:street":"Waver St",
    "iso:country":"GB",
    "sg:address":"36 Waver St",
    "sg:city":"Carlisle",
    "sg:classifiers":[
        {
            "category":"Building & Trades",
            "subcategory":"Construction",
            "type":"Services"
        }
    ],
    "sg:phone":"+44 16973 31204",
    "sg:postcode":"CA5 4DG",
    "sg:province":"Cumbria",
    "sg:tags":[
        "joiner",
        "carpenter"
    ],
    "wof:name":"Abbot & Proud",
    "wof:placetype":"venue"
},
  "geometry": {"coordinates":[-3.3838469982,54.8702964783],"type":"Point"}
}