{
  "type": "Feature",
  "properties": {
    "iso:country":"GB",
    "sg:address":"20 Glasshouse Street",
    "sg:city":"London",
    "sg:classifiers":[
        {
            "category":"Restaurant",
            "type":"Food & Drink"
        }
    ],
    "sg:phone":"+44 20 7734 4888",
    "sg:postcode":"W1B 5DJ",
    "sg:province":"Greater London",
    "wof:name":"The Atlantic Bar & Grill Ltd.",
    "wof:placetype":"venue"
},
  "geometry": {"coordinates":[-0.13816,51.510433],"type":"Point"}
}