{
  "type": "Feature",
  "properties": {
    "iso:country":"GB",
    "sg:address":"225 Melton Road",
    "sg:city":"Leicester",
    "sg:classifiers":[
        {
            "category":"Personal",
            "subcategory":"Beauty Salon",
            "type":"Services"
        }
    ],
    "sg:phone":"+44 116 266 1075",
    "sg:postcode":"LE4 7AN",
    "sg:province":"Leicestershire",
    "sg:tags":[
        "ladies",
        "lady",
        "hairdresser"
    ],
    "wof:name":"Susan Rose",
    "wof:placetype":"venue"
},
  "geometry": {"coordinates":[-1.1161409616,52.6576042175],"type":"Point"}
}