{
  "type": "Feature",
  "properties": {
    "addr:full":"18 Spey Ave Paisley East Renfrewshire PA2 0EG",
    "addr:housenumber":"18",
    "addr:postcode":"pa2 0eg",
    "addr:street":"Spey Ave",
    "iso:country":"GB",
    "sg:address":"18 Spey Ave",
    "sg:city":"Paisley",
    "sg:classifiers":[
        {
            "category":"Food & Beverages",
            "subcategory":"Supermarket",
            "type":"Retail Goods"
        }
    ],
    "sg:postcode":"PA2 0EG",
    "sg:province":"East Renfrewshire",
    "wof:name":"Target Supersave",
    "wof:placetype":"venue"
},
  "geometry": {"coordinates":[-4.468022,55.829609],"type":"Point"}
}