{
  "type": "Feature",
  "properties": {
    "addr:full":"48 Monks Park Wembley Greater London HA9 6JQ",
    "addr:housenumber":"48",
    "addr:postcode":"ha9 6jq",
    "addr:street":"Monks Park",
    "iso:country":"GB",
    "sg:address":"48 Monks Park",
    "sg:city":"Wembley",
    "sg:classifiers":[
        {
            "category":"Personal",
            "subcategory":"Barber",
            "type":"Services"
        }
    ],
    "sg:phone":"+44 20 8903 3781",
    "sg:postcode":"HA9 6JQ",
    "sg:province":"Greater London",
    "sg:tags":[
        "men's",
        "hairdresser"
    ],
    "wof:name":"Latti & Son",
    "wof:placetype":"venue"
},
  "geometry": {"coordinates":[-0.272029,51.545521],"type":"Point"}
}