{
  "type": "Feature",
  "properties": {
    "addr:full":"1 Greengates Leven Fife KY8 5BB",
    "addr:housenumber":"1",
    "addr:postcode":"ky8 5bb",
    "addr:street":"Greengates Leven",
    "iso:country":"GB",
    "sg:address":"1 Greengates",
    "sg:city":"Leven",
    "sg:classifiers":[
        {
            "category":"Building & Trades",
            "subcategory":"Construction",
            "type":"Services"
        },
        {
            "category":"Retail",
            "subcategory":"Storage",
            "type":"Services"
        }
    ],
    "sg:phone":"+44 1333 426684",
    "sg:postcode":"KY8 5BB",
    "sg:province":"Fife",
    "sg:tags":[
        "builder",
        "household",
        "removal"
    ],
    "wof:name":"Michael Hanley",
    "wof:placetype":"venue"
},
  "geometry": {"coordinates":[-3.0074799061,56.2063140869],"type":"Point"}
}