{
  "type": "Feature",
  "properties": {
    "addr:full":"Allars Mill Jedburgh Scottish Borders TD8 6NR",
    "addr:postcode":"td8 6nr",
    "iso:country":"GB",
    "sg:address":"Allars Mill",
    "sg:city":"Jedburgh",
    "sg:classifiers":[
        {
            "category":"Train Station",
            "subcategory":"Light Rail",
            "type":"Transportation"
        }
    ],
    "sg:phone":"+44 1835 863465",
    "sg:postcode":"TD8 6NR",
    "sg:province":"Scottish Borders",
    "sg:tags":[
        "distributor",
        "mnfrs",
        "lime"
    ],
    "wof:name":"W & M Thompson",
    "wof:placetype":"venue"
},
  "geometry": {"coordinates":[-2.5546240807,55.4777183533],"type":"Point"}
}