{
  "type": "Feature",
  "properties": {
    "addr:full":"299 Westward Road, Ebley Stroud Gloucestershire GL5 4TX",
    "addr:housenumber":"299",
    "addr:postcode":"gl5 4tx",
    "addr:street":"Westward Road Ebley",
    "iso:country":"GB",
    "sg:address":"299 Westward Road, Ebley",
    "sg:city":"Stroud",
    "sg:classifiers":[
        {
            "category":"Real Estate",
            "subcategory":"Surveying",
            "type":"Services"
        }
    ],
    "sg:phone":"+44 1453 825269",
    "sg:postcode":"GL5 4TX",
    "sg:province":"Gloucestershire",
    "sg:tags":[
        "surveyor",
        "land",
        "activity"
    ],
    "wof:name":"Mole Data Surveyors",
    "wof:placetype":"venue"
},
  "geometry": {"coordinates":[-2.254375,51.740723],"type":"Point"}
}