{
  "type": "Feature",
  "properties": {
    "addr:full":"The Barracks, Gorefield Wisbech Cambridgeshire PE13 4PQ",
    "addr:postcode":"pe13 4pq",
    "iso:country":"GB",
    "sg:address":"The Barracks, Gorefield",
    "sg:city":"Wisbech",
    "sg:classifiers":[
        {
            "category":"Building & Trades",
            "subcategory":"Construction",
            "type":"Services"
        }
    ],
    "sg:phone":"+44 1945 870001",
    "sg:postcode":"PE13 4PQ",
    "sg:province":"Cambridgeshire",
    "sg:tags":[
        "glazier"
    ],
    "wof:name":"Robert A Spooner",
    "wof:placetype":"venue"
},
  "geometry": {"coordinates":[0.101585,52.686039],"type":"Point"}
}