{
  "type": "Feature",
  "properties": {
    "iso:country":"GB",
    "sg:address":"114 Leavesden Road",
    "sg:city":"Watford",
    "sg:classifiers":[
        {
            "category":"Personal",
            "subcategory":"Sauna",
            "type":"Services"
        }
    ],
    "sg:phone":"+44 1923 240037",
    "sg:postcode":"WD24 5EG",
    "sg:province":"Hertfordshire",
    "wof:name":"Tahiti Health Salon",
    "wof:placetype":"venue"
},
  "geometry": {"coordinates":[-0.40078,51.670536],"type":"Point"}
}