{
  "type": "Feature",
  "properties": {
    "addr:full":"School Croft, Brotherton Knottingley North Yorkshire WF11 9ES",
    "addr:postcode":"wf11 9es",
    "addr:street":"Croft",
    "iso:country":"GB",
    "sg:address":"School Croft, Brotherton",
    "sg:city":"Knottingley",
    "sg:classifiers":[
        {
            "category":"Recreation",
            "subcategory":"Campground",
            "type":"Entertainment"
        }
    ],
    "sg:phone":"+44 1977 607153",
    "sg:postcode":"WF11 9ES",
    "sg:province":"North Yorkshire",
    "sg:tags":[
        "caravan",
        "park"
    ],
    "wof:name":"Lyndale Caravan Park",
    "wof:placetype":"venue"
},
  "geometry": {"coordinates":[-1.2712060213,53.7289886475],"type":"Point"}
}