{
  "type": "Feature",
  "properties": {
    "addr:full":"118 Brackensdale Avenue Derby Derbyshire DE22 4AE",
    "addr:housenumber":"118",
    "addr:postcode":"de22 4ae",
    "addr:street":"Brackensdale Avenue",
    "iso:country":"GB",
    "sg:address":"118 Brackensdale Avenue",
    "sg:city":"Derby",
    "sg:classifiers":[
        {
            "category":"Building & Trades",
            "subcategory":"Plumbing",
            "type":"Services"
        }
    ],
    "sg:postcode":"DE22 4AE",
    "sg:province":"Derbyshire",
    "sg:tags":[
        "plumber",
        "heating"
    ],
    "wof:name":"Brian J Upton",
    "wof:placetype":"venue"
},
  "geometry": {"coordinates":[-1.5178489685,52.9247665405],"type":"Point"}
}