{
  "type": "Feature",
  "properties": {
    "addr:full":"42c Sea Road, Boscombe Bournemouth Dorset BH5 1BQ",
    "addr:housenumber":"42c",
    "addr:postcode":"bh5 1bq",
    "addr:street":"Sea Road",
    "iso:country":"GB",
    "sg:address":"42c Sea Road, Boscombe",
    "sg:city":"Bournemouth",
    "sg:classifiers":[
        {
            "category":"Fast Food",
            "type":"Food & Drink"
        },
        {
            "category":"Food & Beverages",
            "subcategory":"Meat & Fish",
            "type":"Retail Goods"
        }
    ],
    "sg:phone":"+44 1202 309238",
    "sg:postcode":"BH5 1BQ",
    "sg:province":"Dorset",
    "sg:tags":[
        "seafood",
        "take",
        "away"
    ],
    "wof:name":"Trawlers",
    "wof:placetype":"venue"
},
  "geometry": {"coordinates":[-1.8418480158,50.721736908],"type":"Point"}
}