{
  "type": "Feature",
  "properties": {
    "iso:country":"GB",
    "sg:address":"High Street, Maltby",
    "sg:city":"Rotherham",
    "sg:classifiers":[
        {
            "category":"Education",
            "subcategory":"Library",
            "type":"Public Place"
        },
        {
            "category":"Government",
            "subcategory":"Office",
            "type":"Public Place"
        }
    ],
    "sg:phone":"+44 1709 813034",
    "sg:postcode":"S66 8LD",
    "sg:province":"South Yorkshire",
    "sg:tags":[
        "book",
        "local"
    ],
    "wof:name":"Maltby Community Library",
    "wof:placetype":"venue"
},
  "geometry": {"coordinates":[-1.2062649727,53.4225616455],"type":"Point"}
}