{
  "type": "Feature",
  "properties": {
    "iso:country":"GB",
    "sg:address":"24 Byron Avenue",
    "sg:city":"Sutton",
    "sg:classifiers":[
        {
            "category":"Professional",
            "type":"Services"
        }
    ],
    "sg:postcode":"SM1 3RA",
    "sg:province":"Surrey",
    "sg:tags":[
        "reflexologists"
    ],
    "wof:name":"Dana Sanhaji",
    "wof:placetype":"venue"
},
  "geometry": {"coordinates":[-0.179361999,51.3669700623],"type":"Point"}
}