{
  "type": "Feature",
  "properties": {
    "addr:full":"Amex House, North End Road Wembley Greater London HA9 0UU",
    "addr:postcode":"ha9 0uu",
    "addr:street":"North End Road",
    "iso:country":"GB",
    "sg:address":"Amex House, North End Road",
    "sg:city":"Wembley",
    "sg:classifiers":[
        {
            "category":"Professional",
            "subcategory":"Engineering",
            "type":"Services"
        },
        {
            "category":"Building & Trades",
            "subcategory":"Construction",
            "type":"Services"
        }
    ],
    "sg:phone":"+44 20 8900 2889",
    "sg:postcode":"HA9 0UU",
    "sg:province":"Greater London",
    "sg:tags":[
        "contractor",
        "electrical",
        "engineer"
    ],
    "wof:name":"Pirelli Construction Co",
    "wof:placetype":"venue"
},
  "geometry": {"coordinates":[-0.2782309949,51.5621604919],"type":"Point"}
}