{
  "type": "Feature",
  "properties": {
    "addr:full":"42 St Lukes Terrace, Pallion Sunderland Tyne and Wear SR4 6NF",
    "addr:housenumber":"42",
    "addr:postcode":"sr4 6nf",
    "addr:street":"St Lukes Terrace",
    "iso:country":"GB",
    "sg:address":"42 St Lukes Terrace, Pallion",
    "sg:city":"Sunderland",
    "sg:classifiers":[
        {
            "category":"Home & Garden",
            "subcategory":"Carpets & Floor Coverings",
            "type":"Retail Goods"
        }
    ],
    "sg:phone":"+44 191 548 9410",
    "sg:postcode":"SR4 6NF",
    "sg:province":"Tyne and Wear",
    "sg:tags":[
        "carpets",
        "rug",
        "matting"
    ],
    "wof:name":"Pallion Carpets",
    "wof:placetype":"venue"
},
  "geometry": {"coordinates":[-1.414395,54.90789],"type":"Point"}
}