{
  "type": "Feature",
  "properties": {
    "iso:country":"GB",
    "sg:address":"40 Duke Street",
    "sg:city":"Brighton",
    "sg:classifiers":[
        {
            "category":"Arts & Performance",
            "subcategory":"Art Gallery",
            "type":"Entertainment"
        },
        {
            "category":"Museum",
            "subcategory":"Art Museum",
            "type":"Entertainment"
        }
    ],
    "sg:phone":"+44 1273 778646",
    "sg:postcode":"BN1 1AG",
    "sg:province":"East Sussex",
    "wof:name":"Fabrica",
    "wof:placetype":"venue"
},
  "geometry": {"coordinates":[-0.142469,50.822731],"type":"Point"}
}