{
  "type": "Feature",
  "properties": {
    "addr:full":"84 Temple Chambers, Temple Ave London Greater London EC4Y 0HP",
    "addr:housenumber":"84",
    "addr:postcode":"ec4y 0hp",
    "addr:street":"Temple Chambers Temple Ave",
    "iso:country":"GB",
    "sg:address":"84 Temple Chambers, Temple Ave",
    "sg:city":"London",
    "sg:classifiers":[
        {
            "category":"Wholesale",
            "subcategory":"Vending Machines",
            "type":"Manufacturing & Wholesale Goods"
        }
    ],
    "sg:phone":"+44 1234 213571",
    "sg:postcode":"EC4Y 0HP",
    "sg:province":"Greater London",
    "sg:tags":[
        "sale"
    ],
    "wof:name":"Apogee International Ltd",
    "wof:placetype":"venue"
},
  "geometry": {"coordinates":[-0.10832,51.511902],"type":"Point"}
}