{
  "type": "Feature",
  "properties": {
    "iso:country":"GB",
    "sg:address":"Durrington Down Farm, Larkhill",
    "sg:city":"Salisbury",
    "sg:classifiers":[
        {
            "category":"Farming",
            "subcategory":"Livestock Farm",
            "type":"Manufacturing & Wholesale Goods"
        }
    ],
    "sg:phone":"+44 1980 653676",
    "sg:postcode":"SP4 8NU",
    "sg:province":"Hampshire",
    "sg:tags":[
        "others"
    ],
    "wof:name":"I R Baxter",
    "wof:placetype":"venue"
},
  "geometry": {"coordinates":[-1.773042,51.202339],"type":"Point"}
}