{
  "type": "Feature",
  "properties": {
    "iso:country":"GB",
    "sg:address":"142 All Saints Rd, Kings Heath",
    "sg:city":"Birmingham",
    "sg:classifiers":[
        {
            "category":"Professional",
            "subcategory":"Computer Services",
            "type":"Services"
        }
    ],
    "sg:phone":"+44 121 444 5662",
    "sg:postcode":"B14 6AT",
    "sg:province":"West Midlands",
    "sg:tags":[
        "system",
        "software"
    ],
    "wof:name":"D B Systems",
    "wof:placetype":"venue"
},
  "geometry": {"coordinates":[-1.895246,52.427319],"type":"Point"}
}