{
  "type": "Feature",
  "properties": {
    "iso:country":"GB",
    "sg:address":"14 Town End, Bolsover",
    "sg:city":"Chesterfield",
    "sg:classifiers":[
        {
            "category":"Real Estate",
            "subcategory":"Real Estate Agent",
            "type":"Services"
        }
    ],
    "sg:phone":"+44 1246 823259",
    "sg:postcode":"S44 6DT",
    "sg:province":"Derbyshire",
    "wof:name":"Wilkins Vardy Residential",
    "wof:placetype":"venue"
},
  "geometry": {"coordinates":[-1.2903490067,53.2293128967],"type":"Point"}
}