{
  "type": "Feature",
  "properties": {
    "iso:country":"GB",
    "sg:address":"19 Brook End, Parr",
    "sg:city":"St Helens",
    "sg:classifiers":[
        {
            "category":"Home & Garden",
            "subcategory":"Home Furnishings",
            "type":"Retail Goods"
        }
    ],
    "sg:postcode":"WA9 3RS",
    "sg:province":"Cheshire",
    "sg:tags":[
        "blind",
        "curtain",
        "fitting"
    ],
    "wof:name":"Home Touch Curtains",
    "wof:placetype":"venue"
},
  "geometry": {"coordinates":[-2.689203,53.44376],"type":"Point"}
}