{
  "type": "Feature",
  "properties": {
    "iso:country":"GB",
    "sg:address":"3 Kingsley Road",
    "sg:city":"Norwich",
    "sg:classifiers":[
        {
            "category":"Travel",
            "subcategory":"Hotels & Motels",
            "type":"Entertainment"
        }
    ],
    "sg:postcode":"NR1 3RB",
    "sg:province":"Norfolk",
    "sg:tags":[
        "house",
        "guest"
    ],
    "wof:name":"Kingsley Lodge",
    "wof:placetype":"venue"
},
  "geometry": {"coordinates":[1.288931,52.622864],"type":"Point"}
}