{
  "type": "Feature",
  "properties": {
    "addr:full":"Unit E1 Harlow Seed Bed Centre, Lovet Road Harlow Essex CM19 5AF",
    "addr:housenumber":"e1",
    "addr:postcode":"cm19 5af",
    "addr:street":"Lovet Road",
    "iso:country":"GB",
    "sg:address":"Unit E1 Harlow Seed Bed Centre, Lovet Road",
    "sg:city":"Harlow",
    "sg:classifiers":[
        {
            "category":"Professional",
            "subcategory":"Printing & Photocopies",
            "type":"Services"
        }
    ],
    "sg:postcode":"CM19 5AF",
    "sg:province":"Essex",
    "sg:tags":[
        "trophy"
    ],
    "wof:name":"Harlow Trophy Sports",
    "wof:placetype":"venue"
},
  "geometry": {"coordinates":[0.0748099983,51.7637481689],"type":"Point"}
}