{
  "type": "Feature",
  "properties": {
    "iso:country":"GB",
    "sg:address":"Duke Street",
    "sg:city":"Stoke-on-trent",
    "sg:classifiers":[
        {
            "category":"Professional",
            "subcategory":"Engineering",
            "type":"Services"
        }
    ],
    "sg:phone":"+44 1782 316589",
    "sg:postcode":"ST4 3NR",
    "sg:province":"Staffordshire",
    "wof:name":"David Hulse Engineering & Fabrication",
    "wof:placetype":"venue"
},
  "geometry": {"coordinates":[-2.152514,52.995838],"type":"Point"}
}