{
  "type": "Feature",
  "properties": {
    "addr:full":"42 Courneny Crescent Carshalton Surrey SM5 4LZ",
    "addr:housenumber":"42",
    "addr:postcode":"sm5 4lz",
    "addr:street":"Courneny Crescent",
    "iso:country":"GB",
    "sg:address":"42 Courneny Crescent",
    "sg:city":"Carshalton",
    "sg:classifiers":[
        {
            "category":"Parking",
            "type":"Transportation"
        }
    ],
    "sg:phone":"+44 20 8661 1746",
    "sg:postcode":"SM5 4LZ",
    "sg:province":"Surrey",
    "sg:tags":[
        "car",
        "valet"
    ],
    "wof:name":"Grosvenor Mobile Car Valeting Service",
    "wof:placetype":"venue"
},
  "geometry": {"coordinates":[-0.167522,51.351265],"type":"Point"}
}