{
  "type": "Feature",
  "properties": {
    "iso:country":"GB",
    "sg:address":"Unit 6 Salnex Road, Cross Grn",
    "sg:city":"Leeds",
    "sg:classifiers":[
        {
            "category":"Food & Beverages",
            "subcategory":"Liquor & Beverages",
            "type":"Retail Goods"
        }
    ],
    "sg:phone":"+44 113 248 7474",
    "sg:postcode":"LS9 0SR",
    "sg:province":"West Yorkshire",
    "sg:tags":[
        "drink",
        "soft"
    ],
    "wof:name":"Cabana Soft Drinks Ltd.",
    "wof:placetype":"venue"
},
  "geometry": {"coordinates":[-1.49979,53.787491],"type":"Point"}
}