{
  "type": "Feature",
  "properties": {
    "addr:full":"79 High Street Polegate East Sussex BN26 6AE",
    "addr:housenumber":"79",
    "addr:postcode":"bn26 6ae",
    "addr:street":"High Street Polegate",
    "iso:country":"GB",
    "sg:address":"79 High Street",
    "sg:city":"Polegate",
    "sg:classifiers":[
        {
            "category":"Shopping",
            "subcategory":"Clothing, Apparel, & Fashions",
            "type":"Retail Goods"
        }
    ],
    "sg:phone":"+44 1323 483740",
    "sg:postcode":"BN26 6AE",
    "sg:province":"East Sussex",
    "sg:tags":[
        "menswear"
    ],
    "wof:name":"David Buck the Mans Shop",
    "wof:placetype":"venue"
},
  "geometry": {"coordinates":[0.244257,50.822975],"type":"Point"}
}