{
  "type": "Feature",
  "properties": {
    "addr:full":"St Francis, Silver Street, Shepton Beaucham Ilminster Somerset TA19 0JZ",
    "addr:postcode":"ta19 0jz",
    "addr:street":"Silver Street",
    "iso:country":"GB",
    "sg:address":"St Francis, Silver Street, Shepton Beaucham",
    "sg:city":"Ilminster",
    "sg:classifiers":[
        {
            "category":"Professional",
            "subcategory":"Engineering",
            "type":"Services"
        }
    ],
    "sg:phone":"+44 1460 240499",
    "sg:postcode":"TA19 0JZ",
    "sg:province":"Somerset",
    "sg:tags":[
        "precision",
        "engineer"
    ],
    "wof:name":"H J Jennings & Co.",
    "wof:placetype":"venue"
},
  "geometry": {"coordinates":[-2.8563139439,50.9294204712],"type":"Point"}
}