{
  "type": "Feature",
  "properties": {
    "iso:country":"GB",
    "sg:address":"5 Abercorn Terrace",
    "sg:city":"Edinburgh",
    "sg:classifiers":[
        {
            "category":"Travel",
            "subcategory":"Hotels & Motels",
            "type":"Entertainment"
        }
    ],
    "sg:postcode":"EH15 2DD",
    "sg:province":"City of Edinburgh",
    "sg:tags":[
        "house",
        "self",
        "guest",
        "catering"
    ],
    "wof:name":"Number 5 Self Catering Apartments",
    "wof:placetype":"venue"
},
  "geometry": {"coordinates":[-3.107696,55.951031],"type":"Point"}
}