{
  "type": "Feature",
  "properties": {
    "addr:full":"Trevellan Road Falmouth Cornwall TR11 5NE",
    "addr:postcode":"tr11 5ne",
    "addr:street":"Trevellan Road",
    "iso:country":"GB",
    "sg:address":"Trevellan Road",
    "sg:city":"Falmouth",
    "sg:classifiers":[
        {
            "category":"Government",
            "subcategory":"Post Office",
            "type":"Public Place"
        }
    ],
    "sg:phone":"+44 1326 372619",
    "sg:postcode":"TR11 5NE",
    "sg:province":"Cornwall",
    "wof:name":"Mylor Bridge Post Office",
    "wof:placetype":"venue"
},
  "geometry": {"coordinates":[-5.0738039017,50.1839790344],"type":"Point"}
}