{
  "type": "Feature",
  "properties": {
    "addr:full":"24 Ashford Rd Maidstone Kent ME14 5BH",
    "addr:housenumber":"24",
    "addr:postcode":"me14 5bh",
    "addr:street":"Ashford Rd",
    "iso:country":"GB",
    "sg:address":"24 Ashford Rd",
    "sg:city":"Maidstone",
    "sg:classifiers":[
        {
            "category":"Health Services",
            "subcategory":"Dentist",
            "type":"Services"
        }
    ],
    "sg:phone":"+44 1622 752944",
    "sg:postcode":"ME14 5BH",
    "sg:province":"Kent",
    "wof:name":"N Beurne",
    "wof:placetype":"venue"
},
  "geometry": {"coordinates":[0.530951,51.273174],"type":"Point"}
}