{
  "type": "Feature",
  "properties": {
    "iso:country":"GB",
    "sg:address":"Concept House, 11 Fairbairn Road",
    "sg:city":"Livingston",
    "sg:classifiers":[
        {
            "category":"Shopping",
            "subcategory":"Stationery & Office Supplies",
            "type":"Retail Goods"
        },
        {
            "category":"Professional",
            "subcategory":"Printing & Photocopies",
            "type":"Services"
        }
    ],
    "sg:phone":"+44 1506 416161",
    "sg:postcode":"EH54 6TS",
    "sg:province":"West Lothian",
    "sg:tags":[
        "machine",
        "facsimile",
        "duplicating",
        "copying"
    ],
    "wof:name":"Concept Group (Sales) Ltd.",
    "wof:placetype":"venue"
},
  "geometry": {"coordinates":[-3.5285360813,55.8915100098],"type":"Point"}
}