{
  "type": "Feature",
  "properties": {
    "addr:full":"Bolham Road Tiverton Devon EX16 6SH",
    "addr:postcode":"ex16 6sh",
    "addr:street":"Bolham Road",
    "iso:country":"GB",
    "sg:address":"Bolham Road",
    "sg:city":"Tiverton",
    "sg:classifiers":[
        {
            "category":"Professional",
            "subcategory":"Management & Consulting",
            "type":"Services"
        },
        {
            "category":"Education",
            "subcategory":"University",
            "type":"Public Place"
        }
    ],
    "sg:phone":"+44 1884 235352",
    "sg:postcode":"EX16 6SH",
    "sg:province":"Devon",
    "sg:tags":[
        "consultant",
        "training",
        "college",
        "higher"
    ],
    "wof:name":"East Devon College Of Further Education",
    "wof:placetype":"venue"
},
  "geometry": {"coordinates":[-3.492299,50.913834],"type":"Point"}
}