{
  "type": "Feature",
  "properties": {
    "addr:full":"Whites Farm, Baxterley Atherstone Leicestershire CV9 2LN",
    "addr:postcode":"cv9 2ln",
    "iso:country":"GB",
    "sg:address":"Whites Farm, Baxterley",
    "sg:city":"Atherstone",
    "sg:classifiers":[
        {
            "category":"Farming",
            "subcategory":"Farm",
            "type":"Manufacturing & Wholesale Goods"
        }
    ],
    "sg:postcode":"CV9 2LN",
    "sg:province":"Leicestershire",
    "sg:tags":[
        "mixed",
        "crop"
    ],
    "wof:name":"Hayward,J W,",
    "wof:placetype":"venue"
},
  "geometry": {"coordinates":[-1.5918279886,52.5700569153],"type":"Point"}
}