{
  "type": "Feature",
  "properties": {
    "iso:country":"GB",
    "sg:address":"46 Dunedin Drive, East Kilbride",
    "sg:city":"Glasgow",
    "sg:classifiers":[
        {
            "category":"Autos & Motor Vehicles",
            "subcategory":"Motorcycle Sales",
            "type":"Retail Goods"
        }
    ],
    "sg:phone":"+44 1355 229555",
    "sg:postcode":"G75 8QG",
    "sg:province":"South Lanarkshire",
    "sg:tags":[
        "chauffeur",
        "driven",
        "car"
    ],
    "wof:name":"Taxi Cabs of East Kilbride",
    "wof:placetype":"venue"
},
  "geometry": {"coordinates":[-4.213244,55.758987],"type":"Point"}
}