{
  "type": "Feature",
  "properties": {
    "addr:full":"26-28 Goodall Street Walsall West Midlands WS1 1QL",
    "addr:housenumber":"26-28",
    "addr:postcode":"ws1 1ql",
    "addr:street":"Goodall Street",
    "iso:country":"GB",
    "sg:address":"26-28 Goodall Street",
    "sg:city":"Walsall",
    "sg:classifiers":[
        {
            "category":"Professional",
            "subcategory":"Detective & Security Services",
            "type":"Services"
        }
    ],
    "sg:postcode":"WS1 1QL",
    "sg:province":"West Midlands",
    "wof:name":"Centurion Security Shutters Ltd",
    "wof:placetype":"venue"
},
  "geometry": {"coordinates":[-1.9785629511,52.5835571289],"type":"Point"}
}