{
  "type": "Feature",
  "properties": {
    "iso:country":"GB",
    "sg:address":"25 Stamford New Road",
    "sg:city":"Altrincham",
    "sg:classifiers":[
        {
            "category":"Home & Garden",
            "subcategory":"Furniture",
            "type":"Retail Goods"
        }
    ],
    "sg:phone":"+44 161 928 0216",
    "sg:postcode":"WA14 1EB",
    "sg:province":"Cheshire",
    "wof:name":"Sharps Bedrooms",
    "wof:placetype":"venue"
},
  "geometry": {"coordinates":[-2.34984,53.386127],"type":"Point"}
}