{
  "type": "Feature",
  "properties": {
    "addr:full":"46 Mountside Guildford Surrey GU2 4JE",
    "addr:housenumber":"46",
    "addr:postcode":"gu2 4je",
    "addr:street":"Mountside",
    "iso:country":"GB",
    "sg:address":"46 Mountside",
    "sg:city":"Guildford",
    "sg:classifiers":[
        {
            "category":"Professional",
            "subcategory":"Management & Consulting",
            "type":"Services"
        }
    ],
    "sg:phone":"+44 1483 302303",
    "sg:postcode":"GU2 4JE",
    "sg:province":"Surrey",
    "sg:tags":[
        "consultant",
        "business"
    ],
    "wof:name":"S - M Consulting Ltd.",
    "wof:placetype":"venue"
},
  "geometry": {"coordinates":[-0.5846440196,51.2319030762],"type":"Point"}
}