{
  "type": "Feature",
  "properties": {
    "addr:full":"Wellsyke Rd, Adwick Le Street Doncaster North Yorkshire DN6 7DU",
    "addr:postcode":"dn6 7du",
    "addr:street":"Wellsyke Rd",
    "iso:country":"GB",
    "sg:address":"Wellsyke Rd, Adwick Le Street",
    "sg:city":"Doncaster",
    "sg:classifiers":[
        {
            "category":"Professional",
            "subcategory":"Art Services",
            "type":"Services"
        }
    ],
    "sg:phone":"+44 1302 338400",
    "sg:postcode":"DN6 7DU",
    "sg:province":"North Yorkshire",
    "sg:tags":[
        "graphic",
        "designer"
    ],
    "wof:name":"Nuveaux Designs Ltd",
    "wof:placetype":"venue"
},
  "geometry": {"coordinates":[-1.173904,53.578476],"type":"Point"}
}