{
  "type": "Feature",
  "properties": {
    "addr:full":"4b Bold Street Warrington Cheshire WA1 1DR",
    "addr:housenumber":"4b",
    "addr:postcode":"wa1 1dr",
    "addr:street":"Bold Street",
    "iso:country":"GB",
    "sg:address":"4b Bold Street",
    "sg:city":"Warrington",
    "sg:classifiers":[
        {
            "category":"Professional",
            "type":"Services"
        }
    ],
    "sg:phone":"+44 1925 629797",
    "sg:postcode":"WA1 1DR",
    "sg:province":"Cheshire",
    "sg:tags":[
        "caterer"
    ],
    "wof:name":"Brunches",
    "wof:placetype":"venue"
},
  "geometry": {"coordinates":[-2.5958631039,53.3885993958],"type":"Point"}
}