{
  "type": "Feature",
  "properties": {
    "addr:full":"Stand 62 Market Pavilion, New Spitalfields Market London Greater London E10 5SJ",
    "addr:housenumber":"62",
    "addr:postcode":"e10 5sj",
    "addr:street":"Market Pavilion",
    "iso:country":"GB",
    "sg:address":"Stand 62 Market Pavilion, New Spitalfields Market",
    "sg:city":"London",
    "sg:classifiers":[
        {
            "category":"Wholesale",
            "subcategory":"Fruits & Vegetables",
            "type":"Manufacturing & Wholesale Goods"
        }
    ],
    "sg:phone":"+44 20 8558 9868",
    "sg:postcode":"E10 5SJ",
    "sg:province":"Greater London",
    "wof:name":"Walter Braund (Spitalfields) Ltd.",
    "wof:placetype":"venue"
},
  "geometry": {"coordinates":[-0.02097,51.5571899414],"type":"Point"}
}