{
  "type": "Feature",
  "properties": {
    "iso:country":"GB",
    "sg:address":"Lashenden Farm, Headcorn Rd, Biddenden",
    "sg:city":"Ashford",
    "sg:classifiers":[
        {
            "category":"Farming",
            "subcategory":"Livestock Farm",
            "type":"Manufacturing & Wholesale Goods"
        }
    ],
    "sg:phone":"+44 1580 291363",
    "sg:postcode":"TN27 8JZ",
    "sg:province":"Kent",
    "sg:tags":[
        "others"
    ],
    "wof:name":"Weeks,S,& Sons",
    "wof:placetype":"venue"
},
  "geometry": {"coordinates":[0.6423280239,51.1150894165],"type":"Point"}
}