{
  "type": "Feature",
  "properties": {
    "addr:full":"Crossbrook, Cheshunt Waltham Cross Essex EN8 7RQ",
    "addr:postcode":"en8 7rq",
    "addr:street":"Waltham Cross",
    "iso:country":"GB",
    "sg:address":"Crossbrook, Cheshunt",
    "sg:city":"Waltham Cross",
    "sg:classifiers":[
        {
            "category":"Home & Garden",
            "subcategory":"Home Furnishings",
            "type":"Retail Goods"
        }
    ],
    "sg:phone":"+44 1992 628265",
    "sg:postcode":"EN8 7RQ",
    "sg:province":"Essex",
    "sg:tags":[
        "merchant",
        "diy",
        "decorators'"
    ],
    "wof:name":"County Decorating Supplies",
    "wof:placetype":"venue"
},
  "geometry": {"coordinates":[-0.033814,51.69051],"type":"Point"}
}