{
  "type": "Feature",
  "properties": {
    "addr:full":"21 Argyll St Shrewsbury Shropshire SY1 2SF",
    "addr:housenumber":"21",
    "addr:postcode":"sy1 2sf",
    "addr:street":"Argyll St",
    "iso:country":"GB",
    "sg:address":"21 Argyll St",
    "sg:city":"Shrewsbury",
    "sg:classifiers":[
        {
            "category":"Communications",
            "subcategory":"Film & Video Production",
            "type":"Services"
        }
    ],
    "sg:phone":"+44 1743 355170",
    "sg:postcode":"SY1 2SF",
    "sg:province":"Shropshire",
    "sg:tags":[
        "illustrator",
        "artist"
    ],
    "wof:name":"Chebsey Shane Illustrator",
    "wof:placetype":"venue"
},
  "geometry": {"coordinates":[-2.741829,52.716129],"type":"Point"}
}