{
  "type": "Feature",
  "properties": {
    "addr:full":"60 Seymour Rd, Mannammead Plymouth Devon PL3 5AY",
    "addr:housenumber":"60",
    "addr:postcode":"pl3 5ay",
    "addr:street":"Seymour Rd Mannammead",
    "iso:country":"GB",
    "sg:address":"60 Seymour Rd, Mannammead",
    "sg:city":"Plymouth",
    "sg:classifiers":[
        {
            "category":"Manufacturing",
            "subcategory":"Building Materials",
            "type":"Manufacturing & Wholesale Goods"
        }
    ],
    "sg:phone":"+44 1752 663633",
    "sg:postcode":"PL3 5AY",
    "sg:province":"Devon",
    "sg:tags":[
        "mnfr",
        "loose",
        "cover"
    ],
    "wof:name":"Warsols Loose Covers",
    "wof:placetype":"venue"
},
  "geometry": {"coordinates":[-4.1247119904,50.3849334717],"type":"Point"}
}