{
  "type": "Feature",
  "properties": {
    "addr:full":"De Novo House Low Road, Thurlton Norwich Norfolk NR14 6RL",
    "addr:postcode":"nr14 6rl",
    "addr:street":"De;Low Road",
    "iso:country":"GB",
    "sg:address":"De Novo House Low Road, Thurlton",
    "sg:city":"Norwich",
    "sg:classifiers":[
        {
            "category":"Banks & Credit Unions",
            "subcategory":"Financial Services",
            "type":"Services"
        }
    ],
    "sg:phone":"+44 1508 548668",
    "sg:postcode":"NR14 6RL",
    "sg:province":"Norfolk",
    "sg:tags":[
        "consultant"
    ],
    "wof:name":"Finance Management Services Ltd.",
    "wof:placetype":"venue"
},
  "geometry": {"coordinates":[1.5572400093,52.5300254822],"type":"Point"}
}