{
  "type": "Feature",
  "properties": {
    "addr:full":"318 Cowbridge Road West Cardiff Cardiff CF5 5TD",
    "addr:housenumber":"318",
    "addr:postcode":"cf5 5td",
    "addr:street":"Cowbridge Road West",
    "iso:country":"GB",
    "sg:address":"318 Cowbridge Road West",
    "sg:city":"Cardiff",
    "sg:classifiers":[
        {
            "category":"Social Services",
            "subcategory":"Child Care",
            "type":"Services"
        }
    ],
    "sg:phone":"+44 29 2059 1392",
    "sg:postcode":"CF5 5TD",
    "sg:province":"Cardiff",
    "sg:tags":[
        "children's",
        "home"
    ],
    "wof:name":"Crosslands Childrens Home",
    "wof:placetype":"venue"
},
  "geometry": {"coordinates":[-3.247279,51.476318],"type":"Point"}
}