{
  "type": "Feature",
  "properties": {
    "iso:country":"GB",
    "sg:address":"Queens Walk, The Meadows",
    "sg:city":"Nottingham",
    "sg:classifiers":[
        {
            "category":"Place Of Worship",
            "type":"Public Place"
        }
    ],
    "sg:phone":"+44 115 986 5633",
    "sg:postcode":"NG2 2DF",
    "sg:province":"Nottinghamshire",
    "wof:name":"Pilgrim Holiness Church",
    "wof:placetype":"venue"
},
  "geometry": {"coordinates":[-1.153448,52.939274],"type":"Point"}
}