{
  "type": "Feature",
  "properties": {
    "addr:full":"The Market Store, Station Road Redruth Cornwall TR15 2BT",
    "addr:postcode":"tr15 2bt",
    "addr:street":"Station Road",
    "iso:country":"GB",
    "sg:address":"The Market Store, Station Road",
    "sg:city":"Redruth",
    "sg:classifiers":[
        {
            "category":"Shopping",
            "subcategory":"Used Merchandise",
            "type":"Retail Goods"
        }
    ],
    "sg:postcode":"TR15 2BT",
    "sg:province":"Cornwall",
    "sg:tags":[
        "furniture"
    ],
    "wof:name":"Acorn Furniture",
    "wof:placetype":"venue"
},
  "geometry": {"coordinates":[-5.2294340134,50.232509613],"type":"Point"}
}