{
  "type": "Feature",
  "properties": {
    "iso:country":"GB",
    "sg:address":"The Doctors Surgery",
    "sg:city":"Exeter",
    "sg:classifiers":[
        {
            "category":"Health Services",
            "subcategory":"Health Practitioner",
            "type":"Services"
        }
    ],
    "sg:phone":"+44 1392 841022",
    "sg:postcode":"EX5 5NT",
    "sg:province":"Devon",
    "sg:tags":[
        "acupuncture"
    ],
    "wof:name":"R B Hill",
    "wof:placetype":"venue"
},
  "geometry": {"coordinates":[-3.5269589424,50.8088226318],"type":"Point"}
}