{
  "type": "Feature",
  "properties": {
    "addr:full":"49 Swan Lane Wickford Essex SS11 7DB",
    "addr:housenumber":"49",
    "addr:postcode":"ss11 7db",
    "addr:street":"Swan Lane",
    "iso:country":"GB",
    "sg:address":"49 Swan Lane",
    "sg:city":"Wickford",
    "sg:classifiers":[
        {
            "category":"Retail",
            "subcategory":"Auto Repair",
            "type":"Services"
        }
    ],
    "sg:phone":"+44 1268 575046",
    "sg:postcode":"SS11 7DB",
    "sg:province":"Essex",
    "sg:tags":[
        "engine",
        "car",
        "specialist"
    ],
    "wof:name":"Car Care",
    "wof:placetype":"venue"
},
  "geometry": {"coordinates":[0.5216199756,51.6169319153],"type":"Point"}
}