{
  "type": "Feature",
  "properties": {
    "addr:full":"Unit 2 Ham Road Shoreham-by-sea West Sussex BN43 6PA",
    "addr:housenumber":"unit 2",
    "addr:postcode":"bn43 6pa",
    "addr:street":"Ham Road",
    "iso:country":"GB",
    "sg:address":"Unit 2 Ham Road",
    "sg:city":"Shoreham-by-sea",
    "sg:classifiers":[
        {
            "category":"Fast Food",
            "type":"Food & Drink"
        }
    ],
    "sg:phone":"+44 1273 463030",
    "sg:postcode":"BN43 6PA",
    "sg:province":"West Sussex",
    "sg:tags":[
        "away",
        "take"
    ],
    "wof:name":"Why Not (Restaurants) Ltd.",
    "wof:placetype":"venue"
},
  "geometry": {"coordinates":[-0.271189,50.833874],"type":"Point"}
}