{
  "type": "Feature",
  "properties": {
    "iso:country":"GB",
    "sg:address":"Dyffryn Nantlle Entprse Centre, Llanllyfni Road",
    "sg:city":"Caernarfon",
    "sg:classifiers":[
        {
            "category":"Farming",
            "subcategory":"Farm",
            "type":"Manufacturing & Wholesale Goods"
        }
    ],
    "sg:phone":"+44 1286 881849",
    "sg:postcode":"LL54 6DB",
    "sg:province":"Gwynedd",
    "sg:tags":[
        "egg",
        "producer"
    ],
    "wof:name":"David Ian Jones",
    "wof:placetype":"venue"
},
  "geometry": {"coordinates":[-4.283814,53.041245],"type":"Point"}
}