{
  "type": "Feature",
  "properties": {
    "iso:country":"GB",
    "sg:address":"23 Waterden Road",
    "sg:city":"Guildford",
    "sg:classifiers":[
        {
            "category":"Place Of Worship",
            "type":"Public Place"
        },
        {
            "category":"Education",
            "subcategory":"Preschool",
            "type":"Public Place"
        }
    ],
    "sg:phone":"+44 1483 568662",
    "sg:postcode":"GU1 2AZ",
    "sg:province":"Surrey",
    "sg:tags":[
        "pre",
        "school",
        "playgroups",
        "pre-school"
    ],
    "wof:name":"CHRIST CHURCH PLAYGROUP",
    "wof:placetype":"venue"
},
  "geometry": {"coordinates":[-0.561993,51.238853],"type":"Point"}
}