{
  "type": "Feature",
  "properties": {
    "addr:full":"3 Anchor Road, Longton Stoke-on-trent Staffordshire ST3 1SU",
    "addr:housenumber":"3",
    "addr:postcode":"staffordshire st3 1su",
    "addr:street":"Anchor Road",
    "iso:country":"GB",
    "sg:address":"3 Anchor Road, Longton",
    "sg:city":"Stoke-on-trent",
    "sg:classifiers":[
        {
            "category":"Real Estate",
            "subcategory":"Architect",
            "type":"Services"
        }
    ],
    "sg:phone":"+44 1782 312630",
    "sg:postcode":"ST3 1SU",
    "sg:province":"Staffordshire",
    "wof:name":"The Harrison Wood Partnership",
    "wof:placetype":"venue"
},
  "geometry": {"coordinates":[-2.1309258938,52.9911727905],"type":"Point"}
}