{
  "type": "Feature",
  "properties": {
    "addr:full":"79 Ellesmere Street Glasgow Glasgow City G22 5QT",
    "addr:housenumber":"79",
    "addr:postcode":"g22 5qt",
    "addr:street":"Ellesmere Street",
    "iso:country":"GB",
    "sg:address":"79 Ellesmere Street",
    "sg:city":"Glasgow",
    "sg:classifiers":[
        {
            "category":"Personal",
            "subcategory":"Beauty Salon",
            "type":"Services"
        }
    ],
    "sg:postcode":"G22 5QT",
    "sg:province":"Glasgow City",
    "sg:tags":[
        "unisex",
        "hairdresser"
    ],
    "wof:name":"Hair Horizons",
    "wof:placetype":"venue"
},
  "geometry": {"coordinates":[-4.2598900795,55.8778953552],"type":"Point"}
}