{
  "type": "Feature",
  "properties": {
    "addr:full":"Benbow Street London Greater London SE8 3HD",
    "addr:postcode":"se8 3hd",
    "addr:street":"Benbow Street",
    "iso:country":"GB",
    "sg:address":"Benbow Street",
    "sg:city":"London",
    "sg:classifiers":[
        {
            "category":"Government",
            "subcategory":"Office",
            "type":"Public Place"
        }
    ],
    "sg:phone":"+44 20 8692 4328",
    "sg:postcode":"SE8 3HD",
    "sg:province":"Greater London",
    "sg:tags":[
        "local"
    ],
    "wof:name":"Charlotte Turner School",
    "wof:placetype":"venue"
},
  "geometry": {"coordinates":[-0.023979,51.48328],"type":"Point"}
}