{
  "type": "Feature",
  "properties": {
    "addr:full":"23 Gaunt Street Lincoln Lincolnshire LN5 7PU",
    "addr:housenumber":"23",
    "addr:postcode":"ln5 7pu",
    "addr:street":"Gaunt Street",
    "iso:country":"GB",
    "sg:address":"23 Gaunt Street",
    "sg:city":"Lincoln",
    "sg:classifiers":[
        {
            "category":"Professional",
            "subcategory":"Printing & Photocopies",
            "type":"Services"
        }
    ],
    "sg:phone":"+44 1522 532382",
    "sg:postcode":"LN5 7PU",
    "sg:province":"Lincolnshire",
    "sg:tags":[
        "process",
        "screen",
        "printer"
    ],
    "wof:name":"Colour Studios",
    "wof:placetype":"venue"
},
  "geometry": {"coordinates":[-0.545196,53.222591],"type":"Point"}
}