{
  "type": "Feature",
  "properties": {
    "iso:country":"GB",
    "sg:address":"London Road",
    "sg:city":"Ware",
    "sg:classifiers":[
        {
            "category":"Shopping",
            "subcategory":"Computers & Home Electronics",
            "type":"Retail Goods"
        },
        {
            "category":"Home & Garden",
            "subcategory":"Furniture",
            "type":"Retail Goods"
        }
    ],
    "sg:phone":"+44 1920 469241",
    "sg:postcode":"SG12 9QH",
    "sg:province":"Hertfordshire",
    "wof:name":"Wood Bros (Furniture) Ltd.",
    "wof:placetype":"venue"
},
  "geometry": {"coordinates":[-0.029246,51.807411],"type":"Point"}
}