{
  "type": "Feature",
  "properties": {
    "iso:country":"GB",
    "sg:address":"188 Cot Lane, Kingswinford",
    "sg:city":"Brierley Hill",
    "sg:classifiers":[
        {
            "category":"Professional",
            "subcategory":"Detective & Security Services",
            "type":"Services"
        }
    ],
    "sg:postcode":"DY6 9QG",
    "sg:province":"Staffordshire",
    "sg:tags":[
        "alarm",
        "burglar",
        "system"
    ],
    "wof:name":"M G Alarms & Electrics",
    "wof:placetype":"venue"
},
  "geometry": {"coordinates":[-2.171535,52.492771],"type":"Point"}
}