{
  "type": "Feature",
  "properties": {
    "addr:full":"25 Southbourne Gro Bournemouth Dorset BH6 3QS",
    "addr:housenumber":"25",
    "addr:postcode":"bh6 3qs",
    "addr:street":"Southbourne Gro",
    "iso:country":"GB",
    "sg:address":"25 Southbourne Gro",
    "sg:city":"Bournemouth",
    "sg:classifiers":[
        {
            "category":"Shopping",
            "subcategory":"Tobacco",
            "type":"Retail Goods"
        }
    ],
    "sg:phone":"+44 1202 429766",
    "sg:postcode":"BH6 3QS",
    "sg:province":"Dorset",
    "sg:tags":[
        "tobacconist"
    ],
    "wof:name":"The Pipe Shop",
    "wof:placetype":"venue"
},
  "geometry": {"coordinates":[-1.8170200586,50.7263221741],"type":"Point"}
}