{
  "type": "Feature",
  "properties": {
    "iso:country":"GB",
    "sg:address":"Unit 5 Broadmead Business Park, Broadmead Road, Stewartby",
    "sg:city":"Bedford",
    "sg:classifiers":[
        {
            "category":"Autos & Motor Vehicles",
            "subcategory":"Auto Supplies",
            "type":"Retail Goods"
        }
    ],
    "sg:postcode":"MK43 9NX",
    "sg:province":"Bedfordshire",
    "sg:tags":[
        "windscreen"
    ],
    "wof:name":"Autoscreens",
    "wof:placetype":"venue"
},
  "geometry": {"coordinates":[-0.506609,52.066891],"type":"Point"}
}