{
  "type": "Feature",
  "properties": {
    "addr:full":"Enterprise Ho, 24 Leicester Rd Leicester Leicestershire LE9 6JE",
    "addr:housenumber":"24",
    "addr:postcode":"le9 6je",
    "addr:street":"Leicester Rd",
    "iso:country":"GB",
    "sg:address":"Enterprise Ho, 24 Leicester Rd",
    "sg:city":"Leicester",
    "sg:classifiers":[
        {
            "category":"Manufacturing",
            "subcategory":"Textiles",
            "type":"Manufacturing & Wholesale Goods"
        }
    ],
    "sg:phone":"+44 1455 273087",
    "sg:postcode":"LE9 6JE",
    "sg:province":"Leicestershire",
    "sg:tags":[
        "knitwear"
    ],
    "wof:name":"Lewen Design Knitwear Ltd",
    "wof:placetype":"venue"
},
  "geometry": {"coordinates":[-1.23041,52.531528],"type":"Point"}
}