{
  "type": "Feature",
  "properties": {
    "iso:country":"GB",
    "sg:address":"Merry Harriers, Westcott Cullompton",
    "sg:city":"Cullompton",
    "sg:classifiers":[
        {
            "category":"Manufacturing",
            "subcategory":"Petroleum Products",
            "type":"Manufacturing & Wholesale Goods"
        }
    ],
    "sg:phone":"+44 1392 881100",
    "sg:postcode":"EX15 1SA",
    "sg:province":"Devon",
    "sg:tags":[
        "double",
        "glazing"
    ],
    "wof:name":"Westcott Windows",
    "wof:placetype":"venue"
},
  "geometry": {"coordinates":[-3.3926339149,50.858165741],"type":"Point"}
}