{
  "type": "Feature",
  "properties": {
    "addr:full":"Site Office, Longannet Power Station Alloa Clackmannanshire FK10 4AA",
    "addr:postcode":"fk10 4aa",
    "iso:country":"GB",
    "sg:address":"Site Office, Longannet Power Station",
    "sg:city":"Alloa",
    "sg:classifiers":[
        {
            "category":"Professional",
            "subcategory":"Engineering",
            "type":"Services"
        }
    ],
    "sg:phone":"+44 1259 730474",
    "sg:postcode":"FK10 4AA",
    "sg:province":"Clackmannanshire",
    "sg:tags":[
        "electrical",
        "engineer"
    ],
    "wof:name":"James Scott Mechanical & Electrical Services Ltd",
    "wof:placetype":"venue"
},
  "geometry": {"coordinates":[-3.7178359032,56.0827064514],"type":"Point"}
}