{
  "type": "Feature",
  "properties": {
    "addr:full":"Heath Court, Grampian Way, Sinfin Derby Derbyshire DE24 9NG",
    "addr:postcode":"de24 9ng",
    "addr:street":"Heath Court Grampian Way",
    "iso:country":"GB",
    "sg:address":"Heath Court, Grampian Way, Sinfin",
    "sg:city":"Derby",
    "sg:classifiers":[
        {
            "category":"Organizations",
            "subcategory":"Community Association",
            "type":"Services"
        }
    ],
    "sg:phone":"+44 1332 768670",
    "sg:postcode":"DE24 9NG",
    "sg:province":"Derbyshire",
    "sg:tags":[
        "co-operatives",
        "society",
        "housing",
        "trust"
    ],
    "sg:website":"http://www.anchor.org.uk",
    "wof:name":"Anchor Trust",
    "wof:placetype":"venue"
},
  "geometry": {"coordinates":[-1.486909,52.88512],"type":"Point"}
}