{
  "type": "Feature",
  "properties": {
    "addr:full":"54 Balmoral Close Lichfield Staffordshire WS14 9SP",
    "addr:housenumber":"54",
    "addr:postcode":"ws14 9sp",
    "addr:street":"Balmoral Close",
    "iso:country":"GB",
    "sg:address":"54 Balmoral Close",
    "sg:city":"Lichfield",
    "sg:classifiers":[
        {
            "category":"Real Estate",
            "subcategory":"Architect",
            "type":"Services"
        }
    ],
    "sg:postcode":"WS14 9SP",
    "sg:province":"Staffordshire",
    "sg:tags":[
        "architectural"
    ],
    "wof:name":"S D B Design",
    "wof:placetype":"venue"
},
  "geometry": {"coordinates":[-1.812448,52.676598],"type":"Point"}
}