{
  "type": "Feature",
  "properties": {
    "addr:full":"16 Revell Drive, Fetcham Leatherhead Surrey KT22 9PS",
    "addr:housenumber":"16",
    "addr:postcode":"kt22 9ps",
    "addr:street":"Revell Drive",
    "iso:country":"GB",
    "sg:address":"16 Revell Drive, Fetcham",
    "sg:city":"Leatherhead",
    "sg:classifiers":[
        {
            "category":"Wholesale",
            "subcategory":"Construction Materials",
            "type":"Manufacturing & Wholesale Goods"
        },
        {
            "category":"Building & Trades",
            "subcategory":"Construction",
            "type":"Services"
        }
    ],
    "sg:phone":"+44 1372 456022",
    "sg:postcode":"KT22 9PS",
    "sg:province":"Surrey",
    "sg:tags":[
        "asphalt",
        "laying",
        "contractor",
        "paving",
        "macadam",
        "driveway"
    ],
    "wof:name":"T R Jennings & Sons Surfacing Contractors",
    "wof:placetype":"venue"
},
  "geometry": {"coordinates":[-0.3669759929,51.2944564819],"type":"Point"}
}