{
  "type": "Feature",
  "properties": {
    "iso:country":"GB",
    "sg:address":"136 High Street",
    "sg:city":"Cambridge",
    "sg:classifiers":[
        {
            "category":"Manufacturing",
            "subcategory":"Metals",
            "type":"Manufacturing & Wholesale Goods"
        }
    ],
    "sg:phone":"+44 1954 206357",
    "sg:postcode":"CB4 8RX",
    "sg:province":"Cambridgeshire",
    "sg:tags":[
        "work",
        "sheet"
    ],
    "wof:name":"J C Engineering",
    "wof:placetype":"venue"
},
  "geometry": {"coordinates":[0.126861006,52.2909736633],"type":"Point"}
}