{
  "type": "Feature",
  "properties": {
    "addr:full":"13 Apollo Pl West Brompton Greater London SW10 0ET",
    "addr:housenumber":"13",
    "addr:postcode":"sw10 0et",
    "addr:street":"Apollo Pl",
    "iso:country":"GB",
    "sg:address":"13 Apollo Pl",
    "sg:city":"West Brompton",
    "sg:classifiers":[
        {
            "category":"Professional",
            "subcategory":"Business Services",
            "type":"Services"
        }
    ],
    "sg:phone":"+44 20 7352 7727",
    "sg:postcode":"SW10 0ET",
    "sg:province":"Greater London",
    "sg:tags":[
        "hospitality",
        "corporate"
    ],
    "wof:name":"Central Events",
    "wof:placetype":"venue"
},
  "geometry": {"coordinates":[-0.176901,51.481735],"type":"Point"}
}