{
  "type": "Feature",
  "properties": {
    "iso:country":"GB",
    "sg:address":"Winjac, Water Gate, Quadring",
    "sg:city":"Spalding",
    "sg:classifiers":[
        {
            "category":"Autos & Motor Vehicles",
            "subcategory":"Fuel & Gas Station",
            "type":"Retail Goods"
        },
        {
            "category":"Professional",
            "subcategory":"Engineering",
            "type":"Services"
        },
        {
            "category":"Wholesale",
            "subcategory":"Plants",
            "type":"Manufacturing & Wholesale Goods"
        }
    ],
    "sg:phone":"+44 1775 821163",
    "sg:postcode":"PE11 4PY",
    "sg:province":"Lincolnshire",
    "sg:tags":[
        "civil",
        "pump",
        "engineer",
        "sale",
        "servicing"
    ],
    "wof:name":"Lincs Pumps & Pipeline",
    "wof:placetype":"venue"
},
  "geometry": {"coordinates":[-0.180444,52.881104],"type":"Point"}
}