{
  "type": "Feature",
  "properties": {
    "addr:full":"Station Road Industrial Estate Didcot Oxfordshire OX11 7NA",
    "addr:postcode":"ox11 7na",
    "addr:street":"Station Road Industrial Estate",
    "iso:country":"GB",
    "sg:address":"Station Road Industrial Estate",
    "sg:city":"Didcot",
    "sg:classifiers":[
        {
            "category":"Autos & Motor Vehicles",
            "subcategory":"Auto Supplies",
            "type":"Retail Goods"
        }
    ],
    "sg:postcode":"OX11 7NA",
    "sg:province":"Oxfordshire",
    "sg:tags":[
        "car",
        "component"
    ],
    "wof:name":"Fibre Techniques",
    "wof:placetype":"venue"
},
  "geometry": {"coordinates":[-1.241545,51.610207],"type":"Point"}
}