{
  "type": "Feature",
  "properties": {
    "addr:full":"29 Allt-yr-yn-view Newport Newport NP20 5EH",
    "addr:housenumber":"29",
    "addr:postcode":"np20 5eh",
    "addr:street":"Allt-Yr-Yn-View Newport",
    "iso:country":"GB",
    "sg:address":"29 Allt-yr-yn-view",
    "sg:city":"Newport",
    "sg:classifiers":[
        {
            "category":"Building & Trades",
            "subcategory":"Plumbing",
            "type":"Services"
        }
    ],
    "sg:postcode":"NP20 5EH",
    "sg:province":"Newport",
    "sg:tags":[
        "heating"
    ],
    "wof:name":"Raymond M Johnson",
    "wof:placetype":"venue"
},
  "geometry": {"coordinates":[-3.011478,51.594673],"type":"Point"}
}