{
  "type": "Feature",
  "properties": {
    "addr:full":"Po Box 2704 London Greater London NW5 2LW",
    "addr:housenumber":"po",
    "addr:postcode":"nw5 2lw",
    "addr:street":"Box 2704",
    "iso:country":"GB",
    "sg:address":"Po Box 2704",
    "sg:city":"London",
    "sg:classifiers":[
        {
            "category":"Professional",
            "subcategory":"Lawyer & Legal Services",
            "type":"Services"
        }
    ],
    "sg:postcode":"NW5 2LW",
    "sg:province":"Greater London",
    "sg:tags":[
        "advice",
        "counselling"
    ],
    "wof:name":"Womens Therapy Link",
    "wof:placetype":"venue"
},
  "geometry": {"coordinates":[-0.139339,51.5555648804],"type":"Point"}
}