{
  "type": "Feature",
  "properties": {
    "iso:country":"GB",
    "sg:address":"3 Greyfriars Place",
    "sg:city":"Edinburgh",
    "sg:classifiers":[
        {
            "category":"Shopping",
            "subcategory":"Comic Books",
            "type":"Retail Goods"
        }
    ],
    "sg:phone":"+44 131 225 4881",
    "sg:postcode":"EH1 2QQ",
    "sg:province":"City of Edinburgh",
    "sg:tags":[
        "jeweller"
    ],
    "wof:name":"Joe Cool",
    "wof:placetype":"venue"
},
  "geometry": {"coordinates":[-3.191094,55.9468],"type":"Point"}
}