{
  "type": "Feature",
  "properties": {
    "iso:country":"GB",
    "sg:address":"364a High Street",
    "sg:city":"Lincoln",
    "sg:classifiers":[
        {
            "category":"Fast Food",
            "type":"Food & Drink"
        }
    ],
    "sg:phone":"+44 1522 511680",
    "sg:postcode":"LN5 7RL",
    "sg:province":"Lincolnshire",
    "sg:tags":[
        "away",
        "meal",
        "outlet",
        "take"
    ],
    "wof:name":"Balti House Takeaway",
    "wof:placetype":"venue"
},
  "geometry": {"coordinates":[-0.543088,53.224194],"type":"Point"}
}