{
  "type": "Feature",
  "properties": {
    "addr:full":"123 Marlborough Road London Greater London N22 8NL",
    "addr:housenumber":"123",
    "addr:postcode":"n22 8nl",
    "addr:street":"Marlborough Road",
    "iso:country":"GB",
    "sg:address":"123 Marlborough Road",
    "sg:city":"London",
    "sg:classifiers":[
        {
            "category":"Banks & Credit Unions",
            "subcategory":"Financial Services",
            "type":"Services"
        }
    ],
    "sg:postcode":"N22 8NL",
    "sg:province":"Greater London",
    "sg:tags":[
        "consultant"
    ],
    "wof:name":"Bokbavok Financial Contracts Ltd",
    "wof:placetype":"venue"
},
  "geometry": {"coordinates":[-0.1165309995,51.6093406677],"type":"Point"}
}