{
  "type": "Feature",
  "properties": {
    "iso:country":"GB",
    "sg:address":"The Surgery, 37 Ongar Rd",
    "sg:city":"Romford",
    "sg:classifiers":[
        {
            "category":"Health Services",
            "subcategory":"Doctor",
            "type":"Services"
        }
    ],
    "sg:phone":"+44 1992 812961",
    "sg:postcode":"RM4 1UH",
    "sg:province":"Essex",
    "sg:tags":[
        "practitioners"
    ],
    "wof:name":"Harding, P A",
    "wof:placetype":"venue"
},
  "geometry": {"coordinates":[0.12424,51.653912],"type":"Point"}
}