{
  "type": "Feature",
  "properties": {
    "addr:full":"205 Wakefield Road, Smithies Barnsley South Yorkshire S71 1NS",
    "addr:housenumber":"205",
    "addr:postcode":"s71 1ns",
    "addr:street":"Wakefield Road Smithies;Yorkshire",
    "iso:country":"GB",
    "sg:address":"205 Wakefield Road, Smithies",
    "sg:city":"Barnsley",
    "sg:classifiers":[
        {
            "category":"Building & Trades",
            "subcategory":"Equipment Rental",
            "type":"Services"
        }
    ],
    "sg:phone":"+44 1924 291911",
    "sg:postcode":"S71 1NS",
    "sg:province":"South Yorkshire",
    "sg:tags":[
        "plant",
        "machinery"
    ],
    "wof:name":"Booth Plant & Equipment Ltd.",
    "wof:placetype":"venue"
},
  "geometry": {"coordinates":[-1.4734499454,53.5729904175],"type":"Point"}
}