{
  "type": "Feature",
  "properties": {
    "addr:full":"32 Higher Lane, Rainford St Helens Lancashire WA11 8NX",
    "addr:housenumber":"32",
    "addr:postcode":"wa11 8nx",
    "addr:street":"Higher Lane",
    "iso:country":"GB",
    "sg:address":"32 Higher Lane, Rainford",
    "sg:city":"St Helens",
    "sg:classifiers":[
        {
            "category":"Organizations",
            "subcategory":"Community Association",
            "type":"Services"
        }
    ],
    "sg:phone":"+44 1744 886291",
    "sg:postcode":"WA11 8NX",
    "sg:province":"Lancashire",
    "sg:tags":[
        "relation",
        "public"
    ],
    "wof:name":"Whitehouse Promotions",
    "wof:placetype":"venue"
},
  "geometry": {"coordinates":[-2.7834808826,53.5062561035],"type":"Point"}
}