{
  "type": "Feature",
  "properties": {
    "addr:full":"Unit 13, Tile Cross Trading Estate Birmingham West Midlands B33 0NW",
    "addr:housenumber":"unit 13",
    "addr:postcode":"b33 0nw",
    "addr:street":"Tile Cross Trading Estate",
    "iso:country":"GB",
    "sg:address":"Unit 13, Tile Cross Trading Estate",
    "sg:city":"Birmingham",
    "sg:classifiers":[
        {
            "category":"Shopping",
            "subcategory":"Pets & Pet Supplies",
            "type":"Retail Goods"
        }
    ],
    "sg:postcode":"B33 0NW",
    "sg:province":"West Midlands",
    "sg:tags":[
        "food"
    ],
    "wof:name":"Royal Canin Midlands Distribution",
    "wof:placetype":"venue"
},
  "geometry": {"coordinates":[-1.760744,52.481915],"type":"Point"}
}