{
  "type": "Feature",
  "properties": {
    "iso:country":"GB",
    "sg:address":"16a Melton Road",
    "sg:city":"Leicester",
    "sg:classifiers":[
        {
            "category":"Travel",
            "subcategory":"Travel Agent",
            "type":"Entertainment"
        }
    ],
    "sg:phone":"+44 116 268 1177",
    "sg:postcode":"LE4 5EA",
    "sg:province":"Leicestershire",
    "sg:tags":[
        "agency",
        "activity"
    ],
    "wof:name":"A Z Travels",
    "wof:placetype":"venue"
},
  "geometry": {"coordinates":[-1.121184,52.651787],"type":"Point"}
}