{
  "type": "Feature",
  "properties": {
    "addr:full":"18 Winnington Street Northwich Cheshire CW8 1AD",
    "addr:housenumber":"18",
    "addr:postcode":"cw8 1ad",
    "addr:street":"Winnington Street",
    "iso:country":"GB",
    "sg:address":"18 Winnington Street",
    "sg:city":"Northwich",
    "sg:classifiers":[
        {
            "category":"Organizations",
            "subcategory":"Non-profit Organization",
            "type":"Services"
        }
    ],
    "sg:phone":"+44 1606 783337",
    "sg:postcode":"CW8 1AD",
    "sg:province":"Cheshire",
    "sg:tags":[
        "organisation",
        "voluntary",
        "charity"
    ],
    "wof:name":"Gingerbread (An Association for One Parent Families) Ltd.",
    "wof:placetype":"venue"
},
  "geometry": {"coordinates":[-2.51708,53.261189],"type":"Point"}
}