{
  "type": "Feature",
  "properties": {
    "iso:country":"GB",
    "sg:address":"69a Lensfield Rd",
    "sg:city":"Cambridge",
    "sg:classifiers":[
        {
            "category":"Wholesale",
            "subcategory":"Books, Periodicals, & Newspapers",
            "type":"Manufacturing & Wholesale Goods"
        }
    ],
    "sg:phone":"+44 1223 508050",
    "sg:postcode":"CB2 1EN",
    "sg:province":"Cambridgeshire",
    "sg:tags":[
        "publishing"
    ],
    "wof:name":"Keesing's Record Of World Events",
    "wof:placetype":"venue"
},
  "geometry": {"coordinates":[0.122844,52.197926],"type":"Point"}
}