{
  "type": "Feature",
  "properties": {
    "addr:full":"Care Of Kwik-save, West Dyke Rd Redcar North Yorkshire TS10 2ED",
    "addr:postcode":"ts10 2ed",
    "addr:street":"West Dyke Rd",
    "iso:country":"GB",
    "sg:address":"Care Of Kwik-save, West Dyke Rd",
    "sg:city":"Redcar",
    "sg:classifiers":[
        {
            "category":"Food & Beverages",
            "subcategory":"Farmers Market",
            "type":"Retail Goods"
        }
    ],
    "sg:postcode":"TS10 2ED",
    "sg:province":"North Yorkshire",
    "sg:tags":[
        "gardener"
    ],
    "wof:name":"Market Grown Produce",
    "wof:placetype":"venue"
},
  "geometry": {"coordinates":[-1.068343997,54.6140594482],"type":"Point"}
}