{
  "type": "Feature",
  "properties": {
    "iso:country":"GB",
    "sg:address":"89 Gateacre Park Dr",
    "sg:city":"Liverpool",
    "sg:classifiers":[
        {
            "category":"Farming",
            "subcategory":"Nursery",
            "type":"Manufacturing & Wholesale Goods"
        }
    ],
    "sg:postcode":"L25 1PD",
    "sg:province":"Merseyside",
    "sg:tags":[
        "creche"
    ],
    "wof:name":"Holmes,Ann-Marie,",
    "wof:placetype":"venue"
},
  "geometry": {"coordinates":[-2.8727331161,53.3911819458],"type":"Point"}
}