{
  "type": "Feature",
  "properties": {
    "addr:full":"31 Junction Road Andover Hampshire SP10 3QU",
    "addr:housenumber":"31",
    "addr:postcode":"sp10 3qu",
    "addr:street":"Junction Road",
    "iso:country":"GB",
    "sg:address":"31 Junction Road",
    "sg:city":"Andover",
    "sg:classifiers":[
        {
            "category":"Health Services",
            "subcategory":"Dentist",
            "type":"Services"
        }
    ],
    "sg:phone":"+44 1264 323033",
    "sg:postcode":"SP10 3QU",
    "sg:province":"Hampshire",
    "wof:name":"Thomas Neilson",
    "wof:placetype":"venue"
},
  "geometry": {"coordinates":[-1.484585,51.20853],"type":"Point"}
}