{
  "type": "Feature",
  "properties": {
    "iso:country":"GB",
    "sg:address":"8 The Ace Terrace",
    "sg:city":"Spilsby",
    "sg:classifiers":[
        {
            "category":"Recreation",
            "subcategory":"Fishing",
            "type":"Entertainment"
        },
        {
            "category":"Food & Beverages",
            "subcategory":"Groceries & Convenience Stores",
            "type":"Retail Goods"
        }
    ],
    "sg:phone":"+44 1790 752224",
    "sg:postcode":"PE23 5JR",
    "sg:province":"Lincolnshire",
    "sg:tags":[
        "shop",
        "fish",
        "angling",
        "chip"
    ],
    "wof:name":"Ambridge Fisheries",
    "wof:placetype":"venue"
},
  "geometry": {"coordinates":[0.09567,53.173561],"type":"Point"}
}