{
  "type": "Feature",
  "properties": {
    "iso:country":"GB",
    "sg:address":"22 Hillbury Rd",
    "sg:city":"Warlingham",
    "sg:classifiers":[
        {
            "category":"Building & Trades",
            "subcategory":"Construction",
            "type":"Services"
        }
    ],
    "sg:phone":"+44 1883 625265",
    "sg:postcode":"CR6 9TA",
    "sg:province":"Kent",
    "sg:tags":[
        "builder"
    ],
    "wof:name":"Nash Unique",
    "wof:placetype":"venue"
},
  "geometry": {"coordinates":[-0.07714,51.310009],"type":"Point"}
}