{
  "type": "Feature",
  "properties": {
    "iso:country":"GB",
    "sg:address":"Blackmore End",
    "sg:city":"Braintree",
    "sg:classifiers":[
        {
            "category":"Professional",
            "subcategory":"Engineering",
            "type":"Services"
        }
    ],
    "sg:postcode":"CM7 4DB",
    "sg:province":"Essex",
    "sg:tags":[
        "contractor",
        "electrical",
        "engineer"
    ],
    "wof:name":"V F Lewis Electrical",
    "wof:placetype":"venue"
},
  "geometry": {"coordinates":[0.523,51.951832],"type":"Point"}
}