{
  "type": "Feature",
  "properties": {
    "addr:full":"2 Madison Close Gosport Hampshire PO13 9UL",
    "addr:housenumber":"2",
    "addr:postcode":"po13 9ul",
    "addr:street":"Madison Close",
    "iso:country":"GB",
    "sg:address":"2 Madison Close",
    "sg:city":"Gosport",
    "sg:classifiers":[
        {
            "category":"Building & Trades",
            "subcategory":"Construction",
            "type":"Services"
        }
    ],
    "sg:phone":"+44 23 9260 1300",
    "sg:postcode":"PO13 9UL",
    "sg:province":"Hampshire",
    "sg:tags":[
        "roofing"
    ],
    "wof:name":"Brian E Chapman",
    "wof:placetype":"venue"
},
  "geometry": {"coordinates":[-1.1637480259,50.8108482361],"type":"Point"}
}