{
  "type": "Feature",
  "properties": {
    "iso:country":"GB",
    "sg:address":"The Surgery 24 The Hills, Reedham",
    "sg:city":"Norwich",
    "sg:classifiers":[
        {
            "category":"Health Services",
            "subcategory":"Doctor",
            "type":"Services"
        }
    ],
    "sg:phone":"+44 1493 700249",
    "sg:postcode":"NR13 3AR",
    "sg:province":"Norfolk",
    "sg:tags":[
        "practitioners"
    ],
    "wof:name":"Dr N.J Ireland",
    "wof:placetype":"venue"
},
  "geometry": {"coordinates":[1.543642,52.609482],"type":"Point"}
}