{
  "type": "Feature",
  "properties": {
    "addr:full":"The Thatched Roadhouse, Main Road, Martlesham Woodbridge Suffolk IP12 4RJ",
    "addr:postcode":"ip12 4rj",
    "addr:street":"Main Road",
    "iso:country":"GB",
    "sg:address":"The Thatched Roadhouse, Main Road, Martlesham",
    "sg:city":"Woodbridge",
    "sg:classifiers":[
        {
            "category":"Shopping",
            "subcategory":"Antiques",
            "type":"Retail Goods"
        }
    ],
    "sg:phone":"+44 1394 386732",
    "sg:postcode":"IP12 4RJ",
    "sg:province":"Suffolk",
    "wof:name":"Martlesham Antiques",
    "wof:placetype":"venue"
},
  "geometry": {"coordinates":[1.32539,52.10545],"type":"Point"}
}