{
  "type": "Feature",
  "properties": {
    "addr:full":"48 Molesworth Street Wadebridge Cornwall PL27 7DP",
    "addr:housenumber":"48",
    "addr:postcode":"pl27 7dp",
    "addr:street":"Molesworth Street",
    "iso:country":"GB",
    "sg:address":"48 Molesworth Street",
    "sg:city":"Wadebridge",
    "sg:classifiers":[
        {
            "category":"Health Services",
            "subcategory":"Health Practitioner",
            "type":"Services"
        }
    ],
    "sg:phone":"+44 1208 812048",
    "sg:postcode":"PL27 7DP",
    "sg:province":"Cornwall",
    "sg:tags":[
        "osteopath"
    ],
    "wof:name":"Wadebridge Osteopaths",
    "wof:placetype":"venue"
},
  "geometry": {"coordinates":[-4.838333,50.516357],"type":"Point"}
}