{
  "type": "Feature",
  "properties": {
    "iso:country":"GB",
    "sg:address":"Lewin House, Dorking Road",
    "sg:city":"Tadworth",
    "sg:classifiers":[
        {
            "category":"Manufacturing",
            "subcategory":"Textiles",
            "type":"Manufacturing & Wholesale Goods"
        }
    ],
    "sg:postcode":"KT20 5SL",
    "sg:province":"Surrey",
    "sg:tags":[
        "made-up"
    ],
    "wof:name":"Yeats  Robert & Son Ltd.",
    "wof:placetype":"venue"
},
  "geometry": {"coordinates":[-0.225104,51.290695],"type":"Point"}
}