{
  "type": "Feature",
  "properties": {
    "addr:full":"Unit 6 Salvesen Way, Freightliner Rd Hull East Riding of Yorkshire HU3 4UW",
    "addr:housenumber":"unit 6",
    "addr:postcode":"hu3 4uw",
    "addr:street":"Salvesen Way Freightliner Rd",
    "iso:country":"GB",
    "sg:address":"Unit 6 Salvesen Way, Freightliner Rd",
    "sg:city":"Hull",
    "sg:classifiers":[
        {
            "category":"Retail",
            "subcategory":"Driving School",
            "type":"Services"
        }
    ],
    "sg:phone":"+44 1482 222626",
    "sg:postcode":"HU3 4UW",
    "sg:province":"East Riding of Yorkshire",
    "sg:tags":[
        "instruction",
        "cycling",
        "motor"
    ],
    "wof:name":"Aims Rider Training",
    "wof:placetype":"venue"
},
  "geometry": {"coordinates":[-0.3783609867,53.7298698425],"type":"Point"}
}