{
  "type": "Feature",
  "properties": {
    "iso:country":"GB",
    "sg:address":"18 Tattershall Road",
    "sg:city":"Boston",
    "sg:classifiers":[
        {
            "category":"Bars & Pubs",
            "type":"Food & Drink"
        }
    ],
    "sg:phone":"+44 1205 356139",
    "sg:postcode":"PE21 9JS",
    "sg:province":"Lincolnshire",
    "sg:tags":[
        "pubs",
        "inn"
    ],
    "wof:name":"The Unicorn Inn",
    "wof:placetype":"venue"
},
  "geometry": {"coordinates":[-0.029682,52.982784],"type":"Point"}
}