{
  "type": "Feature",
  "properties": {
    "addr:full":"25 Deepdene Wood Dorking Surrey RH5 4BQ",
    "addr:housenumber":"25",
    "addr:postcode":"rh5 4bq",
    "addr:street":"Deepdene Wood",
    "iso:country":"GB",
    "sg:address":"25 Deepdene Wood",
    "sg:city":"Dorking",
    "sg:classifiers":[
        {
            "category":"Shopping",
            "subcategory":"Clothing, Apparel, & Fashions",
            "type":"Retail Goods"
        }
    ],
    "sg:phone":"+44 1306 877070",
    "sg:postcode":"RH5 4BQ",
    "sg:province":"Surrey",
    "sg:tags":[
        "clothing"
    ],
    "wof:name":"Saffron Kesar Ltd.",
    "wof:placetype":"venue"
},
  "geometry": {"coordinates":[-0.3181340098,51.2302856445],"type":"Point"}
}