{
  "type": "Feature",
  "properties": {
    "iso:country":"GB",
    "sg:address":"1 Glebelands, Claygate",
    "sg:city":"Esher",
    "sg:classifiers":[
        {
            "category":"Banks & Credit Unions",
            "subcategory":"Financial Services",
            "type":"Services"
        }
    ],
    "sg:phone":"+44 1372 466005",
    "sg:postcode":"KT10 0LF",
    "sg:province":"Surrey",
    "sg:tags":[
        "agent",
        "tied"
    ],
    "wof:name":"Financial Webb Plc",
    "wof:placetype":"venue"
},
  "geometry": {"coordinates":[-0.335813,51.364624],"type":"Point"}
}