{
  "type": "Feature",
  "properties": {
    "iso:country":"GB",
    "sg:address":"23a Howe Street",
    "sg:city":"Edinburgh",
    "sg:classifiers":[
        {
            "category":"Professional",
            "subcategory":"Business Services",
            "type":"Services"
        }
    ],
    "sg:phone":"+44 131 556 2013",
    "sg:postcode":"EH3 6TF",
    "sg:province":"City of Edinburgh",
    "sg:tags":[
        "tile",
        "stockist"
    ],
    "wof:name":"The Original Tile Co. Ltd.",
    "wof:placetype":"venue"
},
  "geometry": {"coordinates":[-3.202217,55.956448],"type":"Point"}
}