{
  "type": "Feature",
  "properties": {
    "addr:full":"Morven Road St Austell Cornwall PL25 4PP",
    "addr:postcode":"pl25 4pp",
    "addr:street":"Morven Road",
    "iso:country":"GB",
    "sg:address":"Morven Road",
    "sg:city":"St Austell",
    "sg:classifiers":[
        {
            "category":"Education",
            "subcategory":"School",
            "type":"Public Place"
        },
        {
            "category":"Government",
            "subcategory":"Office",
            "type":"Public Place"
        }
    ],
    "sg:phone":"+44 1726 73911",
    "sg:postcode":"PL25 4PP",
    "sg:province":"Cornwall",
    "sg:tags":[
        "local",
        "authority"
    ],
    "wof:name":"Mount Charles C P School",
    "wof:placetype":"venue"
},
  "geometry": {"coordinates":[-4.773374,50.337116],"type":"Point"}
}