{
  "type": "Feature",
  "properties": {
    "addr:full":"2c Bakers Avenue, Walthamstow London Greater London E17 9AW",
    "addr:housenumber":"2c",
    "addr:postcode":"e17 9aw",
    "addr:street":"Bakers Avenue",
    "iso:country":"GB",
    "sg:address":"2c Bakers Avenue, Walthamstow",
    "sg:city":"London",
    "sg:classifiers":[
        {
            "category":"Wholesale",
            "subcategory":"Scrap",
            "type":"Manufacturing & Wholesale Goods"
        },
        {
            "category":"Utilities",
            "subcategory":"Recycling",
            "type":"Services"
        }
    ],
    "sg:phone":"+44 20 8539 3856",
    "sg:postcode":"E17 9AW",
    "sg:province":"Greater London",
    "sg:tags":[
        "waste",
        "metal"
    ],
    "wof:name":"Forest Recycling Project Ltd.",
    "wof:placetype":"venue"
},
  "geometry": {"coordinates":[-0.014729,51.575935],"type":"Point"}
}