{
  "type": "Feature",
  "properties": {
    "addr:full":"160 Oakfield Road, Walton Liverpool Merseyside L4 0UH",
    "addr:housenumber":"160",
    "addr:postcode":"l4 0uh",
    "addr:street":"Oakfield Road",
    "iso:country":"GB",
    "sg:address":"160 Oakfield Road, Walton",
    "sg:city":"Liverpool",
    "sg:classifiers":[
        {
            "category":"Place Of Worship",
            "type":"Public Place"
        }
    ],
    "sg:phone":"+44 151 475 6878",
    "sg:postcode":"L4 0UH",
    "sg:province":"Merseyside",
    "wof:name":"Temple Of Praise",
    "wof:placetype":"venue"
},
  "geometry": {"coordinates":[-2.9585669041,53.4282035828],"type":"Point"}
}