{
  "type": "Feature",
  "properties": {
    "addr:full":"36 Villiers Road Watford Hertfordshire WD19 4AJ",
    "addr:housenumber":"36",
    "addr:postcode":"wd19 4aj",
    "addr:street":"Villiers Road",
    "iso:country":"GB",
    "sg:address":"36 Villiers Road",
    "sg:city":"Watford",
    "sg:classifiers":[
        {
            "category":"Bars & Pubs",
            "type":"Food & Drink"
        }
    ],
    "sg:phone":"+44 1923 221814",
    "sg:postcode":"WD19 4AJ",
    "sg:province":"Hertfordshire",
    "sg:tags":[
        "pubs",
        "inn"
    ],
    "wof:name":"Rifle Volunteer",
    "wof:placetype":"venue"
},
  "geometry": {"coordinates":[-0.380965,51.644787],"type":"Point"}
}