{
  "type": "Feature",
  "properties": {
    "addr:full":"2 Florence St Leeds West Yorkshire LS9 7AW",
    "addr:housenumber":"2",
    "addr:postcode":"ls9 7aw",
    "addr:street":"Florence St",
    "iso:country":"GB",
    "sg:address":"2 Florence St",
    "sg:city":"Leeds",
    "sg:classifiers":[
        {
            "category":"Shopping",
            "subcategory":"Used Merchandise",
            "type":"Retail Goods"
        }
    ],
    "sg:postcode":"LS9 7AW",
    "sg:province":"West Yorkshire",
    "sg:tags":[
        "shop",
        "second-hand"
    ],
    "wof:name":"Bradley,John,",
    "wof:placetype":"venue"
},
  "geometry": {"coordinates":[-1.5134520531,53.8088264465],"type":"Point"}
}