{
  "type": "Feature",
  "properties": {
    "addr:full":"Manchester Road, Droylsden Manchester Greater Manchester M43 6TQ",
    "addr:postcode":"m43 6tq",
    "addr:street":"Manchester Road",
    "iso:country":"GB",
    "sg:address":"Manchester Road, Droylsden",
    "sg:city":"Manchester",
    "sg:classifiers":[
        {
            "category":"Food & Beverages",
            "subcategory":"Supermarket",
            "type":"Retail Goods"
        }
    ],
    "sg:phone":"+44 161 371 3005",
    "sg:postcode":"M43 6TQ",
    "sg:province":"Greater Manchester",
    "wof:name":"Tesco Stores Ltd.",
    "wof:placetype":"venue"
},
  "geometry": {"coordinates":[-2.1501140594,53.4796600342],"type":"Point"}
}