{
  "type": "Feature",
  "properties": {
    "addr:full":"Bod Gaeaf Isaf, Bryncroes Pwllheli Gwynedd LL53 8EB",
    "addr:postcode":"ll53 8eb",
    "iso:country":"GB",
    "sg:address":"Bod Gaeaf Isaf, Bryncroes",
    "sg:city":"Pwllheli",
    "sg:classifiers":[
        {
            "category":"Farming",
            "subcategory":"Farm",
            "type":"Manufacturing & Wholesale Goods"
        }
    ],
    "sg:phone":"+44 1758 730537",
    "sg:postcode":"LL53 8EB",
    "sg:province":"Gwynedd",
    "sg:tags":[
        "mixed",
        "crop"
    ],
    "wof:name":"T R & E Parry",
    "wof:placetype":"venue"
},
  "geometry": {"coordinates":[-4.634529,52.85141],"type":"Point"}
}