{
  "type": "Feature",
  "properties": {
    "iso:country":"GB",
    "sg:address":"265 Stonelaw Road, Rutherglen",
    "sg:city":"Glasgow",
    "sg:classifiers":[
        {
            "category":"Professional",
            "subcategory":"Accounting & Tax Preparation",
            "type":"Services"
        }
    ],
    "sg:phone":"+44 141 569 3165",
    "sg:postcode":"G73 3RN",
    "sg:province":"Glasgow City",
    "sg:tags":[
        "accountant"
    ],
    "wof:name":"Michael Lynas Accounting",
    "wof:placetype":"venue"
},
  "geometry": {"coordinates":[-4.201673,55.817921],"type":"Point"}
}