{
  "type": "Feature",
  "properties": {
    "addr:full":"19 Copsewood Avenue, Whitestone Nuneaton Leicestershire CV11 4TQ",
    "addr:housenumber":"19",
    "addr:postcode":"cv11 4tq",
    "addr:street":"Copsewood Avenue",
    "iso:country":"GB",
    "sg:address":"19 Copsewood Avenue, Whitestone",
    "sg:city":"Nuneaton",
    "sg:classifiers":[
        {
            "category":"Manufacturing",
            "subcategory":"Textiles",
            "type":"Manufacturing & Wholesale Goods"
        }
    ],
    "sg:phone":"+44 24 7666 6232",
    "sg:postcode":"CV11 4TQ",
    "sg:province":"Leicestershire",
    "sg:tags":[
        "made-up"
    ],
    "wof:name":"Aquarius Manufacturing Co.",
    "wof:placetype":"venue"
},
  "geometry": {"coordinates":[-1.43275702,52.5008888245],"type":"Point"}
}