{
  "type": "Feature",
  "properties": {
    "addr:full":"225 Northolt Road Harrow Greater London HA2 8HW",
    "addr:housenumber":"225",
    "addr:postcode":"ha2 8hw",
    "addr:street":"Northolt Road",
    "iso:country":"GB",
    "sg:address":"225 Northolt Road",
    "sg:city":"Harrow",
    "sg:classifiers":[
        {
            "category":"Real Estate",
            "subcategory":"Real Estate Agent",
            "type":"Services"
        }
    ],
    "sg:phone":"+44 20 8422 5501",
    "sg:postcode":"HA2 8HW",
    "sg:province":"Greater London",
    "wof:name":"Bairstow Eves",
    "wof:placetype":"venue"
},
  "geometry": {"coordinates":[-0.3525480032,51.5647888184],"type":"Point"}
}