{
  "type": "Feature",
  "properties": {
    "addr:full":"1 Linnet Road Poole Dorset BH17 7TF",
    "addr:housenumber":"1",
    "addr:postcode":"bh17 7tf",
    "addr:street":"Linnet Road",
    "iso:country":"GB",
    "sg:address":"1 Linnet Road",
    "sg:city":"Poole",
    "sg:classifiers":[
        {
            "category":"Professional",
            "subcategory":"Art Services",
            "type":"Services"
        },
        {
            "category":"Building & Trades",
            "subcategory":"Construction",
            "type":"Services"
        }
    ],
    "sg:phone":"+44 1202 658726",
    "sg:postcode":"BH17 7TF",
    "sg:province":"Dorset",
    "sg:tags":[
        "decorator",
        "painter"
    ],
    "wof:name":"Robert A Pape",
    "wof:placetype":"venue"
},
  "geometry": {"coordinates":[-2.007246,50.744339],"type":"Point"}
}