{
  "type": "Feature",
  "properties": {
    "addr:full":"1 Horizon Park, Barton Road Cambridge Cambridgeshire CB3 7AF",
    "addr:housenumber":"1",
    "addr:postcode":"cb3 7af",
    "addr:street":"Horizon Park Barton Road",
    "iso:country":"GB",
    "sg:address":"1 Horizon Park, Barton Road",
    "sg:city":"Cambridge",
    "sg:classifiers":[
        {
            "category":"Organizations",
            "subcategory":"Community Association",
            "type":"Services"
        }
    ],
    "sg:phone":"+44 1223 576756",
    "sg:postcode":"CB3 7AF",
    "sg:province":"Cambridgeshire",
    "sg:tags":[
        "co-operatives",
        "society",
        "housing",
        "trust"
    ],
    "wof:name":"Granta Housing Society Ltd",
    "wof:placetype":"venue"
},
  "geometry": {"coordinates":[0.0654089972,52.180141449],"type":"Point"}
}