{
  "type": "Feature",
  "properties": {
    "addr:full":"34 Station Road, Draycott Derby Derbyshire DE72 3QB",
    "addr:housenumber":"34",
    "addr:postcode":"de72 3qb",
    "addr:street":"Station Road",
    "iso:country":"GB",
    "sg:address":"34 Station Road, Draycott",
    "sg:city":"Derby",
    "sg:classifiers":[
        {
            "category":"Professional",
            "subcategory":"Engineering",
            "type":"Services"
        },
        {
            "category":"Building & Trades",
            "subcategory":"Construction",
            "type":"Services"
        }
    ],
    "sg:phone":"+44 1332 871840",
    "sg:postcode":"DE72 3QB",
    "sg:province":"Derbyshire",
    "sg:tags":[
        "consulting",
        "contractor",
        "engineer"
    ],
    "wof:name":"Michael Evans & Associates Ltd.",
    "wof:placetype":"venue"
},
  "geometry": {"coordinates":[-1.3825650215,52.9046974182],"type":"Point"}
}