{
  "type": "Feature",
  "properties": {
    "iso:country":"GB",
    "sg:address":"Hedley West Riding Farm, Hedley",
    "sg:city":"Stocksfield",
    "sg:classifiers":[
        {
            "category":"Farming",
            "subcategory":"Livestock Farm",
            "type":"Manufacturing & Wholesale Goods"
        }
    ],
    "sg:postcode":"NE43 7SL",
    "sg:province":"Northumberland",
    "sg:tags":[
        "others"
    ],
    "wof:name":"W Faill",
    "wof:placetype":"venue"
},
  "geometry": {"coordinates":[-1.915894,54.946686],"type":"Point"}
}