{
  "type": "Feature",
  "properties": {
    "addr:full":"63a High Street, Yeadon Leeds West Yorkshire LS19 7SP",
    "addr:housenumber":"63a",
    "addr:postcode":"ls19 7sp",
    "addr:street":"High Street",
    "iso:country":"GB",
    "sg:address":"63a High Street, Yeadon",
    "sg:city":"Leeds",
    "sg:classifiers":[
        {
            "category":"Shopping",
            "subcategory":"Optician",
            "type":"Retail Goods"
        },
        {
            "category":"Health Services",
            "subcategory":"Optometrist",
            "type":"Services"
        }
    ],
    "sg:phone":"+44 113 250 5547",
    "sg:postcode":"LS19 7SP",
    "sg:province":"West Yorkshire",
    "sg:tags":[
        "opthalmic"
    ],
    "wof:name":"David S Webster",
    "wof:placetype":"venue"
},
  "geometry": {"coordinates":[-1.682626,53.866322],"type":"Point"}
}