{
  "type": "Feature",
  "properties": {
    "iso:country":"GB",
    "sg:address":"43 Middle Street North",
    "sg:city":"Driffield",
    "sg:classifiers":[
        {
            "category":"Home & Garden",
            "subcategory":"Furniture",
            "type":"Retail Goods"
        }
    ],
    "sg:phone":"+44 1377 252084",
    "sg:postcode":"YO25 6SS",
    "sg:province":"East Riding of Yorkshire",
    "sg:tags":[
        "outlet"
    ],
    "wof:name":"Bishops House Furnishers Ltd.",
    "wof:placetype":"venue"
},
  "geometry": {"coordinates":[-0.4375329912,54.0038414001],"type":"Point"}
}