{
  "type": "Feature",
  "properties": {
    "addr:full":"18 Juniper Close, Walderslade Chatham Kent ME5 0NX",
    "addr:housenumber":"18",
    "addr:postcode":"me5 0nx",
    "addr:street":"Juniper Close",
    "iso:country":"GB",
    "sg:address":"18 Juniper Close, Walderslade",
    "sg:city":"Chatham",
    "sg:classifiers":[
        {
            "category":"Communications",
            "type":"Services"
        }
    ],
    "sg:postcode":"ME5 0NX",
    "sg:province":"Kent",
    "sg:tags":[
        "telecommunication"
    ],
    "wof:name":"Ashuma Global Communication Ltd",
    "wof:placetype":"venue"
},
  "geometry": {"coordinates":[0.527891,51.346619],"type":"Point"}
}