{
  "type": "Feature",
  "properties": {
    "iso:country":"GB",
    "sg:address":"Universal House, Lord Street",
    "sg:city":"Coventry",
    "sg:classifiers":[
        {
            "category":"Government",
            "subcategory":"Customs House",
            "type":"Public Place"
        }
    ],
    "sg:phone":"+44 24 7671 7240",
    "sg:postcode":"CV5 8DA",
    "sg:province":"West Midlands",
    "sg:tags":[
        "plant",
        "crushing"
    ],
    "wof:name":"John Hill",
    "wof:placetype":"venue"
},
  "geometry": {"coordinates":[-1.533264,52.407475],"type":"Point"}
}