{
  "type": "Feature",
  "properties": {
    "addr:full":"115 Wellgate Rotherham South Yorkshire S60 2NH",
    "addr:housenumber":"115",
    "addr:postcode":"s60 2nh",
    "addr:street":"Wellgate Rotherham South",
    "iso:country":"GB",
    "sg:address":"115 Wellgate",
    "sg:city":"Rotherham",
    "sg:classifiers":[
        {
            "category":"Insurance",
            "subcategory":"Insurance Agent",
            "type":"Services"
        }
    ],
    "sg:phone":"+44 1709 821011",
    "sg:postcode":"S60 2NH",
    "sg:province":"South Yorkshire",
    "sg:tags":[
        "broker"
    ],
    "wof:name":"Ian Walker",
    "wof:placetype":"venue"
},
  "geometry": {"coordinates":[-1.3518719673,53.4284858704],"type":"Point"}
}