{
  "type": "Feature",
  "properties": {
    "addr:full":"10 Girton Way, Croxley Grn Rickmansworth Hertfordshire WD3 3QN",
    "addr:housenumber":"10",
    "addr:postcode":"wd3 3qn",
    "addr:street":"Girton Way Croxley Grn",
    "iso:country":"GB",
    "sg:address":"10 Girton Way, Croxley Grn",
    "sg:city":"Rickmansworth",
    "sg:classifiers":[
        {
            "category":"Manufacturing",
            "subcategory":"Petroleum Products",
            "type":"Manufacturing & Wholesale Goods"
        }
    ],
    "sg:postcode":"WD3 3QN",
    "sg:province":"Hertfordshire",
    "sg:tags":[
        "double",
        "glazing"
    ],
    "wof:name":"Sillwood Construction",
    "wof:placetype":"venue"
},
  "geometry": {"coordinates":[-0.437789,51.651138],"type":"Point"}
}