{
  "type": "Feature",
  "properties": {
    "addr:full":"3 Mandeville Rd Northolt Greater London UB5 5HE",
    "addr:housenumber":"3",
    "addr:postcode":"ub5 5he",
    "addr:street":"Mandeville Rd",
    "iso:country":"GB",
    "sg:address":"3 Mandeville Rd",
    "sg:city":"Northolt",
    "sg:classifiers":[
        {
            "category":"Health Services",
            "subcategory":"Doctor",
            "type":"Services"
        }
    ],
    "sg:phone":"+44 20 8845 3275",
    "sg:postcode":"UB5 5HE",
    "sg:province":"Greater London",
    "sg:tags":[
        "practitioners"
    ],
    "wof:name":"Seimon, J B",
    "wof:placetype":"venue"
},
  "geometry": {"coordinates":[-0.372511,51.544823],"type":"Point"}
}