{
  "type": "Feature",
  "properties": {
    "addr:full":"Unit X Robian Way Swadlincote Derbyshire DE11 9DH",
    "addr:postcode":"de11 9dh",
    "addr:street":"Robian Way",
    "iso:country":"GB",
    "sg:address":"Unit X Robian Way",
    "sg:city":"Swadlincote",
    "sg:classifiers":[
        {
            "category":"Manufacturing",
            "subcategory":"Metals",
            "type":"Manufacturing & Wholesale Goods"
        }
    ],
    "sg:phone":"+44 1283 210675",
    "sg:postcode":"DE11 9DH",
    "sg:province":"Derbyshire",
    "sg:tags":[
        "steel",
        "fabricator",
        "erectors"
    ],
    "wof:name":"Dale Engineering (B O T) Ltd",
    "wof:placetype":"venue"
},
  "geometry": {"coordinates":[-1.552209,52.774094],"type":"Point"}
}