{
  "type": "Feature",
  "properties": {
    "addr:full":"Suite 109, Queensway Ho, 275 High Rd Stratford Greater London E15 2TS",
    "addr:housenumber":"suite 109;275",
    "addr:postcode":"e15 2ts",
    "addr:street":"Queensway Ho;High Rd",
    "iso:country":"GB",
    "sg:address":"Suite 109, Queensway Ho, 275 High Rd",
    "sg:city":"Stratford",
    "sg:classifiers":[
        {
            "category":"Retail",
            "subcategory":"Storage",
            "type":"Services"
        }
    ],
    "sg:phone":"+44 20 8555 3192",
    "sg:postcode":"E15 2TS",
    "sg:province":"Greater London",
    "sg:tags":[
        "household",
        "removal"
    ],
    "wof:name":"One Step Up Removals",
    "wof:placetype":"venue"
},
  "geometry": {"coordinates":[-0.0087400004,51.5419883728],"type":"Point"}
}