{
  "type": "Feature",
  "properties": {
    "addr:full":"Suite 2, 15 Broad Ct, Covent Gdn London Greater London WC2B 5QN",
    "addr:housenumber":"suite 2 15",
    "addr:postcode":"wc2b 5qn",
    "addr:street":"Broad Ct Covent Gdn",
    "iso:country":"GB",
    "sg:address":"Suite 2, 15 Broad Ct, Covent Gdn",
    "sg:city":"London",
    "sg:classifiers":[
        {
            "category":"Professional",
            "subcategory":"Accounting & Tax Preparation",
            "type":"Services"
        }
    ],
    "sg:postcode":"WC2B 5QN",
    "sg:province":"Greater London",
    "sg:tags":[
        "accountant"
    ],
    "wof:name":"Bach,Alan,",
    "wof:placetype":"venue"
},
  "geometry": {"coordinates":[-0.122222,51.514126],"type":"Point"}
}