{
  "type": "Feature",
  "properties": {
    "iso:country":"GB",
    "sg:address":"Stroods, Stevens Lane, Felsted",
    "sg:city":"Dunmow",
    "sg:classifiers":[
        {
            "category":"Home & Garden",
            "subcategory":"Kitchen Supply",
            "type":"Retail Goods"
        }
    ],
    "sg:phone":"+44 1371 821300",
    "sg:postcode":"CM6 3NJ",
    "sg:province":"Essex",
    "sg:tags":[
        "ware"
    ],
    "wof:name":"THE COUNTER SAVER COMPANY",
    "wof:placetype":"venue"
},
  "geometry": {"coordinates":[0.43375,51.855976],"type":"Point"}
}