{
  "type": "Feature",
  "properties": {
    "iso:country":"GB",
    "sg:address":"47 Station Road",
    "sg:city":"Redhill",
    "sg:classifiers":[
        {
            "category":"Professional",
            "type":"Services"
        },
        {
            "category":"Deli",
            "type":"Food & Drink"
        }
    ],
    "sg:phone":"+44 1737 767879",
    "sg:postcode":"RH1 1QH",
    "sg:province":"Surrey",
    "sg:tags":[
        "delivery",
        "sandwich",
        "caterer"
    ],
    "wof:name":"Stuffins",
    "wof:placetype":"venue"
},
  "geometry": {"coordinates":[-0.169817999,51.2405967712],"type":"Point"}
}