{
  "type": "Feature",
  "properties": {
    "addr:full":"37 Parc Gwelfor, Dyserth Rhyl Conwy LL18 6LN",
    "addr:housenumber":"37",
    "addr:postcode":"ll18 6ln",
    "addr:street":"Parc Gwelfor",
    "iso:country":"GB",
    "sg:address":"37 Parc Gwelfor, Dyserth",
    "sg:city":"Rhyl",
    "sg:classifiers":[
        {
            "category":"Building & Trades",
            "subcategory":"Construction",
            "type":"Services"
        }
    ],
    "sg:postcode":"LL18 6LN",
    "sg:province":"Conwy",
    "sg:tags":[
        "builder"
    ],
    "wof:name":"J D Construction",
    "wof:placetype":"venue"
},
  "geometry": {"coordinates":[-3.402939,53.303638],"type":"Point"}
}