{
  "type": "Feature",
  "properties": {
    "addr:full":"11 Market Place Eyemouth Scottish Borders TD14 5HE",
    "addr:housenumber":"11",
    "addr:postcode":"td14 5he",
    "addr:street":"Market Place Eyemouth",
    "iso:country":"GB",
    "sg:address":"11 Market Place",
    "sg:city":"Eyemouth",
    "sg:classifiers":[
        {
            "category":"Shopping",
            "subcategory":"News",
            "type":"Retail Goods"
        }
    ],
    "sg:phone":"+44 1890 750279",
    "sg:postcode":"TD14 5HE",
    "sg:province":"Scottish Borders",
    "sg:tags":[
        "newsagent"
    ],
    "wof:name":"J HORNE",
    "wof:placetype":"venue"
},
  "geometry": {"coordinates":[-2.089545,55.872364],"type":"Point"}
}