{
  "type": "Feature",
  "properties": {
    "iso:country":"GB",
    "sg:address":"New York Industrial Estate, New York Way",
    "sg:city":"Newcastle-upon-tyne",
    "sg:classifiers":[
        {
            "category":"Professional",
            "subcategory":"Engineering",
            "type":"Services"
        },
        {
            "category":"Real Estate",
            "subcategory":"Real Estate Operator",
            "type":"Services"
        }
    ],
    "sg:phone":"+44 191 296 3444",
    "sg:postcode":"NE27 0QF",
    "sg:province":"Northumberland",
    "sg:tags":[
        "instrumentation",
        "consultant",
        "engineer"
    ],
    "wof:name":"Scotia Instrumentation Ltd",
    "wof:placetype":"venue"
},
  "geometry": {"coordinates":[-1.5061490536,55.027721405],"type":"Point"}
}