{
  "type": "Feature",
  "properties": {
    "iso:country":"GB",
    "sg:address":"33 High Street, Keynsham",
    "sg:city":"Bristol",
    "sg:classifiers":[
        {
            "category":"Insurance",
            "subcategory":"Insurance Agent",
            "type":"Services"
        }
    ],
    "sg:postcode":"BS31 1DP",
    "sg:province":"City of Bristol",
    "wof:name":"Colonnade Insurance Brokers",
    "wof:placetype":"venue"
},
  "geometry": {"coordinates":[-2.498643,51.416389],"type":"Point"}
}