{
  "type": "Feature",
  "properties": {
    "addr:full":"5 Overton Walk, Dyce Aberdeen Aberdeen City AB21 7FZ",
    "addr:housenumber":"5",
    "addr:postcode":"ab21 7fz",
    "addr:street":"Overton Walk",
    "iso:country":"GB",
    "sg:address":"5 Overton Walk, Dyce",
    "sg:city":"Aberdeen",
    "sg:classifiers":[
        {
            "category":"Retail",
            "subcategory":"Driving School",
            "type":"Services"
        }
    ],
    "sg:phone":"+44 1224 725103",
    "sg:postcode":"AB21 7FZ",
    "sg:province":"Aberdeen City",
    "wof:name":"Farburn Driving School",
    "wof:placetype":"venue"
},
  "geometry": {"coordinates":[-2.1751770973,57.2027244568],"type":"Point"}
}