{
  "type": "Feature",
  "properties": {
    "addr:full":"1 Lansdowne Gardens Hailsham East Sussex BN27 1LQ",
    "addr:housenumber":"1",
    "addr:postcode":"bn27 1lq",
    "addr:street":"Lansdowne Gardens",
    "iso:country":"GB",
    "sg:address":"1 Lansdowne Gardens",
    "sg:city":"Hailsham",
    "sg:classifiers":[
        {
            "category":"Home & Garden",
            "subcategory":"Household Appliances",
            "type":"Retail Goods"
        }
    ],
    "sg:postcode":"BN27 1LQ",
    "sg:province":"East Sussex",
    "sg:tags":[
        "cleaner",
        "electrical",
        "domestic",
        "vacuum"
    ],
    "wof:name":"B J Powell Domestic Appliance Services",
    "wof:placetype":"venue"
},
  "geometry": {"coordinates":[0.2512809932,50.8749656677],"type":"Point"}
}