{
  "type": "Feature",
  "properties": {
    "iso:country":"GB",
    "sg:address":"8 New Acres Nine Mile Ride",
    "sg:city":"Wokingham",
    "sg:classifiers":[
        {
            "category":"Wholesale",
            "subcategory":"Scrap",
            "type":"Manufacturing & Wholesale Goods"
        }
    ],
    "sg:phone":"+44 1344 771428",
    "sg:postcode":"RG40 3LZ",
    "sg:province":"Berkshire",
    "sg:tags":[
        "waste",
        "metal"
    ],
    "wof:name":"Cash & Collect",
    "wof:placetype":"venue"
},
  "geometry": {"coordinates":[-0.8559489846,51.3770713806],"type":"Point"}
}