{
  "type": "Feature",
  "properties": {
    "addr:full":"Stewards House Solihull West Midlands B91 3DH",
    "addr:housenumber":"solihull",
    "addr:postcode":"b91 3dh",
    "iso:country":"GB",
    "sg:address":"Stewards House",
    "sg:city":"Solihull",
    "sg:classifiers":[
        {
            "category":"Organizations",
            "subcategory":"Membership Organization",
            "type":"Services"
        }
    ],
    "sg:phone":"+44 121 705 0742",
    "sg:postcode":"B91 3DH",
    "sg:province":"West Midlands",
    "sg:tags":[
        "club"
    ],
    "wof:name":"The Royal British Legion",
    "wof:placetype":"venue"
},
  "geometry": {"coordinates":[-1.777848959,52.4150657654],"type":"Point"}
}