{
  "type": "Feature",
  "properties": {
    "iso:country":"GB",
    "sg:address":"58 Raleigh Av",
    "sg:city":"Torquay",
    "sg:classifiers":[
        {
            "category":"Farming",
            "subcategory":"Dairy Farm",
            "type":"Manufacturing & Wholesale Goods"
        }
    ],
    "sg:phone":"+44 1803 612335",
    "sg:postcode":"TQ2 6DN",
    "sg:province":"Devon",
    "wof:name":"R W Clements",
    "wof:placetype":"venue"
},
  "geometry": {"coordinates":[-3.555527,50.472984],"type":"Point"}
}