{
  "type": "Feature",
  "properties": {
    "addr:full":"Binton Farm, Binton Lane, Seale Farnham Hampshire GU10 1LQ",
    "addr:housenumber":"binton",
    "addr:postcode":"gu10 1lq",
    "addr:street":"Binton Lane",
    "iso:country":"GB",
    "sg:address":"Binton Farm, Binton Lane, Seale",
    "sg:city":"Farnham",
    "sg:classifiers":[
        {
            "category":"Professional",
            "type":"Services"
        }
    ],
    "sg:phone":"+44 1252 783606",
    "sg:postcode":"GU10 1LQ",
    "sg:province":"Hampshire",
    "sg:tags":[
        "caterer"
    ],
    "wof:name":"Occasional Cuisine Ltd.",
    "wof:placetype":"venue"
},
  "geometry": {"coordinates":[-0.716264,51.221729],"type":"Point"}
}