{
  "type": "Feature",
  "properties": {
    "addr:full":"90 The St, Tongham Farnham Hampshire GU10 1AA",
    "addr:housenumber":"90",
    "addr:postcode":"gu10 1aa",
    "addr:street":"The St",
    "iso:country":"GB",
    "sg:address":"90 The St, Tongham",
    "sg:city":"Farnham",
    "sg:classifiers":[
        {
            "category":"Farming",
            "subcategory":"Livestock Farm",
            "type":"Manufacturing & Wholesale Goods"
        },
        {
            "category":"Shopping",
            "subcategory":"Florist",
            "type":"Retail Goods"
        }
    ],
    "sg:postcode":"GU10 1AA",
    "sg:province":"Hampshire",
    "sg:tags":[
        "breeder"
    ],
    "wof:name":"Glue,R,",
    "wof:placetype":"venue"
},
  "geometry": {"coordinates":[-0.7318220139,51.2337341309],"type":"Point"}
}