{
  "type": "Feature",
  "properties": {
    "addr:full":"1 Lucknow Drive Sutton-in-ashfield Nottinghamshire NG17 4LS",
    "addr:housenumber":"1",
    "addr:postcode":"ng17 4ls",
    "addr:street":"Lucknow Drive",
    "iso:country":"GB",
    "sg:address":"1 Lucknow Drive",
    "sg:city":"Sutton-in-ashfield",
    "sg:classifiers":[
        {
            "category":"Building & Trades",
            "subcategory":"Equipment Rental",
            "type":"Services"
        }
    ],
    "sg:phone":"+44 1623 516747",
    "sg:postcode":"NG17 4LS",
    "sg:province":"Nottinghamshire",
    "sg:tags":[
        "plant",
        "tool",
        "hire",
        "centre"
    ],
    "wof:name":"THE HANDI HIRE GROUP LTD",
    "wof:placetype":"venue"
},
  "geometry": {"coordinates":[-1.243789,53.127899],"type":"Point"}
}