{
  "type": "Feature",
  "properties": {
    "addr:full":"Phoenix Retail Park Paisley Renfrewshire PA1 2BH",
    "addr:postcode":"pa1 2bh",
    "iso:country":"GB",
    "sg:address":"Phoenix Retail Park",
    "sg:city":"Paisley",
    "sg:classifiers":[
        {
            "category":"Travel",
            "subcategory":"Hotels & Motels",
            "type":"Entertainment"
        }
    ],
    "sg:phone":"+44 141 887 4865",
    "sg:postcode":"PA1 2BH",
    "sg:province":"Renfrewshire",
    "wof:name":"Travel Inn",
    "wof:placetype":"venue"
},
  "geometry": {"coordinates":[-4.45808,55.840508],"type":"Point"}
}