{
  "type": "Feature",
  "properties": {
    "addr:full":"Monkwood Road, Rawmarsh Rotherham South Yorkshire S62 7GA",
    "addr:postcode":"s62 7ga",
    "addr:street":"Monkwood Road",
    "iso:country":"GB",
    "sg:address":"Monkwood Road, Rawmarsh",
    "sg:city":"Rotherham",
    "sg:classifiers":[
        {
            "category":"Education",
            "subcategory":"School",
            "type":"Public Place"
        },
        {
            "category":"Government",
            "subcategory":"Office",
            "type":"Public Place"
        }
    ],
    "sg:phone":"+44 1709 710672",
    "sg:postcode":"S62 7GA",
    "sg:province":"South Yorkshire",
    "sg:tags":[
        "local",
        "authority"
    ],
    "wof:name":"Rawmarsh Comprehensive School",
    "wof:placetype":"venue"
},
  "geometry": {"coordinates":[-1.354484,53.470181],"type":"Point"}
}