{
  "type": "Feature",
  "properties": {
    "addr:full":"73 New Bond Street London Greater London W1S 1RS",
    "addr:housenumber":"73",
    "addr:postcode":"w1s 1rs",
    "addr:street":"New Bond Street",
    "iso:country":"GB",
    "sg:address":"73 New Bond Street",
    "sg:city":"London",
    "sg:classifiers":[
        {
            "category":"Real Estate",
            "subcategory":"Real Estate Agent",
            "type":"Services"
        }
    ],
    "sg:postcode":"W1S 1RS",
    "sg:province":"Greater London",
    "wof:name":"Andrew Wilson & Co",
    "wof:placetype":"venue"
},
  "geometry": {"coordinates":[-0.145839,51.513859],"type":"Point"}
}