{
  "type": "Feature",
  "properties": {
    "addr:full":"Jammy Cotts, Moorland Drive, Stocksbridge Sheffield South Yorkshire S36 1EB",
    "addr:housenumber":"cotts",
    "addr:postcode":"s36 1eb",
    "addr:street":"Moorland Drive",
    "iso:country":"GB",
    "sg:address":"Jammy Cotts, Moorland Drive, Stocksbridge",
    "sg:city":"Sheffield",
    "sg:classifiers":[
        {
            "category":"Building & Trades",
            "subcategory":"Plumbing",
            "type":"Services"
        }
    ],
    "sg:phone":"+44 114 288 5485",
    "sg:postcode":"S36 1EB",
    "sg:province":"South Yorkshire",
    "sg:tags":[
        "heating"
    ],
    "wof:name":"B Rogers Plumbing & Heating Contractor",
    "wof:placetype":"venue"
},
  "geometry": {"coordinates":[-1.5910739899,53.4819717407],"type":"Point"}
}