{
  "type": "Feature",
  "properties": {
    "addr:full":"43 Station Road Aldershot Hampshire GU11 1BA",
    "addr:housenumber":"43",
    "addr:postcode":"gu11 1ba",
    "addr:street":"Station Road",
    "iso:country":"GB",
    "sg:address":"43 Station Road",
    "sg:city":"Aldershot",
    "sg:classifiers":[
        {
            "category":"Restaurant",
            "type":"Food & Drink"
        }
    ],
    "sg:phone":"+44 1252 314042",
    "sg:postcode":"GU11 1BA",
    "sg:province":"Hampshire",
    "wof:name":"Pizzeria Countrymans",
    "wof:placetype":"venue"
},
  "geometry": {"coordinates":[-0.761537,51.249306],"type":"Point"}
}