{
  "type": "Feature",
  "properties": {
    "iso:country":"GB",
    "sg:address":"43 Station Road",
    "sg:city":"Aldershot",
    "sg:classifiers":[
        {
            "category":"Restaurant",
            "type":"Food & Drink"
        }
    ],
    "sg:phone":"+44 1252 314042",
    "sg:postcode":"GU11 1BA",
    "sg:province":"Hampshire",
    "wof:name":"Pizzeria Countrymans",
    "wof:placetype":"venue"
},
  "geometry": {"coordinates":[-0.761537,51.249306],"type":"Point"}
}