{
  "type": "Feature",
  "properties": {
    "addr:full":"Marlowe House, 109 Station Rd Sidcup Kent DA15 7ET",
    "addr:housenumber":"109",
    "addr:postcode":"da15 7et",
    "addr:street":"Station Rd",
    "iso:country":"GB",
    "sg:address":"Marlowe House, 109 Station Rd",
    "sg:city":"Sidcup",
    "sg:classifiers":[
        {
            "category":"Shopping",
            "subcategory":"Books",
            "type":"Retail Goods"
        }
    ],
    "sg:phone":"+44 20 8309 7000",
    "sg:postcode":"DA15 7ET",
    "sg:province":"Kent",
    "wof:name":"United Business Media",
    "wof:placetype":"venue"
},
  "geometry": {"coordinates":[0.1024570018,51.4338798523],"type":"Point"}
}