{
  "type": "Feature",
  "properties": {
    "iso:country":"GB",
    "sg:address":"20 Church Lane",
    "sg:city":"London",
    "sg:classifiers":[
        {
            "category":"Real Estate",
            "subcategory":"Real Estate Operator",
            "type":"Services"
        }
    ],
    "sg:phone":"+44 20 8539 2009",
    "sg:postcode":"E11 1HG",
    "sg:province":"Greater London",
    "sg:tags":[
        "letting",
        "agent"
    ],
    "wof:name":"Theydon Property Services Ltd.",
    "wof:placetype":"venue"
},
  "geometry": {"coordinates":[0.0089090001,51.5681724548],"type":"Point"}
}