{
  "type": "Feature",
  "properties": {
    "iso:country":"GB",
    "sg:address":"Union Road",
    "sg:city":"Oldbury",
    "sg:classifiers":[
        {
            "category":"Structure",
            "subcategory":"Warehouse",
            "type":"Public Place"
        }
    ],
    "sg:phone":"+44 121 544 3222",
    "sg:postcode":"B69 3EX",
    "sg:province":"West Midlands",
    "wof:name":"Confill (Midlands) Ltd.",
    "wof:placetype":"venue"
},
  "geometry": {"coordinates":[-2.025362,52.513588],"type":"Point"}
}