{
  "type": "Feature",
  "properties": {
    "iso:country":"GB",
    "sg:address":"Prince Regent House, High St, Coleshill",
    "sg:city":"Birmingham",
    "sg:classifiers":[
        {
            "category":"Professional",
            "subcategory":"Employment Agencies",
            "type":"Services"
        }
    ],
    "sg:phone":"+44 1675 466611",
    "sg:postcode":"B46 3BP",
    "sg:province":"Warwickshire",
    "sg:tags":[
        "consultant"
    ],
    "wof:name":"Alexander Mann Associates",
    "wof:placetype":"venue"
},
  "geometry": {"coordinates":[-1.705594,52.497486],"type":"Point"}
}