{
  "type": "Feature",
  "properties": {
    "addr:full":"East Walk Seaton Devon EX12 2NP",
    "addr:postcode":"ex12 2np",
    "addr:street":"East Walk",
    "iso:country":"GB",
    "sg:address":"East Walk",
    "sg:city":"Seaton",
    "sg:classifiers":[
        {
            "category":"Travel",
            "subcategory":"Hotels & Motels",
            "type":"Entertainment"
        }
    ],
    "sg:phone":"+44 1297 20560",
    "sg:postcode":"EX12 2NP",
    "sg:province":"Devon",
    "wof:name":"Mariners Hotel",
    "wof:placetype":"venue"
},
  "geometry": {"coordinates":[-3.0758090019,50.7045402527],"type":"Point"}
}