{
  "type": "Feature",
  "properties": {
    "addr:full":"1 Margeth Road Billericay Essex CM12 9UT",
    "addr:housenumber":"1",
    "addr:postcode":"cm12 9ut",
    "addr:street":"Margeth Road",
    "iso:country":"GB",
    "sg:address":"1 Margeth Road",
    "sg:city":"Billericay",
    "sg:classifiers":[
        {
            "category":"Professional",
            "subcategory":"Management & Consulting",
            "type":"Services"
        },
        {
            "category":"Professional",
            "subcategory":"Computer Services",
            "type":"Services"
        }
    ],
    "sg:postcode":"CM12 9UT",
    "sg:province":"Essex",
    "sg:tags":[
        "consultant",
        "business"
    ],
    "wof:name":"Exergis Consultants Ltd.",
    "wof:placetype":"venue"
},
  "geometry": {"coordinates":[0.427284,51.593658],"type":"Point"}
}