{
  "type": "Feature",
  "properties": {
    "addr:full":"Pasture Farm, Main St Newark Nottinghamshire NG22 9LP",
    "addr:postcode":"ng22 9lp",
    "addr:street":"Main St",
    "iso:country":"GB",
    "sg:address":"Pasture Farm, Main St",
    "sg:city":"Newark",
    "sg:classifiers":[
        {
            "category":"Personal",
            "type":"Services"
        }
    ],
    "sg:phone":"+44 1623 836291",
    "sg:postcode":"NG22 9LP",
    "sg:province":"Nottinghamshire",
    "sg:tags":[
        "wedding"
    ],
    "wof:name":"Victorian Carriages",
    "wof:placetype":"venue"
},
  "geometry": {"coordinates":[-0.9691600204,53.212020874],"type":"Point"}
}