{
  "type": "Feature",
  "properties": {
    "iso:country":"GB",
    "sg:address":"30 Lancaster Gate",
    "sg:city":"Bayswater",
    "sg:classifiers":[
        {
            "category":"Wholesale",
            "subcategory":"Books, Periodicals, & Newspapers",
            "type":"Manufacturing & Wholesale Goods"
        }
    ],
    "sg:phone":"+44 20 7413 4334",
    "sg:postcode":"W2 3LP",
    "sg:province":"Greater London",
    "sg:tags":[
        "publishing"
    ],
    "wof:name":"Medeconomics",
    "wof:placetype":"venue"
},
  "geometry": {"coordinates":[-0.179835,51.511852],"type":"Point"}
}