{
  "type": "Feature",
  "properties": {
    "addr:full":"20 High Street, Grantchester Cambridge Cambridgeshire CB3 9NF",
    "addr:housenumber":"20",
    "addr:postcode":"cb3 9nf",
    "addr:street":"High Street",
    "iso:country":"GB",
    "sg:address":"20 High Street, Grantchester",
    "sg:city":"Cambridge",
    "sg:classifiers":[
        {
            "category":"Autos & Motor Vehicles",
            "subcategory":"Automobile Sales",
            "type":"Retail Goods"
        }
    ],
    "sg:phone":"+44 1223 847700",
    "sg:postcode":"CB3 9NF",
    "sg:province":"Cambridgeshire",
    "sg:tags":[
        "car"
    ],
    "wof:name":"Sam Desira",
    "wof:placetype":"venue"
},
  "geometry": {"coordinates":[0.0941080004,52.1801490784],"type":"Point"}
}