{
  "type": "Feature",
  "properties": {
    "addr:full":"3 Castlemaine Avenue Croydon Surrey CR0 2TB",
    "addr:housenumber":"3",
    "addr:postcode":"cr0 2tb",
    "addr:street":"Castlemaine Avenue",
    "iso:country":"GB",
    "sg:address":"3 Castlemaine Avenue",
    "sg:city":"Croydon",
    "sg:classifiers":[
        {
            "category":"Professional",
            "subcategory":"Business Services",
            "type":"Services"
        }
    ],
    "sg:phone":"+44 20 7688 7197",
    "sg:postcode":"CR0 2TB",
    "sg:province":"Surrey",
    "sg:tags":[
        "import",
        "export",
        "agent"
    ],
    "wof:name":"F S International Ltd.",
    "wof:placetype":"venue"
},
  "geometry": {"coordinates":[-0.104489997,51.380191803],"type":"Point"}
}