{
  "type": "Feature",
  "properties": {
    "addr:full":"Field Farm, Little Hereford Ludlow Herefordshire SY8 4AU",
    "addr:postcode":"sy8 4au",
    "addr:street":"Hereford",
    "iso:country":"GB",
    "sg:address":"Field Farm, Little Hereford",
    "sg:city":"Ludlow",
    "sg:classifiers":[
        {
            "category":"Farming",
            "subcategory":"Livestock Farm",
            "type":"Manufacturing & Wholesale Goods"
        }
    ],
    "sg:postcode":"SY8 4AU",
    "sg:province":"Herefordshire",
    "sg:tags":[
        "others"
    ],
    "wof:name":"R S R & D V Hamer",
    "wof:placetype":"venue"
},
  "geometry": {"coordinates":[-2.701775,52.308125],"type":"Point"}
}