{
  "type": "Feature",
  "properties": {
    "iso:country":"GB",
    "sg:address":"48 Padgate La",
    "sg:city":"Warrington",
    "sg:classifiers":[
        {
            "category":"Professional",
            "subcategory":"Computer Services",
            "type":"Services"
        }
    ],
    "sg:phone":"+44 1925 658841",
    "sg:postcode":"WA1 3RU",
    "sg:province":"Cheshire",
    "sg:tags":[
        "system",
        "software"
    ],
    "wof:name":"Mabico",
    "wof:placetype":"venue"
},
  "geometry": {"coordinates":[-2.572973,53.397991],"type":"Point"}
}