{
  "type": "Feature",
  "properties": {
    "addr:full":"Carr-bridge Carr Bridge Highland PH23 3AA",
    "addr:postcode":"ph23 3aa",
    "addr:street":"Carr-Bridge Carr Bridge",
    "iso:country":"GB",
    "sg:address":"Carr-bridge",
    "sg:city":"Carr Bridge",
    "sg:classifiers":[
        {
            "category":"Travel",
            "subcategory":"Hotels & Motels",
            "type":"Entertainment"
        }
    ],
    "sg:phone":"+44 1479 841240",
    "sg:postcode":"PH23 3AA",
    "sg:province":"Highland",
    "wof:name":"Fairwinds Hotel & Chalets",
    "wof:placetype":"venue"
},
  "geometry": {"coordinates":[-3.801759,57.282429],"type":"Point"}
}