{
  "type": "Feature",
  "properties": {
    "iso:country":"GB",
    "sg:address":"214 Binley Road",
    "sg:city":"Coventry",
    "sg:classifiers":[
        {
            "category":"Bars & Pubs",
            "type":"Food & Drink"
        },
        {
            "category":"Community Center",
            "subcategory":"Social",
            "type":"Public Place"
        }
    ],
    "sg:phone":"+44 24 7645 1046",
    "sg:postcode":"CV3 1HG",
    "sg:province":"Warwickshire",
    "sg:tags":[
        "pubs",
        "house",
        "inn",
        "activity"
    ],
    "wof:name":"Biggin Hall Hotel",
    "wof:placetype":"venue"
},
  "geometry": {"coordinates":[-1.470735,52.407055],"type":"Point"}
}