{
  "type": "Feature",
  "properties": {
    "addr:full":"191 Anns Hill Road Gosport Hampshire PO12 3RF",
    "addr:housenumber":"191",
    "addr:postcode":"po12 3rf",
    "addr:street":"Anns Hill Road",
    "iso:country":"GB",
    "sg:address":"191 Anns Hill Road",
    "sg:city":"Gosport",
    "sg:classifiers":[
        {
            "category":"Shopping",
            "subcategory":"Baby Store",
            "type":"Retail Goods"
        }
    ],
    "sg:phone":"+44 23 9235 0158",
    "sg:postcode":"PO12 3RF",
    "sg:province":"Hampshire",
    "sg:tags":[
        "equipment",
        "nursery",
        "accessory"
    ],
    "wof:name":"Ankle Biters",
    "wof:placetype":"venue"
},
  "geometry": {"coordinates":[-1.1490360498,50.793258667],"type":"Point"}
}