{
  "type": "Feature",
  "properties": {
    "addr:full":"70 South Street Lancing West Sussex BN15 8AJ",
    "addr:housenumber":"70",
    "addr:postcode":"bn15 8aj",
    "addr:street":"South Street",
    "iso:country":"GB",
    "sg:address":"70 South Street",
    "sg:city":"Lancing",
    "sg:classifiers":[
        {
            "category":"Professional",
            "subcategory":"Accounting & Tax Preparation",
            "type":"Services"
        }
    ],
    "sg:phone":"+44 1903 854686",
    "sg:postcode":"BN15 8AJ",
    "sg:province":"West Sussex",
    "sg:tags":[
        "accountant"
    ],
    "wof:name":"Till & Cloake",
    "wof:placetype":"venue"
},
  "geometry": {"coordinates":[-0.3227500021,50.8247680664],"type":"Point"}
}