{
  "type": "Feature",
  "properties": {
    "iso:country":"GB",
    "sg:address":"Berkeley House, 15 Hay Hill",
    "sg:city":"London",
    "sg:classifiers":[
        {
            "category":"Banks & Credit Unions",
            "subcategory":"Financial Services",
            "type":"Services"
        }
    ],
    "sg:phone":"+44 20 7499 0990",
    "sg:postcode":"W1J 8NS",
    "sg:province":"Greater London",
    "sg:tags":[
        "adviser"
    ],
    "wof:name":"Aitchison & Colegrave Ltd.",
    "wof:placetype":"venue"
},
  "geometry": {"coordinates":[-0.1433449984,51.5090942383],"type":"Point"}
}