{
  "type": "Feature",
  "properties": {
    "addr:full":"46 Southgate, Market Weighton York East Riding of Yorkshire YO43 3BQ",
    "addr:housenumber":"46",
    "addr:postcode":"yo43 3bq",
    "addr:street":"Southgate Market",
    "iso:country":"GB",
    "sg:address":"46 Southgate, Market Weighton",
    "sg:city":"York",
    "sg:classifiers":[
        {
            "category":"Retail",
            "subcategory":"Veterinary Services",
            "type":"Services"
        }
    ],
    "sg:postcode":"YO43 3BQ",
    "sg:province":"East Riding of Yorkshire",
    "sg:tags":[
        "surgeon"
    ],
    "wof:name":"Wicstun Veterinary Group",
    "wof:placetype":"venue"
},
  "geometry": {"coordinates":[-0.6638849974,53.8620376587],"type":"Point"}
}