{
  "type": "Feature",
  "properties": {
    "iso:country":"GB",
    "sg:address":"Hollow Hedge, Holly Hedges Lane",
    "sg:city":"Hemel Hempstead",
    "sg:classifiers":[
        {
            "category":"Retail",
            "subcategory":"Auto Repair",
            "type":"Services"
        }
    ],
    "sg:postcode":"HP3 0PE",
    "sg:province":"Hertfordshire",
    "sg:tags":[
        "modification",
        "garage"
    ],
    "wof:name":"Safari Services",
    "wof:placetype":"venue"
},
  "geometry": {"coordinates":[-0.522149,51.706593],"type":"Point"}
}