{
  "type": "Feature",
  "properties": {
    "iso:country":"GB",
    "sg:address":"114 New Chester Rd, New Ferry Wirral",
    "sg:city":"Wirral",
    "sg:classifiers":[
        {
            "category":"Communications",
            "subcategory":"Film & Video Production",
            "type":"Services"
        }
    ],
    "sg:phone":"+44 151 645 8899",
    "sg:postcode":"CH62 5AG",
    "sg:province":"Cheshire",
    "sg:tags":[
        "recording",
        "studio"
    ],
    "wof:name":"Petlyn Audio Services",
    "wof:placetype":"venue"
},
  "geometry": {"coordinates":[-2.997026,53.360191],"type":"Point"}
}