{
  "type": "Feature",
  "properties": {
    "addr:full":"3 Station App, Barnehurst Bexleyheath Kent DA7 6HQ",
    "addr:housenumber":"3",
    "addr:postcode":"da7 6hq",
    "iso:country":"GB",
    "sg:address":"3 Station App, Barnehurst",
    "sg:city":"Bexleyheath",
    "sg:classifiers":[
        {
            "category":"Building & Trades",
            "subcategory":"Construction",
            "type":"Services"
        }
    ],
    "sg:phone":"+44 1322 527339",
    "sg:postcode":"DA7 6HQ",
    "sg:province":"Kent",
    "sg:tags":[
        "builder"
    ],
    "wof:name":"Fenwick Builders",
    "wof:placetype":"venue"
},
  "geometry": {"coordinates":[0.1589190066,51.4649620056],"type":"Point"}
}