{
  "type": "Feature",
  "properties": {
    "addr:full":"St Albans Service Centre, Pearce House, Acrewood Way St Albans Hertfordshire AL4 0JY",
    "addr:postcode":"al4 0jy",
    "addr:street":"Acrewood Way",
    "iso:country":"GB",
    "sg:address":"St Albans Service Centre, Pearce House, Acrewood Way",
    "sg:city":"St Albans",
    "sg:classifiers":[
        {
            "category":"Utilities",
            "subcategory":"Refuse",
            "type":"Services"
        }
    ],
    "sg:phone":"+44 1727 839389",
    "sg:postcode":"AL4 0JY",
    "sg:province":"Hertfordshire",
    "sg:tags":[
        "disposal",
        "waste"
    ],
    "wof:name":"Cleanaway Ltd.",
    "wof:placetype":"venue"
},
  "geometry": {"coordinates":[-0.278234,51.751308],"type":"Point"}
}