{
  "type": "Feature",
  "properties": {
    "addr:full":"15 Foxcotte Road, Charlton Andover Hampshire SP10 4AR",
    "addr:housenumber":"15",
    "addr:postcode":"sp10 4ar",
    "addr:street":"Foxcotte Road",
    "iso:country":"GB",
    "sg:address":"15 Foxcotte Road, Charlton",
    "sg:city":"Andover",
    "sg:classifiers":[
        {
            "category":"Retail",
            "subcategory":"Veterinary Services",
            "type":"Services"
        }
    ],
    "sg:phone":"+44 1264 358808",
    "sg:postcode":"SP10 4AR",
    "sg:province":"Hampshire",
    "sg:tags":[
        "surgeon"
    ],
    "wof:name":"Foxcotte Veterinary Group",
    "wof:placetype":"venue"
},
  "geometry": {"coordinates":[-1.5015490055,51.2209663391],"type":"Point"}
}