{
  "type": "Feature",
  "properties": {
    "iso:country":"GB",
    "sg:address":"4 Pwllycrochan Avenue",
    "sg:city":"Colwyn Bay",
    "sg:classifiers":[
        {
            "category":"Health Services",
            "subcategory":"Doctor",
            "type":"Services"
        }
    ],
    "sg:phone":"+44 1492 532125",
    "sg:postcode":"LL29 7DA",
    "sg:province":"Conwy",
    "sg:tags":[
        "practitioners"
    ],
    "wof:name":"Rossland Surgery",
    "wof:placetype":"venue"
},
  "geometry": {"coordinates":[-3.733733,53.296368],"type":"Point"}
}