{
  "type": "Feature",
  "properties": {
    "addr:full":"Cerrig Y Lloi Farm, South Stack Rd Holyhead Isle of Anglesey LL65 1LF",
    "addr:postcode":"ll65 1lf",
    "addr:street":"South Stack Rd",
    "iso:country":"GB",
    "sg:address":"Cerrig Y Lloi Farm, South Stack Rd",
    "sg:city":"Holyhead",
    "sg:classifiers":[
        {
            "category":"Farming",
            "subcategory":"Dairy Farm",
            "type":"Manufacturing & Wholesale Goods"
        }
    ],
    "sg:phone":"+44 1407 764361",
    "sg:postcode":"LL65 1LF",
    "sg:province":"Isle of Anglesey",
    "wof:name":"O J Thomas",
    "wof:placetype":"venue"
},
  "geometry": {"coordinates":[-4.6307139397,53.3063697815],"type":"Point"}
}