{
  "type": "Feature",
  "properties": {
    "addr:full":"4 Fordbridge Road Ashford Greater London TW15 2SG",
    "addr:housenumber":"4",
    "addr:postcode":"tw15 2sg",
    "addr:street":"Fordbridge Road",
    "iso:country":"GB",
    "sg:address":"4 Fordbridge Road",
    "sg:city":"Ashford",
    "sg:classifiers":[
        {
            "category":"Health Services",
            "subcategory":"Doctor",
            "type":"Services"
        },
        {
            "category":"Health Services",
            "subcategory":"Clinic",
            "type":"Services"
        }
    ],
    "sg:phone":"+44 1784 242251",
    "sg:postcode":"TW15 2SG",
    "sg:province":"Greater London",
    "sg:tags":[
        "nh",
        "practitioners"
    ],
    "wof:name":"The Fordbridge Medical Centre",
    "wof:placetype":"venue"
},
  "geometry": {"coordinates":[-0.46219,51.432358],"type":"Point"}
}