{
  "type": "Feature",
  "properties": {
    "iso:country":"GB",
    "sg:address":"36 The Glebe, Cumnor",
    "sg:city":"Oxford",
    "sg:classifiers":[
        {
            "category":"Building & Trades",
            "subcategory":"Landscaping Services",
            "type":"Services"
        }
    ],
    "sg:phone":"+44 1865 864229",
    "sg:postcode":"OX2 9QA",
    "sg:province":"Oxfordshire",
    "sg:tags":[
        "gardening"
    ],
    "wof:name":"Sunshine Gardens",
    "wof:placetype":"venue"
},
  "geometry": {"coordinates":[-1.310649,51.7463],"type":"Point"}
}