{
  "type": "Feature",
  "properties": {
    "addr:full":"Spring Street, Rishton Blackburn Lancashire BB1 4LL",
    "addr:postcode":"bb1 4ll",
    "addr:street":"Spring Street",
    "iso:country":"GB",
    "sg:address":"Spring Street, Rishton",
    "sg:city":"Blackburn",
    "sg:classifiers":[
        {
            "category":"Professional",
            "subcategory":"Engineering",
            "type":"Services"
        },
        {
            "category":"Professional",
            "subcategory":"Printing & Photocopies",
            "type":"Services"
        },
        {
            "category":"Building & Trades",
            "subcategory":"Electrical",
            "type":"Services"
        }
    ],
    "sg:phone":"+44 1254 876353",
    "sg:postcode":"BB1 4LL",
    "sg:province":"Lancashire",
    "sg:tags":[
        "engraving",
        "engineer",
        "electrician",
        "contractor"
    ],
    "wof:name":"Burns Contracting Barrow Ltd",
    "wof:placetype":"venue"
},
  "geometry": {"coordinates":[-2.417644,53.768017],"type":"Point"}
}