{
  "type": "Feature",
  "properties": {
    "addr:full":"5 Milton Avenue Braintree Essex CM7 1AD",
    "addr:housenumber":"5",
    "addr:postcode":"cm7 1ad",
    "addr:street":"Milton Avenue",
    "iso:country":"GB",
    "sg:address":"5 Milton Avenue",
    "sg:city":"Braintree",
    "sg:classifiers":[
        {
            "category":"Personal",
            "type":"Services"
        }
    ],
    "sg:phone":"+44 1376 327869",
    "sg:postcode":"CM7 1AD",
    "sg:province":"Essex",
    "sg:tags":[
        "wedding"
    ],
    "wof:name":"John Warren",
    "wof:placetype":"venue"
},
  "geometry": {"coordinates":[0.555876,51.867191],"type":"Point"}
}