{
  "type": "Feature",
  "properties": {
    "addr:full":"141 St. Marys Lane Upminster Essex RM14 3BL",
    "addr:housenumber":"141",
    "addr:postcode":"rm14 3bl",
    "addr:street":"St. Marys Lane",
    "iso:country":"GB",
    "sg:address":"141 St. Marys Lane",
    "sg:city":"Upminster",
    "sg:classifiers":[
        {
            "category":"Insurance",
            "subcategory":"Insurance Agent",
            "type":"Services"
        }
    ],
    "sg:phone":"+44 1708 225540",
    "sg:postcode":"RM14 3BL",
    "sg:province":"Essex",
    "wof:name":"Century Insurance Centre",
    "wof:placetype":"venue"
},
  "geometry": {"coordinates":[0.249898,51.556335],"type":"Point"}
}