{
  "type": "Feature",
  "properties": {
    "iso:country":"GB",
    "sg:address":"13 Moor Top Road",
    "sg:city":"Halifax",
    "sg:classifiers":[
        {
            "category":"Banks & Credit Unions",
            "subcategory":"Bank",
            "type":"Services"
        }
    ],
    "sg:postcode":"HX2 0NP",
    "sg:province":"West Yorkshire",
    "sg:tags":[
        "stocktaking",
        "inventory"
    ],
    "wof:name":"C F S Associates",
    "wof:placetype":"venue"
},
  "geometry": {"coordinates":[-1.9151200056,53.7267684937],"type":"Point"}
}