{
  "type": "Feature",
  "properties": {
    "iso:country":"GB",
    "sg:address":"2 Creech Hill Cotts, Cranborne",
    "sg:city":"Wimborne",
    "sg:classifiers":[
        {
            "category":"Communications",
            "type":"Services"
        }
    ],
    "sg:phone":"+44 1725 517697",
    "sg:postcode":"BH21 5PN",
    "sg:province":"Dorset",
    "sg:tags":[
        "telecommunication"
    ],
    "wof:name":"Grey Advantage Ltd",
    "wof:placetype":"venue"
},
  "geometry": {"coordinates":[-1.921689,50.91935],"type":"Point"}
}