{
  "type": "Feature",
  "properties": {
    "addr:full":"10 Tewkesbury Road, Cheadle Heath Stockport Cheshire SK3 0SQ",
    "addr:housenumber":"10",
    "addr:postcode":"sk3 0sq",
    "addr:street":"Tewkesbury Road",
    "iso:country":"GB",
    "sg:address":"10 Tewkesbury Road, Cheadle Heath",
    "sg:city":"Stockport",
    "sg:classifiers":[
        {
            "category":"Building & Trades",
            "subcategory":"Construction",
            "type":"Services"
        }
    ],
    "sg:postcode":"SK3 0SQ",
    "sg:province":"Cheshire",
    "sg:tags":[
        "builder"
    ],
    "wof:name":"Parkland Builders Ltd.",
    "wof:placetype":"venue"
},
  "geometry": {"coordinates":[-2.1876211166,53.3973388672],"type":"Point"}
}