{
  "type": "Feature",
  "properties": {
    "iso:country":"GB",
    "sg:address":"Fengate Mobile Home Park",
    "sg:city":"Peterborough",
    "sg:classifiers":[
        {
            "category":"Manufacturing",
            "subcategory":"Buildings",
            "type":"Manufacturing & Wholesale Goods"
        },
        {
            "category":"Community Center",
            "type":"Public Place"
        }
    ],
    "sg:phone":"+44 1733 569088",
    "sg:postcode":"PE1 5XD",
    "sg:province":"Cambridgeshire",
    "sg:tags":[
        "mobile",
        "home",
        "leisure",
        "centre"
    ],
    "wof:name":"SYD AND LOUISE SMITH",
    "wof:placetype":"venue"
},
  "geometry": {"coordinates":[-0.2209589928,52.5749130249],"type":"Point"}
}