{
  "type": "Feature",
  "properties": {
    "addr:full":"Mid Craigie Rd, Kingsway East Dundee Dundee City DD4 7RH",
    "addr:postcode":"dd4 7rh",
    "addr:street":"Craigie Rd",
    "iso:country":"GB",
    "sg:address":"Mid Craigie Rd, Kingsway East",
    "sg:city":"Dundee",
    "sg:classifiers":[
        {
            "category":"Building & Trades",
            "subcategory":"Construction",
            "type":"Services"
        }
    ],
    "sg:phone":"+44 1382 450555",
    "sg:postcode":"DD4 7RH",
    "sg:province":"Dundee City",
    "sg:tags":[
        "management"
    ],
    "wof:name":"Pharos Consulting",
    "wof:placetype":"venue"
},
  "geometry": {"coordinates":[-2.935577,56.47731],"type":"Point"}
}