{
  "type": "Feature",
  "properties": {
    "addr:full":"44 Holly Mount, 291 Hagley Road Birmingham West Midlands B16 9LS",
    "addr:housenumber":"44;291",
    "addr:postcode":"b16 9ls",
    "addr:street":"Holly Mount;Hagley Road",
    "iso:country":"GB",
    "sg:address":"44 Holly Mount, 291 Hagley Road",
    "sg:city":"Birmingham",
    "sg:classifiers":[
        {
            "category":"Communications",
            "subcategory":"News Services",
            "type":"Services"
        }
    ],
    "sg:phone":"+44 121 455 6144",
    "sg:postcode":"B16 9LS",
    "sg:province":"West Midlands",
    "sg:tags":[
        "press"
    ],
    "wof:name":"D B M  Power Presses Ltd.",
    "wof:placetype":"venue"
},
  "geometry": {"coordinates":[-1.908604,52.478596],"type":"Point"}
}