{
  "type": "Feature",
  "properties": {
    "addr:full":"58 Stocks Bank Road Mirfield West Yorkshire WF14 9PZ",
    "addr:housenumber":"58",
    "addr:postcode":"wf14 9pz",
    "addr:street":"Stocks Bank Road",
    "iso:country":"GB",
    "sg:address":"58 Stocks Bank Road",
    "sg:city":"Mirfield",
    "sg:classifiers":[
        {
            "category":"Building & Trades",
            "subcategory":"Plumbing",
            "type":"Services"
        }
    ],
    "sg:postcode":"WF14 9PZ",
    "sg:province":"West Yorkshire",
    "sg:tags":[
        "heating"
    ],
    "wof:name":"S P S Plumbing Contractors",
    "wof:placetype":"venue"
},
  "geometry": {"coordinates":[-1.70926404,53.6797370911],"type":"Point"}
}