{
  "type": "Feature",
  "properties": {
    "iso:country":"GB",
    "sg:address":"463 Edinburgh Rd",
    "sg:city":"Glasgow",
    "sg:classifiers":[
        {
            "category":"Health Services",
            "subcategory":"Doctor",
            "type":"Services"
        }
    ],
    "sg:phone":"+44 141 770 4044",
    "sg:postcode":"G33 3AL",
    "sg:province":"Glasgow City",
    "sg:tags":[
        "practitioners"
    ],
    "wof:name":"Winter, A",
    "wof:placetype":"venue"
},
  "geometry": {"coordinates":[-4.1818737984,55.8632164001],"type":"Point"}
}