{
  "type": "Feature",
  "properties": {
    "addr:full":"222 Branston Road Burton-on-trent Derbyshire DE14 3BT",
    "addr:housenumber":"222",
    "addr:postcode":"de14 3bt",
    "addr:street":"Branston Road",
    "iso:country":"GB",
    "sg:address":"222 Branston Road",
    "sg:city":"Burton-on-trent",
    "sg:classifiers":[
        {
            "category":"Communications",
            "subcategory":"Newspaper",
            "type":"Services"
        }
    ],
    "sg:phone":"+44 1283 542721",
    "sg:postcode":"DE14 3BT",
    "sg:province":"Derbyshire",
    "sg:tags":[
        "magazine"
    ],
    "wof:name":"Ships Monthly I P C Country & Leisure Media",
    "wof:placetype":"venue"
},
  "geometry": {"coordinates":[-1.641789,52.79388],"type":"Point"}
}