{
  "type": "Feature",
  "properties": {
    "addr:full":"The Street, Westleton Saxmundham Suffolk IP17 3AD",
    "addr:postcode":"ip17 3ad",
    "addr:street":"The Street",
    "iso:country":"GB",
    "sg:address":"The Street, Westleton",
    "sg:city":"Saxmundham",
    "sg:classifiers":[
        {
            "category":"Government",
            "subcategory":"Post Office",
            "type":"Public Place"
        }
    ],
    "sg:phone":"+44 1728 648216",
    "sg:postcode":"IP17 3AD",
    "sg:province":"Suffolk",
    "wof:name":"WESTLETON POST OFFICE",
    "wof:placetype":"venue"
},
  "geometry": {"coordinates":[1.534078,52.277332],"type":"Point"}
}