{
  "type": "Feature",
  "properties": {
    "iso:country":"GB",
    "sg:address":"36 Aubrey Street",
    "sg:city":"Hereford",
    "sg:classifiers":[
        {
            "category":"Shopping",
            "subcategory":"Musical Instruments",
            "type":"Retail Goods"
        }
    ],
    "sg:phone":"+44 1568 613477",
    "sg:postcode":"HR4 0BY",
    "sg:province":"Herefordshire",
    "sg:tags":[
        "music",
        "sheet"
    ],
    "wof:name":"Capriole Music",
    "wof:placetype":"venue"
},
  "geometry": {"coordinates":[-2.718329,52.055279],"type":"Point"}
}