{
  "type": "Feature",
  "properties": {
    "addr:full":"Unit 1, Windsor Industrial Estate Hertford Hertfordshire SG13 7EW",
    "addr:housenumber":"unit 1;estate",
    "addr:postcode":"sg13 7ew",
    "addr:street":"Windsor Industrial",
    "iso:country":"GB",
    "sg:address":"Unit 1, Windsor Industrial Estate",
    "sg:city":"Hertford",
    "sg:classifiers":[
        {
            "category":"Shopping",
            "subcategory":"Clothing, Apparel, & Fashions",
            "type":"Retail Goods"
        }
    ],
    "sg:phone":"+44 1992 538003",
    "sg:postcode":"SG13 7EW",
    "sg:province":"Hertfordshire",
    "sg:tags":[
        "clothing"
    ],
    "wof:name":"Flyers Group Plc",
    "wof:placetype":"venue"
},
  "geometry": {"coordinates":[-0.07031,51.80225],"type":"Point"}
}