{
  "type": "Feature",
  "properties": {
    "iso:country":"GB",
    "sg:address":"55 Clarkehouse Road",
    "sg:city":"Sheffield",
    "sg:classifiers":[
        {
            "category":"Professional",
            "subcategory":"Accounting & Tax Preparation",
            "type":"Services"
        }
    ],
    "sg:postcode":"S10 2LE",
    "sg:province":"South Yorkshire",
    "sg:tags":[
        "accountant"
    ],
    "wof:name":"Ingram Forrest Associates",
    "wof:placetype":"venue"
},
  "geometry": {"coordinates":[-1.4944839478,53.3755645752],"type":"Point"}
}