{
  "type": "Feature",
  "properties": {
    "iso:country":"GB",
    "sg:address":"Maldon Road",
    "sg:city":"Burnham-on-crouch",
    "sg:classifiers":[
        {
            "category":"Farming",
            "subcategory":"Dairy Farm",
            "type":"Manufacturing & Wholesale Goods"
        },
        {
            "category":"Food & Beverages",
            "subcategory":"Groceries & Convenience Stores",
            "type":"Retail Goods"
        }
    ],
    "sg:phone":"+44 1621 782059",
    "sg:postcode":"CM0 8NT",
    "sg:province":"Essex",
    "wof:name":"Elm Farm Dairy Ltd.",
    "wof:placetype":"venue"
},
  "geometry": {"coordinates":[0.7951899767,51.6436958313],"type":"Point"}
}