{
  "type": "Feature",
  "properties": {
    "addr:full":"5 Penn Road, Hazlemere High Wycombe Buckinghamshire HP15 7LN",
    "addr:housenumber":"5",
    "addr:postcode":"hp15 7ln",
    "addr:street":"Penn Road",
    "iso:country":"GB",
    "sg:address":"5 Penn Road, Hazlemere",
    "sg:city":"High Wycombe",
    "sg:classifiers":[
        {
            "category":"Real Estate",
            "subcategory":"Surveying",
            "type":"Services"
        },
        {
            "category":"Real Estate",
            "subcategory":"Real Estate Agent",
            "type":"Services"
        }
    ],
    "sg:phone":"+44 1494 716919",
    "sg:postcode":"HP15 7LN",
    "sg:province":"Buckinghamshire",
    "sg:tags":[
        "surveyor",
        "valuer"
    ],
    "wof:name":"THE CHANCELLORS GROUP OF ESTATE AGENTS LTD",
    "wof:placetype":"venue"
},
  "geometry": {"coordinates":[-0.712117,51.651367],"type":"Point"}
}