{
  "type": "Feature",
  "properties": {
    "addr:full":"Unit 7 Fourways Trading Estate Lo, Ngbridge Road, Trafford Park Manchester Cheshire M17 1RJ",
    "addr:housenumber":"unit 7",
    "addr:postcode":"m17 1rj",
    "addr:street":"Trading Estate Lo Ngbridge Road",
    "iso:country":"GB",
    "sg:address":"Unit 7 Fourways Trading Estate Lo, Ngbridge Road, Trafford Park",
    "sg:city":"Manchester",
    "sg:classifiers":[
        {
            "category":"Manufacturing",
            "subcategory":"Building Materials",
            "type":"Manufacturing & Wholesale Goods"
        }
    ],
    "sg:phone":"+44 161 872 5464",
    "sg:postcode":"M17 1RJ",
    "sg:province":"Cheshire",
    "sg:tags":[
        "merchant",
        "builder"
    ],
    "wof:name":"Support Site Ltd.",
    "wof:placetype":"venue"
},
  "geometry": {"coordinates":[-2.3083589077,53.4681396484],"type":"Point"}
}