{
  "type": "Feature",
  "properties": {
    "addr:full":"10 St John Street Manchester Greater Manchester M3 4DY",
    "addr:housenumber":"10",
    "addr:postcode":"m3 4dy",
    "addr:street":"St John Street",
    "iso:country":"GB",
    "sg:address":"10 St John Street",
    "sg:city":"Manchester",
    "sg:classifiers":[
        {
            "category":"Health Services",
            "subcategory":"Doctor",
            "type":"Services"
        }
    ],
    "sg:phone":"+44 161 819 1111",
    "sg:postcode":"M3 4DY",
    "sg:province":"Greater Manchester",
    "sg:tags":[
        "surgeon"
    ],
    "wof:name":"Bethel Rosenberg",
    "wof:placetype":"venue"
},
  "geometry": {"coordinates":[-2.2509140968,53.4778137207],"type":"Point"}
}