{
  "type": "Feature",
  "properties": {
    "iso:country":"GB",
    "sg:address":"Vulcans Lane",
    "sg:city":"Workington",
    "sg:classifiers":[
        {
            "category":"Education",
            "subcategory":"Library",
            "type":"Public Place"
        },
        {
            "category":"Government",
            "subcategory":"Office",
            "type":"Public Place"
        }
    ],
    "sg:phone":"+44 1900 325170",
    "sg:postcode":"CA14 2ND",
    "sg:province":"Cumbria",
    "sg:tags":[
        "book",
        "local"
    ],
    "wof:name":"Workington Library",
    "wof:placetype":"venue"
},
  "geometry": {"coordinates":[-3.548801899,54.6446647644],"type":"Point"}
}