{
  "type": "Feature",
  "properties": {
    "iso:country":"GB",
    "sg:address":"5 East Street, Coggeshall",
    "sg:city":"Colchester",
    "sg:classifiers":[
        {
            "category":"Retail",
            "subcategory":"Repair Shop",
            "type":"Services"
        }
    ],
    "sg:phone":"+44 1376 563154",
    "sg:postcode":"CO6 1SH",
    "sg:province":"Essex",
    "sg:tags":[
        "clocks",
        "watch"
    ],
    "wof:name":"Ardley's",
    "wof:placetype":"venue"
},
  "geometry": {"coordinates":[0.6865010262,51.8711166382],"type":"Point"}
}