{
  "type": "Feature",
  "properties": {
    "addr:full":"13 Adwalton Clo, Freshbrook Swindon Wiltshire SN5 8NG",
    "addr:housenumber":"13",
    "addr:postcode":"sn5 8ng",
    "addr:street":"Adwalton Clo",
    "iso:country":"GB",
    "sg:address":"13 Adwalton Clo, Freshbrook",
    "sg:city":"Swindon",
    "sg:classifiers":[
        {
            "category":"Building & Trades",
            "subcategory":"Construction",
            "type":"Services"
        }
    ],
    "sg:postcode":"SN5 8NG",
    "sg:province":"Wiltshire",
    "sg:tags":[
        "decorator",
        "painter"
    ],
    "wof:name":"Mapstone,Kevin,",
    "wof:placetype":"venue"
},
  "geometry": {"coordinates":[-1.8316290379,51.550567627],"type":"Point"}
}