{
  "type": "Feature",
  "properties": {
    "iso:country":"GB",
    "sg:address":"7 Sharp Clo",
    "sg:city":"Bedford",
    "sg:classifiers":[
        {
            "category":"Wholesale",
            "subcategory":"Toys & Hobbies",
            "type":"Manufacturing & Wholesale Goods"
        }
    ],
    "sg:phone":"+44 1525 861007",
    "sg:postcode":"MK45 2BZ",
    "sg:province":"Bedfordshire",
    "sg:tags":[
        "game"
    ],
    "wof:name":"Learning Land",
    "wof:placetype":"venue"
},
  "geometry": {"coordinates":[-0.431133002,52.0254669189],"type":"Point"}
}