{
  "type": "Feature",
  "properties": {
    "iso:country":"GB",
    "sg:address":"Rear Of Castle Hotel, Jewel Street",
    "sg:city":"Barry",
    "sg:classifiers":[
        {
            "category":"Manufacturing",
            "subcategory":"Wood Products",
            "type":"Manufacturing & Wholesale Goods"
        },
        {
            "category":"Building & Trades",
            "subcategory":"Construction",
            "type":"Services"
        }
    ],
    "sg:phone":"+44 1446 722335",
    "sg:postcode":"CF63 3NQ",
    "sg:province":"The Vale of Glamorgan",
    "sg:tags":[
        "joinery",
        "joiner",
        "carpenter",
        "manufacturer"
    ],
    "wof:name":"Classic Joinery",
    "wof:placetype":"venue"
},
  "geometry": {"coordinates":[-3.25878,51.407261],"type":"Point"}
}