{
  "type": "Feature",
  "properties": {
    "addr:full":"403 Lichfield Road, Barton Under Needwood Burton-on-trent Derbyshire DE13 8EH",
    "addr:housenumber":"403",
    "addr:postcode":"de13 8eh",
    "addr:street":"Lichfield Road",
    "iso:country":"GB",
    "sg:address":"403 Lichfield Road, Barton Under Needwood",
    "sg:city":"Burton-on-trent",
    "sg:classifiers":[
        {
            "category":"Building & Trades",
            "subcategory":"Landscaping Services",
            "type":"Services"
        },
        {
            "category":"Farming",
            "subcategory":"Livestock Farm",
            "type":"Manufacturing & Wholesale Goods"
        }
    ],
    "sg:postcode":"DE13 8EH",
    "sg:province":"Derbyshire",
    "sg:tags":[
        "pond",
        "aquarium",
        "others"
    ],
    "wof:name":"Barton Koi Farm",
    "wof:placetype":"venue"
},
  "geometry": {"coordinates":[-1.7045359612,52.7593193054],"type":"Point"}
}