{
  "type": "Feature",
  "properties": {
    "addr:full":"23 Park Crescent Cardiff Cardiff CF14 7AQ",
    "addr:housenumber":"23",
    "addr:postcode":"cf14 7aq",
    "addr:street":"Park Crescent",
    "iso:country":"GB",
    "sg:address":"23 Park Crescent",
    "sg:city":"Cardiff",
    "sg:classifiers":[
        {
            "category":"Building & Trades",
            "subcategory":"Construction",
            "type":"Services"
        }
    ],
    "sg:phone":"+44 29 2069 2468",
    "sg:postcode":"CF14 7AQ",
    "sg:province":"Cardiff",
    "sg:tags":[
        "window",
        "replacement"
    ],
    "wof:name":"Sunningdale Windows",
    "wof:placetype":"venue"
},
  "geometry": {"coordinates":[-3.231434,51.520275],"type":"Point"}
}