{
  "type": "Feature",
  "properties": {
    "addr:full":"Frognal, Hampstead London Greater London NW3 6XH",
    "addr:postcode":"nw3 6xh",
    "addr:street":"Frognal",
    "iso:country":"GB",
    "sg:address":"Frognal, Hampstead",
    "sg:city":"London",
    "sg:classifiers":[
        {
            "category":"Education",
            "subcategory":"School",
            "type":"Public Place"
        }
    ],
    "sg:phone":"+44 20 7435 2215",
    "sg:postcode":"NW3 6XH",
    "sg:province":"Greater London",
    "sg:tags":[
        "independent",
        "preparatory",
        "foundation"
    ],
    "wof:name":"University College School",
    "wof:placetype":"venue"
},
  "geometry": {"coordinates":[-0.1813949943,51.5580596924],"type":"Point"}
}