{
  "type": "Feature",
  "properties": {
    "iso:country":"GB",
    "sg:address":"Russell Place",
    "sg:city":"Brighton",
    "sg:classifiers":[
        {
            "category":"Shopping",
            "subcategory":"Department Store",
            "type":"Retail Goods"
        }
    ],
    "sg:phone":"+44 1273 326531",
    "sg:postcode":"BN1 2LB",
    "sg:province":"East Sussex",
    "wof:name":"Debenhams Retail Plc",
    "wof:placetype":"venue"
},
  "geometry": {"coordinates":[-0.145269,50.822048],"type":"Point"}
}