{
  "type": "Feature",
  "properties": {
    "addr:full":"11 St. Annes Lane, Sutton Bonington Loughborough Loughborough Leicestershire LE12 5NJ",
    "addr:housenumber":"11",
    "addr:postcode":"le12 5nj",
    "addr:street":"St. Annes Lane",
    "iso:country":"GB",
    "sg:address":"11 St. Annes Lane, Sutton Bonington Loughborough",
    "sg:city":"Loughborough",
    "sg:classifiers":[
        {
            "category":"Health Services",
            "subcategory":"Health Practitioner",
            "type":"Services"
        }
    ],
    "sg:phone":"+44 1509 672457",
    "sg:postcode":"LE12 5NJ",
    "sg:province":"Leicestershire",
    "sg:tags":[
        "acupuncture"
    ],
    "wof:name":"A.F.M Etherton",
    "wof:placetype":"venue"
},
  "geometry": {"coordinates":[-1.249992,52.819958],"type":"Point"}
}