{
  "type": "Feature",
  "properties": {
    "addr:full":"Tir Llwyd Enterprise Park, Kinmel Bay Rhyl Conwy LL18 5JH",
    "addr:postcode":"ll18 5jh",
    "iso:country":"GB",
    "sg:address":"Tir Llwyd Enterprise Park, Kinmel Bay",
    "sg:city":"Rhyl",
    "sg:classifiers":[
        {
            "category":"Utilities",
            "subcategory":"Fuel Oil & Lpg",
            "type":"Services"
        }
    ],
    "sg:phone":"+44 1745 332121",
    "sg:postcode":"LL18 5JH",
    "sg:province":"Conwy",
    "sg:tags":[
        "distributor"
    ],
    "wof:name":"Cambria Oil",
    "wof:placetype":"venue"
},
  "geometry": {"coordinates":[-3.5204389095,53.3104515076],"type":"Point"}
}