{
  "type": "Feature",
  "properties": {
    "addr:full":"84 Westfield Rd West Ealing Greater London W13 9JA",
    "addr:housenumber":"84",
    "addr:postcode":"w13 9ja",
    "addr:street":"Westfield Rd",
    "iso:country":"GB",
    "sg:address":"84 Westfield Rd",
    "sg:city":"West Ealing",
    "sg:classifiers":[
        {
            "category":"Building & Trades",
            "subcategory":"Cleaning & Sanitation",
            "type":"Services"
        }
    ],
    "sg:phone":"+44 20 8579 5082",
    "sg:postcode":"W13 9JA",
    "sg:province":"Greater London",
    "sg:tags":[
        "cleaner",
        "window"
    ],
    "wof:name":"Courage Cleaning Services",
    "wof:placetype":"venue"
},
  "geometry": {"coordinates":[-0.32179901,51.5063591003],"type":"Point"}
}