{
  "type": "Feature",
  "properties": {
    "addr:full":"12 Saffron Clo Taunton Somerset TA1 3XW",
    "addr:housenumber":"12",
    "addr:postcode":"ta1 3xw",
    "iso:country":"GB",
    "sg:address":"12 Saffron Clo",
    "sg:city":"Taunton",
    "sg:classifiers":[
        {
            "category":"Building & Trades",
            "subcategory":"Construction",
            "type":"Services"
        }
    ],
    "sg:phone":"+44 1823 274877",
    "sg:postcode":"TA1 3XW",
    "sg:province":"Somerset",
    "sg:tags":[
        "ceiling",
        "contractor"
    ],
    "wof:name":"Jim Edwards",
    "wof:placetype":"venue"
},
  "geometry": {"coordinates":[-3.084954977,50.9991912842],"type":"Point"}
}