{
  "type": "Feature",
  "properties": {
    "iso:country":"GB",
    "sg:address":"15 Alver Bridge View",
    "sg:city":"Gosport",
    "sg:classifiers":[
        {
            "category":"Organizations",
            "subcategory":"Non-profit Organization",
            "type":"Services"
        }
    ],
    "sg:postcode":"PO12 2HF",
    "sg:province":"Hampshire",
    "sg:tags":[
        "charitable",
        "organisation",
        "voluntary",
        "charity"
    ],
    "wof:name":"Gosport Living History Society",
    "wof:placetype":"venue"
},
  "geometry": {"coordinates":[-1.136169,50.789604],"type":"Point"}
}