{
  "type": "Feature",
  "properties": {
    "iso:country":"GB",
    "sg:address":"Club House, Hawksworth, Guiseley",
    "sg:city":"Leeds",
    "sg:classifiers":[
        {
            "category":"Sports & Exercise",
            "subcategory":"Golf",
            "type":"Entertainment"
        }
    ],
    "sg:phone":"+44 1943 873817",
    "sg:postcode":"LS20 8NP",
    "sg:province":"West Yorkshire",
    "sg:tags":[
        "club",
        "course"
    ],
    "wof:name":"The Bradford Golf Club Ltd.",
    "wof:placetype":"venue"
},
  "geometry": {"coordinates":[-1.710494,53.871956],"type":"Point"}
}