{
  "type": "Feature",
  "properties": {
    "addr:full":"11-12 Market Place Swaffham Norfolk PE37 7AB",
    "addr:housenumber":"11-12",
    "addr:postcode":"pe37 7ab",
    "addr:street":"Market Place",
    "iso:country":"GB",
    "sg:address":"11-12 Market Place",
    "sg:city":"Swaffham",
    "sg:classifiers":[
        {
            "category":"Shopping",
            "subcategory":"Clothing, Apparel, & Fashions",
            "type":"Retail Goods"
        }
    ],
    "sg:postcode":"PE37 7AB",
    "sg:province":"Norfolk",
    "sg:tags":[
        "menswear"
    ],
    "wof:name":"Peter Bell (Menswear)",
    "wof:placetype":"venue"
},
  "geometry": {"coordinates":[0.687356,52.648521],"type":"Point"}
}