{
  "type": "Feature",
  "properties": {
    "iso:country":"GB",
    "sg:address":"Unit 5 Northside Business Park, Hawkins La",
    "sg:city":"Burton On Trent",
    "sg:classifiers":[
        {
            "category":"Professional",
            "subcategory":"Printing & Photocopies",
            "type":"Services"
        }
    ],
    "sg:phone":"+44 1283 562211",
    "sg:postcode":"DE14 1DB",
    "sg:province":"Derbyshire",
    "sg:tags":[
        "duplicating",
        "copying"
    ],
    "wof:name":"A & A Business Machines Ltd",
    "wof:placetype":"venue"
},
  "geometry": {"coordinates":[-1.626979,52.817554],"type":"Point"}
}