{
  "type": "Feature",
  "properties": {
    "addr:full":"Ferry Terminal Weymouth Dorset DT4 8DX",
    "addr:postcode":"dt4 8dx",
    "iso:country":"GB",
    "sg:address":"Ferry Terminal",
    "sg:city":"Weymouth",
    "sg:classifiers":[
        {
            "category":"Freight",
            "type":"Transportation"
        }
    ],
    "sg:phone":"+44 1305 771787",
    "sg:postcode":"DT4 8DX",
    "sg:province":"Dorset",
    "sg:tags":[
        "overseas",
        "shipping",
        "removal"
    ],
    "wof:name":"Care Lines (Weymouth) Ltd.",
    "wof:placetype":"venue"
},
  "geometry": {"coordinates":[-2.4592061043,50.6099014282],"type":"Point"}
}