{
  "type": "Feature",
  "properties": {
    "addr:full":"1 Grange Avenue, Ruddington Nottingham Nottinghamshire NG11 6BD",
    "addr:housenumber":"1",
    "addr:postcode":"ng11 6bd",
    "addr:street":"Grange Avenue",
    "iso:country":"GB",
    "sg:address":"1 Grange Avenue, Ruddington",
    "sg:city":"Nottingham",
    "sg:classifiers":[
        {
            "category":"Building & Trades",
            "subcategory":"Construction",
            "type":"Services"
        }
    ],
    "sg:phone":"+44 115 921 1828",
    "sg:postcode":"NG11 6BD",
    "sg:province":"Nottinghamshire",
    "sg:tags":[
        "dry",
        "plastering",
        "plasterers",
        "lining",
        "related",
        "screeders"
    ],
    "wof:name":"Thomas Day & Son",
    "wof:placetype":"venue"
},
  "geometry": {"coordinates":[-1.154674,52.897118],"type":"Point"}
}