{
  "type": "Feature",
  "properties": {
    "addr:full":"787 High Road London Greater London N12 8JT",
    "addr:housenumber":"787",
    "addr:postcode":"n12 8jt",
    "addr:street":"High Road",
    "iso:country":"GB",
    "sg:address":"787 High Road",
    "sg:city":"London",
    "sg:classifiers":[
        {
            "category":"Personal",
            "subcategory":"Beauty Salon",
            "type":"Services"
        }
    ],
    "sg:phone":"+44 20 8446 4011",
    "sg:postcode":"N12 8JT",
    "sg:province":"Greater London",
    "sg:tags":[
        "unisex",
        "hairdresser"
    ],
    "wof:name":"Lexingtons Ltd.",
    "wof:placetype":"venue"
},
  "geometry": {"coordinates":[-0.17655,51.615993],"type":"Point"}
}