{
  "type": "Feature",
  "properties": {
    "iso:country":"GB",
    "sg:address":"2-3 St Leger Court, Great Linford",
    "sg:city":"Milton Keynes",
    "sg:classifiers":[
        {
            "category":"Government",
            "subcategory":"Post Office",
            "type":"Public Place"
        }
    ],
    "sg:phone":"+44 1908 667088",
    "sg:postcode":"MK14 5HA",
    "sg:province":"Buckinghamshire",
    "wof:name":"St Leger Drive Post Office",
    "wof:placetype":"venue"
},
  "geometry": {"coordinates":[-0.7594839931,52.0661354065],"type":"Point"}
}