{
  "type": "Feature",
  "properties": {
    "iso:country":"GB",
    "sg:address":"12 Littondale Avenue",
    "sg:city":"Knaresborough",
    "sg:classifiers":[
        {
            "category":"Building & Trades",
            "subcategory":"Construction",
            "type":"Services"
        }
    ],
    "sg:phone":"+44 1423 866336",
    "sg:postcode":"HG5 0BQ",
    "sg:province":"North Yorkshire",
    "sg:tags":[
        "builder"
    ],
    "wof:name":"R & J C Smith",
    "wof:placetype":"venue"
},
  "geometry": {"coordinates":[-1.451067,54.009628],"type":"Point"}
}