{
  "type": "Feature",
  "properties": {
    "addr:full":"Matthew Moss Lane Rochdale Lancashire OL11 3LU",
    "addr:postcode":"ol11 3lu",
    "addr:street":"Matthew Moss Lane",
    "iso:country":"GB",
    "sg:address":"Matthew Moss Lane",
    "sg:city":"Rochdale",
    "sg:classifiers":[
        {
            "category":"Education",
            "subcategory":"School",
            "type":"Public Place"
        },
        {
            "category":"Government",
            "subcategory":"Office",
            "type":"Public Place"
        }
    ],
    "sg:phone":"+44 1706 632910",
    "sg:postcode":"OL11 3LU",
    "sg:province":"Lancashire",
    "sg:tags":[
        "local",
        "authority"
    ],
    "wof:name":"Matthew Moss High School",
    "wof:placetype":"venue"
},
  "geometry": {"coordinates":[-2.188833,53.601154],"type":"Point"}
}