{
  "type": "Feature",
  "properties": {
    "iso:country":"GB",
    "sg:address":"54 Hazelwick Road",
    "sg:city":"Crawley",
    "sg:classifiers":[
        {
            "category":"Autos & Motor Vehicles",
            "subcategory":"Fuel & Gas Station",
            "type":"Retail Goods"
        },
        {
            "category":"Utilities",
            "subcategory":"Natural Gas",
            "type":"Services"
        }
    ],
    "sg:phone":"+44 1293 526262",
    "sg:postcode":"RH10 1LZ",
    "sg:province":"Surrey",
    "sg:tags":[
        "control",
        "management",
        "cooker",
        "energy",
        "system",
        "aga"
    ],
    "wof:name":"D H M Spares",
    "wof:placetype":"venue"
},
  "geometry": {"coordinates":[-0.1653079987,51.1190605164],"type":"Point"}
}