{
  "type": "Feature",
  "properties": {
    "addr:full":"14 - 18 Tuley Street, Openshaw Manchester Greater Manchester M11 2DY",
    "addr:housenumber":"18",
    "addr:postcode":"m11 2dy",
    "addr:street":"Tuley Street",
    "iso:country":"GB",
    "sg:address":"14 - 18 Tuley Street, Openshaw",
    "sg:city":"Manchester",
    "sg:classifiers":[
        {
            "category":"Retail",
            "subcategory":"Auto Repair",
            "type":"Services"
        }
    ],
    "sg:phone":"+44 161 230 6592",
    "sg:postcode":"M11 2DY",
    "sg:province":"Greater Manchester",
    "sg:tags":[
        "body",
        "car",
        "repairer"
    ],
    "wof:name":"Corbett Robertson & Co Ltd",
    "wof:placetype":"venue"
},
  "geometry": {"coordinates":[-2.20134902,53.4738006592],"type":"Point"}
}