{
  "type": "Feature",
  "properties": {
    "addr:full":"47 Wanderdown Road Brighton East Sussex BN2 7BT",
    "addr:housenumber":"47",
    "addr:postcode":"bn2 7bt",
    "addr:street":"Wanderdown Road",
    "iso:country":"GB",
    "sg:address":"47 Wanderdown Road",
    "sg:city":"Brighton",
    "sg:classifiers":[
        {
            "category":"Shopping",
            "subcategory":"Clothing, Apparel, & Fashions",
            "type":"Retail Goods"
        },
        {
            "category":"Home & Garden",
            "subcategory":"Building Materials",
            "type":"Retail Goods"
        }
    ],
    "sg:postcode":"BN2 7BT",
    "sg:province":"East Sussex",
    "sg:tags":[
        "roofing",
        "rafter",
        "clothing",
        "fabric",
        "beams"
    ],
    "wof:name":"Manufacs Plc",
    "wof:placetype":"venue"
},
  "geometry": {"coordinates":[-0.071035,50.817936],"type":"Point"}
}