{
  "type": "Feature",
  "properties": {
    "addr:full":"St Johns Divine, Community Cent, 19 Frederick Crescent London Greater London SW9 6XN",
    "addr:postcode":"sw9 6xn",
    "addr:street":"Frederick Crescent",
    "iso:country":"GB",
    "sg:address":"St Johns Divine, Community Cent, 19 Frederick Crescent",
    "sg:city":"London",
    "sg:classifiers":[
        {
            "category":"Professional",
            "subcategory":"Lawyer & Legal Services",
            "type":"Services"
        }
    ],
    "sg:phone":"+44 20 7735 9168",
    "sg:postcode":"SW9 6XN",
    "sg:province":"Greater London",
    "sg:tags":[
        "advice",
        "counselling"
    ],
    "wof:name":"Southwark & Camberwell Wel-Care Agency for Familie",
    "wof:placetype":"venue"
},
  "geometry": {"coordinates":[-0.106121,51.477493],"type":"Point"}
}