{
  "type": "Feature",
  "properties": {
    "addr:full":"Deanery Rd Bristol City of Bristol BS1 5XN",
    "addr:postcode":"bs1 5xn",
    "addr:street":"Deanery Rd",
    "iso:country":"GB",
    "sg:address":"Deanery Rd",
    "sg:city":"Bristol",
    "sg:classifiers":[
        {
            "category":"Organizations",
            "subcategory":"Non-profit Organization",
            "type":"Services"
        }
    ],
    "sg:phone":"+44 117 925 5252",
    "sg:postcode":"BS1 5XN",
    "sg:province":"City of Bristol",
    "sg:tags":[
        "organisation",
        "voluntary",
        "charity"
    ],
    "wof:name":"C P A-Centre For Performing Arts",
    "wof:placetype":"venue"
},
  "geometry": {"coordinates":[-2.6006989479,51.4537696838],"type":"Point"}
}