{
  "type": "Feature",
  "properties": {
    "iso:country":"GB",
    "sg:address":"127 Church Lane West",
    "sg:city":"Aldershot",
    "sg:classifiers":[
        {
            "category":"Real Estate",
            "subcategory":"Real Estate Operator",
            "type":"Services"
        }
    ],
    "sg:phone":"+44 1252 324747",
    "sg:postcode":"GU11 3LH",
    "sg:province":"Hampshire",
    "sg:tags":[
        "letting",
        "agent"
    ],
    "wof:name":"Sanco Properties",
    "wof:placetype":"venue"
},
  "geometry": {"coordinates":[-0.7532520294,51.2405052185],"type":"Point"}
}