{
  "type": "Feature",
  "properties": {
    "addr:full":"163 Northgate Darlington Durham DL1 1TZ",
    "addr:housenumber":"163",
    "addr:postcode":"dl1 1tz",
    "addr:street":"Northgate",
    "iso:country":"GB",
    "sg:address":"163 Northgate",
    "sg:city":"Darlington",
    "sg:classifiers":[
        {
            "category":"Autos & Motor Vehicles",
            "subcategory":"Auto Supplies",
            "type":"Retail Goods"
        }
    ],
    "sg:phone":"+44 1325 382202",
    "sg:postcode":"DL1 1TZ",
    "sg:province":"Durham",
    "sg:tags":[
        "windscreen"
    ],
    "wof:name":"1st A 1 Windscreens U K Ltd.",
    "wof:placetype":"venue"
},
  "geometry": {"coordinates":[-1.5530200005,54.5299415588],"type":"Point"}
}