{
  "type": "Feature",
  "properties": {
    "iso:country":"GB",
    "sg:address":"58 Glasgow Road, St Ninians",
    "sg:city":"Stirling",
    "sg:classifiers":[
        {
            "category":"Restaurant",
            "type":"Food & Drink"
        }
    ],
    "sg:phone":"+44 1786 812311",
    "sg:postcode":"FK7 0PH",
    "sg:province":"Falkirk",
    "sg:tags":[
        "-",
        "italian"
    ],
    "wof:name":"Map showing The Hollybank Restaurant",
    "wof:placetype":"venue"
},
  "geometry": {"coordinates":[-3.936028,56.097183],"type":"Point"}
}