{
  "type": "Feature",
  "properties": {
    "addr:full":"10 Westerdale Chelmsford Essex CM1 6UN",
    "addr:housenumber":"10",
    "addr:postcode":"cm1 6un",
    "addr:street":"Westerdale",
    "iso:country":"GB",
    "sg:address":"10 Westerdale",
    "sg:city":"Chelmsford",
    "sg:classifiers":[
        {
            "category":"Professional",
            "subcategory":"Art Services",
            "type":"Services"
        },
        {
            "category":"Building & Trades",
            "subcategory":"Construction",
            "type":"Services"
        }
    ],
    "sg:phone":"+44 1245 466626",
    "sg:postcode":"CM1 6UN",
    "sg:province":"Essex",
    "sg:tags":[
        "decorator",
        "painter"
    ],
    "wof:name":"S & H Painting & Decorating",
    "wof:placetype":"venue"
},
  "geometry": {"coordinates":[0.488706,51.75539],"type":"Point"}
}