{
  "type": "Feature",
  "properties": {
    "addr:full":"The Slips, Great Harrowden Wellingborough Northamptonshire NN9 5AE",
    "addr:postcode":"nn9 5ae",
    "iso:country":"GB",
    "sg:address":"The Slips, Great Harrowden",
    "sg:city":"Wellingborough",
    "sg:classifiers":[
        {
            "category":"Retail",
            "subcategory":"Car Wash",
            "type":"Services"
        }
    ],
    "sg:postcode":"NN9 5AE",
    "sg:province":"Northamptonshire",
    "sg:tags":[
        "polishing",
        "washing"
    ],
    "wof:name":"Car Wash Services",
    "wof:placetype":"venue"
},
  "geometry": {"coordinates":[-0.7101539969,52.3289756775],"type":"Point"}
}