{
  "type": "Feature",
  "properties": {
    "iso:country":"GB",
    "sg:address":"The Borough",
    "sg:city":"Farnham",
    "sg:classifiers":[
        {
            "category":"Travel",
            "subcategory":"Hotels & Motels",
            "type":"Entertainment"
        }
    ],
    "sg:phone":"+44 1252 715237",
    "sg:postcode":"GU9 7NN",
    "sg:province":"Surrey",
    "wof:name":"The Bush Hotel",
    "wof:placetype":"venue"
},
  "geometry": {"coordinates":[-0.799909,51.214596],"type":"Point"}
}