{
  "type": "Feature",
  "properties": {
    "addr:full":"11 Warren Clo Liversedge West Yorkshire WF15 7HQ",
    "addr:housenumber":"11",
    "addr:postcode":"wf15 7hq",
    "addr:street":"Warren Clo Liversedge West",
    "iso:country":"GB",
    "sg:address":"11 Warren Clo",
    "sg:city":"Liversedge",
    "sg:classifiers":[
        {
            "category":"Building & Trades",
            "subcategory":"Cleaning & Sanitation",
            "type":"Services"
        }
    ],
    "sg:phone":"+44 1924 412686",
    "sg:postcode":"WF15 7HQ",
    "sg:province":"West Yorkshire",
    "sg:tags":[
        "commercial"
    ],
    "wof:name":"Spotless Contract Cleaners & Supplies",
    "wof:placetype":"venue"
},
  "geometry": {"coordinates":[-1.6865600348,53.7022514343],"type":"Point"}
}