{
  "type": "Feature",
  "properties": {
    "addr:full":"53 Calton Avenue London Greater London SE21 7DF",
    "addr:housenumber":"53",
    "addr:postcode":"se21 7df",
    "addr:street":"Calton Avenue",
    "iso:country":"GB",
    "sg:address":"53 Calton Avenue",
    "sg:city":"London",
    "sg:classifiers":[
        {
            "category":"Health Services",
            "subcategory":"Health Practitioner",
            "type":"Services"
        }
    ],
    "sg:phone":"+44 20 8693 3204",
    "sg:postcode":"SE21 7DF",
    "sg:province":"Greater London",
    "sg:tags":[
        "physiotherapist"
    ],
    "wof:name":"C Z Clark",
    "wof:placetype":"venue"
},
  "geometry": {"coordinates":[-0.083248,51.453346],"type":"Point"}
}