{
  "type": "Feature",
  "properties": {
    "iso:country":"GB",
    "sg:address":"Fairview Farm, Wield Road, Preston Candover",
    "sg:city":"Basingstoke",
    "sg:classifiers":[
        {
            "category":"Farming",
            "subcategory":"Poultry Farm",
            "type":"Manufacturing & Wholesale Goods"
        }
    ],
    "sg:phone":"+44 1256 389396",
    "sg:postcode":"RG25 2ES",
    "sg:province":"Hampshire",
    "sg:tags":[
        "game"
    ],
    "wof:name":"Poultry First Ltd.",
    "wof:placetype":"venue"
},
  "geometry": {"coordinates":[-1.133249,51.171516],"type":"Point"}
}