{
  "type": "Feature",
  "properties": {
    "addr:full":"Beswick Avenue, Ensbury Park Bournemouth Dorset BH10 4EX",
    "addr:postcode":"bh10 4ex",
    "addr:street":"Beswick Avenue Ensbury Park",
    "iso:country":"GB",
    "sg:address":"Beswick Avenue, Ensbury Park",
    "sg:city":"Bournemouth",
    "sg:classifiers":[
        {
            "category":"Education",
            "subcategory":"School",
            "type":"Public Place"
        },
        {
            "category":"Government",
            "subcategory":"Office",
            "type":"Public Place"
        }
    ],
    "sg:phone":"+44 1202 527818",
    "sg:postcode":"BH10 4EX",
    "sg:province":"Dorset",
    "sg:tags":[
        "local",
        "authority"
    ],
    "wof:name":"Glenmoor School for Girls",
    "wof:placetype":"venue"
},
  "geometry": {"coordinates":[-1.8880790472,50.7515296936],"type":"Point"}
}