{
  "type": "Feature",
  "properties": {
    "addr:full":"18-19 Avenue Road Southall Greater London UB1 3BL",
    "addr:housenumber":"18-19",
    "addr:postcode":"ub1 3bl",
    "addr:street":"Avenue Road",
    "iso:country":"GB",
    "sg:address":"18-19 Avenue Road",
    "sg:city":"Southall",
    "sg:classifiers":[
        {
            "category":"Health Services",
            "subcategory":"Nursing And Care Facility",
            "type":"Services"
        }
    ],
    "sg:postcode":"UB1 3BL",
    "sg:province":"Greater London",
    "sg:tags":[
        "home"
    ],
    "wof:name":"THE AVENUE ROAD NURSING HOME",
    "wof:placetype":"venue"
},
  "geometry": {"coordinates":[-0.375513,51.509018],"type":"Point"}
}