{
  "type": "Feature",
  "properties": {
    "addr:full":"Unit 2 108 Cecil Rd Swansea Carmarthenshire SA4 4BY",
    "addr:housenumber":"unit 2 108",
    "addr:postcode":"sa4 4by",
    "addr:street":"Cecil Rd",
    "iso:country":"GB",
    "sg:address":"Unit 2 108 Cecil Rd",
    "sg:city":"Swansea",
    "sg:classifiers":[
        {
            "category":"Retail",
            "subcategory":"Auto Repair",
            "type":"Services"
        }
    ],
    "sg:phone":"+44 1792 899978",
    "sg:postcode":"SA4 4BY",
    "sg:province":"Carmarthenshire",
    "sg:tags":[
        "body",
        "car"
    ],
    "wof:name":"J.M.P Body Repairs",
    "wof:placetype":"venue"
},
  "geometry": {"coordinates":[-4.039209,51.672241],"type":"Point"}
}