{
  "type": "Feature",
  "properties": {
    "iso:country":"GB",
    "sg:address":"78 Camden Road",
    "sg:city":"Tunbridge Wells",
    "sg:classifiers":[
        {
            "category":"Autos & Motor Vehicles",
            "subcategory":"Auto Supplies",
            "type":"Retail Goods"
        }
    ],
    "sg:phone":"+44 1892 537161",
    "sg:postcode":"TN1 2QP",
    "sg:province":"Kent",
    "sg:tags":[
        "car",
        "audio"
    ],
    "wof:name":"Road Radio",
    "wof:placetype":"venue"
},
  "geometry": {"coordinates":[0.268959,51.135841],"type":"Point"}
}