{
  "type": "Feature",
  "properties": {
    "addr:full":"Coal Exchange Building, Man Stewart Square Cardiff Cardiff CF10 5ED",
    "addr:postcode":"cf10 5ed",
    "addr:street":"Stewart Square",
    "iso:country":"GB",
    "sg:address":"Coal Exchange Building, Man Stewart Square",
    "sg:city":"Cardiff",
    "sg:classifiers":[
        {
            "category":"Utilities",
            "type":"Services"
        }
    ],
    "sg:phone":"+44 29 2047 1771",
    "sg:postcode":"CF10 5ED",
    "sg:province":"Cardiff",
    "sg:tags":[
        "internet"
    ],
    "wof:name":"Homes on Line Ltd.",
    "wof:placetype":"venue"
},
  "geometry": {"coordinates":[-3.1806690693,51.4812583923],"type":"Point"}
}