{
  "type": "Feature",
  "properties": {
    "addr:full":"21 Allison Street Glasgow Glasgow City G42 8NP",
    "addr:housenumber":"21",
    "addr:postcode":"g42 8np",
    "addr:street":"Allison Street",
    "iso:country":"GB",
    "sg:address":"21 Allison Street",
    "sg:city":"Glasgow",
    "sg:classifiers":[
        {
            "category":"Home & Garden",
            "subcategory":"Household Appliances",
            "type":"Retail Goods"
        },
        {
            "category":"Retail",
            "subcategory":"Event Space",
            "type":"Services"
        }
    ],
    "sg:phone":"+44 141 423 7913",
    "sg:postcode":"G42 8NP",
    "sg:province":"Glasgow City",
    "sg:tags":[
        "electrical",
        "product",
        "domestic",
        "sales"
    ],
    "wof:name":"Harry's Electrical",
    "wof:placetype":"venue"
},
  "geometry": {"coordinates":[-4.2675600052,55.8371658325],"type":"Point"}
}