{
  "type": "Feature",
  "properties": {
    "iso:country":"GB",
    "sg:address":"31 Bridge Street",
    "sg:city":"Pershore",
    "sg:classifiers":[
        {
            "category":"Building & Trades",
            "subcategory":"Construction",
            "type":"Services"
        }
    ],
    "sg:phone":"+44 1386 553561",
    "sg:postcode":"WR10 1AJ",
    "sg:province":"Worcestershire",
    "sg:tags":[
        "builder"
    ],
    "wof:name":"H J Hall (Builders)",
    "wof:placetype":"venue"
},
  "geometry": {"coordinates":[-2.072702,52.10704],"type":"Point"}
}