{
  "type": "Feature",
  "properties": {
    "addr:full":"103 Wantz Road Maldon Essex CM9 7DD",
    "addr:housenumber":"103",
    "addr:postcode":"cm9 7dd",
    "addr:street":"Wantz Road",
    "iso:country":"GB",
    "sg:address":"103 Wantz Road",
    "sg:city":"Maldon",
    "sg:classifiers":[
        {
            "category":"Shopping",
            "subcategory":"Computers & Home Electronics",
            "type":"Retail Goods"
        }
    ],
    "sg:phone":"+44 1621 856187",
    "sg:postcode":"CM9 7DD",
    "sg:province":"Essex",
    "wof:name":"Alan Parkinson",
    "wof:placetype":"venue"
},
  "geometry": {"coordinates":[0.682548,51.726398],"type":"Point"}
}