{
  "type": "Feature",
  "properties": {
    "iso:country":"GB",
    "sg:address":"6 Lainey's Close",
    "sg:city":"Marlborough",
    "sg:classifiers":[
        {
            "category":"Building & Trades",
            "subcategory":"Construction",
            "type":"Services"
        }
    ],
    "sg:postcode":"SN8 1BP",
    "sg:province":"Berkshire",
    "sg:tags":[
        "builder"
    ],
    "wof:name":"A J S Builders",
    "wof:placetype":"venue"
},
  "geometry": {"coordinates":[-1.72721,51.424789],"type":"Point"}
}