{
  "type": "Feature",
  "properties": {
    "addr:full":"7 Crawford Place Whitley Bay Northumberland NE25 8TD",
    "addr:housenumber":"7",
    "addr:postcode":"ne25 8td",
    "addr:street":"Crawford Place",
    "iso:country":"GB",
    "sg:address":"7 Crawford Place",
    "sg:city":"Whitley Bay",
    "sg:classifiers":[
        {
            "category":"Bus Charters",
            "type":"Transportation"
        }
    ],
    "sg:postcode":"NE25 8TD",
    "sg:province":"Northumberland",
    "sg:tags":[
        "hire",
        "coach"
    ],
    "wof:name":"Showtrax Ltd.",
    "wof:placetype":"venue"
},
  "geometry": {"coordinates":[-1.4680759907,55.0382575989],"type":"Point"}
}