{
  "type": "Feature",
  "properties": {
    "iso:country":"GB",
    "sg:address":"79 Balham Park Rd",
    "sg:city":"Balham",
    "sg:classifiers":[
        {
            "category":"Travel",
            "subcategory":"Hotels & Motels",
            "type":"Entertainment"
        }
    ],
    "sg:phone":"+44 20 8767 7926",
    "sg:postcode":"SW12 8EB",
    "sg:province":"Greater London",
    "sg:tags":[
        "self",
        "catering"
    ],
    "wof:name":"Owners Syndicate The",
    "wof:placetype":"venue"
},
  "geometry": {"coordinates":[-0.162244007,51.4438362122],"type":"Point"}
}