{
  "type": "Feature",
  "properties": {
    "iso:country":"GB",
    "sg:address":"61b Lord Avenue",
    "sg:city":"Stockton-on-tees",
    "sg:classifiers":[
        {
            "category":"Professional",
            "subcategory":"Engineering",
            "type":"Services"
        }
    ],
    "sg:phone":"+44 1642 767477",
    "sg:postcode":"TS17 9JX",
    "sg:province":"Durham",
    "sg:tags":[
        "civil",
        "engineer"
    ],
    "wof:name":"Anwen Construction",
    "wof:placetype":"venue"
},
  "geometry": {"coordinates":[-1.292829,54.524761],"type":"Point"}
}