{
  "type": "Feature",
  "properties": {
    "addr:full":"Crown Industrial Estate, 71-73 Nathan Way, Woolwich London Greater London SE28 0BQ",
    "addr:housenumber":"71-73",
    "addr:postcode":"se28 0bq",
    "addr:street":"Nathan Way",
    "iso:country":"GB",
    "sg:address":"Crown Industrial Estate, 71-73 Nathan Way, Woolwich",
    "sg:city":"London",
    "sg:classifiers":[
        {
            "category":"Utilities",
            "subcategory":"Refuse",
            "type":"Services"
        }
    ],
    "sg:phone":"+44 20 8855 2525",
    "sg:postcode":"SE28 0BQ",
    "sg:province":"Greater London",
    "sg:tags":[
        "disposal",
        "waste",
        "retail"
    ],
    "wof:name":"Adams Waste Disposal",
    "wof:placetype":"venue"
},
  "geometry": {"coordinates":[0.0929099992,51.4925613403],"type":"Point"}
}