{
  "type": "Feature",
  "properties": {
    "iso:country":"GB",
    "sg:address":"Runnaford Cottage, Coombe",
    "sg:city":"Buckfastleigh",
    "sg:classifiers":[
        {
            "category":"Manufacturing",
            "subcategory":"Building Materials",
            "type":"Manufacturing & Wholesale Goods"
        }
    ],
    "sg:postcode":"TQ11 0HT",
    "sg:province":"Devon",
    "sg:tags":[
        "stonemason"
    ],
    "wof:name":"Roy Netley",
    "wof:placetype":"venue"
},
  "geometry": {"coordinates":[-3.779209,50.481369],"type":"Point"}
}