{
  "type": "Feature",
  "properties": {
    "addr:full":"7 Park Drive Maldon Essex CM9 5JG",
    "addr:housenumber":"7",
    "addr:postcode":"cm9 5jg",
    "addr:street":"Park Drive",
    "iso:country":"GB",
    "sg:address":"7 Park Drive",
    "sg:city":"Maldon",
    "sg:classifiers":[
        {
            "category":"Building & Trades",
            "subcategory":"Plumbing",
            "type":"Services"
        }
    ],
    "sg:phone":"+44 1621 855278",
    "sg:postcode":"CM9 5JG",
    "sg:province":"Essex",
    "sg:tags":[
        "drain",
        "clearance",
        "sewer"
    ],
    "wof:name":"T M Everitt",
    "wof:placetype":"venue"
},
  "geometry": {"coordinates":[0.687424,51.725761],"type":"Point"}
}