{
  "type": "Feature",
  "properties": {
    "addr:full":"Cornyx La Solihull West Midlands B91 2SQ",
    "addr:postcode":"b91 2sq",
    "addr:street":"Cornyx La Solihull",
    "iso:country":"GB",
    "sg:address":"Cornyx La",
    "sg:city":"Solihull",
    "sg:classifiers":[
        {
            "category":"Place Of Worship",
            "type":"Public Place"
        }
    ],
    "sg:phone":"+44 121 705 3234",
    "sg:postcode":"B91 2SQ",
    "sg:province":"West Midlands",
    "wof:name":"St Francis Of Assisi C Of E Church",
    "wof:placetype":"venue"
},
  "geometry": {"coordinates":[-1.7723840475,52.4239234924],"type":"Point"}
}