{
  "type": "Feature",
  "properties": {
    "addr:full":"Unit 6a, Milestone House Business Park, Milestone Penrith Cumbria CA11 9NQ",
    "addr:housenumber":"unit 6a milestone house",
    "addr:postcode":"ca11 9nq",
    "addr:street":"Business Park Milestone",
    "iso:country":"GB",
    "sg:address":"Unit 6a, Milestone House Business Park, Milestone",
    "sg:city":"Penrith",
    "sg:classifiers":[
        {
            "category":"Manufacturing",
            "subcategory":"Rubber & Plastics",
            "type":"Manufacturing & Wholesale Goods"
        }
    ],
    "sg:phone":"+44 1768 895858",
    "sg:postcode":"CA11 9NQ",
    "sg:province":"Cumbria",
    "sg:tags":[
        "forming",
        "vacuum"
    ],
    "wof:name":"Steve Lythgoe Resin Casting",
    "wof:placetype":"venue"
},
  "geometry": {"coordinates":[-2.7574689388,54.6643028259],"type":"Point"}
}