{
  "type": "Feature",
  "properties": {
    "iso:country":"GB",
    "sg:address":"126-128 High Street",
    "sg:city":"Delabole",
    "sg:classifiers":[
        {
            "category":"Insurance",
            "subcategory":"Insurance Agent",
            "type":"Services"
        }
    ],
    "sg:phone":"+44 1840 213836",
    "sg:postcode":"PL33 9AJ",
    "sg:province":"Cornwall",
    "wof:name":"Cornish Insurance Consultants",
    "wof:placetype":"venue"
},
  "geometry": {"coordinates":[-4.733053,50.62254],"type":"Point"}
}