{
  "type": "Feature",
  "properties": {
    "addr:full":"104 Durham Street Rochdale Lancashire OL11 1LS",
    "addr:housenumber":"104",
    "addr:postcode":"ol11 1ls",
    "addr:street":"Durham Street",
    "iso:country":"GB",
    "sg:address":"104 Durham Street",
    "sg:city":"Rochdale",
    "sg:classifiers":[
        {
            "category":"Shopping",
            "subcategory":"Clothing, Apparel, & Fashions",
            "type":"Retail Goods"
        }
    ],
    "sg:phone":"+44 1706 352144",
    "sg:postcode":"OL11 1LS",
    "sg:province":"Lancashire",
    "sg:tags":[
        "clothing",
        "fabric"
    ],
    "wof:name":"A R F Trading Co",
    "wof:placetype":"venue"
},
  "geometry": {"coordinates":[-2.1502139568,53.6084632874],"type":"Point"}
}