{
  "type": "Feature",
  "properties": {
    "iso:country":"GB",
    "sg:address":"Midland Road",
    "sg:city":"Rotherham",
    "sg:classifiers":[
        {
            "category":"Building & Trades",
            "subcategory":"Construction",
            "type":"Services"
        }
    ],
    "sg:phone":"+44 1709 559547",
    "sg:postcode":"S61 1SZ",
    "sg:province":"South Yorkshire",
    "sg:tags":[
        "joinery"
    ],
    "wof:name":"Mustang Joinery Ltd.",
    "wof:placetype":"venue"
},
  "geometry": {"coordinates":[-1.3719890118,53.4315643311],"type":"Point"}
}