{
  "type": "Feature",
  "properties": {
    "addr:full":"84 High Street, Wargrave Reading Berkshire RG10 8DE",
    "addr:housenumber":"84",
    "addr:postcode":"rg10 8de",
    "addr:street":"High Street",
    "iso:country":"GB",
    "sg:address":"84 High Street, Wargrave",
    "sg:city":"Reading",
    "sg:classifiers":[
        {
            "category":"Professional",
            "subcategory":"Management & Consulting",
            "type":"Services"
        }
    ],
    "sg:postcode":"RG10 8DE",
    "sg:province":"Berkshire",
    "sg:tags":[
        "marketing",
        "consultant"
    ],
    "wof:name":"Matisse Associates",
    "wof:placetype":"venue"
},
  "geometry": {"coordinates":[-0.870405,51.500282],"type":"Point"}
}