{
  "type": "Feature",
  "properties": {
    "addr:full":"8 Grosvenor Way, Mount Pleasant Hill London Greater London E5 9ND",
    "addr:housenumber":"8",
    "addr:postcode":"e5 9nd",
    "addr:street":"Grosvenor Way",
    "iso:country":"GB",
    "sg:address":"8 Grosvenor Way, Mount Pleasant Hill",
    "sg:city":"London",
    "sg:classifiers":[
        {
            "category":"Manufacturing",
            "subcategory":"Apparel",
            "type":"Manufacturing & Wholesale Goods"
        }
    ],
    "sg:postcode":"E5 9ND",
    "sg:province":"Greater London",
    "sg:tags":[
        "shirt",
        "maker"
    ],
    "wof:name":"Euroman Ltd",
    "wof:placetype":"venue"
},
  "geometry": {"coordinates":[-0.0535399988,51.5639610291],"type":"Point"}
}