{
  "type": "Feature",
  "properties": {
    "addr:full":"49-51 Leeds Rd Harrogate North Yorkshire HG2 8AY",
    "addr:housenumber":"49-51",
    "addr:postcode":"hg2 8ay",
    "addr:street":"Leeds Rd",
    "iso:country":"GB",
    "sg:address":"49-51 Leeds Rd",
    "sg:city":"Harrogate",
    "sg:classifiers":[
        {
            "category":"Health Services",
            "subcategory":"Doctor",
            "type":"Services"
        }
    ],
    "sg:phone":"+44 1423 566636",
    "sg:postcode":"HG2 8AY",
    "sg:province":"North Yorkshire",
    "sg:tags":[
        "practitioners"
    ],
    "wof:name":"Chave-Cox, R",
    "wof:placetype":"venue"
},
  "geometry": {"coordinates":[-1.5349760056,53.9799308777],"type":"Point"}
}