{
  "type": "Feature",
  "properties": {
    "iso:country":"GB",
    "sg:address":"Coxwell Rd",
    "sg:city":"Faringdon",
    "sg:classifiers":[
        {
            "category":"Health Services",
            "subcategory":"Clinic",
            "type":"Services"
        }
    ],
    "sg:phone":"+44 1367 242407",
    "sg:postcode":"SN7 7EZ",
    "sg:province":"Oxfordshire",
    "sg:tags":[
        "nh"
    ],
    "wof:name":"Fenhill Medical Practice The",
    "wof:placetype":"venue"
},
  "geometry": {"coordinates":[-1.591639,51.651402],"type":"Point"}
}