{
  "type": "Feature",
  "properties": {
    "addr:full":"South Hill, Langdon Hills Basildon Essex SS16 6JD",
    "addr:postcode":"ss16 6jd",
    "addr:street":"Hill",
    "iso:country":"GB",
    "sg:address":"South Hill, Langdon Hills",
    "sg:city":"Basildon",
    "sg:classifiers":[
        {
            "category":"Retail",
            "subcategory":"Auto Repair",
            "type":"Services"
        }
    ],
    "sg:phone":"+44 1268 542234",
    "sg:postcode":"SS16 6JD",
    "sg:province":"Essex",
    "sg:tags":[
        "modification",
        "garage"
    ],
    "wof:name":"Renault & Volvo Specialists",
    "wof:placetype":"venue"
},
  "geometry": {"coordinates":[0.4205209911,51.5678939819],"type":"Point"}
}