{
  "type": "Feature",
  "properties": {
    "addr:full":"115 Sydney Street Burton-on-trent Derbyshire DE14 2QY",
    "addr:housenumber":"115",
    "addr:postcode":"de14 2qy",
    "addr:street":"Sydney Street",
    "iso:country":"GB",
    "sg:address":"115 Sydney Street",
    "sg:city":"Burton-on-trent",
    "sg:classifiers":[
        {
            "category":"Government",
            "subcategory":"Post Office",
            "type":"Public Place"
        }
    ],
    "sg:phone":"+44 1283 565163",
    "sg:postcode":"DE14 2QY",
    "sg:province":"Derbyshire",
    "wof:name":"Sydney Street Post Office",
    "wof:placetype":"venue"
},
  "geometry": {"coordinates":[-1.630908,52.817764],"type":"Point"}
}