{
  "type": "Feature",
  "properties": {
    "iso:country":"GB",
    "sg:address":"18 Yardley Business Park",
    "sg:city":"Basildon",
    "sg:classifiers":[
        {
            "category":"Freight",
            "type":"Transportation"
        }
    ],
    "sg:phone":"+44 1268 531222",
    "sg:postcode":"SS14 3GL",
    "sg:province":"Essex",
    "sg:tags":[
        "haulage",
        "road"
    ],
    "wof:name":"P H Transport",
    "wof:placetype":"venue"
},
  "geometry": {"coordinates":[0.464788,51.586178],"type":"Point"}
}