{
  "type": "Feature",
  "properties": {
    "iso:country":"GB",
    "sg:address":"17 Kilnhouse Lane",
    "sg:city":"Lytham St. Annes",
    "sg:classifiers":[
        {
            "category":"Professional",
            "subcategory":"Engineering",
            "type":"Services"
        }
    ],
    "sg:phone":"+44 1253 721616",
    "sg:postcode":"FY8 3AB",
    "sg:province":"Lancashire",
    "sg:tags":[
        "contractor",
        "electrical",
        "engineer"
    ],
    "wof:name":"Barnes Bros",
    "wof:placetype":"venue"
},
  "geometry": {"coordinates":[-3.023196,53.763069],"type":"Point"}
}