{
  "type": "Feature",
  "properties": {
    "addr:full":"69 St George's Road, Cullercoats North Shields Tyne and Wear NE30 3LB",
    "addr:housenumber":"69",
    "addr:postcode":"ne30 3lb",
    "addr:street":"St George'S Road",
    "iso:country":"GB",
    "sg:address":"69 St George's Road, Cullercoats",
    "sg:city":"North Shields",
    "sg:classifiers":[
        {
            "category":"Retail",
            "subcategory":"Repair Shop",
            "type":"Services"
        }
    ],
    "sg:phone":"+44 191 252 9924",
    "sg:postcode":"NE30 3LB",
    "sg:province":"Tyne and Wear",
    "sg:tags":[
        "upholsterer"
    ],
    "wof:name":"B & M Upholstery",
    "wof:placetype":"venue"
},
  "geometry": {"coordinates":[-1.438706,55.036793],"type":"Point"}
}