{
  "type": "Feature",
  "properties": {
    "addr:full":"78 Limpsfield Road Warlingham Kent CR6 9RA",
    "addr:housenumber":"78",
    "addr:postcode":"cr6 9ra",
    "addr:street":"Limpsfield Road",
    "iso:country":"GB",
    "sg:address":"78 Limpsfield Road",
    "sg:city":"Warlingham",
    "sg:classifiers":[
        {
            "category":"Shopping",
            "subcategory":"News",
            "type":"Retail Goods"
        }
    ],
    "sg:postcode":"CR6 9RA",
    "sg:province":"Kent",
    "sg:tags":[
        "newsagent"
    ],
    "wof:name":"Sweetwear",
    "wof:placetype":"venue"
},
  "geometry": {"coordinates":[-0.063785,51.318275],"type":"Point"}
}