{
  "type": "Feature",
  "properties": {
    "addr:full":"5 Beacon Drive Seaford East Sussex BN25 2JX",
    "addr:housenumber":"5",
    "addr:postcode":"bn25 2jx",
    "addr:street":"Beacon Drive",
    "iso:country":"GB",
    "sg:address":"5 Beacon Drive",
    "sg:city":"Seaford",
    "sg:classifiers":[
        {
            "category":"Professional",
            "subcategory":"Business Services",
            "type":"Services"
        }
    ],
    "sg:phone":"+44 1323 899802",
    "sg:postcode":"BN25 2JX",
    "sg:province":"East Sussex",
    "sg:tags":[
        "trade"
    ],
    "wof:name":"Traditional Farmfresh Turkey Association",
    "wof:placetype":"venue"
},
  "geometry": {"coordinates":[0.097185,50.781464],"type":"Point"}
}