{
  "type": "Feature",
  "properties": {
    "addr:full":"Cromwell House, Crusader Road Lincoln Lincolnshire LN6 7YT",
    "addr:postcode":"ln6 7yt",
    "addr:street":"Crusader Road",
    "iso:country":"GB",
    "sg:address":"Cromwell House, Crusader Road",
    "sg:city":"Lincoln",
    "sg:classifiers":[
        {
            "category":"Government",
            "subcategory":"Office",
            "type":"Public Place"
        }
    ],
    "sg:phone":"+44 1522 884222",
    "sg:postcode":"LN6 7YT",
    "sg:province":"Lincolnshire",
    "sg:tags":[
        "inland",
        "revenue"
    ],
    "wof:name":"Inland Revenue",
    "wof:placetype":"venue"
},
  "geometry": {"coordinates":[-0.5590239763,53.2198143005],"type":"Point"}
}