{
  "type": "Feature",
  "properties": {
    "iso:country":"GB",
    "sg:address":"16 Back Lane",
    "sg:city":"Sedbergh",
    "sg:classifiers":[
        {
            "category":"Shopping",
            "subcategory":"Antiques",
            "type":"Retail Goods"
        },
        {
            "category":"Shopping",
            "subcategory":"Used Merchandise",
            "type":"Retail Goods"
        }
    ],
    "sg:phone":"+44 15396 20251",
    "sg:postcode":"LA10 5AQ",
    "sg:province":"Cumbria",
    "sg:tags":[
        "shop",
        "second-hand"
    ],
    "wof:name":"Stable Antiques",
    "wof:placetype":"venue"
},
  "geometry": {"coordinates":[-2.526446104,54.3232917786],"type":"Point"}
}