{
  "type": "Feature",
  "properties": {
    "addr:full":"Windmill Farm, York St York North Yorkshire YO1 5PN",
    "addr:postcode":"yo1 5pn",
    "addr:street":"York St York",
    "iso:country":"GB",
    "sg:address":"Windmill Farm, York St",
    "sg:city":"York",
    "sg:classifiers":[
        {
            "category":"Farming",
            "subcategory":"Farm",
            "type":"Manufacturing & Wholesale Goods"
        }
    ],
    "sg:phone":"+44 1904 489759",
    "sg:postcode":"YO1 5PN",
    "sg:province":"North Yorkshire",
    "sg:tags":[
        "mixed",
        "crop"
    ],
    "wof:name":"J Kay",
    "wof:placetype":"venue"
},
  "geometry": {"coordinates":[-1.08135,53.958771],"type":"Point"}
}