{
  "type": "Feature",
  "properties": {
    "iso:country":"GB",
    "sg:address":"50 Wimpole Street",
    "sg:city":"London",
    "sg:classifiers":[
        {
            "category":"Real Estate",
            "subcategory":"Real Estate Agent",
            "type":"Services"
        }
    ],
    "sg:phone":"+44 20 7573 8888",
    "sg:postcode":"W1G 8SQ",
    "sg:province":"Greater London",
    "wof:name":"The Heart Hospital Properties Ltd.",
    "wof:placetype":"venue"
},
  "geometry": {"coordinates":[-0.149143,51.519699],"type":"Point"}
}