{
  "type": "Feature",
  "properties": {
    "iso:country":"GB",
    "sg:address":"Woodsgate Place, Gunters Lane",
    "sg:city":"Bexhill-on-sea",
    "sg:classifiers":[
        {
            "category":"Education",
            "subcategory":"School",
            "type":"Public Place"
        }
    ],
    "sg:phone":"+44 1424 216670",
    "sg:postcode":"TN39 4EB",
    "sg:province":"East Sussex",
    "sg:tags":[
        "independent",
        "preparatory"
    ],
    "wof:name":"Charters Ancaster College",
    "wof:placetype":"venue"
},
  "geometry": {"coordinates":[0.465745,50.850315],"type":"Point"}
}