{
  "type": "Feature",
  "properties": {
    "addr:full":"8 Beech Lane, Kislingbury Northampton Buckinghamshire NN7 4AL",
    "addr:housenumber":"8",
    "addr:postcode":"nn7 4al",
    "addr:street":"Beech Lane",
    "iso:country":"GB",
    "sg:address":"8 Beech Lane, Kislingbury",
    "sg:city":"Northampton",
    "sg:classifiers":[
        {
            "category":"Professional",
            "subcategory":"Art Services",
            "type":"Services"
        }
    ],
    "sg:phone":"+44 1604 832555",
    "sg:postcode":"NN7 4AL",
    "sg:province":"Buckinghamshire",
    "sg:tags":[
        "photographer"
    ],
    "wof:name":"Beedle & Cooper Photograpy",
    "wof:placetype":"venue"
},
  "geometry": {"coordinates":[-0.976271987,52.2316246033],"type":"Point"}
}