{
  "type": "Feature",
  "properties": {
    "iso:country":"GB",
    "sg:address":"12-18 Town Road",
    "sg:city":"Stoke-on-trent",
    "sg:classifiers":[
        {
            "category":"Shopping",
            "subcategory":"Discount & Variety Stores",
            "type":"Retail Goods"
        }
    ],
    "sg:phone":"+44 1782 281785",
    "sg:postcode":"ST1 2JQ",
    "sg:province":"Staffordshire",
    "sg:tags":[
        "centre"
    ],
    "wof:name":"Poundstretcher Ltd.",
    "wof:placetype":"venue"
},
  "geometry": {"coordinates":[-2.174476,53.027313],"type":"Point"}
}