{
  "type": "Feature",
  "properties": {
    "iso:country":"GB",
    "sg:address":"4 Redwing Rise",
    "sg:city":"Guildford",
    "sg:classifiers":[
        {
            "category":"Professional",
            "subcategory":"Secretarial Services",
            "type":"Services"
        }
    ],
    "sg:phone":"+44 1483 562306",
    "sg:postcode":"GU4 7DU",
    "sg:province":"Surrey",
    "wof:name":"Sapphire Office Services",
    "wof:placetype":"venue"
},
  "geometry": {"coordinates":[-0.527959,51.250191],"type":"Point"}
}