{
  "type": "Feature",
  "properties": {
    "addr:full":"64a Little Wakering Road, Great Wakering Southend-on-sea Essex SS3 0JH",
    "addr:housenumber":"64a",
    "addr:postcode":"ss3 0jh",
    "addr:street":"Little Wakering Road",
    "iso:country":"GB",
    "sg:address":"64a Little Wakering Road, Great Wakering",
    "sg:city":"Southend-on-sea",
    "sg:classifiers":[
        {
            "category":"Personal",
            "subcategory":"Beauty Salon",
            "type":"Services"
        }
    ],
    "sg:postcode":"SS3 0JH",
    "sg:province":"Essex",
    "sg:tags":[
        "unisex",
        "hairdresser"
    ],
    "wof:name":"Blades",
    "wof:placetype":"venue"
},
  "geometry": {"coordinates":[0.790277,51.557198],"type":"Point"}
}