{
  "type": "Feature",
  "properties": {
    "addr:full":"31 Horsham Road Littlehampton West Sussex BN17 6BZ",
    "addr:postcode":"bn17 6bz",
    "addr:street":"Horsham Road",
    "iso:country":"GB",
    "sg:address":"31 Horsham Road",
    "sg:city":"Littlehampton",
    "sg:classifiers":[
        {
            "category":"Bars & Pubs",
            "type":"Food & Drink"
        }
    ],
    "sg:phone":"+44 1903 716570",
    "sg:postcode":"BN17 6BZ",
    "sg:province":"West Sussex",
    "sg:tags":[
        "pubs",
        "house",
        "inn",
        "public",
        "activity"
    ],
    "wof:name":"The General Henrys",
    "wof:placetype":"venue"
},
  "geometry": {"coordinates":[-0.531045,50.813046],"type":"Point"}
}