{
  "type": "Feature",
  "properties": {
    "iso:country":"GB",
    "sg:address":"13 Highweek Village",
    "sg:city":"Newton Abbot",
    "sg:classifiers":[
        {
            "category":"Government",
            "subcategory":"Post Office",
            "type":"Public Place"
        }
    ],
    "sg:postcode":"TQ12 1QB",
    "sg:province":"Devon",
    "wof:name":"Highweek Post Office Stores",
    "wof:placetype":"venue"
},
  "geometry": {"coordinates":[-3.626431942,50.5369262695],"type":"Point"}
}