{
  "type": "Feature",
  "properties": {
    "addr:full":"5 Garden Terrace, Vauxhall Bridge Road London Greater London SW1V 2RG",
    "addr:housenumber":"5",
    "addr:postcode":"sw1v 2rg",
    "addr:street":"Garden Terrace Vauxhall Bridge Road",
    "iso:country":"GB",
    "sg:address":"5 Garden Terrace, Vauxhall Bridge Road",
    "sg:city":"London",
    "sg:classifiers":[
        {
            "category":"Building & Trades",
            "subcategory":"Cleaning & Sanitation",
            "type":"Services"
        }
    ],
    "sg:phone":"+44 20 7589 2251",
    "sg:postcode":"SW1V 2RG",
    "sg:province":"Greater London",
    "sg:tags":[
        "commercial"
    ],
    "wof:name":"A to Z Cleaning Co.",
    "wof:placetype":"venue"
},
  "geometry": {"coordinates":[-0.13453,51.49057],"type":"Point"}
}