{
  "type": "Feature",
  "properties": {
    "iso:country":"GB",
    "sg:address":"131 Ridgeway, Plympton",
    "sg:city":"Plymouth",
    "sg:classifiers":[
        {
            "category":"Shopping",
            "subcategory":"News",
            "type":"Retail Goods"
        }
    ],
    "sg:postcode":"PL7 2AA",
    "sg:province":"Devon",
    "sg:tags":[
        "newsagent"
    ],
    "wof:name":"C R Muldowney",
    "wof:placetype":"venue"
},
  "geometry": {"coordinates":[-4.050815,50.387711],"type":"Point"}
}