{
  "type": "Feature",
  "properties": {
    "iso:country":"GB",
    "sg:address":"17 Atlantic Rd",
    "sg:city":"Weston Super Mare",
    "sg:classifiers":[
        {
            "category":"Building & Trades",
            "subcategory":"Plumbing",
            "type":"Services"
        }
    ],
    "sg:phone":"+44 1934 626255",
    "sg:postcode":"BS23 2DT",
    "sg:province":"Somerset",
    "sg:tags":[
        "drain",
        "clearance",
        "sewer"
    ],
    "wof:name":"Aquablast",
    "wof:placetype":"venue"
},
  "geometry": {"coordinates":[-2.989645,51.355431],"type":"Point"}
}