{
  "type": "Feature",
  "properties": {
    "iso:country":"GB",
    "sg:address":"67 The Mead",
    "sg:city":"Darlington",
    "sg:classifiers":[
        {
            "category":"Shopping",
            "subcategory":"Musical Instruments",
            "type":"Retail Goods"
        }
    ],
    "sg:phone":"+44 1325 265001",
    "sg:postcode":"DL1 1EU",
    "sg:province":"Durham",
    "sg:tags":[
        "piano",
        "tuning",
        "maintenance"
    ],
    "wof:name":"Ken Bainbridge",
    "wof:placetype":"venue"
},
  "geometry": {"coordinates":[-1.53229,54.523937],"type":"Point"}
}