{
  "type": "Feature",
  "properties": {
    "addr:full":"73 Argosy Ave Blackpool Lancashire FY3 7NG",
    "addr:housenumber":"73",
    "addr:postcode":"fy3 7ng",
    "addr:street":"Argosy Ave",
    "iso:country":"GB",
    "sg:address":"73 Argosy Ave",
    "sg:city":"Blackpool",
    "sg:classifiers":[
        {
            "category":"Home & Garden",
            "subcategory":"Building Materials",
            "type":"Retail Goods"
        }
    ],
    "sg:postcode":"FY3 7NG",
    "sg:province":"Lancashire",
    "sg:tags":[
        "insulation",
        "installers"
    ],
    "wof:name":"Simmons,Peter,",
    "wof:placetype":"venue"
},
  "geometry": {"coordinates":[-3.018846,53.833549],"type":"Point"}
}