{
  "type": "Feature",
  "properties": {
    "iso:country":"GB",
    "sg:address":"Moorcourt Hall, Oakamoor",
    "sg:city":"Stoke-on-trent",
    "sg:classifiers":[
        {
            "category":"Social Services",
            "subcategory":"Retirement Home",
            "type":"Services"
        }
    ],
    "sg:phone":"+44 1538 702977",
    "sg:postcode":"ST10 3BD",
    "sg:province":"Staffordshire",
    "sg:tags":[
        "residential",
        "care"
    ],
    "wof:name":"Moorcourt Developments Ltd.",
    "wof:placetype":"venue"
},
  "geometry": {"coordinates":[-1.9196180105,53.0012283325],"type":"Point"}
}