{
  "type": "Feature",
  "properties": {
    "iso:country":"GB",
    "sg:address":"1193 Tyburn Rd",
    "sg:city":"Birmingham",
    "sg:classifiers":[
        {
            "category":"Food & Beverages",
            "subcategory":"Liquor & Beverages",
            "type":"Retail Goods"
        }
    ],
    "sg:phone":"+44 121 350 0515",
    "sg:postcode":"B24 0TE",
    "sg:province":"West Midlands",
    "sg:tags":[
        "beer",
        "spirit",
        "wines"
    ],
    "wof:name":"Mr Boozer",
    "wof:placetype":"venue"
},
  "geometry": {"coordinates":[-1.807889,52.52219],"type":"Point"}
}