{
  "type": "Feature",
  "properties": {
    "addr:full":"86 Butely Road Luton Bedfordshire LU4 9EX",
    "addr:housenumber":"86",
    "addr:postcode":"lu4 9ex",
    "addr:street":"Butely Road",
    "iso:country":"GB",
    "sg:address":"86 Butely Road",
    "sg:city":"Luton",
    "sg:classifiers":[
        {
            "category":"Professional",
            "subcategory":"Detective & Security Services",
            "type":"Services"
        }
    ],
    "sg:phone":"+44 1582 576579",
    "sg:postcode":"LU4 9EX",
    "sg:province":"Bedfordshire",
    "sg:tags":[
        "alarm",
        "burglar",
        "system"
    ],
    "wof:name":"Hawk Security Systems (Bedfordshire) Ltd.",
    "wof:placetype":"venue"
},
  "geometry": {"coordinates":[-0.4774169922,51.9084434509],"type":"Point"}
}