{
  "type": "Feature",
  "properties": {
    "iso:country":"GB",
    "sg:address":"35 Greenwood, Tweedmouth",
    "sg:city":"Berwick Upon Tweed",
    "sg:classifiers":[
        {
            "category":"Building & Trades",
            "subcategory":"Construction",
            "type":"Services"
        }
    ],
    "sg:phone":"+44 1289 308697",
    "sg:postcode":"TD15 2EB",
    "sg:province":"Northumberland",
    "sg:tags":[
        "decorator",
        "painter"
    ],
    "wof:name":"I Hay",
    "wof:placetype":"venue"
},
  "geometry": {"coordinates":[-2.018259,55.758762],"type":"Point"}
}