{
  "type": "Feature",
  "properties": {
    "addr:full":"9 Nelson St Southend-on-sea Essex SS1 1EH",
    "addr:housenumber":"9",
    "addr:postcode":"ss1 1eh",
    "addr:street":"Nelson St",
    "iso:country":"GB",
    "sg:address":"9 Nelson St",
    "sg:city":"Southend-on-sea",
    "sg:classifiers":[
        {
            "category":"Professional",
            "subcategory":"Computer Services",
            "type":"Services"
        }
    ],
    "sg:postcode":"SS1 1EH",
    "sg:province":"Essex",
    "sg:tags":[
        "system",
        "software"
    ],
    "wof:name":"Fishbone Technology Ltd",
    "wof:placetype":"venue"
},
  "geometry": {"coordinates":[0.709976,51.53643],"type":"Point"}
}