{
  "type": "Feature",
  "properties": {
    "addr:full":"4th Floor, Strand Bridge House, 138-142 Strand London Greater London WC2R 1HH",
    "addr:housenumber":"4th floor;138-142",
    "addr:postcode":"wc2r 1hh",
    "addr:street":"Strand;Strand",
    "iso:country":"GB",
    "sg:address":"4th Floor, Strand Bridge House, 138-142 Strand",
    "sg:city":"London",
    "sg:classifiers":[
        {
            "category":"Professional",
            "subcategory":"Employment Agencies",
            "type":"Services"
        }
    ],
    "sg:phone":"+44 20 7240 4433",
    "sg:postcode":"WC2R 1HH",
    "sg:province":"Greater London",
    "sg:tags":[
        "consultant"
    ],
    "wof:name":"Hill McGlynn Associates Ltd.",
    "wof:placetype":"venue"
},
  "geometry": {"coordinates":[-0.118704,51.511364],"type":"Point"}
}