{
  "type": "Feature",
  "properties": {
    "addr:full":"15-16 Eastgate Shop Cntr Inverness Highland IV2 3PP",
    "addr:housenumber":"15-16",
    "addr:postcode":"iv2 3pp",
    "addr:street":"Eastgate Shop Cntr",
    "iso:country":"GB",
    "sg:address":"15-16 Eastgate Shop Cntr",
    "sg:city":"Inverness",
    "sg:classifiers":[
        {
            "category":"Shopping",
            "subcategory":"Baby Store",
            "type":"Retail Goods"
        }
    ],
    "sg:phone":"+44 1463 241910",
    "sg:postcode":"IV2 3PP",
    "sg:province":"Highland",
    "sg:tags":[
        "nursery",
        "accessory"
    ],
    "wof:name":"Mothercare",
    "wof:placetype":"venue"
},
  "geometry": {"coordinates":[-4.22086,57.478901],"type":"Point"}
}