{
  "type": "Feature",
  "properties": {
    "iso:country":"GB",
    "sg:address":"30 Ferring Clo, Highfield",
    "sg:city":"Crawley",
    "sg:classifiers":[
        {
            "category":"Building & Trades",
            "subcategory":"Construction",
            "type":"Services"
        }
    ],
    "sg:postcode":"RH11 0AN",
    "sg:province":"West Sussex",
    "sg:tags":[
        "flooring"
    ],
    "wof:name":"Resin Flooring Ltd",
    "wof:placetype":"venue"
},
  "geometry": {"coordinates":[-0.2065079957,51.1232185364],"type":"Point"}
}