{
  "type": "Feature",
  "properties": {
    "addr:full":"9 Waterdell Lane, St Ippolyts Hitchin Hertfordshire SG4 7RA",
    "addr:housenumber":"9",
    "addr:postcode":"sg4 7ra",
    "addr:street":"Waterdell Lane",
    "iso:country":"GB",
    "sg:address":"9 Waterdell Lane, St Ippolyts",
    "sg:city":"Hitchin",
    "sg:classifiers":[
        {
            "category":"Transit Center",
            "subcategory":"Passenger",
            "type":"Transportation"
        }
    ],
    "sg:postcode":"SG4 7RA",
    "sg:province":"Hertfordshire",
    "sg:tags":[
        "boarding",
        "kennel",
        "catteries"
    ],
    "wof:name":"Waterdell Cattery",
    "wof:placetype":"venue"
},
  "geometry": {"coordinates":[-0.265683,51.928772],"type":"Point"}
}