{
  "type": "Feature",
  "properties": {
    "addr:full":"91 South St Bishops Stortford Essex CM23 3AL",
    "addr:housenumber":"91",
    "addr:postcode":"cm23 3al",
    "addr:street":"South St",
    "iso:country":"GB",
    "sg:address":"91 South St",
    "sg:city":"Bishops Stortford",
    "sg:classifiers":[
        {
            "category":"Home & Garden",
            "subcategory":"Carpets & Floor Coverings",
            "type":"Retail Goods"
        }
    ],
    "sg:postcode":"CM23 3AL",
    "sg:province":"Essex",
    "sg:tags":[
        "textile",
        "floorcoverings"
    ],
    "wof:name":"Decorative Floors",
    "wof:placetype":"venue"
},
  "geometry": {"coordinates":[0.160974,51.866455],"type":"Point"}
}