{
  "type": "Feature",
  "properties": {
    "iso:country":"GB",
    "sg:address":"26 Westgate St",
    "sg:city":"Bath",
    "sg:classifiers":[
        {
            "category":"Shopping",
            "subcategory":"News",
            "type":"Retail Goods"
        }
    ],
    "sg:phone":"+44 1225 427832",
    "sg:postcode":"BA1 1EQ",
    "sg:province":"Bath and North East Somerset",
    "sg:tags":[
        "newsagent"
    ],
    "wof:name":"New Plus",
    "wof:placetype":"venue"
},
  "geometry": {"coordinates":[-2.361975,51.381535],"type":"Point"}
}