{
  "type": "Feature",
  "properties": {
    "addr:full":"32 Waterloo Road Wolverhampton West Midlands WV1 4BN",
    "addr:housenumber":"32",
    "addr:postcode":"wv1 4bn",
    "addr:street":"Waterloo Road",
    "iso:country":"GB",
    "sg:address":"32 Waterloo Road",
    "sg:city":"Wolverhampton",
    "sg:classifiers":[
        {
            "category":"Professional",
            "subcategory":"Lawyer & Legal Services",
            "type":"Services"
        }
    ],
    "sg:phone":"+44 1902 426961",
    "sg:postcode":"WV1 4BN",
    "sg:province":"West Midlands",
    "sg:tags":[
        "solicitor"
    ],
    "wof:name":"Geoffrey T Smith & Co",
    "wof:placetype":"venue"
},
  "geometry": {"coordinates":[-2.1323039532,52.5871086121],"type":"Point"}
}