{
  "type": "Feature",
  "properties": {
    "addr:full":"1 Headgate House, Head Street Colchester Essex CO1 1NU",
    "addr:housenumber":"1",
    "addr:postcode":"co1 1nu",
    "addr:street":"Headgate House Head Street",
    "iso:country":"GB",
    "sg:address":"1 Headgate House, Head Street",
    "sg:city":"Colchester",
    "sg:classifiers":[
        {
            "category":"Fast Food",
            "type":"Food & Drink"
        }
    ],
    "sg:phone":"+44 1206 578941",
    "sg:postcode":"CO1 1NU",
    "sg:province":"Essex",
    "sg:tags":[
        "away",
        "take"
    ],
    "wof:name":"Vinny's Restaurant",
    "wof:placetype":"venue"
},
  "geometry": {"coordinates":[0.89606,51.887829],"type":"Point"}
}