{
  "type": "Feature",
  "properties": {
    "addr:full":"St Georges Works, St Georges Quay Lancaster Lancashire LA1 5QJ",
    "addr:postcode":"la1 5qj",
    "addr:street":"St Georges Quay",
    "iso:country":"GB",
    "sg:address":"St Georges Works, St Georges Quay",
    "sg:city":"Lancaster",
    "sg:classifiers":[
        {
            "category":"Building & Trades",
            "subcategory":"Construction",
            "type":"Services"
        }
    ],
    "sg:phone":"+44 1524 846406",
    "sg:postcode":"LA1 5QJ",
    "sg:province":"Lancashire",
    "sg:tags":[
        "roofing"
    ],
    "wof:name":"Roofing Supplies Lancaster",
    "wof:placetype":"venue"
},
  "geometry": {"coordinates":[-2.8111441135,54.0541305542],"type":"Point"}
}