{
  "type": "Feature",
  "properties": {
    "iso:country":"GB",
    "sg:address":"Stand Rd, Newbold",
    "sg:city":"Chesterfield",
    "sg:classifiers":[
        {
            "category":"Bars & Pubs",
            "type":"Food & Drink"
        }
    ],
    "sg:phone":"+44 1246 232975",
    "sg:postcode":"S41 8SJ",
    "sg:province":"Derbyshire",
    "sg:tags":[
        "pubs",
        "inn"
    ],
    "wof:name":"Ward,S H,& Co Ltd",
    "wof:placetype":"venue"
},
  "geometry": {"coordinates":[-1.437149,53.257404],"type":"Point"}
}