{
  "type": "Feature",
  "properties": {
    "iso:country":"GB",
    "sg:address":"Trinity St, Off Tat Bank Rd",
    "sg:city":"Oldbury",
    "sg:classifiers":[
        {
            "category":"Building & Trades",
            "subcategory":"Construction",
            "type":"Services"
        }
    ],
    "sg:phone":"+44 121 543 2950",
    "sg:postcode":"B69 4LA",
    "sg:province":"West Midlands",
    "sg:tags":[
        "platform",
        "work",
        "scaffolding"
    ],
    "wof:name":"Mitie Access Systems",
    "wof:placetype":"venue"
},
  "geometry": {"coordinates":[-2.010734,52.499722],"type":"Point"}
}