{
  "type": "Feature",
  "properties": {
    "addr:full":"Rowantree Filling Station, Crookston Musselburgh City of Edinburgh EH21 8QF",
    "addr:postcode":"eh21 8qf",
    "addr:street":"Musselburgh",
    "iso:country":"GB",
    "sg:address":"Rowantree Filling Station, Crookston",
    "sg:city":"Musselburgh",
    "sg:classifiers":[
        {
            "category":"Freight",
            "type":"Transportation"
        }
    ],
    "sg:phone":"+44 131 665 2335",
    "sg:postcode":"EH21 8QF",
    "sg:province":"City of Edinburgh",
    "sg:tags":[
        "haulage",
        "transport",
        "road"
    ],
    "wof:name":"B Mullen & Sons Ltd.",
    "wof:placetype":"venue"
},
  "geometry": {"coordinates":[-3.0497539043,55.9401168823],"type":"Point"}
}