{
  "type": "Feature",
  "properties": {
    "addr:full":"Roberts Farm, Mount Bures Bures Essex CO8 5AZ",
    "addr:postcode":"co8 5az",
    "iso:country":"GB",
    "sg:address":"Roberts Farm, Mount Bures",
    "sg:city":"Bures",
    "sg:classifiers":[
        {
            "category":"Shopping",
            "type":"Retail Goods"
        }
    ],
    "sg:postcode":"CO8 5AZ",
    "sg:province":"Essex",
    "sg:tags":[
        "merchant"
    ],
    "wof:name":"Mountfold",
    "wof:placetype":"venue"
},
  "geometry": {"coordinates":[0.77066,51.971802],"type":"Point"}
}