{
  "type": "Feature",
  "properties": {
    "iso:country":"GB",
    "sg:address":"83 Deerswood Avenue",
    "sg:city":"Hatfield",
    "sg:classifiers":[
        {
            "category":"Building & Trades",
            "subcategory":"Plumbing",
            "type":"Services"
        }
    ],
    "sg:phone":"+44 1707 276372",
    "sg:postcode":"AL10 8RZ",
    "sg:province":"Hertfordshire",
    "sg:tags":[
        "plumber",
        "heating"
    ],
    "wof:name":"A G N Plumbing",
    "wof:placetype":"venue"
},
  "geometry": {"coordinates":[-0.2256300002,51.7511253357],"type":"Point"}
}