{
  "type": "Feature",
  "properties": {
    "addr:full":"Castle Farm, Keeston Haverfordwest Pembrokeshire SA62 6ED",
    "addr:postcode":"sa62 6ed",
    "addr:street":"Keeston;Pembrokeshire",
    "iso:country":"GB",
    "sg:address":"Castle Farm, Keeston",
    "sg:city":"Haverfordwest",
    "sg:classifiers":[
        {
            "category":"Farming",
            "subcategory":"Dairy Farm",
            "type":"Manufacturing & Wholesale Goods"
        },
        {
            "category":"Farming",
            "subcategory":"Livestock Farm",
            "type":"Manufacturing & Wholesale Goods"
        }
    ],
    "sg:phone":"+44 1437 710268",
    "sg:postcode":"SA62 6ED",
    "sg:province":"Pembrokeshire",
    "sg:tags":[
        "others"
    ],
    "wof:name":"H G & B M & N L Evans",
    "wof:placetype":"venue"
},
  "geometry": {"coordinates":[-5.048198,51.83419],"type":"Point"}
}