{
  "type": "Feature",
  "properties": {
    "addr:full":"41 Tooting High Street London Greater London SW17 0SP",
    "addr:housenumber":"41",
    "addr:postcode":"sw17 0sp",
    "addr:street":"Tooting High Street",
    "iso:country":"GB",
    "sg:address":"41 Tooting High Street",
    "sg:city":"London",
    "sg:classifiers":[
        {
            "category":"Shopping",
            "subcategory":"Comic Books",
            "type":"Retail Goods"
        }
    ],
    "sg:phone":"+44 20 8672 7726",
    "sg:postcode":"SW17 0SP",
    "sg:province":"Greater London",
    "sg:tags":[
        "jeweller"
    ],
    "wof:name":"Gems",
    "wof:placetype":"venue"
},
  "geometry": {"coordinates":[-0.167088002,51.4286231995],"type":"Point"}
}