{
  "type": "Feature",
  "properties": {
    "addr:full":"210 Barnett Wood Lane Ashtead Surrey KT21 2DB",
    "addr:housenumber":"210",
    "addr:postcode":"kt21 2db",
    "addr:street":"Barnett Wood Lane",
    "iso:country":"GB",
    "sg:address":"210 Barnett Wood Lane",
    "sg:city":"Ashtead",
    "sg:classifiers":[
        {
            "category":"Personal",
            "subcategory":"Beauty Salon",
            "type":"Services"
        }
    ],
    "sg:phone":"+44 1372 272439",
    "sg:postcode":"KT21 2DB",
    "sg:province":"Surrey",
    "sg:tags":[
        "unisex",
        "ladies",
        "lady",
        "hairdresser"
    ],
    "wof:name":"Louise Fraser",
    "wof:placetype":"venue"
},
  "geometry": {"coordinates":[-0.3102670014,51.3135261536],"type":"Point"}
}