{
  "type": "Feature",
  "properties": {
    "iso:country":"GB",
    "sg:address":"6 Church Street",
    "sg:city":"Staines",
    "sg:classifiers":[
        {
            "category":"Professional",
            "subcategory":"Art Services",
            "type":"Services"
        },
        {
            "category":"Building & Trades",
            "subcategory":"Construction",
            "type":"Services"
        }
    ],
    "sg:phone":"+44 1784 452717",
    "sg:postcode":"TW18 4EP",
    "sg:province":"Berkshire",
    "sg:tags":[
        "picture",
        "household",
        "framing",
        "spraying",
        "paint"
    ],
    "wof:name":"L B A Gallery",
    "wof:placetype":"venue"
},
  "geometry": {"coordinates":[-0.5138710141,51.4336166382],"type":"Point"}
}