{
  "type": "Feature",
  "properties": {
    "addr:full":"B W P House, The Street, Ardleigh Colchester Essex CO7 7LD",
    "addr:postcode":"co7 7ld",
    "addr:street":"W P House The Street",
    "iso:country":"GB",
    "sg:address":"B W P House, The Street, Ardleigh",
    "sg:city":"Colchester",
    "sg:classifiers":[
        {
            "category":"Travel",
            "subcategory":"Travel Agent",
            "type":"Entertainment"
        }
    ],
    "sg:phone":"+44 1206 230010",
    "sg:postcode":"CO7 7LD",
    "sg:province":"Essex",
    "wof:name":"Classic Voyagers",
    "wof:placetype":"venue"
},
  "geometry": {"coordinates":[0.985040009,51.9277191162],"type":"Point"}
}