{
  "type": "Feature",
  "properties": {
    "addr:full":"56b Collins Rd Southsea Hampshire PO4 9NZ",
    "addr:housenumber":"56b",
    "addr:postcode":"po4 9nz",
    "addr:street":"Collins Rd",
    "iso:country":"GB",
    "sg:address":"56b Collins Rd",
    "sg:city":"Southsea",
    "sg:classifiers":[
        {
            "category":"Health Services",
            "subcategory":"Health Practitioner",
            "type":"Services"
        }
    ],
    "sg:phone":"+44 23 9273 4815",
    "sg:postcode":"PO4 9NZ",
    "sg:province":"Hampshire",
    "sg:tags":[
        "osteopath"
    ],
    "wof:name":"The Osteopathic Practice",
    "wof:placetype":"venue"
},
  "geometry": {"coordinates":[-1.0609929562,50.7850265503],"type":"Point"}
}