{
  "type": "Feature",
  "properties": {
    "addr:full":"Unit 2 Cannon Wharf Business Centre, 35 Evelyn Street London Greater London SE8 5RT",
    "addr:housenumber":"unit 2;business;35",
    "addr:postcode":"greater;se8 5rt",
    "addr:street":"Cannon Wharf;Evelyn Street",
    "iso:country":"GB",
    "sg:address":"Unit 2 Cannon Wharf Business Centre, 35 Evelyn Street",
    "sg:city":"London",
    "sg:classifiers":[
        {
            "category":"Personal",
            "type":"Services"
        }
    ],
    "sg:postcode":"SE8 5RT",
    "sg:province":"Greater London",
    "sg:tags":[
        "delivery"
    ],
    "wof:name":"Nathan Samuels",
    "wof:placetype":"venue"
},
  "geometry": {"coordinates":[-0.04051,51.489128],"type":"Point"}
}