{
  "type": "Feature",
  "properties": {
    "iso:country":"GB",
    "sg:address":"126 Forge St",
    "sg:city":"Glasgow",
    "sg:classifiers":[
        {
            "category":"Shopping",
            "subcategory":"News",
            "type":"Retail Goods"
        }
    ],
    "sg:postcode":"G21 2DQ",
    "sg:province":"East Dunbartonshire",
    "sg:tags":[
        "newsagent"
    ],
    "wof:name":"Park,Eileen,",
    "wof:placetype":"venue"
},
  "geometry": {"coordinates":[-4.212698,55.873943],"type":"Point"}
}