{
  "type": "Feature",
  "properties": {
    "iso:country":"GB",
    "sg:address":"Oxford Road",
    "sg:city":"Marlow",
    "sg:classifiers":[
        {
            "category":"Social Services",
            "subcategory":"Adult Care",
            "type":"Services"
        }
    ],
    "sg:postcode":"SL7 2NL",
    "sg:province":"Berkshire",
    "sg:tags":[
        "housing",
        "sheltered"
    ],
    "wof:name":"Brinkhurst",
    "wof:placetype":"venue"
},
  "geometry": {"coordinates":[-0.7827039957,51.5741004944],"type":"Point"}
}