{
  "type": "Feature",
  "properties": {
    "iso:country":"GB",
    "sg:address":"Half, White Cross Road",
    "sg:city":"York",
    "sg:classifiers":[
        {
            "category":"Professional",
            "subcategory":"Printing & Photocopies",
            "type":"Services"
        },
        {
            "category":"Government",
            "subcategory":"Post Office",
            "type":"Public Place"
        }
    ],
    "sg:phone":"+44 1904 658480",
    "sg:postcode":"YO31 8JR",
    "sg:province":"North Yorkshire",
    "sg:tags":[
        "print",
        "typesetter",
        "typesetting"
    ],
    "wof:name":"R C Bailey & Sons",
    "wof:placetype":"venue"
},
  "geometry": {"coordinates":[-1.075699,53.971481],"type":"Point"}
}