{
  "type": "Feature",
  "properties": {
    "iso:country":"GB",
    "sg:address":"29 Arlington Avenue, Gosforth",
    "sg:city":"Newcastle-upon-tyne",
    "sg:classifiers":[
        {
            "category":"Shopping",
            "subcategory":"Pharmacy",
            "type":"Retail Goods"
        }
    ],
    "sg:phone":"+44 191 285 4334",
    "sg:postcode":"NE3 4TS",
    "sg:province":"Tyne and Wear",
    "sg:tags":[
        "pharmacist",
        "chemist"
    ],
    "wof:name":"Raygale Chemist",
    "wof:placetype":"venue"
},
  "geometry": {"coordinates":[-1.644184,54.999001],"type":"Point"}
}