{
  "type": "Feature",
  "properties": {
    "iso:country":"GB",
    "sg:address":"2 Takeley Business Centre, Dunmow Road, Takeley",
    "sg:city":"Bishops Stortford",
    "sg:classifiers":[
        {
            "category":"Wholesale",
            "subcategory":"Machinery & Supplies",
            "type":"Manufacturing & Wholesale Goods"
        }
    ],
    "sg:phone":"+44 1279 871611",
    "sg:postcode":"CM22 6SJ",
    "sg:province":"Essex",
    "sg:tags":[
        "equipment",
        "-",
        "sale",
        "hydraulic",
        "accessory"
    ],
    "wof:name":"Crimp Hydraulic Services Ltd",
    "wof:placetype":"venue"
},
  "geometry": {"coordinates":[0.2668350041,51.8677711487],"type":"Point"}
}