{
  "type": "Feature",
  "properties": {
    "iso:country":"GB",
    "sg:address":"52 High Street, Shrivenham",
    "sg:city":"Swindon",
    "sg:classifiers":[
        {
            "category":"Home & Garden",
            "subcategory":"Hardware",
            "type":"Retail Goods"
        }
    ],
    "sg:phone":"+44 1793 783449",
    "sg:postcode":"SN6 8AA",
    "sg:province":"Gloucestershire",
    "wof:name":"Shrivenham Hardware",
    "wof:placetype":"venue"
},
  "geometry": {"coordinates":[-1.656847,51.59811],"type":"Point"}
}