{
  "type": "Feature",
  "properties": {
    "iso:country":"GB",
    "sg:address":"Egerton Street",
    "sg:city":"Warrington",
    "sg:classifiers":[
        {
            "category":"Health Services",
            "subcategory":"Nursing And Care Facility",
            "type":"Services"
        }
    ],
    "sg:phone":"+44 1925 573772",
    "sg:postcode":"WA1 2DF",
    "sg:province":"Cheshire",
    "sg:tags":[
        "home"
    ],
    "wof:name":"Riverbank",
    "wof:placetype":"venue"
},
  "geometry": {"coordinates":[-2.579295,53.388912],"type":"Point"}
}