{
  "type": "Feature",
  "properties": {
    "iso:country":"GB",
    "sg:address":"46 Upper Village Road",
    "sg:city":"Ascot",
    "sg:classifiers":[
        {
            "category":"Professional",
            "subcategory":"Computer Services",
            "type":"Services"
        }
    ],
    "sg:postcode":"SL5 7AQ",
    "sg:province":"Berkshire",
    "sg:tags":[
        "consultant"
    ],
    "wof:name":"Microbite Ltd",
    "wof:placetype":"venue"
},
  "geometry": {"coordinates":[-0.6574419737,51.4025878906],"type":"Point"}
}