{
  "type": "Feature",
  "properties": {
    "addr:full":"Unit 3, Crathie Court, Castlehill Ind Est Carluke South Lanarkshire ML8 5UF",
    "addr:housenumber":"unit 3",
    "addr:postcode":"ml8 5uf",
    "addr:street":"Crathie Court",
    "iso:country":"GB",
    "sg:address":"Unit 3, Crathie Court, Castlehill Ind Est",
    "sg:city":"Carluke",
    "sg:classifiers":[
        {
            "category":"Manufacturing",
            "subcategory":"Metals",
            "type":"Manufacturing & Wholesale Goods"
        }
    ],
    "sg:phone":"+44 1555 751611",
    "sg:postcode":"ML8 5UF",
    "sg:province":"South Lanarkshire",
    "sg:tags":[
        "foundry"
    ],
    "wof:name":"T.K Alucast",
    "wof:placetype":"venue"
},
  "geometry": {"coordinates":[-3.869933,55.699448],"type":"Point"}
}