{
  "type": "Feature",
  "properties": {
    "addr:full":"192 Beaumond Road, St Judes Plymouth Devon PL4 9EJ",
    "addr:housenumber":"192",
    "addr:postcode":"pl4 9ej",
    "addr:street":"Beaumond Road",
    "iso:country":"GB",
    "sg:address":"192 Beaumond Road, St Judes",
    "sg:city":"Plymouth",
    "sg:classifiers":[
        {
            "category":"Personal",
            "subcategory":"Beauty Salon",
            "type":"Services"
        }
    ],
    "sg:phone":"+44 1752 660631",
    "sg:postcode":"PL4 9EJ",
    "sg:province":"Devon",
    "sg:tags":[
        "unisex",
        "hairdresser"
    ],
    "wof:name":"Just Hair",
    "wof:placetype":"venue"
},
  "geometry": {"coordinates":[-4.1188530922,50.3755340576],"type":"Point"}
}