{
  "type": "Feature",
  "properties": {
    "iso:country":"GB",
    "sg:address":"38 Holton Road",
    "sg:city":"Barry",
    "sg:classifiers":[
        {
            "category":"Organizations",
            "subcategory":"Non-profit Organization",
            "type":"Services"
        }
    ],
    "sg:phone":"+44 1446 732385",
    "sg:postcode":"CF63 4HD",
    "sg:province":"The Vale of Glamorgan",
    "sg:tags":[
        "organisation",
        "voluntary",
        "charity"
    ],
    "wof:name":"Age Concern",
    "wof:placetype":"venue"
},
  "geometry": {"coordinates":[-3.2704069614,51.4047317505],"type":"Point"}
}