{
  "type": "Feature",
  "properties": {
    "addr:full":"Seafar House, Allanfauld Road Glasgow Falkirk G67 1HP",
    "addr:postcode":"g67 1hp",
    "addr:street":"Allanfauld Road",
    "iso:country":"GB",
    "sg:address":"Seafar House, Allanfauld Road",
    "sg:city":"Glasgow",
    "sg:classifiers":[
        {
            "category":"Shopping",
            "subcategory":"Books",
            "type":"Retail Goods"
        }
    ],
    "sg:postcode":"G67 1HP",
    "sg:province":"Falkirk",
    "sg:tags":[
        "bookseller",
        "retailer"
    ],
    "wof:name":"Bridges Book Shop",
    "wof:placetype":"venue"
},
  "geometry": {"coordinates":[-3.991013,55.952],"type":"Point"}
}