{
  "type": "Feature",
  "properties": {
    "addr:full":"23 Mill Road Lewes East Sussex BN7 2RU",
    "addr:housenumber":"23",
    "addr:postcode":"bn7 2ru",
    "addr:street":"Mill Road",
    "iso:country":"GB",
    "sg:address":"23 Mill Road",
    "sg:city":"Lewes",
    "sg:classifiers":[
        {
            "category":"Building & Trades",
            "subcategory":"Construction",
            "type":"Services"
        }
    ],
    "sg:postcode":"BN7 2RU",
    "sg:province":"East Sussex",
    "sg:tags":[
        "roofing"
    ],
    "wof:name":"Isted Roofing",
    "wof:placetype":"venue"
},
  "geometry": {"coordinates":[0.020389,50.8824386597],"type":"Point"}
}