{
  "type": "Feature",
  "properties": {
    "addr:full":"439 High Road London Greater London N17 6QH",
    "addr:housenumber":"439",
    "addr:postcode":"n17 6qh",
    "addr:street":"High Road",
    "iso:country":"GB",
    "sg:address":"439 High Road",
    "sg:city":"London",
    "sg:classifiers":[
        {
            "category":"Shopping",
            "subcategory":"Florist",
            "type":"Retail Goods"
        }
    ],
    "sg:phone":"+44 20 8808 5501",
    "sg:postcode":"N17 6QH",
    "sg:province":"Greater London",
    "wof:name":"Erden's Florist",
    "wof:placetype":"venue"
},
  "geometry": {"coordinates":[-0.070329,51.589352],"type":"Point"}
}