{
  "type": "Feature",
  "properties": {
    "addr:full":"Marton Welshpool Shropshire SY21 8JX",
    "addr:postcode":"sy21 8jx",
    "iso:country":"GB",
    "sg:address":"Marton",
    "sg:city":"Welshpool",
    "sg:classifiers":[
        {
            "category":"Bars & Pubs",
            "type":"Food & Drink"
        }
    ],
    "sg:phone":"+44 1743 891313",
    "sg:postcode":"SY21 8JX",
    "sg:province":"Shropshire",
    "sg:tags":[
        "pubs",
        "inn"
    ],
    "wof:name":"The Lowfield Inn",
    "wof:placetype":"venue"
},
  "geometry": {"coordinates":[-3.1536099911,52.6343307495],"type":"Point"}
}