{
  "type": "Feature",
  "properties": {
    "iso:country":"GB",
    "sg:address":"58 Heritage Drive",
    "sg:city":"Barry",
    "sg:classifiers":[
        {
            "category":"Professional",
            "type":"Services"
        }
    ],
    "sg:phone":"+44 1446 748353",
    "sg:postcode":"CF62 7FJ",
    "sg:province":"The Vale of Glamorgan",
    "sg:tags":[
        "services",
        "belt",
        "conveyor"
    ],
    "wof:name":"Vision Conveyers",
    "wof:placetype":"venue"
},
  "geometry": {"coordinates":[-3.284635067,51.4070243835],"type":"Point"}
}