{
  "type": "Feature",
  "properties": {
    "iso:country":"GB",
    "sg:address":"154 Grange Road",
    "sg:city":"Birmingham",
    "sg:classifiers":[
        {
            "category":"Building & Trades",
            "subcategory":"Construction",
            "type":"Services"
        }
    ],
    "sg:phone":"+44 121 444 0816",
    "sg:postcode":"B14 7RR",
    "sg:province":"West Midlands",
    "sg:tags":[
        "builder"
    ],
    "wof:name":"A C Adams & Son",
    "wof:placetype":"venue"
},
  "geometry": {"coordinates":[-1.897363,52.435127],"type":"Point"}
}