{
  "type": "Feature",
  "properties": {
    "addr:full":"86 Goodison Blvd Doncaster South Yorkshire DN4 6DG",
    "addr:housenumber":"86",
    "addr:postcode":"dn4 6dg",
    "addr:street":"Goodison Blvd",
    "iso:country":"GB",
    "sg:address":"86 Goodison Blvd",
    "sg:city":"Doncaster",
    "sg:classifiers":[
        {
            "category":"Taxi",
            "type":"Transportation"
        },
        {
            "category":"Military Area",
            "subcategory":"Air Force Base",
            "type":"Public Place"
        }
    ],
    "sg:phone":"+44 1302 531277",
    "sg:postcode":"DN4 6DG",
    "sg:province":"South Yorkshire",
    "sg:tags":[
        "mini",
        "hire",
        "private",
        "cab"
    ],
    "wof:name":"B J Seven",
    "wof:placetype":"venue"
},
  "geometry": {"coordinates":[-1.0734649897,53.5034065247],"type":"Point"}
}