{
  "type": "Feature",
  "properties": {
    "addr:full":"Hillcrest, Whalley Rd, Billington Clitheroe Lancashire BB7 9NW",
    "addr:postcode":"bb7 9nw",
    "addr:street":"Whalley Rd",
    "iso:country":"GB",
    "sg:address":"Hillcrest, Whalley Rd, Billington",
    "sg:city":"Clitheroe",
    "sg:classifiers":[
        {
            "category":"Banks & Credit Unions",
            "subcategory":"Bank",
            "type":"Services"
        }
    ],
    "sg:phone":"+44 1254 825334",
    "sg:postcode":"BB7 9NW",
    "sg:province":"Lancashire",
    "sg:tags":[
        "stocktaking",
        "inventory"
    ],
    "wof:name":"Stocktake UK",
    "wof:placetype":"venue"
},
  "geometry": {"coordinates":[-2.4222970009,53.8165435791],"type":"Point"}
}