{
  "type": "Feature",
  "properties": {
    "addr:full":"Pottergate Alnwick Northumberland NE66 1JW",
    "addr:postcode":"ne66 1jw",
    "addr:street":"Pottergate",
    "iso:country":"GB",
    "sg:address":"Pottergate",
    "sg:city":"Alnwick",
    "sg:classifiers":[
        {
            "category":"Taxi",
            "type":"Transportation"
        },
        {
            "category":"Military Area",
            "subcategory":"Air Force Base",
            "type":"Public Place"
        }
    ],
    "sg:phone":"+44 1665 606666",
    "sg:postcode":"NE66 1JW",
    "sg:province":"Northumberland",
    "sg:tags":[
        "mini",
        "hire",
        "private",
        "cab"
    ],
    "wof:name":"Z Cars",
    "wof:placetype":"venue"
},
  "geometry": {"coordinates":[-1.709999,55.414951],"type":"Point"}
}