{
  "type": "Feature",
  "properties": {
    "addr:full":"Chatterton Works, Chantry Lane Bromley Kent BR2 9QL",
    "addr:postcode":"br2 9ql",
    "addr:street":"Chantry Lane",
    "iso:country":"GB",
    "sg:address":"Chatterton Works, Chantry Lane",
    "sg:city":"Bromley",
    "sg:classifiers":[
        {
            "category":"Professional",
            "subcategory":"Printing & Photocopies",
            "type":"Services"
        }
    ],
    "sg:phone":"+44 20 8460 4780",
    "sg:postcode":"BR2 9QL",
    "sg:province":"Kent",
    "sg:tags":[
        "printer"
    ],
    "wof:name":"Any-Print Ltd.",
    "wof:placetype":"venue"
},
  "geometry": {"coordinates":[0.033745,51.39378],"type":"Point"}
}