{
  "type": "Feature",
  "properties": {
    "iso:country":"GB",
    "sg:address":"29 Charnley Rd",
    "sg:city":"Blackpool",
    "sg:classifiers":[
        {
            "category":"Travel",
            "subcategory":"Hotels & Motels",
            "type":"Entertainment"
        }
    ],
    "sg:phone":"+44 1253 623671",
    "sg:postcode":"FY1 4PE",
    "sg:province":"Lancashire",
    "wof:name":"Clevedon Hotel",
    "wof:placetype":"venue"
},
  "geometry": {"coordinates":[-3.047653,53.815449],"type":"Point"}
}