{
  "type": "Feature",
  "properties": {
    "iso:country":"GB",
    "sg:address":"J Floor Argyle House, 3 Lady Lawson",
    "sg:city":"Edinburgh",
    "sg:classifiers":[
        {
            "category":"Government",
            "subcategory":"Office",
            "type":"Public Place"
        }
    ],
    "sg:phone":"+44 131 529 8500",
    "sg:postcode":"EH3 9SE",
    "sg:province":"City of Edinburgh",
    "sg:tags":[
        "local",
        "central"
    ],
    "wof:name":"Scottish Traffic Area Office",
    "wof:placetype":"venue"
},
  "geometry": {"coordinates":[-3.2015519142,55.9465904236],"type":"Point"}
}