{
  "type": "Feature",
  "properties": {
    "addr:full":"20 Oakdene Avenue Chislehurst Kent BR7 6EA",
    "addr:housenumber":"20",
    "addr:postcode":"br7 6ea",
    "addr:street":"Oakdene Avenue",
    "iso:country":"GB",
    "sg:address":"20 Oakdene Avenue",
    "sg:city":"Chislehurst",
    "sg:classifiers":[
        {
            "category":"Building & Trades",
            "subcategory":"Plumbing",
            "type":"Services"
        }
    ],
    "sg:phone":"+44 20 8851 3963",
    "sg:postcode":"BR7 6EA",
    "sg:province":"Kent",
    "sg:tags":[
        "heating"
    ],
    "wof:name":"A & G Plumbing",
    "wof:placetype":"venue"
},
  "geometry": {"coordinates":[0.056637,51.423313],"type":"Point"}
}