{
  "type": "Feature",
  "properties": {
    "iso:country":"GB",
    "sg:address":"37 Treassowe Road",
    "sg:city":"Penzance",
    "sg:classifiers":[
        {
            "category":"Professional",
            "subcategory":"Engineering",
            "type":"Services"
        }
    ],
    "sg:postcode":"TR18 2AU",
    "sg:province":"Cornwall",
    "sg:tags":[
        "contractor",
        "electrical",
        "engineer"
    ],
    "wof:name":"Alan Symons Electrical Contractor",
    "wof:placetype":"venue"
},
  "geometry": {"coordinates":[-5.5362739563,50.1254348755],"type":"Point"}
}