{
  "type": "Feature",
  "properties": {
    "iso:country":"GB",
    "sg:address":"Cobden Mill, Gower Street",
    "sg:city":"Bolton",
    "sg:classifiers":[
        {
            "category":"Home & Garden",
            "subcategory":"Carpets & Floor Coverings",
            "type":"Retail Goods"
        }
    ],
    "sg:postcode":"BL4 7HA",
    "sg:province":"Lancashire",
    "sg:tags":[
        "carpets",
        "rug",
        "matting"
    ],
    "wof:name":"Davray Floorcoverings",
    "wof:placetype":"venue"
},
  "geometry": {"coordinates":[-2.40704,53.552269],"type":"Point"}
}