{
  "type": "Feature",
  "properties": {
    "iso:country":"GB",
    "sg:address":"144 Thornes Lane",
    "sg:city":"Wakefield",
    "sg:classifiers":[
        {
            "category":"Community Center",
            "subcategory":"Youth",
            "type":"Public Place"
        }
    ],
    "sg:postcode":"WF2 7XG",
    "sg:province":"West Yorkshire",
    "sg:tags":[
        "children's",
        "activity"
    ],
    "wof:name":"Alphabet Zoo",
    "wof:placetype":"venue"
},
  "geometry": {"coordinates":[-1.500541,53.671928],"type":"Point"}
}