{
  "type": "Feature",
  "properties": {
    "iso:country":"GB",
    "sg:address":"Beaumont, Burfield Road",
    "sg:city":"Windsor",
    "sg:classifiers":[
        {
            "category":"Education",
            "subcategory":"Special Training",
            "type":"Public Place"
        }
    ],
    "sg:phone":"+44 1753 868181",
    "sg:postcode":"SL4 2JP",
    "sg:province":"Berkshire",
    "sg:tags":[
        "product",
        "centre"
    ],
    "wof:name":"Icl Training (No 2) Ltd.",
    "wof:placetype":"venue"
},
  "geometry": {"coordinates":[-0.5791490078,51.458114624],"type":"Point"}
}