{
  "type": "Feature",
  "properties": {
    "addr:full":"169 Camberwell Road London Greater London SE5 0HB",
    "addr:housenumber":"169",
    "addr:postcode":"se5 0hb",
    "addr:street":"Camberwell Road",
    "iso:country":"GB",
    "sg:address":"169 Camberwell Road",
    "sg:city":"London",
    "sg:classifiers":[
        {
            "category":"Home & Garden",
            "subcategory":"Furniture",
            "type":"Retail Goods"
        }
    ],
    "sg:phone":"+44 20 8691 0202",
    "sg:postcode":"SE5 0HB",
    "sg:province":"Greater London",
    "wof:name":"The Camberwell Gallery",
    "wof:placetype":"venue"
},
  "geometry": {"coordinates":[-0.093996,51.479721],"type":"Point"}
}