{
  "type": "Feature",
  "properties": {
    "iso:country":"GB",
    "sg:address":"24 Durham Road, Chilton",
    "sg:city":"Ferryhill",
    "sg:classifiers":[
        {
            "category":"Manufacturing",
            "subcategory":"Petroleum Products",
            "type":"Manufacturing & Wholesale Goods"
        }
    ],
    "sg:phone":"+44 1388 721333",
    "sg:postcode":"DL17 0EX",
    "sg:province":"Durham",
    "sg:tags":[
        "double",
        "glazing"
    ],
    "wof:name":"Durham Design",
    "wof:placetype":"venue"
},
  "geometry": {"coordinates":[-1.5591520071,54.6594848633],"type":"Point"}
}