{
  "type": "Feature",
  "properties": {
    "addr:full":"8 Calder St Burnley Lancashire BB11 1PQ",
    "addr:housenumber":"8",
    "addr:postcode":"bb11 1pq",
    "addr:street":"Calder St",
    "iso:country":"GB",
    "sg:address":"8 Calder St",
    "sg:city":"Burnley",
    "sg:classifiers":[
        {
            "category":"Place Of Worship",
            "type":"Public Place"
        }
    ],
    "sg:phone":"+44 1282 422251",
    "sg:postcode":"BB11 1PQ",
    "sg:province":"Lancashire",
    "wof:name":"Christian Science Reading Room",
    "wof:placetype":"venue"
},
  "geometry": {"coordinates":[-2.2472689152,53.790599823],"type":"Point"}
}