{
  "type": "Feature",
  "properties": {
    "addr:full":"Lloyd's Building, 1 Lime Street London Greater London EC3M 7HL",
    "addr:postcode":"ec3m 7hl",
    "addr:street":"Lime Street",
    "iso:country":"GB",
    "sg:address":"Lloyd's Building, 1 Lime Street",
    "sg:city":"London",
    "sg:classifiers":[
        {
            "category":"Insurance",
            "subcategory":"Insurance Agent",
            "type":"Services"
        }
    ],
    "sg:phone":"+44 20 7327 3175",
    "sg:postcode":"EC3M 7HL",
    "sg:province":"Greater London",
    "wof:name":"Hill Aerospace Syndicate 800",
    "wof:placetype":"venue"
},
  "geometry": {"coordinates":[-0.08274,51.512291],"type":"Point"}
}