{
  "type": "Feature",
  "properties": {
    "addr:full":"Lidgett House, 56 Lidgett Lane, Garforth Leeds North Yorkshire LS25 1LL",
    "addr:housenumber":"56",
    "addr:postcode":"ls25 1ll",
    "addr:street":"Lidgett Lane",
    "iso:country":"GB",
    "sg:address":"Lidgett House, 56 Lidgett Lane, Garforth",
    "sg:city":"Leeds",
    "sg:classifiers":[
        {
            "category":"Professional",
            "subcategory":"Employment Agencies",
            "type":"Services"
        }
    ],
    "sg:phone":"+44 113 287 2855",
    "sg:postcode":"LS25 1LL",
    "sg:province":"North Yorkshire",
    "sg:tags":[
        "consultant",
        "recruitment"
    ],
    "sg:website":"http://www.mccourtnewton.co.uk",
    "wof:name":"McCourt Newton Ltd.",
    "wof:placetype":"venue"
},
  "geometry": {"coordinates":[-1.3903290033,53.7901344299],"type":"Point"}
}