{
  "type": "Feature",
  "properties": {
    "iso:country":"GB",
    "sg:address":"Peasholm Gap",
    "sg:city":"Scarborough",
    "sg:classifiers":[
        {
            "category":"Cafe",
            "type":"Food & Drink"
        },
        {
            "category":"Arts & Performance",
            "subcategory":"Theater",
            "type":"Entertainment"
        }
    ],
    "sg:phone":"+44 1723 355000",
    "sg:postcode":"YO12 7TU",
    "sg:province":"North Yorkshire",
    "sg:tags":[
        "tea",
        "room",
        "concert",
        "theatre",
        "hall"
    ],
    "wof:name":"Corner Complex Box Office",
    "wof:placetype":"venue"
},
  "geometry": {"coordinates":[-0.4076089859,54.2927246094],"type":"Point"}
}