{
  "type": "Feature",
  "properties": {
    "addr:full":"18 Station Parade, Tarring Road Worthing West Sussex BN11 4SS",
    "addr:housenumber":"18",
    "addr:postcode":"bn11 4ss",
    "addr:street":"Station Parade Tarring Road",
    "iso:country":"GB",
    "sg:address":"18 Station Parade, Tarring Road",
    "sg:city":"Worthing",
    "sg:classifiers":[
        {
            "category":"Health Services",
            "subcategory":"Dentist",
            "type":"Services"
        }
    ],
    "sg:phone":"+44 1903 241578",
    "sg:postcode":"BN11 4SS",
    "sg:province":"West Sussex",
    "sg:tags":[
        "technician",
        "dental"
    ],
    "wof:name":"Fisher Dental Laboratory",
    "wof:placetype":"venue"
},
  "geometry": {"coordinates":[-0.375424,50.813625],"type":"Point"}
}