{
  "type": "Feature",
  "properties": {
    "iso:country":"GB",
    "sg:address":"260 Hoo Road",
    "sg:city":"Kidderminster",
    "sg:classifiers":[
        {
            "category":"Shopping",
            "subcategory":"News",
            "type":"Retail Goods"
        }
    ],
    "sg:phone":"+44 1562 823989",
    "sg:postcode":"DY10 1LY",
    "sg:province":"Staffordshire",
    "sg:tags":[
        "newsagent"
    ],
    "wof:name":"P & C MINI MARKET",
    "wof:placetype":"venue"
},
  "geometry": {"coordinates":[-2.2439520359,52.380355835],"type":"Point"}
}