{
  "type": "Feature",
  "properties": {
    "addr:full":"45 Coney Grn, Abbotts Barton Winchester Hampshire SO23 7BJ",
    "addr:housenumber":"45",
    "addr:postcode":"so23 7bj",
    "addr:street":"Coney Grn Abbotts Barton",
    "iso:country":"GB",
    "sg:address":"45 Coney Grn, Abbotts Barton",
    "sg:city":"Winchester",
    "sg:classifiers":[
        {
            "category":"Building & Trades",
            "subcategory":"Construction",
            "type":"Services"
        }
    ],
    "sg:postcode":"SO23 7BJ",
    "sg:province":"Hampshire",
    "sg:tags":[
        "glazier"
    ],
    "wof:name":"Hatt,Michael C,",
    "wof:placetype":"venue"
},
  "geometry": {"coordinates":[-1.3168090582,51.0630683899],"type":"Point"}
}