{
  "type": "Feature",
  "properties": {
    "addr:full":"Rose Villa, North Road, Whitemoor St Austell Cornwall PL26 7XL",
    "addr:postcode":"pl26 7xl",
    "addr:street":"North Road",
    "iso:country":"GB",
    "sg:address":"Rose Villa, North Road, Whitemoor",
    "sg:city":"St Austell",
    "sg:classifiers":[
        {
            "category":"Professional",
            "subcategory":"Accounting & Tax Preparation",
            "type":"Services"
        }
    ],
    "sg:phone":"+44 1726 823200",
    "sg:postcode":"PL26 7XL",
    "sg:province":"Cornwall",
    "sg:tags":[
        "accountant"
    ],
    "wof:name":"Asquith Burton Ltd.",
    "wof:placetype":"venue"
},
  "geometry": {"coordinates":[-4.852472,50.385426],"type":"Point"}
}