{
  "type": "Feature",
  "properties": {
    "iso:country":"GB",
    "sg:address":"Fort Road, Lerwick",
    "sg:city":"Lerwick",
    "sg:classifiers":[
        {
            "category":"Professional",
            "subcategory":"Engineering",
            "type":"Services"
        },
        {
            "category":"Building & Trades",
            "subcategory":"Electrical",
            "type":"Services"
        }
    ],
    "sg:phone":"+44 1595 692557",
    "sg:postcode":"ZE1 0LW",
    "sg:province":"Shetland Islands",
    "sg:tags":[
        "engineer",
        "electrician",
        "contractor"
    ],
    "wof:name":"Robertson & Peterson",
    "wof:placetype":"venue"
},
  "geometry": {"coordinates":[-1.1458740234,60.1563796997],"type":"Point"}
}