{
  "type": "Feature",
  "properties": {
    "addr:full":"95-97 Queensway, Bletchley Milton Keynes Buckinghamshire MK2 2DW",
    "addr:housenumber":"95-97",
    "addr:postcode":"mk2 2dw",
    "addr:street":"Queensway",
    "iso:country":"GB",
    "sg:address":"95-97 Queensway, Bletchley",
    "sg:city":"Milton Keynes",
    "sg:classifiers":[
        {
            "category":"Shopping",
            "subcategory":"Crafts & Fabrics",
            "type":"Retail Goods"
        }
    ],
    "sg:phone":"+44 1908 372341",
    "sg:postcode":"MK2 2DW",
    "sg:province":"Buckinghamshire",
    "sg:tags":[
        "shop"
    ],
    "wof:name":"Kash N Karry Fashion & Fabrics",
    "wof:placetype":"venue"
},
  "geometry": {"coordinates":[-0.729872,51.994911],"type":"Point"}
}