{
  "type": "Feature",
  "properties": {
    "iso:country":"GB",
    "sg:address":"The Coach Ho, The Square",
    "sg:city":"Barnard Castle",
    "sg:classifiers":[
        {
            "category":"Professional",
            "type":"Services"
        }
    ],
    "sg:phone":"+44 1833 627201",
    "sg:postcode":"DL12 9SD",
    "sg:province":"Cumbria",
    "sg:tags":[
        "entertainer"
    ],
    "wof:name":"Laser Sporting Ltd",
    "wof:placetype":"venue"
},
  "geometry": {"coordinates":[-1.923809,54.543152],"type":"Point"}
}