{
  "type": "Feature",
  "properties": {
    "iso:country":"GB",
    "sg:address":"6 Aylsham Road",
    "sg:city":"Norwich",
    "sg:classifiers":[
        {
            "category":"Communications",
            "type":"Services"
        }
    ],
    "sg:phone":"+44 1603 625941",
    "sg:postcode":"NR3 3HQ",
    "sg:province":"Norfolk",
    "sg:tags":[
        "tv",
        "video",
        "radio"
    ],
    "wof:name":"Hubbards",
    "wof:placetype":"venue"
},
  "geometry": {"coordinates":[1.290727,52.638863],"type":"Point"}
}