{
  "type": "Feature",
  "properties": {
    "iso:country":"GB",
    "sg:address":"35 New Cavendish Street",
    "sg:city":"London",
    "sg:classifiers":[
        {
            "category":"Bars & Pubs",
            "type":"Food & Drink"
        }
    ],
    "sg:phone":"+44 20 7935 4814",
    "sg:postcode":"W1G 9UE",
    "sg:province":"Greater London",
    "sg:tags":[
        "pubs",
        "inn"
    ],
    "wof:name":"The Duke of York",
    "wof:placetype":"venue"
},
  "geometry": {"coordinates":[-0.149811998,51.5190162659],"type":"Point"}
}