{
  "type": "Feature",
  "properties": {
    "addr:full":"Burcot Brook, Burcot Abingdon Oxfordshire OX14 3DP",
    "addr:postcode":"ox14 3dp",
    "iso:country":"GB",
    "sg:address":"Burcot Brook, Burcot",
    "sg:city":"Abingdon",
    "sg:classifiers":[
        {
            "category":"Health Services",
            "subcategory":"Nursing And Care Facility",
            "type":"Services"
        },
        {
            "category":"Social Services",
            "subcategory":"Retirement Home",
            "type":"Services"
        }
    ],
    "sg:phone":"+44 1865 340324",
    "sg:postcode":"OX14 3DP",
    "sg:province":"Oxfordshire",
    "sg:tags":[
        "residential"
    ],
    "wof:name":"John Masefield Cheshire Homes",
    "wof:placetype":"venue"
},
  "geometry": {"coordinates":[-1.1907000542,51.6607322693],"type":"Point"}
}