{
  "type": "Feature",
  "properties": {
    "addr:full":"Homelea, Uttoxeter Road Rugeley Staffordshire WS15 3EQ",
    "addr:postcode":"ws15 3eq",
    "addr:street":"Uttoxeter Road",
    "iso:country":"GB",
    "sg:address":"Homelea, Uttoxeter Road",
    "sg:city":"Rugeley",
    "sg:classifiers":[
        {
            "category":"Retail",
            "subcategory":"Auto Rental",
            "type":"Services"
        }
    ],
    "sg:phone":"+44 1283 840900",
    "sg:postcode":"WS15 3EQ",
    "sg:province":"Staffordshire",
    "sg:tags":[
        "car",
        "hire",
        "truck"
    ],
    "wof:name":"Magnofax Ltd.",
    "wof:placetype":"venue"
},
  "geometry": {"coordinates":[-1.889538,52.820858],"type":"Point"}
}