{
  "type": "Feature",
  "properties": {
    "addr:full":"1 Manse Rd West Kilbride North Ayrshire KA23 9AT",
    "addr:housenumber":"1",
    "addr:postcode":"ka23 9at",
    "addr:street":"Manse Rd",
    "iso:country":"GB",
    "sg:address":"1 Manse Rd",
    "sg:city":"West Kilbride",
    "sg:classifiers":[
        {
            "category":"Recreation",
            "subcategory":"Marina",
            "type":"Entertainment"
        }
    ],
    "sg:phone":"+44 1294 822850",
    "sg:postcode":"KA23 9AT",
    "sg:province":"North Ayrshire",
    "wof:name":"Marcon Marine Consultants",
    "wof:placetype":"venue"
},
  "geometry": {"coordinates":[-4.856317997,55.6952972412],"type":"Point"}
}