{
  "type": "Feature",
  "properties": {
    "iso:country":"GB",
    "sg:address":"The Causeway Monkwearmouth",
    "sg:city":"Sunderland",
    "sg:classifiers":[
        {
            "category":"Place Of Worship",
            "type":"Public Place"
        }
    ],
    "sg:phone":"+44 191 567 2965",
    "sg:postcode":"SR6 0BH",
    "sg:province":"Tyne and Wear",
    "wof:name":"St. Benets R C Church",
    "wof:placetype":"venue"
},
  "geometry": {"coordinates":[-1.379319,54.914566],"type":"Point"}
}