{
  "type": "Feature",
  "properties": {
    "addr:full":"Nest Road, Fellingindstl Estate Gateshead Tyne and Wear NE10 0ES",
    "addr:postcode":"ne10 0es",
    "addr:street":"Nest Road Fellingindstl Estate",
    "iso:country":"GB",
    "sg:address":"Nest Road, Fellingindstl Estate",
    "sg:city":"Gateshead",
    "sg:classifiers":[
        {
            "category":"Food & Beverages",
            "subcategory":"Liquor & Beverages",
            "type":"Retail Goods"
        },
        {
            "category":"Professional",
            "subcategory":"Business Services",
            "type":"Services"
        }
    ],
    "sg:phone":"+44 191 495 5000",
    "sg:postcode":"NE10 0ES",
    "sg:province":"Tyne and Wear",
    "sg:tags":[
        "wines",
        "agent",
        "beer",
        "export",
        "import",
        "spirit"
    ],
    "wof:name":"Scottish Courage Ltd.",
    "wof:placetype":"venue"
},
  "geometry": {"coordinates":[-1.5674860477,54.9604644775],"type":"Point"}
}