{
  "type": "Feature",
  "properties": {
    "addr:full":"6 Mansel Terrace, Cwmbwrla Swansea Swansea SA5 8NN",
    "addr:housenumber":"6",
    "addr:postcode":"sa5 8nn",
    "addr:street":"Mansel Terrace",
    "iso:country":"GB",
    "sg:address":"6 Mansel Terrace, Cwmbwrla",
    "sg:city":"Swansea",
    "sg:classifiers":[
        {
            "category":"Government",
            "subcategory":"Post Office",
            "type":"Public Place"
        }
    ],
    "sg:phone":"+44 1792 652612",
    "sg:postcode":"SA5 8NN",
    "sg:province":"Swansea",
    "wof:name":"Cwmbwrla Post Office",
    "wof:placetype":"venue"
},
  "geometry": {"coordinates":[-3.9520390034,51.6355361938],"type":"Point"}
}