{
  "type": "Feature",
  "properties": {
    "addr:full":"6-8 Mill Road Burgess Hill East Sussex RH15 8DR",
    "addr:housenumber":"6-8",
    "addr:postcode":"rh15 8dr",
    "addr:street":"Mill Road",
    "iso:country":"GB",
    "sg:address":"6-8 Mill Road",
    "sg:city":"Burgess Hill",
    "sg:classifiers":[
        {
            "category":"Restaurant",
            "type":"Food & Drink"
        }
    ],
    "sg:phone":"+44 1444 236384",
    "sg:postcode":"RH15 8DR",
    "sg:province":"East Sussex",
    "sg:tags":[
        "-",
        "chinese"
    ],
    "wof:name":"China Garden",
    "wof:placetype":"venue"
},
  "geometry": {"coordinates":[-0.1285320073,50.9549064636],"type":"Point"}
}