{
  "type": "Feature",
  "properties": {
    "iso:country":"GB",
    "sg:address":"Tormitchell Quarry",
    "sg:city":"Girvan",
    "sg:classifiers":[
        {
            "category":"Mining & Drilling",
            "type":"Manufacturing & Wholesale Goods"
        },
        {
            "category":"Manufacturing",
            "subcategory":"Glass & Minerals",
            "type":"Manufacturing & Wholesale Goods"
        }
    ],
    "sg:phone":"+44 1465 871250",
    "sg:postcode":"KA26 0TT",
    "sg:province":"South Ayrshire",
    "sg:tags":[
        "chalk",
        "stone",
        "slate",
        "quarry"
    ],
    "wof:name":"Barr Quarries",
    "wof:placetype":"venue"
},
  "geometry": {"coordinates":[-4.8577218056,55.2360305786],"type":"Point"}
}