{
  "type": "Feature",
  "properties": {
    "iso:country":"GB",
    "sg:address":"Leny Road",
    "sg:city":"Callander",
    "sg:classifiers":[
        {
            "category":"Travel",
            "subcategory":"Hotels & Motels",
            "type":"Entertainment"
        }
    ],
    "sg:phone":"+44 1877 330871",
    "sg:postcode":"FK17 8AW",
    "sg:province":"Stirling",
    "sg:tags":[
        "house",
        "guest"
    ],
    "wof:name":"Craig Villa",
    "wof:placetype":"venue"
},
  "geometry": {"coordinates":[-4.2206802368,56.244846344],"type":"Point"}
}