{
  "type": "Feature",
  "properties": {
    "iso:country":"GB",
    "sg:address":"4 Bridge Street",
    "sg:city":"Tadcaster",
    "sg:classifiers":[
        {
            "category":"Real Estate",
            "subcategory":"Developer",
            "type":"Services"
        }
    ],
    "sg:phone":"+44 1937 835573",
    "sg:postcode":"LS24 9AL",
    "sg:province":"North Yorkshire",
    "sg:tags":[
        "property"
    ],
    "wof:name":"City Land (Estates) Ltd.",
    "wof:placetype":"venue"
},
  "geometry": {"coordinates":[-1.260208,53.884979],"type":"Point"}
}