{
  "type": "Feature",
  "properties": {
    "addr:full":"208 Wolverhampton St Dudley West Midlands DY1 1DZ",
    "addr:housenumber":"208",
    "addr:postcode":"dy1 1dz",
    "addr:street":"Wolverhampton St",
    "iso:country":"GB",
    "sg:address":"208 Wolverhampton St",
    "sg:city":"Dudley",
    "sg:classifiers":[
        {
            "category":"Organizations",
            "subcategory":"Non-profit Organization",
            "type":"Services"
        }
    ],
    "sg:postcode":"DY1 1DZ",
    "sg:province":"West Midlands",
    "sg:tags":[
        "organisation",
        "voluntary",
        "charity"
    ],
    "wof:name":"National Council of Young Men's Christia",
    "wof:placetype":"venue"
},
  "geometry": {"coordinates":[-2.0848519802,52.5103302002],"type":"Point"}
}