{
  "type": "Feature",
  "properties": {
    "iso:country":"GB",
    "sg:address":"2 Star Lane",
    "sg:city":"Ringwood",
    "sg:classifiers":[
        {
            "category":"Shopping",
            "subcategory":"Computers & Home Electronics",
            "type":"Retail Goods"
        }
    ],
    "sg:phone":"+44 1425 461230",
    "sg:postcode":"BH24 1AL",
    "sg:province":"Dorset",
    "sg:tags":[
        "hi-fi",
        "centre"
    ],
    "wof:name":"Phonography Ltd.",
    "wof:placetype":"venue"
},
  "geometry": {"coordinates":[-1.7929890156,50.8463287354],"type":"Point"}
}