{
  "type": "Feature",
  "properties": {
    "addr:full":"6 Westbourne Park Road London Greater London W2 5PH",
    "addr:housenumber":"6",
    "addr:postcode":"w2 5ph",
    "addr:street":"Westbourne Park Road",
    "iso:country":"GB",
    "sg:address":"6 Westbourne Park Road",
    "sg:city":"London",
    "sg:classifiers":[
        {
            "category":"Utilities",
            "type":"Services"
        }
    ],
    "sg:postcode":"W2 5PH",
    "sg:province":"Greater London",
    "sg:tags":[
        "internet"
    ],
    "wof:name":"The Peoples Net Ltd",
    "wof:placetype":"venue"
},
  "geometry": {"coordinates":[-0.189598,51.518154],"type":"Point"}
}