{
  "type": "Feature",
  "properties": {
    "iso:country":"GB",
    "sg:address":"3 Camilla House, Chessington Hall Gardens",
    "sg:city":"Chessington",
    "sg:classifiers":[
        {
            "category":"Organizations",
            "subcategory":"Membership Organization",
            "type":"Services"
        }
    ],
    "sg:postcode":"KT9 2HH",
    "sg:province":"Surrey",
    "sg:tags":[
        "club"
    ],
    "wof:name":"The Octopus Garden Ltd",
    "wof:placetype":"venue"
},
  "geometry": {"coordinates":[-0.310905,51.358231],"type":"Point"}
}