{
  "type": "Feature",
  "properties": {
    "iso:country":"GB",
    "sg:address":"Whitleigh Barn, Lancaster Gardens",
    "sg:city":"Plymouth",
    "sg:classifiers":[
        {
            "category":"Arena",
            "subcategory":"Sports Club",
            "type":"Entertainment"
        }
    ],
    "sg:phone":"+44 1752 781495",
    "sg:postcode":"PL5 4AA",
    "sg:province":"Devon",
    "wof:name":"Saxon Amateur Boxing Club",
    "wof:placetype":"venue"
},
  "geometry": {"coordinates":[-4.158406,50.419231],"type":"Point"}
}