{
  "type": "Feature",
  "properties": {
    "addr:full":"Canal Road, Higham Rochester Kent ME3 7JA",
    "addr:postcode":"me3 7ja",
    "addr:street":"Canal Road",
    "iso:country":"GB",
    "sg:address":"Canal Road, Higham",
    "sg:city":"Rochester",
    "sg:classifiers":[
        {
            "category":"Retail",
            "subcategory":"Auto Repair",
            "type":"Services"
        }
    ],
    "sg:phone":"+44 1474 824010",
    "sg:postcode":"ME3 7JA",
    "sg:province":"Kent",
    "sg:tags":[
        "body",
        "car"
    ],
    "wof:name":"Smithy's Auto Body Repair Shop",
    "wof:placetype":"venue"
},
  "geometry": {"coordinates":[0.4597960114,51.4354095459],"type":"Point"}
}