{
  "type": "Feature",
  "properties": {
    "iso:country":"GB",
    "sg:address":"2 Kenilworth Drive",
    "sg:city":"Kidderminster",
    "sg:classifiers":[
        {
            "category":"Professional",
            "subcategory":"Secretarial Services",
            "type":"Services"
        }
    ],
    "sg:phone":"+44 1562 754587",
    "sg:postcode":"DY10 1YD",
    "sg:province":"Staffordshire",
    "wof:name":"Just Write Word Processing & Secretarial Services",
    "wof:placetype":"venue"
},
  "geometry": {"coordinates":[-2.246057,52.368629],"type":"Point"}
}