{
  "type": "Feature",
  "properties": {
    "addr:full":"Unit 12 Ackhurst Road, Common Bank Industrial Estate Chorley Lancashire PR7 1NH",
    "addr:housenumber":"unit 12;estate",
    "addr:postcode":"pr7 1nh",
    "addr:street":"Ackhurst Road Common;Industrial",
    "iso:country":"GB",
    "sg:address":"Unit 12 Ackhurst Road, Common Bank Industrial Estate",
    "sg:city":"Chorley",
    "sg:classifiers":[
        {
            "category":"Professional",
            "subcategory":"Engineering",
            "type":"Services"
        }
    ],
    "sg:postcode":"PR7 1NH",
    "sg:province":"Lancashire",
    "sg:tags":[
        "precision",
        "engineer"
    ],
    "wof:name":"Sharp Engineering Co.",
    "wof:placetype":"venue"
},
  "geometry": {"coordinates":[-2.65396,53.655384],"type":"Point"}
}