{
  "type": "Feature",
  "properties": {
    "addr:full":"25 Old Nichol Street London Greater London E2 7HR",
    "addr:housenumber":"25",
    "addr:postcode":"e2 7hr",
    "addr:street":"Old Nichol Street",
    "iso:country":"GB",
    "sg:address":"25 Old Nichol Street",
    "sg:city":"London",
    "sg:classifiers":[
        {
            "category":"Shopping",
            "subcategory":"Department Store",
            "type":"Retail Goods"
        }
    ],
    "sg:postcode":"E2 7HR",
    "sg:province":"Greater London",
    "wof:name":"J B General Stores",
    "wof:placetype":"venue"
},
  "geometry": {"coordinates":[-0.075374,51.524647],"type":"Point"}
}