{
  "type": "Feature",
  "properties": {
    "addr:full":"595 Stockport Rd, Longsight Manchester Greater Manchester M13 0RX",
    "addr:housenumber":"595",
    "addr:postcode":"m13 0rx",
    "addr:street":"Stockport Rd",
    "iso:country":"GB",
    "sg:address":"595 Stockport Rd, Longsight",
    "sg:city":"Manchester",
    "sg:classifiers":[
        {
            "category":"Communications",
            "subcategory":"Film & Video Production",
            "type":"Services"
        }
    ],
    "sg:phone":"+44 161 224 4116",
    "sg:postcode":"M13 0RX",
    "sg:province":"Greater Manchester",
    "sg:tags":[
        "tv"
    ],
    "wof:name":"Granada Home Technology",
    "wof:placetype":"venue"
},
  "geometry": {"coordinates":[-2.198407,53.455433],"type":"Point"}
}