{
  "type": "Feature",
  "properties": {
    "addr:full":"Lighthouse Cottage, George Street Cromarty Highland IV11 8YJ",
    "addr:postcode":"iv11 8yj",
    "addr:street":"George Street",
    "iso:country":"GB",
    "sg:address":"Lighthouse Cottage, George Street",
    "sg:city":"Cromarty",
    "sg:classifiers":[
        {
            "category":"Education",
            "subcategory":"University",
            "type":"Public Place"
        }
    ],
    "sg:phone":"+44 1381 600548",
    "sg:postcode":"IV11 8YJ",
    "sg:province":"Highland",
    "sg:tags":[
        "medical",
        "school"
    ],
    "wof:name":"Aberdeen University Lighthouse Field Station",
    "wof:placetype":"venue"
},
  "geometry": {"coordinates":[-4.035289,57.681225],"type":"Point"}
}