{
  "type": "Feature",
  "properties": {
    "iso:country":"GB",
    "sg:address":"Farburn Industrial Estate, Burnside Road, Dyce",
    "sg:city":"Aberdeen",
    "sg:classifiers":[
        {
            "category":"Banks & Credit Unions",
            "subcategory":"Bank",
            "type":"Services"
        }
    ],
    "sg:phone":"+44 1224 723647",
    "sg:postcode":"AB21 0HZ",
    "sg:province":"Aberdeen City",
    "sg:tags":[
        "financial",
        "institution"
    ],
    "wof:name":"The Royal Bank of Scotland Plc",
    "wof:placetype":"venue"
},
  "geometry": {"coordinates":[-2.1823101044,57.1991996765],"type":"Point"}
}