{
  "type": "Feature",
  "properties": {
    "iso:country":"GB",
    "sg:address":"Powis Avenue",
    "sg:city":"Tipton",
    "sg:classifiers":[
        {
            "category":"Education",
            "subcategory":"School",
            "type":"Public Place"
        }
    ],
    "sg:phone":"+44 121 557 8733",
    "sg:postcode":"DY4 0RN",
    "sg:province":"West Midlands",
    "sg:tags":[
        "local",
        "authority"
    ],
    "wof:name":"Sandwell Metropolitan Borough Council",
    "wof:placetype":"venue"
},
  "geometry": {"coordinates":[-2.043394,52.539215],"type":"Point"}
}