{
  "type": "Feature",
  "properties": {
    "addr:full":"44 Witton Street Northwich Cheshire CW9 5AG",
    "addr:housenumber":"44",
    "addr:postcode":"cw9 5ag",
    "addr:street":"Witton Street",
    "iso:country":"GB",
    "sg:address":"44 Witton Street",
    "sg:city":"Northwich",
    "sg:classifiers":[
        {
            "category":"Shopping",
            "subcategory":"Photographic Equipment",
            "type":"Retail Goods"
        }
    ],
    "sg:phone":"+44 1606 41110",
    "sg:postcode":"CW9 5AG",
    "sg:province":"Cheshire",
    "sg:tags":[
        "supply"
    ],
    "wof:name":"Wildings Photo & Video Centre",
    "wof:placetype":"venue"
},
  "geometry": {"coordinates":[-2.509119,53.262249],"type":"Point"}
}