{
  "type": "Feature",
  "properties": {
    "iso:country":"GB",
    "sg:address":"Manea Road, Wimblington",
    "sg:city":"March",
    "sg:classifiers":[
        {
            "category":"Shopping",
            "type":"Retail Goods"
        }
    ],
    "sg:phone":"+44 1354 741177",
    "sg:postcode":"PE15 0PA",
    "sg:province":"Cambridgeshire",
    "sg:tags":[
        "merchant"
    ],
    "wof:name":"Dalgety A A M",
    "wof:placetype":"venue"
},
  "geometry": {"coordinates":[0.109835,52.503517],"type":"Point"}
}