{
  "type": "Feature",
  "properties": {
    "addr:full":"475 Welford Road Leicester Leicestershire LE2 6BL",
    "addr:housenumber":"475",
    "addr:postcode":"le2 6bl",
    "addr:street":"Welford Road",
    "iso:country":"GB",
    "sg:address":"475 Welford Road",
    "sg:city":"Leicester",
    "sg:classifiers":[
        {
            "category":"Cinema",
            "subcategory":"Movie Rental",
            "type":"Entertainment"
        }
    ],
    "sg:phone":"+44 116 270 1197",
    "sg:postcode":"LE2 6BL",
    "sg:province":"Leicestershire",
    "sg:tags":[
        "video",
        "library"
    ],
    "wof:name":"Movie Zone",
    "wof:placetype":"venue"
},
  "geometry": {"coordinates":[-1.123333,52.610596],"type":"Point"}
}