{
  "type": "Feature",
  "properties": {
    "iso:country":"GB",
    "sg:address":"25 Carrick Street",
    "sg:city":"Girvan",
    "sg:classifiers":[
        {
            "category":"Building & Trades",
            "subcategory":"Landscaping Services",
            "type":"Services"
        }
    ],
    "sg:phone":"+44 1465 712824",
    "sg:postcode":"KA26 9EQ",
    "sg:province":"South Ayrshire",
    "sg:tags":[
        "preservation",
        "timber"
    ],
    "wof:name":"Ailsa Preservation",
    "wof:placetype":"venue"
},
  "geometry": {"coordinates":[-4.848261,55.245197],"type":"Point"}
}