{
  "type": "Feature",
  "properties": {
    "iso:country":"GB",
    "sg:address":"5 Windsor Rd",
    "sg:city":"Pontypool",
    "sg:classifiers":[
        {
            "category":"Food & Beverages",
            "subcategory":"Supermarket",
            "type":"Retail Goods"
        }
    ],
    "sg:phone":"+44 1495 763614",
    "sg:postcode":"NP4 5HY",
    "sg:province":"Monmouthshire",
    "wof:name":"CRS Ltd",
    "wof:placetype":"venue"
},
  "geometry": {"coordinates":[-3.02566,51.685963],"type":"Point"}
}