{
  "type": "Feature",
  "properties": {
    "iso:country":"GB",
    "sg:address":"20 Moorland Clo",
    "sg:city":"Penzance",
    "sg:classifiers":[
        {
            "category":"Professional",
            "subcategory":"Employment Agencies",
            "type":"Services"
        }
    ],
    "sg:phone":"+44 1736 788799",
    "sg:postcode":"TR19 7EF",
    "sg:province":"Cornwall",
    "sg:tags":[
        "consultant"
    ],
    "wof:name":"Orangefield Employment Agency",
    "wof:placetype":"venue"
},
  "geometry": {"coordinates":[-5.670053,50.153374],"type":"Point"}
}