{
  "type": "Feature",
  "properties": {
    "addr:full":"17-21 Sunbeam Road London Greater London NW10 6JP",
    "addr:housenumber":"17-21",
    "addr:postcode":"nw10 6jp",
    "addr:street":"Sunbeam Road",
    "iso:country":"GB",
    "sg:address":"17-21 Sunbeam Road",
    "sg:city":"London",
    "sg:classifiers":[
        {
            "category":"Manufacturing",
            "subcategory":"Metals",
            "type":"Manufacturing & Wholesale Goods"
        },
        {
            "category":"Building & Trades",
            "subcategory":"Construction",
            "type":"Services"
        }
    ],
    "sg:phone":"+44 20 8357 1000",
    "sg:postcode":"NW10 6JP",
    "sg:province":"Greater London",
    "sg:tags":[
        "pressworkers",
        "worker"
    ],
    "sg:website":"http://www.sunbeamgroup.com",
    "wof:name":"Sunbeam Metal Works Ltd.",
    "wof:placetype":"venue"
},
  "geometry": {"coordinates":[-0.2624379992,51.5262718201],"type":"Point"}
}