{
  "type": "Feature",
  "properties": {
    "iso:country":"GB",
    "sg:address":"1-3 Chalmers St",
    "sg:city":"Clydebank",
    "sg:classifiers":[
        {
            "category":"Bars & Pubs",
            "type":"Food & Drink"
        }
    ],
    "sg:phone":"+44 141 951 4565",
    "sg:postcode":"G81 1RT",
    "sg:province":"East Dunbartonshire",
    "sg:tags":[
        "pubs",
        "inn"
    ],
    "wof:name":"Lomond (Holdings) Ltd",
    "wof:placetype":"venue"
},
  "geometry": {"coordinates":[-4.405699,55.901588],"type":"Point"}
}