{
  "type": "Feature",
  "properties": {
    "iso:country":"GB",
    "sg:address":"Alfriston Road",
    "sg:city":"Seaford",
    "sg:classifiers":[
        {
            "category":"Government",
            "subcategory":"Post Office",
            "type":"Public Place"
        }
    ],
    "sg:postcode":"BN25 3QD",
    "sg:province":"East Sussex",
    "wof:name":"Alfriston Road Post Office",
    "wof:placetype":"venue"
},
  "geometry": {"coordinates":[0.149049,50.793617],"type":"Point"}
}