{
  "type": "Feature",
  "properties": {
    "addr:full":"Brooklyn Road Woking Surrey GU22 7TP",
    "addr:postcode":"gu22 7tp",
    "addr:street":"Brooklyn Road",
    "iso:country":"GB",
    "sg:address":"Brooklyn Road",
    "sg:city":"Woking",
    "sg:classifiers":[
        {
            "category":"Education",
            "subcategory":"School",
            "type":"Public Place"
        }
    ],
    "sg:phone":"+44 1483 772525",
    "sg:postcode":"GU22 7TP",
    "sg:province":"Surrey",
    "sg:tags":[
        "independent",
        "preparatory"
    ],
    "wof:name":"Greenfield School",
    "wof:placetype":"venue"
},
  "geometry": {"coordinates":[-0.5642390251,51.311958313],"type":"Point"}
}