{
  "type": "Feature",
  "properties": {
    "addr:full":"4 Abbey Wood Road, Kings Hill West Malling Kent ME19 5QQ",
    "addr:housenumber":"4",
    "addr:postcode":"me19 5qq",
    "addr:street":"Abbey Wood Road",
    "iso:country":"GB",
    "sg:address":"4 Abbey Wood Road, Kings Hill",
    "sg:city":"West Malling",
    "sg:classifiers":[
        {
            "category":"Professional",
            "subcategory":"Computer Services",
            "type":"Services"
        }
    ],
    "sg:phone":"+44 1732 220010",
    "sg:postcode":"ME19 5QQ",
    "sg:province":"Kent",
    "sg:tags":[
        "system",
        "software"
    ],
    "wof:name":"Relational Database Technology Ltd.",
    "wof:placetype":"venue"
},
  "geometry": {"coordinates":[0.41294,51.293709],"type":"Point"}
}