{
  "type": "Feature",
  "properties": {
    "iso:country":"GB",
    "sg:address":"39 Anchor Road, Aldridge",
    "sg:city":"Walsall",
    "sg:classifiers":[
        {
            "category":"Banks & Credit Unions",
            "subcategory":"Financial Services",
            "type":"Services"
        }
    ],
    "sg:phone":"+44 1922 745540",
    "sg:postcode":"WS9 8PT",
    "sg:province":"Staffordshire",
    "sg:tags":[
        "adviser",
        "pension",
        "consultant"
    ],
    "wof:name":"Regency Financial Management Ltd.",
    "wof:placetype":"venue"
},
  "geometry": {"coordinates":[-1.919186,52.603592],"type":"Point"}
}