{
  "type": "Feature",
  "properties": {
    "addr:full":"Roman Ho, 9 Roman Sq Sittingbourne Kent ME10 4BP",
    "addr:housenumber":"9",
    "addr:postcode":"me10 4bp",
    "addr:street":"Roman Sq",
    "iso:country":"GB",
    "sg:address":"Roman Ho, 9 Roman Sq",
    "sg:city":"Sittingbourne",
    "sg:classifiers":[
        {
            "category":"Social Services",
            "type":"Services"
        }
    ],
    "sg:phone":"+44 1795 562500",
    "sg:postcode":"ME10 4BP",
    "sg:province":"Kent",
    "sg:tags":[
        "benefit",
        "agency"
    ],
    "wof:name":"Benefits Agency",
    "wof:placetype":"venue"
},
  "geometry": {"coordinates":[0.73791,51.34082],"type":"Point"}
}