{
  "type": "Feature",
  "properties": {
    "addr:full":"15a South Methven Street Perth Perth and Kinross PH1 5PE",
    "addr:housenumber":"15a",
    "addr:postcode":"ph1 5pe",
    "addr:street":"South Methven Street",
    "iso:country":"GB",
    "sg:address":"15a South Methven Street",
    "sg:city":"Perth",
    "sg:classifiers":[
        {
            "category":"Home & Garden",
            "subcategory":"Household Appliances",
            "type":"Retail Goods"
        }
    ],
    "sg:phone":"+44 1738 442881",
    "sg:postcode":"PH1 5PE",
    "sg:province":"Perth and Kinross",
    "sg:tags":[
        "domestic",
        "centre"
    ],
    "wof:name":"Fraser Bros",
    "wof:placetype":"venue"
},
  "geometry": {"coordinates":[-3.434769,56.397156],"type":"Point"}
}