{
  "type": "Feature",
  "properties": {
    "addr:full":"Victoria Building, King Street Wigan Lancashire WN1 1BS",
    "addr:postcode":"wn1 1bs",
    "addr:street":"King Street",
    "iso:country":"GB",
    "sg:address":"Victoria Building, King Street",
    "sg:city":"Wigan",
    "sg:classifiers":[
        {
            "category":"Military Area",
            "subcategory":"Air Force Base",
            "type":"Public Place"
        }
    ],
    "sg:postcode":"WN1 1BS",
    "sg:province":"Lancashire",
    "sg:tags":[
        "sanitary"
    ],
    "wof:name":"Rubber Plantation",
    "wof:placetype":"venue"
},
  "geometry": {"coordinates":[-2.6335320473,53.5441551208],"type":"Point"}
}