{
  "type": "Feature",
  "properties": {
    "iso:country":"GB",
    "sg:address":"3 Perrycroft",
    "sg:city":"Windsor",
    "sg:classifiers":[
        {
            "category":"Home & Garden",
            "subcategory":"Carpets & Floor Coverings",
            "type":"Retail Goods"
        }
    ],
    "sg:phone":"+44 1753 867854",
    "sg:postcode":"SL4 4HA",
    "sg:province":"Berkshire",
    "sg:tags":[
        "cleaner",
        "upholstery"
    ],
    "wof:name":"X-Trac Carpet Cleaning Service",
    "wof:placetype":"venue"
},
  "geometry": {"coordinates":[-0.635064,51.472431],"type":"Point"}
}