{
  "type": "Feature",
  "properties": {
    "addr:full":"2 Aberdour Road Dunfermline Fife KY11 4PD",
    "addr:housenumber":"2",
    "addr:postcode":"ky11 4pd",
    "addr:street":"Aberdour Road",
    "iso:country":"GB",
    "sg:address":"2 Aberdour Road",
    "sg:city":"Dunfermline",
    "sg:classifiers":[
        {
            "category":"Professional",
            "subcategory":"Engineering",
            "type":"Services"
        },
        {
            "category":"Building & Trades",
            "subcategory":"Electrical",
            "type":"Services"
        }
    ],
    "sg:phone":"+44 1383 727766",
    "sg:postcode":"KY11 4PD",
    "sg:province":"Fife",
    "sg:tags":[
        "engineer",
        "electrician",
        "contractor"
    ],
    "wof:name":"Brian J Duffy",
    "wof:placetype":"venue"
},
  "geometry": {"coordinates":[-3.431231,56.061661],"type":"Point"}
}