{
  "type": "Feature",
  "properties": {
    "addr:full":"13 Sinclair Pla, Worsley Hall Wigan Lancashire WN5 9SP",
    "addr:housenumber":"13",
    "addr:postcode":"wn5 9sp",
    "addr:street":"Sinclair Pla Worsley Hall",
    "iso:country":"GB",
    "sg:address":"13 Sinclair Pla, Worsley Hall",
    "sg:city":"Wigan",
    "sg:classifiers":[
        {
            "category":"Building & Trades",
            "subcategory":"Landscaping Services",
            "type":"Services"
        }
    ],
    "sg:postcode":"WN5 9SP",
    "sg:province":"Lancashire",
    "sg:tags":[
        "landscape",
        "contractor"
    ],
    "wof:name":"Cashin Landscapes",
    "wof:placetype":"venue"
},
  "geometry": {"coordinates":[-2.664066,53.545986],"type":"Point"}
}