{
  "type": "Feature",
  "properties": {
    "iso:country":"GB",
    "sg:address":"23 Calvados Road",
    "sg:city":"Taunton",
    "sg:classifiers":[
        {
            "category":"Building & Trades",
            "subcategory":"Construction",
            "type":"Services"
        }
    ],
    "sg:phone":"+44 1823 338250",
    "sg:postcode":"TA1 2LA",
    "sg:province":"Somerset",
    "sg:tags":[
        "builder"
    ],
    "wof:name":"Dorwin Developments",
    "wof:placetype":"venue"
},
  "geometry": {"coordinates":[-3.079067,51.01305],"type":"Point"}
}