{
  "type": "Feature",
  "properties": {
    "iso:country":"GB",
    "sg:address":"149 Hastings Road, Bromley Common",
    "sg:city":"Bromley",
    "sg:classifiers":[
        {
            "category":"Restaurant",
            "type":"Food & Drink"
        }
    ],
    "sg:phone":"+44 20 8462 7147",
    "sg:postcode":"BR2 8NQ",
    "sg:province":"Kent",
    "sg:tags":[
        "indian"
    ],
    "wof:name":"Yasmin Tandoori",
    "wof:placetype":"venue"
},
  "geometry": {"coordinates":[0.045237001,51.3743286133],"type":"Point"}
}