{
  "type": "Feature",
  "properties": {
    "addr:full":"18-22 Queen St Leicester Leicestershire LE1 1QR",
    "addr:housenumber":"18-22",
    "addr:postcode":"le1 1qr",
    "addr:street":"Queen St",
    "iso:country":"GB",
    "sg:address":"18-22 Queen St",
    "sg:city":"Leicester",
    "sg:classifiers":[
        {
            "category":"Shopping",
            "subcategory":"Computers & Home Electronics",
            "type":"Retail Goods"
        }
    ],
    "sg:phone":"+44 116 262 2588",
    "sg:postcode":"LE1 1QR",
    "sg:province":"Leicestershire",
    "sg:tags":[
        "electrical"
    ],
    "wof:name":"Senate E M S Ltd",
    "wof:placetype":"venue"
},
  "geometry": {"coordinates":[-1.124539,52.634937],"type":"Point"}
}