{
  "type": "Feature",
  "properties": {
    "addr:full":"Unit C9 Moor Lane Business Centre, Moor Lane Widnes Cheshire WA8 7AQ",
    "addr:postcode":"wa8 7aq",
    "addr:street":"Moor Lane;Moor Lane",
    "iso:country":"GB",
    "sg:address":"Unit C9 Moor Lane Business Centre, Moor Lane",
    "sg:city":"Widnes",
    "sg:classifiers":[
        {
            "category":"Building & Trades",
            "subcategory":"Cleaning & Sanitation",
            "type":"Services"
        }
    ],
    "sg:phone":"+44 151 423 4828",
    "sg:postcode":"WA8 7AQ",
    "sg:province":"Cheshire",
    "sg:tags":[
        "commercial"
    ],
    "wof:name":"Kestrel Cleaning Services",
    "wof:placetype":"venue"
},
  "geometry": {"coordinates":[-2.7408440113,53.3619003296],"type":"Point"}
}