{
  "type": "Feature",
  "properties": {
    "iso:country":"GB",
    "sg:address":"Firwood, Braggs Lane",
    "sg:city":"Herne Bay",
    "sg:classifiers":[
        {
            "category":"Building & Trades",
            "subcategory":"Landscaping Services",
            "type":"Services"
        }
    ],
    "sg:phone":"+44 1227 361153",
    "sg:postcode":"CT6 7NP",
    "sg:province":"Kent",
    "sg:tags":[
        "forestry",
        "surgeon",
        "tree"
    ],
    "wof:name":"D Parr Tree Surgeons & Gardening Contractors",
    "wof:placetype":"venue"
},
  "geometry": {"coordinates":[1.1251,51.371216],"type":"Point"}
}