{
  "type": "Feature",
  "properties": {
    "addr:full":"5 Kerry Close Lymington Hampshire SO41 8HW",
    "addr:housenumber":"5",
    "addr:postcode":"so41 8hw",
    "addr:street":"Kerry Close",
    "iso:country":"GB",
    "sg:address":"5 Kerry Close",
    "sg:city":"Lymington",
    "sg:classifiers":[
        {
            "category":"Shopping",
            "subcategory":"Crafts & Fabrics",
            "type":"Retail Goods"
        }
    ],
    "sg:phone":"+44 1590 679026",
    "sg:postcode":"SO41 8HW",
    "sg:province":"Hampshire",
    "sg:tags":[
        "ceramic"
    ],
    "wof:name":"H & H Ceramics",
    "wof:placetype":"venue"
},
  "geometry": {"coordinates":[-1.560668,50.75499],"type":"Point"}
}