{
  "type": "Feature",
  "properties": {
    "iso:country":"GB",
    "sg:address":"Civic Offices, Harlington Way",
    "sg:city":"Fleet",
    "sg:classifiers":[
        {
            "category":"Government",
            "subcategory":"Office",
            "type":"Public Place"
        }
    ],
    "sg:phone":"+44 1252 811470",
    "sg:postcode":"GU51 4AE",
    "sg:province":"Hampshire",
    "sg:tags":[
        "chamber",
        "commerce"
    ],
    "sg:website":"http://www.nhcci.co.uk",
    "wof:name":"North Hampshire Chamber Of Commerce & Industry",
    "wof:placetype":"venue"
},
  "geometry": {"coordinates":[-0.84603,51.27956],"type":"Point"}
}