{
  "type": "Feature",
  "properties": {
    "iso:country":"GB",
    "sg:address":"2 Reis Street, Off Fairmile Road",
    "sg:city":"Christchurch",
    "sg:classifiers":[
        {
            "category":"Home & Garden",
            "subcategory":"Home Furnishings",
            "type":"Retail Goods"
        }
    ],
    "sg:phone":"+44 1202 473631",
    "sg:postcode":"BH23 2BT",
    "sg:province":"Dorset",
    "sg:tags":[
        "merchant",
        "diy",
        "decorators'"
    ],
    "wof:name":"Crown Berger Decorator Centre",
    "wof:placetype":"venue"
},
  "geometry": {"coordinates":[-1.776564002,50.7340698242],"type":"Point"}
}