{
  "type": "Feature",
  "properties": {
    "addr:full":"80 Longridge Rd Preston Lancashire PR2 6RJ",
    "addr:housenumber":"80",
    "addr:postcode":"pr2 6rj",
    "addr:street":"Longridge Rd",
    "iso:country":"GB",
    "sg:address":"80 Longridge Rd",
    "sg:city":"Preston",
    "sg:classifiers":[
        {
            "category":"Bars & Pubs",
            "type":"Food & Drink"
        }
    ],
    "sg:phone":"+44 1772 792431",
    "sg:postcode":"PR2 6RJ",
    "sg:province":"Lancashire",
    "sg:tags":[
        "pubs",
        "inn"
    ],
    "wof:name":"Gamull The",
    "wof:placetype":"venue"
},
  "geometry": {"coordinates":[-2.6569969654,53.7818260193],"type":"Point"}
}