{
  "type": "Feature",
  "properties": {
    "addr:full":"Unit 2, Water Lane Halifax West Yorkshire HX3 9HG",
    "addr:housenumber":"unit 2",
    "addr:postcode":"hx3 9hg",
    "addr:street":"Water Lane",
    "iso:country":"GB",
    "sg:address":"Unit 2, Water Lane",
    "sg:city":"Halifax",
    "sg:classifiers":[
        {
            "category":"Professional",
            "subcategory":"Engineering",
            "type":"Services"
        }
    ],
    "sg:phone":"+44 1422 347518",
    "sg:postcode":"HX3 9HG",
    "sg:province":"West Yorkshire",
    "wof:name":"Kabel Ltd",
    "wof:placetype":"venue"
},
  "geometry": {"coordinates":[-1.855568,53.717236],"type":"Point"}
}