{
  "type": "Feature",
  "properties": {
    "iso:country":"GB",
    "sg:address":"31-33 Bondgate Withn",
    "sg:city":"Alnwick",
    "sg:classifiers":[
        {
            "category":"Banks & Credit Unions",
            "subcategory":"Bank",
            "type":"Services"
        }
    ],
    "sg:phone":"+44 1665 510418",
    "sg:postcode":"NE66 1SX",
    "sg:province":"Northumberland",
    "wof:name":"Lloyds Tsb Bank Plc",
    "wof:placetype":"venue"
},
  "geometry": {"coordinates":[-1.704865,55.412952],"type":"Point"}
}