{
  "type": "Feature",
  "properties": {
    "iso:country":"GB",
    "sg:address":"85 High Street",
    "sg:city":"Esher",
    "sg:classifiers":[
        {
            "category":"Shopping",
            "subcategory":"Musical Instruments",
            "type":"Retail Goods"
        }
    ],
    "sg:phone":"+44 1372 466195",
    "sg:postcode":"KT10 9QA",
    "sg:province":"Surrey",
    "sg:tags":[
        "music",
        "sheet"
    ],
    "wof:name":"A B C Music Ltd.",
    "wof:placetype":"venue"
},
  "geometry": {"coordinates":[-0.366144,51.368664],"type":"Point"}
}