{
  "type": "Feature",
  "properties": {
    "addr:full":"2-4 Chippingham Place, Chippingham St Sheffield South Yorkshire S9 3SA",
    "addr:housenumber":"2-4",
    "addr:postcode":"s9 3sa",
    "addr:street":"Chippingham Place Chippingham St",
    "iso:country":"GB",
    "sg:address":"2-4 Chippingham Place, Chippingham St",
    "sg:city":"Sheffield",
    "sg:classifiers":[
        {
            "category":"Shopping",
            "type":"Retail Goods"
        }
    ],
    "sg:phone":"+44 114 243 1313",
    "sg:postcode":"S9 3SA",
    "sg:province":"South Yorkshire",
    "sg:tags":[
        "part",
        "accessory"
    ],
    "wof:name":"J.R.S Motor Factors",
    "wof:placetype":"venue"
},
  "geometry": {"coordinates":[-1.433128,53.392696],"type":"Point"}
}