{
  "type": "Feature",
  "properties": {
    "iso:country":"GB",
    "sg:address":"75 Holmes House Avenue",
    "sg:city":"Wigan",
    "sg:classifiers":[
        {
            "category":"Personal",
            "type":"Services"
        }
    ],
    "sg:phone":"+44 1942 212550",
    "sg:postcode":"WN3 6JA",
    "sg:province":"Lancashire",
    "sg:tags":[
        "wedding"
    ],
    "wof:name":"Inspirations",
    "wof:placetype":"venue"
},
  "geometry": {"coordinates":[-2.669666,53.522099],"type":"Point"}
}