{
  "type": "Feature",
  "properties": {
    "iso:country":"GB",
    "sg:address":"Sandy Lane, Preesall",
    "sg:city":"Poulton-le-fylde",
    "sg:classifiers":[
        {
            "category":"Park",
            "subcategory":"Provincial",
            "type":"Public Place"
        },
        {
            "category":"Recreation",
            "subcategory":"Campground",
            "type":"Entertainment"
        }
    ],
    "sg:phone":"+44 1253 811306",
    "sg:postcode":"FY6 0EJ",
    "sg:province":"Lancashire",
    "sg:tags":[
        "holiday",
        "camp",
        "centre"
    ],
    "wof:name":"Willowgrove Caravan Park",
    "wof:placetype":"venue"
},
  "geometry": {"coordinates":[-2.9748589993,53.9260940552],"type":"Point"}
}