{
  "type": "Feature",
  "properties": {
    "addr:full":"Unit 13 Waterloo Park Industrial Estate, Bidford On Avon Alcester Warwickshire B50 4JN",
    "addr:housenumber":"unit 13",
    "addr:postcode":"b50 4jn",
    "addr:street":"Waterloo Park Industrial",
    "iso:country":"GB",
    "sg:address":"Unit 13 Waterloo Park Industrial Estate, Bidford On Avon",
    "sg:city":"Alcester",
    "sg:classifiers":[
        {
            "category":"Retail",
            "subcategory":"Auto Repair",
            "type":"Services"
        }
    ],
    "sg:phone":"+44 1789 490559",
    "sg:postcode":"B50 4JN",
    "sg:province":"Warwickshire",
    "sg:tags":[
        "body",
        "car"
    ],
    "wof:name":"A S Lotta",
    "wof:placetype":"venue"
},
  "geometry": {"coordinates":[-1.8515739441,52.1728553772],"type":"Point"}
}