{
  "type": "Feature",
  "properties": {
    "addr:full":"Pound La Norwich Norfolk NR7 0SR",
    "addr:postcode":"nr7 0sr",
    "iso:country":"GB",
    "sg:address":"Pound La",
    "sg:city":"Norwich",
    "sg:classifiers":[
        {
            "category":"Shopping",
            "subcategory":"Pharmacy",
            "type":"Retail Goods"
        }
    ],
    "sg:phone":"+44 1603 701307",
    "sg:postcode":"NR7 0SR",
    "sg:province":"Norfolk",
    "sg:tags":[
        "pharmacist",
        "chemist"
    ],
    "wof:name":"Sainsbury Pharmacy",
    "wof:placetype":"venue"
},
  "geometry": {"coordinates":[1.3590370417,52.6340637207],"type":"Point"}
}