{
  "type": "Feature",
  "properties": {
    "addr:full":"Hallam Mills Stockport Cheshire SK2 6PT",
    "addr:postcode":"sk2 6pt",
    "addr:street":"Stockport",
    "iso:country":"GB",
    "sg:address":"Hallam Mills",
    "sg:city":"Stockport",
    "sg:classifiers":[
        {
            "category":"Shopping",
            "subcategory":"Clothing, Apparel, & Fashions",
            "type":"Retail Goods"
        }
    ],
    "sg:postcode":"SK2 6PT",
    "sg:province":"Cheshire",
    "sg:tags":[
        "clothing",
        "fabric"
    ],
    "wof:name":"Mandy Marsh Fashions Ltd.",
    "wof:placetype":"venue"
},
  "geometry": {"coordinates":[-2.1515541077,53.395401001],"type":"Point"}
}