{
  "type": "Feature",
  "properties": {
    "addr:full":"2 Glentress Gardens Glenrothes Fife KY7 6XY",
    "addr:housenumber":"2",
    "addr:postcode":"ky7 6xy",
    "addr:street":"Glentress Gardens",
    "iso:country":"GB",
    "sg:address":"2 Glentress Gardens",
    "sg:city":"Glenrothes",
    "sg:classifiers":[
        {
            "category":"Manufacturing",
            "subcategory":"Wood Products",
            "type":"Manufacturing & Wholesale Goods"
        }
    ],
    "sg:phone":"+44 1592 743858",
    "sg:postcode":"KY7 6XY",
    "sg:province":"Fife",
    "sg:tags":[
        "maker",
        "cabinet"
    ],
    "wof:name":"Paul Diver Installation",
    "wof:placetype":"venue"
},
  "geometry": {"coordinates":[-3.1560549736,56.2157592773],"type":"Point"}
}