{
  "type": "Feature",
  "properties": {
    "iso:country":"GB",
    "sg:address":"25 St Thomas Street",
    "sg:city":"Scarborough",
    "sg:classifiers":[
        {
            "category":"Shopping",
            "subcategory":"Florist",
            "type":"Retail Goods"
        }
    ],
    "sg:phone":"+44 1723 500256",
    "sg:postcode":"YO11 1DY",
    "sg:province":"North Yorkshire",
    "wof:name":"April",
    "wof:placetype":"venue"
},
  "geometry": {"coordinates":[-0.399716,54.28363],"type":"Point"}
}