{
  "type": "Feature",
  "properties": {
    "addr:full":"Nathan Grn, Bashall Eaves Clitheroe Lancashire BB7 3DA",
    "addr:postcode":"bb7 3da",
    "addr:street":"Nathan Grn;Eaves",
    "iso:country":"GB",
    "sg:address":"Nathan Grn, Bashall Eaves",
    "sg:city":"Clitheroe",
    "sg:classifiers":[
        {
            "category":"Farming",
            "subcategory":"Livestock Farm",
            "type":"Manufacturing & Wholesale Goods"
        }
    ],
    "sg:postcode":"BB7 3DA",
    "sg:province":"Lancashire",
    "sg:tags":[
        "others"
    ],
    "wof:name":"J F Spurgeon & Son",
    "wof:placetype":"venue"
},
  "geometry": {"coordinates":[-2.4640040398,53.8850440979],"type":"Point"}
}