{
  "type": "Feature",
  "properties": {
    "addr:full":"1a Collinson Ave Scunthorpe Lincolnshire DN15 8AA",
    "addr:housenumber":"1a",
    "addr:postcode":"dn15 8aa",
    "addr:street":"Collinson Ave",
    "iso:country":"GB",
    "sg:address":"1a Collinson Ave",
    "sg:city":"Scunthorpe",
    "sg:classifiers":[
        {
            "category":"Manufacturing",
            "subcategory":"Lumber",
            "type":"Manufacturing & Wholesale Goods"
        }
    ],
    "sg:phone":"+44 1724 276033",
    "sg:postcode":"DN15 8AA",
    "sg:province":"Lincolnshire",
    "sg:tags":[
        "importer",
        "merchants",
        "agent",
        "timber"
    ],
    "wof:name":"Sanderson,D G,",
    "wof:placetype":"venue"
},
  "geometry": {"coordinates":[-0.678879,53.590839],"type":"Point"}
}