{
  "type": "Feature",
  "properties": {
    "addr:full":"90 Fistral Cres Stalybridge Greater Manchester SK15 3HW",
    "addr:housenumber":"90",
    "addr:postcode":"sk15 3hw",
    "addr:street":"Fistral Cres",
    "iso:country":"GB",
    "sg:address":"90 Fistral Cres",
    "sg:city":"Stalybridge",
    "sg:classifiers":[
        {
            "category":"Professional",
            "subcategory":"Computer Services",
            "type":"Services"
        }
    ],
    "sg:phone":"+44 161 304 8511",
    "sg:postcode":"SK15 3HW",
    "sg:province":"Greater Manchester",
    "sg:tags":[
        "system",
        "software"
    ],
    "wof:name":"A M P Systems",
    "wof:placetype":"venue"
},
  "geometry": {"coordinates":[-2.0345420837,53.4912147522],"type":"Point"}
}