{
  "type": "Feature",
  "properties": {
    "addr:full":"Marwick Road March Cambridgeshire PE15 8PW",
    "addr:postcode":"pe15 8pw",
    "addr:street":"Marwick Road",
    "iso:country":"GB",
    "sg:address":"Marwick Road",
    "sg:city":"March",
    "sg:classifiers":[
        {
            "category":"Retail",
            "subcategory":"Storage",
            "type":"Services"
        }
    ],
    "sg:phone":"+44 1354 652555",
    "sg:postcode":"PE15 8PW",
    "sg:province":"Cambridgeshire",
    "sg:tags":[
        "cold"
    ],
    "wof:name":"March Cold Stores Ltd.",
    "wof:placetype":"venue"
},
  "geometry": {"coordinates":[0.091465,52.565639],"type":"Point"}
}