{
  "type": "Feature",
  "properties": {
    "addr:full":"Landmark Ho, Station Rd, Cheadle Hulme Cheadle Cheshire SK8 7BS",
    "addr:postcode":"sk8 7bs",
    "addr:street":"Station Rd",
    "iso:country":"GB",
    "sg:address":"Landmark Ho, Station Rd, Cheadle Hulme",
    "sg:city":"Cheadle",
    "sg:classifiers":[
        {
            "category":"Banks & Credit Unions",
            "subcategory":"Financial Services",
            "type":"Services"
        }
    ],
    "sg:postcode":"SK8 7BS",
    "sg:province":"Cheshire",
    "sg:tags":[
        "adviser"
    ],
    "wof:name":"Vital Financial Services Ltd",
    "wof:placetype":"venue"
},
  "geometry": {"coordinates":[-2.1868700981,53.3749809265],"type":"Point"}
}