{
  "type": "Feature",
  "properties": {
    "addr:full":"11 Telford Road, Ferndown Industrial Estate Wimborne Dorset BH21 7QP",
    "addr:housenumber":"11;estate",
    "addr:postcode":"bh21 7qp",
    "addr:street":"Telford Road;Industrial",
    "iso:country":"GB",
    "sg:address":"11 Telford Road, Ferndown Industrial Estate",
    "sg:city":"Wimborne",
    "sg:classifiers":[
        {
            "category":"Education",
            "subcategory":"Special Training",
            "type":"Public Place"
        },
        {
            "category":"Sports & Exercise",
            "subcategory":"Swimming Pool",
            "type":"Entertainment"
        }
    ],
    "sg:phone":"+44 1202 632211",
    "sg:postcode":"BH21 7QP",
    "sg:province":"Dorset",
    "sg:tags":[
        "diving",
        "school",
        "diver"
    ],
    "wof:name":"I A N T D Merchandise Ltd.",
    "wof:placetype":"venue"
},
  "geometry": {"coordinates":[-1.915755,50.81382],"type":"Point"}
}