{
  "type": "Feature",
  "properties": {
    "addr:full":"34 Midhurst Rd Eastbourne East Sussex BN22 9HW",
    "addr:housenumber":"34",
    "addr:postcode":"bn22 9hw",
    "addr:street":"Midhurst Rd",
    "iso:country":"GB",
    "sg:address":"34 Midhurst Rd",
    "sg:city":"Eastbourne",
    "sg:classifiers":[
        {
            "category":"Professional",
            "subcategory":"Engineering",
            "type":"Services"
        }
    ],
    "sg:phone":"+44 1323 505201",
    "sg:postcode":"BN22 9HW",
    "sg:province":"East Sussex",
    "sg:tags":[
        "contractor",
        "electrical",
        "engineer"
    ],
    "wof:name":"B Hollobone",
    "wof:placetype":"venue"
},
  "geometry": {"coordinates":[0.2834930122,50.8031349182],"type":"Point"}
}