{
  "type": "Feature",
  "properties": {
    "addr:full":"262 Southway Guildford Surrey GU2 8DY",
    "addr:housenumber":"262",
    "addr:postcode":"gu2 8dy",
    "addr:street":"Southway",
    "iso:country":"GB",
    "sg:address":"262 Southway",
    "sg:city":"Guildford",
    "sg:classifiers":[
        {
            "category":"Shopping",
            "subcategory":"News",
            "type":"Retail Goods"
        }
    ],
    "sg:phone":"+44 1483 563269",
    "sg:postcode":"GU2 8DY",
    "sg:province":"Surrey",
    "sg:tags":[
        "newsagent"
    ],
    "wof:name":"Forbuoys",
    "wof:placetype":"venue"
},
  "geometry": {"coordinates":[-0.611931,51.243523],"type":"Point"}
}