{
  "type": "Feature",
  "properties": {
    "iso:country":"GB",
    "sg:address":"45 Links View",
    "sg:city":"Rochdale",
    "sg:classifiers":[
        {
            "category":"Building & Trades",
            "subcategory":"Plumbing",
            "type":"Services"
        }
    ],
    "sg:phone":"+44 1706 650256",
    "sg:postcode":"OL11 4DD",
    "sg:province":"Lancashire",
    "sg:tags":[
        "plumber",
        "central",
        "heating"
    ],
    "wof:name":"Emersons",
    "wof:placetype":"venue"
},
  "geometry": {"coordinates":[-2.184328,53.61068],"type":"Point"}
}