{
  "type": "Feature",
  "properties": {
    "addr:full":"2 Walkley Lane Sheffield South Yorkshire S6 2NY",
    "addr:housenumber":"2",
    "addr:postcode":"s6 2ny",
    "addr:street":"Walkley Lane",
    "iso:country":"GB",
    "sg:address":"2 Walkley Lane",
    "sg:city":"Sheffield",
    "sg:classifiers":[
        {
            "category":"Professional",
            "subcategory":"Engineering",
            "type":"Services"
        }
    ],
    "sg:phone":"+44 114 281 2212",
    "sg:postcode":"S6 2NY",
    "sg:province":"South Yorkshire",
    "sg:tags":[
        "contractor",
        "electrical",
        "engineer"
    ],
    "wof:name":"Walker Miller & Co. Ltd.",
    "wof:placetype":"venue"
},
  "geometry": {"coordinates":[-1.499591,53.395943],"type":"Point"}
}