{
  "type": "Feature",
  "properties": {
    "iso:country":"GB",
    "sg:address":"2 Derby Road",
    "sg:city":"Burton-on-trent",
    "sg:classifiers":[
        {
            "category":"Retail",
            "subcategory":"Auto Repair",
            "type":"Services"
        }
    ],
    "sg:phone":"+44 1283 533670",
    "sg:postcode":"DE14 1RU",
    "sg:province":"Derbyshire",
    "sg:tags":[
        "modification",
        "garage"
    ],
    "wof:name":"J B Motors",
    "wof:placetype":"venue"
},
  "geometry": {"coordinates":[-1.635139,52.814121],"type":"Point"}
}