{
  "type": "Feature",
  "properties": {
    "addr:full":"1 Farm Close, Purley On Thames Reading Berkshire RG8 8BA",
    "addr:housenumber":"1",
    "addr:postcode":"rg8 8ba",
    "addr:street":"Farm Close",
    "iso:country":"GB",
    "sg:address":"1 Farm Close, Purley On Thames",
    "sg:city":"Reading",
    "sg:classifiers":[
        {
            "category":"Professional",
            "subcategory":"Engineering",
            "type":"Services"
        }
    ],
    "sg:phone":"+44 118 961 5959",
    "sg:postcode":"RG8 8BA",
    "sg:province":"Berkshire",
    "sg:tags":[
        "contractor",
        "electrical",
        "engineer"
    ],
    "wof:name":"Electrickery",
    "wof:placetype":"venue"
},
  "geometry": {"coordinates":[-1.046466,51.481472],"type":"Point"}
}