{
  "type": "Feature",
  "properties": {
    "iso:country":"GB",
    "sg:address":"67a Oakfield",
    "sg:city":"Newton Aycliffe",
    "sg:classifiers":[
        {
            "category":"Food & Beverages",
            "subcategory":"Groceries & Convenience Stores",
            "type":"Retail Goods"
        }
    ],
    "sg:phone":"+44 1325 313073",
    "sg:postcode":"DL5 7AT",
    "sg:province":"Durham",
    "wof:name":"BELLS STORES LTD",
    "wof:placetype":"venue"
},
  "geometry": {"coordinates":[-1.585663,54.616657],"type":"Point"}
}