{
  "type": "Feature",
  "properties": {
    "iso:country":"GB",
    "sg:address":"Russett House Farm, Lambswood Hill Rd, Grazeley",
    "sg:city":"Reading",
    "sg:classifiers":[
        {
            "category":"Retail",
            "subcategory":"Auto Repair",
            "type":"Services"
        }
    ],
    "sg:phone":"+44 118 988 4911",
    "sg:postcode":"RG7 1JN",
    "sg:province":"Berkshire",
    "sg:tags":[
        "modification",
        "garage"
    ],
    "wof:name":"Maltins Specialist Cars",
    "wof:placetype":"venue"
},
  "geometry": {"coordinates":[-0.997969,51.394764],"type":"Point"}
}