{
  "type": "Feature",
  "properties": {
    "addr:full":"226 Homerton High Street London Greater London E9 6AS",
    "addr:housenumber":"226",
    "addr:postcode":"e9 6as",
    "addr:street":"Homerton High Street",
    "iso:country":"GB",
    "sg:address":"226 Homerton High Street",
    "sg:city":"London",
    "sg:classifiers":[
        {
            "category":"Government",
            "subcategory":"Post Office",
            "type":"Public Place"
        }
    ],
    "sg:phone":"+44 20 8985 3020",
    "sg:postcode":"E9 6AS",
    "sg:province":"Greater London",
    "wof:name":"Homerton High Street Post Office",
    "wof:placetype":"venue"
},
  "geometry": {"coordinates":[-0.040465001,51.5486221313],"type":"Point"}
}