{
  "type": "Feature",
  "properties": {
    "addr:full":"Towyn Crossroads Abergele Conwy LL22 9HD",
    "addr:postcode":"ll22 9hd",
    "addr:street":"Crossroads",
    "iso:country":"GB",
    "sg:address":"Towyn Crossroads",
    "sg:city":"Abergele",
    "sg:classifiers":[
        {
            "category":"Fast Food",
            "type":"Food & Drink"
        }
    ],
    "sg:phone":"+44 1745 351290",
    "sg:postcode":"LL22 9HD",
    "sg:province":"Conwy",
    "sg:tags":[
        "away",
        "take"
    ],
    "wof:name":"The Pizza Box",
    "wof:placetype":"venue"
},
  "geometry": {"coordinates":[-3.541184,53.301846],"type":"Point"}
}