{
  "type": "Feature",
  "properties": {
    "addr:full":"Milburn Road Inverness Highland IV2 3PY",
    "addr:postcode":"iv2 3py",
    "addr:street":"Milburn Road",
    "iso:country":"GB",
    "sg:address":"Milburn Road",
    "sg:city":"Inverness",
    "sg:classifiers":[
        {
            "category":"Retail",
            "subcategory":"Veterinary Services",
            "type":"Services"
        }
    ],
    "sg:phone":"+44 1463 230893",
    "sg:postcode":"IV2 3PY",
    "sg:province":"Highland",
    "sg:tags":[
        "surgeon"
    ],
    "wof:name":"Edmund Jolley",
    "wof:placetype":"venue"
},
  "geometry": {"coordinates":[-4.206029,57.482487],"type":"Point"}
}