{
  "type": "Feature",
  "properties": {
    "addr:full":"11 Roseburn Street Edinburgh City of Edinburgh EH12 5PW",
    "addr:housenumber":"11",
    "addr:postcode":"eh12 5pw",
    "addr:street":"Roseburn Street",
    "iso:country":"GB",
    "sg:address":"11 Roseburn Street",
    "sg:city":"Edinburgh",
    "sg:classifiers":[
        {
            "category":"Organizations",
            "subcategory":"Community Association",
            "type":"Services"
        },
        {
            "category":"Organizations",
            "subcategory":"Membership Organization",
            "type":"Services"
        }
    ],
    "sg:phone":"+44 131 337 3081",
    "sg:postcode":"EH12 5PW",
    "sg:province":"City of Edinburgh",
    "sg:tags":[
        "club",
        "social"
    ],
    "wof:name":"Beechwood Bowling Club",
    "wof:placetype":"venue"
},
  "geometry": {"coordinates":[-3.2346599102,55.9442825317],"type":"Point"}
}