{
  "type": "Feature",
  "properties": {
    "addr:full":"Woodside Avenue London Greater London N10 3JA",
    "addr:postcode":"n10 3ja",
    "addr:street":"Woodside Avenue",
    "iso:country":"GB",
    "sg:address":"Woodside Avenue",
    "sg:city":"London",
    "sg:classifiers":[
        {
            "category":"Education",
            "subcategory":"School",
            "type":"Public Place"
        }
    ],
    "sg:phone":"+44 20 8883 6540",
    "sg:postcode":"N10 3JA",
    "sg:province":"Greater London",
    "sg:tags":[
        "local",
        "authority"
    ],
    "wof:name":"St. James' Primary School",
    "wof:placetype":"venue"
},
  "geometry": {"coordinates":[-0.152918,51.586273],"type":"Point"}
}