{
  "type": "Feature",
  "properties": {
    "addr:full":"51 & 52 George Street Hove East Sussex BN3 3YB",
    "addr:housenumber":"51 & 52",
    "addr:postcode":"bn3 3yb",
    "addr:street":"George Street",
    "iso:country":"GB",
    "sg:address":"51 & 52 George Street",
    "sg:city":"Hove",
    "sg:classifiers":[
        {
            "category":"Shopping",
            "subcategory":"Books",
            "type":"Retail Goods"
        }
    ],
    "sg:phone":"+44 1273 329241",
    "sg:postcode":"BN3 3YB",
    "sg:province":"East Sussex",
    "sg:tags":[
        "bookseller"
    ],
    "wof:name":"Sussex Stationers",
    "wof:placetype":"venue"
},
  "geometry": {"coordinates":[-0.1727730036,50.8306808472],"type":"Point"}
}