{
  "type": "Feature",
  "properties": {
    "addr:full":"32 Middle Dean St Halifax West Yorkshire HX4 8DP",
    "addr:housenumber":"32",
    "addr:postcode":"hx4 8dp",
    "addr:street":"Middle Dean St",
    "iso:country":"GB",
    "sg:address":"32 Middle Dean St",
    "sg:city":"Halifax",
    "sg:classifiers":[
        {
            "category":"Building & Trades",
            "subcategory":"Construction",
            "type":"Services"
        }
    ],
    "sg:phone":"+44 1422 350660",
    "sg:postcode":"HX4 8DP",
    "sg:province":"West Yorkshire",
    "sg:tags":[
        "builder"
    ],
    "wof:name":"D J H Builders",
    "wof:placetype":"venue"
},
  "geometry": {"coordinates":[-1.8574090004,53.6850013733],"type":"Point"}
}