{
  "type": "Feature",
  "properties": {
    "iso:country":"GB",
    "sg:address":"21 Hope Road",
    "sg:city":"Shanklin",
    "sg:classifiers":[
        {
            "category":"Travel",
            "subcategory":"Hotels & Motels",
            "type":"Entertainment"
        }
    ],
    "sg:phone":"+44 1983 863140",
    "sg:postcode":"PO37 6EA",
    "sg:province":"Isle of Wight",
    "wof:name":"Hope Lodge",
    "wof:placetype":"venue"
},
  "geometry": {"coordinates":[-1.1730899811,50.6329689026],"type":"Point"}
}