{
  "type": "Feature",
  "properties": {
    "addr:full":"63 Macalpine Road Dundee Dundee City DD3 8RE",
    "addr:housenumber":"63",
    "addr:postcode":"dd3 8re",
    "addr:street":"Macalpine Road",
    "iso:country":"GB",
    "sg:address":"63 Macalpine Road",
    "sg:city":"Dundee",
    "sg:classifiers":[
        {
            "category":"Food & Beverages",
            "subcategory":"Bakery",
            "type":"Retail Goods"
        }
    ],
    "sg:phone":"+44 1382 815327",
    "sg:postcode":"DD3 8RE",
    "sg:province":"Dundee City",
    "sg:tags":[
        "baker"
    ],
    "wof:name":"Kingsway Bakery Sales",
    "wof:placetype":"venue"
},
  "geometry": {"coordinates":[-3.007199049,56.489780426],"type":"Point"}
}