{
  "type": "Feature",
  "properties": {
    "addr:full":"258 Kirkdale Sydenham Greater London SE26 4NL",
    "addr:housenumber":"258",
    "addr:postcode":"se26 4nl",
    "addr:street":"Kirkdale Sydenham",
    "iso:country":"GB",
    "sg:address":"258 Kirkdale",
    "sg:city":"Sydenham",
    "sg:classifiers":[
        {
            "category":"Health Services",
            "subcategory":"Nursing And Care Facility",
            "type":"Services"
        }
    ],
    "sg:phone":"+44 20 8659 9004",
    "sg:postcode":"SE26 4NL",
    "sg:province":"Greater London",
    "sg:tags":[
        "home"
    ],
    "wof:name":"Old Cedars",
    "wof:placetype":"venue"
},
  "geometry": {"coordinates":[-0.056508,51.427353],"type":"Point"}
}