{
  "type": "Feature",
  "properties": {
    "addr:full":"30 Flapper Fold Lane, Atherton Manchester Greater Manchester M46 0FA",
    "addr:housenumber":"30",
    "addr:postcode":"m46 0fa",
    "addr:street":"Flapper Fold Lane",
    "iso:country":"GB",
    "sg:address":"30 Flapper Fold Lane, Atherton",
    "sg:city":"Manchester",
    "sg:classifiers":[
        {
            "category":"Organizations",
            "subcategory":"Community Association",
            "type":"Services"
        },
        {
            "category":"Organizations",
            "subcategory":"Membership Organization",
            "type":"Services"
        }
    ],
    "sg:phone":"+44 1942 882240",
    "sg:postcode":"M46 0FA",
    "sg:province":"Greater Manchester",
    "sg:tags":[
        "club",
        "social"
    ],
    "wof:name":"Atherton Liberal Club",
    "wof:placetype":"venue"
},
  "geometry": {"coordinates":[-2.493168,53.525143],"type":"Point"}
}