{
  "type": "Feature",
  "properties": {
    "addr:full":"22 New Street Henley-on-thames Berkshire RG9 2BT",
    "addr:housenumber":"22",
    "addr:postcode":"rg9 2bt",
    "addr:street":"New Street",
    "iso:country":"GB",
    "sg:address":"22 New Street",
    "sg:city":"Henley-on-thames",
    "sg:classifiers":[
        {
            "category":"Home & Garden",
            "subcategory":"Carpets & Floor Coverings",
            "type":"Retail Goods"
        }
    ],
    "sg:postcode":"RG9 2BT",
    "sg:province":"Berkshire",
    "sg:tags":[
        "carpets",
        "rug",
        "matting"
    ],
    "wof:name":"Leslie Blake",
    "wof:placetype":"venue"
},
  "geometry": {"coordinates":[-0.903867,51.5392],"type":"Point"}
}