{
  "type": "Feature",
  "properties": {
    "iso:country":"GB",
    "sg:address":"40 Towerfield Road, Shoeburyness",
    "sg:city":"Southend-on-sea",
    "sg:classifiers":[
        {
            "category":"Manufacturing",
            "subcategory":"Wood Products",
            "type":"Manufacturing & Wholesale Goods"
        }
    ],
    "sg:phone":"+44 1702 293312",
    "sg:postcode":"SS3 9QT",
    "sg:province":"Essex",
    "sg:tags":[
        "packaging",
        "crate",
        "pallets"
    ],
    "wof:name":"Advanced Protective Packaging Ltd.",
    "wof:placetype":"venue"
},
  "geometry": {"coordinates":[0.785183,51.533581],"type":"Point"}
}