{
  "type": "Feature",
  "properties": {
    "addr:full":"28 Short Bridge Street Llanidloes Powys SY18 6AD",
    "addr:housenumber":"28",
    "addr:postcode":"sy18 6ad",
    "addr:street":"Short Bridge Street",
    "iso:country":"GB",
    "sg:address":"28 Short Bridge Street",
    "sg:city":"Llanidloes",
    "sg:classifiers":[
        {
            "category":"Fast Food",
            "type":"Food & Drink"
        }
    ],
    "sg:phone":"+44 1686 411046",
    "sg:postcode":"SY18 6AD",
    "sg:province":"Powys",
    "sg:tags":[
        "away",
        "take"
    ],
    "wof:name":"Kebab House 2 Town",
    "wof:placetype":"venue"
},
  "geometry": {"coordinates":[-3.540406,52.448872],"type":"Point"}
}