{
  "type": "Feature",
  "properties": {
    "addr:full":"56 Uppingham Road Leicester Leicestershire LE5 0QE",
    "addr:housenumber":"56",
    "addr:postcode":"le5 0qe",
    "addr:street":"Uppingham Road",
    "iso:country":"GB",
    "sg:address":"56 Uppingham Road",
    "sg:city":"Leicester",
    "sg:classifiers":[
        {
            "category":"Home & Garden",
            "subcategory":"Building Materials",
            "type":"Retail Goods"
        }
    ],
    "sg:phone":"+44 116 274 0144",
    "sg:postcode":"LE5 0QE",
    "sg:province":"Leicestershire",
    "sg:tags":[
        "furnishers",
        "bathroom",
        "planner"
    ],
    "wof:name":"Slater & Cook",
    "wof:placetype":"venue"
},
  "geometry": {"coordinates":[-1.1008690596,52.6420631409],"type":"Point"}
}