{
  "type": "Feature",
  "properties": {
    "addr:full":"Kings Works, Sir William Smith Road, Kirkton Industrial Estate Arbroath Angus DD11 3RD",
    "addr:postcode":"dd11 3rd",
    "addr:street":"William Smith Road Kirkton Industrial Estate",
    "iso:country":"GB",
    "sg:address":"Kings Works, Sir William Smith Road, Kirkton Industrial Estate",
    "sg:city":"Arbroath",
    "sg:classifiers":[
        {
            "category":"Professional",
            "subcategory":"Engineering",
            "type":"Services"
        }
    ],
    "sg:phone":"+44 1241 870774",
    "sg:postcode":"DD11 3RD",
    "sg:province":"Angus",
    "sg:tags":[
        "engineer",
        "mechanical"
    ],
    "wof:name":"John M Henderson & Co Ltd",
    "wof:placetype":"venue"
},
  "geometry": {"coordinates":[-2.611068964,56.5732688904],"type":"Point"}
}