{
  "type": "Feature",
  "properties": {
    "iso:country":"GB",
    "sg:address":"14 Denmark Road",
    "sg:city":"London",
    "sg:classifiers":[
        {
            "category":"Building & Trades",
            "subcategory":"Plumbing",
            "type":"Services"
        }
    ],
    "sg:phone":"+44 20 8654 9774",
    "sg:postcode":"SE25 5QU",
    "sg:province":"Greater London",
    "sg:tags":[
        "heating"
    ],
    "wof:name":"Southside Plumbing Co",
    "wof:placetype":"venue"
},
  "geometry": {"coordinates":[-0.0685800016,51.3942298889],"type":"Point"}
}