{
  "type": "Feature",
  "properties": {
    "addr:full":"Hillside, Main Road Stocksfield Northumberland NE43 7JR",
    "addr:postcode":"ne43 7jr",
    "addr:street":"Main Road",
    "iso:country":"GB",
    "sg:address":"Hillside, Main Road",
    "sg:city":"Stocksfield",
    "sg:classifiers":[
        {
            "category":"Personal",
            "subcategory":"Beauty Salon",
            "type":"Services"
        }
    ],
    "sg:phone":"+44 1661 843745",
    "sg:postcode":"NE43 7JR",
    "sg:province":"Northumberland",
    "sg:tags":[
        "unisex",
        "hairdresser"
    ],
    "wof:name":"Hair Design by Shonagh",
    "wof:placetype":"venue"
},
  "geometry": {"coordinates":[-1.915894,54.946686],"type":"Point"}
}