{
  "type": "Feature",
  "properties": {
    "addr:full":"Access 5 Rhodes Way Watford Hertfordshire WD24 4YW",
    "addr:housenumber":"5",
    "addr:postcode":"wd24 4yw",
    "addr:street":"Access;Rhodes Way",
    "iso:country":"GB",
    "sg:address":"Access 5 Rhodes Way",
    "sg:city":"Watford",
    "sg:classifiers":[
        {
            "category":"Professional",
            "subcategory":"Computer Services",
            "type":"Services"
        }
    ],
    "sg:postcode":"WD24 4YW",
    "sg:province":"Hertfordshire",
    "sg:tags":[
        "system",
        "software"
    ],
    "wof:name":"Set U K Ltd.",
    "wof:placetype":"venue"
},
  "geometry": {"coordinates":[-0.3881100118,51.6655693054],"type":"Point"}
}