{
  "type": "Feature",
  "properties": {
    "addr:full":"Frenchay Hill, Frenchay Bristol City of Bristol BS16 1LL",
    "addr:postcode":"bs16 1ll",
    "addr:street":"Frenchay Hill",
    "iso:country":"GB",
    "sg:address":"Frenchay Hill, Frenchay",
    "sg:city":"Bristol",
    "sg:classifiers":[
        {
            "category":"Social Services",
            "subcategory":"Adult Care",
            "type":"Services"
        }
    ],
    "sg:phone":"+44 117 956 1038",
    "sg:postcode":"BS16 1LL",
    "sg:province":"City of Bristol",
    "sg:tags":[
        "housing",
        "sheltered"
    ],
    "wof:name":"North Avon District Council",
    "wof:placetype":"venue"
},
  "geometry": {"coordinates":[-2.5914289951,51.453666687],"type":"Point"}
}