{
  "type": "Feature",
  "properties": {
    "iso:country":"GB",
    "sg:address":"5 The Croft, Horncliffe",
    "sg:city":"Berwick-upon-tweed",
    "sg:classifiers":[
        {
            "category":"Freight",
            "type":"Transportation"
        }
    ],
    "sg:phone":"+44 1289 386461",
    "sg:postcode":"TD15 2XJ",
    "sg:province":"Northumberland",
    "sg:tags":[
        "haulage",
        "road"
    ],
    "wof:name":"A Deans",
    "wof:placetype":"venue"
},
  "geometry": {"coordinates":[-2.032191,55.755726],"type":"Point"}
}