{
  "type": "Feature",
  "properties": {
    "addr:full":"Selsmore Road Hayling Island Hampshire PO11 9JZ",
    "addr:postcode":"po11 9jz",
    "addr:street":"Selsmore Road",
    "iso:country":"GB",
    "sg:address":"Selsmore Road",
    "sg:city":"Hayling Island",
    "sg:classifiers":[
        {
            "category":"Health Services",
            "subcategory":"Nursing And Care Facility",
            "type":"Services"
        },
        {
            "category":"Social Services",
            "subcategory":"Retirement Home",
            "type":"Services"
        }
    ],
    "sg:phone":"+44 23 9246 7369",
    "sg:postcode":"PO11 9JZ",
    "sg:province":"Hampshire",
    "sg:tags":[
        "residential"
    ],
    "wof:name":"Wimborne Residential Care Homes",
    "wof:placetype":"venue"
},
  "geometry": {"coordinates":[-0.9748280048,50.7873497009],"type":"Point"}
}