{
  "type": "Feature",
  "properties": {
    "addr:full":"71a Partington Lane, Swinton Manchester Greater Manchester M27 0NS",
    "addr:housenumber":"71a",
    "addr:postcode":"m27 0ns",
    "addr:street":"Partington Lane",
    "iso:country":"GB",
    "sg:address":"71a Partington Lane, Swinton",
    "sg:city":"Manchester",
    "sg:classifiers":[
        {
            "category":"Retail",
            "subcategory":"Auto Repair",
            "type":"Services"
        }
    ],
    "sg:phone":"+44 161 728 1320",
    "sg:postcode":"M27 0NS",
    "sg:province":"Greater Manchester",
    "sg:tags":[
        "modification",
        "garage",
        "related"
    ],
    "wof:name":"Graham Casson",
    "wof:placetype":"venue"
},
  "geometry": {"coordinates":[-2.342031,53.507542],"type":"Point"}
}