{
  "type": "Feature",
  "properties": {
    "iso:country":"GB",
    "sg:address":"80 Wells Road",
    "sg:city":"Malvern",
    "sg:classifiers":[
        {
            "category":"Professional",
            "subcategory":"Management & Consulting",
            "type":"Services"
        }
    ],
    "sg:phone":"+44 1684 575756",
    "sg:postcode":"WR14 4PA",
    "sg:province":"Herefordshire",
    "sg:tags":[
        "marketing",
        "consultant"
    ],
    "wof:name":"Tyler Jordon Associates",
    "wof:placetype":"venue"
},
  "geometry": {"coordinates":[-2.334141,52.09367],"type":"Point"}
}