{
  "type": "Feature",
  "properties": {
    "addr:full":"22 High Street Banchory Aberdeen City AB31 5SR",
    "addr:housenumber":"22",
    "addr:postcode":"ab31 5sr",
    "addr:street":"High Street;Aberdeen",
    "iso:country":"GB",
    "sg:address":"22 High Street",
    "sg:city":"Banchory",
    "sg:classifiers":[
        {
            "category":"Travel",
            "subcategory":"Hotels & Motels",
            "type":"Entertainment"
        }
    ],
    "sg:phone":"+44 1330 822547",
    "sg:postcode":"AB31 5SR",
    "sg:province":"Aberdeen City",
    "wof:name":"Douglas Arms Hotel",
    "wof:placetype":"venue"
},
  "geometry": {"coordinates":[-2.504672,57.051273],"type":"Point"}
}