{
  "type": "Feature",
  "properties": {
    "addr:full":"27 Dingley Pl Clerkenwell Greater London EC1V 8BR",
    "addr:housenumber":"27",
    "addr:postcode":"ec1v 8br",
    "addr:street":"Dingley Pl",
    "iso:country":"GB",
    "sg:address":"27 Dingley Pl",
    "sg:city":"Clerkenwell",
    "sg:classifiers":[
        {
            "category":"Social Services",
            "type":"Services"
        }
    ],
    "sg:phone":"+44 20 7250 1554",
    "sg:postcode":"EC1V 8BR",
    "sg:province":"Greater London",
    "wof:name":"Youth Justice Team",
    "wof:placetype":"venue"
},
  "geometry": {"coordinates":[-0.093741,51.52771],"type":"Point"}
}