{
  "type": "Feature",
  "properties": {
    "iso:country":"GB",
    "sg:address":"4th Floor, Alexandra House 94-96 Talbot Roa",
    "sg:city":"Manchester",
    "sg:classifiers":[
        {
            "category":"Building & Trades",
            "subcategory":"Cleaning & Sanitation",
            "type":"Services"
        }
    ],
    "sg:phone":"+44 161 877 0419",
    "sg:postcode":"M16 0PG",
    "sg:province":"Cheshire",
    "sg:tags":[
        "commercial"
    ],
    "wof:name":"Initial Foodguard",
    "wof:placetype":"venue"
},
  "geometry": {"coordinates":[-2.283919096,53.4598007202],"type":"Point"}
}