{
  "type": "Feature",
  "properties": {
    "addr:full":"Wingate Close, Bilborough Nottingham Nottinghamshire NG8 4LP",
    "addr:postcode":"ng8 4lp",
    "addr:street":"Wingate Close",
    "iso:country":"GB",
    "sg:address":"Wingate Close, Bilborough",
    "sg:city":"Nottingham",
    "sg:classifiers":[
        {
            "category":"Home & Garden",
            "subcategory":"Home Furnishings",
            "type":"Retail Goods"
        }
    ],
    "sg:phone":"+44 115 942 5549",
    "sg:postcode":"NG8 4LP",
    "sg:province":"Nottinghamshire",
    "sg:tags":[
        "furnishers",
        "planner",
        "kitchen"
    ],
    "wof:name":"Worktop Fabrications Ltd.",
    "wof:placetype":"venue"
},
  "geometry": {"coordinates":[-1.2305740118,52.9612083435],"type":"Point"}
}