{
  "type": "Feature",
  "properties": {
    "iso:country":"GB",
    "sg:address":"East Wing Old School House, Britannia Road",
    "sg:city":"Bristol",
    "sg:classifiers":[
        {
            "category":"Education",
            "subcategory":"University",
            "type":"Public Place"
        }
    ],
    "sg:postcode":"BS15 3DB",
    "sg:province":"City of Bristol",
    "sg:tags":[
        "higher"
    ],
    "wof:name":"Kingswood Community Project",
    "wof:placetype":"venue"
},
  "geometry": {"coordinates":[-2.5157589912,51.4600257874],"type":"Point"}
}