{
  "type": "Feature",
  "properties": {
    "iso:country":"GB",
    "sg:address":"Redcroft House, Redcroft Walk",
    "sg:city":"Cranleigh",
    "sg:classifiers":[
        {
            "category":"Real Estate",
            "subcategory":"Developer",
            "type":"Services"
        }
    ],
    "sg:phone":"+44 1483 278444",
    "sg:postcode":"GU6 8DS",
    "sg:province":"Surrey",
    "sg:tags":[
        "property"
    ],
    "wof:name":"Shelton Development Services",
    "wof:placetype":"venue"
},
  "geometry": {"coordinates":[-0.48134,51.139267],"type":"Point"}
}