{
  "type": "Feature",
  "properties": {
    "addr:full":"6 Woollards Lane, Great Shelford Cambridge Cambridgeshire CB2 5LZ",
    "addr:housenumber":"6",
    "addr:postcode":"cb2 5lz",
    "addr:street":"Woollards Lane",
    "iso:country":"GB",
    "sg:address":"6 Woollards Lane, Great Shelford",
    "sg:city":"Cambridge",
    "sg:classifiers":[
        {
            "category":"Health Services",
            "subcategory":"Dentist",
            "type":"Services"
        }
    ],
    "sg:postcode":"CB2 5LZ",
    "sg:province":"Cambridgeshire",
    "wof:name":"Anthony J Chapman",
    "wof:placetype":"venue"
},
  "geometry": {"coordinates":[0.1371400058,52.1468582153],"type":"Point"}
}