{
  "type": "Feature",
  "properties": {
    "iso:country":"GB",
    "sg:address":"29-35 High Street",
    "sg:city":"Harrow",
    "sg:classifiers":[
        {
            "category":"Organizations",
            "subcategory":"Membership Organization",
            "type":"Services"
        }
    ],
    "sg:postcode":"HA1 3HT",
    "sg:province":"Greater London",
    "sg:tags":[
        "club"
    ],
    "wof:name":"West Ruislip(Block E)Management Company",
    "wof:placetype":"venue"
},
  "geometry": {"coordinates":[-0.338726,51.571175],"type":"Point"}
}