{
  "type": "Feature",
  "properties": {
    "addr:full":"Brandwood Quarry, Blackwood Road Bacup Lancashire OL13 0PS",
    "addr:postcode":"ol13 0ps",
    "addr:street":"Brandwood Quarry Blackwood Road",
    "iso:country":"GB",
    "sg:address":"Brandwood Quarry, Blackwood Road",
    "sg:city":"Bacup",
    "sg:classifiers":[
        {
            "category":"Wholesale",
            "subcategory":"Scrap",
            "type":"Manufacturing & Wholesale Goods"
        }
    ],
    "sg:postcode":"OL13 0PS",
    "sg:province":"Lancashire",
    "sg:tags":[
        "breaker",
        "dismantlers"
    ],
    "wof:name":"N & J Motor Spares",
    "wof:placetype":"venue"
},
  "geometry": {"coordinates":[-2.2011039257,53.7027168274],"type":"Point"}
}