{
  "type": "Feature",
  "properties": {
    "addr:full":"159a High Street, Hampton Hill Hampton Greater London TW12 1NL",
    "addr:housenumber":"159a",
    "addr:postcode":"tw12 1nl",
    "addr:street":"High Street",
    "iso:country":"GB",
    "sg:address":"159a High Street, Hampton Hill",
    "sg:city":"Hampton",
    "sg:classifiers":[
        {
            "category":"Professional",
            "subcategory":"Management & Consulting",
            "type":"Services"
        },
        {
            "category":"Professional",
            "subcategory":"Research",
            "type":"Services"
        }
    ],
    "sg:phone":"+44 20 8783 0343",
    "sg:postcode":"TW12 1NL",
    "sg:province":"Greater London",
    "sg:tags":[
        "marketing",
        "market",
        "consultant"
    ],
    "wof:name":"Megaprint Group Ltd",
    "wof:placetype":"venue"
},
  "geometry": {"coordinates":[-0.3556250036,51.4272956848],"type":"Point"}
}