{
  "type": "Feature",
  "properties": {
    "addr:full":"Manor House, Dean Workington Cumbria CA14 4TJ",
    "addr:postcode":"ca14 4tj",
    "addr:street":"Manor;Dean Workington",
    "iso:country":"GB",
    "sg:address":"Manor House, Dean",
    "sg:city":"Workington",
    "sg:classifiers":[
        {
            "category":"Farming",
            "subcategory":"Farm",
            "type":"Manufacturing & Wholesale Goods"
        }
    ],
    "sg:postcode":"CA14 4TJ",
    "sg:province":"Cumbria",
    "sg:tags":[
        "mixed",
        "crop"
    ],
    "wof:name":"Eric Winder Waite",
    "wof:placetype":"venue"
},
  "geometry": {"coordinates":[-3.556449,54.64539],"type":"Point"}
}