{
  "type": "Feature",
  "properties": {
    "iso:country":"GB",
    "sg:address":"6 Osborne Road",
    "sg:city":"Farnborough",
    "sg:classifiers":[
        {
            "category":"Autos & Motor Vehicles",
            "subcategory":"Auto Supplies",
            "type":"Retail Goods"
        }
    ],
    "sg:phone":"+44 1252 540893",
    "sg:postcode":"GU14 6AA",
    "sg:province":"Hampshire",
    "sg:tags":[
        "electric"
    ],
    "wof:name":"A E S Rewinds Ltd.",
    "wof:placetype":"venue"
},
  "geometry": {"coordinates":[-0.754122,51.278847],"type":"Point"}
}