{
  "type": "Feature",
  "properties": {
    "addr:full":"1071 Duke Street Glasgow Glasgow City G31 5NR",
    "addr:housenumber":"1071",
    "addr:postcode":"g31 5nr",
    "addr:street":"Duke Street",
    "iso:country":"GB",
    "sg:address":"1071 Duke Street",
    "sg:city":"Glasgow",
    "sg:classifiers":[
        {
            "category":"Bars & Pubs",
            "subcategory":"Nightclub",
            "type":"Food & Drink"
        }
    ],
    "sg:postcode":"G31 5NR",
    "sg:province":"Glasgow City",
    "sg:tags":[
        "club",
        "night"
    ],
    "wof:name":"Joanna Dee's",
    "wof:placetype":"venue"
},
  "geometry": {"coordinates":[-4.201884,55.857346],"type":"Point"}
}