{
  "type": "Feature",
  "properties": {
    "iso:country":"GB",
    "sg:address":"22 Mottram Old Road",
    "sg:city":"Hyde",
    "sg:classifiers":[
        {
            "category":"Personal",
            "type":"Services"
        }
    ],
    "sg:postcode":"SK14 5NG",
    "sg:province":"Cheshire",
    "sg:tags":[
        "wedding"
    ],
    "wof:name":"S P A Salon Players",
    "wof:placetype":"venue"
},
  "geometry": {"coordinates":[-2.068048954,53.4389038086],"type":"Point"}
}