{
  "type": "Feature",
  "properties": {
    "addr:full":"70-72 Preston New Road Blackburn Lancashire BB2 6BH",
    "addr:housenumber":"70-72",
    "addr:postcode":"bb2 6bh",
    "addr:street":"Preston New Road",
    "iso:country":"GB",
    "sg:address":"70-72 Preston New Road",
    "sg:city":"Blackburn",
    "sg:classifiers":[
        {
            "category":"Travel",
            "subcategory":"Hostel",
            "type":"Entertainment"
        },
        {
            "category":"Organizations",
            "subcategory":"Community Association",
            "type":"Services"
        }
    ],
    "sg:postcode":"BB2 6BH",
    "sg:province":"Lancashire",
    "sg:tags":[
        "associations",
        "co-operatives",
        "housing",
        "trust",
        "societies"
    ],
    "wof:name":"STONHAM HOUSING ASSOCIATION LTD",
    "wof:placetype":"venue"
},
  "geometry": {"coordinates":[-2.495185,53.751446],"type":"Point"}
}