{
  "type": "Feature",
  "properties": {
    "iso:country":"GB",
    "sg:address":"35 Summer Street",
    "sg:city":"Aberdeen",
    "sg:classifiers":[
        {
            "category":"Professional",
            "subcategory":"Management & Consulting",
            "type":"Services"
        }
    ],
    "sg:phone":"+44 1224 636870",
    "sg:postcode":"AB10 1SB",
    "sg:province":"Aberdeen City",
    "sg:tags":[
        "consultant",
        "safety",
        "business"
    ],
    "wof:name":"RED OAK LTD",
    "wof:placetype":"venue"
},
  "geometry": {"coordinates":[-2.109499,57.145058],"type":"Point"}
}