{
  "type": "Feature",
  "properties": {
    "addr:full":"12 North Hill Colchester Essex CO1 1AS",
    "addr:housenumber":"12",
    "addr:postcode":"co1 1as",
    "addr:street":"North Hill Colchester",
    "iso:country":"GB",
    "sg:address":"12 North Hill",
    "sg:city":"Colchester",
    "sg:classifiers":[
        {
            "category":"Professional",
            "subcategory":"Accounting & Tax Preparation",
            "type":"Services"
        }
    ],
    "sg:phone":"+44 1206 577422",
    "sg:postcode":"CO1 1AS",
    "sg:province":"Essex",
    "sg:tags":[
        "accountant"
    ],
    "wof:name":"Horwath Clark Whitehill",
    "wof:placetype":"venue"
},
  "geometry": {"coordinates":[0.896409,51.889809],"type":"Point"}
}