{
  "type": "Feature",
  "properties": {
    "addr:full":"Pryors Bank, Bishops Park Fulham Greater London SW6 3LA",
    "addr:postcode":"sw6 3la",
    "addr:street":"Fulham",
    "iso:country":"GB",
    "sg:address":"Pryors Bank, Bishops Park",
    "sg:city":"Fulham",
    "sg:classifiers":[
        {
            "category":"Organizations",
            "subcategory":"Non-profit Organization",
            "type":"Services"
        }
    ],
    "sg:phone":"+44 20 7736 4443",
    "sg:postcode":"SW6 3LA",
    "sg:province":"Greater London",
    "sg:tags":[
        "organisation",
        "voluntary",
        "charity"
    ],
    "wof:name":"H.A.P.A.",
    "wof:placetype":"venue"
},
  "geometry": {"coordinates":[-0.212500006,51.468208313],"type":"Point"}
}