{
  "type": "Feature",
  "properties": {
    "addr:full":"103 Dereham Road Norwich Norfolk NR2 4HT",
    "addr:housenumber":"103",
    "addr:postcode":"nr2 4ht",
    "addr:street":"Dereham Road Norwich Norfolk",
    "iso:country":"GB",
    "sg:address":"103 Dereham Road",
    "sg:city":"Norwich",
    "sg:classifiers":[
        {
            "category":"Wholesale",
            "subcategory":"Sporting Goods",
            "type":"Manufacturing & Wholesale Goods"
        }
    ],
    "sg:phone":"+44 1603 620843",
    "sg:postcode":"NR2 4HT",
    "sg:province":"Norfolk",
    "sg:tags":[
        "mnfr",
        "sport",
        "equipment"
    ],
    "wof:name":"Culyer Sports",
    "wof:placetype":"venue"
},
  "geometry": {"coordinates":[1.280059,52.633511],"type":"Point"}
}