{
  "type": "Feature",
  "properties": {
    "iso:country":"GB",
    "sg:address":"62 Coalway Road, Penn",
    "sg:city":"Wolverhampton",
    "sg:classifiers":[
        {
            "category":"Building & Trades",
            "subcategory":"Construction",
            "type":"Services"
        }
    ],
    "sg:phone":"+44 1902 335819",
    "sg:postcode":"WV3 7LZ",
    "sg:province":"Staffordshire",
    "sg:tags":[
        "builder"
    ],
    "wof:name":"H Dalton & Son",
    "wof:placetype":"venue"
},
  "geometry": {"coordinates":[-2.152943,52.569244],"type":"Point"}
}