{
  "type": "Feature",
  "properties": {
    "addr:full":"Po Box 85 Horsham West Sussex RH12 3YZ",
    "addr:housenumber":"po box 85",
    "addr:postcode":"rh12 3yz",
    "iso:country":"GB",
    "sg:address":"Po Box 85",
    "sg:city":"Horsham",
    "sg:classifiers":[
        {
            "category":"Food & Beverages",
            "subcategory":"Liquor & Beverages",
            "type":"Retail Goods"
        }
    ],
    "sg:phone":"+44 1798 874722",
    "sg:postcode":"RH12 3YZ",
    "sg:province":"West Sussex",
    "sg:tags":[
        "beer",
        "spirit",
        "wines"
    ],
    "wof:name":"Best Brews & Carafe Ltd",
    "wof:placetype":"venue"
},
  "geometry": {"coordinates":[-0.3827590048,51.0841293335],"type":"Point"}
}