{
  "type": "Feature",
  "properties": {
    "addr:full":"1 Cleveland Walk Bath Somerset BA2 6JS",
    "addr:housenumber":"1",
    "addr:postcode":"ba2 6js",
    "addr:street":"Cleveland Walk",
    "iso:country":"GB",
    "sg:address":"1 Cleveland Walk",
    "sg:city":"Bath",
    "sg:classifiers":[
        {
            "category":"Health Services",
            "subcategory":"Nursing And Care Facility",
            "type":"Services"
        }
    ],
    "sg:phone":"+44 1225 466685",
    "sg:postcode":"BA2 6JS",
    "sg:province":"Somerset",
    "sg:tags":[
        "home"
    ],
    "wof:name":"Westcroft Nursing Homes",
    "wof:placetype":"venue"
},
  "geometry": {"coordinates":[-2.344906,51.381294],"type":"Point"}
}