{
  "type": "Feature",
  "properties": {
    "iso:country":"GB",
    "sg:address":"Stag Hill House",
    "sg:city":"Guildford",
    "sg:classifiers":[
        {
            "category":"Sports & Exercise",
            "subcategory":"Swimming Pool",
            "type":"Entertainment"
        }
    ],
    "sg:phone":"+44 1483 506506",
    "sg:postcode":"GU2 7XJ",
    "sg:province":"Surrey",
    "sg:tags":[
        "examination",
        "board"
    ],
    "wof:name":"The Associated Examining Board",
    "wof:placetype":"venue"
},
  "geometry": {"coordinates":[-0.597989,51.239601],"type":"Point"}
}