{
  "type": "Feature",
  "properties": {
    "addr:full":"Barn Cottage, Dunton Road Basildon Essex SS15 4DB",
    "addr:postcode":"ss15 4db",
    "addr:street":"Dunton Road",
    "iso:country":"GB",
    "sg:address":"Barn Cottage, Dunton Road",
    "sg:city":"Basildon",
    "sg:classifiers":[
        {
            "category":"Building & Trades",
            "subcategory":"Construction",
            "type":"Services"
        }
    ],
    "sg:phone":"+44 1268 548290",
    "sg:postcode":"SS15 4DB",
    "sg:province":"Essex",
    "sg:tags":[
        "roofing"
    ],
    "wof:name":"S D Samuels",
    "wof:placetype":"venue"
},
  "geometry": {"coordinates":[0.444556,51.567795],"type":"Point"}
}