{
  "type": "Feature",
  "properties": {
    "addr:full":"Heath Park, Station Road Hemel Hempstead Hertfordshire HP1 1JF",
    "addr:postcode":"hp1 1jf",
    "addr:street":"Heath Park Station Road",
    "iso:country":"GB",
    "sg:address":"Heath Park, Station Road",
    "sg:city":"Hemel Hempstead",
    "sg:classifiers":[
        {
            "category":"Arena",
            "subcategory":"Sports Club",
            "type":"Entertainment"
        }
    ],
    "sg:phone":"+44 1442 242690",
    "sg:postcode":"HP1 1JF",
    "sg:province":"Hertfordshire",
    "wof:name":"Hemel Hempstead Town Cricket Club",
    "wof:placetype":"venue"
},
  "geometry": {"coordinates":[-0.4750840068,51.7490005493],"type":"Point"}
}