{
  "type": "Feature",
  "properties": {
    "addr:full":"49 Montgomerie Street, Tarbolton Mauchline East Ayrshire KA5 5QA",
    "addr:housenumber":"49",
    "addr:postcode":"ka5 5qa",
    "addr:street":"Montgomerie Street;Mauchline East",
    "iso:country":"GB",
    "sg:address":"49 Montgomerie Street, Tarbolton",
    "sg:city":"Mauchline",
    "sg:classifiers":[
        {
            "category":"Building & Trades",
            "subcategory":"Construction",
            "type":"Services"
        }
    ],
    "sg:phone":"+44 1292 541216",
    "sg:postcode":"KA5 5QA",
    "sg:province":"East Ayrshire",
    "sg:tags":[
        "builder"
    ],
    "wof:name":"J Davidson & Sons",
    "wof:placetype":"venue"
},
  "geometry": {"coordinates":[-4.3789129257,55.5156440735],"type":"Point"}
}