{
  "type": "Feature",
  "properties": {
    "iso:country":"GB",
    "sg:address":"Unit 22, Weaver Ind Est, Blackburne St",
    "sg:city":"Liverpool",
    "sg:classifiers":[
        {
            "category":"Professional",
            "subcategory":"Engineering",
            "type":"Services"
        }
    ],
    "sg:phone":"+44 151 427 8800",
    "sg:postcode":"L19 8JA",
    "sg:province":"Merseyside",
    "sg:tags":[
        "precision",
        "engineer"
    ],
    "wof:name":"Milostar Engineering Ltd",
    "wof:placetype":"venue"
},
  "geometry": {"coordinates":[-2.897539,53.344769],"type":"Point"}
}