{
  "type": "Feature",
  "properties": {
    "iso:country":"GB",
    "sg:address":"Bankfoot",
    "sg:city":"Crook",
    "sg:classifiers":[
        {
            "category":"Bars & Pubs",
            "type":"Food & Drink"
        },
        {
            "category":"Community Center",
            "subcategory":"Social",
            "type":"Public Place"
        }
    ],
    "sg:phone":"+44 1388 768473",
    "sg:postcode":"DL15 9RL",
    "sg:province":"Durham",
    "sg:tags":[
        "pubs",
        "house",
        "inn",
        "activity"
    ],
    "wof:name":"The Farrers Arms",
    "wof:placetype":"venue"
},
  "geometry": {"coordinates":[-1.748794,54.714363],"type":"Point"}
}