{
  "type": "Feature",
  "properties": {
    "addr:full":"105 The Street, Fetcham Leatherhead Surrey KT22 9RD",
    "addr:housenumber":"105",
    "addr:postcode":"kt22 9rd",
    "addr:street":"The Street",
    "iso:country":"GB",
    "sg:address":"105 The Street, Fetcham",
    "sg:city":"Leatherhead",
    "sg:classifiers":[
        {
            "category":"Professional",
            "subcategory":"Detective & Security Services",
            "type":"Services"
        }
    ],
    "sg:postcode":"KT22 9RD",
    "sg:province":"Surrey",
    "sg:tags":[
        "alarm",
        "burglar",
        "system"
    ],
    "wof:name":"A I J Security Ltd.",
    "wof:placetype":"venue"
},
  "geometry": {"coordinates":[-0.3569520116,51.2963142395],"type":"Point"}
}