{
  "type": "Feature",
  "properties": {
    "addr:full":"2 The Walk Rochdale Lancashire OL16 1EP",
    "addr:housenumber":"2",
    "addr:postcode":"ol16 1ep",
    "addr:street":"The Walk",
    "iso:country":"GB",
    "sg:address":"2 The Walk",
    "sg:city":"Rochdale",
    "sg:classifiers":[
        {
            "category":"Shopping",
            "subcategory":"Comic Books",
            "type":"Retail Goods"
        }
    ],
    "sg:postcode":"OL16 1EP",
    "sg:province":"Lancashire",
    "sg:tags":[
        "jeweller"
    ],
    "wof:name":"Cochrane,J,",
    "wof:placetype":"venue"
},
  "geometry": {"coordinates":[-2.1580970287,53.6172599792],"type":"Point"}
}