{
  "type": "Feature",
  "properties": {
    "addr:full":"251 Lower Addiscombe Rd Croydon Surrey CR0 6RD",
    "addr:housenumber":"251",
    "addr:postcode":"cr0 6rd",
    "addr:street":"Lower Addiscombe Rd",
    "iso:country":"GB",
    "sg:address":"251 Lower Addiscombe Rd",
    "sg:city":"Croydon",
    "sg:classifiers":[
        {
            "category":"Food & Beverages",
            "subcategory":"Bakery",
            "type":"Retail Goods"
        }
    ],
    "sg:phone":"+44 20 8654 3361",
    "sg:postcode":"CR0 6RD",
    "sg:province":"Surrey",
    "sg:tags":[
        "baker"
    ],
    "wof:name":"The Baker's Oven",
    "wof:placetype":"venue"
},
  "geometry": {"coordinates":[-0.072529003,51.3805961609],"type":"Point"}
}