{
  "type": "Feature",
  "properties": {
    "iso:country":"GB",
    "sg:address":"12 Westward House, Milnrow",
    "sg:city":"Rochdale",
    "sg:classifiers":[
        {
            "category":"Health Services",
            "subcategory":"Clinic",
            "type":"Services"
        },
        {
            "category":"Health Services",
            "subcategory":"Medical Lab",
            "type":"Services"
        }
    ],
    "sg:phone":"+44 1706 642942",
    "sg:postcode":"OL16 3JX",
    "sg:province":"Lancashire",
    "sg:tags":[
        "x-ray"
    ],
    "wof:name":"X-Ray Engineering Services Ltd.",
    "wof:placetype":"venue"
},
  "geometry": {"coordinates":[-2.108052,53.611652],"type":"Point"}
}