{
  "type": "Feature",
  "properties": {
    "iso:country":"GB",
    "sg:address":"18 Bisley Rd",
    "sg:city":"Stroud",
    "sg:classifiers":[
        {
            "category":"Professional",
            "subcategory":"Computer Services",
            "type":"Services"
        }
    ],
    "sg:phone":"+44 1453 755553",
    "sg:postcode":"GL5 1HE",
    "sg:province":"Gloucestershire",
    "sg:tags":[
        "system",
        "software"
    ],
    "wof:name":"Small World Software",
    "wof:placetype":"venue"
},
  "geometry": {"coordinates":[-2.2028930187,51.7427520752],"type":"Point"}
}