{
  "type": "Feature",
  "properties": {
    "addr:full":"Marwell Manor Farm, Portsmouth Road Eastleigh Hampshire SO50 7HF",
    "addr:postcode":"so50 7hf",
    "addr:street":"Portsmouth Road",
    "iso:country":"GB",
    "sg:address":"Marwell Manor Farm, Portsmouth Road",
    "sg:city":"Eastleigh",
    "sg:classifiers":[
        {
            "category":"Banks & Credit Unions",
            "subcategory":"Investment Brokerage",
            "type":"Services"
        }
    ],
    "sg:postcode":"SO50 7HF",
    "sg:province":"Hampshire",
    "sg:tags":[
        "contractor"
    ],
    "wof:name":"V W Hill & Sons",
    "wof:placetype":"venue"
},
  "geometry": {"coordinates":[-1.3505929708,50.9683227539],"type":"Point"}
}