{
  "type": "Feature",
  "properties": {
    "addr:full":"Cloudsley, High Street Ascot Berkshire SL5 7HP",
    "addr:postcode":"sl5 7hp",
    "addr:street":"High Street",
    "iso:country":"GB",
    "sg:address":"Cloudsley, High Street",
    "sg:city":"Ascot",
    "sg:classifiers":[
        {
            "category":"Manufacturing",
            "subcategory":"Motor Vehicles & Parts",
            "type":"Manufacturing & Wholesale Goods"
        },
        {
            "category":"Autos & Motor Vehicles",
            "subcategory":"Auto Supplies",
            "type":"Retail Goods"
        }
    ],
    "sg:phone":"+44 1344 624855",
    "sg:postcode":"SL5 7HP",
    "sg:province":"Berkshire",
    "sg:tags":[
        "component",
        "commercial",
        "van",
        "truck",
        "manufacturer"
    ],
    "wof:name":"Hope Technical Developments Ltd",
    "wof:placetype":"venue"
},
  "geometry": {"coordinates":[-0.673794,51.410675],"type":"Point"}
}