{
  "type": "Feature",
  "properties": {
    "addr:full":"Unit 3, Guild Rd Bromsgrove Worcestershire B60 2BY",
    "addr:housenumber":"unit 3",
    "addr:postcode":"b60 2by",
    "addr:street":"Guild Rd",
    "iso:country":"GB",
    "sg:address":"Unit 3, Guild Rd",
    "sg:city":"Bromsgrove",
    "sg:classifiers":[
        {
            "category":"Retail",
            "subcategory":"Storage",
            "type":"Services"
        }
    ],
    "sg:phone":"+44 1527 874071",
    "sg:postcode":"B60 2BY",
    "sg:province":"Worcestershire",
    "sg:tags":[
        "household",
        "removal"
    ],
    "wof:name":"Tvs Ltd",
    "wof:placetype":"venue"
},
  "geometry": {"coordinates":[-2.062016964,52.3320388794],"type":"Point"}
}