{
  "type": "Feature",
  "properties": {
    "iso:country":"GB",
    "sg:address":"464-466 Lady Margaret Rd",
    "sg:city":"Southall",
    "sg:classifiers":[
        {
            "category":"Retail",
            "subcategory":"Auto Repair",
            "type":"Services"
        }
    ],
    "sg:phone":"+44 20 8813 0600",
    "sg:postcode":"UB1 2NW",
    "sg:province":"Greater London",
    "sg:tags":[
        "modification",
        "garage"
    ],
    "wof:name":"S H Motor Co",
    "wof:placetype":"venue"
},
  "geometry": {"coordinates":[-0.372361,51.529312],"type":"Point"}
}