{
  "type": "Feature",
  "properties": {
    "addr:full":"147 Deans La Edgware Greater London HA8 9NY",
    "addr:housenumber":"147",
    "addr:postcode":"ha8 9ny",
    "addr:street":"Deans La Edgware",
    "iso:country":"GB",
    "sg:address":"147 Deans La",
    "sg:city":"Edgware",
    "sg:classifiers":[
        {
            "category":"Food & Beverages",
            "subcategory":"Groceries & Convenience Stores",
            "type":"Retail Goods"
        }
    ],
    "sg:phone":"+44 20 8959 3762",
    "sg:postcode":"HA8 9NY",
    "sg:province":"Greater London",
    "wof:name":"Mautner",
    "wof:placetype":"venue"
},
  "geometry": {"coordinates":[-0.2606019974,51.6165046692],"type":"Point"}
}