{
  "type": "Feature",
  "properties": {
    "addr:full":"6 Avon St Hamilton South Lanarkshire ML3 7HU",
    "addr:housenumber":"6",
    "addr:postcode":"ml3 7hu",
    "addr:street":"Avon St",
    "iso:country":"GB",
    "sg:address":"6 Avon St",
    "sg:city":"Hamilton",
    "sg:classifiers":[
        {
            "category":"Shopping",
            "subcategory":"Bicycles & Sporting Goods",
            "type":"Retail Goods"
        }
    ],
    "sg:postcode":"ML3 7HU",
    "sg:province":"South Lanarkshire",
    "sg:tags":[
        "cycle",
        "accessory"
    ],
    "wof:name":"Ralton,Brian,",
    "wof:placetype":"venue"
},
  "geometry": {"coordinates":[-4.037211,55.772404],"type":"Point"}
}