{
  "type": "Feature",
  "properties": {
    "addr:full":"Haydon Court Drive, Haydon Wick Swindon Wiltshire SN25 1QN",
    "addr:postcode":"sn25 1qn",
    "addr:street":"Haydon Court Drive",
    "iso:country":"GB",
    "sg:address":"Haydon Court Drive, Haydon Wick",
    "sg:city":"Swindon",
    "sg:classifiers":[
        {
            "category":"Social Services",
            "subcategory":"Adult Care",
            "type":"Services"
        }
    ],
    "sg:phone":"+44 1793 726472",
    "sg:postcode":"SN25 1QN",
    "sg:province":"Wiltshire",
    "sg:tags":[
        "housing",
        "sheltered"
    ],
    "wof:name":"Haydon Court",
    "wof:placetype":"venue"
},
  "geometry": {"coordinates":[-1.809824,51.591759],"type":"Point"}
}