{
  "type": "Feature",
  "properties": {
    "addr:full":"253 Watford Road, Croxley Green Rickmansworth Hertfordshire WD3 3RX",
    "addr:housenumber":"253",
    "addr:postcode":"wd3 3rx",
    "addr:street":"Watford Road",
    "iso:country":"GB",
    "sg:address":"253 Watford Road, Croxley Green",
    "sg:city":"Rickmansworth",
    "sg:classifiers":[
        {
            "category":"Autos & Motor Vehicles",
            "subcategory":"Automobile Sales",
            "type":"Retail Goods"
        }
    ],
    "sg:phone":"+44 1923 224444",
    "sg:postcode":"WD3 3RX",
    "sg:province":"Hertfordshire",
    "sg:tags":[
        "car"
    ],
    "wof:name":"Currie Motors",
    "wof:placetype":"venue"
},
  "geometry": {"coordinates":[-0.4302479923,51.6513595581],"type":"Point"}
}