{
  "type": "Feature",
  "properties": {
    "addr:full":"811-813 High Road, Leytonstone London Greater London E11 1HQ",
    "addr:housenumber":"811-813",
    "addr:postcode":"e11 1hq",
    "addr:street":"High Road",
    "iso:country":"GB",
    "sg:address":"811-813 High Road, Leytonstone",
    "sg:city":"London",
    "sg:classifiers":[
        {
            "category":"Shopping",
            "subcategory":"Pharmacy",
            "type":"Retail Goods"
        }
    ],
    "sg:phone":"+44 20 8539 2550",
    "sg:postcode":"E11 1HQ",
    "sg:province":"Greater London",
    "sg:tags":[
        "pharmacist",
        "chemist"
    ],
    "wof:name":"Boots the Chemists",
    "wof:placetype":"venue"
},
  "geometry": {"coordinates":[0.0107199997,51.5680885315],"type":"Point"}
}