{
  "type": "Feature",
  "properties": {
    "iso:country":"GB",
    "sg:address":"Promenade",
    "sg:city":"Penzance",
    "sg:classifiers":[
        {
            "category":"Recreation",
            "subcategory":"Amusement Park",
            "type":"Entertainment"
        }
    ],
    "sg:phone":"+44 1736 363824",
    "sg:postcode":"TR18 4HH",
    "sg:province":"Cornwall",
    "sg:tags":[
        "arcade"
    ],
    "wof:name":"The Grand Casino",
    "wof:placetype":"venue"
},
  "geometry": {"coordinates":[-5.5333838463,50.1152114868],"type":"Point"}
}