{
  "type": "Feature",
  "properties": {
    "addr:full":"161 Westbury Av Wood Green Greater London N22 6RX",
    "addr:housenumber":"161",
    "addr:postcode":"n22 6rx",
    "addr:street":"Westbury Av;Green",
    "iso:country":"GB",
    "sg:address":"161 Westbury Av",
    "sg:city":"Wood Green",
    "sg:classifiers":[
        {
            "category":"Health Services",
            "subcategory":"Podiatrist",
            "type":"Services"
        }
    ],
    "sg:phone":"+44 20 8881 3479",
    "sg:postcode":"N22 6RX",
    "sg:province":"Greater London",
    "sg:tags":[
        "podiatrists",
        "chiropodist"
    ],
    "wof:name":"Davina McRobbie",
    "wof:placetype":"venue"
},
  "geometry": {"coordinates":[-0.094304,51.596764],"type":"Point"}
}