{
  "type": "Feature",
  "properties": {
    "iso:country":"GB",
    "sg:address":"35 Forrest Road",
    "sg:city":"Edinburgh",
    "sg:classifiers":[
        {
            "category":"Shopping",
            "subcategory":"Optician",
            "type":"Retail Goods"
        },
        {
            "category":"Health Services",
            "subcategory":"Optometrist",
            "type":"Services"
        }
    ],
    "sg:phone":"+44 131 225 7242",
    "sg:postcode":"EH1 2QT",
    "sg:province":"City of Edinburgh",
    "sg:tags":[
        "opthalmic"
    ],
    "wof:name":"Thomas J Walls",
    "wof:placetype":"venue"
},
  "geometry": {"coordinates":[-3.191346,55.945839],"type":"Point"}
}