{
  "type": "Feature",
  "properties": {
    "iso:country":"GB",
    "sg:address":"12a The Swickham, Wickham",
    "sg:city":"Fareham",
    "sg:classifiers":[
        {
            "category":"Insurance",
            "subcategory":"Insurance Agent",
            "type":"Services"
        }
    ],
    "sg:phone":"+44 1329 832690",
    "sg:postcode":"PO17 5JQ",
    "sg:province":"Hampshire",
    "sg:tags":[
        "broker"
    ],
    "wof:name":"Roger Hearn Ltd.",
    "wof:placetype":"venue"
},
  "geometry": {"coordinates":[-1.187789,50.898479],"type":"Point"}
}