{
  "type": "Feature",
  "properties": {
    "addr:full":"St Peters House, Gower Street Derby Derbyshire DE1 1SB",
    "addr:postcode":"de1 1sb",
    "addr:street":"Gower Street",
    "iso:country":"GB",
    "sg:address":"St Peters House, Gower Street",
    "sg:city":"Derby",
    "sg:classifiers":[
        {
            "category":"Professional",
            "subcategory":"Employment Agencies",
            "type":"Services"
        }
    ],
    "sg:phone":"+44 1332 714300",
    "sg:postcode":"DE1 1SB",
    "sg:province":"Derbyshire",
    "sg:tags":[
        "consultant"
    ],
    "wof:name":"The Jobcentre",
    "wof:placetype":"venue"
},
  "geometry": {"coordinates":[-1.477219,52.919601],"type":"Point"}
}