{
  "type": "Feature",
  "properties": {
    "iso:country":"GB",
    "sg:address":"45 Henton Road, Leicester",
    "sg:city":"Leicester",
    "sg:classifiers":[
        {
            "category":"Recreation",
            "type":"Entertainment"
        }
    ],
    "sg:phone":"+44 116 299 7045",
    "sg:postcode":"LE3 6AY",
    "sg:province":"Leicestershire",
    "sg:tags":[
        "corporate",
        "leisure"
    ],
    "wof:name":"Glenrich Entertainment Ltd",
    "wof:placetype":"venue"
},
  "geometry": {"coordinates":[-1.157206,52.634308],"type":"Point"}
}