{
  "type": "Feature",
  "properties": {
    "addr:full":"124 Sundridge Drive Chatham Kent ME5 8JD",
    "addr:housenumber":"124",
    "addr:postcode":"me5 8jd",
    "addr:street":"Sundridge Drive",
    "iso:country":"GB",
    "sg:address":"124 Sundridge Drive",
    "sg:city":"Chatham",
    "sg:classifiers":[
        {
            "category":"Retail",
            "subcategory":"Auto Repair",
            "type":"Services"
        }
    ],
    "sg:phone":"+44 1634 863007",
    "sg:postcode":"ME5 8JD",
    "sg:province":"Kent",
    "sg:tags":[
        "engine",
        "specialist",
        "diagnostic",
        "tuning",
        "car"
    ],
    "wof:name":"Run Right",
    "wof:placetype":"venue"
},
  "geometry": {"coordinates":[0.533415,51.343063],"type":"Point"}
}