{
  "type": "Feature",
  "properties": {
    "iso:country":"GB",
    "sg:address":"60 Farmcote Ct",
    "sg:city":"Middlesbrough",
    "sg:classifiers":[
        {
            "category":"Building & Trades",
            "subcategory":"Construction",
            "type":"Services"
        }
    ],
    "sg:phone":"+44 1642 594907",
    "sg:postcode":"TS8 9LJ",
    "sg:province":"North Yorkshire",
    "sg:tags":[
        "decorator",
        "painter"
    ],
    "wof:name":"M Moore",
    "wof:placetype":"venue"
},
  "geometry": {"coordinates":[-1.247156,54.518818],"type":"Point"}
}