{
  "type": "Feature",
  "properties": {
    "iso:country":"GB",
    "sg:address":"60 Halkyn Street",
    "sg:city":"Flint",
    "sg:classifiers":[
        {
            "category":"Building & Trades",
            "subcategory":"Construction",
            "type":"Services"
        }
    ],
    "sg:phone":"+44 1352 732562",
    "sg:postcode":"CH6 5HZ",
    "sg:province":"Flintshire",
    "sg:tags":[
        "decorator",
        "painter"
    ],
    "wof:name":"William Collings & Sons",
    "wof:placetype":"venue"
},
  "geometry": {"coordinates":[-3.1395719051,53.2458114624],"type":"Point"}
}