{
  "type": "Feature",
  "properties": {
    "addr:full":"182 Prospecthill Road, Mount Florida Glasgow Glasgow City G42 9LH",
    "addr:housenumber":"182",
    "addr:postcode":"g42 9lh",
    "addr:street":"Prospecthill Road",
    "iso:country":"GB",
    "sg:address":"182 Prospecthill Road, Mount Florida",
    "sg:city":"Glasgow",
    "sg:classifiers":[
        {
            "category":"Real Estate",
            "subcategory":"Architect",
            "type":"Services"
        }
    ],
    "sg:postcode":"G42 9LH",
    "sg:province":"Glasgow City",
    "sg:tags":[
        "architectural"
    ],
    "wof:name":"The Andrew Kerr Partnership",
    "wof:placetype":"venue"
},
  "geometry": {"coordinates":[-4.2618517876,55.8279418945],"type":"Point"}
}