{
  "type": "Feature",
  "properties": {
    "iso:country":"GB",
    "sg:address":"4 Brunswick Road",
    "sg:city":"Buckley",
    "sg:classifiers":[
        {
            "category":"Shopping",
            "subcategory":"Clothing, Apparel, & Fashions",
            "type":"Retail Goods"
        }
    ],
    "sg:postcode":"CH7 2EF",
    "sg:province":"Denbighshire",
    "sg:tags":[
        "shop"
    ],
    "wof:name":"Solo",
    "wof:placetype":"venue"
},
  "geometry": {"coordinates":[-3.080393,53.168076],"type":"Point"}
}