{
  "type": "Feature",
  "properties": {
    "iso:country":"GB",
    "sg:address":"224 Forton Road",
    "sg:city":"Gosport",
    "sg:classifiers":[
        {
            "category":"Autos & Motor Vehicles",
            "subcategory":"Auto Supplies",
            "type":"Retail Goods"
        },
        {
            "category":"Retail",
            "subcategory":"Auto Repair",
            "type":"Services"
        }
    ],
    "sg:phone":"+44 23 9250 2931",
    "sg:postcode":"PO12 3HW",
    "sg:province":"Hampshire",
    "sg:tags":[
        "modification",
        "car",
        "part",
        "garage",
        "accessory"
    ],
    "wof:name":"Forton Tyres Specialist",
    "wof:placetype":"venue"
},
  "geometry": {"coordinates":[-1.147504,50.802998],"type":"Point"}
}