{
  "type": "Feature",
  "properties": {
    "iso:country":"GB",
    "sg:address":"10 Queens Road",
    "sg:city":"Paignton",
    "sg:classifiers":[
        {
            "category":"Travel",
            "subcategory":"Hotels & Motels",
            "type":"Entertainment"
        }
    ],
    "sg:phone":"+44 1803 663499",
    "sg:postcode":"TQ4 6AT",
    "sg:province":"Devon",
    "wof:name":"The Sundale Hotel",
    "wof:placetype":"venue"
},
  "geometry": {"coordinates":[-3.5622329712,50.4333457947],"type":"Point"}
}