{
  "type": "Feature",
  "properties": {
    "addr:full":"Babraham Road, Sawston Cambridge Cambridgeshire CB2 4LJ",
    "addr:postcode":"cb2 4lj",
    "addr:street":"Babraham Road",
    "iso:country":"GB",
    "sg:address":"Babraham Road, Sawston",
    "sg:city":"Cambridge",
    "sg:classifiers":[
        {
            "category":"Building & Trades",
            "subcategory":"Construction",
            "type":"Services"
        }
    ],
    "sg:phone":"+44 1223 836611",
    "sg:postcode":"CB2 4LJ",
    "sg:province":"Cambridgeshire",
    "sg:tags":[
        "builder"
    ],
    "wof:name":"Sindall Ltd.",
    "wof:placetype":"venue"
},
  "geometry": {"coordinates":[0.158822,52.1666259766],"type":"Point"}
}