{
  "type": "Feature",
  "properties": {
    "addr:full":"4-8 South Parade Bath Somerset BA2 4AB",
    "addr:housenumber":"4-8",
    "addr:postcode":"somerset ba2 4ab",
    "addr:street":"South Parade",
    "iso:country":"GB",
    "sg:address":"4-8 South Parade",
    "sg:city":"Bath",
    "sg:classifiers":[
        {
            "category":"Travel",
            "subcategory":"Hotels & Motels",
            "type":"Entertainment"
        },
        {
            "category":"Restaurant",
            "type":"Food & Drink"
        }
    ],
    "sg:phone":"+44 808 144 9494",
    "sg:postcode":"BA2 4AB",
    "sg:province":"Somerset",
    "sg:tags":[
        "-",
        "english"
    ],
    "wof:name":"Pratt's Hotel",
    "wof:placetype":"venue"
},
  "geometry": {"coordinates":[-2.3562140465,51.3799667358],"type":"Point"}
}