{
  "type": "Feature",
  "properties": {
    "addr:full":"100 Lenthay Road Sherborne Dorset DT9 6AG",
    "addr:housenumber":"100",
    "addr:postcode":"dt9 6ag",
    "addr:street":"Lenthay Road",
    "iso:country":"GB",
    "sg:address":"100 Lenthay Road",
    "sg:city":"Sherborne",
    "sg:classifiers":[
        {
            "category":"Retail",
            "subcategory":"Funeral Services",
            "type":"Services"
        }
    ],
    "sg:phone":"+44 1935 812647",
    "sg:postcode":"DT9 6AG",
    "sg:province":"Dorset",
    "sg:tags":[
        "director",
        "cemetery",
        "crematorium"
    ],
    "wof:name":"W S Brister & Son",
    "wof:placetype":"venue"
},
  "geometry": {"coordinates":[-2.5301389694,50.9399986267],"type":"Point"}
}