{
  "type": "Feature",
  "properties": {
    "iso:country":"GB",
    "sg:address":"25 Duke Street",
    "sg:city":"Deal",
    "sg:classifiers":[
        {
            "category":"Personal",
            "subcategory":"Beauty Salon",
            "type":"Services"
        }
    ],
    "sg:phone":"+44 1304 363829",
    "sg:postcode":"CT14 6DS",
    "sg:province":"Kent",
    "sg:tags":[
        "unisex",
        "hairdresser"
    ],
    "wof:name":"Hairoics",
    "wof:placetype":"venue"
},
  "geometry": {"coordinates":[1.4009649754,51.2270927429],"type":"Point"}
}