{
  "type": "Feature",
  "properties": {
    "addr:full":"10 High Street Kirriemuir Angus DD8 4EY",
    "addr:housenumber":"10",
    "addr:postcode":"dd8 4ey",
    "addr:street":"High Street",
    "iso:country":"GB",
    "sg:address":"10 High Street",
    "sg:city":"Kirriemuir",
    "sg:classifiers":[
        {
            "category":"Fast Food",
            "type":"Food & Drink"
        },
        {
            "category":"Restaurant",
            "type":"Food & Drink"
        }
    ],
    "sg:postcode":"DD8 4EY",
    "sg:province":"Angus",
    "sg:tags":[
        "away",
        "take"
    ],
    "wof:name":"Trotters Gift & Coffee Shop",
    "wof:placetype":"venue"
},
  "geometry": {"coordinates":[-3.0044488907,56.6734085083],"type":"Point"}
}