{
  "type": "Feature",
  "properties": {
    "addr:full":"Carlton Works, Savile Park Road Halifax West Yorkshire HX1 2EN",
    "addr:postcode":"hx1 2en",
    "addr:street":"Savile Park Road",
    "iso:country":"GB",
    "sg:address":"Carlton Works, Savile Park Road",
    "sg:city":"Halifax",
    "sg:classifiers":[
        {
            "category":"Professional",
            "subcategory":"Printing & Photocopies",
            "type":"Services"
        }
    ],
    "sg:phone":"+44 1422 353239",
    "sg:postcode":"HX1 2EN",
    "sg:province":"West Yorkshire",
    "sg:tags":[
        "printer"
    ],
    "wof:name":"Pickles Printing Co. Ltd.",
    "wof:placetype":"venue"
},
  "geometry": {"coordinates":[-1.864649,53.721142],"type":"Point"}
}