{
  "type": "Feature",
  "properties": {
    "iso:country":"GB",
    "sg:address":"7 Childwall Parade",
    "sg:city":"Liverpool",
    "sg:classifiers":[
        {
            "category":"Food & Beverages",
            "subcategory":"Candy",
            "type":"Retail Goods"
        }
    ],
    "sg:postcode":"L14 6TT",
    "sg:province":"Merseyside",
    "sg:tags":[
        "confectioner"
    ],
    "wof:name":"SAYERS CONFECTIONERS LTD",
    "wof:placetype":"venue"
},
  "geometry": {"coordinates":[-2.872751,53.410107],"type":"Point"}
}