{
  "type": "Feature",
  "properties": {
    "addr:full":"9 Duke Street Glasgow Glasgow City G4 0UL",
    "addr:housenumber":"9",
    "addr:postcode":"g4 0ul",
    "addr:street":"Duke Street",
    "iso:country":"GB",
    "sg:address":"9 Duke Street",
    "sg:city":"Glasgow",
    "sg:classifiers":[
        {
            "category":"Building & Trades",
            "subcategory":"Construction",
            "type":"Services"
        }
    ],
    "sg:phone":"+44 141 552 4422",
    "sg:postcode":"G4 0UL",
    "sg:province":"Glasgow City",
    "sg:tags":[
        "roofing"
    ],
    "wof:name":"Euroscot Construction Ltd.",
    "wof:placetype":"venue"
},
  "geometry": {"coordinates":[-4.2392950058,55.8604049683],"type":"Point"}
}