{
  "type": "Feature",
  "properties": {
    "addr:full":"7 Broadway Building, Boston Road London Greater London W7 3TT",
    "addr:housenumber":"7",
    "addr:postcode":"w7 3tt",
    "addr:street":"Boston Road",
    "iso:country":"GB",
    "sg:address":"7 Broadway Building, Boston Road",
    "sg:city":"London",
    "sg:classifiers":[
        {
            "category":"Building & Trades",
            "subcategory":"Landscaping Services",
            "type":"Services"
        }
    ],
    "sg:postcode":"W7 3TT",
    "sg:province":"Greater London",
    "sg:tags":[
        "gardening"
    ],
    "wof:name":"Blair Sports",
    "wof:placetype":"venue"
},
  "geometry": {"coordinates":[-0.337178,51.509289],"type":"Point"}
}