{
  "type": "Feature",
  "properties": {
    "addr:full":"128 Broadway Bexleyheath Kent DA6 7DQ",
    "addr:housenumber":"128",
    "addr:postcode":"da6 7dq",
    "addr:street":"Broadway",
    "iso:country":"GB",
    "sg:address":"128 Broadway",
    "sg:city":"Bexleyheath",
    "sg:classifiers":[
        {
            "category":"Shopping",
            "subcategory":"Clothing, Apparel, & Fashions",
            "type":"Retail Goods"
        }
    ],
    "sg:phone":"+44 20 8303 3277",
    "sg:postcode":"DA6 7DQ",
    "sg:province":"Kent",
    "sg:tags":[
        "shop"
    ],
    "wof:name":"Hollie",
    "wof:placetype":"venue"
},
  "geometry": {"coordinates":[0.1445280015,51.4567184448],"type":"Point"}
}