{
  "type": "Feature",
  "properties": {
    "iso:country":"GB",
    "sg:address":"Newtown Bakery, Trafford Street, Newtown",
    "sg:city":"Chester",
    "sg:classifiers":[
        {
            "category":"Cafe",
            "type":"Food & Drink"
        },
        {
            "category":"Food & Beverages",
            "subcategory":"Bakery",
            "type":"Retail Goods"
        }
    ],
    "sg:phone":"+44 1244 381567",
    "sg:postcode":"CH1 3HP",
    "sg:province":"Cheshire",
    "sg:tags":[
        "shop",
        "tea",
        "baker",
        "room"
    ],
    "wof:name":"P & A Davies (Chester) Ltd.",
    "wof:placetype":"venue"
},
  "geometry": {"coordinates":[-2.887814,53.196224],"type":"Point"}
}