{
  "type": "Feature",
  "properties": {
    "addr:full":"Kennelwood, Kennelwood Lane Hatfield Hertfordshire AL10 0LG",
    "addr:postcode":"al10 0lg",
    "addr:street":"Kennelwood Lane",
    "iso:country":"GB",
    "sg:address":"Kennelwood, Kennelwood Lane",
    "sg:city":"Hatfield",
    "sg:classifiers":[
        {
            "category":"Real Estate",
            "subcategory":"Surveying",
            "type":"Services"
        },
        {
            "category":"Real Estate",
            "subcategory":"Architect",
            "type":"Services"
        }
    ],
    "sg:phone":"+44 1707 262204",
    "sg:postcode":"AL10 0LG",
    "sg:province":"Hertfordshire",
    "sg:tags":[
        "building",
        "surveyor"
    ],
    "wof:name":"Griffiths & Co",
    "wof:placetype":"venue"
},
  "geometry": {"coordinates":[-0.233965,51.761028],"type":"Point"}
}