{
  "type": "Feature",
  "properties": {
    "addr:full":"21 Middle Gate Newark Nottinghamshire NG24 1AG",
    "addr:housenumber":"21",
    "addr:postcode":"ng24 1ag",
    "addr:street":"Middle Gate",
    "iso:country":"GB",
    "sg:address":"21 Middle Gate",
    "sg:city":"Newark",
    "sg:classifiers":[
        {
            "category":"Organizations",
            "subcategory":"Non-profit Organization",
            "type":"Services"
        }
    ],
    "sg:phone":"+44 1636 610841",
    "sg:postcode":"NG24 1AG",
    "sg:province":"Nottinghamshire",
    "sg:tags":[
        "charitable",
        "organisation",
        "voluntary",
        "charity"
    ],
    "wof:name":"British Heart Foundation",
    "wof:placetype":"venue"
},
  "geometry": {"coordinates":[-0.810418,53.076962],"type":"Point"}
}