{
  "type": "Feature",
  "properties": {
    "iso:country":"GB",
    "sg:address":"43 Summerfield Terrace",
    "sg:city":"Aberdeen",
    "sg:classifiers":[
        {
            "category":"Building & Trades",
            "subcategory":"Landscaping Services",
            "type":"Services"
        }
    ],
    "sg:postcode":"AB24 5JE",
    "sg:province":"Aberdeen City",
    "sg:tags":[
        "forestry",
        "tree"
    ],
    "wof:name":"Clear Cut Urban Forestry",
    "wof:placetype":"venue"
},
  "geometry": {"coordinates":[-2.0911099911,57.1516571045],"type":"Point"}
}