{
  "type": "Feature",
  "properties": {
    "addr:full":"Care Of Nasons, Maynard Road, Wincheap Industrial Estate Canterbury Kent CT1 3RH",
    "addr:housenumber":"estate",
    "addr:postcode":"ct1 3rh",
    "addr:street":"Maynard Road Wincheap Industrial",
    "iso:country":"GB",
    "sg:address":"Care Of Nasons, Maynard Road, Wincheap Industrial Estate",
    "sg:city":"Canterbury",
    "sg:classifiers":[
        {
            "category":"Home & Garden",
            "subcategory":"Home Furnishings",
            "type":"Retail Goods"
        }
    ],
    "sg:phone":"+44 1227 761097",
    "sg:postcode":"CT1 3RH",
    "sg:province":"Kent",
    "sg:tags":[
        "furnishers",
        "planner",
        "bedroom"
    ],
    "wof:name":"Hammonds Furniture",
    "wof:placetype":"venue"
},
  "geometry": {"coordinates":[1.070634,51.272449],"type":"Point"}
}