{
  "type": "Feature",
  "properties": {
    "iso:country":"GB",
    "sg:address":"35 Market Square",
    "sg:city":"Duns",
    "sg:classifiers":[
        {
            "category":"Food & Beverages",
            "subcategory":"Fruits & Vegetables",
            "type":"Retail Goods"
        }
    ],
    "sg:postcode":"TD11 3AL",
    "sg:province":"East Lothian",
    "sg:tags":[
        "greengrocer"
    ],
    "wof:name":"Malcolm McDonald",
    "wof:placetype":"venue"
},
  "geometry": {"coordinates":[-2.344606,55.777866],"type":"Point"}
}