{
  "type": "Feature",
  "properties": {
    "addr:full":"The Old Glove Factory, Bristol Rd Sherborne Dorset DT9 4HP",
    "addr:postcode":"dt9 4hp",
    "addr:street":"Bristol Rd",
    "iso:country":"GB",
    "sg:address":"The Old Glove Factory, Bristol Rd",
    "sg:city":"Sherborne",
    "sg:classifiers":[
        {
            "category":"Professional",
            "subcategory":"Employment Agencies",
            "type":"Services"
        }
    ],
    "sg:phone":"+44 1935 816579",
    "sg:postcode":"DT9 4HP",
    "sg:province":"Dorset",
    "sg:tags":[
        "consultant"
    ],
    "wof:name":"Helping Hands",
    "wof:placetype":"venue"
},
  "geometry": {"coordinates":[-2.521574,50.949165],"type":"Point"}
}