{
  "type": "Feature",
  "properties": {
    "addr:full":"3 Madrepore Road Torquay Devon TQ1 1EY",
    "addr:housenumber":"3",
    "addr:postcode":"tq1 1ey",
    "addr:street":"Madrepore Road",
    "iso:country":"GB",
    "sg:address":"3 Madrepore Road",
    "sg:city":"Torquay",
    "sg:classifiers":[
        {
            "category":"Wholesale",
            "subcategory":"Medical Equipment & Supplies",
            "type":"Manufacturing & Wholesale Goods"
        }
    ],
    "sg:phone":"+44 1803 294500",
    "sg:postcode":"TQ1 1EY",
    "sg:province":"Devon",
    "sg:tags":[
        "aid",
        "hearing"
    ],
    "wof:name":"17 Wetherby Gardens (Management)",
    "wof:placetype":"venue"
},
  "geometry": {"coordinates":[-3.526714,50.465462],"type":"Point"}
}