{
  "type": "Feature",
  "properties": {
    "addr:full":"44 Victoria Road, Wilton Salisbury Wiltshire SP2 0DY",
    "addr:housenumber":"44",
    "addr:postcode":"sp2 0dy",
    "addr:street":"Victoria Road",
    "iso:country":"GB",
    "sg:address":"44 Victoria Road, Wilton",
    "sg:city":"Salisbury",
    "sg:classifiers":[
        {
            "category":"Building & Trades",
            "subcategory":"Construction",
            "type":"Services"
        }
    ],
    "sg:phone":"+44 1722 743419",
    "sg:postcode":"SP2 0DY",
    "sg:province":"Wiltshire",
    "sg:tags":[
        "decorator",
        "painter"
    ],
    "wof:name":"Kevin Chubb Painting & Decorating",
    "wof:placetype":"venue"
},
  "geometry": {"coordinates":[-1.8720860481,51.0825119019],"type":"Point"}
}