{
  "type": "Feature",
  "properties": {
    "addr:full":"136 Upper Wortley Rd Leeds West Yorkshire LS12 4JJ",
    "addr:housenumber":"136",
    "addr:postcode":"ls12 4jj",
    "addr:street":"Upper Wortley Rd",
    "iso:country":"GB",
    "sg:address":"136 Upper Wortley Rd",
    "sg:city":"Leeds",
    "sg:classifiers":[
        {
            "category":"Bars & Pubs",
            "type":"Food & Drink"
        }
    ],
    "sg:postcode":"LS12 4JJ",
    "sg:province":"West Yorkshire",
    "sg:tags":[
        "pubs",
        "inn"
    ],
    "wof:name":"Punch Inns (U K) Ltd",
    "wof:placetype":"venue"
},
  "geometry": {"coordinates":[-1.5950609446,53.7842941284],"type":"Point"}
}