{
  "type": "Feature",
  "properties": {
    "addr:full":"Showground Road Bridgwater Somerset TA6 6LQ",
    "addr:postcode":"ta6 6lq",
    "addr:street":"Showground Road",
    "iso:country":"GB",
    "sg:address":"Showground Road",
    "sg:city":"Bridgwater",
    "sg:classifiers":[
        {
            "category":"Freight",
            "type":"Transportation"
        }
    ],
    "sg:phone":"+44 870 000 8353",
    "sg:postcode":"TA6 6LQ",
    "sg:province":"Somerset",
    "sg:tags":[
        "haulage",
        "road"
    ],
    "wof:name":"Langdon Group Ltd.",
    "wof:placetype":"venue"
},
  "geometry": {"coordinates":[-2.994799,51.112419],"type":"Point"}
}