{
  "type": "Feature",
  "properties": {
    "addr:full":"78 Peel Lane Heywood Lancashire OL10 4UD",
    "addr:housenumber":"78",
    "addr:postcode":"ol10 4ud",
    "addr:street":"Peel Lane",
    "iso:country":"GB",
    "sg:address":"78 Peel Lane",
    "sg:city":"Heywood",
    "sg:classifiers":[
        {
            "category":"Bars & Pubs",
            "type":"Food & Drink"
        }
    ],
    "sg:phone":"+44 1706 369176",
    "sg:postcode":"OL10 4UD",
    "sg:province":"Lancashire",
    "sg:tags":[
        "pubs",
        "inn"
    ],
    "wof:name":"The Oddfellows Arms",
    "wof:placetype":"venue"
},
  "geometry": {"coordinates":[-2.2269539833,53.6002235413],"type":"Point"}
}