{
  "type": "Feature",
  "properties": {
    "addr:full":"50 King Street King's Lynn Norfolk PE30 1ES",
    "addr:housenumber":"50",
    "addr:postcode":"pe30 1es",
    "addr:street":"King Street",
    "iso:country":"GB",
    "sg:address":"50 King Street",
    "sg:city":"King's Lynn",
    "sg:classifiers":[
        {
            "category":"Banks & Credit Unions",
            "subcategory":"Bank",
            "type":"Services"
        }
    ],
    "sg:phone":"+44 1553 770102",
    "sg:postcode":"PE30 1ES",
    "sg:province":"Norfolk",
    "sg:tags":[
        "broker",
        "mortgage"
    ],
    "wof:name":"The Mortgage Bureau",
    "wof:placetype":"venue"
},
  "geometry": {"coordinates":[0.3940559924,52.7556915283],"type":"Point"}
}