{
  "type": "Feature",
  "properties": {
    "addr:full":"16-20 North Street, Bridgetown Cannock Staffordshire WS11 3BA",
    "addr:housenumber":"16-20",
    "addr:postcode":"ws11 3ba",
    "addr:street":"North Street",
    "iso:country":"GB",
    "sg:address":"16-20 North Street, Bridgetown",
    "sg:city":"Cannock",
    "sg:classifiers":[
        {
            "category":"Wholesale",
            "subcategory":"Toys & Hobbies",
            "type":"Manufacturing & Wholesale Goods"
        }
    ],
    "sg:phone":"+44 1543 577567",
    "sg:postcode":"WS11 3BA",
    "sg:province":"Staffordshire",
    "sg:tags":[
        "balloon",
        "novelty"
    ],
    "wof:name":"Balloons Beautiful Balloons",
    "wof:placetype":"venue"
},
  "geometry": {"coordinates":[-2.031475,52.675087],"type":"Point"}
}