{
  "type": "Feature",
  "properties": {
    "iso:country":"GB",
    "sg:address":"Crusader House, 12 St Stevens Street",
    "sg:city":"Bristol",
    "sg:classifiers":[
        {
            "category":"Sports & Exercise",
            "subcategory":"Playing Field",
            "type":"Entertainment"
        }
    ],
    "sg:postcode":"BS1 1EL",
    "sg:province":"City of Bristol",
    "sg:tags":[
        "transmission",
        "power"
    ],
    "wof:name":"Quantek Engineering Ltd.",
    "wof:placetype":"venue"
},
  "geometry": {"coordinates":[-2.596314,51.454021],"type":"Point"}
}