{
  "type": "Feature",
  "properties": {
    "iso:country":"GB",
    "sg:address":"27 Storey Street",
    "sg:city":"Hemel Hempstead",
    "sg:classifiers":[
        {
            "category":"Building & Trades",
            "subcategory":"Cleaning & Sanitation",
            "type":"Services"
        }
    ],
    "sg:phone":"+44 1442 213669",
    "sg:postcode":"HP3 9SG",
    "sg:province":"Hertfordshire",
    "sg:tags":[
        "commercial",
        "sweep",
        "chimney"
    ],
    "wof:name":"T P Whelton",
    "wof:placetype":"venue"
},
  "geometry": {"coordinates":[-0.471462,51.737736],"type":"Point"}
}