{
  "type": "Feature",
  "properties": {
    "iso:country":"GB",
    "sg:address":"331 Jockey Road",
    "sg:city":"Sutton Coldfield",
    "sg:classifiers":[
        {
            "category":"Professional",
            "subcategory":"Lawyer & Legal Services",
            "type":"Services"
        }
    ],
    "sg:phone":"+44 121 355 5516",
    "sg:postcode":"B73 5XE",
    "sg:province":"West Midlands",
    "sg:tags":[
        "solicitor"
    ],
    "wof:name":"Woollaston's Solicitors",
    "wof:placetype":"venue"
},
  "geometry": {"coordinates":[-1.845932,52.54977],"type":"Point"}
}