{
  "type": "Feature",
  "properties": {
    "iso:country":"GB",
    "sg:address":"Church Lane, Eastern Green",
    "sg:city":"Coventry",
    "sg:classifiers":[
        {
            "category":"Place Of Worship",
            "type":"Public Place"
        },
        {
            "category":"Organizations",
            "subcategory":"Non-profit Organization",
            "type":"Services"
        }
    ],
    "sg:phone":"+44 24 7642 2856",
    "sg:postcode":"CV5 7BX",
    "sg:province":"West Midlands",
    "sg:tags":[
        "charitable",
        "organisation",
        "charity"
    ],
    "wof:name":"St Andrew'S Church",
    "wof:placetype":"venue"
},
  "geometry": {"coordinates":[-1.601129,52.420288],"type":"Point"}
}