{
  "type": "Feature",
  "properties": {
    "iso:country":"GB",
    "sg:address":"Elaine Oddie, Morison Stoneham, 75 Springfield Road",
    "sg:city":"Chelmsford",
    "sg:classifiers":[
        {
            "category":"Banks & Credit Unions",
            "subcategory":"Financial Services",
            "type":"Services"
        }
    ],
    "sg:postcode":"CM2 6JB",
    "sg:province":"Essex",
    "sg:tags":[
        "consultant"
    ],
    "wof:name":"Tymals Investments Ltd",
    "wof:placetype":"venue"
},
  "geometry": {"coordinates":[0.477891,51.731918],"type":"Point"}
}