{
  "type": "Feature",
  "properties": {
    "iso:country":"GB",
    "sg:address":"26-28 Colwyn Av",
    "sg:city":"Colwyn Bay",
    "sg:classifiers":[
        {
            "category":"Retail",
            "subcategory":"Repair Shop",
            "type":"Services"
        }
    ],
    "sg:phone":"+44 1492 546579",
    "sg:postcode":"LL28 4RB",
    "sg:province":"Conwy",
    "sg:tags":[
        "upholsterer"
    ],
    "wof:name":"Rhos Upholstery",
    "wof:placetype":"venue"
},
  "geometry": {"coordinates":[-3.740534,53.309746],"type":"Point"}
}