{
  "type": "Feature",
  "properties": {
    "iso:country":"GB",
    "sg:address":"Rear Of",
    "sg:city":"Romford",
    "sg:classifiers":[
        {
            "category":"Sports & Exercise",
            "subcategory":"Tennis Court",
            "type":"Entertainment"
        }
    ],
    "sg:postcode":"RM7 0ES",
    "sg:province":"Essex",
    "sg:tags":[
        "breakdown",
        "recovery"
    ],
    "wof:name":"Formula 1 Autos",
    "wof:placetype":"venue"
},
  "geometry": {"coordinates":[0.1582199931,51.5684394836],"type":"Point"}
}