{
  "type": "Feature",
  "properties": {
    "addr:full":"14a Highgate Av Highgate Greater London N6 5SB",
    "addr:housenumber":"14a",
    "addr:postcode":"n6 5sb",
    "addr:street":"Highgate Av Highgate",
    "iso:country":"GB",
    "sg:address":"14a Highgate Av",
    "sg:city":"Highgate",
    "sg:classifiers":[
        {
            "category":"Communications",
            "type":"Services"
        }
    ],
    "sg:phone":"+44 7973 110165",
    "sg:postcode":"N6 5SB",
    "sg:province":"Greater London",
    "sg:tags":[
        "audio-visual"
    ],
    "wof:name":"Roger Wilco Productions",
    "wof:placetype":"venue"
},
  "geometry": {"coordinates":[-0.144544,51.574936],"type":"Point"}
}