{
  "type": "Feature",
  "properties": {
    "iso:country":"GB",
    "sg:address":"118 Collier Row Road",
    "sg:city":"Romford",
    "sg:classifiers":[
        {
            "category":"Professional",
            "subcategory":"Detective & Security Services",
            "type":"Services"
        }
    ],
    "sg:phone":"+44 1708 706740",
    "sg:postcode":"RM5 2BB",
    "sg:province":"Essex",
    "sg:tags":[
        "equipment"
    ],
    "wof:name":"Millennium Surveillance Systems Ltd.",
    "wof:placetype":"venue"
},
  "geometry": {"coordinates":[0.156937,51.598068],"type":"Point"}
}