{
  "type": "Feature",
  "properties": {
    "iso:country":"GB",
    "sg:address":"5 Church Street, Orrell",
    "sg:city":"Wigan",
    "sg:classifiers":[
        {
            "category":"Food & Beverages",
            "subcategory":"Bakery",
            "type":"Retail Goods"
        }
    ],
    "sg:phone":"+44 1695 625766",
    "sg:postcode":"WN5 8TG",
    "sg:province":"Lancashire",
    "sg:tags":[
        "baker"
    ],
    "wof:name":"Enfield Traditional Bakery",
    "wof:placetype":"venue"
},
  "geometry": {"coordinates":[-2.711842,53.53326],"type":"Point"}
}