{
  "type": "Feature",
  "properties": {
    "addr:full":"41 Abbott Rd Didcot Oxfordshire OX11 8JB",
    "addr:housenumber":"41",
    "addr:postcode":"ox11 8jb",
    "addr:street":"Abbott Rd",
    "iso:country":"GB",
    "sg:address":"41 Abbott Rd",
    "sg:city":"Didcot",
    "sg:classifiers":[
        {
            "category":"Professional",
            "subcategory":"Art Services",
            "type":"Services"
        },
        {
            "category":"Building & Trades",
            "subcategory":"Construction",
            "type":"Services"
        }
    ],
    "sg:phone":"+44 1235 815768",
    "sg:postcode":"OX11 8JB",
    "sg:province":"Oxfordshire",
    "sg:tags":[
        "decorator",
        "painter"
    ],
    "wof:name":"M Roberts",
    "wof:placetype":"venue"
},
  "geometry": {"coordinates":[-1.245526,51.599655],"type":"Point"}
}