{
  "type": "Feature",
  "properties": {
    "addr:full":"40 London Rd Croydon Surrey CR0 2TA",
    "addr:housenumber":"40",
    "addr:postcode":"cr0 2ta",
    "addr:street":"London Rd",
    "iso:country":"GB",
    "sg:address":"40 London Rd",
    "sg:city":"Croydon",
    "sg:classifiers":[
        {
            "category":"Shopping",
            "subcategory":"Stationery & Office Supplies",
            "type":"Retail Goods"
        }
    ],
    "sg:phone":"+44 20 8680 3535",
    "sg:postcode":"CR0 2TA",
    "sg:province":"Surrey",
    "wof:name":"Unikob",
    "wof:placetype":"venue"
},
  "geometry": {"coordinates":[-0.1042290032,51.3799552917],"type":"Point"}
}