{
  "type": "Feature",
  "properties": {
    "iso:country":"GB",
    "sg:address":"Silvertonhill Avenue",
    "sg:city":"Hamilton",
    "sg:classifiers":[
        {
            "category":"Education",
            "subcategory":"School",
            "type":"Public Place"
        },
        {
            "category":"Government",
            "subcategory":"Office",
            "type":"Public Place"
        }
    ],
    "sg:phone":"+44 1698 282929",
    "sg:postcode":"ML3 7NT",
    "sg:province":"South Lanarkshire",
    "sg:tags":[
        "local",
        "authority"
    ],
    "wof:name":"Chatelherault Primary School",
    "wof:placetype":"venue"
},
  "geometry": {"coordinates":[-4.034678,55.770573],"type":"Point"}
}