{
  "type": "Feature",
  "properties": {
    "iso:country":"GB",
    "sg:address":"180 Great Western Street",
    "sg:city":"Manchester",
    "sg:classifiers":[
        {
            "category":"Fast Food",
            "type":"Food & Drink"
        }
    ],
    "sg:phone":"+44 161 226 6407",
    "sg:postcode":"M14 4LH",
    "sg:province":"Greater Manchester",
    "sg:tags":[
        "away",
        "take"
    ],
    "wof:name":"Alvinos",
    "wof:placetype":"venue"
},
  "geometry": {"coordinates":[-2.239713,53.456097],"type":"Point"}
}