{
  "type": "Feature",
  "properties": {
    "iso:country":"GB",
    "sg:address":"Avening Park, West End, Avening",
    "sg:city":"Tetbury",
    "sg:classifiers":[
        {
            "category":"Personal",
            "type":"Services"
        }
    ],
    "sg:postcode":"GL8 8NE",
    "sg:province":"Gloucestershire",
    "sg:tags":[
        "party",
        "organiser"
    ],
    "wof:name":"Click's Parties Seven Springs",
    "wof:placetype":"venue"
},
  "geometry": {"coordinates":[-2.1609759331,51.6378593445],"type":"Point"}
}