{
  "type": "Feature",
  "properties": {
    "iso:country":"GB",
    "sg:address":"Walton Hospital, Rice Lane",
    "sg:city":"Liverpool",
    "sg:classifiers":[
        {
            "category":"Health Services",
            "subcategory":"Hospital",
            "type":"Services"
        }
    ],
    "sg:phone":"+44 151 525 3611",
    "sg:postcode":"L9 1AE",
    "sg:province":"Merseyside",
    "wof:name":"WLATON HOSPITAL",
    "wof:placetype":"venue"
},
  "geometry": {"coordinates":[-2.961719,53.45541],"type":"Point"}
}