{
  "type": "Feature",
  "properties": {
    "addr:full":"34 Welch Road Hyde Cheshire SK14 4DJ",
    "addr:housenumber":"34",
    "addr:postcode":"sk14 4dj",
    "addr:street":"Welch Road",
    "iso:country":"GB",
    "sg:address":"34 Welch Road",
    "sg:city":"Hyde",
    "sg:classifiers":[
        {
            "category":"Shopping",
            "subcategory":"Pharmacy",
            "type":"Retail Goods"
        }
    ],
    "sg:postcode":"SK14 4DJ",
    "sg:province":"Cheshire",
    "sg:tags":[
        "medicine",
        "therapy"
    ],
    "wof:name":"J Stores",
    "wof:placetype":"venue"
},
  "geometry": {"coordinates":[-2.0624539852,53.4594802856],"type":"Point"}
}