{
  "type": "Feature",
  "properties": {
    "iso:country":"GB",
    "sg:address":"Sleepezzy, Holt Rd, Little Snoring",
    "sg:city":"Fakenham",
    "sg:classifiers":[
        {
            "category":"Building & Trades",
            "subcategory":"Construction",
            "type":"Services"
        }
    ],
    "sg:phone":"+44 1328 878807",
    "sg:postcode":"NR21 0AY",
    "sg:province":"Norfolk",
    "sg:tags":[
        "builder"
    ],
    "wof:name":"T.M Mace",
    "wof:placetype":"venue"
},
  "geometry": {"coordinates":[0.902604,52.850849],"type":"Point"}
}