{
  "type": "Feature",
  "properties": {
    "addr:full":"65 Main Street Wishaw North Lanarkshire ML2 7AB",
    "addr:housenumber":"65",
    "addr:postcode":"ml2 7ab",
    "addr:street":"Main Street",
    "iso:country":"GB",
    "sg:address":"65 Main Street",
    "sg:city":"Wishaw",
    "sg:classifiers":[
        {
            "category":"Personal",
            "subcategory":"Beauty Salon",
            "type":"Services"
        }
    ],
    "sg:phone":"+44 1698 373666",
    "sg:postcode":"ML2 7AB",
    "sg:province":"North Lanarkshire",
    "sg:tags":[
        "unisex",
        "hairdresser"
    ],
    "wof:name":"Y S Hair Design",
    "wof:placetype":"venue"
},
  "geometry": {"coordinates":[-3.920582056,55.774356842],"type":"Point"}
}