{
  "type": "Feature",
  "properties": {
    "iso:country":"GB",
    "sg:address":"16 Tabor Hill, Coedpoeth",
    "sg:city":"Wrexham",
    "sg:classifiers":[
        {
            "category":"Professional",
            "subcategory":"Printing & Photocopies",
            "type":"Services"
        }
    ],
    "sg:phone":"+44 1978 720882",
    "sg:postcode":"LL11 3RU",
    "sg:province":"Wrexham",
    "sg:tags":[
        "printer"
    ],
    "wof:name":"The Coedpoeth Telecottage",
    "wof:placetype":"venue"
},
  "geometry": {"coordinates":[-3.069621,53.051086],"type":"Point"}
}