{
  "type": "Feature",
  "properties": {
    "addr:full":"Unit 3, Key Business Park, Kingsbury Road Birmingham West Midlands B24 9PT",
    "addr:housenumber":"unit 3",
    "addr:postcode":"b24 9pt",
    "addr:street":"Key Business Park Kingsbury Road",
    "iso:country":"GB",
    "sg:address":"Unit 3, Key Business Park, Kingsbury Road",
    "sg:city":"Birmingham",
    "sg:classifiers":[
        {
            "category":"Shopping",
            "subcategory":"Crafts & Fabrics",
            "type":"Retail Goods"
        }
    ],
    "sg:phone":"+44 121 351 6472",
    "sg:postcode":"B24 9PT",
    "sg:province":"West Midlands",
    "sg:tags":[
        "material",
        "art"
    ],
    "wof:name":"Lp Creative Products Ltd.",
    "wof:placetype":"venue"
},
  "geometry": {"coordinates":[-1.809767,52.51741],"type":"Point"}
}