{
  "type": "Feature",
  "properties": {
    "addr:full":"110 West Bow Edinburgh City of Edinburgh EH1 2HH",
    "addr:housenumber":"110",
    "addr:postcode":"eh1 2hh",
    "addr:street":"West Bow",
    "iso:country":"GB",
    "sg:address":"110 West Bow",
    "sg:city":"Edinburgh",
    "sg:classifiers":[
        {
            "category":"Restaurant",
            "type":"Food & Drink"
        }
    ],
    "sg:phone":"+44 131 225 5028",
    "sg:postcode":"EH1 2HH",
    "sg:province":"City of Edinburgh",
    "wof:name":"Caffe Romano",
    "wof:placetype":"venue"
},
  "geometry": {"coordinates":[-3.1944038868,55.9479293823],"type":"Point"}
}