{
  "type": "Feature",
  "properties": {
    "iso:country":"GB",
    "sg:address":"14 Greystone Avenue",
    "sg:city":"Bognor Regis",
    "sg:classifiers":[
        {
            "category":"Shopping",
            "subcategory":"Catalog Store",
            "type":"Retail Goods"
        }
    ],
    "sg:phone":"+44 1243 867867",
    "sg:postcode":"PO21 5EA",
    "sg:province":"West Sussex",
    "sg:tags":[
        "mail",
        "order"
    ],
    "wof:name":"First Base International",
    "wof:placetype":"venue"
},
  "geometry": {"coordinates":[-0.7005149722,50.8033256531],"type":"Point"}
}