{
  "type": "Feature",
  "properties": {
    "addr:full":"30 Leeds Road Dewsbury West Yorkshire WF12 7BG",
    "addr:housenumber":"30",
    "addr:postcode":"wf12 7bg",
    "addr:street":"Leeds Road",
    "iso:country":"GB",
    "sg:address":"30 Leeds Road",
    "sg:city":"Dewsbury",
    "sg:classifiers":[
        {
            "category":"Social Services",
            "subcategory":"Job Training",
            "type":"Services"
        }
    ],
    "sg:phone":"+44 1924 465655",
    "sg:postcode":"WF12 7BG",
    "sg:province":"West Yorkshire",
    "sg:tags":[
        "draughtsman",
        "drawing"
    ],
    "wof:name":"Steve Berry Steelwork Drawing Services",
    "wof:placetype":"venue"
},
  "geometry": {"coordinates":[-1.6155689955,53.6978187561],"type":"Point"}
}