{
  "type": "Feature",
  "properties": {
    "addr:full":"Unit 19 Tolsons Mill Industrial Estate, Fazeley Tamworth Staffordshire B78 3QB",
    "addr:housenumber":"unit 19",
    "addr:postcode":"b78 3qb",
    "addr:street":"Tolsons Mill Industrial Estate",
    "iso:country":"GB",
    "sg:address":"Unit 19 Tolsons Mill Industrial Estate, Fazeley",
    "sg:city":"Tamworth",
    "sg:classifiers":[
        {
            "category":"Professional",
            "subcategory":"Engineering",
            "type":"Services"
        },
        {
            "category":"Home & Garden",
            "subcategory":"Building Materials",
            "type":"Retail Goods"
        }
    ],
    "sg:postcode":"B78 3QB",
    "sg:province":"Staffordshire",
    "sg:tags":[
        "fencing",
        "precision",
        "engineer"
    ],
    "wof:name":"M P D  Engineering Ltd.",
    "wof:placetype":"venue"
},
  "geometry": {"coordinates":[-1.703699,52.615551],"type":"Point"}
}