{
  "type": "Feature",
  "properties": {
    "iso:country":"GB",
    "sg:address":"The Cloisters, South Street",
    "sg:city":"Wells",
    "sg:classifiers":[
        {
            "category":"Real Estate",
            "subcategory":"Real Estate Services",
            "type":"Services"
        },
        {
            "category":"Professional",
            "subcategory":"Management & Consulting",
            "type":"Services"
        }
    ],
    "sg:phone":"+44 1749 670489",
    "sg:postcode":"BA5 1SA",
    "sg:province":"Somerset",
    "sg:tags":[
        "consultant",
        "business"
    ],
    "wof:name":"BROADLEAF MANAGEMENT SERVICES LTD",
    "wof:placetype":"venue"
},
  "geometry": {"coordinates":[-2.6466879845,51.2065544128],"type":"Point"}
}