{
  "type": "Feature",
  "properties": {
    "iso:country":"GB",
    "sg:address":"2 The Rock",
    "sg:city":"Bury",
    "sg:classifiers":[
        {
            "category":"Real Estate",
            "subcategory":"Real Estate Agent",
            "type":"Services"
        }
    ],
    "sg:phone":"+44 161 764 5024",
    "sg:postcode":"BL9 0NT",
    "sg:province":"Lancashire",
    "wof:name":"Bairstow Eves",
    "wof:placetype":"venue"
},
  "geometry": {"coordinates":[-2.297368,53.593609],"type":"Point"}
}