{
  "type": "Feature",
  "properties": {
    "iso:country":"GB",
    "sg:address":"32a Deansway",
    "sg:city":"Chippenham",
    "sg:classifiers":[
        {
            "category":"Farming",
            "subcategory":"Nursery",
            "type":"Manufacturing & Wholesale Goods"
        }
    ],
    "sg:phone":"+44 1249 462285",
    "sg:postcode":"SN15 1QZ",
    "sg:province":"Wiltshire",
    "sg:tags":[
        "creche"
    ],
    "wof:name":"Nippers Nursery School",
    "wof:placetype":"venue"
},
  "geometry": {"coordinates":[-2.122094,51.469631],"type":"Point"}
}