{
  "type": "Feature",
  "properties": {
    "addr:full":"85 Torrington Avenue Coventry Warwickshire CV4 9AQ",
    "addr:housenumber":"85",
    "addr:postcode":"cv4 9aq",
    "addr:street":"Torrington Avenue",
    "iso:country":"GB",
    "sg:address":"85 Torrington Avenue",
    "sg:city":"Coventry",
    "sg:classifiers":[
        {
            "category":"Bus Charters",
            "type":"Transportation"
        }
    ],
    "sg:phone":"+44 1253 400870",
    "sg:postcode":"CV4 9AQ",
    "sg:province":"Warwickshire",
    "sg:tags":[
        "hire",
        "coach"
    ],
    "wof:name":"D S Minibuses",
    "wof:placetype":"venue"
},
  "geometry": {"coordinates":[-1.55943,52.399025],"type":"Point"}
}