{
  "type": "Feature",
  "properties": {
    "addr:full":"North Moor Lane Sunderland Tyne and Wear SR3 3BD",
    "addr:postcode":"sr3 3bd",
    "addr:street":"North Moor Lane",
    "iso:country":"GB",
    "sg:address":"North Moor Lane",
    "sg:city":"Sunderland",
    "sg:classifiers":[
        {
            "category":"Military Area",
            "subcategory":"Air Force Base",
            "type":"Public Place"
        }
    ],
    "sg:phone":"+44 191 511 0505",
    "sg:postcode":"SR3 3BD",
    "sg:province":"Tyne and Wear",
    "sg:tags":[
        "taxi",
        "hire",
        "private"
    ],
    "wof:name":"Lakeside Taxis",
    "wof:placetype":"venue"
},
  "geometry": {"coordinates":[-1.4242589474,54.8820037842],"type":"Point"}
}