{
  "type": "Feature",
  "properties": {
    "addr:full":"Robincroft Road, Allestree Derby Derbyshire DE22 2GL",
    "addr:postcode":"de22 2gl",
    "addr:street":"Robincroft Road",
    "iso:country":"GB",
    "sg:address":"Robincroft Road, Allestree",
    "sg:city":"Derby",
    "sg:classifiers":[
        {
            "category":"Education",
            "subcategory":"School",
            "type":"Public Place"
        }
    ],
    "sg:phone":"+44 1332 550113",
    "sg:postcode":"DE22 2GL",
    "sg:province":"Derbyshire",
    "sg:tags":[
        "local",
        "authority"
    ],
    "wof:name":"Portway Junior School",
    "wof:placetype":"venue"
},
  "geometry": {"coordinates":[-1.479104,52.95369],"type":"Point"}
}