{
  "type": "Feature",
  "properties": {
    "addr:full":"19 Rowton Grange Road, Chapel-en-le-frith High Peak Cheshire SK23 0LA",
    "addr:housenumber":"19",
    "addr:postcode":"sk23 0la",
    "addr:street":"Rowton Grange Road",
    "iso:country":"GB",
    "sg:address":"19 Rowton Grange Road, Chapel-en-le-frith",
    "sg:city":"High Peak",
    "sg:classifiers":[
        {
            "category":"Real Estate",
            "subcategory":"Surveying",
            "type":"Services"
        },
        {
            "category":"Real Estate",
            "subcategory":"Architect",
            "type":"Services"
        }
    ],
    "sg:postcode":"SK23 0LA",
    "sg:province":"Cheshire",
    "sg:tags":[
        "surveyor",
        "valuer"
    ],
    "wof:name":"Frankland Kirby Associates",
    "wof:placetype":"venue"
},
  "geometry": {"coordinates":[-1.9150730371,53.3208427429],"type":"Point"}
}