{
  "type": "Feature",
  "properties": {
    "addr:full":"6 Sunnybank Road Bolton Lancashire BL1 6EG",
    "addr:housenumber":"6",
    "addr:postcode":"bl1 6eg",
    "addr:street":"Sunnybank Road",
    "iso:country":"GB",
    "sg:address":"6 Sunnybank Road",
    "sg:city":"Bolton",
    "sg:classifiers":[
        {
            "category":"Building & Trades",
            "subcategory":"Cleaning & Sanitation",
            "type":"Services"
        }
    ],
    "sg:postcode":"BL1 6EG",
    "sg:province":"Lancashire",
    "sg:tags":[
        "commercial"
    ],
    "wof:name":"Acorn Gardening Services",
    "wof:placetype":"venue"
},
  "geometry": {"coordinates":[-2.4521789551,53.5906143188],"type":"Point"}
}