{
  "type": "Feature",
  "properties": {
    "iso:country":"GB",
    "sg:address":"Flat 12 St Anns Court, St Anns Lane",
    "sg:city":"Huntingdon",
    "sg:classifiers":[
        {
            "category":"Building & Trades",
            "subcategory":"Cleaning & Sanitation",
            "type":"Services"
        }
    ],
    "sg:postcode":"PE29 2EW",
    "sg:province":"Cambridgeshire",
    "sg:tags":[
        "dry",
        "control",
        "damp",
        "rot"
    ],
    "wof:name":"Thompson Property Preservation",
    "wof:placetype":"venue"
},
  "geometry": {"coordinates":[-0.1893039942,52.3351402283],"type":"Point"}
}