{
  "type": "Feature",
  "properties": {
    "addr:full":"31 Langdale Drive, Low Ackworth Pontefract West Yorkshire WF7 7PX",
    "addr:housenumber":"31",
    "addr:postcode":"wf7 7px",
    "addr:street":"Langdale Drive;West",
    "iso:country":"GB",
    "sg:address":"31 Langdale Drive, Low Ackworth",
    "sg:city":"Pontefract",
    "sg:classifiers":[
        {
            "category":"Building & Trades",
            "subcategory":"Plumbing",
            "type":"Services"
        }
    ],
    "sg:phone":"+44 1977 612099",
    "sg:postcode":"WF7 7PX",
    "sg:province":"West Yorkshire",
    "sg:tags":[
        "central",
        "heating"
    ],
    "wof:name":"Brian Plimmer",
    "wof:placetype":"venue"
},
  "geometry": {"coordinates":[-1.3176130056,53.6505203247],"type":"Point"}
}