{
  "type": "Feature",
  "properties": {
    "iso:country":"GB",
    "sg:address":"5-6 Titan Way, Britannia Enterprise Park",
    "sg:city":"Lichfield",
    "sg:classifiers":[
        {
            "category":"Autos & Motor Vehicles",
            "subcategory":"Auto Supplies",
            "type":"Retail Goods"
        }
    ],
    "sg:phone":"+44 1623 753300",
    "sg:postcode":"WS14 9TT",
    "sg:province":"Staffordshire",
    "sg:tags":[
        "electronics"
    ],
    "wof:name":"Injection Correction U K Ltd.",
    "wof:placetype":"venue"
},
  "geometry": {"coordinates":[-1.796435,52.683914],"type":"Point"}
}