{
  "type": "Feature",
  "properties": {
    "addr:full":"Unit 2 Skyport Drive, Harmondsworth West Drayton Greater London UB7 0LB",
    "addr:housenumber":"unit 2",
    "addr:postcode":"ub7 0lb",
    "addr:street":"Skyport Drive",
    "iso:country":"GB",
    "sg:address":"Unit 2 Skyport Drive, Harmondsworth",
    "sg:city":"West Drayton",
    "sg:classifiers":[
        {
            "category":"Freight",
            "type":"Transportation"
        }
    ],
    "sg:phone":"+44 20 8759 4076",
    "sg:postcode":"UB7 0LB",
    "sg:province":"Greater London",
    "sg:tags":[
        "forwarders"
    ],
    "wof:name":"International Bonded Couriers Inc Ltd.",
    "wof:placetype":"venue"
},
  "geometry": {"coordinates":[-0.477834,51.483746],"type":"Point"}
}