{
  "type": "Feature",
  "properties": {
    "iso:country":"GB",
    "sg:address":"Oasis, Forest Green Road, Holyport",
    "sg:city":"Maidenhead",
    "sg:classifiers":[
        {
            "category":"Building & Trades",
            "subcategory":"Construction",
            "type":"Services"
        }
    ],
    "sg:postcode":"SL6 2NN",
    "sg:province":"Berkshire",
    "sg:tags":[
        "builder"
    ],
    "wof:name":"Nicholas C Bull",
    "wof:placetype":"venue"
},
  "geometry": {"coordinates":[-0.701064,51.498466],"type":"Point"}
}