{
  "type": "Feature",
  "properties": {
    "iso:country":"GB",
    "sg:address":"1 Riverside, Trevenen",
    "sg:city":"Helston",
    "sg:classifiers":[
        {
            "category":"Bus Charters",
            "type":"Transportation"
        }
    ],
    "sg:phone":"+44 1326 574732",
    "sg:postcode":"TR13 0NF",
    "sg:province":"Cornwall",
    "sg:tags":[
        "hire",
        "coach"
    ],
    "wof:name":"Pete's Mini Bus Hire",
    "wof:placetype":"venue"
},
  "geometry": {"coordinates":[-5.266959,50.10582],"type":"Point"}
}