{
  "type": "Feature",
  "properties": {
    "addr:full":"1 High Street, Chasetown, Burntwood Walsall Staffordshire WS7 8QW",
    "addr:housenumber":"1",
    "addr:postcode":"ws7 8qw",
    "addr:street":"High Street",
    "iso:country":"GB",
    "sg:address":"1 High Street, Chasetown, Burntwood",
    "sg:city":"Walsall",
    "sg:classifiers":[
        {
            "category":"Sports & Exercise",
            "subcategory":"Gym",
            "type":"Entertainment"
        }
    ],
    "sg:phone":"+44 1543 675228",
    "sg:postcode":"WS7 8QW",
    "sg:province":"Staffordshire",
    "sg:tags":[
        "fitness",
        "health",
        "centre"
    ],
    "wof:name":"Chasetown Leisure",
    "wof:placetype":"venue"
},
  "geometry": {"coordinates":[-1.9343409538,52.6702575684],"type":"Point"}
}