{
  "type": "Feature",
  "properties": {
    "addr:full":"Medway Pavilion Farthing Corner, Motorway Services Area, M2 Rainham Gillingham Kent ME8 8PQ",
    "addr:postcode":"me8 8pq",
    "addr:street":"Corner",
    "iso:country":"GB",
    "sg:address":"Medway Pavilion Farthing Corner, Motorway Services Area, M2 Rainham",
    "sg:city":"Gillingham",
    "sg:classifiers":[
        {
            "category":"Banks & Credit Unions",
            "subcategory":"Bureau De Change",
            "type":"Services"
        }
    ],
    "sg:phone":"+44 1634 375998",
    "sg:postcode":"ME8 8PQ",
    "sg:province":"Kent",
    "wof:name":"Travellers Co-Operation",
    "wof:placetype":"venue"
},
  "geometry": {"coordinates":[0.61464,51.362019],"type":"Point"}
}