{
  "type": "Feature",
  "properties": {
    "addr:full":"78 Crwys Road Cardiff Cardiff CF24 4NP",
    "addr:housenumber":"78",
    "addr:postcode":"cf24 4np",
    "addr:street":"Crwys Road",
    "iso:country":"GB",
    "sg:address":"78 Crwys Road",
    "sg:city":"Cardiff",
    "sg:classifiers":[
        {
            "category":"Professional",
            "subcategory":"Business Services",
            "type":"Services"
        },
        {
            "category":"Organizations",
            "subcategory":"Non-profit Organization",
            "type":"Services"
        }
    ],
    "sg:phone":"+44 29 2038 7291",
    "sg:postcode":"CF24 4NP",
    "sg:province":"Cardiff",
    "sg:tags":[
        "organisation",
        "agent",
        "charitable",
        "export",
        "import",
        "charity"
    ],
    "wof:name":"MULTI INTERNATIONAL AID",
    "wof:placetype":"venue"
},
  "geometry": {"coordinates":[-3.1790049076,51.4958610535],"type":"Point"}
}