{
  "type": "Feature",
  "properties": {
    "addr:full":"140 Vernon Road, Basford Nottingham Nottinghamshire NG6 0AD",
    "addr:housenumber":"140",
    "addr:postcode":"ng6 0ad",
    "addr:street":"Vernon Road",
    "iso:country":"GB",
    "sg:address":"140 Vernon Road, Basford",
    "sg:city":"Nottingham",
    "sg:classifiers":[
        {
            "category":"Education",
            "subcategory":"Special Training",
            "type":"Public Place"
        }
    ],
    "sg:phone":"+44 115 979 1990",
    "sg:postcode":"NG6 0AD",
    "sg:province":"Nottinghamshire",
    "sg:tags":[
        "product",
        "centre"
    ],
    "wof:name":"The Nottinghamshire Chamber of Commerce & Industry",
    "wof:placetype":"venue"
},
  "geometry": {"coordinates":[-1.1775399446,52.9815711975],"type":"Point"}
}