{
  "type": "Feature",
  "properties": {
    "addr:full":"Whitleys Centre, Bayswater London Greater London W2 4YQ",
    "addr:postcode":"w2 4yq",
    "iso:country":"GB",
    "sg:address":"Whitleys Centre, Bayswater",
    "sg:city":"London",
    "sg:classifiers":[
        {
            "category":"Shopping",
            "subcategory":"Clothing, Apparel, & Fashions",
            "type":"Retail Goods"
        }
    ],
    "sg:phone":"+44 20 7792 3391",
    "sg:postcode":"W2 4YQ",
    "sg:province":"Greater London",
    "sg:tags":[
        "tie",
        "neckwear"
    ],
    "wof:name":"Tie Rack Ltd.",
    "wof:placetype":"venue"
},
  "geometry": {"coordinates":[-0.18734,51.511681],"type":"Point"}
}