{
  "type": "Feature",
  "properties": {
    "iso:country":"GB",
    "sg:address":"62 Leagrave Road",
    "sg:city":"Luton",
    "sg:classifiers":[
        {
            "category":"Cinema",
            "subcategory":"Movie Rental",
            "type":"Entertainment"
        }
    ],
    "sg:phone":"+44 1582 458024",
    "sg:postcode":"LU4 8HZ",
    "sg:province":"Bedfordshire",
    "sg:tags":[
        "video",
        "library"
    ],
    "wof:name":"R K Video",
    "wof:placetype":"venue"
},
  "geometry": {"coordinates":[-0.4305399954,51.8871803284],"type":"Point"}
}