{
  "type": "Feature",
  "properties": {
    "addr:full":"122 Scarborough Rd Bridlington East Riding of Yorkshire YO16 7NU",
    "addr:housenumber":"122",
    "addr:postcode":"yo16 7nu",
    "addr:street":"Scarborough Rd",
    "iso:country":"GB",
    "sg:address":"122 Scarborough Rd",
    "sg:city":"Bridlington",
    "sg:classifiers":[
        {
            "category":"Autos & Motor Vehicles",
            "subcategory":"Automobile Sales",
            "type":"Retail Goods"
        }
    ],
    "sg:phone":"+44 1262 606782",
    "sg:postcode":"YO16 7NU",
    "sg:province":"East Riding of Yorkshire",
    "sg:tags":[
        "commercial"
    ],
    "wof:name":"Watts 4x4 Centre",
    "wof:placetype":"venue"
},
  "geometry": {"coordinates":[-0.2105129957,54.0972061157],"type":"Point"}
}