{
  "type": "Feature",
  "properties": {
    "addr:full":"28 Kent Road Orpington Kent BR5 4AD",
    "addr:housenumber":"28",
    "addr:postcode":"br5 4ad",
    "addr:street":"Kent Road",
    "iso:country":"GB",
    "sg:address":"28 Kent Road",
    "sg:city":"Orpington",
    "sg:classifiers":[
        {
            "category":"Farming",
            "subcategory":"Fish & Marine Products",
            "type":"Manufacturing & Wholesale Goods"
        }
    ],
    "sg:phone":"+44 1689 821023",
    "sg:postcode":"BR5 4AD",
    "sg:province":"Kent",
    "sg:tags":[
        "fishmonger"
    ],
    "wof:name":"Winkles",
    "wof:placetype":"venue"
},
  "geometry": {"coordinates":[0.1118360013,51.3865013123],"type":"Point"}
}