{
  "type": "Feature",
  "properties": {
    "addr:full":"Broad Street, Earls Barton Northampton Northamptonshire NN6 0ND",
    "addr:postcode":"nn6 0nd",
    "addr:street":"Broad Street",
    "iso:country":"GB",
    "sg:address":"Broad Street, Earls Barton",
    "sg:city":"Northampton",
    "sg:classifiers":[
        {
            "category":"Education",
            "subcategory":"Library",
            "type":"Public Place"
        }
    ],
    "sg:phone":"+44 1604 810726",
    "sg:postcode":"NN6 0ND",
    "sg:province":"Northamptonshire",
    "sg:tags":[
        "book"
    ],
    "wof:name":"Earls Barton Library",
    "wof:placetype":"venue"
},
  "geometry": {"coordinates":[-0.751745,52.264809],"type":"Point"}
}