{
  "type": "Feature",
  "properties": {
    "addr:full":"34 Victoria St Merthyr Tydfil Merthyr Tydfil CF47 8BW",
    "addr:housenumber":"34",
    "addr:postcode":"cf47 8bw",
    "addr:street":"Victoria St",
    "iso:country":"GB",
    "sg:address":"34 Victoria St",
    "sg:city":"Merthyr Tydfil",
    "sg:classifiers":[
        {
            "category":"Health Services",
            "subcategory":"Clinic",
            "type":"Services"
        }
    ],
    "sg:phone":"+44 1685 721991",
    "sg:postcode":"CF47 8BW",
    "sg:province":"Merthyr Tydfil",
    "sg:tags":[
        "abuse",
        "drug"
    ],
    "wof:name":"Drugaid",
    "wof:placetype":"venue"
},
  "geometry": {"coordinates":[-3.378882,51.745941],"type":"Point"}
}