{
  "type": "Feature",
  "properties": {
    "iso:country":"GB",
    "sg:address":"16 Bushland Rd",
    "sg:city":"Northampton",
    "sg:classifiers":[
        {
            "category":"Professional",
            "subcategory":"Computer Services",
            "type":"Services"
        }
    ],
    "sg:phone":"+44 1604 787111",
    "sg:postcode":"NN3 2NS",
    "sg:province":"Northamptonshire",
    "sg:tags":[
        "system",
        "software"
    ],
    "wof:name":"D I T UK Ltd",
    "wof:placetype":"venue"
},
  "geometry": {"coordinates":[-0.852981,52.259209],"type":"Point"}
}