{
  "type": "Feature",
  "properties": {
    "iso:country":"GB",
    "sg:address":"391 Roman Road",
    "sg:city":"London",
    "sg:classifiers":[
        {
            "category":"Shopping",
            "subcategory":"Music",
            "type":"Retail Goods"
        }
    ],
    "sg:postcode":"E3 5QS",
    "sg:province":"Greater London",
    "sg:tags":[
        "record",
        "tape",
        "cd"
    ],
    "wof:name":"M Poutton",
    "wof:placetype":"venue"
},
  "geometry": {"coordinates":[-0.037564,51.531544],"type":"Point"}
}