{
  "type": "Feature",
  "properties": {
    "addr:full":"6 Church Street Beaminster Dorset DT8 3AZ",
    "addr:housenumber":"6",
    "addr:postcode":"dt8 3az",
    "addr:street":"Church Street",
    "iso:country":"GB",
    "sg:address":"6 Church Street",
    "sg:city":"Beaminster",
    "sg:classifiers":[
        {
            "category":"Fast Food",
            "type":"Food & Drink"
        },
        {
            "category":"Cafe",
            "type":"Food & Drink"
        }
    ],
    "sg:postcode":"DT8 3AZ",
    "sg:province":"Dorset",
    "sg:tags":[
        "tea",
        "away",
        "room",
        "take"
    ],
    "wof:name":"The Tea Shoppe",
    "wof:placetype":"venue"
},
  "geometry": {"coordinates":[-2.7398939133,50.8088226318],"type":"Point"}
}