{
  "type": "Feature",
  "properties": {
    "addr:full":"Pencaerminau Farm, Llanddewi Velfrey Narberth Carmarthenshire SA67 7NY",
    "addr:housenumber":"velfrey",
    "addr:postcode":"sa67 7ny",
    "iso:country":"GB",
    "sg:address":"Pencaerminau Farm, Llanddewi Velfrey",
    "sg:city":"Narberth",
    "sg:classifiers":[
        {
            "category":"Farming",
            "subcategory":"Farm",
            "type":"Manufacturing & Wholesale Goods"
        }
    ],
    "sg:phone":"+44 1834 860239",
    "sg:postcode":"SA67 7NY",
    "sg:province":"Carmarthenshire",
    "sg:tags":[
        "mixed",
        "crop"
    ],
    "wof:name":"D H S E & M R Morgan",
    "wof:placetype":"venue"
},
  "geometry": {"coordinates":[-4.7442269325,51.8011703491],"type":"Point"}
}