{
  "type": "Feature",
  "properties": {
    "addr:full":"Nelson Ho, 52 The Strand Ryde Isle of Wight PO33 1JD",
    "addr:housenumber":"52",
    "addr:postcode":"po33 1jd",
    "addr:street":"The Strand",
    "iso:country":"GB",
    "sg:address":"Nelson Ho, 52 The Strand",
    "sg:city":"Ryde",
    "sg:classifiers":[
        {
            "category":"Travel",
            "subcategory":"Hotels & Motels",
            "type":"Entertainment"
        }
    ],
    "sg:phone":"+44 1983 565447",
    "sg:postcode":"PO33 1JD",
    "sg:province":"Isle of Wight",
    "sg:tags":[
        "self",
        "catering"
    ],
    "wof:name":"Nelson House Holiday Flatlets",
    "wof:placetype":"venue"
},
  "geometry": {"coordinates":[-1.1686660051,50.7275657654],"type":"Point"}
}