{
  "type": "Feature",
  "properties": {
    "addr:full":"3 Beulah Street Harrogate North Yorkshire HG1 1QQ",
    "addr:housenumber":"3",
    "addr:postcode":"hg1 1qq",
    "addr:street":"Beulah Street",
    "iso:country":"GB",
    "sg:address":"3 Beulah Street",
    "sg:city":"Harrogate",
    "sg:classifiers":[
        {
            "category":"Food & Beverages",
            "subcategory":"Fruits & Vegetables",
            "type":"Retail Goods"
        }
    ],
    "sg:phone":"+44 1423 566546",
    "sg:postcode":"HG1 1QQ",
    "sg:province":"North Yorkshire",
    "sg:tags":[
        "greengrocer"
    ],
    "wof:name":"Lowther Fruit Stores",
    "wof:placetype":"venue"
},
  "geometry": {"coordinates":[-1.538791,53.993462],"type":"Point"}
}