{
  "type": "Feature",
  "properties": {
    "addr:full":"Alston Site, Units 189 Mill Road Rugby Warwickshire CV21 1BD",
    "addr:housenumber":"189",
    "addr:postcode":"cv21 1bd",
    "addr:street":"Mill Road",
    "iso:country":"GB",
    "sg:address":"Alston Site, Units 189 Mill Road",
    "sg:city":"Rugby",
    "sg:classifiers":[
        {
            "category":"Structure",
            "subcategory":"Warehouse",
            "type":"Public Place"
        },
        {
            "category":"Manufacturing",
            "subcategory":"Building Materials",
            "type":"Manufacturing & Wholesale Goods"
        }
    ],
    "sg:phone":"+44 1788 547747",
    "sg:postcode":"CV21 1BD",
    "sg:province":"Warwickshire",
    "sg:tags":[
        "tile",
        "mnfrs"
    ],
    "wof:name":"Langley London Ltd.",
    "wof:placetype":"venue"
},
  "geometry": {"coordinates":[-1.25071,52.380531],"type":"Point"}
}