{
  "type": "Feature",
  "properties": {
    "iso:country":"GB",
    "sg:address":"8 Stablefield Rd",
    "sg:city":"Walton On The Naze",
    "sg:classifiers":[
        {
            "category":"Arts & Performance",
            "subcategory":"Music",
            "type":"Entertainment"
        }
    ],
    "sg:phone":"+44 1255 672591",
    "sg:postcode":"CO14 8UG",
    "sg:province":"Essex",
    "sg:tags":[
        "mobile",
        "disco"
    ],
    "wof:name":"Beatbox",
    "wof:placetype":"venue"
},
  "geometry": {"coordinates":[1.2525000572,51.8467178345],"type":"Point"}
}