{
  "type": "Feature",
  "properties": {
    "iso:country":"GB",
    "sg:address":"69 Reddish Lane, Gorton",
    "sg:city":"Manchester",
    "sg:classifiers":[
        {
            "category":"Insurance",
            "subcategory":"Insurance Agent",
            "type":"Services"
        }
    ],
    "sg:phone":"+44 161 231 3434",
    "sg:postcode":"M18 7JH",
    "sg:province":"Greater Manchester",
    "wof:name":"Two Cities Insurance Services Ltd.",
    "wof:placetype":"venue"
},
  "geometry": {"coordinates":[-2.159172,53.455982],"type":"Point"}
}