{
  "type": "Feature",
  "properties": {
    "iso:country":"GB",
    "sg:address":"46 Richmond St",
    "sg:city":"Aberdeen",
    "sg:classifiers":[
        {
            "category":"Personal",
            "type":"Services"
        }
    ],
    "sg:phone":"+44 1224 622600",
    "sg:postcode":"AB25 2TR",
    "sg:province":"Aberdeen City",
    "sg:tags":[
        "stress",
        "management"
    ],
    "wof:name":"Murray Thomson Associates",
    "wof:placetype":"venue"
},
  "geometry": {"coordinates":[-2.113962,57.150143],"type":"Point"}
}