{
  "type": "Feature",
  "properties": {
    "addr:full":"Navigation Drive, Hurst Business Park Brierley Hill West Midlands DY5 1UT",
    "addr:postcode":"dy5 1ut",
    "addr:street":"Navigation Drive Hurst Business Park Brierley Hill",
    "iso:country":"GB",
    "sg:address":"Navigation Drive, Hurst Business Park",
    "sg:city":"Brierley Hill",
    "sg:classifiers":[
        {
            "category":"Government",
            "subcategory":"Fire Station",
            "type":"Public Place"
        }
    ],
    "sg:phone":"+44 1384 482532",
    "sg:postcode":"DY5 1UT",
    "sg:province":"West Midlands",
    "sg:tags":[
        "security"
    ],
    "wof:name":"G B Fire Ltd.",
    "wof:placetype":"venue"
},
  "geometry": {"coordinates":[-2.102929,52.487309],"type":"Point"}
}