{
  "type": "Feature",
  "properties": {
    "addr:full":"4 Manor Court, Wolviston Billingham Durham TS22 5LS",
    "addr:housenumber":"4",
    "addr:postcode":"ts22 5ls",
    "addr:street":"Manor Court",
    "iso:country":"GB",
    "sg:address":"4 Manor Court, Wolviston",
    "sg:city":"Billingham",
    "sg:classifiers":[
        {
            "category":"Shopping",
            "type":"Retail Goods"
        }
    ],
    "sg:phone":"+44 1740 644233",
    "sg:postcode":"TS22 5LS",
    "sg:province":"Durham",
    "sg:tags":[
        "med",
        "scientific",
        "apparatus"
    ],
    "wof:name":"Thelpe Instruments",
    "wof:placetype":"venue"
},
  "geometry": {"coordinates":[-1.3016380072,54.6220016479],"type":"Point"}
}