{
  "type": "Feature",
  "properties": {
    "iso:country":"GB",
    "sg:address":"35 High Street",
    "sg:city":"Totnes",
    "sg:classifiers":[
        {
            "category":"Food & Beverages",
            "subcategory":"Specialty",
            "type":"Retail Goods"
        },
        {
            "category":"Food & Beverages",
            "subcategory":"Bakery",
            "type":"Retail Goods"
        }
    ],
    "sg:phone":"+44 1803 862526",
    "sg:postcode":"TQ9 5NP",
    "sg:province":"Devon",
    "sg:tags":[
        "baker",
        "health",
        "product"
    ],
    "wof:name":"Seeds Bakery",
    "wof:placetype":"venue"
},
  "geometry": {"coordinates":[-3.6888120174,50.4317131042],"type":"Point"}
}