{
  "type": "Feature",
  "properties": {
    "iso:country":"GB",
    "sg:address":"24 Upper Sheffield Rd",
    "sg:city":"Barnsley",
    "sg:classifiers":[
        {
            "category":"Building & Trades",
            "subcategory":"Construction",
            "type":"Services"
        }
    ],
    "sg:phone":"+44 1226 770535",
    "sg:postcode":"S70 4PN",
    "sg:province":"South Yorkshire",
    "sg:tags":[
        "builder"
    ],
    "wof:name":"Wage Construction Ltd",
    "wof:placetype":"venue"
},
  "geometry": {"coordinates":[-1.471083,53.542561],"type":"Point"}
}