{
  "type": "Feature",
  "properties": {
    "iso:country":"GB",
    "sg:address":"Speyside Care Home, 11 Conval Drive",
    "sg:city":"Aberlour",
    "sg:classifiers":[
        {
            "category":"Health Services",
            "subcategory":"Nursing And Care Facility",
            "type":"Services"
        },
        {
            "category":"Social Services",
            "subcategory":"Retirement Home",
            "type":"Services"
        }
    ],
    "sg:phone":"+44 1340 871640",
    "sg:postcode":"AB38 9QE",
    "sg:province":"Moray",
    "sg:tags":[
        "residential"
    ],
    "wof:name":"Speyside Residential Care",
    "wof:placetype":"venue"
},
  "geometry": {"coordinates":[-3.2181620598,57.4720649719],"type":"Point"}
}