{
  "type": "Feature",
  "properties": {
    "addr:full":"6 Parkfield Drive, Queensbury Bradford West Yorkshire BD13 2HH",
    "addr:housenumber":"6",
    "addr:postcode":"bd13 2hh",
    "addr:street":"Parkfield Drive;Bradford West",
    "iso:country":"GB",
    "sg:address":"6 Parkfield Drive, Queensbury",
    "sg:city":"Bradford",
    "sg:classifiers":[
        {
            "category":"Shopping",
            "subcategory":"Gifts & Souvenirs",
            "type":"Retail Goods"
        }
    ],
    "sg:postcode":"BD13 2HH",
    "sg:province":"West Yorkshire",
    "sg:tags":[
        "giftware"
    ],
    "wof:name":"The Rag Doll Co",
    "wof:placetype":"venue"
},
  "geometry": {"coordinates":[-1.8537399769,53.7673721313],"type":"Point"}
}