{
  "type": "Feature",
  "properties": {
    "iso:country":"GB",
    "sg:address":"15 Halifax Rd",
    "sg:city":"Dewsbury",
    "sg:classifiers":[
        {
            "category":"Health Services",
            "subcategory":"Dentist",
            "type":"Services"
        }
    ],
    "sg:phone":"+44 1924 455973",
    "sg:postcode":"WF13 2JH",
    "sg:province":"West Yorkshire",
    "sg:tags":[
        "technician",
        "dental"
    ],
    "wof:name":"P.R Boulton",
    "wof:placetype":"venue"
},
  "geometry": {"coordinates":[-1.6330579519,53.6943054199],"type":"Point"}
}