{
  "type": "Feature",
  "properties": {
    "iso:country":"GB",
    "sg:address":"High Street, Boston Spa",
    "sg:city":"Wetherby",
    "sg:classifiers":[
        {
            "category":"Education",
            "subcategory":"Library",
            "type":"Public Place"
        }
    ],
    "sg:phone":"+44 1937 845239",
    "sg:postcode":"LS23 6BH",
    "sg:province":"West Yorkshire",
    "sg:tags":[
        "book"
    ],
    "wof:name":"Boston Spa Library",
    "wof:placetype":"venue"
},
  "geometry": {"coordinates":[-1.352283,53.906788],"type":"Point"}
}