{
  "type": "Feature",
  "properties": {
    "addr:full":"Dental Surgery, Orme Ho, 13 Maiden La Stamford Cambridgeshire PE9 2AZ",
    "addr:housenumber":"13",
    "addr:postcode":"pe9 2az",
    "addr:street":"Orme;Maiden La Stamford",
    "iso:country":"GB",
    "sg:address":"Dental Surgery, Orme Ho, 13 Maiden La",
    "sg:city":"Stamford",
    "sg:classifiers":[
        {
            "category":"Health Services",
            "subcategory":"Dentist",
            "type":"Services"
        }
    ],
    "sg:phone":"+44 1780 762182",
    "sg:postcode":"PE9 2AZ",
    "sg:province":"Cambridgeshire",
    "wof:name":"M G Coup",
    "wof:placetype":"venue"
},
  "geometry": {"coordinates":[-0.48029,52.652084],"type":"Point"}
}