{
  "type": "Feature",
  "properties": {
    "addr:full":"41 Foxon Lane Caterham Surrey CR3 5SG",
    "addr:housenumber":"41",
    "addr:postcode":"cr3 5sg",
    "addr:street":"Foxon Lane",
    "iso:country":"GB",
    "sg:address":"41 Foxon Lane",
    "sg:city":"Caterham",
    "sg:classifiers":[
        {
            "category":"Taxi",
            "type":"Transportation"
        }
    ],
    "sg:phone":"+44 1883 345544",
    "sg:postcode":"CR3 5SG",
    "sg:province":"Surrey",
    "sg:tags":[
        "mini",
        "cab"
    ],
    "wof:name":"D C Taxi Services",
    "wof:placetype":"venue"
},
  "geometry": {"coordinates":[-0.093833,51.291321],"type":"Point"}
}