{
  "type": "Feature",
  "properties": {
    "addr:full":"6a Parliament St Harrogate North Yorkshire HG1 2QZ",
    "addr:housenumber":"6a",
    "addr:postcode":"hg1 2qz",
    "addr:street":"Parliament St",
    "iso:country":"GB",
    "sg:address":"6a Parliament St",
    "sg:city":"Harrogate",
    "sg:classifiers":[
        {
            "category":"Shopping",
            "subcategory":"Baby Store",
            "type":"Retail Goods"
        }
    ],
    "sg:phone":"+44 1423 560957",
    "sg:postcode":"HG1 2QZ",
    "sg:province":"North Yorkshire",
    "sg:tags":[
        "babywear",
        "childrens"
    ],
    "wof:name":"E & C Maturi",
    "wof:placetype":"venue"
},
  "geometry": {"coordinates":[-1.5425950289,53.9933624268],"type":"Point"}
}