{
  "type": "Feature",
  "properties": {
    "addr:full":"65 Newbottle Street Houghton-le-spring Durham DH4 4AR",
    "addr:housenumber":"65",
    "addr:postcode":"dh4 4ar",
    "addr:street":"Newbottle Street",
    "iso:country":"GB",
    "sg:address":"65 Newbottle Street",
    "sg:city":"Houghton-le-spring",
    "sg:classifiers":[
        {
            "category":"Food & Beverages",
            "subcategory":"Fruits & Vegetables",
            "type":"Retail Goods"
        }
    ],
    "sg:phone":"+44 191 584 3160",
    "sg:postcode":"DH4 4AR",
    "sg:province":"Durham",
    "sg:tags":[
        "greengrocer"
    ],
    "wof:name":"D Johnston",
    "wof:placetype":"venue"
},
  "geometry": {"coordinates":[-1.471748,54.844982],"type":"Point"}
}