{
  "type": "Feature",
  "properties": {
    "addr:full":"84 Grange Cres Sheffield Derbyshire S11 8AZ",
    "addr:housenumber":"84",
    "addr:postcode":"s11 8az",
    "addr:street":"Grange Cres",
    "iso:country":"GB",
    "sg:address":"84 Grange Cres",
    "sg:city":"Sheffield",
    "sg:classifiers":[
        {
            "category":"Professional",
            "subcategory":"Accounting & Tax Preparation",
            "type":"Services"
        }
    ],
    "sg:postcode":"S11 8AZ",
    "sg:province":"Derbyshire",
    "sg:tags":[
        "accountant"
    ],
    "wof:name":"Rodger,J H,",
    "wof:placetype":"venue"
},
  "geometry": {"coordinates":[-1.4867810011,53.3672828674],"type":"Point"}
}