{
  "type": "Feature",
  "properties": {
    "iso:country":"GB",
    "sg:address":"Unit 6 Thornes Office Park, Monckton Road",
    "sg:city":"Wakefield",
    "sg:classifiers":[
        {
            "category":"Professional",
            "type":"Services"
        }
    ],
    "sg:phone":"+44 1924 385476",
    "sg:postcode":"WF2 7AN",
    "sg:province":"West Yorkshire",
    "sg:tags":[
        "shopfitters"
    ],
    "wof:name":"Streamline Store Fitters",
    "wof:placetype":"venue"
},
  "geometry": {"coordinates":[-1.5065079927,53.6669998169],"type":"Point"}
}