{
  "type": "Feature",
  "properties": {
    "addr:full":"11a Miles Lane, Shevington Wigan Lancashire WN6 8EB",
    "addr:housenumber":"11a",
    "addr:postcode":"wn6 8eb",
    "addr:street":"Miles Lane",
    "iso:country":"GB",
    "sg:address":"11a Miles Lane, Shevington",
    "sg:city":"Wigan",
    "sg:classifiers":[
        {
            "category":"Professional",
            "subcategory":"Advertising",
            "type":"Services"
        }
    ],
    "sg:phone":"+44 1257 251516",
    "sg:postcode":"WN6 8EB",
    "sg:province":"Lancashire",
    "sg:tags":[
        "agency"
    ],
    "wof:name":"Caseart Ltd.",
    "wof:placetype":"venue"
},
  "geometry": {"coordinates":[-2.6942620277,53.5724983215],"type":"Point"}
}