{
  "type": "Feature",
  "properties": {
    "iso:country":"GB",
    "sg:address":"12 Lullarook Close, Biggin Hill",
    "sg:city":"Westerham",
    "sg:classifiers":[
        {
            "category":"Professional",
            "subcategory":"Management & Consulting",
            "type":"Services"
        }
    ],
    "sg:phone":"+44 1959 574656",
    "sg:postcode":"TN16 3XG",
    "sg:province":"Kent",
    "sg:tags":[
        "consultant",
        "promotion",
        "direct",
        "sale"
    ],
    "wof:name":"Sales Liaison",
    "wof:placetype":"venue"
},
  "geometry": {"coordinates":[0.0223639999,51.3129844666],"type":"Point"}
}