{
  "type": "Feature",
  "properties": {
    "iso:country":"GB",
    "sg:address":"6 High Park Avenue",
    "sg:city":"Hove",
    "sg:classifiers":[
        {
            "category":"Farming",
            "subcategory":"Farm",
            "type":"Manufacturing & Wholesale Goods"
        }
    ],
    "sg:postcode":"BN3 8PE",
    "sg:province":"East Sussex",
    "sg:tags":[
        "agricultural"
    ],
    "wof:name":"J Twigg",
    "wof:placetype":"venue"
},
  "geometry": {"coordinates":[-0.192303,50.850731],"type":"Point"}
}