{
  "type": "Feature",
  "properties": {
    "addr:full":"44 Borough Road Sunderland Tyne and Wear SR1 1PL",
    "addr:housenumber":"44",
    "addr:postcode":"sr1 1pl",
    "addr:street":"Borough Road",
    "iso:country":"GB",
    "sg:address":"44 Borough Road",
    "sg:city":"Sunderland",
    "sg:classifiers":[
        {
            "category":"Autos & Motor Vehicles",
            "subcategory":"Auto Supplies",
            "type":"Retail Goods"
        }
    ],
    "sg:phone":"+44 191 567 5747",
    "sg:postcode":"SR1 1PL",
    "sg:province":"Tyne and Wear",
    "sg:tags":[
        "exhaust",
        "absorber",
        "shock"
    ],
    "wof:name":"Kwik-Fit",
    "wof:placetype":"venue"
},
  "geometry": {"coordinates":[-1.3783160448,54.904548645],"type":"Point"}
}