{
  "type": "Feature",
  "properties": {
    "addr:full":"Town Farm, Hoggeston Buckingham Buckinghamshire MK18 3LQ",
    "addr:housenumber":"hoggeston",
    "addr:postcode":"mk18 3lq",
    "addr:street":"Buckingham",
    "iso:country":"GB",
    "sg:address":"Town Farm, Hoggeston",
    "sg:city":"Buckingham",
    "sg:classifiers":[
        {
            "category":"Farming",
            "subcategory":"Livestock Farm",
            "type":"Manufacturing & Wholesale Goods"
        }
    ],
    "sg:phone":"+44 1296 712140",
    "sg:postcode":"MK18 3LQ",
    "sg:province":"Buckinghamshire",
    "sg:tags":[
        "others"
    ],
    "wof:name":"J B Baylis",
    "wof:placetype":"venue"
},
  "geometry": {"coordinates":[-0.8282189965,51.9180793762],"type":"Point"}
}