{
  "type": "Feature",
  "properties": {
    "iso:country":"GB",
    "sg:address":"P O Box 400",
    "sg:city":"Tarporley",
    "sg:classifiers":[
        {
            "category":"Education",
            "subcategory":"Special Training",
            "type":"Public Place"
        }
    ],
    "sg:phone":"+44 1829 733669",
    "sg:postcode":"CW6 0FW",
    "sg:province":"Cheshire",
    "sg:tags":[
        "product",
        "centre"
    ],
    "wof:name":"Sandstone Ltd.",
    "wof:placetype":"venue"
},
  "geometry": {"coordinates":[-2.69174,53.190395],"type":"Point"}
}