{
  "type": "Feature",
  "properties": {
    "iso:country":"GB",
    "sg:address":"16 Castle Gate",
    "sg:city":"Newark",
    "sg:classifiers":[
        {
            "category":"Health Services",
            "subcategory":"Dentist",
            "type":"Services"
        }
    ],
    "sg:phone":"+44 1636 703349",
    "sg:postcode":"NG24 1BG",
    "sg:province":"Nottinghamshire",
    "wof:name":"Denticare Ltd.",
    "wof:placetype":"venue"
},
  "geometry": {"coordinates":[-0.812584,53.076931],"type":"Point"}
}