{
  "type": "Feature",
  "properties": {
    "addr:full":"333 Burley Road Leeds West Yorkshire LS4 2JJ",
    "addr:housenumber":"333",
    "addr:postcode":"ls4 2jj",
    "addr:street":"Burley Road",
    "iso:country":"GB",
    "sg:address":"333 Burley Road",
    "sg:city":"Leeds",
    "sg:classifiers":[
        {
            "category":"Fast Food",
            "type":"Food & Drink"
        }
    ],
    "sg:phone":"+44 113 275 3583",
    "sg:postcode":"LS4 2JJ",
    "sg:province":"West Yorkshire",
    "sg:tags":[
        "away",
        "take"
    ],
    "wof:name":"The Village Bakery",
    "wof:placetype":"venue"
},
  "geometry": {"coordinates":[-1.5839970112,53.8095054626],"type":"Point"}
}