{
  "type": "Feature",
  "properties": {
    "addr:full":"48-54 Brook Street London Greater London W1K 5DS",
    "addr:housenumber":"48-54",
    "addr:postcode":"w1k 5ds",
    "addr:street":"Brook Street",
    "iso:country":"GB",
    "sg:address":"48-54 Brook Street",
    "sg:city":"London",
    "sg:classifiers":[
        {
            "category":"Sports & Exercise",
            "subcategory":"Tennis Court",
            "type":"Entertainment"
        }
    ],
    "sg:postcode":"W1K 5DS",
    "sg:province":"Greater London",
    "sg:tags":[
        "breakdown",
        "recovery"
    ],
    "wof:name":"Chesterton Education (Red London) Ltd.",
    "wof:placetype":"venue"
},
  "geometry": {"coordinates":[-0.147522,51.512974],"type":"Point"}
}