{
  "type": "Feature",
  "properties": {
    "addr:full":"Barham Farm, Chapel Lane, Combe Martin Ilfracombe Devon EX34 0HJ",
    "addr:postcode":"ex34 0hj",
    "addr:street":"Chapel Lane",
    "iso:country":"GB",
    "sg:address":"Barham Farm, Chapel Lane, Combe Martin",
    "sg:city":"Ilfracombe",
    "sg:classifiers":[
        {
            "category":"Farming",
            "subcategory":"Livestock Farm",
            "type":"Manufacturing & Wholesale Goods"
        }
    ],
    "sg:phone":"+44 1271 883591",
    "sg:postcode":"EX34 0HJ",
    "sg:province":"Devon",
    "sg:tags":[
        "others"
    ],
    "wof:name":"Gordon Duncan",
    "wof:placetype":"venue"
},
  "geometry": {"coordinates":[-4.025965,51.200401],"type":"Point"}
}