{
  "type": "Feature",
  "properties": {
    "iso:country":"GB",
    "sg:address":"Dolau Cottage, Bridge Street",
    "sg:city":"Llandysul",
    "sg:classifiers":[
        {
            "category":"Taxi",
            "type":"Transportation"
        }
    ],
    "sg:phone":"+44 1559 363463",
    "sg:postcode":"SA44 4BA",
    "sg:province":"Carmarthenshire",
    "sg:tags":[
        "mini",
        "cab"
    ],
    "wof:name":"Graham's Taxi & Minibus Hire",
    "wof:placetype":"venue"
},
  "geometry": {"coordinates":[-4.307817,52.044479],"type":"Point"}
}