{
  "type": "Feature",
  "properties": {
    "addr:full":"Main Street, Epperstone Nottingham Nottinghamshire NG14 6AD",
    "addr:postcode":"ng14 6ad",
    "addr:street":"Main Street",
    "iso:country":"GB",
    "sg:address":"Main Street, Epperstone",
    "sg:city":"Nottingham",
    "sg:classifiers":[
        {
            "category":"Government",
            "subcategory":"Post Office",
            "type":"Public Place"
        }
    ],
    "sg:phone":"+44 115 966 4514",
    "sg:postcode":"NG14 6AD",
    "sg:province":"Nottinghamshire",
    "wof:name":"Epperstone Sub Post Office",
    "wof:placetype":"venue"
},
  "geometry": {"coordinates":[-1.029269,53.029499],"type":"Point"}
}