{
  "type": "Feature",
  "properties": {
    "iso:country":"GB",
    "sg:address":"25 Swinton Hall Road, Swinton",
    "sg:city":"Manchester",
    "sg:classifiers":[
        {
            "category":"Home & Garden",
            "subcategory":"Building Materials",
            "type":"Retail Goods"
        },
        {
            "category":"Home & Garden",
            "subcategory":"Furniture",
            "type":"Retail Goods"
        }
    ],
    "sg:phone":"+44 161 728 3561",
    "sg:postcode":"M27 4BL",
    "sg:province":"Greater Manchester",
    "sg:tags":[
        "installers",
        "planner",
        "built-in",
        "fitted",
        "kitchen"
    ],
    "wof:name":"Sharps Bedrooms Ltd",
    "wof:placetype":"venue"
},
  "geometry": {"coordinates":[-2.337869,53.513432],"type":"Point"}
}