{
  "type": "Feature",
  "properties": {
    "addr:full":"The Annexe Day Centre, Stanley Rd Twickenham Greater London TW2 5PZ",
    "addr:postcode":"tw2 5pz",
    "addr:street":"Stanley Rd",
    "iso:country":"GB",
    "sg:address":"The Annexe Day Centre, Stanley Rd",
    "sg:city":"Twickenham",
    "sg:classifiers":[
        {
            "category":"Organizations",
            "subcategory":"Non-profit Organization",
            "type":"Services"
        }
    ],
    "sg:phone":"+44 20 8898 4225",
    "sg:postcode":"TW2 5PZ",
    "sg:province":"Greater London",
    "sg:tags":[
        "organisation",
        "voluntary",
        "charity"
    ],
    "wof:name":"RAID",
    "wof:placetype":"venue"
},
  "geometry": {"coordinates":[-0.35472,51.43932],"type":"Point"}
}