{
  "type": "Feature",
  "properties": {
    "addr:full":"1 Greenhill, Worksworth Matlock Derbyshire DE4 4EN",
    "addr:housenumber":"1",
    "addr:postcode":"de4 4en",
    "addr:street":"Greenhill Worksworth",
    "iso:country":"GB",
    "sg:address":"1 Greenhill, Worksworth",
    "sg:city":"Matlock",
    "sg:classifiers":[
        {
            "category":"Professional",
            "subcategory":"Management & Consulting",
            "type":"Services"
        },
        {
            "category":"Organizations",
            "subcategory":"Community Association",
            "type":"Services"
        }
    ],
    "sg:phone":"+44 1629 824904",
    "sg:postcode":"DE4 4EN",
    "sg:province":"Derbyshire",
    "sg:tags":[
        "organisation",
        "conservation"
    ],
    "wof:name":"Derbyshire Historic Buildings Trust",
    "wof:placetype":"venue"
},
  "geometry": {"coordinates":[-1.595453,53.085129],"type":"Point"}
}