{
  "type": "Feature",
  "properties": {
    "addr:full":"39 Duckworth St Bury Lancashire BL9 6ND",
    "addr:housenumber":"39",
    "addr:postcode":"bl9 6nd",
    "addr:street":"Duckworth St",
    "iso:country":"GB",
    "sg:address":"39 Duckworth St",
    "sg:city":"Bury",
    "sg:classifiers":[
        {
            "category":"Building & Trades",
            "subcategory":"Construction",
            "type":"Services"
        }
    ],
    "sg:postcode":"BL9 6ND",
    "sg:province":"Lancashire",
    "sg:tags":[
        "roofing"
    ],
    "wof:name":"Turner,Glen,",
    "wof:placetype":"venue"
},
  "geometry": {"coordinates":[-2.287774086,53.6040496826],"type":"Point"}
}