{
  "type": "Feature",
  "properties": {
    "iso:country":"GB",
    "sg:address":"U K A E A, Culham Science Centre",
    "sg:city":"Abingdon",
    "sg:classifiers":[
        {
            "category":"Professional",
            "subcategory":"Employment Agencies",
            "type":"Services"
        }
    ],
    "sg:postcode":"OX14 3DB",
    "sg:province":"Oxfordshire",
    "sg:tags":[
        "consultant"
    ],
    "wof:name":"Compustaff Ltd",
    "wof:placetype":"venue"
},
  "geometry": {"coordinates":[-1.228670001,51.6577186584],"type":"Point"}
}