{
  "type": "Feature",
  "properties": {
    "addr:full":"Middle Mickle Hey Farm, Blackburn Old Road, Rishton Blackburn Lancashire BB1 4AB",
    "addr:housenumber":"hey farm blackburn",
    "addr:postcode":"bb1 4ab",
    "addr:street":"Mickle;Old Road",
    "iso:country":"GB",
    "sg:address":"Middle Mickle Hey Farm, Blackburn Old Road, Rishton",
    "sg:city":"Blackburn",
    "sg:classifiers":[
        {
            "category":"Farming",
            "subcategory":"Livestock Farm",
            "type":"Manufacturing & Wholesale Goods"
        }
    ],
    "sg:phone":"+44 1254 248533",
    "sg:postcode":"BB1 4AB",
    "sg:province":"Lancashire",
    "sg:tags":[
        "others"
    ],
    "wof:name":"R D & J L Ireland",
    "wof:placetype":"venue"
},
  "geometry": {"coordinates":[-2.417644,53.768017],"type":"Point"}
}