{
  "type": "Feature",
  "properties": {
    "iso:country":"GB",
    "sg:address":"137 High Road",
    "sg:city":"Loughton",
    "sg:classifiers":[
        {
            "category":"Personal",
            "subcategory":"Nail Salon",
            "type":"Services"
        }
    ],
    "sg:phone":"+44 20 8502 2222",
    "sg:postcode":"IG10 4LT",
    "sg:province":"Essex",
    "sg:tags":[
        "solarium",
        "tanning"
    ],
    "wof:name":"The Tanning Shop",
    "wof:placetype":"venue"
},
  "geometry": {"coordinates":[0.0515029989,51.643737793],"type":"Point"}
}