{
  "type": "Feature",
  "properties": {
    "iso:country":"GB",
    "sg:address":"11 North Street",
    "sg:city":"Elgin",
    "sg:classifiers":[
        {
            "category":"Shopping",
            "subcategory":"Department Store",
            "type":"Retail Goods"
        }
    ],
    "sg:phone":"+44 1343 540441",
    "sg:postcode":"IV30 4EG",
    "sg:province":"Moray",
    "wof:name":"J Styart",
    "wof:placetype":"venue"
},
  "geometry": {"coordinates":[-3.31727,57.655437],"type":"Point"}
}