{
  "type": "Feature",
  "properties": {
    "iso:country":"GB",
    "sg:address":"45 Victory Rd, West Wilts Trad Est",
    "sg:city":"Westbury",
    "sg:classifiers":[
        {
            "category":"Fast Food",
            "type":"Food & Drink"
        },
        {
            "category":"Cafe",
            "type":"Food & Drink"
        }
    ],
    "sg:postcode":"BA13 4JL",
    "sg:province":"Wiltshire",
    "sg:tags":[
        "tea",
        "away",
        "room",
        "take"
    ],
    "wof:name":"Mears,Thomas,",
    "wof:placetype":"venue"
},
  "geometry": {"coordinates":[-2.214473,51.276134],"type":"Point"}
}