{
  "type": "Feature",
  "properties": {
    "addr:full":"Woodhouse Farm Newcastle Staffordshire ST5 5HL",
    "addr:postcode":"st5 5hl",
    "iso:country":"GB",
    "sg:address":"Woodhouse Farm",
    "sg:city":"Newcastle",
    "sg:classifiers":[
        {
            "category":"Farming",
            "subcategory":"Livestock Farm",
            "type":"Manufacturing & Wholesale Goods"
        },
        {
            "category":"Farming",
            "subcategory":"Farm",
            "type":"Manufacturing & Wholesale Goods"
        }
    ],
    "sg:phone":"+44 1782 680388",
    "sg:postcode":"ST5 5HL",
    "sg:province":"Staffordshire",
    "sg:tags":[
        "mixed",
        "crop",
        "others"
    ],
    "wof:name":"G P & J M Talbot",
    "wof:placetype":"venue"
},
  "geometry": {"coordinates":[-2.293019,52.975277],"type":"Point"}
}