{
  "type": "Feature",
  "properties": {
    "addr:full":"Oxford Street Manchester Greater Manchester M1 4PD",
    "addr:postcode":"m1 4pd",
    "addr:street":"Oxford Street",
    "iso:country":"GB",
    "sg:address":"Oxford Street",
    "sg:city":"Manchester",
    "sg:classifiers":[
        {
            "category":"Cinema",
            "subcategory":"Movie Theater",
            "type":"Entertainment"
        }
    ],
    "sg:postcode":"M1 4PD",
    "sg:province":"Greater Manchester",
    "wof:name":"Odeon Cinemas Ltd.",
    "wof:placetype":"venue"
},
  "geometry": {"coordinates":[-2.24358,53.477226],"type":"Point"}
}