{
  "type": "Feature",
  "properties": {
    "addr:full":"Dellcote, Deacons La Thatcham Berkshire RG18 9RH",
    "addr:postcode":"rg18 9rh",
    "iso:country":"GB",
    "sg:address":"Dellcote, Deacons La",
    "sg:city":"Thatcham",
    "sg:classifiers":[
        {
            "category":"Professional",
            "subcategory":"Computer Services",
            "type":"Services"
        }
    ],
    "sg:phone":"+44 1635 200762",
    "sg:postcode":"RG18 9RH",
    "sg:province":"Berkshire",
    "sg:tags":[
        "system",
        "software"
    ],
    "wof:name":"Doughty Browne Computer Services Ltd",
    "wof:placetype":"venue"
},
  "geometry": {"coordinates":[-1.263599,51.403831],"type":"Point"}
}