{
  "type": "Feature",
  "properties": {
    "addr:full":"33 Oxford St Leamington Spa Warwickshire CV32 4RA",
    "addr:housenumber":"33",
    "addr:postcode":"cv32 4ra",
    "addr:street":"Oxford St",
    "iso:country":"GB",
    "sg:address":"33 Oxford St",
    "sg:city":"Leamington Spa",
    "sg:classifiers":[
        {
            "category":"Professional",
            "subcategory":"Business Services",
            "type":"Services"
        }
    ],
    "sg:phone":"+44 1926 833633",
    "sg:postcode":"CV32 4RA",
    "sg:province":"Warwickshire",
    "sg:tags":[
        "trade"
    ],
    "wof:name":"ACIFC",
    "wof:placetype":"venue"
},
  "geometry": {"coordinates":[-1.532585,52.292488],"type":"Point"}
}