{
  "type": "Feature",
  "properties": {
    "addr:full":"428 St John Street London Greater London EC1V 4NJ",
    "addr:housenumber":"428",
    "addr:postcode":"ec1v 4nj",
    "addr:street":"St John Street",
    "iso:country":"GB",
    "sg:address":"428 St John Street",
    "sg:city":"London",
    "sg:classifiers":[
        {
            "category":"Food & Beverages",
            "subcategory":"Bakery",
            "type":"Retail Goods"
        }
    ],
    "sg:phone":"+44 20 7837 3720",
    "sg:postcode":"EC1V 4NJ",
    "sg:province":"Greater London",
    "sg:tags":[
        "baker"
    ],
    "wof:name":"Bliss Bakery & Patisseries",
    "wof:placetype":"venue"
},
  "geometry": {"coordinates":[-0.106049,51.531898],"type":"Point"}
}