{
  "type": "Feature",
  "properties": {
    "addr:full":"Westway Ho, Rear Of 56-58 Spital St Dartford Kent DA1 2DT",
    "addr:housenumber":"of",
    "addr:postcode":"da1 2dt",
    "addr:street":"Spital St",
    "iso:country":"GB",
    "sg:address":"Westway Ho, Rear Of 56-58 Spital St",
    "sg:city":"Dartford",
    "sg:classifiers":[
        {
            "category":"Home & Garden",
            "subcategory":"Household Appliances",
            "type":"Retail Goods"
        }
    ],
    "sg:phone":"+44 1322 223274",
    "sg:postcode":"DA1 2DT",
    "sg:province":"Kent",
    "sg:tags":[
        "electrical"
    ],
    "wof:name":"D B S Electrical Services",
    "wof:placetype":"venue"
},
  "geometry": {"coordinates":[0.220555,51.444633],"type":"Point"}
}