{
  "type": "Feature",
  "properties": {
    "iso:country":"GB",
    "sg:address":"Breaston",
    "sg:city":"Derby",
    "sg:classifiers":[
        {
            "category":"Farming",
            "subcategory":"Livestock Farm",
            "type":"Manufacturing & Wholesale Goods"
        },
        {
            "category":"Farming",
            "subcategory":"Farm",
            "type":"Manufacturing & Wholesale Goods"
        }
    ],
    "sg:phone":"+44 1332 872368",
    "sg:postcode":"DE72 3DQ",
    "sg:province":"Derbyshire",
    "sg:tags":[
        "mixed",
        "crop",
        "others"
    ],
    "wof:name":"Sheila Sail",
    "wof:placetype":"venue"
},
  "geometry": {"coordinates":[-1.32645,52.904202],"type":"Point"}
}