{
  "type": "Feature",
  "properties": {
    "addr:full":"347a Soho Road Birmingham West Midlands B21 9SE",
    "addr:housenumber":"347a",
    "addr:postcode":"b21 9se",
    "addr:street":"Soho Road",
    "iso:country":"GB",
    "sg:address":"347a Soho Road",
    "sg:city":"Birmingham",
    "sg:classifiers":[
        {
            "category":"Personal",
            "type":"Services"
        },
        {
            "category":"Professional",
            "subcategory":"Lawyer & Legal Services",
            "type":"Services"
        }
    ],
    "sg:phone":"+44 121 515 1115",
    "sg:postcode":"B21 9SE",
    "sg:province":"West Midlands",
    "sg:tags":[
        "advice",
        "counselling"
    ],
    "wof:name":"Immigration Law Consultants Ltd.",
    "wof:placetype":"venue"
},
  "geometry": {"coordinates":[-1.939297,52.504173],"type":"Point"}
}