{
  "type": "Feature",
  "properties": {
    "iso:country":"GB",
    "sg:address":"Unit 4b Building B, Faircharm Trading Estate, Creekside",
    "sg:city":"London",
    "sg:classifiers":[
        {
            "category":"Shopping",
            "subcategory":"Stationery & Office Supplies",
            "type":"Retail Goods"
        }
    ],
    "sg:phone":"+44 20 8469 0282",
    "sg:postcode":"SE8 3DX",
    "sg:province":"Greater London",
    "sg:tags":[
        "printers'"
    ],
    "wof:name":"Ace Book Binders & Print Finishers",
    "wof:placetype":"venue"
},
  "geometry": {"coordinates":[-0.0198899992,51.4775886536],"type":"Point"}
}