{
  "type": "Feature",
  "properties": {
    "addr:full":"33 Egerton Road Twickenham Greater London TW2 7SL",
    "addr:housenumber":"33",
    "addr:postcode":"tw2 7sl",
    "addr:street":"Egerton Road",
    "iso:country":"GB",
    "sg:address":"33 Egerton Road",
    "sg:city":"Twickenham",
    "sg:classifiers":[
        {
            "category":"Retail",
            "subcategory":"Driving School",
            "type":"Services"
        }
    ],
    "sg:postcode":"TW2 7SL",
    "sg:province":"Greater London",
    "wof:name":"St Margaret's School of Motoring",
    "wof:placetype":"venue"
},
  "geometry": {"coordinates":[-0.340617,51.45282],"type":"Point"}
}