{
  "type": "Feature",
  "properties": {
    "addr:full":"12 Craven Park Road London Greater London NW10 4AB",
    "addr:housenumber":"12",
    "addr:postcode":"nw10 4ab",
    "addr:street":"Craven Park Road",
    "iso:country":"GB",
    "sg:address":"12 Craven Park Road",
    "sg:city":"London",
    "sg:classifiers":[
        {
            "category":"Shopping",
            "subcategory":"Stationery & Office Supplies",
            "type":"Retail Goods"
        }
    ],
    "sg:phone":"+44 20 8965 5484",
    "sg:postcode":"NW10 4AB",
    "sg:province":"Greater London",
    "wof:name":"New Card Centre",
    "wof:placetype":"venue"
},
  "geometry": {"coordinates":[-0.249236,51.537994],"type":"Point"}
}