{
  "type": "Feature",
  "properties": {
    "addr:full":"Sandbriggs, Lancaster Road Preston Lancashire PR3 1JA",
    "addr:postcode":"pr3 1ja",
    "addr:street":"Sandbriggs Lancaster Road",
    "iso:country":"GB",
    "sg:address":"Sandbriggs, Lancaster Road",
    "sg:city":"Preston",
    "sg:classifiers":[
        {
            "category":"Travel",
            "subcategory":"Hotels & Motels",
            "type":"Entertainment"
        }
    ],
    "sg:phone":"+44 1995 603080",
    "sg:postcode":"PR3 1JA",
    "sg:province":"Lancashire",
    "sg:tags":[
        "house",
        "guest"
    ],
    "wof:name":"T M Wilkinson",
    "wof:placetype":"venue"
},
  "geometry": {"coordinates":[-2.780695,53.924107],"type":"Point"}
}