{
  "type": "Feature",
  "properties": {
    "iso:country":"GB",
    "sg:address":"108 Commercial Street",
    "sg:city":"Brighouse",
    "sg:classifiers":[
        {
            "category":"Shopping",
            "subcategory":"Florist",
            "type":"Retail Goods"
        }
    ],
    "sg:phone":"+44 1484 400664",
    "sg:postcode":"HD6 1AQ",
    "sg:province":"West Yorkshire",
    "wof:name":"Simply Flowers",
    "wof:placetype":"venue"
},
  "geometry": {"coordinates":[-1.781486,53.702255],"type":"Point"}
}