{
  "type": "Feature",
  "properties": {
    "addr:full":"269 Talbot Rd, Opposite Talbot Showrooms Blackpool Lancashire FY3 7AZ",
    "addr:housenumber":"269",
    "addr:postcode":"fy3 7az",
    "addr:street":"Talbot Rd Opposite Talbot Showrooms",
    "iso:country":"GB",
    "sg:address":"269 Talbot Rd, Opposite Talbot Showrooms",
    "sg:city":"Blackpool",
    "sg:classifiers":[
        {
            "category":"Shopping",
            "subcategory":"Bicycles & Sporting Goods",
            "type":"Retail Goods"
        }
    ],
    "sg:phone":"+44 1253 304500",
    "sg:postcode":"FY3 7AZ",
    "sg:province":"Lancashire",
    "sg:tags":[
        "cycle",
        "accessory"
    ],
    "wof:name":"The Bike Shop",
    "wof:placetype":"venue"
},
  "geometry": {"coordinates":[-3.0357530117,53.8268051147],"type":"Point"}
}