{
  "type": "Feature",
  "properties": {
    "addr:full":"Britannia Works, Kenyon Street, Ramsbottom Bury Lancashire BL0 0AE",
    "addr:postcode":"bl0 0ae",
    "addr:street":"Kenyon Street",
    "iso:country":"GB",
    "sg:address":"Britannia Works, Kenyon Street, Ramsbottom",
    "sg:city":"Bury",
    "sg:classifiers":[
        {
            "category":"Shopping",
            "subcategory":"Discount & Variety Stores",
            "type":"Retail Goods"
        }
    ],
    "sg:postcode":"BL0 0AE",
    "sg:province":"Lancashire",
    "sg:tags":[
        "cleaning",
        "supply"
    ],
    "wof:name":"Kays (Ramsbottom) Ltd.",
    "wof:placetype":"venue"
},
  "geometry": {"coordinates":[-2.30858,53.648201],"type":"Point"}
}