{
  "type": "Feature",
  "properties": {
    "iso:country":"GB",
    "sg:address":"3b Bridge Street",
    "sg:city":"Taunton",
    "sg:classifiers":[
        {
            "category":"Shopping",
            "subcategory":"Music",
            "type":"Retail Goods"
        }
    ],
    "sg:phone":"+44 1823 330978",
    "sg:postcode":"TA1 1TG",
    "sg:province":"Somerset",
    "sg:tags":[
        "dvd",
        "record",
        "tape",
        "vinyl",
        "cd"
    ],
    "wof:name":"Martian Records",
    "wof:placetype":"venue"
},
  "geometry": {"coordinates":[-3.104765892,51.0181465149],"type":"Point"}
}