{
  "type": "Feature",
  "properties": {
    "addr:full":"33 Hawards Close Teignmouth Devon TQ14 9NW",
    "addr:housenumber":"33",
    "addr:postcode":"tq14 9nw",
    "addr:street":"Hawards Close",
    "iso:country":"GB",
    "sg:address":"33 Hawards Close",
    "sg:city":"Teignmouth",
    "sg:classifiers":[
        {
            "category":"Professional",
            "subcategory":"Engineering",
            "type":"Services"
        }
    ],
    "sg:phone":"+44 1626 775802",
    "sg:postcode":"TQ14 9NW",
    "sg:province":"Devon",
    "sg:tags":[
        "contractor",
        "electrical",
        "engineer"
    ],
    "wof:name":"Richard John Hooper",
    "wof:placetype":"venue"
},
  "geometry": {"coordinates":[-3.5094549656,50.558719635],"type":"Point"}
}