{
  "type": "Feature",
  "properties": {
    "iso:country":"GB",
    "sg:address":"19 Wellgate",
    "sg:city":"Rotherham",
    "sg:classifiers":[
        {
            "category":"Home & Garden",
            "subcategory":"Hardware",
            "type":"Retail Goods"
        }
    ],
    "sg:phone":"+44 1709 829962",
    "sg:postcode":"S60 2LT",
    "sg:province":"South Yorkshire",
    "wof:name":"The Iron Mongers",
    "wof:placetype":"venue"
},
  "geometry": {"coordinates":[-1.3542209864,53.4302406311],"type":"Point"}
}