{
  "type": "Feature",
  "properties": {
    "iso:country":"GB",
    "sg:address":"20a Main St, Barwick In Elmet",
    "sg:city":"Leeds",
    "sg:classifiers":[
        {
            "category":"Manufacturing",
            "subcategory":"Tools & Machinery",
            "type":"Manufacturing & Wholesale Goods"
        }
    ],
    "sg:postcode":"LS15 4JQ",
    "sg:province":"West Yorkshire",
    "sg:tags":[
        "society",
        "friendly"
    ],
    "wof:name":"Walsh,John,",
    "wof:placetype":"venue"
},
  "geometry": {"coordinates":[-1.394653,53.831253],"type":"Point"}
}