{
  "type": "Feature",
  "properties": {
    "addr:full":"86 Commercial St Tredegar Blaenau Gwent NP2 3DN",
    "addr:housenumber":"86",
    "addr:postcode":"np2 3dn",
    "addr:street":"Commercial St",
    "iso:country":"GB",
    "sg:address":"86 Commercial St",
    "sg:city":"Tredegar",
    "sg:classifiers":[
        {
            "category":"Shopping",
            "subcategory":"Clothing, Apparel, & Fashions",
            "type":"Retail Goods"
        }
    ],
    "sg:phone":"+44 1495 717532",
    "sg:postcode":"NP2 3DN",
    "sg:province":"Blaenau Gwent",
    "sg:tags":[
        "ladieswear"
    ],
    "wof:name":"Famous Names Seconds",
    "wof:placetype":"venue"
},
  "geometry": {"coordinates":[-3.2459208965,51.7752342224],"type":"Point"}
}