{
  "type": "Feature",
  "properties": {
    "addr:full":"4 The Paddocks Stockport Cheshire SK3 8SW",
    "addr:housenumber":"4",
    "addr:postcode":"sk3 8sw",
    "addr:street":"The Paddocks",
    "iso:country":"GB",
    "sg:address":"4 The Paddocks",
    "sg:city":"Stockport",
    "sg:classifiers":[
        {
            "category":"Building & Trades",
            "subcategory":"Plumbing",
            "type":"Services"
        }
    ],
    "sg:phone":"+44 161 483 8221",
    "sg:postcode":"SK3 8SW",
    "sg:province":"Cheshire",
    "sg:tags":[
        "drain",
        "clearance",
        "sewer"
    ],
    "wof:name":"DRAIN DOCTOR PLUMBING",
    "wof:placetype":"venue"
},
  "geometry": {"coordinates":[-2.148837,53.38871],"type":"Point"}
}