{
  "type": "Feature",
  "properties": {
    "addr:full":"1 Green Farm Close, Castor Peterborough Cambridgeshire PE5 7BE",
    "addr:housenumber":"1",
    "addr:postcode":"pe5 7be",
    "addr:street":"Green Farm Close",
    "iso:country":"GB",
    "sg:address":"1 Green Farm Close, Castor",
    "sg:city":"Peterborough",
    "sg:classifiers":[
        {
            "category":"Building & Trades",
            "subcategory":"Construction",
            "type":"Services"
        }
    ],
    "sg:phone":"+44 1733 380560",
    "sg:postcode":"PE5 7BE",
    "sg:province":"Cambridgeshire",
    "sg:tags":[
        "builder"
    ],
    "wof:name":"Castor Construction Ltd.",
    "wof:placetype":"venue"
},
  "geometry": {"coordinates":[-0.345071,52.574306],"type":"Point"}
}