{
  "type": "Feature",
  "properties": {
    "iso:country":"GB",
    "sg:address":"15 Windsor Close",
    "sg:city":"Halesowen",
    "sg:classifiers":[
        {
            "category":"Manufacturing",
            "subcategory":"Wood Products",
            "type":"Manufacturing & Wholesale Goods"
        }
    ],
    "sg:phone":"+44 121 501 3488",
    "sg:postcode":"B63 4BJ",
    "sg:province":"West Midlands",
    "sg:tags":[
        "sawmill",
        "shaving"
    ],
    "wof:name":"M S Taylor",
    "wof:placetype":"venue"
},
  "geometry": {"coordinates":[-2.062474,52.449413],"type":"Point"}
}