{
  "type": "Feature",
  "properties": {
    "addr:full":"Mill Meadow Way, Etwall Derby Derbyshire DE65 6NL",
    "addr:postcode":"de65 6nl",
    "addr:street":"Mill Meadow Way",
    "iso:country":"GB",
    "sg:address":"Mill Meadow Way, Etwall",
    "sg:city":"Derby",
    "sg:classifiers":[
        {
            "category":"Fast Food",
            "type":"Food & Drink"
        }
    ],
    "sg:postcode":"DE65 6NL",
    "sg:province":"Derbyshire",
    "sg:tags":[
        "away",
        "take"
    ],
    "wof:name":"A Stitch in Time",
    "wof:placetype":"venue"
},
  "geometry": {"coordinates":[-1.6020699739,52.883266449],"type":"Point"}
}