{
  "type": "Feature",
  "properties": {
    "addr:full":"31a French Road Leicester Leicestershire LE5 4AH",
    "addr:housenumber":"31a",
    "addr:postcode":"le5 4ah",
    "addr:street":"French Road",
    "iso:country":"GB",
    "sg:address":"31a French Road",
    "sg:city":"Leicester",
    "sg:classifiers":[
        {
            "category":"Manufacturing",
            "subcategory":"Textiles",
            "type":"Manufacturing & Wholesale Goods"
        }
    ],
    "sg:phone":"+44 116 276 6008",
    "sg:postcode":"LE5 4AH",
    "sg:province":"Leicestershire",
    "sg:tags":[
        "dyer"
    ],
    "wof:name":"U K Finishing Ltd.",
    "wof:placetype":"venue"
},
  "geometry": {"coordinates":[-1.096612,52.640083],"type":"Point"}
}