{
  "type": "Feature",
  "properties": {
    "iso:country":"GB",
    "sg:address":"11 Saracen Drive, Balsall Common",
    "sg:city":"Coventry",
    "sg:classifiers":[
        {
            "category":"Professional",
            "subcategory":"Employment Agencies",
            "type":"Services"
        }
    ],
    "sg:phone":"+44 1676 530000",
    "sg:postcode":"CV7 7UA",
    "sg:province":"Warwickshire",
    "sg:tags":[
        "consultant"
    ],
    "wof:name":"Keystar Personnel",
    "wof:placetype":"venue"
},
  "geometry": {"coordinates":[-1.6715769768,52.3899002075],"type":"Point"}
}