{
  "type": "Feature",
  "properties": {
    "addr:full":"13 Perry Rise London Greater London SE23 2QX",
    "addr:housenumber":"13",
    "addr:postcode":"se23 2qx",
    "addr:street":"Perry Rise",
    "iso:country":"GB",
    "sg:address":"13 Perry Rise",
    "sg:city":"London",
    "sg:classifiers":[
        {
            "category":"Banks & Credit Unions",
            "subcategory":"Bureau De Change",
            "type":"Services"
        }
    ],
    "sg:postcode":"SE23 2QX",
    "sg:province":"Greater London",
    "sg:tags":[
        "town",
        "consultant",
        "planning"
    ],
    "wof:name":"Peter F Pendleton",
    "wof:placetype":"venue"
},
  "geometry": {"coordinates":[-0.042277,51.434246],"type":"Point"}
}