{
  "type": "Feature",
  "properties": {
    "iso:country":"GB",
    "sg:address":"27 Castle Avenue",
    "sg:city":"Epsom",
    "sg:classifiers":[
        {
            "category":"Building & Trades",
            "subcategory":"Construction",
            "type":"Services"
        }
    ],
    "sg:phone":"+44 20 8393 5542",
    "sg:postcode":"KT17 2PL",
    "sg:province":"Surrey",
    "sg:tags":[
        "joinery",
        "joiner",
        "carpenter",
        "carpentry"
    ],
    "wof:name":"Clark's Carpentry & Joinery",
    "wof:placetype":"venue"
},
  "geometry": {"coordinates":[-0.242371,51.349926],"type":"Point"}
}