{
  "type": "Feature",
  "properties": {
    "iso:country":"GB",
    "sg:address":"1 Hockey Close",
    "sg:city":"Loughborough",
    "sg:classifiers":[
        {
            "category":"Wholesale",
            "subcategory":"Non-durable Goods",
            "type":"Manufacturing & Wholesale Goods"
        }
    ],
    "sg:phone":"+44 1509 611721",
    "sg:postcode":"LE11 5TR",
    "sg:province":"Leicestershire",
    "sg:tags":[
        "carry",
        "cash"
    ],
    "wof:name":"Hancocks Distribution",
    "wof:placetype":"venue"
},
  "geometry": {"coordinates":[-1.209349,52.785187],"type":"Point"}
}