{
  "type": "Feature",
  "properties": {
    "iso:country":"GB",
    "sg:address":"St. Barnabas Church Hall, 88 Sackville Rd",
    "sg:city":"Hove",
    "sg:classifiers":[
        {
            "category":"Social Services",
            "subcategory":"Adult Care",
            "type":"Services"
        },
        {
            "category":"Government",
            "subcategory":"Office",
            "type":"Public Place"
        }
    ],
    "sg:phone":"+44 1273 778835",
    "sg:postcode":"BN3 3HE",
    "sg:province":"East Sussex",
    "sg:tags":[
        "centre",
        "agency",
        "authority",
        "education",
        "local",
        "day"
    ],
    "wof:name":"Hove Borough Council",
    "wof:placetype":"venue"
},
  "geometry": {"coordinates":[-0.182449,50.838943],"type":"Point"}
}