{
  "type": "Feature",
  "properties": {
    "addr:full":"Fern Mills, 7 Old Leeds Road Huddersfield West Yorkshire HD1 1SG",
    "addr:housenumber":"7",
    "addr:postcode":"hd1 1sg",
    "addr:street":"Fern Mills;Old Leeds Road",
    "iso:country":"GB",
    "sg:address":"Fern Mills, 7 Old Leeds Road",
    "sg:city":"Huddersfield",
    "sg:classifiers":[
        {
            "category":"Professional",
            "subcategory":"Engineering",
            "type":"Services"
        }
    ],
    "sg:phone":"+44 1484 559195",
    "sg:postcode":"HD1 1SG",
    "sg:province":"West Yorkshire",
    "sg:tags":[
        "contractor",
        "electrical",
        "engineer"
    ],
    "wof:name":"Fern Electrical",
    "wof:placetype":"venue"
},
  "geometry": {"coordinates":[-1.782684,53.646954],"type":"Point"}
}