{
  "type": "Feature",
  "properties": {
    "addr:full":"Cheadle Road, Alton Stoke On Trent Staffordshire ST10 4DH",
    "addr:postcode":"st10 4dh",
    "addr:street":"Cheadle Road;On Trent",
    "iso:country":"GB",
    "sg:address":"Cheadle Road, Alton",
    "sg:city":"Stoke On Trent",
    "sg:classifiers":[
        {
            "category":"Bars & Pubs",
            "type":"Food & Drink"
        }
    ],
    "sg:phone":"+44 1538 755776",
    "sg:postcode":"ST10 4DH",
    "sg:province":"Staffordshire",
    "sg:tags":[
        "pubs",
        "inn"
    ],
    "wof:name":"S R Mccormick",
    "wof:placetype":"venue"
},
  "geometry": {"coordinates":[-1.8937920332,52.9721488953],"type":"Point"}
}