{
  "type": "Feature",
  "properties": {
    "iso:country":"GB",
    "sg:address":"6 Stratton Street",
    "sg:city":"West End",
    "sg:classifiers":[
        {
            "category":"Professional",
            "subcategory":"Business Services",
            "type":"Services"
        }
    ],
    "sg:postcode":"W1X 5FD",
    "sg:province":"Hampshire",
    "sg:tags":[
        "holding"
    ],
    "wof:name":"Kingshott Holdings Ltd",
    "wof:placetype":"venue"
},
  "geometry": {"coordinates":[-0.13899,51.50758],"type":"Point"}
}