{
  "type": "Feature",
  "properties": {
    "iso:country":"GB",
    "sg:address":"Europian Park, Bayton Road Industrial Estate, Bayton Road",
    "sg:city":"Coventry",
    "sg:classifiers":[
        {
            "category":"Personal",
            "type":"Services"
        }
    ],
    "sg:phone":"+44 24 7634 2122",
    "sg:postcode":"CV7 9EL",
    "sg:province":"Warwickshire",
    "sg:tags":[
        "delivery"
    ],
    "wof:name":"Coventry Express Services Ltd.",
    "wof:placetype":"venue"
},
  "geometry": {"coordinates":[-1.470289,52.466],"type":"Point"}
}