{
  "type": "Feature",
  "properties": {
    "addr:full":"Castlelaurie Falkirk Falkirk FK2 7XF",
    "addr:postcode":"fk2 7xf",
    "addr:street":"Castlelaurie",
    "iso:country":"GB",
    "sg:address":"Castlelaurie",
    "sg:city":"Falkirk",
    "sg:classifiers":[
        {
            "category":"Professional",
            "type":"Services"
        }
    ],
    "sg:postcode":"FK2 7XF",
    "sg:province":"Falkirk",
    "sg:tags":[
        "auctioneer"
    ],
    "wof:name":"Central Auctions",
    "wof:placetype":"venue"
},
  "geometry": {"coordinates":[-3.780088,56.012302],"type":"Point"}
}