{
  "type": "Feature",
  "properties": {
    "addr:full":"106 Eastgate Centre Basildon Essex SS14 1AG",
    "addr:housenumber":"106",
    "addr:postcode":"ss14 1ag",
    "addr:street":"Eastgate Centre",
    "iso:country":"GB",
    "sg:address":"106 Eastgate Centre",
    "sg:city":"Basildon",
    "sg:classifiers":[
        {
            "category":"Professional",
            "subcategory":"Printing & Photocopies",
            "type":"Services"
        }
    ],
    "sg:postcode":"SS14 1AG",
    "sg:province":"Essex",
    "sg:tags":[
        "embroiderer"
    ],
    "wof:name":"Needlecrafts",
    "wof:placetype":"venue"
},
  "geometry": {"coordinates":[0.46053,51.569389],"type":"Point"}
}