{
  "type": "Feature",
  "properties": {
    "iso:country":"GB",
    "sg:address":"Warminster, 2 Mount Pleasant, Pontneynydd",
    "sg:city":"Pontypool",
    "sg:classifiers":[
        {
            "category":"Building & Trades",
            "subcategory":"Construction",
            "type":"Services"
        }
    ],
    "sg:postcode":"NP4 6SE",
    "sg:province":"Monmouthshire",
    "sg:tags":[
        "heating",
        "contractor"
    ],
    "wof:name":"K Nash",
    "wof:placetype":"venue"
},
  "geometry": {"coordinates":[-3.0431900024,51.703086853],"type":"Point"}
}