{
  "type": "Feature",
  "properties": {
    "iso:country":"GB",
    "sg:address":"35 Wraxall Gro",
    "sg:city":"Bristol",
    "sg:classifiers":[
        {
            "category":"Building & Trades",
            "subcategory":"Construction",
            "type":"Services"
        }
    ],
    "sg:phone":"+44 117 935 8611",
    "sg:postcode":"BS13 7EG",
    "sg:province":"City of Bristol",
    "sg:tags":[
        "joiner",
        "carpenter"
    ],
    "wof:name":"B Baincon",
    "wof:placetype":"venue"
},
  "geometry": {"coordinates":[-2.6200621128,51.4235267639],"type":"Point"}
}