{
  "type": "Feature",
  "properties": {
    "addr:full":"The Uplands Loughton Essex IG10 1NQ",
    "addr:postcode":"ig10 1nq",
    "addr:street":"The Uplands",
    "iso:country":"GB",
    "sg:address":"The Uplands",
    "sg:city":"Loughton",
    "sg:classifiers":[
        {
            "category":"Arena",
            "subcategory":"Sports Club",
            "type":"Entertainment"
        }
    ],
    "sg:postcode":"IG10 1NQ",
    "sg:province":"Essex",
    "wof:name":"Loughton Cricket Club",
    "wof:placetype":"venue"
},
  "geometry": {"coordinates":[0.0632449985,51.6525650024],"type":"Point"}
}