{
  "type": "Feature",
  "properties": {
    "addr:full":"Severn Square Alfreton Derbyshire DE55 7BQ",
    "addr:postcode":"de55 7bq",
    "iso:country":"GB",
    "sg:address":"Severn Square",
    "sg:city":"Alfreton",
    "sg:classifiers":[
        {
            "category":"Travel",
            "subcategory":"Travel Agent",
            "type":"Entertainment"
        }
    ],
    "sg:postcode":"DE55 7BQ",
    "sg:province":"Derbyshire",
    "wof:name":"Tim Draper Holidays",
    "wof:placetype":"venue"
},
  "geometry": {"coordinates":[-1.3879590034,53.0964317322],"type":"Point"}
}