{
  "type": "Feature",
  "properties": {
    "addr:full":"170 Newland Road Bristol City of Bristol BS13 9DX",
    "addr:housenumber":"170",
    "addr:postcode":"bs13 9dx",
    "addr:street":"Newland Road",
    "iso:country":"GB",
    "sg:address":"170 Newland Road",
    "sg:city":"Bristol",
    "sg:classifiers":[
        {
            "category":"Home & Garden",
            "subcategory":"Carpets & Floor Coverings",
            "type":"Retail Goods"
        }
    ],
    "sg:phone":"+44 117 978 0435",
    "sg:postcode":"BS13 9DX",
    "sg:province":"City of Bristol",
    "sg:tags":[
        "cleaner",
        "upholstery"
    ],
    "wof:name":"Elite Cleaning Service",
    "wof:placetype":"venue"
},
  "geometry": {"coordinates":[-2.612334013,51.4046821594],"type":"Point"}
}