{
  "type": "Feature",
  "properties": {
    "addr:full":"592c Atlas Rd Wembley Greater London HA9 0JH",
    "addr:housenumber":"592c",
    "addr:postcode":"ha9 0jh",
    "addr:street":"Atlas Rd",
    "iso:country":"GB",
    "sg:address":"592c Atlas Rd",
    "sg:city":"Wembley",
    "sg:classifiers":[
        {
            "category":"Wholesale",
            "subcategory":"Non-durable Goods",
            "type":"Manufacturing & Wholesale Goods"
        }
    ],
    "sg:phone":"+44 20 8900 1974",
    "sg:postcode":"HA9 0JH",
    "sg:province":"Greater London",
    "sg:tags":[
        "carry",
        "cash"
    ],
    "wof:name":"Walker Bros",
    "wof:placetype":"venue"
},
  "geometry": {"coordinates":[-0.2692689896,51.5591239929],"type":"Point"}
}