{
  "type": "Feature",
  "properties": {
    "iso:country":"GB",
    "sg:address":"43 Chester Rd",
    "sg:city":"Lower Edmonton",
    "sg:classifiers":[
        {
            "category":"Building & Trades",
            "subcategory":"Construction",
            "type":"Services"
        }
    ],
    "sg:phone":"+44 20 8807 2762",
    "sg:postcode":"N9 8JH",
    "sg:province":"Greater London",
    "sg:tags":[
        "roofing"
    ],
    "wof:name":"R & M Roofing (Enfield) Ltd",
    "wof:placetype":"venue"
},
  "geometry": {"coordinates":[-0.0518260002,51.6296386719],"type":"Point"}
}