{
  "type": "Feature",
  "properties": {
    "iso:country":"GB",
    "sg:address":"105 High Street",
    "sg:city":"Billingshurst",
    "sg:classifiers":[
        {
            "category":"Professional",
            "subcategory":"Management & Consulting",
            "type":"Services"
        },
        {
            "category":"Insurance",
            "subcategory":"Insurance Agent",
            "type":"Services"
        }
    ],
    "sg:phone":"+44 1403 782485",
    "sg:postcode":"RH14 9QX",
    "sg:province":"West Sussex",
    "sg:tags":[
        "consultant",
        "broker",
        "business"
    ],
    "wof:name":"F G T Agencies International",
    "wof:placetype":"venue"
},
  "geometry": {"coordinates":[-0.452454,51.020756],"type":"Point"}
}