{
  "type": "Feature",
  "properties": {
    "addr:full":"Lakelands Sales Office, Church Lane Colchester Essex CO3 8LS",
    "addr:postcode":"co3 8ls",
    "addr:street":"Church Lane",
    "iso:country":"GB",
    "sg:address":"Lakelands Sales Office, Church Lane",
    "sg:city":"Colchester",
    "sg:classifiers":[
        {
            "category":"Real Estate",
            "subcategory":"Real Estate Agent",
            "type":"Services"
        }
    ],
    "sg:phone":"+44 1206 331840",
    "sg:postcode":"CO3 8LS",
    "sg:province":"Essex",
    "wof:name":"Bairstow Regent New Homes",
    "wof:placetype":"venue"
},
  "geometry": {"coordinates":[0.8198500276,51.8728294373],"type":"Point"}
}