{
  "type": "Feature",
  "properties": {
    "addr:full":"36 Hornsby Square Basildon Essex SS15 6SD",
    "addr:housenumber":"36",
    "addr:postcode":"ss15 6sd",
    "addr:street":"Hornsby Square",
    "iso:country":"GB",
    "sg:address":"36 Hornsby Square",
    "sg:city":"Basildon",
    "sg:classifiers":[
        {
            "category":"Professional",
            "subcategory":"Business Services",
            "type":"Services"
        }
    ],
    "sg:phone":"+44 1268 541322",
    "sg:postcode":"SS15 6SD",
    "sg:province":"Essex",
    "sg:tags":[
        "distribution"
    ],
    "wof:name":"I D A Distribution Ltd.",
    "wof:placetype":"venue"
},
  "geometry": {"coordinates":[0.4004600048,51.5767364502],"type":"Point"}
}