{
  "type": "Feature",
  "properties": {
    "addr:full":"5a Frenchay Park Road Bristol City of Bristol BS16 1EB",
    "addr:housenumber":"5a",
    "addr:postcode":"bs16 1eb",
    "addr:street":"Frenchay Park Road",
    "iso:country":"GB",
    "sg:address":"5a Frenchay Park Road",
    "sg:city":"Bristol",
    "sg:classifiers":[
        {
            "category":"Home & Garden",
            "subcategory":"Garden Supply",
            "type":"Retail Goods"
        }
    ],
    "sg:postcode":"BS16 1EB",
    "sg:province":"City of Bristol",
    "sg:tags":[
        "nursery",
        "centre"
    ],
    "wof:name":"D Searle",
    "wof:placetype":"venue"
},
  "geometry": {"coordinates":[-2.53699,51.491291],"type":"Point"}
}