{
  "type": "Feature",
  "properties": {
    "addr:full":"28 Nowell Terr Leeds West Yorkshire LS9 6HX",
    "addr:housenumber":"28",
    "addr:postcode":"ls9 6hx",
    "addr:street":"Nowell Terr",
    "iso:country":"GB",
    "sg:address":"28 Nowell Terr",
    "sg:city":"Leeds",
    "sg:classifiers":[
        {
            "category":"Building & Trades",
            "subcategory":"Construction",
            "type":"Services"
        }
    ],
    "sg:phone":"+44 113 249 5851",
    "sg:postcode":"LS9 6HX",
    "sg:province":"West Yorkshire",
    "sg:tags":[
        "conversion",
        "loft"
    ],
    "wof:name":"Leckenby Joinery",
    "wof:placetype":"venue"
},
  "geometry": {"coordinates":[-1.5040359497,53.8042564392],"type":"Point"}
}