{
  "type": "Feature",
  "properties": {
    "iso:country":"GB",
    "sg:address":"10 Dracaena Avenue",
    "sg:city":"Falmouth",
    "sg:classifiers":[
        {
            "category":"Autos & Motor Vehicles",
            "subcategory":"Auto Supplies",
            "type":"Retail Goods"
        }
    ],
    "sg:phone":"+44 1326 319233",
    "sg:postcode":"TR11 2EF",
    "sg:province":"Cornwall",
    "sg:tags":[
        "tyre"
    ],
    "wof:name":"Ats",
    "wof:placetype":"venue"
},
  "geometry": {"coordinates":[-5.079785,50.151993],"type":"Point"}
}