{
  "type": "Feature",
  "properties": {
    "iso:country":"GB",
    "sg:address":"5 Swinegate",
    "sg:city":"Grantham",
    "sg:classifiers":[
        {
            "category":"Shopping",
            "subcategory":"Stationery & Office Supplies",
            "type":"Retail Goods"
        }
    ],
    "sg:postcode":"NG31 6RJ",
    "sg:province":"Lincolnshire",
    "sg:tags":[
        "equipment"
    ],
    "wof:name":"B S Business Services",
    "wof:placetype":"venue"
},
  "geometry": {"coordinates":[-0.642405,52.914307],"type":"Point"}
}