{
  "type": "Feature",
  "properties": {
    "iso:country":"GB",
    "sg:address":"P O Box 22",
    "sg:city":"Cromer",
    "sg:classifiers":[
        {
            "category":"Manufacturing",
            "subcategory":"Lumber",
            "type":"Manufacturing & Wholesale Goods"
        }
    ],
    "sg:phone":"+44 1263 515125",
    "sg:postcode":"NR27 9RF",
    "sg:province":"Norfolk",
    "sg:tags":[
        "importer",
        "merchants",
        "agent",
        "timber"
    ],
    "wof:name":"A S Limtrae Lilleheden",
    "wof:placetype":"venue"
},
  "geometry": {"coordinates":[1.26787,52.930141],"type":"Point"}
}