{
  "type": "Feature",
  "properties": {
    "iso:country":"GB",
    "sg:address":"56 Albert Road North",
    "sg:city":"Malvern",
    "sg:classifiers":[
        {
            "category":"Building & Trades",
            "subcategory":"Plumbing",
            "type":"Services"
        }
    ],
    "sg:phone":"+44 1684 567097",
    "sg:postcode":"WR14 2TL",
    "sg:province":"Herefordshire",
    "sg:tags":[
        "central",
        "heating"
    ],
    "wof:name":"Howard Jones",
    "wof:placetype":"venue"
},
  "geometry": {"coordinates":[-2.323573,52.113716],"type":"Point"}
}