{
  "type": "Feature",
  "properties": {
    "addr:full":"56 Albert Road North Malvern Herefordshire WR14 2TL",
    "addr:housenumber":"56",
    "addr:postcode":"wr14 2tl",
    "addr:street":"Albert Road North;Herefordshire",
    "iso:country":"GB",
    "sg:address":"56 Albert Road North",
    "sg:city":"Malvern",
    "sg:classifiers":[
        {
            "category":"Building & Trades",
            "subcategory":"Plumbing",
            "type":"Services"
        }
    ],
    "sg:phone":"+44 1684 567097",
    "sg:postcode":"WR14 2TL",
    "sg:province":"Herefordshire",
    "sg:tags":[
        "central",
        "heating"
    ],
    "wof:name":"Howard Jones",
    "wof:placetype":"venue"
},
  "geometry": {"coordinates":[-2.323573,52.113716],"type":"Point"}
}