{
  "type": "Feature",
  "properties": {
    "addr:full":"154 Tenniswood Rd Enfield Greater London EN1 3LX",
    "addr:housenumber":"154",
    "addr:postcode":"en1 3lx",
    "addr:street":"Tenniswood Rd",
    "iso:country":"GB",
    "sg:address":"154 Tenniswood Rd",
    "sg:city":"Enfield",
    "sg:classifiers":[
        {
            "category":"Professional",
            "subcategory":"Engineering",
            "type":"Services"
        }
    ],
    "sg:phone":"+44 20 8366 1892",
    "sg:postcode":"EN1 3LX",
    "sg:province":"Greater London",
    "sg:tags":[
        "contractor",
        "electrical",
        "engineer"
    ],
    "wof:name":"Draper Electrical",
    "wof:placetype":"venue"
},
  "geometry": {"coordinates":[-0.0697410032,51.6606216431],"type":"Point"}
}