{
  "type": "Feature",
  "properties": {
    "iso:country":"GB",
    "sg:address":"237 Dunstall Road",
    "sg:city":"Wolverhampton",
    "sg:classifiers":[
        {
            "category":"Food & Beverages",
            "subcategory":"Candy",
            "type":"Retail Goods"
        }
    ],
    "sg:phone":"+44 1902 421006",
    "sg:postcode":"WV6 0NY",
    "sg:province":"Shropshire",
    "sg:tags":[
        "confectioner"
    ],
    "wof:name":"Partap Sweet Centre",
    "wof:placetype":"venue"
},
  "geometry": {"coordinates":[-2.138847,52.597385],"type":"Point"}
}