{
  "type": "Feature",
  "properties": {
    "addr:full":"5 Wigmore Street London Greater London W1U 1HY",
    "addr:housenumber":"5",
    "addr:postcode":"w1u 1hy",
    "addr:street":"Wigmore Street",
    "iso:country":"GB",
    "sg:address":"5 Wigmore Street",
    "sg:city":"London",
    "sg:classifiers":[
        {
            "category":"Banks & Credit Unions",
            "subcategory":"Financial Services",
            "type":"Services"
        }
    ],
    "sg:postcode":"W1U 1HY",
    "sg:province":"Greater London",
    "sg:tags":[
        "consultant"
    ],
    "wof:name":"Brooks Braithwaite Financial Services Lt",
    "wof:placetype":"venue"
},
  "geometry": {"coordinates":[-0.149889,51.516178],"type":"Point"}
}