{
  "type": "Feature",
  "properties": {
    "addr:full":"105 Horse Shoes Lane, Sheldon Birmingham West Midlands B26 3HS",
    "addr:housenumber":"105",
    "addr:postcode":"b26 3hs",
    "addr:street":"Horse Shoes Lane",
    "iso:country":"GB",
    "sg:address":"105 Horse Shoes Lane, Sheldon",
    "sg:city":"Birmingham",
    "sg:classifiers":[
        {
            "category":"Home & Garden",
            "subcategory":"Garden Supply",
            "type":"Retail Goods"
        }
    ],
    "sg:phone":"+44 121 743 2225",
    "sg:postcode":"B26 3HS",
    "sg:province":"West Midlands",
    "sg:tags":[
        "nursery",
        "centre"
    ],
    "wof:name":"W J Rawlings Nurseries Ltd.",
    "wof:placetype":"venue"
},
  "geometry": {"coordinates":[-1.782476,52.455513],"type":"Point"}
}