{
  "type": "Feature",
  "properties": {
    "addr:full":"147 Wellington Road Rhyl Conwy LL18 1LE",
    "addr:housenumber":"147",
    "addr:postcode":"ll18 1le",
    "addr:street":"Wellington Road",
    "iso:country":"GB",
    "sg:address":"147 Wellington Road",
    "sg:city":"Rhyl",
    "sg:classifiers":[
        {
            "category":"Home & Garden",
            "subcategory":"Household Appliances",
            "type":"Retail Goods"
        },
        {
            "category":"Retail",
            "subcategory":"Event Space",
            "type":"Services"
        }
    ],
    "sg:phone":"+44 1745 337141",
    "sg:postcode":"LL18 1LE",
    "sg:province":"Conwy",
    "sg:tags":[
        "electrical",
        "product",
        "domestic",
        "sales",
        "centre"
    ],
    "wof:name":"Select Domestic Appliances",
    "wof:placetype":"venue"
},
  "geometry": {"coordinates":[-3.4903590679,53.3202056885],"type":"Point"}
}