{
  "type": "Feature",
  "properties": {
    "addr:full":"51 Mill La, Greenfield Bedford Bedfordshire MK45 5DG",
    "addr:housenumber":"51",
    "addr:postcode":"mk45 5dg",
    "addr:street":"Mill La Greenfield",
    "iso:country":"GB",
    "sg:address":"51 Mill La, Greenfield",
    "sg:city":"Bedford",
    "sg:classifiers":[
        {
            "category":"Professional",
            "subcategory":"Management & Consulting",
            "type":"Services"
        }
    ],
    "sg:postcode":"MK45 5DG",
    "sg:province":"Bedfordshire",
    "sg:tags":[
        "consultant",
        "training"
    ],
    "wof:name":"Lambert,Thomas,",
    "wof:placetype":"venue"
},
  "geometry": {"coordinates":[-0.4672560096,52.004650116],"type":"Point"}
}