{
  "type": "Feature",
  "properties": {
    "iso:country":"GB",
    "sg:address":"19 Mark Street",
    "sg:city":"Huddersfield",
    "sg:classifiers":[
        {
            "category":"Building & Trades",
            "subcategory":"Construction",
            "type":"Services"
        }
    ],
    "sg:phone":"+44 1484 434955",
    "sg:postcode":"HD1 4ST",
    "sg:province":"West Yorkshire",
    "sg:tags":[
        "joiner",
        "carpenter"
    ],
    "wof:name":"Trevor Dyson Joinery",
    "wof:placetype":"venue"
},
  "geometry": {"coordinates":[-1.8007589579,53.6428985596],"type":"Point"}
}