{
  "type": "Feature",
  "properties": {
    "iso:country":"GB",
    "sg:address":"Cornwood Farm, Napton Rd, Stockton",
    "sg:city":"Rugby",
    "sg:classifiers":[
        {
            "category":"Shopping",
            "type":"Retail Goods"
        }
    ],
    "sg:phone":"+44 1926 811488",
    "sg:postcode":"CV23 8HU",
    "sg:province":"Northamptonshire",
    "sg:tags":[
        "part",
        "accessory"
    ],
    "wof:name":"Stiky Biznez",
    "wof:placetype":"venue"
},
  "geometry": {"coordinates":[-1.3610500097,52.271938324],"type":"Point"}
}