{
  "type": "Feature",
  "properties": {
    "addr:full":"Copgrove Road, Burton Leonard Harrogate North Yorkshire HG3 3SJ",
    "addr:postcode":"hg3 3sj",
    "addr:street":"Copgrove Road;Leonard",
    "iso:country":"GB",
    "sg:address":"Copgrove Road, Burton Leonard",
    "sg:city":"Harrogate",
    "sg:classifiers":[
        {
            "category":"Bars & Pubs",
            "type":"Food & Drink"
        }
    ],
    "sg:phone":"+44 1765 677332",
    "sg:postcode":"HG3 3SJ",
    "sg:province":"North Yorkshire",
    "sg:tags":[
        "pubs",
        "inn"
    ],
    "wof:name":"Whitbread Hotel Co. Ltd.",
    "wof:placetype":"venue"
},
  "geometry": {"coordinates":[-1.5011390448,54.0690917969],"type":"Point"}
}