{
  "type": "Feature",
  "properties": {
    "addr:full":"22 Fitzwilliam Street Huddersfield West Yorkshire HD1 6BE",
    "addr:housenumber":"22",
    "addr:postcode":"hd1 6be",
    "addr:street":"Fitzwilliam Street",
    "iso:country":"GB",
    "sg:address":"22 Fitzwilliam Street",
    "sg:city":"Huddersfield",
    "sg:classifiers":[
        {
            "category":"Retail",
            "subcategory":"Auto Repair",
            "type":"Services"
        }
    ],
    "sg:phone":"+44 1484 530800",
    "sg:postcode":"HD1 6BE",
    "sg:province":"West Yorkshire",
    "sg:tags":[
        "modification",
        "garage"
    ],
    "wof:name":"Great Northern Street Motors",
    "wof:placetype":"venue"
},
  "geometry": {"coordinates":[-1.779045,53.65134],"type":"Point"}
}