{
  "type": "Feature",
  "properties": {
    "addr:full":"Unit F1 Ennis Close, Baguley Manchester Cheshire M23 9WL",
    "addr:housenumber":"f1",
    "addr:postcode":"m23 9wl",
    "addr:street":"Ennis Close",
    "iso:country":"GB",
    "sg:address":"Unit F1 Ennis Close, Baguley",
    "sg:city":"Manchester",
    "sg:classifiers":[
        {
            "category":"Food & Beverages",
            "subcategory":"Liquor & Beverages",
            "type":"Retail Goods"
        }
    ],
    "sg:phone":"+44 1925 850045",
    "sg:postcode":"M23 9WL",
    "sg:province":"Cheshire",
    "sg:tags":[
        "beer",
        "spirit",
        "wines"
    ],
    "wof:name":"Pieroth Ltd.",
    "wof:placetype":"venue"
},
  "geometry": {"coordinates":[-2.2974789143,53.3905143738],"type":"Point"}
}