{
  "type": "Feature",
  "properties": {
    "iso:country":"GB",
    "sg:address":"St Helens Square",
    "sg:city":"Scarborough",
    "sg:classifiers":[
        {
            "category":"Professional",
            "subcategory":"Business Services",
            "type":"Services"
        },
        {
            "category":"Government",
            "subcategory":"Office",
            "type":"Public Place"
        }
    ],
    "sg:phone":"+44 1723 373579",
    "sg:postcode":"YO11 1EU",
    "sg:province":"North Yorkshire",
    "sg:tags":[
        "operator",
        "local",
        "market"
    ],
    "wof:name":"Market Hall",
    "wof:placetype":"venue"
},
  "geometry": {"coordinates":[-0.3968740106,54.2836112976],"type":"Point"}
}