{
  "type": "Feature",
  "properties": {
    "addr:full":"Town Hall, Bartholomew Square Brighton East Sussex BN1 1JA",
    "addr:postcode":"bn1 1ja",
    "addr:street":"Bartholomew Square",
    "iso:country":"GB",
    "sg:address":"Town Hall, Bartholomew Square",
    "sg:city":"Brighton",
    "sg:classifiers":[
        {
            "category":"Communications",
            "subcategory":"Film & Video Production",
            "type":"Services"
        }
    ],
    "sg:phone":"+44 1273 384211",
    "sg:postcode":"BN1 1JA",
    "sg:province":"East Sussex",
    "sg:tags":[
        "tv",
        "studio"
    ],
    "wof:name":"Southern Screen Commission Ltd.",
    "wof:placetype":"venue"
},
  "geometry": {"coordinates":[-0.140086,50.82093],"type":"Point"}
}