{
  "type": "Feature",
  "properties": {
    "addr:full":"Draffan Road, Netherburn Larkhall South Lanarkshire ML9 3DE",
    "addr:postcode":"ml9 3de",
    "addr:street":"Draffan Road",
    "iso:country":"GB",
    "sg:address":"Draffan Road, Netherburn",
    "sg:city":"Larkhall",
    "sg:classifiers":[
        {
            "category":"Education",
            "subcategory":"School",
            "type":"Public Place"
        },
        {
            "category":"Government",
            "subcategory":"Office",
            "type":"Public Place"
        }
    ],
    "sg:phone":"+44 1698 882484",
    "sg:postcode":"ML9 3DE",
    "sg:province":"South Lanarkshire",
    "sg:tags":[
        "local",
        "authority"
    ],
    "wof:name":"Netherburn Primary School",
    "wof:placetype":"venue"
},
  "geometry": {"coordinates":[-3.9112420082,55.7067298889],"type":"Point"}
}