{
  "type": "Feature",
  "properties": {
    "iso:country":"GB",
    "sg:address":"Building 552",
    "sg:city":"Hounslow",
    "sg:classifiers":[
        {
            "category":"Airline",
            "type":"Transportation"
        }
    ],
    "sg:phone":"+44 20 8759 5566",
    "sg:postcode":"TW6 3RF",
    "sg:province":"Greater London",
    "wof:name":"Trans World Airlines Incorporated",
    "wof:placetype":"venue"
},
  "geometry": {"coordinates":[-0.45527,51.460171],"type":"Point"}
}