{
  "type": "Feature",
  "properties": {
    "iso:country":"GB",
    "sg:address":"Coach Ho Lyndhurst Rd, Bransgore",
    "sg:city":"Christchurch",
    "sg:classifiers":[
        {
            "category":"Government",
            "subcategory":"Customs House",
            "type":"Public Place"
        }
    ],
    "sg:postcode":"BH23 8LA",
    "sg:province":"Dorset",
    "sg:tags":[
        "clearance"
    ],
    "wof:name":"Roche,Brian,",
    "wof:placetype":"venue"
},
  "geometry": {"coordinates":[-1.733091,50.7799],"type":"Point"}
}