{
  "type": "Feature",
  "properties": {
    "addr:full":"8b West Horndon Industrial Park Brentwood Essex CM13 3XD",
    "addr:housenumber":"8b",
    "addr:postcode":"cm13 3xd",
    "addr:street":"West Horndon Industrial Park",
    "iso:country":"GB",
    "sg:address":"8b West Horndon Industrial Park",
    "sg:city":"Brentwood",
    "sg:classifiers":[
        {
            "category":"Manufacturing",
            "subcategory":"Wood Products",
            "type":"Manufacturing & Wholesale Goods"
        }
    ],
    "sg:phone":"+44 1277 811116",
    "sg:postcode":"CM13 3XD",
    "sg:province":"Essex",
    "sg:tags":[
        "packaging",
        "crate",
        "pallets"
    ],
    "wof:name":"Excel Formes & Stereos Ltd.",
    "wof:placetype":"venue"
},
  "geometry": {"coordinates":[0.3387399912,51.5688018799],"type":"Point"}
}