{
  "type": "Feature",
  "properties": {
    "iso:country":"GB",
    "sg:address":"252 Mackie Avenue",
    "sg:city":"Brighton",
    "sg:classifiers":[
        {
            "category":"Retail",
            "subcategory":"Driving School",
            "type":"Services"
        }
    ],
    "sg:postcode":"BN1 8SD",
    "sg:province":"East Sussex",
    "wof:name":"Keith Wells",
    "wof:placetype":"venue"
},
  "geometry": {"coordinates":[-0.129234,50.869442],"type":"Point"}
}