{
  "type": "Feature",
  "properties": {
    "addr:full":"1180 Coventry Road, Yardley Birmingham West Midlands B25 8DA",
    "addr:housenumber":"1180",
    "addr:postcode":"b25 8da",
    "addr:street":"Coventry Road",
    "iso:country":"GB",
    "sg:address":"1180 Coventry Road, Yardley",
    "sg:city":"Birmingham",
    "sg:classifiers":[
        {
            "category":"Personal",
            "subcategory":"Beauty Salon",
            "type":"Services"
        }
    ],
    "sg:phone":"+44 121 605 7775",
    "sg:postcode":"B25 8DA",
    "sg:province":"West Midlands",
    "sg:tags":[
        "unisex",
        "hairdresser"
    ],
    "wof:name":"Noeleens's Unisex Hair Salon",
    "wof:placetype":"venue"
},
  "geometry": {"coordinates":[-1.8305569887,52.4632759094],"type":"Point"}
}