{
  "type": "Feature",
  "properties": {
    "addr:full":"10 Sunny Brae Cres Bingley West Yorkshire BD16 4RF",
    "addr:housenumber":"10",
    "addr:postcode":"bd16 4rf",
    "addr:street":"Sunny Brae Cres",
    "iso:country":"GB",
    "sg:address":"10 Sunny Brae Cres",
    "sg:city":"Bingley",
    "sg:classifiers":[
        {
            "category":"Retail",
            "subcategory":"Auto Repair",
            "type":"Services"
        }
    ],
    "sg:phone":"+44 1274 562591",
    "sg:postcode":"BD16 4RF",
    "sg:province":"West Yorkshire",
    "sg:tags":[
        "engine",
        "car",
        "specialist"
    ],
    "wof:name":"Computa Tune",
    "wof:placetype":"venue"
},
  "geometry": {"coordinates":[-1.8200670481,53.8453102112],"type":"Point"}
}