{
  "type": "Feature",
  "properties": {
    "iso:country":"GB",
    "sg:address":"100 Coronation Street",
    "sg:city":"Blackpool",
    "sg:classifiers":[
        {
            "category":"Travel",
            "subcategory":"Hotels & Motels",
            "type":"Entertainment"
        }
    ],
    "sg:phone":"+44 1253 294609",
    "sg:postcode":"FY1 4QQ",
    "sg:province":"Lancashire",
    "wof:name":"Westhead Hotel",
    "wof:placetype":"venue"
},
  "geometry": {"coordinates":[-3.050094,53.813896],"type":"Point"}
}