{
  "type": "Feature",
  "properties": {
    "addr:full":"18 Belmont Road Smethwick West Midlands B66 4EL",
    "addr:housenumber":"18",
    "addr:postcode":"b66 4el",
    "addr:street":"Belmont Road",
    "iso:country":"GB",
    "sg:address":"18 Belmont Road",
    "sg:city":"Smethwick",
    "sg:classifiers":[
        {
            "category":"Professional",
            "subcategory":"Management & Consulting",
            "type":"Services"
        }
    ],
    "sg:phone":"+44 121 434 4747",
    "sg:postcode":"B66 4EL",
    "sg:province":"West Midlands",
    "sg:tags":[
        "consultant",
        "business"
    ],
    "wof:name":"Novatech Consulting Ltd.",
    "wof:placetype":"venue"
},
  "geometry": {"coordinates":[-1.968919,52.47847],"type":"Point"}
}