{
  "type": "Feature",
  "properties": {
    "addr:full":"Adderley House, Leek New Road, Baddeley Grn Stoke-on-trent Staffordshire ST2 7HG",
    "addr:postcode":"st2 7hg",
    "addr:street":"New Road Baddeley Grn",
    "iso:country":"GB",
    "sg:address":"Adderley House, Leek New Road, Baddeley Grn",
    "sg:city":"Stoke-on-trent",
    "sg:classifiers":[
        {
            "category":"Organizations",
            "subcategory":"Membership Organization",
            "type":"Services"
        }
    ],
    "sg:phone":"+44 1782 541246",
    "sg:postcode":"ST2 7HG",
    "sg:province":"Staffordshire",
    "sg:tags":[
        "club"
    ],
    "wof:name":"Baddeley Green Workingmen's Club & Institute Ltd.",
    "wof:placetype":"venue"
},
  "geometry": {"coordinates":[-2.1367840767,53.0596160889],"type":"Point"}
}