{
  "type": "Feature",
  "properties": {
    "addr:full":"Fore St Chulmleigh Devon EX18 7BR",
    "addr:postcode":"ex18 7br",
    "addr:street":"Fore St",
    "iso:country":"GB",
    "sg:address":"Fore St",
    "sg:city":"Chulmleigh",
    "sg:classifiers":[
        {
            "category":"Retail",
            "subcategory":"Repair Shop",
            "type":"Services"
        }
    ],
    "sg:postcode":"EX18 7BR",
    "sg:province":"Devon",
    "sg:tags":[
        "radio",
        "television",
        "video"
    ],
    "wof:name":"Dowling,Michael,",
    "wof:placetype":"venue"
},
  "geometry": {"coordinates":[-3.867984,50.912079],"type":"Point"}
}