{
  "type": "Feature",
  "properties": {
    "iso:country":"GB",
    "sg:address":"30 Adam Close",
    "sg:city":"High Wycombe",
    "sg:classifiers":[
        {
            "category":"Building & Trades",
            "subcategory":"Landscaping Services",
            "type":"Services"
        }
    ],
    "sg:phone":"+44 1494 531440",
    "sg:postcode":"HP13 6BY",
    "sg:province":"Buckinghamshire",
    "sg:tags":[
        "gardening"
    ],
    "wof:name":"R B Jenkinson",
    "wof:placetype":"venue"
},
  "geometry": {"coordinates":[-0.737326026,51.6351051331],"type":"Point"}
}