{
  "type": "Feature",
  "properties": {
    "iso:country":"GB",
    "sg:address":"42 Woodstock Road East, Begbroke",
    "sg:city":"Kidlington",
    "sg:classifiers":[
        {
            "category":"Professional",
            "subcategory":"Engineering",
            "type":"Services"
        }
    ],
    "sg:phone":"+44 1865 372820",
    "sg:postcode":"OX5 1RG",
    "sg:province":"Buckinghamshire",
    "sg:tags":[
        "civil",
        "engineer"
    ],
    "wof:name":"Civation Ltd.",
    "wof:placetype":"venue"
},
  "geometry": {"coordinates":[-1.30281,51.808212],"type":"Point"}
}