{
  "type": "Feature",
  "properties": {
    "iso:country":"GB",
    "sg:address":"White Rose Ave, New Earswick",
    "sg:city":"York",
    "sg:classifiers":[
        {
            "category":"Social Services",
            "subcategory":"Retirement Home",
            "type":"Services"
        }
    ],
    "sg:postcode":"YO32 4AD",
    "sg:province":"North Yorkshire",
    "sg:tags":[
        "residential",
        "care"
    ],
    "wof:name":"Garth (The)",
    "wof:placetype":"venue"
},
  "geometry": {"coordinates":[-1.0762319565,53.9902877808],"type":"Point"}
}