{
  "type": "Feature",
  "properties": {
    "addr:full":"61 Baxtergate Whitby North Yorkshire YO21 1BL",
    "addr:housenumber":"61",
    "addr:postcode":"yo21 1bl",
    "addr:street":"Baxtergate",
    "iso:country":"GB",
    "sg:address":"61 Baxtergate",
    "sg:city":"Whitby",
    "sg:classifiers":[
        {
            "category":"Shopping",
            "subcategory":"Pharmacy",
            "type":"Retail Goods"
        }
    ],
    "sg:phone":"+44 1947 602184",
    "sg:postcode":"YO21 1BL",
    "sg:province":"North Yorkshire",
    "sg:tags":[
        "pharmacist",
        "chemist"
    ],
    "wof:name":"Moss Chemists",
    "wof:placetype":"venue"
},
  "geometry": {"coordinates":[-0.6152740121,54.4856872559],"type":"Point"}
}