{
  "type": "Feature",
  "properties": {
    "addr:full":"188 Pontefract Road, Cudworth Barnsley South Yorkshire S72 8BE",
    "addr:housenumber":"188",
    "addr:postcode":"s72 8be",
    "addr:street":"Pontefract Road;Yorkshire",
    "iso:country":"GB",
    "sg:address":"188 Pontefract Road, Cudworth",
    "sg:city":"Barnsley",
    "sg:classifiers":[
        {
            "category":"Fast Food",
            "type":"Food & Drink"
        }
    ],
    "sg:phone":"+44 1226 717661",
    "sg:postcode":"S72 8BE",
    "sg:province":"South Yorkshire",
    "sg:tags":[
        "away",
        "take"
    ],
    "wof:name":"Joanne Francis",
    "wof:placetype":"venue"
},
  "geometry": {"coordinates":[-1.412039,53.584045],"type":"Point"}
}