{
  "type": "Feature",
  "properties": {
    "addr:full":"Moat Rd Colchester Essex CO6 3LU",
    "addr:postcode":"co6 3lu",
    "addr:street":"Moat Rd",
    "iso:country":"GB",
    "sg:address":"Moat Rd",
    "sg:city":"Colchester",
    "sg:classifiers":[
        {
            "category":"Bars & Pubs",
            "type":"Food & Drink"
        }
    ],
    "sg:phone":"+44 1206 240446",
    "sg:postcode":"CO6 3LU",
    "sg:province":"Essex",
    "sg:tags":[
        "pubs",
        "inn"
    ],
    "wof:name":"The Vulcan Inn",
    "wof:placetype":"venue"
},
  "geometry": {"coordinates":[0.803953,51.923317],"type":"Point"}
}