{
  "type": "Feature",
  "properties": {
    "iso:country":"GB",
    "sg:address":"161 Upperthorpe Road",
    "sg:city":"Sheffield",
    "sg:classifiers":[
        {
            "category":"Home & Garden",
            "subcategory":"Furniture",
            "type":"Retail Goods"
        },
        {
            "category":"Home & Garden",
            "subcategory":"Carpets & Floor Coverings",
            "type":"Retail Goods"
        }
    ],
    "sg:phone":"+44 114 273 7805",
    "sg:postcode":"S6 3EB",
    "sg:province":"South Yorkshire",
    "sg:tags":[
        "retailer",
        "rug"
    ],
    "wof:name":"A Twelvetree",
    "wof:placetype":"venue"
},
  "geometry": {"coordinates":[-1.485368,53.389557],"type":"Point"}
}