{
  "type": "Feature",
  "properties": {
    "addr:full":"102 Newgate St London Greater London EC1A 7AP",
    "addr:housenumber":"102",
    "addr:postcode":"ec1a 7ap",
    "addr:street":"Newgate St",
    "iso:country":"GB",
    "sg:address":"102 Newgate St",
    "sg:city":"London",
    "sg:classifiers":[
        {
            "category":"Professional",
            "subcategory":"Employment Agencies",
            "type":"Services"
        }
    ],
    "sg:postcode":"EC1A 7AP",
    "sg:province":"Greater London",
    "sg:tags":[
        "consultant"
    ],
    "wof:name":"Clark,Susanna,",
    "wof:placetype":"venue"
},
  "geometry": {"coordinates":[-0.0996199995,51.5156784058],"type":"Point"}
}