{
  "type": "Feature",
  "properties": {
    "iso:country":"GB",
    "sg:address":"470 Kilmarnock Road",
    "sg:city":"Glasgow",
    "sg:classifiers":[
        {
            "category":"Travel",
            "subcategory":"Hotels & Motels",
            "type":"Entertainment"
        }
    ],
    "sg:phone":"+44 141 637 2353",
    "sg:postcode":"G43 2BB",
    "sg:province":"Glasgow City",
    "wof:name":"Tinto Firs Thistle Hotel",
    "wof:placetype":"venue"
},
  "geometry": {"coordinates":[-4.2897548676,55.8155097961],"type":"Point"}
}