{
  "type": "Feature",
  "properties": {
    "addr:full":"Harthill Road, Fauldhouse Bathgate North Lanarkshire EH47 9HS",
    "addr:postcode":"eh47 9hs",
    "addr:street":"Harthill Road;Bathgate",
    "iso:country":"GB",
    "sg:address":"Harthill Road, Fauldhouse",
    "sg:city":"Bathgate",
    "sg:classifiers":[
        {
            "category":"Education",
            "subcategory":"School",
            "type":"Public Place"
        },
        {
            "category":"Government",
            "subcategory":"Office",
            "type":"Public Place"
        }
    ],
    "sg:phone":"+44 1501 770210",
    "sg:postcode":"EH47 9HS",
    "sg:province":"North Lanarkshire",
    "sg:tags":[
        "local",
        "authority"
    ],
    "wof:name":"Falla Hill Primary School",
    "wof:placetype":"venue"
},
  "geometry": {"coordinates":[-3.7066040039,55.8278808594],"type":"Point"}
}