{
  "type": "Feature",
  "properties": {
    "iso:country":"GB",
    "sg:address":"School La",
    "sg:city":"Skelmersdale",
    "sg:classifiers":[
        {
            "category":"Health Services",
            "subcategory":"Podiatrist",
            "type":"Services"
        }
    ],
    "sg:phone":"+44 1695 625064",
    "sg:postcode":"WN8 0LW",
    "sg:province":"Lancashire",
    "sg:tags":[
        "podiatrists",
        "chiropodist"
    ],
    "wof:name":"Karen McGibbon",
    "wof:placetype":"venue"
},
  "geometry": {"coordinates":[-2.727524,53.559143],"type":"Point"}
}