{
  "type": "Feature",
  "properties": {
    "addr:full":"Stockport Rd Manchester Greater Manchester M19 3BS",
    "addr:postcode":"m19 3bs",
    "addr:street":"Stockport Rd",
    "iso:country":"GB",
    "sg:address":"Stockport Rd",
    "sg:city":"Manchester",
    "sg:classifiers":[
        {
            "category":"Place Of Worship",
            "type":"Public Place"
        }
    ],
    "sg:phone":"+44 161 256 1335",
    "sg:postcode":"M19 3BS",
    "sg:province":"Greater Manchester",
    "wof:name":"St Peter C Of E Church",
    "wof:placetype":"venue"
},
  "geometry": {"coordinates":[-2.192009,53.448544],"type":"Point"}
}