{
  "type": "Feature",
  "properties": {
    "addr:full":"11 Grange Terrace Sunderland Tyne and Wear SR2 7DF",
    "addr:housenumber":"11",
    "addr:postcode":"sr2 7df",
    "addr:street":"Grange Terrace",
    "iso:country":"GB",
    "sg:address":"11 Grange Terrace",
    "sg:city":"Sunderland",
    "sg:classifiers":[
        {
            "category":"Health Services",
            "subcategory":"Dentist",
            "type":"Services"
        }
    ],
    "sg:phone":"+44 191 567 4570",
    "sg:postcode":"SR2 7DF",
    "sg:province":"Tyne and Wear",
    "wof:name":"Dental Surgery",
    "wof:placetype":"venue"
},
  "geometry": {"coordinates":[-1.385235,54.900574],"type":"Point"}
}