{
  "type": "Feature",
  "properties": {
    "addr:full":"Wide Lane Southampton Hampshire SO18 2NQ",
    "addr:postcode":"so18 2nq",
    "addr:street":"Wide Lane",
    "iso:country":"GB",
    "sg:address":"Wide Lane",
    "sg:city":"Southampton",
    "sg:classifiers":[
        {
            "category":"Arena",
            "subcategory":"Sports Club",
            "type":"Entertainment"
        }
    ],
    "sg:phone":"+44 23 8090 8909",
    "sg:postcode":"SO18 2NQ",
    "sg:province":"Hampshire",
    "wof:name":"Ford Sports & Social Club",
    "wof:placetype":"venue"
},
  "geometry": {"coordinates":[-1.370639,50.943829],"type":"Point"}
}