{
  "type": "Feature",
  "properties": {
    "addr:full":"194 Darkes Lane Potters Bar Greater London EN6 1AB",
    "addr:housenumber":"194",
    "addr:postcode":"en6 1ab",
    "addr:street":"Darkes Lane",
    "iso:country":"GB",
    "sg:address":"194 Darkes Lane",
    "sg:city":"Potters Bar",
    "sg:classifiers":[
        {
            "category":"Autos & Motor Vehicles",
            "subcategory":"Auto Supplies",
            "type":"Retail Goods"
        }
    ],
    "sg:phone":"+44 1707 852560",
    "sg:postcode":"EN6 1AB",
    "sg:province":"Greater London",
    "sg:tags":[
        "exhaust",
        "absorber",
        "shock"
    ],
    "wof:name":"C & C Exhaust Centre",
    "wof:placetype":"venue"
},
  "geometry": {"coordinates":[-0.1898220032,51.7000656128],"type":"Point"}
}