{
  "type": "Feature",
  "properties": {
    "addr:full":"Town Lane, Charnock Richard Chorley Lancashire PR7 5HQ",
    "addr:postcode":"pr7 5hq",
    "addr:street":"Town Lane",
    "iso:country":"GB",
    "sg:address":"Town Lane, Charnock Richard",
    "sg:city":"Chorley",
    "sg:classifiers":[
        {
            "category":"Freight",
            "type":"Transportation"
        }
    ],
    "sg:phone":"+44 1257 791447",
    "sg:postcode":"PR7 5HQ",
    "sg:province":"Lancashire",
    "sg:tags":[
        "haulage",
        "transport",
        "road"
    ],
    "wof:name":"T Stafford",
    "wof:placetype":"venue"
},
  "geometry": {"coordinates":[-2.682942,53.620899],"type":"Point"}
}