{
  "type": "Feature",
  "properties": {
    "addr:full":"Unit 31 Tallon Road Brentwood Essex CM13 1TE",
    "addr:housenumber":"unit 31",
    "addr:postcode":"cm13 1te",
    "addr:street":"Tallon Road",
    "iso:country":"GB",
    "sg:address":"Unit 31 Tallon Road",
    "sg:city":"Brentwood",
    "sg:classifiers":[
        {
            "category":"Communications",
            "subcategory":"Newspaper",
            "type":"Services"
        }
    ],
    "sg:phone":"+44 1277 205700",
    "sg:postcode":"CM13 1TE",
    "sg:province":"Essex",
    "sg:tags":[
        "magazine"
    ],
    "wof:name":"G & M Fashions (Leisure) Ltd.",
    "wof:placetype":"venue"
},
  "geometry": {"coordinates":[0.35675,51.637032],"type":"Point"}
}