{
  "type": "Feature",
  "properties": {
    "iso:country":"GB",
    "sg:address":"The Holmewood Miners' Institute, Heath Road Holmewood",
    "sg:city":"Chesterfield",
    "sg:classifiers":[
        {
            "category":"Organizations",
            "subcategory":"Membership Organization",
            "type":"Services"
        }
    ],
    "sg:phone":"+44 1246 850429",
    "sg:postcode":"S42 5RB",
    "sg:province":"Derbyshire",
    "sg:tags":[
        "club"
    ],
    "wof:name":"Holmewood Miners' Welfare Social Club Ltd.",
    "wof:placetype":"venue"
},
  "geometry": {"coordinates":[-1.3521399498,53.1890487671],"type":"Point"}
}