{
  "type": "Feature",
  "properties": {
    "iso:country":"GB",
    "sg:address":"22 Reservoir Street",
    "sg:city":"Rochdale",
    "sg:classifiers":[
        {
            "category":"Building & Trades",
            "subcategory":"Construction",
            "type":"Services"
        }
    ],
    "sg:phone":"+44 1706 342542",
    "sg:postcode":"OL16 2XH",
    "sg:province":"Lancashire",
    "sg:tags":[
        "builder"
    ],
    "wof:name":"Bernard Ward",
    "wof:placetype":"venue"
},
  "geometry": {"coordinates":[-2.134773,53.622269],"type":"Point"}
}