{
  "type": "Feature",
  "properties": {
    "addr:full":"141 Hilderthorpe Road Bridlington East Riding of Yorkshire YO15 3AY",
    "addr:housenumber":"141",
    "addr:postcode":"yo15 3ay",
    "addr:street":"Hilderthorpe Road",
    "iso:country":"GB",
    "sg:address":"141 Hilderthorpe Road",
    "sg:city":"Bridlington",
    "sg:classifiers":[
        {
            "category":"Home & Garden",
            "subcategory":"Furniture",
            "type":"Retail Goods"
        }
    ],
    "sg:phone":"+44 1262 400640",
    "sg:postcode":"YO15 3AY",
    "sg:province":"East Riding of Yorkshire",
    "wof:name":"Rymer Schorah Furniture",
    "wof:placetype":"venue"
},
  "geometry": {"coordinates":[-0.199219,54.083179],"type":"Point"}
}