{
  "type": "Feature",
  "properties": {
    "iso:country":"GB",
    "sg:address":"The Grain Store, Woolpacks Yard",
    "sg:city":"Wakefield",
    "sg:classifiers":[
        {
            "category":"Professional",
            "subcategory":"Lawyer & Legal Services",
            "type":"Services"
        }
    ],
    "sg:phone":"+44 1924 290029",
    "sg:postcode":"WF1 2SH",
    "sg:province":"West Yorkshire",
    "sg:tags":[
        "solicitor"
    ],
    "wof:name":"Jones Goodall",
    "wof:placetype":"venue"
},
  "geometry": {"coordinates":[-1.5012899637,53.6829986572],"type":"Point"}
}