{
  "type": "Feature",
  "properties": {
    "iso:country":"GB",
    "sg:address":"Spencer House, Market Lane, Swalwell",
    "sg:city":"Newcastle Upon Tyne",
    "sg:classifiers":[
        {
            "category":"Building & Trades",
            "subcategory":"Construction",
            "type":"Services"
        }
    ],
    "sg:phone":"+44 191 420 0162",
    "sg:postcode":"NE16 3DS",
    "sg:province":"Durham",
    "sg:tags":[
        "builder"
    ],
    "wof:name":"Spencer House Construction",
    "wof:placetype":"venue"
},
  "geometry": {"coordinates":[-1.6830739975,54.954536438],"type":"Point"}
}