{
  "type": "Feature",
  "properties": {
    "iso:country":"GB",
    "sg:address":"Unit C9 Tidys Indust Est",
    "sg:city":"Hassocks",
    "sg:classifiers":[
        {
            "category":"Building & Trades",
            "subcategory":"Construction",
            "type":"Services"
        }
    ],
    "sg:phone":"+44 1444 241877",
    "sg:postcode":"BN6 8SG",
    "sg:province":"East Sussex",
    "sg:tags":[
        "builder"
    ],
    "wof:name":"Woodfern Developments Ltd",
    "wof:placetype":"venue"
},
  "geometry": {"coordinates":[-0.1402689964,50.9239959717],"type":"Point"}
}