{
  "type": "Feature",
  "properties": {
    "iso:country":"GB",
    "sg:address":"20 Gawer Park",
    "sg:city":"Chester",
    "sg:classifiers":[
        {
            "category":"Organizations",
            "subcategory":"Community Association",
            "type":"Services"
        }
    ],
    "sg:phone":"+44 1244 376766",
    "sg:postcode":"CH1 4DA",
    "sg:province":"Cheshire",
    "sg:tags":[
        "relation",
        "public"
    ],
    "wof:name":"Marketing Projects Ltd.",
    "wof:placetype":"venue"
},
  "geometry": {"coordinates":[-2.8959419727,53.205493927],"type":"Point"}
}