{
  "type": "Feature",
  "properties": {
    "iso:country":"GB",
    "sg:address":"6 Hamilton Court",
    "sg:city":"Normanton",
    "sg:classifiers":[
        {
            "category":"Shopping",
            "subcategory":"Computers & Home Electronics",
            "type":"Retail Goods"
        },
        {
            "category":"Professional",
            "subcategory":"Computer Services",
            "type":"Services"
        }
    ],
    "sg:phone":"+44 1924 890088",
    "sg:postcode":"WF6 2TE",
    "sg:province":"West Yorkshire",
    "sg:tags":[
        "software",
        "sales",
        "system"
    ],
    "sg:website":"http://www.custom-micros.co.uk",
    "wof:name":"Custom Micros",
    "wof:placetype":"venue"
},
  "geometry": {"coordinates":[-1.417128,53.703743],"type":"Point"}
}