{
  "type": "Feature",
  "properties": {
    "iso:country":"GB",
    "sg:address":"Court Oak Rd, Harborne",
    "sg:city":"Birmingham",
    "sg:classifiers":[
        {
            "category":"Social Services",
            "type":"Services"
        }
    ],
    "sg:phone":"+44 121 428 2323",
    "sg:postcode":"B17 9AB",
    "sg:province":"West Midlands",
    "wof:name":"Yewcroft Mental Health Resource Centre",
    "wof:placetype":"venue"
},
  "geometry": {"coordinates":[-1.9716320038,52.4603271484],"type":"Point"}
}