{
  "type": "Feature",
  "properties": {
    "addr:full":"72 High St New Malden Surrey KT3 4ET",
    "addr:housenumber":"72",
    "addr:postcode":"kt3 4et",
    "addr:street":"High St",
    "iso:country":"GB",
    "sg:address":"72 High St",
    "sg:city":"New Malden",
    "sg:classifiers":[
        {
            "category":"Shopping",
            "subcategory":"Department Store",
            "type":"Retail Goods"
        }
    ],
    "sg:phone":"+44 20 8942 4282",
    "sg:postcode":"KT3 4ET",
    "sg:province":"Surrey",
    "wof:name":"Pricebusters (Retail) Ltd",
    "wof:placetype":"venue"
},
  "geometry": {"coordinates":[-0.2562580109,51.4015541077],"type":"Point"}
}