{
  "type": "Feature",
  "properties": {
    "addr:full":"187-189 Lower Oxford Street Swansea Neath Port Talbot SA1 3JA",
    "addr:housenumber":"187-189",
    "addr:postcode":"sa1 3ja",
    "addr:street":"Lower Oxford Street",
    "iso:country":"GB",
    "sg:address":"187-189 Lower Oxford Street",
    "sg:city":"Swansea",
    "sg:classifiers":[
        {
            "category":"Retail",
            "subcategory":"Auto Rental",
            "type":"Services"
        }
    ],
    "sg:phone":"+44 1792 650526",
    "sg:postcode":"SA1 3JA",
    "sg:province":"Neath Port Talbot",
    "sg:tags":[
        "car"
    ],
    "wof:name":"Europcar (U K) Ltd.",
    "wof:placetype":"venue"
},
  "geometry": {"coordinates":[-3.9437339306,51.6202087402],"type":"Point"}
}