{
  "type": "Feature",
  "properties": {
    "addr:full":"Accessory Ho, 24 Dalston Gdns Stanmore Greater London HA7 1BU",
    "addr:housenumber":"24",
    "addr:postcode":"ha7 1bu",
    "addr:street":"Dalston Gdns",
    "iso:country":"GB",
    "sg:address":"Accessory Ho, 24 Dalston Gdns",
    "sg:city":"Stanmore",
    "sg:classifiers":[
        {
            "category":"Shopping",
            "subcategory":"Clothing, Apparel, & Fashions",
            "type":"Retail Goods"
        }
    ],
    "sg:phone":"+44 20 8263 5050",
    "sg:postcode":"HA7 1BU",
    "sg:province":"Greater London",
    "sg:tags":[
        "accessory"
    ],
    "wof:name":"Reckless Accessories Ltd",
    "wof:placetype":"venue"
},
  "geometry": {"coordinates":[-0.310409,51.617546],"type":"Point"}
}