{
  "type": "Feature",
  "properties": {
    "iso:country":"GB",
    "sg:address":"Unit 7, Festival Drive",
    "sg:city":"Loughborough",
    "sg:classifiers":[
        {
            "category":"Food & Beverages",
            "subcategory":"Meat & Fish",
            "type":"Retail Goods"
        }
    ],
    "sg:phone":"+44 1509 239249",
    "sg:postcode":"LE11 5XJ",
    "sg:province":"Leicestershire",
    "sg:tags":[
        "merchant"
    ],
    "wof:name":"Sea Prime Seafoods Ltd.",
    "wof:placetype":"venue"
},
  "geometry": {"coordinates":[-1.214379,52.783104],"type":"Point"}
}