{
  "type": "Feature",
  "properties": {
    "addr:full":"South Street Deal Kent CT14 7AN",
    "addr:postcode":"ct14 7an",
    "addr:street":"South Street Deal",
    "iso:country":"GB",
    "sg:address":"South Street",
    "sg:city":"Deal",
    "sg:classifiers":[
        {
            "category":"Retail",
            "subcategory":"Auto Repair",
            "type":"Services"
        }
    ],
    "sg:phone":"+44 1304 368544",
    "sg:postcode":"CT14 7AN",
    "sg:province":"Kent",
    "sg:tags":[
        "modification",
        "garage"
    ],
    "wof:name":"South Court Garage",
    "wof:placetype":"venue"
},
  "geometry": {"coordinates":[1.4029350281,51.2221794128],"type":"Point"}
}