{
  "type": "Feature",
  "properties": {
    "iso:country":"GB",
    "sg:address":"Main St",
    "sg:city":"Falkirk",
    "sg:classifiers":[
        {
            "category":"Food & Beverages",
            "subcategory":"Candy",
            "type":"Retail Goods"
        }
    ],
    "sg:phone":"+44 1324 632391",
    "sg:postcode":"FK1 4EG",
    "sg:province":"Falkirk",
    "sg:tags":[
        "confectionery"
    ],
    "wof:name":"Sugar 'N' Spice",
    "wof:placetype":"venue"
},
  "geometry": {"coordinates":[-3.810873,56.003048],"type":"Point"}
}