{
  "type": "Feature",
  "properties": {
    "iso:country":"GB",
    "sg:address":"19 Market Walk",
    "sg:city":"Newton Abbot",
    "sg:classifiers":[
        {
            "category":"Fast Food",
            "type":"Food & Drink"
        },
        {
            "category":"Restaurant",
            "type":"Food & Drink"
        }
    ],
    "sg:postcode":"TQ12 2RX",
    "sg:province":"Devon",
    "sg:tags":[
        "away",
        "take"
    ],
    "wof:name":"A Lewis",
    "wof:placetype":"venue"
},
  "geometry": {"coordinates":[-3.6117761135,50.5311927795],"type":"Point"}
}