{
  "type": "Feature",
  "properties": {
    "iso:country":"GB",
    "sg:address":"108 Farm Lane",
    "sg:city":"London",
    "sg:classifiers":[
        {
            "category":"Real Estate",
            "subcategory":"Real Estate Operator",
            "type":"Services"
        }
    ],
    "sg:phone":"+44 20 7386 5900",
    "sg:postcode":"SW6 1QH",
    "sg:province":"Greater London",
    "sg:tags":[
        "letting",
        "agent"
    ],
    "wof:name":"Rhonda Hughes",
    "wof:placetype":"venue"
},
  "geometry": {"coordinates":[-0.196643,51.483456],"type":"Point"}
}