{
  "type": "Feature",
  "properties": {
    "addr:full":"Westerhouse Road Glasgow Glasgow City G34 9DT",
    "addr:postcode":"g34 9dt",
    "addr:street":"Westerhouse Road",
    "iso:country":"GB",
    "sg:address":"Westerhouse Road",
    "sg:city":"Glasgow",
    "sg:classifiers":[
        {
            "category":"Transit Center",
            "subcategory":"Freight",
            "type":"Transportation"
        },
        {
            "category":"Commercial Area",
            "type":"Public Place"
        }
    ],
    "sg:phone":"+44 141 773 0114",
    "sg:postcode":"G34 9DT",
    "sg:province":"Glasgow City",
    "sg:tags":[
        "shop",
        "shopping",
        "centre"
    ],
    "wof:name":"Shandwick Square Shopping Centre",
    "wof:placetype":"venue"
},
  "geometry": {"coordinates":[-4.118319,55.86908],"type":"Point"}
}