{
  "type": "Feature",
  "properties": {
    "iso:country":"GB",
    "sg:address":"1 St Flora's Road",
    "sg:city":"Littlehampton",
    "sg:classifiers":[
        {
            "category":"Place Of Worship",
            "type":"Public Place"
        }
    ],
    "sg:postcode":"BN17 6BD",
    "sg:province":"West Sussex",
    "wof:name":"Parkside Evangelical Church",
    "wof:placetype":"venue"
},
  "geometry": {"coordinates":[-0.533861,50.804127],"type":"Point"}
}