{
  "type": "Feature",
  "properties": {
    "addr:full":"18 Castle View West Kilbride North Ayrshire KA23 9HD",
    "addr:housenumber":"18",
    "addr:postcode":"ka23 9hd",
    "addr:street":"Castle View",
    "iso:country":"GB",
    "sg:address":"18 Castle View",
    "sg:city":"West Kilbride",
    "sg:classifiers":[
        {
            "category":"Personal",
            "type":"Services"
        }
    ],
    "sg:phone":"+44 1294 823957",
    "sg:postcode":"KA23 9HD",
    "sg:province":"North Ayrshire",
    "sg:tags":[
        "wedding"
    ],
    "wof:name":"Fairytale Favours",
    "wof:placetype":"venue"
},
  "geometry": {"coordinates":[-4.8538770676,55.6983528137],"type":"Point"}
}