{
  "type": "Feature",
  "properties": {
    "addr:full":"19 Desborough Ave High Wycombe Buckinghamshire HP11 2RS",
    "addr:housenumber":"19",
    "addr:postcode":"hp11 2rs",
    "addr:street":"Desborough Ave",
    "iso:country":"GB",
    "sg:address":"19 Desborough Ave",
    "sg:city":"High Wycombe",
    "sg:classifiers":[
        {
            "category":"Shopping",
            "subcategory":"Music",
            "type":"Retail Goods"
        }
    ],
    "sg:postcode":"HP11 2RS",
    "sg:province":"Buckinghamshire",
    "sg:tags":[
        "record",
        "tape",
        "cd"
    ],
    "wof:name":"O'Neil,David,",
    "wof:placetype":"venue"
},
  "geometry": {"coordinates":[-0.7613540292,51.6333808899],"type":"Point"}
}