{
  "type": "Feature",
  "properties": {
    "addr:full":"10 Windsor Drive Trowbridge Wiltshire BA14 8EA",
    "addr:housenumber":"10",
    "addr:postcode":"ba14 8ea",
    "addr:street":"Windsor Drive",
    "iso:country":"GB",
    "sg:address":"10 Windsor Drive",
    "sg:city":"Trowbridge",
    "sg:classifiers":[
        {
            "category":"Personal",
            "type":"Services"
        },
        {
            "category":"Retail",
            "subcategory":"Laundry & Dry Cleaning",
            "type":"Services"
        }
    ],
    "sg:postcode":"BA14 8EA",
    "sg:province":"Wiltshire",
    "sg:tags":[
        "dressmaker",
        "alteration"
    ],
    "wof:name":"Ivica Clothing",
    "wof:placetype":"venue"
},
  "geometry": {"coordinates":[-2.220554,51.304985],"type":"Point"}
}