{
  "type": "Feature",
  "properties": {
    "iso:country":"GB",
    "sg:address":"Unit 57 Percy Business Park, Rounds Green Road",
    "sg:city":"Oldbury",
    "sg:classifiers":[
        {
            "category":"Manufacturing",
            "subcategory":"Furniture",
            "type":"Manufacturing & Wholesale Goods"
        }
    ],
    "sg:phone":"+44 121 544 4544",
    "sg:postcode":"B69 2RE",
    "sg:province":"West Midlands",
    "sg:tags":[
        "mnfr",
        "garden",
        "patio"
    ],
    "wof:name":"Sense West Crafts",
    "wof:placetype":"venue"
},
  "geometry": {"coordinates":[-2.015845,52.503777],"type":"Point"}
}