{
  "type": "Feature",
  "properties": {
    "addr:full":"Office, Chapelfield Way Cambridge Cambridgeshire CB2 4SY",
    "addr:postcode":"cb2 4sy",
    "addr:street":"Chapelfield Way",
    "iso:country":"GB",
    "sg:address":"Office, Chapelfield Way",
    "sg:city":"Cambridge",
    "sg:classifiers":[
        {
            "category":"Social Services",
            "subcategory":"Adult Care",
            "type":"Services"
        }
    ],
    "sg:phone":"+44 1223 837734",
    "sg:postcode":"CB2 4SY",
    "sg:province":"Cambridgeshire",
    "sg:tags":[
        "housing",
        "sheltered"
    ],
    "wof:name":"Chapelfield Way Sheltered Office",
    "wof:placetype":"venue"
},
  "geometry": {"coordinates":[0.1714400053,52.1253166199],"type":"Point"}
}