{
  "type": "Feature",
  "properties": {
    "iso:country":"GB",
    "sg:address":"58 South St",
    "sg:city":"Exeter",
    "sg:classifiers":[
        {
            "category":"Real Estate",
            "subcategory":"Real Estate Agent",
            "type":"Services"
        }
    ],
    "sg:phone":"+44 1392 437151",
    "sg:postcode":"EX1 1EE",
    "sg:province":"Devon",
    "wof:name":"Mcmillan International Property Shop",
    "wof:placetype":"venue"
},
  "geometry": {"coordinates":[-3.5303359032,50.7204208374],"type":"Point"}
}