{
  "type": "Feature",
  "properties": {
    "iso:country":"GB",
    "sg:address":"Rosemary 18 Homestead Rd, Chelsfield Park Orpington",
    "sg:city":"Orpington",
    "sg:classifiers":[
        {
            "category":"Food & Beverages",
            "subcategory":"Specialty",
            "type":"Retail Goods"
        }
    ],
    "sg:phone":"+44 1689 853077",
    "sg:postcode":"BR6 6HW",
    "sg:province":"Kent",
    "sg:tags":[
        "dietetic",
        "homogenised"
    ],
    "wof:name":"Nature's Sunshine Distributor",
    "wof:placetype":"venue"
},
  "geometry": {"coordinates":[0.10337,51.355701],"type":"Point"}
}