{
  "type": "Feature",
  "properties": {
    "iso:country":"GB",
    "sg:address":"352 Kings Park Avenue",
    "sg:city":"Glasgow",
    "sg:classifiers":[
        {
            "category":"Food & Beverages",
            "subcategory":"Meat & Fish",
            "type":"Retail Goods"
        }
    ],
    "sg:phone":"+44 141 647 6753",
    "sg:postcode":"G73 2AL",
    "sg:province":"Glasgow City",
    "sg:tags":[
        "butcher"
    ],
    "wof:name":"Lothian Butchers",
    "wof:placetype":"venue"
},
  "geometry": {"coordinates":[-4.2264828682,55.8186569214],"type":"Point"}
}