{
  "type": "Feature",
  "properties": {
    "addr:full":"21 Manor Place Edinburgh City of Edinburgh EH3 7DX",
    "addr:housenumber":"21",
    "addr:postcode":"eh3 7dx",
    "addr:street":"Manor Place Edinburgh",
    "iso:country":"GB",
    "sg:address":"21 Manor Place",
    "sg:city":"Edinburgh",
    "sg:classifiers":[
        {
            "category":"Professional",
            "subcategory":"Management & Consulting",
            "type":"Services"
        },
        {
            "category":"Banks & Credit Unions",
            "subcategory":"Investment Brokerage",
            "type":"Services"
        }
    ],
    "sg:phone":"+44 131 226 2221",
    "sg:postcode":"EH3 7DX",
    "sg:province":"City of Edinburgh",
    "sg:tags":[
        "consultant",
        "promotion",
        "sale",
        "sales"
    ],
    "wof:name":"Marketing Store",
    "wof:placetype":"venue"
},
  "geometry": {"coordinates":[-3.214751,55.948467],"type":"Point"}
}