{
  "type": "Feature",
  "properties": {
    "iso:country":"GB",
    "sg:address":"Whanland, Farnell",
    "sg:city":"Brechin",
    "sg:classifiers":[
        {
            "category":"Freight",
            "type":"Transportation"
        }
    ],
    "sg:phone":"+44 1674 674253",
    "sg:postcode":"DD9 6UF",
    "sg:province":"Aberdeenshire",
    "sg:tags":[
        "haulage",
        "transport",
        "road"
    ],
    "wof:name":"R & N Cessford",
    "wof:placetype":"venue"
},
  "geometry": {"coordinates":[-2.6101539135,56.6900901794],"type":"Point"}
}