{
  "type": "Feature",
  "properties": {
    "iso:country":"GB",
    "sg:address":"Newport Rd, Woughton-on-the-green",
    "sg:city":"Milton Keynes",
    "sg:classifiers":[
        {
            "category":"Bars & Pubs",
            "type":"Food & Drink"
        },
        {
            "category":"Community Center",
            "subcategory":"Social",
            "type":"Public Place"
        }
    ],
    "sg:phone":"+44 1908 679489",
    "sg:postcode":"MK6 3BS",
    "sg:province":"Buckinghamshire",
    "sg:tags":[
        "pubs",
        "house",
        "inn",
        "activity"
    ],
    "wof:name":"Ye Olde Swan",
    "wof:placetype":"venue"
},
  "geometry": {"coordinates":[-0.7168390155,52.0194511414],"type":"Point"}
}