{
  "type": "Feature",
  "properties": {
    "iso:country":"GB",
    "sg:address":"Mercian House, 18 Coventry Street",
    "sg:city":"Kidderminster",
    "sg:classifiers":[
        {
            "category":"Insurance",
            "subcategory":"Insurance Agent",
            "type":"Services"
        }
    ],
    "sg:phone":"+44 1562 862424",
    "sg:postcode":"DY10 2BG",
    "sg:province":"Staffordshire",
    "wof:name":"Church Feild",
    "wof:placetype":"venue"
},
  "geometry": {"coordinates":[-2.246726,52.389015],"type":"Point"}
}