{
  "type": "Feature",
  "properties": {
    "iso:country":"GB",
    "sg:address":"145 Townhill Road",
    "sg:city":"Dunfermline",
    "sg:classifiers":[
        {
            "category":"Bars & Pubs",
            "type":"Food & Drink"
        }
    ],
    "sg:phone":"+44 1383 731365",
    "sg:postcode":"KY12 0DS",
    "sg:province":"Fife",
    "sg:tags":[
        "pubs",
        "inn"
    ],
    "wof:name":"Lauders Bar",
    "wof:placetype":"venue"
},
  "geometry": {"coordinates":[-3.44711,56.081989],"type":"Point"}
}