{
  "type": "Feature",
  "properties": {
    "addr:full":"Church View, Churchtown Helston Cornwall TR12 7HQ",
    "addr:postcode":"tr12 7hq",
    "addr:street":"Church View",
    "iso:country":"GB",
    "sg:address":"Church View, Churchtown",
    "sg:city":"Helston",
    "sg:classifiers":[
        {
            "category":"Food & Beverages",
            "subcategory":"Meat & Fish",
            "type":"Retail Goods"
        }
    ],
    "sg:phone":"+44 1326 240203",
    "sg:postcode":"TR12 7HQ",
    "sg:province":"Cornwall",
    "sg:tags":[
        "butcher"
    ],
    "wof:name":"P A Gilbert",
    "wof:placetype":"venue"
},
  "geometry": {"coordinates":[-5.244488,50.046314],"type":"Point"}
}