{
  "type": "Feature",
  "properties": {
    "addr:full":"14 Market Street Bury Lancashire BL9 0AJ",
    "addr:housenumber":"14",
    "addr:postcode":"bl9 0aj",
    "addr:street":"Market Street",
    "iso:country":"GB",
    "sg:address":"14 Market Street",
    "sg:city":"Bury",
    "sg:classifiers":[
        {
            "category":"Real Estate",
            "subcategory":"Real Estate Agent",
            "type":"Services"
        }
    ],
    "sg:phone":"+44 161 761 1215",
    "sg:postcode":"BL9 0AJ",
    "sg:province":"Lancashire",
    "wof:name":"W D C Estates",
    "wof:placetype":"venue"
},
  "geometry": {"coordinates":[-2.2976601124,53.593082428],"type":"Point"}
}