{
  "type": "Feature",
  "properties": {
    "iso:country":"GB",
    "sg:address":"17, Pennine Street,, Pennine Drive,",
    "sg:city":"London",
    "sg:classifiers":[
        {
            "category":"Professional",
            "subcategory":"Computer Services",
            "type":"Services"
        }
    ],
    "sg:postcode":"NW2 1NT",
    "sg:province":"Greater London",
    "sg:tags":[
        "system",
        "software"
    ],
    "wof:name":"Ananta Business Consulting Ltd",
    "wof:placetype":"venue"
},
  "geometry": {"coordinates":[-0.2099,51.567562],"type":"Point"}
}