{
  "type": "Feature",
  "properties": {
    "iso:country":"GB",
    "sg:address":"Malbank School, Welsh Row",
    "sg:city":"Nantwich",
    "sg:classifiers":[
        {
            "category":"Government",
            "subcategory":"Office",
            "type":"Public Place"
        }
    ],
    "sg:phone":"+44 1270 629289",
    "sg:postcode":"CW5 5HD",
    "sg:province":"Cheshire",
    "sg:tags":[
        "local"
    ],
    "wof:name":"Adult Education Office",
    "wof:placetype":"venue"
},
  "geometry": {"coordinates":[-2.5165019035,53.0658912659],"type":"Point"}
}