{
  "type": "Feature",
  "properties": {
    "iso:country":"GB",
    "sg:address":"12 Belper Rd",
    "sg:city":"Derby",
    "sg:classifiers":[
        {
            "category":"Retail",
            "subcategory":"Auto Repair",
            "type":"Services"
        }
    ],
    "sg:postcode":"DE1 3EN",
    "sg:province":"Derbyshire",
    "sg:tags":[
        "modification",
        "garage"
    ],
    "wof:name":"Gibbs,Phillip,",
    "wof:placetype":"venue"
},
  "geometry": {"coordinates":[-1.481760025,52.9306716919],"type":"Point"}
}