{
  "type": "Feature",
  "properties": {
    "addr:full":"100a High Street, Markyate St Albans Hertfordshire AL3 8JZ",
    "addr:housenumber":"100a",
    "addr:postcode":"al3 8jz",
    "addr:street":"High Street",
    "iso:country":"GB",
    "sg:address":"100a High Street, Markyate",
    "sg:city":"St Albans",
    "sg:classifiers":[
        {
            "category":"Personal",
            "subcategory":"Beauty Salon",
            "type":"Services"
        }
    ],
    "sg:postcode":"AL3 8JZ",
    "sg:province":"Hertfordshire",
    "sg:tags":[
        "unisex",
        "hairdresser"
    ],
    "wof:name":"Clare Janes Salon",
    "wof:placetype":"venue"
},
  "geometry": {"coordinates":[-0.459689,51.835304],"type":"Point"}
}