{
  "type": "Feature",
  "properties": {
    "addr:full":"91 Lanehouse Rd, Thornaby Stockton-on-tees Durham TS17 8AB",
    "addr:housenumber":"91",
    "addr:postcode":"ts17 8ab",
    "addr:street":"Lanehouse Rd",
    "iso:country":"GB",
    "sg:address":"91 Lanehouse Rd, Thornaby",
    "sg:city":"Stockton-on-tees",
    "sg:classifiers":[
        {
            "category":"Shopping",
            "subcategory":"Florist",
            "type":"Retail Goods"
        }
    ],
    "sg:postcode":"TS17 8AB",
    "sg:province":"Durham",
    "wof:name":"Riley,Josie,",
    "wof:placetype":"venue"
},
  "geometry": {"coordinates":[-1.3006960154,54.5508766174],"type":"Point"}
}