{
  "type": "Feature",
  "properties": {
    "addr:full":"Fairfield Court, Stourbridge Rd, Fairfield Bromsgrove Worcestershire B61 9NJ",
    "addr:postcode":"b61 9nj",
    "addr:street":"Fairfield Court Stourbridge Rd",
    "iso:country":"GB",
    "sg:address":"Fairfield Court, Stourbridge Rd, Fairfield",
    "sg:city":"Bromsgrove",
    "sg:classifiers":[
        {
            "category":"Home & Garden",
            "subcategory":"Building Materials",
            "type":"Retail Goods"
        }
    ],
    "sg:phone":"+44 1527 877200",
    "sg:postcode":"B61 9NJ",
    "sg:province":"Worcestershire",
    "sg:tags":[
        "equipment",
        "disability"
    ],
    "wof:name":"Magbility",
    "wof:placetype":"venue"
},
  "geometry": {"coordinates":[-2.071159,52.369884],"type":"Point"}
}