{
  "type": "Feature",
  "properties": {
    "addr:full":"9 St. Lukes Terrace Cleckheaton West Yorkshire BD19 6AB",
    "addr:housenumber":"9",
    "addr:postcode":"bd19 6ab",
    "addr:street":"St. Lukes Terrace",
    "iso:country":"GB",
    "sg:address":"9 St. Lukes Terrace",
    "sg:city":"Cleckheaton",
    "sg:classifiers":[
        {
            "category":"Organizations",
            "subcategory":"Non-profit Organization",
            "type":"Services"
        }
    ],
    "sg:phone":"+44 1274 875617",
    "sg:postcode":"BD19 6AB",
    "sg:province":"West Yorkshire",
    "sg:tags":[
        "alarm",
        "system"
    ],
    "wof:name":"Peak Security Systems",
    "wof:placetype":"venue"
},
  "geometry": {"coordinates":[-1.730364,53.722179],"type":"Point"}
}