{
  "type": "Feature",
  "properties": {
    "addr:full":"Belgrave Hall, Belgrave St Leeds West Yorkshire LS2 8DD",
    "addr:postcode":"ls2 8dd",
    "addr:street":"St",
    "iso:country":"GB",
    "sg:address":"Belgrave Hall, Belgrave St",
    "sg:city":"Leeds",
    "sg:classifiers":[
        {
            "category":"Professional",
            "subcategory":"Employment Agencies",
            "type":"Services"
        }
    ],
    "sg:phone":"+44 113 234 7666",
    "sg:postcode":"LS2 8DD",
    "sg:province":"West Yorkshire",
    "sg:tags":[
        "consultant"
    ],
    "wof:name":"Leeds Tec Ltd (The)",
    "wof:placetype":"venue"
},
  "geometry": {"coordinates":[-1.542181015,53.8013420105],"type":"Point"}
}