{
  "type": "Feature",
  "properties": {
    "iso:country":"GB",
    "sg:address":"Colet Court, 100 Hammersmith Road",
    "sg:city":"London",
    "sg:classifiers":[
        {
            "category":"Professional",
            "subcategory":"Management & Consulting",
            "type":"Services"
        }
    ],
    "sg:phone":"+44 20 7637 3434",
    "sg:postcode":"W6 7JP",
    "sg:province":"Greater London",
    "sg:tags":[
        "consultant",
        "business"
    ],
    "wof:name":"International Consulting Services (U K) Ltd.",
    "wof:placetype":"venue"
},
  "geometry": {"coordinates":[-0.21544,51.493584],"type":"Point"}
}