{
  "type": "Feature",
  "properties": {
    "addr:full":"4th Floor Unit 6 Carr Mills 322, Meanwood Road, Meanwood Leeds West Yorkshire LS7 2HY",
    "addr:housenumber":"4th floor unit 6;322",
    "addr:postcode":"ls7 2hy",
    "addr:street":"Carr Mills;Meanwood Road",
    "iso:country":"GB",
    "sg:address":"4th Floor Unit 6 Carr Mills 322, Meanwood Road, Meanwood",
    "sg:city":"Leeds",
    "sg:classifiers":[
        {
            "category":"Communications",
            "subcategory":"Film & Video Production",
            "type":"Services"
        },
        {
            "category":"Professional",
            "subcategory":"Art Services",
            "type":"Services"
        }
    ],
    "sg:phone":"+44 113 368 2474",
    "sg:postcode":"LS7 2HY",
    "sg:province":"West Yorkshire",
    "sg:tags":[
        "illustrator",
        "artist"
    ],
    "wof:name":"Oblong Studios",
    "wof:placetype":"venue"
},
  "geometry": {"coordinates":[-1.54583,53.815529],"type":"Point"}
}