{
  "type": "Feature",
  "properties": {
    "addr:full":"Albion Dock Yard, Hanover Place Bristol City of Bristol BS1 6UT",
    "addr:postcode":"bs1 6ut",
    "addr:street":"Hanover Place",
    "iso:country":"GB",
    "sg:address":"Albion Dock Yard, Hanover Place",
    "sg:city":"Bristol",
    "sg:classifiers":[
        {
            "category":"Manufacturing",
            "subcategory":"Retail Goods",
            "type":"Manufacturing & Wholesale Goods"
        }
    ],
    "sg:phone":"+44 117 926 8396",
    "sg:postcode":"BS1 6UT",
    "sg:province":"City of Bristol",
    "sg:tags":[
        "chandler"
    ],
    "wof:name":"Speed Marine Holdings Ltd",
    "wof:placetype":"venue"
},
  "geometry": {"coordinates":[-2.5914289951,51.453666687],"type":"Point"}
}