{
  "type": "Feature",
  "properties": {
    "addr:full":"136a Elm Gro Hayling Island Hampshire PO11 9EH",
    "addr:housenumber":"136a",
    "addr:postcode":"po11 9eh",
    "addr:street":"Elm Gro",
    "iso:country":"GB",
    "sg:address":"136a Elm Gro",
    "sg:city":"Hayling Island",
    "sg:classifiers":[
        {
            "category":"Deli",
            "type":"Food & Drink"
        }
    ],
    "sg:phone":"+44 23 9246 2324",
    "sg:postcode":"PO11 9EH",
    "sg:province":"Hampshire",
    "sg:tags":[
        "delivery",
        "sandwich"
    ],
    "wof:name":"J Berry",
    "wof:placetype":"venue"
},
  "geometry": {"coordinates":[-0.9766340256,50.7935256958],"type":"Point"}
}