{
  "type": "Feature",
  "properties": {
    "addr:full":"244 Webheath, Netherwood Street London Greater London NW6 2JX",
    "addr:housenumber":"244",
    "addr:postcode":"nw6 2jx",
    "addr:street":"Webheath Netherwood Street",
    "iso:country":"GB",
    "sg:address":"244 Webheath, Netherwood Street",
    "sg:city":"London",
    "sg:classifiers":[
        {
            "category":"Shopping",
            "subcategory":"Books",
            "type":"Retail Goods"
        }
    ],
    "sg:phone":"+44 20 7328 8328",
    "sg:postcode":"NW6 2JX",
    "sg:province":"Greater London",
    "wof:name":"D A G Publications Ltd.",
    "wof:placetype":"venue"
},
  "geometry": {"coordinates":[-0.196749,51.545929],"type":"Point"}
}