{
  "type": "Feature",
  "properties": {
    "addr:full":"New Quay Street, Appledore Bideford Devon EX39 1LU",
    "addr:postcode":"ex39 1lu",
    "addr:street":"New Quay Street",
    "iso:country":"GB",
    "sg:address":"New Quay Street, Appledore",
    "sg:city":"Bideford",
    "sg:classifiers":[
        {
            "category":"Bars & Pubs",
            "type":"Food & Drink"
        }
    ],
    "sg:phone":"+44 1237 474769",
    "sg:postcode":"EX39 1LU",
    "sg:province":"Devon",
    "sg:tags":[
        "pubs",
        "inn"
    ],
    "wof:name":"Bell Inn",
    "wof:placetype":"venue"
},
  "geometry": {"coordinates":[-4.190909,51.053425],"type":"Point"}
}