{
  "type": "Feature",
  "properties": {
    "addr:full":"7 Vale Avenue, Grove Wantage Berkshire OX12 7LU",
    "addr:housenumber":"7",
    "addr:postcode":"ox12 7lu",
    "addr:street":"Vale Avenue Grove",
    "iso:country":"GB",
    "sg:address":"7 Vale Avenue, Grove",
    "sg:city":"Wantage",
    "sg:classifiers":[
        {
            "category":"Professional",
            "subcategory":"Management & Consulting",
            "type":"Services"
        }
    ],
    "sg:postcode":"OX12 7LU",
    "sg:province":"Berkshire",
    "sg:tags":[
        "marketing",
        "consultant"
    ],
    "wof:name":"Craven Associates",
    "wof:placetype":"venue"
},
  "geometry": {"coordinates":[-1.4190340042,51.6094703674],"type":"Point"}
}