{
  "type": "Feature",
  "properties": {
    "iso:country":"GB",
    "sg:address":"18 Blethin Close",
    "sg:city":"Cardiff",
    "sg:classifiers":[
        {
            "category":"Autos & Motor Vehicles",
            "subcategory":"Automobile Sales",
            "type":"Retail Goods"
        },
        {
            "category":"Retail",
            "subcategory":"Auto Repair",
            "type":"Services"
        }
    ],
    "sg:phone":"+44 29 2057 5353",
    "sg:postcode":"CF5 2RR",
    "sg:province":"Cardiff",
    "sg:tags":[
        "modification",
        "garage",
        "car"
    ],
    "wof:name":"DENTS PLUS",
    "wof:placetype":"venue"
},
  "geometry": {"coordinates":[-3.237373,51.504612],"type":"Point"}
}