{
  "type": "Feature",
  "properties": {
    "iso:country":"GB",
    "sg:address":"Strathmore Lodge, 31 Ward Road",
    "sg:city":"Dundee",
    "sg:classifiers":[
        {
            "category":"Organizations",
            "subcategory":"Non-profit Organization",
            "type":"Services"
        }
    ],
    "sg:phone":"+44 1382 225448",
    "sg:postcode":"DD1 1NG",
    "sg:province":"Dundee City",
    "sg:tags":[
        "organisation",
        "voluntary",
        "charity"
    ],
    "wof:name":"The Salvation Army",
    "wof:placetype":"venue"
},
  "geometry": {"coordinates":[-2.967609,56.461376],"type":"Point"}
}