{
  "type": "Feature",
  "properties": {
    "addr:full":"York Barn, Pagets Lane Coventry Warwickshire CV8 3BJ",
    "addr:postcode":"cv8 3bj",
    "addr:street":"Pagets Lane",
    "iso:country":"GB",
    "sg:address":"York Barn, Pagets Lane",
    "sg:city":"Coventry",
    "sg:classifiers":[
        {
            "category":"Professional",
            "type":"Services"
        }
    ],
    "sg:phone":"+44 24 7630 7614",
    "sg:postcode":"CV8 3BJ",
    "sg:province":"Warwickshire",
    "sg:tags":[
        "exhibition"
    ],
    "wof:name":"Vertex Display Ltd.",
    "wof:placetype":"venue"
},
  "geometry": {"coordinates":[-1.50776,52.40696],"type":"Point"}
}