{
  "type": "Feature",
  "properties": {
    "iso:country":"GB",
    "sg:address":"Belhuish Farmhouse, Coombe Keynes",
    "sg:city":"Wareham",
    "sg:classifiers":[
        {
            "category":"Building & Trades",
            "subcategory":"Construction",
            "type":"Services"
        }
    ],
    "sg:phone":"+44 1929 462465",
    "sg:postcode":"BH20 5PS",
    "sg:province":"Dorset",
    "sg:tags":[
        "roofing",
        "craft",
        "thatching",
        "conservation"
    ],
    "wof:name":"Rod Miller Thatchers",
    "wof:placetype":"venue"
},
  "geometry": {"coordinates":[-2.2267940044,50.6597366333],"type":"Point"}
}