{
  "type": "Feature",
  "properties": {
    "addr:full":"Unit 13/14, Waterfall Lane Trading Estate Cradley Heath West Midlands B64 6PU",
    "addr:housenumber":"unit 13 / 14",
    "addr:postcode":"b64 6pu",
    "addr:street":"Waterfall Lane Trading Estate Cradley Heath West",
    "iso:country":"GB",
    "sg:address":"Unit 13/14, Waterfall Lane Trading Estate",
    "sg:city":"Cradley Heath",
    "sg:classifiers":[
        {
            "category":"Professional",
            "subcategory":"Engineering",
            "type":"Services"
        }
    ],
    "sg:phone":"+44 121 508 6570",
    "sg:postcode":"B64 6PU",
    "sg:province":"West Midlands",
    "wof:name":"M H Berlyn Ltd.",
    "wof:placetype":"venue"
},
  "geometry": {"coordinates":[-2.0558888912,52.4724311829],"type":"Point"}
}