{
  "type": "Feature",
  "properties": {
    "addr:full":"178 Botley Rd Chesham Buckinghamshire HP5 1XR",
    "addr:housenumber":"178",
    "addr:postcode":"hp5 1xr",
    "addr:street":"Botley Rd",
    "iso:country":"GB",
    "sg:address":"178 Botley Rd",
    "sg:city":"Chesham",
    "sg:classifiers":[
        {
            "category":"Organizations",
            "subcategory":"Non-profit Organization",
            "type":"Services"
        }
    ],
    "sg:phone":"+44 1494 778137",
    "sg:postcode":"HP5 1XR",
    "sg:province":"Buckinghamshire",
    "sg:tags":[
        "organisation",
        "voluntary",
        "charity"
    ],
    "wof:name":"Ibis Trust Ltd",
    "wof:placetype":"venue"
},
  "geometry": {"coordinates":[-0.580332,51.710312],"type":"Point"}
}