{
  "type": "Feature",
  "properties": {
    "addr:full":"Weston General Hospital, Grange Road Weston-super-mare Somerset BS23 4TQ",
    "addr:postcode":"bs23 4tq",
    "addr:street":"Grange Road",
    "iso:country":"GB",
    "sg:address":"Weston General Hospital, Grange Road",
    "sg:city":"Weston-super-mare",
    "sg:classifiers":[
        {
            "category":"Health Services",
            "subcategory":"Hospital",
            "type":"Services"
        }
    ],
    "sg:phone":"+44 1934 636363",
    "sg:postcode":"BS23 4TQ",
    "sg:province":"Somerset",
    "wof:name":"Weston Area Health N H S Trust",
    "wof:placetype":"venue"
},
  "geometry": {"coordinates":[-2.9771840572,51.3461914062],"type":"Point"}
}