{
  "type": "Feature",
  "properties": {
    "addr:full":"7 High Street Sandy Bedfordshire SG19 1AG",
    "addr:housenumber":"7",
    "addr:postcode":"sg19 1ag",
    "addr:street":"High Street",
    "iso:country":"GB",
    "sg:address":"7 High Street",
    "sg:city":"Sandy",
    "sg:classifiers":[
        {
            "category":"Real Estate",
            "subcategory":"Real Estate Operator",
            "type":"Services"
        }
    ],
    "sg:phone":"+44 1767 691122",
    "sg:postcode":"SG19 1AG",
    "sg:province":"Bedfordshire",
    "sg:tags":[
        "letting",
        "agent"
    ],
    "wof:name":"Lane & Browns",
    "wof:placetype":"venue"
},
  "geometry": {"coordinates":[-0.2872929871,52.1286735535],"type":"Point"}
}