{
  "type": "Feature",
  "properties": {
    "iso:country":"GB",
    "sg:address":"Unit 1 Dibdale Road",
    "sg:city":"Dudley",
    "sg:classifiers":[
        {
            "category":"Shopping",
            "subcategory":"Department Store",
            "type":"Retail Goods"
        },
        {
            "category":"Food & Beverages",
            "subcategory":"Groceries & Convenience Stores",
            "type":"Retail Goods"
        }
    ],
    "sg:phone":"+44 1384 234952",
    "sg:postcode":"DY1 2RX",
    "sg:province":"West Midlands",
    "wof:name":"Tates Spar",
    "wof:placetype":"venue"
},
  "geometry": {"coordinates":[-2.1013090611,52.5168190002],"type":"Point"}
}