{
  "type": "Feature",
  "properties": {
    "iso:country":"GB",
    "sg:address":"Denmans Lane, Fontwell",
    "sg:city":"Arundel",
    "sg:classifiers":[
        {
            "category":"Sports & Exercise",
            "subcategory":"Race Track",
            "type":"Entertainment"
        }
    ],
    "sg:phone":"+44 1480 862850",
    "sg:postcode":"BN18 0SU",
    "sg:province":"West Sussex",
    "sg:tags":[
        "motor"
    ],
    "wof:name":"G Force Technologies Ltd.",
    "wof:placetype":"venue"
},
  "geometry": {"coordinates":[-0.648239,50.854923],"type":"Point"}
}