{
  "type": "Feature",
  "properties": {
    "addr:full":"695 Aylestone Rd Leicester Leicestershire LE2 8TG",
    "addr:housenumber":"695",
    "addr:postcode":"le2 8tg",
    "addr:street":"Aylestone Rd",
    "iso:country":"GB",
    "sg:address":"695 Aylestone Rd",
    "sg:city":"Leicester",
    "sg:classifiers":[
        {
            "category":"Professional",
            "type":"Services"
        }
    ],
    "sg:phone":"+44 116 233 3835",
    "sg:postcode":"LE2 8TG",
    "sg:province":"Leicestershire",
    "sg:tags":[
        "entertainer"
    ],
    "wof:name":"Tony Tadman Comedian",
    "wof:placetype":"venue"
},
  "geometry": {"coordinates":[-1.1539160013,52.6037063599],"type":"Point"}
}