{
  "type": "Feature",
  "properties": {
    "iso:country":"GB",
    "sg:address":"Northside Industrial Park, Whitley Bridge",
    "sg:city":"Goole",
    "sg:classifiers":[
        {
            "category":"Wholesale",
            "subcategory":"Home Furnishings",
            "type":"Manufacturing & Wholesale Goods"
        }
    ],
    "sg:phone":"+44 1977 662211",
    "sg:postcode":"DN14 0GH",
    "sg:province":"East Riding of Yorkshire",
    "sg:tags":[
        "wsale",
        "rug",
        "carpet"
    ],
    "wof:name":"Roger Fell Ltd.",
    "wof:placetype":"venue"
},
  "geometry": {"coordinates":[-1.1531770229,53.6963844299],"type":"Point"}
}