{
  "type": "Feature",
  "properties": {
    "iso:country":"GB",
    "sg:address":"123 Rowland Road",
    "sg:city":"Scunthorpe",
    "sg:classifiers":[
        {
            "category":"Bars & Pubs",
            "type":"Food & Drink"
        }
    ],
    "sg:phone":"+44 1724 843552",
    "sg:postcode":"DN16 1TE",
    "sg:province":"Lincolnshire",
    "sg:tags":[
        "pubs",
        "inn"
    ],
    "wof:name":"The Queens Hotel",
    "wof:placetype":"venue"
},
  "geometry": {"coordinates":[-0.640799,53.585922],"type":"Point"}
}