{
  "type": "Feature",
  "properties": {
    "iso:country":"GB",
    "sg:address":"43 Main Street, Ochiltree",
    "sg:city":"Cumnock",
    "sg:classifiers":[
        {
            "category":"Autos & Motor Vehicles",
            "subcategory":"Auto Supplies",
            "type":"Retail Goods"
        }
    ],
    "sg:phone":"+44 1290 700488",
    "sg:postcode":"KA18 2AB",
    "sg:province":"East Ayrshire",
    "sg:tags":[
        "tyre"
    ],
    "wof:name":"Ochiltree Tyres",
    "wof:placetype":"venue"
},
  "geometry": {"coordinates":[-4.291304,55.466461],"type":"Point"}
}