{
  "type": "Feature",
  "properties": {
    "addr:full":"4 Market St Ashton Under Lyne Greater Manchester OL6 6BX",
    "addr:housenumber":"4",
    "addr:postcode":"ol6 6bx",
    "addr:street":"Market St;Under Lyne",
    "iso:country":"GB",
    "sg:address":"4 Market St",
    "sg:city":"Ashton Under Lyne",
    "sg:classifiers":[
        {
            "category":"Shopping",
            "subcategory":"Comic Books",
            "type":"Retail Goods"
        }
    ],
    "sg:phone":"+44 161 339 0332",
    "sg:postcode":"OL6 6BX",
    "sg:province":"Greater Manchester",
    "sg:tags":[
        "jeweller"
    ],
    "wof:name":"Cathedral Jewellers",
    "wof:placetype":"venue"
},
  "geometry": {"coordinates":[-2.0920259953,53.4888534546],"type":"Point"}
}