{
  "type": "Feature",
  "properties": {
    "addr:full":"Willow Cottage, Blakes Road, Wargrave Reading Berkshire RG10 8LA",
    "addr:postcode":"rg10 8la",
    "addr:street":"Blakes Road",
    "iso:country":"GB",
    "sg:address":"Willow Cottage, Blakes Road, Wargrave",
    "sg:city":"Reading",
    "sg:classifiers":[
        {
            "category":"Professional",
            "subcategory":"Engineering",
            "type":"Services"
        }
    ],
    "sg:phone":"+44 118 940 2047",
    "sg:postcode":"RG10 8LA",
    "sg:province":"Berkshire",
    "sg:tags":[
        "contractor",
        "electrical",
        "engineer"
    ],
    "wof:name":"J S Bennett",
    "wof:placetype":"venue"
},
  "geometry": {"coordinates":[-0.8727520108,51.5097541809],"type":"Point"}
}