{
  "type": "Feature",
  "properties": {
    "addr:full":"1 Waterfront Development, Customhouse Quay Greenock Inverclyde PA15 1EG",
    "addr:housenumber":"1;development",
    "addr:postcode":"pa15 1eg",
    "addr:street":"Waterfront;Customhouse Quay Greenock",
    "iso:country":"GB",
    "sg:address":"1 Waterfront Development, Customhouse Quay",
    "sg:city":"Greenock",
    "sg:classifiers":[
        {
            "category":"Home & Garden",
            "subcategory":"Household Appliances",
            "type":"Retail Goods"
        }
    ],
    "sg:phone":"+44 870 609 7370",
    "sg:postcode":"PA15 1EG",
    "sg:province":"Inverclyde",
    "sg:tags":[
        "electrical",
        "domestic"
    ],
    "wof:name":"Curry's",
    "wof:placetype":"venue"
},
  "geometry": {"coordinates":[-4.75711,55.948437],"type":"Point"}
}