{
  "type": "Feature",
  "properties": {
    "addr:full":"Unit 12a, Salisbury Rd Ringwood Dorset BH24 3PB",
    "addr:housenumber":"unit 12a",
    "addr:postcode":"bh24 3pb",
    "addr:street":"Salisbury Rd",
    "iso:country":"GB",
    "sg:address":"Unit 12a, Salisbury Rd",
    "sg:city":"Ringwood",
    "sg:classifiers":[
        {
            "category":"Home & Garden",
            "subcategory":"Building Materials",
            "type":"Retail Goods"
        }
    ],
    "sg:phone":"+44 1425 481600",
    "sg:postcode":"BH24 3PB",
    "sg:province":"Dorset",
    "sg:tags":[
        "ready",
        "mixed",
        "concrete"
    ],
    "wof:name":"Ace Minimix",
    "wof:placetype":"venue"
},
  "geometry": {"coordinates":[-1.7882139683,50.8564338684],"type":"Point"}
}