{
  "type": "Feature",
  "properties": {
    "iso:country":"GB",
    "sg:address":"5 Green Street",
    "sg:city":"Darlington",
    "sg:classifiers":[
        {
            "category":"Building & Trades",
            "subcategory":"Construction",
            "type":"Services"
        }
    ],
    "sg:phone":"+44 1325 380666",
    "sg:postcode":"DL1 1HJ",
    "sg:province":"Durham",
    "sg:tags":[
        "welder"
    ],
    "wof:name":"T & P Welding & Fabrications",
    "wof:placetype":"venue"
},
  "geometry": {"coordinates":[-1.5431449413,54.5237846375],"type":"Point"}
}