{
  "type": "Feature",
  "properties": {
    "addr:full":"3 Fisheracre Arbroath Angus DD11 1LE",
    "addr:housenumber":"3",
    "addr:postcode":"dd11 1le",
    "addr:street":"Fisheracre",
    "iso:country":"GB",
    "sg:address":"3 Fisheracre",
    "sg:city":"Arbroath",
    "sg:classifiers":[
        {
            "category":"Bars & Pubs",
            "type":"Food & Drink"
        },
        {
            "category":"Community Center",
            "subcategory":"Social",
            "type":"Public Place"
        }
    ],
    "sg:phone":"+44 1241 876970",
    "sg:postcode":"DD11 1LE",
    "sg:province":"Angus",
    "sg:tags":[
        "pubs",
        "house",
        "inn",
        "activity"
    ],
    "wof:name":"The Plough",
    "wof:placetype":"venue"
},
  "geometry": {"coordinates":[-2.582219,56.564583],"type":"Point"}
}