{
  "type": "Feature",
  "properties": {
    "iso:country":"GB",
    "sg:address":"168-170 Mill Road",
    "sg:city":"Cambridge",
    "sg:classifiers":[
        {
            "category":"Manufacturing",
            "subcategory":"Tobacco Products",
            "type":"Manufacturing & Wholesale Goods"
        },
        {
            "category":"Professional",
            "subcategory":"Lawyer & Legal Services",
            "type":"Services"
        }
    ],
    "sg:phone":"+44 1223 411355",
    "sg:postcode":"CB1 3LP",
    "sg:province":"Cambridgeshire",
    "sg:tags":[
        "patent",
        "agent",
        "manufacturer"
    ],
    "wof:name":"BARKER BRETTELL",
    "wof:placetype":"venue"
},
  "geometry": {"coordinates":[0.142572,52.198071],"type":"Point"}
}