{
  "type": "Feature",
  "properties": {
    "addr:full":"Shelletts Ho, Angel Rd Thames Ditton Surrey KT7 0AU",
    "addr:postcode":"kt7 0au",
    "addr:street":"Angel Rd",
    "iso:country":"GB",
    "sg:address":"Shelletts Ho, Angel Rd",
    "sg:city":"Thames Ditton",
    "sg:classifiers":[
        {
            "category":"Retail",
            "subcategory":"Storage",
            "type":"Services"
        }
    ],
    "sg:postcode":"KT7 0AU",
    "sg:province":"Surrey",
    "sg:tags":[
        "household",
        "removal"
    ],
    "wof:name":"Truecare Business Support Ltd",
    "wof:placetype":"venue"
},
  "geometry": {"coordinates":[-0.3333089948,51.3873443604],"type":"Point"}
}