{
  "type": "Feature",
  "properties": {
    "addr:full":"72-80 Hills Rd Cambridge Cambridgeshire CB2 1LA",
    "addr:housenumber":"72-80",
    "addr:postcode":"cb2 1la",
    "addr:street":"Hills Rd",
    "iso:country":"GB",
    "sg:address":"72-80 Hills Rd",
    "sg:city":"Cambridge",
    "sg:classifiers":[
        {
            "category":"Government",
            "subcategory":"Court House",
            "type":"Public Place"
        }
    ],
    "sg:phone":"+44 1223 354416",
    "sg:postcode":"CB2 1LA",
    "sg:province":"Cambridgeshire",
    "wof:name":"Cambridge County Courts",
    "wof:placetype":"venue"
},
  "geometry": {"coordinates":[0.130483,52.195702],"type":"Point"}
}