{
  "type": "Feature",
  "properties": {
    "iso:country":"GB",
    "sg:address":"Birds Farm House, Little Waltham",
    "sg:city":"Chelmsford",
    "sg:classifiers":[
        {
            "category":"Farming",
            "subcategory":"Livestock Farm",
            "type":"Manufacturing & Wholesale Goods"
        }
    ],
    "sg:postcode":"CM3 3NE",
    "sg:province":"Essex",
    "sg:tags":[
        "others"
    ],
    "wof:name":"M D Yates",
    "wof:placetype":"venue"
},
  "geometry": {"coordinates":[0.4889749885,51.7614250183],"type":"Point"}
}