{
  "type": "Feature",
  "properties": {
    "iso:country":"GB",
    "sg:address":"Haslams House, Chorley Old Rd",
    "sg:city":"Bolton",
    "sg:classifiers":[
        {
            "category":"Organizations",
            "subcategory":"Non-profit Organization",
            "type":"Services"
        }
    ],
    "sg:phone":"+44 1204 465870",
    "sg:postcode":"BL1 3AS",
    "sg:province":"Lancashire",
    "sg:tags":[
        "organisation",
        "animal",
        "welfare"
    ],
    "wof:name":"Animal Shelter Charity Shop",
    "wof:placetype":"venue"
},
  "geometry": {"coordinates":[-2.450149,53.585991],"type":"Point"}
}