{
  "type": "Feature",
  "properties": {
    "addr:full":"Addison House, Addison Rd Guildford Surrey GU1 3QG",
    "addr:postcode":"gu1 3qg",
    "addr:street":"Addison Rd",
    "iso:country":"GB",
    "sg:address":"Addison House, Addison Rd",
    "sg:city":"Guildford",
    "sg:classifiers":[
        {
            "category":"Professional",
            "subcategory":"Employment Agencies",
            "type":"Services"
        }
    ],
    "sg:phone":"+44 1483 452262",
    "sg:postcode":"GU1 3QG",
    "sg:province":"Surrey",
    "sg:tags":[
        "pair",
        "au"
    ],
    "wof:name":"Aupairs By Lydia",
    "wof:placetype":"venue"
},
  "geometry": {"coordinates":[-0.5629600286,51.2359428406],"type":"Point"}
}