{
  "type": "Feature",
  "properties": {
    "addr:full":"40-42 Newman Street London Greater London W1T 1QD",
    "addr:housenumber":"40-42",
    "addr:postcode":"w1t 1qd",
    "addr:street":"Newman Street",
    "iso:country":"GB",
    "sg:address":"40-42 Newman Street",
    "sg:city":"London",
    "sg:classifiers":[
        {
            "category":"Professional",
            "subcategory":"Employment Agencies",
            "type":"Services"
        }
    ],
    "sg:phone":"+44 20 7580 1876",
    "sg:postcode":"W1T 1QD",
    "sg:province":"Greater London",
    "sg:tags":[
        "consultant"
    ],
    "wof:name":"Argyle Recruitment",
    "wof:placetype":"venue"
},
  "geometry": {"coordinates":[-0.1364510059,51.5187492371],"type":"Point"}
}