{
  "type": "Feature",
  "properties": {
    "iso:country":"GB",
    "sg:address":"21 Nettleton Ct",
    "sg:city":"Leeds",
    "sg:classifiers":[
        {
            "category":"Bus Charters",
            "type":"Transportation"
        }
    ],
    "sg:postcode":"LS15 9AW",
    "sg:province":"West Yorkshire",
    "sg:tags":[
        "hire",
        "coach"
    ],
    "wof:name":"Tate,Anthony,",
    "wof:placetype":"venue"
},
  "geometry": {"coordinates":[-1.445625,53.796822],"type":"Point"}
}