{
  "type": "Feature",
  "properties": {
    "addr:full":"Pelmark House, 11 Amwell End Ware Hertfordshire SG12 9HP",
    "addr:housenumber":"11",
    "addr:postcode":"sg12 9hp",
    "addr:street":"Amwell End Ware",
    "iso:country":"GB",
    "sg:address":"Pelmark House, 11 Amwell End",
    "sg:city":"Ware",
    "sg:classifiers":[
        {
            "category":"Professional",
            "subcategory":"Management & Consulting",
            "type":"Services"
        }
    ],
    "sg:postcode":"SG12 9HP",
    "sg:province":"Hertfordshire",
    "sg:tags":[
        "consultant",
        "investigation",
        "site"
    ],
    "wof:name":"Site & Soil",
    "wof:placetype":"venue"
},
  "geometry": {"coordinates":[-0.029352,51.8092193604],"type":"Point"}
}