{
  "type": "Feature",
  "properties": {
    "addr:full":"27 Main Road, Cannington Bridgwater Somerset TA5 2JN",
    "addr:housenumber":"27",
    "addr:postcode":"ta5 2jn",
    "addr:street":"Main Road",
    "iso:country":"GB",
    "sg:address":"27 Main Road, Cannington",
    "sg:city":"Bridgwater",
    "sg:classifiers":[
        {
            "category":"Professional",
            "subcategory":"Business Services",
            "type":"Services"
        },
        {
            "category":"Shopping",
            "type":"Retail Goods"
        }
    ],
    "sg:phone":"+44 1278 652265",
    "sg:postcode":"TA5 2JN",
    "sg:province":"Somerset",
    "sg:tags":[
        "merchant",
        "agricultural"
    ],
    "wof:name":"B H White & Son",
    "wof:placetype":"venue"
},
  "geometry": {"coordinates":[-3.0590438843,51.1461715698],"type":"Point"}
}