{
  "type": "Feature",
  "properties": {
    "addr:full":"9 Stanford Close Hove East Sussex BN3 6PU",
    "addr:housenumber":"9",
    "addr:postcode":"bn3 6pu",
    "addr:street":"Stanford Close",
    "iso:country":"GB",
    "sg:address":"9 Stanford Close",
    "sg:city":"Hove",
    "sg:classifiers":[
        {
            "category":"Home & Garden",
            "subcategory":"Kitchen Supply",
            "type":"Retail Goods"
        }
    ],
    "sg:phone":"+44 1273 506353",
    "sg:postcode":"BN3 6PU",
    "sg:province":"East Sussex",
    "sg:tags":[
        "measuring",
        "scale"
    ],
    "wof:name":"Ion Analysis Services Ltd.",
    "wof:placetype":"venue"
},
  "geometry": {"coordinates":[-0.16833,50.843407],"type":"Point"}
}