{
  "type": "Feature",
  "properties": {
    "addr:full":"Lennel Rd Coldstream Northumberland TD12 4AX",
    "addr:postcode":"td12 4ax",
    "addr:street":"Lennel Rd",
    "iso:country":"GB",
    "sg:address":"Lennel Rd",
    "sg:city":"Coldstream",
    "sg:classifiers":[
        {
            "category":"Government",
            "subcategory":"Police Station",
            "type":"Public Place"
        }
    ],
    "sg:phone":"+44 1890 882402",
    "sg:postcode":"TD12 4AX",
    "sg:province":"Northumberland",
    "sg:tags":[
        "support",
        "force"
    ],
    "wof:name":"Police",
    "wof:placetype":"venue"
},
  "geometry": {"coordinates":[-2.2516510487,55.6515769958],"type":"Point"}
}