{
  "type": "Feature",
  "properties": {
    "addr:full":"High St Chesterfield Derbyshire S43 4ET",
    "addr:postcode":"s43 4et",
    "addr:street":"High St",
    "iso:country":"GB",
    "sg:address":"High St",
    "sg:city":"Chesterfield",
    "sg:classifiers":[
        {
            "category":"Community Center",
            "type":"Public Place"
        }
    ],
    "sg:phone":"+44 1246 812997",
    "sg:postcode":"S43 4ET",
    "sg:province":"Derbyshire",
    "sg:tags":[
        "centre"
    ],
    "wof:name":"Barlborough Village Hall",
    "wof:placetype":"venue"
},
  "geometry": {"coordinates":[-1.287809968,53.2903671265],"type":"Point"}
}