{
  "type": "Feature",
  "properties": {
    "addr:full":"413a Brixton Rd London Greater London SW9 7DG",
    "addr:housenumber":"413a",
    "addr:postcode":"sw9 7dg",
    "addr:street":"Brixton Rd",
    "iso:country":"GB",
    "sg:address":"413a Brixton Rd",
    "sg:city":"London",
    "sg:classifiers":[
        {
            "category":"Professional",
            "subcategory":"Lawyer & Legal Services",
            "type":"Services"
        }
    ],
    "sg:postcode":"SW9 7DG",
    "sg:province":"Greater London",
    "sg:tags":[
        "solicitor"
    ],
    "wof:name":"Smith,John Martin,",
    "wof:placetype":"venue"
},
  "geometry": {"coordinates":[-0.114451,51.463604],"type":"Point"}
}