{
  "type": "Feature",
  "properties": {
    "iso:country":"GB",
    "sg:address":"Church Lane House, Church Lane",
    "sg:city":"Chelmsford",
    "sg:classifiers":[
        {
            "category":"Organizations",
            "subcategory":"Professional Association",
            "type":"Services"
        }
    ],
    "sg:phone":"+44 1245 287524",
    "sg:postcode":"CM1 1NH",
    "sg:province":"Essex",
    "sg:tags":[
        "union",
        "trade"
    ],
    "wof:name":"Unison Eastern Regional Office",
    "wof:placetype":"venue"
},
  "geometry": {"coordinates":[0.47182,51.735374],"type":"Point"}
}