{
  "type": "Feature",
  "properties": {
    "addr:full":"1st Flr, Ferrari Ho, 102 College Rd Harrow Greater London HA1 1AH",
    "addr:housenumber":"1st flr;102",
    "addr:postcode":"ha1 1ah",
    "addr:street":"Ferrari Ho;College Rd",
    "iso:country":"GB",
    "sg:address":"1st Flr, Ferrari Ho, 102 College Rd",
    "sg:city":"Harrow",
    "sg:classifiers":[
        {
            "category":"Shopping",
            "subcategory":"Stationery & Office Supplies",
            "type":"Retail Goods"
        }
    ],
    "sg:postcode":"HA1 1AH",
    "sg:province":"Greater London",
    "sg:tags":[
        "printers'"
    ],
    "wof:name":"Polychrome",
    "wof:placetype":"venue"
},
  "geometry": {"coordinates":[-0.33864,51.585758],"type":"Point"}
}