{
  "type": "Feature",
  "properties": {
    "iso:country":"GB",
    "sg:address":"335 Kimberworth Road",
    "sg:city":"Rotherham",
    "sg:classifiers":[
        {
            "category":"Home & Garden",
            "subcategory":"Carpets & Floor Coverings",
            "type":"Retail Goods"
        }
    ],
    "sg:phone":"+44 1709 740665",
    "sg:postcode":"S61 1HD",
    "sg:province":"South Yorkshire",
    "sg:tags":[
        "crane"
    ],
    "wof:name":"D Milnes",
    "wof:placetype":"venue"
},
  "geometry": {"coordinates":[-1.3885190487,53.4332847595],"type":"Point"}
}