{
  "type": "Feature",
  "properties": {
    "addr:full":"19/21 Belgrave Commercial Centre, 160 Belgrave Roa Leicester Leicestershire LE4 5AU",
    "addr:housenumber":"19 / 21;160",
    "addr:postcode":"le4 5au",
    "addr:street":"Belgrave Commercial Centre",
    "iso:country":"GB",
    "sg:address":"19/21 Belgrave Commercial Centre, 160 Belgrave Roa",
    "sg:city":"Leicester",
    "sg:classifiers":[
        {
            "category":"Restaurant",
            "type":"Food & Drink"
        }
    ],
    "sg:phone":"+44 116 261 0888",
    "sg:postcode":"LE4 5AU",
    "sg:province":"Leicestershire",
    "wof:name":"Mirch Masala",
    "wof:placetype":"venue"
},
  "geometry": {"coordinates":[-1.1223640442,52.6550636292],"type":"Point"}
}