{
  "type": "Feature",
  "properties": {
    "addr:full":"38 Hillview Crescent Guildford Surrey GU2 8BQ",
    "addr:housenumber":"38",
    "addr:postcode":"gu2 8bq",
    "addr:street":"Hillview Crescent",
    "iso:country":"GB",
    "sg:address":"38 Hillview Crescent",
    "sg:city":"Guildford",
    "sg:classifiers":[
        {
            "category":"Building & Trades",
            "subcategory":"Plumbing",
            "type":"Services"
        }
    ],
    "sg:postcode":"GU2 8BQ",
    "sg:province":"Surrey",
    "sg:tags":[
        "heating"
    ],
    "wof:name":"Ring-Er-Plumber",
    "wof:placetype":"venue"
},
  "geometry": {"coordinates":[-0.597914,51.251415],"type":"Point"}
}