{
  "type": "Feature",
  "properties": {
    "addr:full":"High Street, Twyford Winchester Hampshire SO21 1NW",
    "addr:postcode":"so21 1nw",
    "addr:street":"High Street",
    "iso:country":"GB",
    "sg:address":"High Street, Twyford",
    "sg:city":"Winchester",
    "sg:classifiers":[
        {
            "category":"Education",
            "subcategory":"School",
            "type":"Public Place"
        }
    ],
    "sg:phone":"+44 1962 712269",
    "sg:postcode":"SO21 1NW",
    "sg:province":"Hampshire",
    "sg:tags":[
        "independent",
        "preparatory"
    ],
    "wof:name":"Twyford School",
    "wof:placetype":"venue"
},
  "geometry": {"coordinates":[-1.312739,51.02359],"type":"Point"}
}