{
  "type": "Feature",
  "properties": {
    "addr:full":"Masons Gate, Marsh Gibbon Bicester Buckinghamshire OX27 0EY",
    "addr:postcode":"ox27 0ey",
    "addr:street":"Masons Gate",
    "iso:country":"GB",
    "sg:address":"Masons Gate, Marsh Gibbon",
    "sg:city":"Bicester",
    "sg:classifiers":[
        {
            "category":"Real Estate",
            "subcategory":"Real Estate Agent",
            "type":"Services"
        }
    ],
    "sg:postcode":"OX27 0EY",
    "sg:province":"Buckinghamshire",
    "wof:name":"B & P Properties Ltd",
    "wof:placetype":"venue"
},
  "geometry": {"coordinates":[-1.0583779812,51.9029045105],"type":"Point"}
}