{
  "type": "Feature",
  "properties": {
    "addr:full":"Crown Row Aberdare Neath Port Talbot CF44 0AT",
    "addr:postcode":"cf44 0at",
    "addr:street":"Crown Row",
    "iso:country":"GB",
    "sg:address":"Crown Row",
    "sg:city":"Aberdare",
    "sg:classifiers":[
        {
            "category":"Education",
            "subcategory":"School",
            "type":"Public Place"
        }
    ],
    "sg:phone":"+44 1685 873336",
    "sg:postcode":"CF44 0AT",
    "sg:province":"Neath Port Talbot",
    "sg:tags":[
        "local",
        "authority"
    ],
    "wof:name":"Cwmbach Church In Wales Primary School",
    "wof:placetype":"venue"
},
  "geometry": {"coordinates":[-3.414152,51.703526],"type":"Point"}
}