{
  "type": "Feature",
  "properties": {
    "iso:country":"GB",
    "sg:address":"Unit, 2, Litchurch Mews",
    "sg:city":"Derby",
    "sg:classifiers":[
        {
            "category":"Retail",
            "subcategory":"Auto Repair",
            "type":"Services"
        }
    ],
    "sg:phone":"+44 1332 200498",
    "sg:postcode":"DE23 8XA",
    "sg:province":"Derbyshire",
    "sg:tags":[
        "modification",
        "garage"
    ],
    "wof:name":"First Stop Auto Service",
    "wof:placetype":"venue"
},
  "geometry": {"coordinates":[-1.4617010355,52.9089736938],"type":"Point"}
}