{
  "type": "Feature",
  "properties": {
    "addr:full":"37 Carsthorne Rd, Hoylake Wirral Merseyside CH47 4FB",
    "addr:housenumber":"37",
    "addr:postcode":"ch47 4fb",
    "addr:street":"Carsthorne Rd",
    "iso:country":"GB",
    "sg:address":"37 Carsthorne Rd, Hoylake",
    "sg:city":"Wirral",
    "sg:classifiers":[
        {
            "category":"Retail",
            "subcategory":"Auto Repair",
            "type":"Services"
        }
    ],
    "sg:postcode":"CH47 4FB",
    "sg:province":"Merseyside",
    "sg:tags":[
        "car",
        "sprayer",
        "painter"
    ],
    "wof:name":"Hoylake Auto Paint",
    "wof:placetype":"venue"
},
  "geometry": {"coordinates":[-3.171325,53.391262],"type":"Point"}
}