{
  "type": "Feature",
  "properties": {
    "addr:full":"10 Midland Road London Greater London NW1 2AD",
    "addr:housenumber":"10",
    "addr:postcode":"nw1 2ad",
    "addr:street":"Midland Road",
    "iso:country":"GB",
    "sg:address":"10 Midland Road",
    "sg:city":"London",
    "sg:classifiers":[
        {
            "category":"Retail",
            "subcategory":"Auto Repair",
            "type":"Services"
        }
    ],
    "sg:postcode":"NW1 2AD",
    "sg:province":"Greater London",
    "sg:tags":[
        "electrician"
    ],
    "wof:name":"M A M Auto Electricians",
    "wof:placetype":"venue"
},
  "geometry": {"coordinates":[-0.2535679936,51.5266113281],"type":"Point"}
}