{
  "type": "Feature",
  "properties": {
    "addr:full":"2 Coltsfoot Rd Ware Hertfordshire SG12 7NW",
    "addr:housenumber":"2",
    "addr:postcode":"sg12 7nw",
    "addr:street":"Coltsfoot Rd",
    "iso:country":"GB",
    "sg:address":"2 Coltsfoot Rd",
    "sg:city":"Ware",
    "sg:classifiers":[
        {
            "category":"Retail",
            "subcategory":"Auto Repair",
            "type":"Services"
        }
    ],
    "sg:phone":"+44 7957 361081",
    "sg:postcode":"SG12 7NW",
    "sg:province":"Hertfordshire",
    "sg:tags":[
        "body",
        "car"
    ],
    "wof:name":"ChipsAway-north & East Herts",
    "wof:placetype":"venue"
},
  "geometry": {"coordinates":[-0.0227480009,51.8189888],"type":"Point"}
}