{
  "type": "Feature",
  "properties": {
    "addr:full":"10 Hamilton Road Thame Buckinghamshire OX9 3XY",
    "addr:housenumber":"10",
    "addr:postcode":"ox9 3xy",
    "addr:street":"Hamilton Road",
    "iso:country":"GB",
    "sg:address":"10 Hamilton Road",
    "sg:city":"Thame",
    "sg:classifiers":[
        {
            "category":"Community Center",
            "type":"Public Place"
        }
    ],
    "sg:phone":"+44 1844 217217",
    "sg:postcode":"OX9 3XY",
    "sg:province":"Buckinghamshire",
    "sg:tags":[
        "box",
        "juke"
    ],
    "wof:name":"Jooks",
    "wof:placetype":"venue"
},
  "geometry": {"coordinates":[-0.9663839936,51.7505340576],"type":"Point"}
}