{
  "type": "Feature",
  "properties": {
    "addr:full":"57 Princess St Luton Bedfordshire LU1 5AT",
    "addr:housenumber":"57",
    "addr:postcode":"lu1 5at",
    "addr:street":"Princess St",
    "iso:country":"GB",
    "sg:address":"57 Princess St",
    "sg:city":"Luton",
    "sg:classifiers":[
        {
            "category":"Shopping",
            "subcategory":"Clothing, Apparel, & Fashions",
            "type":"Retail Goods"
        }
    ],
    "sg:phone":"+44 1582 730044",
    "sg:postcode":"LU1 5AT",
    "sg:province":"Bedfordshire",
    "sg:tags":[
        "cap",
        "hat"
    ],
    "wof:name":"George Warren",
    "wof:placetype":"venue"
},
  "geometry": {"coordinates":[-0.4212090075,51.8772125244],"type":"Point"}
}