{
  "type": "Feature",
  "properties": {
    "addr:full":"David Lloyd Club, Bushey Rd Raynes Park Greater London SW20 8DE",
    "addr:postcode":"sw20 8de",
    "addr:street":"Bushey Rd",
    "iso:country":"GB",
    "sg:address":"David Lloyd Club, Bushey Rd",
    "sg:city":"Raynes Park",
    "sg:classifiers":[
        {
            "category":"Farming",
            "subcategory":"Nursery",
            "type":"Manufacturing & Wholesale Goods"
        }
    ],
    "sg:phone":"+44 20 8543 1711",
    "sg:postcode":"SW20 8DE",
    "sg:province":"Greater London",
    "sg:tags":[
        "creche"
    ],
    "wof:name":"Gatehouse Creche",
    "wof:placetype":"venue"
},
  "geometry": {"coordinates":[-0.2265190035,51.4110946655],"type":"Point"}
}