{
  "type": "Feature",
  "properties": {
    "iso:country":"GB",
    "sg:address":"5 Dursley Road",
    "sg:city":"Trowbridge",
    "sg:classifiers":[
        {
            "category":"Manufacturing",
            "subcategory":"Food",
            "type":"Manufacturing & Wholesale Goods"
        }
    ],
    "sg:phone":"+44 1225 762200",
    "sg:postcode":"BA14 0NN",
    "sg:province":"Wiltshire",
    "sg:tags":[
        "processing"
    ],
    "wof:name":"Food Machinery 2000 Ltd.",
    "wof:placetype":"venue"
},
  "geometry": {"coordinates":[-2.210441,51.314545],"type":"Point"}
}