{
  "type": "Feature",
  "properties": {
    "addr:full":"Beck House, Scagglethorpe Malton North Yorkshire YO17 8ED",
    "addr:postcode":"yo17 8ed",
    "addr:street":"Scagglethorpe",
    "iso:country":"GB",
    "sg:address":"Beck House, Scagglethorpe",
    "sg:city":"Malton",
    "sg:classifiers":[
        {
            "category":"Farming",
            "subcategory":"Farm",
            "type":"Manufacturing & Wholesale Goods"
        }
    ],
    "sg:postcode":"YO17 8ED",
    "sg:province":"North Yorkshire",
    "sg:tags":[
        "mixed",
        "crop"
    ],
    "wof:name":"Gooder Farms",
    "wof:placetype":"venue"
},
  "geometry": {"coordinates":[-0.7267959714,54.1528129578],"type":"Point"}
}