{
  "type": "Feature",
  "properties": {
    "addr:full":"9 Tyldesley Arc, The Galleries Wigan Lancashire WN1 1AL",
    "addr:housenumber":"9",
    "addr:postcode":"wn1 1al",
    "addr:street":"Tyldesley",
    "iso:country":"GB",
    "sg:address":"9 Tyldesley Arc, The Galleries",
    "sg:city":"Wigan",
    "sg:classifiers":[
        {
            "category":"Shopping",
            "subcategory":"Comic Books",
            "type":"Retail Goods"
        }
    ],
    "sg:phone":"+44 1942 829155",
    "sg:postcode":"WN1 1AL",
    "sg:province":"Lancashire",
    "sg:tags":[
        "jeweller"
    ],
    "wof:name":"Back In Time",
    "wof:placetype":"venue"
},
  "geometry": {"coordinates":[-2.6335320473,53.5441551208],"type":"Point"}
}