{
  "type": "Feature",
  "properties": {
    "addr:full":"22 Parson Street London Greater London NW4 1QB",
    "addr:housenumber":"22",
    "addr:postcode":"nw4 1qb",
    "addr:street":"Parson Street",
    "iso:country":"GB",
    "sg:address":"22 Parson Street",
    "sg:city":"London",
    "sg:classifiers":[
        {
            "category":"Shopping",
            "subcategory":"Pharmacy",
            "type":"Retail Goods"
        }
    ],
    "sg:phone":"+44 20 8202 7367",
    "sg:postcode":"NW4 1QB",
    "sg:province":"Greater London",
    "sg:tags":[
        "toiletry"
    ],
    "wof:name":"Wholesale Trading Supplies",
    "wof:placetype":"venue"
},
  "geometry": {"coordinates":[-0.2214670032,51.5904083252],"type":"Point"}
}