{
  "type": "Feature",
  "properties": {
    "iso:country":"GB",
    "sg:address":"15 Shardlow Rd, Alvaston",
    "sg:city":"Derby",
    "sg:classifiers":[
        {
            "category":"Food & Beverages",
            "subcategory":"Liquor & Beverages",
            "type":"Retail Goods"
        }
    ],
    "sg:phone":"+44 1332 571150",
    "sg:postcode":"DE24 0JG",
    "sg:province":"Derbyshire",
    "sg:tags":[
        "beer",
        "spirit",
        "wines"
    ],
    "wof:name":"Whitbread Plc",
    "wof:placetype":"venue"
},
  "geometry": {"coordinates":[-1.4148089886,52.888420105],"type":"Point"}
}