{
  "type": "Feature",
  "properties": {
    "iso:country":"GB",
    "sg:address":"3b High Street",
    "sg:city":"Nairn",
    "sg:classifiers":[
        {
            "category":"Shopping",
            "subcategory":"Clothing, Apparel, & Fashions",
            "type":"Retail Goods"
        }
    ],
    "sg:phone":"+44 1667 455201",
    "sg:postcode":"IV12 4AQ",
    "sg:province":"Highland",
    "sg:tags":[
        "shop"
    ],
    "wof:name":"Burnett & Forbes",
    "wof:placetype":"venue"
},
  "geometry": {"coordinates":[-3.8704469204,57.5834541321],"type":"Point"}
}