{
  "type": "Feature",
  "properties": {
    "addr:full":"68 Chapel Street Porthmadog Gwynedd LL49 9DN",
    "addr:housenumber":"68",
    "addr:postcode":"ll49 9dn",
    "addr:street":"Chapel Street",
    "iso:country":"GB",
    "sg:address":"68 Chapel Street",
    "sg:city":"Porthmadog",
    "sg:classifiers":[
        {
            "category":"Professional",
            "subcategory":"Art Services",
            "type":"Services"
        }
    ],
    "sg:postcode":"LL49 9DN",
    "sg:province":"Gwynedd",
    "sg:tags":[
        "photographer"
    ],
    "wof:name":"Still Moments Photography",
    "wof:placetype":"venue"
},
  "geometry": {"coordinates":[-4.130989,52.928329],"type":"Point"}
}