{
  "type": "Feature",
  "properties": {
    "iso:country":"GB",
    "sg:address":"109 Waterloo Rd",
    "sg:city":"Blyth",
    "sg:classifiers":[
        {
            "category":"Social Services",
            "subcategory":"Retirement Home",
            "type":"Services"
        }
    ],
    "sg:phone":"+44 1670 360115",
    "sg:postcode":"NE24 1DB",
    "sg:province":"Northumberland",
    "sg:tags":[
        "residential",
        "care"
    ],
    "wof:name":"Rubislaw Residential Care Home",
    "wof:placetype":"venue"
},
  "geometry": {"coordinates":[-1.516004,55.125702],"type":"Point"}
}