{
  "type": "Feature",
  "properties": {
    "addr:full":"Stall 7v Market Hall, The Galleries Wigan Lancashire WN1 1PX",
    "addr:housenumber":"7v",
    "addr:postcode":"wn1 1px",
    "addr:street":"Market Hall The",
    "iso:country":"GB",
    "sg:address":"Stall 7v Market Hall, The Galleries",
    "sg:city":"Wigan",
    "sg:classifiers":[
        {
            "category":"Food & Beverages",
            "subcategory":"Fruits & Vegetables",
            "type":"Retail Goods"
        }
    ],
    "sg:phone":"+44 1942 235757",
    "sg:postcode":"WN1 1PX",
    "sg:province":"Lancashire",
    "sg:tags":[
        "greengrocer"
    ],
    "wof:name":"J Powell & Sons",
    "wof:placetype":"venue"
},
  "geometry": {"coordinates":[-2.6335320473,53.5441551208],"type":"Point"}
}