{
  "type": "Feature",
  "properties": {
    "addr:full":"Telegraph House, High Street Sheffield South Yorkshire S1 2GA",
    "addr:postcode":"s1 2ga",
    "addr:street":"High Street",
    "iso:country":"GB",
    "sg:address":"Telegraph House, High Street",
    "sg:city":"Sheffield",
    "sg:classifiers":[
        {
            "category":"Manufacturing",
            "subcategory":"Metals",
            "type":"Manufacturing & Wholesale Goods"
        }
    ],
    "sg:phone":"+44 1629 640666",
    "sg:postcode":"S1 2GA",
    "sg:province":"South Yorkshire",
    "sg:tags":[
        "foundry"
    ],
    "wof:name":"Gilby-France Ltd.",
    "wof:placetype":"venue"
},
  "geometry": {"coordinates":[-1.467684,53.382721],"type":"Point"}
}