{
  "type": "Feature",
  "properties": {
    "iso:country":"GB",
    "sg:address":"Library, Knott Street",
    "sg:city":"Darwen",
    "sg:classifiers":[
        {
            "category":"Education",
            "subcategory":"Library",
            "type":"Public Place"
        }
    ],
    "sg:phone":"+44 1254 706021",
    "sg:postcode":"BB3 3BU",
    "sg:province":"Lancashire",
    "sg:tags":[
        "book"
    ],
    "wof:name":"Darwen Library",
    "wof:placetype":"venue"
},
  "geometry": {"coordinates":[-2.4656939507,53.6967315674],"type":"Point"}
}