{
  "type": "Feature",
  "properties": {
    "addr:full":"60 Sinclair Street Helensburgh Argyll and Bute G84 8TP",
    "addr:housenumber":"60",
    "addr:postcode":"g84 8tp",
    "addr:street":"Sinclair Street",
    "iso:country":"GB",
    "sg:address":"60 Sinclair Street",
    "sg:city":"Helensburgh",
    "sg:classifiers":[
        {
            "category":"Manufacturing",
            "subcategory":"Petroleum Products",
            "type":"Manufacturing & Wholesale Goods"
        }
    ],
    "sg:phone":"+44 1436 675264",
    "sg:postcode":"G84 8TP",
    "sg:province":"Argyll and Bute",
    "sg:tags":[
        "double",
        "glazing"
    ],
    "wof:name":"Focal Point Windows",
    "wof:placetype":"venue"
},
  "geometry": {"coordinates":[-4.7326159477,56.0051841736],"type":"Point"}
}