{
  "type": "Feature",
  "properties": {
    "iso:country":"GB",
    "sg:address":"Ffordd Tudur",
    "sg:city":"Holyhead",
    "sg:classifiers":[
        {
            "category":"Food & Beverages",
            "subcategory":"Supermarket",
            "type":"Retail Goods"
        }
    ],
    "sg:postcode":"LL65 2DU",
    "sg:province":"Isle of Anglesey",
    "wof:name":"Birkhead,C B,",
    "wof:placetype":"venue"
},
  "geometry": {"coordinates":[-4.623781,53.310146],"type":"Point"}
}