{
  "type": "Feature",
  "properties": {
    "iso:country":"GB",
    "sg:address":"Unit 1 St Benedicts Filling Station, 9 Dereham Rd",
    "sg:city":"Norwich",
    "sg:classifiers":[
        {
            "category":"Retail",
            "subcategory":"Auto Rental",
            "type":"Services"
        }
    ],
    "sg:phone":"+44 1603 631912",
    "sg:postcode":"NR2 4HX",
    "sg:province":"Norfolk",
    "sg:tags":[
        "car"
    ],
    "wof:name":"National Car Rental",
    "wof:placetype":"venue"
},
  "geometry": {"coordinates":[1.28487,52.632149],"type":"Point"}
}