{
  "type": "Feature",
  "properties": {
    "addr:full":"1 The Stores Warehouse, Bakers Yard, Ardington Wantage Berkshire OX12 8PT",
    "addr:housenumber":"1",
    "addr:postcode":"ox12 8pt",
    "iso:country":"GB",
    "sg:address":"1 The Stores Warehouse, Bakers Yard, Ardington",
    "sg:city":"Wantage",
    "sg:classifiers":[
        {
            "category":"Professional",
            "subcategory":"Management & Consulting",
            "type":"Services"
        },
        {
            "category":"Professional",
            "subcategory":"Employment Agencies",
            "type":"Services"
        }
    ],
    "sg:phone":"+44 1235 863525",
    "sg:postcode":"OX12 8PT",
    "sg:province":"Berkshire",
    "sg:tags":[
        "consultant",
        "business"
    ],
    "wof:name":"David Southgate Consulting Ltd",
    "wof:placetype":"venue"
},
  "geometry": {"coordinates":[-1.3812789917,51.5919265747],"type":"Point"}
}