{
  "type": "Feature",
  "properties": {
    "iso:country":"GB",
    "sg:address":"544 Huddersfield Road, Wyke",
    "sg:city":"Bradford",
    "sg:classifiers":[
        {
            "category":"Shopping",
            "subcategory":"News",
            "type":"Retail Goods"
        }
    ],
    "sg:phone":"+44 1274 678269",
    "sg:postcode":"BD12 8AD",
    "sg:province":"West Yorkshire",
    "sg:tags":[
        "newsagent"
    ],
    "wof:name":"Wyke News",
    "wof:placetype":"venue"
},
  "geometry": {"coordinates":[-1.767449,53.742649],"type":"Point"}
}