{
  "type": "Feature",
  "properties": {
    "addr:full":"Waterside Ho, Falmouth Rd Penryn Cornwall TR10 8BD",
    "addr:postcode":"tr10 8bd",
    "addr:street":"Falmouth Rd",
    "iso:country":"GB",
    "sg:address":"Waterside Ho, Falmouth Rd",
    "sg:city":"Penryn",
    "sg:classifiers":[
        {
            "category":"Professional",
            "subcategory":"Management & Consulting",
            "type":"Services"
        }
    ],
    "sg:phone":"+44 1326 375044",
    "sg:postcode":"TR10 8BD",
    "sg:province":"Cornwall",
    "sg:tags":[
        "consultant",
        "business"
    ],
    "wof:name":"A.K.H Management Consultants",
    "wof:placetype":"venue"
},
  "geometry": {"coordinates":[-5.104809,50.168575],"type":"Point"}
}