{
  "type": "Feature",
  "properties": {
    "addr:full":"2 Shrubbery La Bedford Bedfordshire MK44 2PH",
    "addr:housenumber":"2",
    "addr:postcode":"mk44 2ph",
    "addr:street":"Shrubbery La",
    "iso:country":"GB",
    "sg:address":"2 Shrubbery La",
    "sg:city":"Bedford",
    "sg:classifiers":[
        {
            "category":"Building & Trades",
            "subcategory":"Construction",
            "type":"Services"
        }
    ],
    "sg:phone":"+44 1234 771061",
    "sg:postcode":"MK44 2PH",
    "sg:province":"Bedfordshire",
    "sg:tags":[
        "builder"
    ],
    "wof:name":"Victor J F Farrar",
    "wof:placetype":"venue"
},
  "geometry": {"coordinates":[-0.4146899879,52.190536499],"type":"Point"}
}