{
  "type": "Feature",
  "properties": {
    "addr:full":"Health Centre, 62 Gooseberry Hill Luton Bedfordshire LU3 2LB",
    "addr:housenumber":"62",
    "addr:postcode":"lu3 2lb",
    "addr:street":"Gooseberry Hill",
    "iso:country":"GB",
    "sg:address":"Health Centre, 62 Gooseberry Hill",
    "sg:city":"Luton",
    "sg:classifiers":[
        {
            "category":"Health Services",
            "subcategory":"Clinic",
            "type":"Services"
        }
    ],
    "sg:phone":"+44 1582 594607",
    "sg:postcode":"LU3 2LB",
    "sg:province":"Bedfordshire",
    "sg:tags":[
        "nh"
    ],
    "wof:name":"Health Centre",
    "wof:placetype":"venue"
},
  "geometry": {"coordinates":[-0.4352000058,51.9132385254],"type":"Point"}
}