{
  "type": "Feature",
  "properties": {
    "iso:country":"GB",
    "sg:address":"Dorchester Road, Lytchett Minster",
    "sg:city":"Poole",
    "sg:classifiers":[
        {
            "category":"Bars & Pubs",
            "type":"Food & Drink"
        }
    ],
    "sg:phone":"+44 1202 622900",
    "sg:postcode":"BH16 6JF",
    "sg:province":"Dorset",
    "sg:tags":[
        "pubs",
        "inn"
    ],
    "wof:name":"The Bakers Arms",
    "wof:placetype":"venue"
},
  "geometry": {"coordinates":[-2.0574219227,50.7355422974],"type":"Point"}
}