{
  "type": "Feature",
  "properties": {
    "iso:country":"GB",
    "sg:address":"Canon Wharf",
    "sg:city":"London",
    "sg:classifiers":[
        {
            "category":"Building & Trades",
            "subcategory":"Cleaning & Sanitation",
            "type":"Services"
        }
    ],
    "sg:phone":"+44 20 7394 8088",
    "sg:postcode":"SE8 5RT",
    "sg:province":"Greater London",
    "sg:tags":[
        "industrial",
        "business",
        "removal"
    ],
    "wof:name":"Mastercrate Ltd.",
    "wof:placetype":"venue"
},
  "geometry": {"coordinates":[-0.04051,51.489128],"type":"Point"}
}