{
  "type": "Feature",
  "properties": {
    "iso:country":"GB",
    "sg:address":"41 Shambles",
    "sg:city":"York",
    "sg:classifiers":[
        {
            "category":"Manufacturing",
            "subcategory":"Jewelry",
            "type":"Manufacturing & Wholesale Goods"
        }
    ],
    "sg:postcode":"YO1 7LX",
    "sg:province":"North Yorkshire",
    "sg:tags":[
        "repair",
        "jewellery"
    ],
    "wof:name":"Tinker,K,",
    "wof:placetype":"venue"
},
  "geometry": {"coordinates":[-1.080272,53.959431],"type":"Point"}
}