{
  "type": "Feature",
  "properties": {
    "iso:country":"GB",
    "sg:address":"112 Soho Road",
    "sg:city":"Birmingham",
    "sg:classifiers":[
        {
            "category":"Fast Food",
            "type":"Food & Drink"
        }
    ],
    "sg:phone":"+44 121 554 5071",
    "sg:postcode":"B21 9DP",
    "sg:province":"West Midlands",
    "sg:tags":[
        "away",
        "take"
    ],
    "wof:name":"Quality Sweet Centre",
    "wof:placetype":"venue"
},
  "geometry": {"coordinates":[-1.930109,52.502613],"type":"Point"}
}