{
  "type": "Feature",
  "properties": {
    "iso:country":"GB",
    "sg:address":"53 Ingrave Road",
    "sg:city":"Brentwood",
    "sg:classifiers":[
        {
            "category":"Building & Trades",
            "subcategory":"Construction",
            "type":"Services"
        }
    ],
    "sg:phone":"+44 1277 221782",
    "sg:postcode":"CM15 8BB",
    "sg:province":"Essex",
    "sg:tags":[
        "builder"
    ],
    "wof:name":"E J & A Tredget Ltd.",
    "wof:placetype":"venue"
},
  "geometry": {"coordinates":[0.311961,51.617485],"type":"Point"}
}