{
  "type": "Feature",
  "properties": {
    "addr:full":"867 Forest Rd Walthamstow Greater London E17 4AT",
    "addr:housenumber":"867",
    "addr:postcode":"e17 4at",
    "addr:street":"Forest Rd",
    "iso:country":"GB",
    "sg:address":"867 Forest Rd",
    "sg:city":"Walthamstow",
    "sg:classifiers":[
        {
            "category":"Food & Beverages",
            "subcategory":"Bakery",
            "type":"Retail Goods"
        }
    ],
    "sg:phone":"+44 20 8527 2063",
    "sg:postcode":"E17 4AT",
    "sg:province":"Greater London",
    "sg:tags":[
        "shop",
        "baker"
    ],
    "wof:name":"Robert Brooks",
    "wof:placetype":"venue"
},
  "geometry": {"coordinates":[-0.0050550001,51.5916671753],"type":"Point"}
}