{
  "type": "Feature",
  "properties": {
    "iso:country":"GB",
    "sg:address":"Town Head Farm, Langwathby",
    "sg:city":"Penrith",
    "sg:classifiers":[
        {
            "category":"Farming",
            "subcategory":"Livestock Farm",
            "type":"Manufacturing & Wholesale Goods"
        }
    ],
    "sg:postcode":"CA10 1LW",
    "sg:province":"Cumbria",
    "sg:tags":[
        "others"
    ],
    "wof:name":"J B Holliday & Sons",
    "wof:placetype":"venue"
},
  "geometry": {"coordinates":[-2.668922,54.695004],"type":"Point"}
}