{
  "type": "Feature",
  "properties": {
    "iso:country":"GB",
    "sg:address":"26 Brougham Street",
    "sg:city":"Edinburgh",
    "sg:classifiers":[
        {
            "category":"Bars & Pubs",
            "type":"Food & Drink"
        }
    ],
    "sg:phone":"+44 131 221 9997",
    "sg:postcode":"EH3 9JH",
    "sg:province":"City of Edinburgh",
    "sg:tags":[
        "pubs",
        "inn"
    ],
    "wof:name":"Cloisters Public House",
    "wof:placetype":"venue"
},
  "geometry": {"coordinates":[-3.2019789219,55.9432678223],"type":"Point"}
}