{
  "type": "Feature",
  "properties": {
    "iso:country":"GB",
    "sg:address":"The Cottage, Speltham Hill",
    "sg:city":"Waterlooville",
    "sg:classifiers":[
        {
            "category":"Health Services",
            "subcategory":"Health Practitioner",
            "type":"Services"
        }
    ],
    "sg:postcode":"PO7 4RU",
    "sg:province":"Hampshire",
    "sg:tags":[
        "physiotherapist"
    ],
    "wof:name":"P R Foster & J grad",
    "wof:placetype":"venue"
},
  "geometry": {"coordinates":[-1.0288540125,50.8826332092],"type":"Point"}
}