{
  "type": "Feature",
  "properties": {
    "addr:full":"81 Eastover Rd, High Littleton Bristol Somerset BS39 6HZ",
    "addr:housenumber":"81",
    "addr:postcode":"bs39 6hz",
    "addr:street":"Eastover Rd",
    "iso:country":"GB",
    "sg:address":"81 Eastover Rd, High Littleton",
    "sg:city":"Bristol",
    "sg:classifiers":[
        {
            "category":"Recreation",
            "subcategory":"Dog Park",
            "type":"Entertainment"
        }
    ],
    "sg:postcode":"BS39 6HZ",
    "sg:province":"Somerset",
    "wof:name":"Higgs,Sandra,",
    "wof:placetype":"venue"
},
  "geometry": {"coordinates":[-2.5082850456,51.3236999512],"type":"Point"}
}