{
  "type": "Feature",
  "properties": {
    "iso:country":"GB",
    "sg:address":"Grange Farm Cottage",
    "sg:city":"Harrogate",
    "sg:classifiers":[
        {
            "category":"Shopping",
            "subcategory":"Computers & Home Electronics",
            "type":"Retail Goods"
        }
    ],
    "sg:phone":"+44 1423 863400",
    "sg:postcode":"HG3 5ES",
    "sg:province":"North Yorkshire",
    "sg:tags":[
        "aerial",
        "television",
        "radio"
    ],
    "wof:name":"Clarkes Aerials",
    "wof:placetype":"venue"
},
  "geometry": {"coordinates":[-1.782591,54.096336],"type":"Point"}
}