{
  "type": "Feature",
  "properties": {
    "addr:full":"11 Chantry Rd Harrow Greater London HA3 6NT",
    "addr:housenumber":"11",
    "addr:postcode":"ha3 6nt",
    "addr:street":"Chantry Rd",
    "iso:country":"GB",
    "sg:address":"11 Chantry Rd",
    "sg:city":"Harrow",
    "sg:classifiers":[
        {
            "category":"Shopping",
            "subcategory":"Antiques",
            "type":"Retail Goods"
        }
    ],
    "sg:phone":"+44 20 8428 0605",
    "sg:postcode":"HA3 6NT",
    "sg:province":"Greater London",
    "wof:name":"Byron Antiques",
    "wof:placetype":"venue"
},
  "geometry": {"coordinates":[-0.3593,51.604965],"type":"Point"}
}