{
  "type": "Feature",
  "properties": {
    "addr:full":"Newtown Farm, Newtown, Buckland St Mary Chard Devon TA20 3TF",
    "addr:postcode":"ta20 3tf",
    "addr:street":"Buckland St",
    "iso:country":"GB",
    "sg:address":"Newtown Farm, Newtown, Buckland St Mary",
    "sg:city":"Chard",
    "sg:classifiers":[
        {
            "category":"Banks & Credit Unions",
            "subcategory":"Investment Brokerage",
            "type":"Services"
        }
    ],
    "sg:postcode":"TA20 3TF",
    "sg:province":"Devon",
    "sg:tags":[
        "contractor"
    ],
    "wof:name":"G R Farmer",
    "wof:placetype":"venue"
},
  "geometry": {"coordinates":[-2.9604740143,50.8735237122],"type":"Point"}
}