{
  "type": "Feature",
  "properties": {
    "iso:country":"GB",
    "sg:address":"280 High Street",
    "sg:city":"Waltham Cross",
    "sg:classifiers":[
        {
            "category":"Shopping",
            "subcategory":"News",
            "type":"Retail Goods"
        }
    ],
    "sg:phone":"+44 1992 307050",
    "sg:postcode":"EN8 7EA",
    "sg:province":"Essex",
    "sg:tags":[
        "newsagent"
    ],
    "wof:name":"Tracy Anne",
    "wof:placetype":"venue"
},
  "geometry": {"coordinates":[-0.033939,51.691578],"type":"Point"}
}