{
  "type": "Feature",
  "properties": {
    "addr:full":"35 Wellfield Road, Roath Cardiff Cardiff CF24 3PA",
    "addr:housenumber":"35",
    "addr:postcode":"cf24 3pa",
    "addr:street":"Wellfield Road",
    "iso:country":"GB",
    "sg:address":"35 Wellfield Road, Roath",
    "sg:city":"Cardiff",
    "sg:classifiers":[
        {
            "category":"Cafe",
            "type":"Food & Drink"
        }
    ],
    "sg:postcode":"CF24 3PA",
    "sg:province":"Cardiff",
    "sg:tags":[
        "tea",
        "room"
    ],
    "wof:name":"Bentley's Cafe",
    "wof:placetype":"venue"
},
  "geometry": {"coordinates":[-3.1656179428,51.495388031],"type":"Point"}
}