{
  "type": "Feature",
  "properties": {
    "iso:country":"GB",
    "sg:address":"68 Sandy Lane",
    "sg:city":"Poulton-le-fylde",
    "sg:classifiers":[
        {
            "category":"Communications",
            "type":"Services"
        }
    ],
    "sg:phone":"+44 1253 810001",
    "sg:postcode":"FY6 0PR",
    "sg:province":"Lancashire",
    "sg:tags":[
        "tv",
        "video",
        "radio"
    ],
    "wof:name":"Amber Domestic Repairs",
    "wof:placetype":"venue"
},
  "geometry": {"coordinates":[-2.966138,53.922638],"type":"Point"}
}