{
  "type": "Feature",
  "properties": {
    "addr:full":"Friargate Walk, St Georges Shopping Centre Preston Lancashire PR1 2NQ",
    "addr:postcode":"pr1 2nq",
    "addr:street":"Friargate Walk St;Preston",
    "iso:country":"GB",
    "sg:address":"Friargate Walk, St Georges Shopping Centre",
    "sg:city":"Preston",
    "sg:classifiers":[
        {
            "category":"Cafe",
            "type":"Food & Drink"
        }
    ],
    "sg:postcode":"PR1 2NQ",
    "sg:province":"Lancashire",
    "sg:tags":[
        "tea",
        "room"
    ],
    "wof:name":"Raffles Coffee House",
    "wof:placetype":"venue"
},
  "geometry": {"coordinates":[-2.706114,53.762341],"type":"Point"}
}