{
  "type": "Feature",
  "properties": {
    "addr:full":"Manor Farm, 40 Main Street, Denton Northampton Buckinghamshire NN7 1DQ",
    "addr:housenumber":"40",
    "addr:postcode":"nn7 1dq",
    "addr:street":"Manor;Main Street",
    "iso:country":"GB",
    "sg:address":"Manor Farm, 40 Main Street, Denton",
    "sg:city":"Northampton",
    "sg:classifiers":[
        {
            "category":"Home & Garden",
            "subcategory":"Garden Supply",
            "type":"Retail Goods"
        },
        {
            "category":"Farming",
            "subcategory":"Livestock Farm",
            "type":"Manufacturing & Wholesale Goods"
        }
    ],
    "sg:postcode":"NN7 1DQ",
    "sg:province":"Buckinghamshire",
    "sg:tags":[
        "bulb",
        "grower",
        "others"
    ],
    "wof:name":"T W & D Penn",
    "wof:placetype":"venue"
},
  "geometry": {"coordinates":[-0.779828012,52.2131729126],"type":"Point"}
}