{
  "type": "Feature",
  "properties": {
    "addr:full":"250 Walsall Rd Cannock Staffordshire WS11 3JL",
    "addr:housenumber":"250",
    "addr:postcode":"ws11 3jl",
    "addr:street":"Walsall Rd",
    "iso:country":"GB",
    "sg:address":"250 Walsall Rd",
    "sg:city":"Cannock",
    "sg:classifiers":[
        {
            "category":"Building & Trades",
            "subcategory":"Construction",
            "type":"Services"
        }
    ],
    "sg:phone":"+44 1543 469991",
    "sg:postcode":"WS11 3JL",
    "sg:province":"Staffordshire",
    "sg:tags":[
        "builder"
    ],
    "wof:name":"County Design & Build",
    "wof:placetype":"venue"
},
  "geometry": {"coordinates":[-2.0254430771,52.6749572754],"type":"Point"}
}