{
  "type": "Feature",
  "properties": {
    "iso:country":"GB",
    "sg:address":"351 Lymington Road, Highcliffe",
    "sg:city":"Christchurch",
    "sg:classifiers":[
        {
            "category":"Shopping",
            "subcategory":"Books",
            "type":"Retail Goods"
        }
    ],
    "sg:phone":"+44 1425 279090",
    "sg:postcode":"BH23 5EG",
    "sg:province":"Dorset",
    "sg:tags":[
        "bookseller",
        "retailer"
    ],
    "wof:name":"Highcliffe Bookshop",
    "wof:placetype":"venue"
},
  "geometry": {"coordinates":[-1.697901,50.741764],"type":"Point"}
}