{
  "type": "Feature",
  "properties": {
    "iso:country":"GB",
    "sg:address":"78 Corston View",
    "sg:city":"Bath",
    "sg:classifiers":[
        {
            "category":"Home & Garden",
            "subcategory":"Household Appliances",
            "type":"Retail Goods"
        }
    ],
    "sg:phone":"+44 1225 834939",
    "sg:postcode":"BA2 2PH",
    "sg:province":"Somerset",
    "sg:tags":[
        "electrical"
    ],
    "wof:name":"Bath Domestic Repairs",
    "wof:placetype":"venue"
},
  "geometry": {"coordinates":[-2.3836400509,51.3631629944],"type":"Point"}
}