{
  "type": "Feature",
  "properties": {
    "iso:country":"GB",
    "sg:address":"Connaught Ave",
    "sg:city":"London",
    "sg:classifiers":[
        {
            "category":"Wholesale",
            "subcategory":"Toys & Hobbies",
            "type":"Manufacturing & Wholesale Goods"
        }
    ],
    "sg:postcode":"E4 7AP",
    "sg:province":"Greater London",
    "sg:tags":[
        "balloon",
        "novelty"
    ],
    "wof:name":"Flowers & Balloons",
    "wof:placetype":"venue"
},
  "geometry": {"coordinates":[0.002068,51.635479],"type":"Point"}
}