{
  "type": "Feature",
  "properties": {
    "addr:full":"Cannock Shopping Centre, Stafford Road Cannock Staffordshire WS11 2AB",
    "addr:postcode":"ws11 2ab",
    "addr:street":"Stafford Road",
    "iso:country":"GB",
    "sg:address":"Cannock Shopping Centre, Stafford Road",
    "sg:city":"Cannock",
    "sg:classifiers":[
        {
            "category":"Commercial Area",
            "type":"Public Place"
        }
    ],
    "sg:phone":"+44 1543 572166",
    "sg:postcode":"WS11 2AB",
    "sg:province":"Staffordshire",
    "sg:tags":[
        "shop",
        "centre"
    ],
    "wof:name":"St Modwen Developments",
    "wof:placetype":"venue"
},
  "geometry": {"coordinates":[-2.033145,52.690952],"type":"Point"}
}