{
  "type": "Feature",
  "properties": {
    "iso:country":"GB",
    "sg:address":"Bird In Eye Farm, Bird In Eye Hill, Framfield",
    "sg:city":"Uckfield",
    "sg:classifiers":[
        {
            "category":"Farming",
            "subcategory":"Livestock Farm",
            "type":"Manufacturing & Wholesale Goods"
        }
    ],
    "sg:phone":"+44 1825 890339",
    "sg:postcode":"TN22 5HA",
    "sg:province":"East Sussex",
    "sg:tags":[
        "others"
    ],
    "wof:name":"C J Berry & Son",
    "wof:placetype":"venue"
},
  "geometry": {"coordinates":[0.1315989941,50.9645805359],"type":"Point"}
}