{
  "type": "Feature",
  "properties": {
    "iso:country":"GB",
    "sg:address":"188 Sandringham Rd",
    "sg:city":"Birmingham",
    "sg:classifiers":[
        {
            "category":"Building & Trades",
            "subcategory":"Cleaning & Sanitation",
            "type":"Services"
        }
    ],
    "sg:phone":"+44 121 356 7485",
    "sg:postcode":"B42 1PG",
    "sg:province":"West Midlands",
    "sg:tags":[
        "commercial"
    ],
    "wof:name":"Crystal Cleaning Sevices",
    "wof:placetype":"venue"
},
  "geometry": {"coordinates":[-1.914115,52.530441],"type":"Point"}
}