{
  "type": "Feature",
  "properties": {
    "iso:country":"GB",
    "sg:address":"50 Campbell Street",
    "sg:city":"Hamilton",
    "sg:classifiers":[
        {
            "category":"Home & Garden",
            "subcategory":"Household Appliances",
            "type":"Retail Goods"
        }
    ],
    "sg:postcode":"ML3 6AS",
    "sg:province":"South Lanarkshire",
    "sg:tags":[
        "electrical"
    ],
    "wof:name":"Shaver Care",
    "wof:placetype":"venue"
},
  "geometry": {"coordinates":[-4.036157,55.775749],"type":"Point"}
}