{
  "type": "Feature",
  "properties": {
    "iso:country":"GB",
    "sg:address":"8 Ludgate Square",
    "sg:city":"London",
    "sg:classifiers":[
        {
            "category":"Manufacturing",
            "subcategory":"Tobacco Products",
            "type":"Manufacturing & Wholesale Goods"
        }
    ],
    "sg:phone":"+44 20 7236 5801",
    "sg:postcode":"EC4M 7AS",
    "sg:province":"Greater London",
    "wof:name":"Benkert Uk Ltd.",
    "wof:placetype":"venue"
},
  "geometry": {"coordinates":[-0.101491,51.513226],"type":"Point"}
}