{
  "type": "Feature",
  "properties": {
    "iso:country":"GB",
    "sg:address":"23 Coed Leddyn",
    "sg:city":"Caerphilly",
    "sg:classifiers":[
        {
            "category":"Travel",
            "subcategory":"Hotels & Motels",
            "type":"Entertainment"
        }
    ],
    "sg:phone":"+44 29 2088 2633",
    "sg:postcode":"CF83 2NF",
    "sg:province":"Caerphilly",
    "sg:tags":[
        "house",
        "guest"
    ],
    "wof:name":"Monterey Guest House",
    "wof:placetype":"venue"
},
  "geometry": {"coordinates":[-3.2301158905,51.5923309326],"type":"Point"}
}