{
  "type": "Feature",
  "properties": {
    "iso:country":"GB",
    "sg:address":"2 Candle Lane",
    "sg:city":"Milnthorpe",
    "sg:classifiers":[
        {
            "category":"Building & Trades",
            "subcategory":"Construction",
            "type":"Services"
        }
    ],
    "sg:phone":"+44 15395 63055",
    "sg:postcode":"LA7 7QS",
    "sg:province":"Cumbria",
    "sg:tags":[
        "joinery",
        "joiner",
        "carpenter"
    ],
    "wof:name":"Chris Jackson Joiner",
    "wof:placetype":"venue"
},
  "geometry": {"coordinates":[-2.7724690437,54.225112915],"type":"Point"}
}