{
  "type": "Feature",
  "properties": {
    "iso:country":"GB",
    "sg:address":"Boston Spa",
    "sg:city":"Wetherby",
    "sg:classifiers":[
        {
            "category":"Education",
            "subcategory":"Library",
            "type":"Public Place"
        }
    ],
    "sg:phone":"+44 1937 546000",
    "sg:postcode":"LS23 7BY",
    "sg:province":"West Yorkshire",
    "sg:tags":[
        "book"
    ],
    "wof:name":"Legal Deposit",
    "wof:placetype":"venue"
},
  "geometry": {"coordinates":[-1.3212200403,53.9196815491],"type":"Point"}
}