{
  "type": "Feature",
  "properties": {
    "iso:country":"GB",
    "sg:address":"Wakeham Lodge, Rogate",
    "sg:city":"Petersfield",
    "sg:classifiers":[
        {
            "category":"Organizations",
            "subcategory":"Non-profit Organization",
            "type":"Services"
        }
    ],
    "sg:phone":"+44 1730 821748",
    "sg:postcode":"GU31 5EJ",
    "sg:province":"Hampshire",
    "sg:tags":[
        "charitable",
        "organisation",
        "voluntary",
        "charity"
    ],
    "wof:name":"Wakeham Trust",
    "wof:placetype":"venue"
},
  "geometry": {"coordinates":[-0.852077,51.007614],"type":"Point"}
}