{
  "type": "Feature",
  "properties": {
    "iso:country":"GB",
    "sg:address":"37 Stanmore Hill",
    "sg:city":"Stanmore",
    "sg:classifiers":[
        {
            "category":"Professional",
            "subcategory":"Business Services",
            "type":"Services"
        }
    ],
    "sg:phone":"+44 70 1070 1118",
    "sg:postcode":"HA7 3DS",
    "sg:province":"Greater London",
    "sg:tags":[
        "trade"
    ],
    "wof:name":"Association Of Independent Computer Spec",
    "wof:placetype":"venue"
},
  "geometry": {"coordinates":[-0.313323,51.619022],"type":"Point"}
}