{
  "type": "Feature",
  "properties": {
    "addr:full":"Miller House, Dunheaved Road Launceston Cornwall PL15 9JL",
    "addr:postcode":"pl15 9jl",
    "addr:street":"Dunheaved Road",
    "iso:country":"GB",
    "sg:address":"Miller House, Dunheaved Road",
    "sg:city":"Launceston",
    "sg:classifiers":[
        {
            "category":"Social Services",
            "subcategory":"Retirement Home",
            "type":"Services"
        }
    ],
    "sg:phone":"+44 1566 773049",
    "sg:postcode":"PL15 9JL",
    "sg:province":"Cornwall",
    "sg:tags":[
        "residential",
        "care"
    ],
    "wof:name":"Cornwall Care Homes",
    "wof:placetype":"venue"
},
  "geometry": {"coordinates":[-4.363278,50.632458],"type":"Point"}
}