{
  "type": "Feature",
  "properties": {
    "addr:full":"56 Station Road Solihull West Midlands B91 3RX",
    "addr:housenumber":"56",
    "addr:postcode":"b91 3rx",
    "addr:street":"Station Road",
    "iso:country":"GB",
    "sg:address":"56 Station Road",
    "sg:city":"Solihull",
    "sg:classifiers":[
        {
            "category":"Restaurant",
            "type":"Food & Drink"
        }
    ],
    "sg:phone":"+44 121 705 3598",
    "sg:postcode":"B91 3RX",
    "sg:province":"West Midlands",
    "sg:tags":[
        "-",
        "chinese"
    ],
    "wof:name":"Chinese House Catering Co Ltd",
    "wof:placetype":"venue"
},
  "geometry": {"coordinates":[-1.781973958,52.4146308899],"type":"Point"}
}