{
  "type": "Feature",
  "properties": {
    "addr:full":"11 Old Stables, Morehouse Farm, Ditchling Rd, Wivelsfield Haywards Heath East Sussex RH17 7RE",
    "addr:housenumber":"11",
    "addr:postcode":"rh17 7re",
    "addr:street":"Old;Morehouse;Ditchling Rd",
    "iso:country":"GB",
    "sg:address":"11 Old Stables, Morehouse Farm, Ditchling Rd, Wivelsfield",
    "sg:city":"Haywards Heath",
    "sg:classifiers":[
        {
            "category":"Professional",
            "subcategory":"Engineering",
            "type":"Services"
        }
    ],
    "sg:phone":"+44 1444 471896",
    "sg:postcode":"RH17 7RE",
    "sg:province":"East Sussex",
    "sg:tags":[
        "contractor",
        "electrical",
        "engineer"
    ],
    "wof:name":"S.J Vicary",
    "wof:placetype":"venue"
},
  "geometry": {"coordinates":[-0.081424,50.964661],"type":"Point"}
}