{
  "type": "Feature",
  "properties": {
    "addr:full":"Little Keep, Bridport Road Dorchester Dorset DT1 1SQ",
    "addr:postcode":"dt1 1sq",
    "addr:street":"Little;Bridport Road",
    "iso:country":"GB",
    "sg:address":"Little Keep, Bridport Road",
    "sg:city":"Dorchester",
    "sg:classifiers":[
        {
            "category":"Organizations",
            "subcategory":"Non-profit Organization",
            "type":"Services"
        }
    ],
    "sg:postcode":"DT1 1SQ",
    "sg:province":"Dorset",
    "sg:tags":[
        "organisation",
        "voluntary",
        "charity"
    ],
    "wof:name":"Village Retail Services Association Ltd.",
    "wof:placetype":"venue"
},
  "geometry": {"coordinates":[-2.441564,50.711906],"type":"Point"}
}