{
  "type": "Feature",
  "properties": {
    "iso:country":"GB",
    "sg:address":"7 Bradford Rd",
    "sg:city":"Cleckheaton",
    "sg:classifiers":[
        {
            "category":"Travel",
            "subcategory":"Travel Agent",
            "type":"Entertainment"
        }
    ],
    "sg:phone":"+44 1274 864486",
    "sg:postcode":"BD19 5AG",
    "sg:province":"West Yorkshire",
    "wof:name":"Travelworld",
    "wof:placetype":"venue"
},
  "geometry": {"coordinates":[-1.71239,53.724304],"type":"Point"}
}