{
  "type": "Feature",
  "properties": {
    "addr:full":"Four Oaks, Sibthorpe Hill, Tuxford Newark Nottinghamshire NG22 0PJ",
    "addr:postcode":"ng22 0pj",
    "addr:street":"Sibthorpe Hill",
    "iso:country":"GB",
    "sg:address":"Four Oaks, Sibthorpe Hill, Tuxford",
    "sg:city":"Newark",
    "sg:classifiers":[
        {
            "category":"Organizations",
            "subcategory":"Non-profit Organization",
            "type":"Services"
        }
    ],
    "sg:phone":"+44 1777 872087",
    "sg:postcode":"NG22 0PJ",
    "sg:province":"Nottinghamshire",
    "sg:tags":[
        "organisation",
        "voluntary",
        "charity"
    ],
    "wof:name":"Make A Wish Foundation U K",
    "wof:placetype":"venue"
},
  "geometry": {"coordinates":[-0.9013140202,53.2310905457],"type":"Point"}
}