{
  "type": "Feature",
  "properties": {
    "addr:full":"Atlas Industrial Estate Glasgow East Dunbartonshire G21 4UG",
    "addr:postcode":"g21 4ug",
    "addr:street":"Estate",
    "iso:country":"GB",
    "sg:address":"Atlas Industrial Estate",
    "sg:city":"Glasgow",
    "sg:classifiers":[
        {
            "category":"Manufacturing",
            "subcategory":"Building Materials",
            "type":"Manufacturing & Wholesale Goods"
        }
    ],
    "sg:phone":"+44 141 558 4706",
    "sg:postcode":"G21 4UG",
    "sg:province":"East Dunbartonshire",
    "sg:tags":[
        "merchant",
        "builder"
    ],
    "wof:name":"David Hislop Ltd.",
    "wof:placetype":"venue"
},
  "geometry": {"coordinates":[-4.22957,55.886761],"type":"Point"}
}