{
  "type": "Feature",
  "properties": {
    "addr:full":"6 Eden Rd Spennymoor Durham DL16 7UE",
    "addr:housenumber":"6",
    "addr:postcode":"dl16 7ue",
    "addr:street":"Eden Rd",
    "iso:country":"GB",
    "sg:address":"6 Eden Rd",
    "sg:city":"Spennymoor",
    "sg:classifiers":[
        {
            "category":"Building & Trades",
            "subcategory":"Construction",
            "type":"Services"
        }
    ],
    "sg:phone":"+44 1388 813552",
    "sg:postcode":"DL16 7UE",
    "sg:province":"Durham",
    "sg:tags":[
        "builder"
    ],
    "wof:name":"Keith McLean",
    "wof:placetype":"venue"
},
  "geometry": {"coordinates":[-1.604657,54.69545],"type":"Point"}
}