{
  "type": "Feature",
  "properties": {
    "addr:full":"Head Office Paul House, Stockport Road Timperley Altrincham Cheshire WA15 7UQ",
    "addr:postcode":"wa15 7uq",
    "addr:street":"Stockport Road",
    "iso:country":"GB",
    "sg:address":"Head Office Paul House, Stockport Road Timperley",
    "sg:city":"Altrincham",
    "sg:classifiers":[
        {
            "category":"Home & Garden",
            "subcategory":"Household Appliances",
            "type":"Retail Goods"
        }
    ],
    "sg:phone":"+44 161 980 8842",
    "sg:postcode":"WA15 7UQ",
    "sg:province":"Cheshire",
    "sg:tags":[
        "electrical"
    ],
    "wof:name":"Sashcrown Ltd.",
    "wof:placetype":"venue"
},
  "geometry": {"coordinates":[-2.3112039566,53.3997688293],"type":"Point"}
}