{
  "type": "Feature",
  "properties": {
    "iso:country":"GB",
    "sg:address":"Copse Road",
    "sg:city":"Fleetwood",
    "sg:classifiers":[
        {
            "category":"Autos & Motor Vehicles",
            "subcategory":"Auto Supplies",
            "type":"Retail Goods"
        }
    ],
    "sg:phone":"+44 1253 770919",
    "sg:postcode":"FY7 7NY",
    "sg:province":"Lancashire",
    "sg:tags":[
        "tyre"
    ],
    "wof:name":"Charlie Browns Autocentres Ltd.",
    "wof:placetype":"venue"
},
  "geometry": {"coordinates":[-3.027597,53.908901],"type":"Point"}
}