{
  "type": "Feature",
  "properties": {
    "addr:full":"Unit 2 31 Whitechapel Technology Centre, 75 Whitechapel Rd London Greater London E1 1DU",
    "addr:housenumber":"unit;31;technology;75",
    "addr:postcode":"e1 1du",
    "addr:street":"Whitechapel;Whitechapel Rd",
    "iso:country":"GB",
    "sg:address":"Unit 2 31 Whitechapel Technology Centre, 75 Whitechapel Rd",
    "sg:city":"London",
    "sg:classifiers":[
        {
            "category":"Professional",
            "subcategory":"Computer Services",
            "type":"Services"
        }
    ],
    "sg:postcode":"E1 1DU",
    "sg:province":"Greater London",
    "sg:tags":[
        "system",
        "software"
    ],
    "wof:name":"Acg",
    "wof:placetype":"venue"
},
  "geometry": {"coordinates":[-0.05792,51.51939],"type":"Point"}
}