{
  "type": "Feature",
  "properties": {
    "iso:country":"GB",
    "sg:address":"Huddersfield Road, Millbrook",
    "sg:city":"Stalybridge",
    "sg:classifiers":[
        {
            "category":"Health Services",
            "subcategory":"Nursing And Care Facility",
            "type":"Services"
        }
    ],
    "sg:phone":"+44 161 338 2385",
    "sg:postcode":"SK15 3JL",
    "sg:province":"Greater Manchester",
    "sg:tags":[
        "home"
    ],
    "wof:name":"Heritage House Nursing Home",
    "wof:placetype":"venue"
},
  "geometry": {"coordinates":[-2.0304698944,53.4935760498],"type":"Point"}
}