{
  "type": "Feature",
  "properties": {
    "addr:full":"Stenning House, 40 Dane Road London Greater London SW19 2NB",
    "addr:housenumber":"40",
    "addr:postcode":"sw19 2nb",
    "addr:street":"Dane Road",
    "iso:country":"GB",
    "sg:address":"Stenning House, 40 Dane Road",
    "sg:city":"London",
    "sg:classifiers":[
        {
            "category":"Professional",
            "subcategory":"Engineering",
            "type":"Services"
        }
    ],
    "sg:postcode":"SW19 2NB",
    "sg:province":"Greater London",
    "sg:tags":[
        "consulting",
        "engineer"
    ],
    "wof:name":"Barker Hawkes Partnership",
    "wof:placetype":"venue"
},
  "geometry": {"coordinates":[-0.1843390018,51.4144935608],"type":"Point"}
}