{
  "type": "Feature",
  "properties": {
    "addr:full":"22 Anthony Grove Gosport Hampshire PO12 4AS",
    "addr:housenumber":"22",
    "addr:postcode":"po12 4as",
    "addr:street":"Anthony Grove",
    "iso:country":"GB",
    "sg:address":"22 Anthony Grove",
    "sg:city":"Gosport",
    "sg:classifiers":[
        {
            "category":"Professional",
            "subcategory":"Engineering",
            "type":"Services"
        },
        {
            "category":"Building & Trades",
            "subcategory":"Construction",
            "type":"Services"
        }
    ],
    "sg:phone":"+44 23 9258 7131",
    "sg:postcode":"PO12 4AS",
    "sg:province":"Hampshire",
    "sg:tags":[
        "installers",
        "gas",
        "engineer"
    ],
    "wof:name":"Andrew Upton",
    "wof:placetype":"venue"
},
  "geometry": {"coordinates":[-1.1504269838,50.8152008057],"type":"Point"}
}