{
  "type": "Feature",
  "properties": {
    "iso:country":"GB",
    "sg:address":"13 Boldmere Gardens",
    "sg:city":"Sutton Coldfield",
    "sg:classifiers":[
        {
            "category":"Building & Trades",
            "subcategory":"Plumbing",
            "type":"Services"
        }
    ],
    "sg:phone":"+44 7721 605939",
    "sg:postcode":"B73 5LN",
    "sg:province":"West Midlands",
    "sg:tags":[
        "central",
        "heating"
    ],
    "wof:name":"Park Plumbing & Heating",
    "wof:placetype":"venue"
},
  "geometry": {"coordinates":[-1.8414859772,52.5500221252],"type":"Point"}
}