{
  "type": "Feature",
  "properties": {
    "addr:full":"Park Walk School, Park Walk West Brompton Greater London SW10 0AY",
    "addr:postcode":"sw10 0ay",
    "addr:street":"Park Walk School Park Walk",
    "iso:country":"GB",
    "sg:address":"Park Walk School, Park Walk",
    "sg:city":"West Brompton",
    "sg:classifiers":[
        {
            "category":"Government",
            "subcategory":"Office",
            "type":"Public Place"
        }
    ],
    "sg:phone":"+44 20 7351 0985",
    "sg:postcode":"SW10 0AY",
    "sg:province":"Greater London",
    "sg:tags":[
        "education",
        "agency",
        "authority"
    ],
    "wof:name":"Pupil Support Service-The Southern Cluster",
    "wof:placetype":"venue"
},
  "geometry": {"coordinates":[-0.1783400029,51.4841995239],"type":"Point"}
}