{
  "type": "Feature",
  "properties": {
    "addr:full":"Brichgrove St Porth Bridgend CF39 9YA",
    "addr:postcode":"cf39 9ya",
    "addr:street":"St Porth",
    "iso:country":"GB",
    "sg:address":"Brichgrove St",
    "sg:city":"Porth",
    "sg:classifiers":[
        {
            "category":"Place Of Worship",
            "type":"Public Place"
        }
    ],
    "sg:phone":"+44 1443 682401",
    "sg:postcode":"CF39 9YA",
    "sg:province":"Bridgend",
    "wof:name":"St. Pauls Church",
    "wof:placetype":"venue"
},
  "geometry": {"coordinates":[-3.4109508991,51.614982605],"type":"Point"}
}