{
  "type": "Feature",
  "properties": {
    "addr:full":"2 Balustrade, London Road Bath Bath and North East Somerset BA1 6QA",
    "addr:housenumber":"2",
    "addr:postcode":"ba1 6qa",
    "addr:street":"Balustrade London Road",
    "iso:country":"GB",
    "sg:address":"2 Balustrade, London Road",
    "sg:city":"Bath",
    "sg:classifiers":[
        {
            "category":"Shopping",
            "subcategory":"Clothing, Apparel, & Fashions",
            "type":"Retail Goods"
        }
    ],
    "sg:phone":"+44 1225 311793",
    "sg:postcode":"BA1 6QA",
    "sg:province":"Bath and North East Somerset",
    "sg:tags":[
        "shop",
        "dress",
        "fancy"
    ],
    "wof:name":"Bath Theatrical Costume Hirebath Theatrical Costum",
    "wof:placetype":"venue"
},
  "geometry": {"coordinates":[-2.347369,51.393791],"type":"Point"}
}