{
  "type": "Feature",
  "properties": {
    "addr:full":"Laverstoke Gardens London Greater London SW15 4JB",
    "addr:postcode":"sw15 4jb",
    "addr:street":"Laverstoke Gardens",
    "iso:country":"GB",
    "sg:address":"Laverstoke Gardens",
    "sg:city":"London",
    "sg:classifiers":[
        {
            "category":"Community Center",
            "type":"Public Place"
        }
    ],
    "sg:phone":"+44 20 8785 0535",
    "sg:postcode":"SW15 4JB",
    "sg:province":"Greater London",
    "sg:tags":[
        "recreation",
        "leisure",
        "centre"
    ],
    "wof:name":"Cannons Health & Fitness",
    "wof:placetype":"venue"
},
  "geometry": {"coordinates":[-0.243944,51.449585],"type":"Point"}
}