{
  "type": "Feature",
  "properties": {
    "addr:full":"205 Newton Road Torquay Devon TQ2 7AH",
    "addr:housenumber":"205",
    "addr:postcode":"tq2 7ah",
    "addr:street":"Newton Road",
    "iso:country":"GB",
    "sg:address":"205 Newton Road",
    "sg:city":"Torquay",
    "sg:classifiers":[
        {
            "category":"Building & Trades",
            "subcategory":"Construction",
            "type":"Services"
        }
    ],
    "sg:postcode":"TQ2 7AH",
    "sg:province":"Devon",
    "sg:tags":[
        "decorator",
        "painter"
    ],
    "wof:name":"Robertw Cole",
    "wof:placetype":"venue"
},
  "geometry": {"coordinates":[-3.55798,50.48592],"type":"Point"}
}