{
  "type": "Feature",
  "properties": {
    "addr:full":"31b Eltisley Avenue Cambridge Cambridgeshire CB3 9JG",
    "addr:housenumber":"31b",
    "addr:postcode":"cb3 9jg",
    "addr:street":"Eltisley Avenue",
    "iso:country":"GB",
    "sg:address":"31b Eltisley Avenue",
    "sg:city":"Cambridge",
    "sg:classifiers":[
        {
            "category":"Personal",
            "subcategory":"Beauty Salon",
            "type":"Services"
        },
        {
            "category":"Personal",
            "subcategory":"Barber",
            "type":"Services"
        }
    ],
    "sg:phone":"+44 1223 355367",
    "sg:postcode":"CB3 9JG",
    "sg:province":"Cambridgeshire",
    "sg:tags":[
        "unisex",
        "lady",
        "hairdresser"
    ],
    "wof:name":"Hair Care",
    "wof:placetype":"venue"
},
  "geometry": {"coordinates":[0.1099959984,52.1946334839],"type":"Point"}
}