{
  "type": "Feature",
  "properties": {
    "addr:full":"10 Crown St Chorley Lancashire PR7 1DX",
    "addr:housenumber":"10",
    "addr:postcode":"pr7 1dx",
    "addr:street":"Crown St",
    "iso:country":"GB",
    "sg:address":"10 Crown St",
    "sg:city":"Chorley",
    "sg:classifiers":[
        {
            "category":"Banks & Credit Unions",
            "subcategory":"Financial Services",
            "type":"Services"
        }
    ],
    "sg:phone":"+44 1257 234999",
    "sg:postcode":"PR7 1DX",
    "sg:province":"Lancashire",
    "sg:tags":[
        "adviser"
    ],
    "wof:name":"Applewood Investment Consultants",
    "wof:placetype":"venue"
},
  "geometry": {"coordinates":[-2.6349680424,53.6544532776],"type":"Point"}
}