{
  "type": "Feature",
  "properties": {
    "addr:full":"6 High Street, Standish Wigan Lancashire WN6 0HL",
    "addr:housenumber":"6",
    "addr:postcode":"wn6 0hl",
    "addr:street":"High Street",
    "iso:country":"GB",
    "sg:address":"6 High Street, Standish",
    "sg:city":"Wigan",
    "sg:classifiers":[
        {
            "category":"Shopping",
            "subcategory":"Pharmacy",
            "type":"Retail Goods"
        }
    ],
    "sg:phone":"+44 1257 422574",
    "sg:postcode":"WN6 0HL",
    "sg:province":"Lancashire",
    "sg:tags":[
        "pharmacist",
        "chemist"
    ],
    "wof:name":"J G Palin",
    "wof:placetype":"venue"
},
  "geometry": {"coordinates":[-2.6636779308,53.5864219666],"type":"Point"}
}