{
  "type": "Feature",
  "properties": {
    "addr:full":"151 Glasgow Road Clydebank East Dunbartonshire G81 1LQ",
    "addr:housenumber":"151",
    "addr:postcode":"g81 1lq",
    "addr:street":"Glasgow Road",
    "iso:country":"GB",
    "sg:address":"151 Glasgow Road",
    "sg:city":"Clydebank",
    "sg:classifiers":[
        {
            "category":"Insurance",
            "subcategory":"Insurance Agent",
            "type":"Services"
        }
    ],
    "sg:phone":"+44 141 952 0371",
    "sg:postcode":"G81 1LQ",
    "sg:province":"East Dunbartonshire",
    "sg:tags":[
        "broker"
    ],
    "wof:name":"J C Roxburgh & Co. Ltd.",
    "wof:placetype":"venue"
},
  "geometry": {"coordinates":[-4.3996300697,55.8973236084],"type":"Point"}
}