{
  "type": "Feature",
  "properties": {
    "addr:full":"Paradise Row, 42 High Street, Ingleton Carnforth Cumbria LA6 3AQ",
    "addr:housenumber":"42",
    "addr:postcode":"la6 3aq",
    "addr:street":"Paradise;High Street",
    "iso:country":"GB",
    "sg:address":"Paradise Row, 42 High Street, Ingleton",
    "sg:city":"Carnforth",
    "sg:classifiers":[
        {
            "category":"Professional",
            "subcategory":"Art Services",
            "type":"Services"
        },
        {
            "category":"Building & Trades",
            "subcategory":"Construction",
            "type":"Services"
        }
    ],
    "sg:phone":"+44 15242 41792",
    "sg:postcode":"LA6 3AQ",
    "sg:province":"Cumbria",
    "sg:tags":[
        "decorator",
        "painter"
    ],
    "wof:name":"Frances Thistlethwaite",
    "wof:placetype":"venue"
},
  "geometry": {"coordinates":[-2.4710841179,54.150226593],"type":"Point"}
}