{
  "type": "Feature",
  "properties": {
    "addr:full":"3 Mersey Sq Stockport Cheshire SK1 1NU",
    "addr:housenumber":"3",
    "addr:postcode":"sk1 1nu",
    "addr:street":"Mersey Sq",
    "iso:country":"GB",
    "sg:address":"3 Mersey Sq",
    "sg:city":"Stockport",
    "sg:classifiers":[
        {
            "category":"Transit Center",
            "subcategory":"Freight",
            "type":"Transportation"
        }
    ],
    "sg:phone":"+44 161 480 4291",
    "sg:postcode":"SK1 1NU",
    "sg:province":"Cheshire",
    "sg:tags":[
        "shop",
        "craft",
        "centre"
    ],
    "wof:name":"Hobbicraft",
    "wof:placetype":"venue"
},
  "geometry": {"coordinates":[-2.1621320248,53.4094924927],"type":"Point"}
}