{
  "type": "Feature",
  "properties": {
    "iso:country":"GB",
    "sg:address":"Fender Farm, Fender Lane",
    "sg:city":"Wirral",
    "sg:classifiers":[
        {
            "category":"Sports & Exercise",
            "subcategory":"Stables",
            "type":"Entertainment"
        },
        {
            "category":"Personal",
            "subcategory":"Adult",
            "type":"Services"
        }
    ],
    "sg:phone":"+44 151 677 5282",
    "sg:postcode":"CH46 9PA",
    "sg:province":"Merseyside",
    "sg:tags":[
        "equestrian",
        "centre",
        "livery",
        "schools",
        "riding"
    ],
    "wof:name":"WIRREL WEST WIRRAL RIDING SCHOOL",
    "wof:placetype":"venue"
},
  "geometry": {"coordinates":[-3.0982499123,53.404510498],"type":"Point"}
}