{
  "type": "Feature",
  "properties": {
    "iso:country":"GB",
    "sg:address":"Unit 1 Rosehill Enterprise Park",
    "sg:city":"Wrexham",
    "sg:classifiers":[
        {
            "category":"Fast Food",
            "type":"Food & Drink"
        }
    ],
    "sg:postcode":"LL14 3RE",
    "sg:province":"Wrexham",
    "sg:tags":[
        "away",
        "take"
    ],
    "wof:name":"Peet,Michael,",
    "wof:placetype":"venue"
},
  "geometry": {"coordinates":[-3.0754001141,52.9777793884],"type":"Point"}
}