{
  "type": "Feature",
  "properties": {
    "iso:country":"GB",
    "sg:address":"71 South Road",
    "sg:city":"Dundee",
    "sg:classifiers":[
        {
            "category":"Shopping",
            "subcategory":"Books",
            "type":"Retail Goods"
        }
    ],
    "sg:postcode":"DD2 3EG",
    "sg:province":"Dundee City",
    "wof:name":"Garlickhill Ltd.",
    "wof:placetype":"venue"
},
  "geometry": {"coordinates":[-3.013539,56.471901],"type":"Point"}
}