{
  "type": "Feature",
  "properties": {
    "addr:full":"93 The Bridge Shopping Centre, Summer Road North Portsmouth Hampshire PO1 1PL",
    "addr:housenumber":"93",
    "addr:postcode":"hampshire po1 1pl",
    "addr:street":"The Bridge Shopping;Summer Road North",
    "iso:country":"GB",
    "sg:address":"93 The Bridge Shopping Centre, Summer Road North",
    "sg:city":"Portsmouth",
    "sg:classifiers":[
        {
            "category":"Shopping",
            "subcategory":"Shoes",
            "type":"Retail Goods"
        }
    ],
    "sg:phone":"+44 23 9287 2983",
    "sg:postcode":"PO1 1PL",
    "sg:province":"Hampshire",
    "sg:tags":[
        "shop"
    ],
    "wof:name":"Shoefayre Ltd.",
    "wof:placetype":"venue"
},
  "geometry": {"coordinates":[-1.087284,50.804008],"type":"Point"}
}