{
  "type": "Feature",
  "properties": {
    "iso:country":"GB",
    "sg:address":"15 Front St",
    "sg:city":"Stanley",
    "sg:classifiers":[
        {
            "category":"Government",
            "subcategory":"Post Office",
            "type":"Public Place"
        }
    ],
    "sg:phone":"+44 1207 232017",
    "sg:postcode":"DH9 6DS",
    "sg:province":"Durham",
    "wof:name":"Craghead Post Office",
    "wof:placetype":"venue"
},
  "geometry": {"coordinates":[-1.668286,54.853542],"type":"Point"}
}