{
  "type": "Feature",
  "properties": {
    "addr:full":"Long Ash Farm, Milton Abbas Blandford Forum Dorset DT11 0BX",
    "addr:housenumber":"abbas blandford forum",
    "addr:postcode":"dt11 0bx",
    "addr:street":"Long Ash Farm",
    "iso:country":"GB",
    "sg:address":"Long Ash Farm, Milton Abbas",
    "sg:city":"Blandford Forum",
    "sg:classifiers":[
        {
            "category":"Community Center",
            "type":"Public Place"
        }
    ],
    "sg:phone":"+44 1258 880447",
    "sg:postcode":"DT11 0BX",
    "sg:province":"Dorset",
    "sg:tags":[
        "recreation",
        "leisure",
        "centre"
    ],
    "wof:name":"Rare Poultry  Pig & Plant Centre",
    "wof:placetype":"venue"
},
  "geometry": {"coordinates":[-2.2700328827,50.818572998],"type":"Point"}
}