{
  "type": "Feature",
  "properties": {
    "addr:full":"Dobbs Lane, Kesgrave Ipswich Suffolk IP5 2QQ",
    "addr:postcode":"ip5 2qq",
    "addr:street":"Dobbs Lane",
    "iso:country":"GB",
    "sg:address":"Dobbs Lane, Kesgrave",
    "sg:city":"Ipswich",
    "sg:classifiers":[
        {
            "category":"Building & Trades",
            "subcategory":"Construction",
            "type":"Services"
        }
    ],
    "sg:postcode":"IP5 2QQ",
    "sg:province":"Suffolk",
    "sg:tags":[
        "builder"
    ],
    "wof:name":"Ingram Smith Ltd",
    "wof:placetype":"venue"
},
  "geometry": {"coordinates":[1.240535,52.066456],"type":"Point"}
}