{
  "type": "Feature",
  "properties": {
    "iso:country":"GB",
    "sg:address":"4 Hagmill Road, Shawhead Industrial Estate",
    "sg:city":"Coatbridge",
    "sg:classifiers":[
        {
            "category":"Wholesale",
            "subcategory":"Machinery & Supplies",
            "type":"Manufacturing & Wholesale Goods"
        }
    ],
    "sg:phone":"+44 1236 422475",
    "sg:postcode":"ML5 4XD",
    "sg:province":"North Lanarkshire",
    "sg:tags":[
        "hydraulic"
    ],
    "wof:name":"Europower Direct Hose Services",
    "wof:placetype":"venue"
},
  "geometry": {"coordinates":[-4.013069,55.844082],"type":"Point"}
}