{
  "type": "Feature",
  "properties": {
    "iso:country":"GB",
    "sg:address":"Unit 31 The Yorkshire Outlet",
    "sg:city":"Doncaster",
    "sg:classifiers":[
        {
            "category":"Shopping",
            "subcategory":"Clothing, Apparel, & Fashions",
            "type":"Retail Goods"
        }
    ],
    "sg:phone":"+44 1302 320888",
    "sg:postcode":"DN4 5JH",
    "sg:province":"South Yorkshire",
    "sg:tags":[
        "menswear"
    ],
    "wof:name":"Moss Bros Suit Co",
    "wof:placetype":"venue"
},
  "geometry": {"coordinates":[-1.0948690176,53.5140838623],"type":"Point"}
}