{
  "type": "Feature",
  "properties": {
    "addr:full":"Edgeley, Moor Lane Chester Cheshire CH3 7QW",
    "addr:postcode":"ch3 7qw",
    "addr:street":"Edgeley Moor Lane",
    "iso:country":"GB",
    "sg:address":"Edgeley, Moor Lane",
    "sg:city":"Chester",
    "sg:classifiers":[
        {
            "category":"Home & Garden",
            "subcategory":"Carpets & Floor Coverings",
            "type":"Retail Goods"
        }
    ],
    "sg:postcode":"CH3 7QW",
    "sg:province":"Cheshire",
    "sg:tags":[
        "carpets",
        "rug",
        "matting"
    ],
    "wof:name":"Country Carpets",
    "wof:placetype":"venue"
},
  "geometry": {"coordinates":[-2.82073,53.173149],"type":"Point"}
}