{
  "type": "Feature",
  "properties": {
    "addr:full":"1st Floor Brooklands Mill, English Street Leigh Lancashire WN7 3EH",
    "addr:postcode":"wn7 3eh",
    "addr:street":"Brooklands Mill English Street Leigh",
    "iso:country":"GB",
    "sg:address":"1st Floor Brooklands Mill, English Street",
    "sg:city":"Leigh",
    "sg:classifiers":[
        {
            "category":"Real Estate",
            "subcategory":"Developer",
            "type":"Services"
        }
    ],
    "sg:postcode":"WN7 3EH",
    "sg:province":"Lancashire",
    "sg:tags":[
        "property"
    ],
    "wof:name":"Oak Tree Property Developments Ltd",
    "wof:placetype":"venue"
},
  "geometry": {"coordinates":[-2.521944,53.489368],"type":"Point"}
}