{
  "type": "Feature",
  "properties": {
    "iso:country":"GB",
    "sg:address":"120 Birchgrove Street",
    "sg:city":"Porth",
    "sg:classifiers":[
        {
            "category":"Food & Beverages",
            "subcategory":"Bakery",
            "type":"Retail Goods"
        }
    ],
    "sg:phone":"+44 1443 683482",
    "sg:postcode":"CF39 9UU",
    "sg:province":"Bridgend",
    "sg:tags":[
        "baker"
    ],
    "wof:name":"Birchgrove Bakery",
    "wof:placetype":"venue"
},
  "geometry": {"coordinates":[-3.4084920883,51.6150169373],"type":"Point"}
}