{
  "type": "Feature",
  "properties": {
    "addr:full":"1233 Stratford Rd, Hall Grn Birmingham West Midlands B28 9AA",
    "addr:housenumber":"1233",
    "addr:postcode":"b28 9aa",
    "addr:street":"Stratford Rd Hall Grn",
    "iso:country":"GB",
    "sg:address":"1233 Stratford Rd, Hall Grn",
    "sg:city":"Birmingham",
    "sg:classifiers":[
        {
            "category":"Shopping",
            "subcategory":"Stationery & Office Supplies",
            "type":"Retail Goods"
        }
    ],
    "sg:postcode":"B28 9AA",
    "sg:province":"West Midlands",
    "sg:tags":[
        "equipment"
    ],
    "wof:name":"Ashwell Interiors Ltd",
    "wof:placetype":"venue"
},
  "geometry": {"coordinates":[-1.845788002,52.4332008362],"type":"Point"}
}