{
  "type": "Feature",
  "properties": {
    "iso:country":"GB",
    "sg:address":"1 Adswood Lane West",
    "sg:city":"Stockport",
    "sg:classifiers":[
        {
            "category":"Organizations",
            "subcategory":"Religious Organization",
            "type":"Services"
        }
    ],
    "sg:phone":"+44 161 292 7270",
    "sg:postcode":"SK3 8HT",
    "sg:province":"Cheshire",
    "sg:tags":[
        "organisation"
    ],
    "wof:name":"Shalom Spirituality Centre",
    "wof:placetype":"venue"
},
  "geometry": {"coordinates":[-2.156504,53.39682],"type":"Point"}
}