{
  "type": "Feature",
  "properties": {
    "addr:full":"28 High Street, Meysey Hampton Cirencester Gloucestershire GL7 5JT",
    "addr:housenumber":"28",
    "addr:postcode":"gl7 5jt",
    "addr:street":"High Street",
    "iso:country":"GB",
    "sg:address":"28 High Street, Meysey Hampton",
    "sg:city":"Cirencester",
    "sg:classifiers":[
        {
            "category":"Bars & Pubs",
            "type":"Food & Drink"
        }
    ],
    "sg:postcode":"GL7 5JT",
    "sg:province":"Gloucestershire",
    "sg:tags":[
        "pubs",
        "inn"
    ],
    "wof:name":"The Masons Arms",
    "wof:placetype":"venue"
},
  "geometry": {"coordinates":[-1.828365,51.701836],"type":"Point"}
}