{
  "type": "Feature",
  "properties": {
    "addr:full":"14a Lime Grove Shepherd's Bush Greater London W12 8EA",
    "addr:housenumber":"14a",
    "addr:postcode":"w12 8ea",
    "addr:street":"Lime Grove",
    "iso:country":"GB",
    "sg:address":"14a Lime Grove",
    "sg:city":"Shepherd's Bush",
    "sg:classifiers":[
        {
            "category":"Food & Beverages",
            "subcategory":"Specialty",
            "type":"Retail Goods"
        }
    ],
    "sg:phone":"+44 20 8354 4322",
    "sg:postcode":"W12 8EA",
    "sg:province":"Greater London",
    "sg:tags":[
        "dietetic",
        "homogenised"
    ],
    "wof:name":"Positive Energy",
    "wof:placetype":"venue"
},
  "geometry": {"coordinates":[-0.227985993,51.5033149719],"type":"Point"}
}