{
  "type": "Feature",
  "properties": {
    "addr:full":"Brookside, Hamsey Road, Barcombe Lewes East Sussex BN8 5TG",
    "addr:postcode":"bn8 5tg",
    "addr:street":"Hamsey Road",
    "iso:country":"GB",
    "sg:address":"Brookside, Hamsey Road, Barcombe",
    "sg:city":"Lewes",
    "sg:classifiers":[
        {
            "category":"Professional",
            "subcategory":"Engineering",
            "type":"Services"
        }
    ],
    "sg:postcode":"BN8 5TG",
    "sg:province":"East Sussex",
    "sg:tags":[
        "contractor",
        "electrical",
        "engineer"
    ],
    "wof:name":"1 Electrical",
    "wof:placetype":"venue"
},
  "geometry": {"coordinates":[0.018538,50.914509],"type":"Point"}
}