{
  "type": "Feature",
  "properties": {
    "iso:country":"GB",
    "sg:address":"Rear Of, 1-9 Tennyson Road",
    "sg:city":"London",
    "sg:classifiers":[
        {
            "category":"Manufacturing",
            "subcategory":"Furniture",
            "type":"Manufacturing & Wholesale Goods"
        }
    ],
    "sg:phone":"+44 20 8542 3999",
    "sg:postcode":"SW19 8SH",
    "sg:province":"Greater London",
    "sg:tags":[
        "mnfr",
        "upholsterer"
    ],
    "wof:name":"London Antique Upholstery",
    "wof:placetype":"venue"
},
  "geometry": {"coordinates":[-0.1873600036,51.4238204956],"type":"Point"}
}