{
  "type": "Feature",
  "properties": {
    "addr:full":"490 Cowbridge Road East, Victoria Park Cardiff Cardiff CF5 1BL",
    "addr:housenumber":"490",
    "addr:postcode":"cf5 1bl",
    "addr:street":"Cowbridge Road",
    "iso:country":"GB",
    "sg:address":"490 Cowbridge Road East, Victoria Park",
    "sg:city":"Cardiff",
    "sg:classifiers":[
        {
            "category":"Shopping",
            "subcategory":"Bicycles & Sporting Goods",
            "type":"Retail Goods"
        }
    ],
    "sg:phone":"+44 29 2057 8579",
    "sg:postcode":"CF5 1BL",
    "sg:province":"Cardiff",
    "sg:tags":[
        "equipment",
        "camping"
    ],
    "wof:name":"Up & under (Outdoor Gear) Ltd.",
    "wof:placetype":"venue"
},
  "geometry": {"coordinates":[-3.2224049568,51.483669281],"type":"Point"}
}