{
  "type": "Feature",
  "properties": {
    "iso:country":"GB",
    "sg:address":"Unit 10 Leap Cross Business Cent, Re, London Road",
    "sg:city":"Hailsham",
    "sg:classifiers":[
        {
            "category":"Farming",
            "subcategory":"Fish & Marine Products",
            "type":"Manufacturing & Wholesale Goods"
        }
    ],
    "sg:phone":"+44 1323 442031",
    "sg:postcode":"BN27 3PD",
    "sg:province":"East Sussex",
    "sg:tags":[
        "fishmonger"
    ],
    "wof:name":"The Sussex Larder",
    "wof:placetype":"venue"
},
  "geometry": {"coordinates":[0.2565200031,50.8653831482],"type":"Point"}
}