{
  "type": "Feature",
  "properties": {
    "iso:country":"GB",
    "sg:address":"Lyndhurst Road, Hinton",
    "sg:city":"Christchurch",
    "sg:classifiers":[
        {
            "category":"Autos & Motor Vehicles",
            "subcategory":"Fuel & Gas Station",
            "type":"Retail Goods"
        }
    ],
    "sg:phone":"+44 1425 276422",
    "sg:postcode":"BH23 7DS",
    "sg:province":"Dorset",
    "sg:tags":[
        "petrol",
        "filling"
    ],
    "wof:name":"Ormston Service Station",
    "wof:placetype":"venue"
},
  "geometry": {"coordinates":[-1.747985,50.76358],"type":"Point"}
}