{
  "type": "Feature",
  "properties": {
    "addr:full":"Milton House, Tundergarth Lockerbie Dumfries and Galloway DG11 2QQ",
    "addr:postcode":"dg11 2qq",
    "addr:street":"Tundergarth",
    "iso:country":"GB",
    "sg:address":"Milton House, Tundergarth",
    "sg:city":"Lockerbie",
    "sg:classifiers":[
        {
            "category":"Health Services",
            "subcategory":"Health Practitioner",
            "type":"Services"
        }
    ],
    "sg:phone":"+44 1576 710251",
    "sg:postcode":"DG11 2QQ",
    "sg:province":"Dumfries and Galloway",
    "sg:tags":[
        "homoeopathic"
    ],
    "wof:name":"C M Hudson",
    "wof:placetype":"venue"
},
  "geometry": {"coordinates":[-3.3545689583,55.1217765808],"type":"Point"}
}