{
  "type": "Feature",
  "properties": {
    "iso:country":"GB",
    "sg:address":"65 Fairlands Ave",
    "sg:city":"Guildford",
    "sg:classifiers":[
        {
            "category":"Shopping",
            "subcategory":"Pharmacy",
            "type":"Retail Goods"
        },
        {
            "category":"Food & Beverages",
            "subcategory":"Groceries & Convenience Stores",
            "type":"Retail Goods"
        }
    ],
    "sg:phone":"+44 1483 237670",
    "sg:postcode":"GU3 3NB",
    "sg:province":"Surrey",
    "sg:tags":[
        "pharmacist",
        "chemist"
    ],
    "wof:name":"Karsons Enterprises Limited",
    "wof:placetype":"venue"
},
  "geometry": {"coordinates":[-0.6205,51.262962],"type":"Point"}
}