{
  "type": "Feature",
  "properties": {
    "iso:country":"GB",
    "sg:address":"317 Hornchurch Road",
    "sg:city":"Hornchurch",
    "sg:classifiers":[
        {
            "category":"Home & Garden",
            "subcategory":"Furniture",
            "type":"Retail Goods"
        }
    ],
    "sg:phone":"+44 1708 477002",
    "sg:postcode":"RM12 4TQ",
    "sg:province":"Essex",
    "wof:name":"A Touch of Class Interiors",
    "wof:placetype":"venue"
},
  "geometry": {"coordinates":[0.1906830072,51.5650939941],"type":"Point"}
}