{
  "type": "Feature",
  "properties": {
    "iso:country":"GB",
    "sg:address":"Linglands Farm, Gowland Lane, Cloughton",
    "sg:city":"Scarborough",
    "sg:classifiers":[
        {
            "category":"Wholesale",
            "subcategory":"Scrap",
            "type":"Manufacturing & Wholesale Goods"
        },
        {
            "category":"Farming",
            "subcategory":"Farm",
            "type":"Manufacturing & Wholesale Goods"
        }
    ],
    "sg:phone":"+44 1723 870218",
    "sg:postcode":"YO13 0DU",
    "sg:province":"North Yorkshire",
    "sg:tags":[
        "mixed",
        "waste",
        "metal",
        "crop"
    ],
    "wof:name":"Specialist Recyling Services",
    "wof:placetype":"venue"
},
  "geometry": {"coordinates":[-0.449066,54.335831],"type":"Point"}
}