{
  "type": "Feature",
  "properties": {
    "addr:full":"Hillcrest Works, Brighouse Rd Halifax West Yorkshire HX3 8DD",
    "addr:postcode":"hx3 8dd",
    "addr:street":"Brighouse Rd",
    "iso:country":"GB",
    "sg:address":"Hillcrest Works, Brighouse Rd",
    "sg:city":"Halifax",
    "sg:classifiers":[
        {
            "category":"Professional",
            "subcategory":"Engineering",
            "type":"Services"
        }
    ],
    "sg:phone":"+44 1422 205224",
    "sg:postcode":"HX3 8DD",
    "sg:province":"West Yorkshire",
    "sg:tags":[
        "precision",
        "engineer"
    ],
    "wof:name":"Anderson-Mitchell Mould Service Ltd",
    "wof:placetype":"venue"
},
  "geometry": {"coordinates":[-1.81046,53.721329],"type":"Point"}
}