{
  "type": "Feature",
  "properties": {
    "addr:full":"21 Market Street Cleethorpes Lincolnshire DN35 8LY",
    "addr:housenumber":"21",
    "addr:postcode":"dn35 8ly",
    "addr:street":"Market Street",
    "iso:country":"GB",
    "sg:address":"21 Market Street",
    "sg:city":"Cleethorpes",
    "sg:classifiers":[
        {
            "category":"Organizations",
            "subcategory":"Community Association",
            "type":"Services"
        },
        {
            "category":"Organizations",
            "subcategory":"Membership Organization",
            "type":"Services"
        }
    ],
    "sg:phone":"+44 1472 691943",
    "sg:postcode":"DN35 8LY",
    "sg:province":"Lincolnshire",
    "sg:tags":[
        "club",
        "social"
    ],
    "wof:name":"Cleethorpes Home Guard Association Club",
    "wof:placetype":"venue"
},
  "geometry": {"coordinates":[-0.0306199994,53.5600204468],"type":"Point"}
}