{
  "type": "Feature",
  "properties": {
    "addr:full":"20 Mathew Street Liverpool Merseyside L2 6RE",
    "addr:housenumber":"20",
    "addr:postcode":"l2 6re",
    "addr:street":"Mathew Street",
    "iso:country":"GB",
    "sg:address":"20 Mathew Street",
    "sg:city":"Liverpool",
    "sg:classifiers":[
        {
            "category":"Cafe",
            "type":"Food & Drink"
        }
    ],
    "sg:phone":"+44 151 255 0006",
    "sg:postcode":"L2 6RE",
    "sg:province":"Merseyside",
    "sg:tags":[
        "tea",
        "snack",
        "bar",
        "room"
    ],
    "wof:name":"RETRO CAFE BAR",
    "wof:placetype":"venue"
},
  "geometry": {"coordinates":[-2.987648,53.406212],"type":"Point"}
}