{
  "type": "Feature",
  "properties": {
    "addr:full":"17 Broadwalk Crawley Surrey RH10 1HJ",
    "addr:housenumber":"17",
    "addr:postcode":"rh10 1hj",
    "addr:street":"Broadwalk",
    "iso:country":"GB",
    "sg:address":"17 Broadwalk",
    "sg:city":"Crawley",
    "sg:classifiers":[
        {
            "category":"Home & Garden",
            "subcategory":"Furniture",
            "type":"Retail Goods"
        }
    ],
    "sg:phone":"+44 1293 536660",
    "sg:postcode":"RH10 1HJ",
    "sg:province":"Surrey",
    "wof:name":"Pine Direct",
    "wof:placetype":"venue"
},
  "geometry": {"coordinates":[-0.1847530007,51.1184577942],"type":"Point"}
}