{
  "type": "Feature",
  "properties": {
    "iso:country":"GB",
    "sg:address":"1a Peets Lane",
    "sg:city":"Southport",
    "sg:classifiers":[
        {
            "category":"Social Services",
            "subcategory":"Retirement Home",
            "type":"Services"
        }
    ],
    "sg:phone":"+44 1704 220311",
    "sg:postcode":"PR9 7PP",
    "sg:province":"Lancashire",
    "sg:tags":[
        "furrier"
    ],
    "wof:name":"Angus Taylor",
    "wof:placetype":"venue"
},
  "geometry": {"coordinates":[-2.9662809372,53.6572608948],"type":"Point"}
}