{
  "type": "Feature",
  "properties": {
    "iso:country":"GB",
    "sg:address":"Wilson Avenue, East Brighton Park",
    "sg:city":"Brighton",
    "sg:classifiers":[
        {
            "category":"Arena",
            "subcategory":"Sports Club",
            "type":"Entertainment"
        }
    ],
    "sg:phone":"+44 1273 609736",
    "sg:postcode":"BN2 5PZ",
    "sg:province":"East Sussex",
    "wof:name":"Whitehawk Football Club",
    "wof:placetype":"venue"
},
  "geometry": {"coordinates":[-0.100959,50.828964],"type":"Point"}
}