{
  "type": "Feature",
  "properties": {
    "addr:full":"4 Russell Street Stockton-on-tees Durham TS18 1NS",
    "addr:housenumber":"4",
    "addr:postcode":"ts18 1ns",
    "addr:street":"Russell Street",
    "iso:country":"GB",
    "sg:address":"4 Russell Street",
    "sg:city":"Stockton-on-tees",
    "sg:classifiers":[
        {
            "category":"Real Estate",
            "subcategory":"Real Estate Operator",
            "type":"Services"
        },
        {
            "category":"Real Estate",
            "subcategory":"Real Estate Agent",
            "type":"Services"
        }
    ],
    "sg:phone":"+44 1642 677704",
    "sg:postcode":"TS18 1NS",
    "sg:province":"Durham",
    "sg:tags":[
        "letting"
    ],
    "wof:name":"Mohan Thind",
    "wof:placetype":"venue"
},
  "geometry": {"coordinates":[-1.317285,54.56451],"type":"Point"}
}