{
  "type": "Feature",
  "properties": {
    "addr:full":"The Common, Mulbarton Norwich Norfolk NR14 8JS",
    "addr:postcode":"nr14 8js",
    "addr:street":"The Common;Norwich",
    "iso:country":"GB",
    "sg:address":"The Common, Mulbarton",
    "sg:city":"Norwich",
    "sg:classifiers":[
        {
            "category":"Government",
            "subcategory":"City Hall",
            "type":"Public Place"
        }
    ],
    "sg:phone":"+44 1508 578223",
    "sg:postcode":"NR14 8JS",
    "sg:province":"Norfolk",
    "wof:name":"Mulbarton Village Hall",
    "wof:placetype":"venue"
},
  "geometry": {"coordinates":[1.2430319786,52.5797080994],"type":"Point"}
}