{
  "type": "Feature",
  "properties": {
    "iso:country":"GB",
    "sg:address":"15 High Street",
    "sg:city":"Sidmouth",
    "sg:classifiers":[
        {
            "category":"Shopping",
            "subcategory":"Stationery & Office Supplies",
            "type":"Retail Goods"
        }
    ],
    "sg:postcode":"EX10 8LN",
    "sg:province":"Devon",
    "wof:name":"S E S Domestic & Commercial Stationers",
    "wof:placetype":"venue"
},
  "geometry": {"coordinates":[-3.23773,50.680244],"type":"Point"}
}