{
  "type": "Feature",
  "properties": {
    "iso:country":"GB",
    "sg:address":"East Hill Farm, Heytesbury",
    "sg:city":"Warminster",
    "sg:classifiers":[
        {
            "category":"Farming",
            "subcategory":"Farm",
            "type":"Manufacturing & Wholesale Goods"
        }
    ],
    "sg:phone":"+44 1985 841177",
    "sg:postcode":"BA12 0HR",
    "sg:province":"Somerset",
    "sg:tags":[
        "mixed",
        "crop"
    ],
    "wof:name":"Richard Guy",
    "wof:placetype":"venue"
},
  "geometry": {"coordinates":[-2.109385,51.182594],"type":"Point"}
}