{
  "type": "Feature",
  "properties": {
    "addr:full":"30 Buccleuch Street Edinburgh City of Edinburgh EH8 9LP",
    "addr:housenumber":"30",
    "addr:postcode":"eh8 9lp",
    "addr:street":"Buccleuch Street",
    "iso:country":"GB",
    "sg:address":"30 Buccleuch Street",
    "sg:city":"Edinburgh",
    "sg:classifiers":[
        {
            "category":"Shopping",
            "subcategory":"Books",
            "type":"Retail Goods"
        }
    ],
    "sg:phone":"+44 131 662 8570",
    "sg:postcode":"EH8 9LP",
    "sg:province":"City of Edinburgh",
    "sg:tags":[
        "bookseller"
    ],
    "wof:name":"McFeely's Bookstore",
    "wof:placetype":"venue"
},
  "geometry": {"coordinates":[-3.1846721172,55.9429855347],"type":"Point"}
}