{
  "type": "Feature",
  "properties": {
    "addr:full":"165 Byerley Road Shildon Durham DL4 1HN",
    "addr:housenumber":"165",
    "addr:postcode":"dl4 1hn",
    "addr:street":"Byerley Road",
    "iso:country":"GB",
    "sg:address":"165 Byerley Road",
    "sg:city":"Shildon",
    "sg:classifiers":[
        {
            "category":"Freight",
            "type":"Transportation"
        }
    ],
    "sg:phone":"+44 1388 774796",
    "sg:postcode":"DL4 1HN",
    "sg:province":"Durham",
    "sg:tags":[
        "haulage",
        "road"
    ],
    "wof:name":"Christopher Lee",
    "wof:placetype":"venue"
},
  "geometry": {"coordinates":[-1.6500760317,54.6276321411],"type":"Point"}
}