{
  "type": "Feature",
  "properties": {
    "iso:country":"GB",
    "sg:address":"149 Northcote Road",
    "sg:city":"London",
    "sg:classifiers":[
        {
            "category":"Shopping",
            "subcategory":"Antiques",
            "type":"Retail Goods"
        }
    ],
    "sg:phone":"+44 20 7924 7257",
    "sg:postcode":"SW11 6QB",
    "sg:province":"Greater London",
    "wof:name":"Carey B",
    "wof:placetype":"venue"
},
  "geometry": {"coordinates":[-0.16461,51.455479],"type":"Point"}
}