{
  "type": "Feature",
  "properties": {
    "addr:full":"Charrington Street London Greater London NW1 1RG",
    "addr:postcode":"nw1 1rg",
    "addr:street":"Charrington Street",
    "iso:country":"GB",
    "sg:address":"Charrington Street",
    "sg:city":"London",
    "sg:classifiers":[
        {
            "category":"Community Center",
            "type":"Public Place"
        }
    ],
    "sg:phone":"+44 20 7387 0126",
    "sg:postcode":"NW1 1RG",
    "sg:province":"Greater London",
    "sg:tags":[
        "conference",
        "room",
        "centre"
    ],
    "wof:name":"South Camden Community School",
    "wof:placetype":"venue"
},
  "geometry": {"coordinates":[-0.1333359927,51.5344963074],"type":"Point"}
}