{
  "type": "Feature",
  "properties": {
    "addr:full":"178 New Bridge St Newcastle Upon Tyne Tyne and Wear NE1 2TE",
    "addr:housenumber":"178",
    "addr:postcode":"ne1 2te",
    "addr:street":"New;St",
    "iso:country":"GB",
    "sg:address":"178 New Bridge St",
    "sg:city":"Newcastle Upon Tyne",
    "sg:classifiers":[
        {
            "category":"Retail",
            "subcategory":"Event Space",
            "type":"Services"
        }
    ],
    "sg:phone":"+44 191 233 0338",
    "sg:postcode":"NE1 2TE",
    "sg:province":"Tyne and Wear",
    "sg:tags":[
        "exhibition",
        "organiser"
    ],
    "wof:name":"Promovere",
    "wof:placetype":"venue"
},
  "geometry": {"coordinates":[-1.6010149717,54.9743309021],"type":"Point"}
}