{
  "type": "Feature",
  "properties": {
    "iso:country":"GB",
    "sg:address":"Unit B The Firs, Bierton",
    "sg:city":"Aylesbury",
    "sg:classifiers":[
        {
            "category":"Organizations",
            "subcategory":"Non-profit Organization",
            "type":"Services"
        }
    ],
    "sg:phone":"+44 1296 421036",
    "sg:postcode":"HP22 5DX",
    "sg:province":"Buckinghamshire",
    "sg:tags":[
        "charitable",
        "organisation",
        "voluntary",
        "charity"
    ],
    "wof:name":"Buckinghamshire Community Action",
    "wof:placetype":"venue"
},
  "geometry": {"coordinates":[-0.7822700143,51.8334617615],"type":"Point"}
}