{
  "type": "Feature",
  "properties": {
    "iso:country":"GB",
    "sg:address":"Unit 19 Reeves Yard, Warwick Road",
    "sg:city":"Whitstable",
    "sg:classifiers":[
        {
            "category":"Home & Garden",
            "subcategory":"Home Furnishings",
            "type":"Retail Goods"
        },
        {
            "category":"Home & Garden",
            "subcategory":"Furniture",
            "type":"Retail Goods"
        }
    ],
    "sg:phone":"+44 1227 263533",
    "sg:postcode":"CT5 1HX",
    "sg:province":"Kent",
    "sg:tags":[
        "homefurnishings"
    ],
    "wof:name":"Seagull Furniture",
    "wof:placetype":"venue"
},
  "geometry": {"coordinates":[1.026406,51.362247],"type":"Point"}
}