{
  "type": "Feature",
  "properties": {
    "addr:full":"India King Court, The Square, Dalston Carlisle Cumbria CA5 7PY",
    "addr:postcode":"ca5 7py",
    "addr:street":"Court The Square",
    "iso:country":"GB",
    "sg:address":"India King Court, The Square, Dalston",
    "sg:city":"Carlisle",
    "sg:classifiers":[
        {
            "category":"Personal",
            "subcategory":"Beauty Salon",
            "type":"Services"
        }
    ],
    "sg:postcode":"CA5 7PY",
    "sg:province":"Cumbria",
    "sg:tags":[
        "unisex",
        "hairdresser"
    ],
    "wof:name":"His & Hers Hair Studio",
    "wof:placetype":"venue"
},
  "geometry": {"coordinates":[-2.9838008881,54.8425254822],"type":"Point"}
}