{
  "type": "Feature",
  "properties": {
    "addr:full":"14 Raeburn Av Burnley Lancashire BB11 2QE",
    "addr:housenumber":"14",
    "addr:postcode":"bb11 2qe",
    "addr:street":"Raeburn Av Burnley",
    "iso:country":"GB",
    "sg:address":"14 Raeburn Av",
    "sg:city":"Burnley",
    "sg:classifiers":[
        {
            "category":"Bus Charters",
            "type":"Transportation"
        }
    ],
    "sg:phone":"+44 1282 424393",
    "sg:postcode":"BB11 2QE",
    "sg:province":"Lancashire",
    "sg:tags":[
        "hire",
        "coach"
    ],
    "wof:name":"Grimshaw Coaches",
    "wof:placetype":"venue"
},
  "geometry": {"coordinates":[-2.2536370754,53.7753295898],"type":"Point"}
}