{
  "type": "Feature",
  "properties": {
    "addr:full":"7 Richmond Mansions, Denton Road Twickenham Greater London TW1 2HH",
    "addr:housenumber":"7",
    "addr:postcode":"tw1 2hh",
    "addr:street":"Denton Road",
    "iso:country":"GB",
    "sg:address":"7 Richmond Mansions, Denton Road",
    "sg:city":"Twickenham",
    "sg:classifiers":[
        {
            "category":"Professional",
            "subcategory":"Management & Consulting",
            "type":"Services"
        }
    ],
    "sg:phone":"+44 20 8607 9272",
    "sg:postcode":"TW1 2HH",
    "sg:province":"Greater London",
    "sg:tags":[
        "consultant",
        "business"
    ],
    "wof:name":"Grandtek Consulting Ltd",
    "wof:placetype":"venue"
},
  "geometry": {"coordinates":[-0.328229,51.446636],"type":"Point"}
}