{
  "type": "Feature",
  "properties": {
    "iso:country":"GB",
    "sg:address":"344 Garratt La",
    "sg:city":"Wandsworth",
    "sg:classifiers":[
        {
            "category":"Real Estate",
            "subcategory":"Real Estate Agent",
            "type":"Services"
        }
    ],
    "sg:phone":"+44 20 8871 4366",
    "sg:postcode":"SW18 4EL",
    "sg:province":"Greater London",
    "wof:name":"Woolwich Property Services",
    "wof:placetype":"venue"
},
  "geometry": {"coordinates":[-0.1885689944,51.4424743652],"type":"Point"}
}