{
  "type": "Feature",
  "properties": {
    "addr:full":"Unit 5-6 Wakefield West Yorkshire WF2 8TQ",
    "addr:housenumber":"unit 5-6",
    "addr:postcode":"wf2 8tq",
    "iso:country":"GB",
    "sg:address":"Unit 5-6",
    "sg:city":"Wakefield",
    "sg:classifiers":[
        {
            "category":"Shopping",
            "subcategory":"Pharmacy",
            "type":"Retail Goods"
        }
    ],
    "sg:phone":"+44 1924 381348",
    "sg:postcode":"WF2 8TQ",
    "sg:province":"West Yorkshire",
    "sg:tags":[
        "medical"
    ],
    "wof:name":"Crescent (2004) Ltd.",
    "wof:placetype":"venue"
},
  "geometry": {"coordinates":[-1.51199,53.678291],"type":"Point"}
}