{
  "type": "Feature",
  "properties": {
    "addr:full":"6 Station Parade Harrogate North Yorkshire HG1 1UE",
    "addr:housenumber":"6",
    "addr:postcode":"hg1 1ue",
    "addr:street":"Station Parade",
    "iso:country":"GB",
    "sg:address":"6 Station Parade",
    "sg:city":"Harrogate",
    "sg:classifiers":[
        {
            "category":"Food & Beverages",
            "subcategory":"Candy",
            "type":"Retail Goods"
        },
        {
            "category":"Bakery",
            "type":"Food & Drink"
        }
    ],
    "sg:postcode":"HG1 1UE",
    "sg:province":"North Yorkshire",
    "sg:tags":[
        "cake",
        "confectionery",
        "maker"
    ],
    "wof:name":"Special Occasions",
    "wof:placetype":"venue"
},
  "geometry": {"coordinates":[-1.538375,53.995583],"type":"Point"}
}