{
  "type": "Feature",
  "properties": {
    "iso:country":"GB",
    "sg:address":"Tower St",
    "sg:city":"Selkirk",
    "sg:classifiers":[
        {
            "category":"Professional",
            "subcategory":"Art Services",
            "type":"Services"
        }
    ],
    "sg:phone":"+44 1896 750023",
    "sg:postcode":"TD7 4LR",
    "sg:province":"Scottish Borders",
    "sg:tags":[
        "photographer"
    ],
    "wof:name":"Ballantyne R Photographic",
    "wof:placetype":"venue"
},
  "geometry": {"coordinates":[-2.841429,55.547329],"type":"Point"}
}