{
  "type": "Feature",
  "properties": {
    "iso:country":"GB",
    "sg:address":"St Andrews Avenue",
    "sg:city":"Colchester",
    "sg:classifiers":[
        {
            "category":"Home & Garden",
            "subcategory":"Hardware",
            "type":"Retail Goods"
        }
    ],
    "sg:phone":"+44 1206 866644",
    "sg:postcode":"CO4 3BG",
    "sg:province":"Essex",
    "sg:tags":[
        "shop",
        "retailer",
        "diy"
    ],
    "sg:website":"http://www.homebase.co.uk",
    "wof:name":"Homebase Ltd",
    "wof:placetype":"venue"
},
  "geometry": {"coordinates":[0.930205,51.886608],"type":"Point"}
}