{
  "type": "Feature",
  "properties": {
    "addr:full":"55 Carnegie Rd, Hillington Ind Est Glasgow Glasgow City G52 4JZ",
    "addr:housenumber":"55",
    "addr:postcode":"g52 4jz",
    "addr:street":"Carnegie Rd;Est",
    "iso:country":"GB",
    "sg:address":"55 Carnegie Rd, Hillington Ind Est",
    "sg:city":"Glasgow",
    "sg:classifiers":[
        {
            "category":"Autos & Motor Vehicles",
            "subcategory":"Automobile Sales",
            "type":"Retail Goods"
        },
        {
            "category":"Retail",
            "subcategory":"Auto Repair",
            "type":"Services"
        }
    ],
    "sg:phone":"+44 141 570 5757",
    "sg:postcode":"G52 4JZ",
    "sg:province":"Glasgow City",
    "sg:tags":[
        "truck",
        "electrician",
        "car"
    ],
    "wof:name":"Caledonia Auto Electrics",
    "wof:placetype":"venue"
},
  "geometry": {"coordinates":[-4.362938,55.855526],"type":"Point"}
}