{
  "type": "Feature",
  "properties": {
    "iso:country":"GB",
    "sg:address":"7 Ward Rd",
    "sg:city":"Dundee",
    "sg:classifiers":[
        {
            "category":"Organizations",
            "subcategory":"Membership Organization",
            "type":"Services"
        }
    ],
    "sg:postcode":"DD1 1LP",
    "sg:province":"Dundee City",
    "sg:tags":[
        "club"
    ],
    "wof:name":"Cosmopolitan Club",
    "wof:placetype":"venue"
},
  "geometry": {"coordinates":[-2.9747240543,56.4619674683],"type":"Point"}
}