{
  "type": "Feature",
  "properties": {
    "addr:full":"7 High St, Sedgley Dudley Staffordshire DY3 1RL",
    "addr:housenumber":"7",
    "addr:postcode":"dy3 1rl",
    "addr:street":"High St",
    "iso:country":"GB",
    "sg:address":"7 High St, Sedgley",
    "sg:city":"Dudley",
    "sg:classifiers":[
        {
            "category":"Retail",
            "subcategory":"Auto Rental",
            "type":"Services"
        }
    ],
    "sg:postcode":"DY3 1RL",
    "sg:province":"Staffordshire",
    "sg:tags":[
        "car"
    ],
    "wof:name":"Auto Direct Rent-A-Car",
    "wof:placetype":"venue"
},
  "geometry": {"coordinates":[-2.1222391129,52.5423622131],"type":"Point"}
}