{
  "type": "Feature",
  "properties": {
    "addr:full":"Moores Farm, Pingewood Reading Berkshire RG30 3UH",
    "addr:postcode":"rg30 3uh",
    "iso:country":"GB",
    "sg:address":"Moores Farm, Pingewood",
    "sg:city":"Reading",
    "sg:classifiers":[
        {
            "category":"Farming",
            "subcategory":"Livestock Farm",
            "type":"Manufacturing & Wholesale Goods"
        }
    ],
    "sg:phone":"+44 118 957 4744",
    "sg:postcode":"RG30 3UH",
    "sg:province":"Berkshire",
    "sg:tags":[
        "others"
    ],
    "wof:name":"Hannington & Son",
    "wof:placetype":"venue"
},
  "geometry": {"coordinates":[-1.0073820353,51.4239082336],"type":"Point"}
}