{
  "type": "Feature",
  "properties": {
    "iso:country":"GB",
    "sg:address":"576-578 Old Chester Rd",
    "sg:city":"Birkenhead",
    "sg:classifiers":[
        {
            "category":"Building & Trades",
            "subcategory":"Construction",
            "type":"Services"
        }
    ],
    "sg:phone":"+44 151 334 5119",
    "sg:postcode":"CH42 4PF",
    "sg:province":"Merseyside",
    "sg:tags":[
        "decorator",
        "painter"
    ],
    "wof:name":"Preston Coating Systems",
    "wof:placetype":"venue"
},
  "geometry": {"coordinates":[-3.014194,53.366589],"type":"Point"}
}