{
  "type": "Feature",
  "properties": {
    "iso:country":"GB",
    "sg:address":"Kingsclere By-pass, Kingsclere",
    "sg:city":"Newbury",
    "sg:classifiers":[
        {
            "category":"Farming",
            "subcategory":"Farm",
            "type":"Manufacturing & Wholesale Goods"
        }
    ],
    "sg:phone":"+44 1635 297217",
    "sg:postcode":"RG20 5NZ",
    "sg:province":"Berkshire",
    "sg:tags":[
        "mixed",
        "crop"
    ],
    "wof:name":"N Rawlings",
    "wof:placetype":"venue"
},
  "geometry": {"coordinates":[-1.2477829456,51.3238945007],"type":"Point"}
}