{
  "type": "Feature",
  "properties": {
    "addr:full":"Streche Road Wareham Dorset BH20 4QQ",
    "addr:postcode":"bh20 4qq",
    "addr:street":"Streche Road",
    "iso:country":"GB",
    "sg:address":"Streche Road",
    "sg:city":"Wareham",
    "sg:classifiers":[
        {
            "category":"Health Services",
            "subcategory":"Hospital",
            "type":"Services"
        }
    ],
    "sg:phone":"+44 1929 552433",
    "sg:postcode":"BH20 4QQ",
    "sg:province":"Dorset",
    "wof:name":"Wareham Community Hospital",
    "wof:placetype":"venue"
},
  "geometry": {"coordinates":[-2.115629,50.686707],"type":"Point"}
}