{
  "type": "Feature",
  "properties": {
    "addr:full":"Hackensall Road, Knott End Poulton-le-fylde Lancashire FY6 0AX",
    "addr:postcode":"fy6 0ax",
    "addr:street":"Hackensall Road Knott End Poulton-Le-Fylde",
    "iso:country":"GB",
    "sg:address":"Hackensall Road, Knott End",
    "sg:city":"Poulton-le-fylde",
    "sg:classifiers":[
        {
            "category":"Place Of Worship",
            "type":"Public Place"
        }
    ],
    "sg:postcode":"FY6 0AX",
    "sg:province":"Lancashire",
    "wof:name":"St. Bernards",
    "wof:placetype":"venue"
},
  "geometry": {"coordinates":[-2.9885339737,53.9253311157],"type":"Point"}
}