{
  "type": "Feature",
  "properties": {
    "addr:full":"Archway Road Sub Post Office, 21 Archway Road London Greater London N19 3TU",
    "addr:housenumber":"21",
    "addr:postcode":"n19 3tu",
    "addr:street":"Archway;Archway Road",
    "iso:country":"GB",
    "sg:address":"Archway Road Sub Post Office, 21 Archway Road",
    "sg:city":"London",
    "sg:classifiers":[
        {
            "category":"Shopping",
            "subcategory":"News",
            "type":"Retail Goods"
        }
    ],
    "sg:phone":"+44 20 7272 1418",
    "sg:postcode":"N19 3TU",
    "sg:province":"Greater London",
    "sg:tags":[
        "newsagent"
    ],
    "wof:name":"Biggs & Co",
    "wof:placetype":"venue"
},
  "geometry": {"coordinates":[-0.1365700066,51.5685195923],"type":"Point"}
}