{
  "type": "Feature",
  "properties": {
    "addr:full":"132 Broughton Street, Cheetham Manchester Greater Manchester M8 8AN",
    "addr:housenumber":"132",
    "addr:postcode":"m8 8an",
    "addr:street":"Broughton Street",
    "iso:country":"GB",
    "sg:address":"132 Broughton Street, Cheetham",
    "sg:city":"Manchester",
    "sg:classifiers":[
        {
            "category":"Sports & Exercise",
            "subcategory":"Athletic Track",
            "type":"Entertainment"
        }
    ],
    "sg:phone":"+44 161 834 8312",
    "sg:postcode":"M8 8AN",
    "sg:province":"Greater Manchester",
    "sg:tags":[
        "bags",
        "accessory",
        "belt"
    ],
    "wof:name":"G Bright Handbags Ltd.",
    "wof:placetype":"venue"
},
  "geometry": {"coordinates":[-2.2474820614,53.4974746704],"type":"Point"}
}