{
  "type": "Feature",
  "properties": {
    "iso:country":"GB",
    "sg:address":"72 West Street, Portchester",
    "sg:city":"Fareham",
    "sg:classifiers":[
        {
            "category":"Professional",
            "subcategory":"Accounting & Tax Preparation",
            "type":"Services"
        }
    ],
    "sg:phone":"+44 23 9220 0270",
    "sg:postcode":"PO16 9UN",
    "sg:province":"Hampshire",
    "sg:tags":[
        "accountant",
        "activity"
    ],
    "wof:name":"D V Marlow & Co",
    "wof:placetype":"venue"
},
  "geometry": {"coordinates":[-1.128741,50.845894],"type":"Point"}
}