{
  "type": "Feature",
  "properties": {
    "iso:country":"GB",
    "sg:address":"6 Bon Accord Square",
    "sg:city":"Aberdeen",
    "sg:classifiers":[
        {
            "category":"Professional",
            "subcategory":"Lawyer & Legal Services",
            "type":"Services"
        }
    ],
    "sg:postcode":"AB11 6XU",
    "sg:province":"Aberdeen City",
    "sg:tags":[
        "solicitor"
    ],
    "wof:name":"Adam Cochran",
    "wof:placetype":"venue"
},
  "geometry": {"coordinates":[-2.106656,57.142822],"type":"Point"}
}