{
  "type": "Feature",
  "properties": {
    "iso:country":"GB",
    "sg:address":"35 Liverpool Road, Crosby",
    "sg:city":"Liverpool",
    "sg:classifiers":[
        {
            "category":"Banks & Credit Unions",
            "subcategory":"Investment Brokerage",
            "type":"Services"
        }
    ],
    "sg:phone":"+44 151 474 0400",
    "sg:postcode":"L23 5SD",
    "sg:province":"Merseyside",
    "sg:tags":[
        "pension"
    ],
    "wof:name":"Ian Dickson",
    "wof:placetype":"venue"
},
  "geometry": {"coordinates":[-3.025559,53.49205],"type":"Point"}
}