{
  "type": "Feature",
  "properties": {
    "iso:country":"GB",
    "sg:address":"3 Birdbrook Road",
    "sg:city":"Birmingham",
    "sg:classifiers":[
        {
            "category":"Shopping",
            "subcategory":"News",
            "type":"Retail Goods"
        }
    ],
    "sg:phone":"+44 121 605 4080",
    "sg:postcode":"B44 8RA",
    "sg:province":"West Midlands",
    "sg:tags":[
        "newsagent"
    ],
    "wof:name":"Brooklyn News",
    "wof:placetype":"venue"
},
  "geometry": {"coordinates":[-1.895109,52.539017],"type":"Point"}
}