{
  "type": "Feature",
  "properties": {
    "iso:country":"GB",
    "sg:address":"Unit 6 Cross Lane Business Park, Headlands Road",
    "sg:city":"Liversedge",
    "sg:classifiers":[
        {
            "category":"Retail",
            "subcategory":"Auto Repair",
            "type":"Services"
        }
    ],
    "sg:postcode":"WF15 6PR",
    "sg:province":"West Yorkshire",
    "sg:tags":[
        "modification",
        "garage"
    ],
    "wof:name":"D E A L S Autos",
    "wof:placetype":"venue"
},
  "geometry": {"coordinates":[-1.703635,53.710667],"type":"Point"}
}