{
  "type": "Feature",
  "properties": {
    "addr:full":"18 Concanon Road London Greater London SW2 5TA",
    "addr:housenumber":"18",
    "addr:postcode":"sw2 5ta",
    "addr:street":"Concanon Road",
    "iso:country":"GB",
    "sg:address":"18 Concanon Road",
    "sg:city":"London",
    "sg:classifiers":[
        {
            "category":"Professional",
            "subcategory":"Computer Services",
            "type":"Services"
        }
    ],
    "sg:phone":"+44 20 7274 0148",
    "sg:postcode":"SW2 5TA",
    "sg:province":"Greater London",
    "sg:tags":[
        "system",
        "software"
    ],
    "wof:name":"Suretech (U K) Ltd.",
    "wof:placetype":"venue"
},
  "geometry": {"coordinates":[-0.121355,51.460613],"type":"Point"}
}