{
  "type": "Feature",
  "properties": {
    "addr:full":"49 Gibson St Glasgow Glasgow City G12 8NN",
    "addr:housenumber":"49",
    "addr:postcode":"g12 8nn",
    "addr:street":"Gibson St",
    "iso:country":"GB",
    "sg:address":"49 Gibson St",
    "sg:city":"Glasgow",
    "sg:classifiers":[
        {
            "category":"Communications",
            "subcategory":"Film & Video Production",
            "type":"Services"
        }
    ],
    "sg:phone":"+44 141 576 4500",
    "sg:postcode":"G12 8NN",
    "sg:province":"Glasgow City",
    "sg:tags":[
        "recording",
        "studio"
    ],
    "wof:name":"Westside Digital",
    "wof:placetype":"venue"
},
  "geometry": {"coordinates":[-4.2843089104,55.8729782104],"type":"Point"}
}