{
  "type": "Feature",
  "properties": {
    "addr:full":"1 Crossing Lane, The Common, Langley Burrell Chippenham Wiltshire SN15 4LQ",
    "addr:housenumber":"1",
    "addr:postcode":"sn15 4lq",
    "addr:street":"Crossing Lane The Common",
    "iso:country":"GB",
    "sg:address":"1 Crossing Lane, The Common, Langley Burrell",
    "sg:city":"Chippenham",
    "sg:classifiers":[
        {
            "category":"Real Estate",
            "subcategory":"Architect",
            "type":"Services"
        }
    ],
    "sg:postcode":"SN15 4LQ",
    "sg:province":"Wiltshire",
    "wof:name":"Roger Wilson",
    "wof:placetype":"venue"
},
  "geometry": {"coordinates":[-2.0952510834,51.4751701355],"type":"Point"}
}