{
  "type": "Feature",
  "properties": {
    "addr:full":"238-240 County Rd Liverpool Merseyside L4 5PJ",
    "addr:housenumber":"238-240",
    "addr:postcode":"l4 5pj",
    "addr:street":"County Rd",
    "iso:country":"GB",
    "sg:address":"238-240 County Rd",
    "sg:city":"Liverpool",
    "sg:classifiers":[
        {
            "category":"Personal",
            "type":"Services"
        }
    ],
    "sg:phone":"+44 151 525 9606",
    "sg:postcode":"L4 5PJ",
    "sg:province":"Merseyside",
    "sg:tags":[
        "wedding"
    ],
    "wof:name":"Special Guests",
    "wof:placetype":"venue"
},
  "geometry": {"coordinates":[-2.968219,53.444923],"type":"Point"}
}