{
  "type": "Feature",
  "properties": {
    "iso:country":"GB",
    "sg:address":"Hamilton Road Maltby",
    "sg:city":"Rotherham",
    "sg:classifiers":[
        {
            "category":"Professional",
            "subcategory":"Engineering",
            "type":"Services"
        }
    ],
    "sg:phone":"+44 1709 813636",
    "sg:postcode":"S66 7NE",
    "sg:province":"South Yorkshire",
    "sg:tags":[
        "precision",
        "engineer"
    ],
    "wof:name":"Lantern Engineering Ltd.",
    "wof:placetype":"venue"
},
  "geometry": {"coordinates":[-1.201234,53.423271],"type":"Point"}
}