{
  "type": "Feature",
  "properties": {
    "iso:country":"GB",
    "sg:address":"21 South Street",
    "sg:city":"Wareham",
    "sg:classifiers":[
        {
            "category":"Shopping",
            "subcategory":"Department Store",
            "type":"Retail Goods"
        },
        {
            "category":"Shopping",
            "subcategory":"Comic Books",
            "type":"Retail Goods"
        }
    ],
    "sg:phone":"+44 1929 554207",
    "sg:postcode":"BH20 4LR",
    "sg:province":"Dorset",
    "sg:tags":[
        "jeweller"
    ],
    "wof:name":"Heirlooms Antique Jewellers & Silversmiths",
    "wof:placetype":"venue"
},
  "geometry": {"coordinates":[-2.109371,50.685001],"type":"Point"}
}