{
  "type": "Feature",
  "properties": {
    "iso:country":"GB",
    "sg:address":"32 High Road, South Wingfield",
    "sg:city":"Alfreton",
    "sg:classifiers":[
        {
            "category":"Travel",
            "subcategory":"Hotels & Motels",
            "type":"Entertainment"
        }
    ],
    "sg:phone":"+44 1773 832280",
    "sg:postcode":"DE55 7LX",
    "sg:province":"Derbyshire",
    "sg:tags":[
        "house",
        "guest"
    ],
    "wof:name":"Platts Farm Guest House",
    "wof:placetype":"venue"
},
  "geometry": {"coordinates":[-1.438392,53.098171],"type":"Point"}
}