{
  "type": "Feature",
  "properties": {
    "addr:full":"274 Green Street London Greater London E7 8LF",
    "addr:housenumber":"274",
    "addr:postcode":"e7 8lf",
    "addr:street":"Green Street",
    "iso:country":"GB",
    "sg:address":"274 Green Street",
    "sg:city":"London",
    "sg:classifiers":[
        {
            "category":"Food & Beverages",
            "subcategory":"Supermarket",
            "type":"Retail Goods"
        }
    ],
    "sg:phone":"+44 20 8471 5051",
    "sg:postcode":"E7 8LF",
    "sg:province":"Greater London",
    "wof:name":"Mina Store",
    "wof:placetype":"venue"
},
  "geometry": {"coordinates":[0.0332809985,51.5383834839],"type":"Point"}
}