{
  "type": "Feature",
  "properties": {
    "iso:country":"GB",
    "sg:address":"2 Northedge La",
    "sg:city":"Halifax",
    "sg:classifiers":[
        {
            "category":"Professional",
            "subcategory":"Detective & Security Services",
            "type":"Services"
        }
    ],
    "sg:phone":"+44 1422 202902",
    "sg:postcode":"HX3 8JZ",
    "sg:province":"West Yorkshire",
    "wof:name":"K Security Ltd",
    "wof:placetype":"venue"
},
  "geometry": {"coordinates":[-1.815114,53.730598],"type":"Point"}
}