{
  "type": "Feature",
  "properties": {
    "addr:full":"Walker Road, Bardon Hill Coalville Leicestershire LE67 1TZ",
    "addr:postcode":"le67 1tz",
    "addr:street":"Walker Road Bardon Hill",
    "iso:country":"GB",
    "sg:address":"Walker Road, Bardon Hill",
    "sg:city":"Coalville",
    "sg:classifiers":[
        {
            "category":"Freight",
            "type":"Transportation"
        }
    ],
    "sg:phone":"+44 1530 831500",
    "sg:postcode":"LE67 1TZ",
    "sg:province":"Leicestershire",
    "sg:tags":[
        "forwarders"
    ],
    "wof:name":"Securicor Omega International Ltd.",
    "wof:placetype":"venue"
},
  "geometry": {"coordinates":[-1.330364,52.702362],"type":"Point"}
}