{
  "type": "Feature",
  "properties": {
    "iso:country":"GB",
    "sg:address":"3 Bidewell Close, Drayton",
    "sg:city":"Norwich",
    "sg:classifiers":[
        {
            "category":"Home & Garden",
            "subcategory":"Home Furnishings",
            "type":"Retail Goods"
        }
    ],
    "sg:postcode":"NR8 6AP",
    "sg:province":"Norfolk",
    "sg:tags":[
        "blind",
        "curtain",
        "fitting"
    ],
    "wof:name":"Curtain Designs",
    "wof:placetype":"venue"
},
  "geometry": {"coordinates":[1.2254149914,52.6754837036],"type":"Point"}
}