{
  "type": "Feature",
  "properties": {
    "iso:country":"GB",
    "sg:address":"23 High Street, Rishton",
    "sg:city":"Blackburn",
    "sg:classifiers":[
        {
            "category":"Food & Beverages",
            "subcategory":"Meat & Fish",
            "type":"Retail Goods"
        }
    ],
    "sg:phone":"+44 1254 887564",
    "sg:postcode":"BB1 4JZ",
    "sg:province":"Lancashire",
    "sg:tags":[
        "butcher"
    ],
    "wof:name":"Peter Norman",
    "wof:placetype":"venue"
},
  "geometry": {"coordinates":[-2.414803,53.768089],"type":"Point"}
}