{
  "type": "Feature",
  "properties": {
    "addr:full":"389 Barking Road London Greater London E6 2JT",
    "addr:housenumber":"389",
    "addr:postcode":"e6 2jt",
    "addr:street":"Barking Road",
    "iso:country":"GB",
    "sg:address":"389 Barking Road",
    "sg:city":"London",
    "sg:classifiers":[
        {
            "category":"Real Estate",
            "subcategory":"Real Estate Agent",
            "type":"Services"
        }
    ],
    "sg:phone":"+44 20 8552 3366",
    "sg:postcode":"E6 2JT",
    "sg:province":"Greater London",
    "wof:name":"Taylors",
    "wof:placetype":"venue"
},
  "geometry": {"coordinates":[0.054796,51.533245],"type":"Point"}
}