{
  "type": "Feature",
  "properties": {
    "addr:full":"Unit 1a Butterthwaite Lane, Ecclesfield Sheffield South Yorkshire S35 9WA",
    "addr:housenumber":"unit 1a",
    "addr:postcode":"s35 9wa",
    "addr:street":"Butterthwaite Lane",
    "iso:country":"GB",
    "sg:address":"Unit 1a Butterthwaite Lane, Ecclesfield",
    "sg:city":"Sheffield",
    "sg:classifiers":[
        {
            "category":"Manufacturing",
            "subcategory":"Petroleum Products",
            "type":"Manufacturing & Wholesale Goods"
        }
    ],
    "sg:postcode":"S35 9WA",
    "sg:province":"South Yorkshire",
    "sg:tags":[
        "double",
        "glazing"
    ],
    "wof:name":"Warwick Development Ltd.",
    "wof:placetype":"venue"
},
  "geometry": {"coordinates":[-1.4519100189,53.4414710999],"type":"Point"}
}