{
  "type": "Feature",
  "properties": {
    "addr:full":"148 Huddersfield Rd Mirfield West Yorkshire WF14 8AN",
    "addr:housenumber":"148",
    "addr:postcode":"wf14 8an",
    "addr:street":"Huddersfield Rd",
    "iso:country":"GB",
    "sg:address":"148 Huddersfield Rd",
    "sg:city":"Mirfield",
    "sg:classifiers":[
        {
            "category":"Home & Garden",
            "subcategory":"Hardware",
            "type":"Retail Goods"
        }
    ],
    "sg:phone":"+44 1924 494496",
    "sg:postcode":"WF14 8AN",
    "sg:province":"West Yorkshire",
    "sg:tags":[
        "retailer",
        "diy"
    ],
    "wof:name":"WHITE ROSE DECOR",
    "wof:placetype":"venue"
},
  "geometry": {"coordinates":[-1.6936750412,53.6741371155],"type":"Point"}
}