{
  "type": "Feature",
  "properties": {
    "iso:country":"GB",
    "sg:address":"118 Rectory Lane, Standish",
    "sg:city":"Wigan",
    "sg:classifiers":[
        {
            "category":"Freight",
            "type":"Transportation"
        }
    ],
    "sg:phone":"+44 1257 423462",
    "sg:postcode":"WN1 2TY",
    "sg:province":"Lancashire",
    "sg:tags":[
        "haulage",
        "road"
    ],
    "wof:name":"C & S Banks",
    "wof:placetype":"venue"
},
  "geometry": {"coordinates":[-2.638644,53.58585],"type":"Point"}
}