{
  "type": "Feature",
  "properties": {
    "addr:full":"40 Chapelhay Heights Weymouth Dorset DT4 8JL",
    "addr:housenumber":"40",
    "addr:postcode":"dt4 8jl",
    "addr:street":"Chapelhay Heights",
    "iso:country":"GB",
    "sg:address":"40 Chapelhay Heights",
    "sg:city":"Weymouth",
    "sg:classifiers":[
        {
            "category":"Retail",
            "subcategory":"Repair Shop",
            "type":"Services"
        }
    ],
    "sg:postcode":"DT4 8JL",
    "sg:province":"Dorset",
    "sg:tags":[
        "maintenance"
    ],
    "wof:name":"M & P Roberts Property Maintenance",
    "wof:placetype":"venue"
},
  "geometry": {"coordinates":[-2.456544,50.605797],"type":"Point"}
}