{
  "type": "Feature",
  "properties": {
    "addr:full":"Riverside House, Irwell Street Salford Greater Manchester M3 5EN",
    "addr:postcode":"m3 5en",
    "addr:street":"Irwell Street",
    "iso:country":"GB",
    "sg:address":"Riverside House, Irwell Street",
    "sg:city":"Salford",
    "sg:classifiers":[
        {
            "category":"Banks & Credit Unions",
            "subcategory":"Investment Brokerage",
            "type":"Services"
        },
        {
            "category":"Banks & Credit Unions",
            "subcategory":"Bank",
            "type":"Services"
        }
    ],
    "sg:phone":"+44 161 834 7195",
    "sg:postcode":"M3 5EN",
    "sg:province":"Greater Manchester",
    "sg:tags":[
        "broker",
        "mortgage"
    ],
    "wof:name":"Migdal Investments Ltd.",
    "wof:placetype":"venue"
},
  "geometry": {"coordinates":[-2.2570290565,53.4816436768],"type":"Point"}
}