{
  "type": "Feature",
  "properties": {
    "iso:country":"GB",
    "sg:address":"Victory Ho, West Pde",
    "sg:city":"Halifax",
    "sg:classifiers":[
        {
            "category":"Professional",
            "subcategory":"Business Services",
            "type":"Services"
        }
    ],
    "sg:postcode":"HX1 2TE",
    "sg:province":"West Yorkshire",
    "sg:tags":[
        "tile",
        "stockist"
    ],
    "wof:name":"Cash & Carry Tiles",
    "wof:placetype":"venue"
},
  "geometry": {"coordinates":[-1.862224,53.721233],"type":"Point"}
}