{
  "type": "Feature",
  "properties": {
    "addr:full":"109 Cumber Close, Malborough Kingsbridge Devon TQ7 3DG",
    "addr:housenumber":"109",
    "addr:postcode":"tq7 3dg",
    "addr:street":"Cumber Close",
    "iso:country":"GB",
    "sg:address":"109 Cumber Close, Malborough",
    "sg:city":"Kingsbridge",
    "sg:classifiers":[
        {
            "category":"Building & Trades",
            "subcategory":"Construction",
            "type":"Services"
        }
    ],
    "sg:postcode":"TQ7 3DG",
    "sg:province":"Devon",
    "sg:tags":[
        "joiner",
        "carpenter"
    ],
    "wof:name":"Roy Pearse",
    "wof:placetype":"venue"
},
  "geometry": {"coordinates":[-3.8060588837,50.2422370911],"type":"Point"}
}