{
  "type": "Feature",
  "properties": {
    "iso:country":"GB",
    "sg:address":"P O Box 127",
    "sg:city":"Northampton",
    "sg:classifiers":[
        {
            "category":"Utilities",
            "type":"Services"
        }
    ],
    "sg:postcode":"NN3 3ZE",
    "sg:province":"Northamptonshire",
    "sg:tags":[
        "internet"
    ],
    "wof:name":"F P Interactive",
    "wof:placetype":"venue"
},
  "geometry": {"coordinates":[-0.8451690078,52.2493095398],"type":"Point"}
}