{
  "type": "Feature",
  "properties": {
    "addr:full":"Unit 11, Brackendale Mills, Brackendale Bradford West Yorkshire BD10 0SJ",
    "addr:housenumber":"unit 11;bradford",
    "addr:postcode":"bd10 0sj",
    "addr:street":"Brackendale Mills Brackendale",
    "iso:country":"GB",
    "sg:address":"Unit 11, Brackendale Mills, Brackendale",
    "sg:city":"Bradford",
    "sg:classifiers":[
        {
            "category":"Building & Trades",
            "subcategory":"Construction",
            "type":"Services"
        }
    ],
    "sg:phone":"+44 1274 771620",
    "sg:postcode":"BD10 0SJ",
    "sg:province":"West Yorkshire",
    "sg:tags":[
        "builder"
    ],
    "wof:name":"R J Building Services",
    "wof:placetype":"venue"
},
  "geometry": {"coordinates":[-1.7430830002,53.8443565369],"type":"Point"}
}