{
  "type": "Feature",
  "properties": {
    "addr:full":"Parsonage Farm, Church Road, Elmstead Market Colchester Essex CO7 7AP",
    "addr:postcode":"co7 7ap",
    "addr:street":"Church Road",
    "iso:country":"GB",
    "sg:address":"Parsonage Farm, Church Road, Elmstead Market",
    "sg:city":"Colchester",
    "sg:classifiers":[
        {
            "category":"Building & Trades",
            "subcategory":"Landscaping Services",
            "type":"Services"
        }
    ],
    "sg:postcode":"CO7 7AP",
    "sg:province":"Essex",
    "sg:tags":[
        "forestry",
        "tree"
    ],
    "wof:name":"Allston Landscapes",
    "wof:placetype":"venue"
},
  "geometry": {"coordinates":[0.9977769852,51.8933753967],"type":"Point"}
}