{
  "type": "Feature",
  "properties": {
    "iso:country":"GB",
    "sg:address":"10 St Martins Palace Plain",
    "sg:city":"Norwich",
    "sg:classifiers":[
        {
            "category":"Shopping",
            "subcategory":"Photographic Equipment",
            "type":"Retail Goods"
        }
    ],
    "sg:phone":"+44 1603 610610",
    "sg:postcode":"NR3 1RN",
    "sg:province":"Norfolk",
    "wof:name":"Foto Majik",
    "wof:placetype":"venue"
},
  "geometry": {"coordinates":[1.3008890152,52.6333961487],"type":"Point"}
}