{
  "type": "Feature",
  "properties": {
    "addr:full":"75 High Street Boston Lincolnshire PE21 8SX",
    "addr:housenumber":"75",
    "addr:postcode":"pe21 8sx",
    "addr:street":"High Street",
    "iso:country":"GB",
    "sg:address":"75 High Street",
    "sg:city":"Boston",
    "sg:classifiers":[
        {
            "category":"Professional",
            "subcategory":"Business Services",
            "type":"Services"
        }
    ],
    "sg:postcode":"PE21 8SX",
    "sg:province":"Lincolnshire",
    "sg:tags":[
        "assessment",
        "quality"
    ],
    "wof:name":"I.I.C. Ltd.",
    "wof:placetype":"venue"
},
  "geometry": {"coordinates":[-0.0291239992,52.974697113],"type":"Point"}
}