{
  "type": "Feature",
  "properties": {
    "iso:country":"GB",
    "sg:address":"16 Chester Street",
    "sg:city":"Mold",
    "sg:classifiers":[
        {
            "category":"Professional",
            "subcategory":"Lawyer & Legal Services",
            "type":"Services"
        }
    ],
    "sg:phone":"+44 1352 753808",
    "sg:postcode":"CH7 1EG",
    "sg:province":"Denbighshire",
    "sg:tags":[
        "solicitor"
    ],
    "wof:name":"Keene & Kelly & Keith Williams & Co",
    "wof:placetype":"venue"
},
  "geometry": {"coordinates":[-3.138173,53.168125],"type":"Point"}
}