{
  "type": "Feature",
  "properties": {
    "iso:country":"GB",
    "sg:address":"119 Griffins Brook Lane",
    "sg:city":"Birmingham",
    "sg:classifiers":[
        {
            "category":"Health Services",
            "subcategory":"Doctor",
            "type":"Services"
        },
        {
            "category":"Health Services",
            "subcategory":"Clinic",
            "type":"Services"
        }
    ],
    "sg:phone":"+44 121 476 2441",
    "sg:postcode":"B30 1QN",
    "sg:province":"West Midlands",
    "sg:tags":[
        "nh",
        "practitioners"
    ],
    "wof:name":"Griffins Brook Medical Centre",
    "wof:placetype":"venue"
},
  "geometry": {"coordinates":[-1.9532879591,52.4260749817],"type":"Point"}
}