{
  "type": "Feature",
  "properties": {
    "addr:full":"119 High Street Hornchurch Essex RM11 1TX",
    "addr:housenumber":"119",
    "addr:postcode":"rm11 1tx",
    "addr:street":"High Street",
    "iso:country":"GB",
    "sg:address":"119 High Street",
    "sg:city":"Hornchurch",
    "sg:classifiers":[
        {
            "category":"Shopping",
            "subcategory":"Gifts & Souvenirs",
            "type":"Retail Goods"
        }
    ],
    "sg:phone":"+44 1708 448597",
    "sg:postcode":"RM11 1TX",
    "sg:province":"Essex",
    "sg:tags":[
        "poster",
        "card"
    ],
    "wof:name":"J Myers",
    "wof:placetype":"venue"
},
  "geometry": {"coordinates":[0.2196500003,51.5626029968],"type":"Point"}
}