{
  "type": "Feature",
  "properties": {
    "addr:full":"82 The Mall, Queensmere Centre Slough Berkshire SL1 1DG",
    "addr:housenumber":"82",
    "addr:postcode":"sl1 1dg",
    "addr:street":"The Mall Queensmere Centre",
    "iso:country":"GB",
    "sg:address":"82 The Mall, Queensmere Centre",
    "sg:city":"Slough",
    "sg:classifiers":[
        {
            "category":"Shopping",
            "subcategory":"Pharmacy",
            "type":"Retail Goods"
        }
    ],
    "sg:phone":"+44 1753 692067",
    "sg:postcode":"SL1 1DG",
    "sg:province":"Berkshire",
    "sg:tags":[
        "store",
        "drug",
        "outlet"
    ],
    "wof:name":"Superdrug Stores Plc",
    "wof:placetype":"venue"
},
  "geometry": {"coordinates":[-0.5964170098,51.5078735352],"type":"Point"}
}