{
  "type": "Feature",
  "properties": {
    "iso:country":"GB",
    "sg:address":"Wested Lane",
    "sg:city":"Swanley",
    "sg:classifiers":[
        {
            "category":"Professional",
            "subcategory":"Detective & Security Services",
            "type":"Services"
        }
    ],
    "sg:phone":"+44 1322 665301",
    "sg:postcode":"BR8 8TE",
    "sg:province":"Kent",
    "wof:name":"Pedham Place Estate Security Office",
    "wof:placetype":"venue"
},
  "geometry": {"coordinates":[0.1901179999,51.387802124],"type":"Point"}
}