{
  "type": "Feature",
  "properties": {
    "iso:country":"GB",
    "sg:address":"10 Main Street, Cruden Bay",
    "sg:city":"Peterhead",
    "sg:classifiers":[
        {
            "category":"Food & Beverages",
            "subcategory":"Fruits & Vegetables",
            "type":"Retail Goods"
        }
    ],
    "sg:phone":"+44 1779 813250",
    "sg:postcode":"AB42 0NA",
    "sg:province":"Aberdeenshire",
    "sg:tags":[
        "greengrocer"
    ],
    "wof:name":"Cruden Bay Stores",
    "wof:placetype":"venue"
},
  "geometry": {"coordinates":[-1.849418,57.416779],"type":"Point"}
}