{
  "type": "Feature",
  "properties": {
    "addr:full":"211 Yorkshire Street Rochdale Lancashire OL12 0DS",
    "addr:housenumber":"211",
    "addr:postcode":"ol12 0ds",
    "addr:street":"Yorkshire Street",
    "iso:country":"GB",
    "sg:address":"211 Yorkshire Street",
    "sg:city":"Rochdale",
    "sg:classifiers":[
        {
            "category":"Manufacturing",
            "subcategory":"Rubber & Plastics",
            "type":"Manufacturing & Wholesale Goods"
        }
    ],
    "sg:phone":"+44 1706 868846",
    "sg:postcode":"OL12 0DS",
    "sg:province":"Lancashire",
    "sg:tags":[
        "product",
        "foam"
    ],
    "wof:name":"The Foam Shop",
    "wof:placetype":"venue"
},
  "geometry": {"coordinates":[-2.1483519077,53.6220741272],"type":"Point"}
}