{
  "type": "Feature",
  "properties": {
    "addr:full":"34 Selby Road Ashford Greater London TW15 1JH",
    "addr:housenumber":"34",
    "addr:postcode":"tw15 1jh",
    "addr:street":"Selby Road",
    "iso:country":"GB",
    "sg:address":"34 Selby Road",
    "sg:city":"Ashford",
    "sg:classifiers":[
        {
            "category":"Real Estate",
            "subcategory":"Surveying",
            "type":"Services"
        }
    ],
    "sg:phone":"+44 1784 240411",
    "sg:postcode":"TW15 1JH",
    "sg:province":"Greater London",
    "sg:tags":[
        "building",
        "surveyor"
    ],
    "wof:name":"Kevin J Turner Assoc Surveyors",
    "wof:placetype":"venue"
},
  "geometry": {"coordinates":[-0.4464130104,51.423664093],"type":"Point"}
}