{
  "type": "Feature",
  "properties": {
    "addr:full":"82 Fishergate Walk, St Georges Shopping Centre Preston Lancashire PR1 2BU",
    "addr:housenumber":"82",
    "addr:postcode":"pr1 2bu",
    "addr:street":"Fishergate Walk St;Preston",
    "iso:country":"GB",
    "sg:address":"82 Fishergate Walk, St Georges Shopping Centre",
    "sg:city":"Preston",
    "sg:classifiers":[
        {
            "category":"Shopping",
            "subcategory":"Clothing, Apparel, & Fashions",
            "type":"Retail Goods"
        }
    ],
    "sg:phone":"+44 1772 827632",
    "sg:postcode":"PR1 2BU",
    "sg:province":"Lancashire",
    "sg:tags":[
        "shop"
    ],
    "wof:name":"Sears Ltd.",
    "wof:placetype":"venue"
},
  "geometry": {"coordinates":[-2.7057290077,53.7579612732],"type":"Point"}
}