{
  "type": "Feature",
  "properties": {
    "iso:country":"GB",
    "sg:address":"The Billet, Parsonage Lane",
    "sg:city":"Sawbridgeworth",
    "sg:classifiers":[
        {
            "category":"Manufacturing",
            "subcategory":"Glass & Minerals",
            "type":"Manufacturing & Wholesale Goods"
        }
    ],
    "sg:phone":"+44 1279 721035",
    "sg:postcode":"CM21 0ND",
    "sg:province":"Essex",
    "sg:tags":[
        "fibre",
        "moulding"
    ],
    "wof:name":"Pro-Laminates",
    "wof:placetype":"venue"
},
  "geometry": {"coordinates":[0.147223,51.812527],"type":"Point"}
}