{
  "type": "Feature",
  "properties": {
    "iso:country":"GB",
    "sg:address":"Community Centre, Bank St",
    "sg:city":"Coleford",
    "sg:classifiers":[
        {
            "category":"Professional",
            "subcategory":"Lawyer & Legal Services",
            "type":"Services"
        }
    ],
    "sg:phone":"+44 1594 833717",
    "sg:postcode":"GL16 8BA",
    "sg:province":"Gloucestershire",
    "sg:tags":[
        "advice",
        "counselling"
    ],
    "wof:name":"Forest Of Dean Cab",
    "wof:placetype":"venue"
},
  "geometry": {"coordinates":[-2.6040890217,51.79139328],"type":"Point"}
}