{
  "type": "Feature",
  "properties": {
    "iso:country":"GB",
    "sg:address":"70c Wheelock Street",
    "sg:city":"Middlewich",
    "sg:classifiers":[
        {
            "category":"Shopping",
            "type":"Retail Goods"
        }
    ],
    "sg:phone":"+44 1606 737208",
    "sg:postcode":"CW10 9AB",
    "sg:province":"Cheshire",
    "sg:tags":[
        "part",
        "accessory"
    ],
    "wof:name":"Middlewich Autoparts",
    "wof:placetype":"venue"
},
  "geometry": {"coordinates":[-2.448631,53.193382],"type":"Point"}
}