{
  "type": "Feature",
  "properties": {
    "addr:full":"Watford Rd St Albans Hertfordshire AL2 3EA",
    "addr:postcode":"al2 3ea",
    "addr:street":"Watford Rd",
    "iso:country":"GB",
    "sg:address":"Watford Rd",
    "sg:city":"St Albans",
    "sg:classifiers":[
        {
            "category":"Restaurant",
            "type":"Food & Drink"
        }
    ],
    "sg:phone":"+44 1727 851103",
    "sg:postcode":"AL2 3EA",
    "sg:province":"Hertfordshire",
    "wof:name":"Punch Inns (U K) Ltd",
    "wof:placetype":"venue"
},
  "geometry": {"coordinates":[-0.357129,51.731964],"type":"Point"}
}