{
  "type": "Feature",
  "properties": {
    "iso:country":"GB",
    "sg:address":"17 Capulet Close, Eaton Socon St. Neots",
    "sg:city":"Huntingdon",
    "sg:classifiers":[
        {
            "category":"Retail",
            "subcategory":"Storage",
            "type":"Services"
        }
    ],
    "sg:phone":"+44 1480 477339",
    "sg:postcode":"PE19 3UQ",
    "sg:province":"Bedfordshire",
    "sg:tags":[
        "shelving",
        "system"
    ],
    "wof:name":"Dashwood Metal Products",
    "wof:placetype":"venue"
},
  "geometry": {"coordinates":[-0.2720400095,52.2462692261],"type":"Point"}
}