{
  "type": "Feature",
  "properties": {
    "addr:full":"18 Lairds Hill Place, Kilsyth Glasgow East Dunbartonshire G65 9EX",
    "addr:housenumber":"18",
    "addr:postcode":"g65 9ex",
    "addr:street":"Lairds Hill Place",
    "iso:country":"GB",
    "sg:address":"18 Lairds Hill Place, Kilsyth",
    "sg:city":"Glasgow",
    "sg:classifiers":[
        {
            "category":"Professional",
            "subcategory":"Accounting & Tax Preparation",
            "type":"Services"
        }
    ],
    "sg:phone":"+44 1236 824027",
    "sg:postcode":"G65 9EX",
    "sg:province":"East Dunbartonshire",
    "sg:tags":[
        "accountant",
        "bookkeeping",
        "primarily",
        "activity"
    ],
    "wof:name":"D & J Business Services",
    "wof:placetype":"venue"
},
  "geometry": {"coordinates":[-4.075466156,55.9766273499],"type":"Point"}
}