{
  "type": "Feature",
  "properties": {
    "addr:full":"36 Easter Warriston Edinburgh City of Edinburgh EH7 4QX",
    "addr:housenumber":"36",
    "addr:postcode":"eh7 4qx",
    "addr:street":"Easter Warriston Edinburgh",
    "iso:country":"GB",
    "sg:address":"36 Easter Warriston",
    "sg:city":"Edinburgh",
    "sg:classifiers":[
        {
            "category":"Professional",
            "subcategory":"Art Services",
            "type":"Services"
        },
        {
            "category":"Building & Trades",
            "subcategory":"Construction",
            "type":"Services"
        }
    ],
    "sg:phone":"+44 131 552 9015",
    "sg:postcode":"EH7 4QX",
    "sg:province":"City of Edinburgh",
    "sg:tags":[
        "decorator",
        "painter"
    ],
    "wof:name":"Curtis Bros Decorators",
    "wof:placetype":"venue"
},
  "geometry": {"coordinates":[-3.199735,55.970722],"type":"Point"}
}