{
  "type": "Feature",
  "properties": {
    "iso:country":"GB",
    "sg:address":"Unit 2 Lowesden Works, Lambourn Woodlands",
    "sg:city":"Hungerford",
    "sg:classifiers":[
        {
            "category":"Professional",
            "subcategory":"Detective & Security Services",
            "type":"Services"
        }
    ],
    "sg:phone":"+44 1488 73585",
    "sg:postcode":"RG17 7RU",
    "sg:province":"Berkshire",
    "sg:tags":[
        "equipment"
    ],
    "wof:name":"Mentor Security Associates",
    "wof:placetype":"venue"
},
  "geometry": {"coordinates":[-1.516156,51.413197],"type":"Point"}
}