{
  "type": "Feature",
  "properties": {
    "addr:full":"24 Fishergate York North Yorkshire YO10 4AB",
    "addr:housenumber":"24",
    "addr:postcode":"yo10 4ab",
    "addr:street":"Fishergate",
    "iso:country":"GB",
    "sg:address":"24 Fishergate",
    "sg:city":"York",
    "sg:classifiers":[
        {
            "category":"Shopping",
            "subcategory":"Pawn Shop",
            "type":"Retail Goods"
        }
    ],
    "sg:phone":"+44 1904 645984",
    "sg:postcode":"YO10 4AB",
    "sg:province":"North Yorkshire",
    "sg:tags":[
        "pawnbroker"
    ],
    "wof:name":"York Pawnbrokers",
    "wof:placetype":"venue"
},
  "geometry": {"coordinates":[-1.077114,53.953766],"type":"Point"}
}