{
  "type": "Feature",
  "properties": {
    "iso:country":"GB",
    "sg:address":"38 & 40 West Street",
    "sg:city":"Bridport",
    "sg:classifiers":[
        {
            "category":"Food & Beverages",
            "subcategory":"Bakery",
            "type":"Retail Goods"
        }
    ],
    "sg:phone":"+44 1308 423384",
    "sg:postcode":"DT6 3QP",
    "sg:province":"Dorset",
    "sg:tags":[
        "baker"
    ],
    "wof:name":"H G Hussey & Sons Ltd.",
    "wof:placetype":"venue"
},
  "geometry": {"coordinates":[-2.7595710754,50.7336997986],"type":"Point"}
}