{
  "type": "Feature",
  "properties": {
    "iso:country":"GB",
    "sg:address":"Newton Moor Industrial Estate, Lodge Street",
    "sg:city":"Hyde",
    "sg:classifiers":[
        {
            "category":"Manufacturing",
            "subcategory":"Wood Products",
            "type":"Manufacturing & Wholesale Goods"
        },
        {
            "category":"Home & Garden",
            "subcategory":"Home Furnishings",
            "type":"Retail Goods"
        }
    ],
    "sg:phone":"+44 161 367 8076",
    "sg:postcode":"SK14 4LE",
    "sg:province":"Cheshire",
    "sg:tags":[
        "furnishers",
        "planner",
        "maker",
        "kitchen",
        "cabinet"
    ],
    "wof:name":"The Richmond Cabinet Co",
    "wof:placetype":"venue"
},
  "geometry": {"coordinates":[-2.080884,53.454311],"type":"Point"}
}