{
  "type": "Feature",
  "properties": {
    "iso:country":"GB",
    "sg:address":"14 Tame Road",
    "sg:city":"Birmingham",
    "sg:classifiers":[
        {
            "category":"Shopping",
            "subcategory":"News",
            "type":"Retail Goods"
        }
    ],
    "sg:phone":"+44 121 327 3272",
    "sg:postcode":"B6 7DS",
    "sg:province":"West Midlands",
    "sg:tags":[
        "newsagent"
    ],
    "wof:name":"Kullar News",
    "wof:placetype":"venue"
},
  "geometry": {"coordinates":[-1.880834,52.513817],"type":"Point"}
}