{
  "type": "Feature",
  "properties": {
    "addr:full":"420-422 Stapleton Road Bristol City of Bristol BS5 6NB",
    "addr:housenumber":"420-422",
    "addr:postcode":"bs5 6nb",
    "addr:street":"Stapleton Road",
    "iso:country":"GB",
    "sg:address":"420-422 Stapleton Road",
    "sg:city":"Bristol",
    "sg:classifiers":[
        {
            "category":"Home & Garden",
            "subcategory":"Furniture",
            "type":"Retail Goods"
        }
    ],
    "sg:phone":"+44 117 951 1041",
    "sg:postcode":"BS5 6NB",
    "sg:province":"City of Bristol",
    "wof:name":"Concord Furnishing",
    "wof:placetype":"venue"
},
  "geometry": {"coordinates":[-2.560779,51.475571],"type":"Point"}
}