{
  "type": "Feature",
  "properties": {
    "addr:full":"Carrick Street Day Centre For The Elderly, 27 Carrick St Ayr South Ayrshire KA7 1NS",
    "addr:housenumber":"27",
    "addr:postcode":"ka7 1ns",
    "addr:street":"Carrick Street;Carrick St",
    "iso:country":"GB",
    "sg:address":"Carrick Street Day Centre For The Elderly, 27 Carrick St",
    "sg:city":"Ayr",
    "sg:classifiers":[
        {
            "category":"Government",
            "subcategory":"Office",
            "type":"Public Place"
        }
    ],
    "sg:phone":"+44 1292 260990",
    "sg:postcode":"KA7 1NS",
    "sg:province":"South Ayrshire",
    "sg:tags":[
        "local"
    ],
    "wof:name":"South Ayrshire Council",
    "wof:placetype":"venue"
},
  "geometry": {"coordinates":[-4.63047,55.46167],"type":"Point"}
}