{
  "type": "Feature",
  "properties": {
    "iso:country":"GB",
    "sg:address":"70-72 Farnborough Road",
    "sg:city":"Farnborough",
    "sg:classifiers":[
        {
            "category":"Banks & Credit Unions",
            "subcategory":"Atm",
            "type":"Services"
        }
    ],
    "sg:postcode":"GU14 6TN",
    "sg:province":"Hampshire",
    "sg:tags":[
        "recording",
        "answering"
    ],
    "wof:name":"A I T Recorders Ltd.",
    "wof:placetype":"venue"
},
  "geometry": {"coordinates":[-0.752981,51.281998],"type":"Point"}
}