{
  "type": "Feature",
  "properties": {
    "iso:country":"GB",
    "sg:address":"Malting, Malting Lane, Dagnall",
    "sg:city":"Berkhamsted",
    "sg:classifiers":[
        {
            "category":"Building & Trades",
            "subcategory":"Construction",
            "type":"Services"
        }
    ],
    "sg:phone":"+44 1442 842589",
    "sg:postcode":"HP4 1QY",
    "sg:province":"Bedfordshire",
    "sg:tags":[
        "builder"
    ],
    "wof:name":"Thameside Construction Co. Ltd.",
    "wof:placetype":"venue"
},
  "geometry": {"coordinates":[-0.560071,51.837891],"type":"Point"}
}