{
  "type": "Feature",
  "properties": {
    "iso:country":"GB",
    "sg:address":"481 Queensferry Road",
    "sg:city":"Edinburgh",
    "sg:classifiers":[
        {
            "category":"Health Services",
            "subcategory":"Podiatrist",
            "type":"Services"
        }
    ],
    "sg:postcode":"EH4 7ND",
    "sg:province":"City of Edinburgh",
    "sg:tags":[
        "podiatrists",
        "chiropodist"
    ],
    "wof:name":"Armstrong's Chiropody",
    "wof:placetype":"venue"
},
  "geometry": {"coordinates":[-3.292439,55.960735],"type":"Point"}
}