{
  "type": "Feature",
  "properties": {
    "addr:full":"114 Lovell Road Cambridge Cambridgeshire CB4 2QP",
    "addr:housenumber":"114",
    "addr:postcode":"cb4 2qp",
    "addr:street":"Lovell Road",
    "iso:country":"GB",
    "sg:address":"114 Lovell Road",
    "sg:city":"Cambridge",
    "sg:classifiers":[
        {
            "category":"Home & Garden",
            "subcategory":"Household Appliances",
            "type":"Retail Goods"
        }
    ],
    "sg:phone":"+44 1223 425587",
    "sg:postcode":"CB4 2QP",
    "sg:province":"Cambridgeshire",
    "sg:tags":[
        "electrical"
    ],
    "wof:name":"I Wilson",
    "wof:placetype":"venue"
},
  "geometry": {"coordinates":[0.1420339942,52.2311973572],"type":"Point"}
}