{
  "type": "Feature",
  "properties": {
    "addr:full":"51 Billet Lane Hornchurch Essex RM11 1AX",
    "addr:housenumber":"51",
    "addr:postcode":"rm11 1ax",
    "addr:street":"Billet Lane",
    "iso:country":"GB",
    "sg:address":"51 Billet Lane",
    "sg:city":"Hornchurch",
    "sg:classifiers":[
        {
            "category":"Arts & Performance",
            "subcategory":"Arts Center",
            "type":"Entertainment"
        },
        {
            "category":"Government",
            "subcategory":"Office",
            "type":"Public Place"
        },
        {
            "category":"Organizations",
            "subcategory":"Non-profit Organization",
            "type":"Services"
        }
    ],
    "sg:phone":"+44 1708 456308",
    "sg:postcode":"RM11 1AX",
    "sg:province":"Essex",
    "sg:tags":[
        "organisation",
        "charity",
        "local",
        "voluntary",
        "centre"
    ],
    "wof:name":"Fairkytes Art Centre",
    "wof:placetype":"venue"
},
  "geometry": {"coordinates":[0.2179760039,51.5639266968],"type":"Point"}
}