{
  "type": "Feature",
  "properties": {
    "addr:full":"Bookings, Abbey Hill Golf Centre, Monks Way Milton Keynes Buckinghamshire MK8 8AA",
    "addr:postcode":"mk8 8aa",
    "addr:street":"Monks Way",
    "iso:country":"GB",
    "sg:address":"Bookings, Abbey Hill Golf Centre, Monks Way",
    "sg:city":"Milton Keynes",
    "sg:classifiers":[
        {
            "category":"Government",
            "subcategory":"Office",
            "type":"Public Place"
        }
    ],
    "sg:phone":"+44 1908 563845",
    "sg:postcode":"MK8 8AA",
    "sg:province":"Buckinghamshire",
    "sg:tags":[
        "local"
    ],
    "wof:name":"Milton Keynes Council",
    "wof:placetype":"venue"
},
  "geometry": {"coordinates":[-0.8112099767,52.0435791016],"type":"Point"}
}