{
  "type": "Feature",
  "properties": {
    "addr:full":"Rufford Drive, Whitefield Manchester Lancashire M45 8PL",
    "addr:postcode":"m45 8pl",
    "addr:street":"Rufford Drive",
    "iso:country":"GB",
    "sg:address":"Rufford Drive, Whitefield",
    "sg:city":"Manchester",
    "sg:classifiers":[
        {
            "category":"Education",
            "subcategory":"School",
            "type":"Public Place"
        }
    ],
    "sg:phone":"+44 161 796 3392",
    "sg:postcode":"M45 8PL",
    "sg:province":"Lancashire",
    "sg:tags":[
        "local",
        "authority"
    ],
    "wof:name":"BURY METROPOLITAN BOROUGH COUNCIL",
    "wof:placetype":"venue"
},
  "geometry": {"coordinates":[-2.28919,53.556782],"type":"Point"}
}