{
  "type": "Feature",
  "properties": {
    "addr:full":"Frome Rd, Odd Down Bath Somerset BA2 2QF",
    "addr:postcode":"ba2 2qf",
    "addr:street":"Frome Rd;Down",
    "iso:country":"GB",
    "sg:address":"Frome Rd, Odd Down",
    "sg:city":"Bath",
    "sg:classifiers":[
        {
            "category":"Place Of Worship",
            "type":"Public Place"
        }
    ],
    "sg:phone":"+44 1225 832268",
    "sg:postcode":"BA2 2QF",
    "sg:province":"Somerset",
    "wof:name":"Rush Hill United Reformed Church",
    "wof:placetype":"venue"
},
  "geometry": {"coordinates":[-2.383552,51.361725],"type":"Point"}
}