{
  "type": "Feature",
  "properties": {
    "addr:full":"5 The Parade Carshalton Surrey SM5 3RL",
    "addr:housenumber":"5",
    "addr:postcode":"sm5 3rl",
    "addr:street":"The Parade",
    "iso:country":"GB",
    "sg:address":"5 The Parade",
    "sg:city":"Carshalton",
    "sg:classifiers":[
        {
            "category":"Real Estate",
            "subcategory":"Real Estate Agent",
            "type":"Services"
        }
    ],
    "sg:postcode":"SM5 3RL",
    "sg:province":"Surrey",
    "wof:name":"Slater Howard Holdings Ltd.",
    "wof:placetype":"venue"
},
  "geometry": {"coordinates":[-0.167364,51.362431],"type":"Point"}
}