{
  "type": "Feature",
  "properties": {
    "addr:full":"Earlscombe Farm, Bittaford Ivybridge Devon PL21 0LD",
    "addr:postcode":"pl21 0ld",
    "addr:street":"Bittaford",
    "iso:country":"GB",
    "sg:address":"Earlscombe Farm, Bittaford",
    "sg:city":"Ivybridge",
    "sg:classifiers":[
        {
            "category":"Farming",
            "subcategory":"Livestock Farm",
            "type":"Manufacturing & Wholesale Goods"
        }
    ],
    "sg:phone":"+44 1752 892331",
    "sg:postcode":"PL21 0LD",
    "sg:province":"Devon",
    "sg:tags":[
        "others"
    ],
    "wof:name":"H Lawson & Partners",
    "wof:placetype":"venue"
},
  "geometry": {"coordinates":[-3.8962869644,50.3772201538],"type":"Point"}
}