{
  "type": "Feature",
  "properties": {
    "addr:full":"69 Market Street, Pocklington York East Riding of Yorkshire YO42 2AE",
    "addr:housenumber":"69",
    "addr:postcode":"yo42 2ae",
    "addr:street":"Market Street",
    "iso:country":"GB",
    "sg:address":"69 Market Street, Pocklington",
    "sg:city":"York",
    "sg:classifiers":[
        {
            "category":"Professional",
            "subcategory":"Printing & Photocopies",
            "type":"Services"
        }
    ],
    "sg:phone":"+44 1759 302139",
    "sg:postcode":"YO42 2AE",
    "sg:province":"East Riding of Yorkshire",
    "sg:tags":[
        "printer"
    ],
    "wof:name":"A & Anita Beattie",
    "wof:placetype":"venue"
},
  "geometry": {"coordinates":[-0.7777119875,53.9314193726],"type":"Point"}
}