{
  "type": "Feature",
  "properties": {
    "addr:full":"Kingsbury House, 15-17 King Street London Greater London SW1Y 6QU",
    "addr:housenumber":"15-17",
    "addr:postcode":"sw1y 6qu",
    "addr:street":"King Street",
    "iso:country":"GB",
    "sg:address":"Kingsbury House, 15-17 King Street",
    "sg:city":"London",
    "sg:classifiers":[
        {
            "category":"Professional",
            "subcategory":"Management & Consulting",
            "type":"Services"
        }
    ],
    "sg:phone":"+44 20 7930 8786",
    "sg:postcode":"SW1Y 6QU",
    "sg:province":"Greater London",
    "sg:tags":[
        "consultant",
        "business"
    ],
    "wof:name":"David Sheppard & Partners Ltd.",
    "wof:placetype":"venue"
},
  "geometry": {"coordinates":[-0.138155,51.506332],"type":"Point"}
}