{
  "type": "Feature",
  "properties": {
    "addr:full":"30 City Of Three Waters, Whitwick Coalville Leicestershire LE67 5AH",
    "addr:housenumber":"30",
    "addr:postcode":"le67 5ah",
    "iso:country":"GB",
    "sg:address":"30 City Of Three Waters, Whitwick",
    "sg:city":"Coalville",
    "sg:classifiers":[
        {
            "category":"Organizations",
            "subcategory":"Non-profit Organization",
            "type":"Services"
        }
    ],
    "sg:phone":"+44 1530 837661",
    "sg:postcode":"LE67 5AH",
    "sg:province":"Leicestershire",
    "sg:tags":[
        "alarm",
        "system"
    ],
    "wof:name":"Omega Alarms",
    "wof:placetype":"venue"
},
  "geometry": {"coordinates":[-1.3549469709,52.7398529053],"type":"Point"}
}