{
  "type": "Feature",
  "properties": {
    "iso:country":"GB",
    "sg:address":"14-18 Station St",
    "sg:city":"Mansfield",
    "sg:classifiers":[
        {
            "category":"Health Services",
            "subcategory":"Dentist",
            "type":"Services"
        }
    ],
    "sg:phone":"+44 1623 650650",
    "sg:postcode":"NG19 8AB",
    "sg:province":"Derbyshire",
    "wof:name":"Susan Prentice",
    "wof:placetype":"venue"
},
  "geometry": {"coordinates":[-1.1964190006,53.1425704956],"type":"Point"}
}