{
  "type": "Feature",
  "properties": {
    "addr:full":"26a Snow Hill Wolverhampton West Midlands WV2 4AF",
    "addr:housenumber":"26a",
    "addr:postcode":"wv2 4af",
    "addr:street":"Snow",
    "iso:country":"GB",
    "sg:address":"26a Snow Hill",
    "sg:city":"Wolverhampton",
    "sg:classifiers":[
        {
            "category":"Shopping",
            "subcategory":"Stationery & Office Supplies",
            "type":"Retail Goods"
        }
    ],
    "sg:phone":"+44 1902 773521",
    "sg:postcode":"WV2 4AF",
    "sg:province":"West Midlands",
    "wof:name":"Whitehead Bros (Wolverhampton) Ltd.",
    "wof:placetype":"venue"
},
  "geometry": {"coordinates":[-2.125704,52.582081],"type":"Point"}
}