{
  "type": "Feature",
  "properties": {
    "addr:full":"96 Felixstowe Road Ipswich Suffolk IP3 8EG",
    "addr:housenumber":"96",
    "addr:postcode":"ip3 8eg",
    "addr:street":"Felixstowe Road",
    "iso:country":"GB",
    "sg:address":"96 Felixstowe Road",
    "sg:city":"Ipswich",
    "sg:classifiers":[
        {
            "category":"Autos & Motor Vehicles",
            "subcategory":"Automobile Sales",
            "type":"Retail Goods"
        }
    ],
    "sg:phone":"+44 1473 320321",
    "sg:postcode":"IP3 8EG",
    "sg:province":"Suffolk",
    "sg:tags":[
        "car"
    ],
    "wof:name":"Peter Brown Autosales",
    "wof:placetype":"venue"
},
  "geometry": {"coordinates":[1.177923,52.048744],"type":"Point"}
}