{
  "type": "Feature",
  "properties": {
    "addr:full":"Unit 36 Knutwood Trading Estate, Underhill Lane Sheffield South Yorkshire S6 1NL",
    "addr:housenumber":"unit 36;estate",
    "addr:postcode":"s6 1nl",
    "addr:street":"Trading;Underhill Lane",
    "iso:country":"GB",
    "sg:address":"Unit 36 Knutwood Trading Estate, Underhill Lane",
    "sg:city":"Sheffield",
    "sg:classifiers":[
        {
            "category":"Bus Charters",
            "type":"Transportation"
        }
    ],
    "sg:phone":"+44 114 232 0415",
    "sg:postcode":"S6 1NL",
    "sg:province":"South Yorkshire",
    "sg:tags":[
        "hire",
        "coach"
    ],
    "wof:name":"G Hobson & Son",
    "wof:placetype":"venue"
},
  "geometry": {"coordinates":[-1.51255,53.425919],"type":"Point"}
}