{
  "type": "Feature",
  "properties": {
    "iso:country":"GB",
    "sg:address":"Green Park Indust Est",
    "sg:city":"Port Talbot",
    "sg:classifiers":[
        {
            "category":"Utilities",
            "subcategory":"Refuse",
            "type":"Services"
        }
    ],
    "sg:phone":"+44 1792 653683",
    "sg:postcode":"SA12 6NT",
    "sg:province":"Neath Port Talbot",
    "sg:tags":[
        "skip",
        "hire"
    ],
    "wof:name":"Valley Waste Services",
    "wof:placetype":"venue"
},
  "geometry": {"coordinates":[-3.802369,51.591385],"type":"Point"}
}