{
  "type": "Feature",
  "properties": {
    "addr:full":"Unit 14 Angel Gate, 320 City Road London Greater London EC1V 2PT",
    "addr:housenumber":"unit 14;320",
    "addr:postcode":"ec1v 2pt",
    "addr:street":"Angel Gate;City Road",
    "iso:country":"GB",
    "sg:address":"Unit 14 Angel Gate, 320 City Road",
    "sg:city":"London",
    "sg:classifiers":[
        {
            "category":"Professional",
            "subcategory":"Computer Services",
            "type":"Services"
        }
    ],
    "sg:phone":"+44 20 7239 8400",
    "sg:postcode":"EC1V 2PT",
    "sg:province":"Greater London",
    "sg:tags":[
        "consultant"
    ],
    "wof:name":"Microgen Management Consultancy (Lim) Ltd.",
    "wof:placetype":"venue"
},
  "geometry": {"coordinates":[-0.1011,51.530579],"type":"Point"}
}