{
  "type": "Feature",
  "properties": {
    "iso:country":"GB",
    "sg:address":"Research House, Fraser Rd",
    "sg:city":"Greenford",
    "sg:classifiers":[
        {
            "category":"Taxi",
            "type":"Transportation"
        }
    ],
    "sg:phone":"+44 20 8998 5544",
    "sg:postcode":"UB6 7AQ",
    "sg:province":"Greater London",
    "sg:tags":[
        "mini",
        "cab"
    ],
    "wof:name":"Medway Cars",
    "wof:placetype":"venue"
},
  "geometry": {"coordinates":[-0.315119,51.539261],"type":"Point"}
}