{
  "type": "Feature",
  "properties": {
    "addr:full":"5 Gentwood Parade, Kings Way Liverpool Merseyside L36 2QB",
    "addr:housenumber":"5",
    "addr:postcode":"l36 2qb",
    "addr:street":"Gentwood Parade Kings Way",
    "iso:country":"GB",
    "sg:address":"5 Gentwood Parade, Kings Way",
    "sg:city":"Liverpool",
    "sg:classifiers":[
        {
            "category":"Shopping",
            "subcategory":"News",
            "type":"Retail Goods"
        }
    ],
    "sg:phone":"+44 151 289 2505",
    "sg:postcode":"L36 2QB",
    "sg:province":"Merseyside",
    "sg:tags":[
        "newsagent"
    ],
    "wof:name":"Cobbett's Newsagents",
    "wof:placetype":"venue"
},
  "geometry": {"coordinates":[-2.8517110348,53.4192619324],"type":"Point"}
}