{
  "type": "Feature",
  "properties": {
    "iso:country":"GB",
    "sg:address":"158 High Street, Harlington",
    "sg:city":"Hayes",
    "sg:classifiers":[
        {
            "category":"Bars & Pubs",
            "type":"Food & Drink"
        }
    ],
    "sg:phone":"+44 20 8759 9608",
    "sg:postcode":"UB3 5DP",
    "sg:province":"Greater London",
    "sg:tags":[
        "pubs",
        "inn"
    ],
    "wof:name":"White Hart",
    "wof:placetype":"venue"
},
  "geometry": {"coordinates":[-0.4354110062,51.4894065857],"type":"Point"}
}