{
  "type": "Feature",
  "properties": {
    "addr:full":"2 Atlas Court Coalville Leicestershire LE67 3FL",
    "addr:housenumber":"2",
    "addr:postcode":"le67 3fl",
    "addr:street":"Atlas Court",
    "iso:country":"GB",
    "sg:address":"2 Atlas Court",
    "sg:city":"Coalville",
    "sg:classifiers":[
        {
            "category":"Building & Trades",
            "subcategory":"Construction",
            "type":"Services"
        }
    ],
    "sg:phone":"+44 1530 831582",
    "sg:postcode":"LE67 3FL",
    "sg:province":"Leicestershire",
    "sg:tags":[
        "decorator",
        "painter"
    ],
    "wof:name":"J & S Seddon (Painting) Ltd.",
    "wof:placetype":"venue"
},
  "geometry": {"coordinates":[-1.3691040277,52.7295799255],"type":"Point"}
}