{
  "type": "Feature",
  "properties": {
    "addr:full":"Crawford Lodge, 98a Redcliffe Gardens London Greater London SW10 9HH",
    "addr:housenumber":"98a",
    "addr:postcode":"sw10 9hh",
    "addr:street":"Redcliffe Gardens",
    "iso:country":"GB",
    "sg:address":"Crawford Lodge, 98a Redcliffe Gardens",
    "sg:city":"London",
    "sg:classifiers":[
        {
            "category":"Professional",
            "subcategory":"Management & Consulting",
            "type":"Services"
        }
    ],
    "sg:phone":"+44 20 7373 2552",
    "sg:postcode":"SW10 9HH",
    "sg:province":"Greater London",
    "sg:tags":[
        "consultant",
        "business"
    ],
    "wof:name":"Beverley Lindsay Associates",
    "wof:placetype":"venue"
},
  "geometry": {"coordinates":[-0.18995,51.48885],"type":"Point"}
}