{
  "type": "Feature",
  "properties": {
    "iso:country":"GB",
    "sg:address":"Westons, Beedon",
    "sg:city":"Newbury",
    "sg:classifiers":[
        {
            "category":"Education",
            "subcategory":"School",
            "type":"Public Place"
        },
        {
            "category":"Government",
            "subcategory":"Office",
            "type":"Public Place"
        }
    ],
    "sg:phone":"+44 1635 248284",
    "sg:postcode":"RG20 8SL",
    "sg:province":"Berkshire",
    "sg:tags":[
        "local",
        "authority"
    ],
    "wof:name":"Beedon C Of E Primary School",
    "wof:placetype":"venue"
},
  "geometry": {"coordinates":[-1.296939,51.494499],"type":"Point"}
}