{
  "type": "Feature",
  "properties": {
    "iso:country":"GB",
    "sg:address":"13 Stanley Street",
    "sg:city":"Bourne",
    "sg:classifiers":[
        {
            "category":"Health Services",
            "subcategory":"Podiatrist",
            "type":"Services"
        }
    ],
    "sg:phone":"+44 1778 393098",
    "sg:postcode":"PE10 9BJ",
    "sg:province":"Lincolnshire",
    "sg:tags":[
        "podiatrists",
        "chiropodist"
    ],
    "wof:name":"S L ROFFE",
    "wof:placetype":"venue"
},
  "geometry": {"coordinates":[-0.377475,52.774773],"type":"Point"}
}