{
  "type": "Feature",
  "properties": {
    "iso:country":"GB",
    "sg:address":"Braxted Park, Great Braxted",
    "sg:city":"Witham",
    "sg:classifiers":[
        {
            "category":"Building & Trades",
            "subcategory":"Construction",
            "type":"Services"
        }
    ],
    "sg:postcode":"CM8 3XB",
    "sg:province":"Essex",
    "sg:tags":[
        "builder"
    ],
    "wof:name":"Foldcroft Ltd.",
    "wof:placetype":"venue"
},
  "geometry": {"coordinates":[0.668602,51.816315],"type":"Point"}
}