{
  "type": "Feature",
  "properties": {
    "addr:full":"Main Road, Inkberrow Worcester Worcestershire WR7 4HH",
    "addr:postcode":"wr7 4hh",
    "addr:street":"Main Road",
    "iso:country":"GB",
    "sg:address":"Main Road, Inkberrow",
    "sg:city":"Worcester",
    "sg:classifiers":[
        {
            "category":"Education",
            "subcategory":"School",
            "type":"Public Place"
        }
    ],
    "sg:postcode":"WR7 4HH",
    "sg:province":"Worcestershire",
    "sg:tags":[
        "local",
        "authority"
    ],
    "wof:name":"Inkberrow First School",
    "wof:placetype":"venue"
},
  "geometry": {"coordinates":[-1.9805569649,52.2132301331],"type":"Point"}
}