{
  "type": "Feature",
  "properties": {
    "addr:full":"Unit B3 Square Studio, 9 Hoxton Sq Islington Greater London N1 6NU",
    "addr:postcode":"n1 6nu",
    "addr:street":"Hoxton Sq",
    "iso:country":"GB",
    "sg:address":"Unit B3 Square Studio, 9 Hoxton Sq",
    "sg:city":"Islington",
    "sg:classifiers":[
        {
            "category":"Professional",
            "type":"Services"
        }
    ],
    "sg:phone":"+44 20 7739 0068",
    "sg:postcode":"N1 6NU",
    "sg:province":"Greater London",
    "sg:tags":[
        "interior",
        "furnishers",
        "designer"
    ],
    "wof:name":"Siobhan Marshall",
    "wof:placetype":"venue"
},
  "geometry": {"coordinates":[-0.0816999972,51.5274200439],"type":"Point"}
}