{
  "type": "Feature",
  "properties": {
    "iso:country":"GB",
    "sg:address":"Begelly",
    "sg:city":"Kilgetty",
    "sg:classifiers":[
        {
            "category":"Farming",
            "subcategory":"Dairy Farm",
            "type":"Manufacturing & Wholesale Goods"
        }
    ],
    "sg:postcode":"SA68 0XN",
    "sg:province":"Pembrokeshire",
    "wof:name":"Hackett Farm",
    "wof:placetype":"venue"
},
  "geometry": {"coordinates":[-4.767879,51.732658],"type":"Point"}
}