{
  "type": "Feature",
  "properties": {
    "addr:full":"13 Bdwy Newcastle-upon-tyne Northumberland NE20 9PW",
    "addr:housenumber":"13;newcastle-upon-tyne",
    "addr:postcode":"ne20 9pw",
    "addr:street":"Bdwy",
    "iso:country":"GB",
    "sg:address":"13 Bdwy",
    "sg:city":"Newcastle-upon-tyne",
    "sg:classifiers":[
        {
            "category":"Deli",
            "type":"Food & Drink"
        }
    ],
    "sg:phone":"+44 1661 860206",
    "sg:postcode":"NE20 9PW",
    "sg:province":"Northumberland",
    "sg:tags":[
        "delicatessen"
    ],
    "wof:name":"The Darras Larder",
    "wof:placetype":"venue"
},
  "geometry": {"coordinates":[-1.7644840479,55.0362472534],"type":"Point"}
}