{
  "type": "Feature",
  "properties": {
    "iso:country":"GB",
    "sg:address":"Shelf Farm, Luppitt",
    "sg:city":"Honiton",
    "sg:classifiers":[
        {
            "category":"Farming",
            "subcategory":"Livestock Farm",
            "type":"Manufacturing & Wholesale Goods"
        }
    ],
    "sg:phone":"+44 1404 891616",
    "sg:postcode":"EX14 4SL",
    "sg:province":"Devon",
    "sg:tags":[
        "others"
    ],
    "wof:name":"T J Wilson & Partners",
    "wof:placetype":"venue"
},
  "geometry": {"coordinates":[-3.181701,50.853161],"type":"Point"}
}