{
  "type": "Feature",
  "properties": {
    "iso:country":"GB",
    "sg:address":"138 Park Lane",
    "sg:city":"Hornchurch",
    "sg:classifiers":[
        {
            "category":"Freight",
            "type":"Transportation"
        }
    ],
    "sg:postcode":"RM11 1BE",
    "sg:province":"Essex",
    "sg:tags":[
        "haulage",
        "road"
    ],
    "wof:name":"Maudwall Transport Ltd",
    "wof:placetype":"venue"
},
  "geometry": {"coordinates":[0.19308,51.568729],"type":"Point"}
}