{
  "type": "Feature",
  "properties": {
    "addr:full":"90 Whiteladies Road, Clifton Bristol City of Bristol BS8 2QN",
    "addr:housenumber":"90",
    "addr:postcode":"bs8 2qn",
    "addr:street":"Whiteladies Road",
    "iso:country":"GB",
    "sg:address":"90 Whiteladies Road, Clifton",
    "sg:city":"Bristol",
    "sg:classifiers":[
        {
            "category":"Professional",
            "subcategory":"Printing & Photocopies",
            "type":"Services"
        }
    ],
    "sg:phone":"+44 117 923 8010",
    "sg:postcode":"BS8 2QN",
    "sg:province":"City of Bristol",
    "sg:tags":[
        "printer"
    ],
    "wof:name":"Kall Kwik Printing",
    "wof:placetype":"venue"
},
  "geometry": {"coordinates":[-2.6118249893,51.4665565491],"type":"Point"}
}