{
  "type": "Feature",
  "properties": {
    "addr:full":"76 Northumberland Street Edinburgh City of Edinburgh EH3 6JG",
    "addr:housenumber":"76",
    "addr:postcode":"eh3 6jg",
    "addr:street":"Northumberland Street",
    "iso:country":"GB",
    "sg:address":"76 Northumberland Street",
    "sg:city":"Edinburgh",
    "sg:classifiers":[
        {
            "category":"Professional",
            "subcategory":"Engineering",
            "type":"Services"
        },
        {
            "category":"Building & Trades",
            "subcategory":"Electrical",
            "type":"Services"
        }
    ],
    "sg:phone":"+44 131 557 0779",
    "sg:postcode":"EH3 6JG",
    "sg:province":"City of Edinburgh",
    "sg:tags":[
        "engineer",
        "electrician",
        "contractor"
    ],
    "wof:name":"S. FINLAYSON & SON LTD",
    "wof:placetype":"venue"
},
  "geometry": {"coordinates":[-3.202163,55.956284],"type":"Point"}
}