{
  "type": "Feature",
  "properties": {
    "addr:full":"Unit 2, 180 Park Avenue London Greater London NW10 7XH",
    "addr:housenumber":"unit 2 180",
    "addr:postcode":"nw10 7xh",
    "addr:street":"Park Avenue",
    "iso:country":"GB",
    "sg:address":"Unit 2, 180 Park Avenue",
    "sg:city":"London",
    "sg:classifiers":[
        {
            "category":"Recreation",
            "subcategory":"Amusement Park",
            "type":"Entertainment"
        },
        {
            "category":"Autos & Motor Vehicles",
            "subcategory":"Recreational Vehicle Sales",
            "type":"Retail Goods"
        }
    ],
    "sg:phone":"+44 20 8965 1216",
    "sg:postcode":"NW10 7XH",
    "sg:province":"Greater London",
    "sg:tags":[
        "machine",
        "gaming",
        "arcade"
    ],
    "wof:name":"Funomatics Ltd",
    "wof:placetype":"venue"
},
  "geometry": {"coordinates":[-0.2914359868,51.5340881348],"type":"Point"}
}