{
  "type": "Feature",
  "properties": {
    "iso:country":"GB",
    "sg:address":"Bird Brook",
    "sg:city":"Halstead",
    "sg:classifiers":[
        {
            "category":"Home & Garden",
            "subcategory":"Garden Supply",
            "type":"Retail Goods"
        }
    ],
    "sg:postcode":"CO9 4BQ",
    "sg:province":"Essex",
    "sg:tags":[
        "nursery",
        "centre"
    ],
    "wof:name":"Robert Bolton & Son",
    "wof:placetype":"venue"
},
  "geometry": {"coordinates":[0.476892,52.024452],"type":"Point"}
}