{
  "type": "Feature",
  "properties": {
    "iso:country":"GB",
    "sg:address":"Lombard House, 206 Rookery Lane",
    "sg:city":"Birmingham",
    "sg:classifiers":[
        {
            "category":"Professional",
            "subcategory":"Accounting & Tax Preparation",
            "type":"Services"
        },
        {
            "category":"Banks & Credit Unions",
            "subcategory":"Financial Services",
            "type":"Services"
        }
    ],
    "sg:postcode":"B21 9PY",
    "sg:province":"West Midlands",
    "sg:tags":[
        "adviser",
        "accountant"
    ],
    "wof:name":"J P R Accountants",
    "wof:placetype":"venue"
},
  "geometry": {"coordinates":[-1.939028,52.511761],"type":"Point"}
}