{
  "type": "Feature",
  "properties": {
    "addr:full":"182 Prendergast Haverfordwest Pembrokeshire SA61 2PQ",
    "addr:housenumber":"182",
    "addr:postcode":"sa61 2pq",
    "addr:street":"Prendergast",
    "iso:country":"GB",
    "sg:address":"182 Prendergast",
    "sg:city":"Haverfordwest",
    "sg:classifiers":[
        {
            "category":"Shopping",
            "subcategory":"Florist",
            "type":"Retail Goods"
        }
    ],
    "sg:phone":"+44 1437 767644",
    "sg:postcode":"SA61 2PQ",
    "sg:province":"Pembrokeshire",
    "wof:name":"Brenda's Florist",
    "wof:placetype":"venue"
},
  "geometry": {"coordinates":[-4.964046,51.809052],"type":"Point"}
}