{
  "type": "Feature",
  "properties": {
    "iso:country":"GB",
    "sg:address":"Lingdale Rd",
    "sg:city":"Birkenhead",
    "sg:classifiers":[
        {
            "category":"Retail",
            "subcategory":"Auto Repair",
            "type":"Services"
        }
    ],
    "sg:phone":"+44 151 652 2453",
    "sg:postcode":"L43 8TE",
    "sg:province":"Merseyside",
    "sg:tags":[
        "modification",
        "garage"
    ],
    "wof:name":"Bidston Motor Co",
    "wof:placetype":"venue"
},
  "geometry": {"coordinates":[-3.057504,53.394466],"type":"Point"}
}