{
  "type": "Feature",
  "properties": {
    "addr:full":"256 High Rd Leyton Leyton Greater London E10 5PW",
    "addr:housenumber":"256",
    "addr:postcode":"e10 5pw",
    "addr:street":"High Rd",
    "iso:country":"GB",
    "sg:address":"256 High Rd Leyton",
    "sg:city":"Leyton",
    "sg:classifiers":[
        {
            "category":"Shopping",
            "subcategory":"Music",
            "type":"Retail Goods"
        }
    ],
    "sg:phone":"+44 20 8558 7580",
    "sg:postcode":"E10 5PW",
    "sg:province":"Greater London",
    "sg:tags":[
        "record",
        "tape",
        "cd"
    ],
    "wof:name":"Symphonies",
    "wof:placetype":"venue"
},
  "geometry": {"coordinates":[-0.0078180004,51.5594406128],"type":"Point"}
}