{
  "type": "Feature",
  "properties": {
    "iso:country":"GB",
    "sg:address":"Ryehill Health Centre, St Peter Street",
    "sg:city":"Dundee",
    "sg:classifiers":[
        {
            "category":"Health Services",
            "subcategory":"Clinic",
            "type":"Services"
        }
    ],
    "sg:phone":"+44 1382 646564",
    "sg:postcode":"DD1 4JH",
    "sg:province":"Dundee City",
    "sg:tags":[
        "planning",
        "family",
        "centre"
    ],
    "wof:name":"Family Planning Well Woman Clinic",
    "wof:placetype":"venue"
},
  "geometry": {"coordinates":[-2.9676089287,56.4613761902],"type":"Point"}
}