{
  "type": "Feature",
  "properties": {
    "iso:country":"GB",
    "sg:address":"32 Park Road",
    "sg:city":"Kingston-upon-thames",
    "sg:classifiers":[
        {
            "category":"Food & Beverages",
            "subcategory":"Liquor & Beverages",
            "type":"Retail Goods"
        }
    ],
    "sg:phone":"+44 20 8546 9880",
    "sg:postcode":"KT2 6BE",
    "sg:province":"Greater London",
    "sg:tags":[
        "beer",
        "wine",
        "spirit",
        "wines"
    ],
    "wof:name":"Euro Wines",
    "wof:placetype":"venue"
},
  "geometry": {"coordinates":[-0.288335,51.416351],"type":"Point"}
}