{
  "type": "Feature",
  "properties": {
    "addr:full":"6 West Avenue South Shields Tyne and Wear NE34 6QU",
    "addr:housenumber":"6",
    "addr:postcode":"ne34 6qu",
    "addr:street":"West Avenue",
    "iso:country":"GB",
    "sg:address":"6 West Avenue",
    "sg:city":"South Shields",
    "sg:classifiers":[
        {
            "category":"Organizations",
            "subcategory":"Community Association",
            "type":"Services"
        },
        {
            "category":"Organizations",
            "subcategory":"Membership Organization",
            "type":"Services"
        }
    ],
    "sg:phone":"+44 191 455 2612",
    "sg:postcode":"NE34 6QU",
    "sg:province":"Tyne and Wear",
    "sg:tags":[
        "club",
        "social"
    ],
    "wof:name":"Westside Club",
    "wof:placetype":"venue"
},
  "geometry": {"coordinates":[-1.414241,54.972057],"type":"Point"}
}