{
  "type": "Feature",
  "properties": {
    "addr:full":"127a Bispham Rd Southport Lancashire PR9 7BJ",
    "addr:housenumber":"127a",
    "addr:postcode":"pr9 7bj",
    "addr:street":"Bispham Rd",
    "iso:country":"GB",
    "sg:address":"127a Bispham Rd",
    "sg:city":"Southport",
    "sg:classifiers":[
        {
            "category":"Retail",
            "subcategory":"Auto Repair",
            "type":"Services"
        }
    ],
    "sg:phone":"+44 1704 228662",
    "sg:postcode":"PR9 7BJ",
    "sg:province":"Lancashire",
    "sg:tags":[
        "modification",
        "garage"
    ],
    "wof:name":"Bispham Motors",
    "wof:placetype":"venue"
},
  "geometry": {"coordinates":[-2.9706730843,53.6478652954],"type":"Point"}
}