{
  "type": "Feature",
  "properties": {
    "addr:full":"Sentinal House, Nuffield Road Poole Dorset BH17 0RE",
    "addr:postcode":"bh17 0re",
    "addr:street":"Nuffield Road",
    "iso:country":"GB",
    "sg:address":"Sentinal House, Nuffield Road",
    "sg:city":"Poole",
    "sg:classifiers":[
        {
            "category":"Professional",
            "subcategory":"Detective & Security Services",
            "type":"Services"
        }
    ],
    "sg:phone":"+44 1202 666222",
    "sg:postcode":"BH17 0RE",
    "sg:province":"Dorset",
    "sg:tags":[
        "equipment"
    ],
    "wof:name":"T D S I Revenue Systems Ltd.",
    "wof:placetype":"venue"
},
  "geometry": {"coordinates":[-1.9751340151,50.7442436218],"type":"Point"}
}