{
  "type": "Feature",
  "properties": {
    "addr:full":"Commonwealth House, Northumberland Avenue London Greater London WC2N 5BW",
    "addr:postcode":"wc2n 5bw",
    "addr:street":"Northumberland Avenue",
    "iso:country":"GB",
    "sg:address":"Commonwealth House, Northumberland Avenue",
    "sg:city":"London",
    "sg:classifiers":[
        {
            "category":"Retail",
            "subcategory":"Event Space",
            "type":"Services"
        },
        {
            "category":"Professional",
            "subcategory":"Business Services",
            "type":"Services"
        }
    ],
    "sg:phone":"+44 20 7706 7390",
    "sg:postcode":"WC2N 5BW",
    "sg:province":"Greater London",
    "sg:tags":[
        "hospitality",
        "corporate",
        "exhibition",
        "organiser"
    ],
    "wof:name":"Twenty First Century V I P",
    "wof:placetype":"venue"
},
  "geometry": {"coordinates":[-0.12616,51.507469],"type":"Point"}
}