{
  "type": "Feature",
  "properties": {
    "iso:country":"GB",
    "sg:address":"Trelowen, St Cleer",
    "sg:city":"Liskeard",
    "sg:classifiers":[
        {
            "category":"Health Services",
            "subcategory":"Chiropractor",
            "type":"Services"
        }
    ],
    "sg:phone":"+44 1579 346980",
    "sg:postcode":"PL14 5DF",
    "sg:province":"Cornwall",
    "wof:name":"Caradon Chiropractic Clinic",
    "wof:placetype":"venue"
},
  "geometry": {"coordinates":[-4.465834,50.453796],"type":"Point"}
}