{
  "type": "Feature",
  "properties": {
    "iso:country":"GB",
    "sg:address":"3 Hall La, Ullesthorpe",
    "sg:city":"Lutterworth",
    "sg:classifiers":[
        {
            "category":"Home & Garden",
            "subcategory":"Hardware",
            "type":"Retail Goods"
        }
    ],
    "sg:phone":"+44 1455 209634",
    "sg:postcode":"LE17 5DD",
    "sg:province":"Leicestershire",
    "sg:tags":[
        "fixing",
        "nuts",
        "bolt"
    ],
    "wof:name":"Rugby Fasteners Ltd",
    "wof:placetype":"venue"
},
  "geometry": {"coordinates":[-1.257339,52.486897],"type":"Point"}
}