{
  "type": "Feature",
  "properties": {
    "addr:full":"Unit 6 Crayside Industrial Estate, Thames Road, Crayford Dartford Kent DA1 4RF",
    "addr:housenumber":"unit 6",
    "addr:postcode":"da1 4rf",
    "addr:street":"Crayside Industrial Estate Thames Road",
    "iso:country":"GB",
    "sg:address":"Unit 6 Crayside Industrial Estate, Thames Road, Crayford",
    "sg:city":"Dartford",
    "sg:classifiers":[
        {
            "category":"Shopping",
            "subcategory":"Stationery & Office Supplies",
            "type":"Retail Goods"
        }
    ],
    "sg:phone":"+44 1322 521545",
    "sg:postcode":"DA1 4RF",
    "sg:province":"Kent",
    "sg:tags":[
        "equipment"
    ],
    "wof:name":"Dartex Office Furniture  Limited",
    "wof:placetype":"venue"
},
  "geometry": {"coordinates":[0.177534,51.452374],"type":"Point"}
}