{
  "type": "Feature",
  "properties": {
    "addr:full":"Brigade House, Brigade Street London Greater London SE3 0TW",
    "addr:postcode":"se3 0tw",
    "addr:street":"Brigade Street",
    "iso:country":"GB",
    "sg:address":"Brigade House, Brigade Street",
    "sg:city":"London",
    "sg:classifiers":[
        {
            "category":"Professional",
            "subcategory":"Art Services",
            "type":"Services"
        }
    ],
    "sg:phone":"+44 20 8318 4707",
    "sg:postcode":"SE3 0TW",
    "sg:province":"Greater London",
    "sg:tags":[
        "graphic",
        "designer"
    ],
    "wof:name":"O'Reilly Richardson",
    "wof:placetype":"venue"
},
  "geometry": {"coordinates":[0.00782,51.466942],"type":"Point"}
}