{
  "type": "Feature",
  "properties": {
    "addr:full":"454-456 London Road, North Cheam Sutton Surrey SM3 8JB",
    "addr:housenumber":"454-456",
    "addr:postcode":"sm3 8jb",
    "addr:street":"London Road",
    "iso:country":"GB",
    "sg:address":"454-456 London Road, North Cheam",
    "sg:city":"Sutton",
    "sg:classifiers":[
        {
            "category":"Autos & Motor Vehicles",
            "subcategory":"Automobile Sales",
            "type":"Retail Goods"
        }
    ],
    "sg:phone":"+44 20 8644 0034",
    "sg:postcode":"SM3 8JB",
    "sg:province":"Surrey",
    "sg:tags":[
        "car"
    ],
    "wof:name":"Motozoom Ltd.",
    "wof:placetype":"venue"
},
  "geometry": {"coordinates":[-0.2287089974,51.3701934814],"type":"Point"}
}