{
  "type": "Feature",
  "properties": {
    "iso:country":"GB",
    "sg:address":"103 Crediton Road",
    "sg:city":"Okehampton",
    "sg:classifiers":[
        {
            "category":"Building & Trades",
            "subcategory":"Construction",
            "type":"Services"
        }
    ],
    "sg:phone":"+44 1837 52473",
    "sg:postcode":"EX20 1NU",
    "sg:province":"Devon",
    "sg:tags":[
        "builder"
    ],
    "wof:name":"E G Hawkins & Son",
    "wof:placetype":"venue"
},
  "geometry": {"coordinates":[-3.994057,50.742722],"type":"Point"}
}