{
  "type": "Feature",
  "properties": {
    "iso:country":"GB",
    "sg:address":"Room 153 Newport Crown Court, Faulkner Road",
    "sg:city":"Newport",
    "sg:classifiers":[
        {
            "category":"Organizations",
            "subcategory":"Non-profit Organization",
            "type":"Services"
        }
    ],
    "sg:phone":"+44 1633 222826",
    "sg:postcode":"NP20 4PR",
    "sg:province":"Newport",
    "sg:tags":[
        "organisation",
        "voluntary",
        "charity"
    ],
    "wof:name":"Gwent Witness Service",
    "wof:placetype":"venue"
},
  "geometry": {"coordinates":[-3.0039908886,51.5879936218],"type":"Point"}
}