{
  "type": "Feature",
  "properties": {
    "iso:country":"GB",
    "sg:address":"Unit 4 Crossley Pk, Crossley Rd",
    "sg:city":"Manchester",
    "sg:classifiers":[
        {
            "category":"Shopping",
            "subcategory":"Clothing, Apparel, & Fashions",
            "type":"Retail Goods"
        }
    ],
    "sg:phone":"+44 161 442 7224",
    "sg:postcode":"M19 2SH",
    "sg:province":"Greater Manchester",
    "sg:tags":[
        "clothing"
    ],
    "wof:name":"A M A C (U K) Ltd",
    "wof:placetype":"venue"
},
  "geometry": {"coordinates":[-2.199339,53.436199],"type":"Point"}
}