{
  "type": "Feature",
  "properties": {
    "iso:country":"GB",
    "sg:address":"Main Street, Endmoor",
    "sg:city":"Kendal",
    "sg:classifiers":[
        {
            "category":"Food & Beverages",
            "subcategory":"Bakery",
            "type":"Retail Goods"
        }
    ],
    "sg:phone":"+44 15395 67559",
    "sg:postcode":"LA8 0EU",
    "sg:province":"Cumbria",
    "sg:tags":[
        "baker"
    ],
    "wof:name":"Naughty But Nice",
    "wof:placetype":"venue"
},
  "geometry": {"coordinates":[-2.708397,54.257046],"type":"Point"}
}