{
  "type": "Feature",
  "properties": {
    "iso:country":"GB",
    "sg:address":"46 Cornbrook Road",
    "sg:city":"Macclesfield",
    "sg:classifiers":[
        {
            "category":"Building & Trades",
            "subcategory":"Landscaping Services",
            "type":"Services"
        }
    ],
    "sg:phone":"+44 1625 619187",
    "sg:postcode":"SK11 7TJ",
    "sg:province":"Cheshire",
    "sg:tags":[
        "landscape",
        "contractor"
    ],
    "wof:name":"Sitre Maintenance Services",
    "wof:placetype":"venue"
},
  "geometry": {"coordinates":[-2.131377,53.243256],"type":"Point"}
}