{
  "type": "Feature",
  "properties": {
    "addr:full":"23 Stanway Road West Bromwich West Midlands B71 1RW",
    "addr:housenumber":"23",
    "addr:postcode":"b71 1rw",
    "addr:street":"Stanway Road",
    "iso:country":"GB",
    "sg:address":"23 Stanway Road",
    "sg:city":"West Bromwich",
    "sg:classifiers":[
        {
            "category":"Building & Trades",
            "subcategory":"Plumbing",
            "type":"Services"
        }
    ],
    "sg:phone":"+44 121 532 4086",
    "sg:postcode":"B71 1RW",
    "sg:province":"West Midlands",
    "sg:tags":[
        "central",
        "installation",
        "system",
        "servicing",
        "heating"
    ],
    "wof:name":"Radway Heating & Plumbing Of West Bromwich",
    "wof:placetype":"venue"
},
  "geometry": {"coordinates":[-1.9897969961,52.5330963135],"type":"Point"}
}