{
  "type": "Feature",
  "properties": {
    "iso:country":"GB",
    "sg:address":"Ringwood Road, West Howe",
    "sg:city":"Bournemouth",
    "sg:classifiers":[
        {
            "category":"Building & Trades",
            "subcategory":"Construction",
            "type":"Services"
        }
    ],
    "sg:phone":"+44 1202 571111",
    "sg:postcode":"BH11 9LH",
    "sg:province":"Dorset",
    "sg:tags":[
        "paint",
        "household",
        "spraying"
    ],
    "wof:name":"I T W Ltd.",
    "wof:placetype":"venue"
},
  "geometry": {"coordinates":[-1.910168,50.774677],"type":"Point"}
}