{
  "type": "Feature",
  "properties": {
    "addr:full":"Charlesfield Industrial Estate, St Boswells Melrose Scottish Borders TD6 0HH",
    "addr:postcode":"td6 0hh",
    "addr:street":"Charlesfield Industrial Estate St",
    "iso:country":"GB",
    "sg:address":"Charlesfield Industrial Estate, St Boswells",
    "sg:city":"Melrose",
    "sg:classifiers":[
        {
            "category":"Wholesale",
            "subcategory":"Machinery & Supplies",
            "type":"Manufacturing & Wholesale Goods"
        }
    ],
    "sg:phone":"+44 1835 823240",
    "sg:postcode":"TD6 0HH",
    "sg:province":"Scottish Borders",
    "wof:name":"G Marshall Tractors",
    "wof:placetype":"venue"
},
  "geometry": {"coordinates":[-2.6619598866,55.5573387146],"type":"Point"}
}