{
  "type": "Feature",
  "properties": {
    "addr:full":"Stanley House, 8 St Chad's Place London Greater London WC1X 9HH",
    "addr:housenumber":"8",
    "addr:postcode":"wc1x 9hh",
    "addr:street":"St Chad'S Place",
    "iso:country":"GB",
    "sg:address":"Stanley House, 8 St Chad's Place",
    "sg:city":"London",
    "sg:classifiers":[
        {
            "category":"Organizations",
            "subcategory":"Non-profit Organization",
            "type":"Services"
        }
    ],
    "sg:phone":"+44 20 7833 5360",
    "sg:postcode":"WC1X 9HH",
    "sg:province":"Greater London",
    "sg:tags":[
        "organisation",
        "voluntary",
        "charity"
    ],
    "wof:name":"National Playing Fields Association",
    "wof:placetype":"venue"
},
  "geometry": {"coordinates":[-0.11979,51.530499],"type":"Point"}
}