{
  "type": "Feature",
  "properties": {
    "iso:country":"GB",
    "sg:address":"Ten Oaks, Rendham",
    "sg:city":"Saxmundham",
    "sg:classifiers":[
        {
            "category":"Banks & Credit Unions",
            "subcategory":"Financial Services",
            "type":"Services"
        }
    ],
    "sg:phone":"+44 1728 663215",
    "sg:postcode":"IP17 2AD",
    "sg:province":"Suffolk",
    "sg:tags":[
        "consultant"
    ],
    "wof:name":"I N G Farm Finance Ltd",
    "wof:placetype":"venue"
},
  "geometry": {"coordinates":[1.439956,52.22876],"type":"Point"}
}