{
  "type": "Feature",
  "properties": {
    "addr:full":"Unit 22, Furnace Industrial Estate Shildon Durham DL4 1QB",
    "addr:housenumber":"unit 22",
    "addr:postcode":"dl4 1qb",
    "addr:street":"Furnace Industrial Estate",
    "iso:country":"GB",
    "sg:address":"Unit 22, Furnace Industrial Estate",
    "sg:city":"Shildon",
    "sg:classifiers":[
        {
            "category":"Retail",
            "subcategory":"Repair Shop",
            "type":"Services"
        }
    ],
    "sg:phone":"+44 1388 772628",
    "sg:postcode":"DL4 1QB",
    "sg:province":"Durham",
    "sg:tags":[
        "upholsterer"
    ],
    "wof:name":"Hall's Upholstery",
    "wof:placetype":"venue"
},
  "geometry": {"coordinates":[-1.651709,54.628571],"type":"Point"}
}