{
  "type": "Feature",
  "properties": {
    "addr:full":"108 Polwarth Terrace Edinburgh City of Edinburgh EH11 1NN",
    "addr:housenumber":"108",
    "addr:postcode":"eh11 1nn",
    "addr:street":"Polwarth Terrace",
    "iso:country":"GB",
    "sg:address":"108 Polwarth Terrace",
    "sg:city":"Edinburgh",
    "sg:classifiers":[
        {
            "category":"Travel",
            "subcategory":"Hotels & Motels",
            "type":"Entertainment"
        }
    ],
    "sg:phone":"+44 131 337 1580",
    "sg:postcode":"EH11 1NN",
    "sg:province":"City of Edinburgh",
    "sg:tags":[
        "house",
        "guest"
    ],
    "wof:name":"Lindsay Guest House",
    "wof:placetype":"venue"
},
  "geometry": {"coordinates":[-3.227226,55.929893],"type":"Point"}
}