{
  "type": "Feature",
  "properties": {
    "addr:full":"264 West Ferry Road London Greater London E14 3AG",
    "addr:housenumber":"264",
    "addr:postcode":"e14 3ag",
    "addr:street":"West Ferry Road",
    "iso:country":"GB",
    "sg:address":"264 West Ferry Road",
    "sg:city":"London",
    "sg:classifiers":[
        {
            "category":"Real Estate",
            "subcategory":"Real Estate Agent",
            "type":"Services"
        }
    ],
    "sg:phone":"+44 20 7515 0800",
    "sg:postcode":"E14 3AG",
    "sg:province":"Greater London",
    "wof:name":"Dockside Property Services",
    "wof:placetype":"venue"
},
  "geometry": {"coordinates":[-0.0180690009,51.4878845215],"type":"Point"}
}