{
  "type": "Feature",
  "properties": {
    "addr:full":"Padbrook, Paramour Street, Ash Canterbury Kent CT3 2EB",
    "addr:postcode":"ct3 2eb",
    "addr:street":"Paramour Street",
    "iso:country":"GB",
    "sg:address":"Padbrook, Paramour Street, Ash",
    "sg:city":"Canterbury",
    "sg:classifiers":[
        {
            "category":"Professional",
            "subcategory":"Detective & Security Services",
            "type":"Services"
        }
    ],
    "sg:phone":"+44 1304 813813",
    "sg:postcode":"CT3 2EB",
    "sg:province":"Kent",
    "sg:tags":[
        "agency"
    ],
    "wof:name":"Finney Loveless Ltd.",
    "wof:placetype":"venue"
},
  "geometry": {"coordinates":[1.2819199562,51.3028297424],"type":"Point"}
}