{
  "type": "Feature",
  "properties": {
    "addr:full":"114 Exeter Road, Kingsteignton Newton Abbot Devon TQ12 3LY",
    "addr:housenumber":"114",
    "addr:postcode":"tq12 3ly",
    "addr:street":"Exeter Road",
    "iso:country":"GB",
    "sg:address":"114 Exeter Road, Kingsteignton",
    "sg:city":"Newton Abbot",
    "sg:classifiers":[
        {
            "category":"Building & Trades",
            "subcategory":"Plumbing",
            "type":"Services"
        }
    ],
    "sg:postcode":"TQ12 3LY",
    "sg:province":"Devon",
    "sg:tags":[
        "heating"
    ],
    "wof:name":"B J Edwards",
    "wof:placetype":"venue"
},
  "geometry": {"coordinates":[-3.5972979069,50.5548744202],"type":"Point"}
}