{
  "type": "Feature",
  "properties": {
    "addr:full":"Kilpatrick House, 3 Bridge Street Alexandria Argyll and Bute G83 0TA",
    "addr:housenumber":"3",
    "addr:postcode":"g83 0ta",
    "addr:street":"Bridge Street",
    "iso:country":"GB",
    "sg:address":"Kilpatrick House, 3 Bridge Street",
    "sg:city":"Alexandria",
    "sg:classifiers":[
        {
            "category":"Health Services",
            "subcategory":"Nursing And Care Facility",
            "type":"Services"
        }
    ],
    "sg:phone":"+44 1389 752085",
    "sg:postcode":"G83 0TA",
    "sg:province":"Argyll and Bute",
    "sg:tags":[
        "home"
    ],
    "wof:name":"Threshold Leven",
    "wof:placetype":"venue"
},
  "geometry": {"coordinates":[-4.575467,55.984943],"type":"Point"}
}