{
  "type": "Feature",
  "properties": {
    "addr:full":"10 Mead Industrial Park, Riverway Harlow Essex CM20 2SE",
    "addr:housenumber":"10",
    "addr:postcode":"cm20 2se",
    "addr:street":"Mead Industrial Park Riverway",
    "iso:country":"GB",
    "sg:address":"10 Mead Industrial Park, Riverway",
    "sg:city":"Harlow",
    "sg:classifiers":[
        {
            "category":"Manufacturing",
            "subcategory":"Metals",
            "type":"Manufacturing & Wholesale Goods"
        },
        {
            "category":"Wholesale",
            "subcategory":"Scrap",
            "type":"Manufacturing & Wholesale Goods"
        }
    ],
    "sg:phone":"+44 1279 423743",
    "sg:postcode":"CM20 2SE",
    "sg:province":"Essex",
    "sg:tags":[
        "precious",
        "waste",
        "recovery"
    ],
    "wof:name":"A W A Refiners Ltd.",
    "wof:placetype":"venue"
},
  "geometry": {"coordinates":[0.097506,51.773151],"type":"Point"}
}