{
  "type": "Feature",
  "properties": {
    "iso:country":"GB",
    "sg:address":"The Flat, Paradise Garage, Toft Road",
    "sg:city":"Knutsford",
    "sg:classifiers":[
        {
            "category":"Professional",
            "type":"Services"
        }
    ],
    "sg:postcode":"WA16 9ED",
    "sg:province":"Cheshire",
    "sg:tags":[
        "interior",
        "furnishers",
        "designer"
    ],
    "wof:name":"Verjilly Originals",
    "wof:placetype":"venue"
},
  "geometry": {"coordinates":[-2.376240015,53.3042030334],"type":"Point"}
}