{
  "type": "Feature",
  "properties": {
    "addr:full":"196 Cambridge Road Hitchin Hertfordshire SG4 0JW",
    "addr:housenumber":"196",
    "addr:postcode":"sg4 0jw",
    "addr:street":"Cambridge Road",
    "iso:country":"GB",
    "sg:address":"196 Cambridge Road",
    "sg:city":"Hitchin",
    "sg:classifiers":[
        {
            "category":"Home & Garden",
            "subcategory":"Hardware",
            "type":"Retail Goods"
        }
    ],
    "sg:postcode":"SG4 0JW",
    "sg:province":"Hertfordshire",
    "sg:tags":[
        "equipment",
        "welding"
    ],
    "wof:name":"Jetweld (U K) Ltd.",
    "wof:placetype":"venue"
},
  "geometry": {"coordinates":[-0.2518619895,51.9586257935],"type":"Point"}
}