{
  "type": "Feature",
  "properties": {
    "iso:country":"GB",
    "sg:address":"The Courtyard, Greenhill Farm, Hathern",
    "sg:city":"Loughborough",
    "sg:classifiers":[
        {
            "category":"Banks & Credit Unions",
            "subcategory":"Financial Services",
            "type":"Services"
        }
    ],
    "sg:phone":"+44 1509 646995",
    "sg:postcode":"LE12 5LF",
    "sg:province":"Leicestershire",
    "sg:tags":[
        "adviser"
    ],
    "wof:name":"H C James & Associates Ltd.",
    "wof:placetype":"venue"
},
  "geometry": {"coordinates":[-1.25617,52.792515],"type":"Point"}
}