{
  "type": "Feature",
  "properties": {
    "iso:country":"GB",
    "sg:address":"North Moor Lane, Halsall",
    "sg:city":"Ormskirk",
    "sg:classifiers":[
        {
            "category":"Manufacturing",
            "subcategory":"Lumber",
            "type":"Manufacturing & Wholesale Goods"
        }
    ],
    "sg:phone":"+44 1704 841400",
    "sg:postcode":"L39 8RF",
    "sg:province":"Lancashire",
    "sg:tags":[
        "importer",
        "merchants",
        "agent",
        "timber"
    ],
    "wof:name":"Brooks Bros (U K) Ltd.",
    "wof:placetype":"venue"
},
  "geometry": {"coordinates":[-2.9546189308,53.5842704773],"type":"Point"}
}