{
  "type": "Feature",
  "properties": {
    "addr:full":"160a Midland Rd Leyton Greater London E10 6JT",
    "addr:housenumber":"160a",
    "addr:postcode":"e10 6jt",
    "addr:street":"Midland Rd",
    "iso:country":"GB",
    "sg:address":"160a Midland Rd",
    "sg:city":"Leyton",
    "sg:classifiers":[
        {
            "category":"Retail",
            "subcategory":"Auto Repair",
            "type":"Services"
        }
    ],
    "sg:phone":"+44 20 8558 2040",
    "sg:postcode":"E10 6JT",
    "sg:province":"Greater London",
    "sg:tags":[
        "modification",
        "garage"
    ],
    "wof:name":"Silverpride Ltd",
    "wof:placetype":"venue"
},
  "geometry": {"coordinates":[-0.006199,51.56929],"type":"Point"}
}