{
  "type": "Feature",
  "properties": {
    "iso:country":"GB",
    "sg:address":"101 Wharncliffe Road",
    "sg:city":"Ilkeston",
    "sg:classifiers":[
        {
            "category":"Shopping",
            "subcategory":"Clothing, Apparel, & Fashions",
            "type":"Retail Goods"
        }
    ],
    "sg:phone":"+44 115 932 6706",
    "sg:postcode":"DE7 5HF",
    "sg:province":"Derbyshire",
    "sg:tags":[
        "haberdasher"
    ],
    "wof:name":"E F Toplis",
    "wof:placetype":"venue"
},
  "geometry": {"coordinates":[-1.3113939762,52.9737205505],"type":"Point"}
}