{
  "type": "Feature",
  "properties": {
    "iso:country":"GB",
    "sg:address":"121 Marine Parade",
    "sg:city":"Sheerness",
    "sg:classifiers":[
        {
            "category":"Home & Garden",
            "subcategory":"Home Furnishings",
            "type":"Retail Goods"
        }
    ],
    "sg:postcode":"ME12 2BX",
    "sg:province":"Kent",
    "sg:tags":[
        "patio",
        "furniture"
    ],
    "wof:name":"Woodlands",
    "wof:placetype":"venue"
},
  "geometry": {"coordinates":[0.782145,51.439983],"type":"Point"}
}