{
  "type": "Feature",
  "properties": {
    "addr:full":"24 Langroyd Road London Greater London SW17 7PL",
    "addr:housenumber":"24",
    "addr:postcode":"sw17 7pl",
    "addr:street":"Langroyd Road",
    "iso:country":"GB",
    "sg:address":"24 Langroyd Road",
    "sg:city":"London",
    "sg:classifiers":[
        {
            "category":"Shopping",
            "subcategory":"Catalog Store",
            "type":"Retail Goods"
        },
        {
            "category":"Shopping",
            "subcategory":"Books",
            "type":"Retail Goods"
        }
    ],
    "sg:phone":"+44 20 8767 7421",
    "sg:postcode":"SW17 7PL",
    "sg:province":"Greater London",
    "sg:tags":[
        "mail",
        "second-hand",
        "order"
    ],
    "wof:name":"Sandpiper Books Ltd.",
    "wof:placetype":"venue"
},
  "geometry": {"coordinates":[-0.163552,51.437881],"type":"Point"}
}