{
  "type": "Feature",
  "properties": {
    "addr:full":"19 Lytham Rd Blackpool Lancashire FY1 6DJ",
    "addr:housenumber":"19",
    "addr:postcode":"fy1 6dj",
    "addr:street":"Lytham Rd",
    "iso:country":"GB",
    "sg:address":"19 Lytham Rd",
    "sg:city":"Blackpool",
    "sg:classifiers":[
        {
            "category":"Recreation",
            "subcategory":"Amusement Park",
            "type":"Entertainment"
        }
    ],
    "sg:postcode":"FY1 6DJ",
    "sg:province":"Lancashire",
    "sg:tags":[
        "arcade"
    ],
    "wof:name":"Lifeboat Amusements",
    "wof:placetype":"venue"
},
  "geometry": {"coordinates":[-3.0542550087,53.8063545227],"type":"Point"}
}