{
  "type": "Feature",
  "properties": {
    "addr:full":"6 Crawford Place, Monkseaton Whitley Bay Northumberland NE25 8TB",
    "addr:housenumber":"6",
    "addr:postcode":"ne25 8tb",
    "addr:street":"Crawford Place",
    "iso:country":"GB",
    "sg:address":"6 Crawford Place, Monkseaton",
    "sg:city":"Whitley Bay",
    "sg:classifiers":[
        {
            "category":"Health Services",
            "subcategory":"Dentist",
            "type":"Services"
        }
    ],
    "sg:phone":"+44 191 252 3638",
    "sg:postcode":"NE25 8TB",
    "sg:province":"Northumberland",
    "wof:name":"Mr Jones Surgery",
    "wof:placetype":"venue"
},
  "geometry": {"coordinates":[-1.4681400061,55.0386734009],"type":"Point"}
}