{
  "type": "Feature",
  "properties": {
    "addr:full":"362 Edgware Road London Greater London W2 1EB",
    "addr:housenumber":"362",
    "addr:postcode":"w2 1eb",
    "addr:street":"Edgware Road",
    "iso:country":"GB",
    "sg:address":"362 Edgware Road",
    "sg:city":"London",
    "sg:classifiers":[
        {
            "category":"Fast Food",
            "type":"Food & Drink"
        },
        {
            "category":"Cafe",
            "type":"Food & Drink"
        }
    ],
    "sg:phone":"+44 20 7723 8669",
    "sg:postcode":"W2 1EB",
    "sg:province":"Greater London",
    "sg:tags":[
        "away",
        "snack",
        "bar",
        "take"
    ],
    "wof:name":"Regent Milk Bar",
    "wof:placetype":"venue"
},
  "geometry": {"coordinates":[-0.1718509942,51.5215263367],"type":"Point"}
}