{
  "type": "Feature",
  "properties": {
    "iso:country":"GB",
    "sg:address":"639 Muller Road, Eastville",
    "sg:city":"Bristol",
    "sg:classifiers":[
        {
            "category":"Social Services",
            "subcategory":"Retirement Home",
            "type":"Services"
        },
        {
            "category":"Organizations",
            "subcategory":"Non-profit Organization",
            "type":"Services"
        }
    ],
    "sg:phone":"+44 117 951 9094",
    "sg:postcode":"BS5 6XS",
    "sg:province":"City of Bristol",
    "sg:tags":[
        "residential",
        "organisation",
        "charity",
        "voluntary",
        "care"
    ],
    "wof:name":"Underhay House",
    "wof:placetype":"venue"
},
  "geometry": {"coordinates":[-2.566071,51.475742],"type":"Point"}
}