{
  "type": "Feature",
  "properties": {
    "addr:full":"271 Church Rd Upper Norwood Greater London SE19 2QQ",
    "addr:housenumber":"271",
    "addr:postcode":"se19 2qq",
    "addr:street":"Church Rd",
    "iso:country":"GB",
    "sg:address":"271 Church Rd",
    "sg:city":"Upper Norwood",
    "sg:classifiers":[
        {
            "category":"Organizations",
            "subcategory":"Non-profit Organization",
            "type":"Services"
        }
    ],
    "sg:phone":"+44 20 8857 7794",
    "sg:postcode":"SE19 2QQ",
    "sg:province":"Greater London",
    "sg:tags":[
        "organisation",
        "voluntary",
        "charity"
    ],
    "wof:name":"Book Aid",
    "wof:placetype":"venue"
},
  "geometry": {"coordinates":[-0.0844480023,51.4129829407],"type":"Point"}
}