{
  "type": "Feature",
  "properties": {
    "iso:country":"GB",
    "sg:address":"11 Crossways House, Luttworth Rd, Blaby",
    "sg:city":"Leicester",
    "sg:classifiers":[
        {
            "category":"Banks & Credit Unions",
            "subcategory":"Bank",
            "type":"Services"
        }
    ],
    "sg:phone":"+44 116 277 2888",
    "sg:postcode":"LE8 4DD",
    "sg:province":"Leicestershire",
    "sg:tags":[
        "broker",
        "mortgage"
    ],
    "wof:name":"Mortgage Advise Agency",
    "wof:placetype":"venue"
},
  "geometry": {"coordinates":[-1.164713,52.573448],"type":"Point"}
}