{
  "type": "Feature",
  "properties": {
    "addr:full":"Capital Pl, 120 Bath Rd Hayes Greater London UB3 5AN",
    "addr:housenumber":"120",
    "addr:postcode":"ub3 5an",
    "addr:street":"Capital Pl;Bath Rd",
    "iso:country":"GB",
    "sg:address":"Capital Pl, 120 Bath Rd",
    "sg:city":"Hayes",
    "sg:classifiers":[
        {
            "category":"Communications",
            "type":"Services"
        }
    ],
    "sg:phone":"+44 20 8607 4521",
    "sg:postcode":"UB3 5AN",
    "sg:province":"Greater London",
    "sg:tags":[
        "data",
        "network"
    ],
    "wof:name":"CITS International Ltd",
    "wof:placetype":"venue"
},
  "geometry": {"coordinates":[-0.4247559905,51.5015525818],"type":"Point"}
}