{
  "type": "Feature",
  "properties": {
    "addr:full":"467 Kingsway Manchester Greater Manchester M19 1NR",
    "addr:housenumber":"467",
    "addr:postcode":"m19 1nr",
    "addr:street":"Kingsway",
    "iso:country":"GB",
    "sg:address":"467 Kingsway",
    "sg:city":"Manchester",
    "sg:classifiers":[
        {
            "category":"Social Services",
            "subcategory":"Adult Care",
            "type":"Services"
        }
    ],
    "sg:postcode":"M19 1NR",
    "sg:province":"Greater Manchester",
    "sg:tags":[
        "domestic",
        "cleaning"
    ],
    "wof:name":"Chadwick,Karen,",
    "wof:placetype":"venue"
},
  "geometry": {"coordinates":[-2.210319,53.427361],"type":"Point"}
}