{
  "type": "Feature",
  "properties": {
    "addr:full":"Unit 1 Westerham Trade Centre, The Flyers Way Westerham Kent TN16 1DE",
    "addr:housenumber":"unit 1;trade centre",
    "addr:postcode":"tn16 1de",
    "addr:street":"The Flyers Way",
    "iso:country":"GB",
    "sg:address":"Unit 1 Westerham Trade Centre, The Flyers Way",
    "sg:city":"Westerham",
    "sg:classifiers":[
        {
            "category":"Home & Garden",
            "subcategory":"Household Appliances",
            "type":"Retail Goods"
        }
    ],
    "sg:phone":"+44 1959 561221",
    "sg:postcode":"TN16 1DE",
    "sg:province":"Kent",
    "sg:tags":[
        "refrigeration",
        "air conditioning"
    ],
    "wof:name":"J & E Hall Ltd.",
    "wof:placetype":"venue"
},
  "geometry": {"coordinates":[0.071265,51.267075],"type":"Point"}
}