{
  "type": "Feature",
  "properties": {
    "iso:country":"GB",
    "sg:address":"Wellfield Road, Murton",
    "sg:city":"Seaham",
    "sg:classifiers":[
        {
            "category":"Health Services",
            "subcategory":"Nursing And Care Facility",
            "type":"Services"
        }
    ],
    "sg:phone":"+44 191 517 1020",
    "sg:postcode":"SR7 9HN",
    "sg:province":"Durham",
    "sg:tags":[
        "home"
    ],
    "wof:name":"S D S K Ltd.",
    "wof:placetype":"venue"
},
  "geometry": {"coordinates":[-1.398289,54.818916],"type":"Point"}
}