{
  "type": "Feature",
  "properties": {
    "addr:full":"Canalside Fort Augustus Highland PH32 4BD",
    "addr:postcode":"ph32 4bd",
    "addr:street":"Canalside",
    "iso:country":"GB",
    "sg:address":"Canalside",
    "sg:city":"Fort Augustus",
    "sg:classifiers":[
        {
            "category":"Food & Beverages",
            "subcategory":"Meat & Fish",
            "type":"Retail Goods"
        }
    ],
    "sg:postcode":"PH32 4BD",
    "sg:province":"Highland",
    "sg:tags":[
        "chip"
    ],
    "wof:name":"Causers Fish Shop",
    "wof:placetype":"venue"
},
  "geometry": {"coordinates":[-4.682744,57.145081],"type":"Point"}
}