{
  "type": "Feature",
  "properties": {
    "addr:full":"Menai Workshops, Lon-pobty Bangor Gwynedd LL57 1HS",
    "addr:postcode":"ll57 1hs",
    "iso:country":"GB",
    "sg:address":"Menai Workshops, Lon-pobty",
    "sg:city":"Bangor",
    "sg:classifiers":[
        {
            "category":"Autos & Motor Vehicles",
            "subcategory":"Auto Supplies",
            "type":"Retail Goods"
        }
    ],
    "sg:phone":"+44 1248 370067",
    "sg:postcode":"LL57 1HS",
    "sg:province":"Gwynedd",
    "sg:tags":[
        "part",
        "motorcycle",
        "accessory"
    ],
    "wof:name":"Celtic Bike Seats",
    "wof:placetype":"venue"
},
  "geometry": {"coordinates":[-4.1260638237,53.2295951843],"type":"Point"}
}