{
  "type": "Feature",
  "properties": {
    "iso:country":"GB",
    "sg:address":"41 Boxmoor Road, Collier Row",
    "sg:city":"Romford",
    "sg:classifiers":[
        {
            "category":"Professional",
            "subcategory":"Engineering",
            "type":"Services"
        }
    ],
    "sg:phone":"+44 1708 734647",
    "sg:postcode":"RM5 2SH",
    "sg:province":"Essex",
    "sg:tags":[
        "contractor",
        "electrical",
        "engineer"
    ],
    "wof:name":"Marc Walters",
    "wof:placetype":"venue"
},
  "geometry": {"coordinates":[0.1667910069,51.6074409485],"type":"Point"}
}