{
  "type": "Feature",
  "properties": {
    "addr:full":"3 Mauchline Avenue Dundee Dundee City DD4 8HU",
    "addr:housenumber":"3",
    "addr:postcode":"dd4 8hu",
    "addr:street":"Mauchline Avenue",
    "iso:country":"GB",
    "sg:address":"3 Mauchline Avenue",
    "sg:city":"Dundee",
    "sg:classifiers":[
        {
            "category":"Fast Food",
            "type":"Food & Drink"
        }
    ],
    "sg:phone":"+44 1382 505144",
    "sg:postcode":"DD4 8HU",
    "sg:province":"Dundee City",
    "sg:tags":[
        "away",
        "meal",
        "outlet",
        "take"
    ],
    "wof:name":"Po Wah Chinese Take Away",
    "wof:placetype":"venue"
},
  "geometry": {"coordinates":[-2.931401,56.479733],"type":"Point"}
}