{
  "type": "Feature",
  "properties": {
    "addr:full":"Stone Lodge Lane West Ipswich Suffolk IP2 9HW",
    "addr:postcode":"ip2 9hw",
    "addr:street":"Lodge Lane West",
    "iso:country":"GB",
    "sg:address":"Stone Lodge Lane West",
    "sg:city":"Ipswich",
    "sg:classifiers":[
        {
            "category":"Education",
            "subcategory":"School",
            "type":"Public Place"
        }
    ],
    "sg:phone":"+44 1473 601175",
    "sg:postcode":"IP2 9HW",
    "sg:province":"Suffolk",
    "sg:tags":[
        "local",
        "authority"
    ],
    "wof:name":"Beacon Hill Special School",
    "wof:placetype":"venue"
},
  "geometry": {"coordinates":[1.129883,52.046413],"type":"Point"}
}