{
  "type": "Feature",
  "properties": {
    "iso:country":"GB",
    "sg:address":"Building 509 Churchill Way, Biggin Hill Airport",
    "sg:city":"Westerham",
    "sg:classifiers":[
        {
            "category":"Personal",
            "type":"Services"
        }
    ],
    "sg:phone":"+44 1959 578101",
    "sg:postcode":"TN16 3BN",
    "sg:province":"Kent",
    "sg:tags":[
        "gift"
    ],
    "wof:name":"Air Displays International Ltd.",
    "wof:placetype":"venue"
},
  "geometry": {"coordinates":[0.0345549993,51.3200950623],"type":"Point"}
}