{
  "type": "Feature",
  "properties": {
    "addr:full":"Northbank, Bowden Melrose Scottish Borders TD6 0SS",
    "addr:postcode":"td6 0ss",
    "addr:street":"Bowden",
    "iso:country":"GB",
    "sg:address":"Northbank, Bowden",
    "sg:city":"Melrose",
    "sg:classifiers":[
        {
            "category":"Building & Trades",
            "subcategory":"Construction",
            "type":"Services"
        }
    ],
    "sg:phone":"+44 1835 822394",
    "sg:postcode":"TD6 0SS",
    "sg:province":"Scottish Borders",
    "sg:tags":[
        "builder"
    ],
    "wof:name":"James Grieve & Son",
    "wof:placetype":"venue"
},
  "geometry": {"coordinates":[-2.707165,55.566696],"type":"Point"}
}