{
  "type": "Feature",
  "properties": {
    "iso:country":"GB",
    "sg:address":"7 Marine Drive",
    "sg:city":"Hornsea",
    "sg:classifiers":[
        {
            "category":"Travel",
            "subcategory":"Hotels & Motels",
            "type":"Entertainment"
        }
    ],
    "sg:phone":"+44 1964 536414",
    "sg:postcode":"HU18 1NJ",
    "sg:province":"East Riding of Yorkshire",
    "sg:tags":[
        "house",
        "guest"
    ],
    "wof:name":"Admiralty Guest House",
    "wof:placetype":"venue"
},
  "geometry": {"coordinates":[-0.161366,53.914085],"type":"Point"}
}