{
  "type": "Feature",
  "properties": {
    "addr:full":"Lilleshall Way, Highfields Stafford Staffordshire ST17 9FD",
    "addr:postcode":"st17 9fd",
    "addr:street":"Lilleshall Way",
    "iso:country":"GB",
    "sg:address":"Lilleshall Way, Highfields",
    "sg:city":"Stafford",
    "sg:classifiers":[
        {
            "category":"Organizations",
            "subcategory":"Community Association",
            "type":"Services"
        }
    ],
    "sg:phone":"+44 1785 222050",
    "sg:postcode":"ST17 9FD",
    "sg:province":"Staffordshire",
    "sg:tags":[
        "society",
        "housing"
    ],
    "wof:name":"Bradford & Northern Housing Association Ltd.",
    "wof:placetype":"venue"
},
  "geometry": {"coordinates":[-2.134239912,52.7897186279],"type":"Point"}
}