{
  "type": "Feature",
  "properties": {
    "addr:full":"17 King Street Watford Hertfordshire WD18 0BW",
    "addr:housenumber":"17",
    "addr:postcode":"wd18 0bw",
    "addr:street":"King Street",
    "iso:country":"GB",
    "sg:address":"17 King Street",
    "sg:city":"Watford",
    "sg:classifiers":[
        {
            "category":"Professional",
            "subcategory":"Lawyer & Legal Services",
            "type":"Services"
        }
    ],
    "sg:postcode":"WD18 0BW",
    "sg:province":"Hertfordshire",
    "sg:tags":[
        "solicitor"
    ],
    "wof:name":"Arnold & Co",
    "wof:placetype":"venue"
},
  "geometry": {"coordinates":[-0.394878,51.6533355713],"type":"Point"}
}