{
  "type": "Feature",
  "properties": {
    "iso:country":"GB",
    "sg:address":"14 Fowler Rd",
    "sg:city":"Sutton Coldfield",
    "sg:classifiers":[
        {
            "category":"Freight",
            "type":"Transportation"
        }
    ],
    "sg:postcode":"B75 7LW",
    "sg:province":"Staffordshire",
    "sg:tags":[
        "haulage",
        "road"
    ],
    "wof:name":"Danaher,Christine,",
    "wof:placetype":"venue"
},
  "geometry": {"coordinates":[-1.786918,52.561714],"type":"Point"}
}