{
  "type": "Feature",
  "properties": {
    "addr:full":"Glastonbury Rd Wells Somerset BA5 1TJ",
    "addr:postcode":"ba5 1tj",
    "addr:street":"Glastonbury Rd",
    "iso:country":"GB",
    "sg:address":"Glastonbury Rd",
    "sg:city":"Wells",
    "sg:classifiers":[
        {
            "category":"Health Services",
            "subcategory":"Hospital",
            "type":"Services"
        }
    ],
    "sg:phone":"+44 1749 676887",
    "sg:postcode":"BA5 1TJ",
    "sg:province":"Somerset",
    "wof:name":"Priory Day Hospital",
    "wof:placetype":"venue"
},
  "geometry": {"coordinates":[-2.652739,51.203915],"type":"Point"}
}