{
  "type": "Feature",
  "properties": {
    "addr:full":"Longcroft Carlisle Cumbria CA5 5BA",
    "addr:postcode":"ca5 5ba",
    "iso:country":"GB",
    "sg:address":"Longcroft",
    "sg:city":"Carlisle",
    "sg:classifiers":[
        {
            "category":"Professional",
            "subcategory":"Engineering",
            "type":"Services"
        }
    ],
    "sg:phone":"+44 16973 51269",
    "sg:postcode":"CA5 5BA",
    "sg:province":"Cumbria",
    "wof:name":"W & Graham",
    "wof:placetype":"venue"
},
  "geometry": {"coordinates":[-3.1863899231,54.9478797913],"type":"Point"}
}