{
  "type": "Feature",
  "properties": {
    "addr:full":"37-39 Snow Hill Stoke-on-trent Staffordshire ST1 4LU",
    "addr:housenumber":"37-39",
    "addr:postcode":"st1 4lu",
    "addr:street":"Snow Hill",
    "iso:country":"GB",
    "sg:address":"37-39 Snow Hill",
    "sg:city":"Stoke-on-trent",
    "sg:classifiers":[
        {
            "category":"Home & Garden",
            "subcategory":"Household Appliances",
            "type":"Retail Goods"
        }
    ],
    "sg:postcode":"ST1 4LU",
    "sg:province":"Staffordshire",
    "sg:tags":[
        "domestic",
        "centre"
    ],
    "wof:name":"The Washer Shop",
    "wof:placetype":"venue"
},
  "geometry": {"coordinates":[-2.183002,53.018543],"type":"Point"}
}