{
  "type": "Feature",
  "properties": {
    "iso:country":"GB",
    "sg:address":"30 Balgownie Place, Bridge Of Don",
    "sg:city":"Aberdeen",
    "sg:classifiers":[
        {
            "category":"Building & Trades",
            "subcategory":"Construction",
            "type":"Services"
        }
    ],
    "sg:postcode":"AB22 8FB",
    "sg:province":"Aberdeen City",
    "sg:tags":[
        "roofing"
    ],
    "wof:name":"S A Winchester",
    "wof:placetype":"venue"
},
  "geometry": {"coordinates":[-2.12114,57.179276],"type":"Point"}
}