{
  "type": "Feature",
  "properties": {
    "addr:full":"31 High Street Wisbech Cambridgeshire PE13 1DE",
    "addr:housenumber":"31",
    "addr:postcode":"pe13 1de",
    "addr:street":"High Street",
    "iso:country":"GB",
    "sg:address":"31 High Street",
    "sg:city":"Wisbech",
    "sg:classifiers":[
        {
            "category":"Wholesale",
            "subcategory":"Medical Equipment & Supplies",
            "type":"Manufacturing & Wholesale Goods"
        }
    ],
    "sg:phone":"+44 1945 474044",
    "sg:postcode":"PE13 1DE",
    "sg:province":"Cambridgeshire",
    "sg:tags":[
        "aid",
        "hearing"
    ],
    "wof:name":"Hearing Aids Centre",
    "wof:placetype":"venue"
},
  "geometry": {"coordinates":[0.1596049964,52.6651496887],"type":"Point"}
}