{
  "type": "Feature",
  "properties": {
    "iso:country":"GB",
    "sg:address":"16 Lord Street",
    "sg:city":"Wrexham",
    "sg:classifiers":[
        {
            "category":"Professional",
            "subcategory":"Employment Agencies",
            "type":"Services"
        }
    ],
    "sg:phone":"+44 1978 203400",
    "sg:postcode":"LL11 1EJ",
    "sg:province":"Wrexham",
    "sg:tags":[
        "consultant"
    ],
    "wof:name":"Employment Service Jobcentre",
    "wof:placetype":"venue"
},
  "geometry": {"coordinates":[-2.99647,53.047478],"type":"Point"}
}