{
  "type": "Feature",
  "properties": {
    "iso:country":"GB",
    "sg:address":"896 Forest Road",
    "sg:city":"London",
    "sg:classifiers":[
        {
            "category":"Education",
            "subcategory":"School",
            "type":"Public Place"
        }
    ],
    "sg:phone":"+44 20 8520 4186",
    "sg:postcode":"E17 4AE",
    "sg:province":"Greater London",
    "sg:tags":[
        "independent",
        "preparatory"
    ],
    "wof:name":"Hyland House School",
    "wof:placetype":"venue"
},
  "geometry": {"coordinates":[0.00954,51.5940513611],"type":"Point"}
}