{
  "type": "Feature",
  "properties": {
    "addr:full":"692 Holloway Road London Greater London N19 3NL",
    "addr:housenumber":"692",
    "addr:postcode":"n19 3nl",
    "addr:street":"Holloway Road",
    "iso:country":"GB",
    "sg:address":"692 Holloway Road",
    "sg:city":"London",
    "sg:classifiers":[
        {
            "category":"Shopping",
            "subcategory":"Florist",
            "type":"Retail Goods"
        }
    ],
    "sg:phone":"+44 20 7272 8217",
    "sg:postcode":"N19 3NL",
    "sg:province":"Greater London",
    "wof:name":"Elli's Florist",
    "wof:placetype":"venue"
},
  "geometry": {"coordinates":[-0.1340319961,51.5652122498],"type":"Point"}
}