{
  "type": "Feature",
  "properties": {
    "addr:full":"12 Buckingham Rd Poole Dorset BH12 2HR",
    "addr:housenumber":"12",
    "addr:postcode":"bh12 2hr",
    "addr:street":"Buckingham Rd",
    "iso:country":"GB",
    "sg:address":"12 Buckingham Rd",
    "sg:city":"Poole",
    "sg:classifiers":[
        {
            "category":"Professional",
            "subcategory":"Business Services",
            "type":"Services"
        }
    ],
    "sg:phone":"+44 1202 741522",
    "sg:postcode":"BH12 2HR",
    "sg:province":"Dorset",
    "sg:tags":[
        "shop",
        "cleaning"
    ],
    "wof:name":"Helping Hands",
    "wof:placetype":"venue"
},
  "geometry": {"coordinates":[-1.930979,50.73827],"type":"Point"}
}