{
  "type": "Feature",
  "properties": {
    "addr:full":"56 Monmouth Road Dorchester Dorset DT1 2DG",
    "addr:housenumber":"56",
    "addr:postcode":"dt1 2dg",
    "addr:street":"Monmouth Road",
    "iso:country":"GB",
    "sg:address":"56 Monmouth Road",
    "sg:city":"Dorchester",
    "sg:classifiers":[
        {
            "category":"Education",
            "subcategory":"Special Training",
            "type":"Public Place"
        },
        {
            "category":"Arena",
            "subcategory":"Sports Club",
            "type":"Entertainment"
        }
    ],
    "sg:postcode":"DT1 2DG",
    "sg:province":"Dorset",
    "sg:tags":[
        "martial art",
        "instruction"
    ],
    "wof:name":"The Wessex Karate Acadamy",
    "wof:placetype":"venue"
},
  "geometry": {"coordinates":[-2.4374010563,50.707485199],"type":"Point"}
}