{
  "type": "Feature",
  "properties": {
    "iso:country":"GB",
    "sg:address":"Studio 1a, 33 Greenwood Place",
    "sg:city":"Kentish Town",
    "sg:classifiers":[
        {
            "category":"Professional",
            "subcategory":"Accounting & Tax Preparation",
            "type":"Services"
        }
    ],
    "sg:phone":"+44 20 7482 1144",
    "sg:postcode":"NW5 1LB",
    "sg:province":"Greater London",
    "sg:tags":[
        "accountant"
    ],
    "wof:name":"Fredericks Chartered Accountants",
    "wof:placetype":"venue"
},
  "geometry": {"coordinates":[-0.1423300058,51.5523986816],"type":"Point"}
}