{
  "type": "Feature",
  "properties": {
    "iso:country":"GB",
    "sg:address":"Suite Two",
    "sg:city":"Dundee",
    "sg:classifiers":[
        {
            "category":"Real Estate",
            "subcategory":"Architect",
            "type":"Services"
        }
    ],
    "sg:postcode":"DD4 7RE",
    "sg:province":"Dundee City",
    "wof:name":"Ritchie Dagen & Allan Ltd.",
    "wof:placetype":"venue"
},
  "geometry": {"coordinates":[-2.92905,56.474892],"type":"Point"}
}