{
  "type": "Feature",
  "properties": {
    "addr:full":"Tylers Road, Roydon Harlow Essex CM19 5LJ",
    "addr:postcode":"cm19 5lj",
    "addr:street":"Tylers Road",
    "iso:country":"GB",
    "sg:address":"Tylers Road, Roydon",
    "sg:city":"Harlow",
    "sg:classifiers":[
        {
            "category":"Bars & Pubs",
            "type":"Food & Drink"
        },
        {
            "category":"Community Center",
            "subcategory":"Social",
            "type":"Public Place"
        }
    ],
    "sg:phone":"+44 1279 792666",
    "sg:postcode":"CM19 5LJ",
    "sg:province":"Essex",
    "sg:tags":[
        "pubs",
        "house",
        "inn",
        "activity"
    ],
    "wof:name":"The Green Man",
    "wof:placetype":"venue"
},
  "geometry": {"coordinates":[0.038872,51.769241],"type":"Point"}
}