{
  "type": "Feature",
  "properties": {
    "addr:full":"Stable Ho, Cockaynes La, Alresford Colchester Essex CO7 8BZ",
    "addr:postcode":"co7 8bz",
    "addr:street":"La Alresford Colchester",
    "iso:country":"GB",
    "sg:address":"Stable Ho, Cockaynes La, Alresford",
    "sg:city":"Colchester",
    "sg:classifiers":[
        {
            "category":"Shopping",
            "subcategory":"Gifts & Souvenirs",
            "type":"Retail Goods"
        }
    ],
    "sg:phone":"+44 1206 825456",
    "sg:postcode":"CO7 8BZ",
    "sg:province":"Essex",
    "sg:tags":[
        "christmas"
    ],
    "wof:name":"Walpert Industries Ltd",
    "wof:placetype":"venue"
},
  "geometry": {"coordinates":[1.007203,51.853226],"type":"Point"}
}