{
  "type": "Feature",
  "properties": {
    "iso:country":"GB",
    "sg:address":"P O Box 6209",
    "sg:city":"Basingstoke",
    "sg:classifiers":[
        {
            "category":"Education",
            "subcategory":"Special Training",
            "type":"Public Place"
        }
    ],
    "sg:postcode":"RG22 4GB",
    "sg:province":"Hampshire",
    "sg:tags":[
        "product",
        "centre"
    ],
    "wof:name":"Deall Publications",
    "wof:placetype":"venue"
},
  "geometry": {"coordinates":[-1.121719,51.235161],"type":"Point"}
}