{
  "type": "Feature",
  "properties": {
    "iso:country":"GB",
    "sg:address":"578 Blackpool Road, Ashton-on-ribble",
    "sg:city":"Preston",
    "sg:classifiers":[
        {
            "category":"Personal",
            "subcategory":"Beauty Salon",
            "type":"Services"
        }
    ],
    "sg:phone":"+44 1772 721715",
    "sg:postcode":"PR4 1JA",
    "sg:province":"Lancashire",
    "sg:tags":[
        "lady",
        "hairdresser"
    ],
    "wof:name":"Capricorn Hair",
    "wof:placetype":"venue"
},
  "geometry": {"coordinates":[-2.87251,53.772961],"type":"Point"}
}