{
  "type": "Feature",
  "properties": {
    "iso:country":"GB",
    "sg:address":"13 High Street",
    "sg:city":"St Albans",
    "sg:classifiers":[
        {
            "category":"Deli",
            "type":"Food & Drink"
        }
    ],
    "sg:phone":"+44 1727 843555",
    "sg:postcode":"AL3 4ED",
    "sg:province":"Hertfordshire",
    "sg:tags":[
        "delivery",
        "sandwich"
    ],
    "wof:name":"J K Palmers",
    "wof:placetype":"venue"
},
  "geometry": {"coordinates":[-0.34048599,51.7509918213],"type":"Point"}
}