{
  "type": "Feature",
  "properties": {
    "addr:full":"1 Severn Side South Bewdley Shropshire DY12 2DX",
    "addr:housenumber":"1",
    "addr:postcode":"dy12 2dx",
    "addr:street":"Severn Side South",
    "iso:country":"GB",
    "sg:address":"1 Severn Side South",
    "sg:city":"Bewdley",
    "sg:classifiers":[
        {
            "category":"Restaurant",
            "type":"Food & Drink"
        }
    ],
    "sg:phone":"+44 1299 403358",
    "sg:postcode":"DY12 2DX",
    "sg:province":"Shropshire",
    "wof:name":"Mallards Cafe",
    "wof:placetype":"venue"
},
  "geometry": {"coordinates":[-2.3141310215,52.3759689331],"type":"Point"}
}