{
  "type": "Feature",
  "properties": {
    "addr:full":"12 Ogmore Crescent, Bridgend Industrial Estate Bridgend Bridgend CF31 3TE",
    "addr:housenumber":"12",
    "addr:postcode":"cf31 3te",
    "addr:street":"Ogmore Crescent;Industrial Estate",
    "iso:country":"GB",
    "sg:address":"12 Ogmore Crescent, Bridgend Industrial Estate",
    "sg:city":"Bridgend",
    "sg:classifiers":[
        {
            "category":"Professional",
            "subcategory":"Engineering",
            "type":"Services"
        }
    ],
    "sg:phone":"+44 1656 766567",
    "sg:postcode":"CF31 3TE",
    "sg:province":"Bridgend",
    "sg:tags":[
        "precision",
        "engineer"
    ],
    "wof:name":"Clive David",
    "wof:placetype":"venue"
},
  "geometry": {"coordinates":[-3.565030098,51.5004615784],"type":"Point"}
}