{
  "type": "Feature",
  "properties": {
    "addr:full":"136 York Rd Hartlepool Durham TS26 9DA",
    "addr:housenumber":"136",
    "addr:postcode":"ts26 9da",
    "addr:street":"York Rd",
    "iso:country":"GB",
    "sg:address":"136 York Rd",
    "sg:city":"Hartlepool",
    "sg:classifiers":[
        {
            "category":"Shopping",
            "subcategory":"Pharmacy",
            "type":"Retail Goods"
        }
    ],
    "sg:postcode":"TS26 9DA",
    "sg:province":"Durham",
    "sg:tags":[
        "pharmacist",
        "chemist"
    ],
    "wof:name":"R T Platts Chemists Ltd",
    "wof:placetype":"venue"
},
  "geometry": {"coordinates":[-1.216533,54.682652],"type":"Point"}
}