{
  "type": "Feature",
  "properties": {
    "iso:country":"GB",
    "sg:address":"Green Laithe, Sandy Lane, Belton",
    "sg:city":"Great Yarmouth",
    "sg:classifiers":[
        {
            "category":"Building & Trades",
            "subcategory":"Construction",
            "type":"Services"
        }
    ],
    "sg:phone":"+44 1493 781838",
    "sg:postcode":"NR31 9LT",
    "sg:province":"Norfolk",
    "sg:tags":[
        "joiner",
        "carpenter"
    ],
    "wof:name":"Corton Windows",
    "wof:placetype":"venue"
},
  "geometry": {"coordinates":[1.660611,52.568222],"type":"Point"}
}