{
  "type": "Feature",
  "properties": {
    "iso:country":"GB",
    "sg:address":"2nd Floor, 1 Occam Court, Rdoccam",
    "sg:city":"Guildford",
    "sg:classifiers":[
        {
            "category":"Professional",
            "subcategory":"Computer Services",
            "type":"Services"
        }
    ],
    "sg:phone":"+44 1483 401000",
    "sg:postcode":"GU2 7YQ",
    "sg:province":"Surrey",
    "sg:tags":[
        "system",
        "software"
    ],
    "wof:name":"Lionhead Studios Ltd.",
    "wof:placetype":"venue"
},
  "geometry": {"coordinates":[-0.6133760214,51.2424507141],"type":"Point"}
}