{
  "type": "Feature",
  "properties": {
    "addr:full":"37 West Street Bexleyheath Kent DA7 4BE",
    "addr:housenumber":"37",
    "addr:postcode":"da7 4be",
    "addr:street":"West Street",
    "iso:country":"GB",
    "sg:address":"37 West Street",
    "sg:city":"Bexleyheath",
    "sg:classifiers":[
        {
            "category":"Shopping",
            "subcategory":"Computers & Home Electronics",
            "type":"Retail Goods"
        }
    ],
    "sg:phone":"+44 20 8304 8341",
    "sg:postcode":"DA7 4BE",
    "sg:province":"Kent",
    "sg:tags":[
        "electrical"
    ],
    "wof:name":"Brampton Electrical Suppliers Ltd.",
    "wof:placetype":"venue"
},
  "geometry": {"coordinates":[0.136441,51.459007],"type":"Point"}
}