{
  "type": "Feature",
  "properties": {
    "addr:full":"6 South Acre Drive Macclesfield Cheshire SK11 7EW",
    "addr:housenumber":"6",
    "addr:postcode":"sk11 7ew",
    "addr:street":"South Acre Drive",
    "iso:country":"GB",
    "sg:address":"6 South Acre Drive",
    "sg:city":"Macclesfield",
    "sg:classifiers":[
        {
            "category":"Insurance",
            "subcategory":"Insurance Agent",
            "type":"Services"
        }
    ],
    "sg:phone":"+44 1625 511611",
    "sg:postcode":"SK11 7EW",
    "sg:province":"Cheshire",
    "sg:tags":[
        "broker"
    ],
    "wof:name":"John D Whittaker & Co",
    "wof:placetype":"venue"
},
  "geometry": {"coordinates":[-2.1053090096,53.256061554],"type":"Point"}
}