{
  "type": "Feature",
  "properties": {
    "addr:full":"98 Gillespie Road London Greater London N5 1LN",
    "addr:housenumber":"98",
    "addr:postcode":"n5 1ln",
    "addr:street":"Gillespie Road",
    "iso:country":"GB",
    "sg:address":"98 Gillespie Road",
    "sg:city":"London",
    "sg:classifiers":[
        {
            "category":"Food & Beverages",
            "subcategory":"Meat & Fish",
            "type":"Retail Goods"
        },
        {
            "category":"Food & Beverages",
            "subcategory":"Groceries & Convenience Stores",
            "type":"Retail Goods"
        }
    ],
    "sg:phone":"+44 20 7359 8364",
    "sg:postcode":"N5 1LN",
    "sg:province":"Greater London",
    "sg:tags":[
        "shop",
        "chip"
    ],
    "wof:name":"Golden Fish Bar",
    "wof:placetype":"venue"
},
  "geometry": {"coordinates":[-0.102669999,51.5594139099],"type":"Point"}
}