{
  "type": "Feature",
  "properties": {
    "addr:full":"5-7 Pembroke Avenue Cambridge Cambridgeshire CB5 9QP",
    "addr:housenumber":"5-7",
    "addr:postcode":"cb5 9qp",
    "addr:street":"Pembroke Avenue",
    "iso:country":"GB",
    "sg:address":"5-7 Pembroke Avenue",
    "sg:city":"Cambridge",
    "sg:classifiers":[
        {
            "category":"Shopping",
            "subcategory":"Hobbies, Toys, & Games",
            "type":"Retail Goods"
        }
    ],
    "sg:phone":"+44 1223 864894",
    "sg:postcode":"CB5 9QP",
    "sg:province":"Cambridgeshire",
    "sg:tags":[
        "toy"
    ],
    "wof:name":"Living & Learning",
    "wof:placetype":"venue"
},
  "geometry": {"coordinates":[0.1826650053,52.2709083557],"type":"Point"}
}