{
  "type": "Feature",
  "properties": {
    "addr:full":"3 Central Avenue Welling Kent DA16 3AX",
    "addr:housenumber":"3",
    "addr:postcode":"da16 3ax",
    "addr:street":"Central Avenue",
    "iso:country":"GB",
    "sg:address":"3 Central Avenue",
    "sg:city":"Welling",
    "sg:classifiers":[
        {
            "category":"Professional",
            "subcategory":"Accounting & Tax Preparation",
            "type":"Services"
        }
    ],
    "sg:postcode":"DA16 3AX",
    "sg:province":"Kent",
    "sg:tags":[
        "accountant"
    ],
    "wof:name":"On Line Direct Services Ltd.",
    "wof:placetype":"venue"
},
  "geometry": {"coordinates":[0.0998440012,51.4640159607],"type":"Point"}
}