{
  "type": "Feature",
  "properties": {
    "addr:full":"New House, Westgate Street, Shouldham King's Lynn Norfolk PE33 0BJ",
    "addr:postcode":"pe33 0bj",
    "addr:street":"Westgate Street;Lynn",
    "iso:country":"GB",
    "sg:address":"New House, Westgate Street, Shouldham",
    "sg:city":"King's Lynn",
    "sg:classifiers":[
        {
            "category":"Manufacturing",
            "subcategory":"Buildings",
            "type":"Manufacturing & Wholesale Goods"
        }
    ],
    "sg:phone":"+44 1366 347774",
    "sg:postcode":"PE33 0BJ",
    "sg:province":"Norfolk",
    "sg:tags":[
        "portable"
    ],
    "wof:name":"West Norfolk Sectional Buildings",
    "wof:placetype":"venue"
},
  "geometry": {"coordinates":[0.4744499922,52.6519508362],"type":"Point"}
}