{
  "type": "Feature",
  "properties": {
    "iso:country":"GB",
    "sg:address":"47 Northfield Road",
    "sg:city":"Cobham",
    "sg:classifiers":[
        {
            "category":"Building & Trades",
            "subcategory":"Cleaning & Sanitation",
            "type":"Services"
        }
    ],
    "sg:phone":"+44 1932 868154",
    "sg:postcode":"KT11 1JL",
    "sg:province":"Surrey",
    "sg:tags":[
        "dry",
        "control",
        "damp",
        "rot"
    ],
    "wof:name":"Allscope Preservations",
    "wof:placetype":"venue"
},
  "geometry": {"coordinates":[-0.415132,51.33445],"type":"Point"}
}