{
  "type": "Feature",
  "properties": {
    "addr:full":"4th Floor, Patrick House Sutton Coldfield West Midlands B72 1QL",
    "addr:housenumber":"4th floor patrick house sutton",
    "addr:postcode":"b72 1ql",
    "addr:street":"Coldfield West",
    "iso:country":"GB",
    "sg:address":"4th Floor, Patrick House",
    "sg:city":"Sutton Coldfield",
    "sg:classifiers":[
        {
            "category":"Professional",
            "subcategory":"Detective & Security Services",
            "type":"Services"
        }
    ],
    "sg:postcode":"B72 1QL",
    "sg:province":"West Midlands",
    "wof:name":"Goodwill Associates Ltd.",
    "wof:placetype":"venue"
},
  "geometry": {"coordinates":[-1.827794,52.534786],"type":"Point"}
}