{
  "type": "Feature",
  "properties": {
    "addr:full":"11 Woodlodge, Woodfield La Ashtead Surrey KT21 2DJ",
    "addr:housenumber":"11",
    "addr:postcode":"kt21 2dj",
    "addr:street":"Woodlodge Woodfield La Ashtead",
    "iso:country":"GB",
    "sg:address":"11 Woodlodge, Woodfield La",
    "sg:city":"Ashtead",
    "sg:classifiers":[
        {
            "category":"Health Services",
            "subcategory":"Dentist",
            "type":"Services"
        }
    ],
    "sg:phone":"+44 1372 275265",
    "sg:postcode":"KT21 2DJ",
    "sg:province":"Surrey",
    "wof:name":"K Nasser",
    "wof:placetype":"venue"
},
  "geometry": {"coordinates":[-0.3010259867,51.3109779358],"type":"Point"}
}