{
  "type": "Feature",
  "properties": {
    "addr:full":"Cover House, 113 Beudley Road Kidderminster Staffordshire DY11 6RX",
    "addr:housenumber":"113",
    "addr:postcode":"dy11 6rx",
    "addr:street":"Beudley Road",
    "iso:country":"GB",
    "sg:address":"Cover House, 113 Beudley Road",
    "sg:city":"Kidderminster",
    "sg:classifiers":[
        {
            "category":"Banks & Credit Unions",
            "subcategory":"Financial Services",
            "type":"Services"
        }
    ],
    "sg:postcode":"DY11 6RX",
    "sg:province":"Staffordshire",
    "sg:tags":[
        "consultant"
    ],
    "wof:name":"K L Plester Insurance Services Ltd.",
    "wof:placetype":"venue"
},
  "geometry": {"coordinates":[-2.2575929165,52.3876190186],"type":"Point"}
}