{
  "type": "Feature",
  "properties": {
    "addr:full":"24 New Rd Chippenham Wiltshire SN15 1HS",
    "addr:housenumber":"24",
    "addr:postcode":"sn15 1hs",
    "addr:street":"New Rd",
    "iso:country":"GB",
    "sg:address":"24 New Rd",
    "sg:city":"Chippenham",
    "sg:classifiers":[
        {
            "category":"Government",
            "subcategory":"Post Office",
            "type":"Public Place"
        }
    ],
    "sg:phone":"+44 1249 653661",
    "sg:postcode":"SN15 1HS",
    "sg:province":"Wiltshire",
    "wof:name":"New Road Post Office",
    "wof:placetype":"venue"
},
  "geometry": {"coordinates":[-2.117323,51.463337],"type":"Point"}
}