{
  "type": "Feature",
  "properties": {
    "addr:full":"145 High Road London Greater London E18 2PA",
    "addr:housenumber":"145",
    "addr:postcode":"e18 2pa",
    "addr:street":"High Road",
    "iso:country":"GB",
    "sg:address":"145 High Road",
    "sg:city":"London",
    "sg:classifiers":[
        {
            "category":"Shopping",
            "subcategory":"Photographic Equipment",
            "type":"Retail Goods"
        }
    ],
    "sg:phone":"+44 20 8504 4008",
    "sg:postcode":"E18 2PA",
    "sg:province":"Greater London",
    "sg:tags":[
        "supply"
    ],
    "wof:name":"N A Gale & Co. Ltd.",
    "wof:placetype":"venue"
},
  "geometry": {"coordinates":[0.0212760009,51.5967559814],"type":"Point"}
}