{
  "type": "Feature",
  "properties": {
    "addr:full":"70 Shaw Street Glasgow Glasgow City G51 3BL",
    "addr:housenumber":"70",
    "addr:postcode":"g51 3bl",
    "addr:street":"Shaw Street",
    "iso:country":"GB",
    "sg:address":"70 Shaw Street",
    "sg:city":"Glasgow",
    "sg:classifiers":[
        {
            "category":"Cinema",
            "subcategory":"Movie Rental",
            "type":"Entertainment"
        }
    ],
    "sg:postcode":"G51 3BL",
    "sg:province":"Glasgow City",
    "sg:tags":[
        "video",
        "library"
    ],
    "wof:name":"Target Home Entertainment",
    "wof:placetype":"venue"
},
  "geometry": {"coordinates":[-4.3163518906,55.8627128601],"type":"Point"}
}