{
  "type": "Feature",
  "properties": {
    "addr:full":"218 Brook Street, Broughty Ferry Dundee Angus DD5 2AH",
    "addr:housenumber":"218",
    "addr:postcode":"dd5 2ah",
    "addr:street":"Brook Street",
    "iso:country":"GB",
    "sg:address":"218 Brook Street, Broughty Ferry",
    "sg:city":"Dundee",
    "sg:classifiers":[
        {
            "category":"Shopping",
            "subcategory":"Gifts & Souvenirs",
            "type":"Retail Goods"
        }
    ],
    "sg:phone":"+44 1382 739883",
    "sg:postcode":"DD5 2AH",
    "sg:province":"Angus",
    "sg:tags":[
        "shop",
        "poster",
        "card"
    ],
    "wof:name":"Kaydee Cards",
    "wof:placetype":"venue"
},
  "geometry": {"coordinates":[-2.874481,56.467102],"type":"Point"}
}