{
  "type": "Feature",
  "properties": {
    "addr:full":"20 St Lukes Terrace Sunderland Tyne and Wear SR4 6NQ",
    "addr:housenumber":"20",
    "addr:postcode":"sr4 6nq",
    "addr:street":"St Lukes Terrace",
    "iso:country":"GB",
    "sg:address":"20 St Lukes Terrace",
    "sg:city":"Sunderland",
    "sg:classifiers":[
        {
            "category":"Government",
            "subcategory":"Post Office",
            "type":"Public Place"
        }
    ],
    "sg:postcode":"SR4 6NQ",
    "sg:province":"Tyne and Wear",
    "wof:name":"Oxford Street Post Office",
    "wof:placetype":"venue"
},
  "geometry": {"coordinates":[-1.414626,54.908588],"type":"Point"}
}