{
  "type": "Feature",
  "properties": {
    "addr:full":"Sun Lane London Greater London SE3 8UG",
    "addr:postcode":"se3 8ug",
    "addr:street":"Sun Lane",
    "iso:country":"GB",
    "sg:address":"Sun Lane",
    "sg:city":"London",
    "sg:classifiers":[
        {
            "category":"Retail",
            "subcategory":"Auto Repair",
            "type":"Services"
        }
    ],
    "sg:phone":"+44 20 8293 9857",
    "sg:postcode":"SE3 8UG",
    "sg:province":"Greater London",
    "sg:tags":[
        "modification",
        "garage"
    ],
    "wof:name":"Standard Autos",
    "wof:placetype":"venue"
},
  "geometry": {"coordinates":[0.025238,51.475231],"type":"Point"}
}