{
  "type": "Feature",
  "properties": {
    "addr:full":"Po Box 46, Bramhall Stockport Cheshire SK7 1QX",
    "addr:housenumber":"po box 46",
    "addr:postcode":"sk7 1qx",
    "iso:country":"GB",
    "sg:address":"Po Box 46, Bramhall",
    "sg:city":"Stockport",
    "sg:classifiers":[
        {
            "category":"Professional",
            "subcategory":"Management & Consulting",
            "type":"Services"
        }
    ],
    "sg:postcode":"SK7 1QX",
    "sg:province":"Cheshire",
    "sg:tags":[
        "consultant",
        "business"
    ],
    "wof:name":"County Business Services",
    "wof:placetype":"venue"
},
  "geometry": {"coordinates":[-2.1675300598,53.3534011841],"type":"Point"}
}