{
  "type": "Feature",
  "properties": {
    "iso:country":"GB",
    "sg:address":"10 King Street",
    "sg:city":"Sandwich",
    "sg:classifiers":[
        {
            "category":"Food & Beverages",
            "subcategory":"Bakery",
            "type":"Retail Goods"
        }
    ],
    "sg:postcode":"CT13 9BY",
    "sg:province":"Kent",
    "sg:tags":[
        "baker"
    ],
    "wof:name":"Bakers Oven",
    "wof:placetype":"venue"
},
  "geometry": {"coordinates":[1.3396990299,51.2747993469],"type":"Point"}
}