{
  "type": "Feature",
  "properties": {
    "addr:full":"Drug Rehabil Cen, 39-41 Axe Street Barking Essex IG11 7LX",
    "addr:housenumber":"39-41",
    "addr:postcode":"ig11 7lx",
    "addr:street":"Cen;Axe Street",
    "iso:country":"GB",
    "sg:address":"Drug Rehabil Cen, 39-41 Axe Street",
    "sg:city":"Barking",
    "sg:classifiers":[
        {
            "category":"Health Services",
            "subcategory":"Clinic",
            "type":"Services"
        }
    ],
    "sg:phone":"+44 20 8507 8668",
    "sg:postcode":"IG11 7LX",
    "sg:province":"Essex",
    "sg:tags":[
        "abuse",
        "drug"
    ],
    "wof:name":"The Axe Project",
    "wof:placetype":"venue"
},
  "geometry": {"coordinates":[0.081115,51.539101],"type":"Point"}
}