{
  "type": "Feature",
  "properties": {
    "addr:full":"Mortimer House, Luston Leominster Herefordshire HR6 0EB",
    "addr:postcode":"hr6 0eb",
    "iso:country":"GB",
    "sg:address":"Mortimer House, Luston",
    "sg:city":"Leominster",
    "sg:classifiers":[
        {
            "category":"Building & Trades",
            "subcategory":"Construction",
            "type":"Services"
        }
    ],
    "sg:phone":"+44 1568 611613",
    "sg:postcode":"HR6 0EB",
    "sg:province":"Herefordshire",
    "sg:tags":[
        "dry",
        "plastering",
        "plasterers",
        "lining",
        "related",
        "screeders"
    ],
    "wof:name":"R E Parry",
    "wof:placetype":"venue"
},
  "geometry": {"coordinates":[-2.7123188972,52.2772293091],"type":"Point"}
}