{
  "type": "Feature",
  "properties": {
    "iso:country":"GB",
    "sg:address":"5 Europa Way, Martineau Lane",
    "sg:city":"Norwich",
    "sg:classifiers":[
        {
            "category":"Government",
            "subcategory":"Post Office",
            "type":"Public Place"
        }
    ],
    "sg:phone":"+44 1603 666250",
    "sg:postcode":"NR1 2EN",
    "sg:province":"Norfolk",
    "sg:tags":[
        "messenger",
        "courier"
    ],
    "wof:name":"Securicor Omega Sameday",
    "wof:placetype":"venue"
},
  "geometry": {"coordinates":[1.310462,52.614902],"type":"Point"}
}