{
  "type": "Feature",
  "properties": {
    "addr:full":"6 North Avenue, Sutton-in-craven Keighley North Yorkshire BD20 7NN",
    "addr:housenumber":"6",
    "addr:postcode":"bd20 7nn",
    "addr:street":"North Avenue",
    "iso:country":"GB",
    "sg:address":"6 North Avenue, Sutton-in-craven",
    "sg:city":"Keighley",
    "sg:classifiers":[
        {
            "category":"Banks & Credit Unions",
            "subcategory":"Investment Brokerage",
            "type":"Services"
        },
        {
            "category":"Autos & Motor Vehicles",
            "subcategory":"Recreational Vehicle Sales",
            "type":"Retail Goods"
        }
    ],
    "sg:phone":"+44 1535 633083",
    "sg:postcode":"BD20 7NN",
    "sg:province":"North Yorkshire",
    "sg:tags":[
        "caravan",
        "hire",
        "motorhomes",
        "trailer",
        "caravans"
    ],
    "wof:name":"Direct Caravan Services",
    "wof:placetype":"venue"
},
  "geometry": {"coordinates":[-1.993411,53.888454],"type":"Point"}
}