{
  "type": "Feature",
  "properties": {
    "addr:full":"Hulley Road, Charter Way Macclesfield Cheshire SK10 2NX",
    "addr:postcode":"sk10 2nx",
    "addr:street":"Hulley Road Charter Way",
    "iso:country":"GB",
    "sg:address":"Hulley Road, Charter Way",
    "sg:city":"Macclesfield",
    "sg:classifiers":[
        {
            "category":"Wholesale",
            "subcategory":"Construction Materials",
            "type":"Manufacturing & Wholesale Goods"
        },
        {
            "category":"Wholesale",
            "subcategory":"Chemicals & Plastics",
            "type":"Manufacturing & Wholesale Goods"
        }
    ],
    "sg:phone":"+44 1625 888065",
    "sg:postcode":"SK10 2NX",
    "sg:province":"Cheshire",
    "sg:tags":[
        "supplier",
        "product",
        "allied",
        "colour"
    ],
    "wof:name":"Ciba Pigments",
    "wof:placetype":"venue"
},
  "geometry": {"coordinates":[-2.111404,53.269844],"type":"Point"}
}