{
  "type": "Feature",
  "properties": {
    "addr:full":"Unit G13, Rudford Indstl Est, Ford Road, Ford Arundel West Sussex BN18 0BD",
    "addr:housenumber":"g13",
    "addr:postcode":"bn18 0bd",
    "addr:street":"Indstl;Ford Road",
    "iso:country":"GB",
    "sg:address":"Unit G13, Rudford Indstl Est, Ford Road, Ford",
    "sg:city":"Arundel",
    "sg:classifiers":[
        {
            "category":"Government",
            "subcategory":"Post Office",
            "type":"Public Place"
        }
    ],
    "sg:postcode":"BN18 0BD",
    "sg:province":"West Sussex",
    "sg:tags":[
        "messenger",
        "courier"
    ],
    "wof:name":"Panic Link",
    "wof:placetype":"venue"
},
  "geometry": {"coordinates":[-0.580514,50.823326],"type":"Point"}
}