{
  "type": "Feature",
  "properties": {
    "iso:country":"GB",
    "sg:address":"Unit 9 The Courtyard, Cults",
    "sg:city":"Aberdeen",
    "sg:classifiers":[
        {
            "category":"Professional",
            "subcategory":"Art Services",
            "type":"Services"
        }
    ],
    "sg:phone":"+44 1224 869993",
    "sg:postcode":"AB15 9SD",
    "sg:province":"Aberdeen City",
    "sg:tags":[
        "framing"
    ],
    "wof:name":"The Framing Studio",
    "wof:placetype":"venue"
},
  "geometry": {"coordinates":[-2.171671,57.116055],"type":"Point"}
}