{
  "type": "Feature",
  "properties": {
    "addr:full":"15 Green Court Road Swanley Kent BR8 8JG",
    "addr:housenumber":"15",
    "addr:postcode":"br8 8jg",
    "addr:street":"Green Court Road",
    "iso:country":"GB",
    "sg:address":"15 Green Court Road",
    "sg:city":"Swanley",
    "sg:classifiers":[
        {
            "category":"Shopping",
            "subcategory":"Stationery & Office Supplies",
            "type":"Retail Goods"
        }
    ],
    "sg:phone":"+44 1322 613610",
    "sg:postcode":"BR8 8JG",
    "sg:province":"Kent",
    "sg:tags":[
        "equipment"
    ],
    "wof:name":"A B Church (Office Furniture) Ltd.",
    "wof:placetype":"venue"
},
  "geometry": {"coordinates":[0.1637399942,51.3868293762],"type":"Point"}
}