{
  "type": "Feature",
  "properties": {
    "addr:full":"125 High Street Berkhamsted Bedfordshire HP4 2DJ",
    "addr:housenumber":"125",
    "addr:postcode":"hp4 2dj",
    "addr:street":"High Street",
    "iso:country":"GB",
    "sg:address":"125 High Street",
    "sg:city":"Berkhamsted",
    "sg:classifiers":[
        {
            "category":"Real Estate",
            "subcategory":"Real Estate Agent",
            "type":"Services"
        }
    ],
    "sg:phone":"+44 1442 863000",
    "sg:postcode":"HP4 2DJ",
    "sg:province":"Bedfordshire",
    "wof:name":"Caesar Nash & Partners",
    "wof:placetype":"venue"
},
  "geometry": {"coordinates":[-0.562019,51.759388],"type":"Point"}
}