{
  "type": "Feature",
  "properties": {
    "iso:country":"GB",
    "sg:address":"61 Lane Green Road, Codsall",
    "sg:city":"Wolverhampton",
    "sg:classifiers":[
        {
            "category":"Home & Garden",
            "subcategory":"Home Furnishings",
            "type":"Retail Goods"
        },
        {
            "category":"Home & Garden",
            "subcategory":"Carpets & Floor Coverings",
            "type":"Retail Goods"
        }
    ],
    "sg:phone":"+44 1902 843138",
    "sg:postcode":"WV8 1LR",
    "sg:province":"Shropshire",
    "sg:tags":[
        "fitting",
        "rug",
        "matting",
        "carpets"
    ],
    "wof:name":"Victor Edward Dutton",
    "wof:placetype":"venue"
},
  "geometry": {"coordinates":[-2.1770009995,52.6218910217],"type":"Point"}
}