{
  "type": "Feature",
  "properties": {
    "addr:full":"Windsor Rd Gerrards Cross Buckinghamshire SL9 8SS",
    "addr:postcode":"sl9 8ss",
    "addr:street":"Windsor Rd",
    "iso:country":"GB",
    "sg:address":"Windsor Rd",
    "sg:city":"Gerrards Cross",
    "sg:classifiers":[
        {
            "category":"Retail",
            "subcategory":"Funeral Services",
            "type":"Services"
        }
    ],
    "sg:phone":"+44 1753 662426",
    "sg:postcode":"SL9 8SS",
    "sg:province":"Buckinghamshire",
    "sg:tags":[
        "cemetery",
        "crematorium"
    ],
    "wof:name":"Buckinghamshire County Council",
    "wof:placetype":"venue"
},
  "geometry": {"coordinates":[-0.576564014,51.572063446],"type":"Point"}
}