{
  "type": "Feature",
  "properties": {
    "iso:country":"GB",
    "sg:address":"Easthill Farm, Lochfoot",
    "sg:city":"Dumfries",
    "sg:classifiers":[
        {
            "category":"Building & Trades",
            "subcategory":"Plumbing",
            "type":"Services"
        },
        {
            "category":"Farming",
            "subcategory":"Farm",
            "type":"Manufacturing & Wholesale Goods"
        }
    ],
    "sg:phone":"+44 1387 730381",
    "sg:postcode":"DG2 8NQ",
    "sg:province":"Dumfries and Galloway",
    "sg:tags":[
        "mixed",
        "plumber",
        "heating",
        "crop"
    ],
    "wof:name":"Hugh G Shuttleworth",
    "wof:placetype":"venue"
},
  "geometry": {"coordinates":[-3.723508,55.045643],"type":"Point"}
}