{
  "type": "Feature",
  "properties": {
    "iso:country":"GB",
    "sg:address":"Marygate 287a Didsbury Road, Heaton Mersey",
    "sg:city":"Stockport",
    "sg:classifiers":[
        {
            "category":"Organizations",
            "subcategory":"Non-profit Organization",
            "type":"Services"
        }
    ],
    "sg:phone":"+44 161 431 8296",
    "sg:postcode":"SK4 3HE",
    "sg:province":"Cheshire",
    "sg:tags":[
        "organisation",
        "voluntary",
        "charity"
    ],
    "wof:name":"Catholic Childrens Rescue Society",
    "wof:placetype":"venue"
},
  "geometry": {"coordinates":[-2.200292,53.413235],"type":"Point"}
}