{
  "type": "Feature",
  "properties": {
    "addr:full":"Trinity Hall Farm, Chippenham Road Newmarket Cambridgeshire CB8 8SN",
    "addr:postcode":"cb8 8sn",
    "addr:street":"Chippenham Road",
    "iso:country":"GB",
    "sg:address":"Trinity Hall Farm, Chippenham Road",
    "sg:city":"Newmarket",
    "sg:classifiers":[
        {
            "category":"Farming",
            "subcategory":"Livestock Farm",
            "type":"Manufacturing & Wholesale Goods"
        }
    ],
    "sg:phone":"+44 1638 500816",
    "sg:postcode":"CB8 8SN",
    "sg:province":"Cambridgeshire",
    "sg:tags":[
        "others"
    ],
    "wof:name":"E F Saltmarsh & Sons",
    "wof:placetype":"venue"
},
  "geometry": {"coordinates":[0.399166,52.249817],"type":"Point"}
}