{
  "type": "Feature",
  "properties": {
    "addr:full":"Chasewaree Industrial Estate, High Street, Burntwood Walsall Staffordshire WS7 8XD",
    "addr:postcode":"ws7 8xd",
    "addr:street":"High Street",
    "iso:country":"GB",
    "sg:address":"Chasewaree Industrial Estate, High Street, Burntwood",
    "sg:city":"Walsall",
    "sg:classifiers":[
        {
            "category":"Building & Trades",
            "subcategory":"Cleaning & Sanitation",
            "type":"Services"
        }
    ],
    "sg:phone":"+44 1543 674675",
    "sg:postcode":"WS7 8XD",
    "sg:province":"Staffordshire",
    "sg:tags":[
        "toilet",
        "portable"
    ],
    "wof:name":"Restroom Rentals",
    "wof:placetype":"venue"
},
  "geometry": {"coordinates":[-1.9380099773,52.676700592],"type":"Point"}
}