{
  "type": "Feature",
  "properties": {
    "iso:country":"GB",
    "sg:address":"P O Box 6",
    "sg:city":"Cirencester",
    "sg:classifiers":[
        {
            "category":"Professional",
            "subcategory":"Management & Consulting",
            "type":"Services"
        }
    ],
    "sg:phone":"+44 1285 644330",
    "sg:postcode":"GL7 7YD",
    "sg:province":"Gloucestershire",
    "sg:tags":[
        "marketing",
        "consultant"
    ],
    "wof:name":"Balance Marketing & Promotions",
    "wof:placetype":"venue"
},
  "geometry": {"coordinates":[-2.015249,51.76281],"type":"Point"}
}