{
  "type": "Feature",
  "properties": {
    "iso:country":"GB",
    "sg:address":"4 Apex Court, Selvage Lane",
    "sg:city":"London",
    "sg:classifiers":[
        {
            "category":"Professional",
            "type":"Services"
        }
    ],
    "sg:postcode":"NW7 3JU",
    "sg:province":"Greater London",
    "sg:tags":[
        "repair",
        "tech",
        "maintenance"
    ],
    "wof:name":"Generics Warehouse Ltd.",
    "wof:placetype":"venue"
},
  "geometry": {"coordinates":[-0.255394,51.621719],"type":"Point"}
}