{
  "type": "Feature",
  "properties": {
    "iso:country":"GB",
    "sg:address":"Unit, 511, 31 Clerkenwell Close",
    "sg:city":"Clerkenwell",
    "sg:classifiers":[
        {
            "category":"Military Area",
            "subcategory":"Army Base",
            "type":"Public Place"
        }
    ],
    "sg:phone":"+44 20 7608 1100",
    "sg:postcode":"EC1R 0AT",
    "sg:province":"Greater London",
    "sg:tags":[
        "button",
        "buckle"
    ],
    "wof:name":"Linda Jolly",
    "wof:placetype":"venue"
},
  "geometry": {"coordinates":[-0.106765,51.524712],"type":"Point"}
}