{
  "type": "Feature",
  "properties": {
    "addr:full":"49 Aberdeen Walk Scarborough North Yorkshire YO11 1BD",
    "addr:housenumber":"49",
    "addr:postcode":"yo11 1bd",
    "addr:street":"Aberdeen Walk",
    "iso:country":"GB",
    "sg:address":"49 Aberdeen Walk",
    "sg:city":"Scarborough",
    "sg:classifiers":[
        {
            "category":"Real Estate",
            "subcategory":"Real Estate Agent",
            "type":"Services"
        }
    ],
    "sg:phone":"+44 1723 363565",
    "sg:postcode":"YO11 1BD",
    "sg:province":"North Yorkshire",
    "wof:name":"Ellis Colin Estate Agents",
    "wof:placetype":"venue"
},
  "geometry": {"coordinates":[-0.4035080075,54.2832450867],"type":"Point"}
}