{
  "type": "Feature",
  "properties": {
    "addr:full":"5 Acton St Bloomsbury Greater London WC1X 9LX",
    "addr:housenumber":"5",
    "addr:postcode":"wc1x 9lx",
    "addr:street":"Acton St",
    "iso:country":"GB",
    "sg:address":"5 Acton St",
    "sg:city":"Bloomsbury",
    "sg:classifiers":[
        {
            "category":"Freight",
            "type":"Transportation"
        }
    ],
    "sg:phone":"+44 20 7833 5686",
    "sg:postcode":"WC1X 9LX",
    "sg:province":"Greater London",
    "sg:tags":[
        "forwarders"
    ],
    "wof:name":"Transafrica Cargo Services",
    "wof:placetype":"venue"
},
  "geometry": {"coordinates":[-0.1160390005,51.5286941528],"type":"Point"}
}