{
  "type": "Feature",
  "properties": {
    "iso:country":"GB",
    "sg:address":"2 Longfield Centre, Prestwich",
    "sg:city":"Manchester",
    "sg:classifiers":[
        {
            "category":"Travel",
            "subcategory":"Travel Agent",
            "type":"Entertainment"
        }
    ],
    "sg:phone":"+44 161 773 1003",
    "sg:postcode":"M25 1AY",
    "sg:province":"Greater Manchester",
    "wof:name":"Going Places Leisure Travel",
    "wof:placetype":"venue"
},
  "geometry": {"coordinates":[-2.285659,53.533314],"type":"Point"}
}