{
  "type": "Feature",
  "properties": {
    "addr:full":"Pant Side, Newbridge Newport Blaenau Gwent NP11 5GD",
    "addr:postcode":"np11 5gd",
    "addr:street":"Pant Side",
    "iso:country":"GB",
    "sg:address":"Pant Side, Newbridge",
    "sg:city":"Newport",
    "sg:classifiers":[
        {
            "category":"Organizations",
            "subcategory":"Community Association",
            "type":"Services"
        },
        {
            "category":"Organizations",
            "subcategory":"Membership Organization",
            "type":"Services"
        }
    ],
    "sg:phone":"+44 1495 243284",
    "sg:postcode":"NP11 5GD",
    "sg:province":"Blaenau Gwent",
    "sg:tags":[
        "club",
        "social"
    ],
    "wof:name":"PANT SOCIAL CLUB",
    "wof:placetype":"venue"
},
  "geometry": {"coordinates":[-3.138525,51.663506],"type":"Point"}
}