{
  "type": "Feature",
  "properties": {
    "addr:full":"10 Drake Walk, Atlantic Wharf Cardiff Cardiff CF1 5AN",
    "addr:housenumber":"10",
    "addr:postcode":"cf1 5an",
    "addr:street":"Drake Walk",
    "iso:country":"GB",
    "sg:address":"10 Drake Walk, Atlantic Wharf",
    "sg:city":"Cardiff",
    "sg:classifiers":[
        {
            "category":"Transit Center",
            "subcategory":"Passenger",
            "type":"Transportation"
        }
    ],
    "sg:phone":"+44 29 2049 9797",
    "sg:postcode":"CF1 5AN",
    "sg:province":"Cardiff",
    "sg:tags":[
        "ship",
        "broker"
    ],
    "wof:name":"Cardiff Ship Management & Services Ltd",
    "wof:placetype":"venue"
},
  "geometry": {"coordinates":[-3.1644999981,51.473690033],"type":"Point"}
}