{
  "type": "Feature",
  "properties": {
    "addr:full":"Cartway Road, Cartway Cove Port Isaac Cornwall PL29 3SH",
    "addr:postcode":"pl29 3sh",
    "addr:street":"Cartway Road Cartway Cove",
    "iso:country":"GB",
    "sg:address":"Cartway Road, Cartway Cove",
    "sg:city":"Port Isaac",
    "sg:classifiers":[
        {
            "category":"Education",
            "subcategory":"Special Training",
            "type":"Public Place"
        }
    ],
    "sg:postcode":"PL29 3SH",
    "sg:province":"Cornwall",
    "sg:tags":[
        "diving",
        "school"
    ],
    "wof:name":"Sub Aqua World",
    "wof:placetype":"venue"
},
  "geometry": {"coordinates":[-4.828199,50.592339],"type":"Point"}
}