{
  "type": "Feature",
  "properties": {
    "iso:country":"GB",
    "sg:address":"50 Hasse Rd, Soham",
    "sg:city":"Ely",
    "sg:classifiers":[
        {
            "category":"Farming",
            "subcategory":"Farm",
            "type":"Manufacturing & Wholesale Goods"
        }
    ],
    "sg:postcode":"CB7 5UW",
    "sg:province":"Cambridgeshire",
    "sg:tags":[
        "mixed",
        "crop"
    ],
    "wof:name":"Crisp,D E,",
    "wof:placetype":"venue"
},
  "geometry": {"coordinates":[0.3447859883,52.3466072083],"type":"Point"}
}