{
  "type": "Feature",
  "properties": {
    "iso:country":"GB",
    "sg:address":"King Charles House, Park End",
    "sg:city":"Oxford",
    "sg:classifiers":[
        {
            "category":"Utilities",
            "subcategory":"Natural Gas",
            "type":"Services"
        }
    ],
    "sg:postcode":"OX1 1JD",
    "sg:province":"Oxfordshire",
    "sg:tags":[
        "supplier"
    ],
    "wof:name":"Enron Direct Ltd.",
    "wof:placetype":"venue"
},
  "geometry": {"coordinates":[-1.266109,51.752602],"type":"Point"}
}