{
  "type": "Feature",
  "properties": {
    "iso:country":"GB",
    "sg:address":"Manor Place, Wellington Road, The Industrial Estate",
    "sg:city":"York",
    "sg:classifiers":[
        {
            "category":"Manufacturing",
            "subcategory":"Chemicals & Compounds",
            "type":"Manufacturing & Wholesale Goods"
        },
        {
            "category":"Home & Garden",
            "subcategory":"Garden Supply",
            "type":"Retail Goods"
        }
    ],
    "sg:phone":"+44 1759 302545",
    "sg:postcode":"YO42 1DN",
    "sg:province":"East Riding of Yorkshire",
    "sg:tags":[
        "fertiliser"
    ],
    "wof:name":"Phosyn Plc",
    "wof:placetype":"venue"
},
  "geometry": {"coordinates":[-0.785522,53.984394],"type":"Point"}
}