{
  "type": "Feature",
  "properties": {
    "iso:country":"GB",
    "sg:address":"27 High West Street",
    "sg:city":"Dorchester",
    "sg:classifiers":[
        {
            "category":"Arts & Performance",
            "subcategory":"Art Gallery",
            "type":"Entertainment"
        },
        {
            "category":"Shopping",
            "subcategory":"Crafts & Fabrics",
            "type":"Retail Goods"
        }
    ],
    "sg:phone":"+44 1305 267917",
    "sg:postcode":"DT1 1UP",
    "sg:province":"Dorset",
    "sg:tags":[
        "material",
        "sale",
        "supply"
    ],
    "wof:name":"Frank Herring & Sons",
    "wof:placetype":"venue"
},
  "geometry": {"coordinates":[-2.439951,50.715004],"type":"Point"}
}