{
  "type": "Feature",
  "properties": {
    "addr:full":"19 Hinton Avenue Cambridge Cambridgeshire CB1 7AR",
    "addr:housenumber":"19",
    "addr:postcode":"cb1 7ar",
    "addr:street":"Hinton Avenue",
    "iso:country":"GB",
    "sg:address":"19 Hinton Avenue",
    "sg:city":"Cambridge",
    "sg:classifiers":[
        {
            "category":"Retail",
            "subcategory":"Driving School",
            "type":"Services"
        }
    ],
    "sg:phone":"+44 1223 244155",
    "sg:postcode":"CB1 7AR",
    "sg:province":"Cambridgeshire",
    "wof:name":"Coleridge Driving School",
    "wof:placetype":"venue"
},
  "geometry": {"coordinates":[0.1500860006,52.1864128113],"type":"Point"}
}