{
  "type": "Feature",
  "properties": {
    "iso:country":"GB",
    "sg:address":"16 Spring Mount",
    "sg:city":"Harrogate",
    "sg:classifiers":[
        {
            "category":"Building & Trades",
            "subcategory":"Landscaping Services",
            "type":"Services"
        }
    ],
    "sg:phone":"+44 1423 505550",
    "sg:postcode":"HG1 2HX",
    "sg:province":"North Yorkshire",
    "sg:tags":[
        "gardening"
    ],
    "wof:name":"Norman Hullah",
    "wof:placetype":"venue"
},
  "geometry": {"coordinates":[-1.544606,53.998493],"type":"Point"}
}