{
  "type": "Feature",
  "properties": {
    "iso:country":"GB",
    "sg:address":"Europa Way",
    "sg:city":"Lichfield",
    "sg:classifiers":[
        {
            "category":"Building & Trades",
            "subcategory":"Construction",
            "type":"Services"
        }
    ],
    "sg:phone":"+44 1543 414223",
    "sg:postcode":"WS14 9TY",
    "sg:province":"Staffordshire",
    "sg:tags":[
        "joinery"
    ],
    "wof:name":"Hermes Joinery",
    "wof:placetype":"venue"
},
  "geometry": {"coordinates":[-1.797555,52.684589],"type":"Point"}
}