{
  "type": "Feature",
  "properties": {
    "addr:full":"The Old Gasworks, The Lerburne Wedmore Somerset BS28 4ED",
    "addr:postcode":"bs28 4ed",
    "iso:country":"GB",
    "sg:address":"The Old Gasworks, The Lerburne",
    "sg:city":"Wedmore",
    "sg:classifiers":[
        {
            "category":"Manufacturing",
            "subcategory":"Signs",
            "type":"Manufacturing & Wholesale Goods"
        }
    ],
    "sg:phone":"+44 1934 712888",
    "sg:postcode":"BS28 4ED",
    "sg:province":"Somerset",
    "sg:tags":[
        "nameplate"
    ],
    "wof:name":"Ideal Signs",
    "wof:placetype":"venue"
},
  "geometry": {"coordinates":[-2.8101599216,51.2276306152],"type":"Point"}
}