{
  "type": "Feature",
  "properties": {
    "iso:country":"GB",
    "sg:address":"23 Orchard Road",
    "sg:city":"Bromley",
    "sg:classifiers":[
        {
            "category":"Travel",
            "subcategory":"Hotels & Motels",
            "type":"Entertainment"
        }
    ],
    "sg:phone":"+44 20 8460 1795",
    "sg:postcode":"BR1 2PR",
    "sg:province":"Kent",
    "wof:name":"Grianan Hotel",
    "wof:placetype":"venue"
},
  "geometry": {"coordinates":[0.0310880002,51.4098930359],"type":"Point"}
}