{
  "type": "Feature",
  "properties": {
    "iso:country":"GB",
    "sg:address":"16 Calderglen Avenue, The Elms,blantyre",
    "sg:city":"Glasgow",
    "sg:classifiers":[
        {
            "category":"Communications",
            "type":"Services"
        }
    ],
    "sg:postcode":"G72 9UN",
    "sg:province":"South Lanarkshire",
    "sg:tags":[
        "data",
        "network"
    ],
    "wof:name":"Process Data Ltd",
    "wof:placetype":"venue"
},
  "geometry": {"coordinates":[-4.103484,55.808128],"type":"Point"}
}