{
  "type": "Feature",
  "properties": {
    "addr:full":"376a Ringwood Rd Poole Dorset BH12 3LT",
    "addr:housenumber":"376a",
    "addr:postcode":"bh12 3lt",
    "addr:street":"Ringwood Rd",
    "iso:country":"GB",
    "sg:address":"376a Ringwood Rd",
    "sg:city":"Poole",
    "sg:classifiers":[
        {
            "category":"Manufacturing",
            "subcategory":"Wood Products",
            "type":"Manufacturing & Wholesale Goods"
        }
    ],
    "sg:phone":"+44 1202 739980",
    "sg:postcode":"BH12 3LT",
    "sg:province":"Dorset",
    "sg:tags":[
        "maker",
        "cabinet"
    ],
    "wof:name":"Kreative Kitchens Ltd",
    "wof:placetype":"venue"
},
  "geometry": {"coordinates":[-1.9504569769,50.7369651794],"type":"Point"}
}