{
  "type": "Feature",
  "properties": {
    "addr:full":"Seafarers Centre, Duke St Birkenhead Merseyside CH41 8BT",
    "addr:postcode":"ch41 8bt",
    "addr:street":"Duke St",
    "iso:country":"GB",
    "sg:address":"Seafarers Centre, Duke St",
    "sg:city":"Birkenhead",
    "sg:classifiers":[
        {
            "category":"Organizations",
            "subcategory":"Non-profit Organization",
            "type":"Services"
        }
    ],
    "sg:phone":"+44 151 653 0903",
    "sg:postcode":"CH41 8BT",
    "sg:province":"Merseyside",
    "sg:tags":[
        "organisation",
        "voluntary",
        "charity"
    ],
    "wof:name":"British & International Sailors Society",
    "wof:placetype":"venue"
},
  "geometry": {"coordinates":[-3.0254890919,53.3925666809],"type":"Point"}
}