{
  "type": "Feature",
  "properties": {
    "addr:full":"192 Argyll Street Dunoon Argyll and Bute PA23 7HA",
    "addr:housenumber":"192",
    "addr:postcode":"pa23 7ha",
    "addr:street":"Argyll Street",
    "iso:country":"GB",
    "sg:address":"192 Argyll Street",
    "sg:city":"Dunoon",
    "sg:classifiers":[
        {
            "category":"Shopping",
            "subcategory":"Department Store",
            "type":"Retail Goods"
        },
        {
            "category":"Shopping",
            "subcategory":"Clothing, Apparel, & Fashions",
            "type":"Retail Goods"
        }
    ],
    "sg:phone":"+44 1369 702355",
    "sg:postcode":"PA23 7HA",
    "sg:province":"Argyll and Bute",
    "sg:tags":[
        "departmental",
        "menswear"
    ],
    "wof:name":"Wright's",
    "wof:placetype":"venue"
},
  "geometry": {"coordinates":[-4.927538,55.950935],"type":"Point"}
}