{
  "type": "Feature",
  "properties": {
    "iso:country":"GB",
    "sg:address":"23 Yewdale Rd",
    "sg:city":"Wigan",
    "sg:classifiers":[
        {
            "category":"Government",
            "subcategory":"Post Office",
            "type":"Public Place"
        }
    ],
    "sg:postcode":"WN4 0EA",
    "sg:province":"Lancashire",
    "wof:name":"Collinson,M,",
    "wof:placetype":"venue"
},
  "geometry": {"coordinates":[-2.649098,53.508438],"type":"Point"}
}