{
  "type": "Feature",
  "properties": {
    "iso:country":"GB",
    "sg:address":"18 Drake Road",
    "sg:city":"Newport",
    "sg:classifiers":[
        {
            "category":"Building & Trades",
            "subcategory":"Construction",
            "type":"Services"
        }
    ],
    "sg:phone":"+44 1983 522997",
    "sg:postcode":"PO30 1EQ",
    "sg:province":"Isle of Wight",
    "sg:tags":[
        "decorator",
        "painter"
    ],
    "wof:name":"D Barnes Decorator",
    "wof:placetype":"venue"
},
  "geometry": {"coordinates":[-1.296109,50.695557],"type":"Point"}
}