{
  "type": "Feature",
  "properties": {
    "iso:country":"GB",
    "sg:address":"Tremains Road",
    "sg:city":"Bridgend",
    "sg:classifiers":[
        {
            "category":"Shopping",
            "subcategory":"Department Store",
            "type":"Retail Goods"
        }
    ],
    "sg:postcode":"CF31 1TZ",
    "sg:province":"Bridgend",
    "wof:name":"T Wright",
    "wof:placetype":"venue"
},
  "geometry": {"coordinates":[-3.571944,51.505058],"type":"Point"}
}