{
  "type": "Feature",
  "properties": {
    "iso:country":"GB",
    "sg:address":"132 Chaddesden Park Road",
    "sg:city":"Derby",
    "sg:classifiers":[
        {
            "category":"Professional",
            "type":"Services"
        },
        {
            "category":"Building & Trades",
            "subcategory":"Cleaning & Sanitation",
            "type":"Services"
        }
    ],
    "sg:phone":"+44 1332 670251",
    "sg:postcode":"DE21 6HG",
    "sg:province":"Derbyshire",
    "sg:tags":[
        "dry",
        "control",
        "damp",
        "rot",
        "preservation"
    ],
    "wof:name":"Preston Preservation",
    "wof:placetype":"venue"
},
  "geometry": {"coordinates":[-1.4404859543,52.9311599731],"type":"Point"}
}