{
  "type": "Feature",
  "properties": {
    "iso:country":"GB",
    "sg:address":"Unit 7, Delaware Drive, Tongwell",
    "sg:city":"Milton Keynes",
    "sg:classifiers":[
        {
            "category":"Food & Beverages",
            "subcategory":"Liquor & Beverages",
            "type":"Retail Goods"
        },
        {
            "category":"Wholesale",
            "subcategory":"Vending Machines",
            "type":"Manufacturing & Wholesale Goods"
        }
    ],
    "sg:phone":"+44 1908 210828",
    "sg:postcode":"MK15 8HD",
    "sg:province":"Buckinghamshire",
    "sg:tags":[
        "drink",
        "soft",
        "sale",
        "manufacturers"
    ],
    "sg:website":"http://www.coca-cola.com",
    "wof:name":"Coca Cola Enterprises Ltd",
    "wof:placetype":"venue"
},
  "geometry": {"coordinates":[-0.735904,52.06498],"type":"Point"}
}