{
  "type": "Feature",
  "properties": {
    "iso:country":"GB",
    "sg:address":"Highgrove Farm Estate, Pinvin",
    "sg:city":"Pershore",
    "sg:classifiers":[
        {
            "category":"Shopping",
            "subcategory":"Gifts & Souvenirs",
            "type":"Retail Goods"
        }
    ],
    "sg:phone":"+44 1905 381061",
    "sg:postcode":"WR10 2LF",
    "sg:province":"Worcestershire",
    "sg:tags":[
        "giftware"
    ],
    "wof:name":"Bowbrook Studios Ltd.",
    "wof:placetype":"venue"
},
  "geometry": {"coordinates":[-2.070859,52.134167],"type":"Point"}
}