{
  "type": "Feature",
  "properties": {
    "iso:country":"GB",
    "sg:address":"Colchester Road, Lawford",
    "sg:city":"Manningtree",
    "sg:classifiers":[
        {
            "category":"Community Center",
            "type":"Public Place"
        },
        {
            "category":"Government",
            "subcategory":"Office",
            "type":"Public Place"
        }
    ],
    "sg:postcode":"CO11 2BN",
    "sg:province":"Essex",
    "sg:tags":[
        "recreation",
        "local",
        "leisure",
        "centre"
    ],
    "wof:name":"Manningtree Sports Hall",
    "wof:placetype":"venue"
},
  "geometry": {"coordinates":[1.042236,51.938225],"type":"Point"}
}