{
  "type": "Feature",
  "properties": {
    "addr:full":"7 Marlborough Close Benfleet Essex SS7 4JA",
    "addr:housenumber":"7",
    "addr:postcode":"ss7 4ja",
    "addr:street":"Marlborough Close",
    "iso:country":"GB",
    "sg:address":"7 Marlborough Close",
    "sg:city":"Benfleet",
    "sg:classifiers":[
        {
            "category":"Building & Trades",
            "subcategory":"Construction",
            "type":"Services"
        }
    ],
    "sg:phone":"+44 1268 752940",
    "sg:postcode":"SS7 4JA",
    "sg:province":"Essex",
    "sg:tags":[
        "heating",
        "contractor"
    ],
    "wof:name":"Taymour Heating & Plumbing",
    "wof:placetype":"venue"
},
  "geometry": {"coordinates":[0.5613769889,51.5743865967],"type":"Point"}
}