{
  "type": "Feature",
  "properties": {
    "addr:full":"101 Canterbury Street Gillingham Kent ME7 5TS",
    "addr:housenumber":"101",
    "addr:postcode":"me7 5ts",
    "addr:street":"Canterbury Street",
    "iso:country":"GB",
    "sg:address":"101 Canterbury Street",
    "sg:city":"Gillingham",
    "sg:classifiers":[
        {
            "category":"Restaurant",
            "type":"Food & Drink"
        }
    ],
    "sg:phone":"+44 1634 855888",
    "sg:postcode":"ME7 5TS",
    "sg:province":"Kent",
    "sg:tags":[
        "indian",
        "-"
    ],
    "wof:name":"New East India Tandoori Restaurant",
    "wof:placetype":"venue"
},
  "geometry": {"coordinates":[0.5442609787,51.3846435547],"type":"Point"}
}