{
  "type": "Feature",
  "properties": {
    "addr:full":"157 Moorgate Rd Leeds North Yorkshire LS25 7ET",
    "addr:housenumber":"157",
    "addr:postcode":"ls25 7et",
    "addr:street":"Moorgate Rd",
    "iso:country":"GB",
    "sg:address":"157 Moorgate Rd",
    "sg:city":"Leeds",
    "sg:classifiers":[
        {
            "category":"Food & Beverages",
            "subcategory":"Supermarket",
            "type":"Retail Goods"
        }
    ],
    "sg:phone":"+44 113 286 0026",
    "sg:postcode":"LS25 7ET",
    "sg:province":"North Yorkshire",
    "wof:name":"Jackson Of Kippax",
    "wof:placetype":"venue"
},
  "geometry": {"coordinates":[-1.374161005,53.774974823],"type":"Point"}
}