{
  "type": "Feature",
  "properties": {
    "addr:full":"Mountjoy Research Centre, University Science Park Durham Durham DH1 3SW",
    "addr:postcode":"dh1 3sw",
    "addr:street":"Science Park",
    "iso:country":"GB",
    "sg:address":"Mountjoy Research Centre, University Science Park",
    "sg:city":"Durham",
    "sg:classifiers":[
        {
            "category":"Professional",
            "subcategory":"Engineering",
            "type":"Services"
        }
    ],
    "sg:phone":"+44 191 384 3366",
    "sg:postcode":"DH1 3SW",
    "sg:province":"Durham",
    "sg:tags":[
        "design",
        "engineer"
    ],
    "wof:name":"Oxford Geotechnica International (U K) Ltd.",
    "wof:placetype":"venue"
},
  "geometry": {"coordinates":[-1.574608,54.777534],"type":"Point"}
}