{
  "type": "Feature",
  "properties": {
    "iso:country":"GB",
    "sg:address":"Whatlington",
    "sg:city":"Battle",
    "sg:classifiers":[
        {
            "category":"Farming",
            "subcategory":"Vineyard",
            "type":"Manufacturing & Wholesale Goods"
        }
    ],
    "sg:postcode":"TN33 0ND",
    "sg:province":"East Sussex",
    "wof:name":"Leeford Vineyards",
    "wof:placetype":"venue"
},
  "geometry": {"coordinates":[0.4890249968,50.9146156311],"type":"Point"}
}