{
  "type": "Feature",
  "properties": {
    "addr:full":"1 Upside Holmesdale Rd Reigate Surrey RH2 0BA",
    "addr:housenumber":"1",
    "addr:postcode":"rh2 0ba",
    "addr:street":"Upside Holmesdale Rd",
    "iso:country":"GB",
    "sg:address":"1 Upside Holmesdale Rd",
    "sg:city":"Reigate",
    "sg:classifiers":[
        {
            "category":"Taxi",
            "type":"Transportation"
        }
    ],
    "sg:phone":"+44 1737 222333",
    "sg:postcode":"RH2 0BA",
    "sg:province":"Surrey",
    "sg:tags":[
        "mini",
        "cab"
    ],
    "wof:name":"Reigate Car Hire",
    "wof:placetype":"venue"
},
  "geometry": {"coordinates":[-0.2049289942,51.2423667908],"type":"Point"}
}