{
  "type": "Feature",
  "properties": {
    "iso:country":"GB",
    "sg:address":"Sunnyside, Gainsborough Road",
    "sg:city":"Gainsborough",
    "sg:classifiers":[
        {
            "category":"Home & Garden",
            "subcategory":"Household Appliances",
            "type":"Retail Goods"
        }
    ],
    "sg:phone":"+44 1427 788876",
    "sg:postcode":"DN21 5JX",
    "sg:province":"Lincolnshire",
    "sg:tags":[
        "electrical"
    ],
    "wof:name":"T J Percival",
    "wof:placetype":"venue"
},
  "geometry": {"coordinates":[-0.7441800237,53.3340530396],"type":"Point"}
}