{
  "type": "Feature",
  "properties": {
    "addr:full":"24 Peascod Street Windsor Berkshire SL4 1DU",
    "addr:housenumber":"24",
    "addr:postcode":"sl4 1du",
    "addr:street":"Peascod Street",
    "iso:country":"GB",
    "sg:address":"24 Peascod Street",
    "sg:city":"Windsor",
    "sg:classifiers":[
        {
            "category":"Shopping",
            "subcategory":"Clothing, Apparel, & Fashions",
            "type":"Retail Goods"
        }
    ],
    "sg:postcode":"SL4 1DU",
    "sg:province":"Berkshire",
    "sg:tags":[
        "shop"
    ],
    "wof:name":"Morgan",
    "wof:placetype":"venue"
},
  "geometry": {"coordinates":[-0.609296,51.481682],"type":"Point"}
}