{
  "type": "Feature",
  "properties": {
    "addr:full":"62 Delph Lane, Delph Oldham Lancashire OL3 5HX",
    "addr:housenumber":"62",
    "addr:postcode":"ol3 5hx",
    "addr:street":"Delph Lane",
    "iso:country":"GB",
    "sg:address":"62 Delph Lane, Delph",
    "sg:city":"Oldham",
    "sg:classifiers":[
        {
            "category":"Manufacturing",
            "subcategory":"Tools & Machinery",
            "type":"Manufacturing & Wholesale Goods"
        },
        {
            "category":"Military Area",
            "subcategory":"Coast Guard Base",
            "type":"Public Place"
        },
        {
            "category":"Retail",
            "subcategory":"Auto Repair",
            "type":"Services"
        }
    ],
    "sg:phone":"+44 1457 871387",
    "sg:postcode":"OL3 5HX",
    "sg:province":"Lancashire",
    "sg:tags":[
        "body",
        "car",
        "supplier",
        "meter",
        "manufacturer"
    ],
    "wof:name":"Saddleworth Meter Services",
    "wof:placetype":"venue"
},
  "geometry": {"coordinates":[-2.0203309059,53.570728302],"type":"Point"}
}