{
  "type": "Feature",
  "properties": {
    "iso:country":"GB",
    "sg:address":"Huddersfield Rd",
    "sg:city":"Mirfield",
    "sg:classifiers":[
        {
            "category":"Bars & Pubs",
            "type":"Food & Drink"
        }
    ],
    "sg:phone":"+44 1924 493079",
    "sg:postcode":"WF14 9DL",
    "sg:province":"West Yorkshire",
    "sg:tags":[
        "pubs",
        "inn"
    ],
    "wof:name":"Pear Tree Inn",
    "wof:placetype":"venue"
},
  "geometry": {"coordinates":[-1.712044,53.679981],"type":"Point"}
}