{
  "type": "Feature",
  "properties": {
    "iso:country":"GB",
    "sg:address":"Top House Farm, Shackerstone",
    "sg:city":"Nuneaton",
    "sg:classifiers":[
        {
            "category":"Shopping",
            "subcategory":"Crafts & Fabrics",
            "type":"Retail Goods"
        }
    ],
    "sg:postcode":"CV13 0BT",
    "sg:province":"Leicestershire",
    "sg:tags":[
        "supplier"
    ],
    "wof:name":"W M Oldham",
    "wof:placetype":"venue"
},
  "geometry": {"coordinates":[-1.41956,52.640652],"type":"Point"}
}