{
  "type": "Feature",
  "properties": {
    "addr:full":"Unit 8 Newall Hall Park Otley North Yorkshire LS21 2RD",
    "addr:housenumber":"unit 8",
    "addr:postcode":"ls21 2rd",
    "addr:street":"Newall Hall Park",
    "iso:country":"GB",
    "sg:address":"Unit 8 Newall Hall Park",
    "sg:city":"Otley",
    "sg:classifiers":[
        {
            "category":"Wholesale",
            "subcategory":"Non-durable Goods",
            "type":"Manufacturing & Wholesale Goods"
        }
    ],
    "sg:phone":"+44 1943 461800",
    "sg:postcode":"LS21 2RD",
    "sg:province":"North Yorkshire",
    "sg:tags":[
        "animal",
        "by-product"
    ],
    "wof:name":"Elite Foods Ltd.",
    "wof:placetype":"venue"
},
  "geometry": {"coordinates":[-1.700049,53.912285],"type":"Point"}
}