{
  "type": "Feature",
  "properties": {
    "addr:full":"9 Notre Dame Mews Northampton Northamptonshire NN1 2BG",
    "addr:housenumber":"9",
    "addr:postcode":"nn1 2bg",
    "addr:street":"Notre Dame Mews",
    "iso:country":"GB",
    "sg:address":"9 Notre Dame Mews",
    "sg:city":"Northampton",
    "sg:classifiers":[
        {
            "category":"Professional",
            "subcategory":"Lawyer & Legal Services",
            "type":"Services"
        }
    ],
    "sg:postcode":"NN1 2BG",
    "sg:province":"Northamptonshire",
    "sg:tags":[
        "solicitor"
    ],
    "wof:name":"Borneo Martell & Partners",
    "wof:placetype":"venue"
},
  "geometry": {"coordinates":[-0.892125,52.239891],"type":"Point"}
}