{
  "type": "Feature",
  "properties": {
    "iso:country":"GB",
    "sg:address":"23 Eastfield Crescent, Laughton",
    "sg:city":"Sheffield",
    "sg:classifiers":[
        {
            "category":"Wholesale",
            "subcategory":"Meat",
            "type":"Manufacturing & Wholesale Goods"
        }
    ],
    "sg:phone":"+44 1909 563509",
    "sg:postcode":"S25 1YT",
    "sg:province":"South Yorkshire",
    "sg:tags":[
        "-"
    ],
    "wof:name":"Temple Meats",
    "wof:placetype":"venue"
},
  "geometry": {"coordinates":[-1.2158850431,53.3877487183],"type":"Point"}
}