{
  "type": "Feature",
  "properties": {
    "addr:full":"The Mill, Argyle Street Tamworth Staffordshire B77 3EG",
    "addr:postcode":"b77 3eg",
    "addr:street":"Argyle Street",
    "iso:country":"GB",
    "sg:address":"The Mill, Argyle Street",
    "sg:city":"Tamworth",
    "sg:classifiers":[
        {
            "category":"Retail",
            "subcategory":"Auto Repair",
            "type":"Services"
        }
    ],
    "sg:postcode":"B77 3EG",
    "sg:province":"Staffordshire",
    "sg:tags":[
        "modification",
        "garage"
    ],
    "wof:name":"Mill Yard Motors",
    "wof:placetype":"venue"
},
  "geometry": {"coordinates":[-1.6739699841,52.628818512],"type":"Point"}
}