{
  "type": "Feature",
  "properties": {
    "addr:full":"158 Yardley Wood Road Birmingham West Midlands B13 9JE",
    "addr:housenumber":"158",
    "addr:postcode":"b13 9je",
    "addr:street":"Yardley Wood Road",
    "iso:country":"GB",
    "sg:address":"158 Yardley Wood Road",
    "sg:city":"Birmingham",
    "sg:classifiers":[
        {
            "category":"Organizations",
            "subcategory":"Non-profit Organization",
            "type":"Services"
        }
    ],
    "sg:phone":"+44 121 449 3387",
    "sg:postcode":"B13 9JE",
    "sg:province":"West Midlands",
    "sg:tags":[
        "organisation",
        "voluntary",
        "charity"
    ],
    "wof:name":"Birmingham Mencap",
    "wof:placetype":"venue"
},
  "geometry": {"coordinates":[-1.871447,52.442249],"type":"Point"}
}