{
  "type": "Feature",
  "properties": {
    "addr:full":"Penllyn Estate Farm, Llwynhelig Cowbridge The Vale of Glamorgan CF71 7AQ",
    "addr:postcode":"cf71 7aq",
    "addr:street":"Penllyn Estate;Llwynhelig;The Vale",
    "iso:country":"GB",
    "sg:address":"Penllyn Estate Farm, Llwynhelig",
    "sg:city":"Cowbridge",
    "sg:classifiers":[
        {
            "category":"Professional",
            "subcategory":"Detective & Security Services",
            "type":"Services"
        }
    ],
    "sg:phone":"+44 1446 771111",
    "sg:postcode":"CF71 7AQ",
    "sg:province":"The Vale of Glamorgan",
    "sg:tags":[
        "alarm",
        "burglar",
        "system"
    ],
    "wof:name":"Pritchard Security Systems Ltd.",
    "wof:placetype":"venue"
},
  "geometry": {"coordinates":[-3.4504249096,51.4623908997],"type":"Point"}
}