{
  "type": "Feature",
  "properties": {
    "addr:full":"Unit 22, Ty Verlon Industrial Estate, Cardiff Road Barry Angus CF6 3BE",
    "addr:housenumber":"unit 22",
    "addr:postcode":"cf6 3be",
    "addr:street":"Ty Verlon Industrial Estate Cardiff Road",
    "iso:country":"GB",
    "sg:address":"Unit 22, Ty Verlon Industrial Estate, Cardiff Road",
    "sg:city":"Barry",
    "sg:classifiers":[
        {
            "category":"Home & Garden",
            "subcategory":"Hardware",
            "type":"Retail Goods"
        }
    ],
    "sg:phone":"+44 1446 748255",
    "sg:postcode":"CF6 3BE",
    "sg:province":"Angus",
    "sg:tags":[
        "compressor",
        "air"
    ],
    "wof:name":"Penarth Pneumatic Ltd.",
    "wof:placetype":"venue"
},
  "geometry": {"coordinates":[-3.27799,51.401779],"type":"Point"}
}