{
  "type": "Feature",
  "properties": {
    "addr:full":"18 Derby Street Preston Lancashire PR1 1DT",
    "addr:housenumber":"18",
    "addr:postcode":"pr1 1dt",
    "addr:street":"Derby Street",
    "iso:country":"GB",
    "sg:address":"18 Derby Street",
    "sg:city":"Preston",
    "sg:classifiers":[
        {
            "category":"Cafe",
            "type":"Food & Drink"
        }
    ],
    "sg:phone":"+44 1772 887172",
    "sg:postcode":"PR1 1DT",
    "sg:province":"Lancashire",
    "sg:tags":[
        "tea",
        "room"
    ],
    "wof:name":"Zoo Coffee Bar",
    "wof:placetype":"venue"
},
  "geometry": {"coordinates":[-2.694065094,53.76014328],"type":"Point"}
}