{
  "type": "Feature",
  "properties": {
    "iso:country":"GB",
    "sg:address":"Page Grn Road",
    "sg:city":"London",
    "sg:classifiers":[
        {
            "category":"Building & Trades",
            "subcategory":"Construction",
            "type":"Services"
        }
    ],
    "sg:phone":"+44 20 8808 0459",
    "sg:postcode":"N15 4PG",
    "sg:province":"Greater London",
    "sg:tags":[
        "roofing",
        "contracting"
    ],
    "wof:name":"S I G Roofing Supplies Ltd.",
    "wof:placetype":"venue"
},
  "geometry": {"coordinates":[-0.072054,51.582748],"type":"Point"}
}