{
  "type": "Feature",
  "properties": {
    "addr:full":"Wests Ho, Elm Gro La Steyning West Sussex BN44 3SA",
    "addr:postcode":"bn44 3sa",
    "addr:street":"Gro La Steyning",
    "iso:country":"GB",
    "sg:address":"Wests Ho, Elm Gro La",
    "sg:city":"Steyning",
    "sg:classifiers":[
        {
            "category":"Building & Trades",
            "subcategory":"Construction",
            "type":"Services"
        }
    ],
    "sg:postcode":"BN44 3SA",
    "sg:province":"West Sussex",
    "sg:tags":[
        "builder"
    ],
    "wof:name":"Osborne,David,",
    "wof:placetype":"venue"
},
  "geometry": {"coordinates":[-0.3177250028,50.8827972412],"type":"Point"}
}