{
  "type": "Feature",
  "properties": {
    "addr:full":"Unit 2 Rheidol Retail Park Aberystwyth Ceredigion SY23 1LL",
    "addr:housenumber":"unit 2",
    "addr:postcode":"sy23 1ll",
    "addr:street":"Rheidol Retail Park",
    "iso:country":"GB",
    "sg:address":"Unit 2 Rheidol Retail Park",
    "sg:city":"Aberystwyth",
    "sg:classifiers":[
        {
            "category":"Shopping",
            "subcategory":"Catalog Store",
            "type":"Retail Goods"
        }
    ],
    "sg:phone":"+44 1970 624930",
    "sg:postcode":"SY23 1LL",
    "sg:province":"Ceredigion",
    "sg:tags":[
        "catalogue",
        "showroom"
    ],
    "wof:name":"Argos Aberystwyth",
    "wof:placetype":"venue"
},
  "geometry": {"coordinates":[-4.0802130699,52.4141159058],"type":"Point"}
}