{
  "type": "Feature",
  "properties": {
    "addr:full":"71 The Queensway Halesowen West Midlands B63 4AQ",
    "addr:housenumber":"71",
    "addr:postcode":"b63 4aq",
    "addr:street":"The Queensway",
    "iso:country":"GB",
    "sg:address":"71 The Queensway",
    "sg:city":"Halesowen",
    "sg:classifiers":[
        {
            "category":"Food & Beverages",
            "subcategory":"Liquor & Beverages",
            "type":"Retail Goods"
        }
    ],
    "sg:postcode":"B63 4AQ",
    "sg:province":"West Midlands",
    "sg:tags":[
        "beer",
        "spirit",
        "wines"
    ],
    "wof:name":"The Wine Bin",
    "wof:placetype":"venue"
},
  "geometry": {"coordinates":[-2.0530409813,52.4486312866],"type":"Point"}
}