{
  "type": "Feature",
  "properties": {
    "addr:full":"18-20 Bank Street Wrexham Wrexham LL11 1AH",
    "addr:housenumber":"18-20",
    "addr:postcode":"ll11 1ah",
    "addr:street":"Bank Street",
    "iso:country":"GB",
    "sg:address":"18-20 Bank Street",
    "sg:city":"Wrexham",
    "sg:classifiers":[
        {
            "category":"Shopping",
            "subcategory":"Jewelry",
            "type":"Retail Goods"
        },
        {
            "category":"Shopping",
            "subcategory":"Comic Books",
            "type":"Retail Goods"
        }
    ],
    "sg:phone":"+44 1978 266370",
    "sg:postcode":"LL11 1AH",
    "sg:province":"Wrexham",
    "sg:tags":[
        "jeweller",
        "sale",
        "jewellery"
    ],
    "wof:name":"C W Hale",
    "wof:placetype":"venue"
},
  "geometry": {"coordinates":[-3.044118,53.059319],"type":"Point"}
}