{
  "type": "Feature",
  "properties": {
    "addr:full":"Channel Road, Sunk Island Hull East Riding of Yorkshire HU12 0QW",
    "addr:postcode":"hu12 0qw",
    "addr:street":"Channel Road",
    "iso:country":"GB",
    "sg:address":"Channel Road, Sunk Island",
    "sg:city":"Hull",
    "sg:classifiers":[
        {
            "category":"Farming",
            "subcategory":"Farm",
            "type":"Manufacturing & Wholesale Goods"
        }
    ],
    "sg:postcode":"HU12 0QW",
    "sg:province":"East Riding of Yorkshire",
    "sg:tags":[
        "mixed",
        "crop"
    ],
    "wof:name":"J A Godfrey & Sons Ltd.",
    "wof:placetype":"venue"
},
  "geometry": {"coordinates":[-0.0477089994,53.6573753357],"type":"Point"}
}