{
  "type": "Feature",
  "properties": {
    "addr:full":"14 Cannon Street Preston Lancashire PR1 3NR",
    "addr:housenumber":"14",
    "addr:postcode":"pr1 3nr",
    "addr:street":"Cannon Street",
    "iso:country":"GB",
    "sg:address":"14 Cannon Street",
    "sg:city":"Preston",
    "sg:classifiers":[
        {
            "category":"Cafe",
            "type":"Food & Drink"
        }
    ],
    "sg:phone":"+44 1772 555650",
    "sg:postcode":"PR1 3NR",
    "sg:province":"Lancashire",
    "sg:tags":[
        "tea",
        "room"
    ],
    "wof:name":"Collinsons Cafe",
    "wof:placetype":"venue"
},
  "geometry": {"coordinates":[-2.6992800236,53.7573623657],"type":"Point"}
}