{
  "type": "Feature",
  "properties": {
    "addr:full":"17 Harebell Meadows Newton Aycliffe Durham DL5 4UG",
    "addr:housenumber":"17",
    "addr:postcode":"dl5 4ug",
    "addr:street":"Harebell Meadows",
    "iso:country":"GB",
    "sg:address":"17 Harebell Meadows",
    "sg:city":"Newton Aycliffe",
    "sg:classifiers":[
        {
            "category":"Organizations",
            "subcategory":"Non-profit Organization",
            "type":"Services"
        }
    ],
    "sg:postcode":"DL5 4UG",
    "sg:province":"Durham",
    "sg:tags":[
        "organisation",
        "voluntary",
        "charity"
    ],
    "wof:name":"Soldiers Sailors & Airmens Families Asso",
    "wof:placetype":"venue"
},
  "geometry": {"coordinates":[-1.5678139925,54.6328353882],"type":"Point"}
}