{
  "type": "Feature",
  "properties": {
    "addr:full":"3 Alum Waters, New Brancepeth Durham Durham DH7 7JL",
    "addr:housenumber":"3",
    "addr:postcode":"dh7 7jl",
    "addr:street":"Alum Waters New Brancepeth",
    "iso:country":"GB",
    "sg:address":"3 Alum Waters, New Brancepeth",
    "sg:city":"Durham",
    "sg:classifiers":[
        {
            "category":"Education",
            "subcategory":"School",
            "type":"Public Place"
        },
        {
            "category":"Education",
            "subcategory":"University",
            "type":"Public Place"
        }
    ],
    "sg:phone":"+44 191 378 9091",
    "sg:postcode":"DH7 7JL",
    "sg:province":"Durham",
    "sg:tags":[
        "private",
        "tuition"
    ],
    "wof:name":"Durham Tuition",
    "wof:placetype":"venue"
},
  "geometry": {"coordinates":[-1.638,54.767929],"type":"Point"}
}