{
  "type": "Feature",
  "properties": {
    "addr:full":"4 Jubilee Cottages, School Lane, Stourmouth Canterbury Kent CT3 1JA",
    "addr:housenumber":"4 jubilee cottages",
    "addr:postcode":"ct3 1ja",
    "addr:street":"School Lane",
    "iso:country":"GB",
    "sg:address":"4 Jubilee Cottages, School Lane, Stourmouth",
    "sg:city":"Canterbury",
    "sg:classifiers":[
        {
            "category":"Building & Trades",
            "subcategory":"Cleaning & Sanitation",
            "type":"Services"
        }
    ],
    "sg:phone":"+44 1227 722549",
    "sg:postcode":"CT3 1JA",
    "sg:province":"Kent",
    "sg:tags":[
        "steam"
    ],
    "wof:name":"T.h Mobile Steam Cleaning",
    "wof:placetype":"venue"
},
  "geometry": {"coordinates":[1.163118,51.274746],"type":"Point"}
}