{
  "type": "Feature",
  "properties": {
    "addr:full":"11 King Street Wrexham Wrexham LL11 1HF",
    "addr:housenumber":"11",
    "addr:postcode":"ll11 1hf",
    "addr:street":"King Street",
    "iso:country":"GB",
    "sg:address":"11 King Street",
    "sg:city":"Wrexham",
    "sg:classifiers":[
        {
            "category":"Fast Food",
            "type":"Food & Drink"
        }
    ],
    "sg:phone":"+44 1978 290724",
    "sg:postcode":"LL11 1HF",
    "sg:province":"Wrexham",
    "sg:tags":[
        "away",
        "meal",
        "outlet",
        "take"
    ],
    "wof:name":"Wrexham Kebab & Pizzas",
    "wof:placetype":"venue"
},
  "geometry": {"coordinates":[-2.997292,53.047688],"type":"Point"}
}