{
  "type": "Feature",
  "properties": {
    "addr:full":"Pamelia Rose, Main Street, Althorpe Scunthorpe Lincolnshire DN17 3HJ",
    "addr:postcode":"dn17 3hj",
    "addr:street":"Main Street",
    "iso:country":"GB",
    "sg:address":"Pamelia Rose, Main Street, Althorpe",
    "sg:city":"Scunthorpe",
    "sg:classifiers":[
        {
            "category":"Building & Trades",
            "subcategory":"Construction",
            "type":"Services"
        }
    ],
    "sg:phone":"+44 1724 783836",
    "sg:postcode":"DN17 3HJ",
    "sg:province":"Lincolnshire",
    "sg:tags":[
        "glazier",
        "decorator",
        "painter"
    ],
    "wof:name":"I Bates Decorator",
    "wof:placetype":"venue"
},
  "geometry": {"coordinates":[-0.746917,53.577271],"type":"Point"}
}