{
  "type": "Feature",
  "properties": {
    "iso:country":"GB",
    "sg:address":"43 Hollands Rd",
    "sg:city":"Haverhill",
    "sg:classifiers":[
        {
            "category":"Manufacturing",
            "subcategory":"Metals",
            "type":"Manufacturing & Wholesale Goods"
        }
    ],
    "sg:phone":"+44 1440 702723",
    "sg:postcode":"CB9 8SA",
    "sg:province":"Essex",
    "sg:tags":[
        "work",
        "sheet"
    ],
    "wof:name":"Camfabs Ltd",
    "wof:placetype":"venue"
},
  "geometry": {"coordinates":[0.441312,52.075798],"type":"Point"}
}