{
  "type": "Feature",
  "properties": {
    "addr:full":"Twin Spires, Bucksburn Aberdeen Aberdeen City AB21 9NR",
    "addr:postcode":"ab21 9nr",
    "addr:street":"Twin;Bucksburn",
    "iso:country":"GB",
    "sg:address":"Twin Spires, Bucksburn",
    "sg:city":"Aberdeen",
    "sg:classifiers":[
        {
            "category":"Farming",
            "subcategory":"Dairy Farm",
            "type":"Manufacturing & Wholesale Goods"
        }
    ],
    "sg:phone":"+44 1224 696371",
    "sg:postcode":"AB21 9NR",
    "sg:province":"Aberdeen City",
    "wof:name":"Aberdeen Milk Co. Ltd.",
    "wof:placetype":"venue"
},
  "geometry": {"coordinates":[-2.18166,57.178139],"type":"Point"}
}