{
  "type": "Feature",
  "properties": {
    "addr:full":"212 Shaw Heath Stockport Cheshire SK2 6QZ",
    "addr:housenumber":"212",
    "addr:postcode":"sk2 6qz",
    "addr:street":"Shaw Heath",
    "iso:country":"GB",
    "sg:address":"212 Shaw Heath",
    "sg:city":"Stockport",
    "sg:classifiers":[
        {
            "category":"Health Services",
            "subcategory":"Dentist",
            "type":"Services"
        }
    ],
    "sg:phone":"+44 161 429 8851",
    "sg:postcode":"SK2 6QZ",
    "sg:province":"Cheshire",
    "wof:name":"Dental Surgery",
    "wof:placetype":"venue"
},
  "geometry": {"coordinates":[-2.157432,53.397717],"type":"Point"}
}