{
  "type": "Feature",
  "properties": {
    "addr:full":"37 Broad Street, Ross-on-wye Hereford Gloucestershire HR9 7DY",
    "addr:housenumber":"37",
    "addr:postcode":"hr9 7dy",
    "addr:street":"Broad Street",
    "iso:country":"GB",
    "sg:address":"37 Broad Street, Ross-on-wye",
    "sg:city":"Hereford",
    "sg:classifiers":[
        {
            "category":"Autos & Motor Vehicles",
            "subcategory":"Auto Supplies",
            "type":"Retail Goods"
        },
        {
            "category":"Shopping",
            "type":"Retail Goods"
        }
    ],
    "sg:phone":"+44 1989 565469",
    "sg:postcode":"HR9 7DY",
    "sg:province":"Gloucestershire",
    "sg:tags":[
        "car",
        "part",
        "accessory"
    ],
    "sg:website":"http://www.andypack.com",
    "wof:name":"Andy Pack Car Care Centre",
    "wof:placetype":"venue"
},
  "geometry": {"coordinates":[-2.582173,51.9156],"type":"Point"}
}