{
  "type": "Feature",
  "properties": {
    "addr:full":"Windmill House, Weatheroak Hill, Alvechurch Birmingham Worcestershire B48 7EA",
    "addr:postcode":"b48 7ea",
    "addr:street":"Weatheroak Hill Alvechurch",
    "iso:country":"GB",
    "sg:address":"Windmill House, Weatheroak Hill, Alvechurch",
    "sg:city":"Birmingham",
    "sg:classifiers":[
        {
            "category":"Organizations",
            "subcategory":"Non-profit Organization",
            "type":"Services"
        }
    ],
    "sg:phone":"+44 1564 822356",
    "sg:postcode":"B48 7EA",
    "sg:province":"Worcestershire",
    "sg:tags":[
        "charitable",
        "organisation",
        "voluntary",
        "charity"
    ],
    "wof:name":"Betel Of Britain",
    "wof:placetype":"venue"
},
  "geometry": {"coordinates":[-1.961614,52.35117],"type":"Point"}
}