{
  "type": "Feature",
  "properties": {
    "addr:full":"Magna Rd Wigston Leicestershire LE18 4ZA",
    "addr:postcode":"le18 4za",
    "addr:street":"Magna Rd",
    "iso:country":"GB",
    "sg:address":"Magna Rd",
    "sg:city":"Wigston",
    "sg:classifiers":[
        {
            "category":"Food & Beverages",
            "subcategory":"Supermarket",
            "type":"Retail Goods"
        }
    ],
    "sg:phone":"+44 116 278 5141",
    "sg:postcode":"LE18 4ZA",
    "sg:province":"Leicestershire",
    "sg:tags":[
        "frozen"
    ],
    "wof:name":"R F Brookes (Leicester) Ltd",
    "wof:placetype":"venue"
},
  "geometry": {"coordinates":[-1.123564,52.580116],"type":"Point"}
}