{
  "type": "Feature",
  "properties": {
    "iso:country":"GB",
    "sg:address":"8 & 9 Bon Accord Crescent",
    "sg:city":"Aberdeen",
    "sg:classifiers":[
        {
            "category":"Wholesale",
            "subcategory":"Books, Periodicals, & Newspapers",
            "type":"Manufacturing & Wholesale Goods"
        }
    ],
    "sg:postcode":"AB1 2DN",
    "sg:province":"Aberdeen City",
    "sg:tags":[
        "publishing"
    ],
    "wof:name":"S.I.C.N. - Confederate Enterprises Ltd",
    "wof:placetype":"venue"
},
  "geometry": {"coordinates":[-2.10626,57.141804],"type":"Point"}
}