{
  "type": "Feature",
  "properties": {
    "addr:full":"Breaker Yard, Semley Shaftesbury Dorset SP7 9AQ",
    "addr:postcode":"sp7 9aq",
    "iso:country":"GB",
    "sg:address":"Breaker Yard, Semley",
    "sg:city":"Shaftesbury",
    "sg:classifiers":[
        {
            "category":"Wholesale",
            "subcategory":"Scrap",
            "type":"Manufacturing & Wholesale Goods"
        }
    ],
    "sg:postcode":"SP7 9AQ",
    "sg:province":"Dorset",
    "sg:tags":[
        "breaker",
        "dismantlers"
    ],
    "wof:name":"Langfords Vehicle Dismantlers",
    "wof:placetype":"venue"
},
  "geometry": {"coordinates":[-2.155759,51.041698],"type":"Point"}
}