{
  "type": "Feature",
  "properties": {
    "addr:full":"2 Ashcroft Drive, Denham Uxbridge Buckinghamshire UB9 5JF",
    "addr:housenumber":"2",
    "addr:postcode":"ub9 5jf",
    "addr:street":"Ashcroft Drive",
    "iso:country":"GB",
    "sg:address":"2 Ashcroft Drive, Denham",
    "sg:city":"Uxbridge",
    "sg:classifiers":[
        {
            "category":"Health Services",
            "subcategory":"Doctor",
            "type":"Services"
        },
        {
            "category":"Health Services",
            "subcategory":"Health Practitioner",
            "type":"Services"
        },
        {
            "category":"Health Services",
            "subcategory":"Dentist",
            "type":"Services"
        }
    ],
    "sg:phone":"+44 1895 833350",
    "sg:postcode":"UB9 5JF",
    "sg:province":"Buckinghamshire",
    "sg:tags":[
        "acupuncture",
        "practitioners"
    ],
    "wof:name":"Ashcroft Dental Surgery",
    "wof:placetype":"venue"
},
  "geometry": {"coordinates":[-0.502882,51.580902],"type":"Point"}
}