{
  "type": "Feature",
  "properties": {
    "addr:full":"6 Mid Causeway, Culross Dunfermline Fife KY12 8HS",
    "addr:housenumber":"6",
    "addr:postcode":"ky12 8hs",
    "addr:street":"Mid Causeway",
    "iso:country":"GB",
    "sg:address":"6 Mid Causeway, Culross",
    "sg:city":"Dunfermline",
    "sg:classifiers":[
        {
            "category":"Travel",
            "subcategory":"Hotels & Motels",
            "type":"Entertainment"
        }
    ],
    "sg:postcode":"KY12 8HS",
    "sg:province":"Fife",
    "wof:name":"Dundonald Arms Hotel",
    "wof:placetype":"venue"
},
  "geometry": {"coordinates":[-3.628791,56.055695],"type":"Point"}
}