{
  "type": "Feature",
  "properties": {
    "addr:full":"Dane Road London Greater London W13 9AQ",
    "addr:postcode":"w13 9aq",
    "addr:street":"Dane Road",
    "iso:country":"GB",
    "sg:address":"Dane Road",
    "sg:city":"London",
    "sg:classifiers":[
        {
            "category":"Retail",
            "subcategory":"Auto Repair",
            "type":"Services"
        }
    ],
    "sg:phone":"+44 20 8579 9808",
    "sg:postcode":"W13 9AQ",
    "sg:province":"Greater London",
    "sg:tags":[
        "modification",
        "garage"
    ],
    "wof:name":"Dane Coachworks Crash Repairers",
    "wof:placetype":"venue"
},
  "geometry": {"coordinates":[-0.314864,51.510666],"type":"Point"}
}