{
  "type": "Feature",
  "properties": {
    "iso:country":"GB",
    "sg:address":"19 Woodlands Road, New Costessey",
    "sg:city":"Norwich",
    "sg:classifiers":[
        {
            "category":"Shopping",
            "subcategory":"Musical Instruments",
            "type":"Retail Goods"
        }
    ],
    "sg:phone":"+44 1603 743447",
    "sg:postcode":"NR5 0NA",
    "sg:province":"Norfolk",
    "sg:tags":[
        "piano",
        "tuning",
        "maintenance"
    ],
    "wof:name":"Robert G Fielder",
    "wof:placetype":"venue"
},
  "geometry": {"coordinates":[1.225938,52.650173],"type":"Point"}
}