{
  "type": "Feature",
  "properties": {
    "iso:country":"GB",
    "sg:address":"Unit 1 Golden House, Waterden Road",
    "sg:city":"London",
    "sg:classifiers":[
        {
            "category":"Professional",
            "type":"Services"
        }
    ],
    "sg:phone":"+44 20 8533 5001",
    "sg:postcode":"E15 2AA",
    "sg:province":"Greater London",
    "sg:tags":[
        "auctioneer"
    ],
    "wof:name":"Plaistow Auctions",
    "wof:placetype":"venue"
},
  "geometry": {"coordinates":[-0.0051600002,51.5320396423],"type":"Point"}
}