{
  "type": "Feature",
  "properties": {
    "addr:full":"5 Barley Croft, Great Boughton Chester Cheshire CH3 5SP",
    "addr:housenumber":"5",
    "addr:postcode":"ch3 5sp",
    "addr:street":"Barley Croft",
    "iso:country":"GB",
    "sg:address":"5 Barley Croft, Great Boughton",
    "sg:city":"Chester",
    "sg:classifiers":[
        {
            "category":"Building & Trades",
            "subcategory":"Construction",
            "type":"Services"
        }
    ],
    "sg:phone":"+44 1244 316795",
    "sg:postcode":"CH3 5SP",
    "sg:province":"Cheshire",
    "sg:tags":[
        "joiner",
        "carpenter"
    ],
    "wof:name":"Rob Parkinson",
    "wof:placetype":"venue"
},
  "geometry": {"coordinates":[-2.863183,53.182728],"type":"Point"}
}