{
  "type": "Feature",
  "properties": {
    "addr:full":"Roman Catholic Cathedral, 11 Belmont Shrewsbury Shropshire SY1 1TE",
    "addr:housenumber":"11",
    "addr:postcode":"sy1 1te",
    "addr:street":"Belmont",
    "iso:country":"GB",
    "sg:address":"Roman Catholic Cathedral, 11 Belmont",
    "sg:city":"Shrewsbury",
    "sg:classifiers":[
        {
            "category":"Place Of Worship",
            "type":"Public Place"
        }
    ],
    "sg:phone":"+44 1743 362366",
    "sg:postcode":"SY1 1TE",
    "sg:province":"Shropshire",
    "wof:name":"Shrewsbury Cathedral",
    "wof:placetype":"venue"
},
  "geometry": {"coordinates":[-2.754469,52.708179],"type":"Point"}
}