{
  "type": "Feature",
  "properties": {
    "iso:country":"GB",
    "sg:address":"Cherry Acre, Llangan",
    "sg:city":"Bridgend",
    "sg:classifiers":[
        {
            "category":"Building & Trades",
            "subcategory":"Landscaping Services",
            "type":"Services"
        }
    ],
    "sg:phone":"+44 1656 862934",
    "sg:postcode":"CF35 5DR",
    "sg:province":"Bridgend",
    "sg:tags":[
        "landscape",
        "contractor"
    ],
    "wof:name":"Ceejay Landscapes Ltd",
    "wof:placetype":"venue"
},
  "geometry": {"coordinates":[-3.5003049374,51.4870643616],"type":"Point"}
}