{
  "type": "Feature",
  "properties": {
    "addr:full":"9 Thomas St Manchester Greater Manchester M4 1EU",
    "addr:housenumber":"9",
    "addr:postcode":"m4 1eu",
    "addr:street":"Thomas St",
    "iso:country":"GB",
    "sg:address":"9 Thomas St",
    "sg:city":"Manchester",
    "sg:classifiers":[
        {
            "category":"Wholesale",
            "subcategory":"Office Equipment",
            "type":"Manufacturing & Wholesale Goods"
        }
    ],
    "sg:phone":"+44 161 834 7625",
    "sg:postcode":"M4 1EU",
    "sg:province":"Greater Manchester",
    "sg:tags":[
        "register",
        "cash",
        "accessory"
    ],
    "wof:name":"Business Equipment & Scales Service Ltd",
    "wof:placetype":"venue"
},
  "geometry": {"coordinates":[-2.23769,53.484814],"type":"Point"}
}