{
  "type": "Feature",
  "properties": {
    "iso:country":"GB",
    "sg:address":"Anchor House, 5 Station Road",
    "sg:city":"Orpington",
    "sg:classifiers":[
        {
            "category":"Organizations",
            "subcategory":"Non-profit Organization",
            "type":"Services"
        }
    ],
    "sg:phone":"+44 1689 811222",
    "sg:postcode":"BR6 0RZ",
    "sg:province":"Kent",
    "sg:tags":[
        "organisation",
        "voluntary",
        "charity"
    ],
    "wof:name":"Orpington Mind",
    "wof:placetype":"venue"
},
  "geometry": {"coordinates":[0.097145,51.373043],"type":"Point"}
}