{
  "type": "Feature",
  "properties": {
    "iso:country":"GB",
    "sg:address":"248 Westburn Road",
    "sg:city":"Aberdeen",
    "sg:classifiers":[
        {
            "category":"Manufacturing",
            "subcategory":"Tools & Machinery",
            "type":"Manufacturing & Wholesale Goods"
        }
    ],
    "sg:phone":"+44 1224 632630",
    "sg:postcode":"AB25 2QU",
    "sg:province":"Aberdeen City",
    "sg:tags":[
        "society",
        "friendly"
    ],
    "wof:name":"Adie Associates",
    "wof:placetype":"venue"
},
  "geometry": {"coordinates":[-2.1300890446,57.152633667],"type":"Point"}
}