{
  "type": "Feature",
  "properties": {
    "addr:full":"Ernest Island House, Green Park Bath Bath and North East Somerset BA1 1XH",
    "addr:postcode":"ba1 1xh",
    "addr:street":"Ernest;Park",
    "iso:country":"GB",
    "sg:address":"Ernest Island House, Green Park",
    "sg:city":"Bath",
    "sg:classifiers":[
        {
            "category":"Building & Trades",
            "subcategory":"Construction",
            "type":"Services"
        }
    ],
    "sg:phone":"+44 1225 428441",
    "sg:postcode":"BA1 1XH",
    "sg:province":"Bath and North East Somerset",
    "sg:tags":[
        "builder"
    ],
    "wof:name":"Ernest Ireland Construction",
    "wof:placetype":"venue"
},
  "geometry": {"coordinates":[-2.368099,51.380341],"type":"Point"}
}