{
  "type": "Feature",
  "properties": {
    "iso:country":"GB",
    "sg:address":"99 Stoneleigh Street",
    "sg:city":"Oldham",
    "sg:classifiers":[
        {
            "category":"Building & Trades",
            "subcategory":"Plumbing",
            "type":"Services"
        }
    ],
    "sg:phone":"+44 161 624 0173",
    "sg:postcode":"OL1 4LF",
    "sg:province":"Lancashire",
    "sg:tags":[
        "heating"
    ],
    "wof:name":"B P Stanton",
    "wof:placetype":"venue"
},
  "geometry": {"coordinates":[-2.095001,53.550755],"type":"Point"}
}