{
  "type": "Feature",
  "properties": {
    "iso:country":"GB",
    "sg:address":"Oldwoods, Bomere Heath",
    "sg:city":"Shrewsbury",
    "sg:classifiers":[
        {
            "category":"Bars & Pubs",
            "type":"Food & Drink"
        }
    ],
    "sg:phone":"+44 1939 290273",
    "sg:postcode":"SY4 3AX",
    "sg:province":"Shropshire",
    "sg:tags":[
        "pubs",
        "inn"
    ],
    "wof:name":"The Romping Cat",
    "wof:placetype":"venue"
},
  "geometry": {"coordinates":[-2.778084,52.772907],"type":"Point"}
}