{
  "type": "Feature",
  "properties": {
    "iso:country":"GB",
    "sg:address":"Pasture House Farm, Pasture Lane, Barrowford",
    "sg:city":"Nelson",
    "sg:classifiers":[
        {
            "category":"Farming",
            "subcategory":"Livestock Farm",
            "type":"Manufacturing & Wholesale Goods"
        }
    ],
    "sg:phone":"+44 1282 615588",
    "sg:postcode":"BB9 6QX",
    "sg:province":"Lancashire",
    "sg:tags":[
        "others"
    ],
    "wof:name":"B J Robinson",
    "wof:placetype":"venue"
},
  "geometry": {"coordinates":[-2.218484,53.855534],"type":"Point"}
}