{
  "type": "Feature",
  "properties": {
    "addr:full":"Kingsbury Community Unit, Honeypot La Colindale Greater London NW9 9QY",
    "addr:postcode":"nw9 9qy",
    "iso:country":"GB",
    "sg:address":"Kingsbury Community Unit, Honeypot La",
    "sg:city":"Colindale",
    "sg:classifiers":[
        {
            "category":"Professional",
            "subcategory":"Lawyer & Legal Services",
            "type":"Services"
        }
    ],
    "sg:phone":"+44 20 8451 8424",
    "sg:postcode":"NW9 9QY",
    "sg:province":"Greater London",
    "sg:tags":[
        "advice",
        "counselling"
    ],
    "wof:name":"Kingsbury Child & Family Centre",
    "wof:placetype":"venue"
},
  "geometry": {"coordinates":[-0.2828299999,51.5892982483],"type":"Point"}
}