{
  "type": "Feature",
  "properties": {
    "addr:full":"115 Oxford Road Swindon Wiltshire SN3 4JA",
    "addr:housenumber":"115",
    "addr:postcode":"sn3 4ja",
    "addr:street":"Oxford Road",
    "iso:country":"GB",
    "sg:address":"115 Oxford Road",
    "sg:city":"Swindon",
    "sg:classifiers":[
        {
            "category":"Building & Trades",
            "subcategory":"Plumbing",
            "type":"Services"
        }
    ],
    "sg:phone":"+44 1793 825679",
    "sg:postcode":"SN3 4JA",
    "sg:province":"Wiltshire",
    "sg:tags":[
        "central",
        "heating"
    ],
    "wof:name":"K A Barnes",
    "wof:placetype":"venue"
},
  "geometry": {"coordinates":[-1.7442059517,51.5742607117],"type":"Point"}
}