{
  "type": "Feature",
  "properties": {
    "iso:country":"GB",
    "sg:address":"Maple Tree Works, Brook Lane, Great Baddow",
    "sg:city":"Chelmsford",
    "sg:classifiers":[
        {
            "category":"Manufacturing",
            "subcategory":"Wood Products",
            "type":"Manufacturing & Wholesale Goods"
        }
    ],
    "sg:phone":"+44 1245 476142",
    "sg:postcode":"CM2 7SX",
    "sg:province":"Essex",
    "sg:tags":[
        "woodturning"
    ],
    "wof:name":"All Oak & Hardwood",
    "wof:placetype":"venue"
},
  "geometry": {"coordinates":[0.49944,51.699841],"type":"Point"}
}