{
  "type": "Feature",
  "properties": {
    "addr:full":"32 Croft Road Torquay Devon TQ2 5UE",
    "addr:housenumber":"32",
    "addr:postcode":"tq2 5ue",
    "addr:street":"Croft Road",
    "iso:country":"GB",
    "sg:address":"32 Croft Road",
    "sg:city":"Torquay",
    "sg:classifiers":[
        {
            "category":"Travel",
            "subcategory":"Hotels & Motels",
            "type":"Entertainment"
        }
    ],
    "sg:phone":"+44 1803 292759",
    "sg:postcode":"TQ2 5UE",
    "sg:province":"Devon",
    "sg:tags":[
        "self",
        "catering"
    ],
    "wof:name":"Clydesdale Holiday Flats",
    "wof:placetype":"venue"
},
  "geometry": {"coordinates":[-3.5335900784,50.465221405],"type":"Point"}
}