{
  "type": "Feature",
  "properties": {
    "addr:full":"19 New Quebec Street London Greater London W1H 7RY",
    "addr:housenumber":"19",
    "addr:postcode":"w1h 7ry",
    "addr:street":"New Quebec Street",
    "iso:country":"GB",
    "sg:address":"19 New Quebec Street",
    "sg:city":"London",
    "sg:classifiers":[
        {
            "category":"Real Estate",
            "subcategory":"Real Estate Agent",
            "type":"Services"
        }
    ],
    "sg:phone":"+44 20 7723 7243",
    "sg:postcode":"W1H 7RY",
    "sg:province":"Greater London",
    "wof:name":"Midcom Properties Ltd.",
    "wof:placetype":"venue"
},
  "geometry": {"coordinates":[-0.1584080011,51.5153465271],"type":"Point"}
}