{
  "type": "Feature",
  "properties": {
    "iso:country":"GB",
    "sg:address":"Aspenshaw Hall, Thornsett",
    "sg:city":"High Peak",
    "sg:classifiers":[
        {
            "category":"Organizations",
            "subcategory":"Membership Organization",
            "type":"Services"
        }
    ],
    "sg:postcode":"SK22 1AU",
    "sg:province":"Cheshire",
    "sg:tags":[
        "club"
    ],
    "wof:name":"The Association of American Dancing",
    "wof:placetype":"venue"
},
  "geometry": {"coordinates":[-1.98153,53.387051],"type":"Point"}
}