{
  "type": "Feature",
  "properties": {
    "iso:country":"GB",
    "sg:address":"2 Church Street",
    "sg:city":"Belford",
    "sg:classifiers":[
        {
            "category":"Government",
            "subcategory":"Post Office",
            "type":"Public Place"
        }
    ],
    "sg:phone":"+44 1668 213201",
    "sg:postcode":"NE70 7LS",
    "sg:province":"Northumberland",
    "wof:name":"Belford Post Office",
    "wof:placetype":"venue"
},
  "geometry": {"coordinates":[-1.8284629583,55.5992164612],"type":"Point"}
}