{
  "type": "Feature",
  "properties": {
    "iso:country":"GB",
    "sg:address":"29 Main Street, Stewarton",
    "sg:city":"Kilmarnock",
    "sg:classifiers":[
        {
            "category":"Cafe",
            "type":"Food & Drink"
        }
    ],
    "sg:phone":"+44 1560 484346",
    "sg:postcode":"KA3 5BS",
    "sg:province":"East Ayrshire",
    "sg:tags":[
        "tea",
        "room"
    ],
    "wof:name":"The Coffee Pot",
    "wof:placetype":"venue"
},
  "geometry": {"coordinates":[-4.5145797729,55.6805725098],"type":"Point"}
}