{
  "type": "Feature",
  "properties": {
    "addr:full":"5 Green St Borehamwood Hertfordshire WD6 5NE",
    "addr:housenumber":"5",
    "addr:postcode":"wd6 5ne",
    "addr:street":"Green St",
    "iso:country":"GB",
    "sg:address":"5 Green St",
    "sg:city":"Borehamwood",
    "sg:classifiers":[
        {
            "category":"Military Area",
            "subcategory":"Air Force Base",
            "type":"Public Place"
        }
    ],
    "sg:phone":"+44 20 8207 4418",
    "sg:postcode":"WD6 5NE",
    "sg:province":"Hertfordshire",
    "sg:tags":[
        "taxi",
        "hire",
        "private"
    ],
    "wof:name":"Ten Pines",
    "wof:placetype":"venue"
},
  "geometry": {"coordinates":[-0.27258,51.674633],"type":"Point"}
}