{
  "type": "Feature",
  "properties": {
    "addr:full":"37 Warren Street London Greater London W1T 6AD",
    "addr:housenumber":"37",
    "addr:postcode":"w1t 6ad",
    "addr:street":"Warren Street",
    "iso:country":"GB",
    "sg:address":"37 Warren Street",
    "sg:city":"London",
    "sg:classifiers":[
        {
            "category":"Manufacturing",
            "subcategory":"Glass & Minerals",
            "type":"Manufacturing & Wholesale Goods"
        }
    ],
    "sg:postcode":"W1T 6AD",
    "sg:province":"Greater London",
    "sg:tags":[
        "mould"
    ],
    "wof:name":"Saunders Bird Limited",
    "wof:placetype":"venue"
},
  "geometry": {"coordinates":[-0.141611,51.523743],"type":"Point"}
}