{
  "type": "Feature",
  "properties": {
    "iso:country":"GB",
    "sg:address":"Little Hill Farms, Wellsbourne",
    "sg:city":"Warwick",
    "sg:classifiers":[
        {
            "category":"Farming",
            "subcategory":"Farm",
            "type":"Manufacturing & Wholesale Goods"
        }
    ],
    "sg:phone":"+44 1789 840261",
    "sg:postcode":"CV35 9EB",
    "sg:province":"Warwickshire",
    "sg:tags":[
        "mixed",
        "crop"
    ],
    "wof:name":"G Hutsby & Sons",
    "wof:placetype":"venue"
},
  "geometry": {"coordinates":[-1.59435,52.207661],"type":"Point"}
}