{
  "type": "Feature",
  "properties": {
    "addr:full":"Ravensbank, Holbeach St Johns Spalding Cambridgeshire PE12 8SP",
    "addr:postcode":"pe12 8sp",
    "addr:street":"Holbeach St;Spalding",
    "iso:country":"GB",
    "sg:address":"Ravensbank, Holbeach St Johns",
    "sg:city":"Spalding",
    "sg:classifiers":[
        {
            "category":"Wholesale",
            "subcategory":"Plants",
            "type":"Manufacturing & Wholesale Goods"
        },
        {
            "category":"Building & Trades",
            "subcategory":"Construction",
            "type":"Services"
        }
    ],
    "sg:phone":"+44 1406 425100",
    "sg:postcode":"PE12 8SP",
    "sg:province":"Cambridgeshire",
    "sg:tags":[
        "fork",
        "lift",
        "truck"
    ],
    "wof:name":"FENLAND MATERIALS HANDLING LTD",
    "wof:placetype":"venue"
},
  "geometry": {"coordinates":[-0.0123300003,52.7614707947],"type":"Point"}
}