{
  "type": "Feature",
  "properties": {
    "addr:full":"41 Burton Road Kendal Cumbria LA9 7LJ",
    "addr:housenumber":"41",
    "addr:postcode":"la9 7lj",
    "addr:street":"Burton Road",
    "iso:country":"GB",
    "sg:address":"41 Burton Road",
    "sg:city":"Kendal",
    "sg:classifiers":[
        {
            "category":"Government",
            "subcategory":"Post Office",
            "type":"Public Place"
        }
    ],
    "sg:postcode":"LA9 7LJ",
    "sg:province":"Cumbria",
    "wof:name":"Rinkfield Post Office",
    "wof:placetype":"venue"
},
  "geometry": {"coordinates":[-2.739262104,54.3150405884],"type":"Point"}
}