{
  "type": "Feature",
  "properties": {
    "addr:full":"375 Richmond Road Twickenham Greater London TW1 2EF",
    "addr:housenumber":"375",
    "addr:postcode":"tw1 2ef",
    "addr:street":"Richmond Road",
    "iso:country":"GB",
    "sg:address":"375 Richmond Road",
    "sg:city":"Twickenham",
    "sg:classifiers":[
        {
            "category":"Professional",
            "type":"Services"
        },
        {
            "category":"Professional",
            "subcategory":"Art Services",
            "type":"Services"
        }
    ],
    "sg:phone":"+44 20 8891 5418",
    "sg:postcode":"TW1 2EF",
    "sg:province":"Greater London",
    "sg:tags":[
        "interior",
        "furnishers",
        "designer"
    ],
    "wof:name":"Roberts Fleming Designs",
    "wof:placetype":"venue"
},
  "geometry": {"coordinates":[-0.310274,51.455662],"type":"Point"}
}