{
  "type": "Feature",
  "properties": {
    "addr:full":"31 Auster Road, North York Trading Estate York North Yorkshire YO30 4XA",
    "addr:housenumber":"31",
    "addr:postcode":"yo30 4xa",
    "addr:street":"Auster Road;Trading",
    "iso:country":"GB",
    "sg:address":"31 Auster Road, North York Trading Estate",
    "sg:city":"York",
    "sg:classifiers":[
        {
            "category":"Shopping",
            "subcategory":"Stationery & Office Supplies",
            "type":"Retail Goods"
        }
    ],
    "sg:postcode":"YO30 4XA",
    "sg:province":"North Yorkshire",
    "sg:tags":[
        "box",
        "carton"
    ],
    "wof:name":"York Box Co.",
    "wof:placetype":"venue"
},
  "geometry": {"coordinates":[-1.093606,53.989346],"type":"Point"}
}