{
  "type": "Feature",
  "properties": {
    "addr:full":"52 Central Avenue Birmingham West Midlands B31 4HU",
    "addr:housenumber":"52",
    "addr:postcode":"b31 4hu",
    "addr:street":"Central Avenue",
    "iso:country":"GB",
    "sg:address":"52 Central Avenue",
    "sg:city":"Birmingham",
    "sg:classifiers":[
        {
            "category":"Home & Garden",
            "subcategory":"Household Appliances",
            "type":"Retail Goods"
        },
        {
            "category":"Retail",
            "subcategory":"Repair Shop",
            "type":"Services"
        }
    ],
    "sg:phone":"+44 121 475 6781",
    "sg:postcode":"B31 4HU",
    "sg:province":"West Midlands",
    "sg:tags":[
        "refrigerator",
        "electrical",
        "servicing",
        "freezer"
    ],
    "wof:name":"Brian Baker",
    "wof:placetype":"venue"
},
  "geometry": {"coordinates":[-1.9728209972,52.4004631042],"type":"Point"}
}