{
  "type": "Feature",
  "properties": {
    "iso:country":"GB",
    "sg:address":"Winchcombe Ho, 123-126 Bartholomew St",
    "sg:city":"Newbury",
    "sg:classifiers":[
        {
            "category":"Banks & Credit Unions",
            "subcategory":"Financial Services",
            "type":"Services"
        }
    ],
    "sg:postcode":"RG14 5BN",
    "sg:province":"Berkshire",
    "sg:tags":[
        "consultant",
        "pension"
    ],
    "wof:name":"K C C Insurance Services (Life & Pension",
    "wof:placetype":"venue"
},
  "geometry": {"coordinates":[-1.325872,51.405872],"type":"Point"}
}