{
  "type": "Feature",
  "properties": {
    "addr:full":"Paines Manor, Pentlow Sudbury Essex CO10 7JT",
    "addr:postcode":"co10 7jt",
    "addr:street":"Paines;Pentlow",
    "iso:country":"GB",
    "sg:address":"Paines Manor, Pentlow",
    "sg:city":"Sudbury",
    "sg:classifiers":[
        {
            "category":"Farming",
            "subcategory":"Livestock Farm",
            "type":"Manufacturing & Wholesale Goods"
        }
    ],
    "sg:phone":"+44 1787 277336",
    "sg:postcode":"CO10 7JT",
    "sg:province":"Essex",
    "sg:tags":[
        "others"
    ],
    "wof:name":"Paines Manor & Pauls Hall Farms",
    "wof:placetype":"venue"
},
  "geometry": {"coordinates":[0.647795,52.073341],"type":"Point"}
}