{
  "type": "Feature",
  "properties": {
    "addr:full":"Unit 4, Hammond Av, Whitehill Industrial Estate Stockport Cheshire SK4 5JF",
    "addr:housenumber":"unit 4",
    "addr:postcode":"sk4 5jf",
    "addr:street":"Hammond Av Whitehill Industrial Estate",
    "iso:country":"GB",
    "sg:address":"Unit 4, Hammond Av, Whitehill Industrial Estate",
    "sg:city":"Stockport",
    "sg:classifiers":[
        {
            "category":"Home & Garden",
            "subcategory":"Building Materials",
            "type":"Retail Goods"
        }
    ],
    "sg:phone":"+44 161 477 2700",
    "sg:postcode":"SK4 5JF",
    "sg:province":"Cheshire",
    "sg:tags":[
        "ready",
        "mixed",
        "concrete"
    ],
    "wof:name":"Tarmac Central Ltd.",
    "wof:placetype":"venue"
},
  "geometry": {"coordinates":[-2.1777999401,53.4321517944],"type":"Point"}
}