{
  "type": "Feature",
  "properties": {
    "addr:full":"13 Brantwood Avenue Erith Kent DA8 1EH",
    "addr:housenumber":"13",
    "addr:postcode":"da8 1eh",
    "addr:street":"Brantwood Avenue",
    "iso:country":"GB",
    "sg:address":"13 Brantwood Avenue",
    "sg:city":"Erith",
    "sg:classifiers":[
        {
            "category":"Building & Trades",
            "subcategory":"Construction",
            "type":"Services"
        }
    ],
    "sg:phone":"+44 1322 449332",
    "sg:postcode":"DA8 1EH",
    "sg:province":"Kent",
    "sg:tags":[
        "joiner",
        "carpenter"
    ],
    "wof:name":"P Burrows",
    "wof:placetype":"venue"
},
  "geometry": {"coordinates":[0.159582,51.476151],"type":"Point"}
}