{
  "type": "Feature",
  "properties": {
    "iso:country":"GB",
    "sg:address":"40 Reynolds Gardens, Moulton",
    "sg:city":"Spalding",
    "sg:classifiers":[
        {
            "category":"Building & Trades",
            "subcategory":"Construction",
            "type":"Services"
        }
    ],
    "sg:postcode":"PE12 6PT",
    "sg:province":"Cambridgeshire",
    "sg:tags":[
        "roofing"
    ],
    "wof:name":"D A P Estimating Services",
    "wof:placetype":"venue"
},
  "geometry": {"coordinates":[-0.0638350025,52.8014526367],"type":"Point"}
}