{
  "type": "Feature",
  "properties": {
    "addr:full":"121 Toronto Road, North End Portsmouth Hampshire PO2 7QD",
    "addr:housenumber":"121",
    "addr:postcode":"hampshire po2 7qd",
    "addr:street":"Toronto Road",
    "iso:country":"GB",
    "sg:address":"121 Toronto Road, North End",
    "sg:city":"Portsmouth",
    "sg:classifiers":[
        {
            "category":"Retail",
            "subcategory":"Auto Repair",
            "type":"Services"
        }
    ],
    "sg:phone":"+44 23 9266 2206",
    "sg:postcode":"PO2 7QD",
    "sg:province":"Hampshire",
    "sg:tags":[
        "modification",
        "garage",
        "related"
    ],
    "wof:name":"Mobile Mechanic Services",
    "wof:placetype":"venue"
},
  "geometry": {"coordinates":[-1.07467,50.809471],"type":"Point"}
}