{
  "type": "Feature",
  "properties": {
    "iso:country":"GB",
    "sg:address":"11a Havant Road",
    "sg:city":"London",
    "sg:classifiers":[
        {
            "category":"Personal",
            "subcategory":"Beauty Salon",
            "type":"Services"
        }
    ],
    "sg:postcode":"E17 3JE",
    "sg:province":"Greater London",
    "sg:tags":[
        "lady",
        "hairdresser"
    ],
    "wof:name":"Norma's",
    "wof:placetype":"venue"
},
  "geometry": {"coordinates":[-0.005706,51.588654],"type":"Point"}
}