{
  "type": "Feature",
  "properties": {
    "iso:country":"GB",
    "sg:address":"34 Vicarage Road",
    "sg:city":"Verwood",
    "sg:classifiers":[
        {
            "category":"Manufacturing",
            "subcategory":"Tools & Machinery",
            "type":"Manufacturing & Wholesale Goods"
        },
        {
            "category":"Banks & Credit Unions",
            "subcategory":"Financial Services",
            "type":"Services"
        }
    ],
    "sg:phone":"+44 1202 823306",
    "sg:postcode":"BH31 6DR",
    "sg:province":"Dorset",
    "sg:tags":[
        "adviser",
        "friendly",
        "society"
    ],
    "wof:name":"Barnes & Hedgecock",
    "wof:placetype":"venue"
},
  "geometry": {"coordinates":[-1.876567,50.880886],"type":"Point"}
}