{
  "type": "Feature",
  "properties": {
    "iso:country":"GB",
    "sg:address":"6 Oak Terr, Cranbrook Rd",
    "sg:city":"Cranbrook",
    "sg:classifiers":[
        {
            "category":"Personal",
            "type":"Services"
        }
    ],
    "sg:phone":"+44 1580 753509",
    "sg:postcode":"TN18 4AZ",
    "sg:province":"East Sussex",
    "sg:tags":[
        "wedding"
    ],
    "wof:name":"Hawkhurst Bridal",
    "wof:placetype":"venue"
},
  "geometry": {"coordinates":[0.500007,51.039146],"type":"Point"}
}