{
  "type": "Feature",
  "properties": {
    "addr:full":"Matrix House Loughborough Motor, Way Trading Estate Loughborough Leicestershire LE12 9NH",
    "addr:postcode":"le12 9nh",
    "addr:street":"Motor Way Trading Estate",
    "iso:country":"GB",
    "sg:address":"Matrix House Loughborough Motor, Way Trading Estate",
    "sg:city":"Loughborough",
    "sg:classifiers":[
        {
            "category":"Professional",
            "subcategory":"Computer Services",
            "type":"Services"
        }
    ],
    "sg:phone":"+44 1509 505777",
    "sg:postcode":"LE12 9NH",
    "sg:province":"Leicestershire",
    "sg:tags":[
        "development",
        "system",
        "software"
    ],
    "wof:name":"Sytation Ltd.",
    "wof:placetype":"venue"
},
  "geometry": {"coordinates":[-1.288652,52.773689],"type":"Point"}
}