{
  "type": "Feature",
  "properties": {
    "iso:country":"GB",
    "sg:address":"Prince Of Wales Road",
    "sg:city":"Dorchester",
    "sg:classifiers":[
        {
            "category":"Education",
            "subcategory":"School",
            "type":"Public Place"
        },
        {
            "category":"Education",
            "subcategory":"University",
            "type":"Public Place"
        }
    ],
    "sg:phone":"+44 1305 251040",
    "sg:postcode":"DT1 1PY",
    "sg:province":"Dorset",
    "sg:tags":[
        "adult",
        "location"
    ],
    "sg:website":"http://www.adult-ed.co.uk",
    "wof:name":"South & West Adult Education",
    "wof:placetype":"venue"
},
  "geometry": {"coordinates":[-2.436575,50.711094],"type":"Point"}
}