{
  "type": "Feature",
  "properties": {
    "iso:country":"GB",
    "sg:address":"Country View, St Catherines Hill",
    "sg:city":"Launceston",
    "sg:classifiers":[
        {
            "category":"Building & Trades",
            "subcategory":"Plumbing",
            "type":"Services"
        }
    ],
    "sg:phone":"+44 1566 775794",
    "sg:postcode":"PL15 7EJ",
    "sg:province":"Cornwall",
    "sg:tags":[
        "plumber",
        "heating"
    ],
    "wof:name":"C A G Davey",
    "wof:placetype":"venue"
},
  "geometry": {"coordinates":[-4.3633441925,50.6367073059],"type":"Point"}
}