{
  "type": "Feature",
  "properties": {
    "addr:full":"Unit 8, Amos Road Sheffield South Yorkshire S9 1BX",
    "addr:housenumber":"unit 8",
    "addr:postcode":"s9 1bx",
    "addr:street":"Amos Road",
    "iso:country":"GB",
    "sg:address":"Unit 8, Amos Road",
    "sg:city":"Sheffield",
    "sg:classifiers":[
        {
            "category":"Wholesale",
            "subcategory":"Painting Supplies",
            "type":"Manufacturing & Wholesale Goods"
        }
    ],
    "sg:phone":"+44 114 244 3856",
    "sg:postcode":"S9 1BX",
    "sg:province":"South Yorkshire",
    "sg:tags":[
        "carbon",
        "product"
    ],
    "wof:name":"Morganite Electrical Carbon",
    "wof:placetype":"venue"
},
  "geometry": {"coordinates":[-1.4188970327,53.4124603271],"type":"Point"}
}