{
  "type": "Feature",
  "properties": {
    "iso:country":"GB",
    "sg:address":"2-16 Colegate",
    "sg:city":"Norwich",
    "sg:classifiers":[
        {
            "category":"Government",
            "subcategory":"Office",
            "type":"Public Place"
        }
    ],
    "sg:phone":"+44 1603 621000",
    "sg:postcode":"NR3 1BQ",
    "sg:province":"Norfolk",
    "sg:tags":[
        "central"
    ],
    "wof:name":"Her Majesty's Stationery Office",
    "wof:placetype":"venue"
},
  "geometry": {"coordinates":[1.2966690063,52.6333198547],"type":"Point"}
}