{
  "type": "Feature",
  "properties": {
    "addr:full":"P O Box 17, 129-139 Layer Road Colchester Essex CO2 9JY",
    "addr:housenumber":"box",
    "addr:postcode":"129-139;co2 9jy",
    "addr:street":"P O;Layer Road Colchester",
    "iso:country":"GB",
    "sg:address":"P O Box 17, 129-139 Layer Road",
    "sg:city":"Colchester",
    "sg:classifiers":[
        {
            "category":"Manufacturing",
            "subcategory":"Building Materials",
            "type":"Manufacturing & Wholesale Goods"
        }
    ],
    "sg:phone":"+44 1206 216000",
    "sg:postcode":"CO2 9JY",
    "sg:province":"Essex",
    "sg:tags":[
        "merchant",
        "builder"
    ],
    "wof:name":"Kent Blaxill & Co. Ltd.",
    "wof:placetype":"venue"
},
  "geometry": {"coordinates":[0.903514,51.8853],"type":"Point"}
}