{
  "type": "Feature",
  "properties": {
    "iso:country":"GB",
    "sg:address":"Horse Mill La",
    "sg:city":"Somerton",
    "sg:classifiers":[
        {
            "category":"Farming",
            "subcategory":"Dairy Farm",
            "type":"Manufacturing & Wholesale Goods"
        }
    ],
    "sg:phone":"+44 1458 272829",
    "sg:postcode":"TA11 7PP",
    "sg:province":"Somerset",
    "wof:name":"Cricket St Thomas Dairies Ltd",
    "wof:placetype":"venue"
},
  "geometry": {"coordinates":[-2.7241179943,51.0559501648],"type":"Point"}
}