{
  "type": "Feature",
  "properties": {
    "addr:full":"Unit 1 A1 Trading Estate, Lewisham Road, Warley Smethwick West Midlands B66 2BS",
    "addr:housenumber":"unit 1 a1",
    "addr:postcode":"b66 2bs",
    "addr:street":"Trading Estate Lewisham Road",
    "iso:country":"GB",
    "sg:address":"Unit 1 A1 Trading Estate, Lewisham Road, Warley",
    "sg:city":"Smethwick",
    "sg:classifiers":[
        {
            "category":"Retail",
            "subcategory":"Repair Shop",
            "type":"Services"
        }
    ],
    "sg:phone":"+44 121 558 7506",
    "sg:postcode":"B66 2BS",
    "sg:province":"West Midlands",
    "sg:tags":[
        "sharpening",
        "tool"
    ],
    "wof:name":"M L Beebee",
    "wof:placetype":"venue"
},
  "geometry": {"coordinates":[-1.9661699533,52.5006599426],"type":"Point"}
}