{
  "type": "Feature",
  "properties": {
    "iso:country":"GB",
    "sg:address":"2 Main Street, Whittington",
    "sg:city":"Lichfield",
    "sg:classifiers":[
        {
            "category":"Bars & Pubs",
            "type":"Food & Drink"
        }
    ],
    "sg:postcode":"WS14 9JU",
    "sg:province":"Staffordshire",
    "sg:tags":[
        "pubs",
        "inn"
    ],
    "wof:name":"The Dog Inn",
    "wof:placetype":"venue"
},
  "geometry": {"coordinates":[-1.7635099888,52.6718788147],"type":"Point"}
}