{
  "type": "Feature",
  "properties": {
    "iso:country":"GB",
    "sg:address":"4 Market Road",
    "sg:city":"Rye",
    "sg:classifiers":[
        {
            "category":"Shopping",
            "subcategory":"Florist",
            "type":"Retail Goods"
        }
    ],
    "sg:phone":"+44 1797 222593",
    "sg:postcode":"TN31 7JA",
    "sg:province":"East Sussex",
    "wof:name":"Maison Fleur",
    "wof:placetype":"venue"
},
  "geometry": {"coordinates":[0.7346519828,50.9505004883],"type":"Point"}
}