{
  "type": "Feature",
  "properties": {
    "addr:full":"8 Buxton Road, High Lane Stockport Cheshire SK6 8BH",
    "addr:housenumber":"8",
    "addr:postcode":"sk6 8bh",
    "addr:street":"Buxton Road High Lane",
    "iso:country":"GB",
    "sg:address":"8 Buxton Road, High Lane",
    "sg:city":"Stockport",
    "sg:classifiers":[
        {
            "category":"Personal",
            "subcategory":"Beauty Salon",
            "type":"Services"
        }
    ],
    "sg:phone":"+44 1663 764242",
    "sg:postcode":"SK6 8BH",
    "sg:province":"Cheshire",
    "wof:name":"Beauty By Barnett",
    "wof:placetype":"venue"
},
  "geometry": {"coordinates":[-2.077154,53.365356],"type":"Point"}
}