{
  "type": "Feature",
  "properties": {
    "iso:country":"GB",
    "sg:address":"23b North Way, Deanshanger",
    "sg:city":"Milton Keynes",
    "sg:classifiers":[
        {
            "category":"Professional",
            "subcategory":"Computer Services",
            "type":"Services"
        }
    ],
    "sg:phone":"+44 1908 526395",
    "sg:postcode":"MK19 6NF",
    "sg:province":"Buckinghamshire",
    "sg:tags":[
        "system",
        "software"
    ],
    "wof:name":"Soul Stealers Ltd.",
    "wof:placetype":"venue"
},
  "geometry": {"coordinates":[-0.8918769956,52.0551109314],"type":"Point"}
}