{
  "type": "Feature",
  "properties": {
    "iso:country":"GB",
    "sg:address":"Unit 2, Shaw Road, Speke",
    "sg:city":"Liverpool",
    "sg:classifiers":[
        {
            "category":"Building & Trades",
            "subcategory":"Plumbing",
            "type":"Services"
        },
        {
            "category":"Home & Garden",
            "subcategory":"Hardware",
            "type":"Retail Goods"
        }
    ],
    "sg:phone":"+44 151 486 0907",
    "sg:postcode":"L24 9JT",
    "sg:province":"Merseyside",
    "sg:tags":[
        "merchant",
        "plumber",
        "plumbers'"
    ],
    "wof:name":"C M B Distributors",
    "wof:placetype":"venue"
},
  "geometry": {"coordinates":[-2.8464169502,53.3507919312],"type":"Point"}
}