{
  "type": "Feature",
  "properties": {
    "addr:full":"30 Malham Road Stourport-on-severn Worcestershire DY13 8NR",
    "addr:housenumber":"30",
    "addr:postcode":"dy13 8nr",
    "addr:street":"Malham Road",
    "iso:country":"GB",
    "sg:address":"30 Malham Road",
    "sg:city":"Stourport-on-severn",
    "sg:classifiers":[
        {
            "category":"Retail",
            "subcategory":"Driving School",
            "type":"Services"
        }
    ],
    "sg:phone":"+44 1299 825675",
    "sg:postcode":"DY13 8NR",
    "sg:province":"Worcestershire",
    "wof:name":"M S M School Of Motoring",
    "wof:placetype":"venue"
},
  "geometry": {"coordinates":[-2.287601,52.355358],"type":"Point"}
}