{
  "type": "Feature",
  "properties": {
    "addr:full":"1 Union Street Newton Abbot Devon TQ12 2JX",
    "addr:housenumber":"1",
    "addr:postcode":"tq12 2jx",
    "addr:street":"Union Street",
    "iso:country":"GB",
    "sg:address":"1 Union Street",
    "sg:city":"Newton Abbot",
    "sg:classifiers":[
        {
            "category":"Real Estate",
            "subcategory":"Real Estate Agent",
            "type":"Services"
        }
    ],
    "sg:phone":"+44 1626 202088",
    "sg:postcode":"TQ12 2JX",
    "sg:province":"Devon",
    "wof:name":"Dartmoor Estates & Property Management",
    "wof:placetype":"venue"
},
  "geometry": {"coordinates":[-3.609909,50.530178],"type":"Point"}
}