{
  "type": "Feature",
  "properties": {
    "addr:full":"5-7 Market Street Aylesbury Buckinghamshire HP20 2PN",
    "addr:housenumber":"5-7",
    "addr:postcode":"hp20 2pn",
    "addr:street":"Market Street",
    "iso:country":"GB",
    "sg:address":"5-7 Market Street",
    "sg:city":"Aylesbury",
    "sg:classifiers":[
        {
            "category":"Real Estate",
            "subcategory":"Real Estate Agent",
            "type":"Services"
        }
    ],
    "sg:phone":"+44 1296 488111",
    "sg:postcode":"HP20 2PN",
    "sg:province":"Buckinghamshire",
    "wof:name":"Brown & Merry",
    "wof:placetype":"venue"
},
  "geometry": {"coordinates":[-0.813556,51.81638],"type":"Point"}
}