{
  "type": "Feature",
  "properties": {
    "addr:full":"49 Market Street, Longton Stoke-on-trent Staffordshire ST3 1BW",
    "addr:housenumber":"49",
    "addr:postcode":"staffordshire st3 1bw",
    "addr:street":"Market Street",
    "iso:country":"GB",
    "sg:address":"49 Market Street, Longton",
    "sg:city":"Stoke-on-trent",
    "sg:classifiers":[
        {
            "category":"Banks & Credit Unions",
            "subcategory":"Financial Services",
            "type":"Services"
        }
    ],
    "sg:phone":"+44 1782 333368",
    "sg:postcode":"ST3 1BW",
    "sg:province":"Staffordshire",
    "sg:tags":[
        "adviser"
    ],
    "wof:name":"Paul Pritchard Financial Services",
    "wof:placetype":"venue"
},
  "geometry": {"coordinates":[-2.1332631111,52.988193512],"type":"Point"}
}