{
  "type": "Feature",
  "properties": {
    "addr:full":"London Road, Chalford Stroud Gloucestershire GL6 8PP",
    "addr:postcode":"gl6 8pp",
    "addr:street":"London Road",
    "iso:country":"GB",
    "sg:address":"London Road, Chalford",
    "sg:city":"Stroud",
    "sg:classifiers":[
        {
            "category":"Shopping",
            "subcategory":"Bicycles & Sporting Goods",
            "type":"Retail Goods"
        }
    ],
    "sg:phone":"+44 1453 884738",
    "sg:postcode":"GL6 8PP",
    "sg:province":"Gloucestershire",
    "sg:tags":[
        "cycle",
        "accessory"
    ],
    "wof:name":"Noah's Ark",
    "wof:placetype":"venue"
},
  "geometry": {"coordinates":[-2.157159,51.7215],"type":"Point"}
}