{
  "type": "Feature",
  "properties": {
    "addr:full":"3 Cattell Road, Cape Industrial Estate Warwick Warwickshire CV34 4JN",
    "addr:housenumber":"3",
    "addr:postcode":"cv34 4jn",
    "addr:street":"Cattell Road Cape Industrial Estate",
    "iso:country":"GB",
    "sg:address":"3 Cattell Road, Cape Industrial Estate",
    "sg:city":"Warwick",
    "sg:classifiers":[
        {
            "category":"Building & Trades",
            "subcategory":"Cleaning & Sanitation",
            "type":"Services"
        }
    ],
    "sg:phone":"+44 1926 496890",
    "sg:postcode":"CV34 4JN",
    "sg:province":"Warwickshire",
    "sg:tags":[
        "contracting",
        "commercial"
    ],
    "wof:name":"Hy-Kleen Of Warwick",
    "wof:placetype":"venue"
},
  "geometry": {"coordinates":[-1.5901479721,52.2864952087],"type":"Point"}
}