{
  "type": "Feature",
  "properties": {
    "iso:country":"GB",
    "sg:address":"Angel Place",
    "sg:city":"Worcester",
    "sg:classifiers":[
        {
            "category":"Bars & Pubs",
            "subcategory":"Nightclub",
            "type":"Food & Drink"
        }
    ],
    "sg:phone":"+44 1905 20218",
    "sg:postcode":"WR1 3QN",
    "sg:province":"Worcestershire",
    "sg:tags":[
        "club",
        "night"
    ],
    "wof:name":"Tramps Night Club",
    "wof:placetype":"venue"
},
  "geometry": {"coordinates":[-2.223091,52.193806],"type":"Point"}
}