{
  "type": "Feature",
  "properties": {
    "addr:full":"Unit 8 M1 Distribution Centre, Meadowhall Sheffield South Yorkshire S9 1EW",
    "addr:housenumber":"unit",
    "addr:postcode":"s9 1ew",
    "iso:country":"GB",
    "sg:address":"Unit 8 M1 Distribution Centre, Meadowhall",
    "sg:city":"Sheffield",
    "sg:classifiers":[
        {
            "category":"Shopping",
            "subcategory":"Beauty & Cosmetics",
            "type":"Retail Goods"
        }
    ],
    "sg:postcode":"S9 1EW",
    "sg:province":"South Yorkshire",
    "sg:tags":[
        "equipment",
        "supply",
        "hairdressing"
    ],
    "wof:name":"Shaw,Bill,",
    "wof:placetype":"venue"
},
  "geometry": {"coordinates":[-1.394774,53.407726],"type":"Point"}
}