{
  "type": "Feature",
  "properties": {
    "addr:full":"D S O Howe Bridge, Eckersley Fold La, Atherton Manchester Greater Manchester M46 9WS",
    "addr:housenumber":"s o",
    "addr:postcode":"manchester m46 9ws",
    "addr:street":"D;Howe Bridge Eckersley Fold La Atherton",
    "iso:country":"GB",
    "sg:address":"D S O Howe Bridge, Eckersley Fold La, Atherton",
    "sg:city":"Manchester",
    "sg:classifiers":[
        {
            "category":"Community Center",
            "type":"Public Place"
        }
    ],
    "sg:phone":"+44 1942 870403",
    "sg:postcode":"M46 9WS",
    "sg:province":"Greater Manchester",
    "sg:tags":[
        "recreation",
        "leisure",
        "centre"
    ],
    "wof:name":"WIGAN METROPOLITAN BOROUGH COUNCIL",
    "wof:placetype":"venue"
},
  "geometry": {"coordinates":[-2.4892408848,53.5231323242],"type":"Point"}
}