{
  "type": "Feature",
  "properties": {
    "addr:full":"1 Quarry Road Tunbridge Wells Kent TN1 2EY",
    "addr:housenumber":"1",
    "addr:postcode":"tn1 2ey",
    "addr:street":"Quarry Road",
    "iso:country":"GB",
    "sg:address":"1 Quarry Road",
    "sg:city":"Tunbridge Wells",
    "sg:classifiers":[
        {
            "category":"Fast Food",
            "type":"Food & Drink"
        },
        {
            "category":"Food & Beverages",
            "subcategory":"Meat & Fish",
            "type":"Retail Goods"
        }
    ],
    "sg:phone":"+44 1892 544020",
    "sg:postcode":"TN1 2EY",
    "sg:province":"Kent",
    "sg:tags":[
        "shop",
        "chip"
    ],
    "wof:name":"No.1 Fish & Chips",
    "wof:placetype":"venue"
},
  "geometry": {"coordinates":[0.270848006,51.1402893066],"type":"Point"}
}