{
  "type": "Feature",
  "properties": {
    "addr:full":"17 Ardross Street Inverness Highland IV3 5NS",
    "addr:housenumber":"17",
    "addr:postcode":"iv3 5ns",
    "addr:street":"Ardross Street",
    "iso:country":"GB",
    "sg:address":"17 Ardross Street",
    "sg:city":"Inverness",
    "sg:classifiers":[
        {
            "category":"Travel",
            "subcategory":"Hotels & Motels",
            "type":"Entertainment"
        }
    ],
    "sg:phone":"+44 1463 232549",
    "sg:postcode":"IV3 5NS",
    "sg:province":"Highland",
    "wof:name":"Whinpark Hotel",
    "wof:placetype":"venue"
},
  "geometry": {"coordinates":[-4.230697,57.474869],"type":"Point"}
}