{
  "type": "Feature",
  "properties": {
    "addr:full":"9 Rickfords Hill Aylesbury Buckinghamshire HP20 2RT",
    "addr:housenumber":"9",
    "addr:postcode":"hp20 2rt",
    "addr:street":"Rickfords Hill",
    "iso:country":"GB",
    "sg:address":"9 Rickfords Hill",
    "sg:city":"Aylesbury",
    "sg:classifiers":[
        {
            "category":"Health Services",
            "subcategory":"Clinic",
            "type":"Services"
        }
    ],
    "sg:phone":"+44 1296 428651",
    "sg:postcode":"HP20 2RT",
    "sg:province":"Buckinghamshire",
    "sg:tags":[
        "planning",
        "family",
        "centre"
    ],
    "wof:name":"LIFE Pregnancy Care Service",
    "wof:placetype":"venue"
},
  "geometry": {"coordinates":[-0.814615,51.816269],"type":"Point"}
}