{
  "type": "Feature",
  "properties": {
    "iso:country":"GB",
    "sg:address":"Anglo House, Worcester Road, Stourport On Severn",
    "sg:city":"Kidderminster",
    "sg:classifiers":[
        {
            "category":"Professional",
            "subcategory":"Computer Services",
            "type":"Services"
        }
    ],
    "sg:phone":"+44 1299 877004",
    "sg:postcode":"DY13 9AW",
    "sg:province":"Worcestershire",
    "sg:tags":[
        "system",
        "software"
    ],
    "wof:name":"Computerproof Ltd.",
    "wof:placetype":"venue"
},
  "geometry": {"coordinates":[-2.270903,52.339062],"type":"Point"}
}