{
  "type": "Feature",
  "properties": {
    "iso:country":"GB",
    "sg:address":"4 Penrallt Terrace",
    "sg:city":"Newport",
    "sg:classifiers":[
        {
            "category":"Professional",
            "subcategory":"Research",
            "type":"Services"
        }
    ],
    "sg:phone":"+44 1239 821088",
    "sg:postcode":"SA42 0QE",
    "sg:province":"Pembrokeshire",
    "sg:tags":[
        "market"
    ],
    "wof:name":"React",
    "wof:placetype":"venue"
},
  "geometry": {"coordinates":[-4.833977,52.016033],"type":"Point"}
}