{
  "type": "Feature",
  "properties": {
    "addr:full":"Whetley Lane Bradford West Yorkshire BD8 9HZ",
    "addr:postcode":"bd8 9hz",
    "addr:street":"Whetley Lane",
    "iso:country":"GB",
    "sg:address":"Whetley Lane",
    "sg:city":"Bradford",
    "sg:classifiers":[
        {
            "category":"Education",
            "subcategory":"School",
            "type":"Public Place"
        },
        {
            "category":"Government",
            "subcategory":"Office",
            "type":"Public Place"
        }
    ],
    "sg:phone":"+44 1274 543755",
    "sg:postcode":"BD8 9HZ",
    "sg:province":"West Yorkshire",
    "sg:tags":[
        "local",
        "authority"
    ],
    "wof:name":"Whetley Middle School",
    "wof:placetype":"venue"
},
  "geometry": {"coordinates":[-1.7763340473,53.8035507202],"type":"Point"}
}