{
  "type": "Feature",
  "properties": {
    "iso:country":"GB",
    "sg:address":"36 Church St",
    "sg:city":"London",
    "sg:classifiers":[
        {
            "category":"Shopping",
            "subcategory":"Antiques",
            "type":"Retail Goods"
        }
    ],
    "sg:postcode":"NW8 8EP",
    "sg:province":"Greater London",
    "wof:name":"Stavri,Lorraine,",
    "wof:placetype":"venue"
},
  "geometry": {"coordinates":[-0.1699430048,51.5238723755],"type":"Point"}
}