{
  "type": "Feature",
  "properties": {
    "iso:country":"GB",
    "sg:address":"127 Graham St",
    "sg:city":"Airdrie",
    "sg:classifiers":[
        {
            "category":"Bars & Pubs",
            "subcategory":"Nightclub",
            "type":"Food & Drink"
        }
    ],
    "sg:phone":"+44 1236 765881",
    "sg:postcode":"ML6 6DE",
    "sg:province":"North Lanarkshire",
    "sg:tags":[
        "club",
        "night"
    ],
    "wof:name":"Double A The",
    "wof:placetype":"venue"
},
  "geometry": {"coordinates":[-3.974944,55.866627],"type":"Point"}
}