{
  "type": "Feature",
  "properties": {
    "addr:full":"5 East Square Basildon Essex SS14 1HS",
    "addr:housenumber":"5",
    "addr:postcode":"ss14 1hs",
    "addr:street":"East Square",
    "iso:country":"GB",
    "sg:address":"5 East Square",
    "sg:city":"Basildon",
    "sg:classifiers":[
        {
            "category":"Food & Beverages",
            "subcategory":"Bakery",
            "type":"Retail Goods"
        }
    ],
    "sg:phone":"+44 1268 531475",
    "sg:postcode":"SS14 1HS",
    "sg:province":"Essex",
    "sg:tags":[
        "pizza"
    ],
    "wof:name":"Pizza Hut (U K) Ltd.",
    "wof:placetype":"venue"
},
  "geometry": {"coordinates":[0.4696640074,51.5697250366],"type":"Point"}
}