{
  "type": "Feature",
  "properties": {
    "addr:full":"61 Lillington Rd Leamington Spa Warwickshire CV32 6LF",
    "addr:housenumber":"61",
    "addr:postcode":"cv32 6lf",
    "addr:street":"Lillington Rd",
    "iso:country":"GB",
    "sg:address":"61 Lillington Rd",
    "sg:city":"Leamington Spa",
    "sg:classifiers":[
        {
            "category":"Organizations",
            "subcategory":"Community Association",
            "type":"Services"
        }
    ],
    "sg:postcode":"CV32 6LF",
    "sg:province":"Warwickshire",
    "sg:tags":[
        "society",
        "housing"
    ],
    "wof:name":"Warwickshire Federation of Women's Insti",
    "wof:placetype":"venue"
},
  "geometry": {"coordinates":[-1.5295610428,52.3037910461],"type":"Point"}
}