{
  "type": "Feature",
  "properties": {
    "iso:country":"GB",
    "sg:address":"34 Munches Street",
    "sg:city":"Dumfries",
    "sg:classifiers":[
        {
            "category":"Shopping",
            "subcategory":"Thrift Store",
            "type":"Retail Goods"
        }
    ],
    "sg:postcode":"DG1 1ET",
    "sg:province":"Dumfries and Galloway",
    "sg:tags":[
        "shop",
        "charity"
    ],
    "wof:name":"The Look-in Charity Shop",
    "wof:placetype":"venue"
},
  "geometry": {"coordinates":[-3.609224081,55.0691795349],"type":"Point"}
}