{
  "type": "Feature",
  "properties": {
    "iso:country":"GB",
    "sg:address":"Tonbridge Rd",
    "sg:city":"Tonbridge",
    "sg:classifiers":[
        {
            "category":"Manufacturing",
            "subcategory":"Rubber & Plastics",
            "type":"Manufacturing & Wholesale Goods"
        }
    ],
    "sg:phone":"+44 1732 850230",
    "sg:postcode":"TN11 0AH",
    "sg:province":"Kent",
    "sg:tags":[
        "mould"
    ],
    "wof:name":"E O C Normalien (UK) Ltd",
    "wof:placetype":"venue"
},
  "geometry": {"coordinates":[0.324694,51.219997],"type":"Point"}
}