{
  "type": "Feature",
  "properties": {
    "addr:full":"4 North Station Approach, South Nutfield Redhill Surrey RH1 4JF",
    "addr:housenumber":"4",
    "addr:postcode":"rh1 4jf",
    "addr:street":"North Station Approach",
    "iso:country":"GB",
    "sg:address":"4 North Station Approach, South Nutfield",
    "sg:city":"Redhill",
    "sg:classifiers":[
        {
            "category":"Retail",
            "subcategory":"Auto Repair",
            "type":"Services"
        }
    ],
    "sg:phone":"+44 1737 822313",
    "sg:postcode":"RH1 4JF",
    "sg:province":"Surrey",
    "sg:tags":[
        "modification",
        "garage"
    ],
    "wof:name":"South Nutfield Garage",
    "wof:placetype":"venue"
},
  "geometry": {"coordinates":[-0.1312749982,51.2274093628],"type":"Point"}
}