{
  "type": "Feature",
  "properties": {
    "addr:full":"62 London Road, Oadby Leicester Leicestershire LE2 5DH",
    "addr:housenumber":"62",
    "addr:postcode":"le2 5dh",
    "addr:street":"London Road",
    "iso:country":"GB",
    "sg:address":"62 London Road, Oadby",
    "sg:city":"Leicester",
    "sg:classifiers":[
        {
            "category":"Shopping",
            "subcategory":"News",
            "type":"Retail Goods"
        }
    ],
    "sg:phone":"+44 116 271 2514",
    "sg:postcode":"LE2 5DH",
    "sg:province":"Leicestershire",
    "sg:tags":[
        "newsagent"
    ],
    "wof:name":"Mercury News",
    "wof:placetype":"venue"
},
  "geometry": {"coordinates":[-1.077064991,52.5968780518],"type":"Point"}
}