{
  "type": "Feature",
  "properties": {
    "addr:full":"11 The Crescent, Holmesfield Dronfield Derbyshire S18 7WY",
    "addr:housenumber":"11",
    "addr:postcode":"s18 7wy",
    "addr:street":"The Crescent",
    "iso:country":"GB",
    "sg:address":"11 The Crescent, Holmesfield",
    "sg:city":"Dronfield",
    "sg:classifiers":[
        {
            "category":"Manufacturing",
            "subcategory":"Building Materials",
            "type":"Manufacturing & Wholesale Goods"
        }
    ],
    "sg:phone":"+44 114 289 1114",
    "sg:postcode":"S18 7WY",
    "sg:province":"Derbyshire",
    "sg:tags":[
        "tile",
        "mnfrs"
    ],
    "wof:name":"S Parkin",
    "wof:placetype":"venue"
},
  "geometry": {"coordinates":[-1.516095,53.296036],"type":"Point"}
}