{
  "type": "Feature",
  "properties": {
    "addr:full":"54 Fortune Green Rd Kilburn Greater London NW6 1UJ",
    "addr:housenumber":"54",
    "addr:postcode":"nw6 1uj",
    "addr:street":"Fortune Green Rd",
    "iso:country":"GB",
    "sg:address":"54 Fortune Green Rd",
    "sg:city":"Kilburn",
    "sg:classifiers":[
        {
            "category":"Organizations",
            "subcategory":"Community Association",
            "type":"Services"
        }
    ],
    "sg:phone":"+44 20 7435 6556",
    "sg:postcode":"NW6 1UJ",
    "sg:province":"Greater London",
    "sg:tags":[
        "society",
        "housing"
    ],
    "wof:name":"The Richmond Fellowship",
    "wof:placetype":"venue"
},
  "geometry": {"coordinates":[-0.195877,51.553905],"type":"Point"}
}