{
  "type": "Feature",
  "properties": {
    "addr:full":"137 Maindy Road Cardiff Cardiff CF24 4HN",
    "addr:housenumber":"137",
    "addr:postcode":"cf24 4hn",
    "addr:street":"Maindy Road",
    "iso:country":"GB",
    "sg:address":"137 Maindy Road",
    "sg:city":"Cardiff",
    "sg:classifiers":[
        {
            "category":"Retail",
            "subcategory":"Auto Repair",
            "type":"Services"
        }
    ],
    "sg:postcode":"CF24 4HN",
    "sg:province":"Cardiff",
    "sg:tags":[
        "engine",
        "car",
        "specialist"
    ],
    "wof:name":"Stadium Auto Sports",
    "wof:placetype":"venue"
},
  "geometry": {"coordinates":[-3.191179,51.496208],"type":"Point"}
}