{
  "type": "Feature",
  "properties": {
    "addr:full":"255 Monton Road, Eccles Manchester Greater Manchester M30 9PS",
    "addr:housenumber":"255",
    "addr:postcode":"m30 9ps",
    "addr:street":"Monton Road",
    "iso:country":"GB",
    "sg:address":"255 Monton Road, Eccles",
    "sg:city":"Manchester",
    "sg:classifiers":[
        {
            "category":"Professional",
            "subcategory":"Secretarial Services",
            "type":"Services"
        }
    ],
    "sg:postcode":"M30 9PS",
    "sg:province":"Greater Manchester",
    "wof:name":"B G Secretarial",
    "wof:placetype":"venue"
},
  "geometry": {"coordinates":[-2.353154,53.49168],"type":"Point"}
}