{
  "type": "Feature",
  "properties": {
    "iso:country":"GB",
    "sg:address":"255 Monton Road, Eccles",
    "sg:city":"Manchester",
    "sg:classifiers":[
        {
            "category":"Professional",
            "subcategory":"Secretarial Services",
            "type":"Services"
        }
    ],
    "sg:postcode":"M30 9PS",
    "sg:province":"Greater Manchester",
    "wof:name":"B G Secretarial",
    "wof:placetype":"venue"
},
  "geometry": {"coordinates":[-2.353154,53.49168],"type":"Point"}
}