{
  "type": "Feature",
  "properties": {
    "addr:full":"48 Loch Leven Road, Battlefield Glasgow Glasgow City G42 9JU",
    "addr:housenumber":"48",
    "addr:postcode":"g42 9ju",
    "addr:street":"Loch Leven Road",
    "iso:country":"GB",
    "sg:address":"48 Loch Leven Road, Battlefield",
    "sg:city":"Glasgow",
    "sg:classifiers":[
        {
            "category":"Professional",
            "subcategory":"Engineering",
            "type":"Services"
        }
    ],
    "sg:phone":"+44 141 632 0868",
    "sg:postcode":"G42 9JU",
    "sg:province":"Glasgow City",
    "sg:tags":[
        "contractor",
        "electrical",
        "engineer"
    ],
    "wof:name":"A Alexander & Son (Electrical) Ltd.",
    "wof:placetype":"venue"
},
  "geometry": {"coordinates":[-4.2661218643,55.8250198364],"type":"Point"}
}