{
  "type": "Feature",
  "properties": {
    "iso:country":"GB",
    "sg:address":"228 Frodingham Rd",
    "sg:city":"Scunthorpe",
    "sg:classifiers":[
        {
            "category":"Building & Trades",
            "subcategory":"Landscaping Services",
            "type":"Services"
        }
    ],
    "sg:postcode":"DN15 7NW",
    "sg:province":"Lincolnshire",
    "sg:tags":[
        "preservation",
        "timber"
    ],
    "wof:name":"Tate,Michael G,",
    "wof:placetype":"venue"
},
  "geometry": {"coordinates":[-0.6553890109,53.5967903137],"type":"Point"}
}