{
  "type": "Feature",
  "properties": {
    "iso:country":"GB",
    "sg:address":"Lower Synderford Farm, Synderford, Thorncombe",
    "sg:city":"Chard",
    "sg:classifiers":[
        {
            "category":"Farming",
            "subcategory":"Livestock Farm",
            "type":"Manufacturing & Wholesale Goods"
        }
    ],
    "sg:phone":"+44 1460 30204",
    "sg:postcode":"TA20 4QA",
    "sg:province":"Devon",
    "sg:tags":[
        "others"
    ],
    "wof:name":"Michael Turner",
    "wof:placetype":"venue"
},
  "geometry": {"coordinates":[-2.8884279728,50.8249282837],"type":"Point"}
}