{
  "type": "Feature",
  "properties": {
    "addr:full":"First Avenue, Porthill Newcastle Staffordshire ST5 8QX",
    "addr:postcode":"st5 8qx",
    "addr:street":"First Avenue",
    "iso:country":"GB",
    "sg:address":"First Avenue, Porthill",
    "sg:city":"Newcastle",
    "sg:classifiers":[
        {
            "category":"Health Services",
            "subcategory":"Nursing And Care Facility",
            "type":"Services"
        }
    ],
    "sg:phone":"+44 1782 636129",
    "sg:postcode":"ST5 8QX",
    "sg:province":"Staffordshire",
    "sg:tags":[
        "home"
    ],
    "wof:name":"Abberley House",
    "wof:placetype":"venue"
},
  "geometry": {"coordinates":[-2.2197489738,53.0378417969],"type":"Point"}
}