{
  "type": "Feature",
  "properties": {
    "iso:country":"GB",
    "sg:address":"Moorhouse, Westerham Road",
    "sg:city":"Westerham",
    "sg:classifiers":[
        {
            "category":"Manufacturing",
            "subcategory":"Building Materials",
            "type":"Manufacturing & Wholesale Goods"
        }
    ],
    "sg:phone":"+44 1959 567500",
    "sg:postcode":"TN16 2ET",
    "sg:province":"Kent",
    "sg:tags":[
        "tile",
        "mnfrs"
    ],
    "wof:name":"Lafarge Roofing Ltd.",
    "wof:placetype":"venue"
},
  "geometry": {"coordinates":[0.049046,51.259014],"type":"Point"}
}