{
  "type": "Feature",
  "properties": {
    "addr:full":"16 Market Buildings Maidstone Kent ME14 1HP",
    "addr:housenumber":"16",
    "addr:postcode":"me14 1hp",
    "addr:street":"Market Buildings",
    "iso:country":"GB",
    "sg:address":"16 Market Buildings",
    "sg:city":"Maidstone",
    "sg:classifiers":[
        {
            "category":"Shopping",
            "subcategory":"Crafts & Fabrics",
            "type":"Retail Goods"
        }
    ],
    "sg:phone":"+44 1622 753303",
    "sg:postcode":"ME14 1HP",
    "sg:province":"Kent",
    "sg:tags":[
        "shop",
        "needlecraft",
        "wool",
        "retailer"
    ],
    "wof:name":"Kent Yarncraft",
    "wof:placetype":"venue"
},
  "geometry": {"coordinates":[0.5219299793,51.2742118835],"type":"Point"}
}