{
  "type": "Feature",
  "properties": {
    "iso:country":"GB",
    "sg:address":"118-120 Cathedral Road",
    "sg:city":"Cardiff",
    "sg:classifiers":[
        {
            "category":"Travel",
            "subcategory":"Hotels & Motels",
            "type":"Entertainment"
        }
    ],
    "sg:phone":"+44 29 2039 5558",
    "sg:postcode":"CF11 9LQ",
    "sg:province":"Cardiff",
    "wof:name":"Lincoln House Hotel",
    "wof:placetype":"venue"
},
  "geometry": {"coordinates":[-3.196703,51.486961],"type":"Point"}
}