{
  "type": "Feature",
  "properties": {
    "iso:country":"GB",
    "sg:address":"Flat 3, Riverside Ct, 80 Whitworth Cres",
    "sg:city":"Southampton",
    "sg:classifiers":[
        {
            "category":"Education",
            "subcategory":"Music School",
            "type":"Public Place"
        }
    ],
    "sg:phone":"+44 23 8055 5202",
    "sg:postcode":"SO18 1GA",
    "sg:province":"Hampshire",
    "sg:tags":[
        "teacher"
    ],
    "wof:name":"J P Talbot",
    "wof:placetype":"venue"
},
  "geometry": {"coordinates":[-1.3760800362,50.9224510193],"type":"Point"}
}