{
  "type": "Feature",
  "properties": {
    "addr:full":"1a New Bridge Street Exeter Devon EX4 3JW",
    "addr:housenumber":"1a",
    "addr:postcode":"ex4 3jw",
    "addr:street":"New Bridge Street",
    "iso:country":"GB",
    "sg:address":"1a New Bridge Street",
    "sg:city":"Exeter",
    "sg:classifiers":[
        {
            "category":"Personal",
            "type":"Services"
        }
    ],
    "sg:phone":"+44 1392 491335",
    "sg:postcode":"EX4 3JW",
    "sg:province":"Devon",
    "sg:tags":[
        "wedding"
    ],
    "wof:name":"Lisa Valentine Colour Studio",
    "wof:placetype":"venue"
},
  "geometry": {"coordinates":[-3.5357079506,50.720085144],"type":"Point"}
}