{
  "type": "Feature",
  "properties": {
    "addr:full":"27 Bridgeland Street Bideford Devon EX39 2PZ",
    "addr:housenumber":"27",
    "addr:postcode":"ex39 2pz",
    "addr:street":"Bridgeland Street",
    "iso:country":"GB",
    "sg:address":"27 Bridgeland Street",
    "sg:city":"Bideford",
    "sg:classifiers":[
        {
            "category":"Professional",
            "subcategory":"Accounting & Tax Preparation",
            "type":"Services"
        }
    ],
    "sg:phone":"+44 1237 471881",
    "sg:postcode":"EX39 2PZ",
    "sg:province":"Devon",
    "sg:tags":[
        "accountant",
        "activity"
    ],
    "wof:name":"Glover Stanbury & Co.",
    "wof:placetype":"venue"
},
  "geometry": {"coordinates":[-4.205458,51.019684],"type":"Point"}
}