{
  "type": "Feature",
  "properties": {
    "addr:full":"Crosscrake Farm, Stainton Kendal Cumbria LA8 0LB",
    "addr:postcode":"la8 0lb",
    "iso:country":"GB",
    "sg:address":"Crosscrake Farm, Stainton",
    "sg:city":"Kendal",
    "sg:classifiers":[
        {
            "category":"Farming",
            "subcategory":"Livestock Farm",
            "type":"Manufacturing & Wholesale Goods"
        },
        {
            "category":"Farming",
            "subcategory":"Farm",
            "type":"Manufacturing & Wholesale Goods"
        }
    ],
    "sg:phone":"+44 15395 60807",
    "sg:postcode":"LA8 0LB",
    "sg:province":"Cumbria",
    "sg:tags":[
        "mixed",
        "crop",
        "others"
    ],
    "wof:name":"R T & M Sutton",
    "wof:placetype":"venue"
},
  "geometry": {"coordinates":[-2.7291300297,54.2779808044],"type":"Point"}
}