{
  "type": "Feature",
  "properties": {
    "iso:country":"GB",
    "sg:address":"North Lodge, Clifton Park Avenue, Clifton Park",
    "sg:city":"York",
    "sg:classifiers":[
        {
            "category":"Professional",
            "type":"Services"
        }
    ],
    "sg:phone":"+44 1904 673885",
    "sg:postcode":"YO30 5YX",
    "sg:province":"North Yorkshire",
    "sg:tags":[
        "shopfitters"
    ],
    "wof:name":"Gem Construction & Shopfitting Ltd.",
    "wof:placetype":"venue"
},
  "geometry": {"coordinates":[-1.10993,53.97747],"type":"Point"}
}