{
  "type": "Feature",
  "properties": {
    "addr:full":"Chapel Street, New Buckenham Norwich Norfolk NR16 2BB",
    "addr:postcode":"nr16 2bb",
    "addr:street":"Chapel Street",
    "iso:country":"GB",
    "sg:address":"Chapel Street, New Buckenham",
    "sg:city":"Norwich",
    "sg:classifiers":[
        {
            "category":"Bars & Pubs",
            "type":"Food & Drink"
        }
    ],
    "sg:phone":"+44 1953 860043",
    "sg:postcode":"NR16 2BB",
    "sg:province":"Norfolk",
    "sg:tags":[
        "pubs",
        "inn"
    ],
    "wof:name":"The George",
    "wof:placetype":"venue"
},
  "geometry": {"coordinates":[1.07189,52.472195],"type":"Point"}
}