{
  "type": "Feature",
  "properties": {
    "addr:full":"Po Box 111 Doncaster South Yorkshire DN1 3DQ",
    "addr:housenumber":"po;111",
    "addr:postcode":"dn1 3dq",
    "addr:street":"Box",
    "iso:country":"GB",
    "sg:address":"Po Box 111",
    "sg:city":"Doncaster",
    "sg:classifiers":[
        {
            "category":"Professional",
            "subcategory":"Lawyer & Legal Services",
            "type":"Services"
        }
    ],
    "sg:phone":"+44 1302 327136",
    "sg:postcode":"DN1 3DQ",
    "sg:province":"South Yorkshire",
    "sg:tags":[
        "solicitor"
    ],
    "wof:name":"Foy & Co.",
    "wof:placetype":"venue"
},
  "geometry": {"coordinates":[-1.130565,53.524391],"type":"Point"}
}