{
  "type": "Feature",
  "properties": {
    "addr:full":"Silver St Braintree Essex CM7 4BP",
    "addr:postcode":"cm7 4bp",
    "addr:street":"Silver St",
    "iso:country":"GB",
    "sg:address":"Silver St",
    "sg:city":"Braintree",
    "sg:classifiers":[
        {
            "category":"Government",
            "subcategory":"Police Station",
            "type":"Public Place"
        }
    ],
    "sg:phone":"+44 1371 850373",
    "sg:postcode":"CM7 4BP",
    "sg:province":"Essex",
    "sg:tags":[
        "support"
    ],
    "wof:name":"Wethersfield Police",
    "wof:placetype":"venue"
},
  "geometry": {"coordinates":[0.4840480089,51.9536094666],"type":"Point"}
}