{
  "type": "Feature",
  "properties": {
    "addr:full":"Dental Surgery, 30 Zetland Rd Bristol City of Bristol BS6 7AB",
    "addr:housenumber":"30",
    "addr:postcode":"bs6 7ab",
    "addr:street":"Zetland Rd",
    "iso:country":"GB",
    "sg:address":"Dental Surgery, 30 Zetland Rd",
    "sg:city":"Bristol",
    "sg:classifiers":[
        {
            "category":"Health Services",
            "subcategory":"Dentist",
            "type":"Services"
        }
    ],
    "sg:phone":"+44 117 942 4126",
    "sg:postcode":"BS6 7AB",
    "sg:province":"City of Bristol",
    "wof:name":"A M Cropper",
    "wof:placetype":"venue"
},
  "geometry": {"coordinates":[-2.6042790413,51.4791488647],"type":"Point"}
}