{
  "type": "Feature",
  "properties": {
    "addr:full":"1st Floor Suite, 32 Uppergate Aberdeen Aberdeen City AB10 1BA",
    "addr:housenumber":"suite 32",
    "addr:postcode":"ab10 1ba",
    "addr:street":"Uppergate Aberdeen",
    "iso:country":"GB",
    "sg:address":"1st Floor Suite, 32 Uppergate",
    "sg:city":"Aberdeen",
    "sg:classifiers":[
        {
            "category":"Professional",
            "subcategory":"Lawyer & Legal Services",
            "type":"Services"
        }
    ],
    "sg:postcode":"AB10 1BA",
    "sg:province":"Aberdeen City",
    "sg:tags":[
        "solicitor"
    ],
    "wof:name":"Taggart Masters",
    "wof:placetype":"venue"
},
  "geometry": {"coordinates":[-2.09863,57.148701],"type":"Point"}
}