{
  "type": "Feature",
  "properties": {
    "addr:full":"43 Darnall Rd Sheffield South Yorkshire S9 5AH",
    "addr:housenumber":"43",
    "addr:postcode":"s9 5ah",
    "addr:street":"Darnall Rd",
    "iso:country":"GB",
    "sg:address":"43 Darnall Rd",
    "sg:city":"Sheffield",
    "sg:classifiers":[
        {
            "category":"Professional",
            "subcategory":"Engineering",
            "type":"Services"
        }
    ],
    "sg:phone":"+44 114 261 0201",
    "sg:postcode":"S9 5AH",
    "sg:province":"South Yorkshire",
    "wof:name":"White Rock Engineering",
    "wof:placetype":"venue"
},
  "geometry": {"coordinates":[-1.424233,53.39349],"type":"Point"}
}