{
  "type": "Feature",
  "properties": {
    "iso:country":"GB",
    "sg:address":"208 Dashwood Avenue",
    "sg:city":"High Wycombe",
    "sg:classifiers":[
        {
            "category":"Shopping",
            "subcategory":"News",
            "type":"Retail Goods"
        }
    ],
    "sg:phone":"+44 1494 462155",
    "sg:postcode":"HP12 3DD",
    "sg:province":"Buckinghamshire",
    "sg:tags":[
        "newsagent"
    ],
    "wof:name":"Dashwood Newsagents",
    "wof:placetype":"venue"
},
  "geometry": {"coordinates":[-0.780924,51.634579],"type":"Point"}
}