{
  "type": "Feature",
  "properties": {
    "addr:full":"174 High Street Guildford Surrey GU1 3HW",
    "addr:housenumber":"174",
    "addr:postcode":"gu1 3hw",
    "addr:street":"High Street",
    "iso:country":"GB",
    "sg:address":"174 High Street",
    "sg:city":"Guildford",
    "sg:classifiers":[
        {
            "category":"Professional",
            "subcategory":"Business Services",
            "type":"Services"
        }
    ],
    "sg:phone":"+44 1483 539121",
    "sg:postcode":"GU1 3HW",
    "sg:province":"Surrey",
    "sg:tags":[
        "trade"
    ],
    "wof:name":"Corporation of Insurance  Financial & Mortgage Advisers Ltd.",
    "wof:placetype":"venue"
},
  "geometry": {"coordinates":[-0.570164,51.236382],"type":"Point"}
}