{
  "type": "Feature",
  "properties": {
    "iso:country":"GB",
    "sg:address":"14-16 Station Street West",
    "sg:city":"Coventry",
    "sg:classifiers":[
        {
            "category":"Wholesale",
            "subcategory":"Electrical",
            "type":"Manufacturing & Wholesale Goods"
        },
        {
            "category":"Shopping",
            "subcategory":"Computers & Home Electronics",
            "type":"Retail Goods"
        }
    ],
    "sg:phone":"+44 24 7668 3906",
    "sg:postcode":"CV6 5NB",
    "sg:province":"Warwickshire",
    "sg:tags":[
        "wholesaler"
    ],
    "wof:name":"G B Electrics",
    "wof:placetype":"venue"
},
  "geometry": {"coordinates":[-1.498847,52.429577],"type":"Point"}
}