{
  "type": "Feature",
  "properties": {
    "iso:country":"GB",
    "sg:address":"18-22 Disney Pl",
    "sg:city":"Southwark",
    "sg:classifiers":[
        {
            "category":"Shopping",
            "subcategory":"Gifts & Souvenirs",
            "type":"Retail Goods"
        }
    ],
    "sg:phone":"+44 20 7403 0144",
    "sg:postcode":"SE1 1HJ",
    "sg:province":"Greater London",
    "sg:tags":[
        "greeting",
        "card"
    ],
    "wof:name":"Dynamite Inc",
    "wof:placetype":"venue"
},
  "geometry": {"coordinates":[-0.0942,51.501839],"type":"Point"}
}