{
  "type": "Feature",
  "properties": {
    "addr:full":"252 Fulham Road London Greater London SW10 9NA",
    "addr:housenumber":"252",
    "addr:postcode":"sw10 9na",
    "addr:street":"Fulham Road",
    "iso:country":"GB",
    "sg:address":"252 Fulham Road",
    "sg:city":"London",
    "sg:classifiers":[
        {
            "category":"Education",
            "subcategory":"School",
            "type":"Public Place"
        }
    ],
    "sg:phone":"+44 20 7352 2588",
    "sg:postcode":"SW10 9NA",
    "sg:province":"Greater London",
    "sg:tags":[
        "local",
        "authority"
    ],
    "wof:name":"Servite R C Primary School",
    "wof:placetype":"venue"
},
  "geometry": {"coordinates":[-0.1834560037,51.4847412109],"type":"Point"}
}