{
  "type": "Feature",
  "properties": {
    "addr:full":"Graphics House, Charnley Road Blackpool Lancashire FY1 4PE",
    "addr:postcode":"fy1 4pe",
    "addr:street":"Charnley Road",
    "iso:country":"GB",
    "sg:address":"Graphics House, Charnley Road",
    "sg:city":"Blackpool",
    "sg:classifiers":[
        {
            "category":"Shopping",
            "subcategory":"Crafts & Fabrics",
            "type":"Retail Goods"
        }
    ],
    "sg:phone":"+44 1253 624402",
    "sg:postcode":"FY1 4PE",
    "sg:province":"Lancashire",
    "sg:tags":[
        "material",
        "graphic",
        "art"
    ],
    "wof:name":"Granthams Graphic Technology",
    "wof:placetype":"venue"
},
  "geometry": {"coordinates":[-3.046459,53.815933],"type":"Point"}
}