{
  "type": "Feature",
  "properties": {
    "iso:country":"GB",
    "sg:address":"23a Victoria Street, Holmfirth",
    "sg:city":"Huddersfield",
    "sg:classifiers":[
        {
            "category":"Restaurant",
            "type":"Food & Drink"
        }
    ],
    "sg:phone":"+44 1484 688121",
    "sg:postcode":"HD9 7DF",
    "sg:province":"South Yorkshire",
    "wof:name":"Poppa Piccolinos",
    "wof:placetype":"venue"
},
  "geometry": {"coordinates":[-1.78707,53.569901],"type":"Point"}
}