{
  "type": "Feature",
  "properties": {
    "iso:country":"GB",
    "sg:address":"1174 Rochdale Road",
    "sg:city":"Manchester",
    "sg:classifiers":[
        {
            "category":"Fast Food",
            "type":"Food & Drink"
        }
    ],
    "sg:phone":"+44 161 720 8563",
    "sg:postcode":"M9 6ER",
    "sg:province":"Greater Manchester",
    "sg:tags":[
        "away",
        "meal",
        "outlet",
        "take"
    ],
    "wof:name":"Sandwich Bar",
    "wof:placetype":"venue"
},
  "geometry": {"coordinates":[-2.204244,53.53138],"type":"Point"}
}