{
  "type": "Feature",
  "properties": {
    "iso:country":"GB",
    "sg:address":"26 Craiksland Pl",
    "sg:city":"Troon",
    "sg:classifiers":[
        {
            "category":"Shopping",
            "subcategory":"Pets & Pet Supplies",
            "type":"Retail Goods"
        }
    ],
    "sg:phone":"+44 1292 311222",
    "sg:postcode":"KA10 7LQ",
    "sg:province":"South Ayrshire",
    "sg:tags":[
        "food"
    ],
    "wof:name":"A J Henry",
    "wof:placetype":"venue"
},
  "geometry": {"coordinates":[-4.6255722046,55.5506896973],"type":"Point"}
}