{
  "type": "Feature",
  "properties": {
    "addr:full":"44 Nolton Place Edgware Greater London HA8 6DL",
    "addr:housenumber":"44",
    "addr:postcode":"ha8 6dl",
    "addr:street":"Nolton Place",
    "iso:country":"GB",
    "sg:address":"44 Nolton Place",
    "sg:city":"Edgware",
    "sg:classifiers":[
        {
            "category":"Professional",
            "subcategory":"Management & Consulting",
            "type":"Services"
        }
    ],
    "sg:phone":"+44 20 8952 0388",
    "sg:postcode":"HA8 6DL",
    "sg:province":"Greater London",
    "sg:tags":[
        "consultant",
        "business"
    ],
    "wof:name":"Hi-Fliers Travel",
    "wof:placetype":"venue"
},
  "geometry": {"coordinates":[-0.28549,51.601143],"type":"Point"}
}