{
  "type": "Feature",
  "properties": {
    "addr:full":"Railway Street Gillingham Kent ME7 1XJ",
    "addr:postcode":"me7 1xj",
    "addr:street":"Railway Street",
    "iso:country":"GB",
    "sg:address":"Railway Street",
    "sg:city":"Gillingham",
    "sg:classifiers":[
        {
            "category":"Autos & Motor Vehicles",
            "subcategory":"Fuel & Gas Station",
            "type":"Retail Goods"
        }
    ],
    "sg:postcode":"ME7 1XJ",
    "sg:province":"Kent",
    "sg:tags":[
        "petrol",
        "filling"
    ],
    "wof:name":"Railside Service Station",
    "wof:placetype":"venue"
},
  "geometry": {"coordinates":[0.5570350289,51.387878418],"type":"Point"}
}