{
  "type": "Feature",
  "properties": {
    "addr:full":"13 Bon Accord Crescent Aberdeen Aberdeen City AB11 6NN",
    "addr:housenumber":"13",
    "addr:postcode":"ab11 6nn",
    "addr:street":"Bon Accord Crescent",
    "iso:country":"GB",
    "sg:address":"13 Bon Accord Crescent",
    "sg:city":"Aberdeen",
    "sg:classifiers":[
        {
            "category":"Professional",
            "subcategory":"Lawyer & Legal Services",
            "type":"Services"
        }
    ],
    "sg:postcode":"AB11 6NN",
    "sg:province":"Aberdeen City",
    "sg:tags":[
        "solicitor"
    ],
    "wof:name":"Craigens",
    "wof:placetype":"venue"
},
  "geometry": {"coordinates":[-2.1062569618,57.1416702271],"type":"Point"}
}