{
  "type": "Feature",
  "properties": {
    "iso:country":"GB",
    "sg:address":"4/5 Loveridge Mews, Loveridge Road",
    "sg:city":"London",
    "sg:classifiers":[
        {
            "category":"Military Area",
            "subcategory":"Air Force Base",
            "type":"Public Place"
        }
    ],
    "sg:postcode":"NW6 2DP",
    "sg:province":"Greater London",
    "sg:tags":[
        "water",
        "treatment"
    ],
    "wof:name":"Stefani Water Purifiers Ltd",
    "wof:placetype":"venue"
},
  "geometry": {"coordinates":[-0.202576,51.546265],"type":"Point"}
}