{
  "type": "Feature",
  "properties": {
    "addr:full":"Fieldings Road, Cheshunt Waltham Cross Essex EN8 9TY",
    "addr:postcode":"en8 9ty",
    "addr:street":"Fieldings Road",
    "iso:country":"GB",
    "sg:address":"Fieldings Road, Cheshunt",
    "sg:city":"Waltham Cross",
    "sg:classifiers":[
        {
            "category":"Building & Trades",
            "subcategory":"Landscaping Services",
            "type":"Services"
        }
    ],
    "sg:phone":"+44 1992 623232",
    "sg:postcode":"EN8 9TY",
    "sg:province":"Essex",
    "sg:tags":[
        "irrigation",
        "system"
    ],
    "wof:name":"E J Woollard Ltd.",
    "wof:placetype":"venue"
},
  "geometry": {"coordinates":[-0.024035,51.709133],"type":"Point"}
}