{
  "type": "Feature",
  "properties": {
    "iso:country":"GB",
    "sg:address":"24 Marine Place",
    "sg:city":"Worthing",
    "sg:classifiers":[
        {
            "category":"Professional",
            "subcategory":"Computer Services",
            "type":"Services"
        }
    ],
    "sg:phone":"+44 1903 210315",
    "sg:postcode":"BN11 3DN",
    "sg:province":"West Sussex",
    "sg:tags":[
        "information"
    ],
    "wof:name":"The Information Shop for Young People",
    "wof:placetype":"venue"
},
  "geometry": {"coordinates":[-0.3690820038,50.8108177185],"type":"Point"}
}