{
  "type": "Feature",
  "properties": {
    "iso:country":"GB",
    "sg:address":"32 Moor Street, Kirkham",
    "sg:city":"Preston",
    "sg:classifiers":[
        {
            "category":"Shopping",
            "subcategory":"Pharmacy",
            "type":"Retail Goods"
        }
    ],
    "sg:phone":"+44 1772 683453",
    "sg:postcode":"PR4 2AU",
    "sg:province":"Lancashire",
    "sg:tags":[
        "dispensing",
        "store",
        "pharmacist",
        "chemist",
        "drug"
    ],
    "wof:name":"Moor Street Pharmacy",
    "wof:placetype":"venue"
},
  "geometry": {"coordinates":[-2.878988,53.781731],"type":"Point"}
}