{
  "type": "Feature",
  "properties": {
    "iso:country":"GB",
    "sg:address":"43 Tyndale Street",
    "sg:city":"Leicester",
    "sg:classifiers":[
        {
            "category":"Professional",
            "subcategory":"Computer Services",
            "type":"Services"
        }
    ],
    "sg:phone":"+44 116 254 1052",
    "sg:postcode":"LE3 0QQ",
    "sg:province":"Leicestershire",
    "sg:tags":[
        "system",
        "software"
    ],
    "wof:name":"Casehope Ltd.",
    "wof:placetype":"venue"
},
  "geometry": {"coordinates":[-1.15142,52.630562],"type":"Point"}
}