{
  "type": "Feature",
  "properties": {
    "addr:full":"94 High Street Dudley West Midlands DY2 7BJ",
    "addr:housenumber":"94",
    "addr:postcode":"dy2 7bj",
    "addr:street":"High Street",
    "iso:country":"GB",
    "sg:address":"94 High Street",
    "sg:city":"Dudley",
    "sg:classifiers":[
        {
            "category":"Food & Beverages",
            "subcategory":"Meat & Fish",
            "type":"Retail Goods"
        }
    ],
    "sg:postcode":"DY2 7BJ",
    "sg:province":"West Midlands",
    "sg:tags":[
        "butcher"
    ],
    "wof:name":"Walter Smith",
    "wof:placetype":"venue"
},
  "geometry": {"coordinates":[-2.068871,52.507854],"type":"Point"}
}