{
  "type": "Feature",
  "properties": {
    "iso:country":"GB",
    "sg:address":"Canning Circus",
    "sg:city":"Nottingham",
    "sg:classifiers":[
        {
            "category":"Bars & Pubs",
            "type":"Food & Drink"
        }
    ],
    "sg:postcode":"NG7 3NE",
    "sg:province":"Nottinghamshire",
    "sg:tags":[
        "pubs",
        "inn"
    ],
    "wof:name":"Michael Doherty",
    "wof:placetype":"venue"
},
  "geometry": {"coordinates":[-1.1612240076,52.955909729],"type":"Point"}
}