{
  "type": "Feature",
  "properties": {
    "addr:full":"132 Church Road Croydon Surrey CR0 1SE",
    "addr:housenumber":"132",
    "addr:postcode":"cr0 1se",
    "addr:street":"Church Road",
    "iso:country":"GB",
    "sg:address":"132 Church Road",
    "sg:city":"Croydon",
    "sg:classifiers":[
        {
            "category":"Retail",
            "subcategory":"Auto Repair",
            "type":"Services"
        }
    ],
    "sg:phone":"+44 20 8688 6255",
    "sg:postcode":"CR0 1SE",
    "sg:province":"Surrey",
    "sg:tags":[
        "modification",
        "garage"
    ],
    "wof:name":"R B Curtis",
    "wof:placetype":"venue"
},
  "geometry": {"coordinates":[-0.10358,51.370247],"type":"Point"}
}