{
  "type": "Feature",
  "properties": {
    "addr:full":"Radley Abingdon Oxfordshire OX14 2HR",
    "addr:postcode":"ox14 2hr",
    "iso:country":"GB",
    "sg:address":"Radley",
    "sg:city":"Abingdon",
    "sg:classifiers":[
        {
            "category":"Education",
            "subcategory":"School",
            "type":"Public Place"
        }
    ],
    "sg:postcode":"OX14 2HR",
    "sg:province":"Oxfordshire",
    "sg:tags":[
        "independent",
        "preparatory"
    ],
    "wof:name":"Radley College",
    "wof:placetype":"venue"
},
  "geometry": {"coordinates":[-1.24981,51.693439],"type":"Point"}
}