{
  "type": "Feature",
  "properties": {
    "iso:country":"GB",
    "sg:address":"32 Heaton Moor Road",
    "sg:city":"Stockport",
    "sg:classifiers":[
        {
            "category":"Health Services",
            "subcategory":"Doctor",
            "type":"Services"
        },
        {
            "category":"Health Services",
            "subcategory":"Clinic",
            "type":"Services"
        }
    ],
    "sg:phone":"+44 161 432 2142",
    "sg:postcode":"SK4 4NX",
    "sg:province":"Cheshire",
    "sg:tags":[
        "nh",
        "practitioners"
    ],
    "wof:name":"Heaton Moor Medical Centre",
    "wof:placetype":"venue"
},
  "geometry": {"coordinates":[-2.179563,53.425041],"type":"Point"}
}