{
  "type": "Feature",
  "properties": {
    "iso:country":"GB",
    "sg:address":"58 Chapel St",
    "sg:city":"Chorley",
    "sg:classifiers":[
        {
            "category":"Fast Food",
            "type":"Food & Drink"
        }
    ],
    "sg:phone":"+44 1257 264096",
    "sg:postcode":"PR7 1BS",
    "sg:province":"Lancashire",
    "sg:tags":[
        "away",
        "take"
    ],
    "wof:name":"Giadas",
    "wof:placetype":"venue"
},
  "geometry": {"coordinates":[-2.6277580261,53.6522865295],"type":"Point"}
}