{
  "type": "Feature",
  "properties": {
    "iso:country":"GB",
    "sg:address":"Unit T12 32 Sovereign St",
    "sg:city":"Leeds",
    "sg:classifiers":[
        {
            "category":"Professional",
            "subcategory":"Employment Agencies",
            "type":"Services"
        }
    ],
    "sg:postcode":"LS1 4BJ",
    "sg:province":"West Yorkshire",
    "sg:tags":[
        "consultant"
    ],
    "wof:name":"Tomkins,Anthony,",
    "wof:placetype":"venue"
},
  "geometry": {"coordinates":[-1.543122,53.793972],"type":"Point"}
}