{
  "type": "Feature",
  "properties": {
    "iso:country":"GB",
    "sg:address":"20 Melcombe St",
    "sg:city":"London",
    "sg:classifiers":[
        {
            "category":"Real Estate",
            "subcategory":"Real Estate Agent",
            "type":"Services"
        }
    ],
    "sg:postcode":"NW1 6AH",
    "sg:province":"Greater London",
    "wof:name":"Bartholomew Estates Ltd",
    "wof:placetype":"venue"
},
  "geometry": {"coordinates":[-0.1599059999,51.522857666],"type":"Point"}
}