{
  "type": "Feature",
  "properties": {
    "addr:full":"25 Station Approach, Hayes Bromley Kent BR2 7EQ",
    "addr:housenumber":"25",
    "addr:postcode":"br2 7eq",
    "addr:street":"Station Approach",
    "iso:country":"GB",
    "sg:address":"25 Station Approach, Hayes",
    "sg:city":"Bromley",
    "sg:classifiers":[
        {
            "category":"Shopping",
            "subcategory":"Music",
            "type":"Retail Goods"
        }
    ],
    "sg:phone":"+44 20 8462 1293",
    "sg:postcode":"BR2 7EQ",
    "sg:province":"Kent",
    "sg:tags":[
        "record",
        "tape",
        "cd"
    ],
    "wof:name":"M Cookman",
    "wof:placetype":"venue"
},
  "geometry": {"coordinates":[0.011361,51.377048],"type":"Point"}
}