{
  "type": "Feature",
  "properties": {
    "iso:country":"GB",
    "sg:address":"2 Warners Mill, Silks Way",
    "sg:city":"Braintree",
    "sg:classifiers":[
        {
            "category":"Professional",
            "subcategory":"Detective & Security Services",
            "type":"Services"
        }
    ],
    "sg:postcode":"CM7 3GB",
    "sg:province":"Essex",
    "wof:name":"Tann,John,Security Services Ltd",
    "wof:placetype":"venue"
},
  "geometry": {"coordinates":[0.553242,51.877758],"type":"Point"}
}