{
  "type": "Feature",
  "properties": {
    "iso:country":"GB",
    "sg:address":"Oakfield House, Level Street",
    "sg:city":"Brierley Hill",
    "sg:classifiers":[
        {
            "category":"Home & Garden",
            "subcategory":"Furniture",
            "type":"Retail Goods"
        }
    ],
    "sg:phone":"+44 1384 79393",
    "sg:postcode":"DY5 1TZ",
    "sg:province":"West Midlands",
    "wof:name":"Levines",
    "wof:placetype":"venue"
},
  "geometry": {"coordinates":[-2.115724,52.484322],"type":"Point"}
}