{
  "type": "Feature",
  "properties": {
    "addr:full":"Stanhope Road Swadlincote Derbyshire DE11 9BG",
    "addr:postcode":"de11 9bg",
    "addr:street":"Stanhope Road",
    "iso:country":"GB",
    "sg:address":"Stanhope Road",
    "sg:city":"Swadlincote",
    "sg:classifiers":[
        {
            "category":"Retail",
            "subcategory":"Auto Repair",
            "type":"Services"
        }
    ],
    "sg:phone":"+44 1283 214639",
    "sg:postcode":"DE11 9BG",
    "sg:province":"Derbyshire",
    "sg:tags":[
        "modification",
        "garage",
        "related"
    ],
    "wof:name":"L & C Motors",
    "wof:placetype":"venue"
},
  "geometry": {"coordinates":[-1.560909,52.770901],"type":"Point"}
}