{
  "type": "Feature",
  "properties": {
    "iso:country":"GB",
    "sg:address":"Burnstone, Higher Clovelly",
    "sg:city":"Bideford",
    "sg:classifiers":[
        {
            "category":"Travel",
            "subcategory":"Hotels & Motels",
            "type":"Entertainment"
        }
    ],
    "sg:phone":"+44 1237 431219",
    "sg:postcode":"EX39 5RX",
    "sg:province":"Devon",
    "sg:tags":[
        "self",
        "catering"
    ],
    "wof:name":"Clovelly Lakeside Lodges",
    "wof:placetype":"venue"
},
  "geometry": {"coordinates":[-4.406489,50.999367],"type":"Point"}
}