{
  "type": "Feature",
  "properties": {
    "addr:full":"28a Kensington Church Street London Greater London W8 4EP",
    "addr:housenumber":"28a",
    "addr:postcode":"w8 4ep",
    "addr:street":"Kensington Church Street",
    "iso:country":"GB",
    "sg:address":"28a Kensington Church Street",
    "sg:city":"London",
    "sg:classifiers":[
        {
            "category":"Shopping",
            "subcategory":"Clothing, Apparel, & Fashions",
            "type":"Retail Goods"
        }
    ],
    "sg:phone":"+44 20 7938 4019",
    "sg:postcode":"W8 4EP",
    "sg:province":"Greater London",
    "sg:tags":[
        "ladieswear"
    ],
    "wof:name":"Oasis Stores",
    "wof:placetype":"venue"
},
  "geometry": {"coordinates":[-0.191376,51.503124],"type":"Point"}
}