{
  "type": "Feature",
  "properties": {
    "iso:country":"GB",
    "sg:address":"70 Soho Road",
    "sg:city":"Birmingham",
    "sg:classifiers":[
        {
            "category":"Organizations",
            "subcategory":"Membership Organization",
            "type":"Services"
        }
    ],
    "sg:phone":"+44 1746 787627",
    "sg:postcode":"B21 9SR",
    "sg:province":"West Midlands",
    "sg:tags":[
        "club"
    ],
    "wof:name":"M P D Management Ltd.",
    "wof:placetype":"venue"
},
  "geometry": {"coordinates":[-1.92642,52.501808],"type":"Point"}
}