{
  "type": "Feature",
  "properties": {
    "addr:full":"56 Hall Road, Morgate Rotherham South Yorkshire S60 2BW",
    "addr:housenumber":"56",
    "addr:postcode":"s60 2bw",
    "addr:street":"Hall Road Morgate",
    "iso:country":"GB",
    "sg:address":"56 Hall Road, Morgate",
    "sg:city":"Rotherham",
    "sg:classifiers":[
        {
            "category":"Professional",
            "subcategory":"Accounting & Tax Preparation",
            "type":"Services"
        }
    ],
    "sg:postcode":"S60 2BW",
    "sg:province":"South Yorkshire",
    "sg:tags":[
        "accountant"
    ],
    "wof:name":"Sam Book-Keeping & Accounts Services",
    "wof:placetype":"venue"
},
  "geometry": {"coordinates":[-1.348754,53.422245],"type":"Point"}
}