{
  "type": "Feature",
  "properties": {
    "addr:full":"Westminster Road Salisbury Wiltshire SP2 7DG",
    "addr:postcode":"sp2 7dg",
    "addr:street":"Westminster Road",
    "iso:country":"GB",
    "sg:address":"Westminster Road",
    "sg:city":"Salisbury",
    "sg:classifiers":[
        {
            "category":"Education",
            "subcategory":"School",
            "type":"Public Place"
        },
        {
            "category":"Government",
            "subcategory":"Office",
            "type":"Public Place"
        }
    ],
    "sg:phone":"+44 1722 336459",
    "sg:postcode":"SP2 7DG",
    "sg:province":"Wiltshire",
    "sg:tags":[
        "local",
        "authority"
    ],
    "wof:name":"Sarum St Paul's C of E (Aided) Primary School",
    "wof:placetype":"venue"
},
  "geometry": {"coordinates":[-1.8064490557,51.0766296387],"type":"Point"}
}