{
  "type": "Feature",
  "properties": {
    "addr:full":"Axe & Cleaver Lane, Woodmarsh, North Bradley Trowbridge Wiltshire BA14 0SZ",
    "addr:postcode":"ba14 0sz",
    "addr:street":"Lane;North",
    "iso:country":"GB",
    "sg:address":"Axe & Cleaver Lane, Woodmarsh, North Bradley",
    "sg:city":"Trowbridge",
    "sg:classifiers":[
        {
            "category":"Building & Trades",
            "subcategory":"Construction",
            "type":"Services"
        }
    ],
    "sg:phone":"+44 1225 754091",
    "sg:postcode":"BA14 0SZ",
    "sg:province":"Wiltshire",
    "sg:tags":[
        "roofing",
        "contracting"
    ],
    "wof:name":"M J Faint Ltd",
    "wof:placetype":"venue"
},
  "geometry": {"coordinates":[-2.21426,51.29998],"type":"Point"}
}