{
  "type": "Feature",
  "properties": {
    "iso:country":"GB",
    "sg:address":"109 Stockport Rd",
    "sg:city":"Stockport",
    "sg:classifiers":[
        {
            "category":"Real Estate",
            "subcategory":"Real Estate Agent",
            "type":"Services"
        }
    ],
    "sg:phone":"+44 161 427 5500",
    "sg:postcode":"SK6 6AF",
    "sg:province":"Cheshire",
    "wof:name":"Clarendon Property Management Ltd",
    "wof:placetype":"venue"
},
  "geometry": {"coordinates":[-2.06737,53.395069],"type":"Point"}
}