{
  "type": "Feature",
  "properties": {
    "iso:country":"GB",
    "sg:address":"225 Shields Road",
    "sg:city":"Newcastle-upon-tyne",
    "sg:classifiers":[
        {
            "category":"Food & Beverages",
            "subcategory":"Meat & Fish",
            "type":"Retail Goods"
        }
    ],
    "sg:postcode":"NE6 1DQ",
    "sg:province":"Tyne and Wear",
    "sg:tags":[
        "butcher"
    ],
    "wof:name":"Byker Butchers",
    "wof:placetype":"venue"
},
  "geometry": {"coordinates":[-1.577514,54.977795],"type":"Point"}
}