{
  "type": "Feature",
  "properties": {
    "addr:full":"8 Stoke Newington High Street London Greater London N16 7PL",
    "addr:housenumber":"8",
    "addr:postcode":"n16 7pl",
    "addr:street":"Stoke Newington High Street",
    "iso:country":"GB",
    "sg:address":"8 Stoke Newington High Street",
    "sg:city":"London",
    "sg:classifiers":[
        {
            "category":"Building & Trades",
            "subcategory":"Plumbing",
            "type":"Services"
        },
        {
            "category":"Home & Garden",
            "subcategory":"Hardware",
            "type":"Retail Goods"
        }
    ],
    "sg:phone":"+44 20 7254 9897",
    "sg:postcode":"N16 7PL",
    "sg:province":"Greater London",
    "sg:tags":[
        "merchant",
        "plumber",
        "plumbers'"
    ],
    "wof:name":"Histohome Ltd",
    "wof:placetype":"venue"
},
  "geometry": {"coordinates":[-0.0743990019,51.5574188232],"type":"Point"}
}