{
  "type": "Feature",
  "properties": {
    "addr:full":"138-142 Bury New Road, Whitefield Manchester Lancashire M45 6AD",
    "addr:housenumber":"138-142",
    "addr:postcode":"m45 6ad",
    "addr:street":"Bury New Road",
    "iso:country":"GB",
    "sg:address":"138-142 Bury New Road, Whitefield",
    "sg:city":"Manchester",
    "sg:classifiers":[
        {
            "category":"Arts & Performance",
            "subcategory":"Art Gallery",
            "type":"Entertainment"
        },
        {
            "category":"Museum",
            "type":"Entertainment"
        }
    ],
    "sg:postcode":"M45 6AD",
    "sg:province":"Lancashire",
    "wof:name":"Henry Donn",
    "wof:placetype":"venue"
},
  "geometry": {"coordinates":[-2.292705,53.547119],"type":"Point"}
}