{
  "type": "Feature",
  "properties": {
    "addr:full":"31-33 King Cross St Halifax West Yorkshire HX1 3JZ",
    "addr:housenumber":"31-33",
    "addr:postcode":"hx1 3jz",
    "addr:street":"King Cross St",
    "iso:country":"GB",
    "sg:address":"31-33 King Cross St",
    "sg:city":"Halifax",
    "sg:classifiers":[
        {
            "category":"Bars & Pubs",
            "type":"Food & Drink"
        }
    ],
    "sg:postcode":"HX1 3JZ",
    "sg:province":"West Yorkshire",
    "sg:tags":[
        "pubs",
        "inn"
    ],
    "wof:name":"Osbourne,D,",
    "wof:placetype":"venue"
},
  "geometry": {"coordinates":[-1.8753739595,53.7172470093],"type":"Point"}
}