{
  "type": "Feature",
  "properties": {
    "addr:full":"82 Aldwick Road Bognor Regis West Sussex PO21 2PE",
    "addr:housenumber":"82",
    "addr:postcode":"po21 2pe",
    "addr:street":"Aldwick Road",
    "iso:country":"GB",
    "sg:address":"82 Aldwick Road",
    "sg:city":"Bognor Regis",
    "sg:classifiers":[
        {
            "category":"Food & Beverages",
            "subcategory":"Meat & Fish",
            "type":"Retail Goods"
        }
    ],
    "sg:phone":"+44 1243 821028",
    "sg:postcode":"PO21 2PE",
    "sg:province":"West Sussex",
    "sg:tags":[
        "butcher"
    ],
    "wof:name":"C & N Lawrence",
    "wof:placetype":"venue"
},
  "geometry": {"coordinates":[-0.6872680187,50.7816505432],"type":"Point"}
}