{
  "type": "Feature",
  "properties": {
    "addr:full":"Riccall Grange Cottage York North Yorkshire YO19 6QL",
    "addr:postcode":"yo19 6ql",
    "addr:street":"York",
    "iso:country":"GB",
    "sg:address":"Riccall Grange Cottage",
    "sg:city":"York",
    "sg:classifiers":[
        {
            "category":"Autos & Motor Vehicles",
            "subcategory":"Motorcycle Sales",
            "type":"Retail Goods"
        }
    ],
    "sg:phone":"+44 1757 248898",
    "sg:postcode":"YO19 6QL",
    "sg:province":"North Yorkshire",
    "sg:tags":[
        "chauffeur",
        "driven",
        "car"
    ],
    "wof:name":"Stretch Limousines",
    "wof:placetype":"venue"
},
  "geometry": {"coordinates":[-1.0569089651,53.8315162659],"type":"Point"}
}