{
  "type": "Feature",
  "properties": {
    "iso:country":"GB",
    "sg:address":"19 Westbury Road, Nottingham",
    "sg:city":"Nottingham",
    "sg:classifiers":[
        {
            "category":"Professional",
            "subcategory":"Business Services",
            "type":"Services"
        }
    ],
    "sg:phone":"+44 115 849 9211",
    "sg:postcode":"NG5 1EP",
    "sg:province":"Nottinghamshire",
    "sg:tags":[
        "answering"
    ],
    "wof:name":"Telepoint International Ltd.",
    "wof:placetype":"venue"
},
  "geometry": {"coordinates":[-1.166427,52.978283],"type":"Point"}
}