{
  "type": "Feature",
  "properties": {
    "iso:country":"GB",
    "sg:address":"239 Church Street",
    "sg:city":"Blackpool",
    "sg:classifiers":[
        {
            "category":"Banks & Credit Unions",
            "subcategory":"Financial Services",
            "type":"Services"
        }
    ],
    "sg:phone":"+44 1253 294822",
    "sg:postcode":"FY1 3PB",
    "sg:province":"Lancashire",
    "sg:tags":[
        "consultant",
        "finance"
    ],
    "wof:name":"London Scottish Finance Ltd.",
    "wof:placetype":"venue"
},
  "geometry": {"coordinates":[-3.042203,53.818596],"type":"Point"}
}