{
  "type": "Feature",
  "properties": {
    "addr:full":"New Ford Business Centre, New Ford Road Waltham Cross Essex EN8 7PG",
    "addr:postcode":"en8 7pg",
    "addr:street":"New Ford Road",
    "iso:country":"GB",
    "sg:address":"New Ford Business Centre, New Ford Road",
    "sg:city":"Waltham Cross",
    "sg:classifiers":[
        {
            "category":"Manufacturing",
            "subcategory":"Metals",
            "type":"Manufacturing & Wholesale Goods"
        }
    ],
    "sg:phone":"+44 1992 643333",
    "sg:postcode":"EN8 7PG",
    "sg:province":"Essex",
    "sg:tags":[
        "steel",
        "fabricator",
        "erectors"
    ],
    "wof:name":"Anker Kraft",
    "wof:placetype":"venue"
},
  "geometry": {"coordinates":[-0.021129,51.683022],"type":"Point"}
}