{
  "type": "Feature",
  "properties": {
    "addr:full":"Management & Technology Centre, Smith St Falkirk Falkirk FK2 7NA",
    "addr:postcode":"fk2 7na",
    "addr:street":"Smith St",
    "iso:country":"GB",
    "sg:address":"Management & Technology Centre, Smith St",
    "sg:city":"Falkirk",
    "sg:classifiers":[
        {
            "category":"Education",
            "subcategory":"Special Training",
            "type":"Public Place"
        }
    ],
    "sg:phone":"+44 1324 620015",
    "sg:postcode":"FK2 7NA",
    "sg:province":"Falkirk",
    "sg:tags":[
        "product",
        "centre"
    ],
    "wof:name":"Training Direct",
    "wof:placetype":"venue"
},
  "geometry": {"coordinates":[-3.78611,56.011711],"type":"Point"}
}