{
  "type": "Feature",
  "properties": {
    "addr:full":"50 Hans Cres, Knightsbridge London Greater London SW1X 0NA",
    "addr:housenumber":"50",
    "addr:postcode":"sw1x 0na",
    "addr:street":"Hans Cres",
    "iso:country":"GB",
    "sg:address":"50 Hans Cres, Knightsbridge",
    "sg:city":"London",
    "sg:classifiers":[
        {
            "category":"Shopping",
            "subcategory":"Books",
            "type":"Retail Goods"
        }
    ],
    "sg:phone":"+44 20 7581 1805",
    "sg:postcode":"SW1X 0NA",
    "sg:province":"Greater London",
    "wof:name":"Cadogan Publications Ltd",
    "wof:placetype":"venue"
},
  "geometry": {"coordinates":[-0.16227,51.499889],"type":"Point"}
}