{
  "type": "Feature",
  "properties": {
    "iso:country":"GB",
    "sg:address":"76 Addison Road",
    "sg:city":"Coventry",
    "sg:classifiers":[
        {
            "category":"Building & Trades",
            "subcategory":"Construction",
            "type":"Services"
        }
    ],
    "sg:phone":"+44 24 7633 5141",
    "sg:postcode":"CV6 2JN",
    "sg:province":"Warwickshire",
    "sg:tags":[
        "decorator",
        "painter"
    ],
    "wof:name":"B J Jones",
    "wof:placetype":"venue"
},
  "geometry": {"coordinates":[-1.530367,52.433819],"type":"Point"}
}