{
  "type": "Feature",
  "properties": {
    "iso:country":"GB",
    "sg:address":"Chainhouse Nurseries, Chain House Lane, Whitestake",
    "sg:city":"Preston",
    "sg:classifiers":[
        {
            "category":"Community Center",
            "type":"Public Place"
        }
    ],
    "sg:phone":"+44 1772 612246",
    "sg:postcode":"PR4 4LB",
    "sg:province":"Lancashire",
    "sg:tags":[
        "nursery",
        "centre"
    ],
    "wof:name":"E N Coxhead Ltd.",
    "wof:placetype":"venue"
},
  "geometry": {"coordinates":[-2.762174,53.714169],"type":"Point"}
}