{
  "type": "Feature",
  "properties": {
    "iso:country":"GB",
    "sg:address":"63-69 Carolgate",
    "sg:city":"Retford",
    "sg:classifiers":[
        {
            "category":"Food & Beverages",
            "subcategory":"Supermarket",
            "type":"Retail Goods"
        }
    ],
    "sg:phone":"+44 1777 707211",
    "sg:postcode":"DN22 6EB",
    "sg:province":"Nottinghamshire",
    "wof:name":"Greater Nottingham Co-Op",
    "wof:placetype":"venue"
},
  "geometry": {"coordinates":[-0.941843,53.320454],"type":"Point"}
}