{
  "type": "Feature",
  "properties": {
    "iso:country":"GB",
    "sg:address":"Eden Cottage Nursery",
    "sg:city":"Kirkby Stephen",
    "sg:classifiers":[
        {
            "category":"Home & Garden",
            "subcategory":"Garden Supply",
            "type":"Retail Goods"
        }
    ],
    "sg:phone":"+44 17683 71630",
    "sg:postcode":"CA17 4AP",
    "sg:province":"Cumbria",
    "sg:tags":[
        "nursery",
        "centre"
    ],
    "wof:name":"Eden Cottage Nursery",
    "wof:placetype":"venue"
},
  "geometry": {"coordinates":[-2.348623,54.472717],"type":"Point"}
}