{
  "type": "Feature",
  "properties": {
    "addr:full":"Hopton Ct, Stoke Lacy Bromyard Herefordshire HR7 4HX",
    "addr:postcode":"hr7 4hx",
    "addr:street":"Hopton Ct",
    "iso:country":"GB",
    "sg:address":"Hopton Ct, Stoke Lacy",
    "sg:city":"Bromyard",
    "sg:classifiers":[
        {
            "category":"Wholesale",
            "subcategory":"Machinery & Supplies",
            "type":"Manufacturing & Wholesale Goods"
        }
    ],
    "sg:postcode":"HR7 4HX",
    "sg:province":"Herefordshire",
    "wof:name":"Orgee,W J N,",
    "wof:placetype":"venue"
},
  "geometry": {"coordinates":[-2.510399,52.189098],"type":"Point"}
}