{
  "type": "Feature",
  "properties": {
    "addr:full":"9 Earlswood Pk Gateshead Tyne and Wear NE9 6AW",
    "addr:housenumber":"9",
    "addr:postcode":"ne9 6aw",
    "addr:street":"Earlswood Pk",
    "iso:country":"GB",
    "sg:address":"9 Earlswood Pk",
    "sg:city":"Gateshead",
    "sg:classifiers":[
        {
            "category":"Shopping",
            "subcategory":"Party Supplies",
            "type":"Retail Goods"
        }
    ],
    "sg:postcode":"NE9 6AW",
    "sg:province":"Tyne and Wear",
    "sg:tags":[
        "inflatables",
        "bouncy",
        "castle"
    ],
    "wof:name":"North East Bounce",
    "wof:placetype":"venue"
},
  "geometry": {"coordinates":[-1.6028079987,54.9309234619],"type":"Point"}
}