{
  "type": "Feature",
  "properties": {
    "addr:full":"Castle Street Beaumaris Isle of Anglesey LL58 8BA",
    "addr:postcode":"ll58 8ba",
    "addr:street":"Castle Street",
    "iso:country":"GB",
    "sg:address":"Castle Street",
    "sg:city":"Beaumaris",
    "sg:classifiers":[
        {
            "category":"Travel",
            "subcategory":"Hotels & Motels",
            "type":"Entertainment"
        }
    ],
    "sg:phone":"+44 1248 810362",
    "sg:postcode":"LL58 8BA",
    "sg:province":"Isle of Anglesey",
    "wof:name":"The Liverpool Arms Hotel",
    "wof:placetype":"venue"
},
  "geometry": {"coordinates":[-4.090996,53.263889],"type":"Point"}
}