{
  "type": "Feature",
  "properties": {
    "addr:full":"29b Avon House, New Broad Street Stratford-upon-avon Warwickshire CV37 6HW",
    "addr:housenumber":"29b",
    "addr:postcode":"cv37 6hw",
    "addr:street":"Avon House New Broad Street",
    "iso:country":"GB",
    "sg:address":"29b Avon House, New Broad Street",
    "sg:city":"Stratford-upon-avon",
    "sg:classifiers":[
        {
            "category":"Organizations",
            "subcategory":"Non-profit Organization",
            "type":"Services"
        }
    ],
    "sg:phone":"+44 1789 267520",
    "sg:postcode":"CV37 6HW",
    "sg:province":"Warwickshire",
    "sg:tags":[
        "organisation",
        "voluntary",
        "charity"
    ],
    "wof:name":"Jennifer Trust",
    "wof:placetype":"venue"
},
  "geometry": {"coordinates":[-1.7072689533,52.1941337585],"type":"Point"}
}