{
  "type": "Feature",
  "properties": {
    "addr:full":"Unit 22 Marketgate Shopping Centre Wigan Lancashire WN1 1JS",
    "addr:housenumber":"unit 22",
    "addr:postcode":"wn1 1js",
    "addr:street":"Marketgate Shopping",
    "iso:country":"GB",
    "sg:address":"Unit 22 Marketgate Shopping Centre",
    "sg:city":"Wigan",
    "sg:classifiers":[
        {
            "category":"Shopping",
            "subcategory":"Gifts & Souvenirs",
            "type":"Retail Goods"
        }
    ],
    "sg:postcode":"WN1 1JS",
    "sg:province":"Lancashire",
    "sg:tags":[
        "poster",
        "card"
    ],
    "wof:name":"Crossthwaite,John Anthony,",
    "wof:placetype":"venue"
},
  "geometry": {"coordinates":[-2.633749,53.546692],"type":"Point"}
}