{
  "type": "Feature",
  "properties": {
    "addr:full":"52-58 Bangor Road Edinburgh City of Edinburgh EH6 5JU",
    "addr:housenumber":"52-58",
    "addr:postcode":"eh6 5ju",
    "addr:street":"Bangor Road",
    "iso:country":"GB",
    "sg:address":"52-58 Bangor Road",
    "sg:city":"Edinburgh",
    "sg:classifiers":[
        {
            "category":"Manufacturing",
            "subcategory":"Building Materials",
            "type":"Manufacturing & Wholesale Goods"
        }
    ],
    "sg:phone":"+44 131 554 0522",
    "sg:postcode":"EH6 5JU",
    "sg:province":"City of Edinburgh",
    "sg:tags":[
        "tile",
        "mnfrs"
    ],
    "wof:name":"Edinburgh Tile Distributors Ltd.",
    "wof:placetype":"venue"
},
  "geometry": {"coordinates":[-3.179244,55.97224],"type":"Point"}
}