{
  "type": "Feature",
  "properties": {
    "addr:full":"Thrissell Street, Easton Bristol City of Bristol BS5 0SW",
    "addr:postcode":"bs5 0sw",
    "addr:street":"Thrissell Street",
    "iso:country":"GB",
    "sg:address":"Thrissell Street, Easton",
    "sg:city":"Bristol",
    "sg:classifiers":[
        {
            "category":"Community Center",
            "type":"Public Place"
        }
    ],
    "sg:phone":"+44 117 955 8840",
    "sg:postcode":"BS5 0SW",
    "sg:province":"City of Bristol",
    "sg:tags":[
        "recreation",
        "leisure",
        "centre"
    ],
    "wof:name":"Easton Leisure Centre",
    "wof:placetype":"venue"
},
  "geometry": {"coordinates":[-2.6910049915,51.4783248901],"type":"Point"}
}