{
  "type": "Feature",
  "properties": {
    "addr:full":"4 Airfield Industrial Estate Shipdham Thetford Norfolk IP25 7SD",
    "addr:housenumber":"4;estate shipdham",
    "addr:postcode":"ip25 7sd",
    "addr:street":"Airfield Industrial",
    "iso:country":"GB",
    "sg:address":"4 Airfield Industrial Estate Shipdham",
    "sg:city":"Thetford",
    "sg:classifiers":[
        {
            "category":"Autos & Motor Vehicles",
            "subcategory":"Automobile Sales",
            "type":"Retail Goods"
        }
    ],
    "sg:phone":"+44 1362 821374",
    "sg:postcode":"IP25 7SD",
    "sg:province":"Norfolk",
    "sg:tags":[
        "commercial",
        "van",
        "truck"
    ],
    "wof:name":"Cab Commercials",
    "wof:placetype":"venue"
},
  "geometry": {"coordinates":[0.8974660039,52.629940033],"type":"Point"}
}