{
  "type": "Feature",
  "properties": {
    "addr:full":"Regent Way King's Lynn Norfolk PE30 5BZ",
    "addr:postcode":"pe30 5bz",
    "addr:street":"Regent Way",
    "iso:country":"GB",
    "sg:address":"Regent Way",
    "sg:city":"King's Lynn",
    "sg:classifiers":[
        {
            "category":"Autos & Motor Vehicles",
            "subcategory":"Auto Supplies",
            "type":"Retail Goods"
        }
    ],
    "sg:phone":"+44 1553 691681",
    "sg:postcode":"PE30 5BZ",
    "sg:province":"Norfolk",
    "sg:tags":[
        "exhaust",
        "absorber",
        "shock"
    ],
    "wof:name":"Kwik-Fit",
    "wof:placetype":"venue"
},
  "geometry": {"coordinates":[0.39878,52.751759],"type":"Point"}
}