{
  "type": "Feature",
  "properties": {
    "addr:full":"Holdtite Ho, 18 Seabeach La Eastbourne East Sussex BN22 7NZ",
    "addr:housenumber":"18",
    "addr:postcode":"bn22 7nz",
    "addr:street":"Seabeach La Eastbourne",
    "iso:country":"GB",
    "sg:address":"Holdtite Ho, 18 Seabeach La",
    "sg:city":"Eastbourne",
    "sg:classifiers":[
        {
            "category":"Sports & Exercise",
            "subcategory":"Playing Field",
            "type":"Entertainment"
        }
    ],
    "sg:postcode":"BN22 7NZ",
    "sg:province":"East Sussex",
    "sg:tags":[
        "sanitary",
        "hygiene",
        "appliance"
    ],
    "wof:name":"Holdtite",
    "wof:placetype":"venue"
},
  "geometry": {"coordinates":[0.3004499972,50.7789802551],"type":"Point"}
}