{
  "type": "Feature",
  "properties": {
    "iso:country":"GB",
    "sg:address":"Gladstone House, 6a Mill Lane",
    "sg:city":"Edinburgh",
    "sg:classifiers":[
        {
            "category":"Bars & Pubs",
            "type":"Food & Drink"
        }
    ],
    "sg:phone":"+44 131 554 5586",
    "sg:postcode":"EH6 6TJ",
    "sg:province":"City of Edinburgh",
    "sg:tags":[
        "pubs",
        "inn"
    ],
    "wof:name":"Gladstones Ltd.",
    "wof:placetype":"venue"
},
  "geometry": {"coordinates":[-3.1756660938,55.9747123718],"type":"Point"}
}