{
  "type": "Feature",
  "properties": {
    "addr:full":"9 Cosgrove Road, Old Stratford Milton Keynes Buckinghamshire MK19 6AG",
    "addr:housenumber":"9",
    "addr:postcode":"mk19 6ag",
    "addr:street":"Cosgrove Road",
    "iso:country":"GB",
    "sg:address":"9 Cosgrove Road, Old Stratford",
    "sg:city":"Milton Keynes",
    "sg:classifiers":[
        {
            "category":"Professional",
            "subcategory":"Computer Services",
            "type":"Services"
        }
    ],
    "sg:phone":"+44 1908 568905",
    "sg:postcode":"MK19 6AG",
    "sg:province":"Buckinghamshire",
    "sg:tags":[
        "system",
        "software"
    ],
    "wof:name":"Travelflex Ltd.",
    "wof:placetype":"venue"
},
  "geometry": {"coordinates":[-0.864257,52.063889],"type":"Point"}
}