{
  "type": "Feature",
  "properties": {
    "addr:full":"Broughton Trade Centre, Broughton Lane Manchester Greater Manchester M7 1UF",
    "addr:postcode":"m7 1uf",
    "addr:street":"Broughton Lane",
    "iso:country":"GB",
    "sg:address":"Broughton Trade Centre, Broughton Lane",
    "sg:city":"Manchester",
    "sg:classifiers":[
        {
            "category":"Shopping",
            "subcategory":"Used Merchandise",
            "type":"Retail Goods"
        }
    ],
    "sg:postcode":"M7 1UF",
    "sg:province":"Greater Manchester",
    "sg:tags":[
        "shop",
        "second-hand"
    ],
    "wof:name":"The Household Trade",
    "wof:placetype":"venue"
},
  "geometry": {"coordinates":[-2.2560501099,53.4957618713],"type":"Point"}
}