{
  "type": "Feature",
  "properties": {
    "iso:country":"GB",
    "sg:address":"55 Merlin Way",
    "sg:city":"East Grinstead",
    "sg:classifiers":[
        {
            "category":"Home & Garden",
            "subcategory":"Building Materials",
            "type":"Retail Goods"
        },
        {
            "category":"Bars & Pubs",
            "subcategory":"Oxygen Bar",
            "type":"Food & Drink"
        }
    ],
    "sg:phone":"+44 1342 300818",
    "sg:postcode":"RH19 3XG",
    "sg:province":"East Sussex",
    "sg:tags":[
        "ventilator",
        "ventilation",
        "system"
    ],
    "sg:website":"http://www.merlinindustrialservices.co.uk",
    "wof:name":"Merlin Industrial Services",
    "wof:placetype":"venue"
},
  "geometry": {"coordinates":[0.003971,51.135391],"type":"Point"}
}