{
  "type": "Feature",
  "properties": {
    "addr:full":"192 Stanley Rd Teddington Greater London TW11 8UE",
    "addr:housenumber":"192",
    "addr:postcode":"tw11 8ue",
    "addr:street":"Stanley Rd",
    "iso:country":"GB",
    "sg:address":"192 Stanley Rd",
    "sg:city":"Teddington",
    "sg:classifiers":[
        {
            "category":"Professional",
            "subcategory":"Business Services",
            "type":"Services"
        }
    ],
    "sg:phone":"+44 20 8943 2524",
    "sg:postcode":"TW11 8UE",
    "sg:province":"Greater London",
    "sg:tags":[
        "shop",
        "cleaning"
    ],
    "wof:name":"Thameside Cleaners",
    "wof:placetype":"venue"
},
  "geometry": {"coordinates":[-0.345660001,51.4322128296],"type":"Point"}
}