{
  "type": "Feature",
  "properties": {
    "iso:country":"GB",
    "sg:address":"17 Summerfield Place",
    "sg:city":"Fraserburgh",
    "sg:classifiers":[
        {
            "category":"Home & Garden",
            "subcategory":"Household Appliances",
            "type":"Retail Goods"
        }
    ],
    "sg:phone":"+44 1346 582549",
    "sg:postcode":"AB43 5YD",
    "sg:province":"Aberdeenshire",
    "sg:tags":[
        "electrical"
    ],
    "wof:name":"Vacuum Services",
    "wof:placetype":"venue"
},
  "geometry": {"coordinates":[-1.9314160347,57.6739845276],"type":"Point"}
}