{
  "type": "Feature",
  "properties": {
    "iso:country":"GB",
    "sg:address":"1-2 Belleton Court",
    "sg:city":"Stockton-on-tees",
    "sg:classifiers":[
        {
            "category":"Home & Garden",
            "subcategory":"Home Furnishings",
            "type":"Retail Goods"
        },
        {
            "category":"Building & Trades",
            "subcategory":"Construction",
            "type":"Services"
        }
    ],
    "sg:postcode":"TS18 3AW",
    "sg:province":"Durham",
    "sg:tags":[
        "furnishers",
        "planner",
        "joiner",
        "carpenter",
        "bedroom"
    ],
    "wof:name":"D J Peacock",
    "wof:placetype":"venue"
},
  "geometry": {"coordinates":[-1.30956,54.558632],"type":"Point"}
}