{
  "type": "Feature",
  "properties": {
    "addr:full":"28 Hyde Grove Sale Cheshire M33 7TE",
    "addr:housenumber":"28;m33",
    "addr:postcode":"7te",
    "addr:street":"Hyde Grove Sale Cheshire",
    "iso:country":"GB",
    "sg:address":"28 Hyde Grove",
    "sg:city":"Sale",
    "sg:classifiers":[
        {
            "category":"Professional",
            "subcategory":"Computer Services",
            "type":"Services"
        }
    ],
    "sg:postcode":"M33 7TE",
    "sg:province":"Cheshire",
    "sg:tags":[
        "system",
        "software"
    ],
    "wof:name":"Happy Medium Ltd",
    "wof:placetype":"venue"
},
  "geometry": {"coordinates":[-2.323385,53.421463],"type":"Point"}
}