{
  "type": "Feature",
  "properties": {
    "addr:full":"The Pavilion, 56 Rosslyn Cres Harrow Greater London HA1 2SZ",
    "addr:housenumber":"56",
    "addr:postcode":"ha1 2sz",
    "addr:street":"Rosslyn Cres",
    "iso:country":"GB",
    "sg:address":"The Pavilion, 56 Rosslyn Cres",
    "sg:city":"Harrow",
    "sg:classifiers":[
        {
            "category":"Freight",
            "type":"Transportation"
        }
    ],
    "sg:postcode":"HA1 2SZ",
    "sg:province":"Greater London",
    "sg:tags":[
        "haulage",
        "road"
    ],
    "wof:name":"All Plant & Transport Ltd",
    "wof:placetype":"venue"
},
  "geometry": {"coordinates":[-0.3360820115,51.5787849426],"type":"Point"}
}