{
  "type": "Feature",
  "properties": {
    "iso:country":"GB",
    "sg:address":"5 Ruthin Street",
    "sg:city":"Sheffield",
    "sg:classifiers":[
        {
            "category":"Professional",
            "subcategory":"Detective & Security Services",
            "type":"Services"
        }
    ],
    "sg:phone":"+44 114 243 2147",
    "sg:postcode":"S4 8DZ",
    "sg:province":"South Yorkshire",
    "wof:name":"Securitas",
    "wof:placetype":"venue"
},
  "geometry": {"coordinates":[-1.43947,53.403763],"type":"Point"}
}