{
  "type": "Feature",
  "properties": {
    "iso:country":"GB",
    "sg:address":"30 Langside Drive",
    "sg:city":"Glasgow",
    "sg:classifiers":[
        {
            "category":"Organizations",
            "subcategory":"Non-profit Organization",
            "type":"Services"
        }
    ],
    "sg:phone":"+44 141 637 3316",
    "sg:postcode":"G43 2QQ",
    "sg:province":"Glasgow City",
    "sg:tags":[
        "organisation",
        "voluntary",
        "charity"
    ],
    "wof:name":"German Speaking Catholic Centre",
    "wof:placetype":"venue"
},
  "geometry": {"coordinates":[-4.278403,55.817661],"type":"Point"}
}