{
  "type": "Feature",
  "properties": {
    "iso:country":"GB",
    "sg:address":"1 Cornwall Av",
    "sg:city":"Bethnal Green",
    "sg:classifiers":[
        {
            "category":"Organizations",
            "subcategory":"Non-profit Organization",
            "type":"Services"
        }
    ],
    "sg:phone":"+44 20 8983 3409",
    "sg:postcode":"E2 0HW",
    "sg:province":"Greater London",
    "sg:tags":[
        "organisation",
        "voluntary",
        "charity"
    ],
    "wof:name":"Bethnal Green Bengali Association",
    "wof:placetype":"venue"
},
  "geometry": {"coordinates":[-0.053273,51.526108],"type":"Point"}
}