{
  "type": "Feature",
  "properties": {
    "addr:full":"988 Tyburn Road, Erdington Birmingham West Midlands B24 0TL",
    "addr:housenumber":"988",
    "addr:postcode":"b24 0tl",
    "addr:street":"Tyburn Road",
    "iso:country":"GB",
    "sg:address":"988 Tyburn Road, Erdington",
    "sg:city":"Birmingham",
    "sg:classifiers":[
        {
            "category":"Arts & Performance",
            "subcategory":"Art Gallery",
            "type":"Entertainment"
        }
    ],
    "sg:phone":"+44 121 384 4831",
    "sg:postcode":"B24 0TL",
    "sg:province":"West Midlands",
    "wof:name":"Midland Pictures & Mirrors",
    "wof:placetype":"venue"
},
  "geometry": {"coordinates":[-1.8187199831,52.5174560547],"type":"Point"}
}