{
  "type": "Feature",
  "properties": {
    "addr:full":"19a Victoria Road, Netley Abbey Southampton Hampshire SO31 5DG",
    "addr:housenumber":"19a",
    "addr:postcode":"so31 5dg",
    "addr:street":"Victoria Road",
    "iso:country":"GB",
    "sg:address":"19a Victoria Road, Netley Abbey",
    "sg:city":"Southampton",
    "sg:classifiers":[
        {
            "category":"Building & Trades",
            "subcategory":"Construction",
            "type":"Services"
        }
    ],
    "sg:phone":"+44 1752 606058",
    "sg:postcode":"SO31 5DG",
    "sg:province":"Hampshire",
    "sg:tags":[
        "window",
        "door"
    ],
    "wof:name":"Effective Glass Treatments (U K) Ltd.",
    "wof:placetype":"venue"
},
  "geometry": {"coordinates":[-1.355572,50.875599],"type":"Point"}
}