{
  "type": "Feature",
  "properties": {
    "addr:full":"14 Warstone Parade East Birmingham West Midlands B18 6NR",
    "addr:housenumber":"14",
    "addr:postcode":"b18 6nr",
    "addr:street":"Warstone Parade East",
    "iso:country":"GB",
    "sg:address":"14 Warstone Parade East",
    "sg:city":"Birmingham",
    "sg:classifiers":[
        {
            "category":"Manufacturing",
            "subcategory":"Jewelry",
            "type":"Manufacturing & Wholesale Goods"
        }
    ],
    "sg:phone":"+44 121 212 0638",
    "sg:postcode":"B18 6NR",
    "sg:province":"West Midlands",
    "sg:tags":[
        "repair",
        "jewellery"
    ],
    "wof:name":"Chainlynk Jewellery",
    "wof:placetype":"venue"
},
  "geometry": {"coordinates":[-1.915007,52.487209],"type":"Point"}
}