{
  "type": "Feature",
  "properties": {
    "addr:full":"17 Dougrie Drive Glasgow Glasgow City G45 9AD",
    "addr:housenumber":"17",
    "addr:postcode":"g45 9ad",
    "addr:street":"Dougrie Drive",
    "iso:country":"GB",
    "sg:address":"17 Dougrie Drive",
    "sg:city":"Glasgow",
    "sg:classifiers":[
        {
            "category":"Shopping",
            "subcategory":"Department Store",
            "type":"Retail Goods"
        }
    ],
    "sg:phone":"+44 141 631 1424",
    "sg:postcode":"G45 9AD",
    "sg:province":"Glasgow City",
    "wof:name":"Castlemilk Grocers",
    "wof:placetype":"venue"
},
  "geometry": {"coordinates":[-4.2336769104,55.8070220947],"type":"Point"}
}