{
  "type": "Feature",
  "properties": {
    "addr:full":"Holbein Close Basingstoke Hampshire RG21 3EX",
    "addr:postcode":"rg21 3ex",
    "addr:street":"Holbein Close",
    "iso:country":"GB",
    "sg:address":"Holbein Close",
    "sg:city":"Basingstoke",
    "sg:classifiers":[
        {
            "category":"Restaurant",
            "type":"Food & Drink"
        }
    ],
    "sg:phone":"+44 1256 818450",
    "sg:postcode":"RG21 3EX",
    "sg:province":"Hampshire",
    "sg:tags":[
        "indian"
    ],
    "wof:name":"Raj Of Blackdam",
    "wof:placetype":"venue"
},
  "geometry": {"coordinates":[-1.0732120275,51.2573013306],"type":"Point"}
}