{
  "type": "Feature",
  "properties": {
    "addr:full":"M1 Markham La Chesterfield Derbyshire S44 5HS",
    "addr:postcode":"s44 5hs",
    "addr:street":"M1;La Chesterfield",
    "iso:country":"GB",
    "sg:address":"M1 Markham La",
    "sg:city":"Chesterfield",
    "sg:classifiers":[
        {
            "category":"Bus Charters",
            "type":"Transportation"
        }
    ],
    "sg:phone":"+44 1246 812309",
    "sg:postcode":"S44 5HS",
    "sg:province":"Derbyshire",
    "sg:tags":[
        "hire",
        "coach"
    ],
    "wof:name":"M1 Commercial Parts",
    "wof:placetype":"venue"
},
  "geometry": {"coordinates":[-1.3299399614,53.2410316467],"type":"Point"}
}