{
  "type": "Feature",
  "properties": {
    "addr:full":"102 Johns Road Fareham Hampshire PO16 0RX",
    "addr:housenumber":"102",
    "addr:postcode":"po16 0rx",
    "addr:street":"Johns Road",
    "iso:country":"GB",
    "sg:address":"102 Johns Road",
    "sg:city":"Fareham",
    "sg:classifiers":[
        {
            "category":"Arts & Performance",
            "subcategory":"Music",
            "type":"Entertainment"
        }
    ],
    "sg:postcode":"PO16 0RX",
    "sg:province":"Hampshire",
    "sg:tags":[
        "mobile",
        "disco"
    ],
    "wof:name":"Golden Sounds & Silver Sounds",
    "wof:placetype":"venue"
},
  "geometry": {"coordinates":[-1.182383,50.84494],"type":"Point"}
}