{
  "type": "Feature",
  "properties": {
    "iso:country":"GB",
    "sg:address":"4 New Road, Little Kingshill",
    "sg:city":"Great Missenden",
    "sg:classifiers":[
        {
            "category":"Building & Trades",
            "subcategory":"Plumbing",
            "type":"Services"
        },
        {
            "category":"Building & Trades",
            "subcategory":"Construction",
            "type":"Services"
        }
    ],
    "sg:postcode":"HP16 0EZ",
    "sg:province":"Buckinghamshire",
    "sg:tags":[
        "heating",
        "contractor"
    ],
    "wof:name":"B Tomlin & Son",
    "wof:placetype":"venue"
},
  "geometry": {"coordinates":[-0.701619029,51.690120697],"type":"Point"}
}