{
  "type": "Feature",
  "properties": {
    "iso:country":"GB",
    "sg:address":", Clayhidon",
    "sg:city":"Cullompton",
    "sg:classifiers":[
        {
            "category":"Bars & Pubs",
            "type":"Food & Drink"
        },
        {
            "category":"Community Center",
            "subcategory":"Social",
            "type":"Public Place"
        }
    ],
    "sg:phone":"+44 1823 680291",
    "sg:postcode":"EX15 3TJ",
    "sg:province":"Devon",
    "sg:tags":[
        "pubs",
        "house",
        "inn",
        "activity"
    ],
    "wof:name":"Half Moon Inn",
    "wof:placetype":"venue"
},
  "geometry": {"coordinates":[-3.2723739147,50.9124984741],"type":"Point"}
}