{
  "type": "Feature",
  "properties": {
    "addr:full":"1 Page Moss Parade Liverpool Merseyside L36 2PA",
    "addr:housenumber":"1",
    "addr:postcode":"l36 2pa",
    "addr:street":"Page Moss Parade",
    "iso:country":"GB",
    "sg:address":"1 Page Moss Parade",
    "sg:city":"Liverpool",
    "sg:classifiers":[
        {
            "category":"Fast Food",
            "type":"Food & Drink"
        }
    ],
    "sg:phone":"+44 151 289 2417",
    "sg:postcode":"L36 2PA",
    "sg:province":"Merseyside",
    "sg:tags":[
        "away",
        "take"
    ],
    "wof:name":"Man Li",
    "wof:placetype":"venue"
},
  "geometry": {"coordinates":[-2.865928,53.417912],"type":"Point"}
}