{
  "type": "Feature",
  "properties": {
    "addr:full":"22-24 Clarendon Rd Cambridge Cambridgeshire CB2 2BH",
    "addr:housenumber":"22-24",
    "addr:postcode":"cb2 2bh",
    "addr:street":"Clarendon Rd",
    "iso:country":"GB",
    "sg:address":"22-24 Clarendon Rd",
    "sg:city":"Cambridge",
    "sg:classifiers":[
        {
            "category":"Retail",
            "subcategory":"Driving School",
            "type":"Services"
        }
    ],
    "sg:phone":"+44 1223 462362",
    "sg:postcode":"CB2 2BH",
    "sg:province":"Cambridgeshire",
    "sg:tags":[
        "instruction",
        "cycling",
        "motor"
    ],
    "wof:name":"Camrider Training Ltd",
    "wof:placetype":"venue"
},
  "geometry": {"coordinates":[0.1325899959,52.1902618408],"type":"Point"}
}