{
  "type": "Feature",
  "properties": {
    "addr:full":"Stamford Hill Community Centre, 110 Stamford Hill Estate Stoke Newington Greater London N16 6RZ",
    "addr:housenumber":"110",
    "addr:postcode":"n16 6rz",
    "addr:street":"Stamford Hill Estate",
    "iso:country":"GB",
    "sg:address":"Stamford Hill Community Centre, 110 Stamford Hill Estate",
    "sg:city":"Stoke Newington",
    "sg:classifiers":[
        {
            "category":"Government",
            "subcategory":"Office",
            "type":"Public Place"
        }
    ],
    "sg:phone":"+44 20 8806 0083",
    "sg:postcode":"N16 6RZ",
    "sg:province":"Greater London",
    "sg:tags":[
        "local"
    ],
    "wof:name":"The Stamford Hill Estate Youth Crime Prevention Initiat",
    "wof:placetype":"venue"
},
  "geometry": {"coordinates":[-0.0736899972,51.5695991516],"type":"Point"}
}