{
  "type": "Feature",
  "properties": {
    "addr:full":"24 London Road, Lindal Ulverston Cumbria LA12 0LL",
    "addr:housenumber":"24",
    "addr:postcode":"la12 0ll",
    "addr:street":"London Road",
    "iso:country":"GB",
    "sg:address":"24 London Road, Lindal",
    "sg:city":"Ulverston",
    "sg:classifiers":[
        {
            "category":"Professional",
            "subcategory":"Art Services",
            "type":"Services"
        }
    ],
    "sg:postcode":"LA12 0LL",
    "sg:province":"Cumbria",
    "sg:tags":[
        "photographer"
    ],
    "wof:name":"Chris Warner Photography",
    "wof:placetype":"venue"
},
  "geometry": {"coordinates":[-3.149493,54.169998],"type":"Point"}
}