{
  "type": "Feature",
  "properties": {
    "iso:country":"GB",
    "sg:address":"Albert Street",
    "sg:city":"Congleton",
    "sg:classifiers":[
        {
            "category":"Retail",
            "subcategory":"Auto Repair",
            "type":"Services"
        }
    ],
    "sg:phone":"+44 1260 273866",
    "sg:postcode":"CW12 1DD",
    "sg:province":"Cheshire",
    "sg:tags":[
        "body",
        "car"
    ],
    "wof:name":"Congleton Coachworks Ltd.",
    "wof:placetype":"venue"
},
  "geometry": {"coordinates":[-2.212205,53.163635],"type":"Point"}
}