{
  "type": "Feature",
  "properties": {
    "iso:country":"GB",
    "sg:address":"145 Avon Rd",
    "sg:city":"Upminster",
    "sg:classifiers":[
        {
            "category":"Food & Beverages",
            "subcategory":"Liquor & Beverages",
            "type":"Retail Goods"
        }
    ],
    "sg:phone":"+44 1708 221011",
    "sg:postcode":"RM14 1RQ",
    "sg:province":"Essex",
    "sg:tags":[
        "beer",
        "spirit",
        "wines"
    ],
    "wof:name":"Victoria Wine",
    "wof:placetype":"venue"
},
  "geometry": {"coordinates":[0.26607,51.568649],"type":"Point"}
}