{
  "type": "Feature",
  "properties": {
    "addr:full":"Daubney Holt Farm, Harrington Spilsby Lincolnshire PE23 4NL",
    "addr:postcode":"pe23 4nl",
    "iso:country":"GB",
    "sg:address":"Daubney Holt Farm, Harrington",
    "sg:city":"Spilsby",
    "sg:classifiers":[
        {
            "category":"Farming",
            "subcategory":"Livestock Farm",
            "type":"Manufacturing & Wholesale Goods"
        }
    ],
    "sg:phone":"+44 1790 753700",
    "sg:postcode":"PE23 4NL",
    "sg:province":"Lincolnshire",
    "sg:tags":[
        "others"
    ],
    "wof:name":"L Stephenson & Son",
    "wof:placetype":"venue"
},
  "geometry": {"coordinates":[0.0418090001,53.2263755798],"type":"Point"}
}