{
  "type": "Feature",
  "properties": {
    "addr:full":"321 Billinge Road Wigan Lancashire WN3 6BL",
    "addr:housenumber":"321",
    "addr:postcode":"wn3 6bl",
    "addr:street":"Billinge Road",
    "iso:country":"GB",
    "sg:address":"321 Billinge Road",
    "sg:city":"Wigan",
    "sg:classifiers":[
        {
            "category":"Retail",
            "subcategory":"Driving School",
            "type":"Services"
        }
    ],
    "sg:phone":"+44 1942 223742",
    "sg:postcode":"WN3 6BL",
    "sg:province":"Lancashire",
    "wof:name":"Wigan Hgv Training School",
    "wof:placetype":"venue"
},
  "geometry": {"coordinates":[-2.6741108894,53.5293159485],"type":"Point"}
}