{
  "type": "Feature",
  "properties": {
    "iso:country":"GB",
    "sg:address":"53 Princes Street",
    "sg:city":"Yeovil",
    "sg:classifiers":[
        {
            "category":"Professional",
            "subcategory":"Detective & Security Services",
            "type":"Services"
        }
    ],
    "sg:phone":"+44 1935 426394",
    "sg:postcode":"BA20 1EE",
    "sg:province":"Somerset",
    "wof:name":"South West Security Ltd.",
    "wof:placetype":"venue"
},
  "geometry": {"coordinates":[-2.633539,50.942558],"type":"Point"}
}