{
  "type": "Feature",
  "properties": {
    "iso:country":"GB",
    "sg:address":"122 Rake La",
    "sg:city":"Wallasey",
    "sg:classifiers":[
        {
            "category":"Food & Beverages",
            "subcategory":"Meat & Fish",
            "type":"Retail Goods"
        }
    ],
    "sg:phone":"+44 151 639 7736",
    "sg:postcode":"L45 5DL",
    "sg:province":"Merseyside",
    "sg:tags":[
        "chip"
    ],
    "wof:name":"Rake Lane Fish & Chips",
    "wof:placetype":"venue"
},
  "geometry": {"coordinates":[-3.041672945,53.4284477234],"type":"Point"}
}