{
  "type": "Feature",
  "properties": {
    "addr:full":"South Street, Mosborough Sheffield South Yorkshire S20 5DF",
    "addr:postcode":"s20 5df",
    "addr:street":"South Street",
    "iso:country":"GB",
    "sg:address":"South Street, Mosborough",
    "sg:city":"Sheffield",
    "sg:classifiers":[
        {
            "category":"Farming",
            "subcategory":"Dairy Farm",
            "type":"Manufacturing & Wholesale Goods"
        }
    ],
    "sg:phone":"+44 114 248 7104",
    "sg:postcode":"S20 5DF",
    "sg:province":"South Yorkshire",
    "wof:name":"Eckington Hall Farm",
    "wof:placetype":"venue"
},
  "geometry": {"coordinates":[-1.3626689911,53.325504303],"type":"Point"}
}