{
  "type": "Feature",
  "properties": {
    "iso:country":"GB",
    "sg:address":"6 Chart Cl",
    "sg:city":"Croydon",
    "sg:classifiers":[
        {
            "category":"Professional",
            "subcategory":"Business Services",
            "type":"Services"
        }
    ],
    "sg:phone":"+44 20 8239 6973",
    "sg:postcode":"CR0 7YF",
    "sg:province":"Surrey",
    "sg:tags":[
        "import",
        "export",
        "agent"
    ],
    "wof:name":"Sonik Enterprises Ltd",
    "wof:placetype":"venue"
},
  "geometry": {"coordinates":[-0.058956001,51.3892631531],"type":"Point"}
}