{
  "type": "Feature",
  "properties": {
    "addr:full":"754-756 Stratford Road, Sparkhill Birmingham West Midlands B11 4BP",
    "addr:housenumber":"754-756",
    "addr:postcode":"b11 4bp",
    "addr:street":"Stratford Road",
    "iso:country":"GB",
    "sg:address":"754-756 Stratford Road, Sparkhill",
    "sg:city":"Birmingham",
    "sg:classifiers":[
        {
            "category":"Shopping",
            "subcategory":"Clothing, Apparel, & Fashions",
            "type":"Retail Goods"
        }
    ],
    "sg:phone":"+44 121 777 8697",
    "sg:postcode":"B11 4BP",
    "sg:province":"West Midlands",
    "sg:tags":[
        "lingerie"
    ],
    "wof:name":"It's Your Price",
    "wof:placetype":"venue"
},
  "geometry": {"coordinates":[-1.8600039482,52.4468612671],"type":"Point"}
}