{
  "type": "Feature",
  "properties": {
    "iso:country":"GB",
    "sg:address":"Unit 7 Sunderlands Est, Church La",
    "sg:city":"Kings Langley",
    "sg:classifiers":[
        {
            "category":"Shopping",
            "subcategory":"Pharmacy",
            "type":"Retail Goods"
        }
    ],
    "sg:phone":"+44 1923 264431",
    "sg:postcode":"WD4 8JX",
    "sg:province":"Hertfordshire",
    "sg:tags":[
        "toiletry"
    ],
    "wof:name":"White Crest International",
    "wof:placetype":"venue"
},
  "geometry": {"coordinates":[-0.450219,51.713551],"type":"Point"}
}