{
  "type": "Feature",
  "properties": {
    "addr:full":"Britannia House, Glenthorne Road London Greater London W6 0LH",
    "addr:postcode":"w6 0lh",
    "addr:street":"Glenthorne Road",
    "iso:country":"GB",
    "sg:address":"Britannia House, Glenthorne Road",
    "sg:city":"London",
    "sg:classifiers":[
        {
            "category":"Professional",
            "subcategory":"Employment Agencies",
            "type":"Services"
        }
    ],
    "sg:phone":"+44 20 8741 5353",
    "sg:postcode":"W6 0LH",
    "sg:province":"Greater London",
    "sg:tags":[
        "consultant"
    ],
    "wof:name":"Elizabeth Norman Executive Recruitment",
    "wof:placetype":"venue"
},
  "geometry": {"coordinates":[-0.22676,51.494282],"type":"Point"}
}