{
  "type": "Feature",
  "properties": {
    "iso:country":"GB",
    "sg:address":"Unit V, Westwood Industrial Estate",
    "sg:city":"Oldham",
    "sg:classifiers":[
        {
            "category":"Professional",
            "subcategory":"Engineering",
            "type":"Services"
        }
    ],
    "sg:phone":"+44 161 627 2367",
    "sg:postcode":"OL9 9LZ",
    "sg:province":"Lancashire",
    "sg:tags":[
        "precision",
        "engineer"
    ],
    "wof:name":"Normec (Manchester) Ltd.",
    "wof:placetype":"venue"
},
  "geometry": {"coordinates":[-2.13211,53.541458],"type":"Point"}
}