{
  "type": "Feature",
  "properties": {
    "addr:full":"Pilot Street Accrington Lancashire BB5 5AH",
    "addr:postcode":"bb5 5ah",
    "addr:street":"Pilot Street",
    "iso:country":"GB",
    "sg:address":"Pilot Street",
    "sg:city":"Accrington",
    "sg:classifiers":[
        {
            "category":"Retail",
            "subcategory":"Auto Repair",
            "type":"Services"
        }
    ],
    "sg:phone":"+44 1254 235347",
    "sg:postcode":"BB5 5AH",
    "sg:province":"Lancashire",
    "sg:tags":[
        "modification",
        "garage",
        "related"
    ],
    "wof:name":"OAKLEIGH GARAGE LTD",
    "wof:placetype":"venue"
},
  "geometry": {"coordinates":[-2.3701291084,53.7611541748],"type":"Point"}
}