{
  "type": "Feature",
  "properties": {
    "addr:full":"78 Moody Road Fareham Hampshire PO14 2BX",
    "addr:housenumber":"78",
    "addr:postcode":"po14 2bx",
    "addr:street":"Moody Road",
    "iso:country":"GB",
    "sg:address":"78 Moody Road",
    "sg:city":"Fareham",
    "sg:classifiers":[
        {
            "category":"Building & Trades",
            "subcategory":"Plumbing",
            "type":"Services"
        }
    ],
    "sg:postcode":"PO14 2BX",
    "sg:province":"Hampshire",
    "sg:tags":[
        "heating"
    ],
    "wof:name":"Duncan Heritage",
    "wof:placetype":"venue"
},
  "geometry": {"coordinates":[-1.217796,50.817116],"type":"Point"}
}