{
  "type": "Feature",
  "properties": {
    "addr:full":"294 Earls Court Road London Greater London SW5 9BB",
    "addr:housenumber":"294",
    "addr:postcode":"sw5 9bb",
    "addr:street":"Earls Court Road",
    "iso:country":"GB",
    "sg:address":"294 Earls Court Road",
    "sg:city":"London",
    "sg:classifiers":[
        {
            "category":"Wholesale",
            "subcategory":"Machinery & Supplies",
            "type":"Manufacturing & Wholesale Goods"
        }
    ],
    "sg:phone":"+44 20 7370 4012",
    "sg:postcode":"SW5 9BB",
    "sg:province":"Greater London",
    "sg:tags":[
        "theatrical"
    ],
    "wof:name":"Futurist",
    "wof:placetype":"venue"
},
  "geometry": {"coordinates":[-0.1912460029,51.4905815125],"type":"Point"}
}