{
  "type": "Feature",
  "properties": {
    "addr:full":"Unit 9 Old Garden House, Bridge Lane London Greater London SW11 3AD",
    "addr:housenumber":"unit 9",
    "addr:postcode":"sw11 3ad",
    "addr:street":"Old Garden;Bridge Lane",
    "iso:country":"GB",
    "sg:address":"Unit 9 Old Garden House, Bridge Lane",
    "sg:city":"London",
    "sg:classifiers":[
        {
            "category":"Food & Beverages",
            "subcategory":"Liquor & Beverages",
            "type":"Retail Goods"
        }
    ],
    "sg:phone":"+44 20 7207 1944",
    "sg:postcode":"SW11 3AD",
    "sg:province":"Greater London",
    "sg:tags":[
        "beer",
        "spirit",
        "wines"
    ],
    "wof:name":"California Direct Ltd.",
    "wof:placetype":"venue"
},
  "geometry": {"coordinates":[-0.167,51.474159],"type":"Point"}
}