{
  "type": "Feature",
  "properties": {
    "iso:country":"GB",
    "sg:address":"80a Barnsley Road, Wombwell",
    "sg:city":"Barnsley",
    "sg:classifiers":[
        {
            "category":"Autos & Motor Vehicles",
            "subcategory":"Motorcycle Sales",
            "type":"Retail Goods"
        }
    ],
    "sg:phone":"+44 1226 752309",
    "sg:postcode":"S73 8DN",
    "sg:province":"South Yorkshire",
    "wof:name":"Bill Thomas Motorcycles",
    "wof:placetype":"venue"
},
  "geometry": {"coordinates":[-1.4055119753,53.5260047913],"type":"Point"}
}