{
  "type": "Feature",
  "properties": {
    "iso:country":"GB",
    "sg:address":"Reynolds Place, West Grn",
    "sg:city":"Crawley",
    "sg:classifiers":[
        {
            "category":"Recreation",
            "subcategory":"Fishing",
            "type":"Entertainment"
        }
    ],
    "sg:phone":"+44 1293 521186",
    "sg:postcode":"RH11 7HB",
    "sg:province":"West Sussex",
    "sg:tags":[
        "angling"
    ],
    "wof:name":"Jack Frost Tackle Ltd.",
    "wof:placetype":"venue"
},
  "geometry": {"coordinates":[-0.199887,51.119217],"type":"Point"}
}