{
  "type": "Feature",
  "properties": {
    "iso:country":"GB",
    "sg:address":"3 Eager Street, Newton Heath",
    "sg:city":"Manchester",
    "sg:classifiers":[
        {
            "category":"Professional",
            "type":"Services"
        }
    ],
    "sg:phone":"+44 161 681 2077",
    "sg:postcode":"M40 1EY",
    "sg:province":"Greater Manchester",
    "sg:tags":[
        "shopfitters"
    ],
    "wof:name":"A Pollick Ltd.",
    "wof:placetype":"venue"
},
  "geometry": {"coordinates":[-2.17868,53.504005],"type":"Point"}
}