{
  "type": "Feature",
  "properties": {
    "addr:full":"The Glebe Saltash Cornwall PL12 5EZ",
    "addr:postcode":"pl12 5ez",
    "addr:street":"The Glebe",
    "iso:country":"GB",
    "sg:address":"The Glebe",
    "sg:city":"Saltash",
    "sg:classifiers":[
        {
            "category":"Shopping",
            "subcategory":"Department Store",
            "type":"Retail Goods"
        },
        {
            "category":"Farming",
            "subcategory":"Dairy Farm",
            "type":"Manufacturing & Wholesale Goods"
        }
    ],
    "sg:phone":"+44 1752 851581",
    "sg:postcode":"PL12 5EZ",
    "sg:province":"Cornwall",
    "wof:name":"Knowles & Son",
    "wof:placetype":"venue"
},
  "geometry": {"coordinates":[-4.3248348236,50.4140205383],"type":"Point"}
}