{
  "type": "Feature",
  "properties": {
    "addr:full":"Unit 1b 8 French Rd Leicester Leicestershire LE5 4AH",
    "addr:housenumber":"unit 1b 8",
    "addr:postcode":"le5 4ah",
    "addr:street":"French Rd",
    "iso:country":"GB",
    "sg:address":"Unit 1b 8 French Rd",
    "sg:city":"Leicester",
    "sg:classifiers":[
        {
            "category":"Home & Garden",
            "subcategory":"Carpets & Floor Coverings",
            "type":"Retail Goods"
        }
    ],
    "sg:phone":"+44 116 274 0100",
    "sg:postcode":"LE5 4AH",
    "sg:province":"Leicestershire",
    "sg:tags":[
        "trimming",
        "trimmer"
    ],
    "wof:name":"Karan Trims Ltd",
    "wof:placetype":"venue"
},
  "geometry": {"coordinates":[-1.097783,52.640221],"type":"Point"}
}