{
  "type": "Feature",
  "properties": {
    "addr:full":"33 Fore Street Wellington Devon TA21 8AG",
    "addr:housenumber":"33",
    "addr:postcode":"ta21 8ag",
    "addr:street":"Fore Street",
    "iso:country":"GB",
    "sg:address":"33 Fore Street",
    "sg:city":"Wellington",
    "sg:classifiers":[
        {
            "category":"Home & Garden",
            "subcategory":"Hardware",
            "type":"Retail Goods"
        }
    ],
    "sg:phone":"+44 1823 662085",
    "sg:postcode":"TA21 8AG",
    "sg:province":"Devon",
    "sg:tags":[
        "merchant",
        "ironmonger"
    ],
    "wof:name":"H T Perry & Son",
    "wof:placetype":"venue"
},
  "geometry": {"coordinates":[-3.2297298908,50.9772720337],"type":"Point"}
}