{
  "type": "Feature",
  "properties": {
    "addr:full":"750 Holloway Road London Greater London N19 3JF",
    "addr:housenumber":"750",
    "addr:postcode":"n19 3jf",
    "addr:street":"Holloway Road",
    "iso:country":"GB",
    "sg:address":"750 Holloway Road",
    "sg:city":"London",
    "sg:classifiers":[
        {
            "category":"Communications",
            "type":"Services"
        }
    ],
    "sg:phone":"+44 20 7281 6911",
    "sg:postcode":"N19 3JF",
    "sg:province":"Greater London",
    "sg:tags":[
        "tv",
        "video",
        "radio"
    ],
    "wof:name":"Teleshop",
    "wof:placetype":"venue"
},
  "geometry": {"coordinates":[-0.130871,51.564449],"type":"Point"}
}