{
  "type": "Feature",
  "properties": {
    "addr:full":"69 Highbury Park, Highbury London Greater London N5 1UA",
    "addr:housenumber":"69",
    "addr:postcode":"n5 1ua",
    "addr:street":"Highbury Park",
    "iso:country":"GB",
    "sg:address":"69 Highbury Park, Highbury",
    "sg:city":"London",
    "sg:classifiers":[
        {
            "category":"Professional",
            "subcategory":"Computer Services",
            "type":"Services"
        }
    ],
    "sg:phone":"+44 20 7359 9010",
    "sg:postcode":"N5 1UA",
    "sg:province":"Greater London",
    "sg:tags":[
        "system",
        "software"
    ],
    "wof:name":"Highbury Computers",
    "wof:placetype":"venue"
},
  "geometry": {"coordinates":[-0.098314,51.555996],"type":"Point"}
}