{
  "type": "Feature",
  "properties": {
    "iso:country":"GB",
    "sg:address":"20 Angel Road",
    "sg:city":"Norwich",
    "sg:classifiers":[
        {
            "category":"Retail",
            "subcategory":"Funeral Services",
            "type":"Services"
        }
    ],
    "sg:phone":"+44 1603 219779",
    "sg:postcode":"NR3 3HP",
    "sg:province":"Norfolk",
    "sg:tags":[
        "director"
    ],
    "wof:name":"Nicholas Potts",
    "wof:placetype":"venue"
},
  "geometry": {"coordinates":[1.293016,52.64175],"type":"Point"}
}