{
  "type": "Feature",
  "properties": {
    "addr:full":"71 High Street Cheadle Staffordshire ST10 1AN",
    "addr:housenumber":"71",
    "addr:postcode":"st10 1an",
    "addr:street":"High Street",
    "iso:country":"GB",
    "sg:address":"71 High Street",
    "sg:city":"Cheadle",
    "sg:classifiers":[
        {
            "category":"Insurance",
            "subcategory":"Insurance Agent",
            "type":"Services"
        }
    ],
    "sg:postcode":"ST10 1AN",
    "sg:province":"Staffordshire",
    "wof:name":"Osborne & Tomkinson Ltd",
    "wof:placetype":"venue"
},
  "geometry": {"coordinates":[-1.990918,52.986309],"type":"Point"}
}