{
  "type": "Feature",
  "properties": {
    "addr:full":"383 Hoylake Road Wirral Merseyside CH46 6DF",
    "addr:housenumber":"383",
    "addr:postcode":"ch46 6df",
    "addr:street":"Hoylake Road",
    "iso:country":"GB",
    "sg:address":"383 Hoylake Road",
    "sg:city":"Wirral",
    "sg:classifiers":[
        {
            "category":"Home & Garden",
            "subcategory":"Furniture",
            "type":"Retail Goods"
        }
    ],
    "sg:phone":"+44 151 606 8585",
    "sg:postcode":"CH46 6DF",
    "sg:province":"Merseyside",
    "wof:name":"The Sofa Co",
    "wof:placetype":"venue"
},
  "geometry": {"coordinates":[-3.121450901,53.3974723816],"type":"Point"}
}