{
  "type": "Feature",
  "properties": {
    "addr:full":"4-5 Napier Street Plymouth Devon PL1 4QX",
    "addr:housenumber":"4-5",
    "addr:postcode":"pl1 4qx",
    "addr:street":"Napier Street",
    "iso:country":"GB",
    "sg:address":"4-5 Napier Street",
    "sg:city":"Plymouth",
    "sg:classifiers":[
        {
            "category":"Social Services",
            "subcategory":"Retirement Home",
            "type":"Services"
        }
    ],
    "sg:phone":"+44 1752 606877",
    "sg:postcode":"PL1 4QX",
    "sg:province":"Devon",
    "sg:tags":[
        "residential",
        "care"
    ],
    "wof:name":"Napier Lodge Residential Home",
    "wof:placetype":"venue"
},
  "geometry": {"coordinates":[-4.169745,50.377239],"type":"Point"}
}