{
  "type": "Feature",
  "properties": {
    "iso:country":"GB",
    "sg:address":"Glencairn, Oatlands Terr",
    "sg:city":"Galashiels",
    "sg:classifiers":[
        {
            "category":"Retail",
            "subcategory":"Driving School",
            "type":"Services"
        }
    ],
    "sg:phone":"+44 1896 753219",
    "sg:postcode":"TD1 3DB",
    "sg:province":"Scottish Borders",
    "wof:name":"Glencairn School Of Motoring",
    "wof:placetype":"venue"
},
  "geometry": {"coordinates":[-2.802979,55.612156],"type":"Point"}
}