{
  "type": "Feature",
  "properties": {
    "addr:full":"4 Sandringham Rise, Shepshed Loughborough Leicestershire LE11 5AS",
    "addr:housenumber":"4",
    "addr:postcode":"le11 5as",
    "addr:street":"Sandringham Rise",
    "iso:country":"GB",
    "sg:address":"4 Sandringham Rise, Shepshed",
    "sg:city":"Loughborough",
    "sg:classifiers":[
        {
            "category":"Professional",
            "type":"Services"
        }
    ],
    "sg:phone":"+44 1509 829451",
    "sg:postcode":"LE11 5AS",
    "sg:province":"Leicestershire",
    "sg:tags":[
        "reflexologists"
    ],
    "wof:name":"Heather Patterson",
    "wof:placetype":"venue"
},
  "geometry": {"coordinates":[-1.223474,52.768524],"type":"Point"}
}