{
  "type": "Feature",
  "properties": {
    "addr:full":"61 Hornby Blvd, Litherland Liverpool Merseyside L21 8HF",
    "addr:housenumber":"61",
    "addr:postcode":"l21 8hf",
    "addr:street":"Hornby Blvd Litherland",
    "iso:country":"GB",
    "sg:address":"61 Hornby Blvd, Litherland",
    "sg:city":"Liverpool",
    "sg:classifiers":[
        {
            "category":"Building & Trades",
            "subcategory":"Construction",
            "type":"Services"
        }
    ],
    "sg:phone":"+44 151 944 1297",
    "sg:postcode":"L21 8HF",
    "sg:province":"Merseyside",
    "sg:tags":[
        "builder"
    ],
    "wof:name":"Kelpie Properties Ltd.",
    "wof:placetype":"venue"
},
  "geometry": {"coordinates":[-3.0007879734,53.4621887207],"type":"Point"}
}