{
  "type": "Feature",
  "properties": {
    "iso:country":"GB",
    "sg:address":"7 Queens Cres",
    "sg:city":"Glasgow",
    "sg:classifiers":[
        {
            "category":"Organizations",
            "subcategory":"Non-profit Organization",
            "type":"Services"
        }
    ],
    "sg:phone":"+44 141 332 2674",
    "sg:postcode":"G4 9BW",
    "sg:province":"Glasgow City",
    "sg:tags":[
        "organisation",
        "voluntary",
        "charity"
    ],
    "wof:name":"Rotary Residential  &  Care Centres",
    "wof:placetype":"venue"
},
  "geometry": {"coordinates":[-4.270086,55.871029],"type":"Point"}
}