{
  "type": "Feature",
  "properties": {
    "addr:full":"55 Sheen Lane London Greater London SW14 8AB",
    "addr:housenumber":"55",
    "addr:postcode":"sw14 8ab",
    "addr:street":"Sheen Lane",
    "iso:country":"GB",
    "sg:address":"55 Sheen Lane",
    "sg:city":"London",
    "sg:classifiers":[
        {
            "category":"Home & Garden",
            "subcategory":"Hardware",
            "type":"Retail Goods"
        }
    ],
    "sg:phone":"+44 20 8876 6845",
    "sg:postcode":"SW14 8AB",
    "sg:province":"Greater London",
    "wof:name":"J R Hardwares",
    "wof:placetype":"venue"
},
  "geometry": {"coordinates":[-0.266504,51.467239],"type":"Point"}
}