{
  "type": "Feature",
  "properties": {
    "iso:country":"GB",
    "sg:address":"Oast View, Main Road, Icklesham",
    "sg:city":"Winchelsea",
    "sg:classifiers":[
        {
            "category":"Building & Trades",
            "subcategory":"Construction",
            "type":"Services"
        }
    ],
    "sg:phone":"+44 1424 813741",
    "sg:postcode":"TN36 4BA",
    "sg:province":"East Sussex",
    "sg:tags":[
        "joiner",
        "carpenter"
    ],
    "wof:name":"P C Medhurst",
    "wof:placetype":"venue"
},
  "geometry": {"coordinates":[0.7068150043,50.9243011475],"type":"Point"}
}