{
  "type": "Feature",
  "properties": {
    "iso:country":"GB",
    "sg:address":"Partners House, Crown Lane, Theale",
    "sg:city":"Reading",
    "sg:classifiers":[
        {
            "category":"Real Estate",
            "subcategory":"Developer",
            "type":"Services"
        }
    ],
    "sg:phone":"+44 118 930 5105",
    "sg:postcode":"RG7 5BQ",
    "sg:province":"Berkshire",
    "sg:tags":[
        "property"
    ],
    "wof:name":"Property & Estate Development Consultants Ltd",
    "wof:placetype":"venue"
},
  "geometry": {"coordinates":[-1.078033,51.438488],"type":"Point"}
}