{
  "type": "Feature",
  "properties": {
    "iso:country":"GB",
    "sg:address":"503 Wakefield Road",
    "sg:city":"Huddersfield",
    "sg:classifiers":[
        {
            "category":"Building & Trades",
            "subcategory":"Plumbing",
            "type":"Services"
        }
    ],
    "sg:postcode":"HD5 9XN",
    "sg:province":"West Yorkshire",
    "sg:tags":[
        "heating"
    ],
    "wof:name":"Walter Best",
    "wof:placetype":"venue"
},
  "geometry": {"coordinates":[-1.7483320236,53.6445350647],"type":"Point"}
}