{
  "type": "Feature",
  "properties": {
    "iso:country":"GB",
    "sg:address":"7 Hunter St, East Kilbride",
    "sg:city":"Glasgow",
    "sg:classifiers":[
        {
            "category":"Personal",
            "subcategory":"Beauty Salon",
            "type":"Services"
        }
    ],
    "sg:phone":"+44 1355 244412",
    "sg:postcode":"G74 4LZ",
    "sg:province":"South Lanarkshire",
    "sg:tags":[
        "unisex",
        "hairdresser"
    ],
    "wof:name":"Black,Elizabeth,",
    "wof:placetype":"venue"
},
  "geometry": {"coordinates":[-4.174929,55.765301],"type":"Point"}
}