{
  "type": "Feature",
  "properties": {
    "iso:country":"GB",
    "sg:address":"Packridge Farm, Packridge Lane",
    "sg:city":"Romsey",
    "sg:classifiers":[
        {
            "category":"Building & Trades",
            "subcategory":"Equipment Rental",
            "type":"Services"
        }
    ],
    "sg:postcode":"SO51 9LL",
    "sg:province":"Hampshire",
    "sg:tags":[
        "hire",
        "catering"
    ],
    "wof:name":"Country Cooks Hire",
    "wof:placetype":"venue"
},
  "geometry": {"coordinates":[-1.450814,50.963814],"type":"Point"}
}