{
  "type": "Feature",
  "properties": {
    "iso:country":"GB",
    "sg:address":"97 Skeffington Rd",
    "sg:city":"Preston",
    "sg:classifiers":[
        {
            "category":"Building & Trades",
            "subcategory":"Construction",
            "type":"Services"
        }
    ],
    "sg:phone":"+44 1772 463765",
    "sg:postcode":"PR1 5UR",
    "sg:province":"Lancashire",
    "sg:tags":[
        "roofing"
    ],
    "wof:name":"B C R",
    "wof:placetype":"venue"
},
  "geometry": {"coordinates":[-2.6802148819,53.765712738],"type":"Point"}
}