{
  "type": "Feature",
  "properties": {
    "addr:full":"Premier House, 43-48 New Street Birmingham West Midlands B2 4LJ",
    "addr:housenumber":"43-48",
    "addr:postcode":"b2 4lj",
    "addr:street":"New Street",
    "iso:country":"GB",
    "sg:address":"Premier House, 43-48 New Street",
    "sg:city":"Birmingham",
    "sg:classifiers":[
        {
            "category":"Retail",
            "subcategory":"Driving School",
            "type":"Services"
        }
    ],
    "sg:postcode":"B2 4LJ",
    "sg:province":"West Midlands",
    "wof:name":"Ernest Reeds",
    "wof:placetype":"venue"
},
  "geometry": {"coordinates":[-1.8993849754,52.4792518616],"type":"Point"}
}