{
  "type": "Feature",
  "properties": {
    "addr:full":"165 King St Norwich Norfolk NR1 1QH",
    "addr:housenumber":"165",
    "addr:postcode":"nr1 1qh",
    "addr:street":"King St",
    "iso:country":"GB",
    "sg:address":"165 King St",
    "sg:city":"Norwich",
    "sg:classifiers":[
        {
            "category":"Shopping",
            "type":"Retail Goods"
        }
    ],
    "sg:phone":"+44 1603 765838",
    "sg:postcode":"NR1 1QH",
    "sg:province":"Norfolk",
    "sg:tags":[
        "part",
        "accessory"
    ],
    "wof:name":"Citroen Parts",
    "wof:placetype":"venue"
},
  "geometry": {"coordinates":[1.3024020195,52.6243972778],"type":"Point"}
}