{
  "type": "Feature",
  "properties": {
    "iso:country":"GB",
    "sg:address":"Unit 12 Broughton Manor Business Park",
    "sg:city":"Newport Pagnell",
    "sg:classifiers":[
        {
            "category":"Professional",
            "subcategory":"Computer Services",
            "type":"Services"
        }
    ],
    "sg:phone":"+44 1908 696464",
    "sg:postcode":"MK16 0HF",
    "sg:province":"Buckinghamshire",
    "sg:tags":[
        "system",
        "software"
    ],
    "wof:name":"First Line Systems Ltd",
    "wof:placetype":"venue"
},
  "geometry": {"coordinates":[-0.6905170083,52.0483169556],"type":"Point"}
}