{
  "type": "Feature",
  "properties": {
    "addr:full":"Fronwen Farm, Horeb Llandysul Carmarthenshire SA44 4JS",
    "addr:postcode":"sa44 4js",
    "iso:country":"GB",
    "sg:address":"Fronwen Farm, Horeb",
    "sg:city":"Llandysul",
    "sg:classifiers":[
        {
            "category":"Farming",
            "subcategory":"Livestock Farm",
            "type":"Manufacturing & Wholesale Goods"
        },
        {
            "category":"Farming",
            "subcategory":"Farm",
            "type":"Manufacturing & Wholesale Goods"
        }
    ],
    "sg:phone":"+44 1559 362370",
    "sg:postcode":"SA44 4JS",
    "sg:province":"Carmarthenshire",
    "sg:tags":[
        "mixed",
        "crop",
        "others"
    ],
    "wof:name":"E A & A & H Thomas",
    "wof:placetype":"venue"
},
  "geometry": {"coordinates":[-4.3078169823,52.0444793701],"type":"Point"}
}