{
  "type": "Feature",
  "properties": {
    "addr:full":"28a High Street Poole Dorset BH15 1BP",
    "addr:housenumber":"28a",
    "addr:postcode":"bh15 1bp",
    "addr:street":"High Street",
    "iso:country":"GB",
    "sg:address":"28a High Street",
    "sg:city":"Poole",
    "sg:classifiers":[
        {
            "category":"Shopping",
            "subcategory":"Department Store",
            "type":"Retail Goods"
        }
    ],
    "sg:phone":"+44 1202 678270",
    "sg:postcode":"BH15 1BP",
    "sg:province":"Dorset",
    "wof:name":"Geoff Barlow Models",
    "wof:placetype":"venue"
},
  "geometry": {"coordinates":[-1.9877170324,50.7133712769],"type":"Point"}
}