{
  "type": "Feature",
  "properties": {
    "iso:country":"GB",
    "sg:address":"Unit C Mandale Industrial Estate, Thornaby",
    "sg:city":"Stockton-on-tees",
    "sg:classifiers":[
        {
            "category":"Manufacturing",
            "subcategory":"Motor Vehicles & Parts",
            "type":"Manufacturing & Wholesale Goods"
        },
        {
            "category":"Wholesale",
            "subcategory":"Machinery & Supplies",
            "type":"Manufacturing & Wholesale Goods"
        }
    ],
    "sg:phone":"+44 1642 671605",
    "sg:postcode":"TS17 6BX",
    "sg:province":"Durham",
    "sg:tags":[
        "bearing",
        "hydraulic"
    ],
    "wof:name":"Fenner Power Transmission",
    "wof:placetype":"venue"
},
  "geometry": {"coordinates":[-1.3030500412,54.5577201843],"type":"Point"}
}