{
  "type": "Feature",
  "properties": {
    "addr:full":"47 Woodnewton Way Corby Northamptonshire NN17 2NS",
    "addr:housenumber":"47",
    "addr:postcode":"nn17 2ns",
    "addr:street":"Woodnewton Way",
    "iso:country":"GB",
    "sg:address":"47 Woodnewton Way",
    "sg:city":"Corby",
    "sg:classifiers":[
        {
            "category":"Arts & Performance",
            "subcategory":"Music",
            "type":"Entertainment"
        }
    ],
    "sg:phone":"+44 1536 267042",
    "sg:postcode":"NN17 2NS",
    "sg:province":"Northamptonshire",
    "sg:tags":[
        "mobile",
        "disco"
    ],
    "wof:name":"Andys Getaround Disco",
    "wof:placetype":"venue"
},
  "geometry": {"coordinates":[-0.716853,52.495205],"type":"Point"}
}