{
  "type": "Feature",
  "properties": {
    "addr:full":"4 Litchfield Mews, Shaftesbury Street South Derby Derbyshire DE23 8YH",
    "addr:housenumber":"4",
    "addr:postcode":"de23 8yh",
    "addr:street":"Litchfield Mews Shaftesbury Street South",
    "iso:country":"GB",
    "sg:address":"4 Litchfield Mews, Shaftesbury Street South",
    "sg:city":"Derby",
    "sg:classifiers":[
        {
            "category":"Shopping",
            "subcategory":"Discount & Variety Stores",
            "type":"Retail Goods"
        }
    ],
    "sg:phone":"+44 1332 298080",
    "sg:postcode":"DE23 8YH",
    "sg:province":"Derbyshire",
    "sg:tags":[
        "cleaning",
        "supply"
    ],
    "wof:name":"Lyall & Ashley",
    "wof:placetype":"venue"
},
  "geometry": {"coordinates":[-1.466989,52.903965],"type":"Point"}
}