{
  "type": "Feature",
  "properties": {
    "iso:country":"GB",
    "sg:address":"1st Floor",
    "sg:city":"Dover",
    "sg:classifiers":[
        {
            "category":"Banks & Credit Unions",
            "subcategory":"Bureau De Change",
            "type":"Services"
        }
    ],
    "sg:phone":"+44 1304 225231",
    "sg:postcode":"CT16 1BT",
    "sg:province":"Kent",
    "sg:tags":[
        "town",
        "consultant",
        "planning"
    ],
    "wof:name":"Dover Town Centre Management Co. Ltd.",
    "wof:placetype":"venue"
},
  "geometry": {"coordinates":[1.311,51.12751],"type":"Point"}
}