{
  "type": "Feature",
  "properties": {
    "addr:full":"View Farm Cambridge Cambridgeshire CB3 8DA",
    "addr:postcode":"cb3 8da",
    "iso:country":"GB",
    "sg:address":"View Farm",
    "sg:city":"Cambridge",
    "sg:classifiers":[
        {
            "category":"Military Area",
            "subcategory":"Army Base",
            "type":"Public Place"
        }
    ],
    "sg:postcode":"CB3 8DA",
    "sg:province":"Cambridgeshire",
    "sg:tags":[
        "transportation",
        "livestock"
    ],
    "wof:name":"K J Speechley & Son",
    "wof:placetype":"venue"
},
  "geometry": {"coordinates":[0.024317,52.239101],"type":"Point"}
}