{
  "type": "Feature",
  "properties": {
    "iso:country":"GB",
    "sg:address":"Stoke Park Hospital, Stapleton",
    "sg:city":"Bristol",
    "sg:classifiers":[
        {
            "category":"Health Services",
            "subcategory":"Clinic",
            "type":"Services"
        }
    ],
    "sg:postcode":"BS16 1QU",
    "sg:province":"City of Bristol",
    "sg:tags":[
        "nh"
    ],
    "wof:name":"Phoenix N H S Trust",
    "wof:placetype":"venue"
},
  "geometry": {"coordinates":[-2.591429,51.453667],"type":"Point"}
}