{
  "type": "Feature",
  "properties": {
    "addr:full":"The Elm The Street Norwich Norfolk NR10 4DH",
    "addr:postcode":"nr10 4dh",
    "addr:street":"The Street",
    "iso:country":"GB",
    "sg:address":"The Elm The Street",
    "sg:city":"Norwich",
    "sg:classifiers":[
        {
            "category":"Manufacturing",
            "subcategory":"Lumber",
            "type":"Manufacturing & Wholesale Goods"
        }
    ],
    "sg:postcode":"NR10 4DH",
    "sg:province":"Norfolk",
    "sg:tags":[
        "importer",
        "merchants",
        "agent",
        "timber"
    ],
    "wof:name":"Robert Patrick Dack",
    "wof:placetype":"venue"
},
  "geometry": {"coordinates":[1.1281399727,52.7605438232],"type":"Point"}
}