{
  "type": "Feature",
  "properties": {
    "addr:full":"Seacroft Mansions, Filey Road Scarborough North Yorkshire YO11 2TX",
    "addr:postcode":"yo11 2tx",
    "addr:street":"Filey Road",
    "iso:country":"GB",
    "sg:address":"Seacroft Mansions, Filey Road",
    "sg:city":"Scarborough",
    "sg:classifiers":[
        {
            "category":"Travel",
            "subcategory":"Hotels & Motels",
            "type":"Entertainment"
        }
    ],
    "sg:phone":"+44 1723 850552",
    "sg:postcode":"YO11 2TX",
    "sg:province":"North Yorkshire",
    "sg:tags":[
        "self",
        "catering"
    ],
    "wof:name":"Kimberley Holiday Flats",
    "wof:placetype":"venue"
},
  "geometry": {"coordinates":[-0.398420006,54.267288208],"type":"Point"}
}