{
  "type": "Feature",
  "properties": {
    "addr:full":"Station Road Cheddar Somerset BS27 3AQ",
    "addr:postcode":"bs27 3aq",
    "addr:street":"Station Road",
    "iso:country":"GB",
    "sg:address":"Station Road",
    "sg:city":"Cheddar",
    "sg:classifiers":[
        {
            "category":"Education",
            "subcategory":"School",
            "type":"Public Place"
        },
        {
            "category":"Community Center",
            "type":"Public Place"
        }
    ],
    "sg:phone":"+44 1934 744939",
    "sg:postcode":"BS27 3AQ",
    "sg:province":"Somerset",
    "sg:tags":[
        "recreation",
        "local",
        "authority",
        "leisure",
        "centre"
    ],
    "wof:name":"The Kings of Wessex Leisure Centre",
    "wof:placetype":"venue"
},
  "geometry": {"coordinates":[-2.7814741135,51.2752952576],"type":"Point"}
}