{
  "type": "Feature",
  "properties": {
    "addr:full":"12 King Square Avenue, Stokes Croft Bristol City of Bristol BS2 8HU",
    "addr:housenumber":"12",
    "addr:postcode":"bs2 8hu",
    "addr:street":"King Square Avenue Stokes Croft",
    "iso:country":"GB",
    "sg:address":"12 King Square Avenue, Stokes Croft",
    "sg:city":"Bristol",
    "sg:classifiers":[
        {
            "category":"Education",
            "subcategory":"Special Training",
            "type":"Public Place"
        },
        {
            "category":"Government",
            "subcategory":"Office",
            "type":"Public Place"
        }
    ],
    "sg:phone":"+44 117 924 4276",
    "sg:postcode":"BS2 8HU",
    "sg:province":"City of Bristol",
    "sg:tags":[
        "product",
        "local",
        "centre"
    ],
    "wof:name":"Open Learning Centre",
    "wof:placetype":"venue"
},
  "geometry": {"coordinates":[-2.5913689137,51.4607963562],"type":"Point"}
}