{
  "type": "Feature",
  "properties": {
    "iso:country":"GB",
    "sg:address":"Pickwell Gardens, Georgeham",
    "sg:city":"Braunton",
    "sg:classifiers":[
        {
            "category":"Food & Beverages",
            "subcategory":"Farmers Market",
            "type":"Retail Goods"
        }
    ],
    "sg:postcode":"EX33 1LA",
    "sg:province":"Devon",
    "sg:tags":[
        "gardener"
    ],
    "wof:name":"Pickwell Gardens Ltd.",
    "wof:placetype":"venue"
},
  "geometry": {"coordinates":[-4.1958937645,51.1368484497],"type":"Point"}
}