{
  "type": "Feature",
  "properties": {
    "addr:full":"Harwood Close Sutton-in-ashfield Nottinghamshire NG17 4PD",
    "addr:postcode":"ng17 4pd",
    "addr:street":"Harwood Close",
    "iso:country":"GB",
    "sg:address":"Harwood Close",
    "sg:city":"Sutton-in-ashfield",
    "sg:classifiers":[
        {
            "category":"Shopping",
            "subcategory":"Pharmacy",
            "type":"Retail Goods"
        }
    ],
    "sg:phone":"+44 1623 555282",
    "sg:postcode":"NG17 4PD",
    "sg:province":"Nottinghamshire",
    "sg:tags":[
        "pharmacist",
        "dispensing",
        "chemist"
    ],
    "wof:name":"Manor Pharmacy Ltd",
    "wof:placetype":"venue"
},
  "geometry": {"coordinates":[-1.2503130436,53.1336784363],"type":"Point"}
}