{
  "type": "Feature",
  "properties": {
    "iso:country":"GB",
    "sg:address":"21 Trustin Crescent",
    "sg:city":"Solihull",
    "sg:classifiers":[
        {
            "category":"Communications",
            "subcategory":"Film & Video Production",
            "type":"Services"
        }
    ],
    "sg:phone":"+44 121 704 3614",
    "sg:postcode":"B92 9QQ",
    "sg:province":"West Midlands",
    "sg:tags":[
        "illustrator",
        "artist"
    ],
    "wof:name":"Mick Davis Cartoons",
    "wof:placetype":"venue"
},
  "geometry": {"coordinates":[-1.76102,52.43325],"type":"Point"}
}