{
  "type": "Feature",
  "properties": {
    "addr:full":"201 Middlewood Rd, Hillsborough Sheffield South Yorkshire S6 4HD",
    "addr:housenumber":"201",
    "addr:postcode":"s6 4hd",
    "addr:street":"Middlewood Rd",
    "iso:country":"GB",
    "sg:address":"201 Middlewood Rd, Hillsborough",
    "sg:city":"Sheffield",
    "sg:classifiers":[
        {
            "category":"Shopping",
            "subcategory":"Mobile Phones",
            "type":"Retail Goods"
        }
    ],
    "sg:postcode":"S6 4HD",
    "sg:province":"South Yorkshire",
    "wof:name":"Clarke,Bill,",
    "wof:placetype":"venue"
},
  "geometry": {"coordinates":[-1.5044089556,53.4074401855],"type":"Point"}
}