{
  "type": "Feature",
  "properties": {
    "addr:full":"Unit 16 Kendrick Trading Estate, Galton Way Swindon Wiltshire SN2 2DU",
    "addr:housenumber":"unit 16",
    "addr:postcode":"sn2 2du",
    "addr:street":"Trading;Galton Way",
    "iso:country":"GB",
    "sg:address":"Unit 16 Kendrick Trading Estate, Galton Way",
    "sg:city":"Swindon",
    "sg:classifiers":[
        {
            "category":"Wholesale",
            "subcategory":"Scrap",
            "type":"Manufacturing & Wholesale Goods"
        }
    ],
    "sg:postcode":"SN2 2DU",
    "sg:province":"Wiltshire",
    "sg:tags":[
        "breaker",
        "dismantlers"
    ],
    "wof:name":"Thamesdown Breakers",
    "wof:placetype":"venue"
},
  "geometry": {"coordinates":[-1.8104000092,51.5714416504],"type":"Point"}
}