{
  "type": "Feature",
  "properties": {
    "iso:country":"GB",
    "sg:address":"6 Queen Street",
    "sg:city":"Newton Abbot",
    "sg:classifiers":[
        {
            "category":"Banks & Credit Unions",
            "subcategory":"Financial Services",
            "type":"Services"
        }
    ],
    "sg:phone":"+44 1626 54331",
    "sg:postcode":"TQ12 2EF",
    "sg:province":"Devon",
    "sg:tags":[
        "building",
        "society"
    ],
    "wof:name":"Portman Building Society",
    "wof:placetype":"venue"
},
  "geometry": {"coordinates":[-3.6096160412,50.5306091309],"type":"Point"}
}