{
  "type": "Feature",
  "properties": {
    "addr:full":"55 Deepdene Vale Dorking Surrey RH4 1NJ",
    "addr:housenumber":"55",
    "addr:postcode":"rh4 1nj",
    "addr:street":"Deepdene Vale",
    "iso:country":"GB",
    "sg:address":"55 Deepdene Vale",
    "sg:city":"Dorking",
    "sg:classifiers":[
        {
            "category":"Health Services",
            "subcategory":"Podiatrist",
            "type":"Services"
        },
        {
            "category":"Health Services",
            "subcategory":"Chiropractor",
            "type":"Services"
        }
    ],
    "sg:phone":"+44 1306 884723",
    "sg:postcode":"RH4 1NJ",
    "sg:province":"Surrey",
    "sg:tags":[
        "chiropodist"
    ],
    "wof:name":"Verity Nicholls",
    "wof:placetype":"venue"
},
  "geometry": {"coordinates":[-0.3211539984,51.2387008667],"type":"Point"}
}