{
  "type": "Feature",
  "properties": {
    "addr:full":"318 Mill St Liverpool Merseyside L8 6QR",
    "addr:housenumber":"318",
    "addr:postcode":"l8 6qr",
    "addr:street":"Mill St",
    "iso:country":"GB",
    "sg:address":"318 Mill St",
    "sg:city":"Liverpool",
    "sg:classifiers":[
        {
            "category":"Personal",
            "subcategory":"Beauty Salon",
            "type":"Services"
        }
    ],
    "sg:postcode":"L8 6QR",
    "sg:province":"Merseyside",
    "sg:tags":[
        "unisex",
        "hairdresser"
    ],
    "wof:name":"Howell,J,",
    "wof:placetype":"venue"
},
  "geometry": {"coordinates":[-2.9709310532,53.3849105835],"type":"Point"}
}