{
  "type": "Feature",
  "properties": {
    "addr:full":"G H Q No1 Union Terrace, Marine Promenade, New Brighton Wirral Merseyside CH45 2JT",
    "addr:postcode":"ch45 2jt",
    "addr:street":"G;Q No1 Union Terrace Marine Promenade",
    "iso:country":"GB",
    "sg:address":"G H Q No1 Union Terrace, Marine Promenade, New Brighton",
    "sg:city":"Wirral",
    "sg:classifiers":[
        {
            "category":"Professional",
            "subcategory":"Management & Consulting",
            "type":"Services"
        }
    ],
    "sg:phone":"+44 151 637 0055",
    "sg:postcode":"CH45 2JT",
    "sg:province":"Merseyside",
    "sg:tags":[
        "music"
    ],
    "wof:name":"Managemajor Ltd.",
    "wof:placetype":"venue"
},
  "geometry": {"coordinates":[-3.0443599224,53.4397392273],"type":"Point"}
}