{
  "type": "Feature",
  "properties": {
    "addr:full":"1 Moredon Road Swindon Wiltshire SN25 3DQ",
    "addr:housenumber":"1",
    "addr:postcode":"sn25 3dq",
    "addr:street":"Moredon Road",
    "iso:country":"GB",
    "sg:address":"1 Moredon Road",
    "sg:city":"Swindon",
    "sg:classifiers":[
        {
            "category":"Fast Food",
            "type":"Food & Drink"
        }
    ],
    "sg:phone":"+44 1793 432983",
    "sg:postcode":"SN25 3DQ",
    "sg:province":"Wiltshire",
    "sg:tags":[
        "away",
        "take"
    ],
    "wof:name":"Shah Jalal Indian Takeaway",
    "wof:placetype":"venue"
},
  "geometry": {"coordinates":[-1.7994220257,51.5831108093],"type":"Point"}
}