{
  "type": "Feature",
  "properties": {
    "addr:full":"11 Dene Path Andover Hampshire SP10 2AJ",
    "addr:housenumber":"11",
    "addr:postcode":"sp10 2aj",
    "addr:street":"Dene Path",
    "iso:country":"GB",
    "sg:address":"11 Dene Path",
    "sg:city":"Andover",
    "sg:classifiers":[
        {
            "category":"Professional",
            "subcategory":"Management & Consulting",
            "type":"Services"
        }
    ],
    "sg:postcode":"SP10 2AJ",
    "sg:province":"Hampshire",
    "sg:tags":[
        "consultant",
        "business"
    ],
    "wof:name":"Dene-Tech Services",
    "wof:placetype":"venue"
},
  "geometry": {"coordinates":[-1.476162,51.205765],"type":"Point"}
}