{
  "type": "Feature",
  "properties": {
    "iso:country":"GB",
    "sg:address":"110a Westbourne Gro",
    "sg:city":"London",
    "sg:classifiers":[
        {
            "category":"Shopping",
            "subcategory":"Comic Books",
            "type":"Retail Goods"
        }
    ],
    "sg:phone":"+44 7956 884103",
    "sg:postcode":"W2 5RU",
    "sg:province":"Greater London",
    "sg:tags":[
        "jeweller"
    ],
    "wof:name":"The Gold Box",
    "wof:placetype":"venue"
},
  "geometry": {"coordinates":[-0.194688,51.519161],"type":"Point"}
}