{
  "type": "Feature",
  "properties": {
    "iso:country":"GB",
    "sg:address":"Kwik Save, Dale Street",
    "sg:city":"Rochdale",
    "sg:classifiers":[
        {
            "category":"Food & Beverages",
            "subcategory":"Meat & Fish",
            "type":"Retail Goods"
        }
    ],
    "sg:postcode":"OL16 4HS",
    "sg:province":"Lancashire",
    "sg:tags":[
        "butcher"
    ],
    "wof:name":"P C Bamford",
    "wof:placetype":"venue"
},
  "geometry": {"coordinates":[-2.11242,53.61087],"type":"Point"}
}