{
  "type": "Feature",
  "properties": {
    "addr:full":"8 Fareham Enterprise Centre, Newgate La Fareham Hampshire PO14 1TH",
    "addr:housenumber":"8",
    "addr:postcode":"po14 1th",
    "addr:street":"Newgate",
    "iso:country":"GB",
    "sg:address":"8 Fareham Enterprise Centre, Newgate La",
    "sg:city":"Fareham",
    "sg:classifiers":[
        {
            "category":"Manufacturing",
            "subcategory":"Tools & Machinery",
            "type":"Manufacturing & Wholesale Goods"
        }
    ],
    "sg:postcode":"PO14 1TH",
    "sg:province":"Hampshire",
    "sg:tags":[
        "design",
        "maker"
    ],
    "wof:name":"Fearl,Gary,",
    "wof:placetype":"venue"
},
  "geometry": {"coordinates":[-1.184910059,50.8413391113],"type":"Point"}
}