{
  "type": "Feature",
  "properties": {
    "iso:country":"GB",
    "sg:address":"Central Garage 4 Grange Rd, Southwick",
    "sg:city":"Brighton",
    "sg:classifiers":[
        {
            "category":"Retail",
            "subcategory":"Auto Repair",
            "type":"Services"
        }
    ],
    "sg:phone":"+44 1273 591138",
    "sg:postcode":"BN42 4DQ",
    "sg:province":"West Sussex",
    "sg:tags":[
        "modification",
        "garage"
    ],
    "wof:name":"S.J.Hawkley Limited",
    "wof:placetype":"venue"
},
  "geometry": {"coordinates":[-0.23742,50.836205],"type":"Point"}
}