{
  "type": "Feature",
  "properties": {
    "addr:full":"3s Choles Lane, Scholes Cleckheaton West Yorkshire BD19 6PA",
    "addr:postcode":"bd19 6pa",
    "addr:street":"Choles Lane",
    "iso:country":"GB",
    "sg:address":"3s Choles Lane, Scholes",
    "sg:city":"Cleckheaton",
    "sg:classifiers":[
        {
            "category":"Fast Food",
            "type":"Food & Drink"
        }
    ],
    "sg:phone":"+44 1274 862006",
    "sg:postcode":"BD19 6PA",
    "sg:province":"West Yorkshire",
    "sg:tags":[
        "away",
        "take"
    ],
    "wof:name":"Shaffiq's",
    "wof:placetype":"venue"
},
  "geometry": {"coordinates":[-1.749255,53.72961],"type":"Point"}
}