{
  "type": "Feature",
  "properties": {
    "iso:country":"GB",
    "sg:address":"19 Highfield Road, Moseley",
    "sg:city":"Birmingham",
    "sg:classifiers":[
        {
            "category":"Professional",
            "type":"Services"
        },
        {
            "category":"Social Services",
            "subcategory":"Job Training",
            "type":"Services"
        }
    ],
    "sg:phone":"+44 121 449 1578",
    "sg:postcode":"B13 9HL",
    "sg:province":"West Midlands",
    "sg:tags":[
        "translator",
        "interpreter",
        "translation",
        "activity"
    ],
    "wof:name":"Ruslan Ltd.",
    "wof:placetype":"venue"
},
  "geometry": {"coordinates":[-1.876134,52.445724],"type":"Point"}
}