{
  "type": "Feature",
  "properties": {
    "iso:country":"GB",
    "sg:address":"The Clock House, North Street",
    "sg:city":"Midhurst",
    "sg:classifiers":[
        {
            "category":"Autos & Motor Vehicles",
            "subcategory":"Motorcycle Sales",
            "type":"Retail Goods"
        }
    ],
    "sg:phone":"+44 1730 812399",
    "sg:postcode":"GU29 9DS",
    "sg:province":"West Sussex",
    "sg:tags":[
        "chauffeur",
        "driven",
        "car"
    ],
    "wof:name":"Executive Chauffeurs",
    "wof:placetype":"venue"
},
  "geometry": {"coordinates":[-0.738613,50.987309],"type":"Point"}
}