{
  "type": "Feature",
  "properties": {
    "addr:full":"1 Gleneagles Close Hereford Herefordshire HR1 1JZ",
    "addr:housenumber":"1",
    "addr:postcode":"hr1 1jz",
    "addr:street":"Gleneagles Close",
    "iso:country":"GB",
    "sg:address":"1 Gleneagles Close",
    "sg:city":"Hereford",
    "sg:classifiers":[
        {
            "category":"Retail",
            "subcategory":"Storage",
            "type":"Services"
        }
    ],
    "sg:phone":"+44 1432 277176",
    "sg:postcode":"HR1 1JZ",
    "sg:province":"Herefordshire",
    "sg:tags":[
        "household",
        "removal"
    ],
    "wof:name":"Ace Removals",
    "wof:placetype":"venue"
},
  "geometry": {"coordinates":[-2.7154359818,52.0756835938],"type":"Point"}
}