{
  "type": "Feature",
  "properties": {
    "addr:full":"Kellaw Road, Yarm Road Industrial Estate Darlington Durham DL1 4YA",
    "addr:housenumber":"estate",
    "addr:postcode":"dl1 4ya",
    "addr:street":"Kellaw Road Yarm Road Industrial",
    "iso:country":"GB",
    "sg:address":"Kellaw Road, Yarm Road Industrial Estate",
    "sg:city":"Darlington",
    "sg:classifiers":[
        {
            "category":"Recreation",
            "type":"Entertainment"
        }
    ],
    "sg:phone":"+44 1325 489012",
    "sg:postcode":"DL1 4YA",
    "sg:province":"Durham",
    "sg:tags":[
        "snooker",
        "billiards",
        "pool"
    ],
    "wof:name":"Avante Sales Ltd.",
    "wof:placetype":"venue"
},
  "geometry": {"coordinates":[-1.5146249533,54.5243377686],"type":"Point"}
}