{
  "type": "Feature",
  "properties": {
    "addr:full":"101 Lidget Street, Lindley Huddersfield West Yorkshire HD3 3JR",
    "addr:housenumber":"101",
    "addr:postcode":"hd3 3jr",
    "addr:street":"Lidget Street;West",
    "iso:country":"GB",
    "sg:address":"101 Lidget Street, Lindley",
    "sg:city":"Huddersfield",
    "sg:classifiers":[
        {
            "category":"Travel",
            "subcategory":"Travel Agent",
            "type":"Entertainment"
        }
    ],
    "sg:phone":"+44 1484 461111",
    "sg:postcode":"HD3 3JR",
    "sg:province":"West Yorkshire",
    "sg:tags":[
        "agency",
        "activity"
    ],
    "wof:name":"Jetsetters Travel",
    "wof:placetype":"venue"
},
  "geometry": {"coordinates":[-1.8246560097,53.6620063782],"type":"Point"}
}