{
  "type": "Feature",
  "properties": {
    "addr:full":"37 Hillside Road, West Kirby Wirral Merseyside CH48 8BD",
    "addr:housenumber":"37",
    "addr:postcode":"ch48 8bd",
    "addr:street":"Hillside Road",
    "iso:country":"GB",
    "sg:address":"37 Hillside Road, West Kirby",
    "sg:city":"Wirral",
    "sg:classifiers":[
        {
            "category":"Personal",
            "type":"Services"
        }
    ],
    "sg:phone":"+44 151 625 3948",
    "sg:postcode":"CH48 8BD",
    "sg:province":"Merseyside",
    "sg:tags":[
        "wedding"
    ],
    "wof:name":"Grange Limousines",
    "wof:placetype":"venue"
},
  "geometry": {"coordinates":[-3.1618340015,53.3714675903],"type":"Point"}
}