{
  "type": "Feature",
  "properties": {
    "addr:full":"10 Kingsdown Park Whitstable Kent CT5 2DU",
    "addr:housenumber":"10",
    "addr:postcode":"ct5 2du",
    "addr:street":"Kingsdown Park Whitstable",
    "iso:country":"GB",
    "sg:address":"10 Kingsdown Park",
    "sg:city":"Whitstable",
    "sg:classifiers":[
        {
            "category":"Real Estate",
            "subcategory":"Real Estate Services",
            "type":"Services"
        },
        {
            "category":"Real Estate",
            "subcategory":"Real Estate Agent",
            "type":"Services"
        }
    ],
    "sg:phone":"+44 1227 771277",
    "sg:postcode":"CT5 2DU",
    "sg:province":"Kent",
    "sg:tags":[
        "management"
    ],
    "wof:name":"J Stuart Management",
    "wof:placetype":"venue"
},
  "geometry": {"coordinates":[1.0399689674,51.3623085022],"type":"Point"}
}