{
  "type": "Feature",
  "properties": {
    "addr:full":"Unit 4, Clarke Hall Farm, Aberford Road Wakefield West Yorkshire WF1 4AL",
    "addr:housenumber":"unit 4",
    "addr:postcode":"wf1 4al",
    "addr:street":"Clarke Hall;Aberford Road",
    "iso:country":"GB",
    "sg:address":"Unit 4, Clarke Hall Farm, Aberford Road",
    "sg:city":"Wakefield",
    "sg:classifiers":[
        {
            "category":"Professional",
            "subcategory":"Computer Services",
            "type":"Services"
        }
    ],
    "sg:phone":"+44 1924 203600",
    "sg:postcode":"WF1 4AL",
    "sg:province":"West Yorkshire",
    "sg:tags":[
        "aided",
        "design"
    ],
    "wof:name":"The CAD Division",
    "wof:placetype":"venue"
},
  "geometry": {"coordinates":[-1.4808900356,53.6944656372],"type":"Point"}
}