{
  "type": "Feature",
  "properties": {
    "addr:full":"Unit 1-2, Springfield Industrial Estate, Forth Street Stirling Stirling FK8 1UE",
    "addr:housenumber":"unit 1-2;estate",
    "addr:postcode":"fk8 1ue",
    "addr:street":"Springfield Industrial;Forth Street",
    "iso:country":"GB",
    "sg:address":"Unit 1-2, Springfield Industrial Estate, Forth Street",
    "sg:city":"Stirling",
    "sg:classifiers":[
        {
            "category":"Manufacturing",
            "subcategory":"Lumber",
            "type":"Manufacturing & Wholesale Goods"
        }
    ],
    "sg:phone":"+44 1786 449977",
    "sg:postcode":"FK8 1UE",
    "sg:province":"Stirling",
    "sg:tags":[
        "merchant",
        "merchants",
        "importer",
        "agent",
        "timber"
    ],
    "wof:name":"Stirling Wood Centre",
    "wof:placetype":"venue"
},
  "geometry": {"coordinates":[-3.935184,56.12431],"type":"Point"}
}