{
  "type": "Feature",
  "properties": {
    "addr:full":"64 Bells Road, Goldstone Great Yarmouth Norfolk NR31 6AG",
    "addr:housenumber":"64",
    "addr:postcode":"nr31 6ag",
    "addr:street":"Bells Road;Yarmouth",
    "iso:country":"GB",
    "sg:address":"64 Bells Road, Goldstone",
    "sg:city":"Great Yarmouth",
    "sg:classifiers":[
        {
            "category":"Building & Trades",
            "subcategory":"Plumbing",
            "type":"Services"
        }
    ],
    "sg:phone":"+44 1493 662322",
    "sg:postcode":"NR31 6AG",
    "sg:province":"Norfolk",
    "sg:tags":[
        "heating"
    ],
    "wof:name":"Russells Plumbing & Heating",
    "wof:placetype":"venue"
},
  "geometry": {"coordinates":[1.7281240225,52.5708122253],"type":"Point"}
}