{
  "type": "Feature",
  "properties": {
    "iso:country":"GB",
    "sg:address":"51 Whitcomb Street",
    "sg:city":"London",
    "sg:classifiers":[
        {
            "category":"Shopping",
            "subcategory":"Event Tickets",
            "type":"Retail Goods"
        }
    ],
    "sg:phone":"+44 20 7925 1031",
    "sg:postcode":"WC2H 7DH",
    "sg:province":"Greater London",
    "sg:tags":[
        "agency"
    ],
    "wof:name":"Tickets Uk",
    "wof:placetype":"venue"
},
  "geometry": {"coordinates":[-0.13019,51.508934],"type":"Point"}
}