{
  "type": "Feature",
  "properties": {
    "addr:full":"Old Telephone Exchange, Margett Street, Cottenham Cambridge Cambridgeshire CB4 8QY",
    "addr:postcode":"cb4 8qy",
    "addr:street":"Margett Street",
    "iso:country":"GB",
    "sg:address":"Old Telephone Exchange, Margett Street, Cottenham",
    "sg:city":"Cambridge",
    "sg:classifiers":[
        {
            "category":"Health Services",
            "subcategory":"Dentist",
            "type":"Services"
        }
    ],
    "sg:postcode":"CB4 8QY",
    "sg:province":"Cambridgeshire",
    "wof:name":"Faber & Associates",
    "wof:placetype":"venue"
},
  "geometry": {"coordinates":[0.126215,52.286472],"type":"Point"}
}