{
  "type": "Feature",
  "properties": {
    "iso:country":"GB",
    "sg:address":"Flat 4 St Clements Court, 78 Beaufoys Avenue",
    "sg:city":"Ferndown",
    "sg:classifiers":[
        {
            "category":"Taxi",
            "type":"Transportation"
        }
    ],
    "sg:phone":"+44 1202 890231",
    "sg:postcode":"BH22 9RL",
    "sg:province":"Dorset",
    "sg:tags":[
        "mini",
        "cab"
    ],
    "wof:name":"Advanced Airports & Courier Services",
    "wof:placetype":"venue"
},
  "geometry": {"coordinates":[-1.889389,50.80183],"type":"Point"}
}