{
  "type": "Feature",
  "properties": {
    "iso:country":"GB",
    "sg:address":"4 Abbots Close",
    "sg:city":"Bodmin",
    "sg:classifiers":[
        {
            "category":"Building & Trades",
            "subcategory":"Cleaning & Sanitation",
            "type":"Services"
        }
    ],
    "sg:phone":"+44 1208 77807",
    "sg:postcode":"PL31 2AH",
    "sg:province":"Cornwall",
    "sg:tags":[
        "dry",
        "control",
        "damp",
        "rot"
    ],
    "wof:name":"Cornish Homecare",
    "wof:placetype":"venue"
},
  "geometry": {"coordinates":[-4.7102971077,50.4682350159],"type":"Point"}
}