{
  "type": "Feature",
  "properties": {
    "addr:full":"50 West St Haslemere Hampshire GU27 2AP",
    "addr:housenumber":"50",
    "addr:postcode":"gu27 2ap",
    "addr:street":"West St",
    "iso:country":"GB",
    "sg:address":"50 West St",
    "sg:city":"Haslemere",
    "sg:classifiers":[
        {
            "category":"Professional",
            "subcategory":"Accounting & Tax Preparation",
            "type":"Services"
        }
    ],
    "sg:phone":"+44 1428 658327",
    "sg:postcode":"GU27 2AP",
    "sg:province":"Hampshire",
    "sg:tags":[
        "herb",
        "spice"
    ],
    "wof:name":"P.C.P",
    "wof:placetype":"venue"
},
  "geometry": {"coordinates":[-0.7115610242,51.0894775391],"type":"Point"}
}