{
  "type": "Feature",
  "properties": {
    "addr:full":"36 Kings Rd Cheltenham Gloucestershire GL52 6BG",
    "addr:housenumber":"36",
    "addr:postcode":"gl52 6bg",
    "addr:street":"Kings Rd",
    "iso:country":"GB",
    "sg:address":"36 Kings Rd",
    "sg:city":"Cheltenham",
    "sg:classifiers":[
        {
            "category":"Shopping",
            "subcategory":"Florist",
            "type":"Retail Goods"
        }
    ],
    "sg:phone":"+44 1242 570100",
    "sg:postcode":"GL52 6BG",
    "sg:province":"Gloucestershire",
    "wof:name":"Tropical Plants Of Bristol",
    "wof:placetype":"venue"
},
  "geometry": {"coordinates":[-2.0606710911,51.8977622986],"type":"Point"}
}