{
  "type": "Feature",
  "properties": {
    "addr:full":"3rd Avenue, Off Millbrook Road, Millbrook Southampton Hampshire SO15 0JZ",
    "addr:postcode":"so15 0jz",
    "addr:street":"3Rd Avenue Off Millbrook Road",
    "iso:country":"GB",
    "sg:address":"3rd Avenue, Off Millbrook Road, Millbrook",
    "sg:city":"Southampton",
    "sg:classifiers":[
        {
            "category":"Manufacturing",
            "subcategory":"Rubber & Plastics",
            "type":"Manufacturing & Wholesale Goods"
        }
    ],
    "sg:phone":"+44 23 8077 1004",
    "sg:postcode":"SO15 0JZ",
    "sg:province":"Hampshire",
    "sg:tags":[
        "supplier",
        "stockist"
    ],
    "wof:name":"Mitchells (Plastic Distributors) Ltd.",
    "wof:placetype":"venue"
},
  "geometry": {"coordinates":[-1.4554610252,50.9162559509],"type":"Point"}
}