{
  "type": "Feature",
  "properties": {
    "iso:country":"GB",
    "sg:address":"Waterloo Mills, Cleveland Street",
    "sg:city":"Hull",
    "sg:classifiers":[
        {
            "category":"Shopping",
            "subcategory":"Pets & Pet Supplies",
            "type":"Retail Goods"
        }
    ],
    "sg:phone":"+44 1482 585315",
    "sg:postcode":"HU8 7PN",
    "sg:province":"East Riding of Yorkshire",
    "wof:name":"P & J Feed & Corn Merchants",
    "wof:placetype":"venue"
},
  "geometry": {"coordinates":[-0.3229900002,53.7558403015],"type":"Point"}
}