{
  "type": "Feature",
  "properties": {
    "addr:full":"Headway House Mansfield Road Nottingham Nottinghamshire NG5 3FL",
    "addr:postcode":"ng5 3fl",
    "addr:street":"Mansfield Road",
    "iso:country":"GB",
    "sg:address":"Headway House Mansfield Road",
    "sg:city":"Nottingham",
    "sg:classifiers":[
        {
            "category":"Organizations",
            "subcategory":"Non-profit Organization",
            "type":"Services"
        }
    ],
    "sg:postcode":"NG5 3FL",
    "sg:province":"Nottinghamshire",
    "sg:tags":[
        "organisation",
        "voluntary",
        "charity"
    ],
    "wof:name":"Headway Nottingham Support Group",
    "wof:placetype":"venue"
},
  "geometry": {"coordinates":[-1.139457,52.993134],"type":"Point"}
}