{
  "type": "Feature",
  "properties": {
    "addr:full":"Old Hereford Rd Abergavenny Herefordshire NP7 6EP",
    "addr:postcode":"np7 6ep",
    "addr:street":"Old Hereford Rd",
    "iso:country":"GB",
    "sg:address":"Old Hereford Rd",
    "sg:city":"Abergavenny",
    "sg:classifiers":[
        {
            "category":"Community Center",
            "type":"Public Place"
        },
        {
            "category":"Organizations",
            "subcategory":"Non-profit Organization",
            "type":"Services"
        }
    ],
    "sg:postcode":"NP7 6EP",
    "sg:province":"Herefordshire",
    "sg:tags":[
        "recreation",
        "voluntary",
        "centre",
        "organisation",
        "leisure",
        "charity"
    ],
    "wof:name":"Monmouthshire County Council",
    "wof:placetype":"venue"
},
  "geometry": {"coordinates":[-3.0186059475,51.8297157288],"type":"Point"}
}