{
  "type": "Feature",
  "properties": {
    "addr:full":"East Lancashire Road, Swinton Manchester Greater Manchester M27 0BH",
    "addr:postcode":"m27 0bh",
    "addr:street":"East Lancashire Road",
    "iso:country":"GB",
    "sg:address":"East Lancashire Road, Swinton",
    "sg:city":"Manchester",
    "sg:classifiers":[
        {
            "category":"Education",
            "subcategory":"School",
            "type":"Public Place"
        },
        {
            "category":"Government",
            "subcategory":"Office",
            "type":"Public Place"
        }
    ],
    "sg:phone":"+44 161 794 1045",
    "sg:postcode":"M27 0BH",
    "sg:province":"Greater Manchester",
    "sg:tags":[
        "local",
        "authority"
    ],
    "wof:name":"Moorside County High School",
    "wof:placetype":"venue"
},
  "geometry": {"coordinates":[-2.3532140255,53.5077705383],"type":"Point"}
}