{
  "type": "Feature",
  "properties": {
    "addr:full":"75 Barnard Way Cannock Staffordshire WS11 2XQ",
    "addr:housenumber":"75",
    "addr:postcode":"ws11 2xq",
    "addr:street":"Barnard Way",
    "iso:country":"GB",
    "sg:address":"75 Barnard Way",
    "sg:city":"Cannock",
    "sg:classifiers":[
        {
            "category":"Organizations",
            "subcategory":"Non-profit Organization",
            "type":"Services"
        }
    ],
    "sg:postcode":"WS11 2XQ",
    "sg:province":"Staffordshire",
    "sg:tags":[
        "organisation",
        "voluntary",
        "charity"
    ],
    "wof:name":"Multiple Sclerosis Society of Great Britain & Northern Ireland",
    "wof:placetype":"venue"
},
  "geometry": {"coordinates":[-2.0164289474,52.6959495544],"type":"Point"}
}