{
  "type": "Feature",
  "properties": {
    "addr:full":"19 Silver Arcade Leicester Leicestershire LE1 5FA",
    "addr:housenumber":"19",
    "addr:postcode":"le1 5fa",
    "addr:street":"Silver Arcade",
    "iso:country":"GB",
    "sg:address":"19 Silver Arcade",
    "sg:city":"Leicester",
    "sg:classifiers":[
        {
            "category":"Shopping",
            "subcategory":"Gifts & Souvenirs",
            "type":"Retail Goods"
        }
    ],
    "sg:phone":"+44 116 262 1376",
    "sg:postcode":"LE1 5FA",
    "sg:province":"Leicestershire",
    "sg:tags":[
        "shop"
    ],
    "wof:name":"Groovy Gifts",
    "wof:placetype":"venue"
},
  "geometry": {"coordinates":[-1.1348179579,52.6353874207],"type":"Point"}
}