{
  "type": "Feature",
  "properties": {
    "iso:country":"GB",
    "sg:address":"47 Shambles",
    "sg:city":"York",
    "sg:classifiers":[
        {
            "category":"Shopping",
            "subcategory":"Hobbies, Toys, & Games",
            "type":"Retail Goods"
        }
    ],
    "sg:phone":"+44 1904 654769",
    "sg:postcode":"YO1 7LX",
    "sg:province":"North Yorkshire",
    "sg:tags":[
        "coin",
        "medal"
    ],
    "wof:name":"John Smith",
    "wof:placetype":"venue"
},
  "geometry": {"coordinates":[-1.080361,53.959801],"type":"Point"}
}