{
  "type": "Feature",
  "properties": {
    "addr:full":"6 Scurlock Drive, Honeybourough, Neyland Milford Haven Pembrokeshire SA73 1PJ",
    "addr:housenumber":"6",
    "addr:postcode":"sa73 1pj",
    "addr:street":"Scurlock Drive",
    "iso:country":"GB",
    "sg:address":"6 Scurlock Drive, Honeybourough, Neyland",
    "sg:city":"Milford Haven",
    "sg:classifiers":[
        {
            "category":"Professional",
            "subcategory":"Engineering",
            "type":"Services"
        },
        {
            "category":"Building & Trades",
            "subcategory":"Electrical",
            "type":"Services"
        }
    ],
    "sg:phone":"+44 1646 601900",
    "sg:postcode":"SA73 1PJ",
    "sg:province":"Pembrokeshire",
    "sg:tags":[
        "engineer",
        "electrician",
        "contractor"
    ],
    "wof:name":"D J Electrics",
    "wof:placetype":"venue"
},
  "geometry": {"coordinates":[-4.949875,51.709881],"type":"Point"}
}