{
  "type": "Feature",
  "properties": {
    "addr:full":"3 Tavistock Rd Newcastle Upon Tyne Tyne and Wear NE2 3HY",
    "addr:housenumber":"3",
    "addr:postcode":"ne2 3hy",
    "addr:street":"Tavistock Rd",
    "iso:country":"GB",
    "sg:address":"3 Tavistock Rd",
    "sg:city":"Newcastle Upon Tyne",
    "sg:classifiers":[
        {
            "category":"Health Services",
            "subcategory":"Health Practitioner",
            "type":"Services"
        }
    ],
    "sg:phone":"+44 191 281 8500",
    "sg:postcode":"NE2 3HY",
    "sg:province":"Tyne and Wear",
    "sg:tags":[
        "psychotherapist"
    ],
    "wof:name":"Beckett Ender",
    "wof:placetype":"venue"
},
  "geometry": {"coordinates":[-1.6055409908,54.9954910278],"type":"Point"}
}