{
  "type": "Feature",
  "properties": {
    "addr:full":"Lower Road Trading Estate Ledbury Gloucestershire HR8 2DJ",
    "addr:postcode":"hr8 2dj",
    "addr:street":"Lower Road Trading Estate",
    "iso:country":"GB",
    "sg:address":"Lower Road Trading Estate",
    "sg:city":"Ledbury",
    "sg:classifiers":[
        {
            "category":"Shopping",
            "type":"Retail Goods"
        }
    ],
    "sg:postcode":"HR8 2DJ",
    "sg:province":"Gloucestershire",
    "sg:tags":[
        "merchant"
    ],
    "wof:name":"Leadon Vale (Crop Management) Ltd.",
    "wof:placetype":"venue"
},
  "geometry": {"coordinates":[-2.4351689816,52.0351295471],"type":"Point"}
}