{
  "type": "Feature",
  "properties": {
    "iso:country":"GB",
    "sg:address":"14 Baneswell Road",
    "sg:city":"Newport",
    "sg:classifiers":[
        {
            "category":"Professional",
            "subcategory":"Lawyer & Legal Services",
            "type":"Services"
        }
    ],
    "sg:phone":"+44 1633 843122",
    "sg:postcode":"NP20 4BP",
    "sg:province":"Newport",
    "sg:tags":[
        "solicitor"
    ],
    "wof:name":"Hodson Parsons",
    "wof:placetype":"venue"
},
  "geometry": {"coordinates":[-2.999049,51.587238],"type":"Point"}
}