{
  "type": "Feature",
  "properties": {
    "iso:country":"GB",
    "sg:address":"2 Academy St",
    "sg:city":"Dumfries",
    "sg:classifiers":[
        {
            "category":"Professional",
            "subcategory":"Accounting & Tax Preparation",
            "type":"Services"
        }
    ],
    "sg:phone":"+44 1387 254944",
    "sg:postcode":"DG1 1BY",
    "sg:province":"Dumfries and Galloway",
    "sg:tags":[
        "accountant"
    ],
    "wof:name":"Armstrong Watson & Co",
    "wof:placetype":"venue"
},
  "geometry": {"coordinates":[-3.61152,55.07103],"type":"Point"}
}