{
  "type": "Feature",
  "properties": {
    "iso:country":"GB",
    "sg:address":"Eastholme, Newsham",
    "sg:city":"Richmond",
    "sg:classifiers":[
        {
            "category":"Retail",
            "subcategory":"Auto Repair",
            "type":"Services"
        }
    ],
    "sg:phone":"+44 1833 621500",
    "sg:postcode":"DL11 7RD",
    "sg:province":"Durham",
    "sg:tags":[
        "body",
        "car"
    ],
    "wof:name":"Eastholme Commercials",
    "wof:placetype":"venue"
},
  "geometry": {"coordinates":[-1.8392169476,54.4855041504],"type":"Point"}
}