{
  "type": "Feature",
  "properties": {
    "addr:full":"58a Beaumont Drive Northampton Northamptonshire NN3 8PS",
    "addr:housenumber":"58a",
    "addr:postcode":"nn3 8ps",
    "addr:street":"Beaumont Drive",
    "iso:country":"GB",
    "sg:address":"58a Beaumont Drive",
    "sg:city":"Northampton",
    "sg:classifiers":[
        {
            "category":"Building & Trades",
            "subcategory":"Cleaning & Sanitation",
            "type":"Services"
        }
    ],
    "sg:postcode":"NN3 8PS",
    "sg:province":"Northamptonshire",
    "sg:tags":[
        "cleaner",
        "window"
    ],
    "wof:name":"E J Treacher & Son",
    "wof:placetype":"venue"
},
  "geometry": {"coordinates":[-0.8129339814,52.2623596191],"type":"Point"}
}