{
  "type": "Feature",
  "properties": {
    "addr:full":"Tredinnick Farm, Tregony Truro Cornwall TR2 5TQ",
    "addr:postcode":"tr2 5tq",
    "addr:street":"Tregony",
    "iso:country":"GB",
    "sg:address":"Tredinnick Farm, Tregony",
    "sg:city":"Truro",
    "sg:classifiers":[
        {
            "category":"Farming",
            "subcategory":"Dairy Farm",
            "type":"Manufacturing & Wholesale Goods"
        }
    ],
    "sg:postcode":"TR2 5TQ",
    "sg:province":"Cornwall",
    "wof:name":"M & M A Thomas & Son",
    "wof:placetype":"venue"
},
  "geometry": {"coordinates":[-4.9126501083,50.2677154541],"type":"Point"}
}