{
  "type": "Feature",
  "properties": {
    "iso:country":"GB",
    "sg:address":"11 Scotland Street",
    "sg:city":"Glasgow",
    "sg:classifiers":[
        {
            "category":"Home & Garden",
            "subcategory":"Home Furnishings",
            "type":"Retail Goods"
        },
        {
            "category":"Home & Garden",
            "subcategory":"Carpets & Floor Coverings",
            "type":"Retail Goods"
        }
    ],
    "sg:phone":"+44 141 429 3388",
    "sg:postcode":"G5 8NB",
    "sg:province":"Glasgow City",
    "sg:tags":[
        "furnishers",
        "planner",
        "bedroom"
    ],
    "wof:name":"Macdonald Bedrooms By Design",
    "wof:placetype":"venue"
},
  "geometry": {"coordinates":[-4.2673430443,55.8497238159],"type":"Point"}
}