{
  "type": "Feature",
  "properties": {
    "addr:full":"26 Faygate Ct, Hemlington Middlesbrough North Yorkshire TS8 9LG",
    "addr:housenumber":"26",
    "addr:postcode":"ts8 9lg",
    "addr:street":"Faygate Ct Hemlington",
    "iso:country":"GB",
    "sg:address":"26 Faygate Ct, Hemlington",
    "sg:city":"Middlesbrough",
    "sg:classifiers":[
        {
            "category":"Real Estate",
            "subcategory":"Real Estate Agent",
            "type":"Services"
        }
    ],
    "sg:postcode":"TS8 9LG",
    "sg:province":"North Yorkshire",
    "wof:name":"Faygate Sheltered Housing",
    "wof:placetype":"venue"
},
  "geometry": {"coordinates":[-1.245784,54.519753],"type":"Point"}
}