{
  "type": "Feature",
  "properties": {
    "addr:full":"Wad House, Nottingham Lane, Old Dalby Melton Mowbray Leicestershire LE14 3LX",
    "addr:postcode":"le14 3lx",
    "addr:street":"Nottingham Lane",
    "iso:country":"GB",
    "sg:address":"Wad House, Nottingham Lane, Old Dalby",
    "sg:city":"Melton Mowbray",
    "sg:classifiers":[
        {
            "category":"Farming",
            "subcategory":"Livestock Farm",
            "type":"Manufacturing & Wholesale Goods"
        }
    ],
    "sg:postcode":"LE14 3LX",
    "sg:province":"Leicestershire",
    "sg:tags":[
        "others"
    ],
    "wof:name":"Alfred J Greaves",
    "wof:placetype":"venue"
},
  "geometry": {"coordinates":[-1.0193259716,52.8132209778],"type":"Point"}
}