{
  "type": "Feature",
  "properties": {
    "addr:full":"Unit 20 London Greater London W3 6UU",
    "addr:housenumber":"unit 20",
    "addr:postcode":"w3 6uu",
    "iso:country":"GB",
    "sg:address":"Unit 20",
    "sg:city":"London",
    "sg:classifiers":[
        {
            "category":"Food & Beverages",
            "subcategory":"Supermarket",
            "type":"Retail Goods"
        }
    ],
    "sg:phone":"+44 20 8993 1289",
    "sg:postcode":"W3 6UU",
    "sg:province":"Greater London",
    "sg:tags":[
        "frozen"
    ],
    "wof:name":"Tastees",
    "wof:placetype":"venue"
},
  "geometry": {"coordinates":[-0.2615889907,51.5179290771],"type":"Point"}
}