{
  "type": "Feature",
  "properties": {
    "addr:full":"7 High Street, Minchinhampton Stroud Gloucestershire GL6 9BN",
    "addr:housenumber":"7",
    "addr:postcode":"gl6 9bn",
    "addr:street":"High Street",
    "iso:country":"GB",
    "sg:address":"7 High Street, Minchinhampton",
    "sg:city":"Stroud",
    "sg:classifiers":[
        {
            "category":"Restaurant",
            "type":"Food & Drink"
        }
    ],
    "sg:postcode":"GL6 9BN",
    "sg:province":"Gloucestershire",
    "wof:name":"The Coffee Bean",
    "wof:placetype":"venue"
},
  "geometry": {"coordinates":[-2.1867060661,51.7051544189],"type":"Point"}
}