{
  "type": "Feature",
  "properties": {
    "addr:full":"Vahalla 7 South Acre, Oakenshaw Crook Durham DL15 0SZ",
    "addr:housenumber":"7",
    "addr:postcode":"dl15 0sz",
    "addr:street":"Vahalla;South Acre Oakenshaw",
    "iso:country":"GB",
    "sg:address":"Vahalla 7 South Acre, Oakenshaw",
    "sg:city":"Crook",
    "sg:classifiers":[
        {
            "category":"Building & Trades",
            "subcategory":"Construction",
            "type":"Services"
        }
    ],
    "sg:phone":"+44 1388 745446",
    "sg:postcode":"DL15 0SZ",
    "sg:province":"Durham",
    "sg:tags":[
        "builder"
    ],
    "wof:name":"Keith Hardman Property Maintanance",
    "wof:placetype":"venue"
},
  "geometry": {"coordinates":[-1.687004,54.726036],"type":"Point"}
}