{
  "type": "Feature",
  "properties": {
    "addr:full":"Metropolitan Buldings, 25 High Street Llangefni Gwynedd LL77 7NA",
    "addr:housenumber":"25",
    "addr:postcode":"ll77 7na",
    "addr:street":"High Street",
    "iso:country":"GB",
    "sg:address":"Metropolitan Buldings, 25 High Street",
    "sg:city":"Llangefni",
    "sg:classifiers":[
        {
            "category":"Health Services",
            "subcategory":"Optometrist",
            "type":"Services"
        },
        {
            "category":"Shopping",
            "subcategory":"Optician",
            "type":"Retail Goods"
        }
    ],
    "sg:phone":"+44 1248 724373",
    "sg:postcode":"LL77 7NA",
    "sg:province":"Gwynedd",
    "sg:tags":[
        "ophthalmic"
    ],
    "wof:name":"Allport Opthalmic Opticians",
    "wof:placetype":"venue"
},
  "geometry": {"coordinates":[-4.3084640503,53.2556037903],"type":"Point"}
}