{
  "type": "Feature",
  "properties": {
    "iso:country":"GB",
    "sg:address":"The Leeds Wall, 100a Gelderd Road",
    "sg:city":"Leeds",
    "sg:classifiers":[
        {
            "category":"Community Center",
            "type":"Public Place"
        }
    ],
    "sg:phone":"+44 113 234 1554",
    "sg:postcode":"LS12 6BY",
    "sg:province":"West Yorkshire",
    "sg:tags":[
        "recreation",
        "leisure",
        "centre"
    ],
    "wof:name":"Star Walls Ltd.",
    "wof:placetype":"venue"
},
  "geometry": {"coordinates":[-1.546587,53.794495],"type":"Point"}
}