{
  "type": "Feature",
  "properties": {
    "addr:full":"Surgery, Patwell La Bruton Somerset BA10 0EG",
    "addr:postcode":"ba10 0eg",
    "addr:street":"La",
    "iso:country":"GB",
    "sg:address":"Surgery, Patwell La",
    "sg:city":"Bruton",
    "sg:classifiers":[
        {
            "category":"Health Services",
            "subcategory":"Doctor",
            "type":"Services"
        }
    ],
    "sg:phone":"+44 1749 812310",
    "sg:postcode":"BA10 0EG",
    "sg:province":"Somerset",
    "sg:tags":[
        "practitioners"
    ],
    "wof:name":"Hawkins, A",
    "wof:placetype":"venue"
},
  "geometry": {"coordinates":[-2.452069,51.112202],"type":"Point"}
}