{
  "type": "Feature",
  "properties": {
    "iso:country":"GB",
    "sg:address":"Dulwich Road, Brockwell Park, Herne Hill",
    "sg:city":"London",
    "sg:classifiers":[
        {
            "category":"Sports & Exercise",
            "subcategory":"Swimming Pool",
            "type":"Entertainment"
        }
    ],
    "sg:phone":"+44 20 7274 3088",
    "sg:postcode":"SE24 0PA",
    "sg:province":"Greater London",
    "wof:name":"Brockwell Lido Ltd.",
    "wof:placetype":"venue"
},
  "geometry": {"coordinates":[-0.10729,51.45385],"type":"Point"}
}