{
  "type": "Feature",
  "properties": {
    "addr:full":"Church Farm, 6 Back Lane, Yeadon Leeds West Yorkshire LS19 7SQ",
    "addr:housenumber":"6",
    "addr:postcode":"ls19 7sq",
    "addr:street":"Back Lane",
    "iso:country":"GB",
    "sg:address":"Church Farm, 6 Back Lane, Yeadon",
    "sg:city":"Leeds",
    "sg:classifiers":[
        {
            "category":"Manufacturing",
            "subcategory":"Wood Products",
            "type":"Manufacturing & Wholesale Goods"
        },
        {
            "category":"Manufacturing",
            "subcategory":"Building Materials",
            "type":"Manufacturing & Wholesale Goods"
        }
    ],
    "sg:phone":"+44 113 250 2738",
    "sg:postcode":"LS19 7SQ",
    "sg:province":"West Yorkshire",
    "sg:tags":[
        "mnfr",
        "maker",
        "cabinet"
    ],
    "wof:name":"Philip J Dobbins",
    "wof:placetype":"venue"
},
  "geometry": {"coordinates":[-1.665596,53.884689],"type":"Point"}
}