{
  "type": "Feature",
  "properties": {
    "iso:country":"GB",
    "sg:address":"12 Tanhouse, Orton Malborne",
    "sg:city":"Peterborough",
    "sg:classifiers":[
        {
            "category":"Home & Garden",
            "subcategory":"Carpets & Floor Coverings",
            "type":"Retail Goods"
        }
    ],
    "sg:postcode":"PE2 5NA",
    "sg:province":"Cambridgeshire",
    "sg:tags":[
        "carpets",
        "rug",
        "matting"
    ],
    "wof:name":"Expert Carpet Fitting",
    "wof:placetype":"venue"
},
  "geometry": {"coordinates":[-0.272681,52.550983],"type":"Point"}
}