{
  "type": "Feature",
  "properties": {
    "iso:country":"GB",
    "sg:address":"60 Calverley Road",
    "sg:city":"Tunbridge Wells",
    "sg:classifiers":[
        {
            "category":"Shopping",
            "subcategory":"Comic Books",
            "type":"Retail Goods"
        }
    ],
    "sg:phone":"+44 1892 526500",
    "sg:postcode":"TN1 2TD",
    "sg:province":"Kent",
    "sg:tags":[
        "jeweller"
    ],
    "wof:name":"H Samuel",
    "wof:placetype":"venue"
},
  "geometry": {"coordinates":[0.268371,51.132717],"type":"Point"}
}