{
  "type": "Feature",
  "properties": {
    "addr:full":"60 Calverley Road Tunbridge Wells Kent TN1 2TD",
    "addr:housenumber":"60",
    "addr:postcode":"tn1 2td",
    "addr:street":"Calverley Road",
    "iso:country":"GB",
    "sg:address":"60 Calverley Road",
    "sg:city":"Tunbridge Wells",
    "sg:classifiers":[
        {
            "category":"Shopping",
            "subcategory":"Comic Books",
            "type":"Retail Goods"
        }
    ],
    "sg:phone":"+44 1892 526500",
    "sg:postcode":"TN1 2TD",
    "sg:province":"Kent",
    "sg:tags":[
        "jeweller"
    ],
    "wof:name":"H Samuel",
    "wof:placetype":"venue"
},
  "geometry": {"coordinates":[0.268371,51.132717],"type":"Point"}
}