{
  "type": "Feature",
  "properties": {
    "iso:country":"GB",
    "sg:address":"Keepers Cottage, Bighton",
    "sg:city":"Alresford",
    "sg:classifiers":[
        {
            "category":"Recreation",
            "type":"Entertainment"
        }
    ],
    "sg:phone":"+44 1962 733378",
    "sg:postcode":"SO24 9SE",
    "sg:province":"Hampshire",
    "sg:tags":[
        "outdoor",
        "pursuit"
    ],
    "wof:name":"Hawkeye Sporting Agency",
    "wof:placetype":"venue"
},
  "geometry": {"coordinates":[-1.12527,51.104385],"type":"Point"}
}