{
  "type": "Feature",
  "properties": {
    "addr:full":"19 Claude Road, Chorlton Cum-hardy Manchester Cheshire M21 8BZ",
    "addr:housenumber":"19",
    "addr:postcode":"m21 8bz",
    "addr:street":"Claude Road",
    "iso:country":"GB",
    "sg:address":"19 Claude Road, Chorlton Cum-hardy",
    "sg:city":"Manchester",
    "sg:classifiers":[
        {
            "category":"Professional",
            "subcategory":"Engineering",
            "type":"Services"
        },
        {
            "category":"Building & Trades",
            "subcategory":"Electrical",
            "type":"Services"
        }
    ],
    "sg:phone":"+44 161 860 5589",
    "sg:postcode":"M21 8BZ",
    "sg:province":"Cheshire",
    "sg:tags":[
        "engineer",
        "electrician",
        "contractor"
    ],
    "wof:name":"Sher & Sons Ltd.",
    "wof:placetype":"venue"
},
  "geometry": {"coordinates":[-2.274596,53.436489],"type":"Point"}
}