{
  "type": "Feature",
  "properties": {
    "iso:country":"GB",
    "sg:address":"37 East St",
    "sg:city":"Blandford Forum",
    "sg:classifiers":[
        {
            "category":"Shopping",
            "subcategory":"Thrift Store",
            "type":"Retail Goods"
        }
    ],
    "sg:phone":"+44 1258 453077",
    "sg:postcode":"DT11 7DU",
    "sg:province":"Dorset",
    "sg:tags":[
        "shop",
        "charity"
    ],
    "wof:name":"Sue Ryder Foundation",
    "wof:placetype":"venue"
},
  "geometry": {"coordinates":[-2.162156105,50.8562812805],"type":"Point"}
}