{
  "type": "Feature",
  "properties": {
    "addr:full":"66 West Street Gravesend Kent DA11 0BE",
    "addr:housenumber":"66",
    "addr:postcode":"da11 0be",
    "addr:street":"West Street",
    "iso:country":"GB",
    "sg:address":"66 West Street",
    "sg:city":"Gravesend",
    "sg:classifiers":[
        {
            "category":"Restaurant",
            "type":"Food & Drink"
        }
    ],
    "sg:phone":"+44 1474 536066",
    "sg:postcode":"DA11 0BE",
    "sg:province":"Kent",
    "sg:tags":[
        "indian"
    ],
    "wof:name":"Gandhi Balti House",
    "wof:placetype":"venue"
},
  "geometry": {"coordinates":[0.3691309988,51.4449653625],"type":"Point"}
}