{
  "type": "Feature",
  "properties": {
    "iso:country":"GB",
    "sg:address":"152 Evington Road",
    "sg:city":"Leicester",
    "sg:classifiers":[
        {
            "category":"Shopping",
            "subcategory":"Optician",
            "type":"Retail Goods"
        }
    ],
    "sg:phone":"+44 116 273 0111",
    "sg:postcode":"LE2 1HL",
    "sg:province":"Leicestershire",
    "sg:tags":[
        "dispensing"
    ],
    "wof:name":"H B Vyas Opticians",
    "wof:placetype":"venue"
},
  "geometry": {"coordinates":[-1.108503,52.62561],"type":"Point"}
}