{
  "type": "Feature",
  "properties": {
    "addr:full":"Lysnoweth, Infirmary Hill Truro Cornwall TR1 2JD",
    "addr:postcode":"tr1 2jd",
    "addr:street":"Lysnoweth Infirmary Hill",
    "iso:country":"GB",
    "sg:address":"Lysnoweth, Infirmary Hill",
    "sg:city":"Truro",
    "sg:classifiers":[
        {
            "category":"Government",
            "subcategory":"Office",
            "type":"Public Place"
        }
    ],
    "sg:phone":"+44 1872 245300",
    "sg:postcode":"TR1 2JD",
    "sg:province":"Cornwall",
    "sg:tags":[
        "inland",
        "revenue"
    ],
    "wof:name":"Inland Revenue",
    "wof:placetype":"venue"
},
  "geometry": {"coordinates":[-5.0536308289,50.2652397156],"type":"Point"}
}