{
  "type": "Feature",
  "properties": {
    "addr:full":"Ham La, Kingswinford Brierley Hill Staffordshire DY6 7JU",
    "addr:postcode":"dy6 7ju",
    "addr:street":"Ham",
    "iso:country":"GB",
    "sg:address":"Ham La, Kingswinford",
    "sg:city":"Brierley Hill",
    "sg:classifiers":[
        {
            "category":"Professional",
            "subcategory":"Lawyer & Legal Services",
            "type":"Services"
        }
    ],
    "sg:postcode":"DY6 7JU",
    "sg:province":"Staffordshire",
    "sg:tags":[
        "patent",
        "agent"
    ],
    "wof:name":"Birmingham City Council",
    "wof:placetype":"venue"
},
  "geometry": {"coordinates":[-2.162345,52.511177],"type":"Point"}
}