{
  "type": "Feature",
  "properties": {
    "addr:full":"Unit 5,3-4 Wells Terr London Greater London N4 3JU",
    "addr:housenumber":"5,3 -4",
    "addr:postcode":"n4 3ju",
    "iso:country":"GB",
    "sg:address":"Unit 5,3-4 Wells Terr",
    "sg:city":"London",
    "sg:classifiers":[
        {
            "category":"Personal",
            "type":"Services"
        }
    ],
    "sg:postcode":"N4 3JU",
    "sg:province":"Greater London",
    "sg:tags":[
        "dressmaker"
    ],
    "wof:name":"Zack,John,Ltd",
    "wof:placetype":"venue"
},
  "geometry": {"coordinates":[-0.1089269966,51.5648651123],"type":"Point"}
}