{
  "type": "Feature",
  "properties": {
    "addr:full":"17 Barnton Street Stirling Stirling FK8 1HF",
    "addr:housenumber":"17",
    "addr:postcode":"fk8 1hf",
    "addr:street":"Barnton Street",
    "iso:country":"GB",
    "sg:address":"17 Barnton Street",
    "sg:city":"Stirling",
    "sg:classifiers":[
        {
            "category":"Restaurant",
            "type":"Food & Drink"
        }
    ],
    "sg:phone":"+44 1786 462809",
    "sg:postcode":"FK8 1HF",
    "sg:province":"Stirling",
    "sg:tags":[
        "-",
        "mexican"
    ],
    "wof:name":"Smiling Jack's",
    "wof:placetype":"venue"
},
  "geometry": {"coordinates":[-3.93832,56.120148],"type":"Point"}
}