{
  "type": "Feature",
  "properties": {
    "addr:full":"Raglan Chambers, 63 Frogmore Street Abergavenny Herefordshire NP7 5AU",
    "addr:housenumber":"63",
    "addr:postcode":"np7 5au",
    "addr:street":"Frogmore Street",
    "iso:country":"GB",
    "sg:address":"Raglan Chambers, 63 Frogmore Street",
    "sg:city":"Abergavenny",
    "sg:classifiers":[
        {
            "category":"Organizations",
            "subcategory":"Non-profit Organization",
            "type":"Services"
        }
    ],
    "sg:phone":"+44 1873 303000",
    "sg:postcode":"NP7 5AU",
    "sg:province":"Herefordshire",
    "sg:tags":[
        "organisation",
        "voluntary",
        "charity"
    ],
    "wof:name":"Marie Curie Cancer Care",
    "wof:placetype":"venue"
},
  "geometry": {"coordinates":[-3.02068,51.825008],"type":"Point"}
}