{
  "type": "Feature",
  "properties": {
    "addr:full":"10 Little Lever Street Manchester Greater Manchester M1 1HR",
    "addr:housenumber":"10",
    "addr:postcode":"m1 1hr",
    "addr:street":"Little Lever Street",
    "iso:country":"GB",
    "sg:address":"10 Little Lever Street",
    "sg:city":"Manchester",
    "sg:classifiers":[
        {
            "category":"Professional",
            "subcategory":"Computer Services",
            "type":"Services"
        }
    ],
    "sg:phone":"+44 161 907 8406",
    "sg:postcode":"M1 1HR",
    "sg:province":"Greater Manchester",
    "sg:tags":[
        "development",
        "system",
        "software"
    ],
    "wof:name":"Unified Technology Ltd.",
    "wof:placetype":"venue"
},
  "geometry": {"coordinates":[-2.23336,53.482117],"type":"Point"}
}