{
  "type": "Feature",
  "properties": {
    "addr:full":"4 Pond Wood Close, Moulton Park Industrial Estate Northampton Northamptonshire NN3 6RT",
    "addr:housenumber":"4;estate",
    "addr:postcode":"nn3 6rt",
    "addr:street":"Pond Wood Close;Park Industrial",
    "iso:country":"GB",
    "sg:address":"4 Pond Wood Close, Moulton Park Industrial Estate",
    "sg:city":"Northampton",
    "sg:classifiers":[
        {
            "category":"Manufacturing",
            "subcategory":"Apparel",
            "type":"Manufacturing & Wholesale Goods"
        }
    ],
    "sg:phone":"+44 1604 644961",
    "sg:postcode":"NN3 6RT",
    "sg:province":"Northamptonshire",
    "sg:tags":[
        "mnfr",
        "footwear"
    ],
    "wof:name":"Spring Line Ltd.",
    "wof:placetype":"venue"
},
  "geometry": {"coordinates":[-0.872449,52.277611],"type":"Point"}
}