{
  "type": "Feature",
  "properties": {
    "iso:country":"GB",
    "sg:address":"83 Lord St",
    "sg:city":"Fleetwood",
    "sg:classifiers":[
        {
            "category":"Shopping",
            "subcategory":"Discount & Variety Stores",
            "type":"Retail Goods"
        }
    ],
    "sg:phone":"+44 1253 776969",
    "sg:postcode":"FY7 6DS",
    "sg:province":"Lancashire",
    "sg:tags":[
        "centre"
    ],
    "wof:name":"Quids In",
    "wof:placetype":"venue"
},
  "geometry": {"coordinates":[-3.011737,53.922424],"type":"Point"}
}