{
  "type": "Feature",
  "properties": {
    "addr:full":"Unit 19 Enterprise House, Dalziel Street Motherwell North Lanarkshire ML1 1PJ",
    "addr:housenumber":"unit 19",
    "addr:postcode":"ml1 1pj",
    "addr:street":"Enterprise;Dalziel Street",
    "iso:country":"GB",
    "sg:address":"Unit 19 Enterprise House, Dalziel Street",
    "sg:city":"Motherwell",
    "sg:classifiers":[
        {
            "category":"Wholesale",
            "subcategory":"Construction Materials",
            "type":"Manufacturing & Wholesale Goods"
        },
        {
            "category":"Manufacturing",
            "subcategory":"Building Materials",
            "type":"Manufacturing & Wholesale Goods"
        }
    ],
    "sg:phone":"+44 1698 307265",
    "sg:postcode":"ML1 1PJ",
    "sg:province":"North Lanarkshire",
    "sg:tags":[
        "tarmac",
        "macadam",
        "laying",
        "asphalt",
        "contractor"
    ],
    "wof:name":"Macways McAdam",
    "wof:placetype":"venue"
},
  "geometry": {"coordinates":[-3.987326,55.792744],"type":"Point"}
}