{
  "type": "Feature",
  "properties": {
    "iso:country":"GB",
    "sg:address":"Wellington Drive",
    "sg:city":"Rugeley",
    "sg:classifiers":[
        {
            "category":"Organizations",
            "subcategory":"Membership Organization",
            "type":"Services"
        }
    ],
    "sg:postcode":"WS15 2JX",
    "sg:province":"Staffordshire",
    "sg:tags":[
        "club"
    ],
    "wof:name":"Police Boys Boxing Club",
    "wof:placetype":"venue"
},
  "geometry": {"coordinates":[-1.934936,52.758308],"type":"Point"}
}