{
  "type": "Feature",
  "properties": {
    "addr:full":"Glenny House, 56 Longbridge Road Barking Essex IG11 8RW",
    "addr:housenumber":"56",
    "addr:postcode":"ig11 8rw",
    "addr:street":"Longbridge Road",
    "iso:country":"GB",
    "sg:address":"Glenny House, 56 Longbridge Road",
    "sg:city":"Barking",
    "sg:classifiers":[
        {
            "category":"Real Estate",
            "subcategory":"Real Estate Agent",
            "type":"Services"
        }
    ],
    "sg:phone":"+44 20 8591 6671",
    "sg:postcode":"IG11 8RW",
    "sg:province":"Essex",
    "wof:name":"Glenny Personnel Ltd.",
    "wof:placetype":"venue"
},
  "geometry": {"coordinates":[0.082597,51.540092],"type":"Point"}
}