{
  "type": "Feature",
  "properties": {
    "iso:country":"GB",
    "sg:address":"2b Front Street, Fencehouses",
    "sg:city":"Houghton-le-spring",
    "sg:classifiers":[
        {
            "category":"Fast Food",
            "type":"Food & Drink"
        }
    ],
    "sg:phone":"+44 191 385 9877",
    "sg:postcode":"DH4 7DX",
    "sg:province":"Durham",
    "sg:tags":[
        "away",
        "take"
    ],
    "wof:name":"Fencehouses Tandoori",
    "wof:placetype":"venue"
},
  "geometry": {"coordinates":[-1.49461,54.86837],"type":"Point"}
}