{
  "type": "Feature",
  "properties": {
    "iso:country":"GB",
    "sg:address":"Unit 15b Barrowmore Trading Estate, Great Barrow",
    "sg:city":"Chester",
    "sg:classifiers":[
        {
            "category":"Manufacturing",
            "subcategory":"Signs",
            "type":"Manufacturing & Wholesale Goods"
        }
    ],
    "sg:phone":"+44 1829 741641",
    "sg:postcode":"CH3 7JA",
    "sg:province":"Cheshire",
    "sg:tags":[
        "nameplate"
    ],
    "wof:name":"Cestrian Signs Ltd.",
    "wof:placetype":"venue"
},
  "geometry": {"coordinates":[-2.794738,53.211887],"type":"Point"}
}