{
  "type": "Feature",
  "properties": {
    "iso:country":"GB",
    "sg:address":"Unit 13, Bladen Street Industrial Estate",
    "sg:city":"Jarrow",
    "sg:classifiers":[
        {
            "category":"Building & Trades",
            "subcategory":"Cleaning & Sanitation",
            "type":"Services"
        },
        {
            "category":"Building & Trades",
            "subcategory":"Construction",
            "type":"Services"
        }
    ],
    "sg:phone":"+44 191 428 0222",
    "sg:postcode":"NE32 3HN",
    "sg:province":"Tyne and Wear",
    "sg:tags":[
        "blast",
        "decorator",
        "painter"
    ],
    "wof:name":"Nor-Clean Ltd.",
    "wof:placetype":"venue"
},
  "geometry": {"coordinates":[-1.49722,54.98214],"type":"Point"}
}