{
  "type": "Feature",
  "properties": {
    "iso:country":"GB",
    "sg:address":"23 Elmers End Road",
    "sg:city":"London",
    "sg:classifiers":[
        {
            "category":"Social Services",
            "subcategory":"Retirement Home",
            "type":"Services"
        }
    ],
    "sg:postcode":"SE20 7ST",
    "sg:province":"Greater London",
    "sg:tags":[
        "residential",
        "care"
    ],
    "wof:name":"Bromley Cheshire Home",
    "wof:placetype":"venue"
},
  "geometry": {"coordinates":[-0.0582440011,51.4071884155],"type":"Point"}
}