{
  "type": "Feature",
  "properties": {
    "iso:country":"GB",
    "sg:address":"The Vineyard, Mill Hill East",
    "sg:city":"London",
    "sg:classifiers":[
        {
            "category":"Professional",
            "subcategory":"Advertising",
            "type":"Services"
        }
    ],
    "sg:postcode":"NW7 1HR",
    "sg:province":"Greater London",
    "sg:tags":[
        "mail",
        "direct"
    ],
    "wof:name":"O'Doffin,Deborah,",
    "wof:placetype":"venue"
},
  "geometry": {"coordinates":[-0.20932,51.605511],"type":"Point"}
}