{
  "type": "Feature",
  "properties": {
    "iso:country":"GB",
    "sg:address":"125 Pinner Road",
    "sg:city":"Watford",
    "sg:classifiers":[
        {
            "category":"Home & Garden",
            "subcategory":"Home Furnishings",
            "type":"Retail Goods"
        }
    ],
    "sg:postcode":"WD19 4EJ",
    "sg:province":"Hertfordshire",
    "sg:tags":[
        "mantelpiece",
        "fireplace"
    ],
    "wof:name":"Grate Ideas",
    "wof:placetype":"venue"
},
  "geometry": {"coordinates":[-0.382126,51.64222],"type":"Point"}
}