{
  "type": "Feature",
  "properties": {
    "addr:full":"Old Bridge Street Truro Cornwall TR1 2AQ",
    "addr:postcode":"tr1 2aq",
    "addr:street":"Old Bridge Street",
    "iso:country":"GB",
    "sg:address":"Old Bridge Street",
    "sg:city":"Truro",
    "sg:classifiers":[
        {
            "category":"Bars & Pubs",
            "type":"Food & Drink"
        }
    ],
    "sg:phone":"+44 1872 242383",
    "sg:postcode":"TR1 2AQ",
    "sg:province":"Cornwall",
    "sg:tags":[
        "pubs",
        "inn"
    ],
    "wof:name":"Greenalls Management Ltd.",
    "wof:placetype":"venue"
},
  "geometry": {"coordinates":[-5.050106,50.264263],"type":"Point"}
}