{
  "type": "Feature",
  "properties": {
    "addr:full":"Flat 18 28a Seymour Place London Greater London W1H 7NW",
    "addr:housenumber":"flat 18 28a",
    "addr:postcode":"w1h 7nw",
    "addr:street":"Seymour Place",
    "iso:country":"GB",
    "sg:address":"Flat 18 28a Seymour Place",
    "sg:city":"London",
    "sg:classifiers":[
        {
            "category":"Banks & Credit Unions",
            "subcategory":"Bank",
            "type":"Services"
        }
    ],
    "sg:postcode":"W1H 7NW",
    "sg:province":"Greater London",
    "wof:name":"First Union Finance Ltd",
    "wof:placetype":"venue"
},
  "geometry": {"coordinates":[-0.16132,51.515491],"type":"Point"}
}