{
  "type": "Feature",
  "properties": {
    "addr:full":"144 Hunters Hall Road Dagenham Essex RM10 8HU",
    "addr:housenumber":"144",
    "addr:postcode":"rm10 8hu",
    "addr:street":"Hunters Hall Road",
    "iso:country":"GB",
    "sg:address":"144 Hunters Hall Road",
    "sg:city":"Dagenham",
    "sg:classifiers":[
        {
            "category":"Building & Trades",
            "subcategory":"Construction",
            "type":"Services"
        }
    ],
    "sg:postcode":"RM10 8HU",
    "sg:province":"Essex",
    "sg:tags":[
        "dry",
        "lining",
        "plasterers",
        "screeders"
    ],
    "wof:name":"B J Nunn",
    "wof:placetype":"venue"
},
  "geometry": {"coordinates":[0.1546120048,51.5483360291],"type":"Point"}
}