{
  "type": "Feature",
  "properties": {
    "addr:full":"Bennett Street, Ardwick Manchester Greater Manchester M12 5AB",
    "addr:postcode":"m12 5ab",
    "addr:street":"Bennett Street",
    "iso:country":"GB",
    "sg:address":"Bennett Street, Ardwick",
    "sg:city":"Manchester",
    "sg:classifiers":[
        {
            "category":"Shopping",
            "subcategory":"Stationery & Office Supplies",
            "type":"Retail Goods"
        }
    ],
    "sg:phone":"+44 161 272 6041",
    "sg:postcode":"M12 5AB",
    "sg:province":"Greater Manchester",
    "sg:tags":[
        "equipment",
        "school"
    ],
    "wof:name":"City Supplies Organisation",
    "wof:placetype":"venue"
},
  "geometry": {"coordinates":[-2.204334,53.469574],"type":"Point"}
}