{
  "type": "Feature",
  "properties": {
    "addr:full":"Unit 6a Great Tong Farm, Great Tong, Headcorn Ashford Kent TN27 9PP",
    "addr:housenumber":"unit 6a;headcorn",
    "addr:postcode":"tn27 9pp",
    "addr:street":"Great Tong;Great",
    "iso:country":"GB",
    "sg:address":"Unit 6a Great Tong Farm, Great Tong, Headcorn",
    "sg:city":"Ashford",
    "sg:classifiers":[
        {
            "category":"Building & Trades",
            "subcategory":"Construction",
            "type":"Services"
        }
    ],
    "sg:phone":"+44 1622 891501",
    "sg:postcode":"TN27 9PP",
    "sg:province":"Kent",
    "sg:tags":[
        "glazier"
    ],
    "wof:name":"Acorn Glass",
    "wof:placetype":"venue"
},
  "geometry": {"coordinates":[0.6309300065,51.1669006348],"type":"Point"}
}