{
  "type": "Feature",
  "properties": {
    "addr:full":"21 Almondvale Centre Livingston West Lothian EH54 6NB",
    "addr:housenumber":"21",
    "addr:postcode":"eh54 6nb",
    "addr:street":"Almondvale Centre",
    "iso:country":"GB",
    "sg:address":"21 Almondvale Centre",
    "sg:city":"Livingston",
    "sg:classifiers":[
        {
            "category":"Home & Garden",
            "subcategory":"Home Furnishings",
            "type":"Retail Goods"
        }
    ],
    "sg:phone":"+44 1506 435481",
    "sg:postcode":"EH54 6NB",
    "sg:province":"West Lothian",
    "sg:tags":[
        "furnishers",
        "planner",
        "kitchen"
    ],
    "wof:name":"Moben Kitchens",
    "wof:placetype":"venue"
},
  "geometry": {"coordinates":[-3.5098340511,55.8862457275],"type":"Point"}
}