{
  "type": "Feature",
  "properties": {
    "addr:full":"P O Box 54 Plymouth Devon PL3 4XU",
    "addr:housenumber":"box 54",
    "addr:postcode":"pl3 4xu",
    "addr:street":"P O",
    "iso:country":"GB",
    "sg:address":"P O Box 54",
    "sg:city":"Plymouth",
    "sg:classifiers":[
        {
            "category":"Professional",
            "type":"Services"
        }
    ],
    "sg:phone":"+44 1752 262200",
    "sg:postcode":"PL3 4XU",
    "sg:province":"Devon",
    "sg:tags":[
        "entertainer"
    ],
    "wof:name":"The Moonlight Agency",
    "wof:placetype":"venue"
},
  "geometry": {"coordinates":[-4.1391592026,50.3857307434],"type":"Point"}
}