{
  "type": "Feature",
  "properties": {
    "iso:country":"GB",
    "sg:address":"Beere Manor Farm, Cannington",
    "sg:city":"Bridgwater",
    "sg:classifiers":[
        {
            "category":"Farming",
            "subcategory":"Farm",
            "type":"Manufacturing & Wholesale Goods"
        }
    ],
    "sg:phone":"+44 1278 653022",
    "sg:postcode":"TA5 2PW",
    "sg:province":"Somerset",
    "sg:tags":[
        "mixed",
        "crop"
    ],
    "wof:name":"A J Passmore & Son",
    "wof:placetype":"venue"
},
  "geometry": {"coordinates":[-3.08751,51.16695],"type":"Point"}
}