{
  "type": "Feature",
  "properties": {
    "addr:full":"354-258 Forest Road London Greater London E17 5JL",
    "addr:housenumber":"354-258",
    "addr:postcode":"e17 5jl",
    "addr:street":"Forest Road",
    "iso:country":"GB",
    "sg:address":"354-258 Forest Road",
    "sg:city":"London",
    "sg:classifiers":[
        {
            "category":"Health Services",
            "subcategory":"Clinic",
            "type":"Services"
        }
    ],
    "sg:phone":"+44 20 8520 6060",
    "sg:postcode":"E17 5JL",
    "sg:province":"Greater London",
    "sg:tags":[
        "nh"
    ],
    "wof:name":"Forest Road Medical Centre",
    "wof:placetype":"venue"
},
  "geometry": {"coordinates":[-0.0262960009,51.5897903442],"type":"Point"}
}