{
  "type": "Feature",
  "properties": {
    "addr:full":"49 St Augustin Way Daventry Northamptonshire NN11 4LR",
    "addr:housenumber":"49",
    "addr:postcode":"nn11 4lr",
    "addr:street":"St Augustin Way",
    "iso:country":"GB",
    "sg:address":"49 St Augustin Way",
    "sg:city":"Daventry",
    "sg:classifiers":[
        {
            "category":"Personal",
            "type":"Services"
        }
    ],
    "sg:phone":"+44 1327 876400",
    "sg:postcode":"NN11 4LR",
    "sg:province":"Northamptonshire",
    "sg:tags":[
        "dressmaker"
    ],
    "wof:name":"Armageddon Ltd",
    "wof:placetype":"venue"
},
  "geometry": {"coordinates":[-1.1576659679,52.2533798218],"type":"Point"}
}