{
  "type": "Feature",
  "properties": {
    "addr:full":"Unit 1 Bongate, Bongate Workshops Jedburgh Scottish Borders TD8 6DU",
    "addr:housenumber":"unit 1",
    "addr:postcode":"td8 6du",
    "addr:street":"Bongate Bongate;Jedburgh",
    "iso:country":"GB",
    "sg:address":"Unit 1 Bongate, Bongate Workshops",
    "sg:city":"Jedburgh",
    "sg:classifiers":[
        {
            "category":"Professional",
            "subcategory":"Engineering",
            "type":"Services"
        }
    ],
    "sg:phone":"+44 1835 862950",
    "sg:postcode":"TD8 6DU",
    "sg:province":"Scottish Borders",
    "wof:name":"Tom Murray Welding Engineering",
    "wof:placetype":"venue"
},
  "geometry": {"coordinates":[-2.549929,55.48151],"type":"Point"}
}