{
  "type": "Feature",
  "properties": {
    "iso:country":"GB",
    "sg:address":"Waterloo Park, Angel Rd",
    "sg:city":"Norwich",
    "sg:classifiers":[
        {
            "category":"Community Center",
            "type":"Public Place"
        }
    ],
    "sg:phone":"+44 1603 789880",
    "sg:postcode":"NR3 3HX",
    "sg:province":"Norfolk",
    "sg:tags":[
        "nursery",
        "centre"
    ],
    "wof:name":"Parkland Rangers",
    "wof:placetype":"venue"
},
  "geometry": {"coordinates":[1.292975,52.640831],"type":"Point"}
}