{
  "type": "Feature",
  "properties": {
    "addr:full":"5 Humond Ledbury Gloucestershire HR8 1BN",
    "addr:housenumber":"5",
    "addr:postcode":"hr8 1bn",
    "addr:street":"Humond",
    "iso:country":"GB",
    "sg:address":"5 Humond",
    "sg:city":"Ledbury",
    "sg:classifiers":[
        {
            "category":"Building & Trades",
            "subcategory":"Construction",
            "type":"Services"
        }
    ],
    "sg:phone":"+44 1531 635437",
    "sg:postcode":"HR8 1BN",
    "sg:province":"Gloucestershire",
    "sg:tags":[
        "monumental",
        "mason"
    ],
    "wof:name":"T A King",
    "wof:placetype":"venue"
},
  "geometry": {"coordinates":[-2.4244349003,52.0423088074],"type":"Point"}
}