{
  "type": "Feature",
  "properties": {
    "addr:full":"44 East Street Chichester West Sussex PO19 1HQ",
    "addr:housenumber":"44",
    "addr:postcode":"po19 1hq",
    "addr:street":"East Street",
    "iso:country":"GB",
    "sg:address":"44 East Street",
    "sg:city":"Chichester",
    "sg:classifiers":[
        {
            "category":"Professional",
            "subcategory":"Management & Consulting",
            "type":"Services"
        }
    ],
    "sg:postcode":"PO19 1HQ",
    "sg:province":"West Sussex",
    "sg:tags":[
        "consultant",
        "transport"
    ],
    "wof:name":"Commercial Specialised Services Ltd",
    "wof:placetype":"venue"
},
  "geometry": {"coordinates":[-0.7752820253,50.8362884521],"type":"Point"}
}