{
  "type": "Feature",
  "properties": {
    "addr:full":"Wayleaf House, Westmill Lane, Cricklade Swindon Gloucestershire SN6 6JL",
    "addr:postcode":"sn6 6jl",
    "addr:street":"Westmill Lane",
    "iso:country":"GB",
    "sg:address":"Wayleaf House, Westmill Lane, Cricklade",
    "sg:city":"Swindon",
    "sg:classifiers":[
        {
            "category":"Professional",
            "type":"Services"
        },
        {
            "category":"Home & Garden",
            "subcategory":"Carpets & Floor Coverings",
            "type":"Retail Goods"
        }
    ],
    "sg:phone":"+44 1793 751014",
    "sg:postcode":"SN6 6JL",
    "sg:province":"Gloucestershire",
    "sg:tags":[
        "damp",
        "dry wall",
        "preservation",
        "tie",
        "rot",
        "replacement"
    ],
    "wof:name":"Academy Timber Treatments Ltd",
    "wof:placetype":"venue"
},
  "geometry": {"coordinates":[-1.85699,51.640049],"type":"Point"}
}