{
  "type": "Feature",
  "properties": {
    "addr:full":"54 Audley Range Blackburn Lancashire BB1 1TF",
    "addr:housenumber":"54",
    "addr:postcode":"bb1 1tf",
    "addr:street":"Audley Range",
    "iso:country":"GB",
    "sg:address":"54 Audley Range",
    "sg:city":"Blackburn",
    "sg:classifiers":[
        {
            "category":"Professional",
            "subcategory":"Business Services",
            "type":"Services"
        }
    ],
    "sg:phone":"+44 1254 660670",
    "sg:postcode":"BB1 1TF",
    "sg:province":"Lancashire",
    "sg:tags":[
        "answering"
    ],
    "wof:name":"The Call Centre",
    "wof:placetype":"venue"
},
  "geometry": {"coordinates":[-2.4704349041,53.7438621521],"type":"Point"}
}