{
  "type": "Feature",
  "properties": {
    "addr:full":"87 Wakefield Road Ossett West Yorkshire WF5 9JY",
    "addr:housenumber":"87",
    "addr:postcode":"wf5 9jy",
    "addr:street":"Wakefield Road",
    "iso:country":"GB",
    "sg:address":"87 Wakefield Road",
    "sg:city":"Ossett",
    "sg:classifiers":[
        {
            "category":"Personal",
            "type":"Services"
        },
        {
            "category":"Sports & Exercise",
            "subcategory":"Tennis Court",
            "type":"Entertainment"
        }
    ],
    "sg:phone":"+44 1924 273368",
    "sg:postcode":"WF5 9JY",
    "sg:province":"West Yorkshire",
    "sg:tags":[
        "breakdown",
        "recovery",
        "wedding"
    ],
    "wof:name":"Marick",
    "wof:placetype":"venue"
},
  "geometry": {"coordinates":[-1.56828,53.685753],"type":"Point"}
}