{
  "type": "Feature",
  "properties": {
    "addr:full":"A S L House, 10 Debdale Lane, Mansfield Woodhouse Mansfield Derbyshire NG19 7NS",
    "addr:housenumber":"10",
    "addr:postcode":"ng19 7ns",
    "addr:street":"A;Debdale Lane",
    "iso:country":"GB",
    "sg:address":"A S L House, 10 Debdale Lane, Mansfield Woodhouse",
    "sg:city":"Mansfield",
    "sg:classifiers":[
        {
            "category":"Professional",
            "subcategory":"Computer Services",
            "type":"Services"
        }
    ],
    "sg:phone":"+44 1623 470775",
    "sg:postcode":"NG19 7NS",
    "sg:province":"Derbyshire",
    "sg:tags":[
        "system",
        "software"
    ],
    "wof:name":"Agency Sales Ltd.",
    "wof:placetype":"venue"
},
  "geometry": {"coordinates":[-1.214876,53.157288],"type":"Point"}
}