{
  "type": "Feature",
  "properties": {
    "addr:full":"142-144 Offord Rd Islington Greater London N1 1SS",
    "addr:postcode":"142-144;n1 1ss",
    "addr:street":"Offord Rd",
    "iso:country":"GB",
    "sg:address":"142-144 Offord Rd",
    "sg:city":"Islington",
    "sg:classifiers":[
        {
            "category":"Professional",
            "subcategory":"Business Services",
            "type":"Services"
        }
    ],
    "sg:phone":"+44 20 7609 1213",
    "sg:postcode":"N1 1SS",
    "sg:province":"Greater London",
    "sg:tags":[
        "agent",
        "manufacturers'"
    ],
    "wof:name":"John Perry",
    "wof:placetype":"venue"
},
  "geometry": {"coordinates":[-0.1095120013,51.5439033508],"type":"Point"}
}