{
  "type": "Feature",
  "properties": {
    "addr:full":"Morley House, Whitchurch Parade Edgware Greater London HA8 6LP",
    "addr:postcode":"ha8 6lp",
    "addr:street":"Whitchurch Parade",
    "iso:country":"GB",
    "sg:address":"Morley House, Whitchurch Parade",
    "sg:city":"Edgware",
    "sg:classifiers":[
        {
            "category":"Professional",
            "subcategory":"Lawyer & Legal Services",
            "type":"Services"
        }
    ],
    "sg:phone":"+44 20 8952 3201",
    "sg:postcode":"HA8 6LP",
    "sg:province":"Greater London",
    "sg:tags":[
        "solicitor"
    ],
    "wof:name":"Heather Mains & Co.",
    "wof:placetype":"venue"
},
  "geometry": {"coordinates":[-0.2870840132,51.6096458435],"type":"Point"}
}