{
  "type": "Feature",
  "properties": {
    "addr:full":"Wayside Cottage, Crowshott, Highclere Newbury Berkshire RG20 9RY",
    "addr:postcode":"rg20 9ry",
    "addr:street":"Crowshott;Newbury",
    "iso:country":"GB",
    "sg:address":"Wayside Cottage, Crowshott, Highclere",
    "sg:city":"Newbury",
    "sg:classifiers":[
        {
            "category":"Manufacturing",
            "subcategory":"Buildings",
            "type":"Manufacturing & Wholesale Goods"
        }
    ],
    "sg:postcode":"RG20 9RY",
    "sg:province":"Berkshire",
    "sg:tags":[
        "framed",
        "timber"
    ],
    "wof:name":"Hartwood Oak Buildings",
    "wof:placetype":"venue"
},
  "geometry": {"coordinates":[-1.3719539642,51.3449363708],"type":"Point"}
}