{
  "type": "Feature",
  "properties": {
    "addr:full":"Holmcroft Road Manchester Greater Manchester M18 7NG",
    "addr:postcode":"m18 7ng",
    "addr:street":"Holmcroft Road",
    "iso:country":"GB",
    "sg:address":"Holmcroft Road",
    "sg:city":"Manchester",
    "sg:classifiers":[
        {
            "category":"Education",
            "subcategory":"Special Training",
            "type":"Public Place"
        },
        {
            "category":"Education",
            "subcategory":"School",
            "type":"Public Place"
        }
    ],
    "sg:phone":"+44 161 223 9915",
    "sg:postcode":"M18 7NG",
    "sg:province":"Greater Manchester",
    "wof:name":"Melland High School",
    "wof:placetype":"venue"
},
  "geometry": {"coordinates":[-2.174309,53.456051],"type":"Point"}
}