{
  "type": "Feature",
  "properties": {
    "addr:full":"448-452 Chester Road Manchester Cheshire M16 9HL",
    "addr:housenumber":"448-452",
    "addr:postcode":"m16 9hl",
    "addr:street":"Chester Road",
    "iso:country":"GB",
    "sg:address":"448-452 Chester Road",
    "sg:city":"Manchester",
    "sg:classifiers":[
        {
            "category":"Home & Garden",
            "subcategory":"Garden Supply",
            "type":"Retail Goods"
        }
    ],
    "sg:phone":"+44 161 848 1110",
    "sg:postcode":"M16 9HL",
    "sg:province":"Cheshire",
    "sg:tags":[
        "nursery",
        "centre"
    ],
    "wof:name":"PARKERS GARDEN CENTRE",
    "wof:placetype":"venue"
},
  "geometry": {"coordinates":[-2.270236,53.464569],"type":"Point"}
}