{
  "type": "Feature",
  "properties": {
    "addr:full":"159 Upper St, Islington Islington Greater London N1 1RE",
    "addr:housenumber":"159",
    "addr:postcode":"n1 1re",
    "addr:street":"Upper St",
    "iso:country":"GB",
    "sg:address":"159 Upper St, Islington",
    "sg:city":"Islington",
    "sg:classifiers":[
        {
            "category":"Government",
            "subcategory":"Office",
            "type":"Public Place"
        }
    ],
    "sg:phone":"+44 20 7527 3231",
    "sg:postcode":"N1 1RE",
    "sg:province":"Greater London",
    "sg:tags":[
        "local"
    ],
    "wof:name":"Islington Council Pest Control Services",
    "wof:placetype":"venue"
},
  "geometry": {"coordinates":[-0.102833,51.5406],"type":"Point"}
}