{
  "type": "Feature",
  "properties": {
    "iso:country":"GB",
    "sg:address":"11 Hook Lane",
    "sg:city":"Welling",
    "sg:classifiers":[
        {
            "category":"Health Services",
            "subcategory":"Dentist",
            "type":"Services"
        }
    ],
    "sg:phone":"+44 20 8303 9579",
    "sg:postcode":"DA16 2DH",
    "sg:province":"Kent",
    "wof:name":"N Karia",
    "wof:placetype":"venue"
},
  "geometry": {"coordinates":[0.107034,51.461708],"type":"Point"}
}