{
  "type": "Feature",
  "properties": {
    "addr:full":"34 St Marys Row, Moseley Birmingham West Midlands B13 8JG",
    "addr:housenumber":"34",
    "addr:postcode":"b13 8jg",
    "addr:street":"St Marys Row",
    "iso:country":"GB",
    "sg:address":"34 St Marys Row, Moseley",
    "sg:city":"Birmingham",
    "sg:classifiers":[
        {
            "category":"Shopping",
            "subcategory":"Thrift Store",
            "type":"Retail Goods"
        }
    ],
    "sg:phone":"+44 121 449 4442",
    "sg:postcode":"B13 8JG",
    "sg:province":"West Midlands",
    "sg:tags":[
        "shop",
        "charity"
    ],
    "sg:website":"http://www.oxfam.org.uk",
    "wof:name":"Oxfam",
    "wof:placetype":"venue"
},
  "geometry": {"coordinates":[-1.8868869543,52.4460411072],"type":"Point"}
}