{
  "type": "Feature",
  "properties": {
    "addr:full":"72 Caereu Rd Newport Newport NP20 4HJ",
    "addr:housenumber":"72",
    "addr:postcode":"np20 4hj",
    "addr:street":"Caereu Rd",
    "iso:country":"GB",
    "sg:address":"72 Caereu Rd",
    "sg:city":"Newport",
    "sg:classifiers":[
        {
            "category":"Real Estate",
            "subcategory":"Architect",
            "type":"Services"
        }
    ],
    "sg:postcode":"NP20 4HJ",
    "sg:province":"Newport",
    "wof:name":"Evans,J H & Partners",
    "wof:placetype":"venue"
},
  "geometry": {"coordinates":[-3.004498,51.586365],"type":"Point"}
}