{
  "type": "Feature",
  "properties": {
    "iso:country":"GB",
    "sg:address":"72 Caereu Rd",
    "sg:city":"Newport",
    "sg:classifiers":[
        {
            "category":"Real Estate",
            "subcategory":"Architect",
            "type":"Services"
        }
    ],
    "sg:postcode":"NP20 4HJ",
    "sg:province":"Newport",
    "wof:name":"Evans,J H & Partners",
    "wof:placetype":"venue"
},
  "geometry": {"coordinates":[-3.004498,51.586365],"type":"Point"}
}