{
  "type": "Feature",
  "properties": {
    "iso:country":"GB",
    "sg:address":"38g Ellesmere Court",
    "sg:city":"Sunderland",
    "sg:classifiers":[
        {
            "category":"Ice Cream",
            "type":"Food & Drink"
        }
    ],
    "sg:phone":"+44 191 523 8860",
    "sg:postcode":"SR2 9TR",
    "sg:province":"Tyne and Wear",
    "wof:name":"Leechmere Ices",
    "wof:placetype":"venue"
},
  "geometry": {"coordinates":[-1.3757549524,54.8807220459],"type":"Point"}
}