{
  "type": "Feature",
  "properties": {
    "addr:full":"14 Mount Pleasant Bilston West Midlands WV14 7LJ",
    "addr:housenumber":"14",
    "addr:postcode":"wv14 7lj",
    "addr:street":"Mount Pleasant",
    "iso:country":"GB",
    "sg:address":"14 Mount Pleasant",
    "sg:city":"Bilston",
    "sg:classifiers":[
        {
            "category":"Shopping",
            "subcategory":"Optician",
            "type":"Retail Goods"
        }
    ],
    "sg:phone":"+44 1902 492020",
    "sg:postcode":"WV14 7LJ",
    "sg:province":"West Midlands",
    "wof:name":"Eye Openers",
    "wof:placetype":"venue"
},
  "geometry": {"coordinates":[-2.0748400688,52.5673065186],"type":"Point"}
}