{
  "type": "Feature",
  "properties": {
    "addr:full":"27 Heaton St, Milnrow Rochdale Lancashire OL16 3PP",
    "addr:housenumber":"27",
    "addr:postcode":"ol16 3pp",
    "addr:street":"Heaton St;Rochdale",
    "iso:country":"GB",
    "sg:address":"27 Heaton St, Milnrow",
    "sg:city":"Rochdale",
    "sg:classifiers":[
        {
            "category":"Utilities",
            "subcategory":"Natural Gas",
            "type":"Services"
        }
    ],
    "sg:phone":"+44 1706 868325",
    "sg:postcode":"OL16 3PP",
    "sg:province":"Lancashire",
    "sg:tags":[
        "supplier"
    ],
    "wof:name":"Gas Transportation Co.",
    "wof:placetype":"venue"
},
  "geometry": {"coordinates":[-2.1033239365,53.6057243347],"type":"Point"}
}