{
  "type": "Feature",
  "properties": {
    "addr:full":"21 Eller Drive, Westwinch King's Lynn Norfolk PE33 0NN",
    "addr:housenumber":"21",
    "addr:postcode":"pe33 0nn",
    "addr:street":"Eller Drive;Lynn",
    "iso:country":"GB",
    "sg:address":"21 Eller Drive, Westwinch",
    "sg:city":"King's Lynn",
    "sg:classifiers":[
        {
            "category":"Home & Garden",
            "subcategory":"Building Materials",
            "type":"Retail Goods"
        },
        {
            "category":"Building & Trades",
            "subcategory":"Construction",
            "type":"Services"
        }
    ],
    "sg:phone":"+44 1553 840922",
    "sg:postcode":"PE33 0NN",
    "sg:province":"Norfolk",
    "sg:tags":[
        "dry",
        "plasterers",
        "installers",
        "lining",
        "insulation",
        "screeders"
    ],
    "wof:name":"Edmund Thomas Elves",
    "wof:placetype":"venue"
},
  "geometry": {"coordinates":[0.41375,52.709881],"type":"Point"}
}