{
  "type": "Feature",
  "properties": {
    "addr:full":"New Whitby Court, Shepley Huddersfield South Yorkshire HD8 8BU",
    "addr:postcode":"hd8 8bu",
    "addr:street":"New Whitby Court",
    "iso:country":"GB",
    "sg:address":"New Whitby Court, Shepley",
    "sg:city":"Huddersfield",
    "sg:classifiers":[
        {
            "category":"Shopping",
            "subcategory":"Pharmacy",
            "type":"Retail Goods"
        }
    ],
    "sg:phone":"+44 1484 604506",
    "sg:postcode":"HD8 8BU",
    "sg:province":"South Yorkshire",
    "sg:tags":[
        "pharmaceutical"
    ],
    "wof:name":"Trinity-Chiesi Pharmaceuticals Ltd.",
    "wof:placetype":"venue"
},
  "geometry": {"coordinates":[-1.705871,53.585651],"type":"Point"}
}