{
  "type": "Feature",
  "properties": {
    "addr:full":"1 Rock Cottage, Main Road, Sellindge Ashford Kent TN25 6AQ",
    "addr:housenumber":"1",
    "addr:postcode":"tn25 6aq",
    "addr:street":"Rock;Main Road",
    "iso:country":"GB",
    "sg:address":"1 Rock Cottage, Main Road, Sellindge",
    "sg:city":"Ashford",
    "sg:classifiers":[
        {
            "category":"Home & Garden",
            "subcategory":"Hardware",
            "type":"Retail Goods"
        }
    ],
    "sg:phone":"+44 1303 814189",
    "sg:postcode":"TN25 6AQ",
    "sg:province":"Kent",
    "sg:tags":[
        "tarpaulin"
    ],
    "wof:name":"R Wilford Tarpaulins",
    "wof:placetype":"venue"
},
  "geometry": {"coordinates":[1.0053249598,51.1030197144],"type":"Point"}
}