{
  "type": "Feature",
  "properties": {
    "addr:full":"21 Long Acre, Covent Garden London Greater London WC2E 9LD",
    "addr:housenumber":"21",
    "addr:postcode":"wc2e 9ld",
    "addr:street":"Long Acre",
    "iso:country":"GB",
    "sg:address":"21 Long Acre, Covent Garden",
    "sg:city":"London",
    "sg:classifiers":[
        {
            "category":"Shopping",
            "subcategory":"Clothing, Apparel, & Fashions",
            "type":"Retail Goods"
        }
    ],
    "sg:phone":"+44 20 7240 3855",
    "sg:postcode":"WC2E 9LD",
    "sg:province":"Greater London",
    "sg:tags":[
        "shop"
    ],
    "wof:name":"Jigsaw",
    "wof:placetype":"venue"
},
  "geometry": {"coordinates":[-0.125521,51.512306],"type":"Point"}
}