{
  "type": "Feature",
  "properties": {
    "addr:full":"Capital House, 662 London Road, Cheam Sutton Surrey SM3 9BY",
    "addr:housenumber":"662",
    "addr:postcode":"sm3 9by",
    "addr:street":"London Road",
    "iso:country":"GB",
    "sg:address":"Capital House, 662 London Road, Cheam",
    "sg:city":"Sutton",
    "sg:classifiers":[
        {
            "category":"Banks & Credit Unions",
            "subcategory":"Investment Brokerage",
            "type":"Services"
        }
    ],
    "sg:phone":"+44 20 8644 5070",
    "sg:postcode":"SM3 9BY",
    "sg:province":"Surrey",
    "sg:tags":[
        "distribution",
        "circular"
    ],
    "wof:name":"County Distribution Group",
    "wof:placetype":"venue"
},
  "geometry": {"coordinates":[-0.223905,51.374496],"type":"Point"}
}