{
  "type": "Feature",
  "properties": {
    "addr:full":"Crossways, Whalley Road Burnley Lancashire BB12 8JR",
    "addr:postcode":"bb12 8jr",
    "addr:street":"Whalley Road",
    "iso:country":"GB",
    "sg:address":"Crossways, Whalley Road",
    "sg:city":"Burnley",
    "sg:classifiers":[
        {
            "category":"Restaurant",
            "type":"Food & Drink"
        }
    ],
    "sg:postcode":"BB12 8JR",
    "sg:province":"Lancashire",
    "wof:name":"Mamma Mia",
    "wof:placetype":"venue"
},
  "geometry": {"coordinates":[-2.32306,53.800678],"type":"Point"}
}