{
  "type": "Feature",
  "properties": {
    "addr:full":"Glenelg, 59 Duncarnock Crescent, Neilston Glasgow East Ayrshire G78 3HH",
    "addr:housenumber":"59",
    "addr:postcode":"g78 3hh",
    "addr:street":"Glenelg;Duncarnock Crescent",
    "iso:country":"GB",
    "sg:address":"Glenelg, 59 Duncarnock Crescent, Neilston",
    "sg:city":"Glasgow",
    "sg:classifiers":[
        {
            "category":"Manufacturing",
            "subcategory":"Paper Products",
            "type":"Manufacturing & Wholesale Goods"
        }
    ],
    "sg:phone":"+44 141 881 1106",
    "sg:postcode":"G78 3HH",
    "sg:province":"East Ayrshire",
    "sg:tags":[
        "cardboard"
    ],
    "wof:name":"Raymond Mccoll",
    "wof:placetype":"venue"
},
  "geometry": {"coordinates":[-4.428218,55.784176],"type":"Point"}
}