{
  "type": "Feature",
  "properties": {
    "addr:full":"1 Bleak Cottages, Ashwells Rd Brentwood Essex CM15 9SG",
    "addr:housenumber":"1",
    "addr:postcode":"cm15 9sg",
    "addr:street":"Bleak Cottages Ashwells Rd",
    "iso:country":"GB",
    "sg:address":"1 Bleak Cottages, Ashwells Rd",
    "sg:city":"Brentwood",
    "sg:classifiers":[
        {
            "category":"Building & Trades",
            "subcategory":"Construction",
            "type":"Services"
        }
    ],
    "sg:phone":"+44 1277 373933",
    "sg:postcode":"CM15 9SG",
    "sg:province":"Essex",
    "sg:tags":[
        "roofing"
    ],
    "wof:name":"Brentwood Roofing",
    "wof:placetype":"venue"
},
  "geometry": {"coordinates":[0.28001,51.645439],"type":"Point"}
}