{
  "type": "Feature",
  "properties": {
    "addr:full":"Unit 21 Salisbury Dorset SP5 3HF",
    "addr:housenumber":"unit 21",
    "addr:postcode":"sp5 3hf",
    "iso:country":"GB",
    "sg:address":"Unit 21",
    "sg:city":"Salisbury",
    "sg:classifiers":[
        {
            "category":"Professional",
            "subcategory":"Printing & Photocopies",
            "type":"Services"
        }
    ],
    "sg:phone":"+44 1722 711118",
    "sg:postcode":"SP5 3HF",
    "sg:province":"Dorset",
    "sg:tags":[
        "embroiderer"
    ],
    "wof:name":"Embroidery Unlimited",
    "wof:placetype":"venue"
},
  "geometry": {"coordinates":[-1.727859,51.013741],"type":"Point"}
}