{
  "type": "Feature",
  "properties": {
    "addr:full":"206 North Sea Lane Grimsby Lincolnshire DN36 4EP",
    "addr:housenumber":"206",
    "addr:postcode":"dn36 4ep",
    "addr:street":"North Sea Lane",
    "iso:country":"GB",
    "sg:address":"206 North Sea Lane",
    "sg:city":"Grimsby",
    "sg:classifiers":[
        {
            "category":"Food & Beverages",
            "subcategory":"Meat & Fish",
            "type":"Retail Goods"
        }
    ],
    "sg:phone":"+44 1472 816269",
    "sg:postcode":"DN36 4EP",
    "sg:province":"Lincolnshire",
    "sg:tags":[
        "chip"
    ],
    "wof:name":"Sea Lane Fisheries",
    "wof:placetype":"venue"
},
  "geometry": {"coordinates":[-0.0150490003,53.5362014771],"type":"Point"}
}