{
  "type": "Feature",
  "properties": {
    "addr:full":"Oakwood House, Meadow Bank Faringdon Oxfordshire SN7 8DS",
    "addr:postcode":"sn7 8ds",
    "iso:country":"GB",
    "sg:address":"Oakwood House, Meadow Bank",
    "sg:city":"Faringdon",
    "sg:classifiers":[
        {
            "category":"Health Services",
            "subcategory":"Hospital",
            "type":"Services"
        }
    ],
    "sg:phone":"+44 1367 242150",
    "sg:postcode":"SN7 8DS",
    "sg:province":"Oxfordshire",
    "wof:name":"FARINGDON DAY HOSPITAL",
    "wof:placetype":"venue"
},
  "geometry": {"coordinates":[-1.5886390209,51.6567764282],"type":"Point"}
}