{
  "type": "Feature",
  "properties": {
    "addr:full":"225-231 Upper Richmond Rd Putney Greater London SW15 6SJ",
    "addr:housenumber":"225-231",
    "addr:postcode":"sw15 6sj",
    "addr:street":"Upper Richmond Rd",
    "iso:country":"GB",
    "sg:address":"225-231 Upper Richmond Rd",
    "sg:city":"Putney",
    "sg:classifiers":[
        {
            "category":"Home & Garden",
            "subcategory":"Carpets & Floor Coverings",
            "type":"Retail Goods"
        }
    ],
    "sg:phone":"+44 20 8788 2361",
    "sg:postcode":"SW15 6SJ",
    "sg:province":"Greater London",
    "sg:tags":[
        "carpets",
        "rug",
        "matting"
    ],
    "wof:name":"Allied Carpet Stores",
    "wof:placetype":"venue"
},
  "geometry": {"coordinates":[-0.218326,51.461277],"type":"Point"}
}