{
  "type": "Feature",
  "properties": {
    "addr:full":"New Green Farm, East Marsh Road, Goxhill Barrow-upon-humber Lincolnshire DN19 7NQ",
    "addr:postcode":"dn19 7nq",
    "addr:street":"East Marsh Road;Barrow-Upon-Humber",
    "iso:country":"GB",
    "sg:address":"New Green Farm, East Marsh Road, Goxhill",
    "sg:city":"Barrow-upon-humber",
    "sg:classifiers":[
        {
            "category":"Farming",
            "subcategory":"Livestock Farm",
            "type":"Manufacturing & Wholesale Goods"
        }
    ],
    "sg:phone":"+44 1469 530620",
    "sg:postcode":"DN19 7NQ",
    "sg:province":"Lincolnshire",
    "sg:tags":[
        "others"
    ],
    "wof:name":"E & J A H Portus",
    "wof:placetype":"venue"
},
  "geometry": {"coordinates":[-0.381838,53.675011],"type":"Point"}
}