{
  "type": "Feature",
  "properties": {
    "iso:country":"GB",
    "sg:address":"76 Pilling Lane, Preesall",
    "sg:city":"Poulton-le-fylde",
    "sg:classifiers":[
        {
            "category":"Home & Garden",
            "subcategory":"Home Furnishings",
            "type":"Retail Goods"
        }
    ],
    "sg:postcode":"FY6 0HB",
    "sg:province":"Lancashire",
    "sg:tags":[
        "furnishers",
        "planner",
        "kitchen"
    ],
    "wof:name":"Schofield Kitchens",
    "wof:placetype":"venue"
},
  "geometry": {"coordinates":[-2.9717109203,53.931022644],"type":"Point"}
}