{
  "type": "Feature",
  "properties": {
    "addr:full":"30-34 Hounds Gate Nottingham Nottinghamshire NG1 7AB",
    "addr:housenumber":"30-34",
    "addr:postcode":"ng1 7ab",
    "addr:street":"Hounds Gate",
    "iso:country":"GB",
    "sg:address":"30-34 Hounds Gate",
    "sg:city":"Nottingham",
    "sg:classifiers":[
        {
            "category":"Professional",
            "subcategory":"Business Services",
            "type":"Services"
        }
    ],
    "sg:phone":"+44 115 941 0900",
    "sg:postcode":"NG1 7AB",
    "sg:province":"Nottinghamshire",
    "sg:tags":[
        "accomodation"
    ],
    "wof:name":"H B S Pension Nominees Ltd",
    "wof:placetype":"venue"
},
  "geometry": {"coordinates":[-1.150442,52.951927],"type":"Point"}
}