{
  "type": "Feature",
  "properties": {
    "addr:full":"Buttercup Farm, Hockliffe Road, Tebworth Leighton Buzzard Bedfordshire LU7 9QA",
    "addr:postcode":"lu7 9qa",
    "addr:street":"Hockliffe Road",
    "iso:country":"GB",
    "sg:address":"Buttercup Farm, Hockliffe Road, Tebworth",
    "sg:city":"Leighton Buzzard",
    "sg:classifiers":[
        {
            "category":"Professional",
            "subcategory":"Management & Consulting",
            "type":"Services"
        }
    ],
    "sg:phone":"+44 1525 875059",
    "sg:postcode":"LU7 9QA",
    "sg:province":"Bedfordshire",
    "sg:tags":[
        "marketing",
        "consultant"
    ],
    "wof:name":"Target Markets",
    "wof:placetype":"venue"
},
  "geometry": {"coordinates":[-0.5859490037,51.9323768616],"type":"Point"}
}