{
  "type": "Feature",
  "properties": {
    "addr:full":"Darlingscott Road Shipston-on-stour Warwickshire CV36 4DY",
    "addr:postcode":"cv36 4dy",
    "addr:street":"Darlingscott Road",
    "iso:country":"GB",
    "sg:address":"Darlingscott Road",
    "sg:city":"Shipston-on-stour",
    "sg:classifiers":[
        {
            "category":"Education",
            "subcategory":"School",
            "type":"Public Place"
        }
    ],
    "sg:phone":"+44 1608 661833",
    "sg:postcode":"CV36 4DY",
    "sg:province":"Warwickshire",
    "sg:tags":[
        "local",
        "authority"
    ],
    "wof:name":"Shipston High School",
    "wof:placetype":"venue"
},
  "geometry": {"coordinates":[-1.6336740255,52.0673141479],"type":"Point"}
}