{
  "type": "Feature",
  "properties": {
    "addr:full":"4 Southend Ledbury Gloucestershire HR8 2EY",
    "addr:housenumber":"4",
    "addr:postcode":"hr8 2ey",
    "addr:street":"Southend",
    "iso:country":"GB",
    "sg:address":"4 Southend",
    "sg:city":"Ledbury",
    "sg:classifiers":[
        {
            "category":"Shopping",
            "subcategory":"Crafts & Fabrics",
            "type":"Retail Goods"
        }
    ],
    "sg:phone":"+44 1531 632442",
    "sg:postcode":"HR8 2EY",
    "sg:province":"Gloucestershire",
    "sg:tags":[
        "shop",
        "needlecraft",
        "wool"
    ],
    "wof:name":"Gallery Needlework",
    "wof:placetype":"venue"
},
  "geometry": {"coordinates":[-2.4224939346,52.0354003906],"type":"Point"}
}