{
  "type": "Feature",
  "properties": {
    "addr:full":"44 Victoria Road Kirkcaldy Fife KY1 1DH",
    "addr:housenumber":"44",
    "addr:postcode":"ky1 1dh",
    "addr:street":"Victoria Road",
    "iso:country":"GB",
    "sg:address":"44 Victoria Road",
    "sg:city":"Kirkcaldy",
    "sg:classifiers":[
        {
            "category":"Professional",
            "subcategory":"Accounting & Tax Preparation",
            "type":"Services"
        }
    ],
    "sg:phone":"+44 1592 263212",
    "sg:postcode":"KY1 1DH",
    "sg:province":"Fife",
    "sg:tags":[
        "accountant"
    ],
    "wof:name":"Scott Oswald",
    "wof:placetype":"venue"
},
  "geometry": {"coordinates":[-3.1617801189,56.115978241],"type":"Point"}
}