{
  "type": "Feature",
  "properties": {
    "addr:full":"Church Farm, Northgate Way, Terrington St Clement King's Lynn Lincolnshire PE34 4LD",
    "addr:postcode":"pe34 4ld",
    "addr:street":"Northgate Way",
    "iso:country":"GB",
    "sg:address":"Church Farm, Northgate Way, Terrington St Clement",
    "sg:city":"King's Lynn",
    "sg:classifiers":[
        {
            "category":"Home & Garden",
            "subcategory":"Garden Supply",
            "type":"Retail Goods"
        }
    ],
    "sg:postcode":"PE34 4LD",
    "sg:province":"Lincolnshire",
    "sg:tags":[
        "planting",
        "tree",
        "shrub"
    ],
    "wof:name":"Church Farm Nurseries Ltd",
    "wof:placetype":"venue"
},
  "geometry": {"coordinates":[0.3070200086,52.7646102905],"type":"Point"}
}