{
  "type": "Feature",
  "properties": {
    "iso:country":"GB",
    "sg:address":"21a Weights Farm, Weights Lane",
    "sg:city":"Redditch",
    "sg:classifiers":[
        {
            "category":"Building & Trades",
            "subcategory":"Construction",
            "type":"Services"
        }
    ],
    "sg:phone":"+44 1527 68179",
    "sg:postcode":"B97 6RG",
    "sg:province":"Warwickshire",
    "sg:tags":[
        "joinery"
    ],
    "wof:name":"Redditch Joinery (Holdings) Ltd.",
    "wof:placetype":"venue"
},
  "geometry": {"coordinates":[-1.941267,52.30727],"type":"Point"}
}