{
  "type": "Feature",
  "properties": {
    "iso:country":"GB",
    "sg:address":"4 Greenhall, Gowkshill",
    "sg:city":"Gorebridge",
    "sg:classifiers":[
        {
            "category":"Organizations",
            "subcategory":"Non-profit Organization",
            "type":"Services"
        }
    ],
    "sg:phone":"+44 1875 823005",
    "sg:postcode":"EH23 4PE",
    "sg:province":"Midlothian",
    "sg:tags":[
        "organisation",
        "voluntary",
        "charity"
    ],
    "wof:name":"Workstart",
    "wof:placetype":"venue"
},
  "geometry": {"coordinates":[-3.0553839207,55.8497543335],"type":"Point"}
}