{
  "type": "Feature",
  "properties": {
    "addr:full":"421-427 Millbrook Road West, Millbrook Southampton Hampshire SO15 0HX",
    "addr:housenumber":"421-427",
    "addr:postcode":"so15 0hx",
    "addr:street":"Millbrook Road West",
    "iso:country":"GB",
    "sg:address":"421-427 Millbrook Road West, Millbrook",
    "sg:city":"Southampton",
    "sg:classifiers":[
        {
            "category":"Communications",
            "subcategory":"Newspaper",
            "type":"Services"
        },
        {
            "category":"Shopping",
            "subcategory":"Books",
            "type":"Retail Goods"
        }
    ],
    "sg:phone":"+44 845 050 1291",
    "sg:postcode":"SO15 0HX",
    "sg:province":"Hampshire",
    "sg:tags":[
        "magazine"
    ],
    "wof:name":"Southern Auto Trader",
    "wof:placetype":"venue"
},
  "geometry": {"coordinates":[-1.4466359615,50.9138679504],"type":"Point"}
}