{
  "type": "Feature",
  "properties": {
    "addr:full":"22 St.mary St Cardiff Cardiff CF10 1AA",
    "addr:housenumber":"22",
    "addr:postcode":"cf10 1aa",
    "addr:street":"St.Mary St",
    "iso:country":"GB",
    "sg:address":"22 St.mary St",
    "sg:city":"Cardiff",
    "sg:classifiers":[
        {
            "category":"Professional",
            "subcategory":"Management & Consulting",
            "type":"Services"
        }
    ],
    "sg:phone":"+44 29 2038 2277",
    "sg:postcode":"CF10 1AA",
    "sg:province":"Cardiff",
    "sg:tags":[
        "music"
    ],
    "wof:name":"First Move Management Ltd",
    "wof:placetype":"venue"
},
  "geometry": {"coordinates":[-3.178352,51.479115],"type":"Point"}
}