{
  "type": "Feature",
  "properties": {
    "addr:full":"Unit 6, City Link Industrial Park, Dick Lane Bradford West Yorkshire BD4 8JP",
    "addr:housenumber":"unit 6",
    "addr:postcode":"bd4 8jp",
    "addr:street":"City Link Industrial Park Dick Lane",
    "iso:country":"GB",
    "sg:address":"Unit 6, City Link Industrial Park, Dick Lane",
    "sg:city":"Bradford",
    "sg:classifiers":[
        {
            "category":"Home & Garden",
            "subcategory":"Building Materials",
            "type":"Retail Goods"
        }
    ],
    "sg:phone":"+44 1274 656012",
    "sg:postcode":"BD4 8JP",
    "sg:province":"West Yorkshire",
    "sg:tags":[
        "insulation",
        "installers"
    ],
    "wof:name":"Orion Insulations",
    "wof:placetype":"venue"
},
  "geometry": {"coordinates":[-1.70724,53.79303],"type":"Point"}
}