{
  "type": "Feature",
  "properties": {
    "addr:full":"137 Winchester Rd Lower Edmonton Greater London N9 9EX",
    "addr:housenumber":"137",
    "addr:postcode":"n9 9ex",
    "addr:street":"Winchester Rd",
    "iso:country":"GB",
    "sg:address":"137 Winchester Rd",
    "sg:city":"Lower Edmonton",
    "sg:classifiers":[
        {
            "category":"Professional",
            "type":"Services"
        }
    ],
    "sg:phone":"+44 20 8803 9122",
    "sg:postcode":"N9 9EX",
    "sg:province":"Greater London",
    "sg:tags":[
        "entertainer"
    ],
    "wof:name":"Pex Puppets",
    "wof:placetype":"venue"
},
  "geometry": {"coordinates":[-0.064942,51.630215],"type":"Point"}
}