{
  "type": "Feature",
  "properties": {
    "addr:full":"98 Bradshawgate Bolton Lancashire BL1 1QJ",
    "addr:housenumber":"98",
    "addr:postcode":"bl1 1qj",
    "addr:street":"Bradshawgate Bolton",
    "iso:country":"GB",
    "sg:address":"98 Bradshawgate",
    "sg:city":"Bolton",
    "sg:classifiers":[
        {
            "category":"Professional",
            "subcategory":"Employment Agencies",
            "type":"Services"
        },
        {
            "category":"Professional",
            "subcategory":"Computer Services",
            "type":"Services"
        }
    ],
    "sg:phone":"+44 1204 532711",
    "sg:postcode":"BL1 1QJ",
    "sg:province":"Lancashire",
    "sg:tags":[
        "consultant",
        "software",
        "system",
        "recruitment"
    ],
    "wof:name":"Tempo Staff Services Ltd",
    "wof:placetype":"venue"
},
  "geometry": {"coordinates":[-2.425992012,53.5768966675],"type":"Point"}
}