{
  "type": "Feature",
  "properties": {
    "iso:country":"GB",
    "sg:address":"Norwood Farm House, Norwood Lane, Meopham",
    "sg:city":"Gravesend",
    "sg:classifiers":[
        {
            "category":"Professional",
            "subcategory":"Management & Consulting",
            "type":"Services"
        }
    ],
    "sg:phone":"+44 1474 812745",
    "sg:postcode":"DA13 0YF",
    "sg:province":"Kent",
    "sg:tags":[
        "consultant",
        "business"
    ],
    "wof:name":"John Ogden & Associates",
    "wof:placetype":"venue"
},
  "geometry": {"coordinates":[0.3623520136,51.383266449],"type":"Point"}
}