{
  "type": "Feature",
  "properties": {
    "addr:full":"246 Bude Crescent, Symonds Grn Stevenage Hertfordshire SG1 2QU",
    "addr:housenumber":"246",
    "addr:postcode":"sg1 2qu",
    "addr:street":"Bude Crescent Symonds Grn",
    "iso:country":"GB",
    "sg:address":"246 Bude Crescent, Symonds Grn",
    "sg:city":"Stevenage",
    "sg:classifiers":[
        {
            "category":"Professional",
            "subcategory":"Printing & Photocopies",
            "type":"Services"
        }
    ],
    "sg:postcode":"SG1 2QU",
    "sg:province":"Hertfordshire",
    "sg:tags":[
        "process",
        "screen",
        "printer"
    ],
    "wof:name":"Printed Images",
    "wof:placetype":"venue"
},
  "geometry": {"coordinates":[-0.2204439938,51.9108314514],"type":"Point"}
}