{
  "type": "Feature",
  "properties": {
    "iso:country":"GB",
    "sg:address":"8 Eversley Crescent",
    "sg:city":"Havant",
    "sg:classifiers":[
        {
            "category":"Taxi",
            "type":"Transportation"
        }
    ],
    "sg:phone":"+44 23 9238 3207",
    "sg:postcode":"PO9 4RD",
    "sg:province":"Hampshire",
    "sg:tags":[
        "mini",
        "cab"
    ],
    "wof:name":"Airside Travel Ltd",
    "wof:placetype":"venue"
},
  "geometry": {"coordinates":[-0.990658,50.865715],"type":"Point"}
}