{
  "type": "Feature",
  "properties": {
    "iso:country":"GB",
    "sg:address":"192 Brighton St",
    "sg:city":"Wallasey",
    "sg:classifiers":[
        {
            "category":"Professional",
            "subcategory":"Engineering",
            "type":"Services"
        }
    ],
    "sg:phone":"+44 151 639 0589",
    "sg:postcode":"L44 8DY",
    "sg:province":"Merseyside",
    "sg:tags":[
        "contractor",
        "electrical",
        "engineer"
    ],
    "wof:name":"Delta Electrical Services",
    "wof:placetype":"venue"
},
  "geometry": {"coordinates":[-3.025471,53.417404],"type":"Point"}
}