{
  "type": "Feature",
  "properties": {
    "addr:full":"32 Cotmer Road, Olton Broad Lowestoft Suffolk NR33 9PW",
    "addr:housenumber":"32",
    "addr:postcode":"nr33 9pw",
    "addr:street":"Cotmer Road",
    "iso:country":"GB",
    "sg:address":"32 Cotmer Road, Olton Broad",
    "sg:city":"Lowestoft",
    "sg:classifiers":[
        {
            "category":"Community Center",
            "type":"Public Place"
        }
    ],
    "sg:phone":"+44 1502 565125",
    "sg:postcode":"NR33 9PW",
    "sg:province":"Suffolk",
    "sg:tags":[
        "recreation",
        "leisure",
        "centre"
    ],
    "wof:name":"Mobile Auto Traps",
    "wof:placetype":"venue"
},
  "geometry": {"coordinates":[1.7089430094,52.4660644531],"type":"Point"}
}