{
  "type": "Feature",
  "properties": {
    "addr:full":"41 Station Rd Hayes Greater London UB3 4BE",
    "addr:housenumber":"41",
    "addr:postcode":"ub3 4be",
    "addr:street":"Station Rd",
    "iso:country":"GB",
    "sg:address":"41 Station Rd",
    "sg:city":"Hayes",
    "sg:classifiers":[
        {
            "category":"Organizations",
            "subcategory":"Non-profit Organization",
            "type":"Services"
        }
    ],
    "sg:phone":"+44 20 8573 2828",
    "sg:postcode":"UB3 4BE",
    "sg:province":"Greater London",
    "sg:tags":[
        "organisation",
        "voluntary",
        "charity"
    ],
    "wof:name":"Relief Fund For Romania",
    "wof:placetype":"venue"
},
  "geometry": {"coordinates":[-0.4189009964,51.5059585571],"type":"Point"}
}