{
  "type": "Feature",
  "properties": {
    "iso:country":"GB",
    "sg:address":"1101 Pollokshaws Rd",
    "sg:city":"Glasgow",
    "sg:classifiers":[
        {
            "category":"Home & Garden",
            "subcategory":"Carpets & Floor Coverings",
            "type":"Retail Goods"
        }
    ],
    "sg:phone":"+44 141 632 0194",
    "sg:postcode":"G41 3YG",
    "sg:province":"Glasgow City",
    "sg:tags":[
        "carpets",
        "rug",
        "matting"
    ],
    "wof:name":"D Wilson",
    "wof:placetype":"venue"
},
  "geometry": {"coordinates":[-4.2799530029,55.8309059143],"type":"Point"}
}