{
  "type": "Feature",
  "properties": {
    "addr:full":"Springfield London Greater London E5 9EF",
    "addr:postcode":"e5 9ef",
    "iso:country":"GB",
    "sg:address":"Springfield",
    "sg:city":"London",
    "sg:classifiers":[
        {
            "category":"Community Center",
            "type":"Public Place"
        },
        {
            "category":"Government",
            "subcategory":"Office",
            "type":"Public Place"
        }
    ],
    "sg:phone":"+44 20 8806 1826",
    "sg:postcode":"E5 9EF",
    "sg:province":"Greater London",
    "sg:tags":[
        "local",
        "leisure",
        "centre"
    ],
    "wof:name":"Springfield Park",
    "wof:placetype":"venue"
},
  "geometry": {"coordinates":[-0.055699,51.568142],"type":"Point"}
}