{
  "type": "Feature",
  "properties": {
    "addr:full":"76 Ellwood Avenue Peterborough Cambridgeshire PE2 8LY",
    "addr:housenumber":"76",
    "addr:postcode":"pe2 8ly",
    "addr:street":"Ellwood Avenue",
    "iso:country":"GB",
    "sg:address":"76 Ellwood Avenue",
    "sg:city":"Peterborough",
    "sg:classifiers":[
        {
            "category":"Home & Garden",
            "subcategory":"Carpets & Floor Coverings",
            "type":"Retail Goods"
        }
    ],
    "sg:phone":"+44 1733 349097",
    "sg:postcode":"PE2 8LY",
    "sg:province":"Cambridgeshire",
    "sg:tags":[
        "carpets",
        "rug",
        "matting"
    ],
    "wof:name":"Ian Hichens",
    "wof:placetype":"venue"
},
  "geometry": {"coordinates":[-0.210629,52.553238],"type":"Point"}
}