{
  "type": "Feature",
  "properties": {
    "iso:country":"GB",
    "sg:address":"P O Box Southbank 16, Southerby Road, Skippers Lane Industrial Estate",
    "sg:city":"Middlesbrough",
    "sg:classifiers":[
        {
            "category":"Professional",
            "type":"Services"
        }
    ],
    "sg:phone":"+44 1642 457461",
    "sg:postcode":"TS6 6LP",
    "sg:province":"North Yorkshire",
    "sg:tags":[
        "auctioneer"
    ],
    "wof:name":"Fairfield Industries Ltd.",
    "wof:placetype":"venue"
},
  "geometry": {"coordinates":[-1.1838400364,54.5737609863],"type":"Point"}
}