{
  "type": "Feature",
  "properties": {
    "iso:country":"GB",
    "sg:address":"3 Clutha Street",
    "sg:city":"Glasgow",
    "sg:classifiers":[
        {
            "category":"Farming",
            "subcategory":"Nursery",
            "type":"Manufacturing & Wholesale Goods"
        },
        {
            "category":"Social Services",
            "subcategory":"Child Care",
            "type":"Services"
        }
    ],
    "sg:phone":"+44 141 427 2301",
    "sg:postcode":"G51 1BL",
    "sg:province":"Glasgow City",
    "sg:tags":[
        "creche"
    ],
    "wof:name":"Clutha Street Day Nursery",
    "wof:placetype":"venue"
},
  "geometry": {"coordinates":[-4.2906851768,55.8524971008],"type":"Point"}
}