{
  "type": "Feature",
  "properties": {
    "iso:country":"GB",
    "sg:address":"11 St Peters Parade",
    "sg:city":"Dewsbury",
    "sg:classifiers":[
        {
            "category":"Shopping",
            "subcategory":"Department Store",
            "type":"Retail Goods"
        }
    ],
    "sg:phone":"+44 1924 457351",
    "sg:postcode":"WF12 8LW",
    "sg:province":"West Yorkshire",
    "wof:name":"Earlsheaton Stores",
    "wof:placetype":"venue"
},
  "geometry": {"coordinates":[-1.612209,53.686649],"type":"Point"}
}