{
  "type": "Feature",
  "properties": {
    "iso:country":"GB",
    "sg:address":"Queens Studios, 117 Salisbury Road",
    "sg:city":"London",
    "sg:classifiers":[
        {
            "category":"Insurance",
            "subcategory":"Insurance Agent",
            "type":"Services"
        }
    ],
    "sg:phone":"+44 20 7328 3331",
    "sg:postcode":"NW6 6RG",
    "sg:province":"Greater London",
    "wof:name":"Gaebel Watkins & Taylor Ltd.",
    "wof:placetype":"venue"
},
  "geometry": {"coordinates":[-0.20701,51.538071],"type":"Point"}
}