{
  "type": "Feature",
  "properties": {
    "iso:country":"GB",
    "sg:address":"42 Helmsdale Crescent",
    "sg:city":"Dundee",
    "sg:classifiers":[
        {
            "category":"Communications",
            "type":"Services"
        }
    ],
    "sg:phone":"+44 1382 884588",
    "sg:postcode":"DD3 0NQ",
    "sg:province":"Dundee City",
    "sg:tags":[
        "audio-visual"
    ],
    "wof:name":"U in View",
    "wof:placetype":"venue"
},
  "geometry": {"coordinates":[-2.983488,56.493103],"type":"Point"}
}