{
  "type": "Feature",
  "properties": {
    "addr:full":"417 Barking Road London Greater London E6 2JX",
    "addr:housenumber":"417",
    "addr:postcode":"e6 2jx",
    "addr:street":"Barking Road",
    "iso:country":"GB",
    "sg:address":"417 Barking Road",
    "sg:city":"London",
    "sg:classifiers":[
        {
            "category":"Real Estate",
            "subcategory":"Real Estate Operator",
            "type":"Services"
        }
    ],
    "sg:phone":"+44 20 8471 0595",
    "sg:postcode":"E6 2JX",
    "sg:province":"Greater London",
    "sg:tags":[
        "letting",
        "agent"
    ],
    "wof:name":"Brickhouse Properties",
    "wof:placetype":"venue"
},
  "geometry": {"coordinates":[0.0562239997,51.5334014893],"type":"Point"}
}