{
  "type": "Feature",
  "properties": {
    "addr:full":"64 New Kings Road Fulham Greater London SW6 4LT",
    "addr:housenumber":"64",
    "addr:postcode":"sw6 4lt",
    "addr:street":"New Kings Road",
    "iso:country":"GB",
    "sg:address":"64 New Kings Road",
    "sg:city":"Fulham",
    "sg:classifiers":[
        {
            "category":"Arts & Performance",
            "subcategory":"Art Gallery",
            "type":"Entertainment"
        }
    ],
    "sg:phone":"+44 20 7736 1928",
    "sg:postcode":"SW6 4LT",
    "sg:province":"Greater London",
    "wof:name":"Anna-mei Chadwick",
    "wof:placetype":"venue"
},
  "geometry": {"coordinates":[-0.202267006,51.4723472595],"type":"Point"}
}