{
  "type": "Feature",
  "properties": {
    "iso:country":"GB",
    "sg:address":"Dan-y-deri Home Care Base, Ystrad Rd",
    "sg:city":"Pentre",
    "sg:classifiers":[
        {
            "category":"Government",
            "subcategory":"Office",
            "type":"Public Place"
        }
    ],
    "sg:phone":"+44 1443 441303",
    "sg:postcode":"CF41 7PS",
    "sg:province":"Rhondda, Cynon, Taff",
    "sg:tags":[
        "local"
    ],
    "wof:name":"Rhondda Cynon Taff County Borough Council",
    "wof:placetype":"venue"
},
  "geometry": {"coordinates":[-3.492894,51.655327],"type":"Point"}
}