{
  "type": "Feature",
  "properties": {
    "addr:full":"35 High St Newmarket Cambridgeshire CB8 8NA",
    "addr:housenumber":"35",
    "addr:postcode":"cb8 8na",
    "addr:street":"High St",
    "iso:country":"GB",
    "sg:address":"35 High St",
    "sg:city":"Newmarket",
    "sg:classifiers":[
        {
            "category":"Farming",
            "subcategory":"Livestock Farm",
            "type":"Manufacturing & Wholesale Goods"
        }
    ],
    "sg:postcode":"CB8 8NA",
    "sg:province":"Cambridgeshire",
    "sg:tags":[
        "breeder"
    ],
    "wof:name":"Greene,G,",
    "wof:placetype":"venue"
},
  "geometry": {"coordinates":[0.407751,52.244656],"type":"Point"}
}