{
  "type": "Feature",
  "properties": {
    "iso:country":"GB",
    "sg:address":"12 Craigmount Gro",
    "sg:city":"Edinburgh",
    "sg:classifiers":[
        {
            "category":"Insurance",
            "subcategory":"Insurance Agent",
            "type":"Services"
        }
    ],
    "sg:phone":"+44 131 339 1151",
    "sg:postcode":"EH12 8BL",
    "sg:province":"City of Edinburgh",
    "wof:name":"Lothian Independent Financial Services",
    "wof:placetype":"venue"
},
  "geometry": {"coordinates":[-3.2953178883,55.9464225769],"type":"Point"}
}