{
  "type": "Feature",
  "properties": {
    "addr:full":"Rear Of Midland Bank, Barnards Green Road Malvern Herefordshire WR14 3NB",
    "addr:housenumber":"rear of",
    "addr:postcode":"wr14 3nb",
    "addr:street":"Barnards Green Road",
    "iso:country":"GB",
    "sg:address":"Rear Of Midland Bank, Barnards Green Road",
    "sg:city":"Malvern",
    "sg:classifiers":[
        {
            "category":"Building & Trades",
            "subcategory":"Plumbing",
            "type":"Services"
        }
    ],
    "sg:phone":"+44 1684 564503",
    "sg:postcode":"WR14 3NB",
    "sg:province":"Herefordshire",
    "sg:tags":[
        "heating"
    ],
    "wof:name":"A to Z Plumbing & Heating Services Ltd.",
    "wof:placetype":"venue"
},
  "geometry": {"coordinates":[-2.31118,52.107849],"type":"Point"}
}