{
  "type": "Feature",
  "properties": {
    "iso:country":"GB",
    "sg:address":"148 Thorne Road, Edenthorpe",
    "sg:city":"Doncaster",
    "sg:classifiers":[
        {
            "category":"Personal",
            "subcategory":"Beauty Salon",
            "type":"Services"
        }
    ],
    "sg:postcode":"DN3 2LU",
    "sg:province":"South Yorkshire",
    "sg:tags":[
        "unisex",
        "hairdresser"
    ],
    "wof:name":"Way-A-Head",
    "wof:placetype":"venue"
},
  "geometry": {"coordinates":[-1.0638420582,53.5540733337],"type":"Point"}
}