{
  "type": "Feature",
  "properties": {
    "iso:country":"GB",
    "sg:address":"The Roofing Centre, Moneyfield Lane",
    "sg:city":"Portsmouth",
    "sg:classifiers":[
        {
            "category":"Building & Trades",
            "subcategory":"Construction",
            "type":"Services"
        },
        {
            "category":"Manufacturing",
            "subcategory":"Building Materials",
            "type":"Manufacturing & Wholesale Goods"
        }
    ],
    "sg:phone":"+44 23 9269 0214",
    "sg:postcode":"PO3 5AY",
    "sg:province":"Hampshire",
    "sg:tags":[
        "roofing",
        "product",
        "related"
    ],
    "sg:website":"http://www.colemanroofing.co.uk",
    "wof:name":"Coleman Roofing Supplies",
    "wof:placetype":"venue"
},
  "geometry": {"coordinates":[-1.062385,50.813335],"type":"Point"}
}