{
  "type": "Feature",
  "properties": {
    "addr:full":"19 Harvest Lane, Moreton Wirral Merseyside CH46 7UF",
    "addr:housenumber":"19",
    "addr:postcode":"ch46 7uf",
    "addr:street":"Harvest Lane",
    "iso:country":"GB",
    "sg:address":"19 Harvest Lane, Moreton",
    "sg:city":"Wirral",
    "sg:classifiers":[
        {
            "category":"Building & Trades",
            "subcategory":"Construction",
            "type":"Services"
        }
    ],
    "sg:phone":"+44 151 677 0730",
    "sg:postcode":"CH46 7UF",
    "sg:province":"Merseyside",
    "sg:tags":[
        "decorator",
        "painter"
    ],
    "wof:name":"Graham Parsons",
    "wof:placetype":"venue"
},
  "geometry": {"coordinates":[-3.1167209148,53.4046440125],"type":"Point"}
}