{
  "type": "Feature",
  "properties": {
    "iso:country":"GB",
    "sg:address":"111 Harley Street",
    "sg:city":"London",
    "sg:classifiers":[
        {
            "category":"Health Services",
            "subcategory":"Health Practitioner",
            "type":"Services"
        }
    ],
    "sg:phone":"+44 20 7935 0977",
    "sg:postcode":"W1G 6AW",
    "sg:province":"Greater London",
    "sg:tags":[
        "psychotherapist"
    ],
    "wof:name":"Lawrence Goldie",
    "wof:placetype":"venue"
},
  "geometry": {"coordinates":[-0.148246,51.521336],"type":"Point"}
}