{
  "type": "Feature",
  "properties": {
    "addr:full":"21 Riley Rd Southwark Greater London SE1 3DG",
    "addr:housenumber":"21",
    "addr:postcode":"se1 3dg",
    "addr:street":"Riley Rd",
    "iso:country":"GB",
    "sg:address":"21 Riley Rd",
    "sg:city":"Southwark",
    "sg:classifiers":[
        {
            "category":"Personal",
            "subcategory":"Beauty Salon",
            "type":"Services"
        }
    ],
    "sg:phone":"+44 20 7407 1521",
    "sg:postcode":"SE1 3DG",
    "sg:province":"Greater London",
    "sg:tags":[
        "lady",
        "hairdresser"
    ],
    "wof:name":"Curly Hair Fashions",
    "wof:placetype":"venue"
},
  "geometry": {"coordinates":[-0.078307,51.497681],"type":"Point"}
}