{
  "type": "Feature",
  "properties": {
    "addr:full":"Baileys Farm Horsham West Sussex RH13 7JR",
    "addr:postcode":"rh13 7jr",
    "iso:country":"GB",
    "sg:address":"Baileys Farm",
    "sg:city":"Horsham",
    "sg:classifiers":[
        {
            "category":"Home & Garden",
            "subcategory":"Kitchen Supply",
            "type":"Retail Goods"
        }
    ],
    "sg:phone":"+44 1403 741111",
    "sg:postcode":"RH13 7JR",
    "sg:province":"West Sussex",
    "sg:tags":[
        "equipment",
        "catering"
    ],
    "wof:name":"Last Orders",
    "wof:placetype":"venue"
},
  "geometry": {"coordinates":[-0.3291000128,51.0651817322],"type":"Point"}
}