{
  "type": "Feature",
  "properties": {
    "iso:country":"GB",
    "sg:address":"14 Britannia Road, Parkstone",
    "sg:city":"Poole",
    "sg:classifiers":[
        {
            "category":"Food & Beverages",
            "subcategory":"Bakery",
            "type":"Retail Goods"
        }
    ],
    "sg:phone":"+44 1202 740731",
    "sg:postcode":"BH14 8BB",
    "sg:province":"Dorset",
    "sg:tags":[
        "shop",
        "baker",
        "confectionery"
    ],
    "wof:name":"Bennetts Family Bakers Ltd.",
    "wof:placetype":"venue"
},
  "geometry": {"coordinates":[-1.9543459415,50.7226257324],"type":"Point"}
}