{
  "type": "Feature",
  "properties": {
    "iso:country":"GB",
    "sg:address":"67 Windmill Gro, Porchester",
    "sg:city":"Fareham",
    "sg:classifiers":[
        {
            "category":"Organizations",
            "subcategory":"Membership Organization",
            "type":"Services"
        }
    ],
    "sg:phone":"+44 23 9220 1696",
    "sg:postcode":"PO16 9HU",
    "sg:province":"Hampshire",
    "sg:tags":[
        "club",
        "social"
    ],
    "wof:name":"Individuals Sea Angling Club",
    "wof:placetype":"venue"
},
  "geometry": {"coordinates":[-1.130738,50.846088],"type":"Point"}
}