{
  "type": "Feature",
  "properties": {
    "addr:full":"Unit A5 Railway Triangle, Walton Rd Portsmouth Hampshire PO6 1TN",
    "addr:postcode":"hampshire po6 1tn",
    "addr:street":"Walton Rd",
    "iso:country":"GB",
    "sg:address":"Unit A5 Railway Triangle, Walton Rd",
    "sg:city":"Portsmouth",
    "sg:classifiers":[
        {
            "category":"Home & Garden",
            "subcategory":"Kitchen Supply",
            "type":"Retail Goods"
        }
    ],
    "sg:phone":"+44 23 9221 0977",
    "sg:postcode":"PO6 1TN",
    "sg:province":"Hampshire",
    "sg:tags":[
        "ware"
    ],
    "wof:name":"House Works",
    "wof:placetype":"venue"
},
  "geometry": {"coordinates":[-1.05226,50.838341],"type":"Point"}
}