{
  "type": "Feature",
  "properties": {
    "iso:country":"GB",
    "sg:address":"Tylers Court, 111a Wardour Street",
    "sg:city":"London",
    "sg:classifiers":[
        {
            "category":"Communications",
            "type":"Services"
        }
    ],
    "sg:phone":"+44 20 7437 3505",
    "sg:postcode":"W1F 0UN",
    "sg:province":"Greater London",
    "sg:tags":[
        "audio-visual"
    ],
    "wof:name":"Ice Pics",
    "wof:placetype":"venue"
},
  "geometry": {"coordinates":[-0.1341180056,51.5132904053],"type":"Point"}
}