{
  "type": "Feature",
  "properties": {
    "iso:country":"GB",
    "sg:address":"2 Cutlers La",
    "sg:city":"Fareham",
    "sg:classifiers":[
        {
            "category":"Building & Trades",
            "subcategory":"Construction",
            "type":"Services"
        }
    ],
    "sg:phone":"+44 1329 668994",
    "sg:postcode":"PO14 2JN",
    "sg:province":"Hampshire",
    "sg:tags":[
        "contractor"
    ],
    "wof:name":"T P C Building Services",
    "wof:placetype":"venue"
},
  "geometry": {"coordinates":[-1.2175990343,50.8268318176],"type":"Point"}
}