{
  "type": "Feature",
  "properties": {
    "addr:full":"27 Wallasey Road Wallasey Merseyside CH45 4NL",
    "addr:housenumber":"27",
    "addr:postcode":"ch45 4nl",
    "addr:street":"Wallasey Road",
    "iso:country":"GB",
    "sg:address":"27 Wallasey Road",
    "sg:city":"Wallasey",
    "sg:classifiers":[
        {
            "category":"Travel",
            "subcategory":"Travel Agent",
            "type":"Entertainment"
        }
    ],
    "sg:phone":"+44 151 638 5926",
    "sg:postcode":"CH45 4NL",
    "sg:province":"Merseyside",
    "sg:tags":[
        "agency",
        "activity"
    ],
    "wof:name":"Usher Travel Service Ltd",
    "wof:placetype":"venue"
},
  "geometry": {"coordinates":[-3.046432,53.419731],"type":"Point"}
}