{
  "type": "Feature",
  "properties": {
    "addr:full":"Ocean Road South Sunderland Tyne and Wear SR2 9RZ",
    "addr:postcode":"sr2 9rz",
    "addr:street":"Ocean Road South",
    "iso:country":"GB",
    "sg:address":"Ocean Road South",
    "sg:city":"Sunderland",
    "sg:classifiers":[
        {
            "category":"Bars & Pubs",
            "type":"Food & Drink"
        }
    ],
    "sg:phone":"+44 191 567 4432",
    "sg:postcode":"SR2 9RZ",
    "sg:province":"Tyne and Wear",
    "sg:tags":[
        "pubs",
        "inn"
    ],
    "wof:name":"Hendon Grange Hotel",
    "wof:placetype":"venue"
},
  "geometry": {"coordinates":[-1.3652839661,54.8853034973],"type":"Point"}
}