{
  "type": "Feature",
  "properties": {
    "addr:full":"112-114 High Street Irvine North Ayrshire KA12 8AH",
    "addr:housenumber":"112-114",
    "addr:postcode":"ka12 8ah",
    "addr:street":"High Street",
    "iso:country":"GB",
    "sg:address":"112-114 High Street",
    "sg:city":"Irvine",
    "sg:classifiers":[
        {
            "category":"Travel",
            "subcategory":"Hotels & Motels",
            "type":"Entertainment"
        }
    ],
    "sg:phone":"+44 1294 278553",
    "sg:postcode":"KA12 8AH",
    "sg:province":"North Ayrshire",
    "wof:name":"Eglinton Arms Hotel",
    "wof:placetype":"venue"
},
  "geometry": {"coordinates":[-4.667235,55.615055],"type":"Point"}
}