{
  "type": "Feature",
  "properties": {
    "addr:full":"Parish Lane, Pease Pottage Crawley Crawley Surrey RH10 5NY",
    "addr:postcode":"rh10 5ny",
    "addr:street":"Parish Lane;Pottage",
    "iso:country":"GB",
    "sg:address":"Parish Lane, Pease Pottage Crawley",
    "sg:city":"Crawley",
    "sg:classifiers":[
        {
            "category":"Retail",
            "subcategory":"Auto Repair",
            "type":"Services"
        }
    ],
    "sg:phone":"+44 1293 515538",
    "sg:postcode":"RH10 5NY",
    "sg:province":"Surrey",
    "sg:tags":[
        "modification",
        "garage"
    ],
    "wof:name":"The Cottage Garage",
    "wof:placetype":"venue"
},
  "geometry": {"coordinates":[-0.1647630036,51.085357666],"type":"Point"}
}