{
  "type": "Feature",
  "properties": {
    "addr:full":"53-55 Castle Street Bolton Lancashire BL2 1AD",
    "addr:housenumber":"53-55",
    "addr:postcode":"bl2 1ad",
    "addr:street":"Castle Street",
    "iso:country":"GB",
    "sg:address":"53-55 Castle Street",
    "sg:city":"Bolton",
    "sg:classifiers":[
        {
            "category":"Shopping",
            "subcategory":"Bicycles & Sporting Goods",
            "type":"Retail Goods"
        }
    ],
    "sg:postcode":"BL2 1AD",
    "sg:province":"Lancashire",
    "sg:tags":[
        "riding",
        "saddlery",
        "wear"
    ],
    "wof:name":"High Brow Bands",
    "wof:placetype":"venue"
},
  "geometry": {"coordinates":[-2.4179010391,53.5783691406],"type":"Point"}
}