{
  "type": "Feature",
  "properties": {
    "iso:country":"GB",
    "sg:address":"Northbrook Farm, Northbrook Road, Shapwick",
    "sg:city":"Bridgwater",
    "sg:classifiers":[
        {
            "category":"Farming",
            "subcategory":"Livestock Farm",
            "type":"Manufacturing & Wholesale Goods"
        }
    ],
    "sg:postcode":"TA7 9NS",
    "sg:province":"Somerset",
    "sg:tags":[
        "others"
    ],
    "wof:name":"G H Elliott",
    "wof:placetype":"venue"
},
  "geometry": {"coordinates":[-2.8342030048,51.1352043152],"type":"Point"}
}