{
  "type": "Feature",
  "properties": {
    "iso:country":"GB",
    "sg:address":"242a Peverell Park Road",
    "sg:city":"Plymouth",
    "sg:classifiers":[
        {
            "category":"Education",
            "subcategory":"Library",
            "type":"Public Place"
        },
        {
            "category":"Government",
            "subcategory":"Office",
            "type":"Public Place"
        }
    ],
    "sg:phone":"+44 1752 706326",
    "sg:postcode":"PL3 4QF",
    "sg:province":"Devon",
    "sg:tags":[
        "book",
        "local"
    ],
    "wof:name":"Peverell Library",
    "wof:placetype":"venue"
},
  "geometry": {"coordinates":[-4.1453781128,50.3937149048],"type":"Point"}
}