{
  "type": "Feature",
  "properties": {
    "iso:country":"GB",
    "sg:address":"300 Union Street",
    "sg:city":"Torquay",
    "sg:classifiers":[
        {
            "category":"Restaurant",
            "type":"Food & Drink"
        }
    ],
    "sg:phone":"+44 1803 294579",
    "sg:postcode":"TQ2 5QZ",
    "sg:province":"Devon",
    "wof:name":"Costa Fiorita",
    "wof:placetype":"venue"
},
  "geometry": {"coordinates":[-3.5394079685,50.4709129333],"type":"Point"}
}