{
  "type": "Feature",
  "properties": {
    "iso:country":"GB",
    "sg:address":"Meadway, Bramhall",
    "sg:city":"Stockport",
    "sg:classifiers":[
        {
            "category":"Personal",
            "subcategory":"Beauty Salon",
            "type":"Services"
        },
        {
            "category":"Personal",
            "subcategory":"Barber",
            "type":"Services"
        }
    ],
    "sg:phone":"+44 161 439 2194",
    "sg:postcode":"SK7 2DG",
    "sg:province":"Cheshire",
    "sg:tags":[
        "unisex",
        "hairdresser"
    ],
    "wof:name":"Bramhall Hair Studio",
    "wof:placetype":"venue"
},
  "geometry": {"coordinates":[-2.1637411118,53.360622406],"type":"Point"}
}