{
  "type": "Feature",
  "properties": {
    "addr:full":"11 Warren Court, Elgin Road Weybridge Surrey KT13 8ST",
    "addr:housenumber":"11",
    "addr:postcode":"kt13 8st",
    "addr:street":"Warren Court Elgin Road",
    "iso:country":"GB",
    "sg:address":"11 Warren Court, Elgin Road",
    "sg:city":"Weybridge",
    "sg:classifiers":[
        {
            "category":"Building & Trades",
            "subcategory":"Construction",
            "type":"Services"
        }
    ],
    "sg:postcode":"KT13 8ST",
    "sg:province":"Surrey",
    "sg:tags":[
        "builder"
    ],
    "wof:name":"Frontier Contractors Ltd",
    "wof:placetype":"venue"
},
  "geometry": {"coordinates":[-0.459245,51.36504],"type":"Point"}
}