{
  "type": "Feature",
  "properties": {
    "addr:full":"7 Bristol Close, Blacon Chester Cheshire CH1 5AW",
    "addr:housenumber":"7",
    "addr:postcode":"ch1 5aw",
    "addr:street":"Bristol Close",
    "iso:country":"GB",
    "sg:address":"7 Bristol Close, Blacon",
    "sg:city":"Chester",
    "sg:classifiers":[
        {
            "category":"Professional",
            "type":"Services"
        },
        {
            "category":"Personal",
            "type":"Services"
        }
    ],
    "sg:phone":"+44 1244 376759",
    "sg:postcode":"CH1 5AW",
    "sg:province":"Cheshire",
    "sg:tags":[
        "dating",
        "friendship",
        "agency",
        "shopfitters"
    ],
    "wof:name":"Cheshire Interiors",
    "wof:placetype":"venue"
},
  "geometry": {"coordinates":[-2.939511,53.204735],"type":"Point"}
}