{
  "type": "Feature",
  "properties": {
    "iso:country":"GB",
    "sg:address":"99 Blackbyres Rd, Barrhead",
    "sg:city":"Glasgow",
    "sg:classifiers":[
        {
            "category":"Freight",
            "type":"Transportation"
        }
    ],
    "sg:phone":"+44 141 876 9260",
    "sg:postcode":"G78 1TN",
    "sg:province":"East Ayrshire",
    "sg:tags":[
        "haulage",
        "road"
    ],
    "wof:name":"J P George Transport Ltd",
    "wof:placetype":"venue"
},
  "geometry": {"coordinates":[-4.383389,55.810829],"type":"Point"}
}