{
  "type": "Feature",
  "properties": {
    "iso:country":"GB",
    "sg:address":"The Birmingham Post & Mail Building, 28 Colmore Circus, Queensway",
    "sg:city":"Birmingham",
    "sg:classifiers":[
        {
            "category":"Communications",
            "subcategory":"Newspaper",
            "type":"Services"
        }
    ],
    "sg:phone":"+44 121 234 5455",
    "sg:postcode":"B4 6AX",
    "sg:province":"West Midlands",
    "sg:tags":[
        "magazine"
    ],
    "wof:name":"Mirror Group Newspapers",
    "wof:placetype":"venue"
},
  "geometry": {"coordinates":[-1.896766,52.4827],"type":"Point"}
}