{
  "type": "Feature",
  "properties": {
    "addr:full":"Castle Court, 1 The Broadway Dudley West Midlands DY1 4AN",
    "addr:housenumber":"1",
    "addr:postcode":"dy1 4an",
    "addr:street":"Castle;The Broadway",
    "iso:country":"GB",
    "sg:address":"Castle Court, 1 The Broadway",
    "sg:city":"Dudley",
    "sg:classifiers":[
        {
            "category":"Professional",
            "subcategory":"Employment Agencies",
            "type":"Services"
        }
    ],
    "sg:phone":"+44 1384 237775",
    "sg:postcode":"DY1 4AN",
    "sg:province":"West Midlands",
    "sg:tags":[
        "consultant"
    ],
    "wof:name":"Concept Recruitment Ltd.",
    "wof:placetype":"venue"
},
  "geometry": {"coordinates":[-2.08061409,52.5122871399],"type":"Point"}
}