{
  "type": "Feature",
  "properties": {
    "addr:full":"100-102 Market Street, Droylsden Manchester Greater Manchester M43 6DE",
    "addr:housenumber":"100-102",
    "addr:postcode":"m43 6de",
    "addr:street":"Market Street",
    "iso:country":"GB",
    "sg:address":"100-102 Market Street, Droylsden",
    "sg:city":"Manchester",
    "sg:classifiers":[
        {
            "category":"Professional",
            "subcategory":"Lawyer & Legal Services",
            "type":"Services"
        }
    ],
    "sg:phone":"+44 161 371 0011",
    "sg:postcode":"M43 6DE",
    "sg:province":"Greater Manchester",
    "sg:tags":[
        "solicitor"
    ],
    "sg:website":"http://www.claim.co.uk",
    "wof:name":"Berkeley Solicitors",
    "wof:placetype":"venue"
},
  "geometry": {"coordinates":[-2.1455340385,53.4792633057],"type":"Point"}
}