{
  "type": "Feature",
  "properties": {
    "addr:full":"C/o Saint & Company, Poets Walk Penrith Cumbria CA11 7HJ",
    "addr:postcode":"ca11 7hj",
    "addr:street":"C;Poets Walk",
    "iso:country":"GB",
    "sg:address":"C/o Saint & Company, Poets Walk",
    "sg:city":"Penrith",
    "sg:classifiers":[
        {
            "category":"Building & Trades",
            "subcategory":"Cleaning & Sanitation",
            "type":"Services"
        }
    ],
    "sg:postcode":"CA11 7HJ",
    "sg:province":"Cumbria",
    "sg:tags":[
        "commercial"
    ],
    "wof:name":"Contract Cleaning Services (Cumbria) Ltd",
    "wof:placetype":"venue"
},
  "geometry": {"coordinates":[-2.7541201115,54.6637611389],"type":"Point"}
}