{
  "type": "Feature",
  "properties": {
    "iso:country":"GB",
    "sg:address":"94 Crescent Road",
    "sg:city":"Maldon",
    "sg:classifiers":[
        {
            "category":"Professional",
            "subcategory":"Computer Services",
            "type":"Services"
        }
    ],
    "sg:postcode":"CM9 4SN",
    "sg:province":"Essex",
    "sg:tags":[
        "consultant"
    ],
    "wof:name":"Sd Taylor Consultancy Ltd.",
    "wof:placetype":"venue"
},
  "geometry": {"coordinates":[0.675197,51.745113],"type":"Point"}
}