{
  "type": "Feature",
  "properties": {
    "iso:country":"GB",
    "sg:address":"12 Castle Business Village",
    "sg:city":"Hampton",
    "sg:classifiers":[
        {
            "category":"Professional",
            "subcategory":"Engineering",
            "type":"Services"
        }
    ],
    "sg:phone":"+44 20 8977 1011",
    "sg:postcode":"TW12 2BX",
    "sg:province":"Greater London",
    "sg:tags":[
        "precision",
        "engineer"
    ],
    "wof:name":"G & E Compton Ltd.",
    "wof:placetype":"venue"
},
  "geometry": {"coordinates":[-0.3630259931,51.4143371582],"type":"Point"}
}