{
  "type": "Feature",
  "properties": {
    "addr:full":"4 Medway Hailsham East Sussex BN27 3HE",
    "addr:housenumber":"4",
    "addr:postcode":"bn27 3he",
    "addr:street":"Medway Hailsham",
    "iso:country":"GB",
    "sg:address":"4 Medway",
    "sg:city":"Hailsham",
    "sg:classifiers":[
        {
            "category":"Farming",
            "subcategory":"Dairy Farm",
            "type":"Manufacturing & Wholesale Goods"
        }
    ],
    "sg:phone":"+44 1323 841469",
    "sg:postcode":"BN27 3HE",
    "sg:province":"East Sussex",
    "wof:name":"M W Walker",
    "wof:placetype":"venue"
},
  "geometry": {"coordinates":[0.246001,50.873489],"type":"Point"}
}