{
  "type": "Feature",
  "properties": {
    "iso:country":"GB",
    "sg:address":"Granville House, 7 Station Parade",
    "sg:city":"Sevenoaks",
    "sg:classifiers":[
        {
            "category":"Travel",
            "subcategory":"Travel Agent",
            "type":"Entertainment"
        }
    ],
    "sg:phone":"+44 1732 811800",
    "sg:postcode":"TN13 1DL",
    "sg:province":"Kent",
    "wof:name":"Deansgate Associates Ltd.",
    "wof:placetype":"venue"
},
  "geometry": {"coordinates":[0.192939,51.270199],"type":"Point"}
}