{
  "type": "Feature",
  "properties": {
    "addr:full":"36 Blairway Avenue Blackpool Lancashire FY3 8LB",
    "addr:housenumber":"36",
    "addr:postcode":"fy3 8lb",
    "addr:street":"Blairway Avenue",
    "iso:country":"GB",
    "sg:address":"36 Blairway Avenue",
    "sg:city":"Blackpool",
    "sg:classifiers":[
        {
            "category":"Building & Trades",
            "subcategory":"Plumbing",
            "type":"Services"
        }
    ],
    "sg:postcode":"FY3 8LB",
    "sg:province":"Lancashire",
    "sg:tags":[
        "central",
        "heating"
    ],
    "wof:name":"Ian Monteath Central Heating",
    "wof:placetype":"venue"
},
  "geometry": {"coordinates":[-3.0234620571,53.8241462708],"type":"Point"}
}