{
  "type": "Feature",
  "properties": {
    "iso:country":"GB",
    "sg:address":"Richmond Rd, Trafford Pk",
    "sg:city":"Manchester",
    "sg:classifiers":[
        {
            "category":"Building & Trades",
            "subcategory":"Construction",
            "type":"Services"
        }
    ],
    "sg:postcode":"M17 1RL",
    "sg:province":"Cheshire",
    "sg:tags":[
        "roofing"
    ],
    "wof:name":"Broderick (Metals) Ltd",
    "wof:placetype":"venue"
},
  "geometry": {"coordinates":[-2.3310511112,53.4737548828],"type":"Point"}
}