{
  "type": "Feature",
  "properties": {
    "addr:full":"Thornes Lane Wakefield West Yorkshire WF1 5QJ",
    "addr:postcode":"wf1 5qj",
    "addr:street":"Thornes Lane",
    "iso:country":"GB",
    "sg:address":"Thornes Lane",
    "sg:city":"Wakefield",
    "sg:classifiers":[
        {
            "category":"Wholesale",
            "subcategory":"Scrap",
            "type":"Manufacturing & Wholesale Goods"
        }
    ],
    "sg:phone":"+44 1924 378868",
    "sg:postcode":"WF1 5QJ",
    "sg:province":"West Yorkshire",
    "sg:tags":[
        "breaker",
        "dismantlers"
    ],
    "wof:name":"Star Salvage",
    "wof:placetype":"venue"
},
  "geometry": {"coordinates":[-1.49359,53.674721],"type":"Point"}
}