{
  "type": "Feature",
  "properties": {
    "addr:full":"Media Ho, 32 Durford Rd Petersfield Hampshire GU31 4HA",
    "addr:housenumber":"32",
    "addr:postcode":"gu31 4ha",
    "addr:street":"Durford Rd",
    "iso:country":"GB",
    "sg:address":"Media Ho, 32 Durford Rd",
    "sg:city":"Petersfield",
    "sg:classifiers":[
        {
            "category":"Professional",
            "subcategory":"Art Services",
            "type":"Services"
        }
    ],
    "sg:phone":"+44 1730 268597",
    "sg:postcode":"GU31 4HA",
    "sg:province":"Hampshire",
    "sg:tags":[
        "graphic",
        "designer"
    ],
    "wof:name":"Imagemakers",
    "wof:placetype":"venue"
},
  "geometry": {"coordinates":[-0.9136999846,51.0029411316],"type":"Point"}
}