{
  "type": "Feature",
  "properties": {
    "addr:full":"Unit 2, Crow Lane Bury Lancashire BL0 9BR",
    "addr:housenumber":"unit 2",
    "addr:postcode":"bl0 9br",
    "addr:street":"Crow Lane",
    "iso:country":"GB",
    "sg:address":"Unit 2, Crow Lane",
    "sg:city":"Bury",
    "sg:classifiers":[
        {
            "category":"Manufacturing",
            "subcategory":"Glass & Minerals",
            "type":"Manufacturing & Wholesale Goods"
        },
        {
            "category":"Manufacturing",
            "subcategory":"Building Materials",
            "type":"Manufacturing & Wholesale Goods"
        }
    ],
    "sg:phone":"+44 1706 823015",
    "sg:postcode":"BL0 9BR",
    "sg:province":"Lancashire",
    "sg:tags":[
        "supplier",
        "specialist",
        "marble",
        "granite",
        "mnfr"
    ],
    "wof:name":"Xerkon Industries Ltd.",
    "wof:placetype":"venue"
},
  "geometry": {"coordinates":[-2.3163459301,53.6497802734],"type":"Point"}
}