{
  "type": "Feature",
  "properties": {
    "iso:country":"GB",
    "sg:address":"Westmoor Farm, Martin Moor, Metheringham",
    "sg:city":"Lincoln",
    "sg:classifiers":[
        {
            "category":"Farming",
            "subcategory":"Livestock Farm",
            "type":"Manufacturing & Wholesale Goods"
        }
    ],
    "sg:phone":"+44 1526 378270",
    "sg:postcode":"LN4 3BQ",
    "sg:province":"Lincolnshire",
    "sg:tags":[
        "others"
    ],
    "wof:name":"Flintham & Scoley",
    "wof:placetype":"venue"
},
  "geometry": {"coordinates":[-0.3254359961,53.1245384216],"type":"Point"}
}