{
  "type": "Feature",
  "properties": {
    "iso:country":"GB",
    "sg:address":"27 Farrington Drive",
    "sg:city":"Ormskirk",
    "sg:classifiers":[
        {
            "category":"Freight",
            "type":"Transportation"
        }
    ],
    "sg:postcode":"L39 1NB",
    "sg:province":"Lancashire",
    "sg:tags":[
        "haulage",
        "road"
    ],
    "wof:name":"William Baxendale Transport",
    "wof:placetype":"venue"
},
  "geometry": {"coordinates":[-2.8847470284,53.5732727051],"type":"Point"}
}