{
  "type": "Feature",
  "properties": {
    "addr:full":"22 Magdala Road Nottingham Nottinghamshire NG3 5DF",
    "addr:housenumber":"22",
    "addr:postcode":"ng3 5df",
    "addr:street":"Magdala Road",
    "iso:country":"GB",
    "sg:address":"22 Magdala Road",
    "sg:city":"Nottingham",
    "sg:classifiers":[
        {
            "category":"Arena",
            "subcategory":"Sports Club",
            "type":"Entertainment"
        }
    ],
    "sg:phone":"+44 115 969 2120",
    "sg:postcode":"NG3 5DF",
    "sg:province":"Nottinghamshire",
    "wof:name":"Redlodge Magdala Road Ltd.",
    "wof:placetype":"venue"
},
  "geometry": {"coordinates":[-1.149413,52.970188],"type":"Point"}
}