{
  "type": "Feature",
  "properties": {
    "addr:full":"High Road, Leavesden Watford Hertfordshire WD25 7AU",
    "addr:postcode":"wd25 7au",
    "addr:street":"High Road",
    "iso:country":"GB",
    "sg:address":"High Road, Leavesden",
    "sg:city":"Watford",
    "sg:classifiers":[
        {
            "category":"Education",
            "subcategory":"School",
            "type":"Public Place"
        }
    ],
    "sg:phone":"+44 1923 674143",
    "sg:postcode":"WD25 7AU",
    "sg:province":"Hertfordshire",
    "sg:tags":[
        "local",
        "authority"
    ],
    "wof:name":"Leavesden Green Junior School",
    "wof:placetype":"venue"
},
  "geometry": {"coordinates":[-0.4030550122,51.7003746033],"type":"Point"}
}