{
  "type": "Feature",
  "properties": {
    "addr:full":"Hollands Way East Grinstead East Sussex RH19 3EN",
    "addr:postcode":"rh19 3en",
    "addr:street":"Hollands Way",
    "iso:country":"GB",
    "sg:address":"Hollands Way",
    "sg:city":"East Grinstead",
    "sg:classifiers":[
        {
            "category":"Shopping",
            "subcategory":"Stationery & Office Supplies",
            "type":"Retail Goods"
        },
        {
            "category":"Government",
            "subcategory":"Post Office",
            "type":"Public Place"
        }
    ],
    "sg:phone":"+44 1342 321969",
    "sg:postcode":"RH19 3EN",
    "sg:province":"East Sussex",
    "wof:name":"Stone Quarry Sub Post Office",
    "wof:placetype":"venue"
},
  "geometry": {"coordinates":[0.0031320001,51.1383705139],"type":"Point"}
}