{
  "type": "Feature",
  "properties": {
    "iso:country":"GB",
    "sg:address":"Curtis House, South Way, Walworth Industrial Estate",
    "sg:city":"Andover",
    "sg:classifiers":[
        {
            "category":"Building & Trades",
            "subcategory":"Locksmith",
            "type":"Services"
        }
    ],
    "sg:phone":"+44 1225 818280",
    "sg:postcode":"SP10 5HJ",
    "sg:province":"Hampshire",
    "sg:tags":[
        "cutting",
        "key"
    ],
    "wof:name":"Curtis Industries (U K) Ltd.",
    "wof:placetype":"venue"
},
  "geometry": {"coordinates":[-1.457255,51.216854],"type":"Point"}
}