{
  "type": "Feature",
  "properties": {
    "iso:country":"GB",
    "sg:address":"21 Park Road, Milngavie",
    "sg:city":"Glasgow",
    "sg:classifiers":[
        {
            "category":"Professional",
            "subcategory":"Lawyer & Legal Services",
            "type":"Services"
        }
    ],
    "sg:phone":"+44 141 956 5454",
    "sg:postcode":"G62 6PJ",
    "sg:province":"East Dunbartonshire",
    "sg:tags":[
        "solicitor"
    ],
    "wof:name":"Campbell Riddell Breeze Paterson",
    "wof:placetype":"venue"
},
  "geometry": {"coordinates":[-4.319406,55.939938],"type":"Point"}
}