{
  "type": "Feature",
  "properties": {
    "iso:country":"GB",
    "sg:address":"34-36 Westlode St",
    "sg:city":"Spalding",
    "sg:classifiers":[
        {
            "category":"Travel",
            "subcategory":"Hostel",
            "type":"Entertainment"
        }
    ],
    "sg:phone":"+44 1775 769065",
    "sg:postcode":"PE11 2AF",
    "sg:province":"Lincolnshire",
    "wof:name":"Westlode Street Hostel",
    "wof:placetype":"venue"
},
  "geometry": {"coordinates":[-0.1481470019,52.789276123],"type":"Point"}
}