{
  "type": "Feature",
  "properties": {
    "iso:country":"GB",
    "sg:address":"The Kiln, New House Farm",
    "sg:city":"Tenbury Wells",
    "sg:classifiers":[
        {
            "category":"Retail",
            "subcategory":"Auto Repair",
            "type":"Services"
        }
    ],
    "sg:phone":"+44 1568 750245",
    "sg:postcode":"WR15 8TW",
    "sg:province":"Herefordshire",
    "sg:tags":[
        "modification",
        "garage"
    ],
    "wof:name":"S J Motors",
    "wof:placetype":"venue"
},
  "geometry": {"coordinates":[-2.594179,52.312584],"type":"Point"}
}