{
  "type": "Feature",
  "properties": {
    "addr:full":"St Runwalds Street Colchester Essex CO1 1HF",
    "addr:postcode":"co1 1hf",
    "addr:street":"Runwalds Street",
    "iso:country":"GB",
    "sg:address":"St Runwalds Street",
    "sg:city":"Colchester",
    "sg:classifiers":[
        {
            "category":"Communications",
            "type":"Services"
        }
    ],
    "sg:phone":"+44 1206 560255",
    "sg:postcode":"CO1 1HF",
    "sg:province":"Essex",
    "sg:tags":[
        "audio-visual"
    ],
    "wof:name":"Signals Essex Media Centre Ltd.",
    "wof:placetype":"venue"
},
  "geometry": {"coordinates":[0.8985990286,51.8902168274],"type":"Point"}
}