{
  "type": "Feature",
  "properties": {
    "addr:full":"Unit 5, Mudlands Industrial Estate, Rainham Essex RM13 8RH",
    "addr:housenumber":"unit 5",
    "addr:postcode":"rm13 8rh",
    "addr:street":"Mudlands Industrial Estate",
    "iso:country":"GB",
    "sg:address":"Unit 5, Mudlands Industrial Estate,",
    "sg:city":"Rainham",
    "sg:classifiers":[
        {
            "category":"Recreation",
            "subcategory":"Fishing",
            "type":"Entertainment"
        }
    ],
    "sg:phone":"+44 1708 630921",
    "sg:postcode":"RM13 8RH",
    "sg:province":"Essex",
    "sg:tags":[
        "equipment",
        "angling"
    ],
    "wof:name":"Colmic Uk",
    "wof:placetype":"venue"
},
  "geometry": {"coordinates":[0.1904260069,51.5179138184],"type":"Point"}
}