{
  "type": "Feature",
  "properties": {
    "iso:country":"GB",
    "sg:address":"119 Westgate Street",
    "sg:city":"Gloucester",
    "sg:classifiers":[
        {
            "category":"Shopping",
            "subcategory":"News",
            "type":"Retail Goods"
        }
    ],
    "sg:phone":"+44 1452 524378",
    "sg:postcode":"GL1 2PG",
    "sg:province":"Gloucestershire",
    "sg:tags":[
        "newsagent"
    ],
    "wof:name":"Stephen Keeling",
    "wof:placetype":"venue"
},
  "geometry": {"coordinates":[-2.2509539127,51.8675003052],"type":"Point"}
}