{
  "type": "Feature",
  "properties": {
    "addr:full":"Common Lane, Marton Winsford Cheshire CW7 2QF",
    "addr:postcode":"cw7 2qf",
    "addr:street":"Common Lane",
    "iso:country":"GB",
    "sg:address":"Common Lane, Marton",
    "sg:city":"Winsford",
    "sg:classifiers":[
        {
            "category":"Sports & Exercise",
            "subcategory":"Stables",
            "type":"Entertainment"
        }
    ],
    "sg:phone":"+44 1606 888543",
    "sg:postcode":"CW7 2QF",
    "sg:province":"Cheshire",
    "sg:tags":[
        "education",
        "equestrian"
    ],
    "wof:name":"Oak Tree Riding Centre",
    "wof:placetype":"venue"
},
  "geometry": {"coordinates":[-2.5625190735,53.2041091919],"type":"Point"}
}