{
  "type": "Feature",
  "properties": {
    "iso:country":"GB",
    "sg:address":"5 St Margarets St",
    "sg:city":"Bradford On Avon",
    "sg:classifiers":[
        {
            "category":"Professional",
            "subcategory":"Management & Consulting",
            "type":"Services"
        }
    ],
    "sg:phone":"+44 1225 868869",
    "sg:postcode":"BA15 1DA",
    "sg:province":"Wiltshire",
    "sg:tags":[
        "environmental",
        "consultant"
    ],
    "wof:name":"Project Research Enviromental Consultants Ltd",
    "wof:placetype":"venue"
},
  "geometry": {"coordinates":[-2.251847,51.346302],"type":"Point"}
}