{
  "type": "Feature",
  "properties": {
    "iso:country":"GB",
    "sg:address":"65 Swakeleys Road",
    "sg:city":"Uxbridge",
    "sg:classifiers":[
        {
            "category":"Insurance",
            "subcategory":"Insurance Agent",
            "type":"Services"
        },
        {
            "category":"Banks & Credit Unions",
            "subcategory":"Financial Services",
            "type":"Services"
        }
    ],
    "sg:phone":"+44 1895 637121",
    "sg:postcode":"UB10 8DQ",
    "sg:province":"Greater London",
    "sg:tags":[
        "consultant",
        "broker"
    ],
    "wof:name":"Neville Birch & Co.",
    "wof:placetype":"venue"
},
  "geometry": {"coordinates":[-0.4471479952,51.565284729],"type":"Point"}
}