{
  "type": "Feature",
  "properties": {
    "addr:full":"Redbeck Mill, Wharncliffe Road Shipley West Yorkshire BD18 2AW",
    "addr:postcode":"bd18 2aw",
    "addr:street":"Wharncliffe Road",
    "iso:country":"GB",
    "sg:address":"Redbeck Mill, Wharncliffe Road",
    "sg:city":"Shipley",
    "sg:classifiers":[
        {
            "category":"Professional",
            "subcategory":"Printing & Photocopies",
            "type":"Services"
        }
    ],
    "sg:phone":"+44 1274 530280",
    "sg:postcode":"BD18 2AW",
    "sg:province":"West Yorkshire",
    "sg:tags":[
        "embroiderer"
    ],
    "wof:name":"Perry P Poucher",
    "wof:placetype":"venue"
},
  "geometry": {"coordinates":[-1.7743190527,53.8254432678],"type":"Point"}
}