{
  "type": "Feature",
  "properties": {
    "addr:full":"West Newham Farm, Milbourne Newcastle-upon-tyne Northumberland NE20 0DJ",
    "addr:postcode":"ne20 0dj",
    "addr:street":"West",
    "iso:country":"GB",
    "sg:address":"West Newham Farm, Milbourne",
    "sg:city":"Newcastle-upon-tyne",
    "sg:classifiers":[
        {
            "category":"Farming",
            "subcategory":"Livestock Farm",
            "type":"Manufacturing & Wholesale Goods"
        }
    ],
    "sg:postcode":"NE20 0DJ",
    "sg:province":"Northumberland",
    "sg:tags":[
        "others"
    ],
    "wof:name":"Edward Moffitt & Son",
    "wof:placetype":"venue"
},
  "geometry": {"coordinates":[-1.817133,55.072178],"type":"Point"}
}