{
  "type": "Feature",
  "properties": {
    "iso:country":"GB",
    "sg:address":"183-184 High Street, Deritend",
    "sg:city":"Birmingham",
    "sg:classifiers":[
        {
            "category":"Home & Garden",
            "subcategory":"Building Materials",
            "type":"Retail Goods"
        }
    ],
    "sg:phone":"+44 121 772 2694",
    "sg:postcode":"B12 0LH",
    "sg:province":"West Midlands",
    "sg:tags":[
        "system",
        "staircase"
    ],
    "wof:name":"William Hawkes (Holdings) Ltd.",
    "wof:placetype":"venue"
},
  "geometry": {"coordinates":[-1.886859,52.475124],"type":"Point"}
}