{
  "type": "Feature",
  "properties": {
    "iso:country":"GB",
    "sg:address":"11 Muriel Clo, Hadleigh",
    "sg:city":"Ipswich",
    "sg:classifiers":[
        {
            "category":"Arena",
            "subcategory":"Sports Club",
            "type":"Entertainment"
        }
    ],
    "sg:postcode":"IP7 5NH",
    "sg:province":"Suffolk",
    "sg:tags":[
        "ground"
    ],
    "wof:name":"Tirrel,Mike,",
    "wof:placetype":"venue"
},
  "geometry": {"coordinates":[0.964957,52.044781],"type":"Point"}
}