{
  "type": "Feature",
  "properties": {
    "iso:country":"GB",
    "sg:address":"Unit 12/16, Pitcliffe Way",
    "sg:city":"Bradford",
    "sg:classifiers":[
        {
            "category":"Manufacturing",
            "subcategory":"Wood Products",
            "type":"Manufacturing & Wholesale Goods"
        },
        {
            "category":"Farming",
            "subcategory":"Farm & Veterinary Services",
            "type":"Manufacturing & Wholesale Goods"
        }
    ],
    "sg:phone":"+44 1274 720019",
    "sg:postcode":"BD5 7SG",
    "sg:province":"West Yorkshire",
    "sg:tags":[
        "packaging",
        "crate",
        "packagers",
        "pallets"
    ],
    "sg:website":"http://www.mailway.co.uk",
    "wof:name":"Mailway Packaging Solutions Ltd.",
    "wof:placetype":"venue"
},
  "geometry": {"coordinates":[-1.750049,53.784061],"type":"Point"}
}