{
  "type": "Feature",
  "properties": {
    "addr:full":"Unit 2, Four Squire Drive, Brynmenyn Industrial Estate Bridgend Bridgend CF32 9TD",
    "addr:housenumber":"unit 2",
    "addr:postcode":"cf32 9td",
    "addr:street":"Four Squire Drive Brynmenyn Industrial Estate",
    "iso:country":"GB",
    "sg:address":"Unit 2, Four Squire Drive, Brynmenyn Industrial Estate",
    "sg:city":"Bridgend",
    "sg:classifiers":[
        {
            "category":"Building & Trades",
            "subcategory":"Construction",
            "type":"Services"
        }
    ],
    "sg:phone":"+44 1656 722500",
    "sg:postcode":"CF32 9TD",
    "sg:province":"Bridgend",
    "sg:tags":[
        "joiner",
        "carpenter"
    ],
    "wof:name":"Mel Wake Joinery Ltd.",
    "wof:placetype":"venue"
},
  "geometry": {"coordinates":[-3.5817439556,51.5513801575],"type":"Point"}
}