{
  "type": "Feature",
  "properties": {
    "addr:full":"1st Floor, 18 Queens Road Southend-on-sea Essex SS1 1LU",
    "addr:housenumber":"18",
    "addr:postcode":"ss1 1lu",
    "addr:street":"Queens Road",
    "iso:country":"GB",
    "sg:address":"1st Floor, 18 Queens Road",
    "sg:city":"Southend-on-sea",
    "sg:classifiers":[
        {
            "category":"Manufacturing",
            "subcategory":"Jewelry",
            "type":"Manufacturing & Wholesale Goods"
        }
    ],
    "sg:phone":"+44 1702 436864",
    "sg:postcode":"SS1 1LU",
    "sg:province":"Essex",
    "sg:tags":[
        "repair",
        "jewellery"
    ],
    "wof:name":"David J Shorter Jewellery",
    "wof:placetype":"venue"
},
  "geometry": {"coordinates":[0.710697,51.539635],"type":"Point"}
}