{
  "type": "Feature",
  "properties": {
    "addr:full":"Roundhouse Woodbridge Suffolk IP12 1EB",
    "addr:postcode":"ip12 1eb",
    "iso:country":"GB",
    "sg:address":"Roundhouse",
    "sg:city":"Woodbridge",
    "sg:classifiers":[
        {
            "category":"Autos & Motor Vehicles",
            "subcategory":"Boat Sales",
            "type":"Retail Goods"
        }
    ],
    "sg:phone":"+44 1394 383222",
    "sg:postcode":"IP12 1EB",
    "sg:province":"Suffolk",
    "sg:tags":[
        "surveyor",
        "yacht"
    ],
    "wof:name":"Ward & McKenzie (Yacht Consultants) Ltd.",
    "wof:placetype":"venue"
},
  "geometry": {"coordinates":[1.32539,52.10545],"type":"Point"}
}