{
  "type": "Feature",
  "properties": {
    "addr:full":"50 High Street Hastings East Sussex TN34 3EN",
    "addr:housenumber":"50",
    "addr:postcode":"tn34 3en",
    "addr:street":"High Street",
    "iso:country":"GB",
    "sg:address":"50 High Street",
    "sg:city":"Hastings",
    "sg:classifiers":[
        {
            "category":"Shopping",
            "subcategory":"Pharmacy",
            "type":"Retail Goods"
        }
    ],
    "sg:phone":"+44 1424 465408",
    "sg:postcode":"TN34 3EN",
    "sg:province":"East Sussex",
    "sg:tags":[
        "medicine",
        "therapy"
    ],
    "wof:name":"Bio-Five-O",
    "wof:placetype":"venue"
},
  "geometry": {"coordinates":[0.591497,50.857132],"type":"Point"}
}