{
  "type": "Feature",
  "properties": {
    "iso:country":"GB",
    "sg:address":"10 Napier Avenue",
    "sg:city":"Blackpool",
    "sg:classifiers":[
        {
            "category":"Travel",
            "subcategory":"Hotels & Motels",
            "type":"Entertainment"
        }
    ],
    "sg:postcode":"FY4 1PA",
    "sg:province":"Lancashire",
    "wof:name":"The Monica Hotel",
    "wof:placetype":"venue"
},
  "geometry": {"coordinates":[-3.055431,53.787163],"type":"Point"}
}