{
  "type": "Feature",
  "properties": {
    "iso:country":"GB",
    "sg:address":"Hill Top House, Palace Lane, Beaulieu",
    "sg:city":"Brockenhurst",
    "sg:classifiers":[
        {
            "category":"Professional",
            "subcategory":"Lawyer & Legal Services",
            "type":"Services"
        }
    ],
    "sg:phone":"+44 1590 612731",
    "sg:postcode":"SO42 7YG",
    "sg:province":"Hampshire",
    "sg:tags":[
        "solicitor"
    ],
    "wof:name":"Brett Johnson",
    "wof:placetype":"venue"
},
  "geometry": {"coordinates":[-1.5720039606,50.8186416626],"type":"Point"}
}