{
  "type": "Feature",
  "properties": {
    "addr:full":"Albion Works, 1a Pool Street, Blakenhall Wolverhampton West Midlands WV2 4HN",
    "addr:housenumber":"1a",
    "addr:postcode":"wv2 4hn",
    "addr:street":"Pool Street",
    "iso:country":"GB",
    "sg:address":"Albion Works, 1a Pool Street, Blakenhall",
    "sg:city":"Wolverhampton",
    "sg:classifiers":[
        {
            "category":"Shopping",
            "subcategory":"Clothing, Apparel, & Fashions",
            "type":"Retail Goods"
        }
    ],
    "sg:phone":"+44 1902 713205",
    "sg:postcode":"WV2 4HN",
    "sg:province":"West Midlands",
    "sg:tags":[
        "clothing",
        "fabric"
    ],
    "wof:name":"Style Wear Clothing Ltd.",
    "wof:placetype":"venue"
},
  "geometry": {"coordinates":[-2.1305799484,52.5775299072],"type":"Point"}
}