{
  "type": "Feature",
  "properties": {
    "addr:full":"Charmouth Road Bath Bath and North East Somerset BA1 3LL",
    "addr:postcode":"ba1 3ll",
    "addr:street":"Charmouth Road",
    "iso:country":"GB",
    "sg:address":"Charmouth Road",
    "sg:city":"Bath",
    "sg:classifiers":[
        {
            "category":"Education",
            "subcategory":"School",
            "type":"Public Place"
        },
        {
            "category":"Government",
            "subcategory":"Office",
            "type":"Public Place"
        }
    ],
    "sg:phone":"+44 1225 421675",
    "sg:postcode":"BA1 3LL",
    "sg:province":"Bath and North East Somerset",
    "sg:tags":[
        "local",
        "authority"
    ],
    "wof:name":"Newbridge Junior School",
    "wof:placetype":"venue"
},
  "geometry": {"coordinates":[-2.3949038982,51.385799408],"type":"Point"}
}