{
  "type": "Feature",
  "properties": {
    "addr:full":"18 Barn Close Seaford East Sussex BN25 3EW",
    "addr:housenumber":"18",
    "addr:postcode":"bn25 3ew",
    "addr:street":"Barn Close",
    "iso:country":"GB",
    "sg:address":"18 Barn Close",
    "sg:city":"Seaford",
    "sg:classifiers":[
        {
            "category":"Home & Garden",
            "subcategory":"Building Materials",
            "type":"Retail Goods"
        }
    ],
    "sg:phone":"+44 1323 899169",
    "sg:postcode":"BN25 3EW",
    "sg:province":"East Sussex",
    "sg:tags":[
        "paint",
        "spraying"
    ],
    "wof:name":"Bob Tec",
    "wof:placetype":"venue"
},
  "geometry": {"coordinates":[0.119069,50.785786],"type":"Point"}
}