{
  "type": "Feature",
  "properties": {
    "iso:country":"GB",
    "sg:address":"40 Eastbourne Terr",
    "sg:city":"Bayswater",
    "sg:classifiers":[
        {
            "category":"Organizations",
            "subcategory":"Non-profit Organization",
            "type":"Services"
        }
    ],
    "sg:phone":"+44 20 7725 2606",
    "sg:postcode":"W2 3QR",
    "sg:province":"Greater London",
    "sg:tags":[
        "organisation",
        "voluntary",
        "charity"
    ],
    "wof:name":"Foundation For Womens Health Research & Developement",
    "wof:placetype":"venue"
},
  "geometry": {"coordinates":[-0.176621,51.515305],"type":"Point"}
}