{
  "type": "Feature",
  "properties": {
    "addr:full":"Boxtree Farm, Lupton Carnforth Cumbria LA6 2PR",
    "addr:postcode":"la6 2pr",
    "iso:country":"GB",
    "sg:address":"Boxtree Farm, Lupton",
    "sg:city":"Carnforth",
    "sg:classifiers":[
        {
            "category":"Farming",
            "subcategory":"Dairy Farm",
            "type":"Manufacturing & Wholesale Goods"
        }
    ],
    "sg:postcode":"LA6 2PR",
    "sg:province":"Cumbria",
    "wof:name":"Davison,Colin,",
    "wof:placetype":"venue"
},
  "geometry": {"coordinates":[-2.6902410984,54.2270584106],"type":"Point"}
}