{
  "type": "Feature",
  "properties": {
    "iso:country":"GB",
    "sg:address":"21 Millbrook",
    "sg:city":"West Malling",
    "sg:classifiers":[
        {
            "category":"Retail",
            "subcategory":"Auto Repair",
            "type":"Services"
        }
    ],
    "sg:postcode":"ME19 5QJ",
    "sg:province":"Kent",
    "sg:tags":[
        "modification",
        "garage"
    ],
    "wof:name":"Darryl Smith Mobile Vehicle Repairs",
    "wof:placetype":"venue"
},
  "geometry": {"coordinates":[0.420286,51.299053],"type":"Point"}
}