{
  "type": "Feature",
  "properties": {
    "iso:country":"GB",
    "sg:address":"38 Tenterton Avenue",
    "sg:city":"Southampton",
    "sg:classifiers":[
        {
            "category":"Building & Trades",
            "subcategory":"Plumbing",
            "type":"Services"
        }
    ],
    "sg:postcode":"SO19 9HT",
    "sg:province":"Hampshire",
    "sg:tags":[
        "heating"
    ],
    "wof:name":"Gary P Barnett",
    "wof:placetype":"venue"
},
  "geometry": {"coordinates":[-1.3513350487,50.8898620605],"type":"Point"}
}