{
  "type": "Feature",
  "properties": {
    "addr:full":"Unit 7 Kinnaird Park Edinburgh City of Edinburgh EH15 3RD",
    "addr:housenumber":"unit 7",
    "addr:postcode":"eh15 3rd",
    "addr:street":"Kinnaird Park Edinburgh",
    "iso:country":"GB",
    "sg:address":"Unit 7 Kinnaird Park",
    "sg:city":"Edinburgh",
    "sg:classifiers":[
        {
            "category":"Sports & Exercise",
            "subcategory":"Sports Center",
            "type":"Entertainment"
        }
    ],
    "sg:phone":"+44 131 657 5585",
    "sg:postcode":"EH15 3RD",
    "sg:province":"City of Edinburgh",
    "sg:tags":[
        "shop",
        "good"
    ],
    "wof:name":"J J B Sports Plc",
    "wof:placetype":"venue"
},
  "geometry": {"coordinates":[-3.1071,55.933571],"type":"Point"}
}