{
  "type": "Feature",
  "properties": {
    "addr:full":"2 Shore Road, Airth Falkirk Falkirk FK2 8LH",
    "addr:housenumber":"2",
    "addr:postcode":"fk2 8lh",
    "addr:street":"Shore Road",
    "iso:country":"GB",
    "sg:address":"2 Shore Road, Airth",
    "sg:city":"Falkirk",
    "sg:classifiers":[
        {
            "category":"Food & Beverages",
            "subcategory":"Fruits & Vegetables",
            "type":"Retail Goods"
        }
    ],
    "sg:postcode":"FK2 8LH",
    "sg:province":"Falkirk",
    "sg:tags":[
        "greengrocer"
    ],
    "wof:name":"The Corner Shop",
    "wof:placetype":"venue"
},
  "geometry": {"coordinates":[-3.770009,56.06897],"type":"Point"}
}