{
  "type": "Feature",
  "properties": {
    "iso:country":"GB",
    "sg:address":"19 Whitegate Road, Brightlingsea",
    "sg:city":"Colchester",
    "sg:classifiers":[
        {
            "category":"Retail",
            "subcategory":"Driving School",
            "type":"Services"
        }
    ],
    "sg:phone":"+44 1206 304345",
    "sg:postcode":"CO7 0EU",
    "sg:province":"Essex",
    "wof:name":"S M J's Driving School",
    "wof:placetype":"venue"
},
  "geometry": {"coordinates":[1.0340590477,51.8109016418],"type":"Point"}
}