{
  "type": "Feature",
  "properties": {
    "iso:country":"GB",
    "sg:address":"Brighton Hill Retail Park",
    "sg:city":"Basingstoke",
    "sg:classifiers":[
        {
            "category":"Food & Beverages",
            "subcategory":"Bakery",
            "type":"Retail Goods"
        }
    ],
    "sg:phone":"+44 1256 346536",
    "sg:postcode":"RG22 6HT",
    "sg:province":"Hampshire",
    "sg:tags":[
        "pizza"
    ],
    "wof:name":"Pizza Hut",
    "wof:placetype":"venue"
},
  "geometry": {"coordinates":[-1.1085189581,51.2518692017],"type":"Point"}
}