{
  "type": "Feature",
  "properties": {
    "addr:full":"57a Wimpole St West End Hampshire W1M 7DF",
    "addr:housenumber":"57a",
    "addr:postcode":"w1m 7df",
    "addr:street":"Wimpole St",
    "iso:country":"GB",
    "sg:address":"57a Wimpole St",
    "sg:city":"West End",
    "sg:classifiers":[
        {
            "category":"Health Services",
            "subcategory":"Dentist",
            "type":"Services"
        }
    ],
    "sg:phone":"+44 20 7224 2160",
    "sg:postcode":"W1M 7DF",
    "sg:province":"Hampshire",
    "wof:name":"O Bahat",
    "wof:placetype":"venue"
},
  "geometry": {"coordinates":[-0.14888,51.519203],"type":"Point"}
}