{
  "type": "Feature",
  "properties": {
    "addr:full":"Queen Marys College, Cliddesden Road Basingstoke Hampshire RG21 3HF",
    "addr:postcode":"rg21 3hf",
    "addr:street":"Cliddesden Road",
    "iso:country":"GB",
    "sg:address":"Queen Marys College, Cliddesden Road",
    "sg:city":"Basingstoke",
    "sg:classifiers":[
        {
            "category":"Education",
            "subcategory":"University",
            "type":"Public Place"
        }
    ],
    "sg:phone":"+44 1256 417500",
    "sg:postcode":"RG21 3HF",
    "sg:province":"Hampshire",
    "sg:tags":[
        "higher"
    ],
    "wof:name":"The Shrubbery Pre-School",
    "wof:placetype":"venue"
},
  "geometry": {"coordinates":[-1.083088994,51.2624435425],"type":"Point"}
}