{
  "type": "Feature",
  "properties": {
    "iso:country":"GB",
    "sg:address":"Crocketts Lane",
    "sg:city":"Smethwick",
    "sg:classifiers":[
        {
            "category":"Education",
            "subcategory":"School",
            "type":"Public Place"
        }
    ],
    "sg:phone":"+44 121 558 1659",
    "sg:postcode":"B66 3BX",
    "sg:province":"West Midlands",
    "sg:tags":[
        "local",
        "authority"
    ],
    "wof:name":"SANDWELL METROPOLITAN BOROUGH COUNCIL",
    "wof:placetype":"venue"
},
  "geometry": {"coordinates":[-1.965162,52.495354],"type":"Point"}
}