{
  "type": "Feature",
  "properties": {
    "addr:full":"6/7 George St Stroud Gloucestershire GL5 3DX",
    "addr:housenumber":"6 / 7",
    "addr:postcode":"gl5 3dx",
    "addr:street":"George St",
    "iso:country":"GB",
    "sg:address":"6/7 George St",
    "sg:city":"Stroud",
    "sg:classifiers":[
        {
            "category":"Shopping",
            "subcategory":"Thrift Store",
            "type":"Retail Goods"
        }
    ],
    "sg:phone":"+44 1453 764934",
    "sg:postcode":"GL5 3DX",
    "sg:province":"Gloucestershire",
    "sg:tags":[
        "shop",
        "charity"
    ],
    "wof:name":"Sue Ryder Foundation",
    "wof:placetype":"venue"
},
  "geometry": {"coordinates":[-2.217703,51.745255],"type":"Point"}
}