{
  "type": "Feature",
  "properties": {
    "addr:full":"Shipwright House, Trefusis Road, Flushing Falmouth Cornwall TR11 5TZ",
    "addr:postcode":"tr11 5tz",
    "addr:street":"Trefusis Road",
    "iso:country":"GB",
    "sg:address":"Shipwright House, Trefusis Road, Flushing",
    "sg:city":"Falmouth",
    "sg:classifiers":[
        {
            "category":"Organizations",
            "subcategory":"Community Association",
            "type":"Services"
        }
    ],
    "sg:postcode":"TR11 5TZ",
    "sg:province":"Cornwall",
    "sg:tags":[
        "relation",
        "public"
    ],
    "wof:name":"Paul Armiger",
    "wof:placetype":"venue"
},
  "geometry": {"coordinates":[-5.061471,50.163044],"type":"Point"}
}