{
  "type": "Feature",
  "properties": {
    "iso:country":"GB",
    "sg:address":"Manner Road",
    "sg:city":"Atherstone",
    "sg:classifiers":[
        {
            "category":"Home & Garden",
            "subcategory":"Carpets & Floor Coverings",
            "type":"Retail Goods"
        }
    ],
    "sg:postcode":"CV9 1QY",
    "sg:province":"Leicestershire",
    "sg:tags":[
        "carpets",
        "rug",
        "matting"
    ],
    "wof:name":"Carpets Curtains Interiors Ltd.",
    "wof:placetype":"venue"
},
  "geometry": {"coordinates":[-1.5392999649,52.5695877075],"type":"Point"}
}