{
  "type": "Feature",
  "properties": {
    "addr:full":"Tullich Road Ballater Aberdeenshire AB35 5QH",
    "addr:postcode":"ab35 5qh",
    "addr:street":"Tullich Road",
    "iso:country":"GB",
    "sg:address":"Tullich Road",
    "sg:city":"Ballater",
    "sg:classifiers":[
        {
            "category":"Shopping",
            "subcategory":"Clothing, Apparel, & Fashions",
            "type":"Retail Goods"
        }
    ],
    "sg:phone":"+44 1339 755496",
    "sg:postcode":"AB35 5QH",
    "sg:province":"Aberdeenshire",
    "sg:tags":[
        "shop"
    ],
    "wof:name":"McEwens Country Shops",
    "wof:placetype":"venue"
},
  "geometry": {"coordinates":[-3.034705,57.049564],"type":"Point"}
}