{
  "type": "Feature",
  "properties": {
    "addr:full":"6 Wargrave Road, Twyford Reading Berkshire RG10 9PG",
    "addr:housenumber":"6",
    "addr:postcode":"rg10 9pg",
    "addr:street":"Wargrave Road",
    "iso:country":"GB",
    "sg:address":"6 Wargrave Road, Twyford",
    "sg:city":"Reading",
    "sg:classifiers":[
        {
            "category":"Professional",
            "subcategory":"Engineering",
            "type":"Services"
        },
        {
            "category":"Building & Trades",
            "subcategory":"Construction",
            "type":"Services"
        }
    ],
    "sg:phone":"+44 118 934 4333",
    "sg:postcode":"RG10 9PG",
    "sg:province":"Berkshire",
    "sg:tags":[
        "excavation",
        "civil",
        "engineer",
        "groundwork",
        "contractor"
    ],
    "wof:name":"Coral Construction Ltd",
    "wof:placetype":"venue"
},
  "geometry": {"coordinates":[-0.8669419885,51.4777145386],"type":"Point"}
}