{
  "type": "Feature",
  "properties": {
    "addr:full":"The Old Mill, Allington Lane Grantham Leicestershire NG32 2JR",
    "addr:postcode":"ng32 2jr",
    "addr:street":"Allington Lane",
    "iso:country":"GB",
    "sg:address":"The Old Mill, Allington Lane",
    "sg:city":"Grantham",
    "sg:classifiers":[
        {
            "category":"Military Area",
            "subcategory":"Army Base",
            "type":"Public Place"
        },
        {
            "category":"Shopping",
            "type":"Retail Goods"
        }
    ],
    "sg:phone":"+44 1400 281384",
    "sg:postcode":"NG32 2JR",
    "sg:province":"Leicestershire",
    "sg:tags":[
        "supplier",
        "bag",
        "-",
        "various",
        "type"
    ],
    "sg:website":"http://www.mandbsacks.com",
    "wof:name":"M & B Sacks Ltd",
    "wof:placetype":"venue"
},
  "geometry": {"coordinates":[-0.7229750156,52.9524307251],"type":"Point"}
}