{
  "type": "Feature",
  "properties": {
    "iso:country":"GB",
    "sg:address":"Barrington Clo",
    "sg:city":"Swindon",
    "sg:classifiers":[
        {
            "category":"Shopping",
            "subcategory":"Department Store",
            "type":"Retail Goods"
        }
    ],
    "sg:phone":"+44 1793 533707",
    "sg:postcode":"SN3 6HF",
    "sg:province":"Wiltshire",
    "wof:name":"M & W Ltd",
    "wof:placetype":"venue"
},
  "geometry": {"coordinates":[-1.728552,51.546452],"type":"Point"}
}