{
  "type": "Feature",
  "properties": {
    "iso:country":"GB",
    "sg:address":"Private Road 5, Colwick Industrial Estate",
    "sg:city":"Nottingham",
    "sg:classifiers":[
        {
            "category":"Retail",
            "subcategory":"Repair Shop",
            "type":"Services"
        }
    ],
    "sg:phone":"+44 115 987 9686",
    "sg:postcode":"NG4 2JU",
    "sg:province":"Nottinghamshire",
    "sg:tags":[
        "equipment",
        "catering"
    ],
    "wof:name":"Midland Catering Engineers",
    "wof:placetype":"venue"
},
  "geometry": {"coordinates":[-1.070177,52.956909],"type":"Point"}
}