{
  "type": "Feature",
  "properties": {
    "addr:full":"4 Weston Yard Guildford Surrey GU5 9AF",
    "addr:housenumber":"4",
    "addr:postcode":"gu5 9af",
    "addr:street":"Weston Yard",
    "iso:country":"GB",
    "sg:address":"4 Weston Yard",
    "sg:city":"Guildford",
    "sg:classifiers":[
        {
            "category":"Building & Trades",
            "subcategory":"Plumbing",
            "type":"Services"
        }
    ],
    "sg:phone":"+44 1483 202851",
    "sg:postcode":"GU5 9AF",
    "sg:province":"Surrey",
    "sg:tags":[
        "merchant",
        "plumbers'"
    ],
    "wof:name":"Duffen & Duffen Ltd",
    "wof:placetype":"venue"
},
  "geometry": {"coordinates":[-0.5891739726,51.248210907],"type":"Point"}
}