{
  "type": "Feature",
  "properties": {
    "iso:country":"GB",
    "sg:address":"2 Commerce Square, The Lace Market",
    "sg:city":"Nottingham",
    "sg:classifiers":[
        {
            "category":"Real Estate",
            "subcategory":"Architect",
            "type":"Services"
        }
    ],
    "sg:phone":"+44 115 950 7313",
    "sg:postcode":"NG1 1HF",
    "sg:province":"Nottinghamshire",
    "wof:name":"Grogan Culling & Co. Ltd.",
    "wof:placetype":"venue"
},
  "geometry": {"coordinates":[-1.1428819895,52.9508132935],"type":"Point"}
}