{
  "type": "Feature",
  "properties": {
    "addr:full":"2b Market Place Rugby Warwickshire CV21 3DY",
    "addr:housenumber":"2b",
    "addr:postcode":"cv21 3dy",
    "addr:street":"Market Place",
    "iso:country":"GB",
    "sg:address":"2b Market Place",
    "sg:city":"Rugby",
    "sg:classifiers":[
        {
            "category":"Professional",
            "subcategory":"Employment Agencies",
            "type":"Services"
        }
    ],
    "sg:phone":"+44 1788 540566",
    "sg:postcode":"CV21 3DY",
    "sg:province":"Warwickshire",
    "sg:tags":[
        "consultant",
        "recruitment"
    ],
    "wof:name":"First Personnel Group Plc",
    "wof:placetype":"venue"
},
  "geometry": {"coordinates":[-1.261667,52.372654],"type":"Point"}
}