{
  "type": "Feature",
  "properties": {
    "addr:full":"661 Stafford Road, Fordhouses Wolverhampton Staffordshire WV10 6QG",
    "addr:housenumber":"661",
    "addr:postcode":"wv10 6qg",
    "addr:street":"Stafford Road Fordhouses",
    "iso:country":"GB",
    "sg:address":"661 Stafford Road, Fordhouses",
    "sg:city":"Wolverhampton",
    "sg:classifiers":[
        {
            "category":"Personal",
            "subcategory":"Beauty Salon",
            "type":"Services"
        }
    ],
    "sg:postcode":"WV10 6QG",
    "sg:province":"Staffordshire",
    "sg:tags":[
        "unisex",
        "hairdresser"
    ],
    "wof:name":"T J's Hair Studio",
    "wof:placetype":"venue"
},
  "geometry": {"coordinates":[-2.127074,52.627628],"type":"Point"}
}