{
  "type": "Feature",
  "properties": {
    "addr:full":"78 High St Lewes East Sussex BN7 1XF",
    "addr:housenumber":"78",
    "addr:postcode":"bn7 1xf",
    "addr:street":"High St",
    "iso:country":"GB",
    "sg:address":"78 High St",
    "sg:city":"Lewes",
    "sg:classifiers":[
        {
            "category":"Professional",
            "type":"Services"
        }
    ],
    "sg:postcode":"BN7 1XF",
    "sg:province":"East Sussex",
    "sg:tags":[
        "repair",
        "tech",
        "maintenance"
    ],
    "wof:name":"Learn the Internet Ltd",
    "wof:placetype":"venue"
},
  "geometry": {"coordinates":[0.0081500001,50.8722381592],"type":"Point"}
}