{
  "type": "Feature",
  "properties": {
    "iso:country":"GB",
    "sg:address":"Whitehill Industrial Estate, Blackburn Road",
    "sg:city":"Bathgate",
    "sg:classifiers":[
        {
            "category":"Retail",
            "subcategory":"Auto Repair",
            "type":"Services"
        }
    ],
    "sg:phone":"+44 1506 631211",
    "sg:postcode":"EH48 2EB",
    "sg:province":"West Lothian",
    "sg:tags":[
        "bodybuilder",
        "repairer"
    ],
    "wof:name":"Jack Allen (Sales & Service)",
    "wof:placetype":"venue"
},
  "geometry": {"coordinates":[-3.695874,55.894627],"type":"Point"}
}