{
  "type": "Feature",
  "properties": {
    "addr:full":"25-27 Brougham Street Edinburgh City of Edinburgh EH3 9JT",
    "addr:housenumber":"25-27",
    "addr:postcode":"eh3 9jt",
    "addr:street":"Brougham Street",
    "iso:country":"GB",
    "sg:address":"25-27 Brougham Street",
    "sg:city":"Edinburgh",
    "sg:classifiers":[
        {
            "category":"Food & Beverages",
            "subcategory":"Meat & Fish",
            "type":"Retail Goods"
        }
    ],
    "sg:phone":"+44 131 229 7793",
    "sg:postcode":"EH3 9JT",
    "sg:province":"City of Edinburgh",
    "sg:tags":[
        "chip"
    ],
    "wof:name":"I L Marinaio",
    "wof:placetype":"venue"
},
  "geometry": {"coordinates":[-3.2019479275,55.9430847168],"type":"Point"}
}