{
  "type": "Feature",
  "properties": {
    "iso:country":"GB",
    "sg:address":"64 Walter Road",
    "sg:city":"Swansea",
    "sg:classifiers":[
        {
            "category":"Health Services",
            "subcategory":"Health Practitioner",
            "type":"Services"
        }
    ],
    "sg:phone":"+44 1792 643815",
    "sg:postcode":"SA1 4PT",
    "sg:province":"Neath Port Talbot",
    "sg:tags":[
        "physiotherapist"
    ],
    "wof:name":"Sandra M Lewis",
    "wof:placetype":"venue"
},
  "geometry": {"coordinates":[-3.9595808983,51.6186294556],"type":"Point"}
}