{
  "type": "Feature",
  "properties": {
    "addr:full":"Marina Trading Centre, The Boat Yard, Brighton Marina Brighton East Sussex BN2 5UF",
    "addr:postcode":"bn2 5uf",
    "addr:street":"The",
    "iso:country":"GB",
    "sg:address":"Marina Trading Centre, The Boat Yard, Brighton Marina",
    "sg:city":"Brighton",
    "sg:classifiers":[
        {
            "category":"Real Estate",
            "subcategory":"Surveying",
            "type":"Services"
        }
    ],
    "sg:phone":"+44 1273 818990",
    "sg:postcode":"BN2 5UF",
    "sg:province":"East Sussex",
    "sg:tags":[
        "surveyor",
        "marine"
    ],
    "wof:name":"Eurotek Marine Ltd.",
    "wof:placetype":"venue"
},
  "geometry": {"coordinates":[-0.091444,50.812279],"type":"Point"}
}