{
  "type": "Feature",
  "properties": {
    "iso:country":"GB",
    "sg:address":"9 Hodson Close, Whetstone",
    "sg:city":"Leicester",
    "sg:classifiers":[
        {
            "category":"Retail",
            "subcategory":"Repair Shop",
            "type":"Services"
        }
    ],
    "sg:phone":"+44 116 286 5821",
    "sg:postcode":"LE8 6EU",
    "sg:province":"Leicestershire",
    "sg:tags":[
        "television",
        "good",
        "video",
        "servicing",
        "maintenance",
        "radio"
    ],
    "wof:name":"Sidwells Of Desford",
    "wof:placetype":"venue"
},
  "geometry": {"coordinates":[-1.1754280329,52.5653038025],"type":"Point"}
}