{
  "type": "Feature",
  "properties": {
    "addr:full":"Ferry House, St James Street Dover Kent CT16 1QD",
    "addr:postcode":"ct16 1qd",
    "addr:street":"St James Street",
    "iso:country":"GB",
    "sg:address":"Ferry House, St James Street",
    "sg:city":"Dover",
    "sg:classifiers":[
        {
            "category":"Freight",
            "type":"Transportation"
        }
    ],
    "sg:phone":"+44 1304 240211",
    "sg:postcode":"CT16 1QD",
    "sg:province":"Kent",
    "sg:tags":[
        "forwarders"
    ],
    "wof:name":"Transclear Ltd.",
    "wof:placetype":"venue"
},
  "geometry": {"coordinates":[1.3173550367,51.1258049011],"type":"Point"}
}