{
  "type": "Feature",
  "properties": {
    "addr:full":"Unit 5 Tye Farm, Cranfield Park Road Wickford Essex SS12 9LE",
    "addr:housenumber":"unit 5",
    "addr:postcode":"ss12 9le",
    "addr:street":"Tye Farm Cranfield Park Road",
    "iso:country":"GB",
    "sg:address":"Unit 5 Tye Farm, Cranfield Park Road",
    "sg:city":"Wickford",
    "sg:classifiers":[
        {
            "category":"Home & Garden",
            "subcategory":"Hardware",
            "type":"Retail Goods"
        }
    ],
    "sg:phone":"+44 1375 644744",
    "sg:postcode":"SS12 9LE",
    "sg:province":"Essex",
    "sg:tags":[
        "fixing",
        "nuts",
        "bolt"
    ],
    "wof:name":"Superior Stainless",
    "wof:placetype":"venue"
},
  "geometry": {"coordinates":[0.518599987,51.6000328064],"type":"Point"}
}