{
  "type": "Feature",
  "properties": {
    "addr:full":"Unit 4 Caxton Mill, Dukinfield Rd Hyde Cheshire SK14 2AZ",
    "addr:housenumber":"unit 4",
    "addr:postcode":"sk14 2az",
    "addr:street":"Dukinfield Rd",
    "iso:country":"GB",
    "sg:address":"Unit 4 Caxton Mill, Dukinfield Rd",
    "sg:city":"Hyde",
    "sg:classifiers":[
        {
            "category":"Retail",
            "subcategory":"Auto Repair",
            "type":"Services"
        }
    ],
    "sg:phone":"+44 161 367 8705",
    "sg:postcode":"SK14 2AZ",
    "sg:province":"Cheshire",
    "sg:tags":[
        "modification",
        "garage"
    ],
    "wof:name":"Chartist Garage",
    "wof:placetype":"venue"
},
  "geometry": {"coordinates":[-2.084458,53.454479],"type":"Point"}
}