{
  "type": "Feature",
  "properties": {
    "addr:full":"Lower Soroba Oban Argyll and Bute PA34 4SB",
    "addr:postcode":"pa34 4sb",
    "iso:country":"GB",
    "sg:address":"Lower Soroba",
    "sg:city":"Oban",
    "sg:classifiers":[
        {
            "category":"Education",
            "subcategory":"School",
            "type":"Public Place"
        }
    ],
    "sg:phone":"+44 1631 564349",
    "sg:postcode":"PA34 4SB",
    "sg:province":"Argyll and Bute",
    "sg:tags":[
        "local",
        "authority"
    ],
    "wof:name":"St. Columba's R C School",
    "wof:placetype":"venue"
},
  "geometry": {"coordinates":[-5.469119072,56.4079818726],"type":"Point"}
}