{
  "type": "Feature",
  "properties": {
    "iso:country":"GB",
    "sg:address":"366 Main Rd",
    "sg:city":"Westerham",
    "sg:classifiers":[
        {
            "category":"Professional",
            "type":"Services"
        }
    ],
    "sg:phone":"+44 1959 576321",
    "sg:postcode":"TN16 2HN",
    "sg:province":"Kent",
    "sg:tags":[
        "shopfitters"
    ],
    "wof:name":"Hammond Project Design",
    "wof:placetype":"venue"
},
  "geometry": {"coordinates":[0.0525600016,51.2999954224],"type":"Point"}
}