{
  "type": "Feature",
  "properties": {
    "iso:country":"GB",
    "sg:address":"54 New Briggate",
    "sg:city":"Leeds",
    "sg:classifiers":[
        {
            "category":"Bars & Pubs",
            "subcategory":"Nightclub",
            "type":"Food & Drink"
        }
    ],
    "sg:phone":"+44 113 242 2224",
    "sg:postcode":"LS1 6NU",
    "sg:province":"West Yorkshire",
    "sg:tags":[
        "club",
        "night"
    ],
    "wof:name":"Club Uropa",
    "wof:placetype":"venue"
},
  "geometry": {"coordinates":[-1.540823,53.800526],"type":"Point"}
}