{
  "type": "Feature",
  "properties": {
    "addr:full":"Enterprise House, Geddington Rd Corby Northamptonshire NN18 8ET",
    "addr:postcode":"nn18 8et",
    "addr:street":"Geddington Rd",
    "iso:country":"GB",
    "sg:address":"Enterprise House, Geddington Rd",
    "sg:city":"Corby",
    "sg:classifiers":[
        {
            "category":"Home & Garden",
            "subcategory":"Home Furnishings",
            "type":"Retail Goods"
        }
    ],
    "sg:phone":"+44 1536 262772",
    "sg:postcode":"NN18 8ET",
    "sg:province":"Northamptonshire",
    "sg:tags":[
        "furnishers",
        "planner",
        "kitchen"
    ],
    "wof:name":"Aspect Interior",
    "wof:placetype":"venue"
},
  "geometry": {"coordinates":[-0.674787,52.488014],"type":"Point"}
}