{
  "type": "Feature",
  "properties": {
    "iso:country":"GB",
    "sg:address":"33 Derby Road",
    "sg:city":"Chesterfield",
    "sg:classifiers":[
        {
            "category":"Home & Garden",
            "subcategory":"Household Appliances",
            "type":"Retail Goods"
        }
    ],
    "sg:phone":"+44 1246 209127",
    "sg:postcode":"S40 2EF",
    "sg:province":"Derbyshire",
    "sg:tags":[
        "domestic",
        "centre"
    ],
    "wof:name":"Cooker Centre",
    "wof:placetype":"venue"
},
  "geometry": {"coordinates":[-1.4260189533,53.2262878418],"type":"Point"}
}