{
  "type": "Feature",
  "properties": {
    "addr:full":"Unit D Saddlers Yard, Saddler St Durham Durham DH1 3NP",
    "addr:housenumber":"unit d",
    "addr:postcode":"dh1 3np",
    "addr:street":"Saddlers Yard Saddler St",
    "iso:country":"GB",
    "sg:address":"Unit D Saddlers Yard, Saddler St",
    "sg:city":"Durham",
    "sg:classifiers":[
        {
            "category":"Transit Center",
            "subcategory":"Freight",
            "type":"Transportation"
        }
    ],
    "sg:phone":"+44 191 386 3050",
    "sg:postcode":"DH1 3NP",
    "sg:province":"Durham",
    "sg:tags":[
        "shop",
        "craft",
        "centre"
    ],
    "wof:name":"Craft Ninehundred",
    "wof:placetype":"venue"
},
  "geometry": {"coordinates":[-1.5746079683,54.7775344849],"type":"Point"}
}