{
  "type": "Feature",
  "properties": {
    "addr:full":"70 Wilton Bank Saltburn-by-the-sea North Yorkshire TS12 1NU",
    "addr:housenumber":"70",
    "addr:postcode":"ts12 1nu",
    "addr:street":"Wilton Bank Saltburn-By-The-Sea",
    "iso:country":"GB",
    "sg:address":"70 Wilton Bank",
    "sg:city":"Saltburn-by-the-sea",
    "sg:classifiers":[
        {
            "category":"Retail",
            "subcategory":"Driving School",
            "type":"Services"
        }
    ],
    "sg:postcode":"TS12 1NU",
    "sg:province":"North Yorkshire",
    "wof:name":"Partlett,Christine,",
    "wof:placetype":"venue"
},
  "geometry": {"coordinates":[-0.9922180176,54.5785713196],"type":"Point"}
}