{
  "type": "Feature",
  "properties": {
    "addr:full":"5 Sloane Street London Greater London SW1X 9LA",
    "addr:housenumber":"5",
    "addr:postcode":"sw1x 9la",
    "addr:street":"Sloane Street",
    "iso:country":"GB",
    "sg:address":"5 Sloane Street",
    "sg:city":"London",
    "sg:classifiers":[
        {
            "category":"Personal",
            "subcategory":"Beauty Salon",
            "type":"Services"
        }
    ],
    "sg:phone":"+44 20 7235 9333",
    "sg:postcode":"SW1X 9LA",
    "sg:province":"Greater London",
    "wof:name":"Fraser Muir Holdings Ltd.",
    "wof:placetype":"venue"
},
  "geometry": {"coordinates":[-0.160273,51.501259],"type":"Point"}
}