{
  "type": "Feature",
  "properties": {
    "addr:full":"311 West Princes Street, Hillhead Glasgow Glasgow City G4 9DR",
    "addr:housenumber":"311",
    "addr:postcode":"g4 9dr",
    "addr:street":"West Princes Street",
    "iso:country":"GB",
    "sg:address":"311 West Princes Street, Hillhead",
    "sg:city":"Glasgow",
    "sg:classifiers":[
        {
            "category":"Building & Trades",
            "subcategory":"Construction",
            "type":"Services"
        }
    ],
    "sg:phone":"+44 141 332 5451",
    "sg:postcode":"G4 9DR",
    "sg:province":"Glasgow City",
    "sg:tags":[
        "decorator",
        "painter"
    ],
    "wof:name":"Guy Lyons",
    "wof:placetype":"venue"
},
  "geometry": {"coordinates":[-4.2765498161,55.8723258972],"type":"Point"}
}