{
  "type": "Feature",
  "properties": {
    "iso:country":"GB",
    "sg:address":"Baird Mure House, 631 Dumbarton Road",
    "sg:city":"Clydebank",
    "sg:classifiers":[
        {
            "category":"Home & Garden",
            "subcategory":"Building Materials",
            "type":"Retail Goods"
        }
    ],
    "sg:phone":"+44 141 579 0918",
    "sg:postcode":"G81 4EU",
    "sg:province":"East Dunbartonshire",
    "sg:tags":[
        "roofing",
        "rafter",
        "beams"
    ],
    "wof:name":"William Duffy",
    "wof:placetype":"venue"
},
  "geometry": {"coordinates":[-4.425449,55.909245],"type":"Point"}
}