{
  "type": "Feature",
  "properties": {
    "addr:full":"217 Chesterton Road Cambridge Cambridgeshire CB4 1AN",
    "addr:housenumber":"217",
    "addr:postcode":"cb4 1an",
    "addr:street":"Chesterton Road",
    "iso:country":"GB",
    "sg:address":"217 Chesterton Road",
    "sg:city":"Cambridge",
    "sg:classifiers":[
        {
            "category":"Travel",
            "subcategory":"Hotels & Motels",
            "type":"Entertainment"
        }
    ],
    "sg:phone":"+44 1223 500776",
    "sg:postcode":"CB4 1AN",
    "sg:province":"Cambridgeshire",
    "sg:tags":[
        "house",
        "guest"
    ],
    "wof:name":"Lynwood House",
    "wof:placetype":"venue"
},
  "geometry": {"coordinates":[0.1293440014,52.2152709961],"type":"Point"}
}