{
  "type": "Feature",
  "properties": {
    "iso:country":"GB",
    "sg:address":"33 New Greenmarket",
    "sg:city":"Newcastle Upon Tyne",
    "sg:classifiers":[
        {
            "category":"Shopping",
            "subcategory":"Books",
            "type":"Retail Goods"
        }
    ],
    "sg:phone":"+44 191 232 3196",
    "sg:postcode":"NE1 7YA",
    "sg:province":"Tyne and Wear",
    "sg:tags":[
        "second-hand"
    ],
    "wof:name":"Bookworms Paradise",
    "wof:placetype":"venue"
},
  "geometry": {"coordinates":[-1.6137299538,54.9773902893],"type":"Point"}
}