{
  "type": "Feature",
  "properties": {
    "iso:country":"GB",
    "sg:address":"London Rd, Chesterton",
    "sg:city":"Newcastle",
    "sg:classifiers":[
        {
            "category":"Bars & Pubs",
            "type":"Food & Drink"
        }
    ],
    "sg:postcode":"ST5 7JB",
    "sg:province":"Staffordshire",
    "sg:tags":[
        "pubs",
        "inn"
    ],
    "wof:name":"Kozlowski,Michael,",
    "wof:placetype":"venue"
},
  "geometry": {"coordinates":[-2.250059,53.041046],"type":"Point"}
}