{
  "type": "Feature",
  "properties": {
    "iso:country":"GB",
    "sg:address":"Christie's Education",
    "sg:city":"London",
    "sg:classifiers":[
        {
            "category":"Education",
            "subcategory":"University",
            "type":"Public Place"
        }
    ],
    "sg:postcode":"SW7 3JS",
    "sg:province":"Greater London",
    "sg:tags":[
        "adult"
    ],
    "wof:name":"Modern Art Studies",
    "wof:placetype":"venue"
},
  "geometry": {"coordinates":[-0.17617,51.493031],"type":"Point"}
}