{
  "type": "Feature",
  "properties": {
    "addr:full":"Hollies Farm, Spondon Road, Dale Abbey Ilkeston Derbyshire DE7 4PQ",
    "addr:postcode":"de7 4pq",
    "addr:street":"Spondon Road",
    "iso:country":"GB",
    "sg:address":"Hollies Farm, Spondon Road, Dale Abbey",
    "sg:city":"Ilkeston",
    "sg:classifiers":[
        {
            "category":"Sports & Exercise",
            "subcategory":"Stables",
            "type":"Entertainment"
        }
    ],
    "sg:postcode":"DE7 4PQ",
    "sg:province":"Derbyshire",
    "sg:tags":[
        "equestrian",
        "centre",
        "livery",
        "schools",
        "riding",
        "education"
    ],
    "wof:name":"HOLLIES FARM STABLES",
    "wof:placetype":"venue"
},
  "geometry": {"coordinates":[-1.3526409864,52.9454612732],"type":"Point"}
}