{
  "type": "Feature",
  "properties": {
    "addr:full":"28 London Road Bromley Kent BR1 3QR",
    "addr:housenumber":"28",
    "addr:postcode":"br1 3qr",
    "addr:street":"London Road",
    "iso:country":"GB",
    "sg:address":"28 London Road",
    "sg:city":"Bromley",
    "sg:classifiers":[
        {
            "category":"Cafe",
            "type":"Food & Drink"
        }
    ],
    "sg:phone":"+44 20 8464 6990",
    "sg:postcode":"BR1 3QR",
    "sg:province":"Kent",
    "sg:tags":[
        "tea",
        "room"
    ],
    "wof:name":"Mazzi's Snack Bar",
    "wof:placetype":"venue"
},
  "geometry": {"coordinates":[0.0107939998,51.4092292786],"type":"Point"}
}