{
  "type": "Feature",
  "properties": {
    "iso:country":"GB",
    "sg:address":"St Leonards Sq",
    "sg:city":"Glasgow",
    "sg:classifiers":[
        {
            "category":"Government",
            "subcategory":"Post Office",
            "type":"Public Place"
        }
    ],
    "sg:phone":"+44 1355 236534",
    "sg:postcode":"G74 2AT",
    "sg:province":"South Lanarkshire",
    "wof:name":"St Leonards Sub Post Office",
    "wof:placetype":"venue"
},
  "geometry": {"coordinates":[-4.158908,55.765011],"type":"Point"}
}