{
  "type": "Feature",
  "properties": {
    "addr:full":"Great Grovehurst Farm, Grovehurst Rd, Iwade Sittingbourne Kent ME9 8RB",
    "addr:postcode":"me9 8rb",
    "addr:street":"Grovehurst Rd;Sittingbourne",
    "iso:country":"GB",
    "sg:address":"Great Grovehurst Farm, Grovehurst Rd, Iwade",
    "sg:city":"Sittingbourne",
    "sg:classifiers":[
        {
            "category":"Shopping",
            "subcategory":"Pets & Pet Supplies",
            "type":"Retail Goods"
        }
    ],
    "sg:phone":"+44 1795 426444",
    "sg:postcode":"ME9 8RB",
    "sg:province":"Kent",
    "wof:name":"T.A.V.A.C",
    "wof:placetype":"venue"
},
  "geometry": {"coordinates":[0.7295470238,51.3765525818],"type":"Point"}
}