{
  "type": "Feature",
  "properties": {
    "iso:country":"GB",
    "sg:address":"2950 Kettering Parkway",
    "sg:city":"Kettering",
    "sg:classifiers":[
        {
            "category":"Professional",
            "subcategory":"Detective & Security Services",
            "type":"Services"
        }
    ],
    "sg:phone":"+44 1536 316016",
    "sg:postcode":"NN15 6XZ",
    "sg:province":"Northamptonshire",
    "sg:tags":[
        "equipment"
    ],
    "wof:name":"Winkhaus (U K) Ltd.",
    "wof:placetype":"venue"
},
  "geometry": {"coordinates":[-0.7092990279,52.3754081726],"type":"Point"}
}