{
  "type": "Feature",
  "properties": {
    "iso:country":"GB",
    "sg:address":"115 High Road",
    "sg:city":"London",
    "sg:classifiers":[
        {
            "category":"Professional",
            "subcategory":"Engineering",
            "type":"Services"
        },
        {
            "category":"Building & Trades",
            "subcategory":"Electrical",
            "type":"Services"
        }
    ],
    "sg:phone":"+44 20 8883 9098",
    "sg:postcode":"N2 8AG",
    "sg:province":"Greater London",
    "sg:tags":[
        "engineer",
        "electrician",
        "contractor"
    ],
    "sg:website":"http://www.ef-elec.co.uk",
    "wof:name":"East Finchley Electrical Contractors",
    "wof:placetype":"venue"
},
  "geometry": {"coordinates":[-0.165349,51.591213],"type":"Point"}
}