{
  "type": "Feature",
  "properties": {
    "addr:full":"Gloucester House, 72 London Hertfordshire AL1 1NS",
    "addr:housenumber":"72",
    "addr:postcode":"al1 1ns",
    "addr:street":"London",
    "iso:country":"GB",
    "sg:address":"Gloucester House, 72",
    "sg:city":"London",
    "sg:classifiers":[
        {
            "category":"Organizations",
            "subcategory":"Membership Organization",
            "type":"Services"
        }
    ],
    "sg:postcode":"AL1 1NS",
    "sg:province":"Hertfordshire",
    "sg:tags":[
        "club"
    ],
    "wof:name":"Lodestar Management Ltd",
    "wof:placetype":"venue"
},
  "geometry": {"coordinates":[-0.3373129964,51.7501754761],"type":"Point"}
}