{
  "type": "Feature",
  "properties": {
    "addr:full":"Sheffield House 1b Amity Gro, Raynes Park London Greater London SW20 0LG",
    "addr:housenumber":"1b",
    "addr:postcode":"sw20 0lg",
    "addr:street":"Amity Gro Raynes Park",
    "iso:country":"GB",
    "sg:address":"Sheffield House 1b Amity Gro, Raynes Park",
    "sg:city":"London",
    "sg:classifiers":[
        {
            "category":"Wholesale",
            "subcategory":"Chemicals & Plastics",
            "type":"Manufacturing & Wholesale Goods"
        }
    ],
    "sg:phone":"+44 20 8946 9151",
    "sg:postcode":"SW20 0LG",
    "sg:province":"Greater London",
    "sg:tags":[
        "product",
        "allied"
    ],
    "wof:name":"Unifi",
    "wof:placetype":"venue"
},
  "geometry": {"coordinates":[-0.231768,51.409466],"type":"Point"}
}