{
  "type": "Feature",
  "properties": {
    "addr:full":"32 The Avenue, Cheam Sutton Surrey SM2 7QB",
    "addr:housenumber":"32",
    "addr:postcode":"sm2 7qb",
    "addr:street":"The Avenue",
    "iso:country":"GB",
    "sg:address":"32 The Avenue, Cheam",
    "sg:city":"Sutton",
    "sg:classifiers":[
        {
            "category":"Health Services",
            "subcategory":"Nursing And Care Facility",
            "type":"Services"
        }
    ],
    "sg:phone":"+44 20 8642 3912",
    "sg:postcode":"SM2 7QB",
    "sg:province":"Surrey",
    "sg:tags":[
        "home"
    ],
    "wof:name":"Avenue Nursing Home",
    "wof:placetype":"venue"
},
  "geometry": {"coordinates":[-0.209992,51.347393],"type":"Point"}
}