{
  "type": "Feature",
  "properties": {
    "iso:country":"GB",
    "sg:address":"Constituency Of Wakefield, 6 Rishworth St",
    "sg:city":"Wakefield",
    "sg:classifiers":[
        {
            "category":"Government",
            "subcategory":"Office",
            "type":"Public Place"
        }
    ],
    "sg:phone":"+44 1924 290590",
    "sg:postcode":"WF1 3BY",
    "sg:province":"West Yorkshire",
    "sg:tags":[
        "mp",
        "meps"
    ],
    "wof:name":"David Hinchliffe MP (Lab)",
    "wof:placetype":"venue"
},
  "geometry": {"coordinates":[-1.50107,53.685501],"type":"Point"}
}