{
  "type": "Feature",
  "properties": {
    "addr:full":"6-8 Fenchurch Bldg(s) London Greater London EC3M 5HT",
    "addr:housenumber":"6-8",
    "addr:postcode":"ec3m 5ht",
    "addr:street":"S",
    "iso:country":"GB",
    "sg:address":"6-8 Fenchurch Bldg(s)",
    "sg:city":"London",
    "sg:classifiers":[
        {
            "category":"Freight",
            "type":"Transportation"
        }
    ],
    "sg:phone":"+44 20 7680 1328",
    "sg:postcode":"EC3M 5HT",
    "sg:province":"Greater London",
    "sg:tags":[
        "overseas",
        "shipping",
        "removal"
    ],
    "wof:name":"Valiant Shipping Co. (London) Ltd.",
    "wof:placetype":"venue"
},
  "geometry": {"coordinates":[-0.0813219994,51.5124931335],"type":"Point"}
}