{
  "type": "Feature",
  "properties": {
    "addr:full":"Unit 5 Endeavour Park, 11 Witney Road Poole Dorset BH17 0GJ",
    "addr:housenumber":"unit 5;11",
    "addr:postcode":"bh17 0gj",
    "addr:street":"Endeavour Park;Witney Road",
    "iso:country":"GB",
    "sg:address":"Unit 5 Endeavour Park, 11 Witney Road",
    "sg:city":"Poole",
    "sg:classifiers":[
        {
            "category":"Home & Garden",
            "subcategory":"Kitchen Supply",
            "type":"Retail Goods"
        }
    ],
    "sg:phone":"+44 1202 684111",
    "sg:postcode":"BH17 0GJ",
    "sg:province":"Dorset",
    "sg:tags":[
        "equipment",
        "catering"
    ],
    "wof:name":"Coffeeman Containers (U K) Ltd.",
    "wof:placetype":"venue"
},
  "geometry": {"coordinates":[-1.9724400043,50.7479095459],"type":"Point"}
}