{
  "type": "Feature",
  "properties": {
    "addr:full":"50 Upper Brook Street, Mayfair London Greater London W1K 2BS",
    "addr:housenumber":"50",
    "addr:postcode":"w1k 2bs",
    "addr:street":"Upper Brook Street",
    "iso:country":"GB",
    "sg:address":"50 Upper Brook Street, Mayfair",
    "sg:city":"London",
    "sg:classifiers":[
        {
            "category":"Professional",
            "subcategory":"Lawyer & Legal Services",
            "type":"Services"
        }
    ],
    "sg:phone":"+44 20 7499 5599",
    "sg:postcode":"W1K 2BS",
    "sg:province":"Greater London",
    "sg:tags":[
        "solicitor"
    ],
    "wof:name":"Sears Tooth",
    "wof:placetype":"venue"
},
  "geometry": {"coordinates":[-0.1544030011,51.5113792419],"type":"Point"}
}