{
  "type": "Feature",
  "properties": {
    "addr:full":"155 Reculver Road, Beltinge Herne Bay Kent CT6 6PW",
    "addr:housenumber":"155",
    "addr:postcode":"ct6 6pw",
    "addr:street":"Reculver Road",
    "iso:country":"GB",
    "sg:address":"155 Reculver Road, Beltinge",
    "sg:city":"Herne Bay",
    "sg:classifiers":[
        {
            "category":"Education",
            "subcategory":"Dance Studio",
            "type":"Public Place"
        }
    ],
    "sg:phone":"+44 1227 369212",
    "sg:postcode":"CT6 6PW",
    "sg:province":"Kent",
    "sg:tags":[
        "school",
        "dancing"
    ],
    "wof:name":"Herne Bay Dance & Karate",
    "wof:placetype":"venue"
},
  "geometry": {"coordinates":[1.1563550234,51.3709259033],"type":"Point"}
}