{
  "type": "Feature",
  "properties": {
    "addr:full":"10 Lint Riggs Falkirk Falkirk FK1 1DG",
    "addr:housenumber":"10",
    "addr:postcode":"fk1 1dg",
    "addr:street":"Lint Riggs",
    "iso:country":"GB",
    "sg:address":"10 Lint Riggs",
    "sg:city":"Falkirk",
    "sg:classifiers":[
        {
            "category":"Shopping",
            "subcategory":"Clothing, Apparel, & Fashions",
            "type":"Retail Goods"
        }
    ],
    "sg:phone":"+44 1324 621399",
    "sg:postcode":"FK1 1DG",
    "sg:province":"Falkirk",
    "sg:tags":[
        "ladieswear"
    ],
    "wof:name":"Sisters",
    "wof:placetype":"venue"
},
  "geometry": {"coordinates":[-3.7862169743,56.0001945496],"type":"Point"}
}