{
  "type": "Feature",
  "properties": {
    "addr:full":"Southmere, Main Road, Bucklesham Ipswich Suffolk IP10 0DN",
    "addr:postcode":"ip10 0dn",
    "addr:street":"Main Road",
    "iso:country":"GB",
    "sg:address":"Southmere, Main Road, Bucklesham",
    "sg:city":"Ipswich",
    "sg:classifiers":[
        {
            "category":"Real Estate",
            "subcategory":"Surveying",
            "type":"Services"
        }
    ],
    "sg:phone":"+44 1473 659480",
    "sg:postcode":"IP10 0DN",
    "sg:province":"Suffolk",
    "sg:tags":[
        "surveyor",
        "valuer"
    ],
    "wof:name":"Richard Brunt & Associate",
    "wof:placetype":"venue"
},
  "geometry": {"coordinates":[1.2703490257,52.0298881531],"type":"Point"}
}