{
  "type": "Feature",
  "properties": {
    "addr:full":"31-32 Duke Street Chelmsford Essex CM1 1HY",
    "addr:housenumber":"31-32",
    "addr:postcode":"cm1 1hy",
    "addr:street":"Duke Street",
    "iso:country":"GB",
    "sg:address":"31-32 Duke Street",
    "sg:city":"Chelmsford",
    "sg:classifiers":[
        {
            "category":"Real Estate",
            "subcategory":"Real Estate Agent",
            "type":"Services"
        }
    ],
    "sg:phone":"+44 1245 347303",
    "sg:postcode":"CM1 1HY",
    "sg:province":"Essex",
    "wof:name":"David Murdoch",
    "wof:placetype":"venue"
},
  "geometry": {"coordinates":[0.467573,51.736572],"type":"Point"}
}