{
  "type": "Feature",
  "properties": {
    "addr:full":"7 Blackhills Road Peterlee Durham SR8 4SB",
    "addr:housenumber":"7",
    "addr:postcode":"sr8 4sb",
    "addr:street":"Blackhills Road",
    "iso:country":"GB",
    "sg:address":"7 Blackhills Road",
    "sg:city":"Peterlee",
    "sg:classifiers":[
        {
            "category":"Shopping",
            "subcategory":"Department Store",
            "type":"Retail Goods"
        }
    ],
    "sg:phone":"+44 191 586 1340",
    "sg:postcode":"SR8 4SB",
    "sg:province":"Durham",
    "wof:name":"Iqbal Singh",
    "wof:placetype":"venue"
},
  "geometry": {"coordinates":[-1.313316,54.763756],"type":"Point"}
}