{
  "type": "Feature",
  "properties": {
    "addr:full":"Unit 3/4 Mayland Industrial Estate Chelmsford Essex CM3 6AX",
    "addr:housenumber":"unit 3 / 4",
    "addr:postcode":"cm3 6ax",
    "addr:street":"Mayland Industrial Estate",
    "iso:country":"GB",
    "sg:address":"Unit 3/4 Mayland Industrial Estate",
    "sg:city":"Chelmsford",
    "sg:classifiers":[
        {
            "category":"Wholesale",
            "subcategory":"Construction Materials",
            "type":"Manufacturing & Wholesale Goods"
        }
    ],
    "sg:phone":"+44 1621 742197",
    "sg:postcode":"CM3 6AX",
    "sg:province":"Essex",
    "sg:tags":[
        "merchant",
        "glass"
    ],
    "wof:name":"Rainbow Windows",
    "wof:placetype":"venue"
},
  "geometry": {"coordinates":[0.77102,51.680691],"type":"Point"}
}