{
  "type": "Feature",
  "properties": {
    "iso:country":"GB",
    "sg:address":"Steps House, Fletching Street",
    "sg:city":"Mayfield",
    "sg:classifiers":[
        {
            "category":"Professional",
            "subcategory":"Business Services",
            "type":"Services"
        }
    ],
    "sg:phone":"+44 1435 873884",
    "sg:postcode":"TN20 6TH",
    "sg:province":"East Sussex",
    "sg:tags":[
        "transfer",
        "agent"
    ],
    "wof:name":"Lakey & Co.",
    "wof:placetype":"venue"
},
  "geometry": {"coordinates":[0.2683410048,51.0214653015],"type":"Point"}
}