{
  "type": "Feature",
  "properties": {
    "addr:full":"2 Reynolds Walk, Horfield Bristol City of Bristol BS7 0HU",
    "addr:housenumber":"2",
    "addr:postcode":"bs7 0hu",
    "addr:street":"Reynolds Walk",
    "iso:country":"GB",
    "sg:address":"2 Reynolds Walk, Horfield",
    "sg:city":"Bristol",
    "sg:classifiers":[
        {
            "category":"Community Center",
            "type":"Public Place"
        }
    ],
    "sg:phone":"+44 117 969 6127",
    "sg:postcode":"BS7 0HU",
    "sg:province":"City of Bristol",
    "sg:tags":[
        "recreation",
        "leisure",
        "centre"
    ],
    "wof:name":"L A Gym",
    "wof:placetype":"venue"
},
  "geometry": {"coordinates":[-2.5746,51.49472],"type":"Point"}
}