{
  "type": "Feature",
  "properties": {
    "iso:country":"GB",
    "sg:address":"469 Dudley Road",
    "sg:city":"Wolverhampton",
    "sg:classifiers":[
        {
            "category":"Manufacturing",
            "subcategory":"Signs",
            "type":"Manufacturing & Wholesale Goods"
        }
    ],
    "sg:phone":"+44 1902 352600",
    "sg:postcode":"WV2 3AF",
    "sg:province":"West Midlands",
    "sg:tags":[
        "writer"
    ],
    "wof:name":"Dennis Signs",
    "wof:placetype":"venue"
},
  "geometry": {"coordinates":[-2.126371,52.575432],"type":"Point"}
}