{
  "type": "Feature",
  "properties": {
    "iso:country":"GB",
    "sg:address":"11 West Street, Covent Gdn",
    "sg:city":"London",
    "sg:classifiers":[
        {
            "category":"Building & Trades",
            "subcategory":"Cleaning & Sanitation",
            "type":"Services"
        }
    ],
    "sg:phone":"+44 20 7836 7836",
    "sg:postcode":"WC2H 9NE",
    "sg:province":"Greater London",
    "sg:tags":[
        "industrial",
        "business",
        "removal"
    ],
    "wof:name":"Mont Developments Ltd",
    "wof:placetype":"venue"
},
  "geometry": {"coordinates":[-0.1284600049,51.5130882263],"type":"Point"}
}