{
  "type": "Feature",
  "properties": {
    "addr:full":"Fore Street Looe Cornwall PL13 2EZ",
    "addr:postcode":"pl13 2ez",
    "addr:street":"Fore Street",
    "iso:country":"GB",
    "sg:address":"Fore Street",
    "sg:city":"Looe",
    "sg:classifiers":[
        {
            "category":"Shopping",
            "subcategory":"Department Store",
            "type":"Retail Goods"
        },
        {
            "category":"Food & Beverages",
            "subcategory":"Supermarket",
            "type":"Retail Goods"
        }
    ],
    "sg:postcode":"PL13 2EZ",
    "sg:province":"Cornwall",
    "wof:name":"Bowdens Stores",
    "wof:placetype":"venue"
},
  "geometry": {"coordinates":[-4.519343853,50.3315010071],"type":"Point"}
}