{
  "type": "Feature",
  "properties": {
    "addr:full":"Municipal Airport Southend-on-sea Essex SS2 6YF",
    "addr:postcode":"ss2 6yf",
    "iso:country":"GB",
    "sg:address":"Municipal Airport",
    "sg:city":"Southend-on-sea",
    "sg:classifiers":[
        {
            "category":"Retail",
            "subcategory":"Auto Repair",
            "type":"Services"
        }
    ],
    "sg:phone":"+44 1702 338635",
    "sg:postcode":"SS2 6YF",
    "sg:province":"Essex",
    "sg:tags":[
        "modification",
        "garage"
    ],
    "wof:name":"Airport Garage Services",
    "wof:placetype":"venue"
},
  "geometry": {"coordinates":[0.7002699971,51.5677909851],"type":"Point"}
}