{
  "type": "Feature",
  "properties": {
    "addr:full":"20 Lingdale Rd, Cheadle Hulme Cheadle Cheshire SK8 5DS",
    "addr:housenumber":"20",
    "addr:postcode":"sk8 5ds",
    "addr:street":"Lingdale Rd",
    "iso:country":"GB",
    "sg:address":"20 Lingdale Rd, Cheadle Hulme",
    "sg:city":"Cheadle",
    "sg:classifiers":[
        {
            "category":"Professional",
            "subcategory":"Management & Consulting",
            "type":"Services"
        }
    ],
    "sg:phone":"+44 161 485 5721",
    "sg:postcode":"SK8 5DS",
    "sg:province":"Cheshire",
    "sg:tags":[
        "consultant",
        "specialist"
    ],
    "wof:name":"Nails At Home",
    "wof:placetype":"venue"
},
  "geometry": {"coordinates":[-2.1966450214,53.3771018982],"type":"Point"}
}