{
  "type": "Feature",
  "properties": {
    "iso:country":"GB",
    "sg:address":"45a Everton Rd",
    "sg:city":"Southport",
    "sg:classifiers":[
        {
            "category":"Shopping",
            "subcategory":"Antiques",
            "type":"Retail Goods"
        }
    ],
    "sg:phone":"+44 1704 569164",
    "sg:postcode":"PR8 4BT",
    "sg:province":"Lancashire",
    "wof:name":"Bone A B",
    "wof:placetype":"venue"
},
  "geometry": {"coordinates":[-3.007941,53.63295],"type":"Point"}
}