{
  "type": "Feature",
  "properties": {
    "iso:country":"GB",
    "sg:address":"498 Church Lane, Kingsbury",
    "sg:city":"Colindale",
    "sg:classifiers":[
        {
            "category":"Retail",
            "subcategory":"Auto Rental",
            "type":"Services"
        }
    ],
    "sg:phone":"+44 20 8205 8385",
    "sg:postcode":"NW9 8UA",
    "sg:province":"Greater London",
    "sg:tags":[
        "truck",
        "hire",
        "van"
    ],
    "wof:name":"Perrys (Suzuki)",
    "wof:placetype":"venue"
},
  "geometry": {"coordinates":[-0.2627300024,51.5807609558],"type":"Point"}
}