{
  "type": "Feature",
  "properties": {
    "addr:full":"14 Huntlands Road Halesowen West Midlands B63 4LY",
    "addr:housenumber":"14",
    "addr:postcode":"b63 4ly",
    "addr:street":"Huntlands Road",
    "iso:country":"GB",
    "sg:address":"14 Huntlands Road",
    "sg:city":"Halesowen",
    "sg:classifiers":[
        {
            "category":"Professional",
            "subcategory":"Accounting & Tax Preparation",
            "type":"Services"
        },
        {
            "category":"Social Services",
            "subcategory":"Job Training",
            "type":"Services"
        }
    ],
    "sg:phone":"+44 121 550 7056",
    "sg:postcode":"B63 4LY",
    "sg:province":"West Midlands",
    "sg:tags":[
        "consultancy"
    ],
    "wof:name":"Nick Lawrence Consultancy Services Ltd.",
    "wof:placetype":"venue"
},
  "geometry": {"coordinates":[-2.0677518845,52.441368103],"type":"Point"}
}