{
  "type": "Feature",
  "properties": {
    "addr:full":"Unit 4, Express Way Business Park Deeside Flintshire CH5 2TF",
    "addr:housenumber":"unit 4",
    "addr:postcode":"ch5 2tf",
    "addr:street":"Express Way Business Park Deeside",
    "iso:country":"GB",
    "sg:address":"Unit 4, Express Way Business Park",
    "sg:city":"Deeside",
    "sg:classifiers":[
        {
            "category":"Cinema",
            "subcategory":"Movie Rental",
            "type":"Entertainment"
        }
    ],
    "sg:phone":"+44 1244 821024",
    "sg:postcode":"CH5 2TF",
    "sg:province":"Flintshire",
    "sg:tags":[
        "video",
        "library"
    ],
    "wof:name":"Derik Parish Coachs",
    "wof:placetype":"venue"
},
  "geometry": {"coordinates":[-3.0190060139,53.2086448669],"type":"Point"}
}