{
  "type": "Feature",
  "properties": {
    "iso:country":"GB",
    "sg:address":"47 Chalmers Street, Ardrishaig",
    "sg:city":"Lochgilphead",
    "sg:classifiers":[
        {
            "category":"Shopping",
            "subcategory":"News",
            "type":"Retail Goods"
        }
    ],
    "sg:phone":"+44 1546 603481",
    "sg:postcode":"PA30 8EY",
    "sg:province":"Argyll and Bute",
    "sg:tags":[
        "newsagent"
    ],
    "wof:name":"Peter Law & Sons",
    "wof:placetype":"venue"
},
  "geometry": {"coordinates":[-5.4482750893,56.0158843994],"type":"Point"}
}