{
  "type": "Feature",
  "properties": {
    "addr:full":"Thorpe Road, Tattershall Thorpe Lincoln Lincolnshire LN4 4PE",
    "addr:postcode":"ln4 4pe",
    "addr:street":"Thorpe Road",
    "iso:country":"GB",
    "sg:address":"Thorpe Road, Tattershall Thorpe",
    "sg:city":"Lincoln",
    "sg:classifiers":[
        {
            "category":"Bars & Pubs",
            "type":"Food & Drink"
        }
    ],
    "sg:phone":"+44 1526 342206",
    "sg:postcode":"LN4 4PE",
    "sg:province":"Lincolnshire",
    "sg:tags":[
        "pubs",
        "house",
        "inn",
        "public",
        "activity"
    ],
    "wof:name":"The Blue Bell Inn",
    "wof:placetype":"venue"
},
  "geometry": {"coordinates":[-0.180285,53.107929],"type":"Point"}
}