{
  "type": "Feature",
  "properties": {
    "addr:full":"94 Streatham Hill London Greater London SW2 4RD",
    "addr:housenumber":"94",
    "addr:postcode":"sw2 4rd",
    "addr:street":"Streatham Hill",
    "iso:country":"GB",
    "sg:address":"94 Streatham Hill",
    "sg:city":"London",
    "sg:classifiers":[
        {
            "category":"Food & Beverages",
            "subcategory":"Bakery",
            "type":"Retail Goods"
        }
    ],
    "sg:phone":"+44 20 8674 6086",
    "sg:postcode":"SW2 4RD",
    "sg:province":"Greater London",
    "sg:tags":[
        "baker"
    ],
    "wof:name":"Pernet Ltd.",
    "wof:placetype":"venue"
},
  "geometry": {"coordinates":[-0.125451,51.440823],"type":"Point"}
}