{
  "type": "Feature",
  "properties": {
    "iso:country":"GB",
    "sg:address":"8 Masons Hill",
    "sg:city":"Bromley",
    "sg:classifiers":[
        {
            "category":"Organizations",
            "subcategory":"Non-profit Organization",
            "type":"Services"
        }
    ],
    "sg:phone":"+44 20 8313 3679",
    "sg:postcode":"BR2 9EY",
    "sg:province":"Kent",
    "sg:tags":[
        "organisation",
        "voluntary",
        "charity"
    ],
    "wof:name":"Greater London Childminding Association",
    "wof:placetype":"venue"
},
  "geometry": {"coordinates":[0.0185100008,51.3987007141],"type":"Point"}
}