{
  "type": "Feature",
  "properties": {
    "addr:full":"Raingills Farm, Ratcliffe Wharf Lane, Forton Preston Lancashire PR3 0AP",
    "addr:postcode":"pr3 0ap",
    "addr:street":"Wharf Lane",
    "iso:country":"GB",
    "sg:address":"Raingills Farm, Ratcliffe Wharf Lane, Forton",
    "sg:city":"Preston",
    "sg:classifiers":[
        {
            "category":"Professional",
            "subcategory":"Computer Services",
            "type":"Services"
        }
    ],
    "sg:postcode":"PR3 0AP",
    "sg:province":"Lancashire",
    "sg:tags":[
        "system",
        "software"
    ],
    "wof:name":"Cyborg I.T. Ltd",
    "wof:placetype":"venue"
},
  "geometry": {"coordinates":[-2.7814939022,53.9563865662],"type":"Point"}
}