{
  "type": "Feature",
  "properties": {
    "iso:country":"GB",
    "sg:address":"125 Jesmond Road",
    "sg:city":"Newcastle-upon-tyne",
    "sg:classifiers":[
        {
            "category":"Bars & Pubs",
            "type":"Food & Drink"
        }
    ],
    "sg:phone":"+44 191 281 2552",
    "sg:postcode":"NE2 1JY",
    "sg:province":"Tyne and Wear",
    "sg:tags":[
        "pubs",
        "inn"
    ],
    "wof:name":"The Punchbowl",
    "wof:placetype":"venue"
},
  "geometry": {"coordinates":[-1.596579,54.9856],"type":"Point"}
}