{
  "type": "Feature",
  "properties": {
    "iso:country":"GB",
    "sg:address":"101 Cavendish Street",
    "sg:city":"Keighley",
    "sg:classifiers":[
        {
            "category":"Shopping",
            "subcategory":"Clothing, Apparel, & Fashions",
            "type":"Retail Goods"
        }
    ],
    "sg:postcode":"BD21 3DG",
    "sg:province":"West Yorkshire",
    "sg:tags":[
        "shop"
    ],
    "wof:name":"Brooklyn Clothing Co",
    "wof:placetype":"venue"
},
  "geometry": {"coordinates":[-1.907968,53.868141],"type":"Point"}
}