{
  "type": "Feature",
  "properties": {
    "addr:full":"Parkgate Darlington Durham DL1 1RZ",
    "addr:postcode":"dl1 1rz",
    "addr:street":"Parkgate",
    "iso:country":"GB",
    "sg:address":"Parkgate",
    "sg:city":"Darlington",
    "sg:classifiers":[
        {
            "category":"Autos & Motor Vehicles",
            "subcategory":"Fuel & Gas Station",
            "type":"Retail Goods"
        }
    ],
    "sg:phone":"+44 1325 355600",
    "sg:postcode":"DL1 1RZ",
    "sg:province":"Durham",
    "sg:tags":[
        "petrol",
        "filling"
    ],
    "wof:name":"Priory Garages",
    "wof:placetype":"venue"
},
  "geometry": {"coordinates":[-1.548894,54.524502],"type":"Point"}
}