{
  "type": "Feature",
  "properties": {
    "iso:country":"GB",
    "sg:address":"The Hall, Upwell",
    "sg:city":"Wisbech",
    "sg:classifiers":[
        {
            "category":"Farming",
            "subcategory":"Livestock Farm",
            "type":"Manufacturing & Wholesale Goods"
        }
    ],
    "sg:postcode":"PE14 9DN",
    "sg:province":"Cambridgeshire",
    "sg:tags":[
        "others"
    ],
    "wof:name":"Roger Hartley Ltd",
    "wof:placetype":"venue"
},
  "geometry": {"coordinates":[0.20239,52.580292],"type":"Point"}
}