{
  "type": "Feature",
  "properties": {
    "iso:country":"GB",
    "sg:address":"Tower Ramparts Centre, Tavern Street",
    "sg:city":"Ipswich",
    "sg:classifiers":[
        {
            "category":"Shopping",
            "subcategory":"Clothing, Apparel, & Fashions",
            "type":"Retail Goods"
        }
    ],
    "sg:phone":"+44 1473 253522",
    "sg:postcode":"IP1 3BB",
    "sg:province":"Suffolk",
    "sg:tags":[
        "shop"
    ],
    "wof:name":"House of Leather",
    "wof:placetype":"venue"
},
  "geometry": {"coordinates":[1.15414,52.059361],"type":"Point"}
}