{
  "type": "Feature",
  "properties": {
    "addr:full":"49 Fore Bondgate Bishop Auckland Durham DL14 7PE",
    "addr:housenumber":"49",
    "addr:postcode":"dl14 7pe",
    "addr:street":"Fore Bondgate;Auckland",
    "iso:country":"GB",
    "sg:address":"49 Fore Bondgate",
    "sg:city":"Bishop Auckland",
    "sg:classifiers":[
        {
            "category":"Shopping",
            "subcategory":"Florist",
            "type":"Retail Goods"
        }
    ],
    "sg:phone":"+44 1388 604943",
    "sg:postcode":"DL14 7PE",
    "sg:province":"Durham",
    "wof:name":"Flowerworld",
    "wof:placetype":"venue"
},
  "geometry": {"coordinates":[-1.6761599779,54.6655197144],"type":"Point"}
}