{
  "type": "Feature",
  "properties": {
    "addr:full":"39 Shrub End Road Colchester Essex CO3 3UE",
    "addr:housenumber":"39",
    "addr:postcode":"co3 3ue",
    "addr:street":"Shrub End Road Colchester",
    "iso:country":"GB",
    "sg:address":"39 Shrub End Road",
    "sg:city":"Colchester",
    "sg:classifiers":[
        {
            "category":"Professional",
            "type":"Services"
        }
    ],
    "sg:postcode":"CO3 3UE",
    "sg:province":"Essex",
    "sg:tags":[
        "caterer"
    ],
    "wof:name":"Liz Bond Catering",
    "wof:placetype":"venue"
},
  "geometry": {"coordinates":[0.875267,51.878963],"type":"Point"}
}