{
  "type": "Feature",
  "properties": {
    "iso:country":"GB",
    "sg:address":"15 Banyard Way",
    "sg:city":"Rochford",
    "sg:classifiers":[
        {
            "category":"Bus Charters",
            "type":"Transportation"
        }
    ],
    "sg:postcode":"SS4 1UQ",
    "sg:province":"Essex",
    "sg:tags":[
        "hire",
        "coach"
    ],
    "wof:name":"Butcher,A K,",
    "wof:placetype":"venue"
},
  "geometry": {"coordinates":[0.6896749735,51.5951766968],"type":"Point"}
}