{
  "type": "Feature",
  "properties": {
    "addr:full":"Overdale, Grainbeck Lane, Killinghall Harrogate North Yorkshire HG3 2AA",
    "addr:postcode":"hg3 2aa",
    "addr:street":"Grainbeck Lane",
    "iso:country":"GB",
    "sg:address":"Overdale, Grainbeck Lane, Killinghall",
    "sg:city":"Harrogate",
    "sg:classifiers":[
        {
            "category":"Farming",
            "subcategory":"Nursery",
            "type":"Manufacturing & Wholesale Goods"
        },
        {
            "category":"Education",
            "subcategory":"Preschool",
            "type":"Public Place"
        }
    ],
    "sg:phone":"+44 1423 506361",
    "sg:postcode":"HG3 2AA",
    "sg:province":"North Yorkshire",
    "sg:tags":[
        "school",
        "creche"
    ],
    "wof:name":"Setting Sail Day Nursery",
    "wof:placetype":"venue"
},
  "geometry": {"coordinates":[-1.564256,54.024055],"type":"Point"}
}