{
  "type": "Feature",
  "properties": {
    "addr:full":"Ogmore Court, Merthyr Mawr Road Bridgend Bridgend CF31 3PN",
    "addr:postcode":"cf31 3pn",
    "addr:street":"Ogmore Court Merthyr Mawr Road",
    "iso:country":"GB",
    "sg:address":"Ogmore Court, Merthyr Mawr Road",
    "sg:city":"Bridgend",
    "sg:classifiers":[
        {
            "category":"Real Estate",
            "subcategory":"Developer",
            "type":"Services"
        }
    ],
    "sg:postcode":"CF31 3PN",
    "sg:province":"Bridgend",
    "sg:tags":[
        "property"
    ],
    "wof:name":"A O A Consulting",
    "wof:placetype":"venue"
},
  "geometry": {"coordinates":[-3.579824,51.501945],"type":"Point"}
}