{
  "type": "Feature",
  "properties": {
    "iso:country":"GB",
    "sg:address":"1 High Street, Helmsley",
    "sg:city":"York",
    "sg:classifiers":[
        {
            "category":"Cafe",
            "type":"Food & Drink"
        }
    ],
    "sg:phone":"+44 1439 770331",
    "sg:postcode":"YO62 5AE",
    "sg:province":"North Yorkshire",
    "sg:tags":[
        "tea",
        "room"
    ],
    "wof:name":"R F & C E Otterburn",
    "wof:placetype":"venue"
},
  "geometry": {"coordinates":[-1.063984,54.247303],"type":"Point"}
}