{
  "type": "Feature",
  "properties": {
    "addr:full":"99 High St Great Missenden Buckinghamshire HP16 0BB",
    "addr:housenumber":"99",
    "addr:postcode":"hp16 0bb",
    "addr:street":"High St",
    "iso:country":"GB",
    "sg:address":"99 High St",
    "sg:city":"Great Missenden",
    "sg:classifiers":[
        {
            "category":"Manufacturing",
            "subcategory":"Furniture",
            "type":"Manufacturing & Wholesale Goods"
        }
    ],
    "sg:phone":"+44 1494 890700",
    "sg:postcode":"HP16 0BB",
    "sg:province":"Buckinghamshire",
    "sg:tags":[
        "mnfr",
        "garden",
        "patio"
    ],
    "wof:name":"Global Collections",
    "wof:placetype":"venue"
},
  "geometry": {"coordinates":[-0.7054209709,51.7019538879],"type":"Point"}
}