{
  "type": "Feature",
  "properties": {
    "addr:full":"190-192 Ravenscroft Road Beckenham Kent BR3 4TW",
    "addr:housenumber":"190-192",
    "addr:postcode":"br3 4tw",
    "addr:street":"Ravenscroft Road",
    "iso:country":"GB",
    "sg:address":"190-192 Ravenscroft Road",
    "sg:city":"Beckenham",
    "sg:classifiers":[
        {
            "category":"Shopping",
            "subcategory":"Optical Goods",
            "type":"Retail Goods"
        }
    ],
    "sg:postcode":"BR3 4TW",
    "sg:province":"Kent",
    "wof:name":"I C Optical Systems Ltd.",
    "wof:placetype":"venue"
},
  "geometry": {"coordinates":[-0.0545030013,51.4069519043],"type":"Point"}
}