{
  "type": "Feature",
  "properties": {
    "iso:country":"GB",
    "sg:address":"15 The Hollow, Mickleover",
    "sg:city":"Derby",
    "sg:classifiers":[
        {
            "category":"Home & Garden",
            "subcategory":"Household Appliances",
            "type":"Retail Goods"
        }
    ],
    "sg:phone":"+44 1332 521220",
    "sg:postcode":"DE3 5DH",
    "sg:province":"Derbyshire",
    "sg:tags":[
        "cleaner",
        "vacuum"
    ],
    "wof:name":"Neptune Central",
    "wof:placetype":"venue"
},
  "geometry": {"coordinates":[-1.55039,52.906109],"type":"Point"}
}