{
  "type": "Feature",
  "properties": {
    "addr:full":"96 Embankment Road Plymouth Devon PL4 9HY",
    "addr:postcode":"pl4 9hy",
    "addr:street":"Embankment Road",
    "iso:country":"GB",
    "sg:address":"96 Embankment Road",
    "sg:city":"Plymouth",
    "sg:classifiers":[
        {
            "category":"Fast Food",
            "type":"Food & Drink"
        }
    ],
    "sg:phone":"+44 1752 227633",
    "sg:postcode":"PL4 9HY",
    "sg:province":"Devon",
    "sg:tags":[
        "away",
        "meal",
        "outlet",
        "take"
    ],
    "wof:name":"China Express",
    "wof:placetype":"venue"
},
  "geometry": {"coordinates":[-4.1194438934,50.3707389832],"type":"Point"}
}