{
  "type": "Feature",
  "properties": {
    "addr:full":"109 Leyland Trading Estate Wellingborough Northamptonshire NN8 1RT",
    "addr:housenumber":"109",
    "addr:postcode":"nn8 1rt",
    "addr:street":"Leyland Trading Estate",
    "iso:country":"GB",
    "sg:address":"109 Leyland Trading Estate",
    "sg:city":"Wellingborough",
    "sg:classifiers":[
        {
            "category":"Manufacturing",
            "subcategory":"Electronics",
            "type":"Manufacturing & Wholesale Goods"
        }
    ],
    "sg:phone":"+44 1933 442599",
    "sg:postcode":"NN8 1RT",
    "sg:province":"Northamptonshire",
    "sg:tags":[
        "computer",
        "-",
        "printed",
        "circuit"
    ],
    "wof:name":"Printquick Ltd.",
    "wof:placetype":"venue"
},
  "geometry": {"coordinates":[-0.6680529714,52.2999382019],"type":"Point"}
}