{
  "type": "Feature",
  "properties": {
    "iso:country":"GB",
    "sg:address":"83 Elton Road, Spiddington",
    "sg:city":"Peterborough",
    "sg:classifiers":[
        {
            "category":"Manufacturing",
            "subcategory":"Chemicals & Compounds",
            "type":"Manufacturing & Wholesale Goods"
        }
    ],
    "sg:phone":"+44 1780 783758",
    "sg:postcode":"PE8 6JX",
    "sg:province":"Cambridgeshire",
    "sg:tags":[
        "pesticide"
    ],
    "wof:name":"Piltland Technology Ltd.",
    "wof:placetype":"venue"
},
  "geometry": {"coordinates":[-0.402908,52.566196],"type":"Point"}
}