{
  "type": "Feature",
  "properties": {
    "addr:full":"41 Heol Dal-y-coppa, Llansamlet Swansea Neath Port Talbot SA7 9UZ",
    "addr:housenumber":"41",
    "addr:postcode":"sa7 9uz",
    "addr:street":"Heol Dal-Y-Coppa",
    "iso:country":"GB",
    "sg:address":"41 Heol Dal-y-coppa, Llansamlet",
    "sg:city":"Swansea",
    "sg:classifiers":[
        {
            "category":"Building & Trades",
            "subcategory":"Cleaning & Sanitation",
            "type":"Services"
        }
    ],
    "sg:phone":"+44 1792 796384",
    "sg:postcode":"SA7 9UZ",
    "sg:province":"Neath Port Talbot",
    "sg:tags":[
        "commercial"
    ],
    "wof:name":"Capital Cleaners Wales",
    "wof:placetype":"venue"
},
  "geometry": {"coordinates":[-3.901196003,51.6619682312],"type":"Point"}
}