{
  "type": "Feature",
  "properties": {
    "addr:full":"Leconfield House, Curzon St West End Hampshire W1Y 7FB",
    "addr:housenumber":"leconfield",
    "addr:postcode":"w1y 7fb",
    "addr:street":"Curzon St",
    "iso:country":"GB",
    "sg:address":"Leconfield House, Curzon St",
    "sg:city":"West End",
    "sg:classifiers":[
        {
            "category":"Professional",
            "subcategory":"Management & Consulting",
            "type":"Services"
        }
    ],
    "sg:phone":"+44 20 7355 1592",
    "sg:postcode":"W1Y 7FB",
    "sg:province":"Hampshire",
    "sg:tags":[
        "consultant",
        "business"
    ],
    "wof:name":"Atlantic Consulting",
    "wof:placetype":"venue"
},
  "geometry": {"coordinates":[-0.144951,51.507957],"type":"Point"}
}