{
  "type": "Feature",
  "properties": {
    "iso:country":"GB",
    "sg:address":"Artro Garage",
    "sg:city":"Llanbedr",
    "sg:classifiers":[
        {
            "category":"Autos & Motor Vehicles",
            "subcategory":"Automobile Sales",
            "type":"Retail Goods"
        }
    ],
    "sg:phone":"+44 1341 241347",
    "sg:postcode":"LL45 2HL",
    "sg:province":"Gwynedd",
    "sg:tags":[
        "car"
    ],
    "wof:name":"R G & K Autos",
    "wof:placetype":"venue"
},
  "geometry": {"coordinates":[-4.100939,52.819725],"type":"Point"}
}