{
  "type": "Feature",
  "properties": {
    "addr:full":"35 Tower Road Dartford Kent DA1 2HE",
    "addr:housenumber":"35",
    "addr:postcode":"da1 2he",
    "addr:street":"Tower Road",
    "iso:country":"GB",
    "sg:address":"35 Tower Road",
    "sg:city":"Dartford",
    "sg:classifiers":[
        {
            "category":"Retail",
            "subcategory":"Auto Repair",
            "type":"Services"
        }
    ],
    "sg:phone":"+44 1322 224270",
    "sg:postcode":"DA1 2HE",
    "sg:province":"Kent",
    "sg:tags":[
        "car",
        "upholsterer"
    ],
    "wof:name":"John Daws Trimming",
    "wof:placetype":"venue"
},
  "geometry": {"coordinates":[0.207,51.444199],"type":"Point"}
}