{
  "type": "Feature",
  "properties": {
    "iso:country":"GB",
    "sg:address":"43 Baker Street",
    "sg:city":"Brighton",
    "sg:classifiers":[
        {
            "category":"Personal",
            "subcategory":"Beauty Salon",
            "type":"Services"
        }
    ],
    "sg:phone":"+44 1273 670746",
    "sg:postcode":"BN1 4JN",
    "sg:province":"East Sussex",
    "sg:tags":[
        "unisex",
        "hairdresser"
    ],
    "wof:name":"Dreams",
    "wof:placetype":"venue"
},
  "geometry": {"coordinates":[-0.135115,50.831684],"type":"Point"}
}