{
  "type": "Feature",
  "properties": {
    "addr:full":"278-280 Brompton Rd Chelsea Greater London SW3 2AS",
    "addr:housenumber":"278-280",
    "addr:postcode":"sw3 2as",
    "addr:street":"Brompton Rd",
    "iso:country":"GB",
    "sg:address":"278-280 Brompton Rd",
    "sg:city":"Chelsea",
    "sg:classifiers":[
        {
            "category":"Home & Garden",
            "subcategory":"Furniture",
            "type":"Retail Goods"
        }
    ],
    "sg:phone":"+44 20 7589 4778",
    "sg:postcode":"SW3 2AS",
    "sg:province":"Greater London",
    "wof:name":"Decorative Fabrics Gallery",
    "wof:placetype":"venue"
},
  "geometry": {"coordinates":[-0.168989,51.493851],"type":"Point"}
}