{
  "type": "Feature",
  "properties": {
    "addr:full":"14 Park Street Windsor Berkshire SL4 1LU",
    "addr:housenumber":"14",
    "addr:postcode":"sl4 1lu",
    "addr:street":"Park Street",
    "iso:country":"GB",
    "sg:address":"14 Park Street",
    "sg:city":"Windsor",
    "sg:classifiers":[
        {
            "category":"Building & Trades",
            "subcategory":"Landscaping Services",
            "type":"Services"
        }
    ],
    "sg:phone":"+44 1753 836000",
    "sg:postcode":"SL4 1LU",
    "sg:province":"Berkshire",
    "sg:tags":[
        "horticultural",
        "consultant"
    ],
    "wof:name":"Southwest (U K) Ltd.",
    "wof:placetype":"venue"
},
  "geometry": {"coordinates":[-0.605428,51.480782],"type":"Point"}
}