{
  "type": "Feature",
  "properties": {
    "iso:country":"GB",
    "sg:address":"Stanley St",
    "sg:city":"Workington",
    "sg:classifiers":[
        {
            "category":"Real Estate",
            "subcategory":"Architect",
            "type":"Services"
        }
    ],
    "sg:postcode":"CA14 2JG",
    "sg:province":"Cumbria",
    "wof:name":"Holm,Eric,",
    "wof:placetype":"venue"
},
  "geometry": {"coordinates":[-3.5625190735,54.6460609436],"type":"Point"}
}