{
  "type": "Feature",
  "properties": {
    "addr:full":"Hillsborough Road Ilfracombe Devon EX34 9NP",
    "addr:postcode":"ex34 9np",
    "addr:street":"Hillsborough Road",
    "iso:country":"GB",
    "sg:address":"Hillsborough Road",
    "sg:city":"Ilfracombe",
    "sg:classifiers":[
        {
            "category":"Travel",
            "subcategory":"Hotels & Motels",
            "type":"Entertainment"
        }
    ],
    "sg:phone":"+44 1271 863606",
    "sg:postcode":"EX34 9NP",
    "sg:province":"Devon",
    "wof:name":"Cliffe Hydro Hotel",
    "wof:placetype":"venue"
},
  "geometry": {"coordinates":[-4.109302,51.206535],"type":"Point"}
}