{
  "type": "Feature",
  "properties": {
    "addr:full":"115 Hartington Road London Greater London SW8 2HB",
    "addr:housenumber":"115",
    "addr:postcode":"sw8 2hb",
    "addr:street":"Hartington Road",
    "iso:country":"GB",
    "sg:address":"115 Hartington Road",
    "sg:city":"London",
    "sg:classifiers":[
        {
            "category":"Professional",
            "subcategory":"Business Services",
            "type":"Services"
        },
        {
            "category":"Organizations",
            "subcategory":"Professional Association",
            "type":"Services"
        }
    ],
    "sg:postcode":"SW8 2HB",
    "sg:province":"Greater London",
    "sg:tags":[
        "organisation",
        "trade"
    ],
    "wof:name":"Exhibition Venue Association",
    "wof:placetype":"venue"
},
  "geometry": {"coordinates":[-0.1271539927,51.476600647],"type":"Point"}
}