{
  "type": "Feature",
  "properties": {
    "iso:country":"GB",
    "sg:address":"94 Norwich Rd",
    "sg:city":"Norwich",
    "sg:classifiers":[
        {
            "category":"Food & Beverages",
            "subcategory":"Groceries & Convenience Stores",
            "type":"Retail Goods"
        }
    ],
    "sg:phone":"+44 1603 742099",
    "sg:postcode":"NR5 0EH",
    "sg:province":"Norfolk",
    "wof:name":"Dillons",
    "wof:placetype":"venue"
},
  "geometry": {"coordinates":[1.23567,52.644325],"type":"Point"}
}