{
  "type": "Feature",
  "properties": {
    "iso:country":"GB",
    "sg:address":"20 Hunter Street",
    "sg:city":"Kirkcaldy",
    "sg:classifiers":[
        {
            "category":"Professional",
            "subcategory":"Printing & Photocopies",
            "type":"Services"
        }
    ],
    "sg:postcode":"KY1 1ED",
    "sg:province":"Fife",
    "sg:tags":[
        "duplicating",
        "copying"
    ],
    "wof:name":"Copysprint (Retail) Ltd.",
    "wof:placetype":"venue"
},
  "geometry": {"coordinates":[-3.1611669064,56.1107406616],"type":"Point"}
}