{
  "type": "Feature",
  "properties": {
    "iso:country":"GB",
    "sg:address":"High Street, Ludgershall",
    "sg:city":"Aylesbury",
    "sg:classifiers":[
        {
            "category":"Farming",
            "subcategory":"Livestock Farm",
            "type":"Manufacturing & Wholesale Goods"
        }
    ],
    "sg:phone":"+44 1844 238324",
    "sg:postcode":"HP18 9PF",
    "sg:province":"Buckinghamshire",
    "sg:tags":[
        "others"
    ],
    "wof:name":"Clifford W J East",
    "wof:placetype":"venue"
},
  "geometry": {"coordinates":[-1.052129,51.819855],"type":"Point"}
}