{
  "type": "Feature",
  "properties": {
    "iso:country":"GB",
    "sg:address":"129 High Road, Shillington",
    "sg:city":"Hitchin",
    "sg:classifiers":[
        {
            "category":"Education",
            "subcategory":"Special Training",
            "type":"Public Place"
        }
    ],
    "sg:phone":"+44 1462 711497",
    "sg:postcode":"SG5 3LU",
    "sg:province":"Bedfordshire",
    "sg:tags":[
        "product",
        "centre"
    ],
    "wof:name":"Outsource Sales Training Ltd.",
    "wof:placetype":"venue"
},
  "geometry": {"coordinates":[-0.367110014,51.9863395691],"type":"Point"}
}