{
  "type": "Feature",
  "properties": {
    "addr:full":"43 Molyneux Street London Greater London W1H 5HW",
    "addr:housenumber":"43",
    "addr:postcode":"w1h 5hw",
    "addr:street":"Molyneux Street",
    "iso:country":"GB",
    "sg:address":"43 Molyneux Street",
    "sg:city":"London",
    "sg:classifiers":[
        {
            "category":"Health Services",
            "subcategory":"Health Practitioner",
            "type":"Services"
        }
    ],
    "sg:postcode":"W1H 5HW",
    "sg:province":"Greater London",
    "sg:tags":[
        "osteopath"
    ],
    "wof:name":"Erica Salisbury",
    "wof:placetype":"venue"
},
  "geometry": {"coordinates":[-0.1646340042,51.5183448792],"type":"Point"}
}