{
  "type": "Feature",
  "properties": {
    "addr:full":"St Anns Well Rd Nottingham Nottinghamshire NG3 1ED",
    "addr:postcode":"ng3 1ed",
    "addr:street":"St;Well Rd",
    "iso:country":"GB",
    "sg:address":"St Anns Well Rd",
    "sg:city":"Nottingham",
    "sg:classifiers":[
        {
            "category":"Organizations",
            "subcategory":"Membership Organization",
            "type":"Services"
        }
    ],
    "sg:phone":"+44 115 958 0101",
    "sg:postcode":"NG3 1ED",
    "sg:province":"Nottinghamshire",
    "sg:tags":[
        "club"
    ],
    "wof:name":"Gala Clubs",
    "wof:placetype":"venue"
},
  "geometry": {"coordinates":[-1.141959,52.958065],"type":"Point"}
}