{
  "type": "Feature",
  "properties": {
    "addr:full":"45 St Patrick Square Edinburgh City of Edinburgh EH8 9ET",
    "addr:housenumber":"45",
    "addr:postcode":"eh8 9et",
    "addr:street":"St Patrick Square",
    "iso:country":"GB",
    "sg:address":"45 St Patrick Square",
    "sg:city":"Edinburgh",
    "sg:classifiers":[
        {
            "category":"Food & Beverages",
            "subcategory":"Specialty",
            "type":"Retail Goods"
        },
        {
            "category":"Restaurant",
            "type":"Food & Drink"
        }
    ],
    "sg:phone":"+44 131 662 1807",
    "sg:postcode":"EH8 9ET",
    "sg:province":"City of Edinburgh",
    "sg:tags":[
        "vegetarian",
        "-"
    ],
    "wof:name":"Annpurna Vegetarian Restaurant",
    "wof:placetype":"venue"
},
  "geometry": {"coordinates":[-3.1836829185,55.9434547424],"type":"Point"}
}