{
  "type": "Feature",
  "properties": {
    "addr:full":"29 Pepys Road London Greater London SE14 5SA",
    "addr:housenumber":"29",
    "addr:postcode":"se14 5sa",
    "addr:street":"Pepys Road",
    "iso:country":"GB",
    "sg:address":"29 Pepys Road",
    "sg:city":"London",
    "sg:classifiers":[
        {
            "category":"Shopping",
            "subcategory":"Musical Instruments",
            "type":"Retail Goods"
        }
    ],
    "sg:postcode":"SE14 5SA",
    "sg:province":"Greater London",
    "wof:name":"Ashley Targett",
    "wof:placetype":"venue"
},
  "geometry": {"coordinates":[-0.045091,51.472721],"type":"Point"}
}