{
  "type": "Feature",
  "properties": {
    "iso:country":"GB",
    "sg:address":"34 Ashley Terrace",
    "sg:city":"Edinburgh",
    "sg:classifiers":[
        {
            "category":"Professional",
            "subcategory":"Computer Services",
            "type":"Services"
        }
    ],
    "sg:phone":"+44 131 337 4130",
    "sg:postcode":"EH11 1RE",
    "sg:province":"City of Edinburgh",
    "sg:tags":[
        "system",
        "software"
    ],
    "wof:name":"Odessa Fibrecomm",
    "wof:placetype":"venue"
},
  "geometry": {"coordinates":[-3.216409,55.941124],"type":"Point"}
}