{
  "type": "Feature",
  "properties": {
    "addr:full":"Black Rock Mills, Waingate, Linthwaite Huddersfield West Yorkshire HD7 5NS",
    "addr:postcode":"hd7 5ns",
    "addr:street":"Black Rock;Waingate;West",
    "iso:country":"GB",
    "sg:address":"Black Rock Mills, Waingate, Linthwaite",
    "sg:city":"Huddersfield",
    "sg:classifiers":[
        {
            "category":"Shopping",
            "subcategory":"Stationery & Office Supplies",
            "type":"Retail Goods"
        }
    ],
    "sg:postcode":"HD7 5NS",
    "sg:province":"West Yorkshire",
    "wof:name":"Alpine Packaging Ltd",
    "wof:placetype":"venue"
},
  "geometry": {"coordinates":[-1.8474090099,53.6258544922],"type":"Point"}
}