{
  "type": "Feature",
  "properties": {
    "addr:full":"Nest Road, Felling Shore Industrial Estate Gateshead Tyne and Wear NE10 0ES",
    "addr:postcode":"ne10 0es",
    "addr:street":"Nest Road Felling Shore Industrial Estate",
    "iso:country":"GB",
    "sg:address":"Nest Road, Felling Shore Industrial Estate",
    "sg:city":"Gateshead",
    "sg:classifiers":[
        {
            "category":"Professional",
            "subcategory":"Detective & Security Services",
            "type":"Services"
        }
    ],
    "sg:phone":"+44 191 469 7511",
    "sg:postcode":"NE10 0ES",
    "sg:province":"Tyne and Wear",
    "wof:name":"Securitas",
    "wof:placetype":"venue"
},
  "geometry": {"coordinates":[-1.5674860477,54.9604644775],"type":"Point"}
}