{
  "type": "Feature",
  "properties": {
    "addr:full":"Slackend Farm Buckie Moray AB56 2BS",
    "addr:postcode":"ab56 2bs",
    "iso:country":"GB",
    "sg:address":"Slackend Farm",
    "sg:city":"Buckie",
    "sg:classifiers":[
        {
            "category":"Home & Garden",
            "subcategory":"Garden Supply",
            "type":"Retail Goods"
        },
        {
            "category":"Farming",
            "subcategory":"Farm",
            "type":"Manufacturing & Wholesale Goods"
        }
    ],
    "sg:postcode":"AB56 2BS",
    "sg:province":"Moray",
    "sg:tags":[
        "mixed",
        "bulb",
        "crop",
        "grower"
    ],
    "wof:name":"I Farquhar",
    "wof:placetype":"venue"
},
  "geometry": {"coordinates":[-2.9652240276,57.676700592],"type":"Point"}
}