{
  "type": "Feature",
  "properties": {
    "addr:full":"Ripley Drive, Normanton Industrial Estate Normanton West Yorkshire WF6 1RY",
    "addr:housenumber":"estate",
    "addr:postcode":"wf6 1ry",
    "addr:street":"Ripley Drive Normanton Industrial;West",
    "iso:country":"GB",
    "sg:address":"Ripley Drive, Normanton Industrial Estate",
    "sg:city":"Normanton",
    "sg:classifiers":[
        {
            "category":"Cafe",
            "type":"Food & Drink"
        }
    ],
    "sg:phone":"+44 1924 223231",
    "sg:postcode":"WF6 1RY",
    "sg:province":"West Yorkshire",
    "sg:tags":[
        "tea",
        "room"
    ],
    "wof:name":"D J's Canteen",
    "wof:placetype":"venue"
},
  "geometry": {"coordinates":[-1.397299,53.705505],"type":"Point"}
}