{
  "type": "Feature",
  "properties": {
    "iso:country":"GB",
    "sg:address":"100 High St, Bushey",
    "sg:city":"Watford",
    "sg:classifiers":[
        {
            "category":"Restaurant",
            "type":"Food & Drink"
        }
    ],
    "sg:phone":"+44 20 8950 4990",
    "sg:postcode":"WD2 3DE",
    "sg:province":"Hertfordshire",
    "sg:tags":[
        "chinese"
    ],
    "wof:name":"Zins Palace",
    "wof:placetype":"venue"
},
  "geometry": {"coordinates":[-0.36307,51.644341],"type":"Point"}
}