{
  "type": "Feature",
  "properties": {
    "addr:full":"14 Carlton Road Southampton Hampshire SO15 2HQ",
    "addr:housenumber":"14",
    "addr:postcode":"so15 2hq",
    "addr:street":"Carlton Road",
    "iso:country":"GB",
    "sg:address":"14 Carlton Road",
    "sg:city":"Southampton",
    "sg:classifiers":[
        {
            "category":"Insurance",
            "subcategory":"Insurance Agent",
            "type":"Services"
        }
    ],
    "sg:postcode":"SO15 2HQ",
    "sg:province":"Hampshire",
    "sg:tags":[
        "broker"
    ],
    "wof:name":"Nicholas & Neal Ltd.",
    "wof:placetype":"venue"
},
  "geometry": {"coordinates":[-1.406467,50.914909],"type":"Point"}
}