{
  "type": "Feature",
  "properties": {
    "addr:full":"Scotts Cottage, Cann Common Shaftesbury Dorset SP7 0EB",
    "addr:postcode":"sp7 0eb",
    "addr:street":"Cann Common",
    "iso:country":"GB",
    "sg:address":"Scotts Cottage, Cann Common",
    "sg:city":"Shaftesbury",
    "sg:classifiers":[
        {
            "category":"Professional",
            "subcategory":"Engineering",
            "type":"Services"
        },
        {
            "category":"Professional",
            "subcategory":"Secretarial Services",
            "type":"Services"
        }
    ],
    "sg:phone":"+44 1747 855639",
    "sg:postcode":"SP7 0EB",
    "sg:province":"Dorset",
    "sg:tags":[
        "contractor",
        "electrical",
        "engineer"
    ],
    "wof:name":"Hopgood L Book-Keeping & Secretarial Services",
    "wof:placetype":"venue"
},
  "geometry": {"coordinates":[-2.166904,50.987446],"type":"Point"}
}