{
  "type": "Feature",
  "properties": {
    "addr:full":"13 Oscar Road Broadstairs Kent CT10 1QJ",
    "addr:housenumber":"13",
    "addr:postcode":"ct10 1qj",
    "addr:street":"Oscar Road",
    "iso:country":"GB",
    "sg:address":"13 Oscar Road",
    "sg:city":"Broadstairs",
    "sg:classifiers":[
        {
            "category":"Shopping",
            "subcategory":"Hobbies, Toys, & Games",
            "type":"Retail Goods"
        },
        {
            "category":"Professional",
            "subcategory":"Business Services",
            "type":"Services"
        }
    ],
    "sg:phone":"+44 1843 601675",
    "sg:postcode":"CT10 1QJ",
    "sg:province":"Kent",
    "sg:tags":[
        "stamp",
        "import",
        "export",
        "agent"
    ],
    "wof:name":"The Stamp Shop",
    "wof:placetype":"venue"
},
  "geometry": {"coordinates":[1.440677,51.356762],"type":"Point"}
}