{
  "type": "Feature",
  "properties": {
    "addr:full":"Unit 2, East Moors Business Park, East Moors Road Cardiff Cardiff CF1 5JX",
    "addr:housenumber":"unit 2",
    "addr:postcode":"cf1 5jx",
    "addr:street":"East Moors Business Park East Moors Road",
    "iso:country":"GB",
    "sg:address":"Unit 2, East Moors Business Park, East Moors Road",
    "sg:city":"Cardiff",
    "sg:classifiers":[
        {
            "category":"Manufacturing",
            "subcategory":"Rubber & Plastics",
            "type":"Manufacturing & Wholesale Goods"
        }
    ],
    "sg:phone":"+44 29 2048 9559",
    "sg:postcode":"CF1 5JX",
    "sg:province":"Cardiff",
    "sg:tags":[
        "seal"
    ],
    "wof:name":"M Barnwell Services Ltd.",
    "wof:placetype":"venue"
},
  "geometry": {"coordinates":[-3.180670023,51.4812583923],"type":"Point"}
}