{
  "type": "Feature",
  "properties": {
    "iso:country":"GB",
    "sg:address":"32 Lingwood Gardens",
    "sg:city":"Isleworth",
    "sg:classifiers":[
        {
            "category":"Building & Trades",
            "subcategory":"Construction",
            "type":"Services"
        }
    ],
    "sg:phone":"+44 20 8568 2461",
    "sg:postcode":"TW7 5LZ",
    "sg:province":"Greater London",
    "sg:tags":[
        "builder"
    ],
    "wof:name":"Hurst Builders",
    "wof:placetype":"venue"
},
  "geometry": {"coordinates":[-0.341213,51.484825],"type":"Point"}
}