{
  "type": "Feature",
  "properties": {
    "iso:country":"GB",
    "sg:address":"57 Ayr Road",
    "sg:city":"Prestwick",
    "sg:classifiers":[
        {
            "category":"Retail",
            "subcategory":"Driving School",
            "type":"Services"
        }
    ],
    "sg:phone":"+44 1292 470893",
    "sg:postcode":"KA9 1SY",
    "sg:province":"South Ayrshire",
    "wof:name":"Chilles School of Motoring",
    "wof:placetype":"venue"
},
  "geometry": {"coordinates":[-4.6157388687,55.4908409119],"type":"Point"}
}