{
  "type": "Feature",
  "properties": {
    "addr:full":"10 Farm Lane Purley Surrey CR8 3PU",
    "addr:housenumber":"10",
    "addr:postcode":"cr8 3pu",
    "addr:street":"Farm Lane",
    "iso:country":"GB",
    "sg:address":"10 Farm Lane",
    "sg:city":"Purley",
    "sg:classifiers":[
        {
            "category":"Professional",
            "subcategory":"Business Services",
            "type":"Services"
        }
    ],
    "sg:postcode":"CR8 3PU",
    "sg:province":"Surrey",
    "sg:tags":[
        "accomodation"
    ],
    "wof:name":"J.J.and E.L.Developments Limited",
    "wof:placetype":"venue"
},
  "geometry": {"coordinates":[-0.1447760016,51.3425636292],"type":"Point"}
}