{
  "type": "Feature",
  "properties": {
    "addr:full":"Forest Road, Huncote Leicester Leicestershire LE9 3LE",
    "addr:postcode":"le9 3le",
    "addr:street":"Forest Road",
    "iso:country":"GB",
    "sg:address":"Forest Road, Huncote",
    "sg:city":"Leicester",
    "sg:classifiers":[
        {
            "category":"Home & Garden",
            "subcategory":"Garden Supply",
            "type":"Retail Goods"
        },
        {
            "category":"Home & Garden",
            "subcategory":"Building Materials",
            "type":"Retail Goods"
        }
    ],
    "sg:phone":"+44 116 286 4871",
    "sg:postcode":"LE9 3LE",
    "sg:province":"Leicestershire",
    "sg:tags":[
        "shale",
        "supplier",
        "sand",
        "including",
        "aggregate",
        "gravel"
    ],
    "wof:name":"Acresford Sand & Gravel Ltd",
    "wof:placetype":"venue"
},
  "geometry": {"coordinates":[-1.237541,52.571842],"type":"Point"}
}