{
  "type": "Feature",
  "properties": {
    "addr:full":"Derby Road, Stapleford Nottingham Nottinghamshire NG9 7AZ",
    "addr:postcode":"ng9 7az",
    "addr:street":"Derby Road",
    "iso:country":"GB",
    "sg:address":"Derby Road, Stapleford",
    "sg:city":"Nottingham",
    "sg:classifiers":[
        {
            "category":"Bars & Pubs",
            "type":"Food & Drink"
        }
    ],
    "sg:phone":"+44 115 939 7351",
    "sg:postcode":"NG9 7AZ",
    "sg:province":"Nottinghamshire",
    "sg:tags":[
        "pubs",
        "inn"
    ],
    "wof:name":"The Midland",
    "wof:placetype":"venue"
},
  "geometry": {"coordinates":[-1.275307,52.929298],"type":"Point"}
}