{
  "type": "Feature",
  "properties": {
    "addr:full":"4 Ashbourne Parade London Greater London W5 3QS",
    "addr:housenumber":"4",
    "addr:postcode":"w5 3qs",
    "addr:street":"Ashbourne Parade",
    "iso:country":"GB",
    "sg:address":"4 Ashbourne Parade",
    "sg:city":"London",
    "sg:classifiers":[
        {
            "category":"Shopping",
            "subcategory":"Department Store",
            "type":"Retail Goods"
        },
        {
            "category":"Food & Beverages",
            "subcategory":"Groceries & Convenience Stores",
            "type":"Retail Goods"
        }
    ],
    "sg:phone":"+44 20 8998 1391",
    "sg:postcode":"W5 3QS",
    "sg:province":"Greater London",
    "wof:name":"Ashbourne Parade Post Office",
    "wof:placetype":"venue"
},
  "geometry": {"coordinates":[-0.2863500118,51.5230674744],"type":"Point"}
}