{
  "type": "Feature",
  "properties": {
    "iso:country":"GB",
    "sg:address":"454 Scalby Rd",
    "sg:city":"Scarborough",
    "sg:classifiers":[
        {
            "category":"Banks & Credit Unions",
            "subcategory":"Bank",
            "type":"Services"
        }
    ],
    "sg:phone":"+44 1723 361331",
    "sg:postcode":"YO12 6EE",
    "sg:province":"North Yorkshire",
    "wof:name":"NatWest",
    "wof:placetype":"venue"
},
  "geometry": {"coordinates":[-0.44199,54.296528],"type":"Point"}
}