{
  "type": "Feature",
  "properties": {
    "iso:country":"GB",
    "sg:address":"118-120 Ewell Rd",
    "sg:city":"Surbiton",
    "sg:classifiers":[
        {
            "category":"Shopping",
            "type":"Retail Goods"
        }
    ],
    "sg:postcode":"KT6 6HA",
    "sg:province":"Surrey",
    "sg:tags":[
        "equipment",
        "clothing",
        "safety"
    ],
    "wof:name":"Melitzer",
    "wof:placetype":"venue"
},
  "geometry": {"coordinates":[-0.298,51.389923],"type":"Point"}
}