{
  "type": "Feature",
  "properties": {
    "addr:full":"15 Granby Street, Littleport Ely Cambridgeshire CB6 1NE",
    "addr:housenumber":"15",
    "addr:postcode":"cb6 1ne",
    "addr:street":"Granby Street",
    "iso:country":"GB",
    "sg:address":"15 Granby Street, Littleport",
    "sg:city":"Ely",
    "sg:classifiers":[
        {
            "category":"Recreation",
            "subcategory":"Fishing",
            "type":"Entertainment"
        }
    ],
    "sg:phone":"+44 1353 860419",
    "sg:postcode":"CB6 1NE",
    "sg:province":"Cambridgeshire",
    "sg:tags":[
        "angling"
    ],
    "wof:name":"Colebys Fishing Tackle",
    "wof:placetype":"venue"
},
  "geometry": {"coordinates":[0.307642,52.457253],"type":"Point"}
}