{
  "type": "Feature",
  "properties": {
    "iso:country":"GB",
    "sg:address":"3 West Street, Millbrook",
    "sg:city":"Torpoint",
    "sg:classifiers":[
        {
            "category":"Retail",
            "subcategory":"Laundry & Dry Cleaning",
            "type":"Services"
        }
    ],
    "sg:phone":"+44 1752 823999",
    "sg:postcode":"PL10 1AA",
    "sg:province":"Cornwall",
    "sg:tags":[
        "launderette"
    ],
    "wof:name":"Tamar Laundry Service",
    "wof:placetype":"venue"
},
  "geometry": {"coordinates":[-4.217769,50.347366],"type":"Point"}
}