{
  "type": "Feature",
  "properties": {
    "iso:country":"GB",
    "sg:address":"The Old Glasshouse, South Street",
    "sg:city":"Wells",
    "sg:classifiers":[
        {
            "category":"Travel",
            "subcategory":"Hostel",
            "type":"Entertainment"
        },
        {
            "category":"Community Center",
            "subcategory":"Youth",
            "type":"Public Place"
        }
    ],
    "sg:phone":"+44 1749 679553",
    "sg:postcode":"BA5 1SL",
    "sg:province":"Somerset",
    "sg:tags":[
        "organisation",
        "centre"
    ],
    "wof:name":"Mendip Young Men's Christian Association",
    "wof:placetype":"venue"
},
  "geometry": {"coordinates":[-2.719279,51.237911],"type":"Point"}
}