{
  "type": "Feature",
  "properties": {
    "iso:country":"GB",
    "sg:address":"26 Cartmel Road",
    "sg:city":"Bexleyheath",
    "sg:classifiers":[
        {
            "category":"Professional",
            "type":"Services"
        },
        {
            "category":"Arts & Performance",
            "subcategory":"Music",
            "type":"Entertainment"
        }
    ],
    "sg:phone":"+44 1322 430779",
    "sg:postcode":"DA7 5EA",
    "sg:province":"Kent",
    "sg:tags":[
        "entertainer",
        "musician",
        "composer"
    ],
    "wof:name":"Thames Fanfare Brass",
    "wof:placetype":"venue"
},
  "geometry": {"coordinates":[0.1476310045,51.4718818665],"type":"Point"}
}