{
  "type": "Feature",
  "properties": {
    "iso:country":"GB",
    "sg:address":"Merle Court Uphill Way, Hunston",
    "sg:city":"Chichester",
    "sg:classifiers":[
        {
            "category":"Social Services",
            "subcategory":"Adult Care",
            "type":"Services"
        },
        {
            "category":"Government",
            "subcategory":"Office",
            "type":"Public Place"
        }
    ],
    "sg:phone":"+44 1243 779999",
    "sg:postcode":"PO20 1QE",
    "sg:province":"West Sussex",
    "sg:tags":[
        "housing",
        "local",
        "sheltered"
    ],
    "wof:name":"Merle Court Sheltered Housing",
    "wof:placetype":"venue"
},
  "geometry": {"coordinates":[-0.781107,50.807186],"type":"Point"}
}