{
  "type": "Feature",
  "properties": {
    "iso:country":"GB",
    "sg:address":"12 Busty Bank, Burnopfield",
    "sg:city":"Newcastle Upon Tyne",
    "sg:classifiers":[
        {
            "category":"Education",
            "subcategory":"Library",
            "type":"Public Place"
        }
    ],
    "sg:phone":"+44 1207 271937",
    "sg:postcode":"NE16 6NF",
    "sg:province":"Durham",
    "sg:tags":[
        "book"
    ],
    "wof:name":"Burnopfield Library",
    "wof:placetype":"venue"
},
  "geometry": {"coordinates":[-1.722233,54.907028],"type":"Point"}
}