{
  "type": "Feature",
  "properties": {
    "addr:full":"Market Place, Barnsley Road, South Elmsall Pontefract West Yorkshire WF9 2SE",
    "addr:postcode":"wf9 2se",
    "addr:street":"Market Place Barnsley Road South;Pontefract West",
    "iso:country":"GB",
    "sg:address":"Market Place, Barnsley Road, South Elmsall",
    "sg:city":"Pontefract",
    "sg:classifiers":[
        {
            "category":"Food & Beverages",
            "subcategory":"Meat & Fish",
            "type":"Retail Goods"
        }
    ],
    "sg:postcode":"WF9 2SE",
    "sg:province":"West Yorkshire",
    "sg:tags":[
        "butcher"
    ],
    "wof:name":"Allens Butchers",
    "wof:placetype":"venue"
},
  "geometry": {"coordinates":[-1.281007,53.598312],"type":"Point"}
}