{
  "type": "Feature",
  "properties": {
    "iso:country":"GB",
    "sg:address":"Unit 3 Richard Street",
    "sg:city":"Stockport",
    "sg:classifiers":[
        {
            "category":"Home & Garden",
            "subcategory":"Home Furnishings",
            "type":"Retail Goods"
        }
    ],
    "sg:postcode":"SK1 2AX",
    "sg:province":"Cheshire",
    "sg:tags":[
        "racking",
        "shelving",
        "diy"
    ],
    "wof:name":"Manchester Racking",
    "wof:placetype":"venue"
},
  "geometry": {"coordinates":[-2.1523358822,53.4148101807],"type":"Point"}
}