{
  "type": "Feature",
  "properties": {
    "addr:full":"176 Corporation Road Birkenhead Merseyside CH41 8JQ",
    "addr:housenumber":"176",
    "addr:postcode":"ch41 8jq",
    "addr:street":"Corporation Road",
    "iso:country":"GB",
    "sg:address":"176 Corporation Road",
    "sg:city":"Birkenhead",
    "sg:classifiers":[
        {
            "category":"Organizations",
            "subcategory":"Non-profit Organization",
            "type":"Services"
        }
    ],
    "sg:postcode":"CH41 8JQ",
    "sg:province":"Merseyside",
    "sg:tags":[
        "organisation",
        "voluntary",
        "charity"
    ],
    "wof:name":"Women's Enterprising Breakthrough",
    "wof:placetype":"venue"
},
  "geometry": {"coordinates":[-3.058143,53.402016],"type":"Point"}
}