{
  "type": "Feature",
  "properties": {
    "addr:full":"Unit 1 & 2 Calder Works Castleford West Yorkshire WF10 1NX",
    "addr:housenumber":"unit 1 & 2",
    "addr:postcode":"wf10 1nx",
    "addr:street":"Calder Works Castleford West",
    "iso:country":"GB",
    "sg:address":"Unit 1 & 2 Calder Works",
    "sg:city":"Castleford",
    "sg:classifiers":[
        {
            "category":"Shopping",
            "subcategory":"Computers & Home Electronics",
            "type":"Retail Goods"
        }
    ],
    "sg:phone":"+44 1977 517555",
    "sg:postcode":"WF10 1NX",
    "sg:province":"West Yorkshire",
    "sg:tags":[
        "electrical"
    ],
    "wof:name":"Hyco Manufacturing Ltd.",
    "wof:placetype":"venue"
},
  "geometry": {"coordinates":[-1.364553,53.728069],"type":"Point"}
}