{
  "type": "Feature",
  "properties": {
    "addr:full":"33 Summerstown London Greater London SW17 0BQ",
    "addr:housenumber":"33",
    "addr:postcode":"sw17 0bq",
    "addr:street":"Summerstown",
    "iso:country":"GB",
    "sg:address":"33 Summerstown",
    "sg:city":"London",
    "sg:classifiers":[
        {
            "category":"Professional",
            "subcategory":"Art Services",
            "type":"Services"
        }
    ],
    "sg:phone":"+44 7974 083683",
    "sg:postcode":"SW17 0BQ",
    "sg:province":"Greater London",
    "sg:tags":[
        "graphic",
        "designer"
    ],
    "wof:name":"Carte Blanche",
    "wof:placetype":"venue"
},
  "geometry": {"coordinates":[-0.185018003,51.4326171875],"type":"Point"}
}