{
  "type": "Feature",
  "properties": {
    "iso:country":"GB",
    "sg:address":"Unit 3 Waterloo Street, Market Rasen",
    "sg:city":"Lincoln",
    "sg:classifiers":[
        {
            "category":"Professional",
            "subcategory":"Employment Agencies",
            "type":"Services"
        }
    ],
    "sg:phone":"+44 1673 844181",
    "sg:postcode":"LN8 3EP",
    "sg:province":"Lincolnshire",
    "sg:tags":[
        "agricultural",
        "advice"
    ],
    "wof:name":"Beltec (Market Rasen) Ltd.",
    "wof:placetype":"venue"
},
  "geometry": {"coordinates":[-0.335788995,53.3878860474],"type":"Point"}
}