{
  "type": "Feature",
  "properties": {
    "iso:country":"GB",
    "sg:address":"Moat Farm, Main Street, Glooston",
    "sg:city":"Market Harborough",
    "sg:classifiers":[
        {
            "category":"Farming",
            "subcategory":"Farm",
            "type":"Manufacturing & Wholesale Goods"
        }
    ],
    "sg:phone":"+44 1858 545272",
    "sg:postcode":"LE16 7ST",
    "sg:province":"Leicestershire",
    "sg:tags":[
        "mixed",
        "crop"
    ],
    "wof:name":"Bryn D Pugh",
    "wof:placetype":"venue"
},
  "geometry": {"coordinates":[-0.9225789905,52.4793968201],"type":"Point"}
}