{
  "type": "Feature",
  "properties": {
    "addr:full":"74 Royal Parade Eastbourne East Sussex BN22 7AQ",
    "addr:housenumber":"74",
    "addr:postcode":"bn22 7aq",
    "addr:street":"Royal Parade",
    "iso:country":"GB",
    "sg:address":"74 Royal Parade",
    "sg:city":"Eastbourne",
    "sg:classifiers":[
        {
            "category":"Travel",
            "subcategory":"Hotels & Motels",
            "type":"Entertainment"
        }
    ],
    "sg:phone":"+44 1323 720059",
    "sg:postcode":"BN22 7AQ",
    "sg:province":"East Sussex",
    "wof:name":"Debra Fox",
    "wof:placetype":"venue"
},
  "geometry": {"coordinates":[0.299829,50.77475],"type":"Point"}
}