{
  "type": "Feature",
  "properties": {
    "addr:full":"176 Franciscan Road London Greater London SW17 8HH",
    "addr:housenumber":"176",
    "addr:postcode":"sw17 8hh",
    "addr:street":"Franciscan Road",
    "iso:country":"GB",
    "sg:address":"176 Franciscan Road",
    "sg:city":"London",
    "sg:classifiers":[
        {
            "category":"Building & Trades",
            "subcategory":"Construction",
            "type":"Services"
        }
    ],
    "sg:postcode":"SW17 8HH",
    "sg:province":"Greater London",
    "sg:tags":[
        "builder"
    ],
    "wof:name":"Mostrim Construction Ltd",
    "wof:placetype":"venue"
},
  "geometry": {"coordinates":[-0.160886,51.427868],"type":"Point"}
}