{
  "type": "Feature",
  "properties": {
    "iso:country":"GB",
    "sg:address":"Units 7 & 8, Simmonds Buildings, Bristol Road",
    "sg:city":"Bristol",
    "sg:classifiers":[
        {
            "category":"Home & Garden",
            "subcategory":"Hardware",
            "type":"Retail Goods"
        }
    ],
    "sg:postcode":"BS16 1RY",
    "sg:province":"City of Bristol",
    "sg:tags":[
        "sealant",
        "glue",
        "adhesives"
    ],
    "wof:name":"S & D Sealants Ltd.",
    "wof:placetype":"venue"
},
  "geometry": {"coordinates":[-2.51634,51.508732],"type":"Point"}
}