{
  "type": "Feature",
  "properties": {
    "addr:full":"Boardenhouse Farm March Cambridgeshire PE15 0UR",
    "addr:postcode":"pe15 0ur",
    "addr:street":"March",
    "iso:country":"GB",
    "sg:address":"Boardenhouse Farm",
    "sg:city":"March",
    "sg:classifiers":[
        {
            "category":"Utilities",
            "subcategory":"Refuse",
            "type":"Services"
        }
    ],
    "sg:phone":"+44 1354 657625",
    "sg:postcode":"PE15 0UR",
    "sg:province":"Cambridgeshire",
    "sg:tags":[
        "disposal",
        "waste"
    ],
    "wof:name":"E & C Rubbish Clearance Services",
    "wof:placetype":"venue"
},
  "geometry": {"coordinates":[0.0889049992,52.5512542725],"type":"Point"}
}