{
  "type": "Feature",
  "properties": {
    "iso:country":"GB",
    "sg:address":"244 Church Lane",
    "sg:city":"London",
    "sg:classifiers":[
        {
            "category":"Personal",
            "subcategory":"Beauty Salon",
            "type":"Services"
        }
    ],
    "sg:phone":"+44 20 8205 1203",
    "sg:postcode":"NW9 8SL",
    "sg:province":"Greater London",
    "sg:tags":[
        "unisex",
        "hairdresser"
    ],
    "wof:name":"Cutting Crew Hair Designers",
    "wof:placetype":"venue"
},
  "geometry": {"coordinates":[-0.2620199919,51.574180603],"type":"Point"}
}