{
  "type": "Feature",
  "properties": {
    "addr:full":"Victoria Street Darwen Lancashire BB3 3HB",
    "addr:postcode":"bb3 3hb",
    "addr:street":"Victoria Street",
    "iso:country":"GB",
    "sg:address":"Victoria Street",
    "sg:city":"Darwen",
    "sg:classifiers":[
        {
            "category":"Health Services",
            "subcategory":"Health Practitioner",
            "type":"Services"
        }
    ],
    "sg:phone":"+44 1254 703151",
    "sg:postcode":"BB3 3HB",
    "sg:province":"Lancashire",
    "sg:tags":[
        "physiotherapist"
    ],
    "wof:name":"Darwen Physiotherapy Clinic",
    "wof:placetype":"venue"
},
  "geometry": {"coordinates":[-2.465469,53.694736],"type":"Point"}
}