{
  "type": "Feature",
  "properties": {
    "iso:country":"GB",
    "sg:address":"4 The Parade, London Road, Felbridge",
    "sg:city":"East Grinstead",
    "sg:classifiers":[
        {
            "category":"Professional",
            "subcategory":"Detective & Security Services",
            "type":"Services"
        }
    ],
    "sg:phone":"+44 1342 321673",
    "sg:postcode":"RH19 1QL",
    "sg:province":"East Sussex",
    "sg:tags":[
        "car"
    ],
    "wof:name":"Car Sound Felbridge",
    "wof:placetype":"venue"
},
  "geometry": {"coordinates":[-0.03503,51.137321],"type":"Point"}
}