{
  "type": "Feature",
  "properties": {
    "addr:full":"Manchester Road, Kearsley Bolton Lancashire BL4 8RU",
    "addr:postcode":"bl4 8ru",
    "addr:street":"Manchester Road",
    "iso:country":"GB",
    "sg:address":"Manchester Road, Kearsley",
    "sg:city":"Bolton",
    "sg:classifiers":[
        {
            "category":"Sports & Exercise",
            "subcategory":"Stables",
            "type":"Entertainment"
        }
    ],
    "sg:phone":"+44 161 794 0058",
    "sg:postcode":"BL4 8RU",
    "sg:province":"Lancashire",
    "sg:tags":[
        "education",
        "equestrian"
    ],
    "wof:name":"Ryders Farm Equestrian Centre",
    "wof:placetype":"venue"
},
  "geometry": {"coordinates":[-2.3753089905,53.5398216248],"type":"Point"}
}