{
  "type": "Feature",
  "properties": {
    "addr:full":"11 Faringdon Rd Swindon Wiltshire SN1 5AR",
    "addr:housenumber":"11",
    "addr:postcode":"sn1 5ar",
    "addr:street":"Faringdon Rd",
    "iso:country":"GB",
    "sg:address":"11 Faringdon Rd",
    "sg:city":"Swindon",
    "sg:classifiers":[
        {
            "category":"Organizations",
            "subcategory":"Religious Organization",
            "type":"Services"
        }
    ],
    "sg:phone":"+44 1793 531810",
    "sg:postcode":"SN1 5AR",
    "sg:province":"Wiltshire",
    "sg:tags":[
        "organisation"
    ],
    "wof:name":"Thamesdown Youth For Christ",
    "wof:placetype":"venue"
},
  "geometry": {"coordinates":[-1.7887,51.561638],"type":"Point"}
}