{
  "type": "Feature",
  "properties": {
    "addr:full":"173 Uppingham Road Leicester Leicestershire LE5 4BP",
    "addr:housenumber":"173",
    "addr:postcode":"le5 4bp",
    "addr:street":"Uppingham Road",
    "iso:country":"GB",
    "sg:address":"173 Uppingham Road",
    "sg:city":"Leicester",
    "sg:classifiers":[
        {
            "category":"Retail",
            "subcategory":"Auto Repair",
            "type":"Services"
        }
    ],
    "sg:phone":"+44 116 276 5310",
    "sg:postcode":"LE5 4BP",
    "sg:province":"Leicestershire",
    "sg:tags":[
        "modification",
        "garage"
    ],
    "wof:name":"Clayton Motors",
    "wof:placetype":"venue"
},
  "geometry": {"coordinates":[-1.094532,52.642086],"type":"Point"}
}