{
  "type": "Feature",
  "properties": {
    "addr:full":"1-3 Castle St Cardiff Cardiff CF1 2BS",
    "addr:housenumber":"1-3",
    "addr:postcode":"cf1 2bs",
    "addr:street":"Castle St",
    "iso:country":"GB",
    "sg:address":"1-3 Castle St",
    "sg:city":"Cardiff",
    "sg:classifiers":[
        {
            "category":"Landmark",
            "subcategory":"Tourist Information",
            "type":"Public Place"
        }
    ],
    "sg:phone":"+44 29 2052 2202",
    "sg:postcode":"CF1 2BS",
    "sg:province":"Cardiff",
    "sg:tags":[
        "tour",
        "guide",
        "sightseeing"
    ],
    "wof:name":"Leisure Link Wales",
    "wof:placetype":"venue"
},
  "geometry": {"coordinates":[-3.2677249908,51.5425872803],"type":"Point"}
}