{
  "type": "Feature",
  "properties": {
    "iso:country":"GB",
    "sg:address":"Smestow Bridge Industrial Estate, Bridgnorth Road, Wombourne",
    "sg:city":"Wolverhampton",
    "sg:classifiers":[
        {
            "category":"Manufacturing",
            "subcategory":"Building Materials",
            "type":"Manufacturing & Wholesale Goods"
        }
    ],
    "sg:phone":"+44 1902 893238",
    "sg:postcode":"WV5 8AY",
    "sg:province":"Shropshire",
    "sg:tags":[
        "merchant",
        "builder"
    ],
    "wof:name":"Reclamation & Salvage",
    "wof:placetype":"venue"
},
  "geometry": {"coordinates":[-2.21471,52.530449],"type":"Point"}
}