{
  "type": "Feature",
  "properties": {
    "iso:country":"GB",
    "sg:address":"30 Farndale",
    "sg:city":"Widnes",
    "sg:classifiers":[
        {
            "category":"Professional",
            "subcategory":"Computer Services",
            "type":"Services"
        }
    ],
    "sg:phone":"+44 151 424 9861",
    "sg:postcode":"WA8 9JL",
    "sg:province":"Cheshire",
    "sg:tags":[
        "consultant"
    ],
    "wof:name":"Cubebase Systems Ltd.",
    "wof:placetype":"venue"
},
  "geometry": {"coordinates":[-2.732108,53.390175],"type":"Point"}
}