{
  "type": "Feature",
  "properties": {
    "addr:full":"37 Crow Lane, Great Billing Northampton Northamptonshire NN3 9BZ",
    "addr:housenumber":"37",
    "addr:postcode":"nn3 9bz",
    "addr:street":"Crow Lane",
    "iso:country":"GB",
    "sg:address":"37 Crow Lane, Great Billing",
    "sg:city":"Northampton",
    "sg:classifiers":[
        {
            "category":"Building & Trades",
            "subcategory":"Equipment Rental",
            "type":"Services"
        }
    ],
    "sg:postcode":"NN3 9BZ",
    "sg:province":"Northamptonshire",
    "sg:tags":[
        "plant",
        "machinery"
    ],
    "wof:name":"Thomas (Haulage) Ltd.",
    "wof:placetype":"venue"
},
  "geometry": {"coordinates":[-0.8087199926,52.2470741272],"type":"Point"}
}