{
  "type": "Feature",
  "properties": {
    "addr:full":"The Willows Saundersfoot Pembrokeshire SA69 9DD",
    "addr:postcode":"sa69 9dd",
    "iso:country":"GB",
    "sg:address":"The Willows",
    "sg:city":"Saundersfoot",
    "sg:classifiers":[
        {
            "category":"Health Services",
            "subcategory":"Dentist",
            "type":"Services"
        }
    ],
    "sg:phone":"+44 1834 812658",
    "sg:postcode":"SA69 9DD",
    "sg:province":"Pembrokeshire",
    "sg:tags":[
        "technician",
        "dental"
    ],
    "wof:name":"J A Evans",
    "wof:placetype":"venue"
},
  "geometry": {"coordinates":[-4.6995558739,51.7102050781],"type":"Point"}
}