{
  "type": "Feature",
  "properties": {
    "addr:full":"Pinner Police Station, Bridge St Pinner Greater London HA5 3HR",
    "addr:postcode":"ha5 3hr",
    "addr:street":"Bridge St",
    "iso:country":"GB",
    "sg:address":"Pinner Police Station, Bridge St",
    "sg:city":"Pinner",
    "sg:classifiers":[
        {
            "category":"Government",
            "subcategory":"Police Station",
            "type":"Public Place"
        }
    ],
    "sg:phone":"+44 20 8429 4545",
    "sg:postcode":"HA5 3HR",
    "sg:province":"Greater London",
    "sg:tags":[
        "support"
    ],
    "wof:name":"Metropolitan Police Service",
    "wof:placetype":"venue"
},
  "geometry": {"coordinates":[-0.380489,51.590939],"type":"Point"}
}