{
  "type": "Feature",
  "properties": {
    "addr:full":"810 Rochdale Rd Oldham Lancashire OL2 6XF",
    "addr:housenumber":"810",
    "addr:postcode":"ol2 6xf",
    "addr:street":"Rochdale Rd",
    "iso:country":"GB",
    "sg:address":"810 Rochdale Rd",
    "sg:city":"Oldham",
    "sg:classifiers":[
        {
            "category":"Food & Beverages",
            "subcategory":"Candy",
            "type":"Retail Goods"
        }
    ],
    "sg:postcode":"OL2 6XF",
    "sg:province":"Lancashire",
    "sg:tags":[
        "confectioner"
    ],
    "wof:name":"Ogden,Vivienne,",
    "wof:placetype":"venue"
},
  "geometry": {"coordinates":[-2.135906,53.582764],"type":"Point"}
}