{
  "type": "Feature",
  "properties": {
    "iso:country":"GB",
    "sg:address":"5 Ryebrook Industrial Estate, Kingston Road",
    "sg:city":"Leatherhead",
    "sg:classifiers":[
        {
            "category":"Building & Trades",
            "subcategory":"Plumbing",
            "type":"Services"
        }
    ],
    "sg:phone":"+44 1372 360777",
    "sg:postcode":"KT22 7PU",
    "sg:province":"Surrey",
    "sg:tags":[
        "merchant",
        "plumbers'"
    ],
    "wof:name":"Plumb Center",
    "wof:placetype":"venue"
},
  "geometry": {"coordinates":[-0.329418987,51.2963600159],"type":"Point"}
}