{
  "type": "Feature",
  "properties": {
    "addr:full":"River Hill, Bramford Ipswich Suffolk IP8 4BB",
    "addr:postcode":"ip8 4bb",
    "addr:street":"River",
    "iso:country":"GB",
    "sg:address":"River Hill, Bramford",
    "sg:city":"Ipswich",
    "sg:classifiers":[
        {
            "category":"Retail",
            "subcategory":"Auto Repair",
            "type":"Services"
        }
    ],
    "sg:postcode":"IP8 4BB",
    "sg:province":"Suffolk",
    "sg:tags":[
        "modification",
        "garage",
        "upholsterer",
        "car"
    ],
    "wof:name":"Goldsmith Upholstery",
    "wof:placetype":"venue"
},
  "geometry": {"coordinates":[1.0973889828,52.0758895874],"type":"Point"}
}