{
  "type": "Feature",
  "properties": {
    "addr:full":"25 Sunny Bank Rd Manchester Greater Manchester M13 0XF",
    "addr:housenumber":"25",
    "addr:postcode":"m13 0xf",
    "addr:street":"Sunny Bank Rd",
    "iso:country":"GB",
    "sg:address":"25 Sunny Bank Rd",
    "sg:city":"Manchester",
    "sg:classifiers":[
        {
            "category":"Shopping",
            "subcategory":"Pharmacy",
            "type":"Retail Goods"
        }
    ],
    "sg:phone":"+44 161 248 6844",
    "sg:postcode":"M13 0XF",
    "sg:province":"Greater Manchester",
    "sg:tags":[
        "medicine",
        "therapy"
    ],
    "wof:name":"Rehman Centre for Hypnosis & Awake Trance Therapy Ltd",
    "wof:placetype":"venue"
},
  "geometry": {"coordinates":[-2.2048370838,53.4539299011],"type":"Point"}
}