{
  "type": "Feature",
  "properties": {
    "iso:country":"GB",
    "sg:address":"Unit 30a, Selly Oak Ind Est, Elliot Rd",
    "sg:city":"Birmingham",
    "sg:classifiers":[
        {
            "category":"Retail",
            "subcategory":"Auto Repair",
            "type":"Services"
        }
    ],
    "sg:phone":"+44 121 414 0607",
    "sg:postcode":"B29 6TJ",
    "sg:province":"West Midlands",
    "sg:tags":[
        "car",
        "upholsterer"
    ],
    "wof:name":"Mint Cars",
    "wof:placetype":"venue"
},
  "geometry": {"coordinates":[-1.93534,52.43858],"type":"Point"}
}