{
  "type": "Feature",
  "properties": {
    "iso:country":"GB",
    "sg:address":"44 Victoria Road West",
    "sg:city":"Thornton-cleveleys",
    "sg:classifiers":[
        {
            "category":"Shopping",
            "subcategory":"Department Store",
            "type":"Retail Goods"
        },
        {
            "category":"Food & Beverages",
            "subcategory":"Specialty",
            "type":"Retail Goods"
        }
    ],
    "sg:phone":"+44 1253 864030",
    "sg:postcode":"FY5 1BU",
    "sg:province":"Lancashire",
    "sg:tags":[
        "product",
        "health",
        "departmental"
    ],
    "wof:name":"HEALTH FROM HERBS LTD",
    "wof:placetype":"venue"
},
  "geometry": {"coordinates":[-3.044235,53.877445],"type":"Point"}
}