{
  "type": "Feature",
  "properties": {
    "addr:full":"Main Street Campbeltown Argyll and Bute PA28 6AB",
    "addr:postcode":"pa28 6ab",
    "addr:street":"Main Street",
    "iso:country":"GB",
    "sg:address":"Main Street",
    "sg:city":"Campbeltown",
    "sg:classifiers":[
        {
            "category":"Travel",
            "subcategory":"Hotels & Motels",
            "type":"Entertainment"
        }
    ],
    "sg:phone":"+44 1586 553431",
    "sg:postcode":"PA28 6AB",
    "sg:province":"Argyll and Bute",
    "wof:name":"HECTOR & MARGARET THOMPSON",
    "wof:placetype":"venue"
},
  "geometry": {"coordinates":[-5.6046290398,55.4246749878],"type":"Point"}
}