{
  "type": "Feature",
  "properties": {
    "addr:full":"114 Kingsmead Road High Wycombe Buckinghamshire HP11 1HZ",
    "addr:housenumber":"114",
    "addr:postcode":"hp11 1hz",
    "addr:street":"Kingsmead Road",
    "iso:country":"GB",
    "sg:address":"114 Kingsmead Road",
    "sg:city":"High Wycombe",
    "sg:classifiers":[
        {
            "category":"Bars & Pubs",
            "type":"Food & Drink"
        }
    ],
    "sg:postcode":"HP11 1HZ",
    "sg:province":"Buckinghamshire",
    "sg:tags":[
        "pubs",
        "inn"
    ],
    "wof:name":"The General Havelock",
    "wof:placetype":"venue"
},
  "geometry": {"coordinates":[-0.7168030143,51.614730835],"type":"Point"}
}