{
  "type": "Feature",
  "properties": {
    "addr:full":"597 York Road Leeds West Yorkshire LS9 6NW",
    "addr:housenumber":"597",
    "addr:postcode":"ls9 6nw",
    "addr:street":"York Road",
    "iso:country":"GB",
    "sg:address":"597 York Road",
    "sg:city":"Leeds",
    "sg:classifiers":[
        {
            "category":"Fast Food",
            "type":"Food & Drink"
        }
    ],
    "sg:phone":"+44 113 248 9801",
    "sg:postcode":"LS9 6NW",
    "sg:province":"West Yorkshire",
    "sg:tags":[
        "away",
        "take"
    ],
    "wof:name":"Guang Wah",
    "wof:placetype":"venue"
},
  "geometry": {"coordinates":[-1.4921040535,53.801700592],"type":"Point"}
}