{
  "type": "Feature",
  "properties": {
    "addr:full":"38 Westfield Rd Yeovil Somerset BA21 3DA",
    "addr:housenumber":"38",
    "addr:postcode":"ba21 3da",
    "addr:street":"Westfield Rd",
    "iso:country":"GB",
    "sg:address":"38 Westfield Rd",
    "sg:city":"Yeovil",
    "sg:classifiers":[
        {
            "category":"Food & Beverages",
            "subcategory":"Meat & Fish",
            "type":"Retail Goods"
        }
    ],
    "sg:postcode":"BA21 3DA",
    "sg:province":"Somerset",
    "sg:tags":[
        "chip"
    ],
    "wof:name":"Westfield Take Away",
    "wof:placetype":"venue"
},
  "geometry": {"coordinates":[-2.6469,50.947453],"type":"Point"}
}