{
  "type": "Feature",
  "properties": {
    "addr:full":"Main Street, Spittal Berwick-upon-tweed Northumberland TD15 1RD",
    "addr:postcode":"td15 1rd",
    "addr:street":"Main Street",
    "iso:country":"GB",
    "sg:address":"Main Street, Spittal",
    "sg:city":"Berwick-upon-tweed",
    "sg:classifiers":[
        {
            "category":"Education",
            "subcategory":"School",
            "type":"Public Place"
        }
    ],
    "sg:phone":"+44 1289 307413",
    "sg:postcode":"TD15 1RD",
    "sg:province":"Northumberland",
    "sg:tags":[
        "local",
        "authority"
    ],
    "wof:name":"Spittal County First School",
    "wof:placetype":"venue"
},
  "geometry": {"coordinates":[-2.0070240498,55.7714347839],"type":"Point"}
}