{
  "type": "Feature",
  "properties": {
    "addr:full":"14 Moormead Budleigh Salterton Devon EX9 6PZ",
    "addr:housenumber":"14",
    "addr:postcode":"ex9 6pz",
    "addr:street":"Moormead Budleigh",
    "iso:country":"GB",
    "sg:address":"14 Moormead",
    "sg:city":"Budleigh Salterton",
    "sg:classifiers":[
        {
            "category":"Building & Trades",
            "subcategory":"Construction",
            "type":"Services"
        }
    ],
    "sg:phone":"+44 1395 442776",
    "sg:postcode":"EX9 6PZ",
    "sg:province":"Devon",
    "sg:tags":[
        "decorator",
        "painter"
    ],
    "wof:name":"Robert J Pearcey",
    "wof:placetype":"venue"
},
  "geometry": {"coordinates":[-3.3324110508,50.6335105896],"type":"Point"}
}