{
  "type": "Feature",
  "properties": {
    "addr:full":"36 Wood Street, Earl Shilton Leicester Leicestershire LE9 7ND",
    "addr:housenumber":"36",
    "addr:postcode":"le9 7nd",
    "addr:street":"Wood Street",
    "iso:country":"GB",
    "sg:address":"36 Wood Street, Earl Shilton",
    "sg:city":"Leicester",
    "sg:classifiers":[
        {
            "category":"Sports & Exercise",
            "subcategory":"Sports Center",
            "type":"Entertainment"
        }
    ],
    "sg:phone":"+44 1455 843566",
    "sg:postcode":"LE9 7ND",
    "sg:province":"Leicestershire",
    "sg:tags":[
        "shop",
        "good"
    ],
    "wof:name":"David Luck Sports",
    "wof:placetype":"venue"
},
  "geometry": {"coordinates":[-1.3176759481,52.575756073],"type":"Point"}
}