{
  "type": "Feature",
  "properties": {
    "addr:full":"Westbury Lane Newport Pagnell Buckinghamshire MK16 8PS",
    "addr:postcode":"mk16 8ps",
    "addr:street":"Westbury Lane",
    "iso:country":"GB",
    "sg:address":"Westbury Lane",
    "sg:city":"Newport Pagnell",
    "sg:classifiers":[
        {
            "category":"Education",
            "subcategory":"School",
            "type":"Public Place"
        },
        {
            "category":"Government",
            "subcategory":"Office",
            "type":"Public Place"
        }
    ],
    "sg:phone":"+44 1908 616060",
    "sg:postcode":"MK16 8PS",
    "sg:province":"Buckinghamshire",
    "sg:tags":[
        "local",
        "authority"
    ],
    "wof:name":"Portfields Combined School",
    "wof:placetype":"venue"
},
  "geometry": {"coordinates":[-0.745889008,52.0913658142],"type":"Point"}
}