{
  "type": "Feature",
  "properties": {
    "addr:full":"30 Main St, Bolsover Chesterfield Derbyshire S44 6JF",
    "addr:housenumber":"30",
    "addr:postcode":"s44 6jf",
    "addr:street":"Main St",
    "iso:country":"GB",
    "sg:address":"30 Main St, Bolsover",
    "sg:city":"Chesterfield",
    "sg:classifiers":[
        {
            "category":"Shopping",
            "subcategory":"Shoes",
            "type":"Retail Goods"
        }
    ],
    "sg:postcode":"S44 6JF",
    "sg:province":"Derbyshire",
    "sg:tags":[
        "shop"
    ],
    "wof:name":"Phillips Fashions",
    "wof:placetype":"venue"
},
  "geometry": {"coordinates":[-1.3027689457,53.2247085571],"type":"Point"}
}