{
  "type": "Feature",
  "properties": {
    "addr:full":"14 Saxon Court Wolverhampton Shropshire WV6 8SA",
    "addr:housenumber":"14",
    "addr:postcode":"wv6 8sa",
    "addr:street":"Saxon Court",
    "iso:country":"GB",
    "sg:address":"14 Saxon Court",
    "sg:city":"Wolverhampton",
    "sg:classifiers":[
        {
            "category":"Wholesale",
            "subcategory":"Electrical",
            "type":"Manufacturing & Wholesale Goods"
        }
    ],
    "sg:postcode":"WV6 8SA",
    "sg:province":"Shropshire",
    "sg:tags":[
        "equipment",
        "refrigeration"
    ],
    "wof:name":"Independent Fire Protection Ltd",
    "wof:placetype":"venue"
},
  "geometry": {"coordinates":[-2.1761488914,52.6011276245],"type":"Point"}
}