{
  "type": "Feature",
  "properties": {
    "addr:full":"Smithy Lane Thornhill Dumfries and Galloway DG3 4LW",
    "addr:postcode":"dg3 4lw",
    "addr:street":"Smithy Lane",
    "iso:country":"GB",
    "sg:address":"Smithy Lane",
    "sg:city":"Thornhill",
    "sg:classifiers":[
        {
            "category":"Professional",
            "subcategory":"Engineering",
            "type":"Services"
        }
    ],
    "sg:phone":"+44 1848 330416",
    "sg:postcode":"DG3 4LW",
    "sg:province":"Dumfries and Galloway",
    "sg:tags":[
        "precision",
        "engineer"
    ],
    "wof:name":"J Maxwell Engineering",
    "wof:placetype":"venue"
},
  "geometry": {"coordinates":[-3.855929,55.221054],"type":"Point"}
}