{
  "type": "Feature",
  "properties": {
    "iso:country":"GB",
    "sg:address":"73 Horley Road",
    "sg:city":"Redhill",
    "sg:classifiers":[
        {
            "category":"Shopping",
            "subcategory":"Baby Store",
            "type":"Retail Goods"
        }
    ],
    "sg:phone":"+44 1737 767681",
    "sg:postcode":"RH1 5AL",
    "sg:province":"Surrey",
    "sg:tags":[
        "nursery",
        "accessory"
    ],
    "wof:name":"Campbell's",
    "wof:placetype":"venue"
},
  "geometry": {"coordinates":[-0.16975,51.213165],"type":"Point"}
}