{
  "type": "Feature",
  "properties": {
    "addr:full":"39 Oldmixon Road Weston-super-mare Somerset BS24 9NR",
    "addr:housenumber":"39",
    "addr:postcode":"bs24 9nr",
    "addr:street":"Oldmixon Road",
    "iso:country":"GB",
    "sg:address":"39 Oldmixon Road",
    "sg:city":"Weston-super-mare",
    "sg:classifiers":[
        {
            "category":"Building & Trades",
            "subcategory":"Construction",
            "type":"Services"
        }
    ],
    "sg:phone":"+44 1934 812643",
    "sg:postcode":"BS24 9NR",
    "sg:province":"Somerset",
    "sg:tags":[
        "builder"
    ],
    "wof:name":"Tim Golding",
    "wof:placetype":"venue"
},
  "geometry": {"coordinates":[-2.956852,51.321232],"type":"Point"}
}