{
  "type": "Feature",
  "properties": {
    "iso:country":"GB",
    "sg:address":"Elland Rd",
    "sg:city":"Leeds",
    "sg:classifiers":[
        {
            "category":"Retail",
            "subcategory":"Auto Rental",
            "type":"Services"
        }
    ],
    "sg:phone":"+44 113 277 7747",
    "sg:postcode":"LS11 0HS",
    "sg:province":"West Yorkshire",
    "sg:tags":[
        "truck",
        "hire",
        "van"
    ],
    "wof:name":"Practical Car & Van Rental",
    "wof:placetype":"venue"
},
  "geometry": {"coordinates":[-1.562016964,53.7809715271],"type":"Point"}
}