{
  "type": "Feature",
  "properties": {
    "iso:country":"GB",
    "sg:address":"2 Hollybush Terrace, Westow Street",
    "sg:city":"London",
    "sg:classifiers":[
        {
            "category":"Food & Beverages",
            "subcategory":"Fruits & Vegetables",
            "type":"Retail Goods"
        }
    ],
    "sg:phone":"+44 20 8653 3500",
    "sg:postcode":"SE19 3SD",
    "sg:province":"Greater London",
    "sg:tags":[
        "greengrocer"
    ],
    "wof:name":"Lawrences",
    "wof:placetype":"venue"
},
  "geometry": {"coordinates":[-0.08294,51.41914],"type":"Point"}
}