{
  "type": "Feature",
  "properties": {
    "addr:full":"2 Fintonagh Drive Maidstone Kent ME14 2AQ",
    "addr:housenumber":"2",
    "addr:postcode":"me14 2aq",
    "addr:street":"Fintonagh Drive",
    "iso:country":"GB",
    "sg:address":"2 Fintonagh Drive",
    "sg:city":"Maidstone",
    "sg:classifiers":[
        {
            "category":"Shopping",
            "subcategory":"Adult",
            "type":"Retail Goods"
        }
    ],
    "sg:postcode":"ME14 2AQ",
    "sg:province":"Kent",
    "sg:tags":[
        "graphologist"
    ],
    "wof:name":"Norma Sweeting",
    "wof:placetype":"venue"
},
  "geometry": {"coordinates":[0.5308750272,51.2847938538],"type":"Point"}
}