{
  "type": "Feature",
  "properties": {
    "addr:full":"6 Station Road South Shields Tyne and Wear NE33 1ED",
    "addr:housenumber":"6",
    "addr:postcode":"ne33 1ed",
    "addr:street":"Station Road",
    "iso:country":"GB",
    "sg:address":"6 Station Road",
    "sg:city":"South Shields",
    "sg:classifiers":[
        {
            "category":"Shopping",
            "subcategory":"Crafts & Fabrics",
            "type":"Retail Goods"
        }
    ],
    "sg:postcode":"NE33 1ED",
    "sg:province":"Tyne and Wear",
    "sg:tags":[
        "shop"
    ],
    "wof:name":"Station Road Fabrics",
    "wof:placetype":"venue"
},
  "geometry": {"coordinates":[-1.438727,54.996456],"type":"Point"}
}