{
  "type": "Feature",
  "properties": {
    "addr:full":"44 Wallace Road London Greater London N1 2PQ",
    "addr:housenumber":"44",
    "addr:postcode":"n1 2pq",
    "addr:street":"Wallace Road",
    "iso:country":"GB",
    "sg:address":"44 Wallace Road",
    "sg:city":"London",
    "sg:classifiers":[
        {
            "category":"Professional",
            "subcategory":"Art Services",
            "type":"Services"
        }
    ],
    "sg:phone":"+44 20 7704 6013",
    "sg:postcode":"N1 2PQ",
    "sg:province":"Greater London",
    "sg:tags":[
        "model",
        "maker"
    ],
    "wof:name":"David Montgomery",
    "wof:placetype":"venue"
},
  "geometry": {"coordinates":[-0.099814,51.537899],"type":"Point"}
}