{
  "type": "Feature",
  "properties": {
    "addr:full":"Unit 2, Mountheath Industrial Park, Prestwich Manchester Greater Manchester M25 9WB",
    "addr:housenumber":"unit 2",
    "addr:postcode":"m25 9wb",
    "addr:street":"Mountheath Industrial Park",
    "iso:country":"GB",
    "sg:address":"Unit 2, Mountheath Industrial Park, Prestwich",
    "sg:city":"Manchester",
    "sg:classifiers":[
        {
            "category":"Shopping",
            "type":"Retail Goods"
        }
    ],
    "sg:phone":"+44 161 798 8611",
    "sg:postcode":"M25 9WB",
    "sg:province":"Greater Manchester",
    "sg:tags":[
        "scientific",
        "apparatus"
    ],
    "wof:name":"Mass Spectrometry Services Ltd.",
    "wof:placetype":"venue"
},
  "geometry": {"coordinates":[-2.2746090889,53.5179100037],"type":"Point"}
}