{
  "type": "Feature",
  "properties": {
    "addr:full":"2-4 Winifred St, Hucknall Nottingham Nottinghamshire NG15 7RX",
    "addr:housenumber":"2-4",
    "addr:postcode":"ng15 7rx",
    "addr:street":"Winifred St",
    "iso:country":"GB",
    "sg:address":"2-4 Winifred St, Hucknall",
    "sg:city":"Nottingham",
    "sg:classifiers":[
        {
            "category":"Sports & Exercise",
            "subcategory":"Sports Center",
            "type":"Entertainment"
        }
    ],
    "sg:phone":"+44 115 963 8945",
    "sg:postcode":"NG15 7RX",
    "sg:province":"Nottinghamshire",
    "sg:tags":[
        "shop",
        "good"
    ],
    "wof:name":"Milano Sports",
    "wof:placetype":"venue"
},
  "geometry": {"coordinates":[-1.1963210106,53.0313606262],"type":"Point"}
}