{
  "type": "Feature",
  "properties": {
    "iso:country":"GB",
    "sg:address":"3 Trafalgar St",
    "sg:city":"Burnley",
    "sg:classifiers":[
        {
            "category":"Autos & Motor Vehicles",
            "subcategory":"Auto Supplies",
            "type":"Retail Goods"
        }
    ],
    "sg:phone":"+44 1282 428337",
    "sg:postcode":"BB11 1TQ",
    "sg:province":"Lancashire",
    "sg:tags":[
        "tyre"
    ],
    "wof:name":"National Tyres And Autocare",
    "wof:placetype":"venue"
},
  "geometry": {"coordinates":[-2.2485640049,53.7860832214],"type":"Point"}
}