{
  "type": "Feature",
  "properties": {
    "iso:country":"GB",
    "sg:address":"1 Coton Rd",
    "sg:city":"Nuneaton",
    "sg:classifiers":[
        {
            "category":"Social Services",
            "subcategory":"Retirement Home",
            "type":"Services"
        }
    ],
    "sg:phone":"+44 24 7632 0099",
    "sg:postcode":"CV11 5TQ",
    "sg:province":"Leicestershire",
    "sg:tags":[
        "care"
    ],
    "wof:name":"Goldsborough Homecare & Nursing Services",
    "wof:placetype":"venue"
},
  "geometry": {"coordinates":[-1.4678659439,52.5209922791],"type":"Point"}
}