{
  "type": "Feature",
  "properties": {
    "iso:country":"GB",
    "sg:address":"117a Vicarage Rd",
    "sg:city":"Smethwick",
    "sg:classifiers":[
        {
            "category":"Food & Beverages",
            "subcategory":"Supermarket",
            "type":"Retail Goods"
        }
    ],
    "sg:postcode":"B68 8HY",
    "sg:province":"West Midlands",
    "wof:name":"Kaur,Sindh",
    "wof:placetype":"venue"
},
  "geometry": {"coordinates":[-2.0001,52.493038],"type":"Point"}
}