{
  "type": "Feature",
  "properties": {
    "addr:full":"14 King Street East Grinstead East Sussex RH19 3DJ",
    "addr:housenumber":"14",
    "addr:postcode":"rh19 3dj",
    "addr:street":"King Street",
    "iso:country":"GB",
    "sg:address":"14 King Street",
    "sg:city":"East Grinstead",
    "sg:classifiers":[
        {
            "category":"Restaurant",
            "type":"Food & Drink"
        }
    ],
    "sg:phone":"+44 1342 301310",
    "sg:postcode":"RH19 3DJ",
    "sg:province":"East Sussex",
    "wof:name":"Theo's Bistro",
    "wof:placetype":"venue"
},
  "geometry": {"coordinates":[-0.0088099996,51.1266403198],"type":"Point"}
}