{
  "type": "Feature",
  "properties": {
    "addr:full":"4 Grosvenor Place London Greater London SW1X 7HD",
    "addr:housenumber":"4",
    "addr:postcode":"sw1x 7hd",
    "addr:street":"Grosvenor Place",
    "iso:country":"GB",
    "sg:address":"4 Grosvenor Place",
    "sg:city":"London",
    "sg:classifiers":[
        {
            "category":"Airline",
            "type":"Transportation"
        }
    ],
    "sg:postcode":"SW1X 7HD",
    "sg:province":"Greater London",
    "sg:tags":[
        "aircraft",
        "charter"
    ],
    "wof:name":"Phoenix Helicopter Charters",
    "wof:placetype":"venue"
},
  "geometry": {"coordinates":[-0.151187,51.501541],"type":"Point"}
}