{
  "type": "Feature",
  "properties": {
    "addr:full":"24 Willow Herb Clo Southampton Hampshire SO31 6XB",
    "addr:housenumber":"24",
    "addr:postcode":"hampshire so31 6xb",
    "addr:street":"Willow",
    "iso:country":"GB",
    "sg:address":"24 Willow Herb Clo",
    "sg:city":"Southampton",
    "sg:classifiers":[
        {
            "category":"Real Estate",
            "subcategory":"Surveying",
            "type":"Services"
        }
    ],
    "sg:phone":"+44 1489 582265",
    "sg:postcode":"SO31 6XB",
    "sg:province":"Hampshire",
    "sg:tags":[
        "surveyor",
        "quantity"
    ],
    "wof:name":"M J Collins",
    "wof:placetype":"venue"
},
  "geometry": {"coordinates":[-1.2874859571,50.8573684692],"type":"Point"}
}