{
  "type": "Feature",
  "properties": {
    "addr:full":"Aston Bury Farm, Aston Stevenage Hertfordshire SG2 7EG",
    "addr:postcode":"sg2 7eg",
    "addr:street":"Aston;Aston",
    "iso:country":"GB",
    "sg:address":"Aston Bury Farm, Aston",
    "sg:city":"Stevenage",
    "sg:classifiers":[
        {
            "category":"Professional",
            "subcategory":"Computer Services",
            "type":"Services"
        }
    ],
    "sg:phone":"+44 1438 880190",
    "sg:postcode":"SG2 7EG",
    "sg:province":"Hertfordshire",
    "sg:tags":[
        "system",
        "software"
    ],
    "wof:name":"Mediqal Ltd.",
    "wof:placetype":"venue"
},
  "geometry": {"coordinates":[-0.150391,51.888332],"type":"Point"}
}