{
  "type": "Feature",
  "properties": {
    "addr:full":"1 South View East, Highfield Rowlands Gill Durham NE39 2DJ",
    "addr:housenumber":"1",
    "addr:postcode":"ne39 2dj",
    "addr:street":"South View East",
    "iso:country":"GB",
    "sg:address":"1 South View East, Highfield",
    "sg:city":"Rowlands Gill",
    "sg:classifiers":[
        {
            "category":"Food & Beverages",
            "subcategory":"Meat & Fish",
            "type":"Retail Goods"
        }
    ],
    "sg:phone":"+44 1207 542418",
    "sg:postcode":"NE39 2DJ",
    "sg:province":"Durham",
    "sg:tags":[
        "butcher"
    ],
    "wof:name":"Norman Walton",
    "wof:placetype":"venue"
},
  "geometry": {"coordinates":[-1.76485,54.922115],"type":"Point"}
}