{
  "type": "Feature",
  "properties": {
    "iso:country":"GB",
    "sg:address":"Holywells Road",
    "sg:city":"Ipswich",
    "sg:classifiers":[
        {
            "category":"Wholesale",
            "subcategory":"Home Furnishings",
            "type":"Manufacturing & Wholesale Goods"
        }
    ],
    "sg:phone":"+44 1473 212310",
    "sg:postcode":"IP3 0DL",
    "sg:province":"Suffolk",
    "sg:tags":[
        "merchant",
        "decorators'"
    ],
    "wof:name":"Johnstone Manders Paints",
    "wof:placetype":"venue"
},
  "geometry": {"coordinates":[1.166569,52.046951],"type":"Point"}
}