{
  "type": "Feature",
  "properties": {
    "addr:full":"20 Bradford Road, Guiseley Leeds West Yorkshire LS20 8NH",
    "addr:housenumber":"20",
    "addr:postcode":"ls20 8nh",
    "addr:street":"Bradford Road",
    "iso:country":"GB",
    "sg:address":"20 Bradford Road, Guiseley",
    "sg:city":"Leeds",
    "sg:classifiers":[
        {
            "category":"Personal",
            "subcategory":"Beauty Salon",
            "type":"Services"
        }
    ],
    "sg:phone":"+44 1943 874610",
    "sg:postcode":"LS20 8NH",
    "sg:province":"West Yorkshire",
    "sg:tags":[
        "unisex",
        "hairdresser"
    ],
    "wof:name":"The Joyce Dixon Salon",
    "wof:placetype":"venue"
},
  "geometry": {"coordinates":[-1.725175,53.876774],"type":"Point"}
}