{
  "type": "Feature",
  "properties": {
    "addr:full":"Quogach Farm Rothesay Argyll and Bute PA20 0QA",
    "addr:postcode":"pa20 0qa",
    "addr:street":"Rothesay",
    "iso:country":"GB",
    "sg:address":"Quogach Farm",
    "sg:city":"Rothesay",
    "sg:classifiers":[
        {
            "category":"Building & Trades",
            "subcategory":"Equipment Rental",
            "type":"Services"
        }
    ],
    "sg:phone":"+44 1700 502651",
    "sg:postcode":"PA20 0QA",
    "sg:province":"Argyll and Bute",
    "sg:tags":[
        "plant",
        "machinery"
    ],
    "wof:name":"William P Reid",
    "wof:placetype":"venue"
},
  "geometry": {"coordinates":[-5.0695209503,55.8588943481],"type":"Point"}
}