{
  "type": "Feature",
  "properties": {
    "iso:country":"GB",
    "sg:address":"182a London Rd",
    "sg:city":"Leicester",
    "sg:classifiers":[
        {
            "category":"Health Services",
            "subcategory":"Health Practitioner",
            "type":"Services"
        }
    ],
    "sg:phone":"+44 116 254 4383",
    "sg:postcode":"LE2 1ND",
    "sg:province":"Leicestershire",
    "sg:tags":[
        "homoeopathic"
    ],
    "wof:name":"Vivienne Hill",
    "wof:placetype":"venue"
},
  "geometry": {"coordinates":[-1.1160370111,52.6248550415],"type":"Point"}
}