{
  "type": "Feature",
  "properties": {
    "addr:full":"Car Of Kwik Save, Kingsmills Rd Wrexham Wrexham LL13 8NH",
    "addr:postcode":"ll13 8nh",
    "addr:street":"Kingsmills Rd",
    "iso:country":"GB",
    "sg:address":"Car Of Kwik Save, Kingsmills Rd",
    "sg:city":"Wrexham",
    "sg:classifiers":[
        {
            "category":"Food & Beverages",
            "subcategory":"Meat & Fish",
            "type":"Retail Goods"
        }
    ],
    "sg:phone":"+44 1978 365070",
    "sg:postcode":"LL13 8NH",
    "sg:province":"Wrexham",
    "sg:tags":[
        "butcher"
    ],
    "wof:name":"Sovereign Meats",
    "wof:placetype":"venue"
},
  "geometry": {"coordinates":[-2.997129,53.041954],"type":"Point"}
}