{
  "type": "Feature",
  "properties": {
    "addr:full":"141 Brookhouse Lane, Bucknall Stoke-on-trent Staffordshire ST2 8ND",
    "addr:housenumber":"141",
    "addr:postcode":"staffordshire st2 8nd",
    "addr:street":"Brookhouse Lane",
    "iso:country":"GB",
    "sg:address":"141 Brookhouse Lane, Bucknall",
    "sg:city":"Stoke-on-trent",
    "sg:classifiers":[
        {
            "category":"Professional",
            "subcategory":"Management & Consulting",
            "type":"Services"
        }
    ],
    "sg:phone":"+44 1782 303305",
    "sg:postcode":"ST2 8ND",
    "sg:province":"Staffordshire",
    "sg:tags":[
        "consultant",
        "promotion",
        "direct",
        "sale"
    ],
    "wof:name":"Centrefold Incentive Advertising Organisation",
    "wof:placetype":"venue"
},
  "geometry": {"coordinates":[-2.1168310642,53.0271263123],"type":"Point"}
}