{
  "type": "Feature",
  "properties": {
    "iso:country":"GB",
    "sg:address":"Hartwell Road",
    "sg:city":"Leeds",
    "sg:classifiers":[
        {
            "category":"Health Services",
            "subcategory":"Nursing And Care Facility",
            "type":"Services"
        }
    ],
    "sg:phone":"+44 113 242 6871",
    "sg:postcode":"LS6 1RY",
    "sg:province":"West Yorkshire",
    "sg:tags":[
        "home"
    ],
    "wof:name":"Southern Cross Healthcare Services Ltd.",
    "wof:placetype":"venue"
},
  "geometry": {"coordinates":[-1.569299,53.807625],"type":"Point"}
}