{
  "type": "Feature",
  "properties": {
    "addr:full":"Blaberry Cottage, Pateley Bridge Road, Burnt Yates Harrogate North Yorkshire HG3 3ES",
    "addr:postcode":"hg3 3es",
    "addr:street":"Pateley Bridge Road",
    "iso:country":"GB",
    "sg:address":"Blaberry Cottage, Pateley Bridge Road, Burnt Yates",
    "sg:city":"Harrogate",
    "sg:classifiers":[
        {
            "category":"Professional",
            "subcategory":"Engineering",
            "type":"Services"
        },
        {
            "category":"Building & Trades",
            "subcategory":"Electrical",
            "type":"Services"
        }
    ],
    "sg:phone":"+44 1423 560173",
    "sg:postcode":"HG3 3ES",
    "sg:province":"North Yorkshire",
    "sg:tags":[
        "engineer",
        "electrician",
        "contractor"
    ],
    "wof:name":"W G A Henley",
    "wof:placetype":"venue"
},
  "geometry": {"coordinates":[-1.6177090406,54.0460548401],"type":"Point"}
}