{
  "type": "Feature",
  "properties": {
    "addr:full":"6 Oxford Street, Oakengates Telford Shropshire TF2 6AA",
    "addr:housenumber":"6",
    "addr:postcode":"tf2 6aa",
    "addr:street":"Oxford Street",
    "iso:country":"GB",
    "sg:address":"6 Oxford Street, Oakengates",
    "sg:city":"Telford",
    "sg:classifiers":[
        {
            "category":"Real Estate",
            "subcategory":"Real Estate Agent",
            "type":"Services"
        }
    ],
    "sg:phone":"+44 1952 620021",
    "sg:postcode":"TF2 6AA",
    "sg:province":"Shropshire",
    "wof:name":"D B Roberts & Partners",
    "wof:placetype":"venue"
},
  "geometry": {"coordinates":[-2.450441,52.694622],"type":"Point"}
}