{
  "type": "Feature",
  "properties": {
    "iso:country":"GB",
    "sg:address":"50 Welby Street",
    "sg:city":"Grantham",
    "sg:classifiers":[
        {
            "category":"Shopping",
            "subcategory":"Gifts & Souvenirs",
            "type":"Retail Goods"
        }
    ],
    "sg:postcode":"NG31 6EA",
    "sg:province":"Lincolnshire",
    "sg:tags":[
        "shop"
    ],
    "wof:name":"Annsons Giftware",
    "wof:placetype":"venue"
},
  "geometry": {"coordinates":[-0.643857,52.910378],"type":"Point"}
}