{
  "type": "Feature",
  "properties": {
    "iso:country":"GB",
    "sg:address":"Broadway Ho, 112-134 Broadway Ho, The Broadway",
    "sg:city":"Wimbledon",
    "sg:classifiers":[
        {
            "category":"Professional",
            "subcategory":"Employment Agencies",
            "type":"Services"
        }
    ],
    "sg:phone":"+44 20 8540 8124",
    "sg:postcode":"SW19 1RL",
    "sg:province":"Greater London",
    "sg:tags":[
        "consultant"
    ],
    "wof:name":"Interlord Ltd",
    "wof:placetype":"venue"
},
  "geometry": {"coordinates":[-0.20026,51.419331],"type":"Point"}
}