{
  "type": "Feature",
  "properties": {
    "addr:full":"2 Green Lane Luton Bedfordshire LU2 8AS",
    "addr:housenumber":"2",
    "addr:postcode":"lu2 8as",
    "addr:street":"Green Lane",
    "iso:country":"GB",
    "sg:address":"2 Green Lane",
    "sg:city":"Luton",
    "sg:classifiers":[
        {
            "category":"Building & Trades",
            "subcategory":"Equipment Rental",
            "type":"Services"
        },
        {
            "category":"Building & Trades",
            "subcategory":"Construction",
            "type":"Services"
        }
    ],
    "sg:phone":"+44 1582 450425",
    "sg:postcode":"LU2 8AS",
    "sg:province":"Bedfordshire",
    "sg:tags":[
        "plant",
        "machinery"
    ],
    "wof:name":"M & C Ryan",
    "wof:placetype":"venue"
},
  "geometry": {"coordinates":[-0.3849619925,51.8989830017],"type":"Point"}
}