{
  "type": "Feature",
  "properties": {
    "addr:full":"Unit 3, 24 Ings Road Wakefield West Yorkshire WF1 1DZ",
    "addr:housenumber":"unit;24",
    "addr:postcode":"wf1 1dz",
    "addr:street":"Ings Road",
    "iso:country":"GB",
    "sg:address":"Unit 3, 24 Ings Road",
    "sg:city":"Wakefield",
    "sg:classifiers":[
        {
            "category":"Retail",
            "subcategory":"Auto Repair",
            "type":"Services"
        }
    ],
    "sg:phone":"+44 1924 291233",
    "sg:postcode":"WF1 1DZ",
    "sg:province":"West Yorkshire",
    "sg:tags":[
        "body",
        "car"
    ],
    "wof:name":"Autotech Repair Centre",
    "wof:placetype":"venue"
},
  "geometry": {"coordinates":[-1.50184,53.678947],"type":"Point"}
}