{
  "type": "Feature",
  "properties": {
    "iso:country":"GB",
    "sg:address":"14-16 Cowcross Street",
    "sg:city":"London",
    "sg:classifiers":[
        {
            "category":"Organizations",
            "subcategory":"Non-profit Organization",
            "type":"Services"
        }
    ],
    "sg:phone":"+44 20 7336 8203",
    "sg:postcode":"EC1M 6DG",
    "sg:province":"Greater London",
    "sg:tags":[
        "organisation",
        "voluntary",
        "charity"
    ],
    "wof:name":"Sustrans Ltd.",
    "wof:placetype":"venue"
},
  "geometry": {"coordinates":[-0.102887,51.520226],"type":"Point"}
}