{
  "type": "Feature",
  "properties": {
    "addr:full":"15 Oakley Wood Road, Bishops Tachbrook Leamington Spa Warwickshire CV33 9RW",
    "addr:housenumber":"15",
    "addr:postcode":"cv33 9rw",
    "addr:street":"Oakley Wood Road",
    "iso:country":"GB",
    "sg:address":"15 Oakley Wood Road, Bishops Tachbrook",
    "sg:city":"Leamington Spa",
    "sg:classifiers":[
        {
            "category":"Building & Trades",
            "subcategory":"Construction",
            "type":"Services"
        }
    ],
    "sg:phone":"+44 1926 339297",
    "sg:postcode":"CV33 9RW",
    "sg:province":"Warwickshire",
    "sg:tags":[
        "dry",
        "plastering",
        "plasterers",
        "lining",
        "related",
        "screeders"
    ],
    "wof:name":"John W Houghton",
    "wof:placetype":"venue"
},
  "geometry": {"coordinates":[-1.542502,52.245876],"type":"Point"}
}