{
  "type": "Feature",
  "properties": {
    "iso:country":"GB",
    "sg:address":"66 Cromwell Avenue",
    "sg:city":"New Malden",
    "sg:classifiers":[
        {
            "category":"Building & Trades",
            "subcategory":"Plumbing",
            "type":"Services"
        }
    ],
    "sg:phone":"+44 20 8942 9899",
    "sg:postcode":"KT3 6DL",
    "sg:province":"Surrey",
    "sg:tags":[
        "heating"
    ],
    "wof:name":"L.P Jeffcoate",
    "wof:placetype":"venue"
},
  "geometry": {"coordinates":[-0.250773,51.397598],"type":"Point"}
}