{
  "type": "Feature",
  "properties": {
    "iso:country":"GB",
    "sg:address":"39 Market Street",
    "sg:city":"Bridgwater",
    "sg:classifiers":[
        {
            "category":"Community Center",
            "subcategory":"Senior",
            "type":"Public Place"
        },
        {
            "category":"Home & Garden",
            "subcategory":"Furniture",
            "type":"Retail Goods"
        }
    ],
    "sg:phone":"+44 1278 444007",
    "sg:postcode":"TA6 3EP",
    "sg:province":"Somerset",
    "sg:tags":[
        "second",
        "hand"
    ],
    "wof:name":"D J's Furnishings",
    "wof:placetype":"venue"
},
  "geometry": {"coordinates":[-3.007395,51.128075],"type":"Point"}
}