{
  "type": "Feature",
  "properties": {
    "iso:country":"GB",
    "sg:address":"74 Icknield Way",
    "sg:city":"Baldock",
    "sg:classifiers":[
        {
            "category":"Professional",
            "subcategory":"Testing Lab",
            "type":"Services"
        }
    ],
    "sg:postcode":"SG7 5AN",
    "sg:province":"Bedfordshire",
    "sg:tags":[
        "mot"
    ],
    "wof:name":"L T G Motors",
    "wof:placetype":"venue"
},
  "geometry": {"coordinates":[-0.192423,51.99115],"type":"Point"}
}