{
  "type": "Feature",
  "properties": {
    "addr:full":"Queens Cross Dudley West Midlands DY1 1QW",
    "addr:postcode":"dy1 1qw",
    "addr:street":"Queens Cross",
    "iso:country":"GB",
    "sg:address":"Queens Cross",
    "sg:city":"Dudley",
    "sg:classifiers":[
        {
            "category":"Shopping",
            "subcategory":"Bicycles & Sporting Goods",
            "type":"Retail Goods"
        }
    ],
    "sg:phone":"+44 1384 844100",
    "sg:postcode":"DY1 1QW",
    "sg:province":"West Midlands",
    "sg:tags":[
        "tyre"
    ],
    "wof:name":"Wyko Equipments Ltd.",
    "wof:placetype":"venue"
},
  "geometry": {"coordinates":[-2.0922460556,52.5063095093],"type":"Point"}
}