{
  "type": "Feature",
  "properties": {
    "addr:full":"1 Statham Walk, Chorlton On Medlock Manchester Greater Manchester M13 9UZ",
    "addr:housenumber":"1",
    "addr:postcode":"m13 9uz",
    "addr:street":"Statham Walk",
    "iso:country":"GB",
    "sg:address":"1 Statham Walk, Chorlton On Medlock",
    "sg:city":"Manchester",
    "sg:classifiers":[
        {
            "category":"Utilities",
            "subcategory":"Refuse",
            "type":"Services"
        }
    ],
    "sg:postcode":"M13 9UZ",
    "sg:province":"Greater Manchester",
    "sg:tags":[
        "disposal",
        "waste"
    ],
    "wof:name":"Allied Waste Disposal",
    "wof:placetype":"venue"
},
  "geometry": {"coordinates":[-2.23069,53.47134],"type":"Point"}
}