{
  "type": "Feature",
  "properties": {
    "addr:full":"580 Leeds Road Wakefield West Yorkshire WF1 2DT",
    "addr:housenumber":"580",
    "addr:postcode":"wf1 2dt",
    "addr:street":"Leeds Road",
    "iso:country":"GB",
    "sg:address":"580 Leeds Road",
    "sg:city":"Wakefield",
    "sg:classifiers":[
        {
            "category":"Personal",
            "subcategory":"Beauty Salon",
            "type":"Services"
        }
    ],
    "sg:phone":"+44 1924 823241",
    "sg:postcode":"WF1 2DT",
    "sg:province":"West Yorkshire",
    "sg:tags":[
        "unisex",
        "hairdresser"
    ],
    "wof:name":"Images",
    "wof:placetype":"venue"
},
  "geometry": {"coordinates":[-1.4999330044,53.7119522095],"type":"Point"}
}