{
  "type": "Feature",
  "properties": {
    "addr:full":"Unit 9 Camelot Court, Bancombe Road Somerton Somerset TA11 6SB",
    "addr:housenumber":"unit 9",
    "addr:postcode":"ta11 6sb",
    "addr:street":"Camelot Court Bancombe Road",
    "iso:country":"GB",
    "sg:address":"Unit 9 Camelot Court, Bancombe Road",
    "sg:city":"Somerton",
    "sg:classifiers":[
        {
            "category":"Personal",
            "subcategory":"Skin Care",
            "type":"Services"
        }
    ],
    "sg:phone":"+44 1458 274035",
    "sg:postcode":"TA11 6SB",
    "sg:province":"Somerset",
    "sg:tags":[
        "leather",
        "merchant"
    ],
    "wof:name":"Litston Leather & Sheepskin",
    "wof:placetype":"venue"
},
  "geometry": {"coordinates":[-2.7489740849,51.056728363],"type":"Point"}
}