{
  "type": "Feature",
  "properties": {
    "addr:full":"70 Commercial Street, Ystalyfera Swansea Carmarthenshire SA9 2HS",
    "addr:housenumber":"70",
    "addr:postcode":"sa9 2hs",
    "addr:street":"Commercial Street",
    "iso:country":"GB",
    "sg:address":"70 Commercial Street, Ystalyfera",
    "sg:city":"Swansea",
    "sg:classifiers":[
        {
            "category":"Bars & Pubs",
            "type":"Food & Drink"
        }
    ],
    "sg:phone":"+44 1639 849420",
    "sg:postcode":"SA9 2HS",
    "sg:province":"Carmarthenshire",
    "sg:tags":[
        "pubs",
        "house",
        "inn",
        "public",
        "activity"
    ],
    "wof:name":"The Corner House",
    "wof:placetype":"venue"
},
  "geometry": {"coordinates":[-3.783969,51.766239],"type":"Point"}
}