{
  "type": "Feature",
  "properties": {
    "addr:full":"Malpas Road, Tilston Malpas Cheshire SY14 7HH",
    "addr:postcode":"sy14 7hh",
    "addr:street":"Malpas Road",
    "iso:country":"GB",
    "sg:address":"Malpas Road, Tilston",
    "sg:city":"Malpas",
    "sg:classifiers":[
        {
            "category":"Bars & Pubs",
            "type":"Food & Drink"
        }
    ],
    "sg:phone":"+44 1829 250255",
    "sg:postcode":"SY14 7HH",
    "sg:province":"Cheshire",
    "sg:tags":[
        "pubs",
        "inn"
    ],
    "wof:name":"Marston Thompson & Evershed Ltd.",
    "wof:placetype":"venue"
},
  "geometry": {"coordinates":[-2.807329,53.056671],"type":"Point"}
}