{
  "type": "Feature",
  "properties": {
    "iso:country":"GB",
    "sg:address":"Haydock Park Road",
    "sg:city":"Derby",
    "sg:classifiers":[
        {
            "category":"Building & Trades",
            "subcategory":"Construction",
            "type":"Services"
        }
    ],
    "sg:phone":"+44 1332 293123",
    "sg:postcode":"DE24 8HT",
    "sg:province":"Derbyshire",
    "sg:tags":[
        "glass",
        "replacement"
    ],
    "wof:name":"Alvaston Glass",
    "wof:placetype":"venue"
},
  "geometry": {"coordinates":[-1.446865,52.898689],"type":"Point"}
}