{
  "type": "Feature",
  "properties": {
    "addr:full":"117 Abington Avenue Northampton Northamptonshire NN1 4QB",
    "addr:housenumber":"117",
    "addr:postcode":"nn1 4qb",
    "addr:street":"Abington Avenue",
    "iso:country":"GB",
    "sg:address":"117 Abington Avenue",
    "sg:city":"Northampton",
    "sg:classifiers":[
        {
            "category":"Home & Garden",
            "subcategory":"Furniture",
            "type":"Retail Goods"
        }
    ],
    "sg:phone":"+44 1604 711000",
    "sg:postcode":"NN1 4QB",
    "sg:province":"Northamptonshire",
    "wof:name":"West Country Pine",
    "wof:placetype":"venue"
},
  "geometry": {"coordinates":[-0.875921,52.248539],"type":"Point"}
}