{
  "type": "Feature",
  "properties": {
    "addr:full":"13 St Andrews Way, Bromely By Bow London Greater London E3 3PB",
    "addr:housenumber":"13",
    "addr:postcode":"e3 3pb",
    "addr:street":"St Andrews Way",
    "iso:country":"GB",
    "sg:address":"13 St Andrews Way, Bromely By Bow",
    "sg:city":"London",
    "sg:classifiers":[
        {
            "category":"Professional",
            "subcategory":"Printing & Photocopies",
            "type":"Services"
        }
    ],
    "sg:phone":"+44 20 7515 0044",
    "sg:postcode":"E3 3PB",
    "sg:province":"Greater London",
    "sg:tags":[
        "print",
        "finisher"
    ],
    "wof:name":"T J Finishing Ltd.",
    "wof:placetype":"venue"
},
  "geometry": {"coordinates":[-0.015266,51.520996],"type":"Point"}
}