{
  "type": "Feature",
  "properties": {
    "iso:country":"GB",
    "sg:address":"301 Bonkle Road, Newmains",
    "sg:city":"Wishaw",
    "sg:classifiers":[
        {
            "category":"Shopping",
            "subcategory":"News",
            "type":"Retail Goods"
        }
    ],
    "sg:postcode":"ML2 9QQ",
    "sg:province":"North Lanarkshire",
    "sg:tags":[
        "newsagent"
    ],
    "wof:name":"The Village Shop",
    "wof:placetype":"venue"
},
  "geometry": {"coordinates":[-3.858846,55.791492],"type":"Point"}
}