{
  "type": "Feature",
  "properties": {
    "addr:full":"Harts Boats, Harts Boat Yard, Portsmouth Road Surbiton Surrey KT6 4HJ",
    "addr:postcode":"kt6 4hj",
    "addr:street":"Portsmouth Road",
    "iso:country":"GB",
    "sg:address":"Harts Boats, Harts Boat Yard, Portsmouth Road",
    "sg:city":"Surbiton",
    "sg:classifiers":[
        {
            "category":"Recreation",
            "subcategory":"Boat Charter",
            "type":"Entertainment"
        }
    ],
    "sg:phone":"+44 1932 228019",
    "sg:postcode":"KT6 4HJ",
    "sg:province":"Surrey",
    "sg:tags":[
        "excursion"
    ],
    "wof:name":"D B H Boat Hire",
    "wof:placetype":"venue"
},
  "geometry": {"coordinates":[-0.3069489896,51.3920593262],"type":"Point"}
}