{
  "type": "Feature",
  "properties": {
    "addr:full":"41 Fore St Exeter Devon EX5 4NN",
    "addr:housenumber":"41",
    "addr:postcode":"ex5 4nn",
    "addr:street":"Fore St",
    "iso:country":"GB",
    "sg:address":"41 Fore St",
    "sg:city":"Exeter",
    "sg:classifiers":[
        {
            "category":"Manufacturing",
            "subcategory":"Glass & Minerals",
            "type":"Manufacturing & Wholesale Goods"
        }
    ],
    "sg:phone":"+44 1392 881882",
    "sg:postcode":"EX5 4NN",
    "sg:province":"Devon",
    "sg:tags":[
        "stained"
    ],
    "wof:name":"Hannah West Designs",
    "wof:placetype":"venue"
},
  "geometry": {"coordinates":[-3.4204499722,50.8280677795],"type":"Point"}
}