{
  "type": "Feature",
  "properties": {
    "addr:full":"29 Tom Stuart Lane St Andrews Fife KY16 8YB",
    "addr:housenumber":"29",
    "addr:postcode":"ky16 8yb",
    "addr:street":"Tom Stuart Lane",
    "iso:country":"GB",
    "sg:address":"29 Tom Stuart Lane",
    "sg:city":"St Andrews",
    "sg:classifiers":[
        {
            "category":"Shopping",
            "subcategory":"Department Store",
            "type":"Retail Goods"
        }
    ],
    "sg:postcode":"KY16 8YB",
    "sg:province":"Fife",
    "wof:name":"Angus McLean",
    "wof:placetype":"venue"
},
  "geometry": {"coordinates":[-2.8036949635,56.3303642273],"type":"Point"}
}