{
  "type": "Feature",
  "properties": {
    "addr:full":"The Warehouse Harrogate North Yorkshire HG1 2AN",
    "addr:postcode":"hg1 2an",
    "iso:country":"GB",
    "sg:address":"The Warehouse",
    "sg:city":"Harrogate",
    "sg:classifiers":[
        {
            "category":"Professional",
            "type":"Services"
        }
    ],
    "sg:phone":"+44 870 330 0787",
    "sg:postcode":"HG1 2AN",
    "sg:province":"North Yorkshire",
    "sg:tags":[
        "entertainer"
    ],
    "wof:name":"The Entertainment Zone (Uk) Ltd.",
    "wof:placetype":"venue"
},
  "geometry": {"coordinates":[-1.544524,53.99469],"type":"Point"}
}