{
  "type": "Feature",
  "properties": {
    "addr:full":"Widmer Farm, Pink Road, Lacey Grn Princes Risborough Buckinghamshire HP27 0PG",
    "addr:postcode":"hp27 0pg",
    "addr:street":"Pink Road;Grn",
    "iso:country":"GB",
    "sg:address":"Widmer Farm, Pink Road, Lacey Grn",
    "sg:city":"Princes Risborough",
    "sg:classifiers":[
        {
            "category":"Sports & Exercise",
            "subcategory":"Stables",
            "type":"Entertainment"
        }
    ],
    "sg:phone":"+44 1844 275139",
    "sg:postcode":"HP27 0PG",
    "sg:province":"Buckinghamshire",
    "sg:tags":[
        "equestrian",
        "centre",
        "livery",
        "schools",
        "riding",
        "education"
    ],
    "wof:name":"Widmer Equestrian Centre",
    "wof:placetype":"venue"
},
  "geometry": {"coordinates":[-0.832952,51.721622],"type":"Point"}
}