{
  "type": "Feature",
  "properties": {
    "addr:full":"Mungy Lane, Doncaster Road Rotherham South Yorkshire S65 4AQ",
    "addr:postcode":"s65 4aq",
    "addr:street":"Mungy Lane Doncaster Road",
    "iso:country":"GB",
    "sg:address":"Mungy Lane, Doncaster Road",
    "sg:city":"Rotherham",
    "sg:classifiers":[
        {
            "category":"Retail",
            "subcategory":"Auto Repair",
            "type":"Services"
        }
    ],
    "sg:phone":"+44 1709 850731",
    "sg:postcode":"S65 4AQ",
    "sg:province":"South Yorkshire",
    "sg:tags":[
        "modification",
        "garage",
        "related"
    ],
    "wof:name":"Thrybergh Motor Services",
    "wof:placetype":"venue"
},
  "geometry": {"coordinates":[-1.30434,53.44928],"type":"Point"}
}