{
  "type": "Feature",
  "properties": {
    "iso:country":"GB",
    "sg:address":"20 Townhead Street",
    "sg:city":"Hamilton",
    "sg:classifiers":[
        {
            "category":"Professional",
            "subcategory":"Computer Services",
            "type":"Services"
        }
    ],
    "sg:phone":"+44 1698 421115",
    "sg:postcode":"ML3 7BE",
    "sg:province":"South Lanarkshire",
    "sg:tags":[
        "system",
        "software"
    ],
    "wof:name":"Sound Technology Systems",
    "wof:placetype":"venue"
},
  "geometry": {"coordinates":[-4.033461,55.775768],"type":"Point"}
}