{
  "type": "Feature",
  "properties": {
    "addr:full":"7 Moston Lane Manchester Greater Manchester M9 4AD",
    "addr:housenumber":"7",
    "addr:postcode":"m9 4ad",
    "addr:street":"Moston Lane",
    "iso:country":"GB",
    "sg:address":"7 Moston Lane",
    "sg:city":"Manchester",
    "sg:classifiers":[
        {
            "category":"Fast Food",
            "type":"Food & Drink"
        }
    ],
    "sg:postcode":"M9 4AD",
    "sg:province":"Greater Manchester",
    "sg:tags":[
        "away",
        "take"
    ],
    "wof:name":"Snax Cafe",
    "wof:placetype":"venue"
},
  "geometry": {"coordinates":[-2.211692,53.513855],"type":"Point"}
}