{
  "type": "Feature",
  "properties": {
    "addr:full":"45 St Johns Street Bedford Bedfordshire MK42 0AB",
    "addr:housenumber":"45",
    "addr:postcode":"mk42 0ab",
    "addr:street":"St Johns Street",
    "iso:country":"GB",
    "sg:address":"45 St Johns Street",
    "sg:city":"Bedford",
    "sg:classifiers":[
        {
            "category":"Bars & Pubs",
            "type":"Food & Drink"
        }
    ],
    "sg:phone":"+44 1234 352862",
    "sg:postcode":"MK42 0AB",
    "sg:province":"Bedfordshire",
    "sg:tags":[
        "pubs",
        "inn"
    ],
    "wof:name":"The Phoenix",
    "wof:placetype":"venue"
},
  "geometry": {"coordinates":[-0.464965,52.1306],"type":"Point"}
}