{
  "type": "Feature",
  "properties": {
    "iso:country":"GB",
    "sg:address":"Barley Mow",
    "sg:city":"Lampeter",
    "sg:classifiers":[
        {
            "category":"Manufacturing",
            "subcategory":"Metals",
            "type":"Manufacturing & Wholesale Goods"
        }
    ],
    "sg:postcode":"SA48 7BY",
    "sg:province":"Carmarthenshire",
    "sg:tags":[
        "blacksmith",
        "forgemasters"
    ],
    "wof:name":"Alec Page",
    "wof:placetype":"venue"
},
  "geometry": {"coordinates":[-4.0774650574,52.1142616272],"type":"Point"}
}