{
  "type": "Feature",
  "properties": {
    "addr:full":"Tiverton Railway Station, Sampford Peverell Tiverton Devon EX16 7EH",
    "addr:housenumber":"peverell",
    "addr:postcode":"ex16 7eh",
    "addr:street":"Sampford",
    "iso:country":"GB",
    "sg:address":"Tiverton Railway Station, Sampford Peverell",
    "sg:city":"Tiverton",
    "sg:classifiers":[
        {
            "category":"Freight",
            "type":"Transportation"
        }
    ],
    "sg:phone":"+44 1884 820246",
    "sg:postcode":"EX16 7EH",
    "sg:province":"Devon",
    "sg:tags":[
        "haulage",
        "road"
    ],
    "wof:name":"Red Star Parcels Ltd.",
    "wof:placetype":"venue"
},
  "geometry": {"coordinates":[-3.3793439865,50.9195594788],"type":"Point"}
}