{
  "type": "Feature",
  "properties": {
    "addr:full":"Festivals House, 198 Park Lane Macclesfield Cheshire SK11 6UD",
    "addr:housenumber":"198",
    "addr:postcode":"sk11 6ud",
    "addr:street":"Park Lane",
    "iso:country":"GB",
    "sg:address":"Festivals House, 198 Park Lane",
    "sg:city":"Macclesfield",
    "sg:classifiers":[
        {
            "category":"Organizations",
            "subcategory":"Non-profit Organization",
            "type":"Services"
        }
    ],
    "sg:phone":"+44 870 774 4290",
    "sg:postcode":"SK11 6UD",
    "sg:province":"Cheshire",
    "sg:tags":[
        "organisation",
        "voluntary",
        "charity"
    ],
    "wof:name":"The British & International Federation of Festivals for Music",
    "wof:placetype":"venue"
},
  "geometry": {"coordinates":[-2.130123,53.25362],"type":"Point"}
}