{
  "type": "Feature",
  "properties": {
    "addr:full":"110 Huddersfield Road Barnsley South Yorkshire S75 1HA",
    "addr:housenumber":"110",
    "addr:postcode":"s75 1ha",
    "addr:street":"Huddersfield Road;Yorkshire",
    "iso:country":"GB",
    "sg:address":"110 Huddersfield Road",
    "sg:city":"Barnsley",
    "sg:classifiers":[
        {
            "category":"Retail",
            "subcategory":"Repair Shop",
            "type":"Services"
        }
    ],
    "sg:phone":"+44 1226 205516",
    "sg:postcode":"S75 1HA",
    "sg:province":"South Yorkshire",
    "sg:tags":[
        "maintenance"
    ],
    "wof:name":"David Heeley",
    "wof:placetype":"venue"
},
  "geometry": {"coordinates":[-1.4969379902,53.5640792847],"type":"Point"}
}