{
  "type": "Feature",
  "properties": {
    "addr:full":"50 The Green, South Bar Banbury Oxfordshire OX16 9AB",
    "addr:housenumber":"50",
    "addr:postcode":"ox16 9ab",
    "addr:street":"The Green",
    "iso:country":"GB",
    "sg:address":"50 The Green, South Bar",
    "sg:city":"Banbury",
    "sg:classifiers":[
        {
            "category":"Real Estate",
            "subcategory":"Surveying",
            "type":"Services"
        }
    ],
    "sg:postcode":"OX16 9AB",
    "sg:province":"Oxfordshire",
    "sg:tags":[
        "surveyor",
        "quantity"
    ],
    "wof:name":"Hadland Manning Bullock & Partners Ltd",
    "wof:placetype":"venue"
},
  "geometry": {"coordinates":[-1.3308589458,52.0544929504],"type":"Point"}
}