{
  "type": "Feature",
  "properties": {
    "iso:country":"GB",
    "sg:address":"Hope Corner Lane",
    "sg:city":"Taunton",
    "sg:classifiers":[
        {
            "category":"Social Services",
            "subcategory":"Adult Care",
            "type":"Services"
        },
        {
            "category":"Government",
            "subcategory":"Office",
            "type":"Public Place"
        }
    ],
    "sg:phone":"+44 1823 275515",
    "sg:postcode":"TA2 7NU",
    "sg:province":"Somerset",
    "sg:tags":[
        "housing",
        "local",
        "sheltered"
    ],
    "wof:name":"Hope Corner Lane Sheltered Housing",
    "wof:placetype":"venue"
},
  "geometry": {"coordinates":[-3.1078689098,51.0359458923],"type":"Point"}
}