{
  "type": "Feature",
  "properties": {
    "addr:full":"39a Oldmeldrum Road, Bucksburn Aberdeen Aberdeen City AB21 9AE",
    "addr:housenumber":"39a",
    "addr:postcode":"ab21 9ae",
    "addr:street":"Oldmeldrum Road",
    "iso:country":"GB",
    "sg:address":"39a Oldmeldrum Road, Bucksburn",
    "sg:city":"Aberdeen",
    "sg:classifiers":[
        {
            "category":"Professional",
            "subcategory":"Accounting & Tax Preparation",
            "type":"Services"
        }
    ],
    "sg:postcode":"AB21 9AE",
    "sg:province":"Aberdeen City",
    "sg:tags":[
        "accountant"
    ],
    "wof:name":"R V L Book Keeping Services",
    "wof:placetype":"venue"
},
  "geometry": {"coordinates":[-2.1733410358,57.1812744141],"type":"Point"}
}