{
  "type": "Feature",
  "properties": {
    "iso:country":"GB",
    "sg:address":"3 Stuart Crescent",
    "sg:city":"Reigate",
    "sg:classifiers":[
        {
            "category":"Building & Trades",
            "subcategory":"Construction",
            "type":"Services"
        }
    ],
    "sg:postcode":"RH2 8EB",
    "sg:province":"Surrey",
    "sg:tags":[
        "glazier"
    ],
    "wof:name":"Glass & Glazing Services",
    "wof:placetype":"venue"
},
  "geometry": {"coordinates":[-0.205295,51.224159],"type":"Point"}
}