{
  "type": "Feature",
  "properties": {
    "iso:country":"GB",
    "sg:address":"Johnson Street, Howe Bridge Atherton",
    "sg:city":"Wigan",
    "sg:classifiers":[
        {
            "category":"Museum",
            "subcategory":"Aquarium",
            "type":"Entertainment"
        }
    ],
    "sg:phone":"+44 1942 884994",
    "sg:postcode":"M46 0RB",
    "sg:province":"Greater Manchester",
    "sg:tags":[
        "vivarium",
        "mnfrs"
    ],
    "wof:name":"High Standards",
    "wof:placetype":"venue"
},
  "geometry": {"coordinates":[-2.5099039078,53.5151405334],"type":"Point"}
}