{
  "type": "Feature",
  "properties": {
    "addr:full":"Unit 10 Chichester Business Cent Rochdale Lancashire OL16 2AU",
    "addr:housenumber":"unit 10",
    "addr:postcode":"ol16 2au",
    "addr:street":"Chichester Business Cent Rochdale",
    "iso:country":"GB",
    "sg:address":"Unit 10 Chichester Business Cent",
    "sg:city":"Rochdale",
    "sg:classifiers":[
        {
            "category":"Building & Trades",
            "subcategory":"Construction",
            "type":"Services"
        }
    ],
    "sg:phone":"+44 1706 352139",
    "sg:postcode":"OL16 2AU",
    "sg:province":"Lancashire",
    "sg:tags":[
        "decorator",
        "painter"
    ],
    "wof:name":"Bamford Decorating Contractors Ltd.",
    "wof:placetype":"venue"
},
  "geometry": {"coordinates":[-2.1440010071,53.6149368286],"type":"Point"}
}