{
  "type": "Feature",
  "properties": {
    "iso:country":"GB",
    "sg:address":"33 Millfields, Eccleston",
    "sg:city":"St Helens",
    "sg:classifiers":[
        {
            "category":"Professional",
            "subcategory":"Accounting & Tax Preparation",
            "type":"Services"
        }
    ],
    "sg:postcode":"WA10 5NS",
    "sg:province":"Merseyside",
    "sg:tags":[
        "accountant"
    ],
    "wof:name":"W H & A Cookson",
    "wof:placetype":"venue"
},
  "geometry": {"coordinates":[-2.769739,53.452885],"type":"Point"}
}