{
  "type": "Feature",
  "properties": {
    "addr:full":"66 High Street Yarm North Yorkshire TS15 9AH",
    "addr:housenumber":"66",
    "addr:postcode":"ts15 9ah",
    "addr:street":"High Street",
    "iso:country":"GB",
    "sg:address":"66 High Street",
    "sg:city":"Yarm",
    "sg:classifiers":[
        {
            "category":"Shopping",
            "subcategory":"Bicycles & Sporting Goods",
            "type":"Retail Goods"
        }
    ],
    "sg:phone":"+44 1642 785423",
    "sg:postcode":"TS15 9AH",
    "sg:province":"North Yorkshire",
    "sg:tags":[
        "riding",
        "saddlery",
        "wear"
    ],
    "wof:name":"D J Sayer Saddlery",
    "wof:placetype":"venue"
},
  "geometry": {"coordinates":[-1.354369998,54.5096855164],"type":"Point"}
}