{
  "type": "Feature",
  "properties": {
    "addr:full":"5 Quantock Close Halesowen West Midlands B63 1HF",
    "addr:housenumber":"5",
    "addr:postcode":"b63 1hf",
    "addr:street":"Quantock Close",
    "iso:country":"GB",
    "sg:address":"5 Quantock Close",
    "sg:city":"Halesowen",
    "sg:classifiers":[
        {
            "category":"Retail",
            "subcategory":"Driving School",
            "type":"Services"
        },
        {
            "category":"Education",
            "subcategory":"School",
            "type":"Public Place"
        }
    ],
    "sg:phone":"+44 121 501 1252",
    "sg:postcode":"B63 1HF",
    "sg:province":"West Midlands",
    "sg:tags":[
        "instruction",
        "cycling",
        "motorcycle",
        "motor"
    ],
    "wof:name":"Roadcraft Motorcycle Training",
    "wof:placetype":"venue"
},
  "geometry": {"coordinates":[-2.07768,52.442181],"type":"Point"}
}