{
  "type": "Feature",
  "properties": {
    "iso:country":"GB",
    "sg:address":"19 Staveley Way, Brixworth Industrial Estate",
    "sg:city":"Northampton",
    "sg:classifiers":[
        {
            "category":"Home & Garden",
            "subcategory":"Home Furnishings",
            "type":"Retail Goods"
        }
    ],
    "sg:postcode":"NN6 9EU",
    "sg:province":"Northamptonshire",
    "sg:tags":[
        "awning",
        "canopy",
        "blinds"
    ],
    "wof:name":"D & R Blinds & Shutters",
    "wof:placetype":"venue"
},
  "geometry": {"coordinates":[-0.8983619809,52.3348312378],"type":"Point"}
}