{
  "type": "Feature",
  "properties": {
    "addr:full":"281 Ashley Road, Parkstone Poole Dorset BH14 9DS",
    "addr:housenumber":"281",
    "addr:postcode":"bh14 9ds",
    "addr:street":"Ashley Road",
    "iso:country":"GB",
    "sg:address":"281 Ashley Road, Parkstone",
    "sg:city":"Poole",
    "sg:classifiers":[
        {
            "category":"Home & Garden",
            "subcategory":"Carpets & Floor Coverings",
            "type":"Retail Goods"
        }
    ],
    "sg:phone":"+44 1202 744665",
    "sg:postcode":"BH14 9DS",
    "sg:province":"Dorset",
    "sg:tags":[
        "carpets",
        "rug",
        "matting"
    ],
    "wof:name":"Classic Carpets",
    "wof:placetype":"venue"
},
  "geometry": {"coordinates":[-1.9380040169,50.7286453247],"type":"Point"}
}