{
  "type": "Feature",
  "properties": {
    "addr:full":"72-74 Seaforth Road Liverpool Merseyside L21 4LF",
    "addr:housenumber":"72-74",
    "addr:postcode":"l21 4lf",
    "addr:street":"Seaforth Road",
    "iso:country":"GB",
    "sg:address":"72-74 Seaforth Road",
    "sg:city":"Liverpool",
    "sg:classifiers":[
        {
            "category":"Bars & Pubs",
            "type":"Food & Drink"
        }
    ],
    "sg:postcode":"L21 4LF",
    "sg:province":"Merseyside",
    "sg:tags":[
        "pubs",
        "inn"
    ],
    "wof:name":"The Seaforth Castle",
    "wof:placetype":"venue"
},
  "geometry": {"coordinates":[-3.008448,53.462296],"type":"Point"}
}