{
  "type": "Feature",
  "properties": {
    "iso:country":"GB",
    "sg:address":"3 Hill View Terrace, Mill Lane",
    "sg:city":"Woodbridge",
    "sg:classifiers":[
        {
            "category":"Home & Garden",
            "subcategory":"Home Furnishings",
            "type":"Retail Goods"
        }
    ],
    "sg:phone":"+44 1394 386328",
    "sg:postcode":"IP12 1HR",
    "sg:province":"Suffolk",
    "sg:tags":[
        "blind",
        "manufacture",
        "fitting",
        "curtain"
    ],
    "wof:name":"Barbara Ray",
    "wof:placetype":"venue"
},
  "geometry": {"coordinates":[1.3253899813,52.1054496765],"type":"Point"}
}