{
  "type": "Feature",
  "properties": {
    "addr:full":"27 Cairo Street Warrington Cheshire WA1 1EH",
    "addr:housenumber":"27",
    "addr:postcode":"wa1 1eh",
    "addr:street":"Cairo Street",
    "iso:country":"GB",
    "sg:address":"27 Cairo Street",
    "sg:city":"Warrington",
    "sg:classifiers":[
        {
            "category":"Insurance",
            "subcategory":"Insurance Agent",
            "type":"Services"
        }
    ],
    "sg:phone":"+44 1925 444408",
    "sg:postcode":"WA1 1EH",
    "sg:province":"Cheshire",
    "wof:name":"Riding Insurance",
    "wof:placetype":"venue"
},
  "geometry": {"coordinates":[-2.594912,53.387436],"type":"Point"}
}