{
  "type": "Feature",
  "properties": {
    "addr:full":"Osprey D, Cellton Indull Estate Exeter Devon EX2 7JG",
    "addr:postcode":"ex2 7jg",
    "iso:country":"GB",
    "sg:address":"Osprey D, Cellton Indull Estate",
    "sg:city":"Exeter",
    "sg:classifiers":[
        {
            "category":"Shopping",
            "subcategory":"Computers & Home Electronics",
            "type":"Retail Goods"
        }
    ],
    "sg:phone":"+44 1392 422212",
    "sg:postcode":"EX2 7JG",
    "sg:province":"Devon",
    "sg:tags":[
        "equipment",
        "radio"
    ],
    "wof:name":"Premier Communication Electronics Ltd.",
    "wof:placetype":"venue"
},
  "geometry": {"coordinates":[-3.464277029,50.7244300842],"type":"Point"}
}