{
  "type": "Feature",
  "properties": {
    "addr:full":"339a Finchley Rd Wembley Greater London HA0 2RX",
    "addr:housenumber":"339a",
    "addr:postcode":"ha0 2rx",
    "addr:street":"Finchley Rd",
    "iso:country":"GB",
    "sg:address":"339a Finchley Rd",
    "sg:city":"Wembley",
    "sg:classifiers":[
        {
            "category":"Professional",
            "subcategory":"Lawyer & Legal Services",
            "type":"Services"
        }
    ],
    "sg:phone":"+44 20 8904 7460",
    "sg:postcode":"HA0 2RX",
    "sg:province":"Greater London",
    "sg:tags":[
        "solicitor"
    ],
    "wof:name":"Juris Chambers",
    "wof:placetype":"venue"
},
  "geometry": {"coordinates":[-0.32584,51.55859],"type":"Point"}
}