{
  "type": "Feature",
  "properties": {
    "addr:full":"37 High Street Shaftesbury Dorset SP7 8JE",
    "addr:housenumber":"37",
    "addr:postcode":"sp7 8je",
    "addr:street":"High Street",
    "iso:country":"GB",
    "sg:address":"37 High Street",
    "sg:city":"Shaftesbury",
    "sg:classifiers":[
        {
            "category":"Shopping",
            "subcategory":"Clothing, Apparel, & Fashions",
            "type":"Retail Goods"
        }
    ],
    "sg:postcode":"SP7 8JE",
    "sg:province":"Dorset",
    "sg:tags":[
        "workwear",
        "protective"
    ],
    "wof:name":"Sport Equip",
    "wof:placetype":"venue"
},
  "geometry": {"coordinates":[-2.1963560581,51.0058555603],"type":"Point"}
}