{
  "type": "Feature",
  "properties": {
    "addr:full":"Warwick House, 87 Warwick Road Olton Solihull West Midlands B92 7HP",
    "addr:housenumber":"87",
    "addr:postcode":"b92 7hp",
    "addr:street":"Warwick Road",
    "iso:country":"GB",
    "sg:address":"Warwick House, 87 Warwick Road Olton",
    "sg:city":"Solihull",
    "sg:classifiers":[
        {
            "category":"Building & Trades",
            "subcategory":"Construction",
            "type":"Services"
        }
    ],
    "sg:phone":"+44 121 764 7644",
    "sg:postcode":"B92 7HP",
    "sg:province":"West Midlands",
    "sg:tags":[
        "roofing"
    ],
    "wof:name":"Vedag Ltd.",
    "wof:placetype":"venue"
},
  "geometry": {"coordinates":[-1.809444,52.440655],"type":"Point"}
}