{
  "type": "Feature",
  "properties": {
    "addr:full":"Church Rd Liverpool Merseyside L26 6LB",
    "addr:postcode":"l26 6lb",
    "addr:street":"Church Rd",
    "iso:country":"GB",
    "sg:address":"Church Rd",
    "sg:city":"Liverpool",
    "sg:classifiers":[
        {
            "category":"Professional",
            "subcategory":"Lawyer & Legal Services",
            "type":"Services"
        }
    ],
    "sg:phone":"+44 151 488 6648",
    "sg:postcode":"L26 6LB",
    "sg:province":"Merseyside",
    "sg:tags":[
        "advice",
        "counselling"
    ],
    "wof:name":"Halewood Listening Ear",
    "wof:placetype":"venue"
},
  "geometry": {"coordinates":[-2.8302109241,53.3704833984],"type":"Point"}
}