{
  "type": "Feature",
  "properties": {
    "iso:country":"GB",
    "sg:address":"Old Bank Ho, 3 Hartshead",
    "sg:city":"Sheffield",
    "sg:classifiers":[
        {
            "category":"Professional",
            "subcategory":"Lawyer & Legal Services",
            "type":"Services"
        }
    ],
    "sg:phone":"+44 114 275 1223",
    "sg:postcode":"S1 2EL",
    "sg:province":"South Yorkshire",
    "sg:tags":[
        "barrister"
    ],
    "wof:name":"J S Baird",
    "wof:placetype":"venue"
},
  "geometry": {"coordinates":[-1.464544,53.38311],"type":"Point"}
}