{
  "type": "Feature",
  "properties": {
    "iso:country":"GB",
    "sg:address":"Upper Hill Farm, Hill",
    "sg:city":"Berkeley",
    "sg:classifiers":[
        {
            "category":"Farming",
            "subcategory":"Livestock Farm",
            "type":"Manufacturing & Wholesale Goods"
        },
        {
            "category":"Farming",
            "subcategory":"Farm",
            "type":"Manufacturing & Wholesale Goods"
        }
    ],
    "sg:phone":"+44 1454 260229",
    "sg:postcode":"GL13 9EE",
    "sg:province":"Gloucestershire",
    "sg:tags":[
        "mixed",
        "crop",
        "others"
    ],
    "wof:name":"Richard T Baimbridge",
    "wof:placetype":"venue"
},
  "geometry": {"coordinates":[-2.4595689774,51.6931877136],"type":"Point"}
}