{
  "type": "Feature",
  "properties": {
    "addr:full":"The Gateway Centre, North Methven Street Perth Perth and Kinross PH1 5PP",
    "addr:postcode":"ph1 5pp",
    "addr:street":"North Methven Street",
    "iso:country":"GB",
    "sg:address":"The Gateway Centre, North Methven Street",
    "sg:city":"Perth",
    "sg:classifiers":[
        {
            "category":"Organizations",
            "subcategory":"Non-profit Organization",
            "type":"Services"
        }
    ],
    "sg:phone":"+44 1738 445899",
    "sg:postcode":"PH1 5PP",
    "sg:province":"Perth and Kinross",
    "sg:tags":[
        "organisation",
        "voluntary",
        "charity"
    ],
    "wof:name":"Perth & Kinross Independent Advocacy Service",
    "wof:placetype":"venue"
},
  "geometry": {"coordinates":[-3.43483,56.398651],"type":"Point"}
}