{
  "type": "Feature",
  "properties": {
    "iso:country":"GB",
    "sg:address":"143 High Street",
    "sg:city":"Newport",
    "sg:classifiers":[
        {
            "category":"Cafe",
            "type":"Food & Drink"
        }
    ],
    "sg:phone":"+44 1983 826190",
    "sg:postcode":"PO30 1TY",
    "sg:province":"Isle of Wight",
    "sg:tags":[
        "tea",
        "room"
    ],
    "wof:name":"Island Images",
    "wof:placetype":"venue"
},
  "geometry": {"coordinates":[-1.291123,50.70055],"type":"Point"}
}