{
  "type": "Feature",
  "properties": {
    "iso:country":"GB",
    "sg:address":"20 Penistone Rd, Kirkburton",
    "sg:city":"Huddersfield",
    "sg:classifiers":[
        {
            "category":"Bars & Pubs",
            "type":"Food & Drink"
        }
    ],
    "sg:postcode":"HD8 0PQ",
    "sg:province":"South Yorkshire",
    "sg:tags":[
        "pubs",
        "inn"
    ],
    "wof:name":"Boden,John,",
    "wof:placetype":"venue"
},
  "geometry": {"coordinates":[-1.715525,53.616547],"type":"Point"}
}