{
  "type": "Feature",
  "properties": {
    "addr:full":"Unit 1/5, Trafalgar Industrial Estate, Sovereign Way Downham Market Cambridgeshire PE38 9SW",
    "addr:housenumber":"unit 1 / 5;estate",
    "addr:postcode":"pe38 9sw",
    "addr:street":"Industrial;Sovereign Way",
    "iso:country":"GB",
    "sg:address":"Unit 1/5, Trafalgar Industrial Estate, Sovereign Way",
    "sg:city":"Downham Market",
    "sg:classifiers":[
        {
            "category":"Shopping",
            "subcategory":"Computers & Home Electronics",
            "type":"Retail Goods"
        }
    ],
    "sg:phone":"+44 1366 389400",
    "sg:postcode":"PE38 9SW",
    "sg:province":"Cambridgeshire",
    "wof:name":"Christopher Clark Workshops",
    "wof:placetype":"venue"
},
  "geometry": {"coordinates":[0.378795,52.602283],"type":"Point"}
}