{
  "type": "Feature",
  "properties": {
    "addr:full":"26 Christchurch St, Fenton Stoke On Trent Staffordshire ST4 3AD",
    "addr:housenumber":"26",
    "addr:postcode":"st4 3ad",
    "addr:street":"Christchurch St",
    "iso:country":"GB",
    "sg:address":"26 Christchurch St, Fenton",
    "sg:city":"Stoke On Trent",
    "sg:classifiers":[
        {
            "category":"Health Services",
            "subcategory":"Nursing And Care Facility",
            "type":"Services"
        }
    ],
    "sg:phone":"+44 1782 745566",
    "sg:postcode":"ST4 3AD",
    "sg:province":"Staffordshire",
    "sg:tags":[
        "home"
    ],
    "wof:name":"Community Careline Services",
    "wof:placetype":"venue"
},
  "geometry": {"coordinates":[-2.164634943,52.998878479],"type":"Point"}
}