{
  "type": "Feature",
  "properties": {
    "addr:full":"25 Mount Pleasant Redditch Warwickshire B97 4HY",
    "addr:housenumber":"25",
    "addr:postcode":"b97 4hy",
    "addr:street":"Mount Pleasant",
    "iso:country":"GB",
    "sg:address":"25 Mount Pleasant",
    "sg:city":"Redditch",
    "sg:classifiers":[
        {
            "category":"Shopping",
            "subcategory":"News",
            "type":"Retail Goods"
        }
    ],
    "sg:phone":"+44 1527 61141",
    "sg:postcode":"B97 4HY",
    "sg:province":"Warwickshire",
    "sg:tags":[
        "newsagent"
    ],
    "wof:name":"JESSONS NEWS",
    "wof:placetype":"venue"
},
  "geometry": {"coordinates":[-1.942247,52.302177],"type":"Point"}
}