{
  "type": "Feature",
  "properties": {
    "iso:country":"GB",
    "sg:address":"24 Tetherdown",
    "sg:city":"London",
    "sg:classifiers":[
        {
            "category":"Farming",
            "subcategory":"Nursery",
            "type":"Manufacturing & Wholesale Goods"
        },
        {
            "category":"Education",
            "subcategory":"Preschool",
            "type":"Public Place"
        }
    ],
    "sg:phone":"+44 20 8883 7958",
    "sg:postcode":"N10 1NB",
    "sg:province":"Greater London",
    "sg:tags":[
        "school",
        "creche"
    ],
    "wof:name":"The Nursery Montessori",
    "wof:placetype":"venue"
},
  "geometry": {"coordinates":[-0.1491030008,51.5922164917],"type":"Point"}
}