{
  "type": "Feature",
  "properties": {
    "addr:full":"68 Brewery Rd Holloway Greater London N7 9NE",
    "addr:housenumber":"68",
    "addr:postcode":"n7 9ne",
    "addr:street":"Brewery Rd",
    "iso:country":"GB",
    "sg:address":"68 Brewery Rd",
    "sg:city":"Holloway",
    "sg:classifiers":[
        {
            "category":"Wholesale",
            "subcategory":"Office Equipment",
            "type":"Manufacturing & Wholesale Goods"
        }
    ],
    "sg:phone":"+44 20 7607 9115",
    "sg:postcode":"N7 9NE",
    "sg:province":"Greater London",
    "sg:tags":[
        "partition",
        "cubicle"
    ],
    "wof:name":"Penwright Supplies",
    "wof:placetype":"venue"
},
  "geometry": {"coordinates":[-0.1216209978,51.5451774597],"type":"Point"}
}