{
  "type": "Feature",
  "properties": {
    "addr:full":"19 Southwick Square, Southwick Brighton West Sussex BN42 4FP",
    "addr:housenumber":"19",
    "addr:postcode":"bn42 4fp",
    "addr:street":"Southwick Square",
    "iso:country":"GB",
    "sg:address":"19 Southwick Square, Southwick",
    "sg:city":"Brighton",
    "sg:classifiers":[
        {
            "category":"Cinema",
            "subcategory":"Movie Rental",
            "type":"Entertainment"
        }
    ],
    "sg:phone":"+44 1273 596362",
    "sg:postcode":"BN42 4FP",
    "sg:province":"West Sussex",
    "sg:tags":[
        "video",
        "library"
    ],
    "wof:name":"Tomorrows World",
    "wof:placetype":"venue"
},
  "geometry": {"coordinates":[-0.23567,50.834068],"type":"Point"}
}