{
  "type": "Feature",
  "properties": {
    "iso:country":"GB",
    "sg:address":"Unit 42 Southwater Arcade, The Telford Centre",
    "sg:city":"Telford",
    "sg:classifiers":[
        {
            "category":"Shopping",
            "subcategory":"Stationery & Office Supplies",
            "type":"Retail Goods"
        }
    ],
    "sg:phone":"+44 1952 291651",
    "sg:postcode":"TF3 4AE",
    "sg:province":"Shropshire",
    "wof:name":"Partners the Stationers",
    "wof:placetype":"venue"
},
  "geometry": {"coordinates":[-2.4540419579,52.6764984131],"type":"Point"}
}