{
  "type": "Feature",
  "properties": {
    "addr:full":"12 Blenheim Crescent London Greater London W11 1NN",
    "addr:housenumber":"12",
    "addr:postcode":"w11 1nn",
    "addr:street":"Blenheim Crescent",
    "iso:country":"GB",
    "sg:address":"12 Blenheim Crescent",
    "sg:city":"London",
    "sg:classifiers":[
        {
            "category":"Cafe",
            "type":"Food & Drink"
        }
    ],
    "sg:phone":"+44 20 7229 3757",
    "sg:postcode":"W11 1NN",
    "sg:province":"Greater London",
    "sg:tags":[
        "tea",
        "room"
    ],
    "wof:name":"Mike's Cafe Ltd.",
    "wof:placetype":"venue"
},
  "geometry": {"coordinates":[-0.205746,51.515858],"type":"Point"}
}