{
  "type": "Feature",
  "properties": {
    "iso:country":"GB",
    "sg:address":"167 Richmond Road",
    "sg:city":"Accrington",
    "sg:classifiers":[
        {
            "category":"Manufacturing",
            "subcategory":"Petroleum Products",
            "type":"Manufacturing & Wholesale Goods"
        },
        {
            "category":"Building & Trades",
            "subcategory":"Construction",
            "type":"Services"
        }
    ],
    "sg:phone":"+44 1254 237967",
    "sg:postcode":"BB5 0JB",
    "sg:province":"Lancashire",
    "sg:tags":[
        "double",
        "glazing",
        "installers"
    ],
    "wof:name":"Ultimate Window Services",
    "wof:placetype":"venue"
},
  "geometry": {"coordinates":[-2.378911,53.746212],"type":"Point"}
}