{
  "type": "Feature",
  "properties": {
    "iso:country":"GB",
    "sg:address":"12 New Southgate Indust Est, Lower Park Rd",
    "sg:city":"Friern Barnet",
    "sg:classifiers":[
        {
            "category":"Manufacturing",
            "subcategory":"Building Materials",
            "type":"Manufacturing & Wholesale Goods"
        }
    ],
    "sg:phone":"+44 20 8368 2593",
    "sg:postcode":"N11 1QD",
    "sg:province":"Greater London",
    "sg:tags":[
        "gate",
        "mnfrs"
    ],
    "wof:name":"Argon Arc Welding Services",
    "wof:placetype":"venue"
},
  "geometry": {"coordinates":[-0.1366900057,51.6121711731],"type":"Point"}
}