{
  "type": "Feature",
  "properties": {
    "iso:country":"GB",
    "sg:address":"11 Union Square",
    "sg:city":"West Calder",
    "sg:classifiers":[
        {
            "category":"Health Services",
            "subcategory":"Optometrist",
            "type":"Services"
        }
    ],
    "sg:phone":"+44 1506 873374",
    "sg:postcode":"EH55 8EY",
    "sg:province":"South Lanarkshire",
    "sg:tags":[
        "optician"
    ],
    "wof:name":"Stewart Opticians",
    "wof:placetype":"venue"
},
  "geometry": {"coordinates":[-3.572372,55.851124],"type":"Point"}
}