{
  "type": "Feature",
  "properties": {
    "iso:country":"GB",
    "sg:address":"Unit 2 Ramsay Colliery, Engine Road",
    "sg:city":"Loanhead",
    "sg:classifiers":[
        {
            "category":"Building & Trades",
            "subcategory":"Construction",
            "type":"Services"
        }
    ],
    "sg:phone":"+44 131 440 0655",
    "sg:postcode":"EH20 9RF",
    "sg:province":"Midlothian",
    "sg:tags":[
        "builder"
    ],
    "wof:name":"Oliver Contracts Ltd.",
    "wof:placetype":"venue"
},
  "geometry": {"coordinates":[-3.14922,55.877697],"type":"Point"}
}