{
  "type": "Feature",
  "properties": {
    "addr:full":"1 Elm Terr Hampstead Greater London NW3 2LL",
    "addr:housenumber":"1",
    "addr:postcode":"nw3 2ll",
    "addr:street":"Elm Terr",
    "iso:country":"GB",
    "sg:address":"1 Elm Terr",
    "sg:city":"Hampstead",
    "sg:classifiers":[
        {
            "category":"Shopping",
            "subcategory":"News",
            "type":"Retail Goods"
        }
    ],
    "sg:phone":"+44 20 7485 5356",
    "sg:postcode":"NW3 2LL",
    "sg:province":"Greater London",
    "sg:tags":[
        "newsagent"
    ],
    "wof:name":"Corner Shop The",
    "wof:placetype":"venue"
},
  "geometry": {"coordinates":[-0.178231,51.559181],"type":"Point"}
}