{
  "type": "Feature",
  "properties": {
    "iso:country":"GB",
    "sg:address":"The Hollies, Chapel Road, Tumby Woodside",
    "sg:city":"Boston",
    "sg:classifiers":[
        {
            "category":"Farming",
            "subcategory":"Crops",
            "type":"Manufacturing & Wholesale Goods"
        },
        {
            "category":"Farming",
            "subcategory":"Farm",
            "type":"Manufacturing & Wholesale Goods"
        }
    ],
    "sg:phone":"+44 1526 342253",
    "sg:postcode":"PE22 7SP",
    "sg:province":"Lincolnshire",
    "sg:tags":[
        "mixed",
        "arable"
    ],
    "wof:name":"B R & S A Wilson",
    "wof:placetype":"venue"
},
  "geometry": {"coordinates":[-0.11249,53.096939],"type":"Point"}
}