{
  "type": "Feature",
  "properties": {
    "iso:country":"GB",
    "sg:address":"Penderllwyngoch, Tynygraig",
    "sg:city":"Ystrad Meurig",
    "sg:classifiers":[
        {
            "category":"Farming",
            "subcategory":"Dairy Farm",
            "type":"Manufacturing & Wholesale Goods"
        }
    ],
    "sg:phone":"+44 1974 261270",
    "sg:postcode":"SY25 6AQ",
    "sg:province":"Ceredigion",
    "wof:name":"Thomas John Humphreys",
    "wof:placetype":"venue"
},
  "geometry": {"coordinates":[-3.9020819664,52.2914733887],"type":"Point"}
}