{
  "type": "Feature",
  "properties": {
    "addr:full":"Hyde St Deptford Greater London SE8 3NT",
    "addr:postcode":"se8 3nt",
    "addr:street":"Hyde St",
    "iso:country":"GB",
    "sg:address":"Hyde St",
    "sg:city":"Deptford",
    "sg:classifiers":[
        {
            "category":"Retail",
            "subcategory":"Auto Repair",
            "type":"Services"
        }
    ],
    "sg:phone":"+44 20 8692 0977",
    "sg:postcode":"SE8 3NT",
    "sg:province":"Greater London",
    "sg:tags":[
        "modification",
        "garage"
    ],
    "wof:name":"VW Van & Caravanette Centre",
    "wof:placetype":"venue"
},
  "geometry": {"coordinates":[-0.0261240005,51.4791107178],"type":"Point"}
}