{
  "type": "Feature",
  "properties": {
    "addr:full":"Holly House, Great North Rd, South Muskham Newark Lincolnshire NG23 6EA",
    "addr:postcode":"ng23 6ea",
    "addr:street":"Great North Rd",
    "iso:country":"GB",
    "sg:address":"Holly House, Great North Rd, South Muskham",
    "sg:city":"Newark",
    "sg:classifiers":[
        {
            "category":"Building & Trades",
            "subcategory":"Construction",
            "type":"Services"
        }
    ],
    "sg:phone":"+44 1636 613283",
    "sg:postcode":"NG23 6EA",
    "sg:province":"Lincolnshire",
    "sg:tags":[
        "builder"
    ],
    "wof:name":"Wells Groundworks",
    "wof:placetype":"venue"
},
  "geometry": {"coordinates":[-0.807319,53.168545],"type":"Point"}
}