{
  "type": "Feature",
  "properties": {
    "addr:full":"Crannafords Newton Abbot Devon TQ13 8DR",
    "addr:postcode":"tq13 8dr",
    "iso:country":"GB",
    "sg:address":"Crannafords",
    "sg:city":"Newton Abbot",
    "sg:classifiers":[
        {
            "category":"Communications",
            "type":"Services"
        }
    ],
    "sg:phone":"+44 1647 432700",
    "sg:postcode":"TQ13 8DR",
    "sg:province":"Devon",
    "sg:tags":[
        "audio-visual"
    ],
    "wof:name":"Post Sound Ltd.",
    "wof:placetype":"venue"
},
  "geometry": {"coordinates":[-3.787979,50.662338],"type":"Point"}
}