{
  "type": "Feature",
  "properties": {
    "addr:full":"The Power Ho, Roundwood Cardiff Caerphilly CF3 7PN",
    "addr:postcode":"cf3 7pn",
    "iso:country":"GB",
    "sg:address":"The Power Ho, Roundwood",
    "sg:city":"Cardiff",
    "sg:classifiers":[
        {
            "category":"Professional",
            "subcategory":"Lawyer & Legal Services",
            "type":"Services"
        }
    ],
    "sg:phone":"+44 29 2054 0202",
    "sg:postcode":"CF3 7PN",
    "sg:province":"Caerphilly",
    "sg:tags":[
        "advice",
        "counselling"
    ],
    "wof:name":"Citizens Advice Bureau",
    "wof:placetype":"venue"
},
  "geometry": {"coordinates":[-3.09191,51.533051],"type":"Point"}
}