{
  "type": "Feature",
  "properties": {
    "addr:full":"30 St Georges Terrace, Jesmond Newcastle Upon Tyne Tyne and Wear NE2 2SY",
    "addr:housenumber":"30",
    "addr:postcode":"ne2 2sy",
    "addr:street":"St Georges Terrace",
    "iso:country":"GB",
    "sg:address":"30 St Georges Terrace, Jesmond",
    "sg:city":"Newcastle Upon Tyne",
    "sg:classifiers":[
        {
            "category":"Food & Beverages",
            "subcategory":"Specialty",
            "type":"Retail Goods"
        },
        {
            "category":"Health Services",
            "subcategory":"Health Practitioner",
            "type":"Services"
        }
    ],
    "sg:phone":"+44 191 281 0670",
    "sg:postcode":"NE2 2SY",
    "sg:province":"Tyne and Wear",
    "sg:tags":[
        "psychologist",
        "retailer"
    ],
    "wof:name":"Alison Maclaren",
    "wof:placetype":"venue"
},
  "geometry": {"coordinates":[-1.6063640118,54.9917564392],"type":"Point"}
}