{
  "type": "Feature",
  "properties": {
    "addr:full":"13 Crown Walk Milton Keynes Buckinghamshire MK9 3AH",
    "addr:housenumber":"13",
    "addr:postcode":"mk9 3ah",
    "addr:street":"Crown Walk",
    "iso:country":"GB",
    "sg:address":"13 Crown Walk",
    "sg:city":"Milton Keynes",
    "sg:classifiers":[
        {
            "category":"Sports & Exercise",
            "subcategory":"Sports Center",
            "type":"Entertainment"
        }
    ],
    "sg:phone":"+44 1908 397657",
    "sg:postcode":"MK9 3AH",
    "sg:province":"Buckinghamshire",
    "sg:tags":[
        "shop",
        "good"
    ],
    "wof:name":"Allsports",
    "wof:placetype":"venue"
},
  "geometry": {"coordinates":[-0.754559,52.041355],"type":"Point"}
}