{
  "type": "Feature",
  "properties": {
    "iso:country":"GB",
    "sg:address":"59 Maytham Rd",
    "sg:city":"Cranbrook",
    "sg:classifiers":[
        {
            "category":"Autos & Motor Vehicles",
            "subcategory":"Automobile Sales",
            "type":"Retail Goods"
        }
    ],
    "sg:postcode":"TN17 4NT",
    "sg:province":"Kent",
    "sg:tags":[
        "car"
    ],
    "wof:name":"Hutson,H H,& Son",
    "wof:placetype":"venue"
},
  "geometry": {"coordinates":[0.657413,51.029694],"type":"Point"}
}