{
  "type": "Feature",
  "properties": {
    "addr:full":"406-408 Talbot Road Blackpool Lancashire FY3 7AY",
    "addr:housenumber":"406-408",
    "addr:postcode":"fy3 7ay",
    "addr:street":"Talbot Road",
    "iso:country":"GB",
    "sg:address":"406-408 Talbot Road",
    "sg:city":"Blackpool",
    "sg:classifiers":[
        {
            "category":"Shopping",
            "subcategory":"Thrift Store",
            "type":"Retail Goods"
        }
    ],
    "sg:phone":"+44 1253 301575",
    "sg:postcode":"FY3 7AY",
    "sg:province":"Lancashire",
    "sg:tags":[
        "shop",
        "charity"
    ],
    "wof:name":"The Salvation Army",
    "wof:placetype":"venue"
},
  "geometry": {"coordinates":[-3.0371329784,53.8263092041],"type":"Point"}
}