{
  "type": "Feature",
  "properties": {
    "iso:country":"GB",
    "sg:address":"Ddol Bont, Pentre Road, St Clears",
    "sg:city":"Carmarthen",
    "sg:classifiers":[
        {
            "category":"Communications",
            "type":"Services"
        }
    ],
    "sg:phone":"+44 1994 230548",
    "sg:postcode":"SA33 4AA",
    "sg:province":"Carmarthenshire",
    "sg:tags":[
        "tv",
        "video",
        "radio"
    ],
    "wof:name":"Ben Evans & Son (T V & Hi Fi) Ltd.",
    "wof:placetype":"venue"
},
  "geometry": {"coordinates":[-4.49709,51.819599],"type":"Point"}
}