{
  "type": "Feature",
  "properties": {
    "addr:full":"24a North Street Worthing West Sussex BN11 1DU",
    "addr:housenumber":"24a",
    "addr:postcode":"bn11 1du",
    "addr:street":"North Street",
    "iso:country":"GB",
    "sg:address":"24a North Street",
    "sg:city":"Worthing",
    "sg:classifiers":[
        {
            "category":"Fast Food",
            "type":"Food & Drink"
        }
    ],
    "sg:phone":"+44 1903 233133",
    "sg:postcode":"BN11 1DU",
    "sg:province":"West Sussex",
    "sg:tags":[
        "away",
        "take"
    ],
    "wof:name":"Texas Pizza",
    "wof:placetype":"venue"
},
  "geometry": {"coordinates":[-0.3705050051,50.81508255],"type":"Point"}
}