{
  "type": "Feature",
  "properties": {
    "addr:full":"Caves Farm, Pitney Langport Somerset TA10 9AL",
    "addr:housenumber":"langport",
    "addr:postcode":"ta10 9al",
    "iso:country":"GB",
    "sg:address":"Caves Farm, Pitney",
    "sg:city":"Langport",
    "sg:classifiers":[
        {
            "category":"Farming",
            "subcategory":"Dairy Farm",
            "type":"Manufacturing & Wholesale Goods"
        }
    ],
    "sg:phone":"+44 1458 250381",
    "sg:postcode":"TA10 9AL",
    "sg:province":"Somerset",
    "wof:name":"R J Cox & Son",
    "wof:placetype":"venue"
},
  "geometry": {"coordinates":[-2.824284,51.042049],"type":"Point"}
}