{
  "type": "Feature",
  "properties": {
    "addr:full":"63 Summerlands Avenue, Acton London Greater London W3 6EW",
    "addr:housenumber":"63",
    "addr:postcode":"w3 6ew",
    "addr:street":"Summerlands Avenue",
    "iso:country":"GB",
    "sg:address":"63 Summerlands Avenue, Acton",
    "sg:city":"London",
    "sg:classifiers":[
        {
            "category":"Health Services",
            "subcategory":"Dentist",
            "type":"Services"
        }
    ],
    "sg:phone":"+44 20 8993 2233",
    "sg:postcode":"W3 6EW",
    "sg:province":"Greater London",
    "wof:name":"Springfield Dental Surgery",
    "wof:placetype":"venue"
},
  "geometry": {"coordinates":[-0.271049,51.511162],"type":"Point"}
}