{
  "type": "Feature",
  "properties": {
    "iso:country":"GB",
    "sg:address":"29 Churchill Parade",
    "sg:city":"Sutton Coldfield",
    "sg:classifiers":[
        {
            "category":"Food & Beverages",
            "subcategory":"Fruits & Vegetables",
            "type":"Retail Goods"
        }
    ],
    "sg:phone":"+44 121 378 0764",
    "sg:postcode":"B75 7LD",
    "sg:province":"Staffordshire",
    "sg:tags":[
        "greengrocer"
    ],
    "wof:name":"D J Lewis",
    "wof:placetype":"venue"
},
  "geometry": {"coordinates":[-1.785852,52.563164],"type":"Point"}
}