{
  "type": "Feature",
  "properties": {
    "iso:country":"GB",
    "sg:address":"31 Wiltshire Way",
    "sg:city":"Westbury",
    "sg:classifiers":[
        {
            "category":"Building & Trades",
            "subcategory":"Construction",
            "type":"Services"
        }
    ],
    "sg:phone":"+44 1373 827965",
    "sg:postcode":"BA13 3XD",
    "sg:province":"Wiltshire",
    "sg:tags":[
        "decorator",
        "painter"
    ],
    "wof:name":"Kevin Austin & Co",
    "wof:placetype":"venue"
},
  "geometry": {"coordinates":[-2.181927,51.265961],"type":"Point"}
}