{
  "type": "Feature",
  "properties": {
    "iso:country":"GB",
    "sg:address":"Unit 2 Hybris Business Park, Warmwell Road",
    "sg:city":"Dorchester",
    "sg:classifiers":[
        {
            "category":"Autos & Motor Vehicles",
            "subcategory":"Boat Sales",
            "type":"Retail Goods"
        }
    ],
    "sg:phone":"+44 1305 854938",
    "sg:postcode":"DT2 8BF",
    "sg:province":"Dorset",
    "sg:tags":[
        "repair",
        "builder"
    ],
    "wof:name":"Golden Hind Marine",
    "wof:placetype":"venue"
},
  "geometry": {"coordinates":[-2.328774929,50.692691803],"type":"Point"}
}