{
  "type": "Feature",
  "properties": {
    "addr:full":"Unit 1 Hackers Close Nottingham Leicestershire NG13 8PU",
    "addr:housenumber":"unit 1",
    "addr:postcode":"ng13 8pu",
    "addr:street":"Hackers Close",
    "iso:country":"GB",
    "sg:address":"Unit 1 Hackers Close",
    "sg:city":"Nottingham",
    "sg:classifiers":[
        {
            "category":"Building & Trades",
            "subcategory":"Construction",
            "type":"Services"
        }
    ],
    "sg:phone":"+44 1949 20956",
    "sg:postcode":"NG13 8PU",
    "sg:province":"Leicestershire",
    "sg:tags":[
        "joinery"
    ],
    "wof:name":"Arch Joinery Services",
    "wof:placetype":"venue"
},
  "geometry": {"coordinates":[-0.9705539942,52.982711792],"type":"Point"}
}