{
  "type": "Feature",
  "properties": {
    "addr:full":"Meadside, Wood Lane, Gallows Tree Common Reading Berkshire RG4 9BD",
    "addr:postcode":"rg4 9bd",
    "addr:street":"Wood Lane Gallows Tree Common",
    "iso:country":"GB",
    "sg:address":"Meadside, Wood Lane, Gallows Tree Common",
    "sg:city":"Reading",
    "sg:classifiers":[
        {
            "category":"Home & Garden",
            "subcategory":"Building Materials",
            "type":"Retail Goods"
        }
    ],
    "sg:phone":"+44 1491 671212",
    "sg:postcode":"RG4 9BD",
    "sg:province":"Berkshire",
    "sg:tags":[
        "fencing"
    ],
    "wof:name":"Arrow Fencing & Playgrounds",
    "wof:placetype":"venue"
},
  "geometry": {"coordinates":[-1.0042229891,51.516708374],"type":"Point"}
}