{
  "type": "Feature",
  "properties": {
    "addr:full":"23 Central Parade, New Addington Croydon Surrey CR0 0JB",
    "addr:housenumber":"23",
    "addr:postcode":"cr0 0jb",
    "addr:street":"Central Parade",
    "iso:country":"GB",
    "sg:address":"23 Central Parade, New Addington",
    "sg:city":"Croydon",
    "sg:classifiers":[
        {
            "category":"Shopping",
            "subcategory":"Pharmacy",
            "type":"Retail Goods"
        }
    ],
    "sg:phone":"+44 1689 843261",
    "sg:postcode":"CR0 0JB",
    "sg:province":"Surrey",
    "sg:tags":[
        "store",
        "drug"
    ],
    "wof:name":"V G Drugstore",
    "wof:placetype":"venue"
},
  "geometry": {"coordinates":[-0.015201,51.341915],"type":"Point"}
}