{
  "type": "Feature",
  "properties": {
    "addr:full":"2 Henforth Cotts, St Martin Helston Cornwall TR12 6BX",
    "addr:housenumber":"2",
    "addr:postcode":"tr12 6bx",
    "addr:street":"Henforth Cotts St",
    "iso:country":"GB",
    "sg:address":"2 Henforth Cotts, St Martin",
    "sg:city":"Helston",
    "sg:classifiers":[
        {
            "category":"Utilities",
            "subcategory":"Fuel Oil & Lpg",
            "type":"Services"
        }
    ],
    "sg:postcode":"TR12 6BX",
    "sg:province":"Cornwall",
    "sg:tags":[
        "peat",
        "firewood",
        "logs"
    ],
    "wof:name":"Cornish Woodland Produce",
    "wof:placetype":"venue"
},
  "geometry": {"coordinates":[-5.1649599075,50.0783882141],"type":"Point"}
}