{
  "type": "Feature",
  "properties": {
    "addr:full":"42 Beverley Road Hull East Riding of Yorkshire HU3 1YE",
    "addr:housenumber":"42",
    "addr:postcode":"hu3 1ye",
    "addr:street":"Beverley Road",
    "iso:country":"GB",
    "sg:address":"42 Beverley Road",
    "sg:city":"Hull",
    "sg:classifiers":[
        {
            "category":"Insurance",
            "subcategory":"Insurance Agent",
            "type":"Services"
        }
    ],
    "sg:phone":"+44 1482 213215",
    "sg:postcode":"HU3 1YE",
    "sg:province":"East Riding of Yorkshire",
    "sg:tags":[
        "broker"
    ],
    "wof:name":"Insurance Partnership Services Ltd.",
    "wof:placetype":"venue"
},
  "geometry": {"coordinates":[-0.3474209905,53.7508735657],"type":"Point"}
}