{
  "type": "Feature",
  "properties": {
    "addr:full":"16 Victoria Terrace, Newbridge Newport Blaenau Gwent NP11 4ET",
    "addr:housenumber":"16",
    "addr:postcode":"np11 4et",
    "addr:street":"Victoria Terrace",
    "iso:country":"GB",
    "sg:address":"16 Victoria Terrace, Newbridge",
    "sg:city":"Newport",
    "sg:classifiers":[
        {
            "category":"Fast Food",
            "type":"Food & Drink"
        }
    ],
    "sg:phone":"+44 1495 249396",
    "sg:postcode":"NP11 4ET",
    "sg:province":"Blaenau Gwent",
    "sg:tags":[
        "away",
        "take"
    ],
    "wof:name":"Kebab & Pizza Parlour",
    "wof:placetype":"venue"
},
  "geometry": {"coordinates":[-3.144615,51.665581],"type":"Point"}
}