{
  "type": "Feature",
  "properties": {
    "addr:full":"Bronydd Isaf Farm, Llanllechid Bangor Gwynedd LL57 3LN",
    "addr:postcode":"ll57 3ln",
    "iso:country":"GB",
    "sg:address":"Bronydd Isaf Farm, Llanllechid",
    "sg:city":"Bangor",
    "sg:classifiers":[
        {
            "category":"Farming",
            "subcategory":"Farm",
            "type":"Manufacturing & Wholesale Goods"
        }
    ],
    "sg:postcode":"LL57 3LN",
    "sg:province":"Gwynedd",
    "sg:tags":[
        "mixed",
        "crop"
    ],
    "wof:name":"T W Davies",
    "wof:placetype":"venue"
},
  "geometry": {"coordinates":[-4.062954,53.196941],"type":"Point"}
}