{
  "type": "Feature",
  "properties": {
    "addr:full":"14 Swan Lane Norwich Norfolk NR15 2XN",
    "addr:housenumber":"14",
    "addr:postcode":"nr15 2xn",
    "addr:street":"Swan Lane",
    "iso:country":"GB",
    "sg:address":"14 Swan Lane",
    "sg:city":"Norwich",
    "sg:classifiers":[
        {
            "category":"Professional",
            "subcategory":"Art Services",
            "type":"Services"
        }
    ],
    "sg:phone":"+44 1508 530488",
    "sg:postcode":"NR15 2XN",
    "sg:province":"Norfolk",
    "sg:tags":[
        "framing"
    ],
    "wof:name":"Courthouse Occasions",
    "wof:placetype":"venue"
},
  "geometry": {"coordinates":[1.2338470221,52.4888191223],"type":"Point"}
}