{
  "type": "Feature",
  "properties": {
    "addr:full":"Howard Way Harlow Essex CM20 2SU",
    "addr:postcode":"cm20 2su",
    "addr:street":"Howard Way",
    "iso:country":"GB",
    "sg:address":"Howard Way",
    "sg:city":"Harlow",
    "sg:classifiers":[
        {
            "category":"Retail",
            "subcategory":"Storage",
            "type":"Services"
        }
    ],
    "sg:phone":"+44 1279 401550",
    "sg:postcode":"CM20 2SU",
    "sg:province":"Essex",
    "sg:tags":[
        "shelving",
        "system"
    ],
    "wof:name":"Gratnells Ltd.",
    "wof:placetype":"venue"
},
  "geometry": {"coordinates":[0.107917,51.782291],"type":"Point"}
}