{
  "type": "Feature",
  "properties": {
    "addr:full":"Betteras Hill Road, Hillam Leeds North Yorkshire LS25 5HB",
    "addr:postcode":"ls25 5hb",
    "addr:street":"Betteras Hill Road",
    "iso:country":"GB",
    "sg:address":"Betteras Hill Road, Hillam",
    "sg:city":"Leeds",
    "sg:classifiers":[
        {
            "category":"Utilities",
            "subcategory":"Refuse",
            "type":"Services"
        }
    ],
    "sg:phone":"+44 1977 682729",
    "sg:postcode":"LS25 5HB",
    "sg:province":"North Yorkshire",
    "sg:tags":[
        "disposal",
        "waste"
    ],
    "wof:name":"Earth Strip Waste Disposal & Tipping Ltd.",
    "wof:placetype":"venue"
},
  "geometry": {"coordinates":[-1.23259902,53.7534751892],"type":"Point"}
}