{
  "type": "Feature",
  "properties": {
    "addr:full":"382 Aston Lane, Witton Birmingham West Midlands B6 6QN",
    "addr:housenumber":"382",
    "addr:postcode":"b6 6qn",
    "addr:street":"Aston Lane",
    "iso:country":"GB",
    "sg:address":"382 Aston Lane, Witton",
    "sg:city":"Birmingham",
    "sg:classifiers":[
        {
            "category":"Shopping",
            "subcategory":"Pawn Shop",
            "type":"Retail Goods"
        }
    ],
    "sg:phone":"+44 121 356 0135",
    "sg:postcode":"B6 6QN",
    "sg:province":"West Midlands",
    "sg:tags":[
        "pawnbroker"
    ],
    "wof:name":"Uncles the Original Pawnbrokers",
    "wof:placetype":"venue"
},
  "geometry": {"coordinates":[-1.887758,52.51239],"type":"Point"}
}