{
  "type": "Feature",
  "properties": {
    "addr:full":"8 Barret Road, Cantley Doncaster South Yorkshire DN4 6JX",
    "addr:housenumber":"8",
    "addr:postcode":"dn4 6jx",
    "addr:street":"Barret Road",
    "iso:country":"GB",
    "sg:address":"8 Barret Road, Cantley",
    "sg:city":"Doncaster",
    "sg:classifiers":[
        {
            "category":"Building & Trades",
            "subcategory":"Construction",
            "type":"Services"
        }
    ],
    "sg:phone":"+44 1302 538266",
    "sg:postcode":"DN4 6JX",
    "sg:province":"South Yorkshire",
    "sg:tags":[
        "tiling",
        "contractor"
    ],
    "wof:name":"David Coleman Tiling",
    "wof:placetype":"venue"
},
  "geometry": {"coordinates":[-1.071753,53.513329],"type":"Point"}
}