{
  "type": "Feature",
  "properties": {
    "addr:full":"30 Brighton Road Worthing West Sussex BN11 3ED",
    "addr:housenumber":"30",
    "addr:postcode":"bn11 3ed",
    "addr:street":"Brighton Road",
    "iso:country":"GB",
    "sg:address":"30 Brighton Road",
    "sg:city":"Worthing",
    "sg:classifiers":[
        {
            "category":"Food & Beverages",
            "subcategory":"Bakery",
            "type":"Retail Goods"
        }
    ],
    "sg:phone":"+44 1903 235339",
    "sg:postcode":"BN11 3ED",
    "sg:province":"West Sussex",
    "sg:tags":[
        "baker"
    ],
    "wof:name":"Fish",
    "wof:placetype":"venue"
},
  "geometry": {"coordinates":[-0.3649249971,50.8119697571],"type":"Point"}
}