{
  "type": "Feature",
  "properties": {
    "addr:full":", Woolsery Bideford Devon EX39 5QS",
    "addr:postcode":"ex39 5qs",
    "iso:country":"GB",
    "sg:address":", Woolsery",
    "sg:city":"Bideford",
    "sg:classifiers":[
        {
            "category":"Bars & Pubs",
            "type":"Food & Drink"
        }
    ],
    "sg:phone":"+44 1237 431061",
    "sg:postcode":"EX39 5QS",
    "sg:province":"Devon",
    "sg:tags":[
        "pubs",
        "inn"
    ],
    "wof:name":"Manor Inn & Restaurant",
    "wof:placetype":"venue"
},
  "geometry": {"coordinates":[-4.378394,50.965759],"type":"Point"}
}