{
  "type": "Feature",
  "properties": {
    "addr:full":"Newpark Shops Pontyclun Bridgend CF72 8RH",
    "addr:postcode":"cf72 8rh",
    "addr:street":"Pontyclun",
    "iso:country":"GB",
    "sg:address":"Newpark Shops",
    "sg:city":"Pontyclun",
    "sg:classifiers":[
        {
            "category":"Autos & Motor Vehicles",
            "subcategory":"Fuel & Gas Station",
            "type":"Retail Goods"
        }
    ],
    "sg:phone":"+44 1443 226865",
    "sg:postcode":"CF72 8RH",
    "sg:province":"Bridgend",
    "sg:tags":[
        "petrol",
        "filling"
    ],
    "wof:name":"Tesco Petrol Filling Stations",
    "wof:placetype":"venue"
},
  "geometry": {"coordinates":[-3.373349,51.532742],"type":"Point"}
}