{
  "type": "Feature",
  "properties": {
    "addr:full":"17a Graham Street Edinburgh City of Edinburgh EH6 5QN",
    "addr:housenumber":"17a",
    "addr:postcode":"eh6 5qn",
    "addr:street":"Graham Street",
    "iso:country":"GB",
    "sg:address":"17a Graham Street",
    "sg:city":"Edinburgh",
    "sg:classifiers":[
        {
            "category":"Organizations",
            "subcategory":"Non-profit Organization",
            "type":"Services"
        }
    ],
    "sg:phone":"+44 131 555 5959",
    "sg:postcode":"EH6 5QN",
    "sg:province":"City of Edinburgh",
    "sg:tags":[
        "organisation",
        "voluntary",
        "charity"
    ],
    "wof:name":"Scottish Association for Mental Health",
    "wof:placetype":"venue"
},
  "geometry": {"coordinates":[-3.186009,55.97282],"type":"Point"}
}