{
  "type": "Feature",
  "properties": {
    "addr:full":"Greenlaw Mains Penicuik Midlothian EH26 0QG",
    "addr:postcode":"eh26 0qg",
    "iso:country":"GB",
    "sg:address":"Greenlaw Mains",
    "sg:city":"Penicuik",
    "sg:classifiers":[
        {
            "category":"Education",
            "subcategory":"University",
            "type":"Public Place"
        },
        {
            "category":"Government",
            "subcategory":"Office",
            "type":"Public Place"
        }
    ],
    "sg:phone":"+44 1968 673594",
    "sg:postcode":"EH26 0QG",
    "sg:province":"Midlothian",
    "sg:tags":[
        "local",
        "adult"
    ],
    "wof:name":"Carnethy Community Learning & Development Edcuatio",
    "wof:placetype":"venue"
},
  "geometry": {"coordinates":[-3.2108359337,55.8475227356],"type":"Point"}
}