{
  "type": "Feature",
  "properties": {
    "addr:full":"2 Rearsby Road Leicester Leicestershire LE4 6GZ",
    "addr:housenumber":"2",
    "addr:postcode":"le4 6gz",
    "addr:street":"Rearsby Road",
    "iso:country":"GB",
    "sg:address":"2 Rearsby Road",
    "sg:city":"Leicester",
    "sg:classifiers":[
        {
            "category":"Professional",
            "subcategory":"Accounting & Tax Preparation",
            "type":"Services"
        }
    ],
    "sg:phone":"+44 116 266 2584",
    "sg:postcode":"LE4 6GZ",
    "sg:province":"Leicestershire",
    "sg:tags":[
        "accountant",
        "activity"
    ],
    "wof:name":"Tanna & Tanna",
    "wof:placetype":"venue"
},
  "geometry": {"coordinates":[-1.1075600386,52.6519165039],"type":"Point"}
}