{
  "type": "Feature",
  "properties": {
    "addr:full":"Goytre Farm, Goytre Port Talbot Neath Port Talbot SA13 2YN",
    "addr:postcode":"sa13 2yn",
    "addr:street":"Goytre;Talbot",
    "iso:country":"GB",
    "sg:address":"Goytre Farm, Goytre",
    "sg:city":"Port Talbot",
    "sg:classifiers":[
        {
            "category":"Farming",
            "subcategory":"Livestock Farm",
            "type":"Manufacturing & Wholesale Goods"
        }
    ],
    "sg:phone":"+44 1639 884539",
    "sg:postcode":"SA13 2YN",
    "sg:province":"Neath Port Talbot",
    "sg:tags":[
        "others"
    ],
    "wof:name":"J N Wheaton",
    "wof:placetype":"venue"
},
  "geometry": {"coordinates":[-3.7553389072,51.5922660828],"type":"Point"}
}