{
  "type": "Feature",
  "properties": {
    "addr:full":"47 Kilmorie Road London Greater London SE23 2SS",
    "addr:housenumber":"47",
    "addr:postcode":"se23 2ss",
    "addr:street":"Kilmorie Road",
    "iso:country":"GB",
    "sg:address":"47 Kilmorie Road",
    "sg:city":"London",
    "sg:classifiers":[
        {
            "category":"Professional",
            "subcategory":"Engineering",
            "type":"Services"
        }
    ],
    "sg:postcode":"SE23 2SS",
    "sg:province":"Greater London",
    "sg:tags":[
        "contractor",
        "electrical",
        "engineer"
    ],
    "wof:name":"Glenn & Barrow Enterprises Ltd.",
    "wof:placetype":"venue"
},
  "geometry": {"coordinates":[-0.040860001,51.4404640198],"type":"Point"}
}