{
  "type": "Feature",
  "properties": {
    "addr:full":"Unit B25 Bolsover Business Park, Station Rd Chesterfield Derbyshire S44 6BB",
    "addr:housenumber":"b25",
    "addr:postcode":"s44 6bb",
    "addr:street":"Business Park Station Rd",
    "iso:country":"GB",
    "sg:address":"Unit B25 Bolsover Business Park, Station Rd",
    "sg:city":"Chesterfield",
    "sg:classifiers":[
        {
            "category":"Education",
            "subcategory":"Special Training",
            "type":"Public Place"
        }
    ],
    "sg:phone":"+44 1246 823400",
    "sg:postcode":"S44 6BB",
    "sg:province":"Derbyshire",
    "sg:tags":[
        "product",
        "centre"
    ],
    "wof:name":"Chase Ltd",
    "wof:placetype":"venue"
},
  "geometry": {"coordinates":[-1.31053,53.233204],"type":"Point"}
}