{
  "type": "Feature",
  "properties": {
    "iso:country":"GB",
    "sg:address":"30 Newgate Street",
    "sg:city":"Morpeth",
    "sg:classifiers":[
        {
            "category":"Shopping",
            "subcategory":"Clothing, Apparel, & Fashions",
            "type":"Retail Goods"
        }
    ],
    "sg:phone":"+44 1670 512344",
    "sg:postcode":"NE61 1BA",
    "sg:province":"Northumberland",
    "sg:tags":[
        "shop"
    ],
    "wof:name":"Tara",
    "wof:placetype":"venue"
},
  "geometry": {"coordinates":[-1.6904530525,55.1682739258],"type":"Point"}
}