{
  "type": "Feature",
  "properties": {
    "iso:country":"GB",
    "sg:address":"13-15 South Street, Dalkeith",
    "sg:city":"Edinburgh",
    "sg:classifiers":[
        {
            "category":"Shopping",
            "subcategory":"Clothing, Apparel, & Fashions",
            "type":"Retail Goods"
        }
    ],
    "sg:phone":"+44 131 663 4104",
    "sg:postcode":"EH22 1AH",
    "sg:province":"City of Edinburgh",
    "sg:tags":[
        "shop"
    ],
    "wof:name":"Gossip Clothing",
    "wof:placetype":"venue"
},
  "geometry": {"coordinates":[-3.069615,55.894028],"type":"Point"}
}