{
  "type": "Feature",
  "properties": {
    "addr:full":"86 Highbury Park London Greater London N5 2XE",
    "addr:housenumber":"86",
    "addr:postcode":"n5 2xe",
    "addr:street":"Highbury Park",
    "iso:country":"GB",
    "sg:address":"86 Highbury Park",
    "sg:city":"London",
    "sg:classifiers":[
        {
            "category":"Health Services",
            "subcategory":"Health Practitioner",
            "type":"Services"
        }
    ],
    "sg:postcode":"N5 2XE",
    "sg:province":"Greater London",
    "sg:tags":[
        "acupuncture"
    ],
    "wof:name":"Philippa Bartlett",
    "wof:placetype":"venue"
},
  "geometry": {"coordinates":[-0.0979610011,51.5573730469],"type":"Point"}
}