{
  "type": "Feature",
  "properties": {
    "addr:full":"2 Park Street, Saltisford Warwick Warwickshire CV34 4TR",
    "addr:housenumber":"2",
    "addr:postcode":"cv34 4tr",
    "addr:street":"Park Street Saltisford",
    "iso:country":"GB",
    "sg:address":"2 Park Street, Saltisford",
    "sg:city":"Warwick",
    "sg:classifiers":[
        {
            "category":"Food & Beverages",
            "subcategory":"Supermarket",
            "type":"Retail Goods"
        }
    ],
    "sg:phone":"+44 1926 493449",
    "sg:postcode":"CV34 4TR",
    "sg:province":"Warwickshire",
    "wof:name":"J Sainsbury",
    "wof:placetype":"venue"
},
  "geometry": {"coordinates":[-1.592593,52.284241],"type":"Point"}
}