{
  "type": "Feature",
  "properties": {
    "addr:full":"25 Harley Street West End Hampshire W1N 2BR",
    "addr:housenumber":"25",
    "addr:street":"Harley Street",
    "iso:country":"GB",
    "sg:address":"25 Harley Street",
    "sg:city":"West End",
    "sg:classifiers":[
        {
            "category":"Professional",
            "subcategory":"Management & Consulting",
            "type":"Services"
        }
    ],
    "sg:postcode":"W1N 2BR",
    "sg:province":"Hampshire",
    "sg:tags":[
        "consultant",
        "business"
    ],
    "wof:name":"John Moore Consultants Ltd",
    "wof:placetype":"venue"
},
  "geometry": {"coordinates":[-0.1389899999,51.5075798035],"type":"Point"}
}