{
  "type": "Feature",
  "properties": {
    "addr:full":"Bank Street, Bishops Waltham Southampton Hampshire SO32 1AN",
    "addr:postcode":"so32 1an",
    "addr:street":"Bank Street",
    "iso:country":"GB",
    "sg:address":"Bank Street, Bishops Waltham",
    "sg:city":"Southampton",
    "sg:classifiers":[
        {
            "category":"Fast Food",
            "type":"Food & Drink"
        },
        {
            "category":"Restaurant",
            "type":"Food & Drink"
        }
    ],
    "sg:phone":"+44 1489 894684",
    "sg:postcode":"SO32 1AN",
    "sg:province":"Hampshire",
    "sg:tags":[
        "away",
        "indian",
        "take"
    ],
    "wof:name":"Waltham Tandoori Restaurant",
    "wof:placetype":"venue"
},
  "geometry": {"coordinates":[-1.2120419741,50.9547996521],"type":"Point"}
}