{
  "type": "Feature",
  "properties": {
    "iso:country":"GB",
    "sg:address":"Slaters Building, Skates Hill",
    "sg:city":"Sudbury",
    "sg:classifiers":[
        {
            "category":"Retail",
            "subcategory":"Auto Repair",
            "type":"Services"
        }
    ],
    "sg:phone":"+44 1787 280288",
    "sg:postcode":"CO10 7QT",
    "sg:province":"Essex",
    "sg:tags":[
        "modification",
        "garage"
    ],
    "wof:name":"Suffolk Automotive Servicing",
    "wof:placetype":"venue"
},
  "geometry": {"coordinates":[0.73439,52.038605],"type":"Point"}
}