{
  "type": "Feature",
  "properties": {
    "addr:full":"Ibex House, 61-65 Baker Street Weybridge Surrey KT13 8AH",
    "addr:housenumber":"61-65",
    "addr:postcode":"kt13 8ah",
    "addr:street":"Baker Street",
    "iso:country":"GB",
    "sg:address":"Ibex House, 61-65 Baker Street",
    "sg:city":"Weybridge",
    "sg:classifiers":[
        {
            "category":"Professional",
            "subcategory":"Accounting & Tax Preparation",
            "type":"Services"
        }
    ],
    "sg:phone":"+44 1932 853393",
    "sg:postcode":"KT13 8AH",
    "sg:province":"Surrey",
    "sg:tags":[
        "accountant",
        "activity"
    ],
    "sg:website":"http://www.midsnell.co.uk",
    "wof:name":"M G I Midgley Snelling Ltd.",
    "wof:placetype":"venue"
},
  "geometry": {"coordinates":[-0.45622,51.371845],"type":"Point"}
}