{
  "type": "Feature",
  "properties": {
    "addr:full":"55 Riding House Street London Greater London W1W 7EE",
    "addr:housenumber":"55",
    "addr:postcode":"w1w 7ee",
    "addr:street":"Riding House Street",
    "iso:country":"GB",
    "sg:address":"55 Riding House Street",
    "sg:city":"London",
    "sg:classifiers":[
        {
            "category":"Professional",
            "subcategory":"Advertising",
            "type":"Services"
        }
    ],
    "sg:phone":"+44 20 7631 8430",
    "sg:postcode":"W1W 7EE",
    "sg:province":"Greater London",
    "sg:tags":[
        "agency"
    ],
    "wof:name":"K B W Ltd.",
    "wof:placetype":"venue"
},
  "geometry": {"coordinates":[-0.139685,51.519154],"type":"Point"}
}