{
  "type": "Feature",
  "properties": {
    "addr:full":"Ashes Lane, Hadlow Tonbridge Kent TN11 0AN",
    "addr:postcode":"tn11 0an",
    "addr:street":"Ashes Lane",
    "iso:country":"GB",
    "sg:address":"Ashes Lane, Hadlow",
    "sg:city":"Tonbridge",
    "sg:classifiers":[
        {
            "category":"Farming",
            "subcategory":"Livestock Farm",
            "type":"Manufacturing & Wholesale Goods"
        }
    ],
    "sg:phone":"+44 1732 850301",
    "sg:postcode":"TN11 0AN",
    "sg:province":"Kent",
    "sg:tags":[
        "others"
    ],
    "wof:name":"Faulkners Farm",
    "wof:placetype":"venue"
},
  "geometry": {"coordinates":[0.321759,51.222103],"type":"Point"}
}