{
  "type": "Feature",
  "properties": {
    "iso:country":"GB",
    "sg:address":"343 Station Road",
    "sg:city":"Harrow",
    "sg:classifiers":[
        {
            "category":"Shopping",
            "subcategory":"Clothing, Apparel, & Fashions",
            "type":"Retail Goods"
        }
    ],
    "sg:phone":"+44 20 8426 0079",
    "sg:postcode":"HA1 2AA",
    "sg:province":"Greater London",
    "sg:tags":[
        "menswear"
    ],
    "wof:name":"The Eye",
    "wof:placetype":"venue"
},
  "geometry": {"coordinates":[-0.334262,51.580406],"type":"Point"}
}