{
  "type": "Feature",
  "properties": {
    "addr:full":"Unit F Tyneside Retail Park, Coast Road, Silverlink Wallsend Tyne and Wear NE28 9ND",
    "addr:postcode":"ne28 9nd",
    "addr:street":"Retail Park Coast Road Silverlink",
    "iso:country":"GB",
    "sg:address":"Unit F Tyneside Retail Park, Coast Road, Silverlink",
    "sg:city":"Wallsend",
    "sg:classifiers":[
        {
            "category":"Home & Garden",
            "subcategory":"Carpets & Floor Coverings",
            "type":"Retail Goods"
        }
    ],
    "sg:phone":"+44 191 262 2145",
    "sg:postcode":"NE28 9ND",
    "sg:province":"Tyne and Wear",
    "sg:tags":[
        "carpets",
        "retailer",
        "rug",
        "matting"
    ],
    "wof:name":"Storey Carpets Ltd.",
    "wof:placetype":"venue"
},
  "geometry": {"coordinates":[-1.4955099821,55.01171875],"type":"Point"}
}