{
  "type": "Feature",
  "properties": {
    "addr:full":"31a St Pauls Avenue, Willesden Green London Greater London NW2 5SS",
    "addr:housenumber":"31a",
    "addr:postcode":"nw2 5ss",
    "addr:street":"St Pauls Avenue",
    "iso:country":"GB",
    "sg:address":"31a St Pauls Avenue, Willesden Green",
    "sg:city":"London",
    "sg:classifiers":[
        {
            "category":"Organizations",
            "subcategory":"Membership Organization",
            "type":"Services"
        }
    ],
    "sg:postcode":"NW2 5SS",
    "sg:province":"Greater London",
    "sg:tags":[
        "club"
    ],
    "wof:name":"Wotalotigot Management Ltd",
    "wof:placetype":"venue"
},
  "geometry": {"coordinates":[-0.224143,51.549168],"type":"Point"}
}