{
  "type": "Feature",
  "properties": {
    "iso:country":"GB",
    "sg:address":"4 High Street",
    "sg:city":"Huntingdon",
    "sg:classifiers":[
        {
            "category":"Professional",
            "type":"Services"
        }
    ],
    "sg:phone":"+44 1480 386034",
    "sg:postcode":"PE29 3TE",
    "sg:province":"Cambridgeshire",
    "sg:tags":[
        "entertainer"
    ],
    "wof:name":"Cromwell Management Entertainment Agency",
    "wof:placetype":"venue"
},
  "geometry": {"coordinates":[-0.17946,52.328018],"type":"Point"}
}