{
  "type": "Feature",
  "properties": {
    "addr:full":"66 Hillcrest Sunderland Tyne and Wear SR3 3NN",
    "addr:housenumber":"66",
    "addr:postcode":"sr3 3nn",
    "addr:street":"Hillcrest",
    "iso:country":"GB",
    "sg:address":"66 Hillcrest",
    "sg:city":"Sunderland",
    "sg:classifiers":[
        {
            "category":"Social Services",
            "subcategory":"Retirement Home",
            "type":"Services"
        }
    ],
    "sg:postcode":"SR3 3NN",
    "sg:province":"Tyne and Wear",
    "sg:tags":[
        "care"
    ],
    "wof:name":"Eldercare",
    "wof:placetype":"venue"
},
  "geometry": {"coordinates":[-1.439828,54.876068],"type":"Point"}
}