{
  "type": "Feature",
  "properties": {
    "iso:country":"GB",
    "sg:address":"102 Shalloak Road",
    "sg:city":"Canterbury",
    "sg:classifiers":[
        {
            "category":"Communications",
            "type":"Services"
        }
    ],
    "sg:postcode":"CT2 0QH",
    "sg:province":"Kent",
    "sg:tags":[
        "tv",
        "video",
        "radio"
    ],
    "wof:name":"Don's T V Service",
    "wof:placetype":"venue"
},
  "geometry": {"coordinates":[1.108545,51.310841],"type":"Point"}
}