{
  "type": "Feature",
  "properties": {
    "iso:country":"GB",
    "sg:address":"Unit 6/8, Crombie Road, Torry",
    "sg:city":"Aberdeen",
    "sg:classifiers":[
        {
            "category":"Retail",
            "subcategory":"Laundry & Dry Cleaning",
            "type":"Services"
        }
    ],
    "sg:phone":"+44 1224 877405",
    "sg:postcode":"AB11 9QQ",
    "sg:province":"Aberdeen City",
    "sg:tags":[
        "cleaner",
        "launderette"
    ],
    "wof:name":"Silver City Cleaners Ltd.",
    "wof:placetype":"venue"
},
  "geometry": {"coordinates":[-2.0865859985,57.1375732422],"type":"Point"}
}