{
  "type": "Feature",
  "properties": {
    "iso:country":"GB",
    "sg:address":"Robins Road, Chasetown Industrial Estate",
    "sg:city":"Burntwood",
    "sg:classifiers":[
        {
            "category":"Home & Garden",
            "subcategory":"Hardware",
            "type":"Retail Goods"
        }
    ],
    "sg:phone":"+44 1543 676101",
    "sg:postcode":"WS7 8XS",
    "sg:province":"Staffordshire",
    "sg:tags":[
        "compressor",
        "air"
    ],
    "wof:name":"Atlas Copco Compressors Ltd.",
    "wof:placetype":"venue"
},
  "geometry": {"coordinates":[-1.9395539761,52.6792259216],"type":"Point"}
}