{
  "type": "Feature",
  "properties": {
    "addr:full":"3 St Pauls Square Perth Perth and Kinross PH1 5QW",
    "addr:housenumber":"3",
    "addr:postcode":"ph1 5qw",
    "addr:street":"St Pauls Square",
    "iso:country":"GB",
    "sg:address":"3 St Pauls Square",
    "sg:city":"Perth",
    "sg:classifiers":[
        {
            "category":"Communications",
            "subcategory":"Newspaper",
            "type":"Services"
        },
        {
            "category":"Wholesale",
            "subcategory":"Books, Periodicals, & Newspapers",
            "type":"Manufacturing & Wholesale Goods"
        }
    ],
    "sg:phone":"+44 1738 446766",
    "sg:postcode":"PH1 5QW",
    "sg:province":"Perth and Kinross",
    "sg:tags":[
        "magazine",
        "publishing"
    ],
    "wof:name":"Premier News & Sport",
    "wof:placetype":"venue"
},
  "geometry": {"coordinates":[-3.4352838993,56.3966560364],"type":"Point"}
}