{
  "type": "Feature",
  "properties": {
    "addr:full":"141 Garth Road Morden Surrey SM4 4LF",
    "addr:housenumber":"141",
    "addr:postcode":"sm4 4lf",
    "addr:street":"Garth Road",
    "iso:country":"GB",
    "sg:address":"141 Garth Road",
    "sg:city":"Morden",
    "sg:classifiers":[
        {
            "category":"Banks & Credit Unions",
            "subcategory":"Financial Services",
            "type":"Services"
        }
    ],
    "sg:postcode":"SM4 4LF",
    "sg:province":"Surrey",
    "sg:tags":[
        "claim",
        "assessor"
    ],
    "wof:name":"Donald Malcolm Beaumont",
    "wof:placetype":"venue"
},
  "geometry": {"coordinates":[-0.2244099975,51.3836021423],"type":"Point"}
}