{
  "type": "Feature",
  "properties": {
    "addr:full":"Mardleybury Farm, Mardleybury Rd, Datchworth Knebworth Hertfordshire SG3 6SG",
    "addr:postcode":"sg3 6sg",
    "addr:street":"Mardleybury Rd",
    "iso:country":"GB",
    "sg:address":"Mardleybury Farm, Mardleybury Rd, Datchworth",
    "sg:city":"Knebworth",
    "sg:classifiers":[
        {
            "category":"Building & Trades",
            "subcategory":"Construction",
            "type":"Services"
        }
    ],
    "sg:phone":"+44 1438 815885",
    "sg:postcode":"SG3 6SG",
    "sg:province":"Hertfordshire",
    "sg:tags":[
        "joiner",
        "carpenter"
    ],
    "wof:name":"Timber Crafts",
    "wof:placetype":"venue"
},
  "geometry": {"coordinates":[-0.1835030019,51.8660774231],"type":"Point"}
}