{
  "type": "Feature",
  "properties": {
    "iso:country":"GB",
    "sg:address":"K & K House, Station Approach, Rickmansworth Rd",
    "sg:city":"Watford",
    "sg:classifiers":[
        {
            "category":"Professional",
            "subcategory":"Detective & Security Services",
            "type":"Services"
        }
    ],
    "sg:phone":"+44 1923 479200",
    "sg:postcode":"WD1 7LR",
    "sg:province":"Hertfordshire",
    "sg:tags":[
        "car"
    ],
    "wof:name":"Cobra Alarms",
    "wof:placetype":"venue"
},
  "geometry": {"coordinates":[-0.403473,51.658478],"type":"Point"}
}