{
  "type": "Feature",
  "properties": {
    "iso:country":"GB",
    "sg:address":"127 Marlene Croft",
    "sg:city":"Birmingham",
    "sg:classifiers":[
        {
            "category":"Home & Garden",
            "subcategory":"Home Furnishings",
            "type":"Retail Goods"
        }
    ],
    "sg:phone":"+44 121 770 4861",
    "sg:postcode":"B37 7JL",
    "sg:province":"West Midlands",
    "sg:tags":[
        "furnishers",
        "planner",
        "kitchen"
    ],
    "wof:name":"D A Hynes",
    "wof:placetype":"venue"
},
  "geometry": {"coordinates":[-1.72848,52.473701],"type":"Point"}
}