{
  "type": "Feature",
  "properties": {
    "iso:country":"GB",
    "sg:address":"22 Lanehead Road",
    "sg:city":"Stoke-on-trent",
    "sg:classifiers":[
        {
            "category":"Home & Garden",
            "subcategory":"Carpets & Floor Coverings",
            "type":"Retail Goods"
        }
    ],
    "sg:postcode":"ST1 5PT",
    "sg:province":"Staffordshire",
    "sg:tags":[
        "cleaner",
        "upholstery"
    ],
    "wof:name":"Fabriclean Group Ltd.",
    "wof:placetype":"venue"
},
  "geometry": {"coordinates":[-2.197093,53.021355],"type":"Point"}
}