{
  "type": "Feature",
  "properties": {
    "addr:full":"17 Cemetery Road Grimsby Lincolnshire DN37 7EP",
    "addr:housenumber":"17",
    "addr:postcode":"dn37 7ep",
    "addr:street":"Cemetery Road",
    "iso:country":"GB",
    "sg:address":"17 Cemetery Road",
    "sg:city":"Grimsby",
    "sg:classifiers":[
        {
            "category":"Building & Trades",
            "subcategory":"Plumbing",
            "type":"Services"
        }
    ],
    "sg:postcode":"DN37 7EP",
    "sg:province":"Lincolnshire",
    "sg:tags":[
        "heating"
    ],
    "wof:name":"Raymond S Francis",
    "wof:placetype":"venue"
},
  "geometry": {"coordinates":[-0.170414,53.541027],"type":"Point"}
}