{
  "type": "Feature",
  "properties": {
    "iso:country":"GB",
    "sg:address":"176 Station Road, Balsall Common",
    "sg:city":"Coventry",
    "sg:classifiers":[
        {
            "category":"Fast Food",
            "type":"Food & Drink"
        }
    ],
    "sg:postcode":"CV7 7FD",
    "sg:province":"Warwickshire",
    "sg:tags":[
        "away",
        "take"
    ],
    "wof:name":"Oriental Express",
    "wof:placetype":"venue"
},
  "geometry": {"coordinates":[-1.649338,52.391861],"type":"Point"}
}