{
  "type": "Feature",
  "properties": {
    "iso:country":"GB",
    "sg:address":"12 Blackmoor Close",
    "sg:city":"Ascot",
    "sg:classifiers":[
        {
            "category":"Building & Trades",
            "subcategory":"Construction",
            "type":"Services"
        }
    ],
    "sg:phone":"+44 1344 882946",
    "sg:postcode":"SL5 8EU",
    "sg:province":"Berkshire",
    "sg:tags":[
        "dry",
        "plastering",
        "plasterers",
        "lining",
        "related",
        "screeders"
    ],
    "wof:name":"Allen Plastering",
    "wof:placetype":"venue"
},
  "geometry": {"coordinates":[-0.695703,51.415531],"type":"Point"}
}