{
  "type": "Feature",
  "properties": {
    "addr:full":"250-252 Commercial Road Portsmouth Hampshire PO1 1HH",
    "addr:housenumber":"250-252",
    "addr:postcode":"hampshire po1 1hh",
    "addr:street":"Commercial Road",
    "iso:country":"GB",
    "sg:address":"250-252 Commercial Road",
    "sg:city":"Portsmouth",
    "sg:classifiers":[
        {
            "category":"Fast Food",
            "type":"Food & Drink"
        }
    ],
    "sg:phone":"+44 23 9229 7273",
    "sg:postcode":"PO1 1HH",
    "sg:province":"Hampshire",
    "sg:tags":[
        "away",
        "take"
    ],
    "wof:name":"K F C",
    "wof:placetype":"venue"
},
  "geometry": {"coordinates":[-1.088019,50.802238],"type":"Point"}
}