{
  "type": "Feature",
  "properties": {
    "addr:full":"Cherry Tree Cottage, Newpound, Wisborough Grn Billingshurst West Sussex RH14 0EJ",
    "addr:postcode":"rh14 0ej",
    "addr:street":"Newpound Wisborough Grn",
    "iso:country":"GB",
    "sg:address":"Cherry Tree Cottage, Newpound, Wisborough Grn",
    "sg:city":"Billingshurst",
    "sg:classifiers":[
        {
            "category":"Manufacturing",
            "subcategory":"Glass & Minerals",
            "type":"Manufacturing & Wholesale Goods"
        }
    ],
    "sg:postcode":"RH14 0EJ",
    "sg:province":"West Sussex",
    "sg:tags":[
        "product"
    ],
    "wof:name":"Coombes,Becky,",
    "wof:placetype":"venue"
},
  "geometry": {"coordinates":[-0.4524280131,51.0211830139],"type":"Point"}
}