{
  "type": "Feature",
  "properties": {
    "iso:country":"GB",
    "sg:address":"38 Lime Gardens, West End",
    "sg:city":"Southampton",
    "sg:classifiers":[
        {
            "category":"Professional",
            "type":"Services"
        }
    ],
    "sg:postcode":"SO30 3RG",
    "sg:province":"Hampshire",
    "sg:tags":[
        "interior",
        "furnishers",
        "designer"
    ],
    "wof:name":"Maycroft Design",
    "wof:placetype":"venue"
},
  "geometry": {"coordinates":[-1.3367500305,50.9333305359],"type":"Point"}
}