{
  "type": "Feature",
  "properties": {
    "iso:country":"GB",
    "sg:address":"42 Edison Road, Rabans Lane Industrial Estate",
    "sg:city":"Aylesbury",
    "sg:classifiers":[
        {
            "category":"Wholesale",
            "subcategory":"Furniture",
            "type":"Manufacturing & Wholesale Goods"
        }
    ],
    "sg:phone":"+44 870 330 7961",
    "sg:postcode":"HP19 8TE",
    "sg:province":"Buckinghamshire",
    "sg:tags":[
        "shop",
        "fitting"
    ],
    "wof:name":"Lift (U K) Ltd.",
    "wof:placetype":"venue"
},
  "geometry": {"coordinates":[-0.8507500291,51.8222312927],"type":"Point"}
}