{
  "type": "Feature",
  "properties": {
    "addr:full":"72 Milton Road Kirkcaldy Fife KY1 1TP",
    "addr:housenumber":"72",
    "addr:postcode":"ky1 1tp",
    "addr:street":"Milton Road",
    "iso:country":"GB",
    "sg:address":"72 Milton Road",
    "sg:city":"Kirkcaldy",
    "sg:classifiers":[
        {
            "category":"Health Services",
            "subcategory":"Nursing And Care Facility",
            "type":"Services"
        }
    ],
    "sg:postcode":"KY1 1TP",
    "sg:province":"Fife",
    "sg:tags":[
        "home"
    ],
    "wof:name":"Abbotsford Nursing Home",
    "wof:placetype":"venue"
},
  "geometry": {"coordinates":[-3.166861,56.103954],"type":"Point"}
}