{
  "type": "Feature",
  "properties": {
    "addr:full":"11 St.winifreds Rd Bournemouth Dorset BH2 6NY",
    "addr:housenumber":"11",
    "addr:postcode":"bh2 6ny",
    "addr:street":"St.Winifreds Rd",
    "iso:country":"GB",
    "sg:address":"11 St.winifreds Rd",
    "sg:city":"Bournemouth",
    "sg:classifiers":[
        {
            "category":"Social Services",
            "subcategory":"Retirement Home",
            "type":"Services"
        }
    ],
    "sg:phone":"+44 1202 291120",
    "sg:postcode":"BH2 6NY",
    "sg:province":"Dorset",
    "sg:tags":[
        "rest"
    ],
    "wof:name":"St.Winifreds",
    "wof:placetype":"venue"
},
  "geometry": {"coordinates":[-1.877096,50.730324],"type":"Point"}
}