{
  "type": "Feature",
  "properties": {
    "addr:full":"Enterprise Way Evesham Gloucestershire WR11 1GS",
    "addr:postcode":"wr11 1gs",
    "addr:street":"Enterprise Way",
    "iso:country":"GB",
    "sg:address":"Enterprise Way",
    "sg:city":"Evesham",
    "sg:classifiers":[
        {
            "category":"Autos & Motor Vehicles",
            "subcategory":"Auto Supplies",
            "type":"Retail Goods"
        }
    ],
    "sg:phone":"+44 1386 760600",
    "sg:postcode":"WR11 1GS",
    "sg:province":"Gloucestershire",
    "sg:tags":[
        "tyre"
    ],
    "wof:name":"Rapid Fit",
    "wof:placetype":"venue"
},
  "geometry": {"coordinates":[-1.9340039492,52.0715560913],"type":"Point"}
}