{
  "type": "Feature",
  "properties": {
    "addr:full":"Exhibition Way Exeter Devon EX4 8HZ",
    "addr:postcode":"ex4 8hz",
    "addr:street":"Exhibition Way",
    "iso:country":"GB",
    "sg:address":"Exhibition Way",
    "sg:city":"Exeter",
    "sg:classifiers":[
        {
            "category":"Farming",
            "subcategory":"Dairy Farm",
            "type":"Manufacturing & Wholesale Goods"
        }
    ],
    "sg:phone":"+44 1392 466123",
    "sg:postcode":"EX4 8HZ",
    "sg:province":"Devon",
    "wof:name":"Wessex Dairies Ltd.",
    "wof:placetype":"venue"
},
  "geometry": {"coordinates":[-3.4830970764,50.7368774414],"type":"Point"}
}