{
  "type": "Feature",
  "properties": {
    "iso:country":"GB",
    "sg:address":"Unit 2 147 Ansley Common",
    "sg:city":"Nuneaton",
    "sg:classifiers":[
        {
            "category":"Shopping",
            "type":"Retail Goods"
        }
    ],
    "sg:phone":"+44 24 7639 6622",
    "sg:postcode":"CV10 0PR",
    "sg:province":"Leicestershire",
    "sg:tags":[
        "part",
        "accessory"
    ],
    "wof:name":"Nu-line Components",
    "wof:placetype":"venue"
},
  "geometry": {"coordinates":[-1.529579,52.537121],"type":"Point"}
}