{
  "type": "Feature",
  "properties": {
    "iso:country":"GB",
    "sg:address":"Po Box 4",
    "sg:city":"Richmond",
    "sg:classifiers":[
        {
            "category":"Banks & Credit Unions",
            "subcategory":"Financial Services",
            "type":"Services"
        }
    ],
    "sg:phone":"+44 20 8940 9835",
    "sg:postcode":"TW9 1PS",
    "sg:province":"Greater London",
    "sg:tags":[
        "consultant"
    ],
    "wof:name":"Richmond Investments Ltd.",
    "wof:placetype":"venue"
},
  "geometry": {"coordinates":[-0.300726,51.461319],"type":"Point"}
}