{
  "type": "Feature",
  "properties": {
    "iso:country":"GB",
    "sg:address":"7 Newport Drive",
    "sg:city":"Alcester",
    "sg:classifiers":[
        {
            "category":"Utilities",
            "subcategory":"Refuse",
            "type":"Services"
        }
    ],
    "sg:postcode":"B49 5BL",
    "sg:province":"Warwickshire",
    "sg:tags":[
        "skip",
        "hire"
    ],
    "wof:name":"Sutors Skip Hire",
    "wof:placetype":"venue"
},
  "geometry": {"coordinates":[-1.875488,52.211853],"type":"Point"}
}