{
  "type": "Feature",
  "properties": {
    "addr:full":"14 Moira Terrace Cardiff Cardiff CF24 0EJ",
    "addr:housenumber":"14",
    "addr:postcode":"cf24 0ej",
    "addr:street":"Moira Terrace",
    "iso:country":"GB",
    "sg:address":"14 Moira Terrace",
    "sg:city":"Cardiff",
    "sg:classifiers":[
        {
            "category":"Professional",
            "subcategory":"Lawyer & Legal Services",
            "type":"Services"
        }
    ],
    "sg:phone":"+44 29 2048 6909",
    "sg:postcode":"CF24 0EJ",
    "sg:province":"Cardiff",
    "sg:tags":[
        "solicitor"
    ],
    "wof:name":"Jim Conod",
    "wof:placetype":"venue"
},
  "geometry": {"coordinates":[-3.1623439789,51.4817886353],"type":"Point"}
}