{
  "type": "Feature",
  "properties": {
    "iso:country":"GB",
    "sg:address":"270 Kirkdale",
    "sg:city":"London",
    "sg:classifiers":[
        {
            "category":"Shopping",
            "subcategory":"Thrift Store",
            "type":"Retail Goods"
        }
    ],
    "sg:phone":"+44 20 8676 8262",
    "sg:postcode":"SE26 4RS",
    "sg:province":"Greater London",
    "sg:tags":[
        "shop",
        "charity"
    ],
    "wof:name":"St. Christophers Charity Shop",
    "wof:placetype":"venue"
},
  "geometry": {"coordinates":[-0.056332,51.427181],"type":"Point"}
}