{
  "type": "Feature",
  "properties": {
    "iso:country":"GB",
    "sg:address":"11 Bourne Rd",
    "sg:city":"Bexley",
    "sg:classifiers":[
        {
            "category":"Health Services",
            "subcategory":"Dentist",
            "type":"Services"
        }
    ],
    "sg:phone":"+44 1322 558548",
    "sg:postcode":"DA5 1LW",
    "sg:province":"Kent",
    "wof:name":"Donnelly S",
    "wof:placetype":"venue"
},
  "geometry": {"coordinates":[0.151013,51.442593],"type":"Point"}
}