{
  "type": "Feature",
  "properties": {
    "iso:country":"GB",
    "sg:address":"C/o Lawrence Jones, 20 Upper Ground",
    "sg:city":"London",
    "sg:classifiers":[
        {
            "category":"Shopping",
            "subcategory":"Department Store",
            "type":"Retail Goods"
        }
    ],
    "sg:postcode":"SE1 9LH",
    "sg:province":"Greater London",
    "wof:name":"Casareen Retail International Ltd",
    "wof:placetype":"venue"
},
  "geometry": {"coordinates":[-0.10691,51.508362],"type":"Point"}
}