{
  "type": "Feature",
  "properties": {
    "iso:country":"GB",
    "sg:address":"7-11 Lionel Street",
    "sg:city":"St Helens",
    "sg:classifiers":[
        {
            "category":"Building & Trades",
            "subcategory":"Construction",
            "type":"Services"
        }
    ],
    "sg:postcode":"WA9 4JN",
    "sg:province":"Cheshire",
    "sg:tags":[
        "decorator",
        "painter"
    ],
    "wof:name":"St. Helens Paint Stripping Services",
    "wof:placetype":"venue"
},
  "geometry": {"coordinates":[-2.699368,53.432762],"type":"Point"}
}