{
  "type": "Feature",
  "properties": {
    "addr:full":"Tall Trees Hotel, Worsall Road, Kirklevington Yarm North Yorkshire TS15 9PE",
    "addr:postcode":"ts15 9pe",
    "addr:street":"Worsall Road",
    "iso:country":"GB",
    "sg:address":"Tall Trees Hotel, Worsall Road, Kirklevington",
    "sg:city":"Yarm",
    "sg:classifiers":[
        {
            "category":"Sports & Exercise",
            "subcategory":"Gym",
            "type":"Entertainment"
        }
    ],
    "sg:phone":"+44 1642 785440",
    "sg:postcode":"TS15 9PE",
    "sg:province":"North Yorkshire",
    "sg:tags":[
        "fitness",
        "health",
        "centre"
    ],
    "wof:name":"The Works Body & Skincare Clinic",
    "wof:placetype":"venue"
},
  "geometry": {"coordinates":[-1.354144,54.508636],"type":"Point"}
}