{
  "type": "Feature",
  "properties": {
    "addr:full":"Hobbs Cross Road Harlow Essex CM17 0LB",
    "addr:postcode":"cm17 0lb",
    "addr:street":"Hobbs Cross Road",
    "iso:country":"GB",
    "sg:address":"Hobbs Cross Road",
    "sg:city":"Harlow",
    "sg:classifiers":[
        {
            "category":"Education",
            "subcategory":"School",
            "type":"Public Place"
        }
    ],
    "sg:phone":"+44 1279 866059",
    "sg:postcode":"CM17 0LB",
    "sg:province":"Essex",
    "sg:tags":[
        "foundation",
        "college"
    ],
    "wof:name":"Churchgate C Of E Aided Primary School",
    "wof:placetype":"venue"
},
  "geometry": {"coordinates":[0.1503529996,51.7811546326],"type":"Point"}
}