{
  "type": "Feature",
  "properties": {
    "addr:full":"10 Low Ousegate York North Yorkshire YO1 1QX",
    "addr:housenumber":"10",
    "addr:postcode":"yo1 1qx",
    "addr:street":"Low Ousegate",
    "iso:country":"GB",
    "sg:address":"10 Low Ousegate",
    "sg:city":"York",
    "sg:classifiers":[
        {
            "category":"Bars & Pubs",
            "type":"Food & Drink"
        }
    ],
    "sg:phone":"+44 1904 686901",
    "sg:postcode":"YO1 1QX",
    "sg:province":"North Yorkshire",
    "sg:tags":[
        "pubs",
        "inn"
    ],
    "wof:name":"O'Neill's",
    "wof:placetype":"venue"
},
  "geometry": {"coordinates":[-1.0838030577,53.9576148987],"type":"Point"}
}