{
  "type": "Feature",
  "properties": {
    "addr:full":"212a West Malvern Road Malvern Herefordshire WR14 4BA",
    "addr:housenumber":"212a",
    "addr:postcode":"wr14 4ba",
    "addr:street":"West Malvern Road",
    "iso:country":"GB",
    "sg:address":"212a West Malvern Road",
    "sg:city":"Malvern",
    "sg:classifiers":[
        {
            "category":"Organizations",
            "subcategory":"Membership Organization",
            "type":"Services"
        }
    ],
    "sg:phone":"+44 1684 560989",
    "sg:postcode":"WR14 4BA",
    "sg:province":"Herefordshire",
    "sg:tags":[
        "club"
    ],
    "wof:name":"Ramblers Association Hereford & Worcester Area",
    "wof:placetype":"venue"
},
  "geometry": {"coordinates":[-2.3479399681,52.115196228],"type":"Point"}
}