{
  "type": "Feature",
  "properties": {
    "iso:country":"GB",
    "sg:address":"17 Broomsleigh Street, West Hampstead",
    "sg:city":"London",
    "sg:classifiers":[
        {
            "category":"Communications",
            "type":"Services"
        }
    ],
    "sg:postcode":"NW6 1QQ",
    "sg:province":"Greater London",
    "sg:tags":[
        "audio-visual"
    ],
    "wof:name":"Eye Tech 2000 Ltd",
    "wof:placetype":"venue"
},
  "geometry": {"coordinates":[-0.198752,51.55048],"type":"Point"}
}