{
  "type": "Feature",
  "properties": {
    "iso:country":"GB",
    "sg:address":"3 Willoway Close",
    "sg:city":"Braunton",
    "sg:classifiers":[
        {
            "category":"Professional",
            "subcategory":"Engineering",
            "type":"Services"
        },
        {
            "category":"Building & Trades",
            "subcategory":"Electrical",
            "type":"Services"
        }
    ],
    "sg:phone":"+44 1271 813998",
    "sg:postcode":"EX33 1AU",
    "sg:province":"Devon",
    "sg:tags":[
        "engineer",
        "electrician",
        "contractor"
    ],
    "wof:name":"T W Webber Electrical Contractors",
    "wof:placetype":"venue"
},
  "geometry": {"coordinates":[-4.1674380302,51.1110534668],"type":"Point"}
}