{
  "type": "Feature",
  "properties": {
    "addr:full":"Cleuchside Farm Jedburgh Scottish Borders TD8 6RD",
    "addr:postcode":"td8 6rd",
    "iso:country":"GB",
    "sg:address":"Cleuchside Farm",
    "sg:city":"Jedburgh",
    "sg:classifiers":[
        {
            "category":"Farming",
            "subcategory":"Farm",
            "type":"Manufacturing & Wholesale Goods"
        }
    ],
    "sg:phone":"+44 1835 862483",
    "sg:postcode":"TD8 6RD",
    "sg:province":"Scottish Borders",
    "sg:tags":[
        "mixed",
        "crop"
    ],
    "wof:name":"J M Yourston & Son",
    "wof:placetype":"venue"
},
  "geometry": {"coordinates":[-2.554624,55.477718],"type":"Point"}
}