{
  "type": "Feature",
  "properties": {
    "addr:full":"72 Watt La Sheffield South Yorkshire S10 5RE",
    "addr:housenumber":"72",
    "addr:postcode":"s10 5re",
    "addr:street":"Watt La Sheffield South",
    "iso:country":"GB",
    "sg:address":"72 Watt La",
    "sg:city":"Sheffield",
    "sg:classifiers":[
        {
            "category":"Building & Trades",
            "subcategory":"Construction",
            "type":"Services"
        }
    ],
    "sg:phone":"+44 114 230 3898",
    "sg:postcode":"S10 5RE",
    "sg:province":"South Yorkshire",
    "sg:tags":[
        "builder"
    ],
    "wof:name":"Alan Hurst Construction",
    "wof:placetype":"venue"
},
  "geometry": {"coordinates":[-1.5237209797,53.376701355],"type":"Point"}
}