{
  "type": "Feature",
  "properties": {
    "addr:full":"232a Whalley Old Road Blackburn Lancashire BB1 5NZ",
    "addr:housenumber":"232a",
    "addr:postcode":"bb1 5nz",
    "addr:street":"Whalley Old Road",
    "iso:country":"GB",
    "sg:address":"232a Whalley Old Road",
    "sg:city":"Blackburn",
    "sg:classifiers":[
        {
            "category":"Government",
            "subcategory":"Post Office",
            "type":"Public Place"
        }
    ],
    "sg:phone":"+44 1254 52659",
    "sg:postcode":"BB1 5NZ",
    "sg:province":"Lancashire",
    "wof:name":"Little Harwood Post Office",
    "wof:placetype":"venue"
},
  "geometry": {"coordinates":[-2.46448493,53.7611846924],"type":"Point"}
}