{
  "type": "Feature",
  "properties": {
    "iso:country":"GB",
    "sg:address":"53 Frith Road",
    "sg:city":"Croydon",
    "sg:classifiers":[
        {
            "category":"Personal",
            "subcategory":"Beauty Salon",
            "type":"Services"
        }
    ],
    "sg:phone":"+44 20 8688 7469",
    "sg:postcode":"CR0 1TB",
    "sg:province":"Surrey",
    "sg:tags":[
        "lady",
        "hairdresser"
    ],
    "wof:name":"Nova Ladies Hairdressing Salon",
    "wof:placetype":"venue"
},
  "geometry": {"coordinates":[-0.102508001,51.3742218018],"type":"Point"}
}