{
  "type": "Feature",
  "properties": {
    "addr:full":"62 Station Road, Glenfield Leicester Leicestershire LE3 8BQ",
    "addr:housenumber":"62",
    "addr:postcode":"le3 8bq",
    "addr:street":"Station Road",
    "iso:country":"GB",
    "sg:address":"62 Station Road, Glenfield",
    "sg:city":"Leicester",
    "sg:classifiers":[
        {
            "category":"Health Services",
            "subcategory":"Dentist",
            "type":"Services"
        }
    ],
    "sg:phone":"+44 116 287 9608",
    "sg:postcode":"LE3 8BQ",
    "sg:province":"Leicestershire",
    "wof:name":"Glenfield Dental Surgery",
    "wof:placetype":"venue"
},
  "geometry": {"coordinates":[-1.202698946,52.6517715454],"type":"Point"}
}