{
  "type": "Feature",
  "properties": {
    "iso:country":"GB",
    "sg:address":"Old Mill Lane Dental Practice, 52 Old Mill Lane, Formby",
    "sg:city":"Liverpool",
    "sg:classifiers":[
        {
            "category":"Health Services",
            "subcategory":"Doctor",
            "type":"Services"
        },
        {
            "category":"Health Services",
            "subcategory":"Dentist",
            "type":"Services"
        }
    ],
    "sg:phone":"+44 1704 871270",
    "sg:postcode":"L37 3PF",
    "sg:province":"Lancashire",
    "wof:name":"VOLYNCHOUK & MASON",
    "wof:placetype":"venue"
},
  "geometry": {"coordinates":[-3.0581450462,53.5619277954],"type":"Point"}
}