{
  "type": "Feature",
  "properties": {
    "addr:full":"14 The Hill Bedford Bedfordshire MK44 3NG",
    "addr:housenumber":"14",
    "addr:postcode":"mk44 3ng",
    "addr:street":"The Hill",
    "iso:country":"GB",
    "sg:address":"14 The Hill",
    "sg:city":"Bedford",
    "sg:classifiers":[
        {
            "category":"Food & Beverages",
            "subcategory":"Meat & Fish",
            "type":"Retail Goods"
        }
    ],
    "sg:phone":"+44 1767 640216",
    "sg:postcode":"MK44 3NG",
    "sg:province":"Bedfordshire",
    "sg:tags":[
        "butcher"
    ],
    "wof:name":"F S Charteress & Son",
    "wof:placetype":"venue"
},
  "geometry": {"coordinates":[-0.3200289905,52.1468658447],"type":"Point"}
}