{
  "type": "Feature",
  "properties": {
    "addr:full":"18 Laggan Square Maidenhead Berkshire SL6 7LA",
    "addr:housenumber":"18",
    "addr:postcode":"sl6 7la",
    "addr:street":"Laggan Square",
    "iso:country":"GB",
    "sg:address":"18 Laggan Square",
    "sg:city":"Maidenhead",
    "sg:classifiers":[
        {
            "category":"Home & Garden",
            "subcategory":"Garden Supply",
            "type":"Retail Goods"
        },
        {
            "category":"Home & Garden",
            "subcategory":"Building Materials",
            "type":"Retail Goods"
        }
    ],
    "sg:phone":"+44 1628 628739",
    "sg:postcode":"SL6 7LA",
    "sg:province":"Berkshire",
    "sg:tags":[
        "shale",
        "supplier",
        "sand",
        "including",
        "aggregate",
        "gravel"
    ],
    "wof:name":"William Bennett & Son",
    "wof:placetype":"venue"
},
  "geometry": {"coordinates":[-0.7216470242,51.5331802368],"type":"Point"}
}