{
  "type": "Feature",
  "properties": {
    "addr:full":"209 Railway Street Nelson Lancashire BB9 0QL",
    "addr:housenumber":"209",
    "addr:postcode":"bb9 0ql",
    "addr:street":"Railway Street",
    "iso:country":"GB",
    "sg:address":"209 Railway Street",
    "sg:city":"Nelson",
    "sg:classifiers":[
        {
            "category":"Shopping",
            "subcategory":"Department Store",
            "type":"Retail Goods"
        },
        {
            "category":"Government",
            "subcategory":"Post Office",
            "type":"Public Place"
        }
    ],
    "sg:phone":"+44 1282 616393",
    "sg:postcode":"BB9 0QL",
    "sg:province":"Lancashire",
    "wof:name":"Parkfield Post Office",
    "wof:placetype":"venue"
},
  "geometry": {"coordinates":[-2.209304,53.831078],"type":"Point"}
}