{
  "type": "Feature",
  "properties": {
    "iso:country":"GB",
    "sg:address":"Alban Gate, London Wall",
    "sg:city":"London",
    "sg:classifiers":[
        {
            "category":"Food & Beverages",
            "subcategory":"Bakery",
            "type":"Retail Goods"
        }
    ],
    "sg:phone":"+44 20 7600 8880",
    "sg:postcode":"EC2M 5QA",
    "sg:province":"Greater London",
    "sg:tags":[
        "pizza"
    ],
    "wof:name":"Pizzaexpress (Restaurants) Ltd.",
    "wof:placetype":"venue"
},
  "geometry": {"coordinates":[-0.08852,51.51733],"type":"Point"}
}