{
  "type": "Feature",
  "properties": {
    "addr:full":"20 Monmouth Street London Greater London WC2H 9HD",
    "addr:housenumber":"20",
    "addr:postcode":"wc2h 9hd",
    "addr:street":"Monmouth Street",
    "iso:country":"GB",
    "sg:address":"20 Monmouth Street",
    "sg:city":"London",
    "sg:classifiers":[
        {
            "category":"Travel",
            "subcategory":"Hotels & Motels",
            "type":"Entertainment"
        }
    ],
    "sg:phone":"+44 20 7836 4300",
    "sg:postcode":"WC2H 9HD",
    "sg:province":"Greater London",
    "wof:name":"Radisson Edwardian Mountbatten Hotel (The)",
    "wof:placetype":"venue"
},
  "geometry": {"coordinates":[-0.1270859987,51.5140533447],"type":"Point"}
}