{
  "type": "Feature",
  "properties": {
    "addr:full":"24 High St East Grinstead East Sussex RH19 3AS",
    "addr:housenumber":"24",
    "addr:postcode":"rh19 3as",
    "addr:street":"High St",
    "iso:country":"GB",
    "sg:address":"24 High St",
    "sg:city":"East Grinstead",
    "sg:classifiers":[
        {
            "category":"Utilities",
            "subcategory":"Fuel Oil & Lpg",
            "type":"Services"
        }
    ],
    "sg:phone":"+44 1342 410014",
    "sg:postcode":"RH19 3AS",
    "sg:province":"East Sussex",
    "wof:name":"Jet",
    "wof:placetype":"venue"
},
  "geometry": {"coordinates":[-0.007277,51.12381],"type":"Point"}
}