{
  "type": "Feature",
  "properties": {
    "addr:full":"5 Lingmoor Drive Burnley Lancashire BB12 8UY",
    "addr:housenumber":"5",
    "addr:postcode":"bb12 8uy",
    "addr:street":"Lingmoor Drive",
    "iso:country":"GB",
    "sg:address":"5 Lingmoor Drive",
    "sg:city":"Burnley",
    "sg:classifiers":[
        {
            "category":"Shopping",
            "subcategory":"Photographic Equipment",
            "type":"Retail Goods"
        }
    ],
    "sg:postcode":"BB12 8UY",
    "sg:province":"Lancashire",
    "wof:name":"Quasar Industries Limited",
    "wof:placetype":"venue"
},
  "geometry": {"coordinates":[-2.303369,53.79702],"type":"Point"}
}