{
  "type": "Feature",
  "properties": {
    "iso:country":"GB",
    "sg:address":"32 Bourtonville",
    "sg:city":"Buckingham",
    "sg:classifiers":[
        {
            "category":"Building & Trades",
            "subcategory":"Landscaping Services",
            "type":"Services"
        }
    ],
    "sg:postcode":"MK18 1AZ",
    "sg:province":"Buckinghamshire",
    "sg:tags":[
        "gardening"
    ],
    "wof:name":"M J B Landscapes",
    "wof:placetype":"venue"
},
  "geometry": {"coordinates":[-0.983123,51.995529],"type":"Point"}
}