{
  "type": "Feature",
  "properties": {
    "iso:country":"GB",
    "sg:address":"Yew Lodge Farm, Algarkirk",
    "sg:city":"Boston",
    "sg:classifiers":[
        {
            "category":"Farming",
            "subcategory":"Farm",
            "type":"Manufacturing & Wholesale Goods"
        }
    ],
    "sg:phone":"+44 1205 460332",
    "sg:postcode":"PE20 2AE",
    "sg:province":"Lincolnshire",
    "sg:tags":[
        "mixed",
        "crop"
    ],
    "wof:name":"R M & L Cook",
    "wof:placetype":"venue"
},
  "geometry": {"coordinates":[-0.08117,52.899776],"type":"Point"}
}