{
  "type": "Feature",
  "properties": {
    "addr:full":"Wash Farm, Halstead Road, Fordham Colchester Essex CO6 3LL",
    "addr:postcode":"co6 3ll",
    "addr:street":"Halstead Road",
    "iso:country":"GB",
    "sg:address":"Wash Farm, Halstead Road, Fordham",
    "sg:city":"Colchester",
    "sg:classifiers":[
        {
            "category":"Organizations",
            "subcategory":"Membership Organization",
            "type":"Services"
        }
    ],
    "sg:postcode":"CO6 3LL",
    "sg:province":"Essex",
    "sg:tags":[
        "club"
    ],
    "wof:name":"Escapades",
    "wof:placetype":"venue"
},
  "geometry": {"coordinates":[0.803098,51.922836],"type":"Point"}
}