{
  "type": "Feature",
  "properties": {
    "addr:full":"19 Cathedral Road Cardiff Cardiff CF11 9HA",
    "addr:housenumber":"19",
    "addr:postcode":"cf11 9ha",
    "addr:street":"Cathedral Road",
    "iso:country":"GB",
    "sg:address":"19 Cathedral Road",
    "sg:city":"Cardiff",
    "sg:classifiers":[
        {
            "category":"Professional",
            "subcategory":"Accounting & Tax Preparation",
            "type":"Services"
        }
    ],
    "sg:phone":"+44 29 2038 8633",
    "sg:postcode":"CF11 9HA",
    "sg:province":"Cardiff",
    "sg:tags":[
        "accountant"
    ],
    "wof:name":"Young & Phillips",
    "wof:placetype":"venue"
},
  "geometry": {"coordinates":[-3.1905,51.482681],"type":"Point"}
}