{
  "type": "Feature",
  "properties": {
    "addr:full":"18 Scott Rd, Olton Solihull West Midlands B92 7LS",
    "addr:housenumber":"18",
    "addr:postcode":"b92 7ls",
    "addr:street":"Scott Rd",
    "iso:country":"GB",
    "sg:address":"18 Scott Rd, Olton",
    "sg:city":"Solihull",
    "sg:classifiers":[
        {
            "category":"Building & Trades",
            "subcategory":"Plumbing",
            "type":"Services"
        }
    ],
    "sg:phone":"+44 121 706 3183",
    "sg:postcode":"B92 7LS",
    "sg:province":"West Midlands",
    "sg:tags":[
        "heating"
    ],
    "wof:name":"R Clark",
    "wof:placetype":"venue"
},
  "geometry": {"coordinates":[-1.8074380159,52.4458808899],"type":"Point"}
}