{
  "type": "Feature",
  "properties": {
    "addr:full":"Waste Lane, Cuddington Northwich Cheshire CW8 2TD",
    "addr:postcode":"cw8 2td",
    "addr:street":"Waste Lane",
    "iso:country":"GB",
    "sg:address":"Waste Lane, Cuddington",
    "sg:city":"Northwich",
    "sg:classifiers":[
        {
            "category":"Building & Trades",
            "subcategory":"Landscaping Services",
            "type":"Services"
        }
    ],
    "sg:phone":"+44 1606 883775",
    "sg:postcode":"CW8 2TD",
    "sg:province":"Cheshire",
    "sg:tags":[
        "landscape",
        "contractor"
    ],
    "wof:name":"Hillview Garden Contractors",
    "wof:placetype":"venue"
},
  "geometry": {"coordinates":[-2.602213,53.238754],"type":"Point"}
}