{
  "type": "Feature",
  "properties": {
    "iso:country":"GB",
    "sg:address":"Unit 1c Sandtoft Industrial Road Sand, Toft Road, Belton",
    "sg:city":"Doncaster",
    "sg:classifiers":[
        {
            "category":"Retail",
            "subcategory":"Auto Repair",
            "type":"Services"
        }
    ],
    "sg:phone":"+44 1427 872981",
    "sg:postcode":"DN9 1PN",
    "sg:province":"Lincolnshire",
    "sg:tags":[
        "modification",
        "garage"
    ],
    "wof:name":"David Campling",
    "wof:placetype":"venue"
},
  "geometry": {"coordinates":[-0.8166390061,53.5528640747],"type":"Point"}
}