{
  "type": "Feature",
  "properties": {
    "addr:full":"Boyd Rd Poole Dorset BH12 4AF",
    "addr:postcode":"bh12 4af",
    "addr:street":"Boyd Rd",
    "iso:country":"GB",
    "sg:address":"Boyd Rd",
    "sg:city":"Poole",
    "sg:classifiers":[
        {
            "category":"Government",
            "subcategory":"Office",
            "type":"Public Place"
        }
    ],
    "sg:phone":"+44 1202 747928",
    "sg:postcode":"BH12 4AF",
    "sg:province":"Dorset",
    "sg:tags":[
        "local"
    ],
    "wof:name":"Boyd Road Sheltered Housing",
    "wof:placetype":"venue"
},
  "geometry": {"coordinates":[-1.9221730232,50.7358474731],"type":"Point"}
}