{
  "type": "Feature",
  "properties": {
    "addr:full":"44 Cudlow Avenue, Rustington Littlehampton West Sussex BN16 2HF",
    "addr:housenumber":"44",
    "addr:postcode":"bn16 2hf",
    "addr:street":"Cudlow Avenue",
    "iso:country":"GB",
    "sg:address":"44 Cudlow Avenue, Rustington",
    "sg:city":"Littlehampton",
    "sg:classifiers":[
        {
            "category":"Professional",
            "subcategory":"Computer Services",
            "type":"Services"
        }
    ],
    "sg:phone":"+44 1903 774446",
    "sg:postcode":"BN16 2HF",
    "sg:province":"West Sussex",
    "sg:tags":[
        "consultant"
    ],
    "wof:name":"First Group Dynamics Ltd.",
    "wof:placetype":"venue"
},
  "geometry": {"coordinates":[-0.51095,50.808861],"type":"Point"}
}