{
  "type": "Feature",
  "properties": {
    "iso:country":"GB",
    "sg:address":"Severn Drive, Wellington",
    "sg:city":"Telford",
    "sg:classifiers":[
        {
            "category":"Education",
            "subcategory":"School",
            "type":"Public Place"
        },
        {
            "category":"Government",
            "subcategory":"Office",
            "type":"Public Place"
        }
    ],
    "sg:phone":"+44 1952 223460",
    "sg:postcode":"TF1 3JB",
    "sg:province":"Shropshire",
    "sg:tags":[
        "local",
        "authority"
    ],
    "wof:name":"Dothill Infants School",
    "wof:placetype":"venue"
},
  "geometry": {"coordinates":[-2.524684906,52.7061958313],"type":"Point"}
}