{
  "type": "Feature",
  "properties": {
    "addr:full":"Smithy Yard, Smithy La Oldham Lancashire OL3 6AW",
    "addr:postcode":"ol3 6aw",
    "addr:street":"Smithy;Smithy",
    "iso:country":"GB",
    "sg:address":"Smithy Yard, Smithy La",
    "sg:city":"Oldham",
    "sg:classifiers":[
        {
            "category":"Retail",
            "subcategory":"Auto Repair",
            "type":"Services"
        }
    ],
    "sg:phone":"+44 1457 870353",
    "sg:postcode":"OL3 6AW",
    "sg:province":"Lancashire",
    "sg:tags":[
        "car",
        "upholsterer"
    ],
    "wof:name":"Delph Motor Trimming Services",
    "wof:placetype":"venue"
},
  "geometry": {"coordinates":[-2.005094,53.548313],"type":"Point"}
}