{
  "type": "Feature",
  "properties": {
    "addr:full":"14 Furze La, West Burley Croydon Surrey CR8 3EG",
    "addr:housenumber":"14",
    "addr:postcode":"cr8 3eg",
    "addr:street":"Furze La West Burley",
    "iso:country":"GB",
    "sg:address":"14 Furze La, West Burley",
    "sg:city":"Croydon",
    "sg:classifiers":[
        {
            "category":"Building & Trades",
            "subcategory":"Cleaning & Sanitation",
            "type":"Services"
        }
    ],
    "sg:postcode":"CR8 3EG",
    "sg:province":"Surrey",
    "sg:tags":[
        "repair",
        "lift",
        "-"
    ],
    "wof:name":"Malik,Aniq,",
    "wof:placetype":"venue"
},
  "geometry": {"coordinates":[-0.12663,51.340889],"type":"Point"}
}