{
  "type": "Feature",
  "properties": {
    "addr:full":"323 Copnor Road Portsmouth Hampshire PO3 5EG",
    "addr:housenumber":"323",
    "addr:postcode":"hampshire po3 5eg",
    "addr:street":"Copnor Road",
    "iso:country":"GB",
    "sg:address":"323 Copnor Road",
    "sg:city":"Portsmouth",
    "sg:classifiers":[
        {
            "category":"Fast Food",
            "type":"Food & Drink"
        }
    ],
    "sg:phone":"+44 23 9269 0559",
    "sg:postcode":"PO3 5EG",
    "sg:province":"Hampshire",
    "sg:tags":[
        "away",
        "take"
    ],
    "wof:name":"The Lunch Box",
    "wof:placetype":"venue"
},
  "geometry": {"coordinates":[-1.06533,50.821617],"type":"Point"}
}