{
  "type": "Feature",
  "properties": {
    "addr:full":"Elmtree Workshop, West Street, Leven Hull East Riding of Yorkshire HU17 5LE",
    "addr:postcode":"hu17 5le",
    "addr:street":"West Street Leven",
    "iso:country":"GB",
    "sg:address":"Elmtree Workshop, West Street, Leven",
    "sg:city":"Hull",
    "sg:classifiers":[
        {
            "category":"Building & Trades",
            "subcategory":"Construction",
            "type":"Services"
        }
    ],
    "sg:phone":"+44 1964 543333",
    "sg:postcode":"HU17 5LE",
    "sg:province":"East Riding of Yorkshire",
    "sg:tags":[
        "joinery"
    ],
    "wof:name":"Brian Fell (Leven) Ltd.",
    "wof:placetype":"venue"
},
  "geometry": {"coordinates":[-0.3171690106,53.8918838501],"type":"Point"}
}