{
  "type": "Feature",
  "properties": {
    "iso:country":"GB",
    "sg:address":"Ground Floor, 79 Palmerston Crescent",
    "sg:city":"London",
    "sg:classifiers":[
        {
            "category":"Banks & Credit Unions",
            "subcategory":"Financial Services",
            "type":"Services"
        }
    ],
    "sg:postcode":"N13 4NG",
    "sg:province":"Greater London",
    "sg:tags":[
        "consultant"
    ],
    "wof:name":"Lightning Seed Finance Ltd",
    "wof:placetype":"venue"
},
  "geometry": {"coordinates":[-0.1134900004,51.6127700806],"type":"Point"}
}