{
  "type": "Feature",
  "properties": {
    "iso:country":"GB",
    "sg:address":"2 Church Street, Warnham",
    "sg:city":"Horsham",
    "sg:classifiers":[
        {
            "category":"Bars & Pubs",
            "type":"Food & Drink"
        }
    ],
    "sg:phone":"+44 1403 265028",
    "sg:postcode":"RH12 3QW",
    "sg:province":"West Sussex",
    "sg:tags":[
        "pubs",
        "inn"
    ],
    "wof:name":"The Sussex Oak",
    "wof:placetype":"venue"
},
  "geometry": {"coordinates":[-0.361627,51.070972],"type":"Point"}
}