{
  "type": "Feature",
  "properties": {
    "iso:country":"GB",
    "sg:address":"Newlands Road, Brightons",
    "sg:city":"Falkirk",
    "sg:classifiers":[
        {
            "category":"Social Services",
            "subcategory":"Job Training",
            "type":"Services"
        },
        {
            "category":"Education",
            "subcategory":"Special Training",
            "type":"Public Place"
        }
    ],
    "sg:phone":"+44 1324 710400",
    "sg:postcode":"FK2 0DE",
    "sg:province":"Falkirk",
    "sg:tags":[
        "product",
        "centre"
    ],
    "wof:name":"Scottish Prison Service College",
    "wof:placetype":"venue"
},
  "geometry": {"coordinates":[-3.728589,55.982109],"type":"Point"}
}