{
  "type": "Feature",
  "properties": {
    "iso:country":"GB",
    "sg:address":"Coetes Cottage",
    "sg:city":"Leven",
    "sg:classifiers":[
        {
            "category":"Building & Trades",
            "subcategory":"Construction",
            "type":"Services"
        }
    ],
    "sg:postcode":"KY8 6JG",
    "sg:province":"Fife",
    "sg:tags":[
        "joiner",
        "carpenter"
    ],
    "wof:name":"N & R Joinery",
    "wof:placetype":"venue"
},
  "geometry": {"coordinates":[-2.998787,56.194401],"type":"Point"}
}