{
  "type": "Feature",
  "properties": {
    "iso:country":"GB",
    "sg:address":"Hollies Way, High St",
    "sg:city":"Potters Bar",
    "sg:classifiers":[
        {
            "category":"Government",
            "subcategory":"Fire Station",
            "type":"Public Place"
        }
    ],
    "sg:phone":"+44 1707 643401",
    "sg:postcode":"EN6 5BH",
    "sg:province":"Greater London",
    "sg:tags":[
        "w'sale",
        "lighting"
    ],
    "wof:name":"Rada Lighting Ltd",
    "wof:placetype":"venue"
},
  "geometry": {"coordinates":[-0.1784240007,51.6930122375],"type":"Point"}
}