{
  "type": "Feature",
  "properties": {
    "addr:full":"108 Copthorne Road, Felbridge East Grinstead East Sussex RH19 2NU",
    "addr:housenumber":"108",
    "addr:postcode":"rh19 2nu",
    "addr:street":"Copthorne Road",
    "iso:country":"GB",
    "sg:address":"108 Copthorne Road, Felbridge",
    "sg:city":"East Grinstead",
    "sg:classifiers":[
        {
            "category":"Personal",
            "type":"Services"
        }
    ],
    "sg:postcode":"RH19 2NU",
    "sg:province":"East Sussex",
    "sg:tags":[
        "delivery"
    ],
    "wof:name":"Gatwick Van Services",
    "wof:placetype":"venue"
},
  "geometry": {"coordinates":[-0.0499759987,51.1409835815],"type":"Point"}
}