{
  "type": "Feature",
  "properties": {
    "addr:full":"Oakfield Ho, 31 Main St Glasgow South Lanarkshire G74 4JU",
    "addr:housenumber":"31",
    "addr:postcode":"g74 4ju",
    "addr:street":"Main St",
    "iso:country":"GB",
    "sg:address":"Oakfield Ho, 31 Main St",
    "sg:city":"Glasgow",
    "sg:classifiers":[
        {
            "category":"Shopping",
            "subcategory":"Computers & Home Electronics",
            "type":"Retail Goods"
        }
    ],
    "sg:phone":"+44 1355 263550",
    "sg:postcode":"G74 4JU",
    "sg:province":"South Lanarkshire",
    "wof:name":"Caledonian Hardwoods Ltd",
    "wof:placetype":"venue"
},
  "geometry": {"coordinates":[-4.17567,55.76646],"type":"Point"}
}