{
  "type": "Feature",
  "properties": {
    "addr:full":"Deerness Orkney Orkney Islands KW17 2QH",
    "addr:housenumber":"orkney orkney",
    "addr:postcode":"kw17 2qh",
    "iso:country":"GB",
    "sg:address":"Deerness",
    "sg:city":"Orkney",
    "sg:classifiers":[
        {
            "category":"Shopping",
            "subcategory":"Department Store",
            "type":"Retail Goods"
        },
        {
            "category":"Food & Beverages",
            "subcategory":"Groceries & Convenience Stores",
            "type":"Retail Goods"
        }
    ],
    "sg:phone":"+44 1856 741208",
    "sg:postcode":"KW17 2QH",
    "sg:province":"Orkney Islands",
    "wof:name":"Deerness Stores & Services",
    "wof:placetype":"venue"
},
  "geometry": {"coordinates":[-2.7428839207,58.9370002747],"type":"Point"}
}