{
  "type": "Feature",
  "properties": {
    "addr:full":"5 Rutherford Road, Maghull Liverpool Lancashire L31 3DD",
    "addr:housenumber":"5",
    "addr:postcode":"l31 3dd",
    "addr:street":"Rutherford Road",
    "iso:country":"GB",
    "sg:address":"5 Rutherford Road, Maghull",
    "sg:city":"Liverpool",
    "sg:classifiers":[
        {
            "category":"Personal",
            "type":"Services"
        },
        {
            "category":"Communications",
            "type":"Services"
        }
    ],
    "sg:phone":"+44 151 531 7627",
    "sg:postcode":"L31 3DD",
    "sg:province":"Lancashire",
    "sg:tags":[
        "audio-visual",
        "wedding"
    ],
    "wof:name":"Cramar Video",
    "wof:placetype":"venue"
},
  "geometry": {"coordinates":[-2.934159,53.506481],"type":"Point"}
}