{
  "type": "Feature",
  "properties": {
    "addr:full":"36 Dowanside Road, Hillhead Glasgow Glasgow City G12 9DW",
    "addr:housenumber":"36",
    "addr:postcode":"g12 9dw",
    "addr:street":"Dowanside Road",
    "iso:country":"GB",
    "sg:address":"36 Dowanside Road, Hillhead",
    "sg:city":"Glasgow",
    "sg:classifiers":[
        {
            "category":"Arena",
            "subcategory":"Sports Club",
            "type":"Entertainment"
        }
    ],
    "sg:phone":"+44 141 357 3456",
    "sg:postcode":"G12 9DW",
    "sg:province":"Glasgow City",
    "wof:name":"Willow Bank Bowling Club",
    "wof:placetype":"venue"
},
  "geometry": {"coordinates":[-4.2970237732,55.8755226135],"type":"Point"}
}