{
  "type": "Feature",
  "properties": {
    "iso:country":"GB",
    "sg:address":"155a Union Street",
    "sg:city":"Larkhall",
    "sg:classifiers":[
        {
            "category":"Sports & Exercise",
            "subcategory":"Athletic Track",
            "type":"Entertainment"
        }
    ],
    "sg:postcode":"ML9 1EB",
    "sg:province":"South Lanarkshire",
    "sg:tags":[
        "bags",
        "accessory",
        "belt"
    ],
    "wof:name":"G M Shoe Repairs",
    "wof:placetype":"venue"
},
  "geometry": {"coordinates":[-3.972394,55.737862],"type":"Point"}
}