{
  "type": "Feature",
  "properties": {
    "addr:full":"Room 14 First Floor Margarethe, House Eismann Way Corby Northamptonshire NN17 5ZB",
    "addr:housenumber":"14 first floor margarethe",
    "addr:postcode":"nn17 5zb",
    "addr:street":"Eismann Way",
    "iso:country":"GB",
    "sg:address":"Room 14 First Floor Margarethe, House Eismann Way",
    "sg:city":"Corby",
    "sg:classifiers":[
        {
            "category":"Utilities",
            "subcategory":"Fuel Oil & Lpg",
            "type":"Services"
        }
    ],
    "sg:postcode":"NN17 5ZB",
    "sg:province":"Northamptonshire",
    "sg:tags":[
        "gas"
    ],
    "wof:name":"Drilltec International Ltd.",
    "wof:placetype":"venue"
},
  "geometry": {"coordinates":[-0.6733660102,52.4952011108],"type":"Point"}
}