{
  "type": "Feature",
  "properties": {
    "iso:country":"GB",
    "sg:address":"204 Heaton Moor Rd",
    "sg:city":"Stockport",
    "sg:classifiers":[
        {
            "category":"Shopping",
            "subcategory":"Thrift Store",
            "type":"Retail Goods"
        }
    ],
    "sg:phone":"+44 161 432 9593",
    "sg:postcode":"SK4 4DU",
    "sg:province":"Cheshire",
    "sg:tags":[
        "shop",
        "charity"
    ],
    "wof:name":"The Children's Society",
    "wof:placetype":"venue"
},
  "geometry": {"coordinates":[-2.1897339821,53.4174156189],"type":"Point"}
}