{
  "type": "Feature",
  "properties": {
    "addr:full":"37 Bittern Road, Sowton Industrial Estate Exeter Devon EX2 7LW",
    "addr:housenumber":"37",
    "addr:postcode":"ex2 7lw",
    "addr:street":"Bittern Road;Industrial Estate",
    "iso:country":"GB",
    "sg:address":"37 Bittern Road, Sowton Industrial Estate",
    "sg:city":"Exeter",
    "sg:classifiers":[
        {
            "category":"Home & Garden",
            "subcategory":"Household Appliances",
            "type":"Retail Goods"
        },
        {
            "category":"Wholesale",
            "subcategory":"Machinery & Supplies",
            "type":"Manufacturing & Wholesale Goods"
        }
    ],
    "sg:postcode":"EX2 7LW",
    "sg:province":"Devon",
    "sg:tags":[
        "electrical"
    ],
    "wof:name":"P R Refrigeration Engineers",
    "wof:placetype":"venue"
},
  "geometry": {"coordinates":[-3.472014,50.722328],"type":"Point"}
}