{
  "type": "Feature",
  "properties": {
    "iso:country":"GB",
    "sg:address":"Hillwood, Main St, Glenfarg",
    "sg:city":"Perth",
    "sg:classifiers":[
        {
            "category":"Building & Trades",
            "subcategory":"Landscaping Services",
            "type":"Services"
        }
    ],
    "sg:phone":"+44 1577 830320",
    "sg:postcode":"PH2 9NT",
    "sg:province":"Perth and Kinross",
    "sg:tags":[
        "designer",
        "architect",
        "landscape"
    ],
    "wof:name":"Glenfarg Garden Design",
    "wof:placetype":"venue"
},
  "geometry": {"coordinates":[-3.3986430168,56.2783546448],"type":"Point"}
}