{
  "type": "Feature",
  "properties": {
    "addr:full":"25 Barony Street Edinburgh City of Edinburgh EH3 6PD",
    "addr:housenumber":"25",
    "addr:postcode":"eh3 6pd",
    "addr:street":"Barony Street",
    "iso:country":"GB",
    "sg:address":"25 Barony Street",
    "sg:city":"Edinburgh",
    "sg:classifiers":[
        {
            "category":"Place Of Worship",
            "subcategory":"Synagogue",
            "type":"Public Place"
        },
        {
            "category":"Banks & Credit Unions",
            "subcategory":"Financial Services",
            "type":"Services"
        }
    ],
    "sg:phone":"+44 131 556 5297",
    "sg:postcode":"EH3 6PD",
    "sg:province":"City of Edinburgh",
    "sg:tags":[
        "claim",
        "assessor"
    ],
    "wof:name":"T & T Technical Services",
    "wof:placetype":"venue"
},
  "geometry": {"coordinates":[-3.191214,55.95797],"type":"Point"}
}