{
  "type": "Feature",
  "properties": {
    "addr:full":"Brownhill Of Auchmunziel, New Deer Turriff Aberdeenshire AB53 6YH",
    "addr:postcode":"ab53 6yh",
    "iso:country":"GB",
    "sg:address":"Brownhill Of Auchmunziel, New Deer",
    "sg:city":"Turriff",
    "sg:classifiers":[
        {
            "category":"Wholesale",
            "subcategory":"Chemicals & Plastics",
            "type":"Manufacturing & Wholesale Goods"
        }
    ],
    "sg:phone":"+44 1771 644730",
    "sg:postcode":"AB53 6YH",
    "sg:province":"Aberdeenshire",
    "sg:tags":[
        "retail",
        "freezer",
        "refrigerator"
    ],
    "wof:name":"Hemsley Refrigeration",
    "wof:placetype":"venue"
},
  "geometry": {"coordinates":[-2.1930038929,57.5111465454],"type":"Point"}
}