{
  "type": "Feature",
  "properties": {
    "addr:full":"119 Tonge Moor Road Bolton Lancashire BL2 2DL",
    "addr:housenumber":"119",
    "addr:postcode":"bl2 2dl",
    "addr:street":"Tonge Moor Road",
    "iso:country":"GB",
    "sg:address":"119 Tonge Moor Road",
    "sg:city":"Bolton",
    "sg:classifiers":[
        {
            "category":"Fast Food",
            "type":"Food & Drink"
        }
    ],
    "sg:phone":"+44 1204 363313",
    "sg:postcode":"BL2 2DL",
    "sg:province":"Lancashire",
    "sg:tags":[
        "delivery"
    ],
    "wof:name":"Chicagos' Pizzas",
    "wof:placetype":"venue"
},
  "geometry": {"coordinates":[-2.414157,53.587299],"type":"Point"}
}