{
  "type": "Feature",
  "properties": {
    "addr:full":"Erskine House, North Avenue, Clydebank Business Park Clydebank East Dunbartonshire G81 2DR",
    "addr:postcode":"g81 2dr",
    "addr:street":"North Avenue Clydebank Business Park Clydebank",
    "iso:country":"GB",
    "sg:address":"Erskine House, North Avenue, Clydebank Business Park",
    "sg:city":"Clydebank",
    "sg:classifiers":[
        {
            "category":"Insurance",
            "subcategory":"Insurance Agent",
            "type":"Services"
        }
    ],
    "sg:phone":"+44 141 951 4100",
    "sg:postcode":"G81 2DR",
    "sg:province":"East Dunbartonshire",
    "sg:tags":[
        "broker"
    ],
    "wof:name":"Hart Insurance Brokers",
    "wof:placetype":"venue"
},
  "geometry": {"coordinates":[-4.414628,55.908684],"type":"Point"}
}