{
  "type": "Feature",
  "properties": {
    "addr:full":"92 Woodcote Road Wallington Surrey SM6 0NG",
    "addr:housenumber":"92",
    "addr:postcode":"sm6 0ng",
    "addr:street":"Woodcote Road",
    "iso:country":"GB",
    "sg:address":"92 Woodcote Road",
    "sg:city":"Wallington",
    "sg:classifiers":[
        {
            "category":"Shopping",
            "subcategory":"Books",
            "type":"Retail Goods"
        }
    ],
    "sg:phone":"+44 20 8669 7739",
    "sg:postcode":"SM6 0NG",
    "sg:province":"Surrey",
    "sg:tags":[
        "bookseller"
    ],
    "wof:name":"W H Smith",
    "wof:placetype":"venue"
},
  "geometry": {"coordinates":[-0.1497389972,51.3582077026],"type":"Point"}
}