{
  "type": "Feature",
  "properties": {
    "addr:full":"Twrog, Glyn Llifon Blaenau Ffestiniog Gwynedd LL41 4DG",
    "addr:postcode":"ll41 4dg",
    "iso:country":"GB",
    "sg:address":"Twrog, Glyn Llifon",
    "sg:city":"Blaenau Ffestiniog",
    "sg:classifiers":[
        {
            "category":"Home & Garden",
            "subcategory":"Kitchen Supply",
            "type":"Retail Goods"
        }
    ],
    "sg:phone":"+44 1766 831477",
    "sg:postcode":"LL41 4DG",
    "sg:province":"Gwynedd",
    "sg:tags":[
        "equipment",
        "catering"
    ],
    "wof:name":"Catercare",
    "wof:placetype":"venue"
},
  "geometry": {"coordinates":[-3.9315590858,52.9613494873],"type":"Point"}
}