{
  "type": "Feature",
  "properties": {
    "iso:country":"GB",
    "sg:address":"10a Chantry Place",
    "sg:city":"Morpeth",
    "sg:classifiers":[
        {
            "category":"Professional",
            "subcategory":"Business Services",
            "type":"Services"
        }
    ],
    "sg:phone":"+44 1670 513575",
    "sg:postcode":"NE61 1PJ",
    "sg:province":"Northumberland",
    "sg:tags":[
        "transfer",
        "agent"
    ],
    "wof:name":"Everett Masson & Furby (North East) Ltd.",
    "wof:placetype":"venue"
},
  "geometry": {"coordinates":[-1.6873320341,55.1671295166],"type":"Point"}
}