{
  "type": "Feature",
  "properties": {
    "addr:full":"3 Vestry Road Street Somerset BA16 0HY",
    "addr:housenumber":"3",
    "addr:postcode":"ba16 0hy",
    "addr:street":"Vestry Road Street",
    "iso:country":"GB",
    "sg:address":"3 Vestry Road",
    "sg:city":"Street",
    "sg:classifiers":[
        {
            "category":"Building & Trades",
            "subcategory":"Plumbing",
            "type":"Services"
        }
    ],
    "sg:phone":"+44 1458 445763",
    "sg:postcode":"BA16 0HY",
    "sg:province":"Somerset",
    "sg:tags":[
        "repair",
        "heating",
        "servicing",
        "boiler"
    ],
    "wof:name":"Barber Oil & Gas Boiler Services",
    "wof:placetype":"venue"
},
  "geometry": {"coordinates":[-2.741609,51.125561],"type":"Point"}
}