{
  "type": "Feature",
  "properties": {
    "addr:full":"37 Wellington Road South Stockport Cheshire SK1 3RP",
    "addr:housenumber":"37",
    "addr:postcode":"sk1 3rp",
    "addr:street":"Wellington Road South",
    "iso:country":"GB",
    "sg:address":"37 Wellington Road South",
    "sg:city":"Stockport",
    "sg:classifiers":[
        {
            "category":"Shopping",
            "subcategory":"News",
            "type":"Retail Goods"
        }
    ],
    "sg:phone":"+44 161 480 4855",
    "sg:postcode":"SK1 3RP",
    "sg:province":"Cheshire",
    "sg:tags":[
        "newsagent"
    ],
    "wof:name":"Johns Newsagents",
    "wof:placetype":"venue"
},
  "geometry": {"coordinates":[-2.1606519222,53.4079971313],"type":"Point"}
}