{
  "type": "Feature",
  "properties": {
    "addr:full":"7a Middlepark Road Dudley West Midlands DY1 2LW",
    "addr:housenumber":"7a",
    "addr:postcode":"dy1 2lw",
    "addr:street":"Middlepark Road",
    "iso:country":"GB",
    "sg:address":"7a Middlepark Road",
    "sg:city":"Dudley",
    "sg:classifiers":[
        {
            "category":"Personal",
            "subcategory":"Barber",
            "type":"Services"
        }
    ],
    "sg:postcode":"DY1 2LW",
    "sg:province":"West Midlands",
    "sg:tags":[
        "men's",
        "hairdresser"
    ],
    "wof:name":"Dave's Barber's Shop",
    "wof:placetype":"venue"
},
  "geometry": {"coordinates":[-2.114194,52.504276],"type":"Point"}
}