{
  "type": "Feature",
  "properties": {
    "addr:full":"Kelso Road Coldstream Northumberland TD12 4NJ",
    "addr:postcode":"td12 4nj",
    "addr:street":"Kelso Road",
    "iso:country":"GB",
    "sg:address":"Kelso Road",
    "sg:city":"Coldstream",
    "sg:classifiers":[
        {
            "category":"Sports & Exercise",
            "subcategory":"Golf",
            "type":"Entertainment"
        }
    ],
    "sg:phone":"+44 1890 882678",
    "sg:postcode":"TD12 4NJ",
    "sg:province":"Northumberland",
    "sg:tags":[
        "club",
        "course"
    ],
    "wof:name":"Hirsel Golf Club",
    "wof:placetype":"venue"
},
  "geometry": {"coordinates":[-2.261655,55.64777],"type":"Point"}
}