{
  "type": "Feature",
  "properties": {
    "addr:full":"239 Highcross Rd Poulton Le Fylde Lancashire FY6 8DB",
    "addr:housenumber":"239",
    "addr:postcode":"fy6 8db",
    "addr:street":"Highcross Rd",
    "iso:country":"GB",
    "sg:address":"239 Highcross Rd",
    "sg:city":"Poulton Le Fylde",
    "sg:classifiers":[
        {
            "category":"Building & Trades",
            "subcategory":"Construction",
            "type":"Services"
        }
    ],
    "sg:phone":"+44 1253 883054",
    "sg:postcode":"FY6 8DB",
    "sg:province":"Lancashire",
    "sg:tags":[
        "builder"
    ],
    "wof:name":"Tattersalls Group",
    "wof:placetype":"venue"
},
  "geometry": {"coordinates":[-2.992133,53.839405],"type":"Point"}
}