{
  "type": "Feature",
  "properties": {
    "addr:full":"Jonathan House, 19 Bayswater Avenue, Westbury Park Bristol City of Bristol BS6 7NU",
    "addr:housenumber":"19",
    "addr:postcode":"bs6 7nu",
    "addr:street":"Bayswater Avenue",
    "iso:country":"GB",
    "sg:address":"Jonathan House, 19 Bayswater Avenue, Westbury Park",
    "sg:city":"Bristol",
    "sg:classifiers":[
        {
            "category":"Health Services",
            "subcategory":"Nursing And Care Facility",
            "type":"Services"
        }
    ],
    "sg:phone":"+44 117 973 6361",
    "sg:postcode":"BS6 7NU",
    "sg:province":"City of Bristol",
    "sg:tags":[
        "home"
    ],
    "wof:name":"Freeways",
    "wof:placetype":"venue"
},
  "geometry": {"coordinates":[-2.611831,51.47699],"type":"Point"}
}