{
  "type": "Feature",
  "properties": {
    "iso:country":"GB",
    "sg:address":"Enterprise Centre",
    "sg:city":"Milton Keynes",
    "sg:classifiers":[
        {
            "category":"Recreation",
            "subcategory":"Barbecue",
            "type":"Entertainment"
        }
    ],
    "sg:postcode":"MK15 8HG",
    "sg:province":"Buckinghamshire",
    "sg:tags":[
        "equipment",
        "retail"
    ],
    "wof:name":"P M E Supplies Ltd",
    "wof:placetype":"venue"
},
  "geometry": {"coordinates":[-0.727749,52.005856],"type":"Point"}
}