{
  "type": "Feature",
  "properties": {
    "iso:country":"GB",
    "sg:address":"Dairymans House, Pinners Lane, Nonington",
    "sg:city":"Dover",
    "sg:classifiers":[
        {
            "category":"Communications",
            "subcategory":"Film & Video Production",
            "type":"Services"
        }
    ],
    "sg:phone":"+44 1304 840947",
    "sg:postcode":"CT15 4LH",
    "sg:province":"Kent",
    "sg:tags":[
        "recording",
        "studio"
    ],
    "wof:name":"Matthew Barwick",
    "wof:placetype":"venue"
},
  "geometry": {"coordinates":[1.2277699709,51.2262229919],"type":"Point"}
}