{
  "type": "Feature",
  "properties": {
    "iso:country":"GB",
    "sg:address":"6 Buckingham Place, Bellfield Road",
    "sg:city":"High Wycombe",
    "sg:classifiers":[
        {
            "category":"Professional",
            "subcategory":"Detective & Security Services",
            "type":"Services"
        }
    ],
    "sg:postcode":"HP13 5HW",
    "sg:province":"Buckinghamshire",
    "sg:tags":[
        "equipment",
        "installers"
    ],
    "wof:name":"Secom Plc",
    "wof:placetype":"venue"
},
  "geometry": {"coordinates":[-0.758771,51.633278],"type":"Point"}
}