{
  "type": "Feature",
  "properties": {
    "iso:country":"GB",
    "sg:address":"27 Hillside Avenue, Silverstone",
    "sg:city":"Towcester",
    "sg:classifiers":[
        {
            "category":"Professional",
            "subcategory":"Secretarial Services",
            "type":"Services"
        }
    ],
    "sg:postcode":"NN12 8UR",
    "sg:province":"Buckinghamshire",
    "wof:name":"Liz Trundle Word Processing Services",
    "wof:placetype":"venue"
},
  "geometry": {"coordinates":[-1.022403,52.093285],"type":"Point"}
}