{
  "type": "Feature",
  "properties": {
    "addr:full":"42 Cross St Camborne Cornwall TR14 8EY",
    "addr:housenumber":"42",
    "addr:postcode":"tr14 8ey",
    "addr:street":"Cross St",
    "iso:country":"GB",
    "sg:address":"42 Cross St",
    "sg:city":"Camborne",
    "sg:classifiers":[
        {
            "category":"Manufacturing",
            "subcategory":"Pottery",
            "type":"Manufacturing & Wholesale Goods"
        }
    ],
    "sg:phone":"+44 1209 711136",
    "sg:postcode":"TR14 8EY",
    "sg:province":"Cornwall",
    "wof:name":"Out of The Blue",
    "wof:placetype":"venue"
},
  "geometry": {"coordinates":[-5.300099,50.212566],"type":"Point"}
}