{
  "type": "Feature",
  "properties": {
    "addr:full":"60 Golborne Road London Greater London W10 5PR",
    "addr:housenumber":"60",
    "addr:postcode":"w10 5pr",
    "addr:street":"Golborne Road",
    "iso:country":"GB",
    "sg:address":"60 Golborne Road",
    "sg:city":"London",
    "sg:classifiers":[
        {
            "category":"Professional",
            "subcategory":"Lawyer & Legal Services",
            "type":"Services"
        }
    ],
    "sg:phone":"+44 20 8960 9222",
    "sg:postcode":"W10 5PR",
    "sg:province":"Greater London",
    "wof:name":"Peter Kandler & Co",
    "wof:placetype":"venue"
},
  "geometry": {"coordinates":[-0.2079299986,51.5223426819],"type":"Point"}
}