{
  "type": "Feature",
  "properties": {
    "addr:full":"2 Auchengill Place Glasgow Glasgow City G34 0EY",
    "addr:housenumber":"2",
    "addr:postcode":"g34 0ey",
    "addr:street":"Auchengill Place",
    "iso:country":"GB",
    "sg:address":"2 Auchengill Place",
    "sg:city":"Glasgow",
    "sg:classifiers":[
        {
            "category":"Education",
            "subcategory":"School",
            "type":"Public Place"
        }
    ],
    "sg:phone":"+44 141 771 5016",
    "sg:postcode":"G34 0EY",
    "sg:province":"Glasgow City",
    "sg:tags":[
        "local",
        "authority"
    ],
    "wof:name":"Bishoploch Primary School",
    "wof:placetype":"venue"
},
  "geometry": {"coordinates":[-4.100561142,55.8733215332],"type":"Point"}
}