{
  "type": "Feature",
  "properties": {
    "addr:full":"Kenwyn Street Truro Cornwall TR1 3DJ",
    "addr:postcode":"tr1 3dj",
    "addr:street":"Kenwyn Street",
    "iso:country":"GB",
    "sg:address":"Kenwyn Street",
    "sg:city":"Truro",
    "sg:classifiers":[
        {
            "category":"Bars & Pubs",
            "type":"Food & Drink"
        }
    ],
    "sg:postcode":"TR1 3DJ",
    "sg:province":"Cornwall",
    "sg:tags":[
        "pubs",
        "inn"
    ],
    "wof:name":"William Iv Public House",
    "wof:placetype":"venue"
},
  "geometry": {"coordinates":[-5.055079,50.26302],"type":"Point"}
}