{
  "type": "Feature",
  "properties": {
    "iso:country":"GB",
    "sg:address":"Meadowbank School, School Road, Meadowbank",
    "sg:city":"Winsford",
    "sg:classifiers":[
        {
            "category":"Professional",
            "subcategory":"Printing & Photocopies",
            "type":"Services"
        }
    ],
    "sg:phone":"+44 1606 861298",
    "sg:postcode":"CW7 2PG",
    "sg:province":"Cheshire",
    "sg:tags":[
        "printer"
    ],
    "wof:name":"Technoprint",
    "wof:placetype":"venue"
},
  "geometry": {"coordinates":[-2.5245089531,53.2104301453],"type":"Point"}
}