{
  "type": "Feature",
  "properties": {
    "iso:country":"GB",
    "sg:address":"43 Oxford Street",
    "sg:city":"Whitstable",
    "sg:classifiers":[
        {
            "category":"Building & Trades",
            "subcategory":"Locksmith",
            "type":"Services"
        }
    ],
    "sg:postcode":"CT5 1DB",
    "sg:province":"Kent",
    "sg:tags":[
        "cutting",
        "key"
    ],
    "wof:name":"Key-Smiths & Cobblers",
    "wof:placetype":"venue"
},
  "geometry": {"coordinates":[1.024977,51.355297],"type":"Point"}
}