{
  "type": "Feature",
  "properties": {
    "iso:country":"GB",
    "sg:address":"Brass Knocker St",
    "sg:city":"Newport",
    "sg:classifiers":[
        {
            "category":"Health Services",
            "subcategory":"Doctor",
            "type":"Services"
        }
    ],
    "sg:phone":"+44 1633 880150",
    "sg:postcode":"NP6 3EG",
    "sg:province":"East Riding of Yorkshire",
    "sg:tags":[
        "practitioners"
    ],
    "wof:name":"Telang Dr S",
    "wof:placetype":"venue"
},
  "geometry": {"coordinates":[-2.830452,51.579948],"type":"Point"}
}