{
  "type": "Feature",
  "properties": {
    "iso:country":"GB",
    "sg:address":"Woodmancote Pl, Brighton Rd",
    "sg:city":"Henfield",
    "sg:classifiers":[
        {
            "category":"Professional",
            "subcategory":"Business Services",
            "type":"Services"
        }
    ],
    "sg:phone":"+44 1273 495792",
    "sg:postcode":"BN5 9SR",
    "sg:province":"West Sussex",
    "sg:tags":[
        "hospitality",
        "corporate"
    ],
    "wof:name":"Woodmancote Place Ltd",
    "wof:placetype":"venue"
},
  "geometry": {"coordinates":[-0.272289,50.931419],"type":"Point"}
}