{
  "type": "Feature",
  "properties": {
    "addr:full":"36 Great St Helens London Greater London EC3A 6AP",
    "addr:housenumber":"36",
    "addr:postcode":"ec3a 6ap",
    "addr:street":"Great St Helens",
    "iso:country":"GB",
    "sg:address":"36 Great St Helens",
    "sg:city":"London",
    "sg:classifiers":[
        {
            "category":"Banks & Credit Unions",
            "subcategory":"Investment Brokerage",
            "type":"Services"
        }
    ],
    "sg:phone":"+44 20 7283 2241",
    "sg:postcode":"EC3A 6AP",
    "sg:province":"Greater London",
    "wof:name":"Close Residential Funding Ltd.",
    "wof:placetype":"venue"
},
  "geometry": {"coordinates":[-0.0824500024,51.5146484375],"type":"Point"}
}