{
  "type": "Feature",
  "properties": {
    "addr:full":"19 Coronation Crescent Crewe Cheshire CW1 4EP",
    "addr:housenumber":"19",
    "addr:postcode":"cw1 4ep",
    "addr:street":"Coronation Crescent",
    "iso:country":"GB",
    "sg:address":"19 Coronation Crescent",
    "sg:city":"Crewe",
    "sg:classifiers":[
        {
            "category":"Shopping",
            "subcategory":"Pets & Pet Supplies",
            "type":"Retail Goods"
        }
    ],
    "sg:phone":"+44 1270 588248",
    "sg:postcode":"CW1 4EP",
    "sg:province":"Cheshire",
    "wof:name":"Coronation Pets",
    "wof:placetype":"venue"
},
  "geometry": {"coordinates":[-2.4334640503,53.1066169739],"type":"Point"}
}