{
  "type": "Feature",
  "properties": {
    "iso:country":"GB",
    "sg:address":"Willow La",
    "sg:city":"Lancaster",
    "sg:classifiers":[
        {
            "category":"Freight",
            "type":"Transportation"
        }
    ],
    "sg:phone":"+44 1524 382910",
    "sg:postcode":"LA1 5NA",
    "sg:province":"Lancashire",
    "sg:tags":[
        "haulage",
        "road"
    ],
    "wof:name":"Sailor Haulage",
    "wof:placetype":"venue"
},
  "geometry": {"coordinates":[-2.8133740425,54.0505104065],"type":"Point"}
}