{
  "type": "Feature",
  "properties": {
    "addr:full":"Mealbank Mill Industrial Estate, Mealbank Kendal Cumbria LA8 9DL",
    "addr:postcode":"la8 9dl",
    "addr:street":"Estate Mealbank",
    "iso:country":"GB",
    "sg:address":"Mealbank Mill Industrial Estate, Mealbank",
    "sg:city":"Kendal",
    "sg:classifiers":[
        {
            "category":"Shopping",
            "subcategory":"Clothing, Apparel, & Fashions",
            "type":"Retail Goods"
        },
        {
            "category":"Shopping",
            "subcategory":"Catalog Store",
            "type":"Retail Goods"
        }
    ],
    "sg:postcode":"LA8 9DL",
    "sg:province":"Cumbria",
    "sg:tags":[
        "house",
        "order",
        "clothing",
        "fabric",
        "mail"
    ],
    "wof:name":"THE TARTAN WEAVERS",
    "wof:placetype":"venue"
},
  "geometry": {"coordinates":[-2.7111339569,54.353553772],"type":"Point"}
}