{
  "type": "Feature",
  "properties": {
    "addr:full":"7 Sea Road Felixstowe Suffolk IP11 2AU",
    "addr:housenumber":"7",
    "addr:postcode":"ip11 2au",
    "addr:street":"Sea Road",
    "iso:country":"GB",
    "sg:address":"7 Sea Road",
    "sg:city":"Felixstowe",
    "sg:classifiers":[
        {
            "category":"Bars & Pubs",
            "subcategory":"Nightclub",
            "type":"Food & Drink"
        }
    ],
    "sg:postcode":"IP11 2AU",
    "sg:province":"Suffolk",
    "sg:tags":[
        "club",
        "night"
    ],
    "wof:name":"La Plage",
    "wof:placetype":"venue"
},
  "geometry": {"coordinates":[1.343372941,51.9572601318],"type":"Point"}
}