{
  "type": "Feature",
  "properties": {
    "iso:country":"GB",
    "sg:address":"7 Central Parade, Green Street",
    "sg:city":"Enfield",
    "sg:classifiers":[
        {
            "category":"Fast Food",
            "type":"Food & Drink"
        }
    ],
    "sg:phone":"+44 20 8804 7297",
    "sg:postcode":"EN3 7HG",
    "sg:province":"Greater London",
    "sg:tags":[
        "away",
        "meal",
        "outlet",
        "take"
    ],
    "wof:name":"New Golden World",
    "wof:placetype":"venue"
},
  "geometry": {"coordinates":[-0.0464879982,51.6567611694],"type":"Point"}
}