{
  "type": "Feature",
  "properties": {
    "iso:country":"GB",
    "sg:address":"76 Milford Street",
    "sg:city":"Salisbury",
    "sg:classifiers":[
        {
            "category":"Banks & Credit Unions",
            "subcategory":"Financial Services",
            "type":"Services"
        }
    ],
    "sg:phone":"+44 1722 336463",
    "sg:postcode":"SP1 2BS",
    "sg:province":"Wiltshire",
    "sg:tags":[
        "consultant"
    ],
    "wof:name":"London Scottish Finance Ltd.",
    "wof:placetype":"venue"
},
  "geometry": {"coordinates":[-1.789729,51.068233],"type":"Point"}
}