{
  "type": "Feature",
  "properties": {
    "addr:full":"47 Hauksbee Gdns, Shenley Lodge Milton Keynes Buckinghamshire MK5 7EF",
    "addr:housenumber":"47;shenley",
    "addr:postcode":"mk5 7ef",
    "addr:street":"Hauksbee Gdns",
    "iso:country":"GB",
    "sg:address":"47 Hauksbee Gdns, Shenley Lodge",
    "sg:city":"Milton Keynes",
    "sg:classifiers":[
        {
            "category":"Shopping",
            "subcategory":"Department Store",
            "type":"Retail Goods"
        }
    ],
    "sg:postcode":"MK5 7EF",
    "sg:province":"Buckinghamshire",
    "wof:name":"Whichcraft",
    "wof:placetype":"venue"
},
  "geometry": {"coordinates":[-0.7705100179,52.0176315308],"type":"Point"}
}