{
  "type": "Feature",
  "properties": {
    "addr:full":"14 St. Lukes Mews Notting Hill Greater London W11 1DF",
    "addr:housenumber":"14",
    "addr:postcode":"w11 1df",
    "addr:street":"St. Lukes Mews",
    "iso:country":"GB",
    "sg:address":"14 St. Lukes Mews",
    "sg:city":"Notting Hill",
    "sg:classifiers":[
        {
            "category":"Wholesale",
            "subcategory":"Music Publishers",
            "type":"Manufacturing & Wholesale Goods"
        }
    ],
    "sg:phone":"+44 20 7229 9906",
    "sg:postcode":"W11 1DF",
    "sg:province":"Greater London",
    "sg:tags":[
        "record"
    ],
    "wof:name":"Italica Records",
    "wof:placetype":"venue"
},
  "geometry": {"coordinates":[-0.2027509958,51.5180587769],"type":"Point"}
}