{
  "type": "Feature",
  "properties": {
    "iso:country":"GB",
    "sg:address":"C/0 Leisure Travel, The Yard",
    "sg:city":"Bristol",
    "sg:classifiers":[
        {
            "category":"Military Area",
            "subcategory":"Air Force Base",
            "type":"Public Place"
        }
    ],
    "sg:phone":"+44 117 969 6799",
    "sg:postcode":"BS34 6LR",
    "sg:province":"Gloucestershire",
    "sg:tags":[
        "taxi",
        "hire",
        "private"
    ],
    "wof:name":"Patchway Taxis",
    "wof:placetype":"venue"
},
  "geometry": {"coordinates":[-2.5628700256,51.5269889832],"type":"Point"}
}