{
  "type": "Feature",
  "properties": {
    "addr:full":"Nailsea Wall Clevedon Somerset BS21 6UE",
    "addr:postcode":"bs21 6ue",
    "iso:country":"GB",
    "sg:address":"Nailsea Wall",
    "sg:city":"Clevedon",
    "sg:classifiers":[
        {
            "category":"Professional",
            "subcategory":"Engineering",
            "type":"Services"
        }
    ],
    "sg:phone":"+44 1275 875338",
    "sg:postcode":"BS21 6UE",
    "sg:province":"Somerset",
    "sg:tags":[
        "civil",
        "engineer"
    ],
    "wof:name":"Ritchies",
    "wof:placetype":"venue"
},
  "geometry": {"coordinates":[-2.826319,51.423561],"type":"Point"}
}