{
  "type": "Feature",
  "properties": {
    "iso:country":"GB",
    "sg:address":"Lance Levy Farm, Sherfield-on-loddon, Hook",
    "sg:city":"Basingstoke",
    "sg:classifiers":[
        {
            "category":"Farming",
            "subcategory":"Farm",
            "type":"Manufacturing & Wholesale Goods"
        }
    ],
    "sg:phone":"+44 1256 882228",
    "sg:postcode":"RG27 0HB",
    "sg:province":"Berkshire",
    "sg:tags":[
        "mixed",
        "crop"
    ],
    "wof:name":"J & D Bowden",
    "wof:placetype":"venue"
},
  "geometry": {"coordinates":[-1.0092200041,51.3098716736],"type":"Point"}
}