{
  "type": "Feature",
  "properties": {
    "addr:full":"303 Stocks Place London Greater London E14 8AE",
    "addr:housenumber":"303",
    "addr:postcode":"e14 8ae",
    "addr:street":"Stocks Place",
    "iso:country":"GB",
    "sg:address":"303 Stocks Place",
    "sg:city":"London",
    "sg:classifiers":[
        {
            "category":"Shopping",
            "subcategory":"Department Store",
            "type":"Retail Goods"
        }
    ],
    "sg:phone":"+44 20 7987 5421",
    "sg:postcode":"E14 8AE",
    "sg:province":"Greater London",
    "wof:name":"Junes Stores",
    "wof:placetype":"venue"
},
  "geometry": {"coordinates":[-0.028198,51.5101394653],"type":"Point"}
}