{
  "type": "Feature",
  "properties": {
    "iso:country":"GB",
    "sg:address":"12 New Parks Crescent",
    "sg:city":"Scarborough",
    "sg:classifiers":[
        {
            "category":"Social Services",
            "subcategory":"Retirement Home",
            "type":"Services"
        }
    ],
    "sg:postcode":"YO12 5JZ",
    "sg:province":"North Yorkshire",
    "sg:tags":[
        "residential",
        "care"
    ],
    "wof:name":"Beechwood Rest Home",
    "wof:placetype":"venue"
},
  "geometry": {"coordinates":[-0.413655,54.276066],"type":"Point"}
}