{
  "type": "Feature",
  "properties": {
    "iso:country":"GB",
    "sg:address":"9 Bultitudes Loke, Caister-on-sea",
    "sg:city":"Great Yarmouth",
    "sg:classifiers":[
        {
            "category":"Recreation",
            "subcategory":"Campground",
            "type":"Entertainment"
        }
    ],
    "sg:phone":"+44 1493 720382",
    "sg:postcode":"NR30 5DH",
    "sg:province":"Norfolk",
    "sg:tags":[
        "caravan",
        "park"
    ],
    "wof:name":"Grasmere Caravan Park",
    "wof:placetype":"venue"
},
  "geometry": {"coordinates":[1.72399,52.612415],"type":"Point"}
}