{
  "type": "Feature",
  "properties": {
    "iso:country":"GB",
    "sg:address":"Manor Road",
    "sg:city":"Blackburn",
    "sg:classifiers":[
        {
            "category":"Education",
            "subcategory":"School",
            "type":"Public Place"
        }
    ],
    "sg:phone":"+44 1254 667449",
    "sg:postcode":"BB2 6LX",
    "sg:province":"Lancashire",
    "sg:tags":[
        "local",
        "authority"
    ],
    "wof:name":"Wensley Fold C of E Primary School",
    "wof:placetype":"venue"
},
  "geometry": {"coordinates":[-2.5073170662,53.7497520447],"type":"Point"}
}