{
  "type": "Feature",
  "properties": {
    "addr:full":"Manor House, Brampton Bryan Bucknell Herefordshire SY7 0DH",
    "addr:postcode":"sy7 0dh",
    "addr:street":"Manor",
    "iso:country":"GB",
    "sg:address":"Manor House, Brampton Bryan",
    "sg:city":"Bucknell",
    "sg:classifiers":[
        {
            "category":"Wholesale",
            "subcategory":"Apparel",
            "type":"Manufacturing & Wholesale Goods"
        }
    ],
    "sg:phone":"+44 1547 530888",
    "sg:postcode":"SY7 0DH",
    "sg:province":"Herefordshire",
    "sg:tags":[
        "babywear",
        "childrens"
    ],
    "wof:name":"Ready Freddie Co. Ltd.",
    "wof:placetype":"venue"
},
  "geometry": {"coordinates":[-2.945099,52.359005],"type":"Point"}
}