{
  "type": "Feature",
  "properties": {
    "iso:country":"GB",
    "sg:address":"44 Ashingdon Rd",
    "sg:city":"Rochford",
    "sg:classifiers":[
        {
            "category":"Shopping",
            "subcategory":"Department Store",
            "type":"Retail Goods"
        }
    ],
    "sg:phone":"+44 1702 545111",
    "sg:postcode":"SS4 1RD",
    "sg:province":"Essex",
    "wof:name":"Dalys Store",
    "wof:placetype":"venue"
},
  "geometry": {"coordinates":[0.700292,51.587025],"type":"Point"}
}