{
  "type": "Feature",
  "properties": {
    "addr:full":"St Peters Sq Ruthin Denbighshire LL15 1DW",
    "addr:postcode":"ll15 1dw",
    "addr:street":"St Peters Sq",
    "iso:country":"GB",
    "sg:address":"St Peters Sq",
    "sg:city":"Ruthin",
    "sg:classifiers":[
        {
            "category":"Banks & Credit Unions",
            "subcategory":"Bank",
            "type":"Services"
        }
    ],
    "sg:phone":"+44 1824 702009",
    "sg:postcode":"LL15 1DW",
    "sg:province":"Denbighshire",
    "wof:name":"NatWest",
    "wof:placetype":"venue"
},
  "geometry": {"coordinates":[-3.3108038902,53.1147155762],"type":"Point"}
}