{
  "type": "Feature",
  "properties": {
    "iso:country":"GB",
    "sg:address":"20 Forth Street",
    "sg:city":"North Berwick",
    "sg:classifiers":[
        {
            "category":"Personal",
            "subcategory":"Beauty Salon",
            "type":"Services"
        },
        {
            "category":"Personal",
            "subcategory":"Barber",
            "type":"Services"
        }
    ],
    "sg:phone":"+44 1620 893055",
    "sg:postcode":"EH39 4HY",
    "sg:province":"East Lothian",
    "sg:tags":[
        "unisex",
        "hairdresser"
    ],
    "wof:name":"Images",
    "wof:placetype":"venue"
},
  "geometry": {"coordinates":[-2.7188260555,56.0592803955],"type":"Point"}
}