{
  "type": "Feature",
  "properties": {
    "addr:full":"38-42 Chelsea Road Bristol City of Bristol BS5 6AF",
    "addr:housenumber":"38-42",
    "addr:postcode":"bs5 6af",
    "addr:street":"Chelsea Road",
    "iso:country":"GB",
    "sg:address":"38-42 Chelsea Road",
    "sg:city":"Bristol",
    "sg:classifiers":[
        {
            "category":"Social Services",
            "subcategory":"Job Training",
            "type":"Services"
        }
    ],
    "sg:phone":"+44 117 941 1908",
    "sg:postcode":"BS5 6AF",
    "sg:province":"City of Bristol",
    "sg:tags":[
        "translator",
        "interpreter"
    ],
    "wof:name":"In Your Own Language Ltd.",
    "wof:placetype":"venue"
},
  "geometry": {"coordinates":[-2.5629,51.463451],"type":"Point"}
}