{
  "type": "Feature",
  "properties": {
    "addr:full":"King Street Bakewell Derbyshire DE45 1DZ",
    "addr:postcode":"de45 1dz",
    "addr:street":"King Street",
    "iso:country":"GB",
    "sg:address":"King Street",
    "sg:city":"Bakewell",
    "sg:classifiers":[
        {
            "category":"Travel",
            "subcategory":"Travel Agent",
            "type":"Entertainment"
        }
    ],
    "sg:phone":"+44 1629 814949",
    "sg:postcode":"DE45 1DZ",
    "sg:province":"Derbyshire",
    "sg:tags":[
        "hotel",
        "agency",
        "booking"
    ],
    "wof:name":"Hotel Focus",
    "wof:placetype":"venue"
},
  "geometry": {"coordinates":[-1.676284,53.212673],"type":"Point"}
}