{
  "type": "Feature",
  "properties": {
    "iso:country":"GB",
    "sg:address":"94 Simmons Way, Lane End",
    "sg:city":"High Wycombe",
    "sg:classifiers":[
        {
            "category":"Professional",
            "subcategory":"Art Services",
            "type":"Services"
        },
        {
            "category":"Building & Trades",
            "subcategory":"Construction",
            "type":"Services"
        }
    ],
    "sg:postcode":"HP14 3JX",
    "sg:province":"Buckinghamshire",
    "sg:tags":[
        "glazier",
        "decorator",
        "painter"
    ],
    "wof:name":"Rex A Judge",
    "wof:placetype":"venue"
},
  "geometry": {"coordinates":[-0.8272650242,51.6205406189],"type":"Point"}
}