{
  "type": "Feature",
  "properties": {
    "iso:country":"GB",
    "sg:address":"P O Box 34090",
    "sg:city":"London",
    "sg:classifiers":[
        {
            "category":"Shopping",
            "subcategory":"Clothing, Apparel, & Fashions",
            "type":"Retail Goods"
        },
        {
            "category":"Professional",
            "subcategory":"Business Services",
            "type":"Services"
        }
    ],
    "sg:phone":"+44 20 8364 2356",
    "sg:postcode":"N21 2XA",
    "sg:province":"Greater London",
    "sg:tags":[
        "distribution",
        "ladieswear"
    ],
    "wof:name":"European Transport Services Ltd.",
    "wof:placetype":"venue"
},
  "geometry": {"coordinates":[-0.091114,51.639187],"type":"Point"}
}