{
  "type": "Feature",
  "properties": {
    "addr:full":"Langbridge Farm, Thornton Road, Nash Milton Keynes Bedfordshire MK17 0HL",
    "addr:postcode":"mk17 0hl",
    "addr:street":"Thornton Road",
    "iso:country":"GB",
    "sg:address":"Langbridge Farm, Thornton Road, Nash",
    "sg:city":"Milton Keynes",
    "sg:classifiers":[
        {
            "category":"Home & Garden",
            "subcategory":"Hardware",
            "type":"Retail Goods"
        }
    ],
    "sg:phone":"+44 1296 714523",
    "sg:postcode":"MK17 0HL",
    "sg:province":"Bedfordshire",
    "sg:tags":[
        "device",
        "fixing",
        "fastener"
    ],
    "wof:name":"High Kit",
    "wof:placetype":"venue"
},
  "geometry": {"coordinates":[-0.8613,51.999619],"type":"Point"}
}