{
  "type": "Feature",
  "properties": {
    "addr:full":"152 Balls Pond Road London Greater London N1 4AD",
    "addr:housenumber":"152",
    "addr:postcode":"n1 4ad",
    "addr:street":"Balls Pond Road",
    "iso:country":"GB",
    "sg:address":"152 Balls Pond Road",
    "sg:city":"London",
    "sg:classifiers":[
        {
            "category":"Professional",
            "subcategory":"Business Services",
            "type":"Services"
        }
    ],
    "sg:postcode":"N1 4AD",
    "sg:province":"Greater London",
    "sg:tags":[
        "bookmaker"
    ],
    "wof:name":"K Johnson",
    "wof:placetype":"venue"
},
  "geometry": {"coordinates":[-0.084987,51.546684],"type":"Point"}
}