{
  "type": "Feature",
  "properties": {
    "iso:country":"GB",
    "sg:address":"15 Hindley Road",
    "sg:city":"Liversedge",
    "sg:classifiers":[
        {
            "category":"Retail",
            "subcategory":"Driving School",
            "type":"Services"
        }
    ],
    "sg:phone":"+44 1924 402310",
    "sg:postcode":"WF15 7DQ",
    "sg:province":"West Yorkshire",
    "wof:name":"Avondale School Of Driving",
    "wof:placetype":"venue"
},
  "geometry": {"coordinates":[-1.6910619736,53.7066993713],"type":"Point"}
}