{
  "type": "Feature",
  "properties": {
    "addr:full":"73-79 Balham High Road London Greater London SW12 9AP",
    "addr:housenumber":"73-79",
    "addr:postcode":"sw12 9ap",
    "addr:street":"Balham High Road",
    "iso:country":"GB",
    "sg:address":"73-79 Balham High Road",
    "sg:city":"London",
    "sg:classifiers":[
        {
            "category":"Autos & Motor Vehicles",
            "subcategory":"Automobile Sales",
            "type":"Retail Goods"
        }
    ],
    "sg:phone":"+44 20 8675 9223",
    "sg:postcode":"SW12 9AP",
    "sg:province":"Greater London",
    "sg:tags":[
        "car"
    ],
    "wof:name":"Bee Gee Autos",
    "wof:placetype":"venue"
},
  "geometry": {"coordinates":[-0.1499930024,51.4458198547],"type":"Point"}
}