{
  "type": "Feature",
  "properties": {
    "iso:country":"GB",
    "sg:address":"11 Crawford Crescent, Blantyre",
    "sg:city":"Glasgow",
    "sg:classifiers":[
        {
            "category":"Personal",
            "type":"Services"
        }
    ],
    "sg:phone":"+44 1698 827004",
    "sg:postcode":"G72 9DR",
    "sg:province":"South Lanarkshire",
    "sg:tags":[
        "wedding"
    ],
    "wof:name":"Viking Video",
    "wof:placetype":"venue"
},
  "geometry": {"coordinates":[-4.095887,55.797527],"type":"Point"}
}