{
  "type": "Feature",
  "properties": {
    "iso:country":"GB",
    "sg:address":"236 Worsley Rd, Swinton",
    "sg:city":"Manchester",
    "sg:classifiers":[
        {
            "category":"Building & Trades",
            "subcategory":"Construction",
            "type":"Services"
        }
    ],
    "sg:phone":"+44 161 793 9423",
    "sg:postcode":"M27 0YF",
    "sg:province":"Greater Manchester",
    "sg:tags":[
        "dry",
        "lining",
        "plasterers",
        "screeders"
    ],
    "wof:name":"Alan Bates",
    "wof:placetype":"venue"
},
  "geometry": {"coordinates":[-2.346241,53.503979],"type":"Point"}
}