{
  "type": "Feature",
  "properties": {
    "iso:country":"GB",
    "sg:address":"291 Brighton Road",
    "sg:city":"South Croydon",
    "sg:classifiers":[
        {
            "category":"Insurance",
            "subcategory":"Insurance Agent",
            "type":"Services"
        }
    ],
    "sg:phone":"+44 20 8686 7626",
    "sg:postcode":"CR2 6EQ",
    "sg:province":"Surrey",
    "sg:tags":[
        "broker"
    ],
    "wof:name":"Lifelong Insurance Brokers",
    "wof:placetype":"venue"
},
  "geometry": {"coordinates":[-0.098106,51.352505],"type":"Point"}
}