{
  "type": "Feature",
  "properties": {
    "addr:full":"44 Westfield Rd Wells Somerset BA5 2HS",
    "addr:housenumber":"44",
    "addr:postcode":"ba5 2hs",
    "addr:street":"Westfield Rd",
    "iso:country":"GB",
    "sg:address":"44 Westfield Rd",
    "sg:city":"Wells",
    "sg:classifiers":[
        {
            "category":"Manufacturing",
            "subcategory":"Textiles",
            "type":"Manufacturing & Wholesale Goods"
        }
    ],
    "sg:phone":"+44 1749 670555",
    "sg:postcode":"BA5 2HS",
    "sg:province":"Somerset",
    "sg:tags":[
        "made-up"
    ],
    "wof:name":"The Bed Shop",
    "wof:placetype":"venue"
},
  "geometry": {"coordinates":[-2.655239,51.20866],"type":"Point"}
}