{
  "type": "Feature",
  "properties": {
    "addr:full":"36 Cowley Hill Lane St Helens Merseyside WA10 2AD",
    "addr:housenumber":"36",
    "addr:postcode":"wa10 2ad",
    "addr:street":"Cowley Hill Lane",
    "iso:country":"GB",
    "sg:address":"36 Cowley Hill Lane",
    "sg:city":"St Helens",
    "sg:classifiers":[
        {
            "category":"Retail",
            "subcategory":"Storage",
            "type":"Services"
        }
    ],
    "sg:phone":"+44 1744 21181",
    "sg:postcode":"WA10 2AD",
    "sg:province":"Merseyside",
    "sg:tags":[
        "household",
        "removal"
    ],
    "wof:name":"Denhome Removals",
    "wof:placetype":"venue"
},
  "geometry": {"coordinates":[-2.745431,53.45871],"type":"Point"}
}