{
  "type": "Feature",
  "properties": {
    "addr:full":"279 Deansgate Manchester Greater Manchester M3 4EW",
    "addr:housenumber":"279",
    "addr:postcode":"m3 4ew",
    "addr:street":"Deansgate",
    "iso:country":"GB",
    "sg:address":"279 Deansgate",
    "sg:city":"Manchester",
    "sg:classifiers":[
        {
            "category":"Professional",
            "subcategory":"Detective & Security Services",
            "type":"Services"
        }
    ],
    "sg:phone":"+44 161 834 5556",
    "sg:postcode":"M3 4EW",
    "sg:province":"Greater Manchester",
    "sg:tags":[
        "locksmith"
    ],
    "wof:name":"Key Lock & Safe (MCr) Ltd",
    "wof:placetype":"venue"
},
  "geometry": {"coordinates":[-2.250471,53.47641],"type":"Point"}
}