{
  "type": "Feature",
  "properties": {
    "iso:country":"GB",
    "sg:address":"5 Main Street, Mochrum",
    "sg:city":"Newton Stewart",
    "sg:classifiers":[
        {
            "category":"Government",
            "subcategory":"Post Office",
            "type":"Public Place"
        }
    ],
    "sg:postcode":"DG8 9LY",
    "sg:province":"Dumfries and Galloway",
    "wof:name":"G & I McCaig",
    "wof:placetype":"venue"
},
  "geometry": {"coordinates":[-4.6108131409,54.7943115234],"type":"Point"}
}