{
  "type": "Feature",
  "properties": {
    "iso:country":"GB",
    "sg:address":"John Street West",
    "sg:city":"Ashton-under-lyne",
    "sg:classifiers":[
        {
            "category":"Autos & Motor Vehicles",
            "subcategory":"Boat Sales",
            "type":"Retail Goods"
        },
        {
            "category":"Manufacturing",
            "subcategory":"Building Materials",
            "type":"Manufacturing & Wholesale Goods"
        }
    ],
    "sg:phone":"+44 161 339 6302",
    "sg:postcode":"OL7 0NY",
    "sg:province":"Greater Manchester",
    "sg:tags":[
        "door",
        "supp",
        "grille",
        "shutter",
        "roller",
        "manufacturer"
    ],
    "wof:name":"Combat Doors Ltd",
    "wof:placetype":"venue"
},
  "geometry": {"coordinates":[-2.1105239391,53.4774894714],"type":"Point"}
}