{
  "type": "Feature",
  "properties": {
    "addr:full":"7 Post Office Road Bournemouth Dorset BH1 1BB",
    "addr:housenumber":"7",
    "addr:postcode":"bh1 1bb",
    "addr:street":"Post Office Road",
    "iso:country":"GB",
    "sg:address":"7 Post Office Road",
    "sg:city":"Bournemouth",
    "sg:classifiers":[
        {
            "category":"Fast Food",
            "type":"Food & Drink"
        }
    ],
    "sg:phone":"+44 1202 292132",
    "sg:postcode":"BH1 1BB",
    "sg:province":"Dorset",
    "sg:tags":[
        "away",
        "meal",
        "outlet",
        "take"
    ],
    "wof:name":"Lord Sandwich",
    "wof:placetype":"venue"
},
  "geometry": {"coordinates":[-1.878161,50.72052],"type":"Point"}
}