{
  "type": "Feature",
  "properties": {
    "iso:country":"GB",
    "sg:address":"161 Lumb Lane",
    "sg:city":"Bradford",
    "sg:classifiers":[
        {
            "category":"Health Services",
            "subcategory":"Doctor",
            "type":"Services"
        },
        {
            "category":"Professional",
            "subcategory":"Testing Lab",
            "type":"Services"
        }
    ],
    "sg:phone":"+44 1274 734994",
    "sg:postcode":"BD8 7SW",
    "sg:province":"West Yorkshire",
    "sg:tags":[
        "pregnancy",
        "practitioners"
    ],
    "wof:name":"Munir A Khan",
    "wof:placetype":"venue"
},
  "geometry": {"coordinates":[-1.765384,53.803471],"type":"Point"}
}