{
  "type": "Feature",
  "properties": {
    "iso:country":"GB",
    "sg:address":"19 Wallsgreen Road, Cardenden",
    "sg:city":"Lochgelly",
    "sg:classifiers":[
        {
            "category":"Education",
            "subcategory":"Special Training",
            "type":"Public Place"
        }
    ],
    "sg:postcode":"KY5 0JF",
    "sg:province":"Fife",
    "sg:tags":[
        "product",
        "centre"
    ],
    "wof:name":"Scotvec Training & Assessment Centre",
    "wof:placetype":"venue"
},
  "geometry": {"coordinates":[-3.265616,56.146053],"type":"Point"}
}