{
  "type": "Feature",
  "properties": {
    "addr:full":"47 South Clerk Street Edinburgh City of Edinburgh EH8 9NZ",
    "addr:housenumber":"47",
    "addr:postcode":"eh8 9nz",
    "addr:street":"South Clerk Street",
    "iso:country":"GB",
    "sg:address":"47 South Clerk Street",
    "sg:city":"Edinburgh",
    "sg:classifiers":[
        {
            "category":"Fast Food",
            "type":"Food & Drink"
        }
    ],
    "sg:phone":"+44 131 668 1171",
    "sg:postcode":"EH8 9NZ",
    "sg:province":"City of Edinburgh",
    "sg:tags":[
        "away",
        "take"
    ],
    "wof:name":"Chilli Connection",
    "wof:placetype":"venue"
},
  "geometry": {"coordinates":[-3.1806271076,55.9408035278],"type":"Point"}
}