{
  "type": "Feature",
  "properties": {
    "iso:country":"GB",
    "sg:address":"65 Buckingham Street",
    "sg:city":"Aylesbury",
    "sg:classifiers":[
        {
            "category":"Real Estate",
            "subcategory":"Real Estate Agent",
            "type":"Services"
        }
    ],
    "sg:phone":"+44 1296 399300",
    "sg:postcode":"HP20 2NF",
    "sg:province":"Buckinghamshire",
    "wof:name":"Steve Holden",
    "wof:placetype":"venue"
},
  "geometry": {"coordinates":[-0.814855,51.819492],"type":"Point"}
}