{
  "type": "Feature",
  "properties": {
    "addr:full":"44 High Street Yarm North Yorkshire TS15 9AE",
    "addr:housenumber":"44",
    "addr:postcode":"ts15 9ae",
    "addr:street":"High Street",
    "iso:country":"GB",
    "sg:address":"44 High Street",
    "sg:city":"Yarm",
    "sg:classifiers":[
        {
            "category":"Shopping",
            "subcategory":"Baby Store",
            "type":"Retail Goods"
        }
    ],
    "sg:phone":"+44 1642 790000",
    "sg:postcode":"TS15 9AE",
    "sg:province":"North Yorkshire",
    "sg:tags":[
        "babywear",
        "childrens"
    ],
    "wof:name":"Poppy Ltd.",
    "wof:placetype":"venue"
},
  "geometry": {"coordinates":[-1.354107976,54.5089378357],"type":"Point"}
}