{
  "type": "Feature",
  "properties": {
    "addr:full":"Oakleys Farm, Maiden Street, Weston Hitchin Hertfordshire SG4 7DQ",
    "addr:postcode":"sg4 7dq",
    "addr:street":"Maiden Street",
    "iso:country":"GB",
    "sg:address":"Oakleys Farm, Maiden Street, Weston",
    "sg:city":"Hitchin",
    "sg:classifiers":[
        {
            "category":"Manufacturing",
            "subcategory":"Metals",
            "type":"Manufacturing & Wholesale Goods"
        }
    ],
    "sg:phone":"+44 1462 790648",
    "sg:postcode":"SG4 7DQ",
    "sg:province":"Hertfordshire",
    "sg:tags":[
        "steel",
        "fabricator",
        "erectors"
    ],
    "wof:name":"Weston Forge",
    "wof:placetype":"venue"
},
  "geometry": {"coordinates":[-0.167553,51.956005],"type":"Point"}
}