{
  "type": "Feature",
  "properties": {
    "addr:full":"138 West Road Newcastle-upon-tyne Tyne and Wear NE4 9QA",
    "addr:housenumber":"138",
    "addr:postcode":"ne4 9qa",
    "addr:street":"West Road",
    "iso:country":"GB",
    "sg:address":"138 West Road",
    "sg:city":"Newcastle-upon-tyne",
    "sg:classifiers":[
        {
            "category":"Shopping",
            "subcategory":"Pawn Shop",
            "type":"Retail Goods"
        }
    ],
    "sg:phone":"+44 191 273 2348",
    "sg:postcode":"NE4 9QA",
    "sg:province":"Tyne and Wear",
    "sg:tags":[
        "pawnbroker"
    ],
    "wof:name":"Albemarle & Bond Pawnbrokers Ltd.",
    "wof:placetype":"venue"
},
  "geometry": {"coordinates":[-1.655427,54.976116],"type":"Point"}
}