{
  "type": "Feature",
  "properties": {
    "iso:country":"GB",
    "sg:address":"67-69 Eastwood Rd",
    "sg:city":"Rayleigh",
    "sg:classifiers":[
        {
            "category":"Professional",
            "subcategory":"Lawyer & Legal Services",
            "type":"Services"
        }
    ],
    "sg:phone":"+44 1268 779900",
    "sg:postcode":"SS6 7JN",
    "sg:province":"Essex",
    "sg:tags":[
        "advice",
        "counselling"
    ],
    "wof:name":"Olive Tree Centre The",
    "wof:placetype":"venue"
},
  "geometry": {"coordinates":[0.608282,51.583759],"type":"Point"}
}