{
  "type": "Feature",
  "properties": {
    "addr:full":"Sapcote Road Industrial Estate Hinckley Leicestershire LE10 2AU",
    "addr:postcode":"le10 2au",
    "addr:street":"Sapcote Road Industrial Estate",
    "iso:country":"GB",
    "sg:address":"Sapcote Road Industrial Estate",
    "sg:city":"Hinckley",
    "sg:classifiers":[
        {
            "category":"Home & Garden",
            "subcategory":"Building Materials",
            "type":"Retail Goods"
        }
    ],
    "sg:phone":"+44 1455 613844",
    "sg:postcode":"LE10 2AU",
    "sg:province":"Leicestershire",
    "sg:tags":[
        "gate",
        "door",
        "barrier"
    ],
    "wof:name":"Burbage Gates Ltd.",
    "wof:placetype":"venue"
},
  "geometry": {"coordinates":[-1.341177,52.536545],"type":"Point"}
}