{
  "type": "Feature",
  "properties": {
    "iso:country":"GB",
    "sg:address":"16 Howes Drive",
    "sg:city":"Aberdeen",
    "sg:classifiers":[
        {
            "category":"Professional",
            "subcategory":"Detective & Security Services",
            "type":"Services"
        }
    ],
    "sg:phone":"+44 1224 690019",
    "sg:postcode":"AB16 7EH",
    "sg:province":"Aberdeen City",
    "sg:tags":[
        "agency",
        "activity"
    ],
    "wof:name":"Shield Investigation Services Ltd",
    "wof:placetype":"venue"
},
  "geometry": {"coordinates":[-2.1659460068,57.1710357666],"type":"Point"}
}