{
  "type": "Feature",
  "properties": {
    "addr:full":"The Gatehouse, Knowle Lane, Meltham Huddersfield West Yorkshire HD7 3DS",
    "addr:postcode":"hd7 3ds",
    "addr:street":"Knowle Lane;West",
    "iso:country":"GB",
    "sg:address":"The Gatehouse, Knowle Lane, Meltham",
    "sg:city":"Huddersfield",
    "sg:classifiers":[
        {
            "category":"Professional",
            "subcategory":"Computer Services",
            "type":"Services"
        }
    ],
    "sg:phone":"+44 1484 854545",
    "sg:postcode":"HD7 3DS",
    "sg:province":"West Yorkshire",
    "sg:tags":[
        "system",
        "software"
    ],
    "wof:name":"Testhys Ltd",
    "wof:placetype":"venue"
},
  "geometry": {"coordinates":[-1.78268,53.64695],"type":"Point"}
}