{
  "type": "Feature",
  "properties": {
    "addr:full":"26 Porthamal Rd Cardiff Cardiff CF4 6AR",
    "addr:housenumber":"26",
    "addr:postcode":"cf4 6ar",
    "addr:street":"Porthamal Rd",
    "iso:country":"GB",
    "sg:address":"26 Porthamal Rd",
    "sg:city":"Cardiff",
    "sg:classifiers":[
        {
            "category":"Home & Garden",
            "subcategory":"Carpets & Floor Coverings",
            "type":"Retail Goods"
        }
    ],
    "sg:phone":"+44 29 2061 0640",
    "sg:postcode":"CF4 6AR",
    "sg:province":"Cardiff",
    "sg:tags":[
        "wall",
        "tie",
        "replacement"
    ],
    "wof:name":"Britannia Wall Tie",
    "wof:placetype":"venue"
},
  "geometry": {"coordinates":[-3.2066171169,51.5207328796],"type":"Point"}
}