{
  "type": "Feature",
  "properties": {
    "iso:country":"GB",
    "sg:address":"24 St John St",
    "sg:city":"Birkenhead",
    "sg:classifiers":[
        {
            "category":"Bars & Pubs",
            "type":"Food & Drink"
        }
    ],
    "sg:phone":"+44 151 647 6095",
    "sg:postcode":"L41 6HY",
    "sg:province":"Merseyside",
    "sg:tags":[
        "pubs",
        "inn"
    ],
    "wof:name":"Garrick Snug The",
    "wof:placetype":"venue"
},
  "geometry": {"coordinates":[-3.026167,53.390015],"type":"Point"}
}