{
  "type": "Feature",
  "properties": {
    "addr:full":"5 Gt. Brockeridge Bristol City of Bristol BS9 3TY",
    "addr:housenumber":"5",
    "addr:postcode":"bs9 3ty",
    "addr:street":"Gt. Brockeridge",
    "iso:country":"GB",
    "sg:address":"5 Gt. Brockeridge",
    "sg:city":"Bristol",
    "sg:classifiers":[
        {
            "category":"Professional",
            "subcategory":"Management & Consulting",
            "type":"Services"
        }
    ],
    "sg:postcode":"BS9 3TY",
    "sg:province":"City of Bristol",
    "sg:tags":[
        "marketing",
        "consultant"
    ],
    "wof:name":"Triangle Marketing",
    "wof:placetype":"venue"
},
  "geometry": {"coordinates":[-2.619274,51.486496],"type":"Point"}
}