{
  "type": "Feature",
  "properties": {
    "addr:full":"99 Allendale Av Nottingham Nottinghamshire NG8 5RF",
    "addr:housenumber":"99",
    "addr:postcode":"ng8 5rf",
    "addr:street":"Allendale Av",
    "iso:country":"GB",
    "sg:address":"99 Allendale Av",
    "sg:city":"Nottingham",
    "sg:classifiers":[
        {
            "category":"Professional",
            "subcategory":"Detective & Security Services",
            "type":"Services"
        }
    ],
    "sg:phone":"+44 115 929 6908",
    "sg:postcode":"NG8 5RF",
    "sg:province":"Nottinghamshire",
    "wof:name":"First Class Security",
    "wof:placetype":"venue"
},
  "geometry": {"coordinates":[-1.2043809891,52.97315979],"type":"Point"}
}