{
  "type": "Feature",
  "properties": {
    "iso:country":"GB",
    "sg:address":"The Aerodrome, Dalby Road",
    "sg:city":"Melton Mowbray",
    "sg:classifiers":[
        {
            "category":"Freight",
            "type":"Transportation"
        }
    ],
    "sg:phone":"+44 1664 480632",
    "sg:postcode":"LE13 0BQ",
    "sg:province":"Leicestershire",
    "sg:tags":[
        "forwarders"
    ],
    "wof:name":"Apecc World Cargo",
    "wof:placetype":"venue"
},
  "geometry": {"coordinates":[-0.8895549774,52.7658691406],"type":"Point"}
}