{
  "type": "Feature",
  "properties": {
    "addr:full":"Lower House Farm, Boulters Lane, Baddesley Ensor Atherstone Leicestershire CV9 2QA",
    "addr:postcode":"cv9 2qa",
    "addr:street":"Lower House;Boulters Lane",
    "iso:country":"GB",
    "sg:address":"Lower House Farm, Boulters Lane, Baddesley Ensor",
    "sg:city":"Atherstone",
    "sg:classifiers":[
        {
            "category":"Home & Garden",
            "subcategory":"Garden Supply",
            "type":"Retail Goods"
        },
        {
            "category":"Recreation",
            "subcategory":"Water Park",
            "type":"Entertainment"
        }
    ],
    "sg:phone":"+44 1827 893005",
    "sg:postcode":"CV9 2QA",
    "sg:province":"Leicestershire",
    "sg:tags":[
        "merchant",
        "manufacture",
        "hide",
        "leather",
        "fashionwear",
        "skin"
    ],
    "wof:name":"Robert W G Daniels",
    "wof:placetype":"venue"
},
  "geometry": {"coordinates":[-1.602051,52.580647],"type":"Point"}
}