{
  "type": "Feature",
  "properties": {
    "addr:full":"Unit 4c, Gower Street, St Georges Telford Shropshire TF2 9HW",
    "addr:housenumber":"unit 4c",
    "addr:postcode":"tf2 9hw",
    "addr:street":"Gower Street",
    "iso:country":"GB",
    "sg:address":"Unit 4c, Gower Street, St Georges",
    "sg:city":"Telford",
    "sg:classifiers":[
        {
            "category":"Education",
            "subcategory":"Music School",
            "type":"Public Place"
        }
    ],
    "sg:phone":"+44 1952 616709",
    "sg:postcode":"TF2 9HW",
    "sg:province":"Shropshire",
    "sg:tags":[
        "conservatory"
    ],
    "wof:name":"C-Thru Ltd.",
    "wof:placetype":"venue"
},
  "geometry": {"coordinates":[-2.4361488819,52.6955909729],"type":"Point"}
}