{
  "type": "Feature",
  "properties": {
    "addr:full":"14 Little Orchard Way, Shalford Guildford Surrey GU4 8JY",
    "addr:housenumber":"14",
    "addr:postcode":"gu4 8jy",
    "addr:street":"Little Orchard Way",
    "iso:country":"GB",
    "sg:address":"14 Little Orchard Way, Shalford",
    "sg:city":"Guildford",
    "sg:classifiers":[
        {
            "category":"Health Services",
            "subcategory":"Clinic",
            "type":"Services"
        }
    ],
    "sg:phone":"+44 1483 503954",
    "sg:postcode":"GU4 8JY",
    "sg:province":"Surrey",
    "sg:tags":[
        "medical"
    ],
    "wof:name":"Alton (U K) Ltd.",
    "wof:placetype":"venue"
},
  "geometry": {"coordinates":[-0.5672129989,51.2086791992],"type":"Point"}
}