{
  "type": "Feature",
  "properties": {
    "iso:country":"GB",
    "sg:address":"427 Manchester Road, Lostock Gralam",
    "sg:city":"Northwich",
    "sg:classifiers":[
        {
            "category":"Food & Beverages",
            "subcategory":"Liquor & Beverages",
            "type":"Retail Goods"
        }
    ],
    "sg:phone":"+44 1606 49543",
    "sg:postcode":"CW9 7QA",
    "sg:province":"Cheshire",
    "sg:tags":[
        "beer",
        "wine",
        "spirit",
        "wines"
    ],
    "wof:name":"Bargain Booze Ltd",
    "wof:placetype":"venue"
},
  "geometry": {"coordinates":[-2.463855,53.271233],"type":"Point"}
}