{
  "type": "Feature",
  "properties": {
    "addr:full":"Manor Farm, Little Mongeham Deal Kent CT14 0HR",
    "addr:postcode":"ct14 0hr",
    "addr:street":"Manor;Little",
    "iso:country":"GB",
    "sg:address":"Manor Farm, Little Mongeham",
    "sg:city":"Deal",
    "sg:classifiers":[
        {
            "category":"Farming",
            "subcategory":"Livestock Farm",
            "type":"Manufacturing & Wholesale Goods"
        }
    ],
    "sg:phone":"+44 1304 372729",
    "sg:postcode":"CT14 0HR",
    "sg:province":"Kent",
    "sg:tags":[
        "others"
    ],
    "wof:name":"Little Mongeham Ltd.",
    "wof:placetype":"venue"
},
  "geometry": {"coordinates":[1.339175,51.209831],"type":"Point"}
}