{
  "type": "Feature",
  "properties": {
    "iso:country":"GB",
    "sg:address":"19 Poplar Way",
    "sg:city":"Ringwood",
    "sg:classifiers":[
        {
            "category":"Building & Trades",
            "subcategory":"Cleaning & Sanitation",
            "type":"Services"
        }
    ],
    "sg:phone":"+44 1425 476445",
    "sg:postcode":"BH24 1UY",
    "sg:province":"Dorset",
    "sg:tags":[
        "commercial"
    ],
    "wof:name":"G W Gore-Thorne",
    "wof:placetype":"venue"
},
  "geometry": {"coordinates":[-1.774294,50.846161],"type":"Point"}
}