{
  "type": "Feature",
  "properties": {
    "addr:full":"23 Oswin Road, Brailsford Industrial Park, Off Hinckley Road Leicester Leicestershire LE3 1HR",
    "addr:housenumber":"23",
    "addr:postcode":"le3 1hr",
    "addr:street":"Oswin Road;Hinckley Road",
    "iso:country":"GB",
    "sg:address":"23 Oswin Road, Brailsford Industrial Park, Off Hinckley Road",
    "sg:city":"Leicester",
    "sg:classifiers":[
        {
            "category":"Shopping",
            "subcategory":"Clothing, Apparel, & Fashions",
            "type":"Retail Goods"
        }
    ],
    "sg:phone":"+44 116 255 8474",
    "sg:postcode":"LE3 1HR",
    "sg:province":"Leicestershire",
    "sg:tags":[
        "clothing"
    ],
    "wof:name":"Feet First Ltd.",
    "wof:placetype":"venue"
},
  "geometry": {"coordinates":[-1.1798000336,52.6322784424],"type":"Point"}
}