{
  "type": "Feature",
  "properties": {
    "iso:country":"GB",
    "sg:address":"Bruce Way, Cambridge Road Industrial Estate",
    "sg:city":"Leicester",
    "sg:classifiers":[
        {
            "category":"Manufacturing",
            "subcategory":"Apparel",
            "type":"Manufacturing & Wholesale Goods"
        }
    ],
    "sg:phone":"+44 116 286 4311",
    "sg:postcode":"LE8 6HP",
    "sg:province":"Leicestershire",
    "sg:tags":[
        "mnfr",
        "footwear"
    ],
    "wof:name":"R Griggs & Co. Ltd.",
    "wof:placetype":"venue"
},
  "geometry": {"coordinates":[-1.1835240126,52.5628547668],"type":"Point"}
}