{
  "type": "Feature",
  "properties": {
    "addr:full":"168 Shepherds Bush Road London Greater London W6 7PB",
    "addr:housenumber":"168",
    "addr:postcode":"w6 7pb",
    "addr:street":"Shepherds Bush Road",
    "iso:country":"GB",
    "sg:address":"168 Shepherds Bush Road",
    "sg:city":"London",
    "sg:classifiers":[
        {
            "category":"Professional",
            "subcategory":"Lawyer & Legal Services",
            "type":"Services"
        }
    ],
    "sg:phone":"+44 20 7602 0284",
    "sg:postcode":"W6 7PB",
    "sg:province":"Greater London",
    "sg:tags":[
        "solicitor"
    ],
    "wof:name":"Wadham Smith & Co",
    "wof:placetype":"venue"
},
  "geometry": {"coordinates":[-0.222868,51.497253],"type":"Point"}
}