{
  "type": "Feature",
  "properties": {
    "addr:full":"3 Meadway Dunstable Bedfordshire LU6 3JT",
    "addr:housenumber":"3",
    "addr:postcode":"lu6 3jt",
    "addr:street":"Meadway",
    "iso:country":"GB",
    "sg:address":"3 Meadway",
    "sg:city":"Dunstable",
    "sg:classifiers":[
        {
            "category":"Building & Trades",
            "subcategory":"Construction",
            "type":"Services"
        }
    ],
    "sg:phone":"+44 1582 605008",
    "sg:postcode":"LU6 3JT",
    "sg:province":"Bedfordshire",
    "sg:tags":[
        "builder"
    ],
    "wof:name":"K Dann Plumbing & Builders",
    "wof:placetype":"venue"
},
  "geometry": {"coordinates":[-0.534895,51.882282],"type":"Point"}
}