{
  "type": "Feature",
  "properties": {
    "addr:full":"Warmington Farm, Alverdiscott Road Bideford Devon EX39 4PN",
    "addr:housenumber":"warmington",
    "addr:postcode":"ex39 4pn",
    "addr:street":"Alverdiscott Road",
    "iso:country":"GB",
    "sg:address":"Warmington Farm, Alverdiscott Road",
    "sg:city":"Bideford",
    "sg:classifiers":[
        {
            "category":"Freight",
            "type":"Transportation"
        }
    ],
    "sg:phone":"+44 1271 326632",
    "sg:postcode":"EX39 4PN",
    "sg:province":"Devon",
    "sg:tags":[
        "haulage",
        "road"
    ],
    "wof:name":"Evans Transport Ltd.",
    "wof:placetype":"venue"
},
  "geometry": {"coordinates":[-4.204259,51.019249],"type":"Point"}
}