{
  "type": "Feature",
  "properties": {
    "addr:full":"161 Main Rd, Shavington Congleton Cheshire CW2 5DP",
    "addr:housenumber":"161",
    "addr:postcode":"cw2 5dp",
    "addr:street":"Main Rd",
    "iso:country":"GB",
    "sg:address":"161 Main Rd, Shavington",
    "sg:city":"Congleton",
    "sg:classifiers":[
        {
            "category":"Shopping",
            "subcategory":"Pharmacy",
            "type":"Retail Goods"
        }
    ],
    "sg:postcode":"CW2 5DP",
    "sg:province":"Cheshire",
    "sg:tags":[
        "pharmacist",
        "chemist"
    ],
    "wof:name":"Hassall,J S,",
    "wof:placetype":"venue"
},
  "geometry": {"coordinates":[-2.447455883,53.062664032],"type":"Point"}
}