{
  "type": "Feature",
  "properties": {
    "addr:full":"Central Promendade Hunstanton Norfolk PE36 5BD",
    "addr:postcode":"pe36 5bd",
    "addr:street":"Hunstanton",
    "iso:country":"GB",
    "sg:address":"Central Promendade",
    "sg:city":"Hunstanton",
    "sg:classifiers":[
        {
            "category":"Community Center",
            "type":"Public Place"
        },
        {
            "category":"Government",
            "subcategory":"Office",
            "type":"Public Place"
        }
    ],
    "sg:phone":"+44 1485 534227",
    "sg:postcode":"PE36 5BD",
    "sg:province":"Norfolk",
    "sg:tags":[
        "recreation",
        "local",
        "leisure",
        "centre"
    ],
    "wof:name":"Oasis Leisure Centre",
    "wof:placetype":"venue"
},
  "geometry": {"coordinates":[0.4944050014,52.9371604919],"type":"Point"}
}