{
  "type": "Feature",
  "properties": {
    "addr:full":"34 The Bury Centre, Kay St Bury Lancashire BL6 6BU",
    "addr:housenumber":"34",
    "addr:postcode":"bl6 6bu",
    "addr:street":"The Bury Centre Kay St",
    "iso:country":"GB",
    "sg:address":"34 The Bury Centre, Kay St",
    "sg:city":"Bury",
    "sg:classifiers":[
        {
            "category":"Real Estate",
            "subcategory":"Architect",
            "type":"Services"
        }
    ],
    "sg:postcode":"BL6 6BU",
    "sg:province":"Lancashire",
    "wof:name":"Chalcroft,Bryn,",
    "wof:placetype":"venue"
},
  "geometry": {"coordinates":[-2.5348300934,53.5978012085],"type":"Point"}
}