{
  "type": "Feature",
  "properties": {
    "iso:country":"GB",
    "sg:address":"13-15 Abercorn Terrace",
    "sg:city":"Edinburgh",
    "sg:classifiers":[
        {
            "category":"Health Services",
            "subcategory":"Nursing And Care Facility",
            "type":"Services"
        },
        {
            "category":"Social Services",
            "subcategory":"Retirement Home",
            "type":"Services"
        }
    ],
    "sg:phone":"+44 131 468 1631",
    "sg:postcode":"EH15 2DE",
    "sg:province":"City of Edinburgh",
    "sg:tags":[
        "residential"
    ],
    "wof:name":"Marina Masson",
    "wof:placetype":"venue"
},
  "geometry": {"coordinates":[-3.107159,55.951038],"type":"Point"}
}