{
  "type": "Feature",
  "properties": {
    "iso:country":"GB",
    "sg:address":"Old Colliery Road, Whiston",
    "sg:city":"Prescot",
    "sg:classifiers":[
        {
            "category":"Shopping",
            "subcategory":"Pharmacy",
            "type":"Retail Goods"
        }
    ],
    "sg:phone":"+44 151 426 6835",
    "sg:postcode":"L35 3SX",
    "sg:province":"Cheshire",
    "sg:tags":[
        "pharmacist",
        "chemist"
    ],
    "wof:name":"Moss Chemist",
    "wof:placetype":"venue"
},
  "geometry": {"coordinates":[-2.8005039692,53.4157409668],"type":"Point"}
}