{
  "type": "Feature",
  "properties": {
    "iso:country":"GB",
    "sg:address":"150 St Anns Road North, Heald Green",
    "sg:city":"Cheadle",
    "sg:classifiers":[
        {
            "category":"Building & Trades",
            "subcategory":"Construction",
            "type":"Services"
        }
    ],
    "sg:phone":"+44 161 436 5812",
    "sg:postcode":"SK8 4RZ",
    "sg:province":"Cheshire",
    "sg:tags":[
        "builder"
    ],
    "wof:name":"Home Maintenance",
    "wof:placetype":"venue"
},
  "geometry": {"coordinates":[-2.227299,53.378456],"type":"Point"}
}