{
  "type": "Feature",
  "properties": {
    "addr:full":"2nd Floor, 15 Great Portland St West End Hampshire W1N 5DB",
    "addr:housenumber":"2nd floor 15",
    "addr:postcode":"w1n 5db",
    "addr:street":"Great Portland St",
    "iso:country":"GB",
    "sg:address":"2nd Floor, 15 Great Portland St",
    "sg:city":"West End",
    "sg:classifiers":[
        {
            "category":"Professional",
            "subcategory":"Art Services",
            "type":"Services"
        }
    ],
    "sg:phone":"+44 20 7323 5778",
    "sg:postcode":"W1N 5DB",
    "sg:province":"Hampshire",
    "sg:tags":[
        "graphic",
        "designer"
    ],
    "wof:name":"Bud",
    "wof:placetype":"venue"
},
  "geometry": {"coordinates":[-0.1412030011,51.5162353516],"type":"Point"}
}