{
  "type": "Feature",
  "properties": {
    "addr:full":"Colebrooke Mill, Colebrooke Crediton Devon EX17 5JL",
    "addr:postcode":"ex17 5jl",
    "addr:street":"Colebrooke;Colebrooke",
    "iso:country":"GB",
    "sg:address":"Colebrooke Mill, Colebrooke",
    "sg:city":"Crediton",
    "sg:classifiers":[
        {
            "category":"Building & Trades",
            "subcategory":"Equipment Rental",
            "type":"Services"
        }
    ],
    "sg:phone":"+44 1363 84121",
    "sg:postcode":"EX17 5JL",
    "sg:province":"Devon",
    "sg:tags":[
        "plant",
        "machinery"
    ],
    "wof:name":"M J Bragg & Son",
    "wof:placetype":"venue"
},
  "geometry": {"coordinates":[-3.7433669567,50.7905654907],"type":"Point"}
}