{
  "type": "Feature",
  "properties": {
    "iso:country":"GB",
    "sg:address":"Model House Farm, Morris Lane, Halsall",
    "sg:city":"Ormskirk",
    "sg:classifiers":[
        {
            "category":"Farming",
            "subcategory":"Farm",
            "type":"Manufacturing & Wholesale Goods"
        }
    ],
    "sg:phone":"+44 1704 840370",
    "sg:postcode":"L39 8SX",
    "sg:province":"Lancashire",
    "sg:tags":[
        "mixed",
        "crop"
    ],
    "wof:name":"Philip Molyneux",
    "wof:placetype":"venue"
},
  "geometry": {"coordinates":[-2.9546189308,53.5842704773],"type":"Point"}
}