{
  "type": "Feature",
  "properties": {
    "iso:country":"GB",
    "sg:address":"326 Chartwell North, Victoria Plaza",
    "sg:city":"Southend-on-sea",
    "sg:classifiers":[
        {
            "category":"Shopping",
            "subcategory":"Hobbies, Toys, & Games",
            "type":"Retail Goods"
        }
    ],
    "sg:postcode":"SS2 5SR",
    "sg:province":"Essex",
    "sg:tags":[
        "shop",
        "toy"
    ],
    "wof:name":"Time Tunnel",
    "wof:placetype":"venue"
},
  "geometry": {"coordinates":[0.7124000192,51.5410003662],"type":"Point"}
}