{
  "type": "Feature",
  "properties": {
    "addr:full":"8 Portesbery Rd Camberley Berkshire GU15 3TA",
    "addr:housenumber":"8",
    "addr:postcode":"gu15 3ta",
    "addr:street":"Portesbery Rd",
    "iso:country":"GB",
    "sg:address":"8 Portesbery Rd",
    "sg:city":"Camberley",
    "sg:classifiers":[
        {
            "category":"Personal",
            "type":"Services"
        },
        {
            "category":"Professional",
            "subcategory":"Lawyer & Legal Services",
            "type":"Services"
        }
    ],
    "sg:phone":"+44 1276 24210",
    "sg:postcode":"GU15 3TA",
    "sg:province":"Berkshire",
    "sg:tags":[
        "advice",
        "counselling"
    ],
    "wof:name":"Connect Christian Counselling Service",
    "wof:placetype":"venue"
},
  "geometry": {"coordinates":[-0.7331640124,51.3403511047],"type":"Point"}
}