{
  "type": "Feature",
  "properties": {
    "addr:full":"Armstrong Technology Centre, Davy Bank Wallsend Tyne and Wear NE28 6UZ",
    "addr:postcode":"ne28 6uz",
    "iso:country":"GB",
    "sg:address":"Armstrong Technology Centre, Davy Bank",
    "sg:city":"Wallsend",
    "sg:classifiers":[
        {
            "category":"Professional",
            "subcategory":"Computer Services",
            "type":"Services"
        }
    ],
    "sg:phone":"+44 191 263 6000",
    "sg:postcode":"NE28 6UZ",
    "sg:province":"Tyne and Wear",
    "sg:tags":[
        "system",
        "software"
    ],
    "wof:name":"Kockums Computer Systems",
    "wof:placetype":"venue"
},
  "geometry": {"coordinates":[-1.5233800411,54.9888191223],"type":"Point"}
}