{
  "type": "Feature",
  "properties": {
    "addr:full":"107 Elmers End Road Beckenham Kent BR3 4SY",
    "addr:housenumber":"107",
    "addr:postcode":"br3 4sy",
    "addr:street":"Elmers End Road",
    "iso:country":"GB",
    "sg:address":"107 Elmers End Road",
    "sg:city":"Beckenham",
    "sg:classifiers":[
        {
            "category":"Home & Garden",
            "subcategory":"Furniture",
            "type":"Retail Goods"
        }
    ],
    "sg:phone":"+44 20 8778 6935",
    "sg:postcode":"BR3 4SY",
    "sg:province":"Kent",
    "wof:name":"Totalgreen Ltd.",
    "wof:placetype":"venue"
},
  "geometry": {"coordinates":[-0.056326,51.405083],"type":"Point"}
}