{
  "type": "Feature",
  "properties": {
    "iso:country":"GB",
    "sg:address":"16 The Street, Kirby Le Soken",
    "sg:city":"Frinton-on-sea",
    "sg:classifiers":[
        {
            "category":"Professional",
            "subcategory":"Accounting & Tax Preparation",
            "type":"Services"
        }
    ],
    "sg:phone":"+44 1255 679566",
    "sg:postcode":"CO13 0EE",
    "sg:province":"Essex",
    "sg:tags":[
        "consultant"
    ],
    "wof:name":"Barbara Thorpe",
    "wof:placetype":"venue"
},
  "geometry": {"coordinates":[1.241911,51.838032],"type":"Point"}
}