{
  "type": "Feature",
  "properties": {
    "addr:full":"84 Burton Road, Findern Derby Derbyshire DE65 6BE",
    "addr:housenumber":"84",
    "addr:postcode":"de65 6be",
    "addr:street":"Burton Road",
    "iso:country":"GB",
    "sg:address":"84 Burton Road, Findern",
    "sg:city":"Derby",
    "sg:classifiers":[
        {
            "category":"Arts & Performance",
            "subcategory":"Music",
            "type":"Entertainment"
        }
    ],
    "sg:phone":"+44 1332 510727",
    "sg:postcode":"DE65 6BE",
    "sg:province":"Derbyshire",
    "sg:tags":[
        "musician",
        "composer"
    ],
    "wof:name":"Graham Woodhouse A Swing Band",
    "wof:placetype":"venue"
},
  "geometry": {"coordinates":[-1.5435700417,52.8841133118],"type":"Point"}
}