{
  "type": "Feature",
  "properties": {
    "addr:full":"127 High Street Fort William Highland PH33 6DG",
    "addr:housenumber":"127",
    "addr:postcode":"ph33 6dg",
    "addr:street":"High Street",
    "iso:country":"GB",
    "sg:address":"127 High Street",
    "sg:city":"Fort William",
    "sg:classifiers":[
        {
            "category":"Shopping",
            "subcategory":"Thrift Store",
            "type":"Retail Goods"
        }
    ],
    "sg:phone":"+44 1397 701488",
    "sg:postcode":"PH33 6DG",
    "sg:province":"Highland",
    "sg:tags":[
        "shop",
        "charity"
    ],
    "wof:name":"Highland Hospice Charity Shop",
    "wof:placetype":"venue"
},
  "geometry": {"coordinates":[-5.1132807732,56.8169746399],"type":"Point"}
}