{
  "type": "Feature",
  "properties": {
    "addr:full":"62 Broad Lane Hampton Greater London TW12 3BG",
    "addr:housenumber":"62",
    "addr:postcode":"tw12 3bg",
    "addr:street":"Broad Lane",
    "iso:country":"GB",
    "sg:address":"62 Broad Lane",
    "sg:city":"Hampton",
    "sg:classifiers":[
        {
            "category":"Building & Trades",
            "subcategory":"Plumbing",
            "type":"Services"
        }
    ],
    "sg:phone":"+44 20 8979 9466",
    "sg:postcode":"TW12 3BG",
    "sg:province":"Greater London",
    "sg:tags":[
        "heating"
    ],
    "wof:name":"David R Alliston",
    "wof:placetype":"venue"
},
  "geometry": {"coordinates":[-0.3733029962,51.4227371216],"type":"Point"}
}