{
  "type": "Feature",
  "properties": {
    "addr:full":"Cockleshell Barn, Exmouth Road, Lympstone Exmouth Devon EX8 5AF",
    "addr:postcode":"ex8 5af",
    "addr:street":"Exmouth Road",
    "iso:country":"GB",
    "sg:address":"Cockleshell Barn, Exmouth Road, Lympstone",
    "sg:city":"Exmouth",
    "sg:classifiers":[
        {
            "category":"Communications",
            "type":"Services"
        }
    ],
    "sg:postcode":"EX8 5AF",
    "sg:province":"Devon",
    "sg:tags":[
        "data",
        "network"
    ],
    "wof:name":"Rightdata Limited",
    "wof:placetype":"venue"
},
  "geometry": {"coordinates":[-3.417639,50.649639],"type":"Point"}
}