{
  "type": "Feature",
  "properties": {
    "iso:country":"GB",
    "sg:address":"Hillside House, 2-6 Friern Park",
    "sg:city":"London",
    "sg:classifiers":[
        {
            "category":"Arena",
            "subcategory":"Bull Ring",
            "type":"Entertainment"
        }
    ],
    "sg:phone":"+44 20 8445 8800",
    "sg:postcode":"N12 9BT",
    "sg:province":"Greater London",
    "sg:tags":[
        "rating",
        "surveyor"
    ],
    "wof:name":"Shaw & Co",
    "wof:placetype":"venue"
},
  "geometry": {"coordinates":[-0.176283,51.615604],"type":"Point"}
}