{
  "type": "Feature",
  "properties": {
    "addr:full":"Speke Rd, Speke Liverpool Merseyside L24 8QB",
    "addr:postcode":"l24 8qb",
    "addr:street":"Speke Rd",
    "iso:country":"GB",
    "sg:address":"Speke Rd, Speke",
    "sg:city":"Liverpool",
    "sg:classifiers":[
        {
            "category":"Autos & Motor Vehicles",
            "subcategory":"Auto Supplies",
            "type":"Retail Goods"
        }
    ],
    "sg:phone":"+44 151 427 5377",
    "sg:postcode":"L24 8QB",
    "sg:province":"Merseyside",
    "sg:tags":[
        "exhaust",
        "absorber",
        "shock"
    ],
    "wof:name":"Budjet Exhausts & Tyres",
    "wof:placetype":"venue"
},
  "geometry": {"coordinates":[-2.882057,53.349609],"type":"Point"}
}