{
  "type": "Feature",
  "properties": {
    "addr:full":"3 Widemarsh St Hereford Herefordshire HR4 9EA",
    "addr:housenumber":"3",
    "addr:postcode":"hr4 9ea",
    "addr:street":"Widemarsh St",
    "iso:country":"GB",
    "sg:address":"3 Widemarsh St",
    "sg:city":"Hereford",
    "sg:classifiers":[
        {
            "category":"Shopping",
            "subcategory":"Clothing, Apparel, & Fashions",
            "type":"Retail Goods"
        }
    ],
    "sg:phone":"+44 1432 278626",
    "sg:postcode":"HR4 9EA",
    "sg:province":"Herefordshire",
    "sg:tags":[
        "ladieswear"
    ],
    "wof:name":"Noyadd Rhulen Country Stores",
    "wof:placetype":"venue"
},
  "geometry": {"coordinates":[-2.7166359425,52.056804657],"type":"Point"}
}