{
  "type": "Feature",
  "properties": {
    "addr:full":"The Pepperpot, Church Street, Upton Upon Severn Worcester Gloucestershire WR8 0HT",
    "addr:postcode":"wr8 0ht",
    "addr:street":"Church Street",
    "iso:country":"GB",
    "sg:address":"The Pepperpot, Church Street, Upton Upon Severn",
    "sg:city":"Worcester",
    "sg:classifiers":[
        {
            "category":"Museum",
            "subcategory":"Art Museum",
            "type":"Entertainment"
        }
    ],
    "sg:phone":"+44 1684 592679",
    "sg:postcode":"WR8 0HT",
    "sg:province":"Gloucestershire",
    "sg:tags":[
        "gallery"
    ],
    "wof:name":"Upton Heritage Centre",
    "wof:placetype":"venue"
},
  "geometry": {"coordinates":[-2.218359,52.0634],"type":"Point"}
}