{
  "type": "Feature",
  "properties": {
    "addr:full":"The Maltings, Station Rd, Ketton Stamford Cambridgeshire PE9 3RQ",
    "addr:postcode":"pe9 3rq",
    "addr:street":"The;Station Rd",
    "iso:country":"GB",
    "sg:address":"The Maltings, Station Rd, Ketton",
    "sg:city":"Stamford",
    "sg:classifiers":[
        {
            "category":"Shopping",
            "subcategory":"Books",
            "type":"Retail Goods"
        }
    ],
    "sg:phone":"+44 1780 720691",
    "sg:postcode":"PE9 3RQ",
    "sg:province":"Cambridgeshire",
    "wof:name":"Baha'I Publishing Trust",
    "wof:placetype":"venue"
},
  "geometry": {"coordinates":[-0.5529990196,52.6308517456],"type":"Point"}
}