{
  "type": "Feature",
  "properties": {
    "iso:country":"GB",
    "sg:address":"Cheddar Road",
    "sg:city":"Axbridge",
    "sg:classifiers":[
        {
            "category":"Health Services",
            "subcategory":"Nursing And Care Facility",
            "type":"Services"
        }
    ],
    "sg:phone":"+44 1934 732358",
    "sg:postcode":"BS26 2DW",
    "sg:province":"Somerset",
    "sg:tags":[
        "home"
    ],
    "wof:name":"St Michaels Cheshire Home",
    "wof:placetype":"venue"
},
  "geometry": {"coordinates":[-2.809998,51.287132],"type":"Point"}
}