{
  "type": "Feature",
  "properties": {
    "addr:full":"3 Temple Chambers, Temple Street Swindon Wiltshire SN4 8DP",
    "addr:housenumber":"3",
    "addr:postcode":"sn4 8dp",
    "addr:street":"Temple Chambers Temple Street",
    "iso:country":"GB",
    "sg:address":"3 Temple Chambers, Temple Street",
    "sg:city":"Swindon",
    "sg:classifiers":[
        {
            "category":"Banks & Credit Unions",
            "subcategory":"Financial Services",
            "type":"Services"
        }
    ],
    "sg:phone":"+44 1793 481431",
    "sg:postcode":"SN4 8DP",
    "sg:province":"Wiltshire",
    "sg:tags":[
        "adviser"
    ],
    "wof:name":"Alexanders",
    "wof:placetype":"venue"
},
  "geometry": {"coordinates":[-1.89513,51.55159],"type":"Point"}
}