{
  "type": "Feature",
  "properties": {
    "iso:country":"GB",
    "sg:address":"77/79 Rushey Green, Catford",
    "sg:city":"London",
    "sg:classifiers":[
        {
            "category":"Arena",
            "subcategory":"Sports Club",
            "type":"Entertainment"
        }
    ],
    "sg:postcode":"SE6 4AF",
    "sg:province":"Greater London",
    "sg:tags":[
        "ground"
    ],
    "wof:name":"Royal Victoria Dock Water Sports Ltd",
    "wof:placetype":"venue"
},
  "geometry": {"coordinates":[-0.018522,51.447002],"type":"Point"}
}