{
  "type": "Feature",
  "properties": {
    "addr:full":"The Osiers, Firs Path Leighton Buzzard Bedfordshire LU7 7JH",
    "addr:postcode":"lu7 7jh",
    "addr:street":"Firs Path",
    "iso:country":"GB",
    "sg:address":"The Osiers, Firs Path",
    "sg:city":"Leighton Buzzard",
    "sg:classifiers":[
        {
            "category":"Professional",
            "subcategory":"Printing & Photocopies",
            "type":"Services"
        }
    ],
    "sg:postcode":"LU7 7JH",
    "sg:province":"Bedfordshire",
    "sg:tags":[
        "print",
        "finisher"
    ],
    "wof:name":"Victoria Print Service",
    "wof:placetype":"venue"
},
  "geometry": {"coordinates":[-0.663909018,51.917350769],"type":"Point"}
}