{
  "type": "Feature",
  "properties": {
    "addr:full":"950 Great West Road Brentford Greater London TW8 9HE",
    "addr:housenumber":"950",
    "addr:postcode":"tw8 9he",
    "addr:street":"Great West Road",
    "iso:country":"GB",
    "sg:address":"950 Great West Road",
    "sg:city":"Brentford",
    "sg:classifiers":[
        {
            "category":"Shopping",
            "subcategory":"Computers & Home Electronics",
            "type":"Retail Goods"
        }
    ],
    "sg:phone":"+44 20 8380 8000",
    "sg:postcode":"TW8 9HE",
    "sg:province":"Greater London",
    "wof:name":"Morse Group Ltd.",
    "wof:placetype":"venue"
},
  "geometry": {"coordinates":[-0.31709,51.487003],"type":"Point"}
}