{
  "type": "Feature",
  "properties": {
    "addr:full":"6 Wisden Rd, Pin Grn Stevenage Hertfordshire SG1 5HZ",
    "addr:housenumber":"6",
    "addr:postcode":"sg1 5hz",
    "addr:street":"Wisden Rd Pin Grn",
    "iso:country":"GB",
    "sg:address":"6 Wisden Rd, Pin Grn",
    "sg:city":"Stevenage",
    "sg:classifiers":[
        {
            "category":"Building & Trades",
            "subcategory":"Plumbing",
            "type":"Services"
        }
    ],
    "sg:postcode":"SG1 5HZ",
    "sg:province":"Hertfordshire",
    "sg:tags":[
        "heating"
    ],
    "wof:name":"Miller,Gary,",
    "wof:placetype":"venue"
},
  "geometry": {"coordinates":[-0.186266,51.916695],"type":"Point"}
}