{
  "type": "Feature",
  "properties": {
    "iso:country":"GB",
    "sg:address":"80 London Road, Widley",
    "sg:city":"Waterlooville",
    "sg:classifiers":[
        {
            "category":"Home & Garden",
            "subcategory":"Home Furnishings",
            "type":"Retail Goods"
        }
    ],
    "sg:phone":"+44 23 9220 1500",
    "sg:postcode":"PO7 5AB",
    "sg:province":"Hampshire",
    "sg:tags":[
        "furnishers",
        "planner",
        "bedroom"
    ],
    "wof:name":"Neta Quality Bedrooms",
    "wof:placetype":"venue"
},
  "geometry": {"coordinates":[-1.044148,50.869358],"type":"Point"}
}