{
  "type": "Feature",
  "properties": {
    "iso:country":"GB",
    "sg:address":"81 Craigside",
    "sg:city":"Stoke On Trent",
    "sg:classifiers":[
        {
            "category":"Retail",
            "subcategory":"Repair Shop",
            "type":"Services"
        }
    ],
    "sg:phone":"+44 1782 516379",
    "sg:postcode":"ST8 6BP",
    "sg:province":"Staffordshire",
    "sg:tags":[
        "plant",
        "machinery"
    ],
    "wof:name":"A Whitehurst",
    "wof:placetype":"venue"
},
  "geometry": {"coordinates":[-2.176715,53.118137],"type":"Point"}
}