{
  "type": "Feature",
  "properties": {
    "addr:full":"French Barn Lane, Blackley Manchester Greater Manchester M9 6PB",
    "addr:postcode":"m9 6pb",
    "addr:street":"Barn Lane",
    "iso:country":"GB",
    "sg:address":"French Barn Lane, Blackley",
    "sg:city":"Manchester",
    "sg:classifiers":[
        {
            "category":"Organizations",
            "subcategory":"Non-profit Organization",
            "type":"Services"
        }
    ],
    "sg:phone":"+44 161 740 0100",
    "sg:postcode":"M9 6PB",
    "sg:province":"Greater Manchester",
    "sg:tags":[
        "organisation",
        "voluntary",
        "charity"
    ],
    "wof:name":"North District Family Unit",
    "wof:placetype":"venue"
},
  "geometry": {"coordinates":[-2.2194690704,53.5248260498],"type":"Point"}
}