{
  "type": "Feature",
  "properties": {
    "addr:full":"Bury Hill Clo Woodbridge Suffolk IP12 1LE",
    "addr:postcode":"ip12 1le",
    "addr:street":"Bury;Clo",
    "iso:country":"GB",
    "sg:address":"Bury Hill Clo",
    "sg:city":"Woodbridge",
    "sg:classifiers":[
        {
            "category":"Arts & Performance",
            "subcategory":"Music",
            "type":"Entertainment"
        }
    ],
    "sg:phone":"+44 7710 280481",
    "sg:postcode":"IP12 1LE",
    "sg:province":"Suffolk",
    "sg:tags":[
        "mobile",
        "disco"
    ],
    "wof:name":"Suffolk Sound & Light Co",
    "wof:placetype":"venue"
},
  "geometry": {"coordinates":[1.31601,52.104515],"type":"Point"}
}