{
  "type": "Feature",
  "properties": {
    "iso:country":"GB",
    "sg:address":"25 Abraham Close, Botley",
    "sg:city":"Southampton",
    "sg:classifiers":[
        {
            "category":"Organizations",
            "subcategory":"Non-profit Organization",
            "type":"Services"
        }
    ],
    "sg:phone":"+44 1489 780633",
    "sg:postcode":"SO30 2RQ",
    "sg:province":"Hampshire",
    "sg:tags":[
        "organisation",
        "voluntary",
        "charity"
    ],
    "wof:name":"Marine Builders Training Trust",
    "wof:placetype":"venue"
},
  "geometry": {"coordinates":[-1.290943,50.909508],"type":"Point"}
}