{
  "type": "Feature",
  "properties": {
    "iso:country":"GB",
    "sg:address":"14 Bowen Square",
    "sg:city":"Daventry",
    "sg:classifiers":[
        {
            "category":"Travel",
            "subcategory":"Travel Agent",
            "type":"Entertainment"
        }
    ],
    "sg:phone":"+44 1327 310696",
    "sg:postcode":"NN11 4DR",
    "sg:province":"Northamptonshire",
    "wof:name":"Co-Op Travel",
    "wof:placetype":"venue"
},
  "geometry": {"coordinates":[-1.1612789631,52.2568740845],"type":"Point"}
}