{
  "type": "Feature",
  "properties": {
    "iso:country":"GB",
    "sg:address":"373 Somerville Rd",
    "sg:city":"Birmingham",
    "sg:classifiers":[
        {
            "category":"Bars & Pubs",
            "type":"Food & Drink"
        }
    ],
    "sg:phone":"+44 121 753 5072",
    "sg:postcode":"B10 9LJ",
    "sg:province":"West Midlands",
    "sg:tags":[
        "pubs",
        "inn"
    ],
    "wof:name":"Monica Inn The",
    "wof:placetype":"venue"
},
  "geometry": {"coordinates":[-1.8403060436,52.4690246582],"type":"Point"}
}