{
  "type": "Feature",
  "properties": {
    "addr:full":"Riverside House, Berry Road, Lavenham Sudbury Essex CO10 9QD",
    "addr:postcode":"co10 9qd",
    "addr:street":"Berry Road",
    "iso:country":"GB",
    "sg:address":"Riverside House, Berry Road, Lavenham",
    "sg:city":"Sudbury",
    "sg:classifiers":[
        {
            "category":"Professional",
            "subcategory":"Business Services",
            "type":"Services"
        }
    ],
    "sg:phone":"+44 1787 249450",
    "sg:postcode":"CO10 9QD",
    "sg:province":"Essex",
    "sg:tags":[
        "holding"
    ],
    "wof:name":"Grove Holdings Ltd.",
    "wof:placetype":"venue"
},
  "geometry": {"coordinates":[0.7952880263,52.1071205139],"type":"Point"}
}