{
  "type": "Feature",
  "properties": {
    "addr:full":"Mason Avenue Leamington Spa Warwickshire CV32 7QE",
    "addr:postcode":"cv32 7qe",
    "addr:street":"Mason Avenue",
    "iso:country":"GB",
    "sg:address":"Mason Avenue",
    "sg:city":"Leamington Spa",
    "sg:classifiers":[
        {
            "category":"Community Center",
            "subcategory":"Youth",
            "type":"Public Place"
        }
    ],
    "sg:phone":"+44 1926 429287",
    "sg:postcode":"CV32 7QE",
    "sg:province":"Warwickshire",
    "sg:tags":[
        "organisation",
        "centre"
    ],
    "wof:name":"Lillington Community Centre",
    "wof:placetype":"venue"
},
  "geometry": {"coordinates":[-1.517788,52.301323],"type":"Point"}
}