{
  "type": "Feature",
  "properties": {
    "addr:full":"10 Oulton Crescent Potters Bar Greater London EN6 3ED",
    "addr:housenumber":"10",
    "addr:postcode":"en6 3ed",
    "addr:street":"Oulton Crescent",
    "iso:country":"GB",
    "sg:address":"10 Oulton Crescent",
    "sg:city":"Potters Bar",
    "sg:classifiers":[
        {
            "category":"Building & Trades",
            "subcategory":"Construction",
            "type":"Services"
        }
    ],
    "sg:postcode":"EN6 3ED",
    "sg:province":"Greater London",
    "sg:tags":[
        "roofing"
    ],
    "wof:name":"Abbey Roofing & Property Maintenance",
    "wof:placetype":"venue"
},
  "geometry": {"coordinates":[-0.2093659937,51.6966896057],"type":"Point"}
}