{
  "type": "Feature",
  "properties": {
    "addr:full":"7 Bromham Mill Milton Keynes Buckinghamshire MK14 5QP",
    "addr:housenumber":"7",
    "addr:postcode":"mk14 5qp",
    "addr:street":"Bromham Mill",
    "iso:country":"GB",
    "sg:address":"7 Bromham Mill",
    "sg:city":"Milton Keynes",
    "sg:classifiers":[
        {
            "category":"Shopping",
            "subcategory":"Crafts & Fabrics",
            "type":"Retail Goods"
        }
    ],
    "sg:phone":"+44 1908 210894",
    "sg:postcode":"MK14 5QP",
    "sg:province":"Buckinghamshire",
    "sg:tags":[
        "material",
        "art"
    ],
    "wof:name":"Debbie Crafts",
    "wof:placetype":"venue"
},
  "geometry": {"coordinates":[-0.7502440214,52.074508667],"type":"Point"}
}