{
  "type": "Feature",
  "properties": {
    "addr:full":"46 Wood Street Lytham St Annes Lancashire FY8 1QG",
    "addr:housenumber":"46",
    "addr:postcode":"fy8 1qg",
    "addr:street":"Wood Street",
    "iso:country":"GB",
    "sg:address":"46 Wood Street",
    "sg:city":"Lytham St Annes",
    "sg:classifiers":[
        {
            "category":"Banks & Credit Unions",
            "subcategory":"Financial Services",
            "type":"Services"
        }
    ],
    "sg:postcode":"FY8 1QG",
    "sg:province":"Lancashire",
    "sg:tags":[
        "claim",
        "assessor"
    ],
    "wof:name":"Ian Woodhead",
    "wof:placetype":"venue"
},
  "geometry": {"coordinates":[-3.030924,53.750408],"type":"Point"}
}