{
  "type": "Feature",
  "properties": {
    "addr:full":"113 Oaklands Road London Greater London W7 2DT",
    "addr:housenumber":"113",
    "addr:postcode":"w7 2dt",
    "addr:street":"Oaklands Road",
    "iso:country":"GB",
    "sg:address":"113 Oaklands Road",
    "sg:city":"London",
    "sg:classifiers":[
        {
            "category":"Retail",
            "subcategory":"Repair Shop",
            "type":"Services"
        }
    ],
    "sg:phone":"+44 20 8840 4455",
    "sg:postcode":"W7 2DT",
    "sg:province":"Greater London",
    "sg:tags":[
        "radio",
        "television",
        "video"
    ],
    "wof:name":"Forth Electronic Services Ltd.",
    "wof:placetype":"venue"
},
  "geometry": {"coordinates":[-0.328051,51.506599],"type":"Point"}
}