{
  "type": "Feature",
  "properties": {
    "iso:country":"GB",
    "sg:address":"Hill Cottage, Hill Rd",
    "sg:city":"Hindhead",
    "sg:classifiers":[
        {
            "category":"Retail",
            "subcategory":"Repair Shop",
            "type":"Services"
        }
    ],
    "sg:phone":"+44 1428 604609",
    "sg:postcode":"GU26 6HL",
    "sg:province":"Hampshire",
    "sg:tags":[
        "clocks",
        "watch"
    ],
    "wof:name":"J L Williams",
    "wof:placetype":"venue"
},
  "geometry": {"coordinates":[-0.7531679869,51.1218795776],"type":"Point"}
}