{
  "type": "Feature",
  "properties": {
    "iso:country":"GB",
    "sg:address":"332 Northolt Rd",
    "sg:city":"Harrow",
    "sg:classifiers":[
        {
            "category":"Autos & Motor Vehicles",
            "subcategory":"Fuel & Gas Station",
            "type":"Retail Goods"
        }
    ],
    "sg:phone":"+44 20 8423 9230",
    "sg:postcode":"HA2 8ES",
    "sg:province":"Greater London",
    "sg:tags":[
        "petrol",
        "filling"
    ],
    "wof:name":"Total Convenience Stores",
    "wof:placetype":"venue"
},
  "geometry": {"coordinates":[-0.357029,51.561859],"type":"Point"}
}