{
  "type": "Feature",
  "properties": {
    "addr:full":"6 Oxford Street Ripley Derbyshire DE5 3AL",
    "addr:housenumber":"6",
    "addr:postcode":"de5 3al",
    "addr:street":"Oxford Street",
    "iso:country":"GB",
    "sg:address":"6 Oxford Street",
    "sg:city":"Ripley",
    "sg:classifiers":[
        {
            "category":"Food & Beverages",
            "subcategory":"Meat & Fish",
            "type":"Retail Goods"
        }
    ],
    "sg:phone":"+44 1773 742965",
    "sg:postcode":"DE5 3AL",
    "sg:province":"Derbyshire",
    "sg:tags":[
        "butcher"
    ],
    "wof:name":"The Butcher Shop",
    "wof:placetype":"venue"
},
  "geometry": {"coordinates":[-1.4066799879,53.0496940613],"type":"Point"}
}