{
  "type": "Feature",
  "properties": {
    "addr:full":"Soigne Farm Workshops, West Acre King's Lynn Norfolk PE32 1UH",
    "addr:postcode":"pe32 1uh",
    "addr:street":"Lynn",
    "iso:country":"GB",
    "sg:address":"Soigne Farm Workshops, West Acre",
    "sg:city":"King's Lynn",
    "sg:classifiers":[
        {
            "category":"Home & Garden",
            "subcategory":"Building Materials",
            "type":"Retail Goods"
        }
    ],
    "sg:phone":"+44 1760 755113",
    "sg:postcode":"PE32 1UH",
    "sg:province":"Norfolk",
    "sg:tags":[
        "fencing"
    ],
    "wof:name":"Fencerite",
    "wof:placetype":"venue"
},
  "geometry": {"coordinates":[0.6296799779,52.7296791077],"type":"Point"}
}