{
  "type": "Feature",
  "properties": {
    "addr:full":"Unit 9 & 10 Houghton Road, North Anston Trading Estate Sheffield South Yorkshire S25 4JJ",
    "addr:housenumber":"unit 9 & 10",
    "addr:postcode":"s25 4jj",
    "addr:street":"Houghton Road North Anston Trading Estate",
    "iso:country":"GB",
    "sg:address":"Unit 9 & 10 Houghton Road, North Anston Trading Estate",
    "sg:city":"Sheffield",
    "sg:classifiers":[
        {
            "category":"Professional",
            "subcategory":"Printing & Photocopies",
            "type":"Services"
        }
    ],
    "sg:phone":"+44 1909 564177",
    "sg:postcode":"S25 4JJ",
    "sg:province":"South Yorkshire",
    "sg:tags":[
        "printer"
    ],
    "wof:name":"Drawnorth Ltd.",
    "wof:placetype":"venue"
},
  "geometry": {"coordinates":[-1.2362699509,53.366481781],"type":"Point"}
}