{
  "type": "Feature",
  "properties": {
    "iso:country":"GB",
    "sg:address":"Queen Anne House, Gonville Place",
    "sg:city":"Cambridge",
    "sg:classifiers":[
        {
            "category":"Organizations",
            "subcategory":"Non-profit Organization",
            "type":"Services"
        }
    ],
    "sg:phone":"+44 1223 356998",
    "sg:postcode":"CB1 1ND",
    "sg:province":"Cambridgeshire",
    "sg:tags":[
        "organisation",
        "voluntary",
        "charity"
    ],
    "wof:name":"Y M C A (Cambridge) Trading Ltd.",
    "wof:placetype":"venue"
},
  "geometry": {"coordinates":[0.130215,52.201576],"type":"Point"}
}