{
  "type": "Feature",
  "properties": {
    "addr:full":"44 Howard St Gloucester Gloucestershire GL1 4UU",
    "addr:housenumber":"44",
    "addr:postcode":"gl1 4uu",
    "addr:street":"Howard St",
    "iso:country":"GB",
    "sg:address":"44 Howard St",
    "sg:city":"Gloucester",
    "sg:classifiers":[
        {
            "category":"Building & Trades",
            "subcategory":"Construction",
            "type":"Services"
        }
    ],
    "sg:phone":"+44 1452 421984",
    "sg:postcode":"GL1 4UU",
    "sg:province":"Gloucestershire",
    "sg:tags":[
        "builder"
    ],
    "wof:name":"J R Hunt",
    "wof:placetype":"venue"
},
  "geometry": {"coordinates":[-2.240319,51.855396],"type":"Point"}
}