{
  "type": "Feature",
  "properties": {
    "addr:full":"Marshall Meadows Farm Berwick-upon-tweed Northumberland TD15 1UT",
    "addr:postcode":"td15 1ut",
    "addr:street":"Marshall Meadows;Northumberland",
    "iso:country":"GB",
    "sg:address":"Marshall Meadows Farm",
    "sg:city":"Berwick-upon-tweed",
    "sg:classifiers":[
        {
            "category":"Farming",
            "subcategory":"Livestock Farm",
            "type":"Manufacturing & Wholesale Goods"
        }
    ],
    "sg:phone":"+44 1289 307375",
    "sg:postcode":"TD15 1UT",
    "sg:province":"Northumberland",
    "sg:tags":[
        "others"
    ],
    "wof:name":"James Fairbairn",
    "wof:placetype":"venue"
},
  "geometry": {"coordinates":[-2.0070240498,55.7714347839],"type":"Point"}
}