{
  "type": "Feature",
  "properties": {
    "addr:full":"3 High Main Street, Dalmellington Ayr East Ayrshire KA6 7QN",
    "addr:housenumber":"3",
    "addr:postcode":"ayr;ka6 7qn",
    "addr:street":"High Main Street",
    "iso:country":"GB",
    "sg:address":"3 High Main Street, Dalmellington",
    "sg:city":"Ayr",
    "sg:classifiers":[
        {
            "category":"Cafe",
            "type":"Food & Drink"
        },
        {
            "category":"Food & Beverages",
            "subcategory":"Groceries & Convenience Stores",
            "type":"Retail Goods"
        }
    ],
    "sg:phone":"+44 1292 550060",
    "sg:postcode":"KA6 7QN",
    "sg:province":"East Ayrshire",
    "sg:tags":[
        "shop",
        "tea",
        "fish",
        "room",
        "chip"
    ],
    "wof:name":"James & Ann McHattie",
    "wof:placetype":"venue"
},
  "geometry": {"coordinates":[-4.3968081474,55.3235054016],"type":"Point"}
}