{
  "type": "Feature",
  "properties": {
    "iso:country":"GB",
    "sg:address":"14 Mill Street",
    "sg:city":"Bideford",
    "sg:classifiers":[
        {
            "category":"Food & Beverages",
            "subcategory":"Specialty",
            "type":"Retail Goods"
        }
    ],
    "sg:phone":"+44 1237 472715",
    "sg:postcode":"EX39 2JT",
    "sg:province":"Devon",
    "sg:tags":[
        "retailer",
        "product",
        "health"
    ],
    "wof:name":"Bideford Health Foods",
    "wof:placetype":"venue"
},
  "geometry": {"coordinates":[-4.2061038017,51.0186538696],"type":"Point"}
}