{
  "type": "Feature",
  "properties": {
    "addr:full":"Page's Park Station, Billington Road Leighton Buzzard Bedfordshire LU7 4TN",
    "addr:postcode":"lu7 4tn",
    "addr:street":"Billington Road",
    "iso:country":"GB",
    "sg:address":"Page's Park Station, Billington Road",
    "sg:city":"Leighton Buzzard",
    "sg:classifiers":[
        {
            "category":"Landmark",
            "subcategory":"Tourist Attraction",
            "type":"Public Place"
        }
    ],
    "sg:phone":"+44 1525 373888",
    "sg:postcode":"LU7 4TN",
    "sg:province":"Bedfordshire",
    "sg:tags":[
        "interest"
    ],
    "wof:name":"Leighton Buzzard Railway Ltd.",
    "wof:placetype":"venue"
},
  "geometry": {"coordinates":[-0.65221,51.907009],"type":"Point"}
}