{
  "type": "Feature",
  "properties": {
    "iso:country":"GB",
    "sg:address":"8 Market Place, High Street",
    "sg:city":"Alcester",
    "sg:classifiers":[
        {
            "category":"Personal",
            "subcategory":"Beauty Salon",
            "type":"Services"
        },
        {
            "category":"Personal",
            "subcategory":"Barber",
            "type":"Services"
        }
    ],
    "sg:phone":"+44 1789 764688",
    "sg:postcode":"B49 5AE",
    "sg:province":"Warwickshire",
    "sg:tags":[
        "unisex",
        "hairdresser"
    ],
    "wof:name":"Alauna Hair Studio",
    "wof:placetype":"venue"
},
  "geometry": {"coordinates":[-1.860992,52.221798],"type":"Point"}
}