{
  "type": "Feature",
  "properties": {
    "iso:country":"GB",
    "sg:address":"24-26 Busby Road, Clarkston",
    "sg:city":"Glasgow",
    "sg:classifiers":[
        {
            "category":"Banks & Credit Unions",
            "subcategory":"Bank",
            "type":"Services"
        },
        {
            "category":"Banks & Credit Unions",
            "subcategory":"Financial Services",
            "type":"Services"
        }
    ],
    "sg:phone":"+44 141 638 7088",
    "sg:postcode":"G76 7XQ",
    "sg:province":"East Renfrewshire",
    "sg:tags":[
        "building",
        "society",
        "institution"
    ],
    "wof:name":"Alliance & Leicester plc",
    "wof:placetype":"venue"
},
  "geometry": {"coordinates":[-4.277322,55.789726],"type":"Point"}
}