{
  "type": "Feature",
  "properties": {
    "addr:full":"355 Walworth Road London Greater London SE17 2AL",
    "addr:housenumber":"355",
    "addr:postcode":"se17 2al",
    "addr:street":"Walworth Road",
    "iso:country":"GB",
    "sg:address":"355 Walworth Road",
    "sg:city":"London",
    "sg:classifiers":[
        {
            "category":"Banks & Credit Unions",
            "subcategory":"Bank",
            "type":"Services"
        }
    ],
    "sg:phone":"+44 845 604 0010",
    "sg:postcode":"SE17 2AL",
    "sg:province":"Greater London",
    "wof:name":"Halifax Plc",
    "wof:placetype":"venue"
},
  "geometry": {"coordinates":[-0.0942699984,51.4862632751],"type":"Point"}
}