{
  "type": "Feature",
  "properties": {
    "addr:full":"Hadleigh Road Industrial Estate, Arkwright Road Ipswich Suffolk IP2 0UB",
    "addr:postcode":"ip2 0ub",
    "addr:street":"Hadleigh Road Industrial Estate Arkwright Road",
    "iso:country":"GB",
    "sg:address":"Hadleigh Road Industrial Estate, Arkwright Road",
    "sg:city":"Ipswich",
    "sg:classifiers":[
        {
            "category":"Building & Trades",
            "subcategory":"Construction",
            "type":"Services"
        }
    ],
    "sg:phone":"+44 1473 257686",
    "sg:postcode":"IP2 0UB",
    "sg:province":"Suffolk",
    "sg:tags":[
        "joinery"
    ],
    "wof:name":"Magnet",
    "wof:placetype":"venue"
},
  "geometry": {"coordinates":[1.1247860193,52.0581092834],"type":"Point"}
}