{
  "type": "Feature",
  "properties": {
    "addr:full":"Collett Way, Great Western Business Park, Yate Bristol Gloucestershire BS37 5NL",
    "addr:postcode":"bs37 5nl",
    "addr:street":"Collett Way Great",
    "iso:country":"GB",
    "sg:address":"Collett Way, Great Western Business Park, Yate",
    "sg:city":"Bristol",
    "sg:classifiers":[
        {
            "category":"Autos & Motor Vehicles",
            "subcategory":"Fuel & Gas Station",
            "type":"Retail Goods"
        }
    ],
    "sg:postcode":"BS37 5NL",
    "sg:province":"Gloucestershire",
    "sg:tags":[
        "injection"
    ],
    "wof:name":"Shaun Arkinstall Fuel Injection Services",
    "wof:placetype":"venue"
},
  "geometry": {"coordinates":[-2.431978941,51.5469284058],"type":"Point"}
}