{
  "type": "Feature",
  "properties": {
    "addr:full":"42 Old Sneddon Street Paisley Renfrewshire PA3 2AP",
    "addr:housenumber":"42",
    "addr:postcode":"pa3 2ap",
    "addr:street":"Old Sneddon Street",
    "iso:country":"GB",
    "sg:address":"42 Old Sneddon Street",
    "sg:city":"Paisley",
    "sg:classifiers":[
        {
            "category":"Professional",
            "type":"Services"
        }
    ],
    "sg:postcode":"PA3 2AP",
    "sg:province":"Renfrewshire",
    "sg:tags":[
        "caterer"
    ],
    "wof:name":"A N M Catering",
    "wof:placetype":"venue"
},
  "geometry": {"coordinates":[-4.424756,55.847546],"type":"Point"}
}