{
  "type": "Feature",
  "properties": {
    "addr:full":"41 Victoria Road, Old Town Swindon Wiltshire SN1 3AJ",
    "addr:housenumber":"41",
    "addr:postcode":"sn1 3aj",
    "addr:street":"Victoria Road",
    "iso:country":"GB",
    "sg:address":"41 Victoria Road, Old Town",
    "sg:city":"Swindon",
    "sg:classifiers":[
        {
            "category":"Travel",
            "subcategory":"Hotels & Motels",
            "type":"Entertainment"
        }
    ],
    "sg:postcode":"SN1 3AJ",
    "sg:province":"Wiltshire",
    "sg:tags":[
        "house",
        "guest"
    ],
    "wof:name":"Acorn Guest House",
    "wof:placetype":"venue"
},
  "geometry": {"coordinates":[-1.7818139791,51.5617637634],"type":"Point"}
}