{
  "type": "Feature",
  "properties": {
    "addr:full":"175 Steelhouse Lane Wolverhampton West Midlands WV2 2AU",
    "addr:housenumber":"175",
    "addr:postcode":"wv2 2au",
    "addr:street":"Steelhouse Lane",
    "iso:country":"GB",
    "sg:address":"175 Steelhouse Lane",
    "sg:city":"Wolverhampton",
    "sg:classifiers":[
        {
            "category":"Health Services",
            "subcategory":"Doctor",
            "type":"Services"
        }
    ],
    "sg:phone":"+44 1902 455771",
    "sg:postcode":"WV2 2AU",
    "sg:province":"West Midlands",
    "sg:tags":[
        "practitioners"
    ],
    "wof:name":"Grove Medical Centre",
    "wof:placetype":"venue"
},
  "geometry": {"coordinates":[-2.1149830818,52.5765647888],"type":"Point"}
}