{
  "type": "Feature",
  "properties": {
    "iso:country":"GB",
    "sg:address":"Lane End Farm Stables, North Sydmonton",
    "sg:city":"Newbury",
    "sg:classifiers":[
        {
            "category":"Retail",
            "subcategory":"Auto Repair",
            "type":"Services"
        }
    ],
    "sg:postcode":"RG20 4UL",
    "sg:province":"Berkshire",
    "sg:tags":[
        "modification",
        "garage"
    ],
    "wof:name":"McBarnett",
    "wof:placetype":"venue"
},
  "geometry": {"coordinates":[-1.2819260359,51.3561668396],"type":"Point"}
}