{
  "type": "Feature",
  "properties": {
    "iso:country":"GB",
    "sg:address":"St Denys Church Centre, Dundee Rd",
    "sg:city":"Southampton",
    "sg:classifiers":[
        {
            "category":"Place Of Worship",
            "type":"Public Place"
        }
    ],
    "sg:phone":"+44 23 8067 1757",
    "sg:postcode":"SO17 2ND",
    "sg:province":"Hampshire",
    "wof:name":"St Denys Parish Church",
    "wof:placetype":"venue"
},
  "geometry": {"coordinates":[-1.389759,50.925663],"type":"Point"}
}