{
  "type": "Feature",
  "properties": {
    "addr:full":"19 Church St Hertford Hertfordshire SG14 1EJ",
    "addr:housenumber":"19",
    "addr:postcode":"sg14 1ej",
    "addr:street":"Church St",
    "iso:country":"GB",
    "sg:address":"19 Church St",
    "sg:city":"Hertford",
    "sg:classifiers":[
        {
            "category":"Professional",
            "subcategory":"Lawyer & Legal Services",
            "type":"Services"
        }
    ],
    "sg:phone":"+44 1992 509000",
    "sg:postcode":"SG14 1EJ",
    "sg:province":"Hertfordshire",
    "sg:tags":[
        "solicitor"
    ],
    "wof:name":"Watsons",
    "wof:placetype":"venue"
},
  "geometry": {"coordinates":[-0.076981999,51.7958106995],"type":"Point"}
}