{
  "type": "Feature",
  "properties": {
    "addr:full":"91 St Bernards Road, Whitwick Coalville Leicestershire LE67 5GY",
    "addr:housenumber":"91",
    "addr:postcode":"le67 5gy",
    "addr:street":"St Bernards Road",
    "iso:country":"GB",
    "sg:address":"91 St Bernards Road, Whitwick",
    "sg:city":"Coalville",
    "sg:classifiers":[
        {
            "category":"Building & Trades",
            "subcategory":"Plumbing",
            "type":"Services"
        }
    ],
    "sg:phone":"+44 1530 811032",
    "sg:postcode":"LE67 5GY",
    "sg:province":"Leicestershire",
    "sg:tags":[
        "heating"
    ],
    "wof:name":"Companion Alarm & Boiler Services",
    "wof:placetype":"venue"
},
  "geometry": {"coordinates":[-1.3502589464,52.7389793396],"type":"Point"}
}