{
  "type": "Feature",
  "properties": {
    "addr:full":"13 Abbott Road Bournemouth Dorset BH9 1EU",
    "addr:housenumber":"13",
    "addr:postcode":"bh9 1eu",
    "addr:street":"Abbott Road",
    "iso:country":"GB",
    "sg:address":"13 Abbott Road",
    "sg:city":"Bournemouth",
    "sg:classifiers":[
        {
            "category":"Real Estate",
            "subcategory":"Real Estate Services",
            "type":"Services"
        },
        {
            "category":"Building & Trades",
            "subcategory":"Construction",
            "type":"Services"
        }
    ],
    "sg:phone":"+44 1202 516452",
    "sg:postcode":"BH9 1EU",
    "sg:province":"Dorset",
    "sg:tags":[
        "builder"
    ],
    "wof:name":"Keith Bennallack",
    "wof:placetype":"venue"
},
  "geometry": {"coordinates":[-1.8687490225,50.7419281006],"type":"Point"}
}