{
  "type": "Feature",
  "properties": {
    "addr:full":"Wheal Alfred Road Hayle Cornwall TR27 5JT",
    "addr:postcode":"tr27 5jt",
    "addr:street":"Wheal Alfred Road",
    "iso:country":"GB",
    "sg:address":"Wheal Alfred Road",
    "sg:city":"Hayle",
    "sg:classifiers":[
        {
            "category":"Retail",
            "subcategory":"Auto Repair",
            "type":"Services"
        }
    ],
    "sg:phone":"+44 1736 754806",
    "sg:postcode":"TR27 5JT",
    "sg:province":"Cornwall",
    "sg:tags":[
        "modification",
        "garage"
    ],
    "wof:name":"Vehicle Maintenance Service",
    "wof:placetype":"venue"
},
  "geometry": {"coordinates":[-5.3975100517,50.1866874695],"type":"Point"}
}