{
  "type": "Feature",
  "properties": {
    "iso:country":"GB",
    "sg:address":"11 Crow Park Drive, Burton Joyce",
    "sg:city":"Nottingham",
    "sg:classifiers":[
        {
            "category":"Manufacturing",
            "subcategory":"Building Materials",
            "type":"Manufacturing & Wholesale Goods"
        }
    ],
    "sg:postcode":"NG14 5AS",
    "sg:province":"Nottinghamshire",
    "sg:tags":[
        "tile",
        "mnfrs"
    ],
    "wof:name":"Whites (Tiling Contractors) Ltd",
    "wof:placetype":"venue"
},
  "geometry": {"coordinates":[-1.035569,52.987419],"type":"Point"}
}