{
  "type": "Feature",
  "properties": {
    "addr:full":"11 Crow Park Drive, Burton Joyce Nottingham Nottinghamshire NG14 5AS",
    "addr:housenumber":"11",
    "addr:postcode":"ng14 5as",
    "addr:street":"Crow Park Drive;Joyce",
    "iso:country":"GB",
    "sg:address":"11 Crow Park Drive, Burton Joyce",
    "sg:city":"Nottingham",
    "sg:classifiers":[
        {
            "category":"Manufacturing",
            "subcategory":"Building Materials",
            "type":"Manufacturing & Wholesale Goods"
        }
    ],
    "sg:postcode":"NG14 5AS",
    "sg:province":"Nottinghamshire",
    "sg:tags":[
        "tile",
        "mnfrs"
    ],
    "wof:name":"Whites (Tiling Contractors) Ltd",
    "wof:placetype":"venue"
},
  "geometry": {"coordinates":[-1.035569,52.987419],"type":"Point"}
}