{
  "type": "Feature",
  "properties": {
    "addr:full":"The Surgery, 25 Buller Rd Leicester Leicestershire LE4 5GB",
    "addr:housenumber":"25",
    "addr:postcode":"le4 5gb",
    "addr:street":"Buller Rd",
    "iso:country":"GB",
    "sg:address":"The Surgery, 25 Buller Rd",
    "sg:city":"Leicester",
    "sg:classifiers":[
        {
            "category":"Health Services",
            "subcategory":"Doctor",
            "type":"Services"
        }
    ],
    "sg:phone":"+44 116 266 5227",
    "sg:postcode":"LE4 5GB",
    "sg:province":"Leicestershire",
    "sg:tags":[
        "practitioners"
    ],
    "wof:name":"Modi, D",
    "wof:placetype":"venue"
},
  "geometry": {"coordinates":[-1.12407,52.649189],"type":"Point"}
}