{
  "type": "Feature",
  "properties": {
    "iso:country":"GB",
    "sg:address":"56 Mapleton Clo",
    "sg:city":"Newton Abbot",
    "sg:classifiers":[
        {
            "category":"Social Services",
            "subcategory":"Adult Care",
            "type":"Services"
        },
        {
            "category":"Government",
            "subcategory":"Office",
            "type":"Public Place"
        }
    ],
    "sg:postcode":"TQ12 1RF",
    "sg:province":"Devon",
    "sg:tags":[
        "housing",
        "local",
        "sheltered"
    ],
    "wof:name":"Teignbridge District Council",
    "wof:placetype":"venue"
},
  "geometry": {"coordinates":[-3.6241369247,50.5325584412],"type":"Point"}
}