{
  "type": "Feature",
  "properties": {
    "addr:full":"198 Wandsworth Road London Greater London SW8 2JU",
    "addr:housenumber":"198",
    "addr:postcode":"sw8 2ju",
    "addr:street":"Wandsworth Road",
    "iso:country":"GB",
    "sg:address":"198 Wandsworth Road",
    "sg:city":"London",
    "sg:classifiers":[
        {
            "category":"Retail",
            "subcategory":"Laundry & Dry Cleaning",
            "type":"Services"
        }
    ],
    "sg:phone":"+44 20 7622 2602",
    "sg:postcode":"SW8 2JU",
    "sg:province":"Greater London",
    "sg:tags":[
        "cleaner",
        "alteration"
    ],
    "wof:name":"Taniya",
    "wof:placetype":"venue"
},
  "geometry": {"coordinates":[-0.131207,51.475864],"type":"Point"}
}