{
  "type": "Feature",
  "properties": {
    "addr:full":"18 Market Place Fakenham Norfolk NR21 9BH",
    "addr:housenumber":"18",
    "addr:postcode":"nr21 9bh",
    "addr:street":"Market Place",
    "iso:country":"GB",
    "sg:address":"18 Market Place",
    "sg:city":"Fakenham",
    "sg:classifiers":[
        {
            "category":"Professional",
            "subcategory":"Lawyer & Legal Services",
            "type":"Services"
        }
    ],
    "sg:phone":"+44 1328 863231",
    "sg:postcode":"NR21 9BH",
    "sg:province":"Norfolk",
    "sg:tags":[
        "solicitor"
    ],
    "wof:name":"Hayes & Storr",
    "wof:placetype":"venue"
},
  "geometry": {"coordinates":[0.846799016,52.8300170898],"type":"Point"}
}