{
  "type": "Feature",
  "properties": {
    "iso:country":"GB",
    "sg:address":"10 Westover Road",
    "sg:city":"Bournemouth",
    "sg:classifiers":[
        {
            "category":"Personal",
            "subcategory":"Beauty Salon",
            "type":"Services"
        },
        {
            "category":"Personal",
            "subcategory":"Barber",
            "type":"Services"
        }
    ],
    "sg:phone":"+44 1202 293799",
    "sg:postcode":"BH1 2BY",
    "sg:province":"Dorset",
    "sg:tags":[
        "unisex",
        "hairdresser"
    ],
    "wof:name":"Rags Hair Design",
    "wof:placetype":"venue"
},
  "geometry": {"coordinates":[-1.875821,50.719158],"type":"Point"}
}