{
  "type": "Feature",
  "properties": {
    "iso:country":"GB",
    "sg:address":"Manners Avenue, Manners Industrial Estate",
    "sg:city":"Ilkeston",
    "sg:classifiers":[
        {
            "category":"Shopping",
            "type":"Retail Goods"
        }
    ],
    "sg:phone":"+44 115 944 4555",
    "sg:postcode":"DE7 8EF",
    "sg:province":"Derbyshire",
    "sg:tags":[
        "bag"
    ],
    "wof:name":"Peak Packaging Ltd.",
    "wof:placetype":"venue"
},
  "geometry": {"coordinates":[-1.309729,52.977039],"type":"Point"}
}