{
  "type": "Feature",
  "properties": {
    "addr:full":"Lake Field, Morlais Ridge Winchelsea East Sussex TN36 4LL",
    "addr:postcode":"tn36 4ll",
    "addr:street":"Lake;Morlais Ridge",
    "iso:country":"GB",
    "sg:address":"Lake Field, Morlais Ridge",
    "sg:city":"Winchelsea",
    "sg:classifiers":[
        {
            "category":"Manufacturing",
            "subcategory":"Pottery",
            "type":"Manufacturing & Wholesale Goods"
        }
    ],
    "sg:postcode":"TN36 4LL",
    "sg:province":"East Sussex",
    "wof:name":"Gopsall Pottery",
    "wof:placetype":"venue"
},
  "geometry": {"coordinates":[0.7068150043,50.9243011475],"type":"Point"}
}