{
  "type": "Feature",
  "properties": {
    "addr:full":"21 The Mall Bristol City of Bristol BS8 4JG",
    "addr:housenumber":"21",
    "addr:postcode":"bs8 4jg",
    "addr:street":"The Mall",
    "iso:country":"GB",
    "sg:address":"21 The Mall",
    "sg:city":"Bristol",
    "sg:classifiers":[
        {
            "category":"Shopping",
            "subcategory":"Musical Instruments",
            "type":"Retail Goods"
        },
        {
            "category":"Communications",
            "subcategory":"Film & Video Production",
            "type":"Services"
        }
    ],
    "sg:phone":"+44 117 946 7700",
    "sg:postcode":"BS8 4JG",
    "sg:province":"City of Bristol",
    "sg:tags":[
        "recording",
        "studio",
        "sheet",
        "music"
    ],
    "wof:name":"Music Connections West Ltd",
    "wof:placetype":"venue"
},
  "geometry": {"coordinates":[-2.621623,51.455723],"type":"Point"}
}