{
  "type": "Feature",
  "properties": {
    "iso:country":"GB",
    "sg:address":"15 Crossland Way",
    "sg:city":"Doncaster",
    "sg:classifiers":[
        {
            "category":"Personal",
            "subcategory":"Beauty Salon",
            "type":"Services"
        }
    ],
    "sg:phone":"+44 1302 780101",
    "sg:postcode":"DN5 9EX",
    "sg:province":"South Yorkshire",
    "sg:tags":[
        "lady",
        "hairdresser"
    ],
    "wof:name":"Maggies",
    "wof:placetype":"venue"
},
  "geometry": {"coordinates":[-1.165809,53.542755],"type":"Point"}
}