{
  "type": "Feature",
  "properties": {
    "addr:full":"11 Carr Lane, Rawdon Leeds West Yorkshire LS19 6PD",
    "addr:housenumber":"11",
    "addr:postcode":"ls19 6pd",
    "addr:street":"Carr Lane",
    "iso:country":"GB",
    "sg:address":"11 Carr Lane, Rawdon",
    "sg:city":"Leeds",
    "sg:classifiers":[
        {
            "category":"Communications",
            "type":"Services"
        }
    ],
    "sg:phone":"+44 113 250 4318",
    "sg:postcode":"LS19 6PD",
    "sg:province":"West Yorkshire",
    "sg:tags":[
        "audio-visual"
    ],
    "wof:name":"B C Vision",
    "wof:placetype":"venue"
},
  "geometry": {"coordinates":[-1.6701799631,53.8480072021],"type":"Point"}
}