{
  "type": "Feature",
  "properties": {
    "addr:full":"Malvern Road, Powick Worcester Worcestershire WR2 4SN",
    "addr:postcode":"wr2 4sn",
    "addr:street":"Malvern Road",
    "iso:country":"GB",
    "sg:address":"Malvern Road, Powick",
    "sg:city":"Worcester",
    "sg:classifiers":[
        {
            "category":"Farming",
            "subcategory":"Livestock Farm",
            "type":"Manufacturing & Wholesale Goods"
        }
    ],
    "sg:postcode":"WR2 4SN",
    "sg:province":"Worcestershire",
    "sg:tags":[
        "others"
    ],
    "wof:name":"M & A W Rankin",
    "wof:placetype":"venue"
},
  "geometry": {"coordinates":[-2.235819,52.186684],"type":"Point"}
}