{
  "type": "Feature",
  "properties": {
    "addr:full":"12 Sutherland Avenue, Ealing London Greater London W13 8LE",
    "addr:housenumber":"12",
    "addr:postcode":"w13 8le",
    "addr:street":"Sutherland Avenue",
    "iso:country":"GB",
    "sg:address":"12 Sutherland Avenue, Ealing",
    "sg:city":"London",
    "sg:classifiers":[
        {
            "category":"Health Services",
            "subcategory":"Health Practitioner",
            "type":"Services"
        }
    ],
    "sg:postcode":"W13 8LE",
    "sg:province":"Greater London",
    "sg:tags":[
        "hypnotherapists"
    ],
    "wof:name":"de Burgh Julie",
    "wof:placetype":"venue"
},
  "geometry": {"coordinates":[-0.3208650053,51.5166320801],"type":"Point"}
}