{
  "type": "Feature",
  "properties": {
    "addr:full":"Bridgewater House, Bridgewater St Sale Cheshire M33 7EQ",
    "addr:postcode":"m33 7eq",
    "addr:street":"Bridgewater St",
    "iso:country":"GB",
    "sg:address":"Bridgewater House, Bridgewater St",
    "sg:city":"Sale",
    "sg:classifiers":[
        {
            "category":"Wholesale",
            "subcategory":"Medical Equipment & Supplies",
            "type":"Manufacturing & Wholesale Goods"
        }
    ],
    "sg:phone":"+44 161 905 3333",
    "sg:postcode":"M33 7EQ",
    "sg:province":"Cheshire",
    "sg:tags":[
        "hospital"
    ],
    "wof:name":"Allergy Control Treatment Ltd",
    "wof:placetype":"venue"
},
  "geometry": {"coordinates":[-2.3182690144,53.426700592],"type":"Point"}
}