{
  "type": "Feature",
  "properties": {
    "addr:full":"32 Beatrice Street Oswestry Shropshire SY11 1QG",
    "addr:housenumber":"32",
    "addr:postcode":"sy11 1qg",
    "addr:street":"Beatrice Street",
    "iso:country":"GB",
    "sg:address":"32 Beatrice Street",
    "sg:city":"Oswestry",
    "sg:classifiers":[
        {
            "category":"Shopping",
            "subcategory":"Books",
            "type":"Retail Goods"
        }
    ],
    "sg:postcode":"SY11 1QG",
    "sg:province":"Shropshire",
    "sg:tags":[
        "second-hand"
    ],
    "wof:name":"Book World",
    "wof:placetype":"venue"
},
  "geometry": {"coordinates":[-3.0525670052,52.8610839844],"type":"Point"}
}