{
  "type": "Feature",
  "properties": {
    "addr:full":"Chancery Court, Lincoln Road High Wycombe Buckinghamshire HP12 3RE",
    "addr:postcode":"hp12 3re",
    "addr:street":"Chancery Court Lincoln Road",
    "iso:country":"GB",
    "sg:address":"Chancery Court, Lincoln Road",
    "sg:city":"High Wycombe",
    "sg:classifiers":[
        {
            "category":"Professional",
            "subcategory":"Computer Services",
            "type":"Services"
        }
    ],
    "sg:postcode":"HP12 3RE",
    "sg:province":"Buckinghamshire",
    "sg:tags":[
        "system",
        "software"
    ],
    "wof:name":"T J McCabe & Associates U K Ltd.",
    "wof:placetype":"venue"
},
  "geometry": {"coordinates":[-0.772314,51.622009],"type":"Point"}
}