{
  "type": "Feature",
  "properties": {
    "addr:full":"Flat 4 22 Lansdown Terrace, Malvern Road Cheltenham Gloucestershire GL50 3JP",
    "addr:housenumber":"22",
    "addr:postcode":"gl50 3jp",
    "addr:street":"Lansdown Terrace Malvern Road",
    "iso:country":"GB",
    "sg:address":"Flat 4 22 Lansdown Terrace, Malvern Road",
    "sg:city":"Cheltenham",
    "sg:classifiers":[
        {
            "category":"Building & Trades",
            "subcategory":"Construction",
            "type":"Services"
        }
    ],
    "sg:postcode":"GL50 3JP",
    "sg:province":"Gloucestershire",
    "sg:tags":[
        "dry",
        "lining",
        "plasterers",
        "screeders"
    ],
    "wof:name":"C K Plastering",
    "wof:placetype":"venue"
},
  "geometry": {"coordinates":[-2.078459,51.898048],"type":"Point"}
}