{
  "type": "Feature",
  "properties": {
    "iso:country":"GB",
    "sg:address":"Lee Carter Health Studio, Off Lowergate",
    "sg:city":"Clitheroe",
    "sg:classifiers":[
        {
            "category":"Sports & Exercise",
            "subcategory":"Gym",
            "type":"Entertainment"
        },
        {
            "category":"Health Services",
            "subcategory":"Podiatrist",
            "type":"Services"
        }
    ],
    "sg:phone":"+44 1200 424475",
    "sg:postcode":"BB7 1AD",
    "sg:province":"Lancashire",
    "sg:tags":[
        "fitness",
        "podiatrists",
        "chiropodist",
        "centre"
    ],
    "wof:name":"Lee Carter Health Studio",
    "wof:placetype":"venue"
},
  "geometry": {"coordinates":[-2.391749,53.87278],"type":"Point"}
}