{
  "type": "Feature",
  "properties": {
    "addr:full":"136 Windsor Avenue, Penn Wolverhampton Staffordshire WV4 4BN",
    "addr:housenumber":"136",
    "addr:postcode":"wv4 4bn",
    "addr:street":"Windsor Avenue",
    "iso:country":"GB",
    "sg:address":"136 Windsor Avenue, Penn",
    "sg:city":"Wolverhampton",
    "sg:classifiers":[
        {
            "category":"Professional",
            "subcategory":"Engineering",
            "type":"Services"
        }
    ],
    "sg:phone":"+44 1902 337448",
    "sg:postcode":"WV4 4BN",
    "sg:province":"Staffordshire",
    "sg:tags":[
        "contractor",
        "electrical",
        "engineer"
    ],
    "wof:name":"Pennwood Electrical Services",
    "wof:placetype":"venue"
},
  "geometry": {"coordinates":[-2.15573,52.566864],"type":"Point"}
}