{
  "type": "Feature",
  "properties": {
    "addr:full":"1002a Pollokshaws Rd Glasgow Glasgow City G41 2HG",
    "addr:housenumber":"1002a",
    "addr:postcode":"g41 2hg",
    "addr:street":"Pollokshaws Rd",
    "iso:country":"GB",
    "sg:address":"1002a Pollokshaws Rd",
    "sg:city":"Glasgow",
    "sg:classifiers":[
        {
            "category":"Shopping",
            "subcategory":"Pharmacy",
            "type":"Retail Goods"
        }
    ],
    "sg:phone":"+44 141 649 7870",
    "sg:postcode":"G41 2HG",
    "sg:province":"Glasgow City",
    "sg:tags":[
        "store",
        "drug"
    ],
    "wof:name":"Familycare",
    "wof:placetype":"venue"
},
  "geometry": {"coordinates":[-4.278165,55.832268],"type":"Point"}
}