{
  "type": "Feature",
  "properties": {
    "iso:country":"GB",
    "sg:address":"14 Heathside Way, Hartley Wintney",
    "sg:city":"Hook",
    "sg:classifiers":[
        {
            "category":"Building & Trades",
            "subcategory":"Cleaning & Sanitation",
            "type":"Services"
        }
    ],
    "sg:phone":"+44 1252 845848",
    "sg:postcode":"RG27 8SG",
    "sg:province":"Berkshire",
    "sg:tags":[
        "facility"
    ],
    "wof:name":"The Cranwood Partnership Ltd.",
    "wof:placetype":"venue"
},
  "geometry": {"coordinates":[-0.904753983,51.3084831238],"type":"Point"}
}