{
  "type": "Feature",
  "properties": {
    "iso:country":"GB",
    "sg:address":"St Margarets House Nursing Home, Williamsburgh, Elie",
    "sg:city":"Leven",
    "sg:classifiers":[
        {
            "category":"Health Services",
            "subcategory":"Nursing And Care Facility",
            "type":"Services"
        }
    ],
    "sg:phone":"+44 1333 330124",
    "sg:postcode":"KY9 1BA",
    "sg:province":"Fife",
    "sg:tags":[
        "home"
    ],
    "wof:name":"St Margarets House Nursing Home",
    "wof:placetype":"venue"
},
  "geometry": {"coordinates":[-2.817634,56.190788],"type":"Point"}
}