{
  "type": "Feature",
  "properties": {
    "addr:full":"Community Clinic, 78 Mattock La West Ealing Greater London W13 9NZ",
    "addr:housenumber":"78",
    "addr:postcode":"w13 9nz",
    "addr:street":"Mattock La West",
    "iso:country":"GB",
    "sg:address":"Community Clinic, 78 Mattock La",
    "sg:city":"West Ealing",
    "sg:classifiers":[
        {
            "category":"Health Services",
            "subcategory":"Clinic",
            "type":"Services"
        }
    ],
    "sg:phone":"+44 20 8574 2444",
    "sg:postcode":"W13 9NZ",
    "sg:province":"Greater London",
    "sg:tags":[
        "nh"
    ],
    "wof:name":"Mattock Lane Health Centre",
    "wof:placetype":"venue"
},
  "geometry": {"coordinates":[-0.3154099882,51.5100402832],"type":"Point"}
}