{
  "type": "Feature",
  "properties": {
    "iso:country":"GB",
    "sg:address":"422 Bromford Road",
    "sg:city":"Birmingham",
    "sg:classifiers":[
        {
            "category":"Professional",
            "subcategory":"Engineering",
            "type":"Services"
        },
        {
            "category":"Building & Trades",
            "subcategory":"Electrical",
            "type":"Services"
        }
    ],
    "sg:postcode":"B36 8JH",
    "sg:province":"West Midlands",
    "sg:tags":[
        "engineer",
        "electrician",
        "contractor"
    ],
    "wof:name":"CLIVE A MARSHALL",
    "wof:placetype":"venue"
},
  "geometry": {"coordinates":[-1.81196,52.500809],"type":"Point"}
}