{
  "type": "Feature",
  "properties": {
    "addr:full":"129 Singlewell Road Gravesend Kent DA11 7QA",
    "addr:housenumber":"129",
    "addr:postcode":"da11 7qa",
    "addr:street":"Singlewell Road",
    "iso:country":"GB",
    "sg:address":"129 Singlewell Road",
    "sg:city":"Gravesend",
    "sg:classifiers":[
        {
            "category":"Government",
            "subcategory":"Post Office",
            "type":"Public Place"
        }
    ],
    "sg:phone":"+44 1474 533207",
    "sg:postcode":"DA11 7QA",
    "sg:province":"Kent",
    "wof:name":"Singlewell Road Post Office & Newsagents",
    "wof:placetype":"venue"
},
  "geometry": {"coordinates":[0.367689997,51.4288787842],"type":"Point"}
}