{
  "type": "Feature",
  "properties": {
    "addr:full":"40 Long Causeway Peterborough Cambridgeshire PE1 1YJ",
    "addr:housenumber":"40",
    "addr:postcode":"pe1 1yj",
    "addr:street":"Long Causeway",
    "iso:country":"GB",
    "sg:address":"40 Long Causeway",
    "sg:city":"Peterborough",
    "sg:classifiers":[
        {
            "category":"Banks & Credit Unions",
            "subcategory":"Bank",
            "type":"Services"
        }
    ],
    "sg:phone":"+44 800 226341",
    "sg:postcode":"PE1 1YJ",
    "sg:province":"Cambridgeshire",
    "sg:tags":[
        "financial",
        "institution"
    ],
    "wof:name":"Cheltenham & Gloucester plc",
    "wof:placetype":"venue"
},
  "geometry": {"coordinates":[-0.2422820032,52.5727157593],"type":"Point"}
}