{
  "type": "Feature",
  "properties": {
    "iso:country":"GB",
    "sg:address":"215 Maryhill Road",
    "sg:city":"Glasgow",
    "sg:classifiers":[
        {
            "category":"Banks & Credit Unions",
            "subcategory":"Bank",
            "type":"Services"
        }
    ],
    "sg:phone":"+44 141 332 0220",
    "sg:postcode":"G20 7XJ",
    "sg:province":"Glasgow City",
    "sg:tags":[
        "broker",
        "mortgage"
    ],
    "wof:name":"FAIR DEAL MORTGAGE SERVICES",
    "wof:placetype":"venue"
},
  "geometry": {"coordinates":[-4.270797,55.874493],"type":"Point"}
}