{
  "type": "Feature",
  "properties": {
    "addr:full":"205 Oxford Road Reading Berkshire RG1 7PX",
    "addr:housenumber":"205",
    "addr:postcode":"rg1 7px",
    "addr:street":"Oxford Road",
    "iso:country":"GB",
    "sg:address":"205 Oxford Road",
    "sg:city":"Reading",
    "sg:classifiers":[
        {
            "category":"Shopping",
            "subcategory":"Department Store",
            "type":"Retail Goods"
        }
    ],
    "sg:phone":"+44 118 958 2517",
    "sg:postcode":"RG1 7PX",
    "sg:province":"Berkshire",
    "wof:name":"Anand Food Store",
    "wof:placetype":"venue"
},
  "geometry": {"coordinates":[-0.98616,51.455338],"type":"Point"}
}