{
  "type": "Feature",
  "properties": {
    "iso:country":"GB",
    "sg:address":"1 Sandown Road",
    "sg:city":"Leicester",
    "sg:classifiers":[
        {
            "category":"Professional",
            "subcategory":"Engineering",
            "type":"Services"
        },
        {
            "category":"Building & Trades",
            "subcategory":"Electrical",
            "type":"Services"
        }
    ],
    "sg:phone":"+44 116 270 2289",
    "sg:postcode":"LE2 2BJ",
    "sg:province":"Leicestershire",
    "sg:tags":[
        "engineer",
        "electrician",
        "contractor"
    ],
    "wof:name":"John Morrison",
    "wof:placetype":"venue"
},
  "geometry": {"coordinates":[-1.1067340374,52.6161842346],"type":"Point"}
}