{
  "type": "Feature",
  "properties": {
    "addr:full":"P O Box 14526 Dunfermline Fife KY11 4ZD",
    "addr:housenumber":"box",
    "addr:postcode":"14526;ky11 4zd",
    "iso:country":"GB",
    "sg:address":"P O Box 14526",
    "sg:city":"Dunfermline",
    "sg:classifiers":[
        {
            "category":"Shopping",
            "subcategory":"Stationery & Office Supplies",
            "type":"Retail Goods"
        }
    ],
    "sg:postcode":"KY11 4ZD",
    "sg:province":"Fife",
    "sg:tags":[
        "item",
        "promotional"
    ],
    "wof:name":"Grange Enterprise Ltd",
    "wof:placetype":"venue"
},
  "geometry": {"coordinates":[-3.4291000366,56.0665206909],"type":"Point"}
}