{
  "type": "Feature",
  "properties": {
    "addr:full":"105 Ardrossan Gardens Worcester Park Surrey KT4 7AY",
    "addr:housenumber":"105",
    "addr:postcode":"kt4 7ay",
    "addr:street":"Ardrossan Gardens;Park",
    "iso:country":"GB",
    "sg:address":"105 Ardrossan Gardens",
    "sg:city":"Worcester Park",
    "sg:classifiers":[
        {
            "category":"Building & Trades",
            "subcategory":"Construction",
            "type":"Services"
        }
    ],
    "sg:phone":"+44 20 8337 3847",
    "sg:postcode":"KT4 7AY",
    "sg:province":"Surrey",
    "sg:tags":[
        "roofing"
    ],
    "wof:name":"Just Roofing",
    "wof:placetype":"venue"
},
  "geometry": {"coordinates":[-0.2458440065,51.3719711304],"type":"Point"}
}