{
  "type": "Feature",
  "properties": {
    "iso:country":"GB",
    "sg:address":"Suite 103, 73 Holborn St",
    "sg:city":"Aberdeen",
    "sg:classifiers":[
        {
            "category":"Professional",
            "subcategory":"Research",
            "type":"Services"
        }
    ],
    "sg:phone":"+44 1224 581919",
    "sg:postcode":"AB10 6BR",
    "sg:province":"Aberdeen City",
    "sg:tags":[
        "market"
    ],
    "wof:name":"Copus Associates Ltd",
    "wof:placetype":"venue"
},
  "geometry": {"coordinates":[-2.113209,57.14114],"type":"Point"}
}