{
  "type": "Feature",
  "properties": {
    "iso:country":"GB",
    "sg:address":"Star Rooms, Springfield Road",
    "sg:city":"Tunbridge Wells",
    "sg:classifiers":[
        {
            "category":"Farming",
            "subcategory":"Nursery",
            "type":"Manufacturing & Wholesale Goods"
        }
    ],
    "sg:phone":"+44 1892 542173",
    "sg:postcode":"TN4 0RD",
    "sg:province":"Kent",
    "sg:tags":[
        "creche"
    ],
    "wof:name":"West Kent College Nursery",
    "wof:placetype":"venue"
},
  "geometry": {"coordinates":[0.258178,51.157719],"type":"Point"}
}