{
  "type": "Feature",
  "properties": {
    "iso:country":"GB",
    "sg:address":"43 Spring Plat",
    "sg:city":"Crawley",
    "sg:classifiers":[
        {
            "category":"Organizations",
            "subcategory":"Non-profit Organization",
            "type":"Services"
        }
    ],
    "sg:phone":"+44 1293 519931",
    "sg:postcode":"RH10 7DG",
    "sg:province":"Surrey",
    "sg:tags":[
        "organisation",
        "voluntary",
        "charity"
    ],
    "wof:name":"United Response",
    "wof:placetype":"venue"
},
  "geometry": {"coordinates":[-0.1537829936,51.1148376465],"type":"Point"}
}