{
  "type": "Feature",
  "properties": {
    "addr:full":"6 Denbigh Street Llanrwst Conwy LL26 0LL",
    "addr:housenumber":"6",
    "addr:postcode":"ll26 0ll",
    "addr:street":"Denbigh Street",
    "iso:country":"GB",
    "sg:address":"6 Denbigh Street",
    "sg:city":"Llanrwst",
    "sg:classifiers":[
        {
            "category":"Professional",
            "subcategory":"Employment Agencies",
            "type":"Services"
        }
    ],
    "sg:phone":"+44 1492 613400",
    "sg:postcode":"LL26 0LL",
    "sg:province":"Conwy",
    "sg:tags":[
        "consultant"
    ],
    "wof:name":"Job Centre",
    "wof:placetype":"venue"
},
  "geometry": {"coordinates":[-3.796854,53.139015],"type":"Point"}
}