{
  "type": "Feature",
  "properties": {
    "iso:country":"GB",
    "sg:address":"2 Bathford Hill",
    "sg:city":"Bath",
    "sg:classifiers":[
        {
            "category":"Bars & Pubs",
            "type":"Food & Drink"
        }
    ],
    "sg:phone":"+44 1225 852297",
    "sg:postcode":"BA1 7SL",
    "sg:province":"Bath and North East Somerset",
    "sg:tags":[
        "pubs",
        "inn"
    ],
    "wof:name":"Crown Inn The",
    "wof:placetype":"venue"
},
  "geometry": {"coordinates":[-2.306972,51.400871],"type":"Point"}
}