{
  "type": "Feature",
  "properties": {
    "addr:full":"Higher Drive Banstead Surrey SM7 1PL",
    "addr:postcode":"sm7 1pl",
    "addr:street":"Higher Drive",
    "iso:country":"GB",
    "sg:address":"Higher Drive",
    "sg:city":"Banstead",
    "sg:classifiers":[
        {
            "category":"Education",
            "subcategory":"Music School",
            "type":"Public Place"
        }
    ],
    "sg:postcode":"SM7 1PL",
    "sg:province":"Surrey",
    "sg:tags":[
        "teacher"
    ],
    "wof:name":"John Dudley & Nancy Long Singing Lessons",
    "wof:placetype":"venue"
},
  "geometry": {"coordinates":[-0.2270859927,51.336139679],"type":"Point"}
}