{
  "type": "Feature",
  "properties": {
    "addr:full":"Ferrybridge, Junction Off A1-m62 Knottingley North Yorkshire WF11 0AF",
    "addr:postcode":"wf11 0af",
    "addr:street":"Ferrybridge;Off;Knottingley",
    "iso:country":"GB",
    "sg:address":"Ferrybridge, Junction Off A1-m62",
    "sg:city":"Knottingley",
    "sg:classifiers":[
        {
            "category":"Autos & Motor Vehicles",
            "subcategory":"Fuel & Gas Station",
            "type":"Retail Goods"
        }
    ],
    "sg:phone":"+44 1977 672767",
    "sg:postcode":"WF11 0AF",
    "sg:province":"North Yorkshire",
    "sg:tags":[
        "hr",
        "petrol"
    ],
    "wof:name":"Granada Services Area",
    "wof:placetype":"venue"
},
  "geometry": {"coordinates":[-1.2146890163,53.686290741],"type":"Point"}
}