{
  "type": "Feature",
  "properties": {
    "addr:full":"177 Greenford Road Greenford Greater London UB6 8QX",
    "addr:housenumber":"177",
    "addr:postcode":"ub6 8qx",
    "addr:street":"Greenford Road",
    "iso:country":"GB",
    "sg:address":"177 Greenford Road",
    "sg:city":"Greenford",
    "sg:classifiers":[
        {
            "category":"Banks & Credit Unions",
            "subcategory":"Bank",
            "type":"Services"
        }
    ],
    "sg:phone":"+44 20 8218 6900",
    "sg:postcode":"UB6 8QX",
    "sg:province":"Greater London",
    "wof:name":"Barclays Bank Plc",
    "wof:placetype":"venue"
},
  "geometry": {"coordinates":[-0.3523530066,51.5279121399],"type":"Point"}
}