{
  "type": "Feature",
  "properties": {
    "addr:full":"18a Park Road Peterborough Cambridgeshire PE1 2TD",
    "addr:housenumber":"18a",
    "addr:postcode":"pe1 2td",
    "addr:street":"Park Road",
    "iso:country":"GB",
    "sg:address":"18a Park Road",
    "sg:city":"Peterborough",
    "sg:classifiers":[
        {
            "category":"Personal",
            "subcategory":"Beauty Salon",
            "type":"Services"
        }
    ],
    "sg:postcode":"PE1 2TD",
    "sg:province":"Cambridgeshire",
    "wof:name":"T Sloane",
    "wof:placetype":"venue"
},
  "geometry": {"coordinates":[-0.242811,52.57515],"type":"Point"}
}