{
  "type": "Feature",
  "properties": {
    "iso:country":"GB",
    "sg:address":"67-73 Woodgrange Road, Forest Gate",
    "sg:city":"London",
    "sg:classifiers":[
        {
            "category":"Food & Beverages",
            "subcategory":"Supermarket",
            "type":"Retail Goods"
        }
    ],
    "sg:phone":"+44 20 8534 2430",
    "sg:postcode":"E7 0EL",
    "sg:province":"Greater London",
    "wof:name":"Somerfield",
    "wof:placetype":"venue"
},
  "geometry": {"coordinates":[0.024642,51.548969],"type":"Point"}
}