{
  "type": "Feature",
  "properties": {
    "addr:full":"62 Richmond Dr, Perton Wolverhampton Shropshire WV6 7RR",
    "addr:housenumber":"62",
    "addr:postcode":"wv6 7rr",
    "addr:street":"Richmond Dr",
    "iso:country":"GB",
    "sg:address":"62 Richmond Dr, Perton",
    "sg:city":"Wolverhampton",
    "sg:classifiers":[
        {
            "category":"Manufacturing",
            "subcategory":"Wood Products",
            "type":"Manufacturing & Wholesale Goods"
        }
    ],
    "sg:phone":"+44 1902 750849",
    "sg:postcode":"WV6 7RR",
    "sg:province":"Shropshire",
    "sg:tags":[
        "packaging",
        "crate",
        "pallets"
    ],
    "wof:name":"Arco Packaging Machinery Ltd",
    "wof:placetype":"venue"
},
  "geometry": {"coordinates":[-2.194257021,52.5902938843],"type":"Point"}
}