{
  "type": "Feature",
  "properties": {
    "addr:full":"97a High Street Huntingdon Cambridgeshire PE29 3DP",
    "addr:housenumber":"97a",
    "addr:postcode":"pe29 3dp",
    "addr:street":"High Street",
    "iso:country":"GB",
    "sg:address":"97a High Street",
    "sg:city":"Huntingdon",
    "sg:classifiers":[
        {
            "category":"Food & Beverages",
            "subcategory":"Bakery",
            "type":"Retail Goods"
        }
    ],
    "sg:phone":"+44 1480 451566",
    "sg:postcode":"PE29 3DP",
    "sg:province":"Cambridgeshire",
    "sg:tags":[
        "baker"
    ],
    "wof:name":"Bonnett's (Bakers) Ltd.",
    "wof:placetype":"venue"
},
  "geometry": {"coordinates":[-0.185197,52.331196],"type":"Point"}
}