{
  "type": "Feature",
  "properties": {
    "iso:country":"GB",
    "sg:address":"56 Derbeth Cres",
    "sg:city":"Aberdeen",
    "sg:classifiers":[
        {
            "category":"Building & Trades",
            "subcategory":"Construction",
            "type":"Services"
        }
    ],
    "sg:phone":"+44 1224 691856",
    "sg:postcode":"AB16 6LN",
    "sg:province":"Aberdeen City",
    "sg:tags":[
        "builder"
    ],
    "wof:name":"Davidson Builders (Aberdeen) Ltd",
    "wof:placetype":"venue"
},
  "geometry": {"coordinates":[-2.1752400398,57.1513061523],"type":"Point"}
}