{
  "type": "Feature",
  "properties": {
    "iso:country":"GB",
    "sg:address":"455 Finchley Rd",
    "sg:city":"Hampstead",
    "sg:classifiers":[
        {
            "category":"Cafe",
            "type":"Food & Drink"
        }
    ],
    "sg:phone":"+44 20 7813 5850",
    "sg:postcode":"NW3 6HN",
    "sg:province":"Greater London",
    "sg:tags":[
        "tea",
        "room"
    ],
    "wof:name":"Earl Of Sandwich",
    "wof:placetype":"venue"
},
  "geometry": {"coordinates":[-0.188139,51.5527],"type":"Point"}
}