{
  "type": "Feature",
  "properties": {
    "iso:country":"GB",
    "sg:address":"118 Cavendish Place",
    "sg:city":"Eastbourne",
    "sg:classifiers":[
        {
            "category":"Shopping",
            "subcategory":"Pharmacy",
            "type":"Retail Goods"
        }
    ],
    "sg:phone":"+44 1323 721836",
    "sg:postcode":"BN21 3TZ",
    "sg:province":"East Sussex",
    "sg:tags":[
        "pharmacist",
        "chemist"
    ],
    "wof:name":"Cavendish Place Pharmacy",
    "wof:placetype":"venue"
},
  "geometry": {"coordinates":[0.288212,50.771538],"type":"Point"}
}