{
  "type": "Feature",
  "properties": {
    "addr:full":"29-31 Brook Street Selby East Riding of Yorkshire YO8 4AL",
    "addr:housenumber":"29-31",
    "addr:postcode":"yo8 4al",
    "addr:street":"Brook Street",
    "iso:country":"GB",
    "sg:address":"29-31 Brook Street",
    "sg:city":"Selby",
    "sg:classifiers":[
        {
            "category":"Home & Garden",
            "subcategory":"Home Furnishings",
            "type":"Retail Goods"
        }
    ],
    "sg:phone":"+44 1757 705025",
    "sg:postcode":"YO8 4AL",
    "sg:province":"East Riding of Yorkshire",
    "sg:tags":[
        "furnishers",
        "planner",
        "kitchen"
    ],
    "wof:name":"J P David's (Home Improvements) Ltd.",
    "wof:placetype":"venue"
},
  "geometry": {"coordinates":[-1.0742709637,53.7820396423],"type":"Point"}
}