{
  "type": "Feature",
  "properties": {
    "addr:full":"Worminghall Road, Oakley Aylesbury Buckinghamshire HP18 9UL",
    "addr:postcode":"hp18 9ul",
    "addr:street":"Worminghall Road",
    "iso:country":"GB",
    "sg:address":"Worminghall Road, Oakley",
    "sg:city":"Aylesbury",
    "sg:classifiers":[
        {
            "category":"Building & Trades",
            "subcategory":"Plumbing",
            "type":"Services"
        }
    ],
    "sg:phone":"+44 1844 338137",
    "sg:postcode":"HP18 9UL",
    "sg:province":"Buckinghamshire",
    "sg:tags":[
        "merchant",
        "plumbers'"
    ],
    "wof:name":"Watermark P H S Ltd.",
    "wof:placetype":"venue"
},
  "geometry": {"coordinates":[-1.0726189613,51.8060340881],"type":"Point"}
}