{
  "type": "Feature",
  "properties": {
    "addr:full":"Ockford Farm Northiam Rye East Sussex TN31 6HP",
    "addr:postcode":"tn31 6hp",
    "iso:country":"GB",
    "sg:address":"Ockford Farm Northiam",
    "sg:city":"Rye",
    "sg:classifiers":[
        {
            "category":"Food & Beverages",
            "subcategory":"Farmers Market",
            "type":"Retail Goods"
        }
    ],
    "sg:phone":"+44 1797 253110",
    "sg:postcode":"TN31 6HP",
    "sg:province":"East Sussex",
    "sg:tags":[
        "farm",
        "shop",
        "pyo"
    ],
    "wof:name":"Frank Williams & Son",
    "wof:placetype":"venue"
},
  "geometry": {"coordinates":[0.6021469831,50.9979743958],"type":"Point"}
}