{
  "type": "Feature",
  "properties": {
    "iso:country":"GB",
    "sg:address":"Marden House, Alfriston Road",
    "sg:city":"Seaford",
    "sg:classifiers":[
        {
            "category":"Professional",
            "subcategory":"Employment Agencies",
            "type":"Services"
        }
    ],
    "sg:postcode":"BN25 3QG",
    "sg:province":"East Sussex",
    "sg:tags":[
        "consultant"
    ],
    "wof:name":"Gold Helm London Ltd",
    "wof:placetype":"venue"
},
  "geometry": {"coordinates":[0.149049,50.793617],"type":"Point"}
}