{
  "type": "Feature",
  "properties": {
    "iso:country":"GB",
    "sg:address":"Saxonbrook Medical, Maidenbower Sq",
    "sg:city":"Crawley",
    "sg:classifiers":[
        {
            "category":"Health Services",
            "subcategory":"Doctor",
            "type":"Services"
        }
    ],
    "sg:phone":"+44 1293 888183",
    "sg:postcode":"RH10 7QH",
    "sg:province":"Surrey",
    "sg:tags":[
        "practitioners"
    ],
    "wof:name":"Thomas, G",
    "wof:placetype":"venue"
},
  "geometry": {"coordinates":[-0.1499679983,51.1068496704],"type":"Point"}
}