{
  "type": "Feature",
  "properties": {
    "iso:country":"GB",
    "sg:address":"53 Old Fallings La",
    "sg:city":"Wolverhampton",
    "sg:classifiers":[
        {
            "category":"Building & Trades",
            "subcategory":"Construction",
            "type":"Services"
        }
    ],
    "sg:phone":"+44 1902 307505",
    "sg:postcode":"WV10 8BH",
    "sg:province":"Staffordshire",
    "sg:tags":[
        "dry",
        "lining",
        "plasterers",
        "screeders"
    ],
    "wof:name":"Creative Plaster",
    "wof:placetype":"venue"
},
  "geometry": {"coordinates":[-2.105474,52.609203],"type":"Point"}
}