{
  "type": "Feature",
  "properties": {
    "addr:full":"The Old Cinema, Raglan Road Hengoed Caerphilly CF82 7LY",
    "addr:postcode":"cf82 7ly",
    "addr:street":"Raglan Road",
    "iso:country":"GB",
    "sg:address":"The Old Cinema, Raglan Road",
    "sg:city":"Hengoed",
    "sg:classifiers":[
        {
            "category":"Retail",
            "subcategory":"Repair Shop",
            "type":"Services"
        },
        {
            "category":"Manufacturing",
            "subcategory":"Furniture",
            "type":"Manufacturing & Wholesale Goods"
        }
    ],
    "sg:phone":"+44 1443 815525",
    "sg:postcode":"CF82 7LY",
    "sg:province":"Caerphilly",
    "sg:tags":[
        "mnfr",
        "upholsterer"
    ],
    "wof:name":"New Look Upholstery",
    "wof:placetype":"venue"
},
  "geometry": {"coordinates":[-3.231799,51.648319],"type":"Point"}
}