{
  "type": "Feature",
  "properties": {
    "addr:full":"3-5 Hampden Square, Osidge Lane, Southgate London Greater London N14 5JP",
    "addr:housenumber":"3-5",
    "addr:postcode":"n14 5jp",
    "addr:street":"Hampden Square Osidge Lane",
    "iso:country":"GB",
    "sg:address":"3-5 Hampden Square, Osidge Lane, Southgate",
    "sg:city":"London",
    "sg:classifiers":[
        {
            "category":"Home & Garden",
            "subcategory":"Building Materials",
            "type":"Retail Goods"
        }
    ],
    "sg:phone":"+44 20 8368 6463",
    "sg:postcode":"N14 5JP",
    "sg:province":"Greater London",
    "sg:tags":[
        "furnishers",
        "bathroom",
        "planner"
    ],
    "wof:name":"Venezia Bathrooms",
    "wof:placetype":"venue"
},
  "geometry": {"coordinates":[-0.142575,51.631866],"type":"Point"}
}