{
  "type": "Feature",
  "properties": {
    "iso:country":"GB",
    "sg:address":"21 Queensville Avenue",
    "sg:city":"Stafford",
    "sg:classifiers":[
        {
            "category":"Building & Trades",
            "subcategory":"Landscaping Services",
            "type":"Services"
        }
    ],
    "sg:phone":"+44 1785 225044",
    "sg:postcode":"ST17 4LS",
    "sg:province":"Staffordshire",
    "sg:tags":[
        "landscape",
        "contractor"
    ],
    "wof:name":"Enhance Landscaping",
    "wof:placetype":"venue"
},
  "geometry": {"coordinates":[-2.0999178886,52.7995567322],"type":"Point"}
}