{
  "type": "Feature",
  "properties": {
    "iso:country":"GB",
    "sg:address":"Fairview Industrial Estate, Holland Road",
    "sg:city":"Oxted",
    "sg:classifiers":[
        {
            "category":"Professional",
            "subcategory":"Accounting & Tax Preparation",
            "type":"Services"
        }
    ],
    "sg:postcode":"RH8 9BD",
    "sg:province":"Surrey",
    "sg:tags":[
        "accountant"
    ],
    "wof:name":"Barry Compton & Co",
    "wof:placetype":"venue"
},
  "geometry": {"coordinates":[-0.00468,51.254894],"type":"Point"}
}