{
  "type": "Feature",
  "properties": {
    "addr:full":"Civic Hall Totnes Devon TQ9 5SF",
    "addr:postcode":"tq9 5sf",
    "iso:country":"GB",
    "sg:address":"Civic Hall",
    "sg:city":"Totnes",
    "sg:classifiers":[
        {
            "category":"Fast Food",
            "type":"Food & Drink"
        }
    ],
    "sg:postcode":"TQ9 5SF",
    "sg:province":"Devon",
    "sg:tags":[
        "away",
        "take"
    ],
    "wof:name":"Julie Alty",
    "wof:placetype":"venue"
},
  "geometry": {"coordinates":[-3.688092947,50.4341468811],"type":"Point"}
}