{
  "type": "Feature",
  "properties": {
    "iso:country":"GB",
    "sg:address":"37 Eastgate Centre",
    "sg:city":"Basildon",
    "sg:classifiers":[
        {
            "category":"Home & Garden",
            "subcategory":"Home Furnishings",
            "type":"Retail Goods"
        },
        {
            "category":"Shopping",
            "subcategory":"Shoes",
            "type":"Retail Goods"
        }
    ],
    "sg:postcode":"SS14 1AE",
    "sg:province":"Essex",
    "sg:tags":[
        "shop",
        "candle"
    ],
    "wof:name":"House of Wax Ltd",
    "wof:placetype":"venue"
},
  "geometry": {"coordinates":[0.46053,51.569389],"type":"Point"}
}