{
  "type": "Feature",
  "properties": {
    "iso:country":"GB",
    "sg:address":"Marston Magna, Marston Magna",
    "sg:city":"Yeovil",
    "sg:classifiers":[
        {
            "category":"Education",
            "subcategory":"Music School",
            "type":"Public Place"
        }
    ],
    "sg:postcode":"BA22 8BZ",
    "sg:province":"Dorset",
    "wof:name":"Sharps & Flats",
    "wof:placetype":"venue"
},
  "geometry": {"coordinates":[-2.580861,50.999226],"type":"Point"}
}