{
  "type": "Feature",
  "properties": {
    "iso:country":"GB",
    "sg:address":"238a Green Lanes",
    "sg:city":"London",
    "sg:classifiers":[
        {
            "category":"Professional",
            "subcategory":"Art Services",
            "type":"Services"
        }
    ],
    "sg:phone":"+44 20 8882 1977",
    "sg:postcode":"N13 5TU",
    "sg:province":"Greater London",
    "sg:tags":[
        "photographer"
    ],
    "wof:name":"Zoom",
    "wof:placetype":"venue"
},
  "geometry": {"coordinates":[-0.108934,51.617493],"type":"Point"}
}