{
  "type": "Feature",
  "properties": {
    "addr:full":"Westwood House, Elmhurst Road Reading Berkshire RG8 9BN",
    "addr:postcode":"rg8 9bn",
    "addr:street":"Elmhurst Road",
    "iso:country":"GB",
    "sg:address":"Westwood House, Elmhurst Road",
    "sg:city":"Reading",
    "sg:classifiers":[
        {
            "category":"Professional",
            "type":"Services"
        }
    ],
    "sg:phone":"+44 1491 875386",
    "sg:postcode":"RG8 9BN",
    "sg:province":"Berkshire",
    "sg:tags":[
        "directory",
        "pub"
    ],
    "wof:name":"Parkway Research Ltd.",
    "wof:placetype":"venue"
},
  "geometry": {"coordinates":[-1.1355400085,51.5255699158],"type":"Point"}
}