{
  "type": "Feature",
  "properties": {
    "addr:full":"40 Sunnydale Road London Greater London SE12 8JN",
    "addr:housenumber":"40",
    "addr:postcode":"se12 8jn",
    "addr:street":"Sunnydale Road",
    "iso:country":"GB",
    "sg:address":"40 Sunnydale Road",
    "sg:city":"London",
    "sg:classifiers":[
        {
            "category":"Education",
            "subcategory":"Music School",
            "type":"Public Place"
        }
    ],
    "sg:postcode":"SE12 8JN",
    "sg:province":"Greater London",
    "sg:tags":[
        "teacher"
    ],
    "wof:name":"William & Elizabeth Baulch",
    "wof:placetype":"venue"
},
  "geometry": {"coordinates":[0.0234769993,51.4557609558],"type":"Point"}
}