{
  "type": "Feature",
  "properties": {
    "iso:country":"GB",
    "sg:address":"The Surgery West End, Herstmonceux",
    "sg:city":"Hailsham",
    "sg:classifiers":[
        {
            "category":"Health Services",
            "subcategory":"Doctor",
            "type":"Services"
        }
    ],
    "sg:phone":"+44 1323 833535",
    "sg:postcode":"BN27 4NN",
    "sg:province":"East Sussex",
    "sg:tags":[
        "practitioners"
    ],
    "wof:name":"Dr G Baker",
    "wof:placetype":"venue"
},
  "geometry": {"coordinates":[0.3215439916,50.8890800476],"type":"Point"}
}