{
  "type": "Feature",
  "properties": {
    "iso:country":"GB",
    "sg:address":"57 Olivers Battery Road North",
    "sg:city":"Winchester",
    "sg:classifiers":[
        {
            "category":"Building & Trades",
            "subcategory":"Construction",
            "type":"Services"
        }
    ],
    "sg:phone":"+44 1962 864466",
    "sg:postcode":"SO22 4JB",
    "sg:province":"Hampshire",
    "sg:tags":[
        "builder"
    ],
    "wof:name":"Eastcourt Estates",
    "wof:placetype":"venue"
},
  "geometry": {"coordinates":[-1.347189,51.050999],"type":"Point"}
}