{
  "type": "Feature",
  "properties": {
    "addr:full":"Laneside, Top Road, Acton Trussell Stafford Staffordshire ST17 0RQ",
    "addr:postcode":"st17 0rq",
    "addr:street":"Top Road",
    "iso:country":"GB",
    "sg:address":"Laneside, Top Road, Acton Trussell",
    "sg:city":"Stafford",
    "sg:classifiers":[
        {
            "category":"Building & Trades",
            "subcategory":"Construction",
            "type":"Services"
        }
    ],
    "sg:postcode":"ST17 0RQ",
    "sg:province":"Staffordshire",
    "sg:tags":[
        "management"
    ],
    "wof:name":"Gennoa",
    "wof:placetype":"venue"
},
  "geometry": {"coordinates":[-2.096998,52.760452],"type":"Point"}
}