{
  "type": "Feature",
  "properties": {
    "iso:country":"GB",
    "sg:address":"19 East Street",
    "sg:city":"Newquay",
    "sg:classifiers":[
        {
            "category":"Shopping",
            "subcategory":"Catalog Store",
            "type":"Retail Goods"
        }
    ],
    "sg:phone":"+44 1637 850508",
    "sg:postcode":"TR7 1DN",
    "sg:province":"Cornwall",
    "sg:tags":[
        "catalogue",
        "showroom"
    ],
    "wof:name":"Argos Ltd.",
    "wof:placetype":"venue"
},
  "geometry": {"coordinates":[-5.081171,50.414082],"type":"Point"}
}