{
  "type": "Feature",
  "properties": {
    "addr:full":"West End Rd, Haydock St. Helens Lancashire WA11 0AX",
    "addr:postcode":"wa11 0ax",
    "addr:street":"West End Rd Haydock",
    "iso:country":"GB",
    "sg:address":"West End Rd, Haydock",
    "sg:city":"St. Helens",
    "sg:classifiers":[
        {
            "category":"Retail",
            "subcategory":"Auto Repair",
            "type":"Services"
        }
    ],
    "sg:phone":"+44 1744 22110",
    "sg:postcode":"WA11 0AX",
    "sg:province":"Lancashire",
    "sg:tags":[
        "car",
        "upholsterer"
    ],
    "wof:name":"The Northwest Valet Centre",
    "wof:placetype":"venue"
},
  "geometry": {"coordinates":[-2.6883089542,53.4681396484],"type":"Point"}
}