{
  "type": "Feature",
  "properties": {
    "addr:full":"3 Whitefield Rd Bristol City of Bristol BS5 7TF",
    "addr:housenumber":"3",
    "addr:postcode":"bs5 7tf",
    "addr:street":"Whitefield Rd",
    "iso:country":"GB",
    "sg:address":"3 Whitefield Rd",
    "sg:city":"Bristol",
    "sg:classifiers":[
        {
            "category":"Building & Trades",
            "subcategory":"Construction",
            "type":"Services"
        }
    ],
    "sg:phone":"+44 117 967 0721",
    "sg:postcode":"BS5 7TF",
    "sg:province":"City of Bristol",
    "sg:tags":[
        "roofing"
    ],
    "wof:name":"B Lawson Roofing",
    "wof:placetype":"venue"
},
  "geometry": {"coordinates":[-2.5382869244,51.4675064087],"type":"Point"}
}