{
  "type": "Feature",
  "properties": {
    "iso:country":"GB",
    "sg:address":"1 Hermitage Rd",
    "sg:city":"Loughborough",
    "sg:classifiers":[
        {
            "category":"Communications",
            "subcategory":"Film & Video Production",
            "type":"Services"
        },
        {
            "category":"Professional",
            "subcategory":"Art Services",
            "type":"Services"
        }
    ],
    "sg:postcode":"LE11 4PA",
    "sg:province":"Leicestershire",
    "sg:tags":[
        "photographer",
        "illustrator",
        "artist"
    ],
    "wof:name":"Vaughan,S,",
    "wof:placetype":"venue"
},
  "geometry": {"coordinates":[-1.240073,52.766758],"type":"Point"}
}