{
  "type": "Feature",
  "properties": {
    "addr:full":"5 Cliff Grove Avenue, Chilwell Nottingham Nottinghamshire NG9 4DP",
    "addr:housenumber":"5",
    "addr:postcode":"ng9 4dp",
    "addr:street":"Cliff Grove Avenue",
    "iso:country":"GB",
    "sg:address":"5 Cliff Grove Avenue, Chilwell",
    "sg:city":"Nottingham",
    "sg:classifiers":[
        {
            "category":"Health Services",
            "subcategory":"Clinic",
            "type":"Services"
        }
    ],
    "sg:postcode":"NG9 4DP",
    "sg:province":"Nottinghamshire",
    "sg:tags":[
        "aromatherapy"
    ],
    "wof:name":"Jan Lyon",
    "wof:placetype":"venue"
},
  "geometry": {"coordinates":[-1.2313740253,52.9269561768],"type":"Point"}
}