{
  "type": "Feature",
  "properties": {
    "iso:country":"GB",
    "sg:address":"Balvadoch Farm",
    "sg:city":"Dunkeld",
    "sg:classifiers":[
        {
            "category":"Farming",
            "subcategory":"Farm",
            "type":"Manufacturing & Wholesale Goods"
        }
    ],
    "sg:postcode":"PH8 0HF",
    "sg:province":"Perth and Kinross",
    "sg:tags":[
        "mixed",
        "crop"
    ],
    "wof:name":"David Rodger",
    "wof:placetype":"venue"
},
  "geometry": {"coordinates":[-3.5854539871,56.565448761],"type":"Point"}
}