{
  "type": "Feature",
  "properties": {
    "addr:full":"39 Osborne St Colchester Essex CO2 7DB",
    "addr:housenumber":"39",
    "addr:postcode":"co2 7db",
    "addr:street":"Osborne St",
    "iso:country":"GB",
    "sg:address":"39 Osborne St",
    "sg:city":"Colchester",
    "sg:classifiers":[
        {
            "category":"Shopping",
            "subcategory":"Used Merchandise",
            "type":"Retail Goods"
        }
    ],
    "sg:phone":"+44 1206 549781",
    "sg:postcode":"CO2 7DB",
    "sg:province":"Essex",
    "sg:tags":[
        "shop",
        "second-hand"
    ],
    "wof:name":"Cornucopia",
    "wof:placetype":"venue"
},
  "geometry": {"coordinates":[0.9010580182,51.8872032166],"type":"Point"}
}