{
  "type": "Feature",
  "properties": {
    "iso:country":"GB",
    "sg:address":"Ground Floor,merdon Ho, Rowlatts Hill",
    "sg:city":"Leicester",
    "sg:classifiers":[
        {
            "category":"Organizations",
            "subcategory":"Non-profit Organization",
            "type":"Services"
        }
    ],
    "sg:postcode":"LE5 4UH",
    "sg:province":"Leicestershire",
    "sg:tags":[
        "organisation",
        "voluntary",
        "charity"
    ],
    "wof:name":"Rowlatts Hill Tenants & Residents Associ",
    "wof:placetype":"venue"
},
  "geometry": {"coordinates":[-1.08504,52.637131],"type":"Point"}
}