{
  "type": "Feature",
  "properties": {
    "addr:full":"14 Park Springs Road Gainsborough Lincolnshire DN21 1PG",
    "addr:housenumber":"14",
    "addr:postcode":"dn21 1pg",
    "addr:street":"Park Springs Road",
    "iso:country":"GB",
    "sg:address":"14 Park Springs Road",
    "sg:city":"Gainsborough",
    "sg:classifiers":[
        {
            "category":"Social Services",
            "subcategory":"Retirement Home",
            "type":"Services"
        }
    ],
    "sg:postcode":"DN21 1PG",
    "sg:province":"Lincolnshire",
    "sg:tags":[
        "residential",
        "care"
    ],
    "wof:name":"Park Springs Road Residential Care",
    "wof:placetype":"venue"
},
  "geometry": {"coordinates":[-0.758523,53.390968],"type":"Point"}
}