{
  "type": "Feature",
  "properties": {
    "iso:country":"GB",
    "sg:address":"30 Abbey Brook Court",
    "sg:city":"Sheffield",
    "sg:classifiers":[
        {
            "category":"Retail",
            "subcategory":"Storage",
            "type":"Services"
        }
    ],
    "sg:phone":"+44 114 274 8165",
    "sg:postcode":"S8 7UU",
    "sg:province":"Derbyshire",
    "sg:tags":[
        "household",
        "removal"
    ],
    "wof:name":"Carriole Removals",
    "wof:placetype":"venue"
},
  "geometry": {"coordinates":[-1.483515,53.334],"type":"Point"}
}