{
  "type": "Feature",
  "properties": {
    "addr:full":"Unit 2, 88 Middlesex Street Glasgow Glasgow City G41 1EE",
    "addr:housenumber":"unit;88",
    "addr:postcode":"g41 1ee",
    "addr:street":"Middlesex Street",
    "iso:country":"GB",
    "sg:address":"Unit 2, 88 Middlesex Street",
    "sg:city":"Glasgow",
    "sg:classifiers":[
        {
            "category":"Manufacturing",
            "subcategory":"Metals",
            "type":"Manufacturing & Wholesale Goods"
        },
        {
            "category":"Shopping",
            "subcategory":"Pets & Pet Supplies",
            "type":"Retail Goods"
        }
    ],
    "sg:phone":"+44 141 429 8788",
    "sg:postcode":"G41 1EE",
    "sg:province":"Glasgow City",
    "sg:tags":[
        "food",
        "work",
        "sheet"
    ],
    "wof:name":"Alltech Ltd.",
    "wof:placetype":"venue"
},
  "geometry": {"coordinates":[-4.282719,55.851685],"type":"Point"}
}