{
  "type": "Feature",
  "properties": {
    "iso:country":"GB",
    "sg:address":"Blacklands Road, Upper Bucklebury",
    "sg:city":"Reading",
    "sg:classifiers":[
        {
            "category":"Education",
            "subcategory":"School",
            "type":"Public Place"
        },
        {
            "category":"Government",
            "subcategory":"Office",
            "type":"Public Place"
        }
    ],
    "sg:phone":"+44 1635 862965",
    "sg:postcode":"RG7 6QP",
    "sg:province":"Berkshire",
    "sg:tags":[
        "local",
        "authority"
    ],
    "wof:name":"Bucklebury C of E Primary School",
    "wof:placetype":"venue"
},
  "geometry": {"coordinates":[-1.221992,51.412224],"type":"Point"}
}