{
  "type": "Feature",
  "properties": {
    "addr:full":"213 Carlisle Lane, Waterloo London Greater London SE1 7LH",
    "addr:housenumber":"213",
    "addr:postcode":"se1 7lh",
    "addr:street":"Carlisle Lane",
    "iso:country":"GB",
    "sg:address":"213 Carlisle Lane, Waterloo",
    "sg:city":"London",
    "sg:classifiers":[
        {
            "category":"Retail",
            "subcategory":"Storage",
            "type":"Services"
        }
    ],
    "sg:phone":"+44 20 7928 9955",
    "sg:postcode":"SE1 7LH",
    "sg:province":"Greater London",
    "sg:tags":[
        "household",
        "removal"
    ],
    "wof:name":"1st For Storage Ltd.",
    "wof:placetype":"venue"
},
  "geometry": {"coordinates":[-0.116034,51.498295],"type":"Point"}
}