{
  "type": "Feature",
  "properties": {
    "iso:country":"GB",
    "sg:address":"136 Pike Road",
    "sg:city":"Plymouth",
    "sg:classifiers":[
        {
            "category":"Home & Garden",
            "subcategory":"Building Materials",
            "type":"Retail Goods"
        }
    ],
    "sg:phone":"+44 1752 668224",
    "sg:postcode":"PL3 6HH",
    "sg:province":"Devon",
    "sg:tags":[
        "garage",
        "door"
    ],
    "wof:name":"Advantage Door Systems",
    "wof:placetype":"venue"
},
  "geometry": {"coordinates":[-4.100125,50.387562],"type":"Point"}
}