{
  "type": "Feature",
  "properties": {
    "addr:full":"4 Bowbridge Rd Newark Nottinghamshire NG24 4BZ",
    "addr:housenumber":"4",
    "addr:postcode":"ng24 4bz",
    "addr:street":"Bowbridge Rd",
    "iso:country":"GB",
    "sg:address":"4 Bowbridge Rd",
    "sg:city":"Newark",
    "sg:classifiers":[
        {
            "category":"Home & Garden",
            "subcategory":"Household Appliances",
            "type":"Retail Goods"
        }
    ],
    "sg:postcode":"NG24 4BZ",
    "sg:province":"Nottinghamshire",
    "sg:tags":[
        "electrical"
    ],
    "wof:name":"Footitt & Haynes",
    "wof:placetype":"venue"
},
  "geometry": {"coordinates":[-0.8051810265,53.0716896057],"type":"Point"}
}