{
  "type": "Feature",
  "properties": {
    "addr:full":"23a Fitzwilliam Street Rushden Bedfordshire NN10 0NN",
    "addr:housenumber":"23a",
    "addr:postcode":"nn10 0nn",
    "addr:street":"Fitzwilliam Street",
    "iso:country":"GB",
    "sg:address":"23a Fitzwilliam Street",
    "sg:city":"Rushden",
    "sg:classifiers":[
        {
            "category":"Shopping",
            "subcategory":"Clothing, Apparel, & Fashions",
            "type":"Retail Goods"
        }
    ],
    "sg:postcode":"NN10 0NN",
    "sg:province":"Bedfordshire",
    "sg:tags":[
        "clothing"
    ],
    "wof:name":"Dancepool Ltd.",
    "wof:placetype":"venue"
},
  "geometry": {"coordinates":[-0.600925982,52.2912559509],"type":"Point"}
}