{
  "type": "Feature",
  "properties": {
    "addr:full":"220 Chorley New Road, Horwich Bolton Lancashire BL6 5NP",
    "addr:housenumber":"220",
    "addr:postcode":"bl6 5np",
    "addr:street":"Chorley New Road",
    "iso:country":"GB",
    "sg:address":"220 Chorley New Road, Horwich",
    "sg:city":"Bolton",
    "sg:classifiers":[
        {
            "category":"Fast Food",
            "type":"Food & Drink"
        }
    ],
    "sg:phone":"+44 1204 667910",
    "sg:postcode":"BL6 5NP",
    "sg:province":"Lancashire",
    "sg:tags":[
        "away",
        "take"
    ],
    "wof:name":"Milano Take Away",
    "wof:placetype":"venue"
},
  "geometry": {"coordinates":[-2.5455079079,53.5945053101],"type":"Point"}
}