{
  "type": "Feature",
  "properties": {
    "iso:country":"GB",
    "sg:address":"The Chough, 3 The Strand",
    "sg:city":"Padstow",
    "sg:classifiers":[
        {
            "category":"Food & Beverages",
            "subcategory":"Bakery",
            "type":"Retail Goods"
        }
    ],
    "sg:postcode":"PL28 8AJ",
    "sg:province":"Cornwall",
    "sg:tags":[
        "baker"
    ],
    "wof:name":"W R Ead",
    "wof:placetype":"venue"
},
  "geometry": {"coordinates":[-4.941839,50.537365],"type":"Point"}
}