{
  "type": "Feature",
  "properties": {
    "addr:full":"126 Haslucks Grn Rd Solihull West Midlands B90 2EH",
    "addr:housenumber":"126",
    "addr:postcode":"b90 2eh",
    "addr:street":"Haslucks Grn Rd",
    "iso:country":"GB",
    "sg:address":"126 Haslucks Grn Rd",
    "sg:city":"Solihull",
    "sg:classifiers":[
        {
            "category":"Farming",
            "subcategory":"Fish & Marine Products",
            "type":"Manufacturing & Wholesale Goods"
        }
    ],
    "sg:postcode":"B90 2EH",
    "sg:province":"West Midlands",
    "sg:tags":[
        "fishmonger"
    ],
    "wof:name":"Prior,J R,",
    "wof:placetype":"venue"
},
  "geometry": {"coordinates":[-1.835017,52.411331],"type":"Point"}
}