{
  "type": "Feature",
  "properties": {
    "iso:country":"GB",
    "sg:address":"Sun Life House, 85-103 Queens Road",
    "sg:city":"Reading",
    "sg:classifiers":[
        {
            "category":"Manufacturing",
            "subcategory":"Tools & Machinery",
            "type":"Manufacturing & Wholesale Goods"
        }
    ],
    "sg:phone":"+44 118 958 6171",
    "sg:postcode":"RG1 4LP",
    "sg:province":"Berkshire",
    "sg:tags":[
        "society",
        "friendly"
    ],
    "wof:name":"Sun Life",
    "wof:placetype":"venue"
},
  "geometry": {"coordinates":[-0.961442,51.453758],"type":"Point"}
}