{
  "type": "Feature",
  "properties": {
    "addr:full":"2 Peterson Rd Wakefield West Yorkshire WF1 4EB",
    "addr:housenumber":"2",
    "addr:postcode":"wf1 4eb",
    "addr:street":"Peterson Rd",
    "iso:country":"GB",
    "sg:address":"2 Peterson Rd",
    "sg:city":"Wakefield",
    "sg:classifiers":[
        {
            "category":"Travel",
            "subcategory":"Hostel",
            "type":"Entertainment"
        }
    ],
    "sg:postcode":"WF1 4EB",
    "sg:province":"West Yorkshire",
    "wof:name":"Ferncliffe House",
    "wof:placetype":"venue"
},
  "geometry": {"coordinates":[-1.490836978,53.6809082031],"type":"Point"}
}