{
  "type": "Feature",
  "properties": {
    "addr:full":"3-4 Learoyd Road New Romney Kent TN28 8XU",
    "addr:housenumber":"3-4",
    "addr:postcode":"tn28 8xu",
    "addr:street":"Learoyd Road",
    "iso:country":"GB",
    "sg:address":"3-4 Learoyd Road",
    "sg:city":"New Romney",
    "sg:classifiers":[
        {
            "category":"Building & Trades",
            "subcategory":"Construction",
            "type":"Services"
        }
    ],
    "sg:phone":"+44 1797 366724",
    "sg:postcode":"TN28 8XU",
    "sg:province":"Kent",
    "sg:tags":[
        "welder"
    ],
    "wof:name":"E & P Engineering Services",
    "wof:placetype":"venue"
},
  "geometry": {"coordinates":[0.9498400092,50.9835929871],"type":"Point"}
}