{
  "type": "Feature",
  "properties": {
    "iso:country":"GB",
    "sg:address":"17-19 Taylor St",
    "sg:city":"Luton",
    "sg:classifiers":[
        {
            "category":"Manufacturing",
            "subcategory":"Metals",
            "type":"Manufacturing & Wholesale Goods"
        }
    ],
    "sg:phone":"+44 1582 482004",
    "sg:postcode":"LU2 0EY",
    "sg:province":"Bedfordshire",
    "sg:tags":[
        "work",
        "sheet"
    ],
    "wof:name":"F W Fabrication Ltd",
    "wof:placetype":"venue"
},
  "geometry": {"coordinates":[-0.4092150033,51.8851737976],"type":"Point"}
}