{
  "type": "Feature",
  "properties": {
    "addr:full":"8 Valeria Close Wallsend Tyne and Wear NE28 9QY",
    "addr:housenumber":"8",
    "addr:postcode":"ne28 9qy",
    "addr:street":"Valeria Close",
    "iso:country":"GB",
    "sg:address":"8 Valeria Close",
    "sg:city":"Wallsend",
    "sg:classifiers":[
        {
            "category":"Retail",
            "subcategory":"Driving School",
            "type":"Services"
        }
    ],
    "sg:phone":"+44 191 234 3327",
    "sg:postcode":"NE28 9QY",
    "sg:province":"Tyne and Wear",
    "wof:name":"Charlton Driving School",
    "wof:placetype":"venue"
},
  "geometry": {"coordinates":[-1.5168139935,55.0139808655],"type":"Point"}
}