{
  "type": "Feature",
  "properties": {
    "addr:full":"10 Market Street, Birstall Batley West Yorkshire WF17 9EN",
    "addr:housenumber":"10",
    "addr:postcode":"wf17 9en",
    "addr:street":"Market Street",
    "iso:country":"GB",
    "sg:address":"10 Market Street, Birstall",
    "sg:city":"Batley",
    "sg:classifiers":[
        {
            "category":"Shopping",
            "subcategory":"Florist",
            "type":"Retail Goods"
        }
    ],
    "sg:phone":"+44 1924 474285",
    "sg:postcode":"WF17 9EN",
    "sg:province":"West Yorkshire",
    "wof:name":"Akeroyd's",
    "wof:placetype":"venue"
},
  "geometry": {"coordinates":[-1.6607769728,53.7313728333],"type":"Point"}
}