{
  "type": "Feature",
  "properties": {
    "iso:country":"GB",
    "sg:address":"71 Duke Street",
    "sg:city":"St. Helens",
    "sg:classifiers":[
        {
            "category":"Shopping",
            "subcategory":"Antiques",
            "type":"Retail Goods"
        }
    ],
    "sg:phone":"+44 1744 604081",
    "sg:postcode":"WA10 2JF",
    "sg:province":"Merseyside",
    "wof:name":"Stamps Antiques Books",
    "wof:placetype":"venue"
},
  "geometry": {"coordinates":[-2.7424459457,53.4557952881],"type":"Point"}
}