{
  "type": "Feature",
  "properties": {
    "addr:full":"6-8 Tudor Court, Brighton Road Sutton Surrey SM2 5AE",
    "addr:housenumber":"6-8",
    "addr:postcode":"sm2 5ae",
    "addr:street":"Tudor Court Brighton Road",
    "iso:country":"GB",
    "sg:address":"6-8 Tudor Court, Brighton Road",
    "sg:city":"Sutton",
    "sg:classifiers":[
        {
            "category":"Shopping",
            "subcategory":"Department Store",
            "type":"Retail Goods"
        }
    ],
    "sg:phone":"+44 20 8643 1166",
    "sg:postcode":"SM2 5AE",
    "sg:province":"Surrey",
    "wof:name":"Peter Boswell (Restorations) Ltd.",
    "wof:placetype":"venue"
},
  "geometry": {"coordinates":[-0.191080004,51.358921051],"type":"Point"}
}