{
  "type": "Feature",
  "properties": {
    "iso:country":"GB",
    "sg:address":"Chainbridge Road",
    "sg:city":"Blaydon-on-tyne",
    "sg:classifiers":[
        {
            "category":"Autos & Motor Vehicles",
            "subcategory":"Fuel & Gas Station",
            "type":"Retail Goods"
        }
    ],
    "sg:postcode":"NE21 5ST",
    "sg:province":"Tyne and Wear",
    "sg:tags":[
        "petrol",
        "filling"
    ],
    "wof:name":"Save Chainbridge",
    "wof:placetype":"venue"
},
  "geometry": {"coordinates":[-1.7058310509,54.966091156],"type":"Point"}
}