{
  "type": "Feature",
  "properties": {
    "addr:full":"189 Garratt Lane London Greater London SW18 4DR",
    "addr:housenumber":"189",
    "addr:postcode":"sw18 4dr",
    "addr:street":"Garratt Lane",
    "iso:country":"GB",
    "sg:address":"189 Garratt Lane",
    "sg:city":"London",
    "sg:classifiers":[
        {
            "category":"Restaurant",
            "type":"Food & Drink"
        }
    ],
    "sg:phone":"+44 20 8871 9464",
    "sg:postcode":"SW18 4DR",
    "sg:province":"Greater London",
    "wof:name":"Nino Salva",
    "wof:placetype":"venue"
},
  "geometry": {"coordinates":[-0.18976,51.450432],"type":"Point"}
}