{
  "type": "Feature",
  "properties": {
    "iso:country":"GB",
    "sg:address":"High St, Burton In Lonsdale",
    "sg:city":"Carnforth",
    "sg:classifiers":[
        {
            "category":"Government",
            "subcategory":"Post Office",
            "type":"Public Place"
        }
    ],
    "sg:phone":"+44 15242 61283",
    "sg:postcode":"LA6 3JP",
    "sg:province":"Cumbria",
    "wof:name":"Burton in Lonsdale P.O",
    "wof:placetype":"venue"
},
  "geometry": {"coordinates":[-2.4652030468,54.1532745361],"type":"Point"}
}