{
  "type": "Feature",
  "properties": {
    "iso:country":"GB",
    "sg:address":"Stoke Hall Farm, Stoke Hall Lane, Stoke",
    "sg:city":"Nantwich",
    "sg:classifiers":[
        {
            "category":"Farming",
            "subcategory":"Livestock Farm",
            "type":"Manufacturing & Wholesale Goods"
        }
    ],
    "sg:phone":"+44 1270 528219",
    "sg:postcode":"CW5 6AS",
    "sg:province":"Cheshire",
    "sg:tags":[
        "others"
    ],
    "wof:name":"P H Bourne & Partners",
    "wof:placetype":"venue"
},
  "geometry": {"coordinates":[-2.565887928,53.1073799133],"type":"Point"}
}