{
  "type": "Feature",
  "properties": {
    "iso:country":"GB",
    "sg:address":"Wellington Place",
    "sg:city":"Port Talbot",
    "sg:classifiers":[
        {
            "category":"Building & Trades",
            "subcategory":"Construction",
            "type":"Services"
        }
    ],
    "sg:postcode":"SA12 6LL",
    "sg:province":"Neath Port Talbot",
    "sg:tags":[
        "glazier"
    ],
    "wof:name":"Talbot Glass",
    "wof:placetype":"venue"
},
  "geometry": {"coordinates":[-3.792419,51.594379],"type":"Point"}
}