{
  "type": "Feature",
  "properties": {
    "iso:country":"GB",
    "sg:address":"127 Blackburn Street, Radcliffe",
    "sg:city":"Manchester",
    "sg:classifiers":[
        {
            "category":"Farming",
            "subcategory":"Nursery",
            "type":"Manufacturing & Wholesale Goods"
        },
        {
            "category":"Education",
            "subcategory":"School",
            "type":"Public Place"
        }
    ],
    "sg:phone":"+44 161 724 4184",
    "sg:postcode":"M26 3WQ",
    "sg:province":"Greater Manchester",
    "sg:tags":[
        "creche",
        "local",
        "authority"
    ],
    "wof:name":"Bank House Day Nursery",
    "wof:placetype":"venue"
},
  "geometry": {"coordinates":[-2.328266,53.562237],"type":"Point"}
}