{
  "type": "Feature",
  "properties": {
    "addr:full":"2 Peacocktail Clo Edinburgh City of Edinburgh EH15 3QS",
    "addr:housenumber":"2",
    "addr:postcode":"eh15 3qs",
    "addr:street":"Peacocktail Clo Edinburgh",
    "iso:country":"GB",
    "sg:address":"2 Peacocktail Clo",
    "sg:city":"Edinburgh",
    "sg:classifiers":[
        {
            "category":"Building & Trades",
            "subcategory":"Construction",
            "type":"Services"
        }
    ],
    "sg:phone":"+44 131 657 2917",
    "sg:postcode":"EH15 3QS",
    "sg:province":"City of Edinburgh",
    "sg:tags":[
        "builder"
    ],
    "wof:name":"Aacorn Services",
    "wof:placetype":"venue"
},
  "geometry": {"coordinates":[-3.114912,55.938766],"type":"Point"}
}