{
  "type": "Feature",
  "properties": {
    "iso:country":"GB",
    "sg:address":"43 Burrowgate",
    "sg:city":"Penrith",
    "sg:classifiers":[
        {
            "category":"Shopping",
            "subcategory":"Used Merchandise",
            "type":"Retail Goods"
        }
    ],
    "sg:phone":"+44 1768 864115",
    "sg:postcode":"CA11 7TA",
    "sg:province":"Cumbria",
    "sg:tags":[
        "furniture"
    ],
    "wof:name":"S.R.S",
    "wof:placetype":"venue"
},
  "geometry": {"coordinates":[-2.751548,54.665115],"type":"Point"}
}