{
  "type": "Feature",
  "properties": {
    "iso:country":"GB",
    "sg:address":"3 Clare Street",
    "sg:city":"Northampton",
    "sg:classifiers":[
        {
            "category":"Military Area",
            "subcategory":"Air Force Base",
            "type":"Public Place"
        }
    ],
    "sg:phone":"+44 1604 638888",
    "sg:postcode":"NN1 3JG",
    "sg:province":"Northamptonshire",
    "sg:tags":[
        "taxi",
        "hire",
        "private"
    ],
    "wof:name":"Alpha Taxis",
    "wof:placetype":"venue"
},
  "geometry": {"coordinates":[-0.889641,52.243595],"type":"Point"}
}