{
  "type": "Feature",
  "properties": {
    "addr:full":"Colby Lane Appleby-in-westmorland Cumbria CA16 6RJ",
    "addr:postcode":"ca16 6rj",
    "addr:street":"Colby Lane",
    "iso:country":"GB",
    "sg:address":"Colby Lane",
    "sg:city":"Appleby-in-westmorland",
    "sg:classifiers":[
        {
            "category":"Food & Beverages",
            "subcategory":"Groceries & Convenience Stores",
            "type":"Retail Goods"
        }
    ],
    "sg:phone":"+44 17683 52529",
    "sg:postcode":"CA16 6RJ",
    "sg:province":"Cumbria",
    "wof:name":"Scattergate Stores",
    "wof:placetype":"venue"
},
  "geometry": {"coordinates":[-2.497524,54.572346],"type":"Point"}
}