{
  "type": "Feature",
  "properties": {
    "addr:full":"78 Taff Street Pontypridd Caerphilly CF37 4SU",
    "addr:housenumber":"78",
    "addr:postcode":"cf37 4su",
    "addr:street":"Taff Street",
    "iso:country":"GB",
    "sg:address":"78 Taff Street",
    "sg:city":"Pontypridd",
    "sg:classifiers":[
        {
            "category":"Shopping",
            "subcategory":"Shoes",
            "type":"Retail Goods"
        }
    ],
    "sg:phone":"+44 1443 407306",
    "sg:postcode":"CF37 4SU",
    "sg:province":"Caerphilly",
    "wof:name":"Timpson Shoe Repairs",
    "wof:placetype":"venue"
},
  "geometry": {"coordinates":[-3.3406999111,51.6018943787],"type":"Point"}
}