{
  "type": "Feature",
  "properties": {
    "iso:country":"GB",
    "sg:address":"Carlatton Demense, Heads Nook",
    "sg:city":"Brampton",
    "sg:classifiers":[
        {
            "category":"Farming",
            "subcategory":"Dairy Farm",
            "type":"Manufacturing & Wholesale Goods"
        }
    ],
    "sg:phone":"+44 1768 896663",
    "sg:postcode":"CA8 9BX",
    "sg:province":"Cumbria",
    "sg:tags":[
        "farmer"
    ],
    "wof:name":"J & M E HUTCHINSON",
    "wof:placetype":"venue"
},
  "geometry": {"coordinates":[-2.790884,54.889664],"type":"Point"}
}