{
  "type": "Feature",
  "properties": {
    "addr:full":"56 Thames Road London Greater London W4 3RE",
    "addr:housenumber":"56",
    "addr:postcode":"w4 3re",
    "addr:street":"Thames Road",
    "iso:country":"GB",
    "sg:address":"56 Thames Road",
    "sg:city":"London",
    "sg:classifiers":[
        {
            "category":"Food & Beverages",
            "subcategory":"Fruits & Vegetables",
            "type":"Retail Goods"
        }
    ],
    "sg:phone":"+44 20 8994 1985",
    "sg:postcode":"W4 3RE",
    "sg:province":"Greater London",
    "sg:tags":[
        "greengrocer"
    ],
    "wof:name":"B & B Lawrence",
    "wof:placetype":"venue"
},
  "geometry": {"coordinates":[-0.280662,51.48658],"type":"Point"}
}