{
  "type": "Feature",
  "properties": {
    "addr:full":"2 Sherwood Drive, Barton Seagrave Kettering Northamptonshire NN15 6UU",
    "addr:housenumber":"2",
    "addr:postcode":"nn15 6uu",
    "addr:street":"Sherwood Drive",
    "iso:country":"GB",
    "sg:address":"2 Sherwood Drive, Barton Seagrave",
    "sg:city":"Kettering",
    "sg:classifiers":[
        {
            "category":"Home & Garden",
            "subcategory":"Carpets & Floor Coverings",
            "type":"Retail Goods"
        }
    ],
    "sg:phone":"+44 1536 723188",
    "sg:postcode":"NN15 6UU",
    "sg:province":"Northamptonshire",
    "sg:tags":[
        "cleaner",
        "upholstery"
    ],
    "wof:name":"Servicemaster",
    "wof:placetype":"venue"
},
  "geometry": {"coordinates":[-0.6978920102,52.3775558472],"type":"Point"}
}