{
  "type": "Feature",
  "properties": {
    "addr:full":"25 Torridon Rd Dewsbury West Yorkshire WF12 7NX",
    "addr:housenumber":"25",
    "addr:postcode":"wf12 7nx",
    "addr:street":"Torridon Rd",
    "iso:country":"GB",
    "sg:address":"25 Torridon Rd",
    "sg:city":"Dewsbury",
    "sg:classifiers":[
        {
            "category":"Home & Garden",
            "subcategory":"Building Materials",
            "type":"Retail Goods"
        },
        {
            "category":"Building & Trades",
            "subcategory":"Construction",
            "type":"Services"
        }
    ],
    "sg:phone":"+44 1924 463155",
    "sg:postcode":"WF12 7NX",
    "sg:province":"West Yorkshire",
    "sg:tags":[
        "fencing",
        "contractor"
    ],
    "wof:name":"Leyburn Fencing Contractors",
    "wof:placetype":"venue"
},
  "geometry": {"coordinates":[-1.6154680252,53.7008743286],"type":"Point"}
}