{
  "type": "Feature",
  "properties": {
    "addr:full":"40 Teign Street Teignmouth Devon TQ14 8EA",
    "addr:housenumber":"40",
    "addr:postcode":"tq14 8ea",
    "addr:street":"Teign Street",
    "iso:country":"GB",
    "sg:address":"40 Teign Street",
    "sg:city":"Teignmouth",
    "sg:classifiers":[
        {
            "category":"Shopping",
            "subcategory":"Baby Store",
            "type":"Retail Goods"
        }
    ],
    "sg:phone":"+44 1626 770363",
    "sg:postcode":"TQ14 8EA",
    "sg:province":"Devon",
    "sg:tags":[
        "babywear",
        "childrens"
    ],
    "wof:name":"Peanuts",
    "wof:placetype":"venue"
},
  "geometry": {"coordinates":[-3.497702,50.546253],"type":"Point"}
}