{
  "type": "Feature",
  "properties": {
    "addr:full":"1 Matlock Road Brighton East Sussex BN1 5BF",
    "addr:housenumber":"1",
    "addr:postcode":"bn1 5bf",
    "addr:street":"Matlock Road",
    "iso:country":"GB",
    "sg:address":"1 Matlock Road",
    "sg:city":"Brighton",
    "sg:classifiers":[
        {
            "category":"Shopping",
            "subcategory":"Department Store",
            "type":"Retail Goods"
        }
    ],
    "sg:phone":"+44 1273 552630",
    "sg:postcode":"BN1 5BF",
    "sg:province":"East Sussex",
    "wof:name":"Matlock Stores",
    "wof:placetype":"venue"
},
  "geometry": {"coordinates":[-0.1588719934,50.8432312012],"type":"Point"}
}