{
  "type": "Feature",
  "properties": {
    "addr:full":"17a Claremont Crescent Whitley Bay Northumberland NE26 3HL",
    "addr:housenumber":"17a",
    "addr:postcode":"ne26 3hl",
    "addr:street":"Claremont Crescent",
    "iso:country":"GB",
    "sg:address":"17a Claremont Crescent",
    "sg:city":"Whitley Bay",
    "sg:classifiers":[
        {
            "category":"Real Estate",
            "subcategory":"Real Estate Agent",
            "type":"Services"
        }
    ],
    "sg:phone":"+44 191 252 4193",
    "sg:postcode":"NE26 3HL",
    "sg:province":"Northumberland",
    "wof:name":"J G Sawyers & Sons",
    "wof:placetype":"venue"
},
  "geometry": {"coordinates":[-1.4618370533,55.0543556213],"type":"Point"}
}