{
  "type": "Feature",
  "properties": {
    "addr:full":"22-26 Dickson Road Blackpool Lancashire FY1 2AH",
    "addr:housenumber":"22-26",
    "addr:postcode":"fy1 2ah",
    "addr:street":"Dickson Road",
    "iso:country":"GB",
    "sg:address":"22-26 Dickson Road",
    "sg:city":"Blackpool",
    "sg:classifiers":[
        {
            "category":"Shopping",
            "subcategory":"Used Merchandise",
            "type":"Retail Goods"
        }
    ],
    "sg:phone":"+44 1253 295559",
    "sg:postcode":"FY1 2AH",
    "sg:province":"Lancashire",
    "sg:tags":[
        "shop",
        "second-hand"
    ],
    "wof:name":"Robert  Gaskin",
    "wof:placetype":"venue"
},
  "geometry": {"coordinates":[-3.0524001122,53.8215904236],"type":"Point"}
}