{
  "type": "Feature",
  "properties": {
    "addr:full":"41 Kaims Court, Livingston Village Livingston West Lothian EH54 7DB",
    "addr:housenumber":"41",
    "addr:postcode":"eh54 7db",
    "addr:street":"Kaims Court",
    "iso:country":"GB",
    "sg:address":"41 Kaims Court, Livingston Village",
    "sg:city":"Livingston",
    "sg:classifiers":[
        {
            "category":"Building & Trades",
            "subcategory":"Plumbing",
            "type":"Services"
        }
    ],
    "sg:phone":"+44 1506 462672",
    "sg:postcode":"EH54 7DB",
    "sg:province":"West Lothian",
    "sg:tags":[
        "heating"
    ],
    "wof:name":"B J W Plumbing & Heating Services",
    "wof:placetype":"venue"
},
  "geometry": {"coordinates":[-3.535337,55.883171],"type":"Point"}
}