{
  "type": "Feature",
  "properties": {
    "addr:full":"137 Beeleigh Link Chelmsford Essex CM2 6PH",
    "addr:housenumber":"137",
    "addr:postcode":"cm2 6ph",
    "addr:street":"Beeleigh Link",
    "iso:country":"GB",
    "sg:address":"137 Beeleigh Link",
    "sg:city":"Chelmsford",
    "sg:classifiers":[
        {
            "category":"Retail",
            "subcategory":"Driving School",
            "type":"Services"
        }
    ],
    "sg:postcode":"CM2 6PH",
    "sg:province":"Essex",
    "wof:name":"1ST Gear School of Motoring",
    "wof:placetype":"venue"
},
  "geometry": {"coordinates":[0.500970006,51.7359695435],"type":"Point"}
}