{
  "type": "Feature",
  "properties": {
    "iso:country":"GB",
    "sg:address":"Duloe",
    "sg:city":"Liskeard",
    "sg:classifiers":[
        {
            "category":"Travel",
            "subcategory":"Hotels & Motels",
            "type":"Entertainment"
        }
    ],
    "sg:phone":"+44 1503 262730",
    "sg:postcode":"PL14 4PP",
    "sg:province":"Cornwall",
    "sg:tags":[
        "self",
        "catering"
    ],
    "wof:name":"Treworgey Cottages",
    "wof:placetype":"venue"
},
  "geometry": {"coordinates":[-4.465834,50.453796],"type":"Point"}
}