{
  "type": "Feature",
  "properties": {
    "addr:full":"95 Station Road Port Talbot Neath Port Talbot SA13 1NR",
    "addr:housenumber":"95",
    "addr:postcode":"sa13 1nr",
    "addr:street":"Station Road",
    "iso:country":"GB",
    "sg:address":"95 Station Road",
    "sg:city":"Port Talbot",
    "sg:classifiers":[
        {
            "category":"Shopping",
            "subcategory":"Clothing, Apparel, & Fashions",
            "type":"Retail Goods"
        }
    ],
    "sg:phone":"+44 1639 884478",
    "sg:postcode":"SA13 1NR",
    "sg:province":"Neath Port Talbot",
    "sg:tags":[
        "shop"
    ],
    "wof:name":"Emphasis",
    "wof:placetype":"venue"
},
  "geometry": {"coordinates":[-3.7831919193,51.5956268311],"type":"Point"}
}