{
  "type": "Feature",
  "properties": {
    "addr:full":"25 Villiers Street London Greater London WC2N 6ND",
    "addr:housenumber":"25",
    "addr:postcode":"wc2n 6nd",
    "addr:street":"Villiers Street",
    "iso:country":"GB",
    "sg:address":"25 Villiers Street",
    "sg:city":"London",
    "sg:classifiers":[
        {
            "category":"Banks & Credit Unions",
            "subcategory":"Financial Services",
            "type":"Services"
        }
    ],
    "sg:phone":"+44 20 7976 2176",
    "sg:postcode":"WC2N 6ND",
    "sg:province":"Greater London",
    "sg:tags":[
        "adviser"
    ],
    "wof:name":"Alfred Blackmore",
    "wof:placetype":"venue"
},
  "geometry": {"coordinates":[-0.123978,51.50827],"type":"Point"}
}