{
  "type": "Feature",
  "properties": {
    "iso:country":"GB",
    "sg:address":"54 Oxford St",
    "sg:city":"Reading",
    "sg:classifiers":[
        {
            "category":"Home & Garden",
            "subcategory":"Household Appliances",
            "type":"Retail Goods"
        }
    ],
    "sg:phone":"+44 118 947 2214",
    "sg:postcode":"RG4 8HN",
    "sg:province":"Berkshire",
    "sg:tags":[
        "electrical"
    ],
    "wof:name":"K9 Electrical Engineers",
    "wof:placetype":"venue"
},
  "geometry": {"coordinates":[-0.973672986,51.4689826965],"type":"Point"}
}