{
  "type": "Feature",
  "properties": {
    "iso:country":"GB",
    "sg:address":"23 Great Northern Road",
    "sg:city":"Dunstable",
    "sg:classifiers":[
        {
            "category":"Shopping",
            "subcategory":"Hobbies, Toys, & Games",
            "type":"Retail Goods"
        },
        {
            "category":"Food & Beverages",
            "subcategory":"Bakery",
            "type":"Retail Goods"
        }
    ],
    "sg:phone":"+44 1582 662779",
    "sg:postcode":"LU5 4BN",
    "sg:province":"Bedfordshire",
    "sg:tags":[
        "baker",
        "kite"
    ],
    "wof:name":"Stevens Bakery",
    "wof:placetype":"venue"
},
  "geometry": {"coordinates":[-0.513196,51.882442],"type":"Point"}
}