{
  "type": "Feature",
  "properties": {
    "addr:full":"7 St Marys Rise, Writhlington Bath Somerset BA3 3PD",
    "addr:housenumber":"7",
    "addr:postcode":"ba3 3pd",
    "addr:street":"St Marys Rise",
    "iso:country":"GB",
    "sg:address":"7 St Marys Rise, Writhlington",
    "sg:city":"Bath",
    "sg:classifiers":[
        {
            "category":"Building & Trades",
            "subcategory":"Construction",
            "type":"Services"
        }
    ],
    "sg:phone":"+44 1761 435737",
    "sg:postcode":"BA3 3PD",
    "sg:province":"Somerset",
    "sg:tags":[
        "welder"
    ],
    "wof:name":"A W S Engineering",
    "wof:placetype":"venue"
},
  "geometry": {"coordinates":[-2.42782,51.291557],"type":"Point"}
}