{
  "type": "Feature",
  "properties": {
    "addr:full":"33b Station Rd, Marston Green Birmingham West Midlands B37 7AB",
    "addr:housenumber":"33b",
    "addr:postcode":"b37 7ab",
    "addr:street":"Station Rd",
    "iso:country":"GB",
    "sg:address":"33b Station Rd, Marston Green",
    "sg:city":"Birmingham",
    "sg:classifiers":[
        {
            "category":"Cinema",
            "subcategory":"Movie Rental",
            "type":"Entertainment"
        }
    ],
    "sg:postcode":"B37 7AB",
    "sg:province":"West Midlands",
    "sg:tags":[
        "video",
        "library"
    ],
    "wof:name":"Premier Video",
    "wof:placetype":"venue"
},
  "geometry": {"coordinates":[-1.7528419495,52.4673843384],"type":"Point"}
}