{
  "type": "Feature",
  "properties": {
    "addr:full":"Lines House, 78 High St Stevenage Hertfordshire SG1 3DW",
    "addr:housenumber":"78",
    "addr:postcode":"sg1 3dw",
    "addr:street":"High St",
    "iso:country":"GB",
    "sg:address":"Lines House, 78 High St",
    "sg:city":"Stevenage",
    "sg:classifiers":[
        {
            "category":"Manufacturing",
            "subcategory":"Electronics",
            "type":"Manufacturing & Wholesale Goods"
        }
    ],
    "sg:phone":"+44 1438 312393",
    "sg:postcode":"SG1 3DW",
    "sg:province":"Hertfordshire",
    "sg:tags":[
        "mnfr",
        "component",
        "electronic"
    ],
    "wof:name":"Arrow Components",
    "wof:placetype":"venue"
},
  "geometry": {"coordinates":[-0.208077997,51.9108123779],"type":"Point"}
}