{
  "type": "Feature",
  "properties": {
    "addr:full":"Lund Farm, Hawksworth La, Guiseley Leeds West Yorkshire LS20 8NT",
    "addr:housenumber":"hawksworth",
    "addr:postcode":"ls20 8nt",
    "addr:street":"La Guiseley Leeds West",
    "iso:country":"GB",
    "sg:address":"Lund Farm, Hawksworth La, Guiseley",
    "sg:city":"Leeds",
    "sg:classifiers":[
        {
            "category":"Farming",
            "subcategory":"Farm",
            "type":"Manufacturing & Wholesale Goods"
        }
    ],
    "sg:postcode":"LS20 8NT",
    "sg:province":"West Yorkshire",
    "sg:tags":[
        "mixed",
        "crop"
    ],
    "wof:name":"Paxton,F W,",
    "wof:placetype":"venue"
},
  "geometry": {"coordinates":[-1.7104940414,53.8719558716],"type":"Point"}
}