{
  "type": "Feature",
  "properties": {
    "addr:full":"P O Box 4676 Sutton Coldfield West Midlands B72 1EX",
    "addr:housenumber":"p o;4676",
    "addr:postcode":"b72 1ex",
    "iso:country":"GB",
    "sg:address":"P O Box 4676",
    "sg:city":"Sutton Coldfield",
    "sg:classifiers":[
        {
            "category":"Professional",
            "subcategory":"Computer Services",
            "type":"Services"
        }
    ],
    "sg:phone":"+44 121 354 3412",
    "sg:postcode":"B72 1EX",
    "sg:province":"West Midlands",
    "sg:tags":[
        "consultant"
    ],
    "wof:name":"Visual Precision Ltd.",
    "wof:placetype":"venue"
},
  "geometry": {"coordinates":[-1.8236290216,52.5544509888],"type":"Point"}
}