{
  "type": "Feature",
  "properties": {
    "iso:country":"GB",
    "sg:address":"109 High Street",
    "sg:city":"Berkhamsted",
    "sg:classifiers":[
        {
            "category":"Health Services",
            "subcategory":"Health Practitioner",
            "type":"Services"
        }
    ],
    "sg:phone":"+44 1442 878900",
    "sg:postcode":"HP4 2DG",
    "sg:province":"Bedfordshire",
    "sg:tags":[
        "osteopath"
    ],
    "wof:name":"Juliet Hanwell",
    "wof:placetype":"venue"
},
  "geometry": {"coordinates":[-0.560852,51.759155],"type":"Point"}
}