{
  "type": "Feature",
  "properties": {
    "iso:country":"GB",
    "sg:address":"249 West George Street",
    "sg:city":"Glasgow",
    "sg:classifiers":[
        {
            "category":"Professional",
            "subcategory":"Lawyer & Legal Services",
            "type":"Services"
        }
    ],
    "sg:phone":"+44 141 304 3434",
    "sg:postcode":"G2 4RD",
    "sg:province":"Glasgow City",
    "sg:tags":[
        "solicitor"
    ],
    "wof:name":"Bird Semple",
    "wof:placetype":"venue"
},
  "geometry": {"coordinates":[-4.262318,55.862911],"type":"Point"}
}