{
  "type": "Feature",
  "properties": {
    "iso:country":"GB",
    "sg:address":"22 Belmont Street",
    "sg:city":"Aberdeen",
    "sg:classifiers":[
        {
            "category":"Shopping",
            "subcategory":"Hobbies, Toys, & Games",
            "type":"Retail Goods"
        }
    ],
    "sg:postcode":"AB10 1JH",
    "sg:province":"Aberdeen City",
    "sg:tags":[
        "collectors'",
        "item"
    ],
    "wof:name":"Belle's Bears",
    "wof:placetype":"venue"
},
  "geometry": {"coordinates":[-2.101259,57.147045],"type":"Point"}
}