{
  "type": "Feature",
  "properties": {
    "addr:full":"106 Drummond Rd Romford Essex RM7 7EW",
    "addr:housenumber":"106",
    "addr:postcode":"rm7 7ew",
    "addr:street":"Drummond Rd",
    "iso:country":"GB",
    "sg:address":"106 Drummond Rd",
    "sg:city":"Romford",
    "sg:classifiers":[
        {
            "category":"Building & Trades",
            "subcategory":"Construction",
            "type":"Services"
        }
    ],
    "sg:postcode":"RM7 7EW",
    "sg:province":"Essex",
    "sg:tags":[
        "joiner",
        "carpenter"
    ],
    "wof:name":"Carpentry by Tony",
    "wof:placetype":"venue"
},
  "geometry": {"coordinates":[0.1709309965,51.5819816589],"type":"Point"}
}