{
  "type": "Feature",
  "properties": {
    "addr:full":"68 Howard Rd Cricklewood Greater London NW2 6DR",
    "addr:housenumber":"68",
    "addr:postcode":"nw2 6dr",
    "addr:street":"Howard Rd",
    "iso:country":"GB",
    "sg:address":"68 Howard Rd",
    "sg:city":"Cricklewood",
    "sg:classifiers":[
        {
            "category":"Building & Trades",
            "subcategory":"Construction",
            "type":"Services"
        }
    ],
    "sg:phone":"+44 20 8969 4177",
    "sg:postcode":"NW2 6DR",
    "sg:province":"Greater London",
    "sg:tags":[
        "roofing"
    ],
    "wof:name":"Residential Roofing",
    "wof:placetype":"venue"
},
  "geometry": {"coordinates":[-0.217535,51.555138],"type":"Point"}
}