{
  "type": "Feature",
  "properties": {
    "addr:full":"Castle Head Farm, Lindale Grange-over-sands Cumbria LA11 6LL",
    "addr:postcode":"la11 6ll",
    "iso:country":"GB",
    "sg:address":"Castle Head Farm, Lindale",
    "sg:city":"Grange-over-sands",
    "sg:classifiers":[
        {
            "category":"Farming",
            "subcategory":"Dairy Farm",
            "type":"Manufacturing & Wholesale Goods"
        }
    ],
    "sg:phone":"+44 15395 33031",
    "sg:postcode":"LA11 6LL",
    "sg:province":"Cumbria",
    "wof:name":"Messrs R H Tyson",
    "wof:placetype":"venue"
},
  "geometry": {"coordinates":[-2.8944489956,54.2165718079],"type":"Point"}
}