{
  "type": "Feature",
  "properties": {
    "iso:country":"GB",
    "sg:address":"Guy St",
    "sg:city":"Stoke-on-trent",
    "sg:classifiers":[
        {
            "category":"Fast Food",
            "type":"Food & Drink"
        }
    ],
    "sg:postcode":"ST2 9BB",
    "sg:province":"Staffordshire",
    "sg:tags":[
        "away",
        "take"
    ],
    "wof:name":"P & M's Takeaway",
    "wof:placetype":"venue"
},
  "geometry": {"coordinates":[-2.139194,53.025066],"type":"Point"}
}