{
  "type": "Feature",
  "properties": {
    "addr:full":"Carney Cottage, High Street Winkleigh Devon EX19 8HX",
    "addr:postcode":"ex19 8hx",
    "addr:street":"High Street",
    "iso:country":"GB",
    "sg:address":"Carney Cottage, High Street",
    "sg:city":"Winkleigh",
    "sg:classifiers":[
        {
            "category":"Retail",
            "subcategory":"Funeral Services",
            "type":"Services"
        }
    ],
    "sg:phone":"+44 1837 83387",
    "sg:postcode":"EX19 8HX",
    "sg:province":"Devon",
    "sg:tags":[
        "director",
        "cemetery",
        "crematorium"
    ],
    "wof:name":"William David Carne",
    "wof:placetype":"venue"
},
  "geometry": {"coordinates":[-3.942385,50.855579],"type":"Point"}
}