{
  "type": "Feature",
  "properties": {
    "iso:country":"GB",
    "sg:address":"Unit4 Stanton Road",
    "sg:city":"Southampton",
    "sg:classifiers":[
        {
            "category":"Professional",
            "subcategory":"Printing & Photocopies",
            "type":"Services"
        }
    ],
    "sg:phone":"+44 23 8077 1197",
    "sg:postcode":"SO15 4HU",
    "sg:province":"Hampshire",
    "sg:tags":[
        "printer"
    ],
    "wof:name":"Inprint (Litho) Ltd.",
    "wof:placetype":"venue"
},
  "geometry": {"coordinates":[-1.407319,50.909939],"type":"Point"}
}