{
  "type": "Feature",
  "properties": {
    "addr:full":"678 Walmersley Road Bury Lancashire BL9 6RN",
    "addr:housenumber":"678",
    "addr:postcode":"bl9 6rn",
    "addr:street":"Walmersley Road",
    "iso:country":"GB",
    "sg:address":"678 Walmersley Road",
    "sg:city":"Bury",
    "sg:classifiers":[
        {
            "category":"Government",
            "subcategory":"Post Office",
            "type":"Public Place"
        }
    ],
    "sg:phone":"+44 161 764 4728",
    "sg:postcode":"BL9 6RN",
    "sg:province":"Lancashire",
    "wof:name":"Walmersley Post Office",
    "wof:placetype":"venue"
},
  "geometry": {"coordinates":[-2.2948160172,53.617805481],"type":"Point"}
}