{
  "type": "Feature",
  "properties": {
    "addr:full":"Hill Top Road, Stockton Heath Warrington Cheshire WA4 2EF",
    "addr:postcode":"wa4 2ef",
    "addr:street":"Hill Top Road",
    "iso:country":"GB",
    "sg:address":"Hill Top Road, Stockton Heath",
    "sg:city":"Warrington",
    "sg:classifiers":[
        {
            "category":"Health Services",
            "subcategory":"Nursing And Care Facility",
            "type":"Services"
        }
    ],
    "sg:phone":"+44 1925 265865",
    "sg:postcode":"WA4 2EF",
    "sg:province":"Cheshire",
    "sg:tags":[
        "home"
    ],
    "wof:name":"Summerville Nursing Home",
    "wof:placetype":"venue"
},
  "geometry": {"coordinates":[-2.5621340275,53.3773536682],"type":"Point"}
}