{
  "type": "Feature",
  "properties": {
    "addr:full":"Hazel Road Southampton Hampshire SO19 7GB",
    "addr:postcode":"so19 7gb",
    "addr:street":"Hazel Road",
    "iso:country":"GB",
    "sg:address":"Hazel Road",
    "sg:city":"Southampton",
    "sg:classifiers":[
        {
            "category":"Home & Garden",
            "subcategory":"Home Furnishings",
            "type":"Retail Goods"
        }
    ],
    "sg:phone":"+44 23 8043 7202",
    "sg:postcode":"SO19 7GB",
    "sg:province":"Hampshire",
    "sg:tags":[
        "furnishers",
        "planner",
        "kitchen"
    ],
    "wof:name":"Taylor Tredre",
    "wof:placetype":"venue"
},
  "geometry": {"coordinates":[-1.381717,50.902645],"type":"Point"}
}