{
  "type": "Feature",
  "properties": {
    "addr:full":"177 Wardour Street London Greater London W1F 8WX",
    "addr:housenumber":"177",
    "addr:postcode":"w1f 8wx",
    "addr:street":"Wardour Street",
    "iso:country":"GB",
    "sg:address":"177 Wardour Street",
    "sg:city":"London",
    "sg:classifiers":[
        {
            "category":"Professional",
            "subcategory":"Advertising",
            "type":"Services"
        }
    ],
    "sg:phone":"+44 20 7287 2211",
    "sg:postcode":"W1F 8WX",
    "sg:province":"Greater London",
    "sg:tags":[
        "agency"
    ],
    "wof:name":"Eardrum Ltd.",
    "wof:placetype":"venue"
},
  "geometry": {"coordinates":[-0.135344,51.514977],"type":"Point"}
}