{
  "type": "Feature",
  "properties": {
    "addr:full":"462 Preston Old Road Blackburn Lancashire BB2 5LY",
    "addr:housenumber":"462",
    "addr:postcode":"bb2 5ly",
    "addr:street":"Preston Old Road",
    "iso:country":"GB",
    "sg:address":"462 Preston Old Road",
    "sg:city":"Blackburn",
    "sg:classifiers":[
        {
            "category":"Building & Trades",
            "subcategory":"Locksmith",
            "type":"Services"
        }
    ],
    "sg:phone":"+44 1254 209593",
    "sg:postcode":"BB2 5LY",
    "sg:province":"Lancashire",
    "sg:tags":[
        "steeplejack"
    ],
    "wof:name":"Warburton Steeplejacks & Co",
    "wof:placetype":"venue"
},
  "geometry": {"coordinates":[-2.5226809978,53.7317314148],"type":"Point"}
}