{
  "type": "Feature",
  "properties": {
    "addr:full":"Hill Farm, Pontesford Hill Shrewsbury Shropshire SY5 0UH",
    "addr:postcode":"sy5 0uh",
    "addr:street":"Hill;Pontesford Hill",
    "iso:country":"GB",
    "sg:address":"Hill Farm, Pontesford Hill",
    "sg:city":"Shrewsbury",
    "sg:classifiers":[
        {
            "category":"Organizations",
            "subcategory":"Non-profit Organization",
            "type":"Services"
        }
    ],
    "sg:phone":"+44 1743 791975",
    "sg:postcode":"SY5 0UH",
    "sg:province":"Shropshire",
    "sg:tags":[
        "organisation",
        "voluntary",
        "charity"
    ],
    "wof:name":"Hill Farm Project",
    "wof:placetype":"venue"
},
  "geometry": {"coordinates":[-2.8787300587,52.6425895691],"type":"Point"}
}