{
  "type": "Feature",
  "properties": {
    "iso:country":"GB",
    "sg:address":"3 St Peters Lane, Blythe Bridge",
    "sg:city":"Stoke-on-trent",
    "sg:classifiers":[
        {
            "category":"Building & Trades",
            "subcategory":"Construction",
            "type":"Services"
        }
    ],
    "sg:phone":"+44 1782 399986",
    "sg:postcode":"ST11 9TG",
    "sg:province":"Staffordshire",
    "sg:tags":[
        "builder"
    ],
    "wof:name":"D & P Homes Ltd.",
    "wof:placetype":"venue"
},
  "geometry": {"coordinates":[-2.072661,52.96735],"type":"Point"}
}