{
  "type": "Feature",
  "properties": {
    "addr:full":"28 Corporation Street Dewsbury West Yorkshire WF13 1QG",
    "addr:housenumber":"28",
    "addr:postcode":"wf13 1qg",
    "addr:street":"Corporation Street",
    "iso:country":"GB",
    "sg:address":"28 Corporation Street",
    "sg:city":"Dewsbury",
    "sg:classifiers":[
        {
            "category":"Shopping",
            "subcategory":"News",
            "type":"Retail Goods"
        }
    ],
    "sg:phone":"+44 1924 46435",
    "sg:postcode":"WF13 1QG",
    "sg:province":"West Yorkshire",
    "sg:tags":[
        "newsagent"
    ],
    "wof:name":"Patbro Newsagents",
    "wof:placetype":"venue"
},
  "geometry": {"coordinates":[-1.6278159618,53.6925811768],"type":"Point"}
}