{
  "type": "Feature",
  "properties": {
    "iso:country":"GB",
    "sg:address":"31 Eggbridge Lane, Waverton",
    "sg:city":"Chester",
    "sg:classifiers":[
        {
            "category":"Building & Trades",
            "subcategory":"Construction",
            "type":"Services"
        },
        {
            "category":"Military Area",
            "subcategory":"Air Force Base",
            "type":"Public Place"
        }
    ],
    "sg:postcode":"CH3 7PE",
    "sg:province":"Cheshire",
    "sg:tags":[
        "groundwork",
        "excavation",
        "contractor"
    ],
    "wof:name":"E E T Contractors",
    "wof:placetype":"venue"
},
  "geometry": {"coordinates":[-2.8191509247,53.1710014343],"type":"Point"}
}