{
  "type": "Feature",
  "properties": {
    "addr:full":"16 Main Street, Fauldhouse Bathgate North Lanarkshire EH47 9HX",
    "addr:housenumber":"16",
    "addr:postcode":"eh47 9hx",
    "addr:street":"Main Street;Bathgate",
    "iso:country":"GB",
    "sg:address":"16 Main Street, Fauldhouse",
    "sg:city":"Bathgate",
    "sg:classifiers":[
        {
            "category":"Food & Beverages",
            "subcategory":"Meat & Fish",
            "type":"Retail Goods"
        }
    ],
    "sg:postcode":"EH47 9HX",
    "sg:province":"North Lanarkshire",
    "sg:tags":[
        "butcher"
    ],
    "wof:name":"P Brannan",
    "wof:placetype":"venue"
},
  "geometry": {"coordinates":[-3.7077150345,55.8275299072],"type":"Point"}
}