{
  "type": "Feature",
  "properties": {
    "iso:country":"GB",
    "sg:address":"Oxford Road, Hay On Wye",
    "sg:city":"Hereford",
    "sg:classifiers":[
        {
            "category":"Travel",
            "subcategory":"Hotels & Motels",
            "type":"Entertainment"
        }
    ],
    "sg:phone":"+44 1497 820613",
    "sg:postcode":"HR3 5AJ",
    "sg:province":"Herefordshire",
    "sg:tags":[
        "house",
        "guest"
    ],
    "wof:name":"La Fosse Guest House",
    "wof:placetype":"venue"
},
  "geometry": {"coordinates":[-3.123751,52.073559],"type":"Point"}
}