{
  "type": "Feature",
  "properties": {
    "addr:full":"Portleven Surgery, Sunset Gardens Helston Cornwall TR13 9BT",
    "addr:postcode":"tr13 9bt",
    "addr:street":"Sunset Gardens",
    "iso:country":"GB",
    "sg:address":"Portleven Surgery, Sunset Gardens",
    "sg:city":"Helston",
    "sg:classifiers":[
        {
            "category":"Health Services",
            "subcategory":"Doctor",
            "type":"Services"
        }
    ],
    "sg:phone":"+44 1326 562204",
    "sg:postcode":"TR13 9BT",
    "sg:province":"Cornwall",
    "sg:tags":[
        "practitioners"
    ],
    "wof:name":"Whittle, K G",
    "wof:placetype":"venue"
},
  "geometry": {"coordinates":[-5.266959,50.10582],"type":"Point"}
}