{
  "type": "Feature",
  "properties": {
    "iso:country":"GB",
    "sg:address":"2-4 Oxford Road",
    "sg:city":"Manchester",
    "sg:classifiers":[
        {
            "category":"Real Estate",
            "subcategory":"Real Estate Agent",
            "type":"Services"
        }
    ],
    "sg:phone":"+44 161 236 6883",
    "sg:postcode":"M1 5QA",
    "sg:province":"Greater Manchester",
    "wof:name":"Ebbrose Ltd.",
    "wof:placetype":"venue"
},
  "geometry": {"coordinates":[-2.243309,53.476948],"type":"Point"}
}