{
  "type": "Feature",
  "properties": {
    "iso:country":"GB",
    "sg:address":"13 Lewis Road",
    "sg:city":"Emsworth",
    "sg:classifiers":[
        {
            "category":"Retail",
            "subcategory":"Driving School",
            "type":"Services"
        }
    ],
    "sg:phone":"+44 1243 373088",
    "sg:postcode":"PO10 7RP",
    "sg:province":"Hampshire",
    "wof:name":"Unity School Of Motoring",
    "wof:placetype":"venue"
},
  "geometry": {"coordinates":[-0.934625,50.860348],"type":"Point"}
}