{
  "type": "Feature",
  "properties": {
    "iso:country":"GB",
    "sg:address":"Unit C, The Old Bakery",
    "sg:city":"Swindon",
    "sg:classifiers":[
        {
            "category":"Wholesale",
            "subcategory":"Medical Equipment & Supplies",
            "type":"Manufacturing & Wholesale Goods"
        },
        {
            "category":"Military Area",
            "subcategory":"Air Force Base",
            "type":"Public Place"
        }
    ],
    "sg:phone":"+44 1793 692666",
    "sg:postcode":"SN2 2NP",
    "sg:province":"Wiltshire",
    "sg:tags":[
        "sanitary",
        "hospital"
    ],
    "wof:name":"Stainless Design Services Ltd",
    "wof:placetype":"venue"
},
  "geometry": {"coordinates":[-1.8031,51.573231],"type":"Point"}
}