{
  "type": "Feature",
  "properties": {
    "addr:full":"Russell Grant Building, Fish Dock Rd Grimsby Lincolnshire DN31 3PD",
    "addr:postcode":"dn31 3pd",
    "addr:street":"Russell;Dock Rd",
    "iso:country":"GB",
    "sg:address":"Russell Grant Building, Fish Dock Rd",
    "sg:city":"Grimsby",
    "sg:classifiers":[
        {
            "category":"Food & Beverages",
            "subcategory":"Meat & Fish",
            "type":"Retail Goods"
        }
    ],
    "sg:phone":"+44 1472 354114",
    "sg:postcode":"DN31 3PD",
    "sg:province":"Lincolnshire",
    "sg:tags":[
        "merchant"
    ],
    "wof:name":"Lofthouse T & D",
    "wof:placetype":"venue"
},
  "geometry": {"coordinates":[-0.0694499984,53.5797080994],"type":"Point"}
}