{
  "type": "Feature",
  "properties": {
    "iso:country":"GB",
    "sg:address":"Gate House, 2 High St",
    "sg:city":"Totnes",
    "sg:classifiers":[
        {
            "category":"Real Estate",
            "subcategory":"Surveying",
            "type":"Services"
        }
    ],
    "sg:phone":"+44 1803 862002",
    "sg:postcode":"TQ9 5RZ",
    "sg:province":"Devon",
    "sg:tags":[
        "surveyor",
        "valuer"
    ],
    "wof:name":"Michelmore Hughes",
    "wof:placetype":"venue"
},
  "geometry": {"coordinates":[-3.687421,50.43132],"type":"Point"}
}