{
  "type": "Feature",
  "properties": {
    "addr:full":"Lionheart Stadium, Post Office Road, Featherstone Pontefract West Yorkshire WF7 5EN",
    "addr:postcode":"wf7 5en",
    "addr:street":"Office Road;West",
    "iso:country":"GB",
    "sg:address":"Lionheart Stadium, Post Office Road, Featherstone",
    "sg:city":"Pontefract",
    "sg:classifiers":[
        {
            "category":"Arena",
            "subcategory":"Sports Club",
            "type":"Entertainment"
        }
    ],
    "sg:phone":"+44 1977 702386",
    "sg:postcode":"WF7 5EN",
    "sg:province":"West Yorkshire",
    "wof:name":"Featherstone Rovers R L F C",
    "wof:placetype":"venue"
},
  "geometry": {"coordinates":[-1.3556660414,53.6778755188],"type":"Point"}
}