{
  "type": "Feature",
  "properties": {
    "addr:full":"Goldthorn Park Primary School, Ward Rd Wolverhampton Staffordshire WV4 5ET",
    "addr:postcode":"wv4 5et",
    "addr:street":"Ward Rd",
    "iso:country":"GB",
    "sg:address":"Goldthorn Park Primary School, Ward Rd",
    "sg:city":"Wolverhampton",
    "sg:classifiers":[
        {
            "category":"Government",
            "subcategory":"Office",
            "type":"Public Place"
        }
    ],
    "sg:phone":"+44 1902 342814",
    "sg:postcode":"WV4 5ET",
    "sg:province":"Staffordshire",
    "sg:tags":[
        "local"
    ],
    "wof:name":"Wolverhampton Borough Council",
    "wof:placetype":"venue"
},
  "geometry": {"coordinates":[-2.1396620274,52.5662765503],"type":"Point"}
}