{
  "type": "Feature",
  "properties": {
    "addr:full":"Newton, Keithhall Inverurie Aberdeenshire AB51 0NB",
    "addr:postcode":"ab51 0nb",
    "iso:country":"GB",
    "sg:address":"Newton, Keithhall",
    "sg:city":"Inverurie",
    "sg:classifiers":[
        {
            "category":"Farming",
            "subcategory":"Livestock Farm",
            "type":"Manufacturing & Wholesale Goods"
        }
    ],
    "sg:postcode":"AB51 0NB",
    "sg:province":"Aberdeenshire",
    "sg:tags":[
        "others"
    ],
    "wof:name":"P I Donald & Son",
    "wof:placetype":"venue"
},
  "geometry": {"coordinates":[-2.363842,57.274666],"type":"Point"}
}