{
  "type": "Feature",
  "properties": {
    "iso:country":"GB",
    "sg:address":"Caretaker, Berkeley Road, Staple Hill",
    "sg:city":"Bristol",
    "sg:classifiers":[
        {
            "category":"Social Services",
            "subcategory":"Adult Care",
            "type":"Services"
        }
    ],
    "sg:phone":"+44 117 957 0408",
    "sg:postcode":"BS16 5HS",
    "sg:province":"City of Bristol",
    "sg:tags":[
        "housing",
        "sheltered"
    ],
    "wof:name":"Berkeley House",
    "wof:placetype":"venue"
},
  "geometry": {"coordinates":[-2.591429,51.453667],"type":"Point"}
}