{
  "type": "Feature",
  "properties": {
    "addr:full":"51 St Andrews Street South Bury St Edmunds Suffolk IP33 1SD",
    "addr:housenumber":"51",
    "addr:postcode":"ip33 1sd",
    "addr:street":"St Andrews Street South",
    "iso:country":"GB",
    "sg:address":"51 St Andrews Street South",
    "sg:city":"Bury St Edmunds",
    "sg:classifiers":[
        {
            "category":"Professional",
            "subcategory":"Computer Services",
            "type":"Services"
        }
    ],
    "sg:phone":"+44 1284 702305",
    "sg:postcode":"IP33 1SD",
    "sg:province":"Suffolk",
    "sg:tags":[
        "system",
        "software"
    ],
    "wof:name":"The Computer Magic Centre",
    "wof:placetype":"venue"
},
  "geometry": {"coordinates":[0.71097,52.244831],"type":"Point"}
}