{
  "type": "Feature",
  "properties": {
    "addr:full":"67 Mostyn Street Llandudno Conwy LL30 2NN",
    "addr:housenumber":"67",
    "addr:postcode":"ll30 2nn",
    "addr:street":"Mostyn Street",
    "iso:country":"GB",
    "sg:address":"67 Mostyn Street",
    "sg:city":"Llandudno",
    "sg:classifiers":[
        {
            "category":"Shopping",
            "subcategory":"Bicycles & Sporting Goods",
            "type":"Retail Goods"
        }
    ],
    "sg:phone":"+44 1492 872511",
    "sg:postcode":"LL30 2NN",
    "sg:province":"Conwy",
    "sg:tags":[
        "equipment",
        "camping"
    ],
    "wof:name":"Millets Leisure",
    "wof:placetype":"venue"
},
  "geometry": {"coordinates":[-3.8287959099,53.3238830566],"type":"Point"}
}