{
  "type": "Feature",
  "properties": {
    "iso:country":"GB",
    "sg:address":"20 Blackbull Road",
    "sg:city":"Folkestone",
    "sg:classifiers":[
        {
            "category":"Retail",
            "subcategory":"Repair Shop",
            "type":"Services"
        }
    ],
    "sg:phone":"+44 1303 257776",
    "sg:postcode":"CT19 5QN",
    "sg:province":"Kent",
    "sg:tags":[
        "television",
        "good",
        "video",
        "servicing",
        "maintenance",
        "radio"
    ],
    "wof:name":"Folkestone T V Centre",
    "wof:placetype":"venue"
},
  "geometry": {"coordinates":[1.178213,51.085957],"type":"Point"}
}