{
  "type": "Feature",
  "properties": {
    "addr:full":"23 Portland Road Ashford Greater London TW15 3BU",
    "addr:housenumber":"23",
    "addr:postcode":"tw15 3bu",
    "addr:street":"Portland Road",
    "iso:country":"GB",
    "sg:address":"23 Portland Road",
    "sg:city":"Ashford",
    "sg:classifiers":[
        {
            "category":"Professional",
            "subcategory":"Engineering",
            "type":"Services"
        },
        {
            "category":"Building & Trades",
            "subcategory":"Electrical",
            "type":"Services"
        }
    ],
    "sg:phone":"+44 1784 256246",
    "sg:postcode":"TW15 3BU",
    "sg:province":"Greater London",
    "sg:tags":[
        "engineer",
        "electrician",
        "contractor"
    ],
    "wof:name":"Ashford Electrical",
    "wof:placetype":"venue"
},
  "geometry": {"coordinates":[-0.475241,51.438747],"type":"Point"}
}