{
  "type": "Feature",
  "properties": {
    "addr:full":"Unit 7 Stockwell Centre, Stephenson Way Crawley Surrey RH10 1TN",
    "addr:housenumber":"unit 7",
    "addr:postcode":"rh10 1tn",
    "addr:street":"Stephenson Way",
    "iso:country":"GB",
    "sg:address":"Unit 7 Stockwell Centre, Stephenson Way",
    "sg:city":"Crawley",
    "sg:classifiers":[
        {
            "category":"Freight",
            "type":"Transportation"
        },
        {
            "category":"Professional",
            "subcategory":"Business Services",
            "type":"Services"
        }
    ],
    "sg:phone":"+44 1293 439898",
    "sg:postcode":"RH10 1TN",
    "sg:province":"Surrey",
    "sg:tags":[
        "haulage",
        "import",
        "export",
        "road",
        "agent"
    ],
    "wof:name":"Universal Transport & Trading Ltd.",
    "wof:placetype":"venue"
},
  "geometry": {"coordinates":[-0.184753,51.118458],"type":"Point"}
}