{
  "type": "Feature",
  "properties": {
    "addr:full":"Unit A2 Riding Court, Riding Court Road, Datchet Slough Berkshire SL3 9LE",
    "addr:housenumber":"a2",
    "addr:postcode":"sl3 9le",
    "addr:street":"Riding Court Riding Court Road",
    "iso:country":"GB",
    "sg:address":"Unit A2 Riding Court, Riding Court Road, Datchet",
    "sg:city":"Slough",
    "sg:classifiers":[
        {
            "category":"Real Estate",
            "subcategory":"Architect",
            "type":"Services"
        }
    ],
    "sg:phone":"+44 1753 580033",
    "sg:postcode":"SL3 9LE",
    "sg:province":"Berkshire",
    "wof:name":"Edgington Spink & Hyne",
    "wof:placetype":"venue"
},
  "geometry": {"coordinates":[-0.5657600164,51.4871635437],"type":"Point"}
}