{
  "type": "Feature",
  "properties": {
    "iso:country":"GB",
    "sg:address":"100 Barbirolli Square",
    "sg:city":"Manchester",
    "sg:classifiers":[
        {
            "category":"Professional",
            "subcategory":"Computer Services",
            "type":"Services"
        }
    ],
    "sg:phone":"+44 1444 416859",
    "sg:postcode":"M2 3AB",
    "sg:province":"Greater Manchester",
    "sg:tags":[
        "system",
        "software"
    ],
    "wof:name":"Microlab Ltd.",
    "wof:placetype":"venue"
},
  "geometry": {"coordinates":[-2.246304,53.475746],"type":"Point"}
}