{
  "type": "Feature",
  "properties": {
    "iso:country":"GB",
    "sg:address":"1st Floor, Transport House, John Dobson St, Newcastle",
    "sg:city":"Newcastle Upon Tyne",
    "sg:classifiers":[
        {
            "category":"Organizations",
            "subcategory":"Professional Association",
            "type":"Services"
        }
    ],
    "sg:phone":"+44 191 222 0330",
    "sg:postcode":"NE1 8TW",
    "sg:province":"Tyne and Wear",
    "sg:tags":[
        "union",
        "trade"
    ],
    "wof:name":"Public & Commercial Services Union",
    "wof:placetype":"venue"
},
  "geometry": {"coordinates":[-1.610424,54.97604],"type":"Point"}
}