{
  "type": "Feature",
  "properties": {
    "addr:full":"779 Finchley Road London Greater London NW11 8DR",
    "addr:housenumber":"779",
    "addr:postcode":"nw11 8dr",
    "addr:street":"Finchley Road",
    "iso:country":"GB",
    "sg:address":"779 Finchley Road",
    "sg:city":"London",
    "sg:classifiers":[
        {
            "category":"Organizations",
            "subcategory":"Non-profit Organization",
            "type":"Services"
        }
    ],
    "sg:postcode":"NW11 8DR",
    "sg:province":"Greater London",
    "sg:tags":[
        "organisation",
        "voluntary",
        "charity"
    ],
    "wof:name":"Thirty-Fives Womens Campaign for Soviet Jewry",
    "wof:placetype":"venue"
},
  "geometry": {"coordinates":[-0.1963669956,51.5655670166],"type":"Point"}
}