{
  "type": "Feature",
  "properties": {
    "iso:country":"GB",
    "sg:address":"1a Highlands Road",
    "sg:city":"Runcorn",
    "sg:classifiers":[
        {
            "category":"Education",
            "subcategory":"Preschool",
            "type":"Public Place"
        }
    ],
    "sg:phone":"+44 1928 581150",
    "sg:postcode":"WA7 4PS",
    "sg:province":"Cheshire",
    "sg:tags":[
        "pre-school",
        "playgroups"
    ],
    "wof:name":"Vicarage Lodge Playgroup",
    "wof:placetype":"venue"
},
  "geometry": {"coordinates":[-2.739620924,53.3334579468],"type":"Point"}
}