{
  "type": "Feature",
  "properties": {
    "iso:country":"GB",
    "sg:address":"Hillend Grn",
    "sg:city":"Dymock",
    "sg:classifiers":[
        {
            "category":"Manufacturing",
            "subcategory":"Signs",
            "type":"Manufacturing & Wholesale Goods"
        }
    ],
    "sg:postcode":"GL18 2AB",
    "sg:province":"Gloucestershire",
    "sg:tags":[
        "nameplate"
    ],
    "wof:name":"Spa Signs & Service",
    "wof:placetype":"venue"
},
  "geometry": {"coordinates":[-2.439709,51.978809],"type":"Point"}
}