{
  "type": "Feature",
  "properties": {
    "iso:country":"GB",
    "sg:address":"Spa Lane",
    "sg:city":"Harrogate",
    "sg:classifiers":[
        {
            "category":"Government",
            "subcategory":"Office",
            "type":"Public Place"
        },
        {
            "category":"Sports & Exercise",
            "subcategory":"Swimming Pool",
            "type":"Entertainment"
        }
    ],
    "sg:phone":"+44 1423 883155",
    "sg:postcode":"HG2 7JF",
    "sg:province":"North Yorkshire",
    "sg:tags":[
        "operation",
        "local"
    ],
    "wof:name":"Starbeck Swimming Pool",
    "wof:placetype":"venue"
},
  "geometry": {"coordinates":[-1.498018,53.997952],"type":"Point"}
}