{
  "type": "Feature",
  "properties": {
    "addr:full":"Southgate House, Thaxted Rd Saffron Walden Cambridgeshire CB10 2UR",
    "addr:postcode":"cb10 2ur",
    "addr:street":"Thaxted Rd",
    "iso:country":"GB",
    "sg:address":"Southgate House, Thaxted Rd",
    "sg:city":"Saffron Walden",
    "sg:classifiers":[
        {
            "category":"Home & Garden",
            "subcategory":"Home Furnishings",
            "type":"Retail Goods"
        }
    ],
    "sg:phone":"+44 1799 522061",
    "sg:postcode":"CB10 2UR",
    "sg:province":"Cambridgeshire",
    "sg:tags":[
        "homefurnishings"
    ],
    "wof:name":"Chris Allen Furniture",
    "wof:placetype":"venue"
},
  "geometry": {"coordinates":[0.25777,52.011978],"type":"Point"}
}