{
  "type": "Feature",
  "properties": {
    "addr:full":"38 Parkhouse Road Ardrossan North Ayrshire KA22 8AN",
    "addr:housenumber":"38",
    "addr:postcode":"ka22 8an",
    "addr:street":"Parkhouse Road",
    "iso:country":"GB",
    "sg:address":"38 Parkhouse Road",
    "sg:city":"Ardrossan",
    "sg:classifiers":[
        {
            "category":"Organizations",
            "subcategory":"Non-profit Organization",
            "type":"Services"
        }
    ],
    "sg:phone":"+44 1294 469955",
    "sg:postcode":"KA22 8AN",
    "sg:province":"North Ayrshire",
    "sg:tags":[
        "organisation",
        "voluntary",
        "charity"
    ],
    "wof:name":"Alzheimer's Scotland Action on Dementia",
    "wof:placetype":"venue"
},
  "geometry": {"coordinates":[-4.803499,55.646389],"type":"Point"}
}