{
  "type": "Feature",
  "properties": {
    "iso:country":"GB",
    "sg:address":"The Health Centre, Trevaylor Rd",
    "sg:city":"Falmouth",
    "sg:classifiers":[
        {
            "category":"Health Services",
            "subcategory":"Doctor",
            "type":"Services"
        }
    ],
    "sg:phone":"+44 1326 434800",
    "sg:postcode":"TR11 2LH",
    "sg:province":"Cornwall",
    "sg:tags":[
        "practitioners"
    ],
    "wof:name":"Slater, P D",
    "wof:placetype":"venue"
},
  "geometry": {"coordinates":[-5.080033,50.152206],"type":"Point"}
}