{
  "type": "Feature",
  "properties": {
    "iso:country":"GB",
    "sg:address":"3 Campden Road",
    "sg:city":"South Croydon",
    "sg:classifiers":[
        {
            "category":"Social Services",
            "subcategory":"Retirement Home",
            "type":"Services"
        }
    ],
    "sg:phone":"+44 20 8680 1219",
    "sg:postcode":"CR2 7EQ",
    "sg:province":"Surrey",
    "sg:tags":[
        "residential",
        "care"
    ],
    "wof:name":"Tamarind Care Ltd.",
    "wof:placetype":"venue"
},
  "geometry": {"coordinates":[-0.0855960026,51.36120224],"type":"Point"}
}