{
  "type": "Feature",
  "properties": {
    "addr:full":"40 Beaver Rd Coalville Leicestershire LE67 3LD",
    "addr:housenumber":"40",
    "addr:postcode":"le67 3ld",
    "addr:street":"Beaver Rd",
    "iso:country":"GB",
    "sg:address":"40 Beaver Rd",
    "sg:city":"Coalville",
    "sg:classifiers":[
        {
            "category":"Cinema",
            "subcategory":"Movie Rental",
            "type":"Entertainment"
        }
    ],
    "sg:phone":"+44 1530 812573",
    "sg:postcode":"LE67 3LD",
    "sg:province":"Leicestershire",
    "sg:tags":[
        "video",
        "library"
    ],
    "wof:name":"Starlite Video",
    "wof:placetype":"venue"
},
  "geometry": {"coordinates":[-1.372306,52.718784],"type":"Point"}
}