{
  "type": "Feature",
  "properties": {
    "iso:country":"GB",
    "sg:address":"100 Nicol Street",
    "sg:city":"Kirkcaldy",
    "sg:classifiers":[
        {
            "category":"Building & Trades",
            "subcategory":"Plumbing",
            "type":"Services"
        },
        {
            "category":"Home & Garden",
            "subcategory":"Hardware",
            "type":"Retail Goods"
        }
    ],
    "sg:phone":"+44 1592 264732",
    "sg:postcode":"KY1 1PF",
    "sg:province":"Fife",
    "sg:tags":[
        "merchant",
        "plumber",
        "plumbers'"
    ],
    "wof:name":"Plumb Center Ltd",
    "wof:placetype":"venue"
},
  "geometry": {"coordinates":[-3.1682960987,56.1075248718],"type":"Point"}
}