{
  "type": "Feature",
  "properties": {
    "addr:full":"1 Betterton House, Betterton St, Covent Garden Holborn Greater London WC2H 9BT",
    "addr:housenumber":"1",
    "addr:postcode":"wc2h 9bt",
    "addr:street":"Betterton House Betterton St",
    "iso:country":"GB",
    "sg:address":"1 Betterton House, Betterton St, Covent Garden",
    "sg:city":"Holborn",
    "sg:classifiers":[
        {
            "category":"Museum",
            "subcategory":"Art Museum",
            "type":"Entertainment"
        }
    ],
    "sg:phone":"+44 20 7692 9200",
    "sg:postcode":"WC2H 9BT",
    "sg:province":"Greater London",
    "sg:tags":[
        "gallery"
    ],
    "wof:name":"Incubator",
    "wof:placetype":"venue"
},
  "geometry": {"coordinates":[-0.124,51.514709],"type":"Point"}
}