{
  "type": "Feature",
  "properties": {
    "addr:full":"137 Station Road Shotts North Lanarkshire ML7 4BJ",
    "addr:housenumber":"137",
    "addr:postcode":"ml7 4bj",
    "addr:street":"Station Road",
    "iso:country":"GB",
    "sg:address":"137 Station Road",
    "sg:city":"Shotts",
    "sg:classifiers":[
        {
            "category":"Health Services",
            "subcategory":"Optometrist",
            "type":"Services"
        },
        {
            "category":"Shopping",
            "subcategory":"Optician",
            "type":"Retail Goods"
        }
    ],
    "sg:phone":"+44 1501 820427",
    "sg:postcode":"ML7 4BJ",
    "sg:province":"North Lanarkshire",
    "sg:tags":[
        "ophthalmic"
    ],
    "wof:name":"Maurice N Lipsey",
    "wof:placetype":"venue"
},
  "geometry": {"coordinates":[-3.796697,55.81879],"type":"Point"}
}