{
  "type": "Feature",
  "properties": {
    "iso:country":"GB",
    "sg:address":"Chapel Road, Ridgewell",
    "sg:city":"Halstead",
    "sg:classifiers":[
        {
            "category":"Professional",
            "subcategory":"Printing & Photocopies",
            "type":"Services"
        }
    ],
    "sg:phone":"+44 1440 788866",
    "sg:postcode":"CO9 4RU",
    "sg:province":"Essex",
    "sg:tags":[
        "process",
        "screen",
        "printer"
    ],
    "wof:name":"Traditional Print Ltd.",
    "wof:placetype":"venue"
},
  "geometry": {"coordinates":[0.53186,52.039803],"type":"Point"}
}