{
  "type": "Feature",
  "properties": {
    "iso:country":"GB",
    "sg:address":"2 Sewardstone Rd",
    "sg:city":"Waltham Abbey",
    "sg:classifiers":[
        {
            "category":"Health Services",
            "subcategory":"Health Practitioner",
            "type":"Services"
        }
    ],
    "sg:phone":"+44 1992 715804",
    "sg:postcode":"EN9 1NA",
    "sg:province":"Essex",
    "sg:tags":[
        "physiotherapist"
    ],
    "wof:name":"L K J Connor",
    "wof:placetype":"venue"
},
  "geometry": {"coordinates":[0.00146,51.686687],"type":"Point"}
}