{
  "type": "Feature",
  "properties": {
    "addr:full":"Off River Road, Eaton Ford Huntingdon Bedfordshire PE19 7AU",
    "addr:postcode":"pe19 7au",
    "addr:street":"Off River Road",
    "iso:country":"GB",
    "sg:address":"Off River Road, Eaton Ford",
    "sg:city":"Huntingdon",
    "sg:classifiers":[
        {
            "category":"Organizations",
            "subcategory":"Membership Organization",
            "type":"Services"
        },
        {
            "category":"Arena",
            "subcategory":"Sports Club",
            "type":"Entertainment"
        }
    ],
    "sg:phone":"+44 1480 218119",
    "sg:postcode":"PE19 7AU",
    "sg:province":"Bedfordshire",
    "wof:name":"St.Neots & District Indoor Bowling Club",
    "wof:placetype":"venue"
},
  "geometry": {"coordinates":[-0.282424,52.227955],"type":"Point"}
}