{
  "type": "Feature",
  "properties": {
    "addr:full":"Unit 15a Eley Estate, Angel Road, Edmonton London Greater London N18 3BH",
    "addr:housenumber":"unit 15a",
    "addr:postcode":"n18 3bh",
    "addr:street":"Eley Estate Angel Road Edmonton",
    "iso:country":"GB",
    "sg:address":"Unit 15a Eley Estate, Angel Road, Edmonton",
    "sg:city":"London",
    "sg:classifiers":[
        {
            "category":"Home & Garden",
            "subcategory":"Carpets & Floor Coverings",
            "type":"Retail Goods"
        }
    ],
    "sg:phone":"+44 20 8884 2596",
    "sg:postcode":"N18 3BH",
    "sg:province":"Greater London",
    "sg:tags":[
        "carpets",
        "rug",
        "matting"
    ],
    "wof:name":"Allied Carpet Stores",
    "wof:placetype":"venue"
},
  "geometry": {"coordinates":[-0.045519,51.615429],"type":"Point"}
}