{
  "type": "Feature",
  "properties": {
    "addr:full":"Well Lane, North Stifford Grays Essex RM16 5UL",
    "addr:postcode":"rm16 5ul",
    "addr:street":"Well Lane",
    "iso:country":"GB",
    "sg:address":"Well Lane, North Stifford",
    "sg:city":"Grays",
    "sg:classifiers":[
        {
            "category":"Sports & Exercise",
            "subcategory":"Stables",
            "type":"Entertainment"
        }
    ],
    "sg:phone":"+44 1375 375304",
    "sg:postcode":"RM16 5UL",
    "sg:province":"Essex",
    "sg:tags":[
        "education",
        "equestrian"
    ],
    "wof:name":"Well Lane Stables",
    "wof:placetype":"venue"
},
  "geometry": {"coordinates":[0.3048630059,51.4980010986],"type":"Point"}
}