{
  "type": "Feature",
  "properties": {
    "addr:full":"Muirhall Garage, 167 Main Street Larbert Falkirk FK5 4AN",
    "addr:housenumber":"167",
    "addr:postcode":"fk5 4an",
    "addr:street":"Main Street",
    "iso:country":"GB",
    "sg:address":"Muirhall Garage, 167 Main Street",
    "sg:city":"Larbert",
    "sg:classifiers":[
        {
            "category":"Autos & Motor Vehicles",
            "subcategory":"Automobile Sales",
            "type":"Retail Goods"
        }
    ],
    "sg:phone":"+44 1324 562799",
    "sg:postcode":"FK5 4AN",
    "sg:province":"Falkirk",
    "sg:tags":[
        "car"
    ],
    "wof:name":"Hardie of Larbert",
    "wof:placetype":"venue"
},
  "geometry": {"coordinates":[-3.8243689537,56.0243835449],"type":"Point"}
}