{
  "type": "Feature",
  "properties": {
    "addr:full":"P O Box 3087 Chiswick Greater London W4 4ZP",
    "addr:housenumber":"p o;3087",
    "addr:postcode":"w4 4zp",
    "addr:street":"Chiswick",
    "iso:country":"GB",
    "sg:address":"P O Box 3087",
    "sg:city":"Chiswick",
    "sg:classifiers":[
        {
            "category":"Organizations",
            "subcategory":"Non-profit Organization",
            "type":"Services"
        }
    ],
    "sg:phone":"+44 20 8994 9874",
    "sg:postcode":"W4 4ZP",
    "sg:province":"Greater London",
    "sg:tags":[
        "organisation",
        "voluntary",
        "charity"
    ],
    "wof:name":"Medical Advisory Service The",
    "wof:placetype":"venue"
},
  "geometry": {"coordinates":[-0.270089,51.492531],"type":"Point"}
}