{
  "type": "Feature",
  "properties": {
    "addr:full":"Orwell House, Manse Rd Kinross Clackmannanshire KY13 9YQ",
    "addr:postcode":"ky13 9yq",
    "addr:street":"Manse Rd",
    "iso:country":"GB",
    "sg:address":"Orwell House, Manse Rd",
    "sg:city":"Kinross",
    "sg:classifiers":[
        {
            "category":"Real Estate",
            "subcategory":"Real Estate Agent",
            "type":"Services"
        }
    ],
    "sg:phone":"+44 1577 865926",
    "sg:postcode":"KY13 9YQ",
    "sg:province":"Clackmannanshire",
    "wof:name":"County Home Search Co Ltd",
    "wof:placetype":"venue"
},
  "geometry": {"coordinates":[-3.4204039574,56.2287864685],"type":"Point"}
}