{
  "type": "Feature",
  "properties": {
    "addr:full":"Bridgwater Area Taunton Devon TA3 6AJ",
    "addr:postcode":"ta3 6aj",
    "iso:country":"GB",
    "sg:address":"Bridgwater Area",
    "sg:city":"Taunton",
    "sg:classifiers":[
        {
            "category":"Organizations",
            "subcategory":"Non-profit Organization",
            "type":"Services"
        }
    ],
    "sg:phone":"+44 1823 480355",
    "sg:postcode":"TA3 6AJ",
    "sg:province":"Devon",
    "sg:tags":[
        "organisation",
        "voluntary",
        "charity"
    ],
    "wof:name":"S S A F A Forces Help",
    "wof:placetype":"venue"
},
  "geometry": {"coordinates":[-2.96606,50.981049],"type":"Point"}
}