{
  "type": "Feature",
  "properties": {
    "iso:country":"GB",
    "sg:address":"Herriot House, North Place",
    "sg:city":"Cheltenham",
    "sg:classifiers":[
        {
            "category":"Home & Garden",
            "subcategory":"Kitchen Supply",
            "type":"Retail Goods"
        }
    ],
    "sg:phone":"+44 1242 573227",
    "sg:postcode":"GL50 4DS",
    "sg:province":"Gloucestershire",
    "sg:tags":[
        "equipment",
        "catering"
    ],
    "wof:name":"Hospitality Equipment Supplies Ltd.",
    "wof:placetype":"venue"
},
  "geometry": {"coordinates":[-2.072179,51.904369],"type":"Point"}
}