{
  "type": "Feature",
  "properties": {
    "addr:full":"Sharples Park Bolton Lancashire BL1 6PQ",
    "addr:postcode":"bl1 6pq",
    "iso:country":"GB",
    "sg:address":"Sharples Park",
    "sg:city":"Bolton",
    "sg:classifiers":[
        {
            "category":"Education",
            "subcategory":"School",
            "type":"Public Place"
        },
        {
            "category":"Organizations",
            "subcategory":"Religious Organization",
            "type":"Services"
        }
    ],
    "sg:phone":"+44 1204 301204",
    "sg:postcode":"BL1 6PQ",
    "sg:province":"Lancashire",
    "sg:tags":[
        "organisation",
        "local",
        "authority"
    ],
    "wof:name":"Thornleigh Salesian College",
    "wof:placetype":"venue"
},
  "geometry": {"coordinates":[-2.4410610199,53.6017913818],"type":"Point"}
}