{
  "type": "Feature",
  "properties": {
    "addr:full":"139 Effingham Street Rotherham South Yorkshire S65 1BL",
    "addr:housenumber":"139",
    "addr:postcode":"s65 1bl",
    "addr:street":"Effingham Street",
    "iso:country":"GB",
    "sg:address":"139 Effingham Street",
    "sg:city":"Rotherham",
    "sg:classifiers":[
        {
            "category":"Personal",
            "subcategory":"Beauty Salon",
            "type":"Services"
        },
        {
            "category":"Personal",
            "subcategory":"Barber",
            "type":"Services"
        }
    ],
    "sg:phone":"+44 1709 368308",
    "sg:postcode":"S65 1BL",
    "sg:province":"South Yorkshire",
    "sg:tags":[
        "unisex",
        "hairdresser"
    ],
    "sg:website":"http://www.lecoiffeur.co.uk",
    "wof:name":"Le Coiffeur Ii",
    "wof:placetype":"venue"
},
  "geometry": {"coordinates":[-1.353841,53.435917],"type":"Point"}
}