{
  "type": "Feature",
  "properties": {
    "addr:full":"Church Street, Great Wilbraham Cambridge Cambridgeshire CB1 5JQ",
    "addr:postcode":"cb1 5jq",
    "addr:street":"Church Street",
    "iso:country":"GB",
    "sg:address":"Church Street, Great Wilbraham",
    "sg:city":"Cambridge",
    "sg:classifiers":[
        {
            "category":"Education",
            "subcategory":"School",
            "type":"Public Place"
        }
    ],
    "sg:phone":"+44 1223 880408",
    "sg:postcode":"CB1 5JQ",
    "sg:province":"Cambridgeshire",
    "sg:tags":[
        "local",
        "authority"
    ],
    "wof:name":"Great Wilbraham Primary School",
    "wof:placetype":"venue"
},
  "geometry": {"coordinates":[0.2666150033,52.1930236816],"type":"Point"}
}