{
  "type": "Feature",
  "properties": {
    "iso:country":"GB",
    "sg:address":"43 Hopewell Yard, Hopewell Street",
    "sg:city":"London",
    "sg:classifiers":[
        {
            "category":"Professional",
            "subcategory":"Business Services",
            "type":"Services"
        }
    ],
    "sg:phone":"+44 20 7703 9884",
    "sg:postcode":"SE5 7QS",
    "sg:province":"Greater London",
    "sg:tags":[
        "distribution"
    ],
    "wof:name":"Blueheart Promotions",
    "wof:placetype":"venue"
},
  "geometry": {"coordinates":[-0.08902,51.477211],"type":"Point"}
}