{
  "type": "Feature",
  "properties": {
    "addr:full":"53 Fleet Street London Greater London EC4Y 1BE",
    "addr:housenumber":"53",
    "addr:postcode":"ec4y 1be",
    "addr:street":"Fleet Street",
    "iso:country":"GB",
    "sg:address":"53 Fleet Street",
    "sg:city":"London",
    "sg:classifiers":[
        {
            "category":"Banks & Credit Unions",
            "subcategory":"Financial Services",
            "type":"Services"
        }
    ],
    "sg:phone":"+44 20 7356 0866",
    "sg:postcode":"EC4Y 1BE",
    "sg:province":"Greater London",
    "sg:tags":[
        "adviser"
    ],
    "wof:name":"Winter Dean Partnership",
    "wof:placetype":"venue"
},
  "geometry": {"coordinates":[-0.1087540016,51.5141220093],"type":"Point"}
}