{
  "type": "Feature",
  "properties": {
    "addr:full":"Lovedays Mead Stroud Gloucestershire GL5 1XB",
    "addr:postcode":"gl5 1xb",
    "iso:country":"GB",
    "sg:address":"Lovedays Mead",
    "sg:city":"Stroud",
    "sg:classifiers":[
        {
            "category":"Organizations",
            "subcategory":"Non-profit Organization",
            "type":"Services"
        }
    ],
    "sg:phone":"+44 1453 764065",
    "sg:postcode":"GL5 1XB",
    "sg:province":"Gloucestershire",
    "sg:tags":[
        "organisation",
        "voluntary",
        "charity"
    ],
    "wof:name":"The Hiram Trust",
    "wof:placetype":"venue"
},
  "geometry": {"coordinates":[-2.218014,51.748016],"type":"Point"}
}