{
  "type": "Feature",
  "properties": {
    "addr:full":"Tan House Farm, Ball Lane, Kingsley Warrington Cheshire WA6 8HL",
    "addr:postcode":"wa6 8hl",
    "addr:street":"Ball Lane",
    "iso:country":"GB",
    "sg:address":"Tan House Farm, Ball Lane, Kingsley",
    "sg:city":"Warrington",
    "sg:classifiers":[
        {
            "category":"Farming",
            "subcategory":"Livestock Farm",
            "type":"Manufacturing & Wholesale Goods"
        }
    ],
    "sg:postcode":"WA6 8HL",
    "sg:province":"Cheshire",
    "sg:tags":[
        "others"
    ],
    "wof:name":"A F Shallcross",
    "wof:placetype":"venue"
},
  "geometry": {"coordinates":[-2.67337,53.268963],"type":"Point"}
}