{
  "type": "Feature",
  "properties": {
    "addr:full":"3 Glaholm Road Sunderland Tyne and Wear SR1 2NX",
    "addr:housenumber":"3",
    "addr:postcode":"sr1 2nx",
    "addr:street":"Glaholm Road",
    "iso:country":"GB",
    "sg:address":"3 Glaholm Road",
    "sg:city":"Sunderland",
    "sg:classifiers":[
        {
            "category":"Manufacturing",
            "subcategory":"Petroleum Products",
            "type":"Manufacturing & Wholesale Goods"
        }
    ],
    "sg:phone":"+44 191 510 2023",
    "sg:postcode":"SR1 2NX",
    "sg:province":"Tyne and Wear",
    "sg:tags":[
        "double",
        "glazing"
    ],
    "wof:name":"B & M Glass",
    "wof:placetype":"venue"
},
  "geometry": {"coordinates":[-1.368436,54.903091],"type":"Point"}
}