{
  "type": "Feature",
  "properties": {
    "addr:full":"132b London Road, St Leonards On Sea Hastings East Sussex TN37 6LT",
    "addr:housenumber":"132b",
    "addr:postcode":"tn37 6lt",
    "addr:street":"London Road",
    "iso:country":"GB",
    "sg:address":"132b London Road, St Leonards On Sea",
    "sg:city":"Hastings",
    "sg:classifiers":[
        {
            "category":"Real Estate",
            "subcategory":"Real Estate Operator",
            "type":"Services"
        }
    ],
    "sg:phone":"+44 1424 437261",
    "sg:postcode":"TN37 6LT",
    "sg:province":"East Sussex",
    "sg:tags":[
        "letting",
        "agent"
    ],
    "wof:name":"Slate Securities",
    "wof:placetype":"venue"
},
  "geometry": {"coordinates":[0.556843,50.861523],"type":"Point"}
}