{
  "type": "Feature",
  "properties": {
    "addr:full":"9/10 Coronation Bldg(s), Wallasey Road Wallasey Merseyside CH45 4NE",
    "addr:housenumber":"9 / 10",
    "addr:postcode":"ch45 4ne",
    "addr:street":"Coronation Bldg S Wallasey Road",
    "iso:country":"GB",
    "sg:address":"9/10 Coronation Bldg(s), Wallasey Road",
    "sg:city":"Wallasey",
    "sg:classifiers":[
        {
            "category":"Banks & Credit Unions",
            "subcategory":"Bank",
            "type":"Services"
        }
    ],
    "sg:phone":"+44 845 604 5010",
    "sg:postcode":"CH45 4NE",
    "sg:province":"Merseyside",
    "wof:name":"Halifax Plc",
    "wof:placetype":"venue"
},
  "geometry": {"coordinates":[-3.046298,53.419899],"type":"Point"}
}