{
  "type": "Feature",
  "properties": {
    "addr:full":"Dolphin House, Albany Park Camberley Hampshire GU16 7PL",
    "addr:postcode":"gu16 7pl",
    "addr:street":"Park",
    "iso:country":"GB",
    "sg:address":"Dolphin House, Albany Park",
    "sg:city":"Camberley",
    "sg:classifiers":[
        {
            "category":"Professional",
            "subcategory":"Art Services",
            "type":"Services"
        },
        {
            "category":"Real Estate",
            "subcategory":"Architect",
            "type":"Services"
        }
    ],
    "sg:postcode":"GU16 7PL",
    "sg:province":"Hampshire",
    "sg:tags":[
        "consultant",
        "design"
    ],
    "wof:name":"Wigram Tivendale Associates",
    "wof:placetype":"venue"
},
  "geometry": {"coordinates":[-0.7511590123,51.3178291321],"type":"Point"}
}