{
  "type": "Feature",
  "properties": {
    "addr:full":"50 Compton Road Leeds West Yorkshire LS9 6DG",
    "addr:housenumber":"50",
    "addr:postcode":"ls9 6dg",
    "addr:street":"Compton Road",
    "iso:country":"GB",
    "sg:address":"50 Compton Road",
    "sg:city":"Leeds",
    "sg:classifiers":[
        {
            "category":"Government",
            "subcategory":"Post Office",
            "type":"Public Place"
        }
    ],
    "sg:phone":"+44 845 722 3344",
    "sg:postcode":"LS9 6DG",
    "sg:province":"West Yorkshire",
    "sg:website":"http://www.postoffice.co.uk",
    "wof:name":"Compton Road Post Office",
    "wof:placetype":"venue"
},
  "geometry": {"coordinates":[-1.510257,53.808079],"type":"Point"}
}