{
  "type": "Feature",
  "properties": {
    "addr:full":"70 Reddicap Heath Road Sutton Coldfield Staffordshire B75 7EW",
    "addr:housenumber":"70",
    "addr:postcode":"b75 7ew",
    "addr:street":"Reddicap Heath Road",
    "iso:country":"GB",
    "sg:address":"70 Reddicap Heath Road",
    "sg:city":"Sutton Coldfield",
    "sg:classifiers":[
        {
            "category":"Social Services",
            "subcategory":"Retirement Home",
            "type":"Services"
        }
    ],
    "sg:phone":"+44 121 329 2222",
    "sg:postcode":"B75 7EW",
    "sg:province":"Staffordshire",
    "sg:tags":[
        "residential",
        "care"
    ],
    "wof:name":"Heathway Residential Care",
    "wof:placetype":"venue"
},
  "geometry": {"coordinates":[-1.795756,52.560944],"type":"Point"}
}