{
  "type": "Feature",
  "properties": {
    "iso:country":"GB",
    "sg:address":"12a Wimborne Rd",
    "sg:city":"Bournemouth",
    "sg:classifiers":[
        {
            "category":"Health Services",
            "subcategory":"Dentist",
            "type":"Services"
        }
    ],
    "sg:phone":"+44 1202 555421",
    "sg:postcode":"BH2 6NG",
    "sg:province":"Dorset",
    "wof:name":"R L Wood",
    "wof:placetype":"venue"
},
  "geometry": {"coordinates":[-1.876696,50.725796],"type":"Point"}
}