{
  "type": "Feature",
  "properties": {
    "iso:country":"GB",
    "sg:address":"31 Upper Barr",
    "sg:city":"Oxford",
    "sg:classifiers":[
        {
            "category":"Shopping",
            "subcategory":"Gifts & Souvenirs",
            "type":"Retail Goods"
        }
    ],
    "sg:phone":"+44 1865 779500",
    "sg:postcode":"OX4 3UX",
    "sg:province":"Oxfordshire",
    "sg:tags":[
        "shop",
        "poster",
        "card"
    ],
    "wof:name":"THE WISHING WELL",
    "wof:placetype":"venue"
},
  "geometry": {"coordinates":[-1.215386,51.731785],"type":"Point"}
}