{
  "type": "Feature",
  "properties": {
    "addr:full":"3-4 Featherstone Terrace Southall Greater London UB2 5AL",
    "addr:housenumber":"3-4",
    "addr:postcode":"ub2 5al",
    "addr:street":"Featherstone Terrace",
    "iso:country":"GB",
    "sg:address":"3-4 Featherstone Terrace",
    "sg:city":"Southall",
    "sg:classifiers":[
        {
            "category":"Health Services",
            "subcategory":"Clinic",
            "type":"Services"
        }
    ],
    "sg:phone":"+44 208992841",
    "sg:postcode":"UB2 5AL",
    "sg:province":"Greater London",
    "sg:tags":[
        "misuse",
        "alcohol"
    ],
    "wof:name":"Turning Point",
    "wof:placetype":"venue"
},
  "geometry": {"coordinates":[-0.3827930093,51.5021209717],"type":"Point"}
}