{
  "type": "Feature",
  "properties": {
    "addr:full":"52 Fore Street Trowbridge Wiltshire BA14 8ES",
    "addr:housenumber":"52",
    "addr:postcode":"ba14 8es",
    "addr:street":"Fore Street",
    "iso:country":"GB",
    "sg:address":"52 Fore Street",
    "sg:city":"Trowbridge",
    "sg:classifiers":[
        {
            "category":"Shopping",
            "subcategory":"Shoes",
            "type":"Retail Goods"
        }
    ],
    "sg:phone":"+44 1225 775443",
    "sg:postcode":"BA14 8ES",
    "sg:province":"Wiltshire",
    "sg:tags":[
        "shop"
    ],
    "wof:name":"Oliver's Shoes",
    "wof:placetype":"venue"
},
  "geometry": {"coordinates":[-2.207758,51.321194],"type":"Point"}
}