{
  "type": "Feature",
  "properties": {
    "addr:full":"63 Bard Road London Greater London W10 6TP",
    "addr:housenumber":"63",
    "addr:postcode":"w10 6tp",
    "addr:street":"Bard Road",
    "iso:country":"GB",
    "sg:address":"63 Bard Road",
    "sg:city":"London",
    "sg:classifiers":[
        {
            "category":"Professional",
            "subcategory":"Computer Services",
            "type":"Services"
        }
    ],
    "sg:phone":"+44 20 8968 6241",
    "sg:postcode":"W10 6TP",
    "sg:province":"Greater London",
    "sg:tags":[
        "system",
        "software"
    ],
    "wof:name":"The Notting Dale Technology Centre Ltd.",
    "wof:placetype":"venue"
},
  "geometry": {"coordinates":[-0.2196290046,51.5121192932],"type":"Point"}
}