{
  "type": "Feature",
  "properties": {
    "addr:full":"Unit 0 St Marks Road, St James Industrial Estate Corby Northamptonshire NN18 8AN",
    "addr:housenumber":"unit 0",
    "addr:postcode":"nn18 8an",
    "addr:street":"St Marks Road St;Estate",
    "iso:country":"GB",
    "sg:address":"Unit 0 St Marks Road, St James Industrial Estate",
    "sg:city":"Corby",
    "sg:classifiers":[
        {
            "category":"Manufacturing",
            "subcategory":"Wood Products",
            "type":"Manufacturing & Wholesale Goods"
        },
        {
            "category":"Organizations",
            "subcategory":"Non-profit Organization",
            "type":"Services"
        }
    ],
    "sg:postcode":"NN18 8AN",
    "sg:province":"Northamptonshire",
    "sg:tags":[
        "voluntary",
        "organisation",
        "crate",
        "packaging",
        "pallets",
        "charity"
    ],
    "wof:name":"The Teamwork Trust Ltd.",
    "wof:placetype":"venue"
},
  "geometry": {"coordinates":[-0.6859279871,52.4861717224],"type":"Point"}
}