{
  "type": "Feature",
  "properties": {
    "addr:full":"Owles Farm Buntingford Hertfordshire SG9 9PL",
    "addr:postcode":"sg9 9pl",
    "iso:country":"GB",
    "sg:address":"Owles Farm",
    "sg:city":"Buntingford",
    "sg:classifiers":[
        {
            "category":"Farming",
            "subcategory":"Livestock Farm",
            "type":"Manufacturing & Wholesale Goods"
        }
    ],
    "sg:phone":"+44 1763 271376",
    "sg:postcode":"SG9 9PL",
    "sg:province":"Hertfordshire",
    "sg:tags":[
        "others"
    ],
    "wof:name":"Ralph E Scott",
    "wof:placetype":"venue"
},
  "geometry": {"coordinates":[-0.018635,51.946301],"type":"Point"}
}