{
  "type": "Feature",
  "properties": {
    "addr:full":"214 Edgware Rd Bayswater Greater London W2 1DH",
    "addr:housenumber":"214",
    "addr:postcode":"w2 1dh",
    "addr:street":"Edgware Rd",
    "iso:country":"GB",
    "sg:address":"214 Edgware Rd",
    "sg:city":"Bayswater",
    "sg:classifiers":[
        {
            "category":"Travel",
            "subcategory":"Travel Agent",
            "type":"Entertainment"
        }
    ],
    "sg:phone":"+44 870 500 1002",
    "sg:postcode":"W2 1DH",
    "sg:province":"Greater London",
    "wof:name":"Travelmood Ltd",
    "wof:placetype":"venue"
},
  "geometry": {"coordinates":[-0.16906,51.519127],"type":"Point"}
}