{
  "type": "Feature",
  "properties": {
    "iso:country":"GB",
    "sg:address":"Victory Business Centre, Somers Road North",
    "sg:city":"Portsmouth",
    "sg:classifiers":[
        {
            "category":"Freight",
            "type":"Transportation"
        }
    ],
    "sg:phone":"+44 800 568855",
    "sg:postcode":"PO1 1PJ",
    "sg:province":"Hampshire",
    "sg:tags":[
        "haulage",
        "road"
    ],
    "wof:name":"Alarm Distribution (U K) Ltd.",
    "wof:placetype":"venue"
},
  "geometry": {"coordinates":[-1.087284,50.804008],"type":"Point"}
}