{
  "type": "Feature",
  "properties": {
    "addr:full":"Sunnyhaze, Chapel Street Seaton Devon EX12 4AN",
    "addr:postcode":"ex12 4an",
    "addr:street":"Chapel Street",
    "iso:country":"GB",
    "sg:address":"Sunnyhaze, Chapel Street",
    "sg:city":"Seaton",
    "sg:classifiers":[
        {
            "category":"Education",
            "subcategory":"Music School",
            "type":"Public Place"
        }
    ],
    "sg:postcode":"EX12 4AN",
    "sg:province":"Devon",
    "sg:tags":[
        "conservatory"
    ],
    "wof:name":"Conservatory Services",
    "wof:placetype":"venue"
},
  "geometry": {"coordinates":[-3.075809,50.70454],"type":"Point"}
}