{
  "type": "Feature",
  "properties": {
    "addr:full":"Hamlets Service Station, 261 Commercial Road Whitechapel Greater London E1 2BT",
    "addr:housenumber":"261",
    "addr:postcode":"e1 2bt",
    "addr:street":"Commercial Road",
    "iso:country":"GB",
    "sg:address":"Hamlets Service Station, 261 Commercial Road",
    "sg:city":"Whitechapel",
    "sg:classifiers":[
        {
            "category":"Autos & Motor Vehicles",
            "subcategory":"Fuel & Gas Station",
            "type":"Retail Goods"
        }
    ],
    "sg:phone":"+44 20 7790 3296",
    "sg:postcode":"E1 2BT",
    "sg:province":"Greater London",
    "sg:tags":[
        "petrol",
        "filling"
    ],
    "wof:name":"Bp Express Shopping",
    "wof:placetype":"venue"
},
  "geometry": {"coordinates":[-0.0584499985,51.5147399902],"type":"Point"}
}