{
  "type": "Feature",
  "properties": {
    "iso:country":"GB",
    "sg:address":"Little Mera, East Quay",
    "sg:city":"St Austell",
    "sg:classifiers":[
        {
            "category":"Restaurant",
            "type":"Food & Drink"
        }
    ],
    "sg:phone":"+44 1726 843051",
    "sg:postcode":"PL26 6QQ",
    "sg:province":"Cornwall",
    "wof:name":"The Sundeck Restuarant",
    "wof:placetype":"venue"
},
  "geometry": {"coordinates":[-4.78416,50.27021],"type":"Point"}
}