{
  "type": "Feature",
  "properties": {
    "iso:country":"GB",
    "sg:address":"30 Eastholme Drive",
    "sg:city":"York",
    "sg:classifiers":[
        {
            "category":"Food & Beverages",
            "subcategory":"Bakery",
            "type":"Retail Goods"
        }
    ],
    "sg:phone":"+44 1904 640400",
    "sg:postcode":"YO30 5SW",
    "sg:province":"North Yorkshire",
    "sg:tags":[
        "baker"
    ],
    "wof:name":"Oven Gloves",
    "wof:placetype":"venue"
},
  "geometry": {"coordinates":[-1.1078469753,53.9799575806],"type":"Point"}
}