{
  "type": "Feature",
  "properties": {
    "addr:full":"New Loom House, 101 Back Church Lane London Greater London E1 1LU",
    "addr:housenumber":"101",
    "addr:postcode":"e1 1lu",
    "addr:street":"Back Church Lane",
    "iso:country":"GB",
    "sg:address":"New Loom House, 101 Back Church Lane",
    "sg:city":"London",
    "sg:classifiers":[
        {
            "category":"Professional",
            "subcategory":"Art Services",
            "type":"Services"
        }
    ],
    "sg:phone":"+44 20 8852 2575",
    "sg:postcode":"E1 1LU",
    "sg:province":"Greater London",
    "sg:tags":[
        "graphic",
        "designer"
    ],
    "wof:name":"Profex Partnership",
    "wof:placetype":"venue"
},
  "geometry": {"coordinates":[-0.067264,51.512653],"type":"Point"}
}