{
  "type": "Feature",
  "properties": {
    "iso:country":"GB",
    "sg:address":"24 Derby Street",
    "sg:city":"Ormskirk",
    "sg:classifiers":[
        {
            "category":"Banks & Credit Unions",
            "subcategory":"Bank",
            "type":"Services"
        }
    ],
    "sg:phone":"+44 1695 572421",
    "sg:postcode":"L39 2BY",
    "sg:province":"Lancashire",
    "sg:tags":[
        "financial",
        "institution"
    ],
    "wof:name":"The Royal Bank of Scotland Plc",
    "wof:placetype":"venue"
},
  "geometry": {"coordinates":[-2.884853,53.568768],"type":"Point"}
}