{
  "type": "Feature",
  "properties": {
    "iso:country":"GB",
    "sg:address":"57/59 High Street",
    "sg:city":"Wincanton",
    "sg:classifiers":[
        {
            "category":"Utilities",
            "subcategory":"Refuse",
            "type":"Services"
        }
    ],
    "sg:phone":"+44 1963 32851",
    "sg:postcode":"BA9 9JZ",
    "sg:province":"Somerset",
    "sg:tags":[
        "disposal",
        "waste",
        "retail"
    ],
    "wof:name":"Special Collections Services",
    "wof:placetype":"venue"
},
  "geometry": {"coordinates":[-2.407215,51.056938],"type":"Point"}
}