{
  "type": "Feature",
  "properties": {
    "iso:country":"GB",
    "sg:address":"1 Church Causeway",
    "sg:city":"Sandy",
    "sg:classifiers":[
        {
            "category":"Military Area",
            "subcategory":"Air Force Base",
            "type":"Public Place"
        }
    ],
    "sg:phone":"+44 1767 260443",
    "sg:postcode":"SG19 2RL",
    "sg:province":"Bedfordshire",
    "sg:tags":[
        "taxi",
        "hire",
        "private"
    ],
    "wof:name":"Derek Smith",
    "wof:placetype":"venue"
},
  "geometry": {"coordinates":[-0.244996,52.145988],"type":"Point"}
}