{
  "type": "Feature",
  "properties": {
    "iso:country":"GB",
    "sg:address":"406 Selby Road",
    "sg:city":"Leeds",
    "sg:classifiers":[
        {
            "category":"Building & Trades",
            "subcategory":"Construction",
            "type":"Services"
        }
    ],
    "sg:phone":"+44 113 264 6599",
    "sg:postcode":"LS15 9BQ",
    "sg:province":"West Yorkshire",
    "sg:tags":[
        "builder"
    ],
    "wof:name":"Edward William Yoward",
    "wof:placetype":"venue"
},
  "geometry": {"coordinates":[-1.448616,53.797813],"type":"Point"}
}