{
  "type": "Feature",
  "properties": {
    "addr:full":"Station Road Thornton-cleveleys Lancashire FY5 5HY",
    "addr:postcode":"fy5 5hy",
    "addr:street":"Station Road",
    "iso:country":"GB",
    "sg:address":"Station Road",
    "sg:city":"Thornton-cleveleys",
    "sg:classifiers":[
        {
            "category":"Education",
            "subcategory":"School",
            "type":"Public Place"
        }
    ],
    "sg:phone":"+44 1253 823420",
    "sg:postcode":"FY5 5HY",
    "sg:province":"Lancashire",
    "sg:tags":[
        "local",
        "authority"
    ],
    "wof:name":"Baines Endowed Primary School",
    "wof:placetype":"venue"
},
  "geometry": {"coordinates":[-2.99482,53.872421],"type":"Point"}
}