{
  "type": "Feature",
  "properties": {
    "addr:full":"1 Cranfield Rd Liverpool Merseyside L23 9TY",
    "addr:housenumber":"1",
    "addr:postcode":"l23 9ty",
    "addr:street":"Cranfield Rd",
    "iso:country":"GB",
    "sg:address":"1 Cranfield Rd",
    "sg:city":"Liverpool",
    "sg:classifiers":[
        {
            "category":"Health Services",
            "subcategory":"Podiatrist",
            "type":"Services"
        }
    ],
    "sg:phone":"+44 151 286 2416",
    "sg:postcode":"L23 9TY",
    "sg:province":"Merseyside",
    "sg:tags":[
        "podiatrists",
        "chiropodist"
    ],
    "wof:name":"Deirdre Hennessy",
    "wof:placetype":"venue"
},
  "geometry": {"coordinates":[-3.00738,53.492744],"type":"Point"}
}