{
  "type": "Feature",
  "properties": {
    "addr:full":"Wood Lane Resource Centre, Apedale Rd Stoke On Trent Cheshire ST7 8PH",
    "addr:postcode":"st7 8ph",
    "addr:street":"Wood Lane;Apedale Rd",
    "iso:country":"GB",
    "sg:address":"Wood Lane Resource Centre, Apedale Rd",
    "sg:city":"Stoke On Trent",
    "sg:classifiers":[
        {
            "category":"Farming",
            "subcategory":"Nursery",
            "type":"Manufacturing & Wholesale Goods"
        }
    ],
    "sg:phone":"+44 1782 723389",
    "sg:postcode":"ST7 8PH",
    "sg:province":"Cheshire",
    "sg:tags":[
        "creche"
    ],
    "wof:name":"Wood Lane Mother & Toddler Group",
    "wof:placetype":"venue"
},
  "geometry": {"coordinates":[-2.293129,53.056938],"type":"Point"}
}