{
  "type": "Feature",
  "properties": {
    "addr:full":"Bridgton Ho, Tunbridge Wks, Tunbridge Rd, Harold Hill Romford Essex RM3 8TS",
    "addr:postcode":"rm3 8ts",
    "addr:street":"Wks Tunbridge Rd Harold Hill",
    "iso:country":"GB",
    "sg:address":"Bridgton Ho, Tunbridge Wks, Tunbridge Rd, Harold Hill",
    "sg:city":"Romford",
    "sg:classifiers":[
        {
            "category":"Shopping",
            "subcategory":"Stationery & Office Supplies",
            "type":"Retail Goods"
        }
    ],
    "sg:postcode":"RM3 8TS",
    "sg:province":"Essex",
    "sg:tags":[
        "box",
        "carton"
    ],
    "wof:name":"Lee Cutting & Creasing Ltd",
    "wof:placetype":"venue"
},
  "geometry": {"coordinates":[0.21852,51.599941],"type":"Point"}
}