{
  "type": "Feature",
  "properties": {
    "iso:country":"GB",
    "sg:address":"303 Hotwell Road",
    "sg:city":"Bristol",
    "sg:classifiers":[
        {
            "category":"Building & Trades",
            "subcategory":"Construction",
            "type":"Services"
        }
    ],
    "sg:phone":"+44 117 921 3194",
    "sg:postcode":"BS8 4NQ",
    "sg:province":"City of Bristol",
    "sg:tags":[
        "decorator",
        "painter"
    ],
    "wof:name":"Paul Allen Jones",
    "wof:placetype":"venue"
},
  "geometry": {"coordinates":[-2.620928,51.450081],"type":"Point"}
}