{
  "type": "Feature",
  "properties": {
    "addr:full":"56 Revidge Road Blackburn Lancashire BB2 6JQ",
    "addr:housenumber":"56",
    "addr:postcode":"bb2 6jq",
    "addr:street":"Revidge Road",
    "iso:country":"GB",
    "sg:address":"56 Revidge Road",
    "sg:city":"Blackburn",
    "sg:classifiers":[
        {
            "category":"Shopping",
            "subcategory":"News",
            "type":"Retail Goods"
        }
    ],
    "sg:phone":"+44 1254 55413",
    "sg:postcode":"BB2 6JQ",
    "sg:province":"Lancashire",
    "sg:tags":[
        "newsagent"
    ],
    "wof:name":"K & P Renno",
    "wof:placetype":"venue"
},
  "geometry": {"coordinates":[-2.5070319176,53.754119873],"type":"Point"}
}