{
  "type": "Feature",
  "properties": {
    "addr:full":"The Black Horse Swindon Wiltshire SN4 0DQ",
    "addr:postcode":"sn4 0dq",
    "addr:street":"Swindon",
    "iso:country":"GB",
    "sg:address":"The Black Horse",
    "sg:city":"Swindon",
    "sg:classifiers":[
        {
            "category":"Building & Trades",
            "subcategory":"Plumbing",
            "type":"Services"
        }
    ],
    "sg:phone":"+44 1793 791141",
    "sg:postcode":"SN4 0DQ",
    "sg:province":"Wiltshire",
    "sg:tags":[
        "central",
        "heating"
    ],
    "wof:name":"R.K. Sansum",
    "wof:placetype":"venue"
},
  "geometry": {"coordinates":[-1.703199029,51.531463623],"type":"Point"}
}