{
  "type": "Feature",
  "properties": {
    "addr:full":"20 Edinburgh Road Biggar Dumfries and Galloway ML12 6AX",
    "addr:housenumber":"20",
    "addr:postcode":"ml12 6ax",
    "addr:street":"Edinburgh Road",
    "iso:country":"GB",
    "sg:address":"20 Edinburgh Road",
    "sg:city":"Biggar",
    "sg:classifiers":[
        {
            "category":"Arena",
            "subcategory":"Sports Club",
            "type":"Entertainment"
        }
    ],
    "sg:phone":"+44 1899 220510",
    "sg:postcode":"ML12 6AX",
    "sg:province":"Dumfries and Galloway",
    "wof:name":"Biggar Bowling Club",
    "wof:placetype":"venue"
},
  "geometry": {"coordinates":[-3.5171000957,55.6272583008],"type":"Point"}
}