{
  "type": "Feature",
  "properties": {
    "addr:full":"14 Lorne Park Road Bournemouth Dorset BH1 1JN",
    "addr:housenumber":"14",
    "addr:postcode":"bh1 1jn",
    "addr:street":"Lorne Park Road",
    "iso:country":"GB",
    "sg:address":"14 Lorne Park Road",
    "sg:city":"Bournemouth",
    "sg:classifiers":[
        {
            "category":"Communications",
            "subcategory":"News Services",
            "type":"Services"
        }
    ],
    "sg:phone":"+44 1202 558833",
    "sg:postcode":"BH1 1JN",
    "sg:province":"Dorset",
    "sg:tags":[
        "photo",
        "agency"
    ],
    "wof:name":"Bournemouth News & Picture Service",
    "wof:placetype":"venue"
},
  "geometry": {"coordinates":[-1.8705699444,50.7229652405],"type":"Point"}
}