{
  "type": "Feature",
  "properties": {
    "addr:full":"Top Lodge Farm, Kelmarsh Northampton Northamptonshire NN6 9LT",
    "addr:housenumber":"kelmarsh",
    "addr:postcode":"nn6 9lt",
    "addr:street":"Northampton",
    "iso:country":"GB",
    "sg:address":"Top Lodge Farm, Kelmarsh",
    "sg:city":"Northampton",
    "sg:classifiers":[
        {
            "category":"Farming",
            "subcategory":"Livestock Farm",
            "type":"Manufacturing & Wholesale Goods"
        }
    ],
    "sg:phone":"+44 1604 686206",
    "sg:postcode":"NN6 9LT",
    "sg:province":"Northamptonshire",
    "sg:tags":[
        "others"
    ],
    "wof:name":"R F Hayward(Kelton Farms)Ltd.",
    "wof:placetype":"venue"
},
  "geometry": {"coordinates":[-0.918059,52.405346],"type":"Point"}
}