{
  "type": "Feature",
  "properties": {
    "iso:country":"GB",
    "sg:address":"26 Black Bull Road",
    "sg:city":"Folkestone",
    "sg:classifiers":[
        {
            "category":"Personal",
            "subcategory":"Beauty Salon",
            "type":"Services"
        }
    ],
    "sg:phone":"+44 1303 252340",
    "sg:postcode":"CT19 5QP",
    "sg:province":"Kent",
    "sg:tags":[
        "lady",
        "hairdresser"
    ],
    "wof:name":"Tizzy's Hair Salon",
    "wof:placetype":"venue"
},
  "geometry": {"coordinates":[1.178747,51.086296],"type":"Point"}
}