{
  "type": "Feature",
  "properties": {
    "addr:full":"3 Workshop, Coalburn Farm, Hepscott Morpeth Northumberland NE61 6LG",
    "addr:housenumber":"3",
    "addr:postcode":"ne61 6lg",
    "addr:street":"Workshop Coalburn",
    "iso:country":"GB",
    "sg:address":"3 Workshop, Coalburn Farm, Hepscott",
    "sg:city":"Morpeth",
    "sg:classifiers":[
        {
            "category":"Farming",
            "subcategory":"Dairy Farm",
            "type":"Manufacturing & Wholesale Goods"
        }
    ],
    "sg:phone":"+44 1670 515001",
    "sg:postcode":"NE61 6LG",
    "sg:province":"Northumberland",
    "wof:name":"M A Stawart",
    "wof:placetype":"venue"
},
  "geometry": {"coordinates":[-1.6570390463,55.1465339661],"type":"Point"}
}