{
  "type": "Feature",
  "properties": {
    "iso:country":"GB",
    "sg:address":"2 Toll Gavel",
    "sg:city":"Beverley",
    "sg:classifiers":[
        {
            "category":"Retail",
            "subcategory":"Laundry & Dry Cleaning",
            "type":"Services"
        }
    ],
    "sg:phone":"+44 1482 862172",
    "sg:postcode":"HU17 9AJ",
    "sg:province":"East Riding of Yorkshire",
    "sg:tags":[
        "alteration"
    ],
    "wof:name":"Johnson Cleaners UK Ltd",
    "wof:placetype":"venue"
},
  "geometry": {"coordinates":[-0.4303770065,53.8418807983],"type":"Point"}
}