{
  "type": "Feature",
  "properties": {
    "addr:full":"Beacon House, Stokenchurch Business Park, Ibstone Road High Wycombe Buckinghamshire HP14 3AQ",
    "addr:postcode":"hp14 3aq",
    "addr:street":"Stokenchurch Business Park Ibstone Road",
    "iso:country":"GB",
    "sg:address":"Beacon House, Stokenchurch Business Park, Ibstone Road",
    "sg:city":"High Wycombe",
    "sg:classifiers":[
        {
            "category":"Professional",
            "subcategory":"Computer Services",
            "type":"Services"
        }
    ],
    "sg:phone":"+44 1494 486500",
    "sg:postcode":"HP14 3AQ",
    "sg:province":"Buckinghamshire",
    "sg:tags":[
        "system",
        "software"
    ],
    "wof:name":"Redprairie Ltd.",
    "wof:placetype":"venue"
},
  "geometry": {"coordinates":[-0.80233,51.644939],"type":"Point"}
}