{
  "type": "Feature",
  "properties": {
    "iso:country":"GB",
    "sg:address":"Llynddwr Uchaf",
    "sg:city":"Pencader",
    "sg:classifiers":[
        {
            "category":"Farming",
            "subcategory":"Livestock Farm",
            "type":"Manufacturing & Wholesale Goods"
        }
    ],
    "sg:phone":"+44 1559 384946",
    "sg:postcode":"SA39 9HL",
    "sg:province":"Carmarthenshire",
    "sg:tags":[
        "others"
    ],
    "wof:name":"James Alan Jones",
    "wof:placetype":"venue"
},
  "geometry": {"coordinates":[-4.2658638954,52.0002288818],"type":"Point"}
}