{
  "type": "Feature",
  "properties": {
    "addr:full":"Diners Club House, 19 Kingsmead Farnborough Hampshire GU14 7SR",
    "addr:housenumber":"19",
    "addr:postcode":"gu14 7sr",
    "iso:country":"GB",
    "sg:address":"Diners Club House, 19 Kingsmead",
    "sg:city":"Farnborough",
    "sg:classifiers":[
        {
            "category":"Banks & Credit Unions",
            "subcategory":"Financial Services",
            "type":"Services"
        }
    ],
    "sg:phone":"+44 800 460800",
    "sg:postcode":"GU14 7SR",
    "sg:province":"Hampshire",
    "sg:tags":[
        "discount",
        "card"
    ],
    "wof:name":"Citibank International Plc",
    "wof:placetype":"venue"
},
  "geometry": {"coordinates":[-0.7542350292,51.2921142578],"type":"Point"}
}