{
  "type": "Feature",
  "properties": {
    "addr:full":"Shingle Bank Drive, Milford On Sea Lymington Hampshire SO41 0WR",
    "addr:postcode":"so41 0wr",
    "addr:street":"Bank Drive",
    "iso:country":"GB",
    "sg:address":"Shingle Bank Drive, Milford On Sea",
    "sg:city":"Lymington",
    "sg:classifiers":[
        {
            "category":"Social Services",
            "subcategory":"Adult Care",
            "type":"Services"
        }
    ],
    "sg:phone":"+44 1590 645887",
    "sg:postcode":"SO41 0WR",
    "sg:province":"Hampshire",
    "sg:tags":[
        "housing",
        "sheltered"
    ],
    "wof:name":"Homegrange",
    "wof:placetype":"venue"
},
  "geometry": {"coordinates":[-1.595822,50.723564],"type":"Point"}
}