{
  "type": "Feature",
  "properties": {
    "addr:full":"21 High Street Addlestone Surrey KT15 1TL",
    "addr:housenumber":"21",
    "addr:postcode":"kt15 1tl",
    "addr:street":"High Street",
    "iso:country":"GB",
    "sg:address":"21 High Street",
    "sg:city":"Addlestone",
    "sg:classifiers":[
        {
            "category":"Fast Food",
            "type":"Food & Drink"
        }
    ],
    "sg:phone":"+44 1932 831818",
    "sg:postcode":"KT15 1TL",
    "sg:province":"Surrey",
    "sg:tags":[
        "away",
        "meal",
        "outlet",
        "take"
    ],
    "wof:name":"Jononi of Addlestone",
    "wof:placetype":"venue"
},
  "geometry": {"coordinates":[-0.493573,51.371181],"type":"Point"}
}