{
  "type": "Feature",
  "properties": {
    "addr:full":"62 Whiterow Park Trowbridge Wiltshire BA14 0EQ",
    "addr:housenumber":"62",
    "addr:postcode":"ba14 0eq",
    "addr:street":"Whiterow Park",
    "iso:country":"GB",
    "sg:address":"62 Whiterow Park",
    "sg:city":"Trowbridge",
    "sg:classifiers":[
        {
            "category":"Retail",
            "subcategory":"Auto Repair",
            "type":"Services"
        }
    ],
    "sg:phone":"+44 1225 777572",
    "sg:postcode":"BA14 0EQ",
    "sg:province":"Wiltshire",
    "sg:tags":[
        "engine",
        "specialist",
        "diagnostic",
        "tuning",
        "car"
    ],
    "wof:name":"Hometune Motoring Services",
    "wof:placetype":"venue"
},
  "geometry": {"coordinates":[-2.2282478809,51.3074913025],"type":"Point"}
}