{
  "type": "Feature",
  "properties": {
    "iso:country":"GB",
    "sg:address":"74 Wynall Lane",
    "sg:city":"Stourbridge",
    "sg:classifiers":[
        {
            "category":"Fast Food",
            "type":"Food & Drink"
        }
    ],
    "sg:phone":"+44 1384 423415",
    "sg:postcode":"DY9 9AQ",
    "sg:province":"West Midlands",
    "sg:tags":[
        "away",
        "meal",
        "outlet",
        "take"
    ],
    "wof:name":"Art Cuisine",
    "wof:placetype":"venue"
},
  "geometry": {"coordinates":[-2.1056990623,52.4474372864],"type":"Point"}
}