{
  "type": "Feature",
  "properties": {
    "addr:full":"20 Rabans Clo, Rabans Lane Indust Est Aylesbury Buckinghamshire HP19 3RS",
    "addr:housenumber":"20",
    "addr:postcode":"hp19 3rs",
    "addr:street":"Rabans Clo Rabans Lane",
    "iso:country":"GB",
    "sg:address":"20 Rabans Clo, Rabans Lane Indust Est",
    "sg:city":"Aylesbury",
    "sg:classifiers":[
        {
            "category":"Home & Garden",
            "subcategory":"Hardware",
            "type":"Retail Goods"
        }
    ],
    "sg:phone":"+44 1296 393503",
    "sg:postcode":"HP19 3RS",
    "sg:province":"Buckinghamshire",
    "sg:tags":[
        "device",
        "fixing",
        "fastener"
    ],
    "wof:name":"A R Professional Equipment",
    "wof:placetype":"venue"
},
  "geometry": {"coordinates":[-0.8316699862,51.8263015747],"type":"Point"}
}