{
  "type": "Feature",
  "properties": {
    "addr:full":"131 High Street Ibstock Leicestershire LE67 6JQ",
    "addr:housenumber":"131",
    "addr:postcode":"le67 6jq",
    "addr:street":"High Street",
    "iso:country":"GB",
    "sg:address":"131 High Street",
    "sg:city":"Ibstock",
    "sg:classifiers":[
        {
            "category":"Personal",
            "subcategory":"Beauty Salon",
            "type":"Services"
        },
        {
            "category":"Personal",
            "subcategory":"Barber",
            "type":"Services"
        }
    ],
    "sg:phone":"+44 1530 261479",
    "sg:postcode":"LE67 6JQ",
    "sg:province":"Leicestershire",
    "sg:tags":[
        "unisex",
        "hairdresser"
    ],
    "wof:name":"Hair by Sandra",
    "wof:placetype":"venue"
},
  "geometry": {"coordinates":[-1.401507,52.684723],"type":"Point"}
}