{
  "type": "Feature",
  "properties": {
    "addr:full":"12 Ampthill Road Southampton Hampshire SO15 8LP",
    "addr:housenumber":"12",
    "addr:postcode":"so15 8lp",
    "addr:street":"Ampthill Road",
    "iso:country":"GB",
    "sg:address":"12 Ampthill Road",
    "sg:city":"Southampton",
    "sg:classifiers":[
        {
            "category":"Personal",
            "type":"Services"
        }
    ],
    "sg:postcode":"SO15 8LP",
    "sg:province":"Hampshire",
    "sg:tags":[
        "dressmaker"
    ],
    "wof:name":"Sue Grove Designs",
    "wof:placetype":"venue"
},
  "geometry": {"coordinates":[-1.4336279631,50.9165458679],"type":"Point"}
}