{
  "type": "Feature",
  "properties": {
    "addr:full":"5 Llys Y Nant, Pentre Halkyn Holywell Denbighshire CH8 8LN",
    "addr:housenumber":"5;halkyn",
    "addr:postcode":"ch8 8ln",
    "addr:street":"Llys Y;Pentre",
    "iso:country":"GB",
    "sg:address":"5 Llys Y Nant, Pentre Halkyn",
    "sg:city":"Holywell",
    "sg:classifiers":[
        {
            "category":"Home & Garden",
            "subcategory":"Building Materials",
            "type":"Retail Goods"
        }
    ],
    "sg:phone":"+44 1352 780352",
    "sg:postcode":"CH8 8LN",
    "sg:province":"Denbighshire",
    "sg:tags":[
        "fencing"
    ],
    "wof:name":"A 1 Fencing",
    "wof:placetype":"venue"
},
  "geometry": {"coordinates":[-3.18676,53.227516],"type":"Point"}
}