{
  "type": "Feature",
  "properties": {
    "iso:country":"GB",
    "sg:address":"66 College Road",
    "sg:city":"Harrow",
    "sg:classifiers":[
        {
            "category":"Professional",
            "subcategory":"Business Services",
            "type":"Services"
        },
        {
            "category":"Conference Center",
            "type":"Public Place"
        }
    ],
    "sg:phone":"+44 20 8324 1234",
    "sg:postcode":"HA1 1FD",
    "sg:province":"Greater London",
    "sg:tags":[
        "centre"
    ],
    "wof:name":"Regus-Harrow",
    "wof:placetype":"venue"
},
  "geometry": {"coordinates":[-0.3380460143,51.5802383423],"type":"Point"}
}