{
  "type": "Feature",
  "properties": {
    "addr:full":"Unit 10, Aizlewood Road Sheffield Derbyshire S8 0XY",
    "addr:housenumber":"unit 10",
    "addr:postcode":"s8 0xy",
    "addr:street":"Aizlewood Road",
    "iso:country":"GB",
    "sg:address":"Unit 10, Aizlewood Road",
    "sg:city":"Sheffield",
    "sg:classifiers":[
        {
            "category":"Communications",
            "type":"Services"
        }
    ],
    "sg:postcode":"S8 0XY",
    "sg:province":"Derbyshire",
    "sg:tags":[
        "audio-visual"
    ],
    "wof:name":"Sheffield Video Services",
    "wof:placetype":"venue"
},
  "geometry": {"coordinates":[-1.4784129858,53.3608131409],"type":"Point"}
}