{
  "type": "Feature",
  "properties": {
    "iso:country":"GB",
    "sg:address":"26 Sidmouth Drive",
    "sg:city":"Ruislip",
    "sg:classifiers":[
        {
            "category":"Building & Trades",
            "subcategory":"Plumbing",
            "type":"Services"
        }
    ],
    "sg:postcode":"HA4 0BY",
    "sg:province":"Greater London",
    "sg:tags":[
        "plumber",
        "heating"
    ],
    "wof:name":"DAVID DOWNS & CO,",
    "wof:placetype":"venue"
},
  "geometry": {"coordinates":[-0.40784,51.564869],"type":"Point"}
}