{
  "type": "Feature",
  "properties": {
    "addr:full":"49 St Catherines Rd Grantham Lincolnshire NG31 9DE",
    "addr:housenumber":"49",
    "addr:postcode":"ng31 9de",
    "addr:street":"St Catherines Rd",
    "iso:country":"GB",
    "sg:address":"49 St Catherines Rd",
    "sg:city":"Grantham",
    "sg:classifiers":[
        {
            "category":"Social Services",
            "type":"Services"
        }
    ],
    "sg:phone":"+44 1476 564560",
    "sg:postcode":"NG31 9DE",
    "sg:province":"Lincolnshire",
    "wof:name":"St Catherines Road Adolescent Centre",
    "wof:placetype":"venue"
},
  "geometry": {"coordinates":[-0.6341620088,52.9108467102],"type":"Point"}
}