{
  "type": "Feature",
  "properties": {
    "addr:full":"Unit 17, Stenson Rd Coalville Leicestershire LE67 4JP",
    "addr:housenumber":"unit 17",
    "addr:postcode":"le67 4jp",
    "addr:street":"Stenson Rd",
    "iso:country":"GB",
    "sg:address":"Unit 17, Stenson Rd",
    "sg:city":"Coalville",
    "sg:classifiers":[
        {
            "category":"Communications",
            "type":"Services"
        }
    ],
    "sg:phone":"+44 1530 276570",
    "sg:postcode":"LE67 4JP",
    "sg:province":"Leicestershire",
    "sg:tags":[
        "telecommunication"
    ],
    "wof:name":"GCS Communications",
    "wof:placetype":"venue"
},
  "geometry": {"coordinates":[-1.3622390032,52.7261962891],"type":"Point"}
}