{
  "type": "Feature",
  "properties": {
    "iso:country":"GB",
    "sg:address":"9 Alcester Road",
    "sg:city":"Studley",
    "sg:classifiers":[
        {
            "category":"Real Estate",
            "subcategory":"Real Estate Agent",
            "type":"Services"
        }
    ],
    "sg:phone":"+44 1527 853028",
    "sg:postcode":"B80 7AN",
    "sg:province":"Warwickshire",
    "wof:name":"Nigel Poole McGinn",
    "wof:placetype":"venue"
},
  "geometry": {"coordinates":[-1.894416,52.274109],"type":"Point"}
}