{
  "type": "Feature",
  "properties": {
    "addr:full":"Unit 1 Litchurch Mews, Sir Francis Ley Industrial Derby Derbyshire DE23 8XA",
    "addr:housenumber":"unit 1",
    "addr:postcode":"de23 8xa",
    "addr:street":"Litchurch Mews Sir Francis Ley",
    "iso:country":"GB",
    "sg:address":"Unit 1 Litchurch Mews, Sir Francis Ley Industrial",
    "sg:city":"Derby",
    "sg:classifiers":[
        {
            "category":"Retail",
            "subcategory":"Auto Rental",
            "type":"Services"
        }
    ],
    "sg:phone":"+44 1332 296263",
    "sg:postcode":"DE23 8XA",
    "sg:province":"Derbyshire",
    "sg:tags":[
        "truck",
        "hire",
        "van"
    ],
    "wof:name":"Whitaker Car & Van Hire",
    "wof:placetype":"venue"
},
  "geometry": {"coordinates":[-1.4654400349,52.9053382874],"type":"Point"}
}