{
  "type": "Feature",
  "properties": {
    "iso:country":"GB",
    "sg:address":"7 Octagon Street",
    "sg:city":"Plymouth",
    "sg:classifiers":[
        {
            "category":"Organizations",
            "subcategory":"Membership Organization",
            "type":"Services"
        }
    ],
    "sg:phone":"+44 1752 673401",
    "sg:postcode":"PL1 1TU",
    "sg:province":"Devon",
    "sg:tags":[
        "club"
    ],
    "wof:name":"Octagon Social Club",
    "wof:placetype":"venue"
},
  "geometry": {"coordinates":[-4.1517782211,50.3703842163],"type":"Point"}
}