{
  "type": "Feature",
  "properties": {
    "addr:full":"P O Box 12 Runcorn Cheshire WA7 2DN",
    "addr:housenumber":"box 12",
    "addr:postcode":"wa7 2dn",
    "addr:street":"P O",
    "iso:country":"GB",
    "sg:address":"P O Box 12",
    "sg:city":"Runcorn",
    "sg:classifiers":[
        {
            "category":"Professional",
            "subcategory":"Employment Agencies",
            "type":"Services"
        }
    ],
    "sg:phone":"+44 1928 715151",
    "sg:postcode":"WA7 2DN",
    "sg:province":"Cheshire",
    "sg:tags":[
        "consultant"
    ],
    "wof:name":"Office Of National Statistics",
    "wof:placetype":"venue"
},
  "geometry": {"coordinates":[-2.698875,53.326771],"type":"Point"}
}