{
  "type": "Feature",
  "properties": {
    "iso:country":"GB",
    "sg:address":"113 Alfreton Road, South Normanton",
    "sg:city":"Alfreton",
    "sg:classifiers":[
        {
            "category":"Autos & Motor Vehicles",
            "subcategory":"Automobile Sales",
            "type":"Retail Goods"
        }
    ],
    "sg:postcode":"DE55 2ES",
    "sg:province":"Derbyshire",
    "sg:tags":[
        "car"
    ],
    "wof:name":"Carnfield Motor Co.",
    "wof:placetype":"venue"
},
  "geometry": {"coordinates":[-1.325975,53.099606],"type":"Point"}
}