{
  "type": "Feature",
  "properties": {
    "iso:country":"GB",
    "sg:address":"19 King Street",
    "sg:city":"Richmond",
    "sg:classifiers":[
        {
            "category":"Shopping",
            "subcategory":"Clothing, Apparel, & Fashions",
            "type":"Retail Goods"
        },
        {
            "category":"Professional",
            "subcategory":"Art Services",
            "type":"Services"
        }
    ],
    "sg:postcode":"TW9 1ND",
    "sg:province":"Greater London",
    "sg:tags":[
        "clothing",
        "framing"
    ],
    "wof:name":"Regatta",
    "wof:placetype":"venue"
},
  "geometry": {"coordinates":[-0.306537,51.460007],"type":"Point"}
}