{
  "type": "Feature",
  "properties": {
    "iso:country":"GB",
    "sg:address":"Cross Roads Farm, Eastwell",
    "sg:city":"Melton Mowbray",
    "sg:classifiers":[
        {
            "category":"Food & Beverages",
            "subcategory":"Fruits & Vegetables",
            "type":"Retail Goods"
        },
        {
            "category":"Farming",
            "subcategory":"Farm",
            "type":"Manufacturing & Wholesale Goods"
        }
    ],
    "sg:phone":"+44 1949 860242",
    "sg:postcode":"LE14 4EF",
    "sg:province":"Leicestershire",
    "sg:tags":[
        "mixed",
        "greengrocer",
        "crop"
    ],
    "wof:name":"J H HEWSON & SON",
    "wof:placetype":"venue"
},
  "geometry": {"coordinates":[-0.86147,52.841228],"type":"Point"}
}