{
  "type": "Feature",
  "properties": {
    "iso:country":"GB",
    "sg:address":"237 Cirencester Road, Charlton Kings",
    "sg:city":"Cheltenham",
    "sg:classifiers":[
        {
            "category":"Restaurant",
            "type":"Food & Drink"
        },
        {
            "category":"Community Center",
            "subcategory":"Social",
            "type":"Public Place"
        },
        {
            "category":"Community Center",
            "type":"Public Place"
        }
    ],
    "sg:phone":"+44 1242 529404",
    "sg:postcode":"GL53 8EB",
    "sg:province":"Gloucestershire",
    "sg:tags":[
        "conference",
        "house",
        "activity",
        "room",
        "centre"
    ],
    "wof:name":"Little Owl",
    "wof:placetype":"venue"
},
  "geometry": {"coordinates":[-2.053472,51.876976],"type":"Point"}
}