{
  "type": "Feature",
  "properties": {
    "addr:full":"67 Milton Park, Abingdon Oxfordshire OX14 4RX",
    "addr:housenumber":"67",
    "addr:postcode":"ox14 4rx",
    "addr:street":"Milton Park",
    "iso:country":"GB",
    "sg:address":"67 Milton Park, Abingdon",
    "sg:city":"Oxfordshire",
    "sg:classifiers":[
        {
            "category":"Professional",
            "subcategory":"Computer Services",
            "type":"Services"
        }
    ],
    "sg:postcode":"OX14 4RX",
    "sg:website":"http://www.omprompt.com",
    "wof:name":"OmPrompt",
    "wof:placetype":"venue"
},
  "geometry": {"coordinates":[-1.289082,51.671711],"type":"Point"}
}