{
  "type": "Feature",
  "properties": {
    "iso:country":"GB",
    "sg:address":"1 Fawe Street",
    "sg:city":"London",
    "sg:classifiers":[
        {
            "category":"Manufacturing",
            "subcategory":"Metals",
            "type":"Manufacturing & Wholesale Goods"
        },
        {
            "category":"Arts & Performance",
            "subcategory":"Art Gallery",
            "type":"Entertainment"
        }
    ],
    "sg:phone":"+44 20 7515 8052",
    "sg:postcode":"E14 6PD",
    "sg:province":"Greater London",
    "sg:tags":[
        "foundry"
    ],
    "wof:name":"A B Fine Art Foundry Ltd",
    "wof:placetype":"venue"
},
  "geometry": {"coordinates":[-0.0156890005,51.5172691345],"type":"Point"}
}