{
  "type": "Feature",
  "properties": {
    "addr:full":"65 Kingsnorth Road Ashford Kent TN23 6HZ",
    "addr:housenumber":"65",
    "addr:postcode":"tn23 6hz",
    "addr:street":"Kingsnorth Road",
    "iso:country":"GB",
    "sg:address":"65 Kingsnorth Road",
    "sg:city":"Ashford",
    "sg:classifiers":[
        {
            "category":"Personal",
            "subcategory":"Beauty Salon",
            "type":"Services"
        }
    ],
    "sg:phone":"+44 1233 625450",
    "sg:postcode":"TN23 6HZ",
    "sg:province":"Kent",
    "sg:tags":[
        "unisex",
        "hairdresser"
    ],
    "wof:name":"Banana Split",
    "wof:placetype":"venue"
},
  "geometry": {"coordinates":[0.8628330231,51.1334838867],"type":"Point"}
}