{
  "type": "Feature",
  "properties": {
    "iso:country":"GB",
    "sg:address":"25 Grange Avenue",
    "sg:city":"Warrington",
    "sg:classifiers":[
        {
            "category":"Sports & Exercise",
            "subcategory":"Gym",
            "type":"Entertainment"
        }
    ],
    "sg:phone":"+44 1925 445728",
    "sg:postcode":"WA4 1PN",
    "sg:province":"Cheshire",
    "sg:tags":[
        "fitness",
        "health",
        "centre"
    ],
    "wof:name":"Hard Labour Gym",
    "wof:placetype":"venue"
},
  "geometry": {"coordinates":[-2.566271,53.382195],"type":"Point"}
}