{
  "type": "Feature",
  "properties": {
    "iso:country":"GB",
    "sg:address":"6 Craig Y Don Parade",
    "sg:city":"Llandudno",
    "sg:classifiers":[
        {
            "category":"Travel",
            "subcategory":"Hotels & Motels",
            "type":"Entertainment"
        }
    ],
    "sg:postcode":"LL30 1BG",
    "sg:province":"Conwy",
    "wof:name":"Bromwell Court Hotel",
    "wof:placetype":"venue"
},
  "geometry": {"coordinates":[-3.809819,53.322124],"type":"Point"}
}