{
  "type": "Feature",
  "properties": {
    "addr:full":"12 Humber Close, Durrington Worthing West Sussex BN13 3NW",
    "addr:housenumber":"12",
    "addr:postcode":"bn13 3nw",
    "addr:street":"Humber Close",
    "iso:country":"GB",
    "sg:address":"12 Humber Close, Durrington",
    "sg:city":"Worthing",
    "sg:classifiers":[
        {
            "category":"Professional",
            "subcategory":"Management & Consulting",
            "type":"Services"
        }
    ],
    "sg:postcode":"BN13 3NW",
    "sg:province":"West Sussex",
    "sg:tags":[
        "consultant",
        "business"
    ],
    "wof:name":"Lavender Consulting Ltd",
    "wof:placetype":"venue"
},
  "geometry": {"coordinates":[-0.421588,50.835442],"type":"Point"}
}