{
  "type": "Feature",
  "properties": {
    "iso:country":"GB",
    "sg:address":"Ladbrooke Road",
    "sg:city":"Ashton-under-lyne",
    "sg:classifiers":[
        {
            "category":"Retail",
            "subcategory":"Auto Repair",
            "type":"Services"
        }
    ],
    "sg:phone":"+44 161 339 7724",
    "sg:postcode":"OL6 8PN",
    "sg:province":"Greater Manchester",
    "sg:tags":[
        "modification",
        "garage"
    ],
    "wof:name":"R G Motors",
    "wof:placetype":"venue"
},
  "geometry": {"coordinates":[-2.0907390118,53.4974441528],"type":"Point"}
}