{
  "type": "Feature",
  "properties": {
    "iso:country":"GB",
    "sg:address":"Hillside Cottage, Brandsby St, Crayke",
    "sg:city":"York",
    "sg:classifiers":[
        {
            "category":"Building & Trades",
            "subcategory":"Construction",
            "type":"Services"
        }
    ],
    "sg:phone":"+44 1347 821666",
    "sg:postcode":"YO61 4TB",
    "sg:province":"North Yorkshire",
    "sg:tags":[
        "demolition",
        "contractor"
    ],
    "wof:name":"R.L Moverley",
    "wof:placetype":"venue"
},
  "geometry": {"coordinates":[-1.099554,54.144135],"type":"Point"}
}