{
  "type": "Feature",
  "properties": {
    "iso:country":"GB",
    "sg:address":"Potton Road, Hilton",
    "sg:city":"Huntingdon",
    "sg:classifiers":[
        {
            "category":"Farming",
            "subcategory":"Nursery",
            "type":"Manufacturing & Wholesale Goods"
        },
        {
            "category":"Social Services",
            "subcategory":"Child Care",
            "type":"Services"
        }
    ],
    "sg:phone":"+44 1480 830351",
    "sg:postcode":"PE28 9NG",
    "sg:province":"Bedfordshire",
    "sg:tags":[
        "creche"
    ],
    "wof:name":"Sunshine Day Nursery",
    "wof:placetype":"venue"
},
  "geometry": {"coordinates":[-0.1116520017,52.2806396484],"type":"Point"}
}