{
  "type": "Feature",
  "properties": {
    "addr:full":"14 Barham Avenue, Elstree Borehamwood Hertfordshire WD6 3PN",
    "addr:housenumber":"14",
    "addr:postcode":"wd6 3pn",
    "addr:street":"Barham Avenue",
    "iso:country":"GB",
    "sg:address":"14 Barham Avenue, Elstree",
    "sg:city":"Borehamwood",
    "sg:classifiers":[
        {
            "category":"Professional",
            "subcategory":"Accounting & Tax Preparation",
            "type":"Services"
        }
    ],
    "sg:phone":"+44 20 8953 9035",
    "sg:postcode":"WD6 3PN",
    "sg:province":"Hertfordshire",
    "sg:tags":[
        "accountant"
    ],
    "wof:name":"Stephen Bickler",
    "wof:placetype":"venue"
},
  "geometry": {"coordinates":[-0.286435,51.653458],"type":"Point"}
}