{
  "type": "Feature",
  "properties": {
    "addr:full":"Unit E4 North Caldeen Road, Calder Street Coatbridge North Lanarkshire ML5 4EF",
    "addr:housenumber":"e4",
    "addr:postcode":"ml5 4ef",
    "addr:street":"North Caldeen Road Calder Street",
    "iso:country":"GB",
    "sg:address":"Unit E4 North Caldeen Road, Calder Street",
    "sg:city":"Coatbridge",
    "sg:classifiers":[
        {
            "category":"Professional",
            "subcategory":"Engineering",
            "type":"Services"
        },
        {
            "category":"Building & Trades",
            "subcategory":"Electrical",
            "type":"Services"
        }
    ],
    "sg:phone":"+44 1236 440310",
    "sg:postcode":"ML5 4EF",
    "sg:province":"North Lanarkshire",
    "sg:tags":[
        "consultant",
        "engineer",
        "lighting",
        "contractor"
    ],
    "wof:name":"Parkersell (Lighting & Electrical) Services Ltd.",
    "wof:placetype":"venue"
},
  "geometry": {"coordinates":[-4.012055,55.856117],"type":"Point"}
}