{
  "type": "Feature",
  "properties": {
    "addr:full":"Unit 4 Bayton Way Coventry Warwickshire CV7 9ER",
    "addr:housenumber":"unit 4",
    "addr:postcode":"cv7 9er",
    "addr:street":"Bayton Way",
    "iso:country":"GB",
    "sg:address":"Unit 4 Bayton Way",
    "sg:city":"Coventry",
    "sg:classifiers":[
        {
            "category":"Professional",
            "subcategory":"Engineering",
            "type":"Services"
        }
    ],
    "sg:postcode":"CV7 9ER",
    "sg:province":"Warwickshire",
    "wof:name":"B S Chima Engineering",
    "wof:placetype":"venue"
},
  "geometry": {"coordinates":[-1.470289,52.466],"type":"Point"}
}