{
  "type": "Feature",
  "properties": {
    "iso:country":"GB",
    "sg:address":"Unit 2 Greyhound Park Rd, Greyhound Retail Park",
    "sg:city":"Chester",
    "sg:classifiers":[
        {
            "category":"Shopping",
            "subcategory":"Used Merchandise",
            "type":"Retail Goods"
        }
    ],
    "sg:phone":"+44 1244 390071",
    "sg:postcode":"CH1 4QG",
    "sg:province":"Cheshire",
    "sg:tags":[
        "shop",
        "second-hand"
    ],
    "wof:name":"Allders",
    "wof:placetype":"venue"
},
  "geometry": {"coordinates":[-2.910799,53.198421],"type":"Point"}
}