{
  "type": "Feature",
  "properties": {
    "addr:full":"Unit 37 Imex Business Park, Shobnall Rd Burton On Trent Derbyshire DE14 2AU",
    "addr:housenumber":"unit 37",
    "addr:postcode":"trent derbyshire de14 2au",
    "addr:street":"Imex Business Park Shobnall Rd",
    "iso:country":"GB",
    "sg:address":"Unit 37 Imex Business Park, Shobnall Rd",
    "sg:city":"Burton On Trent",
    "sg:classifiers":[
        {
            "category":"Professional",
            "subcategory":"Computer Services",
            "type":"Services"
        }
    ],
    "sg:phone":"+44 1283 533258",
    "sg:postcode":"DE14 2AU",
    "sg:province":"Derbyshire",
    "sg:tags":[
        "consultant"
    ],
    "wof:name":"Broadgate Software Ltd",
    "wof:placetype":"venue"
},
  "geometry": {"coordinates":[-1.647701025,52.8043518066],"type":"Point"}
}