{
  "type": "Feature",
  "properties": {
    "addr:full":"21 Broad Lane, Mouldgreen Huddersfield West Yorkshire HD5 9BX",
    "addr:housenumber":"21",
    "addr:postcode":"hd5 9bx",
    "addr:street":"Broad Lane;West",
    "iso:country":"GB",
    "sg:address":"21 Broad Lane, Mouldgreen",
    "sg:city":"Huddersfield",
    "sg:classifiers":[
        {
            "category":"Personal",
            "subcategory":"Beauty Salon",
            "type":"Services"
        }
    ],
    "sg:postcode":"HD5 9BX",
    "sg:province":"West Yorkshire",
    "sg:tags":[
        "unisex",
        "hairdresser"
    ],
    "wof:name":"Tangles",
    "wof:placetype":"venue"
},
  "geometry": {"coordinates":[-1.76183,53.645782],"type":"Point"}
}