{
  "type": "Feature",
  "properties": {
    "addr:full":"46 Briggate Brighouse West Yorkshire HD6 1EF",
    "addr:housenumber":"46",
    "addr:postcode":"hd6 1ef",
    "addr:street":"Briggate Brighouse West",
    "iso:country":"GB",
    "sg:address":"46 Briggate",
    "sg:city":"Brighouse",
    "sg:classifiers":[
        {
            "category":"Bars & Pubs",
            "type":"Food & Drink"
        },
        {
            "category":"Travel",
            "subcategory":"Hotels & Motels",
            "type":"Entertainment"
        }
    ],
    "sg:phone":"+44 1484 714816",
    "sg:postcode":"HD6 1EF",
    "sg:province":"West Yorkshire",
    "sg:tags":[
        "pubs",
        "inn"
    ],
    "wof:name":"Black Bull Hotel",
    "wof:placetype":"venue"
},
  "geometry": {"coordinates":[-1.782655,53.701923],"type":"Point"}
}