{
  "type": "Feature",
  "properties": {
    "iso:country":"GB",
    "sg:address":"Financial Services, Debtors, 8 Wellington Sq",
    "sg:city":"Ayr",
    "sg:classifiers":[
        {
            "category":"Government",
            "subcategory":"Office",
            "type":"Public Place"
        }
    ],
    "sg:phone":"+44 1292 612570",
    "sg:postcode":"KA7 1EN",
    "sg:province":"South Ayrshire",
    "sg:tags":[
        "local"
    ],
    "wof:name":"South Ayrshire Council",
    "wof:placetype":"venue"
},
  "geometry": {"coordinates":[-4.63583,55.46167],"type":"Point"}
}