{
  "type": "Feature",
  "properties": {
    "addr:full":"291 Gorton Rd Stockport Cheshire SK5 6LL",
    "addr:housenumber":"291",
    "addr:postcode":"sk5 6ll",
    "addr:street":"Gorton Rd",
    "iso:country":"GB",
    "sg:address":"291 Gorton Rd",
    "sg:city":"Stockport",
    "sg:classifiers":[
        {
            "category":"Professional",
            "subcategory":"Engineering",
            "type":"Services"
        }
    ],
    "sg:phone":"+44 161 442 2618",
    "sg:postcode":"SK5 6LL",
    "sg:province":"Cheshire",
    "sg:tags":[
        "engineer",
        "mechanical"
    ],
    "wof:name":"Wheeler W",
    "wof:placetype":"venue"
},
  "geometry": {"coordinates":[-2.157488,53.445889],"type":"Point"}
}