{
  "type": "Feature",
  "properties": {
    "addr:full":"Bracken House, Charles Street Manchester Greater Manchester M1 7BD",
    "addr:postcode":"m1 7bd",
    "addr:street":"Charles Street",
    "iso:country":"GB",
    "sg:address":"Bracken House, Charles Street",
    "sg:city":"Manchester",
    "sg:classifiers":[
        {
            "category":"Banks & Credit Unions",
            "subcategory":"Financial Services",
            "type":"Services"
        }
    ],
    "sg:phone":"+44 161 276 2415",
    "sg:postcode":"M1 7BD",
    "sg:province":"Greater Manchester",
    "sg:tags":[
        "consultant",
        "finance"
    ],
    "wof:name":"BLEMAIN FINANCE LTD",
    "wof:placetype":"venue"
},
  "geometry": {"coordinates":[-2.236006,53.474346],"type":"Point"}
}