{
  "type": "Feature",
  "properties": {
    "iso:country":"GB",
    "sg:address":"7 Croft Road",
    "sg:city":"Selby",
    "sg:classifiers":[
        {
            "category":"Food & Beverages",
            "subcategory":"Meat & Fish",
            "type":"Retail Goods"
        }
    ],
    "sg:phone":"+44 1757 618069",
    "sg:postcode":"YO8 8JL",
    "sg:province":"East Riding of Yorkshire",
    "sg:tags":[
        "chip"
    ],
    "wof:name":"Camblesforth Fisheries",
    "wof:placetype":"venue"
},
  "geometry": {"coordinates":[-1.0159549713,53.7276573181],"type":"Point"}
}