{
  "type": "Feature",
  "properties": {
    "addr:full":"8 Fore Street Torrington Devon EX38 8HQ",
    "addr:housenumber":"8",
    "addr:postcode":"ex38 8hq",
    "addr:street":"Fore Street",
    "iso:country":"GB",
    "sg:address":"8 Fore Street",
    "sg:city":"Torrington",
    "sg:classifiers":[
        {
            "category":"Shopping",
            "subcategory":"News",
            "type":"Retail Goods"
        }
    ],
    "sg:phone":"+44 1271 324304",
    "sg:postcode":"EX38 8HQ",
    "sg:province":"Devon",
    "sg:tags":[
        "newsagent"
    ],
    "wof:name":"Martins the Newsagent",
    "wof:placetype":"venue"
},
  "geometry": {"coordinates":[-4.142823,50.952202],"type":"Point"}
}