{
  "type": "Feature",
  "properties": {
    "iso:country":"GB",
    "sg:address":"110 Brandon Road, Binley",
    "sg:city":"Coventry",
    "sg:classifiers":[
        {
            "category":"Shopping",
            "subcategory":"Pharmacy",
            "type":"Retail Goods"
        }
    ],
    "sg:phone":"+44 24 7644 9642",
    "sg:postcode":"CV3 2JE",
    "sg:province":"Warwickshire",
    "sg:tags":[
        "pharmacist",
        "chemist"
    ],
    "wof:name":"Dhaliwal Chemist",
    "wof:placetype":"venue"
},
  "geometry": {"coordinates":[-1.442179,52.399448],"type":"Point"}
}