{
  "type": "Feature",
  "properties": {
    "iso:country":"GB",
    "sg:address":"369 Bellegrove Road",
    "sg:city":"Welling",
    "sg:classifiers":[
        {
            "category":"Building & Trades",
            "subcategory":"Construction",
            "type":"Services"
        }
    ],
    "sg:postcode":"DA16 3RL",
    "sg:province":"Kent",
    "sg:tags":[
        "welder"
    ],
    "wof:name":"Rochester Mobile Welding",
    "wof:placetype":"venue"
},
  "geometry": {"coordinates":[0.0851830021,51.4660453796],"type":"Point"}
}