{
  "type": "Feature",
  "properties": {
    "addr:full":"Hartwell Farm, 25 Court Road, Cranfield Bedford Bedfordshire MK43 0DX",
    "addr:housenumber":"25",
    "addr:postcode":"mk43 0dx",
    "addr:street":"Hartwell;Court Road",
    "iso:country":"GB",
    "sg:address":"Hartwell Farm, 25 Court Road, Cranfield",
    "sg:city":"Bedford",
    "sg:classifiers":[
        {
            "category":"Manufacturing",
            "subcategory":"Metals",
            "type":"Manufacturing & Wholesale Goods"
        }
    ],
    "sg:phone":"+44 1234 751188",
    "sg:postcode":"MK43 0DX",
    "sg:province":"Bedfordshire",
    "sg:tags":[
        "product",
        "fabricated"
    ],
    "wof:name":"J R Trolleys Ltd.",
    "wof:placetype":"venue"
},
  "geometry": {"coordinates":[-0.599939,52.072948],"type":"Point"}
}