{
  "type": "Feature",
  "properties": {
    "iso:country":"GB",
    "sg:address":"107 Clive Road",
    "sg:city":"London",
    "sg:classifiers":[
        {
            "category":"Professional",
            "subcategory":"Printing & Photocopies",
            "type":"Services"
        }
    ],
    "sg:phone":"+44 20 8761 7373",
    "sg:postcode":"SE21 8DB",
    "sg:province":"Greater London",
    "sg:tags":[
        "printer"
    ],
    "wof:name":"First Stop Print",
    "wof:placetype":"venue"
},
  "geometry": {"coordinates":[-0.088849,51.440975],"type":"Point"}
}