{
  "type": "Feature",
  "properties": {
    "addr:full":"50 Waddell Street Glasgow Glasgow City G5 0LU",
    "addr:housenumber":"50",
    "addr:postcode":"g5 0lu",
    "addr:street":"Waddell Street",
    "iso:country":"GB",
    "sg:address":"50 Waddell Street",
    "sg:city":"Glasgow",
    "sg:classifiers":[
        {
            "category":"Wholesale",
            "subcategory":"Electrical",
            "type":"Manufacturing & Wholesale Goods"
        }
    ],
    "sg:postcode":"G5 0LU",
    "sg:province":"Glasgow City",
    "sg:tags":[
        "equipment",
        "refrigeration"
    ],
    "wof:name":"M & S Fire Protection (Glasgow) Ltd.",
    "wof:placetype":"venue"
},
  "geometry": {"coordinates":[-4.2439317703,55.8481445312],"type":"Point"}
}