{
  "type": "Feature",
  "properties": {
    "iso:country":"GB",
    "sg:address":"59 Berlin Rd",
    "sg:city":"Hastings",
    "sg:classifiers":[
        {
            "category":"Social Services",
            "subcategory":"Retirement Home",
            "type":"Services"
        }
    ],
    "sg:phone":"+44 1424 432682",
    "sg:postcode":"TN35 5JD",
    "sg:province":"East Sussex",
    "sg:tags":[
        "rest"
    ],
    "wof:name":"Arden House",
    "wof:placetype":"venue"
},
  "geometry": {"coordinates":[0.607435,50.8675],"type":"Point"}
}