{
  "type": "Feature",
  "properties": {
    "addr:full":"9 Denton Road, Canton Cardiff Cardiff CF5 1PD",
    "addr:housenumber":"9",
    "addr:postcode":"cf5 1pd",
    "addr:street":"Denton Road",
    "iso:country":"GB",
    "sg:address":"9 Denton Road, Canton",
    "sg:city":"Cardiff",
    "sg:classifiers":[
        {
            "category":"Communications",
            "type":"Services"
        }
    ],
    "sg:phone":"+44 29 2034 1830",
    "sg:postcode":"CF5 1PD",
    "sg:province":"Cardiff",
    "sg:tags":[
        "audio-visual"
    ],
    "wof:name":"Neil Harris",
    "wof:placetype":"venue"
},
  "geometry": {"coordinates":[-3.203004,51.480007],"type":"Point"}
}