{
  "type": "Feature",
  "properties": {
    "iso:country":"GB",
    "sg:address":"Front Street, Braco",
    "sg:city":"Dunblane",
    "sg:classifiers":[
        {
            "category":"Food & Beverages",
            "subcategory":"Groceries & Convenience Stores",
            "type":"Retail Goods"
        }
    ],
    "sg:postcode":"FK15 9QN",
    "sg:province":"Perth and Kinross",
    "wof:name":"The Braco Shop",
    "wof:placetype":"venue"
},
  "geometry": {"coordinates":[-3.878739,56.26535],"type":"Point"}
}