{
  "type": "Feature",
  "properties": {
    "addr:full":"Windmill Bank, Wombourne Wolverhampton Shropshire WV5 9JD",
    "addr:postcode":"wv5 9jd",
    "iso:country":"GB",
    "sg:address":"Windmill Bank, Wombourne",
    "sg:city":"Wolverhampton",
    "sg:classifiers":[
        {
            "category":"Food & Beverages",
            "subcategory":"Groceries & Convenience Stores",
            "type":"Retail Goods"
        }
    ],
    "sg:phone":"+44 1902 892848",
    "sg:postcode":"WV5 9JD",
    "sg:province":"Shropshire",
    "wof:name":"Quills Midlands Ltd",
    "wof:placetype":"venue"
},
  "geometry": {"coordinates":[-2.1873390675,52.5368499756],"type":"Point"}
}