{
  "type": "Feature",
  "properties": {
    "iso:country":"GB",
    "sg:address":"75 Broadway",
    "sg:city":"Doncaster",
    "sg:classifiers":[
        {
            "category":"Fast Food",
            "type":"Food & Drink"
        }
    ],
    "sg:phone":"+44 1302 843307",
    "sg:postcode":"DN7 4HA",
    "sg:province":"South Yorkshire",
    "sg:tags":[
        "away",
        "take"
    ],
    "wof:name":"Broadway Chinese Diner",
    "wof:placetype":"venue"
},
  "geometry": {"coordinates":[-1.019479,53.580811],"type":"Point"}
}