{
  "type": "Feature",
  "properties": {
    "iso:country":"GB",
    "sg:address":"119 Parker Drive",
    "sg:city":"Leicester",
    "sg:classifiers":[
        {
            "category":"Shopping",
            "subcategory":"Luggage & Leather Goods",
            "type":"Retail Goods"
        }
    ],
    "sg:phone":"+44 116 235 0419",
    "sg:postcode":"LE4 0JP",
    "sg:province":"Leicestershire",
    "sg:tags":[
        "mnfr",
        "cane",
        "basketware"
    ],
    "wof:name":"Kingsway Cane Furniture Ltd.",
    "wof:placetype":"venue"
},
  "geometry": {"coordinates":[-1.143771,52.654907],"type":"Point"}
}