{
  "type": "Feature",
  "properties": {
    "addr:full":"3 Whitehall London Greater London SW1A 2DD",
    "addr:housenumber":"3",
    "addr:postcode":"sw1a 2dd",
    "addr:street":"Whitehall",
    "iso:country":"GB",
    "sg:address":"3 Whitehall",
    "sg:city":"London",
    "sg:classifiers":[
        {
            "category":"Personal",
            "type":"Services"
        },
        {
            "category":"Shopping",
            "subcategory":"Gifts & Souvenirs",
            "type":"Retail Goods"
        }
    ],
    "sg:phone":"+44 20 7930 4826",
    "sg:postcode":"SW1A 2DD",
    "sg:province":"Greater London",
    "sg:tags":[
        "giftware"
    ],
    "wof:name":"Lambert Souvenirs Ltd",
    "wof:placetype":"venue"
},
  "geometry": {"coordinates":[-0.1273220032,51.5071258545],"type":"Point"}
}