{
  "type": "Feature",
  "properties": {
    "addr:full":"17 Claremont Cres Southampton Hampshire SO15 4GR",
    "addr:housenumber":"17",
    "addr:postcode":"so15 4gr",
    "addr:street":"Claremont Cres",
    "iso:country":"GB",
    "sg:address":"17 Claremont Cres",
    "sg:city":"Southampton",
    "sg:classifiers":[
        {
            "category":"Building & Trades",
            "subcategory":"Construction",
            "type":"Services"
        }
    ],
    "sg:phone":"+44 23 8077 2966",
    "sg:postcode":"SO15 4GR",
    "sg:province":"Hampshire",
    "sg:tags":[
        "builder"
    ],
    "wof:name":"R P Contractors & Consultants",
    "wof:placetype":"venue"
},
  "geometry": {"coordinates":[-1.4420150518,50.9170799255],"type":"Point"}
}