{
  "type": "Feature",
  "properties": {
    "addr:full":"Rear Of 180 Addington Rd South Croydon Surrey CR2 8LB",
    "addr:housenumber":"180",
    "addr:postcode":"cr2 8lb",
    "addr:street":"Addington Rd",
    "iso:country":"GB",
    "sg:address":"Rear Of 180 Addington Rd",
    "sg:city":"South Croydon",
    "sg:classifiers":[
        {
            "category":"Retail",
            "subcategory":"Auto Repair",
            "type":"Services"
        }
    ],
    "sg:postcode":"CR2 8LB",
    "sg:province":"Surrey",
    "sg:tags":[
        "modification",
        "garage"
    ],
    "wof:name":"Pride & Joy Auto's",
    "wof:placetype":"venue"
},
  "geometry": {"coordinates":[-0.0977640003,51.3545150757],"type":"Point"}
}