{
  "type": "Feature",
  "properties": {
    "addr:full":"Unit 4 Cleeve House, Lambourne Crescent Cardiff Cardiff CF14 5GZ",
    "addr:housenumber":"unit 4 cleeve house",
    "addr:postcode":"cf14 5gz",
    "addr:street":"Lambourne Crescent",
    "iso:country":"GB",
    "sg:address":"Unit 4 Cleeve House, Lambourne Crescent",
    "sg:city":"Cardiff",
    "sg:classifiers":[
        {
            "category":"Banks & Credit Unions",
            "subcategory":"Bank",
            "type":"Services"
        }
    ],
    "sg:phone":"+44 29 2022 5621",
    "sg:postcode":"CF14 5GZ",
    "sg:province":"Cardiff",
    "wof:name":"Girobank",
    "wof:placetype":"venue"
},
  "geometry": {"coordinates":[-3.191978,51.522346],"type":"Point"}
}