{
  "type": "Feature",
  "properties": {
    "iso:country":"GB",
    "sg:address":"Wyndam Park, Wedglen Industrial Estate",
    "sg:city":"Midhurst",
    "sg:classifiers":[
        {
            "category":"Building & Trades",
            "subcategory":"Equipment Rental",
            "type":"Services"
        }
    ],
    "sg:phone":"+44 1730 814867",
    "sg:postcode":"GU29 9RE",
    "sg:province":"West Sussex",
    "sg:tags":[
        "hire",
        "centre"
    ],
    "wof:name":"Holme Hill Hire",
    "wof:placetype":"venue"
},
  "geometry": {"coordinates":[-0.74058,50.984913],"type":"Point"}
}