{
  "type": "Feature",
  "properties": {
    "addr:full":"Blackwater Close, Fairview Industrial Estate, Manor Way Rainham Essex RM13 8UA",
    "addr:housenumber":"estate",
    "addr:postcode":"rm13 8ua",
    "addr:street":"Blackwater Close;Manor Way",
    "iso:country":"GB",
    "sg:address":"Blackwater Close, Fairview Industrial Estate, Manor Way",
    "sg:city":"Rainham",
    "sg:classifiers":[
        {
            "category":"Freight",
            "type":"Transportation"
        }
    ],
    "sg:phone":"+44 1708 524311",
    "sg:postcode":"RM13 8UA",
    "sg:province":"Essex",
    "sg:tags":[
        "haulage",
        "road"
    ],
    "wof:name":"Forest Trucking (U K) Ltd.",
    "wof:placetype":"venue"
},
  "geometry": {"coordinates":[0.1752710044,51.5155334473],"type":"Point"}
}