{
  "type": "Feature",
  "properties": {
    "addr:full":"Woolley Farm, Hyde Mill Lane Stafford Shropshire ST19 9DJ",
    "addr:postcode":"st19 9dj",
    "addr:street":"Hyde Mill Lane",
    "iso:country":"GB",
    "sg:address":"Woolley Farm, Hyde Mill Lane",
    "sg:city":"Stafford",
    "sg:classifiers":[
        {
            "category":"Farming",
            "subcategory":"Livestock Farm",
            "type":"Manufacturing & Wholesale Goods"
        }
    ],
    "sg:postcode":"ST19 9DJ",
    "sg:province":"Shropshire",
    "sg:tags":[
        "others"
    ],
    "wof:name":"T L White",
    "wof:placetype":"venue"
},
  "geometry": {"coordinates":[-2.1819899082,52.6698493958],"type":"Point"}
}