{
  "type": "Feature",
  "properties": {
    "addr:full":"14 Kensington Sq London Greater London W8 5HH",
    "addr:housenumber":"14",
    "addr:postcode":"w8 5hh",
    "addr:street":"Kensington Sq",
    "iso:country":"GB",
    "sg:address":"14 Kensington Sq",
    "sg:city":"London",
    "sg:classifiers":[
        {
            "category":"Wholesale",
            "subcategory":"Chemicals & Plastics",
            "type":"Manufacturing & Wholesale Goods"
        }
    ],
    "sg:phone":"+44 20 7468 2424",
    "sg:postcode":"W8 5HH",
    "sg:province":"Greater London",
    "sg:tags":[
        "product",
        "allied"
    ],
    "wof:name":"Ipsen International Ltd",
    "wof:placetype":"venue"
},
  "geometry": {"coordinates":[-0.190075,51.500988],"type":"Point"}
}