{
  "type": "Feature",
  "properties": {
    "addr:full":"Spaldington Airfield, Howden Goole East Riding of Yorkshire DN14 7NG",
    "addr:postcode":"dn14 7ng",
    "iso:country":"GB",
    "sg:address":"Spaldington Airfield, Howden",
    "sg:city":"Goole",
    "sg:classifiers":[
        {
            "category":"Home & Garden",
            "subcategory":"Garden Supply",
            "type":"Retail Goods"
        }
    ],
    "sg:phone":"+44 1430 431511",
    "sg:postcode":"DN14 7NG",
    "sg:province":"East Riding of Yorkshire",
    "sg:tags":[
        "fertiliser"
    ],
    "wof:name":"Contract Fertiliser & Storage Ltd.",
    "wof:placetype":"venue"
},
  "geometry": {"coordinates":[-0.8610560298,53.7476654053],"type":"Point"}
}