{
  "type": "Feature",
  "properties": {
    "addr:full":"Studio 248, 37 Store St Bloomsbury Greater London WC1E 7BS",
    "addr:housenumber":"37",
    "addr:postcode":"wc1e 7bs",
    "addr:street":"Store St",
    "iso:country":"GB",
    "sg:address":"Studio 248, 37 Store St",
    "sg:city":"Bloomsbury",
    "sg:classifiers":[
        {
            "category":"Communications",
            "type":"Services"
        }
    ],
    "sg:phone":"+44 20 7272 2212",
    "sg:postcode":"WC1E 7BS",
    "sg:province":"Greater London",
    "sg:tags":[
        "audio-visual"
    ],
    "wof:name":"Good Morning Good Afternoon TV Productions",
    "wof:placetype":"venue"
},
  "geometry": {"coordinates":[-0.1312000006,51.5197792053],"type":"Point"}
}