{
  "type": "Feature",
  "properties": {
    "addr:full":"Unit 1 Wested Farm, Eynsford Road, Crockenhill Swanley Kent BR8 8EJ",
    "addr:housenumber":"unit 1 wested farm",
    "addr:postcode":"br8 8ej",
    "addr:street":"Eynsford Road",
    "iso:country":"GB",
    "sg:address":"Unit 1 Wested Farm, Eynsford Road, Crockenhill",
    "sg:city":"Swanley",
    "sg:classifiers":[
        {
            "category":"Home & Garden",
            "subcategory":"Hardware",
            "type":"Retail Goods"
        }
    ],
    "sg:postcode":"BR8 8EJ",
    "sg:province":"Kent",
    "sg:tags":[
        "lawnmowers",
        "machinery"
    ],
    "wof:name":"R R Reynolds & Son",
    "wof:placetype":"venue"
},
  "geometry": {"coordinates":[0.18087,51.380329],"type":"Point"}
}