{
  "type": "Feature",
  "properties": {
    "iso:country":"GB",
    "sg:address":"North Street",
    "sg:city":"Glenrothes",
    "sg:classifiers":[
        {
            "category":"Retail",
            "subcategory":"Veterinary Services",
            "type":"Services"
        }
    ],
    "sg:phone":"+44 1592 753231",
    "sg:postcode":"KY7 5NA",
    "sg:province":"Fife",
    "sg:tags":[
        "surgeon"
    ],
    "wof:name":"Kingdom Veterinary Clinic",
    "wof:placetype":"venue"
},
  "geometry": {"coordinates":[-3.168152,56.197159],"type":"Point"}
}