{
  "type": "Feature",
  "properties": {
    "addr:full":"Stonelea, Stenness Stromness Orkney Islands KW16 3JX",
    "addr:postcode":"kw16 3jx",
    "iso:country":"GB",
    "sg:address":"Stonelea, Stenness",
    "sg:city":"Stromness",
    "sg:classifiers":[
        {
            "category":"Professional",
            "subcategory":"Engineering",
            "type":"Services"
        }
    ],
    "sg:phone":"+44 1856 851342",
    "sg:postcode":"KW16 3JX",
    "sg:province":"Orkney Islands",
    "wof:name":"Linklater Engineering",
    "wof:placetype":"venue"
},
  "geometry": {"coordinates":[-3.2977590561,58.9634857178],"type":"Point"}
}