{
  "type": "Feature",
  "properties": {
    "iso:country":"GB",
    "sg:address":"High St",
    "sg:city":"Clacton On Sea",
    "sg:classifiers":[
        {
            "category":"Recreation",
            "subcategory":"Fishing",
            "type":"Entertainment"
        }
    ],
    "sg:phone":"+44 1255 860343",
    "sg:postcode":"CO16 0DY",
    "sg:province":"Essex",
    "sg:tags":[
        "angling"
    ],
    "wof:name":"Tackle Up",
    "wof:placetype":"venue"
},
  "geometry": {"coordinates":[1.15792,51.859978],"type":"Point"}
}