{
  "type": "Feature",
  "properties": {
    "iso:country":"GB",
    "sg:address":"Po Box 57, Huyton, Knowsley",
    "sg:city":"Prescot",
    "sg:classifiers":[
        {
            "category":"Organizations",
            "subcategory":"Community Association",
            "type":"Services"
        },
        {
            "category":"Organizations",
            "subcategory":"Non-profit Organization",
            "type":"Services"
        }
    ],
    "sg:phone":"+44 151 480 8873",
    "sg:postcode":"L36 0YX",
    "sg:province":"Merseyside",
    "sg:tags":[
        "associations",
        "voluntary",
        "organisation",
        "co-operatives",
        "societies",
        "trust",
        "housing",
        "charity"
    ],
    "wof:name":"KNOWSLEY DISABILITY CONCERN",
    "wof:placetype":"venue"
},
  "geometry": {"coordinates":[-2.82942,53.401611],"type":"Point"}
}