{
  "type": "Feature",
  "properties": {
    "addr:full":"54 Wyeverne Road, Cathays Cardiff Cardiff CF24 4BH",
    "addr:housenumber":"54",
    "addr:postcode":"cf24 4bh",
    "addr:street":"Wyeverne Road",
    "iso:country":"GB",
    "sg:address":"54 Wyeverne Road, Cathays",
    "sg:city":"Cardiff",
    "sg:classifiers":[
        {
            "category":"Organizations",
            "subcategory":"Community Association",
            "type":"Services"
        },
        {
            "category":"Organizations",
            "subcategory":"Membership Organization",
            "type":"Services"
        }
    ],
    "sg:phone":"+44 29 2022 0902",
    "sg:postcode":"CF24 4BH",
    "sg:province":"Cardiff",
    "sg:tags":[
        "club",
        "social"
    ],
    "wof:name":"Cathays Conservative Club",
    "wof:placetype":"venue"
},
  "geometry": {"coordinates":[-3.1770670414,51.4906768799],"type":"Point"}
}