{
  "type": "Feature",
  "properties": {
    "iso:country":"GB",
    "sg:address":"Pictureville",
    "sg:city":"Bradford",
    "sg:classifiers":[
        {
            "category":"Cinema",
            "subcategory":"Movie Theater",
            "type":"Entertainment"
        }
    ],
    "sg:phone":"+44 1274 732277",
    "sg:postcode":"BD1 1NQ",
    "sg:province":"West Yorkshire",
    "wof:name":"Pictureville Cinema",
    "wof:placetype":"venue"
},
  "geometry": {"coordinates":[-1.756149,53.791069],"type":"Point"}
}