{
  "type": "Feature",
  "properties": {
    "addr:full":"23 Main Street, Barton Under Needwood Burton-on-trent Derbyshire DE13 8AA",
    "addr:housenumber":"23",
    "addr:postcode":"de13 8aa",
    "addr:street":"Main Street",
    "iso:country":"GB",
    "sg:address":"23 Main Street, Barton Under Needwood",
    "sg:city":"Burton-on-trent",
    "sg:classifiers":[
        {
            "category":"Home & Garden",
            "subcategory":"Home Furnishings",
            "type":"Retail Goods"
        }
    ],
    "sg:postcode":"DE13 8AA",
    "sg:province":"Derbyshire",
    "sg:tags":[
        "blind",
        "curtain",
        "fitting"
    ],
    "wof:name":"The Curtain Works",
    "wof:placetype":"venue"
},
  "geometry": {"coordinates":[-1.722785,52.764389],"type":"Point"}
}