{
  "type": "Feature",
  "properties": {
    "iso:country":"GB",
    "sg:address":"Builyeon Road South",
    "sg:city":"South Queensferry",
    "sg:classifiers":[
        {
            "category":"Fast Food",
            "type":"Food & Drink"
        },
        {
            "category":"Restaurant",
            "type":"Food & Drink"
        }
    ],
    "sg:phone":"+44 131 331 5981",
    "sg:postcode":"EH30 9YJ",
    "sg:province":"City of Edinburgh",
    "sg:tags":[
        "away",
        "-",
        "american",
        "take"
    ],
    "wof:name":"McDonald's Restaurants Ltd",
    "wof:placetype":"venue"
},
  "geometry": {"coordinates":[-3.411349,55.984486],"type":"Point"}
}