{
  "type": "Feature",
  "properties": {
    "iso:country":"GB",
    "sg:address":"25 High Street",
    "sg:city":"Llandovery",
    "sg:classifiers":[
        {
            "category":"Landmark",
            "subcategory":"Tourist Attraction",
            "type":"Public Place"
        }
    ],
    "sg:postcode":"SA20 0PU",
    "sg:province":"Carmarthenshire",
    "sg:tags":[
        "interest"
    ],
    "wof:name":"Towy Vale Hamstery",
    "wof:placetype":"venue"
},
  "geometry": {"coordinates":[-3.794074,51.993961],"type":"Point"}
}