{
  "type": "Feature",
  "properties": {
    "iso:country":"GB",
    "sg:address":"523 Bearwood Road",
    "sg:city":"Smethwick",
    "sg:classifiers":[
        {
            "category":"Home & Garden",
            "subcategory":"Household Appliances",
            "type":"Retail Goods"
        },
        {
            "category":"Communications",
            "type":"Services"
        }
    ],
    "sg:phone":"+44 121 429 1161",
    "sg:postcode":"B66 4BE",
    "sg:province":"West Midlands",
    "sg:tags":[
        "tv",
        "video",
        "domestic",
        "sales",
        "radio"
    ],
    "wof:name":"N T C",
    "wof:placetype":"venue"
},
  "geometry": {"coordinates":[-1.969507,52.476109],"type":"Point"}
}