{
  "type": "Feature",
  "properties": {
    "addr:full":"70 Davies Rd, West Bridgeford Nottingham Nottinghamshire NG2 5JA",
    "addr:housenumber":"70",
    "addr:postcode":"ng2 5ja",
    "addr:street":"Davies Rd West",
    "iso:country":"GB",
    "sg:address":"70 Davies Rd, West Bridgeford",
    "sg:city":"Nottingham",
    "sg:classifiers":[
        {
            "category":"Shopping",
            "type":"Retail Goods"
        }
    ],
    "sg:phone":"+44 115 923 2020",
    "sg:postcode":"NG2 5JA",
    "sg:province":"Nottinghamshire",
    "sg:tags":[
        "scientific",
        "apparatus"
    ],
    "wof:name":"Histological Equipment Ltd",
    "wof:placetype":"venue"
},
  "geometry": {"coordinates":[-1.118859,52.931011],"type":"Point"}
}