{
  "type": "Feature",
  "properties": {
    "iso:country":"GB",
    "sg:address":"9 Lochmore Close, Hinckley",
    "sg:city":"Leicester",
    "sg:classifiers":[
        {
            "category":"Building & Trades",
            "subcategory":"Construction",
            "type":"Services"
        }
    ],
    "sg:phone":"+44 1455 610543",
    "sg:postcode":"LE10 0TY",
    "sg:province":"Leicestershire",
    "sg:tags":[
        "roofing"
    ],
    "wof:name":"G & L Roofing Contractors",
    "wof:placetype":"venue"
},
  "geometry": {"coordinates":[-1.3954399824,52.5408706665],"type":"Point"}
}