{
  "type": "Feature",
  "properties": {
    "iso:country":"GB",
    "sg:address":"45 Questor",
    "sg:city":"Dartford",
    "sg:classifiers":[
        {
            "category":"Manufacturing",
            "subcategory":"Metals",
            "type":"Manufacturing & Wholesale Goods"
        }
    ],
    "sg:phone":"+44 20 8853 4233",
    "sg:postcode":"DA1 1JG",
    "sg:province":"Kent",
    "sg:tags":[
        "die-casting"
    ],
    "wof:name":"Powatool Repairs",
    "wof:placetype":"venue"
},
  "geometry": {"coordinates":[0.2241069973,51.4412918091],"type":"Point"}
}