{
  "type": "Feature",
  "properties": {
    "addr:full":"46-48 Church Gate Leicester Leicestershire LE1 4AJ",
    "addr:housenumber":"46-48",
    "addr:postcode":"le1 4aj",
    "addr:street":"Church Gate",
    "iso:country":"GB",
    "sg:address":"46-48 Church Gate",
    "sg:city":"Leicester",
    "sg:classifiers":[
        {
            "category":"Restaurant",
            "type":"Food & Drink"
        }
    ],
    "sg:phone":"+44 116 262 7752",
    "sg:postcode":"LE1 4AJ",
    "sg:province":"Leicestershire",
    "wof:name":"Swiss Cottage Restaurants Ltd",
    "wof:placetype":"venue"
},
  "geometry": {"coordinates":[-1.134509,52.637398],"type":"Point"}
}