{
  "type": "Feature",
  "properties": {
    "iso:country":"GB",
    "sg:address":"Horton Hill, Horton",
    "sg:city":"Bristol",
    "sg:classifiers":[
        {
            "category":"Building & Trades",
            "subcategory":"Cleaning & Sanitation",
            "type":"Services"
        }
    ],
    "sg:phone":"+44 1454 325335",
    "sg:postcode":"BS37 6QP",
    "sg:province":"Gloucestershire",
    "sg:tags":[
        "toilet",
        "portable"
    ],
    "wof:name":"Convenience Co. Central",
    "wof:placetype":"venue"
},
  "geometry": {"coordinates":[-2.353535,51.559292],"type":"Point"}
}