{
  "type": "Feature",
  "properties": {
    "addr:full":"Unit 1, Burnham Close Burnley Lancashire BB11 4AJ",
    "addr:housenumber":"unit 1",
    "addr:postcode":"bb11 4aj",
    "addr:street":"Burnham Close",
    "iso:country":"GB",
    "sg:address":"Unit 1, Burnham Close",
    "sg:city":"Burnley",
    "sg:classifiers":[
        {
            "category":"Wholesale",
            "subcategory":"Electrical",
            "type":"Manufacturing & Wholesale Goods"
        },
        {
            "category":"Shopping",
            "subcategory":"Computers & Home Electronics",
            "type":"Retail Goods"
        }
    ],
    "sg:phone":"+44 1282 448888",
    "sg:postcode":"BB11 4AJ",
    "sg:province":"Lancashire",
    "sg:tags":[
        "wholesaler"
    ],
    "wof:name":"Power Saver Electrical Supplies Ltd.",
    "wof:placetype":"venue"
},
  "geometry": {"coordinates":[-2.258234024,53.7882347107],"type":"Point"}
}