{
  "type": "Feature",
  "properties": {
    "iso:country":"GB",
    "sg:address":"34 Portland Rd",
    "sg:city":"Walsall",
    "sg:classifiers":[
        {
            "category":"Shopping",
            "subcategory":"Pharmacy",
            "type":"Retail Goods"
        }
    ],
    "sg:phone":"+44 1922 452054",
    "sg:postcode":"WS9 8PZ",
    "sg:province":"Staffordshire",
    "sg:tags":[
        "pharmacist",
        "chemist"
    ],
    "wof:name":"Lloyds Chemist",
    "wof:placetype":"venue"
},
  "geometry": {"coordinates":[-1.919829,52.602524],"type":"Point"}
}