{
  "type": "Feature",
  "properties": {
    "addr:full":"Orchard Court Orchard Lane Bristol City of Bristol BS1 5DS",
    "addr:postcode":"bs1 5ds",
    "addr:street":"Orchard Court Orchard Lane",
    "iso:country":"GB",
    "sg:address":"Orchard Court Orchard Lane",
    "sg:city":"Bristol",
    "sg:classifiers":[
        {
            "category":"Professional",
            "subcategory":"Lawyer & Legal Services",
            "type":"Services"
        }
    ],
    "sg:postcode":"BS1 5DS",
    "sg:province":"City of Bristol",
    "sg:tags":[
        "solicitor"
    ],
    "wof:name":"Convey Direct Ltd",
    "wof:placetype":"venue"
},
  "geometry": {"coordinates":[-2.599109,51.453606],"type":"Point"}
}