{
  "type": "Feature",
  "properties": {
    "addr:full":"Union Road Off Roway Lane Oldbury West Midlands B69 3EN",
    "addr:postcode":"b69 3en",
    "addr:street":"Union Road Off Roway Lane",
    "iso:country":"GB",
    "sg:address":"Union Road Off Roway Lane",
    "sg:city":"Oldbury",
    "sg:classifiers":[
        {
            "category":"Utilities",
            "subcategory":"Fuel Oil & Lpg",
            "type":"Services"
        }
    ],
    "sg:phone":"+44 121 552 9229",
    "sg:postcode":"B69 3EN",
    "sg:province":"West Midlands",
    "sg:tags":[
        "distributor"
    ],
    "wof:name":"Kuwait Petroleum (G B) Ltd.",
    "wof:placetype":"venue"
},
  "geometry": {"coordinates":[-2.025362,52.513588],"type":"Point"}
}