{
  "type": "Feature",
  "properties": {
    "addr:full":"354 Uxbridge Road, Shepherds Bush London Greater London W12 7LL",
    "addr:housenumber":"354",
    "addr:postcode":"w12 7ll",
    "addr:street":"Uxbridge Road",
    "iso:country":"GB",
    "sg:address":"354 Uxbridge Road, Shepherds Bush",
    "sg:city":"London",
    "sg:classifiers":[
        {
            "category":"Food & Beverages",
            "subcategory":"Specialty",
            "type":"Retail Goods"
        }
    ],
    "sg:phone":"+44 20 8743 5665",
    "sg:postcode":"W12 7LL",
    "sg:province":"Greater London",
    "sg:tags":[
        "product",
        "health"
    ],
    "wof:name":"The Nature Health Centre",
    "wof:placetype":"venue"
},
  "geometry": {"coordinates":[-0.233661,51.506603],"type":"Point"}
}