{
  "type": "Feature",
  "properties": {
    "addr:full":"63 Charlotte Road London Greater London EC2A 3PE",
    "addr:housenumber":"63",
    "addr:postcode":"ec2a 3pe",
    "addr:street":"Charlotte Road",
    "iso:country":"GB",
    "sg:address":"63 Charlotte Road",
    "sg:city":"London",
    "sg:classifiers":[
        {
            "category":"Bars & Pubs",
            "type":"Food & Drink"
        }
    ],
    "sg:phone":"+44 20 7739 5245",
    "sg:postcode":"EC2A 3PE",
    "sg:province":"Greater London",
    "sg:tags":[
        "pubs",
        "inn"
    ],
    "wof:name":"Bricklayers Arms",
    "wof:placetype":"venue"
},
  "geometry": {"coordinates":[-0.081087,51.526173],"type":"Point"}
}