{
  "type": "Feature",
  "properties": {
    "iso:country":"GB",
    "sg:address":"250-252 Hipswell Highway",
    "sg:city":"Coventry",
    "sg:classifiers":[
        {
            "category":"Shopping",
            "subcategory":"News",
            "type":"Retail Goods"
        }
    ],
    "sg:phone":"+44 24 7645 3523",
    "sg:postcode":"CV2 5FS",
    "sg:province":"Warwickshire",
    "sg:tags":[
        "newsagent"
    ],
    "wof:name":"G T News",
    "wof:placetype":"venue"
},
  "geometry": {"coordinates":[-1.4597940445,52.4092941284],"type":"Point"}
}