{
  "type": "Feature",
  "properties": {
    "addr:full":"57 West St Sittingbourne Kent ME10 1AN",
    "addr:housenumber":"57",
    "addr:postcode":"me10 1an",
    "addr:street":"West St",
    "iso:country":"GB",
    "sg:address":"57 West St",
    "sg:city":"Sittingbourne",
    "sg:classifiers":[
        {
            "category":"Manufacturing",
            "subcategory":"Tools & Machinery",
            "type":"Manufacturing & Wholesale Goods"
        }
    ],
    "sg:postcode":"ME10 1AN",
    "sg:province":"Kent",
    "sg:tags":[
        "society",
        "friendly"
    ],
    "wof:name":"Troubridge,K P,",
    "wof:placetype":"venue"
},
  "geometry": {"coordinates":[0.729564,51.341003],"type":"Point"}
}