{
  "type": "Feature",
  "properties": {
    "addr:full":"9 Bourchier Avenue Braintree Essex CM7 9FY",
    "addr:housenumber":"9",
    "addr:postcode":"cm7 9fy",
    "addr:street":"Bourchier Avenue",
    "iso:country":"GB",
    "sg:address":"9 Bourchier Avenue",
    "sg:city":"Braintree",
    "sg:classifiers":[
        {
            "category":"Personal",
            "subcategory":"Tanning Parlor",
            "type":"Services"
        }
    ],
    "sg:postcode":"CM7 9FY",
    "sg:province":"Essex",
    "sg:tags":[
        "sunbeds"
    ],
    "wof:name":"Supertan Sunbed Hire",
    "wof:placetype":"venue"
},
  "geometry": {"coordinates":[0.582603991,51.8872451782],"type":"Point"}
}