{
  "type": "Feature",
  "properties": {
    "iso:country":"GB",
    "sg:address":"6 Dial Lane",
    "sg:city":"Ipswich",
    "sg:classifiers":[
        {
            "category":"Personal",
            "subcategory":"Beauty Salon",
            "type":"Services"
        },
        {
            "category":"Personal",
            "subcategory":"Barber",
            "type":"Services"
        }
    ],
    "sg:phone":"+44 1473 255600",
    "sg:postcode":"IP1 1DL",
    "sg:province":"Suffolk",
    "sg:tags":[
        "unisex",
        "hairdresser"
    ],
    "wof:name":"Hairmasters",
    "wof:placetype":"venue"
},
  "geometry": {"coordinates":[1.154416,52.057529],"type":"Point"}
}