{
  "type": "Feature",
  "properties": {
    "iso:country":"GB",
    "sg:address":"65 Brunswick Rd",
    "sg:city":"Edinburgh",
    "sg:classifiers":[
        {
            "category":"Professional",
            "subcategory":"Art Services",
            "type":"Services"
        }
    ],
    "sg:phone":"+44 131 652 1331",
    "sg:postcode":"EH7 5PD",
    "sg:province":"City of Edinburgh",
    "sg:tags":[
        "photographer"
    ],
    "wof:name":"John Chadwick Photography",
    "wof:placetype":"venue"
},
  "geometry": {"coordinates":[-3.1737949848,55.9574584961],"type":"Point"}
}