{
  "type": "Feature",
  "properties": {
    "addr:full":"Wardens Office, Kiln Court, North Drive Beaconsfield Buckinghamshire HP9 1UH",
    "addr:postcode":"hp9 1uh",
    "addr:street":"Kiln Court North Drive",
    "iso:country":"GB",
    "sg:address":"Wardens Office, Kiln Court, North Drive",
    "sg:city":"Beaconsfield",
    "sg:classifiers":[
        {
            "category":"Social Services",
            "subcategory":"Adult Care",
            "type":"Services"
        },
        {
            "category":"Organizations",
            "subcategory":"Community Association",
            "type":"Services"
        }
    ],
    "sg:phone":"+44 1494 671624",
    "sg:postcode":"HP9 1UH",
    "sg:province":"Buckinghamshire",
    "sg:tags":[
        "co-operatives",
        "society",
        "housing",
        "trust",
        "sheltered"
    ],
    "wof:name":"Beacon Housing Association",
    "wof:placetype":"venue"
},
  "geometry": {"coordinates":[-0.6649489999,51.5997810364],"type":"Point"}
}