{
  "type": "Feature",
  "properties": {
    "addr:full":"34 Ealing Broadway Centre, The Broadway London Greater London W5 5JY",
    "addr:housenumber":"34",
    "addr:postcode":"w5 5jy",
    "addr:street":"Ealing;The Broadway",
    "iso:country":"GB",
    "sg:address":"34 Ealing Broadway Centre, The Broadway",
    "sg:city":"London",
    "sg:classifiers":[
        {
            "category":"Shopping",
            "subcategory":"Shoes",
            "type":"Retail Goods"
        }
    ],
    "sg:phone":"+44 20 8567 1662",
    "sg:postcode":"W5 5JY",
    "sg:province":"Greater London",
    "wof:name":"Timpsons",
    "wof:placetype":"venue"
},
  "geometry": {"coordinates":[-0.3070600033,51.5037689209],"type":"Point"}
}