{
  "type": "Feature",
  "properties": {
    "addr:full":"207 Allensbank Road, Heath Cardiff Cardiff CF14 3QZ",
    "addr:housenumber":"207",
    "addr:postcode":"cf14 3qz",
    "addr:street":"Allensbank Road",
    "iso:country":"GB",
    "sg:address":"207 Allensbank Road, Heath",
    "sg:city":"Cardiff",
    "sg:classifiers":[
        {
            "category":"Building & Trades",
            "subcategory":"Plumbing",
            "type":"Services"
        }
    ],
    "sg:phone":"+44 29 2076 4279",
    "sg:postcode":"CF14 3QZ",
    "sg:province":"Cardiff",
    "sg:tags":[
        "central",
        "heating"
    ],
    "wof:name":"John Lorford Central Heating & Plumbing",
    "wof:placetype":"venue"
},
  "geometry": {"coordinates":[-3.1832129955,51.507522583],"type":"Point"}
}