{
  "type": "Feature",
  "properties": {
    "addr:full":"Technology Management Centre, Marsh Lane Preston Lancashire PR1 8UD",
    "addr:postcode":"pr1 8ud",
    "addr:street":"Marsh Lane",
    "iso:country":"GB",
    "sg:address":"Technology Management Centre, Marsh Lane",
    "sg:city":"Preston",
    "sg:classifiers":[
        {
            "category":"Government",
            "subcategory":"Office",
            "type":"Public Place"
        }
    ],
    "sg:phone":"+44 1772 558111",
    "sg:postcode":"PR1 8UD",
    "sg:province":"Lancashire",
    "sg:tags":[
        "development",
        "agency"
    ],
    "wof:name":"Preston Partnership",
    "wof:placetype":"venue"
},
  "geometry": {"coordinates":[-2.7057290077,53.7579612732],"type":"Point"}
}