{
  "type": "Feature",
  "properties": {
    "addr:full":"10 Viburnum View, Abbeymead Gloucester Gloucestershire GL4 5US",
    "addr:housenumber":"10",
    "addr:postcode":"gl4 5us",
    "addr:street":"Viburnum View",
    "iso:country":"GB",
    "sg:address":"10 Viburnum View, Abbeymead",
    "sg:city":"Gloucester",
    "sg:classifiers":[
        {
            "category":"Organizations",
            "subcategory":"Non-profit Organization",
            "type":"Services"
        }
    ],
    "sg:phone":"+44 1452 612535",
    "sg:postcode":"GL4 5US",
    "sg:province":"Gloucestershire",
    "sg:tags":[
        "organisation",
        "voluntary",
        "charity"
    ],
    "wof:name":"The Children's Society",
    "wof:placetype":"venue"
},
  "geometry": {"coordinates":[-2.19708395,51.8440742493],"type":"Point"}
}