{
  "type": "Feature",
  "properties": {
    "addr:full":"32 Fisher Street Carlisle Cumbria CA3 8RH",
    "addr:housenumber":"32",
    "addr:postcode":"ca3 8rh",
    "addr:street":"Fisher Street",
    "iso:country":"GB",
    "sg:address":"32 Fisher Street",
    "sg:city":"Carlisle",
    "sg:classifiers":[
        {
            "category":"Fast Food",
            "type":"Food & Drink"
        }
    ],
    "sg:phone":"+44 1228 514550",
    "sg:postcode":"CA3 8RH",
    "sg:province":"Cumbria",
    "sg:tags":[
        "away",
        "meal",
        "outlet",
        "take"
    ],
    "wof:name":"The Sandwich Place",
    "wof:placetype":"venue"
},
  "geometry": {"coordinates":[-2.936682,54.895412],"type":"Point"}
}