{
  "type": "Feature",
  "properties": {
    "iso:country":"GB",
    "sg:address":"45 Knightsbridge",
    "sg:city":"London",
    "sg:classifiers":[
        {
            "category":"Cinema",
            "subcategory":"Movie Theater",
            "type":"Entertainment"
        }
    ],
    "sg:phone":"+44 20 7369 1723",
    "sg:postcode":"SW1X 7NL",
    "sg:province":"Greater London",
    "wof:name":"Minema Cinema",
    "wof:placetype":"venue"
},
  "geometry": {"coordinates":[-0.155106,51.502346],"type":"Point"}
}