{
  "type": "Feature",
  "properties": {
    "addr:full":"Nightingales Corner Amersham Buckinghamshire HP7 9PY",
    "addr:postcode":"hp7 9py",
    "addr:street":"Amersham",
    "iso:country":"GB",
    "sg:address":"Nightingales Corner",
    "sg:city":"Amersham",
    "sg:classifiers":[
        {
            "category":"Shopping",
            "subcategory":"Baby Store",
            "type":"Retail Goods"
        }
    ],
    "sg:phone":"+44 1494 764200",
    "sg:postcode":"HP7 9PY",
    "sg:province":"Buckinghamshire",
    "sg:tags":[
        "babywear",
        "childrens"
    ],
    "wof:name":"Peter Pans Parlour",
    "wof:placetype":"venue"
},
  "geometry": {"coordinates":[-0.5652300119,51.6665992737],"type":"Point"}
}