{
  "type": "Feature",
  "properties": {
    "iso:country":"GB",
    "sg:address":"Village Hall",
    "sg:city":"Sandbach",
    "sg:classifiers":[
        {
            "category":"Government",
            "subcategory":"City Hall",
            "type":"Public Place"
        }
    ],
    "sg:phone":"+44 1270 763964",
    "sg:postcode":"CW11 1RG",
    "sg:province":"Cheshire",
    "wof:name":"Bradwall Village Hall Committee",
    "wof:placetype":"venue"
},
  "geometry": {"coordinates":[-2.3636479378,53.1422080994],"type":"Point"}
}