{
  "type": "Feature",
  "properties": {
    "addr:full":"14 Clydesdale Gardens Bognor Regis West Sussex PO22 9BE",
    "addr:housenumber":"14",
    "addr:postcode":"po22 9be",
    "addr:street":"Clydesdale Gardens",
    "iso:country":"GB",
    "sg:address":"14 Clydesdale Gardens",
    "sg:city":"Bognor Regis",
    "sg:classifiers":[
        {
            "category":"Building & Trades",
            "subcategory":"Construction",
            "type":"Services"
        }
    ],
    "sg:phone":"+44 1243 866729",
    "sg:postcode":"PO22 9BE",
    "sg:province":"West Sussex",
    "sg:tags":[
        "glazier"
    ],
    "wof:name":"In-dec",
    "wof:placetype":"venue"
},
  "geometry": {"coordinates":[-0.688853,50.80275],"type":"Point"}
}