{
  "type": "Feature",
  "properties": {
    "addr:full":"32 Heol Llanelli, Trinsaraa Kidwelly Carmarthenshire SA17 4AA",
    "addr:housenumber":"32",
    "addr:postcode":"sa17 4aa",
    "addr:street":"Heol Llanelli Trinsaraa",
    "iso:country":"GB",
    "sg:address":"32 Heol Llanelli, Trinsaraa",
    "sg:city":"Kidwelly",
    "sg:classifiers":[
        {
            "category":"Fast Food",
            "type":"Food & Drink"
        },
        {
            "category":"Food & Beverages",
            "subcategory":"Meat & Fish",
            "type":"Retail Goods"
        }
    ],
    "sg:phone":"+44 1554 811098",
    "sg:postcode":"SA17 4AA",
    "sg:province":"Carmarthenshire",
    "sg:tags":[
        "shop",
        "chip"
    ],
    "wof:name":"The Village Fish & Chip Bar",
    "wof:placetype":"venue"
},
  "geometry": {"coordinates":[-4.241487,51.719658],"type":"Point"}
}