{
  "type": "Feature",
  "properties": {
    "addr:full":"31 King Street Saffron Walden Cambridgeshire CB10 1EU",
    "addr:housenumber":"31",
    "addr:postcode":"cb10 1eu",
    "addr:street":"King Street",
    "iso:country":"GB",
    "sg:address":"31 King Street",
    "sg:city":"Saffron Walden",
    "sg:classifiers":[
        {
            "category":"Home & Garden",
            "subcategory":"Furniture",
            "type":"Retail Goods"
        }
    ],
    "sg:phone":"+44 1799 523076",
    "sg:postcode":"CB10 1EU",
    "sg:province":"Cambridgeshire",
    "sg:tags":[
        "outlet"
    ],
    "wof:name":"Glasswells Ltd.",
    "wof:placetype":"venue"
},
  "geometry": {"coordinates":[0.2395170033,52.0230751038],"type":"Point"}
}