{
  "type": "Feature",
  "properties": {
    "iso:country":"GB",
    "sg:address":"St. Aldates Chambers, St. Aldates",
    "sg:city":"Oxford",
    "sg:classifiers":[
        {
            "category":"Professional",
            "subcategory":"Management & Consulting",
            "type":"Services"
        }
    ],
    "sg:phone":"+44 1865 202886",
    "sg:postcode":"OX1 1DS",
    "sg:province":"Oxfordshire",
    "sg:tags":[
        "consultant",
        "energy",
        "conservation"
    ],
    "wof:name":"Energy Efficiency Advice Centre Charitable Trust",
    "wof:placetype":"venue"
},
  "geometry": {"coordinates":[-1.256499052,51.7472496033],"type":"Point"}
}