{
  "type": "Feature",
  "properties": {
    "iso:country":"GB",
    "sg:address":"Canterbury Rd, Wingham",
    "sg:city":"Canterbury",
    "sg:classifiers":[
        {
            "category":"Home & Garden",
            "subcategory":"Garden Supply",
            "type":"Retail Goods"
        }
    ],
    "sg:postcode":"CT3 1NH",
    "sg:province":"Kent",
    "sg:tags":[
        "nursery",
        "centre"
    ],
    "wof:name":"Fairview Nurseries",
    "wof:placetype":"venue"
},
  "geometry": {"coordinates":[1.2149389982,51.2724761963],"type":"Point"}
}