{
  "type": "Feature",
  "properties": {
    "addr:full":"Handley Lodge Farm, Handley Lane Chesterfield Derbyshire S45 9AT",
    "addr:housenumber":"handley",
    "addr:postcode":"s45 9at",
    "addr:street":"Lodge Farm Handley Lane",
    "iso:country":"GB",
    "sg:address":"Handley Lodge Farm, Handley Lane",
    "sg:city":"Chesterfield",
    "sg:classifiers":[
        {
            "category":"Banks & Credit Unions",
            "subcategory":"Investment Brokerage",
            "type":"Services"
        }
    ],
    "sg:postcode":"S45 9AT",
    "sg:province":"Derbyshire",
    "sg:tags":[
        "contractor"
    ],
    "wof:name":"Friswell Agricultural Contractors",
    "wof:placetype":"venue"
},
  "geometry": {"coordinates":[-1.4362900257,53.1530189514],"type":"Point"}
}