{
  "type": "Feature",
  "properties": {
    "addr:full":"7 The Parade, Castle Drive Dinas Powys The Vale of Glamorgan CF64 4NR",
    "addr:housenumber":"7",
    "addr:postcode":"cf64 4nr",
    "addr:street":"The Parade Castle Drive;Vale",
    "iso:country":"GB",
    "sg:address":"7 The Parade, Castle Drive",
    "sg:city":"Dinas Powys",
    "sg:classifiers":[
        {
            "category":"Food & Beverages",
            "subcategory":"Fruits & Vegetables",
            "type":"Retail Goods"
        }
    ],
    "sg:phone":"+44 29 2051 2477",
    "sg:postcode":"CF64 4NR",
    "sg:province":"The Vale of Glamorgan",
    "sg:tags":[
        "greengrocer"
    ],
    "wof:name":"F Brown",
    "wof:placetype":"venue"
},
  "geometry": {"coordinates":[-3.2198190689,51.4330291748],"type":"Point"}
}