{
  "type": "Feature",
  "properties": {
    "addr:full":"Thomas Way Industrial Estate Glastonbury Somerset BA6 9LU",
    "addr:housenumber":"estate",
    "addr:postcode":"ba6 9lu",
    "addr:street":"Thomas Way Industrial",
    "iso:country":"GB",
    "sg:address":"Thomas Way Industrial Estate",
    "sg:city":"Glastonbury",
    "sg:classifiers":[
        {
            "category":"Wholesale",
            "subcategory":"Scrap",
            "type":"Manufacturing & Wholesale Goods"
        }
    ],
    "sg:phone":"+44 1458 835131",
    "sg:postcode":"BA6 9LU",
    "sg:province":"Somerset",
    "sg:tags":[
        "waste",
        "metal"
    ],
    "wof:name":"J C Thomas & Sons",
    "wof:placetype":"venue"
},
  "geometry": {"coordinates":[-2.7170090675,51.1475906372],"type":"Point"}
}