{
  "type": "Feature",
  "properties": {
    "iso:country":"GB",
    "sg:address":"4 Webbons Way, Heol Y Gors",
    "sg:city":"Swansea",
    "sg:classifiers":[
        {
            "category":"Shopping",
            "subcategory":"Computers & Home Electronics",
            "type":"Retail Goods"
        }
    ],
    "sg:phone":"+44 1792 580228",
    "sg:postcode":"SA1 6RY",
    "sg:province":"Neath Port Talbot",
    "sg:tags":[
        "equipment",
        "radio"
    ],
    "wof:name":"Circuit Circuit Communications Ltd",
    "wof:placetype":"venue"
},
  "geometry": {"coordinates":[-3.9713490009,51.6331214905],"type":"Point"}
}