{
  "type": "Feature",
  "properties": {
    "addr:full":"Park Lane, High Street, Otford Sevenoaks Kent TN15 6NA",
    "addr:postcode":"tn15 6na",
    "addr:street":"Park Lane High Street",
    "iso:country":"GB",
    "sg:address":"Park Lane, High Street, Otford",
    "sg:city":"Sevenoaks",
    "sg:classifiers":[
        {
            "category":"Professional",
            "subcategory":"Printing & Photocopies",
            "type":"Services"
        }
    ],
    "sg:phone":"+44 1959 522606",
    "sg:postcode":"TN15 6NA",
    "sg:province":"Kent",
    "sg:tags":[
        "printer"
    ],
    "wof:name":"Longmore Press Ltd.",
    "wof:placetype":"venue"
},
  "geometry": {"coordinates":[0.227927,51.303177],"type":"Point"}
}