{
  "type": "Feature",
  "properties": {
    "iso:country":"GB",
    "sg:address":"29 The Precinct, Winchester Road, Chandler's Ford",
    "sg:city":"Eastleigh",
    "sg:classifiers":[
        {
            "category":"Travel",
            "subcategory":"Travel Agent",
            "type":"Entertainment"
        }
    ],
    "sg:phone":"+44 23 8025 5545",
    "sg:postcode":"SO53 2GA",
    "sg:province":"Hampshire",
    "wof:name":"Holidays Business Travel",
    "wof:placetype":"venue"
},
  "geometry": {"coordinates":[-1.38231,50.982632],"type":"Point"}
}