{
  "type": "Feature",
  "properties": {
    "addr:full":"Swale Reach, Wraik Hill Whitstable Kent CT5 3BY",
    "addr:postcode":"ct5 3by",
    "addr:street":"Hill",
    "iso:country":"GB",
    "sg:address":"Swale Reach, Wraik Hill",
    "sg:city":"Whitstable",
    "sg:classifiers":[
        {
            "category":"Airport",
            "subcategory":"General Aviation",
            "type":"Transportation"
        }
    ],
    "sg:phone":"+44 1227 262426",
    "sg:postcode":"CT5 3BY",
    "sg:province":"Kent",
    "sg:tags":[
        "consultant"
    ],
    "sg:website":"http://www.netcomuk.co.uk",
    "wof:name":"Airspace Services Ltd",
    "wof:placetype":"venue"
},
  "geometry": {"coordinates":[1.0264060497,51.362247467],"type":"Point"}
}