{
  "type": "Feature",
  "properties": {
    "addr:full":"Firgrove Hill Farnham Surrey GU9 8LQ",
    "addr:postcode":"gu9 8lq",
    "addr:street":"Firgrove Hill Farnham",
    "iso:country":"GB",
    "sg:address":"Firgrove Hill",
    "sg:city":"Farnham",
    "sg:classifiers":[
        {
            "category":"Travel",
            "subcategory":"Hotels & Motels",
            "type":"Entertainment"
        }
    ],
    "sg:postcode":"GU9 8LQ",
    "sg:province":"Surrey",
    "wof:name":"Stafford House Hotel",
    "wof:placetype":"venue"
},
  "geometry": {"coordinates":[-0.796279,51.209229],"type":"Point"}
}