{
  "type": "Feature",
  "properties": {
    "addr:full":"1 Wyeverne Rd Cardiff Cardiff CF2 4BG",
    "addr:housenumber":"1",
    "addr:postcode":"cf2 4bg",
    "addr:street":"Wyeverne Rd",
    "iso:country":"GB",
    "sg:address":"1 Wyeverne Rd",
    "sg:city":"Cardiff",
    "sg:classifiers":[
        {
            "category":"Food & Beverages",
            "subcategory":"Meat & Fish",
            "type":"Retail Goods"
        }
    ],
    "sg:phone":"+44 29 2034 4775",
    "sg:postcode":"CF2 4BG",
    "sg:province":"Cardiff",
    "sg:tags":[
        "chip"
    ],
    "wof:name":"Yung's Fish Bar",
    "wof:placetype":"venue"
},
  "geometry": {"coordinates":[-3.1744298935,51.4894752502],"type":"Point"}
}