{
  "type": "Feature",
  "properties": {
    "addr:full":"Tanton Hall Farm, Stokesley Middlesbrough North Yorkshire TS9 5JT",
    "addr:postcode":"ts9 5jt",
    "iso:country":"GB",
    "sg:address":"Tanton Hall Farm, Stokesley",
    "sg:city":"Middlesbrough",
    "sg:classifiers":[
        {
            "category":"Arts & Performance",
            "subcategory":"Art Gallery",
            "type":"Entertainment"
        }
    ],
    "sg:phone":"+44 1642 711371",
    "sg:postcode":"TS9 5JT",
    "sg:province":"North Yorkshire",
    "wof:name":"The Byre Yard",
    "wof:placetype":"venue"
},
  "geometry": {"coordinates":[-1.1887899637,54.470703125],"type":"Point"}
}