{
  "type": "Feature",
  "properties": {
    "addr:full":"Harlington Road Uxbridge Buckinghamshire UB8 3HE",
    "addr:postcode":"ub8 3he",
    "addr:street":"Harlington Road",
    "iso:country":"GB",
    "sg:address":"Harlington Road",
    "sg:city":"Uxbridge",
    "sg:classifiers":[
        {
            "category":"Autos & Motor Vehicles",
            "subcategory":"Fuel & Gas Station",
            "type":"Retail Goods"
        }
    ],
    "sg:postcode":"UB8 3HE",
    "sg:province":"Buckinghamshire",
    "sg:tags":[
        "petrol",
        "filling"
    ],
    "wof:name":"Reliance Service Station",
    "wof:placetype":"venue"
},
  "geometry": {"coordinates":[-0.456736,51.5341],"type":"Point"}
}