{
  "type": "Feature",
  "properties": {
    "addr:full":"98 Abbey Barn Road High Wycombe Buckinghamshire HP11 1RW",
    "addr:housenumber":"98",
    "addr:postcode":"hp11 1rw",
    "addr:street":"Abbey Barn Road",
    "iso:country":"GB",
    "sg:address":"98 Abbey Barn Road",
    "sg:city":"High Wycombe",
    "sg:classifiers":[
        {
            "category":"Building & Trades",
            "subcategory":"Construction",
            "type":"Services"
        }
    ],
    "sg:phone":"+44 1494 449049",
    "sg:postcode":"HP11 1RW",
    "sg:province":"Buckinghamshire",
    "sg:tags":[
        "builder"
    ],
    "wof:name":"J R Audry Building Contractors",
    "wof:placetype":"venue"
},
  "geometry": {"coordinates":[-0.722186029,51.6174736023],"type":"Point"}
}