{
  "type": "Feature",
  "properties": {
    "addr:full":"22-24 Lord Street Gainsborough Lincolnshire DN21 2DB",
    "addr:housenumber":"22-24",
    "addr:postcode":"dn21 2db",
    "addr:street":"Lord Street",
    "iso:country":"GB",
    "sg:address":"22-24 Lord Street",
    "sg:city":"Gainsborough",
    "sg:classifiers":[
        {
            "category":"Food & Beverages",
            "subcategory":"Meat & Fish",
            "type":"Retail Goods"
        }
    ],
    "sg:phone":"+44 1427 612016",
    "sg:postcode":"DN21 2DB",
    "sg:province":"Lincolnshire",
    "sg:tags":[
        "butcher"
    ],
    "wof:name":"R & W Surfleet",
    "wof:placetype":"venue"
},
  "geometry": {"coordinates":[-0.777051,53.399696],"type":"Point"}
}