{
  "type": "Feature",
  "properties": {
    "addr:full":"29 Standalane, Stewarton Kilmarnock East Ayrshire KA3 3AW",
    "addr:housenumber":"29",
    "addr:postcode":"ka3 3aw",
    "addr:street":"Standalane Stewarton",
    "iso:country":"GB",
    "sg:address":"29 Standalane, Stewarton",
    "sg:city":"Kilmarnock",
    "sg:classifiers":[
        {
            "category":"Building & Trades",
            "subcategory":"Plumbing",
            "type":"Services"
        }
    ],
    "sg:postcode":"KA3 3AW",
    "sg:province":"East Ayrshire",
    "sg:tags":[
        "heating"
    ],
    "wof:name":"Homecare (Gas Services) Ltd.",
    "wof:placetype":"venue"
},
  "geometry": {"coordinates":[-4.520728,55.680164],"type":"Point"}
}