{
  "type": "Feature",
  "properties": {
    "addr:full":"46 Locksley Drive Ferndown Dorset BH22 8JZ",
    "addr:housenumber":"46",
    "addr:postcode":"bh22 8jz",
    "addr:street":"Locksley Drive",
    "iso:country":"GB",
    "sg:address":"46 Locksley Drive",
    "sg:city":"Ferndown",
    "sg:classifiers":[
        {
            "category":"Education",
            "subcategory":"Special Training",
            "type":"Public Place"
        }
    ],
    "sg:postcode":"BH22 8JZ",
    "sg:province":"Dorset",
    "sg:tags":[
        "product",
        "centre"
    ],
    "wof:name":"A W Computer Training",
    "wof:placetype":"venue"
},
  "geometry": {"coordinates":[-1.8991539478,50.7919082642],"type":"Point"}
}