{
  "type": "Feature",
  "properties": {
    "addr:full":"29 Chesham Road Bury Lancashire BL9 6LY",
    "addr:housenumber":"29",
    "addr:postcode":"bl9 6ly",
    "addr:street":"Chesham Road",
    "iso:country":"GB",
    "sg:address":"29 Chesham Road",
    "sg:city":"Bury",
    "sg:classifiers":[
        {
            "category":"Shopping",
            "subcategory":"Crafts & Fabrics",
            "type":"Retail Goods"
        }
    ],
    "sg:phone":"+44 161 797 4234",
    "sg:postcode":"BL9 6LY",
    "sg:province":"Lancashire",
    "sg:tags":[
        "shop",
        "needlecraft",
        "wool"
    ],
    "wof:name":"Baimar Supplies",
    "wof:placetype":"venue"
},
  "geometry": {"coordinates":[-2.2876119614,53.6028060913],"type":"Point"}
}