{
  "type": "Feature",
  "properties": {
    "addr:full":"41a Wood St Ashby De La Zouch Derbyshire LE65 1EL",
    "addr:housenumber":"41a",
    "addr:postcode":"le65 1el",
    "addr:street":"Wood St",
    "iso:country":"GB",
    "sg:address":"41a Wood St",
    "sg:city":"Ashby De La Zouch",
    "sg:classifiers":[
        {
            "category":"Manufacturing",
            "subcategory":"Metals",
            "type":"Manufacturing & Wholesale Goods"
        }
    ],
    "sg:phone":"+44 1530 411066",
    "sg:postcode":"LE65 1EL",
    "sg:province":"Derbyshire",
    "sg:tags":[
        "blacksmith",
        "forgemasters"
    ],
    "wof:name":"G L Budworth",
    "wof:placetype":"venue"
},
  "geometry": {"coordinates":[-1.465446949,52.7489128113],"type":"Point"}
}