{
  "type": "Feature",
  "properties": {
    "addr:full":"7 Terrace Walk Bath Bath and North East Somerset BA1 1LN",
    "addr:housenumber":"7",
    "addr:postcode":"ba1 1ln",
    "addr:street":"Terrace Walk",
    "iso:country":"GB",
    "sg:address":"7 Terrace Walk",
    "sg:city":"Bath",
    "sg:classifiers":[
        {
            "category":"Cinema",
            "subcategory":"Movie Rental",
            "type":"Entertainment"
        }
    ],
    "sg:phone":"+44 1225 462033",
    "sg:postcode":"BA1 1LN",
    "sg:province":"Bath and North East Somerset",
    "sg:tags":[
        "video",
        "library"
    ],
    "wof:name":"On the Video Front",
    "wof:placetype":"venue"
},
  "geometry": {"coordinates":[-2.3577680588,51.3813438416],"type":"Point"}
}