{
  "type": "Feature",
  "properties": {
    "addr:full":"72 Boutport Street Barnstaple Devon EX31 1SR",
    "addr:housenumber":"72",
    "addr:postcode":"ex31 1sr",
    "addr:street":"Boutport Street",
    "iso:country":"GB",
    "sg:address":"72 Boutport Street",
    "sg:city":"Barnstaple",
    "sg:classifiers":[
        {
            "category":"Shopping",
            "subcategory":"Discount & Variety Stores",
            "type":"Retail Goods"
        }
    ],
    "sg:phone":"+44 1271 377386",
    "sg:postcode":"EX31 1SR",
    "sg:province":"Devon",
    "sg:tags":[
        "shop",
        "model"
    ],
    "wof:name":"North Devon Models",
    "wof:placetype":"venue"
},
  "geometry": {"coordinates":[-4.058848,51.078918],"type":"Point"}
}