{
  "type": "Feature",
  "properties": {
    "addr:full":"Potash Terminal Middlesbrough North Yorkshire TS6 6UD",
    "addr:postcode":"ts6 6ud",
    "iso:country":"GB",
    "sg:address":"Potash Terminal",
    "sg:city":"Middlesbrough",
    "sg:classifiers":[
        {
            "category":"Freight",
            "type":"Transportation"
        }
    ],
    "sg:phone":"+44 1642 456611",
    "sg:postcode":"TS6 6UD",
    "sg:province":"North Yorkshire",
    "sg:tags":[
        "overseas",
        "shipping",
        "removal"
    ],
    "wof:name":"Louis Dreyfus Trading Ltd.",
    "wof:placetype":"venue"
},
  "geometry": {"coordinates":[-1.139860034,54.6017799377],"type":"Point"}
}