{
  "type": "Feature",
  "properties": {
    "addr:full":"156 Cumberland Street Macclesfield Cheshire SK10 1BP",
    "addr:housenumber":"156",
    "addr:postcode":"sk10 1bp",
    "addr:street":"Cumberland Street",
    "iso:country":"GB",
    "sg:address":"156 Cumberland Street",
    "sg:city":"Macclesfield",
    "sg:classifiers":[
        {
            "category":"Health Services",
            "subcategory":"Dentist",
            "type":"Services"
        }
    ],
    "sg:phone":"+44 1625 431063",
    "sg:postcode":"SK10 1BP",
    "sg:province":"Cheshire",
    "wof:name":"S R Smith",
    "wof:placetype":"venue"
},
  "geometry": {"coordinates":[-2.134299,53.262314],"type":"Point"}
}