{
  "type": "Feature",
  "properties": {
    "iso:country":"GB",
    "sg:address":"Bencewell Farm, Oakley Road",
    "sg:city":"Bromley",
    "sg:classifiers":[
        {
            "category":"Building & Trades",
            "subcategory":"Landscaping Services",
            "type":"Services"
        }
    ],
    "sg:phone":"+44 20 8462 9479",
    "sg:postcode":"BR2 8HG",
    "sg:province":"Kent",
    "sg:tags":[
        "pond",
        "aquarium"
    ],
    "wof:name":"World of Koi",
    "wof:placetype":"venue"
},
  "geometry": {"coordinates":[0.03911,51.374161],"type":"Point"}
}