{
  "type": "Feature",
  "properties": {
    "addr:full":"766 Uxbridge Rd Hayes Greater London UB4 0RU",
    "addr:housenumber":"766",
    "addr:postcode":"ub4 0ru",
    "addr:street":"Uxbridge Rd",
    "iso:country":"GB",
    "sg:address":"766 Uxbridge Rd",
    "sg:city":"Hayes",
    "sg:classifiers":[
        {
            "category":"Shopping",
            "subcategory":"Mobile Phones",
            "type":"Retail Goods"
        }
    ],
    "sg:phone":"+44 20 8573 6696",
    "sg:postcode":"UB4 0RU",
    "sg:province":"Greater London",
    "wof:name":"Moco",
    "wof:placetype":"venue"
},
  "geometry": {"coordinates":[-0.414832,51.520538],"type":"Point"}
}