{
  "type": "Feature",
  "properties": {
    "iso:country":"GB",
    "sg:address":"90 Town Street, Armley",
    "sg:city":"Leeds",
    "sg:classifiers":[
        {
            "category":"Shopping",
            "subcategory":"Computers & Home Electronics",
            "type":"Retail Goods"
        }
    ],
    "sg:phone":"+44 113 263 4451",
    "sg:postcode":"LS12 3AA",
    "sg:province":"West Yorkshire",
    "sg:tags":[
        "aerial",
        "television",
        "radio"
    ],
    "wof:name":"Dave Electrical Ltd.",
    "wof:placetype":"venue"
},
  "geometry": {"coordinates":[-1.5933740139,53.7966918945],"type":"Point"}
}