{
  "type": "Feature",
  "properties": {
    "addr:full":"166 Albert Street Dundee Dundee City DD4 6QW",
    "addr:housenumber":"166",
    "addr:postcode":"dd4 6qw",
    "addr:street":"Albert Street",
    "iso:country":"GB",
    "sg:address":"166 Albert Street",
    "sg:city":"Dundee",
    "sg:classifiers":[
        {
            "category":"Personal",
            "subcategory":"Beauty Salon",
            "type":"Services"
        }
    ],
    "sg:phone":"+44 1382 450696",
    "sg:postcode":"DD4 6QW",
    "sg:province":"Dundee City",
    "sg:tags":[
        "unisex",
        "hairdresser"
    ],
    "wof:name":"Strands",
    "wof:placetype":"venue"
},
  "geometry": {"coordinates":[-2.95674,56.472454],"type":"Point"}
}