{
  "type": "Feature",
  "properties": {
    "addr:full":"705-707 Oldham Rd Rochdale Lancashire OL16 4RH",
    "addr:housenumber":"705-707",
    "addr:postcode":"ol16 4rh",
    "addr:street":"Oldham Rd",
    "iso:country":"GB",
    "sg:address":"705-707 Oldham Rd",
    "sg:city":"Rochdale",
    "sg:classifiers":[
        {
            "category":"Food & Beverages",
            "subcategory":"Liquor & Beverages",
            "type":"Retail Goods"
        }
    ],
    "sg:phone":"+44 1706 645947",
    "sg:postcode":"OL16 4RH",
    "sg:province":"Lancashire",
    "sg:tags":[
        "beer",
        "spirit",
        "wines"
    ],
    "wof:name":"Tina's Off Licence & Grocers",
    "wof:placetype":"venue"
},
  "geometry": {"coordinates":[-2.1435210705,53.5938072205],"type":"Point"}
}