{
  "type": "Feature",
  "properties": {
    "iso:country":"GB",
    "sg:address":"Lydbrook Valley Springs, Central Lydbrook",
    "sg:city":"Lydbrook",
    "sg:classifiers":[
        {
            "category":"Professional",
            "subcategory":"Engineering",
            "type":"Services"
        }
    ],
    "sg:phone":"+44 1594 860789",
    "sg:postcode":"GL17 9PP",
    "sg:province":"Gloucestershire",
    "sg:tags":[
        "contractor",
        "electrical",
        "engineer"
    ],
    "wof:name":"Robert Harry Morgan Electrical Services Ltd.",
    "wof:placetype":"venue"
},
  "geometry": {"coordinates":[-2.580163,51.839935],"type":"Point"}
}