{
  "type": "Feature",
  "properties": {
    "addr:full":"88 Renfrew Road Paisley Renfrewshire PA3 4BJ",
    "addr:housenumber":"88",
    "addr:postcode":"pa3 4bj",
    "addr:street":"Renfrew Road",
    "iso:country":"GB",
    "sg:address":"88 Renfrew Road",
    "sg:city":"Paisley",
    "sg:classifiers":[
        {
            "category":"Travel",
            "subcategory":"Hotels & Motels",
            "type":"Entertainment"
        }
    ],
    "sg:postcode":"PA3 4BJ",
    "sg:province":"Renfrewshire",
    "sg:tags":[
        "house",
        "guest"
    ],
    "wof:name":"Clabern Guest House",
    "wof:placetype":"venue"
},
  "geometry": {"coordinates":[-4.4160900116,55.8552436829],"type":"Point"}
}