{
  "type": "Feature",
  "properties": {
    "iso:country":"GB",
    "sg:address":"1 Derby Street",
    "sg:city":"Bury",
    "sg:classifiers":[
        {
            "category":"Autos & Motor Vehicles",
            "subcategory":"Automobile Sales",
            "type":"Retail Goods"
        }
    ],
    "sg:phone":"+44 161 764 5454",
    "sg:postcode":"BL9 0NW",
    "sg:province":"Lancashire",
    "sg:tags":[
        "car"
    ],
    "wof:name":"Dixon Ford (Bury)",
    "wof:placetype":"venue"
},
  "geometry": {"coordinates":[-2.289824,53.594227],"type":"Point"}
}