{
  "type": "Feature",
  "properties": {
    "addr:full":"St James Road, Eccleston Park Prescot Merseyside L34 2RH",
    "addr:postcode":"l34 2rh",
    "addr:street":"St James Road",
    "iso:country":"GB",
    "sg:address":"St James Road, Eccleston Park",
    "sg:city":"Prescot",
    "sg:classifiers":[
        {
            "category":"Bars & Pubs",
            "type":"Food & Drink"
        },
        {
            "category":"Community Center",
            "subcategory":"Social",
            "type":"Public Place"
        }
    ],
    "sg:phone":"+44 151 426 9693",
    "sg:postcode":"L34 2RH",
    "sg:province":"Merseyside",
    "sg:tags":[
        "pubs",
        "house",
        "inn",
        "activity"
    ],
    "wof:name":"Wellington Hotel",
    "wof:placetype":"venue"
},
  "geometry": {"coordinates":[-2.7933940887,53.4333953857],"type":"Point"}
}