{
  "type": "Feature",
  "properties": {
    "addr:full":"14 Oxford Street Daventry Northamptonshire NN11 4AD",
    "addr:housenumber":"14",
    "addr:postcode":"nn11 4ad",
    "addr:street":"Oxford Street",
    "iso:country":"GB",
    "sg:address":"14 Oxford Street",
    "sg:city":"Daventry",
    "sg:classifiers":[
        {
            "category":"Professional",
            "subcategory":"Employment Agencies",
            "type":"Services"
        }
    ],
    "sg:phone":"+44 1327 885200",
    "sg:postcode":"NN11 4AD",
    "sg:province":"Northamptonshire",
    "sg:tags":[
        "consultant"
    ],
    "wof:name":"Employment Service Jobcentre",
    "wof:placetype":"venue"
},
  "geometry": {"coordinates":[-1.163715,52.255878],"type":"Point"}
}