{
  "type": "Feature",
  "properties": {
    "iso:country":"GB",
    "sg:address":"12a Balderton Gate",
    "sg:city":"Newark",
    "sg:classifiers":[
        {
            "category":"Insurance",
            "subcategory":"Insurance Agent",
            "type":"Services"
        }
    ],
    "sg:postcode":"NG24 1UE",
    "sg:province":"Nottinghamshire",
    "sg:tags":[
        "broker"
    ],
    "wof:name":"J H Dale Insurance",
    "wof:placetype":"venue"
},
  "geometry": {"coordinates":[-0.807308,53.075146],"type":"Point"}
}