{
  "type": "Feature",
  "properties": {
    "addr:full":"12 Tithebarn Grove, Calcot Reading Berkshire RG31 7YX",
    "addr:housenumber":"12",
    "addr:postcode":"rg31 7yx",
    "addr:street":"Tithebarn Grove",
    "iso:country":"GB",
    "sg:address":"12 Tithebarn Grove, Calcot",
    "sg:city":"Reading",
    "sg:classifiers":[
        {
            "category":"Professional",
            "subcategory":"Management & Consulting",
            "type":"Services"
        }
    ],
    "sg:postcode":"RG31 7YX",
    "sg:province":"Berkshire",
    "sg:tags":[
        "consultant",
        "business"
    ],
    "wof:name":"I T C Consultancy",
    "wof:placetype":"venue"
},
  "geometry": {"coordinates":[-1.0270500183,51.4423866272],"type":"Point"}
}