{
  "type": "Feature",
  "properties": {
    "iso:country":"GB",
    "sg:address":"124 Lilycroft Road",
    "sg:city":"Bradford",
    "sg:classifiers":[
        {
            "category":"Shopping",
            "subcategory":"Shoes",
            "type":"Retail Goods"
        }
    ],
    "sg:postcode":"BD9 5AE",
    "sg:province":"West Yorkshire",
    "sg:tags":[
        "shop"
    ],
    "wof:name":"Ackroyds Footwear",
    "wof:placetype":"venue"
},
  "geometry": {"coordinates":[-1.781797,53.806904],"type":"Point"}
}