{
  "type": "Feature",
  "properties": {
    "addr:full":"52 Middle Street Yeovil Somerset BA20 1LX",
    "addr:housenumber":"52",
    "addr:postcode":"ba20 1lx",
    "addr:street":"Middle Street",
    "iso:country":"GB",
    "sg:address":"52 Middle Street",
    "sg:city":"Yeovil",
    "sg:classifiers":[
        {
            "category":"Banks & Credit Unions",
            "subcategory":"Financial Services",
            "type":"Services"
        }
    ],
    "sg:phone":"+44 1935 479839",
    "sg:postcode":"BA20 1LX",
    "sg:province":"Somerset",
    "sg:tags":[
        "adviser"
    ],
    "wof:name":"Aegis Insurance Brokers Ltd.",
    "wof:placetype":"venue"
},
  "geometry": {"coordinates":[-2.6291680336,50.9410438538],"type":"Point"}
}