{
  "type": "Feature",
  "properties": {
    "addr:full":"Winston Works, Brierley Lane, Bradley Bilston West Midlands WV14 8TU",
    "addr:postcode":"wv14 8tu",
    "addr:street":"Brierley Lane",
    "iso:country":"GB",
    "sg:address":"Winston Works, Brierley Lane, Bradley",
    "sg:city":"Bilston",
    "sg:classifiers":[
        {
            "category":"Home & Garden",
            "subcategory":"Hardware",
            "type":"Retail Goods"
        }
    ],
    "sg:phone":"+44 1902 494498",
    "sg:postcode":"WV14 8TU",
    "sg:province":"West Midlands",
    "sg:tags":[
        "device",
        "fixing",
        "fastener"
    ],
    "wof:name":"Hague Fasteners Ltd.",
    "wof:placetype":"venue"
},
  "geometry": {"coordinates":[-2.0743570328,52.5560112],"type":"Point"}
}