{
  "type": "Feature",
  "properties": {
    "iso:country":"GB",
    "sg:address":"Unit 5 Port Talbot Workshops, Addison Rd",
    "sg:city":"Port Talbot",
    "sg:classifiers":[
        {
            "category":"Professional",
            "subcategory":"Engineering",
            "type":"Services"
        }
    ],
    "sg:phone":"+44 1639 890062",
    "sg:postcode":"SA12 6HZ",
    "sg:province":"Neath Port Talbot",
    "sg:tags":[
        "consulting",
        "engineer"
    ],
    "wof:name":"A C S Environmental Ltd",
    "wof:placetype":"venue"
},
  "geometry": {"coordinates":[-3.8023691177,51.5913848877],"type":"Point"}
}