{
  "type": "Feature",
  "properties": {
    "addr:full":"17 Berwick Rd Rainham Essex RM13 9QU",
    "addr:housenumber":"17",
    "addr:postcode":"rm13 9qu",
    "addr:street":"Berwick Rd",
    "iso:country":"GB",
    "sg:address":"17 Berwick Rd",
    "sg:city":"Rainham",
    "sg:classifiers":[
        {
            "category":"Health Services",
            "subcategory":"Doctor",
            "type":"Services"
        }
    ],
    "sg:phone":"+44 1708 520830",
    "sg:postcode":"RM13 9QU",
    "sg:province":"Essex",
    "sg:tags":[
        "practitioners"
    ],
    "wof:name":"Adur, R M",
    "wof:placetype":"venue"
},
  "geometry": {"coordinates":[0.2141219974,51.526763916],"type":"Point"}
}