{
  "type": "Feature",
  "properties": {
    "addr:full":"Unit 4-5 Ainsworth Mall, Ainsworth Street Blackburn Lancashire BB1 6AD",
    "addr:housenumber":"unit 4-5",
    "addr:postcode":"bb1 6ad",
    "addr:street":"Ainsworth Mall Ainsworth Street",
    "iso:country":"GB",
    "sg:address":"Unit 4-5 Ainsworth Mall, Ainsworth Street",
    "sg:city":"Blackburn",
    "sg:classifiers":[
        {
            "category":"Shopping",
            "subcategory":"Gifts & Souvenirs",
            "type":"Retail Goods"
        }
    ],
    "sg:phone":"+44 1254 697348",
    "sg:postcode":"BB1 6AD",
    "sg:province":"Lancashire",
    "sg:tags":[
        "poster",
        "card"
    ],
    "wof:name":"Paperchain",
    "wof:placetype":"venue"
},
  "geometry": {"coordinates":[-2.480399,53.748516],"type":"Point"}
}