{
  "type": "Feature",
  "properties": {
    "addr:full":"56 Beancroft Road Castleford West Yorkshire WF10 5BS",
    "addr:housenumber":"56",
    "addr:postcode":"wf10 5bs",
    "addr:street":"Beancroft Road",
    "iso:country":"GB",
    "sg:address":"56 Beancroft Road",
    "sg:city":"Castleford",
    "sg:classifiers":[
        {
            "category":"Shopping",
            "subcategory":"News",
            "type":"Retail Goods"
        }
    ],
    "sg:postcode":"WF10 5BS",
    "sg:province":"West Yorkshire",
    "sg:tags":[
        "newsagent"
    ],
    "wof:name":"Beancroft News",
    "wof:placetype":"venue"
},
  "geometry": {"coordinates":[-1.3558210135,53.7212982178],"type":"Point"}
}