{
  "type": "Feature",
  "properties": {
    "iso:country":"GB",
    "sg:address":"Po Box 70",
    "sg:city":"Daventry",
    "sg:phone":"+44 1327 313600",
    "sg:postcode":"NN11 5ZP",
    "sg:province":"Northamptonshire",
    "wof:name":"Ingersoll Maschinen und Werkzeuge G M B H",
    "wof:placetype":"venue"
},
  "geometry": {"coordinates":[-1.158109,52.273319],"type":"Point"}
}