{
  "type": "Feature",
  "properties": {
    "addr:full":"47 High Street Heathfield East Sussex TN21 8HU",
    "addr:housenumber":"47",
    "addr:postcode":"tn21 8hu",
    "addr:street":"High Street",
    "iso:country":"GB",
    "sg:address":"47 High Street",
    "sg:city":"Heathfield",
    "sg:classifiers":[
        {
            "category":"Food & Beverages",
            "subcategory":"Meat & Fish",
            "type":"Retail Goods"
        }
    ],
    "sg:phone":"+44 1435 863527",
    "sg:postcode":"TN21 8HU",
    "sg:province":"East Sussex",
    "sg:tags":[
        "butcher"
    ],
    "wof:name":"Pomfret Butchers",
    "wof:placetype":"venue"
},
  "geometry": {"coordinates":[0.2496940047,50.9709014893],"type":"Point"}
}