{
  "type": "Feature",
  "properties": {
    "addr:full":"5 Lovelace Way, Fleckney Leicester Leicestershire LE8 8TT",
    "addr:housenumber":"5",
    "addr:postcode":"le8 8tt",
    "addr:street":"Lovelace Way",
    "iso:country":"GB",
    "sg:address":"5 Lovelace Way, Fleckney",
    "sg:city":"Leicester",
    "sg:classifiers":[
        {
            "category":"Building & Trades",
            "subcategory":"Construction",
            "type":"Services"
        }
    ],
    "sg:phone":"+44 116 240 2793",
    "sg:postcode":"LE8 8TT",
    "sg:province":"Leicestershire",
    "sg:tags":[
        "installers",
        "gas"
    ],
    "wof:name":"A Brown",
    "wof:placetype":"venue"
},
  "geometry": {"coordinates":[-1.0421710014,52.5338554382],"type":"Point"}
}