{
  "type": "Feature",
  "properties": {
    "addr:full":"24 Landsdown Avenue, South Kirkby Pontefract West Yorkshire WF9 3EU",
    "addr:housenumber":"24",
    "addr:postcode":"wf9 3eu",
    "addr:street":"Landsdown Avenue;West",
    "iso:country":"GB",
    "sg:address":"24 Landsdown Avenue, South Kirkby",
    "sg:city":"Pontefract",
    "sg:classifiers":[
        {
            "category":"Building & Trades",
            "subcategory":"Construction",
            "type":"Services"
        }
    ],
    "sg:postcode":"WF9 3EU",
    "sg:province":"West Yorkshire",
    "sg:tags":[
        "demolition",
        "contractor"
    ],
    "wof:name":"I H Equipment",
    "wof:placetype":"venue"
},
  "geometry": {"coordinates":[-1.3358999491,53.5866394043],"type":"Point"}
}