{
  "type": "Feature",
  "properties": {
    "addr:full":"Crest Ho, 7 Highfield Rd Birmingham West Midlands B15 3ED",
    "addr:housenumber":"7",
    "addr:postcode":"b15 3ed",
    "addr:street":"Highfield Rd",
    "iso:country":"GB",
    "sg:address":"Crest Ho, 7 Highfield Rd",
    "sg:city":"Birmingham",
    "sg:classifiers":[
        {
            "category":"Professional",
            "type":"Services"
        }
    ],
    "sg:phone":"+44 121 454 8588",
    "sg:postcode":"B15 3ED",
    "sg:province":"West Midlands",
    "sg:tags":[
        "control",
        "system"
    ],
    "wof:name":"H S Q Technology",
    "wof:placetype":"venue"
},
  "geometry": {"coordinates":[-1.908604,52.478596],"type":"Point"}
}