{
  "type": "Feature",
  "properties": {
    "iso:country":"GB",
    "sg:address":"6 West La",
    "sg:city":"Bradford",
    "sg:classifiers":[
        {
            "category":"Farming",
            "subcategory":"Nursery",
            "type":"Manufacturing & Wholesale Goods"
        }
    ],
    "sg:phone":"+44 1274 834358",
    "sg:postcode":"BD13 3HX",
    "sg:province":"West Yorkshire",
    "sg:tags":[
        "creche"
    ],
    "wof:name":"Princess Christian Day Nursery",
    "wof:placetype":"venue"
},
  "geometry": {"coordinates":[-1.8508249521,53.7910308838],"type":"Point"}
}