{
  "type": "Feature",
  "properties": {
    "iso:country":"GB",
    "sg:address":"29 Victoria Street",
    "sg:city":"Tenby",
    "sg:classifiers":[
        {
            "category":"Travel",
            "subcategory":"Hotels & Motels",
            "type":"Entertainment"
        }
    ],
    "sg:phone":"+44 1834 842403",
    "sg:postcode":"SA70 7DY",
    "sg:province":"Pembrokeshire",
    "wof:name":"Hildebrand Hotel",
    "wof:placetype":"venue"
},
  "geometry": {"coordinates":[-4.702127,51.669605],"type":"Point"}
}