{
  "type": "Feature",
  "properties": {
    "addr:full":"Swan Street, Evenwood Bishop Auckland Durham DL14 9RN",
    "addr:postcode":"dl14 9rn",
    "addr:street":"Swan Street;Auckland",
    "iso:country":"GB",
    "sg:address":"Swan Street, Evenwood",
    "sg:city":"Bishop Auckland",
    "sg:classifiers":[
        {
            "category":"Building & Trades",
            "subcategory":"Electrical",
            "type":"Services"
        }
    ],
    "sg:phone":"+44 1388 835800",
    "sg:postcode":"DL14 9RN",
    "sg:province":"Durham",
    "sg:tags":[
        "galvanising"
    ],
    "wof:name":"Industrial Coatings",
    "wof:placetype":"venue"
},
  "geometry": {"coordinates":[-1.764384,54.623741],"type":"Point"}
}