{
  "type": "Feature",
  "properties": {
    "addr:full":"41 Broadway Bradford West Yorkshire BD1 1DA",
    "addr:housenumber":"41",
    "addr:postcode":"bd1 1da",
    "addr:street":"Broadway",
    "iso:country":"GB",
    "sg:address":"41 Broadway",
    "sg:city":"Bradford",
    "sg:classifiers":[
        {
            "category":"Shopping",
            "subcategory":"Baby Store",
            "type":"Retail Goods"
        }
    ],
    "sg:phone":"+44 1274 732002",
    "sg:postcode":"BD1 1DA",
    "sg:province":"West Yorkshire",
    "sg:tags":[
        "nursery",
        "accessory"
    ],
    "wof:name":"Mothercare Uk",
    "wof:placetype":"venue"
},
  "geometry": {"coordinates":[-1.750886,53.794605],"type":"Point"}
}