{
  "type": "Feature",
  "properties": {
    "addr:full":"Unit 46 Armstrong Centre, Invincible Drive Newcastle-upon-tyne Tyne and Wear NE4 7HX",
    "addr:housenumber":"unit 46",
    "addr:postcode":"ne4 7hx",
    "addr:street":"Armstrong Centre Invincible Drive",
    "iso:country":"GB",
    "sg:address":"Unit 46 Armstrong Centre, Invincible Drive",
    "sg:city":"Newcastle-upon-tyne",
    "sg:classifiers":[
        {
            "category":"Banks & Credit Unions",
            "subcategory":"Bureau De Change",
            "type":"Services"
        },
        {
            "category":"Building & Trades",
            "subcategory":"Cleaning & Sanitation",
            "type":"Services"
        }
    ],
    "sg:phone":"+44 191 272 0395",
    "sg:postcode":"NE4 7HX",
    "sg:province":"Tyne and Wear",
    "sg:tags":[
        "hygiene",
        "cleansing"
    ],
    "wof:name":"Cannon Hygiene Ltd",
    "wof:placetype":"venue"
},
  "geometry": {"coordinates":[-1.63624,54.962059],"type":"Point"}
}