{
  "type": "Feature",
  "properties": {
    "addr:full":"13-27 Hastings Rd Bromley Kent BR2 8NA",
    "addr:housenumber":"13-27",
    "addr:postcode":"br2 8na",
    "addr:street":"Hastings Rd",
    "iso:country":"GB",
    "sg:address":"13-27 Hastings Rd",
    "sg:city":"Bromley",
    "sg:classifiers":[
        {
            "category":"Autos & Motor Vehicles",
            "subcategory":"Auto Supplies",
            "type":"Retail Goods"
        }
    ],
    "sg:phone":"+44 20 8462 6225",
    "sg:postcode":"BR2 8NA",
    "sg:province":"Kent",
    "sg:tags":[
        "tyre"
    ],
    "wof:name":"Motorway Tyres & Autocentres",
    "wof:placetype":"venue"
},
  "geometry": {"coordinates":[0.0435120016,51.378112793],"type":"Point"}
}