{
  "type": "Feature",
  "properties": {
    "addr:full":"19b Park Avenue South Harpenden Hertfordshire AL5 2DZ",
    "addr:housenumber":"19b",
    "addr:postcode":"al5 2dz",
    "addr:street":"Park Avenue South",
    "iso:country":"GB",
    "sg:address":"19b Park Avenue South",
    "sg:city":"Harpenden",
    "sg:classifiers":[
        {
            "category":"Professional",
            "subcategory":"Management & Consulting",
            "type":"Services"
        }
    ],
    "sg:phone":"+44 1582 767376",
    "sg:postcode":"AL5 2DZ",
    "sg:province":"Hertfordshire",
    "sg:tags":[
        "consultant",
        "business"
    ],
    "wof:name":"A G L Associates",
    "wof:placetype":"venue"
},
  "geometry": {"coordinates":[-0.369091,51.813332],"type":"Point"}
}