{
  "type": "Feature",
  "properties": {
    "addr:full":"13 Market St, Hindley Wigan Lancashire WN2 3AE",
    "addr:housenumber":"13",
    "addr:postcode":"wn2 3ae",
    "addr:street":"Market St",
    "iso:country":"GB",
    "sg:address":"13 Market St, Hindley",
    "sg:city":"Wigan",
    "sg:classifiers":[
        {
            "category":"Shopping",
            "subcategory":"Clothing, Apparel, & Fashions",
            "type":"Retail Goods"
        }
    ],
    "sg:postcode":"WN2 3AE",
    "sg:province":"Lancashire",
    "sg:tags":[
        "dresswear"
    ],
    "wof:name":"Miller,Patricia,",
    "wof:placetype":"venue"
},
  "geometry": {"coordinates":[-2.576488,53.536694],"type":"Point"}
}