{
  "type": "Feature",
  "properties": {
    "addr:full":"19 Hartland Drive Edgware Greater London HA8 8RJ",
    "addr:housenumber":"19",
    "addr:postcode":"ha8 8rj",
    "addr:street":"Hartland Drive",
    "iso:country":"GB",
    "sg:address":"19 Hartland Drive",
    "sg:city":"Edgware",
    "sg:classifiers":[
        {
            "category":"Professional",
            "subcategory":"Computer Services",
            "type":"Services"
        }
    ],
    "sg:phone":"+44 20 8958 2067",
    "sg:postcode":"HA8 8RJ",
    "sg:province":"Greater London",
    "sg:tags":[
        "system",
        "software"
    ],
    "wof:name":"Powerkey Ltd.",
    "wof:placetype":"venue"
},
  "geometry": {"coordinates":[-0.273297,51.628544],"type":"Point"}
}