{
  "type": "Feature",
  "properties": {
    "iso:country":"GB",
    "sg:address":"Rear Of 13 New Road, Stanborough",
    "sg:city":"Welwyn Garden City",
    "sg:classifiers":[
        {
            "category":"Professional",
            "subcategory":"Engineering",
            "type":"Services"
        },
        {
            "category":"Building & Trades",
            "subcategory":"Electrical",
            "type":"Services"
        }
    ],
    "sg:phone":"+44 1707 336173",
    "sg:postcode":"AL8 7TX",
    "sg:province":"Hertfordshire",
    "sg:tags":[
        "engineer",
        "electrician",
        "contractor"
    ],
    "wof:name":"A & H Ross",
    "wof:placetype":"venue"
},
  "geometry": {"coordinates":[-0.2275599986,51.7877006531],"type":"Point"}
}