{
  "type": "Feature",
  "properties": {
    "addr:full":"10 Castle Gro, Horbury Wakefield West Yorkshire WF4 5DX",
    "addr:housenumber":"10",
    "addr:postcode":"wf4 5dx",
    "addr:street":"Castle Gro Horbury",
    "iso:country":"GB",
    "sg:address":"10 Castle Gro, Horbury",
    "sg:city":"Wakefield",
    "sg:classifiers":[
        {
            "category":"Banks & Credit Unions",
            "subcategory":"Bank",
            "type":"Services"
        }
    ],
    "sg:phone":"+44 1924 276071",
    "sg:postcode":"WF4 5DX",
    "sg:province":"West Yorkshire",
    "sg:tags":[
        "broker",
        "mortgage"
    ],
    "wof:name":"John Dunford",
    "wof:placetype":"venue"
},
  "geometry": {"coordinates":[-1.5465899706,53.6561737061],"type":"Point"}
}