{
  "type": "Feature",
  "properties": {
    "iso:country":"GB",
    "sg:address":"152 High Street, Newburgh",
    "sg:city":"Cupar",
    "sg:classifiers":[
        {
            "category":"Home & Garden",
            "subcategory":"Kitchen Supply",
            "type":"Retail Goods"
        }
    ],
    "sg:phone":"+44 1337 841029",
    "sg:postcode":"KY14 6DZ",
    "sg:province":"Fife",
    "sg:tags":[
        "measuring",
        "scale"
    ],
    "wof:name":"Thistlebay Ltd.",
    "wof:placetype":"venue"
},
  "geometry": {"coordinates":[-3.241784,56.350723],"type":"Point"}
}