{
  "type": "Feature",
  "properties": {
    "iso:country":"GB",
    "sg:address":"9 Dunstaffnage Place",
    "sg:city":"Glenrothes",
    "sg:classifiers":[
        {
            "category":"Manufacturing",
            "subcategory":"Electronics",
            "type":"Manufacturing & Wholesale Goods"
        }
    ],
    "sg:phone":"+44 1592 630340",
    "sg:postcode":"KY7 4QQ",
    "sg:province":"Fife",
    "sg:tags":[
        "control",
        "component",
        "-",
        "electronic"
    ],
    "wof:name":"Qual-Tech Sales",
    "wof:placetype":"venue"
},
  "geometry": {"coordinates":[-3.164429,56.187168],"type":"Point"}
}