{
  "type": "Feature",
  "properties": {
    "addr:full":"1 Coton Crescent Shrewsbury Shropshire SY1 2NY",
    "addr:housenumber":"1",
    "addr:postcode":"sy1 2ny",
    "addr:street":"Coton Crescent",
    "iso:country":"GB",
    "sg:address":"1 Coton Crescent",
    "sg:city":"Shrewsbury",
    "sg:classifiers":[
        {
            "category":"Social Services",
            "subcategory":"Retirement Home",
            "type":"Services"
        }
    ],
    "sg:phone":"+44 1743 353026",
    "sg:postcode":"SY1 2NY",
    "sg:province":"Shropshire",
    "sg:tags":[
        "residential",
        "care"
    ],
    "wof:name":"Heatherlea Residential Home",
    "wof:placetype":"venue"
},
  "geometry": {"coordinates":[-2.753624,52.716515],"type":"Point"}
}