{
  "type": "Feature",
  "properties": {
    "addr:full":"14 Andre Street London Greater London E8 2AA",
    "addr:housenumber":"14",
    "addr:postcode":"e8 2aa",
    "addr:street":"Andre Street",
    "iso:country":"GB",
    "sg:address":"14 Andre Street",
    "sg:city":"London",
    "sg:classifiers":[
        {
            "category":"Utilities",
            "type":"Services"
        }
    ],
    "sg:postcode":"E8 2AA",
    "sg:province":"Greater London",
    "sg:tags":[
        "internet"
    ],
    "wof:name":"21-21 Millennium Club Ltd",
    "wof:placetype":"venue"
},
  "geometry": {"coordinates":[-0.0638440028,51.5517654419],"type":"Point"}
}