{
  "type": "Feature",
  "properties": {
    "addr:full":"Unit 16 Headlands Business Park, Salisbury Road Ringwood Dorset BH24 3PB",
    "addr:housenumber":"unit 16",
    "addr:postcode":"bh24 3pb",
    "addr:street":"Headlands Business Park Salisbury Road",
    "iso:country":"GB",
    "sg:address":"Unit 16 Headlands Business Park, Salisbury Road",
    "sg:city":"Ringwood",
    "sg:classifiers":[
        {
            "category":"Education",
            "subcategory":"Special Training",
            "type":"Public Place"
        }
    ],
    "sg:phone":"+44 121 697 6600",
    "sg:postcode":"BH24 3PB",
    "sg:province":"Dorset",
    "sg:tags":[
        "product",
        "centre"
    ],
    "wof:name":"Pinewood Computer Holdings Ltd",
    "wof:placetype":"venue"
},
  "geometry": {"coordinates":[-1.7929890156,50.8463287354],"type":"Point"}
}