{
  "type": "Feature",
  "properties": {
    "addr:full":"5 Causeway Cotts, Chiddingstone Causeway Tonbridge Kent TN11 8JR",
    "addr:housenumber":"5",
    "addr:postcode":"tn11 8jr",
    "addr:street":"Causeway;Causeway",
    "iso:country":"GB",
    "sg:address":"5 Causeway Cotts, Chiddingstone Causeway",
    "sg:city":"Tonbridge",
    "sg:classifiers":[
        {
            "category":"Farming",
            "subcategory":"Dairy Farm",
            "type":"Manufacturing & Wholesale Goods"
        }
    ],
    "sg:postcode":"TN11 8JR",
    "sg:province":"Kent",
    "wof:name":"Penrose,Alan,",
    "wof:placetype":"venue"
},
  "geometry": {"coordinates":[0.18122,51.198669],"type":"Point"}
}