{
  "type": "Feature",
  "properties": {
    "addr:full":"35 Queen Street Emsworth Hampshire PO10 7BL",
    "addr:housenumber":"35",
    "addr:postcode":"po10 7bl",
    "addr:street":"Queen Street",
    "iso:country":"GB",
    "sg:address":"35 Queen Street",
    "sg:city":"Emsworth",
    "sg:classifiers":[
        {
            "category":"Bars & Pubs",
            "type":"Food & Drink"
        }
    ],
    "sg:phone":"+44 1243 372587",
    "sg:postcode":"PO10 7BL",
    "sg:province":"Hampshire",
    "sg:tags":[
        "pubs",
        "inn"
    ],
    "wof:name":"The Lord Raglan",
    "wof:placetype":"venue"
},
  "geometry": {"coordinates":[-0.9326739907,50.8464241028],"type":"Point"}
}