{
  "type": "Feature",
  "properties": {
    "addr:full":"Colbrans Farm, Laughton Lewes East Sussex BN8 6BZ",
    "addr:postcode":"bn8 6bz",
    "addr:street":"Laughton",
    "iso:country":"GB",
    "sg:address":"Colbrans Farm, Laughton",
    "sg:city":"Lewes",
    "sg:classifiers":[
        {
            "category":"Farming",
            "subcategory":"Livestock Farm",
            "type":"Manufacturing & Wholesale Goods"
        }
    ],
    "sg:postcode":"BN8 6BZ",
    "sg:province":"East Sussex",
    "sg:tags":[
        "others"
    ],
    "wof:name":"T W Simpson",
    "wof:placetype":"venue"
},
  "geometry": {"coordinates":[0.13454,50.898365],"type":"Point"}
}