{
  "type": "Feature",
  "properties": {
    "iso:country":"GB",
    "sg:address":"Furnival Gardens, Dove Pier Upper Mall",
    "sg:city":"London",
    "sg:classifiers":[
        {
            "category":"Retail",
            "subcategory":"Event Space",
            "type":"Services"
        }
    ],
    "sg:phone":"+44 20 8748 2715",
    "sg:postcode":"W6 9TA",
    "sg:province":"Greater London",
    "sg:tags":[
        "sale",
        "boat"
    ],
    "wof:name":"London Tideway Harbour Co. Ltd.",
    "wof:placetype":"venue"
},
  "geometry": {"coordinates":[-0.2356400043,51.4905509949],"type":"Point"}
}