{
  "type": "Feature",
  "properties": {
    "addr:full":"32 Grafton Road Oldbury West Midlands B68 8BP",
    "addr:housenumber":"32",
    "addr:postcode":"b68 8bp",
    "addr:street":"Grafton Road",
    "iso:country":"GB",
    "sg:address":"32 Grafton Road",
    "sg:city":"Oldbury",
    "sg:classifiers":[
        {
            "category":"Building & Trades",
            "subcategory":"Landscaping Services",
            "type":"Services"
        }
    ],
    "sg:postcode":"B68 8BP",
    "sg:province":"West Midlands",
    "sg:tags":[
        "forestry",
        "surgeon",
        "tree"
    ],
    "wof:name":"H & W Tree Surgery",
    "wof:placetype":"venue"
},
  "geometry": {"coordinates":[-2.018117,52.481041],"type":"Point"}
}