{
  "type": "Feature",
  "properties": {
    "addr:full":"Gnatts Farm, Buckland Yelverton Devon PL20 6HA",
    "addr:postcode":"pl20 6ha",
    "addr:street":"Buckland",
    "iso:country":"GB",
    "sg:address":"Gnatts Farm, Buckland",
    "sg:city":"Yelverton",
    "sg:classifiers":[
        {
            "category":"Farming",
            "subcategory":"Dairy Farm",
            "type":"Manufacturing & Wholesale Goods"
        }
    ],
    "sg:phone":"+44 1822 852659",
    "sg:postcode":"PL20 6HA",
    "sg:province":"Devon",
    "wof:name":"W S Mattacott",
    "wof:placetype":"venue"
},
  "geometry": {"coordinates":[-4.0878591537,50.4923782349],"type":"Point"}
}