{
  "type": "Feature",
  "properties": {
    "iso:country":"GB",
    "sg:address":"3 Quaside Street, Leith",
    "sg:city":"Edinburgh",
    "sg:classifiers":[
        {
            "category":"Utilities",
            "type":"Services"
        }
    ],
    "sg:postcode":"EH6 6EJ",
    "sg:province":"City of Edinburgh",
    "sg:tags":[
        "internet"
    ],
    "wof:name":"Spidacom Ltd.",
    "wof:placetype":"venue"
},
  "geometry": {"coordinates":[-3.17342,55.975903],"type":"Point"}
}