{
  "type": "Feature",
  "properties": {
    "addr:full":"20 Bridge Lane London Greater London SW11 3AD",
    "addr:housenumber":"20",
    "addr:postcode":"sw11 3ad",
    "addr:street":"Bridge Lane",
    "iso:country":"GB",
    "sg:address":"20 Bridge Lane",
    "sg:city":"London",
    "sg:classifiers":[
        {
            "category":"Health Services",
            "subcategory":"Doctor",
            "type":"Services"
        },
        {
            "category":"Health Services",
            "subcategory":"Clinic",
            "type":"Services"
        }
    ],
    "sg:phone":"+44 20 7978 6737",
    "sg:postcode":"SW11 3AD",
    "sg:province":"Greater London",
    "sg:tags":[
        "nh",
        "practitioners"
    ],
    "wof:name":"Bridge Lane Health Centre",
    "wof:placetype":"venue"
},
  "geometry": {"coordinates":[-0.166901,51.473751],"type":"Point"}
}