{
  "type": "Feature",
  "properties": {
    "addr:full":"Allen Gardiner House, Pembury Road Tunbridge Wells East Sussex TN2 3QU",
    "addr:postcode":"tn2 3qu",
    "addr:street":"Pembury Road",
    "iso:country":"GB",
    "sg:address":"Allen Gardiner House, Pembury Road",
    "sg:city":"Tunbridge Wells",
    "sg:classifiers":[
        {
            "category":"Organizations",
            "subcategory":"Non-profit Organization",
            "type":"Services"
        }
    ],
    "sg:phone":"+44 1892 538647",
    "sg:postcode":"TN2 3QU",
    "sg:province":"East Sussex",
    "sg:tags":[
        "organisation",
        "voluntary",
        "charity"
    ],
    "wof:name":"The South American Mission Society",
    "wof:placetype":"venue"
},
  "geometry": {"coordinates":[0.2865650058,51.1363601685],"type":"Point"}
}