{
  "type": "Feature",
  "properties": {
    "addr:full":"130 High Street Shepperton Surrey TW17 9BG",
    "addr:housenumber":"130",
    "addr:postcode":"tw17 9bg",
    "addr:street":"High Street",
    "iso:country":"GB",
    "sg:address":"130 High Street",
    "sg:city":"Shepperton",
    "sg:classifiers":[
        {
            "category":"Professional",
            "subcategory":"Business Services",
            "type":"Services"
        }
    ],
    "sg:phone":"+44 1932 252555",
    "sg:postcode":"TW17 9BG",
    "sg:province":"Surrey",
    "sg:tags":[
        "tile",
        "stockist"
    ],
    "wof:name":"Artisan Tiles",
    "wof:placetype":"venue"
},
  "geometry": {"coordinates":[-0.4496560097,51.3915748596],"type":"Point"}
}