{
  "type": "Feature",
  "properties": {
    "iso:country":"GB",
    "sg:address":"25 Church Rd, Wimbledon Village",
    "sg:city":"Wimbledon",
    "sg:classifiers":[
        {
            "category":"Shopping",
            "subcategory":"Clothing, Apparel, & Fashions",
            "type":"Retail Goods"
        }
    ],
    "sg:phone":"+44 20 8947 4366",
    "sg:postcode":"SW19 5DQ",
    "sg:province":"Greater London",
    "sg:tags":[
        "shop"
    ],
    "wof:name":"Valentina",
    "wof:placetype":"venue"
},
  "geometry": {"coordinates":[-0.2171519995,51.4261207581],"type":"Point"}
}