{
  "type": "Feature",
  "properties": {
    "addr:full":"20 Old Station Road Newmarket Cambridgeshire CB8 8DN",
    "addr:housenumber":"20",
    "addr:postcode":"cb8 8dn",
    "addr:street":"Old Station Road",
    "iso:country":"GB",
    "sg:address":"20 Old Station Road",
    "sg:city":"Newmarket",
    "sg:classifiers":[
        {
            "category":"Shopping",
            "subcategory":"Clothing, Apparel, & Fashions",
            "type":"Retail Goods"
        }
    ],
    "sg:phone":"+44 1638 664006",
    "sg:postcode":"CB8 8DN",
    "sg:province":"Cambridgeshire",
    "sg:tags":[
        "shop"
    ],
    "wof:name":"Judith Fisher",
    "wof:placetype":"venue"
},
  "geometry": {"coordinates":[0.410065,52.245281],"type":"Point"}
}