{
  "type": "Feature",
  "properties": {
    "iso:country":"GB",
    "sg:address":"25 The Dene, Abinger Hammer",
    "sg:city":"Dorking",
    "sg:classifiers":[
        {
            "category":"Home & Garden",
            "subcategory":"Building Materials",
            "type":"Retail Goods"
        },
        {
            "category":"Banks & Credit Unions",
            "subcategory":"Financial Services",
            "type":"Services"
        }
    ],
    "sg:phone":"+44 1306 730677",
    "sg:postcode":"RH5 6PX",
    "sg:province":"Surrey",
    "sg:tags":[
        "ornamental",
        "metalwork",
        "production"
    ],
    "wof:name":"Ironcraft",
    "wof:placetype":"venue"
},
  "geometry": {"coordinates":[-0.432434,51.215931],"type":"Point"}
}