{
  "type": "Feature",
  "properties": {
    "addr:full":"1 Great Cumberland Place London Greater London W1H 7AL",
    "addr:housenumber":"1",
    "addr:postcode":"w1h 7al",
    "addr:street":"Great Cumberland Place",
    "iso:country":"GB",
    "sg:address":"1 Great Cumberland Place",
    "sg:city":"London",
    "sg:classifiers":[
        {
            "category":"Real Estate",
            "subcategory":"Surveying",
            "type":"Services"
        }
    ],
    "sg:postcode":"W1H 7AL",
    "sg:province":"Greater London",
    "sg:tags":[
        "surveyor",
        "valuer"
    ],
    "wof:name":"Anthony Filer & Co",
    "wof:placetype":"venue"
},
  "geometry": {"coordinates":[-0.1593270004,51.5137939453],"type":"Point"}
}