{
  "type": "Feature",
  "properties": {
    "addr:full":"Rear Of 430 Kingstanding Road Birmingham West Midlands B44 9SA",
    "addr:housenumber":"430",
    "addr:postcode":"b44 9sa",
    "addr:street":"Kingstanding Road",
    "iso:country":"GB",
    "sg:address":"Rear Of 430 Kingstanding Road",
    "sg:city":"Birmingham",
    "sg:classifiers":[
        {
            "category":"Retail",
            "subcategory":"Auto Repair",
            "type":"Services"
        }
    ],
    "sg:phone":"+44 121 373 2186",
    "sg:postcode":"B44 9SA",
    "sg:province":"West Midlands",
    "sg:tags":[
        "modification",
        "garage"
    ],
    "wof:name":"Mossons Garage",
    "wof:placetype":"venue"
},
  "geometry": {"coordinates":[-1.8857200146,52.5421981812],"type":"Point"}
}