{
  "type": "Feature",
  "properties": {
    "iso:country":"GB",
    "sg:address":"77 Halse Road",
    "sg:city":"Brackley",
    "sg:classifiers":[
        {
            "category":"Health Services",
            "subcategory":"Doctor",
            "type":"Services"
        }
    ],
    "sg:phone":"+44 1280 702436",
    "sg:postcode":"NN13 6EQ",
    "sg:province":"Buckinghamshire",
    "sg:tags":[
        "practitioners"
    ],
    "wof:name":"Washington House Surgery",
    "wof:placetype":"venue"
},
  "geometry": {"coordinates":[-1.146616,52.035435],"type":"Point"}
}