{
  "type": "Feature",
  "properties": {
    "iso:country":"GB",
    "sg:address":"154 Harlesden Rd, Willesden",
    "sg:city":"Willesden",
    "sg:classifiers":[
        {
            "category":"Organizations",
            "subcategory":"Non-profit Organization",
            "type":"Services"
        }
    ],
    "sg:phone":"+44 20 8459 3177",
    "sg:postcode":"NW10 3RX",
    "sg:province":"Greater London",
    "sg:tags":[
        "organisation",
        "voluntary",
        "charity"
    ],
    "wof:name":"Brent Independent Living Scheme",
    "wof:placetype":"venue"
},
  "geometry": {"coordinates":[-0.235639,51.543968],"type":"Point"}
}