{
  "type": "Feature",
  "properties": {
    "iso:country":"GB",
    "sg:address":"Unit 8 Centenary Estate, Centenary Road, Brimsdown",
    "sg:city":"Enfield",
    "sg:classifiers":[
        {
            "category":"Shopping",
            "subcategory":"Stationery & Office Supplies",
            "type":"Retail Goods"
        }
    ],
    "sg:phone":"+44 20 8804 4747",
    "sg:postcode":"EN3 7UF",
    "sg:province":"Greater London",
    "wof:name":"Kingsfield Heath",
    "wof:placetype":"venue"
},
  "geometry": {"coordinates":[-0.0277389996,51.6486968994],"type":"Point"}
}