{
  "type": "Feature",
  "properties": {
    "addr:full":"1082 South Street Glasgow Glasgow City G14 0AP",
    "addr:housenumber":"1082",
    "addr:postcode":"g14 0ap",
    "addr:street":"South Street",
    "iso:country":"GB",
    "sg:address":"1082 South Street",
    "sg:city":"Glasgow",
    "sg:classifiers":[
        {
            "category":"Professional",
            "subcategory":"Testing Lab",
            "type":"Services"
        }
    ],
    "sg:phone":"+44 141 950 1308",
    "sg:postcode":"G14 0AP",
    "sg:province":"Glasgow City",
    "sg:tags":[
        "mot"
    ],
    "wof:name":"Scotstoun Mot & Service Centre",
    "wof:placetype":"venue"
},
  "geometry": {"coordinates":[-4.3511118889,55.876739502],"type":"Point"}
}