{
  "type": "Feature",
  "properties": {
    "iso:country":"GB",
    "sg:address":"Adelaide Farm Cafe",
    "sg:city":"Deal",
    "sg:classifiers":[
        {
            "category":"Cafe",
            "type":"Food & Drink"
        }
    ],
    "sg:phone":"+44 1304 620158",
    "sg:postcode":"CT14 0AT",
    "sg:province":"Kent",
    "sg:tags":[
        "tea",
        "room"
    ],
    "wof:name":"The Adelaide Farm Cafe",
    "wof:placetype":"venue"
},
  "geometry": {"coordinates":[1.403235,51.223129],"type":"Point"}
}