{
  "type": "Feature",
  "properties": {
    "addr:full":"Sandown Airport Sandown Isle of Wight PO36 0JP",
    "addr:postcode":"po36 0jp",
    "iso:country":"GB",
    "sg:address":"Sandown Airport",
    "sg:city":"Sandown",
    "sg:classifiers":[
        {
            "category":"Airline",
            "type":"Transportation"
        }
    ],
    "sg:phone":"+44 1983 408374",
    "sg:postcode":"PO36 0JP",
    "sg:province":"Isle of Wight",
    "sg:tags":[
        "airport"
    ],
    "wof:name":"Birnie Air Services",
    "wof:placetype":"venue"
},
  "geometry": {"coordinates":[-1.1501640081,50.6560134888],"type":"Point"}
}