{
  "type": "Feature",
  "properties": {
    "addr:full":"11 Princess Street, Castle Gresley Swadlincote Derbyshire DE11 9JZ",
    "addr:housenumber":"11",
    "addr:postcode":"de11 9jz",
    "addr:street":"Princess Street",
    "iso:country":"GB",
    "sg:address":"11 Princess Street, Castle Gresley",
    "sg:city":"Swadlincote",
    "sg:classifiers":[
        {
            "category":"Fast Food",
            "type":"Food & Drink"
        }
    ],
    "sg:phone":"+44 1283 224579",
    "sg:postcode":"DE11 9JZ",
    "sg:province":"Derbyshire",
    "sg:tags":[
        "away",
        "take"
    ],
    "wof:name":"King Wah",
    "wof:placetype":"venue"
},
  "geometry": {"coordinates":[-1.5721479654,52.7583389282],"type":"Point"}
}