{
  "type": "Feature",
  "properties": {
    "addr:full":"19 Godlings Way Braintree Essex CM7 1HW",
    "addr:housenumber":"19",
    "addr:postcode":"cm7 1hw",
    "addr:street":"Godlings Way",
    "iso:country":"GB",
    "sg:address":"19 Godlings Way",
    "sg:city":"Braintree",
    "sg:classifiers":[
        {
            "category":"Organizations",
            "subcategory":"Membership Organization",
            "type":"Services"
        }
    ],
    "sg:phone":"+44 1376 321718",
    "sg:postcode":"CM7 1HW",
    "sg:province":"Essex",
    "sg:tags":[
        "club"
    ],
    "wof:name":"N B Management Ltd",
    "wof:placetype":"venue"
},
  "geometry": {"coordinates":[0.5477520227,51.8737602234],"type":"Point"}
}