{
  "type": "Feature",
  "properties": {
    "addr:full":"132 Town St, Stanningley Pudsey West Yorkshire LS28 6ER",
    "addr:housenumber":"132",
    "addr:postcode":"ls28 6er",
    "addr:street":"Town St;West",
    "iso:country":"GB",
    "sg:address":"132 Town St, Stanningley",
    "sg:city":"Pudsey",
    "sg:classifiers":[
        {
            "category":"Home & Garden",
            "subcategory":"Building Materials",
            "type":"Retail Goods"
        }
    ],
    "sg:phone":"+44 113 257 1512",
    "sg:postcode":"LS28 6ER",
    "sg:province":"West Yorkshire",
    "sg:tags":[
        "plaster",
        "ware"
    ],
    "wof:name":"Distinct Decor",
    "wof:placetype":"venue"
},
  "geometry": {"coordinates":[-1.6646230221,53.8062591553],"type":"Point"}
}