{
  "type": "Feature",
  "properties": {
    "addr:full":"Billet Lane Berkhamsted Bedfordshire HP4 1DP",
    "addr:postcode":"hp4 1dp",
    "addr:street":"Billet Lane",
    "iso:country":"GB",
    "sg:address":"Billet Lane",
    "sg:city":"Berkhamsted",
    "sg:classifiers":[
        {
            "category":"Retail",
            "subcategory":"Auto Repair",
            "type":"Services"
        }
    ],
    "sg:phone":"+44 1442 871911",
    "sg:postcode":"HP4 1DP",
    "sg:province":"Bedfordshire",
    "sg:tags":[
        "modification",
        "garage",
        "related"
    ],
    "wof:name":"T A Lingard Motors",
    "wof:placetype":"venue"
},
  "geometry": {"coordinates":[-0.5760840178,51.7688331604],"type":"Point"}
}