{
  "type": "Feature",
  "properties": {
    "iso:country":"GB",
    "sg:address":"56 Bigland Street",
    "sg:city":"London",
    "sg:classifiers":[
        {
            "category":"Education",
            "subcategory":"School",
            "type":"Public Place"
        }
    ],
    "sg:phone":"+44 20 7790 7878",
    "sg:postcode":"E1 2ND",
    "sg:province":"Greater London",
    "sg:tags":[
        "independent",
        "preparatory"
    ],
    "wof:name":"Jamiatul Ummah",
    "wof:placetype":"venue"
},
  "geometry": {"coordinates":[-0.0590419993,51.5127105713],"type":"Point"}
}