{
  "type": "Feature",
  "properties": {
    "iso:country":"GB",
    "sg:address":"33 The Hundred",
    "sg:city":"Romsey",
    "sg:classifiers":[
        {
            "category":"Home & Garden",
            "subcategory":"Home Furnishings",
            "type":"Retail Goods"
        }
    ],
    "sg:postcode":"SO51 8YF",
    "sg:province":"Hampshire",
    "sg:tags":[
        "patio",
        "furniture"
    ],
    "wof:name":"Homes & Gardens by Romsey Designs",
    "wof:placetype":"venue"
},
  "geometry": {"coordinates":[-1.49734,50.988762],"type":"Point"}
}