{
  "type": "Feature",
  "properties": {
    "addr:full":"264 Vauxhall Bridge Road London Greater London SW1V 1BB",
    "addr:housenumber":"264",
    "addr:postcode":"sw1v 1bb",
    "addr:street":"Vauxhall Bridge Road",
    "iso:country":"GB",
    "sg:address":"264 Vauxhall Bridge Road",
    "sg:city":"London",
    "sg:classifiers":[
        {
            "category":"Cafe",
            "type":"Food & Drink"
        },
        {
            "category":"Shopping",
            "subcategory":"Books",
            "type":"Retail Goods"
        }
    ],
    "sg:phone":"+44 20 7834 5363",
    "sg:postcode":"SW1V 1BB",
    "sg:province":"Greater London",
    "sg:tags":[
        "bookseller",
        "tea",
        "room"
    ],
    "wof:name":"Padre Pio Bookshop",
    "wof:placetype":"venue"
},
  "geometry": {"coordinates":[-0.1411859989,51.4946403503],"type":"Point"}
}