{
  "type": "Feature",
  "properties": {
    "addr:full":"22 Ashtree Bank, Brereton Rugeley Staffordshire WS15 1HN",
    "addr:housenumber":"22",
    "addr:postcode":"ws15 1hn",
    "addr:street":"Ashtree Bank",
    "iso:country":"GB",
    "sg:address":"22 Ashtree Bank, Brereton",
    "sg:city":"Rugeley",
    "sg:classifiers":[
        {
            "category":"Building & Trades",
            "subcategory":"Equipment Rental",
            "type":"Services"
        }
    ],
    "sg:phone":"+44 1889 270137",
    "sg:postcode":"WS15 1HN",
    "sg:province":"Staffordshire",
    "sg:tags":[
        "plant",
        "machinery"
    ],
    "wof:name":"C N Greene & Sons Ltd.",
    "wof:placetype":"venue"
},
  "geometry": {"coordinates":[-1.9188569784,52.7478523254],"type":"Point"}
}