{
  "type": "Feature",
  "properties": {
    "addr:full":"8a Geraldine Rd Wandsworth Greater London SW18 2NU",
    "addr:housenumber":"8a",
    "addr:postcode":"sw18 2nu",
    "addr:street":"Geraldine Rd",
    "iso:country":"GB",
    "sg:address":"8a Geraldine Rd",
    "sg:city":"Wandsworth",
    "sg:classifiers":[
        {
            "category":"Retail",
            "subcategory":"Auto Repair",
            "type":"Services"
        }
    ],
    "sg:phone":"+44 20 8871 4805",
    "sg:postcode":"SW18 2NU",
    "sg:province":"Greater London",
    "sg:tags":[
        "modification",
        "garage"
    ],
    "wof:name":"C G Motors",
    "wof:placetype":"venue"
},
  "geometry": {"coordinates":[-0.185527,51.457081],"type":"Point"}
}