{
  "type": "Feature",
  "properties": {
    "iso:country":"GB",
    "sg:address":"85 Smallbrook Queensway",
    "sg:city":"Birmingham",
    "sg:classifiers":[
        {
            "category":"Professional",
            "subcategory":"Engineering",
            "type":"Services"
        }
    ],
    "sg:phone":"+44 1248 680040",
    "sg:postcode":"B5 4HX",
    "sg:province":"West Midlands",
    "sg:tags":[
        "design",
        "engineer"
    ],
    "wof:name":"D C V Birmingham",
    "wof:placetype":"venue"
},
  "geometry": {"coordinates":[-1.89639,52.47657],"type":"Point"}
}