{
  "type": "Feature",
  "properties": {
    "iso:country":"GB",
    "sg:address":"9 High Street",
    "sg:city":"Buckie",
    "sg:classifiers":[
        {
            "category":"Shopping",
            "subcategory":"Comic Books",
            "type":"Retail Goods"
        }
    ],
    "sg:postcode":"AB56 1AL",
    "sg:province":"Moray",
    "sg:tags":[
        "jeweller"
    ],
    "wof:name":"D G  McGregor",
    "wof:placetype":"venue"
},
  "geometry": {"coordinates":[-2.964307,57.675934],"type":"Point"}
}