{
  "type": "Feature",
  "properties": {
    "iso:country":"GB",
    "sg:address":"Stafferton Way",
    "sg:city":"Maidenhead",
    "sg:classifiers":[
        {
            "category":"Autos & Motor Vehicles",
            "subcategory":"Automobile Sales",
            "type":"Retail Goods"
        }
    ],
    "sg:phone":"+44 1628 680300",
    "sg:postcode":"SL6 1AY",
    "sg:province":"Berkshire",
    "sg:tags":[
        "car"
    ],
    "wof:name":"Altwood",
    "wof:placetype":"venue"
},
  "geometry": {"coordinates":[-0.719734,51.517319],"type":"Point"}
}