{
  "type": "Feature",
  "properties": {
    "addr:full":"Hallot Hey Farm, Primrose Vale Stockport Cheshire SK12 5NH",
    "addr:postcode":"sk12 5nh",
    "addr:street":"Hallot Hey;Primrose Vale",
    "iso:country":"GB",
    "sg:address":"Hallot Hey Farm, Primrose Vale",
    "sg:city":"Stockport",
    "sg:classifiers":[
        {
            "category":"Freight",
            "type":"Transportation"
        }
    ],
    "sg:phone":"+44 1663 744579",
    "sg:postcode":"SK12 5NH",
    "sg:province":"Cheshire",
    "sg:tags":[
        "haulage",
        "road"
    ],
    "wof:name":"Roberts Transport Services",
    "wof:placetype":"venue"
},
  "geometry": {"coordinates":[-2.0789599419,53.3470497131],"type":"Point"}
}