{
  "type": "Feature",
  "properties": {
    "addr:full":"Etongate, 110 Windsor Road Slough Berkshire SL1 2JA",
    "addr:housenumber":"110",
    "addr:postcode":"sl1 2ja",
    "addr:street":"Etongate;Windsor Road",
    "iso:country":"GB",
    "sg:address":"Etongate, 110 Windsor Road",
    "sg:city":"Slough",
    "sg:classifiers":[
        {
            "category":"Professional",
            "subcategory":"Computer Services",
            "type":"Services"
        }
    ],
    "sg:postcode":"SL1 2JA",
    "sg:province":"Berkshire",
    "sg:tags":[
        "consultant"
    ],
    "wof:name":"Networks Plus Ltd.",
    "wof:placetype":"venue"
},
  "geometry": {"coordinates":[-0.596417,51.507874],"type":"Point"}
}