{
  "type": "Feature",
  "properties": {
    "iso:country":"GB",
    "sg:address":"18 Stafford Street, St Georges",
    "sg:city":"Telford",
    "sg:classifiers":[
        {
            "category":"Food & Beverages",
            "subcategory":"Meat & Fish",
            "type":"Retail Goods"
        }
    ],
    "sg:postcode":"TF2 9JQ",
    "sg:province":"Shropshire",
    "sg:tags":[
        "butcher"
    ],
    "wof:name":"Ernie's Butchers & Freezer Centre",
    "wof:placetype":"venue"
},
  "geometry": {"coordinates":[-2.436453104,52.6940574646],"type":"Point"}
}