{
  "type": "Feature",
  "properties": {
    "addr:full":"21 Brunswick Road Shoreham-by-sea West Sussex BN43 5WA",
    "addr:housenumber":"21",
    "addr:postcode":"bn43 5wa",
    "addr:street":"Brunswick Road",
    "iso:country":"GB",
    "sg:address":"21 Brunswick Road",
    "sg:city":"Shoreham-by-sea",
    "sg:classifiers":[
        {
            "category":"Home & Garden",
            "subcategory":"Home Furnishings",
            "type":"Retail Goods"
        }
    ],
    "sg:phone":"+44 1903 205606",
    "sg:postcode":"BN43 5WA",
    "sg:province":"West Sussex",
    "sg:tags":[
        "blind",
        "curtain",
        "fitting"
    ],
    "wof:name":"Chantillylace",
    "wof:placetype":"venue"
},
  "geometry": {"coordinates":[-0.272784,50.833912],"type":"Point"}
}