{
  "type": "Feature",
  "properties": {
    "addr:full":"98-100 North Rd Chesterfield Derbyshire S43 4PF",
    "addr:housenumber":"98-100",
    "addr:postcode":"s43 4pf",
    "addr:street":"North Rd",
    "iso:country":"GB",
    "sg:address":"98-100 North Rd",
    "sg:city":"Chesterfield",
    "sg:classifiers":[
        {
            "category":"Professional",
            "subcategory":"Engineering",
            "type":"Services"
        }
    ],
    "sg:phone":"+44 1246 813621",
    "sg:postcode":"S43 4PF",
    "sg:province":"Derbyshire",
    "sg:tags":[
        "contractor",
        "electrical",
        "engineer"
    ],
    "wof:name":"Gower Domestic",
    "wof:placetype":"venue"
},
  "geometry": {"coordinates":[-1.263206,53.277649],"type":"Point"}
}