{
  "type": "Feature",
  "properties": {
    "addr:full":"Unit 13 Block 1, Souter Head Road, Altens Industrial Estate Aberdeen Aberdeen City AB12 3LF",
    "addr:housenumber":"unit 13 block 1",
    "addr:postcode":"ab12 3lf",
    "addr:street":"Souter Head Road Altens Industrial Estate",
    "iso:country":"GB",
    "sg:address":"Unit 13 Block 1, Souter Head Road, Altens Industrial Estate",
    "sg:city":"Aberdeen",
    "sg:classifiers":[
        {
            "category":"Home & Garden",
            "subcategory":"Home Furnishings",
            "type":"Retail Goods"
        }
    ],
    "sg:postcode":"AB12 3LF",
    "sg:province":"Aberdeen City",
    "sg:tags":[
        "pipe",
        "fitting"
    ],
    "wof:name":"Wilsons Aberdeen Ltd.",
    "wof:placetype":"venue"
},
  "geometry": {"coordinates":[-2.080849,57.109871],"type":"Point"}
}