{
  "type": "Feature",
  "properties": {
    "iso:country":"GB",
    "sg:address":"29 Knoll Croft Road",
    "sg:city":"Shotts",
    "sg:classifiers":[
        {
            "category":"Professional",
            "subcategory":"Business Services",
            "type":"Services"
        },
        {
            "category":"Casinos & Gambling",
            "type":"Entertainment"
        }
    ],
    "sg:postcode":"ML7 5JF",
    "sg:province":"North Lanarkshire",
    "sg:tags":[
        "turf",
        "accountant",
        "bookmaker"
    ],
    "wof:name":"Lorna Vance",
    "wof:placetype":"venue"
},
  "geometry": {"coordinates":[-3.7817540169,55.8129005432],"type":"Point"}
}