{
  "type": "Feature",
  "properties": {
    "iso:country":"GB",
    "sg:address":"High St",
    "sg:city":"Goole",
    "sg:classifiers":[
        {
            "category":"Place Of Worship",
            "type":"Public Place"
        }
    ],
    "sg:phone":"+44 1405 860866",
    "sg:postcode":"DN14 9HF",
    "sg:province":"East Riding of Yorkshire",
    "wof:name":"Snaith Priory",
    "wof:placetype":"venue"
},
  "geometry": {"coordinates":[-1.020635,53.707108],"type":"Point"}
}