{
  "type": "Feature",
  "properties": {
    "iso:country":"GB",
    "sg:address":"92 Manor St",
    "sg:city":"Braintree",
    "sg:classifiers":[
        {
            "category":"Military Area",
            "subcategory":"Air Force Base",
            "type":"Public Place"
        }
    ],
    "sg:phone":"+44 1376 323232",
    "sg:postcode":"CM7 3HS",
    "sg:province":"Essex",
    "sg:tags":[
        "taxi",
        "hire",
        "private"
    ],
    "wof:name":"Direct Line Taxis",
    "wof:placetype":"venue"
},
  "geometry": {"coordinates":[0.5606629848,51.8777389526],"type":"Point"}
}