{
  "type": "Feature",
  "properties": {
    "addr:full":"Health Centre, Greenway North Curry Taunton Devon TA3 6NQ",
    "addr:housenumber":"curry",
    "addr:postcode":"ta3 6nq",
    "addr:street":"Greenway North",
    "iso:country":"GB",
    "sg:address":"Health Centre, Greenway North Curry",
    "sg:city":"Taunton",
    "sg:classifiers":[
        {
            "category":"Health Services",
            "subcategory":"Doctor",
            "type":"Services"
        },
        {
            "category":"Health Services",
            "subcategory":"Clinic",
            "type":"Services"
        }
    ],
    "sg:phone":"+44 1823 490505",
    "sg:postcode":"TA3 6NQ",
    "sg:province":"Devon",
    "sg:tags":[
        "nh",
        "practitioners"
    ],
    "wof:name":"N Chapman & J Hickman Drs",
    "wof:placetype":"venue"
},
  "geometry": {"coordinates":[-2.9703390598,51.0229263306],"type":"Point"}
}