{
  "type": "Feature",
  "properties": {
    "addr:full":"Hauldy, Bryncrug Tywyn Gwynedd LL36 9PT",
    "addr:postcode":"ll36 9pt",
    "iso:country":"GB",
    "sg:address":"Hauldy, Bryncrug",
    "sg:city":"Tywyn",
    "sg:classifiers":[
        {
            "category":"Freight",
            "type":"Transportation"
        }
    ],
    "sg:phone":"+44 1654 710560",
    "sg:postcode":"LL36 9PT",
    "sg:province":"Gwynedd",
    "sg:tags":[
        "haulage",
        "transport",
        "road"
    ],
    "wof:name":"Lloyd Jones L & Son",
    "wof:placetype":"venue"
},
  "geometry": {"coordinates":[-4.0884189606,52.5865859985],"type":"Point"}
}