{
  "type": "Feature",
  "properties": {
    "iso:country":"GB",
    "sg:address":"Unit 18, Upper Glazed Walkway",
    "sg:city":"Moorgate",
    "sg:classifiers":[
        {
            "category":"Shopping",
            "subcategory":"Gifts & Souvenirs",
            "type":"Retail Goods"
        }
    ],
    "sg:phone":"+44 20 7377 0096",
    "sg:postcode":"EC2M 7PY",
    "sg:province":"Greater London",
    "sg:tags":[
        "shop"
    ],
    "wof:name":"Classic Characters",
    "wof:placetype":"venue"
},
  "geometry": {"coordinates":[-0.0829600021,51.5173683167],"type":"Point"}
}