{
  "type": "Feature",
  "properties": {
    "addr:full":"23-25 Orwell Road Clacton-on-sea Essex CO15 1PP",
    "addr:housenumber":"23-25",
    "addr:postcode":"co15 1pp",
    "addr:street":"Orwell Road",
    "iso:country":"GB",
    "sg:address":"23-25 Orwell Road",
    "sg:city":"Clacton-on-sea",
    "sg:classifiers":[
        {
            "category":"Retail",
            "subcategory":"Laundry & Dry Cleaning",
            "type":"Services"
        }
    ],
    "sg:postcode":"CO15 1PP",
    "sg:province":"Essex",
    "sg:tags":[
        "alteration"
    ],
    "wof:name":"Smiths Service Centre",
    "wof:placetype":"venue"
},
  "geometry": {"coordinates":[1.1550370455,51.7892417908],"type":"Point"}
}