{
  "type": "Feature",
  "properties": {
    "iso:country":"GB",
    "sg:address":"Joppa Farm, Kelynack",
    "sg:city":"Penzance",
    "sg:classifiers":[
        {
            "category":"Transit Center",
            "subcategory":"Passenger",
            "type":"Transportation"
        }
    ],
    "sg:postcode":"TR19 7RW",
    "sg:province":"Cornwall",
    "sg:tags":[
        "boarding",
        "kennel",
        "catteries"
    ],
    "wof:name":"Joppa Farm Boarding Kennels & Cattery",
    "wof:placetype":"venue"
},
  "geometry": {"coordinates":[-5.6645,50.105499],"type":"Point"}
}