{
  "type": "Feature",
  "properties": {
    "addr:full":"258 High Street, Ponders End Enfield Greater London EN3 4HB",
    "addr:housenumber":"258",
    "addr:postcode":"en3 4hb",
    "addr:street":"High Street Ponders End",
    "iso:country":"GB",
    "sg:address":"258 High Street, Ponders End",
    "sg:city":"Enfield",
    "sg:classifiers":[
        {
            "category":"Personal",
            "type":"Services"
        },
        {
            "category":"Shopping",
            "subcategory":"Bridal",
            "type":"Retail Goods"
        }
    ],
    "sg:phone":"+44 20 8443 4061",
    "sg:postcode":"EN3 4HB",
    "sg:province":"Greater London",
    "sg:tags":[
        "shop",
        "gown",
        "wedding"
    ],
    "wof:name":"Celebrations",
    "wof:placetype":"venue"
},
  "geometry": {"coordinates":[-0.046502,51.649929],"type":"Point"}
}