{
  "type": "Feature",
  "properties": {
    "addr:full":"Unit 1 Wall Street, Cocker Trading Estate Blackpool Lancashire FY1 2EP",
    "addr:housenumber":"unit 1",
    "addr:postcode":"fy1 2ep",
    "addr:street":"Wall Street;Trading Estate",
    "iso:country":"GB",
    "sg:address":"Unit 1 Wall Street, Cocker Trading Estate",
    "sg:city":"Blackpool",
    "sg:classifiers":[
        {
            "category":"Home & Garden",
            "subcategory":"Home Furnishings",
            "type":"Retail Goods"
        }
    ],
    "sg:phone":"+44 1253 622002",
    "sg:postcode":"FY1 2EP",
    "sg:province":"Lancashire",
    "sg:tags":[
        "furnishers",
        "planner",
        "bedroom"
    ],
    "wof:name":"Honeycombe Furniture Design Ltd.",
    "wof:placetype":"venue"
},
  "geometry": {"coordinates":[-3.048144,53.825214],"type":"Point"}
}