{
  "type": "Feature",
  "properties": {
    "iso:country":"GB",
    "sg:address":"Taylors Yard, Union St",
    "sg:city":"Newport Pagnell",
    "sg:classifiers":[
        {
            "category":"Manufacturing",
            "subcategory":"Glass & Minerals",
            "type":"Manufacturing & Wholesale Goods"
        }
    ],
    "sg:phone":"+44 1908 615440",
    "sg:postcode":"MK16 8ET",
    "sg:province":"Buckinghamshire",
    "sg:tags":[
        "supp",
        "replacement"
    ],
    "wof:name":"D & R Glass",
    "wof:placetype":"venue"
},
  "geometry": {"coordinates":[-0.723019,52.086697],"type":"Point"}
}