{
  "type": "Feature",
  "properties": {
    "iso:country":"GB",
    "sg:address":"Kimada House, 442 Flixton Road",
    "sg:city":"Manchester",
    "sg:classifiers":[
        {
            "category":"Professional",
            "subcategory":"Employment Agencies",
            "type":"Services"
        }
    ],
    "sg:phone":"+44 161 746 8811",
    "sg:postcode":"M41 6EY",
    "sg:province":"Cheshire",
    "sg:tags":[
        "consultant"
    ],
    "wof:name":"Heads Employment Agency Ltd.",
    "wof:placetype":"venue"
},
  "geometry": {"coordinates":[-2.38443,53.44426],"type":"Point"}
}