{
  "type": "Feature",
  "properties": {
    "iso:country":"GB",
    "sg:address":"Froghall Lane",
    "sg:city":"Warrington",
    "sg:classifiers":[
        {
            "category":"Autos & Motor Vehicles",
            "subcategory":"Automobile Sales",
            "type":"Retail Goods"
        },
        {
            "category":"Autos & Motor Vehicles",
            "subcategory":"Motorcycle Sales",
            "type":"Retail Goods"
        }
    ],
    "sg:phone":"+44 1925 418572",
    "sg:postcode":"WA1 1UE",
    "sg:province":"Cheshire",
    "sg:tags":[
        "car",
        "used"
    ],
    "wof:name":"Bank Park Motors",
    "wof:placetype":"venue"
},
  "geometry": {"coordinates":[-2.603305,53.391968],"type":"Point"}
}