{
  "type": "Feature",
  "properties": {
    "addr:full":"Jacaranda Studio, Money Row Green Maidenhead Berkshire SL6 2NA",
    "addr:postcode":"sl6 2na",
    "addr:street":"Row Green",
    "iso:country":"GB",
    "sg:address":"Jacaranda Studio, Money Row Green",
    "sg:city":"Maidenhead",
    "sg:classifiers":[
        {
            "category":"Professional",
            "type":"Services"
        }
    ],
    "sg:postcode":"SL6 2NA",
    "sg:province":"Berkshire",
    "sg:tags":[
        "entertainer"
    ],
    "wof:name":"Jacaranda Childrens Entertainer",
    "wof:placetype":"venue"
},
  "geometry": {"coordinates":[-0.727257,51.522373],"type":"Point"}
}