{
  "type": "Feature",
  "properties": {
    "addr:full":"102 St. Georges Rd Brighton East Sussex BN2 1EA",
    "addr:housenumber":"102",
    "addr:postcode":"bn2 1ea",
    "addr:street":"St. Georges Rd",
    "iso:country":"GB",
    "sg:address":"102 St. Georges Rd",
    "sg:city":"Brighton",
    "sg:classifiers":[
        {
            "category":"Food & Beverages",
            "subcategory":"Liquor & Beverages",
            "type":"Retail Goods"
        }
    ],
    "sg:phone":"+44 1273 626235",
    "sg:postcode":"BN2 1EA",
    "sg:province":"East Sussex",
    "sg:tags":[
        "beer",
        "spirit",
        "wines"
    ],
    "wof:name":"Victoria Wine Company",
    "wof:placetype":"venue"
},
  "geometry": {"coordinates":[-0.122906,50.818893],"type":"Point"}
}