{
  "type": "Feature",
  "properties": {
    "addr:full":"9 Gladys Av Waterlooville Hampshire PO8 8HT",
    "addr:housenumber":"9",
    "addr:postcode":"po8 8ht",
    "addr:street":"Gladys Av Waterlooville",
    "iso:country":"GB",
    "sg:address":"9 Gladys Av",
    "sg:city":"Waterlooville",
    "sg:classifiers":[
        {
            "category":"Building & Trades",
            "subcategory":"Construction",
            "type":"Services"
        }
    ],
    "sg:phone":"+44 23 9223 0342",
    "sg:postcode":"PO8 8HT",
    "sg:province":"Hampshire",
    "sg:tags":[
        "decorator",
        "painter"
    ],
    "wof:name":"T E Eggleton",
    "wof:placetype":"venue"
},
  "geometry": {"coordinates":[-1.018576,50.899372],"type":"Point"}
}