{
  "type": "Feature",
  "properties": {
    "iso:country":"GB",
    "sg:address":"47 Westwood Avenue",
    "sg:city":"Kendal",
    "sg:classifiers":[
        {
            "category":"Real Estate",
            "subcategory":"Surveying",
            "type":"Services"
        }
    ],
    "sg:phone":"+44 1539 726353",
    "sg:postcode":"LA9 5BB",
    "sg:province":"Cumbria",
    "sg:tags":[
        "surveyor",
        "valuer"
    ],
    "wof:name":"D V EDMONDSON",
    "wof:placetype":"venue"
},
  "geometry": {"coordinates":[-2.755184,54.317558],"type":"Point"}
}