{
  "type": "Feature",
  "properties": {
    "addr:full":"15 Wardour Street London Greater London W1D 6PX",
    "addr:housenumber":"15",
    "addr:postcode":"w1d 6px",
    "addr:street":"Wardour Street",
    "iso:country":"GB",
    "sg:address":"15 Wardour Street",
    "sg:city":"London",
    "sg:classifiers":[
        {
            "category":"Restaurant",
            "type":"Food & Drink"
        }
    ],
    "sg:phone":"+44 20 7437 5065",
    "sg:postcode":"W1D 6PX",
    "sg:province":"Greater London",
    "sg:tags":[
        "chinese"
    ],
    "wof:name":"The London Jade Garden",
    "wof:placetype":"venue"
},
  "geometry": {"coordinates":[-0.1319500059,51.510799408],"type":"Point"}
}