{
  "type": "Feature",
  "properties": {
    "addr:full":"519 Clarkston Road Glasgow East Renfrewshire G44 3PN",
    "addr:housenumber":"519",
    "addr:postcode":"g44 3pn",
    "addr:street":"Clarkston Road",
    "iso:country":"GB",
    "sg:address":"519 Clarkston Road",
    "sg:city":"Glasgow",
    "sg:classifiers":[
        {
            "category":"Professional",
            "subcategory":"Art Services",
            "type":"Services"
        }
    ],
    "sg:phone":"+44 141 633 3606",
    "sg:postcode":"G44 3PN",
    "sg:province":"East Renfrewshire",
    "sg:tags":[
        "picture",
        "framing"
    ],
    "wof:name":"Muirend Picture Framers",
    "wof:placetype":"venue"
},
  "geometry": {"coordinates":[-4.271624,55.808945],"type":"Point"}
}