{
  "type": "Feature",
  "properties": {
    "addr:full":"Canal Side Welshpool Shropshire SY21 7AH",
    "addr:postcode":"sy21 7ah",
    "addr:street":"Canal Side",
    "iso:country":"GB",
    "sg:address":"Canal Side",
    "sg:city":"Welshpool",
    "sg:classifiers":[
        {
            "category":"Manufacturing",
            "subcategory":"Building Materials",
            "type":"Manufacturing & Wholesale Goods"
        }
    ],
    "sg:phone":"+44 1938 552533",
    "sg:postcode":"SY21 7AH",
    "sg:province":"Shropshire",
    "sg:tags":[
        "merchant",
        "builder"
    ],
    "wof:name":"Travis Perkins Trading Co. Ltd.",
    "wof:placetype":"venue"
},
  "geometry": {"coordinates":[-3.146123,52.657398],"type":"Point"}
}