{
  "type": "Feature",
  "properties": {
    "addr:full":"Derby Road Loughborough Leicestershire LE11 5AH",
    "addr:postcode":"le11 5ah",
    "addr:street":"Derby Road",
    "iso:country":"GB",
    "sg:address":"Derby Road",
    "sg:city":"Loughborough",
    "sg:classifiers":[
        {
            "category":"Autos & Motor Vehicles",
            "subcategory":"Automobile Sales",
            "type":"Retail Goods"
        }
    ],
    "sg:phone":"+44 1509 213232",
    "sg:postcode":"LE11 5AH",
    "sg:province":"Leicestershire",
    "sg:tags":[
        "commercial"
    ],
    "wof:name":"Moseley (Continental Coachwork) Ltd.",
    "wof:placetype":"venue"
},
  "geometry": {"coordinates":[-1.220399,52.779541],"type":"Point"}
}