{
  "type": "Feature",
  "properties": {
    "addr:full":"P O Box 4725, Twyford Reading Berkshire RG10 0YG",
    "addr:housenumber":"p o;4725",
    "addr:postcode":"rg10 0yg",
    "addr:street":"Twyford",
    "iso:country":"GB",
    "sg:address":"P O Box 4725, Twyford",
    "sg:city":"Reading",
    "sg:classifiers":[
        {
            "category":"Farming",
            "subcategory":"Farm",
            "type":"Manufacturing & Wholesale Goods"
        }
    ],
    "sg:postcode":"RG10 0YG",
    "sg:province":"Berkshire",
    "sg:tags":[
        "agricultural"
    ],
    "wof:name":"I I S D Ltd.",
    "wof:placetype":"venue"
},
  "geometry": {"coordinates":[-0.8528860211,51.4585494995],"type":"Point"}
}