{
  "type": "Feature",
  "properties": {
    "iso:country":"GB",
    "sg:address":"Lodge 65 Overstone Golf Course, Billing Lane, Overstone",
    "sg:city":"Northampton",
    "sg:classifiers":[
        {
            "category":"Building & Trades",
            "subcategory":"Construction",
            "type":"Services"
        }
    ],
    "sg:phone":"+44 1908 392121",
    "sg:postcode":"NN6 0AP",
    "sg:province":"Northamptonshire",
    "sg:tags":[
        "builder"
    ],
    "wof:name":"M S Building Services Ltd.",
    "wof:placetype":"venue"
},
  "geometry": {"coordinates":[-0.813489,52.291874],"type":"Point"}
}