{
  "type": "Feature",
  "properties": {
    "iso:country":"GB",
    "sg:address":"19 Ash Road, Barnsbury Estate",
    "sg:city":"Woking",
    "sg:classifiers":[
        {
            "category":"Building & Trades",
            "subcategory":"Construction",
            "type":"Services"
        }
    ],
    "sg:phone":"+44 1483 722184",
    "sg:postcode":"GU22 0BJ",
    "sg:province":"Surrey",
    "sg:tags":[
        "decorator",
        "painter"
    ],
    "wof:name":"Lawrence Michael Interior & Exterior Decorating",
    "wof:placetype":"venue"
},
  "geometry": {"coordinates":[-0.56726,51.304909],"type":"Point"}
}