{
  "type": "Feature",
  "properties": {
    "iso:country":"GB",
    "sg:address":"50a Bolton Street",
    "sg:city":"Bury",
    "sg:classifiers":[
        {
            "category":"Professional",
            "subcategory":"Printing & Photocopies",
            "type":"Services"
        }
    ],
    "sg:phone":"+44 161 761 3501",
    "sg:postcode":"BL9 0LL",
    "sg:province":"Lancashire",
    "sg:tags":[
        "printer"
    ],
    "wof:name":"Rosehill Printers & Converters Ltd.",
    "wof:placetype":"venue"
},
  "geometry": {"coordinates":[-2.300385,53.593849],"type":"Point"}
}