{
  "type": "Feature",
  "properties": {
    "iso:country":"GB",
    "sg:address":"201 Wolseley Rd",
    "sg:city":"Plymouth",
    "sg:classifiers":[
        {
            "category":"Food & Beverages",
            "subcategory":"Bakery",
            "type":"Retail Goods"
        }
    ],
    "sg:phone":"+44 1752 605361",
    "sg:postcode":"PL2 2DX",
    "sg:province":"Devon",
    "sg:tags":[
        "baker"
    ],
    "wof:name":"Warrens",
    "wof:placetype":"venue"
},
  "geometry": {"coordinates":[-4.178139,50.39534],"type":"Point"}
}