{
  "type": "Feature",
  "properties": {
    "addr:full":"147 Hermit Road London Greater London E16 4LE",
    "addr:housenumber":"147",
    "addr:postcode":"e16 4le",
    "addr:street":"Hermit Road",
    "iso:country":"GB",
    "sg:address":"147 Hermit Road",
    "sg:city":"London",
    "sg:classifiers":[
        {
            "category":"Fast Food",
            "type":"Food & Drink"
        }
    ],
    "sg:phone":"+44 20 7237 7015",
    "sg:postcode":"E16 4LE",
    "sg:province":"Greater London",
    "sg:tags":[
        "away",
        "meal",
        "outlet",
        "take"
    ],
    "wof:name":"SILVER SEA",
    "wof:placetype":"venue"
},
  "geometry": {"coordinates":[0.012098,51.52211],"type":"Point"}
}