{
  "type": "Feature",
  "properties": {
    "addr:full":"Ardleigh Green Road Hornchurch Essex RM11 2JY",
    "addr:postcode":"rm11 2jy",
    "addr:street":"Ardleigh Green Road",
    "iso:country":"GB",
    "sg:address":"Ardleigh Green Road",
    "sg:city":"Hornchurch",
    "sg:classifiers":[
        {
            "category":"Bars & Pubs",
            "type":"Food & Drink"
        }
    ],
    "sg:phone":"+44 1708 442550",
    "sg:postcode":"RM11 2JY",
    "sg:province":"Essex",
    "sg:tags":[
        "pubs",
        "inn"
    ],
    "wof:name":"The Spencers Arms",
    "wof:placetype":"venue"
},
  "geometry": {"coordinates":[0.2224750072,51.5864562988],"type":"Point"}
}