{
  "type": "Feature",
  "properties": {
    "addr:full":"215 Lower Mortlake Road Richmond Greater London TW9 2LN",
    "addr:housenumber":"215",
    "addr:postcode":"tw9 2ln",
    "addr:street":"Lower Mortlake Road",
    "iso:country":"GB",
    "sg:address":"215 Lower Mortlake Road",
    "sg:city":"Richmond",
    "sg:classifiers":[
        {
            "category":"Food & Beverages",
            "subcategory":"Bakery",
            "type":"Retail Goods"
        }
    ],
    "sg:phone":"+44 20 8332 9030",
    "sg:postcode":"TW9 2LN",
    "sg:province":"Greater London",
    "sg:tags":[
        "baker"
    ],
    "wof:name":"The Bakewell Cake Co.",
    "wof:placetype":"venue"
},
  "geometry": {"coordinates":[-0.292486012,51.4664764404],"type":"Point"}
}