{
  "type": "Feature",
  "properties": {
    "addr:full":"87 Lee Gate Bolton Lancashire BL2 4BQ",
    "addr:housenumber":"87",
    "addr:postcode":"bl2 4bq",
    "addr:street":"Lee Gate",
    "iso:country":"GB",
    "sg:address":"87 Lee Gate",
    "sg:city":"Bolton",
    "sg:classifiers":[
        {
            "category":"Shopping",
            "subcategory":"Clothing, Apparel, & Fashions",
            "type":"Retail Goods"
        }
    ],
    "sg:phone":"+44 1204 302272",
    "sg:postcode":"BL2 4BQ",
    "sg:province":"Lancashire",
    "sg:tags":[
        "shop"
    ],
    "wof:name":"Labels for Less",
    "wof:placetype":"venue"
},
  "geometry": {"coordinates":[-2.3973329067,53.6068305969],"type":"Point"}
}