{
  "type": "Feature",
  "properties": {
    "addr:full":"90 Westgate Guisborough North Yorkshire TS14 6AP",
    "addr:housenumber":"90",
    "addr:postcode":"ts14 6ap",
    "addr:street":"Westgate Guisborough",
    "iso:country":"GB",
    "sg:address":"90 Westgate",
    "sg:city":"Guisborough",
    "sg:classifiers":[
        {
            "category":"Education",
            "subcategory":"Library",
            "type":"Public Place"
        },
        {
            "category":"Government",
            "subcategory":"Office",
            "type":"Public Place"
        }
    ],
    "sg:phone":"+44 1287 632668",
    "sg:postcode":"TS14 6AP",
    "sg:province":"North Yorkshire",
    "sg:tags":[
        "book",
        "local"
    ],
    "wof:name":"Guisborough Branch Library",
    "wof:placetype":"venue"
},
  "geometry": {"coordinates":[-1.0565999746,54.5346412659],"type":"Point"}
}