{
  "type": "Feature",
  "properties": {
    "iso:country":"GB",
    "sg:address":"The Nursery Site, Hixberry Lane",
    "sg:city":"St Albans",
    "sg:classifiers":[
        {
            "category":"Government",
            "subcategory":"Office",
            "type":"Public Place"
        }
    ],
    "sg:phone":"+44 1727 848168",
    "sg:postcode":"AL4 0TZ",
    "sg:province":"Hertfordshire",
    "sg:tags":[
        "local"
    ],
    "wof:name":"Countryside Management Service",
    "wof:placetype":"venue"
},
  "geometry": {"coordinates":[-0.29359,51.748909],"type":"Point"}
}