{
  "type": "Feature",
  "properties": {
    "iso:country":"GB",
    "sg:address":"12 London Rd",
    "sg:city":"Nottingham",
    "sg:classifiers":[
        {
            "category":"Utilities",
            "subcategory":"Natural Gas",
            "type":"Services"
        }
    ],
    "sg:phone":"+44 115 950 2816",
    "sg:postcode":"NG2 3AB",
    "sg:province":"Nottinghamshire",
    "sg:tags":[
        "control",
        "energy",
        "management",
        "system"
    ],
    "wof:name":"A H S Emstar PLC",
    "wof:placetype":"venue"
},
  "geometry": {"coordinates":[-1.14045,52.948811],"type":"Point"}
}