{
  "type": "Feature",
  "properties": {
    "iso:country":"GB",
    "sg:address":"Communications Ho, 13-17 All Hallows Rd",
    "sg:city":"Blackpool",
    "sg:classifiers":[
        {
            "category":"Manufacturing",
            "subcategory":"Metals",
            "type":"Manufacturing & Wholesale Goods"
        }
    ],
    "sg:phone":"+44 1253 596922",
    "sg:postcode":"FY2 0AS",
    "sg:province":"Lancashire",
    "sg:tags":[
        "steel",
        "stockholder"
    ],
    "wof:name":"Atlas Re-Inforcements Ltd",
    "wof:placetype":"venue"
},
  "geometry": {"coordinates":[-3.0391,53.852829],"type":"Point"}
}