{
  "type": "Feature",
  "properties": {
    "iso:country":"GB",
    "sg:address":"187 Meriden Drive",
    "sg:city":"Birmingham",
    "sg:classifiers":[
        {
            "category":"Home & Garden",
            "subcategory":"Garden Supply",
            "type":"Retail Goods"
        },
        {
            "category":"Building & Trades",
            "subcategory":"Construction",
            "type":"Services"
        }
    ],
    "sg:phone":"+44 121 770 6226",
    "sg:postcode":"B37 6BT",
    "sg:province":"West Midlands",
    "sg:tags":[
        "equipment",
        "playground",
        "contractor"
    ],
    "wof:name":"John Berry",
    "wof:placetype":"venue"
},
  "geometry": {"coordinates":[-1.7439899445,52.4928741455],"type":"Point"}
}