{
  "type": "Feature",
  "properties": {
    "iso:country":"GB",
    "sg:address":"Unit 53 Heming Road, Washford",
    "sg:city":"Redditch",
    "sg:classifiers":[
        {
            "category":"Professional",
            "subcategory":"Business Services",
            "type":"Services"
        }
    ],
    "sg:phone":"+44 1527 510755",
    "sg:postcode":"B98 0DZ",
    "sg:province":"Warwickshire",
    "sg:tags":[
        "distribution"
    ],
    "wof:name":"Valeo Service Uk Ltd.",
    "wof:placetype":"venue"
},
  "geometry": {"coordinates":[-1.894309,52.287804],"type":"Point"}
}