{
  "type": "Feature",
  "properties": {
    "addr:full":"84 Mill Lane, West Derby Liverpool Merseyside L12 7JD",
    "addr:housenumber":"84",
    "addr:postcode":"l12 7jd",
    "addr:street":"Mill Lane West Derby",
    "iso:country":"GB",
    "sg:address":"84 Mill Lane, West Derby",
    "sg:city":"Liverpool",
    "sg:classifiers":[
        {
            "category":"Shopping",
            "subcategory":"News",
            "type":"Retail Goods"
        }
    ],
    "sg:phone":"+44 151 226 1597",
    "sg:postcode":"L12 7JD",
    "sg:province":"Merseyside",
    "sg:tags":[
        "newsagent"
    ],
    "wof:name":"A & M HIGHAM",
    "wof:placetype":"venue"
},
  "geometry": {"coordinates":[-2.9113769531,53.4303512573],"type":"Point"}
}