{
  "type": "Feature",
  "properties": {
    "addr:full":"Caxton Hill, Ware Road Hertford Hertfordshire SG13 7LU",
    "addr:postcode":"sg13 7lu",
    "addr:street":"Caxton;Ware Road",
    "iso:country":"GB",
    "sg:address":"Caxton Hill, Ware Road",
    "sg:city":"Hertford",
    "sg:classifiers":[
        {
            "category":"Professional",
            "subcategory":"Printing & Photocopies",
            "type":"Services"
        }
    ],
    "sg:postcode":"SG13 7LU",
    "sg:province":"Hertfordshire",
    "sg:tags":[
        "printer"
    ],
    "wof:name":"Tydale Enterprises Ltd.",
    "wof:placetype":"venue"
},
  "geometry": {"coordinates":[-0.0633419976,51.7958908081],"type":"Point"}
}