{
  "type": "Feature",
  "properties": {
    "addr:full":"20 Abbey Court Battle East Sussex TN33 0TZ",
    "addr:housenumber":"20",
    "addr:postcode":"tn33 0tz",
    "addr:street":"Abbey Court",
    "iso:country":"GB",
    "sg:address":"20 Abbey Court",
    "sg:city":"Battle",
    "sg:classifiers":[
        {
            "category":"Home & Garden",
            "subcategory":"Furniture",
            "type":"Retail Goods"
        }
    ],
    "sg:postcode":"TN33 0TZ",
    "sg:province":"East Sussex",
    "wof:name":"Mrs P Kirk",
    "wof:placetype":"venue"
},
  "geometry": {"coordinates":[0.4857349992,50.9169502258],"type":"Point"}
}