{
  "type": "Feature",
  "properties": {
    "addr:full":"2 Winchester Street Whitchurch Hampshire RG28 7AL",
    "addr:housenumber":"2",
    "addr:postcode":"rg28 7al",
    "addr:street":"Winchester Street",
    "iso:country":"GB",
    "sg:address":"2 Winchester Street",
    "sg:city":"Whitchurch",
    "sg:classifiers":[
        {
            "category":"Retail",
            "subcategory":"Laundry & Dry Cleaning",
            "type":"Services"
        }
    ],
    "sg:postcode":"RG28 7AL",
    "sg:province":"Hampshire",
    "sg:tags":[
        "alteration"
    ],
    "wof:name":"Finishing Touch",
    "wof:placetype":"venue"
},
  "geometry": {"coordinates":[-1.3390320539,51.2297554016],"type":"Point"}
}