{
  "type": "Feature",
  "properties": {
    "iso:country":"GB",
    "sg:address":"Culver Pde",
    "sg:city":"Sandown",
    "sg:classifiers":[
        {
            "category":"Cafe",
            "type":"Food & Drink"
        }
    ],
    "sg:phone":"+44 1983 408500",
    "sg:postcode":"PO36 8AT",
    "sg:province":"Isle of Wight",
    "sg:tags":[
        "tea",
        "room"
    ],
    "wof:name":"Wight City Cafeteria",
    "wof:placetype":"venue"
},
  "geometry": {"coordinates":[-1.145524025,50.6575698853],"type":"Point"}
}