{
  "type": "Feature",
  "properties": {
    "addr:full":"183 New Rd Ferndown Dorset BH22 8ED",
    "addr:housenumber":"183",
    "addr:postcode":"bh22 8ed",
    "addr:street":"New Rd",
    "iso:country":"GB",
    "sg:address":"183 New Rd",
    "sg:city":"Ferndown",
    "sg:classifiers":[
        {
            "category":"Health Services",
            "subcategory":"Dentist",
            "type":"Services"
        }
    ],
    "sg:phone":"+44 1202 573411",
    "sg:postcode":"BH22 8ED",
    "sg:province":"Dorset",
    "wof:name":"O G Roberts",
    "wof:placetype":"venue"
},
  "geometry": {"coordinates":[-1.8819190264,50.7813301086],"type":"Point"}
}