{
  "type": "Feature",
  "properties": {
    "addr:full":"20 Atholl Street Preston Lancashire PR1 8TA",
    "addr:housenumber":"20",
    "addr:postcode":"pr1 8ta",
    "addr:street":"Atholl Street",
    "iso:country":"GB",
    "sg:address":"20 Atholl Street",
    "sg:city":"Preston",
    "sg:classifiers":[
        {
            "category":"Shopping",
            "subcategory":"Stationery & Office Supplies",
            "type":"Retail Goods"
        },
        {
            "category":"Professional",
            "subcategory":"Printing & Photocopies",
            "type":"Services"
        }
    ],
    "sg:phone":"+44 1772 204845",
    "sg:postcode":"PR1 8TA",
    "sg:province":"Lancashire",
    "sg:tags":[
        "finishing",
        "tag",
        "computer",
        "label"
    ],
    "wof:name":"Kontakt Labels",
    "wof:placetype":"venue"
},
  "geometry": {"coordinates":[-2.7149240971,53.7605705261],"type":"Point"}
}