{
  "type": "Feature",
  "properties": {
    "addr:full":"272 Ermin Street, Stratton St Margaret Swindon Wiltshire SN3 4LW",
    "addr:housenumber":"272",
    "addr:postcode":"sn3 4lw",
    "addr:street":"Ermin Street",
    "iso:country":"GB",
    "sg:address":"272 Ermin Street, Stratton St Margaret",
    "sg:city":"Swindon",
    "sg:classifiers":[
        {
            "category":"Retail",
            "subcategory":"Auto Rental",
            "type":"Services"
        }
    ],
    "sg:phone":"+44 1793 822193",
    "sg:postcode":"SN3 4LW",
    "sg:province":"Wiltshire",
    "sg:tags":[
        "car"
    ],
    "wof:name":"Duncan Self Drive Ltd.",
    "wof:placetype":"venue"
},
  "geometry": {"coordinates":[-1.7409199476,51.5785102844],"type":"Point"}
}