{
  "type": "Feature",
  "properties": {
    "addr:full":"The Coach House, 106 Dover Road Folkestone Kent CT20 1NN",
    "addr:housenumber":"106",
    "addr:postcode":"ct20 1nn",
    "addr:street":"Dover Road",
    "iso:country":"GB",
    "sg:address":"The Coach House, 106 Dover Road",
    "sg:city":"Folkestone",
    "sg:classifiers":[
        {
            "category":"Shopping",
            "subcategory":"Books",
            "type":"Retail Goods"
        }
    ],
    "sg:phone":"+44 1303 220567",
    "sg:postcode":"CT20 1NN",
    "sg:province":"Kent",
    "sg:tags":[
        "second-hand"
    ],
    "wof:name":"Harrison Barrie Ltd.",
    "wof:placetype":"venue"
},
  "geometry": {"coordinates":[1.1856050491,51.0841293335],"type":"Point"}
}