{
  "type": "Feature",
  "properties": {
    "addr:full":"22 Davaar Ave Cumnock East Ayrshire KA18 3BE",
    "addr:housenumber":"22",
    "addr:postcode":"ka18 3be",
    "addr:street":"Davaar Ave",
    "iso:country":"GB",
    "sg:address":"22 Davaar Ave",
    "sg:city":"Cumnock",
    "sg:classifiers":[
        {
            "category":"Shopping",
            "subcategory":"Computers & Home Electronics",
            "type":"Retail Goods"
        }
    ],
    "sg:postcode":"KA18 3BE",
    "sg:province":"East Ayrshire",
    "sg:tags":[
        "aerial",
        "television",
        "radio"
    ],
    "wof:name":"Bell,Ian,Aerials",
    "wof:placetype":"venue"
},
  "geometry": {"coordinates":[-4.2411789894,55.4407653809],"type":"Point"}
}