{
  "type": "Feature",
  "properties": {
    "addr:full":"122 Alexandra Park Rd Muswell Hill Greater London N10 2AH",
    "addr:housenumber":"122",
    "addr:postcode":"n10 2ah",
    "addr:street":"Alexandra Park Rd",
    "iso:country":"GB",
    "sg:address":"122 Alexandra Park Rd",
    "sg:city":"Muswell Hill",
    "sg:classifiers":[
        {
            "category":"Food & Beverages",
            "subcategory":"Supermarket",
            "type":"Retail Goods"
        }
    ],
    "sg:phone":"+44 20 8883 9292",
    "sg:postcode":"N10 2AH",
    "sg:province":"Greater London",
    "wof:name":"Capital Supermarket",
    "wof:placetype":"venue"
},
  "geometry": {"coordinates":[-0.1434269994,51.6068115234],"type":"Point"}
}