{
  "type": "Feature",
  "properties": {
    "addr:full":"14 Liscard Way Wallasey Merseyside L44 5TP",
    "addr:housenumber":"14",
    "addr:postcode":"l44 5tp",
    "addr:street":"Liscard Way",
    "iso:country":"GB",
    "sg:address":"14 Liscard Way",
    "sg:city":"Wallasey",
    "sg:classifiers":[
        {
            "category":"Shopping",
            "subcategory":"Discount & Variety Stores",
            "type":"Retail Goods"
        }
    ],
    "sg:phone":"+44 151 638 5856",
    "sg:postcode":"L44 5TP",
    "sg:province":"Merseyside",
    "sg:tags":[
        "centre"
    ],
    "wof:name":"Pound Lines Extra",
    "wof:placetype":"venue"
},
  "geometry": {"coordinates":[-3.0429620743,53.4193649292],"type":"Point"}
}