{
  "type": "Feature",
  "properties": {
    "iso:country":"GB",
    "sg:address":"Clayton Street",
    "sg:city":"Blackburn",
    "sg:classifiers":[
        {
            "category":"Community Center",
            "subcategory":"Youth",
            "type":"Public Place"
        }
    ],
    "sg:phone":"+44 1254 663537",
    "sg:postcode":"BB2 2ED",
    "sg:province":"Lancashire",
    "sg:tags":[
        "organisation",
        "centre"
    ],
    "wof:name":"West End Youth & Community Centre",
    "wof:placetype":"venue"
},
  "geometry": {"coordinates":[-2.486139,53.746269],"type":"Point"}
}