{
  "type": "Feature",
  "properties": {
    "addr:full":"High Road Buckhurst Hill Essex IG9 5RX",
    "addr:postcode":"ig9 5rx",
    "addr:street":"High Road",
    "iso:country":"GB",
    "sg:address":"High Road",
    "sg:city":"Buckhurst Hill",
    "sg:classifiers":[
        {
            "category":"Place Of Worship",
            "type":"Public Place"
        },
        {
            "category":"Education",
            "subcategory":"School",
            "type":"Public Place"
        }
    ],
    "sg:phone":"+44 20 8504 2934",
    "sg:postcode":"IG9 5RX",
    "sg:province":"Essex",
    "sg:tags":[
        "local",
        "authority"
    ],
    "wof:name":"St. Johns C of E Primary School",
    "wof:placetype":"venue"
},
  "geometry": {"coordinates":[0.0373400003,51.6328849792],"type":"Point"}
}