{
  "type": "Feature",
  "properties": {
    "addr:full":"64 Cheriton High Street Folkestone Kent CT19 4HB",
    "addr:housenumber":"64",
    "addr:postcode":"ct19 4hb",
    "addr:street":"Cheriton High Street",
    "iso:country":"GB",
    "sg:address":"64 Cheriton High Street",
    "sg:city":"Folkestone",
    "sg:classifiers":[
        {
            "category":"Education",
            "subcategory":"Library",
            "type":"Public Place"
        }
    ],
    "sg:phone":"+44 1303 275163",
    "sg:postcode":"CT19 4HB",
    "sg:province":"Kent",
    "sg:tags":[
        "book"
    ],
    "wof:name":"Cheriton Library",
    "wof:placetype":"venue"
},
  "geometry": {"coordinates":[1.1420890093,51.0881309509],"type":"Point"}
}