{
  "type": "Feature",
  "properties": {
    "iso:country":"GB",
    "sg:address":"24 Belcombe Rd",
    "sg:city":"Bradford On Avon",
    "sg:classifiers":[
        {
            "category":"Wholesale",
            "subcategory":"Fruits & Vegetables",
            "type":"Manufacturing & Wholesale Goods"
        }
    ],
    "sg:phone":"+44 1225 863132",
    "sg:postcode":"BA15 1LZ",
    "sg:province":"Wiltshire",
    "wof:name":"G G Brown",
    "wof:placetype":"venue"
},
  "geometry": {"coordinates":[-2.260695,51.344688],"type":"Point"}
}