{
  "type": "Feature",
  "properties": {
    "iso:country":"GB",
    "sg:address":"92 Old Bath Road, Charvil",
    "sg:city":"Reading",
    "sg:classifiers":[
        {
            "category":"Professional",
            "subcategory":"Art Services",
            "type":"Services"
        }
    ],
    "sg:postcode":"RG10 9QJ",
    "sg:province":"Berkshire",
    "sg:tags":[
        "photographer"
    ],
    "wof:name":"M & K F Martin Photographers",
    "wof:placetype":"venue"
},
  "geometry": {"coordinates":[-0.881822,51.477879],"type":"Point"}
}