{
  "type": "Feature",
  "properties": {
    "iso:country":"GB",
    "sg:address":"Suite E, Gostrey House, Union Road",
    "sg:city":"Farnham",
    "sg:classifiers":[
        {
            "category":"Manufacturing",
            "subcategory":"Electronics",
            "type":"Manufacturing & Wholesale Goods"
        }
    ],
    "sg:phone":"+44 1252 726200",
    "sg:postcode":"GU9 7PT",
    "sg:province":"Surrey",
    "sg:tags":[
        "control",
        "component",
        "-",
        "electronic"
    ],
    "wof:name":"Efore (U K) Ltd.",
    "wof:placetype":"venue"
},
  "geometry": {"coordinates":[-0.796429,51.213661],"type":"Point"}
}