{
  "type": "Feature",
  "properties": {
    "addr:full":"Unit 5, Sandallstone Road, Kirk Sandall Industrial Estate Doncaster South Yorkshire DN3 1QR",
    "addr:housenumber":"unit 5;estate",
    "addr:postcode":"dn3 1qr",
    "addr:street":"Sandallstone Road Kirk;Industrial",
    "iso:country":"GB",
    "sg:address":"Unit 5, Sandallstone Road, Kirk Sandall Industrial Estate",
    "sg:city":"Doncaster",
    "sg:classifiers":[
        {
            "category":"Retail",
            "subcategory":"Auto Repair",
            "type":"Services"
        }
    ],
    "sg:phone":"+44 1302 888811",
    "sg:postcode":"DN3 1QR",
    "sg:province":"South Yorkshire",
    "sg:tags":[
        "bodybuilder",
        "repairer"
    ],
    "wof:name":"Excel Conversions Ltd.",
    "wof:placetype":"venue"
},
  "geometry": {"coordinates":[-1.0736390352,53.5617599487],"type":"Point"}
}