{
  "type": "Feature",
  "properties": {
    "addr:full":"The Delph Centre, Civic Way Swadlincote Derbyshire DE11 0AD",
    "addr:postcode":"de11 0ad",
    "addr:street":"Civic Way",
    "iso:country":"GB",
    "sg:address":"The Delph Centre, Civic Way",
    "sg:city":"Swadlincote",
    "sg:classifiers":[
        {
            "category":"Bars & Pubs",
            "subcategory":"Wine Bar",
            "type":"Food & Drink"
        }
    ],
    "sg:postcode":"DE11 0AD",
    "sg:province":"Derbyshire",
    "wof:name":"Dephi Wine Bar",
    "wof:placetype":"venue"
},
  "geometry": {"coordinates":[-1.552209,52.774094],"type":"Point"}
}