{
  "type": "Feature",
  "properties": {
    "addr:full":"18 Northfield Avenue, Ealing London Greater London W13 9RJ",
    "addr:housenumber":"18",
    "addr:postcode":"w13 9rj",
    "addr:street":"Northfield Avenue",
    "iso:country":"GB",
    "sg:address":"18 Northfield Avenue, Ealing",
    "sg:city":"London",
    "sg:classifiers":[
        {
            "category":"Shopping",
            "subcategory":"Department Store",
            "type":"Retail Goods"
        }
    ],
    "sg:postcode":"W13 9RJ",
    "sg:province":"Greater London",
    "wof:name":"Northfield Discount Stores",
    "wof:placetype":"venue"
},
  "geometry": {"coordinates":[-0.3195070028,51.5052452087],"type":"Point"}
}