{
  "type": "Feature",
  "properties": {
    "iso:country":"GB",
    "sg:address":"2a Heaton Street",
    "sg:city":"Blackburn",
    "sg:classifiers":[
        {
            "category":"Professional",
            "subcategory":"Business Services",
            "type":"Services"
        },
        {
            "category":"Manufacturing",
            "subcategory":"Signs",
            "type":"Manufacturing & Wholesale Goods"
        }
    ],
    "sg:phone":"+44 1254 677855",
    "sg:postcode":"BB2 2EF",
    "sg:province":"Lancashire",
    "sg:tags":[
        "poster",
        "writer",
        "designer"
    ],
    "wof:name":"The Sign & Poster Studio",
    "wof:placetype":"venue"
},
  "geometry": {"coordinates":[-2.486700058,53.7463798523],"type":"Point"}
}