{
  "type": "Feature",
  "properties": {
    "addr:full":"Burns Road Middlesbrough North Yorkshire TS6 9AW",
    "addr:postcode":"ts6 9aw",
    "addr:street":"Burns Road",
    "iso:country":"GB",
    "sg:address":"Burns Road",
    "sg:city":"Middlesbrough",
    "sg:classifiers":[
        {
            "category":"Education",
            "subcategory":"School",
            "type":"Public Place"
        }
    ],
    "sg:phone":"+44 1642 466101",
    "sg:postcode":"TS6 9AW",
    "sg:province":"North Yorkshire",
    "sg:tags":[
        "local",
        "authority"
    ],
    "wof:name":"Eston Park School",
    "wof:placetype":"venue"
},
  "geometry": {"coordinates":[-1.1580859423,54.5656051636],"type":"Point"}
}