{
  "type": "Feature",
  "properties": {
    "iso:country":"GB",
    "sg:address":"7 Ratliffe Road",
    "sg:city":"Rugby",
    "sg:classifiers":[
        {
            "category":"Retail",
            "subcategory":"Repair Shop",
            "type":"Services"
        }
    ],
    "sg:phone":"+44 1788 811604",
    "sg:postcode":"CV22 6HB",
    "sg:province":"Warwickshire",
    "sg:tags":[
        "maintenance"
    ],
    "wof:name":"H C Chater Services Ltd.",
    "wof:placetype":"venue"
},
  "geometry": {"coordinates":[-1.273015,52.356758],"type":"Point"}
}