{
  "type": "Feature",
  "properties": {
    "addr:full":"Rumblingwell Dunfermline Fife KY12 9AP",
    "addr:postcode":"ky12 9ap",
    "iso:country":"GB",
    "sg:address":"Rumblingwell",
    "sg:city":"Dunfermline",
    "sg:classifiers":[
        {
            "category":"Autos & Motor Vehicles",
            "subcategory":"Fuel & Gas Station",
            "type":"Retail Goods"
        }
    ],
    "sg:postcode":"KY12 9AP",
    "sg:province":"Fife",
    "sg:tags":[
        "petrol",
        "filling"
    ],
    "wof:name":"Petrol Plus (Angus) Ltd.",
    "wof:placetype":"venue"
},
  "geometry": {"coordinates":[-3.484659,56.078804],"type":"Point"}
}