{
  "type": "Feature",
  "properties": {
    "addr:full":"4 Rope Walk Preston Lancashire PR3 1NS",
    "addr:housenumber":"4",
    "addr:postcode":"pr3 1ns",
    "addr:street":"Rope Walk",
    "iso:country":"GB",
    "sg:address":"4 Rope Walk",
    "sg:city":"Preston",
    "sg:classifiers":[
        {
            "category":"Professional",
            "subcategory":"Computer Services",
            "type":"Services"
        }
    ],
    "sg:phone":"+44 1995 602001",
    "sg:postcode":"PR3 1NS",
    "sg:province":"Lancashire",
    "sg:tags":[
        "system",
        "software"
    ],
    "wof:name":"X S Distribution Ltd",
    "wof:placetype":"venue"
},
  "geometry": {"coordinates":[-2.775589,53.901386],"type":"Point"}
}