{
  "type": "Feature",
  "properties": {
    "addr:full":"Heaselands Stables, Barham Canterbury Kent CT4 6QA",
    "addr:postcode":"ct4 6qa",
    "iso:country":"GB",
    "sg:address":"Heaselands Stables, Barham",
    "sg:city":"Canterbury",
    "sg:classifiers":[
        {
            "category":"Professional",
            "subcategory":"Management & Consulting",
            "type":"Services"
        }
    ],
    "sg:postcode":"CT4 6QA",
    "sg:province":"Kent",
    "sg:tags":[
        "consultant",
        "business"
    ],
    "wof:name":"Norman,Roy,Ltd",
    "wof:placetype":"venue"
},
  "geometry": {"coordinates":[1.1570949554,51.2022781372],"type":"Point"}
}