{
  "type": "Feature",
  "properties": {
    "addr:full":"South Street Oakham Leicestershire LE15 6BG",
    "addr:postcode":"le15 6bg",
    "addr:street":"South Street",
    "iso:country":"GB",
    "sg:address":"South Street",
    "sg:city":"Oakham",
    "sg:classifiers":[
        {
            "category":"Travel",
            "subcategory":"Hotels & Motels",
            "type":"Entertainment"
        }
    ],
    "sg:phone":"+44 1572 723330",
    "sg:postcode":"LE15 6BG",
    "sg:province":"Leicestershire",
    "wof:name":"Milburn Motel",
    "wof:placetype":"venue"
},
  "geometry": {"coordinates":[-0.729611,52.668957],"type":"Point"}
}