{
  "type": "Feature",
  "properties": {
    "addr:full":"Camden Mill, Lower Bristol Rd Bath Somerset BA2 3DQ",
    "addr:postcode":"ba2 3dq",
    "addr:street":"Camden;Lower Bristol Rd",
    "iso:country":"GB",
    "sg:address":"Camden Mill, Lower Bristol Rd",
    "sg:city":"Bath",
    "sg:classifiers":[
        {
            "category":"Banks & Credit Unions",
            "subcategory":"Financial Services",
            "type":"Services"
        }
    ],
    "sg:phone":"+44 1225 867599",
    "sg:postcode":"BA2 3DQ",
    "sg:province":"Somerset",
    "sg:tags":[
        "consultant"
    ],
    "wof:name":"Happold Trust Publications Ltd",
    "wof:placetype":"venue"
},
  "geometry": {"coordinates":[-2.3705840111,51.3796234131],"type":"Point"}
}