{
  "type": "Feature",
  "properties": {
    "addr:full":"7-9 Queen Street Forfar Angus DD8 3AJ",
    "addr:housenumber":"7-9",
    "addr:postcode":"dd8 3aj",
    "addr:street":"Queen Street",
    "iso:country":"GB",
    "sg:address":"7-9 Queen Street",
    "sg:city":"Forfar",
    "sg:classifiers":[
        {
            "category":"Professional",
            "subcategory":"Printing & Photocopies",
            "type":"Services"
        }
    ],
    "sg:phone":"+44 1307 464078",
    "sg:postcode":"DD8 3AJ",
    "sg:province":"Angus",
    "sg:tags":[
        "printer"
    ],
    "wof:name":"Neil A Robertson Printers & Stationers",
    "wof:placetype":"venue"
},
  "geometry": {"coordinates":[-2.888199,56.645237],"type":"Point"}
}