{
  "type": "Feature",
  "properties": {
    "addr:full":"3-5 High Street Princes Risborough Buckinghamshire HP27 0AE",
    "addr:housenumber":"3-5",
    "addr:postcode":"hp27 0ae",
    "addr:street":"High Street",
    "iso:country":"GB",
    "sg:address":"3-5 High Street",
    "sg:city":"Princes Risborough",
    "sg:classifiers":[
        {
            "category":"Communications",
            "type":"Services"
        }
    ],
    "sg:phone":"+44 1844 343196",
    "sg:postcode":"HP27 0AE",
    "sg:province":"Buckinghamshire",
    "sg:tags":[
        "tv",
        "video",
        "radio"
    ],
    "wof:name":"Teleline",
    "wof:placetype":"venue"
},
  "geometry": {"coordinates":[-0.8305900097,51.7230796814],"type":"Point"}
}