{
  "type": "Feature",
  "properties": {
    "iso:country":"GB",
    "sg:address":"1 Wortley Moor Lane Trading Esta, Te",
    "sg:city":"Leeds",
    "sg:classifiers":[
        {
            "category":"Manufacturing",
            "subcategory":"Metals",
            "type":"Manufacturing & Wholesale Goods"
        }
    ],
    "sg:phone":"+44 113 231 1093",
    "sg:postcode":"LS12 4HX",
    "sg:province":"West Yorkshire",
    "wof:name":"Acorn Nisil Ltd.",
    "wof:placetype":"venue"
},
  "geometry": {"coordinates":[-1.59716,53.792004],"type":"Point"}
}