{
  "type": "Feature",
  "properties": {
    "addr:full":"Victoria Rd, Horwich Bolton Lancashire BL6 5PH",
    "addr:postcode":"bl6 5ph",
    "addr:street":"Victoria Rd",
    "iso:country":"GB",
    "sg:address":"Victoria Rd, Horwich",
    "sg:city":"Bolton",
    "sg:classifiers":[
        {
            "category":"Education",
            "subcategory":"School",
            "type":"Public Place"
        }
    ],
    "sg:phone":"+44 1204 697144",
    "sg:postcode":"BL6 5PH",
    "sg:province":"Lancashire",
    "sg:tags":[
        "local",
        "authority"
    ],
    "wof:name":"St. Mary's R.C Primary School",
    "wof:placetype":"venue"
},
  "geometry": {"coordinates":[-2.541664,53.598499],"type":"Point"}
}