{
  "type": "Feature",
  "properties": {
    "addr:full":"18 Pearse Gro, Walton Pk Milton Keynes Buckinghamshire MK7 7HD",
    "addr:housenumber":"18",
    "addr:postcode":"mk7 7hd",
    "addr:street":"Pearse Gro Walton Pk",
    "iso:country":"GB",
    "sg:address":"18 Pearse Gro, Walton Pk",
    "sg:city":"Milton Keynes",
    "sg:classifiers":[
        {
            "category":"Social Services",
            "subcategory":"Adult Care",
            "type":"Services"
        }
    ],
    "sg:postcode":"MK7 7HD",
    "sg:province":"Buckinghamshire",
    "sg:tags":[
        "domestic",
        "cleaning"
    ],
    "wof:name":"Quality Cleaning",
    "wof:placetype":"venue"
},
  "geometry": {"coordinates":[-0.7002679706,52.0151824951],"type":"Point"}
}