{
  "type": "Feature",
  "properties": {
    "addr:full":"10 Scotstoun Street Glasgow Glasgow City G14 0UL",
    "addr:housenumber":"10",
    "addr:postcode":"g14 0ul",
    "addr:street":"Scotstoun Street",
    "iso:country":"GB",
    "sg:address":"10 Scotstoun Street",
    "sg:city":"Glasgow",
    "sg:classifiers":[
        {
            "category":"Personal",
            "subcategory":"Beauty Salon",
            "type":"Services"
        }
    ],
    "sg:phone":"+44 141 959 6722",
    "sg:postcode":"G14 0UL",
    "sg:province":"Glasgow City",
    "sg:tags":[
        "unisex",
        "hairdresser"
    ],
    "wof:name":"D Paterson",
    "wof:placetype":"venue"
},
  "geometry": {"coordinates":[-4.344039917,55.876083374],"type":"Point"}
}