{
  "type": "Feature",
  "properties": {
    "addr:full":"45 Craven Road Orpington Kent BR6 7RU",
    "addr:housenumber":"45",
    "addr:postcode":"br6 7ru",
    "addr:street":"Craven Road",
    "iso:country":"GB",
    "sg:address":"45 Craven Road",
    "sg:city":"Orpington",
    "sg:classifiers":[
        {
            "category":"Travel",
            "subcategory":"Travel Agent",
            "type":"Entertainment"
        }
    ],
    "sg:phone":"+44 1689 837987",
    "sg:postcode":"BR6 7RU",
    "sg:province":"Kent",
    "wof:name":"Rhodemoor Ltd.",
    "wof:placetype":"venue"
},
  "geometry": {"coordinates":[0.1206619963,51.3674354553],"type":"Point"}
}