{
  "type": "Feature",
  "properties": {
    "addr:full":"School Lane Buckingham Buckinghamshire MK18 1HB",
    "addr:postcode":"mk18 1hb",
    "addr:street":"School Lane",
    "iso:country":"GB",
    "sg:address":"School Lane",
    "sg:city":"Buckingham",
    "sg:classifiers":[
        {
            "category":"Shopping",
            "type":"Retail Goods"
        }
    ],
    "sg:phone":"+44 1280 813605",
    "sg:postcode":"MK18 1HB",
    "sg:province":"Buckinghamshire",
    "sg:tags":[
        "part",
        "accessory"
    ],
    "wof:name":"West End Garage & Autoparts",
    "wof:placetype":"venue"
},
  "geometry": {"coordinates":[-0.990174,51.999653],"type":"Point"}
}