{
  "type": "Feature",
  "properties": {
    "iso:country":"GB",
    "sg:address":"153 Elliott Street, Tyldesley",
    "sg:city":"Manchester",
    "sg:classifiers":[
        {
            "category":"Building & Trades",
            "subcategory":"Construction",
            "type":"Services"
        }
    ],
    "sg:phone":"+44 1942 874000",
    "sg:postcode":"M29 8FL",
    "sg:province":"Greater Manchester",
    "sg:tags":[
        "flooring"
    ],
    "wof:name":"The Patterned Driveway Co. Ltd.",
    "wof:placetype":"venue"
},
  "geometry": {"coordinates":[-2.468696,53.514156],"type":"Point"}
}