{
  "type": "Feature",
  "properties": {
    "iso:country":"GB",
    "sg:address":"Waste Disposal Authority, Trent Bridge Ho, Fox Rd",
    "sg:city":"Nottingham",
    "sg:classifiers":[
        {
            "category":"Government",
            "subcategory":"Office",
            "type":"Public Place"
        }
    ],
    "sg:phone":"+44 115 977 4383",
    "sg:postcode":"NG2 6AJ",
    "sg:province":"Nottinghamshire",
    "sg:tags":[
        "local"
    ],
    "wof:name":"Nottinghamshire County Council",
    "wof:placetype":"venue"
},
  "geometry": {"coordinates":[-1.13043,52.936859],"type":"Point"}
}