{
  "type": "Feature",
  "properties": {
    "addr:full":"29 London Rd Bromley Kent BR1 1DG",
    "addr:housenumber":"29",
    "addr:postcode":"br1 1dg",
    "addr:street":"London Rd",
    "iso:country":"GB",
    "sg:address":"29 London Rd",
    "sg:city":"Bromley",
    "sg:classifiers":[
        {
            "category":"Education",
            "subcategory":"Special Training",
            "type":"Public Place"
        }
    ],
    "sg:phone":"+44 20 8466 9100",
    "sg:postcode":"BR1 1DG",
    "sg:province":"Kent",
    "sg:tags":[
        "product",
        "centre"
    ],
    "wof:name":"Pitman Training Centre",
    "wof:placetype":"venue"
},
  "geometry": {"coordinates":[0.011,51.408249],"type":"Point"}
}