{
  "type": "Feature",
  "properties": {
    "addr:full":"84 Ravens Way Bognor Regis West Sussex PO22 9ER",
    "addr:housenumber":"84",
    "addr:postcode":"po22 9er",
    "addr:street":"Ravens Way",
    "iso:country":"GB",
    "sg:address":"84 Ravens Way",
    "sg:city":"Bognor Regis",
    "sg:classifiers":[
        {
            "category":"Arts & Performance",
            "subcategory":"Music",
            "type":"Entertainment"
        }
    ],
    "sg:phone":"+44 1243 829268",
    "sg:postcode":"PO22 9ER",
    "sg:province":"West Sussex",
    "sg:tags":[
        "mobile",
        "disco"
    ],
    "wof:name":"Terry D Nicholas Disco Entertainment",
    "wof:placetype":"venue"
},
  "geometry": {"coordinates":[-0.6822980046,50.8001022339],"type":"Point"}
}