{
  "type": "Feature",
  "properties": {
    "addr:full":"Canning Road Southport Lancashire PR9 7SW",
    "addr:postcode":"pr9 7sw",
    "addr:street":"Canning Road",
    "iso:country":"GB",
    "sg:address":"Canning Road",
    "sg:city":"Southport",
    "sg:classifiers":[
        {
            "category":"Travel",
            "subcategory":"Travel Agent",
            "type":"Entertainment"
        }
    ],
    "sg:phone":"+44 870 755 6006",
    "sg:postcode":"PR9 7SW",
    "sg:province":"Lancashire",
    "wof:name":"Cruise Options",
    "wof:placetype":"venue"
},
  "geometry": {"coordinates":[-2.969604,53.647499],"type":"Point"}
}