{
  "type": "Feature",
  "properties": {
    "iso:country":"GB",
    "sg:address":"The White House, 5 Ashdown",
    "sg:city":"Uckfield",
    "sg:classifiers":[
        {
            "category":"Utilities",
            "subcategory":"Fuel Oil & Lpg",
            "type":"Services"
        }
    ],
    "sg:phone":"+44 1892 852568",
    "sg:postcode":"TN22 3AN",
    "sg:province":"East Sussex",
    "sg:tags":[
        "coal",
        "smokeless"
    ],
    "wof:name":"N Dawson",
    "wof:placetype":"venue"
},
  "geometry": {"coordinates":[0.059689,51.038914],"type":"Point"}
}