{
  "type": "Feature",
  "properties": {
    "iso:country":"GB",
    "sg:address":"27 Harcourt Road, Boscombe",
    "sg:city":"Bournemouth",
    "sg:classifiers":[
        {
            "category":"Autos & Motor Vehicles",
            "subcategory":"Auto Supplies",
            "type":"Retail Goods"
        }
    ],
    "sg:postcode":"BH5 2JQ",
    "sg:province":"Dorset",
    "sg:tags":[
        "part",
        "motorcycle",
        "accessory"
    ],
    "wof:name":"Battistini",
    "wof:placetype":"venue"
},
  "geometry": {"coordinates":[-1.8240580559,50.7290267944],"type":"Point"}
}