{
  "type": "Feature",
  "properties": {
    "addr:full":"Arundel Road Worthing West Sussex BN13 3ES",
    "addr:postcode":"bn13 3es",
    "addr:street":"Arundel Road",
    "iso:country":"GB",
    "sg:address":"Arundel Road",
    "sg:city":"Worthing",
    "sg:classifiers":[
        {
            "category":"Retail",
            "subcategory":"Auto Repair",
            "type":"Services"
        }
    ],
    "sg:postcode":"BN13 3ES",
    "sg:province":"West Sussex",
    "sg:tags":[
        "body",
        "car"
    ],
    "wof:name":"D Boyce",
    "wof:placetype":"venue"
},
  "geometry": {"coordinates":[-0.4039539993,50.8406143188],"type":"Point"}
}