{
  "type": "Feature",
  "properties": {
    "addr:full":"25 Bennan Gdns Dundee Angus DD5 3EJ",
    "addr:housenumber":"25",
    "addr:postcode":"dd5 3ej",
    "addr:street":"Bennan Gdns",
    "iso:country":"GB",
    "sg:address":"25 Bennan Gdns",
    "sg:city":"Dundee",
    "sg:classifiers":[
        {
            "category":"Professional",
            "subcategory":"Detective & Security Services",
            "type":"Services"
        }
    ],
    "sg:postcode":"DD5 3EJ",
    "sg:province":"Angus",
    "sg:tags":[
        "agency"
    ],
    "wof:name":"Trace Investigations Ltd",
    "wof:placetype":"venue"
},
  "geometry": {"coordinates":[-2.86799,56.473015],"type":"Point"}
}