{
  "type": "Feature",
  "properties": {
    "iso:country":"GB",
    "sg:address":"Trenleigh Drive",
    "sg:city":"Weston-super-mare",
    "sg:classifiers":[
        {
            "category":"Social Services",
            "subcategory":"Adult Care",
            "type":"Services"
        },
        {
            "category":"Government",
            "subcategory":"Office",
            "type":"Public Place"
        }
    ],
    "sg:phone":"+44 1934 520693",
    "sg:postcode":"BS22 6LT",
    "sg:province":"Somerset",
    "sg:tags":[
        "local",
        "day",
        "centre"
    ],
    "wof:name":"Severn Unit Day Centre",
    "wof:placetype":"venue"
},
  "geometry": {"coordinates":[-2.920589,51.362476],"type":"Point"}
}