{
  "type": "Feature",
  "properties": {
    "addr:full":"11 Sea Road, Boscombe Bournemouth Dorset BH5 1DH",
    "addr:housenumber":"11",
    "addr:postcode":"bh5 1dh",
    "addr:street":"Sea Road",
    "iso:country":"GB",
    "sg:address":"11 Sea Road, Boscombe",
    "sg:city":"Bournemouth",
    "sg:classifiers":[
        {
            "category":"Cafe",
            "type":"Food & Drink"
        }
    ],
    "sg:phone":"+44 1202 396191",
    "sg:postcode":"BH5 1DH",
    "sg:province":"Dorset",
    "sg:tags":[
        "tea",
        "room"
    ],
    "wof:name":"International Cafe",
    "wof:placetype":"venue"
},
  "geometry": {"coordinates":[-1.8405519724,50.7255859375],"type":"Point"}
}