{
  "type": "Feature",
  "properties": {
    "addr:full":"Windmill Lane Belper Derbyshire DE56 1GP",
    "addr:postcode":"de56 1gp",
    "addr:street":"Windmill Lane",
    "iso:country":"GB",
    "sg:address":"Windmill Lane",
    "sg:city":"Belper",
    "sg:classifiers":[
        {
            "category":"Government",
            "subcategory":"Post Office",
            "type":"Public Place"
        }
    ],
    "sg:phone":"+44 1773 822192",
    "sg:postcode":"DE56 1GP",
    "sg:province":"Derbyshire",
    "wof:name":"Windmill Lane Post Office",
    "wof:placetype":"venue"
},
  "geometry": {"coordinates":[-1.4731639624,53.0289916992],"type":"Point"}
}