{
  "type": "Feature",
  "properties": {
    "addr:full":"Finchley Road Tube Station London Greater London NW3 6LP",
    "addr:postcode":"nw3 6lp",
    "addr:street":"Finchley Road",
    "iso:country":"GB",
    "sg:address":"Finchley Road Tube Station",
    "sg:city":"London",
    "sg:classifiers":[
        {
            "category":"Building & Trades",
            "subcategory":"Locksmith",
            "type":"Services"
        },
        {
            "category":"Shopping",
            "subcategory":"Shoes",
            "type":"Retail Goods"
        }
    ],
    "sg:phone":"+44 20 7328 9757",
    "sg:postcode":"NW3 6LP",
    "sg:province":"Greater London",
    "wof:name":"George'S",
    "wof:placetype":"venue"
},
  "geometry": {"coordinates":[-0.18003,51.547039],"type":"Point"}
}