{
  "type": "Feature",
  "properties": {
    "iso:country":"GB",
    "sg:address":"10 York Pl",
    "sg:city":"Perth",
    "sg:classifiers":[
        {
            "category":"Organizations",
            "subcategory":"Non-profit Organization",
            "type":"Services"
        }
    ],
    "sg:phone":"+44 1738 444230",
    "sg:postcode":"PH2 8EP",
    "sg:province":"Perth and Kinross",
    "sg:tags":[
        "organisation",
        "voluntary",
        "charity"
    ],
    "wof:name":"Tayside Native Woodlands",
    "wof:placetype":"venue"
},
  "geometry": {"coordinates":[-3.439168,56.395447],"type":"Point"}
}