{
  "type": "Feature",
  "properties": {
    "iso:country":"GB",
    "sg:address":"The Cottage, Old Railway Wks",
    "sg:city":"Ashford",
    "sg:classifiers":[
        {
            "category":"Professional",
            "subcategory":"Engineering",
            "type":"Services"
        }
    ],
    "sg:postcode":"TN24 0PN",
    "sg:province":"Kent",
    "sg:tags":[
        "consultant",
        "structural"
    ],
    "wof:name":"Abbey Underpinning & Foundations Ltd",
    "wof:placetype":"venue"
},
  "geometry": {"coordinates":[0.9122080207,51.1396446228],"type":"Point"}
}