{
  "type": "Feature",
  "properties": {
    "addr:full":"44 Keymer Road Hassocks East Sussex BN6 8AR",
    "addr:housenumber":"44",
    "addr:postcode":"bn6 8ar",
    "addr:street":"Keymer Road",
    "iso:country":"GB",
    "sg:address":"44 Keymer Road",
    "sg:city":"Hassocks",
    "sg:classifiers":[
        {
            "category":"Shopping",
            "subcategory":"News",
            "type":"Retail Goods"
        }
    ],
    "sg:phone":"+44 1273 844486",
    "sg:postcode":"BN6 8AR",
    "sg:province":"East Sussex",
    "sg:tags":[
        "newsagent"
    ],
    "wof:name":"Martin the Newsagent",
    "wof:placetype":"venue"
},
  "geometry": {"coordinates":[-0.1407600045,50.9240493774],"type":"Point"}
}