{
  "type": "Feature",
  "properties": {
    "iso:country":"GB",
    "sg:address":"71 Rhyl Coast Rd",
    "sg:city":"Rhyl",
    "sg:classifiers":[
        {
            "category":"Professional",
            "subcategory":"Computer Services",
            "type":"Services"
        }
    ],
    "sg:phone":"+44 1745 344644",
    "sg:postcode":"LL18 3PW",
    "sg:province":"Conwy",
    "sg:tags":[
        "system",
        "software"
    ],
    "wof:name":"P C'S 'r' Us Ltd",
    "wof:placetype":"venue"
},
  "geometry": {"coordinates":[-3.471565,53.326801],"type":"Point"}
}