{
  "type": "Feature",
  "properties": {
    "addr:full":"14 Huntsmead Billericay Essex CM12 9JA",
    "addr:housenumber":"14",
    "addr:postcode":"cm12 9ja",
    "addr:street":"Huntsmead Billericay",
    "iso:country":"GB",
    "sg:address":"14 Huntsmead",
    "sg:city":"Billericay",
    "sg:classifiers":[
        {
            "category":"Professional",
            "subcategory":"Engineering",
            "type":"Services"
        }
    ],
    "sg:phone":"+44 1277 623997",
    "sg:postcode":"CM12 9JA",
    "sg:province":"Essex",
    "sg:tags":[
        "contractor",
        "electrical",
        "engineer"
    ],
    "wof:name":"Smith Electrical & Building Services Ltd.",
    "wof:placetype":"venue"
},
  "geometry": {"coordinates":[0.4100199938,51.617401123],"type":"Point"}
}