{
  "type": "Feature",
  "properties": {
    "addr:full":"10 Crown Arcade, Union Street Kingston-upon-thames Greater London KT1 2RD",
    "addr:housenumber":"10;arcade",
    "addr:postcode":"kt1 2rd",
    "addr:street":"Crown;Union Street",
    "iso:country":"GB",
    "sg:address":"10 Crown Arcade, Union Street",
    "sg:city":"Kingston-upon-thames",
    "sg:classifiers":[
        {
            "category":"Shopping",
            "subcategory":"Gifts & Souvenirs",
            "type":"Retail Goods"
        }
    ],
    "sg:postcode":"KT1 2RD",
    "sg:province":"Greater London",
    "sg:tags":[
        "shop"
    ],
    "wof:name":"Brass Tacks",
    "wof:placetype":"venue"
},
  "geometry": {"coordinates":[-0.29903,51.40633],"type":"Point"}
}