{
  "type": "Feature",
  "properties": {
    "addr:full":"45 Corston Ro Colchester Essex CO1 1RT",
    "addr:housenumber":"45",
    "addr:postcode":"co1 1rt",
    "addr:street":"Corston Ro Colchester",
    "iso:country":"GB",
    "sg:address":"45 Corston Ro",
    "sg:city":"Colchester",
    "sg:classifiers":[
        {
            "category":"Professional",
            "subcategory":"Accounting & Tax Preparation",
            "type":"Services"
        }
    ],
    "sg:phone":"+44 1206 762040",
    "sg:postcode":"CO1 1RT",
    "sg:province":"Essex",
    "sg:tags":[
        "accountant"
    ],
    "wof:name":"Olley Brazington",
    "wof:placetype":"venue"
},
  "geometry": {"coordinates":[0.898359,51.894985],"type":"Point"}
}