{
  "type": "Feature",
  "properties": {
    "addr:full":"Royal-oak Cottage, Hook Road, Wimblington March Cambridgeshire PE15 0QL",
    "addr:postcode":"pe15 0ql",
    "addr:street":"Hook Road;March",
    "iso:country":"GB",
    "sg:address":"Royal-oak Cottage, Hook Road, Wimblington",
    "sg:city":"March",
    "sg:classifiers":[
        {
            "category":"Personal",
            "type":"Services"
        }
    ],
    "sg:postcode":"PE15 0QL",
    "sg:province":"Cambridgeshire",
    "sg:tags":[
        "delivery"
    ],
    "wof:name":"Eastwood Express",
    "wof:placetype":"venue"
},
  "geometry": {"coordinates":[0.08618,52.508385],"type":"Point"}
}