{
  "type": "Feature",
  "properties": {
    "addr:full":"9 York Place Leeds West Yorkshire LS1 2DS",
    "addr:housenumber":"9",
    "addr:postcode":"ls1 2ds",
    "addr:street":"York Place",
    "iso:country":"GB",
    "sg:address":"9 York Place",
    "sg:city":"Leeds",
    "sg:classifiers":[
        {
            "category":"Professional",
            "subcategory":"Employment Agencies",
            "type":"Services"
        }
    ],
    "sg:phone":"+44 113 246 1333",
    "sg:postcode":"LS1 2DS",
    "sg:province":"West Yorkshire",
    "sg:tags":[
        "consultant"
    ],
    "wof:name":"Sales & Marketing Selection Ltd.",
    "wof:placetype":"venue"
},
  "geometry": {"coordinates":[-1.551627,53.796848],"type":"Point"}
}