{
  "type": "Feature",
  "properties": {
    "addr:full":"Suite C563, 72 New Bond Street London Greater London W1S 1RR",
    "addr:housenumber":"suite c563 72",
    "addr:postcode":"w1s 1rr",
    "addr:street":"New Bond Street",
    "iso:country":"GB",
    "sg:address":"Suite C563, 72 New Bond Street",
    "sg:city":"London",
    "sg:classifiers":[
        {
            "category":"Education",
            "subcategory":"Special Training",
            "type":"Public Place"
        }
    ],
    "sg:postcode":"W1S 1RR",
    "sg:province":"Greater London",
    "sg:tags":[
        "diving",
        "school"
    ],
    "wof:name":"The Diving Frog Ltd",
    "wof:placetype":"venue"
},
  "geometry": {"coordinates":[-0.145786,51.513813],"type":"Point"}
}