{
  "type": "Feature",
  "properties": {
    "iso:country":"GB",
    "sg:address":"Salmestone Grange",
    "sg:city":"Margate",
    "sg:classifiers":[
        {
            "category":"Personal",
            "type":"Services"
        }
    ],
    "sg:postcode":"CT9 4BX",
    "sg:province":"Kent",
    "sg:tags":[
        "wedding"
    ],
    "wof:name":"Salmestone Grange Ltd.",
    "wof:placetype":"venue"
},
  "geometry": {"coordinates":[1.3807450533,51.3778533936],"type":"Point"}
}