{
  "type": "Feature",
  "properties": {
    "addr:full":"Iken House, 160 Anglia International Airpark, Rendlesham Woodbridge Suffolk IP12 2TW",
    "addr:housenumber":"iken;160;international;rendlesham woodbridge",
    "addr:postcode":"ip12 2tw",
    "addr:street":"Anglia",
    "iso:country":"GB",
    "sg:address":"Iken House, 160 Anglia International Airpark, Rendlesham",
    "sg:city":"Woodbridge",
    "sg:classifiers":[
        {
            "category":"Professional",
            "subcategory":"Testing Lab",
            "type":"Services"
        }
    ],
    "sg:phone":"+44 1394 420943",
    "sg:postcode":"IP12 2TW",
    "sg:province":"Suffolk",
    "sg:tags":[
        "inspection",
        "calibration"
    ],
    "wof:name":"W H D Microanalysis Consultants Ltd.",
    "wof:placetype":"venue"
},
  "geometry": {"coordinates":[1.417536,52.127487],"type":"Point"}
}