{
  "type": "Feature",
  "properties": {
    "iso:country":"GB",
    "sg:address":"40 Common Lane, Hemingford Abbots",
    "sg:city":"Huntingdon",
    "sg:classifiers":[
        {
            "category":"Building & Trades",
            "subcategory":"Construction",
            "type":"Services"
        }
    ],
    "sg:phone":"+44 1480 468500",
    "sg:postcode":"PE28 9AN",
    "sg:province":"Bedfordshire",
    "sg:tags":[
        "management"
    ],
    "wof:name":"Blyde Associates",
    "wof:placetype":"venue"
},
  "geometry": {"coordinates":[-0.090964,52.303841],"type":"Point"}
}