{
  "type": "Feature",
  "properties": {
    "addr:full":"Gatemore Farm, Gatemore Road, Winfrith Newburgh Dorchester Dorset DT2 8LB",
    "addr:postcode":"dt2 8lb",
    "addr:street":"Gatemore Road",
    "iso:country":"GB",
    "sg:address":"Gatemore Farm, Gatemore Road, Winfrith Newburgh",
    "sg:city":"Dorchester",
    "sg:classifiers":[
        {
            "category":"Professional",
            "subcategory":"Engineering",
            "type":"Services"
        }
    ],
    "sg:phone":"+44 1305 851882",
    "sg:postcode":"DT2 8LB",
    "sg:province":"Dorset",
    "sg:tags":[
        "civil",
        "engineer"
    ],
    "wof:name":"Worgret Construction Ltd.",
    "wof:placetype":"venue"
},
  "geometry": {"coordinates":[-2.277784,50.674458],"type":"Point"}
}