{
  "type": "Feature",
  "properties": {
    "iso:country":"GB",
    "sg:address":"Buxton Road, Chinley",
    "sg:city":"High Peak",
    "sg:classifiers":[
        {
            "category":"Education",
            "subcategory":"School",
            "type":"Public Place"
        },
        {
            "category":"Government",
            "subcategory":"Office",
            "type":"Public Place"
        }
    ],
    "sg:phone":"+44 1663 750324",
    "sg:postcode":"SK23 6ES",
    "sg:province":"Cheshire",
    "sg:tags":[
        "local",
        "authority"
    ],
    "wof:name":"Peak School",
    "wof:placetype":"venue"
},
  "geometry": {"coordinates":[-1.939894,53.338741],"type":"Point"}
}