{
  "type": "Feature",
  "properties": {
    "addr:full":"61 The Pavement, Park Hill Sheffield South Yorkshire S2 5RD",
    "addr:housenumber":"61",
    "addr:postcode":"s2 5rd",
    "addr:street":"The Pavement",
    "iso:country":"GB",
    "sg:address":"61 The Pavement, Park Hill",
    "sg:city":"Sheffield",
    "sg:classifiers":[
        {
            "category":"Bars & Pubs",
            "type":"Food & Drink"
        }
    ],
    "sg:postcode":"S2 5RD",
    "sg:province":"South Yorkshire",
    "sg:tags":[
        "pubs",
        "inn"
    ],
    "wof:name":"The Earl George",
    "wof:placetype":"venue"
},
  "geometry": {"coordinates":[-1.459429,53.381866],"type":"Point"}
}