{
  "type": "Feature",
  "properties": {
    "iso:country":"GB",
    "sg:address":"Ruskin Way",
    "sg:city":"Knutsford",
    "sg:classifiers":[
        {
            "category":"Manufacturing",
            "subcategory":"Textiles",
            "type":"Manufacturing & Wholesale Goods"
        }
    ],
    "sg:phone":"+44 1565 633535",
    "sg:postcode":"WA16 6TJ",
    "sg:province":"Cheshire",
    "sg:tags":[
        "knitwear"
    ],
    "wof:name":"Cheshire Textiles Ltd.",
    "wof:placetype":"venue"
},
  "geometry": {"coordinates":[-2.372664,53.307468],"type":"Point"}
}