{
  "type": "Feature",
  "properties": {
    "addr:full":"1b St. Oswins Place, Tynemouth North Shields Tyne and Wear NE30 4RQ",
    "addr:housenumber":"1b",
    "addr:postcode":"ne30 4rq",
    "addr:street":"St. Oswins Place",
    "iso:country":"GB",
    "sg:address":"1b St. Oswins Place, Tynemouth",
    "sg:city":"North Shields",
    "sg:classifiers":[
        {
            "category":"Banks & Credit Unions",
            "subcategory":"Financial Services",
            "type":"Services"
        }
    ],
    "sg:phone":"+44 191 296 1188",
    "sg:postcode":"NE30 4RQ",
    "sg:province":"Tyne and Wear",
    "sg:tags":[
        "consultant",
        "pension"
    ],
    "wof:name":"Middleton & Co",
    "wof:placetype":"venue"
},
  "geometry": {"coordinates":[-1.425583005,55.0185813904],"type":"Point"}
}