{
  "type": "Feature",
  "properties": {
    "iso:country":"GB",
    "sg:address":"30 Stoney Lane, Quinton",
    "sg:city":"Birmingham",
    "sg:classifiers":[
        {
            "category":"Manufacturing",
            "subcategory":"Wood Products",
            "type":"Manufacturing & Wholesale Goods"
        }
    ],
    "sg:phone":"+44 121 422 5565",
    "sg:postcode":"B32 1AN",
    "sg:province":"West Midlands",
    "sg:tags":[
        "maker",
        "cabinet"
    ],
    "wof:name":"R K Andrews",
    "wof:placetype":"venue"
},
  "geometry": {"coordinates":[-2.007646,52.460423],"type":"Point"}
}