{
  "type": "Feature",
  "properties": {
    "addr:full":"11 Rock Avenue Lynton Devon EX35 6DL",
    "addr:housenumber":"11",
    "addr:postcode":"ex35 6dl",
    "addr:street":"Rock Avenue",
    "iso:country":"GB",
    "sg:address":"11 Rock Avenue",
    "sg:city":"Lynton",
    "sg:classifiers":[
        {
            "category":"Freight",
            "type":"Transportation"
        }
    ],
    "sg:phone":"+44 1598 752371",
    "sg:postcode":"EX35 6DL",
    "sg:province":"Devon",
    "sg:tags":[
        "haulage",
        "road"
    ],
    "wof:name":"D.A Dyer",
    "wof:placetype":"venue"
},
  "geometry": {"coordinates":[-3.841568,51.228481],"type":"Point"}
}