{
  "type": "Feature",
  "properties": {
    "iso:country":"GB",
    "sg:address":"Pencroft, Pencroft Drive",
    "sg:city":"Dartford",
    "sg:classifiers":[
        {
            "category":"Real Estate",
            "subcategory":"Developer",
            "type":"Services"
        }
    ],
    "sg:phone":"+44 1322 223871",
    "sg:postcode":"DA1 2PB",
    "sg:province":"Kent",
    "sg:tags":[
        "property"
    ],
    "wof:name":"Greatfield Ltd.",
    "wof:placetype":"venue"
},
  "geometry": {"coordinates":[0.2044049948,51.4432983398],"type":"Point"}
}