{
  "type": "Feature",
  "properties": {
    "iso:country":"GB",
    "sg:address":"56-57 Middle St South",
    "sg:city":"Driffield",
    "sg:classifiers":[
        {
            "category":"Cinema",
            "subcategory":"Movie Rental",
            "type":"Entertainment"
        }
    ],
    "sg:phone":"+44 1377 241145",
    "sg:postcode":"YO25 6PS",
    "sg:province":"East Riding of Yorkshire",
    "sg:tags":[
        "video",
        "library"
    ],
    "wof:name":"Choices Video Ltd",
    "wof:placetype":"venue"
},
  "geometry": {"coordinates":[-0.438142,54.004368],"type":"Point"}
}