{
  "type": "Feature",
  "properties": {
    "addr:full":"The Unit, High St, Kexby Gainsborough Lincolnshire DN21 5LZ",
    "addr:housenumber":"unit",
    "addr:postcode":"dn21 5lz",
    "addr:street":"High St",
    "iso:country":"GB",
    "sg:address":"The Unit, High St, Kexby",
    "sg:city":"Gainsborough",
    "sg:classifiers":[
        {
            "category":"Shopping",
            "subcategory":"Computers & Home Electronics",
            "type":"Retail Goods"
        }
    ],
    "sg:phone":"+44 1427 787797",
    "sg:postcode":"DN21 5LZ",
    "sg:province":"Lincolnshire",
    "sg:tags":[
        "aerial",
        "television",
        "radio"
    ],
    "wof:name":"1st Direct Aerials",
    "wof:placetype":"venue"
},
  "geometry": {"coordinates":[-0.6923729777,53.3618888855],"type":"Point"}
}