{
  "type": "Feature",
  "properties": {
    "iso:country":"GB",
    "sg:address":"Paddington Green",
    "sg:city":"Bayswater",
    "sg:classifiers":[
        {
            "category":"Place Of Worship",
            "type":"Public Place"
        }
    ],
    "sg:phone":"+44 20 7262 3787",
    "sg:postcode":"W2 1LG",
    "sg:province":"Greater London",
    "wof:name":"Church Of St Mary On Paddington Green",
    "wof:placetype":"venue"
},
  "geometry": {"coordinates":[-0.173579,51.520615],"type":"Point"}
}