{
  "type": "Feature",
  "properties": {
    "iso:country":"GB",
    "sg:address":"Easton Business Centre, Felix Road",
    "sg:city":"Bristol",
    "sg:classifiers":[
        {
            "category":"Wholesale",
            "subcategory":"Machinery & Supplies",
            "type":"Manufacturing & Wholesale Goods"
        }
    ],
    "sg:href":"http://api.simplegeo.com/1.0/features/SG_0YOeRMrT0R1v2PjnbTHiuN_51.478325_-2.691005@1300740015.json",
    "sg:postcode":"BS5 0HE",
    "sg:province":"City of Bristol",
    "sg:tags":[
        "equipment",
        "pneumatic",
        "system"
    ],
    "wof:name":"Webbair Ltd.",
    "wof:placetype":"venue"
},
  "geometry": {"coordinates":[-2.691005,51.478325],"type":"Point"}
}