{
  "type": "Feature",
  "properties": {
    "iso:country":"GB",
    "sg:address":"168 High Rd, Byfleet",
    "sg:city":"West Byfleet",
    "sg:classifiers":[
        {
            "category":"Shopping",
            "subcategory":"News",
            "type":"Retail Goods"
        }
    ],
    "sg:phone":"+44 1932 354367",
    "sg:postcode":"KT14 7RG",
    "sg:province":"Surrey",
    "sg:tags":[
        "newsagent"
    ],
    "wof:name":"Kellys Of Byfleet",
    "wof:placetype":"venue"
},
  "geometry": {"coordinates":[-0.4701330066,51.3379364014],"type":"Point"}
}