{
  "type": "Feature",
  "properties": {
    "iso:country":"GB",
    "sg:address":"10 Howe Walk",
    "sg:city":"Burnley",
    "sg:classifiers":[
        {
            "category":"Communications",
            "subcategory":"Film & Video Production",
            "type":"Services"
        }
    ],
    "sg:phone":"+44 1282 437118",
    "sg:postcode":"BB11 1QB",
    "sg:province":"Lancashire",
    "sg:tags":[
        "tv",
        "studio"
    ],
    "wof:name":"Harry Garlick the T V Centre Ltd.",
    "wof:placetype":"venue"
},
  "geometry": {"coordinates":[-2.2438089848,53.7880096436],"type":"Point"}
}