{
  "type": "Feature",
  "properties": {
    "iso:country":"GB",
    "sg:address":"19 Temple Road, Ealing",
    "sg:city":"London",
    "sg:classifiers":[
        {
            "category":"Professional",
            "subcategory":"Engineering",
            "type":"Services"
        }
    ],
    "sg:phone":"+44 20 8579 6238",
    "sg:postcode":"W5 4SL",
    "sg:province":"Greater London",
    "sg:tags":[
        "contractor",
        "electrical",
        "engineer"
    ],
    "wof:name":"London Telecom",
    "wof:placetype":"venue"
},
  "geometry": {"coordinates":[-0.3076620102,51.4985351562],"type":"Point"}
}