{
  "type": "Feature",
  "properties": {
    "addr:full":"Lapworth House, Wharf Lane, Lapworth Solihull Warwickshire B94 5QH",
    "addr:postcode":"b94 5qh",
    "addr:street":"Wharf Lane",
    "iso:country":"GB",
    "sg:address":"Lapworth House, Wharf Lane, Lapworth",
    "sg:city":"Solihull",
    "sg:classifiers":[
        {
            "category":"Manufacturing",
            "subcategory":"Tools & Machinery",
            "type":"Manufacturing & Wholesale Goods"
        }
    ],
    "sg:phone":"+44 1564 730066",
    "sg:postcode":"B94 5QH",
    "sg:province":"Warwickshire",
    "sg:tags":[
        "society",
        "friendly"
    ],
    "wof:name":"Willies  Henley & Partners Ltd.",
    "wof:placetype":"venue"
},
  "geometry": {"coordinates":[-1.7621480227,52.337272644],"type":"Point"}
}