{
  "type": "Feature",
  "properties": {
    "iso:country":"GB",
    "sg:address":"2 St Georges Parade, Perry Hill",
    "sg:city":"London",
    "sg:classifiers":[
        {
            "category":"Cafe",
            "type":"Food & Drink"
        }
    ],
    "sg:phone":"+44 20 8699 4601",
    "sg:postcode":"SE6 4DT",
    "sg:province":"Greater London",
    "sg:tags":[
        "tea",
        "snack",
        "bar",
        "room"
    ],
    "wof:name":"Sema'S Cafe",
    "wof:placetype":"venue"
},
  "geometry": {"coordinates":[-0.033569999,51.4388198853],"type":"Point"}
}