{
  "type": "Feature",
  "properties": {
    "iso:country":"GB",
    "sg:address":"Letter Box Cottage, High Street, Carlby",
    "sg:city":"Stamford",
    "sg:classifiers":[
        {
            "category":"Farming",
            "subcategory":"Farm",
            "type":"Manufacturing & Wholesale Goods"
        }
    ],
    "sg:phone":"+44 1778 590200",
    "sg:postcode":"PE9 4LX",
    "sg:province":"Cambridgeshire",
    "sg:tags":[
        "mixed",
        "crop"
    ],
    "wof:name":"D R W Pope",
    "wof:placetype":"venue"
},
  "geometry": {"coordinates":[-0.445621,52.713036],"type":"Point"}
}