{
  "type": "Feature",
  "properties": {
    "addr:full":"71 Crown Way Leamington Spa Warwickshire CV32 7SH",
    "addr:housenumber":"71",
    "addr:postcode":"cv32 7sh",
    "addr:street":"Crown Way",
    "iso:country":"GB",
    "sg:address":"71 Crown Way",
    "sg:city":"Leamington Spa",
    "sg:classifiers":[
        {
            "category":"Fast Food",
            "type":"Food & Drink"
        }
    ],
    "sg:phone":"+44 1926 424775",
    "sg:postcode":"CV32 7SH",
    "sg:province":"Warwickshire",
    "sg:tags":[
        "away",
        "take"
    ],
    "wof:name":"The Winson",
    "wof:placetype":"venue"
},
  "geometry": {"coordinates":[-1.519265,52.302513],"type":"Point"}
}