{
  "type": "Feature",
  "properties": {
    "iso:country":"GB",
    "sg:address":"Mcgregor Avenue",
    "sg:city":"Lochgelly",
    "sg:classifiers":[
        {
            "category":"Education",
            "subcategory":"School",
            "type":"Public Place"
        },
        {
            "category":"Government",
            "subcategory":"Office",
            "type":"Public Place"
        }
    ],
    "sg:phone":"+44 1592 418110",
    "sg:postcode":"KY5 9PE",
    "sg:province":"Fife",
    "sg:tags":[
        "local",
        "authority"
    ],
    "wof:name":"Fife District Council",
    "wof:placetype":"venue"
},
  "geometry": {"coordinates":[-3.314229,56.12999],"type":"Point"}
}