{
  "type": "Feature",
  "properties": {
    "addr:full":"15 Lots Rd West Brompton Greater London SW10 0QJ",
    "addr:housenumber":"15",
    "addr:postcode":"sw10 0qj",
    "addr:street":"Lots Rd",
    "iso:country":"GB",
    "sg:address":"15 Lots Rd",
    "sg:city":"West Brompton",
    "sg:classifiers":[
        {
            "category":"Professional",
            "subcategory":"Art Services",
            "type":"Services"
        }
    ],
    "sg:phone":"+44 20 7351 1222",
    "sg:postcode":"SW10 0QJ",
    "sg:province":"Greater London",
    "sg:tags":[
        "photographer"
    ],
    "wof:name":"Carolyn Trayler Partnership",
    "wof:placetype":"venue"
},
  "geometry": {"coordinates":[-0.178566,51.47982],"type":"Point"}
}