{
  "type": "Feature",
  "properties": {
    "iso:country":"GB",
    "sg:address":"581 Fishponds Road, Fishponds",
    "sg:city":"Bristol",
    "sg:classifiers":[
        {
            "category":"Professional",
            "subcategory":"Printing & Photocopies",
            "type":"Services"
        }
    ],
    "sg:phone":"+44 117 965 4800",
    "sg:postcode":"BS16 3AA",
    "sg:province":"City of Bristol",
    "sg:tags":[
        "printer"
    ],
    "wof:name":"Prontaprint",
    "wof:placetype":"venue"
},
  "geometry": {"coordinates":[-2.538023,51.476868],"type":"Point"}
}