{
  "type": "Feature",
  "properties": {
    "addr:full":"119 Rotherhithe Street London Greater London SE16 4NF",
    "addr:housenumber":"119",
    "addr:postcode":"se16 4nf",
    "addr:street":"Rotherhithe Street",
    "iso:country":"GB",
    "sg:address":"119 Rotherhithe Street",
    "sg:city":"London",
    "sg:classifiers":[
        {
            "category":"Communications",
            "subcategory":"Film & Video Production",
            "type":"Services"
        }
    ],
    "sg:phone":"+44 20 7231 2209",
    "sg:postcode":"SE16 4NF",
    "sg:province":"Greater London",
    "sg:tags":[
        "tv",
        "studio"
    ],
    "wof:name":"Squirrel Films Distribution Ltd.",
    "wof:placetype":"venue"
},
  "geometry": {"coordinates":[-0.053871,51.501759],"type":"Point"}
}