{
  "type": "Feature",
  "properties": {
    "iso:country":"GB",
    "sg:address":"Brook Cottage, Bednall Head",
    "sg:city":"Stafford",
    "sg:classifiers":[
        {
            "category":"Building & Trades",
            "subcategory":"Construction",
            "type":"Services"
        }
    ],
    "sg:phone":"+44 1785 664792",
    "sg:postcode":"ST17 0SF",
    "sg:province":"Staffordshire",
    "sg:tags":[
        "roofing"
    ],
    "wof:name":"R D Roofing Services Ltd",
    "wof:placetype":"venue"
},
  "geometry": {"coordinates":[-2.039824,52.775558],"type":"Point"}
}