{
  "type": "Feature",
  "properties": {
    "addr:full":"Inwood Farm, Netherstowey Bridgwater Somerset TA5 1HY",
    "addr:postcode":"ta5 1hy",
    "addr:street":"Netherstowey",
    "iso:country":"GB",
    "sg:address":"Inwood Farm, Netherstowey",
    "sg:city":"Bridgwater",
    "sg:classifiers":[
        {
            "category":"Farming",
            "subcategory":"Livestock Farm",
            "type":"Manufacturing & Wholesale Goods"
        }
    ],
    "sg:phone":"+44 1278 732344",
    "sg:postcode":"TA5 1HY",
    "sg:province":"Somerset",
    "sg:tags":[
        "others"
    ],
    "wof:name":"F G Jeanes",
    "wof:placetype":"venue"
},
  "geometry": {"coordinates":[-3.14096,51.146542],"type":"Point"}
}