{
  "type": "Feature",
  "properties": {
    "addr:full":"P O Box 51 Bordon Hampshire GU35 9JA",
    "addr:housenumber":"box 51",
    "addr:postcode":"gu35 9ja",
    "addr:street":"P O",
    "iso:country":"GB",
    "sg:address":"P O Box 51",
    "sg:city":"Bordon",
    "sg:classifiers":[
        {
            "category":"Shopping",
            "subcategory":"Books",
            "type":"Retail Goods"
        }
    ],
    "sg:phone":"+44 1420 488040",
    "sg:postcode":"GU35 9JA",
    "sg:province":"Hampshire",
    "wof:name":"Eldon Publications Ltd",
    "wof:placetype":"venue"
},
  "geometry": {"coordinates":[-0.873363,51.112701],"type":"Point"}
}