{
  "type": "Feature",
  "properties": {
    "addr:full":"25-29 Cowgate Dundee Dundee City DD1 2BG",
    "addr:housenumber":"25-29",
    "addr:postcode":"dd1 2bg",
    "addr:street":"Cowgate",
    "iso:country":"GB",
    "sg:address":"25-29 Cowgate",
    "sg:city":"Dundee",
    "sg:classifiers":[
        {
            "category":"Restaurant",
            "type":"Food & Drink"
        }
    ],
    "sg:phone":"+44 1382 206898",
    "sg:postcode":"DD1 2BG",
    "sg:province":"Dundee City",
    "wof:name":"First Leisure Trading Ltd.",
    "wof:placetype":"venue"
},
  "geometry": {"coordinates":[-2.967739,56.464031],"type":"Point"}
}