{
  "type": "Feature",
  "properties": {
    "addr:full":"1 Rectory Cottage, White Post Road, Hanworth Norwich Norfolk NR11 7HN",
    "addr:housenumber":"1",
    "addr:postcode":"nr11 7hn",
    "addr:street":"Rectory Cottage White;Road;Norwich",
    "iso:country":"GB",
    "sg:address":"1 Rectory Cottage, White Post Road, Hanworth",
    "sg:city":"Norwich",
    "sg:classifiers":[
        {
            "category":"Manufacturing",
            "subcategory":"Lumber",
            "type":"Manufacturing & Wholesale Goods"
        }
    ],
    "sg:phone":"+44 1263 761456",
    "sg:postcode":"NR11 7HN",
    "sg:province":"Norfolk",
    "sg:tags":[
        "importer",
        "merchants",
        "agent",
        "timber"
    ],
    "wof:name":"Peter H G Hall",
    "wof:placetype":"venue"
},
  "geometry": {"coordinates":[1.2586679459,52.8717689514],"type":"Point"}
}