{
  "type": "Feature",
  "properties": {
    "addr:full":"64 Renfield Street Glasgow Glasgow City G2 1NQ",
    "addr:housenumber":"64",
    "addr:postcode":"g2 1nq",
    "addr:street":"Renfield Street",
    "iso:country":"GB",
    "sg:address":"64 Renfield Street",
    "sg:city":"Glasgow",
    "sg:classifiers":[
        {
            "category":"Restaurant",
            "type":"Food & Drink"
        }
    ],
    "sg:phone":"+44 141 332 5063",
    "sg:postcode":"G2 1NQ",
    "sg:province":"Glasgow City",
    "sg:tags":[
        "italian"
    ],
    "wof:name":"Tony's Restuarant",
    "wof:placetype":"venue"
},
  "geometry": {"coordinates":[-4.2559828758,55.8631057739],"type":"Point"}
}