{
  "type": "Feature",
  "properties": {
    "addr:full":"115 Estcourt Road, Fulham London Greater London SW6 7HB",
    "addr:housenumber":"115",
    "addr:postcode":"sw6 7hb",
    "addr:street":"Estcourt Road",
    "iso:country":"GB",
    "sg:address":"115 Estcourt Road, Fulham",
    "sg:city":"London",
    "sg:classifiers":[
        {
            "category":"Autos & Motor Vehicles",
            "subcategory":"Auto Supplies",
            "type":"Retail Goods"
        }
    ],
    "sg:phone":"+44 20 7385 2632",
    "sg:postcode":"SW6 7HB",
    "sg:province":"Greater London",
    "sg:tags":[
        "tyre"
    ],
    "wof:name":"Greyhound Tyres of London",
    "wof:placetype":"venue"
},
  "geometry": {"coordinates":[-0.2061859965,51.4818725586],"type":"Point"}
}