{
  "type": "Feature",
  "properties": {
    "iso:country":"GB",
    "sg:address":"9 Hayfield Close",
    "sg:city":"Belper",
    "sg:classifiers":[
        {
            "category":"Personal",
            "subcategory":"Beauty Salon",
            "type":"Services"
        }
    ],
    "sg:phone":"+44 1773 820188",
    "sg:postcode":"DE56 1FA",
    "sg:province":"Derbyshire",
    "sg:tags":[
        "unisex",
        "hairdresser"
    ],
    "wof:name":"Head Masters Hairdressers",
    "wof:placetype":"venue"
},
  "geometry": {"coordinates":[-1.468639,53.030449],"type":"Point"}
}