{
  "type": "Feature",
  "properties": {
    "addr:full":"17 Lavender Rd Basingstoke Hampshire RG22 5NN",
    "addr:housenumber":"17",
    "addr:postcode":"rg22 5nn",
    "addr:street":"Lavender Rd",
    "iso:country":"GB",
    "sg:address":"17 Lavender Rd",
    "sg:city":"Basingstoke",
    "sg:classifiers":[
        {
            "category":"Building & Trades",
            "subcategory":"Construction",
            "type":"Services"
        }
    ],
    "sg:phone":"+44 1256 477582",
    "sg:postcode":"RG22 5NN",
    "sg:province":"Hampshire",
    "sg:tags":[
        "decorator",
        "painter"
    ],
    "wof:name":"RAS Build Plan Services",
    "wof:placetype":"venue"
},
  "geometry": {"coordinates":[-1.137172,51.239403],"type":"Point"}
}