{
  "type": "Feature",
  "properties": {
    "addr:full":"Fairview, Winchester Road, Waltham Chase Southampton Hampshire SO32 2LX",
    "addr:postcode":"so32 2lx",
    "addr:street":"Winchester Road",
    "iso:country":"GB",
    "sg:address":"Fairview, Winchester Road, Waltham Chase",
    "sg:city":"Southampton",
    "sg:classifiers":[
        {
            "category":"Building & Trades",
            "subcategory":"Construction",
            "type":"Services"
        }
    ],
    "sg:phone":"+44 1489 892345",
    "sg:postcode":"SO32 2LX",
    "sg:province":"Hampshire",
    "sg:tags":[
        "joiner",
        "carpenter"
    ],
    "wof:name":"Fairview Joinery",
    "wof:placetype":"venue"
},
  "geometry": {"coordinates":[-1.201114,50.932346],"type":"Point"}
}