{
  "type": "Feature",
  "properties": {
    "addr:full":"Mortuary, 127 Poplar High St Poplar Greater London E14 0AE",
    "addr:housenumber":"127",
    "addr:postcode":"e14 0ae",
    "addr:street":"Poplar High St",
    "iso:country":"GB",
    "sg:address":"Mortuary, 127 Poplar High St",
    "sg:city":"Poplar",
    "sg:classifiers":[
        {
            "category":"Government",
            "subcategory":"Office",
            "type":"Public Place"
        }
    ],
    "sg:phone":"+44 20 7987 2793",
    "sg:postcode":"E14 0AE",
    "sg:province":"Greater London",
    "sg:tags":[
        "local"
    ],
    "wof:name":"London Borough Of Tower Hamlets",
    "wof:placetype":"venue"
},
  "geometry": {"coordinates":[-0.0165589992,51.5089416504],"type":"Point"}
}