{
  "type": "Feature",
  "properties": {
    "addr:full":"Unit 7 Pipers Court Reading Berkshire RG19 4ER",
    "addr:housenumber":"unit 7",
    "addr:postcode":"rg19 4er",
    "addr:street":"Pipers Court",
    "iso:country":"GB",
    "sg:address":"Unit 7 Pipers Court",
    "sg:city":"Reading",
    "sg:classifiers":[
        {
            "category":"Retail",
            "subcategory":"Auto Repair",
            "type":"Services"
        }
    ],
    "sg:postcode":"RG19 4ER",
    "sg:province":"Berkshire",
    "sg:tags":[
        "modification",
        "garage"
    ],
    "wof:name":"Halfway Garages (Padworth) Ltd.",
    "wof:placetype":"venue"
},
  "geometry": {"coordinates":[-1.2281689644,51.399230957],"type":"Point"}
}