{
  "type": "Feature",
  "properties": {
    "iso:country":"GB",
    "sg:address":"15 Upper Abbotts Hill",
    "sg:city":"Aylesbury",
    "sg:classifiers":[
        {
            "category":"Building & Trades",
            "subcategory":"Plumbing",
            "type":"Services"
        }
    ],
    "sg:phone":"+44 1296 392588",
    "sg:postcode":"HP19 7SD",
    "sg:province":"Buckinghamshire",
    "sg:tags":[
        "heating"
    ],
    "wof:name":"Mr Gasman",
    "wof:placetype":"venue"
},
  "geometry": {"coordinates":[-0.8339329958,51.8110313416],"type":"Point"}
}