{
  "type": "Feature",
  "properties": {
    "addr:full":"9a Dalton Way Middlewich Cheshire CW10 0HU",
    "addr:housenumber":"9a",
    "addr:postcode":"cw10 0hu",
    "addr:street":"Dalton Way",
    "iso:country":"GB",
    "sg:address":"9a Dalton Way",
    "sg:city":"Middlewich",
    "sg:classifiers":[
        {
            "category":"Government",
            "subcategory":"Post Office",
            "type":"Public Place"
        }
    ],
    "sg:phone":"+44 1606 737677",
    "sg:postcode":"CW10 0HU",
    "sg:province":"Cheshire",
    "sg:tags":[
        "messenger",
        "courier"
    ],
    "wof:name":"Goldlink (N W) Ltd.",
    "wof:placetype":"venue"
},
  "geometry": {"coordinates":[-2.437794,53.193085],"type":"Point"}
}