{
  "type": "Feature",
  "properties": {
    "iso:country":"GB",
    "sg:address":"190 Campden Hill Rd",
    "sg:city":"Kensington",
    "sg:classifiers":[
        {
            "category":"Professional",
            "type":"Services"
        }
    ],
    "sg:phone":"+44 70 7156 5758",
    "sg:postcode":"W8 7TH",
    "sg:province":"Greater London",
    "sg:tags":[
        "relocation"
    ],
    "wof:name":"Trading Places",
    "wof:placetype":"venue"
},
  "geometry": {"coordinates":[-0.199523,51.508419],"type":"Point"}
}