{
  "type": "Feature",
  "properties": {
    "iso:country":"GB",
    "sg:address":"The Promenade",
    "sg:city":"Barmouth",
    "sg:classifiers":[
        {
            "category":"Restaurant",
            "type":"Food & Drink"
        }
    ],
    "sg:phone":"+44 1341 280514",
    "sg:postcode":"LL42 1BX",
    "sg:province":"Gwynedd",
    "wof:name":"Promenade Cafe & Restaurant",
    "wof:placetype":"venue"
},
  "geometry": {"coordinates":[-4.055159,52.722664],"type":"Point"}
}