{
  "type": "Feature",
  "properties": {
    "iso:country":"GB",
    "sg:address":"44 Compton Way",
    "sg:city":"Winchester",
    "sg:classifiers":[
        {
            "category":"Health Services",
            "subcategory":"Health Practitioner",
            "type":"Services"
        }
    ],
    "sg:phone":"+44 1962 868978",
    "sg:postcode":"SO22 4HW",
    "sg:province":"Hampshire",
    "sg:tags":[
        "therapist",
        "speech"
    ],
    "wof:name":"Jennifer Dixon Adv.Dip.Couns",
    "wof:placetype":"venue"
},
  "geometry": {"coordinates":[-1.346884,51.043995],"type":"Point"}
}