{
  "type": "Feature",
  "properties": {
    "addr:full":"1 Lynmouth Street Lynmouth Devon EX35 6EH",
    "addr:housenumber":"1",
    "addr:postcode":"ex35 6eh",
    "addr:street":"Lynmouth Street",
    "iso:country":"GB",
    "sg:address":"1 Lynmouth Street",
    "sg:city":"Lynmouth",
    "sg:classifiers":[
        {
            "category":"Food & Beverages",
            "subcategory":"Candy",
            "type":"Retail Goods"
        }
    ],
    "sg:phone":"+44 1598 753900",
    "sg:postcode":"EX35 6EH",
    "sg:province":"Devon",
    "sg:tags":[
        "confectioner"
    ],
    "wof:name":"Fudgies",
    "wof:placetype":"venue"
},
  "geometry": {"coordinates":[-3.831614,51.231503],"type":"Point"}
}