{
  "type": "Feature",
  "properties": {
    "iso:country":"GB",
    "sg:address":"Landells",
    "sg:city":"Bampton",
    "sg:classifiers":[
        {
            "category":"Health Services",
            "subcategory":"Doctor",
            "type":"Services"
        }
    ],
    "sg:phone":"+44 1993 850257",
    "sg:postcode":"OX18 2LJ",
    "sg:province":"Gloucestershire",
    "sg:tags":[
        "practitioners"
    ],
    "wof:name":"Bampton Surgery",
    "wof:placetype":"venue"
},
  "geometry": {"coordinates":[-1.54836905,51.7295837402],"type":"Point"}
}