{
  "type": "Feature",
  "properties": {
    "iso:country":"GB",
    "sg:address":"Belcon House, Essex Road",
    "sg:city":"Hoddesdon",
    "sg:classifiers":[
        {
            "category":"Organizations",
            "subcategory":"Membership Organization",
            "type":"Services"
        }
    ],
    "sg:postcode":"EN11 0DR",
    "sg:province":"Essex",
    "sg:tags":[
        "club"
    ],
    "wof:name":"First Ancells Farm (Fleet) Management Co",
    "wof:placetype":"venue"
},
  "geometry": {"coordinates":[-0.0078140004,51.7647895813],"type":"Point"}
}