{
  "type": "Feature",
  "properties": {
    "addr:full":"119 Caerphilly Road Cardiff Cardiff CF14 4QA",
    "addr:housenumber":"119",
    "addr:postcode":"cf14 4qa",
    "addr:street":"Caerphilly Road",
    "iso:country":"GB",
    "sg:address":"119 Caerphilly Road",
    "sg:city":"Cardiff",
    "sg:classifiers":[
        {
            "category":"Fast Food",
            "type":"Food & Drink"
        }
    ],
    "sg:phone":"+44 29 2062 0817",
    "sg:postcode":"CF14 4QA",
    "sg:province":"Cardiff",
    "sg:tags":[
        "away",
        "meal",
        "outlet",
        "take"
    ],
    "wof:name":"Delhi Cuisine",
    "wof:placetype":"venue"
},
  "geometry": {"coordinates":[-3.2000279427,51.5119094849],"type":"Point"}
}