{
  "type": "Feature",
  "properties": {
    "iso:country":"GB",
    "sg:address":"70-74 Norwich Avenue West, Westbourne",
    "sg:city":"Bournemouth",
    "sg:classifiers":[
        {
            "category":"Building & Trades",
            "subcategory":"Construction",
            "type":"Services"
        }
    ],
    "sg:phone":"+44 1202 762020",
    "sg:postcode":"BH2 6AW",
    "sg:province":"Dorset",
    "sg:tags":[
        "contractor",
        "paving",
        "driveway"
    ],
    "wof:name":"Drivescape Ltd.",
    "wof:placetype":"venue"
},
  "geometry": {"coordinates":[-1.892007,50.721485],"type":"Point"}
}