{
  "type": "Feature",
  "properties": {
    "addr:full":"17 The Mall, 359 Upper St London Greater London N1 0PD",
    "addr:housenumber":"17;359",
    "addr:postcode":"n1 0pd",
    "addr:street":"The;Upper St",
    "iso:country":"GB",
    "sg:address":"17 The Mall, 359 Upper St",
    "sg:city":"London",
    "sg:classifiers":[
        {
            "category":"Shopping",
            "subcategory":"Used Merchandise",
            "type":"Retail Goods"
        }
    ],
    "sg:postcode":"N1 0PD",
    "sg:province":"Greater London",
    "sg:tags":[
        "shop",
        "second-hand"
    ],
    "wof:name":"Goldstrom,A & T,",
    "wof:placetype":"venue"
},
  "geometry": {"coordinates":[-0.104629,51.534466],"type":"Point"}
}