{
  "type": "Feature",
  "properties": {
    "iso:country":"GB",
    "sg:address":"143-145 Fulham Rd",
    "sg:city":"Chelsea",
    "sg:classifiers":[
        {
            "category":"Professional",
            "type":"Services"
        }
    ],
    "sg:phone":"+44 20 7584 9808",
    "sg:postcode":"SW3 6SD",
    "sg:province":"Greater London",
    "sg:tags":[
        "interior",
        "furnishers",
        "designer"
    ],
    "wof:name":"Oggetti Alessi",
    "wof:placetype":"venue"
},
  "geometry": {"coordinates":[-0.170592,51.49231],"type":"Point"}
}