{
  "type": "Feature",
  "properties": {
    "addr:full":"116 London Road Leicester Leicestershire LE2 0QS",
    "addr:housenumber":"116",
    "addr:postcode":"le2 0qs",
    "addr:street":"London Road",
    "iso:country":"GB",
    "sg:address":"116 London Road",
    "sg:city":"Leicester",
    "sg:classifiers":[
        {
            "category":"Cafe",
            "type":"Food & Drink"
        }
    ],
    "sg:phone":"+44 116 254 0255",
    "sg:postcode":"LE2 0QS",
    "sg:province":"Leicestershire",
    "sg:tags":[
        "tea",
        "room"
    ],
    "wof:name":"The Snack Box",
    "wof:placetype":"venue"
},
  "geometry": {"coordinates":[-1.1204500198,52.6278152466],"type":"Point"}
}