{
  "type": "Feature",
  "properties": {
    "addr:full":"113 Whitehouse Loan Edinburgh City of Edinburgh EH9 1BB",
    "addr:housenumber":"113",
    "addr:postcode":"eh9 1bb",
    "addr:street":"Whitehouse Loan",
    "iso:country":"GB",
    "sg:address":"113 Whitehouse Loan",
    "sg:city":"Edinburgh",
    "sg:classifiers":[
        {
            "category":"Organizations",
            "subcategory":"Religious Organization",
            "type":"Services"
        }
    ],
    "sg:phone":"+44 131 452 8794",
    "sg:postcode":"EH9 1BB",
    "sg:province":"City of Edinburgh",
    "sg:tags":[
        "organisation"
    ],
    "wof:name":"The Adult Formation Centre",
    "wof:placetype":"venue"
},
  "geometry": {"coordinates":[-3.188699007,55.9380493164],"type":"Point"}
}