{
  "type": "Feature",
  "properties": {
    "addr:full":"Arch 34 Portslade Road London Greater London SW8 3DH",
    "addr:housenumber":"34",
    "addr:postcode":"sw8 3dh",
    "addr:street":"Arch;Portslade Road",
    "iso:country":"GB",
    "sg:address":"Arch 34 Portslade Road",
    "sg:city":"London",
    "sg:classifiers":[
        {
            "category":"Retail",
            "subcategory":"Auto Repair",
            "type":"Services"
        }
    ],
    "sg:phone":"+44 20 7498 5657",
    "sg:postcode":"SW8 3DH",
    "sg:province":"Greater London",
    "sg:tags":[
        "modification",
        "garage",
        "related"
    ],
    "wof:name":"Auto Ian",
    "wof:placetype":"venue"
},
  "geometry": {"coordinates":[-0.1403100044,51.471408844],"type":"Point"}
}