{
  "type": "Feature",
  "properties": {
    "addr:full":"123 Liverpool Rd Newcastle Staffordshire ST5 9ER",
    "addr:housenumber":"123",
    "addr:postcode":"st5 9er",
    "addr:street":"Liverpool Rd",
    "iso:country":"GB",
    "sg:address":"123 Liverpool Rd",
    "sg:city":"Newcastle",
    "sg:classifiers":[
        {
            "category":"Health Services",
            "subcategory":"Doctor",
            "type":"Services"
        }
    ],
    "sg:phone":"+44 1782 637082",
    "sg:postcode":"ST5 9ER",
    "sg:province":"Staffordshire",
    "sg:tags":[
        "practitioners"
    ],
    "wof:name":"Hussain, L M",
    "wof:placetype":"venue"
},
  "geometry": {"coordinates":[-2.230815,53.018478],"type":"Point"}
}