{
  "type": "Feature",
  "properties": {
    "addr:full":"Foxfire, Beales Lane Farnham Hampshire GU10 4PY",
    "addr:postcode":"gu10 4py",
    "addr:street":"Beales Lane",
    "iso:country":"GB",
    "sg:address":"Foxfire, Beales Lane",
    "sg:city":"Farnham",
    "sg:classifiers":[
        {
            "category":"Home & Garden",
            "subcategory":"Building Materials",
            "type":"Retail Goods"
        }
    ],
    "sg:phone":"+44 1252 717582",
    "sg:postcode":"GU10 4PY",
    "sg:province":"Hampshire",
    "sg:tags":[
        "fencing"
    ],
    "wof:name":"Fawns (Aldershot) Ltd.",
    "wof:placetype":"venue"
},
  "geometry": {"coordinates":[-0.81843,51.198139],"type":"Point"}
}