{
  "type": "Feature",
  "properties": {
    "addr:full":"506-508 Coventry Road, Small Heath Birmingham West Midlands B10 0UN",
    "addr:housenumber":"506-508",
    "addr:postcode":"b10 0un",
    "addr:street":"Coventry Road",
    "iso:country":"GB",
    "sg:address":"506-508 Coventry Road, Small Heath",
    "sg:city":"Birmingham",
    "sg:classifiers":[
        {
            "category":"Personal",
            "subcategory":"Beauty Salon",
            "type":"Services"
        }
    ],
    "sg:phone":"+44 121 766 7107",
    "sg:postcode":"B10 0UN",
    "sg:province":"West Midlands",
    "sg:tags":[
        "unisex",
        "hairdresser"
    ],
    "wof:name":"D & O Cosmetics",
    "wof:placetype":"venue"
},
  "geometry": {"coordinates":[-1.857475996,52.4693603516],"type":"Point"}
}