{
  "type": "Feature",
  "properties": {
    "iso:country":"GB",
    "sg:address":"51 Leigh Road",
    "sg:city":"Eastleigh",
    "sg:classifiers":[
        {
            "category":"Shopping",
            "subcategory":"Used Merchandise",
            "type":"Retail Goods"
        }
    ],
    "sg:phone":"+44 23 8064 2651",
    "sg:postcode":"SO50 9DD",
    "sg:province":"Hampshire",
    "sg:tags":[
        "shop",
        "second-hand"
    ],
    "wof:name":"Cash Convertors",
    "wof:placetype":"venue"
},
  "geometry": {"coordinates":[-1.354366,50.969364],"type":"Point"}
}