{
  "type": "Feature",
  "properties": {
    "iso:country":"GB",
    "sg:address":"578 Glasgow Road",
    "sg:city":"Clydebank",
    "sg:classifiers":[
        {
            "category":"Autos & Motor Vehicles",
            "subcategory":"Auto Supplies",
            "type":"Retail Goods"
        }
    ],
    "sg:phone":"+44 141 952 7848",
    "sg:postcode":"G81 1NH",
    "sg:province":"East Dunbartonshire",
    "sg:tags":[
        "tyre"
    ],
    "wof:name":"National Tyres and Autocare",
    "wof:placetype":"venue"
},
  "geometry": {"coordinates":[-4.3879442215,55.8912887573],"type":"Point"}
}