{
  "type": "Feature",
  "properties": {
    "addr:full":"18 New St, Mawdesley Ormskirk Lancashire L40 2QP",
    "addr:housenumber":"18",
    "addr:postcode":"l40 2qp",
    "addr:street":"New St",
    "iso:country":"GB",
    "sg:address":"18 New St, Mawdesley",
    "sg:city":"Ormskirk",
    "sg:classifiers":[
        {
            "category":"Retail",
            "subcategory":"Auto Repair",
            "type":"Services"
        }
    ],
    "sg:phone":"+44 1704 822276",
    "sg:postcode":"L40 2QP",
    "sg:province":"Lancashire",
    "sg:tags":[
        "modification",
        "garage"
    ],
    "wof:name":"J.D Dickinson & Son",
    "wof:placetype":"venue"
},
  "geometry": {"coordinates":[-2.7694029808,53.62657547],"type":"Point"}
}