{
  "type": "Feature",
  "properties": {
    "iso:country":"GB",
    "sg:address":"52 Rosemead Drive, Oadby",
    "sg:city":"Leicester",
    "sg:classifiers":[
        {
            "category":"Government",
            "subcategory":"Post Office",
            "type":"Public Place"
        }
    ],
    "sg:phone":"+44 116 271 5487",
    "sg:postcode":"LE2 5SF",
    "sg:province":"Leicestershire",
    "wof:name":"South Oadby Post Office",
    "wof:placetype":"venue"
},
  "geometry": {"coordinates":[-1.0778330564,52.5930862427],"type":"Point"}
}