{
  "type": "Feature",
  "properties": {
    "iso:country":"GB",
    "sg:address":"93 Pontmorlais",
    "sg:city":"Merthyr Tydfil",
    "sg:classifiers":[
        {
            "category":"Shopping",
            "subcategory":"Gifts & Souvenirs",
            "type":"Retail Goods"
        }
    ],
    "sg:postcode":"CF47 8UH",
    "sg:province":"Merthyr Tydfil",
    "sg:tags":[
        "shop"
    ],
    "wof:name":"Savannah Moon",
    "wof:placetype":"venue"
},
  "geometry": {"coordinates":[-3.379349,51.74905],"type":"Point"}
}