{
  "type": "Feature",
  "properties": {
    "addr:full":"Leicester Road Lutterworth Leicestershire LE17 4NJ",
    "addr:postcode":"le17 4nj",
    "addr:street":"Leicester Road",
    "iso:country":"GB",
    "sg:address":"Leicester Road",
    "sg:city":"Lutterworth",
    "sg:classifiers":[
        {
            "category":"Shopping",
            "subcategory":"Bicycles & Sporting Goods",
            "type":"Retail Goods"
        }
    ],
    "sg:phone":"+44 1455 559309",
    "sg:postcode":"LE17 4NJ",
    "sg:province":"Leicestershire",
    "sg:tags":[
        "cycle",
        "accessory"
    ],
    "wof:name":"Lutterworth Cycle Centre",
    "wof:placetype":"venue"
},
  "geometry": {"coordinates":[-1.198149,52.46571],"type":"Point"}
}