{
  "type": "Feature",
  "properties": {
    "iso:country":"GB",
    "sg:address":"Haven Lane",
    "sg:city":"Oldham",
    "sg:classifiers":[
        {
            "category":"Education",
            "subcategory":"University",
            "type":"Public Place"
        },
        {
            "category":"Community Center",
            "subcategory":"Youth",
            "type":"Public Place"
        },
        {
            "category":"Government",
            "subcategory":"Office",
            "type":"Public Place"
        }
    ],
    "sg:phone":"+44 161 678 7360",
    "sg:postcode":"OL4 2QH",
    "sg:province":"Lancashire",
    "sg:tags":[
        "local",
        "adult",
        "centre"
    ],
    "wof:name":"OLDHAM METROPOLITAN BOROUGH COUNCIL",
    "wof:placetype":"venue"
},
  "geometry": {"coordinates":[-2.0751190186,53.5616989136],"type":"Point"}
}