{
  "type": "Feature",
  "properties": {
    "addr:full":"Beaulieu Wood Farm, Buckland Newton Dorchester Dorset DT2 7DG",
    "addr:postcode":"dt2 7dg",
    "addr:street":"Wood;Buckland Newton",
    "iso:country":"GB",
    "sg:address":"Beaulieu Wood Farm, Buckland Newton",
    "sg:city":"Dorchester",
    "sg:classifiers":[
        {
            "category":"Farming",
            "subcategory":"Livestock Farm",
            "type":"Manufacturing & Wholesale Goods"
        }
    ],
    "sg:postcode":"DT2 7DG",
    "sg:province":"Dorset",
    "sg:tags":[
        "others"
    ],
    "wof:name":"Barry Douglas George Newman",
    "wof:placetype":"venue"
},
  "geometry": {"coordinates":[-2.444163,50.843937],"type":"Point"}
}