{
  "type": "Feature",
  "properties": {
    "addr:full":"29 Daniel Clo, Thurrock Grays Essex RM16 6PR",
    "addr:housenumber":"29",
    "addr:postcode":"rm16 6pr",
    "addr:street":"Daniel;Grays",
    "iso:country":"GB",
    "sg:address":"29 Daniel Clo, Thurrock",
    "sg:city":"Grays",
    "sg:classifiers":[
        {
            "category":"Building & Trades",
            "subcategory":"Construction",
            "type":"Services"
        }
    ],
    "sg:postcode":"RM16 6PR",
    "sg:province":"Essex",
    "sg:tags":[
        "dry",
        "lining",
        "plasterers",
        "screeders"
    ],
    "wof:name":"Spreadwell Plastering",
    "wof:placetype":"venue"
},
  "geometry": {"coordinates":[0.3051759899,51.4926147461],"type":"Point"}
}