{
  "type": "Feature",
  "properties": {
    "addr:full":"14 Ray Drive Maidenhead Berkshire SL6 8NG",
    "addr:housenumber":"14",
    "addr:postcode":"sl6 8ng",
    "addr:street":"Ray Drive",
    "iso:country":"GB",
    "sg:address":"14 Ray Drive",
    "sg:city":"Maidenhead",
    "sg:classifiers":[
        {
            "category":"Shopping",
            "subcategory":"Pharmacy",
            "type":"Retail Goods"
        }
    ],
    "sg:phone":"+44 1628 778121",
    "sg:postcode":"SL6 8NG",
    "sg:province":"Berkshire",
    "sg:tags":[
        "medicine",
        "therapy"
    ],
    "wof:name":"Herbal Medicine Clinic",
    "wof:placetype":"venue"
},
  "geometry": {"coordinates":[-0.7063339949,51.5241355896],"type":"Point"}
}