{
  "type": "Feature",
  "properties": {
    "addr:full":"65 North Square London Greater London N9 0HY",
    "addr:housenumber":"65",
    "addr:postcode":"n9 0hy",
    "addr:street":"North Square",
    "iso:country":"GB",
    "sg:address":"65 North Square",
    "sg:city":"London",
    "sg:classifiers":[
        {
            "category":"Social Services",
            "subcategory":"Job Training",
            "type":"Services"
        },
        {
            "category":"Community Center",
            "type":"Public Place"
        }
    ],
    "sg:phone":"+44 20 8345 6301",
    "sg:postcode":"N9 0HY",
    "sg:province":"Greater London",
    "sg:tags":[
        "centre"
    ],
    "wof:name":"Enfield Education & Training Centre",
    "wof:placetype":"venue"
},
  "geometry": {"coordinates":[-0.0571100004,51.6258087158],"type":"Point"}
}