{
  "type": "Feature",
  "properties": {
    "iso:country":"GB",
    "sg:address":"41 Baltic Gardens",
    "sg:city":"Dundee",
    "sg:classifiers":[
        {
            "category":"Social Services",
            "subcategory":"Adult Care",
            "type":"Services"
        },
        {
            "category":"Real Estate",
            "subcategory":"Real Estate Agent",
            "type":"Services"
        }
    ],
    "sg:phone":"+44 1382 643458",
    "sg:postcode":"DD2 1EA",
    "sg:province":"Dundee City",
    "sg:tags":[
        "housing",
        "sheltered"
    ],
    "wof:name":"Step Row Sheltered Housing",
    "wof:placetype":"venue"
},
  "geometry": {"coordinates":[-3.051436,56.462132],"type":"Point"}
}