{
  "type": "Feature",
  "properties": {
    "addr:full":"10 Institute Road Swanage Dorset BH19 1BX",
    "addr:housenumber":"10",
    "addr:postcode":"bh19 1bx",
    "addr:street":"Institute Road",
    "iso:country":"GB",
    "sg:address":"10 Institute Road",
    "sg:city":"Swanage",
    "sg:classifiers":[
        {
            "category":"Transit Center",
            "subcategory":"Freight",
            "type":"Transportation"
        }
    ],
    "sg:postcode":"BH19 1BX",
    "sg:province":"Dorset",
    "sg:tags":[
        "shop",
        "craft",
        "centre"
    ],
    "wof:name":"Casa Jarris",
    "wof:placetype":"venue"
},
  "geometry": {"coordinates":[-1.9571570158,50.6087799072],"type":"Point"}
}