{
  "type": "Feature",
  "properties": {
    "addr:full":"Rosemary Lane Peterlee Durham SR8 3BQ",
    "addr:postcode":"sr8 3bq",
    "addr:street":"Rosemary Lane",
    "iso:country":"GB",
    "sg:address":"Rosemary Lane",
    "sg:city":"Peterlee",
    "sg:classifiers":[
        {
            "category":"Farming",
            "subcategory":"Nursery",
            "type":"Manufacturing & Wholesale Goods"
        },
        {
            "category":"Government",
            "subcategory":"Office",
            "type":"Public Place"
        }
    ],
    "sg:phone":"+44 191 527 1168",
    "sg:postcode":"SR8 3BQ",
    "sg:province":"Durham",
    "sg:tags":[
        "local",
        "creche"
    ],
    "wof:name":"Rosemary Lane Nursery School",
    "wof:placetype":"venue"
},
  "geometry": {"coordinates":[-1.355236,54.785027],"type":"Point"}
}