{
  "type": "Feature",
  "properties": {
    "addr:full":"191 Sherwood Street, Warsop Mansfield Derbyshire NG20 0HG",
    "addr:housenumber":"191",
    "addr:postcode":"ng20 0hg",
    "addr:street":"Sherwood Street",
    "iso:country":"GB",
    "sg:address":"191 Sherwood Street, Warsop",
    "sg:city":"Mansfield",
    "sg:classifiers":[
        {
            "category":"Building & Trades",
            "subcategory":"Construction",
            "type":"Services"
        }
    ],
    "sg:postcode":"NG20 0HG",
    "sg:province":"Derbyshire",
    "sg:tags":[
        "decorator",
        "painter"
    ],
    "wof:name":"William Buxton",
    "wof:placetype":"venue"
},
  "geometry": {"coordinates":[-1.1464220285,53.1976509094],"type":"Point"}
}