{
  "type": "Feature",
  "properties": {
    "addr:full":"132 Queens Rd, Beighton Sheffield South Yorkshire S20 1DW",
    "addr:housenumber":"132",
    "addr:postcode":"s20 1dw",
    "addr:street":"Queens Rd",
    "iso:country":"GB",
    "sg:address":"132 Queens Rd, Beighton",
    "sg:city":"Sheffield",
    "sg:classifiers":[
        {
            "category":"Food & Beverages",
            "subcategory":"Bakery",
            "type":"Retail Goods"
        }
    ],
    "sg:phone":"+44 114 269 4444",
    "sg:postcode":"S20 1DW",
    "sg:province":"South Yorkshire",
    "sg:tags":[
        "baker"
    ],
    "wof:name":"R Smith & Son",
    "wof:placetype":"venue"
},
  "geometry": {"coordinates":[-1.343525,53.349564],"type":"Point"}
}