{
  "type": "Feature",
  "properties": {
    "addr:full":"203 High Street London Greater London W3 9DR",
    "addr:housenumber":"203",
    "addr:postcode":"w3 9dr",
    "addr:street":"High Street",
    "iso:country":"GB",
    "sg:address":"203 High Street",
    "sg:city":"London",
    "sg:classifiers":[
        {
            "category":"Professional",
            "type":"Services"
        },
        {
            "category":"Real Estate",
            "subcategory":"Real Estate Agent",
            "type":"Services"
        }
    ],
    "sg:phone":"+44 20 8992 0056",
    "sg:postcode":"W3 9DR",
    "sg:province":"Greater London",
    "sg:tags":[
        "auctioneer"
    ],
    "wof:name":"Eydmann Street & Bridge",
    "wof:placetype":"venue"
},
  "geometry": {"coordinates":[-0.272464,51.507385],"type":"Point"}
}