{
  "type": "Feature",
  "properties": {
    "iso:country":"GB",
    "sg:address":"Nova Chambers",
    "sg:city":"Cheadle",
    "sg:classifiers":[
        {
            "category":"Professional",
            "subcategory":"Computer Services",
            "type":"Services"
        }
    ],
    "sg:phone":"+44 161 491 4726",
    "sg:postcode":"SK8 1DW",
    "sg:province":"Cheshire",
    "sg:tags":[
        "information"
    ],
    "wof:name":"Lorac Clinical Pharmacy Services Ltd.",
    "wof:placetype":"venue"
},
  "geometry": {"coordinates":[-2.212272,53.395248],"type":"Point"}
}