{
  "type": "Feature",
  "properties": {
    "iso:country":"GB",
    "sg:address":"50 Chesnut Avenue, The Parade Oadby",
    "sg:city":"Leicester",
    "sg:classifiers":[
        {
            "category":"Sports & Exercise",
            "subcategory":"Sports Center",
            "type":"Entertainment"
        }
    ],
    "sg:phone":"+44 116 271 2651",
    "sg:postcode":"LE2 5JG",
    "sg:province":"Leicestershire",
    "sg:tags":[
        "shop",
        "good"
    ],
    "wof:name":"David Bedder Sports",
    "wof:placetype":"venue"
},
  "geometry": {"coordinates":[-1.0840270519,52.5986862183],"type":"Point"}
}