{
  "type": "Feature",
  "properties": {
    "addr:full":"11 Quarter Gate Chelmsford Essex CM3 5GT",
    "addr:housenumber":"11",
    "addr:postcode":"cm3 5gt",
    "addr:street":"Quarter Gate",
    "iso:country":"GB",
    "sg:address":"11 Quarter Gate",
    "sg:city":"Chelmsford",
    "sg:classifiers":[
        {
            "category":"Building & Trades",
            "subcategory":"Plumbing",
            "type":"Services"
        }
    ],
    "sg:postcode":"CM3 5GT",
    "sg:province":"Essex",
    "sg:tags":[
        "central",
        "heating"
    ],
    "wof:name":"Broughton Plumbing",
    "wof:placetype":"venue"
},
  "geometry": {"coordinates":[0.6192709804,51.6372718811],"type":"Point"}
}