{
  "type": "Feature",
  "properties": {
    "addr:full":"Unit 1 Sandy Bridge Llanelli Carmarthenshire SA15 3EU",
    "addr:housenumber":"unit 1",
    "addr:postcode":"sa15 3eu",
    "addr:street":"Sandy Bridge",
    "iso:country":"GB",
    "sg:address":"Unit 1 Sandy Bridge",
    "sg:city":"Llanelli",
    "sg:classifiers":[
        {
            "category":"Home & Garden",
            "subcategory":"Carpets & Floor Coverings",
            "type":"Retail Goods"
        }
    ],
    "sg:phone":"+44 1554 776666",
    "sg:postcode":"SA15 3EU",
    "sg:province":"Carmarthenshire",
    "sg:tags":[
        "carpets",
        "rug",
        "matting"
    ],
    "wof:name":"Mike Rickwood Carpet Wharehouse",
    "wof:placetype":"venue"
},
  "geometry": {"coordinates":[-4.1726279259,51.6838302612],"type":"Point"}
}