{
  "type": "Feature",
  "properties": {
    "addr:full":"320 High Street Bangor Gwynedd LL57 1YA",
    "addr:housenumber":"320",
    "addr:postcode":"ll57 1ya",
    "addr:street":"High Street",
    "iso:country":"GB",
    "sg:address":"320 High Street",
    "sg:city":"Bangor",
    "sg:classifiers":[
        {
            "category":"Shopping",
            "subcategory":"Music",
            "type":"Retail Goods"
        }
    ],
    "sg:phone":"+44 1248 353020",
    "sg:postcode":"LL57 1YA",
    "sg:province":"Gwynedd",
    "sg:tags":[
        "dvd",
        "record",
        "tape",
        "vinyl",
        "cd"
    ],
    "sg:website":"http://www.cobrecordsbangor.com",
    "wof:name":"Cob Records",
    "wof:placetype":"venue"
},
  "geometry": {"coordinates":[-4.114512,53.230942],"type":"Point"}
}