{
  "type": "Feature",
  "properties": {
    "addr:full":"335 Dover Road, Walmer Deal Kent CT14 7NX",
    "addr:housenumber":"335",
    "addr:postcode":"ct14 7nx",
    "addr:street":"Dover Road",
    "iso:country":"GB",
    "sg:address":"335 Dover Road, Walmer",
    "sg:city":"Deal",
    "sg:classifiers":[
        {
            "category":"Bars & Pubs",
            "type":"Food & Drink"
        }
    ],
    "sg:postcode":"CT14 7NX",
    "sg:province":"Kent",
    "sg:tags":[
        "pubs",
        "inn"
    ],
    "wof:name":"The Thompson Bell",
    "wof:placetype":"venue"
},
  "geometry": {"coordinates":[1.388447,51.200764],"type":"Point"}
}