{
  "type": "Feature",
  "properties": {
    "addr:full":"16 Fore Street Taunton Somerset TA1 1HX",
    "addr:housenumber":"16",
    "addr:postcode":"ta1 1hx",
    "addr:street":"Fore Street",
    "iso:country":"GB",
    "sg:address":"16 Fore Street",
    "sg:city":"Taunton",
    "sg:classifiers":[
        {
            "category":"Banks & Credit Unions",
            "subcategory":"Financial Services",
            "type":"Services"
        }
    ],
    "sg:phone":"+44 1823 288465",
    "sg:postcode":"TA1 1HX",
    "sg:province":"Somerset",
    "sg:tags":[
        "building",
        "society"
    ],
    "wof:name":"Portman Building Society",
    "wof:placetype":"venue"
},
  "geometry": {"coordinates":[-3.10291,51.014744],"type":"Point"}
}