{
  "type": "Feature",
  "properties": {
    "addr:full":"70-71 New Bond St London Greater London W1S 1DE",
    "addr:housenumber":"70-71",
    "addr:postcode":"w1s 1de",
    "addr:street":"New Bond St",
    "iso:country":"GB",
    "sg:address":"70-71 New Bond St",
    "sg:city":"London",
    "sg:classifiers":[
        {
            "category":"Professional",
            "subcategory":"Employment Agencies",
            "type":"Services"
        }
    ],
    "sg:postcode":"W1S 1DE",
    "sg:province":"Greater London",
    "sg:tags":[
        "consultant"
    ],
    "wof:name":"Mainstream Personnel Ltd",
    "wof:placetype":"venue"
},
  "geometry": {"coordinates":[-0.1456809938,51.5137138367],"type":"Point"}
}