{
  "type": "Feature",
  "properties": {
    "iso:country":"GB",
    "sg:address":"Sarai, Danesway",
    "sg:city":"High Peak",
    "sg:classifiers":[
        {
            "category":"Shopping",
            "subcategory":"Computers & Home Electronics",
            "type":"Retail Goods"
        }
    ],
    "sg:phone":"+44 1298 814641",
    "sg:postcode":"SK23 0JH",
    "sg:province":"Cheshire",
    "sg:tags":[
        "aerial",
        "television",
        "radio"
    ],
    "wof:name":"Antenna",
    "wof:placetype":"venue"
},
  "geometry": {"coordinates":[-1.912532,53.325478],"type":"Point"}
}