{
  "type": "Feature",
  "properties": {
    "iso:country":"GB",
    "sg:address":"New House, Welton",
    "sg:city":"Carlisle",
    "sg:classifiers":[
        {
            "category":"Farming",
            "subcategory":"Farm",
            "type":"Manufacturing & Wholesale Goods"
        }
    ],
    "sg:postcode":"CA5 7HN",
    "sg:province":"Cumbria",
    "sg:tags":[
        "mixed",
        "crop"
    ],
    "wof:name":"Leonard Skelton",
    "wof:placetype":"venue"
},
  "geometry": {"coordinates":[-2.980079,54.81028],"type":"Point"}
}