{
  "type": "Feature",
  "properties": {
    "iso:country":"GB",
    "sg:address":"Sherborne House, 13 Savile Row",
    "sg:city":"London",
    "sg:classifiers":[
        {
            "category":"Shopping",
            "subcategory":"News",
            "type":"Retail Goods"
        }
    ],
    "sg:phone":"+44 20 7734 3366",
    "sg:postcode":"W1S 3PR",
    "sg:province":"Greater London",
    "sg:tags":[
        "newsagent"
    ],
    "wof:name":"Ford Mills Ltd.",
    "wof:placetype":"venue"
},
  "geometry": {"coordinates":[-0.140273,51.511002],"type":"Point"}
}