{
  "type": "Feature",
  "properties": {
    "iso:country":"GB",
    "sg:address":"Unit 5 The Billings, 3 Walnut Tree Close",
    "sg:city":"Guildford",
    "sg:classifiers":[
        {
            "category":"Wholesale",
            "subcategory":"Machinery & Supplies",
            "type":"Manufacturing & Wholesale Goods"
        }
    ],
    "sg:phone":"+44 1483 300926",
    "sg:postcode":"GU1 4UL",
    "sg:province":"Surrey",
    "sg:tags":[
        "theatrical"
    ],
    "wof:name":"Bower Wood Presentations & Production Services",
    "wof:placetype":"venue"
},
  "geometry": {"coordinates":[-0.570516,51.237087],"type":"Point"}
}