{
  "type": "Feature",
  "properties": {
    "iso:country":"GB",
    "sg:address":"20 Richardson Road",
    "sg:city":"Hove",
    "sg:classifiers":[
        {
            "category":"Deli",
            "type":"Food & Drink"
        },
        {
            "category":"Farming",
            "subcategory":"Fish & Marine Products",
            "type":"Manufacturing & Wholesale Goods"
        }
    ],
    "sg:phone":"+44 1273 738779",
    "sg:postcode":"BN3 5RB",
    "sg:province":"East Sussex",
    "sg:tags":[
        "fishmonger",
        "delicatessen"
    ],
    "wof:name":"Cantors of Hove",
    "wof:placetype":"venue"
},
  "geometry": {"coordinates":[-0.188417,50.831188],"type":"Point"}
}