{
  "type": "Feature",
  "properties": {
    "addr:full":"4 Gatcombe Close, Calcot Reading Berkshire RG31 4XQ",
    "addr:housenumber":"4",
    "addr:postcode":"rg31 4xq",
    "addr:street":"Gatcombe Close",
    "iso:country":"GB",
    "sg:address":"4 Gatcombe Close, Calcot",
    "sg:city":"Reading",
    "sg:classifiers":[
        {
            "category":"Building & Trades",
            "subcategory":"Plumbing",
            "type":"Services"
        }
    ],
    "sg:phone":"+44 118 941 8291",
    "sg:postcode":"RG31 4XQ",
    "sg:province":"Berkshire",
    "sg:tags":[
        "heating"
    ],
    "wof:name":"M Thomas Plumbing & Heating",
    "wof:placetype":"venue"
},
  "geometry": {"coordinates":[-1.0492719412,51.442779541],"type":"Point"}
}