{
  "type": "Feature",
  "properties": {
    "addr:full":"Station Road, Patchway Bristol Gloucestershire BS34 6LR",
    "addr:postcode":"bs34 6lr",
    "addr:street":"Station Road",
    "iso:country":"GB",
    "sg:address":"Station Road, Patchway",
    "sg:city":"Bristol",
    "sg:classifiers":[
        {
            "category":"Manufacturing",
            "subcategory":"Building Materials",
            "type":"Manufacturing & Wholesale Goods"
        }
    ],
    "sg:phone":"+44 117 931 5071",
    "sg:postcode":"BS34 6LR",
    "sg:province":"Gloucestershire",
    "sg:tags":[
        "merchant",
        "builder"
    ],
    "wof:name":"Patchway Building Supplies",
    "wof:placetype":"venue"
},
  "geometry": {"coordinates":[-2.5667750835,51.5315933228],"type":"Point"}
}