{
  "type": "Feature",
  "properties": {
    "iso:country":"GB",
    "sg:address":"The Mount, Bounty Road",
    "sg:city":"Basingstoke",
    "sg:classifiers":[
        {
            "category":"Professional",
            "type":"Services"
        }
    ],
    "sg:phone":"+44 1256 414050",
    "sg:postcode":"RG21 3DD",
    "sg:province":"Hampshire",
    "sg:tags":[
        "caterer"
    ],
    "wof:name":"John Burton Catering",
    "wof:placetype":"venue"
},
  "geometry": {"coordinates":[-1.083089,51.262444],"type":"Point"}
}