{
  "type": "Feature",
  "properties": {
    "addr:full":"183 Bruntsfield Place Edinburgh City of Edinburgh EH10 4DG",
    "addr:housenumber":"183",
    "addr:postcode":"eh10 4dg",
    "addr:street":"Bruntsfield Place Edinburgh",
    "iso:country":"GB",
    "sg:address":"183 Bruntsfield Place",
    "sg:city":"Edinburgh",
    "sg:classifiers":[
        {
            "category":"Bars & Pubs",
            "type":"Food & Drink"
        },
        {
            "category":"Fast Food",
            "type":"Food & Drink"
        }
    ],
    "sg:phone":"+44 131 228 4770",
    "sg:postcode":"EH10 4DG",
    "sg:province":"City of Edinburgh",
    "sg:tags":[
        "away",
        "pubs",
        "inn",
        "outlet",
        "meal",
        "take"
    ],
    "wof:name":"INCA",
    "wof:placetype":"venue"
},
  "geometry": {"coordinates":[-3.2098588943,55.9360275269],"type":"Point"}
}