{
  "type": "Feature",
  "properties": {
    "iso:country":"GB",
    "sg:address":"19 Broadwater Rd",
    "sg:city":"Welwyn Garden City",
    "sg:classifiers":[
        {
            "category":"Shopping",
            "type":"Retail Goods"
        }
    ],
    "sg:phone":"+44 1707 325564",
    "sg:postcode":"AL7 3BQ",
    "sg:province":"Hertfordshire",
    "sg:tags":[
        "part",
        "accessory"
    ],
    "wof:name":"Autela Wheels",
    "wof:placetype":"venue"
},
  "geometry": {"coordinates":[-0.1994449943,51.7998847961],"type":"Point"}
}