{
  "type": "Feature",
  "properties": {
    "addr:full":"12 Spindleberry Gro Bristol Somerset BS48 1QE",
    "addr:housenumber":"12",
    "addr:postcode":"bs48 1qe",
    "addr:street":"Spindleberry Gro",
    "iso:country":"GB",
    "sg:address":"12 Spindleberry Gro",
    "sg:city":"Bristol",
    "sg:classifiers":[
        {
            "category":"Professional",
            "subcategory":"Management & Consulting",
            "type":"Services"
        }
    ],
    "sg:phone":"+44 1275 857040",
    "sg:postcode":"BS48 1QE",
    "sg:province":"Somerset",
    "sg:tags":[
        "consultant",
        "specialist"
    ],
    "wof:name":"Top To Toe",
    "wof:placetype":"venue"
},
  "geometry": {"coordinates":[-2.744785,51.435841],"type":"Point"}
}