{
  "type": "Feature",
  "properties": {
    "addr:full":"Southam Road, Long Itchington Southam Warwickshire CV47 9QL",
    "addr:postcode":"cv47 9ql",
    "addr:street":"Southam Road",
    "iso:country":"GB",
    "sg:address":"Southam Road, Long Itchington",
    "sg:city":"Southam",
    "sg:classifiers":[
        {
            "category":"Manufacturing",
            "subcategory":"Buildings",
            "type":"Manufacturing & Wholesale Goods"
        }
    ],
    "sg:phone":"+44 1926 815757",
    "sg:postcode":"CV47 9QL",
    "sg:province":"Warwickshire",
    "sg:tags":[
        "portable"
    ],
    "wof:name":"Warwick Buildings Ltd.",
    "wof:placetype":"venue"
},
  "geometry": {"coordinates":[-1.390047,52.277569],"type":"Point"}
}