{
  "type": "Feature",
  "properties": {
    "addr:full":"King Lane, Clutton Bristol Somerset BS39 5QL",
    "addr:postcode":"bs39 5ql",
    "addr:street":"King Lane",
    "iso:country":"GB",
    "sg:address":"King Lane, Clutton",
    "sg:city":"Bristol",
    "sg:classifiers":[
        {
            "category":"Bars & Pubs",
            "type":"Food & Drink"
        }
    ],
    "sg:phone":"+44 1761 452303",
    "sg:postcode":"BS39 5QL",
    "sg:province":"Somerset",
    "sg:tags":[
        "pubs",
        "inn"
    ],
    "wof:name":"Great Western Inns & Taverns Ltd.",
    "wof:placetype":"venue"
},
  "geometry": {"coordinates":[-2.5476930141,51.3304481506],"type":"Point"}
}