{
  "type": "Feature",
  "properties": {
    "iso:country":"GB",
    "sg:address":"4 Overstone Road",
    "sg:city":"Northampton",
    "sg:classifiers":[
        {
            "category":"Personal",
            "subcategory":"Tattoo Parlor",
            "type":"Services"
        }
    ],
    "sg:phone":"+44 1604 620644",
    "sg:postcode":"NN1 3JH",
    "sg:province":"Northamptonshire",
    "sg:tags":[
        "tattooing",
        "piercing"
    ],
    "wof:name":"Skin Skills",
    "wof:placetype":"venue"
},
  "geometry": {"coordinates":[-0.88891,52.243382],"type":"Point"}
}