{
  "type": "Feature",
  "properties": {
    "addr:full":"Fraisthorpe, Carnaby Bridlington East Riding of Yorkshire YO15 3QR",
    "addr:postcode":"yo15 3qr",
    "iso:country":"GB",
    "sg:address":"Fraisthorpe, Carnaby",
    "sg:city":"Bridlington",
    "sg:classifiers":[
        {
            "category":"Farming",
            "subcategory":"Farm",
            "type":"Manufacturing & Wholesale Goods"
        }
    ],
    "sg:postcode":"YO15 3QR",
    "sg:province":"East Riding of Yorkshire",
    "sg:tags":[
        "mixed",
        "crop"
    ],
    "wof:name":"G L Riby",
    "wof:placetype":"venue"
},
  "geometry": {"coordinates":[-0.240682,54.039665],"type":"Point"}
}