{
  "type": "Feature",
  "properties": {
    "addr:full":"The White House, 3 High Street Stevenage Hertfordshire SG1 3BG",
    "addr:housenumber":"3",
    "addr:postcode":"sg1 3bg",
    "addr:street":"High Street",
    "iso:country":"GB",
    "sg:address":"The White House, 3 High Street",
    "sg:city":"Stevenage",
    "sg:classifiers":[
        {
            "category":"Social Services",
            "subcategory":"Job Training",
            "type":"Services"
        },
        {
            "category":"Education",
            "subcategory":"Special Training",
            "type":"Public Place"
        }
    ],
    "sg:phone":"+44 1438 747897",
    "sg:postcode":"SG1 3BG",
    "sg:province":"Hertfordshire",
    "sg:tags":[
        "product",
        "centre"
    ],
    "wof:name":"Office Academy Ltd",
    "wof:placetype":"venue"
},
  "geometry": {"coordinates":[-0.208965,51.914684],"type":"Point"}
}