{
  "type": "Feature",
  "properties": {
    "addr:full":"209 Gorgie Road Edinburgh City of Edinburgh EH11 2PP",
    "addr:housenumber":"209",
    "addr:postcode":"eh11 2pp",
    "addr:street":"Gorgie Road",
    "iso:country":"GB",
    "sg:address":"209 Gorgie Road",
    "sg:city":"Edinburgh",
    "sg:classifiers":[
        {
            "category":"Cafe",
            "type":"Food & Drink"
        }
    ],
    "sg:postcode":"EH11 2PP",
    "sg:province":"City of Edinburgh",
    "sg:tags":[
        "tea",
        "room"
    ],
    "wof:name":"Koffee Pot",
    "wof:placetype":"venue"
},
  "geometry": {"coordinates":[-3.2426249981,55.9352111816],"type":"Point"}
}