{
  "type": "Feature",
  "properties": {
    "addr:full":"818 Newport Rd Cardiff Caerphilly CF3 8LH",
    "addr:housenumber":"818",
    "addr:postcode":"cf3 8lh",
    "addr:street":"Newport Rd",
    "iso:country":"GB",
    "sg:address":"818 Newport Rd",
    "sg:city":"Cardiff",
    "sg:classifiers":[
        {
            "category":"Shopping",
            "subcategory":"Florist",
            "type":"Retail Goods"
        }
    ],
    "sg:phone":"+44 29 2077 8143",
    "sg:postcode":"CF3 8LH",
    "sg:province":"Caerphilly",
    "wof:name":"Elizabeth Foulkes",
    "wof:placetype":"venue"
},
  "geometry": {"coordinates":[-3.130721,51.509289],"type":"Point"}
}