{
  "type": "Feature",
  "properties": {
    "iso:country":"GB",
    "sg:address":"Kirkstall Design Centre, Bridge Road, Kirkstall",
    "sg:city":"Leeds",
    "sg:classifiers":[
        {
            "category":"Professional",
            "subcategory":"Art Services",
            "type":"Services"
        }
    ],
    "sg:phone":"+44 113 274 2861",
    "sg:postcode":"LS5 3BW",
    "sg:province":"West Yorkshire",
    "sg:tags":[
        "photographer"
    ],
    "wof:name":"Visage",
    "wof:placetype":"venue"
},
  "geometry": {"coordinates":[-1.597249,53.816902],"type":"Point"}
}