{
  "type": "Feature",
  "properties": {
    "addr:full":"195 Marsh Rd Luton Bedfordshire LU3 2QQ",
    "addr:housenumber":"195",
    "addr:postcode":"lu3 2qq",
    "addr:street":"Marsh Rd",
    "iso:country":"GB",
    "sg:address":"195 Marsh Rd",
    "sg:city":"Luton",
    "sg:classifiers":[
        {
            "category":"Shopping",
            "subcategory":"News",
            "type":"Retail Goods"
        }
    ],
    "sg:phone":"+44 1582 597284",
    "sg:postcode":"LU3 2QQ",
    "sg:province":"Bedfordshire",
    "sg:tags":[
        "newsagent"
    ],
    "wof:name":"Gibbs Newsagents",
    "wof:placetype":"venue"
},
  "geometry": {"coordinates":[-0.454472,51.905102],"type":"Point"}
}