{
  "type": "Feature",
  "properties": {
    "iso:country":"GB",
    "sg:address":"Aspley Lane, Aspley",
    "sg:city":"Nottingham",
    "sg:classifiers":[
        {
            "category":"Bars & Pubs",
            "type":"Food & Drink"
        }
    ],
    "sg:phone":"+44 115 929 1821",
    "sg:postcode":"NG8 5RX",
    "sg:province":"Nottinghamshire",
    "sg:tags":[
        "pubs",
        "inn"
    ],
    "wof:name":"Beacon Hotel",
    "wof:placetype":"venue"
},
  "geometry": {"coordinates":[-1.2146719694,52.9736976624],"type":"Point"}
}