{
  "type": "Feature",
  "properties": {
    "iso:country":"GB",
    "sg:address":"187 Mayne Street",
    "sg:city":"Stoke-on-trent",
    "sg:classifiers":[
        {
            "category":"Shopping",
            "subcategory":"Clothing, Apparel, & Fashions",
            "type":"Retail Goods"
        }
    ],
    "sg:postcode":"ST4 4QZ",
    "sg:province":"Staffordshire",
    "sg:tags":[
        "shop"
    ],
    "wof:name":"Fashion Outlook",
    "wof:placetype":"venue"
},
  "geometry": {"coordinates":[-2.198549,52.976871],"type":"Point"}
}