{
  "type": "Feature",
  "properties": {
    "addr:full":"The Glade, Bronallt Rd, Hendy Swansea Carmarthenshire SA4 1UD",
    "addr:postcode":"sa4 1ud",
    "addr:street":"The Glade Bronallt Rd",
    "iso:country":"GB",
    "sg:address":"The Glade, Bronallt Rd, Hendy",
    "sg:city":"Swansea",
    "sg:classifiers":[
        {
            "category":"Professional",
            "type":"Services"
        }
    ],
    "sg:phone":"+44 1792 884201",
    "sg:postcode":"SA4 1UD",
    "sg:province":"Carmarthenshire",
    "sg:tags":[
        "exhibition"
    ],
    "wof:name":"Creative Designs",
    "wof:placetype":"venue"
},
  "geometry": {"coordinates":[-4.068570137,51.6847915649],"type":"Point"}
}