{
  "type": "Feature",
  "properties": {
    "addr:full":"24 Lea Road, Ravenshead Nottingham Nottinghamshire NG15 9EG",
    "addr:housenumber":"24",
    "addr:postcode":"ng15 9eg",
    "addr:street":"Lea Road",
    "iso:country":"GB",
    "sg:address":"24 Lea Road, Ravenshead",
    "sg:city":"Nottingham",
    "sg:classifiers":[
        {
            "category":"Education",
            "subcategory":"Music School",
            "type":"Public Place"
        }
    ],
    "sg:postcode":"NG15 9EG",
    "sg:province":"Nottinghamshire",
    "sg:tags":[
        "teacher"
    ],
    "wof:name":"David Evans",
    "wof:placetype":"venue"
},
  "geometry": {"coordinates":[-1.1565359831,53.0863876343],"type":"Point"}
}