{
  "type": "Feature",
  "properties": {
    "addr:full":"39 Carrs Lane, Cudworth Barnsley South Yorkshire S72 8EQ",
    "addr:housenumber":"39",
    "addr:postcode":"s72 8eq",
    "addr:street":"Carrs Lane;Yorkshire",
    "iso:country":"GB",
    "sg:address":"39 Carrs Lane, Cudworth",
    "sg:city":"Barnsley",
    "sg:classifiers":[
        {
            "category":"Education",
            "subcategory":"Music School",
            "type":"Public Place"
        }
    ],
    "sg:phone":"+44 1226 710985",
    "sg:postcode":"S72 8EQ",
    "sg:province":"South Yorkshire",
    "sg:tags":[
        "teacher"
    ],
    "wof:name":"Jack Richards",
    "wof:placetype":"venue"
},
  "geometry": {"coordinates":[-1.414224,53.568146],"type":"Point"}
}