{
  "type": "Feature",
  "properties": {
    "addr:full":"St Anns North, Watson Street, Letham Forfar Angus DD8 2QX",
    "addr:postcode":"dd8 2qx",
    "addr:street":"North Watson Street",
    "iso:country":"GB",
    "sg:address":"St Anns North, Watson Street, Letham",
    "sg:city":"Forfar",
    "sg:classifiers":[
        {
            "category":"Health Services",
            "subcategory":"Dentist",
            "type":"Services"
        }
    ],
    "sg:postcode":"DD8 2QX",
    "sg:province":"Angus",
    "wof:name":"S V Tallett",
    "wof:placetype":"venue"
},
  "geometry": {"coordinates":[-2.7691690922,56.6276359558],"type":"Point"}
}