{
  "type": "Feature",
  "properties": {
    "iso:country":"GB",
    "sg:address":"5 Langhorne Gardens",
    "sg:city":"Folkestone",
    "sg:classifiers":[
        {
            "category":"Building & Trades",
            "subcategory":"Construction",
            "type":"Services"
        }
    ],
    "sg:phone":"+44 1303 221634",
    "sg:postcode":"CT20 2EA",
    "sg:province":"Kent",
    "sg:tags":[
        "builder"
    ],
    "wof:name":"Alltrades Allhours",
    "wof:placetype":"venue"
},
  "geometry": {"coordinates":[1.1726200581,51.076423645],"type":"Point"}
}