{
  "type": "Feature",
  "properties": {
    "addr:full":"38 Spring Street London Greater London W2 1JA",
    "addr:housenumber":"38",
    "addr:postcode":"w2 1ja",
    "addr:street":"Spring Street",
    "iso:country":"GB",
    "sg:address":"38 Spring Street",
    "sg:city":"London",
    "sg:classifiers":[
        {
            "category":"Professional",
            "subcategory":"Detective & Security Services",
            "type":"Services"
        }
    ],
    "sg:phone":"+44 20 7706 2203",
    "sg:postcode":"W2 1JA",
    "sg:province":"Greater London",
    "wof:name":"Blue T Ltd.",
    "wof:placetype":"venue"
},
  "geometry": {"coordinates":[-0.175347,51.514687],"type":"Point"}
}