{
  "type": "Feature",
  "properties": {
    "iso:country":"GB",
    "sg:address":"12 Bilberry Close",
    "sg:city":"Stourport-on-severn",
    "sg:classifiers":[
        {
            "category":"Professional",
            "subcategory":"Engineering",
            "type":"Services"
        }
    ],
    "sg:postcode":"DY13 8TL",
    "sg:province":"Worcestershire",
    "sg:tags":[
        "structural",
        "engineer"
    ],
    "wof:name":"Steel Frame Designs Ltd",
    "wof:placetype":"venue"
},
  "geometry": {"coordinates":[-2.2911920547,52.3459320068],"type":"Point"}
}