{
  "type": "Feature",
  "properties": {
    "iso:country":"GB",
    "sg:address":"43 Belle Cross Road",
    "sg:city":"Kingsbridge",
    "sg:classifiers":[
        {
            "category":"Building & Trades",
            "subcategory":"Construction",
            "type":"Services"
        }
    ],
    "sg:postcode":"TQ7 1NL",
    "sg:province":"Devon",
    "sg:tags":[
        "builder"
    ],
    "wof:name":"G H Rhymes & Son",
    "wof:placetype":"venue"
},
  "geometry": {"coordinates":[-3.763435,50.290565],"type":"Point"}
}