{
  "type": "Feature",
  "properties": {
    "addr:full":"4 Fore Street Trowbridge Wiltshire BA14 8HD",
    "addr:housenumber":"4",
    "addr:postcode":"ba14 8hd",
    "addr:street":"Fore Street",
    "iso:country":"GB",
    "sg:address":"4 Fore Street",
    "sg:city":"Trowbridge",
    "sg:classifiers":[
        {
            "category":"Home & Garden",
            "subcategory":"Furniture",
            "type":"Retail Goods"
        }
    ],
    "sg:postcode":"BA14 8HD",
    "sg:province":"Wiltshire",
    "wof:name":"Belinda Miller",
    "wof:placetype":"venue"
},
  "geometry": {"coordinates":[-2.209891,51.321121],"type":"Point"}
}