{
  "type": "Feature",
  "properties": {
    "addr:full":"34 High St Luton Bedfordshire LU4 9LF",
    "addr:housenumber":"34",
    "addr:postcode":"lu4 9lf",
    "addr:street":"High St",
    "iso:country":"GB",
    "sg:address":"34 High St",
    "sg:city":"Luton",
    "sg:classifiers":[
        {
            "category":"Building & Trades",
            "subcategory":"Equipment Rental",
            "type":"Services"
        }
    ],
    "sg:phone":"+44 1582 597101",
    "sg:postcode":"LU4 9LF",
    "sg:province":"Bedfordshire",
    "sg:tags":[
        "plant",
        "machinery"
    ],
    "wof:name":"M & J Hire Centres",
    "wof:placetype":"venue"
},
  "geometry": {"coordinates":[-0.4655550122,51.902469635],"type":"Point"}
}