{
  "type": "Feature",
  "properties": {
    "addr:full":"13 Lucius Street Torquay Devon TQ2 5UW",
    "addr:housenumber":"13",
    "addr:postcode":"tq2 5uw",
    "addr:street":"Lucius Street",
    "iso:country":"GB",
    "sg:address":"13 Lucius Street",
    "sg:city":"Torquay",
    "sg:classifiers":[
        {
            "category":"Shopping",
            "subcategory":"News",
            "type":"Retail Goods"
        }
    ],
    "sg:phone":"+44 1803 405172",
    "sg:postcode":"TQ2 5UW",
    "sg:province":"Devon",
    "sg:tags":[
        "newsagent"
    ],
    "wof:name":"Smiths News",
    "wof:placetype":"venue"
},
  "geometry": {"coordinates":[-3.5384969711,50.4678153992],"type":"Point"}
}