{
  "type": "Feature",
  "properties": {
    "iso:country":"GB",
    "sg:address":"Unit 3 Brewery Yd, Brewery La",
    "sg:city":"Baldock",
    "sg:classifiers":[
        {
            "category":"Manufacturing",
            "subcategory":"Rubber & Plastics",
            "type":"Manufacturing & Wholesale Goods"
        }
    ],
    "sg:postcode":"SG7 5AT",
    "sg:province":"Bedfordshire",
    "sg:tags":[
        "mould"
    ],
    "wof:name":"Bygrave,Richard,",
    "wof:placetype":"venue"
},
  "geometry": {"coordinates":[-0.192096,51.990643],"type":"Point"}
}