{
  "type": "Feature",
  "properties": {
    "iso:country":"GB",
    "sg:address":"26 Lichfield Rd",
    "sg:city":"Exeter",
    "sg:classifiers":[
        {
            "category":"Banks & Credit Unions",
            "subcategory":"Financial Services",
            "type":"Services"
        }
    ],
    "sg:postcode":"EX4 2EU",
    "sg:province":"Devon",
    "sg:tags":[
        "agent",
        "tied"
    ],
    "wof:name":"Moreton Financial Partnership",
    "wof:placetype":"venue"
},
  "geometry": {"coordinates":[-3.561322,50.725082],"type":"Point"}
}