{
  "type": "Feature",
  "properties": {
    "addr:full":"Unit 4a Tinsley Industrial Estate, Shepcote Way Sheffield South Yorkshire S9 1TH",
    "addr:housenumber":"unit 4a",
    "addr:postcode":"s9 1th",
    "addr:street":"Tinsley Industrial Estate Shepcote Way",
    "iso:country":"GB",
    "sg:address":"Unit 4a Tinsley Industrial Estate, Shepcote Way",
    "sg:city":"Sheffield",
    "sg:classifiers":[
        {
            "category":"Professional",
            "subcategory":"Engineering",
            "type":"Services"
        }
    ],
    "sg:phone":"+44 114 256 5200",
    "sg:postcode":"S9 1TH",
    "sg:province":"South Yorkshire",
    "sg:tags":[
        "engineer"
    ],
    "wof:name":"Anfast Ltd.",
    "wof:placetype":"venue"
},
  "geometry": {"coordinates":[-1.410534,53.395969],"type":"Point"}
}