{
  "type": "Feature",
  "properties": {
    "addr:full":"322 Union Street Plymouth Devon PL1 3HP",
    "addr:housenumber":"322",
    "addr:postcode":"pl1 3hp",
    "addr:street":"Union Street",
    "iso:country":"GB",
    "sg:address":"322 Union Street",
    "sg:city":"Plymouth",
    "sg:classifiers":[
        {
            "category":"Food & Beverages",
            "subcategory":"Bakery",
            "type":"Retail Goods"
        }
    ],
    "sg:phone":"+44 1752 224380",
    "sg:postcode":"PL1 3HP",
    "sg:province":"Devon",
    "sg:tags":[
        "baker"
    ],
    "wof:name":"Warrens",
    "wof:placetype":"venue"
},
  "geometry": {"coordinates":[-4.158602,50.369625],"type":"Point"}
}