{
  "type": "Feature",
  "properties": {
    "addr:full":"74a High St Ipswich Suffolk IP6 8AW",
    "addr:housenumber":"74a",
    "addr:postcode":"ip6 8aw",
    "addr:street":"High St",
    "iso:country":"GB",
    "sg:address":"74a High St",
    "sg:city":"Ipswich",
    "sg:classifiers":[
        {
            "category":"Shopping",
            "subcategory":"Discount & Variety Stores",
            "type":"Retail Goods"
        }
    ],
    "sg:phone":"+44 1449 720327",
    "sg:postcode":"IP6 8AW",
    "sg:province":"Suffolk",
    "sg:tags":[
        "cleaning",
        "supply"
    ],
    "wof:name":"The Clean Shop",
    "wof:placetype":"venue"
},
  "geometry": {"coordinates":[1.0513429642,52.1544876099],"type":"Point"}
}