{
  "type": "Feature",
  "properties": {
    "addr:full":"31 Meat Wholesale Market, Pershore Street Birmingham West Midlands B5 4RJ",
    "addr:housenumber":"31",
    "addr:postcode":"b5 4rj",
    "addr:street":"Pershore Street",
    "iso:country":"GB",
    "sg:address":"31 Meat Wholesale Market, Pershore Street",
    "sg:city":"Birmingham",
    "sg:classifiers":[
        {
            "category":"Wholesale",
            "subcategory":"Meat",
            "type":"Manufacturing & Wholesale Goods"
        }
    ],
    "sg:phone":"+44 121 622 4751",
    "sg:postcode":"B5 4RJ",
    "sg:province":"West Midlands",
    "sg:tags":[
        "-"
    ],
    "wof:name":"Weddel Swift Distribution Ltd.",
    "wof:placetype":"venue"
},
  "geometry": {"coordinates":[-1.89552,52.475632],"type":"Point"}
}