{
  "type": "Feature",
  "properties": {
    "addr:full":"10 The Green Newport Pagnell Buckinghamshire MK16 0JW",
    "addr:housenumber":"10",
    "addr:postcode":"mk16 0jw",
    "addr:street":"The Green",
    "iso:country":"GB",
    "sg:address":"10 The Green",
    "sg:city":"Newport Pagnell",
    "sg:classifiers":[
        {
            "category":"Professional",
            "subcategory":"Management & Consulting",
            "type":"Services"
        }
    ],
    "sg:postcode":"MK16 0JW",
    "sg:province":"Buckinghamshire",
    "sg:tags":[
        "consultant",
        "business"
    ],
    "wof:name":"P G P Sales & Management Training Consul",
    "wof:placetype":"venue"
},
  "geometry": {"coordinates":[-0.728608,52.083893],"type":"Point"}
}