{
  "type": "Feature",
  "properties": {
    "addr:full":"20 Shear Brow Blackburn Lancashire BB1 7EU",
    "addr:housenumber":"20",
    "addr:postcode":"bb1 7eu",
    "addr:street":"Shear Brow",
    "iso:country":"GB",
    "sg:address":"20 Shear Brow",
    "sg:city":"Blackburn",
    "sg:classifiers":[
        {
            "category":"Professional",
            "type":"Services"
        }
    ],
    "sg:phone":"+44 1254 263146",
    "sg:postcode":"BB1 7EU",
    "sg:province":"Lancashire",
    "sg:tags":[
        "shopfitters"
    ],
    "wof:name":"Hi-Tech Contracts U K",
    "wof:placetype":"venue"
},
  "geometry": {"coordinates":[-2.4870679379,53.7539787292],"type":"Point"}
}