{
  "type": "Feature",
  "properties": {
    "iso:country":"GB",
    "sg:address":"140a Kents Hill Road",
    "sg:city":"Benfleet",
    "sg:classifiers":[
        {
            "category":"Home & Garden",
            "subcategory":"Hardware",
            "type":"Retail Goods"
        },
        {
            "category":"Communications",
            "type":"Services"
        }
    ],
    "sg:postcode":"SS7 5PH",
    "sg:province":"Essex",
    "sg:tags":[
        "public",
        "music",
        "system",
        "generator",
        "address"
    ],
    "wof:name":"Phase Audio",
    "wof:placetype":"venue"
},
  "geometry": {"coordinates":[0.560194,51.558826],"type":"Point"}
}