{
  "type": "Feature",
  "properties": {
    "addr:full":"Unit 42, First Ave, Deeside Indstl Pk Deeside Flintshire CH5 2NU",
    "addr:housenumber":"unit 42",
    "addr:postcode":"ch5 2nu",
    "addr:street":"First Ave;Indstl Pk Deeside",
    "iso:country":"GB",
    "sg:address":"Unit 42, First Ave, Deeside Indstl Pk",
    "sg:city":"Deeside",
    "sg:classifiers":[
        {
            "category":"Professional",
            "subcategory":"Printing & Photocopies",
            "type":"Services"
        }
    ],
    "sg:postcode":"CH5 2NU",
    "sg:province":"Flintshire",
    "sg:tags":[
        "computer",
        "tag",
        "label"
    ],
    "wof:name":"Computer Labels Ltd",
    "wof:placetype":"venue"
},
  "geometry": {"coordinates":[-3.024987936,53.2024803162],"type":"Point"}
}