{
  "type": "Feature",
  "properties": {
    "addr:full":"Upper Allen Street Sheffield South Yorkshire S3 7HA",
    "addr:postcode":"s3 7ha",
    "addr:street":"Upper Allen Street",
    "iso:country":"GB",
    "sg:address":"Upper Allen Street",
    "sg:city":"Sheffield",
    "sg:classifiers":[
        {
            "category":"Manufacturing",
            "subcategory":"Metals",
            "type":"Manufacturing & Wholesale Goods"
        }
    ],
    "sg:phone":"+44 114 272 7094",
    "sg:postcode":"S3 7HA",
    "sg:province":"South Yorkshire",
    "sg:tags":[
        "work",
        "sheet"
    ],
    "wof:name":"W & G W Garratt Ltd.",
    "wof:placetype":"venue"
},
  "geometry": {"coordinates":[-1.4788240194,53.3857002258],"type":"Point"}
}