{
  "type": "Feature",
  "properties": {
    "iso:country":"GB",
    "sg:address":"485 Nottingham Rd",
    "sg:city":"Nottingham",
    "sg:classifiers":[
        {
            "category":"Professional",
            "subcategory":"Computer Services",
            "type":"Services"
        }
    ],
    "sg:phone":"+44 115 979 1255",
    "sg:postcode":"NG6 0FB",
    "sg:province":"Nottinghamshire",
    "sg:tags":[
        "system",
        "software"
    ],
    "wof:name":"Globe-Tek Computers",
    "wof:placetype":"venue"
},
  "geometry": {"coordinates":[-1.176174,52.981049],"type":"Point"}
}