{
  "type": "Feature",
  "properties": {
    "iso:country":"GB",
    "sg:address":"154 Uxbridge Road",
    "sg:city":"London",
    "sg:classifiers":[
        {
            "category":"Home & Garden",
            "subcategory":"Building Materials",
            "type":"Retail Goods"
        }
    ],
    "sg:phone":"+44 20 8567 7380",
    "sg:postcode":"W13 8SB",
    "sg:province":"Greater London",
    "sg:tags":[
        "furnishers",
        "bathroom",
        "planner"
    ],
    "wof:name":"Stanwells Kitchens & Bathrooms",
    "wof:placetype":"venue"
},
  "geometry": {"coordinates":[-0.3189449906,51.5110321045],"type":"Point"}
}