{
  "type": "Feature",
  "properties": {
    "iso:country":"GB",
    "sg:address":"Lawnswood Road",
    "sg:city":"Stourbridge",
    "sg:classifiers":[
        {
            "category":"Education",
            "subcategory":"School",
            "type":"Public Place"
        },
        {
            "category":"Government",
            "subcategory":"Office",
            "type":"Public Place"
        }
    ],
    "sg:phone":"+44 1384 818615",
    "sg:postcode":"DY8 5BZ",
    "sg:province":"Staffordshire",
    "sg:tags":[
        "local",
        "authority"
    ],
    "wof:name":"Belle Vue Primary School",
    "wof:placetype":"venue"
},
  "geometry": {"coordinates":[-2.1770288944,52.4827804565],"type":"Point"}
}