{
  "type": "Feature",
  "properties": {
    "iso:country":"GB",
    "sg:address":"50 Cornmarket Street",
    "sg:city":"Oxford",
    "sg:classifiers":[
        {
            "category":"Shopping",
            "subcategory":"Shoes",
            "type":"Retail Goods"
        }
    ],
    "sg:phone":"+44 1865 245794",
    "sg:postcode":"OX1 3HA",
    "sg:province":"Oxfordshire",
    "sg:tags":[
        "shop"
    ],
    "wof:name":"Clarks Shop",
    "wof:placetype":"venue"
},
  "geometry": {"coordinates":[-1.258211,51.752853],"type":"Point"}
}