{
  "type": "Feature",
  "properties": {
    "addr:full":"108 Station Road Nottingham Nottinghamshire NG9 2AY",
    "addr:housenumber":"108",
    "addr:postcode":"ng9 2ay",
    "addr:street":"Station Road",
    "iso:country":"GB",
    "sg:address":"108 Station Road",
    "sg:city":"Nottingham",
    "sg:classifiers":[
        {
            "category":"Health Services",
            "subcategory":"Dentist",
            "type":"Services"
        }
    ],
    "sg:phone":"+44 115 925 1050",
    "sg:postcode":"NG9 2AY",
    "sg:province":"Nottinghamshire",
    "sg:tags":[
        "technician",
        "instrument",
        "dental"
    ],
    "wof:name":"Impressions Dental Laboratory Ltd.",
    "wof:placetype":"venue"
},
  "geometry": {"coordinates":[-1.2117940187,52.9245452881],"type":"Point"}
}