{
  "type": "Feature",
  "properties": {
    "addr:full":"Old Workshop The, Speke Street Newport Newport NP19 8EX",
    "addr:housenumber":"the",
    "addr:postcode":"np19 8ex",
    "addr:street":"Speke Street",
    "iso:country":"GB",
    "sg:address":"Old Workshop The, Speke Street",
    "sg:city":"Newport",
    "sg:classifiers":[
        {
            "category":"Real Estate",
            "subcategory":"Architect",
            "type":"Services"
        }
    ],
    "sg:phone":"+44 1633 259996",
    "sg:postcode":"NP19 8EX",
    "sg:province":"Newport",
    "wof:name":"Larcombe & Co",
    "wof:placetype":"venue"
},
  "geometry": {"coordinates":[-2.9882569313,51.5910491943],"type":"Point"}
}