{
  "type": "Feature",
  "properties": {
    "iso:country":"GB",
    "sg:address":"82 Tollgate",
    "sg:city":"Peterborough",
    "sg:classifiers":[
        {
            "category":"Insurance",
            "subcategory":"Insurance Agent",
            "type":"Services"
        }
    ],
    "sg:phone":"+44 1733 265655",
    "sg:postcode":"PE3 9XB",
    "sg:province":"Cambridgeshire",
    "wof:name":"Time To Insure Insurance Consultants",
    "wof:placetype":"venue"
},
  "geometry": {"coordinates":[-0.284725,52.585571],"type":"Point"}
}