{
  "type": "Feature",
  "properties": {
    "addr:full":"10 Agnes Terrace Barnsley South Yorkshire S70 1NN",
    "addr:housenumber":"10",
    "addr:postcode":"s70 1nn",
    "addr:street":"Agnes Terrace;Yorkshire",
    "iso:country":"GB",
    "sg:address":"10 Agnes Terrace",
    "sg:city":"Barnsley",
    "sg:classifiers":[
        {
            "category":"Shopping",
            "subcategory":"Florist",
            "type":"Retail Goods"
        }
    ],
    "sg:phone":"+44 1226 244800",
    "sg:postcode":"S70 1NN",
    "sg:province":"South Yorkshire",
    "wof:name":"Oakwell Flower Corner",
    "wof:placetype":"venue"
},
  "geometry": {"coordinates":[-1.4822529554,53.5478591919],"type":"Point"}
}