{
  "type": "Feature",
  "properties": {
    "addr:full":"33 Broom Gro Rotherham South Yorkshire S60 2TE",
    "addr:housenumber":"33",
    "addr:postcode":"s60 2te",
    "addr:street":"Broom Gro Rotherham South",
    "iso:country":"GB",
    "sg:address":"33 Broom Gro",
    "sg:city":"Rotherham",
    "sg:classifiers":[
        {
            "category":"Organizations",
            "subcategory":"Political Organization",
            "type":"Services"
        }
    ],
    "sg:phone":"+44 1709 518175",
    "sg:postcode":"S60 2TE",
    "sg:province":"South Yorkshire",
    "sg:tags":[
        "party"
    ],
    "wof:name":"Rotherham Liberal Democrats",
    "wof:placetype":"venue"
},
  "geometry": {"coordinates":[-1.338941,53.422314],"type":"Point"}
}