{
  "type": "Feature",
  "properties": {
    "iso:country":"GB",
    "sg:address":"73 Rebbeck Rd",
    "sg:city":"Bournemouth",
    "sg:classifiers":[
        {
            "category":"Shopping",
            "subcategory":"Computers & Home Electronics",
            "type":"Retail Goods"
        }
    ],
    "sg:phone":"+44 1202 427305",
    "sg:postcode":"BH7 6LP",
    "sg:province":"Dorset",
    "sg:tags":[
        "equipment",
        "audio-visual"
    ],
    "wof:name":"T J Bawn",
    "wof:placetype":"venue"
},
  "geometry": {"coordinates":[-1.828115,50.732101],"type":"Point"}
}