{
  "type": "Feature",
  "properties": {
    "iso:country":"GB",
    "sg:address":"48 New Oxford St",
    "sg:city":"London",
    "sg:classifiers":[
        {
            "category":"Cafe",
            "type":"Food & Drink"
        }
    ],
    "sg:postcode":"WC1A 1ES",
    "sg:province":"Greater London",
    "sg:tags":[
        "tea",
        "room"
    ],
    "wof:name":"Girawsol Cafe",
    "wof:placetype":"venue"
},
  "geometry": {"coordinates":[-0.1261170059,51.5171432495],"type":"Point"}
}