{
  "type": "Feature",
  "properties": {
    "addr:full":"56-60 Mount Pleasant Liverpool Merseyside L3 5SH",
    "addr:housenumber":"56-60",
    "addr:postcode":"l3 5sh",
    "addr:street":"Mount Pleasant",
    "iso:country":"GB",
    "sg:address":"56-60 Mount Pleasant",
    "sg:city":"Liverpool",
    "sg:classifiers":[
        {
            "category":"Organizations",
            "subcategory":"Non-profit Organization",
            "type":"Services"
        }
    ],
    "sg:phone":"+44 151 709 9516",
    "sg:postcode":"L3 5SH",
    "sg:province":"Merseyside",
    "sg:tags":[
        "organisation",
        "voluntary",
        "charity"
    ],
    "wof:name":"Y M C A",
    "wof:placetype":"venue"
},
  "geometry": {"coordinates":[-2.97407794,53.4038467407],"type":"Point"}
}