{
  "type": "Feature",
  "properties": {
    "iso:country":"GB",
    "sg:address":"Walsall Road, Darlaston",
    "sg:city":"Wednesbury",
    "sg:classifiers":[
        {
            "category":"Professional",
            "subcategory":"Engineering",
            "type":"Services"
        }
    ],
    "sg:postcode":"WS10 9SR",
    "sg:province":"West Midlands",
    "wof:name":"Triplex Alloys Ltd.",
    "wof:placetype":"venue"
},
  "geometry": {"coordinates":[-2.034454,52.566963],"type":"Point"}
}