{
  "type": "Feature",
  "properties": {
    "addr:full":"Deanhill House, Deanhill Avenue Clacton On Sea Essex CO15 5AX",
    "addr:postcode":"co15 5ax",
    "addr:street":"Deanhill Avenue",
    "iso:country":"GB",
    "sg:address":"Deanhill House, Deanhill Avenue",
    "sg:city":"Clacton On Sea",
    "sg:classifiers":[
        {
            "category":"Autos & Motor Vehicles",
            "subcategory":"Automobile Sales",
            "type":"Retail Goods"
        }
    ],
    "sg:phone":"+44 1255 421095",
    "sg:postcode":"CO15 5AX",
    "sg:province":"Essex",
    "sg:tags":[
        "commercial"
    ],
    "wof:name":"R.P Finch Car Sales",
    "wof:placetype":"venue"
},
  "geometry": {"coordinates":[1.177575,51.801472],"type":"Point"}
}