{
  "type": "Feature",
  "properties": {
    "addr:full":"Bedford House London Greater London NW1 7JR",
    "addr:postcode":"nw1 7jr",
    "iso:country":"GB",
    "sg:address":"Bedford House",
    "sg:city":"London",
    "sg:classifiers":[
        {
            "category":"Organizations",
            "subcategory":"Community Association",
            "type":"Services"
        }
    ],
    "sg:phone":"+44 20 8408 8517",
    "sg:postcode":"NW1 7JR",
    "sg:province":"Greater London",
    "sg:tags":[
        "society",
        "housing"
    ],
    "wof:name":"Central & Cecil Housing Trust",
    "wof:placetype":"venue"
},
  "geometry": {"coordinates":[-0.087914,51.50737],"type":"Point"}
}