{
  "type": "Feature",
  "properties": {
    "iso:country":"GB",
    "sg:address":"Beeches Lodge, Hildon, Broughton",
    "sg:city":"Stockbridge",
    "sg:classifiers":[
        {
            "category":"Education",
            "subcategory":"Special Training",
            "type":"Public Place"
        }
    ],
    "sg:phone":"+44 1794 301266",
    "sg:postcode":"SO20 8DG",
    "sg:province":"Hampshire",
    "sg:tags":[
        "school",
        "flying"
    ],
    "wof:name":"Lotus Balloons",
    "wof:placetype":"venue"
},
  "geometry": {"coordinates":[-1.5639679432,51.0928077698],"type":"Point"}
}