{
  "type": "Feature",
  "properties": {
    "iso:country":"GB",
    "sg:address":"The Gatehouse, 43 Invincible Rd",
    "sg:city":"Farnborough",
    "sg:classifiers":[
        {
            "category":"Real Estate",
            "subcategory":"Real Estate Agent",
            "type":"Services"
        }
    ],
    "sg:phone":"+44 1252 516087",
    "sg:postcode":"GU14 7QU",
    "sg:province":"Hampshire",
    "wof:name":"Kingsgrove Estates",
    "wof:placetype":"venue"
},
  "geometry": {"coordinates":[-0.755569,51.293724],"type":"Point"}
}