{
  "type": "Feature",
  "properties": {
    "iso:country":"GB",
    "sg:address":"Unit 2 South Newton Industrial Estate, Warminster Road, South Newton",
    "sg:city":"Salisbury",
    "sg:classifiers":[
        {
            "category":"Professional",
            "type":"Services"
        }
    ],
    "sg:phone":"+44 1722 744004",
    "sg:postcode":"SP2 0QW",
    "sg:province":"Wiltshire",
    "sg:tags":[
        "exhibition"
    ],
    "wof:name":"Illusions Ltd.",
    "wof:placetype":"venue"
},
  "geometry": {"coordinates":[-1.87963,51.110958],"type":"Point"}
}