{
  "type": "Feature",
  "properties": {
    "iso:country":"GB",
    "sg:address":"32-36 Andover Street",
    "sg:city":"Leicester",
    "sg:classifiers":[
        {
            "category":"Manufacturing",
            "subcategory":"Metals",
            "type":"Manufacturing & Wholesale Goods"
        }
    ],
    "sg:phone":"+44 116 247 1515",
    "sg:postcode":"LE2 0JB",
    "sg:province":"Leicestershire",
    "sg:tags":[
        "steel",
        "fabricator",
        "erectors"
    ],
    "wof:name":"Central Fabrications (Leicester) Ltd.",
    "wof:placetype":"venue"
},
  "geometry": {"coordinates":[-1.122548,52.630726],"type":"Point"}
}