{
  "type": "Feature",
  "properties": {
    "iso:country":"GB",
    "sg:address":"40 Lichfield Road",
    "sg:city":"Walsall",
    "sg:classifiers":[
        {
            "category":"Travel",
            "subcategory":"Hotels & Motels",
            "type":"Entertainment"
        }
    ],
    "sg:phone":"+44 1922 628475",
    "sg:postcode":"WS4 2DH",
    "sg:province":"West Midlands",
    "sg:tags":[
        "house",
        "guest"
    ],
    "wof:name":"Daldrada Guest House",
    "wof:placetype":"venue"
},
  "geometry": {"coordinates":[-1.9702069759,52.5949554443],"type":"Point"}
}