{
  "type": "Feature",
  "properties": {
    "iso:country":"GB",
    "sg:address":"Unit 21 Marsh Lane Trading Estat, E Marsh Lane",
    "sg:city":"Bristol",
    "sg:classifiers":[
        {
            "category":"Food & Beverages",
            "subcategory":"Supermarket",
            "type":"Retail Goods"
        }
    ],
    "sg:phone":"+44 1275 371317",
    "sg:postcode":"BS20 0NH",
    "sg:province":"Somerset",
    "sg:tags":[
        "frozen"
    ],
    "wof:name":"Good Taste Foods Ltd.",
    "wof:placetype":"venue"
},
  "geometry": {"coordinates":[-2.706399,51.482159],"type":"Point"}
}