{
  "type": "Feature",
  "properties": {
    "addr:full":"St Marks Street Bolton Lancashire BL3 6NS",
    "addr:postcode":"bl3 6ns",
    "addr:street":"St Marks Street",
    "iso:country":"GB",
    "sg:address":"St Marks Street",
    "sg:city":"Bolton",
    "sg:classifiers":[
        {
            "category":"Manufacturing",
            "subcategory":"Motor Vehicles & Parts",
            "type":"Manufacturing & Wholesale Goods"
        }
    ],
    "sg:phone":"+44 1204 532211",
    "sg:postcode":"BL3 6NS",
    "sg:province":"Lancashire",
    "sg:tags":[
        "bearing"
    ],
    "wof:name":"Bearing Power Ltd.",
    "wof:placetype":"venue"
},
  "geometry": {"coordinates":[-2.4262440205,53.5697784424],"type":"Point"}
}