{
  "type": "Feature",
  "properties": {
    "addr:full":"Units 1 & 2 Acorn Business Centre, Arran Rd Perth Perth and Kinross PH1 3DZ",
    "addr:housenumber":"units 1 & 2",
    "addr:postcode":"ph1 3dz",
    "addr:street":"Acorn Business Centre Arran Rd",
    "iso:country":"GB",
    "sg:address":"Units 1 & 2 Acorn Business Centre, Arran Rd",
    "sg:city":"Perth",
    "sg:classifiers":[
        {
            "category":"Manufacturing",
            "subcategory":"Petroleum Products",
            "type":"Manufacturing & Wholesale Goods"
        }
    ],
    "sg:phone":"+44 1738 442177",
    "sg:postcode":"PH1 3DZ",
    "sg:province":"Perth and Kinross",
    "sg:tags":[
        "double",
        "glazing"
    ],
    "wof:name":"Discovery Windows",
    "wof:placetype":"venue"
},
  "geometry": {"coordinates":[-3.4578700066,56.4160499573],"type":"Point"}
}