{
  "type": "Feature",
  "properties": {
    "iso:country":"GB",
    "sg:address":"18 Rutland Sq",
    "sg:city":"Edinburgh",
    "sg:classifiers":[
        {
            "category":"Professional",
            "subcategory":"Art Services",
            "type":"Services"
        }
    ],
    "sg:phone":"+44 131 221 1521",
    "sg:postcode":"EH1 2BB",
    "sg:province":"City of Edinburgh",
    "sg:tags":[
        "consultant",
        "design"
    ],
    "wof:name":"Criterion Design Consultants",
    "wof:placetype":"venue"
},
  "geometry": {"coordinates":[-3.2095599174,55.9484214783],"type":"Point"}
}