{
  "type": "Feature",
  "properties": {
    "iso:country":"GB",
    "sg:address":"57 Sleaford Road, Tattershall Bridge",
    "sg:city":"Lincoln",
    "sg:classifiers":[
        {
            "category":"Banks & Credit Unions",
            "subcategory":"Investment Brokerage",
            "type":"Services"
        },
        {
            "category":"Train Station",
            "subcategory":"Rail",
            "type":"Transportation"
        }
    ],
    "sg:phone":"+44 1526 345670",
    "sg:postcode":"LN4 4JG",
    "sg:province":"Lincolnshire",
    "sg:tags":[
        "caravan",
        "hire"
    ],
    "wof:name":"Vantage Caravans",
    "wof:placetype":"venue"
},
  "geometry": {"coordinates":[-0.2128340006,53.0917434692],"type":"Point"}
}