{
  "type": "Feature",
  "properties": {
    "addr:full":"50 Empress Way, Euxton Chorley Lancashire PR7 6QB",
    "addr:housenumber":"50",
    "addr:postcode":"pr7 6qb",
    "addr:street":"Empress Way",
    "iso:country":"GB",
    "sg:address":"50 Empress Way, Euxton",
    "sg:city":"Chorley",
    "sg:classifiers":[
        {
            "category":"Building & Trades",
            "subcategory":"Construction",
            "type":"Services"
        },
        {
            "category":"Manufacturing",
            "subcategory":"Building Materials",
            "type":"Manufacturing & Wholesale Goods"
        }
    ],
    "sg:phone":"+44 1257 241466",
    "sg:postcode":"PR7 6QB",
    "sg:province":"Lancashire",
    "sg:tags":[
        "tarmac",
        "road",
        "surfacing",
        "asphalt"
    ],
    "wof:name":"David Cooper",
    "wof:placetype":"venue"
},
  "geometry": {"coordinates":[-2.664283,53.663673],"type":"Point"}
}