{
  "type": "Feature",
  "properties": {
    "iso:country":"GB",
    "sg:address":"31 Railway Rd",
    "sg:city":"Ilkley",
    "sg:classifiers":[
        {
            "category":"Shopping",
            "subcategory":"Computers & Home Electronics",
            "type":"Retail Goods"
        },
        {
            "category":"Communications",
            "type":"Services"
        }
    ],
    "sg:phone":"+44 1943 609308",
    "sg:postcode":"LS29 8HP",
    "sg:province":"North Yorkshire",
    "sg:tags":[
        "tv",
        "radio",
        "television",
        "video",
        "sale"
    ],
    "wof:name":"Cleggs",
    "wof:placetype":"venue"
},
  "geometry": {"coordinates":[-1.819419,53.925114],"type":"Point"}
}