{
  "type": "Feature",
  "properties": {
    "addr:full":"19 College Street Lampeter Carmarthenshire SA48 7DY",
    "addr:housenumber":"19",
    "addr:postcode":"sa48 7dy",
    "addr:street":"College Street",
    "iso:country":"GB",
    "sg:address":"19 College Street",
    "sg:city":"Lampeter",
    "sg:classifiers":[
        {
            "category":"Professional",
            "subcategory":"Lawyer & Legal Services",
            "type":"Services"
        }
    ],
    "sg:phone":"+44 1570 423300",
    "sg:postcode":"SA48 7DY",
    "sg:province":"Carmarthenshire",
    "sg:tags":[
        "solicitor"
    ],
    "wof:name":"Cliff Williams & Co.",
    "wof:placetype":"venue"
},
  "geometry": {"coordinates":[-4.0775251389,52.1144866943],"type":"Point"}
}