{
  "type": "Feature",
  "properties": {
    "iso:country":"GB",
    "sg:address":"Bessingby Road",
    "sg:city":"Bridlington",
    "sg:classifiers":[
        {
            "category":"Health Services",
            "subcategory":"Hospital",
            "type":"Services"
        }
    ],
    "sg:phone":"+44 1262 606666",
    "sg:postcode":"YO16 4QP",
    "sg:province":"East Riding of Yorkshire",
    "wof:name":"Bridlington & District Hospital",
    "wof:placetype":"venue"
},
  "geometry": {"coordinates":[-0.2118539959,54.0842399597],"type":"Point"}
}