{
  "type": "Feature",
  "properties": {
    "iso:country":"GB",
    "sg:address":"Mertoun Farm",
    "sg:city":"Melrose",
    "sg:classifiers":[
        {
            "category":"Real Estate",
            "subcategory":"Real Estate Agent",
            "type":"Services"
        },
        {
            "category":"Farming",
            "subcategory":"Farm",
            "type":"Manufacturing & Wholesale Goods"
        }
    ],
    "sg:phone":"+44 1835 823236",
    "sg:postcode":"TD6 0RP",
    "sg:province":"Scottish Borders",
    "sg:tags":[
        "mixed",
        "crop"
    ],
    "wof:name":"The Duke of Sutherland",
    "wof:placetype":"venue"
},
  "geometry": {"coordinates":[-2.737578,55.598831],"type":"Point"}
}