{
  "type": "Feature",
  "properties": {
    "addr:full":"226 Davidson Road Croydon Surrey CR0 6DF",
    "addr:housenumber":"226",
    "addr:postcode":"cr0 6df",
    "addr:street":"Davidson Road",
    "iso:country":"GB",
    "sg:address":"226 Davidson Road",
    "sg:city":"Croydon",
    "sg:classifiers":[
        {
            "category":"Building & Trades",
            "subcategory":"Construction",
            "type":"Services"
        }
    ],
    "sg:phone":"+44 20 8656 4803",
    "sg:postcode":"CR0 6DF",
    "sg:province":"Surrey",
    "sg:tags":[
        "builder"
    ],
    "wof:name":"Christiansons",
    "wof:placetype":"venue"
},
  "geometry": {"coordinates":[-0.084887,51.385399],"type":"Point"}
}