{
  "type": "Feature",
  "properties": {
    "iso:country":"GB",
    "sg:address":"Honey Hill, Blean",
    "sg:city":"Canterbury",
    "sg:classifiers":[
        {
            "category":"Museum",
            "subcategory":"Zoo",
            "type":"Entertainment"
        }
    ],
    "sg:phone":"+44 1227 765168",
    "sg:postcode":"CT2 9JR",
    "sg:province":"Kent",
    "wof:name":"Druidstone Wildlife Park",
    "wof:placetype":"venue"
},
  "geometry": {"coordinates":[1.0348500013,51.3145599365],"type":"Point"}
}