{
  "type": "Feature",
  "properties": {
    "iso:country":"GB",
    "sg:address":"38 Springside View",
    "sg:city":"Bury",
    "sg:classifiers":[
        {
            "category":"Personal",
            "type":"Services"
        }
    ],
    "sg:postcode":"BL8 4LU",
    "sg:province":"Lancashire",
    "sg:tags":[
        "wedding"
    ],
    "wof:name":"In-Style Wedding Cars",
    "wof:placetype":"venue"
},
  "geometry": {"coordinates":[-2.317696,53.61628],"type":"Point"}
}