{
  "type": "Feature",
  "properties": {
    "iso:country":"GB",
    "sg:address":"12 Riverside Walk",
    "sg:city":"Wickford",
    "sg:classifiers":[
        {
            "category":"Retail",
            "subcategory":"Auto Repair",
            "type":"Services"
        }
    ],
    "sg:postcode":"SS12 0DU",
    "sg:province":"Essex",
    "sg:tags":[
        "engine",
        "car",
        "specialist"
    ],
    "wof:name":"Techtune",
    "wof:placetype":"venue"
},
  "geometry": {"coordinates":[0.513294,51.615177],"type":"Point"}
}