{
  "type": "Feature",
  "properties": {
    "iso:country":"GB",
    "sg:address":"Coleman Grn, Wheathampstead",
    "sg:city":"St Albans",
    "sg:classifiers":[
        {
            "category":"Transit Center",
            "subcategory":"Passenger",
            "type":"Transportation"
        },
        {
            "category":"Retail",
            "subcategory":"Pet Boarding",
            "type":"Services"
        }
    ],
    "sg:phone":"+44 1582 832410",
    "sg:postcode":"AL4 8ET",
    "sg:province":"Hertfordshire",
    "sg:tags":[
        "kennel",
        "catteries"
    ],
    "wof:name":"Coleman Green Boarding Kennels & Cattery",
    "wof:placetype":"venue"
},
  "geometry": {"coordinates":[-0.29424,51.806702],"type":"Point"}
}