{
  "type": "Feature",
  "properties": {
    "addr:full":"2 - 4 Dellfield Parade, Cowley Uxbridge Buckinghamshire UB8 2EN",
    "addr:housenumber":"4",
    "addr:postcode":"ub8 2en",
    "addr:street":"Dellfield Parade",
    "iso:country":"GB",
    "sg:address":"2 - 4 Dellfield Parade, Cowley",
    "sg:city":"Uxbridge",
    "sg:classifiers":[
        {
            "category":"Shopping",
            "subcategory":"Bicycles & Sporting Goods",
            "type":"Retail Goods"
        }
    ],
    "sg:phone":"+44 1895 232755",
    "sg:postcode":"UB8 2EN",
    "sg:province":"Buckinghamshire",
    "sg:tags":[
        "cycle",
        "accessory"
    ],
    "wof:name":"Rippingales Cycles",
    "wof:placetype":"venue"
},
  "geometry": {"coordinates":[-0.480891,51.527493],"type":"Point"}
}