{
  "type": "Feature",
  "properties": {
    "addr:full":"Hanover House, 78-82 High Street Brentwood Essex CM14 4AP",
    "addr:housenumber":"78-82",
    "addr:postcode":"cm14 4ap",
    "addr:street":"High Street",
    "iso:country":"GB",
    "sg:address":"Hanover House, 78-82 High Street",
    "sg:city":"Brentwood",
    "sg:classifiers":[
        {
            "category":"Real Estate",
            "subcategory":"Surveying",
            "type":"Services"
        }
    ],
    "sg:phone":"+44 1277 212794",
    "sg:postcode":"CM14 4AP",
    "sg:province":"Essex",
    "sg:tags":[
        "building",
        "surveyor",
        "land",
        "activity"
    ],
    "wof:name":"Gryphon Surveys Ltd.",
    "wof:placetype":"venue"
},
  "geometry": {"coordinates":[0.300084,51.619675],"type":"Point"}
}