{
  "type": "Feature",
  "properties": {
    "iso:country":"GB",
    "sg:address":"Unit 1, Britannia Building, Coventry Road",
    "sg:city":"Hinckley",
    "sg:classifiers":[
        {
            "category":"Manufacturing",
            "subcategory":"Glass & Minerals",
            "type":"Manufacturing & Wholesale Goods"
        }
    ],
    "sg:postcode":"LE10 1LW",
    "sg:province":"Leicestershire",
    "sg:tags":[
        "mnfrs",
        "fibre"
    ],
    "wof:name":"Creative G R P Ltd.",
    "wof:placetype":"venue"
},
  "geometry": {"coordinates":[-1.3727539778,52.5424385071],"type":"Point"}
}