{
  "type": "Feature",
  "properties": {
    "addr:full":"C/o Harris & Co, 4-6 Canfield Pl London Greater London NW6 3BT",
    "addr:housenumber":"/ o;4-6",
    "addr:postcode":"nw6 3bt",
    "addr:street":"C;Canfield Pl",
    "iso:country":"GB",
    "sg:address":"C/o Harris & Co, 4-6 Canfield Pl",
    "sg:city":"London",
    "sg:classifiers":[
        {
            "category":"Professional",
            "subcategory":"Computer Services",
            "type":"Services"
        }
    ],
    "sg:postcode":"NW6 3BT",
    "sg:province":"Greater London",
    "sg:tags":[
        "system",
        "software"
    ],
    "wof:name":"Arbor Glade Ltd",
    "wof:placetype":"venue"
},
  "geometry": {"coordinates":[-0.1802629977,51.5468635559],"type":"Point"}
}