{
  "type": "Feature",
  "properties": {
    "addr:full":"1 School Wynd, Ratho Newbridge City of Edinburgh EH28 8TT",
    "addr:housenumber":"1",
    "addr:postcode":"eh28 8tt",
    "addr:street":"School Wynd",
    "iso:country":"GB",
    "sg:address":"1 School Wynd, Ratho",
    "sg:city":"Newbridge",
    "sg:classifiers":[
        {
            "category":"Education",
            "subcategory":"School",
            "type":"Public Place"
        }
    ],
    "sg:phone":"+44 131 335 0070",
    "sg:postcode":"EH28 8TT",
    "sg:province":"City of Edinburgh",
    "sg:tags":[
        "local",
        "authority"
    ],
    "wof:name":"Ratho Primary School",
    "wof:placetype":"venue"
},
  "geometry": {"coordinates":[-3.383587,55.928658],"type":"Point"}
}