{
  "type": "Feature",
  "properties": {
    "addr:full":"14 Redeness St York North Yorkshire YO31 7UU",
    "addr:housenumber":"14",
    "addr:postcode":"yo31 7uu",
    "addr:street":"Redeness St York",
    "iso:country":"GB",
    "sg:address":"14 Redeness St",
    "sg:city":"York",
    "sg:classifiers":[
        {
            "category":"Shopping",
            "subcategory":"Jewelry",
            "type":"Retail Goods"
        },
        {
            "category":"Utilities",
            "subcategory":"Natural Gas",
            "type":"Services"
        }
    ],
    "sg:postcode":"YO31 7UU",
    "sg:province":"North Yorkshire",
    "sg:tags":[
        "supplier",
        "diamond"
    ],
    "wof:name":"Bird,Christopher,",
    "wof:placetype":"venue"
},
  "geometry": {"coordinates":[-1.0714889765,53.9622535706],"type":"Point"}
}