{
  "type": "Feature",
  "properties": {
    "iso:country":"GB",
    "sg:address":"333 Western Avenue, Acton",
    "sg:city":"London",
    "sg:classifiers":[
        {
            "category":"Banks & Credit Unions",
            "subcategory":"Bank",
            "type":"Services"
        }
    ],
    "sg:phone":"+44 20 8752 3000",
    "sg:postcode":"W3 0RS",
    "sg:province":"Greater London",
    "sg:tags":[
        "purchase",
        "hire",
        "leasing"
    ],
    "wof:name":"333wa Ltd.",
    "wof:placetype":"venue"
},
  "geometry": {"coordinates":[-0.2731029987,51.52576828],"type":"Point"}
}