{
  "type": "Feature",
  "properties": {
    "iso:country":"GB",
    "sg:address":"30 Shortlands Grn",
    "sg:city":"Welwyn Garden City",
    "sg:classifiers":[
        {
            "category":"Building & Trades",
            "subcategory":"Construction",
            "type":"Services"
        }
    ],
    "sg:phone":"+44 1707 335685",
    "sg:postcode":"AL7 3RX",
    "sg:province":"Hertfordshire",
    "sg:tags":[
        "decorator",
        "painter"
    ],
    "wof:name":"Gerard O'Donoghue Painting & Decorating",
    "wof:placetype":"venue"
},
  "geometry": {"coordinates":[-0.1895499974,51.7958374023],"type":"Point"}
}