{
  "type": "Feature",
  "properties": {
    "addr:full":"Morrab Road Penzance Cornwall TR18 4HD",
    "addr:postcode":"tr18 4hd",
    "addr:street":"Morrab Road",
    "iso:country":"GB",
    "sg:address":"Morrab Road",
    "sg:city":"Penzance",
    "sg:classifiers":[
        {
            "category":"Shopping",
            "subcategory":"News",
            "type":"Retail Goods"
        }
    ],
    "sg:phone":"+44 1736 350001",
    "sg:postcode":"TR18 4HD",
    "sg:province":"Cornwall",
    "sg:tags":[
        "newsagent"
    ],
    "wof:name":"Morrab News",
    "wof:placetype":"venue"
},
  "geometry": {"coordinates":[-5.5394639969,50.1180000305],"type":"Point"}
}