{
  "type": "Feature",
  "properties": {
    "iso:country":"GB",
    "sg:address":"12 Finkle Street",
    "sg:city":"Malton",
    "sg:classifiers":[
        {
            "category":"Farming",
            "subcategory":"Fish & Marine Products",
            "type":"Manufacturing & Wholesale Goods"
        },
        {
            "category":"Food & Beverages",
            "subcategory":"Meat & Fish",
            "type":"Retail Goods"
        }
    ],
    "sg:phone":"+44 1653 693406",
    "sg:postcode":"YO17 7JD",
    "sg:province":"North Yorkshire",
    "sg:tags":[
        "fishmonger",
        "related"
    ],
    "wof:name":"Malton Fisheries",
    "wof:placetype":"venue"
},
  "geometry": {"coordinates":[-0.798539,54.136356],"type":"Point"}
}