{
  "type": "Feature",
  "properties": {
    "iso:country":"GB",
    "sg:address":"Care Of T J Hughes, Hardshaw Centre",
    "sg:city":"St Helens",
    "sg:classifiers":[
        {
            "category":"Shopping",
            "subcategory":"Department Store",
            "type":"Retail Goods"
        }
    ],
    "sg:phone":"+44 1744 453221",
    "sg:postcode":"WA10 1EB",
    "sg:province":"Merseyside",
    "wof:name":"T J Hughes",
    "wof:placetype":"venue"
},
  "geometry": {"coordinates":[-2.738868,53.451687],"type":"Point"}
}