{
  "type": "Feature",
  "properties": {
    "iso:country":"GB",
    "sg:address":"132 High Street",
    "sg:city":"Sidmouth",
    "sg:classifiers":[
        {
            "category":"Professional",
            "subcategory":"Engineering",
            "type":"Services"
        },
        {
            "category":"Food & Beverages",
            "subcategory":"Liquor & Beverages",
            "type":"Retail Goods"
        }
    ],
    "sg:phone":"+44 1395 515122",
    "sg:postcode":"EX10 8EA",
    "sg:province":"Devon",
    "sg:tags":[
        "wines",
        "contractor",
        "beer",
        "electrical",
        "spirit",
        "engineer"
    ],
    "wof:name":"Wine Seller the",
    "wof:placetype":"venue"
},
  "geometry": {"coordinates":[-3.238233,50.682186],"type":"Point"}
}