{
  "type": "Feature",
  "properties": {
    "addr:full":"Unit 4, Lockwood Industrial Park, Millmead Road London Greater London N17 9QP",
    "addr:housenumber":"unit 4",
    "addr:postcode":"n17 9qp",
    "addr:street":"Industrial Park Millmead Road",
    "iso:country":"GB",
    "sg:address":"Unit 4, Lockwood Industrial Park, Millmead Road",
    "sg:city":"London",
    "sg:classifiers":[
        {
            "category":"Professional",
            "subcategory":"Business Services",
            "type":"Services"
        }
    ],
    "sg:phone":"+44 20 8365 1414",
    "sg:postcode":"N17 9QP",
    "sg:province":"Greater London",
    "sg:tags":[
        "import",
        "export",
        "agent"
    ],
    "wof:name":"Dryer & Hoffman Ltd.",
    "wof:placetype":"venue"
},
  "geometry": {"coordinates":[-0.0571,51.59071],"type":"Point"}
}