{
  "type": "Feature",
  "properties": {
    "addr:full":"17 Rotunda Terrace, Montpellier Street Cheltenham Gloucestershire GL50 1SW",
    "addr:housenumber":"17",
    "addr:postcode":"gl50 1sw",
    "addr:street":"Rotunda Terrace Montpellier Street",
    "iso:country":"GB",
    "sg:address":"17 Rotunda Terrace, Montpellier Street",
    "sg:city":"Cheltenham",
    "sg:classifiers":[
        {
            "category":"Home & Garden",
            "subcategory":"Home Furnishings",
            "type":"Retail Goods"
        }
    ],
    "sg:phone":"+44 1242 577027",
    "sg:postcode":"GL50 1SW",
    "sg:province":"Gloucestershire",
    "sg:tags":[
        "beds",
        "bedding",
        "blanket",
        "soft",
        "sale"
    ],
    "wof:name":"The Square Pillow",
    "wof:placetype":"venue"
},
  "geometry": {"coordinates":[-2.078459,51.898048],"type":"Point"}
}