{
  "type": "Feature",
  "properties": {
    "iso:country":"GB",
    "sg:address":"Manfield Way, Holmbush",
    "sg:city":"St. Austell",
    "sg:classifiers":[
        {
            "category":"Wholesale",
            "subcategory":"Non-durable Goods",
            "type":"Manufacturing & Wholesale Goods"
        }
    ],
    "sg:phone":"+44 1726 72746",
    "sg:postcode":"PL25 3JH",
    "sg:province":"Cornwall",
    "sg:tags":[
        "carry",
        "wholesaler",
        "cash"
    ],
    "sg:website":"http://www.booker.co.uk",
    "wof:name":"Booker Cash & Carry Ltd",
    "wof:placetype":"venue"
},
  "geometry": {"coordinates":[-4.755317,50.342106],"type":"Point"}
}