{
  "type": "Feature",
  "properties": {
    "iso:country":"GB",
    "sg:address":"20 Oakwood Close",
    "sg:city":"Hastings",
    "sg:classifiers":[
        {
            "category":"Building & Trades",
            "subcategory":"Plumbing",
            "type":"Services"
        }
    ],
    "sg:postcode":"TN34 2JF",
    "sg:province":"East Sussex",
    "sg:tags":[
        "heating"
    ],
    "wof:name":"Adrian P Marketis",
    "wof:placetype":"venue"
},
  "geometry": {"coordinates":[0.581332,50.873859],"type":"Point"}
}