{
  "type": "Feature",
  "properties": {
    "iso:country":"GB",
    "sg:address":"29 Birches Crest, Hatch Warren",
    "sg:city":"Basingstoke",
    "sg:classifiers":[
        {
            "category":"Home & Garden",
            "subcategory":"Household Appliances",
            "type":"Retail Goods"
        }
    ],
    "sg:postcode":"RG22 4RP",
    "sg:province":"Hampshire",
    "sg:tags":[
        "electrical",
        "domestic"
    ],
    "wof:name":"Ugrow Limited",
    "wof:placetype":"venue"
},
  "geometry": {"coordinates":[-1.131999,51.233913],"type":"Point"}
}