{
  "type": "Feature",
  "properties": {
    "iso:country":"GB",
    "sg:address":"190 Charlton Rd",
    "sg:city":"Harrow",
    "sg:classifiers":[
        {
            "category":"Banks & Credit Unions",
            "subcategory":"Bank",
            "type":"Services"
        }
    ],
    "sg:phone":"+44 20 8204 2600",
    "sg:postcode":"HA3 9HJ",
    "sg:province":"Greater London",
    "sg:tags":[
        "broker",
        "mortgage"
    ],
    "wof:name":"Fosta Financial Services",
    "wof:placetype":"venue"
},
  "geometry": {"coordinates":[-0.295598,51.593285],"type":"Point"}
}