{
  "type": "Feature",
  "properties": {
    "addr:full":"10 Park Lane, Milford On Sea Lymington Hampshire SO41 0PT",
    "addr:housenumber":"10",
    "addr:postcode":"so41 0pt",
    "addr:street":"Park Lane",
    "iso:country":"GB",
    "sg:address":"10 Park Lane, Milford On Sea",
    "sg:city":"Lymington",
    "sg:classifiers":[
        {
            "category":"Professional",
            "subcategory":"Management & Consulting",
            "type":"Services"
        }
    ],
    "sg:postcode":"SO41 0PT",
    "sg:province":"Hampshire",
    "sg:tags":[
        "consultant",
        "business"
    ],
    "wof:name":"Transcrip Ltd",
    "wof:placetype":"venue"
},
  "geometry": {"coordinates":[-1.5959390402,50.7244567871],"type":"Point"}
}