{
  "type": "Feature",
  "properties": {
    "addr:full":"Orchard Lane Leigh Lancashire WN7 1NU",
    "addr:postcode":"wn7 1nu",
    "addr:street":"Orchard Lane",
    "iso:country":"GB",
    "sg:address":"Orchard Lane",
    "sg:city":"Leigh",
    "sg:classifiers":[
        {
            "category":"Social Services",
            "type":"Services"
        }
    ],
    "sg:phone":"+44 1942 673511",
    "sg:postcode":"WN7 1NU",
    "sg:province":"Lancashire",
    "wof:name":"Woodview Hostel",
    "wof:placetype":"venue"
},
  "geometry": {"coordinates":[-2.508244,53.506924],"type":"Point"}
}