{
  "type": "Feature",
  "properties": {
    "addr:full":"59-61 Cross Street Manchester Greater Manchester M2 4JW",
    "addr:housenumber":"59-61",
    "addr:postcode":"m2 4jw",
    "addr:street":"Cross Street",
    "iso:country":"GB",
    "sg:address":"59-61 Cross Street",
    "sg:city":"Manchester",
    "sg:classifiers":[
        {
            "category":"Personal",
            "subcategory":"Shoe Repair & Shine",
            "type":"Services"
        },
        {
            "category":"Shopping",
            "subcategory":"Shoes",
            "type":"Retail Goods"
        }
    ],
    "sg:phone":"+44 161 832 2138",
    "sg:postcode":"M2 4JW",
    "sg:province":"Greater Manchester",
    "wof:name":"Kenneth J Fisher",
    "wof:placetype":"venue"
},
  "geometry": {"coordinates":[-2.245038,53.480309],"type":"Point"}
}