{
  "type": "Feature",
  "properties": {
    "iso:country":"GB",
    "sg:address":"4 Greyhound Road",
    "sg:city":"London",
    "sg:classifiers":[
        {
            "category":"Organizations",
            "subcategory":"Political Organization",
            "type":"Services"
        }
    ],
    "sg:phone":"+44 20 7385 1002",
    "sg:postcode":"W6 8NX",
    "sg:province":"Greater London",
    "sg:tags":[
        "party"
    ],
    "wof:name":"Hammersmith & Fulham Conservative Association",
    "wof:placetype":"venue"
},
  "geometry": {"coordinates":[-0.2195640057,51.4847335815],"type":"Point"}
}