{
  "type": "Feature",
  "properties": {
    "addr:full":"79 South Croxted Road, West Dulwich London Greater London SE21 8BA",
    "addr:housenumber":"79",
    "addr:postcode":"se21 8ba",
    "addr:street":"South Croxted Road",
    "iso:country":"GB",
    "sg:address":"79 South Croxted Road, West Dulwich",
    "sg:city":"London",
    "sg:classifiers":[
        {
            "category":"Building & Trades",
            "subcategory":"Construction",
            "type":"Services"
        }
    ],
    "sg:phone":"+44 20 8670 7760",
    "sg:postcode":"SE21 8BA",
    "sg:province":"Greater London",
    "sg:tags":[
        "roofing"
    ],
    "wof:name":"L M Q Roofing Contractors",
    "wof:placetype":"venue"
},
  "geometry": {"coordinates":[-0.086763,51.428886],"type":"Point"}
}