{
  "type": "Feature",
  "properties": {
    "iso:country":"GB",
    "sg:address":"70 Yardley Road, Acocks Green",
    "sg:city":"Birmingham",
    "sg:classifiers":[
        {
            "category":"Personal",
            "subcategory":"Tanning Parlor",
            "type":"Services"
        }
    ],
    "sg:phone":"+44 1675 465504",
    "sg:postcode":"B27 6LG",
    "sg:province":"West Midlands",
    "sg:tags":[
        "sunbeds"
    ],
    "wof:name":"Eurosun Hire Ltd.",
    "wof:placetype":"venue"
},
  "geometry": {"coordinates":[-1.818062,52.452003],"type":"Point"}
}