{
  "type": "Feature",
  "properties": {
    "iso:country":"GB",
    "sg:address":"The Green, Harrold",
    "sg:city":"Bedford",
    "sg:classifiers":[
        {
            "category":"Education",
            "subcategory":"School",
            "type":"Public Place"
        }
    ],
    "sg:phone":"+44 1234 720312",
    "sg:postcode":"MK43 7DE",
    "sg:province":"Bedfordshire",
    "sg:tags":[
        "local",
        "authority"
    ],
    "wof:name":"Harrold Lower School",
    "wof:placetype":"venue"
},
  "geometry": {"coordinates":[-0.610479,52.201248],"type":"Point"}
}