{
  "type": "Feature",
  "properties": {
    "iso:country":"GB",
    "sg:address":"22 City Road",
    "sg:city":"London",
    "sg:classifiers":[
        {
            "category":"Professional",
            "subcategory":"Computer Services",
            "type":"Services"
        }
    ],
    "sg:postcode":"EC1Y 2AJ",
    "sg:province":"Greater London",
    "sg:tags":[
        "system",
        "software"
    ],
    "wof:name":"Investment Intelligence Systems Corp",
    "wof:placetype":"venue"
},
  "geometry": {"coordinates":[-0.0873439983,51.5225944519],"type":"Point"}
}