{
  "type": "Feature",
  "properties": {
    "addr:full":"3 Bold Street Liverpool Merseyside L1 4DJ",
    "addr:housenumber":"3",
    "addr:postcode":"l1 4dj",
    "addr:street":"Bold Street",
    "iso:country":"GB",
    "sg:address":"3 Bold Street",
    "sg:city":"Liverpool",
    "sg:classifiers":[
        {
            "category":"Shopping",
            "subcategory":"Hobbies, Toys, & Games",
            "type":"Retail Goods"
        },
        {
            "category":"Shopping",
            "subcategory":"News",
            "type":"Retail Goods"
        }
    ],
    "sg:phone":"+44 151 708 7395",
    "sg:postcode":"L1 4DJ",
    "sg:province":"Merseyside",
    "sg:tags":[
        "shop",
        "toy",
        "newsagent",
        "sale"
    ],
    "wof:name":"Early Learning Centre Ltd",
    "wof:placetype":"venue"
},
  "geometry": {"coordinates":[-2.980987072,53.4045906067],"type":"Point"}
}