{
  "type": "Feature",
  "properties": {
    "addr:full":"Millfield Court, 169 Dogsthorpe Road Peterborough Cambridgeshire PE1 3BZ",
    "addr:housenumber":"169",
    "addr:postcode":"pe1 3bz",
    "addr:street":"Millfield;Dogsthorpe Road",
    "iso:country":"GB",
    "sg:address":"Millfield Court, 169 Dogsthorpe Road",
    "sg:city":"Peterborough",
    "sg:classifiers":[
        {
            "category":"Organizations",
            "subcategory":"Community Association",
            "type":"Services"
        }
    ],
    "sg:phone":"+44 1733 345508",
    "sg:postcode":"PE1 3BZ",
    "sg:province":"Cambridgeshire",
    "sg:tags":[
        "co-operatives",
        "society",
        "housing",
        "trust"
    ],
    "sg:website":"http://www.anchor.org.uk",
    "wof:name":"Anchor Trust",
    "wof:placetype":"venue"
},
  "geometry": {"coordinates":[-0.2416830063,52.5864639282],"type":"Point"}
}