{
  "type": "Feature",
  "properties": {
    "addr:full":"Unit 4, 100 The Highway London Greater London E1W 2BX",
    "addr:housenumber":"unit 4",
    "addr:postcode":"100;e1w 2bx",
    "addr:street":"The Highway",
    "iso:country":"GB",
    "sg:address":"Unit 4, 100 The Highway",
    "sg:city":"London",
    "sg:classifiers":[
        {
            "category":"Shopping",
            "subcategory":"Stationery & Office Supplies",
            "type":"Retail Goods"
        }
    ],
    "sg:phone":"+44 20 7481 1180",
    "sg:postcode":"E1W 2BX",
    "sg:province":"Greater London",
    "sg:tags":[
        "printers'"
    ],
    "wof:name":"Maritime Printing Co. Ltd.",
    "wof:placetype":"venue"
},
  "geometry": {"coordinates":[-0.0615819991,51.5092277527],"type":"Point"}
}