{
  "type": "Feature",
  "properties": {
    "iso:country":"GB",
    "sg:address":"Redcar Terrace, West Boldon",
    "sg:city":"East Boldon",
    "sg:classifiers":[
        {
            "category":"Bars & Pubs",
            "type":"Food & Drink"
        },
        {
            "category":"Community Center",
            "subcategory":"Social",
            "type":"Public Place"
        }
    ],
    "sg:phone":"+44 191 536 4197",
    "sg:postcode":"NE36 0PZ",
    "sg:province":"Tyne and Wear",
    "sg:tags":[
        "pubs",
        "house",
        "inn",
        "activity"
    ],
    "wof:name":"The Red Lion Inn",
    "wof:placetype":"venue"
},
  "geometry": {"coordinates":[-1.424329,54.94558],"type":"Point"}
}