{
  "type": "Feature",
  "properties": {
    "iso:country":"GB",
    "sg:address":"Great Oaks Farm, Wormley",
    "sg:city":"Godalming",
    "sg:classifiers":[
        {
            "category":"Retail",
            "subcategory":"Veterinary Services",
            "type":"Services"
        }
    ],
    "sg:postcode":"GU8 4XL",
    "sg:province":"Surrey",
    "sg:tags":[
        "surgeon"
    ],
    "wof:name":"Trevor Armstrong",
    "wof:placetype":"venue"
},
  "geometry": {"coordinates":[-0.64805,51.116001],"type":"Point"}
}