{
  "type": "Feature",
  "properties": {
    "iso:country":"GB",
    "sg:address":"3 Bruntsfield Crescent",
    "sg:city":"Edinburgh",
    "sg:classifiers":[
        {
            "category":"Government",
            "subcategory":"Office",
            "type":"Public Place"
        }
    ],
    "sg:phone":"+44 131 446 9611",
    "sg:postcode":"EH10 4HD",
    "sg:province":"City of Edinburgh",
    "sg:tags":[
        "project",
        "gov",
        "community"
    ],
    "wof:name":"Seteg",
    "wof:placetype":"venue"
},
  "geometry": {"coordinates":[-3.2073791027,55.9369812012],"type":"Point"}
}