{
  "type": "Feature",
  "properties": {
    "addr:full":"2 Glamis Centre Glenrothes Fife KY7 4RH",
    "addr:housenumber":"2",
    "addr:postcode":"ky7 4rh",
    "addr:street":"Glamis Centre",
    "iso:country":"GB",
    "sg:address":"2 Glamis Centre",
    "sg:city":"Glenrothes",
    "sg:classifiers":[
        {
            "category":"Food & Beverages",
            "subcategory":"Meat & Fish",
            "type":"Retail Goods"
        }
    ],
    "sg:phone":"+44 1592 771457",
    "sg:postcode":"KY7 4RH",
    "sg:province":"Fife",
    "sg:tags":[
        "butcher"
    ],
    "wof:name":"Alex Mitchell",
    "wof:placetype":"venue"
},
  "geometry": {"coordinates":[-3.164719,56.182823],"type":"Point"}
}