{
  "type": "Feature",
  "properties": {
    "addr:full":"26-27 Dunstall Hill Industrial Estate, Gorsebrook Road Wolverhampton Shropshire WV6 0PJ",
    "addr:housenumber":"26-27",
    "addr:postcode":"shropshire wv6 0pj",
    "addr:street":"Dunstall Hill Industrial Estate Gorsebrook Road",
    "iso:country":"GB",
    "sg:address":"26-27 Dunstall Hill Industrial Estate, Gorsebrook Road",
    "sg:city":"Wolverhampton",
    "sg:classifiers":[
        {
            "category":"Personal",
            "type":"Services"
        }
    ],
    "sg:phone":"+44 1902 714102",
    "sg:postcode":"WV6 0PJ",
    "sg:province":"Shropshire",
    "sg:tags":[
        "delivery"
    ],
    "wof:name":"Royal Mail Parcelforce",
    "wof:placetype":"venue"
},
  "geometry": {"coordinates":[-2.132336,52.596218],"type":"Point"}
}