{
  "type": "Feature",
  "properties": {
    "iso:country":"GB",
    "sg:address":"149 Uppingham Rd",
    "sg:city":"Leicester",
    "sg:classifiers":[
        {
            "category":"Shopping",
            "subcategory":"Pharmacy",
            "type":"Retail Goods"
        }
    ],
    "sg:phone":"+44 116 274 3136",
    "sg:postcode":"LE5 4BP",
    "sg:province":"Leicestershire",
    "sg:tags":[
        "pharmacist",
        "chemist"
    ],
    "wof:name":"F O Robinson Ltd",
    "wof:placetype":"venue"
},
  "geometry": {"coordinates":[-1.09529,52.642071],"type":"Point"}
}