{
  "type": "Feature",
  "properties": {
    "iso:country":"GB",
    "sg:address":"Dukes Gallery, Cartway",
    "sg:city":"Bridgnorth",
    "sg:classifiers":[
        {
            "category":"Shopping",
            "subcategory":"Clothing, Apparel, & Fashions",
            "type":"Retail Goods"
        }
    ],
    "sg:phone":"+44 1746 764445",
    "sg:postcode":"WV16 4BG",
    "sg:province":"Shropshire",
    "sg:tags":[
        "shop",
        "dress",
        "fancy"
    ],
    "wof:name":"Cartway Kapers",
    "wof:placetype":"venue"
},
  "geometry": {"coordinates":[-2.420479,52.536819],"type":"Point"}
}