{
  "type": "Feature",
  "properties": {
    "iso:country":"GB",
    "sg:address":"Abberton Car Sale",
    "sg:city":"Colchester",
    "sg:classifiers":[
        {
            "category":"Autos & Motor Vehicles",
            "subcategory":"Automobile Sales",
            "type":"Retail Goods"
        }
    ],
    "sg:phone":"+44 1206 571578",
    "sg:postcode":"CO2 7JP",
    "sg:province":"Essex",
    "sg:tags":[
        "car"
    ],
    "wof:name":"Abberton Car Sale",
    "wof:placetype":"venue"
},
  "geometry": {"coordinates":[0.903514,51.8853],"type":"Point"}
}