{
  "type": "Feature",
  "properties": {
    "addr:full":"1 Edmunds Corner, Old Cross Hertford Hertfordshire SG14 1RE",
    "addr:housenumber":"1",
    "addr:postcode":"sg14 1re",
    "addr:street":"Edmunds Corner Old Cross",
    "iso:country":"GB",
    "sg:address":"1 Edmunds Corner, Old Cross",
    "sg:city":"Hertford",
    "sg:classifiers":[
        {
            "category":"Professional",
            "subcategory":"Lawyer & Legal Services",
            "type":"Services"
        }
    ],
    "sg:phone":"+44 1992 552292",
    "sg:postcode":"SG14 1RE",
    "sg:province":"Hertfordshire",
    "sg:tags":[
        "solicitor"
    ],
    "wof:name":"Peter H Sturrock",
    "wof:placetype":"venue"
},
  "geometry": {"coordinates":[-0.082699,51.796341],"type":"Point"}
}