{
  "type": "Feature",
  "properties": {
    "addr:full":"Lansdown Road Bath Bath and North East Somerset BA1 5EQ",
    "addr:postcode":"ba1 5eq",
    "addr:street":"Lansdown Road",
    "iso:country":"GB",
    "sg:address":"Lansdown Road",
    "sg:city":"Bath",
    "sg:classifiers":[
        {
            "category":"Home & Garden",
            "subcategory":"Home Furnishings",
            "type":"Retail Goods"
        },
        {
            "category":"Building & Trades",
            "subcategory":"Construction",
            "type":"Services"
        }
    ],
    "sg:phone":"+44 1225 330843",
    "sg:postcode":"BA1 5EQ",
    "sg:province":"Bath and North East Somerset",
    "sg:tags":[
        "furnishers",
        "planner",
        "joiner",
        "carpenter",
        "kitchen"
    ],
    "wof:name":"Westside Design",
    "wof:placetype":"venue"
},
  "geometry": {"coordinates":[-2.3621790409,51.3889007568],"type":"Point"}
}