{
  "type": "Feature",
  "properties": {
    "addr:full":"55 Friars Lane Barrow-in-furness Cumbria LA13 9NS",
    "addr:housenumber":"55",
    "addr:postcode":"la13 9ns",
    "addr:street":"Friars Lane",
    "iso:country":"GB",
    "sg:address":"55 Friars Lane",
    "sg:city":"Barrow-in-furness",
    "sg:classifiers":[
        {
            "category":"Professional",
            "subcategory":"Business Services",
            "type":"Services"
        }
    ],
    "sg:postcode":"LA13 9NS",
    "sg:province":"Cumbria",
    "sg:tags":[
        "bookmaker"
    ],
    "wof:name":"James Thorp",
    "wof:placetype":"venue"
},
  "geometry": {"coordinates":[-3.201267004,54.1165962219],"type":"Point"}
}