{
  "type": "Feature",
  "properties": {
    "iso:country":"GB",
    "sg:address":"42 Hampden Rd, Langley",
    "sg:city":"Slough",
    "sg:classifiers":[
        {
            "category":"Building & Trades",
            "subcategory":"Construction",
            "type":"Services"
        }
    ],
    "sg:phone":"+44 1753 814180",
    "sg:postcode":"SL3 8SE",
    "sg:province":"Berkshire",
    "sg:tags":[
        "roofing"
    ],
    "wof:name":"DPR",
    "wof:placetype":"venue"
},
  "geometry": {"coordinates":[-0.549139,51.502483],"type":"Point"}
}