{
  "type": "Feature",
  "properties": {
    "addr:full":"103 Green Street, Forest Gate London Greater London E7 8JF",
    "addr:housenumber":"103",
    "addr:postcode":"e7 8jf",
    "addr:street":"Green Street",
    "iso:country":"GB",
    "sg:address":"103 Green Street, Forest Gate",
    "sg:city":"London",
    "sg:classifiers":[
        {
            "category":"Food & Beverages",
            "subcategory":"Supermarket",
            "type":"Retail Goods"
        }
    ],
    "sg:phone":"+44 20 8471 1152",
    "sg:postcode":"E7 8JF",
    "sg:province":"Greater London",
    "wof:name":"Toor Supermarkets",
    "wof:placetype":"venue"
},
  "geometry": {"coordinates":[0.0321229994,51.5446968079],"type":"Point"}
}