{
  "type": "Feature",
  "properties": {
    "addr:full":"2 The Avenue, Fairfield Stockton-on-tees Durham TS19 7EY",
    "addr:housenumber":"2",
    "addr:postcode":"ts19 7ey",
    "addr:street":"The Avenue",
    "iso:country":"GB",
    "sg:address":"2 The Avenue, Fairfield",
    "sg:city":"Stockton-on-tees",
    "sg:classifiers":[
        {
            "category":"Health Services",
            "subcategory":"Nursing And Care Facility",
            "type":"Services"
        }
    ],
    "sg:phone":"+44 1642 884001",
    "sg:postcode":"TS19 7EY",
    "sg:province":"Durham",
    "sg:tags":[
        "home"
    ],
    "wof:name":"Charnwood Nursing Home",
    "wof:placetype":"venue"
},
  "geometry": {"coordinates":[-1.3532400131,54.569480896],"type":"Point"}
}