{
  "type": "Feature",
  "properties": {
    "iso:country":"GB",
    "sg:address":"29 Cole Street",
    "sg:city":"Scunthorpe",
    "sg:classifiers":[
        {
            "category":"Personal",
            "subcategory":"Beauty Salon",
            "type":"Services"
        }
    ],
    "sg:phone":"+44 1724 276565",
    "sg:postcode":"DN15 6QY",
    "sg:province":"Lincolnshire",
    "sg:tags":[
        "unisex",
        "hairdresser"
    ],
    "wof:name":"Beauty by Yvonne",
    "wof:placetype":"venue"
},
  "geometry": {"coordinates":[-0.64594,53.589249],"type":"Point"}
}