{
  "type": "Feature",
  "properties": {
    "addr:full":"Spinney Hill Road Leicester Leicestershire LE5 3GH",
    "addr:postcode":"le5 3gh",
    "addr:street":"Spinney Hill Road",
    "iso:country":"GB",
    "sg:address":"Spinney Hill Road",
    "sg:city":"Leicester",
    "sg:classifiers":[
        {
            "category":"Place Of Worship",
            "type":"Public Place"
        },
        {
            "category":"Organizations",
            "subcategory":"Non-profit Organization",
            "type":"Services"
        }
    ],
    "sg:phone":"+44 116 251 1668",
    "sg:postcode":"LE5 3GH",
    "sg:province":"Leicestershire",
    "sg:tags":[
        "charitable",
        "organisation",
        "charity"
    ],
    "wof:name":"EMMANUEL UNITED REFORMED CHURCH",
    "wof:placetype":"venue"
},
  "geometry": {"coordinates":[-1.1083589792,52.6409912109],"type":"Point"}
}