{
  "type": "Feature",
  "properties": {
    "iso:country":"GB",
    "sg:address":"470 Hempshaw Lane",
    "sg:city":"Stockport",
    "sg:classifiers":[
        {
            "category":"Shopping",
            "subcategory":"Gifts & Souvenirs",
            "type":"Retail Goods"
        }
    ],
    "sg:postcode":"SK2 5SU",
    "sg:province":"Cheshire",
    "sg:tags":[
        "poster",
        "card"
    ],
    "wof:name":"Hempshaw Lane Sub Post Office",
    "wof:placetype":"venue"
},
  "geometry": {"coordinates":[-2.1346540451,53.4011993408],"type":"Point"}
}