{
  "type": "Feature",
  "properties": {
    "addr:full":"High Street March Cambridgeshire PE15 9JJ",
    "addr:postcode":"pe15 9jj",
    "addr:street":"High Street",
    "iso:country":"GB",
    "sg:address":"High Street",
    "sg:city":"March",
    "sg:classifiers":[
        {
            "category":"Museum",
            "subcategory":"Art Museum",
            "type":"Entertainment"
        },
        {
            "category":"Museum",
            "type":"Entertainment"
        }
    ],
    "sg:phone":"+44 1354 655300",
    "sg:postcode":"PE15 9JJ",
    "sg:province":"Cambridgeshire",
    "sg:tags":[
        "gallery"
    ],
    "wof:name":"March & District Museum",
    "wof:placetype":"venue"
},
  "geometry": {"coordinates":[0.08808,52.54977],"type":"Point"}
}