{
  "type": "Feature",
  "properties": {
    "iso:country":"GB",
    "sg:address":"839 Longbridge Rd",
    "sg:city":"Dagenham",
    "sg:classifiers":[
        {
            "category":"Shopping",
            "subcategory":"Party Supplies",
            "type":"Retail Goods"
        }
    ],
    "sg:phone":"+44 20 8597 4000",
    "sg:postcode":"RM8 2DA",
    "sg:province":"Essex",
    "sg:tags":[
        "inflatables",
        "bouncy",
        "castle"
    ],
    "wof:name":"A Bouncy Castle",
    "wof:placetype":"venue"
},
  "geometry": {"coordinates":[0.1149429977,51.5517234802],"type":"Point"}
}