{
  "type": "Feature",
  "properties": {
    "addr:full":"Barnfield Road Crawley Surrey RH10 8DS",
    "addr:postcode":"rh10 8ds",
    "addr:street":"Barnfield Road",
    "iso:country":"GB",
    "sg:address":"Barnfield Road",
    "sg:city":"Crawley",
    "sg:classifiers":[
        {
            "category":"Community Center",
            "type":"Public Place"
        }
    ],
    "sg:phone":"+44 1293 616284",
    "sg:postcode":"RH10 8DS",
    "sg:province":"Surrey",
    "sg:tags":[
        "centre"
    ],
    "wof:name":"Northgate Community Centre",
    "wof:placetype":"venue"
},
  "geometry": {"coordinates":[-0.187447,51.122696],"type":"Point"}
}