{
  "type": "Feature",
  "properties": {
    "iso:country":"GB",
    "sg:address":"262 Wellington Road South, Heaviley",
    "sg:city":"Stockport",
    "sg:classifiers":[
        {
            "category":"Shopping",
            "subcategory":"Florist",
            "type":"Retail Goods"
        }
    ],
    "sg:phone":"+44 161 480 0112",
    "sg:postcode":"SK2 6ND",
    "sg:province":"Cheshire",
    "wof:name":"Gresty's Florists",
    "wof:placetype":"venue"
},
  "geometry": {"coordinates":[-2.1538820267,53.3992500305],"type":"Point"}
}