{
  "type": "Feature",
  "properties": {
    "addr:full":"Station Road, Gnosall Stafford Staffordshire ST20 0EZ",
    "addr:postcode":"st20 0ez",
    "addr:street":"Station Road",
    "iso:country":"GB",
    "sg:address":"Station Road, Gnosall",
    "sg:city":"Stafford",
    "sg:classifiers":[
        {
            "category":"Autos & Motor Vehicles",
            "subcategory":"Fuel & Gas Station",
            "type":"Retail Goods"
        }
    ],
    "sg:phone":"+44 1785 822364",
    "sg:postcode":"ST20 0EZ",
    "sg:province":"Staffordshire",
    "sg:tags":[
        "petrol",
        "filling"
    ],
    "wof:name":"Gnosall Service Station",
    "wof:placetype":"venue"
},
  "geometry": {"coordinates":[-2.256487,52.78233],"type":"Point"}
}