{
  "type": "Feature",
  "properties": {
    "iso:country":"GB",
    "sg:address":"24 Second Avenue, Southbourne",
    "sg:city":"Emsworth",
    "sg:classifiers":[
        {
            "category":"Building & Trades",
            "subcategory":"Construction",
            "type":"Services"
        }
    ],
    "sg:phone":"+44 1243 374506",
    "sg:postcode":"PO10 8HP",
    "sg:province":"Hampshire",
    "sg:tags":[
        "decorator",
        "painter"
    ],
    "wof:name":"J B Cooper",
    "wof:placetype":"venue"
},
  "geometry": {"coordinates":[-0.911652,50.847107],"type":"Point"}
}