{
  "type": "Feature",
  "properties": {
    "addr:full":"40 Nottingham Road Ilkeston Derbyshire DE7 5NL",
    "addr:housenumber":"40",
    "addr:postcode":"de7 5nl",
    "addr:street":"Nottingham Road",
    "iso:country":"GB",
    "sg:address":"40 Nottingham Road",
    "sg:city":"Ilkeston",
    "sg:classifiers":[
        {
            "category":"Shopping",
            "subcategory":"Pharmacy",
            "type":"Retail Goods"
        }
    ],
    "sg:phone":"+44 115 932 5447",
    "sg:postcode":"DE7 5NL",
    "sg:province":"Derbyshire",
    "sg:tags":[
        "pharmacist",
        "dispensing",
        "chemist"
    ],
    "wof:name":"Manor Pharmacy Ltd",
    "wof:placetype":"venue"
},
  "geometry": {"coordinates":[-1.305242,52.966606],"type":"Point"}
}