{
  "type": "Feature",
  "properties": {
    "addr:full":"P O Box 37 Northallerton North Yorkshire DL7 9YZ",
    "addr:housenumber":"box 37",
    "addr:postcode":"dl7 9yz",
    "addr:street":"P O",
    "iso:country":"GB",
    "sg:address":"P O Box 37",
    "sg:city":"Northallerton",
    "sg:classifiers":[
        {
            "category":"Building & Trades",
            "subcategory":"Cleaning & Sanitation",
            "type":"Services"
        }
    ],
    "sg:phone":"+44 1677 424621",
    "sg:postcode":"DL7 9YZ",
    "sg:province":"North Yorkshire",
    "sg:tags":[
        "facility"
    ],
    "wof:name":"Aqumen Services Ltd",
    "wof:placetype":"venue"
},
  "geometry": {"coordinates":[-1.4315199852,54.3383598328],"type":"Point"}
}