{
  "type": "Feature",
  "properties": {
    "addr:full":"Suite B Ground Floor, Hawbank House Cheadle Cheshire SK8 1AL",
    "addr:housenumber":"suite b ground floor hawbank house cheadle",
    "addr:postcode":"sk8 1al",
    "iso:country":"GB",
    "sg:address":"Suite B Ground Floor, Hawbank House",
    "sg:city":"Cheadle",
    "sg:classifiers":[
        {
            "category":"Communications",
            "type":"Services"
        }
    ],
    "sg:phone":"+44 161 491 1451",
    "sg:postcode":"SK8 1AL",
    "sg:province":"Cheshire",
    "sg:tags":[
        "telecommunication"
    ],
    "wof:name":"I T S",
    "wof:placetype":"venue"
},
  "geometry": {"coordinates":[-2.212272,53.395248],"type":"Point"}
}