{
  "type": "Feature",
  "properties": {
    "addr:full":"Glanville Road Bromley Kent BR2 9LW",
    "addr:postcode":"br2 9lw",
    "addr:street":"Glanville Road",
    "iso:country":"GB",
    "sg:address":"Glanville Road",
    "sg:city":"Bromley",
    "sg:classifiers":[
        {
            "category":"Arena",
            "subcategory":"Sports Club",
            "type":"Entertainment"
        }
    ],
    "sg:phone":"+44 20 8460 4052",
    "sg:postcode":"BR2 9LW",
    "sg:province":"Kent",
    "wof:name":"Wendover Lawn Tennis Club Ltd.",
    "wof:placetype":"venue"
},
  "geometry": {"coordinates":[0.025501,51.398499],"type":"Point"}
}