{
  "type": "Feature",
  "properties": {
    "addr:full":"4 Central Chambers, Railway Street Leyburn North Yorkshire DL8 5BB",
    "addr:housenumber":"4",
    "addr:postcode":"dl8 5bb",
    "addr:street":"Railway Street",
    "iso:country":"GB",
    "sg:address":"4 Central Chambers, Railway Street",
    "sg:city":"Leyburn",
    "sg:classifiers":[
        {
            "category":"Landmark",
            "subcategory":"Tourist Information",
            "type":"Public Place"
        }
    ],
    "sg:phone":"+44 1969 623069",
    "sg:postcode":"DL8 5BB",
    "sg:province":"North Yorkshire",
    "wof:name":"Tourist Information Centre",
    "wof:placetype":"venue"
},
  "geometry": {"coordinates":[-1.830434,54.310139],"type":"Point"}
}