{
  "type": "Feature",
  "properties": {
    "iso:country":"GB",
    "sg:address":"Bawtry Road",
    "sg:city":"Rotherham",
    "sg:classifiers":[
        {
            "category":"Parking",
            "type":"Transportation"
        }
    ],
    "sg:phone":"+44 1709 720070",
    "sg:postcode":"S60 5DN",
    "sg:province":"South Yorkshire",
    "sg:tags":[
        "car",
        "valet"
    ],
    "wof:name":"The New Budget Tyre Co.",
    "wof:placetype":"venue"
},
  "geometry": {"coordinates":[-1.348487,53.405212],"type":"Point"}
}