{
  "type": "Feature",
  "properties": {
    "iso:country":"GB",
    "sg:address":"14 Boeing Way",
    "sg:city":"Bury St Edmunds",
    "sg:classifiers":[
        {
            "category":"Retail",
            "subcategory":"Event Space",
            "type":"Services"
        }
    ],
    "sg:phone":"+44 1638 515548",
    "sg:postcode":"IP28 7RJ",
    "sg:province":"Cambridgeshire",
    "sg:tags":[
        "exhibition",
        "organiser"
    ],
    "wof:name":"Scorrpitex Ltd",
    "wof:placetype":"venue"
},
  "geometry": {"coordinates":[0.5037500262,52.3486404419],"type":"Point"}
}