{
  "type": "Feature",
  "properties": {
    "iso:country":"GB",
    "sg:address":"42 Glynne Road",
    "sg:city":"Bangor",
    "sg:classifiers":[
        {
            "category":"Building & Trades",
            "subcategory":"Construction",
            "type":"Services"
        }
    ],
    "sg:phone":"+44 1248 355326",
    "sg:postcode":"LL57 1AN",
    "sg:province":"Gwynedd",
    "sg:tags":[
        "decorator",
        "painter"
    ],
    "wof:name":"J Williams",
    "wof:placetype":"venue"
},
  "geometry": {"coordinates":[-4.124144,53.231724],"type":"Point"}
}