{
  "type": "Feature",
  "properties": {
    "iso:country":"GB",
    "sg:address":"78a Neville Street, Oakhill",
    "sg:city":"Stoke-on-trent",
    "sg:classifiers":[
        {
            "category":"Professional",
            "subcategory":"Art Services",
            "type":"Services"
        }
    ],
    "sg:postcode":"ST4 5BJ",
    "sg:province":"Staffordshire",
    "sg:tags":[
        "stone",
        "restoration",
        "cleaning"
    ],
    "wof:name":"Stoke Cleaning Services",
    "wof:placetype":"venue"
},
  "geometry": {"coordinates":[-2.1969239712,52.9906806946],"type":"Point"}
}