{
  "type": "Feature",
  "properties": {
    "addr:full":"The Precinct, Boverton Road Llantwit Major The Vale of Glamorgan CF61 1XA",
    "addr:postcode":"cf61 1xa",
    "addr:street":"Boverton Road;Vale",
    "iso:country":"GB",
    "sg:address":"The Precinct, Boverton Road",
    "sg:city":"Llantwit Major",
    "sg:classifiers":[
        {
            "category":"Food & Beverages",
            "subcategory":"Supermarket",
            "type":"Retail Goods"
        }
    ],
    "sg:phone":"+44 1446 792344",
    "sg:postcode":"CF61 1XA",
    "sg:province":"The Vale of Glamorgan",
    "wof:name":"Gateway Food Markets",
    "wof:placetype":"venue"
},
  "geometry": {"coordinates":[-3.488492012,51.4101600647],"type":"Point"}
}