{
  "type": "Feature",
  "properties": {
    "iso:country":"GB",
    "sg:address":"Railway Sidings, Wigginton Road",
    "sg:city":"York",
    "sg:classifiers":[
        {
            "category":"Utilities",
            "subcategory":"Refuse",
            "type":"Services"
        }
    ],
    "sg:phone":"+44 1904 623678",
    "sg:postcode":"YO31 8JG",
    "sg:province":"North Yorkshire",
    "sg:tags":[
        "skip",
        "hire"
    ],
    "wof:name":"Dennings Of York",
    "wof:placetype":"venue"
},
  "geometry": {"coordinates":[-1.08216,53.97316],"type":"Point"}
}