{
  "type": "Feature",
  "properties": {
    "addr:full":"14 Ashby Street, Hendon Sunderland Tyne and Wear SR2 8QA",
    "addr:housenumber":"14",
    "addr:postcode":"sr2 8qa",
    "addr:street":"Ashby Street",
    "iso:country":"GB",
    "sg:address":"14 Ashby Street, Hendon",
    "sg:city":"Sunderland",
    "sg:classifiers":[
        {
            "category":"Utilities",
            "subcategory":"Natural Gas",
            "type":"Services"
        }
    ],
    "sg:phone":"+44 191 567 8088",
    "sg:postcode":"SR2 8QA",
    "sg:province":"Tyne and Wear",
    "sg:tags":[
        "supplier"
    ],
    "wof:name":"Flo-Gas Services",
    "wof:placetype":"venue"
},
  "geometry": {"coordinates":[-1.367459,54.891239],"type":"Point"}
}