{
  "type": "Feature",
  "properties": {
    "addr:full":"2 Walshaw Place Oldham Lancashire OL1 3UY",
    "addr:housenumber":"2",
    "addr:postcode":"ol1 3uy",
    "addr:street":"Walshaw Place",
    "iso:country":"GB",
    "sg:address":"2 Walshaw Place",
    "sg:city":"Oldham",
    "sg:classifiers":[
        {
            "category":"Manufacturing",
            "subcategory":"Textiles",
            "type":"Manufacturing & Wholesale Goods"
        }
    ],
    "sg:phone":"+44 161 626 6769",
    "sg:postcode":"OL1 3UY",
    "sg:province":"Lancashire",
    "sg:tags":[
        "merchant",
        "agent"
    ],
    "wof:name":"Din Textiles",
    "wof:placetype":"venue"
},
  "geometry": {"coordinates":[-2.1041049957,53.5435600281],"type":"Point"}
}