{
  "type": "Feature",
  "properties": {
    "iso:country":"GB",
    "sg:address":"Rose Ct, 3 Deighton Grove La, Crockey Hill",
    "sg:city":"York",
    "sg:classifiers":[
        {
            "category":"Wholesale",
            "subcategory":"Machinery & Supplies",
            "type":"Manufacturing & Wholesale Goods"
        }
    ],
    "sg:postcode":"YO19 4SN",
    "sg:province":"North Yorkshire",
    "sg:tags":[
        "hydraulic"
    ],
    "wof:name":"Hyde,R S,",
    "wof:placetype":"venue"
},
  "geometry": {"coordinates":[-1.0501149893,53.9105873108],"type":"Point"}
}