{
  "type": "Feature",
  "properties": {
    "addr:full":"256 Lumb La Manchester Greater Manchester M43 7LG",
    "addr:housenumber":"256",
    "addr:postcode":"m43 7lg",
    "addr:street":"Lumb La Manchester",
    "iso:country":"GB",
    "sg:address":"256 Lumb La",
    "sg:city":"Manchester",
    "sg:classifiers":[
        {
            "category":"Government",
            "subcategory":"Post Office",
            "type":"Public Place"
        }
    ],
    "sg:phone":"+44 161 370 2422",
    "sg:postcode":"M43 7LG",
    "sg:province":"Greater Manchester",
    "wof:name":"Lund,Paulina,",
    "wof:placetype":"venue"
},
  "geometry": {"coordinates":[-2.132539,53.492039],"type":"Point"}
}