{
  "type": "Feature",
  "properties": {
    "addr:full":"Farm& Garden Stores, 18 Strath Gairloch Highland IV21 2BX",
    "addr:housenumber":"18",
    "addr:postcode":"iv21 2bx",
    "addr:street":"Strath Gairloch",
    "iso:country":"GB",
    "sg:address":"Farm& Garden Stores, 18 Strath",
    "sg:city":"Gairloch",
    "sg:classifiers":[
        {
            "category":"Shopping",
            "subcategory":"Pets & Pet Supplies",
            "type":"Retail Goods"
        }
    ],
    "sg:phone":"+44 1445 712083",
    "sg:postcode":"IV21 2BX",
    "sg:province":"Highland",
    "sg:tags":[
        "food",
        "feed",
        "animal"
    ],
    "wof:name":"Farm & Garden Stores",
    "wof:placetype":"venue"
},
  "geometry": {"coordinates":[-5.7224960327,57.7315597534],"type":"Point"}
}