{
  "type": "Feature",
  "properties": {
    "iso:country":"GB",
    "sg:address":"3 Moreton Avenue, Great Barr",
    "sg:city":"Birmingham",
    "sg:classifiers":[
        {
            "category":"Manufacturing",
            "subcategory":"Tools & Machinery",
            "type":"Manufacturing & Wholesale Goods"
        },
        {
            "category":"Insurance",
            "subcategory":"Insurance Agent",
            "type":"Services"
        }
    ],
    "sg:phone":"+44 121 325 0633",
    "sg:postcode":"B43 7QP",
    "sg:province":"West Midlands",
    "sg:tags":[
        "society",
        "friendly"
    ],
    "wof:name":"J E Oakley & Son (Midlands) Ltd.",
    "wof:placetype":"venue"
},
  "geometry": {"coordinates":[-1.910298,52.553406],"type":"Point"}
}