{
  "type": "Feature",
  "properties": {
    "iso:country":"GB",
    "sg:address":"Wellington St",
    "sg:city":"Stockport",
    "sg:classifiers":[
        {
            "category":"Bars & Pubs",
            "subcategory":"Nightclub",
            "type":"Food & Drink"
        }
    ],
    "sg:postcode":"SK1 3AD",
    "sg:province":"Cheshire",
    "sg:tags":[
        "club",
        "night"
    ],
    "wof:name":"Peaches",
    "wof:placetype":"venue"
},
  "geometry": {"coordinates":[-2.155883,53.409126],"type":"Point"}
}