{
  "type": "Feature",
  "properties": {
    "addr:full":"Unit 9/10 Leeds West Yorkshire LS11 5SS",
    "addr:housenumber":"unit 9 / 10",
    "addr:postcode":"ls11 5ss",
    "addr:street":"Leeds West",
    "iso:country":"GB",
    "sg:address":"Unit 9/10",
    "sg:city":"Leeds",
    "sg:classifiers":[
        {
            "category":"Wholesale",
            "subcategory":"Construction Materials",
            "type":"Manufacturing & Wholesale Goods"
        }
    ],
    "sg:phone":"+44 113 276 5552",
    "sg:postcode":"LS11 5SS",
    "sg:province":"West Yorkshire",
    "sg:tags":[
        "coating",
        "powder"
    ],
    "wof:name":"Wilkinson Investments Ltd.",
    "wof:placetype":"venue"
},
  "geometry": {"coordinates":[-1.551842,53.791779],"type":"Point"}
}