{
  "type": "Feature",
  "properties": {
    "addr:full":"24 Tudor Street London Greater London EC4Y 0AY",
    "addr:housenumber":"24",
    "addr:postcode":"ec4y 0ay",
    "addr:street":"Tudor Street",
    "iso:country":"GB",
    "sg:address":"24 Tudor Street",
    "sg:city":"London",
    "sg:classifiers":[
        {
            "category":"Food & Beverages",
            "subcategory":"Candy",
            "type":"Retail Goods"
        }
    ],
    "sg:postcode":"EC4Y 0AY",
    "sg:province":"Greater London",
    "sg:tags":[
        "confectioner"
    ],
    "wof:name":"City Confectionery",
    "wof:placetype":"venue"
},
  "geometry": {"coordinates":[-0.106559,51.512756],"type":"Point"}
}