{
  "type": "Feature",
  "properties": {
    "addr:full":"St Sepulchre Gate Doncaster South Yorkshire DN1 1TD",
    "addr:postcode":"dn1 1td",
    "addr:street":"St Sepulchre Gate",
    "iso:country":"GB",
    "sg:address":"St Sepulchre Gate",
    "sg:city":"Doncaster",
    "sg:classifiers":[
        {
            "category":"Bars & Pubs",
            "type":"Food & Drink"
        }
    ],
    "sg:phone":"+44 1302 367126",
    "sg:postcode":"DN1 1TD",
    "sg:province":"South Yorkshire",
    "sg:tags":[
        "pubs",
        "inn"
    ],
    "wof:name":"Paris Gate",
    "wof:placetype":"venue"
},
  "geometry": {"coordinates":[-1.136173,53.523151],"type":"Point"}
}