{
  "type": "Feature",
  "properties": {
    "addr:full":"158 Whinney Field Road Newcastle-upon-tyne Tyne and Wear NE6 4RR",
    "addr:housenumber":"158",
    "addr:postcode":"ne6 4rr",
    "addr:street":"Whinney Field Road",
    "iso:country":"GB",
    "sg:address":"158 Whinney Field Road",
    "sg:city":"Newcastle-upon-tyne",
    "sg:classifiers":[
        {
            "category":"Building & Trades",
            "subcategory":"Landscaping Services",
            "type":"Services"
        }
    ],
    "sg:postcode":"NE6 4RR",
    "sg:province":"Tyne and Wear",
    "sg:tags":[
        "landscape",
        "contractor"
    ],
    "wof:name":"Jasmine Garden Services",
    "wof:placetype":"venue"
},
  "geometry": {"coordinates":[-1.5547540188,54.9855804443],"type":"Point"}
}