{
  "type": "Feature",
  "properties": {
    "addr:full":"Deepdale, Mill Street Preston Lancashire PR1 5BY",
    "addr:postcode":"pr1 5by",
    "addr:street":"Deepdale Mill Street",
    "iso:country":"GB",
    "sg:address":"Deepdale, Mill Street",
    "sg:city":"Preston",
    "sg:classifiers":[
        {
            "category":"Farming",
            "subcategory":"Farm",
            "type":"Manufacturing & Wholesale Goods"
        },
        {
            "category":"Retail",
            "subcategory":"Auto Repair",
            "type":"Services"
        }
    ],
    "sg:phone":"+44 1772 796047",
    "sg:postcode":"PR1 5BY",
    "sg:province":"Lancashire",
    "sg:tags":[
        "mixed",
        "electrical",
        "electrician",
        "crop",
        "centre"
    ],
    "wof:name":"Ribblesdale Auto Electrics Units Ltd",
    "wof:placetype":"venue"
},
  "geometry": {"coordinates":[-2.6849389076,53.7661933899],"type":"Point"}
}