{
  "type": "Feature",
  "properties": {
    "addr:full":"159 Oak Street Norwich Norfolk NR3 3AY",
    "addr:housenumber":"159",
    "addr:postcode":"nr3 3ay",
    "addr:street":"Oak Street",
    "iso:country":"GB",
    "sg:address":"159 Oak Street",
    "sg:city":"Norwich",
    "sg:classifiers":[
        {
            "category":"Retail",
            "subcategory":"Auto Repair",
            "type":"Services"
        }
    ],
    "sg:phone":"+44 1603 441527",
    "sg:postcode":"NR3 3AY",
    "sg:province":"Norfolk",
    "sg:tags":[
        "modification",
        "garage"
    ],
    "wof:name":"B & P Autocare",
    "wof:placetype":"venue"
},
  "geometry": {"coordinates":[1.288477,52.637241],"type":"Point"}
}