{
  "type": "Feature",
  "properties": {
    "iso:country":"GB",
    "sg:address":"204 Liverpool Road, Penwortham",
    "sg:city":"Preston",
    "sg:classifiers":[
        {
            "category":"Professional",
            "subcategory":"Art Services",
            "type":"Services"
        }
    ],
    "sg:phone":"+44 1772 750411",
    "sg:postcode":"PR1 0LY",
    "sg:province":"Lancashire",
    "sg:tags":[
        "picture",
        "framing"
    ],
    "wof:name":"Howick Gallery",
    "wof:placetype":"venue"
},
  "geometry": {"coordinates":[-2.743468,53.74435],"type":"Point"}
}