{
  "type": "Feature",
  "properties": {
    "addr:full":"1a Northern Road Swindon Wiltshire SN2 1NY",
    "addr:housenumber":"1a",
    "addr:postcode":"sn2 1ny",
    "addr:street":"Northern Road",
    "iso:country":"GB",
    "sg:address":"1a Northern Road",
    "sg:city":"Swindon",
    "sg:classifiers":[
        {
            "category":"Home & Garden",
            "subcategory":"Garden Supply",
            "type":"Retail Goods"
        }
    ],
    "sg:phone":"+44 1793 535580",
    "sg:postcode":"SN2 1NY",
    "sg:province":"Wiltshire",
    "sg:tags":[
        "nursery",
        "centre"
    ],
    "wof:name":"Northern Road Nurseries",
    "wof:placetype":"venue"
},
  "geometry": {"coordinates":[-1.794108,51.571541],"type":"Point"}
}