{
  "type": "Feature",
  "properties": {
    "iso:country":"GB",
    "sg:address":"66 High St, Watton",
    "sg:city":"Thetford",
    "sg:classifiers":[
        {
            "category":"Shopping",
            "subcategory":"Clothing, Apparel, & Fashions",
            "type":"Retail Goods"
        }
    ],
    "sg:postcode":"IP25 6AH",
    "sg:province":"Norfolk",
    "sg:tags":[
        "shop"
    ],
    "wof:name":"Studio of Labels",
    "wof:placetype":"venue"
},
  "geometry": {"coordinates":[0.8228979707,52.5714836121],"type":"Point"}
}