{
  "type": "Feature",
  "properties": {
    "addr:full":"Unit 13 Nestfield Industrial Estate Darlington Durham DL1 2NW",
    "addr:housenumber":"unit 13;estate",
    "addr:postcode":"dl1 2nw",
    "addr:street":"Nestfield Industrial",
    "iso:country":"GB",
    "sg:address":"Unit 13 Nestfield Industrial Estate",
    "sg:city":"Darlington",
    "sg:classifiers":[
        {
            "category":"Professional",
            "subcategory":"Printing & Photocopies",
            "type":"Services"
        }
    ],
    "sg:phone":"+44 1325 361124",
    "sg:postcode":"DL1 2NW",
    "sg:province":"Durham",
    "sg:tags":[
        "printer"
    ],
    "sg:website":"http://www.stelro.co.uk",
    "wof:name":"Stelro Print & Design Ltd",
    "wof:placetype":"venue"
},
  "geometry": {"coordinates":[-1.539049,54.534729],"type":"Point"}
}