{
  "type": "Feature",
  "properties": {
    "addr:full":"Garden St, Thurmaston Leicester Leicestershire LE4 8DS",
    "addr:postcode":"le4 8ds",
    "addr:street":"Garden St",
    "iso:country":"GB",
    "sg:address":"Garden St, Thurmaston",
    "sg:city":"Leicester",
    "sg:classifiers":[
        {
            "category":"Bars & Pubs",
            "type":"Food & Drink"
        }
    ],
    "sg:phone":"+44 116 269 4112",
    "sg:postcode":"LE4 8DS",
    "sg:province":"Leicestershire",
    "sg:tags":[
        "pubs",
        "inn"
    ],
    "wof:name":"The Generous Briton",
    "wof:placetype":"venue"
},
  "geometry": {"coordinates":[-1.098999,52.679089],"type":"Point"}
}