{
  "type": "Feature",
  "properties": {
    "addr:full":"8 Atlantic Ct, Sunnyside Rd Woolacombe Devon EX34 7DG",
    "addr:housenumber":"8",
    "addr:postcode":"ex34 7dg",
    "addr:street":"Atlantic Ct Sunnyside Rd",
    "iso:country":"GB",
    "sg:address":"8 Atlantic Ct, Sunnyside Rd",
    "sg:city":"Woolacombe",
    "sg:classifiers":[
        {
            "category":"Building & Trades",
            "subcategory":"Construction",
            "type":"Services"
        }
    ],
    "sg:phone":"+44 1271 870524",
    "sg:postcode":"EX34 7DG",
    "sg:province":"Devon",
    "sg:tags":[
        "builder"
    ],
    "wof:name":"R & P Jaggers",
    "wof:placetype":"venue"
},
  "geometry": {"coordinates":[-4.206484,51.172867],"type":"Point"}
}