{
  "type": "Feature",
  "properties": {
    "iso:country":"GB",
    "sg:address":"3a West Street",
    "sg:city":"Havant",
    "sg:classifiers":[
        {
            "category":"Farming",
            "subcategory":"Fish & Marine Products",
            "type":"Manufacturing & Wholesale Goods"
        },
        {
            "category":"Food & Beverages",
            "subcategory":"Meat & Fish",
            "type":"Retail Goods"
        }
    ],
    "sg:phone":"+44 23 9248 3147",
    "sg:postcode":"PO9 1EH",
    "sg:province":"Hampshire",
    "sg:tags":[
        "fishmonger",
        "butcher"
    ],
    "wof:name":"D Tallant",
    "wof:placetype":"venue"
},
  "geometry": {"coordinates":[-0.98208,50.851288],"type":"Point"}
}