{
  "type": "Feature",
  "properties": {
    "addr:full":"109 Fenchurch Street London Greater London EC3M 5JJ",
    "addr:housenumber":"109",
    "addr:postcode":"ec3m 5jj",
    "addr:street":"Fenchurch Street",
    "iso:country":"GB",
    "sg:address":"109 Fenchurch Street",
    "sg:city":"London",
    "sg:classifiers":[
        {
            "category":"Professional",
            "subcategory":"Printing & Photocopies",
            "type":"Services"
        }
    ],
    "sg:phone":"+44 20 7480 5717",
    "sg:postcode":"EC3M 5JJ",
    "sg:province":"Greater London",
    "sg:tags":[
        "duplicating",
        "copying"
    ],
    "wof:name":"The Color Co.",
    "wof:placetype":"venue"
},
  "geometry": {"coordinates":[-0.0796469972,51.5123558044],"type":"Point"}
}