{
  "type": "Feature",
  "properties": {
    "addr:full":"43 High St Bedford Bedfordshire MK40 1RY",
    "addr:housenumber":"43",
    "addr:postcode":"mk40 1ry",
    "addr:street":"High St",
    "iso:country":"GB",
    "sg:address":"43 High St",
    "sg:city":"Bedford",
    "sg:classifiers":[
        {
            "category":"Shopping",
            "subcategory":"Bicycles & Sporting Goods",
            "type":"Retail Goods"
        }
    ],
    "sg:postcode":"MK40 1RY",
    "sg:province":"Bedfordshire",
    "sg:tags":[
        "equipment",
        "camping"
    ],
    "wof:name":"Milletts (Camping & Countrywear) Ltd",
    "wof:placetype":"venue"
},
  "geometry": {"coordinates":[-0.4661979973,52.1361503601],"type":"Point"}
}