{
  "type": "Feature",
  "properties": {
    "addr:full":"28 The Droveway Hove East Sussex BN3 6LE",
    "addr:housenumber":"28",
    "addr:postcode":"bn3 6le",
    "addr:street":"The Droveway Hove",
    "iso:country":"GB",
    "sg:address":"28 The Droveway",
    "sg:city":"Hove",
    "sg:classifiers":[
        {
            "category":"Manufacturing",
            "subcategory":"Printing",
            "type":"Manufacturing & Wholesale Goods"
        }
    ],
    "sg:phone":"+44 1273 563318",
    "sg:postcode":"BN3 6LE",
    "sg:province":"East Sussex",
    "sg:tags":[
        "bookbinder"
    ],
    "wof:name":"Dunn-coleman N",
    "wof:placetype":"venue"
},
  "geometry": {"coordinates":[-0.1631930023,50.8418807983],"type":"Point"}
}