{
  "type": "Feature",
  "properties": {
    "addr:full":"Bellcrag Works, Dalsholm Rd Glasgow Glasgow City G20 0TB",
    "addr:postcode":"g20 0tb",
    "addr:street":"Dalsholm Rd",
    "iso:country":"GB",
    "sg:address":"Bellcrag Works, Dalsholm Rd",
    "sg:city":"Glasgow",
    "sg:classifiers":[
        {
            "category":"Building & Trades",
            "subcategory":"Construction",
            "type":"Services"
        }
    ],
    "sg:phone":"+44 141 945 0222",
    "sg:postcode":"G20 0TB",
    "sg:province":"Glasgow City",
    "sg:tags":[
        "builder"
    ],
    "wof:name":"Skillbase",
    "wof:placetype":"venue"
},
  "geometry": {"coordinates":[-4.31022,55.893959],"type":"Point"}
}