{
  "type": "Feature",
  "properties": {
    "iso:country":"GB",
    "sg:address":"23 Holland Rd, Peverell",
    "sg:city":"Plymouth",
    "sg:classifiers":[
        {
            "category":"Home & Garden",
            "subcategory":"Carpets & Floor Coverings",
            "type":"Retail Goods"
        }
    ],
    "sg:phone":"+44 1752 673015",
    "sg:postcode":"PL3 4PQ",
    "sg:province":"Devon",
    "sg:tags":[
        "cleaner",
        "upholstery"
    ],
    "wof:name":"Wall-To-wall",
    "wof:placetype":"venue"
},
  "geometry": {"coordinates":[-4.137722,50.389484],"type":"Point"}
}