{
  "type": "Feature",
  "properties": {
    "iso:country":"GB",
    "sg:address":"217 West Street",
    "sg:city":"Fareham",
    "sg:classifiers":[
        {
            "category":"Professional",
            "subcategory":"Accounting & Tax Preparation",
            "type":"Services"
        }
    ],
    "sg:phone":"+44 1329 220554",
    "sg:postcode":"PO16 0ET",
    "sg:province":"Hampshire",
    "sg:tags":[
        "accountant"
    ],
    "wof:name":"Donnelly Hamilton Brent",
    "wof:placetype":"venue"
},
  "geometry": {"coordinates":[-1.187447,50.852722],"type":"Point"}
}