{
  "type": "Feature",
  "properties": {
    "addr:full":"91 Watling Street, Bridgtown Cannock Staffordshire WS11 3BG",
    "addr:housenumber":"91",
    "addr:postcode":"ws11 3bg",
    "addr:street":"Watling Street",
    "iso:country":"GB",
    "sg:address":"91 Watling Street, Bridgtown",
    "sg:city":"Cannock",
    "sg:classifiers":[
        {
            "category":"Building & Trades",
            "subcategory":"Construction",
            "type":"Services"
        }
    ],
    "sg:phone":"+44 1543 573153",
    "sg:postcode":"WS11 3BG",
    "sg:province":"Staffordshire",
    "sg:tags":[
        "builder"
    ],
    "wof:name":"Wren Design & Build Ltd.",
    "wof:placetype":"venue"
},
  "geometry": {"coordinates":[-2.031934,52.675011],"type":"Point"}
}