{
  "type": "Feature",
  "properties": {
    "iso:country":"GB",
    "sg:address":"20 Eastgate",
    "sg:city":"Louth",
    "sg:classifiers":[
        {
            "category":"Professional",
            "type":"Services"
        }
    ],
    "sg:phone":"+44 1472 750000",
    "sg:postcode":"LN11 9NE",
    "sg:province":"Lincolnshire",
    "sg:tags":[
        "directory",
        "pub"
    ],
    "wof:name":"P Capital Design",
    "wof:placetype":"venue"
},
  "geometry": {"coordinates":[-0.006562,53.366749],"type":"Point"}
}