{
  "type": "Feature",
  "properties": {
    "iso:country":"GB",
    "sg:address":"Ashburton Road West, Trafford Park",
    "sg:city":"Manchester",
    "sg:classifiers":[
        {
            "category":"Wholesale",
            "subcategory":"Chemicals & Plastics",
            "type":"Manufacturing & Wholesale Goods"
        }
    ],
    "sg:phone":"+44 161 876 5673",
    "sg:postcode":"M17 1TD",
    "sg:province":"Cheshire",
    "sg:tags":[
        "product",
        "allied"
    ],
    "wof:name":"Polartech Ltd.",
    "wof:placetype":"venue"
},
  "geometry": {"coordinates":[-2.343575,53.473862],"type":"Point"}
}