{
  "type": "Feature",
  "properties": {
    "iso:country":"GB",
    "sg:address":"30/32 High Street",
    "sg:city":"Fochabers",
    "sg:classifiers":[
        {
            "category":"Retail",
            "subcategory":"Auto Repair",
            "type":"Services"
        }
    ],
    "sg:phone":"+44 1343 820258",
    "sg:postcode":"IV32 7DX",
    "sg:province":"Moray",
    "sg:tags":[
        "modification",
        "garage"
    ],
    "wof:name":"W J Mitchell (Investments) Ltd.",
    "wof:placetype":"venue"
},
  "geometry": {"coordinates":[-3.0941,57.613338],"type":"Point"}
}