{
  "type": "Feature",
  "properties": {
    "iso:country":"GB",
    "sg:address":"Stock Road",
    "sg:city":"Billericay",
    "sg:classifiers":[
        {
            "category":"Education",
            "subcategory":"Vocational School",
            "type":"Public Place"
        },
        {
            "category":"Education",
            "subcategory":"School",
            "type":"Public Place"
        }
    ],
    "sg:phone":"+44 1277 623171",
    "sg:postcode":"CM12 0RT",
    "sg:province":"Essex",
    "sg:tags":[
        "evening",
        "local",
        "class",
        "authority"
    ],
    "wof:name":"Mayflower County High School",
    "wof:placetype":"venue"
},
  "geometry": {"coordinates":[0.432441,51.644135],"type":"Point"}
}