{
  "type": "Feature",
  "properties": {
    "addr:full":"17 Hazelwood, Silverstone Towcester Buckinghamshire NN12 8TX",
    "addr:housenumber":"17",
    "addr:postcode":"nn12 8tx",
    "addr:street":"Hazelwood Silverstone",
    "iso:country":"GB",
    "sg:address":"17 Hazelwood, Silverstone",
    "sg:city":"Towcester",
    "sg:classifiers":[
        {
            "category":"Professional",
            "subcategory":"Accounting & Tax Preparation",
            "type":"Services"
        }
    ],
    "sg:phone":"+44 1327 858842",
    "sg:postcode":"NN12 8TX",
    "sg:province":"Buckinghamshire",
    "sg:tags":[
        "accountant"
    ],
    "wof:name":"D.J Smith Book-keeping",
    "wof:placetype":"venue"
},
  "geometry": {"coordinates":[-1.0347310305,52.0899276733],"type":"Point"}
}