{
  "type": "Feature",
  "properties": {
    "iso:country":"GB",
    "sg:address":"78 Eastham Village Road",
    "sg:city":"Wirral",
    "sg:classifiers":[
        {
            "category":"Food & Beverages",
            "subcategory":"Fruits & Vegetables",
            "type":"Retail Goods"
        }
    ],
    "sg:phone":"+44 151 327 1577",
    "sg:postcode":"CH62 0AW",
    "sg:province":"Cheshire",
    "sg:tags":[
        "greengrocer"
    ],
    "wof:name":"Fergies",
    "wof:placetype":"venue"
},
  "geometry": {"coordinates":[-2.9609680176,53.3143157959],"type":"Point"}
}