{
  "type": "Feature",
  "properties": {
    "addr:full":"2 Wilfred Street Carlisle Cumbria CA1 1PQ",
    "addr:housenumber":"2",
    "addr:postcode":"ca1 1pq",
    "addr:street":"Wilfred Street",
    "iso:country":"GB",
    "sg:address":"2 Wilfred Street",
    "sg:city":"Carlisle",
    "sg:classifiers":[
        {
            "category":"Restaurant",
            "type":"Food & Drink"
        }
    ],
    "sg:phone":"+44 1228 599866",
    "sg:postcode":"CA1 1PQ",
    "sg:province":"Cumbria",
    "sg:tags":[
        "indian"
    ],
    "wof:name":"Cassia",
    "wof:placetype":"venue"
},
  "geometry": {"coordinates":[-2.928919,54.892399],"type":"Point"}
}