{
  "type": "Feature",
  "properties": {
    "addr:full":"13 Lincoln Avenue Thornton-cleveleys Lancashire FY5 2DT",
    "addr:housenumber":"13",
    "addr:postcode":"fy5 2dt",
    "addr:street":"Lincoln Avenue",
    "iso:country":"GB",
    "sg:address":"13 Lincoln Avenue",
    "sg:city":"Thornton-cleveleys",
    "sg:classifiers":[
        {
            "category":"Professional",
            "subcategory":"Printing & Photocopies",
            "type":"Services"
        }
    ],
    "sg:postcode":"FY5 2DT",
    "sg:province":"Lancashire",
    "sg:tags":[
        "engraving"
    ],
    "wof:name":"Engraving Services",
    "wof:placetype":"venue"
},
  "geometry": {"coordinates":[-3.033935,53.882301],"type":"Point"}
}