{
  "type": "Feature",
  "properties": {
    "addr:full":"25 Beaufort Grn, Park North Swindon Wiltshire SN3 2AE",
    "addr:housenumber":"25",
    "addr:postcode":"sn3 2ae",
    "addr:street":"Beaufort Grn Park North",
    "iso:country":"GB",
    "sg:address":"25 Beaufort Grn, Park North",
    "sg:city":"Swindon",
    "sg:classifiers":[
        {
            "category":"Professional",
            "subcategory":"Art Services",
            "type":"Services"
        },
        {
            "category":"Building & Trades",
            "subcategory":"Construction",
            "type":"Services"
        }
    ],
    "sg:phone":"+44 1793 642461",
    "sg:postcode":"SN3 2AE",
    "sg:province":"Wiltshire",
    "sg:tags":[
        "decorator",
        "painter"
    ],
    "wof:name":"Harris Decorating",
    "wof:placetype":"venue"
},
  "geometry": {"coordinates":[-1.7448990345,51.5544548035],"type":"Point"}
}