{
  "type": "Feature",
  "properties": {
    "addr:full":"27 Dudley Street Grimsby Lincolnshire DN31 2AW",
    "addr:housenumber":"27",
    "addr:postcode":"dn31 2aw",
    "addr:street":"Dudley Street",
    "iso:country":"GB",
    "sg:address":"27 Dudley Street",
    "sg:city":"Grimsby",
    "sg:classifiers":[
        {
            "category":"Health Services",
            "subcategory":"Dentist",
            "type":"Services"
        }
    ],
    "sg:phone":"+44 1472 320775",
    "sg:postcode":"DN31 2AW",
    "sg:province":"Lincolnshire",
    "wof:name":"Cottingham & Hoyle",
    "wof:placetype":"venue"
},
  "geometry": {"coordinates":[-0.095526,53.563519],"type":"Point"}
}