{
  "type": "Feature",
  "properties": {
    "addr:full":"Independent House, Independent Business Park, Imberhorne Lane East Grinstead East Sussex RH19 1TU",
    "addr:postcode":"rh19 1tu",
    "addr:street":"Imberhorne Lane",
    "iso:country":"GB",
    "sg:address":"Independent House, Independent Business Park, Imberhorne Lane",
    "sg:city":"East Grinstead",
    "sg:classifiers":[
        {
            "category":"Professional",
            "subcategory":"Management & Consulting",
            "type":"Services"
        },
        {
            "category":"Manufacturing",
            "subcategory":"Building Materials",
            "type":"Manufacturing & Wholesale Goods"
        }
    ],
    "sg:phone":"+44 1342 312714",
    "sg:postcode":"RH19 1TU",
    "sg:province":"East Sussex",
    "sg:tags":[
        "extrusion",
        "holding",
        "activity"
    ],
    "wof:name":"Marsdale Plastics",
    "wof:placetype":"venue"
},
  "geometry": {"coordinates":[-0.0075679999,51.1239814758],"type":"Point"}
}