{
  "type": "Feature",
  "properties": {
    "iso:country":"GB",
    "sg:address":"West End Road, Norton",
    "sg:city":"Doncaster",
    "sg:classifiers":[
        {
            "category":"Organizations",
            "subcategory":"Community Association",
            "type":"Services"
        },
        {
            "category":"Organizations",
            "subcategory":"Membership Organization",
            "type":"Services"
        }
    ],
    "sg:phone":"+44 1302 709889",
    "sg:postcode":"DN6 9DH",
    "sg:province":"North Yorkshire",
    "sg:tags":[
        "club",
        "social"
    ],
    "wof:name":"Norton Coronation Working Mens Club",
    "wof:placetype":"venue"
},
  "geometry": {"coordinates":[-1.1705240011,53.632434845],"type":"Point"}
}