{
  "type": "Feature",
  "properties": {
    "addr:full":"103 North Street Martock Somerset TA12 6EJ",
    "addr:housenumber":"103",
    "addr:postcode":"ta12 6ej",
    "addr:street":"North Street",
    "iso:country":"GB",
    "sg:address":"103 North Street",
    "sg:city":"Martock",
    "sg:classifiers":[
        {
            "category":"Personal",
            "subcategory":"Beauty Salon",
            "type":"Services"
        }
    ],
    "sg:phone":"+44 1935 825134",
    "sg:postcode":"TA12 6EJ",
    "sg:province":"Somerset",
    "sg:tags":[
        "unisex",
        "hairdresser"
    ],
    "wof:name":"Zoricas Hair & Beauty Concept",
    "wof:placetype":"venue"
},
  "geometry": {"coordinates":[-2.76685,50.975037],"type":"Point"}
}