{
  "type": "Feature",
  "properties": {
    "addr:full":"Highfield House, Royds Lane Leeds West Yorkshire LS12 6DU",
    "addr:postcode":"ls12 6du",
    "addr:street":"Royds Lane",
    "iso:country":"GB",
    "sg:address":"Highfield House, Royds Lane",
    "sg:city":"Leeds",
    "sg:classifiers":[
        {
            "category":"Shopping",
            "subcategory":"Computers & Home Electronics",
            "type":"Retail Goods"
        }
    ],
    "sg:phone":"+44 113 263 1535",
    "sg:postcode":"LS12 6DU",
    "sg:province":"West Yorkshire",
    "wof:name":"Ronald D Rawcliffe Ltd.",
    "wof:placetype":"venue"
},
  "geometry": {"coordinates":[-1.5908340216,53.7815818787],"type":"Point"}
}