{
  "type": "Feature",
  "properties": {
    "addr:full":"21 High Street Bracknell Berkshire RG12 1DL",
    "addr:housenumber":"21",
    "addr:postcode":"rg12 1dl",
    "addr:street":"High Street",
    "iso:country":"GB",
    "sg:address":"21 High Street",
    "sg:city":"Bracknell",
    "sg:classifiers":[
        {
            "category":"Professional",
            "type":"Services"
        },
        {
            "category":"Fast Food",
            "type":"Food & Drink"
        }
    ],
    "sg:phone":"+44 1344 305505",
    "sg:postcode":"RG12 1DL",
    "sg:province":"Berkshire",
    "sg:tags":[
        "take",
        "away",
        "meal",
        "outlet",
        "caterer"
    ],
    "wof:name":"The Classic Sandwich & Savoury Co",
    "wof:placetype":"venue"
},
  "geometry": {"coordinates":[-0.751599,51.416882],"type":"Point"}
}