{
  "type": "Feature",
  "properties": {
    "addr:full":"Harmsworth House, 13-15 Bouverie Street London Greater London EC4Y 8DP",
    "addr:housenumber":"13-15",
    "addr:postcode":"ec4y 8dp",
    "addr:street":"Bouverie Street",
    "iso:country":"GB",
    "sg:address":"Harmsworth House, 13-15 Bouverie Street",
    "sg:city":"London",
    "sg:classifiers":[
        {
            "category":"Organizations",
            "subcategory":"Non-profit Organization",
            "type":"Services"
        }
    ],
    "sg:phone":"+44 870 333 0123",
    "sg:postcode":"EC4Y 8DP",
    "sg:province":"Greater London",
    "sg:tags":[
        "organisation",
        "voluntary",
        "charity"
    ],
    "wof:name":"The Charity Commission",
    "wof:placetype":"venue"
},
  "geometry": {"coordinates":[-0.0793500021,51.562877655],"type":"Point"}
}