{
  "type": "Feature",
  "properties": {
    "addr:full":"9 Westlecot Road, Old Town Swindon Wiltshire SN1 4EZ",
    "addr:housenumber":"9",
    "addr:postcode":"sn1 4ez",
    "addr:street":"Westlecot Road",
    "iso:country":"GB",
    "sg:address":"9 Westlecot Road, Old Town",
    "sg:city":"Swindon",
    "sg:classifiers":[
        {
            "category":"Professional",
            "subcategory":"Computer Services",
            "type":"Services"
        }
    ],
    "sg:postcode":"SN1 4EZ",
    "sg:province":"Wiltshire",
    "sg:tags":[
        "system",
        "software"
    ],
    "wof:name":"Amos Ltd.",
    "wof:placetype":"venue"
},
  "geometry": {"coordinates":[-1.781279,51.547871],"type":"Point"}
}