{
  "type": "Feature",
  "properties": {
    "addr:full":"6-7 Slate Street, Morriston Swansea Swansea SA6 8AY",
    "addr:housenumber":"6-7",
    "addr:postcode":"sa6 8ay",
    "addr:street":"Slate Street",
    "iso:country":"GB",
    "sg:address":"6-7 Slate Street, Morriston",
    "sg:city":"Swansea",
    "sg:classifiers":[
        {
            "category":"Travel",
            "subcategory":"Hostel",
            "type":"Entertainment"
        }
    ],
    "sg:postcode":"SA6 8AY",
    "sg:province":"Swansea",
    "wof:name":"Family Wish Project",
    "wof:placetype":"venue"
},
  "geometry": {"coordinates":[-3.926363,51.664246],"type":"Point"}
}