{
  "type": "Feature",
  "properties": {
    "addr:full":"Unit 4 Mayflower Close, Chandlers Ford Southampton Hampshire SO53 4AR",
    "addr:housenumber":"unit 4",
    "addr:postcode":"so53 4ar",
    "addr:street":"Mayflower Close Chandlers",
    "iso:country":"GB",
    "sg:address":"Unit 4 Mayflower Close, Chandlers Ford",
    "sg:city":"Southampton",
    "sg:classifiers":[
        {
            "category":"Wholesale",
            "subcategory":"Medical Equipment & Supplies",
            "type":"Manufacturing & Wholesale Goods"
        }
    ],
    "sg:phone":"+44 23 8027 4123",
    "sg:postcode":"SO53 4AR",
    "sg:province":"Hampshire",
    "sg:tags":[
        "lubricating"
    ],
    "wof:name":"Mayflower (Uk)",
    "wof:placetype":"venue"
},
  "geometry": {"coordinates":[-1.395442009,50.982219696],"type":"Point"}
}