{
  "type": "Feature",
  "properties": {
    "addr:full":"4-10 Pechell St, Ashton-on-ribble Preston Lancashire PR2 2RN",
    "addr:housenumber":"4-10",
    "addr:postcode":"pr2 2rn",
    "addr:street":"Pechell St",
    "iso:country":"GB",
    "sg:address":"4-10 Pechell St, Ashton-on-ribble",
    "sg:city":"Preston",
    "sg:classifiers":[
        {
            "category":"Manufacturing",
            "subcategory":"Tools & Machinery",
            "type":"Manufacturing & Wholesale Goods"
        }
    ],
    "sg:postcode":"PR2 2RN",
    "sg:province":"Lancashire",
    "wof:name":"G & B Machine Tool Systems Ltd",
    "wof:placetype":"venue"
},
  "geometry": {"coordinates":[-2.722487,53.765213],"type":"Point"}
}