{
  "type": "Feature",
  "properties": {
    "iso:country":"GB",
    "sg:address":"Nutholm Farm",
    "sg:city":"Lockerbie",
    "sg:classifiers":[
        {
            "category":"Farming",
            "subcategory":"Dairy Farm",
            "type":"Manufacturing & Wholesale Goods"
        }
    ],
    "sg:phone":"+44 1576 510229",
    "sg:postcode":"DG11 1DB",
    "sg:province":"Dumfries and Galloway",
    "wof:name":"W Shanks",
    "wof:placetype":"venue"
},
  "geometry": {"coordinates":[-3.420439,55.12104],"type":"Point"}
}