{
  "type": "Feature",
  "properties": {
    "addr:full":"Davies Lane London Greater London E11 3DR",
    "addr:postcode":"e11 3dr",
    "addr:street":"Davies Lane",
    "iso:country":"GB",
    "sg:address":"Davies Lane",
    "sg:city":"London",
    "sg:classifiers":[
        {
            "category":"Education",
            "subcategory":"School",
            "type":"Public Place"
        },
        {
            "category":"Community Center",
            "subcategory":"Youth",
            "type":"Public Place"
        }
    ],
    "sg:phone":"+44 20 8539 5469",
    "sg:postcode":"E11 3DR",
    "sg:province":"Greater London",
    "sg:tags":[
        "organisation",
        "local",
        "authority",
        "centre"
    ],
    "wof:name":"LONDON BOROUGH OF WALTHAM FOREST",
    "wof:placetype":"venue"
},
  "geometry": {"coordinates":[0.012201,51.5643005371],"type":"Point"}
}