{
  "type": "Feature",
  "properties": {
    "iso:country":"GB",
    "sg:address":"120 Morning Lane",
    "sg:city":"London",
    "sg:classifiers":[
        {
            "category":"Personal",
            "subcategory":"Beauty Salon",
            "type":"Services"
        }
    ],
    "sg:postcode":"E9 6LH",
    "sg:province":"Greater London",
    "sg:tags":[
        "unisex",
        "hairdresser"
    ],
    "wof:name":"Aries Barbers",
    "wof:placetype":"venue"
},
  "geometry": {"coordinates":[-0.050443,51.547016],"type":"Point"}
}