{
  "type": "Feature",
  "properties": {
    "iso:country":"GB",
    "sg:address":"Gilnow Mill, Spa Road",
    "sg:city":"Bolton",
    "sg:classifiers":[
        {
            "category":"Shopping",
            "subcategory":"Gifts & Souvenirs",
            "type":"Retail Goods"
        }
    ],
    "sg:postcode":"BL1 4LF",
    "sg:province":"Lancashire",
    "sg:tags":[
        "greeting",
        "card"
    ],
    "wof:name":"Carol Vosper",
    "wof:placetype":"venue"
},
  "geometry": {"coordinates":[-2.444149,53.576481],"type":"Point"}
}