{
  "type": "Feature",
  "properties": {
    "iso:country":"GB",
    "sg:address":"11 Wood Street",
    "sg:city":"Lytham St Annes",
    "sg:classifiers":[
        {
            "category":"Professional",
            "subcategory":"Engineering",
            "type":"Services"
        },
        {
            "category":"Building & Trades",
            "subcategory":"Electrical",
            "type":"Services"
        }
    ],
    "sg:phone":"+44 1253 724311",
    "sg:postcode":"FY8 1QS",
    "sg:province":"Lancashire",
    "sg:tags":[
        "engineer",
        "electrician",
        "contractor"
    ],
    "wof:name":"FRED STONES & SON LTD",
    "wof:placetype":"venue"
},
  "geometry": {"coordinates":[-3.028436,53.751335],"type":"Point"}
}