{
  "type": "Feature",
  "properties": {
    "addr:full":"34 Southey Lane, Kingskerswell Newton Abbot Devon TQ12 5JG",
    "addr:housenumber":"34",
    "addr:postcode":"tq12 5jg",
    "addr:street":"Southey Lane",
    "iso:country":"GB",
    "sg:address":"34 Southey Lane, Kingskerswell",
    "sg:city":"Newton Abbot",
    "sg:classifiers":[
        {
            "category":"Professional",
            "subcategory":"Management & Consulting",
            "type":"Services"
        }
    ],
    "sg:postcode":"TQ12 5JG",
    "sg:province":"Devon",
    "sg:tags":[
        "consultant",
        "specialist"
    ],
    "wof:name":"Joanne Rawcliffe",
    "wof:placetype":"venue"
},
  "geometry": {"coordinates":[-3.575304985,50.4940071106],"type":"Point"}
}