{
  "type": "Feature",
  "properties": {
    "addr:full":"Stall 116-117, St John Market Liverpool Merseyside L1 1NP",
    "addr:housenumber":"116-117",
    "addr:postcode":"l1 1np",
    "addr:street":"St",
    "iso:country":"GB",
    "sg:address":"Stall 116-117, St John Market",
    "sg:city":"Liverpool",
    "sg:classifiers":[
        {
            "category":"Home & Garden",
            "subcategory":"Home Furnishings",
            "type":"Retail Goods"
        }
    ],
    "sg:phone":"+44 151 709 5834",
    "sg:postcode":"L1 1NP",
    "sg:province":"Merseyside",
    "sg:tags":[
        "beds",
        "bedding",
        "blanket"
    ],
    "wof:name":"St.Johns Bedding & Curtains",
    "wof:placetype":"venue"
},
  "geometry": {"coordinates":[-2.9784810543,53.4097747803],"type":"Point"}
}