{
  "type": "Feature",
  "properties": {
    "addr:full":"3-5 Wentworth Street London Greater London E1 7TB",
    "addr:housenumber":"3-5",
    "addr:postcode":"e1 7tb",
    "addr:street":"Wentworth Street",
    "iso:country":"GB",
    "sg:address":"3-5 Wentworth Street",
    "sg:city":"London",
    "sg:classifiers":[
        {
            "category":"Shopping",
            "subcategory":"Luggage & Leather Goods",
            "type":"Retail Goods"
        }
    ],
    "sg:phone":"+44 20 7247 9681",
    "sg:postcode":"E1 7TB",
    "sg:province":"Greater London",
    "wof:name":"Rose Leatherwear Ltd.",
    "wof:placetype":"venue"
},
  "geometry": {"coordinates":[-0.0763610005,51.5163764954],"type":"Point"}
}