{
  "type": "Feature",
  "properties": {
    "addr:full":"62 Albert Rd Southsea Hampshire PO5 2SL",
    "addr:housenumber":"62",
    "addr:postcode":"po5 2sl",
    "addr:street":"Albert Rd",
    "iso:country":"GB",
    "sg:address":"62 Albert Rd",
    "sg:city":"Southsea",
    "sg:classifiers":[
        {
            "category":"Shopping",
            "subcategory":"Music",
            "type":"Retail Goods"
        }
    ],
    "sg:phone":"+44 23 9279 6066",
    "sg:postcode":"PO5 2SL",
    "sg:province":"Hampshire",
    "sg:tags":[
        "record",
        "tape",
        "cd"
    ],
    "wof:name":"Underground Records",
    "wof:placetype":"venue"
},
  "geometry": {"coordinates":[-1.079782,50.786831],"type":"Point"}
}