{
  "type": "Feature",
  "properties": {
    "addr:full":"59 Albert Rd Tamworth Staffordshire B79 7JN",
    "addr:housenumber":"59",
    "addr:postcode":"b79 7jn",
    "addr:street":"Albert Rd",
    "iso:country":"GB",
    "sg:address":"59 Albert Rd",
    "sg:city":"Tamworth",
    "sg:classifiers":[
        {
            "category":"Banks & Credit Unions",
            "subcategory":"Bank",
            "type":"Services"
        }
    ],
    "sg:postcode":"B79 7JN",
    "sg:province":"Staffordshire",
    "sg:tags":[
        "broker",
        "mortgage"
    ],
    "wof:name":"Main Event Mortgages Ltd",
    "wof:placetype":"venue"
},
  "geometry": {"coordinates":[-1.68818295,52.6364860535],"type":"Point"}
}