{
  "type": "Feature",
  "properties": {
    "iso:country":"GB",
    "sg:address":", Dinas Dinlle",
    "sg:city":"Caernarfon",
    "sg:classifiers":[
        {
            "category":"Restaurant",
            "type":"Food & Drink"
        }
    ],
    "sg:phone":"+44 1286 830929",
    "sg:postcode":"LL54 5TW",
    "sg:province":"Gwynedd",
    "wof:name":"The Surfer",
    "wof:placetype":"venue"
},
  "geometry": {"coordinates":[-4.2782378197,53.1030006409],"type":"Point"}
}