{
  "type": "Feature",
  "properties": {
    "iso:country":"GB",
    "sg:address":"2 New Road",
    "sg:city":"Southampton",
    "sg:classifiers":[
        {
            "category":"Real Estate",
            "subcategory":"Developer",
            "type":"Services"
        }
    ],
    "sg:phone":"+44 23 8063 6708",
    "sg:postcode":"SO14 0AA",
    "sg:province":"Hampshire",
    "sg:tags":[
        "property"
    ],
    "wof:name":"Hull Hampshire Estates Services Ltd.",
    "wof:placetype":"venue"
},
  "geometry": {"coordinates":[-1.401202,50.906982],"type":"Point"}
}