{
  "type": "Feature",
  "properties": {
    "addr:full":"2a Great Gays Fareham Hampshire PO14 3JU",
    "addr:housenumber":"2a",
    "addr:postcode":"po14 3ju",
    "addr:street":"Great Gays",
    "iso:country":"GB",
    "sg:address":"2a Great Gays",
    "sg:city":"Fareham",
    "sg:classifiers":[
        {
            "category":"Building & Trades",
            "subcategory":"Construction",
            "type":"Services"
        }
    ],
    "sg:postcode":"PO14 3JU",
    "sg:province":"Hampshire",
    "sg:tags":[
        "builder"
    ],
    "wof:name":"Knights",
    "wof:placetype":"venue"
},
  "geometry": {"coordinates":[-1.23445,50.819012],"type":"Point"}
}