{
  "type": "Feature",
  "properties": {
    "iso:country":"GB",
    "sg:address":"Unit I, The Loddon Centre",
    "sg:city":"Basingstoke",
    "sg:classifiers":[
        {
            "category":"Manufacturing",
            "subcategory":"Tools & Machinery",
            "type":"Manufacturing & Wholesale Goods"
        },
        {
            "category":"Building & Trades",
            "subcategory":"Construction",
            "type":"Services"
        }
    ],
    "sg:phone":"+44 1256 330441",
    "sg:postcode":"RG24 8FL",
    "sg:province":"Hampshire",
    "sg:tags":[
        "bearing",
        "valve",
        "stockist"
    ],
    "wof:name":"OVENTROP U K LTD",
    "wof:placetype":"venue"
},
  "geometry": {"coordinates":[-1.0639400482,51.278049469],"type":"Point"}
}