{
  "type": "Feature",
  "properties": {
    "addr:full":"1 St Bryde St Glasgow South Lanarkshire G74 4HQ",
    "addr:housenumber":"1",
    "addr:postcode":"g74 4hq",
    "addr:street":"St Bryde St",
    "iso:country":"GB",
    "sg:address":"1 St Bryde St",
    "sg:city":"Glasgow",
    "sg:classifiers":[
        {
            "category":"Professional",
            "type":"Services"
        }
    ],
    "sg:phone":"+44 1355 573090",
    "sg:postcode":"G74 4HQ",
    "sg:province":"South Lanarkshire",
    "sg:tags":[
        "caterer"
    ],
    "wof:name":"Capers",
    "wof:placetype":"venue"
},
  "geometry": {"coordinates":[-4.173189,55.766651],"type":"Point"}
}