{
  "type": "Feature",
  "properties": {
    "iso:country":"GB",
    "sg:address":"68 Great Titchfield Street",
    "sg:city":"London",
    "sg:classifiers":[
        {
            "category":"Bars & Pubs",
            "type":"Food & Drink"
        }
    ],
    "sg:phone":"+44 20 7636 4405",
    "sg:postcode":"W1W 7QL",
    "sg:province":"Greater London",
    "sg:tags":[
        "pubs",
        "inn"
    ],
    "wof:name":"The Kings Arms",
    "wof:placetype":"venue"
},
  "geometry": {"coordinates":[-0.1373790056,51.5187149048],"type":"Point"}
}