{
  "type": "Feature",
  "properties": {
    "iso:country":"GB",
    "sg:address":"27 St Chads Road",
    "sg:city":"Blackpool",
    "sg:classifiers":[
        {
            "category":"Travel",
            "subcategory":"Hotels & Motels",
            "type":"Entertainment"
        }
    ],
    "sg:postcode":"FY1 6BP",
    "sg:province":"Lancashire",
    "sg:tags":[
        "house",
        "self",
        "guest",
        "catering"
    ],
    "wof:name":"Miami Holiday Flats",
    "wof:placetype":"venue"
},
  "geometry": {"coordinates":[-3.053247,53.802711],"type":"Point"}
}