{
  "type": "Feature",
  "properties": {
    "addr:full":"21 Main Street, Farcet Peterborough Cambridgeshire PE7 3AN",
    "addr:housenumber":"21",
    "addr:postcode":"pe7 3an",
    "addr:street":"Main Street",
    "iso:country":"GB",
    "sg:address":"21 Main Street, Farcet",
    "sg:city":"Peterborough",
    "sg:classifiers":[
        {
            "category":"Parking",
            "type":"Transportation"
        }
    ],
    "sg:phone":"+44 1733 245171",
    "sg:postcode":"PE7 3AN",
    "sg:province":"Cambridgeshire",
    "sg:tags":[
        "car",
        "valet"
    ],
    "wof:name":"Pro-Clean Master Valeters",
    "wof:placetype":"venue"
},
  "geometry": {"coordinates":[-0.2274650037,52.5363807678],"type":"Point"}
}