{
  "type": "Feature",
  "properties": {
    "addr:full":"Parkburn Rd Glasgow East Dunbartonshire G65 9DQ",
    "addr:postcode":"g65 9dq",
    "addr:street":"Parkburn Rd",
    "iso:country":"GB",
    "sg:address":"Parkburn Rd",
    "sg:city":"Glasgow",
    "sg:classifiers":[
        {
            "category":"Retail",
            "subcategory":"Funeral Services",
            "type":"Services"
        }
    ],
    "sg:phone":"+44 1236 822158",
    "sg:postcode":"G65 9DQ",
    "sg:province":"East Dunbartonshire",
    "wof:name":"Co-operative Funeral Services",
    "wof:placetype":"venue"
},
  "geometry": {"coordinates":[-4.0571088791,55.9803466797],"type":"Point"}
}