{
  "type": "Feature",
  "properties": {
    "addr:full":"Cathedral Chambers Ripon North Yorkshire HG4 1PA",
    "addr:postcode":"hg4 1pa",
    "iso:country":"GB",
    "sg:address":"Cathedral Chambers",
    "sg:city":"Ripon",
    "sg:classifiers":[
        {
            "category":"Professional",
            "subcategory":"Lawyer & Legal Services",
            "type":"Services"
        }
    ],
    "sg:phone":"+44 1765 605629",
    "sg:postcode":"HG4 1PA",
    "sg:province":"North Yorkshire",
    "sg:tags":[
        "conveyancing"
    ],
    "wof:name":"Tunnard & Co.",
    "wof:placetype":"venue"
},
  "geometry": {"coordinates":[-1.5235790014,54.1367950439],"type":"Point"}
}