{
  "type": "Feature",
  "properties": {
    "iso:country":"GB",
    "sg:address":"38 Crwys Road",
    "sg:city":"Cardiff",
    "sg:classifiers":[
        {
            "category":"Personal",
            "subcategory":"Beauty Salon",
            "type":"Services"
        },
        {
            "category":"Personal",
            "subcategory":"Barber",
            "type":"Services"
        }
    ],
    "sg:phone":"+44 29 2037 3904",
    "sg:postcode":"CF24 4NN",
    "sg:province":"Cardiff",
    "sg:tags":[
        "unisex",
        "hairdresser"
    ],
    "wof:name":"Hair By George",
    "wof:placetype":"venue"
},
  "geometry": {"coordinates":[-3.1765170097,51.4947776794],"type":"Point"}
}