{
  "type": "Feature",
  "properties": {
    "iso:country":"GB",
    "sg:address":"100 Main Street",
    "sg:city":"Coatbridge",
    "sg:classifiers":[
        {
            "category":"Shopping",
            "subcategory":"Clothing, Apparel, & Fashions",
            "type":"Retail Goods"
        }
    ],
    "sg:postcode":"ML5 3BQ",
    "sg:province":"North Lanarkshire",
    "sg:tags":[
        "ladieswear"
    ],
    "wof:name":"Adlib",
    "wof:placetype":"venue"
},
  "geometry": {"coordinates":[-4.022397,55.861202],"type":"Point"}
}