{
  "type": "Feature",
  "properties": {
    "addr:full":"Unit 40 Rassau Indust Est Ebbw Vale Blaenau Gwent NP23 5SD",
    "addr:housenumber":"unit 40",
    "addr:postcode":"np23 5sd",
    "addr:street":"Indust",
    "iso:country":"GB",
    "sg:address":"Unit 40 Rassau Indust Est",
    "sg:city":"Ebbw Vale",
    "sg:classifiers":[
        {
            "category":"Autos & Motor Vehicles",
            "subcategory":"Auto Supplies",
            "type":"Retail Goods"
        }
    ],
    "sg:phone":"+44 1495 308304",
    "sg:postcode":"NP23 5SD",
    "sg:province":"Blaenau Gwent",
    "sg:tags":[
        "transmission",
        "equipment",
        "power"
    ],
    "wof:name":"Hitachi Cable",
    "wof:placetype":"venue"
},
  "geometry": {"coordinates":[-3.2255589962,51.8072357178],"type":"Point"}
}