{
  "type": "Feature",
  "properties": {
    "iso:country":"GB",
    "sg:address":"Bowland Road, Clovenfords",
    "sg:city":"Galashiels",
    "sg:classifiers":[
        {
            "category":"Government",
            "subcategory":"Post Office",
            "type":"Public Place"
        }
    ],
    "sg:phone":"+44 845 722 3344",
    "sg:postcode":"TD1 3ND",
    "sg:province":"Scottish Borders",
    "wof:name":"The Post Office Clovenfords",
    "wof:placetype":"venue"
},
  "geometry": {"coordinates":[-2.878989,55.623287],"type":"Point"}
}