{
  "type": "Feature",
  "properties": {
    "addr:full":"2 Station Bldg(s), Dovemount Hawick Cumbria TD9 7AA",
    "addr:housenumber":"2",
    "addr:postcode":"td9 7aa",
    "addr:street":"Hawick",
    "iso:country":"GB",
    "sg:address":"2 Station Bldg(s), Dovemount",
    "sg:city":"Hawick",
    "sg:classifiers":[
        {
            "category":"Shopping",
            "subcategory":"Photographic Equipment",
            "type":"Retail Goods"
        }
    ],
    "sg:phone":"+44 1450 370523",
    "sg:postcode":"TD9 7AA",
    "sg:province":"Cumbria",
    "wof:name":"Pariss Photographic Studio & Picture Frames",
    "wof:placetype":"venue"
},
  "geometry": {"coordinates":[-2.7875490189,55.4221458435],"type":"Point"}
}