{
  "type": "Feature",
  "properties": {
    "addr:full":"Unit 26 Vulcan Wks, Wargrave Rd Newton-le-willows Cheshire WA12 8RU",
    "addr:housenumber":"unit 26",
    "addr:postcode":"wa12 8ru",
    "addr:street":"Vulcan Wks Wargrave Rd",
    "iso:country":"GB",
    "sg:address":"Unit 26 Vulcan Wks, Wargrave Rd",
    "sg:city":"Newton-le-willows",
    "sg:classifiers":[
        {
            "category":"Building & Trades",
            "subcategory":"Plumbing",
            "type":"Services"
        }
    ],
    "sg:phone":"+44 1925 220891",
    "sg:postcode":"WA12 8RU",
    "sg:province":"Cheshire",
    "sg:tags":[
        "heating"
    ],
    "wof:name":"Boiler Supplies & Installation Ltd",
    "wof:placetype":"venue"
},
  "geometry": {"coordinates":[-2.6342840195,53.4510803223],"type":"Point"}
}