{
  "type": "Feature",
  "properties": {
    "addr:full":"Rockingham House, Aldenham Rd, Bushey Watford Hertfordshire WD2 2LX",
    "addr:postcode":"wd2 2lx",
    "addr:street":"Aldenham Rd",
    "iso:country":"GB",
    "sg:address":"Rockingham House, Aldenham Rd, Bushey",
    "sg:city":"Watford",
    "sg:classifiers":[
        {
            "category":"Retail",
            "subcategory":"Driving School",
            "type":"Services"
        }
    ],
    "sg:phone":"+44 1923 210604",
    "sg:postcode":"WD2 2LX",
    "sg:province":"Hertfordshire",
    "wof:name":"LifeSkill School of Driving",
    "wof:placetype":"venue"
},
  "geometry": {"coordinates":[-0.36307,51.644341],"type":"Point"}
}