{
  "type": "Feature",
  "properties": {
    "addr:full":"Rushton Spencer Macclesfield Cheshire SK11 0QX",
    "addr:postcode":"sk11 0qx",
    "iso:country":"GB",
    "sg:address":"Rushton Spencer",
    "sg:city":"Macclesfield",
    "sg:classifiers":[
        {
            "category":"Freight",
            "type":"Transportation"
        }
    ],
    "sg:phone":"+44 1260 226209",
    "sg:postcode":"SK11 0QX",
    "sg:province":"Cheshire",
    "sg:tags":[
        "haulage",
        "road"
    ],
    "wof:name":"Moss & Lovatt (Milk Carriers) Ltd.",
    "wof:placetype":"venue"
},
  "geometry": {"coordinates":[-2.092769,53.223969],"type":"Point"}
}