{
  "type": "Feature",
  "properties": {
    "addr:full":"7 Brunel Rd Leigh On Sea Essex SS9 5JL",
    "addr:housenumber":"7",
    "addr:postcode":"ss9 5jl",
    "addr:street":"Brunel Rd",
    "iso:country":"GB",
    "sg:address":"7 Brunel Rd",
    "sg:city":"Leigh On Sea",
    "sg:classifiers":[
        {
            "category":"Building & Trades",
            "subcategory":"Construction",
            "type":"Services"
        }
    ],
    "sg:phone":"+44 1702 527026",
    "sg:postcode":"SS9 5JL",
    "sg:province":"Essex",
    "sg:tags":[
        "builder"
    ],
    "wof:name":"Darby Builders",
    "wof:placetype":"venue"
},
  "geometry": {"coordinates":[0.6448349953,51.5700492859],"type":"Point"}
}