{
  "type": "Feature",
  "properties": {
    "addr:full":"Unit 10 Greencroft Industrial Park, Anfield Plain Stanley Durham DH9 7YB",
    "addr:housenumber":"unit 10",
    "addr:postcode":"dh9 7yb",
    "addr:street":"Industrial Park Anfield Plain Stanley",
    "iso:country":"GB",
    "sg:address":"Unit 10 Greencroft Industrial Park, Anfield Plain",
    "sg:city":"Stanley",
    "sg:classifiers":[
        {
            "category":"Professional",
            "subcategory":"Art Services",
            "type":"Services"
        }
    ],
    "sg:phone":"+44 1207 529123",
    "sg:postcode":"DH9 7YB",
    "sg:province":"Durham",
    "sg:tags":[
        "graphic",
        "designer"
    ],
    "wof:name":"Graphic International",
    "wof:placetype":"venue"
},
  "geometry": {"coordinates":[-1.7443039417,54.8511390686],"type":"Point"}
}