{
  "type": "Feature",
  "properties": {
    "addr:full":"T A Centre, Arle Rd Cheltenham Gloucestershire GL51 8JU",
    "addr:postcode":"gl51 8ju",
    "addr:street":"Arle Rd",
    "iso:country":"GB",
    "sg:address":"T A Centre, Arle Rd",
    "sg:city":"Cheltenham",
    "sg:classifiers":[
        {
            "category":"Professional",
            "subcategory":"Employment Agencies",
            "type":"Services"
        }
    ],
    "sg:phone":"+44 1242 251612",
    "sg:postcode":"GL51 8JU",
    "sg:province":"Gloucestershire",
    "sg:tags":[
        "consultant"
    ],
    "wof:name":"Regular Forces Employment Association Ltd",
    "wof:placetype":"venue"
},
  "geometry": {"coordinates":[-2.0931499004,51.9038505554],"type":"Point"}
}