{
  "type": "Feature",
  "properties": {
    "addr:full":"6 The Business Centre, The Street Woodbridge Suffolk IP13 7SA",
    "addr:housenumber":"6",
    "addr:postcode":"ip13 7sa",
    "addr:street":"The;The Street",
    "iso:country":"GB",
    "sg:address":"6 The Business Centre, The Street",
    "sg:city":"Woodbridge",
    "sg:classifiers":[
        {
            "category":"Shopping",
            "subcategory":"Clothing, Apparel, & Fashions",
            "type":"Retail Goods"
        },
        {
            "category":"Professional",
            "type":"Services"
        },
        {
            "category":"Communications",
            "type":"Services"
        }
    ],
    "sg:phone":"+44 1728 685774",
    "sg:postcode":"IP13 7SA",
    "sg:province":"Suffolk",
    "sg:tags":[
        "t-shirt",
        "exhibition",
        "audio-visual"
    ],
    "wof:name":"Doves Communications Ltd",
    "wof:placetype":"venue"
},
  "geometry": {"coordinates":[1.26887,52.221699],"type":"Point"}
}