{
  "type": "Feature",
  "properties": {
    "iso:country":"GB",
    "sg:address":"The Gate House, Knowle Lane",
    "sg:city":"Cranleigh",
    "sg:classifiers":[
        {
            "category":"Professional",
            "subcategory":"Business Services",
            "type":"Services"
        }
    ],
    "sg:phone":"+44 1483 271333",
    "sg:postcode":"GU6 8RD",
    "sg:province":"Surrey",
    "sg:tags":[
        "holding"
    ],
    "wof:name":"Davline Holdings Ltd.",
    "wof:placetype":"venue"
},
  "geometry": {"coordinates":[-0.4906570017,51.1408691406],"type":"Point"}
}