{
  "type": "Feature",
  "properties": {
    "iso:country":"GB",
    "sg:address":"Penhole Yard, Quarry Crescent, Pennygillam Industrial Estate",
    "sg:city":"Launceston",
    "sg:classifiers":[
        {
            "category":"Professional",
            "subcategory":"Business Services",
            "type":"Services"
        }
    ],
    "sg:postcode":"PL15 7ED",
    "sg:province":"Cornwall",
    "sg:tags":[
        "distribution"
    ],
    "wof:name":"D B Distribution",
    "wof:placetype":"venue"
},
  "geometry": {"coordinates":[-4.4105839729,50.5666999817],"type":"Point"}
}