{
  "type": "Feature",
  "properties": {
    "iso:country":"GB",
    "sg:address":"Commodore House, Northwales Business Park",
    "sg:city":"Abergele",
    "sg:classifiers":[
        {
            "category":"Professional",
            "type":"Services"
        },
        {
            "category":"Conference Center",
            "type":"Public Place"
        }
    ],
    "sg:phone":"+44 1745 828400",
    "sg:postcode":"LL22 8LJ",
    "sg:province":"Conwy",
    "sg:tags":[
        "related"
    ],
    "wof:name":"Worldspan International Plc",
    "wof:placetype":"venue"
},
  "geometry": {"coordinates":[-3.581144,53.284355],"type":"Point"}
}