{
  "type": "Feature",
  "properties": {
    "addr:full":"12 Aylesbury Road Doncaster South Yorkshire DN2 6LT",
    "addr:housenumber":"12",
    "addr:postcode":"dn2 6lt",
    "addr:street":"Aylesbury Road",
    "iso:country":"GB",
    "sg:address":"12 Aylesbury Road",
    "sg:city":"Doncaster",
    "sg:classifiers":[
        {
            "category":"Shopping",
            "subcategory":"Pets & Pet Supplies",
            "type":"Retail Goods"
        },
        {
            "category":"Retail",
            "subcategory":"Animal Services",
            "type":"Services"
        }
    ],
    "sg:phone":"+44 1302 344872",
    "sg:postcode":"DN2 6LT",
    "sg:province":"South Yorkshire",
    "wof:name":"Bob Grass",
    "wof:placetype":"venue"
},
  "geometry": {"coordinates":[-1.096817,53.527607],"type":"Point"}
}