{
  "type": "Feature",
  "properties": {
    "addr:full":"22a Farm St West End Hampshire W1X 7RE",
    "addr:housenumber":"22a",
    "addr:postcode":"w1x 7re",
    "addr:street":"Farm St",
    "iso:country":"GB",
    "sg:address":"22a Farm St",
    "sg:city":"West End",
    "sg:classifiers":[
        {
            "category":"Manufacturing",
            "subcategory":"Textiles",
            "type":"Manufacturing & Wholesale Goods"
        }
    ],
    "sg:phone":"+44 20 7493 7661",
    "sg:postcode":"W1X 7RE",
    "sg:province":"Hampshire",
    "sg:tags":[
        "mnfr",
        "rug",
        "carpet"
    ],
    "wof:name":"Barkotex Ltd",
    "wof:placetype":"venue"
},
  "geometry": {"coordinates":[-0.1489890069,51.5089645386],"type":"Point"}
}