{
  "type": "Feature",
  "properties": {
    "iso:country":"GB",
    "sg:address":"52 Birds Avenue",
    "sg:city":"Margate",
    "sg:classifiers":[
        {
            "category":"Recreation",
            "subcategory":"Dog Park",
            "type":"Entertainment"
        },
        {
            "category":"Retail",
            "subcategory":"Animal Services",
            "type":"Services"
        }
    ],
    "sg:phone":"+44 1843 831986",
    "sg:postcode":"CT9 5NE",
    "sg:province":"Kent",
    "sg:tags":[
        "grooming",
        "clipping"
    ],
    "wof:name":"Anne's Dog Grooming Service",
    "wof:placetype":"venue"
},
  "geometry": {"coordinates":[1.358138,51.375576],"type":"Point"}
}