{
  "type": "Feature",
  "properties": {
    "iso:country":"GB",
    "sg:address":"8 Roberts Road",
    "sg:city":"Belvedere",
    "sg:classifiers":[
        {
            "category":"Building & Trades",
            "subcategory":"Construction",
            "type":"Services"
        }
    ],
    "sg:postcode":"DA17 6NP",
    "sg:province":"Kent",
    "sg:tags":[
        "decorator",
        "painter"
    ],
    "wof:name":"Paul Fleming",
    "wof:placetype":"venue"
},
  "geometry": {"coordinates":[0.151329,51.483288],"type":"Point"}
}