{
  "type": "Feature",
  "properties": {
    "addr:full":"5b Loaning Road Edinburgh City of Edinburgh EH7 6JF",
    "addr:housenumber":"5b",
    "addr:postcode":"eh7 6jf",
    "addr:street":"Loaning Road",
    "iso:country":"GB",
    "sg:address":"5b Loaning Road",
    "sg:city":"Edinburgh",
    "sg:classifiers":[
        {
            "category":"Brewery",
            "type":"Food & Drink"
        }
    ],
    "sg:phone":"+44 131 468 6969",
    "sg:postcode":"EH7 6JF",
    "sg:province":"City of Edinburgh",
    "sg:tags":[
        "brewer"
    ],
    "wof:name":"Restalrig Village Brewer Ltd.",
    "wof:placetype":"venue"
},
  "geometry": {"coordinates":[-3.146302,55.960686],"type":"Point"}
}