{
  "type": "Feature",
  "properties": {
    "addr:full":"Stanley Ho, Lowergate Clitheroe Lancashire BB7 1AD",
    "addr:postcode":"bb7 1ad",
    "addr:street":"Lowergate",
    "iso:country":"GB",
    "sg:address":"Stanley Ho, Lowergate",
    "sg:city":"Clitheroe",
    "sg:classifiers":[
        {
            "category":"Banks & Credit Unions",
            "subcategory":"Bureau De Change",
            "type":"Services"
        }
    ],
    "sg:phone":"+44 1200 443334",
    "sg:postcode":"BB7 1AD",
    "sg:province":"Lancashire",
    "sg:tags":[
        "town",
        "consultant",
        "planning"
    ],
    "wof:name":"John Willcock",
    "wof:placetype":"venue"
},
  "geometry": {"coordinates":[-2.391749,53.87278],"type":"Point"}
}