{
  "type": "Feature",
  "properties": {
    "iso:country":"GB",
    "sg:address":"16a Victoria Rd",
    "sg:city":"Exmouth",
    "sg:classifiers":[
        {
            "category":"Shopping",
            "subcategory":"Computers & Home Electronics",
            "type":"Retail Goods"
        }
    ],
    "sg:phone":"+44 1395 272900",
    "sg:postcode":"EX8 1DL",
    "sg:province":"Devon",
    "sg:tags":[
        "consumables"
    ],
    "wof:name":"Kenborne Mail Order",
    "wof:placetype":"venue"
},
  "geometry": {"coordinates":[-3.416388,50.619194],"type":"Point"}
}