{
  "type": "Feature",
  "properties": {
    "addr:full":"49 Edenfield Road, Mobberley Knutsford Cheshire WA16 7HE",
    "addr:housenumber":"49",
    "addr:postcode":"wa16 7he",
    "addr:street":"Edenfield Road",
    "iso:country":"GB",
    "sg:address":"49 Edenfield Road, Mobberley",
    "sg:city":"Knutsford",
    "sg:classifiers":[
        {
            "category":"Building & Trades",
            "subcategory":"Landscaping Services",
            "type":"Services"
        }
    ],
    "sg:postcode":"WA16 7HE",
    "sg:province":"Cheshire",
    "sg:tags":[
        "landscape",
        "contractor"
    ],
    "wof:name":"Wilmslow Garden Landscapes",
    "wof:placetype":"venue"
},
  "geometry": {"coordinates":[-2.3306279182,53.3113708496],"type":"Point"}
}