{
  "type": "Feature",
  "properties": {
    "addr:full":"1 Bank Plain Norwich Norfolk NR2 4TH",
    "addr:housenumber":"1",
    "addr:postcode":"nr2 4th",
    "addr:street":"Bank Plain Norwich Norfolk",
    "iso:country":"GB",
    "sg:address":"1 Bank Plain",
    "sg:city":"Norwich",
    "sg:classifiers":[
        {
            "category":"Banks & Credit Unions",
            "subcategory":"Bank",
            "type":"Services"
        }
    ],
    "sg:phone":"+44 845 603 3610",
    "sg:postcode":"NR2 4TH",
    "sg:province":"Norfolk",
    "wof:name":"Halifax Plc",
    "wof:placetype":"venue"
},
  "geometry": {"coordinates":[1.297845,52.62957],"type":"Point"}
}