{
  "type": "Feature",
  "properties": {
    "iso:country":"GB",
    "sg:address":"Hibernia Way Barton Dock Road, Stretford",
    "sg:city":"Manchester",
    "sg:classifiers":[
        {
            "category":"Home & Garden",
            "subcategory":"Home Furnishings",
            "type":"Retail Goods"
        }
    ],
    "sg:phone":"+44 161 865 8666",
    "sg:postcode":"M32 0XL",
    "sg:province":"Cheshire",
    "sg:tags":[
        "tube",
        "fitting",
        "stockist"
    ],
    "wof:name":"Le Bas Tube Co",
    "wof:placetype":"venue"
},
  "geometry": {"coordinates":[-2.32985,53.461739],"type":"Point"}
}