{
  "type": "Feature",
  "properties": {
    "iso:country":"GB",
    "sg:address":"Rose Green Rd, St George",
    "sg:city":"Bristol",
    "sg:classifiers":[
        {
            "category":"Retail",
            "subcategory":"Storage",
            "type":"Services"
        }
    ],
    "sg:phone":"+44 1452 332290",
    "sg:postcode":"BS5 7UW",
    "sg:province":"City of Bristol",
    "sg:tags":[
        "shelving",
        "system"
    ],
    "wof:name":"Ace Systems",
    "wof:placetype":"venue"
},
  "geometry": {"coordinates":[-2.5470430851,51.4694137573],"type":"Point"}
}