{
  "type": "Feature",
  "properties": {
    "iso:country":"GB",
    "sg:address":"1 St. Leonards Clo",
    "sg:city":"Newton Abbot",
    "sg:classifiers":[
        {
            "category":"Military Area",
            "subcategory":"Air Force Base",
            "type":"Public Place"
        }
    ],
    "sg:phone":"+44 1626 333827",
    "sg:postcode":"TQ12 1JZ",
    "sg:province":"Devon",
    "sg:tags":[
        "taxi",
        "hire",
        "private"
    ],
    "wof:name":"Buckland Taxis",
    "wof:placetype":"venue"
},
  "geometry": {"coordinates":[-3.613627,50.527538],"type":"Point"}
}