{
  "type": "Feature",
  "properties": {
    "addr:full":"Mulberry Cottage Harlow Essex CM17 0PS",
    "addr:postcode":"cm17 0ps",
    "iso:country":"GB",
    "sg:address":"Mulberry Cottage",
    "sg:city":"Harlow",
    "sg:classifiers":[
        {
            "category":"Manufacturing",
            "subcategory":"Rubber & Plastics",
            "type":"Manufacturing & Wholesale Goods"
        }
    ],
    "sg:phone":"+44 1279 731112",
    "sg:postcode":"CM17 0PS",
    "sg:province":"Essex",
    "sg:tags":[
        "product"
    ],
    "wof:name":"Cross Industries Ltd",
    "wof:placetype":"venue"
},
  "geometry": {"coordinates":[0.129519999,51.7834510803],"type":"Point"}
}