{
  "type": "Feature",
  "properties": {
    "addr:full":"91 Airbles Road Motherwell North Lanarkshire ML1 2TJ",
    "addr:housenumber":"91",
    "addr:postcode":"ml1 2tj",
    "addr:street":"Airbles Road",
    "iso:country":"GB",
    "sg:address":"91 Airbles Road",
    "sg:city":"Motherwell",
    "sg:classifiers":[
        {
            "category":"Retail",
            "subcategory":"Auto Repair",
            "type":"Services"
        }
    ],
    "sg:phone":"+44 1698 268705",
    "sg:postcode":"ML1 2TJ",
    "sg:province":"North Lanarkshire",
    "sg:tags":[
        "bodybuilder",
        "repairer"
    ],
    "wof:name":"E Cocozza & Sons Ltd.",
    "wof:placetype":"venue"
},
  "geometry": {"coordinates":[-3.9853999615,55.7827987671],"type":"Point"}
}