{
  "type": "Feature",
  "properties": {
    "addr:full":"298 Upper Street London Greater London N1 2TU",
    "addr:housenumber":"298",
    "addr:postcode":"n1 2tu",
    "addr:street":"Upper Street",
    "iso:country":"GB",
    "sg:address":"298 Upper Street",
    "sg:city":"London",
    "sg:classifiers":[
        {
            "category":"Real Estate",
            "subcategory":"Real Estate Agent",
            "type":"Services"
        }
    ],
    "sg:phone":"+44 20 7359 3636",
    "sg:postcode":"N1 2TU",
    "sg:province":"Greater London",
    "wof:name":"Kinleigh Folkard & Hayward",
    "wof:placetype":"venue"
},
  "geometry": {"coordinates":[-0.1023060009,51.5380630493],"type":"Point"}
}