{
  "type": "Feature",
  "properties": {
    "addr:full":"46 Wilton Avenue Redcar North Yorkshire TS10 5PW",
    "addr:housenumber":"46",
    "addr:postcode":"ts10 5pw",
    "addr:street":"Wilton Avenue",
    "iso:country":"GB",
    "sg:address":"46 Wilton Avenue",
    "sg:city":"Redcar",
    "sg:classifiers":[
        {
            "category":"Shopping",
            "subcategory":"Computers & Home Electronics",
            "type":"Retail Goods"
        }
    ],
    "sg:phone":"+44 1642 474164",
    "sg:postcode":"TS10 5PW",
    "sg:province":"North Yorkshire",
    "sg:tags":[
        "aerial",
        "television",
        "radio"
    ],
    "wof:name":"Cleveland County Aerials",
    "wof:placetype":"venue"
},
  "geometry": {"coordinates":[-1.105025,54.603893],"type":"Point"}
}