{
  "type": "Feature",
  "properties": {
    "iso:country":"GB",
    "sg:address":"11 Tangier Road",
    "sg:city":"Portsmouth",
    "sg:classifiers":[
        {
            "category":"Building & Trades",
            "subcategory":"Construction",
            "type":"Services"
        }
    ],
    "sg:postcode":"PO3 6JG",
    "sg:province":"Hampshire",
    "sg:tags":[
        "builder"
    ],
    "wof:name":"D Hill Builders Ltd",
    "wof:placetype":"venue"
},
  "geometry": {"coordinates":[-1.0627440214,50.8089485168],"type":"Point"}
}