{
  "type": "Feature",
  "properties": {
    "addr:full":"Childrens Residential Unit, Hollybank Ho, Hollybank Cres Stoke-on-trent Staffordshire ST4 5AS",
    "addr:housenumber":"unit",
    "addr:postcode":"st4 5as",
    "addr:street":"Hollybank Cres",
    "iso:country":"GB",
    "sg:address":"Childrens Residential Unit, Hollybank Ho, Hollybank Cres",
    "sg:city":"Stoke-on-trent",
    "sg:classifiers":[
        {
            "category":"Social Services",
            "subcategory":"Child Care",
            "type":"Services"
        },
        {
            "category":"Government",
            "subcategory":"Office",
            "type":"Public Place"
        }
    ],
    "sg:postcode":"ST4 5AS",
    "sg:province":"Staffordshire",
    "sg:tags":[
        "home",
        "local",
        "children's"
    ],
    "wof:name":"Stoke-on-Trent City Council",
    "wof:placetype":"venue"
},
  "geometry": {"coordinates":[-2.1949999332,52.9937400818],"type":"Point"}
}