{
  "type": "Feature",
  "properties": {
    "iso:country":"GB",
    "sg:address":"120-121 Sidwell Street",
    "sg:city":"Exeter",
    "sg:classifiers":[
        {
            "category":"Food & Beverages",
            "subcategory":"Groceries & Convenience Stores",
            "type":"Retail Goods"
        }
    ],
    "sg:postcode":"EX4 6RY",
    "sg:province":"Devon",
    "wof:name":"Exeter Food Store",
    "wof:placetype":"venue"
},
  "geometry": {"coordinates":[-3.5221090317,50.728061676],"type":"Point"}
}