{
  "type": "Feature",
  "properties": {
    "iso:country":"GB",
    "sg:address":"Blackpool Rd",
    "sg:city":"London",
    "sg:classifiers":[
        {
            "category":"Building & Trades",
            "subcategory":"Construction",
            "type":"Services"
        }
    ],
    "sg:postcode":"SE15 3SU",
    "sg:province":"Greater London",
    "sg:tags":[
        "builder"
    ],
    "wof:name":"Webber,Robert Jack,",
    "wof:placetype":"venue"
},
  "geometry": {"coordinates":[-0.0639389977,51.4691390991],"type":"Point"}
}