{
  "type": "Feature",
  "properties": {
    "addr:full":"51 Chudleigh Road Birmingham West Midlands B23 6HG",
    "addr:housenumber":"51",
    "addr:postcode":"b23 6hg",
    "addr:street":"Chudleigh Road",
    "iso:country":"GB",
    "sg:address":"51 Chudleigh Road",
    "sg:city":"Birmingham",
    "sg:classifiers":[
        {
            "category":"Building & Trades",
            "subcategory":"Construction",
            "type":"Services"
        }
    ],
    "sg:phone":"+44 121 373 3010",
    "sg:postcode":"B23 6HG",
    "sg:province":"West Midlands",
    "sg:tags":[
        "tiling",
        "contractor"
    ],
    "wof:name":"Gary C Manders",
    "wof:placetype":"venue"
},
  "geometry": {"coordinates":[-1.85328,52.524769],"type":"Point"}
}