{
  "type": "Feature",
  "properties": {
    "iso:country":"GB",
    "sg:address":"Po Box 1745",
    "sg:city":"Bath",
    "sg:classifiers":[
        {
            "category":"Education",
            "subcategory":"University",
            "type":"Public Place"
        }
    ],
    "sg:phone":"+44 1225 444774",
    "sg:postcode":"BA2 6YE",
    "sg:province":"Somerset",
    "sg:tags":[
        "higher"
    ],
    "wof:name":"London School of Journalism",
    "wof:placetype":"venue"
},
  "geometry": {"coordinates":[-2.3238089085,51.3956298828],"type":"Point"}
}