{
  "type": "Feature",
  "properties": {
    "iso:country":"GB",
    "sg:address":"Belleview Way, Tomlinson Road",
    "sg:city":"Hartlepool",
    "sg:classifiers":[
        {
            "category":"Retail",
            "subcategory":"Car Wash",
            "type":"Services"
        }
    ],
    "sg:postcode":"TS25 1JZ",
    "sg:province":"Durham",
    "sg:tags":[
        "polishing",
        "washing"
    ],
    "wof:name":"Imo Car Wash",
    "wof:placetype":"venue"
},
  "geometry": {"coordinates":[-1.217739,54.66568],"type":"Point"}
}