{
  "type": "Feature",
  "properties": {
    "iso:country":"GB",
    "sg:address":"142-144 Old Rd",
    "sg:city":"Clacton-on-sea",
    "sg:classifiers":[
        {
            "category":"Health Services",
            "subcategory":"Doctor",
            "type":"Services"
        },
        {
            "category":"Food & Beverages",
            "subcategory":"Groceries & Convenience Stores",
            "type":"Retail Goods"
        }
    ],
    "sg:postcode":"CO15 3BA",
    "sg:province":"Essex",
    "sg:tags":[
        "practitioners"
    ],
    "wof:name":"Mirza,K U,",
    "wof:placetype":"venue"
},
  "geometry": {"coordinates":[1.148376,51.794449],"type":"Point"}
}