{
  "type": "Feature",
  "properties": {
    "addr:full":"193 High Rd Ilford Essex IG1 1LZ",
    "addr:housenumber":"193",
    "addr:postcode":"ig1 1lz",
    "addr:street":"High Rd",
    "iso:country":"GB",
    "sg:address":"193 High Rd",
    "sg:city":"Ilford",
    "sg:classifiers":[
        {
            "category":"Home & Garden",
            "subcategory":"Kitchen Supply",
            "type":"Retail Goods"
        }
    ],
    "sg:phone":"+44 20 8478 0994",
    "sg:postcode":"IG1 1LZ",
    "sg:province":"Essex",
    "sg:tags":[
        "table"
    ],
    "wof:name":"Amy's Ltd",
    "wof:placetype":"venue"
},
  "geometry": {"coordinates":[0.0748620033,51.559425354],"type":"Point"}
}