{
  "type": "Feature",
  "properties": {
    "iso:country":"GB",
    "sg:address":"Beaver Ho, Plough Rd",
    "sg:city":"Colchester",
    "sg:classifiers":[
        {
            "category":"Building & Trades",
            "subcategory":"Electrical",
            "type":"Services"
        }
    ],
    "sg:postcode":"CO7 8LG",
    "sg:province":"Essex",
    "sg:tags":[
        "lighting"
    ],
    "wof:name":"Reflexion Lighting Ltd",
    "wof:placetype":"venue"
},
  "geometry": {"coordinates":[1.0659,51.850269],"type":"Point"}
}