{
  "type": "Feature",
  "properties": {
    "addr:full":"149 Albany Road Coventry West Midlands CV5 6ND",
    "addr:housenumber":"149",
    "addr:postcode":"cv5 6nd",
    "addr:street":"Albany Road",
    "iso:country":"GB",
    "sg:address":"149 Albany Road",
    "sg:city":"Coventry",
    "sg:classifiers":[
        {
            "category":"Professional",
            "subcategory":"Business Services",
            "type":"Services"
        }
    ],
    "sg:postcode":"CV5 6ND",
    "sg:province":"West Midlands",
    "sg:tags":[
        "accomodation"
    ],
    "wof:name":"Misthaven Developments Limited",
    "wof:placetype":"venue"
},
  "geometry": {"coordinates":[-1.527062,52.401119],"type":"Point"}
}