{
  "type": "Feature",
  "properties": {
    "addr:full":"Earl Grey House, Grey St Newcastle Upon Tyne Tyne and Wear NE1 6EF",
    "addr:postcode":"ne1 6ef",
    "addr:street":"Grey St",
    "iso:country":"GB",
    "sg:address":"Earl Grey House, Grey St",
    "sg:city":"Newcastle Upon Tyne",
    "sg:classifiers":[
        {
            "category":"Professional",
            "subcategory":"Lawyer & Legal Services",
            "type":"Services"
        }
    ],
    "sg:phone":"+44 191 204 6000",
    "sg:postcode":"NE1 6EF",
    "sg:province":"Tyne and Wear",
    "sg:tags":[
        "solicitor"
    ],
    "wof:name":"RUSSELL JONES AND WALKER",
    "wof:placetype":"venue"
},
  "geometry": {"coordinates":[-1.612464,54.972691],"type":"Point"}
}