{
  "type": "Feature",
  "properties": {
    "addr:full":"15-16 Lower Park Row Bristol City of Bristol BS1 5BN",
    "addr:housenumber":"15-16",
    "addr:postcode":"bs1 5bn",
    "addr:street":"Lower Park Row",
    "iso:country":"GB",
    "sg:address":"15-16 Lower Park Row",
    "sg:city":"Bristol",
    "sg:classifiers":[
        {
            "category":"Communications",
            "type":"Services"
        }
    ],
    "sg:phone":"+44 117 903 0700",
    "sg:postcode":"BS1 5BN",
    "sg:province":"City of Bristol",
    "sg:tags":[
        "telecommunication"
    ],
    "wof:name":"Communication Stem Ltd.",
    "wof:placetype":"venue"
},
  "geometry": {"coordinates":[-2.5983319283,51.4558334351],"type":"Point"}
}