{
  "type": "Feature",
  "properties": {
    "iso:country":"GB",
    "sg:address":"29 London Road",
    "sg:city":"Twickenham",
    "sg:classifiers":[
        {
            "category":"Organizations",
            "subcategory":"Membership Organization",
            "type":"Services"
        }
    ],
    "sg:phone":"+44 20 8892 3100",
    "sg:postcode":"TW1 3SZ",
    "sg:province":"Greater London",
    "sg:tags":[
        "club"
    ],
    "wof:name":"Poplar Way Residents Association Ltd.",
    "wof:placetype":"venue"
},
  "geometry": {"coordinates":[-0.3287819922,51.4475593567],"type":"Point"}
}