{
  "type": "Feature",
  "properties": {
    "iso:country":"GB",
    "sg:address":"Grey Lea, Canon Pyon",
    "sg:city":"Hereford",
    "sg:classifiers":[
        {
            "category":"Farming",
            "subcategory":"Livestock Farm",
            "type":"Manufacturing & Wholesale Goods"
        }
    ],
    "sg:postcode":"HR4 8NR",
    "sg:province":"Herefordshire",
    "sg:tags":[
        "others"
    ],
    "wof:name":"Ian E France",
    "wof:placetype":"venue"
},
  "geometry": {"coordinates":[-2.7869839668,52.1360244751],"type":"Point"}
}