{
  "type": "Feature",
  "properties": {
    "addr:full":"Buckhaven Parish Church Hall, Randall Street, Buckhaven Leven Fife KY8 1AT",
    "addr:postcode":"ky8 1at",
    "addr:street":"Randall Street Buckhaven Leven",
    "iso:country":"GB",
    "sg:address":"Buckhaven Parish Church Hall, Randall Street, Buckhaven",
    "sg:city":"Leven",
    "sg:classifiers":[
        {
            "category":"Community Center",
            "subcategory":"Youth",
            "type":"Public Place"
        }
    ],
    "sg:phone":"+44 1592 587003",
    "sg:postcode":"KY8 1AT",
    "sg:province":"Fife",
    "sg:tags":[
        "organisation",
        "centre"
    ],
    "wof:name":"Mad Kids Club",
    "wof:placetype":"venue"
},
  "geometry": {"coordinates":[-3.038649,56.175171],"type":"Point"}
}