{
  "type": "Feature",
  "properties": {
    "iso:country":"GB",
    "sg:address":"54 North Road",
    "sg:city":"Darlington",
    "sg:classifiers":[
        {
            "category":"Professional",
            "subcategory":"Art Services",
            "type":"Services"
        }
    ],
    "sg:phone":"+44 1325 358132",
    "sg:postcode":"DL1 2EQ",
    "sg:province":"Durham",
    "sg:tags":[
        "framing"
    ],
    "wof:name":"Gisburne Framers",
    "wof:placetype":"venue"
},
  "geometry": {"coordinates":[-1.552437,54.536846],"type":"Point"}
}