{
  "type": "Feature",
  "properties": {
    "addr:full":"Prince Of Wales Pier, The Esplande Dover Kent CT17 9BX",
    "addr:postcode":"ct17 9bx",
    "addr:street":"Prince",
    "iso:country":"GB",
    "sg:address":"Prince Of Wales Pier, The Esplande",
    "sg:city":"Dover",
    "sg:classifiers":[
        {
            "category":"Cafe",
            "type":"Food & Drink"
        }
    ],
    "sg:postcode":"CT17 9BX",
    "sg:province":"Kent",
    "sg:tags":[
        "tea",
        "room"
    ],
    "wof:name":"Lighthouse Cafe",
    "wof:placetype":"venue"
},
  "geometry": {"coordinates":[1.309397,51.120144],"type":"Point"}
}