{
  "type": "Feature",
  "properties": {
    "addr:full":"Stirling Clo Leigh Lancashire WN7 2UB",
    "addr:postcode":"wn7 2ub",
    "addr:street":"Leigh",
    "iso:country":"GB",
    "sg:address":"Stirling Clo",
    "sg:city":"Leigh",
    "sg:classifiers":[
        {
            "category":"Community Center",
            "type":"Public Place"
        }
    ],
    "sg:phone":"+44 1942 674548",
    "sg:postcode":"WN7 2UB",
    "sg:province":"Lancashire",
    "sg:tags":[
        "centre"
    ],
    "wof:name":"Higher Fold Community Hall",
    "wof:placetype":"venue"
},
  "geometry": {"coordinates":[-2.485255003,53.5012130737],"type":"Point"}
}