{
  "type": "Feature",
  "properties": {
    "addr:full":"London Road Wallington Surrey SM6 7BJ",
    "addr:postcode":"sm6 7bj",
    "addr:street":"London Road",
    "iso:country":"GB",
    "sg:address":"London Road",
    "sg:city":"Wallington",
    "sg:classifiers":[
        {
            "category":"Shopping",
            "subcategory":"Computers & Home Electronics",
            "type":"Retail Goods"
        }
    ],
    "sg:phone":"+44 20 8647 4740",
    "sg:postcode":"SM6 7BJ",
    "sg:province":"Surrey",
    "sg:tags":[
        "tape",
        "video"
    ],
    "wof:name":"Miles of Tape Ltd.",
    "wof:placetype":"venue"
},
  "geometry": {"coordinates":[-0.156544,51.381523],"type":"Point"}
}