{
  "type": "Feature",
  "properties": {
    "iso:country":"GB",
    "sg:address":"James Charles House, 37a Aylesbury Street, Bletchley",
    "sg:city":"Milton Keynes",
    "sg:classifiers":[
        {
            "category":"Professional",
            "subcategory":"Lawyer & Legal Services",
            "type":"Services"
        }
    ],
    "sg:postcode":"MK2 2PS",
    "sg:province":"Buckinghamshire",
    "sg:tags":[
        "solicitor"
    ],
    "wof:name":"Jones Miller & Co.",
    "wof:placetype":"venue"
},
  "geometry": {"coordinates":[-0.717463,51.996803],"type":"Point"}
}