{
  "type": "Feature",
  "properties": {
    "addr:full":"8 Grafton Road King's Lynn Norfolk PE30 3HA",
    "addr:housenumber":"8",
    "addr:postcode":"pe30 3ha",
    "addr:street":"Grafton Road",
    "iso:country":"GB",
    "sg:address":"8 Grafton Road",
    "sg:city":"King's Lynn",
    "sg:classifiers":[
        {
            "category":"Social Services",
            "type":"Services"
        },
        {
            "category":"Personal",
            "type":"Services"
        },
        {
            "category":"Professional",
            "subcategory":"Lawyer & Legal Services",
            "type":"Services"
        }
    ],
    "sg:phone":"+44 870 740 8669",
    "sg:postcode":"PE30 3HA",
    "sg:province":"Norfolk",
    "sg:tags":[
        "advice",
        "helplines",
        "counselling"
    ],
    "wof:name":"Connections Counselling Ltd",
    "wof:placetype":"venue"
},
  "geometry": {"coordinates":[0.4366399944,52.7690391541],"type":"Point"}
}