{
  "type": "Feature",
  "properties": {
    "iso:country":"GB",
    "sg:address":"92 Green Lane",
    "sg:city":"Buxton",
    "sg:classifiers":[
        {
            "category":"Organizations",
            "subcategory":"Non-profit Organization",
            "type":"Services"
        }
    ],
    "sg:phone":"+44 1298 72347",
    "sg:postcode":"SK17 9DJ",
    "sg:province":"Derbyshire",
    "sg:tags":[
        "organisation",
        "voluntary",
        "charity"
    ],
    "wof:name":"Cavendale",
    "wof:placetype":"venue"
},
  "geometry": {"coordinates":[-1.92275,53.250183],"type":"Point"}
}