{
  "type": "Feature",
  "properties": {
    "addr:full":"Business Centre, 42 Wycombe Rd, Holmer Green High Wycombe Buckinghamshire HP15 6RY",
    "addr:housenumber":"42",
    "addr:postcode":"hp15 6ry",
    "addr:street":"Wycombe Rd Holmer Green",
    "iso:country":"GB",
    "sg:address":"Business Centre, 42 Wycombe Rd, Holmer Green",
    "sg:city":"High Wycombe",
    "sg:classifiers":[
        {
            "category":"Manufacturing",
            "subcategory":"Electronics",
            "type":"Manufacturing & Wholesale Goods"
        }
    ],
    "sg:phone":"+44 1494 711030",
    "sg:postcode":"HP15 6RY",
    "sg:province":"Buckinghamshire",
    "sg:tags":[
        "printed",
        "circuit"
    ],
    "wof:name":"Dl Designs",
    "wof:placetype":"venue"
},
  "geometry": {"coordinates":[-0.693794,51.66468],"type":"Point"}
}