{
  "type": "Feature",
  "properties": {
    "iso:country":"GB",
    "sg:address":"Carmondean Centre",
    "sg:city":"Livingston",
    "sg:classifiers":[
        {
            "category":"Autos & Motor Vehicles",
            "subcategory":"Auto Supplies",
            "type":"Retail Goods"
        }
    ],
    "sg:phone":"+44 1506 430838",
    "sg:postcode":"EH54 8PT",
    "sg:province":"West Lothian",
    "sg:tags":[
        "exhaust",
        "absorber",
        "shock"
    ],
    "wof:name":"Kwik-Fit",
    "wof:placetype":"venue"
},
  "geometry": {"coordinates":[-3.549094,55.904453],"type":"Point"}
}