{
  "type": "Feature",
  "properties": {
    "addr:full":"Apedale Rd, Chesterton Newcastle Staffordshire ST5 6BL",
    "addr:postcode":"st5 6bl",
    "addr:street":"Apedale Rd",
    "iso:country":"GB",
    "sg:address":"Apedale Rd, Chesterton",
    "sg:city":"Newcastle",
    "sg:classifiers":[
        {
            "category":"Mining & Drilling",
            "type":"Manufacturing & Wholesale Goods"
        }
    ],
    "sg:phone":"+44 1782 565860",
    "sg:postcode":"ST5 6BL",
    "sg:province":"Staffordshire",
    "sg:tags":[
        "coal"
    ],
    "wof:name":"Aurora Mining Ltd",
    "wof:placetype":"venue"
},
  "geometry": {"coordinates":[-2.269516,53.037888],"type":"Point"}
}