{
  "type": "Feature",
  "properties": {
    "iso:country":"GB",
    "sg:address":"5-6 College Street",
    "sg:city":"Lampeter",
    "sg:classifiers":[
        {
            "category":"Government",
            "subcategory":"Post Office",
            "type":"Public Place"
        }
    ],
    "sg:phone":"+44 1570 422553",
    "sg:postcode":"SA48 7DZ",
    "sg:province":"Carmarthenshire",
    "wof:name":"Lampeter Post Office",
    "wof:placetype":"venue"
},
  "geometry": {"coordinates":[-4.0781841278,52.1136932373],"type":"Point"}
}