{
  "type": "Feature",
  "properties": {
    "iso:country":"GB",
    "sg:address":"179 Railway Arches",
    "sg:city":"London",
    "sg:classifiers":[
        {
            "category":"Professional",
            "subcategory":"Detective & Security Services",
            "type":"Services"
        }
    ],
    "sg:phone":"+44 20 8743 4056",
    "sg:postcode":"W12 8DF",
    "sg:province":"Greater London",
    "sg:tags":[
        "locksmith"
    ],
    "wof:name":"W G Stores Ltd.",
    "wof:placetype":"venue"
},
  "geometry": {"coordinates":[-0.22663,51.502449],"type":"Point"}
}