{
  "type": "Feature",
  "properties": {
    "iso:country":"GB",
    "sg:address":"Flestcher Ho, Stafford Pk 17",
    "sg:city":"Telford",
    "sg:classifiers":[
        {
            "category":"Professional",
            "subcategory":"Business Services",
            "type":"Services"
        },
        {
            "category":"Shopping",
            "subcategory":"Computers & Home Electronics",
            "type":"Retail Goods"
        }
    ],
    "sg:phone":"+44 1952 299990",
    "sg:postcode":"TF3 3DG",
    "sg:province":"Shropshire",
    "sg:tags":[
        "distribution"
    ],
    "wof:name":"Procase Ltd",
    "wof:placetype":"venue"
},
  "geometry": {"coordinates":[-2.424777,52.672031],"type":"Point"}
}