{
  "type": "Feature",
  "properties": {
    "iso:country":"GB",
    "sg:address":"17 Park Rd",
    "sg:city":"Barnet",
    "sg:classifiers":[
        {
            "category":"Professional",
            "subcategory":"Engineering",
            "type":"Services"
        }
    ],
    "sg:phone":"+44 20 8449 4351",
    "sg:postcode":"EN4 9QA",
    "sg:province":"Hertfordshire",
    "sg:tags":[
        "contractor",
        "electrical",
        "engineer"
    ],
    "wof:name":"J D C Contractors",
    "wof:placetype":"venue"
},
  "geometry": {"coordinates":[-0.167379,51.65229],"type":"Point"}
}