{
  "type": "Feature",
  "properties": {
    "addr:full":"5 Conifer Crest, Wash Common Newbury Berkshire RG14 6RS",
    "addr:housenumber":"5",
    "addr:postcode":"rg14 6rs",
    "addr:street":"Conifer Crest;Common",
    "iso:country":"GB",
    "sg:address":"5 Conifer Crest, Wash Common",
    "sg:city":"Newbury",
    "sg:classifiers":[
        {
            "category":"Real Estate",
            "subcategory":"Surveying",
            "type":"Services"
        }
    ],
    "sg:postcode":"RG14 6RS",
    "sg:province":"Berkshire",
    "sg:tags":[
        "surveyor",
        "quantity"
    ],
    "wof:name":"Worthington Associates Ltd.",
    "wof:placetype":"venue"
},
  "geometry": {"coordinates":[-1.3483580351,51.3731803894],"type":"Point"}
}