{
  "type": "Feature",
  "properties": {
    "addr:full":"Trevilling Farm, Bodieve Wadebridge Cornwall PL27 6EQ",
    "addr:postcode":"pl27 6eq",
    "addr:street":"Bodieve",
    "iso:country":"GB",
    "sg:address":"Trevilling Farm, Bodieve",
    "sg:city":"Wadebridge",
    "sg:classifiers":[
        {
            "category":"Farming",
            "subcategory":"Dairy Farm",
            "type":"Manufacturing & Wholesale Goods"
        }
    ],
    "sg:postcode":"PL27 6EQ",
    "sg:province":"Cornwall",
    "wof:name":"Williams Dairy",
    "wof:placetype":"venue"
},
  "geometry": {"coordinates":[-4.8312211037,50.5251235962],"type":"Point"}
}