{
  "type": "Feature",
  "properties": {
    "iso:country":"GB",
    "sg:address":"Budshead Rd, Whitleigh Green",
    "sg:city":"Plymouth",
    "sg:classifiers":[
        {
            "category":"Bars & Pubs",
            "type":"Food & Drink"
        }
    ],
    "sg:phone":"+44 1752 782289",
    "sg:postcode":"PL5 4DD",
    "sg:province":"Devon",
    "sg:tags":[
        "pubs",
        "inn"
    ],
    "wof:name":"The Albermarle",
    "wof:placetype":"venue"
},
  "geometry": {"coordinates":[-4.158406,50.419231],"type":"Point"}
}