{
  "type": "Feature",
  "properties": {
    "addr:full":"C/o Messrs Siva Yogan & Co. Hounslow Bus, Unit 1 First Floor Alice Way, 239 Hanw Hounslow Greater London TW3 3UD",
    "addr:housenumber":"unit 1 first floor;239",
    "addr:postcode":"tw3 3ud",
    "addr:street":"C;Alice Way",
    "iso:country":"GB",
    "sg:address":"C/o Messrs Siva Yogan & Co. Hounslow Bus, Unit 1 First Floor Alice Way, 239 Hanw",
    "sg:city":"Hounslow",
    "sg:classifiers":[
        {
            "category":"Taxi",
            "type":"Transportation"
        }
    ],
    "sg:postcode":"TW3 3UD",
    "sg:province":"Greater London",
    "sg:tags":[
        "mini",
        "cab"
    ],
    "wof:name":"Parklane Cars (U K) Ltd",
    "wof:placetype":"venue"
},
  "geometry": {"coordinates":[-0.36685,51.462761],"type":"Point"}
}