{
  "type": "Feature",
  "properties": {
    "iso:country":"GB",
    "sg:address":"Suite 4-6",
    "sg:city":"Preston",
    "sg:classifiers":[
        {
            "category":"Professional",
            "subcategory":"Credit Reporting & Collection",
            "type":"Services"
        }
    ],
    "sg:phone":"+44 1772 454505",
    "sg:postcode":"PR25 3GR",
    "sg:province":"Lancashire",
    "sg:tags":[
        "collecting",
        "agency",
        "debt"
    ],
    "wof:name":"Creditsafe Ltd",
    "wof:placetype":"venue"
},
  "geometry": {"coordinates":[-2.68755,53.7075],"type":"Point"}
}