{
  "type": "Feature",
  "properties": {
    "addr:full":"2 St Leonards Street Bedford Bedfordshire MK42 9BS",
    "addr:housenumber":"2",
    "addr:postcode":"mk42 9bs",
    "addr:street":"St Leonards Street",
    "iso:country":"GB",
    "sg:address":"2 St Leonards Street",
    "sg:city":"Bedford",
    "sg:classifiers":[
        {
            "category":"Professional",
            "subcategory":"Engineering",
            "type":"Services"
        }
    ],
    "sg:phone":"+44 1234 356740",
    "sg:postcode":"MK42 9BS",
    "sg:province":"Bedfordshire",
    "sg:tags":[
        "contractor",
        "electrical",
        "engineer"
    ],
    "wof:name":"Ian F Lucas Electrical",
    "wof:placetype":"venue"
},
  "geometry": {"coordinates":[-0.465912,52.129612],"type":"Point"}
}