{
  "type": "Feature",
  "properties": {
    "addr:full":"160 West Park Av Preston Lancashire PR2 1SY",
    "addr:housenumber":"160",
    "addr:postcode":"pr2 1sy",
    "addr:street":"West Park Av",
    "iso:country":"GB",
    "sg:address":"160 West Park Av",
    "sg:city":"Preston",
    "sg:classifiers":[
        {
            "category":"Building & Trades",
            "subcategory":"Construction",
            "type":"Services"
        }
    ],
    "sg:phone":"+44 1772 731173",
    "sg:postcode":"PR2 1SY",
    "sg:province":"Lancashire",
    "sg:tags":[
        "dry",
        "lining",
        "plasterers",
        "screeders"
    ],
    "wof:name":"John Russell",
    "wof:placetype":"venue"
},
  "geometry": {"coordinates":[-2.7484788895,53.7721405029],"type":"Point"}
}