{
  "type": "Feature",
  "properties": {
    "addr:full":"61-75 Empress Road Southampton Hampshire SO14 0JW",
    "addr:housenumber":"61-75",
    "addr:postcode":"so14 0jw",
    "addr:street":"Empress Road",
    "iso:country":"GB",
    "sg:address":"61-75 Empress Road",
    "sg:city":"Southampton",
    "sg:classifiers":[
        {
            "category":"Manufacturing",
            "subcategory":"Metals",
            "type":"Manufacturing & Wholesale Goods"
        }
    ],
    "sg:phone":"+44 23 8022 5639",
    "sg:postcode":"SO14 0JW",
    "sg:province":"Hampshire",
    "wof:name":"Hampshire Electro Plating Co. Ltd.",
    "wof:placetype":"venue"
},
  "geometry": {"coordinates":[-1.3946150541,50.9174385071],"type":"Point"}
}