{
  "type": "Feature",
  "properties": {
    "iso:country":"GB",
    "sg:address":"4 Crescent St",
    "sg:city":"Weymouth",
    "sg:classifiers":[
        {
            "category":"Professional",
            "subcategory":"Printing & Photocopies",
            "type":"Services"
        }
    ],
    "sg:phone":"+44 1305 777235",
    "sg:postcode":"DT4 7BX",
    "sg:province":"Dorset",
    "sg:tags":[
        "embroiderer"
    ],
    "wof:name":"Stylish Stitches The Embroidery People",
    "wof:placetype":"venue"
},
  "geometry": {"coordinates":[-2.453591,50.61478],"type":"Point"}
}