{
  "type": "Feature",
  "properties": {
    "addr:full":"10 Witcham Close, Lower Earley Reading Berkshire RG6 4HA",
    "addr:housenumber":"10",
    "addr:postcode":"rg6 4ha",
    "addr:street":"Witcham Close",
    "iso:country":"GB",
    "sg:address":"10 Witcham Close, Lower Earley",
    "sg:city":"Reading",
    "sg:classifiers":[
        {
            "category":"Professional",
            "subcategory":"Employment Agencies",
            "type":"Services"
        }
    ],
    "sg:phone":"+44 118 975 8186",
    "sg:postcode":"RG6 4HA",
    "sg:province":"Berkshire",
    "sg:tags":[
        "consultant",
        "recruitment"
    ],
    "wof:name":"Redwood Starke Ltd",
    "wof:placetype":"venue"
},
  "geometry": {"coordinates":[-0.914786,51.423016],"type":"Point"}
}