{
  "type": "Feature",
  "properties": {
    "addr:full":"83 Constance Road Leicester Leicestershire LE5 5DF",
    "addr:housenumber":"83",
    "addr:postcode":"le5 5df",
    "addr:street":"Constance Road",
    "iso:country":"GB",
    "sg:address":"83 Constance Road",
    "sg:city":"Leicester",
    "sg:classifiers":[
        {
            "category":"Shopping",
            "subcategory":"Clothing, Apparel, & Fashions",
            "type":"Retail Goods"
        }
    ],
    "sg:phone":"+44 116 273 1559",
    "sg:postcode":"LE5 5DF",
    "sg:province":"Leicestershire",
    "sg:tags":[
        "clothing",
        "fabric"
    ],
    "wof:name":"S I S Clothing",
    "wof:placetype":"venue"
},
  "geometry": {"coordinates":[-1.101174,52.631374],"type":"Point"}
}