{
  "type": "Feature",
  "properties": {
    "iso:country":"GB",
    "sg:address":"14 Cibi Walk, Frogmore Street",
    "sg:city":"Abergavenny",
    "sg:classifiers":[
        {
            "category":"Retail",
            "subcategory":"Photofinishing",
            "type":"Services"
        }
    ],
    "sg:phone":"+44 1873 853966",
    "sg:postcode":"NP7 5AJ",
    "sg:province":"Herefordshire",
    "sg:tags":[
        "photographic",
        "processor"
    ],
    "wof:name":"Sketchley Retail Ltd.",
    "wof:placetype":"venue"
},
  "geometry": {"coordinates":[-3.02068,51.825008],"type":"Point"}
}