{
  "type": "Feature",
  "properties": {
    "iso:country":"GB",
    "sg:address":"A5 Delta Way, Bridgtown",
    "sg:city":"Cannock",
    "sg:classifiers":[
        {
            "category":"Autos & Motor Vehicles",
            "subcategory":"Automobile Sales",
            "type":"Retail Goods"
        }
    ],
    "sg:phone":"+44 1543 579555",
    "sg:postcode":"WS11 3BE",
    "sg:province":"Staffordshire",
    "sg:tags":[
        "commercial"
    ],
    "wof:name":"Walsall Trailer & Commercials Ltd",
    "wof:placetype":"venue"
},
  "geometry": {"coordinates":[-2.0256710052,52.683681488],"type":"Point"}
}