{
  "type": "Feature",
  "properties": {
    "addr:full":"Colin Booth Yard, Humber Rd Barton Upon Humber Lincolnshire DN18 5BN",
    "addr:postcode":"dn18 5bn",
    "addr:street":"Humber Rd",
    "iso:country":"GB",
    "sg:address":"Colin Booth Yard, Humber Rd",
    "sg:city":"Barton Upon Humber",
    "sg:classifiers":[
        {
            "category":"Retail",
            "subcategory":"Auto Repair",
            "type":"Services"
        }
    ],
    "sg:phone":"+44 1652 661300",
    "sg:postcode":"DN18 5BN",
    "sg:province":"Lincolnshire",
    "sg:tags":[
        "modification",
        "garage"
    ],
    "wof:name":"C Cherry",
    "wof:placetype":"venue"
},
  "geometry": {"coordinates":[-0.4432410002,53.6844482422],"type":"Point"}
}