{
  "type": "Feature",
  "properties": {
    "addr:full":"72 Cudnell Ave Bournemouth Dorset BH11 9DA",
    "addr:housenumber":"72",
    "addr:postcode":"bh11 9da",
    "addr:street":"Cudnell Ave",
    "iso:country":"GB",
    "sg:address":"72 Cudnell Ave",
    "sg:city":"Bournemouth",
    "sg:classifiers":[
        {
            "category":"Building & Trades",
            "subcategory":"Plumbing",
            "type":"Services"
        }
    ],
    "sg:postcode":"BH11 9DA",
    "sg:province":"Dorset",
    "sg:tags":[
        "heating"
    ],
    "wof:name":"Boothroyd,E & M,",
    "wof:placetype":"venue"
},
  "geometry": {"coordinates":[-1.917523,50.770699],"type":"Point"}
}