{
  "type": "Feature",
  "properties": {
    "addr:full":"1 School Road, Warmley Bristol Gloucestershire BS30 8EN",
    "addr:housenumber":"1",
    "addr:postcode":"bs30 8en",
    "addr:street":"School Road",
    "iso:country":"GB",
    "sg:address":"1 School Road, Warmley",
    "sg:city":"Bristol",
    "sg:classifiers":[
        {
            "category":"Shopping",
            "subcategory":"Pharmacy",
            "type":"Retail Goods"
        }
    ],
    "sg:postcode":"BS30 8EN",
    "sg:province":"Gloucestershire",
    "sg:tags":[
        "pharmacist",
        "chemist"
    ],
    "wof:name":"Stuart Moul",
    "wof:placetype":"venue"
},
  "geometry": {"coordinates":[-2.4834239483,51.4459915161],"type":"Point"}
}