{
  "type": "Feature",
  "properties": {
    "addr:full":"66 Cambridge Street Sheffield South Yorkshire S1 4HP",
    "addr:housenumber":"66",
    "addr:postcode":"s1 4hp",
    "addr:street":"Cambridge Street",
    "iso:country":"GB",
    "sg:address":"66 Cambridge Street",
    "sg:city":"Sheffield",
    "sg:classifiers":[
        {
            "category":"Shopping",
            "subcategory":"Hobbies, Toys, & Games",
            "type":"Retail Goods"
        },
        {
            "category":"Transit Center",
            "subcategory":"Freight",
            "type":"Transportation"
        }
    ],
    "sg:phone":"+44 114 273 0066",
    "sg:postcode":"S1 4HP",
    "sg:province":"South Yorkshire",
    "sg:tags":[
        "collectors'",
        "item",
        "collector"
    ],
    "wof:name":"Frames of Mind",
    "wof:placetype":"venue"
},
  "geometry": {"coordinates":[-1.4717969894,53.3783988953],"type":"Point"}
}