{
  "type": "Feature",
  "properties": {
    "iso:country":"GB",
    "sg:address":"Temple Ho, 20 Holywell Row",
    "sg:city":"London",
    "sg:classifiers":[
        {
            "category":"Banks & Credit Unions",
            "subcategory":"Financial Services",
            "type":"Services"
        }
    ],
    "sg:postcode":"EC2A 4JB",
    "sg:province":"Greater London",
    "sg:tags":[
        "consultant"
    ],
    "wof:name":"All-Time Investments Ltd",
    "wof:placetype":"venue"
},
  "geometry": {"coordinates":[-0.0833000019,51.5223312378],"type":"Point"}
}