{
  "type": "Feature",
  "properties": {
    "addr:full":"22 Welburn Gro, Ormesby Middlesbrough North Yorkshire TS7 9BN",
    "addr:housenumber":"22",
    "addr:postcode":"ts7 9bn",
    "addr:street":"Welburn Gro",
    "iso:country":"GB",
    "sg:address":"22 Welburn Gro, Ormesby",
    "sg:city":"Middlesbrough",
    "sg:classifiers":[
        {
            "category":"Retail",
            "subcategory":"Driving School",
            "type":"Services"
        }
    ],
    "sg:phone":"+44 1642 314353",
    "sg:postcode":"TS7 9BN",
    "sg:province":"North Yorkshire",
    "wof:name":"Gornall Brian School of Motoring",
    "wof:placetype":"venue"
},
  "geometry": {"coordinates":[-1.1801970005,54.5458145142],"type":"Point"}
}