{
  "type": "Feature",
  "properties": {
    "iso:country":"GB",
    "sg:address":"86 North Road",
    "sg:city":"Withernsea",
    "sg:classifiers":[
        {
            "category":"Building & Trades",
            "subcategory":"Construction",
            "type":"Services"
        }
    ],
    "sg:phone":"+44 1964 614067",
    "sg:postcode":"HU19 2AY",
    "sg:province":"East Riding of Yorkshire",
    "sg:tags":[
        "decorator",
        "painter"
    ],
    "wof:name":"A P Fairweather Painter & Decorator",
    "wof:placetype":"venue"
},
  "geometry": {"coordinates":[0.0273850001,53.7353210449],"type":"Point"}
}