{
  "type": "Feature",
  "properties": {
    "iso:country":"GB",
    "sg:address":"30 Sunnyside Rd",
    "sg:city":"Weston Super Mare",
    "sg:classifiers":[
        {
            "category":"Building & Trades",
            "subcategory":"Construction",
            "type":"Services"
        }
    ],
    "sg:phone":"+44 1934 627643",
    "sg:postcode":"BS23 1BP",
    "sg:province":"Somerset",
    "sg:tags":[
        "builder"
    ],
    "wof:name":"Lees Building & Roofing Contractors",
    "wof:placetype":"venue"
},
  "geometry": {"coordinates":[-2.970922,51.338467],"type":"Point"}
}