{
  "type": "Feature",
  "properties": {
    "addr:full":"22 Franklin Road Shoreham-by-sea West Sussex BN43 6YD",
    "addr:housenumber":"22",
    "addr:postcode":"bn43 6yd",
    "addr:street":"Franklin Road",
    "iso:country":"GB",
    "sg:address":"22 Franklin Road",
    "sg:city":"Shoreham-by-sea",
    "sg:classifiers":[
        {
            "category":"Building & Trades",
            "subcategory":"Construction",
            "type":"Services"
        }
    ],
    "sg:phone":"+44 1273 591380",
    "sg:postcode":"BN43 6YD",
    "sg:province":"West Sussex",
    "sg:tags":[
        "builder"
    ],
    "wof:name":"Brian Gumbrell",
    "wof:placetype":"venue"
},
  "geometry": {"coordinates":[-0.2453790009,50.840473175],"type":"Point"}
}