{
  "type": "Feature",
  "properties": {
    "addr:full":"14 Hawkins Clo Lichfield Staffordshire WS13 7NZ",
    "addr:housenumber":"14",
    "addr:postcode":"ws13 7nz",
    "addr:street":"Hawkins Clo",
    "iso:country":"GB",
    "sg:address":"14 Hawkins Clo",
    "sg:city":"Lichfield",
    "sg:classifiers":[
        {
            "category":"Professional",
            "subcategory":"Advertising",
            "type":"Services"
        }
    ],
    "sg:postcode":"WS13 7NZ",
    "sg:province":"Staffordshire",
    "sg:tags":[
        "agency"
    ],
    "wof:name":"Lang,David,",
    "wof:placetype":"venue"
},
  "geometry": {"coordinates":[-1.8310250044,52.6953964233],"type":"Point"}
}