{
  "type": "Feature",
  "properties": {
    "addr:full":"20 Oak Farm Close, Blackwater Camberley Hampshire GU17 0JU",
    "addr:housenumber":"20",
    "addr:postcode":"gu17 0ju",
    "addr:street":"Oak Farm Close",
    "iso:country":"GB",
    "sg:address":"20 Oak Farm Close, Blackwater",
    "sg:city":"Camberley",
    "sg:classifiers":[
        {
            "category":"Professional",
            "subcategory":"Art Services",
            "type":"Services"
        },
        {
            "category":"Building & Trades",
            "subcategory":"Construction",
            "type":"Services"
        }
    ],
    "sg:phone":"+44 1252 872429",
    "sg:postcode":"GU17 0JU",
    "sg:province":"Hampshire",
    "sg:tags":[
        "decorator",
        "painter"
    ],
    "wof:name":"Altered Images",
    "wof:placetype":"venue"
},
  "geometry": {"coordinates":[-0.7995610237,51.3373565674],"type":"Point"}
}