{
  "type": "Feature",
  "properties": {
    "iso:country":"GB",
    "sg:address":"150b Lytham Road, Warton",
    "sg:city":"Preston",
    "sg:classifiers":[
        {
            "category":"Professional",
            "subcategory":"Business Services",
            "type":"Services"
        }
    ],
    "sg:postcode":"PR4 1XE",
    "sg:province":"Lancashire",
    "sg:tags":[
        "bookmaker"
    ],
    "wof:name":"Fylde Racing",
    "wof:placetype":"venue"
},
  "geometry": {"coordinates":[-2.876951,53.752506],"type":"Point"}
}