{
  "type": "Feature",
  "properties": {
    "iso:country":"GB",
    "sg:address":"The Old Barn, Dunsborough Park, Ripley",
    "sg:city":"Woking",
    "sg:classifiers":[
        {
            "category":"Manufacturing",
            "subcategory":"Chemicals & Compounds",
            "type":"Manufacturing & Wholesale Goods"
        },
        {
            "category":"Banks & Credit Unions",
            "subcategory":"Investment Brokerage",
            "type":"Services"
        }
    ],
    "sg:phone":"+44 1932 347999",
    "sg:postcode":"GU23 6AL",
    "sg:province":"Surrey",
    "sg:tags":[
        "abrasive",
        "product",
        "production",
        "-"
    ],
    "wof:name":"Winchem Ltd.",
    "wof:placetype":"venue"
},
  "geometry": {"coordinates":[-0.490569,51.30106],"type":"Point"}
}