{
  "type": "Feature",
  "properties": {
    "iso:country":"GB",
    "sg:address":"489 Pollokshaws Road",
    "sg:city":"Glasgow",
    "sg:classifiers":[
        {
            "category":"Fast Food",
            "type":"Food & Drink"
        }
    ],
    "sg:phone":"+44 141 424 1655",
    "sg:postcode":"G41 2QQ",
    "sg:province":"Glasgow City",
    "sg:tags":[
        "away",
        "take"
    ],
    "wof:name":"McDonalds Restaurants Ltd.",
    "wof:placetype":"venue"
},
  "geometry": {"coordinates":[-4.2665748596,55.8401031494],"type":"Point"}
}