{
  "type": "Feature",
  "properties": {
    "iso:country":"GB",
    "sg:address":"1 Castle Close, Calverton",
    "sg:city":"Nottingham",
    "sg:classifiers":[
        {
            "category":"Shopping",
            "subcategory":"Stationery & Office Supplies",
            "type":"Retail Goods"
        },
        {
            "category":"Social Services",
            "subcategory":"Job Training",
            "type":"Services"
        },
        {
            "category":"Real Estate",
            "subcategory":"Architect",
            "type":"Services"
        }
    ],
    "sg:phone":"+44 115 965 4492",
    "sg:postcode":"NG14 6LX",
    "sg:province":"Nottinghamshire",
    "sg:tags":[
        "draughtsman",
        "drawing"
    ],
    "wof:name":"K M C",
    "wof:placetype":"venue"
},
  "geometry": {"coordinates":[-1.090542,53.039387],"type":"Point"}
}