{
  "type": "Feature",
  "properties": {
    "addr:full":"Unit 16 Milmead Industrial Centre, Mill Mead Road London Greater London N17 9QU",
    "addr:housenumber":"unit 16",
    "addr:postcode":"n17 9qu",
    "addr:street":"Milmead;Mill Mead Road",
    "iso:country":"GB",
    "sg:address":"Unit 16 Milmead Industrial Centre, Mill Mead Road",
    "sg:city":"London",
    "sg:classifiers":[
        {
            "category":"Manufacturing",
            "subcategory":"Textiles",
            "type":"Manufacturing & Wholesale Goods"
        }
    ],
    "sg:phone":"+44 20 8880 3177",
    "sg:postcode":"N17 9QU",
    "sg:province":"Greater London",
    "sg:tags":[
        "knitwear"
    ],
    "wof:name":"Jessgrove Ltd.",
    "wof:placetype":"venue"
},
  "geometry": {"coordinates":[-0.0573,51.59251],"type":"Point"}
}