{
  "type": "Feature",
  "properties": {
    "addr:full":"Unit, 6 Stockport Cheshire SK3 0AL",
    "addr:housenumber":"unit 6",
    "addr:postcode":"sk3 0al",
    "iso:country":"GB",
    "sg:address":"Unit, 6",
    "sg:city":"Stockport",
    "sg:classifiers":[
        {
            "category":"Professional",
            "subcategory":"Printing & Photocopies",
            "type":"Services"
        }
    ],
    "sg:phone":"+44 161 477 1700",
    "sg:postcode":"SK3 0AL",
    "sg:province":"Cheshire",
    "sg:tags":[
        "plate",
        "lithographic",
        "maker"
    ],
    "wof:name":"T.R Shown Print Services Ltd",
    "wof:placetype":"venue"
},
  "geometry": {"coordinates":[-2.183619,53.401798],"type":"Point"}
}