{
  "type": "Feature",
  "properties": {
    "addr:full":"273 Moston La Manchester Greater Manchester M40 9WJ",
    "addr:housenumber":"273",
    "addr:postcode":"m40 9wj",
    "addr:street":"Moston La Manchester",
    "iso:country":"GB",
    "sg:address":"273 Moston La",
    "sg:city":"Manchester",
    "sg:classifiers":[
        {
            "category":"Shopping",
            "subcategory":"Gifts & Souvenirs",
            "type":"Retail Goods"
        }
    ],
    "sg:postcode":"M40 9WJ",
    "sg:province":"Greater Manchester",
    "sg:tags":[
        "shop"
    ],
    "wof:name":"McNair,Anita,",
    "wof:placetype":"venue"
},
  "geometry": {"coordinates":[-2.194989,53.510841],"type":"Point"}
}