{
  "type": "Feature",
  "properties": {
    "addr:full":"80 Mill St Macclesfield Cheshire SK11 6NH",
    "addr:housenumber":"80",
    "addr:postcode":"sk11 6nh",
    "addr:street":"Mill St",
    "iso:country":"GB",
    "sg:address":"80 Mill St",
    "sg:city":"Macclesfield",
    "sg:classifiers":[
        {
            "category":"Shopping",
            "subcategory":"Crafts & Fabrics",
            "type":"Retail Goods"
        }
    ],
    "sg:phone":"+44 1625 425214",
    "sg:postcode":"SK11 6NH",
    "sg:province":"Cheshire",
    "sg:tags":[
        "shop",
        "needlecraft",
        "wool"
    ],
    "wof:name":"Spinning Wheel (Macclesfield) Ltd The",
    "wof:placetype":"venue"
},
  "geometry": {"coordinates":[-2.1256809235,53.2580757141],"type":"Point"}
}