{
  "type": "Feature",
  "properties": {
    "addr:full":"Framland, Naldertown Wantage Berkshire OX12 9DL",
    "addr:postcode":"ox12 9dl",
    "iso:country":"GB",
    "sg:address":"Framland, Naldertown",
    "sg:city":"Wantage",
    "sg:classifiers":[
        {
            "category":"Health Services",
            "subcategory":"Nursing And Care Facility",
            "type":"Services"
        }
    ],
    "sg:phone":"+44 1235 765166",
    "sg:postcode":"OX12 9DL",
    "sg:province":"Berkshire",
    "sg:tags":[
        "home",
        "residential"
    ],
    "wof:name":"Pilgrim Homes",
    "wof:placetype":"venue"
},
  "geometry": {"coordinates":[-1.4386589527,51.5904045105],"type":"Point"}
}