{
  "type": "Feature",
  "properties": {
    "iso:country":"GB",
    "sg:address":"2 River Street",
    "sg:city":"Pewsey",
    "sg:classifiers":[
        {
            "category":"Shopping",
            "subcategory":"Clothing, Apparel, & Fashions",
            "type":"Retail Goods"
        }
    ],
    "sg:phone":"+44 1672 563304",
    "sg:postcode":"SN9 5DH",
    "sg:province":"Wiltshire",
    "sg:tags":[
        "dresswear"
    ],
    "wof:name":"Change Gear Boutique",
    "wof:placetype":"venue"
},
  "geometry": {"coordinates":[-1.765248,51.339127],"type":"Point"}
}