{
  "type": "Feature",
  "properties": {
    "addr:full":"The Street, Kettleburgh Woodbridge Suffolk IP13 7JT",
    "addr:postcode":"ip13 7jt",
    "addr:street":"The Street",
    "iso:country":"GB",
    "sg:address":"The Street, Kettleburgh",
    "sg:city":"Woodbridge",
    "sg:classifiers":[
        {
            "category":"Restaurant",
            "type":"Food & Drink"
        },
        {
            "category":"Community Center",
            "subcategory":"Social",
            "type":"Public Place"
        }
    ],
    "sg:phone":"+44 1728 723760",
    "sg:postcode":"IP13 7JT",
    "sg:province":"Suffolk",
    "sg:tags":[
        "house",
        "activity"
    ],
    "wof:name":"THE CHEQUERS INN",
    "wof:placetype":"venue"
},
  "geometry": {"coordinates":[1.2946759462,52.1600646973],"type":"Point"}
}