{
  "type": "Feature",
  "properties": {
    "iso:country":"GB",
    "sg:address":"School Lane, Three Legged Cross",
    "sg:city":"Wimborne",
    "sg:classifiers":[
        {
            "category":"Social Services",
            "subcategory":"Retirement Home",
            "type":"Services"
        },
        {
            "category":"Real Estate",
            "subcategory":"Real Estate Agent",
            "type":"Services"
        }
    ],
    "sg:phone":"+44 1202 822561",
    "sg:postcode":"BH21 6RU",
    "sg:province":"Dorset",
    "sg:tags":[
        "rest"
    ],
    "wof:name":"The Cottage Rest Home",
    "wof:placetype":"venue"
},
  "geometry": {"coordinates":[-1.874069,50.846012],"type":"Point"}
}