{
  "type": "Feature",
  "properties": {
    "addr:full":"Po Box 2, Axminster Colyton Devon EX24 6RT",
    "addr:housenumber":"po;2",
    "addr:postcode":"ex24 6rt",
    "addr:street":"Box",
    "iso:country":"GB",
    "sg:address":"Po Box 2, Axminster",
    "sg:city":"Colyton",
    "sg:classifiers":[
        {
            "category":"Shopping",
            "subcategory":"Hobbies, Toys, & Games",
            "type":"Retail Goods"
        },
        {
            "category":"Professional",
            "subcategory":"Art Services",
            "type":"Services"
        }
    ],
    "sg:postcode":"EX24 6RT",
    "sg:province":"Devon",
    "sg:tags":[
        "model",
        "toy",
        "maker"
    ],
    "wof:name":"Austin,David,",
    "wof:placetype":"venue"
},
  "geometry": {"coordinates":[-3.070244,50.740337],"type":"Point"}
}