{
  "type": "Feature",
  "properties": {
    "iso:country":"GB",
    "sg:address":"201 Bridge Road",
    "sg:city":"Wakefield",
    "sg:classifiers":[
        {
            "category":"Bars & Pubs",
            "type":"Food & Drink"
        }
    ],
    "sg:phone":"+44 1924 272795",
    "sg:postcode":"WF4 5PR",
    "sg:province":"West Yorkshire",
    "sg:tags":[
        "pubs",
        "inn"
    ],
    "wof:name":"The Ship Inn",
    "wof:placetype":"venue"
},
  "geometry": {"coordinates":[-1.576856,53.657917],"type":"Point"}
}