{
  "type": "Feature",
  "properties": {
    "addr:full":"18 St Johns Road Edinburgh City of Edinburgh EH12 6NY",
    "addr:housenumber":"18",
    "addr:postcode":"eh12 6ny",
    "addr:street":"St Johns Road",
    "iso:country":"GB",
    "sg:address":"18 St Johns Road",
    "sg:city":"Edinburgh",
    "sg:classifiers":[
        {
            "category":"Travel",
            "subcategory":"Hotels & Motels",
            "type":"Entertainment"
        }
    ],
    "sg:phone":"+44 131 334 7845",
    "sg:postcode":"EH12 6NY",
    "sg:province":"City of Edinburgh",
    "sg:tags":[
        "house",
        "guest"
    ],
    "wof:name":"Tudorbank Lodge",
    "wof:placetype":"venue"
},
  "geometry": {"coordinates":[-3.276271,55.942307],"type":"Point"}
}