{
  "type": "Feature",
  "properties": {
    "addr:full":"Angell Rd London Greater London SW9 7PD",
    "addr:postcode":"sw9 7pd",
    "addr:street":"Angell Rd",
    "iso:country":"GB",
    "sg:address":"Angell Rd",
    "sg:city":"London",
    "sg:classifiers":[
        {
            "category":"Community Center",
            "type":"Public Place"
        }
    ],
    "sg:postcode":"SW9 7PD",
    "sg:province":"Greater London",
    "sg:tags":[
        "centre"
    ],
    "wof:name":"London Borough of Lambeth",
    "wof:placetype":"venue"
},
  "geometry": {"coordinates":[-0.1088259965,51.4676094055],"type":"Point"}
}