{
  "type": "Feature",
  "properties": {
    "addr:full":"5 Welbeck Avenue Bromley Kent BR1 5DN",
    "addr:housenumber":"5",
    "addr:postcode":"br1 5dn",
    "addr:street":"Welbeck Avenue",
    "iso:country":"GB",
    "sg:address":"5 Welbeck Avenue",
    "sg:city":"Bromley",
    "sg:classifiers":[
        {
            "category":"Building & Trades",
            "subcategory":"Plumbing",
            "type":"Services"
        }
    ],
    "sg:postcode":"BR1 5DN",
    "sg:province":"Kent",
    "sg:tags":[
        "heating"
    ],
    "wof:name":"Bromley Plumbing & Heating",
    "wof:placetype":"venue"
},
  "geometry": {"coordinates":[0.020484,51.426437],"type":"Point"}
}