{
  "type": "Feature",
  "properties": {
    "iso:country":"GB",
    "sg:address":"9 Mosslands Drive, Wallasey Village",
    "sg:city":"Wallasey",
    "sg:classifiers":[
        {
            "category":"Building & Trades",
            "subcategory":"Construction",
            "type":"Services"
        }
    ],
    "sg:postcode":"CH45 8PE",
    "sg:province":"Merseyside",
    "sg:tags":[
        "roofing"
    ],
    "wof:name":"A R Povey Roofing",
    "wof:placetype":"venue"
},
  "geometry": {"coordinates":[-3.0672230721,53.4221420288],"type":"Point"}
}