{
  "type": "Feature",
  "properties": {
    "addr:full":"7 Standishgate Wigan Lancashire WN1 1UE",
    "addr:housenumber":"7",
    "addr:postcode":"wn1 1ue",
    "addr:street":"Standishgate Wigan",
    "iso:country":"GB",
    "sg:address":"7 Standishgate",
    "sg:city":"Wigan",
    "sg:classifiers":[
        {
            "category":"Shopping",
            "subcategory":"Baby Store",
            "type":"Retail Goods"
        }
    ],
    "sg:phone":"+44 1942 230121",
    "sg:postcode":"WN1 1UE",
    "sg:province":"Lancashire",
    "sg:tags":[
        "nursery",
        "accessory"
    ],
    "wof:name":"Mothercare Uk",
    "wof:placetype":"venue"
},
  "geometry": {"coordinates":[-2.6306369305,53.5471038818],"type":"Point"}
}