{
  "type": "Feature",
  "properties": {
    "iso:country":"GB",
    "sg:address":"Haugh Rd",
    "sg:city":"Elgin",
    "sg:classifiers":[
        {
            "category":"Government",
            "subcategory":"Fire Station",
            "type":"Public Place"
        }
    ],
    "sg:phone":"+44 1343 542244",
    "sg:postcode":"IV30 1AR",
    "sg:province":"Moray",
    "wof:name":"Grampian Fire Brigade",
    "wof:placetype":"venue"
},
  "geometry": {"coordinates":[-3.317869,57.649368],"type":"Point"}
}