{
  "type": "Feature",
  "properties": {
    "addr:full":"Louisiana Hotel London Greater London N8 0RE",
    "addr:postcode":"n8 0re",
    "iso:country":"GB",
    "sg:address":"Louisiana Hotel",
    "sg:city":"London",
    "sg:classifiers":[
        {
            "category":"Travel",
            "subcategory":"Hostel",
            "type":"Entertainment"
        }
    ],
    "sg:phone":"+44 20 8341 0726",
    "sg:postcode":"N8 0RE",
    "sg:province":"Greater London",
    "wof:name":"Louisianna Properties Ltd.",
    "wof:placetype":"venue"
},
  "geometry": {"coordinates":[-0.1006399989,51.5858383179],"type":"Point"}
}