{
  "type": "Feature",
  "properties": {
    "iso:country":"GB",
    "sg:address":"37a Quebec Road",
    "sg:city":"Dereham",
    "sg:classifiers":[
        {
            "category":"Professional",
            "subcategory":"Engineering",
            "type":"Services"
        },
        {
            "category":"Real Estate",
            "subcategory":"Architect",
            "type":"Services"
        }
    ],
    "sg:phone":"+44 1362 695873",
    "sg:postcode":"NR19 2DR",
    "sg:province":"Norfolk",
    "sg:tags":[
        "civil",
        "engineer"
    ],
    "wof:name":"GADWALL MARINE LTD",
    "wof:placetype":"venue"
},
  "geometry": {"coordinates":[0.939113,52.685425],"type":"Point"}
}