{
  "type": "Feature",
  "properties": {
    "addr:full":"13 Bridge Street, Loddon Norwich Norfolk NR14 6NA",
    "addr:housenumber":"13",
    "addr:postcode":"nr14 6na",
    "addr:street":"Bridge Street;Norwich",
    "iso:country":"GB",
    "sg:address":"13 Bridge Street, Loddon",
    "sg:city":"Norwich",
    "sg:classifiers":[
        {
            "category":"Banks & Credit Unions",
            "subcategory":"Investment Brokerage",
            "type":"Services"
        }
    ],
    "sg:postcode":"NR14 6NA",
    "sg:province":"Norfolk",
    "sg:tags":[
        "contractor"
    ],
    "wof:name":"East Norfolk Machinery Ring Ltd.",
    "wof:placetype":"venue"
},
  "geometry": {"coordinates":[1.4804589748,52.5365333557],"type":"Point"}
}