{
  "type": "Feature",
  "properties": {
    "addr:full":"4 Ladysmith Road Enfield Greater London EN1 3AA",
    "addr:housenumber":"4",
    "addr:postcode":"en1 3aa",
    "addr:street":"Ladysmith Road",
    "iso:country":"GB",
    "sg:address":"4 Ladysmith Road",
    "sg:city":"Enfield",
    "sg:classifiers":[
        {
            "category":"Personal",
            "subcategory":"Beauty Salon",
            "type":"Services"
        }
    ],
    "sg:phone":"+44 20 8367 8402",
    "sg:postcode":"EN1 3AA",
    "sg:province":"Greater London",
    "sg:tags":[
        "unisex",
        "hairdresser"
    ],
    "wof:name":"Night & Day",
    "wof:placetype":"venue"
},
  "geometry": {"coordinates":[-0.073602,51.65247],"type":"Point"}
}