{
  "type": "Feature",
  "properties": {
    "addr:full":"208 Shaw Heath Stockport Cheshire SK2 6QZ",
    "addr:housenumber":"208",
    "addr:postcode":"sk2 6qz",
    "addr:street":"Shaw Heath",
    "iso:country":"GB",
    "sg:address":"208 Shaw Heath",
    "sg:city":"Stockport",
    "sg:classifiers":[
        {
            "category":"Personal",
            "subcategory":"Beauty Salon",
            "type":"Services"
        }
    ],
    "sg:phone":"+44 161 477 7223",
    "sg:postcode":"SK2 6QZ",
    "sg:province":"Cheshire",
    "sg:tags":[
        "unisex",
        "hairdresser"
    ],
    "wof:name":"Changes",
    "wof:placetype":"venue"
},
  "geometry": {"coordinates":[-2.157443,53.397854],"type":"Point"}
}