{
  "type": "Feature",
  "properties": {
    "addr:full":"Haydn Holme, Station Road, Elmesthorpe Leicester Leicestershire LE9 7SG",
    "addr:postcode":"le9 7sg",
    "addr:street":"Station Road",
    "iso:country":"GB",
    "sg:address":"Haydn Holme, Station Road, Elmesthorpe",
    "sg:city":"Leicester",
    "sg:classifiers":[
        {
            "category":"Building & Trades",
            "subcategory":"Landscaping Services",
            "type":"Services"
        }
    ],
    "sg:phone":"+44 1455 842364",
    "sg:postcode":"LE9 7SG",
    "sg:province":"Leicestershire",
    "sg:tags":[
        "landscape",
        "contractor"
    ],
    "wof:name":"W D & B HARDING & SON,",
    "wof:placetype":"venue"
},
  "geometry": {"coordinates":[-1.3090189695,52.559841156],"type":"Point"}
}