{
  "type": "Feature",
  "properties": {
    "iso:country":"GB",
    "sg:address":"89a High Street",
    "sg:city":"Burnham-on-crouch",
    "sg:classifiers":[
        {
            "category":"Health Services",
            "subcategory":"Dentist",
            "type":"Services"
        }
    ],
    "sg:phone":"+44 1621 782644",
    "sg:postcode":"CM0 8AH",
    "sg:province":"Essex",
    "wof:name":"Burnham Dental Practice",
    "wof:placetype":"venue"
},
  "geometry": {"coordinates":[0.82061,51.625103],"type":"Point"}
}