{
  "type": "Feature",
  "properties": {
    "addr:full":"199 Stapleton Rd Bristol City of Bristol BS5 0PA",
    "addr:housenumber":"199",
    "addr:postcode":"bs5 0pa",
    "addr:street":"Stapleton Rd",
    "iso:country":"GB",
    "sg:address":"199 Stapleton Rd",
    "sg:city":"Bristol",
    "sg:classifiers":[
        {
            "category":"Building & Trades",
            "subcategory":"Construction",
            "type":"Services"
        }
    ],
    "sg:phone":"+44 7774 449448",
    "sg:postcode":"BS5 0PA",
    "sg:province":"City of Bristol",
    "sg:tags":[
        "decorator",
        "painter"
    ],
    "wof:name":"Premier Decorators",
    "wof:placetype":"venue"
},
  "geometry": {"coordinates":[-2.5705759525,51.4635772705],"type":"Point"}
}