{
  "type": "Feature",
  "properties": {
    "addr:full":"31 Fishpool Street St. Albans Hertfordshire AL3 4RS",
    "addr:housenumber":"31",
    "addr:postcode":"al3 4rs",
    "addr:street":"Fishpool Street",
    "iso:country":"GB",
    "sg:address":"31 Fishpool Street",
    "sg:city":"St. Albans",
    "sg:classifiers":[
        {
            "category":"Shopping",
            "subcategory":"Photographic Equipment",
            "type":"Retail Goods"
        }
    ],
    "sg:postcode":"AL3 4RS",
    "sg:province":"Hertfordshire",
    "wof:name":"Eis Ltd",
    "wof:placetype":"venue"
},
  "geometry": {"coordinates":[-0.347569,51.751453],"type":"Point"}
}