{
  "type": "Feature",
  "properties": {
    "iso:country":"GB",
    "sg:address":"Apex House, London Road",
    "sg:city":"Bracknell",
    "sg:classifiers":[
        {
            "category":"Professional",
            "subcategory":"Business Services",
            "type":"Services"
        }
    ],
    "sg:phone":"+44 1344 303060",
    "sg:postcode":"RG12 2TE",
    "sg:province":"Berkshire",
    "sg:tags":[
        "accomodation"
    ],
    "wof:name":"Apex House",
    "wof:placetype":"venue"
},
  "geometry": {"coordinates":[-0.7442690134,51.4164619446],"type":"Point"}
}