{
  "type": "Feature",
  "properties": {
    "iso:country":"GB",
    "sg:address":"Chapel House, Chapel Street",
    "sg:city":"Congleton",
    "sg:classifiers":[
        {
            "category":"Organizations",
            "subcategory":"Political Organization",
            "type":"Services"
        }
    ],
    "sg:phone":"+44 1260 297170",
    "sg:postcode":"CW12 4AB",
    "sg:province":"Cheshire",
    "sg:tags":[
        "party"
    ],
    "wof:name":"Congleton Constitutionancy Liberal Democrats",
    "wof:placetype":"venue"
},
  "geometry": {"coordinates":[-2.2116310596,53.1619491577],"type":"Point"}
}