{
  "type": "Feature",
  "properties": {
    "iso:country":"GB",
    "sg:address":"Bryant Avenue, Gallows Corner",
    "sg:city":"Romford",
    "sg:classifiers":[
        {
            "category":"Home & Garden",
            "subcategory":"Home Furnishings",
            "type":"Retail Goods"
        }
    ],
    "sg:phone":"+44 1708 373708",
    "sg:postcode":"RM3 0AP",
    "sg:province":"Essex",
    "sg:tags":[
        "mantelpiece",
        "fireplace"
    ],
    "wof:name":"Roy Blackman Associates",
    "wof:placetype":"venue"
},
  "geometry": {"coordinates":[0.2207,51.588867],"type":"Point"}
}