{
  "type": "Feature",
  "properties": {
    "iso:country":"GB",
    "sg:address":"35 Beachwood Gro, Pencoed",
    "sg:city":"Bridgend",
    "sg:classifiers":[
        {
            "category":"Bus Charters",
            "type":"Transportation"
        }
    ],
    "sg:phone":"+44 1656 862505",
    "sg:postcode":"CF35 6SU",
    "sg:province":"Bridgend",
    "sg:tags":[
        "hire",
        "coach"
    ],
    "wof:name":"Easyway Mini Coach Hire",
    "wof:placetype":"venue"
},
  "geometry": {"coordinates":[-3.4892590046,51.5281295776],"type":"Point"}
}