{
  "type": "Feature",
  "properties": {
    "addr:full":"131 Station Road Addlestone Surrey KT15 2AT",
    "addr:housenumber":"131",
    "addr:postcode":"kt15 2at",
    "addr:street":"Station Road",
    "iso:country":"GB",
    "sg:address":"131 Station Road",
    "sg:city":"Addlestone",
    "sg:classifiers":[
        {
            "category":"Fast Food",
            "type":"Food & Drink"
        }
    ],
    "sg:phone":"+44 1932 842200",
    "sg:postcode":"KT15 2AT",
    "sg:province":"Surrey",
    "sg:tags":[
        "away",
        "meal",
        "outlet",
        "take"
    ],
    "wof:name":"J B Takeout",
    "wof:placetype":"venue"
},
  "geometry": {"coordinates":[-0.486936,51.371838],"type":"Point"}
}