{
  "type": "Feature",
  "properties": {
    "iso:country":"GB",
    "sg:address":"159 Clarendon Park Road",
    "sg:city":"Leicester",
    "sg:classifiers":[
        {
            "category":"Personal",
            "type":"Services"
        },
        {
            "category":"Government",
            "subcategory":"Customs House",
            "type":"Public Place"
        }
    ],
    "sg:phone":"+44 116 270 2022",
    "sg:postcode":"LE2 3AJ",
    "sg:province":"Leicestershire",
    "sg:tags":[
        "clearance"
    ],
    "wof:name":"P L Corrall",
    "wof:placetype":"venue"
},
  "geometry": {"coordinates":[-1.1183179617,52.6165847778],"type":"Point"}
}