{
  "type": "Feature",
  "properties": {
    "addr:full":"153 Quarry Street Hamilton South Lanarkshire ML3 7HR",
    "addr:housenumber":"153",
    "addr:postcode":"ml3 7hr",
    "addr:street":"Quarry Street",
    "iso:country":"GB",
    "sg:address":"153 Quarry Street",
    "sg:city":"Hamilton",
    "sg:classifiers":[
        {
            "category":"Professional",
            "subcategory":"Lawyer & Legal Services",
            "type":"Services"
        }
    ],
    "sg:postcode":"ML3 7HR",
    "sg:province":"South Lanarkshire",
    "sg:tags":[
        "solicitor"
    ],
    "wof:name":"Neil Coats & Co",
    "wof:placetype":"venue"
},
  "geometry": {"coordinates":[-4.037549,55.772919],"type":"Point"}
}