{
  "type": "Feature",
  "properties": {
    "iso:country":"GB",
    "sg:address":"938 Brighton Road",
    "sg:city":"Purley",
    "sg:classifiers":[
        {
            "category":"Banks & Credit Unions",
            "subcategory":"Bank",
            "type":"Services"
        }
    ],
    "sg:phone":"+44 20 8668 5471",
    "sg:postcode":"CR8 2LP",
    "sg:province":"Surrey",
    "wof:name":"Abbey National Plc",
    "wof:placetype":"venue"
},
  "geometry": {"coordinates":[-0.116128,51.33926],"type":"Point"}
}