{
  "type": "Feature",
  "properties": {
    "iso:country":"GB",
    "sg:address":"174 High Street, Lye",
    "sg:city":"Stourbridge",
    "sg:classifiers":[
        {
            "category":"Restaurant",
            "type":"Food & Drink"
        }
    ],
    "sg:phone":"+44 1384 891111",
    "sg:postcode":"DY9 8LN",
    "sg:province":"West Midlands",
    "sg:tags":[
        "indian"
    ],
    "wof:name":"Margala Point",
    "wof:placetype":"venue"
},
  "geometry": {"coordinates":[-2.114055,52.457039],"type":"Point"}
}