{
  "type": "Feature",
  "properties": {
    "addr:full":"100 Thornhill Road Falkirk Falkirk FK2 7AE",
    "addr:housenumber":"100",
    "addr:postcode":"fk2 7ae",
    "addr:street":"Thornhill Road",
    "iso:country":"GB",
    "sg:address":"100 Thornhill Road",
    "sg:city":"Falkirk",
    "sg:classifiers":[
        {
            "category":"Bars & Pubs",
            "type":"Food & Drink"
        }
    ],
    "sg:phone":"+44 1324 611068",
    "sg:postcode":"FK2 7AE",
    "sg:province":"Falkirk",
    "sg:tags":[
        "pubs",
        "inn"
    ],
    "wof:name":"The Gordon Lounge",
    "wof:placetype":"venue"
},
  "geometry": {"coordinates":[-3.7732830048,56.0034637451],"type":"Point"}
}