{
  "type": "Feature",
  "properties": {
    "addr:full":"Church Drove, Outwell Wisbech Cambridgeshire PE14 8RH",
    "addr:postcode":"pe14 8rh",
    "addr:street":"Church",
    "iso:country":"GB",
    "sg:address":"Church Drove, Outwell",
    "sg:city":"Wisbech",
    "sg:classifiers":[
        {
            "category":"Education",
            "subcategory":"School",
            "type":"Public Place"
        }
    ],
    "sg:phone":"+44 1945 772439",
    "sg:postcode":"PE14 8RH",
    "sg:province":"Cambridgeshire",
    "sg:tags":[
        "local",
        "authority"
    ],
    "wof:name":"Beaupre School",
    "wof:placetype":"venue"
},
  "geometry": {"coordinates":[0.2292030007,52.606464386],"type":"Point"}
}