{
  "type": "Feature",
  "properties": {
    "addr:full":"159 Kenmure Street Glasgow Glasgow City G41 2LE",
    "addr:housenumber":"159",
    "addr:postcode":"g41 2le",
    "addr:street":"Kenmure Street",
    "iso:country":"GB",
    "sg:address":"159 Kenmure Street",
    "sg:city":"Glasgow",
    "sg:classifiers":[
        {
            "category":"Wholesale",
            "subcategory":"Meat",
            "type":"Manufacturing & Wholesale Goods"
        }
    ],
    "sg:postcode":"G41 2LE",
    "sg:province":"Glasgow City",
    "sg:tags":[
        "-"
    ],
    "wof:name":"Sabir Bros Halal Meat",
    "wof:placetype":"venue"
},
  "geometry": {"coordinates":[-4.2726979256,55.8420639038],"type":"Point"}
}