{
  "type": "Feature",
  "properties": {
    "addr:full":"The Crypt St Johns Church, 200 Cambridge Heath Road London Greater London E2 9PA",
    "addr:housenumber":"200",
    "addr:postcode":"e2 9pa",
    "addr:street":"St;Cambridge Heath Road",
    "iso:country":"GB",
    "sg:address":"The Crypt St Johns Church, 200 Cambridge Heath Road",
    "sg:city":"London",
    "sg:classifiers":[
        {
            "category":"Education",
            "subcategory":"School",
            "type":"Public Place"
        }
    ],
    "sg:phone":"+44 20 8980 5881",
    "sg:postcode":"E2 9PA",
    "sg:province":"Greater London",
    "sg:tags":[
        "local",
        "authority"
    ],
    "wof:name":"Education & Training Consortium",
    "wof:placetype":"venue"
},
  "geometry": {"coordinates":[-0.05537,51.527748],"type":"Point"}
}