{
  "type": "Feature",
  "properties": {
    "addr:full":"138 Manchester Road, Swinton Manchester Greater Manchester M27 5EP",
    "addr:housenumber":"138",
    "addr:postcode":"m27 5ep",
    "addr:street":"Manchester Road",
    "iso:country":"GB",
    "sg:address":"138 Manchester Road, Swinton",
    "sg:city":"Manchester",
    "sg:classifiers":[
        {
            "category":"Travel",
            "subcategory":"Hotels & Motels",
            "type":"Entertainment"
        }
    ],
    "sg:postcode":"M27 5EP",
    "sg:province":"Greater Manchester",
    "wof:name":"Cordells",
    "wof:placetype":"venue"
},
  "geometry": {"coordinates":[-2.3258080482,53.5073280334],"type":"Point"}
}