{
  "type": "Feature",
  "properties": {
    "addr:full":"42 Market Street Wirral Merseyside CH47 2AF",
    "addr:housenumber":"42",
    "addr:postcode":"ch47 2af",
    "addr:street":"Market Street",
    "iso:country":"GB",
    "sg:address":"42 Market Street",
    "sg:city":"Wirral",
    "sg:classifiers":[
        {
            "category":"Retail",
            "subcategory":"Laundry & Dry Cleaning",
            "type":"Services"
        }
    ],
    "sg:phone":"+44 151 632 3916",
    "sg:postcode":"CH47 2AF",
    "sg:province":"Merseyside",
    "sg:tags":[
        "launderette"
    ],
    "wof:name":"Hoylake Washeteria",
    "wof:placetype":"venue"
},
  "geometry": {"coordinates":[-3.1775729656,53.3920593262],"type":"Point"}
}