{
  "type": "Feature",
  "properties": {
    "iso:country":"GB",
    "sg:address":"Unit 13 Brake Shear House, 164 High Street",
    "sg:city":"Barnet",
    "sg:classifiers":[
        {
            "category":"Professional",
            "subcategory":"Management & Consulting",
            "type":"Services"
        }
    ],
    "sg:phone":"+44 20 8440 0144",
    "sg:postcode":"EN5 5XP",
    "sg:province":"Hertfordshire",
    "sg:tags":[
        "marketing",
        "consultant"
    ],
    "wof:name":"Adept Marketing Ltd.",
    "wof:placetype":"venue"
},
  "geometry": {"coordinates":[-0.2016119957,51.6554107666],"type":"Point"}
}