{
  "type": "Feature",
  "properties": {
    "addr:full":"Unit 11 Maidenhead Berkshire SL6 8DP",
    "addr:housenumber":"unit 11",
    "addr:postcode":"sl6 8dp",
    "iso:country":"GB",
    "sg:address":"Unit 11",
    "sg:city":"Maidenhead",
    "sg:classifiers":[
        {
            "category":"Building & Trades",
            "subcategory":"Landscaping Services",
            "type":"Services"
        }
    ],
    "sg:postcode":"SL6 8DP",
    "sg:province":"Berkshire",
    "sg:tags":[
        "gardening"
    ],
    "wof:name":"The Natural Group",
    "wof:placetype":"venue"
},
  "geometry": {"coordinates":[-0.727257,51.522373],"type":"Point"}
}