{
  "type": "Feature",
  "properties": {
    "addr:full":"Thornes Wharf Lane Wakefield West Yorkshire WF1 5RQ",
    "addr:postcode":"wf1 5rq",
    "addr:street":"Thornes Wharf Lane",
    "iso:country":"GB",
    "sg:address":"Thornes Wharf Lane",
    "sg:city":"Wakefield",
    "sg:classifiers":[
        {
            "category":"Shopping",
            "subcategory":"Clothing, Apparel, & Fashions",
            "type":"Retail Goods"
        }
    ],
    "sg:phone":"+44 1924 375951",
    "sg:postcode":"WF1 5RQ",
    "sg:province":"West Yorkshire",
    "sg:tags":[
        "mnfr",
        "protective",
        "uniform",
        "wear",
        "workwear",
        "staff"
    ],
    "wof:name":"Wm Sugden & Sons Ltd.",
    "wof:placetype":"venue"
},
  "geometry": {"coordinates":[-1.49359,53.674721],"type":"Point"}
}