{
  "type": "Feature",
  "properties": {
    "iso:country":"GB",
    "sg:address":"94 Town Street, Horsforth",
    "sg:city":"Leeds",
    "sg:classifiers":[
        {
            "category":"Real Estate",
            "subcategory":"Surveying",
            "type":"Services"
        }
    ],
    "sg:phone":"+44 113 281 8273",
    "sg:postcode":"LS18 4AP",
    "sg:province":"West Yorkshire",
    "sg:tags":[
        "building",
        "surveyor"
    ],
    "wof:name":"Lawson & Co.",
    "wof:placetype":"venue"
},
  "geometry": {"coordinates":[-1.639478,53.838581],"type":"Point"}
}