{
  "type": "Feature",
  "properties": {
    "iso:country":"GB",
    "sg:address":"Castle Precinct",
    "sg:city":"Knaresborough",
    "sg:classifiers":[
        {
            "category":"Professional",
            "subcategory":"Accounting & Tax Preparation",
            "type":"Services"
        }
    ],
    "sg:postcode":"HG5 8AS",
    "sg:province":"North Yorkshire",
    "sg:tags":[
        "accountant"
    ],
    "wof:name":"Colman,Robert,",
    "wof:placetype":"venue"
},
  "geometry": {"coordinates":[-1.4690070152,54.00522995],"type":"Point"}
}