{
  "type": "Feature",
  "properties": {
    "addr:full":"17 Ulwell Road Swanage Dorset BH19 1LF",
    "addr:housenumber":"17",
    "addr:postcode":"bh19 1lf",
    "addr:street":"Ulwell Road",
    "iso:country":"GB",
    "sg:address":"17 Ulwell Road",
    "sg:city":"Swanage",
    "sg:classifiers":[
        {
            "category":"Travel",
            "subcategory":"Hotels & Motels",
            "type":"Entertainment"
        }
    ],
    "sg:phone":"+44 1929 422887",
    "sg:postcode":"BH19 1LF",
    "sg:province":"Dorset",
    "wof:name":"Tower Lodge Private Hotel",
    "wof:placetype":"venue"
},
  "geometry": {"coordinates":[-1.9586420059,50.6188316345],"type":"Point"}
}