{
  "type": "Feature",
  "properties": {
    "addr:full":"Unit 2 Hanson Road, Aintree Industrial Estate Liverpool Merseyside L9 7BP",
    "addr:housenumber":"unit 2",
    "addr:postcode":"l9 7bp",
    "addr:street":"Hanson Road Aintree Industrial Estate",
    "iso:country":"GB",
    "sg:address":"Unit 2 Hanson Road, Aintree Industrial Estate",
    "sg:city":"Liverpool",
    "sg:classifiers":[
        {
            "category":"Wholesale",
            "subcategory":"Scrap",
            "type":"Manufacturing & Wholesale Goods"
        }
    ],
    "sg:postcode":"L9 7BP",
    "sg:province":"Merseyside",
    "sg:tags":[
        "breaker",
        "dismantlers"
    ],
    "wof:name":"Brookfield Salvage",
    "wof:placetype":"venue"
},
  "geometry": {"coordinates":[-2.944011,53.458344],"type":"Point"}
}