{
  "type": "Feature",
  "properties": {
    "addr:full":"P O Box 7 Holsworthy Cornwall EX22 7ZA",
    "addr:housenumber":"7",
    "addr:postcode":"ex22 7za",
    "addr:street":"P O Box",
    "iso:country":"GB",
    "sg:address":"P O Box 7",
    "sg:city":"Holsworthy",
    "sg:classifiers":[
        {
            "category":"Professional",
            "subcategory":"Computer Services",
            "type":"Services"
        }
    ],
    "sg:phone":"+44 1409 241294",
    "sg:postcode":"EX22 7ZA",
    "sg:province":"Cornwall",
    "sg:tags":[
        "system",
        "software"
    ],
    "wof:name":"European Solutions Ltd.",
    "wof:placetype":"venue"
},
  "geometry": {"coordinates":[-4.3462238312,50.8628768921],"type":"Point"}
}