{
  "type": "Feature",
  "properties": {
    "addr:full":"139 The Harlequin Watford Hertfordshire WD17 2TL",
    "addr:housenumber":"139",
    "addr:postcode":"wd17 2tl",
    "addr:street":"The Harlequin",
    "iso:country":"GB",
    "sg:address":"139 The Harlequin",
    "sg:city":"Watford",
    "sg:classifiers":[
        {
            "category":"Shopping",
            "subcategory":"Luggage & Leather Goods",
            "type":"Retail Goods"
        }
    ],
    "sg:postcode":"WD17 2TL",
    "sg:province":"Hertfordshire",
    "sg:tags":[
        "shop",
        "leathergoods"
    ],
    "wof:name":"The Bag Boutique",
    "wof:placetype":"venue"
},
  "geometry": {"coordinates":[-0.393678993,51.6549987793],"type":"Point"}
}