{
  "type": "Feature",
  "properties": {
    "addr:full":"Stephenson Close Daventry Northamptonshire NN11 5RF",
    "addr:postcode":"nn11 5rf",
    "addr:street":"Stephenson Close",
    "iso:country":"GB",
    "sg:address":"Stephenson Close",
    "sg:city":"Daventry",
    "sg:classifiers":[
        {
            "category":"Organizations",
            "subcategory":"Membership Organization",
            "type":"Services"
        }
    ],
    "sg:phone":"+44 1327 312233",
    "sg:postcode":"NN11 5RF",
    "sg:province":"Northamptonshire",
    "sg:tags":[
        "club"
    ],
    "wof:name":"Truck Stop Supply Co. Ltd.",
    "wof:placetype":"venue"
},
  "geometry": {"coordinates":[-1.1622389555,52.260433197],"type":"Point"}
}