{
  "type": "Feature",
  "properties": {
    "iso:country":"GB",
    "sg:address":"Hob Farm, Gorsey Bank, Wirksworth",
    "sg:city":"Matlock",
    "sg:classifiers":[
        {
            "category":"Farming",
            "subcategory":"Livestock Farm",
            "type":"Manufacturing & Wholesale Goods"
        }
    ],
    "sg:phone":"+44 1629 822592",
    "sg:postcode":"DE4 4AD",
    "sg:province":"Derbyshire",
    "sg:tags":[
        "others"
    ],
    "wof:name":"Philip Wood",
    "wof:placetype":"venue"
},
  "geometry": {"coordinates":[-1.574056,53.082214],"type":"Point"}
}