{
  "type": "Feature",
  "properties": {
    "iso:country":"GB",
    "sg:address":"46 West Street",
    "sg:city":"Chichester",
    "sg:classifiers":[
        {
            "category":"Shopping",
            "subcategory":"Books",
            "type":"Retail Goods"
        }
    ],
    "sg:phone":"+44 1243 782700",
    "sg:postcode":"PO19 1RP",
    "sg:province":"West Sussex",
    "wof:name":"Prospero Books",
    "wof:placetype":"venue"
},
  "geometry": {"coordinates":[-0.783306,50.836761],"type":"Point"}
}