{
  "type": "Feature",
  "properties": {
    "iso:country":"GB",
    "sg:address":"Old Town Hall, Albion Street",
    "sg:city":"Brighton",
    "sg:classifiers":[
        {
            "category":"Banks & Credit Unions",
            "subcategory":"Financial Services",
            "type":"Services"
        }
    ],
    "sg:phone":"+44 1273 596633",
    "sg:postcode":"BN42 4AX",
    "sg:province":"West Sussex",
    "sg:tags":[
        "consultant"
    ],
    "wof:name":"Wellesley Associates",
    "wof:placetype":"venue"
},
  "geometry": {"coordinates":[-0.2350399941,50.8314704895],"type":"Point"}
}