{
  "type": "Feature",
  "properties": {
    "iso:country":"GB",
    "sg:address":"28 Devonshire Street",
    "sg:city":"Keighley",
    "sg:classifiers":[
        {
            "category":"Banks & Credit Unions",
            "subcategory":"Financial Services",
            "type":"Services"
        }
    ],
    "sg:phone":"+44 1535 681392",
    "sg:postcode":"BD21 2AU",
    "sg:province":"West Yorkshire",
    "sg:tags":[
        "adviser"
    ],
    "wof:name":"Yorkshire Financial Clinics Ltd.",
    "wof:placetype":"venue"
},
  "geometry": {"coordinates":[-1.911697,53.867661],"type":"Point"}
}