{
  "type": "Feature",
  "properties": {
    "iso:country":"GB",
    "sg:address":"Bibsworth Avenue",
    "sg:city":"Broadway",
    "sg:classifiers":[
        {
            "category":"Food & Beverages",
            "subcategory":"Supermarket",
            "type":"Retail Goods"
        }
    ],
    "sg:phone":"+44 1386 852202",
    "sg:postcode":"WR12 7BH",
    "sg:province":"Gloucestershire",
    "wof:name":"Millner Spa",
    "wof:placetype":"venue"
},
  "geometry": {"coordinates":[-1.8528079987,52.0401535034],"type":"Point"}
}