{
  "type": "Feature",
  "properties": {
    "iso:country":"GB",
    "sg:address":", Shawford",
    "sg:city":"Winchester",
    "sg:classifiers":[
        {
            "category":"Social Services",
            "subcategory":"Retirement Home",
            "type":"Services"
        }
    ],
    "sg:phone":"+44 1962 713242",
    "sg:postcode":"SO21 2AG",
    "sg:province":"Hampshire",
    "sg:tags":[
        "residential",
        "care"
    ],
    "wof:name":"Brackenlea Rest Home",
    "wof:placetype":"venue"
},
  "geometry": {"coordinates":[-1.321032,51.020813],"type":"Point"}
}