{
  "type": "Feature",
  "properties": {
    "addr:full":"D Floor, Milburn House Newcastle-upon-tyne Tyne and Wear NE1 1PQ",
    "addr:housenumber":"d;milburn",
    "addr:postcode":"ne1 1pq",
    "iso:country":"GB",
    "sg:address":"D Floor, Milburn House",
    "sg:city":"Newcastle-upon-tyne",
    "sg:classifiers":[
        {
            "category":"Professional",
            "subcategory":"Employment Agencies",
            "type":"Services"
        }
    ],
    "sg:postcode":"NE1 1PQ",
    "sg:province":"Tyne and Wear",
    "sg:tags":[
        "career",
        "guidance"
    ],
    "wof:name":"Mary C L Hunter",
    "wof:placetype":"venue"
},
  "geometry": {"coordinates":[-1.609940052,54.9701194763],"type":"Point"}
}