{
  "type": "Feature",
  "properties": {
    "addr:full":"5-7 Fore Street Port Glasgow Inverclyde PA14 5EE",
    "addr:housenumber":"5-7",
    "addr:postcode":"pa14 5ee",
    "addr:street":"Fore Street",
    "iso:country":"GB",
    "sg:address":"5-7 Fore Street",
    "sg:city":"Port Glasgow",
    "sg:classifiers":[
        {
            "category":"Government",
            "subcategory":"Post Office",
            "type":"Public Place"
        }
    ],
    "sg:phone":"+44 1475 743637",
    "sg:postcode":"PA14 5EE",
    "sg:province":"Inverclyde",
    "wof:name":"Port Glasgow M S Post Office",
    "wof:placetype":"venue"
},
  "geometry": {"coordinates":[-4.6800889969,55.9322395325],"type":"Point"}
}