{
  "type": "Feature",
  "properties": {
    "iso:country":"GB",
    "sg:address":"3 Rosebriar Clo, Pyrford Rd",
    "sg:city":"Woking",
    "sg:classifiers":[
        {
            "category":"Professional",
            "subcategory":"Accounting & Tax Preparation",
            "type":"Services"
        }
    ],
    "sg:phone":"+44 1932 353102",
    "sg:postcode":"GU22 8TY",
    "sg:province":"Surrey",
    "sg:tags":[
        "accountant"
    ],
    "wof:name":"Byrne D.F. & Co Chartered Accountants",
    "wof:placetype":"venue"
},
  "geometry": {"coordinates":[-0.502165,51.323727],"type":"Point"}
}