{
  "type": "Feature",
  "properties": {
    "addr:full":"Unit 5 Whitefield, Lepe Road Southampton Hampshire SO45 1XR",
    "addr:housenumber":"unit 5",
    "addr:postcode":"so45 1xr",
    "addr:street":"Lepe Road",
    "iso:country":"GB",
    "sg:address":"Unit 5 Whitefield, Lepe Road",
    "sg:city":"Southampton",
    "sg:classifiers":[
        {
            "category":"Manufacturing",
            "subcategory":"Motor Vehicles & Parts",
            "type":"Manufacturing & Wholesale Goods"
        }
    ],
    "sg:phone":"+44 23 8089 2858",
    "sg:postcode":"SO45 1XR",
    "sg:province":"Hampshire",
    "sg:tags":[
        "machine",
        "shop"
    ],
    "wof:name":"Elite Fabrications",
    "wof:placetype":"venue"
},
  "geometry": {"coordinates":[-1.3671699762,50.8065605164],"type":"Point"}
}