{
  "type": "Feature",
  "properties": {
    "addr:full":"28 Wolseley Gardens, Grove Park Chiswick Greater London W4 3LR",
    "addr:housenumber":"28",
    "addr:postcode":"w4 3lr",
    "addr:street":"Wolseley Gardens",
    "iso:country":"GB",
    "sg:address":"28 Wolseley Gardens, Grove Park",
    "sg:city":"Chiswick",
    "sg:classifiers":[
        {
            "category":"Professional",
            "subcategory":"Engineering",
            "type":"Services"
        }
    ],
    "sg:phone":"+44 20 8747 8378",
    "sg:postcode":"W4 3LR",
    "sg:province":"Greater London",
    "sg:tags":[
        "contractor",
        "electrical",
        "engineer"
    ],
    "wof:name":"Direct Current",
    "wof:placetype":"venue"
},
  "geometry": {"coordinates":[-0.274773,51.487713],"type":"Point"}
}