{
  "type": "Feature",
  "properties": {
    "iso:country":"GB",
    "sg:address":"7 Ivy Street",
    "sg:city":"Salisbury",
    "sg:classifiers":[
        {
            "category":"Shopping",
            "subcategory":"Florist",
            "type":"Retail Goods"
        }
    ],
    "sg:phone":"+44 1722 327537",
    "sg:postcode":"SP1 2AY",
    "sg:province":"Wiltshire",
    "wof:name":"Mayfair Flowers",
    "wof:placetype":"venue"
},
  "geometry": {"coordinates":[-1.7931530476,51.0667877197],"type":"Point"}
}