{
  "type": "Feature",
  "properties": {
    "addr:full":"Ham Grn Garage, Ham Grn Trowbridge Wiltshire BA14 6PX",
    "addr:postcode":"ba14 6px",
    "addr:street":"Ham;Ham Grn",
    "iso:country":"GB",
    "sg:address":"Ham Grn Garage, Ham Grn",
    "sg:city":"Trowbridge",
    "sg:classifiers":[
        {
            "category":"Autos & Motor Vehicles",
            "subcategory":"Automobile Sales",
            "type":"Retail Goods"
        },
        {
            "category":"Retail",
            "subcategory":"Auto Repair",
            "type":"Services"
        }
    ],
    "sg:postcode":"BA14 6PX",
    "sg:province":"Wiltshire",
    "sg:tags":[
        "modification",
        "garage",
        "car"
    ],
    "wof:name":"White,Stuart,",
    "wof:placetype":"venue"
},
  "geometry": {"coordinates":[-2.2083740234,51.3153419495],"type":"Point"}
}