{
  "type": "Feature",
  "properties": {
    "iso:country":"GB",
    "sg:address":"9 Algitha Road",
    "sg:city":"Skegness",
    "sg:classifiers":[
        {
            "category":"Travel",
            "subcategory":"Hotels & Motels",
            "type":"Entertainment"
        }
    ],
    "sg:postcode":"PE25 2AG",
    "sg:province":"Lincolnshire",
    "wof:name":"The Shires Hotel",
    "wof:placetype":"venue"
},
  "geometry": {"coordinates":[0.337351,53.144375],"type":"Point"}
}