{
  "type": "Feature",
  "properties": {
    "addr:full":"Lords Hill Farm, Appletree Lane, Inkberrow Worcester Worcestershire WR7 4JA",
    "addr:postcode":"wr7 4ja",
    "addr:street":"Lords Hill;Appletree Lane",
    "iso:country":"GB",
    "sg:address":"Lords Hill Farm, Appletree Lane, Inkberrow",
    "sg:city":"Worcester",
    "sg:classifiers":[
        {
            "category":"Farming",
            "subcategory":"Poultry Farm",
            "type":"Manufacturing & Wholesale Goods"
        }
    ],
    "sg:phone":"+44 1386 793357",
    "sg:postcode":"WR7 4JA",
    "sg:province":"Worcestershire",
    "sg:tags":[
        "game"
    ],
    "wof:name":"A R & J S Jordon",
    "wof:placetype":"venue"
},
  "geometry": {"coordinates":[-1.980557,52.21323],"type":"Point"}
}