{
  "type": "Feature",
  "properties": {
    "iso:country":"GB",
    "sg:address":"17 Awliscombe Rd",
    "sg:city":"Welling",
    "sg:classifiers":[
        {
            "category":"Retail",
            "subcategory":"Driving School",
            "type":"Services"
        }
    ],
    "sg:phone":"+44 20 8855 8577",
    "sg:postcode":"DA16 3JT",
    "sg:province":"Kent",
    "wof:name":"Learn & Advance Driving Academy",
    "wof:placetype":"venue"
},
  "geometry": {"coordinates":[0.099578999,51.4678726196],"type":"Point"}
}