{
  "type": "Feature",
  "properties": {
    "addr:full":"4 Little Langlands, East Hagbourne Didcot Oxfordshire OX11 9TA",
    "addr:housenumber":"4",
    "addr:postcode":"ox11 9ta",
    "addr:street":"Little Langlands East",
    "iso:country":"GB",
    "sg:address":"4 Little Langlands, East Hagbourne",
    "sg:city":"Didcot",
    "sg:classifiers":[
        {
            "category":"Building & Trades",
            "subcategory":"Construction",
            "type":"Services"
        }
    ],
    "sg:phone":"+44 1235 817897",
    "sg:postcode":"OX11 9TA",
    "sg:province":"Oxfordshire",
    "sg:tags":[
        "excavation",
        "specialised",
        "groundwork",
        "contractor"
    ],
    "wof:name":"Buckle & Davies Construction Ltd.",
    "wof:placetype":"venue"
},
  "geometry": {"coordinates":[-1.235279,51.593037],"type":"Point"}
}