{
  "type": "Feature",
  "properties": {
    "addr:full":"5-9 Main Street, New Deer Turriff Aberdeenshire AB53 6TA",
    "addr:housenumber":"5-9",
    "addr:postcode":"ab53 6ta",
    "addr:street":"Main Street",
    "iso:country":"GB",
    "sg:address":"5-9 Main Street, New Deer",
    "sg:city":"Turriff",
    "sg:classifiers":[
        {
            "category":"Personal",
            "subcategory":"Beauty Salon",
            "type":"Services"
        }
    ],
    "sg:phone":"+44 1771 644796",
    "sg:postcode":"AB53 6TA",
    "sg:province":"Aberdeenshire",
    "sg:tags":[
        "unisex",
        "hairdresser"
    ],
    "wof:name":"Catherine's Hair & Beauty",
    "wof:placetype":"venue"
},
  "geometry": {"coordinates":[-2.193217,57.512196],"type":"Point"}
}