{
  "type": "Feature",
  "properties": {
    "iso:country":"GB",
    "sg:address":"55 Pinkneys Road",
    "sg:city":"Maidenhead",
    "sg:classifiers":[
        {
            "category":"Professional",
            "subcategory":"Computer Services",
            "type":"Services"
        }
    ],
    "sg:postcode":"SL6 5DX",
    "sg:province":"Berkshire",
    "sg:tags":[
        "system",
        "software"
    ],
    "wof:name":"David Cownley Associates Ltd.",
    "wof:placetype":"venue"
},
  "geometry": {"coordinates":[-0.756741,51.527317],"type":"Point"}
}