{
  "type": "Feature",
  "properties": {
    "addr:full":"17 Cirencester St Bayswater Greater London W2 5SR",
    "addr:housenumber":"17",
    "addr:postcode":"w2 5sr",
    "addr:street":"Cirencester St",
    "iso:country":"GB",
    "sg:address":"17 Cirencester St",
    "sg:city":"Bayswater",
    "sg:classifiers":[
        {
            "category":"Place Of Worship",
            "type":"Public Place"
        }
    ],
    "sg:phone":"+44 20 7286 2672",
    "sg:postcode":"W2 5SR",
    "sg:province":"Greater London",
    "wof:name":"Our Lady Of Sorrows R C Church",
    "wof:placetype":"venue"
},
  "geometry": {"coordinates":[-0.191331,51.521439],"type":"Point"}
}