{
  "type": "Feature",
  "properties": {
    "addr:full":"28 Bridge Street Belper Derbyshire DE56 1AX",
    "addr:housenumber":"28",
    "addr:postcode":"de56 1ax",
    "addr:street":"Bridge Street",
    "iso:country":"GB",
    "sg:address":"28 Bridge Street",
    "sg:city":"Belper",
    "sg:classifiers":[
        {
            "category":"Personal",
            "subcategory":"Beauty Salon",
            "type":"Services"
        }
    ],
    "sg:phone":"+44 1773 824085",
    "sg:postcode":"DE56 1AX",
    "sg:province":"Derbyshire",
    "sg:tags":[
        "unisex",
        "hairdresser"
    ],
    "wof:name":"Richard Leonard",
    "wof:placetype":"venue"
},
  "geometry": {"coordinates":[-1.484968,53.025063],"type":"Point"}
}