{
  "type": "Feature",
  "properties": {
    "addr:full":"Broughton House, Norton Lane, Chew Magna Bristol Somerset BS40 8RW",
    "addr:postcode":"bs40 8rw",
    "addr:street":"Norton Lane",
    "iso:country":"GB",
    "sg:address":"Broughton House, Norton Lane, Chew Magna",
    "sg:city":"Bristol",
    "sg:classifiers":[
        {
            "category":"Professional",
            "subcategory":"Engineering",
            "type":"Services"
        }
    ],
    "sg:phone":"+44 1275 333025",
    "sg:postcode":"BS40 8RW",
    "sg:province":"Somerset",
    "sg:tags":[
        "contractor",
        "electrical",
        "engineer"
    ],
    "wof:name":"A J Electrical",
    "wof:placetype":"venue"
},
  "geometry": {"coordinates":[-2.598569,51.372456],"type":"Point"}
}