{
  "type": "Feature",
  "properties": {
    "addr:full":"9 Ealing Broadway Centre, The Bdwy London Greater London W5 5JY",
    "addr:housenumber":"9",
    "addr:postcode":"w5 5jy",
    "addr:street":"Ealing",
    "iso:country":"GB",
    "sg:address":"9 Ealing Broadway Centre, The Bdwy",
    "sg:city":"London",
    "sg:classifiers":[
        {
            "category":"Shopping",
            "subcategory":"Gifts & Souvenirs",
            "type":"Retail Goods"
        }
    ],
    "sg:phone":"+44 20 8840 9829",
    "sg:postcode":"W5 5JY",
    "sg:province":"Greater London",
    "sg:tags":[
        "shop"
    ],
    "wof:name":"Wax Lyrical Ltd.",
    "wof:placetype":"venue"
},
  "geometry": {"coordinates":[-0.3070600033,51.5037689209],"type":"Point"}
}