{
  "type": "Feature",
  "properties": {
    "iso:country":"GB",
    "sg:address":"Coronation St",
    "sg:city":"Stockport",
    "sg:classifiers":[
        {
            "category":"Place Of Worship",
            "type":"Public Place"
        }
    ],
    "sg:phone":"+44 161 483 5674",
    "sg:postcode":"SK5 7PG",
    "sg:province":"Cheshire",
    "wof:name":"Seventh Day Adventist Church",
    "wof:placetype":"venue"
},
  "geometry": {"coordinates":[-2.162294,53.421856],"type":"Point"}
}