{
  "type": "Feature",
  "properties": {
    "addr:full":"75 Station Road, Chingford London Greater London E4 7BU",
    "addr:housenumber":"75",
    "addr:postcode":"e4 7bu",
    "addr:street":"Station Road",
    "iso:country":"GB",
    "sg:address":"75 Station Road, Chingford",
    "sg:city":"London",
    "sg:classifiers":[
        {
            "category":"Food & Beverages",
            "subcategory":"Liquor & Beverages",
            "type":"Retail Goods"
        }
    ],
    "sg:phone":"+44 20 8529 1192",
    "sg:postcode":"E4 7BU",
    "sg:province":"Greater London",
    "sg:tags":[
        "beer",
        "spirit",
        "wines"
    ],
    "wof:name":"Wine Rack",
    "wof:placetype":"venue"
},
  "geometry": {"coordinates":[0.006,51.63203],"type":"Point"}
}