{
  "type": "Feature",
  "properties": {
    "addr:full":"Pine View, California Lane, Bushey Watford Hertfordshire WD2 31ES",
    "addr:postcode":"wd2 31es",
    "addr:street":"View California Lane",
    "iso:country":"GB",
    "sg:address":"Pine View, California Lane, Bushey",
    "sg:city":"Watford",
    "sg:classifiers":[
        {
            "category":"Professional",
            "type":"Services"
        }
    ],
    "sg:phone":"+44 20 8950 0571",
    "sg:postcode":"WD2 31ES",
    "sg:province":"Hertfordshire",
    "sg:tags":[
        "auctioneer"
    ],
    "wof:name":"Rabbow & Co",
    "wof:placetype":"venue"
},
  "geometry": {"coordinates":[-0.343524009,51.6350746155],"type":"Point"}
}