{
  "type": "Feature",
  "properties": {
    "addr:full":"1 Crock La Bridport Dorset DT6 4DE",
    "addr:housenumber":"1",
    "addr:postcode":"dt6 4de",
    "addr:street":"Crock La Bridport",
    "iso:country":"GB",
    "sg:address":"1 Crock La",
    "sg:city":"Bridport",
    "sg:classifiers":[
        {
            "category":"Professional",
            "subcategory":"Management & Consulting",
            "type":"Services"
        }
    ],
    "sg:phone":"+44 1308 424666",
    "sg:postcode":"DT6 4DE",
    "sg:province":"Dorset",
    "sg:tags":[
        "consultant",
        "business"
    ],
    "wof:name":"P R Hines",
    "wof:placetype":"venue"
},
  "geometry": {"coordinates":[-2.7476389408,50.7322006226],"type":"Point"}
}