{
  "type": "Feature",
  "properties": {
    "iso:country":"GB",
    "sg:address":"8 Hill Court, Paulton",
    "sg:city":"Bristol",
    "sg:classifiers":[
        {
            "category":"Personal",
            "subcategory":"Beauty Salon",
            "type":"Services"
        }
    ],
    "sg:phone":"+44 1761 413006",
    "sg:postcode":"BS39 7QG",
    "sg:province":"Somerset",
    "sg:tags":[
        "unisex",
        "hairdresser"
    ],
    "wof:name":"Terry's Hair Artist",
    "wof:placetype":"venue"
},
  "geometry": {"coordinates":[-2.500631094,51.3056259155],"type":"Point"}
}