{
  "type": "Feature",
  "properties": {
    "iso:country":"GB",
    "sg:address":"11 Argyle Street",
    "sg:city":"Ullapool",
    "sg:classifiers":[
        {
            "category":"Banks & Credit Unions",
            "subcategory":"Bank",
            "type":"Services"
        }
    ],
    "sg:phone":"+44 1854 612112",
    "sg:postcode":"IV26 2UD",
    "sg:province":"Highland",
    "sg:tags":[
        "financial",
        "institution"
    ],
    "sg:website":"http://www.rbs.co.uk",
    "wof:name":"The Royal Bank of Scotland plc",
    "wof:placetype":"venue"
},
  "geometry": {"coordinates":[-5.155739,57.896873],"type":"Point"}
}