{
  "type": "Feature",
  "properties": {
    "iso:country":"GB",
    "sg:address":"4 Dale Street",
    "sg:city":"Manchester",
    "sg:classifiers":[
        {
            "category":"Banks & Credit Unions",
            "subcategory":"Bank",
            "type":"Services"
        }
    ],
    "sg:phone":"+44 161 236 0973",
    "sg:postcode":"M1 1JW",
    "sg:province":"Greater Manchester",
    "wof:name":"United Bank Ltd.",
    "wof:placetype":"venue"
},
  "geometry": {"coordinates":[-2.235597,53.482304],"type":"Point"}
}