{
  "type": "Feature",
  "properties": {
    "iso:country":"GB",
    "sg:address":"Gatehouse (the), 16 Arlington Street",
    "sg:city":"London",
    "sg:classifiers":[
        {
            "category":"Real Estate",
            "subcategory":"Developer",
            "type":"Services"
        }
    ],
    "sg:phone":"+44 20 7258 6100",
    "sg:postcode":"SW1A 1RD",
    "sg:province":"Greater London",
    "sg:tags":[
        "property"
    ],
    "wof:name":"Drayfield Ltd.",
    "wof:placetype":"venue"
},
  "geometry": {"coordinates":[-0.127144,51.506325],"type":"Point"}
}