{
  "type": "Feature",
  "properties": {
    "iso:country":"GB",
    "sg:address":"81 Rockwell Grn",
    "sg:city":"Wellington",
    "sg:classifiers":[
        {
            "category":"Education",
            "subcategory":"Special Training",
            "type":"Public Place"
        }
    ],
    "sg:postcode":"TA21 9BX",
    "sg:province":"Devon",
    "sg:tags":[
        "school",
        "language"
    ],
    "wof:name":"Colin Bryce",
    "wof:placetype":"venue"
},
  "geometry": {"coordinates":[-3.242548,50.973652],"type":"Point"}
}