{
  "type": "Feature",
  "properties": {
    "addr:full":"9 Western Parade Reigate Surrey RH2 8AU",
    "addr:housenumber":"9",
    "addr:postcode":"rh2 8au",
    "addr:street":"Western Parade",
    "iso:country":"GB",
    "sg:address":"9 Western Parade",
    "sg:city":"Reigate",
    "sg:classifiers":[
        {
            "category":"Building & Trades",
            "subcategory":"Cleaning & Sanitation",
            "type":"Services"
        }
    ],
    "sg:phone":"+44 1737 240001",
    "sg:postcode":"RH2 8AU",
    "sg:province":"Surrey",
    "sg:tags":[
        "sweep",
        "chimney"
    ],
    "wof:name":"Reigate Chimney Sweeping Services",
    "wof:placetype":"venue"
},
  "geometry": {"coordinates":[-0.2000660002,51.2238502502],"type":"Point"}
}