{
  "type": "Feature",
  "properties": {
    "iso:country":"GB",
    "sg:address":"Four Ashes Road, Cryers Hill",
    "sg:city":"High Wycombe",
    "sg:classifiers":[
        {
            "category":"Community Center",
            "type":"Public Place"
        }
    ],
    "sg:phone":"+44 1494 716473",
    "sg:postcode":"HP15 6LA",
    "sg:province":"Buckinghamshire",
    "sg:tags":[
        "conference",
        "room",
        "centre"
    ],
    "wof:name":"Uplands Conference & Training Centre",
    "wof:placetype":"venue"
},
  "geometry": {"coordinates":[-0.736681,51.663937],"type":"Point"}
}