{
  "type": "Feature",
  "properties": {
    "addr:full":"Moland Forge, Central Trading Estate, Shaw Road Dudley West Midlands DY2 8QX",
    "addr:postcode":"dy2 8qx",
    "addr:street":"Shaw Road",
    "iso:country":"GB",
    "sg:address":"Moland Forge, Central Trading Estate, Shaw Road",
    "sg:city":"Dudley",
    "sg:classifiers":[
        {
            "category":"Manufacturing",
            "subcategory":"Metals",
            "type":"Manufacturing & Wholesale Goods"
        }
    ],
    "sg:phone":"+44 1384 243833",
    "sg:postcode":"DY2 8QX",
    "sg:province":"West Midlands",
    "sg:tags":[
        "blacksmith",
        "forgemasters"
    ],
    "wof:name":"Jenkins Dunn Forgings Ltd.",
    "wof:placetype":"venue"
},
  "geometry": {"coordinates":[-2.0835089684,52.5095214844],"type":"Point"}
}