{
  "type": "Feature",
  "properties": {
    "iso:country":"GB",
    "sg:address":"12-14 Bouverie Place",
    "sg:city":"Folkestone",
    "sg:classifiers":[
        {
            "category":"Organizations",
            "subcategory":"Non-profit Organization",
            "type":"Services"
        }
    ],
    "sg:phone":"+44 1303 850733",
    "sg:postcode":"CT20 1AU",
    "sg:province":"Kent",
    "sg:tags":[
        "organisation",
        "voluntary",
        "charity"
    ],
    "wof:name":"Folkestone Rainbow Centre",
    "wof:placetype":"venue"
},
  "geometry": {"coordinates":[1.177305,51.079624],"type":"Point"}
}