{
  "type": "Feature",
  "properties": {
    "addr:full":"90 Walcot Street Bath Bath and North East Somerset BA1 5BG",
    "addr:housenumber":"90",
    "addr:postcode":"ba1 5bg",
    "addr:street":"Walcot Street",
    "iso:country":"GB",
    "sg:address":"90 Walcot Street",
    "sg:city":"Bath",
    "sg:classifiers":[
        {
            "category":"Real Estate",
            "subcategory":"Architect",
            "type":"Services"
        }
    ],
    "sg:phone":"+44 1225 446400",
    "sg:postcode":"BA1 5BG",
    "sg:province":"Bath and North East Somerset",
    "wof:name":"Bennett Dludgiewicz & Date Architects",
    "wof:placetype":"venue"
},
  "geometry": {"coordinates":[-2.3593709469,51.3863563538],"type":"Point"}
}