{
  "type": "Feature",
  "properties": {
    "iso:country":"GB",
    "sg:address":"Slutchers Lane, Centre Park",
    "sg:city":"Warrington",
    "sg:classifiers":[
        {
            "category":"Sports & Exercise",
            "subcategory":"Golf",
            "type":"Entertainment"
        }
    ],
    "sg:phone":"+44 1925 234800",
    "sg:postcode":"WA1 1QL",
    "sg:province":"Cheshire",
    "sg:tags":[
        "club",
        "equipment"
    ],
    "wof:name":"Drivetime Ltd.",
    "wof:placetype":"venue"
},
  "geometry": {"coordinates":[-2.599793911,53.3815612793],"type":"Point"}
}