{
  "type": "Feature",
  "properties": {
    "addr:full":"Dalkeith Mkt, Dalkeith Arcade Bournemouth Dorset BH1 1EP",
    "addr:housenumber":"arcade",
    "addr:postcode":"bh1 1ep",
    "iso:country":"GB",
    "sg:address":"Dalkeith Mkt, Dalkeith Arcade",
    "sg:city":"Bournemouth",
    "sg:classifiers":[
        {
            "category":"Shopping",
            "subcategory":"Antiques",
            "type":"Retail Goods"
        }
    ],
    "sg:postcode":"BH1 1EP",
    "sg:province":"Dorset",
    "wof:name":"French,G,",
    "wof:placetype":"venue"
},
  "geometry": {"coordinates":[-1.8758699894,50.7216720581],"type":"Point"}
}