{
  "type": "Feature",
  "properties": {
    "addr:full":"68 Moorhen Drive, Lower Early Reading Berkshire RG6 4NZ",
    "addr:housenumber":"68",
    "addr:postcode":"rg6 4nz",
    "addr:street":"Moorhen Drive Lower",
    "iso:country":"GB",
    "sg:address":"68 Moorhen Drive, Lower Early",
    "sg:city":"Reading",
    "sg:classifiers":[
        {
            "category":"Shopping",
            "subcategory":"Party Supplies",
            "type":"Retail Goods"
        }
    ],
    "sg:phone":"+44 118 975 0854",
    "sg:postcode":"RG6 4NZ",
    "sg:province":"Berkshire",
    "sg:tags":[
        "inflatables",
        "bouncy",
        "castle"
    ],
    "wof:name":"ALPHA LEISURE",
    "wof:placetype":"venue"
},
  "geometry": {"coordinates":[-0.926065,51.426685],"type":"Point"}
}