{
  "type": "Feature",
  "properties": {
    "iso:country":"GB",
    "sg:address":"High Snab, Gressingham",
    "sg:city":"Lancaster",
    "sg:classifiers":[
        {
            "category":"Farming",
            "subcategory":"Dairy Farm",
            "type":"Manufacturing & Wholesale Goods"
        }
    ],
    "sg:postcode":"LA2 8LS",
    "sg:province":"Lancashire",
    "wof:name":"A T & D J Burrow",
    "wof:placetype":"venue"
},
  "geometry": {"coordinates":[-2.6575069427,54.123790741],"type":"Point"}
}