{
  "type": "Feature",
  "properties": {
    "iso:country":"GB",
    "sg:address":"Convent Road",
    "sg:city":"Broadstairs",
    "sg:classifiers":[
        {
            "category":"Social Services",
            "subcategory":"Retirement Home",
            "type":"Services"
        }
    ],
    "sg:phone":"+44 1843 602266",
    "sg:postcode":"CT10 3PR",
    "sg:province":"Kent",
    "sg:tags":[
        "residential",
        "care"
    ],
    "wof:name":"Port Regis Care Centre",
    "wof:placetype":"venue"
},
  "geometry": {"coordinates":[1.431245,51.376289],"type":"Point"}
}