{
  "type": "Feature",
  "properties": {
    "iso:country":"GB",
    "sg:address":"28 Le Strange Terrace",
    "sg:city":"Hunstanton",
    "sg:classifiers":[
        {
            "category":"Retail",
            "subcategory":"Laundry & Dry Cleaning",
            "type":"Services"
        }
    ],
    "sg:postcode":"PE36 5AJ",
    "sg:province":"Norfolk",
    "sg:tags":[
        "alteration"
    ],
    "wof:name":"Phoenix Dry Cleaning Co.",
    "wof:placetype":"venue"
},
  "geometry": {"coordinates":[0.48725,52.938683],"type":"Point"}
}