{
  "type": "Feature",
  "properties": {
    "iso:country":"GB",
    "sg:address":"Lauriston, Wych Hill",
    "sg:city":"Woking",
    "sg:classifiers":[
        {
            "category":"Shopping",
            "subcategory":"Pharmacy",
            "type":"Retail Goods"
        }
    ],
    "sg:postcode":"GU22 0HA",
    "sg:province":"Surrey",
    "sg:tags":[
        "medicine",
        "therapy"
    ],
    "wof:name":"Linda Vaughan",
    "wof:placetype":"venue"
},
  "geometry": {"coordinates":[-0.57171,51.30938],"type":"Point"}
}