{
  "type": "Feature",
  "properties": {
    "iso:country":"GB",
    "sg:address":"5 Broad Oth Lane, Shevington",
    "sg:city":"Wigan",
    "sg:classifiers":[
        {
            "category":"Shopping",
            "subcategory":"News",
            "type":"Retail Goods"
        }
    ],
    "sg:phone":"+44 1257 252460",
    "sg:postcode":"WN6 8EA",
    "sg:province":"Lancashire",
    "sg:tags":[
        "newsagent"
    ],
    "wof:name":"News Front",
    "wof:placetype":"venue"
},
  "geometry": {"coordinates":[-2.6929719448,53.5724716187],"type":"Point"}
}