{
  "type": "Feature",
  "properties": {
    "iso:country":"GB",
    "sg:address":"23 Watcombe Road",
    "sg:city":"Watlington",
    "sg:classifiers":[
        {
            "category":"Personal",
            "subcategory":"Adult",
            "type":"Services"
        }
    ],
    "sg:postcode":"OX49 5QJ",
    "sg:province":"Oxfordshire",
    "sg:tags":[
        "equestrian"
    ],
    "wof:name":"William Smith",
    "wof:placetype":"venue"
},
  "geometry": {"coordinates":[-1.004677,51.644058],"type":"Point"}
}