{
  "type": "Feature",
  "properties": {
    "iso:country":"GB",
    "sg:address":"41 Skaife Road",
    "sg:city":"Sale",
    "sg:classifiers":[
        {
            "category":"Retail",
            "subcategory":"Emissions Testing",
            "type":"Services"
        },
        {
            "category":"Retail",
            "subcategory":"Auto Repair",
            "type":"Services"
        }
    ],
    "sg:phone":"+44 161 973 1015",
    "sg:postcode":"M33 2HA",
    "sg:province":"Cheshire",
    "sg:tags":[
        "modification",
        "garage",
        "mot"
    ],
    "wof:name":"K A Walker",
    "wof:placetype":"venue"
},
  "geometry": {"coordinates":[-2.299619,53.422749],"type":"Point"}
}