{
  "type": "Feature",
  "properties": {
    "addr:full":"Elder Hall, Peasenhall Saxmundham Suffolk IP17 2HG",
    "addr:housenumber":"saxmundham",
    "addr:postcode":"ip17 2hg",
    "iso:country":"GB",
    "sg:address":"Elder Hall, Peasenhall",
    "sg:city":"Saxmundham",
    "sg:classifiers":[
        {
            "category":"Farming",
            "subcategory":"Livestock Farm",
            "type":"Manufacturing & Wholesale Goods"
        }
    ],
    "sg:phone":"+44 1728 660270",
    "sg:postcode":"IP17 2HG",
    "sg:province":"Suffolk",
    "sg:tags":[
        "others"
    ],
    "wof:name":"R & I Macfarlane",
    "wof:placetype":"venue"
},
  "geometry": {"coordinates":[1.450644,52.271198],"type":"Point"}
}