{
  "type": "Feature",
  "properties": {
    "addr:full":"60 Main Avenue, Bush Hill Park Enfield Greater London EN1 1DH",
    "addr:housenumber":"60",
    "addr:postcode":"en1 1dh",
    "addr:street":"Main Avenue Bush Hill Park",
    "iso:country":"GB",
    "sg:address":"60 Main Avenue, Bush Hill Park",
    "sg:city":"Enfield",
    "sg:classifiers":[
        {
            "category":"Food & Beverages",
            "subcategory":"Liquor & Beverages",
            "type":"Retail Goods"
        }
    ],
    "sg:phone":"+44 20 8367 7217",
    "sg:postcode":"EN1 1DH",
    "sg:province":"Greater London",
    "sg:tags":[
        "beer",
        "spirit",
        "wines"
    ],
    "wof:name":"Camden Wines",
    "wof:placetype":"venue"
},
  "geometry": {"coordinates":[-0.0641530007,51.6451568604],"type":"Point"}
}