{
  "type": "Feature",
  "properties": {
    "addr:full":"Railway Approach Harrow Greater London HA3 5BT",
    "addr:postcode":"ha3 5bt",
    "addr:street":"Railway Approach",
    "iso:country":"GB",
    "sg:address":"Railway Approach",
    "sg:city":"Harrow",
    "sg:classifiers":[
        {
            "category":"Bars & Pubs",
            "type":"Food & Drink"
        }
    ],
    "sg:phone":"+44 20 8427 0459",
    "sg:postcode":"HA3 5BT",
    "sg:province":"Greater London",
    "sg:tags":[
        "pubs",
        "inn"
    ],
    "wof:name":"Railway Hotel",
    "wof:placetype":"venue"
},
  "geometry": {"coordinates":[-0.332927,51.590446],"type":"Point"}
}