{
  "type": "Feature",
  "properties": {
    "addr:full":"182 Earlsway, Team Valley Trading Est Gateshead Tyne and Wear NE11 0RQ",
    "addr:housenumber":"182",
    "addr:postcode":"ne11 0rq",
    "addr:street":"Earlsway",
    "iso:country":"GB",
    "sg:address":"182 Earlsway, Team Valley Trading Est",
    "sg:city":"Gateshead",
    "sg:classifiers":[
        {
            "category":"Banks & Credit Unions",
            "subcategory":"Investment Brokerage",
            "type":"Services"
        }
    ],
    "sg:phone":"+44 191 482 5220",
    "sg:postcode":"NE11 0RQ",
    "sg:province":"Tyne and Wear",
    "sg:tags":[
        "distribution",
        "circular"
    ],
    "wof:name":"Household Advertising Ltd",
    "wof:placetype":"venue"
},
  "geometry": {"coordinates":[-1.6179100275,54.9417991638],"type":"Point"}
}