{
  "type": "Feature",
  "properties": {
    "iso:country":"GB",
    "sg:address":"41 Bull Street",
    "sg:city":"Birmingham",
    "sg:classifiers":[
        {
            "category":"Retail",
            "subcategory":"Laundry & Dry Cleaning",
            "type":"Services"
        }
    ],
    "sg:phone":"+44 121 236 6064",
    "sg:postcode":"B4 6AF",
    "sg:province":"West Midlands",
    "sg:tags":[
        "alteration"
    ],
    "wof:name":"Johnson Cleaners U K Ltd.",
    "wof:placetype":"venue"
},
  "geometry": {"coordinates":[-1.89629,52.481998],"type":"Point"}
}