{
  "type": "Feature",
  "properties": {
    "iso:country":"GB",
    "sg:address":"54 Mitton Street",
    "sg:city":"Stourport-on-severn",
    "sg:classifiers":[
        {
            "category":"Bars & Pubs",
            "type":"Food & Drink"
        }
    ],
    "sg:phone":"+44 1299 829449",
    "sg:postcode":"DY13 9AA",
    "sg:province":"Worcestershire",
    "sg:tags":[
        "pubs",
        "inn"
    ],
    "wof:name":"Shepherd Neame Ltd.",
    "wof:placetype":"venue"
},
  "geometry": {"coordinates":[-2.275743,52.339882],"type":"Point"}
}