{
  "type": "Feature",
  "properties": {
    "addr:full":"319 Frost Lane, Hythe Southampton Hampshire SO45 3NB",
    "addr:housenumber":"319",
    "addr:postcode":"so45 3nb",
    "addr:street":"Frost Lane",
    "iso:country":"GB",
    "sg:address":"319 Frost Lane, Hythe",
    "sg:city":"Southampton",
    "sg:classifiers":[
        {
            "category":"Manufacturing",
            "subcategory":"Signs",
            "type":"Manufacturing & Wholesale Goods"
        }
    ],
    "sg:phone":"+44 23 8087 9028",
    "sg:postcode":"SO45 3NB",
    "sg:province":"Hampshire",
    "sg:tags":[
        "commercial",
        "maker"
    ],
    "wof:name":"Graffito Signs",
    "wof:placetype":"venue"
},
  "geometry": {"coordinates":[-1.387588,50.860737],"type":"Point"}
}