{
  "type": "Feature",
  "properties": {
    "addr:full":"21 Old Hall Road Dereham Norfolk NR19 1SE",
    "addr:housenumber":"21",
    "addr:postcode":"nr19 1se",
    "addr:street":"Old Hall Road",
    "iso:country":"GB",
    "sg:address":"21 Old Hall Road",
    "sg:city":"Dereham",
    "sg:classifiers":[
        {
            "category":"Organizations",
            "subcategory":"Non-profit Organization",
            "type":"Services"
        }
    ],
    "sg:phone":"+44 1362 853057",
    "sg:postcode":"NR19 1SE",
    "sg:province":"Norfolk",
    "sg:tags":[
        "organisation",
        "voluntary",
        "charity"
    ],
    "wof:name":"U K Transplant",
    "wof:placetype":"venue"
},
  "geometry": {"coordinates":[0.9410060048,52.6669082642],"type":"Point"}
}