{
  "type": "Feature",
  "properties": {
    "addr:full":"116 Park Lane London Greater London N17 0JP",
    "addr:housenumber":"116",
    "addr:postcode":"n17 0jp",
    "addr:street":"Park Lane",
    "iso:country":"GB",
    "sg:address":"116 Park Lane",
    "sg:city":"London",
    "sg:classifiers":[
        {
            "category":"Food & Beverages",
            "subcategory":"Liquor & Beverages",
            "type":"Retail Goods"
        }
    ],
    "sg:postcode":"N17 0JP",
    "sg:province":"Greater London",
    "sg:tags":[
        "beer",
        "wine",
        "spirit",
        "wines"
    ],
    "wof:name":"Park Lane Wine Mart",
    "wof:placetype":"venue"
},
  "geometry": {"coordinates":[-0.05961,51.602566],"type":"Point"}
}