{
  "type": "Feature",
  "properties": {
    "addr:full":"Hillview, The Quarry, Brockhampton Cheltenham Gloucestershire GL54 5XL",
    "addr:postcode":"gl54 5xl",
    "addr:street":"Brockhampton",
    "iso:country":"GB",
    "sg:address":"Hillview, The Quarry, Brockhampton",
    "sg:city":"Cheltenham",
    "sg:classifiers":[
        {
            "category":"Communications",
            "type":"Services"
        }
    ],
    "sg:phone":"+44 1242 820777",
    "sg:postcode":"GL54 5XL",
    "sg:province":"Gloucestershire",
    "sg:tags":[
        "telecommunication"
    ],
    "wof:name":"Reed Telecom",
    "wof:placetype":"venue"
},
  "geometry": {"coordinates":[-1.9496890306,51.8998832703],"type":"Point"}
}