{
  "type": "Feature",
  "properties": {
    "addr:full":"Woodend Colliery Bathgate West Lothian EH48 3AP",
    "addr:postcode":"eh48 3ap",
    "addr:street":"Bathgate",
    "iso:country":"GB",
    "sg:address":"Woodend Colliery",
    "sg:city":"Bathgate",
    "sg:classifiers":[
        {
            "category":"Mining & Drilling",
            "type":"Manufacturing & Wholesale Goods"
        }
    ],
    "sg:phone":"+44 1501 730231",
    "sg:postcode":"EH48 3AP",
    "sg:province":"West Lothian",
    "sg:tags":[
        "coal"
    ],
    "wof:name":"Coal Products Ltd.",
    "wof:placetype":"venue"
},
  "geometry": {"coordinates":[-3.771669,55.884369],"type":"Point"}
}