{
  "type": "Feature",
  "properties": {
    "addr:full":"Unit 4, Cavendish Place Ashton-under-lyne Greater Manchester OL6 7DQ",
    "addr:housenumber":"unit 4",
    "addr:postcode":"ol6 7dq",
    "addr:street":"Cavendish Place",
    "iso:country":"GB",
    "sg:address":"Unit 4, Cavendish Place",
    "sg:city":"Ashton-under-lyne",
    "sg:classifiers":[
        {
            "category":"Bus Stop",
            "subcategory":"None",
            "type":"Transportation"
        }
    ],
    "sg:phone":"+44 161 330 7969",
    "sg:postcode":"OL6 7DQ",
    "sg:province":"Greater Manchester",
    "sg:tags":[
        "filter"
    ],
    "wof:name":"Elliott & Co",
    "wof:placetype":"venue"
},
  "geometry": {"coordinates":[-2.1010389328,53.489566803],"type":"Point"}
}