{
  "type": "Feature",
  "properties": {
    "addr:full":"Sales Line Only, Coypool, Marshmills Plymouth Devon PL7 4NW",
    "addr:postcode":"pl7 4nw",
    "addr:street":"Sales Line;Marshmills",
    "iso:country":"GB",
    "sg:address":"Sales Line Only, Coypool, Marshmills",
    "sg:city":"Plymouth",
    "sg:classifiers":[
        {
            "category":"Shopping",
            "subcategory":"Department Store",
            "type":"Retail Goods"
        },
        {
            "category":"Wholesale",
            "subcategory":"Books, Periodicals, & Newspapers",
            "type":"Manufacturing & Wholesale Goods"
        }
    ],
    "sg:phone":"+44 1752 341177",
    "sg:postcode":"PL7 4NW",
    "sg:province":"Devon",
    "sg:tags":[
        "waste",
        "surplus"
    ],
    "wof:name":"Eko-Tek Power Ltd.",
    "wof:placetype":"venue"
},
  "geometry": {"coordinates":[-4.0834999084,50.3914413452],"type":"Point"}
}