{
  "type": "Feature",
  "properties": {
    "addr:full":"19 Tooting Bec Road London Greater London SW17 8BS",
    "addr:housenumber":"19",
    "addr:postcode":"sw17 8bs",
    "addr:street":"Tooting Bec Road",
    "iso:country":"GB",
    "sg:address":"19 Tooting Bec Road",
    "sg:city":"London",
    "sg:classifiers":[
        {
            "category":"Education",
            "subcategory":"School",
            "type":"Public Place"
        }
    ],
    "sg:phone":"+44 20 8672 9227",
    "sg:postcode":"SW17 8BS",
    "sg:province":"Greater London",
    "sg:tags":[
        "local",
        "authority"
    ],
    "wof:name":"St. Anselm S Primary School",
    "wof:placetype":"venue"
},
  "geometry": {"coordinates":[-0.1579259932,51.4353942871],"type":"Point"}
}