{
  "type": "Feature",
  "properties": {
    "iso:country":"GB",
    "sg:address":"3 Edgar St",
    "sg:city":"Accrington",
    "sg:classifiers":[
        {
            "category":"Taxi",
            "type":"Transportation"
        }
    ],
    "sg:phone":"+44 1254 872112",
    "sg:postcode":"BB5 1PT",
    "sg:province":"Lancashire",
    "sg:tags":[
        "mini",
        "cab"
    ],
    "wof:name":"A1 Supercars",
    "wof:placetype":"venue"
},
  "geometry": {"coordinates":[-2.368139,53.753696],"type":"Point"}
}