{
  "type": "Feature",
  "properties": {
    "addr:full":"Cotsvale, Harrowbeer Lane Yelverton Devon PL20 6EA",
    "addr:postcode":"pl20 6ea",
    "addr:street":"Harrowbeer Lane",
    "iso:country":"GB",
    "sg:address":"Cotsvale, Harrowbeer Lane",
    "sg:city":"Yelverton",
    "sg:classifiers":[
        {
            "category":"Building & Trades",
            "subcategory":"Construction",
            "type":"Services"
        }
    ],
    "sg:postcode":"PL20 6EA",
    "sg:province":"Devon",
    "sg:tags":[
        "builder"
    ],
    "wof:name":"City Builders",
    "wof:placetype":"venue"
},
  "geometry": {"coordinates":[-4.0878591537,50.4923782349],"type":"Point"}
}