{
  "type": "Feature",
  "properties": {
    "addr:full":"8 Victoria Parade Broadstairs Kent CT10 1QS",
    "addr:housenumber":"8",
    "addr:postcode":"ct10 1qs",
    "addr:street":"Victoria Parade",
    "iso:country":"GB",
    "sg:address":"8 Victoria Parade",
    "sg:city":"Broadstairs",
    "sg:classifiers":[
        {
            "category":"Restaurant",
            "type":"Food & Drink"
        }
    ],
    "sg:phone":"+44 1843 861289",
    "sg:postcode":"CT10 1QS",
    "sg:province":"Kent",
    "wof:name":"Rino's",
    "wof:placetype":"venue"
},
  "geometry": {"coordinates":[1.441936,51.357738],"type":"Point"}
}