{
  "type": "Feature",
  "properties": {
    "addr:full":"12 Netherfarm Road Gateshead Tyne and Wear NE10 0YR",
    "addr:housenumber":"12",
    "addr:postcode":"ne10 0yr",
    "addr:street":"Netherfarm Road",
    "iso:country":"GB",
    "sg:address":"12 Netherfarm Road",
    "sg:city":"Gateshead",
    "sg:classifiers":[
        {
            "category":"Personal",
            "type":"Services"
        }
    ],
    "sg:phone":"+44 191 469 4963",
    "sg:postcode":"NE10 0YR",
    "sg:province":"Tyne and Wear",
    "sg:tags":[
        "wedding"
    ],
    "wof:name":"Scott's Wedding Cars",
    "wof:placetype":"venue"
},
  "geometry": {"coordinates":[-1.551275,54.953781],"type":"Point"}
}