{
  "type": "Feature",
  "properties": {
    "addr:full":"West Itchenor Chichester West Sussex PO20 7HE",
    "addr:postcode":"po20 7he",
    "addr:street":"West Itchenor",
    "iso:country":"GB",
    "sg:address":"West Itchenor",
    "sg:city":"Chichester",
    "sg:classifiers":[
        {
            "category":"Place Of Worship",
            "type":"Public Place"
        }
    ],
    "sg:phone":"+44 1243 514057",
    "sg:postcode":"PO20 7HE",
    "sg:province":"West Sussex",
    "wof:name":"St Nicholas C Of E Church",
    "wof:placetype":"venue"
},
  "geometry": {"coordinates":[-0.83558,50.796509],"type":"Point"}
}