{
  "type": "Feature",
  "properties": {
    "iso:country":"GB",
    "sg:address":"94 Whyterose Terrace, Methil",
    "sg:city":"Leven",
    "sg:classifiers":[
        {
            "category":"Shopping",
            "subcategory":"Discount & Variety Stores",
            "type":"Retail Goods"
        }
    ],
    "sg:phone":"+44 1333 426823",
    "sg:postcode":"KY8 3AS",
    "sg:province":"Fife",
    "sg:tags":[
        "cleaning",
        "supply"
    ],
    "wof:name":"Shepherd & Miller",
    "wof:placetype":"venue"
},
  "geometry": {"coordinates":[-3.007614,56.188511],"type":"Point"}
}