{
  "type": "Feature",
  "properties": {
    "addr:full":"Thames Rd Barking Essex IG11 0JD",
    "addr:postcode":"essex ig11 0jd",
    "addr:street":"Thames Rd",
    "iso:country":"GB",
    "sg:address":"Thames Rd",
    "sg:city":"Barking",
    "sg:classifiers":[
        {
            "category":"Freight",
            "type":"Transportation"
        }
    ],
    "sg:phone":"+44 20 8507 2001",
    "sg:postcode":"IG11 0JD",
    "sg:province":"Essex",
    "sg:tags":[
        "forwarders"
    ],
    "wof:name":"Quadrant (Express) Ltd",
    "wof:placetype":"venue"
},
  "geometry": {"coordinates":[0.0980449989,51.5252838135],"type":"Point"}
}