{
  "type": "Feature",
  "properties": {
    "addr:full":"High Street Newton-le-willows Cheshire WA12 9SL",
    "addr:postcode":"wa12 9sl",
    "addr:street":"High Street",
    "iso:country":"GB",
    "sg:address":"High Street",
    "sg:city":"Newton-le-willows",
    "sg:classifiers":[
        {
            "category":"Bars & Pubs",
            "type":"Food & Drink"
        }
    ],
    "sg:phone":"+44 1925 225376",
    "sg:postcode":"WA12 9SL",
    "sg:province":"Cheshire",
    "sg:tags":[
        "pubs",
        "inn"
    ],
    "wof:name":"Blue Bell Hotel",
    "wof:placetype":"venue"
},
  "geometry": {"coordinates":[-2.6222341061,53.4582366943],"type":"Point"}
}