{
  "type": "Feature",
  "properties": {
    "addr:full":"Chiddingstone Causeway Tonbridge Kent TN11 8JP",
    "addr:postcode":"tn11 8jp",
    "addr:street":"Chiddingstone Causeway",
    "iso:country":"GB",
    "sg:address":"Chiddingstone Causeway",
    "sg:city":"Tonbridge",
    "sg:classifiers":[
        {
            "category":"Shopping",
            "subcategory":"Department Store",
            "type":"Retail Goods"
        }
    ],
    "sg:phone":"+44 1892 870327",
    "sg:postcode":"TN11 8JP",
    "sg:province":"Kent",
    "wof:name":"Causeway Stores & Post Office",
    "wof:placetype":"venue"
},
  "geometry": {"coordinates":[0.16981,51.198608],"type":"Point"}
}