{
  "type": "Feature",
  "properties": {
    "addr:full":"Southport Old Road, Formby Liverpool Lancashire L37 0AB",
    "addr:postcode":"l37 0ab",
    "addr:street":"Southport Old Road",
    "iso:country":"GB",
    "sg:address":"Southport Old Road, Formby",
    "sg:city":"Liverpool",
    "sg:classifiers":[
        {
            "category":"Travel",
            "subcategory":"Hotels & Motels",
            "type":"Entertainment"
        },
        {
            "category":"Restaurant",
            "type":"Food & Drink"
        }
    ],
    "sg:phone":"+44 1704 572430",
    "sg:postcode":"L37 0AB",
    "sg:province":"Lancashire",
    "sg:tags":[
        "-",
        "french"
    ],
    "wof:name":"Tree Tops Hotel",
    "wof:placetype":"venue"
},
  "geometry": {"coordinates":[-3.046954,53.573326],"type":"Point"}
}