{
  "type": "Feature",
  "properties": {
    "iso:country":"GB",
    "sg:address":"500 Wallisdown Road",
    "sg:city":"Bournemouth",
    "sg:classifiers":[
        {
            "category":"Manufacturing",
            "subcategory":"Building Materials",
            "type":"Manufacturing & Wholesale Goods"
        }
    ],
    "sg:phone":"+44 1202 519411",
    "sg:postcode":"BH11 8PT",
    "sg:province":"Dorset",
    "sg:tags":[
        "merchant",
        "builder"
    ],
    "wof:name":"Travis Perkins Trading Co. Ltd.",
    "wof:placetype":"venue"
},
  "geometry": {"coordinates":[-1.9272389412,50.7518997192],"type":"Point"}
}