{
  "type": "Feature",
  "properties": {
    "addr:full":"Kibble Bank Community Centre, Underley Street Burnley Lancashire BB10 2BX",
    "addr:postcode":"bb10 2bx",
    "addr:street":"Underley Street",
    "iso:country":"GB",
    "sg:address":"Kibble Bank Community Centre, Underley Street",
    "sg:city":"Burnley",
    "sg:classifiers":[
        {
            "category":"Community Center",
            "type":"Public Place"
        },
        {
            "category":"Government",
            "subcategory":"Office",
            "type":"Public Place"
        }
    ],
    "sg:phone":"+44 1282 420012",
    "sg:postcode":"BB10 2BX",
    "sg:province":"Lancashire",
    "sg:tags":[
        "local",
        "centre"
    ],
    "wof:name":"Lanehead Community Centre",
    "wof:placetype":"venue"
},
  "geometry": {"coordinates":[-2.220375061,53.8160438538],"type":"Point"}
}