{
  "type": "Feature",
  "properties": {
    "addr:full":"54 North Street Thame Buckinghamshire OX9 3BH",
    "addr:housenumber":"54",
    "addr:postcode":"ox9 3bh",
    "addr:street":"North Street",
    "iso:country":"GB",
    "sg:address":"54 North Street",
    "sg:city":"Thame",
    "sg:classifiers":[
        {
            "category":"Arts & Performance",
            "subcategory":"Art Gallery",
            "type":"Entertainment"
        }
    ],
    "sg:phone":"+44 1844 217622",
    "sg:postcode":"OX9 3BH",
    "sg:province":"Buckinghamshire",
    "wof:name":"The Red Gallery",
    "wof:placetype":"venue"
},
  "geometry": {"coordinates":[-0.976263,51.747631],"type":"Point"}
}