{
  "type": "Feature",
  "properties": {
    "iso:country":"GB",
    "sg:address":"9 Swan Alley, Leading To Church Walks, Off Burscough Street",
    "sg:city":"Ormskirk",
    "sg:classifiers":[
        {
            "category":"Shopping",
            "subcategory":"Crafts & Fabrics",
            "type":"Retail Goods"
        }
    ],
    "sg:phone":"+44 1695 573356",
    "sg:postcode":"L39 2EG",
    "sg:province":"Lancashire",
    "sg:tags":[
        "shop"
    ],
    "wof:name":"Maureen's Fabrics",
    "wof:placetype":"venue"
},
  "geometry": {"coordinates":[-2.8863,53.566277],"type":"Point"}
}