{
  "type": "Feature",
  "properties": {
    "iso:country":"GB",
    "sg:address":"12 Thames Centre",
    "sg:city":"Newton Aycliffe",
    "sg:classifiers":[
        {
            "category":"Shopping",
            "subcategory":"Gifts & Souvenirs",
            "type":"Retail Goods"
        }
    ],
    "sg:postcode":"DL5 4SB",
    "sg:province":"Durham",
    "sg:tags":[
        "shop"
    ],
    "wof:name":"Top Value",
    "wof:placetype":"venue"
},
  "geometry": {"coordinates":[-1.5714739561,54.6191864014],"type":"Point"}
}