{
  "type": "Feature",
  "properties": {
    "addr:full":"258 Archway Road London Greater London N6 5AX",
    "addr:housenumber":"258",
    "addr:postcode":"n6 5ax",
    "addr:street":"Archway Road",
    "iso:country":"GB",
    "sg:address":"258 Archway Road",
    "sg:city":"London",
    "sg:classifiers":[
        {
            "category":"Arts & Performance",
            "subcategory":"Art Gallery",
            "type":"Entertainment"
        }
    ],
    "sg:postcode":"N6 5AX",
    "sg:province":"Greater London",
    "wof:name":"ROMANESQUE FINE ART & FURNITURE",
    "wof:placetype":"venue"
},
  "geometry": {"coordinates":[-0.142153,51.574898],"type":"Point"}
}