{
  "type": "Feature",
  "properties": {
    "addr:full":"84 Longfellow Drive Rotherham South Yorkshire S65 2LL",
    "addr:housenumber":"84",
    "addr:postcode":"s65 2ll",
    "addr:street":"Longfellow Drive",
    "iso:country":"GB",
    "sg:address":"84 Longfellow Drive",
    "sg:city":"Rotherham",
    "sg:classifiers":[
        {
            "category":"Organizations",
            "subcategory":"Non-profit Organization",
            "type":"Services"
        }
    ],
    "sg:postcode":"S65 2LL",
    "sg:province":"South Yorkshire",
    "sg:tags":[
        "organisation",
        "voluntary",
        "charity"
    ],
    "wof:name":"Save the Children Fund",
    "wof:placetype":"venue"
},
  "geometry": {"coordinates":[-1.3308490515,53.4250144958],"type":"Point"}
}