{
  "type": "Feature",
  "properties": {
    "addr:full":"7-9 Grove St Edinburgh City of Edinburgh EH3 8AF",
    "addr:housenumber":"7-9",
    "addr:postcode":"eh3 8af",
    "addr:street":"Grove St Edinburgh",
    "iso:country":"GB",
    "sg:address":"7-9 Grove St",
    "sg:city":"Edinburgh",
    "sg:classifiers":[
        {
            "category":"Shopping",
            "subcategory":"Department Store",
            "type":"Retail Goods"
        }
    ],
    "sg:postcode":"EH3 8AF",
    "sg:province":"City of Edinburgh",
    "wof:name":"Sweeney,M,",
    "wof:placetype":"venue"
},
  "geometry": {"coordinates":[-3.212668,55.945915],"type":"Point"}
}