{
  "type": "Feature",
  "properties": {
    "iso:country":"GB",
    "sg:address":"Pioneer House, Birmingham Street",
    "sg:city":"Halesowen",
    "sg:classifiers":[
        {
            "category":"Freight",
            "type":"Transportation"
        }
    ],
    "sg:phone":"+44 121 585 0303",
    "sg:postcode":"B63 3HN",
    "sg:province":"West Midlands",
    "sg:tags":[
        "forwarders"
    ],
    "wof:name":"Euro Freight Shipping Agencies Ltd.",
    "wof:placetype":"venue"
},
  "geometry": {"coordinates":[-2.049549,52.448246],"type":"Point"}
}