{
  "type": "Feature",
  "properties": {
    "addr:full":"50b Ealing Road Wembley Greater London HA0 4TQ",
    "addr:housenumber":"50b",
    "addr:postcode":"ha0 4tq",
    "addr:street":"Ealing Road",
    "iso:country":"GB",
    "sg:address":"50b Ealing Road",
    "sg:city":"Wembley",
    "sg:classifiers":[
        {
            "category":"Food & Beverages",
            "subcategory":"Candy",
            "type":"Retail Goods"
        },
        {
            "category":"Restaurant",
            "type":"Food & Drink"
        }
    ],
    "sg:phone":"+44 20 8902 8008",
    "sg:postcode":"HA0 4TQ",
    "sg:province":"Greater London",
    "sg:tags":[
        "confectioner",
        "vegetarian",
        "-"
    ],
    "wof:name":"Naklank Sweet Mart",
    "wof:placetype":"venue"
},
  "geometry": {"coordinates":[-0.2985709906,51.550327301],"type":"Point"}
}