{
  "type": "Feature",
  "properties": {
    "iso:country":"GB",
    "sg:address":"Oakhill House, Daisy Nook, Failsworth",
    "sg:city":"Manchester",
    "sg:classifiers":[
        {
            "category":"Building & Trades",
            "subcategory":"Construction",
            "type":"Services"
        }
    ],
    "sg:phone":"+44 161 339 3503",
    "sg:postcode":"M35 9WJ",
    "sg:province":"Lancashire",
    "sg:tags":[
        "builder"
    ],
    "wof:name":"D Whitehead Builders",
    "wof:placetype":"venue"
},
  "geometry": {"coordinates":[-2.248809,53.479622],"type":"Point"}
}