{
  "type": "Feature",
  "properties": {
    "addr:full":"615-617 Stretford Rd Manchester Cheshire M16 0QA",
    "addr:postcode":"615-617;m16 0qa",
    "addr:street":"Stretford Rd",
    "iso:country":"GB",
    "sg:address":"615-617 Stretford Rd",
    "sg:city":"Manchester",
    "sg:classifiers":[
        {
            "category":"Professional",
            "subcategory":"Detective & Security Services",
            "type":"Services"
        }
    ],
    "sg:phone":"+44 161 877 3301",
    "sg:postcode":"M16 0QA",
    "sg:province":"Cheshire",
    "sg:tags":[
        "car"
    ],
    "wof:name":"Sextons Toad Group",
    "wof:placetype":"venue"
},
  "geometry": {"coordinates":[-2.274659,53.462341],"type":"Point"}
}