{
  "type": "Feature",
  "properties": {
    "addr:full":"Padge Rd, Beeston Nottingham Nottinghamshire NG9 2JR",
    "addr:postcode":"ng9 2jr",
    "addr:street":"Padge Rd",
    "iso:country":"GB",
    "sg:address":"Padge Rd, Beeston",
    "sg:city":"Nottingham",
    "sg:classifiers":[
        {
            "category":"Wholesale",
            "subcategory":"Sporting Goods",
            "type":"Manufacturing & Wholesale Goods"
        }
    ],
    "sg:postcode":"NG9 2JR",
    "sg:province":"Nottinghamshire",
    "sg:tags":[
        "mnfr",
        "sport",
        "equipment"
    ],
    "wof:name":"Uhlsport (U K) Ltd",
    "wof:placetype":"venue"
},
  "geometry": {"coordinates":[-1.1992009878,52.9276008606],"type":"Point"}
}