{
  "type": "Feature",
  "properties": {
    "iso:country":"GB",
    "sg:address":"30a Runshaw La",
    "sg:city":"Chorley",
    "sg:classifiers":[
        {
            "category":"Real Estate",
            "subcategory":"Surveying",
            "type":"Services"
        }
    ],
    "sg:phone":"+44 1257 271090",
    "sg:postcode":"PR7 6AU",
    "sg:province":"Lancashire",
    "sg:tags":[
        "surveyor",
        "land"
    ],
    "wof:name":"Chris Heaton Surveys Ltd",
    "wof:placetype":"venue"
},
  "geometry": {"coordinates":[-2.6789638996,53.6701622009],"type":"Point"}
}