{
  "type": "Feature",
  "properties": {
    "addr:full":"Nightingale House, 1 Fulham High Street London Greater London SW6 3JH",
    "addr:housenumber":"1",
    "addr:postcode":"sw6 3jh",
    "addr:street":"Fulham High Street",
    "iso:country":"GB",
    "sg:address":"Nightingale House, 1 Fulham High Street",
    "sg:city":"London",
    "sg:classifiers":[
        {
            "category":"Professional",
            "type":"Services"
        }
    ],
    "sg:phone":"+44 20 7384 3028",
    "sg:postcode":"SW6 3JH",
    "sg:province":"Greater London",
    "sg:tags":[
        "exhibition"
    ],
    "wof:name":"R B C Opus",
    "wof:placetype":"venue"
},
  "geometry": {"coordinates":[-0.210947,51.471401],"type":"Point"}
}