{
  "type": "Feature",
  "properties": {
    "addr:full":"42 Cliffe High Street Lewes East Sussex BN7 2AN",
    "addr:housenumber":"42",
    "addr:postcode":"bn7 2an",
    "addr:street":"High Street",
    "iso:country":"GB",
    "sg:address":"42 Cliffe High Street",
    "sg:city":"Lewes",
    "sg:classifiers":[
        {
            "category":"Shopping",
            "subcategory":"Antiques",
            "type":"Retail Goods"
        }
    ],
    "sg:phone":"+44 1273 486866",
    "sg:postcode":"BN7 2AN",
    "sg:province":"East Sussex",
    "wof:name":"Emporium Antiques Centre",
    "wof:placetype":"venue"
},
  "geometry": {"coordinates":[0.017708,50.874142],"type":"Point"}
}