{
  "type": "Feature",
  "properties": {
    "addr:full":"Building, 81-82 First Avenue, Pensnett Trading Estate Brierley Hill Staffordshire DY6 7FJ",
    "addr:housenumber":"81-82",
    "addr:postcode":"dy6 7fj",
    "addr:street":"First Avenue Pensnett Trading Estate",
    "iso:country":"GB",
    "sg:address":"Building, 81-82 First Avenue, Pensnett Trading Estate",
    "sg:city":"Brierley Hill",
    "sg:classifiers":[
        {
            "category":"Home & Garden",
            "subcategory":"Hardware",
            "type":"Retail Goods"
        }
    ],
    "sg:phone":"+44 1384 276280",
    "sg:postcode":"DY6 7FJ",
    "sg:province":"Staffordshire",
    "sg:tags":[
        "device",
        "fixing",
        "fastener"
    ],
    "wof:name":"M L M Fasteners Ltd.",
    "wof:placetype":"venue"
},
  "geometry": {"coordinates":[-2.1466910839,52.5051727295],"type":"Point"}
}