{
  "type": "Feature",
  "properties": {
    "addr:full":"74 Pinnox Street Stoke-on-trent Staffordshire ST6 6AF",
    "addr:housenumber":"74",
    "addr:postcode":"st6 6af",
    "addr:street":"Pinnox Street",
    "iso:country":"GB",
    "sg:address":"74 Pinnox Street",
    "sg:city":"Stoke-on-trent",
    "sg:classifiers":[
        {
            "category":"Manufacturing",
            "subcategory":"Metals",
            "type":"Manufacturing & Wholesale Goods"
        }
    ],
    "sg:phone":"+44 1782 819901",
    "sg:postcode":"ST6 6AF",
    "sg:province":"Staffordshire",
    "sg:tags":[
        "steel",
        "fabricator",
        "erectors"
    ],
    "wof:name":"P Brammer Engineering",
    "wof:placetype":"venue"
},
  "geometry": {"coordinates":[-2.206987,53.054974],"type":"Point"}
}