{
  "type": "Feature",
  "properties": {
    "addr:full":"24 Commercial Square Leicester Leicestershire LE2 7SR",
    "addr:housenumber":"24",
    "addr:postcode":"le2 7sr",
    "addr:street":"Commercial Square",
    "iso:country":"GB",
    "sg:address":"24 Commercial Square",
    "sg:city":"Leicester",
    "sg:classifiers":[
        {
            "category":"Food & Beverages",
            "subcategory":"Fruits & Vegetables",
            "type":"Retail Goods"
        }
    ],
    "sg:phone":"+44 116 233 3252",
    "sg:postcode":"LE2 7SR",
    "sg:province":"Leicestershire",
    "sg:tags":[
        "greengrocer"
    ],
    "wof:name":"Adrian Dale Produce",
    "wof:placetype":"venue"
},
  "geometry": {"coordinates":[-1.134515,52.618084],"type":"Point"}
}