{
  "type": "Feature",
  "properties": {
    "iso:country":"GB",
    "sg:address":"Gidlow, Stockport Road, Thelwall",
    "sg:city":"Warrington",
    "sg:classifiers":[
        {
            "category":"Building & Trades",
            "subcategory":"Construction",
            "type":"Services"
        }
    ],
    "sg:phone":"+44 1925 602426",
    "sg:postcode":"WA4 2TB",
    "sg:province":"Cheshire",
    "sg:tags":[
        "joiner",
        "carpenter"
    ],
    "wof:name":"Moore Construction",
    "wof:placetype":"venue"
},
  "geometry": {"coordinates":[-2.533504,53.382641],"type":"Point"}
}