{
  "type": "Feature",
  "properties": {
    "addr:full":"24 Ravenoak Road, Woodsmoor Stockport Cheshire SK2 7BQ",
    "addr:housenumber":"24",
    "addr:postcode":"sk2 7bq",
    "addr:street":"Ravenoak Road Woodsmoor",
    "iso:country":"GB",
    "sg:address":"24 Ravenoak Road, Woodsmoor",
    "sg:city":"Stockport",
    "sg:classifiers":[
        {
            "category":"Organizations",
            "subcategory":"Non-profit Organization",
            "type":"Services"
        }
    ],
    "sg:phone":"+44 161 292 1083",
    "sg:postcode":"SK2 7BQ",
    "sg:province":"Cheshire",
    "sg:tags":[
        "organisation",
        "voluntary",
        "charity"
    ],
    "wof:name":"When You Wish upon A Star",
    "wof:placetype":"venue"
},
  "geometry": {"coordinates":[-2.14588,53.387856],"type":"Point"}
}