{
  "type": "Feature",
  "properties": {
    "addr:full":"Woodlands Road Chippenham Gloucestershire SN14 0HF",
    "addr:postcode":"sn14 0hf",
    "addr:street":"Woodlands Road",
    "iso:country":"GB",
    "sg:address":"Woodlands Road",
    "sg:city":"Chippenham",
    "sg:classifiers":[
        {
            "category":"Organizations",
            "subcategory":"Community Association",
            "type":"Services"
        },
        {
            "category":"Organizations",
            "subcategory":"Membership Organization",
            "type":"Services"
        }
    ],
    "sg:phone":"+44 1249 655594",
    "sg:postcode":"SN14 0HF",
    "sg:province":"Gloucestershire",
    "sg:tags":[
        "club",
        "social"
    ],
    "wof:name":"Loyalty Social Club",
    "wof:placetype":"venue"
},
  "geometry": {"coordinates":[-2.127754,51.463234],"type":"Point"}
}