{
  "type": "Feature",
  "properties": {
    "addr:full":"67 Wootton Road Bedford Bedfordshire MK43 9BJ",
    "addr:housenumber":"67",
    "addr:postcode":"mk43 9bj",
    "addr:street":"Wootton Road",
    "iso:country":"GB",
    "sg:address":"67 Wootton Road",
    "sg:city":"Bedford",
    "sg:classifiers":[
        {
            "category":"Professional",
            "type":"Services"
        }
    ],
    "sg:postcode":"MK43 9BJ",
    "sg:province":"Bedfordshire",
    "sg:tags":[
        "pattern",
        "industrial",
        "maker"
    ],
    "wof:name":"Kempston Precision Woodworking",
    "wof:placetype":"venue"
},
  "geometry": {"coordinates":[-0.527099,52.095749],"type":"Point"}
}