{
  "type": "Feature",
  "properties": {
    "addr:full":"27 Kent Walk Peterlee Durham SR8 2BN",
    "addr:housenumber":"27",
    "addr:postcode":"sr8 2bn",
    "addr:street":"Kent Walk",
    "iso:country":"GB",
    "sg:address":"27 Kent Walk",
    "sg:city":"Peterlee",
    "sg:classifiers":[
        {
            "category":"Shopping",
            "subcategory":"Photographic Equipment",
            "type":"Retail Goods"
        }
    ],
    "sg:phone":"+44 191 586 2389",
    "sg:postcode":"SR8 2BN",
    "sg:province":"Durham",
    "wof:name":"Sunshine Studio",
    "wof:placetype":"venue"
},
  "geometry": {"coordinates":[-1.3330550194,54.7609939575],"type":"Point"}
}