{
  "type": "Feature",
  "properties": {
    "iso:country":"GB",
    "sg:address":"14 Eastgate Square",
    "sg:city":"Pickering",
    "sg:classifiers":[
        {
            "category":"Health Services",
            "subcategory":"Optometrist",
            "type":"Services"
        },
        {
            "category":"Shopping",
            "subcategory":"Optician",
            "type":"Retail Goods"
        }
    ],
    "sg:phone":"+44 1751 472737",
    "sg:postcode":"YO18 7DP",
    "sg:province":"North Yorkshire",
    "sg:tags":[
        "ophthalmic"
    ],
    "wof:name":"Robinsons Opticians",
    "wof:placetype":"venue"
},
  "geometry": {"coordinates":[-0.7793880105,54.245010376],"type":"Point"}
}