{
  "type": "Feature",
  "properties": {
    "addr:full":"11 St Hilary's Drive Llandudno Junction Conwy LL31 9SS",
    "addr:housenumber":"11",
    "addr:postcode":"ll31 9ss",
    "addr:street":"St Hilary'S Drive",
    "iso:country":"GB",
    "sg:address":"11 St Hilary's Drive",
    "sg:city":"Llandudno Junction",
    "sg:classifiers":[
        {
            "category":"Building & Trades",
            "subcategory":"Plumbing",
            "type":"Services"
        },
        {
            "category":"Building & Trades",
            "subcategory":"Construction",
            "type":"Services"
        }
    ],
    "sg:phone":"+44 1492 584793",
    "sg:postcode":"LL31 9SS",
    "sg:province":"Conwy",
    "sg:tags":[
        "heating",
        "contractor"
    ],
    "wof:name":"David Roberts",
    "wof:placetype":"venue"
},
  "geometry": {"coordinates":[-3.818278,53.288609],"type":"Point"}
}