{
  "type": "Feature",
  "properties": {
    "addr:full":"3 Fishers Close, Kilsby Rugby Northamptonshire CV23 8XH",
    "addr:housenumber":"3",
    "addr:postcode":"kilsby;cv23 8xh",
    "addr:street":"Fishers Close",
    "iso:country":"GB",
    "sg:address":"3 Fishers Close, Kilsby",
    "sg:city":"Rugby",
    "sg:classifiers":[
        {
            "category":"Building & Trades",
            "subcategory":"Cleaning & Sanitation",
            "type":"Services"
        }
    ],
    "sg:phone":"+44 1788 823515",
    "sg:postcode":"CV23 8XH",
    "sg:province":"Northamptonshire",
    "sg:tags":[
        "contracting",
        "commercial"
    ],
    "wof:name":"Scrubbers Cleaning Service",
    "wof:placetype":"venue"
},
  "geometry": {"coordinates":[-1.1787439585,52.3329277039],"type":"Point"}
}