{
  "type": "Feature",
  "properties": {
    "addr:full":"1 Lumley St, Mayfair London Greater London W1K 6NB",
    "addr:housenumber":"1",
    "addr:postcode":"w1k 6nb",
    "addr:street":"Lumley St",
    "iso:country":"GB",
    "sg:address":"1 Lumley St, Mayfair",
    "sg:city":"London",
    "sg:classifiers":[
        {
            "category":"Professional",
            "type":"Services"
        }
    ],
    "sg:postcode":"W1K 6NB",
    "sg:province":"Greater London",
    "sg:tags":[
        "caterer"
    ],
    "wof:name":"Cuisine Naturelle Ltd",
    "wof:placetype":"venue"
},
  "geometry": {"coordinates":[-0.1517190039,51.5135612488],"type":"Point"}
}