{
  "type": "Feature",
  "properties": {
    "iso:country":"GB",
    "sg:address":"57 Lonsdale Road",
    "sg:city":"Southend-on-sea",
    "sg:classifiers":[
        {
            "category":"Government",
            "subcategory":"Post Office",
            "type":"Public Place"
        }
    ],
    "sg:postcode":"SS2 4LX",
    "sg:province":"Essex",
    "wof:name":"Lonsdale Road Post Office",
    "wof:placetype":"venue"
},
  "geometry": {"coordinates":[0.7335090041,51.546005249],"type":"Point"}
}