{
  "type": "Feature",
  "properties": {
    "iso:country":"GB",
    "sg:address":"22 Wind St",
    "sg:city":"Swansea",
    "sg:classifiers":[
        {
            "category":"Restaurant",
            "type":"Food & Drink"
        }
    ],
    "sg:postcode":"SA1 2DY",
    "sg:province":"Neath Port Talbot",
    "wof:name":"Cafe Devereaux",
    "wof:placetype":"venue"
},
  "geometry": {"coordinates":[-3.9394850731,51.619392395],"type":"Point"}
}