{
  "type": "Feature",
  "properties": {
    "iso:country":"GB",
    "sg:address":"North Orbital Rd",
    "sg:city":"West Malling",
    "sg:classifiers":[
        {
            "category":"Shopping",
            "subcategory":"Pharmacy",
            "type":"Retail Goods"
        }
    ],
    "sg:phone":"+44 1732 584000",
    "sg:postcode":"ME19 4AH",
    "sg:province":"Kent",
    "sg:tags":[
        "pharmaceutical"
    ],
    "wof:name":"Aventis",
    "wof:placetype":"venue"
},
  "geometry": {"coordinates":[0.4129399955,51.2937088013],"type":"Point"}
}