{
  "type": "Feature",
  "properties": {
    "iso:country":"GB",
    "sg:address":"Market Hall, Grosvenor",
    "sg:city":"Macclesfield",
    "sg:classifiers":[
        {
            "category":"Shopping",
            "subcategory":"Crafts & Fabrics",
            "type":"Retail Goods"
        }
    ],
    "sg:postcode":"SK11 6AB",
    "sg:province":"Cheshire",
    "sg:tags":[
        "shop"
    ],
    "wof:name":"W K Yates Fabrics",
    "wof:placetype":"venue"
},
  "geometry": {"coordinates":[-2.125756,53.255669],"type":"Point"}
}