{
  "type": "Feature",
  "properties": {
    "iso:country":"GB",
    "sg:address":"162 Bolton Road, Worsley",
    "sg:city":"Manchester",
    "sg:classifiers":[
        {
            "category":"Personal",
            "subcategory":"Barber",
            "type":"Services"
        }
    ],
    "sg:phone":"+44 161 703 8853",
    "sg:postcode":"M28 3BN",
    "sg:province":"Greater Manchester",
    "sg:tags":[
        "men's",
        "hairdresser"
    ],
    "wof:name":"The Barber Shop",
    "wof:placetype":"venue"
},
  "geometry": {"coordinates":[-2.3997058868,53.5279808044],"type":"Point"}
}