{
  "type": "Feature",
  "properties": {
    "iso:country":"GB",
    "sg:address":"Limes Ho, Purfleet St",
    "sg:city":"King's Lynn",
    "sg:classifiers":[
        {
            "category":"Communications",
            "subcategory":"Newspaper",
            "type":"Services"
        }
    ],
    "sg:phone":"+44 1553 692006",
    "sg:postcode":"PE30 1HL",
    "sg:province":"Norfolk",
    "sg:tags":[
        "magazine"
    ],
    "wof:name":"Citizen The",
    "wof:placetype":"venue"
},
  "geometry": {"coordinates":[0.39472,52.75375],"type":"Point"}
}