{
  "type": "Feature",
  "properties": {
    "addr:full":"233 High St Crowthorne Berkshire RG45 7AH",
    "addr:housenumber":"233",
    "addr:postcode":"rg45 7ah",
    "addr:street":"High St",
    "iso:country":"GB",
    "sg:address":"233 High St",
    "sg:city":"Crowthorne",
    "sg:classifiers":[
        {
            "category":"Professional",
            "subcategory":"Computer Services",
            "type":"Services"
        }
    ],
    "sg:postcode":"RG45 7AH",
    "sg:province":"Berkshire",
    "sg:tags":[
        "system",
        "software"
    ],
    "wof:name":"Montague,Wade,",
    "wof:placetype":"venue"
},
  "geometry": {"coordinates":[-0.794131,51.367371],"type":"Point"}
}