{
  "type": "Feature",
  "properties": {
    "addr:full":"3 Orchard Close, Copford Green Colchester Essex CO6 1DB",
    "addr:housenumber":"3",
    "addr:postcode":"co6 1db",
    "addr:street":"Orchard Close",
    "iso:country":"GB",
    "sg:address":"3 Orchard Close, Copford Green",
    "sg:city":"Colchester",
    "sg:classifiers":[
        {
            "category":"Education",
            "subcategory":"School",
            "type":"Public Place"
        }
    ],
    "sg:phone":"+44 1376 573573",
    "sg:postcode":"CO6 1DB",
    "sg:province":"Essex",
    "sg:tags":[
        "local",
        "authority"
    ],
    "wof:name":"Leasing Life Training Ltd.",
    "wof:placetype":"venue"
},
  "geometry": {"coordinates":[0.801306,51.868519],"type":"Point"}
}