{
  "type": "Feature",
  "properties": {
    "iso:country":"GB",
    "sg:address":"Erroll Court",
    "sg:city":"Turriff",
    "sg:classifiers":[
        {
            "category":"Government",
            "subcategory":"Office",
            "type":"Public Place"
        },
        {
            "category":"Social Services",
            "subcategory":"Adult Care",
            "type":"Services"
        },
        {
            "category":"Social Services",
            "subcategory":"Retirement Home",
            "type":"Services"
        }
    ],
    "sg:phone":"+44 1888 562577",
    "sg:postcode":"AB53 4LZ",
    "sg:province":"Aberdeenshire",
    "sg:tags":[
        "housing",
        "local",
        "accommodation",
        "sheltered"
    ],
    "wof:name":"Erroll Court Sheltered Housing",
    "wof:placetype":"venue"
},
  "geometry": {"coordinates":[-2.455229,57.539902],"type":"Point"}
}