{
  "type": "Feature",
  "properties": {
    "iso:country":"GB",
    "sg:address":"Fire Station, Lichfield Road",
    "sg:city":"Sutton Coldfield",
    "sg:classifiers":[
        {
            "category":"Government",
            "subcategory":"Fire Station",
            "type":"Public Place"
        }
    ],
    "sg:phone":"+44 121 354 3663",
    "sg:postcode":"B74 2NT",
    "sg:province":"Staffordshire",
    "wof:name":"West Midlands Fire Service",
    "wof:placetype":"venue"
},
  "geometry": {"coordinates":[-1.830194,52.58754],"type":"Point"}
}