{
  "type": "Feature",
  "properties": {
    "iso:country":"GB",
    "sg:address":"30 Woodbridge Road",
    "sg:city":"Ipswich",
    "sg:classifiers":[
        {
            "category":"Home & Garden",
            "subcategory":"Furniture",
            "type":"Retail Goods"
        }
    ],
    "sg:postcode":"IP4 2EG",
    "sg:province":"Suffolk",
    "wof:name":"Stollhope Ltd.",
    "wof:placetype":"venue"
},
  "geometry": {"coordinates":[1.160447,52.057968],"type":"Point"}
}