{
  "type": "Feature",
  "properties": {
    "addr:full":"Manor Farm, Newark Road, Cotham Newark Lincolnshire NG23 5JS",
    "addr:postcode":"ng23 5js",
    "addr:street":"Manor;Newark Road",
    "iso:country":"GB",
    "sg:address":"Manor Farm, Newark Road, Cotham",
    "sg:city":"Newark",
    "sg:classifiers":[
        {
            "category":"Shopping",
            "subcategory":"Antiques",
            "type":"Retail Goods"
        }
    ],
    "sg:postcode":"NG23 5JS",
    "sg:province":"Lincolnshire",
    "wof:name":"R A Berry Antiques",
    "wof:placetype":"venue"
},
  "geometry": {"coordinates":[-0.8150290251,53.0184669495],"type":"Point"}
}