{
  "type": "Feature",
  "properties": {
    "iso:country":"GB",
    "sg:address":"87 High St",
    "sg:city":"New Malden",
    "sg:classifiers":[
        {
            "category":"Food & Beverages",
            "subcategory":"Bakery",
            "type":"Retail Goods"
        }
    ],
    "sg:phone":"+44 20 8949 9130",
    "sg:postcode":"KT3 4BP",
    "sg:province":"Surrey",
    "sg:tags":[
        "baker"
    ],
    "wof:name":"Manuels Bakery",
    "wof:placetype":"venue"
},
  "geometry": {"coordinates":[-0.2560839951,51.4010848999],"type":"Point"}
}