{
  "type": "Feature",
  "properties": {
    "iso:country":"GB",
    "sg:address":"Unit 1, Valley Road Business Park",
    "sg:city":"Keighley",
    "sg:classifiers":[
        {
            "category":"Shopping",
            "type":"Retail Goods"
        }
    ],
    "sg:phone":"+44 1535 609516",
    "sg:postcode":"BD21 4LZ",
    "sg:province":"West Yorkshire",
    "sg:tags":[
        "part",
        "accessory"
    ],
    "wof:name":"B M S Auto's",
    "wof:placetype":"venue"
},
  "geometry": {"coordinates":[-1.887134,53.86956],"type":"Point"}
}