{
  "type": "Feature",
  "properties": {
    "addr:full":"12 High St Maidenhead Berkshire SL6 1QJ",
    "addr:housenumber":"12",
    "addr:postcode":"sl6 1qj",
    "addr:street":"High St",
    "iso:country":"GB",
    "sg:address":"12 High St",
    "sg:city":"Maidenhead",
    "sg:classifiers":[
        {
            "category":"Shopping",
            "subcategory":"Clothing, Apparel, & Fashions",
            "type":"Retail Goods"
        }
    ],
    "sg:phone":"+44 1628 672610",
    "sg:postcode":"SL6 1QJ",
    "sg:province":"Berkshire",
    "sg:tags":[
        "menswear"
    ],
    "wof:name":"Michael Chell",
    "wof:placetype":"venue"
},
  "geometry": {"coordinates":[-0.7178500295,51.5231018066],"type":"Point"}
}