{
  "type": "Feature",
  "properties": {
    "addr:full":"10 Wollaton Avenue Sheffield Derbyshire S17 4LA",
    "addr:housenumber":"10",
    "addr:postcode":"s17 4la",
    "addr:street":"Wollaton Avenue",
    "iso:country":"GB",
    "sg:address":"10 Wollaton Avenue",
    "sg:city":"Sheffield",
    "sg:classifiers":[
        {
            "category":"Health Services",
            "subcategory":"Nursing And Care Facility",
            "type":"Services"
        }
    ],
    "sg:phone":"+44 114 236 9906",
    "sg:postcode":"S17 4LA",
    "sg:province":"Derbyshire",
    "sg:tags":[
        "agency"
    ],
    "wof:name":"Guardian Angels Bureau Ltd",
    "wof:placetype":"venue"
},
  "geometry": {"coordinates":[-1.519767046,53.317615509],"type":"Point"}
}