{
  "type": "Feature",
  "properties": {
    "iso:country":"GB",
    "sg:address":"34a Queenstown Rd",
    "sg:city":"South Lambeth",
    "sg:classifiers":[
        {
            "category":"Restaurant",
            "type":"Food & Drink"
        }
    ],
    "sg:phone":"+44 20 7720 1161",
    "sg:postcode":"SW8 3RX",
    "sg:province":"Greater London",
    "wof:name":"Princetel Ltd",
    "wof:placetype":"venue"
},
  "geometry": {"coordinates":[-0.150443,51.467461],"type":"Point"}
}