{
  "type": "Feature",
  "properties": {
    "addr:full":"2 High Street, Saxilby Lincoln Lincolnshire LN1 2LN",
    "addr:housenumber":"2",
    "addr:postcode":"ln1 2ln",
    "addr:street":"High Street",
    "iso:country":"GB",
    "sg:address":"2 High Street, Saxilby",
    "sg:city":"Lincoln",
    "sg:classifiers":[
        {
            "category":"Manufacturing",
            "subcategory":"Wood Products",
            "type":"Manufacturing & Wholesale Goods"
        }
    ],
    "sg:postcode":"LN1 2LN",
    "sg:province":"Lincolnshire",
    "sg:tags":[
        "maker",
        "cabinet"
    ],
    "wof:name":"K A Jubb Cabinet Makers",
    "wof:placetype":"venue"
},
  "geometry": {"coordinates":[-0.576975,53.339947],"type":"Point"}
}