{
  "type": "Feature",
  "properties": {
    "iso:country":"GB",
    "sg:address":"Jennings Way",
    "sg:city":"Hemel Hempstead",
    "sg:classifiers":[
        {
            "category":"Organizations",
            "subcategory":"Community Association",
            "type":"Services"
        }
    ],
    "sg:phone":"+44 1442 245701",
    "sg:postcode":"HP3 9XG",
    "sg:province":"Hertfordshire",
    "sg:tags":[
        "society",
        "housing"
    ],
    "wof:name":"Paddington Churches Housing Association",
    "wof:placetype":"venue"
},
  "geometry": {"coordinates":[-0.4607689977,51.7457008362],"type":"Point"}
}