{
  "type": "Feature",
  "properties": {
    "iso:country":"GB",
    "sg:address":"220 Main Street, Barrhead",
    "sg:city":"Glasgow",
    "sg:classifiers":[
        {
            "category":"Personal",
            "subcategory":"Beauty Salon",
            "type":"Services"
        }
    ],
    "sg:phone":"+44 141 881 4137",
    "sg:postcode":"G78 1SN",
    "sg:province":"East Ayrshire",
    "sg:tags":[
        "unisex",
        "hairdresser"
    ],
    "wof:name":"James Taylor",
    "wof:placetype":"venue"
},
  "geometry": {"coordinates":[-4.386815,55.801846],"type":"Point"}
}