{
  "type": "Feature",
  "properties": {
    "iso:country":"GB",
    "sg:address":"Clyst Heath, Woodwater Lane",
    "sg:city":"Exeter",
    "sg:classifiers":[
        {
            "category":"Shopping",
            "subcategory":"Pharmacy",
            "type":"Retail Goods"
        }
    ],
    "sg:postcode":"EX2 7EY",
    "sg:province":"Devon",
    "sg:tags":[
        "medicine",
        "therapy"
    ],
    "wof:name":"H Read",
    "wof:placetype":"venue"
},
  "geometry": {"coordinates":[-3.461369,50.71159],"type":"Point"}
}