{
  "type": "Feature",
  "properties": {
    "iso:country":"GB",
    "sg:address":"Unit 16, Riverside Way, Ravensthorpe Indstl Est",
    "sg:city":"Dewsbury",
    "sg:classifiers":[
        {
            "category":"Manufacturing",
            "subcategory":"Metals",
            "type":"Manufacturing & Wholesale Goods"
        }
    ],
    "sg:postcode":"WF13 3LG",
    "sg:province":"West Yorkshire",
    "sg:tags":[
        "steel",
        "stockholder"
    ],
    "wof:name":"Riverside Stainless",
    "wof:placetype":"venue"
},
  "geometry": {"coordinates":[-1.6660369635,53.6760406494],"type":"Point"}
}