{
  "type": "Feature",
  "properties": {
    "iso:country":"GB",
    "sg:address":"32 Barnton Gardens",
    "sg:city":"Edinburgh",
    "sg:classifiers":[
        {
            "category":"Professional",
            "subcategory":"Management & Consulting",
            "type":"Services"
        },
        {
            "category":"Professional",
            "subcategory":"Advertising",
            "type":"Services"
        }
    ],
    "sg:phone":"+44 131 312 7771",
    "sg:postcode":"EH4 6AE",
    "sg:province":"City of Edinburgh",
    "sg:tags":[
        "marketing",
        "agency",
        "consultant"
    ],
    "wof:name":"The Gupta Partnership",
    "wof:placetype":"venue"
},
  "geometry": {"coordinates":[-3.301197052,55.9681358337],"type":"Point"}
}