{
  "type": "Feature",
  "properties": {
    "addr:full":"337 Red Bank Road Blackpool Lancashire FY2 0HJ",
    "addr:housenumber":"337",
    "addr:postcode":"fy2 0hj",
    "addr:street":"Red Bank Road",
    "iso:country":"GB",
    "sg:address":"337 Red Bank Road",
    "sg:city":"Blackpool",
    "sg:classifiers":[
        {
            "category":"Food & Beverages",
            "subcategory":"Bakery",
            "type":"Retail Goods"
        }
    ],
    "sg:phone":"+44 1253 500391",
    "sg:postcode":"FY2 0HJ",
    "sg:province":"Lancashire",
    "sg:tags":[
        "baker"
    ],
    "wof:name":"Hamptons",
    "wof:placetype":"venue"
},
  "geometry": {"coordinates":[-3.0400679111,53.8521194458],"type":"Point"}
}