{
  "type": "Feature",
  "properties": {
    "addr:full":"Bentley Lane, Bispham Ormskirk Lancashire L40 3SW",
    "addr:postcode":"l40 3sw",
    "addr:street":"Bentley Lane",
    "iso:country":"GB",
    "sg:address":"Bentley Lane, Bispham",
    "sg:city":"Ormskirk",
    "sg:classifiers":[
        {
            "category":"Farming",
            "subcategory":"Dairy Farm",
            "type":"Manufacturing & Wholesale Goods"
        },
        {
            "category":"Food & Beverages",
            "subcategory":"Groceries & Convenience Stores",
            "type":"Retail Goods"
        }
    ],
    "sg:phone":"+44 1704 822238",
    "sg:postcode":"L40 3SW",
    "sg:province":"Lancashire",
    "wof:name":"J V & S H Rowland & Sons Ltd.",
    "wof:placetype":"venue"
},
  "geometry": {"coordinates":[-2.7742140293,53.6155281067],"type":"Point"}
}