{
  "type": "Feature",
  "properties": {
    "iso:country":"GB",
    "sg:address":"2 Swallows Meadow, Off Cranmore Boulevard, Shirley",
    "sg:city":"Solihull",
    "sg:classifiers":[
        {
            "category":"Health Services",
            "subcategory":"Nursing And Care Facility",
            "type":"Services"
        },
        {
            "category":"Government",
            "subcategory":"Office",
            "type":"Public Place"
        }
    ],
    "sg:phone":"+44 121 733 7582",
    "sg:postcode":"B90 4QA",
    "sg:province":"West Midlands",
    "sg:tags":[
        "project",
        "gov",
        "community",
        "home"
    ],
    "wof:name":"Swallows Meadow Nursing Home",
    "wof:placetype":"venue"
},
  "geometry": {"coordinates":[-1.8131949902,52.3965263367],"type":"Point"}
}