{
  "type": "Feature",
  "properties": {
    "addr:full":"115-119 Camden High Street London Greater London NW1 7JS",
    "addr:housenumber":"115-119",
    "addr:postcode":"nw1 7js",
    "addr:street":"Camden High Street",
    "iso:country":"GB",
    "sg:address":"115-119 Camden High Street",
    "sg:city":"London",
    "sg:classifiers":[
        {
            "category":"Shopping",
            "subcategory":"Department Store",
            "type":"Retail Goods"
        }
    ],
    "sg:phone":"+44 20 7485 3932",
    "sg:postcode":"NW1 7JS",
    "sg:province":"Greater London",
    "sg:tags":[
        "departmental"
    ],
    "wof:name":"Woolworths plc",
    "wof:placetype":"venue"
},
  "geometry": {"coordinates":[-0.141524,51.537415],"type":"Point"}
}