{
  "type": "Feature",
  "properties": {
    "addr:full":"3 Barkeley Vale Falmouth Cornwall TR11 3PL",
    "addr:housenumber":"3",
    "addr:postcode":"tr11 3pl",
    "addr:street":"Barkeley Vale",
    "iso:country":"GB",
    "sg:address":"3 Barkeley Vale",
    "sg:city":"Falmouth",
    "sg:classifiers":[
        {
            "category":"Community Center",
            "subcategory":"Social",
            "type":"Public Place"
        }
    ],
    "sg:phone":"+44 1326 211545",
    "sg:postcode":"TR11 3PL",
    "sg:province":"Cornwall",
    "sg:tags":[
        "frozen",
        "food",
        "freezer",
        "centre"
    ],
    "wof:name":"Iceland Foods Plc",
    "wof:placetype":"venue"
},
  "geometry": {"coordinates":[-5.0735440254,50.1543312073],"type":"Point"}
}