{
  "type": "Feature",
  "properties": {
    "iso:country":"GB",
    "sg:address":"Unit 9 Southlands Centre, Ormesby Road",
    "sg:city":"Middlesbrough",
    "sg:classifiers":[
        {
            "category":"Home & Garden",
            "subcategory":"Household Appliances",
            "type":"Retail Goods"
        }
    ],
    "sg:phone":"+44 1642 300640",
    "sg:postcode":"TS3 0HB",
    "sg:province":"North Yorkshire",
    "sg:tags":[
        "electrical"
    ],
    "wof:name":"Kwik Fix Domestic Appliance Repairs",
    "wof:placetype":"venue"
},
  "geometry": {"coordinates":[-1.19156,54.55344],"type":"Point"}
}