{
  "type": "Feature",
  "properties": {
    "addr:full":"The Rise, Main St, Kirkby Malzeard Ripon North Yorkshire HG4 3RY",
    "addr:postcode":"hg4 3ry",
    "addr:street":"The Rise Main St",
    "iso:country":"GB",
    "sg:address":"The Rise, Main St, Kirkby Malzeard",
    "sg:city":"Ripon",
    "sg:classifiers":[
        {
            "category":"Professional",
            "type":"Services"
        },
        {
            "category":"Banks & Credit Unions",
            "subcategory":"Investment Brokerage",
            "type":"Services"
        }
    ],
    "sg:phone":"+44 1765 658407",
    "sg:postcode":"HG4 3RY",
    "sg:province":"North Yorkshire",
    "sg:tags":[
        "farm",
        "agricultural",
        "contractor"
    ],
    "wof:name":"G W Mawer",
    "wof:placetype":"venue"
},
  "geometry": {"coordinates":[-1.6484639645,54.1642189026],"type":"Point"}
}