{
  "type": "Feature",
  "properties": {
    "addr:full":"13a Marsh Lane, Henstridge Templecombe Somerset BA8 0TG",
    "addr:housenumber":"13a",
    "addr:postcode":"ba8 0tg",
    "addr:street":"Marsh Lane",
    "iso:country":"GB",
    "sg:address":"13a Marsh Lane, Henstridge",
    "sg:city":"Templecombe",
    "sg:classifiers":[
        {
            "category":"Utilities",
            "subcategory":"Refuse",
            "type":"Services"
        }
    ],
    "sg:phone":"+44 1963 363656",
    "sg:postcode":"BA8 0TG",
    "sg:province":"Somerset",
    "sg:tags":[
        "skip",
        "hire"
    ],
    "wof:name":"Churngold Waste Management",
    "wof:placetype":"venue"
},
  "geometry": {"coordinates":[-2.370646,50.980526],"type":"Point"}
}