{
  "type": "Feature",
  "properties": {
    "iso:country":"GB",
    "sg:address":"88-94 Wentworth St",
    "sg:city":"Whitechapel",
    "sg:classifiers":[
        {
            "category":"Wholesale",
            "subcategory":"Apparel",
            "type":"Manufacturing & Wholesale Goods"
        }
    ],
    "sg:phone":"+44 20 7375 2244",
    "sg:postcode":"E1 7SA",
    "sg:province":"Greater London",
    "sg:tags":[
        "babywear",
        "childrens"
    ],
    "wof:name":"Sunny's Wholesale",
    "wof:placetype":"venue"
},
  "geometry": {"coordinates":[-0.071232,51.517075],"type":"Point"}
}