{
  "type": "Feature",
  "properties": {
    "iso:country":"GB",
    "sg:address":"Orchard Ho, Orchard Av",
    "sg:city":"Clevedon",
    "sg:classifiers":[
        {
            "category":"Education",
            "subcategory":"Special Training",
            "type":"Public Place"
        }
    ],
    "sg:phone":"+44 1275 819040",
    "sg:postcode":"BS21 6RQ",
    "sg:province":"Somerset",
    "sg:tags":[
        "product",
        "centre"
    ],
    "wof:name":"Coverpoint Legal Training",
    "wof:placetype":"venue"
},
  "geometry": {"coordinates":[-2.806189,51.444145],"type":"Point"}
}