{
  "type": "Feature",
  "properties": {
    "addr:full":"252 Lampton Rd Hounslow Greater London TW3 4EX",
    "addr:housenumber":"252",
    "addr:postcode":"tw3 4ex",
    "addr:street":"Lampton Rd",
    "iso:country":"GB",
    "sg:address":"252 Lampton Rd",
    "sg:city":"Hounslow",
    "sg:classifiers":[
        {
            "category":"Shopping",
            "type":"Retail Goods"
        }
    ],
    "sg:phone":"+44 20 8737 8444",
    "sg:postcode":"TW3 4EX",
    "sg:province":"Greater London",
    "sg:tags":[
        "household",
        "store"
    ],
    "wof:name":"Eurobell Associates Ltd",
    "wof:placetype":"venue"
},
  "geometry": {"coordinates":[-0.363601,51.477768],"type":"Point"}
}