{
  "type": "Feature",
  "properties": {
    "addr:full":"60 Hillbrow Beckenham Kent BR1 2PQ",
    "addr:housenumber":"60",
    "addr:postcode":"br1 2pq",
    "addr:street":"Hillbrow",
    "iso:country":"GB",
    "sg:address":"60 Hillbrow",
    "sg:city":"Beckenham",
    "sg:classifiers":[
        {
            "category":"Real Estate",
            "subcategory":"Surveying",
            "type":"Services"
        }
    ],
    "sg:phone":"+44 20 8778 7777",
    "sg:postcode":"BR1 2PQ",
    "sg:province":"Kent",
    "sg:tags":[
        "surveyor",
        "quantity"
    ],
    "wof:name":"Vincent & Partners",
    "wof:placetype":"venue"
},
  "geometry": {"coordinates":[0.0396700017,51.4082298279],"type":"Point"}
}