{
  "type": "Feature",
  "properties": {
    "addr:full":"New Loom Ho, 101 Back Church La Whitechapel Greater London E1 1LU",
    "addr:housenumber":"101",
    "addr:postcode":"e1 1lu",
    "addr:street":"Back Church La Whitechapel",
    "iso:country":"GB",
    "sg:address":"New Loom Ho, 101 Back Church La",
    "sg:city":"Whitechapel",
    "sg:classifiers":[
        {
            "category":"Utilities",
            "subcategory":"Cable",
            "type":"Services"
        }
    ],
    "sg:phone":"+44 20 7702 9677",
    "sg:postcode":"E1 1LU",
    "sg:province":"Greater London",
    "sg:tags":[
        "tv"
    ],
    "wof:name":"Kelly Technical Services",
    "wof:placetype":"venue"
},
  "geometry": {"coordinates":[-0.06717,51.512699],"type":"Point"}
}