{
  "type": "Feature",
  "properties": {
    "iso:country":"GB",
    "sg:address":"Four Lane Ends",
    "sg:city":"Skipton",
    "sg:classifiers":[
        {
            "category":"Wholesale",
            "subcategory":"Construction Materials",
            "type":"Manufacturing & Wholesale Goods"
        },
        {
            "category":"Manufacturing",
            "subcategory":"Glass & Minerals",
            "type":"Manufacturing & Wholesale Goods"
        }
    ],
    "sg:phone":"+44 1756 799415",
    "sg:postcode":"BD23 6AD",
    "sg:province":"Lancashire",
    "sg:tags":[
        "stone",
        "asphalt",
        "slate",
        "macadam",
        "chalk",
        "whole"
    ],
    "wof:name":"Tarmac Quarry Products Ltd.",
    "wof:placetype":"venue"
},
  "geometry": {"coordinates":[-2.0185139179,53.9602012634],"type":"Point"}
}