{
  "type": "Feature",
  "properties": {
    "iso:country":"GB",
    "sg:address":"8c Victoria Dr",
    "sg:city":"Wimbledon",
    "sg:classifiers":[
        {
            "category":"Health Services",
            "subcategory":"Doctor",
            "type":"Services"
        }
    ],
    "sg:phone":"+44 20 8780 1040",
    "sg:postcode":"SW19 6AE",
    "sg:province":"Greater London",
    "sg:tags":[
        "practitioners"
    ],
    "wof:name":"Moudgil, V K",
    "wof:placetype":"venue"
},
  "geometry": {"coordinates":[-0.219804,51.446411],"type":"Point"}
}