{
  "type": "Feature",
  "properties": {
    "addr:full":"Willows Farm, Wanlip Road, Syston Leicester Leicestershire LE7 8PD",
    "addr:postcode":"le7 8pd",
    "addr:street":"Wanlip Road",
    "iso:country":"GB",
    "sg:address":"Willows Farm, Wanlip Road, Syston",
    "sg:city":"Leicester",
    "sg:classifiers":[
        {
            "category":"Recreation",
            "subcategory":"Fishing",
            "type":"Entertainment"
        }
    ],
    "sg:postcode":"LE7 8PD",
    "sg:province":"Leicestershire",
    "sg:tags":[
        "angling"
    ],
    "wof:name":"Willows Farm Fishing",
    "wof:placetype":"venue"
},
  "geometry": {"coordinates":[-1.0096900463,52.6745491028],"type":"Point"}
}