{
  "type": "Feature",
  "properties": {
    "iso:country":"GB",
    "sg:address":"Ribbleton Hall Drive, Ribbleton",
    "sg:city":"Preston",
    "sg:classifiers":[
        {
            "category":"Education",
            "subcategory":"School",
            "type":"Public Place"
        }
    ],
    "sg:phone":"+44 1772 651110",
    "sg:postcode":"PR2 6EE",
    "sg:province":"Lancashire",
    "sg:tags":[
        "local",
        "authority"
    ],
    "wof:name":"Ribbleton Hall High School",
    "wof:placetype":"venue"
},
  "geometry": {"coordinates":[-2.659434,53.777496],"type":"Point"}
}