{
  "type": "Feature",
  "properties": {
    "addr:full":"5 Glebe Crescent, New Bilton Rugby Warwickshire CV21 2HG",
    "addr:housenumber":"5",
    "addr:postcode":"cv21 2hg",
    "addr:street":"Glebe Crescent",
    "iso:country":"GB",
    "sg:address":"5 Glebe Crescent, New Bilton",
    "sg:city":"Rugby",
    "sg:classifiers":[
        {
            "category":"Health Services",
            "subcategory":"Nursing And Care Facility",
            "type":"Services"
        }
    ],
    "sg:phone":"+44 1788 826967",
    "sg:postcode":"CV21 2HG",
    "sg:province":"Warwickshire",
    "sg:tags":[
        "agency"
    ],
    "wof:name":"Linda's Care Agency",
    "wof:placetype":"venue"
},
  "geometry": {"coordinates":[-1.2759950161,52.372177124],"type":"Point"}
}