{
  "type": "Feature",
  "properties": {
    "addr:full":"756c Old Edinburgh Road, Uddingston Glasgow Glasgow City G71 6LA",
    "addr:housenumber":"756c",
    "addr:postcode":"g71 6la",
    "addr:street":"Old Edinburgh Road",
    "iso:country":"GB",
    "sg:address":"756c Old Edinburgh Road, Uddingston",
    "sg:city":"Glasgow",
    "sg:classifiers":[
        {
            "category":"Shopping",
            "subcategory":"News",
            "type":"Retail Goods"
        }
    ],
    "sg:phone":"+44 1698 327138",
    "sg:postcode":"G71 6LA",
    "sg:province":"Glasgow City",
    "sg:tags":[
        "newsagent"
    ],
    "wof:name":"H Differ",
    "wof:placetype":"venue"
},
  "geometry": {"coordinates":[-4.0510630608,55.8237113953],"type":"Point"}
}