{
  "type": "Feature",
  "properties": {
    "addr:full":"St Georges Place Northwich Cheshire CW8 4WE",
    "addr:postcode":"cw8 4we",
    "addr:street":"St Georges Place",
    "iso:country":"GB",
    "sg:address":"St Georges Place",
    "sg:city":"Northwich",
    "sg:classifiers":[
        {
            "category":"Professional",
            "subcategory":"Accounting & Tax Preparation",
            "type":"Services"
        }
    ],
    "sg:postcode":"CW8 4WE",
    "sg:province":"Cheshire",
    "sg:tags":[
        "accountant"
    ],
    "wof:name":"Bennett Brooks & Co. Ltd.",
    "wof:placetype":"venue"
},
  "geometry": {"coordinates":[-2.514469,53.247486],"type":"Point"}
}