{
  "type": "Feature",
  "properties": {
    "iso:country":"GB",
    "sg:address":"43 Carr Street",
    "sg:city":"Ipswich",
    "sg:classifiers":[
        {
            "category":"Home & Garden",
            "subcategory":"Furniture",
            "type":"Retail Goods"
        }
    ],
    "sg:phone":"+44 1473 219609",
    "sg:postcode":"IP4 1HA",
    "sg:province":"Suffolk",
    "wof:name":"Exmoor Pine Ltd.",
    "wof:placetype":"venue"
},
  "geometry": {"coordinates":[1.158173,52.057526],"type":"Point"}
}