{
  "type": "Feature",
  "properties": {
    "addr:full":"Jury St Centre Manchester Greater Manchester M8 8FN",
    "addr:postcode":"m8 8fn",
    "addr:street":"Jury St",
    "iso:country":"GB",
    "sg:address":"Jury St Centre",
    "sg:city":"Manchester",
    "sg:classifiers":[
        {
            "category":"Shopping",
            "subcategory":"Clothing, Apparel, & Fashions",
            "type":"Retail Goods"
        }
    ],
    "sg:phone":"+44 161 839 0286",
    "sg:postcode":"M8 8FN",
    "sg:province":"Greater Manchester",
    "sg:tags":[
        "clothing"
    ],
    "wof:name":"Sohal Brothers Ltd.",
    "wof:placetype":"venue"
},
  "geometry": {"coordinates":[-2.249529,53.493805],"type":"Point"}
}