{
  "type": "Feature",
  "properties": {
    "addr:full":"Lynes Barn, Winchcombe Cheltenham Gloucestershire GL54 5AT",
    "addr:postcode":"gl54 5at",
    "iso:country":"GB",
    "sg:address":"Lynes Barn, Winchcombe",
    "sg:city":"Cheltenham",
    "sg:classifiers":[
        {
            "category":"Farming",
            "subcategory":"Livestock Farm",
            "type":"Manufacturing & Wholesale Goods"
        }
    ],
    "sg:postcode":"GL54 5AT",
    "sg:province":"Gloucestershire",
    "sg:tags":[
        "others"
    ],
    "wof:name":"R Lee-Warner",
    "wof:placetype":"venue"
},
  "geometry": {"coordinates":[-1.9643529654,51.9533882141],"type":"Point"}
}