{
  "type": "Feature",
  "properties": {
    "iso:country":"GB",
    "sg:address":"Hill Top, Bolsover",
    "sg:city":"Chesterfield",
    "sg:classifiers":[
        {
            "category":"Bars & Pubs",
            "type":"Food & Drink"
        }
    ],
    "sg:phone":"+44 1246 822337",
    "sg:postcode":"S44 6NG",
    "sg:province":"Derbyshire",
    "sg:tags":[
        "pubs",
        "inn"
    ],
    "wof:name":"The Black Bull Inn",
    "wof:placetype":"venue"
},
  "geometry": {"coordinates":[-1.2909890413,53.2293319702],"type":"Point"}
}