{
  "type": "Feature",
  "properties": {
    "iso:country":"GB",
    "sg:address":"Unit 1/2, Exeter Airport Business Park",
    "sg:city":"Exeter",
    "sg:classifiers":[
        {
            "category":"Manufacturing",
            "subcategory":"Metals",
            "type":"Manufacturing & Wholesale Goods"
        }
    ],
    "sg:phone":"+44 1392 364521",
    "sg:postcode":"EX5 2LJ",
    "sg:province":"Devon",
    "wof:name":"T W Misco",
    "wof:placetype":"venue"
},
  "geometry": {"coordinates":[-3.4107840061,50.7301902771],"type":"Point"}
}