{
  "type": "Feature",
  "properties": {
    "addr:full":"45 Pinewood Road Ferndown Dorset BH22 9RP",
    "addr:housenumber":"45",
    "addr:postcode":"bh22 9rp",
    "addr:street":"Pinewood Road",
    "iso:country":"GB",
    "sg:address":"45 Pinewood Road",
    "sg:city":"Ferndown",
    "sg:classifiers":[
        {
            "category":"Real Estate",
            "subcategory":"Surveying",
            "type":"Services"
        },
        {
            "category":"Real Estate",
            "subcategory":"Architect",
            "type":"Services"
        }
    ],
    "sg:postcode":"BH22 9RP",
    "sg:province":"Dorset",
    "sg:tags":[
        "surveyor",
        "quantity"
    ],
    "wof:name":"Miller Rendell Partnership",
    "wof:placetype":"venue"
},
  "geometry": {"coordinates":[-1.8970609903,50.8125419617],"type":"Point"}
}