{
  "type": "Feature",
  "properties": {
    "iso:country":"GB",
    "sg:address":"14 Camden Rd",
    "sg:city":"Bristol",
    "sg:classifiers":[
        {
            "category":"Retail",
            "subcategory":"Auto Repair",
            "type":"Services"
        }
    ],
    "sg:postcode":"BS3 1QA",
    "sg:province":"City of Bristol",
    "sg:tags":[
        "modification",
        "garage"
    ],
    "wof:name":"Payne,Chris,",
    "wof:placetype":"venue"
},
  "geometry": {"coordinates":[-2.6060650349,51.4455184937],"type":"Point"}
}