{
  "type": "Feature",
  "properties": {
    "iso:country":"GB",
    "sg:address":"25 High Street, Brompton",
    "sg:city":"Gillingham",
    "sg:classifiers":[
        {
            "category":"Government",
            "subcategory":"Post Office",
            "type":"Public Place"
        }
    ],
    "sg:phone":"+44 1634 842973",
    "sg:postcode":"ME7 5AA",
    "sg:province":"Kent",
    "wof:name":"Brompton Post Office",
    "wof:placetype":"venue"
},
  "geometry": {"coordinates":[0.536343,51.39106],"type":"Point"}
}