{
  "type": "Feature",
  "properties": {
    "addr:full":"Suite 8 Pavilion Business Centre, Stanningley Rd Pudsey West Yorkshire LS28 6NB",
    "addr:housenumber":"suite 8",
    "addr:postcode":"ls28 6nb",
    "addr:street":"Pavilion Business Centre Stanningley Rd",
    "iso:country":"GB",
    "sg:address":"Suite 8 Pavilion Business Centre, Stanningley Rd",
    "sg:city":"Pudsey",
    "sg:classifiers":[
        {
            "category":"Building & Trades",
            "subcategory":"Construction",
            "type":"Services"
        }
    ],
    "sg:phone":"+44 113 204 0202",
    "sg:postcode":"LS28 6NB",
    "sg:province":"West Yorkshire",
    "sg:tags":[
        "dry",
        "lining",
        "plasterers",
        "screeders"
    ],
    "wof:name":"Safeguard Exterior Coating",
    "wof:placetype":"venue"
},
  "geometry": {"coordinates":[-1.656269,53.797684],"type":"Point"}
}