{
  "type": "Feature",
  "properties": {
    "addr:full":"West Park Road, Newchapel Lingfield Surrey RH7 6HT",
    "addr:postcode":"rh7 6ht",
    "addr:street":"West Park Road",
    "iso:country":"GB",
    "sg:address":"West Park Road, Newchapel",
    "sg:city":"Lingfield",
    "sg:classifiers":[
        {
            "category":"Recreation",
            "subcategory":"Campground",
            "type":"Entertainment"
        }
    ],
    "sg:phone":"+44 1342 712106",
    "sg:postcode":"RH7 6HT",
    "sg:province":"Surrey",
    "sg:tags":[
        "site",
        "camping"
    ],
    "wof:name":"Perry Wood Scout Camp International",
    "wof:placetype":"venue"
},
  "geometry": {"coordinates":[-0.019686,51.17482],"type":"Point"}
}