{
  "type": "Feature",
  "properties": {
    "addr:full":"126 Upper Tooting Road London Greater London SW17 7EN",
    "addr:housenumber":"126",
    "addr:postcode":"sw17 7en",
    "addr:street":"Upper Tooting Road",
    "iso:country":"GB",
    "sg:address":"126 Upper Tooting Road",
    "sg:city":"London",
    "sg:classifiers":[
        {
            "category":"Food & Beverages",
            "subcategory":"Fruits & Vegetables",
            "type":"Retail Goods"
        }
    ],
    "sg:phone":"+44 20 8682 4988",
    "sg:postcode":"SW17 7EN",
    "sg:province":"Greater London",
    "sg:tags":[
        "greengrocer"
    ],
    "wof:name":"Naturefresh Ltd.",
    "wof:placetype":"venue"
},
  "geometry": {"coordinates":[-0.1625349969,51.4337310791],"type":"Point"}
}