{
  "type": "Feature",
  "properties": {
    "addr:full":"The Old Mill, East Sutton, Sutton Valance Maidstone Kent ME17 3DB",
    "addr:postcode":"me17 3db",
    "addr:street":"East Sutton;Valance",
    "iso:country":"GB",
    "sg:address":"The Old Mill, East Sutton, Sutton Valance",
    "sg:city":"Maidstone",
    "sg:classifiers":[
        {
            "category":"Professional",
            "subcategory":"Business Services",
            "type":"Services"
        }
    ],
    "sg:phone":"+44 1622 844988",
    "sg:postcode":"ME17 3DB",
    "sg:province":"Kent",
    "sg:tags":[
        "publishers'"
    ],
    "wof:name":"Gillian Gray Compilation Services",
    "wof:placetype":"venue"
},
  "geometry": {"coordinates":[0.612725,51.213902],"type":"Point"}
}