{
  "type": "Feature",
  "properties": {
    "addr:full":"38 Hylton Road Sunderland Tyne and Wear SR4 7AF",
    "addr:housenumber":"38",
    "addr:postcode":"sr4 7af",
    "addr:street":"Hylton Road",
    "iso:country":"GB",
    "sg:address":"38 Hylton Road",
    "sg:city":"Sunderland",
    "sg:classifiers":[
        {
            "category":"Home & Garden",
            "subcategory":"Household Appliances",
            "type":"Retail Goods"
        }
    ],
    "sg:postcode":"SR4 7AF",
    "sg:province":"Tyne and Wear",
    "sg:tags":[
        "electrical"
    ],
    "wof:name":"Jackwood Domestics",
    "wof:placetype":"venue"
},
  "geometry": {"coordinates":[-1.39573,54.907246],"type":"Point"}
}