{
  "type": "Feature",
  "properties": {
    "addr:full":"Bogey Lane, Pontesbury Shrewsbury Shropshire SY5 0TF",
    "addr:postcode":"sy5 0tf",
    "addr:street":"Bogey Lane",
    "iso:country":"GB",
    "sg:address":"Bogey Lane, Pontesbury",
    "sg:city":"Shrewsbury",
    "sg:classifiers":[
        {
            "category":"Education",
            "subcategory":"School",
            "type":"Public Place"
        }
    ],
    "sg:phone":"+44 1743 790226",
    "sg:postcode":"SY5 0TF",
    "sg:province":"Shropshire",
    "sg:tags":[
        "local",
        "authority"
    ],
    "wof:name":"Pontesbury C of E Primary School",
    "wof:placetype":"venue"
},
  "geometry": {"coordinates":[-2.886108,52.647495],"type":"Point"}
}