{
  "type": "Feature",
  "properties": {
    "addr:full":"7 Walton Street London Greater London SW3 2JD",
    "addr:housenumber":"7",
    "addr:postcode":"sw3 2jd",
    "addr:street":"Walton Street",
    "iso:country":"GB",
    "sg:address":"7 Walton Street",
    "sg:city":"London",
    "sg:classifiers":[
        {
            "category":"Manufacturing",
            "subcategory":"Textiles",
            "type":"Manufacturing & Wholesale Goods"
        }
    ],
    "sg:phone":"+44 20 7584 1165",
    "sg:postcode":"SW3 2JD",
    "sg:province":"Greater London",
    "sg:tags":[
        "designer"
    ],
    "wof:name":"Chelsea Textiles Ltd.",
    "wof:placetype":"venue"
},
  "geometry": {"coordinates":[-0.164921,51.495815],"type":"Point"}
}