{
  "type": "Feature",
  "properties": {
    "iso:country":"GB",
    "sg:address":"27a High St",
    "sg:city":"Purley",
    "sg:classifiers":[
        {
            "category":"Fast Food",
            "type":"Food & Drink"
        }
    ],
    "sg:phone":"+44 20 8660 5618",
    "sg:postcode":"CR8 2AF",
    "sg:province":"Surrey",
    "sg:tags":[
        "away",
        "take"
    ],
    "wof:name":"Chef's Caterers",
    "wof:placetype":"venue"
},
  "geometry": {"coordinates":[-0.1155449972,51.338973999],"type":"Point"}
}