{
  "type": "Feature",
  "properties": {
    "iso:country":"GB",
    "sg:address":"York Ho, Old Bank Rd",
    "sg:city":"Dewsbury",
    "sg:classifiers":[
        {
            "category":"Professional",
            "subcategory":"Business Services",
            "type":"Services"
        }
    ],
    "sg:postcode":"WF12 7AH",
    "sg:province":"West Yorkshire",
    "sg:tags":[
        "holding"
    ],
    "wof:name":"Vernon Philmore Holdings Ltd",
    "wof:placetype":"venue"
},
  "geometry": {"coordinates":[-1.6141539812,53.6940536499],"type":"Point"}
}