{
  "type": "Feature",
  "properties": {
    "iso:country":"GB",
    "sg:address":"Banton Mill, Kilsyth",
    "sg:city":"Glasgow",
    "sg:classifiers":[
        {
            "category":"Manufacturing",
            "subcategory":"Buildings",
            "type":"Manufacturing & Wholesale Goods"
        }
    ],
    "sg:phone":"+44 1236 823011",
    "sg:postcode":"G65 0QG",
    "sg:province":"East Dunbartonshire",
    "sg:tags":[
        "framed",
        "timber"
    ],
    "wof:name":"Bennett Timber Products Ltd",
    "wof:placetype":"venue"
},
  "geometry": {"coordinates":[-4.058848,55.978645],"type":"Point"}
}