{
  "type": "Feature",
  "properties": {
    "addr:full":"Poplar Gro Preston Lancashire PR5 6RE",
    "addr:postcode":"pr5 6re",
    "addr:street":"Gro Preston",
    "iso:country":"GB",
    "sg:address":"Poplar Gro",
    "sg:city":"Preston",
    "sg:classifiers":[
        {
            "category":"Health Services",
            "subcategory":"Nursing And Care Facility",
            "type":"Services"
        }
    ],
    "sg:phone":"+44 1772 337105",
    "sg:postcode":"PR5 6RE",
    "sg:province":"Lancashire",
    "sg:tags":[
        "home"
    ],
    "wof:name":"Withy Grove House",
    "wof:placetype":"venue"
},
  "geometry": {"coordinates":[-2.6571888924,53.7322540283],"type":"Point"}
}