{
  "type": "Feature",
  "properties": {
    "addr:full":"Principal House, 8 Pendlebury Rd, Gatley Cheadle Cheshire SK8 4BH",
    "addr:housenumber":"8",
    "addr:postcode":"sk8 4bh",
    "addr:street":"Pendlebury Rd;Cheadle",
    "iso:country":"GB",
    "sg:address":"Principal House, 8 Pendlebury Rd, Gatley",
    "sg:city":"Cheadle",
    "sg:classifiers":[
        {
            "category":"Personal",
            "type":"Services"
        }
    ],
    "sg:phone":"+44 161 491 6800",
    "sg:postcode":"SK8 4BH",
    "sg:province":"Cheshire",
    "sg:tags":[
        "consultant",
        "fitness"
    ],
    "wof:name":"FitKid UK",
    "wof:placetype":"venue"
},
  "geometry": {"coordinates":[-2.2352058887,53.3944129944],"type":"Point"}
}