{
  "type": "Feature",
  "properties": {
    "addr:full":"Essell Caravan Centre, Worcester Road South, Hartlebury Stourport-on-severn Worcestershire DY13 9SH",
    "addr:postcode":"dy13 9sh",
    "addr:street":"Worcester Road South",
    "iso:country":"GB",
    "sg:address":"Essell Caravan Centre, Worcester Road South, Hartlebury",
    "sg:city":"Stourport-on-severn",
    "sg:classifiers":[
        {
            "category":"Insurance",
            "subcategory":"Insurance Agent",
            "type":"Services"
        }
    ],
    "sg:phone":"+44 1299 253367",
    "sg:postcode":"DY13 9SH",
    "sg:province":"Worcestershire",
    "wof:name":"Park Home Insurance (West Midlands)",
    "wof:placetype":"venue"
},
  "geometry": {"coordinates":[-2.2340600491,52.3200111389],"type":"Point"}
}