{
  "type": "Feature",
  "properties": {
    "addr:full":"1st Floor, Atlas Works, Nelson Street Carlisle Cumbria CA2 5NB",
    "addr:postcode":"ca2 5nb",
    "addr:street":"Nelson Street",
    "iso:country":"GB",
    "sg:address":"1st Floor, Atlas Works, Nelson Street",
    "sg:city":"Carlisle",
    "sg:classifiers":[
        {
            "category":"Community Center",
            "type":"Public Place"
        }
    ],
    "sg:postcode":"CA2 5NB",
    "sg:province":"Cumbria",
    "sg:tags":[
        "recreation",
        "leisure",
        "centre"
    ],
    "wof:name":"Magic Castle Adventure Playground",
    "wof:placetype":"venue"
},
  "geometry": {"coordinates":[-2.94077,54.887161],"type":"Point"}
}