{
  "type": "Feature",
  "properties": {
    "addr:full":"Strathmore Road Barnard Castle Cumbria DL12 8DS",
    "addr:postcode":"dl12 8ds",
    "addr:street":"Strathmore Road",
    "iso:country":"GB",
    "sg:address":"Strathmore Road",
    "sg:city":"Barnard Castle",
    "sg:classifiers":[
        {
            "category":"Community Center",
            "type":"Public Place"
        }
    ],
    "sg:phone":"+44 1833 690400",
    "sg:postcode":"DL12 8DS",
    "sg:province":"Cumbria",
    "sg:tags":[
        "recreation",
        "leisure",
        "centre"
    ],
    "wof:name":"Teesdale Sports Centre",
    "wof:placetype":"venue"
},
  "geometry": {"coordinates":[-1.915855,54.551369],"type":"Point"}
}