{
  "type": "Feature",
  "properties": {
    "addr:full":"57 Gwendolen Road Leicester Leicestershire LE5 5FL",
    "addr:housenumber":"57",
    "addr:postcode":"le5 5fl",
    "addr:street":"Gwendolen Road",
    "iso:country":"GB",
    "sg:address":"57 Gwendolen Road",
    "sg:city":"Leicester",
    "sg:classifiers":[
        {
            "category":"Shopping",
            "subcategory":"Stationery & Office Supplies",
            "type":"Retail Goods"
        }
    ],
    "sg:phone":"+44 116 273 4668",
    "sg:postcode":"LE5 5FL",
    "sg:province":"Leicestershire",
    "sg:tags":[
        "printers'"
    ],
    "wof:name":"G & J Watts",
    "wof:placetype":"venue"
},
  "geometry": {"coordinates":[-1.103886,52.631351],"type":"Point"}
}