{
  "type": "Feature",
  "properties": {
    "iso:country":"GB",
    "sg:address":"120 Raddlebarn Road, Selly Oak",
    "sg:city":"Birmingham",
    "sg:classifiers":[
        {
            "category":"Professional",
            "subcategory":"Accounting & Tax Preparation",
            "type":"Services"
        },
        {
            "category":"Banks & Credit Unions",
            "subcategory":"Bank",
            "type":"Services"
        }
    ],
    "sg:postcode":"B29 6HQ",
    "sg:province":"West Midlands",
    "sg:tags":[
        "accountant",
        "broker",
        "mortgage"
    ],
    "wof:name":"Essell & Co",
    "wof:placetype":"venue"
},
  "geometry": {"coordinates":[-1.9293689728,52.4368782043],"type":"Point"}
}