{
  "type": "Feature",
  "properties": {
    "iso:country":"GB",
    "sg:address":"134 Grays Inn Road",
    "sg:city":"London",
    "sg:classifiers":[
        {
            "category":"Shopping",
            "subcategory":"Luggage & Leather Goods",
            "type":"Retail Goods"
        }
    ],
    "sg:phone":"+44 20 7837 5429",
    "sg:postcode":"WC1X 8AS",
    "sg:province":"Greater London",
    "sg:tags":[
        "shop",
        "leathergoods"
    ],
    "wof:name":"Innsight",
    "wof:placetype":"venue"
},
  "geometry": {"coordinates":[-0.112999,51.521049],"type":"Point"}
}