{
  "type": "Feature",
  "properties": {
    "iso:country":"GB",
    "sg:address":"2 Bedfont Lane",
    "sg:city":"Feltham",
    "sg:classifiers":[
        {
            "category":"Fast Food",
            "type":"Food & Drink"
        }
    ],
    "sg:phone":"+44 20 8844 1600",
    "sg:postcode":"TW14 9NJ",
    "sg:province":"Greater London",
    "sg:tags":[
        "away",
        "take"
    ],
    "wof:name":"McDonald's",
    "wof:placetype":"venue"
},
  "geometry": {"coordinates":[-0.4114899933,51.4479942322],"type":"Point"}
}