{
  "type": "Feature",
  "properties": {
    "addr:full":"16 South St Farnham Surrey GU9 7RP",
    "addr:housenumber":"16",
    "addr:postcode":"gu9 7rp",
    "addr:street":"South St",
    "iso:country":"GB",
    "sg:address":"16 South St",
    "sg:city":"Farnham",
    "sg:classifiers":[
        {
            "category":"Food & Beverages",
            "subcategory":"Supermarket",
            "type":"Retail Goods"
        }
    ],
    "sg:phone":"+44 1252 734077",
    "sg:postcode":"GU9 7RP",
    "sg:province":"Surrey",
    "wof:name":"J Sainsbury PLC",
    "wof:placetype":"venue"
},
  "geometry": {"coordinates":[-0.795919,51.214409],"type":"Point"}
}