{
  "type": "Feature",
  "properties": {
    "addr:full":"Buckley House, 6-9 Buckley Rd Ind Est Rochdale Lancashire OL12 9EF",
    "addr:housenumber":"6-9",
    "addr:postcode":"ol12 9ef",
    "addr:street":"Buckley Rd",
    "iso:country":"GB",
    "sg:address":"Buckley House, 6-9 Buckley Rd Ind Est",
    "sg:city":"Rochdale",
    "sg:classifiers":[
        {
            "category":"Professional",
            "subcategory":"Printing & Photocopies",
            "type":"Services"
        }
    ],
    "sg:phone":"+44 1706 643050",
    "sg:postcode":"OL12 9EF",
    "sg:province":"Lancashire",
    "sg:tags":[
        "duplicating",
        "copying"
    ],
    "wof:name":"Apex Group",
    "wof:placetype":"venue"
},
  "geometry": {"coordinates":[-2.140004,53.633827],"type":"Point"}
}