{
  "type": "Feature",
  "properties": {
    "iso:country":"GB",
    "sg:address":"7 London Street",
    "sg:city":"Faringdon",
    "sg:classifiers":[
        {
            "category":"Food & Beverages",
            "subcategory":"Meat & Fish",
            "type":"Retail Goods"
        }
    ],
    "sg:phone":"+44 1367 243572",
    "sg:postcode":"SN7 7AE",
    "sg:province":"Oxfordshire",
    "sg:tags":[
        "chip"
    ],
    "wof:name":"The Rainbow",
    "wof:placetype":"venue"
},
  "geometry": {"coordinates":[-1.5828959942,51.6581382751],"type":"Point"}
}