{
  "type": "Feature",
  "properties": {
    "addr:full":"Olympic House, 129/131 New Road, Croxley Grn Rickmansworth Hertfordshire WD3 3EN",
    "addr:housenumber":"129 / 131",
    "addr:postcode":"wd3 3en",
    "addr:street":"New Road Croxley Grn",
    "iso:country":"GB",
    "sg:address":"Olympic House, 129/131 New Road, Croxley Grn",
    "sg:city":"Rickmansworth",
    "sg:classifiers":[
        {
            "category":"Manufacturing",
            "subcategory":"Buildings",
            "type":"Manufacturing & Wholesale Goods"
        }
    ],
    "sg:phone":"+44 1923 777199",
    "sg:postcode":"WD3 3EN",
    "sg:province":"Hertfordshire",
    "sg:tags":[
        "system",
        "air conditioning"
    ],
    "wof:name":"Optimum Maintenance Systems Ltd.",
    "wof:placetype":"venue"
},
  "geometry": {"coordinates":[-0.4487699866,51.6484527588],"type":"Point"}
}