{
  "type": "Feature",
  "properties": {
    "addr:full":"28 Chivington Cl0 Solihull West Midlands B90 4YS",
    "addr:housenumber":"28",
    "addr:postcode":"b90 4ys",
    "addr:street":"Chivington Cl0",
    "iso:country":"GB",
    "sg:address":"28 Chivington Cl0",
    "sg:city":"Solihull",
    "sg:classifiers":[
        {
            "category":"Professional",
            "subcategory":"Management & Consulting",
            "type":"Services"
        },
        {
            "category":"Government",
            "subcategory":"Fire Station",
            "type":"Public Place"
        }
    ],
    "sg:phone":"+44 121 733 3233",
    "sg:postcode":"B90 4YS",
    "sg:province":"West Midlands",
    "sg:tags":[
        "consultant",
        "protection",
        "engineer"
    ],
    "wof:name":"Monument Fire Detection Systems",
    "wof:placetype":"venue"
},
  "geometry": {"coordinates":[-1.7861289978,52.3890991211],"type":"Point"}
}