{
  "type": "Feature",
  "properties": {
    "iso:country":"GB",
    "sg:address":"98 West Street",
    "sg:city":"Havant",
    "sg:classifiers":[
        {
            "category":"Autos & Motor Vehicles",
            "subcategory":"Automobile Sales",
            "type":"Retail Goods"
        }
    ],
    "sg:postcode":"PO9 1LN",
    "sg:province":"Hampshire",
    "sg:tags":[
        "car"
    ],
    "wof:name":"Havant Used Car Centre Ltd.",
    "wof:placetype":"venue"
},
  "geometry": {"coordinates":[-0.986904,50.852196],"type":"Point"}
}