{
  "type": "Feature",
  "properties": {
    "iso:country":"GB",
    "sg:address":"Princes Road",
    "sg:city":"Chelmsford",
    "sg:classifiers":[
        {
            "category":"Travel",
            "subcategory":"Hotels & Motels",
            "type":"Entertainment"
        }
    ],
    "sg:phone":"+44 1245 264848",
    "sg:postcode":"CM2 9AJ",
    "sg:province":"Essex",
    "wof:name":"Miami Hotel",
    "wof:placetype":"venue"
},
  "geometry": {"coordinates":[0.461572,51.721703],"type":"Point"}
}