{
  "type": "Feature",
  "properties": {
    "addr:full":"820 Manchester Road, Castleton Rochdale Lancashire OL11 3AW",
    "addr:housenumber":"820",
    "addr:postcode":"ol11 3aw",
    "addr:street":"Manchester Road",
    "iso:country":"GB",
    "sg:address":"820 Manchester Road, Castleton",
    "sg:city":"Rochdale",
    "sg:classifiers":[
        {
            "category":"Manufacturing",
            "subcategory":"Petroleum Products",
            "type":"Manufacturing & Wholesale Goods"
        }
    ],
    "sg:postcode":"OL11 3AW",
    "sg:province":"Lancashire",
    "sg:tags":[
        "double",
        "glazing"
    ],
    "wof:name":"Craig & Glen Wilkinson",
    "wof:placetype":"venue"
},
  "geometry": {"coordinates":[-2.1794068813,53.5920448303],"type":"Point"}
}