{
  "type": "Feature",
  "properties": {
    "iso:country":"GB",
    "sg:address":"Church Close Farm, Coniston Cold",
    "sg:city":"Skipton",
    "sg:classifiers":[
        {
            "category":"Farming",
            "subcategory":"Livestock Farm",
            "type":"Manufacturing & Wholesale Goods"
        }
    ],
    "sg:phone":"+44 1756 749526",
    "sg:postcode":"BD23 4EA",
    "sg:province":"Lancashire",
    "sg:tags":[
        "others"
    ],
    "wof:name":"G E Hall",
    "wof:placetype":"venue"
},
  "geometry": {"coordinates":[-2.1499,53.991394],"type":"Point"}
}