{
  "type": "Feature",
  "properties": {
    "iso:country":"GB",
    "sg:address":"30 Welford Place",
    "sg:city":"Wimbledon",
    "sg:classifiers":[
        {
            "category":"Professional",
            "subcategory":"Management & Consulting",
            "type":"Services"
        }
    ],
    "sg:phone":"+44 20 8944 1004",
    "sg:postcode":"SW19 5AJ",
    "sg:province":"Greater London",
    "sg:tags":[
        "consultant",
        "business"
    ],
    "wof:name":"Elizabeth Hornby & Associates",
    "wof:placetype":"venue"
},
  "geometry": {"coordinates":[-0.213759,51.430038],"type":"Point"}
}