{
  "type": "Feature",
  "properties": {
    "iso:country":"GB",
    "sg:address":"Unit B The Timberworks, Greeham",
    "sg:city":"Wellington",
    "sg:classifiers":[
        {
            "category":"Retail",
            "subcategory":"Auto Repair",
            "type":"Services"
        }
    ],
    "sg:phone":"+44 1823 672909",
    "sg:postcode":"TA21 0LY",
    "sg:province":"Devon",
    "sg:tags":[
        "repairs",
        "repairer",
        "commercial",
        "accessory",
        "bodybuilder",
        "part",
        "servicing",
        "vehicle"
    ],
    "wof:name":"Pullman Fleet Services",
    "wof:placetype":"venue"
},
  "geometry": {"coordinates":[-3.2266390324,50.9792709351],"type":"Point"}
}