{
  "type": "Feature",
  "properties": {
    "iso:country":"GB",
    "sg:address":"Sissinghurst Road, Biddenden",
    "sg:city":"Ashford",
    "sg:classifiers":[
        {
            "category":"Home & Garden",
            "subcategory":"Garden Supply",
            "type":"Retail Goods"
        }
    ],
    "sg:phone":"+44 1580 292070",
    "sg:postcode":"TN27 8DQ",
    "sg:province":"Kent",
    "sg:tags":[
        "nursery",
        "centre"
    ],
    "wof:name":"Garden Crafts Ltd.",
    "wof:placetype":"venue"
},
  "geometry": {"coordinates":[0.6423280239,51.1150894165],"type":"Point"}
}