{
  "type": "Feature",
  "properties": {
    "addr:full":"Heneford Farm, Chetnole Sherborne Dorset DT9 6PE",
    "addr:postcode":"dt9 6pe",
    "iso:country":"GB",
    "sg:address":"Heneford Farm, Chetnole",
    "sg:city":"Sherborne",
    "sg:classifiers":[
        {
            "category":"Farming",
            "subcategory":"Livestock Farm",
            "type":"Manufacturing & Wholesale Goods"
        }
    ],
    "sg:phone":"+44 1935 872297",
    "sg:postcode":"DT9 6PE",
    "sg:province":"Dorset",
    "sg:tags":[
        "others"
    ],
    "wof:name":"A & R Farms Ltd",
    "wof:placetype":"venue"
},
  "geometry": {"coordinates":[-2.567193985,50.8708953857],"type":"Point"}
}