{
  "type": "Feature",
  "properties": {
    "iso:country":"GB",
    "sg:address":"Applebys Business Cnt",
    "sg:city":"Oldham",
    "sg:classifiers":[
        {
            "category":"Building & Trades",
            "subcategory":"Construction",
            "type":"Services"
        }
    ],
    "sg:phone":"+44 1457 810110",
    "sg:postcode":"OL4 4HH",
    "sg:province":"Lancashire",
    "sg:tags":[
        "builder"
    ],
    "wof:name":"M Mills Building Contractors",
    "wof:placetype":"venue"
},
  "geometry": {"coordinates":[-2.0295,53.537048],"type":"Point"}
}