{
  "type": "Feature",
  "properties": {
    "addr:full":"110 Birkenshaw Way, Armadale Bathgate West Lothian EH48 3QX",
    "addr:housenumber":"110",
    "addr:postcode":"eh48 3qx",
    "addr:street":"Birkenshaw Way;Bathgate",
    "iso:country":"GB",
    "sg:address":"110 Birkenshaw Way, Armadale",
    "sg:city":"Bathgate",
    "sg:classifiers":[
        {
            "category":"Personal",
            "subcategory":"Beauty Salon",
            "type":"Services"
        }
    ],
    "sg:phone":"+44 1501 733987",
    "sg:postcode":"EH48 3QX",
    "sg:province":"West Lothian",
    "sg:tags":[
        "unisex",
        "hairdresser"
    ],
    "wof:name":"Katrina's",
    "wof:placetype":"venue"
},
  "geometry": {"coordinates":[-3.706554,55.901562],"type":"Point"}
}