{
  "type": "Feature",
  "properties": {
    "iso:country":"GB",
    "sg:address":"25 West Avenue",
    "sg:city":"Filey",
    "sg:classifiers":[
        {
            "category":"Travel",
            "subcategory":"Hotels & Motels",
            "type":"Entertainment"
        }
    ],
    "sg:postcode":"YO14 9AX",
    "sg:province":"North Yorkshire",
    "sg:tags":[
        "house",
        "guest"
    ],
    "wof:name":"This'lldo Binton Guest House",
    "wof:placetype":"venue"
},
  "geometry": {"coordinates":[-0.2889699936,54.2086334229],"type":"Point"}
}