{
  "type": "Feature",
  "properties": {
    "addr:full":"11 Burson Road, Beaumont Leys Leicester Leicestershire LE4 1BS",
    "addr:housenumber":"11",
    "addr:postcode":"le4 1bs",
    "addr:street":"Burson Road",
    "iso:country":"GB",
    "sg:address":"11 Burson Road, Beaumont Leys",
    "sg:city":"Leicester",
    "sg:classifiers":[
        {
            "category":"Manufacturing",
            "subcategory":"Food",
            "type":"Manufacturing & Wholesale Goods"
        },
        {
            "category":"Food & Beverages",
            "subcategory":"Supermarket",
            "type":"Retail Goods"
        }
    ],
    "sg:phone":"+44 116 234 2000",
    "sg:postcode":"LE4 1BS",
    "sg:province":"Leicestershire",
    "sg:tags":[
        "frozen",
        "product",
        "manufacturer"
    ],
    "wof:name":"Walkers Snack Foods Ltd.",
    "wof:placetype":"venue"
},
  "geometry": {"coordinates":[-1.159479022,52.672454834],"type":"Point"}
}