{
  "type": "Feature",
  "properties": {
    "addr:full":"12 St Marys Street Whitchurch Cheshire SY13 1QY",
    "addr:housenumber":"12",
    "addr:postcode":"sy13 1qy",
    "addr:street":"St Marys Street",
    "iso:country":"GB",
    "sg:address":"12 St Marys Street",
    "sg:city":"Whitchurch",
    "sg:classifiers":[
        {
            "category":"Landmark",
            "subcategory":"Tourist Information",
            "type":"Public Place"
        }
    ],
    "sg:phone":"+44 1948 665432",
    "sg:postcode":"SY13 1QY",
    "sg:province":"Cheshire",
    "wof:name":"The Whitchurch Heritage & Tourist Information Centre",
    "wof:placetype":"venue"
},
  "geometry": {"coordinates":[-2.68302,52.970036],"type":"Point"}
}