{
  "type": "Feature",
  "properties": {
    "addr:full":"286b Chase Road, Southgate London Greater London N14 6HF",
    "addr:housenumber":"286b",
    "addr:postcode":"n14 6hf",
    "addr:street":"Chase Road",
    "iso:country":"GB",
    "sg:address":"286b Chase Road, Southgate",
    "sg:city":"London",
    "sg:classifiers":[
        {
            "category":"Real Estate",
            "subcategory":"Real Estate Agent",
            "type":"Services"
        }
    ],
    "sg:phone":"+44 20 8882 8818",
    "sg:postcode":"N14 6HF",
    "sg:province":"Greater London",
    "wof:name":"Ashgrove Investments Ltd.",
    "wof:placetype":"venue"
},
  "geometry": {"coordinates":[-0.126645,51.633511],"type":"Point"}
}