{
  "type": "Feature",
  "properties": {
    "iso:country":"GB",
    "sg:address":"302 High St",
    "sg:city":"Bangor",
    "sg:classifiers":[
        {
            "category":"Professional",
            "subcategory":"Management & Consulting",
            "type":"Services"
        }
    ],
    "sg:phone":"+44 1248 372036",
    "sg:postcode":"LL57 1UL",
    "sg:province":"Gwynedd",
    "sg:tags":[
        "consultant",
        "business"
    ],
    "wof:name":"Kirkham & Elphick",
    "wof:placetype":"venue"
},
  "geometry": {"coordinates":[-4.114512,53.230942],"type":"Point"}
}