{
  "type": "Feature",
  "properties": {
    "addr:full":"130 Broomhall Road, Pendlebury Manchester Greater Manchester M27 8XG",
    "addr:housenumber":"130",
    "addr:postcode":"m27 8xg",
    "addr:street":"Broomhall Road",
    "iso:country":"GB",
    "sg:address":"130 Broomhall Road, Pendlebury",
    "sg:city":"Manchester",
    "sg:classifiers":[
        {
            "category":"Retail",
            "subcategory":"Driving School",
            "type":"Services"
        }
    ],
    "sg:phone":"+44 161 736 6698",
    "sg:postcode":"M27 8XG",
    "sg:province":"Greater Manchester",
    "wof:name":"JACK COOPER",
    "wof:placetype":"venue"
},
  "geometry": {"coordinates":[-2.308938,53.505104],"type":"Point"}
}