{
  "type": "Feature",
  "properties": {
    "addr:full":"16 Railway Arch, 16 Viaduct St Huddersfield West Yorkshire HD1 5AW",
    "addr:housenumber":"16;16",
    "addr:postcode":"hd1 5aw",
    "addr:street":"Railway Arch;Viaduct St",
    "iso:country":"GB",
    "sg:address":"16 Railway Arch, 16 Viaduct St",
    "sg:city":"Huddersfield",
    "sg:classifiers":[
        {
            "category":"Professional",
            "subcategory":"Engineering",
            "type":"Services"
        }
    ],
    "sg:phone":"+44 1484 543548",
    "sg:postcode":"HD1 5AW",
    "sg:province":"West Yorkshire",
    "sg:tags":[
        "ge",
        "engineer",
        "mechanical"
    ],
    "wof:name":"A Singh",
    "wof:placetype":"venue"
},
  "geometry": {"coordinates":[-1.782684,53.646954],"type":"Point"}
}