{
  "type": "Feature",
  "properties": {
    "iso:country":"GB",
    "sg:address":"43 Alcester Road, Moseley",
    "sg:city":"Birmingham",
    "sg:classifiers":[
        {
            "category":"Bars & Pubs",
            "type":"Food & Drink"
        }
    ],
    "sg:phone":"+44 121 449 1082",
    "sg:postcode":"B13 8AA",
    "sg:province":"West Midlands",
    "sg:tags":[
        "pubs",
        "inn"
    ],
    "wof:name":"The Jug of Ale",
    "wof:placetype":"venue"
},
  "geometry": {"coordinates":[-1.888874054,52.4508209229],"type":"Point"}
}