{
  "type": "Feature",
  "properties": {
    "addr:full":"Ormstells, Camps Road Saffron Walden Cambridgeshire CB10 2JQ",
    "addr:postcode":"cb10 2jq",
    "addr:street":"Camps Road",
    "iso:country":"GB",
    "sg:address":"Ormstells, Camps Road",
    "sg:city":"Saffron Walden",
    "sg:classifiers":[
        {
            "category":"Building & Trades",
            "subcategory":"Construction",
            "type":"Services"
        }
    ],
    "sg:phone":"+44 1799 584346",
    "sg:postcode":"CB10 2JQ",
    "sg:province":"Cambridgeshire",
    "sg:tags":[
        "contractor"
    ],
    "wof:name":"Ford Construction",
    "wof:placetype":"venue"
},
  "geometry": {"coordinates":[0.239938,52.020576],"type":"Point"}
}