{
  "type": "Feature",
  "properties": {
    "iso:country":"GB",
    "sg:address":"286 Ashley Down Road, Ashley Down",
    "sg:city":"Bristol",
    "sg:classifiers":[
        {
            "category":"Health Services",
            "subcategory":"Health Practitioner",
            "type":"Services"
        }
    ],
    "sg:postcode":"BS7 9BQ",
    "sg:province":"City of Bristol",
    "sg:tags":[
        "herbalist"
    ],
    "wof:name":"Julia Green",
    "wof:placetype":"venue"
},
  "geometry": {"coordinates":[-2.5807650089,51.4748687744],"type":"Point"}
}