{
  "type": "Feature",
  "properties": {
    "iso:country":"GB",
    "sg:address":"The Adelaide Centre, Adelaide Terrace",
    "sg:city":"Newcastle-upon-tyne",
    "sg:classifiers":[
        {
            "category":"Food & Beverages",
            "subcategory":"Bakery",
            "type":"Retail Goods"
        }
    ],
    "sg:phone":"+44 191 273 6187",
    "sg:postcode":"NE4 8BE",
    "sg:province":"Tyne and Wear",
    "sg:tags":[
        "baker"
    ],
    "wof:name":"Greggs of Gosforth",
    "wof:placetype":"venue"
},
  "geometry": {"coordinates":[-1.65574,54.970268],"type":"Point"}
}