{
  "type": "Feature",
  "properties": {
    "addr:full":"15 Brackley Avenue, Smallthorne Stoke-on-trent Staffordshire ST6 7DN",
    "addr:housenumber":"15",
    "addr:postcode":"st6 7dn",
    "addr:street":"Brackley Avenue",
    "iso:country":"GB",
    "sg:address":"15 Brackley Avenue, Smallthorne",
    "sg:city":"Stoke-on-trent",
    "sg:classifiers":[
        {
            "category":"Shopping",
            "subcategory":"Party Supplies",
            "type":"Retail Goods"
        }
    ],
    "sg:postcode":"ST6 7DN",
    "sg:province":"Staffordshire",
    "sg:tags":[
        "inflatables",
        "bouncy",
        "castle"
    ],
    "wof:name":"Bouncers Bouncy Castles",
    "wof:placetype":"venue"
},
  "geometry": {"coordinates":[-2.18083,53.050285],"type":"Point"}
}