{
  "type": "Feature",
  "properties": {
    "iso:country":"GB",
    "sg:address":"Alington Road Little Barford, St Neots",
    "sg:city":"Huntingdon",
    "sg:classifiers":[
        {
            "category":"Retail",
            "subcategory":"Storage",
            "type":"Services"
        }
    ],
    "sg:phone":"+44 1480 405161",
    "sg:postcode":"PE19 6YH",
    "sg:province":"Bedfordshire",
    "sg:tags":[
        "household",
        "removal"
    ],
    "wof:name":"Brittains Removals",
    "wof:placetype":"venue"
},
  "geometry": {"coordinates":[-0.270005,52.208118],"type":"Point"}
}