{
  "type": "Feature",
  "properties": {
    "iso:country":"GB",
    "sg:address":"Granby Av",
    "sg:city":"Birmingham",
    "sg:classifiers":[
        {
            "category":"Building & Trades",
            "subcategory":"Landscaping Services",
            "type":"Services"
        }
    ],
    "sg:phone":"+44 121 783 7666",
    "sg:postcode":"B33 0YA",
    "sg:province":"West Midlands",
    "sg:tags":[
        "forestry",
        "tree"
    ],
    "wof:name":"Glendale Countryside",
    "wof:placetype":"venue"
},
  "geometry": {"coordinates":[-1.7754640579,52.4740791321],"type":"Point"}
}