{
  "type": "Feature",
  "properties": {
    "addr:full":"Carrick View, Coalhall Ayr East Ayrshire KA6 6ND",
    "addr:postcode":"ka6 6nd",
    "addr:street":"Carrick;East",
    "iso:country":"GB",
    "sg:address":"Carrick View, Coalhall",
    "sg:city":"Ayr",
    "sg:classifiers":[
        {
            "category":"Taxi",
            "type":"Transportation"
        },
        {
            "category":"Military Area",
            "subcategory":"Air Force Base",
            "type":"Public Place"
        }
    ],
    "sg:postcode":"KA6 6ND",
    "sg:province":"East Ayrshire",
    "sg:tags":[
        "mini",
        "hire",
        "private",
        "cab"
    ],
    "wof:name":"Cowan,Hugh,",
    "wof:placetype":"venue"
},
  "geometry": {"coordinates":[-4.4590449333,55.4481468201],"type":"Point"}
}