{
  "type": "Feature",
  "properties": {
    "iso:country":"GB",
    "sg:address":"422 Lymington Rd",
    "sg:city":"Christchurch",
    "sg:classifiers":[
        {
            "category":"Shopping",
            "subcategory":"Clothing, Apparel, & Fashions",
            "type":"Retail Goods"
        }
    ],
    "sg:phone":"+44 1425 276928",
    "sg:postcode":"BH23 5HE",
    "sg:province":"Dorset",
    "sg:tags":[
        "dresswear"
    ],
    "wof:name":"Gemma Dress Agency",
    "wof:placetype":"venue"
},
  "geometry": {"coordinates":[-1.695701,50.742626],"type":"Point"}
}