{
  "type": "Feature",
  "properties": {
    "addr:full":"38 Ship St Brighton East Sussex BN1 1AB",
    "addr:housenumber":"38",
    "addr:postcode":"bn1 1ab",
    "addr:street":"Ship St",
    "iso:country":"GB",
    "sg:address":"38 Ship St",
    "sg:city":"Brighton",
    "sg:classifiers":[
        {
            "category":"Professional",
            "subcategory":"Management & Consulting",
            "type":"Services"
        }
    ],
    "sg:postcode":"BN1 1AB",
    "sg:province":"East Sussex",
    "sg:tags":[
        "consultant",
        "business"
    ],
    "wof:name":"Gilchrist,Alan,",
    "wof:placetype":"venue"
},
  "geometry": {"coordinates":[-0.141722,50.823021],"type":"Point"}
}