{
  "type": "Feature",
  "properties": {
    "iso:country":"GB",
    "sg:address":"Glebe Cottage, Donhead St.mary",
    "sg:city":"Shaftesbury",
    "sg:classifiers":[
        {
            "category":"Professional",
            "subcategory":"Management & Consulting",
            "type":"Services"
        }
    ],
    "sg:postcode":"SP7 9DQ",
    "sg:province":"Dorset",
    "sg:tags":[
        "consultant",
        "business"
    ],
    "wof:name":"Fieldmoss Ltd",
    "wof:placetype":"venue"
},
  "geometry": {"coordinates":[-2.215729,51.030155],"type":"Point"}
}