{
  "type": "Feature",
  "properties": {
    "addr:full":"P O Box 777 Stevenage Hertfordshire SG1 4XW",
    "addr:housenumber":"777",
    "addr:postcode":"sg1 4xw",
    "addr:street":"P O Box",
    "iso:country":"GB",
    "sg:address":"P O Box 777",
    "sg:city":"Stevenage",
    "sg:classifiers":[
        {
            "category":"Place Of Worship",
            "type":"Public Place"
        }
    ],
    "sg:phone":"+44 1438 360799",
    "sg:postcode":"SG1 4XW",
    "sg:province":"Hertfordshire",
    "wof:name":"Stevenage Christian Fellowship",
    "wof:placetype":"venue"
},
  "geometry": {"coordinates":[-0.18868,51.905609],"type":"Point"}
}