{
  "type": "Feature",
  "properties": {
    "addr:full":"Carlesmoor, Carlesmoor Lane, Kirkby Malzeard Ripon North Yorkshire HG4 3QS",
    "addr:postcode":"hg4 3qs",
    "addr:street":"Carlesmoor Lane",
    "iso:country":"GB",
    "sg:address":"Carlesmoor, Carlesmoor Lane, Kirkby Malzeard",
    "sg:city":"Ripon",
    "sg:classifiers":[
        {
            "category":"Farming",
            "subcategory":"Livestock Farm",
            "type":"Manufacturing & Wholesale Goods"
        }
    ],
    "sg:postcode":"HG4 3QS",
    "sg:province":"North Yorkshire",
    "sg:tags":[
        "others"
    ],
    "wof:name":"Geoffery Lobley",
    "wof:placetype":"venue"
},
  "geometry": {"coordinates":[-1.6484639645,54.1642189026],"type":"Point"}
}