{
  "type": "Feature",
  "properties": {
    "addr:full":"Carley Drive, Westfield Sheffield South Yorkshire S20 8NQ",
    "addr:postcode":"s20 8nq",
    "addr:street":"Carley Drive",
    "iso:country":"GB",
    "sg:address":"Carley Drive, Westfield",
    "sg:city":"Sheffield",
    "sg:classifiers":[
        {
            "category":"Community Center",
            "subcategory":"Youth",
            "type":"Public Place"
        }
    ],
    "sg:phone":"+44 114 247 4925",
    "sg:postcode":"S20 8NQ",
    "sg:province":"South Yorkshire",
    "sg:tags":[
        "organisation",
        "centre"
    ],
    "wof:name":"John Barnett Youth Centre",
    "wof:placetype":"venue"
},
  "geometry": {"coordinates":[-1.350392,53.329208],"type":"Point"}
}