{
  "type": "Feature",
  "properties": {
    "addr:full":"The Square Huntly Aberdeenshire AB54 8AF",
    "addr:postcode":"ab54 8af",
    "addr:street":"The Square",
    "iso:country":"GB",
    "sg:address":"The Square",
    "sg:city":"Huntly",
    "sg:classifiers":[
        {
            "category":"Travel",
            "subcategory":"Hotels & Motels",
            "type":"Entertainment"
        }
    ],
    "sg:phone":"+44 1466 792288",
    "sg:postcode":"AB54 8AF",
    "sg:province":"Aberdeenshire",
    "wof:name":"Gordon Arms Hotel",
    "wof:placetype":"venue"
},
  "geometry": {"coordinates":[-2.7934091091,57.4425811768],"type":"Point"}
}