{
  "type": "Feature",
  "properties": {
    "addr:full":"Upper Down Rd Holywell Denbighshire CH8 9AJ",
    "addr:postcode":"ch8 9aj",
    "addr:street":"Upper Down Rd",
    "iso:country":"GB",
    "sg:address":"Upper Down Rd",
    "sg:city":"Holywell",
    "sg:classifiers":[
        {
            "category":"Health Services",
            "subcategory":"Nursing And Care Facility",
            "type":"Services"
        }
    ],
    "sg:phone":"+44 1745 560674",
    "sg:postcode":"CH8 9AJ",
    "sg:province":"Denbighshire",
    "sg:tags":[
        "home"
    ],
    "wof:name":"Altbridge Nursing Home",
    "wof:placetype":"venue"
},
  "geometry": {"coordinates":[-3.280649,53.293732],"type":"Point"}
}