{
  "type": "Feature",
  "properties": {
    "addr:full":"16 Medway Street Chatham Kent ME4 4HA",
    "addr:housenumber":"16",
    "addr:postcode":"me4 4ha",
    "addr:street":"Medway Street",
    "iso:country":"GB",
    "sg:address":"16 Medway Street",
    "sg:city":"Chatham",
    "sg:classifiers":[
        {
            "category":"Home & Garden",
            "subcategory":"Furniture",
            "type":"Retail Goods"
        }
    ],
    "sg:phone":"+44 1634 818196",
    "sg:postcode":"ME4 4HA",
    "sg:province":"Kent",
    "wof:name":"Not Just Furniture",
    "wof:placetype":"venue"
},
  "geometry": {"coordinates":[0.5210260153,51.3840827942],"type":"Point"}
}