{
  "type": "Feature",
  "properties": {
    "addr:full":"98 Telegraph Road, Heswall Wirral Merseyside CH60 0AQ",
    "addr:housenumber":"98",
    "addr:postcode":"ch60 0aq",
    "addr:street":"Telegraph Road",
    "iso:country":"GB",
    "sg:address":"98 Telegraph Road, Heswall",
    "sg:city":"Wirral",
    "sg:classifiers":[
        {
            "category":"Personal",
            "subcategory":"Beauty Salon",
            "type":"Services"
        },
        {
            "category":"Personal",
            "subcategory":"Barber",
            "type":"Services"
        }
    ],
    "sg:phone":"+44 151 342 1522",
    "sg:postcode":"CH60 0AQ",
    "sg:province":"Merseyside",
    "sg:tags":[
        "unisex",
        "hairdresser"
    ],
    "wof:name":"Joseph Hairdressing",
    "wof:placetype":"venue"
},
  "geometry": {"coordinates":[-3.093542099,53.3261909485],"type":"Point"}
}