{
  "type": "Feature",
  "properties": {
    "iso:country":"GB",
    "sg:address":"135 Haunch Lane",
    "sg:city":"Birmingham",
    "sg:classifiers":[
        {
            "category":"Building & Trades",
            "subcategory":"Construction",
            "type":"Services"
        }
    ],
    "sg:phone":"+44 121 444 6055",
    "sg:postcode":"B13 0PA",
    "sg:province":"West Midlands",
    "sg:tags":[
        "builder"
    ],
    "wof:name":"Rwt Building Contractors",
    "wof:placetype":"venue"
},
  "geometry": {"coordinates":[-1.8856559992,52.4231262207],"type":"Point"}
}