{
  "type": "Feature",
  "properties": {
    "addr:full":"Medical Centre, 2 Church Av Sidcup Kent DA14 6BU",
    "addr:housenumber":"2",
    "addr:postcode":"da14 6bu",
    "addr:street":"Church Av",
    "iso:country":"GB",
    "sg:address":"Medical Centre, 2 Church Av",
    "sg:city":"Sidcup",
    "sg:classifiers":[
        {
            "category":"Health Services",
            "subcategory":"Doctor",
            "type":"Services"
        }
    ],
    "sg:phone":"+44 20 8302 1114",
    "sg:postcode":"DA14 6BU",
    "sg:province":"Kent",
    "sg:tags":[
        "practitioners"
    ],
    "wof:name":"Bandyopadhyay, S",
    "wof:placetype":"venue"
},
  "geometry": {"coordinates":[0.103945002,51.4259185791],"type":"Point"}
}