{
  "type": "Feature",
  "properties": {
    "iso:country":"GB",
    "sg:address":"Reigate Heights, 44c Church Street",
    "sg:city":"Reigate",
    "sg:classifiers":[
        {
            "category":"Organizations",
            "subcategory":"Non-profit Organization",
            "type":"Services"
        }
    ],
    "sg:phone":"+44 1737 224439",
    "sg:postcode":"RH2 0AJ",
    "sg:province":"Surrey",
    "sg:tags":[
        "organisation",
        "voluntary",
        "charity"
    ],
    "wof:name":"Mencap",
    "wof:placetype":"venue"
},
  "geometry": {"coordinates":[-0.204779,51.235744],"type":"Point"}
}