{
  "type": "Feature",
  "properties": {
    "addr:full":"34 Park Crescent Brighton East Sussex BN2 3HB",
    "addr:housenumber":"34",
    "addr:postcode":"bn2 3hb",
    "addr:street":"Park Crescent",
    "iso:country":"GB",
    "sg:address":"34 Park Crescent",
    "sg:city":"Brighton",
    "sg:classifiers":[
        {
            "category":"Shopping",
            "subcategory":"Pharmacy",
            "type":"Retail Goods"
        }
    ],
    "sg:phone":"+44 1273 702413",
    "sg:postcode":"BN2 3HB",
    "sg:province":"East Sussex",
    "sg:tags":[
        "medicine",
        "therapy"
    ],
    "wof:name":"Daniel Bridge",
    "wof:placetype":"venue"
},
  "geometry": {"coordinates":[-0.1293260008,50.8345184326],"type":"Point"}
}