{
  "type": "Feature",
  "properties": {
    "addr:full":"Greenwells Garth Garage, Coundon Bishop Auckland Durham DL14 8LR",
    "addr:postcode":"dl14 8lr",
    "addr:street":"Greenwells;Bishop Auckland",
    "iso:country":"GB",
    "sg:address":"Greenwells Garth Garage, Coundon",
    "sg:city":"Bishop Auckland",
    "sg:classifiers":[
        {
            "category":"Retail",
            "subcategory":"Driving School",
            "type":"Services"
        }
    ],
    "sg:phone":"+44 1388 721297",
    "sg:postcode":"DL14 8LR",
    "sg:province":"Durham",
    "wof:name":"L G V Twinway Driving School",
    "wof:placetype":"venue"
},
  "geometry": {"coordinates":[-1.628616,54.664146],"type":"Point"}
}