{
  "type": "Feature",
  "properties": {
    "iso:country":"GB",
    "sg:address":"3 Woodside Terrace",
    "sg:city":"Glasgow",
    "sg:classifiers":[
        {
            "category":"Real Estate",
            "subcategory":"Architect",
            "type":"Services"
        }
    ],
    "sg:phone":"+44 141 400 2500",
    "sg:postcode":"G3 7UY",
    "sg:province":"Glasgow City",
    "wof:name":"Thomas Robinson Architects Ltd.",
    "wof:placetype":"venue"
},
  "geometry": {"coordinates":[-4.273381,55.867771],"type":"Point"}
}