{
  "type": "Feature",
  "properties": {
    "iso:country":"GB",
    "sg:address":"2 Court Mews, London Rd",
    "sg:city":"Cheltenham",
    "sg:classifiers":[
        {
            "category":"Professional",
            "subcategory":"Computer Services",
            "type":"Services"
        }
    ],
    "sg:phone":"+44 1242 239229",
    "sg:postcode":"GL52 6HS",
    "sg:province":"Gloucestershire",
    "sg:tags":[
        "system",
        "software"
    ],
    "wof:name":"Gender Software",
    "wof:placetype":"venue"
},
  "geometry": {"coordinates":[-2.051443,51.889385],"type":"Point"}
}