{
  "type": "Feature",
  "properties": {
    "addr:full":"227 Woodlands Road Gillingham Kent ME7 2SW",
    "addr:housenumber":"227",
    "addr:postcode":"me7 2sw",
    "addr:street":"Woodlands Road",
    "iso:country":"GB",
    "sg:address":"227 Woodlands Road",
    "sg:city":"Gillingham",
    "sg:classifiers":[
        {
            "category":"Building & Trades",
            "subcategory":"Landscaping Services",
            "type":"Services"
        }
    ],
    "sg:postcode":"ME7 2SW",
    "sg:province":"Kent",
    "sg:tags":[
        "forestry",
        "tree"
    ],
    "wof:name":"John W Callow",
    "wof:placetype":"venue"
},
  "geometry": {"coordinates":[0.56866,51.385197],"type":"Point"}
}