{
  "type": "Feature",
  "properties": {
    "addr:full":"9 Carthusian St London Greater London EC1M 6EB",
    "addr:housenumber":"9",
    "addr:postcode":"ec1m 6eb",
    "addr:street":"Carthusian St",
    "iso:country":"GB",
    "sg:address":"9 Carthusian St",
    "sg:city":"London",
    "sg:classifiers":[
        {
            "category":"Food & Beverages",
            "subcategory":"Candy",
            "type":"Retail Goods"
        }
    ],
    "sg:postcode":"EC1M 6EB",
    "sg:province":"Greater London",
    "sg:tags":[
        "confectioner"
    ],
    "wof:name":"Thakar,Deepak,",
    "wof:placetype":"venue"
},
  "geometry": {"coordinates":[-0.09796,51.52055],"type":"Point"}
}