{
  "type": "Feature",
  "properties": {
    "addr:full":"Nether House, Nayland Road Bures Essex CO8 5BY",
    "addr:postcode":"co8 5by",
    "addr:street":"Nayland Road",
    "iso:country":"GB",
    "sg:address":"Nether House, Nayland Road",
    "sg:city":"Bures",
    "sg:classifiers":[
        {
            "category":"Wholesale",
            "subcategory":"Fruits & Vegetables",
            "type":"Manufacturing & Wholesale Goods"
        }
    ],
    "sg:phone":"+44 1787 227989",
    "sg:postcode":"CO8 5BY",
    "sg:province":"Essex",
    "wof:name":"East Anglian Bean Sprouts",
    "wof:placetype":"venue"
},
  "geometry": {"coordinates":[0.7780560255,51.970615387],"type":"Point"}
}