{
  "type": "Feature",
  "properties": {
    "addr:full":"High Street, Hambledon Waterlooville Hampshire PO7 4RS",
    "addr:postcode":"po7 4rs",
    "addr:street":"High Street",
    "iso:country":"GB",
    "sg:address":"High Street, Hambledon",
    "sg:city":"Waterlooville",
    "sg:classifiers":[
        {
            "category":"Insurance",
            "subcategory":"Insurance Agent",
            "type":"Services"
        }
    ],
    "sg:phone":"+44 23 9263 2555",
    "sg:postcode":"PO7 4RS",
    "sg:province":"Hampshire",
    "sg:tags":[
        "broker"
    ],
    "wof:name":"Miller & Co (Insurance Brokers) Ltd",
    "wof:placetype":"venue"
},
  "geometry": {"coordinates":[-1.0867869854,50.9303131104],"type":"Point"}
}