{
  "type": "Feature",
  "properties": {
    "addr:full":"53 Portland Place London Greater London W1B 1QJ",
    "addr:housenumber":"53",
    "addr:postcode":"w1b 1qj",
    "addr:street":"Portland Place",
    "iso:country":"GB",
    "sg:address":"53 Portland Place",
    "sg:city":"London",
    "sg:classifiers":[
        {
            "category":"Health Services",
            "subcategory":"Dentist",
            "type":"Services"
        }
    ],
    "sg:phone":"+44 20 7580 4642",
    "sg:postcode":"W1B 1QJ",
    "sg:province":"Greater London",
    "wof:name":"The Orthodontic Practice",
    "wof:placetype":"venue"
},
  "geometry": {"coordinates":[-0.145944,51.521667],"type":"Point"}
}