{
  "type": "Feature",
  "properties": {
    "iso:country":"GB",
    "sg:address":"Victoria Road, Blackheath",
    "sg:city":"Halesowen",
    "sg:classifiers":[
        {
            "category":"Home & Garden",
            "subcategory":"Hardware",
            "type":"Retail Goods"
        }
    ],
    "sg:phone":"+44 121 559 1754",
    "sg:postcode":"B62 8HZ",
    "sg:province":"West Midlands",
    "sg:tags":[
        "fixing",
        "nuts",
        "bolt"
    ],
    "wof:name":"United Engineering Co. (Blackheath) Ltd.",
    "wof:placetype":"venue"
},
  "geometry": {"coordinates":[-2.0367050171,52.4715843201],"type":"Point"}
}