{
  "type": "Feature",
  "properties": {
    "iso:country":"GB",
    "sg:address":"Unit 30 Purfleet Industrial Park, London Road, Aveley",
    "sg:city":"South Ockendon",
    "sg:classifiers":[
        {
            "category":"Freight",
            "type":"Transportation"
        }
    ],
    "sg:phone":"+44 1708 891300",
    "sg:postcode":"RM15 4YA",
    "sg:province":"Essex",
    "sg:tags":[
        "haulage",
        "road"
    ],
    "wof:name":"Birds Groupage Services Ltd.",
    "wof:placetype":"venue"
},
  "geometry": {"coordinates":[0.233642,51.493118],"type":"Point"}
}