{
  "type": "Feature",
  "properties": {
    "iso:country":"GB",
    "sg:address":"Mylord Crescent, Camperdown Industrial Estate, Killingworth",
    "sg:city":"Newcastle-upon-tyne",
    "sg:classifiers":[
        {
            "category":"Manufacturing",
            "subcategory":"Chemicals & Compounds",
            "type":"Manufacturing & Wholesale Goods"
        },
        {
            "category":"Home & Garden",
            "subcategory":"Hardware",
            "type":"Retail Goods"
        }
    ],
    "sg:phone":"+44 191 268 5054",
    "sg:postcode":"NE12 5XG",
    "sg:province":"Tyne and Wear",
    "sg:tags":[
        "battery",
        "manufacturer"
    ],
    "wof:name":"Entek International Ltd",
    "wof:placetype":"venue"
},
  "geometry": {"coordinates":[-1.582792,55.043541],"type":"Point"}
}