{
  "type": "Feature",
  "properties": {
    "addr:full":"1 Balmellie Street Turriff Aberdeenshire AB53 4DW",
    "addr:housenumber":"1",
    "addr:postcode":"ab53 4dw",
    "addr:street":"Balmellie Street",
    "iso:country":"GB",
    "sg:address":"1 Balmellie Street",
    "sg:city":"Turriff",
    "sg:classifiers":[
        {
            "category":"Health Services",
            "subcategory":"Chiropractor",
            "type":"Services"
        }
    ],
    "sg:phone":"+44 1888 569123",
    "sg:postcode":"AB53 4DW",
    "sg:province":"Aberdeenshire",
    "wof:name":"Turriff Chiropractic Clinic",
    "wof:placetype":"venue"
},
  "geometry": {"coordinates":[-2.4599928856,57.5372886658],"type":"Point"}
}