{
  "type": "Feature",
  "properties": {
    "addr:full":"75 Hyde Park Road Plymouth Devon PL3 4JN",
    "addr:housenumber":"75",
    "addr:postcode":"pl3 4jn",
    "addr:street":"Hyde Park Road",
    "iso:country":"GB",
    "sg:address":"75 Hyde Park Road",
    "sg:city":"Plymouth",
    "sg:classifiers":[
        {
            "category":"Shopping",
            "subcategory":"Gifts & Souvenirs",
            "type":"Retail Goods"
        },
        {
            "category":"Shopping",
            "subcategory":"Comic Books",
            "type":"Retail Goods"
        },
        {
            "category":"Professional",
            "subcategory":"Printing & Photocopies",
            "type":"Services"
        }
    ],
    "sg:phone":"+44 1752 226787",
    "sg:postcode":"PL3 4JN",
    "sg:province":"Devon",
    "sg:tags":[
        "trophy",
        "supplier",
        "jeweller",
        "medal"
    ],
    "wof:name":"PLYMOUTH TROPHYMAN",
    "wof:placetype":"venue"
},
  "geometry": {"coordinates":[-4.138073,50.385639],"type":"Point"}
}