{
  "type": "Feature",
  "properties": {
    "addr:full":"88 Main St, Fulford York North Yorkshire YO10 4PS",
    "addr:housenumber":"88",
    "addr:postcode":"yo10 4ps",
    "addr:street":"Main St",
    "iso:country":"GB",
    "sg:address":"88 Main St, Fulford",
    "sg:city":"York",
    "sg:classifiers":[
        {
            "category":"Home & Garden",
            "subcategory":"Furniture",
            "type":"Retail Goods"
        }
    ],
    "sg:phone":"+44 1904 673939",
    "sg:postcode":"YO10 4PS",
    "sg:province":"North Yorkshire",
    "wof:name":"Rococo (York) Ltd",
    "wof:placetype":"venue"
},
  "geometry": {"coordinates":[-1.071409,53.934231],"type":"Point"}
}