{
  "type": "Feature",
  "properties": {
    "addr:full":"12 Kendall Avenue Stratford-upon-avon Warwickshire CV37 6SG",
    "addr:housenumber":"12",
    "addr:postcode":"cv37 6sg",
    "addr:street":"Kendall Avenue",
    "iso:country":"GB",
    "sg:address":"12 Kendall Avenue",
    "sg:city":"Stratford-upon-avon",
    "sg:classifiers":[
        {
            "category":"Arena",
            "subcategory":"Sports Club",
            "type":"Entertainment"
        }
    ],
    "sg:postcode":"CV37 6SG",
    "sg:province":"Warwickshire",
    "wof:name":"Avon Bowling Club",
    "wof:placetype":"venue"
},
  "geometry": {"coordinates":[-1.708225,52.196899],"type":"Point"}
}