{
  "type": "Feature",
  "properties": {
    "addr:full":"102 Dudley Rd West Tipton West Midlands DY4 7TJ",
    "addr:housenumber":"102",
    "addr:postcode":"dy4 7tj",
    "addr:street":"Dudley Rd West Tipton",
    "iso:country":"GB",
    "sg:address":"102 Dudley Rd West",
    "sg:city":"Tipton",
    "sg:classifiers":[
        {
            "category":"Farming",
            "subcategory":"Nursery",
            "type":"Manufacturing & Wholesale Goods"
        }
    ],
    "sg:phone":"+44 121 557 6262",
    "sg:postcode":"DY4 7TJ",
    "sg:province":"West Midlands",
    "sg:tags":[
        "creche"
    ],
    "wof:name":"Kiddies World Day Nursery",
    "wof:placetype":"venue"
},
  "geometry": {"coordinates":[-2.070697,52.528137],"type":"Point"}
}