{
  "type": "Feature",
  "properties": {
    "addr:full":"Sewer Blockages, Marmion Rd Southsea Hampshire PO5 2BA",
    "addr:postcode":"po5 2ba",
    "addr:street":"Marmion Rd",
    "iso:country":"GB",
    "sg:address":"Sewer Blockages, Marmion Rd",
    "sg:city":"Southsea",
    "sg:classifiers":[
        {
            "category":"Government",
            "subcategory":"Office",
            "type":"Public Place"
        }
    ],
    "sg:phone":"+44 1962 848505",
    "sg:postcode":"PO5 2BA",
    "sg:province":"Hampshire",
    "sg:tags":[
        "local"
    ],
    "wof:name":"Winchester City Council",
    "wof:placetype":"venue"
},
  "geometry": {"coordinates":[-1.0881639719,50.7846641541],"type":"Point"}
}