{
  "type": "Feature",
  "properties": {
    "addr:full":"191 Shirley Road, Foy's Corner, Shirley Southampton Hampshire SO15 3FG",
    "addr:housenumber":"191",
    "addr:postcode":"so15 3fg",
    "addr:street":"Shirley Road Foy'S Corner",
    "iso:country":"GB",
    "sg:address":"191 Shirley Road, Foy's Corner, Shirley",
    "sg:city":"Southampton",
    "sg:classifiers":[
        {
            "category":"Personal",
            "type":"Services"
        }
    ],
    "sg:phone":"+44 23 8070 3366",
    "sg:postcode":"SO15 3FG",
    "sg:province":"Hampshire",
    "sg:tags":[
        "tailor"
    ],
    "wof:name":"Vaghela's",
    "wof:placetype":"venue"
},
  "geometry": {"coordinates":[-1.422901988,50.9143562317],"type":"Point"}
}