{
  "type": "Feature",
  "properties": {
    "addr:full":"68 Faraday Mill Business Park, Catteswater Road Plymouth Devon PL4 0ST",
    "addr:housenumber":"68",
    "addr:postcode":"pl4 0st",
    "addr:street":"Faraday Mill Business Park Catteswater Road",
    "iso:country":"GB",
    "sg:address":"68 Faraday Mill Business Park, Catteswater Road",
    "sg:city":"Plymouth",
    "sg:classifiers":[
        {
            "category":"Shopping",
            "subcategory":"Stationery & Office Supplies",
            "type":"Retail Goods"
        }
    ],
    "sg:phone":"+44 1752 255119",
    "sg:postcode":"PL4 0ST",
    "sg:province":"Devon",
    "sg:tags":[
        "equipment"
    ],
    "wof:name":"The Office Furniture Warehouse",
    "wof:placetype":"venue"
},
  "geometry": {"coordinates":[-4.1134419441,50.3686485291],"type":"Point"}
}