{
  "type": "Feature",
  "properties": {
    "iso:country":"GB",
    "sg:address":"Sussex Road",
    "sg:city":"New Romney",
    "sg:classifiers":[
        {
            "category":"Retail",
            "subcategory":"Auto Repair",
            "type":"Services"
        }
    ],
    "sg:postcode":"TN28 8HJ",
    "sg:province":"Kent",
    "sg:tags":[
        "modification",
        "garage"
    ],
    "wof:name":"Tracey Fagg",
    "wof:placetype":"venue"
},
  "geometry": {"coordinates":[0.934691,50.985023],"type":"Point"}
}