{
  "type": "Feature",
  "properties": {
    "addr:full":"994 Pollokshaws Road Glasgow Glasgow City G41 2HA",
    "addr:housenumber":"994",
    "addr:postcode":"g41 2ha",
    "addr:street":"Pollokshaws Road",
    "iso:country":"GB",
    "sg:address":"994 Pollokshaws Road",
    "sg:city":"Glasgow",
    "sg:classifiers":[
        {
            "category":"Retail",
            "subcategory":"Laundry & Dry Cleaning",
            "type":"Services"
        }
    ],
    "sg:phone":"+44 141 632 0469",
    "sg:postcode":"G41 2HA",
    "sg:province":"Glasgow City",
    "sg:tags":[
        "alteration"
    ],
    "wof:name":"Clark Thomas Tailors",
    "wof:placetype":"venue"
},
  "geometry": {"coordinates":[-4.278005,55.832359],"type":"Point"}
}