{
  "type": "Feature",
  "properties": {
    "addr:full":"Woodmeadow Garage, Roughtown Road Off Stockport Road, Mossley Ashton-under-lyne Greater Manchester OL5 0RD",
    "addr:postcode":"ol5 0rd",
    "addr:street":"Roughtown Road Off Stockport Road",
    "iso:country":"GB",
    "sg:address":"Woodmeadow Garage, Roughtown Road Off Stockport Road, Mossley",
    "sg:city":"Ashton-under-lyne",
    "sg:classifiers":[
        {
            "category":"Retail",
            "subcategory":"Auto Repair",
            "type":"Services"
        }
    ],
    "sg:phone":"+44 1457 837759",
    "sg:postcode":"OL5 0RD",
    "sg:province":"Greater Manchester",
    "sg:tags":[
        "body",
        "car"
    ],
    "wof:name":"Johnsons Motor Bodies",
    "wof:placetype":"venue"
},
  "geometry": {"coordinates":[-2.04033,53.52309],"type":"Point"}
}