{
  "type": "Feature",
  "properties": {
    "iso:country":"GB",
    "sg:address":"Station Street, Whetstone",
    "sg:city":"Leicester",
    "sg:classifiers":[
        {
            "category":"Professional",
            "subcategory":"Engineering",
            "type":"Services"
        }
    ],
    "sg:phone":"+44 116 286 2165",
    "sg:postcode":"LE8 6JS",
    "sg:province":"Leicestershire",
    "sg:tags":[
        "contractor",
        "electrical",
        "engineer"
    ],
    "wof:name":"Electrical Design & Manufacturing Co. Ltd.",
    "wof:placetype":"venue"
},
  "geometry": {"coordinates":[-1.182068944,52.5741882324],"type":"Point"}
}