{
  "type": "Feature",
  "properties": {
    "iso:country":"GB",
    "sg:address":"Unit 10 Freemantle Business Cent, Re 152 Millbrook",
    "sg:city":"Southampton",
    "sg:classifiers":[
        {
            "category":"Organizations",
            "subcategory":"Community Association",
            "type":"Services"
        }
    ],
    "sg:phone":"+44 23 8063 1593",
    "sg:postcode":"SO15 1JR",
    "sg:province":"Hampshire",
    "sg:tags":[
        "relation",
        "public"
    ],
    "wof:name":"Wise Marketing Ltd.",
    "wof:placetype":"venue"
},
  "geometry": {"coordinates":[-1.419629,50.90564],"type":"Point"}
}