{
  "type": "Feature",
  "properties": {
    "addr:full":"29 Court Yard, Eltham Eltham Greater London SE9 5PR",
    "addr:housenumber":"29",
    "addr:postcode":"se9 5pr",
    "addr:street":"Court Yard",
    "iso:country":"GB",
    "sg:address":"29 Court Yard, Eltham",
    "sg:city":"Eltham",
    "sg:classifiers":[
        {
            "category":"Retail",
            "subcategory":"Laundry & Dry Cleaning",
            "type":"Services"
        }
    ],
    "sg:phone":"+44 20 8859 3648",
    "sg:postcode":"SE9 5PR",
    "sg:province":"Greater London",
    "sg:tags":[
        "alteration"
    ],
    "wof:name":"Vic-Klean (Eltham)",
    "wof:placetype":"venue"
},
  "geometry": {"coordinates":[0.05167,51.4499397278],"type":"Point"}
}