{
  "type": "Feature",
  "properties": {
    "iso:country":"GB",
    "sg:address":"1 Collingcroft Clo",
    "sg:city":"Northampton",
    "sg:classifiers":[
        {
            "category":"Manufacturing",
            "subcategory":"Signs",
            "type":"Manufacturing & Wholesale Goods"
        }
    ],
    "sg:phone":"+44 1604 700920",
    "sg:postcode":"NN4 0BN",
    "sg:province":"Northamptonshire",
    "sg:tags":[
        "maker"
    ],
    "wof:name":"De Signs",
    "wof:placetype":"venue"
},
  "geometry": {"coordinates":[-0.9137740135,52.2073364258],"type":"Point"}
}