{
  "type": "Feature",
  "properties": {
    "addr:full":"26 East Church Street Buckie Moray AB56 1AB",
    "addr:housenumber":"26",
    "addr:postcode":"ab56 1ab",
    "addr:street":"East Church Street",
    "iso:country":"GB",
    "sg:address":"26 East Church Street",
    "sg:city":"Buckie",
    "sg:classifiers":[
        {
            "category":"Shopping",
            "subcategory":"Shoes",
            "type":"Retail Goods"
        }
    ],
    "sg:postcode":"AB56 1AB",
    "sg:province":"Moray",
    "sg:tags":[
        "shop"
    ],
    "wof:name":"D.E. Shoes",
    "wof:placetype":"venue"
},
  "geometry": {"coordinates":[-2.961766,57.677074],"type":"Point"}
}