{
  "type": "Feature",
  "properties": {
    "addr:full":"Westwood Business Centre, 69 Aberdalgie Road Glasgow Glasgow City G34 9HJ",
    "addr:housenumber":"69",
    "addr:postcode":"g34 9hj",
    "addr:street":"Aberdalgie Road",
    "iso:country":"GB",
    "sg:address":"Westwood Business Centre, 69 Aberdalgie Road",
    "sg:city":"Glasgow",
    "sg:classifiers":[
        {
            "category":"Government",
            "subcategory":"Office",
            "type":"Public Place"
        }
    ],
    "sg:phone":"+44 141 771 8677",
    "sg:postcode":"G34 9HJ",
    "sg:province":"Glasgow City",
    "sg:tags":[
        "project",
        "gov",
        "community"
    ],
    "wof:name":"Safe Greater Easterhouse",
    "wof:placetype":"venue"
},
  "geometry": {"coordinates":[-4.11685,55.86805],"type":"Point"}
}