{
  "type": "Feature",
  "properties": {
    "addr:full":"134 Portchester Road Fareham Hampshire PO16 8QP",
    "addr:housenumber":"134",
    "addr:postcode":"po16 8qp",
    "addr:street":"Portchester Road",
    "iso:country":"GB",
    "sg:address":"134 Portchester Road",
    "sg:city":"Fareham",
    "sg:classifiers":[
        {
            "category":"Health Services",
            "subcategory":"Nursing And Care Facility",
            "type":"Services"
        },
        {
            "category":"Social Services",
            "subcategory":"Retirement Home",
            "type":"Services"
        }
    ],
    "sg:phone":"+44 1329 233603",
    "sg:postcode":"PO16 8QP",
    "sg:province":"Hampshire",
    "sg:tags":[
        "residential"
    ],
    "wof:name":"Cornelia House",
    "wof:placetype":"venue"
},
  "geometry": {"coordinates":[-1.14341,50.84898],"type":"Point"}
}