{
  "type": "Feature",
  "properties": {
    "addr:full":"Unit 4, 296 Newark Road, North Hykeham Lincoln Lincolnshire LN5 8JX",
    "addr:housenumber":"unit 4 296",
    "addr:postcode":"ln5 8jx",
    "addr:street":"Newark Road North",
    "iso:country":"GB",
    "sg:address":"Unit 4, 296 Newark Road, North Hykeham",
    "sg:city":"Lincoln",
    "sg:classifiers":[
        {
            "category":"Home & Garden",
            "subcategory":"Furniture",
            "type":"Retail Goods"
        }
    ],
    "sg:phone":"+44 1522 694447",
    "sg:postcode":"LN5 8JX",
    "sg:province":"Lincolnshire",
    "wof:name":"J R Pine",
    "wof:placetype":"venue"
},
  "geometry": {"coordinates":[-0.5519379973,53.2040367126],"type":"Point"}
}