{
  "type": "Feature",
  "properties": {
    "addr:full":"226 High St Beckenham Kent BR3 1EN",
    "addr:housenumber":"226",
    "addr:postcode":"br3 1en",
    "addr:street":"High St",
    "iso:country":"GB",
    "sg:address":"226 High St",
    "sg:city":"Beckenham",
    "sg:classifiers":[
        {
            "category":"Sports & Exercise",
            "subcategory":"Sports Center",
            "type":"Entertainment"
        }
    ],
    "sg:phone":"+44 20 8650 5355",
    "sg:postcode":"BR3 1EN",
    "sg:province":"Kent",
    "sg:tags":[
        "shop",
        "good"
    ],
    "wof:name":"Beckenham Sports & Toys",
    "wof:placetype":"venue"
},
  "geometry": {"coordinates":[-0.028925,51.406586],"type":"Point"}
}