{
  "type": "Feature",
  "properties": {
    "iso:country":"GB",
    "sg:address":"Roundhay, 3 Pit Farm Road",
    "sg:city":"Guildford",
    "sg:classifiers":[
        {
            "category":"Social Services",
            "subcategory":"Retirement Home",
            "type":"Services"
        },
        {
            "category":"Organizations",
            "subcategory":"Community Association",
            "type":"Services"
        }
    ],
    "sg:phone":"+44 1483 561367",
    "sg:postcode":"GU1 2JH",
    "sg:province":"Surrey",
    "sg:tags":[
        "society",
        "housing",
        "sheltered",
        "accommodation"
    ],
    "wof:name":"Abbeyfield Guildford Society",
    "wof:placetype":"venue"
},
  "geometry": {"coordinates":[-0.570516,51.237087],"type":"Point"}
}