{
  "type": "Feature",
  "properties": {
    "addr:full":"Old Winton Rd Andover Hampshire SP10 2BZ",
    "addr:postcode":"sp10 2bz",
    "addr:street":"Old Winton Rd",
    "iso:country":"GB",
    "sg:address":"Old Winton Rd",
    "sg:city":"Andover",
    "sg:classifiers":[
        {
            "category":"Parking",
            "type":"Transportation"
        }
    ],
    "sg:postcode":"SP10 2BZ",
    "sg:province":"Hampshire",
    "sg:tags":[
        "car",
        "valet"
    ],
    "wof:name":"Williams,Kevin,",
    "wof:placetype":"venue"
},
  "geometry": {"coordinates":[-1.4776829481,51.2040328979],"type":"Point"}
}