{
  "type": "Feature",
  "properties": {
    "addr:full":"Second Floor, 26 Eastcastle Street London Greater London W1W 8DF",
    "addr:housenumber":"second floor 26",
    "addr:postcode":"w1w 8df",
    "addr:street":"Eastcastle Street",
    "iso:country":"GB",
    "sg:address":"Second Floor, 26 Eastcastle Street",
    "sg:city":"London",
    "sg:classifiers":[
        {
            "category":"Manufacturing",
            "subcategory":"Textiles",
            "type":"Manufacturing & Wholesale Goods"
        }
    ],
    "sg:postcode":"W1W 8DF",
    "sg:province":"Greater London",
    "sg:tags":[
        "merchant",
        "agent"
    ],
    "wof:name":"Kate Hathway Ltd.",
    "wof:placetype":"venue"
},
  "geometry": {"coordinates":[-0.138342,51.51672],"type":"Point"}
}