{
  "type": "Feature",
  "properties": {
    "iso:country":"GB",
    "sg:address":"950 Argyle St",
    "sg:city":"Glasgow",
    "sg:classifiers":[
        {
            "category":"Health Services",
            "subcategory":"Dentist",
            "type":"Services"
        }
    ],
    "sg:phone":"+44 141 204 4080",
    "sg:postcode":"G3 8LU",
    "sg:province":"Glasgow City",
    "wof:name":"Argyle Dental Practice",
    "wof:placetype":"venue"
},
  "geometry": {"coordinates":[-4.279669,55.863369],"type":"Point"}
}