{
  "type": "Feature",
  "properties": {
    "iso:country":"GB",
    "sg:address":"55 South Coast Rd",
    "sg:city":"Peacehaven",
    "sg:classifiers":[
        {
            "category":"Health Services",
            "subcategory":"Doctor",
            "type":"Services"
        }
    ],
    "sg:phone":"+44 1273 588777",
    "sg:postcode":"BN10 8QW",
    "sg:province":"East Sussex",
    "sg:tags":[
        "practitioners"
    ],
    "wof:name":"Gupta, V K",
    "wof:placetype":"venue"
},
  "geometry": {"coordinates":[0.0154839996,50.7881355286],"type":"Point"}
}