{
  "type": "Feature",
  "properties": {
    "iso:country":"GB",
    "sg:address":"Leaze Farm, Wharfside, Lympsham",
    "sg:city":"Weston-super-mare",
    "sg:classifiers":[
        {
            "category":"Farming",
            "subcategory":"Livestock Farm",
            "type":"Manufacturing & Wholesale Goods"
        }
    ],
    "sg:postcode":"BS24 0EZ",
    "sg:province":"Somerset",
    "sg:tags":[
        "others"
    ],
    "wof:name":"F E Luff",
    "wof:placetype":"venue"
},
  "geometry": {"coordinates":[-2.952351,51.284443],"type":"Point"}
}