{
  "type": "Feature",
  "properties": {
    "iso:country":"GB",
    "sg:address":"50 Manchester Road",
    "sg:city":"Preston",
    "sg:classifiers":[
        {
            "category":"Professional",
            "subcategory":"Printing & Photocopies",
            "type":"Services"
        }
    ],
    "sg:phone":"+44 1772 556688",
    "sg:postcode":"PR1 3YH",
    "sg:province":"Lancashire",
    "sg:tags":[
        "embroiderer"
    ],
    "wof:name":"Stephen Simpson",
    "wof:placetype":"venue"
},
  "geometry": {"coordinates":[-2.692974,53.758598],"type":"Point"}
}