{
  "type": "Feature",
  "properties": {
    "iso:country":"GB",
    "sg:address":"3 High Street, Cheslyn Hay",
    "sg:city":"Walsall",
    "sg:classifiers":[
        {
            "category":"Shopping",
            "subcategory":"Pharmacy",
            "type":"Retail Goods"
        }
    ],
    "sg:phone":"+44 1922 413053",
    "sg:postcode":"WS6 7AB",
    "sg:province":"Staffordshire",
    "sg:tags":[
        "pharmacist",
        "chemist"
    ],
    "wof:name":"Stevenson Chemist",
    "wof:placetype":"venue"
},
  "geometry": {"coordinates":[-2.0313670635,52.6615867615],"type":"Point"}
}