{
  "type": "Feature",
  "properties": {
    "iso:country":"GB",
    "sg:address":"16 Carwood",
    "sg:city":"Telford",
    "sg:classifiers":[
        {
            "category":"Government",
            "subcategory":"Office",
            "type":"Public Place"
        }
    ],
    "sg:phone":"+44 1952 592436",
    "sg:postcode":"TF3 1YA",
    "sg:province":"Shropshire",
    "sg:tags":[
        "local"
    ],
    "wof:name":"People With Learning Difficulties Division",
    "wof:placetype":"venue"
},
  "geometry": {"coordinates":[-2.4497230053,52.648273468],"type":"Point"}
}