{
  "type": "Feature",
  "properties": {
    "addr:full":"252 Bridgewater Road Wembley Greater London HA0 1AS",
    "addr:housenumber":"252",
    "addr:postcode":"ha0 1as",
    "addr:street":"Bridgewater Road",
    "iso:country":"GB",
    "sg:address":"252 Bridgewater Road",
    "sg:city":"Wembley",
    "sg:classifiers":[
        {
            "category":"Health Services",
            "subcategory":"Doctor",
            "type":"Services"
        }
    ],
    "sg:postcode":"HA0 1AS",
    "sg:province":"Greater London",
    "sg:tags":[
        "practitioners"
    ],
    "wof:name":"Visico Ltd",
    "wof:placetype":"venue"
},
  "geometry": {"coordinates":[-0.309244,51.547012],"type":"Point"}
}