{
  "type": "Feature",
  "properties": {
    "iso:country":"GB",
    "sg:address":"160-162 Cemetery Road",
    "sg:city":"Sheffield",
    "sg:classifiers":[
        {
            "category":"Bars & Pubs",
            "type":"Food & Drink"
        }
    ],
    "sg:phone":"+44 114 276 8920",
    "sg:postcode":"S11 8FR",
    "sg:province":"Derbyshire",
    "sg:tags":[
        "pubs",
        "inn"
    ],
    "wof:name":"The Vine Inn",
    "wof:placetype":"venue"
},
  "geometry": {"coordinates":[-1.490549,53.369431],"type":"Point"}
}