{
  "type": "Feature",
  "properties": {
    "addr:full":"108 Oxford Road High Wycombe Buckinghamshire HP11 2DN",
    "addr:housenumber":"108",
    "addr:postcode":"hp11 2dn",
    "addr:street":"Oxford Road",
    "iso:country":"GB",
    "sg:address":"108 Oxford Road",
    "sg:city":"High Wycombe",
    "sg:classifiers":[
        {
            "category":"Building & Trades",
            "subcategory":"Construction",
            "type":"Services"
        },
        {
            "category":"Organizations",
            "subcategory":"Professional Association",
            "type":"Services"
        }
    ],
    "sg:phone":"+44 1494 526931",
    "sg:postcode":"HP11 2DN",
    "sg:province":"Buckinghamshire",
    "sg:tags":[
        "union",
        "activity"
    ],
    "wof:name":"GMB",
    "wof:placetype":"venue"
},
  "geometry": {"coordinates":[-0.755533,51.632019],"type":"Point"}
}