{
  "type": "Feature",
  "properties": {
    "iso:country":"GB",
    "sg:address":"Clare House, Church Street, Ticehurst",
    "sg:city":"Wadhurst",
    "sg:classifiers":[
        {
            "category":"Food & Beverages",
            "subcategory":"Fruits & Vegetables",
            "type":"Retail Goods"
        }
    ],
    "sg:phone":"+44 1580 200668",
    "sg:postcode":"TN5 7AE",
    "sg:province":"East Sussex",
    "sg:tags":[
        "greengrocer"
    ],
    "wof:name":"C Leach",
    "wof:placetype":"venue"
},
  "geometry": {"coordinates":[0.407889,51.046303],"type":"Point"}
}