{
  "type": "Feature",
  "properties": {
    "iso:country":"GB",
    "sg:address":"123 Northcote Rd",
    "sg:city":"Croydon",
    "sg:classifiers":[
        {
            "category":"Food & Beverages",
            "subcategory":"Liquor & Beverages",
            "type":"Retail Goods"
        }
    ],
    "sg:phone":"+44 20 8683 3451",
    "sg:postcode":"CR0 2HZ",
    "sg:province":"Surrey",
    "sg:tags":[
        "beer",
        "spirit",
        "wines"
    ],
    "wof:name":"Bottle & Basket Off Licence",
    "wof:placetype":"venue"
},
  "geometry": {"coordinates":[-0.091577,51.388744],"type":"Point"}
}