{
  "type": "Feature",
  "properties": {
    "iso:country":"GB",
    "sg:address":"Broadway Drive",
    "sg:city":"Halesworth",
    "sg:classifiers":[
        {
            "category":"Professional",
            "subcategory":"Business Services",
            "type":"Services"
        },
        {
            "category":"Shopping",
            "type":"Retail Goods"
        }
    ],
    "sg:phone":"+44 1986 873612",
    "sg:postcode":"IP19 8QR",
    "sg:province":"Suffolk",
    "sg:tags":[
        "merchant",
        "agricultural"
    ],
    "wof:name":"Crop Care Holdings Ltd.",
    "wof:placetype":"venue"
},
  "geometry": {"coordinates":[1.503773,52.344131],"type":"Point"}
}