{
  "type": "Feature",
  "properties": {
    "addr:full":"22 Taffs Mead Embkmt Cardiff Cardiff CF11 6RH",
    "addr:housenumber":"22",
    "addr:postcode":"cf11 6rh",
    "addr:street":"Taffs Mead Embkmt",
    "iso:country":"GB",
    "sg:address":"22 Taffs Mead Embkmt",
    "sg:city":"Cardiff",
    "sg:classifiers":[
        {
            "category":"Retail",
            "subcategory":"Repair Shop",
            "type":"Services"
        }
    ],
    "sg:postcode":"CF11 6RH",
    "sg:province":"Cardiff",
    "sg:tags":[
        "furniture"
    ],
    "wof:name":"Fitzpatrick Restoration",
    "wof:placetype":"venue"
},
  "geometry": {"coordinates":[-3.1828670502,51.474029541],"type":"Point"}
}