{
  "type": "Feature",
  "properties": {
    "iso:country":"GB",
    "sg:address":"Lake Road, Off Florence Road",
    "sg:city":"Chichester",
    "sg:classifiers":[
        {
            "category":"Home & Garden",
            "subcategory":"Hardware",
            "type":"Retail Goods"
        }
    ],
    "sg:phone":"+44 1243 789392",
    "sg:postcode":"PO19 7TD",
    "sg:province":"West Sussex",
    "sg:tags":[
        "lawnmowers",
        "machinery"
    ],
    "wof:name":"Chichester Mowers",
    "wof:placetype":"venue"
},
  "geometry": {"coordinates":[-0.760494,50.835224],"type":"Point"}
}