{
  "type": "Feature",
  "properties": {
    "iso:country":"GB",
    "sg:address":"Dudley Road",
    "sg:city":"Brierley Hill",
    "sg:classifiers":[
        {
            "category":"Restaurant",
            "type":"Food & Drink"
        }
    ],
    "sg:phone":"+44 1384 291290",
    "sg:postcode":"DY6 8BS",
    "sg:province":"Staffordshire",
    "wof:name":"Kingswinford Brewers Fayre & Travel Inn",
    "wof:placetype":"venue"
},
  "geometry": {"coordinates":[-2.117409,52.490849],"type":"Point"}
}