{
  "type": "Feature",
  "properties": {
    "iso:country":"GB",
    "sg:address":"17 Crud Y Gwynt, Mynydd Isa",
    "sg:city":"Buckley",
    "sg:classifiers":[
        {
            "category":"Building & Trades",
            "subcategory":"Construction",
            "type":"Services"
        }
    ],
    "sg:postcode":"CH7 6TB",
    "sg:province":"Denbighshire",
    "sg:tags":[
        "joiner",
        "carpenter"
    ],
    "wof:name":"D Duckworth",
    "wof:placetype":"venue"
},
  "geometry": {"coordinates":[-3.120426,53.174435],"type":"Point"}
}