{
  "type": "Feature",
  "properties": {
    "addr:full":"Gardner Ho, Olympus Park Business Centre Gloucester Gloucestershire GL2 4NF",
    "addr:postcode":"gl2 4nf",
    "iso:country":"GB",
    "sg:address":"Gardner Ho, Olympus Park Business Centre",
    "sg:city":"Gloucester",
    "sg:classifiers":[
        {
            "category":"Professional",
            "subcategory":"Detective & Security Services",
            "type":"Services"
        }
    ],
    "sg:phone":"+44 1452 883337",
    "sg:postcode":"GL2 4NF",
    "sg:province":"Gloucestershire",
    "sg:tags":[
        "alarm",
        "burglar",
        "system"
    ],
    "wof:name":"Gardner Security",
    "wof:placetype":"venue"
},
  "geometry": {"coordinates":[-2.27399,51.832272],"type":"Point"}
}