{
  "type": "Feature",
  "properties": {
    "iso:country":"GB",
    "sg:address":"174 Southworth Road",
    "sg:city":"Newton-le-willows",
    "sg:classifiers":[
        {
            "category":"Home & Garden",
            "subcategory":"Garden Supply",
            "type":"Retail Goods"
        }
    ],
    "sg:phone":"+44 1925 224138",
    "sg:postcode":"WA12 0BS",
    "sg:province":"Cheshire",
    "sg:tags":[
        "nursery",
        "centre"
    ],
    "wof:name":"Microse Ltd.",
    "wof:placetype":"venue"
},
  "geometry": {"coordinates":[-2.6052589417,53.455581665],"type":"Point"}
}