{
  "type": "Feature",
  "properties": {
    "iso:country":"GB",
    "sg:address":"2 Greenwood Way",
    "sg:city":"Birmingham",
    "sg:classifiers":[
        {
            "category":"Real Estate",
            "subcategory":"Real Estate Operator",
            "type":"Services"
        },
        {
            "category":"Transit Center",
            "subcategory":"Freight",
            "type":"Transportation"
        },
        {
            "category":"Commercial Area",
            "type":"Public Place"
        }
    ],
    "sg:phone":"+44 121 788 0708",
    "sg:postcode":"B37 5TL",
    "sg:province":"West Midlands",
    "sg:tags":[
        "shop",
        "shopping",
        "property",
        "leasing",
        "centre"
    ],
    "wof:name":"IN SHOPS CENTRES LTD",
    "wof:placetype":"venue"
},
  "geometry": {"coordinates":[-1.73983,52.479511],"type":"Point"}
}