{
  "type": "Feature",
  "properties": {
    "iso:country":"GB",
    "sg:address":"Esk Gro, Coach House, Inveresk Village",
    "sg:city":"Musselburgh",
    "sg:classifiers":[
        {
            "category":"Manufacturing",
            "subcategory":"Wood Products",
            "type":"Manufacturing & Wholesale Goods"
        }
    ],
    "sg:phone":"+44 131 665 0764",
    "sg:postcode":"EH21 7TD",
    "sg:province":"City of Edinburgh",
    "sg:tags":[
        "maker",
        "cabinet"
    ],
    "wof:name":"Hart Cabinet Makers",
    "wof:placetype":"venue"
},
  "geometry": {"coordinates":[-3.049754,55.940117],"type":"Point"}
}