{
  "type": "Feature",
  "properties": {
    "addr:full":"Wallace St Galston East Ayrshire KA4 8HP",
    "addr:postcode":"ka4 8hp",
    "addr:street":"Wallace St",
    "iso:country":"GB",
    "sg:address":"Wallace St",
    "sg:city":"Galston",
    "sg:classifiers":[
        {
            "category":"Retail",
            "subcategory":"Veterinary Services",
            "type":"Services"
        }
    ],
    "sg:phone":"+44 1563 820367",
    "sg:postcode":"KA4 8HP",
    "sg:province":"East Ayrshire",
    "sg:tags":[
        "surgeon"
    ],
    "wof:name":"Valley Veterinary Surgery",
    "wof:placetype":"venue"
},
  "geometry": {"coordinates":[-4.3798441887,55.600025177],"type":"Point"}
}