{
  "type": "Feature",
  "properties": {
    "iso:country":"GB",
    "sg:address":"Lewth Farm, Lewth La",
    "sg:city":"Preston",
    "sg:classifiers":[
        {
            "category":"Utilities",
            "subcategory":"Refuse",
            "type":"Services"
        }
    ],
    "sg:phone":"+44 1772 690483",
    "sg:postcode":"PR4 0TD",
    "sg:province":"Lancashire",
    "sg:tags":[
        "skip",
        "hire"
    ],
    "wof:name":"E H Mini Skip Hire",
    "wof:placetype":"venue"
},
  "geometry": {"coordinates":[-2.78624,53.821579],"type":"Point"}
}