{
  "type": "Feature",
  "properties": {
    "iso:country":"GB",
    "sg:address":"2 The Fairings",
    "sg:city":"Tenterden",
    "sg:classifiers":[
        {
            "category":"Professional",
            "subcategory":"Detective & Security Services",
            "type":"Services"
        }
    ],
    "sg:postcode":"TN30 6QX",
    "sg:province":"Kent",
    "sg:tags":[
        "locksmith"
    ],
    "wof:name":"Wealden Security Centre",
    "wof:placetype":"venue"
},
  "geometry": {"coordinates":[0.6904039979,51.0703048706],"type":"Point"}
}