{
  "type": "Feature",
  "properties": {
    "addr:full":"Elm Gable, Cowbit Road Spalding Lincolnshire PE11 2RJ",
    "addr:postcode":"pe11 2rj",
    "addr:street":"Cowbit Road",
    "iso:country":"GB",
    "sg:address":"Elm Gable, Cowbit Road",
    "sg:city":"Spalding",
    "sg:classifiers":[
        {
            "category":"Farming",
            "subcategory":"Farm",
            "type":"Manufacturing & Wholesale Goods"
        }
    ],
    "sg:phone":"+44 1775 723892",
    "sg:postcode":"PE11 2RJ",
    "sg:province":"Lincolnshire",
    "sg:tags":[
        "mixed",
        "crop"
    ],
    "wof:name":"R Chappell & Sons",
    "wof:placetype":"venue"
},
  "geometry": {"coordinates":[-0.151488,52.788342],"type":"Point"}
}