{
  "type": "Feature",
  "properties": {
    "addr:full":"11 St Pauls Road Newton Abbot Devon TQ12 2HP",
    "addr:housenumber":"11",
    "addr:postcode":"tq12 2hp",
    "addr:street":"St Pauls Road",
    "iso:country":"GB",
    "sg:address":"11 St Pauls Road",
    "sg:city":"Newton Abbot",
    "sg:classifiers":[
        {
            "category":"Health Services",
            "subcategory":"Dentist",
            "type":"Services"
        }
    ],
    "sg:phone":"+44 1626 205072",
    "sg:postcode":"TQ12 2HP",
    "sg:province":"Devon",
    "wof:name":"Ian McDermott",
    "wof:placetype":"venue"
},
  "geometry": {"coordinates":[-3.603713,50.530521],"type":"Point"}
}