{
  "type": "Feature",
  "properties": {
    "iso:country":"GB",
    "sg:address":"N12 Troonway Business Centre, Humberstone Lane, Thurmaston",
    "sg:city":"Leicester",
    "sg:classifiers":[
        {
            "category":"Building & Trades",
            "subcategory":"Electrical",
            "type":"Services"
        }
    ],
    "sg:phone":"+44 116 246 4271",
    "sg:postcode":"LE4 7JW",
    "sg:province":"Leicestershire",
    "sg:tags":[
        "lighting"
    ],
    "wof:name":"The G B Lamp Co. Ltd.",
    "wof:placetype":"venue"
},
  "geometry": {"coordinates":[-1.10816,52.662319],"type":"Point"}
}