{
  "type": "Feature",
  "properties": {
    "iso:country":"GB",
    "sg:address":"9 Hick Lane",
    "sg:city":"Batley",
    "sg:classifiers":[
        {
            "category":"Personal",
            "subcategory":"Beauty Salon",
            "type":"Services"
        }
    ],
    "sg:phone":"+44 1924 445661",
    "sg:postcode":"WF17 5TD",
    "sg:province":"West Yorkshire",
    "wof:name":"Skin & Tonic Beauty Studio",
    "wof:placetype":"venue"
},
  "geometry": {"coordinates":[-1.62788,53.712128],"type":"Point"}
}