{
  "type": "Feature",
  "properties": {
    "addr:full":"26 Pine Road, Didsbury Manchester Greater Manchester M20 6UZ",
    "addr:housenumber":"26",
    "addr:postcode":"m20 6uz",
    "addr:street":"Pine Road",
    "iso:country":"GB",
    "sg:address":"26 Pine Road, Didsbury",
    "sg:city":"Manchester",
    "sg:classifiers":[
        {
            "category":"Professional",
            "subcategory":"Art Services",
            "type":"Services"
        }
    ],
    "sg:phone":"+44 161 445 2000",
    "sg:postcode":"M20 6UZ",
    "sg:province":"Greater Manchester",
    "sg:tags":[
        "graphic",
        "designer"
    ],
    "wof:name":"Tin Drum Associates Ltd.",
    "wof:placetype":"venue"
},
  "geometry": {"coordinates":[-2.2343170643,53.4196434021],"type":"Point"}
}