{
  "type": "Feature",
  "properties": {
    "addr:full":"2 Chapel Street, Pemberton Wigan Lancashire WN5 8JP",
    "addr:housenumber":"2",
    "addr:postcode":"wn5 8jp",
    "addr:street":"Chapel Street",
    "iso:country":"GB",
    "sg:address":"2 Chapel Street, Pemberton",
    "sg:city":"Wigan",
    "sg:classifiers":[
        {
            "category":"Shopping",
            "subcategory":"Comic Books",
            "type":"Retail Goods"
        }
    ],
    "sg:postcode":"WN5 8JP",
    "sg:province":"Lancashire",
    "sg:tags":[
        "jeweller"
    ],
    "wof:name":"Whites Jewellers",
    "wof:placetype":"venue"
},
  "geometry": {"coordinates":[-2.6846790314,53.5356712341],"type":"Point"}
}