{
  "type": "Feature",
  "properties": {
    "iso:country":"GB",
    "sg:address":"187 Shepherds Bush Market",
    "sg:city":"London",
    "sg:classifiers":[
        {
            "category":"Shopping",
            "subcategory":"Pharmacy",
            "type":"Retail Goods"
        }
    ],
    "sg:phone":"+44 20 8743 1772",
    "sg:postcode":"W12 8DF",
    "sg:province":"Greater London",
    "sg:tags":[
        "store",
        "drug"
    ],
    "wof:name":"Phils Drug Store",
    "wof:placetype":"venue"
},
  "geometry": {"coordinates":[-0.227339,51.505322],"type":"Point"}
}