{
  "type": "Feature",
  "properties": {
    "addr:full":"1 Clarks Terrace, Allonby Maryport Cumbria CA15 6PU",
    "addr:housenumber":"1",
    "addr:postcode":"ca15 6pu",
    "addr:street":"Clarks Terrace",
    "iso:country":"GB",
    "sg:address":"1 Clarks Terrace, Allonby",
    "sg:city":"Maryport",
    "sg:classifiers":[
        {
            "category":"Government",
            "subcategory":"Post Office",
            "type":"Public Place"
        }
    ],
    "sg:postcode":"CA15 6PU",
    "sg:province":"Cumbria",
    "wof:name":"Allonby Post Office",
    "wof:placetype":"venue"
},
  "geometry": {"coordinates":[-3.496535,54.712391],"type":"Point"}
}