{
  "type": "Feature",
  "properties": {
    "iso:country":"GB",
    "sg:address":"23 Terrace Road",
    "sg:city":"Buxton",
    "sg:classifiers":[
        {
            "category":"Shopping",
            "subcategory":"News",
            "type":"Retail Goods"
        }
    ],
    "sg:postcode":"SK17 6DU",
    "sg:province":"Derbyshire",
    "sg:tags":[
        "newsagent"
    ],
    "wof:name":"P & M Goodwin",
    "wof:placetype":"venue"
},
  "geometry": {"coordinates":[-1.9132750034,53.256729126],"type":"Point"}
}