{
  "type": "Feature",
  "properties": {
    "addr:full":"5 Cortina Rise, Darfield Barnsley South Yorkshire S73 9RH",
    "addr:housenumber":"5",
    "addr:postcode":"s73 9rh",
    "addr:street":"Cortina Rise;Yorkshire",
    "iso:country":"GB",
    "sg:address":"5 Cortina Rise, Darfield",
    "sg:city":"Barnsley",
    "sg:classifiers":[
        {
            "category":"Building & Trades",
            "subcategory":"Construction",
            "type":"Services"
        }
    ],
    "sg:postcode":"S73 9RH",
    "sg:province":"South Yorkshire",
    "sg:tags":[
        "builder"
    ],
    "wof:name":"Tracethrough Ltd",
    "wof:placetype":"venue"
},
  "geometry": {"coordinates":[-1.3916050196,53.5395698547],"type":"Point"}
}