{
  "type": "Feature",
  "properties": {
    "addr:full":"714 High Rd London Greater London N12 9QD",
    "addr:housenumber":"714",
    "addr:postcode":"n12 9qd",
    "addr:street":"High Rd",
    "iso:country":"GB",
    "sg:address":"714 High Rd",
    "sg:city":"London",
    "sg:classifiers":[
        {
            "category":"Travel",
            "subcategory":"Travel Agent",
            "type":"Entertainment"
        }
    ],
    "sg:phone":"+44 20 8446 4181",
    "sg:postcode":"N12 9QD",
    "sg:province":"Greater London",
    "sg:tags":[
        "agency",
        "activity"
    ],
    "wof:name":"Preston Travel Ltd",
    "wof:placetype":"venue"
},
  "geometry": {"coordinates":[-0.1756940037,51.613117218],"type":"Point"}
}