{
  "type": "Feature",
  "properties": {
    "addr:full":"48 Camp Road Farnborough Hampshire GU14 6EP",
    "addr:housenumber":"48",
    "addr:postcode":"gu14 6ep",
    "addr:street":"Camp Road",
    "iso:country":"GB",
    "sg:address":"48 Camp Road",
    "sg:city":"Farnborough",
    "sg:classifiers":[
        {
            "category":"Professional",
            "subcategory":"Accounting & Tax Preparation",
            "type":"Services"
        }
    ],
    "sg:phone":"+44 1252 517704",
    "sg:postcode":"GU14 6EP",
    "sg:province":"Hampshire",
    "sg:tags":[
        "consultant"
    ],
    "wof:name":"A K M Associates",
    "wof:placetype":"venue"
},
  "geometry": {"coordinates":[-0.747287,51.276352],"type":"Point"}
}