{
  "type": "Feature",
  "properties": {
    "iso:country":"GB",
    "sg:address":"Rose Ash",
    "sg:city":"South Molton",
    "sg:classifiers":[
        {
            "category":"Building & Trades",
            "subcategory":"Cleaning & Sanitation",
            "type":"Services"
        }
    ],
    "sg:phone":"+44 1769 550868",
    "sg:postcode":"EX36 4QT",
    "sg:province":"Devon",
    "sg:tags":[
        "commercial"
    ],
    "wof:name":"Graffiti Busters",
    "wof:placetype":"venue"
},
  "geometry": {"coordinates":[-3.8318240643,51.0176467896],"type":"Point"}
}