{
  "type": "Feature",
  "properties": {
    "addr:full":"Suite 3,  Heathcote Buildings, Heathcoat St Nottingham Nottinghamshire NG1 3AA",
    "addr:housenumber":"suite 3",
    "addr:postcode":"ng1 3aa",
    "addr:street":"Heathcote Buildings Heathcoat St",
    "iso:country":"GB",
    "sg:address":"Suite 3,  Heathcote Buildings, Heathcoat St",
    "sg:city":"Nottingham",
    "sg:classifiers":[
        {
            "category":"Professional",
            "subcategory":"Employment Agencies",
            "type":"Services"
        }
    ],
    "sg:phone":"+44 115 941 8818",
    "sg:postcode":"NG1 3AA",
    "sg:province":"Nottinghamshire",
    "sg:tags":[
        "consultant"
    ],
    "wof:name":"N.B Selection Ltd",
    "wof:placetype":"venue"
},
  "geometry": {"coordinates":[-1.143079,52.95491],"type":"Point"}
}