{
  "type": "Feature",
  "properties": {
    "iso:country":"GB",
    "sg:address":"P O Box 2772",
    "sg:city":"New Milton",
    "sg:classifiers":[
        {
            "category":"Professional",
            "subcategory":"Employment Agencies",
            "type":"Services"
        }
    ],
    "sg:postcode":"BH25 5FT",
    "sg:province":"Hampshire",
    "sg:tags":[
        "consultant"
    ],
    "wof:name":"The Locum Exchange Ltd.",
    "wof:placetype":"venue"
},
  "geometry": {"coordinates":[-1.653929,50.762192],"type":"Point"}
}