{
  "type": "Feature",
  "properties": {
    "addr:full":"72 Hornby Road Blackpool Lancashire FY1 4QJ",
    "addr:housenumber":"72",
    "addr:postcode":"fy1 4qj",
    "addr:street":"Hornby Road",
    "iso:country":"GB",
    "sg:address":"72 Hornby Road",
    "sg:city":"Blackpool",
    "sg:classifiers":[
        {
            "category":"Travel",
            "subcategory":"Hotels & Motels",
            "type":"Entertainment"
        }
    ],
    "sg:phone":"+44 1253 627327",
    "sg:postcode":"FY1 4QJ",
    "sg:province":"Lancashire",
    "sg:tags":[
        "house",
        "guest"
    ],
    "wof:name":"Leawood",
    "wof:placetype":"venue"
},
  "geometry": {"coordinates":[-3.048576,53.81443],"type":"Point"}
}