{
  "type": "Feature",
  "properties": {
    "iso:country":"GB",
    "sg:address":"1106 Cathcart Road",
    "sg:city":"Glasgow",
    "sg:classifiers":[
        {
            "category":"Fast Food",
            "type":"Food & Drink"
        }
    ],
    "sg:phone":"+44 141 649 1688",
    "sg:postcode":"G42 9EG",
    "sg:province":"Glasgow City",
    "sg:tags":[
        "away",
        "take"
    ],
    "wof:name":"Williams House",
    "wof:placetype":"venue"
},
  "geometry": {"coordinates":[-4.2581458092,55.8266601562],"type":"Point"}
}