{
  "type": "Feature",
  "properties": {
    "addr:full":"78 Cromwell Road Cambridge Cambridgeshire CB1 3EG",
    "addr:housenumber":"78",
    "addr:postcode":"cb1 3eg",
    "addr:street":"Cromwell Road",
    "iso:country":"GB",
    "sg:address":"78 Cromwell Road",
    "sg:city":"Cambridge",
    "sg:classifiers":[
        {
            "category":"Professional",
            "subcategory":"Management & Consulting",
            "type":"Services"
        }
    ],
    "sg:phone":"+44 1223 515230",
    "sg:postcode":"CB1 3EG",
    "sg:province":"Cambridgeshire",
    "sg:tags":[
        "consultant",
        "business"
    ],
    "wof:name":"Catchpole Consulting Ltd.",
    "wof:placetype":"venue"
},
  "geometry": {"coordinates":[0.1470019966,52.2028770447],"type":"Point"}
}