{
  "type": "Feature",
  "properties": {
    "addr:full":"19 Barnston Lane Wirral Merseyside CH46 7TN",
    "addr:housenumber":"19",
    "addr:postcode":"ch46 7tn",
    "addr:street":"Barnston Lane",
    "iso:country":"GB",
    "sg:address":"19 Barnston Lane",
    "sg:city":"Wirral",
    "sg:classifiers":[
        {
            "category":"Building & Trades",
            "subcategory":"Cleaning & Sanitation",
            "type":"Services"
        }
    ],
    "sg:phone":"+44 151 606 0700",
    "sg:postcode":"CH46 7TN",
    "sg:province":"Merseyside",
    "sg:tags":[
        "commercial"
    ],
    "wof:name":"Initial Cleaning Services",
    "wof:placetype":"venue"
},
  "geometry": {"coordinates":[-3.1134910583,53.40209198],"type":"Point"}
}