{
  "type": "Feature",
  "properties": {
    "iso:country":"GB",
    "sg:address":"3-7 Church Street",
    "sg:city":"Southwell",
    "sg:classifiers":[
        {
            "category":"Shopping",
            "subcategory":"Antiques",
            "type":"Retail Goods"
        }
    ],
    "sg:phone":"+44 1636 815001",
    "sg:postcode":"NG25 0HQ",
    "sg:province":"Nottinghamshire",
    "wof:name":"Strouds of Southwell Antiques",
    "wof:placetype":"venue"
},
  "geometry": {"coordinates":[-0.954845,53.078011],"type":"Point"}
}