{
  "type": "Feature",
  "properties": {
    "addr:full":"17 Deptford Broadway London Greater London SE8 4PA",
    "addr:housenumber":"17",
    "addr:postcode":"se8 4pa",
    "addr:street":"Deptford Broadway",
    "iso:country":"GB",
    "sg:address":"17 Deptford Broadway",
    "sg:city":"London",
    "sg:classifiers":[
        {
            "category":"Communications",
            "subcategory":"Film & Video Production",
            "type":"Services"
        }
    ],
    "sg:phone":"+44 20 8691 1900",
    "sg:postcode":"SE8 4PA",
    "sg:province":"Greater London",
    "sg:tags":[
        "recording",
        "sound",
        "studio"
    ],
    "sg:website":"http://www.imthurricane.org",
    "wof:name":"Hurricane Studios Ltd",
    "wof:placetype":"venue"
},
  "geometry": {"coordinates":[-0.023464,51.474316],"type":"Point"}
}