{
  "type": "Feature",
  "properties": {
    "addr:full":"Finmere Rd Eastbourne East Sussex BN22 8QJ",
    "addr:postcode":"bn22 8qj",
    "addr:street":"Finmere Rd",
    "iso:country":"GB",
    "sg:address":"Finmere Rd",
    "sg:city":"Eastbourne",
    "sg:classifiers":[
        {
            "category":"Manufacturing",
            "subcategory":"Building Materials",
            "type":"Manufacturing & Wholesale Goods"
        }
    ],
    "sg:phone":"+44 1323 725121",
    "sg:postcode":"BN22 8QJ",
    "sg:province":"East Sussex",
    "sg:tags":[
        "merchant",
        "builder"
    ],
    "wof:name":"Hall & Co.Ltd",
    "wof:placetype":"venue"
},
  "geometry": {"coordinates":[0.302157,50.784569],"type":"Point"}
}