{
  "type": "Feature",
  "properties": {
    "addr:full":"Whithorn School, Castlehill, Whithorn Newton Stewart Dumfries and Galloway DG8 8PN",
    "addr:postcode":"dg8 8pn",
    "addr:street":"Castlehill;Newton Stewart",
    "iso:country":"GB",
    "sg:address":"Whithorn School, Castlehill, Whithorn",
    "sg:city":"Newton Stewart",
    "sg:classifiers":[
        {
            "category":"Government",
            "subcategory":"Office",
            "type":"Public Place"
        }
    ],
    "sg:phone":"+44 1988 500364",
    "sg:postcode":"DG8 8PN",
    "sg:province":"Dumfries and Galloway",
    "sg:tags":[
        "local"
    ],
    "wof:name":"South Machars Community Centre",
    "wof:placetype":"venue"
},
  "geometry": {"coordinates":[-4.415584,54.733227],"type":"Point"}
}