{
  "type": "Feature",
  "properties": {
    "iso:country":"GB",
    "sg:address":"58-60 High Street, Earls Barton",
    "sg:city":"Northampton",
    "sg:classifiers":[
        {
            "category":"Building & Trades",
            "subcategory":"Construction",
            "type":"Services"
        }
    ],
    "sg:postcode":"NN6 0JG",
    "sg:province":"Northamptonshire",
    "sg:tags":[
        "builder"
    ],
    "wof:name":"H A Cox & Sons Ltd",
    "wof:placetype":"venue"
},
  "geometry": {"coordinates":[-0.7507429719,52.2666320801],"type":"Point"}
}