{
  "type": "Feature",
  "properties": {
    "iso:country":"GB",
    "sg:address":"Grangewood Farm Estate, Walton",
    "sg:city":"Chesterfield",
    "sg:classifiers":[
        {
            "category":"Health Services",
            "subcategory":"Nursing And Care Facility",
            "type":"Services"
        }
    ],
    "sg:phone":"+44 1246 200140",
    "sg:postcode":"S40 2UN",
    "sg:province":"Derbyshire",
    "sg:tags":[
        "home"
    ],
    "wof:name":"Fisher Close Nursing Home",
    "wof:placetype":"venue"
},
  "geometry": {"coordinates":[-1.4395200014,53.2193908691],"type":"Point"}
}