{
  "type": "Feature",
  "properties": {
    "iso:country":"GB",
    "sg:address":"320 London Road",
    "sg:city":"Leicester",
    "sg:classifiers":[
        {
            "category":"Education",
            "subcategory":"School",
            "type":"Public Place"
        }
    ],
    "sg:phone":"+44 116 270 5343",
    "sg:postcode":"LE2 2PJ",
    "sg:province":"Leicestershire",
    "sg:tags":[
        "independent",
        "preparatory"
    ],
    "wof:name":"The Leicester Islamic Academy",
    "wof:placetype":"venue"
},
  "geometry": {"coordinates":[-1.110161,52.61895],"type":"Point"}
}