{
  "type": "Feature",
  "properties": {
    "addr:full":"The Green, Wickham St Paul Halstead Essex CO9 2PT",
    "addr:postcode":"co9 2pt",
    "addr:street":"Green Wickham",
    "iso:country":"GB",
    "sg:address":"The Green, Wickham St Paul",
    "sg:city":"Halstead",
    "sg:classifiers":[
        {
            "category":"Bars & Pubs",
            "type":"Food & Drink"
        }
    ],
    "sg:postcode":"CO9 2PT",
    "sg:province":"Essex",
    "sg:tags":[
        "pubs",
        "inn"
    ],
    "wof:name":"Victory Inn & Wickhamship Restaurant (The)",
    "wof:placetype":"venue"
},
  "geometry": {"coordinates":[0.635825,51.943996],"type":"Point"}
}