{
  "type": "Feature",
  "properties": {
    "addr:full":"39 Lichfield Rd Birmingham West Midlands B6 5RW",
    "addr:housenumber":"39",
    "addr:postcode":"b6 5rw",
    "addr:street":"Lichfield Rd",
    "iso:country":"GB",
    "sg:address":"39 Lichfield Rd",
    "sg:city":"Birmingham",
    "sg:classifiers":[
        {
            "category":"Professional",
            "subcategory":"Engineering",
            "type":"Services"
        }
    ],
    "sg:phone":"+44 121 328 5454",
    "sg:postcode":"B6 5RW",
    "sg:province":"West Midlands",
    "sg:tags":[
        "engineer"
    ],
    "wof:name":"Gordon Richards",
    "wof:placetype":"venue"
},
  "geometry": {"coordinates":[-1.88161695,52.4994506836],"type":"Point"}
}