{
  "type": "Feature",
  "properties": {
    "iso:country":"GB",
    "sg:address":"Unit 39 Marchington Industrial Estate, Marchington",
    "sg:city":"Uttoxeter",
    "sg:classifiers":[
        {
            "category":"Autos & Motor Vehicles",
            "subcategory":"Auto Supplies",
            "type":"Retail Goods"
        },
        {
            "category":"Retail",
            "subcategory":"Auto Repair",
            "type":"Services"
        }
    ],
    "sg:phone":"+44 1283 820144",
    "sg:postcode":"ST14 8LP",
    "sg:province":"Derbyshire",
    "sg:tags":[
        "rubber",
        "car",
        "specialist",
        "tyre",
        "customizing"
    ],
    "wof:name":"Xpress (Staffordshire) Ltd.",
    "wof:placetype":"venue"
},
  "geometry": {"coordinates":[-1.8012640476,52.8653068542],"type":"Point"}
}