{
  "type": "Feature",
  "properties": {
    "addr:full":"P O Box 11 Wirral Merseyside CH46 0XA",
    "addr:housenumber":"box 11",
    "addr:postcode":"ch46 0xa",
    "addr:street":"P O",
    "iso:country":"GB",
    "sg:address":"P O Box 11",
    "sg:city":"Wirral",
    "sg:classifiers":[
        {
            "category":"Autos & Motor Vehicles",
            "subcategory":"Motorcycle Sales",
            "type":"Retail Goods"
        }
    ],
    "sg:phone":"+44 151 678 0099",
    "sg:postcode":"CH46 0XA",
    "sg:province":"Merseyside",
    "sg:tags":[
        "chauffeur",
        "driven",
        "car"
    ],
    "wof:name":"Airport International Network",
    "wof:placetype":"venue"
},
  "geometry": {"coordinates":[-3.1119799614,53.4003982544],"type":"Point"}
}