{
  "type": "Feature",
  "properties": {
    "addr:full":"37 Bridge Street Evesham Gloucestershire WR11 4SQ",
    "addr:housenumber":"37",
    "addr:postcode":"wr11 4sq",
    "addr:street":"Bridge Street",
    "iso:country":"GB",
    "sg:address":"37 Bridge Street",
    "sg:city":"Evesham",
    "sg:classifiers":[
        {
            "category":"Shopping",
            "subcategory":"Gifts & Souvenirs",
            "type":"Retail Goods"
        }
    ],
    "sg:phone":"+44 1386 443338",
    "sg:postcode":"WR11 4SQ",
    "sg:province":"Gloucestershire",
    "sg:tags":[
        "poster",
        "card"
    ],
    "wof:name":"Papermoon",
    "wof:placetype":"venue"
},
  "geometry": {"coordinates":[-1.945465,52.092247],"type":"Point"}
}