{
  "type": "Feature",
  "properties": {
    "addr:full":"9-10 Domingo St London Greater London EC1Y 0TA",
    "addr:housenumber":"9-10",
    "addr:postcode":"ec1y 0ta",
    "addr:street":"Domingo St",
    "iso:country":"GB",
    "sg:address":"9-10 Domingo St",
    "sg:city":"London",
    "sg:classifiers":[
        {
            "category":"Utilities",
            "type":"Services"
        }
    ],
    "sg:postcode":"EC1Y 0TA",
    "sg:province":"Greater London",
    "sg:tags":[
        "internet"
    ],
    "wof:name":"Ardeo Plc",
    "wof:placetype":"venue"
},
  "geometry": {"coordinates":[-0.0966579989,51.5238494873],"type":"Point"}
}