{
  "type": "Feature",
  "properties": {
    "addr:full":"180 Strand London Greater London WC2R 2NN",
    "addr:housenumber":"180",
    "addr:postcode":"wc2r 2nn",
    "addr:street":"Strand",
    "iso:country":"GB",
    "sg:address":"180 Strand",
    "sg:city":"London",
    "sg:classifiers":[
        {
            "category":"Banks & Credit Unions",
            "subcategory":"Investment Brokerage",
            "type":"Services"
        }
    ],
    "sg:phone":"+44 20 7438 2260",
    "sg:postcode":"WC2R 2NN",
    "sg:province":"Greater London",
    "sg:tags":[
        "stockbroker"
    ],
    "wof:name":"Quick & Reilly Ltd",
    "wof:placetype":"venue"
},
  "geometry": {"coordinates":[-0.1151449978,51.5126190186],"type":"Point"}
}