{
  "type": "Feature",
  "properties": {
    "addr:full":"The Parsonage, High St Rochester Kent ME3 0BS",
    "addr:postcode":"me3 0bs",
    "addr:street":"High St",
    "iso:country":"GB",
    "sg:address":"The Parsonage, High St",
    "sg:city":"Rochester",
    "sg:classifiers":[
        {
            "category":"Place Of Worship",
            "type":"Public Place"
        }
    ],
    "sg:phone":"+44 1634 270263",
    "sg:postcode":"ME3 0BS",
    "sg:province":"Kent",
    "wof:name":"St Peter & St Paul Upper Stoke",
    "wof:placetype":"venue"
},
  "geometry": {"coordinates":[0.7171199918,51.4581985474],"type":"Point"}
}