{
  "type": "Feature",
  "properties": {
    "addr:full":"257a Penhill Drive Swindon Wiltshire SN2 5HN",
    "addr:housenumber":"257a",
    "addr:postcode":"sn2 5hn",
    "addr:street":"Penhill Drive",
    "iso:country":"GB",
    "sg:address":"257a Penhill Drive",
    "sg:city":"Swindon",
    "sg:classifiers":[
        {
            "category":"Shopping",
            "subcategory":"Pharmacy",
            "type":"Retail Goods"
        }
    ],
    "sg:phone":"+44 1793 723534",
    "sg:postcode":"SN2 5HN",
    "sg:province":"Wiltshire",
    "sg:tags":[
        "pharmacist",
        "chemist"
    ],
    "wof:name":"D W & H C Taylor",
    "wof:placetype":"venue"
},
  "geometry": {"coordinates":[-1.780782,51.595554],"type":"Point"}
}