{
  "type": "Feature",
  "properties": {
    "iso:country":"GB",
    "sg:address":"Building 22 Bay 9 First Avenue, Pensnett Trading Estate, Kingswinford",
    "sg:city":"Brierley Hill",
    "sg:classifiers":[
        {
            "category":"Retail",
            "subcategory":"Auto Repair",
            "type":"Services"
        }
    ],
    "sg:phone":"+44 1384 294808",
    "sg:postcode":"DY6 7PP",
    "sg:province":"Staffordshire",
    "sg:tags":[
        "modification",
        "garage"
    ],
    "wof:name":"Martin & Griffiths Automobile Engineers",
    "wof:placetype":"venue"
},
  "geometry": {"coordinates":[-2.144964,52.509171],"type":"Point"}
}