{
  "type": "Feature",
  "properties": {
    "iso:country":"GB",
    "sg:address":"54 Cannock Street",
    "sg:city":"Leicester",
    "sg:classifiers":[
        {
            "category":"Shopping",
            "subcategory":"Clothing, Apparel, & Fashions",
            "type":"Retail Goods"
        }
    ],
    "sg:phone":"+44 116 276 5656",
    "sg:postcode":"LE4 9HR",
    "sg:province":"Leicestershire",
    "sg:tags":[
        "clothing",
        "fabric"
    ],
    "wof:name":"Aristo Fabrics Ltd.",
    "wof:placetype":"venue"
},
  "geometry": {"coordinates":[-1.0799930096,52.6631507874],"type":"Point"}
}