{
  "type": "Feature",
  "properties": {
    "iso:country":"GB",
    "sg:address":"50 High St",
    "sg:city":"Stroud",
    "sg:classifiers":[
        {
            "category":"Transit Center",
            "subcategory":"Freight",
            "type":"Transportation"
        }
    ],
    "sg:phone":"+44 1453 752439",
    "sg:postcode":"GL5 1AN",
    "sg:province":"Gloucestershire",
    "sg:tags":[
        "shop",
        "craft",
        "centre"
    ],
    "wof:name":"Warehouse The",
    "wof:placetype":"venue"
},
  "geometry": {"coordinates":[-2.215434,51.745182],"type":"Point"}
}