{
  "type": "Feature",
  "properties": {
    "addr:full":"Ashton Green Drive St. Helens Cheshire WA9 2AP",
    "addr:postcode":"wa9 2ap",
    "addr:street":"Ashton Green Drive",
    "iso:country":"GB",
    "sg:address":"Ashton Green Drive",
    "sg:city":"St. Helens",
    "sg:classifiers":[
        {
            "category":"Professional",
            "subcategory":"Lawyer & Legal Services",
            "type":"Services"
        }
    ],
    "sg:phone":"+44 1744 614609",
    "sg:postcode":"WA9 2AP",
    "sg:province":"Cheshire",
    "sg:tags":[
        "advice",
        "counselling"
    ],
    "wof:name":"St. Helens Mediation & Neighbour Dispute Service",
    "wof:placetype":"venue"
},
  "geometry": {"coordinates":[-2.698179,53.448456],"type":"Point"}
}