{
  "type": "Feature",
  "properties": {
    "addr:full":"Annablleyn At House, 9-13 Ewell Road Sutton Surrey SM3 8BZ",
    "addr:housenumber":"9-13",
    "addr:postcode":"sm3 8bz",
    "addr:street":"Ewell Road",
    "iso:country":"GB",
    "sg:address":"Annablleyn At House, 9-13 Ewell Road",
    "sg:city":"Sutton",
    "sg:classifiers":[
        {
            "category":"Real Estate",
            "subcategory":"Real Estate Agent",
            "type":"Services"
        }
    ],
    "sg:phone":"+44 20 8722 5800",
    "sg:postcode":"SM3 8BZ",
    "sg:province":"Surrey",
    "wof:name":"Countrywide Residential Lettings Ltd.",
    "wof:placetype":"venue"
},
  "geometry": {"coordinates":[-0.216932,51.357552],"type":"Point"}
}