{
  "type": "Feature",
  "properties": {
    "addr:full":"Longfield Dartford Kent DA3 8PE",
    "addr:postcode":"da3 8pe",
    "iso:country":"GB",
    "sg:address":"Longfield",
    "sg:city":"Dartford",
    "sg:classifiers":[
        {
            "category":"Restaurant",
            "type":"Food & Drink"
        }
    ],
    "sg:phone":"+44 1474 854900",
    "sg:postcode":"DA3 8PE",
    "sg:province":"Kent",
    "wof:name":"The Brandshatch Thistle Hotel",
    "wof:placetype":"venue"
},
  "geometry": {"coordinates":[0.2534799874,51.3588409424],"type":"Point"}
}