{
  "type": "Feature",
  "properties": {
    "addr:full":"Nether Mains Court, Echt Westhill Aberdeen City AB32 6UL",
    "addr:postcode":"ab32 6ul",
    "addr:street":"Nether Mains Court",
    "iso:country":"GB",
    "sg:address":"Nether Mains Court, Echt",
    "sg:city":"Westhill",
    "sg:classifiers":[
        {
            "category":"Social Services",
            "subcategory":"Adult Care",
            "type":"Services"
        },
        {
            "category":"Social Services",
            "subcategory":"Retirement Home",
            "type":"Services"
        }
    ],
    "sg:phone":"+44 1330 860464",
    "sg:postcode":"AB32 6UL",
    "sg:province":"Aberdeen City",
    "sg:tags":[
        "housing",
        "sheltered",
        "accommodation"
    ],
    "wof:name":"Castlehill Housing Association",
    "wof:placetype":"venue"
},
  "geometry": {"coordinates":[-2.292684,57.149445],"type":"Point"}
}