{
  "type": "Feature",
  "properties": {
    "iso:country":"GB",
    "sg:address":"Pitt Farm, Pinnar Lane, Southowram",
    "sg:city":"Halifax",
    "sg:classifiers":[
        {
            "category":"Food & Beverages",
            "subcategory":"Farmers Market",
            "type":"Retail Goods"
        }
    ],
    "sg:phone":"+44 1422 365691",
    "sg:postcode":"HX3 9QT",
    "sg:province":"West Yorkshire",
    "sg:tags":[
        "gardener"
    ],
    "wof:name":"Kitson Bros",
    "wof:placetype":"venue"
},
  "geometry": {"coordinates":[-1.8323550224,53.7071533203],"type":"Point"}
}