{
  "type": "Feature",
  "properties": {
    "addr:full":"Brightwell Street, Brightwell-cum-sotwestreet Wallingford Oxfordshire OX10 0RX",
    "addr:postcode":"ox10 0rx",
    "addr:street":"Brightwell Street Brightwell-Cum-Sotwestreet",
    "iso:country":"GB",
    "sg:address":"Brightwell Street, Brightwell-cum-sotwestreet",
    "sg:city":"Wallingford",
    "sg:classifiers":[
        {
            "category":"Retail",
            "subcategory":"Auto Repair",
            "type":"Services"
        }
    ],
    "sg:postcode":"OX10 0RX",
    "sg:province":"Oxfordshire",
    "sg:tags":[
        "modification",
        "garage"
    ],
    "wof:name":"Brightwell Garage",
    "wof:placetype":"venue"
},
  "geometry": {"coordinates":[-1.1653089523,51.6134262085],"type":"Point"}
}