{
  "type": "Feature",
  "properties": {
    "addr:full":"Unit 4, Caxton Place Stevenage Hertfordshire SG1 2UF",
    "addr:housenumber":"unit 4",
    "addr:postcode":"sg1 2uf",
    "addr:street":"Caxton Place",
    "iso:country":"GB",
    "sg:address":"Unit 4, Caxton Place",
    "sg:city":"Stevenage",
    "sg:classifiers":[
        {
            "category":"Shopping",
            "subcategory":"Computers & Home Electronics",
            "type":"Retail Goods"
        }
    ],
    "sg:postcode":"SG1 2UF",
    "sg:province":"Hertfordshire",
    "wof:name":"Saxon Technology Ltd.",
    "wof:placetype":"venue"
},
  "geometry": {"coordinates":[-0.215549,51.899029],"type":"Point"}
}