{
  "type": "Feature",
  "properties": {
    "iso:country":"GB",
    "sg:address":"19 Bourg De Peage Av",
    "sg:city":"East Grinstead",
    "sg:classifiers":[
        {
            "category":"Place Of Worship",
            "type":"Public Place"
        }
    ],
    "sg:phone":"+44 1342 314605",
    "sg:postcode":"RH19 3YD",
    "sg:province":"East Sussex",
    "wof:name":"United Reformed Church",
    "wof:placetype":"venue"
},
  "geometry": {"coordinates":[0.000792,51.127048],"type":"Point"}
}