{
  "type": "Feature",
  "properties": {
    "iso:country":"GB",
    "sg:address":"51 Westmead",
    "sg:city":"Windsor",
    "sg:classifiers":[
        {
            "category":"Military Area",
            "subcategory":"Air Force Base",
            "type":"Public Place"
        }
    ],
    "sg:postcode":"SL4 3NN",
    "sg:province":"Berkshire",
    "sg:tags":[
        "taxi",
        "hire",
        "private"
    ],
    "wof:name":"P J Nash",
    "wof:placetype":"venue"
},
  "geometry": {"coordinates":[-0.624169,51.473896],"type":"Point"}
}