{
  "type": "Feature",
  "properties": {
    "iso:country":"GB",
    "sg:address":"Eaton Lodge Dental Surgery, 2 Bath St",
    "sg:city":"Rhyl",
    "sg:classifiers":[
        {
            "category":"Health Services",
            "subcategory":"Dentist",
            "type":"Services"
        }
    ],
    "sg:postcode":"LL18 3EB",
    "sg:province":"Conwy",
    "wof:name":"Nuttall,B J,",
    "wof:placetype":"venue"
},
  "geometry": {"coordinates":[-3.472384,53.311581],"type":"Point"}
}