{
  "type": "Feature",
  "properties": {
    "iso:country":"GB",
    "sg:address":"3 Overelord Close, Shefford",
    "sg:city":"Shefford",
    "sg:classifiers":[
        {
            "category":"Real Estate",
            "subcategory":"Architect",
            "type":"Services"
        }
    ],
    "sg:phone":"+44 1462 711576",
    "sg:postcode":"SG17 5UT",
    "sg:province":"Bedfordshire",
    "sg:tags":[
        "technologist",
        "architectural"
    ],
    "wof:name":"Parkside Building Design",
    "wof:placetype":"venue"
},
  "geometry": {"coordinates":[-0.333909,52.036221],"type":"Point"}
}