{
  "type": "Feature",
  "properties": {
    "iso:country":"GB",
    "sg:address":"5 Cherry Cross, Totnes Down Hill",
    "sg:city":"Totnes",
    "sg:classifiers":[
        {
            "category":"Wholesale",
            "subcategory":"Books, Periodicals, & Newspapers",
            "type":"Manufacturing & Wholesale Goods"
        }
    ],
    "sg:postcode":"TQ9 5EU",
    "sg:province":"Devon",
    "sg:tags":[
        "publishing"
    ],
    "wof:name":"Vantage Books",
    "wof:placetype":"venue"
},
  "geometry": {"coordinates":[-3.685194,50.426929],"type":"Point"}
}