{
  "type": "Feature",
  "properties": {
    "addr:full":"74 Taylor Road, Haydock St Helens Lancashire WA11 9YG",
    "addr:housenumber":"74",
    "addr:postcode":"wa11 9yg",
    "addr:street":"Taylor Road Haydock",
    "iso:country":"GB",
    "sg:address":"74 Taylor Road, Haydock",
    "sg:city":"St Helens",
    "sg:classifiers":[
        {
            "category":"Building & Trades",
            "subcategory":"Construction",
            "type":"Services"
        }
    ],
    "sg:phone":"+44 1942 726360",
    "sg:postcode":"WA11 9YG",
    "sg:province":"Lancashire",
    "sg:tags":[
        "supplier",
        "installers",
        "cladding"
    ],
    "wof:name":"U P V C Excell",
    "wof:placetype":"venue"
},
  "geometry": {"coordinates":[-2.6515219212,53.469619751],"type":"Point"}
}