{
  "type": "Feature",
  "properties": {
    "addr:full":"39 Burnley Road East Rossendale Lancashire BB4 9AG",
    "addr:housenumber":"39",
    "addr:postcode":"bb4 9ag",
    "addr:street":"Burnley Road East",
    "iso:country":"GB",
    "sg:address":"39 Burnley Road East",
    "sg:city":"Rossendale",
    "sg:classifiers":[
        {
            "category":"Personal",
            "subcategory":"Barber",
            "type":"Services"
        }
    ],
    "sg:phone":"+44 1706 222393",
    "sg:postcode":"BB4 9AG",
    "sg:province":"Lancashire",
    "sg:tags":[
        "unisex",
        "men's",
        "hairdresser"
    ],
    "wof:name":"Muz's Barbers Shop",
    "wof:placetype":"venue"
},
  "geometry": {"coordinates":[-2.2526860237,53.6938438416],"type":"Point"}
}