{
  "type": "Feature",
  "properties": {
    "addr:full":"46 Woodside Rd Huddersfield West Yorkshire HD4 5JR",
    "addr:housenumber":"46",
    "addr:postcode":"hd4 5jr",
    "addr:street":"Woodside Rd",
    "iso:country":"GB",
    "sg:address":"46 Woodside Rd",
    "sg:city":"Huddersfield",
    "sg:classifiers":[
        {
            "category":"Professional",
            "subcategory":"Management & Consulting",
            "type":"Services"
        }
    ],
    "sg:phone":"+44 1484 518437",
    "sg:postcode":"HD4 5JR",
    "sg:province":"West Yorkshire",
    "sg:tags":[
        "consultant",
        "business"
    ],
    "wof:name":"K J Astill",
    "wof:placetype":"venue"
},
  "geometry": {"coordinates":[-1.8055380583,53.6295852661],"type":"Point"}
}