{
  "type": "Feature",
  "properties": {
    "iso:country":"GB",
    "sg:address":"Firth Lodge",
    "sg:city":"Roslin",
    "sg:classifiers":[
        {
            "category":"Shopping",
            "subcategory":"Pharmacy",
            "type":"Retail Goods"
        }
    ],
    "sg:phone":"+44 1968 678789",
    "sg:postcode":"EH25 9QJ",
    "sg:province":"Midlothian",
    "sg:tags":[
        "medicine",
        "therapy"
    ],
    "wof:name":"Good Health for All",
    "wof:placetype":"venue"
},
  "geometry": {"coordinates":[-3.166119,55.858326],"type":"Point"}
}