{
  "type": "Feature",
  "properties": {
    "addr:full":"Ecclesfield Sheffield South Yorkshire S35 9WD",
    "addr:postcode":"s35 9wd",
    "iso:country":"GB",
    "sg:address":"Ecclesfield",
    "sg:city":"Sheffield",
    "sg:classifiers":[
        {
            "category":"Education",
            "subcategory":"School",
            "type":"Public Place"
        },
        {
            "category":"Government",
            "subcategory":"Office",
            "type":"Public Place"
        }
    ],
    "sg:phone":"+44 114 246 1156",
    "sg:postcode":"S35 9WD",
    "sg:province":"South Yorkshire",
    "sg:tags":[
        "local",
        "authority"
    ],
    "wof:name":"Ecclesfield Comprehensive School",
    "wof:placetype":"venue"
},
  "geometry": {"coordinates":[-1.4657599926,53.4476394653],"type":"Point"}
}