{
  "type": "Feature",
  "properties": {
    "iso:country":"GB",
    "sg:address":"Spook Hill",
    "sg:city":"Dorking",
    "sg:classifiers":[
        {
            "category":"Social Services",
            "subcategory":"Retirement Home",
            "type":"Services"
        }
    ],
    "sg:phone":"+44 1306 876567",
    "sg:postcode":"RH5 4EG",
    "sg:province":"Surrey",
    "sg:tags":[
        "rest"
    ],
    "wof:name":"Stanecroft",
    "wof:placetype":"venue"
},
  "geometry": {"coordinates":[-0.328279,51.21476],"type":"Point"}
}