{
  "type": "Feature",
  "properties": {
    "addr:full":"5 Charnwood Walk Leicester Leicestershire LE5 3FN",
    "addr:housenumber":"5",
    "addr:postcode":"le5 3fn",
    "addr:street":"Charnwood Walk",
    "iso:country":"GB",
    "sg:address":"5 Charnwood Walk",
    "sg:city":"Leicester",
    "sg:classifiers":[
        {
            "category":"Community Center",
            "type":"Public Place"
        }
    ],
    "sg:phone":"+44 116 253 6398",
    "sg:postcode":"LE5 3FN",
    "sg:province":"Leicestershire",
    "sg:tags":[
        "centre"
    ],
    "wof:name":"Charnwood Tenants Association",
    "wof:placetype":"venue"
},
  "geometry": {"coordinates":[-1.1090669632,52.6401405334],"type":"Point"}
}