{
  "type": "Feature",
  "properties": {
    "addr:full":"Burr Lane, Shalbourne Marlborough Berkshire SN8 3PT",
    "addr:postcode":"sn8 3pt",
    "addr:street":"Burr Lane",
    "iso:country":"GB",
    "sg:address":"Burr Lane, Shalbourne",
    "sg:city":"Marlborough",
    "sg:classifiers":[
        {
            "category":"Bars & Pubs",
            "type":"Food & Drink"
        }
    ],
    "sg:postcode":"SN8 3PT",
    "sg:province":"Berkshire",
    "sg:tags":[
        "pubs",
        "inn"
    ],
    "wof:name":"Plough Inn",
    "wof:placetype":"venue"
},
  "geometry": {"coordinates":[-1.5514960289,51.3636131287],"type":"Point"}
}