{
  "type": "Feature",
  "properties": {
    "addr:full":"9 The Courtyard, Roman Way Birmingham Warwickshire B46 1HQ",
    "addr:housenumber":"9",
    "addr:postcode":"b46 1hq",
    "addr:street":"The Courtyard Roman Way",
    "iso:country":"GB",
    "sg:address":"9 The Courtyard, Roman Way",
    "sg:city":"Birmingham",
    "sg:classifiers":[
        {
            "category":"Building & Trades",
            "subcategory":"Construction",
            "type":"Services"
        }
    ],
    "sg:phone":"+44 1675 467666",
    "sg:postcode":"B46 1HQ",
    "sg:province":"Warwickshire",
    "sg:tags":[
        "builder"
    ],
    "wof:name":"Dixon Housing Midlands",
    "wof:placetype":"venue"
},
  "geometry": {"coordinates":[-1.712078,52.514328],"type":"Point"}
}