{
  "type": "Feature",
  "properties": {
    "iso:country":"GB",
    "sg:address":"Shopping Centre, Glenloy Street, Caol",
    "sg:city":"Fort William",
    "sg:classifiers":[
        {
            "category":"Organizations",
            "subcategory":"Non-profit Organization",
            "type":"Services"
        }
    ],
    "sg:phone":"+44 1397 702340",
    "sg:postcode":"PH33 7DR",
    "sg:province":"Highland",
    "sg:tags":[
        "charitable",
        "organisation",
        "voluntary",
        "charity"
    ],
    "sg:website":"http://www.lad.org.uk",
    "wof:name":"Loch Aber Council on Alcohol",
    "wof:placetype":"venue"
},
  "geometry": {"coordinates":[-5.102344,56.838356],"type":"Point"}
}