{
  "type": "Feature",
  "properties": {
    "iso:country":"GB",
    "sg:address":"Apple Dorne, Allimore Green, Haughton",
    "sg:city":"Stafford",
    "sg:classifiers":[
        {
            "category":"Arts & Performance",
            "subcategory":"Theater",
            "type":"Entertainment"
        }
    ],
    "sg:phone":"+44 1785 824824",
    "sg:postcode":"ST18 9JQ",
    "sg:province":"Staffordshire",
    "sg:tags":[
        "theatrical",
        "agency"
    ],
    "wof:name":"M J Enterprises",
    "wof:placetype":"venue"
},
  "geometry": {"coordinates":[-2.198554,52.780666],"type":"Point"}
}