{
  "type": "Feature",
  "properties": {
    "iso:country":"GB",
    "sg:address":"35 Blackness Road",
    "sg:city":"Linlithgow",
    "sg:classifiers":[
        {
            "category":"Organizations",
            "subcategory":"Community Association",
            "type":"Services"
        }
    ],
    "sg:phone":"+44 1506 671384",
    "sg:postcode":"EH49 7JD",
    "sg:province":"Falkirk",
    "sg:tags":[
        "co-operatives",
        "society",
        "housing",
        "trust"
    ],
    "sg:website":"http://www.arkha.org.uk",
    "wof:name":"Ark Housing Association Ltd",
    "wof:placetype":"venue"
},
  "geometry": {"coordinates":[-3.594302,55.978748],"type":"Point"}
}