{
  "type": "Feature",
  "properties": {
    "addr:full":"2a Little Market Row, Leybourne West Malling Kent ME19 5QL",
    "addr:housenumber":"2a",
    "addr:postcode":"me19 5ql",
    "addr:street":"Little Market Row",
    "iso:country":"GB",
    "sg:address":"2a Little Market Row, Leybourne",
    "sg:city":"West Malling",
    "sg:classifiers":[
        {
            "category":"Professional",
            "subcategory":"Accounting & Tax Preparation",
            "type":"Services"
        }
    ],
    "sg:phone":"+44 1732 871671",
    "sg:postcode":"ME19 5QL",
    "sg:province":"Kent",
    "sg:tags":[
        "accountant"
    ],
    "wof:name":"Marriotts",
    "wof:placetype":"venue"
},
  "geometry": {"coordinates":[0.424767,51.301521],"type":"Point"}
}