{
  "type": "Feature",
  "properties": {
    "addr:full":"Bank End Quarry, Bank End, Bank End Road Doncaster Lincolnshire DN9 3AN",
    "addr:postcode":"dn9 3an",
    "addr:street":"Quarry Bank End Bank End Road",
    "iso:country":"GB",
    "sg:address":"Bank End Quarry, Bank End, Bank End Road",
    "sg:city":"Doncaster",
    "sg:classifiers":[
        {
            "category":"Manufacturing",
            "subcategory":"Glass & Minerals",
            "type":"Manufacturing & Wholesale Goods"
        }
    ],
    "sg:phone":"+44 1302 772596",
    "sg:postcode":"DN9 3AN",
    "sg:province":"Lincolnshire",
    "sg:tags":[
        "chalk",
        "stone",
        "slate"
    ],
    "wof:name":"Fernwood Aggregates",
    "wof:placetype":"venue"
},
  "geometry": {"coordinates":[-0.9872620106,53.4959373474],"type":"Point"}
}