{
  "type": "Feature",
  "properties": {
    "iso:country":"GB",
    "sg:address":"16b Wakefield Road, Ackworth",
    "sg:city":"Pontefract",
    "sg:classifiers":[
        {
            "category":"Building & Trades",
            "subcategory":"Construction",
            "type":"Services"
        }
    ],
    "sg:phone":"+44 1977 614062",
    "sg:postcode":"WF7 7DE",
    "sg:province":"West Yorkshire",
    "sg:tags":[
        "joinery",
        "joiner",
        "carpenter",
        "carpentry"
    ],
    "wof:name":"Stephen D Booth",
    "wof:placetype":"venue"
},
  "geometry": {"coordinates":[-1.34279,53.640743],"type":"Point"}
}