{
  "type": "Feature",
  "properties": {
    "addr:full":"134 Havering Road Romford Essex RM1 4RD",
    "addr:housenumber":"134",
    "addr:postcode":"rm1 4rd",
    "addr:street":"Havering Road",
    "iso:country":"GB",
    "sg:address":"134 Havering Road",
    "sg:city":"Romford",
    "sg:classifiers":[
        {
            "category":"Building & Trades",
            "subcategory":"Plumbing",
            "type":"Services"
        }
    ],
    "sg:postcode":"RM1 4RD",
    "sg:province":"Essex",
    "sg:tags":[
        "heating"
    ],
    "wof:name":"S Hogger",
    "wof:placetype":"venue"
},
  "geometry": {"coordinates":[0.173883,51.591942],"type":"Point"}
}