{
  "type": "Feature",
  "properties": {
    "iso:country":"GB",
    "sg:address":"Divisional Secretary, 15 Ensign Court, The Marina",
    "sg:city":"Hartlepool",
    "sg:classifiers":[
        {
            "category":"Education",
            "subcategory":"Special Training",
            "type":"Public Place"
        }
    ],
    "sg:phone":"+44 1429 863351",
    "sg:postcode":"TS24 0XJ",
    "sg:province":"Durham",
    "sg:tags":[
        "aid",
        "first"
    ],
    "wof:name":"St.John Ambulance",
    "wof:placetype":"venue"
},
  "geometry": {"coordinates":[-1.214119,54.685406],"type":"Point"}
}