{
  "type": "Feature",
  "properties": {
    "addr:full":"Mansfield Road, Clipstone Village Mansfield Nottinghamshire NG21 9AB",
    "addr:postcode":"ng21 9ab",
    "addr:street":"Mansfield Road",
    "iso:country":"GB",
    "sg:address":"Mansfield Road, Clipstone Village",
    "sg:city":"Mansfield",
    "sg:classifiers":[
        {
            "category":"Bars & Pubs",
            "type":"Food & Drink"
        }
    ],
    "sg:phone":"+44 1623 423392",
    "sg:postcode":"NG21 9AB",
    "sg:province":"Nottinghamshire",
    "sg:tags":[
        "pubs",
        "inn"
    ],
    "wof:name":"Squinting Cat",
    "wof:placetype":"venue"
},
  "geometry": {"coordinates":[-1.1242940426,53.1602935791],"type":"Point"}
}