{
  "type": "Feature",
  "properties": {
    "addr:full":"307-309 High Street Slough Berkshire SL1 1BD",
    "addr:housenumber":"307-309",
    "addr:postcode":"sl1 1bd",
    "addr:street":"High Street",
    "iso:country":"GB",
    "sg:address":"307-309 High Street",
    "sg:city":"Slough",
    "sg:classifiers":[
        {
            "category":"Retail",
            "subcategory":"Laundry & Dry Cleaning",
            "type":"Services"
        }
    ],
    "sg:phone":"+44 1753 523452",
    "sg:postcode":"SL1 1BD",
    "sg:province":"Berkshire",
    "sg:tags":[
        "alteration"
    ],
    "wof:name":"Top Tone Cleaners Ltd.",
    "wof:placetype":"venue"
},
  "geometry": {"coordinates":[-0.5859540105,51.5074958801],"type":"Point"}
}