{
  "type": "Feature",
  "properties": {
    "addr:full":"The Point, 16 South Pde Doncaster South Yorkshire DN1 2DR",
    "addr:housenumber":"16",
    "addr:postcode":"dn1 2dr",
    "addr:street":"South Pde",
    "iso:country":"GB",
    "sg:address":"The Point, 16 South Pde",
    "sg:city":"Doncaster",
    "sg:classifiers":[
        {
            "category":"Shopping",
            "subcategory":"Books",
            "type":"Retail Goods"
        }
    ],
    "sg:phone":"+44 1302 343868",
    "sg:postcode":"DN1 2DR",
    "sg:province":"South Yorkshire",
    "sg:tags":[
        "bookseller"
    ],
    "wof:name":"Exclamation Books",
    "wof:placetype":"venue"
},
  "geometry": {"coordinates":[-1.130565,53.524391],"type":"Point"}
}