{
  "type": "Feature",
  "properties": {
    "addr:full":"27 Thomas St Dungannon Cardiff CF23 9BA",
    "addr:housenumber":"27",
    "addr:postcode":"cf23 9ba",
    "addr:street":"Thomas St",
    "iso:country":"GB",
    "sg:address":"27 Thomas St",
    "sg:city":"Dungannon",
    "sg:classifiers":[
        {
            "category":"Home & Garden",
            "subcategory":"Hardware",
            "type":"Retail Goods"
        }
    ],
    "sg:phone":"+44 1850 322175",
    "sg:postcode":"CF23 9BA",
    "sg:province":"Cardiff",
    "sg:tags":[
        "paint",
        "coating"
    ],
    "wof:name":"Ashton Agencies Ltd",
    "wof:placetype":"venue"
},
  "geometry": {"coordinates":[-3.149116,51.50742],"type":"Point"}
}