{
  "type": "Feature",
  "properties": {
    "iso:country":"GB",
    "sg:address":"181 Northdown Road, Cliftonville",
    "sg:city":"Margate",
    "sg:classifiers":[
        {
            "category":"Shopping",
            "subcategory":"Pharmacy",
            "type":"Retail Goods"
        }
    ],
    "sg:phone":"+44 1843 220690",
    "sg:postcode":"CT9 2PA",
    "sg:province":"Kent",
    "sg:tags":[
        "store",
        "drug"
    ],
    "wof:name":"Serena Supersave Stores",
    "wof:placetype":"venue"
},
  "geometry": {"coordinates":[1.398477,51.387653],"type":"Point"}
}