{
  "type": "Feature",
  "properties": {
    "addr:full":"17 Birdlip Close Waterlooville Hampshire PO8 9PW",
    "addr:housenumber":"17",
    "addr:postcode":"po8 9pw",
    "addr:street":"Birdlip Close",
    "iso:country":"GB",
    "sg:address":"17 Birdlip Close",
    "sg:city":"Waterlooville",
    "sg:classifiers":[
        {
            "category":"Bus Stop",
            "subcategory":"None",
            "type":"Transportation"
        }
    ],
    "sg:postcode":"PO8 9PW",
    "sg:province":"Hampshire",
    "sg:tags":[
        "filter"
    ],
    "wof:name":"C A E Trislot Nv",
    "wof:placetype":"venue"
},
  "geometry": {"coordinates":[-1.0151599646,50.9089164734],"type":"Point"}
}