{
  "type": "Feature",
  "properties": {
    "addr:full":"Main Street, Cliffton Campville Tamworth Staffordshire B79 0AP",
    "addr:postcode":"b79 0ap",
    "addr:street":"Main Street",
    "iso:country":"GB",
    "sg:address":"Main Street, Cliffton Campville",
    "sg:city":"Tamworth",
    "sg:classifiers":[
        {
            "category":"Shopping",
            "subcategory":"Department Store",
            "type":"Retail Goods"
        },
        {
            "category":"Home & Garden",
            "subcategory":"Garden Supply",
            "type":"Retail Goods"
        }
    ],
    "sg:phone":"+44 1827 373307",
    "sg:postcode":"B79 0AP",
    "sg:province":"Staffordshire",
    "sg:tags":[
        "nursery",
        "centre"
    ],
    "wof:name":"Jackson Nurseries",
    "wof:placetype":"venue"
},
  "geometry": {"coordinates":[-1.623845,52.696304],"type":"Point"}
}