{
  "type": "Feature",
  "properties": {
    "addr:full":"Barton Close, Cheriton Fitzpaine Crediton Devon EX17 4JB",
    "addr:postcode":"ex17 4jb",
    "addr:street":"Barton Close;Fitzpaine",
    "iso:country":"GB",
    "sg:address":"Barton Close, Cheriton Fitzpaine",
    "sg:city":"Crediton",
    "sg:classifiers":[
        {
            "category":"Health Services",
            "subcategory":"Doctor",
            "type":"Services"
        }
    ],
    "sg:phone":"+44 1363 866322",
    "sg:postcode":"EX17 4JB",
    "sg:province":"Devon",
    "sg:tags":[
        "practitioners"
    ],
    "wof:name":"R M Bull Surgery",
    "wof:placetype":"venue"
},
  "geometry": {"coordinates":[-3.6108210087,50.8441886902],"type":"Point"}
}