{
  "type": "Feature",
  "properties": {
    "iso:country":"GB",
    "sg:address":"Eagle Farm Road",
    "sg:city":"Biggleswade",
    "sg:classifiers":[
        {
            "category":"Education",
            "subcategory":"School",
            "type":"Public Place"
        }
    ],
    "sg:phone":"+44 1767 312745",
    "sg:postcode":"SG18 8JB",
    "sg:province":"Bedfordshire",
    "sg:tags":[
        "local",
        "authority"
    ],
    "wof:name":"Stratton Upper School",
    "wof:placetype":"venue"
},
  "geometry": {"coordinates":[-0.251023,52.085617],"type":"Point"}
}