{
  "type": "Feature",
  "properties": {
    "addr:full":"21 Auckland Avenue Brockenhurst Hampshire SO42 7RS",
    "addr:housenumber":"21",
    "addr:postcode":"so42 7rs",
    "addr:street":"Auckland Avenue",
    "iso:country":"GB",
    "sg:address":"21 Auckland Avenue",
    "sg:city":"Brockenhurst",
    "sg:classifiers":[
        {
            "category":"Building & Trades",
            "subcategory":"Landscaping Services",
            "type":"Services"
        }
    ],
    "sg:phone":"+44 1590 624034",
    "sg:postcode":"SO42 7RS",
    "sg:province":"Hampshire",
    "sg:tags":[
        "forestry",
        "surgeon",
        "tree"
    ],
    "wof:name":"Owen Parker",
    "wof:placetype":"venue"
},
  "geometry": {"coordinates":[-1.574991,50.818558],"type":"Point"}
}