{
  "type": "Feature",
  "properties": {
    "iso:country":"GB",
    "sg:address":"Unit 8, Hirwaun Industrial Estate, Hirwaun",
    "sg:city":"Aberdare",
    "sg:classifiers":[
        {
            "category":"Manufacturing",
            "subcategory":"Electronics",
            "type":"Manufacturing & Wholesale Goods"
        }
    ],
    "sg:phone":"+44 1685 811421",
    "sg:postcode":"CF44 9YE",
    "sg:province":"Neath Port Talbot",
    "sg:tags":[
        "control",
        "component",
        "-",
        "electronic"
    ],
    "wof:name":"Welsh Trust Electronics Ltd.",
    "wof:placetype":"venue"
},
  "geometry": {"coordinates":[-3.549364,51.744064],"type":"Point"}
}