{
  "type": "Feature",
  "properties": {
    "addr:full":"71a Storr Hill, Wyke Bradford West Yorkshire BD12 8PQ",
    "addr:housenumber":"71a",
    "addr:postcode":"bd12 8pq",
    "addr:street":"Storr Hill",
    "iso:country":"GB",
    "sg:address":"71a Storr Hill, Wyke",
    "sg:city":"Bradford",
    "sg:classifiers":[
        {
            "category":"Building & Trades",
            "subcategory":"Construction",
            "type":"Services"
        },
        {
            "category":"Real Estate",
            "subcategory":"Architect",
            "type":"Services"
        }
    ],
    "sg:phone":"+44 1274 677420",
    "sg:postcode":"BD12 8PQ",
    "sg:province":"West Yorkshire",
    "sg:tags":[
        "builder",
        "welder"
    ],
    "wof:name":"FOSTER BROTHERS (STEEL FABRICATORS)",
    "wof:placetype":"venue"
},
  "geometry": {"coordinates":[-1.766294,53.746483],"type":"Point"}
}