{
  "type": "Feature",
  "properties": {
    "iso:country":"GB",
    "sg:address":"48 Causewayhead",
    "sg:city":"Penzance",
    "sg:classifiers":[
        {
            "category":"Real Estate",
            "subcategory":"Real Estate Agent",
            "type":"Services"
        }
    ],
    "sg:phone":"+44 1736 369296",
    "sg:postcode":"TR18 2SS",
    "sg:province":"Cornwall",
    "wof:name":"R Whitlock",
    "wof:placetype":"venue"
},
  "geometry": {"coordinates":[-5.538676,50.120171],"type":"Point"}
}