{
  "type": "Feature",
  "properties": {
    "iso:country":"GB",
    "sg:address":"127 Kingston Road",
    "sg:city":"New Malden",
    "sg:classifiers":[
        {
            "category":"Food & Beverages",
            "subcategory":"Fruits & Vegetables",
            "type":"Retail Goods"
        },
        {
            "category":"Food & Beverages",
            "subcategory":"Groceries & Convenience Stores",
            "type":"Retail Goods"
        }
    ],
    "sg:phone":"+44 20 8336 1883",
    "sg:postcode":"KT3 3NX",
    "sg:province":"Surrey",
    "sg:tags":[
        "grocer",
        "greengrocer"
    ],
    "wof:name":"S & R Kim",
    "wof:placetype":"venue"
},
  "geometry": {"coordinates":[-0.2646720111,51.4006385803],"type":"Point"}
}