{
  "type": "Feature",
  "properties": {
    "iso:country":"GB",
    "sg:address":"287 Baldwins Lane, Croxley Green",
    "sg:city":"Rickmansworth",
    "sg:classifiers":[
        {
            "category":"Building & Trades",
            "subcategory":"Landscaping Services",
            "type":"Services"
        }
    ],
    "sg:phone":"+44 1923 778235",
    "sg:postcode":"WD3 3LE",
    "sg:province":"Hertfordshire",
    "sg:tags":[
        "landscape",
        "contractor"
    ],
    "wof:name":"Ian Watson",
    "wof:placetype":"venue"
},
  "geometry": {"coordinates":[-0.448349,51.653629],"type":"Point"}
}