{
  "type": "Feature",
  "properties": {
    "addr:full":"Wolverton House, 54 George Rd Godalming Surrey GU7 3LU",
    "addr:housenumber":"54",
    "addr:postcode":"gu7 3lu",
    "addr:street":"George Rd",
    "iso:country":"GB",
    "sg:address":"Wolverton House, 54 George Rd",
    "sg:city":"Godalming",
    "sg:classifiers":[
        {
            "category":"Professional",
            "subcategory":"Employment Agencies",
            "type":"Services"
        }
    ],
    "sg:phone":"+44 1932 352525",
    "sg:postcode":"GU7 3LU",
    "sg:province":"Surrey",
    "sg:tags":[
        "consultant"
    ],
    "wof:name":"Wolverton House Group",
    "wof:placetype":"venue"
},
  "geometry": {"coordinates":[-0.605078,51.198517],"type":"Point"}
}