{
  "type": "Feature",
  "properties": {
    "iso:country":"GB",
    "sg:address":"35 Uppingham Road",
    "sg:city":"Leicester",
    "sg:classifiers":[
        {
            "category":"Real Estate",
            "subcategory":"Real Estate Operator",
            "type":"Services"
        }
    ],
    "sg:phone":"+44 116 246 1543",
    "sg:postcode":"LE5 3TA",
    "sg:province":"Leicestershire",
    "sg:tags":[
        "letting",
        "agent"
    ],
    "wof:name":"P S R Estate Agents",
    "wof:placetype":"venue"
},
  "geometry": {"coordinates":[-1.103199,52.642128],"type":"Point"}
}