{
  "type": "Feature",
  "properties": {
    "addr:full":"20 Oak Lea Av Rotherham South Yorkshire S63 6LU",
    "addr:housenumber":"20",
    "addr:postcode":"s63 6lu",
    "addr:street":"Oak Lea Av Rotherham South",
    "iso:country":"GB",
    "sg:address":"20 Oak Lea Av",
    "sg:city":"Rotherham",
    "sg:classifiers":[
        {
            "category":"Government",
            "subcategory":"Office",
            "type":"Public Place"
        }
    ],
    "sg:phone":"+44 1709 872557",
    "sg:postcode":"S63 6LU",
    "sg:province":"South Yorkshire",
    "sg:tags":[
        "local"
    ],
    "wof:name":"Richard S Russell",
    "wof:placetype":"venue"
},
  "geometry": {"coordinates":[-1.3609980345,53.5043182373],"type":"Point"}
}