{
  "type": "Feature",
  "properties": {
    "iso:country":"GB",
    "sg:address":"Green Farm, Church Road, Thompson",
    "sg:city":"Thetford",
    "sg:classifiers":[
        {
            "category":"Farming",
            "subcategory":"Livestock Farm",
            "type":"Manufacturing & Wholesale Goods"
        },
        {
            "category":"Farming",
            "subcategory":"Farm",
            "type":"Manufacturing & Wholesale Goods"
        }
    ],
    "sg:phone":"+44 1953 483391",
    "sg:postcode":"IP24 1PZ",
    "sg:province":"Norfolk",
    "sg:tags":[
        "mixed",
        "crop",
        "others"
    ],
    "wof:name":"A T Robertson & Sons",
    "wof:placetype":"venue"
},
  "geometry": {"coordinates":[0.83012,52.533142],"type":"Point"}
}