{
  "type": "Feature",
  "properties": {
    "iso:country":"GB",
    "sg:address":"130 Trelawney Road, Peverell",
    "sg:city":"Plymouth",
    "sg:classifiers":[
        {
            "category":"Professional",
            "subcategory":"Advertising",
            "type":"Services"
        }
    ],
    "sg:phone":"+44 1752 848100",
    "sg:postcode":"PL3 4JZ",
    "sg:province":"Devon",
    "sg:tags":[
        "agency"
    ],
    "wof:name":"Net-trader",
    "wof:placetype":"venue"
},
  "geometry": {"coordinates":[-4.143538,50.38813],"type":"Point"}
}