{
  "type": "Feature",
  "properties": {
    "addr:full":"Crawley Road, Wood Green London Greater London N22 6AG",
    "addr:postcode":"n22 6ag",
    "addr:street":"Crawley Road",
    "iso:country":"GB",
    "sg:address":"Crawley Road, Wood Green",
    "sg:city":"London",
    "sg:classifiers":[
        {
            "category":"Retail",
            "subcategory":"Auto Repair",
            "type":"Services"
        }
    ],
    "sg:phone":"+44 20 8888 3461",
    "sg:postcode":"N22 6AG",
    "sg:province":"Greater London",
    "sg:tags":[
        "bathroom",
        "fixture"
    ],
    "wof:name":"Barber Wilsons & Co. Ltd.",
    "wof:placetype":"venue"
},
  "geometry": {"coordinates":[-0.094624,51.595116],"type":"Point"}
}