{
  "type": "Feature",
  "properties": {
    "iso:country":"GB",
    "sg:address":"Innerbridge Street, Guardbridge",
    "sg:city":"St Andrews",
    "sg:classifiers":[
        {
            "category":"Organizations",
            "subcategory":"Community Association",
            "type":"Services"
        },
        {
            "category":"Organizations",
            "subcategory":"Membership Organization",
            "type":"Services"
        }
    ],
    "sg:postcode":"KY16 0UZ",
    "sg:province":"Fife",
    "sg:tags":[
        "club",
        "social"
    ],
    "wof:name":"GUARDBRIDGE SPORTS & SOCIAL CLUB",
    "wof:placetype":"venue"
},
  "geometry": {"coordinates":[-2.893211,56.366417],"type":"Point"}
}