{
  "type": "Feature",
  "properties": {
    "iso:country":"GB",
    "sg:address":"College Road",
    "sg:city":"Uttoxeter",
    "sg:classifiers":[
        {
            "category":"Shopping",
            "subcategory":"Department Store",
            "type":"Retail Goods"
        }
    ],
    "sg:phone":"+44 1889 590397",
    "sg:postcode":"ST14 5HR",
    "sg:province":"Derbyshire",
    "wof:name":"Rosemary Edge",
    "wof:placetype":"venue"
},
  "geometry": {"coordinates":[-1.8590680361,52.963558197],"type":"Point"}
}