{
  "type": "Feature",
  "properties": {
    "addr:full":"26 Ladbroke Gro Notting Hill Greater London W11 3BQ",
    "addr:housenumber":"26",
    "addr:postcode":"w11 3bq",
    "addr:street":"Ladbroke Gro",
    "iso:country":"GB",
    "sg:address":"26 Ladbroke Gro",
    "sg:city":"Notting Hill",
    "sg:classifiers":[
        {
            "category":"Building & Trades",
            "subcategory":"Landscaping Services",
            "type":"Services"
        }
    ],
    "sg:phone":"+44 20 7243 8889",
    "sg:postcode":"W11 3BQ",
    "sg:province":"Greater London",
    "sg:tags":[
        "design",
        "garden"
    ],
    "wof:name":"Diana Ward Garden Design",
    "wof:placetype":"venue"
},
  "geometry": {"coordinates":[-0.2038830072,51.5092964172],"type":"Point"}
}