{
  "type": "Feature",
  "properties": {
    "addr:full":"23 Bankfields Ashford Kent TN27 9QY",
    "addr:housenumber":"23",
    "addr:postcode":"tn27 9qy",
    "addr:street":"Bankfields",
    "iso:country":"GB",
    "sg:address":"23 Bankfields",
    "sg:city":"Ashford",
    "sg:classifiers":[
        {
            "category":"Professional",
            "subcategory":"Accounting & Tax Preparation",
            "type":"Services"
        }
    ],
    "sg:postcode":"TN27 9QY",
    "sg:province":"Kent",
    "sg:tags":[
        "accountant"
    ],
    "wof:name":"Hawtin,Peter J,",
    "wof:placetype":"venue"
},
  "geometry": {"coordinates":[0.6185200214,51.1706466675],"type":"Point"}
}