{
  "type": "Feature",
  "properties": {
    "iso:country":"GB",
    "sg:address":"Brynglas Farm, Llangynog",
    "sg:city":"Carmarthen",
    "sg:classifiers":[
        {
            "category":"Farming",
            "subcategory":"Livestock Farm",
            "type":"Manufacturing & Wholesale Goods"
        }
    ],
    "sg:phone":"+44 1267 236170",
    "sg:postcode":"SA33 5DJ",
    "sg:province":"Carmarthenshire",
    "sg:tags":[
        "others"
    ],
    "wof:name":"Alcwyn & E O Phillips",
    "wof:placetype":"venue"
},
  "geometry": {"coordinates":[-4.409969,51.821075],"type":"Point"}
}