{
  "type": "Feature",
  "properties": {
    "iso:country":"GB",
    "sg:address":"Maylord Orchards Shopping Centre",
    "sg:city":"Hereford",
    "sg:classifiers":[
        {
            "category":"Government",
            "subcategory":"Office",
            "type":"Public Place"
        }
    ],
    "sg:phone":"+44 1432 342166",
    "sg:postcode":"HR1 2DT",
    "sg:province":"Herefordshire",
    "sg:tags":[
        "central"
    ],
    "wof:name":"Shopmobility",
    "wof:placetype":"venue"
},
  "geometry": {"coordinates":[-2.71451,52.05759],"type":"Point"}
}