{
  "type": "Feature",
  "properties": {
    "addr:full":"The Beeches 7 Bridle Road, Burton Joyce Nottingham Nottinghamshire NG14 5FT",
    "addr:housenumber":"7",
    "addr:postcode":"ng14 5ft",
    "addr:street":"Bridle Road",
    "iso:country":"GB",
    "sg:address":"The Beeches 7 Bridle Road, Burton Joyce",
    "sg:city":"Nottingham",
    "sg:classifiers":[
        {
            "category":"Professional",
            "subcategory":"Employment Agencies",
            "type":"Services"
        }
    ],
    "sg:postcode":"NG14 5FT",
    "sg:province":"Nottinghamshire",
    "sg:tags":[
        "consultant"
    ],
    "wof:name":"Elite Security Personnel Ltd",
    "wof:placetype":"venue"
},
  "geometry": {"coordinates":[-1.0363240242,52.9872665405],"type":"Point"}
}