{
  "type": "Feature",
  "properties": {
    "addr:full":"135 Rectory Gro Hampton Greater London TW12 1EQ",
    "addr:housenumber":"135",
    "addr:postcode":"tw12 1eq",
    "addr:street":"Rectory Gro",
    "iso:country":"GB",
    "sg:address":"135 Rectory Gro",
    "sg:city":"Hampton",
    "sg:classifiers":[
        {
            "category":"Arts & Performance",
            "subcategory":"Music",
            "type":"Entertainment"
        }
    ],
    "sg:postcode":"TW12 1EQ",
    "sg:province":"Greater London",
    "sg:tags":[
        "mobile",
        "disco"
    ],
    "wof:name":"Lightning Sounds Mobile Disco",
    "wof:placetype":"venue"
},
  "geometry": {"coordinates":[-0.3805820048,51.4327545166],"type":"Point"}
}