{
  "type": "Feature",
  "properties": {
    "iso:country":"GB",
    "sg:address":"3 Gosditch Street",
    "sg:city":"Cirencester",
    "sg:classifiers":[
        {
            "category":"Restaurant",
            "type":"Food & Drink"
        }
    ],
    "sg:phone":"+44 1285 652375",
    "sg:postcode":"GL7 2AG",
    "sg:province":"Gloucestershire",
    "sg:tags":[
        "-",
        "english"
    ],
    "wof:name":"Harry Hares",
    "wof:placetype":"venue"
},
  "geometry": {"coordinates":[-1.968748,51.717781],"type":"Point"}
}