{
  "type": "Feature",
  "properties": {
    "addr:full":"229a Ashley Road, Hale Altrincham Cheshire WA15 9SX",
    "addr:housenumber":"229a",
    "addr:postcode":"wa15 9sx",
    "addr:street":"Ashley Road",
    "iso:country":"GB",
    "sg:address":"229a Ashley Road, Hale",
    "sg:city":"Altrincham",
    "sg:classifiers":[
        {
            "category":"Real Estate",
            "subcategory":"Surveying",
            "type":"Services"
        }
    ],
    "sg:postcode":"WA15 9SX",
    "sg:province":"Cheshire",
    "sg:tags":[
        "surveyor",
        "quantity"
    ],
    "wof:name":"Mike Duxbury",
    "wof:placetype":"venue"
},
  "geometry": {"coordinates":[-2.343269,53.375904],"type":"Point"}
}