{
  "type": "Feature",
  "properties": {
    "addr:full":"11 Alpha Rd, Chobham Woking Surrey GU24 8NE",
    "addr:housenumber":"11",
    "addr:postcode":"gu24 8ne",
    "addr:street":"Alpha Rd",
    "iso:country":"GB",
    "sg:address":"11 Alpha Rd, Chobham",
    "sg:city":"Woking",
    "sg:classifiers":[
        {
            "category":"Banks & Credit Unions",
            "subcategory":"Bank",
            "type":"Services"
        }
    ],
    "sg:phone":"+44 1276 855194",
    "sg:postcode":"GU24 8NE",
    "sg:province":"Surrey",
    "sg:tags":[
        "broker",
        "mortgage"
    ],
    "wof:name":"Kevin Sewell",
    "wof:placetype":"venue"
},
  "geometry": {"coordinates":[-0.599808,51.350388],"type":"Point"}
}