{
  "type": "Feature",
  "properties": {
    "addr:full":"Vauxhall Business Centre, Vauxhall Road Liverpool Merseyside L3 6DJ",
    "addr:postcode":"l3 6dj",
    "addr:street":"Vauxhall Road",
    "iso:country":"GB",
    "sg:address":"Vauxhall Business Centre, Vauxhall Road",
    "sg:city":"Liverpool",
    "sg:classifiers":[
        {
            "category":"Retail",
            "subcategory":"Driving School",
            "type":"Services"
        }
    ],
    "sg:phone":"+44 151 236 2227",
    "sg:postcode":"L3 6DJ",
    "sg:province":"Merseyside",
    "sg:tags":[
        "instruction",
        "cycling",
        "motor"
    ],
    "wof:name":"Liverpool Motor Cycle Training",
    "wof:placetype":"venue"
},
  "geometry": {"coordinates":[-2.9885098934,53.4122314453],"type":"Point"}
}