{
  "type": "Feature",
  "properties": {
    "addr:full":"Oakley Hill, Merley Wimborne Dorset BH21 1RJ",
    "addr:postcode":"bh21 1rj",
    "addr:street":"Oakley Hill Merley",
    "iso:country":"GB",
    "sg:address":"Oakley Hill, Merley",
    "sg:city":"Wimborne",
    "sg:classifiers":[
        {
            "category":"Restaurant",
            "type":"Food & Drink"
        }
    ],
    "sg:postcode":"BH21 1RJ",
    "sg:province":"Dorset",
    "wof:name":"Les Bouviers Restaurants Ltd",
    "wof:placetype":"venue"
},
  "geometry": {"coordinates":[-1.9887089729,50.8022346497],"type":"Point"}
}