{
  "type": "Feature",
  "properties": {
    "addr:full":"Earls Court Advice Centre, 282 Earls Court Rd Earl's Court Greater London SW5 9AS",
    "addr:housenumber":"282",
    "addr:postcode":"sw5 9as",
    "addr:street":"Court;Earls Court Rd Earl'S Court",
    "iso:country":"GB",
    "sg:address":"Earls Court Advice Centre, 282 Earls Court Rd",
    "sg:city":"Earl's Court",
    "sg:classifiers":[
        {
            "category":"Government",
            "subcategory":"Office",
            "type":"Public Place"
        }
    ],
    "sg:phone":"+44 20 7835 2151",
    "sg:postcode":"SW5 9AS",
    "sg:province":"Greater London",
    "sg:tags":[
        "local"
    ],
    "wof:name":"Royal Borough Of Kensington & Chelsea The",
    "wof:placetype":"venue"
},
  "geometry": {"coordinates":[-0.191678,51.491058],"type":"Point"}
}