{
  "type": "Feature",
  "properties": {
    "addr:full":"4 St Peters Close Otley North Yorkshire LS21 1RF",
    "addr:housenumber":"4",
    "addr:postcode":"ls21 1rf",
    "addr:street":"St Peters Close",
    "iso:country":"GB",
    "sg:address":"4 St Peters Close",
    "sg:city":"Otley",
    "sg:classifiers":[
        {
            "category":"Organizations",
            "subcategory":"Non-profit Organization",
            "type":"Services"
        }
    ],
    "sg:phone":"+44 1943 465115",
    "sg:postcode":"LS21 1RF",
    "sg:province":"North Yorkshire",
    "sg:tags":[
        "charitable",
        "organisation",
        "voluntary",
        "charity"
    ],
    "wof:name":"Otley & District Talking Newspaper",
    "wof:placetype":"venue"
},
  "geometry": {"coordinates":[-1.682964,53.90749],"type":"Point"}
}