{
  "type": "Feature",
  "properties": {
    "addr:full":"Hutton Beck House, Stokesley Rd Guisborough North Yorkshire TS14 8DL",
    "addr:postcode":"ts14 8dl",
    "addr:street":"Stokesley Rd",
    "iso:country":"GB",
    "sg:address":"Hutton Beck House, Stokesley Rd",
    "sg:city":"Guisborough",
    "sg:classifiers":[
        {
            "category":"Health Services",
            "subcategory":"Doctor",
            "type":"Services"
        }
    ],
    "sg:phone":"+44 1287 632500",
    "sg:postcode":"TS14 8DL",
    "sg:province":"North Yorkshire",
    "sg:tags":[
        "practitioners"
    ],
    "wof:name":"Gale, J",
    "wof:placetype":"venue"
},
  "geometry": {"coordinates":[-1.0719840527,54.5325775146],"type":"Point"}
}