{
  "type": "Feature",
  "properties": {
    "addr:full":"Hanger 3, Blackpool Airport Blackpool Lancashire FY4 2QY",
    "addr:housenumber":"3",
    "addr:postcode":"fy4 2qy",
    "addr:street":"Hanger",
    "iso:country":"GB",
    "sg:address":"Hanger 3, Blackpool Airport",
    "sg:city":"Blackpool",
    "sg:classifiers":[
        {
            "category":"Airline",
            "type":"Transportation"
        }
    ],
    "sg:phone":"+44 1253 407070",
    "sg:postcode":"FY4 2QY",
    "sg:province":"Lancashire",
    "sg:tags":[
        "aircraft",
        "charter"
    ],
    "wof:name":"Pool Aviation (N W) Ltd.",
    "wof:placetype":"venue"
},
  "geometry": {"coordinates":[-3.040619,53.784691],"type":"Point"}
}