{
  "type": "Feature",
  "properties": {
    "iso:country":"GB",
    "sg:address":"32 Bellmans Rd",
    "sg:city":"Peterborough",
    "sg:classifiers":[
        {
            "category":"Military Area",
            "subcategory":"Air Force Base",
            "type":"Public Place"
        }
    ],
    "sg:phone":"+44 1733 702266",
    "sg:postcode":"PE7 1TY",
    "sg:province":"Cambridgeshire",
    "sg:tags":[
        "taxi",
        "hire",
        "private"
    ],
    "wof:name":"Gold Cars",
    "wof:placetype":"venue"
},
  "geometry": {"coordinates":[-0.115528,52.555275],"type":"Point"}
}