{
  "type": "Feature",
  "properties": {
    "addr:full":"Observatories, Alston Lane Preston Lancashire PR3 3BN",
    "addr:postcode":"pr3 3bn",
    "addr:street":"Alston Lane",
    "iso:country":"GB",
    "sg:address":"Observatories, Alston Lane",
    "sg:city":"Preston",
    "sg:classifiers":[
        {
            "category":"Education",
            "subcategory":"University",
            "type":"Public Place"
        }
    ],
    "sg:phone":"+44 1772 782379",
    "sg:postcode":"PR3 3BN",
    "sg:province":"Lancashire",
    "sg:tags":[
        "medical",
        "school"
    ],
    "wof:name":"University of Central Lancashire",
    "wof:placetype":"venue"
},
  "geometry": {"coordinates":[-2.6085939407,53.8128509521],"type":"Point"}
}