{
  "type": "Feature",
  "properties": {
    "iso:country":"GB",
    "sg:address":"Drury Lane",
    "sg:city":"Hastings",
    "sg:classifiers":[
        {
            "category":"Home & Garden",
            "subcategory":"Household Appliances",
            "type":"Retail Goods"
        }
    ],
    "sg:postcode":"TN34 1DQ",
    "sg:province":"East Sussex",
    "sg:tags":[
        "domestic",
        "centre"
    ],
    "wof:name":"D A P Philips Hastings",
    "wof:placetype":"venue"
},
  "geometry": {"coordinates":[0.5786979795,50.8561897278],"type":"Point"}
}