{
  "type": "Feature",
  "properties": {
    "addr:full":"Prospect Cottage, Kempsey Common, Kempsey Worcester Worcestershire WR5 3QE",
    "addr:housenumber":"kempsey",
    "addr:postcode":"wr5 3qe",
    "addr:street":"Common Kempsey",
    "iso:country":"GB",
    "sg:address":"Prospect Cottage, Kempsey Common, Kempsey",
    "sg:city":"Worcester",
    "sg:classifiers":[
        {
            "category":"Retail",
            "subcategory":"Veterinary Services",
            "type":"Services"
        }
    ],
    "sg:phone":"+44 1905 821796",
    "sg:postcode":"WR5 3QE",
    "sg:province":"Worcestershire",
    "sg:tags":[
        "surgeon"
    ],
    "wof:name":"Homoeopathic Veterinary Surgeon",
    "wof:placetype":"venue"
},
  "geometry": {"coordinates":[-2.217885,52.140137],"type":"Point"}
}