{
  "type": "Feature",
  "properties": {
    "addr:full":"68 Medomsley Road Consett Durham DH8 5HP",
    "addr:housenumber":"68",
    "addr:postcode":"dh8 5hp",
    "addr:street":"Medomsley Road",
    "iso:country":"GB",
    "sg:address":"68 Medomsley Road",
    "sg:city":"Consett",
    "sg:classifiers":[
        {
            "category":"Shopping",
            "subcategory":"Pharmacy",
            "type":"Retail Goods"
        }
    ],
    "sg:phone":"+44 1207 502535",
    "sg:postcode":"DH8 5HP",
    "sg:province":"Durham",
    "sg:tags":[
        "pharmacist",
        "chemist"
    ],
    "wof:name":"Moss Chemists",
    "wof:placetype":"venue"
},
  "geometry": {"coordinates":[-1.832054,54.854698],"type":"Point"}
}