{
  "type": "Feature",
  "properties": {
    "iso:country":"GB",
    "sg:address":"Woodchurch Rd",
    "sg:city":"Birkenhead",
    "sg:classifiers":[
        {
            "category":"Organizations",
            "subcategory":"Non-profit Organization",
            "type":"Services"
        }
    ],
    "sg:phone":"+44 151 653 4787",
    "sg:postcode":"CH41 2UE",
    "sg:province":"Merseyside",
    "sg:tags":[
        "organisation",
        "voluntary",
        "charity"
    ],
    "wof:name":"Wirral Talking Newspaper",
    "wof:placetype":"venue"
},
  "geometry": {"coordinates":[-3.0360488892,53.3851547241],"type":"Point"}
}