{
  "type": "Feature",
  "properties": {
    "iso:country":"GB",
    "sg:address":"55 Iveley Road",
    "sg:city":"London",
    "sg:classifiers":[
        {
            "category":"Building & Trades",
            "subcategory":"Construction",
            "type":"Services"
        },
        {
            "category":"Building & Trades",
            "subcategory":"Electrical",
            "type":"Services"
        }
    ],
    "sg:phone":"+44 20 7627 5005",
    "sg:postcode":"SW4 0EN",
    "sg:province":"Greater London",
    "sg:tags":[
        "consultant",
        "lighting",
        "design"
    ],
    "wof:name":"Low Voltage Systems Ltd.",
    "wof:placetype":"venue"
},
  "geometry": {"coordinates":[-0.140577,51.468487],"type":"Point"}
}