{
  "type": "Feature",
  "properties": {
    "addr:full":"98 York Road Battersea Greater London SW11 3RD",
    "addr:housenumber":"98",
    "addr:postcode":"sw11 3rd",
    "addr:street":"York Road",
    "iso:country":"GB",
    "sg:address":"98 York Road",
    "sg:city":"Battersea",
    "sg:classifiers":[
        {
            "category":"Autos & Motor Vehicles",
            "subcategory":"Automobile Sales",
            "type":"Retail Goods"
        }
    ],
    "sg:phone":"+44 20 7924 6644",
    "sg:postcode":"SW11 3RD",
    "sg:province":"Greater London",
    "sg:tags":[
        "car"
    ],
    "wof:name":"Dover Court Battersea",
    "wof:placetype":"venue"
},
  "geometry": {"coordinates":[-0.177148,51.469143],"type":"Point"}
}