{
  "type": "Feature",
  "properties": {
    "addr:full":"Landkey Road Barnstaple Devon EX32 9BZ",
    "addr:postcode":"ex32 9bz",
    "addr:street":"Landkey Road",
    "iso:country":"GB",
    "sg:address":"Landkey Road",
    "sg:city":"Barnstaple",
    "sg:classifiers":[
        {
            "category":"Health Services",
            "subcategory":"Health Practitioner",
            "type":"Services"
        }
    ],
    "sg:postcode":"EX32 9BZ",
    "sg:province":"Devon",
    "sg:tags":[
        "homoeopathic"
    ],
    "wof:name":"P J Nelson",
    "wof:placetype":"venue"
},
  "geometry": {"coordinates":[-4.0440587997,51.0705413818],"type":"Point"}
}