{
  "type": "Feature",
  "properties": {
    "addr:full":"141 Moss Road, Birkdale Southport Lancashire PR8 4JA",
    "addr:housenumber":"141",
    "addr:postcode":"pr8 4ja",
    "addr:street":"Moss Road",
    "iso:country":"GB",
    "sg:address":"141 Moss Road, Birkdale",
    "sg:city":"Southport",
    "sg:classifiers":[
        {
            "category":"Professional",
            "type":"Services"
        }
    ],
    "sg:postcode":"PR8 4JA",
    "sg:province":"Lancashire",
    "sg:tags":[
        "entertainer"
    ],
    "wof:name":"John Relton Pianist",
    "wof:placetype":"venue"
},
  "geometry": {"coordinates":[-2.9886341095,53.6247406006],"type":"Point"}
}