{
  "type": "Feature",
  "properties": {
    "iso:country":"GB",
    "sg:address":"1a Wilby Street",
    "sg:city":"Northampton",
    "sg:classifiers":[
        {
            "category":"Real Estate",
            "subcategory":"Real Estate Agent",
            "type":"Services"
        }
    ],
    "sg:phone":"+44 1604 230586",
    "sg:postcode":"NN1 5JX",
    "sg:province":"Northamptonshire",
    "wof:name":"Jacques Management",
    "wof:placetype":"venue"
},
  "geometry": {"coordinates":[-0.8757179976,52.241973877],"type":"Point"}
}