{
  "type": "Feature",
  "properties": {
    "iso:country":"GB",
    "sg:address":"52-54 Union Street",
    "sg:city":"Aberdeen",
    "sg:classifiers":[
        {
            "category":"Banks & Credit Unions",
            "subcategory":"Bank",
            "type":"Services"
        }
    ],
    "sg:phone":"+44 845 607 7010",
    "sg:postcode":"AB10 1WR",
    "sg:province":"Aberdeen City",
    "wof:name":"Halifax Plc",
    "wof:placetype":"venue"
},
  "geometry": {"coordinates":[-2.108833,57.144543],"type":"Point"}
}