{
  "type": "Feature",
  "properties": {
    "iso:country":"GB",
    "sg:address":"Unit 4 Thomas Mitchell Homes",
    "sg:city":"Kirkcaldy",
    "sg:classifiers":[
        {
            "category":"Autos & Motor Vehicles",
            "subcategory":"Auto Supplies",
            "type":"Retail Goods"
        },
        {
            "category":"Home & Garden",
            "subcategory":"Building Materials",
            "type":"Retail Goods"
        },
        {
            "category":"Manufacturing",
            "subcategory":"Motor Vehicles & Parts",
            "type":"Manufacturing & Wholesale Goods"
        }
    ],
    "sg:phone":"+44 1592 630244",
    "sg:postcode":"KY1 4EH",
    "sg:province":"Fife",
    "sg:tags":[
        "car",
        "manufacturer",
        "lacquer",
        "paint"
    ],
    "wof:name":"Autopaint Fife Ltd",
    "wof:placetype":"venue"
},
  "geometry": {"coordinates":[-3.163029,56.109596],"type":"Point"}
}