{
  "type": "Feature",
  "properties": {
    "addr:full":"64 North Road, Kirkburton Huddersfield South Yorkshire HD8 0RW",
    "addr:housenumber":"64",
    "addr:postcode":"hd8 0rw",
    "addr:street":"North Road",
    "iso:country":"GB",
    "sg:address":"64 North Road, Kirkburton",
    "sg:city":"Huddersfield",
    "sg:classifiers":[
        {
            "category":"Bars & Pubs",
            "type":"Food & Drink"
        },
        {
            "category":"Community Center",
            "subcategory":"Social",
            "type":"Public Place"
        }
    ],
    "sg:phone":"+44 1484 602521",
    "sg:postcode":"HD8 0RW",
    "sg:province":"South Yorkshire",
    "sg:tags":[
        "pubs",
        "house",
        "inn",
        "activity"
    ],
    "wof:name":"THE ROYAL",
    "wof:placetype":"venue"
},
  "geometry": {"coordinates":[-1.705271,53.612755],"type":"Point"}
}