{
  "type": "Feature",
  "properties": {
    "addr:full":"5 Chapel Street, Mumbles Swansea Swansea SA3 4NH",
    "addr:housenumber":"5",
    "addr:postcode":"sa3 4nh",
    "addr:street":"Chapel Street",
    "iso:country":"GB",
    "sg:address":"5 Chapel Street, Mumbles",
    "sg:city":"Swansea",
    "sg:classifiers":[
        {
            "category":"Travel",
            "subcategory":"Travel Agent",
            "type":"Entertainment"
        }
    ],
    "sg:phone":"+44 1792 367321",
    "sg:postcode":"SA3 4NH",
    "sg:province":"Swansea",
    "wof:name":"Reg Bateman Travel",
    "wof:placetype":"venue"
},
  "geometry": {"coordinates":[-4.001651,51.574558],"type":"Point"}
}