{
  "type": "Feature",
  "properties": {
    "iso:country":"GB",
    "sg:address":"44 High Street, Coedpoeth",
    "sg:city":"Wrexham",
    "sg:classifiers":[
        {
            "category":"Health Services",
            "subcategory":"Podiatrist",
            "type":"Services"
        }
    ],
    "sg:phone":"+44 1978 756593",
    "sg:postcode":"LL11 3SB",
    "sg:province":"Wrexham",
    "sg:tags":[
        "podiatrists",
        "chiropodist"
    ],
    "wof:name":"C A Kendrick",
    "wof:placetype":"venue"
},
  "geometry": {"coordinates":[-3.075439,53.056252],"type":"Point"}
}