{
  "type": "Feature",
  "properties": {
    "iso:country":"GB",
    "sg:address":"The Shopping Precinct, Main Square",
    "sg:city":"Camberley",
    "sg:classifiers":[
        {
            "category":"Cafe",
            "type":"Food & Drink"
        }
    ],
    "sg:phone":"+44 1276 675834",
    "sg:postcode":"GU15 3SD",
    "sg:province":"Berkshire",
    "sg:tags":[
        "tea",
        "room"
    ],
    "wof:name":"Giardino Group Ltd.",
    "wof:placetype":"venue"
},
  "geometry": {"coordinates":[-0.7342299819,51.3362159729],"type":"Point"}
}