{
  "type": "Feature",
  "properties": {
    "addr:full":"61-69 Derngate Northampton Northamptonshire NN1 1UU",
    "addr:housenumber":"61-69",
    "addr:postcode":"nn1 1uu",
    "addr:street":"Derngate Northampton",
    "iso:country":"GB",
    "sg:address":"61-69 Derngate",
    "sg:city":"Northampton",
    "sg:classifiers":[
        {
            "category":"Professional",
            "subcategory":"Lawyer & Legal Services",
            "type":"Services"
        }
    ],
    "sg:phone":"+44 1604 628986",
    "sg:postcode":"NN1 1UU",
    "sg:province":"Northamptonshire",
    "sg:tags":[
        "advice",
        "counselling"
    ],
    "wof:name":"Northamptonshire Lesbian & Gay Resource Centre",
    "wof:placetype":"venue"
},
  "geometry": {"coordinates":[-0.890524,52.235897],"type":"Point"}
}