{
  "type": "Feature",
  "properties": {
    "addr:full":"William Woods End Building, Palatine St, Castle Blvd Nottingham Nottinghamshire NG7 1GA",
    "addr:postcode":"ng7 1ga",
    "addr:street":"Palatine St Castle Blvd",
    "iso:country":"GB",
    "sg:address":"William Woods End Building, Palatine St, Castle Blvd",
    "sg:city":"Nottingham",
    "sg:classifiers":[
        {
            "category":"Wholesale",
            "subcategory":"Vending Machines",
            "type":"Manufacturing & Wholesale Goods"
        }
    ],
    "sg:postcode":"NG7 1GA",
    "sg:province":"Nottinghamshire",
    "sg:tags":[
        "sale"
    ],
    "wof:name":"Aardvark Vending",
    "wof:placetype":"venue"
},
  "geometry": {"coordinates":[-1.16798,52.94495],"type":"Point"}
}