{
  "type": "Feature",
  "properties": {
    "iso:country":"GB",
    "sg:address":"Twyn Pandy, Llangynidr",
    "sg:city":"Crickhowell",
    "sg:classifiers":[
        {
            "category":"Shopping",
            "subcategory":"Florist",
            "type":"Retail Goods"
        }
    ],
    "sg:phone":"+44 1874 730432",
    "sg:postcode":"LD3 7LA",
    "sg:province":"Powys",
    "wof:name":"Buds & Blooms",
    "wof:placetype":"venue"
},
  "geometry": {"coordinates":[-3.3914399147,51.9482307434],"type":"Point"}
}