{
  "type": "Feature",
  "properties": {
    "iso:country":"GB",
    "sg:address":"Unit 22a Digby Dr",
    "sg:city":"Melton Mowbray",
    "sg:classifiers":[
        {
            "category":"Shopping",
            "subcategory":"Catalog Store",
            "type":"Retail Goods"
        }
    ],
    "sg:postcode":"LE13 0RQ",
    "sg:province":"Leicestershire",
    "sg:tags":[
        "mail",
        "order"
    ],
    "wof:name":"Hall,Christopher,",
    "wof:placetype":"venue"
},
  "geometry": {"coordinates":[-0.9087389708,52.7512588501],"type":"Point"}
}