{
  "type": "Feature",
  "properties": {
    "addr:full":"9 Alverton Terrace Penzance Cornwall TR18 4JH",
    "addr:housenumber":"9",
    "addr:postcode":"tr18 4jh",
    "addr:street":"Alverton Terrace",
    "iso:country":"GB",
    "sg:address":"9 Alverton Terrace",
    "sg:city":"Penzance",
    "sg:classifiers":[
        {
            "category":"Food & Beverages",
            "subcategory":"Groceries & Convenience Stores",
            "type":"Retail Goods"
        }
    ],
    "sg:phone":"+44 1736 331441",
    "sg:postcode":"TR18 4JH",
    "sg:province":"Cornwall",
    "wof:name":"The Little Shop",
    "wof:placetype":"venue"
},
  "geometry": {"coordinates":[-5.5422539711,50.1180038452],"type":"Point"}
}