{
  "type": "Feature",
  "properties": {
    "addr:full":"92 Wolverhampton Road, Essington Wolverhampton Staffordshire WV11 2BT",
    "addr:housenumber":"92",
    "addr:postcode":"wv11 2bt",
    "addr:street":"Wolverhampton Road",
    "iso:country":"GB",
    "sg:address":"92 Wolverhampton Road, Essington",
    "sg:city":"Wolverhampton",
    "sg:classifiers":[
        {
            "category":"Building & Trades",
            "subcategory":"Construction",
            "type":"Services"
        }
    ],
    "sg:phone":"+44 1922 403589",
    "sg:postcode":"WV11 2BT",
    "sg:province":"Staffordshire",
    "sg:tags":[
        "decorator",
        "painter"
    ],
    "wof:name":"A & J Butler",
    "wof:placetype":"venue"
},
  "geometry": {"coordinates":[-2.060941,52.625301],"type":"Point"}
}