{
  "type": "Feature",
  "properties": {
    "iso:country":"GB",
    "sg:address":"Main Road, Hursley",
    "sg:city":"Winchester",
    "sg:classifiers":[
        {
            "category":"Shopping",
            "subcategory":"Antiques",
            "type":"Retail Goods"
        },
        {
            "category":"Shopping",
            "subcategory":"Books",
            "type":"Retail Goods"
        }
    ],
    "sg:postcode":"SO21 2JY",
    "sg:province":"Hampshire",
    "wof:name":"Hursley Antiques",
    "wof:placetype":"venue"
},
  "geometry": {"coordinates":[-1.390614,51.024597],"type":"Point"}
}