{
  "type": "Feature",
  "properties": {
    "iso:country":"GB",
    "sg:address":"Darby Lane, Hindley",
    "sg:city":"Wigan",
    "sg:classifiers":[
        {
            "category":"Manufacturing",
            "subcategory":"Petroleum Products",
            "type":"Manufacturing & Wholesale Goods"
        }
    ],
    "sg:postcode":"WN2 3DW",
    "sg:province":"Lancashire",
    "sg:tags":[
        "double",
        "glazing"
    ],
    "wof:name":"Burcul Ltd.",
    "wof:placetype":"venue"
},
  "geometry": {"coordinates":[-2.579696,53.536926],"type":"Point"}
}