{
  "type": "Feature",
  "properties": {
    "addr:full":"84 Bridge Road Uxbridge Buckinghamshire UB8 2QW",
    "addr:housenumber":"84",
    "addr:postcode":"ub8 2qw",
    "addr:street":"Bridge Road",
    "iso:country":"GB",
    "sg:address":"84 Bridge Road",
    "sg:city":"Uxbridge",
    "sg:classifiers":[
        {
            "category":"Real Estate",
            "subcategory":"Architect",
            "type":"Services"
        }
    ],
    "sg:phone":"+44 1895 822488",
    "sg:postcode":"UB8 2QW",
    "sg:province":"Buckinghamshire",
    "sg:tags":[
        "architectural"
    ],
    "wof:name":"Home Plans",
    "wof:placetype":"venue"
},
  "geometry": {"coordinates":[-0.4828380048,51.5393028259],"type":"Point"}
}