{
  "type": "Feature",
  "properties": {
    "addr:full":"2 Bahama Road, Haydock Industrial Estate St Helens Lancashire WA11 9XB",
    "addr:housenumber":"2",
    "addr:postcode":"wa11 9xb",
    "addr:street":"Bahama Road Haydock Industrial Estate",
    "iso:country":"GB",
    "sg:address":"2 Bahama Road, Haydock Industrial Estate",
    "sg:city":"St Helens",
    "sg:classifiers":[
        {
            "category":"Shopping",
            "subcategory":"Party Supplies",
            "type":"Retail Goods"
        }
    ],
    "sg:phone":"+44 1942 896058",
    "sg:postcode":"WA11 9XB",
    "sg:province":"Lancashire",
    "sg:tags":[
        "marquees",
        "floor",
        "tent"
    ],
    "wof:name":"Smiths Marquees",
    "wof:placetype":"venue"
},
  "geometry": {"coordinates":[-2.6648890972,53.4733657837],"type":"Point"}
}