{
  "type": "Feature",
  "properties": {
    "addr:full":"Neville House, Beaumont Rd Banbury Oxfordshire OX16 7RB",
    "addr:postcode":"ox16 7rb",
    "addr:street":"Beaumont Rd",
    "iso:country":"GB",
    "sg:address":"Neville House, Beaumont Rd",
    "sg:city":"Banbury",
    "sg:classifiers":[
        {
            "category":"Shopping",
            "subcategory":"Discount & Variety Stores",
            "type":"Retail Goods"
        }
    ],
    "sg:phone":"+44 1295 253106",
    "sg:postcode":"OX16 7RB",
    "sg:province":"Oxfordshire",
    "sg:tags":[
        "cleaning",
        "supply"
    ],
    "wof:name":"Dreumex Ltd",
    "wof:placetype":"venue"
},
  "geometry": {"coordinates":[-1.3449939489,52.073764801],"type":"Point"}
}