{
  "type": "Feature",
  "properties": {
    "iso:country":"GB",
    "sg:address":"46b Hartington Street",
    "sg:city":"Bedford",
    "sg:classifiers":[
        {
            "category":"Manufacturing",
            "subcategory":"Signs",
            "type":"Manufacturing & Wholesale Goods"
        }
    ],
    "sg:phone":"+44 1234 350119",
    "sg:postcode":"MK41 7RL",
    "sg:province":"Bedfordshire",
    "sg:tags":[
        "writer"
    ],
    "wof:name":"Marriott Sign Writers",
    "wof:placetype":"venue"
},
  "geometry": {"coordinates":[-0.471448,52.145187],"type":"Point"}
}