{
  "type": "Feature",
  "properties": {
    "addr:full":"Unit 36 Upper Ground Level, The Oracle Centre Reading Berkshire RG1 2AH",
    "addr:housenumber":"unit 36",
    "addr:postcode":"rg1 2ah",
    "addr:street":"Upper Ground Level The Oracle Centre",
    "iso:country":"GB",
    "sg:address":"Unit 36 Upper Ground Level, The Oracle Centre",
    "sg:city":"Reading",
    "sg:classifiers":[
        {
            "category":"Shopping",
            "subcategory":"Comic Books",
            "type":"Retail Goods"
        }
    ],
    "sg:postcode":"RG1 2AH",
    "sg:province":"Berkshire",
    "sg:tags":[
        "jeweller"
    ],
    "wof:name":"Leslie Davis",
    "wof:placetype":"venue"
},
  "geometry": {"coordinates":[-0.9673590064,51.4494895935],"type":"Point"}
}