{
  "type": "Feature",
  "properties": {
    "iso:country":"GB",
    "sg:address":"Lambert House, Brook St",
    "sg:city":"Glossop",
    "sg:classifiers":[
        {
            "category":"Professional",
            "subcategory":"Accounting & Tax Preparation",
            "type":"Services"
        }
    ],
    "sg:phone":"+44 1457 856850",
    "sg:postcode":"SK13 8BG",
    "sg:province":"Derbyshire",
    "sg:tags":[
        "accountant"
    ],
    "wof:name":"Vernon Payne",
    "wof:placetype":"venue"
},
  "geometry": {"coordinates":[-1.955119,53.443218],"type":"Point"}
}