{
  "type": "Feature",
  "properties": {
    "addr:full":"71 Bath Road, Longwell Grn Bristol Gloucestershire BS30 9DF",
    "addr:housenumber":"71",
    "addr:postcode":"bs30 9df",
    "addr:street":"Bath Road Longwell Grn",
    "iso:country":"GB",
    "sg:address":"71 Bath Road, Longwell Grn",
    "sg:city":"Bristol",
    "sg:classifiers":[
        {
            "category":"Education",
            "subcategory":"Music School",
            "type":"Public Place"
        }
    ],
    "sg:postcode":"BS30 9DF",
    "sg:province":"Gloucestershire",
    "sg:tags":[
        "conservatory"
    ],
    "wof:name":"Kingsway Garden Buildings Ltd.",
    "wof:placetype":"venue"
},
  "geometry": {"coordinates":[-2.493863,51.438232],"type":"Point"}
}