{
  "type": "Feature",
  "properties": {
    "addr:full":"6 Bristol House, 80a Southampton Row London Greater London WC1B 4BB",
    "addr:housenumber":"6;80a",
    "addr:postcode":"wc1b 4bb",
    "addr:street":"Bristol House;Southampton Row",
    "iso:country":"GB",
    "sg:address":"6 Bristol House, 80a Southampton Row",
    "sg:city":"London",
    "sg:classifiers":[
        {
            "category":"Professional",
            "subcategory":"Lawyer & Legal Services",
            "type":"Services"
        }
    ],
    "sg:phone":"+44 20 7430 2102",
    "sg:postcode":"WC1B 4BB",
    "sg:province":"Greater London",
    "wof:name":"Samir Saleh & Associates",
    "wof:placetype":"venue"
},
  "geometry": {"coordinates":[-0.1218020022,51.5197906494],"type":"Point"}
}