{
  "type": "Feature",
  "properties": {
    "addr:full":"10 The Garth, Front Street, Winlaton Blaydon-on-tyne Tyne and Wear NE21 6DD",
    "addr:housenumber":"10",
    "addr:postcode":"ne21 6dd",
    "addr:street":"The Garth Front Street",
    "iso:country":"GB",
    "sg:address":"10 The Garth, Front Street, Winlaton",
    "sg:city":"Blaydon-on-tyne",
    "sg:classifiers":[
        {
            "category":"Food & Beverages",
            "subcategory":"Fruits & Vegetables",
            "type":"Retail Goods"
        }
    ],
    "sg:phone":"+44 191 414 3969",
    "sg:postcode":"NE21 6DD",
    "sg:province":"Tyne and Wear",
    "sg:tags":[
        "greengrocer"
    ],
    "wof:name":"Bennett's",
    "wof:placetype":"venue"
},
  "geometry": {"coordinates":[-1.725729,54.956642],"type":"Point"}
}