{
  "type": "Feature",
  "properties": {
    "addr:full":"9 Mill Close Carshalton Surrey SM5 2NE",
    "addr:housenumber":"9",
    "addr:postcode":"sm5 2ne",
    "addr:street":"Mill Close",
    "iso:country":"GB",
    "sg:address":"9 Mill Close",
    "sg:city":"Carshalton",
    "sg:classifiers":[
        {
            "category":"Professional",
            "subcategory":"Management & Consulting",
            "type":"Services"
        }
    ],
    "sg:phone":"+44 7770 482816",
    "sg:postcode":"SM5 2NE",
    "sg:province":"Surrey",
    "sg:tags":[
        "consultant",
        "business"
    ],
    "wof:name":"D T Consultants Ltd.",
    "wof:placetype":"venue"
},
  "geometry": {"coordinates":[-0.1585910022,51.3752593994],"type":"Point"}
}