{
  "type": "Feature",
  "properties": {
    "iso:country":"GB",
    "sg:address":"16 Carstairs Road, Carstairs",
    "sg:city":"Lanark",
    "sg:classifiers":[
        {
            "category":"Government",
            "subcategory":"Post Office",
            "type":"Public Place"
        }
    ],
    "sg:phone":"+44 1555 870220",
    "sg:postcode":"ML11 8QB",
    "sg:province":"South Lanarkshire",
    "wof:name":"Carstairs Sub Post Office",
    "wof:placetype":"venue"
},
  "geometry": {"coordinates":[-3.6801528931,55.6932945251],"type":"Point"}
}