{
  "type": "Feature",
  "properties": {
    "addr:full":"20 Fulmar Court Leeds West Yorkshire LS10 3HB",
    "addr:housenumber":"20",
    "addr:postcode":"ls10 3hb",
    "addr:street":"Fulmar Court",
    "iso:country":"GB",
    "sg:address":"20 Fulmar Court",
    "sg:city":"Leeds",
    "sg:classifiers":[
        {
            "category":"Banks & Credit Unions",
            "subcategory":"Financial Services",
            "type":"Services"
        },
        {
            "category":"Professional",
            "subcategory":"Credit Reporting & Collection",
            "type":"Services"
        }
    ],
    "sg:phone":"+44 113 277 7713",
    "sg:postcode":"LS10 3HB",
    "sg:province":"West Yorkshire",
    "sg:tags":[
        "adviser",
        "pension",
        "consultant"
    ],
    "wof:name":"Oakhill Partnership",
    "wof:placetype":"venue"
},
  "geometry": {"coordinates":[-1.536389,53.749966],"type":"Point"}
}