{
  "type": "Feature",
  "properties": {
    "iso:country":"GB",
    "sg:address":"Hawthorns",
    "sg:city":"Braintree",
    "sg:classifiers":[
        {
            "category":"Professional",
            "subcategory":"Engineering",
            "type":"Services"
        }
    ],
    "sg:phone":"+44 1371 851593",
    "sg:postcode":"CM7 4ED",
    "sg:province":"Essex",
    "sg:tags":[
        "gas",
        "engineer"
    ],
    "wof:name":"Steven Osborne",
    "wof:placetype":"venue"
},
  "geometry": {"coordinates":[0.46423,51.962311],"type":"Point"}
}