{
  "type": "Feature",
  "properties": {
    "addr:full":"138 Lower Road London Greater London SE16 2UG",
    "addr:housenumber":"138",
    "addr:postcode":"se16 2ug",
    "addr:street":"Lower Road",
    "iso:country":"GB",
    "sg:address":"138 Lower Road",
    "sg:city":"London",
    "sg:classifiers":[
        {
            "category":"Building & Trades",
            "subcategory":"Cleaning & Sanitation",
            "type":"Services"
        }
    ],
    "sg:phone":"+44 20 7394 9007",
    "sg:postcode":"SE16 2UG",
    "sg:province":"Greater London",
    "sg:tags":[
        "commercial"
    ],
    "wof:name":"Kleanwell",
    "wof:placetype":"venue"
},
  "geometry": {"coordinates":[-0.0468060002,51.4928131104],"type":"Point"}
}