{
  "type": "Feature",
  "properties": {
    "iso:country":"GB",
    "sg:address":"20 Colvin Road, Eastham",
    "sg:city":"London",
    "sg:classifiers":[
        {
            "category":"Communications",
            "type":"Services"
        }
    ],
    "sg:phone":"+44 20 8472 6661",
    "sg:postcode":"E6 1JL",
    "sg:province":"Greater London",
    "sg:tags":[
        "tv",
        "video",
        "radio"
    ],
    "wof:name":"East London Electronics",
    "wof:placetype":"venue"
},
  "geometry": {"coordinates":[0.0488630012,51.5372886658],"type":"Point"}
}