{
  "type": "Feature",
  "properties": {
    "addr:full":"Unit 14 Barnes Trading Estate, Main Street Rotherham South Yorkshire S66 2SQ",
    "addr:housenumber":"unit 14",
    "addr:postcode":"s66 2sq",
    "addr:street":"Barnes Trading Estate Main Street",
    "iso:country":"GB",
    "sg:address":"Unit 14 Barnes Trading Estate, Main Street",
    "sg:city":"Rotherham",
    "sg:classifiers":[
        {
            "category":"Autos & Motor Vehicles",
            "subcategory":"Auto Supplies",
            "type":"Retail Goods"
        }
    ],
    "sg:phone":"+44 1709 703777",
    "sg:postcode":"S66 2SQ",
    "sg:province":"South Yorkshire",
    "sg:tags":[
        "rubber",
        "tyre"
    ],
    "wof:name":"Bramley Tyres",
    "wof:placetype":"venue"
},
  "geometry": {"coordinates":[-1.2652100325,53.4254188538],"type":"Point"}
}