{
  "type": "Feature",
  "properties": {
    "addr:full":"9 Iverson Road London Greater London NW6 2QT",
    "addr:housenumber":"9",
    "addr:postcode":"nw6 2qt",
    "addr:street":"Iverson Road",
    "iso:country":"GB",
    "sg:address":"9 Iverson Road",
    "sg:city":"London",
    "sg:classifiers":[
        {
            "category":"Organizations",
            "subcategory":"Religious Organization",
            "type":"Services"
        }
    ],
    "sg:phone":"+44 20 7625 7043",
    "sg:postcode":"NW6 2QT",
    "sg:province":"Greater London",
    "sg:tags":[
        "organisation"
    ],
    "wof:name":"The Brondesbury Christian Centre",
    "wof:placetype":"venue"
},
  "geometry": {"coordinates":[-0.202095,51.546043],"type":"Point"}
}