{
  "type": "Feature",
  "properties": {
    "iso:country":"GB",
    "sg:address":"Priory Fields",
    "sg:city":"Stroud",
    "sg:classifiers":[
        {
            "category":"Health Services",
            "subcategory":"Nursing And Care Facility",
            "type":"Services"
        }
    ],
    "sg:phone":"+44 1453 835904",
    "sg:postcode":"GL6 0PT",
    "sg:province":"Gloucestershire",
    "sg:tags":[
        "home"
    ],
    "wof:name":"Priory Nursing Home The",
    "wof:placetype":"venue"
},
  "geometry": {"coordinates":[-2.234972,51.680328],"type":"Point"}
}