{
  "type": "Feature",
  "properties": {
    "iso:country":"GB",
    "sg:address":"21 Queen Street",
    "sg:city":"Dumfries",
    "sg:classifiers":[
        {
            "category":"Shopping",
            "subcategory":"Pets & Pet Supplies",
            "type":"Retail Goods"
        }
    ],
    "sg:postcode":"DG1 2JG",
    "sg:province":"Dumfries and Galloway",
    "wof:name":"Alec McCubbin",
    "wof:placetype":"venue"
},
  "geometry": {"coordinates":[-3.608162,55.068203],"type":"Point"}
}