{
  "type": "Feature",
  "properties": {
    "iso:country":"GB",
    "sg:address":"6 Woodside Crescent",
    "sg:city":"Glasgow",
    "sg:classifiers":[
        {
            "category":"Banks & Credit Unions",
            "subcategory":"Financial Services",
            "type":"Services"
        }
    ],
    "sg:phone":"+44 141 332 3113",
    "sg:postcode":"G3 7UL",
    "sg:province":"Glasgow City",
    "sg:tags":[
        "adviser",
        "independent",
        "consultant"
    ],
    "sg:website":"http://www.finesco.co.uk",
    "wof:name":"Finesco Financial Services Ltd",
    "wof:placetype":"venue"
},
  "geometry": {"coordinates":[-4.272173,55.867104],"type":"Point"}
}