{
  "type": "Feature",
  "properties": {
    "addr:full":"768 Fulham Rd Fulham Greater London SW6 5SJ",
    "addr:housenumber":"768",
    "addr:postcode":"sw6 5sj",
    "addr:street":"Fulham Rd",
    "iso:country":"GB",
    "sg:address":"768 Fulham Rd",
    "sg:city":"Fulham",
    "sg:classifiers":[
        {
            "category":"Personal",
            "type":"Services"
        }
    ],
    "sg:phone":"+44 20 7384 1684",
    "sg:postcode":"SW6 5SJ",
    "sg:province":"Greater London",
    "sg:tags":[
        "wedding"
    ],
    "wof:name":"Secret Garden",
    "wof:placetype":"venue"
},
  "geometry": {"coordinates":[-0.2101799995,51.4723396301],"type":"Point"}
}