{
  "type": "Feature",
  "properties": {
    "addr:full":"Bridge Mill, Cowan Bridge Carnforth Cumbria LA6 2HS",
    "addr:postcode":"la6 2hs",
    "addr:street":"Bridge Mill Cowan Bridge",
    "iso:country":"GB",
    "sg:address":"Bridge Mill, Cowan Bridge",
    "sg:city":"Carnforth",
    "sg:classifiers":[
        {
            "category":"Shopping",
            "subcategory":"Clothing, Apparel, & Fashions",
            "type":"Retail Goods"
        }
    ],
    "sg:phone":"+44 15242 71071",
    "sg:postcode":"LA6 2HS",
    "sg:province":"Cumbria",
    "sg:tags":[
        "shop"
    ],
    "wof:name":"Jumpers Ltd.",
    "wof:placetype":"venue"
},
  "geometry": {"coordinates":[-2.559568882,54.182636261],"type":"Point"}
}