{
  "type": "Feature",
  "properties": {
    "addr:full":"Upcott Farm, Almeley Hereford Herefordshire HR3 6LA",
    "addr:housenumber":"almeley",
    "addr:postcode":"hr3 6la",
    "iso:country":"GB",
    "sg:address":"Upcott Farm, Almeley",
    "sg:city":"Hereford",
    "sg:classifiers":[
        {
            "category":"Farming",
            "subcategory":"Livestock Farm",
            "type":"Manufacturing & Wholesale Goods"
        }
    ],
    "sg:postcode":"HR3 6LA",
    "sg:province":"Herefordshire",
    "sg:tags":[
        "others"
    ],
    "wof:name":"E J Goodwin & Son",
    "wof:placetype":"venue"
},
  "geometry": {"coordinates":[-2.9763989449,52.1577606201],"type":"Point"}
}