{
  "type": "Feature",
  "properties": {
    "iso:country":"GB",
    "sg:address":"2 Arthur Green Av",
    "sg:city":"Nottingham",
    "sg:classifiers":[
        {
            "category":"Personal",
            "subcategory":"Psychics & Astrologers",
            "type":"Services"
        }
    ],
    "sg:phone":"+44 1623 750212",
    "sg:postcode":"NG17 9FY",
    "sg:province":"Nottinghamshire",
    "sg:tags":[
        "clairvoyant",
        "palmist"
    ],
    "wof:name":"Carol",
    "wof:placetype":"venue"
},
  "geometry": {"coordinates":[-1.268569,53.082752],"type":"Point"}
}