{
  "type": "Feature",
  "properties": {
    "addr:full":"Unit 3 Francis Ct, Burnt Mill Indust Est Harlow Essex CM20 2HS",
    "addr:housenumber":"unit 3",
    "addr:postcode":"cm20 2hs",
    "addr:street":"Francis Ct;Indust Est",
    "iso:country":"GB",
    "sg:address":"Unit 3 Francis Ct, Burnt Mill Indust Est",
    "sg:city":"Harlow",
    "sg:classifiers":[
        {
            "category":"Retail",
            "subcategory":"Auto Rental",
            "type":"Services"
        }
    ],
    "sg:phone":"+44 1279 442050",
    "sg:postcode":"CM20 2HS",
    "sg:province":"Essex",
    "sg:tags":[
        "truck",
        "hire",
        "van"
    ],
    "wof:name":"D I Y Van Hire",
    "wof:placetype":"venue"
},
  "geometry": {"coordinates":[0.0975060016,51.7731513977],"type":"Point"}
}