{
  "type": "Feature",
  "properties": {
    "addr:full":"Twitchell Lane, Aston Clinton Aylesbury Buckinghamshire HP22 5JJ",
    "addr:postcode":"hp22 5jj",
    "addr:street":"Twitchell Lane",
    "iso:country":"GB",
    "sg:address":"Twitchell Lane, Aston Clinton",
    "sg:city":"Aylesbury",
    "sg:classifiers":[
        {
            "category":"Education",
            "subcategory":"School",
            "type":"Public Place"
        },
        {
            "category":"Government",
            "subcategory":"Office",
            "type":"Public Place"
        }
    ],
    "sg:postcode":"HP22 5JJ",
    "sg:province":"Buckinghamshire",
    "sg:tags":[
        "local",
        "authority"
    ],
    "wof:name":"Aston Clinton County Combined School",
    "wof:placetype":"venue"
},
  "geometry": {"coordinates":[-0.7279189825,51.8008460999],"type":"Point"}
}