{
  "type": "Feature",
  "properties": {
    "addr:full":"Cairo Studios, 4 Nile Street London Greater London N1 7RF",
    "addr:housenumber":"4",
    "addr:postcode":"n1 7rf",
    "addr:street":"Nile Street",
    "iso:country":"GB",
    "sg:address":"Cairo Studios, 4 Nile Street",
    "sg:city":"London",
    "sg:classifiers":[
        {
            "category":"Communications",
            "type":"Services"
        }
    ],
    "sg:phone":"+44 20 7251 6966",
    "sg:postcode":"N1 7RF",
    "sg:province":"Greater London",
    "sg:tags":[
        "broadcasting"
    ],
    "wof:name":"Ricochet Films Ltd.",
    "wof:placetype":"venue"
},
  "geometry": {"coordinates":[-0.0912100002,51.5291213989],"type":"Point"}
}