{
  "type": "Feature",
  "properties": {
    "addr:full":"40 Couchmore Avenue Esher Surrey KT10 9AU",
    "addr:housenumber":"40",
    "addr:postcode":"kt10 9au",
    "addr:street":"Couchmore Avenue",
    "iso:country":"GB",
    "sg:address":"40 Couchmore Avenue",
    "sg:city":"Esher",
    "sg:classifiers":[
        {
            "category":"Professional",
            "subcategory":"Management & Consulting",
            "type":"Services"
        }
    ],
    "sg:phone":"+44 20 8339 0061",
    "sg:postcode":"KT10 9AU",
    "sg:province":"Surrey",
    "sg:tags":[
        "consultant",
        "business"
    ],
    "wof:name":"International Business Consultancy Ltd.",
    "wof:placetype":"venue"
},
  "geometry": {"coordinates":[-0.343946,51.378521],"type":"Point"}
}