{
  "type": "Feature",
  "properties": {
    "addr:full":"9a Mill Rd Saxmundham Suffolk IP17 1DP",
    "addr:housenumber":"9a",
    "addr:postcode":"ip17 1dp",
    "addr:street":"Mill Rd",
    "iso:country":"GB",
    "sg:address":"9a Mill Rd",
    "sg:city":"Saxmundham",
    "sg:classifiers":[
        {
            "category":"Autos & Motor Vehicles",
            "subcategory":"Auto Supplies",
            "type":"Retail Goods"
        }
    ],
    "sg:phone":"+44 1728 604487",
    "sg:postcode":"IP17 1DP",
    "sg:province":"Suffolk",
    "sg:tags":[
        "car",
        "component"
    ],
    "wof:name":"Interior Vehicle Curtains",
    "wof:placetype":"venue"
},
  "geometry": {"coordinates":[1.48857,52.214085],"type":"Point"}
}