{
  "type": "Feature",
  "properties": {
    "addr:full":"Drakes Drive Stevenage Hertfordshire SG2 0EY",
    "addr:postcode":"sg2 0ey",
    "addr:street":"Drakes Drive",
    "iso:country":"GB",
    "sg:address":"Drakes Drive",
    "sg:city":"Stevenage",
    "sg:classifiers":[
        {
            "category":"Health Services",
            "subcategory":"Nursing And Care Facility",
            "type":"Services"
        },
        {
            "category":"Social Services",
            "subcategory":"Retirement Home",
            "type":"Services"
        }
    ],
    "sg:phone":"+44 1438 354811",
    "sg:postcode":"SG2 0EY",
    "sg:province":"Hertfordshire",
    "sg:tags":[
        "residential"
    ],
    "wof:name":"Newhaven",
    "wof:placetype":"venue"
},
  "geometry": {"coordinates":[-0.175004,51.912403],"type":"Point"}
}