{
  "type": "Feature",
  "properties": {
    "iso:country":"GB",
    "sg:address":"3 Graham Cres, Cadishead",
    "sg:city":"Manchester",
    "sg:classifiers":[
        {
            "category":"Building & Trades",
            "subcategory":"Landscaping Services",
            "type":"Services"
        }
    ],
    "sg:phone":"+44 161 775 9761",
    "sg:postcode":"M44 5DU",
    "sg:province":"Greater Manchester",
    "sg:tags":[
        "landscape",
        "contractor"
    ],
    "wof:name":"Utility Builders Ltd.",
    "wof:placetype":"venue"
},
  "geometry": {"coordinates":[-2.446755,53.419094],"type":"Point"}
}