{
  "type": "Feature",
  "properties": {
    "iso:country":"GB",
    "sg:address":"Orchard Place Business Centre, Orchard Place Farm, Comp Road",
    "sg:city":"Sevenoaks",
    "sg:classifiers":[
        {
            "category":"Manufacturing",
            "subcategory":"Metals",
            "type":"Manufacturing & Wholesale Goods"
        }
    ],
    "sg:phone":"+44 1732 886083",
    "sg:postcode":"TN15 8QX",
    "sg:province":"Kent",
    "sg:tags":[
        "steel",
        "fabricator",
        "erectors"
    ],
    "wof:name":"Oates & Maynard",
    "wof:placetype":"venue"
},
  "geometry": {"coordinates":[0.35046,51.287601],"type":"Point"}
}