{
  "type": "Feature",
  "properties": {
    "addr:full":"91 Maple Rd Surbiton Surrey KT6 4AW",
    "addr:housenumber":"91",
    "addr:postcode":"kt6 4aw",
    "addr:street":"Maple Rd",
    "iso:country":"GB",
    "sg:address":"91 Maple Rd",
    "sg:city":"Surbiton",
    "sg:classifiers":[
        {
            "category":"Professional",
            "subcategory":"Lawyer & Legal Services",
            "type":"Services"
        }
    ],
    "sg:phone":"+44 20 8390 8711",
    "sg:postcode":"KT6 4AW",
    "sg:province":"Surrey",
    "sg:tags":[
        "solicitor"
    ],
    "wof:name":"Thompson Bowers",
    "wof:placetype":"venue"
},
  "geometry": {"coordinates":[-0.30764,51.395233],"type":"Point"}
}