{
  "type": "Feature",
  "properties": {
    "addr:full":"175 Clarence Street Kingston-upon-thames Greater London KT1 1QT",
    "addr:housenumber":"175",
    "addr:postcode":"kt1 1qt",
    "addr:street":"Clarence Street",
    "iso:country":"GB",
    "sg:address":"175 Clarence Street",
    "sg:city":"Kingston-upon-thames",
    "sg:classifiers":[
        {
            "category":"Shopping",
            "subcategory":"Pharmacy",
            "type":"Retail Goods"
        }
    ],
    "sg:phone":"+44 20 8546 2793",
    "sg:postcode":"KT1 1QT",
    "sg:province":"Greater London",
    "sg:tags":[
        "store",
        "drug"
    ],
    "wof:name":"Superdrug",
    "wof:placetype":"venue"
},
  "geometry": {"coordinates":[-0.3009389937,51.4121322632],"type":"Point"}
}