{
  "type": "Feature",
  "properties": {
    "addr:full":"5 Premier Industrial Estate, Leys Road, Brockmoor Brierley Hill West Midlands DY5 3UP",
    "addr:housenumber":"5",
    "addr:postcode":"dy5 3up",
    "addr:street":"Premier Industrial Estate Leys Road Brockmoor Brierley Hill",
    "iso:country":"GB",
    "sg:address":"5 Premier Industrial Estate, Leys Road, Brockmoor",
    "sg:city":"Brierley Hill",
    "sg:classifiers":[
        {
            "category":"Shopping",
            "subcategory":"Computers & Home Electronics",
            "type":"Retail Goods"
        },
        {
            "category":"Home & Garden",
            "subcategory":"Furniture",
            "type":"Retail Goods"
        }
    ],
    "sg:phone":"+44 1384 76322",
    "sg:postcode":"DY5 3UP",
    "sg:province":"West Midlands",
    "wof:name":"Thistle Furniture",
    "wof:placetype":"venue"
},
  "geometry": {"coordinates":[-2.121301,52.482044],"type":"Point"}
}