{
  "type": "Feature",
  "properties": {
    "addr:full":"7 Middle Street Horsham West Sussex RH12 1NW",
    "addr:housenumber":"7",
    "addr:postcode":"rh12 1nw",
    "addr:street":"Middle Street",
    "iso:country":"GB",
    "sg:address":"7 Middle Street",
    "sg:city":"Horsham",
    "sg:classifiers":[
        {
            "category":"Fast Food",
            "type":"Food & Drink"
        }
    ],
    "sg:phone":"+44 1403 217753",
    "sg:postcode":"RH12 1NW",
    "sg:province":"West Sussex",
    "sg:tags":[
        "away",
        "take"
    ],
    "wof:name":"Options Sandwich Bar & Take Away",
    "wof:placetype":"venue"
},
  "geometry": {"coordinates":[-0.3285290003,51.0623855591],"type":"Point"}
}