{
  "type": "Feature",
  "properties": {
    "addr:full":"51 Fairies Rd Perth Perth and Kinross PH1 1LZ",
    "addr:housenumber":"51",
    "addr:postcode":"ph1 1lz",
    "addr:street":"Fairies Rd",
    "iso:country":"GB",
    "sg:address":"51 Fairies Rd",
    "sg:city":"Perth",
    "sg:classifiers":[
        {
            "category":"Health Services",
            "subcategory":"Nursing And Care Facility",
            "type":"Services"
        },
        {
            "category":"Social Services",
            "subcategory":"Retirement Home",
            "type":"Services"
        }
    ],
    "sg:phone":"+44 1738 639018",
    "sg:postcode":"PH1 1LZ",
    "sg:province":"Perth and Kinross",
    "sg:tags":[
        "residential"
    ],
    "wof:name":"Ark Brae",
    "wof:placetype":"venue"
},
  "geometry": {"coordinates":[-3.462831974,56.3964767456],"type":"Point"}
}