{
  "type": "Feature",
  "properties": {
    "addr:full":"112-114 Bloomfield Road Blackpool Lancashire FY1 6JW",
    "addr:housenumber":"112-114",
    "addr:postcode":"fy1 6jw",
    "addr:street":"Bloomfield Road",
    "iso:country":"GB",
    "sg:address":"112-114 Bloomfield Road",
    "sg:city":"Blackpool",
    "sg:classifiers":[
        {
            "category":"Travel",
            "subcategory":"Hotels & Motels",
            "type":"Entertainment"
        }
    ],
    "sg:phone":"+44 1253 344379",
    "sg:postcode":"FY1 6JW",
    "sg:province":"Lancashire",
    "wof:name":"The Concorde Hotel",
    "wof:placetype":"venue"
},
  "geometry": {"coordinates":[-3.0443150997,53.8042640686],"type":"Point"}
}