{
  "type": "Feature",
  "properties": {
    "iso:country":"GB",
    "sg:address":"37 Russell Square",
    "sg:city":"Brighton",
    "sg:classifiers":[
        {
            "category":"Travel",
            "subcategory":"Hotels & Motels",
            "type":"Entertainment"
        }
    ],
    "sg:phone":"+44 1273 326129",
    "sg:postcode":"BN1 2EF",
    "sg:province":"East Sussex",
    "sg:tags":[
        "house",
        "guest"
    ],
    "wof:name":"G P Lowis",
    "wof:placetype":"venue"
},
  "geometry": {"coordinates":[-0.148174,50.822758],"type":"Point"}
}