{
  "type": "Feature",
  "properties": {
    "addr:full":"50 Glantawe Park, Ystradgynlais Swansea Carmarthenshire SA9 1AE",
    "addr:housenumber":"50",
    "addr:postcode":"sa9 1ae",
    "addr:street":"Glantawe Park",
    "iso:country":"GB",
    "sg:address":"50 Glantawe Park, Ystradgynlais",
    "sg:city":"Swansea",
    "sg:classifiers":[
        {
            "category":"Farming",
            "subcategory":"Dairy Farm",
            "type":"Manufacturing & Wholesale Goods"
        }
    ],
    "sg:postcode":"SA9 1AE",
    "sg:province":"Carmarthenshire",
    "wof:name":"Jeffrey Lewis",
    "wof:placetype":"venue"
},
  "geometry": {"coordinates":[-3.7761690617,51.7670593262],"type":"Point"}
}