{
  "type": "Feature",
  "properties": {
    "iso:country":"GB",
    "sg:address":"2 Causeway Side, Linthwaite",
    "sg:city":"Huddersfield",
    "sg:classifiers":[
        {
            "category":"Personal",
            "subcategory":"Beauty Salon",
            "type":"Services"
        }
    ],
    "sg:postcode":"HD7 5NL",
    "sg:province":"West Yorkshire",
    "sg:tags":[
        "unisex",
        "hairdresser"
    ],
    "wof:name":"Sybil's",
    "wof:placetype":"venue"
},
  "geometry": {"coordinates":[-1.8564840555,53.6234817505],"type":"Point"}
}