{
  "type": "Feature",
  "properties": {
    "addr:full":"6 Starkie St Preston Lancashire PR1 3LU",
    "addr:housenumber":"6",
    "addr:postcode":"pr1 3lu",
    "addr:street":"Starkie St",
    "iso:country":"GB",
    "sg:address":"6 Starkie St",
    "sg:city":"Preston",
    "sg:classifiers":[
        {
            "category":"Professional",
            "subcategory":"Management & Consulting",
            "type":"Services"
        }
    ],
    "sg:postcode":"PR1 3LU",
    "sg:province":"Lancashire",
    "sg:tags":[
        "consultant"
    ],
    "wof:name":"Euro Connect 2000 Ltd",
    "wof:placetype":"venue"
},
  "geometry": {"coordinates":[-2.6998848915,53.7547683716],"type":"Point"}
}