{
  "type": "Feature",
  "properties": {
    "addr:full":"92 Holt Road Liverpool Merseyside L7 2PR",
    "addr:housenumber":"92",
    "addr:postcode":"l7 2pr",
    "addr:street":"Holt Road",
    "iso:country":"GB",
    "sg:address":"92 Holt Road",
    "sg:city":"Liverpool",
    "sg:classifiers":[
        {
            "category":"Shopping",
            "subcategory":"Clothing, Apparel, & Fashions",
            "type":"Retail Goods"
        }
    ],
    "sg:postcode":"L7 2PR",
    "sg:province":"Merseyside",
    "sg:tags":[
        "shop"
    ],
    "wof:name":"Syhlet Fashions",
    "wof:placetype":"venue"
},
  "geometry": {"coordinates":[-2.9482080936,53.4094734192],"type":"Point"}
}