{
  "type": "Feature",
  "properties": {
    "addr:full":"106 Ashton Road East, Failsworth Manchester Lancashire M35 9PR",
    "addr:housenumber":"106",
    "addr:postcode":"m35 9pr",
    "addr:street":"Ashton Road East",
    "iso:country":"GB",
    "sg:address":"106 Ashton Road East, Failsworth",
    "sg:city":"Manchester",
    "sg:classifiers":[
        {
            "category":"Real Estate",
            "subcategory":"Real Estate Agent",
            "type":"Services"
        }
    ],
    "sg:postcode":"M35 9PR",
    "sg:province":"Lancashire",
    "wof:name":"Macdonald & Son",
    "wof:placetype":"venue"
},
  "geometry": {"coordinates":[-2.1499021053,53.5104484558],"type":"Point"}
}