{
  "type": "Feature",
  "properties": {
    "iso:country":"GB",
    "sg:address":"Unit B12 Moss Indust Est, St Helens Rd",
    "sg:city":"Leigh",
    "sg:classifiers":[
        {
            "category":"Building & Trades",
            "subcategory":"Equipment Rental",
            "type":"Services"
        }
    ],
    "sg:phone":"+44 1942 261911",
    "sg:postcode":"WN7 3PT",
    "sg:province":"Lancashire",
    "sg:tags":[
        "hire",
        "centre"
    ],
    "wof:name":"M & I Plant Services Ltd",
    "wof:placetype":"venue"
},
  "geometry": {"coordinates":[-2.5425860882,53.4787826538],"type":"Point"}
}