{
  "type": "Feature",
  "properties": {
    "addr:full":"425 Finchampstead Rd, Finchampstead Wokingham Berkshire RG40 3RL",
    "addr:housenumber":"425",
    "addr:postcode":"rg40 3rl",
    "addr:street":"Finchampstead Rd",
    "iso:country":"GB",
    "sg:address":"425 Finchampstead Rd, Finchampstead",
    "sg:city":"Wokingham",
    "sg:classifiers":[
        {
            "category":"Food & Beverages",
            "subcategory":"Meat & Fish",
            "type":"Retail Goods"
        }
    ],
    "sg:phone":"+44 118 973 3761",
    "sg:postcode":"RG40 3RL",
    "sg:province":"Berkshire",
    "sg:tags":[
        "chip"
    ],
    "wof:name":"Bob's Fish & Chip Bar",
    "wof:placetype":"venue"
},
  "geometry": {"coordinates":[-0.8559039831,51.3773498535],"type":"Point"}
}