{
  "type": "Feature",
  "properties": {
    "addr:full":"Brickendon Bury Hertford Hertfordshire SG13 8NP",
    "addr:postcode":"sg13 8np",
    "addr:street":"Brickendon;Hertford",
    "iso:country":"GB",
    "sg:address":"Brickendon Bury",
    "sg:city":"Hertford",
    "sg:classifiers":[
        {
            "category":"Government",
            "subcategory":"Post Office",
            "type":"Public Place"
        }
    ],
    "sg:phone":"+44 1992 535188",
    "sg:postcode":"SG13 8NP",
    "sg:province":"Hertfordshire",
    "sg:tags":[
        "window",
        "display",
        "dressing"
    ],
    "wof:name":"Warway Promotions",
    "wof:placetype":"venue"
},
  "geometry": {"coordinates":[-0.084236,51.755196],"type":"Point"}
}