{
  "type": "Feature",
  "properties": {
    "addr:full":"4 High St Sandown Isle of Wight PO36 8DA",
    "addr:housenumber":"4",
    "addr:postcode":"po36 8da",
    "addr:street":"High St",
    "iso:country":"GB",
    "sg:address":"4 High St",
    "sg:city":"Sandown",
    "sg:classifiers":[
        {
            "category":"Shopping",
            "subcategory":"Gifts & Souvenirs",
            "type":"Retail Goods"
        }
    ],
    "sg:postcode":"PO36 8DA",
    "sg:province":"Isle of Wight",
    "sg:tags":[
        "shop"
    ],
    "wof:name":"Haywood,J,",
    "wof:placetype":"venue"
},
  "geometry": {"coordinates":[-1.155518,50.653702],"type":"Point"}
}