{
  "type": "Feature",
  "properties": {
    "addr:full":"26 Ida Road Skegness Lincolnshire PE25 2AR",
    "addr:housenumber":"26",
    "addr:postcode":"pe25 2ar",
    "addr:street":"Ida Road",
    "iso:country":"GB",
    "sg:address":"26 Ida Road",
    "sg:city":"Skegness",
    "sg:classifiers":[
        {
            "category":"Health Services",
            "subcategory":"Optometrist",
            "type":"Services"
        }
    ],
    "sg:postcode":"PE25 2AR",
    "sg:province":"Lincolnshire",
    "sg:tags":[
        "optician"
    ],
    "wof:name":"Peach Jane Opticians",
    "wof:placetype":"venue"
},
  "geometry": {"coordinates":[0.339596,53.144936],"type":"Point"}
}