{
  "type": "Feature",
  "properties": {
    "iso:country":"GB",
    "sg:address":"26 Ida Road",
    "sg:city":"Skegness",
    "sg:classifiers":[
        {
            "category":"Health Services",
            "subcategory":"Optometrist",
            "type":"Services"
        }
    ],
    "sg:postcode":"PE25 2AR",
    "sg:province":"Lincolnshire",
    "sg:tags":[
        "optician"
    ],
    "wof:name":"Peach Jane Opticians",
    "wof:placetype":"venue"
},
  "geometry": {"coordinates":[0.339596,53.144936],"type":"Point"}
}