{
  "type": "Feature",
  "properties": {
    "addr:full":"Garlandhayes Farm Cullompton Devon EX15 1SB",
    "addr:housenumber":"cullompton",
    "addr:postcode":"ex15 1sb",
    "addr:street":"Devon",
    "iso:country":"GB",
    "sg:address":"Garlandhayes Farm",
    "sg:city":"Cullompton",
    "sg:classifiers":[
        {
            "category":"Home & Garden",
            "subcategory":"Garden Supply",
            "type":"Retail Goods"
        },
        {
            "category":"Farming",
            "subcategory":"Livestock Farm",
            "type":"Manufacturing & Wholesale Goods"
        }
    ],
    "sg:phone":"+44 1392 881262",
    "sg:postcode":"EX15 1SB",
    "sg:province":"Devon",
    "sg:tags":[
        "bulb",
        "grower",
        "others"
    ],
    "wof:name":"Stephen J Casely",
    "wof:placetype":"venue"
},
  "geometry": {"coordinates":[-3.3926339149,50.858165741],"type":"Point"}
}