{
  "type": "Feature",
  "properties": {
    "addr:full":"Branthill Farms Wells-next-the-sea Norfolk NR23 1SB",
    "addr:postcode":"nr23 1sb",
    "addr:street":"Wells-Next-The-Sea",
    "iso:country":"GB",
    "sg:address":"Branthill Farms",
    "sg:city":"Wells-next-the-sea",
    "sg:classifiers":[
        {
            "category":"Farming",
            "subcategory":"Crops",
            "type":"Manufacturing & Wholesale Goods"
        },
        {
            "category":"Farming",
            "subcategory":"Livestock Farm",
            "type":"Manufacturing & Wholesale Goods"
        }
    ],
    "sg:phone":"+44 1328 710246",
    "sg:postcode":"NR23 1SB",
    "sg:province":"Norfolk",
    "sg:tags":[
        "arable",
        "others"
    ],
    "wof:name":"Branthill Farms Ltd",
    "wof:placetype":"venue"
},
  "geometry": {"coordinates":[0.85581,52.952644],"type":"Point"}
}