{
  "type": "Feature",
  "properties": {
    "iso:country":"GB",
    "sg:address":"1569 Stratford Road, Hall Grn",
    "sg:city":"Birmingham",
    "sg:classifiers":[
        {
            "category":"Shopping",
            "subcategory":"Clothing, Apparel, & Fashions",
            "type":"Retail Goods"
        }
    ],
    "sg:phone":"+44 121 745 3545",
    "sg:postcode":"B28 9JA",
    "sg:province":"West Midlands",
    "sg:tags":[
        "menswear"
    ],
    "wof:name":"Tony James",
    "wof:placetype":"venue"
},
  "geometry": {"coordinates":[-1.8355569839,52.4210777283],"type":"Point"}
}