{
  "type": "Feature",
  "properties": {
    "addr:full":"Spencer House, 23 Sheen Road Richmond Greater London TW9 1BN",
    "addr:housenumber":"23",
    "addr:postcode":"tw9 1bn",
    "addr:street":"Sheen Road",
    "iso:country":"GB",
    "sg:address":"Spencer House, 23 Sheen Road",
    "sg:city":"Richmond",
    "sg:classifiers":[
        {
            "category":"Education",
            "subcategory":"Special Training",
            "type":"Public Place"
        }
    ],
    "sg:phone":"+44 20 8322 4000",
    "sg:postcode":"TW9 1BN",
    "sg:province":"Greater London",
    "sg:tags":[
        "product",
        "centre"
    ],
    "wof:name":"Achieve Learning (U K) Ltd.",
    "wof:placetype":"venue"
},
  "geometry": {"coordinates":[-0.301684,51.461151],"type":"Point"}
}