{
  "type": "Feature",
  "properties": {
    "addr:full":"32 Warwick Road, Radcliffe Manchester Greater Manchester M26 4HL",
    "addr:housenumber":"32",
    "addr:postcode":"m26 4hl",
    "addr:street":"Warwick Road",
    "iso:country":"GB",
    "sg:address":"32 Warwick Road, Radcliffe",
    "sg:city":"Manchester",
    "sg:classifiers":[
        {
            "category":"Building & Trades",
            "subcategory":"Construction",
            "type":"Services"
        }
    ],
    "sg:phone":"+44 161 723 3787",
    "sg:postcode":"M26 4HL",
    "sg:province":"Greater Manchester",
    "sg:tags":[
        "builder"
    ],
    "wof:name":"G & W Building (Bolton) Ltd.",
    "wof:placetype":"venue"
},
  "geometry": {"coordinates":[-2.3350338936,53.5734596252],"type":"Point"}
}