{
  "type": "Feature",
  "properties": {
    "addr:full":"King Richard Court, Wootton Brook Close Northampton Northamptonshire NN4 0XU",
    "addr:postcode":"nn4 0xu",
    "addr:street":"King Richard Court;Brook Close",
    "iso:country":"GB",
    "sg:address":"King Richard Court, Wootton Brook Close",
    "sg:city":"Northampton",
    "sg:classifiers":[
        {
            "category":"Social Services",
            "subcategory":"Adult Care",
            "type":"Services"
        },
        {
            "category":"Social Services",
            "subcategory":"Retirement Home",
            "type":"Services"
        }
    ],
    "sg:phone":"+44 1604 708014",
    "sg:postcode":"NN4 0XU",
    "sg:province":"Northamptonshire",
    "sg:tags":[
        "housing",
        "sheltered",
        "accommodation"
    ],
    "wof:name":"King Richard Court",
    "wof:placetype":"venue"
},
  "geometry": {"coordinates":[-0.9007340074,52.2048454285],"type":"Point"}
}