{
  "type": "Feature",
  "properties": {
    "iso:country":"GB",
    "sg:address":"Bullhouse Mill, Lee Lane, Penistone",
    "sg:city":"Sheffield",
    "sg:classifiers":[
        {
            "category":"Recreation",
            "subcategory":"Fishing",
            "type":"Entertainment"
        }
    ],
    "sg:phone":"+44 1226 370224",
    "sg:postcode":"S36 9NN",
    "sg:province":"South Yorkshire",
    "sg:tags":[
        "equipment",
        "angling"
    ],
    "wof:name":"Awnhaven Ltd.",
    "wof:placetype":"venue"
},
  "geometry": {"coordinates":[-1.680191,53.520504],"type":"Point"}
}