{
  "type": "Feature",
  "properties": {
    "iso:country":"GB",
    "sg:address":"29 Elgar Ave, Tolworth",
    "sg:city":"Surbiton",
    "sg:classifiers":[
        {
            "category":"Professional",
            "subcategory":"Art Services",
            "type":"Services"
        }
    ],
    "sg:phone":"+44 20 8390 7204",
    "sg:postcode":"KT5 9JH",
    "sg:province":"Surrey",
    "sg:tags":[
        "photographer"
    ],
    "wof:name":"Jones,Marion,",
    "wof:placetype":"venue"
},
  "geometry": {"coordinates":[-0.282927,51.384323],"type":"Point"}
}