{
  "type": "Feature",
  "properties": {
    "iso:country":"GB",
    "sg:address":"West Marsh Lane, Barrow Haven",
    "sg:city":"Barrow-upon-humber",
    "sg:classifiers":[
        {
            "category":"Autos & Motor Vehicles",
            "subcategory":"Motorcycle Sales",
            "type":"Retail Goods"
        }
    ],
    "sg:phone":"+44 1469 532600",
    "sg:postcode":"DN19 7HA",
    "sg:province":"Lincolnshire",
    "sg:tags":[
        "scooter",
        "cycle"
    ],
    "wof:name":"Haven Trials Sport",
    "wof:placetype":"venue"
},
  "geometry": {"coordinates":[-0.402279,53.695259],"type":"Point"}
}