{
  "type": "Feature",
  "properties": {
    "addr:full":"84 King Edward Street Macclesfield Cheshire SK10 1AT",
    "addr:housenumber":"84",
    "addr:postcode":"sk10 1at",
    "addr:street":"King Edward Street",
    "iso:country":"GB",
    "sg:address":"84 King Edward Street",
    "sg:city":"Macclesfield",
    "sg:classifiers":[
        {
            "category":"Personal",
            "subcategory":"Beauty Salon",
            "type":"Services"
        }
    ],
    "sg:phone":"+44 1625 428307",
    "sg:postcode":"SK10 1AT",
    "sg:province":"Cheshire",
    "sg:tags":[
        "lady",
        "hairdresser"
    ],
    "wof:name":"Twiggy",
    "wof:placetype":"venue"
},
  "geometry": {"coordinates":[-2.1314949989,53.2609825134],"type":"Point"}
}