{
  "type": "Feature",
  "properties": {
    "addr:full":"Highfields Farm, Fenny Bentley Ashbourne Derbyshire DE6 1LE",
    "addr:postcode":"de6 1le",
    "iso:country":"GB",
    "sg:address":"Highfields Farm, Fenny Bentley",
    "sg:city":"Ashbourne",
    "sg:classifiers":[
        {
            "category":"Recreation",
            "subcategory":"Campground",
            "type":"Entertainment"
        }
    ],
    "sg:phone":"+44 1335 350228",
    "sg:postcode":"DE6 1LE",
    "sg:province":"Derbyshire",
    "sg:tags":[
        "site",
        "camping"
    ],
    "wof:name":"Highfields Farm Caravan & Camping Park",
    "wof:placetype":"venue"
},
  "geometry": {"coordinates":[-1.7325639725,53.0182800293],"type":"Point"}
}