{
  "type": "Feature",
  "properties": {
    "iso:country":"GB",
    "sg:address":"62 Leighswood Road",
    "sg:city":"Walsall",
    "sg:classifiers":[
        {
            "category":"Fast Food",
            "type":"Food & Drink"
        }
    ],
    "sg:phone":"+44 1922 455540",
    "sg:postcode":"WS9 8AW",
    "sg:province":"Staffordshire",
    "sg:tags":[
        "away",
        "take"
    ],
    "wof:name":"The Corner Stores",
    "wof:placetype":"venue"
},
  "geometry": {"coordinates":[-1.922614,52.606731],"type":"Point"}
}