{
  "type": "Feature",
  "properties": {
    "addr:full":"47 High St Hinton St. George Somerset TA17 8SE",
    "addr:housenumber":"47",
    "addr:postcode":"ta17 8se",
    "addr:street":"High St",
    "iso:country":"GB",
    "sg:address":"47 High St",
    "sg:city":"Hinton St. George",
    "sg:classifiers":[
        {
            "category":"Farming",
            "subcategory":"Dairy Farm",
            "type":"Manufacturing & Wholesale Goods"
        }
    ],
    "sg:phone":"+44 1460 72706",
    "sg:postcode":"TA17 8SE",
    "sg:province":"Somerset",
    "wof:name":"The Personal Service Stores",
    "wof:placetype":"venue"
},
  "geometry": {"coordinates":[-2.824655056,50.9100914001],"type":"Point"}
}