{
  "type": "Feature",
  "properties": {
    "addr:full":"24 Bank Street Ossett West Yorkshire WF5 8NL",
    "addr:housenumber":"24",
    "addr:postcode":"wf5 8nl",
    "addr:street":"Bank Street",
    "iso:country":"GB",
    "sg:address":"24 Bank Street",
    "sg:city":"Ossett",
    "sg:classifiers":[
        {
            "category":"Shopping",
            "subcategory":"News",
            "type":"Retail Goods"
        }
    ],
    "sg:postcode":"WF5 8NL",
    "sg:province":"West Yorkshire",
    "sg:tags":[
        "newsagent"
    ],
    "wof:name":"Newscentre",
    "wof:placetype":"venue"
},
  "geometry": {"coordinates":[-1.581138,53.67852],"type":"Point"}
}