{
  "type": "Feature",
  "properties": {
    "iso:country":"GB",
    "sg:address":"61 Hannah Street",
    "sg:city":"Porth",
    "sg:classifiers":[
        {
            "category":"Food & Beverages",
            "subcategory":"Fruits & Vegetables",
            "type":"Retail Goods"
        }
    ],
    "sg:postcode":"CF39 9RA",
    "sg:province":"Bridgend",
    "sg:tags":[
        "greengrocer"
    ],
    "wof:name":"Norman Jones",
    "wof:placetype":"venue"
},
  "geometry": {"coordinates":[-3.4059450626,51.610824585],"type":"Point"}
}