{
  "type": "Feature",
  "properties": {
    "addr:full":"Basement Warehouse, Rear Of 114 High Street Herne Bay Kent CT6 5JY",
    "addr:housenumber":"114",
    "addr:postcode":"ct6 5jy",
    "addr:street":"High Street",
    "iso:country":"GB",
    "sg:address":"Basement Warehouse, Rear Of 114 High Street",
    "sg:city":"Herne Bay",
    "sg:classifiers":[
        {
            "category":"Shopping",
            "subcategory":"Discount & Variety Stores",
            "type":"Retail Goods"
        }
    ],
    "sg:phone":"+44 1843 864087",
    "sg:postcode":"CT6 5JY",
    "sg:province":"Kent",
    "sg:tags":[
        "cleaning",
        "supply"
    ],
    "wof:name":"Total Supplies Ltd.",
    "wof:placetype":"venue"
},
  "geometry": {"coordinates":[1.1251000166,51.3712158203],"type":"Point"}
}