{
  "type": "Feature",
  "properties": {
    "iso:country":"GB",
    "sg:address":"The Town House, Betson Street, Markinch",
    "sg:city":"Glenrothes",
    "sg:classifiers":[
        {
            "category":"Community Center",
            "subcategory":"Youth",
            "type":"Public Place"
        }
    ],
    "sg:phone":"+44 1592 756447",
    "sg:postcode":"KY7 6AA",
    "sg:province":"Fife",
    "sg:tags":[
        "organisation",
        "centre"
    ],
    "wof:name":"Youth First",
    "wof:placetype":"venue"
},
  "geometry": {"coordinates":[-3.1346890926,56.2037315369],"type":"Point"}
}