{
  "type": "Feature",
  "properties": {
    "addr:full":"15-17 Canal Street Paisley Renfrewshire PA1 2HD",
    "addr:housenumber":"15-17",
    "addr:postcode":"pa1 2hd",
    "addr:street":"Canal Street",
    "iso:country":"GB",
    "sg:address":"15-17 Canal Street",
    "sg:city":"Paisley",
    "sg:classifiers":[
        {
            "category":"Bars & Pubs",
            "type":"Food & Drink"
        },
        {
            "category":"Community Center",
            "subcategory":"Social",
            "type":"Public Place"
        }
    ],
    "sg:phone":"+44 141 842 8970",
    "sg:postcode":"PA1 2HD",
    "sg:province":"Renfrewshire",
    "sg:tags":[
        "pubs",
        "house",
        "inn",
        "activity"
    ],
    "wof:name":"Tennants Taverns",
    "wof:placetype":"venue"
},
  "geometry": {"coordinates":[-4.425842762,55.8413238525],"type":"Point"}
}