{
  "type": "Feature",
  "properties": {
    "iso:country":"GB",
    "sg:address":"193 Sparrows Herne",
    "sg:city":"Bushey",
    "sg:classifiers":[
        {
            "category":"Organizations",
            "subcategory":"Membership Organization",
            "type":"Services"
        }
    ],
    "sg:postcode":"WD2 1AJ",
    "sg:province":"Hertfordshire",
    "sg:tags":[
        "club"
    ],
    "wof:name":"Two Avenue Road Ltd",
    "wof:placetype":"venue"
},
  "geometry": {"coordinates":[-0.3478620052,51.6371383667],"type":"Point"}
}