{
  "type": "Feature",
  "properties": {
    "addr:full":"1, Pine Lodge, Craine Close Liverpool Merseyside L4 7XT",
    "addr:housenumber":"1",
    "addr:postcode":"l4 7xt",
    "addr:street":"Craine Close",
    "iso:country":"GB",
    "sg:address":"1, Pine Lodge, Craine Close",
    "sg:city":"Liverpool",
    "sg:classifiers":[
        {
            "category":"Social Services",
            "subcategory":"Adult Care",
            "type":"Services"
        },
        {
            "category":"Social Services",
            "subcategory":"Retirement Home",
            "type":"Services"
        }
    ],
    "sg:phone":"+44 151 260 4144",
    "sg:postcode":"L4 7XT",
    "sg:province":"Merseyside",
    "sg:tags":[
        "housing",
        "sheltered",
        "accommodation"
    ],
    "wof:name":"Pine Lodge",
    "wof:placetype":"venue"
},
  "geometry": {"coordinates":[-2.9505939484,53.4387512207],"type":"Point"}
}