{
  "type": "Feature",
  "properties": {
    "iso:country":"GB",
    "sg:address":"Broomfields, Courtlands",
    "sg:city":"Uckfield",
    "sg:classifiers":[
        {
            "category":"Professional",
            "subcategory":"Employment Agencies",
            "type":"Services"
        }
    ],
    "sg:phone":"+44 1825 713369",
    "sg:postcode":"TN22 3LS",
    "sg:province":"East Sussex",
    "sg:tags":[
        "agricultural",
        "advice"
    ],
    "wof:name":"Heathfield Agricultural Show Society",
    "wof:placetype":"venue"
},
  "geometry": {"coordinates":[0.0966499969,50.9718132019],"type":"Point"}
}