{
  "type": "Feature",
  "properties": {
    "iso:country":"GB",
    "sg:address":"36 Treforthlan, Paynters Lane End",
    "sg:city":"Redruth",
    "sg:classifiers":[
        {
            "category":"Professional",
            "subcategory":"Engineering",
            "type":"Services"
        }
    ],
    "sg:phone":"+44 1209 842661",
    "sg:postcode":"TR16 4RN",
    "sg:province":"Cornwall",
    "sg:tags":[
        "design",
        "engineer"
    ],
    "wof:name":"Design Technical Services",
    "wof:placetype":"venue"
},
  "geometry": {"coordinates":[-5.26621,50.24369],"type":"Point"}
}