{
  "type": "Feature",
  "properties": {
    "iso:country":"GB",
    "sg:address":"St. Michaels Gate Ho, High St",
    "sg:city":"Lincoln",
    "sg:classifiers":[
        {
            "category":"Social Services",
            "subcategory":"Adult Care",
            "type":"Services"
        }
    ],
    "sg:phone":"+44 1522 722209",
    "sg:postcode":"LN5 9RF",
    "sg:province":"Lincolnshire",
    "sg:tags":[
        "housing",
        "sheltered"
    ],
    "wof:name":"Bailfarm Sheltered Homes Ltd",
    "wof:placetype":"venue"
},
  "geometry": {"coordinates":[-0.541183,53.16473],"type":"Point"}
}