{
  "type": "Feature",
  "properties": {
    "addr:full":"Vine Cottage, Briars Brook Ormskirk Lancashire L40 5XD",
    "addr:postcode":"l40 5xd",
    "addr:street":"Briars Brook Ormskirk",
    "iso:country":"GB",
    "sg:address":"Vine Cottage, Briars Brook",
    "sg:city":"Ormskirk",
    "sg:classifiers":[
        {
            "category":"Real Estate",
            "subcategory":"Architect",
            "type":"Services"
        }
    ],
    "sg:phone":"+44 1704 892182",
    "sg:postcode":"L40 5XD",
    "sg:province":"Lancashire",
    "wof:name":"William Woodward Architect",
    "wof:placetype":"venue"
},
  "geometry": {"coordinates":[-2.825579,53.592716],"type":"Point"}
}