{
  "type": "Feature",
  "properties": {
    "iso:country":"GB",
    "sg:address":"25 Forty Lane",
    "sg:city":"Wembley",
    "sg:classifiers":[
        {
            "category":"Communications",
            "subcategory":"Film & Video Production",
            "type":"Services"
        }
    ],
    "sg:phone":"+44 20 8908 3398",
    "sg:postcode":"HA9 9EU",
    "sg:province":"Greater London",
    "sg:tags":[
        "tv"
    ],
    "wof:name":"Palmer Wholesale",
    "wof:placetype":"venue"
},
  "geometry": {"coordinates":[-0.2690609992,51.5656700134],"type":"Point"}
}