{
  "type": "Feature",
  "properties": {
    "addr:full":"517 Oxford Road Reading Berkshire RG30 1HF",
    "addr:housenumber":"517",
    "addr:postcode":"rg30 1hf",
    "addr:street":"Oxford Road",
    "iso:country":"GB",
    "sg:address":"517 Oxford Road",
    "sg:city":"Reading",
    "sg:classifiers":[
        {
            "category":"Personal",
            "subcategory":"Beauty Salon",
            "type":"Services"
        }
    ],
    "sg:postcode":"RG30 1HF",
    "sg:province":"Berkshire",
    "sg:tags":[
        "unisex",
        "hairdresser"
    ],
    "wof:name":"Alfonso's",
    "wof:placetype":"venue"
},
  "geometry": {"coordinates":[-0.9990760088,51.4573249817],"type":"Point"}
}