{
  "type": "Feature",
  "properties": {
    "addr:full":"12 King St Nottingham Nottinghamshire NG1 2AS",
    "addr:housenumber":"12",
    "addr:postcode":"ng1 2as",
    "addr:street":"King St",
    "iso:country":"GB",
    "sg:address":"12 King St",
    "sg:city":"Nottingham",
    "sg:classifiers":[
        {
            "category":"Personal",
            "subcategory":"Beauty Salon",
            "type":"Services"
        }
    ],
    "sg:phone":"+44 115 947 2332",
    "sg:postcode":"NG1 2AS",
    "sg:province":"Nottinghamshire",
    "sg:tags":[
        "unisex",
        "hairdresser"
    ],
    "wof:name":"Keith Hall Salons",
    "wof:placetype":"venue"
},
  "geometry": {"coordinates":[-1.149346,52.954399],"type":"Point"}
}