{
  "type": "Feature",
  "properties": {
    "addr:full":"1st Class Company Services 72, New Bond Street, London Greater London W1S 1RR",
    "addr:housenumber":"72",
    "addr:postcode":"w1s 1rr",
    "addr:street":"New Bond Street",
    "iso:country":"GB",
    "sg:address":"1st Class Company Services 72, New Bond Street,",
    "sg:city":"London",
    "sg:classifiers":[
        {
            "category":"Professional",
            "subcategory":"Management & Consulting",
            "type":"Services"
        }
    ],
    "sg:postcode":"W1S 1RR",
    "sg:province":"Greater London",
    "sg:tags":[
        "consultant",
        "business"
    ],
    "wof:name":"Telesense Consulting Ltd",
    "wof:placetype":"venue"
},
  "geometry": {"coordinates":[-0.14444,51.512272],"type":"Point"}
}