{
  "type": "Feature",
  "properties": {
    "addr:full":"Greathouse, Swindon Rd Chippenham Wiltshire SN15 5NA",
    "addr:postcode":"sn15 5na",
    "addr:street":"Swindon Rd",
    "iso:country":"GB",
    "sg:address":"Greathouse, Swindon Rd",
    "sg:city":"Chippenham",
    "sg:classifiers":[
        {
            "category":"Health Services",
            "subcategory":"Nursing And Care Facility",
            "type":"Services"
        }
    ],
    "sg:phone":"+44 1249 750719",
    "sg:postcode":"SN15 5NA",
    "sg:province":"Wiltshire",
    "sg:tags":[
        "home"
    ],
    "wof:name":"Cheshire Foundation Homes",
    "wof:placetype":"venue"
},
  "geometry": {"coordinates":[-2.1194300652,51.4604415894],"type":"Point"}
}