{
  "type": "Feature",
  "properties": {
    "iso:country":"GB",
    "sg:address":"20 Linkfield Rd",
    "sg:city":"Musselburgh",
    "sg:classifiers":[
        {
            "category":"Building & Trades",
            "subcategory":"Construction",
            "type":"Services"
        }
    ],
    "sg:phone":"+44 131 665 4441",
    "sg:postcode":"EH21 7LQ",
    "sg:province":"City of Edinburgh",
    "sg:tags":[
        "builder"
    ],
    "wof:name":"A Pryde Construction",
    "wof:placetype":"venue"
},
  "geometry": {"coordinates":[-3.0430829525,55.9389724731],"type":"Point"}
}