{
  "type": "Feature",
  "properties": {
    "iso:country":"GB",
    "sg:address":"Hillfield Lane, Stretton",
    "sg:city":"Burton-on-trent",
    "sg:classifiers":[
        {
            "category":"Building & Trades",
            "subcategory":"Construction",
            "type":"Services"
        }
    ],
    "sg:phone":"+44 1525 244900",
    "sg:postcode":"DE13 0BP",
    "sg:province":"Derbyshire",
    "sg:tags":[
        "roofing"
    ],
    "wof:name":"Forticrete Ltd.",
    "wof:placetype":"venue"
},
  "geometry": {"coordinates":[-1.625126,52.83353],"type":"Point"}
}