{
  "type": "Feature",
  "properties": {
    "iso:country":"GB",
    "sg:address":"Unit 11 Old Station Yd",
    "sg:city":"Chesterfield",
    "sg:classifiers":[
        {
            "category":"Retail",
            "subcategory":"Auto Repair",
            "type":"Services"
        }
    ],
    "sg:postcode":"S43 1LS",
    "sg:province":"Derbyshire",
    "sg:tags":[
        "modification",
        "garage"
    ],
    "wof:name":"Garage Services by Rich & Walker",
    "wof:placetype":"venue"
},
  "geometry": {"coordinates":[-1.4112789631,53.2588615417],"type":"Point"}
}