{
  "type": "Feature",
  "properties": {
    "addr:full":"14 Coleman Road London Greater London SE5 7TG",
    "addr:housenumber":"14",
    "addr:postcode":"se5 7tg",
    "addr:street":"Coleman Road",
    "iso:country":"GB",
    "sg:address":"14 Coleman Road",
    "sg:city":"London",
    "sg:classifiers":[
        {
            "category":"Bars & Pubs",
            "type":"Food & Drink"
        }
    ],
    "sg:phone":"+44 20 7277 1790",
    "sg:postcode":"SE5 7TG",
    "sg:province":"Greater London",
    "sg:tags":[
        "pubs",
        "inn"
    ],
    "wof:name":"St. Georges Tavern",
    "wof:placetype":"venue"
},
  "geometry": {"coordinates":[-0.0852480009,51.4800643921],"type":"Point"}
}