{
  "type": "Feature",
  "properties": {
    "addr:full":"Ringway Road Moss Nook, Withenshaw Manchester Greater Manchester M22 5WF",
    "addr:postcode":"m22 5wf",
    "addr:street":"Ringway Road",
    "iso:country":"GB",
    "sg:address":"Ringway Road Moss Nook, Withenshaw",
    "sg:city":"Manchester",
    "sg:classifiers":[
        {
            "category":"Home & Garden",
            "subcategory":"Garden Supply",
            "type":"Retail Goods"
        }
    ],
    "sg:phone":"+44 161 437 1557",
    "sg:postcode":"M22 5WF",
    "sg:province":"Greater Manchester",
    "sg:tags":[
        "nursery",
        "centre"
    ],
    "wof:name":"PRIMROSE COTTAGE NURSERY & GARDEN CENTRE",
    "wof:placetype":"venue"
},
  "geometry": {"coordinates":[-2.250944,53.364929],"type":"Point"}
}