{
  "type": "Feature",
  "properties": {
    "addr:full":"29 Blacksmith Lane, Prestwood Great Missenden Buckinghamshire HP16 0NP",
    "addr:housenumber":"29",
    "addr:postcode":"hp16 0np",
    "addr:street":"Blacksmith Lane Prestwood",
    "iso:country":"GB",
    "sg:address":"29 Blacksmith Lane, Prestwood",
    "sg:city":"Great Missenden",
    "sg:classifiers":[
        {
            "category":"Manufacturing",
            "subcategory":"Glass & Minerals",
            "type":"Manufacturing & Wholesale Goods"
        }
    ],
    "sg:phone":"+44 1494 865231",
    "sg:postcode":"HP16 0NP",
    "sg:province":"Buckinghamshire",
    "sg:tags":[
        "mnfrs",
        "fibre",
        "glassware",
        "china",
        "mnfr"
    ],
    "wof:name":"Ceramic Restorations",
    "wof:placetype":"venue"
},
  "geometry": {"coordinates":[-0.737561,51.698112],"type":"Point"}
}