{
  "type": "Feature",
  "properties": {
    "addr:full":"88 Bewley Drive Liverpool Merseyside L32 6QJ",
    "addr:housenumber":"88",
    "addr:postcode":"l32 6qj",
    "addr:street":"Bewley Drive",
    "iso:country":"GB",
    "sg:address":"88 Bewley Drive",
    "sg:city":"Liverpool",
    "sg:classifiers":[
        {
            "category":"Shopping",
            "subcategory":"Florist",
            "type":"Retail Goods"
        }
    ],
    "sg:phone":"+44 151 545 0215",
    "sg:postcode":"L32 6QJ",
    "sg:province":"Merseyside",
    "wof:name":"Pats Florist",
    "wof:placetype":"venue"
},
  "geometry": {"coordinates":[-2.882324934,53.4708023071],"type":"Point"}
}