{
  "type": "Feature",
  "properties": {
    "iso:country":"GB",
    "sg:address":"46 High Street, Caister On Sea",
    "sg:city":"Great Yarmouth",
    "sg:classifiers":[
        {
            "category":"Shopping",
            "subcategory":"Pharmacy",
            "type":"Retail Goods"
        }
    ],
    "sg:phone":"+44 1493 720469",
    "sg:postcode":"NR30 5EP",
    "sg:province":"Norfolk",
    "sg:tags":[
        "pharmacist",
        "dispensing",
        "chemist"
    ],
    "wof:name":"Co-Op Pharmacy",
    "wof:placetype":"venue"
},
  "geometry": {"coordinates":[1.727992,52.647541],"type":"Point"}
}