{
  "type": "Feature",
  "properties": {
    "addr:full":"31b Factory Road Birmingham West Midlands B18 5LH",
    "addr:housenumber":"31b",
    "addr:postcode":"b18 5lh",
    "addr:street":"Factory Road",
    "iso:country":"GB",
    "sg:address":"31b Factory Road",
    "sg:city":"Birmingham",
    "sg:classifiers":[
        {
            "category":"Shopping",
            "subcategory":"Clothing, Apparel, & Fashions",
            "type":"Retail Goods"
        }
    ],
    "sg:phone":"+44 121 554 5642",
    "sg:postcode":"B18 5LH",
    "sg:province":"West Midlands",
    "sg:tags":[
        "leather",
        "garment"
    ],
    "wof:name":"K S B (Uk) Ltd.",
    "wof:placetype":"venue"
},
  "geometry": {"coordinates":[-1.9283560514,52.4983062744],"type":"Point"}
}