{
  "type": "Feature",
  "properties": {
    "iso:country":"GB",
    "sg:address":"The Bridle House, Bridle Path, Beddington",
    "sg:city":"Croydon",
    "sg:classifiers":[
        {
            "category":"Health Services",
            "subcategory":"Dentist",
            "type":"Services"
        }
    ],
    "sg:phone":"+44 20 8667 1595",
    "sg:postcode":"CR0 4SB",
    "sg:province":"Surrey",
    "sg:tags":[
        "technician",
        "dental"
    ],
    "wof:name":"MARTIN SEABOURNE",
    "wof:placetype":"venue"
},
  "geometry": {"coordinates":[-0.129282,51.36985],"type":"Point"}
}