{
  "type": "Feature",
  "properties": {
    "addr:full":"Breck Road Poulton-le-fylde Lancashire FY6 7AQ",
    "addr:postcode":"fy6 7aq",
    "addr:street":"Breck Road Poulton-Le-Fylde",
    "iso:country":"GB",
    "sg:address":"Breck Road",
    "sg:city":"Poulton-le-fylde",
    "sg:classifiers":[
        {
            "category":"Organizations",
            "subcategory":"Community Association",
            "type":"Services"
        },
        {
            "category":"Organizations",
            "subcategory":"Membership Organization",
            "type":"Services"
        }
    ],
    "sg:phone":"+44 1253 884897",
    "sg:postcode":"FY6 7AQ",
    "sg:province":"Lancashire",
    "sg:tags":[
        "club",
        "social"
    ],
    "wof:name":"ST JOHNS CATHOLIC CLUB & ASSEMBLY ROOMS",
    "wof:placetype":"venue"
},
  "geometry": {"coordinates":[-2.982228,53.856853],"type":"Point"}
}