{
  "type": "Feature",
  "properties": {
    "iso:country":"GB",
    "sg:address":"132 Liddell Way",
    "sg:city":"Ascot",
    "sg:classifiers":[
        {
            "category":"Organizations",
            "subcategory":"Religious Organization",
            "type":"Services"
        }
    ],
    "sg:phone":"+44 1344 628143",
    "sg:postcode":"SL5 9UZ",
    "sg:province":"Berkshire",
    "sg:tags":[
        "organisation",
        "place",
        "worship"
    ],
    "sg:website":"http://www.watchtower.org",
    "wof:name":"Jehovah's Witnesses",
    "wof:placetype":"venue"
},
  "geometry": {"coordinates":[-0.678786,51.402328],"type":"Point"}
}