{
  "type": "Feature",
  "properties": {
    "iso:country":"GB",
    "sg:address":"Wheler Road, Severn Stars Estate, Whitley",
    "sg:city":"Coventry",
    "sg:classifiers":[
        {
            "category":"Professional",
            "subcategory":"Computer Services",
            "type":"Services"
        }
    ],
    "sg:postcode":"CV3 4LG",
    "sg:province":"Warwickshire",
    "sg:tags":[
        "system",
        "software"
    ],
    "wof:name":"W B S Office Electronics Ltd.",
    "wof:placetype":"venue"
},
  "geometry": {"coordinates":[-1.4818450212,52.3945808411],"type":"Point"}
}