{
  "type": "Feature",
  "properties": {
    "iso:country":"GB",
    "sg:address":"28 Northcott Avenue",
    "sg:city":"Wood Green",
    "sg:classifiers":[
        {
            "category":"Building & Trades",
            "subcategory":"Construction",
            "type":"Services"
        }
    ],
    "sg:phone":"+44 20 8888 5974",
    "sg:postcode":"N22 7DB",
    "sg:province":"Greater London",
    "sg:tags":[
        "builder"
    ],
    "wof:name":"Jack Brown",
    "wof:placetype":"venue"
},
  "geometry": {"coordinates":[-0.1192729995,51.6015205383],"type":"Point"}
}