{
  "type": "Feature",
  "properties": {
    "addr:full":"13 Talgarth Road Manchester Greater Manchester M40 7QA",
    "addr:housenumber":"13",
    "addr:postcode":"m40 7qa",
    "addr:street":"Talgarth Road",
    "iso:country":"GB",
    "sg:address":"13 Talgarth Road",
    "sg:city":"Manchester",
    "sg:classifiers":[
        {
            "category":"Professional",
            "subcategory":"Printing & Photocopies",
            "type":"Services"
        }
    ],
    "sg:postcode":"M40 7QA",
    "sg:province":"Greater Manchester",
    "sg:tags":[
        "computer",
        "tag",
        "label"
    ],
    "wof:name":"Hindle Labels",
    "wof:placetype":"venue"
},
  "geometry": {"coordinates":[-2.224352,53.494293],"type":"Point"}
}