{
  "type": "Feature",
  "properties": {
    "iso:country":"GB",
    "sg:address":"327a Wellingborough Road",
    "sg:city":"Northampton",
    "sg:classifiers":[
        {
            "category":"Professional",
            "subcategory":"Lawyer & Legal Services",
            "type":"Services"
        }
    ],
    "sg:postcode":"NN1 4EW",
    "sg:province":"Northamptonshire",
    "sg:tags":[
        "solicitor"
    ],
    "wof:name":"Prester Coleman & Co",
    "wof:placetype":"venue"
},
  "geometry": {"coordinates":[-0.873145,52.243351],"type":"Point"}
}