{
  "type": "Feature",
  "properties": {
    "iso:country":"GB",
    "sg:address":"15 Victoria Sq",
    "sg:city":"Aberdare",
    "sg:classifiers":[
        {
            "category":"Retail",
            "subcategory":"Laundry & Dry Cleaning",
            "type":"Services"
        }
    ],
    "sg:phone":"+44 1685 871084",
    "sg:postcode":"CF44 7LA",
    "sg:province":"Neath Port Talbot",
    "sg:tags":[
        "alteration"
    ],
    "wof:name":"Bollom Ltd",
    "wof:placetype":"venue"
},
  "geometry": {"coordinates":[-3.444563,51.713123],"type":"Point"}
}