{
  "type": "Feature",
  "properties": {
    "iso:country":"GB",
    "sg:address":"The Gables, Watling Street",
    "sg:city":"Hinckley",
    "sg:classifiers":[
        {
            "category":"Travel",
            "subcategory":"Hotels & Motels",
            "type":"Entertainment"
        }
    ],
    "sg:postcode":"LE10 3JA",
    "sg:province":"Leicestershire",
    "sg:tags":[
        "house",
        "guest"
    ],
    "wof:name":"Gables Guest House",
    "wof:placetype":"venue"
},
  "geometry": {"coordinates":[-1.374085,52.52541],"type":"Point"}
}