{
  "type": "Feature",
  "properties": {
    "iso:country":"GB",
    "sg:address":"Unit G, Alanbrooke Business Park, Station Road",
    "sg:city":"Thirsk",
    "sg:classifiers":[
        {
            "category":"Professional",
            "subcategory":"Printing & Photocopies",
            "type":"Services"
        }
    ],
    "sg:phone":"+44 1845 574243",
    "sg:postcode":"YO7 3SE",
    "sg:province":"North Yorkshire",
    "sg:tags":[
        "trophy"
    ],
    "wof:name":"Fox (Mouldings) Ltd.",
    "wof:placetype":"venue"
},
  "geometry": {"coordinates":[-1.342253,54.232689],"type":"Point"}
}