{
  "type": "Feature",
  "properties": {
    "addr:full":"8 Littlemoor Road Pudsey West Yorkshire LS28 9EP",
    "addr:housenumber":"8",
    "addr:postcode":"ls28 9ep",
    "addr:street":"Littlemoor Road",
    "iso:country":"GB",
    "sg:address":"8 Littlemoor Road",
    "sg:city":"Pudsey",
    "sg:classifiers":[
        {
            "category":"Manufacturing",
            "subcategory":"Furniture",
            "type":"Manufacturing & Wholesale Goods"
        }
    ],
    "sg:phone":"+44 113 257 9219",
    "sg:postcode":"LS28 9EP",
    "sg:province":"West Yorkshire",
    "sg:tags":[
        "mnfr",
        "upholsterer"
    ],
    "wof:name":"P Walker",
    "wof:placetype":"venue"
},
  "geometry": {"coordinates":[-1.657793,53.788582],"type":"Point"}
}