{
  "type": "Feature",
  "properties": {
    "addr:full":"Units 12-19, Guinness Road Trading Estate, Trafford Park Manchester Cheshire M17 1SB",
    "addr:housenumber":"units 12-19",
    "addr:postcode":"m17 1sb",
    "addr:street":"Guinness Road Trading Estate;Park",
    "iso:country":"GB",
    "sg:address":"Units 12-19, Guinness Road Trading Estate, Trafford Park",
    "sg:city":"Manchester",
    "sg:classifiers":[
        {
            "category":"Home & Garden",
            "subcategory":"Home Furnishings",
            "type":"Retail Goods"
        },
        {
            "category":"Home & Garden",
            "subcategory":"Building Materials",
            "type":"Retail Goods"
        }
    ],
    "sg:phone":"+44 161 872 7041",
    "sg:postcode":"M17 1SB",
    "sg:province":"Cheshire",
    "sg:tags":[
        "installers",
        "planner",
        "kitchen",
        "furnishers"
    ],
    "wof:name":"Johnson & Johnson Furniture Plc",
    "wof:placetype":"venue"
},
  "geometry": {"coordinates":[-2.3083589077,53.4681396484],"type":"Point"}
}