{
  "type": "Feature",
  "properties": {
    "addr:full":"Recreation Ground, Price Avenue, Mile Oak Tamworth Staffordshire B78 3NL",
    "addr:postcode":"b78 3nl",
    "addr:street":"Recreation;Price Avenue",
    "iso:country":"GB",
    "sg:address":"Recreation Ground, Price Avenue, Mile Oak",
    "sg:city":"Tamworth",
    "sg:classifiers":[
        {
            "category":"Building & Trades",
            "subcategory":"Landscaping Services",
            "type":"Services"
        },
        {
            "category":"Arena",
            "subcategory":"Sports Club",
            "type":"Entertainment"
        }
    ],
    "sg:phone":"+44 1827 289614",
    "sg:postcode":"B78 3NL",
    "sg:province":"Staffordshire",
    "sg:tags":[
        "contractor",
        "ground"
    ],
    "wof:name":"Mile Oak Rovers Football Club",
    "wof:placetype":"venue"
},
  "geometry": {"coordinates":[-1.732869029,52.6184806824],"type":"Point"}
}