{
  "type": "Feature",
  "properties": {
    "iso:country":"GB",
    "sg:address":"Hillier Garden Centres, Woodhouse Lane, Botley",
    "sg:city":"Southampton",
    "sg:classifiers":[
        {
            "category":"Home & Garden",
            "subcategory":"Garden Supply",
            "type":"Retail Goods"
        }
    ],
    "sg:phone":"+44 1489 789998",
    "sg:postcode":"SO30 2EZ",
    "sg:province":"Hampshire",
    "sg:tags":[
        "turfing"
    ],
    "wof:name":"Rolawn (Turf Growers)",
    "wof:placetype":"venue"
},
  "geometry": {"coordinates":[-1.270219,50.914333],"type":"Point"}
}