{
  "type": "Feature",
  "properties": {
    "addr:full":"4 Pendlebury Road, Gatley Cheadle Cheshire SK8 4BH",
    "addr:housenumber":"4",
    "addr:postcode":"sk8 4bh",
    "addr:street":"Pendlebury Road;Cheadle",
    "iso:country":"GB",
    "sg:address":"4 Pendlebury Road, Gatley",
    "sg:city":"Cheadle",
    "sg:classifiers":[
        {
            "category":"Personal",
            "subcategory":"Beauty Salon",
            "type":"Services"
        }
    ],
    "sg:phone":"+44 161 428 3485",
    "sg:postcode":"SK8 4BH",
    "sg:province":"Cheshire",
    "sg:tags":[
        "unisex",
        "hairdresser"
    ],
    "wof:name":"Elegance Hair Design",
    "wof:placetype":"venue"
},
  "geometry": {"coordinates":[-2.2353789806,53.3943214417],"type":"Point"}
}