{
  "type": "Feature",
  "properties": {
    "addr:full":"Elmsleigh, Penhallow Truro Cornwall TR4 9LT",
    "addr:postcode":"tr4 9lt",
    "iso:country":"GB",
    "sg:address":"Elmsleigh, Penhallow",
    "sg:city":"Truro",
    "sg:classifiers":[
        {
            "category":"Building & Trades",
            "subcategory":"Construction",
            "type":"Services"
        }
    ],
    "sg:phone":"+44 1872 572625",
    "sg:postcode":"TR4 9LT",
    "sg:province":"Cornwall",
    "sg:tags":[
        "builder"
    ],
    "wof:name":"Elmsleigh Forge",
    "wof:placetype":"venue"
},
  "geometry": {"coordinates":[-5.1365671158,50.3163604736],"type":"Point"}
}