{
  "type": "Feature",
  "properties": {
    "addr:full":"1 Greenhill Main Rd Sheffield Derbyshire S8 7RA",
    "addr:housenumber":"1",
    "addr:postcode":"s8 7ra",
    "addr:street":"Greenhill Main Rd",
    "iso:country":"GB",
    "sg:address":"1 Greenhill Main Rd",
    "sg:city":"Sheffield",
    "sg:classifiers":[
        {
            "category":"Manufacturing",
            "subcategory":"Tools & Machinery",
            "type":"Manufacturing & Wholesale Goods"
        }
    ],
    "sg:postcode":"S8 7RA",
    "sg:province":"Derbyshire",
    "sg:tags":[
        "society",
        "friendly"
    ],
    "wof:name":"Hamnet Hart Clarke",
    "wof:placetype":"venue"
},
  "geometry": {"coordinates":[-1.4876329899,53.327167511],"type":"Point"}
}