{
  "type": "Feature",
  "properties": {
    "iso:country":"GB",
    "sg:address":"25 Connaught Street",
    "sg:city":"London",
    "sg:classifiers":[
        {
            "category":"Shopping",
            "subcategory":"Books",
            "type":"Retail Goods"
        }
    ],
    "sg:phone":"+44 20 7262 7900",
    "sg:postcode":"W2 2AY",
    "sg:province":"Greater London",
    "sg:tags":[
        "second-hand"
    ],
    "wof:name":"The Virtual Gallery Ltd.",
    "wof:placetype":"venue"
},
  "geometry": {"coordinates":[-0.165482,51.514439],"type":"Point"}
}