{
  "type": "Feature",
  "properties": {
    "iso:country":"GB",
    "sg:address":"72 Hollway Road",
    "sg:city":"Bristol",
    "sg:classifiers":[
        {
            "category":"Food & Beverages",
            "subcategory":"Meat & Fish",
            "type":"Retail Goods"
        }
    ],
    "sg:phone":"+44 1275 831411",
    "sg:postcode":"BS14 8PG",
    "sg:province":"City of Bristol",
    "sg:tags":[
        "butcher"
    ],
    "wof:name":"James & Son",
    "wof:placetype":"venue"
},
  "geometry": {"coordinates":[-2.5462119579,51.4119110107],"type":"Point"}
}