{
  "type": "Feature",
  "properties": {
    "iso:country":"GB",
    "sg:address":"Unit 2 Dradfield Industrial Estate, Dradfield Lane",
    "sg:city":"Southampton",
    "sg:classifiers":[
        {
            "category":"Home & Garden",
            "subcategory":"Furniture",
            "type":"Retail Goods"
        }
    ],
    "sg:postcode":"SO32 3QD",
    "sg:province":"Hampshire",
    "wof:name":"Pine Products",
    "wof:placetype":"venue"
},
  "geometry": {"coordinates":[-1.13211,50.91864],"type":"Point"}
}