{
  "type": "Feature",
  "properties": {
    "iso:country":"GB",
    "sg:address":"1a Risley Lane, Breaston",
    "sg:city":"Derby",
    "sg:classifiers":[
        {
            "category":"Shopping",
            "subcategory":"Crafts & Fabrics",
            "type":"Retail Goods"
        }
    ],
    "sg:phone":"+44 1332 874466",
    "sg:postcode":"DE72 3AU",
    "sg:province":"Derbyshire",
    "sg:tags":[
        "shop",
        "needlecraft",
        "wool"
    ],
    "wof:name":"U Knit 2",
    "wof:placetype":"venue"
},
  "geometry": {"coordinates":[-1.316746,52.897583],"type":"Point"}
}