{
  "type": "Feature",
  "properties": {
    "iso:country":"GB",
    "sg:address":"Survey Department, 83 Sankey St",
    "sg:city":"Warrington",
    "sg:classifiers":[
        {
            "category":"Real Estate",
            "subcategory":"Surveying",
            "type":"Services"
        }
    ],
    "sg:postcode":"WA1 1NJ",
    "sg:province":"Cheshire",
    "sg:tags":[
        "surveyor",
        "valuer"
    ],
    "wof:name":"Jones & Chapman Royal Insurance Property",
    "wof:placetype":"venue"
},
  "geometry": {"coordinates":[-2.59851,53.388538],"type":"Point"}
}