{
  "type": "Feature",
  "properties": {
    "addr:full":"22-23 Nutford Place London Greater London W1H 5YH",
    "addr:housenumber":"22-23",
    "addr:postcode":"w1h 5yh",
    "addr:street":"Nutford Place",
    "iso:country":"GB",
    "sg:address":"22-23 Nutford Place",
    "sg:city":"London",
    "sg:classifiers":[
        {
            "category":"Restaurant",
            "type":"Food & Drink"
        }
    ],
    "sg:phone":"+44 20 7723 8331",
    "sg:postcode":"W1H 5YH",
    "sg:province":"Greater London",
    "wof:name":"Safa",
    "wof:placetype":"venue"
},
  "geometry": {"coordinates":[-0.1639879942,51.5164909363],"type":"Point"}
}