{
  "type": "Feature",
  "properties": {
    "iso:country":"GB",
    "sg:address":"Lewes Road",
    "sg:city":"Forest Row",
    "sg:classifiers":[
        {
            "category":"Manufacturing",
            "subcategory":"Tools & Machinery",
            "type":"Manufacturing & Wholesale Goods"
        },
        {
            "category":"Professional",
            "subcategory":"Engineering",
            "type":"Services"
        }
    ],
    "sg:phone":"+44 1342 824814",
    "sg:postcode":"RH18 5AA",
    "sg:province":"East Sussex",
    "sg:tags":[
        "design",
        "maker",
        "engineer"
    ],
    "wof:name":"Arc Precision Engineers & Toolmakers",
    "wof:placetype":"venue"
},
  "geometry": {"coordinates":[0.0334549993,51.0973091125],"type":"Point"}
}