{
  "type": "Feature",
  "properties": {
    "addr:full":"14-17 Mander Street, Merridale Wolverhampton Staffordshire WV3 0JZ",
    "addr:housenumber":"14-17",
    "addr:postcode":"wv3 0jz",
    "addr:street":"Mander Street",
    "iso:country":"GB",
    "sg:address":"14-17 Mander Street, Merridale",
    "sg:city":"Wolverhampton",
    "sg:classifiers":[
        {
            "category":"Retail",
            "subcategory":"Auto Repair",
            "type":"Services"
        }
    ],
    "sg:phone":"+44 1902 427121",
    "sg:postcode":"WV3 0JZ",
    "sg:province":"Staffordshire",
    "sg:tags":[
        "modification",
        "garage"
    ],
    "wof:name":"Contact Motor Services",
    "wof:placetype":"venue"
},
  "geometry": {"coordinates":[-2.1348741055,52.5792884827],"type":"Point"}
}