{
  "type": "Feature",
  "properties": {
    "addr:full":"32 Magdalen Street Norwich Norfolk NR3 1HU",
    "addr:housenumber":"32",
    "addr:postcode":"nr3 1hu",
    "addr:street":"Magdalen Street",
    "iso:country":"GB",
    "sg:address":"32 Magdalen Street",
    "sg:city":"Norwich",
    "sg:classifiers":[
        {
            "category":"Personal",
            "subcategory":"Beauty Salon",
            "type":"Services"
        }
    ],
    "sg:postcode":"NR3 1HU",
    "sg:province":"Norfolk",
    "sg:tags":[
        "lady",
        "hairdresser"
    ],
    "wof:name":"Claphams Hairdressers",
    "wof:placetype":"venue"
},
  "geometry": {"coordinates":[1.296379,52.634533],"type":"Point"}
}