{
  "type": "Feature",
  "properties": {
    "addr:full":"56 Rochester Street Chatham Kent ME4 6RR",
    "addr:housenumber":"56",
    "addr:postcode":"me4 6rr",
    "addr:street":"Rochester Street",
    "iso:country":"GB",
    "sg:address":"56 Rochester Street",
    "sg:city":"Chatham",
    "sg:classifiers":[
        {
            "category":"Retail",
            "subcategory":"Storage",
            "type":"Services"
        }
    ],
    "sg:postcode":"ME4 6RR",
    "sg:province":"Kent",
    "sg:tags":[
        "household",
        "activity",
        "domestic",
        "removal"
    ],
    "wof:name":"R B H Removals",
    "wof:placetype":"venue"
},
  "geometry": {"coordinates":[0.520303,51.378197],"type":"Point"}
}