{
  "type": "Feature",
  "properties": {
    "iso:country":"GB",
    "sg:address":"170 Congleton Road, Talke",
    "sg:city":"Stoke-on-trent",
    "sg:classifiers":[
        {
            "category":"Fast Food",
            "type":"Food & Drink"
        }
    ],
    "sg:phone":"+44 1782 782786",
    "sg:postcode":"ST7 1LT",
    "sg:province":"Cheshire",
    "sg:tags":[
        "away",
        "take"
    ],
    "wof:name":"Wans Chinese Take Away",
    "wof:placetype":"venue"
},
  "geometry": {"coordinates":[-2.2599079609,53.0855026245],"type":"Point"}
}