{
  "type": "Feature",
  "properties": {
    "addr:full":"Premier House, 309 Ballards Lane, North Finchley London Greater London N12 8LU",
    "addr:housenumber":"309",
    "addr:postcode":"n12 8lu",
    "addr:street":"Ballards Lane",
    "iso:country":"GB",
    "sg:address":"Premier House, 309 Ballards Lane, North Finchley",
    "sg:city":"London",
    "sg:classifiers":[
        {
            "category":"Personal",
            "type":"Services"
        }
    ],
    "sg:phone":"+44 20 8446 3255",
    "sg:postcode":"N12 8LU",
    "sg:province":"Greater London",
    "sg:tags":[
        "dressmaker"
    ],
    "wof:name":"Madison Avenue Gown House Ltd.",
    "wof:placetype":"venue"
},
  "geometry": {"coordinates":[-0.1779289991,51.6124992371],"type":"Point"}
}