{
  "type": "Feature",
  "properties": {
    "addr:full":"Forest Hall Barn, Forest Hall Road Stansted Essex CM24 8TU",
    "addr:postcode":"cm24 8tu",
    "addr:street":"Forest Hall Road",
    "iso:country":"GB",
    "sg:address":"Forest Hall Barn, Forest Hall Road",
    "sg:city":"Stansted",
    "sg:classifiers":[
        {
            "category":"Building & Trades",
            "subcategory":"Construction",
            "type":"Services"
        }
    ],
    "sg:phone":"+44 1279 813763",
    "sg:postcode":"CM24 8TU",
    "sg:province":"Essex",
    "sg:tags":[
        "builder"
    ],
    "wof:name":"Peter Francis Richard O'Gram",
    "wof:placetype":"venue"
},
  "geometry": {"coordinates":[0.205854997,51.8943481445],"type":"Point"}
}