{
  "type": "Feature",
  "properties": {
    "iso:country":"GB",
    "sg:address":"124-126 High Street",
    "sg:city":"Stevenage",
    "sg:classifiers":[
        {
            "category":"Retail",
            "subcategory":"Auto Rental",
            "type":"Services"
        }
    ],
    "sg:phone":"+44 1438 351113",
    "sg:postcode":"SG1 3DE",
    "sg:province":"Hertfordshire",
    "sg:tags":[
        "car"
    ],
    "wof:name":"Stevenage Car & Commercials Ltd.",
    "wof:placetype":"venue"
},
  "geometry": {"coordinates":[-0.207712,51.910145],"type":"Point"}
}