{
  "type": "Feature",
  "properties": {
    "iso:country":"GB",
    "sg:address":"33 Mayflower Street",
    "sg:city":"Plymouth",
    "sg:classifiers":[
        {
            "category":"Shopping",
            "subcategory":"Gifts & Souvenirs",
            "type":"Retail Goods"
        }
    ],
    "sg:phone":"+44 1752 662591",
    "sg:postcode":"PL1 1QJ",
    "sg:province":"Devon",
    "sg:tags":[
        "shop"
    ],
    "wof:name":"Mayflower Galleries",
    "wof:placetype":"venue"
},
  "geometry": {"coordinates":[-4.1417,50.373211],"type":"Point"}
}