{
  "type": "Feature",
  "properties": {
    "iso:country":"GB",
    "sg:address":"80 Windmill Road",
    "sg:city":"Brentford",
    "sg:classifiers":[
        {
            "category":"Organizations",
            "subcategory":"Non-profit Organization",
            "type":"Services"
        }
    ],
    "sg:phone":"+44 20 8326 6767",
    "sg:postcode":"TW8 0QH",
    "sg:province":"Greater London",
    "sg:tags":[
        "organisation",
        "voluntary",
        "charity"
    ],
    "wof:name":"The Leprosy Mission International",
    "wof:placetype":"venue"
},
  "geometry": {"coordinates":[-0.3089179993,51.4897460938],"type":"Point"}
}