{
  "type": "Feature",
  "properties": {
    "iso:country":"GB",
    "sg:address":"Harlestone Road Surgery, 117 Harlestone Rd",
    "sg:city":"Northampton",
    "sg:classifiers":[
        {
            "category":"Health Services",
            "subcategory":"Doctor",
            "type":"Services"
        }
    ],
    "sg:phone":"+44 1604 751832",
    "sg:postcode":"NN5 7AQ",
    "sg:province":"Northamptonshire",
    "sg:tags":[
        "practitioners"
    ],
    "wof:name":"Saynor, C E",
    "wof:placetype":"venue"
},
  "geometry": {"coordinates":[-0.92304,52.24696],"type":"Point"}
}