{
  "type": "Feature",
  "properties": {
    "iso:country":"GB",
    "sg:address":"1 Barton Close, Wembury",
    "sg:city":"Plymouth",
    "sg:classifiers":[
        {
            "category":"Military Area",
            "subcategory":"Air Force Base",
            "type":"Public Place"
        }
    ],
    "sg:postcode":"PL9 0LF",
    "sg:province":"Devon",
    "sg:tags":[
        "taxi",
        "hire",
        "private"
    ],
    "wof:name":"Wembury Cars",
    "wof:placetype":"venue"
},
  "geometry": {"coordinates":[-4.070816,50.326565],"type":"Point"}
}