{
  "type": "Feature",
  "properties": {
    "iso:country":"GB",
    "sg:address":"4/10 Harbour Place",
    "sg:city":"Burntisland",
    "sg:classifiers":[
        {
            "category":"Shopping",
            "subcategory":"Optical Goods",
            "type":"Retail Goods"
        }
    ],
    "sg:phone":"+44 1592 874140",
    "sg:postcode":"KY3 9DP",
    "sg:province":"Fife",
    "wof:name":"10 Kaypul Optics",
    "wof:placetype":"venue"
},
  "geometry": {"coordinates":[-3.236699,56.058731],"type":"Point"}
}