{
  "type": "Feature",
  "properties": {
    "iso:country":"GB",
    "sg:address":"126 Primrose Av",
    "sg:city":"Wolverhampton",
    "sg:classifiers":[
        {
            "category":"Manufacturing",
            "subcategory":"Building Materials",
            "type":"Manufacturing & Wholesale Goods"
        }
    ],
    "sg:phone":"+44 1902 788828",
    "sg:postcode":"WV10 8AR",
    "sg:province":"Staffordshire",
    "sg:tags":[
        "tarmac",
        "asphalt"
    ],
    "wof:name":"Macs Tarmac",
    "wof:placetype":"venue"
},
  "geometry": {"coordinates":[-2.116817,52.629513],"type":"Point"}
}