{
  "type": "Feature",
  "properties": {
    "iso:country":"GB",
    "sg:address":"5 The Highway",
    "sg:city":"Beaconsfield",
    "sg:classifiers":[
        {
            "category":"Shopping",
            "subcategory":"Pharmacy",
            "type":"Retail Goods"
        }
    ],
    "sg:phone":"+44 1494 672677",
    "sg:postcode":"HP9 1QD",
    "sg:province":"Buckinghamshire",
    "sg:tags":[
        "pharmacist",
        "chemist"
    ],
    "wof:name":"Lister Chemist",
    "wof:placetype":"venue"
},
  "geometry": {"coordinates":[-0.645569,51.61042],"type":"Point"}
}