{
  "type": "Feature",
  "properties": {
    "iso:country":"GB",
    "sg:address":"Frederick House, 8 Acorn Business Park, Heaton Lane",
    "sg:city":"Stockport",
    "sg:classifiers":[
        {
            "category":"Utilities",
            "subcategory":"Refuse",
            "type":"Services"
        }
    ],
    "sg:phone":"+44 161 480 9672",
    "sg:postcode":"SK4 1AS",
    "sg:province":"Cheshire",
    "sg:tags":[
        "disposal",
        "waste"
    ],
    "wof:name":"Simister Engineering Services Ltd.",
    "wof:placetype":"venue"
},
  "geometry": {"coordinates":[-2.16881,53.409744],"type":"Point"}
}