{
  "type": "Feature",
  "properties": {
    "addr:full":"Broadwater, Coronation Av Dawlish Devon EX7 9EF",
    "addr:postcode":"ex7 9ef",
    "addr:street":"Coronation Av",
    "iso:country":"GB",
    "sg:address":"Broadwater, Coronation Av",
    "sg:city":"Dawlish",
    "sg:classifiers":[
        {
            "category":"Manufacturing",
            "subcategory":"Tools & Machinery",
            "type":"Manufacturing & Wholesale Goods"
        }
    ],
    "sg:phone":"+44 1626 864249",
    "sg:postcode":"EX7 9EF",
    "sg:province":"Devon",
    "wof:name":"Silver Chain Tools",
    "wof:placetype":"venue"
},
  "geometry": {"coordinates":[-3.474359,50.576046],"type":"Point"}
}