{
  "type": "Feature",
  "properties": {
    "addr:full":"Unit 20 Maxwell Rd Peterborough Cambridgeshire PE2 7JD",
    "addr:housenumber":"unit 20",
    "addr:postcode":"pe2 7jd",
    "addr:street":"Maxwell Rd",
    "iso:country":"GB",
    "sg:address":"Unit 20 Maxwell Rd",
    "sg:city":"Peterborough",
    "sg:classifiers":[
        {
            "category":"Shopping",
            "subcategory":"Tobacco",
            "type":"Retail Goods"
        }
    ],
    "sg:phone":"+44 1733 371177",
    "sg:postcode":"PE2 7JD",
    "sg:province":"Cambridgeshire",
    "sg:tags":[
        "confectioner",
        "tobacconist"
    ],
    "wof:name":"Barnack Foods Ltd",
    "wof:placetype":"venue"
},
  "geometry": {"coordinates":[-0.2615320086,52.5571632385],"type":"Point"}
}