{
  "type": "Feature",
  "properties": {
    "iso:country":"GB",
    "sg:address":"Somerville Way, Fowler Road",
    "sg:city":"Aylesbury",
    "sg:classifiers":[
        {
            "category":"Food & Beverages",
            "subcategory":"Groceries & Convenience Stores",
            "type":"Retail Goods"
        }
    ],
    "sg:phone":"+44 1296 485556",
    "sg:postcode":"HP21 8QT",
    "sg:province":"Buckinghamshire",
    "wof:name":"Gibbs Newsagents",
    "wof:placetype":"venue"
},
  "geometry": {"coordinates":[-0.81899,51.806229],"type":"Point"}
}