{
  "type": "Feature",
  "properties": {
    "iso:country":"GB",
    "sg:address":"24 Garden Way",
    "sg:city":"Newport",
    "sg:classifiers":[
        {
            "category":"Building & Trades",
            "subcategory":"Construction",
            "type":"Services"
        }
    ],
    "sg:phone":"+44 1983 528323",
    "sg:postcode":"PO30 2BN",
    "sg:province":"Isle of Wight",
    "sg:tags":[
        "builder"
    ],
    "wof:name":"M Dunne",
    "wof:placetype":"venue"
},
  "geometry": {"coordinates":[-1.282911,50.696098],"type":"Point"}
}