{
  "type": "Feature",
  "properties": {
    "addr:full":"65 Fox Road Exeter Devon EX4 8NB",
    "addr:housenumber":"65",
    "addr:postcode":"ex4 8nb",
    "addr:street":"Fox Road",
    "iso:country":"GB",
    "sg:address":"65 Fox Road",
    "sg:city":"Exeter",
    "sg:classifiers":[
        {
            "category":"Professional",
            "subcategory":"Secretarial Services",
            "type":"Services"
        },
        {
            "category":"Professional",
            "subcategory":"Art Services",
            "type":"Services"
        }
    ],
    "sg:phone":"+44 1392 467766",
    "sg:postcode":"EX4 8NB",
    "sg:province":"Devon",
    "sg:tags":[
        "photographer"
    ],
    "wof:name":"J E Palmer",
    "wof:placetype":"venue"
},
  "geometry": {"coordinates":[-3.4930720329,50.7419166565],"type":"Point"}
}