{
  "type": "Feature",
  "properties": {
    "addr:full":"15 Bradshaw Close, Barton-le-clay Bedford Bedfordshire MK45 4JS",
    "addr:housenumber":"15",
    "addr:postcode":"mk45 4js",
    "addr:street":"Bradshaw Close",
    "iso:country":"GB",
    "sg:address":"15 Bradshaw Close, Barton-le-clay",
    "sg:city":"Bedford",
    "sg:classifiers":[
        {
            "category":"Building & Trades",
            "subcategory":"Plumbing",
            "type":"Services"
        }
    ],
    "sg:phone":"+44 1582 882211",
    "sg:postcode":"MK45 4JS",
    "sg:province":"Bedfordshire",
    "sg:tags":[
        "central",
        "heating"
    ],
    "wof:name":"Compass Heating & Plumbing",
    "wof:placetype":"venue"
},
  "geometry": {"coordinates":[-0.425928,51.967808],"type":"Point"}
}