{
  "type": "Feature",
  "properties": {
    "addr:full":"21 Presley Way, Crownhill Milton Keynes Buckinghamshire MK8 0ES",
    "addr:housenumber":"21",
    "addr:postcode":"mk8 0es",
    "addr:street":"Presley Way",
    "iso:country":"GB",
    "sg:address":"21 Presley Way, Crownhill",
    "sg:city":"Milton Keynes",
    "sg:classifiers":[
        {
            "category":"Professional",
            "subcategory":"Management & Consulting",
            "type":"Services"
        }
    ],
    "sg:phone":"+44 1908 261122",
    "sg:postcode":"MK8 0ES",
    "sg:province":"Buckinghamshire",
    "sg:tags":[
        "consultant",
        "business"
    ],
    "wof:name":"Millar Management Systems Ltd.",
    "wof:placetype":"venue"
},
  "geometry": {"coordinates":[-0.798144,52.027225],"type":"Point"}
}