{
  "type": "Feature",
  "properties": {
    "addr:full":"35 Revesby Walk Birmingham West Midlands B7 4LG",
    "addr:housenumber":"35",
    "addr:postcode":"b7 4lg",
    "addr:street":"Revesby Walk",
    "iso:country":"GB",
    "sg:address":"35 Revesby Walk",
    "sg:city":"Birmingham",
    "sg:classifiers":[
        {
            "category":"Food & Beverages",
            "subcategory":"Meat & Fish",
            "type":"Retail Goods"
        }
    ],
    "sg:postcode":"B7 4LG",
    "sg:province":"West Midlands",
    "sg:tags":[
        "chip"
    ],
    "wof:name":"Camran's Kebab House",
    "wof:placetype":"venue"
},
  "geometry": {"coordinates":[-1.8762539625,52.4865608215],"type":"Point"}
}