{
  "type": "Feature",
  "properties": {
    "iso:country":"GB",
    "sg:address":"295 Marine Rd Central",
    "sg:city":"Morecambe",
    "sg:classifiers":[
        {
            "category":"Shopping",
            "subcategory":"Gifts & Souvenirs",
            "type":"Retail Goods"
        }
    ],
    "sg:phone":"+44 1524 415575",
    "sg:postcode":"LA4 5BY",
    "sg:province":"Lancashire",
    "sg:tags":[
        "shop"
    ],
    "wof:name":"The Shell Shop",
    "wof:placetype":"venue"
},
  "geometry": {"coordinates":[-2.864343,54.07423],"type":"Point"}
}