{
  "type": "Feature",
  "properties": {
    "iso:country":"GB",
    "sg:address":"33 Florence Road",
    "sg:city":"Bournemouth",
    "sg:classifiers":[
        {
            "category":"Social Services",
            "subcategory":"Retirement Home",
            "type":"Services"
        }
    ],
    "sg:postcode":"BH5 1HJ",
    "sg:province":"Dorset",
    "sg:tags":[
        "rest"
    ],
    "wof:name":"The White House",
    "wof:placetype":"venue"
},
  "geometry": {"coordinates":[-1.83507,50.725052],"type":"Point"}
}