{
  "type": "Feature",
  "properties": {
    "addr:full":"Barlae Farm Newton Stewart Dumfries and Galloway DG8 0DN",
    "addr:postcode":"dg8 0dn",
    "addr:street":"Stewart",
    "iso:country":"GB",
    "sg:address":"Barlae Farm",
    "sg:city":"Newton Stewart",
    "sg:classifiers":[
        {
            "category":"Farming",
            "subcategory":"Farm",
            "type":"Manufacturing & Wholesale Goods"
        }
    ],
    "sg:phone":"+44 1671 830220",
    "sg:postcode":"DG8 0DN",
    "sg:province":"Dumfries and Galloway",
    "sg:tags":[
        "mixed",
        "crop"
    ],
    "wof:name":"K Plunklett",
    "wof:placetype":"venue"
},
  "geometry": {"coordinates":[-4.770479,54.902241],"type":"Point"}
}