{
  "type": "Feature",
  "properties": {
    "iso:country":"GB",
    "sg:address":"36 Rosslyn Hill, Hampstead",
    "sg:city":"London",
    "sg:classifiers":[
        {
            "category":"Health Services",
            "subcategory":"Dentist",
            "type":"Services"
        }
    ],
    "sg:phone":"+44 20 7435 2550",
    "sg:postcode":"NW3 1NH",
    "sg:province":"Greater London",
    "wof:name":"The Practice on the Hill",
    "wof:placetype":"venue"
},
  "geometry": {"coordinates":[-0.172313,51.554787],"type":"Point"}
}