{
  "type": "Feature",
  "properties": {
    "addr:full":"Church Street, Farnworth Bolton Lancashire BL4 8AG",
    "addr:postcode":"bl4 8ag",
    "addr:street":"Church Street",
    "iso:country":"GB",
    "sg:address":"Church Street, Farnworth",
    "sg:city":"Bolton",
    "sg:classifiers":[
        {
            "category":"Organizations",
            "subcategory":"Membership Organization",
            "type":"Services"
        }
    ],
    "sg:phone":"+44 1204 573168",
    "sg:postcode":"BL4 8AG",
    "sg:province":"Lancashire",
    "sg:tags":[
        "club"
    ],
    "wof:name":"St.Gregory's Social Club",
    "wof:placetype":"venue"
},
  "geometry": {"coordinates":[-2.393549,53.548805],"type":"Point"}
}