{
  "type": "Feature",
  "properties": {
    "addr:full":"16 Northumberland Road Bath Bath and North East Somerset BA1 5AR",
    "addr:housenumber":"16",
    "addr:postcode":"ba1 5ar",
    "addr:street":"Northumberland Road",
    "iso:country":"GB",
    "sg:address":"16 Northumberland Road",
    "sg:city":"Bath",
    "sg:classifiers":[
        {
            "category":"Shopping",
            "subcategory":"Comic Books",
            "type":"Retail Goods"
        }
    ],
    "sg:phone":"+44 1225 329300",
    "sg:postcode":"BA1 5AR",
    "sg:province":"Bath and North East Somerset",
    "sg:tags":[
        "jeweller"
    ],
    "wof:name":"Justice Designer Jewellery",
    "wof:placetype":"venue"
},
  "geometry": {"coordinates":[-2.3600540161,51.3823471069],"type":"Point"}
}