{
  "type": "Feature",
  "properties": {
    "iso:country":"GB",
    "sg:address":"Transport Way, Cowley",
    "sg:city":"Oxford",
    "sg:classifiers":[
        {
            "category":"Retail",
            "subcategory":"Auto Rental",
            "type":"Services"
        }
    ],
    "sg:phone":"+44 1865 715500",
    "sg:postcode":"OX4 5LX",
    "sg:province":"Oxfordshire",
    "sg:tags":[
        "car"
    ],
    "wof:name":"Hotsons Eurodrive",
    "wof:placetype":"venue"
},
  "geometry": {"coordinates":[-1.21001,51.733749],"type":"Point"}
}