{
  "type": "Feature",
  "properties": {
    "iso:country":"GB",
    "sg:address":"Avenue Farm, Hevingham",
    "sg:city":"Norwich",
    "sg:classifiers":[
        {
            "category":"Farming",
            "subcategory":"Farm",
            "type":"Manufacturing & Wholesale Goods"
        }
    ],
    "sg:phone":"+44 1603 754267",
    "sg:postcode":"NR10 5QS",
    "sg:province":"Norfolk",
    "sg:tags":[
        "mixed",
        "crop"
    ],
    "wof:name":"F Waller",
    "wof:placetype":"venue"
},
  "geometry": {"coordinates":[1.2625639439,52.7431602478],"type":"Point"}
}