{
  "type": "Feature",
  "properties": {
    "iso:country":"GB",
    "sg:address":"3 Southvale Road",
    "sg:city":"London",
    "sg:classifiers":[
        {
            "category":"Shopping",
            "subcategory":"Books",
            "type":"Retail Goods"
        }
    ],
    "sg:phone":"+44 20 8318 2112",
    "sg:postcode":"SE3 0TP",
    "sg:province":"Greater London",
    "wof:name":"Southvale Publishing",
    "wof:placetype":"venue"
},
  "geometry": {"coordinates":[0.007178,51.466648],"type":"Point"}
}