{
  "type": "Feature",
  "properties": {
    "addr:full":"16 High Street Uxbridge Buckinghamshire UB8 1JN",
    "addr:housenumber":"16",
    "addr:postcode":"ub8 1jn",
    "addr:street":"High Street",
    "iso:country":"GB",
    "sg:address":"16 High Street",
    "sg:city":"Uxbridge",
    "sg:classifiers":[
        {
            "category":"Professional",
            "subcategory":"Accounting & Tax Preparation",
            "type":"Services"
        }
    ],
    "sg:phone":"+44 1895 258257",
    "sg:postcode":"UB8 1JN",
    "sg:province":"Buckinghamshire",
    "sg:tags":[
        "accountant"
    ],
    "wof:name":"M J Harvey & Co",
    "wof:placetype":"venue"
},
  "geometry": {"coordinates":[-0.476724,51.545052],"type":"Point"}
}