{
  "type": "Feature",
  "properties": {
    "iso:country":"GB",
    "sg:address":"Carlton House, Registry Street",
    "sg:city":"Stoke-on-trent",
    "sg:classifiers":[
        {
            "category":"Manufacturing",
            "subcategory":"Pottery",
            "type":"Manufacturing & Wholesale Goods"
        }
    ],
    "sg:phone":"+44 1782 848805",
    "sg:postcode":"ST4 1JP",
    "sg:province":"Staffordshire",
    "wof:name":"Pyramid Pottery Co. Ltd.",
    "wof:placetype":"venue"
},
  "geometry": {"coordinates":[-2.184337,53.007298],"type":"Point"}
}