{
  "type": "Feature",
  "properties": {
    "iso:country":"GB",
    "sg:address":"Kings Church Centre, Catford Hill",
    "sg:city":"London",
    "sg:classifiers":[
        {
            "category":"Place Of Worship",
            "type":"Public Place"
        }
    ],
    "sg:postcode":"SE6 4PS",
    "sg:province":"Greater London",
    "wof:name":"King's Church Catford",
    "wof:placetype":"venue"
},
  "geometry": {"coordinates":[-0.03158,51.439968],"type":"Point"}
}