{
  "type": "Feature",
  "properties": {
    "iso:country":"GB",
    "sg:address":"Staines Road",
    "sg:city":"Chertsey",
    "sg:classifiers":[
        {
            "category":"Wholesale",
            "subcategory":"Construction Materials",
            "type":"Manufacturing & Wholesale Goods"
        }
    ],
    "sg:phone":"+44 1932 566555",
    "sg:postcode":"KT16 8PP",
    "sg:province":"Surrey",
    "sg:tags":[
        "whole",
        "asphalt",
        "macadam"
    ],
    "wof:name":"Colas Ltd.",
    "wof:placetype":"venue"
},
  "geometry": {"coordinates":[-0.507719,51.408852],"type":"Point"}
}