{
  "type": "Feature",
  "properties": {
    "iso:country":"GB",
    "sg:address":"27 Stanley Gro",
    "sg:city":"Croydon",
    "sg:classifiers":[
        {
            "category":"Building & Trades",
            "subcategory":"Plumbing",
            "type":"Services"
        }
    ],
    "sg:postcode":"CR0 3QW",
    "sg:province":"Surrey",
    "sg:tags":[
        "heating"
    ],
    "wof:name":"S Beadle",
    "wof:placetype":"venue"
},
  "geometry": {"coordinates":[-0.114607,51.387848],"type":"Point"}
}