{
  "type": "Feature",
  "properties": {
    "addr:full":"Gordleton Farm, Silver St Lymington Hampshire SO41 6DJ",
    "addr:postcode":"so41 6dj",
    "addr:street":"Silver St",
    "iso:country":"GB",
    "sg:address":"Gordleton Farm, Silver St",
    "sg:city":"Lymington",
    "sg:classifiers":[
        {
            "category":"Manufacturing",
            "subcategory":"Wood Products",
            "type":"Manufacturing & Wholesale Goods"
        }
    ],
    "sg:postcode":"SO41 6DJ",
    "sg:province":"Hampshire",
    "sg:tags":[
        "maker",
        "cabinet"
    ],
    "wof:name":"Nunan,P,",
    "wof:placetype":"venue"
},
  "geometry": {"coordinates":[-1.538910985,50.7589378357],"type":"Point"}
}