{
  "type": "Feature",
  "properties": {
    "addr:full":"Old Friends School, Cross Park House, Low Green Leeds West Yorkshire LS19 6HB",
    "addr:postcode":"ls19 6hb",
    "addr:street":"Cross;Low Green Leeds West",
    "iso:country":"GB",
    "sg:address":"Old Friends School, Cross Park House, Low Green",
    "sg:city":"Leeds",
    "sg:classifiers":[
        {
            "category":"Professional",
            "subcategory":"Accounting & Tax Preparation",
            "type":"Services"
        }
    ],
    "sg:phone":"+44 113 281 8366",
    "sg:postcode":"LS19 6HB",
    "sg:province":"West Yorkshire",
    "sg:tags":[
        "accountant"
    ],
    "wof:name":"Mjb Consultants Ltd.",
    "wof:placetype":"venue"
},
  "geometry": {"coordinates":[-1.6770089865,53.8486442566],"type":"Point"}
}