{
  "type": "Feature",
  "properties": {
    "iso:country":"GB",
    "sg:address":"17-18 Maynard Court",
    "sg:city":"Waltham Abbey",
    "sg:classifiers":[
        {
            "category":"Health Services",
            "subcategory":"Doctor",
            "type":"Services"
        }
    ],
    "sg:phone":"+44 1992 761387",
    "sg:postcode":"EN9 3DU",
    "sg:province":"Essex",
    "sg:tags":[
        "practitioners"
    ],
    "wof:name":"B Berry",
    "wof:placetype":"venue"
},
  "geometry": {"coordinates":[0.01994,51.68541],"type":"Point"}
}