{
  "type": "Feature",
  "properties": {
    "addr:full":"Highfields Farm, Stowting Common Ashford Kent TN25 6BG",
    "addr:housenumber":"stowting",
    "addr:postcode":"tn25 6bg",
    "addr:street":"Common",
    "iso:country":"GB",
    "sg:address":"Highfields Farm, Stowting Common",
    "sg:city":"Ashford",
    "sg:classifiers":[
        {
            "category":"Farming",
            "subcategory":"Livestock Farm",
            "type":"Manufacturing & Wholesale Goods"
        }
    ],
    "sg:postcode":"TN25 6BG",
    "sg:province":"Kent",
    "sg:tags":[
        "others"
    ],
    "wof:name":"L J & A P Roberts",
    "wof:placetype":"venue"
},
  "geometry": {"coordinates":[1.0352449417,51.1358413696],"type":"Point"}
}