{
  "type": "Feature",
  "properties": {
    "iso:country":"GB",
    "sg:address":"64 North End Road",
    "sg:city":"London",
    "sg:classifiers":[
        {
            "category":"Home & Garden",
            "subcategory":"Hardware",
            "type":"Retail Goods"
        }
    ],
    "sg:phone":"+44 20 7603 9323",
    "sg:postcode":"W14 9EP",
    "sg:province":"Greater London",
    "wof:name":"Handy Hardware Stores",
    "wof:placetype":"venue"
},
  "geometry": {"coordinates":[-0.2073,51.491169],"type":"Point"}
}