{
  "type": "Feature",
  "properties": {
    "addr:full":"20 Aldermanbury London Greater London EC2V 7HP",
    "addr:housenumber":"20",
    "addr:postcode":"ec2v 7hp",
    "addr:street":"Aldermanbury",
    "iso:country":"GB",
    "sg:address":"20 Aldermanbury",
    "sg:city":"London",
    "sg:classifiers":[
        {
            "category":"Organizations",
            "subcategory":"Membership Organization",
            "type":"Services"
        }
    ],
    "sg:phone":"+44 20 7814 0200",
    "sg:postcode":"EC2V 7HP",
    "sg:province":"Greater London",
    "sg:tags":[
        "club"
    ],
    "wof:name":"City Livery Club",
    "wof:placetype":"venue"
},
  "geometry": {"coordinates":[-0.092638,51.516285],"type":"Point"}
}