{
  "type": "Feature",
  "properties": {
    "addr:full":"36 Talbot Rd Twickenham Greater London TW2 6SJ",
    "addr:housenumber":"36",
    "addr:postcode":"tw2 6sj",
    "addr:street":"Talbot Rd",
    "iso:country":"GB",
    "sg:address":"36 Talbot Rd",
    "sg:city":"Twickenham",
    "sg:classifiers":[
        {
            "category":"Banks & Credit Unions",
            "subcategory":"Investment Brokerage",
            "type":"Services"
        }
    ],
    "sg:phone":"+44 20 8898 4970",
    "sg:postcode":"TW2 6SJ",
    "sg:province":"Greater London",
    "sg:tags":[
        "agent"
    ],
    "wof:name":"Greenwood Ltd",
    "wof:placetype":"venue"
},
  "geometry": {"coordinates":[-0.3391039968,51.4476623535],"type":"Point"}
}