{
  "type": "Feature",
  "properties": {
    "iso:country":"GB",
    "sg:address":"21 Gresty Ave, Wythenshawe",
    "sg:city":"Manchester",
    "sg:classifiers":[
        {
            "category":"Professional",
            "subcategory":"Detective & Security Services",
            "type":"Services"
        }
    ],
    "sg:postcode":"M22 5JQ",
    "sg:province":"Greater Manchester",
    "sg:tags":[
        "alarm",
        "burglar",
        "system"
    ],
    "wof:name":"A & R Security Systems",
    "wof:placetype":"venue"
},
  "geometry": {"coordinates":[-2.2451701164,53.3736152649],"type":"Point"}
}