{
  "type": "Feature",
  "properties": {
    "addr:full":"Bakery Lane, Windsor Square Exmouth Devon EX8 1JZ",
    "addr:postcode":"ex8 1jz",
    "addr:street":"Bakery Lane;Square",
    "iso:country":"GB",
    "sg:address":"Bakery Lane, Windsor Square",
    "sg:city":"Exmouth",
    "sg:classifiers":[
        {
            "category":"Retail",
            "subcategory":"Auto Repair",
            "type":"Services"
        }
    ],
    "sg:phone":"+44 1395 279621",
    "sg:postcode":"EX8 1JZ",
    "sg:province":"Devon",
    "sg:tags":[
        "modification",
        "garage"
    ],
    "wof:name":"S & T Motor Repairs",
    "wof:placetype":"venue"
},
  "geometry": {"coordinates":[-3.4132890701,50.6194152832],"type":"Point"}
}