{
  "type": "Feature",
  "properties": {
    "addr:full":"Unit 21 Beaumont Court, Beaumont Close Banbury Oxfordshire OX16 7TG",
    "addr:housenumber":"unit 21",
    "addr:postcode":"ox16 7tg",
    "addr:street":"Beaumont Court Beaumont Close",
    "iso:country":"GB",
    "sg:address":"Unit 21 Beaumont Court, Beaumont Close",
    "sg:city":"Banbury",
    "sg:classifiers":[
        {
            "category":"Professional",
            "subcategory":"Art Services",
            "type":"Services"
        }
    ],
    "sg:postcode":"OX16 7TG",
    "sg:province":"Oxfordshire",
    "sg:tags":[
        "photographer"
    ],
    "wof:name":"Tudor Photography",
    "wof:placetype":"venue"
},
  "geometry": {"coordinates":[-1.339916,52.077766],"type":"Point"}
}