{
  "type": "Feature",
  "properties": {
    "iso:country":"GB",
    "sg:address":"Cowley Mill Road",
    "sg:city":"Uxbridge",
    "sg:classifiers":[
        {
            "category":"Professional",
            "subcategory":"Management & Consulting",
            "type":"Services"
        }
    ],
    "sg:postcode":"UB8 2QE",
    "sg:province":"Buckinghamshire",
    "sg:tags":[
        "marketing",
        "consultant"
    ],
    "wof:name":"Critchley Evans Associates Ltd.",
    "wof:placetype":"venue"
},
  "geometry": {"coordinates":[-0.490699,51.539261],"type":"Point"}
}