{
  "type": "Feature",
  "properties": {
    "addr:full":"Atlas Works, Water Lane, Holbeck Leeds West Yorkshire LS11 9UD",
    "addr:postcode":"ls11 9ud",
    "addr:street":"Water Lane",
    "iso:country":"GB",
    "sg:address":"Atlas Works, Water Lane, Holbeck",
    "sg:city":"Leeds",
    "sg:classifiers":[
        {
            "category":"Building & Trades",
            "subcategory":"Construction",
            "type":"Services"
        }
    ],
    "sg:phone":"+44 113 245 6177",
    "sg:postcode":"LS11 9UD",
    "sg:province":"West Yorkshire",
    "sg:tags":[
        "fork",
        "lift",
        "truck"
    ],
    "wof:name":"Protier Forks & Attachments",
    "wof:placetype":"venue"
},
  "geometry": {"coordinates":[-1.5554200411,53.7915115356],"type":"Point"}
}