{
  "type": "Feature",
  "properties": {
    "addr:full":"11 Edith Avenue Peacehaven East Sussex BN10 8JB",
    "addr:housenumber":"11",
    "addr:postcode":"bn10 8jb",
    "addr:street":"Edith Avenue Peacehaven",
    "iso:country":"GB",
    "sg:address":"11 Edith Avenue",
    "sg:city":"Peacehaven",
    "sg:classifiers":[
        {
            "category":"Retail",
            "subcategory":"Veterinary Services",
            "type":"Services"
        }
    ],
    "sg:phone":"+44 1273 585386",
    "sg:postcode":"BN10 8JB",
    "sg:province":"East Sussex",
    "sg:tags":[
        "surgeon"
    ],
    "wof:name":"Meridian Veterinary Practice",
    "wof:placetype":"venue"
},
  "geometry": {"coordinates":[-0.0013229999,50.7917823792],"type":"Point"}
}