{
  "type": "Feature",
  "properties": {
    "iso:country":"GB",
    "sg:address":"1 Whiteheads Lane",
    "sg:city":"Bradford On Avon",
    "sg:classifiers":[
        {
            "category":"Organizations",
            "subcategory":"Religious Organization",
            "type":"Services"
        }
    ],
    "sg:phone":"+44 1225 865393",
    "sg:postcode":"BA15 1JU",
    "sg:province":"Wiltshire",
    "sg:tags":[
        "organisation",
        "place",
        "worship"
    ],
    "wof:name":"Quakers Religious Society Of Friends",
    "wof:placetype":"venue"
},
  "geometry": {"coordinates":[-2.248981,51.349136],"type":"Point"}
}