{
  "type": "Feature",
  "properties": {
    "iso:country":"GB",
    "sg:address":"6 Greystones Drive",
    "sg:city":"Reigate",
    "sg:classifiers":[
        {
            "category":"Professional",
            "subcategory":"Computer Services",
            "type":"Services"
        }
    ],
    "sg:phone":"+44 1737 241111",
    "sg:postcode":"RH2 0HA",
    "sg:province":"Surrey",
    "sg:tags":[
        "consultant"
    ],
    "wof:name":"Document Flow Ltd.",
    "wof:placetype":"venue"
},
  "geometry": {"coordinates":[-0.190525,51.247993],"type":"Point"}
}