{
  "type": "Feature",
  "properties": {
    "addr:full":"89-91 High Street Arbroath Angus DD11 1DP",
    "addr:housenumber":"89-91",
    "addr:postcode":"dd11 1dp",
    "addr:street":"High Street",
    "iso:country":"GB",
    "sg:address":"89-91 High Street",
    "sg:city":"Arbroath",
    "sg:classifiers":[
        {
            "category":"Professional",
            "subcategory":"Lawyer & Legal Services",
            "type":"Services"
        }
    ],
    "sg:phone":"+44 1241 430660",
    "sg:postcode":"DD11 1DP",
    "sg:province":"Angus",
    "sg:tags":[
        "solicitor"
    ],
    "wof:name":"R Bruce & Co",
    "wof:placetype":"venue"
},
  "geometry": {"coordinates":[-2.5811829567,56.5585632324],"type":"Point"}
}