{
  "type": "Feature",
  "properties": {
    "iso:country":"GB",
    "sg:address":"32 Leslie Hough Way",
    "sg:city":"Salford",
    "sg:classifiers":[
        {
            "category":"Communications",
            "type":"Services"
        }
    ],
    "sg:phone":"+44 161 925 0833",
    "sg:postcode":"M6 6AJ",
    "sg:province":"Greater Manchester",
    "sg:tags":[
        "telecommunication"
    ],
    "wof:name":"Central Telecom",
    "wof:placetype":"venue"
},
  "geometry": {"coordinates":[-2.2744939327,53.4923667908],"type":"Point"}
}