{
  "type": "Feature",
  "properties": {
    "addr:full":"146 Burnt Ash Hill, Lee London Greater London SE12 0HU",
    "addr:housenumber":"146",
    "addr:postcode":"se12 0hu",
    "addr:street":"Burnt Ash Hill Lee",
    "iso:country":"GB",
    "sg:address":"146 Burnt Ash Hill, Lee",
    "sg:city":"London",
    "sg:classifiers":[
        {
            "category":"Retail",
            "subcategory":"Veterinary Services",
            "type":"Services"
        }
    ],
    "sg:phone":"+44 20 8857 6888",
    "sg:postcode":"SE12 0HU",
    "sg:province":"Greater London",
    "sg:tags":[
        "surgeon"
    ],
    "wof:name":"Burnt Ash Hill Surgery",
    "wof:placetype":"venue"
},
  "geometry": {"coordinates":[0.018226,51.442646],"type":"Point"}
}