{
  "type": "Feature",
  "properties": {
    "addr:full":"4 Gibbons St Nottingham Nottinghamshire NG7 2SB",
    "addr:housenumber":"4",
    "addr:postcode":"ng7 2sb",
    "addr:street":"Gibbons St",
    "iso:country":"GB",
    "sg:address":"4 Gibbons St",
    "sg:city":"Nottingham",
    "sg:classifiers":[
        {
            "category":"Building & Trades",
            "subcategory":"Construction",
            "type":"Services"
        }
    ],
    "sg:phone":"+44 115 979 2800",
    "sg:postcode":"NG7 2SB",
    "sg:province":"Nottinghamshire",
    "sg:tags":[
        "demolition",
        "contractor"
    ],
    "wof:name":"Demco Demolition Ltd",
    "wof:placetype":"venue"
},
  "geometry": {"coordinates":[-1.1795619726,52.9364051819],"type":"Point"}
}