{
  "type": "Feature",
  "properties": {
    "addr:full":"321 Rayleigh Rd Leigh On Sea Essex SS9 5PX",
    "addr:housenumber":"321",
    "addr:postcode":"ss9 5px",
    "addr:street":"Rayleigh Rd",
    "iso:country":"GB",
    "sg:address":"321 Rayleigh Rd",
    "sg:city":"Leigh On Sea",
    "sg:classifiers":[
        {
            "category":"Restaurant",
            "type":"Food & Drink"
        }
    ],
    "sg:phone":"+44 1702 524271",
    "sg:postcode":"SS9 5PX",
    "sg:province":"Essex",
    "wof:name":"Bellhouse Harvester The",
    "wof:placetype":"venue"
},
  "geometry": {"coordinates":[0.6520249844,51.5696296692],"type":"Point"}
}