{
  "type": "Feature",
  "properties": {
    "addr:full":"162a London Rd Kingston-upon-thames Greater London KT2 6QW",
    "addr:housenumber":"162a",
    "addr:postcode":"kt2 6qw",
    "addr:street":"London Rd",
    "iso:country":"GB",
    "sg:address":"162a London Rd",
    "sg:city":"Kingston-upon-thames",
    "sg:classifiers":[
        {
            "category":"Manufacturing",
            "subcategory":"Electronics",
            "type":"Manufacturing & Wholesale Goods"
        },
        {
            "category":"Communications",
            "type":"Services"
        }
    ],
    "sg:phone":"+44 20 8547 1666",
    "sg:postcode":"KT2 6QW",
    "sg:province":"Greater London",
    "sg:tags":[
        "control",
        "tv",
        "-",
        "component",
        "video",
        "radio",
        "electronic"
    ],
    "wof:name":"Multi-Tech",
    "wof:placetype":"venue"
},
  "geometry": {"coordinates":[-0.2891600132,51.4124412537],"type":"Point"}
}