{
  "type": "Feature",
  "properties": {
    "addr:full":"121 Sun Lane Gravesend Kent DA12 5HW",
    "addr:housenumber":"121",
    "addr:postcode":"da12 5hw",
    "addr:street":"Sun Lane",
    "iso:country":"GB",
    "sg:address":"121 Sun Lane",
    "sg:city":"Gravesend",
    "sg:classifiers":[
        {
            "category":"Retail",
            "subcategory":"Auto Repair",
            "type":"Services"
        }
    ],
    "sg:phone":"+44 1474 534779",
    "sg:postcode":"DA12 5HW",
    "sg:province":"Kent",
    "sg:tags":[
        "modification",
        "garage"
    ],
    "wof:name":"Gemini Engineering",
    "wof:placetype":"venue"
},
  "geometry": {"coordinates":[0.3765470088,51.4269332886],"type":"Point"}
}