{
  "type": "Feature",
  "properties": {
    "addr:full":"236 Tokynton Avenue Wembley Greater London HA9 6HJ",
    "addr:housenumber":"236",
    "addr:postcode":"ha9 6hj",
    "addr:street":"Tokynton Avenue",
    "iso:country":"GB",
    "sg:address":"236 Tokynton Avenue",
    "sg:city":"Wembley",
    "sg:classifiers":[
        {
            "category":"Shopping",
            "subcategory":"Books",
            "type":"Retail Goods"
        }
    ],
    "sg:phone":"+44 20 8903 8670",
    "sg:postcode":"HA9 6HJ",
    "sg:province":"Greater London",
    "wof:name":"Valley Press",
    "wof:placetype":"venue"
},
  "geometry": {"coordinates":[-0.282223,51.548195],"type":"Point"}
}