{
  "type": "Feature",
  "properties": {
    "iso:country":"GB",
    "sg:address":"Unit 12 Blackness Avenue, Altens Industrial Estate",
    "sg:city":"Aberdeen",
    "sg:classifiers":[
        {
            "category":"Professional",
            "subcategory":"Testing Lab",
            "type":"Services"
        }
    ],
    "sg:postcode":"AB12 3PG",
    "sg:province":"Aberdeen City",
    "sg:tags":[
        "inspection",
        "calibration"
    ],
    "wof:name":"Drilling Tools Inspection Services Ltd.",
    "wof:placetype":"venue"
},
  "geometry": {"coordinates":[-2.075509,57.110714],"type":"Point"}
}