{
  "type": "Feature",
  "properties": {
    "iso:country":"GB",
    "sg:address":"Unit C Kingsbury Works, Kingsbury Rd",
    "sg:city":"Colindale",
    "sg:classifiers":[
        {
            "category":"Retail",
            "subcategory":"Auto Repair",
            "type":"Services"
        }
    ],
    "sg:phone":"+44 20 8205 0610",
    "sg:postcode":"NW9 8UP",
    "sg:province":"Greater London",
    "sg:tags":[
        "modification",
        "garage"
    ],
    "wof:name":"Europa Motors",
    "wof:placetype":"venue"
},
  "geometry": {"coordinates":[-0.2608299851,51.5815086365],"type":"Point"}
}