{
  "type": "Feature",
  "properties": {
    "addr:full":"28 Waterloo Street Weston-super-mare Somerset BS23 1LN",
    "addr:housenumber":"28",
    "addr:postcode":"bs23 1ln",
    "addr:street":"Waterloo Street",
    "iso:country":"GB",
    "sg:address":"28 Waterloo Street",
    "sg:city":"Weston-super-mare",
    "sg:classifiers":[
        {
            "category":"Communications",
            "subcategory":"Newspaper",
            "type":"Services"
        }
    ],
    "sg:phone":"+44 1934 629934",
    "sg:postcode":"BS23 1LN",
    "sg:province":"Somerset",
    "sg:tags":[
        "magazine"
    ],
    "wof:name":"The Evening Post",
    "wof:placetype":"venue"
},
  "geometry": {"coordinates":[-2.9775629044,51.3500175476],"type":"Point"}
}