{
  "type": "Feature",
  "properties": {
    "addr:full":"92a Walgrove Road Chesterfield Derbyshire S40 2DS",
    "addr:housenumber":"92a",
    "addr:postcode":"s40 2ds",
    "addr:street":"Walgrove Road",
    "iso:country":"GB",
    "sg:address":"92a Walgrove Road",
    "sg:city":"Chesterfield",
    "sg:classifiers":[
        {
            "category":"Retail",
            "subcategory":"Auto Repair",
            "type":"Services"
        }
    ],
    "sg:phone":"+44 1246 278181",
    "sg:postcode":"S40 2DS",
    "sg:province":"Derbyshire",
    "sg:tags":[
        "modification",
        "garage"
    ],
    "wof:name":"Walgrove Garage Ltd.",
    "wof:placetype":"venue"
},
  "geometry": {"coordinates":[-1.450916,53.230129],"type":"Point"}
}