{
  "type": "Feature",
  "properties": {
    "addr:full":"Middle Marsh Farm, Burgh Le Marsh Skegness Lincolnshire PE24 5EF",
    "addr:housenumber":"le marsh",
    "addr:postcode":"pe24 5ef",
    "addr:street":"Middle",
    "iso:country":"GB",
    "sg:address":"Middle Marsh Farm, Burgh Le Marsh",
    "sg:city":"Skegness",
    "sg:classifiers":[
        {
            "category":"Farming",
            "subcategory":"Farm",
            "type":"Manufacturing & Wholesale Goods"
        }
    ],
    "sg:phone":"+44 1754 810866",
    "sg:postcode":"PE24 5EF",
    "sg:province":"Lincolnshire",
    "sg:tags":[
        "mixed",
        "crop"
    ],
    "wof:name":"J Dodsworth",
    "wof:placetype":"venue"
},
  "geometry": {"coordinates":[0.242941,53.161354],"type":"Point"}
}