{
  "type": "Feature",
  "properties": {
    "addr:full":"8 Woodland Way Merthyr Tydfil Caerphilly CF48 1SQ",
    "addr:housenumber":"8",
    "addr:postcode":"cf48 1sq",
    "addr:street":"Woodland Way",
    "iso:country":"GB",
    "sg:address":"8 Woodland Way",
    "sg:city":"Merthyr Tydfil",
    "sg:classifiers":[
        {
            "category":"Building & Trades",
            "subcategory":"Construction",
            "type":"Services"
        }
    ],
    "sg:phone":"+44 1685 382820",
    "sg:postcode":"CF48 1SQ",
    "sg:province":"Caerphilly",
    "sg:tags":[
        "builder"
    ],
    "wof:name":"Neil Evans",
    "wof:placetype":"venue"
},
  "geometry": {"coordinates":[-3.403145,51.744019],"type":"Point"}
}