{
  "type": "Feature",
  "properties": {
    "iso:country":"GB",
    "sg:address":"15 Market Place",
    "sg:city":"Hertford",
    "sg:classifiers":[
        {
            "category":"Shopping",
            "subcategory":"Thrift Store",
            "type":"Retail Goods"
        }
    ],
    "sg:phone":"+44 1992 584343",
    "sg:postcode":"SG14 1DQ",
    "sg:province":"Hertfordshire",
    "sg:tags":[
        "shop",
        "charity"
    ],
    "wof:name":"Oxfam Charity Shop",
    "wof:placetype":"venue"
},
  "geometry": {"coordinates":[-0.0771360025,51.7962722778],"type":"Point"}
}