{
  "type": "Feature",
  "properties": {
    "iso:country":"GB",
    "sg:address":"86 Seaside",
    "sg:city":"Eastbourne",
    "sg:classifiers":[
        {
            "category":"Fast Food",
            "type":"Food & Drink"
        }
    ],
    "sg:postcode":"BN22 7QP",
    "sg:province":"East Sussex",
    "sg:tags":[
        "away",
        "take"
    ],
    "wof:name":"Dolphin Fish Bar",
    "wof:placetype":"venue"
},
  "geometry": {"coordinates":[0.294805,50.771809],"type":"Point"}
}