{
  "type": "Feature",
  "properties": {
    "iso:country":"GB",
    "sg:address":"134 Thaxted Rd",
    "sg:city":"Saffron Walden",
    "sg:classifiers":[
        {
            "category":"Health Services",
            "subcategory":"Health Practitioner",
            "type":"Services"
        }
    ],
    "sg:phone":"+44 1799 528323",
    "sg:postcode":"CB11 3BJ",
    "sg:province":"Essex",
    "sg:tags":[
        "psychotherapist"
    ],
    "wof:name":"F Mouchet",
    "wof:placetype":"venue"
},
  "geometry": {"coordinates":[0.25193,52.017914],"type":"Point"}
}