{
  "type": "Feature",
  "properties": {
    "addr:full":"37 Park Hall Road London Greater London N2 9PT",
    "addr:housenumber":"37",
    "addr:postcode":"n2 9pt",
    "addr:street":"Park Hall Road",
    "iso:country":"GB",
    "sg:address":"37 Park Hall Road",
    "sg:city":"London",
    "sg:classifiers":[
        {
            "category":"Education",
            "subcategory":"Special Training",
            "type":"Public Place"
        }
    ],
    "sg:phone":"+44 20 8365 3869",
    "sg:postcode":"N2 9PT",
    "sg:province":"Greater London",
    "sg:tags":[
        "product",
        "centre"
    ],
    "wof:name":"The Society for Effective Affective Learning",
    "wof:placetype":"venue"
},
  "geometry": {"coordinates":[-0.1617839932,51.5885162354],"type":"Point"}
}