{
  "type": "Feature",
  "properties": {
    "iso:country":"GB",
    "sg:address":"116 Crewe Road, Shavington",
    "sg:city":"Crewe",
    "sg:classifiers":[
        {
            "category":"Organizations",
            "subcategory":"Membership Organization",
            "type":"Services"
        }
    ],
    "sg:phone":"+44 1270 569066",
    "sg:postcode":"CW2 5DL",
    "sg:province":"Cheshire",
    "sg:tags":[
        "club",
        "social"
    ],
    "wof:name":"Shavington Social Club & Institute Ltd",
    "wof:placetype":"venue"
},
  "geometry": {"coordinates":[-2.4440250397,53.0649642944],"type":"Point"}
}