{
  "type": "Feature",
  "properties": {
    "addr:full":"78 Lower Weybourne Lane Farnham Surrey GU9 9HP",
    "addr:housenumber":"78",
    "addr:postcode":"gu9 9hp",
    "addr:street":"Lower Weybourne Lane",
    "iso:country":"GB",
    "sg:address":"78 Lower Weybourne Lane",
    "sg:city":"Farnham",
    "sg:classifiers":[
        {
            "category":"Home & Garden",
            "subcategory":"Building Materials",
            "type":"Retail Goods"
        }
    ],
    "sg:postcode":"GU9 9HP",
    "sg:province":"Surrey",
    "sg:tags":[
        "equipment",
        "disability"
    ],
    "wof:name":"McCabe Builders",
    "wof:placetype":"venue"
},
  "geometry": {"coordinates":[-0.7841179967,51.2370071411],"type":"Point"}
}