{
  "type": "Feature",
  "properties": {
    "iso:country":"GB",
    "sg:address":"24-26 Penel Orlieu",
    "sg:city":"Bridgwater",
    "sg:classifiers":[
        {
            "category":"Building & Trades",
            "subcategory":"Construction",
            "type":"Services"
        }
    ],
    "sg:phone":"+44 1278 459725",
    "sg:postcode":"TA6 3PF",
    "sg:province":"Somerset",
    "sg:tags":[
        "builder"
    ],
    "wof:name":"Lilley & Lilley Building Contractors",
    "wof:placetype":"venue"
},
  "geometry": {"coordinates":[-3.007929,51.127689],"type":"Point"}
}