{
  "type": "Feature",
  "properties": {
    "addr:full":"Russell Drive, Keyingham Hull East Riding of Yorkshire HU12 9RU",
    "addr:postcode":"hu12 9ru",
    "addr:street":"Russell Drive",
    "iso:country":"GB",
    "sg:address":"Russell Drive, Keyingham",
    "sg:city":"Hull",
    "sg:classifiers":[
        {
            "category":"Education",
            "subcategory":"School",
            "type":"Public Place"
        }
    ],
    "sg:phone":"+44 1964 623930",
    "sg:postcode":"HU12 9RU",
    "sg:province":"East Riding of Yorkshire",
    "sg:tags":[
        "local",
        "authority"
    ],
    "wof:name":"Keyingham County Infants School",
    "wof:placetype":"venue"
},
  "geometry": {"coordinates":[-0.109569,53.708321],"type":"Point"}
}