{
  "type": "Feature",
  "properties": {
    "addr:full":"175 St Sepulchre Gate West Doncaster South Yorkshire DN1 3AW",
    "addr:housenumber":"175",
    "addr:postcode":"dn1 3aw",
    "addr:street":"St Sepulchre Gate West",
    "iso:country":"GB",
    "sg:address":"175 St Sepulchre Gate West",
    "sg:city":"Doncaster",
    "sg:classifiers":[
        {
            "category":"Personal",
            "subcategory":"Beauty Salon",
            "type":"Services"
        }
    ],
    "sg:phone":"+44 1302 349819",
    "sg:postcode":"DN1 3AW",
    "sg:province":"South Yorkshire",
    "sg:tags":[
        "lady",
        "hairdresser"
    ],
    "wof:name":"Wendy's",
    "wof:placetype":"venue"
},
  "geometry": {"coordinates":[-1.138298,53.518482],"type":"Point"}
}