{
  "type": "Feature",
  "properties": {
    "addr:full":"Netherton Ho, Netherton Rd Glasgow Glasgow City G13 1AX",
    "addr:postcode":"g13 1ax",
    "addr:street":"Netherton Rd",
    "iso:country":"GB",
    "sg:address":"Netherton Ho, Netherton Rd",
    "sg:city":"Glasgow",
    "sg:classifiers":[
        {
            "category":"Home & Garden",
            "subcategory":"Carpets & Floor Coverings",
            "type":"Retail Goods"
        }
    ],
    "sg:phone":"+44 141 950 6233",
    "sg:postcode":"G13 1AX",
    "sg:province":"Glasgow City",
    "sg:tags":[
        "cleaner",
        "upholstery"
    ],
    "wof:name":"ServiceMaster",
    "wof:placetype":"venue"
},
  "geometry": {"coordinates":[-4.3286957741,55.8973503113],"type":"Point"}
}