{
  "type": "Feature",
  "properties": {
    "iso:country":"GB",
    "sg:address":"90 Nags Head Hill",
    "sg:city":"Bristol",
    "sg:classifiers":[
        {
            "category":"Personal",
            "subcategory":"Barber",
            "type":"Services"
        }
    ],
    "sg:phone":"+44 117 947 5061",
    "sg:postcode":"BS5 8QL",
    "sg:province":"City of Bristol",
    "sg:tags":[
        "men's",
        "hairdresser"
    ],
    "wof:name":"Tony's Hairstylists",
    "wof:placetype":"venue"
},
  "geometry": {"coordinates":[-2.528059,51.454823],"type":"Point"}
}