{
  "type": "Feature",
  "properties": {
    "addr:full":"269 Acklam Road Middlesbrough North Yorkshire TS5 7BP",
    "addr:housenumber":"269",
    "addr:postcode":"ts5 7bp",
    "addr:street":"Acklam Road",
    "iso:country":"GB",
    "sg:address":"269 Acklam Road",
    "sg:city":"Middlesbrough",
    "sg:classifiers":[
        {
            "category":"Food & Beverages",
            "subcategory":"Fruits & Vegetables",
            "type":"Retail Goods"
        }
    ],
    "sg:phone":"+44 1642 815441",
    "sg:postcode":"TS5 7BP",
    "sg:province":"North Yorkshire",
    "sg:tags":[
        "greengrocer"
    ],
    "wof:name":"Cane's",
    "wof:placetype":"venue"
},
  "geometry": {"coordinates":[-1.2579519749,54.545627594],"type":"Point"}
}