{
  "type": "Feature",
  "properties": {
    "iso:country":"GB",
    "sg:address":"374 Caledonian Road",
    "sg:city":"London",
    "sg:classifiers":[
        {
            "category":"Communications",
            "type":"Services"
        }
    ],
    "sg:phone":"+44 20 7700 5528",
    "sg:postcode":"N1 1DY",
    "sg:province":"Greater London",
    "sg:tags":[
        "telecommunication"
    ],
    "wof:name":"Iftah Communications",
    "wof:placetype":"venue"
},
  "geometry": {"coordinates":[-0.117032,51.541759],"type":"Point"}
}