{
  "type": "Feature",
  "properties": {
    "addr:full":"6 The Street, Wrecclesham Farnham Hampshire GU10 4PR",
    "addr:housenumber":"6",
    "addr:postcode":"gu10 4pr",
    "addr:street":"The Street",
    "iso:country":"GB",
    "sg:address":"6 The Street, Wrecclesham",
    "sg:city":"Farnham",
    "sg:classifiers":[
        {
            "category":"Retail",
            "subcategory":"Repair Shop",
            "type":"Services"
        }
    ],
    "sg:phone":"+44 1252 710909",
    "sg:postcode":"GU10 4PR",
    "sg:province":"Hampshire",
    "sg:tags":[
        "upholsterer"
    ],
    "wof:name":"J A Corrigan Upholstery",
    "wof:placetype":"venue"
},
  "geometry": {"coordinates":[-0.817967,51.199474],"type":"Point"}
}