{
  "type": "Feature",
  "properties": {
    "iso:country":"GB",
    "sg:address":"511 Ridgeway Road",
    "sg:city":"Sheffield",
    "sg:classifiers":[
        {
            "category":"Military Area",
            "subcategory":"Air Force Base",
            "type":"Public Place"
        }
    ],
    "sg:phone":"+44 114 239 3939",
    "sg:postcode":"S12 2JY",
    "sg:province":"Derbyshire",
    "sg:tags":[
        "taxi",
        "hire",
        "private"
    ],
    "wof:name":"Confederate Car Co",
    "wof:placetype":"venue"
},
  "geometry": {"coordinates":[-1.427625,53.354759],"type":"Point"}
}