{
  "type": "Feature",
  "properties": {
    "iso:country":"GB",
    "sg:address":"Hanover House, Seldown Road",
    "sg:city":"Poole",
    "sg:classifiers":[
        {
            "category":"Organizations",
            "subcategory":"Community Association",
            "type":"Services"
        }
    ],
    "sg:phone":"+44 1202 673360",
    "sg:postcode":"BH15 1UE",
    "sg:province":"Dorset",
    "sg:tags":[
        "co-operatives",
        "society",
        "housing",
        "trust"
    ],
    "wof:name":"Hanover Housing Association Ltd",
    "wof:placetype":"venue"
},
  "geometry": {"coordinates":[-1.974101,50.719795],"type":"Point"}
}