{
  "type": "Feature",
  "properties": {
    "iso:country":"GB",
    "sg:address":"95 Main Street, Broughton Astley",
    "sg:city":"Leicester",
    "sg:classifiers":[
        {
            "category":"Home & Garden",
            "subcategory":"Household Appliances",
            "type":"Retail Goods"
        }
    ],
    "sg:phone":"+44 1455 285350",
    "sg:postcode":"LE9 6RE",
    "sg:province":"Leicestershire",
    "sg:tags":[
        "refrigeration",
        "air conditioning"
    ],
    "wof:name":"T L M Services Ltd.",
    "wof:placetype":"venue"
},
  "geometry": {"coordinates":[-1.230218,52.534386],"type":"Point"}
}