{
  "type": "Feature",
  "properties": {
    "iso:country":"GB",
    "sg:address":"79 Kenwood Drive",
    "sg:city":"Beckenham",
    "sg:classifiers":[
        {
            "category":"Professional",
            "type":"Services"
        }
    ],
    "sg:phone":"+44 20 8650 9701",
    "sg:postcode":"BR3 6QZ",
    "sg:province":"Kent",
    "sg:tags":[
        "caterer"
    ],
    "wof:name":"Flowering Cherry Catering",
    "wof:placetype":"venue"
},
  "geometry": {"coordinates":[-0.0120369997,51.4002380371],"type":"Point"}
}