{
  "type": "Feature",
  "properties": {
    "addr:full":"8 Daines Way Southend On Sea Essex SS1 3PF",
    "addr:housenumber":"8",
    "addr:postcode":"ss1 3pf",
    "addr:street":"Daines Way",
    "iso:country":"GB",
    "sg:address":"8 Daines Way",
    "sg:city":"Southend On Sea",
    "sg:classifiers":[
        {
            "category":"Professional",
            "subcategory":"Accounting & Tax Preparation",
            "type":"Services"
        }
    ],
    "sg:phone":"+44 1702 585056",
    "sg:postcode":"SS1 3PF",
    "sg:province":"Essex",
    "sg:tags":[
        "accountant"
    ],
    "wof:name":"E W Hughes",
    "wof:placetype":"venue"
},
  "geometry": {"coordinates":[0.76127702,51.5392570496],"type":"Point"}
}