{
  "type": "Feature",
  "properties": {
    "iso:country":"GB",
    "sg:address":"27 Oldford Road",
    "sg:city":"London",
    "sg:classifiers":[
        {
            "category":"Taxi",
            "type":"Transportation"
        }
    ],
    "sg:phone":"+44 20 8981 7111",
    "sg:postcode":"E2 9PJ",
    "sg:province":"Greater London",
    "sg:tags":[
        "mini",
        "cab"
    ],
    "wof:name":"Lady Cars",
    "wof:placetype":"venue"
},
  "geometry": {"coordinates":[-0.054143,51.529926],"type":"Point"}
}