{
  "type": "Feature",
  "properties": {
    "iso:country":"GB",
    "sg:address":"4-10 Swan Street, Bawtry",
    "sg:city":"Doncaster",
    "sg:classifiers":[
        {
            "category":"Shopping",
            "subcategory":"Antiques",
            "type":"Retail Goods"
        }
    ],
    "sg:phone":"+44 1302 710621",
    "sg:postcode":"DN10 6JQ",
    "sg:province":"Lincolnshire",
    "wof:name":"TREASURE HOUSE ANTIQUES CENTRE",
    "wof:placetype":"venue"
},
  "geometry": {"coordinates":[-1.0209709406,53.4286689758],"type":"Point"}
}