{
  "type": "Feature",
  "properties": {
    "iso:country":"GB",
    "sg:address":"Unit 4 Park Business Centre, Park Road",
    "sg:city":"Southampton",
    "sg:classifiers":[
        {
            "category":"Professional",
            "type":"Services"
        }
    ],
    "sg:phone":"+44 23 8023 0045",
    "sg:postcode":"SO15 3US",
    "sg:province":"Hampshire",
    "sg:tags":[
        "marine"
    ],
    "wof:name":"B P S C Marine Services",
    "wof:placetype":"venue"
},
  "geometry": {"coordinates":[-1.407319,50.909939],"type":"Point"}
}