{
  "type": "Feature",
  "properties": {
    "addr:full":"73 Fore Street, Barton Torquay Devon TQ2 8BP",
    "addr:housenumber":"73",
    "addr:postcode":"tq2 8bp",
    "addr:street":"Fore Street",
    "iso:country":"GB",
    "sg:address":"73 Fore Street, Barton",
    "sg:city":"Torquay",
    "sg:classifiers":[
        {
            "category":"Food & Beverages",
            "subcategory":"Meat & Fish",
            "type":"Retail Goods"
        }
    ],
    "sg:postcode":"TQ2 8BP",
    "sg:province":"Devon",
    "sg:tags":[
        "chip"
    ],
    "wof:name":"Granville's",
    "wof:placetype":"venue"
},
  "geometry": {"coordinates":[-3.53165,50.491177],"type":"Point"}
}