{
  "type": "Feature",
  "properties": {
    "iso:country":"GB",
    "sg:address":"Shop 3 Station Ave",
    "sg:city":"Filey",
    "sg:classifiers":[
        {
            "category":"Shopping",
            "subcategory":"Comic Books",
            "type":"Retail Goods"
        }
    ],
    "sg:postcode":"YO14 9AQ",
    "sg:province":"North Yorkshire",
    "sg:tags":[
        "jeweller"
    ],
    "wof:name":"Ashton,Susan,",
    "wof:placetype":"venue"
},
  "geometry": {"coordinates":[-0.2907490134,54.2118453979],"type":"Point"}
}