{
  "type": "Feature",
  "properties": {
    "addr:full":"Scapa Distillery, St Olas Kirkwall Orkney Islands KW15 1SE",
    "addr:postcode":"kw15 1se",
    "addr:street":"St",
    "iso:country":"GB",
    "sg:address":"Scapa Distillery, St Olas",
    "sg:city":"Kirkwall",
    "sg:classifiers":[
        {
            "category":"Distillery",
            "subcategory":"None",
            "type":"Food & Drink"
        }
    ],
    "sg:phone":"+44 1856 872071",
    "sg:postcode":"KW15 1SE",
    "sg:province":"Orkney Islands",
    "wof:name":"Punch Retail Ltd",
    "wof:placetype":"venue"
},
  "geometry": {"coordinates":[-2.9604189396,58.9817314148],"type":"Point"}
}