{
  "type": "Feature",
  "properties": {
    "iso:country":"GB",
    "sg:address":"107 Selkirk Road",
    "sg:city":"London",
    "sg:classifiers":[
        {
            "category":"Shopping",
            "subcategory":"Stationery & Office Supplies",
            "type":"Retail Goods"
        }
    ],
    "sg:postcode":"SW17 0EW",
    "sg:province":"Greater London",
    "wof:name":"B M Wholesale",
    "wof:placetype":"venue"
},
  "geometry": {"coordinates":[-0.171327,51.430386],"type":"Point"}
}