{
  "type": "Feature",
  "properties": {
    "iso:country":"GB",
    "sg:address":"1 Duncan Clo, St Mellons",
    "sg:city":"Cardiff",
    "sg:classifiers":[
        {
            "category":"Building & Trades",
            "subcategory":"Construction",
            "type":"Services"
        }
    ],
    "sg:postcode":"CF3 1NP",
    "sg:province":"Caerphilly",
    "sg:tags":[
        "joiner",
        "carpenter"
    ],
    "wof:name":"Jones,G,",
    "wof:placetype":"venue"
},
  "geometry": {"coordinates":[-3.113557,51.52132],"type":"Point"}
}