{
  "type": "Feature",
  "properties": {
    "addr:full":"39 Lordswood Road Birmingham West Midlands B17 9QT",
    "addr:housenumber":"39",
    "addr:postcode":"b17 9qt",
    "addr:street":"Lordswood Road",
    "iso:country":"GB",
    "sg:address":"39 Lordswood Road",
    "sg:city":"Birmingham",
    "sg:classifiers":[
        {
            "category":"Retail",
            "subcategory":"Veterinary Services",
            "type":"Services"
        }
    ],
    "sg:phone":"+44 121 426 4343",
    "sg:postcode":"B17 9QT",
    "sg:province":"West Midlands",
    "sg:tags":[
        "surgeon"
    ],
    "wof:name":"Clifford & Watts",
    "wof:placetype":"venue"
},
  "geometry": {"coordinates":[-1.9591259956,52.4588050842],"type":"Point"}
}