{
  "type": "Feature",
  "properties": {
    "addr:full":"114 Greenacre Nottingham Nottinghamshire NG12 4BB",
    "addr:housenumber":"114",
    "addr:postcode":"ng12 4bb",
    "addr:street":"Greenacre",
    "iso:country":"GB",
    "sg:address":"114 Greenacre",
    "sg:city":"Nottingham",
    "sg:classifiers":[
        {
            "category":"Building & Trades",
            "subcategory":"Construction",
            "type":"Services"
        }
    ],
    "sg:phone":"+44 115 945 2995",
    "sg:postcode":"NG12 4BB",
    "sg:province":"Nottinghamshire",
    "sg:tags":[
        "builder"
    ],
    "wof:name":"S B Building Services",
    "wof:placetype":"venue"
},
  "geometry": {"coordinates":[-1.110754,52.915314],"type":"Point"}
}