{
  "type": "Feature",
  "properties": {
    "iso:country":"GB",
    "sg:address":"Port Tennant Works, Fabian Way",
    "sg:city":"Swansea",
    "sg:classifiers":[
        {
            "category":"Home & Garden",
            "subcategory":"Hardware",
            "type":"Retail Goods"
        }
    ],
    "sg:phone":"+44 1792 492400",
    "sg:postcode":"SA1 8PS",
    "sg:province":"Neath Port Talbot",
    "sg:tags":[
        "product",
        "wire",
        "electrical"
    ],
    "wof:name":"Aluminium Wire & Conductor Plc",
    "wof:placetype":"venue"
},
  "geometry": {"coordinates":[-3.927149,51.621494],"type":"Point"}
}