{
  "type": "Feature",
  "properties": {
    "iso:country":"GB",
    "sg:address":"Allen Ho, Newarke St",
    "sg:city":"Leicester",
    "sg:classifiers":[
        {
            "category":"Professional",
            "subcategory":"Engineering",
            "type":"Services"
        }
    ],
    "sg:postcode":"LE1 5SG",
    "sg:province":"Leicestershire",
    "sg:tags":[
        "civil",
        "engineer"
    ],
    "wof:name":"Glenfield Keytec International Ltd",
    "wof:placetype":"venue"
},
  "geometry": {"coordinates":[-1.1386979818,52.6317672729],"type":"Point"}
}