{
  "type": "Feature",
  "properties": {
    "iso:country":"GB",
    "sg:address":"Northside Westfloat, Dock Road",
    "sg:city":"Birkenhead",
    "sg:classifiers":[
        {
            "category":"Manufacturing",
            "subcategory":"Watercraft",
            "type":"Manufacturing & Wholesale Goods"
        }
    ],
    "sg:postcode":"CH41 1DF",
    "sg:province":"Merseyside",
    "sg:tags":[
        "repair",
        "ship",
        "builder"
    ],
    "wof:name":"F J Marine Services",
    "wof:placetype":"venue"
},
  "geometry": {"coordinates":[-3.025489,53.392567],"type":"Point"}
}