{
  "type": "Feature",
  "properties": {
    "addr:full":"The Stables, Springfield Road Chorley Lancashire PR7 1JB",
    "addr:postcode":"pr7 1jb",
    "addr:street":"Springfield Road",
    "iso:country":"GB",
    "sg:address":"The Stables, Springfield Road",
    "sg:city":"Chorley",
    "sg:classifiers":[
        {
            "category":"Professional",
            "subcategory":"Accounting & Tax Preparation",
            "type":"Services"
        }
    ],
    "sg:phone":"+44 1257 264788",
    "sg:postcode":"PR7 1JB",
    "sg:province":"Lancashire",
    "sg:tags":[
        "accountant"
    ],
    "wof:name":"Astley Business Services",
    "wof:placetype":"venue"
},
  "geometry": {"coordinates":[-2.636314,53.65398],"type":"Point"}
}