{
  "type": "Feature",
  "properties": {
    "addr:full":"16-17 Lewisham Centre, Riverdale Lewisham Greater London SE13 7EP",
    "addr:housenumber":"16-17",
    "addr:postcode":"se13 7ep",
    "addr:street":"Lewisham Centre",
    "iso:country":"GB",
    "sg:address":"16-17 Lewisham Centre, Riverdale",
    "sg:city":"Lewisham",
    "sg:classifiers":[
        {
            "category":"Shopping",
            "subcategory":"Clothing, Apparel, & Fashions",
            "type":"Retail Goods"
        }
    ],
    "sg:phone":"+44 20 8852 0779",
    "sg:postcode":"SE13 7EP",
    "sg:province":"Greater London",
    "sg:tags":[
        "shop"
    ],
    "wof:name":"Evans Ltd",
    "wof:placetype":"venue"
},
  "geometry": {"coordinates":[-0.0096699996,51.4666976929],"type":"Point"}
}