{
  "type": "Feature",
  "properties": {
    "addr:full":"89 The Broadway Sunderland Tyne and Wear SR4 8PQ",
    "addr:housenumber":"89",
    "addr:postcode":"sr4 8pq",
    "addr:street":"The Broadway",
    "iso:country":"GB",
    "sg:address":"89 The Broadway",
    "sg:city":"Sunderland",
    "sg:classifiers":[
        {
            "category":"Personal",
            "subcategory":"Beauty Salon",
            "type":"Services"
        }
    ],
    "sg:phone":"+44 191 528 4242",
    "sg:postcode":"SR4 8PQ",
    "sg:province":"Tyne and Wear",
    "sg:tags":[
        "unisex",
        "hairdresser"
    ],
    "wof:name":"The Broadway Hair Salon",
    "wof:placetype":"venue"
},
  "geometry": {"coordinates":[-1.4331120253,54.8939208984],"type":"Point"}
}