{
  "type": "Feature",
  "properties": {
    "iso:country":"GB",
    "sg:address":"8b Brook Parade, High Road",
    "sg:city":"Chigwell",
    "sg:classifiers":[
        {
            "category":"Shopping",
            "subcategory":"Clothing, Apparel, & Fashions",
            "type":"Retail Goods"
        },
        {
            "category":"Shopping",
            "subcategory":"Baby Store",
            "type":"Retail Goods"
        }
    ],
    "sg:phone":"+44 20 8559 9937",
    "sg:postcode":"IG7 6PE",
    "sg:province":"Essex",
    "sg:tags":[
        "child",
        "childrens",
        "babywear"
    ],
    "wof:name":"Storm Kids",
    "wof:placetype":"venue"
},
  "geometry": {"coordinates":[0.071166,51.620594],"type":"Point"}
}