{
  "type": "Feature",
  "properties": {
    "addr:full":"34 Springburn Way Glasgow East Dunbartonshire G21 1DW",
    "addr:housenumber":"34",
    "addr:postcode":"g21 1dw",
    "addr:street":"Springburn Way",
    "iso:country":"GB",
    "sg:address":"34 Springburn Way",
    "sg:city":"Glasgow",
    "sg:classifiers":[
        {
            "category":"Retail",
            "subcategory":"Funeral Services",
            "type":"Services"
        }
    ],
    "sg:phone":"+44 141 558 6201",
    "sg:postcode":"G21 1DW",
    "sg:province":"East Dunbartonshire",
    "wof:name":"Co-Operative Funeral Services",
    "wof:placetype":"venue"
},
  "geometry": {"coordinates":[-4.233123,55.881207],"type":"Point"}
}