{
  "type": "Feature",
  "properties": {
    "addr:full":"78 Kingsway South, Latchford Warrington Cheshire WA4 1QA",
    "addr:housenumber":"78",
    "addr:postcode":"wa4 1qa",
    "addr:street":"Kingsway",
    "iso:country":"GB",
    "sg:address":"78 Kingsway South, Latchford",
    "sg:city":"Warrington",
    "sg:classifiers":[
        {
            "category":"Bus Charters",
            "type":"Transportation"
        }
    ],
    "sg:phone":"+44 1925 633344",
    "sg:postcode":"WA4 1QA",
    "sg:province":"Cheshire",
    "sg:tags":[
        "hire",
        "coach"
    ],
    "wof:name":"A A Mini Coaches",
    "wof:placetype":"venue"
},
  "geometry": {"coordinates":[-2.561295,53.384029],"type":"Point"}
}