{
  "type": "Feature",
  "properties": {
    "addr:full":"58 Edison Road, Rabans Lane Industrial Estate Aylesbury Buckinghamshire HP19 8UT",
    "addr:housenumber":"58",
    "addr:postcode":"hp19 8ut",
    "addr:street":"Edison Road Rabans Lane Industrial Estate",
    "iso:country":"GB",
    "sg:address":"58 Edison Road, Rabans Lane Industrial Estate",
    "sg:city":"Aylesbury",
    "sg:classifiers":[
        {
            "category":"Professional",
            "subcategory":"Computer Services",
            "type":"Services"
        }
    ],
    "sg:phone":"+44 1296 505100",
    "sg:postcode":"HP19 8UT",
    "sg:province":"Buckinghamshire",
    "sg:tags":[
        "system",
        "software"
    ],
    "wof:name":"Compusys Plc",
    "wof:placetype":"venue"
},
  "geometry": {"coordinates":[-0.8527500033,51.8227996826],"type":"Point"}
}