{
  "type": "Feature",
  "properties": {
    "iso:country":"GB",
    "sg:address":"Dunganachy House, Balivanich",
    "sg:city":"Isle Of Benbecula",
    "sg:classifiers":[
        {
            "category":"Recreation",
            "subcategory":"Campground",
            "type":"Entertainment"
        }
    ],
    "sg:postcode":"HS7 5LX",
    "sg:province":"Eilean Siar",
    "sg:tags":[
        "caravan",
        "park"
    ],
    "wof:name":"J Macdonald",
    "wof:placetype":"venue"
},
  "geometry": {"coordinates":[-7.3910079002,57.4736862183],"type":"Point"}
}