{
  "type": "Feature",
  "properties": {
    "addr:full":"Roe Lodge, Sowery Row, Southwaite Carlisle Cumbria CA4 0LH",
    "addr:postcode":"ca4 0lh",
    "addr:street":"Sowery Row",
    "iso:country":"GB",
    "sg:address":"Roe Lodge, Sowery Row, Southwaite",
    "sg:city":"Carlisle",
    "sg:classifiers":[
        {
            "category":"Building & Trades",
            "subcategory":"Construction",
            "type":"Services"
        }
    ],
    "sg:phone":"+44 836250003",
    "sg:postcode":"CA4 0LH",
    "sg:province":"Cumbria",
    "sg:tags":[
        "builder"
    ],
    "wof:name":"J M Fisher",
    "wof:placetype":"venue"
},
  "geometry": {"coordinates":[-2.8561820984,54.7978134155],"type":"Point"}
}