{
  "type": "Feature",
  "properties": {
    "iso:country":"GB",
    "sg:address":"1a Cardigan Road",
    "sg:city":"Bournemouth",
    "sg:classifiers":[
        {
            "category":"Military Area",
            "subcategory":"Air Force Base",
            "type":"Public Place"
        }
    ],
    "sg:phone":"+44 1202 518000",
    "sg:postcode":"BH9 1BB",
    "sg:province":"Dorset",
    "sg:tags":[
        "taxi",
        "hire",
        "private"
    ],
    "wof:name":"Mobile Radio Cars",
    "wof:placetype":"venue"
},
  "geometry": {"coordinates":[-1.8784960508,50.7411689758],"type":"Point"}
}