{
  "type": "Feature",
  "properties": {
    "addr:full":"363 Manchester Road Warrington Cheshire WA1 3LS",
    "addr:housenumber":"363",
    "addr:postcode":"wa1 3ls",
    "addr:street":"Manchester Road",
    "iso:country":"GB",
    "sg:address":"363 Manchester Road",
    "sg:city":"Warrington",
    "sg:classifiers":[
        {
            "category":"Home & Garden",
            "subcategory":"Household Appliances",
            "type":"Retail Goods"
        }
    ],
    "sg:phone":"+44 1925 813667",
    "sg:postcode":"WA1 3LS",
    "sg:province":"Cheshire",
    "sg:tags":[
        "electrical"
    ],
    "wof:name":"Northwest Appliance Care",
    "wof:placetype":"venue"
},
  "geometry": {"coordinates":[-2.562203,53.397652],"type":"Point"}
}