{
  "type": "Feature",
  "properties": {
    "addr:full":"34 Victoria Road Romford Essex RM1 2JH",
    "addr:housenumber":"34",
    "addr:postcode":"rm1 2jh",
    "addr:street":"Victoria Road",
    "iso:country":"GB",
    "sg:address":"34 Victoria Road",
    "sg:city":"Romford",
    "sg:classifiers":[
        {
            "category":"Professional",
            "subcategory":"Detective & Security Services",
            "type":"Services"
        }
    ],
    "sg:phone":"+44 1708 727383",
    "sg:postcode":"RM1 2JH",
    "sg:province":"Essex",
    "sg:tags":[
        "locksmith"
    ],
    "wof:name":"Romford Security Centre",
    "wof:placetype":"venue"
},
  "geometry": {"coordinates":[0.1851010025,51.5743331909],"type":"Point"}
}