{
  "type": "Feature",
  "properties": {
    "iso:country":"GB",
    "sg:address":"58 Addiscombe Rd",
    "sg:city":"Croydon",
    "sg:classifiers":[
        {
            "category":"Organizations",
            "subcategory":"Membership Organization",
            "type":"Services"
        }
    ],
    "sg:phone":"+44 20 8680 0084",
    "sg:postcode":"CR0 6SB",
    "sg:province":"Surrey",
    "sg:tags":[
        "club"
    ],
    "wof:name":"Croydon D & J Club Ltd",
    "wof:placetype":"venue"
},
  "geometry": {"coordinates":[-0.0740209967,51.3825531006],"type":"Point"}
}