{
  "type": "Feature",
  "properties": {
    "iso:country":"GB",
    "sg:address":"Keen Shay Keens  2nd Floor, Exchange Buliding",
    "sg:city":"Bedford",
    "sg:classifiers":[
        {
            "category":"Professional",
            "subcategory":"Business Services",
            "type":"Services"
        }
    ],
    "sg:postcode":"MK40 3JG",
    "sg:province":"Bedfordshire",
    "wof:name":"Virtual Online Solutions Ltd",
    "wof:placetype":"venue"
},
  "geometry": {"coordinates":[-0.464958,52.138973],"type":"Point"}
}