{
  "type": "Feature",
  "properties": {
    "addr:full":"Abbots Road Whitby North Yorkshire YO22 4EB",
    "addr:postcode":"yo22 4eb",
    "addr:street":"Abbots Road",
    "iso:country":"GB",
    "sg:address":"Abbots Road",
    "sg:city":"Whitby",
    "sg:classifiers":[
        {
            "category":"Community Center",
            "subcategory":"Youth",
            "type":"Public Place"
        },
        {
            "category":"Government",
            "subcategory":"Office",
            "type":"Public Place"
        }
    ],
    "sg:phone":"+44 1947 820464",
    "sg:postcode":"YO22 4EB",
    "sg:province":"North Yorkshire",
    "sg:tags":[
        "organisation",
        "local",
        "centre"
    ],
    "wof:name":"Helredale Play Centre",
    "wof:placetype":"venue"
},
  "geometry": {"coordinates":[-0.609557,54.479164],"type":"Point"}
}