{
  "type": "Feature",
  "properties": {
    "addr:full":"9 Main Road, Radcliffe-on-trent Nottingham Nottinghamshire NG12 2FD",
    "addr:housenumber":"9",
    "addr:postcode":"ng12 2fd",
    "addr:street":"Main Road",
    "iso:country":"GB",
    "sg:address":"9 Main Road, Radcliffe-on-trent",
    "sg:city":"Nottingham",
    "sg:classifiers":[
        {
            "category":"Government",
            "subcategory":"Post Office",
            "type":"Public Place"
        }
    ],
    "sg:postcode":"NG12 2FD",
    "sg:province":"Nottinghamshire",
    "wof:name":"Radcliffe on Trent Post Office",
    "wof:placetype":"venue"
},
  "geometry": {"coordinates":[-1.0393550396,52.9467811584],"type":"Point"}
}