{
  "type": "Feature",
  "properties": {
    "addr:full":"30 Half Acre Rd London Greater London W7 3JJ",
    "addr:housenumber":"30",
    "addr:postcode":"w7 3jj",
    "addr:street":"Half Acre Rd",
    "iso:country":"GB",
    "sg:address":"30 Half Acre Rd",
    "sg:city":"London",
    "sg:classifiers":[
        {
            "category":"Building & Trades",
            "subcategory":"Landscaping Services",
            "type":"Services"
        }
    ],
    "sg:postcode":"W7 3JJ",
    "sg:province":"Greater London",
    "sg:tags":[
        "design",
        "garden"
    ],
    "wof:name":"Marshall,Rob,",
    "wof:placetype":"venue"
},
  "geometry": {"coordinates":[-0.341895,51.509281],"type":"Point"}
}