{
  "type": "Feature",
  "properties": {
    "iso:country":"GB",
    "sg:address":"394 Warwick Rd",
    "sg:city":"Solihull",
    "sg:classifiers":[
        {
            "category":"Health Services",
            "subcategory":"Clinic",
            "type":"Services"
        }
    ],
    "sg:phone":"+44 121 705 3509",
    "sg:postcode":"B91 1BB",
    "sg:province":"West Midlands",
    "sg:tags":[
        "nh"
    ],
    "wof:name":"Edgbaston Health Clinic",
    "wof:placetype":"venue"
},
  "geometry": {"coordinates":[-1.796126,52.425072],"type":"Point"}
}