{
  "type": "Feature",
  "properties": {
    "iso:country":"GB",
    "sg:address":"Hayward House",
    "sg:city":"Nottingham",
    "sg:classifiers":[
        {
            "category":"Organizations",
            "subcategory":"Non-profit Organization",
            "type":"Services"
        }
    ],
    "sg:phone":"+44 115 962 7996",
    "sg:postcode":"NG5 1PJ",
    "sg:province":"Nottinghamshire",
    "sg:tags":[
        "organisation",
        "voluntary",
        "charity"
    ],
    "wof:name":"Hayward House Cancer Care Trust",
    "wof:placetype":"venue"
},
  "geometry": {"coordinates":[-1.15891397,52.9715538025],"type":"Point"}
}