{
  "type": "Feature",
  "properties": {
    "addr:full":"15 Fellowes Rd, Old Fletton Peterborough Cambridgeshire PE2 8EA",
    "addr:housenumber":"15",
    "addr:postcode":"pe2 8ea",
    "addr:street":"Fellowes Rd",
    "iso:country":"GB",
    "sg:address":"15 Fellowes Rd, Old Fletton",
    "sg:city":"Peterborough",
    "sg:classifiers":[
        {
            "category":"Professional",
            "subcategory":"Art Services",
            "type":"Services"
        }
    ],
    "sg:phone":"+44 1733 770328",
    "sg:postcode":"PE2 8EA",
    "sg:province":"Cambridgeshire",
    "sg:tags":[
        "graphic",
        "designer"
    ],
    "wof:name":"Stringlo",
    "wof:placetype":"venue"
},
  "geometry": {"coordinates":[-0.240957,52.559231],"type":"Point"}
}