{
  "type": "Feature",
  "properties": {
    "addr:full":"Higgins Lane, Burscough Ormskirk Lancashire L40 8JB",
    "addr:postcode":"l40 8jb",
    "addr:street":"Higgins Lane",
    "iso:country":"GB",
    "sg:address":"Higgins Lane, Burscough",
    "sg:city":"Ormskirk",
    "sg:classifiers":[
        {
            "category":"Retail",
            "subcategory":"Auto Repair",
            "type":"Services"
        }
    ],
    "sg:phone":"+44 1704 896005",
    "sg:postcode":"L40 8JB",
    "sg:province":"Lancashire",
    "sg:tags":[
        "bodybuilder",
        "repairer"
    ],
    "wof:name":"Allen Munro Trailers Ltd",
    "wof:placetype":"venue"
},
  "geometry": {"coordinates":[-2.8601241112,53.5995140076],"type":"Point"}
}