{
  "type": "Feature",
  "properties": {
    "addr:full":"Marsh Road, Hilperton Marsh Trowbridge Wiltshire BA14 7PL",
    "addr:postcode":"ba14 7pl",
    "addr:street":"Marsh Road",
    "iso:country":"GB",
    "sg:address":"Marsh Road, Hilperton Marsh",
    "sg:city":"Trowbridge",
    "sg:classifiers":[
        {
            "category":"Farming",
            "subcategory":"Poultry Farm",
            "type":"Manufacturing & Wholesale Goods"
        }
    ],
    "sg:phone":"+44 1225 752841",
    "sg:postcode":"BA14 7PL",
    "sg:province":"Wiltshire",
    "sg:tags":[
        "game",
        "farmer"
    ],
    "wof:name":"Maurice Millard (Hatcheries) Ltd.",
    "wof:placetype":"venue"
},
  "geometry": {"coordinates":[-2.208374,51.315342],"type":"Point"}
}