{
  "type": "Feature",
  "properties": {
    "addr:full":"Unit 14 Indstl Est, Fleet Rd, Holbeach Spalding Cambridgeshire PE12 8LA",
    "addr:housenumber":"unit 14",
    "addr:postcode":"pe12 8la",
    "addr:street":"Indstl Est Fleet Rd;Spalding",
    "iso:country":"GB",
    "sg:address":"Unit 14 Indstl Est, Fleet Rd, Holbeach",
    "sg:city":"Spalding",
    "sg:classifiers":[
        {
            "category":"Manufacturing",
            "subcategory":"Glass & Minerals",
            "type":"Manufacturing & Wholesale Goods"
        }
    ],
    "sg:postcode":"PE12 8LA",
    "sg:province":"Cambridgeshire",
    "sg:tags":[
        "fibre",
        "moulding"
    ],
    "wof:name":"P N Moulding",
    "wof:placetype":"venue"
},
  "geometry": {"coordinates":[0.0348099992,52.8046188354],"type":"Point"}
}