{
  "type": "Feature",
  "properties": {
    "iso:country":"GB",
    "sg:address":"1 Kilspindie Street, Dunsinane Industrial Estate",
    "sg:city":"Dundee",
    "sg:classifiers":[
        {
            "category":"Manufacturing",
            "subcategory":"Paper Products",
            "type":"Manufacturing & Wholesale Goods"
        }
    ],
    "sg:phone":"+44 1382 828228",
    "sg:postcode":"DD2 3EW",
    "sg:province":"Dundee City",
    "sg:tags":[
        "stationery",
        "mnfr"
    ],
    "wof:name":"Lindegaard U K Ltd.",
    "wof:placetype":"venue"
},
  "geometry": {"coordinates":[-3.01838,56.479012],"type":"Point"}
}