{
  "type": "Feature",
  "properties": {
    "addr:full":"48 Gt Eastern St London Greater London EC2A 3EP",
    "addr:housenumber":"48",
    "addr:postcode":"ec2a 3ep",
    "addr:street":"Gt Eastern St",
    "iso:country":"GB",
    "sg:address":"48 Gt Eastern St",
    "sg:city":"London",
    "sg:classifiers":[
        {
            "category":"Communications",
            "subcategory":"Film & Video Production",
            "type":"Services"
        }
    ],
    "sg:phone":"+44 20 7613 5657",
    "sg:postcode":"EC2A 3EP",
    "sg:province":"Greater London",
    "sg:tags":[
        "pr",
        "telemarketing"
    ],
    "wof:name":"Valid Data Ltd",
    "wof:placetype":"venue"
},
  "geometry": {"coordinates":[-0.080924,51.524826],"type":"Point"}
}