{
  "type": "Feature",
  "properties": {
    "addr:full":"Beech House, Witham Park, Waterside South Lincoln Lincolnshire LN5 7JH",
    "addr:postcode":"ln5 7jh",
    "addr:street":"Witham Park;Lincoln",
    "iso:country":"GB",
    "sg:address":"Beech House, Witham Park, Waterside South",
    "sg:city":"Lincoln",
    "sg:classifiers":[
        {
            "category":"Education",
            "subcategory":"Special Training",
            "type":"Public Place"
        }
    ],
    "sg:phone":"+44 1522 567765",
    "sg:postcode":"LN5 7JH",
    "sg:province":"Lincolnshire",
    "sg:tags":[
        "product",
        "centre"
    ],
    "wof:name":"Lincolnshire Training & Enterprise Council Ltd.",
    "wof:placetype":"venue"
},
  "geometry": {"coordinates":[-0.5390610099,53.2281608582],"type":"Point"}
}