{
  "type": "Feature",
  "properties": {
    "iso:country":"GB",
    "sg:address":"112 Winter Hey Lane, Horwich",
    "sg:city":"Bolton",
    "sg:classifiers":[
        {
            "category":"Shopping",
            "subcategory":"Baby Store",
            "type":"Retail Goods"
        }
    ],
    "sg:postcode":"BL6 7PJ",
    "sg:province":"Lancashire",
    "sg:tags":[
        "nursery",
        "accessory"
    ],
    "wof:name":"Chubby Cherubs",
    "wof:placetype":"venue"
},
  "geometry": {"coordinates":[-2.549226,53.597931],"type":"Point"}
}