{
  "type": "Feature",
  "properties": {
    "addr:full":"35 The Idlewells Sutton-in-ashfield Nottinghamshire NG17 1BN",
    "addr:housenumber":"35",
    "addr:postcode":"ng17 1bn",
    "addr:street":"The Idlewells Sutton-In-Ashfield",
    "iso:country":"GB",
    "sg:address":"35 The Idlewells",
    "sg:city":"Sutton-in-ashfield",
    "sg:classifiers":[
        {
            "category":"Shopping",
            "subcategory":"Pharmacy",
            "type":"Retail Goods"
        }
    ],
    "sg:phone":"+44 1623 554094",
    "sg:postcode":"NG17 1BN",
    "sg:province":"Nottinghamshire",
    "sg:tags":[
        "pharmacist",
        "chemist"
    ],
    "wof:name":"Boots the Chemist",
    "wof:placetype":"venue"
},
  "geometry": {"coordinates":[-1.2770889997,53.1218414307],"type":"Point"}
}