{
  "type": "Feature",
  "properties": {
    "addr:full":"183 North St Bristol City of Bristol BS3 1JQ",
    "addr:housenumber":"183",
    "addr:postcode":"bs3 1jq",
    "addr:street":"North St",
    "iso:country":"GB",
    "sg:address":"183 North St",
    "sg:city":"Bristol",
    "sg:classifiers":[
        {
            "category":"Food & Beverages",
            "subcategory":"Fruits & Vegetables",
            "type":"Retail Goods"
        }
    ],
    "sg:postcode":"BS3 1JQ",
    "sg:province":"City of Bristol",
    "sg:tags":[
        "greengrocer"
    ],
    "wof:name":"Granny Smiffs",
    "wof:placetype":"venue"
},
  "geometry": {"coordinates":[-2.6021289825,51.4413490295],"type":"Point"}
}