{
  "type": "Feature",
  "properties": {
    "iso:country":"GB",
    "sg:address":"Unit 17-19, Century Park, Garrison Lane",
    "sg:city":"Birmingham",
    "sg:classifiers":[
        {
            "category":"Manufacturing",
            "subcategory":"Wood Products",
            "type":"Manufacturing & Wholesale Goods"
        }
    ],
    "sg:phone":"+44 121 789 8567",
    "sg:postcode":"B9 4NZ",
    "sg:province":"West Midlands",
    "sg:tags":[
        "packaging",
        "crate",
        "pallets"
    ],
    "wof:name":"Oaktree Packaging Co. Ltd.",
    "wof:placetype":"venue"
},
  "geometry": {"coordinates":[-1.863436,52.477154],"type":"Point"}
}