{
  "type": "Feature",
  "properties": {
    "addr:full":"2 Howsmoor Lane, Blackhorse Bristol City of Bristol BS16 7AQ",
    "addr:housenumber":"2",
    "addr:postcode":"bs16 7aq",
    "addr:street":"Howsmoor Lane",
    "iso:country":"GB",
    "sg:address":"2 Howsmoor Lane, Blackhorse",
    "sg:city":"Bristol",
    "sg:classifiers":[
        {
            "category":"Wholesale",
            "subcategory":"Scrap",
            "type":"Manufacturing & Wholesale Goods"
        }
    ],
    "sg:postcode":"BS16 7AQ",
    "sg:province":"City of Bristol",
    "sg:tags":[
        "waste",
        "metal"
    ],
    "wof:name":"Blackhorse Scrap Metal Merchants Ltd.",
    "wof:placetype":"venue"
},
  "geometry": {"coordinates":[-2.478049,51.498581],"type":"Point"}
}