{
  "type": "Feature",
  "properties": {
    "iso:country":"GB",
    "sg:address":"27 Staplehurst Rd",
    "sg:city":"Lewisham",
    "sg:classifiers":[
        {
            "category":"Professional",
            "subcategory":"Computer Services",
            "type":"Services"
        }
    ],
    "sg:phone":"+44 20 8355 0936",
    "sg:postcode":"SE13 5ND",
    "sg:province":"Greater London",
    "sg:tags":[
        "system",
        "software"
    ],
    "wof:name":"Power Systems International",
    "wof:placetype":"venue"
},
  "geometry": {"coordinates":[-0.000274,51.453449],"type":"Point"}
}