{
  "type": "Feature",
  "properties": {
    "addr:full":"Balloch Road, Balloch Alexandria Argyll and Bute G83 8SR",
    "addr:postcode":"g83 8sr",
    "addr:street":"Balloch Road",
    "iso:country":"GB",
    "sg:address":"Balloch Road, Balloch",
    "sg:city":"Alexandria",
    "sg:classifiers":[
        {
            "category":"Travel",
            "subcategory":"Hotels & Motels",
            "type":"Entertainment"
        }
    ],
    "sg:phone":"+44 1389 759631",
    "sg:postcode":"G83 8SR",
    "sg:province":"Argyll and Bute",
    "sg:tags":[
        "house",
        "guest"
    ],
    "wof:name":"Lomond Villa",
    "wof:placetype":"venue"
},
  "geometry": {"coordinates":[-4.5794491768,56.0040512085],"type":"Point"}
}