{
  "type": "Feature",
  "properties": {
    "addr:full":"Suite 24-26 Lever Street Manchester Greater Manchester M1 1DZ",
    "addr:housenumber":"suite 24-26",
    "addr:postcode":"m1 1dz",
    "addr:street":"Lever Street",
    "iso:country":"GB",
    "sg:address":"Suite 24-26 Lever Street",
    "sg:city":"Manchester",
    "sg:classifiers":[
        {
            "category":"Professional",
            "subcategory":"Detective & Security Services",
            "type":"Services"
        }
    ],
    "sg:phone":"+44 161 236 8011",
    "sg:postcode":"M1 1DZ",
    "sg:province":"Greater Manchester",
    "wof:name":"Emirates Security Services",
    "wof:placetype":"venue"
},
  "geometry": {"coordinates":[-2.2339100838,53.4823875427],"type":"Point"}
}