{
  "type": "Feature",
  "properties": {
    "addr:full":"77 Sherwood Park Road Mitcham Greater London CR4 1NB",
    "addr:housenumber":"77",
    "addr:postcode":"cr4 1nb",
    "addr:street":"Sherwood Park Road",
    "iso:country":"GB",
    "sg:address":"77 Sherwood Park Road",
    "sg:city":"Mitcham",
    "sg:classifiers":[
        {
            "category":"Fast Food",
            "type":"Food & Drink"
        }
    ],
    "sg:phone":"+44 20 8679 1808",
    "sg:postcode":"CR4 1NB",
    "sg:province":"Greater London",
    "sg:tags":[
        "away",
        "take"
    ],
    "wof:name":"New Moon Take Away",
    "wof:placetype":"venue"
},
  "geometry": {"coordinates":[-0.141364,51.399261],"type":"Point"}
}