{
  "type": "Feature",
  "properties": {
    "iso:country":"GB",
    "sg:address":"76 Swaffield Road",
    "sg:city":"London",
    "sg:classifiers":[
        {
            "category":"Farming",
            "subcategory":"Nursery",
            "type":"Manufacturing & Wholesale Goods"
        }
    ],
    "sg:phone":"+44 20 8877 3875",
    "sg:postcode":"SW18 3TJ",
    "sg:province":"Greater London",
    "sg:tags":[
        "creche"
    ],
    "wof:name":"Brocklebank Work Place Nursery",
    "wof:placetype":"venue"
},
  "geometry": {"coordinates":[-0.188898,51.44894],"type":"Point"}
}