{
  "type": "Feature",
  "properties": {
    "iso:country":"GB",
    "sg:address":"117 Cuckoo Lane",
    "sg:city":"Fareham",
    "sg:classifiers":[
        {
            "category":"Taxi",
            "type":"Transportation"
        },
        {
            "category":"Military Area",
            "subcategory":"Air Force Base",
            "type":"Public Place"
        }
    ],
    "sg:phone":"+44 1329 667636",
    "sg:postcode":"PO14 3TR",
    "sg:province":"Hampshire",
    "sg:tags":[
        "hire",
        "private",
        "vehicle"
    ],
    "wof:name":"People to Places Taxis",
    "wof:placetype":"venue"
},
  "geometry": {"coordinates":[-1.222474,50.830242],"type":"Point"}
}