{
  "type": "Feature",
  "properties": {
    "iso:country":"GB",
    "sg:address":"Carlton St",
    "sg:city":"Castleford",
    "sg:classifiers":[
        {
            "category":"Bars & Pubs",
            "type":"Food & Drink"
        }
    ],
    "sg:phone":"+44 1977 552145",
    "sg:postcode":"WF10 1AN",
    "sg:province":"West Yorkshire",
    "sg:tags":[
        "pubs",
        "inn"
    ],
    "wof:name":"Carltons",
    "wof:placetype":"venue"
},
  "geometry": {"coordinates":[-1.350429,53.726501],"type":"Point"}
}