{
  "type": "Feature",
  "properties": {
    "addr:full":"2 Nursery Lane Coldstream Northumberland TD12 4DE",
    "addr:housenumber":"2",
    "addr:postcode":"td12 4de",
    "addr:street":"Nursery Lane",
    "iso:country":"GB",
    "sg:address":"2 Nursery Lane",
    "sg:city":"Coldstream",
    "sg:classifiers":[
        {
            "category":"Personal",
            "subcategory":"Beauty Salon",
            "type":"Services"
        },
        {
            "category":"Personal",
            "subcategory":"Barber",
            "type":"Services"
        }
    ],
    "sg:phone":"+44 1890 882705",
    "sg:postcode":"TD12 4DE",
    "sg:province":"Northumberland",
    "sg:tags":[
        "unisex",
        "hairdresser"
    ],
    "wof:name":"Sasha Hairstylist",
    "wof:placetype":"venue"
},
  "geometry": {"coordinates":[-2.2533829212,55.6524810791],"type":"Point"}
}