{
  "type": "Feature",
  "properties": {
    "addr:full":"Unit 8, Fairway Industrial Centre Bristol Gloucestershire BS34 7QS",
    "addr:housenumber":"unit 8",
    "addr:postcode":"bs34 7qs",
    "addr:street":"Fairway Industrial Centre",
    "iso:country":"GB",
    "sg:address":"Unit 8, Fairway Industrial Centre",
    "sg:city":"Bristol",
    "sg:classifiers":[
        {
            "category":"Health Services",
            "subcategory":"Medical Lab",
            "type":"Services"
        }
    ],
    "sg:postcode":"BS34 7QS",
    "sg:province":"Gloucestershire",
    "sg:tags":[
        "dental"
    ],
    "wof:name":"Hammonds Dental Laboratory",
    "wof:placetype":"venue"
},
  "geometry": {"coordinates":[-2.581812,51.511215],"type":"Point"}
}