{
  "type": "Feature",
  "properties": {
    "addr:full":"Loftus, Basington Saltburn-by-the-sea North Yorkshire TS13 4UB",
    "addr:postcode":"ts13 4ub",
    "iso:country":"GB",
    "sg:address":"Loftus, Basington",
    "sg:city":"Saltburn-by-the-sea",
    "sg:classifiers":[
        {
            "category":"Real Estate",
            "subcategory":"Real Estate Agent",
            "type":"Services"
        }
    ],
    "sg:phone":"+44 1287 640468",
    "sg:postcode":"TS13 4UB",
    "sg:province":"North Yorkshire",
    "wof:name":"Grinkle Park Estate",
    "wof:placetype":"venue"
},
  "geometry": {"coordinates":[-0.85598,54.524551],"type":"Point"}
}