{
  "type": "Feature",
  "properties": {
    "addr:full":"Peatfield Court, Stapleford Nottingham Nottinghamshire NG9 8GN",
    "addr:postcode":"ng9 8gn",
    "addr:street":"Peatfield Court",
    "iso:country":"GB",
    "sg:address":"Peatfield Court, Stapleford",
    "sg:city":"Nottingham",
    "sg:classifiers":[
        {
            "category":"Social Services",
            "subcategory":"Adult Care",
            "type":"Services"
        },
        {
            "category":"Real Estate",
            "subcategory":"Real Estate Agent",
            "type":"Services"
        }
    ],
    "sg:phone":"+44 115 939 7586",
    "sg:postcode":"NG9 8GN",
    "sg:province":"Nottinghamshire",
    "sg:tags":[
        "housing",
        "sheltered"
    ],
    "wof:name":"Peatfield Court Sheltered Housing",
    "wof:placetype":"venue"
},
  "geometry": {"coordinates":[-1.2746609449,52.9379005432],"type":"Point"}
}