{
  "type": "Feature",
  "properties": {
    "addr:full":"Woodmansterne Road Coulsdon Surrey CR5 2DL",
    "addr:postcode":"cr5 2dl",
    "addr:street":"Woodmansterne Road",
    "iso:country":"GB",
    "sg:address":"Woodmansterne Road",
    "sg:city":"Coulsdon",
    "sg:classifiers":[
        {
            "category":"Place Of Worship",
            "type":"Public Place"
        }
    ],
    "sg:phone":"+44 20 8660 0398",
    "sg:postcode":"CR5 2DL",
    "sg:province":"Surrey",
    "wof:name":"St Andrews C Of E Church",
    "wof:placetype":"venue"
},
  "geometry": {"coordinates":[-0.139179,51.318924],"type":"Point"}
}