{
  "type": "Feature",
  "properties": {
    "iso:country":"GB",
    "sg:address":"44 The Broadway",
    "sg:city":"Epsom",
    "sg:classifiers":[
        {
            "category":"Professional",
            "subcategory":"Printing & Photocopies",
            "type":"Services"
        }
    ],
    "sg:postcode":"KT17 2HS",
    "sg:province":"Surrey",
    "sg:tags":[
        "printer"
    ],
    "wof:name":"P & M Litho",
    "wof:placetype":"venue"
},
  "geometry": {"coordinates":[-0.2421350032,51.3608055115],"type":"Point"}
}