{
  "type": "Feature",
  "properties": {
    "addr:full":"Brewers Bush Bonnyrigg Midlothian EH19 3JH",
    "addr:postcode":"eh19 3jh",
    "addr:street":"Bush",
    "iso:country":"GB",
    "sg:address":"Brewers Bush",
    "sg:city":"Bonnyrigg",
    "sg:classifiers":[
        {
            "category":"Organizations",
            "subcategory":"Community Association",
            "type":"Services"
        },
        {
            "category":"Organizations",
            "subcategory":"Non-profit Organization",
            "type":"Services"
        }
    ],
    "sg:phone":"+44 1875 821025",
    "sg:postcode":"EH19 3JH",
    "sg:province":"Midlothian",
    "sg:tags":[
        "organisation",
        "care",
        "animal",
        "welfare"
    ],
    "wof:name":"Lothian Cat Rescue",
    "wof:placetype":"venue"
},
  "geometry": {"coordinates":[-3.1040699482,55.8740348816],"type":"Point"}
}