{
  "type": "Feature",
  "properties": {
    "addr:full":"Unit 2 West Point, New Hythe Lane, Larkfield Aylesford Kent ME20 6XJ",
    "addr:housenumber":"unit 2",
    "addr:postcode":"me20 6xj",
    "addr:street":"Hythe Lane",
    "iso:country":"GB",
    "sg:address":"Unit 2 West Point, New Hythe Lane, Larkfield",
    "sg:city":"Aylesford",
    "sg:classifiers":[
        {
            "category":"Food & Beverages",
            "subcategory":"Groceries & Convenience Stores",
            "type":"Retail Goods"
        }
    ],
    "sg:phone":"+44 1622 882380",
    "sg:postcode":"ME20 6XJ",
    "sg:province":"Kent",
    "wof:name":"South East Convenience Stores Ltd.",
    "wof:placetype":"venue"
},
  "geometry": {"coordinates":[0.4420050085,51.3011512756],"type":"Point"}
}