{
  "type": "Feature",
  "properties": {
    "addr:full":"50 Mortonhall Gate Edinburgh City of Edinburgh EH16 6TJ",
    "addr:housenumber":"50",
    "addr:postcode":"eh16 6tj",
    "addr:street":"Mortonhall Gate",
    "iso:country":"GB",
    "sg:address":"50 Mortonhall Gate",
    "sg:city":"Edinburgh",
    "sg:classifiers":[
        {
            "category":"Bars & Pubs",
            "type":"Food & Drink"
        }
    ],
    "sg:phone":"+44 131 664 0773",
    "sg:postcode":"EH16 6TJ",
    "sg:province":"City of Edinburgh",
    "sg:tags":[
        "pubs",
        "inn"
    ],
    "wof:name":"The Stable Bar",
    "wof:placetype":"venue"
},
  "geometry": {"coordinates":[-3.177884,55.899914],"type":"Point"}
}