{
  "type": "Feature",
  "properties": {
    "addr:full":"39 Silverdale Close, Frodsham Warrington Cheshire WA6 7NE",
    "addr:housenumber":"39",
    "addr:postcode":"wa6 7ne",
    "addr:street":"Silverdale Close",
    "iso:country":"GB",
    "sg:address":"39 Silverdale Close, Frodsham",
    "sg:city":"Warrington",
    "sg:classifiers":[
        {
            "category":"Building & Trades",
            "subcategory":"Construction",
            "type":"Services"
        }
    ],
    "sg:postcode":"WA6 7NE",
    "sg:province":"Cheshire",
    "sg:tags":[
        "joiner",
        "carpenter"
    ],
    "wof:name":"David John Oultram",
    "wof:placetype":"venue"
},
  "geometry": {"coordinates":[-2.7152850628,53.2915725708],"type":"Point"}
}