{
  "type": "Feature",
  "properties": {
    "addr:full":"Gilbert House, Grace Road, Marsh Barton Exeter Devon EX2 8PU",
    "addr:postcode":"ex2 8pu",
    "addr:street":"Grace Road",
    "iso:country":"GB",
    "sg:address":"Gilbert House, Grace Road, Marsh Barton",
    "sg:city":"Exeter",
    "sg:classifiers":[
        {
            "category":"Home & Garden",
            "subcategory":"Garden Supply",
            "type":"Retail Goods"
        }
    ],
    "sg:phone":"+44 1392 456200",
    "sg:postcode":"EX2 8PU",
    "sg:province":"Devon",
    "sg:tags":[
        "sand",
        "gravel"
    ],
    "wof:name":"Pre Mix",
    "wof:placetype":"venue"
},
  "geometry": {"coordinates":[-3.527245,50.708672],"type":"Point"}
}