{
  "type": "Feature",
  "properties": {
    "iso:country":"GB",
    "sg:address":"1 Altwood Rd",
    "sg:city":"Maidenhead",
    "sg:classifiers":[
        {
            "category":"Shopping",
            "subcategory":"Antiques",
            "type":"Retail Goods"
        }
    ],
    "sg:phone":"+44 1628 622687",
    "sg:postcode":"SL6 4PB",
    "sg:province":"Berkshire",
    "wof:name":"Ann & Norman Antiques",
    "wof:placetype":"venue"
},
  "geometry": {"coordinates":[-0.742253,51.514709],"type":"Point"}
}