{
  "type": "Feature",
  "properties": {
    "addr:full":"374 Ewell Road Surbiton Surrey KT6 7BB",
    "addr:housenumber":"374",
    "addr:postcode":"kt6 7bb",
    "addr:street":"Ewell Road",
    "iso:country":"GB",
    "sg:address":"374 Ewell Road",
    "sg:city":"Surbiton",
    "sg:classifiers":[
        {
            "category":"Food & Beverages",
            "subcategory":"Supermarket",
            "type":"Retail Goods"
        }
    ],
    "sg:phone":"+44 20 8390 3180",
    "sg:postcode":"KT6 7BB",
    "sg:province":"Surrey",
    "sg:website":"http://www.budgens.co.uk",
    "wof:name":"Budgens Stores Ltd",
    "wof:placetype":"venue"
},
  "geometry": {"coordinates":[-0.2872639894,51.3827133179],"type":"Point"}
}