{
  "type": "Feature",
  "properties": {
    "addr:full":"Derwen House, Court Rd Bridgend Bridgend CF31 1BN",
    "addr:postcode":"cf31 1bn",
    "addr:street":"Court Rd",
    "iso:country":"GB",
    "sg:address":"Derwen House, Court Rd",
    "sg:city":"Bridgend",
    "sg:classifiers":[
        {
            "category":"Professional",
            "subcategory":"Lawyer & Legal Services",
            "type":"Services"
        }
    ],
    "sg:phone":"+44 1656 660016",
    "sg:postcode":"CF31 1BN",
    "sg:province":"Bridgend",
    "sg:tags":[
        "solicitor"
    ],
    "wof:name":"Richard Jenkins & Co",
    "wof:placetype":"venue"
},
  "geometry": {"coordinates":[-3.5761549473,51.5064315796],"type":"Point"}
}