{
  "type": "Feature",
  "properties": {
    "addr:full":"169 High St Guildford Surrey GU1 3AJ",
    "addr:housenumber":"169",
    "addr:postcode":"gu1 3aj",
    "addr:street":"High St",
    "iso:country":"GB",
    "sg:address":"169 High St",
    "sg:city":"Guildford",
    "sg:classifiers":[
        {
            "category":"Bars & Pubs",
            "type":"Food & Drink"
        }
    ],
    "sg:phone":"+44 1483 504227",
    "sg:postcode":"GU1 3AJ",
    "sg:province":"Surrey",
    "sg:tags":[
        "pubs",
        "inn"
    ],
    "wof:name":"Three Pigeons The",
    "wof:placetype":"venue"
},
  "geometry": {"coordinates":[-0.5706179738,51.2363777161],"type":"Point"}
}