{
  "type": "Feature",
  "properties": {
    "addr:full":"Compton Bassett Gardens, Compton Bassett Calne Wiltshire SN11 8RE",
    "addr:postcode":"sn11 8re",
    "addr:street":"Bassett Gardens",
    "iso:country":"GB",
    "sg:address":"Compton Bassett Gardens, Compton Bassett",
    "sg:city":"Calne",
    "sg:classifiers":[
        {
            "category":"Building & Trades",
            "subcategory":"Landscaping Services",
            "type":"Services"
        }
    ],
    "sg:phone":"+44 1249 814453",
    "sg:postcode":"SN11 8RE",
    "sg:province":"Wiltshire",
    "sg:tags":[
        "designer",
        "landscape",
        "contractor"
    ],
    "wof:name":"Great Western Landscaping Co",
    "wof:placetype":"venue"
},
  "geometry": {"coordinates":[-2.0049118996,51.4376716614],"type":"Point"}
}