{
  "type": "Feature",
  "properties": {
    "addr:full":"Kimpton Bottom Lane, Kimpton Hitchin Hertfordshire SG4 8ET",
    "addr:housenumber":"kimpton",
    "addr:postcode":"sg4 8et",
    "addr:street":"Bottom Lane",
    "iso:country":"GB",
    "sg:address":"Kimpton Bottom Lane, Kimpton",
    "sg:city":"Hitchin",
    "sg:classifiers":[
        {
            "category":"Home & Garden",
            "subcategory":"Garden Supply",
            "type":"Retail Goods"
        }
    ],
    "sg:phone":"+44 1438 833560",
    "sg:postcode":"SG4 8ET",
    "sg:province":"Hertfordshire",
    "sg:tags":[
        "tree",
        "shrub"
    ],
    "wof:name":"Kimpton Bottom Nursery",
    "wof:placetype":"venue"
},
  "geometry": {"coordinates":[-0.298339,51.851173],"type":"Point"}
}