{
  "type": "Feature",
  "properties": {
    "addr:full":"Burnbrae, Rubislaw Den North Aberdeen Aberdeen City AB15 4AL",
    "addr:postcode":"ab15 4al",
    "addr:street":"Rubislaw Den North",
    "iso:country":"GB",
    "sg:address":"Burnbrae, Rubislaw Den North",
    "sg:city":"Aberdeen",
    "sg:classifiers":[
        {
            "category":"Building & Trades",
            "subcategory":"Construction",
            "type":"Services"
        }
    ],
    "sg:postcode":"AB15 4AL",
    "sg:province":"Aberdeen City",
    "sg:tags":[
        "builder"
    ],
    "wof:name":"Engvale Ltd",
    "wof:placetype":"venue"
},
  "geometry": {"coordinates":[-2.138927,57.144539],"type":"Point"}
}