{
  "type": "Feature",
  "properties": {
    "iso:country":"GB",
    "sg:address":"40 King Edwards Avenue",
    "sg:city":"Gloucester",
    "sg:classifiers":[
        {
            "category":"Military Area",
            "subcategory":"Air Force Base",
            "type":"Public Place"
        }
    ],
    "sg:phone":"+44 1452 525521",
    "sg:postcode":"GL1 5DF",
    "sg:province":"Gloucestershire",
    "sg:tags":[
        "taxi",
        "hire",
        "private"
    ],
    "wof:name":"C & T Cabs",
    "wof:placetype":"venue"
},
  "geometry": {"coordinates":[-2.2482299805,51.8498001099],"type":"Point"}
}