{
  "type": "Feature",
  "properties": {
    "iso:country":"GB",
    "sg:address":"30 Lees Road, Knowsley Industrial Park North",
    "sg:city":"Liverpool",
    "sg:classifiers":[
        {
            "category":"Retail",
            "subcategory":"Auto Repair",
            "type":"Services"
        }
    ],
    "sg:phone":"+44 151 548 5929",
    "sg:postcode":"L33 7SE",
    "sg:province":"Lancashire",
    "sg:tags":[
        "body",
        "car"
    ],
    "wof:name":"McCormick Vehicle Repairs",
    "wof:placetype":"venue"
},
  "geometry": {"coordinates":[-2.863691,53.480701],"type":"Point"}
}