{
  "type": "Feature",
  "properties": {
    "iso:country":"GB",
    "sg:address":"Monklands Industrial Estate, Kirkshaws Road",
    "sg:city":"Coatbridge",
    "sg:classifiers":[
        {
            "category":"Professional",
            "subcategory":"Business Services",
            "type":"Services"
        }
    ],
    "sg:postcode":"ML5 4RP",
    "sg:province":"North Lanarkshire",
    "sg:tags":[
        "tile",
        "stockist"
    ],
    "wof:name":"J R Cash & Carry Tiles",
    "wof:placetype":"venue"
},
  "geometry": {"coordinates":[-4.0325779915,55.8546676636],"type":"Point"}
}