{
  "type": "Feature",
  "properties": {
    "addr:full":"58 Canyon Road, Netherton Industrial Estate Wishaw North Lanarkshire ML2 0EG",
    "addr:housenumber":"58",
    "addr:postcode":"ml2 0eg",
    "addr:street":"Canyon Road;Industrial Estate",
    "iso:country":"GB",
    "sg:address":"58 Canyon Road, Netherton Industrial Estate",
    "sg:city":"Wishaw",
    "sg:classifiers":[
        {
            "category":"Manufacturing",
            "subcategory":"Tools & Machinery",
            "type":"Manufacturing & Wholesale Goods"
        }
    ],
    "sg:phone":"+44 1698 360222",
    "sg:postcode":"ML2 0EG",
    "sg:province":"North Lanarkshire",
    "sg:tags":[
        "design",
        "maker"
    ],
    "wof:name":"Ensen (scotland) Ltd",
    "wof:placetype":"venue"
},
  "geometry": {"coordinates":[-3.951162,55.770973],"type":"Point"}
}