{
  "type": "Feature",
  "properties": {
    "iso:country":"GB",
    "sg:address":"Clarendon Rd",
    "sg:city":"Worthing",
    "sg:classifiers":[
        {
            "category":"Building & Trades",
            "subcategory":"Construction",
            "type":"Services"
        }
    ],
    "sg:phone":"+44 1903 215554",
    "sg:postcode":"BN14 8QH",
    "sg:province":"West Sussex",
    "sg:tags":[
        "builder"
    ],
    "wof:name":"D M Casey",
    "wof:placetype":"venue"
},
  "geometry": {"coordinates":[-0.359409,50.831188],"type":"Point"}
}