{
  "type": "Feature",
  "properties": {
    "addr:full":"Challow Works, East Challow Wantage Berkshire OX12 9SY",
    "addr:postcode":"ox12 9sy",
    "addr:street":"East",
    "iso:country":"GB",
    "sg:address":"Challow Works, East Challow",
    "sg:city":"Wantage",
    "sg:classifiers":[
        {
            "category":"Professional",
            "subcategory":"Engineering",
            "type":"Services"
        }
    ],
    "sg:phone":"+44 1235 770770",
    "sg:postcode":"OX12 9SY",
    "sg:province":"Berkshire",
    "wof:name":"Barrett Engineers Ltd.",
    "wof:placetype":"venue"
},
  "geometry": {"coordinates":[-1.4523789883,51.5912361145],"type":"Point"}
}