{
  "type": "Feature",
  "properties": {
    "addr:full":"Trident House, Manchester Road Altrincham Cheshire WA14 4PJ",
    "addr:postcode":"wa14 4pj",
    "addr:street":"Manchester Road",
    "iso:country":"GB",
    "sg:address":"Trident House, Manchester Road",
    "sg:city":"Altrincham",
    "sg:classifiers":[
        {
            "category":"Autos & Motor Vehicles",
            "subcategory":"Automobile Sales",
            "type":"Retail Goods"
        }
    ],
    "sg:phone":"+44 161 613 4062",
    "sg:postcode":"WA14 4PJ",
    "sg:province":"Cheshire",
    "sg:tags":[
        "commercial"
    ],
    "wof:name":"Lonerider Ltd.",
    "wof:placetype":"venue"
},
  "geometry": {"coordinates":[-2.352194,53.397484],"type":"Point"}
}