{
  "type": "Feature",
  "properties": {
    "iso:country":"GB",
    "sg:address":"Hannay House, 39 Clarendon Road",
    "sg:city":"Watford",
    "sg:classifiers":[
        {
            "category":"Real Estate",
            "subcategory":"Surveying",
            "type":"Services"
        }
    ],
    "sg:phone":"+44 1923 254445",
    "sg:postcode":"WD17 1LA",
    "sg:province":"Hertfordshire",
    "sg:tags":[
        "surveyor",
        "quantity"
    ],
    "wof:name":"Mpg Associates Ltd.",
    "wof:placetype":"venue"
},
  "geometry": {"coordinates":[-0.397175,51.65852],"type":"Point"}
}