{
  "type": "Feature",
  "properties": {
    "addr:full":"41 Fore Street Callington Cornwall PL17 7AQ",
    "addr:housenumber":"41",
    "addr:postcode":"pl17 7aq",
    "addr:street":"Fore Street",
    "iso:country":"GB",
    "sg:address":"41 Fore Street",
    "sg:city":"Callington",
    "sg:classifiers":[
        {
            "category":"Real Estate",
            "subcategory":"Real Estate Agent",
            "type":"Services"
        }
    ],
    "sg:phone":"+44 1579 383585",
    "sg:postcode":"PL17 7AQ",
    "sg:province":"Cornwall",
    "wof:name":"Kittows",
    "wof:placetype":"venue"
},
  "geometry": {"coordinates":[-4.3154220581,50.5030899048],"type":"Point"}
}