{
  "type": "Feature",
  "properties": {
    "addr:full":"2a Queens Road Southport Lancashire PR9 9HN",
    "addr:housenumber":"2a",
    "addr:postcode":"pr9 9hn",
    "addr:street":"Queens Road",
    "iso:country":"GB",
    "sg:address":"2a Queens Road",
    "sg:city":"Southport",
    "sg:classifiers":[
        {
            "category":"Autos & Motor Vehicles",
            "subcategory":"Automobile Sales",
            "type":"Retail Goods"
        }
    ],
    "sg:phone":"+44 1704 531199",
    "sg:postcode":"PR9 9HN",
    "sg:province":"Lancashire",
    "sg:tags":[
        "car"
    ],
    "wof:name":"Oldfields (Automobiles) Ltd.",
    "wof:placetype":"venue"
},
  "geometry": {"coordinates":[-2.9956688881,53.6511688232],"type":"Point"}
}