{
  "type": "Feature",
  "properties": {
    "addr:full":"Rose Cottage Farm, Weaverham Road, Gorstage Northwich Cheshire CW8 2SG",
    "addr:postcode":"cw8 2sg",
    "addr:street":"Weaverham Road Gorstage",
    "iso:country":"GB",
    "sg:address":"Rose Cottage Farm, Weaverham Road, Gorstage",
    "sg:city":"Northwich",
    "sg:classifiers":[
        {
            "category":"Retail",
            "subcategory":"Veterinary Services",
            "type":"Services"
        }
    ],
    "sg:postcode":"CW8 2SG",
    "sg:province":"Cheshire",
    "sg:tags":[
        "surgeon"
    ],
    "wof:name":"Burgess & Graham",
    "wof:placetype":"venue"
},
  "geometry": {"coordinates":[-2.5842990875,53.249622345],"type":"Point"}
}