{
  "type": "Feature",
  "properties": {
    "iso:country":"GB",
    "sg:address":"6 Howard Street North",
    "sg:city":"Great Yarmouth",
    "sg:classifiers":[
        {
            "category":"Food & Beverages",
            "subcategory":"Bakery",
            "type":"Retail Goods"
        },
        {
            "category":"Home & Garden",
            "subcategory":"Kitchen Supply",
            "type":"Retail Goods"
        }
    ],
    "sg:phone":"+44 1493 842336",
    "sg:postcode":"NR30 1PF",
    "sg:province":"Norfolk",
    "sg:tags":[
        "confectioner",
        "baker",
        "confectionery"
    ],
    "wof:name":"Watsons Bakery",
    "wof:placetype":"venue"
},
  "geometry": {"coordinates":[1.72464,52.608955],"type":"Point"}
}