{
  "type": "Feature",
  "properties": {
    "addr:full":"Douneside House, Tarland Aboyne Aberdeenshire AB34 4UL",
    "addr:postcode":"ab34 4ul",
    "addr:street":"Tarland",
    "iso:country":"GB",
    "sg:address":"Douneside House, Tarland",
    "sg:city":"Aboyne",
    "sg:classifiers":[
        {
            "category":"Community Center",
            "type":"Public Place"
        }
    ],
    "sg:phone":"+44 1339 881320",
    "sg:postcode":"AB34 4UL",
    "sg:province":"Aberdeenshire",
    "sg:tags":[
        "recreation",
        "leisure",
        "centre"
    ],
    "wof:name":"Macrobert Trust",
    "wof:placetype":"venue"
},
  "geometry": {"coordinates":[-2.854389,57.131126],"type":"Point"}
}