{
  "type": "Feature",
  "properties": {
    "addr:full":"2e Brookfield Avenue, Bredbury Stockport Cheshire SK6 1DF",
    "addr:housenumber":"2e",
    "addr:postcode":"sk6 1df",
    "addr:street":"Brookfield Avenue",
    "iso:country":"GB",
    "sg:address":"2e Brookfield Avenue, Bredbury",
    "sg:city":"Stockport",
    "sg:classifiers":[
        {
            "category":"Building & Trades",
            "subcategory":"Construction",
            "type":"Services"
        }
    ],
    "sg:phone":"+44 161 494 7176",
    "sg:postcode":"SK6 1DF",
    "sg:province":"Cheshire",
    "sg:tags":[
        "builder"
    ],
    "wof:name":"T J Builders",
    "wof:placetype":"venue"
},
  "geometry": {"coordinates":[-2.1058,53.422829],"type":"Point"}
}