{
  "type": "Feature",
  "properties": {
    "iso:country":"GB",
    "sg:address":"Bradley Road, Burrough Grn",
    "sg:city":"Newmarket",
    "sg:classifiers":[
        {
            "category":"Bars & Pubs",
            "type":"Food & Drink"
        }
    ],
    "sg:postcode":"CB8 9NH",
    "sg:province":"Cambridgeshire",
    "sg:tags":[
        "pubs",
        "inn"
    ],
    "wof:name":"The Bull",
    "wof:placetype":"venue"
},
  "geometry": {"coordinates":[0.391325,52.177467],"type":"Point"}
}