{
  "type": "Feature",
  "properties": {
    "addr:full":"337 Eglinton Street Glasgow Glasgow City G5 9SP",
    "addr:housenumber":"337",
    "addr:postcode":"g5 9sp",
    "addr:street":"Eglinton Street",
    "iso:country":"GB",
    "sg:address":"337 Eglinton Street",
    "sg:city":"Glasgow",
    "sg:classifiers":[
        {
            "category":"Food & Beverages",
            "subcategory":"Supermarket",
            "type":"Retail Goods"
        },
        {
            "category":"Food & Beverages",
            "subcategory":"Groceries & Convenience Stores",
            "type":"Retail Goods"
        }
    ],
    "sg:phone":"+44 141 429 4722",
    "sg:postcode":"G5 9SP",
    "sg:province":"Glasgow City",
    "wof:name":"Eglinton General Stores",
    "wof:placetype":"venue"
},
  "geometry": {"coordinates":[-4.260988,55.846649],"type":"Point"}
}