{
  "type": "Feature",
  "properties": {
    "iso:country":"GB",
    "sg:address":"Vine House, Church Street",
    "sg:city":"Princes Risborough",
    "sg:classifiers":[
        {
            "category":"Professional",
            "type":"Services"
        }
    ],
    "sg:phone":"+44 1628 669500",
    "sg:postcode":"HP27 9AA",
    "sg:province":"Buckinghamshire",
    "sg:tags":[
        "caterer"
    ],
    "wof:name":"Houston & Church Ltd.",
    "wof:placetype":"venue"
},
  "geometry": {"coordinates":[-0.832529,51.7243],"type":"Point"}
}