{
  "type": "Feature",
  "properties": {
    "iso:country":"GB",
    "sg:address":"Brook House, Brook Street",
    "sg:city":"Loughborough",
    "sg:classifiers":[
        {
            "category":"Shopping",
            "subcategory":"Music",
            "type":"Retail Goods"
        },
        {
            "category":"Shopping",
            "subcategory":"Computers & Home Electronics",
            "type":"Retail Goods"
        }
    ],
    "sg:phone":"+44 1509 829301",
    "sg:postcode":"LE12 9RG",
    "sg:province":"Leicestershire",
    "sg:tags":[
        "record",
        "electrical",
        "tape",
        "cd"
    ],
    "wof:name":"Red Hedgehog Music Ltd.",
    "wof:placetype":"venue"
},
  "geometry": {"coordinates":[-1.288422,52.77668],"type":"Point"}
}