{
  "type": "Feature",
  "properties": {
    "addr:full":"33 Weardale Lane, Queenslie Industrial Estate Glasgow Glasgow City G33 4JJ",
    "addr:housenumber":"33",
    "addr:postcode":"g33 4jj",
    "addr:street":"Weardale Lane Queenslie Industrial Estate",
    "iso:country":"GB",
    "sg:address":"33 Weardale Lane, Queenslie Industrial Estate",
    "sg:city":"Glasgow",
    "sg:classifiers":[
        {
            "category":"Building & Trades",
            "subcategory":"Construction",
            "type":"Services"
        }
    ],
    "sg:phone":"+44 141 774 3666",
    "sg:postcode":"G33 4JJ",
    "sg:province":"Glasgow City",
    "sg:tags":[
        "tiling",
        "contractor"
    ],
    "wof:name":"A Dececco Ltd.",
    "wof:placetype":"venue"
},
  "geometry": {"coordinates":[-4.1512827873,55.8661842346],"type":"Point"}
}