{
  "type": "Feature",
  "properties": {
    "iso:country":"GB",
    "sg:address":"Unit 7, Alexandria Industrial Estate, Station Road",
    "sg:city":"Cullompton",
    "sg:classifiers":[
        {
            "category":"Banks & Credit Unions",
            "subcategory":"Bureau De Change",
            "type":"Services"
        },
        {
            "category":"Autos & Motor Vehicles",
            "subcategory":"Auto Supplies",
            "type":"Retail Goods"
        }
    ],
    "sg:phone":"+44 1884 35562",
    "sg:postcode":"EX15 1BW",
    "sg:province":"Devon",
    "sg:tags":[
        "exhaust",
        "absorber",
        "shock",
        "system",
        "wholesaler",
        "manufacturer"
    ],
    "wof:name":"M B Components South West Ltd",
    "wof:placetype":"venue"
},
  "geometry": {"coordinates":[-3.3858940601,50.8614616394],"type":"Point"}
}