{
  "type": "Feature",
  "properties": {
    "iso:country":"GB",
    "sg:address":"The Old Works, Dover Street",
    "sg:city":"Maidstone",
    "sg:classifiers":[
        {
            "category":"Retail",
            "subcategory":"Auto Repair",
            "type":"Services"
        }
    ],
    "sg:postcode":"ME16 8LE",
    "sg:province":"Kent",
    "sg:tags":[
        "body",
        "car"
    ],
    "wof:name":"S R Paint & Body Repairs",
    "wof:placetype":"venue"
},
  "geometry": {"coordinates":[0.4978300035,51.2660293579],"type":"Point"}
}