{
  "type": "Feature",
  "properties": {
    "iso:country":"GB",
    "sg:address":"Ditribution Centre, Bookers Way",
    "sg:city":"Sheffield",
    "sg:classifiers":[
        {
            "category":"Wholesale",
            "subcategory":"Scrap",
            "type":"Manufacturing & Wholesale Goods"
        }
    ],
    "sg:phone":"+44 1909 519351",
    "sg:postcode":"S25 3SH",
    "sg:province":"South Yorkshire",
    "sg:tags":[
        "waste",
        "metal"
    ],
    "wof:name":"Safety Kleen Uk",
    "wof:placetype":"venue"
},
  "geometry": {"coordinates":[-1.23664,53.37019],"type":"Point"}
}