{
  "type": "Feature",
  "properties": {
    "addr:full":"12 Grays Inn Sq Bloomsbury Greater London WC1R 5JP",
    "addr:housenumber":"12",
    "addr:postcode":"wc1r 5jp",
    "addr:street":"Grays Inn Sq",
    "iso:country":"GB",
    "sg:address":"12 Grays Inn Sq",
    "sg:city":"Bloomsbury",
    "sg:classifiers":[
        {
            "category":"Professional",
            "subcategory":"Lawyer & Legal Services",
            "type":"Services"
        }
    ],
    "sg:phone":"+44 20 7404 4866",
    "sg:postcode":"WC1R 5JP",
    "sg:province":"Greater London",
    "sg:tags":[
        "barrister"
    ],
    "wof:name":"Andrzej J Kolodziej",
    "wof:placetype":"venue"
},
  "geometry": {"coordinates":[-0.114384,51.519127],"type":"Point"}
}