{
  "type": "Feature",
  "properties": {
    "iso:country":"GB",
    "sg:address":"37 Fengate",
    "sg:city":"Peterborough",
    "sg:classifiers":[
        {
            "category":"Retail",
            "subcategory":"Auto Repair",
            "type":"Services"
        }
    ],
    "sg:phone":"+44 1733 343941",
    "sg:postcode":"PE1 5BA",
    "sg:province":"Cambridgeshire",
    "sg:tags":[
        "modification",
        "garage",
        "related"
    ],
    "wof:name":"Ellingworth Garage",
    "wof:placetype":"venue"
},
  "geometry": {"coordinates":[-0.2266049981,52.5714225769],"type":"Point"}
}