{
  "type": "Feature",
  "properties": {
    "addr:full":"434 Hoe Street, Walthamstow London Greater London E17 9AA",
    "addr:housenumber":"434",
    "addr:postcode":"e17 9aa",
    "addr:street":"Hoe Street",
    "iso:country":"GB",
    "sg:address":"434 Hoe Street, Walthamstow",
    "sg:city":"London",
    "sg:classifiers":[
        {
            "category":"Taxi",
            "type":"Transportation"
        }
    ],
    "sg:phone":"+44 20 8521 4303",
    "sg:postcode":"E17 9AA",
    "sg:province":"Greater London",
    "sg:tags":[
        "mini",
        "cab"
    ],
    "wof:name":"Bailey Gardiner Cars Ltd.",
    "wof:placetype":"venue"
},
  "geometry": {"coordinates":[-0.015693,51.576454],"type":"Point"}
}