{
  "type": "Feature",
  "properties": {
    "addr:full":"62 Middle Street Brighton East Sussex BN1 1AL",
    "addr:housenumber":"62",
    "addr:postcode":"bn1 1al",
    "addr:street":"Middle Street",
    "iso:country":"GB",
    "sg:address":"62 Middle Street",
    "sg:city":"Brighton",
    "sg:classifiers":[
        {
            "category":"Shopping",
            "subcategory":"Department Store",
            "type":"Retail Goods"
        }
    ],
    "sg:phone":"+44 1273 722040",
    "sg:postcode":"BN1 1AL",
    "sg:province":"East Sussex",
    "wof:name":"Soul Jazz On Sea",
    "wof:placetype":"venue"
},
  "geometry": {"coordinates":[-0.143009,50.82103],"type":"Point"}
}