{
  "type": "Feature",
  "properties": {
    "addr:full":"Heatherwick Road Aberdeen Aberdeen City AB12 5ST",
    "addr:postcode":"ab12 5st",
    "addr:street":"Heatherwick Road",
    "iso:country":"GB",
    "sg:address":"Heatherwick Road",
    "sg:city":"Aberdeen",
    "sg:classifiers":[
        {
            "category":"Education",
            "subcategory":"School",
            "type":"Public Place"
        }
    ],
    "sg:phone":"+44 1224 872989",
    "sg:postcode":"AB12 5ST",
    "sg:province":"Aberdeen City",
    "sg:tags":[
        "local",
        "authority"
    ],
    "wof:name":"Craighill Primary School",
    "wof:placetype":"venue"
},
  "geometry": {"coordinates":[-2.115674,57.117485],"type":"Point"}
}