{
  "type": "Feature",
  "properties": {
    "addr:full":"132 Walsall Road, Stone Cross West Bromwich West Midlands B71 3HP",
    "addr:housenumber":"132",
    "addr:postcode":"b71 3hp",
    "addr:street":"Walsall Road",
    "iso:country":"GB",
    "sg:address":"132 Walsall Road, Stone Cross",
    "sg:city":"West Bromwich",
    "sg:classifiers":[
        {
            "category":"Real Estate",
            "subcategory":"Real Estate Agent",
            "type":"Services"
        }
    ],
    "sg:phone":"+44 121 601 9370",
    "sg:postcode":"B71 3HP",
    "sg:province":"West Midlands",
    "wof:name":"Bartram's Estate Agents",
    "wof:placetype":"venue"
},
  "geometry": {"coordinates":[-1.983797,52.544456],"type":"Point"}
}