{
  "type": "Feature",
  "properties": {
    "iso:country":"GB",
    "sg:address":"49 Briton Ferry Road",
    "sg:city":"Neath",
    "sg:classifiers":[
        {
            "category":"Bars & Pubs",
            "type":"Food & Drink"
        }
    ],
    "sg:phone":"+44 1639 641556",
    "sg:postcode":"SA11 1AR",
    "sg:province":"Neath Port Talbot",
    "sg:tags":[
        "pubs",
        "house",
        "inn",
        "public",
        "activity"
    ],
    "wof:name":"The Cambrian Arms",
    "wof:placetype":"venue"
},
  "geometry": {"coordinates":[-3.807412,51.655495],"type":"Point"}
}