{
  "type": "Feature",
  "properties": {
    "addr:full":"Marsh Farm, Lovington Castle Cary Somerset BA7 7PU",
    "addr:postcode":"ba7 7pu",
    "iso:country":"GB",
    "sg:address":"Marsh Farm, Lovington",
    "sg:city":"Castle Cary",
    "sg:classifiers":[
        {
            "category":"Professional",
            "subcategory":"Engineering",
            "type":"Services"
        }
    ],
    "sg:postcode":"BA7 7PU",
    "sg:province":"Somerset",
    "sg:tags":[
        "civil",
        "engineer"
    ],
    "wof:name":"Signup Engineering",
    "wof:placetype":"venue"
},
  "geometry": {"coordinates":[-2.5180859566,51.0890693665],"type":"Point"}
}