{
  "type": "Feature",
  "properties": {
    "addr:full":"10 Melton Road Leicester Leicestershire LE4 5EA",
    "addr:housenumber":"10",
    "addr:postcode":"le4 5ea",
    "addr:street":"Melton Road",
    "iso:country":"GB",
    "sg:address":"10 Melton Road",
    "sg:city":"Leicester",
    "sg:classifiers":[
        {
            "category":"Shopping",
            "subcategory":"Jewelry",
            "type":"Retail Goods"
        },
        {
            "category":"Shopping",
            "subcategory":"Comic Books",
            "type":"Retail Goods"
        }
    ],
    "sg:phone":"+44 116 266 9356",
    "sg:postcode":"LE4 5EA",
    "sg:province":"Leicestershire",
    "sg:tags":[
        "jeweller",
        "sale",
        "jewellery"
    ],
    "wof:name":"Jayant Jewellers",
    "wof:placetype":"venue"
},
  "geometry": {"coordinates":[-1.121213,52.651653],"type":"Point"}
}