{
  "type": "Feature",
  "properties": {
    "iso:country":"GB",
    "sg:address":"Oxford Rd",
    "sg:city":"Gerrards Cross",
    "sg:classifiers":[
        {
            "category":"Manufacturing",
            "subcategory":"Signs",
            "type":"Manufacturing & Wholesale Goods"
        }
    ],
    "sg:phone":"+44 1753 890500",
    "sg:postcode":"SL9 7BB",
    "sg:province":"Buckinghamshire",
    "sg:tags":[
        "identification",
        "card"
    ],
    "wof:name":"Shackman Instruments",
    "wof:placetype":"venue"
},
  "geometry": {"coordinates":[-0.5311840177,51.5739135742],"type":"Point"}
}