{
  "type": "Feature",
  "properties": {
    "addr:full":"10 Woodbridge Rd Guildford Surrey GU1 4PU",
    "addr:housenumber":"10",
    "addr:postcode":"gu1 4pu",
    "addr:street":"Woodbridge Rd",
    "iso:country":"GB",
    "sg:address":"10 Woodbridge Rd",
    "sg:city":"Guildford",
    "sg:classifiers":[
        {
            "category":"Bus Charters",
            "type":"Transportation"
        }
    ],
    "sg:postcode":"GU1 4PU",
    "sg:province":"Surrey",
    "sg:tags":[
        "coach"
    ],
    "wof:name":"Khaliqu,Abdul,",
    "wof:placetype":"venue"
},
  "geometry": {"coordinates":[-0.5753430128,51.2376594543],"type":"Point"}
}