{
  "type": "Feature",
  "properties": {
    "addr:full":"22 Newburn Street London Greater London SE11 5PJ",
    "addr:housenumber":"22",
    "addr:postcode":"se11 5pj",
    "addr:street":"Newburn Street",
    "iso:country":"GB",
    "sg:address":"22 Newburn Street",
    "sg:city":"London",
    "sg:classifiers":[
        {
            "category":"Real Estate",
            "subcategory":"Developer",
            "type":"Services"
        }
    ],
    "sg:postcode":"SE11 5PJ",
    "sg:province":"Greater London",
    "sg:tags":[
        "property"
    ],
    "wof:name":"Hi-Ted International Ltd.",
    "wof:placetype":"venue"
},
  "geometry": {"coordinates":[-0.1150769964,51.4894065857],"type":"Point"}
}