{
  "type": "Feature",
  "properties": {
    "iso:country":"GB",
    "sg:address":"126 High Street",
    "sg:city":"Rochester",
    "sg:classifiers":[
        {
            "category":"Shopping",
            "subcategory":"Clothing, Apparel, & Fashions",
            "type":"Retail Goods"
        },
        {
            "category":"Shopping",
            "subcategory":"Baby Store",
            "type":"Retail Goods"
        }
    ],
    "sg:phone":"+44 1634 819887",
    "sg:postcode":"ME1 1JT",
    "sg:province":"Kent",
    "sg:tags":[
        "child",
        "childrens",
        "babywear"
    ],
    "wof:name":"Just For Kidz",
    "wof:placetype":"venue"
},
  "geometry": {"coordinates":[0.505413,51.387676],"type":"Point"}
}