{
  "type": "Feature",
  "properties": {
    "iso:country":"GB",
    "sg:address":"Orchard View, West Acres",
    "sg:city":"Carlisle",
    "sg:classifiers":[
        {
            "category":"Wholesale",
            "subcategory":"Farm Supplies",
            "type":"Manufacturing & Wholesale Goods"
        }
    ],
    "sg:phone":"+44 1228 75320",
    "sg:postcode":"CA6 6DA",
    "sg:province":"Cumbria",
    "sg:tags":[
        "straw",
        "hay",
        "merchant"
    ],
    "wof:name":"F W H Liddell",
    "wof:placetype":"venue"
},
  "geometry": {"coordinates":[-2.89872,54.98671],"type":"Point"}
}