{
  "type": "Feature",
  "properties": {
    "addr:full":"Rear Of New Tavern Inn, Wingate Low, Wheatley Hill Durham Durham DH6 3LP",
    "addr:housenumber":"rear of",
    "addr:postcode":"dh6 3lp",
    "addr:street":"Wingate;Hill",
    "iso:country":"GB",
    "sg:address":"Rear Of New Tavern Inn, Wingate Low, Wheatley Hill",
    "sg:city":"Durham",
    "sg:classifiers":[
        {
            "category":"Professional",
            "subcategory":"Business Services",
            "type":"Services"
        }
    ],
    "sg:postcode":"DH6 3LP",
    "sg:province":"Durham",
    "sg:tags":[
        "bookmaker"
    ],
    "wof:name":"John Ridley",
    "wof:placetype":"venue"
},
  "geometry": {"coordinates":[-1.4166040421,54.7445602417],"type":"Point"}
}