{
  "type": "Feature",
  "properties": {
    "addr:full":"New Barn Office, Funtington Chichester West Sussex PO18 9DA",
    "addr:postcode":"po18 9da",
    "addr:street":"Funtington",
    "iso:country":"GB",
    "sg:address":"New Barn Office, Funtington",
    "sg:city":"Chichester",
    "sg:classifiers":[
        {
            "category":"Farming",
            "subcategory":"Livestock Farm",
            "type":"Manufacturing & Wholesale Goods"
        },
        {
            "category":"Farming",
            "subcategory":"Farm",
            "type":"Manufacturing & Wholesale Goods"
        }
    ],
    "sg:phone":"+44 1243 576155",
    "sg:postcode":"PO18 9DA",
    "sg:province":"West Sussex",
    "sg:tags":[
        "mixed",
        "crop",
        "others"
    ],
    "wof:name":"Basil Baird (Fareham) Ltd.",
    "wof:placetype":"venue"
},
  "geometry": {"coordinates":[-0.8663979769,50.8720397949],"type":"Point"}
}