{
  "type": "Feature",
  "properties": {
    "iso:country":"GB",
    "sg:address":"Westburn Rd",
    "sg:city":"Aberdeen",
    "sg:classifiers":[
        {
            "category":"Education",
            "subcategory":"University",
            "type":"Public Place"
        }
    ],
    "sg:phone":"+44 1224 681818",
    "sg:postcode":"AB25 2XG",
    "sg:province":"Aberdeen City",
    "sg:tags":[
        "medical",
        "school"
    ],
    "wof:name":"Foresterhill College",
    "wof:placetype":"venue"
},
  "geometry": {"coordinates":[-2.115034,57.153126],"type":"Point"}
}