{
  "type": "Feature",
  "properties": {
    "addr:full":"137 Gisburn Road, Barrowford Nelson Lancashire BB9 6EP",
    "addr:housenumber":"137",
    "addr:postcode":"bb9 6ep",
    "addr:street":"Gisburn Road",
    "iso:country":"GB",
    "sg:address":"137 Gisburn Road, Barrowford",
    "sg:city":"Nelson",
    "sg:classifiers":[
        {
            "category":"Shopping",
            "subcategory":"Pharmacy",
            "type":"Retail Goods"
        }
    ],
    "sg:phone":"+44 1282 612639",
    "sg:postcode":"BB9 6EP",
    "sg:province":"Lancashire",
    "sg:tags":[
        "pharmacist",
        "dispensing",
        "chemist"
    ],
    "wof:name":"VILLAGE PHARMACY",
    "wof:placetype":"venue"
},
  "geometry": {"coordinates":[-2.215036,53.853333],"type":"Point"}
}