{
  "type": "Feature",
  "properties": {
    "addr:full":"18 Park Brow Drive, Kirkby Liverpool Merseyside L32 6QP",
    "addr:housenumber":"18",
    "addr:postcode":"l32 6qp",
    "addr:street":"Park Brow Drive",
    "iso:country":"GB",
    "sg:address":"18 Park Brow Drive, Kirkby",
    "sg:city":"Liverpool",
    "sg:classifiers":[
        {
            "category":"Taxi",
            "type":"Transportation"
        },
        {
            "category":"Military Area",
            "subcategory":"Air Force Base",
            "type":"Public Place"
        }
    ],
    "sg:phone":"+44 151 546 4444",
    "sg:postcode":"L32 6QP",
    "sg:province":"Merseyside",
    "sg:tags":[
        "hire",
        "private"
    ],
    "wof:name":"Acorn Cars",
    "wof:placetype":"venue"
},
  "geometry": {"coordinates":[-2.8768730164,53.4747085571],"type":"Point"}
}