{
  "type": "Feature",
  "properties": {
    "addr:full":"67b Milton Park Abingdon Oxfordshire OX14 4RX",
    "addr:housenumber":"67b",
    "addr:postcode":"ox14 4rx",
    "addr:street":"Milton Park",
    "iso:country":"GB",
    "sg:address":"67b Milton Park",
    "sg:city":"Abingdon",
    "sg:classifiers":[
        {
            "category":"Health Services",
            "subcategory":"Clinic",
            "type":"Services"
        }
    ],
    "sg:phone":"+44 1235 862997",
    "sg:postcode":"OX14 4RX",
    "sg:province":"Oxfordshire",
    "sg:tags":[
        "medical"
    ],
    "wof:name":"Resmed (U K) Ltd.",
    "wof:placetype":"venue"
},
  "geometry": {"coordinates":[-1.2853569984,51.6324501038],"type":"Point"}
}