{
  "type": "Feature",
  "properties": {
    "iso:country":"GB",
    "sg:address":"44 Heaton Moor Rd",
    "sg:city":"Stockport",
    "sg:classifiers":[
        {
            "category":"Banks & Credit Unions",
            "subcategory":"Bank",
            "type":"Services"
        }
    ],
    "sg:phone":"+44 161 432 9449",
    "sg:postcode":"SK4 4NY",
    "sg:province":"Cheshire",
    "wof:name":"NatWest",
    "wof:placetype":"venue"
},
  "geometry": {"coordinates":[-2.181288,53.42424],"type":"Point"}
}