{
  "type": "Feature",
  "properties": {
    "addr:full":"4 Pier Road Seaview Isle of Wight PO34 5BL",
    "addr:housenumber":"4",
    "addr:postcode":"po34 5bl",
    "addr:street":"Pier Road",
    "iso:country":"GB",
    "sg:address":"4 Pier Road",
    "sg:city":"Seaview",
    "sg:classifiers":[
        {
            "category":"Shopping",
            "subcategory":"News",
            "type":"Retail Goods"
        },
        {
            "category":"Government",
            "subcategory":"Post Office",
            "type":"Public Place"
        }
    ],
    "sg:phone":"+44 1983 613306",
    "sg:postcode":"PO34 5BL",
    "sg:province":"Isle of Wight",
    "sg:tags":[
        "newsagent"
    ],
    "wof:name":"Seaview Post Office",
    "wof:placetype":"venue"
},
  "geometry": {"coordinates":[-1.109397,50.719345],"type":"Point"}
}