{
  "type": "Feature",
  "properties": {
    "addr:full":"Lloyd Way, Kimpton Hitchin Hertfordshire SG4 8QS",
    "addr:postcode":"sg4 8qs",
    "addr:street":"Lloyd Way",
    "iso:country":"GB",
    "sg:address":"Lloyd Way, Kimpton",
    "sg:city":"Hitchin",
    "sg:classifiers":[
        {
            "category":"Social Services",
            "subcategory":"Adult Care",
            "type":"Services"
        }
    ],
    "sg:phone":"+44 1438 832380",
    "sg:postcode":"SG4 8QS",
    "sg:province":"Hertfordshire",
    "sg:tags":[
        "housing",
        "sheltered"
    ],
    "wof:name":"Probyn House",
    "wof:placetype":"venue"
},
  "geometry": {"coordinates":[-0.2983390093,51.8511734009],"type":"Point"}
}