{
  "type": "Feature",
  "properties": {
    "addr:full":"50 Ledbury Road Hereford Herefordshire HR1 2SY",
    "addr:housenumber":"50",
    "addr:postcode":"hr1 2sy",
    "addr:street":"Ledbury Road",
    "iso:country":"GB",
    "sg:address":"50 Ledbury Road",
    "sg:city":"Hereford",
    "sg:classifiers":[
        {
            "category":"Professional",
            "subcategory":"Lawyer & Legal Services",
            "type":"Services"
        }
    ],
    "sg:phone":"+44 1432 359000",
    "sg:postcode":"HR1 2SY",
    "sg:province":"Herefordshire",
    "sg:tags":[
        "practitioner",
        "insolvency"
    ],
    "wof:name":"E Mary Grove & Co",
    "wof:placetype":"venue"
},
  "geometry": {"coordinates":[-2.703394,52.054108],"type":"Point"}
}