{
  "type": "Feature",
  "properties": {
    "addr:full":"Richmond House Avonmouth Way Bristol City of Bristol BS11 8DE",
    "addr:postcode":"bs11 8de",
    "addr:street":"Avonmouth Way",
    "iso:country":"GB",
    "sg:address":"Richmond House Avonmouth Way",
    "sg:city":"Bristol",
    "sg:classifiers":[
        {
            "category":"Professional",
            "subcategory":"Engineering",
            "type":"Services"
        }
    ],
    "sg:phone":"+44 117 914 8400",
    "sg:postcode":"BS11 8DE",
    "sg:province":"City of Bristol",
    "sg:tags":[
        "civil",
        "engineer"
    ],
    "wof:name":"Macob (Southwest)",
    "wof:placetype":"venue"
},
  "geometry": {"coordinates":[-2.6748991013,51.5049781799],"type":"Point"}
}