{
  "type": "Feature",
  "properties": {
    "addr:full":"Back Lane, Shrewley Warwick Warwickshire CV35 7BD",
    "addr:postcode":"cv35 7bd",
    "addr:street":"Back Lane",
    "iso:country":"GB",
    "sg:address":"Back Lane, Shrewley",
    "sg:city":"Warwick",
    "sg:classifiers":[
        {
            "category":"Farming",
            "subcategory":"Dairy Farm",
            "type":"Manufacturing & Wholesale Goods"
        }
    ],
    "sg:phone":"+44 1926 842383",
    "sg:postcode":"CV35 7BD",
    "sg:province":"Warwickshire",
    "sg:tags":[
        "farmer"
    ],
    "wof:name":"R & A E Wallbank",
    "wof:placetype":"venue"
},
  "geometry": {"coordinates":[-1.672279954,52.3059921265],"type":"Point"}
}