{
  "type": "Feature",
  "properties": {
    "addr:full":"Second Floor, Willow Ho, Willow Row Derby Derbyshire DE1 3NZ",
    "addr:housenumber":"second floor",
    "addr:postcode":"de1 3nz",
    "addr:street":"Willow Ho Willow Row",
    "iso:country":"GB",
    "sg:address":"Second Floor, Willow Ho, Willow Row",
    "sg:city":"Derby",
    "sg:classifiers":[
        {
            "category":"Government",
            "subcategory":"Court House",
            "type":"Public Place"
        }
    ],
    "sg:phone":"+44 1332 290214",
    "sg:postcode":"DE1 3NZ",
    "sg:province":"Derbyshire",
    "wof:name":"Family Court Welfare Service",
    "wof:placetype":"venue"
},
  "geometry": {"coordinates":[-1.4820530415,52.9252357483],"type":"Point"}
}