{
  "type": "Feature",
  "properties": {
    "addr:full":"Broadmoor Kilgetty Pembrokeshire SA68 0RH",
    "addr:postcode":"sa68 0rh",
    "iso:country":"GB",
    "sg:address":"Broadmoor",
    "sg:city":"Kilgetty",
    "sg:classifiers":[
        {
            "category":"Travel",
            "subcategory":"Hotels & Motels",
            "type":"Entertainment"
        }
    ],
    "sg:phone":"+44 1834 811212",
    "sg:postcode":"SA68 0RH",
    "sg:province":"Pembrokeshire",
    "sg:tags":[
        "self",
        "catering"
    ],
    "wof:name":"A & A Eardley",
    "wof:placetype":"venue"
},
  "geometry": {"coordinates":[-4.7145628929,51.7328338623],"type":"Point"}
}