{
  "type": "Feature",
  "properties": {
    "iso:country":"GB",
    "sg:address":"Santa Rosa",
    "sg:city":"Newton Abbot",
    "sg:classifiers":[
        {
            "category":"Building & Trades",
            "subcategory":"Plumbing",
            "type":"Services"
        }
    ],
    "sg:phone":"+44 1626 872607",
    "sg:postcode":"TQ12 4QJ",
    "sg:province":"Devon",
    "sg:tags":[
        "heating"
    ],
    "wof:name":"Clovis",
    "wof:placetype":"venue"
},
  "geometry": {"coordinates":[-3.6076591015,50.5288696289],"type":"Point"}
}