{
  "type": "Feature",
  "properties": {
    "addr:full":"Unit 2 James Little Street Kilmarnock East Ayrshire KA1 4AT",
    "addr:housenumber":"unit 2",
    "addr:postcode":"ka1 4at",
    "addr:street":"James Little Street",
    "iso:country":"GB",
    "sg:address":"Unit 2 James Little Street",
    "sg:city":"Kilmarnock",
    "sg:classifiers":[
        {
            "category":"Communications",
            "subcategory":"Film & Video Production",
            "type":"Services"
        }
    ],
    "sg:phone":"+44 1563 540444",
    "sg:postcode":"KA1 4AT",
    "sg:province":"East Ayrshire",
    "sg:tags":[
        "tv",
        "studio"
    ],
    "wof:name":"Audio Vision Services",
    "wof:placetype":"venue"
},
  "geometry": {"coordinates":[-4.4959368706,55.6022415161],"type":"Point"}
}