{
  "type": "Feature",
  "properties": {
    "iso:country":"GB",
    "sg:address":"18 Willow St",
    "sg:city":"Congleton",
    "sg:classifiers":[
        {
            "category":"Restaurant",
            "type":"Food & Drink"
        }
    ],
    "sg:phone":"+44 1260 270990",
    "sg:postcode":"CW12 1RL",
    "sg:province":"Cheshire",
    "wof:name":"The Grapevine",
    "wof:placetype":"venue"
},
  "geometry": {"coordinates":[-2.205952,53.164635],"type":"Point"}
}