{
  "type": "Feature",
  "properties": {
    "addr:full":"76 St Nicolas Park Drive Nuneaton Leicestershire CV11 6DJ",
    "addr:housenumber":"76",
    "addr:postcode":"cv11 6dj",
    "addr:street":"St Nicolas Park Drive",
    "iso:country":"GB",
    "sg:address":"76 St Nicolas Park Drive",
    "sg:city":"Nuneaton",
    "sg:classifiers":[
        {
            "category":"Food & Beverages",
            "subcategory":"Liquor & Beverages",
            "type":"Retail Goods"
        }
    ],
    "sg:phone":"+44 24 7632 8384",
    "sg:postcode":"CV11 6DJ",
    "sg:province":"Leicestershire",
    "sg:tags":[
        "beer",
        "spirit",
        "wines"
    ],
    "wof:name":"Thresher",
    "wof:placetype":"venue"
},
  "geometry": {"coordinates":[-1.445773,52.535728],"type":"Point"}
}