{
  "type": "Feature",
  "properties": {
    "addr:full":"Unit 12 Hornet Close, Pysons Road Industrial Estate Broadstairs Kent CT10 2YD",
    "addr:housenumber":"unit 12",
    "addr:postcode":"ct10 2yd",
    "addr:street":"Hornet Close Pysons Road Industrial Estate",
    "iso:country":"GB",
    "sg:address":"Unit 12 Hornet Close, Pysons Road Industrial Estate",
    "sg:city":"Broadstairs",
    "sg:classifiers":[
        {
            "category":"Retail",
            "subcategory":"Auto Repair",
            "type":"Services"
        }
    ],
    "sg:phone":"+44 1843 603480",
    "sg:postcode":"CT10 2YD",
    "sg:province":"Kent",
    "sg:tags":[
        "bodybuilder",
        "repairer"
    ],
    "wof:name":"Thanet Commercials",
    "wof:placetype":"venue"
},
  "geometry": {"coordinates":[1.441059947,51.3586044312],"type":"Point"}
}