{
  "type": "Feature",
  "properties": {
    "addr:full":"Winding St Hastings East Sussex TN34 3AT",
    "addr:postcode":"tn34 3at",
    "addr:street":"Winding St",
    "iso:country":"GB",
    "sg:address":"Winding St",
    "sg:city":"Hastings",
    "sg:classifiers":[
        {
            "category":"Social Services",
            "type":"Services"
        }
    ],
    "sg:phone":"+44 1424 439560",
    "sg:postcode":"TN34 3AT",
    "sg:province":"East Sussex",
    "wof:name":"Isabel Blackman Centre",
    "wof:placetype":"venue"
},
  "geometry": {"coordinates":[0.591755,50.856541],"type":"Point"}
}