{
  "type": "Feature",
  "properties": {
    "iso:country":"GB",
    "sg:address":"47 Narrow Lane, Histon",
    "sg:city":"Cambridge",
    "sg:classifiers":[
        {
            "category":"Real Estate",
            "subcategory":"Architect",
            "type":"Services"
        }
    ],
    "sg:postcode":"CB4 9HD",
    "sg:province":"Cambridgeshire",
    "wof:name":"Braxbridge Engineering Ltd",
    "wof:placetype":"venue"
},
  "geometry": {"coordinates":[0.1080090031,52.2551422119],"type":"Point"}
}