{
  "type": "Feature",
  "properties": {
    "addr:full":"Ridgefield, Harrowden Road Wellingborough Northamptonshire NN8 5BD",
    "addr:postcode":"nn8 5bd",
    "addr:street":"Harrowden Road",
    "iso:country":"GB",
    "sg:address":"Ridgefield, Harrowden Road",
    "sg:city":"Wellingborough",
    "sg:classifiers":[
        {
            "category":"Building & Trades",
            "subcategory":"Construction",
            "type":"Services"
        },
        {
            "category":"Sports & Exercise",
            "subcategory":"Playing Field",
            "type":"Entertainment"
        }
    ],
    "sg:phone":"+44 1933 223695",
    "sg:postcode":"NN8 5BD",
    "sg:province":"Northamptonshire",
    "sg:tags":[
        "tennis",
        "court",
        "surface"
    ],
    "wof:name":"M T O'Boyle",
    "wof:placetype":"venue"
},
  "geometry": {"coordinates":[-0.696296,52.302422],"type":"Point"}
}