{
  "type": "Feature",
  "properties": {
    "iso:country":"GB",
    "sg:address":"12c High Street",
    "sg:city":"Bury St Edmunds",
    "sg:classifiers":[
        {
            "category":"Restaurant",
            "type":"Food & Drink"
        }
    ],
    "sg:phone":"+44 1638 712209",
    "sg:postcode":"IP28 6EQ",
    "sg:province":"Cambridgeshire",
    "sg:tags":[
        "indian"
    ],
    "wof:name":"Gandhi Tandoori Indian Restaurant",
    "wof:placetype":"venue"
},
  "geometry": {"coordinates":[0.542907,52.316399],"type":"Point"}
}