{
  "type": "Feature",
  "properties": {
    "iso:country":"GB",
    "sg:address":"134 Crouch Hill",
    "sg:city":"London",
    "sg:classifiers":[
        {
            "category":"Professional",
            "subcategory":"Computer Services",
            "type":"Services"
        }
    ],
    "sg:phone":"+44 20 8341 0566",
    "sg:postcode":"N8 9DX",
    "sg:province":"Greater London",
    "sg:tags":[
        "system",
        "software"
    ],
    "wof:name":"Barnard Microsystems Ltd.",
    "wof:placetype":"venue"
},
  "geometry": {"coordinates":[-0.127039,51.57457],"type":"Point"}
}