{
  "type": "Feature",
  "properties": {
    "iso:country":"GB",
    "sg:address":"Woodside Road",
    "sg:city":"Eastleigh",
    "sg:classifiers":[
        {
            "category":"Wholesale",
            "subcategory":"Non-durable Goods",
            "type":"Manufacturing & Wholesale Goods"
        }
    ],
    "sg:phone":"+44 23 8061 0816",
    "sg:postcode":"SO50 4ET",
    "sg:province":"Hampshire",
    "sg:tags":[
        "carry",
        "cash"
    ],
    "wof:name":"Booker Cash & Carry",
    "wof:placetype":"venue"
},
  "geometry": {"coordinates":[-1.3689990044,50.975440979],"type":"Point"}
}