{
  "type": "Feature",
  "properties": {
    "iso:country":"GB",
    "sg:address":"North Mersey Business Centre, Knowsley Industrial Park",
    "sg:city":"Liverpool",
    "sg:classifiers":[
        {
            "category":"Government",
            "subcategory":"Post Office",
            "type":"Public Place"
        }
    ],
    "sg:phone":"+44 151 292 8222",
    "sg:postcode":"L33 7UZ",
    "sg:province":"Lancashire",
    "sg:tags":[
        "messenger",
        "courier"
    ],
    "wof:name":"Fast Wheels Transport & Couriers",
    "wof:placetype":"venue"
},
  "geometry": {"coordinates":[-2.8445940018,53.4834632874],"type":"Point"}
}