{
  "type": "Feature",
  "properties": {
    "addr:full":"Grange Court, Abingdon Science Park Abingdon Oxfordshire OX14 3NU",
    "addr:postcode":"ox14 3nu",
    "addr:street":"Grange;Park",
    "iso:country":"GB",
    "sg:address":"Grange Court, Abingdon Science Park",
    "sg:city":"Abingdon",
    "sg:classifiers":[
        {
            "category":"Building & Trades",
            "subcategory":"Construction",
            "type":"Services"
        }
    ],
    "sg:phone":"+44 1235 544500",
    "sg:postcode":"OX14 3NU",
    "sg:province":"Oxfordshire",
    "sg:tags":[
        "builder"
    ],
    "wof:name":"J B Leadbitter & Co. Ltd.",
    "wof:placetype":"venue"
},
  "geometry": {"coordinates":[-1.2599070072,51.6719741821],"type":"Point"}
}