{
  "type": "Feature",
  "properties": {
    "iso:country":"GB",
    "sg:address":"The Farmhouse, Nix Hill Road, Wimblington",
    "sg:city":"March",
    "sg:classifiers":[
        {
            "category":"Travel",
            "subcategory":"Hotels & Motels",
            "type":"Entertainment"
        }
    ],
    "sg:postcode":"PE15 0PL",
    "sg:province":"Cambridgeshire",
    "sg:tags":[
        "self",
        "catering"
    ],
    "wof:name":"Snowise",
    "wof:placetype":"venue"
},
  "geometry": {"coordinates":[0.08618,52.508385],"type":"Point"}
}