{
  "type": "Feature",
  "properties": {
    "addr:full":"121 St Georges Road Dagenham Essex RM9 5JB",
    "addr:housenumber":"121",
    "addr:postcode":"rm9 5jb",
    "addr:street":"St Georges Road",
    "iso:country":"GB",
    "sg:address":"121 St Georges Road",
    "sg:city":"Dagenham",
    "sg:classifiers":[
        {
            "category":"Building & Trades",
            "subcategory":"Construction",
            "type":"Services"
        }
    ],
    "sg:phone":"+44 20 8596 0700",
    "sg:postcode":"RM9 5JB",
    "sg:province":"Essex",
    "sg:tags":[
        "roofing"
    ],
    "wof:name":"W P Roofing",
    "wof:placetype":"venue"
},
  "geometry": {"coordinates":[0.1396349967,51.550327301],"type":"Point"}
}