{
  "type": "Feature",
  "properties": {
    "iso:country":"GB",
    "sg:address":"Medstead Lodge, Wield Road, Madstead",
    "sg:city":"Alton",
    "sg:classifiers":[
        {
            "category":"Professional",
            "subcategory":"Management & Consulting",
            "type":"Services"
        }
    ],
    "sg:phone":"+44 1420 561094",
    "sg:postcode":"GU34 5LY",
    "sg:province":"Hampshire",
    "sg:tags":[
        "marketing",
        "consultant"
    ],
    "wof:name":"Far Atlantic Ltd.",
    "wof:placetype":"venue"
},
  "geometry": {"coordinates":[-1.064815,51.129547],"type":"Point"}
}