{
  "type": "Feature",
  "properties": {
    "addr:full":"39 Larkshall Road London Greater London E4 7HS",
    "addr:housenumber":"39",
    "addr:postcode":"e4 7hs",
    "addr:street":"Larkshall Road",
    "iso:country":"GB",
    "sg:address":"39 Larkshall Road",
    "sg:city":"London",
    "sg:classifiers":[
        {
            "category":"Real Estate",
            "subcategory":"Real Estate Agent",
            "type":"Services"
        },
        {
            "category":"Social Services",
            "subcategory":"Retirement Home",
            "type":"Services"
        }
    ],
    "sg:phone":"+44 20 8523 8061",
    "sg:postcode":"E4 7HS",
    "sg:province":"Greater London",
    "sg:tags":[
        "residential",
        "care"
    ],
    "wof:name":"M C C H SOCIETY LTD",
    "wof:placetype":"venue"
},
  "geometry": {"coordinates":[0.0029509999,51.6266174316],"type":"Point"}
}