{
  "type": "Feature",
  "properties": {
    "addr:full":"8 Stallins Lane, Kingswinford Brierley Hill Staffordshire DY6 7HT",
    "addr:housenumber":"8",
    "addr:postcode":"dy6 7ht",
    "addr:street":"Stallins Lane",
    "iso:country":"GB",
    "sg:address":"8 Stallins Lane, Kingswinford",
    "sg:city":"Brierley Hill",
    "sg:classifiers":[
        {
            "category":"Banks & Credit Unions",
            "subcategory":"Financial Services",
            "type":"Services"
        }
    ],
    "sg:phone":"+44 1384 402290",
    "sg:postcode":"DY6 7HT",
    "sg:province":"Staffordshire",
    "sg:tags":[
        "consultant"
    ],
    "wof:name":"T M V Finance Ltd.",
    "wof:placetype":"venue"
},
  "geometry": {"coordinates":[-2.169769,52.50415],"type":"Point"}
}