{
  "type": "Feature",
  "properties": {
    "addr:full":"63 Campden Street London Greater London W8 7EL",
    "addr:housenumber":"63",
    "addr:postcode":"w8 7el",
    "addr:street":"Campden Street",
    "iso:country":"GB",
    "sg:address":"63 Campden Street",
    "sg:city":"London",
    "sg:classifiers":[
        {
            "category":"Professional",
            "subcategory":"Art Services",
            "type":"Services"
        }
    ],
    "sg:phone":"+44 20 7727 0997",
    "sg:postcode":"W8 7EL",
    "sg:province":"Greater London",
    "sg:tags":[
        "photographer"
    ],
    "wof:name":"Peter Knab",
    "wof:placetype":"venue"
},
  "geometry": {"coordinates":[-0.197485,51.506184],"type":"Point"}
}