{
  "type": "Feature",
  "properties": {
    "addr:full":"361 Chester Road Sutton Coldfield West Midlands B73 5BL",
    "addr:housenumber":"361",
    "addr:postcode":"b73 5bl",
    "addr:street":"Chester Road",
    "iso:country":"GB",
    "sg:address":"361 Chester Road",
    "sg:city":"Sutton Coldfield",
    "sg:classifiers":[
        {
            "category":"Building & Trades",
            "subcategory":"Construction",
            "type":"Services"
        }
    ],
    "sg:phone":"+44 121 373 2228",
    "sg:postcode":"B73 5BL",
    "sg:province":"West Midlands",
    "sg:tags":[
        "glazier"
    ],
    "wof:name":"Eric Bradknock",
    "wof:placetype":"venue"
},
  "geometry": {"coordinates":[-1.8451499939,52.5414352417],"type":"Point"}
}