{
  "type": "Feature",
  "properties": {
    "addr:full":"10 Woodgate Way South Glenrothes Fife KY7 4PF",
    "addr:housenumber":"10",
    "addr:postcode":"ky7 4pf",
    "addr:street":"Woodgate Way South",
    "iso:country":"GB",
    "sg:address":"10 Woodgate Way South",
    "sg:city":"Glenrothes",
    "sg:classifiers":[
        {
            "category":"Building & Trades",
            "subcategory":"Construction",
            "type":"Services"
        }
    ],
    "sg:phone":"+44 1592 770222",
    "sg:postcode":"KY7 4PF",
    "sg:province":"Fife",
    "sg:tags":[
        "flooring"
    ],
    "wof:name":"G.L Taxis",
    "wof:placetype":"venue"
},
  "geometry": {"coordinates":[-3.151691,56.186466],"type":"Point"}
}