{
  "type": "Feature",
  "properties": {
    "addr:full":"43-45 Oundle Road Peterborough Cambridgeshire PE2 9PB",
    "addr:housenumber":"43-45",
    "addr:postcode":"pe2 9pb",
    "addr:street":"Oundle Road",
    "iso:country":"GB",
    "sg:address":"43-45 Oundle Road",
    "sg:city":"Peterborough",
    "sg:classifiers":[
        {
            "category":"Autos & Motor Vehicles",
            "subcategory":"Auto Supplies",
            "type":"Retail Goods"
        }
    ],
    "sg:phone":"+44 1733 562698",
    "sg:postcode":"PE2 9PB",
    "sg:province":"Cambridgeshire",
    "sg:tags":[
        "tyre"
    ],
    "wof:name":"Tom Russo Tyre & Exhaust Centre",
    "wof:placetype":"venue"
},
  "geometry": {"coordinates":[-0.2478809953,52.5657997131],"type":"Point"}
}