{
  "type": "Feature",
  "properties": {
    "addr:full":"Welford Road Leicester Leicestershire LE2 1AD",
    "addr:postcode":"le2 1ad",
    "addr:street":"Welford Road",
    "iso:country":"GB",
    "sg:address":"Welford Road",
    "sg:city":"Leicester",
    "sg:classifiers":[
        {
            "category":"Parking",
            "type":"Transportation"
        }
    ],
    "sg:phone":"+44 20 7499 7050",
    "sg:postcode":"LE2 1AD",
    "sg:province":"Leicestershire",
    "sg:tags":[
        "car",
        "park"
    ],
    "wof:name":"Ncp",
    "wof:placetype":"venue"
},
  "geometry": {"coordinates":[-1.1183199883,52.628578186],"type":"Point"}
}