{
  "type": "Feature",
  "properties": {
    "addr:full":"Moorland County First School, Maslin Drive, Beanhill Milton Keynes Buckinghamshire MK6 4ND",
    "addr:postcode":"mk6 4nd",
    "addr:street":"Maslin Drive",
    "iso:country":"GB",
    "sg:address":"Moorland County First School, Maslin Drive, Beanhill",
    "sg:city":"Milton Keynes",
    "sg:classifiers":[
        {
            "category":"Professional",
            "type":"Services"
        }
    ],
    "sg:phone":"+44 1908 678644",
    "sg:postcode":"MK6 4ND",
    "sg:province":"Buckinghamshire",
    "sg:tags":[
        "caterer"
    ],
    "wof:name":"Moorland Kitchens",
    "wof:placetype":"venue"
},
  "geometry": {"coordinates":[-0.737159,52.01825],"type":"Point"}
}