{
  "type": "Feature",
  "properties": {
    "addr:full":"Witch Road Kilmarnock East Ayrshire KA3 1JF",
    "addr:postcode":"ka3 1jf",
    "addr:street":"Witch Road",
    "iso:country":"GB",
    "sg:address":"Witch Road",
    "sg:city":"Kilmarnock",
    "sg:classifiers":[
        {
            "category":"Education",
            "subcategory":"Special Training",
            "type":"Public Place"
        },
        {
            "category":"Education",
            "subcategory":"School",
            "type":"Public Place"
        },
        {
            "category":"Government",
            "subcategory":"Office",
            "type":"Public Place"
        }
    ],
    "sg:phone":"+44 1563 533863",
    "sg:postcode":"KA3 1JF",
    "sg:province":"East Ayrshire",
    "sg:tags":[
        "local"
    ],
    "wof:name":"Witchhill School",
    "wof:placetype":"venue"
},
  "geometry": {"coordinates":[-4.497089,55.615601],"type":"Point"}
}