{
  "type": "Feature",
  "properties": {
    "addr:full":"5 The Valley Leeds North Yorkshire LS17 7NL",
    "addr:housenumber":"5",
    "addr:postcode":"ls17 7nl",
    "addr:street":"The Valley Leeds",
    "iso:country":"GB",
    "sg:address":"5 The Valley",
    "sg:city":"Leeds",
    "sg:classifiers":[
        {
            "category":"Building & Trades",
            "subcategory":"Construction",
            "type":"Services"
        }
    ],
    "sg:phone":"+44 113 267 9137",
    "sg:postcode":"LS17 7NL",
    "sg:province":"North Yorkshire",
    "sg:tags":[
        "decorator",
        "painter"
    ],
    "wof:name":"Edwin Holmes",
    "wof:placetype":"venue"
},
  "geometry": {"coordinates":[-1.5563770533,53.8590660095],"type":"Point"}
}