{
  "type": "Feature",
  "properties": {
    "iso:country":"GB",
    "sg:address":"48 Coniston Gardens",
    "sg:city":"London",
    "sg:classifiers":[
        {
            "category":"Building & Trades",
            "subcategory":"Construction",
            "type":"Services"
        }
    ],
    "sg:phone":"+44 20 8205 2305",
    "sg:postcode":"NW9 0BB",
    "sg:province":"Greater London",
    "sg:tags":[
        "dry",
        "lining",
        "plasterers",
        "screeders"
    ],
    "wof:name":"Frank Culkin",
    "wof:placetype":"venue"
},
  "geometry": {"coordinates":[-0.256967,51.583557],"type":"Point"}
}