{
  "type": "Feature",
  "properties": {
    "iso:country":"GB",
    "sg:address":"51 Chipstead Valley Road",
    "sg:city":"Coulsdon",
    "sg:classifiers":[
        {
            "category":"Shopping",
            "subcategory":"Discount & Variety Stores",
            "type":"Retail Goods"
        }
    ],
    "sg:postcode":"CR5 2RB",
    "sg:province":"Surrey",
    "sg:tags":[
        "shop",
        "model"
    ],
    "wof:name":"Downs Classic Models",
    "wof:placetype":"venue"
},
  "geometry": {"coordinates":[-0.140531,51.319988],"type":"Point"}
}