{
  "type": "Feature",
  "properties": {
    "addr:full":"Marlborough Court, Pickford Street Macclesfield Cheshire SK11 6JD",
    "addr:postcode":"sk11 6jd",
    "addr:street":"Marlborough Court Pickford Street",
    "iso:country":"GB",
    "sg:address":"Marlborough Court, Pickford Street",
    "sg:city":"Macclesfield",
    "sg:classifiers":[
        {
            "category":"Restaurant",
            "type":"Food & Drink"
        }
    ],
    "sg:phone":"+44 1625 500505",
    "sg:postcode":"SK11 6JD",
    "sg:province":"Cheshire",
    "wof:name":"Valtellina Pizzeria & Ristorante",
    "wof:placetype":"venue"
},
  "geometry": {"coordinates":[-2.122799,53.257599],"type":"Point"}
}