{
  "type": "Feature",
  "properties": {
    "addr:full":"12 St James's Parade Bath Bath and North East Somerset BA1 1UL",
    "addr:housenumber":"12",
    "addr:postcode":"ba1 1ul",
    "addr:street":"St James'S Parade",
    "iso:country":"GB",
    "sg:address":"12 St James's Parade",
    "sg:city":"Bath",
    "sg:classifiers":[
        {
            "category":"Personal",
            "subcategory":"Shoe Repair & Shine",
            "type":"Services"
        },
        {
            "category":"Shopping",
            "subcategory":"Shoes",
            "type":"Retail Goods"
        }
    ],
    "sg:phone":"+44 1225 422944",
    "sg:postcode":"BA1 1UL",
    "sg:province":"Bath and North East Somerset",
    "wof:name":"D & D Shoe Repairs",
    "wof:placetype":"venue"
},
  "geometry": {"coordinates":[-2.3607699871,51.3791007996],"type":"Point"}
}