{
  "type": "Feature",
  "properties": {
    "addr:full":"Unit 13-14 The Promenades Centre Bridlington East Riding of Yorkshire YO15 2NG",
    "addr:housenumber":"unit 13-14",
    "addr:postcode":"yo15 2ng",
    "addr:street":"The;Bridlington",
    "iso:country":"GB",
    "sg:address":"Unit 13-14 The Promenades Centre",
    "sg:city":"Bridlington",
    "sg:classifiers":[
        {
            "category":"Shopping",
            "subcategory":"Clothing, Apparel, & Fashions",
            "type":"Retail Goods"
        }
    ],
    "sg:phone":"+44 1262 605039",
    "sg:postcode":"YO15 2NG",
    "sg:province":"East Riding of Yorkshire",
    "sg:tags":[
        "shop"
    ],
    "wof:name":"New Look",
    "wof:placetype":"venue"
},
  "geometry": {"coordinates":[-0.192424,54.083496],"type":"Point"}
}