{
  "type": "Feature",
  "properties": {
    "addr:full":"Strand Street Whitehaven Cumbria CA28 7LW",
    "addr:postcode":"ca28 7lw",
    "addr:street":"Strand Street",
    "iso:country":"GB",
    "sg:address":"Strand Street",
    "sg:city":"Whitehaven",
    "sg:classifiers":[
        {
            "category":"Bars & Pubs",
            "type":"Food & Drink"
        }
    ],
    "sg:phone":"+44 1946 592029",
    "sg:postcode":"CA28 7LW",
    "sg:province":"Cumbria",
    "sg:tags":[
        "pubs",
        "inn"
    ],
    "wof:name":"The White House",
    "wof:placetype":"venue"
},
  "geometry": {"coordinates":[-3.5906350613,54.5481262207],"type":"Point"}
}