{
  "type": "Feature",
  "properties": {
    "iso:country":"GB",
    "sg:address":"Unit 13 Castle View Business Centre, Gas House Rd",
    "sg:city":"Rochester",
    "sg:classifiers":[
        {
            "category":"Autos & Motor Vehicles",
            "subcategory":"Automobile Sales",
            "type":"Retail Goods"
        },
        {
            "category":"Retail",
            "subcategory":"Auto Repair",
            "type":"Services"
        }
    ],
    "sg:postcode":"ME1 1PB",
    "sg:province":"Kent",
    "sg:tags":[
        "modification",
        "garage",
        "car"
    ],
    "wof:name":"Smith,Terence John,",
    "wof:placetype":"venue"
},
  "geometry": {"coordinates":[0.50667,51.391441],"type":"Point"}
}