{
  "type": "Feature",
  "properties": {
    "addr:full":"Sawmills, Wellington Street Bradford West Yorkshire BD4 8BW",
    "addr:postcode":"bd4 8bw",
    "addr:street":"Wellington Street",
    "iso:country":"GB",
    "sg:address":"Sawmills, Wellington Street",
    "sg:city":"Bradford",
    "sg:classifiers":[
        {
            "category":"Manufacturing",
            "subcategory":"Lumber",
            "type":"Manufacturing & Wholesale Goods"
        }
    ],
    "sg:phone":"+44 1274 656563",
    "sg:postcode":"BD4 8BW",
    "sg:province":"West Yorkshire",
    "sg:tags":[
        "importer",
        "merchants",
        "agent",
        "timber"
    ],
    "wof:name":"Peter Ramsey (Timber) Ltd.",
    "wof:placetype":"venue"
},
  "geometry": {"coordinates":[-1.7154040337,53.789150238],"type":"Point"}
}