{
  "type": "Feature",
  "properties": {
    "iso:country":"GB",
    "sg:address":"1 Saxons Rise, Ratby",
    "sg:city":"Leicester",
    "sg:classifiers":[
        {
            "category":"Professional",
            "subcategory":"Accounting & Tax Preparation",
            "type":"Services"
        }
    ],
    "sg:postcode":"LE6 0NF",
    "sg:province":"Leicestershire",
    "sg:tags":[
        "accountant"
    ],
    "wof:name":"Book-Keeping & Credit Control Services",
    "wof:placetype":"venue"
},
  "geometry": {"coordinates":[-1.2440099716,52.6511650085],"type":"Point"}
}