{
  "type": "Feature",
  "properties": {
    "addr:full":"Brocklands Farm, 93 Flitton Road, Glenford Bedford Bedfordshire MK45 5DJ",
    "addr:housenumber":"93",
    "addr:postcode":"mk45 5dj",
    "addr:street":"Flitton Road",
    "iso:country":"GB",
    "sg:address":"Brocklands Farm, 93 Flitton Road, Glenford",
    "sg:city":"Bedford",
    "sg:classifiers":[
        {
            "category":"Communications",
            "subcategory":"Film & Video Production",
            "type":"Services"
        }
    ],
    "sg:phone":"+44 1525 717171",
    "sg:postcode":"MK45 5DJ",
    "sg:province":"Bedfordshire",
    "sg:tags":[
        "curers",
        "bacon",
        "ham"
    ],
    "wof:name":"John & Peter Oakley",
    "wof:placetype":"venue"
},
  "geometry": {"coordinates":[-0.4630399942,52.0040893555],"type":"Point"}
}