{
  "type": "Feature",
  "properties": {
    "addr:full":"Hurlfield Dental Centre, 49 Hurlfield Rd Sheffield Derbyshire S12 2SD",
    "addr:housenumber":"49",
    "addr:postcode":"s12 2sd",
    "addr:street":"Hurlfield Rd",
    "iso:country":"GB",
    "sg:address":"Hurlfield Dental Centre, 49 Hurlfield Rd",
    "sg:city":"Sheffield",
    "sg:classifiers":[
        {
            "category":"Health Services",
            "subcategory":"Dentist",
            "type":"Services"
        }
    ],
    "sg:phone":"+44 114 239 1906",
    "sg:postcode":"S12 2SD",
    "sg:province":"Derbyshire",
    "wof:name":"J Williams",
    "wof:placetype":"venue"
},
  "geometry": {"coordinates":[-1.4645440578,53.3831100464],"type":"Point"}
}