{
  "type": "Feature",
  "properties": {
    "addr:full":"A38 Kennford Exeter Devon EX6 7TF",
    "addr:postcode":"ex6 7tf",
    "iso:country":"GB",
    "sg:address":"A38 Kennford",
    "sg:city":"Exeter",
    "sg:classifiers":[
        {
            "category":"Shopping",
            "subcategory":"Bicycles & Sporting Goods",
            "type":"Retail Goods"
        }
    ],
    "sg:phone":"+44 1392 833303",
    "sg:postcode":"EX6 7TF",
    "sg:province":"Devon",
    "sg:tags":[
        "shop",
        "cycle",
        "accessory"
    ],
    "wof:name":"Partridge Cycles Superstores",
    "wof:placetype":"venue"
},
  "geometry": {"coordinates":[-3.5385529995,50.6631622314],"type":"Point"}
}