{
  "type": "Feature",
  "properties": {
    "addr:full":"Longmeadow, Wootton Northampton Northamptonshire NN4 6AN",
    "addr:postcode":"nn4 6an",
    "addr:street":"Wootton",
    "iso:country":"GB",
    "sg:address":"Longmeadow, Wootton",
    "sg:city":"Northampton",
    "sg:classifiers":[
        {
            "category":"Real Estate",
            "subcategory":"Real Estate Agent",
            "type":"Services"
        }
    ],
    "sg:phone":"+44 1604 677995",
    "sg:postcode":"NN4 6AN",
    "sg:province":"Northamptonshire",
    "wof:name":"Connell Estate Agents",
    "wof:placetype":"venue"
},
  "geometry": {"coordinates":[-0.8856840134,52.2018966675],"type":"Point"}
}