{
  "type": "Feature",
  "properties": {
    "addr:full":"Cairnmill Sawmill, Penpont Thornhill Dumfries and Galloway DG3 4LZ",
    "addr:postcode":"dg3 4lz",
    "iso:country":"GB",
    "sg:address":"Cairnmill Sawmill, Penpont",
    "sg:city":"Thornhill",
    "sg:classifiers":[
        {
            "category":"Manufacturing",
            "subcategory":"Lumber",
            "type":"Manufacturing & Wholesale Goods"
        }
    ],
    "sg:phone":"+44 1848 331662",
    "sg:postcode":"DG3 4LZ",
    "sg:province":"Dumfries and Galloway",
    "sg:tags":[
        "importer",
        "merchants",
        "agent",
        "timber"
    ],
    "wof:name":"McConnell Wood Products",
    "wof:placetype":"venue"
},
  "geometry": {"coordinates":[-3.811779,55.232811],"type":"Point"}
}