{
  "type": "Feature",
  "properties": {
    "addr:full":"37 High Street Ipswich Suffolk IP7 5AF",
    "addr:housenumber":"37",
    "addr:postcode":"ip7 5af",
    "addr:street":"High Street",
    "iso:country":"GB",
    "sg:address":"37 High Street",
    "sg:city":"Ipswich",
    "sg:classifiers":[
        {
            "category":"Shopping",
            "subcategory":"Department Store",
            "type":"Retail Goods"
        },
        {
            "category":"Shopping",
            "subcategory":"Crafts & Fabrics",
            "type":"Retail Goods"
        }
    ],
    "sg:phone":"+44 1473 827752",
    "sg:postcode":"IP7 5AF",
    "sg:province":"Suffolk",
    "sg:tags":[
        "material",
        "art"
    ],
    "wof:name":"Bryan Haylock",
    "wof:placetype":"venue"
},
  "geometry": {"coordinates":[0.954326,52.042873],"type":"Point"}
}