{
  "type": "Feature",
  "properties": {
    "addr:full":"1065 Thornton Road Bradford West Yorkshire BD8 0PA",
    "addr:housenumber":"1065",
    "addr:postcode":"bd8 0pa",
    "addr:street":"Thornton Road",
    "iso:country":"GB",
    "sg:address":"1065 Thornton Road",
    "sg:city":"Bradford",
    "sg:classifiers":[
        {
            "category":"Professional",
            "subcategory":"Printing & Photocopies",
            "type":"Services"
        }
    ],
    "sg:phone":"+44 1274 882222",
    "sg:postcode":"BD8 0PA",
    "sg:province":"West Yorkshire",
    "sg:tags":[
        "finishing",
        "tag",
        "computer",
        "label",
        "supply"
    ],
    "wof:name":"GRANGEFIELD PRODUCTS (MAIL ORDER) LTD",
    "wof:placetype":"venue"
},
  "geometry": {"coordinates":[-1.810098052,53.7947692871],"type":"Point"}
}