{
  "type": "Feature",
  "properties": {
    "addr:full":"15 Kinsway Ho, Team Valley Gateshead Tyne and Wear NE11 0HW",
    "addr:housenumber":"15",
    "addr:postcode":"ne11 0hw",
    "addr:street":"Kinsway Ho",
    "iso:country":"GB",
    "sg:address":"15 Kinsway Ho, Team Valley",
    "sg:city":"Gateshead",
    "sg:classifiers":[
        {
            "category":"Real Estate",
            "subcategory":"Architect",
            "type":"Services"
        }
    ],
    "sg:phone":"+44 191 491 0288",
    "sg:postcode":"NE11 0HW",
    "sg:province":"Tyne and Wear",
    "sg:tags":[
        "architectural"
    ],
    "wof:name":"Kingsway Design",
    "wof:placetype":"venue"
},
  "geometry": {"coordinates":[-1.6181299686,54.932220459],"type":"Point"}
}