{
  "type": "Feature",
  "properties": {
    "addr:full":"Farthing Road Indstl Est, Farthing Rd Ipswich Suffolk IP1 5AP",
    "addr:postcode":"ip1 5ap",
    "addr:street":"Farthing Road Indstl Est Farthing Rd",
    "iso:country":"GB",
    "sg:address":"Farthing Road Indstl Est, Farthing Rd",
    "sg:city":"Ipswich",
    "sg:classifiers":[
        {
            "category":"Building & Trades",
            "subcategory":"Construction",
            "type":"Services"
        }
    ],
    "sg:phone":"+44 1473 461461",
    "sg:postcode":"IP1 5AP",
    "sg:province":"Suffolk",
    "sg:tags":[
        "guttering"
    ],
    "wof:name":"Specialised Fixings Ltd",
    "wof:placetype":"venue"
},
  "geometry": {"coordinates":[1.1101150513,52.0657196045],"type":"Point"}
}