{
  "type": "Feature",
  "properties": {
    "iso:country":"GB",
    "sg:address":"36 Penton Av",
    "sg:city":"Staines",
    "sg:classifiers":[
        {
            "category":"Professional",
            "subcategory":"Engineering",
            "type":"Services"
        }
    ],
    "sg:phone":"+44 1784 459943",
    "sg:postcode":"TW18 2ND",
    "sg:province":"Berkshire",
    "sg:tags":[
        "gas",
        "engineer"
    ],
    "wof:name":"K W H Services",
    "wof:placetype":"venue"
},
  "geometry": {"coordinates":[-0.507959,51.419285],"type":"Point"}
}