{
  "type": "Feature",
  "properties": {
    "addr:full":"195 Baslow Road Sheffield Derbyshire S17 4DT",
    "addr:housenumber":"195",
    "addr:postcode":"s17 4dt",
    "addr:street":"Baslow Road",
    "iso:country":"GB",
    "sg:address":"195 Baslow Road",
    "sg:city":"Sheffield",
    "sg:classifiers":[
        {
            "category":"Personal",
            "subcategory":"Beauty Salon",
            "type":"Services"
        },
        {
            "category":"Personal",
            "subcategory":"Barber",
            "type":"Services"
        }
    ],
    "sg:phone":"+44 114 236 6025",
    "sg:postcode":"S17 4DT",
    "sg:province":"Derbyshire",
    "sg:tags":[
        "unisex",
        "hairdresser"
    ],
    "wof:name":"195 Hairline",
    "wof:placetype":"venue"
},
  "geometry": {"coordinates":[-1.5333449841,53.3152427673],"type":"Point"}
}