{
  "type": "Feature",
  "properties": {
    "iso:country":"GB",
    "sg:address":"110 Brook Drive",
    "sg:city":"London",
    "sg:classifiers":[
        {
            "category":"Manufacturing",
            "subcategory":"Building Materials",
            "type":"Manufacturing & Wholesale Goods"
        }
    ],
    "sg:phone":"+44 20 7582 6712",
    "sg:postcode":"SE11 4TQ",
    "sg:province":"Greater London",
    "sg:tags":[
        "mnfr",
        "marble",
        "specialist"
    ],
    "wof:name":"Dorlin Flooring Co",
    "wof:placetype":"venue"
},
  "geometry": {"coordinates":[-0.1066119969,51.4939041138],"type":"Point"}
}