{
  "type": "Feature",
  "properties": {
    "iso:country":"GB",
    "sg:address":"6 St Fagans Drive, St Fagans",
    "sg:city":"Cardiff",
    "sg:classifiers":[
        {
            "category":"Professional",
            "subcategory":"Business Services",
            "type":"Services"
        }
    ],
    "sg:phone":"+44 29 2056 2364",
    "sg:postcode":"CF5 6EF",
    "sg:province":"Cardiff",
    "sg:tags":[
        "food",
        "import",
        "export",
        "agent"
    ],
    "wof:name":"Agri S G J Ltd.",
    "wof:placetype":"venue"
},
  "geometry": {"coordinates":[-3.26839,51.488415],"type":"Point"}
}