{
  "type": "Feature",
  "properties": {
    "addr:full":"Boulton Road Solihull West Midlands B91 2JU",
    "addr:postcode":"b91 2ju",
    "addr:street":"Boulton Road",
    "iso:country":"GB",
    "sg:address":"Boulton Road",
    "sg:city":"Solihull",
    "sg:classifiers":[
        {
            "category":"Retail",
            "subcategory":"Auto Repair",
            "type":"Services"
        }
    ],
    "sg:phone":"+44 121 705 0677",
    "sg:postcode":"B91 2JU",
    "sg:province":"West Midlands",
    "sg:tags":[
        "body",
        "car",
        "repairer"
    ],
    "wof:name":"Bodyworks Solihull",
    "wof:placetype":"venue"
},
  "geometry": {"coordinates":[-1.775639,52.427235],"type":"Point"}
}