{
  "type": "Feature",
  "properties": {
    "iso:country":"GB",
    "sg:address":"62 Hillside Avenue",
    "sg:city":"Canterbury",
    "sg:classifiers":[
        {
            "category":"Retail",
            "subcategory":"Driving School",
            "type":"Services"
        }
    ],
    "sg:phone":"+44 1227 455520",
    "sg:postcode":"CT2 8HA",
    "sg:province":"Kent",
    "wof:name":"City School of Motoring",
    "wof:placetype":"venue"
},
  "geometry": {"coordinates":[1.0573840141,51.2860031128],"type":"Point"}
}