{
  "type": "Feature",
  "properties": {
    "iso:country":"GB",
    "sg:address":"461 Birmingham Road",
    "sg:city":"Redditch",
    "sg:classifiers":[
        {
            "category":"Real Estate",
            "subcategory":"Surveying",
            "type":"Services"
        }
    ],
    "sg:phone":"+44 1527 69699",
    "sg:postcode":"B97 6RL",
    "sg:province":"Warwickshire",
    "sg:tags":[
        "surveyor",
        "valuer"
    ],
    "wof:name":"Peter J Drake",
    "wof:placetype":"venue"
},
  "geometry": {"coordinates":[-1.947911,52.330456],"type":"Point"}
}