{
  "type": "Feature",
  "properties": {
    "addr:full":"Kwik Save Superstore Driffield East Riding of Yorkshire YO25 6PS",
    "addr:postcode":"yo25 6ps",
    "iso:country":"GB",
    "sg:address":"Kwik Save Superstore",
    "sg:city":"Driffield",
    "sg:classifiers":[
        {
            "category":"Food & Beverages",
            "subcategory":"Fruits & Vegetables",
            "type":"Retail Goods"
        }
    ],
    "sg:phone":"+44 1377 257012",
    "sg:postcode":"YO25 6PS",
    "sg:province":"East Riding of Yorkshire",
    "sg:tags":[
        "greengrocer"
    ],
    "wof:name":"Hewitt's Fruiterers",
    "wof:placetype":"venue"
},
  "geometry": {"coordinates":[-0.436299,54.008968],"type":"Point"}
}