{
  "type": "Feature",
  "properties": {
    "addr:full":"251 Oakleigh Rd North Totteridge Greater London N20 0TX",
    "addr:housenumber":"251",
    "addr:postcode":"n20 0tx",
    "addr:street":"Oakleigh Rd",
    "iso:country":"GB",
    "sg:address":"251 Oakleigh Rd North",
    "sg:city":"Totteridge",
    "sg:classifiers":[
        {
            "category":"Shopping",
            "subcategory":"News",
            "type":"Retail Goods"
        },
        {
            "category":"Food & Beverages",
            "subcategory":"Groceries & Convenience Stores",
            "type":"Retail Goods"
        }
    ],
    "sg:phone":"+44 20 8368 7855",
    "sg:postcode":"N20 0TX",
    "sg:province":"Greater London",
    "sg:tags":[
        "newsagent"
    ],
    "wof:name":"Mayo Brooks",
    "wof:placetype":"venue"
},
  "geometry": {"coordinates":[-0.1596529931,51.6259994507],"type":"Point"}
}