{
  "type": "Feature",
  "properties": {
    "iso:country":"GB",
    "sg:address":"North Manchester General Hospital, Delaunays Rd",
    "sg:city":"Manchester",
    "sg:classifiers":[
        {
            "category":"Social Services",
            "subcategory":"Retirement Home",
            "type":"Services"
        }
    ],
    "sg:phone":"+44 161 720 2871",
    "sg:postcode":"M8 5RB",
    "sg:province":"Greater Manchester",
    "sg:tags":[
        "care"
    ],
    "wof:name":"BNA",
    "wof:placetype":"venue"
},
  "geometry": {"coordinates":[-2.2295,53.517872],"type":"Point"}
}