{
  "type": "Feature",
  "properties": {
    "iso:country":"GB",
    "sg:address":"21 Hallot Close",
    "sg:city":"Birmingham",
    "sg:classifiers":[
        {
            "category":"Professional",
            "subcategory":"Lawyer & Legal Services",
            "type":"Services"
        }
    ],
    "sg:phone":"+44 121 384 5017",
    "sg:postcode":"B23 5YW",
    "sg:province":"West Midlands",
    "wof:name":"Wills & Testaments",
    "wof:placetype":"venue"
},
  "geometry": {"coordinates":[-1.853874,52.540222],"type":"Point"}
}