{
  "type": "Feature",
  "properties": {
    "addr:full":"Swaledale House, Little Musgrave Kirkby Stephen Cumbria CA17 4PQ",
    "addr:postcode":"ca17 4pq",
    "addr:street":"Little",
    "iso:country":"GB",
    "sg:address":"Swaledale House, Little Musgrave",
    "sg:city":"Kirkby Stephen",
    "sg:classifiers":[
        {
            "category":"Freight",
            "type":"Transportation"
        }
    ],
    "sg:phone":"+44 17683 41461",
    "sg:postcode":"CA17 4PQ",
    "sg:province":"Cumbria",
    "sg:tags":[
        "haulage",
        "road"
    ],
    "wof:name":"Harker Transport",
    "wof:placetype":"venue"
},
  "geometry": {"coordinates":[-2.348623,54.472717],"type":"Point"}
}