{
  "type": "Feature",
  "properties": {
    "addr:full":"1/3 Hale Lane, Mill Hill London Greater London NW7 3NU",
    "addr:housenumber":"1 / 3",
    "addr:postcode":"nw7 3nu",
    "addr:street":"Hale Lane",
    "iso:country":"GB",
    "sg:address":"1/3 Hale Lane, Mill Hill",
    "sg:city":"London",
    "sg:classifiers":[
        {
            "category":"Autos & Motor Vehicles",
            "subcategory":"Automobile Sales",
            "type":"Retail Goods"
        }
    ],
    "sg:postcode":"NW7 3NU",
    "sg:province":"Greater London",
    "sg:tags":[
        "car"
    ],
    "wof:name":"The Mill Hill Car Co. Ltd.",
    "wof:placetype":"venue"
},
  "geometry": {"coordinates":[-0.2503429949,51.6134490967],"type":"Point"}
}