{
  "type": "Feature",
  "properties": {
    "iso:country":"GB",
    "sg:address":"29 Castle Street",
    "sg:city":"Swansea",
    "sg:classifiers":[
        {
            "category":"Shopping",
            "subcategory":"Bicycles & Sporting Goods",
            "type":"Retail Goods"
        }
    ],
    "sg:phone":"+44 1792 650510",
    "sg:postcode":"SA1 1HY",
    "sg:province":"Neath Port Talbot",
    "sg:tags":[
        "equipment",
        "camping"
    ],
    "wof:name":"Famous Army Stores",
    "wof:placetype":"venue"
},
  "geometry": {"coordinates":[-3.941936,51.621304],"type":"Point"}
}