{
  "type": "Feature",
  "properties": {
    "iso:country":"GB",
    "sg:address":"92 Keptie Street",
    "sg:city":"Arbroath",
    "sg:classifiers":[
        {
            "category":"Professional",
            "subcategory":"Engineering",
            "type":"Services"
        }
    ],
    "sg:phone":"+44 1241 872427",
    "sg:postcode":"DD11 3AY",
    "sg:province":"Angus",
    "sg:tags":[
        "contractor",
        "electrical",
        "engineer"
    ],
    "wof:name":"Albert Nicoll",
    "wof:placetype":"venue"
},
  "geometry": {"coordinates":[-2.5925090313,56.5597114563],"type":"Point"}
}