{
  "type": "Feature",
  "properties": {
    "iso:country":"GB",
    "sg:address":"8 West Bridgend",
    "sg:city":"Dumbarton",
    "sg:classifiers":[
        {
            "category":"Professional",
            "subcategory":"Art Services",
            "type":"Services"
        }
    ],
    "sg:phone":"+44 1389 761618",
    "sg:postcode":"G82 4AB",
    "sg:province":"Argyll and Bute",
    "sg:tags":[
        "framing"
    ],
    "wof:name":"Framework",
    "wof:placetype":"venue"
},
  "geometry": {"coordinates":[-4.5773611069,55.9443626404],"type":"Point"}
}