{
  "type": "Feature",
  "properties": {
    "iso:country":"GB",
    "sg:address":"Appleshaw",
    "sg:city":"Andover",
    "sg:classifiers":[
        {
            "category":"Shopping",
            "subcategory":"Department Store",
            "type":"Retail Goods"
        }
    ],
    "sg:postcode":"SP11 9BN",
    "sg:province":"Hampshire",
    "wof:name":"Appleshaw Post Office & General Store",
    "wof:placetype":"venue"
},
  "geometry": {"coordinates":[-1.56471,51.237621],"type":"Point"}
}