{
  "type": "Feature",
  "properties": {
    "iso:country":"GB",
    "sg:address":"12 Lowmarch Industrial Estate",
    "sg:city":"Daventry",
    "sg:classifiers":[
        {
            "category":"Wholesale",
            "subcategory":"Chemicals & Plastics",
            "type":"Manufacturing & Wholesale Goods"
        }
    ],
    "sg:phone":"+44 1327 310079",
    "sg:postcode":"NN1 4SD",
    "sg:province":"Northamptonshire",
    "sg:tags":[
        "product",
        "allied"
    ],
    "wof:name":"Endeavour Speciality Chemicals Ltd.",
    "wof:placetype":"venue"
},
  "geometry": {"coordinates":[-0.87838,52.25013],"type":"Point"}
}