{
  "type": "Feature",
  "properties": {
    "addr:full":"Po Box 50 Ashford Kent TN26 1ZY",
    "addr:housenumber":"po box 50",
    "addr:postcode":"tn26 1zy",
    "iso:country":"GB",
    "sg:address":"Po Box 50",
    "sg:city":"Ashford",
    "sg:classifiers":[
        {
            "category":"Autos & Motor Vehicles",
            "subcategory":"Auto Supplies",
            "type":"Retail Goods"
        }
    ],
    "sg:phone":"+44 1233 820000",
    "sg:postcode":"TN26 1ZY",
    "sg:province":"Kent",
    "sg:tags":[
        "car",
        "accessory"
    ],
    "wof:name":"Pagoda Operations Ltd.",
    "wof:placetype":"venue"
},
  "geometry": {"coordinates":[0.843387,51.097366],"type":"Point"}
}