{
  "type": "Feature",
  "properties": {
    "addr:full":"Old Mill Farm, Common Road, Waddingham Gainsborough Lincolnshire DN21 4RL",
    "addr:postcode":"dn21 4rl",
    "addr:street":"Common Road",
    "iso:country":"GB",
    "sg:address":"Old Mill Farm, Common Road, Waddingham",
    "sg:city":"Gainsborough",
    "sg:classifiers":[
        {
            "category":"Farming",
            "subcategory":"Farm",
            "type":"Manufacturing & Wholesale Goods"
        }
    ],
    "sg:phone":"+44 1673 818292",
    "sg:postcode":"DN21 4RL",
    "sg:province":"Lincolnshire",
    "sg:tags":[
        "mixed",
        "crop"
    ],
    "wof:name":"R L & R J Sykes",
    "wof:placetype":"venue"
},
  "geometry": {"coordinates":[-0.51924,53.453232],"type":"Point"}
}