{
  "type": "Feature",
  "properties": {
    "addr:full":"Civic Centre, 44 York Street Twickenham Greater London TW1 3BZ",
    "addr:housenumber":"44",
    "addr:postcode":"tw1 3bz",
    "addr:street":"York Street",
    "iso:country":"GB",
    "sg:address":"Civic Centre, 44 York Street",
    "sg:city":"Twickenham",
    "sg:classifiers":[
        {
            "category":"Professional",
            "subcategory":"Computer Services",
            "type":"Services"
        },
        {
            "category":"Government",
            "subcategory":"Office",
            "type":"Public Place"
        }
    ],
    "sg:phone":"+44 20 8891 7272",
    "sg:postcode":"TW1 3BZ",
    "sg:province":"Greater London",
    "sg:tags":[
        "information",
        "local"
    ],
    "wof:name":"Twickenham Information Centre",
    "wof:placetype":"venue"
},
  "geometry": {"coordinates":[-0.3282290101,51.4466362],"type":"Point"}
}