{
  "type": "Feature",
  "properties": {
    "addr:full":"Whitewell Lane Ryton Tyne and Wear NE40 3PG",
    "addr:postcode":"ne40 3pg",
    "addr:street":"Whitewell Lane",
    "iso:country":"GB",
    "sg:address":"Whitewell Lane",
    "sg:city":"Ryton",
    "sg:classifiers":[
        {
            "category":"Professional",
            "subcategory":"Management & Consulting",
            "type":"Services"
        }
    ],
    "sg:postcode":"NE40 3PG",
    "sg:province":"Tyne and Wear",
    "sg:tags":[
        "consultant",
        "business"
    ],
    "wof:name":"Mark Frazer",
    "wof:placetype":"venue"
},
  "geometry": {"coordinates":[-1.7617690563,54.9751930237],"type":"Point"}
}