{
  "type": "Feature",
  "properties": {
    "addr:full":"Hope Carr Industrial Estate, Butts Street Leigh Lancashire WN7 3XA",
    "addr:postcode":"wn7 3xa",
    "addr:street":"Carr Industrial Estate Butts Street Leigh",
    "iso:country":"GB",
    "sg:address":"Hope Carr Industrial Estate, Butts Street",
    "sg:city":"Leigh",
    "sg:classifiers":[
        {
            "category":"Manufacturing",
            "subcategory":"Glass & Minerals",
            "type":"Manufacturing & Wholesale Goods"
        }
    ],
    "sg:phone":"+44 1942 602096",
    "sg:postcode":"WN7 3XA",
    "sg:province":"Lancashire",
    "sg:tags":[
        "product"
    ],
    "wof:name":"Regency Glass",
    "wof:placetype":"venue"
},
  "geometry": {"coordinates":[-2.5425860882,53.4787826538],"type":"Point"}
}