{
  "type": "Feature",
  "properties": {
    "iso:country":"GB",
    "sg:address":"681 Pershore Rd, Sellypark",
    "sg:city":"Birmingham",
    "sg:classifiers":[
        {
            "category":"Professional",
            "subcategory":"Art Services",
            "type":"Services"
        }
    ],
    "sg:postcode":"B29 7NY",
    "sg:province":"West Midlands",
    "sg:tags":[
        "graphic",
        "designer"
    ],
    "wof:name":"Main Street Advertising Ltd",
    "wof:placetype":"venue"
},
  "geometry": {"coordinates":[-1.9149069786,52.4448165894],"type":"Point"}
}