{
  "type": "Feature",
  "properties": {
    "addr:full":"Squire Lodge, Latherford Close, Four Ashes Wolverhampton Staffordshire WV10 7DY",
    "addr:postcode":"ashes;wv10 7dy",
    "addr:street":"Latherford Close",
    "iso:country":"GB",
    "sg:address":"Squire Lodge, Latherford Close, Four Ashes",
    "sg:city":"Wolverhampton",
    "sg:classifiers":[
        {
            "category":"Building & Trades",
            "subcategory":"Construction",
            "type":"Services"
        }
    ],
    "sg:phone":"+44 1902 791929",
    "sg:postcode":"WV10 7DY",
    "sg:province":"Staffordshire",
    "sg:tags":[
        "welder",
        "mechanical"
    ],
    "wof:name":"Clinstown Ltd.",
    "wof:placetype":"venue"
},
  "geometry": {"coordinates":[-2.1226139069,52.6733207703],"type":"Point"}
}