{
  "type": "Feature",
  "properties": {
    "addr:full":"5-7 William Street Windsor Berkshire SL4 1ED",
    "addr:housenumber":"5-7",
    "addr:postcode":"sl4 1ed",
    "addr:street":"William Street",
    "iso:country":"GB",
    "sg:address":"5-7 William Street",
    "sg:city":"Windsor",
    "sg:classifiers":[
        {
            "category":"Banks & Credit Unions",
            "subcategory":"Financial Services",
            "type":"Services"
        }
    ],
    "sg:phone":"+44 1753 230500",
    "sg:postcode":"SL4 1ED",
    "sg:province":"Berkshire",
    "sg:tags":[
        "building",
        "society"
    ],
    "wof:name":"Nationwide Building Society",
    "wof:placetype":"venue"
},
  "geometry": {"coordinates":[-0.610833,51.481022],"type":"Point"}
}