{
  "type": "Feature",
  "properties": {
    "iso:country":"GB",
    "sg:address":"The Railway Station, Leominster",
    "sg:city":"Hereford",
    "sg:classifiers":[
        {
            "category":"Retail",
            "subcategory":"Repair Shop",
            "type":"Services"
        }
    ],
    "sg:phone":"+44 1568 616404",
    "sg:postcode":"HR6 8AR",
    "sg:province":"Herefordshire",
    "sg:tags":[
        "upholstering",
        "upholsterer"
    ],
    "wof:name":"A & P Leach",
    "wof:placetype":"venue"
},
  "geometry": {"coordinates":[-2.743553,52.227077],"type":"Point"}
}