{
  "type": "Feature",
  "properties": {
    "iso:country":"GB",
    "sg:address":"21-23 North Street",
    "sg:city":"Bridgwater",
    "sg:classifiers":[
        {
            "category":"Bars & Pubs",
            "type":"Food & Drink"
        }
    ],
    "sg:phone":"+44 1278 433053",
    "sg:postcode":"TA6 3PW",
    "sg:province":"Somerset",
    "sg:tags":[
        "pubs",
        "inn"
    ],
    "wof:name":"Annie's Bar",
    "wof:placetype":"venue"
},
  "geometry": {"coordinates":[-3.010438,51.127789],"type":"Point"}
}