{
  "type": "Feature",
  "properties": {
    "addr:full":"1 Plymouth Road Buckfastleigh Devon TQ11 0DA",
    "addr:housenumber":"1",
    "addr:postcode":"tq11 0da",
    "addr:street":"Plymouth Road",
    "iso:country":"GB",
    "sg:address":"1 Plymouth Road",
    "sg:city":"Buckfastleigh",
    "sg:classifiers":[
        {
            "category":"Food & Beverages",
            "subcategory":"Meat & Fish",
            "type":"Retail Goods"
        }
    ],
    "sg:phone":"+44 1364 642390",
    "sg:postcode":"TQ11 0DA",
    "sg:province":"Devon",
    "sg:tags":[
        "chip"
    ],
    "wof:name":"The Fish Bar",
    "wof:placetype":"venue"
},
  "geometry": {"coordinates":[-3.7782070637,50.481136322],"type":"Point"}
}