{
  "type": "Feature",
  "properties": {
    "iso:country":"GB",
    "sg:address":"5 Coborn Rd",
    "sg:city":"Bow",
    "sg:classifiers":[
        {
            "category":"Personal",
            "type":"Services"
        },
        {
            "category":"Professional",
            "subcategory":"Lawyer & Legal Services",
            "type":"Services"
        }
    ],
    "sg:phone":"+44 20 8981 8421",
    "sg:postcode":"E3 2DA",
    "sg:province":"Greater London",
    "sg:tags":[
        "advice",
        "counselling"
    ],
    "wof:name":"Tower Hamlet Victim Support Scheme",
    "wof:placetype":"venue"
},
  "geometry": {"coordinates":[-0.0292140003,51.5268859863],"type":"Point"}
}