{
  "type": "Feature",
  "properties": {
    "addr:full":"2 Mandeville Road London Greater London N14 7NH",
    "addr:housenumber":"2",
    "addr:postcode":"n14 7nh",
    "addr:street":"Mandeville Road",
    "iso:country":"GB",
    "sg:address":"2 Mandeville Road",
    "sg:city":"London",
    "sg:classifiers":[
        {
            "category":"Education",
            "subcategory":"Music School",
            "type":"Public Place"
        },
        {
            "category":"Education",
            "subcategory":"School",
            "type":"Public Place"
        }
    ],
    "sg:phone":"+44 20 8361 8999",
    "sg:postcode":"N14 7NH",
    "sg:province":"Greater London",
    "sg:tags":[
        "drama"
    ],
    "wof:name":"Stagecoach Theatre Arts plc",
    "wof:placetype":"venue"
},
  "geometry": {"coordinates":[-0.137527,51.627441],"type":"Point"}
}