{
  "type": "Feature",
  "properties": {
    "iso:country":"GB",
    "sg:address":"163a Pier Approach Rd",
    "sg:city":"Gillingham",
    "sg:classifiers":[
        {
            "category":"Wholesale",
            "subcategory":"Scrap",
            "type":"Manufacturing & Wholesale Goods"
        }
    ],
    "sg:phone":"+44 1634 281682",
    "sg:postcode":"ME7 1RS",
    "sg:province":"Kent",
    "sg:tags":[
        "breaker",
        "dismantlers"
    ],
    "wof:name":"Off The Shelf",
    "wof:placetype":"venue"
},
  "geometry": {"coordinates":[0.5533149838,51.3967819214],"type":"Point"}
}