{
  "type": "Feature",
  "properties": {
    "addr:full":"370 Court Oak Road Birmingham West Midlands B32 2DY",
    "addr:housenumber":"370",
    "addr:postcode":"b32 2dy",
    "addr:street":"Court Oak Road",
    "iso:country":"GB",
    "sg:address":"370 Court Oak Road",
    "sg:city":"Birmingham",
    "sg:classifiers":[
        {
            "category":"Autos & Motor Vehicles",
            "subcategory":"Automobile Sales",
            "type":"Retail Goods"
        }
    ],
    "sg:postcode":"B32 2DY",
    "sg:province":"West Midlands",
    "sg:tags":[
        "car"
    ],
    "wof:name":"Maxitron Ltd",
    "wof:placetype":"venue"
},
  "geometry": {"coordinates":[-1.9816440344,52.4604759216],"type":"Point"}
}