{
  "type": "Feature",
  "properties": {
    "addr:full":"24 Fentum Road Guildford Surrey GU2 9SA",
    "addr:housenumber":"24",
    "addr:postcode":"gu2 9sa",
    "addr:street":"Fentum Road",
    "iso:country":"GB",
    "sg:address":"24 Fentum Road",
    "sg:city":"Guildford",
    "sg:classifiers":[
        {
            "category":"Professional",
            "subcategory":"Computer Services",
            "type":"Services"
        }
    ],
    "sg:postcode":"GU2 9SA",
    "sg:province":"Surrey",
    "sg:tags":[
        "system",
        "software"
    ],
    "wof:name":"Mark Lamport",
    "wof:placetype":"venue"
},
  "geometry": {"coordinates":[-0.594623,51.252754],"type":"Point"}
}