{
  "type": "Feature",
  "properties": {
    "addr:full":"1 Castle Way Stockton-on-tees Durham TS18 1AL",
    "addr:housenumber":"1",
    "addr:postcode":"ts18 1al",
    "addr:street":"Castle Way",
    "iso:country":"GB",
    "sg:address":"1 Castle Way",
    "sg:city":"Stockton-on-tees",
    "sg:classifiers":[
        {
            "category":"Cafe",
            "type":"Food & Drink"
        }
    ],
    "sg:phone":"+44 1642 633710",
    "sg:postcode":"TS18 1AL",
    "sg:province":"Durham",
    "sg:tags":[
        "tea",
        "snack",
        "bar",
        "room"
    ],
    "wof:name":"The Galley",
    "wof:placetype":"venue"
},
  "geometry": {"coordinates":[-1.3479549885,54.5706253052],"type":"Point"}
}