{
  "type": "Feature",
  "properties": {
    "addr:full":"Staddleside Farm, Thorndon Cross Okehampton Devon EX20 4NG",
    "addr:housenumber":"thorndon",
    "addr:postcode":"ex20 4ng",
    "addr:street":"Cross Okehampton",
    "iso:country":"GB",
    "sg:address":"Staddleside Farm, Thorndon Cross",
    "sg:city":"Okehampton",
    "sg:classifiers":[
        {
            "category":"Utilities",
            "subcategory":"Fuel Oil & Lpg",
            "type":"Services"
        }
    ],
    "sg:phone":"+44 1837 861362",
    "sg:postcode":"EX20 4NG",
    "sg:province":"Devon",
    "wof:name":"P Ferguson",
    "wof:placetype":"venue"
},
  "geometry": {"coordinates":[-4.0817642212,50.7269363403],"type":"Point"}
}