{
  "type": "Feature",
  "properties": {
    "addr:full":"21 Copthall Avenue London Greater London EC2R 7BP",
    "addr:housenumber":"21",
    "addr:postcode":"ec2r 7bp",
    "addr:street":"Copthall Avenue",
    "iso:country":"GB",
    "sg:address":"21 Copthall Avenue",
    "sg:city":"London",
    "sg:classifiers":[
        {
            "category":"Food & Beverages",
            "subcategory":"Candy",
            "type":"Retail Goods"
        }
    ],
    "sg:phone":"+44 20 7588 7000",
    "sg:postcode":"EC2R 7BP",
    "sg:province":"Greater London",
    "sg:tags":[
        "confectioner"
    ],
    "wof:name":"Leonidas Belgian Fine Chocolates",
    "wof:placetype":"venue"
},
  "geometry": {"coordinates":[-0.087889,51.516823],"type":"Point"}
}