{
  "type": "Feature",
  "properties": {
    "addr:full":", Greenhaugh Hexham Northumberland NE48 1PW",
    "addr:postcode":"ne48 1pw",
    "addr:street":"Greenhaugh",
    "iso:country":"GB",
    "sg:address":", Greenhaugh",
    "sg:city":"Hexham",
    "sg:classifiers":[
        {
            "category":"Bars & Pubs",
            "type":"Food & Drink"
        },
        {
            "category":"Community Center",
            "subcategory":"Social",
            "type":"Public Place"
        }
    ],
    "sg:phone":"+44 1434 240391",
    "sg:postcode":"NE48 1PW",
    "sg:province":"Northumberland",
    "sg:tags":[
        "pubs",
        "house",
        "inn",
        "activity"
    ],
    "wof:name":"Holly Bush Inn",
    "wof:placetype":"venue"
},
  "geometry": {"coordinates":[-2.32167,55.178329],"type":"Point"}
}