{
  "type": "Feature",
  "properties": {
    "iso:country":"GB",
    "sg:address":"Upper Court Road, Woldingham",
    "sg:city":"Caterham",
    "sg:classifiers":[
        {
            "category":"Organizations",
            "subcategory":"Membership Organization",
            "type":"Services"
        }
    ],
    "sg:phone":"+44 1883 653330",
    "sg:postcode":"CR3 7BE",
    "sg:province":"Surrey",
    "sg:tags":[
        "club"
    ],
    "wof:name":"Woldingham Village Club",
    "wof:placetype":"venue"
},
  "geometry": {"coordinates":[-0.0351339988,51.2834205627],"type":"Point"}
}