{
  "type": "Feature",
  "properties": {
    "addr:full":"Shop Unit 2 West Street, Gorseinon Swansea Carmarthenshire SA4 4AA",
    "addr:housenumber":"unit 2",
    "addr:postcode":"sa4 4aa",
    "addr:street":"West Street",
    "iso:country":"GB",
    "sg:address":"Shop Unit 2 West Street, Gorseinon",
    "sg:city":"Swansea",
    "sg:classifiers":[
        {
            "category":"Personal",
            "subcategory":"Beauty Salon",
            "type":"Services"
        }
    ],
    "sg:phone":"+44 1792 897172",
    "sg:postcode":"SA4 4AA",
    "sg:province":"Carmarthenshire",
    "sg:tags":[
        "unisex",
        "hairdresser"
    ],
    "wof:name":"Salon One",
    "wof:placetype":"venue"
},
  "geometry": {"coordinates":[-4.0412192345,51.6666755676],"type":"Point"}
}