{
  "type": "Feature",
  "properties": {
    "addr:full":"Mapledurham, Kewferry Drive Northwood Greater London HA6 2NU",
    "addr:postcode":"ha6 2nu",
    "addr:street":"Kewferry Drive",
    "iso:country":"GB",
    "sg:address":"Mapledurham, Kewferry Drive",
    "sg:city":"Northwood",
    "sg:classifiers":[
        {
            "category":"Organizations",
            "subcategory":"Membership Organization",
            "type":"Services"
        }
    ],
    "sg:postcode":"HA6 2NU",
    "sg:province":"Greater London",
    "sg:tags":[
        "club"
    ],
    "wof:name":"Kewferry Drive Residents' Co  Ltd",
    "wof:placetype":"venue"
},
  "geometry": {"coordinates":[-0.4241859913,51.611541748],"type":"Point"}
}