{
  "type": "Feature",
  "properties": {
    "addr:full":"Pear Tree Cottage, Selsley East Stroud Gloucestershire GL5 5LL",
    "addr:postcode":"gl5 5ll",
    "addr:street":"Selsley East",
    "iso:country":"GB",
    "sg:address":"Pear Tree Cottage, Selsley East",
    "sg:city":"Stroud",
    "sg:classifiers":[
        {
            "category":"Professional",
            "subcategory":"Management & Consulting",
            "type":"Services"
        }
    ],
    "sg:phone":"+44 1453 873216",
    "sg:postcode":"GL5 5LL",
    "sg:province":"Gloucestershire",
    "sg:tags":[
        "consultant",
        "business"
    ],
    "wof:name":"Darke-Taylor Wellsite Consultants Ltd.",
    "wof:placetype":"venue"
},
  "geometry": {"coordinates":[-2.24062,51.734344],"type":"Point"}
}