{
  "type": "Feature",
  "properties": {
    "addr:full":"6 Maria Street Kirkcaldy Fife KY1 1BP",
    "addr:housenumber":"6",
    "addr:postcode":"ky1 1bp",
    "addr:street":"Maria Street",
    "iso:country":"GB",
    "sg:address":"6 Maria Street",
    "sg:city":"Kirkcaldy",
    "sg:classifiers":[
        {
            "category":"Manufacturing",
            "subcategory":"Wood Products",
            "type":"Manufacturing & Wholesale Goods"
        },
        {
            "category":"Wholesale",
            "subcategory":"Furniture",
            "type":"Manufacturing & Wholesale Goods"
        }
    ],
    "sg:phone":"+44 1592 263728",
    "sg:postcode":"KY1 1BP",
    "sg:province":"Fife",
    "sg:tags":[
        "shop",
        "fitting",
        "maker",
        "cabinet"
    ],
    "wof:name":"JAMES GREIG",
    "wof:placetype":"venue"
},
  "geometry": {"coordinates":[-3.1569368839,56.1177558899],"type":"Point"}
}