{
  "type": "Feature",
  "properties": {
    "addr:full":"4th Floor 66/68 Margaret Street London Greater London W1W 8SR",
    "addr:housenumber":"4th floor 66 / 68",
    "addr:postcode":"w1w 8sr",
    "addr:street":"Margaret Street",
    "iso:country":"GB",
    "sg:address":"4th Floor 66/68 Margaret Street",
    "sg:city":"London",
    "sg:classifiers":[
        {
            "category":"Communications",
            "subcategory":"Film & Video Production",
            "type":"Services"
        }
    ],
    "sg:phone":"+44 20 7580 6799",
    "sg:postcode":"W1W 8SR",
    "sg:province":"Greater London",
    "sg:tags":[
        "tv",
        "studio"
    ],
    "wof:name":"National Film Trustee Co. Ltd.",
    "wof:placetype":"venue"
},
  "geometry": {"coordinates":[-0.1400700063,51.5167312622],"type":"Point"}
}