{
  "type": "Feature",
  "properties": {
    "addr:full":"57 North Bar Within Beverley East Riding of Yorkshire HU17 8DG",
    "addr:housenumber":"57",
    "addr:postcode":"hu17 8dg",
    "addr:street":"North Bar",
    "iso:country":"GB",
    "sg:address":"57 North Bar Within",
    "sg:city":"Beverley",
    "sg:classifiers":[
        {
            "category":"Health Services",
            "subcategory":"Podiatrist",
            "type":"Services"
        }
    ],
    "sg:postcode":"HU17 8DG",
    "sg:province":"East Riding of Yorkshire",
    "sg:tags":[
        "podiatrists",
        "chiropodist"
    ],
    "wof:name":"Margaret Tindale",
    "wof:placetype":"venue"
},
  "geometry": {"coordinates":[-0.4357089996,53.8446960449],"type":"Point"}
}