{
  "type": "Feature",
  "properties": {
    "iso:country":"GB",
    "sg:address":"299a Whitley Road",
    "sg:city":"Whitley Bay",
    "sg:classifiers":[
        {
            "category":"Professional",
            "subcategory":"Accounting & Tax Preparation",
            "type":"Services"
        }
    ],
    "sg:phone":"+44 191 251 0008",
    "sg:postcode":"NE26 2SN",
    "sg:province":"Northumberland",
    "sg:tags":[
        "accountant"
    ],
    "wof:name":"Tindle & Co",
    "wof:placetype":"venue"
},
  "geometry": {"coordinates":[-1.446356,55.042072],"type":"Point"}
}