{
  "type": "Feature",
  "properties": {
    "addr:full":"378 Great Northern Road Aberdeen Aberdeen City AB24 2AX",
    "addr:housenumber":"378",
    "addr:postcode":"ab24 2ax",
    "addr:street":"Great Northern Road",
    "iso:country":"GB",
    "sg:address":"378 Great Northern Road",
    "sg:city":"Aberdeen",
    "sg:classifiers":[
        {
            "category":"Shopping",
            "subcategory":"Stationery & Office Supplies",
            "type":"Retail Goods"
        }
    ],
    "sg:postcode":"AB24 2AX",
    "sg:province":"Aberdeen City",
    "sg:tags":[
        "equipment"
    ],
    "wof:name":"Murray Park",
    "wof:placetype":"venue"
},
  "geometry": {"coordinates":[-2.1232340336,57.1701927185],"type":"Point"}
}