{
  "type": "Feature",
  "properties": {
    "addr:full":"4 Winsover Road Spalding Lincolnshire PE11 1EH",
    "addr:housenumber":"4",
    "addr:postcode":"pe11 1eh",
    "addr:street":"Winsover Road",
    "iso:country":"GB",
    "sg:address":"4 Winsover Road",
    "sg:city":"Spalding",
    "sg:classifiers":[
        {
            "category":"Bars & Pubs",
            "type":"Food & Drink"
        },
        {
            "category":"Community Center",
            "subcategory":"Social",
            "type":"Public Place"
        }
    ],
    "sg:phone":"+44 1775 723193",
    "sg:postcode":"PE11 1EH",
    "sg:province":"Lincolnshire",
    "sg:tags":[
        "pubs",
        "house",
        "inn",
        "activity"
    ],
    "wof:name":"The Station Gates",
    "wof:placetype":"venue"
},
  "geometry": {"coordinates":[-0.1580290049,52.7867393494],"type":"Point"}
}