{
  "type": "Feature",
  "properties": {
    "addr:full":"83 Pentland View Edinburgh City of Edinburgh EH10 6PT",
    "addr:housenumber":"83",
    "addr:postcode":"eh10 6pt",
    "addr:street":"Pentland View Edinburgh",
    "iso:country":"GB",
    "sg:address":"83 Pentland View",
    "sg:city":"Edinburgh",
    "sg:classifiers":[
        {
            "category":"Social Services",
            "subcategory":"Child Care",
            "type":"Services"
        }
    ],
    "sg:phone":"+44 131 445 4024",
    "sg:postcode":"EH10 6PT",
    "sg:province":"City of Edinburgh",
    "sg:tags":[
        "children's",
        "home"
    ],
    "wof:name":"Pentland View Close Support Unit",
    "wof:placetype":"venue"
},
  "geometry": {"coordinates":[-3.2162120342,55.9078330994],"type":"Point"}
}