{
  "type": "Feature",
  "properties": {
    "addr:full":"142 Weyhill Road Andover Hampshire SP10 3BG",
    "addr:housenumber":"142",
    "addr:postcode":"sp10 3bg",
    "addr:street":"Weyhill Road",
    "iso:country":"GB",
    "sg:address":"142 Weyhill Road",
    "sg:city":"Andover",
    "sg:classifiers":[
        {
            "category":"Retail",
            "subcategory":"Repair Shop",
            "type":"Services"
        }
    ],
    "sg:phone":"+44 1264 336772",
    "sg:postcode":"SP10 3BG",
    "sg:province":"Hampshire",
    "sg:tags":[
        "maintenance"
    ],
    "wof:name":"Tricorn Europe",
    "wof:placetype":"venue"
},
  "geometry": {"coordinates":[-1.504513979,51.2088928223],"type":"Point"}
}