{
  "type": "Feature",
  "properties": {
    "addr:full":"48-52 Nottingham Road, Ripley Derby Derbyshire DE5 3AT",
    "addr:housenumber":"48-52",
    "addr:postcode":"de5 3at",
    "addr:street":"Nottingham Road",
    "iso:country":"GB",
    "sg:address":"48-52 Nottingham Road, Ripley",
    "sg:city":"Derby",
    "sg:classifiers":[
        {
            "category":"Manufacturing",
            "subcategory":"Building Materials",
            "type":"Manufacturing & Wholesale Goods"
        }
    ],
    "sg:phone":"+44 1773 742351",
    "sg:postcode":"DE5 3AT",
    "sg:province":"Derbyshire",
    "sg:tags":[
        "merchant",
        "builder"
    ],
    "wof:name":"Clower & Son (Builders Merchants) Ltd.",
    "wof:placetype":"venue"
},
  "geometry": {"coordinates":[-1.4020580053,53.050327301],"type":"Point"}
}