{
  "type": "Feature",
  "properties": {
    "iso:country":"GB",
    "sg:address":"70 Oxford Street",
    "sg:city":"London",
    "sg:classifiers":[
        {
            "category":"Professional",
            "subcategory":"Computer Services",
            "type":"Services"
        }
    ],
    "sg:phone":"+44 20 7580 7888",
    "sg:postcode":"W1D 1BS",
    "sg:province":"Greater London",
    "sg:tags":[
        "system",
        "software"
    ],
    "wof:name":"Procom Electronic",
    "wof:placetype":"venue"
},
  "geometry": {"coordinates":[-0.134222,51.516136],"type":"Point"}
}