{
  "type": "Feature",
  "properties": {
    "addr:full":"11 Unicorn Park, Unicorn Park Avenue, Brislington Bristol City of Bristol BS4 4EX",
    "addr:housenumber":"11",
    "addr:postcode":"bs4 4ex",
    "addr:street":"Unicorn Park Unicorn Park Avenue",
    "iso:country":"GB",
    "sg:address":"11 Unicorn Park, Unicorn Park Avenue, Brislington",
    "sg:city":"Bristol",
    "sg:classifiers":[
        {
            "category":"Wholesale",
            "subcategory":"Books, Periodicals, & Newspapers",
            "type":"Manufacturing & Wholesale Goods"
        }
    ],
    "sg:phone":"+44 117 977 0070",
    "sg:postcode":"BS4 4EX",
    "sg:province":"City of Bristol",
    "sg:tags":[
        "newsagent"
    ],
    "wof:name":"Surridge Dawson Brislington",
    "wof:placetype":"venue"
},
  "geometry": {"coordinates":[-2.55474,51.449478],"type":"Point"}
}