{
  "type": "Feature",
  "properties": {
    "iso:country":"GB",
    "sg:address":"17 Rise Road",
    "sg:city":"Ascot",
    "sg:classifiers":[
        {
            "category":"Professional",
            "subcategory":"Employment Agencies",
            "type":"Services"
        }
    ],
    "sg:postcode":"SL5 0BH",
    "sg:province":"Berkshire",
    "sg:tags":[
        "consultant"
    ],
    "wof:name":"Profile Search & Selection",
    "wof:placetype":"venue"
},
  "geometry": {"coordinates":[-0.640383,51.396488],"type":"Point"}
}