{
  "type": "Feature",
  "properties": {
    "addr:full":"16 Birch Road, Kippax Leeds North Yorkshire LS25 7DY",
    "addr:housenumber":"16",
    "addr:postcode":"ls25 7dy",
    "addr:street":"Birch Road",
    "iso:country":"GB",
    "sg:address":"16 Birch Road, Kippax",
    "sg:city":"Leeds",
    "sg:classifiers":[
        {
            "category":"Building & Trades",
            "subcategory":"Construction",
            "type":"Services"
        }
    ],
    "sg:postcode":"LS25 7DY",
    "sg:province":"North Yorkshire",
    "sg:tags":[
        "decorator",
        "painter"
    ],
    "wof:name":"Wills & Reed",
    "wof:placetype":"venue"
},
  "geometry": {"coordinates":[-1.3767650127,53.7747077942],"type":"Point"}
}