{
  "type": "Feature",
  "properties": {
    "addr:full":"64 Victoria St Glasgow South Lanarkshire G72 0BS",
    "addr:housenumber":"64",
    "addr:postcode":"g72 0bs",
    "addr:street":"Victoria St",
    "iso:country":"GB",
    "sg:address":"64 Victoria St",
    "sg:city":"Glasgow",
    "sg:classifiers":[
        {
            "category":"Health Services",
            "subcategory":"Doctor",
            "type":"Services"
        }
    ],
    "sg:phone":"+44 1698 823260",
    "sg:postcode":"G72 0BS",
    "sg:province":"South Lanarkshire",
    "sg:tags":[
        "practitioners"
    ],
    "wof:name":"Suckle, N E",
    "wof:placetype":"venue"
},
  "geometry": {"coordinates":[-4.091791,55.791458],"type":"Point"}
}