{
  "type": "Feature",
  "properties": {
    "addr:full":"6 Sunny Gardens Parade London Greater London NW4 1JA",
    "addr:housenumber":"6",
    "addr:postcode":"nw4 1ja",
    "addr:street":"Sunny Gardens Parade",
    "iso:country":"GB",
    "sg:address":"6 Sunny Gardens Parade",
    "sg:city":"London",
    "sg:classifiers":[
        {
            "category":"Personal",
            "subcategory":"Beauty Salon",
            "type":"Services"
        }
    ],
    "sg:postcode":"NW4 1JA",
    "sg:province":"Greater London",
    "sg:tags":[
        "unisex",
        "hairdresser"
    ],
    "wof:name":"Beba's Hair Fashions",
    "wof:placetype":"venue"
},
  "geometry": {"coordinates":[-0.2257840037,51.5986862183],"type":"Point"}
}