{
  "type": "Feature",
  "properties": {
    "addr:full":"320 Firecrest Court, Centre Park Warrington Cheshire WA1 1RG",
    "addr:housenumber":"320",
    "addr:postcode":"wa1 1rg",
    "addr:street":"Firecrest Court Centre Park",
    "iso:country":"GB",
    "sg:address":"320 Firecrest Court, Centre Park",
    "sg:city":"Warrington",
    "sg:classifiers":[
        {
            "category":"Shopping",
            "subcategory":"Clothing, Apparel, & Fashions",
            "type":"Retail Goods"
        },
        {
            "category":"Manufacturing",
            "subcategory":"Apparel",
            "type":"Manufacturing & Wholesale Goods"
        }
    ],
    "sg:phone":"+44 1925 821182",
    "sg:postcode":"WA1 1RG",
    "sg:province":"Cheshire",
    "sg:tags":[
        "mnfr",
        "footwear",
        "sportswear"
    ],
    "wof:name":"New Balance Athletic Shoes (U K) Ltd.",
    "wof:placetype":"venue"
},
  "geometry": {"coordinates":[-2.5968101025,53.3811416626],"type":"Point"}
}