{
  "type": "Feature",
  "properties": {
    "addr:full":"Cobbs Wood Industrial Estate, Hanover Close Ashford Kent TN23 1EJ",
    "addr:housenumber":"estate",
    "addr:postcode":"tn23 1ej",
    "addr:street":"Cobbs Wood Industrial;Hanover Close",
    "iso:country":"GB",
    "sg:address":"Cobbs Wood Industrial Estate, Hanover Close",
    "sg:city":"Ashford",
    "sg:classifiers":[
        {
            "category":"Real Estate",
            "subcategory":"Surveying",
            "type":"Services"
        }
    ],
    "sg:phone":"+44 1233 658270",
    "sg:postcode":"TN23 1EJ",
    "sg:province":"Kent",
    "sg:tags":[
        "surveyor",
        "land",
        "activity"
    ],
    "sg:website":"http://www.groundsolutions.co.uk",
    "wof:name":"Ground Solutions Group Ltd",
    "wof:placetype":"venue"
},
  "geometry": {"coordinates":[0.8760370016,51.1466331482],"type":"Point"}
}