{
  "type": "Feature",
  "properties": {
    "addr:full":"Station Road Westbury Wiltshire BA13 4TW",
    "addr:postcode":"ba13 4tw",
    "addr:street":"Station Road",
    "iso:country":"GB",
    "sg:address":"Station Road",
    "sg:city":"Westbury",
    "sg:classifiers":[
        {
            "category":"Building & Trades",
            "subcategory":"Construction",
            "type":"Services"
        }
    ],
    "sg:phone":"+44 1373 823814",
    "sg:postcode":"BA13 4TW",
    "sg:province":"Wiltshire",
    "sg:tags":[
        "contractor"
    ],
    "wof:name":"Alhco Ltd.",
    "wof:placetype":"venue"
},
  "geometry": {"coordinates":[-2.195949,51.266579],"type":"Point"}
}