{
  "type": "Feature",
  "properties": {
    "addr:full":"Cross Wynd, Falkland Cupar Fife KY15 7BE",
    "addr:postcode":"ky15 7be",
    "addr:street":"Cross Wynd Falkland Cupar",
    "iso:country":"GB",
    "sg:address":"Cross Wynd, Falkland",
    "sg:city":"Cupar",
    "sg:classifiers":[
        {
            "category":"Cafe",
            "type":"Food & Drink"
        }
    ],
    "sg:phone":"+44 1337 857477",
    "sg:postcode":"KY15 7BE",
    "sg:province":"Fife",
    "sg:tags":[
        "tea",
        "snack",
        "bar",
        "room"
    ],
    "wof:name":"Kind Kyttock's Kitchen",
    "wof:placetype":"venue"
},
  "geometry": {"coordinates":[-3.2017700672,56.2522850037],"type":"Point"}
}