{
  "type": "Feature",
  "properties": {
    "addr:full":"84b Darlington Street Wolverhampton West Midlands WV1 4EX",
    "addr:housenumber":"84b",
    "addr:postcode":"wv1 4ex",
    "addr:street":"Darlington Street",
    "iso:country":"GB",
    "sg:address":"84b Darlington Street",
    "sg:city":"Wolverhampton",
    "sg:classifiers":[
        {
            "category":"Personal",
            "subcategory":"Beauty Salon",
            "type":"Services"
        }
    ],
    "sg:phone":"+44 1902 422746",
    "sg:postcode":"WV1 4EX",
    "sg:province":"West Midlands",
    "sg:tags":[
        "unisex",
        "hairdresser"
    ],
    "wof:name":"Zaks Hair Design",
    "wof:placetype":"venue"
},
  "geometry": {"coordinates":[-2.1311640739,52.5854797363],"type":"Point"}
}