{
  "type": "Feature",
  "properties": {
    "addr:full":"27 Longridge Rd Bathgate North Lanarkshire EH47 8HB",
    "addr:housenumber":"27",
    "addr:postcode":"eh47 8hb",
    "addr:street":"Longridge Rd Bathgate",
    "iso:country":"GB",
    "sg:address":"27 Longridge Rd",
    "sg:city":"Bathgate",
    "sg:classifiers":[
        {
            "category":"Manufacturing",
            "subcategory":"Wood Products",
            "type":"Manufacturing & Wholesale Goods"
        }
    ],
    "sg:phone":"+44 1501 741697",
    "sg:postcode":"EH47 8HB",
    "sg:province":"North Lanarkshire",
    "sg:tags":[
        "packaging",
        "crate",
        "pallets"
    ],
    "wof:name":"Vaspac",
    "wof:placetype":"venue"
},
  "geometry": {"coordinates":[-3.6891260147,55.8609466553],"type":"Point"}
}