{
  "type": "Feature",
  "properties": {
    "addr:full":"New Street Horsham West Sussex RH13 5EL",
    "addr:postcode":"rh13 5el",
    "addr:street":"New Street",
    "iso:country":"GB",
    "sg:address":"New Street",
    "sg:city":"Horsham",
    "sg:classifiers":[
        {
            "category":"Organizations",
            "subcategory":"Non-profit Organization",
            "type":"Services"
        }
    ],
    "sg:phone":"+44 1403 260560",
    "sg:postcode":"RH13 5EL",
    "sg:province":"West Sussex",
    "sg:tags":[
        "organisation",
        "voluntary",
        "charity"
    ],
    "wof:name":"Horsham District Age Concern",
    "wof:placetype":"venue"
},
  "geometry": {"coordinates":[-0.3178290129,51.0641937256],"type":"Point"}
}