{
  "type": "Feature",
  "properties": {
    "addr:full":"Northfield Hotel, Northfield Road Minehead Somerset TA24 5PU",
    "addr:postcode":"ta24 5pu",
    "addr:street":"Northfield Road",
    "iso:country":"GB",
    "sg:address":"Northfield Hotel, Northfield Road",
    "sg:city":"Minehead",
    "sg:classifiers":[
        {
            "category":"Travel",
            "subcategory":"Hotels & Motels",
            "type":"Entertainment"
        }
    ],
    "sg:phone":"+44 1643 705155",
    "sg:postcode":"TA24 5PU",
    "sg:province":"Somerset",
    "wof:name":"The Mariners Hotel Ltd.",
    "wof:placetype":"venue"
},
  "geometry": {"coordinates":[-3.479969,51.205406],"type":"Point"}
}