{
  "type": "Feature",
  "properties": {
    "addr:full":"22 Blackmore Letchworth Hertfordshire SG6 2SY",
    "addr:housenumber":"22",
    "addr:postcode":"sg6 2sy",
    "addr:street":"Blackmore Letchworth",
    "iso:country":"GB",
    "sg:address":"22 Blackmore",
    "sg:city":"Letchworth",
    "sg:classifiers":[
        {
            "category":"Professional",
            "subcategory":"Engineering",
            "type":"Services"
        }
    ],
    "sg:postcode":"SG6 2SY",
    "sg:province":"Hertfordshire",
    "sg:tags":[
        "contractor",
        "electrical",
        "engineer"
    ],
    "wof:name":"J P Wilson Engineer",
    "wof:placetype":"venue"
},
  "geometry": {"coordinates":[-0.212292,51.96701],"type":"Point"}
}