{
  "type": "Feature",
  "properties": {
    "addr:full":"Unit 14, Greenway Workshops, Bedwas Caerphilly Caerphilly CF83 8DW",
    "addr:housenumber":"unit 14",
    "addr:postcode":"cf83 8dw",
    "addr:street":"Greenway Workshops",
    "iso:country":"GB",
    "sg:address":"Unit 14, Greenway Workshops, Bedwas",
    "sg:city":"Caerphilly",
    "sg:classifiers":[
        {
            "category":"Government",
            "subcategory":"Fire Station",
            "type":"Public Place"
        }
    ],
    "sg:phone":"+44 29 2088 5569",
    "sg:postcode":"CF83 8DW",
    "sg:province":"Caerphilly",
    "sg:tags":[
        "security"
    ],
    "wof:name":"Sentinel Sprinklers Ltd",
    "wof:placetype":"venue"
},
  "geometry": {"coordinates":[-3.2102689743,51.59349823],"type":"Point"}
}