{
  "type": "Feature",
  "properties": {
    "iso:country":"GB",
    "sg:address":"131 Badgeney Road",
    "sg:city":"March",
    "sg:classifiers":[
        {
            "category":"Social Services",
            "subcategory":"Retirement Home",
            "type":"Services"
        }
    ],
    "sg:phone":"+44 1354 654016",
    "sg:postcode":"PE15 9AU",
    "sg:province":"Cambridgeshire",
    "sg:tags":[
        "residential",
        "care"
    ],
    "wof:name":"Fern Trees Residential Home",
    "wof:placetype":"venue"
},
  "geometry": {"coordinates":[0.099448,52.550724],"type":"Point"}
}