{
  "type": "Feature",
  "properties": {
    "addr:full":"Minehead Delivery Office, Post Office Lane Minehead Somerset TA24 5AA",
    "addr:postcode":"ta24 5aa",
    "addr:street":"Office Lane",
    "iso:country":"GB",
    "sg:address":"Minehead Delivery Office, Post Office Lane",
    "sg:city":"Minehead",
    "sg:classifiers":[
        {
            "category":"Freight",
            "type":"Transportation"
        }
    ],
    "sg:phone":"+44 1643 703211",
    "sg:postcode":"TA24 5AA",
    "sg:province":"Somerset",
    "sg:tags":[
        "haulage",
        "road"
    ],
    "wof:name":"The Post Office",
    "wof:placetype":"venue"
},
  "geometry": {"coordinates":[-3.4799690247,51.205406189],"type":"Point"}
}