{
  "type": "Feature",
  "properties": {
    "addr:full":"Old Meeting Street West Bromwich West Midlands B70 9SZ",
    "addr:postcode":"b70 9sz",
    "addr:street":"Meeting Street",
    "iso:country":"GB",
    "sg:address":"Old Meeting Street",
    "sg:city":"West Bromwich",
    "sg:classifiers":[
        {
            "category":"Place Of Worship",
            "type":"Public Place"
        },
        {
            "category":"Organizations",
            "subcategory":"Non-profit Organization",
            "type":"Services"
        }
    ],
    "sg:phone":"+44 121 553 5375",
    "sg:postcode":"B70 9SZ",
    "sg:province":"West Midlands",
    "sg:tags":[
        "charitable",
        "organisation",
        "charity"
    ],
    "wof:name":"Shree Krishna Temple",
    "wof:placetype":"venue"
},
  "geometry": {"coordinates":[-2.006329,52.527786],"type":"Point"}
}