{
  "type": "Feature",
  "properties": {
    "iso:country":"GB",
    "sg:address":"Cairnton",
    "sg:city":"Banchory",
    "sg:classifiers":[
        {
            "category":"Professional",
            "subcategory":"Business Services",
            "type":"Services"
        }
    ],
    "sg:phone":"+44 1339 883536",
    "sg:postcode":"AB31 4QP",
    "sg:province":"Aberdeen City",
    "sg:tags":[
        "hospitality",
        "corporate"
    ],
    "wof:name":"Howie Irvine Sporting Factors",
    "wof:placetype":"venue"
},
  "geometry": {"coordinates":[-2.613949,57.102871],"type":"Point"}
}