{
  "type": "Feature",
  "properties": {
    "iso:country":"GB",
    "sg:address":"96b Coronation Street",
    "sg:city":"Blackpool",
    "sg:classifiers":[
        {
            "category":"Cafe",
            "type":"Food & Drink"
        }
    ],
    "sg:phone":"+44 1253 621960",
    "sg:postcode":"FY1 4QE",
    "sg:province":"Lancashire",
    "sg:tags":[
        "tea",
        "snack",
        "bar",
        "room"
    ],
    "wof:name":"Swiss Cottage Cafe",
    "wof:placetype":"venue"
},
  "geometry": {"coordinates":[-3.05028,53.814053],"type":"Point"}
}