{
  "type": "Feature",
  "properties": {
    "addr:full":"132 Wellingborough Road Northampton Northamptonshire NN1 4DT",
    "addr:housenumber":"132",
    "addr:postcode":"nn1 4dt",
    "addr:street":"Wellingborough Road",
    "iso:country":"GB",
    "sg:address":"132 Wellingborough Road",
    "sg:city":"Northampton",
    "sg:classifiers":[
        {
            "category":"Personal",
            "subcategory":"Beauty Salon",
            "type":"Services"
        }
    ],
    "sg:phone":"+44 1604 627739",
    "sg:postcode":"NN1 4DT",
    "sg:province":"Northamptonshire",
    "sg:tags":[
        "unisex",
        "hairdresser"
    ],
    "wof:name":"The Strand",
    "wof:placetype":"venue"
},
  "geometry": {"coordinates":[-0.881444,52.24136],"type":"Point"}
}