{
  "type": "Feature",
  "properties": {
    "iso:country":"GB",
    "sg:address":"7 Hockerley Avenue, Whaley Bridge",
    "sg:city":"High Peak",
    "sg:classifiers":[
        {
            "category":"Manufacturing",
            "subcategory":"Petroleum Products",
            "type":"Manufacturing & Wholesale Goods"
        }
    ],
    "sg:phone":"+44 1663 735238",
    "sg:postcode":"SK23 7RT",
    "sg:province":"Cheshire",
    "sg:tags":[
        "double",
        "glazing"
    ],
    "wof:name":"Peveril Windows",
    "wof:placetype":"venue"
},
  "geometry": {"coordinates":[-1.989934,53.334389],"type":"Point"}
}