{
  "type": "Feature",
  "properties": {
    "iso:country":"GB",
    "sg:address":"38 Beech Grove",
    "sg:city":"York",
    "sg:classifiers":[
        {
            "category":"Building & Trades",
            "subcategory":"Construction",
            "type":"Services"
        }
    ],
    "sg:phone":"+44 1904 792221",
    "sg:postcode":"YO26 5LA",
    "sg:province":"North Yorkshire",
    "sg:tags":[
        "decorator",
        "painter"
    ],
    "wof:name":"Mike Coulson",
    "wof:placetype":"venue"
},
  "geometry": {"coordinates":[-1.1253089905,53.9582633972],"type":"Point"}
}