{
  "type": "Feature",
  "properties": {
    "addr:full":"Brandon House Painswick Road Cheltenham Gloucestershire GL50 2EU",
    "addr:postcode":"gl50 2eu",
    "addr:street":"Painswick Road",
    "iso:country":"GB",
    "sg:address":"Brandon House Painswick Road",
    "sg:city":"Cheltenham",
    "sg:classifiers":[
        {
            "category":"Professional",
            "subcategory":"Engineering",
            "type":"Services"
        }
    ],
    "sg:postcode":"GL50 2EU",
    "sg:province":"Gloucestershire",
    "sg:tags":[
        "consulting",
        "engineer"
    ],
    "wof:name":"Parsons Brinckerhoff Ltd.",
    "wof:placetype":"venue"
},
  "geometry": {"coordinates":[-2.082082,51.891411],"type":"Point"}
}