{
  "type": "Feature",
  "properties": {
    "iso:country":"GB",
    "sg:address":"Colne Bridge Works, Colne Bridge",
    "sg:city":"Huddersfield",
    "sg:classifiers":[
        {
            "category":"Building & Trades",
            "subcategory":"Construction",
            "type":"Services"
        }
    ],
    "sg:phone":"+44 1484 456249",
    "sg:postcode":"HD5 0RQ",
    "sg:province":"West Yorkshire",
    "sg:tags":[
        "management",
        "traffic",
        "system"
    ],
    "wof:name":"Moxon Traffic Management Ltd.",
    "wof:placetype":"venue"
},
  "geometry": {"coordinates":[-1.734218955,53.677898407],"type":"Point"}
}