{
  "type": "Feature",
  "properties": {
    "addr:full":"54 Marine Parade East Lee On The Solent Hampshire PO13 9BW",
    "addr:housenumber":"54",
    "addr:postcode":"po13 9bw",
    "addr:street":"Marine Parade",
    "iso:country":"GB",
    "sg:address":"54 Marine Parade East",
    "sg:city":"Lee On The Solent",
    "sg:classifiers":[
        {
            "category":"Bars & Pubs",
            "type":"Food & Drink"
        }
    ],
    "sg:phone":"+44 23 9255 9811",
    "sg:postcode":"PO13 9BW",
    "sg:province":"Hampshire",
    "sg:tags":[
        "pubs",
        "inn"
    ],
    "wof:name":"Old Ship The",
    "wof:placetype":"venue"
},
  "geometry": {"coordinates":[-1.202369,50.800629],"type":"Point"}
}