{
  "type": "Feature",
  "properties": {
    "iso:country":"GB",
    "sg:address":"Walkinshaw Road",
    "sg:city":"Renfrew",
    "sg:classifiers":[
        {
            "category":"Sports & Exercise",
            "subcategory":"Playing Field",
            "type":"Entertainment"
        },
        {
            "category":"Arena",
            "subcategory":"Sports Club",
            "type":"Entertainment"
        }
    ],
    "sg:phone":"+44 141 814 3355",
    "sg:postcode":"PA4 9LP",
    "sg:province":"Renfrewshire",
    "sg:tags":[
        "developer",
        "stadium",
        "surface",
        "contractor"
    ],
    "wof:name":"Sportsgrounds Ltd",
    "wof:placetype":"venue"
},
  "geometry": {"coordinates":[-4.44272995,55.8735237122],"type":"Point"}
}