{
  "type": "Feature",
  "properties": {
    "addr:full":"32 Gilman Place, Hanley Stoke-on-trent Staffordshire ST1 3PG",
    "addr:housenumber":"32",
    "addr:postcode":"staffordshire st1 3pg",
    "addr:street":"Gilman Place",
    "iso:country":"GB",
    "sg:address":"32 Gilman Place, Hanley",
    "sg:city":"Stoke-on-trent",
    "sg:classifiers":[
        {
            "category":"Banks & Credit Unions",
            "subcategory":"Financial Services",
            "type":"Services"
        }
    ],
    "sg:postcode":"ST1 3PG",
    "sg:province":"Staffordshire",
    "sg:tags":[
        "adviser"
    ],
    "wof:name":"Randell Pace Insurance Services",
    "wof:placetype":"venue"
},
  "geometry": {"coordinates":[-2.1719610691,53.0247192383],"type":"Point"}
}