{
  "type": "Feature",
  "properties": {
    "addr:full":"45 Eatons Mead London Greater London E4 8AN",
    "addr:housenumber":"45",
    "addr:postcode":"e4 8an",
    "addr:street":"Eatons Mead",
    "iso:country":"GB",
    "sg:address":"45 Eatons Mead",
    "sg:city":"London",
    "sg:classifiers":[
        {
            "category":"Retail",
            "subcategory":"Repair Shop",
            "type":"Services"
        }
    ],
    "sg:phone":"+44 20 8529 4055",
    "sg:postcode":"E4 8AN",
    "sg:province":"Greater London",
    "sg:tags":[
        "clocks",
        "watch"
    ],
    "wof:name":"G J Watch Repairs",
    "wof:placetype":"venue"
},
  "geometry": {"coordinates":[-0.019103,51.62706],"type":"Point"}
}