{
  "type": "Feature",
  "properties": {
    "addr:full":"9 Portman Street London Greater London W1H 6DY",
    "addr:housenumber":"9",
    "addr:postcode":"w1h 6dy",
    "addr:street":"Portman Street",
    "iso:country":"GB",
    "sg:address":"9 Portman Street",
    "sg:city":"London",
    "sg:classifiers":[
        {
            "category":"Organizations",
            "subcategory":"Membership Organization",
            "type":"Services"
        }
    ],
    "sg:phone":"+44 20 7499 6090",
    "sg:postcode":"W1H 6DY",
    "sg:province":"Greater London",
    "sg:tags":[
        "club"
    ],
    "wof:name":"Arab Bankers Association",
    "wof:placetype":"venue"
},
  "geometry": {"coordinates":[-0.1561290026,51.5144462585],"type":"Point"}
}