{
  "type": "Feature",
  "properties": {
    "iso:country":"GB",
    "sg:address":"12 Muirkirk Road, Lugar",
    "sg:city":"Cumnock",
    "sg:classifiers":[
        {
            "category":"Building & Trades",
            "subcategory":"Construction",
            "type":"Services"
        }
    ],
    "sg:phone":"+44 1290 421430",
    "sg:postcode":"KA18 3LJ",
    "sg:province":"East Ayrshire",
    "sg:tags":[
        "demolition",
        "contractor"
    ],
    "wof:name":"Turners",
    "wof:placetype":"venue"
},
  "geometry": {"coordinates":[-4.2356591225,55.4619483948],"type":"Point"}
}