{
  "type": "Feature",
  "properties": {
    "addr:full":"259 Main Street Bellshill North Lanarkshire ML4 1AJ",
    "addr:housenumber":"259",
    "addr:postcode":"ml4 1aj",
    "addr:street":"Main Street",
    "iso:country":"GB",
    "sg:address":"259 Main Street",
    "sg:city":"Bellshill",
    "sg:classifiers":[
        {
            "category":"Cafe",
            "type":"Food & Drink"
        }
    ],
    "sg:phone":"+44 1698 746167",
    "sg:postcode":"ML4 1AJ",
    "sg:province":"North Lanarkshire",
    "sg:tags":[
        "tea",
        "room"
    ],
    "wof:name":"Cafe D'Ora",
    "wof:placetype":"venue"
},
  "geometry": {"coordinates":[-4.021173,55.819221],"type":"Point"}
}