{
  "type": "Feature",
  "properties": {
    "addr:full":"Rhydygors, Talog Carmarthen Carmarthenshire SA33 6NS",
    "addr:postcode":"sa33 6ns",
    "addr:street":"Talog;Carmarthenshire",
    "iso:country":"GB",
    "sg:address":"Rhydygors, Talog",
    "sg:city":"Carmarthen",
    "sg:classifiers":[
        {
            "category":"Farming",
            "subcategory":"Dairy Farm",
            "type":"Manufacturing & Wholesale Goods"
        }
    ],
    "sg:phone":"+44 1994 484345",
    "sg:postcode":"SA33 6NS",
    "sg:province":"Carmarthenshire",
    "wof:name":"G & M M Davies",
    "wof:placetype":"venue"
},
  "geometry": {"coordinates":[-4.366099,51.89064],"type":"Point"}
}