{
  "type": "Feature",
  "properties": {
    "addr:full":"1 Heron St Stoke On Trent Staffordshire ST4 3AR",
    "addr:housenumber":"1",
    "addr:postcode":"st4 3ar",
    "addr:street":"Heron St",
    "iso:country":"GB",
    "sg:address":"1 Heron St",
    "sg:city":"Stoke On Trent",
    "sg:classifiers":[
        {
            "category":"Bars & Pubs",
            "type":"Food & Drink"
        }
    ],
    "sg:phone":"+44 1782 312420",
    "sg:postcode":"ST4 3AR",
    "sg:province":"Staffordshire",
    "sg:tags":[
        "pubs",
        "inn"
    ],
    "wof:name":"Railway Inn The",
    "wof:placetype":"venue"
},
  "geometry": {"coordinates":[-2.1616299152,52.9942474365],"type":"Point"}
}