{
  "type": "Feature",
  "properties": {
    "addr:full":"23 Arboretum Street Nottingham Nottinghamshire NG1 4JA",
    "addr:housenumber":"23",
    "addr:postcode":"ng1 4ja",
    "addr:street":"Arboretum Street",
    "iso:country":"GB",
    "sg:address":"23 Arboretum Street",
    "sg:city":"Nottingham",
    "sg:classifiers":[
        {
            "category":"Bars & Pubs",
            "type":"Food & Drink"
        }
    ],
    "sg:phone":"+44 115 978 5914",
    "sg:postcode":"NG1 4JA",
    "sg:province":"Nottinghamshire",
    "sg:tags":[
        "pubs",
        "inn"
    ],
    "wof:name":"The Park",
    "wof:placetype":"venue"
},
  "geometry": {"coordinates":[-1.158965,52.961838],"type":"Point"}
}