{
  "type": "Feature",
  "properties": {
    "addr:full":"Thorncliffe Road Bradford West Yorkshire BD8 7DD",
    "addr:postcode":"bd8 7dd",
    "addr:street":"Thorncliffe Road",
    "iso:country":"GB",
    "sg:address":"Thorncliffe Road",
    "sg:city":"Bradford",
    "sg:classifiers":[
        {
            "category":"Freight",
            "type":"Transportation"
        }
    ],
    "sg:phone":"+44 1274 493513",
    "sg:postcode":"BD8 7DD",
    "sg:province":"West Yorkshire",
    "sg:tags":[
        "forwarders"
    ],
    "wof:name":"Thompson Davis & Co. Ltd.",
    "wof:placetype":"venue"
},
  "geometry": {"coordinates":[-1.760329,53.805489],"type":"Point"}
}