{
  "type": "Feature",
  "properties": {
    "iso:country":"GB",
    "sg:address":"15 Old Church Rd",
    "sg:city":"Chingford",
    "sg:classifiers":[
        {
            "category":"Shopping",
            "subcategory":"Clothing, Apparel, & Fashions",
            "type":"Retail Goods"
        }
    ],
    "sg:phone":"+44 20 8523 7775",
    "sg:postcode":"E4 6SJ",
    "sg:province":"Greater London",
    "sg:tags":[
        "clothing"
    ],
    "wof:name":"Goldcoast International Ltd",
    "wof:placetype":"venue"
},
  "geometry": {"coordinates":[-0.0172920004,51.6179008484],"type":"Point"}
}