{
  "type": "Feature",
  "properties": {
    "iso:country":"GB",
    "sg:address":"Southam Road",
    "sg:city":"Banbury",
    "sg:classifiers":[
        {
            "category":"Retail",
            "subcategory":"Auto Repair",
            "type":"Services"
        }
    ],
    "sg:phone":"+44 1295 750494",
    "sg:postcode":"OX17 1RH",
    "sg:province":"Northamptonshire",
    "sg:tags":[
        "modification",
        "garage"
    ],
    "wof:name":"Boltons Auto Services",
    "wof:placetype":"venue"
},
  "geometry": {"coordinates":[-1.359594,52.140373],"type":"Point"}
}