{
  "type": "Feature",
  "properties": {
    "addr:full":"31 Tudor Close London Greater London N6 5PR",
    "addr:housenumber":"31",
    "addr:postcode":"n6 5pr",
    "addr:street":"Tudor Close",
    "iso:country":"GB",
    "sg:address":"31 Tudor Close",
    "sg:city":"London",
    "sg:classifiers":[
        {
            "category":"Shopping",
            "subcategory":"Department Store",
            "type":"Retail Goods"
        }
    ],
    "sg:postcode":"N6 5PR",
    "sg:province":"Greater London",
    "wof:name":"Ashanti Music Co  Ltd",
    "wof:placetype":"venue"
},
  "geometry": {"coordinates":[-0.1380800009,51.57239151],"type":"Point"}
}