{
  "type": "Feature",
  "properties": {
    "addr:full":"Lazarus Court, Woodgate, Rothley Leicester Leicestershire LE7 7LL",
    "addr:postcode":"le7 7ll",
    "addr:street":"Lazarus Court Woodgate",
    "iso:country":"GB",
    "sg:address":"Lazarus Court, Woodgate, Rothley",
    "sg:city":"Leicester",
    "sg:classifiers":[
        {
            "category":"Retail",
            "subcategory":"Auto Repair",
            "type":"Services"
        }
    ],
    "sg:postcode":"LE7 7LL",
    "sg:province":"Leicestershire",
    "sg:tags":[
        "modification",
        "garage"
    ],
    "wof:name":"N Aldridge",
    "wof:placetype":"venue"
},
  "geometry": {"coordinates":[-1.137163043,52.708366394],"type":"Point"}
}