{
  "type": "Feature",
  "properties": {
    "addr:full":"130 Dover Road, Walmer Deal Kent CT14 7JG",
    "addr:housenumber":"130",
    "addr:postcode":"ct14 7jg",
    "addr:street":"Dover Road",
    "iso:country":"GB",
    "sg:address":"130 Dover Road, Walmer",
    "sg:city":"Deal",
    "sg:classifiers":[
        {
            "category":"Recreation",
            "subcategory":"Dog Park",
            "type":"Entertainment"
        },
        {
            "category":"Retail",
            "subcategory":"Animal Services",
            "type":"Services"
        }
    ],
    "sg:phone":"+44 1304 361695",
    "sg:postcode":"CT14 7JG",
    "sg:province":"Kent",
    "sg:tags":[
        "grooming",
        "clipping"
    ],
    "wof:name":"The Dog Grooming Service",
    "wof:placetype":"venue"
},
  "geometry": {"coordinates":[1.39825,51.208214],"type":"Point"}
}