{
  "type": "Feature",
  "properties": {
    "iso:country":"GB",
    "sg:address":"Unit 67, Cross Way, Hillend Industrial Park",
    "sg:city":"Dunfermline",
    "sg:classifiers":[
        {
            "category":"Farming",
            "subcategory":"Fish & Marine Products",
            "type":"Manufacturing & Wholesale Goods"
        }
    ],
    "sg:phone":"+44 1383 821421",
    "sg:postcode":"KY11 9JE",
    "sg:province":"Fife",
    "sg:tags":[
        "fishmonger",
        "supplier",
        "shell",
        "processor"
    ],
    "wof:name":"Iona Shell",
    "wof:placetype":"venue"
},
  "geometry": {"coordinates":[-3.346404,56.04538],"type":"Point"}
}