{
  "type": "Feature",
  "properties": {
    "iso:country":"GB",
    "sg:address":"Pennyhurst Mill, Haig Street, Wigan Pier",
    "sg:city":"Wigan",
    "sg:classifiers":[
        {
            "category":"Building & Trades",
            "subcategory":"Construction",
            "type":"Services"
        }
    ],
    "sg:phone":"+44 1942 491631",
    "sg:postcode":"WN3 4AZ",
    "sg:province":"Lancashire",
    "sg:tags":[
        "builder"
    ],
    "wof:name":"Clem Turton Ltd.",
    "wof:placetype":"venue"
},
  "geometry": {"coordinates":[-2.64113,53.542728],"type":"Point"}
}