{
  "type": "Feature",
  "properties": {
    "addr:full":"52 Mount Rd, Nether Stowey Bridgwater Somerset TA5 1LX",
    "addr:housenumber":"52",
    "addr:postcode":"ta5 1lx",
    "addr:street":"Mount Rd",
    "iso:country":"GB",
    "sg:address":"52 Mount Rd, Nether Stowey",
    "sg:city":"Bridgwater",
    "sg:classifiers":[
        {
            "category":"Real Estate",
            "subcategory":"Architect",
            "type":"Services"
        }
    ],
    "sg:phone":"+44 1278 722484",
    "sg:postcode":"TA5 1LX",
    "sg:province":"Somerset",
    "wof:name":"Hobert Engineering Ltd",
    "wof:placetype":"venue"
},
  "geometry": {"coordinates":[-3.163262,51.151958],"type":"Point"}
}