{
  "type": "Feature",
  "properties": {
    "addr:full":"4 Frenze Road Diss Norfolk IP22 4PA",
    "addr:housenumber":"4",
    "addr:postcode":"ip22 4pa",
    "addr:street":"Frenze Road",
    "iso:country":"GB",
    "sg:address":"4 Frenze Road",
    "sg:city":"Diss",
    "sg:classifiers":[
        {
            "category":"Retail",
            "subcategory":"Repair Shop",
            "type":"Services"
        }
    ],
    "sg:postcode":"IP22 4PA",
    "sg:province":"Norfolk",
    "sg:tags":[
        "radio",
        "television",
        "video"
    ],
    "wof:name":"G R Brame Ltd.",
    "wof:placetype":"venue"
},
  "geometry": {"coordinates":[1.1123770475,52.3766517639],"type":"Point"}
}