{
  "type": "Feature",
  "properties": {
    "addr:full":"7 Carlisle St, Dresden Stoke-on-trent Staffordshire ST3 4HL",
    "addr:housenumber":"7",
    "addr:postcode":"staffordshire st3 4hl",
    "addr:street":"Carlisle St",
    "iso:country":"GB",
    "sg:address":"7 Carlisle St, Dresden",
    "sg:city":"Stoke-on-trent",
    "sg:classifiers":[
        {
            "category":"Food & Beverages",
            "subcategory":"Liquor & Beverages",
            "type":"Retail Goods"
        }
    ],
    "sg:postcode":"ST3 4HL",
    "sg:province":"Staffordshire",
    "sg:tags":[
        "beer",
        "spirit",
        "wines"
    ],
    "wof:name":"D J's",
    "wof:placetype":"venue"
},
  "geometry": {"coordinates":[-2.1358659267,52.9787521362],"type":"Point"}
}