{
  "type": "Feature",
  "properties": {
    "addr:full":"4 Harropwell Lane Pontefract North Yorkshire WF8 1QY",
    "addr:housenumber":"4",
    "addr:postcode":"wf8 1qy",
    "addr:street":"Harropwell Lane",
    "iso:country":"GB",
    "sg:address":"4 Harropwell Lane",
    "sg:city":"Pontefract",
    "sg:classifiers":[
        {
            "category":"Organizations",
            "subcategory":"Non-profit Organization",
            "type":"Services"
        }
    ],
    "sg:phone":"+44 1977 706932",
    "sg:postcode":"WF8 1QY",
    "sg:province":"North Yorkshire",
    "sg:tags":[
        "charitable",
        "organisation",
        "voluntary",
        "charity"
    ],
    "wof:name":"Pontefract Family Centre",
    "wof:placetype":"venue"
},
  "geometry": {"coordinates":[-1.3052220345,53.692401886],"type":"Point"}
}