{
  "type": "Feature",
  "properties": {
    "iso:country":"GB",
    "sg:address":"10 Middle Row",
    "sg:city":"East Grinstead",
    "sg:classifiers":[
        {
            "category":"Health Services",
            "subcategory":"Optometrist",
            "type":"Services"
        },
        {
            "category":"Shopping",
            "subcategory":"Optician",
            "type":"Retail Goods"
        }
    ],
    "sg:phone":"+44 1342 312377",
    "sg:postcode":"RH19 3AX",
    "sg:province":"East Sussex",
    "sg:tags":[
        "ophthalmic"
    ],
    "wof:name":"Arthur Hayes Opticians Ltd",
    "wof:placetype":"venue"
},
  "geometry": {"coordinates":[-0.006165,51.123871],"type":"Point"}
}