{
  "type": "Feature",
  "properties": {
    "addr:full":"11-12 St Dominics Square Luton Bedfordshire LU4 0UN",
    "addr:housenumber":"11-12",
    "addr:postcode":"lu4 0un",
    "addr:street":"St Dominics Square",
    "iso:country":"GB",
    "sg:address":"11-12 St Dominics Square",
    "sg:city":"Luton",
    "sg:classifiers":[
        {
            "category":"Home & Garden",
            "subcategory":"Hardware",
            "type":"Retail Goods"
        }
    ],
    "sg:phone":"+44 1582 606449",
    "sg:postcode":"LU4 0UN",
    "sg:province":"Bedfordshire",
    "wof:name":"Lewsey Hardware",
    "wof:placetype":"venue"
},
  "geometry": {"coordinates":[-0.495807,51.901993],"type":"Point"}
}