{
  "type": "Feature",
  "properties": {
    "iso:country":"GB",
    "sg:address":"4 Park St",
    "sg:city":"Chester",
    "sg:classifiers":[
        {
            "category":"Health Services",
            "subcategory":"Dentist",
            "type":"Services"
        }
    ],
    "sg:phone":"+44 1244 321378",
    "sg:postcode":"CH1 1RN",
    "sg:province":"Cheshire",
    "wof:name":"Park Street Dental Clinic",
    "wof:placetype":"venue"
},
  "geometry": {"coordinates":[-2.8884000778,53.1888237],"type":"Point"}
}