{
  "type": "Feature",
  "properties": {
    "addr:full":"8 Cross Cheaping Coventry West Midlands CV1 1HF",
    "addr:housenumber":"8",
    "addr:postcode":"cv1 1hf",
    "addr:street":"Cross Cheaping",
    "iso:country":"GB",
    "sg:address":"8 Cross Cheaping",
    "sg:city":"Coventry",
    "sg:classifiers":[
        {
            "category":"Banks & Credit Unions",
            "subcategory":"Financial Services",
            "type":"Services"
        }
    ],
    "sg:phone":"+44 24 7622 5510",
    "sg:postcode":"CV1 1HF",
    "sg:province":"West Midlands",
    "sg:tags":[
        "consultant"
    ],
    "wof:name":"Money Shop",
    "wof:placetype":"venue"
},
  "geometry": {"coordinates":[-1.510434,52.409485],"type":"Point"}
}