{
  "type": "Feature",
  "properties": {
    "iso:country":"GB",
    "sg:address":"Unit 2 Whitby Court Abbey Road, Shepley",
    "sg:city":"Huddersfield",
    "sg:classifiers":[
        {
            "category":"Shopping",
            "subcategory":"Stationery & Office Supplies",
            "type":"Retail Goods"
        }
    ],
    "sg:postcode":"HD8 8EH",
    "sg:province":"South Yorkshire",
    "sg:tags":[
        "item",
        "promotional"
    ],
    "wof:name":"M A G Promotions Ltd.",
    "wof:placetype":"venue"
},
  "geometry": {"coordinates":[-1.699034,53.590118],"type":"Point"}
}