{
  "type": "Feature",
  "properties": {
    "iso:country":"GB",
    "sg:address":"18 Britten Street",
    "sg:city":"London",
    "sg:classifiers":[
        {
            "category":"Personal",
            "subcategory":"Beauty Salon",
            "type":"Services"
        }
    ],
    "sg:postcode":"SW3 3TU",
    "sg:province":"Greater London",
    "sg:tags":[
        "unisex",
        "hairdresser"
    ],
    "wof:name":"Chumi",
    "wof:placetype":"venue"
},
  "geometry": {"coordinates":[-0.167930007,51.4892501831],"type":"Point"}
}