{
  "type": "Feature",
  "properties": {
    "addr:full":"58 Stubbington Lane Fareham Hampshire PO14 2PE",
    "addr:housenumber":"58",
    "addr:postcode":"po14 2pe",
    "addr:street":"Stubbington Lane",
    "iso:country":"GB",
    "sg:address":"58 Stubbington Lane",
    "sg:city":"Fareham",
    "sg:classifiers":[
        {
            "category":"Real Estate",
            "subcategory":"Real Estate Services",
            "type":"Services"
        },
        {
            "category":"Building & Trades",
            "subcategory":"Construction",
            "type":"Services"
        }
    ],
    "sg:phone":"+44 1329 665291",
    "sg:postcode":"PO14 2PE",
    "sg:province":"Hampshire",
    "sg:tags":[
        "builder"
    ],
    "wof:name":"Builders Estimating Service",
    "wof:placetype":"venue"
},
  "geometry": {"coordinates":[-1.21442,50.820213],"type":"Point"}
}