{
  "type": "Feature",
  "properties": {
    "addr:full":"4 Southbourne Court, Drury Lane Sheffield Derbyshire S17 3GG",
    "addr:housenumber":"4",
    "addr:postcode":"s17 3gg",
    "addr:street":"Southbourne Court Drury Lane",
    "iso:country":"GB",
    "sg:address":"4 Southbourne Court, Drury Lane",
    "sg:city":"Sheffield",
    "sg:classifiers":[
        {
            "category":"Building & Trades",
            "subcategory":"Landscaping Services",
            "type":"Services"
        }
    ],
    "sg:postcode":"S17 3GG",
    "sg:province":"Derbyshire",
    "sg:tags":[
        "horticultural",
        "consultant"
    ],
    "wof:name":"Conveyor & Plant Services",
    "wof:placetype":"venue"
},
  "geometry": {"coordinates":[-1.4645440578,53.3831100464],"type":"Point"}
}