{
  "type": "Feature",
  "properties": {
    "iso:country":"GB",
    "sg:address":"Timberland House, 5 Beadlef State, Hithercroft",
    "sg:city":"Wallingford",
    "sg:classifiers":[
        {
            "category":"Home & Garden",
            "subcategory":"Carpets & Floor Coverings",
            "type":"Retail Goods"
        }
    ],
    "sg:phone":"+44 1491 835000",
    "sg:postcode":"OX10 9EZ",
    "sg:province":"Oxfordshire",
    "sg:tags":[
        "textile",
        "floorcoverings"
    ],
    "wof:name":"Timberland Flooring Co. Ltd.",
    "wof:placetype":"venue"
},
  "geometry": {"coordinates":[-1.1256229877,51.6009101868],"type":"Point"}
}