{
  "type": "Feature",
  "properties": {
    "addr:full":"Hartswood House, Reading Road, Chineham Basingstoke Hampshire RG24 8LN",
    "addr:postcode":"rg24 8ln",
    "addr:street":"Reading Road",
    "iso:country":"GB",
    "sg:address":"Hartswood House, Reading Road, Chineham",
    "sg:city":"Basingstoke",
    "sg:classifiers":[
        {
            "category":"Professional",
            "subcategory":"Printing & Photocopies",
            "type":"Services"
        }
    ],
    "sg:phone":"+44 1256 352434",
    "sg:postcode":"RG24 8LN",
    "sg:province":"Hampshire",
    "sg:tags":[
        "printer"
    ],
    "wof:name":"Personalised Print",
    "wof:placetype":"venue"
},
  "geometry": {"coordinates":[-1.073531,51.279404],"type":"Point"}
}