{
  "type": "Feature",
  "properties": {
    "addr:full":"Oyster Bay House, Chambers Wharf Faversham Kent ME13 7BT",
    "addr:postcode":"me13 7bt",
    "addr:street":"Chambers Wharf",
    "iso:country":"GB",
    "sg:address":"Oyster Bay House, Chambers Wharf",
    "sg:city":"Faversham",
    "sg:classifiers":[
        {
            "category":"Manufacturing",
            "subcategory":"Tools & Machinery",
            "type":"Manufacturing & Wholesale Goods"
        },
        {
            "category":"Insurance",
            "subcategory":"Insurance Agent",
            "type":"Services"
        }
    ],
    "sg:phone":"+44 1795 539416",
    "sg:postcode":"ME13 7BT",
    "sg:province":"Kent",
    "sg:tags":[
        "society",
        "friendly"
    ],
    "wof:name":"Rickard Lazenby International Ltd.",
    "wof:placetype":"venue"
},
  "geometry": {"coordinates":[0.88344,51.309605],"type":"Point"}
}