{
  "type": "Feature",
  "properties": {
    "addr:full":"Sets Road, Blackbouurow King's Lynn Norfolk PE32 1SL",
    "addr:postcode":"pe32 1sl",
    "addr:street":"Sets Road Blackbouurow;Lynn",
    "iso:country":"GB",
    "sg:address":"Sets Road, Blackbouurow",
    "sg:city":"King's Lynn",
    "sg:classifiers":[
        {
            "category":"Retail",
            "subcategory":"Auto Repair",
            "type":"Services"
        }
    ],
    "sg:phone":"+44 1553 841263",
    "sg:postcode":"PE32 1SL",
    "sg:province":"Norfolk",
    "sg:tags":[
        "modification",
        "garage"
    ],
    "wof:name":"Economy Motor Repairs",
    "wof:placetype":"venue"
},
  "geometry": {"coordinates":[0.4602699876,52.7048187256],"type":"Point"}
}