{
  "type": "Feature",
  "properties": {
    "addr:full":"85 Mottingham Road London Greater London SE9 4TJ",
    "addr:housenumber":"85",
    "addr:postcode":"se9 4tj",
    "addr:street":"Mottingham Road",
    "iso:country":"GB",
    "sg:address":"85 Mottingham Road",
    "sg:city":"London",
    "sg:classifiers":[
        {
            "category":"Shopping",
            "subcategory":"Bicycles & Sporting Goods",
            "type":"Retail Goods"
        },
        {
            "category":"Autos & Motor Vehicles",
            "subcategory":"Motorcycle Sales",
            "type":"Retail Goods"
        }
    ],
    "sg:phone":"+44 20 8851 0218",
    "sg:postcode":"SE9 4TJ",
    "sg:province":"Greater London",
    "sg:tags":[
        "scooter",
        "accessory",
        "cycle"
    ],
    "wof:name":"Karpart",
    "wof:placetype":"venue"
},
  "geometry": {"coordinates":[0.045504,51.4359703064],"type":"Point"}
}