{
  "type": "Feature",
  "properties": {
    "iso:country":"GB",
    "sg:address":"82 Silk Street",
    "sg:city":"Manchester",
    "sg:classifiers":[
        {
            "category":"Building & Trades",
            "subcategory":"Cleaning & Sanitation",
            "type":"Services"
        }
    ],
    "sg:phone":"+44 161 236 5378",
    "sg:postcode":"M4 6BJ",
    "sg:province":"Greater Manchester",
    "sg:tags":[
        "commercial"
    ],
    "wof:name":"Manchester Whipclean",
    "wof:placetype":"venue"
},
  "geometry": {"coordinates":[-2.2268199921,53.4862709045],"type":"Point"}
}