{
  "type": "Feature",
  "properties": {
    "iso:country":"GB",
    "sg:address":"2 Drake Court",
    "sg:city":"Middlesbrough",
    "sg:classifiers":[
        {
            "category":"Professional",
            "subcategory":"Engineering",
            "type":"Services"
        }
    ],
    "sg:phone":"+44 1642 220289",
    "sg:postcode":"TS2 1RS",
    "sg:province":"Durham",
    "wof:name":"Klinger Ltd.",
    "wof:placetype":"venue"
},
  "geometry": {"coordinates":[-1.254086,54.581718],"type":"Point"}
}