{
  "type": "Feature",
  "properties": {
    "addr:full":"165 Newgate Street Bishop Auckland Durham DL14 7EN",
    "addr:housenumber":"165",
    "addr:postcode":"dl14 7en",
    "addr:street":"Newgate Street",
    "iso:country":"GB",
    "sg:address":"165 Newgate Street",
    "sg:city":"Bishop Auckland",
    "sg:classifiers":[
        {
            "category":"Bars & Pubs",
            "type":"Food & Drink"
        }
    ],
    "sg:phone":"+44 1388 605953",
    "sg:postcode":"DL14 7EN",
    "sg:province":"Durham",
    "sg:tags":[
        "pubs",
        "inn"
    ],
    "wof:name":"The Cumberland Arms",
    "wof:placetype":"venue"
},
  "geometry": {"coordinates":[-1.67572,54.659798],"type":"Point"}
}