{
  "type": "Feature",
  "properties": {
    "iso:country":"GB",
    "sg:address":"4 Cairndale Close",
    "sg:city":"Bromley",
    "sg:classifiers":[
        {
            "category":"Professional",
            "subcategory":"Computer Services",
            "type":"Services"
        }
    ],
    "sg:postcode":"BR1 4HH",
    "sg:province":"Kent",
    "sg:tags":[
        "system",
        "software"
    ],
    "wof:name":"Logical Objects Ltd.",
    "wof:placetype":"venue"
},
  "geometry": {"coordinates":[0.008837,51.416424],"type":"Point"}
}