{
  "type": "Feature",
  "properties": {
    "iso:country":"GB",
    "sg:address":"Chester Road, Pentre",
    "sg:city":"Deeside",
    "sg:classifiers":[
        {
            "category":"Retail",
            "subcategory":"Repair Shop",
            "type":"Services"
        }
    ],
    "sg:phone":"+44 1244 537198",
    "sg:postcode":"CH5 2DT",
    "sg:province":"Flintshire",
    "sg:tags":[
        "radio",
        "television",
        "video"
    ],
    "wof:name":"Capital Distributors",
    "wof:placetype":"venue"
},
  "geometry": {"coordinates":[-3.024988,53.20248],"type":"Point"}
}