{
  "type": "Feature",
  "properties": {
    "addr:full":"91 Corstorphine Road, Murrayfield Edinburgh City of Edinburgh EH12 5QE",
    "addr:housenumber":"91",
    "addr:postcode":"eh12 5qe",
    "addr:street":"Corstorphine Road",
    "iso:country":"GB",
    "sg:address":"91 Corstorphine Road, Murrayfield",
    "sg:city":"Edinburgh",
    "sg:classifiers":[
        {
            "category":"Health Services",
            "subcategory":"Doctor",
            "type":"Services"
        },
        {
            "category":"Health Services",
            "subcategory":"Dentist",
            "type":"Services"
        }
    ],
    "sg:phone":"+44 131 337 2983",
    "sg:postcode":"EH12 5QE",
    "sg:province":"City of Edinburgh",
    "wof:name":"THE MURRAYFIELD DENTAL PRACTICE",
    "wof:placetype":"venue"
},
  "geometry": {"coordinates":[-3.2475879192,55.9450683594],"type":"Point"}
}