{
  "type": "Feature",
  "properties": {
    "addr:full":"9 Coombe Road New Malden Surrey KT3 4PX",
    "addr:housenumber":"9",
    "addr:postcode":"kt3 4px",
    "addr:street":"Coombe Road",
    "iso:country":"GB",
    "sg:address":"9 Coombe Road",
    "sg:city":"New Malden",
    "sg:classifiers":[
        {
            "category":"Personal",
            "subcategory":"Beauty Salon",
            "type":"Services"
        }
    ],
    "sg:phone":"+44 20 8949 0191",
    "sg:postcode":"KT3 4PX",
    "sg:province":"Surrey",
    "wof:name":"Parkjuns",
    "wof:placetype":"venue"
},
  "geometry": {"coordinates":[-0.2567819953,51.4041976929],"type":"Point"}
}