{
  "type": "Feature",
  "properties": {
    "addr:full":"17 Cranemoor Avenue Christchurch Dorset BH23 5AN",
    "addr:housenumber":"17",
    "addr:postcode":"bh23 5an",
    "addr:street":"Cranemoor Avenue",
    "iso:country":"GB",
    "sg:address":"17 Cranemoor Avenue",
    "sg:city":"Christchurch",
    "sg:classifiers":[
        {
            "category":"Building & Trades",
            "subcategory":"Construction",
            "type":"Services"
        },
        {
            "category":"Manufacturing",
            "subcategory":"Paper Products",
            "type":"Manufacturing & Wholesale Goods"
        }
    ],
    "sg:phone":"+44 1425 273949",
    "sg:postcode":"BH23 5AN",
    "sg:province":"Dorset",
    "sg:tags":[
        "cardboard",
        "decorator",
        "painter"
    ],
    "wof:name":"A Pitt",
    "wof:placetype":"venue"
},
  "geometry": {"coordinates":[-1.7106039524,50.7504272461],"type":"Point"}
}