{
  "type": "Feature",
  "properties": {
    "addr:full":"9 Old Town London Greater London SW4 0JT",
    "addr:housenumber":"9",
    "addr:postcode":"sw4 0jt",
    "addr:street":"Old",
    "iso:country":"GB",
    "sg:address":"9 Old Town",
    "sg:city":"London",
    "sg:classifiers":[
        {
            "category":"Shopping",
            "subcategory":"Thrift Store",
            "type":"Retail Goods"
        }
    ],
    "sg:phone":"+44 20 7498 2349",
    "sg:postcode":"SW4 0JT",
    "sg:province":"Greater London",
    "sg:tags":[
        "shop",
        "charity"
    ],
    "wof:name":"Trinity House Charity Shops",
    "wof:placetype":"venue"
},
  "geometry": {"coordinates":[-0.1410589963,51.4652290344],"type":"Point"}
}