{
  "type": "Feature",
  "properties": {
    "addr:full":"105 Mount Pleasant Road London Greater London NW10 3EH",
    "addr:housenumber":"105",
    "addr:postcode":"nw10 3eh",
    "addr:street":"Mount Pleasant Road",
    "iso:country":"GB",
    "sg:address":"105 Mount Pleasant Road",
    "sg:city":"London",
    "sg:classifiers":[
        {
            "category":"Travel",
            "subcategory":"Travel Agent",
            "type":"Entertainment"
        },
        {
            "category":"Recreation",
            "subcategory":"Gun Range",
            "type":"Entertainment"
        }
    ],
    "sg:phone":"+44 20 8459 8787",
    "sg:postcode":"NW10 3EH",
    "sg:province":"Greater London",
    "sg:tags":[
        "operator",
        "tour",
        "agency",
        "activity"
    ],
    "sg:website":"http://www.sailingholidays.com",
    "wof:name":"Neilson Sailing Holidays Ltd",
    "wof:placetype":"venue"
},
  "geometry": {"coordinates":[-0.224389,51.542736],"type":"Point"}
}