{
  "type": "Feature",
  "properties": {
    "addr:full":"36 Rockwood Crescent, Calverley Pudsey West Yorkshire LS28 5AE",
    "addr:housenumber":"36",
    "addr:postcode":"ls28 5ae",
    "addr:street":"Rockwood Crescent;West",
    "iso:country":"GB",
    "sg:address":"36 Rockwood Crescent, Calverley",
    "sg:city":"Pudsey",
    "sg:classifiers":[
        {
            "category":"Building & Trades",
            "subcategory":"Plumbing",
            "type":"Services"
        }
    ],
    "sg:phone":"+44 113 257 9337",
    "sg:postcode":"LS28 5AE",
    "sg:province":"West Yorkshire",
    "sg:tags":[
        "heating"
    ],
    "wof:name":"G.F Wilson",
    "wof:placetype":"venue"
},
  "geometry": {"coordinates":[-1.6890950203,53.8117713928],"type":"Point"}
}