{
  "type": "Feature",
  "properties": {
    "addr:full":"5 Enborne Rd Newbury Berkshire RG14 6AG",
    "addr:housenumber":"5",
    "addr:postcode":"rg14 6ag",
    "addr:street":"Enborne Rd",
    "iso:country":"GB",
    "sg:address":"5 Enborne Rd",
    "sg:city":"Newbury",
    "sg:classifiers":[
        {
            "category":"Bars & Pubs",
            "type":"Food & Drink"
        }
    ],
    "sg:phone":"+44 1635 40912",
    "sg:postcode":"RG14 6AG",
    "sg:province":"Berkshire",
    "sg:tags":[
        "pubs",
        "inn"
    ],
    "wof:name":"Lamb Inn The",
    "wof:placetype":"venue"
},
  "geometry": {"coordinates":[-1.3313230276,51.3964385986],"type":"Point"}
}