{
  "type": "Feature",
  "properties": {
    "iso:country":"GB",
    "sg:address":"15 Westby Road, Boscombe",
    "sg:city":"Bournemouth",
    "sg:classifiers":[
        {
            "category":"Travel",
            "subcategory":"Hotels & Motels",
            "type":"Entertainment"
        }
    ],
    "sg:postcode":"BH5 1HA",
    "sg:province":"Dorset",
    "wof:name":"Au-Levant Hotel",
    "wof:placetype":"venue"
},
  "geometry": {"coordinates":[-1.838982,50.724892],"type":"Point"}
}