{
  "type": "Feature",
  "properties": {
    "addr:full":"Forest Road, New Ollerton Newark Nottinghamshire NG22 9QT",
    "addr:postcode":"ng22 9qt",
    "addr:street":"Forest Road New",
    "iso:country":"GB",
    "sg:address":"Forest Road, New Ollerton",
    "sg:city":"Newark",
    "sg:classifiers":[
        {
            "category":"Shopping",
            "subcategory":"Mobile Phones",
            "type":"Retail Goods"
        }
    ],
    "sg:phone":"+44 1623 862800",
    "sg:postcode":"NG22 9QT",
    "sg:province":"Nottinghamshire",
    "wof:name":"Chatterbox Communications & Mobile Phones",
    "wof:placetype":"venue"
},
  "geometry": {"coordinates":[-1.0034439564,53.2043838501],"type":"Point"}
}