{
  "type": "Feature",
  "properties": {
    "iso:country":"GB",
    "sg:address":"5 Wrightington Street",
    "sg:city":"Wigan",
    "sg:classifiers":[
        {
            "category":"Real Estate",
            "subcategory":"Real Estate Operator",
            "type":"Services"
        }
    ],
    "sg:phone":"+44 1942 825714",
    "sg:postcode":"WN1 2AZ",
    "sg:province":"Lancashire",
    "sg:tags":[
        "letting",
        "agent"
    ],
    "wof:name":"Hall & Houghton Ltd.",
    "wof:placetype":"venue"
},
  "geometry": {"coordinates":[-2.6328999996,53.5512733459],"type":"Point"}
}