{
  "type": "Feature",
  "properties": {
    "addr:full":"144 Hunslet Road Leeds West Yorkshire LS10 1JY",
    "addr:housenumber":"144",
    "addr:postcode":"ls10 1jy",
    "addr:street":"Hunslet Road",
    "iso:country":"GB",
    "sg:address":"144 Hunslet Road",
    "sg:city":"Leeds",
    "sg:classifiers":[
        {
            "category":"Manufacturing",
            "subcategory":"Motor Vehicles & Parts",
            "type":"Manufacturing & Wholesale Goods"
        },
        {
            "category":"Autos & Motor Vehicles",
            "subcategory":"Auto Supplies",
            "type":"Retail Goods"
        }
    ],
    "sg:phone":"+44 113 245 3643",
    "sg:postcode":"LS10 1JY",
    "sg:province":"West Yorkshire",
    "sg:tags":[
        "manufacturer",
        "motorcycle",
        "accessory"
    ],
    "wof:name":"Startright Motor Cycles",
    "wof:placetype":"venue"
},
  "geometry": {"coordinates":[-1.5349760056,53.787361145],"type":"Point"}
}