{
  "type": "Feature",
  "properties": {
    "addr:full":"Benenden Barn, The Street Cranbrook Kent TN17 4BZ",
    "addr:postcode":"tn17 4bz",
    "addr:street":"The Street",
    "iso:country":"GB",
    "sg:address":"Benenden Barn, The Street",
    "sg:city":"Cranbrook",
    "sg:classifiers":[
        {
            "category":"Building & Trades",
            "subcategory":"Construction",
            "type":"Services"
        }
    ],
    "sg:phone":"+44 1580 241605",
    "sg:postcode":"TN17 4BZ",
    "sg:province":"Kent",
    "sg:tags":[
        "builder"
    ],
    "wof:name":"S F Webb",
    "wof:placetype":"venue"
},
  "geometry": {"coordinates":[0.5806949735,51.0668716431],"type":"Point"}
}