{
  "type": "Feature",
  "properties": {
    "iso:country":"GB",
    "sg:address":"Cherry Tree Walk, Ranskill",
    "sg:city":"Retford",
    "sg:classifiers":[
        {
            "category":"Government",
            "subcategory":"Office",
            "type":"Public Place"
        }
    ],
    "sg:postcode":"DN22 8LH",
    "sg:province":"Nottinghamshire",
    "sg:tags":[
        "local"
    ],
    "wof:name":"Ranskill Primary School",
    "wof:placetype":"venue"
},
  "geometry": {"coordinates":[-1.013329,53.384106],"type":"Point"}
}