{
  "type": "Feature",
  "properties": {
    "addr:full":"1 Croft Stairs Newcastle-upon-tyne Tyne and Wear NE1 2HG",
    "addr:housenumber":"1",
    "addr:postcode":"ne1 2hg",
    "addr:street":"Croft Stairs",
    "iso:country":"GB",
    "sg:address":"1 Croft Stairs",
    "sg:city":"Newcastle-upon-tyne",
    "sg:classifiers":[
        {
            "category":"Professional",
            "subcategory":"Accounting & Tax Preparation",
            "type":"Services"
        }
    ],
    "sg:phone":"+44 191 232 7834",
    "sg:postcode":"NE1 2HG",
    "sg:province":"Tyne and Wear",
    "sg:tags":[
        "accountant"
    ],
    "wof:name":"Grant Williamson",
    "wof:placetype":"venue"
},
  "geometry": {"coordinates":[-1.6062890291,54.9712409973],"type":"Point"}
}