{
  "type": "Feature",
  "properties": {
    "iso:country":"GB",
    "sg:address":"155a Brighton Road",
    "sg:city":"Coulsdon",
    "sg:classifiers":[
        {
            "category":"Military Area",
            "subcategory":"Air Force Base",
            "type":"Public Place"
        }
    ],
    "sg:phone":"+44 20 8668 4545",
    "sg:postcode":"CR5 2NH",
    "sg:province":"Surrey",
    "sg:tags":[
        "taxi",
        "hire",
        "private"
    ],
    "wof:name":"Admiral Car Hire",
    "wof:placetype":"venue"
},
  "geometry": {"coordinates":[-0.1377439946,51.3210716248],"type":"Point"}
}