{
  "type": "Feature",
  "properties": {
    "addr:full":"22 The Chare Peterlee Durham SR8 1AE",
    "addr:housenumber":"22",
    "addr:postcode":"sr8 1ae",
    "addr:street":"The Chare",
    "iso:country":"GB",
    "sg:address":"22 The Chare",
    "sg:city":"Peterlee",
    "sg:classifiers":[
        {
            "category":"Food & Beverages",
            "subcategory":"Fruits & Vegetables",
            "type":"Retail Goods"
        }
    ],
    "sg:phone":"+44 191 586 0603",
    "sg:postcode":"SR8 1AE",
    "sg:province":"Durham",
    "sg:tags":[
        "greengrocer"
    ],
    "wof:name":"A Bookless & Co. Ltd.",
    "wof:placetype":"venue"
},
  "geometry": {"coordinates":[-1.3492219448,54.7454032898],"type":"Point"}
}