{
  "type": "Feature",
  "properties": {
    "addr:full":"Botolph Claydon Buckingham Buckinghamshire MK18 2LR",
    "addr:postcode":"mk18 2lr",
    "iso:country":"GB",
    "sg:address":"Botolph Claydon",
    "sg:city":"Buckingham",
    "sg:classifiers":[
        {
            "category":"Shopping",
            "subcategory":"Pharmacy",
            "type":"Retail Goods"
        }
    ],
    "sg:phone":"+44 1296 714222",
    "sg:postcode":"MK18 2LR",
    "sg:province":"Buckinghamshire",
    "sg:tags":[
        "medical"
    ],
    "wof:name":"Tcs Biosciences Ltd.",
    "wof:placetype":"venue"
},
  "geometry": {"coordinates":[-0.93401,51.91613],"type":"Point"}
}