{
  "type": "Feature",
  "properties": {
    "iso:country":"GB",
    "sg:address":"Unit 1 19-21 London Road",
    "sg:city":"Hinckley",
    "sg:classifiers":[
        {
            "category":"Freight",
            "type":"Transportation"
        }
    ],
    "sg:phone":"+44 1455 611117",
    "sg:postcode":"LE10 1HQ",
    "sg:province":"Leicestershire",
    "sg:tags":[
        "haulage",
        "road"
    ],
    "wof:name":"Colin Burrett",
    "wof:placetype":"venue"
},
  "geometry": {"coordinates":[-1.364931941,52.5417900085],"type":"Point"}
}