{
  "type": "Feature",
  "properties": {
    "addr:full":"198 Barton Street Gloucester Gloucestershire GL1 4HE",
    "addr:housenumber":"198",
    "addr:postcode":"gl1 4he",
    "addr:street":"Barton Street",
    "iso:country":"GB",
    "sg:address":"198 Barton Street",
    "sg:city":"Gloucester",
    "sg:classifiers":[
        {
            "category":"Personal",
            "subcategory":"Tattoo Parlor",
            "type":"Services"
        }
    ],
    "sg:phone":"+44 1452 418410",
    "sg:postcode":"GL1 4HE",
    "sg:province":"Gloucestershire",
    "sg:tags":[
        "tattooing",
        "piercing",
        "artist"
    ],
    "wof:name":"Bob's Tattooist",
    "wof:placetype":"venue"
},
  "geometry": {"coordinates":[-2.233993,51.859001],"type":"Point"}
}