{
  "type": "Feature",
  "properties": {
    "addr:full":"9-11 Church Street Twickenham Greater London TW1 3NJ",
    "addr:housenumber":"9-11",
    "addr:postcode":"tw1 3nj",
    "addr:street":"Church Street",
    "iso:country":"GB",
    "sg:address":"9-11 Church Street",
    "sg:city":"Twickenham",
    "sg:classifiers":[
        {
            "category":"Bars & Pubs",
            "type":"Food & Drink"
        }
    ],
    "sg:phone":"+44 20 8891 1717",
    "sg:postcode":"TW1 3NJ",
    "sg:province":"Greater London",
    "sg:tags":[
        "pubs",
        "inn"
    ],
    "wof:name":"The Eel Pie Pub",
    "wof:placetype":"venue"
},
  "geometry": {"coordinates":[-0.3264369965,51.4470787048],"type":"Point"}
}