{
  "type": "Feature",
  "properties": {
    "addr:full":"178 Reevy Avenue Bradford West Yorkshire BD6 3RP",
    "addr:housenumber":"178",
    "addr:postcode":"bd6 3rp",
    "addr:street":"Reevy Avenue",
    "iso:country":"GB",
    "sg:address":"178 Reevy Avenue",
    "sg:city":"Bradford",
    "sg:classifiers":[
        {
            "category":"Retail",
            "subcategory":"Driving School",
            "type":"Services"
        }
    ],
    "sg:phone":"+44 1274 674661",
    "sg:postcode":"BD6 3RP",
    "sg:province":"West Yorkshire",
    "wof:name":"Professional School of Motoring",
    "wof:placetype":"venue"
},
  "geometry": {"coordinates":[-1.7922739983,53.7617683411],"type":"Point"}
}