{
  "type": "Feature",
  "properties": {
    "addr:full":"273 London Road Greenhithe Kent DA9 9DB",
    "addr:housenumber":"273",
    "addr:postcode":"da9 9db",
    "addr:street":"London Road",
    "iso:country":"GB",
    "sg:address":"273 London Road",
    "sg:city":"Greenhithe",
    "sg:classifiers":[
        {
            "category":"Health Services",
            "subcategory":"Doctor",
            "type":"Services"
        }
    ],
    "sg:phone":"+44 1322 382010",
    "sg:postcode":"DA9 9DB",
    "sg:province":"Kent",
    "sg:tags":[
        "practitioners"
    ],
    "wof:name":"North Kent Health Care N H S Trust",
    "wof:placetype":"venue"
},
  "geometry": {"coordinates":[0.2629989982,51.4461402893],"type":"Point"}
}