{
  "type": "Feature",
  "properties": {
    "addr:full":"337 Kentish Town Road London Greater London NW5 2TJ",
    "addr:housenumber":"337",
    "addr:postcode":"nw5 2tj",
    "addr:street":"Kentish Town Road",
    "iso:country":"GB",
    "sg:address":"337 Kentish Town Road",
    "sg:city":"London",
    "sg:classifiers":[
        {
            "category":"Fast Food",
            "type":"Food & Drink"
        }
    ],
    "sg:phone":"+44 20 7284 4504",
    "sg:postcode":"NW5 2TJ",
    "sg:province":"Greater London",
    "sg:tags":[
        "away",
        "take"
    ],
    "wof:name":"Chicken Express American Fried Chicken Ltd.",
    "wof:placetype":"venue"
},
  "geometry": {"coordinates":[-0.1407089978,51.5512084961],"type":"Point"}
}