{
  "type": "Feature",
  "properties": {
    "addr:full":"Farrowby Farm, Hinxworth Baldock Bedfordshire SG7 5EY",
    "addr:postcode":"sg7 5ey",
    "iso:country":"GB",
    "sg:address":"Farrowby Farm, Hinxworth",
    "sg:city":"Baldock",
    "sg:classifiers":[
        {
            "category":"Deli",
            "type":"Food & Drink"
        }
    ],
    "sg:phone":"+44 1462 733700",
    "sg:postcode":"SG7 5EY",
    "sg:province":"Bedfordshire",
    "sg:tags":[
        "delicatessen"
    ],
    "wof:name":"Ashwell Delicatessen",
    "wof:placetype":"venue"
},
  "geometry": {"coordinates":[-0.199899,52.049484],"type":"Point"}
}