{
  "type": "Feature",
  "properties": {
    "addr:full":"Ynys Bridge, Heol Yr Ynys Cardiff Caerphilly CF15 7NT",
    "addr:postcode":"cf15 7nt",
    "addr:street":"Ynys Bridge Heol Yr Ynys",
    "iso:country":"GB",
    "sg:address":"Ynys Bridge, Heol Yr Ynys",
    "sg:city":"Cardiff",
    "sg:classifiers":[
        {
            "category":"Home & Garden",
            "subcategory":"Household Appliances",
            "type":"Retail Goods"
        }
    ],
    "sg:phone":"+44 29 2081 3131",
    "sg:postcode":"CF15 7NT",
    "sg:province":"Caerphilly",
    "sg:tags":[
        "refrigeration",
        "air conditioning"
    ],
    "wof:name":"R V S Management Services Ltd.",
    "wof:placetype":"venue"
},
  "geometry": {"coordinates":[-3.25727,51.534039],"type":"Point"}
}