{
  "type": "Feature",
  "properties": {
    "addr:full":"20 Market Place, Long Buckby Northampton Northamptonshire NN6 7RR",
    "addr:housenumber":"20",
    "addr:postcode":"nn6 7rr",
    "addr:street":"Market Place",
    "iso:country":"GB",
    "sg:address":"20 Market Place, Long Buckby",
    "sg:city":"Northampton",
    "sg:classifiers":[
        {
            "category":"Insurance",
            "subcategory":"Insurance Agent",
            "type":"Services"
        }
    ],
    "sg:phone":"+44 1327 842529",
    "sg:postcode":"NN6 7RR",
    "sg:province":"Northamptonshire",
    "sg:tags":[
        "broker"
    ],
    "wof:name":"L BALL",
    "wof:placetype":"venue"
},
  "geometry": {"coordinates":[-1.079871,52.30262],"type":"Point"}
}