{
  "type": "Feature",
  "properties": {
    "addr:full":"13 Woodhouse Gro London Greater London E12 6SR",
    "addr:housenumber":"13",
    "addr:postcode":"e12 6sr",
    "addr:street":"Woodhouse Gro",
    "iso:country":"GB",
    "sg:address":"13 Woodhouse Gro",
    "sg:city":"London",
    "sg:classifiers":[
        {
            "category":"Shopping",
            "subcategory":"Clothing, Apparel, & Fashions",
            "type":"Retail Goods"
        }
    ],
    "sg:phone":"+44 20 8471 0453",
    "sg:postcode":"E12 6SR",
    "sg:province":"Greater London",
    "sg:tags":[
        "sportswear"
    ],
    "wof:name":"Magzs Group Industries",
    "wof:placetype":"venue"
},
  "geometry": {"coordinates":[0.0480570011,51.5409126282],"type":"Point"}
}