{
  "type": "Feature",
  "properties": {
    "iso:country":"GB",
    "sg:address":"986 Camarthen Road, Fforestfach",
    "sg:city":"Swansea",
    "sg:classifiers":[
        {
            "category":"Professional",
            "subcategory":"Engineering",
            "type":"Services"
        },
        {
            "category":"Building & Trades",
            "subcategory":"Construction",
            "type":"Services"
        }
    ],
    "sg:phone":"+44 1792 561522",
    "sg:postcode":"SA5 4AE",
    "sg:province":"Swansea",
    "sg:tags":[
        "civil",
        "engineer",
        "driveway",
        "paving",
        "contractor"
    ],
    "wof:name":"West Glamorgan Landscapes",
    "wof:placetype":"venue"
},
  "geometry": {"coordinates":[-3.989019,51.645512],"type":"Point"}
}