{
  "type": "Feature",
  "properties": {
    "iso:country":"GB",
    "sg:address":"30 Eastway Rd",
    "sg:city":"Wigston",
    "sg:classifiers":[
        {
            "category":"Professional",
            "subcategory":"Secretarial Services",
            "type":"Services"
        }
    ],
    "sg:phone":"+44 116 288 1452",
    "sg:postcode":"LE18 1NH",
    "sg:province":"Leicestershire",
    "wof:name":"B C Hardy",
    "wof:placetype":"venue"
},
  "geometry": {"coordinates":[-1.1024249792,52.5918617249],"type":"Point"}
}