{
  "type": "Feature",
  "properties": {
    "iso:country":"GB",
    "sg:address":"19-21 Lightbody Street",
    "sg:city":"Liverpool",
    "sg:classifiers":[
        {
            "category":"Building & Trades",
            "subcategory":"Construction",
            "type":"Services"
        }
    ],
    "sg:phone":"+44 151 207 2057",
    "sg:postcode":"L5 9UU",
    "sg:province":"Merseyside",
    "sg:tags":[
        "demolition",
        "contractor"
    ],
    "wof:name":"J Doyle & Co. (Demolition) Ltd.",
    "wof:placetype":"venue"
},
  "geometry": {"coordinates":[-2.995399,53.422497],"type":"Point"}
}