{
  "type": "Feature",
  "properties": {
    "addr:full":"Remus House, Coltsfoot Drive, Woodston Peterborough Cambridgeshire PE2 9JX",
    "addr:postcode":"pe2 9jx",
    "addr:street":"Coltsfoot Drive",
    "iso:country":"GB",
    "sg:address":"Remus House, Coltsfoot Drive, Woodston",
    "sg:city":"Peterborough",
    "sg:classifiers":[
        {
            "category":"Shopping",
            "subcategory":"Books",
            "type":"Retail Goods"
        },
        {
            "category":"Wholesale",
            "subcategory":"Books, Periodicals, & Newspapers",
            "type":"Manufacturing & Wholesale Goods"
        }
    ],
    "sg:phone":"+44 1733 313524",
    "sg:postcode":"PE2 9JX",
    "sg:province":"Cambridgeshire",
    "sg:tags":[
        "publisher"
    ],
    "wof:name":"Poetry Now",
    "wof:placetype":"venue"
},
  "geometry": {"coordinates":[-0.258704,52.561279],"type":"Point"}
}