{
  "type": "Feature",
  "properties": {
    "iso:country":"GB",
    "sg:address":"228 St.johns Road",
    "sg:city":"Tunbridge Wells",
    "sg:classifiers":[
        {
            "category":"Professional",
            "subcategory":"Computer Services",
            "type":"Services"
        }
    ],
    "sg:postcode":"TN4 9XD",
    "sg:province":"Kent",
    "sg:tags":[
        "system",
        "software"
    ],
    "wof:name":"Heraldtech Ltd",
    "wof:placetype":"venue"
},
  "geometry": {"coordinates":[0.262081,51.14978],"type":"Point"}
}