{
  "type": "Feature",
  "properties": {
    "addr:full":"Merry Orchard Cottage, Cowesfield Salisbury Dorset SP5 2RB",
    "addr:postcode":"sp5 2rb",
    "addr:street":"Merry;Cowesfield",
    "iso:country":"GB",
    "sg:address":"Merry Orchard Cottage, Cowesfield",
    "sg:city":"Salisbury",
    "sg:classifiers":[
        {
            "category":"Sports & Exercise",
            "subcategory":"Skate Park",
            "type":"Entertainment"
        }
    ],
    "sg:phone":"+44 1794 884772",
    "sg:postcode":"SP5 2RB",
    "sg:province":"Dorset",
    "sg:tags":[
        "mushroom"
    ],
    "wof:name":"Merry Orchard Mushrooms",
    "wof:placetype":"venue"
},
  "geometry": {"coordinates":[-1.61866,51.009289],"type":"Point"}
}