{
  "type": "Feature",
  "properties": {
    "addr:full":"235 Torquay Road Paignton Devon TQ3 2HW",
    "addr:housenumber":"235",
    "addr:postcode":"tq3 2hw",
    "addr:street":"Torquay Road",
    "iso:country":"GB",
    "sg:address":"235 Torquay Road",
    "sg:city":"Paignton",
    "sg:classifiers":[
        {
            "category":"Food & Beverages",
            "subcategory":"Liquor & Beverages",
            "type":"Retail Goods"
        }
    ],
    "sg:phone":"+44 1803 559073",
    "sg:postcode":"TQ3 2HW",
    "sg:province":"Devon",
    "sg:tags":[
        "beer",
        "spirit",
        "wines"
    ],
    "wof:name":"Manor Wine Stores",
    "wof:placetype":"venue"
},
  "geometry": {"coordinates":[-3.5637490749,50.4441604614],"type":"Point"}
}