{
  "type": "Feature",
  "properties": {
    "addr:full":"4 Woodside Preston Lancashire PR25 4GT",
    "addr:housenumber":"4",
    "addr:postcode":"pr25 4gt",
    "addr:street":"Woodside Preston",
    "iso:country":"GB",
    "sg:address":"4 Woodside",
    "sg:city":"Preston",
    "sg:classifiers":[
        {
            "category":"Food & Beverages",
            "subcategory":"Liquor & Beverages",
            "type":"Retail Goods"
        }
    ],
    "sg:phone":"+44 1772 424319",
    "sg:postcode":"PR25 4GT",
    "sg:province":"Lancashire",
    "sg:tags":[
        "beer",
        "spirit",
        "wines"
    ],
    "wof:name":"The Pullman Wine Co. Ltd.",
    "wof:placetype":"venue"
},
  "geometry": {"coordinates":[-2.7106840611,53.7794265747],"type":"Point"}
}