{
  "type": "Feature",
  "properties": {
    "iso:country":"GB",
    "sg:address":"30 Lion Yard",
    "sg:city":"Cambridge",
    "sg:classifiers":[
        {
            "category":"Shopping",
            "subcategory":"Clothing, Apparel, & Fashions",
            "type":"Retail Goods"
        }
    ],
    "sg:phone":"+44 1223 369274",
    "sg:postcode":"CB2 3NA",
    "sg:province":"Cambridgeshire",
    "sg:tags":[
        "shop"
    ],
    "wof:name":"Evans Ltd",
    "wof:placetype":"venue"
},
  "geometry": {"coordinates":[0.121509,52.204922],"type":"Point"}
}