{
  "type": "Feature",
  "properties": {
    "addr:full":"High Street, Loscoe Heanor Derbyshire DE75 7LE",
    "addr:postcode":"de75 7le",
    "addr:street":"High Street",
    "iso:country":"GB",
    "sg:address":"High Street, Loscoe",
    "sg:city":"Heanor",
    "sg:classifiers":[
        {
            "category":"Bars & Pubs",
            "type":"Food & Drink"
        },
        {
            "category":"Community Center",
            "subcategory":"Social",
            "type":"Public Place"
        }
    ],
    "sg:phone":"+44 1773 713862",
    "sg:postcode":"DE75 7LE",
    "sg:province":"Derbyshire",
    "sg:tags":[
        "pubs",
        "house",
        "inn",
        "activity"
    ],
    "wof:name":"The Eclipse Inn",
    "wof:placetype":"venue"
},
  "geometry": {"coordinates":[-1.3598639965,53.0162696838],"type":"Point"}
}