{
  "type": "Feature",
  "properties": {
    "addr:full":"Windmill Lane, Denton Manchester Greater Manchester M34 3RB",
    "addr:postcode":"m34 3rb",
    "addr:street":"Windmill Lane",
    "iso:country":"GB",
    "sg:address":"Windmill Lane, Denton",
    "sg:city":"Manchester",
    "sg:classifiers":[
        {
            "category":"Home & Garden",
            "subcategory":"Building Materials",
            "type":"Retail Goods"
        }
    ],
    "sg:postcode":"M34 3RB",
    "sg:province":"Greater Manchester",
    "sg:tags":[
        "access",
        "equipment"
    ],
    "wof:name":"Nationwide Access Ltd.",
    "wof:placetype":"venue"
},
  "geometry": {"coordinates":[-2.122496,53.455463],"type":"Point"}
}