{
  "type": "Feature",
  "properties": {
    "iso:country":"GB",
    "sg:address":"Old Station Yard, Llantwit Fardre",
    "sg:city":"Pontypridd",
    "sg:classifiers":[
        {
            "category":"Health Services",
            "subcategory":"Nursing And Care Facility",
            "type":"Services"
        },
        {
            "category":"Social Services",
            "subcategory":"Retirement Home",
            "type":"Services"
        }
    ],
    "sg:phone":"+44 1443 206329",
    "sg:postcode":"CF38 2LZ",
    "sg:province":"Rhondda, Cynon, Taff",
    "sg:tags":[
        "residential"
    ],
    "wof:name":"Penrhos Residential Home",
    "wof:placetype":"venue"
},
  "geometry": {"coordinates":[-3.33397,51.557659],"type":"Point"}
}