{
  "type": "Feature",
  "properties": {
    "addr:full":"Unit 1 Fulmer Brae, Lanedywell Livingston West Lothian EH54 6AB",
    "addr:housenumber":"unit 1",
    "addr:postcode":"eh54 6ab",
    "addr:street":"Fulmer Brae Lanedywell",
    "iso:country":"GB",
    "sg:address":"Unit 1 Fulmer Brae, Lanedywell",
    "sg:city":"Livingston",
    "sg:classifiers":[
        {
            "category":"Fast Food",
            "type":"Food & Drink"
        }
    ],
    "sg:phone":"+44 1506 413141",
    "sg:postcode":"EH54 6AB",
    "sg:province":"West Lothian",
    "sg:tags":[
        "away",
        "take"
    ],
    "wof:name":"Cafe Shabaz",
    "wof:placetype":"venue"
},
  "geometry": {"coordinates":[-3.5098340511,55.8862457275],"type":"Point"}
}