{
  "type": "Feature",
  "properties": {
    "addr:full":"Winston Hall, 20 East Park Rd Blackburn Lancashire BB1 8BB",
    "addr:housenumber":"20",
    "addr:postcode":"bb1 8bb",
    "addr:street":"East Park Rd",
    "iso:country":"GB",
    "sg:address":"Winston Hall, 20 East Park Rd",
    "sg:city":"Blackburn",
    "sg:classifiers":[
        {
            "category":"Professional",
            "subcategory":"Advertising",
            "type":"Services"
        }
    ],
    "sg:phone":"+44 1254 681808",
    "sg:postcode":"BB1 8BB",
    "sg:province":"Lancashire",
    "sg:tags":[
        "agency"
    ],
    "wof:name":"Danz Marketing Ltd",
    "wof:placetype":"venue"
},
  "geometry": {"coordinates":[-2.480399,53.748516],"type":"Point"}
}