{
  "type": "Feature",
  "properties": {
    "addr:full":"437 Hornsey Rd London Greater London N19 4DF",
    "addr:housenumber":"437",
    "addr:postcode":"n19 4df",
    "addr:street":"Hornsey Rd",
    "iso:country":"GB",
    "sg:address":"437 Hornsey Rd",
    "sg:city":"London",
    "sg:classifiers":[
        {
            "category":"Fast Food",
            "type":"Food & Drink"
        }
    ],
    "sg:postcode":"N19 4DF",
    "sg:province":"Greater London",
    "sg:tags":[
        "away",
        "take"
    ],
    "wof:name":"Hamlet",
    "wof:placetype":"venue"
},
  "geometry": {"coordinates":[-0.122376,51.567169],"type":"Point"}
}