{
  "type": "Feature",
  "properties": {
    "addr:full":"Aston Hall Stone Staffordshire ST15 0BJ",
    "addr:postcode":"st15 0bj",
    "addr:street":"Aston",
    "iso:country":"GB",
    "sg:address":"Aston Hall",
    "sg:city":"Stone",
    "sg:classifiers":[
        {
            "category":"Place Of Worship",
            "type":"Public Place"
        }
    ],
    "sg:phone":"+44 1785 811502",
    "sg:postcode":"ST15 0BJ",
    "sg:province":"Staffordshire",
    "wof:name":"Holy Micheal Archangel R C Church",
    "wof:placetype":"venue"
},
  "geometry": {"coordinates":[-2.1278860569,52.8777122498],"type":"Point"}
}