{
  "type": "Feature",
  "properties": {
    "iso:country":"GB",
    "sg:address":"35 St Leonards Avenue",
    "sg:city":"Bedford",
    "sg:classifiers":[
        {
            "category":"Building & Trades",
            "subcategory":"Construction",
            "type":"Services"
        }
    ],
    "sg:phone":"+44 1234 266857",
    "sg:postcode":"MK42 0RB",
    "sg:province":"Bedfordshire",
    "sg:tags":[
        "joiner",
        "carpenter"
    ],
    "wof:name":"Jonathan D Wells",
    "wof:placetype":"venue"
},
  "geometry": {"coordinates":[-0.4639410079,52.128616333],"type":"Point"}
}