{
  "type": "Feature",
  "properties": {
    "addr:full":"Pasture Street Grimsby Lincolnshire DN32 9AB",
    "addr:postcode":"dn32 9ab",
    "addr:street":"Pasture Street",
    "iso:country":"GB",
    "sg:address":"Pasture Street",
    "sg:city":"Grimsby",
    "sg:classifiers":[
        {
            "category":"Recreation",
            "type":"Entertainment"
        }
    ],
    "sg:phone":"+44 1472 362707",
    "sg:postcode":"DN32 9AB",
    "sg:province":"Lincolnshire",
    "sg:tags":[
        "snooker",
        "billiards",
        "pool"
    ],
    "wof:name":"Grimsby Snooker Club",
    "wof:placetype":"venue"
},
  "geometry": {"coordinates":[-0.0772140026,53.5656394958],"type":"Point"}
}