{
  "type": "Feature",
  "properties": {
    "addr:full":"Eastgate Peebles Scottish Borders EH45 8AD",
    "addr:postcode":"eh45 8ad",
    "addr:street":"Eastgate",
    "iso:country":"GB",
    "sg:address":"Eastgate",
    "sg:city":"Peebles",
    "sg:classifiers":[
        {
            "category":"Place Of Worship",
            "type":"Public Place"
        },
        {
            "category":"Organizations",
            "subcategory":"Non-profit Organization",
            "type":"Services"
        }
    ],
    "sg:phone":"+44 1721 723121",
    "sg:postcode":"EH45 8AD",
    "sg:province":"Scottish Borders",
    "sg:tags":[
        "charitable",
        "organisation",
        "charity"
    ],
    "wof:name":"ST ANDREWS LECKIE MEMORIAL PARISH CHURCH",
    "wof:placetype":"venue"
},
  "geometry": {"coordinates":[-3.188191,55.652065],"type":"Point"}
}