{
  "type": "Feature",
  "properties": {
    "addr:full":"Corthan Crescent Aberdeen Aberdeen City AB12 5BB",
    "addr:postcode":"ab12 5bb",
    "addr:street":"Corthan Crescent",
    "iso:country":"GB",
    "sg:address":"Corthan Crescent",
    "sg:city":"Aberdeen",
    "sg:classifiers":[
        {
            "category":"Government",
            "subcategory":"Office",
            "type":"Public Place"
        },
        {
            "category":"Community Center",
            "type":"Public Place"
        },
        {
            "category":"Arena",
            "subcategory":"Sports Club",
            "type":"Entertainment"
        }
    ],
    "sg:phone":"+44 1224 879759",
    "sg:postcode":"AB12 5BB",
    "sg:province":"Aberdeen City",
    "sg:tags":[
        "recreation",
        "local",
        "leisure",
        "centre"
    ],
    "wof:name":"Kincorth Sports Centre",
    "wof:placetype":"venue"
},
  "geometry": {"coordinates":[-2.1011550426,57.1232070923],"type":"Point"}
}