{
  "type": "Feature",
  "properties": {
    "iso:country":"GB",
    "sg:address":"120 London Road, Long Sutton",
    "sg:city":"Spalding",
    "sg:classifiers":[
        {
            "category":"Home & Garden",
            "subcategory":"Home Furnishings",
            "type":"Retail Goods"
        },
        {
            "category":"Building & Trades",
            "subcategory":"Landfill",
            "type":"Services"
        }
    ],
    "sg:phone":"+44 1406 364447",
    "sg:postcode":"PE12 9EE",
    "sg:province":"Cambridgeshire",
    "sg:tags":[
        "blind",
        "awning",
        "canopy",
        "blinds"
    ],
    "wof:name":"Solo Window Blinds",
    "wof:placetype":"venue"
},
  "geometry": {"coordinates":[0.129371,52.780949],"type":"Point"}
}