{
  "type": "Feature",
  "properties": {
    "addr:full":"24-26 Priory Road Liverpool Merseyside L4 2RY",
    "addr:housenumber":"24-26",
    "addr:postcode":"l4 2ry",
    "addr:street":"Priory Road",
    "iso:country":"GB",
    "sg:address":"24-26 Priory Road",
    "sg:city":"Liverpool",
    "sg:classifiers":[
        {
            "category":"Food & Beverages",
            "subcategory":"Liquor & Beverages",
            "type":"Retail Goods"
        }
    ],
    "sg:phone":"+44 151 263 1127",
    "sg:postcode":"L4 2RY",
    "sg:province":"Merseyside",
    "sg:tags":[
        "beer",
        "spirit",
        "wines"
    ],
    "wof:name":"Drinks Cabin",
    "wof:placetype":"venue"
},
  "geometry": {"coordinates":[-2.950665,53.42907],"type":"Point"}
}