{
  "type": "Feature",
  "properties": {
    "addr:full":"95 Salisbury Road Andover Hampshire SP10 2LN",
    "addr:housenumber":"95",
    "addr:postcode":"sp10 2ln",
    "addr:street":"Salisbury Road",
    "iso:country":"GB",
    "sg:address":"95 Salisbury Road",
    "sg:city":"Andover",
    "sg:classifiers":[
        {
            "category":"Building & Trades",
            "subcategory":"Plumbing",
            "type":"Services"
        }
    ],
    "sg:postcode":"SP10 2LN",
    "sg:province":"Hampshire",
    "sg:tags":[
        "central",
        "heating"
    ],
    "wof:name":"P A Wise",
    "wof:placetype":"venue"
},
  "geometry": {"coordinates":[-1.4984929562,51.2018890381],"type":"Point"}
}