{
  "type": "Feature",
  "properties": {
    "addr:full":"34 Glenavon Rd Birkenhead Merseyside L43 0RE",
    "addr:housenumber":"34",
    "addr:postcode":"l43 0re",
    "addr:street":"Glenavon Rd",
    "iso:country":"GB",
    "sg:address":"34 Glenavon Rd",
    "sg:city":"Birkenhead",
    "sg:classifiers":[
        {
            "category":"Organizations",
            "subcategory":"Non-profit Organization",
            "type":"Services"
        }
    ],
    "sg:phone":"+44 151 608 0588",
    "sg:postcode":"L43 0RE",
    "sg:province":"Merseyside",
    "sg:tags":[
        "organisation",
        "voluntary",
        "charity"
    ],
    "wof:name":"Dewan Iqbal Foundation",
    "wof:placetype":"venue"
},
  "geometry": {"coordinates":[-3.0488409996,53.3694076538],"type":"Point"}
}