{
  "type": "Feature",
  "properties": {
    "iso:country":"GB",
    "sg:address":"69 Worthing Road, Rustington",
    "sg:city":"Littlehampton",
    "sg:classifiers":[
        {
            "category":"Wholesale",
            "subcategory":"Machinery & Supplies",
            "type":"Manufacturing & Wholesale Goods"
        }
    ],
    "sg:phone":"+44 1903 775138",
    "sg:postcode":"BN16 3JU",
    "sg:province":"West Sussex",
    "sg:tags":[
        "industrial",
        "commercial"
    ],
    "wof:name":"Crimptech International Ltd.",
    "wof:placetype":"venue"
},
  "geometry": {"coordinates":[-0.506718,50.816849],"type":"Point"}
}