{
  "type": "Feature",
  "properties": {
    "iso:country":"GB",
    "sg:address":"45 Market Pl",
    "sg:city":"Thirsk",
    "sg:classifiers":[
        {
            "category":"Food & Beverages",
            "subcategory":"Bakery",
            "type":"Retail Goods"
        }
    ],
    "sg:postcode":"YO7 1HA",
    "sg:province":"North Yorkshire",
    "sg:tags":[
        "baker"
    ],
    "wof:name":"Thomas of York Ltd",
    "wof:placetype":"venue"
},
  "geometry": {"coordinates":[-1.3432450294,54.2328567505],"type":"Point"}
}