{
  "type": "Feature",
  "properties": {
    "addr:full":"26 Deverell Clo Bradford-on-avon Wiltshire BA15 1UZ",
    "addr:housenumber":"26",
    "addr:postcode":"ba15 1uz",
    "addr:street":"Deverell Clo Bradford-On-Avon",
    "iso:country":"GB",
    "sg:address":"26 Deverell Clo",
    "sg:city":"Bradford-on-avon",
    "sg:classifiers":[
        {
            "category":"Organizations",
            "subcategory":"Non-profit Organization",
            "type":"Services"
        }
    ],
    "sg:phone":"+44 1225 865609",
    "sg:postcode":"BA15 1UZ",
    "sg:province":"Wiltshire",
    "sg:tags":[
        "organisation",
        "voluntary",
        "charity"
    ],
    "wof:name":"Link",
    "wof:placetype":"venue"
},
  "geometry": {"coordinates":[-2.2427110672,51.3380050659],"type":"Point"}
}