{
  "type": "Feature",
  "properties": {
    "addr:full":"Gearmesh Centre, Factory Rd, Blaydonhaugh Indstl Est Gateshead Tyne and Wear NE21 5SA",
    "addr:postcode":"ne21 5sa",
    "addr:street":"Factory Rd;Indstl Est",
    "iso:country":"GB",
    "sg:address":"Gearmesh Centre, Factory Rd, Blaydonhaugh Indstl Est",
    "sg:city":"Gateshead",
    "sg:classifiers":[
        {
            "category":"Professional",
            "subcategory":"Engineering",
            "type":"Services"
        }
    ],
    "sg:postcode":"NE21 5SA",
    "sg:province":"Tyne and Wear",
    "wof:name":"Contract Site Services Ltd",
    "wof:placetype":"venue"
},
  "geometry": {"coordinates":[-1.7051000595,54.9665603638],"type":"Point"}
}