{
  "type": "Feature",
  "properties": {
    "addr:full":"The Dunvant 234 Dunvant Rd, Dunvant Swansea Swansea SA2 7SR",
    "addr:housenumber":"234",
    "addr:postcode":"sa2 7sr",
    "addr:street":"Dunvant Rd",
    "iso:country":"GB",
    "sg:address":"The Dunvant 234 Dunvant Rd, Dunvant",
    "sg:city":"Swansea",
    "sg:classifiers":[
        {
            "category":"Bars & Pubs",
            "type":"Food & Drink"
        }
    ],
    "sg:phone":"+44 1792 208112",
    "sg:postcode":"SA2 7SR",
    "sg:province":"Swansea",
    "sg:tags":[
        "pubs",
        "inn"
    ],
    "wof:name":"Hungry Horse",
    "wof:placetype":"venue"
},
  "geometry": {"coordinates":[-4.037805,51.626015],"type":"Point"}
}