{
  "type": "Feature",
  "properties": {
    "addr:full":"2 Dolforgan Hall, Kerry Newtown Powys SY16 4DN",
    "addr:housenumber":"2",
    "addr:postcode":"sy16 4dn",
    "addr:street":"Dolforgan Hall Kerry",
    "iso:country":"GB",
    "sg:address":"2 Dolforgan Hall, Kerry",
    "sg:city":"Newtown",
    "sg:classifiers":[
        {
            "category":"Freight",
            "type":"Transportation"
        }
    ],
    "sg:phone":"+44 1686 670496",
    "sg:postcode":"SY16 4DN",
    "sg:province":"Powys",
    "sg:tags":[
        "haulage",
        "road"
    ],
    "wof:name":"Russel J Francis",
    "wof:placetype":"venue"
},
  "geometry": {"coordinates":[-3.2594239712,52.5011482239],"type":"Point"}
}