{
  "type": "Feature",
  "properties": {
    "iso:country":"GB",
    "sg:address":"39 Lavant Street",
    "sg:city":"Petersfield",
    "sg:classifiers":[
        {
            "category":"Real Estate",
            "subcategory":"Surveying",
            "type":"Services"
        }
    ],
    "sg:phone":"+44 1730 231390",
    "sg:postcode":"GU32 3EL",
    "sg:province":"Hampshire",
    "sg:tags":[
        "building",
        "surveyor"
    ],
    "wof:name":"Richard Glover",
    "wof:placetype":"venue"
},
  "geometry": {"coordinates":[-0.939986,51.006077],"type":"Point"}
}