{
  "type": "Feature",
  "properties": {
    "iso:country":"GB",
    "sg:address":"Lombard Road, Merton",
    "sg:city":"London",
    "sg:classifiers":[
        {
            "category":"Autos & Motor Vehicles",
            "subcategory":"Auto Supplies",
            "type":"Retail Goods"
        }
    ],
    "sg:phone":"+44 20 8542 1181",
    "sg:postcode":"SW19 3XB",
    "sg:province":"Greater London",
    "sg:tags":[
        "electric"
    ],
    "wof:name":"Watliff Co. Ltd.",
    "wof:placetype":"venue"
},
  "geometry": {"coordinates":[-0.192112,51.409637],"type":"Point"}
}