{
  "type": "Feature",
  "properties": {
    "iso:country":"GB",
    "sg:address":"High Royd Farm",
    "sg:city":"Hebden Bridge",
    "sg:classifiers":[
        {
            "category":"Farming",
            "subcategory":"Livestock Farm",
            "type":"Manufacturing & Wholesale Goods"
        }
    ],
    "sg:postcode":"HX7 8PH",
    "sg:province":"West Yorkshire",
    "sg:tags":[
        "others"
    ],
    "wof:name":"E Pickles & Son",
    "wof:placetype":"venue"
},
  "geometry": {"coordinates":[-1.99372,53.742264],"type":"Point"}
}