{
  "type": "Feature",
  "properties": {
    "addr:full":"Charlton Centre High Street Dover Kent CT16 1TT",
    "addr:postcode":"dover;ct16 1tt",
    "addr:street":"High Street",
    "iso:country":"GB",
    "sg:address":"Charlton Centre High Street",
    "sg:city":"Dover",
    "sg:classifiers":[
        {
            "category":"Commercial Area",
            "type":"Public Place"
        }
    ],
    "sg:postcode":"CT16 1TT",
    "sg:province":"Kent",
    "sg:tags":[
        "shop",
        "centre"
    ],
    "wof:name":"Charlton Shopping Centre",
    "wof:placetype":"venue"
},
  "geometry": {"coordinates":[1.3287609816,51.1268463135],"type":"Point"}
}