{
  "type": "Feature",
  "properties": {
    "iso:country":"GB",
    "sg:address":"23 Penyrheol Dr",
    "sg:city":"Llanelli",
    "sg:classifiers":[
        {
            "category":"Building & Trades",
            "subcategory":"Construction",
            "type":"Services"
        }
    ],
    "sg:postcode":"SA15 3NX",
    "sg:province":"Carmarthenshire",
    "sg:tags":[
        "monumental",
        "mason"
    ],
    "wof:name":"Roberts,Dyfrig H,",
    "wof:placetype":"venue"
},
  "geometry": {"coordinates":[-4.15103,51.694176],"type":"Point"}
}