{
  "type": "Feature",
  "properties": {
    "addr:full":"78 High Holborn London Greater London WC1V 6LS",
    "addr:housenumber":"78",
    "addr:postcode":"wc1v 6ls",
    "addr:street":"High Holborn",
    "iso:country":"GB",
    "sg:address":"78 High Holborn",
    "sg:city":"London",
    "sg:classifiers":[
        {
            "category":"Bars & Pubs",
            "subcategory":"Wine Bar",
            "type":"Food & Drink"
        }
    ],
    "sg:phone":"+44 20 7242 4292",
    "sg:postcode":"WC1V 6LS",
    "sg:province":"Greater London",
    "wof:name":"Corts Bar & Restaurant",
    "wof:placetype":"venue"
},
  "geometry": {"coordinates":[-0.073363,51.577599],"type":"Point"}
}