{
  "type": "Feature",
  "properties": {
    "iso:country":"GB",
    "sg:address":"Enterprise Ho, 27 Hastings Rd",
    "sg:city":"Bromley",
    "sg:classifiers":[
        {
            "category":"Professional",
            "subcategory":"Management & Consulting",
            "type":"Services"
        }
    ],
    "sg:postcode":"BR2 8NA",
    "sg:province":"Kent",
    "sg:tags":[
        "consultant",
        "business"
    ],
    "wof:name":"Siggs,Christine A,",
    "wof:placetype":"venue"
},
  "geometry": {"coordinates":[0.0433599986,51.3781394958],"type":"Point"}
}