{
  "type": "Feature",
  "properties": {
    "addr:full":"Plymbridge Lane, Crownhill Plymouth Devon PL6 8BW",
    "addr:postcode":"pl6 8bw",
    "addr:street":"Plymbridge Lane",
    "iso:country":"GB",
    "sg:address":"Plymbridge Lane, Crownhill",
    "sg:city":"Plymouth",
    "sg:classifiers":[
        {
            "category":"Building & Trades",
            "subcategory":"Construction",
            "type":"Services"
        }
    ],
    "sg:phone":"+44 1752 793448",
    "sg:postcode":"PL6 8BW",
    "sg:province":"Devon",
    "sg:tags":[
        "builder"
    ],
    "wof:name":"E Thomas Construction",
    "wof:placetype":"venue"
},
  "geometry": {"coordinates":[-4.119481,50.419353],"type":"Point"}
}