{
  "type": "Feature",
  "properties": {
    "iso:country":"GB",
    "sg:address":"Trewaun Farm, Llansawel",
    "sg:city":"Llandeilo",
    "sg:classifiers":[
        {
            "category":"Farming",
            "subcategory":"Livestock Farm",
            "type":"Manufacturing & Wholesale Goods"
        }
    ],
    "sg:phone":"+44 1558 685273",
    "sg:postcode":"SA19 7JU",
    "sg:province":"Carmarthenshire",
    "sg:tags":[
        "others"
    ],
    "wof:name":"E.R Thomas",
    "wof:placetype":"venue"
},
  "geometry": {"coordinates":[-4.0128788948,52.0073814392],"type":"Point"}
}