{
  "type": "Feature",
  "properties": {
    "iso:country":"GB",
    "sg:address":"Plantation House, Milber Trading Estate",
    "sg:city":"Newton Abbot",
    "sg:classifiers":[
        {
            "category":"Professional",
            "subcategory":"Computer Services",
            "type":"Services"
        }
    ],
    "sg:phone":"+44 1626 363235",
    "sg:postcode":"TQ12 4SG",
    "sg:province":"Devon",
    "sg:tags":[
        "system",
        "software"
    ],
    "wof:name":"Newline Systems South West Ltd.",
    "wof:placetype":"venue"
},
  "geometry": {"coordinates":[-3.575735,50.523258],"type":"Point"}
}