{
  "type": "Feature",
  "properties": {
    "iso:country":"GB",
    "sg:address":"1 Devonport Mews, Devonport Rd",
    "sg:city":"Shepherd's Bush",
    "sg:classifiers":[
        {
            "category":"Retail",
            "subcategory":"Auto Repair",
            "type":"Services"
        }
    ],
    "sg:phone":"+44 20 8743 4127",
    "sg:postcode":"W12 8NG",
    "sg:province":"Greater London",
    "sg:tags":[
        "body",
        "car"
    ],
    "wof:name":"Michael Harrop",
    "wof:placetype":"venue"
},
  "geometry": {"coordinates":[-0.23155,51.505859],"type":"Point"}
}