{
  "type": "Feature",
  "properties": {
    "iso:country":"GB",
    "sg:address":"38 Ridgeway Moor, Ridgeway",
    "sg:city":"Sheffield",
    "sg:classifiers":[
        {
            "category":"Building & Trades",
            "subcategory":"Construction",
            "type":"Services"
        }
    ],
    "sg:phone":"+44 1246 436660",
    "sg:postcode":"S12 3XW",
    "sg:province":"Derbyshire",
    "sg:tags":[
        "ventilation",
        "contractor"
    ],
    "wof:name":"R Bell",
    "wof:placetype":"venue"
},
  "geometry": {"coordinates":[-1.3990060091,53.3246536255],"type":"Point"}
}