{
  "type": "Feature",
  "properties": {
    "iso:country":"GB",
    "sg:address":"121b Cleveland Street",
    "sg:city":"London",
    "sg:classifiers":[
        {
            "category":"Retail",
            "subcategory":"Photofinishing",
            "type":"Services"
        }
    ],
    "sg:postcode":"W1T 6PU",
    "sg:province":"Greater London",
    "sg:tags":[
        "photographic",
        "processor"
    ],
    "wof:name":"G D Photographic Ltd.",
    "wof:placetype":"venue"
},
  "geometry": {"coordinates":[-0.141146,51.522274],"type":"Point"}
}