{
  "type": "Feature",
  "properties": {
    "iso:country":"GB",
    "sg:address":"139 Eastcotts Road",
    "sg:city":"Bedford",
    "sg:classifiers":[
        {
            "category":"Bars & Pubs",
            "type":"Food & Drink"
        }
    ],
    "sg:phone":"+44 1234 215079",
    "sg:postcode":"MK42 0JU",
    "sg:province":"Bedfordshire",
    "sg:tags":[
        "pubs",
        "inn"
    ],
    "wof:name":"Turnpikes",
    "wof:placetype":"venue"
},
  "geometry": {"coordinates":[-0.437929,52.12006],"type":"Point"}
}