{
  "type": "Feature",
  "properties": {
    "addr:full":"Sunnyside Road Weston-super-mare Somerset BS23 3PZ",
    "addr:postcode":"bs23 3pz",
    "addr:street":"Sunnyside Road",
    "iso:country":"GB",
    "sg:address":"Sunnyside Road",
    "sg:city":"Weston-super-mare",
    "sg:classifiers":[
        {
            "category":"Home & Garden",
            "subcategory":"Building Materials",
            "type":"Retail Goods"
        }
    ],
    "sg:phone":"+44 1934 635226",
    "sg:postcode":"BS23 3PZ",
    "sg:province":"Somerset",
    "sg:tags":[
        "insulation",
        "installers"
    ],
    "wof:name":"Cabletec Flexibles Ltd.",
    "wof:placetype":"venue"
},
  "geometry": {"coordinates":[-2.971654,51.339375],"type":"Point"}
}