{
  "type": "Feature",
  "properties": {
    "addr:full":"78-82 High Street March Cambridgeshire PE15 9LD",
    "addr:housenumber":"78-82",
    "addr:postcode":"pe15 9ld",
    "addr:street":"High Street",
    "iso:country":"GB",
    "sg:address":"78-82 High Street",
    "sg:city":"March",
    "sg:classifiers":[
        {
            "category":"Bars & Pubs",
            "subcategory":"Nightclub",
            "type":"Food & Drink"
        }
    ],
    "sg:postcode":"PE15 9LD",
    "sg:province":"Cambridgeshire",
    "sg:tags":[
        "club",
        "night",
        "activity"
    ],
    "wof:name":"PLANET MARCH",
    "wof:placetype":"venue"
},
  "geometry": {"coordinates":[0.0876149982,52.5470085144],"type":"Point"}
}