{
  "type": "Feature",
  "properties": {
    "addr:full":"Craigmill House, Bridgefoot, Strathmartine Dundee Dundee City DD3 0PH",
    "addr:postcode":"dd3 0ph",
    "iso:country":"GB",
    "sg:address":"Craigmill House, Bridgefoot, Strathmartine",
    "sg:city":"Dundee",
    "sg:classifiers":[
        {
            "category":"Home & Garden",
            "subcategory":"Building Materials",
            "type":"Retail Goods"
        },
        {
            "category":"Building & Trades",
            "subcategory":"Construction",
            "type":"Services"
        }
    ],
    "sg:phone":"+44 1382 884604",
    "sg:postcode":"DD3 0PH",
    "sg:province":"Dundee City",
    "sg:tags":[
        "roofing",
        "builder"
    ],
    "wof:name":"Dundee Roofing Supplies Ltd.",
    "wof:placetype":"venue"
},
  "geometry": {"coordinates":[-3.0138099194,56.5055465698],"type":"Point"}
}