{
  "type": "Feature",
  "properties": {
    "addr:full":"Duck Lane, Laverstock Salisbury Wiltshire SP1 1PU",
    "addr:postcode":"sp1 1pu",
    "addr:street":"Duck Lane",
    "iso:country":"GB",
    "sg:address":"Duck Lane, Laverstock",
    "sg:city":"Salisbury",
    "sg:classifiers":[
        {
            "category":"Bars & Pubs",
            "type":"Food & Drink"
        }
    ],
    "sg:postcode":"SP1 1PU",
    "sg:province":"Wiltshire",
    "sg:tags":[
        "pubs",
        "inn"
    ],
    "wof:name":"The Duck Inn",
    "wof:placetype":"venue"
},
  "geometry": {"coordinates":[-1.776184,51.073475],"type":"Point"}
}