{
  "type": "Feature",
  "properties": {
    "iso:country":"GB",
    "sg:address":"43 Montague Road",
    "sg:city":"Richmond",
    "sg:classifiers":[
        {
            "category":"Health Services",
            "subcategory":"Doctor",
            "type":"Services"
        }
    ],
    "sg:phone":"+44 20 8332 3015",
    "sg:postcode":"TW10 6QJ",
    "sg:province":"Greater London",
    "sg:tags":[
        "practitioners"
    ],
    "wof:name":"M Cross",
    "wof:placetype":"venue"
},
  "geometry": {"coordinates":[-0.297816,51.455582],"type":"Point"}
}