{
  "type": "Feature",
  "properties": {
    "iso:country":"GB",
    "sg:address":"Three Horse Shoes Yard, Bridge Street",
    "sg:city":"Otley",
    "sg:classifiers":[
        {
            "category":"Professional",
            "subcategory":"Art Services",
            "type":"Services"
        }
    ],
    "sg:phone":"+44 1943 462845",
    "sg:postcode":"LS21 1BQ",
    "sg:province":"North Yorkshire",
    "sg:tags":[
        "picture",
        "framing"
    ],
    "wof:name":"Holdsworth Framing",
    "wof:placetype":"venue"
},
  "geometry": {"coordinates":[-1.6949529648,53.9057197571],"type":"Point"}
}