{
  "type": "Feature",
  "properties": {
    "addr:full":"Gilliatt Street Scunthorpe Lincolnshire DN15 6EY",
    "addr:postcode":"dn15 6ey",
    "addr:street":"Gilliatt Street",
    "iso:country":"GB",
    "sg:address":"Gilliatt Street",
    "sg:city":"Scunthorpe",
    "sg:classifiers":[
        {
            "category":"Organizations",
            "subcategory":"Membership Organization",
            "type":"Services"
        }
    ],
    "sg:phone":"+44 1724 844094",
    "sg:postcode":"DN15 6EY",
    "sg:province":"Lincolnshire",
    "sg:tags":[
        "club"
    ],
    "wof:name":"Liberal Club",
    "wof:placetype":"venue"
},
  "geometry": {"coordinates":[-0.649509,53.592255],"type":"Point"}
}