{
  "type": "Feature",
  "properties": {
    "iso:country":"GB",
    "sg:address":"Enterprise House, Southbank Business Park, Kirkintilloch",
    "sg:city":"Glasgow",
    "sg:classifiers":[
        {
            "category":"Professional",
            "subcategory":"Accounting & Tax Preparation",
            "type":"Services"
        }
    ],
    "sg:phone":"+44 141 578 2252",
    "sg:postcode":"G66 1XQ",
    "sg:province":"East Dunbartonshire",
    "sg:tags":[
        "consultant"
    ],
    "wof:name":"O'Connell Consulting",
    "wof:placetype":"venue"
},
  "geometry": {"coordinates":[-4.15813,55.934509],"type":"Point"}
}