{
  "type": "Feature",
  "properties": {
    "iso:country":"GB",
    "sg:address":"Unit 4 Havelock St",
    "sg:city":"Dewsbury",
    "sg:classifiers":[
        {
            "category":"Shopping",
            "subcategory":"Computers & Home Electronics",
            "type":"Retail Goods"
        }
    ],
    "sg:phone":"+44 1924 480053",
    "sg:postcode":"WF13 3LU",
    "sg:province":"West Yorkshire",
    "sg:tags":[
        "electrical"
    ],
    "wof:name":"Raben Electrical Ltd",
    "wof:placetype":"venue"
},
  "geometry": {"coordinates":[-1.665536,53.677166],"type":"Point"}
}