{
  "type": "Feature",
  "properties": {
    "addr:full":"Comberton Pl Kidderminster Staffordshire DY10 1QR",
    "addr:postcode":"dy10 1qr",
    "addr:street":"Comberton Pl",
    "iso:country":"GB",
    "sg:address":"Comberton Pl",
    "sg:city":"Kidderminster",
    "sg:classifiers":[
        {
            "category":"Professional",
            "subcategory":"Business Services",
            "type":"Services"
        }
    ],
    "sg:phone":"+44 1562 745257",
    "sg:postcode":"DY10 1QR",
    "sg:province":"Staffordshire",
    "sg:tags":[
        "operator",
        "market"
    ],
    "wof:name":"Kidderminster Market Office",
    "wof:placetype":"venue"
},
  "geometry": {"coordinates":[-2.240509,52.384846],"type":"Point"}
}