{
  "type": "Feature",
  "properties": {
    "iso:country":"GB",
    "sg:address":"223 Manchester Road",
    "sg:city":"Bolton",
    "sg:classifiers":[
        {
            "category":"Food & Beverages",
            "subcategory":"Meat & Fish",
            "type":"Retail Goods"
        }
    ],
    "sg:phone":"+44 1204 572562",
    "sg:postcode":"BL4 8QX",
    "sg:province":"Lancashire",
    "sg:tags":[
        "butcher"
    ],
    "wof:name":"J Wolstencroft",
    "wof:placetype":"venue"
},
  "geometry": {"coordinates":[-2.366394043,53.5369796753],"type":"Point"}
}