{
  "type": "Feature",
  "properties": {
    "iso:country":"GB",
    "sg:address":"Chelford Rd",
    "sg:city":"Macclesfield",
    "sg:classifiers":[
        {
            "category":"Bars & Pubs",
            "type":"Food & Drink"
        }
    ],
    "sg:phone":"+44 1625 424312",
    "sg:postcode":"SK11 9PG",
    "sg:province":"Cheshire",
    "sg:tags":[
        "pubs",
        "inn"
    ],
    "wof:name":"Blacksmiths Arms",
    "wof:placetype":"venue"
},
  "geometry": {"coordinates":[-2.2724568844,53.2655067444],"type":"Point"}
}