{
  "type": "Feature",
  "properties": {
    "iso:country":"GB",
    "sg:address":"99 Oaklands, Guilden Sutton",
    "sg:city":"Chester",
    "sg:classifiers":[
        {
            "category":"Home & Garden",
            "subcategory":"Home Furnishings",
            "type":"Retail Goods"
        }
    ],
    "sg:postcode":"CH3 7HG",
    "sg:province":"Cheshire",
    "sg:tags":[
        "blind",
        "curtain",
        "fitting"
    ],
    "wof:name":"Curtain Workshop",
    "wof:placetype":"venue"
},
  "geometry": {"coordinates":[-2.828936,53.20808],"type":"Point"}
}