{
  "type": "Feature",
  "properties": {
    "addr:full":"17 The Dr Isleworth Greater London TW7 4AB",
    "addr:housenumber":"17",
    "addr:postcode":"tw7 4ab",
    "addr:street":"The Dr",
    "iso:country":"GB",
    "sg:address":"17 The Dr",
    "sg:city":"Isleworth",
    "sg:classifiers":[
        {
            "category":"Building & Trades",
            "subcategory":"Construction",
            "type":"Services"
        }
    ],
    "sg:postcode":"TW7 4AB",
    "sg:province":"Greater London",
    "sg:tags":[
        "builder"
    ],
    "wof:name":"Abrams,Michael,",
    "wof:placetype":"venue"
},
  "geometry": {"coordinates":[-0.3478690088,51.4751319885],"type":"Point"}
}