{
  "type": "Feature",
  "properties": {
    "addr:full":"132 Silverlea Av Wallasey Merseyside L45 4QU",
    "addr:housenumber":"132",
    "addr:postcode":"l45 4qu",
    "addr:street":"Silverlea Av",
    "iso:country":"GB",
    "sg:address":"132 Silverlea Av",
    "sg:city":"Wallasey",
    "sg:classifiers":[
        {
            "category":"Sports & Exercise",
            "subcategory":"Gym",
            "type":"Entertainment"
        }
    ],
    "sg:phone":"+44 151 639 9500",
    "sg:postcode":"L45 4QU",
    "sg:province":"Merseyside",
    "sg:tags":[
        "fitness",
        "health",
        "centre"
    ],
    "wof:name":"Reshape You",
    "wof:placetype":"venue"
},
  "geometry": {"coordinates":[-3.0480589867,53.4201011658],"type":"Point"}
}