{
  "type": "Feature",
  "properties": {
    "addr:full":"18 Winsor Street Caerphilly Caerphilly CF83 1FW",
    "addr:housenumber":"18",
    "addr:postcode":"cf83 1fw",
    "addr:street":"Winsor Street",
    "iso:country":"GB",
    "sg:address":"18 Winsor Street",
    "sg:city":"Caerphilly",
    "sg:classifiers":[
        {
            "category":"Personal",
            "subcategory":"Beauty Salon",
            "type":"Services"
        }
    ],
    "sg:phone":"+44 29 2088 9310",
    "sg:postcode":"CF83 1FW",
    "sg:province":"Caerphilly",
    "wof:name":"Beauty Box",
    "wof:placetype":"venue"
},
  "geometry": {"coordinates":[-3.219193,51.573719],"type":"Point"}
}