{
  "type": "Feature",
  "properties": {
    "addr:full":"40a Braunstone Close Leicester Leicestershire LE3 2GE",
    "addr:housenumber":"40a",
    "addr:postcode":"le3 2ge",
    "addr:street":"Braunstone Close",
    "iso:country":"GB",
    "sg:address":"40a Braunstone Close",
    "sg:city":"Leicester",
    "sg:classifiers":[
        {
            "category":"Retail",
            "subcategory":"Auto Repair",
            "type":"Services"
        }
    ],
    "sg:phone":"+44 116 289 9195",
    "sg:postcode":"LE3 2GE",
    "sg:province":"Leicestershire",
    "sg:tags":[
        "body",
        "car"
    ],
    "wof:name":"Kirby Road Garage (Leicester) Ltd.",
    "wof:placetype":"venue"
},
  "geometry": {"coordinates":[-1.170599,52.613895],"type":"Point"}
}