{
  "type": "Feature",
  "properties": {
    "addr:full":"160 Park Ave, Aztec West, Almondsbury Bristol Gloucestershire BS32 4RR",
    "addr:housenumber":"160",
    "addr:postcode":"bs32 4rr",
    "addr:street":"Park Ave",
    "iso:country":"GB",
    "sg:address":"160 Park Ave, Aztec West, Almondsbury",
    "sg:city":"Bristol",
    "sg:classifiers":[
        {
            "category":"Manufacturing",
            "subcategory":"Buildings",
            "type":"Manufacturing & Wholesale Goods"
        }
    ],
    "sg:postcode":"BS32 4RR",
    "sg:province":"Gloucestershire",
    "sg:tags":[
        "system",
        "air conditioning"
    ],
    "wof:name":"Trox (U K) Ltd",
    "wof:placetype":"venue"
},
  "geometry": {"coordinates":[-2.5705089569,51.5430831909],"type":"Point"}
}