{
  "type": "Feature",
  "properties": {
    "addr:full":"4 Balmoral Terrace Inverness Highland IV2 3UU",
    "addr:housenumber":"4",
    "addr:postcode":"iv2 3uu",
    "addr:street":"Balmoral Terrace",
    "iso:country":"GB",
    "sg:address":"4 Balmoral Terrace",
    "sg:city":"Inverness",
    "sg:classifiers":[
        {
            "category":"Home & Garden",
            "subcategory":"Household Appliances",
            "type":"Retail Goods"
        }
    ],
    "sg:phone":"+44 1463 711997",
    "sg:postcode":"IV2 3UU",
    "sg:province":"Highland",
    "sg:tags":[
        "electrical"
    ],
    "wof:name":"Speedfix",
    "wof:placetype":"venue"
},
  "geometry": {"coordinates":[-4.20053,57.475475],"type":"Point"}
}