{
  "type": "Feature",
  "properties": {
    "addr:full":"Ewert Ho, Ewert Pl Oxford Oxfordshire OX2 7BZ",
    "addr:postcode":"ox2 7bz",
    "addr:street":"Ewert Pl",
    "iso:country":"GB",
    "sg:address":"Ewert Ho, Ewert Pl",
    "sg:city":"Oxford",
    "sg:classifiers":[
        {
            "category":"Government",
            "subcategory":"Office",
            "type":"Public Place"
        }
    ],
    "sg:phone":"+44 1865 554291",
    "sg:postcode":"OX2 7BZ",
    "sg:province":"Oxfordshire",
    "sg:tags":[
        "education",
        "agency",
        "authority"
    ],
    "wof:name":"Oxford Delegacy Of Local Examinations",
    "wof:placetype":"venue"
},
  "geometry": {"coordinates":[-1.2643489838,51.7767410278],"type":"Point"}
}