{
  "type": "Feature",
  "properties": {
    "addr:full":"40 Dulwich Gr London Greater London SE22 8PP",
    "addr:housenumber":"40",
    "addr:postcode":"se22 8pp",
    "addr:street":"Dulwich Gr",
    "iso:country":"GB",
    "sg:address":"40 Dulwich Gr",
    "sg:city":"London",
    "sg:classifiers":[
        {
            "category":"Organizations",
            "subcategory":"Non-profit Organization",
            "type":"Services"
        }
    ],
    "sg:phone":"+44 20 8693 3311",
    "sg:postcode":"SE22 8PP",
    "sg:province":"Greater London",
    "sg:tags":[
        "organisation",
        "voluntary",
        "charity"
    ],
    "wof:name":"Rainer Housing",
    "wof:placetype":"venue"
},
  "geometry": {"coordinates":[-0.0776600018,51.4595413208],"type":"Point"}
}