{
  "type": "Feature",
  "properties": {
    "addr:full":"3 Wulfric Close, Penkridge Stafford Shropshire ST19 5EW",
    "addr:housenumber":"3",
    "addr:postcode":"st19 5ew",
    "addr:street":"Wulfric Close",
    "iso:country":"GB",
    "sg:address":"3 Wulfric Close, Penkridge",
    "sg:city":"Stafford",
    "sg:classifiers":[
        {
            "category":"Government",
            "subcategory":"Post Office",
            "type":"Public Place"
        }
    ],
    "sg:postcode":"ST19 5EW",
    "sg:province":"Shropshire",
    "sg:tags":[
        "messenger",
        "courier"
    ],
    "wof:name":"Mapleton Marketing",
    "wof:placetype":"venue"
},
  "geometry": {"coordinates":[-2.1036689281,52.7226066589],"type":"Point"}
}