{
  "type": "Feature",
  "properties": {
    "addr:full":"Uphill Farm, Foddington, Babcary Somerton Somerset TA11 7EL",
    "addr:postcode":"ta11 7el",
    "iso:country":"GB",
    "sg:address":"Uphill Farm, Foddington, Babcary",
    "sg:city":"Somerton",
    "sg:classifiers":[
        {
            "category":"Farming",
            "subcategory":"Livestock Farm",
            "type":"Manufacturing & Wholesale Goods"
        }
    ],
    "sg:phone":"+44 1963 240302",
    "sg:postcode":"TA11 7EL",
    "sg:province":"Somerset",
    "sg:tags":[
        "others"
    ],
    "wof:name":"R W & G A Baber & Son",
    "wof:placetype":"venue"
},
  "geometry": {"coordinates":[-2.6252889633,51.0559310913],"type":"Point"}
}