{
  "type": "Feature",
  "properties": {
    "addr:full":"280 The Meadway, Tilehurst Reading Berkshire RG30 4PE",
    "addr:housenumber":"280",
    "addr:postcode":"rg30 4pe",
    "addr:street":"The Meadway",
    "iso:country":"GB",
    "sg:address":"280 The Meadway, Tilehurst",
    "sg:city":"Reading",
    "sg:classifiers":[
        {
            "category":"Place Of Worship",
            "type":"Public Place"
        }
    ],
    "sg:phone":"+44 118 942 7524",
    "sg:postcode":"RG30 4PE",
    "sg:province":"Berkshire",
    "wof:name":"CHURCH OF JESUS CHRIST OF LATTER-DAY SAINTS (GREAT BRITAIN)",
    "wof:placetype":"venue"
},
  "geometry": {"coordinates":[-1.0307990313,51.4530792236],"type":"Point"}
}