{
  "type": "Feature",
  "properties": {
    "addr:full":"1 The Regent Centre Glasgow East Dunbartonshire G66 1JH",
    "addr:housenumber":"1",
    "addr:postcode":"g66 1jh",
    "addr:street":"The",
    "iso:country":"GB",
    "sg:address":"1 The Regent Centre",
    "sg:city":"Glasgow",
    "sg:classifiers":[
        {
            "category":"Travel",
            "subcategory":"Travel Agent",
            "type":"Entertainment"
        }
    ],
    "sg:phone":"+44 141 775 0855",
    "sg:postcode":"G66 1JH",
    "sg:province":"East Dunbartonshire",
    "wof:name":"Lunn Poly",
    "wof:placetype":"venue"
},
  "geometry": {"coordinates":[-4.15795,55.93959],"type":"Point"}
}