{
  "type": "Feature",
  "properties": {
    "addr:full":"11a Stodman St Newark Nottinghamshire NG24 1AN",
    "addr:housenumber":"11a",
    "addr:postcode":"ng24 1an",
    "addr:street":"Stodman St",
    "iso:country":"GB",
    "sg:address":"11a Stodman St",
    "sg:city":"Newark",
    "sg:classifiers":[
        {
            "category":"Professional",
            "subcategory":"Business Services",
            "type":"Services"
        }
    ],
    "sg:phone":"+44 70 7122 3836",
    "sg:postcode":"NG24 1AN",
    "sg:province":"Nottinghamshire",
    "sg:tags":[
        "broker",
        "commodity"
    ],
    "wof:name":"Rob Hughes Quality Marketing",
    "wof:placetype":"venue"
},
  "geometry": {"coordinates":[-0.8114020228,53.0764389038],"type":"Point"}
}