{
  "type": "Feature",
  "properties": {
    "addr:full":"Cb Shop, 330 Bridge Rd Spalding Cambridgeshire PE12 9SH",
    "addr:housenumber":"330",
    "addr:postcode":"pe12 9sh",
    "addr:street":"Bridge Rd Spalding",
    "iso:country":"GB",
    "sg:address":"Cb Shop, 330 Bridge Rd",
    "sg:city":"Spalding",
    "sg:classifiers":[
        {
            "category":"Shopping",
            "subcategory":"Computers & Home Electronics",
            "type":"Retail Goods"
        }
    ],
    "sg:phone":"+44 1406 351881",
    "sg:postcode":"PE12 9SH",
    "sg:province":"Cambridgeshire",
    "sg:tags":[
        "equipment",
        "radio"
    ],
    "wof:name":"S M Communications",
    "wof:placetype":"venue"
},
  "geometry": {"coordinates":[0.17276,52.773521],"type":"Point"}
}