{
  "type": "Feature",
  "properties": {
    "addr:full":"Blencathra House, Carleton Penrith Cumbria CA11 8SW",
    "addr:postcode":"ca11 8sw",
    "iso:country":"GB",
    "sg:address":"Blencathra House, Carleton",
    "sg:city":"Penrith",
    "sg:classifiers":[
        {
            "category":"Education",
            "subcategory":"Special Training",
            "type":"Public Place"
        }
    ],
    "sg:phone":"+44 1768 890939",
    "sg:postcode":"CA11 8SW",
    "sg:province":"Cumbria",
    "sg:tags":[
        "product",
        "centre"
    ],
    "wof:name":"Nexus Training & Development Ltd.",
    "wof:placetype":"venue"
},
  "geometry": {"coordinates":[-2.7302789688,54.6607017517],"type":"Point"}
}