{
  "type": "Feature",
  "properties": {
    "addr:full":"Beechlands Lodge, Maynards Grn Heathfield East Sussex TN21 0BU",
    "addr:postcode":"tn21 0bu",
    "addr:street":"Maynards Grn Heathfield",
    "iso:country":"GB",
    "sg:address":"Beechlands Lodge, Maynards Grn",
    "sg:city":"Heathfield",
    "sg:classifiers":[
        {
            "category":"Shopping",
            "subcategory":"Crafts & Fabrics",
            "type":"Retail Goods"
        }
    ],
    "sg:postcode":"TN21 0BU",
    "sg:province":"East Sussex",
    "sg:tags":[
        "shop"
    ],
    "wof:name":"Freelance Fabrics (Luton) Ltd",
    "wof:placetype":"venue"
},
  "geometry": {"coordinates":[0.252349,50.971859],"type":"Point"}
}