{
  "type": "Feature",
  "properties": {
    "iso:country":"GB",
    "sg:address":"Unit 3a Wharfedale Road, Euroway Trading Estate",
    "sg:city":"Bradford",
    "sg:classifiers":[
        {
            "category":"Shopping",
            "type":"Retail Goods"
        }
    ],
    "sg:phone":"+44 1274 686574",
    "sg:postcode":"BD4 6SG",
    "sg:province":"West Yorkshire",
    "sg:tags":[
        "part",
        "accessory"
    ],
    "wof:name":"Carnography Plc",
    "wof:placetype":"venue"
},
  "geometry": {"coordinates":[-1.7382600307,53.7571105957],"type":"Point"}
}