{
  "type": "Feature",
  "properties": {
    "addr:full":"Belmont Road Wallington Surrey SM6 8TE",
    "addr:postcode":"sm6 8te",
    "addr:street":"Belmont Road",
    "iso:country":"GB",
    "sg:address":"Belmont Road",
    "sg:city":"Wallington",
    "sg:classifiers":[
        {
            "category":"Retail",
            "subcategory":"Auto Repair",
            "type":"Services"
        }
    ],
    "sg:phone":"+44 20 8669 6960",
    "sg:postcode":"SM6 8TE",
    "sg:province":"Surrey",
    "sg:tags":[
        "body",
        "car",
        "repairer"
    ],
    "wof:name":"B & T Autos",
    "wof:placetype":"venue"
},
  "geometry": {"coordinates":[-0.1471409947,51.362323761],"type":"Point"}
}