{
  "type": "Feature",
  "properties": {
    "addr:full":"Church Lane, Winthorpe Skegness Lincolnshire PE25 1EW",
    "addr:postcode":"pe25 1ew",
    "addr:street":"Church Lane",
    "iso:country":"GB",
    "sg:address":"Church Lane, Winthorpe",
    "sg:city":"Skegness",
    "sg:classifiers":[
        {
            "category":"Bars & Pubs",
            "type":"Food & Drink"
        }
    ],
    "sg:phone":"+44 1754 765514",
    "sg:postcode":"PE25 1EW",
    "sg:province":"Lincolnshire",
    "sg:tags":[
        "pubs",
        "inn"
    ],
    "wof:name":"The Friendship",
    "wof:placetype":"venue"
},
  "geometry": {"coordinates":[0.334762007,53.1654548645],"type":"Point"}
}