{
  "type": "Feature",
  "properties": {
    "addr:full":"Block D, Doman Road Camberley Berkshire GU15 3DF",
    "addr:postcode":"gu15 3df",
    "addr:street":"Doman Road",
    "iso:country":"GB",
    "sg:address":"Block D, Doman Road",
    "sg:city":"Camberley",
    "sg:classifiers":[
        {
            "category":"Professional",
            "subcategory":"Testing Lab",
            "type":"Services"
        }
    ],
    "sg:phone":"+44 1276 65777",
    "sg:postcode":"GU15 3DF",
    "sg:province":"Berkshire",
    "sg:tags":[
        "mot"
    ],
    "wof:name":"Camberley M O T & Repair Centre",
    "wof:placetype":"venue"
},
  "geometry": {"coordinates":[-0.73423,51.336216],"type":"Point"}
}