{
  "type": "Feature",
  "properties": {
    "addr:full":"4 Railway Street, Pocklington York East Riding of Yorkshire YO42 2QZ",
    "addr:housenumber":"4",
    "addr:postcode":"yo42 2qz",
    "addr:street":"Railway Street",
    "iso:country":"GB",
    "sg:address":"4 Railway Street, Pocklington",
    "sg:city":"York",
    "sg:classifiers":[
        {
            "category":"Professional",
            "subcategory":"Management & Consulting",
            "type":"Services"
        }
    ],
    "sg:phone":"+44 1759 304229",
    "sg:postcode":"YO42 2QZ",
    "sg:province":"East Riding of Yorkshire",
    "sg:tags":[
        "consultant",
        "specialist"
    ],
    "wof:name":"Nicola Jane",
    "wof:placetype":"venue"
},
  "geometry": {"coordinates":[-0.7803840041,53.9299697876],"type":"Point"}
}