{
  "type": "Feature",
  "properties": {
    "addr:full":"10 Tolmers Road, Cuffley Potters Bar Greater London EN6 4LA",
    "addr:housenumber":"10",
    "addr:postcode":"en6 4la",
    "addr:street":"Tolmers Road",
    "iso:country":"GB",
    "sg:address":"10 Tolmers Road, Cuffley",
    "sg:city":"Potters Bar",
    "sg:classifiers":[
        {
            "category":"Shopping",
            "subcategory":"Books",
            "type":"Retail Goods"
        }
    ],
    "sg:phone":"+44 1707 872720",
    "sg:postcode":"EN6 4LA",
    "sg:province":"Greater London",
    "wof:name":"Aedificamus Press Publishers",
    "wof:placetype":"venue"
},
  "geometry": {"coordinates":[-0.110431,51.708553],"type":"Point"}
}