{
  "type": "Feature",
  "properties": {
    "iso:country":"GB",
    "sg:address":"2 The Chase, Little Eaton",
    "sg:city":"Derby",
    "sg:classifiers":[
        {
            "category":"Government",
            "subcategory":"Department Of Motor Vehicles",
            "type":"Public Place"
        },
        {
            "category":"Retail",
            "subcategory":"Auto Repair",
            "type":"Services"
        },
        {
            "category":"Sports & Exercise",
            "subcategory":"Tennis Court",
            "type":"Entertainment"
        }
    ],
    "sg:phone":"+44 1332 883462",
    "sg:postcode":"DE21 5AS",
    "sg:province":"Derbyshire",
    "sg:tags":[
        "breakdown",
        "car",
        "modification",
        "recovery",
        "garage"
    ],
    "wof:name":"Robby Stone Salvage",
    "wof:placetype":"venue"
},
  "geometry": {"coordinates":[-1.454508,52.980145],"type":"Point"}
}