{
  "type": "Feature",
  "properties": {
    "iso:country":"GB",
    "sg:address":"Sterling House, 27 Hatchlands Road",
    "sg:city":"Redhill",
    "sg:classifiers":[
        {
            "category":"Airline",
            "type":"Transportation"
        }
    ],
    "sg:postcode":"RH1 6AB",
    "sg:province":"Surrey",
    "wof:name":"Biggin Hill Helicopter Events Ltd",
    "wof:placetype":"venue"
},
  "geometry": {"coordinates":[-0.180054,51.238667],"type":"Point"}
}