{
  "type": "Feature",
  "properties": {
    "iso:country":"GB",
    "sg:address":"Babbage Road",
    "sg:city":"Stevenage",
    "sg:classifiers":[
        {
            "category":"Building & Trades",
            "subcategory":"Construction",
            "type":"Services"
        }
    ],
    "sg:phone":"+44 1438 740055",
    "sg:postcode":"SG1 2EB",
    "sg:province":"Hertfordshire",
    "sg:tags":[
        "ceiling",
        "contractor"
    ],
    "wof:name":"C C F",
    "wof:placetype":"venue"
},
  "geometry": {"coordinates":[-0.2207520008,51.9028739929],"type":"Point"}
}