{
  "type": "Feature",
  "properties": {
    "addr:full":"Rear Of 1 Emsworth Rd, Shirley Southampton Hampshire SO15 3LY",
    "addr:housenumber":"rear of 1",
    "addr:postcode":"so15 3ly",
    "addr:street":"Emsworth Rd",
    "iso:country":"GB",
    "sg:address":"Rear Of 1 Emsworth Rd, Shirley",
    "sg:city":"Southampton",
    "sg:classifiers":[
        {
            "category":"Building & Trades",
            "subcategory":"Construction",
            "type":"Services"
        }
    ],
    "sg:phone":"+44 23 8077 6527",
    "sg:postcode":"SO15 3LY",
    "sg:province":"Hampshire",
    "sg:tags":[
        "joinery"
    ],
    "wof:name":"Edmonds Joinery",
    "wof:placetype":"venue"
},
  "geometry": {"coordinates":[-1.407319,50.909939],"type":"Point"}
}