{
  "type": "Feature",
  "properties": {
    "addr:full":"30 Barassiebank Lane Troon South Ayrshire KA10 6RW",
    "addr:housenumber":"30",
    "addr:postcode":"ka10 6rw",
    "addr:street":"Barassiebank Lane",
    "iso:country":"GB",
    "sg:address":"30 Barassiebank Lane",
    "sg:city":"Troon",
    "sg:classifiers":[
        {
            "category":"Farming",
            "subcategory":"Nursery",
            "type":"Manufacturing & Wholesale Goods"
        },
        {
            "category":"Education",
            "subcategory":"Preschool",
            "type":"Public Place"
        }
    ],
    "sg:phone":"+44 1292 311117",
    "sg:postcode":"KA10 6RW",
    "sg:province":"South Ayrshire",
    "sg:tags":[
        "school",
        "creche"
    ],
    "wof:name":"Sand Castle Nursery",
    "wof:placetype":"venue"
},
  "geometry": {"coordinates":[-4.655996,55.557068],"type":"Point"}
}