{
  "type": "Feature",
  "properties": {
    "addr:full":"722-726 Cranbrook Road, Barkingside Ilford Essex IG6 1HU",
    "addr:housenumber":"722-726",
    "addr:postcode":"ig6 1hu",
    "addr:street":"Cranbrook Road",
    "iso:country":"GB",
    "sg:address":"722-726 Cranbrook Road, Barkingside",
    "sg:city":"Ilford",
    "sg:classifiers":[
        {
            "category":"Insurance",
            "subcategory":"Insurance Agent",
            "type":"Services"
        }
    ],
    "sg:phone":"+44 20 8550 6685",
    "sg:postcode":"IG6 1HU",
    "sg:province":"Essex",
    "sg:tags":[
        "broker"
    ],
    "wof:name":"W A Ringrose Ltd.",
    "wof:placetype":"venue"
},
  "geometry": {"coordinates":[0.07507,51.582329],"type":"Point"}
}