{
  "type": "Feature",
  "properties": {
    "iso:country":"GB",
    "sg:address":"Unit 2 Olds App, Tolpits La",
    "sg:city":"Watford",
    "sg:classifiers":[
        {
            "category":"Retail",
            "subcategory":"Auto Repair",
            "type":"Services"
        }
    ],
    "sg:postcode":"WD18 9QY",
    "sg:province":"Hertfordshire",
    "sg:tags":[
        "body",
        "car"
    ],
    "wof:name":"Group Two",
    "wof:placetype":"venue"
},
  "geometry": {"coordinates":[-0.44022,51.638302],"type":"Point"}
}