{
  "type": "Feature",
  "properties": {
    "iso:country":"GB",
    "sg:address":"87 Brownshore Lane, Essington",
    "sg:city":"Wolverhampton",
    "sg:classifiers":[
        {
            "category":"Health Services",
            "subcategory":"Doctor",
            "type":"Services"
        }
    ],
    "sg:phone":"+44 1922 712933",
    "sg:postcode":"WV11 2AE",
    "sg:province":"Staffordshire",
    "sg:tags":[
        "practitioners"
    ],
    "wof:name":"S Ganguly",
    "wof:placetype":"venue"
},
  "geometry": {"coordinates":[-2.054043,52.626797],"type":"Point"}
}