{
  "type": "Feature",
  "properties": {
    "addr:full":"20 Conduit St West End Hampshire W1R 9TD",
    "addr:housenumber":"20",
    "addr:postcode":"w1r 9td",
    "addr:street":"Conduit St",
    "iso:country":"GB",
    "sg:address":"20 Conduit St",
    "sg:city":"West End",
    "sg:classifiers":[
        {
            "category":"Manufacturing",
            "subcategory":"Metals",
            "type":"Manufacturing & Wholesale Goods"
        }
    ],
    "sg:phone":"+44 20 7629 8370",
    "sg:postcode":"W1R 9TD",
    "sg:province":"Hampshire",
    "sg:tags":[
        "merchant"
    ],
    "wof:name":"Mintrade Ltd",
    "wof:placetype":"venue"
},
  "geometry": {"coordinates":[-0.142382,51.512066],"type":"Point"}
}