{
  "type": "Feature",
  "properties": {
    "iso:country":"GB",
    "sg:address":"24 Station Road, Farncombe",
    "sg:city":"Godalming",
    "sg:classifiers":[
        {
            "category":"Organizations",
            "subcategory":"Membership Organization",
            "type":"Services"
        }
    ],
    "sg:phone":"+44 1483 420983",
    "sg:postcode":"GU7 3NG",
    "sg:province":"Surrey",
    "sg:tags":[
        "club"
    ],
    "wof:name":"Farncombe Social Club",
    "wof:placetype":"venue"
},
  "geometry": {"coordinates":[-0.603453,51.198299],"type":"Point"}
}