{
  "type": "Feature",
  "properties": {
    "addr:full":"114 Walgrove Road Chesterfield Derbyshire S40 2DS",
    "addr:housenumber":"114",
    "addr:postcode":"s40 2ds",
    "addr:street":"Walgrove Road",
    "iso:country":"GB",
    "sg:address":"114 Walgrove Road",
    "sg:city":"Chesterfield",
    "sg:classifiers":[
        {
            "category":"Shopping",
            "subcategory":"Musical Instruments",
            "type":"Retail Goods"
        }
    ],
    "sg:phone":"+44 1246 200570",
    "sg:postcode":"S40 2DS",
    "sg:province":"Derbyshire",
    "wof:name":"Neil Bagshaw",
    "wof:placetype":"venue"
},
  "geometry": {"coordinates":[-1.451155,53.230804],"type":"Point"}
}