{
  "type": "Feature",
  "properties": {
    "addr:full":"1 Worplesdon Road Guildford Surrey GU2 9RW",
    "addr:housenumber":"1",
    "addr:postcode":"gu2 9rw",
    "addr:street":"Worplesdon Road",
    "iso:country":"GB",
    "sg:address":"1 Worplesdon Road",
    "sg:city":"Guildford",
    "sg:classifiers":[
        {
            "category":"Personal",
            "subcategory":"Beauty Salon",
            "type":"Services"
        }
    ],
    "sg:phone":"+44 1483 504342",
    "sg:postcode":"GU2 9RW",
    "sg:province":"Surrey",
    "sg:tags":[
        "unisex",
        "hairdresser"
    ],
    "wof:name":"Clip & Curl",
    "wof:placetype":"venue"
},
  "geometry": {"coordinates":[-0.588588,51.249882],"type":"Point"}
}