{
  "type": "Feature",
  "properties": {
    "addr:full":"10 Howard Court, Nerston Industrial Estate Glasgow South Lanarkshire G74 4QZ",
    "addr:housenumber":"10",
    "addr:postcode":"g74 4qz",
    "addr:street":"Howard Court Nerston Industrial Estate",
    "iso:country":"GB",
    "sg:address":"10 Howard Court, Nerston Industrial Estate",
    "sg:city":"Glasgow",
    "sg:classifiers":[
        {
            "category":"Wholesale",
            "subcategory":"Vending Machines",
            "type":"Manufacturing & Wholesale Goods"
        }
    ],
    "sg:postcode":"G74 4QZ",
    "sg:province":"South Lanarkshire",
    "sg:tags":[
        "sale"
    ],
    "wof:name":"Photo-Me International Plc",
    "wof:placetype":"venue"
},
  "geometry": {"coordinates":[-4.165652,55.779247],"type":"Point"}
}