{
  "type": "Feature",
  "properties": {
    "iso:country":"GB",
    "sg:address":"Matthew House, 22-28 Colston Street",
    "sg:city":"Bristol",
    "sg:classifiers":[
        {
            "category":"Professional",
            "subcategory":"Management & Consulting",
            "type":"Services"
        }
    ],
    "sg:phone":"+44 20 7313 8181",
    "sg:postcode":"BS1 5AE",
    "sg:province":"City of Bristol",
    "sg:tags":[
        "consultant",
        "promotion",
        "direct",
        "sale"
    ],
    "wof:name":"C B A (Marketing & Promotions)",
    "wof:placetype":"venue"
},
  "geometry": {"coordinates":[-2.5974290371,51.4551506042],"type":"Point"}
}