{
  "type": "Feature",
  "properties": {
    "iso:country":"GB",
    "sg:address":"7 Ruspidge Road",
    "sg:city":"Cinderford",
    "sg:classifiers":[
        {
            "category":"Personal",
            "subcategory":"Beauty Salon",
            "type":"Services"
        }
    ],
    "sg:postcode":"GL14 3AD",
    "sg:province":"Gloucestershire",
    "sg:tags":[
        "unisex",
        "hairdresser"
    ],
    "wof:name":"Steve's Hairdressing",
    "wof:placetype":"venue"
},
  "geometry": {"coordinates":[-2.504272,51.809547],"type":"Point"}
}