{
  "type": "Feature",
  "properties": {
    "addr:full":"6 Lawns Court Royston Bedfordshire SG8 9EW",
    "addr:housenumber":"6",
    "addr:postcode":"sg8 9ew",
    "addr:street":"Lawns Court",
    "iso:country":"GB",
    "sg:address":"6 Lawns Court",
    "sg:city":"Royston",
    "sg:classifiers":[
        {
            "category":"Manufacturing",
            "subcategory":"Petroleum Products",
            "type":"Manufacturing & Wholesale Goods"
        }
    ],
    "sg:phone":"+44 1763 247828",
    "sg:postcode":"SG8 9EW",
    "sg:province":"Bedfordshire",
    "sg:tags":[
        "double",
        "glazing"
    ],
    "wof:name":"W Gibbs J Macfarlen & L Newton",
    "wof:placetype":"venue"
},
  "geometry": {"coordinates":[-0.021284,52.045696],"type":"Point"}
}