{
  "type": "Feature",
  "properties": {
    "addr:full":"431 George Street Aberdeen Aberdeen City AB25 1ER",
    "addr:housenumber":"431",
    "addr:postcode":"ab25 1er",
    "addr:street":"George Street",
    "iso:country":"GB",
    "sg:address":"431 George Street",
    "sg:city":"Aberdeen",
    "sg:classifiers":[
        {
            "category":"Organizations",
            "subcategory":"Non-profit Organization",
            "type":"Services"
        }
    ],
    "sg:phone":"+44 1224 639390",
    "sg:postcode":"AB25 1ER",
    "sg:province":"Aberdeen City",
    "sg:tags":[
        "organisation",
        "voluntary",
        "charity"
    ],
    "wof:name":"Voluntary Service",
    "wof:placetype":"venue"
},
  "geometry": {"coordinates":[-2.105309,57.153439],"type":"Point"}
}