{
  "type": "Feature",
  "properties": {
    "addr:full":"Unit 8c Royce Avenue, Cowpen Industrial Estate Billingham Durham TS23 4BX",
    "addr:housenumber":"unit 8c",
    "addr:postcode":"ts23 4bx",
    "addr:street":"Royce Avenue Cowpen Industrial Estate",
    "iso:country":"GB",
    "sg:address":"Unit 8c Royce Avenue, Cowpen Industrial Estate",
    "sg:city":"Billingham",
    "sg:classifiers":[
        {
            "category":"Building & Trades",
            "subcategory":"Construction",
            "type":"Services"
        }
    ],
    "sg:phone":"+44 1642 370662",
    "sg:postcode":"TS23 4BX",
    "sg:province":"Durham",
    "sg:tags":[
        "heating",
        "contractor"
    ],
    "wof:name":"Avonside Plumbing & Heating (North East) Ltd.",
    "wof:placetype":"venue"
},
  "geometry": {"coordinates":[-1.2623989582,54.6122322083],"type":"Point"}
}