{
  "type": "Feature",
  "properties": {
    "addr:full":"150 Brackens Lane, Alvaston Derby Derbyshire DE24 0AL",
    "addr:housenumber":"150",
    "addr:postcode":"de24 0al",
    "addr:street":"Brackens Lane",
    "iso:country":"GB",
    "sg:address":"150 Brackens Lane, Alvaston",
    "sg:city":"Derby",
    "sg:classifiers":[
        {
            "category":"Health Services",
            "subcategory":"Podiatrist",
            "type":"Services"
        }
    ],
    "sg:phone":"+44 1332 571531",
    "sg:postcode":"DE24 0AL",
    "sg:province":"Derbyshire",
    "sg:tags":[
        "podiatrists",
        "chiropodist"
    ],
    "wof:name":"GORDON KEMP",
    "wof:placetype":"venue"
},
  "geometry": {"coordinates":[-1.4451099634,52.8902206421],"type":"Point"}
}