{
  "type": "Feature",
  "properties": {
    "addr:full":"24 Alston Dr, Bradwell Abbey Milton Keynes Buckinghamshire MK13 9HA",
    "addr:housenumber":"24",
    "addr:postcode":"mk13 9ha",
    "addr:street":"Alston Dr",
    "iso:country":"GB",
    "sg:address":"24 Alston Dr, Bradwell Abbey",
    "sg:city":"Milton Keynes",
    "sg:classifiers":[
        {
            "category":"Retail",
            "subcategory":"Repair Shop",
            "type":"Services"
        }
    ],
    "sg:phone":"+44 1908 220311",
    "sg:postcode":"MK13 9HA",
    "sg:province":"Buckinghamshire",
    "sg:tags":[
        "clocks",
        "watch"
    ],
    "wof:name":"Junghans U K Ltd",
    "wof:placetype":"venue"
},
  "geometry": {"coordinates":[-0.797733,52.047234],"type":"Point"}
}