{
  "type": "Feature",
  "properties": {
    "iso:country":"GB",
    "sg:address":"26 Newmarket Street",
    "sg:city":"Ayr",
    "sg:classifiers":[
        {
            "category":"Shopping",
            "subcategory":"Comic Books",
            "type":"Retail Goods"
        }
    ],
    "sg:phone":"+44 1292 282649",
    "sg:postcode":"KA7 1LP",
    "sg:province":"South Ayrshire",
    "sg:tags":[
        "jeweller"
    ],
    "wof:name":"Classics",
    "wof:placetype":"venue"
},
  "geometry": {"coordinates":[-4.630424,55.463547],"type":"Point"}
}