{
  "type": "Feature",
  "properties": {
    "addr:full":"9-11 Victoria Road, Taverham Norwich Norfolk NR8 6NU",
    "addr:housenumber":"9-11",
    "addr:postcode":"nr8 6nu",
    "addr:street":"Victoria Road;Norwich Norfolk",
    "iso:country":"GB",
    "sg:address":"9-11 Victoria Road, Taverham",
    "sg:city":"Norwich",
    "sg:classifiers":[
        {
            "category":"Home & Garden",
            "subcategory":"Hardware",
            "type":"Retail Goods"
        }
    ],
    "sg:postcode":"NR8 6NU",
    "sg:province":"Norfolk",
    "wof:name":"Taverham Hardware & D I Y",
    "wof:placetype":"venue"
},
  "geometry": {"coordinates":[1.2013670206,52.6807594299],"type":"Point"}
}