{
  "type": "Feature",
  "properties": {
    "addr:full":"Northgate Garage Canterbury Kent CT1 1SW",
    "addr:postcode":"ct1 1sw",
    "iso:country":"GB",
    "sg:address":"Northgate Garage",
    "sg:city":"Canterbury",
    "sg:classifiers":[
        {
            "category":"Autos & Motor Vehicles",
            "subcategory":"Automobile Sales",
            "type":"Retail Goods"
        }
    ],
    "sg:postcode":"CT1 1SW",
    "sg:province":"Kent",
    "sg:tags":[
        "car"
    ],
    "wof:name":"Northgate Garage (Canterbury) Ltd.",
    "wof:placetype":"venue"
},
  "geometry": {"coordinates":[1.08474,51.283035],"type":"Point"}
}