{
  "type": "Feature",
  "properties": {
    "iso:country":"GB",
    "sg:address":"124 Shirley Road",
    "sg:city":"Southampton",
    "sg:classifiers":[
        {
            "category":"Food & Beverages",
            "subcategory":"Meat & Fish",
            "type":"Retail Goods"
        },
        {
            "category":"Food & Beverages",
            "subcategory":"Groceries & Convenience Stores",
            "type":"Retail Goods"
        }
    ],
    "sg:phone":"+44 23 8022 8590",
    "sg:postcode":"SO15 3FD",
    "sg:province":"Hampshire",
    "sg:tags":[
        "shop",
        "chip"
    ],
    "wof:name":"Peters Fish & Chip Shop",
    "wof:placetype":"venue"
},
  "geometry": {"coordinates":[-1.4215320349,50.9125671387],"type":"Point"}
}