{
  "type": "Feature",
  "properties": {
    "iso:country":"GB",
    "sg:address":"Frost Lane, Hythe",
    "sg:city":"Southampton",
    "sg:classifiers":[
        {
            "category":"Food & Beverages",
            "subcategory":"Farmers Market",
            "type":"Retail Goods"
        }
    ],
    "sg:phone":"+44 23 8084 3778",
    "sg:postcode":"SO45 3NE",
    "sg:province":"Hampshire",
    "sg:tags":[
        "farm",
        "shop",
        "pyo"
    ],
    "wof:name":"Furzedown Farm",
    "wof:placetype":"venue"
},
  "geometry": {"coordinates":[-1.388102,50.860062],"type":"Point"}
}