{
  "type": "Feature",
  "properties": {
    "iso:country":"GB",
    "sg:address":"3 Church Lane",
    "sg:city":"Pudsey",
    "sg:classifiers":[
        {
            "category":"Shopping",
            "subcategory":"Gifts & Souvenirs",
            "type":"Retail Goods"
        }
    ],
    "sg:phone":"+44 113 257 5346",
    "sg:postcode":"LS28 7LD",
    "sg:province":"West Yorkshire",
    "sg:tags":[
        "shop",
        "poster",
        "card"
    ],
    "wof:name":"Greetings",
    "wof:placetype":"venue"
},
  "geometry": {"coordinates":[-1.663387,53.796486],"type":"Point"}
}