{
  "type": "Feature",
  "properties": {
    "iso:country":"GB",
    "sg:address":"55 Hyndland Street",
    "sg:city":"Glasgow",
    "sg:classifiers":[
        {
            "category":"Retail",
            "subcategory":"Veterinary Services",
            "type":"Services"
        }
    ],
    "sg:phone":"+44 141 357 3139",
    "sg:postcode":"G11 5QF",
    "sg:province":"Glasgow City",
    "sg:tags":[
        "surgeon"
    ],
    "wof:name":"Aikman & Neilson",
    "wof:placetype":"venue"
},
  "geometry": {"coordinates":[-4.302477,55.872208],"type":"Point"}
}