{
  "type": "Feature",
  "properties": {
    "addr:full":"14 Golfview Road, Bieldside Aberdeen Aberdeen City AB15 9DQ",
    "addr:housenumber":"14",
    "addr:postcode":"ab15 9dq",
    "addr:street":"Golfview Road",
    "iso:country":"GB",
    "sg:address":"14 Golfview Road, Bieldside",
    "sg:city":"Aberdeen",
    "sg:classifiers":[
        {
            "category":"Professional",
            "subcategory":"Management & Consulting",
            "type":"Services"
        }
    ],
    "sg:phone":"+44 1224 868467",
    "sg:postcode":"AB15 9DQ",
    "sg:province":"Aberdeen City",
    "sg:tags":[
        "consultant",
        "business"
    ],
    "wof:name":"Adapt Consultancy Ltd.",
    "wof:placetype":"venue"
},
  "geometry": {"coordinates":[-2.194273,57.11232],"type":"Point"}
}