{
  "type": "Feature",
  "properties": {
    "iso:country":"GB",
    "sg:address":"205 London Road",
    "sg:city":"Sevenoaks",
    "sg:classifiers":[
        {
            "category":"Bars & Pubs",
            "type":"Food & Drink"
        }
    ],
    "sg:phone":"+44 1732 452477",
    "sg:postcode":"TN13 1DW",
    "sg:province":"Kent",
    "sg:tags":[
        "pubs",
        "inn"
    ],
    "wof:name":"Railway & Bicycle",
    "wof:placetype":"venue"
},
  "geometry": {"coordinates":[0.183287,51.276752],"type":"Point"}
}