{
  "type": "Feature",
  "properties": {
    "iso:country":"GB",
    "sg:address":"21 Brook Clo",
    "sg:city":"East Grinstead",
    "sg:classifiers":[
        {
            "category":"Food & Beverages",
            "subcategory":"Liquor & Beverages",
            "type":"Retail Goods"
        }
    ],
    "sg:phone":"+44 1342 328359",
    "sg:postcode":"RH19 3XZ",
    "sg:province":"East Sussex",
    "sg:tags":[
        "beer",
        "spirit",
        "wines"
    ],
    "wof:name":"Wineservice",
    "wof:placetype":"venue"
},
  "geometry": {"coordinates":[0.006647,51.125072],"type":"Point"}
}