{
  "type": "Feature",
  "properties": {
    "addr:full":"Panfield House, Severn Stoke Road, Besford Worcester Gloucestershire WR8 9AW",
    "addr:housenumber":"panfield",
    "addr:postcode":"wr8 9aw",
    "addr:street":"Severn Stoke Road",
    "iso:country":"GB",
    "sg:address":"Panfield House, Severn Stoke Road, Besford",
    "sg:city":"Worcester",
    "sg:classifiers":[
        {
            "category":"Banks & Credit Unions",
            "subcategory":"Financial Services",
            "type":"Services"
        }
    ],
    "sg:phone":"+44 1386 552763",
    "sg:postcode":"WR8 9AW",
    "sg:province":"Gloucestershire",
    "sg:tags":[
        "consultant"
    ],
    "wof:name":"Ricall Finance",
    "wof:placetype":"venue"
},
  "geometry": {"coordinates":[-2.1354589462,52.1033592224],"type":"Point"}
}