{
  "type": "Feature",
  "properties": {
    "iso:country":"GB",
    "sg:address":"217a Wigan Road",
    "sg:city":"Leigh",
    "sg:classifiers":[
        {
            "category":"Autos & Motor Vehicles",
            "subcategory":"Fuel & Gas Station",
            "type":"Retail Goods"
        }
    ],
    "sg:phone":"+44 1942 673741",
    "sg:postcode":"WN7 5DW",
    "sg:province":"Lancashire",
    "sg:tags":[
        "petrol",
        "filling"
    ],
    "wof:name":"Save Service Station",
    "wof:placetype":"venue"
},
  "geometry": {"coordinates":[-2.5350039005,53.5042037964],"type":"Point"}
}