{
  "type": "Feature",
  "properties": {
    "iso:country":"GB",
    "sg:address":"32 Towler Street",
    "sg:city":"Peterborough",
    "sg:classifiers":[
        {
            "category":"Retail",
            "subcategory":"Auto Repair",
            "type":"Services"
        }
    ],
    "sg:postcode":"PE1 2TX",
    "sg:province":"Cambridgeshire",
    "sg:tags":[
        "modification",
        "garage"
    ],
    "wof:name":"Central Auto Repairs",
    "wof:placetype":"venue"
},
  "geometry": {"coordinates":[-0.241608,52.579781],"type":"Point"}
}