{
  "type": "Feature",
  "properties": {
    "addr:full":"Thornbarrow Road Windermere Cumbria LA23 2DF",
    "addr:postcode":"la23 2df",
    "addr:street":"Thornbarrow Road",
    "iso:country":"GB",
    "sg:address":"Thornbarrow Road",
    "sg:city":"Windermere",
    "sg:classifiers":[
        {
            "category":"Travel",
            "subcategory":"Hotels & Motels",
            "type":"Entertainment"
        }
    ],
    "sg:postcode":"LA23 2DF",
    "sg:province":"Cumbria",
    "wof:name":"Hillthwaite House Hotel Ltd.",
    "wof:placetype":"venue"
},
  "geometry": {"coordinates":[-2.902055,54.371777],"type":"Point"}
}