{
  "type": "Feature",
  "properties": {
    "addr:full":"57 Lower Church Lane Tipton West Midlands DY4 7PE",
    "addr:housenumber":"57",
    "addr:postcode":"dy4 7pe",
    "addr:street":"Lower Church Lane",
    "iso:country":"GB",
    "sg:address":"57 Lower Church Lane",
    "sg:city":"Tipton",
    "sg:classifiers":[
        {
            "category":"Bars & Pubs",
            "type":"Food & Drink"
        }
    ],
    "sg:phone":"+44 121 520 2865",
    "sg:postcode":"DY4 7PE",
    "sg:province":"West Midlands",
    "sg:tags":[
        "pubs",
        "inn"
    ],
    "wof:name":"The Old Court House",
    "wof:placetype":"venue"
},
  "geometry": {"coordinates":[-2.0501730442,52.5287857056],"type":"Point"}
}