{
  "type": "Feature",
  "properties": {
    "addr:full":"10 Market Street Abergele Conwy LL22 7AA",
    "addr:housenumber":"10",
    "addr:postcode":"ll22 7aa",
    "addr:street":"Market Street",
    "iso:country":"GB",
    "sg:address":"10 Market Street",
    "sg:city":"Abergele",
    "sg:classifiers":[
        {
            "category":"Insurance",
            "subcategory":"Insurance Agent",
            "type":"Services"
        },
        {
            "category":"Banks & Credit Unions",
            "subcategory":"Financial Services",
            "type":"Services"
        }
    ],
    "sg:phone":"+44 1745 833297",
    "sg:postcode":"LL22 7AA",
    "sg:province":"Conwy",
    "sg:tags":[
        "consultant"
    ],
    "wof:name":"J CARR & CO",
    "wof:placetype":"venue"
},
  "geometry": {"coordinates":[-3.5818319321,53.2845153809],"type":"Point"}
}