{
  "type": "Feature",
  "properties": {
    "addr:full":"52 East Bridge Rd Chelmsford Essex CM3 5SD",
    "addr:housenumber":"52",
    "addr:postcode":"cm3 5sd",
    "addr:street":"East Bridge Rd",
    "iso:country":"GB",
    "sg:address":"52 East Bridge Rd",
    "sg:city":"Chelmsford",
    "sg:classifiers":[
        {
            "category":"Shopping",
            "type":"Retail Goods"
        }
    ],
    "sg:phone":"+44 1245 321020",
    "sg:postcode":"CM3 5SD",
    "sg:province":"Essex",
    "sg:tags":[
        "part",
        "accessory"
    ],
    "wof:name":"Roofbox Hire Company The",
    "wof:placetype":"venue"
},
  "geometry": {"coordinates":[0.6145060062,51.6505203247],"type":"Point"}
}