{
  "type": "Feature",
  "properties": {
    "iso:country":"GB",
    "sg:address":"4 Trinity Street",
    "sg:city":"Colchester",
    "sg:classifiers":[
        {
            "category":"Organizations",
            "subcategory":"Non-profit Organization",
            "type":"Services"
        }
    ],
    "sg:phone":"+44 1206 369309",
    "sg:postcode":"CO1 1JN",
    "sg:province":"Essex",
    "sg:tags":[
        "organisation",
        "voluntary",
        "charity"
    ],
    "wof:name":"Cruse - Bereavement Care",
    "wof:placetype":"venue"
},
  "geometry": {"coordinates":[0.899022,51.888874],"type":"Point"}
}