{
  "type": "Feature",
  "properties": {
    "iso:country":"GB",
    "sg:address":"Far Rownall, Thorney Edge Rd",
    "sg:city":"Stoke On Trent",
    "sg:classifiers":[
        {
            "category":"Farming",
            "subcategory":"Livestock Farm",
            "type":"Manufacturing & Wholesale Goods"
        }
    ],
    "sg:phone":"+44 1782 550322",
    "sg:postcode":"ST9 9LD",
    "sg:province":"Staffordshire",
    "sg:tags":[
        "others"
    ],
    "wof:name":"T G Charlesworth",
    "wof:placetype":"venue"
},
  "geometry": {"coordinates":[-2.100067,53.050812],"type":"Point"}
}