{
  "type": "Feature",
  "properties": {
    "addr:full":"Old Skene Road, Kingswells Aberdeen Aberdeen City AB15 8QA",
    "addr:postcode":"ab15 8qa",
    "addr:street":"Old Skene Road",
    "iso:country":"GB",
    "sg:address":"Old Skene Road, Kingswells",
    "sg:city":"Aberdeen",
    "sg:classifiers":[
        {
            "category":"Restaurant",
            "type":"Food & Drink"
        }
    ],
    "sg:phone":"+44 1224 740318",
    "sg:postcode":"AB15 8QA",
    "sg:province":"Aberdeen City",
    "wof:name":"Four Mile House",
    "wof:placetype":"venue"
},
  "geometry": {"coordinates":[-2.226133,57.155704],"type":"Point"}
}