{
  "type": "Feature",
  "properties": {
    "iso:country":"GB",
    "sg:address":"18 Wern Fawr Rd, Wern Tarw",
    "sg:city":"Bridgend",
    "sg:classifiers":[
        {
            "category":"Transit Center",
            "subcategory":"Passenger",
            "type":"Transportation"
        }
    ],
    "sg:phone":"+44 1656 864572",
    "sg:postcode":"CF35 6NF",
    "sg:province":"Bridgend",
    "sg:tags":[
        "boarding",
        "kennel",
        "catteries"
    ],
    "wof:name":"Lloyds (Manufacturing) Engineering",
    "wof:placetype":"venue"
},
  "geometry": {"coordinates":[-3.495001,51.546352],"type":"Point"}
}