{
  "type": "Feature",
  "properties": {
    "iso:country":"GB",
    "sg:address":"1 Balmoral Close",
    "sg:city":"Malvern",
    "sg:classifiers":[
        {
            "category":"Personal",
            "subcategory":"Adult",
            "type":"Services"
        }
    ],
    "sg:phone":"+44 1684 565111",
    "sg:postcode":"WR14 1YD",
    "sg:province":"Herefordshire",
    "sg:tags":[
        "equestrian"
    ],
    "wof:name":"Malvern Mobile Farriers",
    "wof:placetype":"venue"
},
  "geometry": {"coordinates":[-2.305638,52.13483],"type":"Point"}
}