{
  "type": "Feature",
  "properties": {
    "iso:country":"GB",
    "sg:address":"36 Station Road",
    "sg:city":"Shotts",
    "sg:classifiers":[
        {
            "category":"Shopping",
            "subcategory":"Pharmacy",
            "type":"Retail Goods"
        }
    ],
    "sg:phone":"+44 1501 823729",
    "sg:postcode":"ML7 5EB",
    "sg:province":"North Lanarkshire",
    "sg:tags":[
        "pharmacist",
        "chemist"
    ],
    "wof:name":"Crawford Chemists",
    "wof:placetype":"venue"
},
  "geometry": {"coordinates":[-3.790999,55.81797],"type":"Point"}
}