{
  "type": "Feature",
  "properties": {
    "addr:full":"St Helens, Victoria Road, Bushey Heath Watford Hertfordshire WD24 5AY",
    "addr:postcode":"wd24 5ay",
    "addr:street":"Victoria Road",
    "iso:country":"GB",
    "sg:address":"St Helens, Victoria Road, Bushey Heath",
    "sg:city":"Watford",
    "sg:classifiers":[
        {
            "category":"Building & Trades",
            "subcategory":"Construction",
            "type":"Services"
        }
    ],
    "sg:postcode":"WD24 5AY",
    "sg:province":"Hertfordshire",
    "sg:tags":[
        "decorator",
        "painter"
    ],
    "wof:name":"Gascoigne Painter & Decorators",
    "wof:placetype":"venue"
},
  "geometry": {"coordinates":[-0.3987500072,51.6701812744],"type":"Point"}
}