{
  "type": "Feature",
  "properties": {
    "iso:country":"GB",
    "sg:address":"42 Lambs Conduic Street",
    "sg:city":"London",
    "sg:classifiers":[
        {
            "category":"Personal",
            "subcategory":"Beauty Salon",
            "type":"Services"
        }
    ],
    "sg:phone":"+44 20 7405 7797",
    "sg:postcode":"WC1N 3LJ",
    "sg:province":"Greater London",
    "sg:tags":[
        "lady",
        "hairdresser"
    ],
    "wof:name":"Frankie Cochrane Hairdressing",
    "wof:placetype":"venue"
},
  "geometry": {"coordinates":[-0.118099,51.521538],"type":"Point"}
}