{
  "type": "Feature",
  "properties": {
    "addr:full":"79 Heaton Av Romford Essex RM3 7HL",
    "addr:housenumber":"79",
    "addr:postcode":"rm3 7hl",
    "addr:street":"Heaton Av",
    "iso:country":"GB",
    "sg:address":"79 Heaton Av",
    "sg:city":"Romford",
    "sg:classifiers":[
        {
            "category":"Building & Trades",
            "subcategory":"Plumbing",
            "type":"Services"
        }
    ],
    "sg:phone":"+44 1708 344548",
    "sg:postcode":"RM3 7HL",
    "sg:province":"Essex",
    "sg:tags":[
        "heating"
    ],
    "wof:name":"S Birch",
    "wof:placetype":"venue"
},
  "geometry": {"coordinates":[0.2063380033,51.5990257263],"type":"Point"}
}