{
  "type": "Feature",
  "properties": {
    "addr:full":"Highshore House, New Bridge Street Truro Cornwall TR1 2AA",
    "addr:postcode":"tr1 2aa",
    "addr:street":"New Bridge Street",
    "iso:country":"GB",
    "sg:address":"Highshore House, New Bridge Street",
    "sg:city":"Truro",
    "sg:classifiers":[
        {
            "category":"Building & Trades",
            "subcategory":"Construction",
            "type":"Services"
        }
    ],
    "sg:postcode":"TR1 2AA",
    "sg:province":"Cornwall",
    "sg:tags":[
        "builder"
    ],
    "wof:name":"Cruzan Construction Ltd",
    "wof:placetype":"venue"
},
  "geometry": {"coordinates":[-5.048279,50.264126],"type":"Point"}
}