{
  "type": "Feature",
  "properties": {
    "addr:full":"77 Green La Scarborough North Yorkshire YO12 6HT",
    "addr:housenumber":"77",
    "addr:postcode":"yo12 6ht",
    "addr:street":"Green La Scarborough",
    "iso:country":"GB",
    "sg:address":"77 Green La",
    "sg:city":"Scarborough",
    "sg:classifiers":[
        {
            "category":"Place Of Worship",
            "type":"Public Place"
        }
    ],
    "sg:phone":"+44 1723 363205",
    "sg:postcode":"YO12 6HT",
    "sg:province":"North Yorkshire",
    "wof:name":"St Mark C of E Church",
    "wof:placetype":"venue"
},
  "geometry": {"coordinates":[-0.4308289886,54.2932510376],"type":"Point"}
}