{
  "type": "Feature",
  "properties": {
    "addr:full":"Unit 5c & D West Horndon Industrial, Park, Station Road West Horndon Brentwood Essex CM13 3XL",
    "addr:housenumber":"unit;& d",
    "addr:postcode":"cm13 3xl",
    "addr:street":"West Horndon Industrial Park Station Road West",
    "iso:country":"GB",
    "sg:address":"Unit 5c & D West Horndon Industrial, Park, Station Road West Horndon",
    "sg:city":"Brentwood",
    "sg:classifiers":[
        {
            "category":"Freight",
            "type":"Transportation"
        }
    ],
    "sg:phone":"+44 1277 812122",
    "sg:postcode":"CM13 3XL",
    "sg:province":"Essex",
    "sg:tags":[
        "forwarders"
    ],
    "wof:name":"Jayco International Forwarding Ltd.",
    "wof:placetype":"venue"
},
  "geometry": {"coordinates":[0.3374300003,51.5693511963],"type":"Point"}
}