{
  "type": "Feature",
  "properties": {
    "addr:full":"132 Moss Lane, Timperley Altrincham Cheshire WA15 6JL",
    "addr:housenumber":"132",
    "addr:postcode":"wa15 6jl",
    "addr:street":"Moss Lane",
    "iso:country":"GB",
    "sg:address":"132 Moss Lane, Timperley",
    "sg:city":"Altrincham",
    "sg:classifiers":[
        {
            "category":"Arts & Performance",
            "subcategory":"Theater",
            "type":"Entertainment"
        }
    ],
    "sg:phone":"+44 161 928 7115",
    "sg:postcode":"WA15 6JL",
    "sg:province":"Cheshire",
    "sg:tags":[
        "theatrical",
        "agency"
    ],
    "wof:name":"The Producers Casting Agency",
    "wof:placetype":"venue"
},
  "geometry": {"coordinates":[-2.3332540989,53.4005203247],"type":"Point"}
}