{
  "type": "Feature",
  "properties": {
    "addr:full":"7-11 Cross Arcade Leeds West Yorkshire LS1 6AZ",
    "addr:housenumber":"7-11",
    "addr:postcode":"ls1 6az",
    "addr:street":"Cross",
    "iso:country":"GB",
    "sg:address":"7-11 Cross Arcade",
    "sg:city":"Leeds",
    "sg:classifiers":[
        {
            "category":"Shopping",
            "subcategory":"Clothing, Apparel, & Fashions",
            "type":"Retail Goods"
        }
    ],
    "sg:phone":"+44 113 243 2110",
    "sg:postcode":"LS1 6AZ",
    "sg:province":"West Yorkshire",
    "sg:tags":[
        "menswear"
    ],
    "wof:name":"Flannels Accessories",
    "wof:placetype":"venue"
},
  "geometry": {"coordinates":[-1.5410430431,53.7979354858],"type":"Point"}
}