{
  "type": "Feature",
  "properties": {
    "addr:full":"Unit Q, Rocket Trading Centre, Bowring Park Road Liverpool Merseyside L14 3NZ",
    "addr:postcode":"l14 3nz",
    "addr:street":"Bowring Park Road",
    "iso:country":"GB",
    "sg:address":"Unit Q, Rocket Trading Centre, Bowring Park Road",
    "sg:city":"Liverpool",
    "sg:classifiers":[
        {
            "category":"Building & Trades",
            "subcategory":"Construction",
            "type":"Services"
        }
    ],
    "sg:phone":"+44 151 220 3767",
    "sg:postcode":"L14 3NZ",
    "sg:province":"Merseyside",
    "sg:tags":[
        "builder"
    ],
    "wof:name":"J Hawkins Ltd.",
    "wof:placetype":"venue"
},
  "geometry": {"coordinates":[-2.8950030804,53.4065818787],"type":"Point"}
}