{
  "type": "Feature",
  "properties": {
    "iso:country":"GB",
    "sg:address":"Great West Road, Syon Lane",
    "sg:city":"Isleworth",
    "sg:classifiers":[
        {
            "category":"Home & Garden",
            "subcategory":"Household Appliances",
            "type":"Retail Goods"
        }
    ],
    "sg:phone":"+44 845 600 7002",
    "sg:postcode":"TW7 5NP",
    "sg:province":"Greater London",
    "sg:tags":[
        "electrical",
        "domestic"
    ],
    "wof:name":"Comet Group Plc",
    "wof:placetype":"venue"
},
  "geometry": {"coordinates":[-0.3261,51.483566],"type":"Point"}
}