{
  "type": "Feature",
  "properties": {
    "iso:country":"GB",
    "sg:address":"1 Riverside, Edge Bolton",
    "sg:city":"Shrewsbury",
    "sg:classifiers":[
        {
            "category":"Manufacturing",
            "subcategory":"Petroleum Products",
            "type":"Manufacturing & Wholesale Goods"
        }
    ],
    "sg:phone":"+44 1939 250802",
    "sg:postcode":"SY4 4EJ",
    "sg:province":"Shropshire",
    "sg:tags":[
        "double",
        "glazing"
    ],
    "wof:name":"Riverside Joinery",
    "wof:placetype":"venue"
},
  "geometry": {"coordinates":[-2.6414,52.791618],"type":"Point"}
}