{
  "type": "Feature",
  "properties": {
    "addr:full":"Town House, 2 Wemyssfield Kirkcaldy Fife KY1 1XW",
    "addr:housenumber":"2",
    "addr:postcode":"ky1 1xw",
    "addr:street":"Wemyssfield",
    "iso:country":"GB",
    "sg:address":"Town House, 2 Wemyssfield",
    "sg:city":"Kirkcaldy",
    "sg:classifiers":[
        {
            "category":"Government",
            "subcategory":"Office",
            "type":"Public Place"
        }
    ],
    "sg:phone":"+44 1592 412121",
    "sg:postcode":"KY1 1XW",
    "sg:province":"Fife",
    "sg:tags":[
        "death",
        "births",
        "marriage",
        "birth",
        "registration",
        "local"
    ],
    "wof:name":"Registration of Births Deaths & Marriages",
    "wof:placetype":"venue"
},
  "geometry": {"coordinates":[-3.163029,56.109596],"type":"Point"}
}