{
  "type": "Feature",
  "properties": {
    "iso:country":"GB",
    "sg:address":"26a Market Street",
    "sg:city":"Leicester",
    "sg:classifiers":[
        {
            "category":"Food & Beverages",
            "subcategory":"Candy",
            "type":"Retail Goods"
        }
    ],
    "sg:phone":"+44 116 255 2018",
    "sg:postcode":"LE1 6DP",
    "sg:province":"Leicestershire",
    "sg:tags":[
        "confectioner"
    ],
    "wof:name":"Thorntons Plc",
    "wof:placetype":"venue"
},
  "geometry": {"coordinates":[-1.133116,52.632687],"type":"Point"}
}