{
  "type": "Feature",
  "properties": {
    "addr:full":"6 Deansfield Close, Armthorpe Doncaster South Yorkshire DN3 3BZ",
    "addr:housenumber":"6",
    "addr:postcode":"dn3 3bz",
    "addr:street":"Deansfield Close",
    "iso:country":"GB",
    "sg:address":"6 Deansfield Close, Armthorpe",
    "sg:city":"Doncaster",
    "sg:classifiers":[
        {
            "category":"Building & Trades",
            "subcategory":"Construction",
            "type":"Services"
        }
    ],
    "sg:postcode":"DN3 3BZ",
    "sg:province":"South Yorkshire",
    "sg:tags":[
        "glazier",
        "decorator",
        "painter"
    ],
    "wof:name":"J W Burton",
    "wof:placetype":"venue"
},
  "geometry": {"coordinates":[-1.0532510281,53.5322647095],"type":"Point"}
}