{
  "type": "Feature",
  "properties": {
    "addr:full":"35 Darwen Street Blackburn Lancashire BB2 2BH",
    "addr:housenumber":"35",
    "addr:postcode":"bb2 2bh",
    "addr:street":"Darwen Street",
    "iso:country":"GB",
    "sg:address":"35 Darwen Street",
    "sg:city":"Blackburn",
    "sg:classifiers":[
        {
            "category":"Fast Food",
            "type":"Food & Drink"
        }
    ],
    "sg:phone":"+44 1254 264827",
    "sg:postcode":"BB2 2BH",
    "sg:province":"Lancashire",
    "sg:tags":[
        "away",
        "meal",
        "outlet",
        "take"
    ],
    "wof:name":"Pyramid Pizza & Kebab",
    "wof:placetype":"venue"
},
  "geometry": {"coordinates":[-2.4823460579,53.7465744019],"type":"Point"}
}