{
  "type": "Feature",
  "properties": {
    "iso:country":"GB",
    "sg:address":"29 Palace Avenue",
    "sg:city":"Paignton",
    "sg:classifiers":[
        {
            "category":"Cafe",
            "type":"Food & Drink"
        }
    ],
    "sg:phone":"+44 1803 666957",
    "sg:postcode":"TQ3 3EQ",
    "sg:province":"Devon",
    "sg:tags":[
        "tea",
        "room"
    ],
    "wof:name":"Cafe Du Palais",
    "wof:placetype":"venue"
},
  "geometry": {"coordinates":[-3.569561,50.435646],"type":"Point"}
}