{
  "type": "Feature",
  "properties": {
    "iso:country":"GB",
    "sg:address":"67 Mill Lane, Trimley",
    "sg:city":"Felixstowe",
    "sg:classifiers":[
        {
            "category":"Building & Trades",
            "subcategory":"Plumbing",
            "type":"Services"
        }
    ],
    "sg:postcode":"IP11 0RP",
    "sg:province":"Suffolk",
    "sg:tags":[
        "heating"
    ],
    "wof:name":"Heating Services",
    "wof:placetype":"venue"
},
  "geometry": {"coordinates":[1.311113,51.993538],"type":"Point"}
}