{
  "type": "Feature",
  "properties": {
    "iso:country":"GB",
    "sg:address":"127 Rectory Rd",
    "sg:city":"Redditch",
    "sg:classifiers":[
        {
            "category":"Food & Beverages",
            "subcategory":"Meat & Fish",
            "type":"Retail Goods"
        },
        {
            "category":"Food & Beverages",
            "subcategory":"Groceries & Convenience Stores",
            "type":"Retail Goods"
        }
    ],
    "sg:phone":"+44 1527 543649",
    "sg:postcode":"B97 4LG",
    "sg:province":"Warwickshire",
    "sg:tags":[
        "shop",
        "chip"
    ],
    "wof:name":"Rectory Road Fish Bar",
    "wof:placetype":"venue"
},
  "geometry": {"coordinates":[-1.950157,52.294582],"type":"Point"}
}