{
  "type": "Feature",
  "properties": {
    "addr:full":"Galt House, 31 Bank St Irvine North Ayrshire KA12 0LL",
    "addr:housenumber":"31",
    "addr:postcode":"ka12 0ll",
    "addr:street":"Bank St",
    "iso:country":"GB",
    "sg:address":"Galt House, 31 Bank St",
    "sg:city":"Irvine",
    "sg:classifiers":[
        {
            "category":"Shopping",
            "subcategory":"Clothing, Apparel, & Fashions",
            "type":"Retail Goods"
        }
    ],
    "sg:phone":"+44 1294 311777",
    "sg:postcode":"KA12 0LL",
    "sg:province":"North Ayrshire",
    "sg:tags":[
        "mnfr",
        "staff",
        "wear",
        "uniform"
    ],
    "wof:name":"D.M.K Design & Print",
    "wof:placetype":"venue"
},
  "geometry": {"coordinates":[-4.6645379066,55.616027832],"type":"Point"}
}