{
  "type": "Feature",
  "properties": {
    "addr:full":"Bush Hay, The Street Yatton Keynell Chippenham Gloucestershire SN14 7BA",
    "addr:postcode":"sn14 7ba",
    "addr:street":"Bush Hay The Street",
    "iso:country":"GB",
    "sg:address":"Bush Hay, The Street Yatton Keynell",
    "sg:city":"Chippenham",
    "sg:classifiers":[
        {
            "category":"Professional",
            "subcategory":"Management & Consulting",
            "type":"Services"
        }
    ],
    "sg:postcode":"SN14 7BA",
    "sg:province":"Gloucestershire",
    "sg:tags":[
        "consultant",
        "business"
    ],
    "wof:name":"M & L Consultancy Services Ltd",
    "wof:placetype":"venue"
},
  "geometry": {"coordinates":[-2.194081,51.48764],"type":"Point"}
}