{
  "type": "Feature",
  "properties": {
    "addr:full":"Woodlea Farm Bishop Auckland Durham DL14 0PU",
    "addr:postcode":"dl14 0pu",
    "iso:country":"GB",
    "sg:address":"Woodlea Farm",
    "sg:city":"Bishop Auckland",
    "sg:classifiers":[
        {
            "category":"Farming",
            "subcategory":"Livestock Farm",
            "type":"Manufacturing & Wholesale Goods"
        }
    ],
    "sg:phone":"+44 1388 833331",
    "sg:postcode":"DL14 0PU",
    "sg:province":"Durham",
    "sg:tags":[
        "others"
    ],
    "wof:name":"C Allanson",
    "wof:placetype":"venue"
},
  "geometry": {"coordinates":[-1.680494,54.650101],"type":"Point"}
}