{
  "type": "Feature",
  "properties": {
    "addr:full":"Unit 3, Valley Works, Greenland Rd Sheffield South Yorkshire S9 5EX",
    "addr:housenumber":"unit 3",
    "addr:postcode":"s9 5ex",
    "addr:street":"Valley Works Greenland Rd",
    "iso:country":"GB",
    "sg:address":"Unit 3, Valley Works, Greenland Rd",
    "sg:city":"Sheffield",
    "sg:classifiers":[
        {
            "category":"Mining & Drilling",
            "type":"Manufacturing & Wholesale Goods"
        }
    ],
    "sg:phone":"+44 114 243 5533",
    "sg:postcode":"S9 5EX",
    "sg:province":"South Yorkshire",
    "sg:tags":[
        "contractor"
    ],
    "wof:name":"Corecut Ltd",
    "wof:placetype":"venue"
},
  "geometry": {"coordinates":[-1.4154700041,53.3984184265],"type":"Point"}
}