{
  "type": "Feature",
  "properties": {
    "iso:country":"GB",
    "sg:address":"5 Davis Way",
    "sg:city":"Fareham",
    "sg:classifiers":[
        {
            "category":"Retail",
            "subcategory":"Auto Repair",
            "type":"Services"
        }
    ],
    "sg:phone":"+44 1329 827979",
    "sg:postcode":"PO14 1JF",
    "sg:province":"Hampshire",
    "sg:tags":[
        "modification",
        "garage"
    ],
    "wof:name":"Newgate Motor Services",
    "wof:placetype":"venue"
},
  "geometry": {"coordinates":[-1.185428977,50.8386688232],"type":"Point"}
}