{
  "type": "Feature",
  "properties": {
    "addr:full":"27 Whitelee Gardens Hebden Bridge West Yorkshire HX7 5PA",
    "addr:housenumber":"27",
    "addr:postcode":"hx7 5pa",
    "addr:street":"Whitelee Gardens;West",
    "iso:country":"GB",
    "sg:address":"27 Whitelee Gardens",
    "sg:city":"Hebden Bridge",
    "sg:classifiers":[
        {
            "category":"Building & Trades",
            "subcategory":"Construction",
            "type":"Services"
        }
    ],
    "sg:phone":"+44 1422 883966",
    "sg:postcode":"HX7 5PA",
    "sg:province":"West Yorkshire",
    "sg:tags":[
        "decorator",
        "painter"
    ],
    "wof:name":"J K Jackson",
    "wof:placetype":"venue"
},
  "geometry": {"coordinates":[-1.9773639441,53.7306861877],"type":"Point"}
}