{
  "type": "Feature",
  "properties": {
    "addr:full":"76 Old Shoreham Road Brighton East Sussex BN1 5DD",
    "addr:housenumber":"76",
    "addr:postcode":"bn1 5dd",
    "addr:street":"Old Shoreham Road",
    "iso:country":"GB",
    "sg:address":"76 Old Shoreham Road",
    "sg:city":"Brighton",
    "sg:classifiers":[
        {
            "category":"Education",
            "subcategory":"Special Training",
            "type":"Public Place"
        }
    ],
    "sg:postcode":"BN1 5DD",
    "sg:province":"East Sussex",
    "sg:tags":[
        "aid",
        "first"
    ],
    "wof:name":"First Aid Training",
    "wof:placetype":"venue"
},
  "geometry": {"coordinates":[-0.1488569975,50.8335990906],"type":"Point"}
}