{
  "type": "Feature",
  "properties": {
    "addr:full":"231 Heath Road Leighton Buzzard Bedfordshire LU7 3AG",
    "addr:housenumber":"231",
    "addr:postcode":"lu7 3ag",
    "addr:street":"Heath Road",
    "iso:country":"GB",
    "sg:address":"231 Heath Road",
    "sg:city":"Leighton Buzzard",
    "sg:classifiers":[
        {
            "category":"Professional",
            "subcategory":"Management & Consulting",
            "type":"Services"
        }
    ],
    "sg:phone":"+44 1525 372613",
    "sg:postcode":"LU7 3AG",
    "sg:province":"Bedfordshire",
    "sg:tags":[
        "consultant",
        "business"
    ],
    "wof:name":"Interlink Systems Engineering Ltd.",
    "wof:placetype":"venue"
},
  "geometry": {"coordinates":[-0.6580770016,51.92993927],"type":"Point"}
}