{
  "type": "Feature",
  "properties": {
    "iso:country":"GB",
    "sg:address":"Unit 9a, Silverhills Road",
    "sg:city":"Newton Abbot",
    "sg:classifiers":[
        {
            "category":"Retail",
            "subcategory":"Auto Repair",
            "type":"Services"
        }
    ],
    "sg:phone":"+44 1626 363630",
    "sg:postcode":"TQ12 5ND",
    "sg:province":"Devon",
    "sg:tags":[
        "modification",
        "garage"
    ],
    "wof:name":"Monnington Motors Ltd.",
    "wof:placetype":"venue"
},
  "geometry": {"coordinates":[-3.598299,50.517071],"type":"Point"}
}