{
  "type": "Feature",
  "properties": {
    "addr:full":"35 Forth Crescent Stirling Stirling FK8 1LG",
    "addr:housenumber":"35",
    "addr:postcode":"fk8 1lg",
    "addr:street":"Forth Crescent",
    "iso:country":"GB",
    "sg:address":"35 Forth Crescent",
    "sg:city":"Stirling",
    "sg:classifiers":[
        {
            "category":"Personal",
            "subcategory":"Beauty Salon",
            "type":"Services"
        },
        {
            "category":"Personal",
            "subcategory":"Barber",
            "type":"Services"
        }
    ],
    "sg:phone":"+44 1786 473557",
    "sg:postcode":"FK8 1LG",
    "sg:province":"Stirling",
    "sg:tags":[
        "unisex",
        "hairdresser"
    ],
    "wof:name":"The Hair Studio",
    "wof:placetype":"venue"
},
  "geometry": {"coordinates":[-3.9292869568,56.1239852905],"type":"Point"}
}