{
  "type": "Feature",
  "properties": {
    "addr:full":"Shopping Precinct Merthyr Tydfil Merthyr Tydfil CF47 8SF",
    "addr:postcode":"cf47 8sf",
    "addr:street":"Merthyr Tydfil",
    "iso:country":"GB",
    "sg:address":"Shopping Precinct",
    "sg:city":"Merthyr Tydfil",
    "sg:classifiers":[
        {
            "category":"Fast Food",
            "type":"Food & Drink"
        }
    ],
    "sg:phone":"+44 1685 384332",
    "sg:postcode":"CF47 8SF",
    "sg:province":"Merthyr Tydfil",
    "sg:tags":[
        "away",
        "meal",
        "outlet",
        "take"
    ],
    "wof:name":"Jim Shu Sing",
    "wof:placetype":"venue"
},
  "geometry": {"coordinates":[-3.376464,51.750439],"type":"Point"}
}