{
  "type": "Feature",
  "properties": {
    "addr:full":"Unit 3 Wilton Shopping Village, Wilton Salisbury Wiltshire SP2 0RS",
    "addr:housenumber":"unit 3",
    "addr:postcode":"sp2 0rs",
    "addr:street":"Wilton Shopping Village",
    "iso:country":"GB",
    "sg:address":"Unit 3 Wilton Shopping Village, Wilton",
    "sg:city":"Salisbury",
    "sg:classifiers":[
        {
            "category":"Shopping",
            "subcategory":"Clothing, Apparel, & Fashions",
            "type":"Retail Goods"
        }
    ],
    "sg:phone":"+44 1722 741310",
    "sg:postcode":"SP2 0RS",
    "sg:province":"Wiltshire",
    "sg:tags":[
        "ladieswear"
    ],
    "wof:name":"C  E  & I  Gowns Ltd.",
    "wof:placetype":"venue"
},
  "geometry": {"coordinates":[-1.8632769585,51.0795478821],"type":"Point"}
}