{
  "type": "Feature",
  "properties": {
    "addr:full":"Unit 7 Derwent Way, Wath West Industrial Estate Rotherham South Yorkshire S63 7EN",
    "addr:housenumber":"unit 7;estate",
    "addr:postcode":"s63 7en",
    "addr:street":"Derwent Way;South",
    "iso:country":"GB",
    "sg:address":"Unit 7 Derwent Way, Wath West Industrial Estate",
    "sg:city":"Rotherham",
    "sg:classifiers":[
        {
            "category":"Retail",
            "subcategory":"Auto Repair",
            "type":"Services"
        }
    ],
    "sg:phone":"+44 1709 878908",
    "sg:postcode":"S63 7EN",
    "sg:province":"South Yorkshire",
    "sg:tags":[
        "car",
        "servicing",
        "radiator"
    ],
    "wof:name":"South Yorkshire Radiators",
    "wof:placetype":"venue"
},
  "geometry": {"coordinates":[-1.3200700283,53.4992485046],"type":"Point"}
}