{
  "type": "Feature",
  "properties": {
    "iso:country":"GB",
    "sg:address":"Glastonbury Road, Meare",
    "sg:city":"Glastonbury",
    "sg:classifiers":[
        {
            "category":"Social Services",
            "subcategory":"Retirement Home",
            "type":"Services"
        }
    ],
    "sg:phone":"+44 1458 860379",
    "sg:postcode":"BA6 9SN",
    "sg:province":"Somerset",
    "sg:tags":[
        "residential",
        "care"
    ],
    "wof:name":"Down House",
    "wof:placetype":"venue"
},
  "geometry": {"coordinates":[-2.717009,51.147591],"type":"Point"}
}