{
  "type": "Feature",
  "properties": {
    "iso:country":"GB",
    "sg:address":"Highburrow Lane, Wilson Way",
    "sg:city":"Redruth",
    "sg:classifiers":[
        {
            "category":"Communications",
            "subcategory":"Newspaper",
            "type":"Services"
        }
    ],
    "sg:phone":"+44 1209 313556",
    "sg:postcode":"TR15 3RX",
    "sg:province":"Cornwall",
    "sg:tags":[
        "magazine"
    ],
    "wof:name":"T Magazine Ltd.",
    "wof:placetype":"venue"
},
  "geometry": {"coordinates":[-5.261086,50.22477],"type":"Point"}
}