{
  "type": "Feature",
  "properties": {
    "addr:full":"121 The Horsefair Bristol City of Bristol BS1 3JY",
    "addr:housenumber":"121",
    "addr:postcode":"bs1 3jy",
    "addr:street":"The Horsefair",
    "iso:country":"GB",
    "sg:address":"121 The Horsefair",
    "sg:city":"Bristol",
    "sg:classifiers":[
        {
            "category":"Home & Garden",
            "subcategory":"Furniture",
            "type":"Retail Goods"
        }
    ],
    "sg:phone":"+44 117 925 2185",
    "sg:postcode":"BS1 3JY",
    "sg:province":"City of Bristol",
    "sg:tags":[
        "built-in",
        "fitted"
    ],
    "wof:name":"Sharps Bedrooms",
    "wof:placetype":"venue"
},
  "geometry": {"coordinates":[-2.587463,51.458981],"type":"Point"}
}