{
  "type": "Feature",
  "properties": {
    "addr:full":"West Farm, Church St, Whixley York North Yorkshire YO26 8AR",
    "addr:postcode":"yo26 8ar",
    "addr:street":"Church St",
    "iso:country":"GB",
    "sg:address":"West Farm, Church St, Whixley",
    "sg:city":"York",
    "sg:classifiers":[
        {
            "category":"Farming",
            "subcategory":"Dairy Farm",
            "type":"Manufacturing & Wholesale Goods"
        }
    ],
    "sg:phone":"+44 1423 330595",
    "sg:postcode":"YO26 8AR",
    "sg:province":"North Yorkshire",
    "wof:name":"D Bramley",
    "wof:placetype":"venue"
},
  "geometry": {"coordinates":[-1.327428,54.016209],"type":"Point"}
}