{
  "type": "Feature",
  "properties": {
    "addr:full":"Unit M Airport Executive Park, Presidents Way Luton Bedfordshire LU2 9NY",
    "addr:postcode":"lu2 9ny",
    "addr:street":"Executive Park Presidents Way",
    "iso:country":"GB",
    "sg:address":"Unit M Airport Executive Park, Presidents Way",
    "sg:city":"Luton",
    "sg:classifiers":[
        {
            "category":"Coffee & Tea",
            "type":"Food & Drink"
        }
    ],
    "sg:phone":"+44 1582 418222",
    "sg:postcode":"LU2 9NY",
    "sg:province":"Bedfordshire",
    "wof:name":"First Choice Coffee Ltd.",
    "wof:placetype":"venue"
},
  "geometry": {"coordinates":[-0.375695,51.877029],"type":"Point"}
}