{
  "type": "Feature",
  "properties": {
    "iso:country":"GB",
    "sg:address":"31a Plashet Road",
    "sg:city":"London",
    "sg:classifiers":[
        {
            "category":"Shopping",
            "subcategory":"Clothing, Apparel, & Fashions",
            "type":"Retail Goods"
        }
    ],
    "sg:phone":"+44 20 8470 4331",
    "sg:postcode":"E13 0QA",
    "sg:province":"Greater London",
    "sg:tags":[
        "leather",
        "garment"
    ],
    "wof:name":"Intu Manufacturing Co",
    "wof:placetype":"venue"
},
  "geometry": {"coordinates":[0.024453,51.537197],"type":"Point"}
}