{
  "type": "Feature",
  "properties": {
    "addr:full":"50 Gresham Street, 4th Floor London Greater London EC2V 7AY",
    "addr:housenumber":"50;4th",
    "addr:postcode":"ec2v 7ay",
    "addr:street":"Gresham Street;Floor",
    "iso:country":"GB",
    "sg:address":"50 Gresham Street, 4th Floor",
    "sg:city":"London",
    "sg:classifiers":[
        {
            "category":"Airline",
            "type":"Transportation"
        }
    ],
    "sg:phone":"+44 20 7600 5138",
    "sg:postcode":"EC2V 7AY",
    "sg:province":"Greater London",
    "sg:tags":[
        "aircraft",
        "charter"
    ],
    "wof:name":"Sach & Co. Ltd.",
    "wof:placetype":"venue"
},
  "geometry": {"coordinates":[-0.093359,51.515419],"type":"Point"}
}