{
  "type": "Feature",
  "properties": {
    "iso:country":"GB",
    "sg:address":"12 Surrey Road",
    "sg:city":"Barking",
    "sg:classifiers":[
        {
            "category":"Building & Trades",
            "subcategory":"Construction",
            "type":"Services"
        }
    ],
    "sg:postcode":"IG11 7QT",
    "sg:province":"Essex",
    "sg:tags":[
        "builder"
    ],
    "wof:name":"A J L Roberts",
    "wof:placetype":"venue"
},
  "geometry": {"coordinates":[0.091054,51.536529541],"type":"Point"}
}