{
  "type": "Feature",
  "properties": {
    "addr:full":"22 Burgate Canterbury Kent CT1 2HG",
    "addr:housenumber":"22",
    "addr:postcode":"ct1 2hg",
    "addr:street":"Burgate Canterbury",
    "iso:country":"GB",
    "sg:address":"22 Burgate",
    "sg:city":"Canterbury",
    "sg:classifiers":[
        {
            "category":"Professional",
            "subcategory":"Art Services",
            "type":"Services"
        }
    ],
    "sg:postcode":"CT1 2HG",
    "sg:province":"Kent",
    "sg:tags":[
        "framing"
    ],
    "wof:name":"Barter,Tony,",
    "wof:placetype":"venue"
},
  "geometry": {"coordinates":[1.082535,51.278858],"type":"Point"}
}