{
  "type": "Feature",
  "properties": {
    "iso:country":"GB",
    "sg:address":"19 Montpelier Street",
    "sg:city":"London",
    "sg:classifiers":[
        {
            "category":"Bars & Pubs",
            "type":"Food & Drink"
        }
    ],
    "sg:phone":"+44 20 7589 5251",
    "sg:postcode":"SW7 1HF",
    "sg:province":"Greater London",
    "sg:tags":[
        "pubs",
        "inn"
    ],
    "wof:name":"The Tea Clipper",
    "wof:placetype":"venue"
},
  "geometry": {"coordinates":[-0.1660429984,51.4996566772],"type":"Point"}
}