{
  "type": "Feature",
  "properties": {
    "addr:full":"Union Street Congleton Cheshire CW12 1JB",
    "addr:postcode":"cw12 1jb",
    "addr:street":"Union Street",
    "iso:country":"GB",
    "sg:address":"Union Street",
    "sg:city":"Congleton",
    "sg:classifiers":[
        {
            "category":"Home & Garden",
            "subcategory":"Home Furnishings",
            "type":"Retail Goods"
        }
    ],
    "sg:phone":"+44 1260 276163",
    "sg:postcode":"CW12 1JB",
    "sg:province":"Cheshire",
    "sg:tags":[
        "furnishers",
        "planner",
        "kitchen"
    ],
    "wof:name":"Finelines Hand Crafted Kitchens",
    "wof:placetype":"venue"
},
  "geometry": {"coordinates":[-2.214384079,53.1672210693],"type":"Point"}
}