{
  "type": "Feature",
  "properties": {
    "addr:full":"7 Penketh Av Manchester Greater Manchester M29 7DS",
    "addr:housenumber":"7",
    "addr:postcode":"m29 7ds",
    "addr:street":"Penketh Av",
    "iso:country":"GB",
    "sg:address":"7 Penketh Av",
    "sg:city":"Manchester",
    "sg:classifiers":[
        {
            "category":"Building & Trades",
            "subcategory":"Construction",
            "type":"Services"
        }
    ],
    "sg:phone":"+44 1942 884079",
    "sg:postcode":"M29 7DS",
    "sg:province":"Greater Manchester",
    "sg:tags":[
        "builder"
    ],
    "wof:name":"Building Trade Price Brokers",
    "wof:placetype":"venue"
},
  "geometry": {"coordinates":[-2.4548220634,53.5011634827],"type":"Point"}
}