{
  "type": "Feature",
  "properties": {
    "iso:country":"GB",
    "sg:address":"566 Rayleigh Road",
    "sg:city":"Leigh-on-sea",
    "sg:classifiers":[
        {
            "category":"Fast Food",
            "type":"Food & Drink"
        }
    ],
    "sg:phone":"+44 1702 527054",
    "sg:postcode":"SS9 5HX",
    "sg:province":"Essex",
    "sg:tags":[
        "away",
        "take"
    ],
    "wof:name":"Good Luck Take Away",
    "wof:placetype":"venue"
},
  "geometry": {"coordinates":[0.63929,51.572788],"type":"Point"}
}