{
  "type": "Feature",
  "properties": {
    "addr:full":"Castle House Press, North Chambers, Castle Arcade Cardiff Cardiff CF10 1BX",
    "addr:postcode":"cf10 1bx",
    "addr:street":"North Chambers Castle",
    "iso:country":"GB",
    "sg:address":"Castle House Press, North Chambers, Castle Arcade",
    "sg:city":"Cardiff",
    "sg:classifiers":[
        {
            "category":"Professional",
            "subcategory":"Art Services",
            "type":"Services"
        },
        {
            "category":"Utilities",
            "type":"Services"
        }
    ],
    "sg:postcode":"CF10 1BX",
    "sg:province":"Cardiff",
    "sg:tags":[
        "consultant",
        "design",
        "internet"
    ],
    "wof:name":"Kode Digital Ltd.",
    "wof:placetype":"venue"
},
  "geometry": {"coordinates":[-3.180669,51.481258],"type":"Point"}
}