{
  "type": "Feature",
  "properties": {
    "addr:full":"33 Harrow Place Stone Staffordshire ST15 8ST",
    "addr:housenumber":"33",
    "addr:postcode":"st15 8st",
    "addr:street":"Harrow Place",
    "iso:country":"GB",
    "sg:address":"33 Harrow Place",
    "sg:city":"Stone",
    "sg:classifiers":[
        {
            "category":"Communications",
            "type":"Services"
        }
    ],
    "sg:phone":"+44 1785 817536",
    "sg:postcode":"ST15 8ST",
    "sg:province":"Staffordshire",
    "sg:tags":[
        "data",
        "network"
    ],
    "wof:name":"Flow-Line Communications",
    "wof:placetype":"venue"
},
  "geometry": {"coordinates":[-2.1283199787,52.8954696655],"type":"Point"}
}