{
  "type": "Feature",
  "properties": {
    "iso:country":"GB",
    "sg:address":"51 Moorfield Road",
    "sg:city":"Cambridge",
    "sg:classifiers":[
        {
            "category":"Airport",
            "subcategory":"General Aviation",
            "type":"Transportation"
        }
    ],
    "sg:phone":"+44 1395 567808",
    "sg:postcode":"CB2 4PP",
    "sg:province":"Cambridgeshire",
    "wof:name":"F A M  Ltd.",
    "wof:placetype":"venue"
},
  "geometry": {"coordinates":[0.158493,52.096416],"type":"Point"}
}