{
  "type": "Feature",
  "properties": {
    "addr:full":"20 Montpelier Vale London Greater London SE3 0TA",
    "addr:housenumber":"20",
    "addr:postcode":"se3 0ta",
    "addr:street":"Montpelier Vale",
    "iso:country":"GB",
    "sg:address":"20 Montpelier Vale",
    "sg:city":"London",
    "sg:classifiers":[
        {
            "category":"Sports & Exercise",
            "subcategory":"Sports Center",
            "type":"Entertainment"
        }
    ],
    "sg:phone":"+44 20 8318 9905",
    "sg:postcode":"SE3 0TA",
    "sg:province":"Greater London",
    "sg:tags":[
        "shop",
        "good"
    ],
    "wof:name":"Just Associates Group Ltd.",
    "wof:placetype":"venue"
},
  "geometry": {"coordinates":[0.008774,51.466747],"type":"Point"}
}