{
  "type": "Feature",
  "properties": {
    "addr:full":"Old Station Llandrindod Wells Powys LD1 6NN",
    "addr:postcode":"ld1 6nn",
    "addr:street":"Llandrindod Wells",
    "iso:country":"GB",
    "sg:address":"Old Station",
    "sg:city":"Llandrindod Wells",
    "sg:classifiers":[
        {
            "category":"Recreation",
            "subcategory":"Campground",
            "type":"Entertainment"
        }
    ],
    "sg:phone":"+44 1597 810409",
    "sg:postcode":"LD1 6NN",
    "sg:province":"Powys",
    "sg:tags":[
        "caravan",
        "park"
    ],
    "wof:name":"The Caravan Club",
    "wof:placetype":"venue"
},
  "geometry": {"coordinates":[-3.377029,52.24575],"type":"Point"}
}