{
  "type": "Feature",
  "properties": {
    "iso:country":"GB",
    "sg:address":"206 Whitegate Drive",
    "sg:city":"Blackpool",
    "sg:classifiers":[
        {
            "category":"Shopping",
            "subcategory":"News",
            "type":"Retail Goods"
        }
    ],
    "sg:phone":"+44 1253 762583",
    "sg:postcode":"FY3 9JL",
    "sg:province":"Lancashire",
    "sg:tags":[
        "newsagent"
    ],
    "wof:name":"R & L Simpson",
    "wof:placetype":"venue"
},
  "geometry": {"coordinates":[-3.031568,53.808258],"type":"Point"}
}