{
  "type": "Feature",
  "properties": {
    "iso:country":"GB",
    "sg:address":"C/o Cooper Young, Kirkdale House Kirkdale Road",
    "sg:city":"London",
    "sg:classifiers":[
        {
            "category":"Shopping",
            "subcategory":"Department Store",
            "type":"Retail Goods"
        }
    ],
    "sg:postcode":"E11 1HP",
    "sg:province":"Greater London",
    "wof:name":"Servecrown Ltd",
    "wof:placetype":"venue"
},
  "geometry": {"coordinates":[0.0118549997,51.5692596436],"type":"Point"}
}