{
  "type": "Feature",
  "properties": {
    "addr:full":"12b Eleanors Cross Dunstable Bedfordshire LU6 1SU",
    "addr:housenumber":"12b",
    "addr:postcode":"lu6 1su",
    "addr:street":"Eleanors Cross",
    "iso:country":"GB",
    "sg:address":"12b Eleanors Cross",
    "sg:city":"Dunstable",
    "sg:classifiers":[
        {
            "category":"Social Services",
            "subcategory":"Job Training",
            "type":"Services"
        },
        {
            "category":"Personal",
            "subcategory":"Nail Salon",
            "type":"Services"
        }
    ],
    "sg:phone":"+44 1582 478378",
    "sg:postcode":"LU6 1SU",
    "sg:province":"Bedfordshire",
    "sg:tags":[
        "solarium",
        "tanning",
        "related",
        "activity"
    ],
    "wof:name":"Shades Tanning",
    "wof:placetype":"venue"
},
  "geometry": {"coordinates":[-0.523105979,51.8863258362],"type":"Point"}
}