{
  "type": "Feature",
  "properties": {
    "addr:full":"13 Gloucester Road Teddington Greater London TW11 0NS",
    "addr:housenumber":"13",
    "addr:postcode":"tw11 0ns",
    "addr:street":"Gloucester Road",
    "iso:country":"GB",
    "sg:address":"13 Gloucester Road",
    "sg:city":"Teddington",
    "sg:classifiers":[
        {
            "category":"Health Services",
            "subcategory":"Doctor",
            "type":"Services"
        }
    ],
    "sg:phone":"+44 20 8977 2516",
    "sg:postcode":"TW11 0NS",
    "sg:province":"Greater London",
    "sg:tags":[
        "practitioners"
    ],
    "wof:name":"Home Lodge Surgery",
    "wof:placetype":"venue"
},
  "geometry": {"coordinates":[-0.3441829979,51.4289207458],"type":"Point"}
}