{
  "type": "Feature",
  "properties": {
    "addr:full":"9 Queen St Leigh Lancashire WN7 4NQ",
    "addr:housenumber":"9",
    "addr:postcode":"wn7 4nq",
    "addr:street":"Queen St",
    "iso:country":"GB",
    "sg:address":"9 Queen St",
    "sg:city":"Leigh",
    "sg:classifiers":[
        {
            "category":"Shopping",
            "subcategory":"Pets & Pet Supplies",
            "type":"Retail Goods"
        }
    ],
    "sg:postcode":"WN7 4NQ",
    "sg:province":"Lancashire",
    "wof:name":"Ralphson,Robert,",
    "wof:placetype":"venue"
},
  "geometry": {"coordinates":[-2.512381,53.495895],"type":"Point"}
}