{
  "type": "Feature",
  "properties": {
    "addr:full":"Windsor Road Slough Berkshire SL1 2HJ",
    "addr:postcode":"sl1 2hj",
    "addr:street":"Windsor Road",
    "iso:country":"GB",
    "sg:address":"Windsor Road",
    "sg:city":"Slough",
    "sg:classifiers":[
        {
            "category":"Government",
            "subcategory":"Court House",
            "type":"Public Place"
        }
    ],
    "sg:phone":"+44 1753 521345",
    "sg:postcode":"SL1 2HJ",
    "sg:province":"Berkshire",
    "wof:name":"Lord Chancellors Department",
    "wof:placetype":"venue"
},
  "geometry": {"coordinates":[-0.5968809724,51.5068511963],"type":"Point"}
}