{
  "type": "Feature",
  "properties": {
    "iso:country":"GB",
    "sg:address":"Leighton Hall Farm, Leighton Road",
    "sg:city":"Ellesmere Port",
    "sg:classifiers":[
        {
            "category":"Farming",
            "subcategory":"Farm",
            "type":"Manufacturing & Wholesale Goods"
        }
    ],
    "sg:phone":"+44 151 336 7605",
    "sg:postcode":"CH64 3SW",
    "sg:province":"Cheshire",
    "sg:tags":[
        "mixed",
        "crop"
    ],
    "wof:name":"Stephen Geoffrey & Clive Albert Lloyd",
    "wof:placetype":"venue"
},
  "geometry": {"coordinates":[-3.0717899799,53.3054618835],"type":"Point"}
}