{
  "type": "Feature",
  "properties": {
    "addr:full":"1 Ballina Mews Southampton Hampshire SO16 4LN",
    "addr:housenumber":"1",
    "addr:postcode":"so16 4ln",
    "addr:street":"Ballina Mews",
    "iso:country":"GB",
    "sg:address":"1 Ballina Mews",
    "sg:city":"Southampton",
    "sg:classifiers":[
        {
            "category":"Professional",
            "subcategory":"Engineering",
            "type":"Services"
        }
    ],
    "sg:postcode":"SO16 4LN",
    "sg:province":"Hampshire",
    "sg:tags":[
        "contractor",
        "electrical",
        "engineer"
    ],
    "wof:name":"R E S Electrical Services",
    "wof:placetype":"venue"
},
  "geometry": {"coordinates":[-1.44381,50.92313],"type":"Point"}
}