{
  "type": "Feature",
  "properties": {
    "addr:full":"91 Macklin Street Derby Derbyshire DE1 1LG",
    "addr:housenumber":"91",
    "addr:postcode":"de1 1lg",
    "addr:street":"Macklin Street",
    "iso:country":"GB",
    "sg:address":"91 Macklin Street",
    "sg:city":"Derby",
    "sg:classifiers":[
        {
            "category":"Shopping",
            "subcategory":"Books",
            "type":"Retail Goods"
        }
    ],
    "sg:phone":"+44 1332 384248",
    "sg:postcode":"DE1 1LG",
    "sg:province":"Derbyshire",
    "sg:tags":[
        "bookseller",
        "retailer"
    ],
    "wof:name":"The Railway Bookshop",
    "wof:placetype":"venue"
},
  "geometry": {"coordinates":[-1.481714,52.920959],"type":"Point"}
}