{
  "type": "Feature",
  "properties": {
    "iso:country":"GB",
    "sg:address":"Brede Lane, Sedlescombe",
    "sg:city":"Battle",
    "sg:classifiers":[
        {
            "category":"Education",
            "subcategory":"School",
            "type":"Public Place"
        }
    ],
    "sg:phone":"+44 1424 870585",
    "sg:postcode":"TN33 0QN",
    "sg:province":"East Sussex",
    "sg:tags":[
        "local",
        "authority"
    ],
    "wof:name":"Sedlescombe C of E Primary School",
    "wof:placetype":"venue"
},
  "geometry": {"coordinates":[0.55441,50.940094],"type":"Point"}
}