{
  "type": "Feature",
  "properties": {
    "iso:country":"GB",
    "sg:address":"Beck House, South Ambersham",
    "sg:city":"Midhurst",
    "sg:classifiers":[
        {
            "category":"Museum",
            "subcategory":"Art Museum",
            "type":"Entertainment"
        }
    ],
    "sg:phone":"+44 1798 861581",
    "sg:postcode":"GU29 0BX",
    "sg:province":"West Sussex",
    "sg:tags":[
        "gallery"
    ],
    "wof:name":"Peter's Barn Gallery",
    "wof:placetype":"venue"
},
  "geometry": {"coordinates":[-0.74058,50.984913],"type":"Point"}
}