{
  "type": "Feature",
  "properties": {
    "addr:full":"65 Fortess Road London Greater London NW5 1AG",
    "addr:housenumber":"65",
    "addr:postcode":"nw5 1ag",
    "addr:street":"Fortess Road",
    "iso:country":"GB",
    "sg:address":"65 Fortess Road",
    "sg:city":"London",
    "sg:classifiers":[
        {
            "category":"Professional",
            "subcategory":"Computer Services",
            "type":"Services"
        }
    ],
    "sg:phone":"+44 20 7485 3225",
    "sg:postcode":"NW5 1AG",
    "sg:province":"Greater London",
    "sg:tags":[
        "consultant"
    ],
    "wof:name":"Prologic Systems Ltd.",
    "wof:placetype":"venue"
},
  "geometry": {"coordinates":[-0.1403850019,51.5542678833],"type":"Point"}
}