{
  "type": "Feature",
  "properties": {
    "addr:full":"Unit 2g Thomas James Centre, Brigehouse Mills, Station Rd Howarth Keighley North Yorkshire BD22 8PA",
    "addr:housenumber":"2g",
    "addr:postcode":"bd22 8pa",
    "addr:street":"Thomas James;Station Rd",
    "iso:country":"GB",
    "sg:address":"Unit 2g Thomas James Centre, Brigehouse Mills, Station Rd Howarth",
    "sg:city":"Keighley",
    "sg:classifiers":[
        {
            "category":"Manufacturing",
            "subcategory":"Signs",
            "type":"Manufacturing & Wholesale Goods"
        }
    ],
    "sg:phone":"+44 1535 644355",
    "sg:postcode":"BD22 8PA",
    "sg:province":"North Yorkshire",
    "sg:tags":[
        "nameplate"
    ],
    "wof:name":"A P S Sign Makers & Writers",
    "wof:placetype":"venue"
},
  "geometry": {"coordinates":[-1.9481699467,53.8284187317],"type":"Point"}
}