{
  "type": "Feature",
  "properties": {
    "iso:country":"GB",
    "sg:address":"185 Granton Road",
    "sg:city":"Edinburgh",
    "sg:classifiers":[
        {
            "category":"Professional",
            "subcategory":"Art Services",
            "type":"Services"
        },
        {
            "category":"Building & Trades",
            "subcategory":"Construction",
            "type":"Services"
        },
        {
            "category":"Health Services",
            "subcategory":"Podiatrist",
            "type":"Services"
        }
    ],
    "sg:phone":"+44 131 552 5088",
    "sg:postcode":"EH5 3RQ",
    "sg:province":"City of Edinburgh",
    "sg:tags":[
        "podiatrists",
        "decorator",
        "painter",
        "chiropodist"
    ],
    "wof:name":"James Marshall",
    "wof:placetype":"venue"
},
  "geometry": {"coordinates":[-3.2162408829,55.9785575867],"type":"Point"}
}