{
  "type": "Feature",
  "properties": {
    "iso:country":"GB",
    "sg:address":"89 Foxholes Road",
    "sg:city":"Rochdale",
    "sg:classifiers":[
        {
            "category":"Building & Trades",
            "subcategory":"Construction",
            "type":"Services"
        }
    ],
    "sg:phone":"+44 1706 523950",
    "sg:postcode":"OL12 0EF",
    "sg:province":"Lancashire",
    "sg:tags":[
        "builder"
    ],
    "wof:name":"C A B Building Services",
    "wof:placetype":"venue"
},
  "geometry": {"coordinates":[-2.149023056,53.6273384094],"type":"Point"}
}