{
  "type": "Feature",
  "properties": {
    "addr:full":"149 Old Ashby Road Loughborough Leicestershire LE11 4PQ",
    "addr:housenumber":"149",
    "addr:postcode":"le11 4pq",
    "addr:street":"Old Ashby Road",
    "iso:country":"GB",
    "sg:address":"149 Old Ashby Road",
    "sg:city":"Loughborough",
    "sg:classifiers":[
        {
            "category":"Food & Beverages",
            "subcategory":"Groceries & Convenience Stores",
            "type":"Retail Goods"
        }
    ],
    "sg:phone":"+44 1509 265121",
    "sg:postcode":"LE11 4PQ",
    "sg:province":"Leicestershire",
    "wof:name":"Spar",
    "wof:placetype":"venue"
},
  "geometry": {"coordinates":[-1.247416,52.764824],"type":"Point"}
}