{
  "type": "Feature",
  "properties": {
    "addr:full":"1 Hendre, Onllwyn Neath Neath Port Talbot SA10 9HH",
    "addr:housenumber":"1;onllwyn",
    "addr:postcode":"sa10 9hh",
    "addr:street":"Hendre",
    "iso:country":"GB",
    "sg:address":"1 Hendre, Onllwyn",
    "sg:city":"Neath",
    "sg:classifiers":[
        {
            "category":"Freight",
            "type":"Transportation"
        }
    ],
    "sg:postcode":"SA10 9HH",
    "sg:province":"Neath Port Talbot",
    "sg:tags":[
        "haulage",
        "road"
    ],
    "wof:name":"Williams,Tony,& Son Ltd",
    "wof:placetype":"venue"
},
  "geometry": {"coordinates":[-3.67853,51.77927],"type":"Point"}
}