{
  "type": "Feature",
  "properties": {
    "iso:country":"GB",
    "sg:address":"1 Hendre, Onllwyn",
    "sg:city":"Neath",
    "sg:classifiers":[
        {
            "category":"Freight",
            "type":"Transportation"
        }
    ],
    "sg:postcode":"SA10 9HH",
    "sg:province":"Neath Port Talbot",
    "sg:tags":[
        "haulage",
        "road"
    ],
    "wof:name":"Williams,Tony,& Son Ltd",
    "wof:placetype":"venue"
},
  "geometry": {"coordinates":[-3.67853,51.77927],"type":"Point"}
}