{
  "type": "Feature",
  "properties": {
    "iso:country":"GB",
    "sg:address":"12 Tennand Close, Cheshunt",
    "sg:city":"Waltham Cross",
    "sg:classifiers":[
        {
            "category":"Building & Trades",
            "subcategory":"Construction",
            "type":"Services"
        }
    ],
    "sg:phone":"+44 1992 625537",
    "sg:postcode":"EN7 6DJ",
    "sg:province":"Greater London",
    "sg:tags":[
        "joiner",
        "carpenter"
    ],
    "wof:name":"James E Rowland",
    "wof:placetype":"venue"
},
  "geometry": {"coordinates":[-0.061534,51.720886],"type":"Point"}
}