{
  "type": "Feature",
  "properties": {
    "addr:full":"25 Caroline St Cardiff Cardiff CF1 1FF",
    "addr:housenumber":"25",
    "addr:postcode":"cf1 1ff",
    "addr:street":"Caroline St",
    "iso:country":"GB",
    "sg:address":"25 Caroline St",
    "sg:city":"Cardiff",
    "sg:classifiers":[
        {
            "category":"Bars & Pubs",
            "type":"Food & Drink"
        }
    ],
    "sg:phone":"+44 29 2064 9891",
    "sg:postcode":"CF1 1FF",
    "sg:province":"Cardiff",
    "sg:tags":[
        "pubs",
        "inn"
    ],
    "wof:name":"Kings Cross Hotel",
    "wof:placetype":"venue"
},
  "geometry": {"coordinates":[-3.1754190922,51.4781684875],"type":"Point"}
}