{
  "type": "Feature",
  "properties": {
    "iso:country":"GB",
    "sg:address":", Llanfarian",
    "sg:city":"Aberystwyth",
    "sg:classifiers":[
        {
            "category":"Recreation",
            "subcategory":"Campground",
            "type":"Entertainment"
        }
    ],
    "sg:phone":"+44 1970 617254",
    "sg:postcode":"SY23 4QQ",
    "sg:province":"Ceredigion",
    "sg:tags":[
        "caravan",
        "park"
    ],
    "wof:name":"Morfa Bychan Holiday Park",
    "wof:placetype":"venue"
},
  "geometry": {"coordinates":[-4.0033288002,52.3469009399],"type":"Point"}
}