{
  "type": "Feature",
  "properties": {
    "addr:full":"109 Hilary Avenue, Bowring Park Liverpool Merseyside L14 6UP",
    "addr:housenumber":"109",
    "addr:postcode":"l14 6up",
    "addr:street":"Hilary Avenue Bowring Park",
    "iso:country":"GB",
    "sg:address":"109 Hilary Avenue, Bowring Park",
    "sg:city":"Liverpool",
    "sg:classifiers":[
        {
            "category":"Building & Trades",
            "subcategory":"Construction",
            "type":"Services"
        }
    ],
    "sg:postcode":"L14 6UP",
    "sg:province":"Merseyside",
    "sg:tags":[
        "builder"
    ],
    "wof:name":"Marmion Contractors",
    "wof:placetype":"venue"
},
  "geometry": {"coordinates":[-2.8795111179,53.4104957581],"type":"Point"}
}