{
  "type": "Feature",
  "properties": {
    "iso:country":"GB",
    "sg:address":"Bracebridge House",
    "sg:city":"Lincoln",
    "sg:classifiers":[
        {
            "category":"Home & Garden",
            "subcategory":"Home Furnishings",
            "type":"Retail Goods"
        },
        {
            "category":"Building & Trades",
            "subcategory":"Construction",
            "type":"Services"
        }
    ],
    "sg:phone":"+44 1522 546149",
    "sg:postcode":"LN5 8QJ",
    "sg:province":"Lincolnshire",
    "sg:tags":[
        "mantelpiece",
        "fireplace"
    ],
    "wof:name":"Plaster Craft",
    "wof:placetype":"venue"
},
  "geometry": {"coordinates":[-0.5492190123,53.2054901123],"type":"Point"}
}