{
  "type": "Feature",
  "properties": {
    "addr:full":"Foundry St Northampton Northamptonshire NN1 1PN",
    "addr:postcode":"nn1 1pn",
    "addr:street":"Foundry St",
    "iso:country":"GB",
    "sg:address":"Foundry St",
    "sg:city":"Northampton",
    "sg:classifiers":[
        {
            "category":"Retail",
            "subcategory":"Auto Repair",
            "type":"Services"
        }
    ],
    "sg:postcode":"NN1 1PN",
    "sg:province":"Northamptonshire",
    "sg:tags":[
        "modification",
        "garage"
    ],
    "wof:name":"Underwood,A J,& Son",
    "wof:placetype":"venue"
},
  "geometry": {"coordinates":[-0.8984230161,52.2350234985],"type":"Point"}
}