{
  "type": "Feature",
  "properties": {
    "addr:full":"Vicarage, 5 Northcourt Clo Newport Isle of Wight PO30 3LD",
    "addr:housenumber":"5",
    "addr:postcode":"po30 3ld",
    "addr:street":"Northcourt Clo",
    "iso:country":"GB",
    "sg:address":"Vicarage, 5 Northcourt Clo",
    "sg:city":"Newport",
    "sg:classifiers":[
        {
            "category":"Place Of Worship",
            "type":"Public Place"
        }
    ],
    "sg:phone":"+44 1983 741044",
    "sg:postcode":"PO30 3LD",
    "sg:province":"Isle of Wight",
    "wof:name":"St Andrew's Chale",
    "wof:placetype":"venue"
},
  "geometry": {"coordinates":[-1.2959389687,50.7000999451],"type":"Point"}
}