{
  "type": "Feature",
  "properties": {
    "iso:country":"GB",
    "sg:address":"24 Deptford High St",
    "sg:city":"London",
    "sg:classifiers":[
        {
            "category":"Travel",
            "subcategory":"Travel Agent",
            "type":"Entertainment"
        }
    ],
    "sg:postcode":"SE8 4AF",
    "sg:province":"Greater London",
    "wof:name":"Bustin Loose",
    "wof:placetype":"venue"
},
  "geometry": {"coordinates":[-0.023223,51.474285],"type":"Point"}
}