{
  "type": "Feature",
  "properties": {
    "iso:country":"GB",
    "sg:address":"New Street, Bridgend Industrial Estate",
    "sg:city":"Bridgend",
    "sg:classifiers":[
        {
            "category":"Shopping",
            "subcategory":"Pets & Pet Supplies",
            "type":"Retail Goods"
        }
    ],
    "sg:phone":"+44 1656 668614",
    "sg:postcode":"CF31 3UD",
    "sg:province":"Bridgend",
    "sg:tags":[
        "sundries",
        "butcher"
    ],
    "wof:name":"Brolyn Butchers Supplies",
    "wof:placetype":"venue"
},
  "geometry": {"coordinates":[-3.560689,51.499222],"type":"Point"}
}