{
  "type": "Feature",
  "properties": {
    "iso:country":"GB",
    "sg:address":"Unit 15, Tanfield Industrial Estate, Tanfield Lea",
    "sg:city":"Stanley",
    "sg:classifiers":[
        {
            "category":"Home & Garden",
            "subcategory":"Building Materials",
            "type":"Retail Goods"
        }
    ],
    "sg:phone":"+44 1207 290177",
    "sg:postcode":"DH9 9QX",
    "sg:province":"Durham",
    "sg:tags":[
        "polythene",
        "plastic"
    ],
    "wof:name":"Jay Bee Plastiks",
    "wof:placetype":"venue"
},
  "geometry": {"coordinates":[-1.703039,54.88932],"type":"Point"}
}