{
  "type": "Feature",
  "properties": {
    "iso:country":"GB",
    "sg:address":"29 Market Street",
    "sg:city":"Hyde",
    "sg:classifiers":[
        {
            "category":"Retail",
            "subcategory":"Laundry & Dry Cleaning",
            "type":"Services"
        }
    ],
    "sg:phone":"+44 161 368 2062",
    "sg:postcode":"SK14 2AD",
    "sg:province":"Cheshire",
    "sg:tags":[
        "alteration"
    ],
    "wof:name":"Joe Berger & Sons Ltd.",
    "wof:placetype":"venue"
},
  "geometry": {"coordinates":[-2.081039,53.452419],"type":"Point"}
}