{
  "type": "Feature",
  "properties": {
    "addr:full":"5 North Street Wareham Dorset BH20 4AB",
    "addr:housenumber":"5",
    "addr:postcode":"bh20 4ab",
    "addr:street":"North Street",
    "iso:country":"GB",
    "sg:address":"5 North Street",
    "sg:city":"Wareham",
    "sg:classifiers":[
        {
            "category":"Shopping",
            "subcategory":"Thrift Store",
            "type":"Retail Goods"
        }
    ],
    "sg:phone":"+44 1929 550729",
    "sg:postcode":"BH20 4AB",
    "sg:province":"Dorset",
    "sg:tags":[
        "shop",
        "charity"
    ],
    "wof:name":"Help the Aged",
    "wof:placetype":"venue"
},
  "geometry": {"coordinates":[-2.1102449894,50.6862258911],"type":"Point"}
}