{
  "type": "Feature",
  "properties": {
    "addr:full":"34 Bridlington Road Watford Hertfordshire WD19 7AE",
    "addr:housenumber":"34",
    "addr:postcode":"wd19 7ae",
    "addr:street":"Bridlington Road",
    "iso:country":"GB",
    "sg:address":"34 Bridlington Road",
    "sg:city":"Watford",
    "sg:classifiers":[
        {
            "category":"Personal",
            "subcategory":"Beauty Salon",
            "type":"Services"
        }
    ],
    "sg:phone":"+44 20 8428 3872",
    "sg:postcode":"WD19 7AE",
    "sg:province":"Hertfordshire",
    "sg:tags":[
        "unisex",
        "hairdresser"
    ],
    "wof:name":"Poppy's Hair Design",
    "wof:placetype":"venue"
},
  "geometry": {"coordinates":[-0.388389,51.6269],"type":"Point"}
}