{
  "type": "Feature",
  "properties": {
    "addr:full":"208 Station Road, Burton Latimer Kettering Northamptonshire NN15 5NT",
    "addr:housenumber":"208",
    "addr:postcode":"nn15 5nt",
    "addr:street":"Station Road",
    "iso:country":"GB",
    "sg:address":"208 Station Road, Burton Latimer",
    "sg:city":"Kettering",
    "sg:classifiers":[
        {
            "category":"Personal",
            "type":"Services"
        }
    ],
    "sg:phone":"+44 1536 514217",
    "sg:postcode":"NN15 5NT",
    "sg:province":"Northamptonshire",
    "sg:tags":[
        "delivery"
    ],
    "wof:name":"Handy Vans",
    "wof:placetype":"venue"
},
  "geometry": {"coordinates":[-0.6933919787,52.3648147583],"type":"Point"}
}