{
  "type": "Feature",
  "properties": {
    "iso:country":"GB",
    "sg:address":"Unit 14 Apex Business Centre, Boscombe Road, Dunstable",
    "sg:city":"Luton",
    "sg:classifiers":[
        {
            "category":"Home & Garden",
            "subcategory":"Hardware",
            "type":"Retail Goods"
        }
    ],
    "sg:phone":"+44 1582 666334",
    "sg:postcode":"LU5 4SB",
    "sg:province":"Bedfordshire",
    "sg:tags":[
        "component",
        "electronic"
    ],
    "wof:name":"E F D International Inc",
    "wof:placetype":"venue"
},
  "geometry": {"coordinates":[-0.51497,51.89558],"type":"Point"}
}