{
  "type": "Feature",
  "properties": {
    "iso:country":"GB",
    "sg:address":"1 Keymer Road",
    "sg:city":"Burgess Hill",
    "sg:classifiers":[
        {
            "category":"Real Estate",
            "subcategory":"Real Estate Agent",
            "type":"Services"
        }
    ],
    "sg:phone":"+44 1444 245201",
    "sg:postcode":"RH15 0AD",
    "sg:province":"East Sussex",
    "wof:name":"Stephen Parsons Estate Agents",
    "wof:placetype":"venue"
},
  "geometry": {"coordinates":[-0.1259160042,50.9463348389],"type":"Point"}
}