{
  "type": "Feature",
  "properties": {
    "addr:full":"Fleet Road Spalding Cambridgeshire PE12 7AX",
    "addr:postcode":"pe12 7ax",
    "addr:street":"Fleet Road Spalding",
    "iso:country":"GB",
    "sg:address":"Fleet Road",
    "sg:city":"Spalding",
    "sg:classifiers":[
        {
            "category":"Home & Garden",
            "subcategory":"Garden Supply",
            "type":"Retail Goods"
        }
    ],
    "sg:phone":"+44 1406 422942",
    "sg:postcode":"PE12 7AX",
    "sg:province":"Cambridgeshire",
    "sg:tags":[
        "nursery",
        "centre"
    ],
    "wof:name":"Sabans Garden Centre",
    "wof:placetype":"venue"
},
  "geometry": {"coordinates":[0.0290300008,52.8035469055],"type":"Point"}
}