{
  "type": "Feature",
  "properties": {
    "addr:full":"9 The Tapestries, Straight Rd Windsor Berkshire SL4 2RN",
    "addr:housenumber":"9",
    "addr:postcode":"sl4 2rn",
    "addr:street":"Straight Rd",
    "iso:country":"GB",
    "sg:address":"9 The Tapestries, Straight Rd",
    "sg:city":"Windsor",
    "sg:classifiers":[
        {
            "category":"Building & Trades",
            "subcategory":"Construction",
            "type":"Services"
        }
    ],
    "sg:postcode":"SL4 2RN",
    "sg:province":"Berkshire",
    "sg:tags":[
        "builder"
    ],
    "wof:name":"Excalibur Building & Maintenance",
    "wof:placetype":"venue"
},
  "geometry": {"coordinates":[-0.5791490078,51.458114624],"type":"Point"}
}