{
  "type": "Feature",
  "properties": {
    "addr:full":"91 Glenfield Rd Paisley East Renfrewshire PA2 8TE",
    "addr:housenumber":"91",
    "addr:postcode":"pa2 8te",
    "addr:street":"Glenfield Rd",
    "iso:country":"GB",
    "sg:address":"91 Glenfield Rd",
    "sg:city":"Paisley",
    "sg:classifiers":[
        {
            "category":"Bus Charters",
            "type":"Transportation"
        }
    ],
    "sg:phone":"+44 141 884 7311",
    "sg:postcode":"PA2 8TE",
    "sg:province":"East Renfrewshire",
    "sg:tags":[
        "hire",
        "coach"
    ],
    "wof:name":"M & C Executive Coaches",
    "wof:placetype":"venue"
},
  "geometry": {"coordinates":[-4.426729,55.817478],"type":"Point"}
}