{
  "type": "Feature",
  "properties": {
    "addr:full":"Indigo Building, Mulberry Business Park, Fishponds Road Wokingham Berkshire RG41 2GY",
    "addr:postcode":"rg41 2gy",
    "addr:street":"Mulberry Business Park Fishponds Road",
    "iso:country":"GB",
    "sg:address":"Indigo Building, Mulberry Business Park, Fishponds Road",
    "sg:city":"Wokingham",
    "sg:classifiers":[
        {
            "category":"Wholesale",
            "subcategory":"Medical Equipment & Supplies",
            "type":"Manufacturing & Wholesale Goods"
        }
    ],
    "sg:phone":"+44 118 977 3100",
    "sg:postcode":"RG41 2GY",
    "sg:province":"Berkshire",
    "sg:tags":[
        "hospital"
    ],
    "wof:name":"Baleca Medical Ltd.",
    "wof:placetype":"venue"
},
  "geometry": {"coordinates":[-0.8490800261,51.4026985168],"type":"Point"}
}