{
  "type": "Feature",
  "properties": {
    "iso:country":"GB",
    "sg:address":"38 Church St",
    "sg:city":"Royston",
    "sg:classifiers":[
        {
            "category":"Professional",
            "subcategory":"Research",
            "type":"Services"
        }
    ],
    "sg:phone":"+44 1763 208004",
    "sg:postcode":"SG8 7RE",
    "sg:province":"Bedfordshire",
    "sg:tags":[
        "market"
    ],
    "wof:name":"YKDM Pharmaceutical Market Analysis",
    "wof:placetype":"venue"
},
  "geometry": {"coordinates":[0.105461,52.097061],"type":"Point"}
}