{
  "type": "Feature",
  "properties": {
    "iso:country":"GB",
    "sg:address":"New Pond Rd",
    "sg:city":"High Wycombe",
    "sg:classifiers":[
        {
            "category":"Restaurant",
            "type":"Food & Drink"
        }
    ],
    "sg:phone":"+44 1494 715947",
    "sg:postcode":"HP15 6SX",
    "sg:province":"Buckinghamshire",
    "wof:name":"Old English Pubs Ltd",
    "wof:placetype":"venue"
},
  "geometry": {"coordinates":[-0.696494,51.667389],"type":"Point"}
}