{
  "type": "Feature",
  "properties": {
    "addr:full":"137 Wycombe Lane, Wooburn Grn High Wycombe Buckinghamshire HP10 0HJ",
    "addr:housenumber":"137",
    "addr:postcode":"hp10 0hj",
    "addr:street":"Wycombe Lane;Grn",
    "iso:country":"GB",
    "sg:address":"137 Wycombe Lane, Wooburn Grn",
    "sg:city":"High Wycombe",
    "sg:classifiers":[
        {
            "category":"Personal",
            "type":"Services"
        },
        {
            "category":"Building & Trades",
            "subcategory":"Construction",
            "type":"Services"
        }
    ],
    "sg:phone":"+44 1628 525740",
    "sg:postcode":"HP10 0HJ",
    "sg:province":"Buckinghamshire",
    "sg:tags":[
        "contracting",
        "roofing",
        "wedding"
    ],
    "wof:name":"Allan Wise & Co",
    "wof:placetype":"venue"
},
  "geometry": {"coordinates":[-0.6847659945,51.5939712524],"type":"Point"}
}