{
  "type": "Feature",
  "properties": {
    "iso:country":"GB",
    "sg:address":"136 Bridgegate",
    "sg:city":"Glasgow",
    "sg:classifiers":[
        {
            "category":"Shopping",
            "subcategory":"Crafts & Fabrics",
            "type":"Retail Goods"
        },
        {
            "category":"Real Estate",
            "subcategory":"Architect",
            "type":"Services"
        }
    ],
    "sg:phone":"+44 141 553 1513",
    "sg:postcode":"G1 5HZ",
    "sg:province":"Glasgow City",
    "sg:tags":[
        "tartan",
        "supplier",
        "kilt",
        "accessory"
    ],
    "wof:name":"Macleod Highland Supplies",
    "wof:placetype":"venue"
},
  "geometry": {"coordinates":[-4.2500228882,55.8547439575],"type":"Point"}
}