{
  "type": "Feature",
  "properties": {
    "addr:full":"17 Wood St, Old Town Swindon Wiltshire SN1 4AN",
    "addr:housenumber":"17",
    "addr:postcode":"sn1 4an",
    "addr:street":"Wood St",
    "iso:country":"GB",
    "sg:address":"17 Wood St, Old Town",
    "sg:city":"Swindon",
    "sg:classifiers":[
        {
            "category":"Shopping",
            "subcategory":"Antiques",
            "type":"Retail Goods"
        }
    ],
    "sg:postcode":"SN1 4AN",
    "sg:province":"Wiltshire",
    "wof:name":"Old Town Antiques",
    "wof:placetype":"venue"
},
  "geometry": {"coordinates":[-1.775534,51.552319],"type":"Point"}
}