{
  "type": "Feature",
  "properties": {
    "iso:country":"GB",
    "sg:address":"8 Lumley Avenue",
    "sg:city":"Skegness",
    "sg:classifiers":[
        {
            "category":"Organizations",
            "subcategory":"Community Association",
            "type":"Services"
        },
        {
            "category":"Organizations",
            "subcategory":"Membership Organization",
            "type":"Services"
        }
    ],
    "sg:phone":"+44 1754 763257",
    "sg:postcode":"PE25 2AH",
    "sg:province":"Lincolnshire",
    "sg:tags":[
        "club",
        "social"
    ],
    "wof:name":"Avenue Club",
    "wof:placetype":"venue"
},
  "geometry": {"coordinates":[0.339575,53.143738],"type":"Point"}
}