{
  "type": "Feature",
  "properties": {
    "addr:full":"Linden House, Ruckamore Road Torquay Devon TQ2 6HF",
    "addr:postcode":"tq2 6hf",
    "addr:street":"Ruckamore Road",
    "iso:country":"GB",
    "sg:address":"Linden House, Ruckamore Road",
    "sg:city":"Torquay",
    "sg:classifiers":[
        {
            "category":"Travel",
            "subcategory":"Hotels & Motels",
            "type":"Entertainment"
        }
    ],
    "sg:postcode":"TQ2 6HF",
    "sg:province":"Devon",
    "sg:tags":[
        "self",
        "catering"
    ],
    "wof:name":"Linden House Holiday Flats",
    "wof:placetype":"venue"
},
  "geometry": {"coordinates":[-3.549527,50.466007],"type":"Point"}
}