{
  "type": "Feature",
  "properties": {
    "iso:country":"GB",
    "sg:address":"Northdown Hill, St Peters",
    "sg:city":"Broadstairs",
    "sg:classifiers":[
        {
            "category":"Social Services",
            "subcategory":"Child Care",
            "type":"Services"
        }
    ],
    "sg:phone":"+44 1843 863733",
    "sg:postcode":"CT10 3HU",
    "sg:province":"Kent",
    "sg:tags":[
        "children's",
        "home"
    ],
    "wof:name":"Sea Meadows",
    "wof:placetype":"venue"
},
  "geometry": {"coordinates":[1.4182200432,51.3729400635],"type":"Point"}
}