{
  "type": "Feature",
  "properties": {
    "iso:country":"GB",
    "sg:address":"1 Wilden Road, Pattinson Industrial Estate",
    "sg:city":"Washington",
    "sg:classifiers":[
        {
            "category":"Autos & Motor Vehicles",
            "subcategory":"Fuel & Gas Station",
            "type":"Retail Goods"
        },
        {
            "category":"Building & Trades",
            "subcategory":"Pest Control",
            "type":"Services"
        }
    ],
    "sg:phone":"+44 191 419 1616",
    "sg:postcode":"NE38 8QB",
    "sg:province":"Durham",
    "sg:tags":[
        "pump",
        "corrosion",
        "sale",
        "prevention",
        "servicing"
    ],
    "wof:name":"K R M Engineering & Repair Services",
    "wof:placetype":"venue"
},
  "geometry": {"coordinates":[-1.502655,54.894131],"type":"Point"}
}