{
  "type": "Feature",
  "properties": {
    "addr:full":"23 Clover Crescent, Calverley Pudsey West Yorkshire LS28 5SZ",
    "addr:housenumber":"23",
    "addr:postcode":"ls28 5sz",
    "addr:street":"Clover Crescent;West",
    "iso:country":"GB",
    "sg:address":"23 Clover Crescent, Calverley",
    "sg:city":"Pudsey",
    "sg:classifiers":[
        {
            "category":"Personal",
            "subcategory":"Tanning Parlor",
            "type":"Services"
        },
        {
            "category":"Home & Garden",
            "subcategory":"Building Materials",
            "type":"Retail Goods"
        }
    ],
    "sg:phone":"+44 7774 918342",
    "sg:postcode":"LS28 5SZ",
    "sg:province":"West Yorkshire",
    "sg:tags":[
        "sunbeds",
        "hire",
        "sunbed"
    ],
    "wof:name":"Pudsey Sunbeds",
    "wof:placetype":"venue"
},
  "geometry": {"coordinates":[-1.694104,53.828724],"type":"Point"}
}