{
  "type": "Feature",
  "properties": {
    "iso:country":"GB",
    "sg:address":"208 High Street North",
    "sg:city":"Dunstable",
    "sg:classifiers":[
        {
            "category":"Building & Trades",
            "subcategory":"Construction",
            "type":"Services"
        }
    ],
    "sg:phone":"+44 1582 477388",
    "sg:postcode":"LU6 1AU",
    "sg:province":"Bedfordshire",
    "sg:tags":[
        "builder"
    ],
    "wof:name":"Ideal Building Services",
    "wof:placetype":"venue"
},
  "geometry": {"coordinates":[-0.532011,51.894085],"type":"Point"}
}