{
  "type": "Feature",
  "properties": {
    "iso:country":"GB",
    "sg:address":"4 Dollar Road",
    "sg:city":"Tillicoultry",
    "sg:classifiers":[
        {
            "category":"Professional",
            "subcategory":"Accounting & Tax Preparation",
            "type":"Services"
        }
    ],
    "sg:postcode":"FK13 6PA",
    "sg:province":"Clackmannanshire",
    "sg:tags":[
        "accountant"
    ],
    "wof:name":"Abacus Bookkeeping & Business Services",
    "wof:placetype":"venue"
},
  "geometry": {"coordinates":[-3.738325,56.153088],"type":"Point"}
}