{
  "type": "Feature",
  "properties": {
    "addr:full":"24/26 Market Road Doncaster South Yorkshire DN1 1LP",
    "addr:housenumber":"24 / 26",
    "addr:postcode":"dn1 1lp",
    "addr:street":"Market Road",
    "iso:country":"GB",
    "sg:address":"24/26 Market Road",
    "sg:city":"Doncaster",
    "sg:classifiers":[
        {
            "category":"Shopping",
            "subcategory":"Computers & Home Electronics",
            "type":"Retail Goods"
        }
    ],
    "sg:phone":"+44 1302 761530",
    "sg:postcode":"DN1 1LP",
    "sg:province":"South Yorkshire",
    "sg:tags":[
        "equipment",
        "video",
        "cctv"
    ],
    "wof:name":"Catch Commercial Security",
    "wof:placetype":"venue"
},
  "geometry": {"coordinates":[-1.1309620142,53.5259666443],"type":"Point"}
}