{
  "type": "Feature",
  "properties": {
    "addr:full":"4 Forres St Edinburgh City of Edinburgh EH3 6BJ",
    "addr:housenumber":"4",
    "addr:postcode":"eh3 6bj",
    "addr:street":"Forres St Edinburgh",
    "iso:country":"GB",
    "sg:address":"4 Forres St",
    "sg:city":"Edinburgh",
    "sg:classifiers":[
        {
            "category":"Farming",
            "subcategory":"Nursery",
            "type":"Manufacturing & Wholesale Goods"
        }
    ],
    "sg:phone":"+44 131 226 5692",
    "sg:postcode":"EH3 6BJ",
    "sg:province":"City of Edinburgh",
    "sg:tags":[
        "creche"
    ],
    "wof:name":"4 Forres St Nursery",
    "wof:placetype":"venue"
},
  "geometry": {"coordinates":[-3.2079019547,55.9536361694],"type":"Point"}
}