{
  "type": "Feature",
  "properties": {
    "addr:full":"Dane Road Seaford East Sussex BN25 1DU",
    "addr:postcode":"bn25 1du",
    "addr:street":"Dane Road",
    "iso:country":"GB",
    "sg:address":"Dane Road",
    "sg:city":"Seaford",
    "sg:classifiers":[
        {
            "category":"Health Services",
            "subcategory":"Nursing And Care Facility",
            "type":"Services"
        }
    ],
    "sg:phone":"+44 1323 897845",
    "sg:postcode":"BN25 1DU",
    "sg:province":"East Sussex",
    "sg:tags":[
        "home"
    ],
    "wof:name":"Freshford Cottage",
    "wof:placetype":"venue"
},
  "geometry": {"coordinates":[0.10026,50.772427],"type":"Point"}
}