{
  "type": "Feature",
  "properties": {
    "addr:full":"Starvenden Lane, Cranbrook Common Cranbrook Kent TN17 2AN",
    "addr:postcode":"tn17 2an",
    "addr:street":"Starvenden Lane;Common",
    "iso:country":"GB",
    "sg:address":"Starvenden Lane, Cranbrook Common",
    "sg:city":"Cranbrook",
    "sg:classifiers":[
        {
            "category":"Sports & Exercise",
            "subcategory":"Stables",
            "type":"Entertainment"
        }
    ],
    "sg:phone":"+44 1580 713833",
    "sg:postcode":"TN17 2AN",
    "sg:province":"Kent",
    "sg:tags":[
        "education",
        "equestrian"
    ],
    "wof:name":"Appletree Stables & Riding School",
    "wof:placetype":"venue"
},
  "geometry": {"coordinates":[0.549731,51.12038],"type":"Point"}
}