{
  "type": "Feature",
  "properties": {
    "addr:full":"Old College Campus, Dew Street Haverfordwest Pembrokeshire SA61 1ST",
    "addr:postcode":"sa61 1st",
    "addr:street":"Old;Dew Street",
    "iso:country":"GB",
    "sg:address":"Old College Campus, Dew Street",
    "sg:city":"Haverfordwest",
    "sg:classifiers":[
        {
            "category":"Education",
            "subcategory":"University",
            "type":"Public Place"
        },
        {
            "category":"Government",
            "subcategory":"Office",
            "type":"Public Place"
        }
    ],
    "sg:postcode":"SA61 1ST",
    "sg:province":"Pembrokeshire",
    "sg:tags":[
        "local",
        "higher"
    ],
    "wof:name":"Haverfordwest Community Education Centre",
    "wof:placetype":"venue"
},
  "geometry": {"coordinates":[-4.977350235,51.7987632751],"type":"Point"}
}