{
  "type": "Feature",
  "properties": {
    "addr:full":"Conifer House, Bockhampton Road Hungerford Berkshire RG17 8PR",
    "addr:postcode":"rg17 8pr",
    "addr:street":"Bockhampton Road",
    "iso:country":"GB",
    "sg:address":"Conifer House, Bockhampton Road",
    "sg:city":"Hungerford",
    "sg:classifiers":[
        {
            "category":"Shopping",
            "subcategory":"Clothing, Apparel, & Fashions",
            "type":"Retail Goods"
        }
    ],
    "sg:postcode":"RG17 8PR",
    "sg:province":"Berkshire",
    "sg:tags":[
        "tie",
        "neckwear"
    ],
    "wof:name":"Cravats Ltd.",
    "wof:placetype":"venue"
},
  "geometry": {"coordinates":[-1.5281840563,51.5050239563],"type":"Point"}
}