{
  "type": "Feature",
  "properties": {
    "iso:country":"GB",
    "sg:address":"Maynard House, The Common",
    "sg:city":"Hatfield",
    "sg:classifiers":[
        {
            "category":"Organizations",
            "subcategory":"Membership Organization",
            "type":"Services"
        }
    ],
    "sg:phone":"+44 1707 268742",
    "sg:postcode":"AL10 0NF",
    "sg:province":"Hertfordshire",
    "sg:tags":[
        "club"
    ],
    "wof:name":"Conservative Club",
    "wof:placetype":"venue"
},
  "geometry": {"coordinates":[-0.229393,51.763325],"type":"Point"}
}