{
  "type": "Feature",
  "properties": {
    "addr:full":"244 Terminus Road Eastbourne East Sussex BN21 3DE",
    "addr:housenumber":"244",
    "addr:postcode":"bn21 3de",
    "addr:street":"Terminus Road",
    "iso:country":"GB",
    "sg:address":"244 Terminus Road",
    "sg:city":"Eastbourne",
    "sg:classifiers":[
        {
            "category":"Shopping",
            "subcategory":"Gifts & Souvenirs",
            "type":"Retail Goods"
        }
    ],
    "sg:phone":"+44 1323 731849",
    "sg:postcode":"BN21 3DE",
    "sg:province":"East Sussex",
    "sg:tags":[
        "shop"
    ],
    "wof:name":"Its A Gift",
    "wof:placetype":"venue"
},
  "geometry": {"coordinates":[0.289996,50.766666],"type":"Point"}
}