{
  "type": "Feature",
  "properties": {
    "iso:country":"GB",
    "sg:address":"1 St Bernards Row",
    "sg:city":"Edinburgh",
    "sg:classifiers":[
        {
            "category":"Real Estate",
            "subcategory":"Architect",
            "type":"Services"
        }
    ],
    "sg:phone":"+44 131 343 6222",
    "sg:postcode":"EH4 1HW",
    "sg:province":"City of Edinburgh",
    "wof:name":"Lewis & Hickey",
    "wof:placetype":"venue"
},
  "geometry": {"coordinates":[-3.2098300457,55.9588737488],"type":"Point"}
}