{
  "type": "Feature",
  "properties": {
    "iso:country":"GB",
    "sg:address":"1 Rushetts Close, Southwell",
    "sg:city":"Portland",
    "sg:classifiers":[
        {
            "category":"Building & Trades",
            "subcategory":"Construction",
            "type":"Services"
        }
    ],
    "sg:phone":"+44 1305 826168",
    "sg:postcode":"DT5 2LU",
    "sg:province":"Dorset",
    "sg:tags":[
        "decorator",
        "painter"
    ],
    "wof:name":"Graham's Painting & Decorating Services",
    "wof:placetype":"venue"
},
  "geometry": {"coordinates":[-2.445468,50.532955],"type":"Point"}
}