{
  "type": "Feature",
  "properties": {
    "iso:country":"GB",
    "sg:address":"Hurst House, 157-169 Walton Road, East Molesley",
    "sg:city":"Walton-on-thames",
    "sg:classifiers":[
        {
            "category":"Professional",
            "subcategory":"Research",
            "type":"Services"
        }
    ],
    "sg:phone":"+44 20 8941 8887",
    "sg:postcode":"KT8 0DX",
    "sg:province":"Greater London",
    "sg:tags":[
        "market"
    ],
    "wof:name":"Topflight Research Ltd.",
    "wof:placetype":"venue"
},
  "geometry": {"coordinates":[-0.3573699892,51.4008407593],"type":"Point"}
}