{
  "type": "Feature",
  "properties": {
    "addr:full":"Lon Parcwr Ruthin Denbighshire LL15 1NA",
    "addr:postcode":"ll15 1na",
    "addr:street":"Lon Parcwr",
    "iso:country":"GB",
    "sg:address":"Lon Parcwr",
    "sg:city":"Ruthin",
    "sg:classifiers":[
        {
            "category":"Retail",
            "subcategory":"Auto Repair",
            "type":"Services"
        }
    ],
    "sg:postcode":"LL15 1NA",
    "sg:province":"Denbighshire",
    "sg:tags":[
        "modification",
        "garage"
    ],
    "wof:name":"D & S Motors",
    "wof:placetype":"venue"
},
  "geometry": {"coordinates":[-3.312096,53.121628],"type":"Point"}
}