{
  "type": "Feature",
  "properties": {
    "iso:country":"GB",
    "sg:address":"Eynesbury Hardwicke",
    "sg:city":"Huntingdon",
    "sg:classifiers":[
        {
            "category":"Sports & Exercise",
            "subcategory":"Golf",
            "type":"Entertainment"
        }
    ],
    "sg:phone":"+44 1480 215153",
    "sg:postcode":"PE19 4XN",
    "sg:province":"Bedfordshire",
    "sg:tags":[
        "club",
        "course"
    ],
    "wof:name":"Abbotsley Golf & Squash Club",
    "wof:placetype":"venue"
},
  "geometry": {"coordinates":[-0.24732,52.197079],"type":"Point"}
}