{
  "type": "Feature",
  "properties": {
    "iso:country":"GB",
    "sg:address":"Westcott Farm House, Rockbeare",
    "sg:city":"Exeter",
    "sg:classifiers":[
        {
            "category":"Building & Trades",
            "subcategory":"Construction",
            "type":"Services"
        }
    ],
    "sg:postcode":"EX5 2LU",
    "sg:province":"Devon",
    "sg:tags":[
        "builder"
    ],
    "wof:name":"W Sheppard & Son",
    "wof:placetype":"venue"
},
  "geometry": {"coordinates":[-3.3910839558,50.7460441589],"type":"Point"}
}