{
  "type": "Feature",
  "properties": {
    "iso:country":"GB",
    "sg:address":"Richmond Lodge, The Common, Mulbarton",
    "sg:city":"Norwich",
    "sg:classifiers":[
        {
            "category":"Social Services",
            "subcategory":"Retirement Home",
            "type":"Services"
        }
    ],
    "sg:phone":"+44 1508 570449",
    "sg:postcode":"NR14 8JW",
    "sg:province":"Norfolk",
    "sg:tags":[
        "residential",
        "care"
    ],
    "wof:name":"Richmond Lodge Care Home",
    "wof:placetype":"venue"
},
  "geometry": {"coordinates":[1.237467,52.558319],"type":"Point"}
}