{
  "type": "Feature",
  "properties": {
    "addr:full":"Eithinog Wen Farm, Pontllyfni Caernarfon Gwynedd LL54 5EY",
    "addr:postcode":"ll54 5ey",
    "addr:street":"Eithinog Wen;Pontllyfni",
    "iso:country":"GB",
    "sg:address":"Eithinog Wen Farm, Pontllyfni",
    "sg:city":"Caernarfon",
    "sg:classifiers":[
        {
            "category":"Farming",
            "subcategory":"Livestock Farm",
            "type":"Manufacturing & Wholesale Goods"
        },
        {
            "category":"Retail",
            "subcategory":"Animal Services",
            "type":"Services"
        }
    ],
    "sg:phone":"+44 1286 660269",
    "sg:postcode":"LL54 5EY",
    "sg:province":"Gwynedd",
    "sg:tags":[
        "breeder",
        "others"
    ],
    "wof:name":"Evan Hughes & Son",
    "wof:placetype":"venue"
},
  "geometry": {"coordinates":[-4.3379650116,53.0463638306],"type":"Point"}
}