{
  "type": "Feature",
  "properties": {
    "iso:country":"GB",
    "sg:address":"103 High St",
    "sg:city":"Crediton",
    "sg:classifiers":[
        {
            "category":"Cafe",
            "type":"Food & Drink"
        }
    ],
    "sg:postcode":"EX17 3LF",
    "sg:province":"Devon",
    "sg:tags":[
        "tea",
        "room"
    ],
    "wof:name":"Gillard,Rachel,",
    "wof:placetype":"venue"
},
  "geometry": {"coordinates":[-3.661471,50.790977],"type":"Point"}
}