{
  "type": "Feature",
  "properties": {
    "iso:country":"GB",
    "sg:address":"8 The Bridge",
    "sg:city":"Chippenham",
    "sg:classifiers":[
        {
            "category":"Retail",
            "subcategory":"Laundry & Dry Cleaning",
            "type":"Services"
        }
    ],
    "sg:phone":"+44 1249 650964",
    "sg:postcode":"SN15 1EX",
    "sg:province":"Wiltshire",
    "sg:tags":[
        "alteration"
    ],
    "wof:name":"Brooks Cleaning Services Ltd.",
    "wof:placetype":"venue"
},
  "geometry": {"coordinates":[-2.117239,51.459618],"type":"Point"}
}