{
  "type": "Feature",
  "properties": {
    "addr:full":"224 Jubilee St Whitechapel Greater London E1 3BS",
    "addr:housenumber":"224",
    "addr:postcode":"e1 3bs",
    "addr:street":"Jubilee St",
    "iso:country":"GB",
    "sg:address":"224 Jubilee St",
    "sg:city":"Whitechapel",
    "sg:classifiers":[
        {
            "category":"Food & Beverages",
            "subcategory":"Bakery",
            "type":"Retail Goods"
        }
    ],
    "sg:phone":"+44 20 7790 1050",
    "sg:postcode":"E1 3BS",
    "sg:province":"Greater London",
    "sg:tags":[
        "baker"
    ],
    "wof:name":"Rinkoff's Bakeries",
    "wof:placetype":"venue"
},
  "geometry": {"coordinates":[-0.0529769994,51.5199279785],"type":"Point"}
}