{
  "type": "Feature",
  "properties": {
    "iso:country":"GB",
    "sg:address":"Unit 3, Orford Rd, Newton East",
    "sg:city":"Manchester",
    "sg:classifiers":[
        {
            "category":"Retail",
            "subcategory":"Auto Repair",
            "type":"Services"
        }
    ],
    "sg:phone":"+44 161 682 8994",
    "sg:postcode":"M25 3DB",
    "sg:province":"Greater Manchester",
    "sg:tags":[
        "car",
        "specialist",
        "customizing"
    ],
    "wof:name":"Discount Tyres",
    "wof:placetype":"venue"
},
  "geometry": {"coordinates":[-2.280364,53.536709],"type":"Point"}
}