{
  "type": "Feature",
  "properties": {
    "iso:country":"GB",
    "sg:address":"Camphill",
    "sg:city":"Paisley",
    "sg:classifiers":[
        {
            "category":"Education",
            "subcategory":"School",
            "type":"Public Place"
        },
        {
            "category":"Government",
            "subcategory":"Office",
            "type":"Public Place"
        }
    ],
    "sg:phone":"+44 141 887 4261",
    "sg:postcode":"PA1 2HL",
    "sg:province":"Renfrewshire",
    "sg:tags":[
        "agency",
        "local",
        "authority"
    ],
    "wof:name":"RENFREWSHIRE COUNCIL",
    "wof:placetype":"venue"
},
  "geometry": {"coordinates":[-4.432049,55.840446],"type":"Point"}
}