{
  "type": "Feature",
  "properties": {
    "addr:full":"102 Euston Street London Greater London NW1 2HA",
    "addr:housenumber":"102",
    "addr:postcode":"nw1 2ha",
    "addr:street":"Euston Street",
    "iso:country":"GB",
    "sg:address":"102 Euston Street",
    "sg:city":"London",
    "sg:classifiers":[
        {
            "category":"Education",
            "subcategory":"Library",
            "type":"Public Place"
        }
    ],
    "sg:phone":"+44 20 7387 0317",
    "sg:postcode":"NW1 2HA",
    "sg:province":"Greater London",
    "sg:tags":[
        "book"
    ],
    "wof:name":"The Society of College  National & University Libraries",
    "wof:placetype":"venue"
},
  "geometry": {"coordinates":[-0.135119,51.527119],"type":"Point"}
}