{
  "type": "Feature",
  "properties": {
    "iso:country":"GB",
    "sg:address":"37 Market Square",
    "sg:city":"Duns",
    "sg:classifiers":[
        {
            "category":"Professional",
            "subcategory":"Accounting & Tax Preparation",
            "type":"Services"
        }
    ],
    "sg:postcode":"TD11 3AL",
    "sg:province":"East Lothian",
    "sg:tags":[
        "accountant"
    ],
    "wof:name":"Nancy Hodge Farm Business Services",
    "wof:placetype":"venue"
},
  "geometry": {"coordinates":[-2.344375,55.777798],"type":"Point"}
}