{
  "type": "Feature",
  "properties": {
    "iso:country":"GB",
    "sg:address":"20 Market St",
    "sg:city":"Guildford",
    "sg:classifiers":[
        {
            "category":"Fast Food",
            "type":"Food & Drink"
        }
    ],
    "sg:phone":"+44 1483 452503",
    "sg:postcode":"GU1 4LB",
    "sg:province":"Surrey",
    "sg:tags":[
        "away",
        "take"
    ],
    "wof:name":"Jo Clarks",
    "wof:placetype":"venue"
},
  "geometry": {"coordinates":[-0.5731920004,51.2363433838],"type":"Point"}
}