{
  "type": "Feature",
  "properties": {
    "iso:country":"GB",
    "sg:address":"Springbank, Tuckenhay",
    "sg:city":"Totnes",
    "sg:classifiers":[
        {
            "category":"Building & Trades",
            "subcategory":"Construction",
            "type":"Services"
        }
    ],
    "sg:phone":"+44 1803 732428",
    "sg:postcode":"TQ9 7EQ",
    "sg:province":"Devon",
    "sg:tags":[
        "builder"
    ],
    "wof:name":"J.T Tibbetts & Sons",
    "wof:placetype":"venue"
},
  "geometry": {"coordinates":[-3.663515,50.392757],"type":"Point"}
}