{
  "type": "Feature",
  "properties": {
    "iso:country":"GB",
    "sg:address":"Corse Lawn Garage, Corse Lawn",
    "sg:city":"Gloucester",
    "sg:classifiers":[
        {
            "category":"Retail",
            "subcategory":"Auto Repair",
            "type":"Services"
        }
    ],
    "sg:phone":"+44 1452 781007",
    "sg:postcode":"GL19 4PE",
    "sg:province":"Gloucestershire",
    "sg:tags":[
        "body",
        "car",
        "modification",
        "related",
        "garage"
    ],
    "wof:name":"N R T Motors",
    "wof:placetype":"venue"
},
  "geometry": {"coordinates":[-2.246639,51.97467],"type":"Point"}
}