{
  "type": "Feature",
  "properties": {
    "addr:full":"Burrowfield Welwyn Garden City Hertfordshire AL7 4SS",
    "addr:postcode":"al7 4ss",
    "addr:street":"Burrowfield",
    "iso:country":"GB",
    "sg:address":"Burrowfield",
    "sg:city":"Welwyn Garden City",
    "sg:classifiers":[
        {
            "category":"Professional",
            "subcategory":"Engineering",
            "type":"Services"
        }
    ],
    "sg:phone":"+44 1707 330215",
    "sg:postcode":"AL7 4SS",
    "sg:province":"Hertfordshire",
    "wof:name":"A G Parker Engineering Ltd.",
    "wof:placetype":"venue"
},
  "geometry": {"coordinates":[-0.2089039981,51.7891235352],"type":"Point"}
}