{
  "type": "Feature",
  "properties": {
    "iso:country":"GB",
    "sg:address":"24 Abington Avenue",
    "sg:city":"Northampton",
    "sg:classifiers":[
        {
            "category":"Community Center",
            "subcategory":"Youth",
            "type":"Public Place"
        }
    ],
    "sg:phone":"+44 1604 639793",
    "sg:postcode":"NN1 4NY",
    "sg:province":"Northamptonshire",
    "sg:tags":[
        "organisation",
        "centre"
    ],
    "wof:name":"The Guide Association",
    "wof:placetype":"venue"
},
  "geometry": {"coordinates":[-0.881028,52.246826],"type":"Point"}
}