{
  "type": "Feature",
  "properties": {
    "iso:country":"GB",
    "sg:address":"23 Verity View",
    "sg:city":"Leeds",
    "sg:classifiers":[
        {
            "category":"Building & Trades",
            "subcategory":"Construction",
            "type":"Services"
        }
    ],
    "sg:phone":"+44 113 248 3303",
    "sg:postcode":"LS9 0EE",
    "sg:province":"West Yorkshire",
    "sg:tags":[
        "roofing"
    ],
    "wof:name":"John Matthews",
    "wof:placetype":"venue"
},
  "geometry": {"coordinates":[-1.4822560549,53.8012542725],"type":"Point"}
}