{
  "type": "Feature",
  "properties": {
    "addr:full":"Riverside Way, Sheffield Road Rotherham South Yorkshire S60 1DS",
    "addr:postcode":"s60 1ds",
    "addr:street":"Riverside Way Sheffield Road",
    "iso:country":"GB",
    "sg:address":"Riverside Way, Sheffield Road",
    "sg:city":"Rotherham",
    "sg:classifiers":[
        {
            "category":"Autos & Motor Vehicles",
            "subcategory":"Automobile Sales",
            "type":"Retail Goods"
        }
    ],
    "sg:phone":"+44 1709 820555",
    "sg:postcode":"S60 1DS",
    "sg:province":"South Yorkshire",
    "sg:tags":[
        "car"
    ],
    "wof:name":"Dixon Citroen",
    "wof:placetype":"venue"
},
  "geometry": {"coordinates":[-1.3655320406,53.4235877991],"type":"Point"}
}