{
  "type": "Feature",
  "properties": {
    "addr:full":"75 Putney Bridge Rd London Greater London SW15 2PA",
    "addr:housenumber":"75",
    "addr:postcode":"sw15 2pa",
    "addr:street":"Putney Bridge Rd",
    "iso:country":"GB",
    "sg:address":"75 Putney Bridge Rd",
    "sg:city":"London",
    "sg:classifiers":[
        {
            "category":"Autos & Motor Vehicles",
            "subcategory":"Automobile Sales",
            "type":"Retail Goods"
        }
    ],
    "sg:phone":"+44 20 8874 7508",
    "sg:postcode":"SW15 2PA",
    "sg:province":"Greater London",
    "sg:tags":[
        "car"
    ],
    "wof:name":"Selwyn Motor Co Ltd",
    "wof:placetype":"venue"
},
  "geometry": {"coordinates":[-0.2024459988,51.4610061646],"type":"Point"}
}