{
  "type": "Feature",
  "properties": {
    "iso:country":"GB",
    "sg:address":"282 Wellington Rd",
    "sg:city":"Birmingham",
    "sg:classifiers":[
        {
            "category":"Home & Garden",
            "subcategory":"Household Appliances",
            "type":"Retail Goods"
        }
    ],
    "sg:phone":"+44 121 356 9980",
    "sg:postcode":"B20 2QL",
    "sg:province":"West Midlands",
    "sg:tags":[
        "domestic",
        "centre"
    ],
    "wof:name":"L C Home Appliance Centre",
    "wof:placetype":"venue"
},
  "geometry": {"coordinates":[-1.902284,52.515095],"type":"Point"}
}