{
  "type": "Feature",
  "properties": {
    "addr:full":"Fox Road, Bourn Cambridge Cambridgeshire CB3 7TY",
    "addr:postcode":"cb3 7ty",
    "addr:street":"Fox Road Bourn",
    "iso:country":"GB",
    "sg:address":"Fox Road, Bourn",
    "sg:city":"Cambridge",
    "sg:classifiers":[
        {
            "category":"Professional",
            "subcategory":"Engineering",
            "type":"Services"
        }
    ],
    "sg:phone":"+44 1954 719333",
    "sg:postcode":"CB3 7TY",
    "sg:province":"Cambridgeshire",
    "wof:name":"M J Rolls",
    "wof:placetype":"venue"
},
  "geometry": {"coordinates":[-0.0604679994,52.1864547729],"type":"Point"}
}