{
  "type": "Feature",
  "properties": {
    "iso:country":"GB",
    "sg:address":"564 High Road Leytonstone",
    "sg:city":"Wanstead",
    "sg:classifiers":[
        {
            "category":"Professional",
            "subcategory":"Engineering",
            "type":"Services"
        }
    ],
    "sg:phone":"+44 20 8539 3365",
    "sg:postcode":"E11 3DH",
    "sg:province":"Greater London",
    "sg:tags":[
        "precision",
        "engineer"
    ],
    "wof:name":"Apollo Specialist Engineering Ltd",
    "wof:placetype":"venue"
},
  "geometry": {"coordinates":[0.00988,51.563599],"type":"Point"}
}