{
  "type": "Feature",
  "properties": {
    "addr:full":"Unit 6c Lion Way, Swansea Enterprise Park Swansea Neath Port Talbot SA7 9EN",
    "addr:housenumber":"unit 6c;enterprise",
    "addr:postcode":"sa7",
    "addr:street":"Lion Way;Park",
    "iso:country":"GB",
    "sg:address":"Unit 6c Lion Way, Swansea Enterprise Park",
    "sg:city":"Swansea",
    "sg:classifiers":[
        {
            "category":"Professional",
            "subcategory":"Detective & Security Services",
            "type":"Services"
        }
    ],
    "sg:phone":"+44 1792 516020",
    "sg:postcode":"SA7 9EN",
    "sg:province":"Neath Port Talbot",
    "wof:name":"F.J Crimewatch Security Services Ltd",
    "wof:placetype":"venue"
},
  "geometry": {"coordinates":[-3.9101989269,51.6568336487],"type":"Point"}
}