{
  "type": "Feature",
  "properties": {
    "addr:full":"Mrs Building, Hill End Road, Harefield Uxbridge Buckinghamshire UB9 6HG",
    "addr:postcode":"ub9 6hg",
    "addr:street":"Hill End Road",
    "iso:country":"GB",
    "sg:address":"Mrs Building, Hill End Road, Harefield",
    "sg:city":"Uxbridge",
    "sg:classifiers":[
        {
            "category":"Health Services",
            "subcategory":"Clinic",
            "type":"Services"
        }
    ],
    "sg:phone":"+44 1895 822808",
    "sg:postcode":"UB9 6HG",
    "sg:province":"Buckinghamshire",
    "sg:tags":[
        "medical"
    ],
    "wof:name":"Cordatech Ltd",
    "wof:placetype":"venue"
},
  "geometry": {"coordinates":[-0.4820719957,51.604019165],"type":"Point"}
}