{
  "type": "Feature",
  "properties": {
    "iso:country":"GB",
    "sg:address":"Easterton Of Gagie, Kellas, Broughty Ferry",
    "sg:city":"Dundee",
    "sg:classifiers":[
        {
            "category":"Farming",
            "subcategory":"Farm",
            "type":"Manufacturing & Wholesale Goods"
        }
    ],
    "sg:phone":"+44 1382 350370",
    "sg:postcode":"DD5 3PP",
    "sg:province":"Angus",
    "sg:tags":[
        "mixed",
        "crop"
    ],
    "wof:name":"N & E Macrury & Son",
    "wof:placetype":"venue"
},
  "geometry": {"coordinates":[-2.88789,56.52401],"type":"Point"}
}