{
  "type": "Feature",
  "properties": {
    "addr:full":"27 Gaolgate Street Stafford Staffordshire ST16 2NT",
    "addr:housenumber":"27",
    "addr:postcode":"st16 2nt",
    "addr:street":"Gaolgate Street",
    "iso:country":"GB",
    "sg:address":"27 Gaolgate Street",
    "sg:city":"Stafford",
    "sg:classifiers":[
        {
            "category":"Shopping",
            "subcategory":"Used Merchandise",
            "type":"Retail Goods"
        }
    ],
    "sg:phone":"+44 1785 220212",
    "sg:postcode":"ST16 2NT",
    "sg:province":"Staffordshire",
    "sg:tags":[
        "shop",
        "second-hand"
    ],
    "wof:name":"Springfield House (Oaken) Ltd.",
    "wof:placetype":"venue"
},
  "geometry": {"coordinates":[-2.118117094,52.8086204529],"type":"Point"}
}