{
  "type": "Feature",
  "properties": {
    "iso:country":"GB",
    "sg:address":"Village Stores, High Street",
    "sg:city":"Spennymoor",
    "sg:classifiers":[
        {
            "category":"Shopping",
            "subcategory":"Department Store",
            "type":"Retail Goods"
        }
    ],
    "sg:postcode":"DL16 7PH",
    "sg:province":"Durham",
    "wof:name":"Joyce Thompson",
    "wof:placetype":"venue"
},
  "geometry": {"coordinates":[-1.582214,54.702061],"type":"Point"}
}