{
  "type": "Feature",
  "properties": {
    "iso:country":"GB",
    "sg:address":"20 Fairview Close, Walthamstow",
    "sg:city":"London",
    "sg:classifiers":[
        {
            "category":"Retail",
            "subcategory":"Driving School",
            "type":"Services"
        }
    ],
    "sg:postcode":"E17 5HJ",
    "sg:province":"Greater London",
    "wof:name":"Wilkins School of Motoring",
    "wof:placetype":"venue"
},
  "geometry": {"coordinates":[-0.0328040011,51.5987014771],"type":"Point"}
}