{
  "type": "Feature",
  "properties": {
    "addr:full":"26 Academy Street Glasgow Glasgow City G32 9AA",
    "addr:housenumber":"26",
    "addr:postcode":"g32 9aa",
    "addr:street":"Academy Street",
    "iso:country":"GB",
    "sg:address":"26 Academy Street",
    "sg:city":"Glasgow",
    "sg:classifiers":[
        {
            "category":"Education",
            "subcategory":"School",
            "type":"Public Place"
        }
    ],
    "sg:phone":"+44 141 582 0080",
    "sg:postcode":"G32 9AA",
    "sg:province":"Glasgow City",
    "sg:tags":[
        "local",
        "authority"
    ],
    "wof:name":"Eastbank Academy",
    "wof:placetype":"venue"
},
  "geometry": {"coordinates":[-4.1626558304,55.8515129089],"type":"Point"}
}