{
  "type": "Feature",
  "properties": {
    "iso:country":"GB",
    "sg:address":"Carlton Hayes Site, King Edward Avenue, Narborough",
    "sg:city":"Leicester",
    "sg:classifiers":[
        {
            "category":"Professional",
            "subcategory":"Engineering",
            "type":"Services"
        }
    ],
    "sg:phone":"+44 116 275 3529",
    "sg:postcode":"LE9 5DT",
    "sg:province":"Leicestershire",
    "sg:tags":[
        "design",
        "engineer"
    ],
    "wof:name":"Sir William Halcrow & Partners",
    "wof:placetype":"venue"
},
  "geometry": {"coordinates":[-1.2119699717,52.5717391968],"type":"Point"}
}