{
  "type": "Feature",
  "properties": {
    "addr:full":"Tewkesbury Road Worcester Gloucestershire WR8 0PW",
    "addr:postcode":"wr8 0pw",
    "addr:street":"Tewkesbury Road",
    "iso:country":"GB",
    "sg:address":"Tewkesbury Road",
    "sg:city":"Worcester",
    "sg:classifiers":[
        {
            "category":"Retail",
            "subcategory":"Auto Repair",
            "type":"Services"
        }
    ],
    "sg:phone":"+44 1684 592271",
    "sg:postcode":"WR8 0PW",
    "sg:province":"Gloucestershire",
    "sg:tags":[
        "modification",
        "garage"
    ],
    "wof:name":"S Bishop",
    "wof:placetype":"venue"
},
  "geometry": {"coordinates":[-2.19493,52.067478],"type":"Point"}
}