{
  "type": "Feature",
  "properties": {
    "iso:country":"GB",
    "sg:address":"24 Stert St",
    "sg:city":"Abingdon",
    "sg:classifiers":[
        {
            "category":"Travel",
            "subcategory":"Travel Agent",
            "type":"Entertainment"
        }
    ],
    "sg:phone":"+44 1235 553565",
    "sg:postcode":"OX14 3JS",
    "sg:province":"Oxfordshire",
    "wof:name":"Harvey Thomas Travel",
    "wof:placetype":"venue"
},
  "geometry": {"coordinates":[-1.281468,51.67078],"type":"Point"}
}