{
  "type": "Feature",
  "properties": {
    "addr:full":"24 Stert St Abingdon Oxfordshire OX14 3JS",
    "addr:housenumber":"24",
    "addr:postcode":"ox14 3js",
    "addr:street":"Stert St",
    "iso:country":"GB",
    "sg:address":"24 Stert St",
    "sg:city":"Abingdon",
    "sg:classifiers":[
        {
            "category":"Travel",
            "subcategory":"Travel Agent",
            "type":"Entertainment"
        }
    ],
    "sg:phone":"+44 1235 553565",
    "sg:postcode":"OX14 3JS",
    "sg:province":"Oxfordshire",
    "wof:name":"Harvey Thomas Travel",
    "wof:placetype":"venue"
},
  "geometry": {"coordinates":[-1.281468,51.67078],"type":"Point"}
}