{
  "type": "Feature",
  "properties": {
    "iso:country":"GB",
    "sg:address":"Stuart Street",
    "sg:city":"Rothesay",
    "sg:classifiers":[
        {
            "category":"Museum",
            "subcategory":"Art Museum",
            "type":"Entertainment"
        }
    ],
    "sg:phone":"+44 1700 505067",
    "sg:postcode":"PA20 0EP",
    "sg:province":"Argyll and Bute",
    "sg:tags":[
        "gallery"
    ],
    "wof:name":"Buteshire Natural History Society",
    "wof:placetype":"venue"
},
  "geometry": {"coordinates":[-5.069521,55.858894],"type":"Point"}
}