{
  "type": "Feature",
  "properties": {
    "addr:full":"Small Holm Lockerbie Dumfries and Galloway DG11 1JY",
    "addr:postcode":"dg11 1jy",
    "iso:country":"GB",
    "sg:address":"Small Holm",
    "sg:city":"Lockerbie",
    "sg:classifiers":[
        {
            "category":"Farming",
            "subcategory":"Livestock Farm",
            "type":"Manufacturing & Wholesale Goods"
        }
    ],
    "sg:phone":"+44 1387 810445",
    "sg:postcode":"DG11 1JY",
    "sg:province":"Dumfries and Galloway",
    "sg:tags":[
        "others"
    ],
    "wof:name":"B D Pattie",
    "wof:placetype":"venue"
},
  "geometry": {"coordinates":[-3.4204390049,55.1210403442],"type":"Point"}
}