{
  "type": "Feature",
  "properties": {
    "addr:full":"38 High St Kingston Upon Thames Greater London KT1 1HL",
    "addr:housenumber":"38",
    "addr:postcode":"kt1 1hl",
    "addr:street":"High St",
    "iso:country":"GB",
    "sg:address":"38 High St",
    "sg:city":"Kingston Upon Thames",
    "sg:classifiers":[
        {
            "category":"Shopping",
            "subcategory":"Clothing, Apparel, & Fashions",
            "type":"Retail Goods"
        }
    ],
    "sg:phone":"+44 20 8541 4635",
    "sg:postcode":"KT1 1HL",
    "sg:province":"Greater London",
    "sg:tags":[
        "maternity",
        "wear"
    ],
    "wof:name":"La Mama",
    "wof:placetype":"venue"
},
  "geometry": {"coordinates":[-0.3077589869,51.4079437256],"type":"Point"}
}