{
  "type": "Feature",
  "properties": {
    "iso:country":"GB",
    "sg:address":"Treverbyn Rd",
    "sg:city":"St Austell",
    "sg:classifiers":[
        {
            "category":"Professional",
            "type":"Services"
        }
    ],
    "sg:phone":"+44 1726 850401",
    "sg:postcode":"PL26 8TL",
    "sg:province":"Cornwall",
    "sg:tags":[
        "car",
        "transportation"
    ],
    "wof:name":"Philps Of Stenalees",
    "wof:placetype":"venue"
},
  "geometry": {"coordinates":[-4.792609,50.37936],"type":"Point"}
}