{
  "type": "Feature",
  "properties": {
    "iso:country":"GB",
    "sg:address":"69 Kingsway, Caversham Park",
    "sg:city":"Reading",
    "sg:classifiers":[
        {
            "category":"Shopping",
            "subcategory":"Computers & Home Electronics",
            "type":"Retail Goods"
        }
    ],
    "sg:phone":"+44 118 946 4646",
    "sg:postcode":"RG4 6RH",
    "sg:province":"Berkshire",
    "wof:name":"Balmore Business Systems",
    "wof:placetype":"venue"
},
  "geometry": {"coordinates":[-0.9586549997,51.4857711792],"type":"Point"}
}