{
  "type": "Feature",
  "properties": {
    "iso:country":"GB",
    "sg:address":"13 Stratford Place",
    "sg:city":"London",
    "sg:classifiers":[
        {
            "category":"Real Estate",
            "subcategory":"Surveying",
            "type":"Services"
        }
    ],
    "sg:phone":"+44 20 7495 7898",
    "sg:postcode":"W1C 1BD",
    "sg:province":"Greater London",
    "sg:tags":[
        "surveyor",
        "valuer"
    ],
    "wof:name":"Michael Perlin & Co",
    "wof:placetype":"venue"
},
  "geometry": {"coordinates":[-0.149519,51.514992],"type":"Point"}
}