{
  "type": "Feature",
  "properties": {
    "iso:country":"GB",
    "sg:address":"38 Moray Place",
    "sg:city":"Edinburgh",
    "sg:classifiers":[
        {
            "category":"Travel",
            "subcategory":"Hotels & Motels",
            "type":"Entertainment"
        }
    ],
    "sg:phone":"+44 131 225 1101",
    "sg:postcode":"EH3 6BT",
    "sg:province":"City of Edinburgh",
    "sg:tags":[
        "self",
        "catering"
    ],
    "wof:name":"Festival Beds",
    "wof:placetype":"venue"
},
  "geometry": {"coordinates":[-3.2090349197,55.9539070129],"type":"Point"}
}