{
  "type": "Feature",
  "properties": {
    "iso:country":"GB",
    "sg:address":"Unit 8 Metro Centre, Bridge Rd",
    "sg:city":"Orpington",
    "sg:classifiers":[
        {
            "category":"Building & Trades",
            "subcategory":"Construction",
            "type":"Services"
        }
    ],
    "sg:phone":"+44 1689 896415",
    "sg:postcode":"BR5 2BE",
    "sg:province":"Kent",
    "sg:tags":[
        "heating",
        "contractor"
    ],
    "wof:name":"Peak Mechanical Services",
    "wof:placetype":"venue"
},
  "geometry": {"coordinates":[0.10702,51.38644],"type":"Point"}
}