{
  "type": "Feature",
  "properties": {
    "addr:full":"71-73 Briston Road Melton Constable Norfolk NR24 2AP",
    "addr:housenumber":"71-73",
    "addr:postcode":"nr24 2ap",
    "addr:street":"Briston Road",
    "iso:country":"GB",
    "sg:address":"71-73 Briston Road",
    "sg:city":"Melton Constable",
    "sg:classifiers":[
        {
            "category":"Shopping",
            "subcategory":"Department Store",
            "type":"Retail Goods"
        }
    ],
    "sg:phone":"+44 1263 861173",
    "sg:postcode":"NR24 2AP",
    "sg:province":"Norfolk",
    "wof:name":"Melton Stores",
    "wof:placetype":"venue"
},
  "geometry": {"coordinates":[1.0384969711,52.8566703796],"type":"Point"}
}