{
  "type": "Feature",
  "properties": {
    "addr:full":"22 Mason Hill View Preston Lancashire PR2 8DP",
    "addr:housenumber":"22",
    "addr:postcode":"pr2 8dp",
    "addr:street":"Mason Hill",
    "iso:country":"GB",
    "sg:address":"22 Mason Hill View",
    "sg:city":"Preston",
    "sg:classifiers":[
        {
            "category":"Building & Trades",
            "subcategory":"Cleaning & Sanitation",
            "type":"Services"
        }
    ],
    "sg:phone":"+44 1772 719998",
    "sg:postcode":"PR2 8DP",
    "sg:province":"Lancashire",
    "sg:tags":[
        "commercial"
    ],
    "wof:name":"Apple Clean",
    "wof:placetype":"venue"
},
  "geometry": {"coordinates":[-2.695882082,53.781993866],"type":"Point"}
}