{
  "type": "Feature",
  "properties": {
    "addr:full":"70 Waterdale Doncaster South Yorkshire DN1 3BU",
    "addr:housenumber":"70",
    "addr:postcode":"dn1 3bu",
    "addr:street":"Waterdale Doncaster South",
    "iso:country":"GB",
    "sg:address":"70 Waterdale",
    "sg:city":"Doncaster",
    "sg:classifiers":[
        {
            "category":"Professional",
            "subcategory":"Lawyer & Legal Services",
            "type":"Services"
        }
    ],
    "sg:phone":"+44 1302 360606",
    "sg:postcode":"DN1 3BU",
    "sg:province":"South Yorkshire",
    "sg:tags":[
        "solicitor"
    ],
    "wof:name":"G V Hale & Co",
    "wof:placetype":"venue"
},
  "geometry": {"coordinates":[-1.132057,53.520164],"type":"Point"}
}