{
  "type": "Feature",
  "properties": {
    "addr:full":"The Level Crossing, Station Road, Elmswell Bury St Edmunds Suffolk IP30 9HA",
    "addr:postcode":"ip30 9ha",
    "addr:street":"The Level Crossing Station Road",
    "iso:country":"GB",
    "sg:address":"The Level Crossing, Station Road, Elmswell",
    "sg:city":"Bury St Edmunds",
    "sg:classifiers":[
        {
            "category":"Retail",
            "subcategory":"Veterinary Services",
            "type":"Services"
        }
    ],
    "sg:phone":"+44 1359 241761",
    "sg:postcode":"IP30 9HA",
    "sg:province":"Suffolk",
    "sg:tags":[
        "surgeon"
    ],
    "wof:name":"The Old Tea Room Veterinary Surgery",
    "wof:placetype":"venue"
},
  "geometry": {"coordinates":[0.91154,52.23711],"type":"Point"}
}