{
  "type": "Feature",
  "properties": {
    "iso:country":"GB",
    "sg:address":"23 St Andrew Street",
    "sg:city":"Castle Douglas",
    "sg:classifiers":[
        {
            "category":"Home & Garden",
            "subcategory":"Furniture",
            "type":"Retail Goods"
        }
    ],
    "sg:phone":"+44 1556 504010",
    "sg:postcode":"DG7 1EL",
    "sg:province":"Dumfries and Galloway",
    "wof:name":"New Leaf Designs",
    "wof:placetype":"venue"
},
  "geometry": {"coordinates":[-3.931522,54.939034],"type":"Point"}
}