{
  "type": "Feature",
  "properties": {
    "addr:full":"Unit 3, Moss Road, Stanway Colchester Essex CO3 0LE",
    "addr:housenumber":"unit 3",
    "addr:postcode":"co3 0le",
    "addr:street":"Moss Road",
    "iso:country":"GB",
    "sg:address":"Unit 3, Moss Road, Stanway",
    "sg:city":"Colchester",
    "sg:classifiers":[
        {
            "category":"Building & Trades",
            "subcategory":"Equipment Rental",
            "type":"Services"
        }
    ],
    "sg:phone":"+44 1206 765244",
    "sg:postcode":"CO3 0LE",
    "sg:province":"Essex",
    "sg:tags":[
        "plant",
        "machinery"
    ],
    "wof:name":"Target Plant & Sales Ltd.",
    "wof:placetype":"venue"
},
  "geometry": {"coordinates":[0.84928,51.876865],"type":"Point"}
}