{
  "type": "Feature",
  "properties": {
    "iso:country":"GB",
    "sg:address":"468 Bromley Road",
    "sg:city":"Bromley",
    "sg:classifiers":[
        {
            "category":"Retail",
            "subcategory":"Funeral Services",
            "type":"Services"
        }
    ],
    "sg:phone":"+44 20 8697 2487",
    "sg:postcode":"BR1 4PP",
    "sg:province":"Kent",
    "wof:name":"Dignity Funerals Ltd.",
    "wof:placetype":"venue"
},
  "geometry": {"coordinates":[-0.0041319998,51.4244384766],"type":"Point"}
}