{
  "type": "Feature",
  "properties": {
    "addr:full":"51 Colebourne Road Birmingham West Midlands B13 0EZ",
    "addr:housenumber":"51",
    "addr:postcode":"b13 0ez",
    "addr:street":"Colebourne Road",
    "iso:country":"GB",
    "sg:address":"51 Colebourne Road",
    "sg:city":"Birmingham",
    "sg:classifiers":[
        {
            "category":"Shopping",
            "subcategory":"Optical Goods",
            "type":"Retail Goods"
        },
        {
            "category":"Wholesale",
            "subcategory":"Medical Equipment & Supplies",
            "type":"Manufacturing & Wholesale Goods"
        }
    ],
    "sg:postcode":"B13 0EZ",
    "sg:province":"West Midlands",
    "wof:name":"ZAHID KHAN",
    "wof:placetype":"venue"
},
  "geometry": {"coordinates":[-1.860183,52.427952],"type":"Point"}
}