{
  "type": "Feature",
  "properties": {
    "iso:country":"GB",
    "sg:address":"Porte Marsh Industrial Estate, Redman Road",
    "sg:city":"Calne",
    "sg:classifiers":[
        {
            "category":"Government",
            "subcategory":"Department Of Motor Vehicles",
            "type":"Public Place"
        }
    ],
    "sg:phone":"+44 1249 815141",
    "sg:postcode":"SN11 9PR",
    "sg:province":"Wiltshire",
    "sg:tags":[
        "conversion"
    ],
    "wof:name":"Specialist Vehicle Options",
    "wof:placetype":"venue"
},
  "geometry": {"coordinates":[-2.004912,51.437672],"type":"Point"}
}