{
  "type": "Feature",
  "properties": {
    "iso:country":"GB",
    "sg:address":"Unit 1a, St. Johns Ind Est, St. Johns Chapel",
    "sg:city":"Bishop Auckland",
    "sg:classifiers":[
        {
            "category":"Manufacturing",
            "subcategory":"Glass & Minerals",
            "type":"Manufacturing & Wholesale Goods"
        }
    ],
    "sg:phone":"+44 1388 537342",
    "sg:postcode":"DL13 1RP",
    "sg:province":"Durham",
    "sg:tags":[
        "fibre",
        "moulding"
    ],
    "wof:name":"A P R Fibreglass Products",
    "wof:placetype":"venue"
},
  "geometry": {"coordinates":[-2.17726,54.737549],"type":"Point"}
}