{
  "type": "Feature",
  "properties": {
    "addr:full":"94 Riverside Drive, Stoneclough Radcliffe Manchester Greater Manchester M26 1HY",
    "addr:housenumber":"94",
    "addr:postcode":"m26 1hy",
    "addr:street":"Riverside Drive",
    "iso:country":"GB",
    "sg:address":"94 Riverside Drive, Stoneclough Radcliffe",
    "sg:city":"Manchester",
    "sg:classifiers":[
        {
            "category":"Building & Trades",
            "subcategory":"Plumbing",
            "type":"Services"
        }
    ],
    "sg:postcode":"M26 1HY",
    "sg:province":"Greater Manchester",
    "sg:tags":[
        "heating"
    ],
    "wof:name":"Riverside Engineering Services",
    "wof:placetype":"venue"
},
  "geometry": {"coordinates":[-2.3677890301,53.5479812622],"type":"Point"}
}