{
  "type": "Feature",
  "properties": {
    "iso:country":"GB",
    "sg:address":"110 Common Edge Road",
    "sg:city":"Blackpool",
    "sg:classifiers":[
        {
            "category":"Building & Trades",
            "subcategory":"Construction",
            "type":"Services"
        }
    ],
    "sg:phone":"+44 1253 792911",
    "sg:postcode":"FY4 5AZ",
    "sg:province":"Lancashire",
    "sg:tags":[
        "dry",
        "plastering",
        "plasterers",
        "lining",
        "related",
        "screeders"
    ],
    "wof:name":"Hansons Of Blackpool",
    "wof:placetype":"venue"
},
  "geometry": {"coordinates":[-3.0226540565,53.7848243713],"type":"Point"}
}