{
  "type": "Feature",
  "properties": {
    "iso:country":"GB",
    "sg:address":"Fp Leach And Co, 62/64 Northumbria Drive",
    "sg:city":"Bristol",
    "sg:classifiers":[
        {
            "category":"Professional",
            "subcategory":"Advertising",
            "type":"Services"
        }
    ],
    "sg:postcode":"BS9 4HW",
    "sg:province":"City of Bristol",
    "sg:tags":[
        "mail",
        "direct"
    ],
    "wof:name":"Data Driven Marketing Ltd",
    "wof:placetype":"venue"
},
  "geometry": {"coordinates":[-2.61122,51.48016],"type":"Point"}
}