{
  "type": "Feature",
  "properties": {
    "iso:country":"GB",
    "sg:address":"Newington Court, 1 Collins Road",
    "sg:city":"London",
    "sg:classifiers":[
        {
            "category":"Travel",
            "subcategory":"Hostel",
            "type":"Entertainment"
        }
    ],
    "sg:phone":"+44 20 7359 2495",
    "sg:postcode":"N5 2UF",
    "sg:province":"Greater London",
    "wof:name":"Newington Court Ltd.",
    "wof:placetype":"venue"
},
  "geometry": {"coordinates":[-0.0923490003,51.556930542],"type":"Point"}
}