{
  "type": "Feature",
  "properties": {
    "iso:country":"GB",
    "sg:address":"Children & Families, 20 Russell Sq",
    "sg:city":"Telford",
    "sg:classifiers":[
        {
            "category":"Social Services",
            "type":"Services"
        }
    ],
    "sg:phone":"+44 1952 586226",
    "sg:postcode":"TF7 5BB",
    "sg:province":"Shropshire",
    "wof:name":"South Wrekin Initial Response Team",
    "wof:placetype":"venue"
},
  "geometry": {"coordinates":[-2.4514300823,52.636341095],"type":"Point"}
}