{
  "type": "Feature",
  "properties": {
    "addr:full":"Beaconsfield House, High Street, Upton Gainsborough Lincolnshire DN21 5NQ",
    "addr:postcode":"dn21 5nq",
    "addr:street":"High Street",
    "iso:country":"GB",
    "sg:address":"Beaconsfield House, High Street, Upton",
    "sg:city":"Gainsborough",
    "sg:classifiers":[
        {
            "category":"Building & Trades",
            "subcategory":"Cleaning & Sanitation",
            "type":"Services"
        }
    ],
    "sg:phone":"+44 1427 838304",
    "sg:postcode":"DN21 5NQ",
    "sg:province":"Lincolnshire",
    "sg:tags":[
        "blast"
    ],
    "wof:name":"Custom Vehicle Engineering Ltd.",
    "wof:placetype":"venue"
},
  "geometry": {"coordinates":[-0.696318984,53.3702507019],"type":"Point"}
}