{
  "type": "Feature",
  "properties": {
    "iso:country":"GB",
    "sg:address":"52 Vienna Road, Edgeley",
    "sg:city":"Stockport",
    "sg:classifiers":[
        {
            "category":"Professional",
            "subcategory":"Management & Consulting",
            "type":"Services"
        }
    ],
    "sg:phone":"+44 161 477 6387",
    "sg:postcode":"SK3 9QQ",
    "sg:province":"Cheshire",
    "sg:tags":[
        "consultant",
        "specialist"
    ],
    "wof:name":"Express Beauty",
    "wof:placetype":"venue"
},
  "geometry": {"coordinates":[-2.171216,53.3969],"type":"Point"}
}