{
  "type": "Feature",
  "properties": {
    "iso:country":"GB",
    "sg:address":"Woolstone",
    "sg:city":"Cheltenham",
    "sg:classifiers":[
        {
            "category":"Place Of Worship",
            "type":"Public Place"
        }
    ],
    "sg:phone":"+44 1242 672921",
    "sg:postcode":"GL52 4RG",
    "sg:province":"Gloucestershire",
    "wof:name":"St Martin De Tours",
    "wof:placetype":"venue"
},
  "geometry": {"coordinates":[-2.061299,51.966873],"type":"Point"}
}