{
  "type": "Feature",
  "properties": {
    "addr:full":"Rear Of 49 High Street Tamworth Staffordshire B78 1DX",
    "addr:housenumber":"rear of 49",
    "addr:postcode":"b78 1dx",
    "addr:street":"High Street",
    "iso:country":"GB",
    "sg:address":"Rear Of 49 High Street",
    "sg:city":"Tamworth",
    "sg:classifiers":[
        {
            "category":"Professional",
            "subcategory":"Engineering",
            "type":"Services"
        }
    ],
    "sg:phone":"+44 1827 892584",
    "sg:postcode":"B78 1DX",
    "sg:province":"Staffordshire",
    "sg:tags":[
        "precision",
        "engineer"
    ],
    "wof:name":"Pavrak Engineering",
    "wof:placetype":"venue"
},
  "geometry": {"coordinates":[-1.6117899418,52.6205215454],"type":"Point"}
}