{
  "type": "Feature",
  "properties": {
    "addr:full":"The Cottage, Tolvaddon Camborne Cornwall TR14 0EH",
    "addr:postcode":"tr14 0eh",
    "addr:street":"Tolvaddon",
    "iso:country":"GB",
    "sg:address":"The Cottage, Tolvaddon",
    "sg:city":"Camborne",
    "sg:classifiers":[
        {
            "category":"Building & Trades",
            "subcategory":"Construction",
            "type":"Services"
        }
    ],
    "sg:phone":"+44 1209 612233",
    "sg:postcode":"TR14 0EH",
    "sg:province":"Cornwall",
    "sg:tags":[
        "roofing"
    ],
    "wof:name":"A B A Roofing",
    "wof:placetype":"venue"
},
  "geometry": {"coordinates":[-5.2844948769,50.2314872742],"type":"Point"}
}