{
  "type": "Feature",
  "properties": {
    "iso:country":"GB",
    "sg:address":"62 Furnival Ave",
    "sg:city":"Slough",
    "sg:classifiers":[
        {
            "category":"Wholesale",
            "subcategory":"Scrap",
            "type":"Manufacturing & Wholesale Goods"
        }
    ],
    "sg:postcode":"SL2 1DW",
    "sg:province":"Berkshire",
    "sg:tags":[
        "waste",
        "metal"
    ],
    "wof:name":"Drayton Recycling Ltd",
    "wof:placetype":"venue"
},
  "geometry": {"coordinates":[-0.620335,51.527405],"type":"Point"}
}