{
  "type": "Feature",
  "properties": {
    "addr:full":"81 Babbacombe Rd Torquay Devon TQ1 3SR",
    "addr:housenumber":"81",
    "addr:postcode":"tq1 3sr",
    "addr:street":"Babbacombe Rd",
    "iso:country":"GB",
    "sg:address":"81 Babbacombe Rd",
    "sg:city":"Torquay",
    "sg:classifiers":[
        {
            "category":"Cafe",
            "type":"Food & Drink"
        }
    ],
    "sg:phone":"+44 1803 326296",
    "sg:postcode":"TQ1 3SR",
    "sg:province":"Devon",
    "sg:tags":[
        "tea",
        "room"
    ],
    "wof:name":"The Coffee Bean",
    "wof:placetype":"venue"
},
  "geometry": {"coordinates":[-3.515146,50.478493],"type":"Point"}
}