{
  "type": "Feature",
  "properties": {
    "addr:full":"Pleckgate Road Blackburn Lancashire BB1 8QW",
    "addr:postcode":"bb1 8qw",
    "addr:street":"Pleckgate Road",
    "iso:country":"GB",
    "sg:address":"Pleckgate Road",
    "sg:city":"Blackburn",
    "sg:classifiers":[
        {
            "category":"Bars & Pubs",
            "type":"Food & Drink"
        },
        {
            "category":"Community Center",
            "subcategory":"Social",
            "type":"Public Place"
        }
    ],
    "sg:phone":"+44 1254 240887",
    "sg:postcode":"BB1 8QW",
    "sg:province":"Lancashire",
    "sg:tags":[
        "pubs",
        "house",
        "inn",
        "activity"
    ],
    "wof:name":"Knowles Arms Hotel",
    "wof:placetype":"venue"
},
  "geometry": {"coordinates":[-2.4822940826,53.7740745544],"type":"Point"}
}