{
  "type": "Feature",
  "properties": {
    "iso:country":"GB",
    "sg:address":"11 Beach Rd",
    "sg:city":"Perranporth",
    "sg:classifiers":[
        {
            "category":"Restaurant",
            "type":"Food & Drink"
        }
    ],
    "sg:phone":"+44 1872 572183",
    "sg:postcode":"TR6 0JL",
    "sg:province":"Cornwall",
    "wof:name":"Haddocks End Fish Restaurant",
    "wof:placetype":"venue"
},
  "geometry": {"coordinates":[-5.154581,50.345512],"type":"Point"}
}