{
  "type": "Feature",
  "properties": {
    "addr:full":"Holmer Trading Estate, Block A Hereford Herefordshire HR1 1JS",
    "addr:postcode":"hr1 1js",
    "addr:street":"Trading;Block",
    "iso:country":"GB",
    "sg:address":"Holmer Trading Estate, Block A",
    "sg:city":"Hereford",
    "sg:classifiers":[
        {
            "category":"Home & Garden",
            "subcategory":"Hardware",
            "type":"Retail Goods"
        }
    ],
    "sg:postcode":"HR1 1JS",
    "sg:province":"Herefordshire",
    "sg:tags":[
        "equipment",
        "bathroom",
        "fitting"
    ],
    "wof:name":"Elite Bathrooms",
    "wof:placetype":"venue"
},
  "geometry": {"coordinates":[-2.7192549706,52.0793037415],"type":"Point"}
}