{
  "type": "Feature",
  "properties": {
    "iso:country":"GB",
    "sg:address":"72 Sedlescombe Road North",
    "sg:city":"St Leonards-on-sea",
    "sg:classifiers":[
        {
            "category":"Shopping",
            "subcategory":"Used Merchandise",
            "type":"Retail Goods"
        }
    ],
    "sg:postcode":"TN37 7DT",
    "sg:province":"East Sussex",
    "sg:tags":[
        "shop",
        "second-hand"
    ],
    "wof:name":"C D S Discounts",
    "wof:placetype":"venue"
},
  "geometry": {"coordinates":[0.557449,50.870174],"type":"Point"}
}