{
  "type": "Feature",
  "properties": {
    "addr:full":"9 Manor Road, Heather Coalville Leicestershire LE67 2RA",
    "addr:housenumber":"9",
    "addr:postcode":"le67 2ra",
    "addr:street":"Manor Road",
    "iso:country":"GB",
    "sg:address":"9 Manor Road, Heather",
    "sg:city":"Coalville",
    "sg:classifiers":[
        {
            "category":"Building & Trades",
            "subcategory":"Plumbing",
            "type":"Services"
        }
    ],
    "sg:postcode":"LE67 2RA",
    "sg:province":"Leicestershire",
    "sg:tags":[
        "heating"
    ],
    "wof:name":"Kenneth V Wooley",
    "wof:placetype":"venue"
},
  "geometry": {"coordinates":[-1.3788460493,52.7106781006],"type":"Point"}
}