{
  "type": "Feature",
  "properties": {
    "iso:country":"GB",
    "sg:address":"24a Quay Road",
    "sg:city":"Bridlington",
    "sg:classifiers":[
        {
            "category":"Shopping",
            "subcategory":"Thrift Store",
            "type":"Retail Goods"
        }
    ],
    "sg:phone":"+44 1262 679038",
    "sg:postcode":"YO15 2AP",
    "sg:province":"East Riding of Yorkshire",
    "sg:tags":[
        "shop",
        "charity"
    ],
    "wof:name":"Rspca",
    "wof:placetype":"venue"
},
  "geometry": {"coordinates":[-0.195192,54.085056],"type":"Point"}
}