{
  "type": "Feature",
  "properties": {
    "addr:full":"194 Woodlands Road Southampton Hampshire SO40 7GL",
    "addr:housenumber":"194",
    "addr:postcode":"so40 7gl",
    "addr:street":"Woodlands Road",
    "iso:country":"GB",
    "sg:address":"194 Woodlands Road",
    "sg:city":"Southampton",
    "sg:classifiers":[
        {
            "category":"Building & Trades",
            "subcategory":"Construction",
            "type":"Services"
        }
    ],
    "sg:postcode":"SO40 7GL",
    "sg:province":"Hampshire",
    "sg:tags":[
        "contractor"
    ],
    "wof:name":"Gyles Construction Ltd.",
    "wof:placetype":"venue"
},
  "geometry": {"coordinates":[-1.5447280407,50.9023742676],"type":"Point"}
}