{
  "type": "Feature",
  "properties": {
    "addr:full":"Ashwood Brierley Hill Staffordshire DY6 0AQ",
    "addr:postcode":"dy6 0aq",
    "iso:country":"GB",
    "sg:address":"Ashwood",
    "sg:city":"Brierley Hill",
    "sg:classifiers":[
        {
            "category":"Autos & Motor Vehicles",
            "subcategory":"Boat Sales",
            "type":"Retail Goods"
        }
    ],
    "sg:phone":"+44 1384 401464",
    "sg:postcode":"DY6 0AQ",
    "sg:province":"Staffordshire",
    "sg:tags":[
        "repair",
        "builder"
    ],
    "wof:name":"Orion Narrowboats Ltd.",
    "wof:placetype":"venue"
},
  "geometry": {"coordinates":[-2.20135,52.492168],"type":"Point"}
}