{
  "type": "Feature",
  "properties": {
    "iso:country":"GB",
    "sg:address":"Kingscombe House, Station Road, Kelly Bray",
    "sg:city":"Callington",
    "sg:classifiers":[
        {
            "category":"Building & Trades",
            "subcategory":"Construction",
            "type":"Services"
        }
    ],
    "sg:postcode":"PL17 8ER",
    "sg:province":"Cornwall",
    "sg:tags":[
        "builder"
    ],
    "wof:name":"Connell J M Building & Roofing Contractor",
    "wof:placetype":"venue"
},
  "geometry": {"coordinates":[-4.309844017,50.5222663879],"type":"Point"}
}