{
  "type": "Feature",
  "properties": {
    "addr:full":"24 Chevington Grove Whitley Bay Northumberland NE25 9UG",
    "addr:housenumber":"24",
    "addr:postcode":"ne25 9ug",
    "addr:street":"Chevington Grove",
    "iso:country":"GB",
    "sg:address":"24 Chevington Grove",
    "sg:city":"Whitley Bay",
    "sg:classifiers":[
        {
            "category":"Professional",
            "subcategory":"Engineering",
            "type":"Services"
        }
    ],
    "sg:phone":"+44 191 291 0304",
    "sg:postcode":"NE25 9UG",
    "sg:province":"Northumberland",
    "sg:tags":[
        "consulting",
        "engineer"
    ],
    "wof:name":"Plastic Pipes",
    "wof:placetype":"venue"
},
  "geometry": {"coordinates":[-1.4715729952,55.0512924194],"type":"Point"}
}