{
  "type": "Feature",
  "properties": {
    "addr:full":"Cofause Lane, Bramley, Tadley Basingstoke Berkshire RG26 5DN",
    "addr:postcode":"rg26 5dn",
    "addr:street":"Cofause Lane",
    "iso:country":"GB",
    "sg:address":"Cofause Lane, Bramley, Tadley",
    "sg:city":"Basingstoke",
    "sg:classifiers":[
        {
            "category":"Real Estate",
            "subcategory":"Surveying",
            "type":"Services"
        }
    ],
    "sg:phone":"+44 1256 880798",
    "sg:postcode":"RG26 5DN",
    "sg:province":"Berkshire",
    "sg:tags":[
        "surveyor",
        "valuer"
    ],
    "wof:name":"Clare Montague & Co Chartered Surveyors",
    "wof:placetype":"venue"
},
  "geometry": {"coordinates":[-1.0608240366,51.3305244446],"type":"Point"}
}