{
  "type": "Feature",
  "properties": {
    "addr:full":"235 Chingford Mount Road London Greater London E4 8LP",
    "addr:housenumber":"235",
    "addr:postcode":"e4 8lp",
    "addr:street":"Chingford Mount Road",
    "iso:country":"GB",
    "sg:address":"235 Chingford Mount Road",
    "sg:city":"London",
    "sg:classifiers":[
        {
            "category":"Home & Garden",
            "subcategory":"Household Appliances",
            "type":"Retail Goods"
        }
    ],
    "sg:postcode":"E4 8LP",
    "sg:province":"Greater London",
    "sg:tags":[
        "electrical",
        "domestic"
    ],
    "wof:name":"SOUNDS ELECTRICAL",
    "wof:placetype":"venue"
},
  "geometry": {"coordinates":[-0.0175429992,51.6156425476],"type":"Point"}
}