{
  "type": "Feature",
  "properties": {
    "addr:full":"B23 St Davids Square Swansea Neath Port Talbot SA1 3LG",
    "addr:postcode":"b23;sa1 3lg",
    "addr:street":"St Davids Square",
    "iso:country":"GB",
    "sg:address":"B23 St Davids Square",
    "sg:city":"Swansea",
    "sg:classifiers":[
        {
            "category":"Personal",
            "subcategory":"Beauty Salon",
            "type":"Services"
        }
    ],
    "sg:phone":"+44 1792 465963",
    "sg:postcode":"SA1 3LG",
    "sg:province":"Neath Port Talbot",
    "sg:tags":[
        "unisex",
        "hairdresser"
    ],
    "wof:name":"Mane Attraction",
    "wof:placetype":"venue"
},
  "geometry": {"coordinates":[-3.940928936,51.6231536865],"type":"Point"}
}