{
  "type": "Feature",
  "properties": {
    "addr:full":"7 Clifford Street West End Hampshire W1X 2US",
    "addr:housenumber":"7",
    "addr:postcode":"w1x 2us",
    "addr:street":"Clifford Street",
    "iso:country":"GB",
    "sg:address":"7 Clifford Street",
    "sg:city":"West End",
    "sg:classifiers":[
        {
            "category":"Organizations",
            "subcategory":"Membership Organization",
            "type":"Services"
        }
    ],
    "sg:postcode":"W1X 2US",
    "sg:province":"Hampshire",
    "sg:tags":[
        "club"
    ],
    "wof:name":"City & West End Management Ltd",
    "wof:placetype":"venue"
},
  "geometry": {"coordinates":[-0.13899,51.50758],"type":"Point"}
}