{
  "type": "Feature",
  "properties": {
    "iso:country":"GB",
    "sg:address":"25 Cromwell St",
    "sg:city":"Rotherham",
    "sg:classifiers":[
        {
            "category":"Military Area",
            "subcategory":"Air Force Base",
            "type":"Public Place"
        }
    ],
    "sg:phone":"+44 1709 880593",
    "sg:postcode":"S63 0HW",
    "sg:province":"South Yorkshire",
    "sg:tags":[
        "taxi",
        "hire",
        "private"
    ],
    "wof:name":"Neils Taxis",
    "wof:placetype":"venue"
},
  "geometry": {"coordinates":[-1.300903,53.551468],"type":"Point"}
}