{
  "type": "Feature",
  "properties": {
    "addr:full":"70 Rodney St Liverpool Merseyside L1 9AF",
    "addr:housenumber":"70",
    "addr:postcode":"l1 9af",
    "addr:street":"Rodney St",
    "iso:country":"GB",
    "sg:address":"70 Rodney St",
    "sg:city":"Liverpool",
    "sg:classifiers":[
        {
            "category":"Wholesale",
            "subcategory":"Meat",
            "type":"Manufacturing & Wholesale Goods"
        }
    ],
    "sg:phone":"+44 151 545 1950",
    "sg:postcode":"L1 9AF",
    "sg:province":"Merseyside",
    "sg:tags":[
        "-"
    ],
    "wof:name":"Direct Meat Co Ltd",
    "wof:placetype":"venue"
},
  "geometry": {"coordinates":[-2.973915,53.400494],"type":"Point"}
}