{
  "type": "Feature",
  "properties": {
    "addr:full":"98 Wilmot Street, Long Eaton Nottingham Derbyshire NG10 3DQ",
    "addr:housenumber":"98",
    "addr:postcode":"ng10 3dq",
    "addr:street":"Wilmot Street",
    "iso:country":"GB",
    "sg:address":"98 Wilmot Street, Long Eaton",
    "sg:city":"Nottingham",
    "sg:classifiers":[
        {
            "category":"Social Services",
            "subcategory":"Adult Care",
            "type":"Services"
        },
        {
            "category":"Government",
            "subcategory":"Office",
            "type":"Public Place"
        }
    ],
    "sg:phone":"+44 115 972 9053",
    "sg:postcode":"NG10 3DQ",
    "sg:province":"Derbyshire",
    "sg:tags":[
        "housing",
        "local",
        "sheltered"
    ],
    "wof:name":"Wilmot Street Sheltered Housing",
    "wof:placetype":"venue"
},
  "geometry": {"coordinates":[-1.2967009544,52.8848495483],"type":"Point"}
}