{
  "type": "Feature",
  "properties": {
    "addr:full":"Garretts Farm, Plough Road Sheerness Kent ME12 1RQ",
    "addr:postcode":"me12 1rq",
    "addr:street":"Garretts;Plough Road",
    "iso:country":"GB",
    "sg:address":"Garretts Farm, Plough Road",
    "sg:city":"Sheerness",
    "sg:classifiers":[
        {
            "category":"Government",
            "subcategory":"Department Of Motor Vehicles",
            "type":"Public Place"
        }
    ],
    "sg:phone":"+44 1795 880870",
    "sg:postcode":"ME12 1RQ",
    "sg:province":"Kent",
    "sg:tags":[
        "engine",
        "component"
    ],
    "wof:name":"Exhaust Direct Ltd",
    "wof:placetype":"venue"
},
  "geometry": {"coordinates":[0.764665,51.43885],"type":"Point"}
}