{
  "type": "Feature",
  "properties": {
    "addr:full":"56 High Street Tranent East Lothian EH33 1HH",
    "addr:housenumber":"56",
    "addr:postcode":"eh33 1hh",
    "addr:street":"High Street",
    "iso:country":"GB",
    "sg:address":"56 High Street",
    "sg:city":"Tranent",
    "sg:classifiers":[
        {
            "category":"Building & Trades",
            "subcategory":"Construction",
            "type":"Services"
        }
    ],
    "sg:phone":"+44 1875 610292",
    "sg:postcode":"EH33 1HH",
    "sg:province":"East Lothian",
    "sg:tags":[
        "dry",
        "lining",
        "plasterers",
        "screeders"
    ],
    "wof:name":"George McNeill & Son",
    "wof:placetype":"venue"
},
  "geometry": {"coordinates":[-2.9518549442,55.9439315796],"type":"Point"}
}