{
  "type": "Feature",
  "properties": {
    "addr:full":"36 Ormskirk Road, Rainford St Helens Lancashire WA11 8DH",
    "addr:housenumber":"36",
    "addr:postcode":"wa11 8dh",
    "addr:street":"Ormskirk Road Rainford",
    "iso:country":"GB",
    "sg:address":"36 Ormskirk Road, Rainford",
    "sg:city":"St Helens",
    "sg:classifiers":[
        {
            "category":"Wholesale",
            "subcategory":"Chemicals & Plastics",
            "type":"Manufacturing & Wholesale Goods"
        }
    ],
    "sg:phone":"+44 1744 882510",
    "sg:postcode":"WA11 8DH",
    "sg:province":"Lancashire",
    "sg:tags":[
        "retail",
        "freezer",
        "refrigerator"
    ],
    "wof:name":"P Melling",
    "wof:placetype":"venue"
},
  "geometry": {"coordinates":[-2.7904310226,53.5037651062],"type":"Point"}
}