{
  "type": "Feature",
  "properties": {
    "addr:full":"Wingard House, Lincoln St, Healey Wood Industrial Estate Burnley Lancashire BB11 2HW",
    "addr:housenumber":"estate",
    "addr:postcode":"bb11 2hw",
    "addr:street":"Lincoln St Healey Wood Industrial",
    "iso:country":"GB",
    "sg:address":"Wingard House, Lincoln St, Healey Wood Industrial Estate",
    "sg:city":"Burnley",
    "sg:classifiers":[
        {
            "category":"Manufacturing",
            "subcategory":"Signs",
            "type":"Manufacturing & Wholesale Goods"
        }
    ],
    "sg:phone":"+44 1282 454807",
    "sg:postcode":"BB11 2HW",
    "sg:province":"Lancashire",
    "sg:tags":[
        "nameplate"
    ],
    "wof:name":"Boydell & Jack Signs",
    "wof:placetype":"venue"
},
  "geometry": {"coordinates":[-2.242244,53.783241],"type":"Point"}
}