{
  "type": "Feature",
  "properties": {
    "addr:full":"Albion Mills, Hutson Street Bradford West Yorkshire BD5 7LZ",
    "addr:postcode":"bd5 7lz",
    "addr:street":"Albion;Hutson Street",
    "iso:country":"GB",
    "sg:address":"Albion Mills, Hutson Street",
    "sg:city":"Bradford",
    "sg:classifiers":[
        {
            "category":"Sports & Exercise",
            "subcategory":"Golf",
            "type":"Entertainment"
        }
    ],
    "sg:phone":"+44 1274 733877",
    "sg:postcode":"BD5 7LZ",
    "sg:province":"West Yorkshire",
    "sg:tags":[
        "greeting",
        "card"
    ],
    "wof:name":"Memories Cards Ltd.",
    "wof:placetype":"venue"
},
  "geometry": {"coordinates":[-1.76096,53.780128],"type":"Point"}
}