{
  "type": "Feature",
  "properties": {
    "addr:full":"Home Farm, Ashton Wold Peterborough Cambridgeshire PE8 5LZ",
    "addr:postcode":"pe8 5lz",
    "addr:street":"Wold Peterborough",
    "iso:country":"GB",
    "sg:address":"Home Farm, Ashton Wold",
    "sg:city":"Peterborough",
    "sg:classifiers":[
        {
            "category":"Real Estate",
            "subcategory":"Real Estate Agent",
            "type":"Services"
        }
    ],
    "sg:phone":"+44 1832 272264",
    "sg:postcode":"PE8 5LZ",
    "sg:province":"Cambridgeshire",
    "wof:name":"Ashton Farms",
    "wof:placetype":"venue"
},
  "geometry": {"coordinates":[-0.4477519989,52.4821662903],"type":"Point"}
}