{
  "type": "Feature",
  "properties": {
    "addr:full":"Leicester Road, Broughton Astley Leicester Leicestershire LE9 6RB",
    "addr:postcode":"le9 6rb",
    "addr:street":"Leicester Road",
    "iso:country":"GB",
    "sg:address":"Leicester Road, Broughton Astley",
    "sg:city":"Leicester",
    "sg:classifiers":[
        {
            "category":"Farming",
            "subcategory":"Livestock Farm",
            "type":"Manufacturing & Wholesale Goods"
        }
    ],
    "sg:postcode":"LE9 6RB",
    "sg:province":"Leicestershire",
    "sg:tags":[
        "others"
    ],
    "wof:name":"A D Wheway",
    "wof:placetype":"venue"
},
  "geometry": {"coordinates":[-1.2255929708,52.5316772461],"type":"Point"}
}