{
  "type": "Feature",
  "properties": {
    "addr:full":"329 Leeds Road Ilkley North Yorkshire LS29 8NF",
    "addr:housenumber":"329",
    "addr:postcode":"ls29 8nf",
    "addr:street":"Leeds Road",
    "iso:country":"GB",
    "sg:address":"329 Leeds Road",
    "sg:city":"Ilkley",
    "sg:classifiers":[
        {
            "category":"Autos & Motor Vehicles",
            "subcategory":"Fuel & Gas Station",
            "type":"Retail Goods"
        }
    ],
    "sg:phone":"+44 1943 816141",
    "sg:postcode":"LS29 8NF",
    "sg:province":"North Yorkshire",
    "sg:tags":[
        "petrol",
        "filling"
    ],
    "wof:name":"Stepping Stone Service Station",
    "wof:placetype":"venue"
},
  "geometry": {"coordinates":[-1.801726,53.92992],"type":"Point"}
}