{
  "type": "Feature",
  "properties": {
    "addr:full":"1b Valley View Gardens Kenley Surrey CR8 5BR",
    "addr:housenumber":"1b",
    "addr:postcode":"cr8 5br",
    "addr:street":"Valley View Gardens",
    "iso:country":"GB",
    "sg:address":"1b Valley View Gardens",
    "sg:city":"Kenley",
    "sg:classifiers":[
        {
            "category":"Professional",
            "subcategory":"Computer Services",
            "type":"Services"
        }
    ],
    "sg:postcode":"CR8 5BR",
    "sg:province":"Surrey",
    "sg:tags":[
        "system",
        "software"
    ],
    "wof:name":"Fast Applications Ltd",
    "wof:placetype":"venue"
},
  "geometry": {"coordinates":[-0.0901160017,51.3208503723],"type":"Point"}
}