{
  "type": "Feature",
  "properties": {
    "addr:full":"205 Dialstone La Stockport Cheshire SK2 7LF",
    "addr:housenumber":"205",
    "addr:postcode":"sk2 7lf",
    "addr:street":"Dialstone La Stockport",
    "iso:country":"GB",
    "sg:address":"205 Dialstone La",
    "sg:city":"Stockport",
    "sg:classifiers":[
        {
            "category":"Professional",
            "type":"Services"
        }
    ],
    "sg:phone":"+44 161 456 7827",
    "sg:postcode":"SK2 7LF",
    "sg:province":"Cheshire",
    "sg:tags":[
        "shopfitters"
    ],
    "wof:name":"Creative Shopfitting Co Ltd",
    "wof:placetype":"venue"
},
  "geometry": {"coordinates":[-2.130624,53.39146],"type":"Point"}
}