{
  "type": "Feature",
  "properties": {
    "addr:full":"Libbys Drive, New Mills Trading Estate, Slad Road Stroud Gloucestershire GL5 1RN",
    "addr:postcode":"gl5 1rn",
    "addr:street":"Libbys Drive;Trading Estate Slad Road",
    "iso:country":"GB",
    "sg:address":"Libbys Drive, New Mills Trading Estate, Slad Road",
    "sg:city":"Stroud",
    "sg:classifiers":[
        {
            "category":"Organizations",
            "subcategory":"Community Association",
            "type":"Services"
        }
    ],
    "sg:phone":"+44 1453 750151",
    "sg:postcode":"GL5 1RN",
    "sg:province":"Gloucestershire",
    "sg:tags":[
        "relation",
        "public"
    ],
    "wof:name":"Granger Publicity Ltd.",
    "wof:placetype":"venue"
},
  "geometry": {"coordinates":[-2.206012,51.74931],"type":"Point"}
}