{
  "type": "Feature",
  "properties": {
    "iso:country":"GB",
    "sg:address":"3 Tudor Avenue",
    "sg:city":"Watford",
    "sg:classifiers":[
        {
            "category":"Shopping",
            "subcategory":"Computers & Home Electronics",
            "type":"Retail Goods"
        }
    ],
    "sg:phone":"+44 20 8950 5000",
    "sg:postcode":"WD24 7NU",
    "sg:province":"Hertfordshire",
    "sg:tags":[
        "aerial",
        "television",
        "radio"
    ],
    "wof:name":"Aerials of Watford",
    "wof:placetype":"venue"
},
  "geometry": {"coordinates":[-0.385905,51.67387],"type":"Point"}
}