{
  "type": "Feature",
  "properties": {
    "addr:full":"7 Harrier House, Sullivan Close London Greater London SW11 2NW",
    "addr:housenumber":"7",
    "addr:postcode":"sw11 2nw",
    "addr:street":"Sullivan Close",
    "iso:country":"GB",
    "sg:address":"7 Harrier House, Sullivan Close",
    "sg:city":"London",
    "sg:classifiers":[
        {
            "category":"Education",
            "subcategory":"School",
            "type":"Public Place"
        }
    ],
    "sg:postcode":"SW11 2NW",
    "sg:province":"Greater London",
    "sg:tags":[
        "local",
        "authority"
    ],
    "wof:name":"X-Ceptional Learning Ltd",
    "wof:placetype":"venue"
},
  "geometry": {"coordinates":[-0.1706099957,51.4667892456],"type":"Point"}
}