{
  "type": "Feature",
  "properties": {
    "iso:country":"GB",
    "sg:address":"Glebelands, Gadbridge Rd, Weobley",
    "sg:city":"Hereford",
    "sg:classifiers":[
        {
            "category":"Health Services",
            "subcategory":"Dentist",
            "type":"Services"
        }
    ],
    "sg:phone":"+44 1544 318166",
    "sg:postcode":"HR4 8SN",
    "sg:province":"Herefordshire",
    "wof:name":"James D Smith B.D.S",
    "wof:placetype":"venue"
},
  "geometry": {"coordinates":[-2.873729,52.159172],"type":"Point"}
}