{
  "type": "Feature",
  "properties": {
    "addr:full":"15 Mackenzie Gardens, Stewartfield Glasgow South Lanarkshire G74 4SA",
    "addr:housenumber":"15",
    "addr:postcode":"g74 4sa",
    "addr:street":"Mackenzie Gardens Stewartfield",
    "iso:country":"GB",
    "sg:address":"15 Mackenzie Gardens, Stewartfield",
    "sg:city":"Glasgow",
    "sg:classifiers":[
        {
            "category":"Home & Garden",
            "subcategory":"Home Furnishings",
            "type":"Retail Goods"
        }
    ],
    "sg:phone":"+44 1355 222109",
    "sg:postcode":"G74 4SA",
    "sg:province":"South Lanarkshire",
    "sg:tags":[
        "homefurnishings"
    ],
    "wof:name":"Shonatso Metal Furniture",
    "wof:placetype":"venue"
},
  "geometry": {"coordinates":[-4.2141289711,55.7745857239],"type":"Point"}
}