{
  "type": "Feature",
  "properties": {
    "iso:country":"GB",
    "sg:address":"1 Leighton Avenue",
    "sg:city":"Pinner",
    "sg:classifiers":[
        {
            "category":"Building & Trades",
            "subcategory":"Construction",
            "type":"Services"
        },
        {
            "category":"Building & Trades",
            "subcategory":"Electrical",
            "type":"Services"
        }
    ],
    "sg:postcode":"HA5 3BW",
    "sg:province":"Greater London",
    "sg:tags":[
        "roofing",
        "electrician",
        "contractor"
    ],
    "wof:name":"K.J. ELECTRICAL SERVICES LTD",
    "wof:placetype":"venue"
},
  "geometry": {"coordinates":[-0.3818570077,51.5963859558],"type":"Point"}
}