{
  "type": "Feature",
  "properties": {
    "addr:full":"4 Newburn Rd Newcastle Upon Tyne Northumberland NE15 8LX",
    "addr:housenumber":"4",
    "addr:postcode":"ne15 8lx",
    "addr:street":"Newburn Rd",
    "iso:country":"GB",
    "sg:address":"4 Newburn Rd",
    "sg:city":"Newcastle Upon Tyne",
    "sg:classifiers":[
        {
            "category":"Health Services",
            "subcategory":"Doctor",
            "type":"Services"
        }
    ],
    "sg:phone":"+44 191 229 0090",
    "sg:postcode":"NE15 8LX",
    "sg:province":"Northumberland",
    "sg:tags":[
        "practitioners"
    ],
    "wof:name":"Ashley, B K",
    "wof:placetype":"venue"
},
  "geometry": {"coordinates":[-1.743595,54.986046],"type":"Point"}
}