{
  "type": "Feature",
  "properties": {
    "addr:full":"10 Back West Avenue Newcastle-upon-tyne Tyne and Wear NE3 4ES",
    "addr:housenumber":"10",
    "addr:postcode":"ne3 4es",
    "addr:street":"Back West Avenue",
    "iso:country":"GB",
    "sg:address":"10 Back West Avenue",
    "sg:city":"Newcastle-upon-tyne",
    "sg:classifiers":[
        {
            "category":"Building & Trades",
            "subcategory":"Construction",
            "type":"Services"
        }
    ],
    "sg:phone":"+44 191 236 7439",
    "sg:postcode":"NE3 4ES",
    "sg:province":"Tyne and Wear",
    "sg:tags":[
        "builder"
    ],
    "wof:name":"Alan B Cairns & Son",
    "wof:placetype":"venue"
},
  "geometry": {"coordinates":[-1.6224399805,55.0047111511],"type":"Point"}
}