{
  "type": "Feature",
  "properties": {
    "iso:country":"GB",
    "sg:address":"7 Sutton Lane",
    "sg:city":"Middlewich",
    "sg:classifiers":[
        {
            "category":"Utilities",
            "subcategory":"Fuel Oil & Lpg",
            "type":"Services"
        }
    ],
    "sg:postcode":"CW10 0AD",
    "sg:province":"Cheshire",
    "sg:tags":[
        "coal",
        "smokeless"
    ],
    "wof:name":"White & Sons",
    "wof:placetype":"venue"
},
  "geometry": {"coordinates":[-2.4437110424,53.1869544983],"type":"Point"}
}