{
  "type": "Feature",
  "properties": {
    "addr:full":"215 Wexham Road Slough Berkshire SL2 5JT",
    "addr:housenumber":"215",
    "addr:postcode":"sl2 5jt",
    "addr:street":"Wexham Road",
    "iso:country":"GB",
    "sg:address":"215 Wexham Road",
    "sg:city":"Slough",
    "sg:classifiers":[
        {
            "category":"Shopping",
            "subcategory":"Department Store",
            "type":"Retail Goods"
        }
    ],
    "sg:phone":"+44 1753 511050",
    "sg:postcode":"SL2 5JT",
    "sg:province":"Berkshire",
    "wof:name":"Sabar Bros",
    "wof:placetype":"venue"
},
  "geometry": {"coordinates":[-0.5789399743,51.5167236328],"type":"Point"}
}