{
  "type": "Feature",
  "properties": {
    "iso:country":"GB",
    "sg:address":"1 Slater St",
    "sg:city":"Leicester",
    "sg:classifiers":[
        {
            "category":"Wholesale",
            "subcategory":"Non-durable Goods",
            "type":"Manufacturing & Wholesale Goods"
        }
    ],
    "sg:phone":"+44 116 251 9996",
    "sg:postcode":"LE3 5AS",
    "sg:province":"Leicestershire",
    "sg:tags":[
        "carry",
        "cash"
    ],
    "wof:name":"Direct Pizza Supplies",
    "wof:placetype":"venue"
},
  "geometry": {"coordinates":[-1.140605,52.642494],"type":"Point"}
}