{
  "type": "Feature",
  "properties": {
    "iso:country":"GB",
    "sg:address":"2 Tennyson Place, Walton Le Dale",
    "sg:city":"Preston",
    "sg:classifiers":[
        {
            "category":"Building & Trades",
            "subcategory":"Construction",
            "type":"Services"
        }
    ],
    "sg:phone":"+44 1772 334356",
    "sg:postcode":"PR5 4TT",
    "sg:province":"Lancashire",
    "sg:tags":[
        "joiner",
        "carpenter"
    ],
    "wof:name":"D Hilton",
    "wof:placetype":"venue"
},
  "geometry": {"coordinates":[-2.6725080013,53.7355651855],"type":"Point"}
}