{
  "type": "Feature",
  "properties": {
    "addr:full":"8 Dawset Sq London Greater London NW1 6PU",
    "addr:housenumber":"8",
    "addr:postcode":"nw1 6pu",
    "addr:street":"Dawset Sq",
    "iso:country":"GB",
    "sg:address":"8 Dawset Sq",
    "sg:city":"London",
    "sg:classifiers":[
        {
            "category":"Real Estate",
            "subcategory":"Architect",
            "type":"Services"
        }
    ],
    "sg:phone":"+44 20 7723 5655",
    "sg:postcode":"NW1 6PU",
    "sg:province":"Greater London",
    "wof:name":"Rokoko Ltd",
    "wof:placetype":"venue"
},
  "geometry": {"coordinates":[-0.160189,51.523064],"type":"Point"}
}