{
  "type": "Feature",
  "properties": {
    "addr:full":"Britannia Wks, Stafford St Market Drayton Shropshire TF9 1HZ",
    "addr:postcode":"tf9 1hz",
    "addr:street":"Stafford St",
    "iso:country":"GB",
    "sg:address":"Britannia Wks, Stafford St",
    "sg:city":"Market Drayton",
    "sg:classifiers":[
        {
            "category":"Retail",
            "subcategory":"Auto Repair",
            "type":"Services"
        }
    ],
    "sg:postcode":"TF9 1HZ",
    "sg:province":"Shropshire",
    "sg:tags":[
        "modification",
        "garage"
    ],
    "wof:name":"K & R Smith",
    "wof:placetype":"venue"
},
  "geometry": {"coordinates":[-2.4861719608,52.9040908813],"type":"Point"}
}