{
  "type": "Feature",
  "properties": {
    "addr:full":"23-25 Kirk Gate Newark Nottinghamshire NG24 1AD",
    "addr:housenumber":"23-25",
    "addr:postcode":"ng24 1ad",
    "addr:street":"Kirk Gate",
    "iso:country":"GB",
    "sg:address":"23-25 Kirk Gate",
    "sg:city":"Newark",
    "sg:classifiers":[
        {
            "category":"Shopping",
            "subcategory":"Discount & Variety Stores",
            "type":"Retail Goods"
        }
    ],
    "sg:phone":"+44 1636 613924",
    "sg:postcode":"NG24 1AD",
    "sg:province":"Nottinghamshire",
    "sg:tags":[
        "centre"
    ],
    "wof:name":"Mad Harry's Discount Store",
    "wof:placetype":"venue"
},
  "geometry": {"coordinates":[-0.8100039959,53.0780220032],"type":"Point"}
}