{
  "type": "Feature",
  "properties": {
    "addr:full":"93 Green Rd Oxford Oxfordshire OX3 8LD",
    "addr:housenumber":"93",
    "addr:postcode":"ox3 8ld",
    "addr:street":"Green Rd",
    "iso:country":"GB",
    "sg:address":"93 Green Rd",
    "sg:city":"Oxford",
    "sg:classifiers":[
        {
            "category":"Personal",
            "type":"Services"
        }
    ],
    "sg:phone":"+44 1865 452400",
    "sg:postcode":"OX3 8LD",
    "sg:province":"Oxfordshire",
    "sg:tags":[
        "stress",
        "management"
    ],
    "wof:name":"Oxford Stress Council",
    "wof:placetype":"venue"
},
  "geometry": {"coordinates":[-1.194306016,51.759929657],"type":"Point"}
}