{
  "type": "Feature",
  "properties": {
    "addr:full":"Moss Road Farm Shop, 29-31 Moss Road, Askern Doncaster North Yorkshire DN6 0LW",
    "addr:housenumber":"29-31",
    "addr:postcode":"dn6 0lw",
    "addr:street":"Moss Road;Moss Road",
    "iso:country":"GB",
    "sg:address":"Moss Road Farm Shop, 29-31 Moss Road, Askern",
    "sg:city":"Doncaster",
    "sg:classifiers":[
        {
            "category":"Food & Beverages",
            "subcategory":"Groceries & Convenience Stores",
            "type":"Retail Goods"
        }
    ],
    "sg:phone":"+44 1302 708941",
    "sg:postcode":"DN6 0LW",
    "sg:province":"North Yorkshire",
    "wof:name":"Moss Road Farm Shop",
    "wof:placetype":"venue"
},
  "geometry": {"coordinates":[-1.1437000036,53.6164207458],"type":"Point"}
}