{
  "type": "Feature",
  "properties": {
    "iso:country":"GB",
    "sg:address":"30 Station Rd, Camperdown",
    "sg:city":"Newcastle Upon Tyne",
    "sg:classifiers":[
        {
            "category":"Shopping",
            "type":"Retail Goods"
        }
    ],
    "sg:phone":"+44 191 268 3612",
    "sg:postcode":"NE12 5UX",
    "sg:province":"Tyne and Wear",
    "sg:tags":[
        "household",
        "store"
    ],
    "wof:name":"K Kaurs & Singh S",
    "wof:placetype":"venue"
},
  "geometry": {"coordinates":[-1.5814269781,55.0419006348],"type":"Point"}
}