{
  "type": "Feature",
  "properties": {
    "addr:full":"31 Spencer Court, Spencer Road London Greater London SW20 0QW",
    "addr:housenumber":"31",
    "addr:postcode":"sw20 0qw",
    "addr:street":"Spencer Court Spencer Road",
    "iso:country":"GB",
    "sg:address":"31 Spencer Court, Spencer Road",
    "sg:city":"London",
    "sg:classifiers":[
        {
            "category":"Professional",
            "subcategory":"Management & Consulting",
            "type":"Services"
        }
    ],
    "sg:postcode":"SW20 0QW",
    "sg:province":"Greater London",
    "sg:tags":[
        "consultant",
        "business"
    ],
    "wof:name":"Zamojski & Co. Ltd.",
    "wof:placetype":"venue"
},
  "geometry": {"coordinates":[-0.234031,51.41172],"type":"Point"}
}