{
  "type": "Feature",
  "properties": {
    "addr:full":"Unit 4-19, Ropery Business Park, Anchor & Hope Lane London Greater London SE7 7RX",
    "addr:housenumber":"4-19",
    "addr:postcode":"se7 7rx",
    "addr:street":"Ropery Business Park;Lane",
    "iso:country":"GB",
    "sg:address":"Unit 4-19, Ropery Business Park, Anchor & Hope Lane",
    "sg:city":"London",
    "sg:classifiers":[
        {
            "category":"Building & Trades",
            "subcategory":"Cleaning & Sanitation",
            "type":"Services"
        }
    ],
    "sg:phone":"+44 20 8293 4176",
    "sg:postcode":"SE7 7RX",
    "sg:province":"Greater London",
    "sg:tags":[
        "repair",
        "lift",
        "-"
    ],
    "wof:name":"Jackson Lift Services Ltd.",
    "wof:placetype":"venue"
},
  "geometry": {"coordinates":[0.0319099985,51.4905204773],"type":"Point"}
}