{
  "type": "Feature",
  "properties": {
    "addr:full":"213-217 Hartford Road Enfield Greater London EN3 5JH",
    "addr:housenumber":"213-217",
    "addr:postcode":"en3 5jh",
    "addr:street":"Hartford Road",
    "iso:country":"GB",
    "sg:address":"213-217 Hartford Road",
    "sg:city":"Enfield",
    "sg:classifiers":[
        {
            "category":"Shopping",
            "type":"Retail Goods"
        }
    ],
    "sg:phone":"+44 20 8805 0375",
    "sg:postcode":"EN3 5JH",
    "sg:province":"Greater London",
    "sg:tags":[
        "part",
        "accessory"
    ],
    "wof:name":"Autela Components Ltd.",
    "wof:placetype":"venue"
},
  "geometry": {"coordinates":[-0.04676,51.65868],"type":"Point"}
}