{
  "type": "Feature",
  "properties": {
    "addr:full":"21a Prettyman Dr, Llandarcy Neath Neath Port Talbot SA10 6HZ",
    "addr:housenumber":"21a",
    "addr:postcode":"sa10 6hz",
    "addr:street":"Prettyman Dr Llandarcy",
    "iso:country":"GB",
    "sg:address":"21a Prettyman Dr, Llandarcy",
    "sg:city":"Neath",
    "sg:classifiers":[
        {
            "category":"Building & Trades",
            "subcategory":"Construction",
            "type":"Services"
        }
    ],
    "sg:postcode":"SA10 6HZ",
    "sg:province":"Neath Port Talbot",
    "sg:tags":[
        "builder"
    ],
    "wof:name":"Davies,Michael,",
    "wof:placetype":"venue"
},
  "geometry": {"coordinates":[-3.856711,51.642151],"type":"Point"}
}