{
  "type": "Feature",
  "properties": {
    "addr:full":"251 Turners Hill, Cheshunt Waltham Cross Essex EN8 9DG",
    "addr:housenumber":"251",
    "addr:postcode":"en8 9dg",
    "addr:street":"Turners Hill Cheshunt;Cross",
    "iso:country":"GB",
    "sg:address":"251 Turners Hill, Cheshunt",
    "sg:city":"Waltham Cross",
    "sg:classifiers":[
        {
            "category":"Education",
            "subcategory":"Special Training",
            "type":"Public Place"
        }
    ],
    "sg:phone":"+44 1992 622222",
    "sg:postcode":"EN8 9DG",
    "sg:province":"Essex",
    "sg:tags":[
        "product",
        "centre"
    ],
    "wof:name":"Hospitality Plus",
    "wof:placetype":"venue"
},
  "geometry": {"coordinates":[-0.0342190005,51.7047386169],"type":"Point"}
}