{
  "type": "Feature",
  "properties": {
    "addr:full":"90 Denmark St Bedford Bedfordshire MK40 3TJ",
    "addr:housenumber":"90",
    "addr:postcode":"mk40 3tj",
    "addr:street":"Denmark St",
    "iso:country":"GB",
    "sg:address":"90 Denmark St",
    "sg:city":"Bedford",
    "sg:classifiers":[
        {
            "category":"Place Of Worship",
            "type":"Public Place"
        }
    ],
    "sg:phone":"+44 1234 217519",
    "sg:postcode":"MK40 3TJ",
    "sg:province":"Bedfordshire",
    "wof:name":"Russell Park Baptist Church",
    "wof:placetype":"venue"
},
  "geometry": {"coordinates":[-0.451564014,52.1387367249],"type":"Point"}
}