{
  "type": "Feature",
  "properties": {
    "iso:country":"GB",
    "sg:address":"13a Melville Street",
    "sg:city":"Edinburgh",
    "sg:classifiers":[
        {
            "category":"Professional",
            "subcategory":"Computer Services",
            "type":"Services"
        }
    ],
    "sg:postcode":"EH3 7PE",
    "sg:province":"City of Edinburgh",
    "sg:tags":[
        "information"
    ],
    "wof:name":"The European Movement Scottish Council",
    "wof:placetype":"venue"
},
  "geometry": {"coordinates":[-3.211732,55.95092],"type":"Point"}
}