{
  "type": "Feature",
  "properties": {
    "addr:full":"Unit 3-4, North Court Bridgend Bridgend CF31 3TP",
    "addr:housenumber":"unit 3-4",
    "addr:postcode":"cf31 3tp",
    "addr:street":"North Court",
    "iso:country":"GB",
    "sg:address":"Unit 3-4, North Court",
    "sg:city":"Bridgend",
    "sg:classifiers":[
        {
            "category":"Manufacturing",
            "subcategory":"Food",
            "type":"Manufacturing & Wholesale Goods"
        }
    ],
    "sg:phone":"+44 870 905 0082",
    "sg:postcode":"CF31 3TP",
    "sg:province":"Bridgend",
    "sg:tags":[
        "mech",
        "processing"
    ],
    "wof:name":"Avery Berkel",
    "wof:placetype":"venue"
},
  "geometry": {"coordinates":[-3.5399138927,51.5031890869],"type":"Point"}
}