{
  "type": "Feature",
  "properties": {
    "addr:full":"Unit 4 Hecla Works, Brown Street, Bamber Bridge Preston Lancashire PR5 6NQ",
    "addr:housenumber":"unit 4",
    "addr:postcode":"pr5 6nq",
    "addr:street":"Hecla Works Brown Street",
    "iso:country":"GB",
    "sg:address":"Unit 4 Hecla Works, Brown Street, Bamber Bridge",
    "sg:city":"Preston",
    "sg:classifiers":[
        {
            "category":"Retail",
            "subcategory":"Auto Repair",
            "type":"Services"
        }
    ],
    "sg:phone":"+44 1772 334093",
    "sg:postcode":"PR5 6NQ",
    "sg:province":"Lancashire",
    "sg:tags":[
        "body",
        "car"
    ],
    "wof:name":"A & S Autocentre",
    "wof:placetype":"venue"
},
  "geometry": {"coordinates":[-2.6605689526,53.7277641296],"type":"Point"}
}