{
  "type": "Feature",
  "properties": {
    "iso:country":"GB",
    "sg:address":"101 High Street, Biddulph",
    "sg:city":"Stoke-on-trent",
    "sg:classifiers":[
        {
            "category":"Real Estate",
            "subcategory":"Real Estate Agent",
            "type":"Services"
        }
    ],
    "sg:phone":"+44 1782 518866",
    "sg:postcode":"ST8 6AB",
    "sg:province":"Staffordshire",
    "wof:name":"Norman Griffiths & Co.",
    "wof:placetype":"venue"
},
  "geometry": {"coordinates":[-2.176245,53.115204],"type":"Point"}
}