{
  "type": "Feature",
  "properties": {
    "addr:full":"3 Park Road Blackpool Lancashire FY1 4JQ",
    "addr:housenumber":"3",
    "addr:postcode":"fy1 4jq",
    "addr:street":"Park Road",
    "iso:country":"GB",
    "sg:address":"3 Park Road",
    "sg:city":"Blackpool",
    "sg:classifiers":[
        {
            "category":"Travel",
            "subcategory":"Hotels & Motels",
            "type":"Entertainment"
        }
    ],
    "sg:phone":"+44 1253 627399",
    "sg:postcode":"FY1 4JQ",
    "sg:province":"Lancashire",
    "sg:tags":[
        "house",
        "self",
        "guest",
        "catering"
    ],
    "wof:name":"Enville Holiday Flats",
    "wof:placetype":"venue"
},
  "geometry": {"coordinates":[-3.045457,53.817726],"type":"Point"}
}