{
  "type": "Feature",
  "properties": {
    "addr:full":"5 Newtown Rd Bishops Stortford Essex CM23 3SA",
    "addr:housenumber":"5",
    "addr:postcode":"cm23 3sa",
    "addr:street":"Newtown Rd",
    "iso:country":"GB",
    "sg:address":"5 Newtown Rd",
    "sg:city":"Bishops Stortford",
    "sg:classifiers":[
        {
            "category":"Insurance",
            "subcategory":"Insurance Agent",
            "type":"Services"
        }
    ],
    "sg:postcode":"CM23 3SA",
    "sg:province":"Essex",
    "wof:name":"Presentquote Ltd",
    "wof:placetype":"venue"
},
  "geometry": {"coordinates":[0.159365,51.867764],"type":"Point"}
}