{
  "type": "Feature",
  "properties": {
    "iso:country":"GB",
    "sg:address":"Soldridge House, Soldridge Road, Medstead",
    "sg:city":"Alton",
    "sg:classifiers":[
        {
            "category":"Organizations",
            "subcategory":"Community Association",
            "type":"Services"
        }
    ],
    "sg:phone":"+44 1420 562811",
    "sg:postcode":"GU34 5JF",
    "sg:province":"Hampshire",
    "sg:tags":[
        "relation",
        "public"
    ],
    "wof:name":"John Lewis Press & Public Relations",
    "wof:placetype":"venue"
},
  "geometry": {"coordinates":[-1.068466,51.112793],"type":"Point"}
}