{
  "type": "Feature",
  "properties": {
    "addr:full":"308 Manchester Road, Blackrod Bolton Lancashire BL6 5BB",
    "addr:housenumber":"308",
    "addr:postcode":"bl6 5bb",
    "addr:street":"Manchester Road",
    "iso:country":"GB",
    "sg:address":"308 Manchester Road, Blackrod",
    "sg:city":"Bolton",
    "sg:classifiers":[
        {
            "category":"Organizations",
            "subcategory":"Membership Organization",
            "type":"Services"
        }
    ],
    "sg:phone":"+44 1204 696330",
    "sg:postcode":"BL6 5BB",
    "sg:province":"Lancashire",
    "sg:tags":[
        "club",
        "social"
    ],
    "wof:name":"The Royal British Legion",
    "wof:placetype":"venue"
},
  "geometry": {"coordinates":[-2.5754818916,53.5888366699],"type":"Point"}
}