{
  "type": "Feature",
  "properties": {
    "addr:full":"191 Western Road Brighton East Sussex BN1 2BA",
    "addr:housenumber":"191",
    "addr:postcode":"bn1 2ba",
    "addr:street":"Western Road",
    "iso:country":"GB",
    "sg:address":"191 Western Road",
    "sg:city":"Brighton",
    "sg:classifiers":[
        {
            "category":"Shopping",
            "subcategory":"Department Store",
            "type":"Retail Goods"
        }
    ],
    "sg:phone":"+44 1273 205211",
    "sg:postcode":"BN1 2BA",
    "sg:province":"East Sussex",
    "wof:name":"Primark Stores Ltd.",
    "wof:placetype":"venue"
},
  "geometry": {"coordinates":[-0.144983,50.823742],"type":"Point"}
}