{
  "type": "Feature",
  "properties": {
    "iso:country":"GB",
    "sg:address":"Unit 11 Abercrombie Rd, Britonwood Trad, Knowsley",
    "sg:city":"Liverpool",
    "sg:classifiers":[
        {
            "category":"Retail",
            "subcategory":"Auto Repair",
            "type":"Services"
        }
    ],
    "sg:postcode":"L33 7YN",
    "sg:province":"Lancashire",
    "sg:tags":[
        "bodybuilder",
        "repairer"
    ],
    "wof:name":"Wright,Christopher,",
    "wof:placetype":"venue"
},
  "geometry": {"coordinates":[-2.8606090546,53.4704399109],"type":"Point"}
}