{
  "type": "Feature",
  "properties": {
    "iso:country":"GB",
    "sg:address":"Seafield House, 37 Castle Street",
    "sg:city":"Banff",
    "sg:classifiers":[
        {
            "category":"Government",
            "subcategory":"Office",
            "type":"Public Place"
        }
    ],
    "sg:phone":"+44 1261 812001",
    "sg:postcode":"AB45 1FQ",
    "sg:province":"Aberdeenshire",
    "sg:tags":[
        "local"
    ],
    "wof:name":"ABERDEENSHIRE COUNCIL",
    "wof:placetype":"venue"
},
  "geometry": {"coordinates":[-2.523639,57.666763],"type":"Point"}
}