{
  "type": "Feature",
  "properties": {
    "addr:full":"45 Dovecot Street Stockton-on-tees Durham TS18 1LJ",
    "addr:housenumber":"45",
    "addr:postcode":"ts18 1lj",
    "addr:street":"Dovecot Street",
    "iso:country":"GB",
    "sg:address":"45 Dovecot Street",
    "sg:city":"Stockton-on-tees",
    "sg:classifiers":[
        {
            "category":"Home & Garden",
            "subcategory":"Carpets & Floor Coverings",
            "type":"Retail Goods"
        }
    ],
    "sg:phone":"+44 1642 676300",
    "sg:postcode":"TS18 1LJ",
    "sg:province":"Durham",
    "sg:tags":[
        "carpets",
        "rug",
        "matting"
    ],
    "wof:name":"Leslie Fisher & Co. (Stockton) Ltd.",
    "wof:placetype":"venue"
},
  "geometry": {"coordinates":[-1.3162510395,54.5641708374],"type":"Point"}
}