{
  "type": "Feature",
  "properties": {
    "iso:country":"GB",
    "sg:address":"22 Savay Lane, Denham Grn, Denham",
    "sg:city":"Uxbridge",
    "sg:classifiers":[
        {
            "category":"Building & Trades",
            "subcategory":"Cleaning & Sanitation",
            "type":"Services"
        }
    ],
    "sg:phone":"+44 1895 833620",
    "sg:postcode":"UB9 5NH",
    "sg:province":"Buckinghamshire",
    "sg:tags":[
        "commercial"
    ],
    "wof:name":"Millennium Denham Ltd.",
    "wof:placetype":"venue"
},
  "geometry": {"coordinates":[-0.494831,51.580936],"type":"Point"}
}