{
  "type": "Feature",
  "properties": {
    "addr:full":"The Studio, 42 Beverley Road, Blacko Nelson Lancashire BB9 6LX",
    "addr:housenumber":"42",
    "addr:postcode":"bb9 6lx",
    "addr:street":"Beverley Road",
    "iso:country":"GB",
    "sg:address":"The Studio, 42 Beverley Road, Blacko",
    "sg:city":"Nelson",
    "sg:classifiers":[
        {
            "category":"Professional",
            "subcategory":"Advertising",
            "type":"Services"
        }
    ],
    "sg:phone":"+44 1282 617372",
    "sg:postcode":"BB9 6LX",
    "sg:province":"Lancashire",
    "sg:tags":[
        "agency"
    ],
    "wof:name":"Allen Jameson & Peel Ltd.",
    "wof:placetype":"venue"
},
  "geometry": {"coordinates":[-2.214138031,53.8668251038],"type":"Point"}
}