{
  "type": "Feature",
  "properties": {
    "addr:full":"Broadmoor Road Cinderford Gloucestershire GL14 2YL",
    "addr:postcode":"gl14 2yl",
    "addr:street":"Broadmoor Road",
    "iso:country":"GB",
    "sg:address":"Broadmoor Road",
    "sg:city":"Cinderford",
    "sg:classifiers":[
        {
            "category":"Personal",
            "type":"Services"
        }
    ],
    "sg:phone":"+44 1594 827333",
    "sg:postcode":"GL14 2YL",
    "sg:province":"Gloucestershire",
    "sg:tags":[
        "delivery"
    ],
    "wof:name":"Blue Band Express Services Ltd.",
    "wof:placetype":"venue"
},
  "geometry": {"coordinates":[-2.499834,51.825214],"type":"Point"}
}