{
  "type": "Feature",
  "properties": {
    "addr:full":"Shepherds Lane Bracknell Berkshire RG12 2BT",
    "addr:postcode":"rg12 2bt",
    "addr:street":"Shepherds Lane",
    "iso:country":"GB",
    "sg:address":"Shepherds Lane",
    "sg:city":"Bracknell",
    "sg:classifiers":[
        {
            "category":"Bars & Pubs",
            "type":"Food & Drink"
        }
    ],
    "sg:phone":"+44 1344 484711",
    "sg:postcode":"RG12 2BT",
    "sg:province":"Berkshire",
    "sg:tags":[
        "pubs",
        "inn"
    ],
    "wof:name":"Prince of Wales",
    "wof:placetype":"venue"
},
  "geometry": {"coordinates":[-0.7460290194,51.4212036133],"type":"Point"}
}