{
  "type": "Feature",
  "properties": {
    "addr:full":"20 St. Simons Close, Offerton Stockport Cheshire SK2 5AF",
    "addr:housenumber":"20",
    "addr:postcode":"sk2 5af",
    "addr:street":"St. Simons Close",
    "iso:country":"GB",
    "sg:address":"20 St. Simons Close, Offerton",
    "sg:city":"Stockport",
    "sg:classifiers":[
        {
            "category":"Building & Trades",
            "subcategory":"Plumbing",
            "type":"Services"
        }
    ],
    "sg:phone":"+44 161 480 8517",
    "sg:postcode":"SK2 5AF",
    "sg:province":"Cheshire",
    "sg:tags":[
        "heating"
    ],
    "wof:name":"H Harnett",
    "wof:placetype":"venue"
},
  "geometry": {"coordinates":[-2.1341199875,53.4041023254],"type":"Point"}
}