{
  "type": "Feature",
  "properties": {
    "iso:country":"GB",
    "sg:address":"Unit 4, Parker Street, Piccadilly Plaza",
    "sg:city":"Manchester",
    "sg:classifiers":[
        {
            "category":"Food & Beverages",
            "subcategory":"Meat & Fish",
            "type":"Retail Goods"
        },
        {
            "category":"Food & Beverages",
            "subcategory":"Groceries & Convenience Stores",
            "type":"Retail Goods"
        }
    ],
    "sg:phone":"+44 161 236 0298",
    "sg:postcode":"M1 4AJ",
    "sg:province":"Greater Manchester",
    "sg:tags":[
        "shop",
        "chip"
    ],
    "wof:name":"The Station Chippy",
    "wof:placetype":"venue"
},
  "geometry": {"coordinates":[-2.238591,53.48082],"type":"Point"}
}