{
  "type": "Feature",
  "properties": {
    "addr:full":"4 Links Dr Borehamwood Hertfordshire WD6 3PS",
    "addr:housenumber":"4",
    "addr:postcode":"wd6 3ps",
    "addr:street":"Links Dr",
    "iso:country":"GB",
    "sg:address":"4 Links Dr",
    "sg:city":"Borehamwood",
    "sg:classifiers":[
        {
            "category":"Banks & Credit Unions",
            "subcategory":"Investment Brokerage",
            "type":"Services"
        }
    ],
    "sg:postcode":"WD6 3PS",
    "sg:province":"Hertfordshire",
    "sg:tags":[
        "moneylender"
    ],
    "wof:name":"Watchtower Investments Ltd",
    "wof:placetype":"venue"
},
  "geometry": {"coordinates":[-0.284295,51.65255],"type":"Point"}
}