{
  "type": "Feature",
  "properties": {
    "addr:full":"41 Ashcroft Road Cirencester Gloucestershire GL7 1QZ",
    "addr:housenumber":"41",
    "addr:postcode":"gl7 1qz",
    "addr:street":"Ashcroft Road",
    "iso:country":"GB",
    "sg:address":"41 Ashcroft Road",
    "sg:city":"Cirencester",
    "sg:classifiers":[
        {
            "category":"Professional",
            "subcategory":"Computer Services",
            "type":"Services"
        }
    ],
    "sg:postcode":"GL7 1QZ",
    "sg:province":"Gloucestershire",
    "sg:tags":[
        "system",
        "software"
    ],
    "wof:name":"Beaver Programming Ltd.",
    "wof:placetype":"venue"
},
  "geometry": {"coordinates":[-1.9698979855,51.7142333984],"type":"Point"}
}