{
  "type": "Feature",
  "properties": {
    "iso:country":"GB",
    "sg:address":"41 Huddersfield Road, Newhey",
    "sg:city":"Rochdale",
    "sg:classifiers":[
        {
            "category":"Bars & Pubs",
            "type":"Food & Drink"
        }
    ],
    "sg:phone":"+44 1706 847900",
    "sg:postcode":"OL16 3QZ",
    "sg:province":"Lancashire",
    "sg:tags":[
        "pubs",
        "inn"
    ],
    "wof:name":"The Lower Bird in Hand",
    "wof:placetype":"venue"
},
  "geometry": {"coordinates":[-2.0952839851,53.6014060974],"type":"Point"}
}