{
  "type": "Feature",
  "properties": {
    "iso:country":"GB",
    "sg:address":"66 Market Place",
    "sg:city":"Warwick",
    "sg:classifiers":[
        {
            "category":"Cafe",
            "type":"Food & Drink"
        }
    ],
    "sg:postcode":"CV34 4SD",
    "sg:province":"Warwickshire",
    "sg:tags":[
        "tea",
        "room"
    ],
    "wof:name":"Wylies Cafe",
    "wof:placetype":"venue"
},
  "geometry": {"coordinates":[-1.5902899504,52.2815170288],"type":"Point"}
}