{
  "type": "Feature",
  "properties": {
    "iso:country":"GB",
    "sg:address":"Prospect Ho, 191-199 London Rd, Isleworth",
    "sg:city":"Twickenham",
    "sg:classifiers":[
        {
            "category":"Real Estate",
            "subcategory":"Architect",
            "type":"Services"
        }
    ],
    "sg:postcode":"TW7 5BQ",
    "sg:province":"Greater London",
    "wof:name":"Arkitus",
    "wof:placetype":"venue"
},
  "geometry": {"coordinates":[-0.32003,51.479622],"type":"Point"}
}