{
  "type": "Feature",
  "properties": {
    "addr:full":"5 Cherry Street Warwick Warwickshire CV34 4LR",
    "addr:housenumber":"5",
    "addr:postcode":"cv34 4lr",
    "addr:street":"Cherry Street",
    "iso:country":"GB",
    "sg:address":"5 Cherry Street",
    "sg:city":"Warwick",
    "sg:classifiers":[
        {
            "category":"Autos & Motor Vehicles",
            "subcategory":"Auto Supplies",
            "type":"Retail Goods"
        }
    ],
    "sg:phone":"+44 1926 407441",
    "sg:postcode":"CV34 4LR",
    "sg:province":"Warwickshire",
    "sg:tags":[
        "tyre"
    ],
    "wof:name":"Tyreman Ltd.",
    "wof:placetype":"venue"
},
  "geometry": {"coordinates":[-1.578367,52.284813],"type":"Point"}
}