{
  "type": "Feature",
  "properties": {
    "addr:full":"Unit 47 Cuthbert Court, Bede Industrial Estate Jarrow Tyne and Wear NE32 3HG",
    "addr:housenumber":"unit 47",
    "addr:postcode":"ne32 3hg",
    "addr:street":"Cuthbert Court;Industrial Estate",
    "iso:country":"GB",
    "sg:address":"Unit 47 Cuthbert Court, Bede Industrial Estate",
    "sg:city":"Jarrow",
    "sg:classifiers":[
        {
            "category":"Building & Trades",
            "subcategory":"Construction",
            "type":"Services"
        }
    ],
    "sg:phone":"+44 191 483 2299",
    "sg:postcode":"NE32 3HG",
    "sg:province":"Tyne and Wear",
    "sg:tags":[
        "resurfacing",
        "laying",
        "flooring",
        "floor"
    ],
    "wof:name":"Durastic Ltd.",
    "wof:placetype":"venue"
},
  "geometry": {"coordinates":[-1.4680999517,54.9769172668],"type":"Point"}
}