{
  "type": "Feature",
  "properties": {
    "iso:country":"GB",
    "sg:address":"78 Dyer Street",
    "sg:city":"Cirencester",
    "sg:classifiers":[
        {
            "category":"Banks & Credit Unions",
            "subcategory":"Bank",
            "type":"Services"
        }
    ],
    "sg:phone":"+44 1285 659010",
    "sg:postcode":"GL7 2PF",
    "sg:province":"Gloucestershire",
    "sg:tags":[
        "broker",
        "mortgage"
    ],
    "wof:name":"A K Wenban",
    "wof:placetype":"venue"
},
  "geometry": {"coordinates":[-1.962942,51.715977],"type":"Point"}
}