{
  "type": "Feature",
  "properties": {
    "addr:full":"116 Chapel Road Worthing West Sussex BN11 1BY",
    "addr:housenumber":"116",
    "addr:postcode":"bn11 1by",
    "addr:street":"Chapel Road",
    "iso:country":"GB",
    "sg:address":"116 Chapel Road",
    "sg:city":"Worthing",
    "sg:classifiers":[
        {
            "category":"Professional",
            "subcategory":"Computer Services",
            "type":"Services"
        }
    ],
    "sg:phone":"+44 1903 217000",
    "sg:postcode":"BN11 1BY",
    "sg:province":"West Sussex",
    "sg:tags":[
        "system",
        "software"
    ],
    "wof:name":"Zacs Computer Services",
    "wof:placetype":"venue"
},
  "geometry": {"coordinates":[-0.372397989,50.8169670105],"type":"Point"}
}