{
  "type": "Feature",
  "properties": {
    "addr:full":"639 Galleywood Road Chelmsford Essex CM2 8BT",
    "addr:housenumber":"639",
    "addr:postcode":"cm2 8bt",
    "addr:street":"Galleywood Road",
    "iso:country":"GB",
    "sg:address":"639 Galleywood Road",
    "sg:city":"Chelmsford",
    "sg:classifiers":[
        {
            "category":"Wholesale",
            "subcategory":"Computers",
            "type":"Manufacturing & Wholesale Goods"
        },
        {
            "category":"Utilities",
            "type":"Services"
        }
    ],
    "sg:phone":"+44 1245 346985",
    "sg:postcode":"CM2 8BT",
    "sg:province":"Essex",
    "sg:tags":[
        "supplier",
        "consumables",
        "internet"
    ],
    "wof:name":"Bishop Consultancy",
    "wof:placetype":"venue"
},
  "geometry": {"coordinates":[0.4639529884,51.707660675],"type":"Point"}
}