{
  "type": "Feature",
  "properties": {
    "addr:full":"The Bridge Ho, Mill La Sheffield Derbyshire S18 6XL",
    "addr:postcode":"s18 6xl",
    "addr:street":"La Sheffield",
    "iso:country":"GB",
    "sg:address":"The Bridge Ho, Mill La",
    "sg:city":"Sheffield",
    "sg:classifiers":[
        {
            "category":"Professional",
            "type":"Services"
        }
    ],
    "sg:phone":"+44 1246 291511",
    "sg:postcode":"S18 6XL",
    "sg:province":"Derbyshire",
    "sg:tags":[
        "shopfitters"
    ],
    "wof:name":"Icarus Design",
    "wof:placetype":"venue"
},
  "geometry": {"coordinates":[-1.4645400047,53.3831100464],"type":"Point"}
}