{
  "type": "Feature",
  "properties": {
    "addr:full":"24 Victoria St Shildon Durham DL4 1PE",
    "addr:housenumber":"24",
    "addr:postcode":"dl4 1pe",
    "addr:street":"Victoria St",
    "iso:country":"GB",
    "sg:address":"24 Victoria St",
    "sg:city":"Shildon",
    "sg:classifiers":[
        {
            "category":"Shopping",
            "subcategory":"Florist",
            "type":"Retail Goods"
        }
    ],
    "sg:phone":"+44 1383 772474",
    "sg:postcode":"DL4 1PE",
    "sg:province":"Durham",
    "wof:name":"Forget Me Not Designer Floristry Service",
    "wof:placetype":"venue"
},
  "geometry": {"coordinates":[-1.642269,54.626358],"type":"Point"}
}