{
  "type": "Feature",
  "properties": {
    "iso:country":"GB",
    "sg:address":"Hawthorn Drive, Briar Bank Park, Wilstead",
    "sg:city":"Bedford",
    "sg:classifiers":[
        {
            "category":"Organizations",
            "subcategory":"Membership Organization",
            "type":"Services"
        }
    ],
    "sg:phone":"+44 1234 740236",
    "sg:postcode":"MK45 3ES",
    "sg:province":"Bedfordshire",
    "sg:tags":[
        "club"
    ],
    "wof:name":"Briar Bank Park",
    "wof:placetype":"venue"
},
  "geometry": {"coordinates":[-0.448657,52.075359],"type":"Point"}
}