{
  "type": "Feature",
  "properties": {
    "addr:full":"11 Museum St Ipswich Suffolk IP1 1HH",
    "addr:housenumber":"11",
    "addr:postcode":"ip1 1hh",
    "addr:street":"Museum St",
    "iso:country":"GB",
    "sg:address":"11 Museum St",
    "sg:city":"Ipswich",
    "sg:classifiers":[
        {
            "category":"Real Estate",
            "subcategory":"Surveying",
            "type":"Services"
        }
    ],
    "sg:phone":"+44 1473 214841",
    "sg:postcode":"IP1 1HH",
    "sg:province":"Suffolk",
    "sg:tags":[
        "surveyor",
        "valuer"
    ],
    "wof:name":"Strutt And Parker",
    "wof:placetype":"venue"
},
  "geometry": {"coordinates":[1.1506309509,52.0576858521],"type":"Point"}
}