{
  "type": "Feature",
  "properties": {
    "addr:full":"227a Alfreton Rd Alfreton Derbyshire DE55 5JH",
    "addr:housenumber":"227a",
    "addr:postcode":"de55 5jh",
    "addr:street":"Alfreton Rd",
    "iso:country":"GB",
    "sg:address":"227a Alfreton Rd",
    "sg:city":"Alfreton",
    "sg:classifiers":[
        {
            "category":"Building & Trades",
            "subcategory":"Plumbing",
            "type":"Services"
        }
    ],
    "sg:postcode":"DE55 5JH",
    "sg:province":"Derbyshire",
    "sg:tags":[
        "heating"
    ],
    "wof:name":"Grainger,P,",
    "wof:placetype":"venue"
},
  "geometry": {"coordinates":[-1.3541510105,53.1208953857],"type":"Point"}
}