{
  "type": "Feature",
  "properties": {
    "addr:full":"58 St Helens Road Swansea Neath Port Talbot SA1 4BE",
    "addr:housenumber":"58",
    "addr:postcode":"sa1 4be",
    "addr:street":"St Helens Road",
    "iso:country":"GB",
    "sg:address":"58 St Helens Road",
    "sg:city":"Swansea",
    "sg:classifiers":[
        {
            "category":"Professional",
            "subcategory":"Art Services",
            "type":"Services"
        }
    ],
    "sg:postcode":"SA1 4BE",
    "sg:province":"Neath Port Talbot",
    "sg:tags":[
        "framing"
    ],
    "wof:name":"The Craftsman Picture Framing",
    "wof:placetype":"venue"
},
  "geometry": {"coordinates":[-3.9618990421,51.6143951416],"type":"Point"}
}