{
  "type": "Feature",
  "properties": {
    "addr:full":"46 High St Bridgwater Somerset TA6 3BL",
    "addr:housenumber":"46",
    "addr:postcode":"ta6 3bl",
    "addr:street":"High St",
    "iso:country":"GB",
    "sg:address":"46 High St",
    "sg:city":"Bridgwater",
    "sg:classifiers":[
        {
            "category":"Cafe",
            "type":"Food & Drink"
        }
    ],
    "sg:phone":"+44 1278 446616",
    "sg:postcode":"TA6 3BL",
    "sg:province":"Somerset",
    "sg:tags":[
        "tea",
        "room"
    ],
    "wof:name":"Chandos Restaurant",
    "wof:placetype":"venue"
},
  "geometry": {"coordinates":[-3.006280899,51.1279792786],"type":"Point"}
}