{
  "type": "Feature",
  "properties": {
    "addr:full":"96 Sandpit Lane St Albans Hertfordshire AL4 0BX",
    "addr:housenumber":"96",
    "addr:postcode":"al4 0bx",
    "addr:street":"Sandpit Lane",
    "iso:country":"GB",
    "sg:address":"96 Sandpit Lane",
    "sg:city":"St Albans",
    "sg:classifiers":[
        {
            "category":"Real Estate",
            "subcategory":"Surveying",
            "type":"Services"
        }
    ],
    "sg:phone":"+44 1727 839900",
    "sg:postcode":"AL4 0BX",
    "sg:province":"Hertfordshire",
    "sg:tags":[
        "building",
        "surveyor",
        "valuer"
    ],
    "wof:name":"C G Bone Associates",
    "wof:placetype":"venue"
},
  "geometry": {"coordinates":[-0.3014569879,51.7605247498],"type":"Point"}
}