{
  "type": "Feature",
  "properties": {
    "iso:country":"GB",
    "sg:address":"30-31 Parkway Centre",
    "sg:city":"Middlesbrough",
    "sg:classifiers":[
        {
            "category":"Shopping",
            "subcategory":"Baby Store",
            "type":"Retail Goods"
        }
    ],
    "sg:postcode":"TS8 0TJ",
    "sg:province":"North Yorkshire",
    "sg:tags":[
        "babywear",
        "childrens"
    ],
    "wof:name":"Beal,Paul,",
    "wof:placetype":"venue"
},
  "geometry": {"coordinates":[-1.214304,54.523476],"type":"Point"}
}