{
  "type": "Feature",
  "properties": {
    "addr:full":"Cromar Ho, 9 Broad St Wokingham Berkshire RG40 1AU",
    "addr:housenumber":"9",
    "addr:postcode":"rg40 1au",
    "addr:street":"Broad St",
    "iso:country":"GB",
    "sg:address":"Cromar Ho, 9 Broad St",
    "sg:city":"Wokingham",
    "sg:classifiers":[
        {
            "category":"Banks & Credit Unions",
            "subcategory":"Financial Services",
            "type":"Services"
        }
    ],
    "sg:postcode":"RG40 1AU",
    "sg:province":"Berkshire",
    "sg:tags":[
        "consultant"
    ],
    "wof:name":"Royscot Trust Plc",
    "wof:placetype":"venue"
},
  "geometry": {"coordinates":[-0.834594,51.410801],"type":"Point"}
}