{
  "type": "Feature",
  "properties": {
    "addr:full":"Llys Llewelyn Trefriw Conwy LL27 0JH",
    "addr:postcode":"ll27 0jh",
    "addr:street":"Llys",
    "iso:country":"GB",
    "sg:address":"Llys Llewelyn",
    "sg:city":"Trefriw",
    "sg:classifiers":[
        {
            "category":"Travel",
            "subcategory":"Hotels & Motels",
            "type":"Entertainment"
        }
    ],
    "sg:phone":"+44 1492 640625",
    "sg:postcode":"LL27 0JH",
    "sg:province":"Conwy",
    "sg:tags":[
        "house",
        "guest"
    ],
    "wof:name":"Llys Llewelyn Guest House",
    "wof:placetype":"venue"
},
  "geometry": {"coordinates":[-3.824586,53.151676],"type":"Point"}
}