{
  "type": "Feature",
  "properties": {
    "iso:country":"GB",
    "sg:address":"39 Penny Street",
    "sg:city":"Blackburn",
    "sg:classifiers":[
        {
            "category":"Fast Food",
            "type":"Food & Drink"
        }
    ],
    "sg:postcode":"BB1 6HQ",
    "sg:province":"Lancashire",
    "sg:tags":[
        "away",
        "take"
    ],
    "wof:name":"Jolly Rooster",
    "wof:placetype":"venue"
},
  "geometry": {"coordinates":[-2.479121,53.749977],"type":"Point"}
}