{
  "type": "Feature",
  "properties": {
    "addr:full":"39 Penny Street Blackburn Lancashire BB1 6HQ",
    "addr:housenumber":"39",
    "addr:postcode":"bb1 6hq",
    "addr:street":"Penny Street",
    "iso:country":"GB",
    "sg:address":"39 Penny Street",
    "sg:city":"Blackburn",
    "sg:classifiers":[
        {
            "category":"Fast Food",
            "type":"Food & Drink"
        }
    ],
    "sg:postcode":"BB1 6HQ",
    "sg:province":"Lancashire",
    "sg:tags":[
        "away",
        "take"
    ],
    "wof:name":"Jolly Rooster",
    "wof:placetype":"venue"
},
  "geometry": {"coordinates":[-2.479121,53.749977],"type":"Point"}
}