{
  "type": "Feature",
  "properties": {
    "iso:country":"GB",
    "sg:address":"510 Hertford Rd",
    "sg:city":"Enfield",
    "sg:classifiers":[
        {
            "category":"Bars & Pubs",
            "type":"Food & Drink"
        }
    ],
    "sg:phone":"+44 20 8804 1737",
    "sg:postcode":"EN3 5SS",
    "sg:province":"Greater London",
    "sg:tags":[
        "pubs",
        "inn"
    ],
    "wof:name":"Texas Cantina",
    "wof:placetype":"venue"
},
  "geometry": {"coordinates":[-0.043236,51.666508],"type":"Point"}
}