{
  "type": "Feature",
  "properties": {
    "addr:full":"17 Market Street Wymondham Norfolk NR18 0AJ",
    "addr:housenumber":"17",
    "addr:postcode":"nr18 0aj",
    "addr:street":"Market Street",
    "iso:country":"GB",
    "sg:address":"17 Market Street",
    "sg:city":"Wymondham",
    "sg:classifiers":[
        {
            "category":"Food & Beverages",
            "subcategory":"Specialty",
            "type":"Retail Goods"
        }
    ],
    "sg:phone":"+44 1953 603738",
    "sg:postcode":"NR18 0AJ",
    "sg:province":"Norfolk",
    "sg:tags":[
        "product",
        "health"
    ],
    "wof:name":"Wymondham Health Foods",
    "wof:placetype":"venue"
},
  "geometry": {"coordinates":[1.1116709709,52.5706520081],"type":"Point"}
}