{
  "type": "Feature",
  "properties": {
    "addr:full":"St. Rochs Secondary School, 40 Royston Rd Glasgow East Dunbartonshire G21 2NF",
    "addr:housenumber":"40",
    "addr:postcode":"g21 2nf",
    "addr:street":"Royston Rd",
    "iso:country":"GB",
    "sg:address":"St. Rochs Secondary School, 40 Royston Rd",
    "sg:city":"Glasgow",
    "sg:classifiers":[
        {
            "category":"Social Services",
            "type":"Services"
        }
    ],
    "sg:phone":"+44 141 552 0927",
    "sg:postcode":"G21 2NF",
    "sg:province":"East Dunbartonshire",
    "sg:tags":[
        "educational"
    ],
    "wof:name":"School Attendance Department",
    "wof:placetype":"venue"
},
  "geometry": {"coordinates":[-4.23195,55.86911],"type":"Point"}
}