{
  "type": "Feature",
  "properties": {
    "addr:full":"P O Box 241 Margate Kent CT9 3GN",
    "addr:housenumber":"241",
    "addr:postcode":"ct9 3gn",
    "addr:street":"P O Box;Margate",
    "iso:country":"GB",
    "sg:address":"P O Box 241",
    "sg:city":"Margate",
    "sg:classifiers":[
        {
            "category":"Utilities",
            "type":"Services"
        }
    ],
    "sg:phone":"+44 7741 178968",
    "sg:postcode":"CT9 3GN",
    "sg:province":"Kent",
    "sg:tags":[
        "internet"
    ],
    "wof:name":"South East Web Services",
    "wof:placetype":"venue"
},
  "geometry": {"coordinates":[1.379247,51.386662],"type":"Point"}
}