{
  "type": "Feature",
  "properties": {
    "addr:full":"7 Market House Arcade, Fore Street Bodmin Cornwall PL31 2JA",
    "addr:housenumber":"7",
    "addr:postcode":"pl31 2ja",
    "addr:street":"Market House;Fore Street",
    "iso:country":"GB",
    "sg:address":"7 Market House Arcade, Fore Street",
    "sg:city":"Bodmin",
    "sg:classifiers":[
        {
            "category":"Food & Beverages",
            "subcategory":"Specialty",
            "type":"Retail Goods"
        }
    ],
    "sg:phone":"+44 1208 76625",
    "sg:postcode":"PL31 2JA",
    "sg:province":"Cornwall",
    "sg:tags":[
        "product",
        "health"
    ],
    "wof:name":"The Bran Tub",
    "wof:placetype":"venue"
},
  "geometry": {"coordinates":[-4.716369,50.471046],"type":"Point"}
}