{
  "type": "Feature",
  "properties": {
    "iso:country":"GB",
    "sg:address":"8 The Larun Beat",
    "sg:city":"Yarm",
    "sg:classifiers":[
        {
            "category":"Building & Trades",
            "subcategory":"Plumbing",
            "type":"Services"
        }
    ],
    "sg:postcode":"TS15 9HW",
    "sg:province":"North Yorkshire",
    "sg:tags":[
        "heating"
    ],
    "wof:name":"John L Bullen",
    "wof:placetype":"venue"
},
  "geometry": {"coordinates":[-1.3526849747,54.5009155273],"type":"Point"}
}