{
  "type": "Feature",
  "properties": {
    "iso:country":"GB",
    "sg:address":"5 The Circle, Pontllanfraith",
    "sg:city":"Blackwood",
    "sg:classifiers":[
        {
            "category":"Fast Food",
            "type":"Food & Drink"
        }
    ],
    "sg:phone":"+44 1495 228085",
    "sg:postcode":"NP12 2NP",
    "sg:province":"Caerphilly",
    "sg:tags":[
        "away",
        "meal",
        "outlet",
        "take"
    ],
    "wof:name":"Jade Garden",
    "wof:placetype":"venue"
},
  "geometry": {"coordinates":[-3.191607,51.639278],"type":"Point"}
}