{
  "type": "Feature",
  "properties": {
    "addr:full":"Chynoweth Penhallick, Carn Brea Redruth Cornwall TR15 3YJ",
    "addr:postcode":"tr15 3yj",
    "iso:country":"GB",
    "sg:address":"Chynoweth Penhallick, Carn Brea",
    "sg:city":"Redruth",
    "sg:classifiers":[
        {
            "category":"Professional",
            "subcategory":"Computer Services",
            "type":"Services"
        }
    ],
    "sg:postcode":"TR15 3YJ",
    "sg:province":"Cornwall",
    "sg:tags":[
        "system",
        "software"
    ],
    "wof:name":"Soft-Ex Computers",
    "wof:placetype":"venue"
},
  "geometry": {"coordinates":[-5.2294340134,50.232509613],"type":"Point"}
}