{
  "type": "Feature",
  "properties": {
    "addr:full":"Leuchars St Andrews Fife KY16 0DU",
    "addr:postcode":"ky16 0du",
    "addr:street":"Leuchars St Andrews",
    "iso:country":"GB",
    "sg:address":"Leuchars",
    "sg:city":"St Andrews",
    "sg:classifiers":[
        {
            "category":"Bars & Pubs",
            "type":"Food & Drink"
        }
    ],
    "sg:phone":"+44 1334 839220",
    "sg:postcode":"KY16 0DU",
    "sg:province":"Fife",
    "sg:tags":[
        "pubs",
        "inn"
    ],
    "wof:name":"St. Michaels Inn",
    "wof:placetype":"venue"
},
  "geometry": {"coordinates":[-2.9048900604,56.3940391541],"type":"Point"}
}