{
  "type": "Feature",
  "properties": {
    "addr:full":"7 Broad Street Chesham Buckinghamshire HP5 3EA",
    "addr:housenumber":"7",
    "addr:postcode":"hp5 3ea",
    "addr:street":"Broad Street",
    "iso:country":"GB",
    "sg:address":"7 Broad Street",
    "sg:city":"Chesham",
    "sg:classifiers":[
        {
            "category":"Personal",
            "subcategory":"Beauty Salon",
            "type":"Services"
        }
    ],
    "sg:phone":"+44 1494 783427",
    "sg:postcode":"HP5 3EA",
    "sg:province":"Buckinghamshire",
    "sg:tags":[
        "unisex",
        "hairdresser"
    ],
    "wof:name":"Sam Sara",
    "wof:placetype":"venue"
},
  "geometry": {"coordinates":[-0.610832,51.708118],"type":"Point"}
}