{
  "type": "Feature",
  "properties": {
    "addr:full":"Old Post Office Cotts, Chapel Lane, Hargrave Chester Cheshire CH3 7RW",
    "addr:postcode":"ch3 7rw",
    "addr:street":"Chapel Lane",
    "iso:country":"GB",
    "sg:address":"Old Post Office Cotts, Chapel Lane, Hargrave",
    "sg:city":"Chester",
    "sg:classifiers":[
        {
            "category":"Wholesale",
            "subcategory":"Scrap",
            "type":"Manufacturing & Wholesale Goods"
        }
    ],
    "sg:phone":"+44 1829 781331",
    "sg:postcode":"CH3 7RW",
    "sg:province":"Cheshire",
    "sg:tags":[
        "waste",
        "metal"
    ],
    "wof:name":"Sidney C Smith",
    "wof:placetype":"venue"
},
  "geometry": {"coordinates":[-2.7734310627,53.1546859741],"type":"Point"}
}