{
  "type": "Feature",
  "properties": {
    "iso:country":"GB",
    "sg:address":"91 Avenue Road Extension",
    "sg:city":"Leicester",
    "sg:classifiers":[
        {
            "category":"Manufacturing",
            "subcategory":"Metals",
            "type":"Manufacturing & Wholesale Goods"
        }
    ],
    "sg:phone":"+44 116 270 1516",
    "sg:postcode":"LE2 3EQ",
    "sg:province":"Leicestershire",
    "sg:tags":[
        "work",
        "sheet"
    ],
    "wof:name":"Steelteq",
    "wof:placetype":"venue"
},
  "geometry": {"coordinates":[-1.121019,52.614014],"type":"Point"}
}