{
  "type": "Feature",
  "properties": {
    "addr:full":"The Fox And Goose Inn, Parracombe Barnstaple Devon EX31 4PE",
    "addr:postcode":"ex31 4pe",
    "iso:country":"GB",
    "sg:address":"The Fox And Goose Inn, Parracombe",
    "sg:city":"Barnstaple",
    "sg:classifiers":[
        {
            "category":"Professional",
            "subcategory":"Business Services",
            "type":"Services"
        }
    ],
    "sg:phone":"+44 1598 763267",
    "sg:postcode":"EX31 4PE",
    "sg:province":"Devon",
    "sg:tags":[
        "publishers'"
    ],
    "wof:name":"Castle Links Ltd.",
    "wof:placetype":"venue"
},
  "geometry": {"coordinates":[-3.9059948921,51.1877632141],"type":"Point"}
}