{
  "type": "Feature",
  "properties": {
    "addr:full":"Wray Common Rd Reigate Surrey RH2 0ND",
    "addr:postcode":"rh2 0nd",
    "addr:street":"Wray Common Rd",
    "iso:country":"GB",
    "sg:address":"Wray Common Rd",
    "sg:city":"Reigate",
    "sg:classifiers":[
        {
            "category":"Health Services",
            "subcategory":"Nursing And Care Facility",
            "type":"Services"
        }
    ],
    "sg:phone":"+44 1737 240563",
    "sg:postcode":"RH2 0ND",
    "sg:province":"Surrey",
    "sg:tags":[
        "home"
    ],
    "wof:name":"Wray Common Private Nursing Home",
    "wof:placetype":"venue"
},
  "geometry": {"coordinates":[-0.1892289966,51.2432746887],"type":"Point"}
}