{
  "type": "Feature",
  "properties": {
    "addr:full":"Clive Dennis Court, Hythe Road, Willesborough Ashford Kent TN24 0LX",
    "addr:postcode":"tn24 0lx",
    "addr:street":"Court Hythe Road",
    "iso:country":"GB",
    "sg:address":"Clive Dennis Court, Hythe Road, Willesborough",
    "sg:city":"Ashford",
    "sg:classifiers":[
        {
            "category":"Health Services",
            "subcategory":"Nursing And Care Facility",
            "type":"Services"
        }
    ],
    "sg:phone":"+44 1233 664085",
    "sg:postcode":"TN24 0LX",
    "sg:province":"Kent",
    "sg:tags":[
        "home"
    ],
    "wof:name":"Ashminster House",
    "wof:placetype":"venue"
},
  "geometry": {"coordinates":[0.890935,51.145409],"type":"Point"}
}