{
  "type": "Feature",
  "properties": {
    "addr:full":"Whitegate Northwich Cheshire CW8 2BA",
    "addr:postcode":"cw8 2ba",
    "addr:street":"Whitegate Northwich",
    "iso:country":"GB",
    "sg:address":"Whitegate",
    "sg:city":"Northwich",
    "sg:classifiers":[
        {
            "category":"Sports & Exercise",
            "subcategory":"Golf",
            "type":"Entertainment"
        }
    ],
    "sg:phone":"+44 1606 301291",
    "sg:postcode":"CW8 2BA",
    "sg:province":"Cheshire",
    "sg:tags":[
        "club",
        "course"
    ],
    "wof:name":"Vale Royal Abbey Golf Club",
    "wof:placetype":"venue"
},
  "geometry": {"coordinates":[-2.54376,53.2234],"type":"Point"}
}