{
  "type": "Feature",
  "properties": {
    "addr:full":"207 High Street Stoke-on-trent Staffordshire ST6 5EG",
    "addr:housenumber":"207",
    "addr:postcode":"st6 5eg",
    "addr:street":"High Street",
    "iso:country":"GB",
    "sg:address":"207 High Street",
    "sg:city":"Stoke-on-trent",
    "sg:classifiers":[
        {
            "category":"Home & Garden",
            "subcategory":"Hardware",
            "type":"Retail Goods"
        }
    ],
    "sg:phone":"+44 1782 837454",
    "sg:postcode":"ST6 5EG",
    "sg:province":"Staffordshire",
    "sg:tags":[
        "retailer",
        "diy"
    ],
    "wof:name":"Farrs",
    "wof:placetype":"venue"
},
  "geometry": {"coordinates":[-2.210654974,53.0606040955],"type":"Point"}
}