{
  "type": "Feature",
  "properties": {
    "addr:full":"Moor Lodge, Sugworth, Bradfield Sheffield South Yorkshire S6 6JA",
    "addr:postcode":"s6 6ja",
    "addr:street":"Sugworth",
    "iso:country":"GB",
    "sg:address":"Moor Lodge, Sugworth, Bradfield",
    "sg:city":"Sheffield",
    "sg:classifiers":[
        {
            "category":"Professional",
            "type":"Services"
        }
    ],
    "sg:phone":"+44 114 285 1900",
    "sg:postcode":"S6 6JA",
    "sg:province":"South Yorkshire",
    "sg:tags":[
        "caterer"
    ],
    "wof:name":"The Real Cake Co",
    "wof:placetype":"venue"
},
  "geometry": {"coordinates":[-1.5975040197,53.4282646179],"type":"Point"}
}