{
  "type": "Feature",
  "properties": {
    "iso:country":"GB",
    "sg:address":"36 Beaufort Road",
    "sg:city":"Kingston-upon-thames",
    "sg:classifiers":[
        {
            "category":"Social Services",
            "subcategory":"Retirement Home",
            "type":"Services"
        }
    ],
    "sg:phone":"+44 20 8549 6782",
    "sg:postcode":"KT1 2TQ",
    "sg:province":"Greater London",
    "sg:tags":[
        "residential",
        "care"
    ],
    "wof:name":"Hollymead Lodge",
    "wof:placetype":"venue"
},
  "geometry": {"coordinates":[-0.3006489873,51.4008255005],"type":"Point"}
}