{
  "type": "Feature",
  "properties": {
    "addr:full":"383 Liverpool Road, Walmer Bridge Preston Lancashire PR4 5JS",
    "addr:housenumber":"383",
    "addr:postcode":"pr4 5js",
    "addr:street":"Liverpool Road",
    "iso:country":"GB",
    "sg:address":"383 Liverpool Road, Walmer Bridge",
    "sg:city":"Preston",
    "sg:classifiers":[
        {
            "category":"Building & Trades",
            "subcategory":"Construction",
            "type":"Services"
        }
    ],
    "sg:postcode":"PR4 5JS",
    "sg:province":"Lancashire",
    "sg:tags":[
        "builder"
    ],
    "wof:name":"Quality Contractors",
    "wof:placetype":"venue"
},
  "geometry": {"coordinates":[-2.7752590179,53.7314491272],"type":"Point"}
}