{
  "type": "Feature",
  "properties": {
    "iso:country":"GB",
    "sg:address":"1b The Parade, Buckingham Road",
    "sg:city":"Edgware",
    "sg:classifiers":[
        {
            "category":"Taxi",
            "type":"Transportation"
        }
    ],
    "sg:phone":"+44 20 8952 4484",
    "sg:postcode":"HA8 6LY",
    "sg:province":"Greater London",
    "sg:tags":[
        "mini",
        "cab"
    ],
    "wof:name":"Beeline Car Travel",
    "wof:placetype":"venue"
},
  "geometry": {"coordinates":[-0.2824020088,51.6089248657],"type":"Point"}
}