{
  "type": "Feature",
  "properties": {
    "iso:country":"GB",
    "sg:address":"2 Maryland Court, Rainham",
    "sg:city":"Gillingham",
    "sg:classifiers":[
        {
            "category":"Transit Center",
            "subcategory":"Freight",
            "type":"Transportation"
        },
        {
            "category":"Shopping",
            "subcategory":"Computers & Home Electronics",
            "type":"Retail Goods"
        }
    ],
    "sg:phone":"+44 1634 389004",
    "sg:postcode":"ME8 8QY",
    "sg:province":"Kent",
    "sg:tags":[
        "hi-fi",
        "fi",
        "hi",
        "centre"
    ],
    "wof:name":"Progressive Audio",
    "wof:placetype":"venue"
},
  "geometry": {"coordinates":[0.602568984,51.3474197388],"type":"Point"}
}