{
  "type": "Feature",
  "properties": {
    "addr:full":"Nut Tree, Vole Road, Mark Highbridge Somerset TA9 4PD",
    "addr:postcode":"ta9 4pd",
    "addr:street":"Nut;Vole Road",
    "iso:country":"GB",
    "sg:address":"Nut Tree, Vole Road, Mark",
    "sg:city":"Highbridge",
    "sg:classifiers":[
        {
            "category":"Farming",
            "subcategory":"Livestock Farm",
            "type":"Manufacturing & Wholesale Goods"
        }
    ],
    "sg:postcode":"TA9 4PD",
    "sg:province":"Somerset",
    "sg:tags":[
        "others"
    ],
    "wof:name":"Robert E Carnell",
    "wof:placetype":"venue"
},
  "geometry": {"coordinates":[-2.892619,51.227337],"type":"Point"}
}