{
  "type": "Feature",
  "properties": {
    "iso:country":"GB",
    "sg:address":"383 Birmingham Road, Wylde Green",
    "sg:city":"Sutton Coldfield",
    "sg:classifiers":[
        {
            "category":"Retail",
            "subcategory":"Laundry & Dry Cleaning",
            "type":"Services"
        }
    ],
    "sg:phone":"+44 121 373 8052",
    "sg:postcode":"B72 1AT",
    "sg:province":"West Midlands",
    "sg:tags":[
        "launderette"
    ],
    "wof:name":"Dolly's",
    "wof:placetype":"venue"
},
  "geometry": {"coordinates":[-1.826461,52.536694],"type":"Point"}
}