{
  "type": "Feature",
  "properties": {
    "addr:full":"Care Of Allied Carpet, Denby Dale Road Wakefield West Yorkshire WF1 1RN",
    "addr:postcode":"wf1 1rn",
    "addr:street":"Denby Dale Road",
    "iso:country":"GB",
    "sg:address":"Care Of Allied Carpet, Denby Dale Road",
    "sg:city":"Wakefield",
    "sg:classifiers":[
        {
            "category":"Home & Garden",
            "subcategory":"Furniture",
            "type":"Retail Goods"
        }
    ],
    "sg:phone":"+44 1924 201578",
    "sg:postcode":"WF1 1RN",
    "sg:province":"West Yorkshire",
    "wof:name":"Sofa Co",
    "wof:placetype":"venue"
},
  "geometry": {"coordinates":[-1.4955400229,53.6780204773],"type":"Point"}
}