{
  "type": "Feature",
  "properties": {
    "addr:full":"St Michael & All Angels, High Street Lyndhurst Hampshire SO43 7BB",
    "addr:postcode":"so43 7bb",
    "addr:street":"High Street",
    "iso:country":"GB",
    "sg:address":"St Michael & All Angels, High Street",
    "sg:city":"Lyndhurst",
    "sg:classifiers":[
        {
            "category":"Education",
            "subcategory":"School",
            "type":"Public Place"
        }
    ],
    "sg:phone":"+44 23 8028 2244",
    "sg:postcode":"SO43 7BB",
    "sg:province":"Hampshire",
    "sg:tags":[
        "local",
        "authority"
    ],
    "wof:name":"St Michael & All Angels C Of E Aided Infant School",
    "wof:placetype":"venue"
},
  "geometry": {"coordinates":[-1.5762790442,50.8725852966],"type":"Point"}
}