{
  "type": "Feature",
  "properties": {
    "iso:country":"GB",
    "sg:address":"96 Tividale Road, Tividale",
    "sg:city":"Smethwick",
    "sg:classifiers":[
        {
            "category":"Shopping",
            "subcategory":"Department Store",
            "type":"Retail Goods"
        },
        {
            "category":"Food & Beverages",
            "subcategory":"Groceries & Convenience Stores",
            "type":"Retail Goods"
        }
    ],
    "sg:phone":"+44 121 520 7566",
    "sg:postcode":"B69 2LQ",
    "sg:province":"West Midlands",
    "wof:name":"Tivdale Food Store",
    "wof:placetype":"venue"
},
  "geometry": {"coordinates":[-2.058398962,52.5143508911],"type":"Point"}
}