{
  "type": "Feature",
  "properties": {
    "iso:country":"GB",
    "sg:address":"12 Moorfield Road",
    "sg:city":"Orpington",
    "sg:classifiers":[
        {
            "category":"Manufacturing",
            "subcategory":"Tools & Machinery",
            "type":"Manufacturing & Wholesale Goods"
        },
        {
            "category":"Insurance",
            "subcategory":"Insurance Agent",
            "type":"Services"
        }
    ],
    "sg:phone":"+44 1689 824471",
    "sg:postcode":"BR6 0HQ",
    "sg:province":"Kent",
    "sg:tags":[
        "society",
        "broker",
        "friendly"
    ],
    "wof:name":"Morrell Insurance Brokers",
    "wof:placetype":"venue"
},
  "geometry": {"coordinates":[0.102655001,51.3800315857],"type":"Point"}
}