{
  "type": "Feature",
  "properties": {
    "addr:full":"17 Brook Street Macclesfield Cheshire SK11 7AA",
    "addr:housenumber":"17",
    "addr:postcode":"sk11 7aa",
    "addr:street":"Brook Street",
    "iso:country":"GB",
    "sg:address":"17 Brook Street",
    "sg:city":"Macclesfield",
    "sg:classifiers":[
        {
            "category":"Building & Trades",
            "subcategory":"Construction",
            "type":"Services"
        }
    ],
    "sg:postcode":"SK11 7AA",
    "sg:province":"Cheshire",
    "sg:tags":[
        "joiner",
        "carpenter"
    ],
    "wof:name":"E Connor Joiner",
    "wof:placetype":"venue"
},
  "geometry": {"coordinates":[-2.1211349964,53.2565956116],"type":"Point"}
}