{
  "type": "Feature",
  "properties": {
    "iso:country":"GB",
    "sg:address":"32a Station Road",
    "sg:city":"Gerrards Cross",
    "sg:classifiers":[
        {
            "category":"Banks & Credit Unions",
            "subcategory":"Financial Services",
            "type":"Services"
        }
    ],
    "sg:phone":"+44 1753 886649",
    "sg:postcode":"SL9 8EL",
    "sg:province":"Buckinghamshire",
    "sg:tags":[
        "adviser",
        "independent"
    ],
    "wof:name":"REGENCY INVESTMENT SERVICES LTD",
    "wof:placetype":"venue"
},
  "geometry": {"coordinates":[-0.5501,51.587433],"type":"Point"}
}