{
  "type": "Feature",
  "properties": {
    "addr:full":"22 Nottingham Road, Lowdham Nottingham Nottinghamshire NG14 7AP",
    "addr:housenumber":"22",
    "addr:postcode":"ng14 7ap",
    "addr:street":"Nottingham Road",
    "iso:country":"GB",
    "sg:address":"22 Nottingham Road, Lowdham",
    "sg:city":"Nottingham",
    "sg:classifiers":[
        {
            "category":"Real Estate",
            "subcategory":"Developer",
            "type":"Services"
        },
        {
            "category":"Building & Trades",
            "subcategory":"Construction",
            "type":"Services"
        }
    ],
    "sg:phone":"+44 115 966 3672",
    "sg:postcode":"NG14 7AP",
    "sg:province":"Nottinghamshire",
    "sg:tags":[
        "residential",
        "builder",
        "property"
    ],
    "wof:name":"County Homeowner Ltd",
    "wof:placetype":"venue"
},
  "geometry": {"coordinates":[-1.005394,53.006336],"type":"Point"}
}