{
  "type": "Feature",
  "properties": {
    "addr:full":"12 Braintree Enterprise Centre, 46 Springwood Drive, 46 Springwood Drive Braintree Essex CM7 2YN",
    "addr:housenumber":"12;46;46",
    "addr:postcode":"cm7 2yn",
    "addr:street":"Braintree Enterprise;Springwood Drive;Springwood Drive",
    "iso:country":"GB",
    "sg:address":"12 Braintree Enterprise Centre, 46 Springwood Drive, 46 Springwood Drive",
    "sg:city":"Braintree",
    "sg:classifiers":[
        {
            "category":"Government",
            "subcategory":"Post Office",
            "type":"Public Place"
        }
    ],
    "sg:phone":"+44 1376 502702",
    "sg:postcode":"CM7 2YN",
    "sg:province":"Essex",
    "sg:tags":[
        "messenger",
        "courier"
    ],
    "wof:name":"Action Vans",
    "wof:placetype":"venue"
},
  "geometry": {"coordinates":[0.5532420278,51.8777580261],"type":"Point"}
}