{
  "type": "Feature",
  "properties": {
    "iso:country":"GB",
    "sg:address":"1b Summerland Rd",
    "sg:city":"Minehead",
    "sg:classifiers":[
        {
            "category":"Shopping",
            "type":"Retail Goods"
        }
    ],
    "sg:phone":"+44 1643 705066",
    "sg:postcode":"TA24 5BP",
    "sg:province":"Somerset",
    "sg:tags":[
        "part",
        "accessory"
    ],
    "wof:name":"Minehead Motor Parts",
    "wof:placetype":"venue"
},
  "geometry": {"coordinates":[-3.476753,51.20586],"type":"Point"}
}