{
  "type": "Feature",
  "properties": {
    "iso:country":"GB",
    "sg:address":"3 Bayview Road, Newton",
    "sg:city":"Porthcawl",
    "sg:classifiers":[
        {
            "category":"Building & Trades",
            "subcategory":"Construction",
            "type":"Services"
        }
    ],
    "sg:phone":"+44 1656 786047",
    "sg:postcode":"CF36 5NF",
    "sg:province":"Bridgend",
    "sg:tags":[
        "decorator",
        "painter"
    ],
    "wof:name":"Martin Pride Decorating Services",
    "wof:placetype":"venue"
},
  "geometry": {"coordinates":[-3.677954,51.479134],"type":"Point"}
}