{
  "type": "Feature",
  "properties": {
    "iso:country":"GB",
    "sg:address":"Bashley Road",
    "sg:city":"New Milton",
    "sg:classifiers":[
        {
            "category":"Community Center",
            "type":"Public Place"
        }
    ],
    "sg:phone":"+44 1425 612772",
    "sg:postcode":"BH25 5RY",
    "sg:province":"Hampshire",
    "sg:tags":[
        "nursery",
        "centre"
    ],
    "wof:name":"Northacre Nurseries",
    "wof:placetype":"venue"
},
  "geometry": {"coordinates":[-1.6579890251,50.7721977234],"type":"Point"}
}