{
  "type": "Feature",
  "properties": {
    "iso:country":"GB",
    "sg:address":"35 New Bdwy",
    "sg:city":"London",
    "sg:classifiers":[
        {
            "category":"Travel",
            "subcategory":"Travel Agent",
            "type":"Entertainment"
        }
    ],
    "sg:phone":"+44 20 8566 2770",
    "sg:postcode":"W5 5AH",
    "sg:province":"Greater London",
    "wof:name":"Ealing Travel Services Ltd.",
    "wof:placetype":"venue"
},
  "geometry": {"coordinates":[-0.306057,51.512871],"type":"Point"}
}