{
  "type": "Feature",
  "properties": {
    "iso:country":"GB",
    "sg:address":"40 Castle St",
    "sg:city":"Hertford",
    "sg:classifiers":[
        {
            "category":"Taxi",
            "type":"Transportation"
        }
    ],
    "sg:phone":"+44 1992 500100",
    "sg:postcode":"SG14 1HH",
    "sg:province":"Hertfordshire",
    "sg:tags":[
        "mini",
        "cab"
    ],
    "wof:name":"Lovesgroves Cabs",
    "wof:placetype":"venue"
},
  "geometry": {"coordinates":[-0.08036,51.794407],"type":"Point"}
}