{
  "type": "Feature",
  "properties": {
    "addr:full":"West Sleekburn Ind Est Bedlington Northumberland NE22 7LQ",
    "addr:postcode":"ne22 7lq",
    "addr:street":"West Sleekburn;Northumberland",
    "iso:country":"GB",
    "sg:address":"West Sleekburn Ind Est",
    "sg:city":"Bedlington",
    "sg:classifiers":[
        {
            "category":"Wholesale",
            "subcategory":"Scrap",
            "type":"Manufacturing & Wholesale Goods"
        }
    ],
    "sg:phone":"+44 1670 824050",
    "sg:postcode":"NE22 7LQ",
    "sg:province":"Northumberland",
    "sg:tags":[
        "car",
        "breaker",
        "dismantlers"
    ],
    "wof:name":"T & W Davison",
    "wof:placetype":"venue"
},
  "geometry": {"coordinates":[-1.562188983,55.1434249878],"type":"Point"}
}