{
  "type": "Feature",
  "properties": {
    "addr:full":"50 Hayes End Dr Hayes Greater London UB4 8HD",
    "addr:housenumber":"50",
    "addr:postcode":"ub4 8hd",
    "addr:street":"Hayes End Dr",
    "iso:country":"GB",
    "sg:address":"50 Hayes End Dr",
    "sg:city":"Hayes",
    "sg:classifiers":[
        {
            "category":"Building & Trades",
            "subcategory":"Construction",
            "type":"Services"
        }
    ],
    "sg:phone":"+44 20 8561 0673",
    "sg:postcode":"UB4 8HD",
    "sg:province":"Greater London",
    "sg:tags":[
        "builder"
    ],
    "wof:name":"Howell S J",
    "wof:placetype":"venue"
},
  "geometry": {"coordinates":[-0.434761,51.528286],"type":"Point"}
}