{
  "type": "Feature",
  "properties": {
    "addr:full":"Manchester Rd Sheffield South Yorkshire S10 5PL",
    "addr:postcode":"s10 5pl",
    "addr:street":"Manchester Rd",
    "iso:country":"GB",
    "sg:address":"Manchester Rd",
    "sg:city":"Sheffield",
    "sg:classifiers":[
        {
            "category":"Place Of Worship",
            "type":"Public Place"
        }
    ],
    "sg:phone":"+44 114 267 0006",
    "sg:postcode":"S10 5PL",
    "sg:province":"South Yorkshire",
    "wof:name":"St.Columba's Church",
    "wof:placetype":"venue"
},
  "geometry": {"coordinates":[-1.5232460499,53.3808403015],"type":"Point"}
}