{
  "type": "Feature",
  "properties": {
    "addr:full":"Quay West, Trafford Wharf Road, Wharfside Manchester Cheshire M17 1HH",
    "addr:postcode":"m17 1hh",
    "addr:street":"Quay West;Wharf Road",
    "iso:country":"GB",
    "sg:address":"Quay West, Trafford Wharf Road, Wharfside",
    "sg:city":"Manchester",
    "sg:classifiers":[
        {
            "category":"Insurance",
            "subcategory":"Insurance Agent",
            "type":"Services"
        }
    ],
    "sg:phone":"+44 161 877 8454",
    "sg:postcode":"M17 1HH",
    "sg:province":"Cheshire",
    "sg:tags":[
        "broker"
    ],
    "wof:name":"Rochester Kemp Holdings Ltd.",
    "wof:placetype":"venue"
},
  "geometry": {"coordinates":[-2.3008189201,53.4695510864],"type":"Point"}
}