{
  "type": "Feature",
  "properties": {
    "addr:full":"5 Isleworth Road Exeter Devon EX4 1QU",
    "addr:housenumber":"5",
    "addr:postcode":"ex4 1qu",
    "addr:street":"Isleworth Road",
    "iso:country":"GB",
    "sg:address":"5 Isleworth Road",
    "sg:city":"Exeter",
    "sg:classifiers":[
        {
            "category":"Building & Trades",
            "subcategory":"Construction",
            "type":"Services"
        }
    ],
    "sg:phone":"+44 1392 420946",
    "sg:postcode":"EX4 1QU",
    "sg:province":"Devon",
    "sg:tags":[
        "tiling",
        "contractor"
    ],
    "wof:name":"David Head",
    "wof:placetype":"venue"
},
  "geometry": {"coordinates":[-3.5497510433,50.7201728821],"type":"Point"}
}