{
  "type": "Feature",
  "properties": {
    "iso:country":"GB",
    "sg:address":"219 Railway Arches, Trussley Rd",
    "sg:city":"Hammersmith",
    "sg:classifiers":[
        {
            "category":"Home & Garden",
            "subcategory":"Hardware",
            "type":"Retail Goods"
        },
        {
            "category":"Shopping",
            "subcategory":"Photographic Equipment",
            "type":"Retail Goods"
        }
    ],
    "sg:phone":"+44 20 8748 0882",
    "sg:postcode":"W6 7PP",
    "sg:province":"Greater London",
    "sg:tags":[
        "part",
        "accessory",
        "supply"
    ],
    "wof:name":"Scooter Surgery",
    "wof:placetype":"venue"
},
  "geometry": {"coordinates":[-0.22634,51.498119],"type":"Point"}
}