{
  "type": "Feature",
  "properties": {
    "addr:full":"The Health Centre, Bacup Road, Rawtenstall Rossendale Lancashire BB4 7PL",
    "addr:postcode":"bb4 7pl",
    "addr:street":"Bacup Road",
    "iso:country":"GB",
    "sg:address":"The Health Centre, Bacup Road, Rawtenstall",
    "sg:city":"Rossendale",
    "sg:classifiers":[
        {
            "category":"Health Services",
            "subcategory":"Doctor",
            "type":"Services"
        }
    ],
    "sg:postcode":"BB4 7PL",
    "sg:province":"Lancashire",
    "sg:tags":[
        "practitioners"
    ],
    "wof:name":"J U D Bachh",
    "wof:placetype":"venue"
},
  "geometry": {"coordinates":[-2.279869,53.700371],"type":"Point"}
}