{
  "type": "Feature",
  "properties": {
    "addr:full":"109 Bernard St Southampton Hampshire SO14 3EA",
    "addr:housenumber":"109",
    "addr:postcode":"so14 3ea",
    "addr:street":"Bernard St",
    "iso:country":"GB",
    "sg:address":"109 Bernard St",
    "sg:city":"Southampton",
    "sg:classifiers":[
        {
            "category":"Shopping",
            "subcategory":"Florist",
            "type":"Retail Goods"
        }
    ],
    "sg:phone":"+44 23 8033 0682",
    "sg:postcode":"SO14 3EA",
    "sg:province":"Hampshire",
    "wof:name":"Barbara Morgan",
    "wof:placetype":"venue"
},
  "geometry": {"coordinates":[-1.397898,50.899002],"type":"Point"}
}