{
  "type": "Feature",
  "properties": {
    "iso:country":"GB",
    "sg:address":"Coventry Road",
    "sg:city":"Rugby",
    "sg:classifiers":[
        {
            "category":"Bars & Pubs",
            "type":"Food & Drink"
        }
    ],
    "sg:phone":"+44 1788 832355",
    "sg:postcode":"CV23 0NE",
    "sg:province":"Northamptonshire",
    "sg:tags":[
        "pubs",
        "inn"
    ],
    "wof:name":"The Bulls Head Brewers Fayre",
    "wof:placetype":"venue"
},
  "geometry": {"coordinates":[-1.370459,52.412159],"type":"Point"}
}