{
  "type": "Feature",
  "properties": {
    "addr:full":"30 Reform Street Beith North Ayrshire KA15 2AE",
    "addr:housenumber":"30",
    "addr:postcode":"ka15 2ae",
    "addr:street":"Reform Street",
    "iso:country":"GB",
    "sg:address":"30 Reform Street",
    "sg:city":"Beith",
    "sg:classifiers":[
        {
            "category":"Farming",
            "subcategory":"Nursery",
            "type":"Manufacturing & Wholesale Goods"
        }
    ],
    "sg:postcode":"KA15 2AE",
    "sg:province":"North Ayrshire",
    "sg:tags":[
        "creche"
    ],
    "wof:name":"Braefoot Nursery",
    "wof:placetype":"venue"
},
  "geometry": {"coordinates":[-4.6336898804,55.7520942688],"type":"Point"}
}