{
  "type": "Feature",
  "properties": {
    "iso:country":"GB",
    "sg:address":"Crome Lea Farm, Madingley Road, Coton",
    "sg:city":"Cambridge",
    "sg:classifiers":[
        {
            "category":"Shopping",
            "subcategory":"Florist",
            "type":"Retail Goods"
        }
    ],
    "sg:phone":"+44 1954 212122",
    "sg:postcode":"CB3 7PH",
    "sg:province":"Cambridgeshire",
    "wof:name":"Fulbourn Manor Nurseries",
    "wof:placetype":"venue"
},
  "geometry": {"coordinates":[0.060245,52.210323],"type":"Point"}
}