{
  "type": "Feature",
  "properties": {
    "addr:full":"26 Orchard Rd Guildford Surrey GU4 7JH",
    "addr:housenumber":"26",
    "addr:postcode":"gu4 7jh",
    "addr:street":"Orchard Rd",
    "iso:country":"GB",
    "sg:address":"26 Orchard Rd",
    "sg:city":"Guildford",
    "sg:classifiers":[
        {
            "category":"Food & Beverages",
            "subcategory":"Meat & Fish",
            "type":"Retail Goods"
        }
    ],
    "sg:phone":"+44 1483 302762",
    "sg:postcode":"GU4 7JH",
    "sg:province":"Surrey",
    "sg:tags":[
        "merchant"
    ],
    "wof:name":"John Ross Jr (Aberdeen) Ltd",
    "wof:placetype":"venue"
},
  "geometry": {"coordinates":[-0.5431270003,51.2603378296],"type":"Point"}
}