{
  "type": "Feature",
  "properties": {
    "addr:full":"1 St George's Place York North Yorkshire YO24 1GN",
    "addr:housenumber":"1",
    "addr:postcode":"yo24 1gn",
    "addr:street":"St George'S Place York",
    "iso:country":"GB",
    "sg:address":"1 St George's Place",
    "sg:city":"York",
    "sg:classifiers":[
        {
            "category":"Professional",
            "subcategory":"Computer Services",
            "type":"Services"
        }
    ],
    "sg:phone":"+44 1904 611666",
    "sg:postcode":"YO24 1GN",
    "sg:province":"North Yorkshire",
    "sg:tags":[
        "system",
        "software"
    ],
    "wof:name":"Aran Plc",
    "wof:placetype":"venue"
},
  "geometry": {"coordinates":[-1.091137,53.94651],"type":"Point"}
}