{
  "type": "Feature",
  "properties": {
    "addr:full":"98 West Clyde Street Helensburgh Argyll and Bute G84 8BE",
    "addr:housenumber":"98",
    "addr:postcode":"g84 8be",
    "addr:street":"West Clyde Street",
    "iso:country":"GB",
    "sg:address":"98 West Clyde Street",
    "sg:city":"Helensburgh",
    "sg:classifiers":[
        {
            "category":"Travel",
            "subcategory":"Hotels & Motels",
            "type":"Entertainment"
        }
    ],
    "sg:phone":"+44 1436 673461",
    "sg:postcode":"G84 8BE",
    "sg:province":"Argyll and Bute",
    "sg:tags":[
        "house",
        "guest"
    ],
    "wof:name":"Ardmore Guest House",
    "wof:placetype":"venue"
},
  "geometry": {"coordinates":[-4.741811,56.004379],"type":"Point"}
}