{
  "type": "Feature",
  "properties": {
    "iso:country":"GB",
    "sg:address":"Cromlech Farm, Rhoscolyn",
    "sg:city":"Holyhead",
    "sg:classifiers":[
        {
            "category":"Farming",
            "subcategory":"Farm",
            "type":"Manufacturing & Wholesale Goods"
        }
    ],
    "sg:phone":"+44 1407 860251",
    "sg:postcode":"LL65 2EQ",
    "sg:province":"Isle of Anglesey",
    "sg:tags":[
        "mixed",
        "crop"
    ],
    "wof:name":"A Evans",
    "wof:placetype":"venue"
},
  "geometry": {"coordinates":[-4.6307139397,53.3063697815],"type":"Point"}
}