{
  "type": "Feature",
  "properties": {
    "iso:country":"GB",
    "sg:address":"7 East Moor Park",
    "sg:city":"Harpenden",
    "sg:classifiers":[
        {
            "category":"Government",
            "subcategory":"Fire Station",
            "type":"Public Place"
        }
    ],
    "sg:phone":"+44 1582 769500",
    "sg:postcode":"AL5 1BN",
    "sg:province":"Hertfordshire",
    "sg:tags":[
        "security"
    ],
    "wof:name":"Fire Guard",
    "wof:placetype":"venue"
},
  "geometry": {"coordinates":[-0.344268,51.804272],"type":"Point"}
}