{
  "type": "Feature",
  "properties": {
    "iso:country":"GB",
    "sg:address":"32 South St",
    "sg:city":"Keith",
    "sg:classifiers":[
        {
            "category":"Bus Charters",
            "type":"Transportation"
        }
    ],
    "sg:phone":"+44 1542 882482",
    "sg:postcode":"AB55 3TU",
    "sg:province":"Moray",
    "sg:tags":[
        "hire",
        "coach"
    ],
    "wof:name":"R E Stables",
    "wof:placetype":"venue"
},
  "geometry": {"coordinates":[-2.95045,57.54324],"type":"Point"}
}