{
  "type": "Feature",
  "properties": {
    "addr:full":"Botteslow Street Stoke-on-trent Staffordshire ST1 3NE",
    "addr:postcode":"st1 3ne",
    "addr:street":"Botteslow Street",
    "iso:country":"GB",
    "sg:address":"Botteslow Street",
    "sg:city":"Stoke-on-trent",
    "sg:classifiers":[
        {
            "category":"Retail",
            "subcategory":"Auto Repair",
            "type":"Services"
        }
    ],
    "sg:postcode":"ST1 3NE",
    "sg:province":"Staffordshire",
    "sg:tags":[
        "modification",
        "garage"
    ],
    "wof:name":"W H Jervis & Sons",
    "wof:placetype":"venue"
},
  "geometry": {"coordinates":[-2.168049,53.022144],"type":"Point"}
}