{
  "type": "Feature",
  "properties": {
    "iso:country":"GB",
    "sg:address":"Tamworth Road, Sawley, Long Eaton",
    "sg:city":"Nottingham",
    "sg:classifiers":[
        {
            "category":"Retail",
            "subcategory":"Emissions Testing",
            "type":"Services"
        },
        {
            "category":"Retail",
            "subcategory":"Auto Repair",
            "type":"Services"
        }
    ],
    "sg:phone":"+44 115 946 3268",
    "sg:postcode":"NG10 3AB",
    "sg:province":"Derbyshire",
    "sg:tags":[
        "modification",
        "garage",
        "mot"
    ],
    "wof:name":"Kam Servicing",
    "wof:placetype":"venue"
},
  "geometry": {"coordinates":[-1.282719,52.887581],"type":"Point"}
}