{
  "type": "Feature",
  "properties": {
    "addr:full":"Sandringham Cres Worksop Nottinghamshire S81 7EU",
    "addr:postcode":"s81 7eu",
    "addr:street":"Sandringham Cres",
    "iso:country":"GB",
    "sg:address":"Sandringham Cres",
    "sg:city":"Worksop",
    "sg:classifiers":[
        {
            "category":"Community Center",
            "type":"Public Place"
        }
    ],
    "sg:phone":"+44 1909 500935",
    "sg:postcode":"S81 7EU",
    "sg:province":"Nottinghamshire",
    "sg:tags":[
        "centre"
    ],
    "wof:name":"Balmoral Community Centre",
    "wof:placetype":"venue"
},
  "geometry": {"coordinates":[-1.130312,53.323299],"type":"Point"}
}