{
  "type": "Feature",
  "properties": {
    "addr:full":"370 Reading Road, Winnersh Wokingham Berkshire RG41 5EJ",
    "addr:housenumber":"370",
    "addr:postcode":"rg41 5ej",
    "addr:street":"Reading Road",
    "iso:country":"GB",
    "sg:address":"370 Reading Road, Winnersh",
    "sg:city":"Wokingham",
    "sg:classifiers":[
        {
            "category":"Autos & Motor Vehicles",
            "subcategory":"Auto Supplies",
            "type":"Retail Goods"
        }
    ],
    "sg:phone":"+44 118 989 1123",
    "sg:postcode":"RG41 5EJ",
    "sg:province":"Berkshire",
    "sg:tags":[
        "exhaust",
        "absorber",
        "shock",
        "tyre"
    ],
    "wof:name":"Edmunds Exhaust & Autocare Ltd",
    "wof:placetype":"venue"
},
  "geometry": {"coordinates":[-0.875169,51.42741],"type":"Point"}
}