{
  "type": "Feature",
  "properties": {
    "addr:full":"103 Whitehouse Loan Edinburgh City of Edinburgh EH9 1AT",
    "addr:housenumber":"103",
    "addr:postcode":"eh9 1at",
    "addr:street":"Whitehouse Loan",
    "iso:country":"GB",
    "sg:address":"103 Whitehouse Loan",
    "sg:city":"Edinburgh",
    "sg:classifiers":[
        {
            "category":"Health Services",
            "subcategory":"Dentist",
            "type":"Services"
        }
    ],
    "sg:phone":"+44 131 446 9500",
    "sg:postcode":"EH9 1AT",
    "sg:province":"City of Edinburgh",
    "wof:name":"Iain M Stewart",
    "wof:placetype":"venue"
},
  "geometry": {"coordinates":[-3.2014019489,55.9357147217],"type":"Point"}
}