{
  "type": "Feature",
  "properties": {
    "addr:full":"320b London Road, Hazel Gro Stockport Cheshire SK7 4RF",
    "addr:housenumber":"320b",
    "addr:postcode":"sk7 4rf",
    "addr:street":"London Road",
    "iso:country":"GB",
    "sg:address":"320b London Road, Hazel Gro",
    "sg:city":"Stockport",
    "sg:classifiers":[
        {
            "category":"Building & Trades",
            "subcategory":"Construction",
            "type":"Services"
        }
    ],
    "sg:postcode":"SK7 4RF",
    "sg:province":"Cheshire",
    "sg:tags":[
        "tiling",
        "contractor"
    ],
    "wof:name":"David J Billington",
    "wof:placetype":"venue"
},
  "geometry": {"coordinates":[-2.115649,53.376789],"type":"Point"}
}