{
  "type": "Feature",
  "properties": {
    "addr:full":"352 Nuneaton Road, Bulkington Nuneaton Warwickshire CV12 9RR",
    "addr:housenumber":"352",
    "addr:postcode":"cv12 9rr",
    "addr:street":"Nuneaton Road",
    "iso:country":"GB",
    "sg:address":"352 Nuneaton Road, Bulkington",
    "sg:city":"Nuneaton",
    "sg:classifiers":[
        {
            "category":"Sports & Exercise",
            "subcategory":"Stables",
            "type":"Entertainment"
        }
    ],
    "sg:phone":"+44 24 7631 2170",
    "sg:postcode":"CV12 9RR",
    "sg:province":"Warwickshire",
    "sg:tags":[
        "equestrian",
        "centre",
        "livery",
        "schools",
        "riding",
        "education"
    ],
    "wof:name":"Chase Riding School",
    "wof:placetype":"venue"
},
  "geometry": {"coordinates":[-1.431261,52.491173],"type":"Point"}
}