{
  "type": "Feature",
  "properties": {
    "addr:full":"Vencourt House, 255 King Street London Greater London W6 0RF",
    "addr:housenumber":"255",
    "addr:postcode":"w6 0rf",
    "addr:street":"King Street",
    "iso:country":"GB",
    "sg:address":"Vencourt House, 255 King Street",
    "sg:city":"London",
    "sg:classifiers":[
        {
            "category":"Travel",
            "subcategory":"Hotels & Motels",
            "type":"Entertainment"
        }
    ],
    "sg:phone":"+44 20 8563 8855",
    "sg:postcode":"W6 0RF",
    "sg:province":"Greater London",
    "wof:name":"Vencourt",
    "wof:placetype":"venue"
},
  "geometry": {"coordinates":[-0.244913,51.493271],"type":"Point"}
}