{
  "type": "Feature",
  "properties": {
    "addr:full":"586 Gorton Road Stockport Cheshire SK5 6RE",
    "addr:housenumber":"586",
    "addr:postcode":"sk5 6re",
    "addr:street":"Gorton Road",
    "iso:country":"GB",
    "sg:address":"586 Gorton Road",
    "sg:city":"Stockport",
    "sg:classifiers":[
        {
            "category":"Personal",
            "subcategory":"Beauty Salon",
            "type":"Services"
        }
    ],
    "sg:postcode":"SK5 6RE",
    "sg:province":"Cheshire",
    "sg:tags":[
        "lady",
        "hairdresser"
    ],
    "wof:name":"Panache",
    "wof:placetype":"venue"
},
  "geometry": {"coordinates":[-2.157603,53.453594],"type":"Point"}
}