{
  "type": "Feature",
  "properties": {
    "iso:country":"GB",
    "sg:address":"Leeds Road, Birstall",
    "sg:city":"Batley",
    "sg:classifiers":[
        {
            "category":"Arena",
            "subcategory":"Sports Club",
            "type":"Entertainment"
        }
    ],
    "sg:phone":"+44 1924 473650",
    "sg:postcode":"WF17 0EJ",
    "sg:province":"West Yorkshire",
    "wof:name":"Birstall Cricket Club",
    "wof:placetype":"venue"
},
  "geometry": {"coordinates":[-1.6420340538,53.736530304],"type":"Point"}
}