{
  "type": "Feature",
  "properties": {
    "addr:full":"Hereford Rd Shrewsbury Shropshire SY3 0DA",
    "addr:postcode":"sy3 0da",
    "addr:street":"Hereford Rd",
    "iso:country":"GB",
    "sg:address":"Hereford Rd",
    "sg:city":"Shrewsbury",
    "sg:classifiers":[
        {
            "category":"Home & Garden",
            "subcategory":"Garden Supply",
            "type":"Retail Goods"
        }
    ],
    "sg:phone":"+44 1743 874261",
    "sg:postcode":"SY3 0DA",
    "sg:province":"Shropshire",
    "sg:tags":[
        "nursery",
        "centre"
    ],
    "wof:name":"Bayley's Garden Centre",
    "wof:placetype":"venue"
},
  "geometry": {"coordinates":[-2.7582740784,52.681968689],"type":"Point"}
}