{
  "type": "Feature",
  "properties": {
    "addr:full":"86 Northway Scarborough North Yorkshire YO12 7AG",
    "addr:housenumber":"86",
    "addr:postcode":"yo12 7ag",
    "addr:street":"Northway",
    "iso:country":"GB",
    "sg:address":"86 Northway",
    "sg:city":"Scarborough",
    "sg:classifiers":[
        {
            "category":"Restaurant",
            "type":"Food & Drink"
        },
        {
            "category":"Food & Beverages",
            "subcategory":"Meat & Fish",
            "type":"Retail Goods"
        }
    ],
    "sg:phone":"+44 1723 375719",
    "sg:postcode":"YO12 7AG",
    "sg:province":"North Yorkshire",
    "sg:tags":[
        "chip"
    ],
    "wof:name":"Baxters Fisheries",
    "wof:placetype":"venue"
},
  "geometry": {"coordinates":[-0.4084770083,54.2820167542],"type":"Point"}
}