{
  "type": "Feature",
  "properties": {
    "addr:full":"219 Field End Road Pinner Greater London HA5 1QZ",
    "addr:housenumber":"219",
    "addr:postcode":"ha5 1qz",
    "addr:street":"Field End Road",
    "iso:country":"GB",
    "sg:address":"219 Field End Road",
    "sg:city":"Pinner",
    "sg:classifiers":[
        {
            "category":"Restaurant",
            "type":"Food & Drink"
        }
    ],
    "sg:phone":"+44 20 8868 9622",
    "sg:postcode":"HA5 1QZ",
    "sg:province":"Greater London",
    "wof:name":"The Knife & Fork",
    "wof:placetype":"venue"
},
  "geometry": {"coordinates":[-0.398349,51.5774],"type":"Point"}
}