{
  "type": "Feature",
  "properties": {
    "addr:full":"Merrydale House, Linford Road Grays Essex RM16 4LQ",
    "addr:postcode":"rm16 4lq",
    "addr:street":"Linford Road",
    "iso:country":"GB",
    "sg:address":"Merrydale House, Linford Road",
    "sg:city":"Grays",
    "sg:classifiers":[
        {
            "category":"Structure",
            "subcategory":"Warehouse",
            "type":"Public Place"
        }
    ],
    "sg:phone":"+44 1375 851113",
    "sg:postcode":"RM16 4LQ",
    "sg:province":"Essex",
    "wof:name":"Linford Services Ltd.",
    "wof:placetype":"venue"
},
  "geometry": {"coordinates":[0.3813979924,51.4819221497],"type":"Point"}
}