{
  "type": "Feature",
  "properties": {
    "iso:country":"GB",
    "sg:address":"45 Penny St",
    "sg:city":"Lancaster",
    "sg:classifiers":[
        {
            "category":"Banks & Credit Unions",
            "subcategory":"Bank",
            "type":"Services"
        }
    ],
    "sg:phone":"+44 1524 68155",
    "sg:postcode":"LA1 1UE",
    "sg:province":"Lancashire",
    "wof:name":"Yorkshire Bank Plc",
    "wof:placetype":"venue"
},
  "geometry": {"coordinates":[-2.8001101017,54.0472488403],"type":"Point"}
}