{
  "type": "Feature",
  "properties": {
    "addr:full":"11 Kiln Gardens, Hartley Wintney Hook Berkshire RG27 8RG",
    "addr:housenumber":"11",
    "addr:postcode":"rg27 8rg",
    "addr:street":"Kiln Gardens",
    "iso:country":"GB",
    "sg:address":"11 Kiln Gardens, Hartley Wintney",
    "sg:city":"Hook",
    "sg:classifiers":[
        {
            "category":"Personal",
            "subcategory":"Beauty Salon",
            "type":"Services"
        }
    ],
    "sg:phone":"+44 1252 844966",
    "sg:postcode":"RG27 8RG",
    "sg:province":"Berkshire",
    "wof:name":"Sugar 'N Spice Beauty Therapy",
    "wof:placetype":"venue"
},
  "geometry": {"coordinates":[-0.9085310102,51.3043708801],"type":"Point"}
}