{
  "type": "Feature",
  "properties": {
    "addr:full":"Unit 2 Wakefield Rd Bootle Merseyside L30 6TZ",
    "addr:housenumber":"unit 2",
    "addr:postcode":"l30 6tz",
    "addr:street":"Wakefield Rd",
    "iso:country":"GB",
    "sg:address":"Unit 2 Wakefield Rd",
    "sg:city":"Bootle",
    "sg:classifiers":[
        {
            "category":"Manufacturing",
            "subcategory":"Petroleum Products",
            "type":"Manufacturing & Wholesale Goods"
        }
    ],
    "sg:phone":"+44 151 525 3030",
    "sg:postcode":"L30 6TZ",
    "sg:province":"Merseyside",
    "sg:tags":[
        "double",
        "glazing"
    ],
    "wof:name":"Castile Windows",
    "wof:placetype":"venue"
},
  "geometry": {"coordinates":[-2.959387,53.483223],"type":"Point"}
}