{
  "type": "Feature",
  "properties": {
    "addr:full":"Highgates, Abbots Lane Kenley Surrey CR8 5JB",
    "addr:postcode":"cr8 5jb",
    "addr:street":"Abbots Lane",
    "iso:country":"GB",
    "sg:address":"Highgates, Abbots Lane",
    "sg:city":"Kenley",
    "sg:classifiers":[
        {
            "category":"Building & Trades",
            "subcategory":"Construction",
            "type":"Services"
        }
    ],
    "sg:phone":"+44 20 8660 5991",
    "sg:postcode":"CR8 5JB",
    "sg:province":"Surrey",
    "sg:tags":[
        "tiling",
        "contractor"
    ],
    "wof:name":"South Eastern Ceramic Tiling",
    "wof:placetype":"venue"
},
  "geometry": {"coordinates":[-0.0995149985,51.3227996826],"type":"Point"}
}