{
  "type": "Feature",
  "properties": {
    "addr:full":"The Custard Factory, Gibbs Street Birmingham West Midlands B9 4AA",
    "addr:postcode":"b9 4aa",
    "addr:street":"Gibbs Street",
    "iso:country":"GB",
    "sg:address":"The Custard Factory, Gibbs Street",
    "sg:city":"Birmingham",
    "sg:classifiers":[
        {
            "category":"Shopping",
            "subcategory":"Stationery & Office Supplies",
            "type":"Retail Goods"
        },
        {
            "category":"Manufacturing",
            "subcategory":"Textiles",
            "type":"Manufacturing & Wholesale Goods"
        }
    ],
    "sg:phone":"+44 121 773 6833",
    "sg:postcode":"B9 4AA",
    "sg:province":"West Midlands",
    "sg:tags":[
        "designer",
        "manufacturer"
    ],
    "wof:name":"Cinnamon Aitch",
    "wof:placetype":"venue"
},
  "geometry": {"coordinates":[-1.86649,52.478168],"type":"Point"}
}