{
  "type": "Feature",
  "properties": {
    "iso:country":"GB",
    "sg:address":"Coxcombe Cottage, Woodside Road, Chiddingfold",
    "sg:city":"Godalming",
    "sg:classifiers":[
        {
            "category":"Building & Trades",
            "subcategory":"Construction",
            "type":"Services"
        }
    ],
    "sg:phone":"+44 1428 683427",
    "sg:postcode":"GU8 4QD",
    "sg:province":"Surrey",
    "sg:tags":[
        "builder"
    ],
    "wof:name":"Hobbs Construction",
    "wof:placetype":"venue"
},
  "geometry": {"coordinates":[-0.6314690113,51.114200592],"type":"Point"}
}