{
  "type": "Feature",
  "properties": {
    "addr:full":"1 Barnfield, East Allington Totnes Devon TQ9 7QR",
    "addr:housenumber":"1",
    "addr:postcode":"tq9 7qr",
    "addr:street":"Barnfield East",
    "iso:country":"GB",
    "sg:address":"1 Barnfield, East Allington",
    "sg:city":"Totnes",
    "sg:classifiers":[
        {
            "category":"Freight",
            "type":"Transportation"
        }
    ],
    "sg:phone":"+44 7779 788680",
    "sg:postcode":"TQ9 7QR",
    "sg:province":"Devon",
    "sg:tags":[
        "haulage",
        "road"
    ],
    "wof:name":"Jeremy Bishop Haulage",
    "wof:placetype":"venue"
},
  "geometry": {"coordinates":[-3.730133,50.324837],"type":"Point"}
}