{
  "type": "Feature",
  "properties": {
    "iso:country":"GB",
    "sg:address":"415 Crofton Rd",
    "sg:city":"Orpington",
    "sg:classifiers":[
        {
            "category":"Shopping",
            "subcategory":"Comic Books",
            "type":"Retail Goods"
        }
    ],
    "sg:phone":"+44 1689 850861",
    "sg:postcode":"BR6 8NL",
    "sg:province":"Kent",
    "sg:tags":[
        "jeweller"
    ],
    "wof:name":"Mitchell & Meredith",
    "wof:placetype":"venue"
},
  "geometry": {"coordinates":[0.054513,51.366867],"type":"Point"}
}