{
  "type": "Feature",
  "properties": {
    "addr:full":"Caellian, Pen-y-garnedd, Llanrhaeadr Ym Mochnant Oswestry Shropshire SY10 0AS",
    "addr:postcode":"sy10 0as",
    "iso:country":"GB",
    "sg:address":"Caellian, Pen-y-garnedd, Llanrhaeadr Ym Mochnant",
    "sg:city":"Oswestry",
    "sg:classifiers":[
        {
            "category":"Farming",
            "subcategory":"Livestock Farm",
            "type":"Manufacturing & Wholesale Goods"
        }
    ],
    "sg:phone":"+44 1691 648405",
    "sg:postcode":"SY10 0AS",
    "sg:province":"Shropshire",
    "sg:tags":[
        "others"
    ],
    "wof:name":"F Jones",
    "wof:placetype":"venue"
},
  "geometry": {"coordinates":[-3.302218914,52.8252944946],"type":"Point"}
}