{
  "type": "Feature",
  "properties": {
    "iso:country":"GB",
    "sg:address":"31 Fore Street",
    "sg:city":"Ipswich",
    "sg:classifiers":[
        {
            "category":"Personal",
            "subcategory":"Beauty Salon",
            "type":"Services"
        }
    ],
    "sg:postcode":"IP4 1JY",
    "sg:province":"Suffolk",
    "wof:name":"Perfections Health & Beauty Salon",
    "wof:placetype":"venue"
},
  "geometry": {"coordinates":[1.159621,52.05444],"type":"Point"}
}