{
  "type": "Feature",
  "properties": {
    "addr:full":"4 Willand Rd Cullompton Devon EX15 1AP",
    "addr:housenumber":"4",
    "addr:postcode":"ex15 1ap",
    "addr:street":"Willand Rd",
    "iso:country":"GB",
    "sg:address":"4 Willand Rd",
    "sg:city":"Cullompton",
    "sg:classifiers":[
        {
            "category":"Place Of Worship",
            "type":"Public Place"
        }
    ],
    "sg:phone":"+44 1884 32679",
    "sg:postcode":"EX15 1AP",
    "sg:province":"Devon",
    "wof:name":"Sampford Peverell Methodist Church",
    "wof:placetype":"venue"
},
  "geometry": {"coordinates":[-3.3930668831,50.8618965149],"type":"Point"}
}