{
  "type": "Feature",
  "properties": {
    "addr:full":"64 Edmund Grn, Gosfield Halstead Essex CO9 1UF",
    "addr:housenumber":"64",
    "addr:postcode":"co9 1uf",
    "addr:street":"Edmund Grn Gosfield",
    "iso:country":"GB",
    "sg:address":"64 Edmund Grn, Gosfield",
    "sg:city":"Halstead",
    "sg:classifiers":[
        {
            "category":"Building & Trades",
            "subcategory":"Construction",
            "type":"Services"
        }
    ],
    "sg:phone":"+44 1787 474740",
    "sg:postcode":"CO9 1UF",
    "sg:province":"Essex",
    "sg:tags":[
        "builder"
    ],
    "wof:name":"C E Crace",
    "wof:placetype":"venue"
},
  "geometry": {"coordinates":[0.5944780111,51.9357414246],"type":"Point"}
}