{
  "type": "Feature",
  "properties": {
    "addr:full":"1 Kent Rd, Whitehill Bordon Hampshire GU35 9PZ",
    "addr:housenumber":"1",
    "addr:postcode":"gu35 9pz",
    "addr:street":"Kent Rd",
    "iso:country":"GB",
    "sg:address":"1 Kent Rd, Whitehill",
    "sg:city":"Bordon",
    "sg:classifiers":[
        {
            "category":"Real Estate",
            "subcategory":"Real Estate Agent",
            "type":"Services"
        }
    ],
    "sg:postcode":"GU35 9PZ",
    "sg:province":"Hampshire",
    "wof:name":"A & C Property Management",
    "wof:placetype":"venue"
},
  "geometry": {"coordinates":[-0.86455,51.104736],"type":"Point"}
}