{
  "type": "Feature",
  "properties": {
    "iso:country":"GB",
    "sg:address":"1 Clarage House, Long Lane",
    "sg:city":"Halesowen",
    "sg:classifiers":[
        {
            "category":"Autos & Motor Vehicles",
            "subcategory":"Motorcycle Sales",
            "type":"Retail Goods"
        }
    ],
    "sg:postcode":"B62 9LA",
    "sg:province":"West Midlands",
    "wof:name":"Black Country Motorcycles",
    "wof:placetype":"venue"
},
  "geometry": {"coordinates":[-2.033,52.469582],"type":"Point"}
}