{
  "type": "Feature",
  "properties": {
    "addr:full":"161 Hoxton St Islington Greater London N1 6PJ",
    "addr:housenumber":"161",
    "addr:postcode":"n1 6pj",
    "addr:street":"Hoxton St",
    "iso:country":"GB",
    "sg:address":"161 Hoxton St",
    "sg:city":"Islington",
    "sg:classifiers":[
        {
            "category":"Travel",
            "subcategory":"Travel Agent",
            "type":"Entertainment"
        }
    ],
    "sg:phone":"+44 20 7689 2220",
    "sg:postcode":"N1 6PJ",
    "sg:province":"Greater London",
    "wof:name":"General Travel Services",
    "wof:placetype":"venue"
},
  "geometry": {"coordinates":[-0.0803819969,51.5313987732],"type":"Point"}
}