{
  "type": "Feature",
  "properties": {
    "addr:full":"Finlay Motors, Boyton Woodbridge Suffolk IP12 3LH",
    "addr:postcode":"ip12 3lh",
    "iso:country":"GB",
    "sg:address":"Finlay Motors, Boyton",
    "sg:city":"Woodbridge",
    "sg:classifiers":[
        {
            "category":"Retail",
            "subcategory":"Auto Repair",
            "type":"Services"
        }
    ],
    "sg:phone":"+44 1394 411712",
    "sg:postcode":"IP12 3LH",
    "sg:province":"Suffolk",
    "sg:tags":[
        "modification",
        "garage",
        "related"
    ],
    "wof:name":"Finlay Motors Boyton",
    "wof:placetype":"venue"
},
  "geometry": {"coordinates":[1.4671349525,52.071144104],"type":"Point"}
}