{
  "type": "Feature",
  "properties": {
    "addr:full":"146 Allestree Lane Derby Derbyshire DE22 2JY",
    "addr:housenumber":"146",
    "addr:postcode":"de22 2jy",
    "addr:street":"Allestree Lane",
    "iso:country":"GB",
    "sg:address":"146 Allestree Lane",
    "sg:city":"Derby",
    "sg:classifiers":[
        {
            "category":"Building & Trades",
            "subcategory":"Plumbing",
            "type":"Services"
        }
    ],
    "sg:postcode":"DE22 2JY",
    "sg:province":"Derbyshire",
    "sg:tags":[
        "heating"
    ],
    "wof:name":"Allestree Builders & Plumbers",
    "wof:placetype":"venue"
},
  "geometry": {"coordinates":[-1.4998929501,52.9474868774],"type":"Point"}
}