{
  "type": "Feature",
  "properties": {
    "iso:country":"GB",
    "sg:address":"70 Pollard Lane",
    "sg:city":"Bradford",
    "sg:classifiers":[
        {
            "category":"Farming",
            "subcategory":"Nursery",
            "type":"Manufacturing & Wholesale Goods"
        }
    ],
    "sg:phone":"+44 1274 635987",
    "sg:postcode":"BD2 4RW",
    "sg:province":"West Yorkshire",
    "sg:tags":[
        "creche"
    ],
    "wof:name":"A Z Private Day Nursery",
    "wof:placetype":"venue"
},
  "geometry": {"coordinates":[-1.727381,53.80534],"type":"Point"}
}