{
  "type": "Feature",
  "properties": {
    "addr:full":"116a Western Road Brighton East Sussex BN1 2AB",
    "addr:housenumber":"116a",
    "addr:postcode":"bn1 2ab",
    "addr:street":"Western Road",
    "iso:country":"GB",
    "sg:address":"116a Western Road",
    "sg:city":"Brighton",
    "sg:classifiers":[
        {
            "category":"Fast Food",
            "type":"Food & Drink"
        },
        {
            "category":"Restaurant",
            "type":"Food & Drink"
        }
    ],
    "sg:phone":"+44 1273 328267",
    "sg:postcode":"BN1 2AB",
    "sg:province":"East Sussex",
    "sg:tags":[
        "away",
        "take"
    ],
    "wof:name":"Bankers Fish Restaurant",
    "wof:placetype":"venue"
},
  "geometry": {"coordinates":[-0.154917,50.82523],"type":"Point"}
}