{
  "type": "Feature",
  "properties": {
    "addr:full":"219 Northdown Road, Cliftonville Margate Kent CT9 2PF",
    "addr:housenumber":"219",
    "addr:postcode":"ct9 2pf",
    "addr:street":"Northdown Road;Margate",
    "iso:country":"GB",
    "sg:address":"219 Northdown Road, Cliftonville",
    "sg:city":"Margate",
    "sg:classifiers":[
        {
            "category":"Food & Beverages",
            "subcategory":"Groceries & Convenience Stores",
            "type":"Retail Goods"
        }
    ],
    "sg:phone":"+44 1843 224745",
    "sg:postcode":"CT9 2PF",
    "sg:province":"Kent",
    "wof:name":"Moylers",
    "wof:placetype":"venue"
},
  "geometry": {"coordinates":[1.39641,51.387959],"type":"Point"}
}