{
  "type": "Feature",
  "properties": {
    "iso:country":"GB",
    "sg:address":"19 Tyburn La, Westoning",
    "sg:city":"Bedford",
    "sg:classifiers":[
        {
            "category":"Farming",
            "subcategory":"Livestock Farm",
            "type":"Manufacturing & Wholesale Goods"
        }
    ],
    "sg:phone":"+44 1525 633864",
    "sg:postcode":"MK45 5JU",
    "sg:province":"Bedfordshire",
    "sg:tags":[
        "breeder"
    ],
    "wof:name":"Floral Displays",
    "wof:placetype":"venue"
},
  "geometry": {"coordinates":[-0.45809,51.993519],"type":"Point"}
}