{
  "type": "Feature",
  "properties": {
    "addr:full":"37 Mistley Side Basildon Essex SS16 4AP",
    "addr:housenumber":"37",
    "addr:postcode":"ss16 4ap",
    "addr:street":"Mistley Side Basildon",
    "iso:country":"GB",
    "sg:address":"37 Mistley Side",
    "sg:city":"Basildon",
    "sg:classifiers":[
        {
            "category":"Manufacturing",
            "subcategory":"Building Materials",
            "type":"Manufacturing & Wholesale Goods"
        }
    ],
    "sg:phone":"+44 1268 523001",
    "sg:postcode":"SS16 4AP",
    "sg:province":"Essex",
    "sg:tags":[
        "tarmac",
        "asphalt"
    ],
    "wof:name":"R & D Mastics",
    "wof:placetype":"venue"
},
  "geometry": {"coordinates":[0.472046,51.567284],"type":"Point"}
}