{
  "type": "Feature",
  "properties": {
    "iso:country":"GB",
    "sg:address":"4 Cherry Way, Horton",
    "sg:city":"Slough",
    "sg:classifiers":[
        {
            "category":"Manufacturing",
            "subcategory":"Furniture",
            "type":"Manufacturing & Wholesale Goods"
        }
    ],
    "sg:phone":"+44 1753 680207",
    "sg:postcode":"SL3 9PU",
    "sg:province":"Berkshire",
    "sg:tags":[
        "polishing",
        "french"
    ],
    "wof:name":"C & H French Polishers",
    "wof:placetype":"venue"
},
  "geometry": {"coordinates":[-0.58062,51.549839],"type":"Point"}
}