{
  "type": "Feature",
  "properties": {
    "addr:full":"8 Norwith Road, Bessacarr Doncaster South Yorkshire DN4 7HW",
    "addr:housenumber":"8",
    "addr:postcode":"dn4 7hw",
    "addr:street":"Norwith Road",
    "iso:country":"GB",
    "sg:address":"8 Norwith Road, Bessacarr",
    "sg:city":"Doncaster",
    "sg:classifiers":[
        {
            "category":"Retail",
            "subcategory":"Repair Shop",
            "type":"Services"
        }
    ],
    "sg:postcode":"DN4 7HW",
    "sg:province":"South Yorkshire",
    "sg:tags":[
        "radio",
        "television",
        "video"
    ],
    "wof:name":"N F Burkinshaw",
    "wof:placetype":"venue"
},
  "geometry": {"coordinates":[-1.0817970037,53.4989395142],"type":"Point"}
}