{
  "type": "Feature",
  "properties": {
    "addr:full":"27 Lang Road Derby Derbyshire DE24 0GB",
    "addr:housenumber":"27",
    "addr:postcode":"de24 0gb",
    "addr:street":"Lang Road",
    "iso:country":"GB",
    "sg:address":"27 Lang Road",
    "sg:city":"Derby",
    "sg:classifiers":[
        {
            "category":"Professional",
            "subcategory":"Printing & Photocopies",
            "type":"Services"
        }
    ],
    "sg:phone":"+44 1332 571706",
    "sg:postcode":"DE24 0GB",
    "sg:province":"Derbyshire",
    "sg:tags":[
        "printer"
    ],
    "wof:name":"Oak-Leaf Printers",
    "wof:placetype":"venue"
},
  "geometry": {"coordinates":[-1.4382480383,52.8916091919],"type":"Point"}
}