{
  "type": "Feature",
  "properties": {
    "iso:country":"GB",
    "sg:address":"Abersoch Road, Llanbedrog",
    "sg:city":"Pwllheli",
    "sg:classifiers":[
        {
            "category":"Home & Garden",
            "subcategory":"Hardware",
            "type":"Retail Goods"
        },
        {
            "category":"Retail",
            "subcategory":"Auto Repair",
            "type":"Services"
        }
    ],
    "sg:postcode":"LL53 7UB",
    "sg:province":"Gwynedd",
    "sg:tags":[
        "modification",
        "garage",
        "machinery",
        "lawnmowers"
    ],
    "wof:name":"Ger-y-Nant Garage",
    "wof:placetype":"venue"
},
  "geometry": {"coordinates":[-4.4851088524,52.8581123352],"type":"Point"}
}