{
  "type": "Feature",
  "properties": {
    "iso:country":"GB",
    "sg:address":"Tow Lane, Foston",
    "sg:city":"Grantham",
    "sg:classifiers":[
        {
            "category":"Home & Garden",
            "subcategory":"Garden Supply",
            "type":"Retail Goods"
        }
    ],
    "sg:phone":"+44 1400 281354",
    "sg:postcode":"NG32 2LE",
    "sg:province":"Leicestershire",
    "sg:tags":[
        "nursery",
        "centre"
    ],
    "wof:name":"Orchard Nurseries",
    "wof:placetype":"venue"
},
  "geometry": {"coordinates":[-0.7219650149,52.977142334],"type":"Point"}
}