{
  "type": "Feature",
  "properties": {
    "addr:full":"89 Tweedholm Avenue East Walkerburn Scottish Borders EH43 6AP",
    "addr:housenumber":"89",
    "addr:postcode":"eh43 6ap",
    "addr:street":"Tweedholm Avenue East Walkerburn",
    "iso:country":"GB",
    "sg:address":"89 Tweedholm Avenue East",
    "sg:city":"Walkerburn",
    "sg:classifiers":[
        {
            "category":"Utilities",
            "subcategory":"Refuse",
            "type":"Services"
        }
    ],
    "sg:phone":"+44 1896 870770",
    "sg:postcode":"EH43 6AP",
    "sg:province":"Scottish Borders",
    "sg:tags":[
        "disposal",
        "waste"
    ],
    "wof:name":"Forth Environmental Services",
    "wof:placetype":"venue"
},
  "geometry": {"coordinates":[-3.0092220306,55.6240653992],"type":"Point"}
}