{
  "type": "Feature",
  "properties": {
    "addr:full":"Po Box 111 Shipley West Yorkshire BD18 1YS",
    "addr:housenumber":"po",
    "addr:postcode":"bd18 1ys",
    "addr:street":"Box 111",
    "iso:country":"GB",
    "sg:address":"Po Box 111",
    "sg:city":"Shipley",
    "sg:classifiers":[
        {
            "category":"Shopping",
            "subcategory":"Computers & Home Electronics",
            "type":"Retail Goods"
        }
    ],
    "sg:phone":"+44 1274 787100",
    "sg:postcode":"BD18 1YS",
    "sg:province":"West Yorkshire",
    "sg:tags":[
        "equipment",
        "video",
        "cctv"
    ],
    "wof:name":"JAC Enterprises",
    "wof:placetype":"venue"
},
  "geometry": {"coordinates":[-1.756269,53.831451],"type":"Point"}
}