{
  "type": "Feature",
  "properties": {
    "iso:country":"GB",
    "sg:address":"70 Hatton Rd",
    "sg:city":"Chester",
    "sg:classifiers":[
        {
            "category":"Social Services",
            "subcategory":"Child Care",
            "type":"Services"
        },
        {
            "category":"Social Services",
            "subcategory":"Adult Care",
            "type":"Services"
        }
    ],
    "sg:phone":"+44 1244 373603",
    "sg:postcode":"CH1 5EE",
    "sg:province":"Cheshire",
    "sg:tags":[
        "day",
        "centre"
    ],
    "wof:name":"Day Centre For Children",
    "wof:placetype":"venue"
},
  "geometry": {"coordinates":[-2.9253540039,53.2102622986],"type":"Point"}
}