{
  "type": "Feature",
  "properties": {
    "addr:full":"Newcastle Rd South Shields Tyne and Wear NE34 9AA",
    "addr:postcode":"ne34 9aa",
    "addr:street":"Newcastle Rd",
    "iso:country":"GB",
    "sg:address":"Newcastle Rd",
    "sg:city":"South Shields",
    "sg:classifiers":[
        {
            "category":"Bars & Pubs",
            "type":"Food & Drink"
        }
    ],
    "sg:phone":"+44 191 427 2901",
    "sg:postcode":"NE34 9AA",
    "sg:province":"Tyne and Wear",
    "sg:tags":[
        "pubs",
        "inn"
    ],
    "wof:name":"Simonside Arms",
    "wof:placetype":"venue"
},
  "geometry": {"coordinates":[-1.45456,54.973839],"type":"Point"}
}