{
  "type": "Feature",
  "properties": {
    "iso:country":"GB",
    "sg:address":"Unit A Rear Of 2 Lloyd Street",
    "sg:city":"Rochdale",
    "sg:classifiers":[
        {
            "category":"Autos & Motor Vehicles",
            "subcategory":"Automobile Sales",
            "type":"Retail Goods"
        }
    ],
    "sg:postcode":"OL12 8AA",
    "sg:province":"Lancashire",
    "sg:tags":[
        "car"
    ],
    "wof:name":"Newline Motors",
    "wof:placetype":"venue"
},
  "geometry": {"coordinates":[-2.162766,53.619007],"type":"Point"}
}