{
  "type": "Feature",
  "properties": {
    "addr:full":"106 Albert Street Birmingham West Midlands B5 5LG",
    "addr:housenumber":"106",
    "addr:postcode":"b5 5lg",
    "addr:street":"Albert Street",
    "iso:country":"GB",
    "sg:address":"106 Albert Street",
    "sg:city":"Birmingham",
    "sg:classifiers":[
        {
            "category":"Bars & Pubs",
            "type":"Food & Drink"
        }
    ],
    "sg:postcode":"B5 5LG",
    "sg:province":"West Midlands",
    "sg:tags":[
        "pubs",
        "inn"
    ],
    "wof:name":"The Woodman",
    "wof:placetype":"venue"
},
  "geometry": {"coordinates":[-1.886766,52.481697],"type":"Point"}
}