{
  "type": "Feature",
  "properties": {
    "addr:full":"110a Harrogate Road Leeds West Yorkshire LS7 4NY",
    "addr:housenumber":"110a",
    "addr:postcode":"ls7 4ny",
    "addr:street":"Harrogate Road",
    "iso:country":"GB",
    "sg:address":"110a Harrogate Road",
    "sg:city":"Leeds",
    "sg:classifiers":[
        {
            "category":"Shopping",
            "subcategory":"Clothing, Apparel, & Fashions",
            "type":"Retail Goods"
        }
    ],
    "sg:phone":"+44 113 294 0055",
    "sg:postcode":"LS7 4NY",
    "sg:province":"West Yorkshire",
    "sg:tags":[
        "ladieswear"
    ],
    "wof:name":"Stockade",
    "wof:placetype":"venue"
},
  "geometry": {"coordinates":[-1.5378789902,53.8288803101],"type":"Point"}
}