{
  "type": "Feature",
  "properties": {
    "addr:full":"27-29 Long Street Wigston Leicestershire LE18 2BP",
    "addr:housenumber":"27-29",
    "addr:postcode":"le18 2bp",
    "addr:street":"Long Street",
    "iso:country":"GB",
    "sg:address":"27-29 Long Street",
    "sg:city":"Wigston",
    "sg:classifiers":[
        {
            "category":"Health Services",
            "subcategory":"Nursing And Care Facility",
            "type":"Services"
        }
    ],
    "sg:phone":"+44 116 257 1330",
    "sg:postcode":"LE18 2BP",
    "sg:province":"Leicestershire",
    "sg:tags":[
        "home"
    ],
    "wof:name":"WIGSTON NURSING HOME",
    "wof:placetype":"venue"
},
  "geometry": {"coordinates":[-1.1092220545,52.5828704834],"type":"Point"}
}