{
  "type": "Feature",
  "properties": {
    "iso:country":"GB",
    "sg:address":"Ure Bank Top",
    "sg:city":"Ripon",
    "sg:classifiers":[
        {
            "category":"Recreation",
            "subcategory":"Campground",
            "type":"Entertainment"
        }
    ],
    "sg:phone":"+44 1765 602964",
    "sg:postcode":"HG4 1JD",
    "sg:province":"North Yorkshire",
    "sg:tags":[
        "caravan",
        "park"
    ],
    "wof:name":"Riverside Meadow Country Caravan Park",
    "wof:placetype":"venue"
},
  "geometry": {"coordinates":[-1.516111,54.146217],"type":"Point"}
}