{
  "type": "Feature",
  "properties": {
    "addr:full":"Withington Forge, Cross Keys Hereford Herefordshire HR1 3NU",
    "addr:postcode":"hr1 3nu",
    "addr:street":"Withington Forge",
    "iso:country":"GB",
    "sg:address":"Withington Forge, Cross Keys",
    "sg:city":"Hereford",
    "sg:classifiers":[
        {
            "category":"Home & Garden",
            "subcategory":"Furniture",
            "type":"Retail Goods"
        }
    ],
    "sg:postcode":"HR1 3NU",
    "sg:province":"Herefordshire",
    "wof:name":"Pullen,A J,",
    "wof:placetype":"venue"
},
  "geometry": {"coordinates":[-2.637644,52.085419],"type":"Point"}
}