{
  "type": "Feature",
  "properties": {
    "addr:full":"Po Box 13, Castlehill Campbeltown Argyll and Bute PA28 6AP",
    "addr:housenumber":"po box 13",
    "addr:postcode":"pa28 6ap",
    "addr:street":"Castlehill",
    "iso:country":"GB",
    "sg:address":"Po Box 13, Castlehill",
    "sg:city":"Campbeltown",
    "sg:classifiers":[
        {
            "category":"Banks & Credit Unions",
            "subcategory":"Bank",
            "type":"Services"
        }
    ],
    "sg:phone":"+44 1586 553617",
    "sg:postcode":"PA28 6AP",
    "sg:province":"Argyll and Bute",
    "sg:tags":[
        "financial",
        "institution"
    ],
    "wof:name":"The Royal Bank of Scotland plc",
    "wof:placetype":"venue"
},
  "geometry": {"coordinates":[-5.6102390289,55.4314193726],"type":"Point"}
}