{
  "type": "Feature",
  "properties": {
    "addr:full":"Waunlanyrafon Llanelli Carmarthenshire SA15 3AB",
    "addr:postcode":"sa15 3ab",
    "iso:country":"GB",
    "sg:address":"Waunlanyrafon",
    "sg:city":"Llanelli",
    "sg:classifiers":[
        {
            "category":"Place Of Worship",
            "type":"Public Place"
        }
    ],
    "sg:phone":"+44 1554 774070",
    "sg:postcode":"SA15 3AB",
    "sg:province":"Carmarthenshire",
    "wof:name":"Our Lady Queen Of Peace",
    "wof:placetype":"venue"
},
  "geometry": {"coordinates":[-4.1650061607,51.6812553406],"type":"Point"}
}