{
  "type": "Feature",
  "properties": {
    "addr:full":"403 Brighton Road Lancing West Sussex BN15 8JX",
    "addr:housenumber":"403",
    "addr:postcode":"bn15 8jx",
    "addr:street":"Brighton Road",
    "iso:country":"GB",
    "sg:address":"403 Brighton Road",
    "sg:city":"Lancing",
    "sg:classifiers":[
        {
            "category":"Fast Food",
            "type":"Food & Drink"
        }
    ],
    "sg:phone":"+44 1903 752062",
    "sg:postcode":"BN15 8JX",
    "sg:province":"West Sussex",
    "sg:tags":[
        "away",
        "take"
    ],
    "wof:name":"The Golden Palace",
    "wof:placetype":"venue"
},
  "geometry": {"coordinates":[-0.296801,50.825775],"type":"Point"}
}