{
  "type": "Feature",
  "properties": {
    "iso:country":"GB",
    "sg:address":"109 Queensway",
    "sg:city":"Orpington",
    "sg:classifiers":[
        {
            "category":"Bars & Pubs",
            "type":"Food & Drink"
        }
    ],
    "sg:phone":"+44 1689 891606",
    "sg:postcode":"BR5 1DG",
    "sg:province":"Kent",
    "sg:tags":[
        "pubs",
        "inn"
    ],
    "wof:name":"Sovereign of the Seas",
    "wof:placetype":"venue"
},
  "geometry": {"coordinates":[0.072204,51.389206],"type":"Point"}
}