{
  "type": "Feature",
  "properties": {
    "iso:country":"GB",
    "sg:address":"36 Newbound Mill La Pleasley",
    "sg:city":"Mansfield",
    "sg:classifiers":[
        {
            "category":"Health Services",
            "subcategory":"Podiatrist",
            "type":"Services"
        }
    ],
    "sg:phone":"+44 1623 810587",
    "sg:postcode":"NG19 7PT",
    "sg:province":"Derbyshire",
    "sg:tags":[
        "podiatrists",
        "chiropodist"
    ],
    "wof:name":"Kim Burton",
    "wof:placetype":"venue"
},
  "geometry": {"coordinates":[-1.250721,53.171227],"type":"Point"}
}