{
  "type": "Feature",
  "properties": {
    "iso:country":"GB",
    "sg:address":"Gorton Retail Market, Gortoncross Street",
    "sg:city":"Manchester",
    "sg:classifiers":[
        {
            "category":"Farming",
            "subcategory":"Fish & Marine Products",
            "type":"Manufacturing & Wholesale Goods"
        }
    ],
    "sg:phone":"+44 161 223 0911",
    "sg:postcode":"M18 8LD",
    "sg:province":"Greater Manchester",
    "sg:tags":[
        "fishmonger"
    ],
    "wof:name":"Charlie Hills Quality Fish",
    "wof:placetype":"venue"
},
  "geometry": {"coordinates":[-2.1561288834,53.4686660767],"type":"Point"}
}