{
  "type": "Feature",
  "properties": {
    "iso:country":"GB",
    "sg:address":"15 Greville Av",
    "sg:city":"South Croydon",
    "sg:classifiers":[
        {
            "category":"Professional",
            "type":"Services"
        }
    ],
    "sg:phone":"+44 20 8651 5195",
    "sg:postcode":"CR2 8NN",
    "sg:province":"Surrey",
    "sg:tags":[
        "shopfitters"
    ],
    "wof:name":"Redfearn Building Services",
    "wof:placetype":"venue"
},
  "geometry": {"coordinates":[-0.0520039983,51.3433761597],"type":"Point"}
}