{
  "type": "Feature",
  "properties": {
    "iso:country":"GB",
    "sg:address":"Rivington, Dexter Lane, Hurley",
    "sg:city":"Atherstone",
    "sg:classifiers":[
        {
            "category":"Professional",
            "subcategory":"Engineering",
            "type":"Services"
        }
    ],
    "sg:postcode":"CV9 2JG",
    "sg:province":"Leicestershire",
    "sg:tags":[
        "contractor",
        "electrical",
        "engineer"
    ],
    "wof:name":"Barry William Robinson",
    "wof:placetype":"venue"
},
  "geometry": {"coordinates":[-1.644608,52.561119],"type":"Point"}
}