{
  "type": "Feature",
  "properties": {
    "iso:country":"GB",
    "sg:address":"Unit 5 Garth Works, Taffs Well",
    "sg:city":"Pontypridd",
    "sg:classifiers":[
        {
            "category":"Taxi",
            "type":"Transportation"
        }
    ],
    "sg:phone":"+44 1443 404040",
    "sg:postcode":"CF15 7RN",
    "sg:province":"Caerphilly",
    "sg:tags":[
        "mini",
        "cab"
    ],
    "wof:name":"Ponty Cabs",
    "wof:placetype":"venue"
},
  "geometry": {"coordinates":[-3.26715,51.543541],"type":"Point"}
}