{
  "type": "Feature",
  "properties": {
    "addr:full":"6 Lime Gro Woking Surrey GU22 9PW",
    "addr:housenumber":"6",
    "addr:postcode":"gu22 9pw",
    "addr:street":"Lime Gro",
    "iso:country":"GB",
    "sg:address":"6 Lime Gro",
    "sg:city":"Woking",
    "sg:classifiers":[
        {
            "category":"Shopping",
            "subcategory":"Musical Instruments",
            "type":"Retail Goods"
        }
    ],
    "sg:phone":"+44 1483 755944",
    "sg:postcode":"GU22 9PW",
    "sg:province":"Surrey",
    "wof:name":"Rosendean Fine Guitars",
    "wof:placetype":"venue"
},
  "geometry": {"coordinates":[-0.5548419952,51.3010253906],"type":"Point"}
}