{
  "type": "Feature",
  "properties": {
    "iso:country":"GB",
    "sg:address":"Tinto House, Station Road",
    "sg:city":"South Molton",
    "sg:classifiers":[
        {
            "category":"Professional",
            "subcategory":"Art Services",
            "type":"Services"
        }
    ],
    "sg:postcode":"EX36 3LL",
    "sg:province":"Devon",
    "sg:tags":[
        "graphic",
        "designer"
    ],
    "wof:name":"Image Marketing",
    "wof:placetype":"venue"
},
  "geometry": {"coordinates":[-3.8304219246,51.0190391541],"type":"Point"}
}