{
  "type": "Feature",
  "properties": {
    "addr:full":"Trenchard Drive, Llanishen Cardiff Cardiff CF14 5LJ",
    "addr:postcode":"cf14 5lj",
    "addr:street":"Trenchard Drive",
    "iso:country":"GB",
    "sg:address":"Trenchard Drive, Llanishen",
    "sg:city":"Cardiff",
    "sg:classifiers":[
        {
            "category":"Social Services",
            "type":"Services"
        }
    ],
    "sg:phone":"+44 29 2074 7055",
    "sg:postcode":"CF14 5LJ",
    "sg:province":"Cardiff",
    "wof:name":"Iorwerth Jones Resource Centre",
    "wof:placetype":"venue"
},
  "geometry": {"coordinates":[-3.195524931,51.5282478333],"type":"Point"}
}