{
  "type": "Feature",
  "properties": {
    "addr:full":"Unit 5, Rivermead Newbury Berkshire RG19 4EP",
    "addr:housenumber":"unit 5",
    "addr:postcode":"rg19 4ep",
    "iso:country":"GB",
    "sg:address":"Unit 5, Rivermead",
    "sg:city":"Newbury",
    "sg:classifiers":[
        {
            "category":"Manufacturing",
            "subcategory":"Electronics",
            "type":"Manufacturing & Wholesale Goods"
        }
    ],
    "sg:postcode":"RG19 4EP",
    "sg:province":"Berkshire",
    "sg:tags":[
        "computer",
        "-",
        "printed",
        "circuit"
    ],
    "wof:name":"Sigtec Europe Ltd.",
    "wof:placetype":"venue"
},
  "geometry": {"coordinates":[-1.2281689644,51.399230957],"type":"Point"}
}