{
  "type": "Feature",
  "properties": {
    "iso:country":"GB",
    "sg:address":"15 Whitehall Rd",
    "sg:city":"Halesowen",
    "sg:classifiers":[
        {
            "category":"Autos & Motor Vehicles",
            "subcategory":"Automobile Sales",
            "type":"Retail Goods"
        }
    ],
    "sg:phone":"+44 121 602 2118",
    "sg:postcode":"B63 3JR",
    "sg:province":"West Midlands",
    "sg:tags":[
        "commercial"
    ],
    "wof:name":"D C Car Finance",
    "wof:placetype":"venue"
},
  "geometry": {"coordinates":[-2.048679,52.452042],"type":"Point"}
}