{
  "type": "Feature",
  "properties": {
    "addr:full":"7 Luthers Close, Kelvedon Hatch Brentwood Essex CM15 0DJ",
    "addr:housenumber":"7",
    "addr:postcode":"kelvedon;cm15 0dj",
    "addr:street":"Luthers Close",
    "iso:country":"GB",
    "sg:address":"7 Luthers Close, Kelvedon Hatch",
    "sg:city":"Brentwood",
    "sg:classifiers":[
        {
            "category":"Building & Trades",
            "subcategory":"Landscaping Services",
            "type":"Services"
        }
    ],
    "sg:phone":"+44 1277 373225",
    "sg:postcode":"CM15 0DJ",
    "sg:province":"Essex",
    "sg:tags":[
        "gardening"
    ],
    "wof:name":"Keith Geoffrey Nickels",
    "wof:placetype":"venue"
},
  "geometry": {"coordinates":[0.2709470093,51.6667785645],"type":"Point"}
}