{
  "type": "Feature",
  "properties": {
    "addr:full":"Unit 4 Lyons Road Manchester Cheshire M17 1RN",
    "addr:housenumber":"unit 4",
    "addr:postcode":"m17 1rn",
    "addr:street":"Lyons Road",
    "iso:country":"GB",
    "sg:address":"Unit 4 Lyons Road",
    "sg:city":"Manchester",
    "sg:classifiers":[
        {
            "category":"Manufacturing",
            "subcategory":"Wood Products",
            "type":"Manufacturing & Wholesale Goods"
        }
    ],
    "sg:phone":"+44 161 877 8668",
    "sg:postcode":"M17 1RN",
    "sg:province":"Cheshire",
    "sg:tags":[
        "packaging",
        "crate",
        "pallets"
    ],
    "wof:name":"Avocet Vk Ltd.",
    "wof:placetype":"venue"
},
  "geometry": {"coordinates":[-2.3275790215,53.4725532532],"type":"Point"}
}