{
  "type": "Feature",
  "properties": {
    "addr:full":"Wolverley Kidderminster Staffordshire DY11 5TH",
    "addr:postcode":"dy11 5th",
    "iso:country":"GB",
    "sg:address":"Wolverley",
    "sg:city":"Kidderminster",
    "sg:classifiers":[
        {
            "category":"Health Services",
            "subcategory":"Doctor",
            "type":"Services"
        }
    ],
    "sg:phone":"+44 1562 850800",
    "sg:postcode":"DY11 5TH",
    "sg:province":"Staffordshire",
    "sg:tags":[
        "practitioners"
    ],
    "wof:name":"The Surgery",
    "wof:placetype":"venue"
},
  "geometry": {"coordinates":[-2.2534599304,52.4111099243],"type":"Point"}
}