{
  "type": "Feature",
  "properties": {
    "addr:full":"17 Friday Street Minehead Somerset TA24 5UB",
    "addr:housenumber":"17",
    "addr:postcode":"ta24 5ub",
    "addr:street":"Friday Street",
    "iso:country":"GB",
    "sg:address":"17 Friday Street",
    "sg:city":"Minehead",
    "sg:classifiers":[
        {
            "category":"Landmark",
            "subcategory":"Tourist Information",
            "type":"Public Place"
        },
        {
            "category":"Government",
            "subcategory":"Office",
            "type":"Public Place"
        }
    ],
    "sg:phone":"+44 1643 702624",
    "sg:postcode":"TA24 5UB",
    "sg:province":"Somerset",
    "sg:tags":[
        "local"
    ],
    "wof:name":"Tourist Information Centre",
    "wof:placetype":"venue"
},
  "geometry": {"coordinates":[-3.4781730175,51.2047729492],"type":"Point"}
}