{
  "type": "Feature",
  "properties": {
    "iso:country":"GB",
    "sg:address":"Cornerways, Frost Morchard Bishop",
    "sg:city":"Crediton",
    "sg:classifiers":[
        {
            "category":"Manufacturing",
            "subcategory":"Aerospace",
            "type":"Manufacturing & Wholesale Goods"
        }
    ],
    "sg:phone":"+44 1363 877203",
    "sg:postcode":"EX17 6NZ",
    "sg:province":"Devon",
    "sg:tags":[
        "aircraft",
        "furnishing",
        "fitting"
    ],
    "wof:name":"Nolan Enterprises Ltd.",
    "wof:placetype":"venue"
},
  "geometry": {"coordinates":[-3.748311,50.854126],"type":"Point"}
}