{
  "type": "Feature",
  "properties": {
    "addr:full":"1 The Green, Dunston Lincoln Lincolnshire LN4 2HE",
    "addr:housenumber":"1",
    "addr:postcode":"ln4 2he",
    "addr:street":"The Green",
    "iso:country":"GB",
    "sg:address":"1 The Green, Dunston",
    "sg:city":"Lincoln",
    "sg:classifiers":[
        {
            "category":"Farming",
            "subcategory":"Farm",
            "type":"Manufacturing & Wholesale Goods"
        },
        {
            "category":"Home & Garden",
            "subcategory":"Kitchen Supply",
            "type":"Retail Goods"
        }
    ],
    "sg:phone":"+44 1526 322673",
    "sg:postcode":"LN4 2HE",
    "sg:province":"Lincolnshire",
    "sg:tags":[
        "equipment",
        "agricultural",
        "catering"
    ],
    "wof:name":"Storey & Milburn",
    "wof:placetype":"venue"
},
  "geometry": {"coordinates":[-0.4070959985,53.1529884338],"type":"Point"}
}