{
  "type": "Feature",
  "properties": {
    "addr:full":"11 Spring Street London Greater London W2 3RA",
    "addr:housenumber":"11",
    "addr:postcode":"w2 3ra",
    "addr:street":"Spring Street",
    "iso:country":"GB",
    "sg:address":"11 Spring Street",
    "sg:city":"London",
    "sg:classifiers":[
        {
            "category":"Home & Garden",
            "subcategory":"Carpets & Floor Coverings",
            "type":"Retail Goods"
        }
    ],
    "sg:phone":"+44 20 7262 1153",
    "sg:postcode":"W2 3RA",
    "sg:province":"Greater London",
    "sg:tags":[
        "rug"
    ],
    "wof:name":"Franses Conservation",
    "wof:placetype":"venue"
},
  "geometry": {"coordinates":[-0.175819,51.514606],"type":"Point"}
}