{
  "type": "Feature",
  "properties": {
    "addr:full":"102 Elgin Avenue, Maida Vale London Greater London W9 2HD",
    "addr:housenumber":"102",
    "addr:postcode":"w9 2hd",
    "addr:street":"Elgin Avenue",
    "iso:country":"GB",
    "sg:address":"102 Elgin Avenue, Maida Vale",
    "sg:city":"London",
    "sg:classifiers":[
        {
            "category":"Real Estate",
            "subcategory":"Real Estate Agent",
            "type":"Services"
        }
    ],
    "sg:phone":"+44 20 7286 6207",
    "sg:postcode":"W9 2HD",
    "sg:province":"Greater London",
    "wof:name":"Eagerstart Properties Ltd.",
    "wof:placetype":"venue"
},
  "geometry": {"coordinates":[-0.194496,51.525963],"type":"Point"}
}