{
  "type": "Feature",
  "properties": {
    "iso:country":"GB",
    "sg:address":"Unit 14, Sundial House, Common Lane",
    "sg:city":"Warrington",
    "sg:classifiers":[
        {
            "category":"Home & Garden",
            "subcategory":"Household Appliances",
            "type":"Retail Goods"
        },
        {
            "category":"Shopping",
            "subcategory":"Comic Books",
            "type":"Retail Goods"
        }
    ],
    "sg:phone":"+44 1925 767017",
    "sg:postcode":"WA3 4EH",
    "sg:province":"Cheshire",
    "sg:tags":[
        "electrical",
        "jeweller",
        "domestic"
    ],
    "wof:name":"Sundial Jewellery",
    "wof:placetype":"venue"
},
  "geometry": {"coordinates":[-2.532294,53.457764],"type":"Point"}
}