{
  "type": "Feature",
  "properties": {
    "iso:country":"GB",
    "sg:address":"13 Bernard Rd",
    "sg:city":"Brighton",
    "sg:classifiers":[
        {
            "category":"Professional",
            "subcategory":"Art Services",
            "type":"Services"
        }
    ],
    "sg:phone":"+44 1273 602933",
    "sg:postcode":"BN2 3ER",
    "sg:province":"East Sussex",
    "sg:tags":[
        "photographer"
    ],
    "wof:name":"Robert Wilkinson",
    "wof:placetype":"venue"
},
  "geometry": {"coordinates":[-0.119891,50.83176],"type":"Point"}
}