{
  "type": "Feature",
  "properties": {
    "addr:full":"55 Orchard St Weston Super Mare Somerset BS23 1RJ",
    "addr:housenumber":"55",
    "addr:postcode":"bs23 1rj",
    "addr:street":"Orchard St",
    "iso:country":"GB",
    "sg:address":"55 Orchard St",
    "sg:city":"Weston Super Mare",
    "sg:classifiers":[
        {
            "category":"Retail",
            "subcategory":"Laundry & Dry Cleaning",
            "type":"Services"
        }
    ],
    "sg:phone":"+44 1934 622938",
    "sg:postcode":"BS23 1RJ",
    "sg:province":"Somerset",
    "sg:tags":[
        "alteration"
    ],
    "wof:name":"A & P Cleaners",
    "wof:placetype":"venue"
},
  "geometry": {"coordinates":[-2.976019,51.34938],"type":"Point"}
}