{
  "type": "Feature",
  "properties": {
    "iso:country":"GB",
    "sg:address":"8-10 St Georges Square",
    "sg:city":"Hebden Bridge",
    "sg:classifiers":[
        {
            "category":"Shopping",
            "subcategory":"Clothing, Apparel, & Fashions",
            "type":"Retail Goods"
        }
    ],
    "sg:phone":"+44 1422 843963",
    "sg:postcode":"HX7 8ET",
    "sg:province":"West Yorkshire",
    "sg:tags":[
        "shop"
    ],
    "wof:name":"The Shop in the Square",
    "wof:placetype":"venue"
},
  "geometry": {"coordinates":[-2.0124819279,53.74193573],"type":"Point"}
}