{
  "type": "Feature",
  "properties": {
    "iso:country":"GB",
    "sg:address":"222 Tankerton Road",
    "sg:city":"Whitstable",
    "sg:classifiers":[
        {
            "category":"Building & Trades",
            "subcategory":"Construction",
            "type":"Services"
        }
    ],
    "sg:phone":"+44 1227 275227",
    "sg:postcode":"CT5 2AT",
    "sg:province":"Kent",
    "sg:tags":[
        "builder"
    ],
    "wof:name":"Blackmore & Co. Ltd.",
    "wof:placetype":"venue"
},
  "geometry": {"coordinates":[1.0508370399,51.3636016846],"type":"Point"}
}