{
  "type": "Feature",
  "properties": {
    "iso:country":"GB",
    "sg:address":"81a Hitchin Road",
    "sg:city":"Arlesey",
    "sg:classifiers":[
        {
            "category":"Home & Garden",
            "subcategory":"Garden Supply",
            "type":"Retail Goods"
        }
    ],
    "sg:phone":"+44 1462 835000",
    "sg:postcode":"SG15 6RT",
    "sg:province":"Bedfordshire",
    "sg:tags":[
        "sand",
        "gravel"
    ],
    "wof:name":"Materials Movement Ltd.",
    "wof:placetype":"venue"
},
  "geometry": {"coordinates":[-0.266909,52.000069],"type":"Point"}
}