{
  "type": "Feature",
  "properties": {
    "addr:full":"Unit 2 Barwick Road, Garforth Leeds North Yorkshire LS25 1QF",
    "addr:housenumber":"unit 2",
    "addr:postcode":"ls25 1qf",
    "addr:street":"Barwick Road",
    "iso:country":"GB",
    "sg:address":"Unit 2 Barwick Road, Garforth",
    "sg:city":"Leeds",
    "sg:classifiers":[
        {
            "category":"Retail",
            "subcategory":"Auto Repair",
            "type":"Services"
        }
    ],
    "sg:phone":"+44 113 232 0343",
    "sg:postcode":"LS25 1QF",
    "sg:province":"North Yorkshire",
    "sg:tags":[
        "body",
        "car"
    ],
    "wof:name":"D Driver Vehicle Maintenance",
    "wof:placetype":"venue"
},
  "geometry": {"coordinates":[-1.388939023,53.7988853455],"type":"Point"}
}