{
  "type": "Feature",
  "properties": {
    "addr:full":"1 High Street, Meadowhall Centre Sheffield South Yorkshire S9 1EP",
    "addr:housenumber":"1",
    "addr:postcode":"s9 1ep",
    "addr:street":"High Street",
    "iso:country":"GB",
    "sg:address":"1 High Street, Meadowhall Centre",
    "sg:city":"Sheffield",
    "sg:classifiers":[
        {
            "category":"Food & Beverages",
            "subcategory":"Candy",
            "type":"Retail Goods"
        }
    ],
    "sg:phone":"+44 114 256 8071",
    "sg:postcode":"S9 1EP",
    "sg:province":"South Yorkshire",
    "sg:tags":[
        "confectioner"
    ],
    "wof:name":"Thorntons Plc",
    "wof:placetype":"venue"
},
  "geometry": {"coordinates":[-1.395641,53.411278],"type":"Point"}
}