{
  "type": "Feature",
  "properties": {
    "iso:country":"GB",
    "sg:address":"7 Birchs Clo, Hockliffe",
    "sg:city":"Leighton Buzzard",
    "sg:classifiers":[
        {
            "category":"Building & Trades",
            "subcategory":"Construction",
            "type":"Services"
        }
    ],
    "sg:postcode":"LU7 9LU",
    "sg:province":"Bedfordshire",
    "sg:tags":[
        "supplier",
        "installers",
        "cladding"
    ],
    "wof:name":"D W Cladding",
    "wof:placetype":"venue"
},
  "geometry": {"coordinates":[-0.585949,51.932377],"type":"Point"}
}