{
  "type": "Feature",
  "properties": {
    "addr:full":"41 South Street, Milnathort Kinross Clackmannanshire KY13 9XB",
    "addr:housenumber":"41",
    "addr:postcode":"ky13 9xb",
    "addr:street":"South Street",
    "iso:country":"GB",
    "sg:address":"41 South Street, Milnathort",
    "sg:city":"Kinross",
    "sg:classifiers":[
        {
            "category":"Food & Beverages",
            "subcategory":"Bakery",
            "type":"Retail Goods"
        }
    ],
    "sg:postcode":"KY13 9XB",
    "sg:province":"Clackmannanshire",
    "sg:tags":[
        "baker"
    ],
    "wof:name":"L Walker",
    "wof:placetype":"venue"
},
  "geometry": {"coordinates":[-3.420888,56.225624],"type":"Point"}
}