{
  "type": "Feature",
  "properties": {
    "iso:country":"GB",
    "sg:address":"41 South Street, Milnathort",
    "sg:city":"Kinross",
    "sg:classifiers":[
        {
            "category":"Food & Beverages",
            "subcategory":"Bakery",
            "type":"Retail Goods"
        }
    ],
    "sg:postcode":"KY13 9XB",
    "sg:province":"Clackmannanshire",
    "sg:tags":[
        "baker"
    ],
    "wof:name":"L Walker",
    "wof:placetype":"venue"
},
  "geometry": {"coordinates":[-3.420888,56.225624],"type":"Point"}
}