{
  "type": "Feature",
  "properties": {
    "addr:full":"Bramleys, Far Grn Dursley Gloucestershire GL11 5EL",
    "addr:postcode":"gl11 5el",
    "addr:street":"Bramleys Far Grn",
    "iso:country":"GB",
    "sg:address":"Bramleys, Far Grn",
    "sg:city":"Dursley",
    "sg:classifiers":[
        {
            "category":"Shopping",
            "subcategory":"Computers & Home Electronics",
            "type":"Retail Goods"
        }
    ],
    "sg:postcode":"GL11 5EL",
    "sg:province":"Gloucestershire",
    "sg:tags":[
        "consumables"
    ],
    "wof:name":"Simms Business Forms",
    "wof:placetype":"venue"
},
  "geometry": {"coordinates":[-2.365212,51.693291],"type":"Point"}
}