{
  "type": "Feature",
  "properties": {
    "addr:full":"66 Wigmore Street West End Greater London W1H 0HQ",
    "addr:housenumber":"66",
    "addr:postcode":"w1h 0hq",
    "addr:street":"Wigmore Street",
    "iso:country":"GB",
    "sg:address":"66 Wigmore Street",
    "sg:city":"West End",
    "sg:classifiers":[
        {
            "category":"Wholesale",
            "subcategory":"Non-durable Goods",
            "type":"Manufacturing & Wholesale Goods"
        }
    ],
    "sg:postcode":"W1H 0HQ",
    "sg:province":"Greater London",
    "sg:tags":[
        "carry",
        "cash"
    ],
    "wof:name":"Seidis Ltd",
    "wof:placetype":"venue"
},
  "geometry": {"coordinates":[-0.15961,51.516178],"type":"Point"}
}