{
  "type": "Feature",
  "properties": {
    "addr:full":"9 Blairbeth Terr Glasgow Glasgow City G73 4JB",
    "addr:housenumber":"9",
    "addr:postcode":"g73 4jb",
    "addr:street":"Blairbeth Terr",
    "iso:country":"GB",
    "sg:address":"9 Blairbeth Terr",
    "sg:city":"Glasgow",
    "sg:classifiers":[
        {
            "category":"Manufacturing",
            "subcategory":"Signs",
            "type":"Manufacturing & Wholesale Goods"
        }
    ],
    "sg:phone":"+44 141 774 0487",
    "sg:postcode":"G73 4JB",
    "sg:province":"Glasgow City",
    "sg:tags":[
        "nameplate"
    ],
    "wof:name":"Bob McMillan",
    "wof:placetype":"venue"
},
  "geometry": {"coordinates":[-4.211648941,55.8159751892],"type":"Point"}
}