{
  "type": "Feature",
  "properties": {
    "addr:full":"3 Market Pl Tetbury Gloucestershire GL8 8DA",
    "addr:housenumber":"3",
    "addr:postcode":"gl8 8da",
    "addr:street":"Market Pl",
    "iso:country":"GB",
    "sg:address":"3 Market Pl",
    "sg:city":"Tetbury",
    "sg:classifiers":[
        {
            "category":"Food & Beverages",
            "subcategory":"Groceries & Convenience Stores",
            "type":"Retail Goods"
        }
    ],
    "sg:postcode":"GL8 8DA",
    "sg:province":"Gloucestershire",
    "wof:name":"Ponting,Edward B,",
    "wof:placetype":"venue"
},
  "geometry": {"coordinates":[-2.159494,51.63652],"type":"Point"}
}