{
  "type": "Feature",
  "properties": {
    "addr:full":"6 Southend Road Grays Essex RM17 5NH",
    "addr:housenumber":"6",
    "addr:postcode":"rm17 5nh",
    "addr:street":"Southend Road",
    "iso:country":"GB",
    "sg:address":"6 Southend Road",
    "sg:city":"Grays",
    "sg:classifiers":[
        {
            "category":"Food & Beverages",
            "subcategory":"Liquor & Beverages",
            "type":"Retail Goods"
        }
    ],
    "sg:phone":"+44 1375 372526",
    "sg:postcode":"RM17 5NH",
    "sg:province":"Essex",
    "sg:tags":[
        "beer",
        "spirit",
        "wines"
    ],
    "wof:name":"Nabco Off Licence",
    "wof:placetype":"venue"
},
  "geometry": {"coordinates":[0.335817,51.483315],"type":"Point"}
}