{
  "type": "Feature",
  "properties": {
    "addr:full":"Trinity Court, Albion Street, Crowland Peterborough Cambridgeshire PE6 0EA",
    "addr:postcode":"pe6 0ea",
    "addr:street":"Trinity Court Albion Street",
    "iso:country":"GB",
    "sg:address":"Trinity Court, Albion Street, Crowland",
    "sg:city":"Peterborough",
    "sg:classifiers":[
        {
            "category":"Social Services",
            "subcategory":"Adult Care",
            "type":"Services"
        },
        {
            "category":"Government",
            "subcategory":"Office",
            "type":"Public Place"
        }
    ],
    "sg:phone":"+44 1733 210505",
    "sg:postcode":"PE6 0EA",
    "sg:province":"Cambridgeshire",
    "sg:tags":[
        "housing",
        "local",
        "sheltered"
    ],
    "wof:name":"West Street Sheltered Housing",
    "wof:placetype":"venue"
},
  "geometry": {"coordinates":[-0.169244,52.673779],"type":"Point"}
}