{
  "type": "Feature",
  "properties": {
    "addr:full":"2 Bell Street, Wellington Telford Shropshire TF1 1LS",
    "addr:housenumber":"2",
    "addr:postcode":"tf1 1ls",
    "addr:street":"Bell Street",
    "iso:country":"GB",
    "sg:address":"2 Bell Street, Wellington",
    "sg:city":"Telford",
    "sg:classifiers":[
        {
            "category":"Shopping",
            "subcategory":"Music",
            "type":"Retail Goods"
        }
    ],
    "sg:phone":"+44 1952 244845",
    "sg:postcode":"TF1 1LS",
    "sg:province":"Shropshire",
    "sg:tags":[
        "record",
        "tape",
        "cd"
    ],
    "wof:name":"Langland Records",
    "wof:placetype":"venue"
},
  "geometry": {"coordinates":[-2.5176370144,52.7002067566],"type":"Point"}
}