{
  "type": "Feature",
  "properties": {
    "iso:country":"GB",
    "sg:address":"31 Little London",
    "sg:city":"Chichester",
    "sg:classifiers":[
        {
            "category":"Health Services",
            "subcategory":"Dentist",
            "type":"Services"
        }
    ],
    "sg:phone":"+44 1243 782878",
    "sg:postcode":"PO19 1PL",
    "sg:province":"West Sussex",
    "wof:name":"Little London Dental Surgery",
    "wof:placetype":"venue"
},
  "geometry": {"coordinates":[-0.775835,50.836285],"type":"Point"}
}