{
  "type": "Feature",
  "properties": {
    "iso:country":"GB",
    "sg:address":"Unit 5, Tarvin Sands Industries, Barrow Lane",
    "sg:city":"Chester",
    "sg:classifiers":[
        {
            "category":"Professional",
            "subcategory":"Engineering",
            "type":"Services"
        }
    ],
    "sg:phone":"+44 1829 740992",
    "sg:postcode":"CH3 8JF",
    "sg:province":"Cheshire",
    "sg:tags":[
        "precision",
        "engineer"
    ],
    "wof:name":"R A Chiltern",
    "wof:placetype":"venue"
},
  "geometry": {"coordinates":[-2.76428,53.20433],"type":"Point"}
}