{
  "type": "Feature",
  "properties": {
    "iso:country":"GB",
    "sg:address":"11 High Street",
    "sg:city":"Pinner",
    "sg:classifiers":[
        {
            "category":"Restaurant",
            "type":"Food & Drink"
        }
    ],
    "sg:phone":"+44 20 8866 0286",
    "sg:postcode":"HA5 5PJ",
    "sg:province":"Greater London",
    "sg:tags":[
        "french"
    ],
    "wof:name":"Friends Restaurant",
    "wof:placetype":"venue"
},
  "geometry": {"coordinates":[-0.381605,51.594112],"type":"Point"}
}