{
  "type": "Feature",
  "properties": {
    "addr:full":"1204 New Chester Rd, Eastham Wirral Cheshire CH62 9AE",
    "addr:housenumber":"1204",
    "addr:postcode":"ch62 9ae",
    "addr:street":"New Chester Rd",
    "iso:country":"GB",
    "sg:address":"1204 New Chester Rd, Eastham",
    "sg:city":"Wirral",
    "sg:classifiers":[
        {
            "category":"Shopping",
            "subcategory":"News",
            "type":"Retail Goods"
        }
    ],
    "sg:phone":"+44 151 327 1005",
    "sg:postcode":"CH62 9AE",
    "sg:province":"Cheshire",
    "sg:tags":[
        "newsagent"
    ],
    "wof:name":"Dillons One-Stop",
    "wof:placetype":"venue"
},
  "geometry": {"coordinates":[-2.96531,53.312965],"type":"Point"}
}