{
  "type": "Feature",
  "properties": {
    "iso:country":"GB",
    "sg:address":"202 Lawrence Hill",
    "sg:city":"Bristol",
    "sg:classifiers":[
        {
            "category":"Shopping",
            "type":"Retail Goods"
        }
    ],
    "sg:phone":"+44 117 955 9559",
    "sg:postcode":"BS5 0DR",
    "sg:province":"City of Bristol",
    "sg:tags":[
        "part",
        "accessory"
    ],
    "wof:name":"VW Dreammachine",
    "wof:placetype":"venue"
},
  "geometry": {"coordinates":[-2.565626,51.457874],"type":"Point"}
}