{
  "type": "Feature",
  "properties": {
    "addr:full":"Oxford Street Wellingborough Northamptonshire NN8 4JG",
    "addr:postcode":"nn8 4jg",
    "addr:street":"Oxford Street",
    "iso:country":"GB",
    "sg:address":"Oxford Street",
    "sg:city":"Wellingborough",
    "sg:classifiers":[
        {
            "category":"Autos & Motor Vehicles",
            "subcategory":"Auto Supplies",
            "type":"Retail Goods"
        }
    ],
    "sg:phone":"+44 1933 276316",
    "sg:postcode":"NN8 4JG",
    "sg:province":"Northamptonshire",
    "sg:tags":[
        "exhaust",
        "absorber",
        "shock"
    ],
    "wof:name":"Kwik-Fit",
    "wof:placetype":"venue"
},
  "geometry": {"coordinates":[-0.695274,52.30154],"type":"Point"}
}