{
  "type": "Feature",
  "properties": {
    "addr:full":"14 London Road Brighton East Sussex BN1 4JA",
    "addr:housenumber":"14",
    "addr:postcode":"bn1 4ja",
    "addr:street":"London Road",
    "iso:country":"GB",
    "sg:address":"14 London Road",
    "sg:city":"Brighton",
    "sg:classifiers":[
        {
            "category":"Travel",
            "subcategory":"Travel Agent",
            "type":"Entertainment"
        }
    ],
    "sg:phone":"+44 1273 570070",
    "sg:postcode":"BN1 4JA",
    "sg:province":"East Sussex",
    "wof:name":"Lunn Poly Ltd.",
    "wof:placetype":"venue"
},
  "geometry": {"coordinates":[-0.1362459958,50.83045578],"type":"Point"}
}