{
  "type": "Feature",
  "properties": {
    "addr:full":"600 Windmillhill Street Motherwell North Lanarkshire ML1 2HN",
    "addr:housenumber":"600",
    "addr:postcode":"ml1 2hn",
    "addr:street":"Windmillhill Street",
    "iso:country":"GB",
    "sg:address":"600 Windmillhill Street",
    "sg:city":"Motherwell",
    "sg:classifiers":[
        {
            "category":"Social Services",
            "type":"Services"
        }
    ],
    "sg:phone":"+44 1698 483500",
    "sg:postcode":"ML1 2HN",
    "sg:province":"North Lanarkshire",
    "sg:tags":[
        "benefit",
        "agency"
    ],
    "wof:name":"Department of Health & Social Services (The",
    "wof:placetype":"venue"
},
  "geometry": {"coordinates":[-3.9774990082,55.781791687],"type":"Point"}
}