{
  "type": "Feature",
  "properties": {
    "iso:country":"GB",
    "sg:address":"Stanton Service Station, Station Road, Stoney Stanton",
    "sg:city":"Leicester",
    "sg:classifiers":[
        {
            "category":"Retail",
            "subcategory":"Auto Repair",
            "type":"Services"
        }
    ],
    "sg:postcode":"LE9 6LY",
    "sg:province":"Leicestershire",
    "sg:tags":[
        "modification",
        "garage"
    ],
    "wof:name":"A Peberdy",
    "wof:placetype":"venue"
},
  "geometry": {"coordinates":[-1.2797,52.548222],"type":"Point"}
}