{
  "type": "Feature",
  "properties": {
    "addr:full":"Kinfisher House, Auld Mart Road Kinross Clackmannanshire KY13 9FR",
    "addr:postcode":"ky13 9fr",
    "addr:street":"Road",
    "iso:country":"GB",
    "sg:address":"Kinfisher House, Auld Mart Road",
    "sg:city":"Kinross",
    "sg:classifiers":[
        {
            "category":"Professional",
            "subcategory":"Business Services",
            "type":"Services"
        }
    ],
    "sg:phone":"+44 1577 861123",
    "sg:postcode":"KY13 9FR",
    "sg:province":"Clackmannanshire",
    "sg:tags":[
        "holding"
    ],
    "wof:name":"Thomas Findlay (Holdings) Ltd.",
    "wof:placetype":"venue"
},
  "geometry": {"coordinates":[-3.421495,56.221581],"type":"Point"}
}