{
  "type": "Feature",
  "properties": {
    "iso:country":"GB",
    "sg:address":"1 Mendip Way",
    "sg:city":"Luton",
    "sg:classifiers":[
        {
            "category":"Building & Trades",
            "subcategory":"Construction",
            "type":"Services"
        }
    ],
    "sg:phone":"+44 1582 575694",
    "sg:postcode":"LU3 3JJ",
    "sg:province":"Bedfordshire",
    "sg:tags":[
        "builder"
    ],
    "wof:name":"D J Cleary",
    "wof:placetype":"venue"
},
  "geometry": {"coordinates":[-0.470189,51.923565],"type":"Point"}
}