{
  "type": "Feature",
  "properties": {
    "iso:country":"GB",
    "sg:address":"Twankhams Alley, 160 High Street",
    "sg:city":"Epping",
    "sg:classifiers":[
        {
            "category":"Professional",
            "subcategory":"Computer Services",
            "type":"Services"
        }
    ],
    "sg:postcode":"CM16 4AQ",
    "sg:province":"Essex",
    "sg:tags":[
        "system",
        "software"
    ],
    "wof:name":"Multicard Ltd",
    "wof:placetype":"venue"
},
  "geometry": {"coordinates":[0.111659,51.699299],"type":"Point"}
}