{
  "type": "Feature",
  "properties": {
    "iso:country":"GB",
    "sg:address":"12 Ivor Place",
    "sg:city":"London",
    "sg:classifiers":[
        {
            "category":"Banks & Credit Unions",
            "subcategory":"Bank",
            "type":"Services"
        }
    ],
    "sg:phone":"+44 20 7262 9033",
    "sg:postcode":"NW1 6HS",
    "sg:province":"Greater London",
    "sg:tags":[
        "broker",
        "mortgage"
    ],
    "wof:name":"D & J Watson",
    "wof:placetype":"venue"
},
  "geometry": {"coordinates":[-0.161972,51.524303],"type":"Point"}
}