{
  "type": "Feature",
  "properties": {
    "iso:country":"GB",
    "sg:address":"Nixon Street, Castleton",
    "sg:city":"Rochdale",
    "sg:classifiers":[
        {
            "category":"Autos & Motor Vehicles",
            "subcategory":"Automobile Sales",
            "type":"Retail Goods"
        }
    ],
    "sg:phone":"+44 870 600 8800",
    "sg:postcode":"OL11 3JW",
    "sg:province":"Lancashire",
    "sg:tags":[
        "car"
    ],
    "wof:name":"Carcraft of Rochdale Ltd.",
    "wof:placetype":"venue"
},
  "geometry": {"coordinates":[-2.182264,53.596718],"type":"Point"}
}