{
  "type": "Feature",
  "properties": {
    "addr:full":"Kitty Brewster Indust Est, Coniston Blyth Northumberland NE24 4RG",
    "addr:postcode":"ne24 4rg",
    "addr:street":"Indust",
    "iso:country":"GB",
    "sg:address":"Kitty Brewster Indust Est, Coniston",
    "sg:city":"Blyth",
    "sg:classifiers":[
        {
            "category":"Professional",
            "subcategory":"Testing Lab",
            "type":"Services"
        }
    ],
    "sg:phone":"+44 1670 361661",
    "sg:postcode":"NE24 4RG",
    "sg:province":"Northumberland",
    "sg:tags":[
        "laboratory"
    ],
    "wof:name":"S H Scientific",
    "wof:placetype":"venue"
},
  "geometry": {"coordinates":[-1.5537689924,55.1297149658],"type":"Point"}
}