{
  "type": "Feature",
  "properties": {
    "addr:full":"Hollingley Farm, Denton Ilkley North Yorkshire LS29 0HS",
    "addr:postcode":"ls29 0hs",
    "iso:country":"GB",
    "sg:address":"Hollingley Farm, Denton",
    "sg:city":"Ilkley",
    "sg:classifiers":[
        {
            "category":"Farming",
            "subcategory":"Livestock Farm",
            "type":"Manufacturing & Wholesale Goods"
        }
    ],
    "sg:phone":"+44 1943 608593",
    "sg:postcode":"LS29 0HS",
    "sg:province":"North Yorkshire",
    "sg:tags":[
        "others"
    ],
    "wof:name":"T A Broderick",
    "wof:placetype":"venue"
},
  "geometry": {"coordinates":[-1.783072,53.936768],"type":"Point"}
}