{
  "type": "Feature",
  "properties": {
    "addr:full":"Gelli Farm, Lloc Holywell Denbighshire CH8 8SD",
    "addr:postcode":"ch8 8sd",
    "iso:country":"GB",
    "sg:address":"Gelli Farm, Lloc",
    "sg:city":"Holywell",
    "sg:classifiers":[
        {
            "category":"Farming",
            "subcategory":"Livestock Farm",
            "type":"Manufacturing & Wholesale Goods"
        }
    ],
    "sg:phone":"+44 1745 560468",
    "sg:postcode":"CH8 8SD",
    "sg:province":"Denbighshire",
    "sg:tags":[
        "others"
    ],
    "wof:name":"R Owen & Son",
    "wof:placetype":"venue"
},
  "geometry": {"coordinates":[-3.2849590778,53.2796897888],"type":"Point"}
}