{
  "type": "Feature",
  "properties": {
    "addr:full":"Fore St, Constantine Falmouth Cornwall TR11 5AB",
    "addr:postcode":"tr11 5ab",
    "addr:street":"Fore St",
    "iso:country":"GB",
    "sg:address":"Fore St, Constantine",
    "sg:city":"Falmouth",
    "sg:classifiers":[
        {
            "category":"Bars & Pubs",
            "type":"Food & Drink"
        }
    ],
    "sg:phone":"+44 1326 340254",
    "sg:postcode":"TR11 5AB",
    "sg:province":"Cornwall",
    "sg:tags":[
        "pubs",
        "inn"
    ],
    "wof:name":"THE QUEENS ARMS",
    "wof:placetype":"venue"
},
  "geometry": {"coordinates":[-5.1887488365,50.1205558777],"type":"Point"}
}