{
  "type": "Feature",
  "properties": {
    "iso:country":"GB",
    "sg:address":"William Knox House",
    "sg:city":"Neath",
    "sg:classifiers":[
        {
            "category":"Communications",
            "subcategory":"Newspaper",
            "type":"Services"
        }
    ],
    "sg:phone":"+44 1792 324000",
    "sg:postcode":"SA10 6EL",
    "sg:province":"Neath Port Talbot",
    "sg:tags":[
        "magazine"
    ],
    "wof:name":"West Coast Publishing Ltd.",
    "wof:placetype":"venue"
},
  "geometry": {"coordinates":[-3.849109,51.652351],"type":"Point"}
}