{
  "type": "Feature",
  "properties": {
    "addr:full":"31 Curtis Road Hemel Hempstead Hertfordshire HP3 8LE",
    "addr:housenumber":"31",
    "addr:postcode":"hp3 8le",
    "addr:street":"Curtis Road",
    "iso:country":"GB",
    "sg:address":"31 Curtis Road",
    "sg:city":"Hemel Hempstead",
    "sg:classifiers":[
        {
            "category":"Professional",
            "subcategory":"Engineering",
            "type":"Services"
        }
    ],
    "sg:postcode":"HP3 8LE",
    "sg:province":"Hertfordshire",
    "sg:tags":[
        "underpinning",
        "foundation",
        "engineer"
    ],
    "wof:name":"Paul Young Structural Repairs",
    "wof:placetype":"venue"
},
  "geometry": {"coordinates":[-0.428788,51.748577],"type":"Point"}
}