{
  "type": "Feature",
  "properties": {
    "addr:full":"288b Woodham Lane, New Haw Addlestone Surrey KT15 3NT",
    "addr:housenumber":"288b",
    "addr:postcode":"kt15 3nt",
    "addr:street":"Woodham Lane",
    "iso:country":"GB",
    "sg:address":"288b Woodham Lane, New Haw",
    "sg:city":"Addlestone",
    "sg:classifiers":[
        {
            "category":"Wholesale",
            "subcategory":"Construction Materials",
            "type":"Manufacturing & Wholesale Goods"
        },
        {
            "category":"Manufacturing",
            "subcategory":"Lumber",
            "type":"Manufacturing & Wholesale Goods"
        }
    ],
    "sg:phone":"+44 1932 336086",
    "sg:postcode":"KT15 3NT",
    "sg:province":"Surrey",
    "sg:tags":[
        "merchant",
        "merchants",
        "agent",
        "glass",
        "importer",
        "timber"
    ],
    "wof:name":"The Surrey Glasshouse",
    "wof:placetype":"venue"
},
  "geometry": {"coordinates":[-0.490329,51.353519],"type":"Point"}
}