{
  "type": "Feature",
  "properties": {
    "iso:country":"GB",
    "sg:address":"1 Market Hill",
    "sg:city":"Southam",
    "sg:classifiers":[
        {
            "category":"Shopping",
            "subcategory":"Pharmacy",
            "type":"Retail Goods"
        }
    ],
    "sg:phone":"+44 1926 812287",
    "sg:postcode":"CV47 0HE",
    "sg:province":"Warwickshire",
    "sg:tags":[
        "pharmacist",
        "chemist"
    ],
    "wof:name":"Taylor (Southam) Ltd.",
    "wof:placetype":"venue"
},
  "geometry": {"coordinates":[-1.38803,52.252674],"type":"Point"}
}