{
  "type": "Feature",
  "properties": {
    "iso:country":"GB",
    "sg:address":"Stone Castle, London Rd",
    "sg:city":"Greenhithe",
    "sg:classifiers":[
        {
            "category":"Professional",
            "subcategory":"Engineering",
            "type":"Services"
        }
    ],
    "sg:phone":"+44 1322 387935",
    "sg:postcode":"DA9 9JG",
    "sg:province":"Kent",
    "sg:tags":[
        "consulting",
        "engineer"
    ],
    "wof:name":"Simons A F-I P K",
    "wof:placetype":"venue"
},
  "geometry": {"coordinates":[0.27694,51.447861],"type":"Point"}
}