{
  "type": "Feature",
  "properties": {
    "addr:full":"119 Bon Accord Street Aberdeen Aberdeen City AB11 6EH",
    "addr:housenumber":"119",
    "addr:postcode":"ab11 6eh",
    "addr:street":"Bon Accord Street",
    "iso:country":"GB",
    "sg:address":"119 Bon Accord Street",
    "sg:city":"Aberdeen",
    "sg:classifiers":[
        {
            "category":"Professional",
            "subcategory":"Printing & Photocopies",
            "type":"Services"
        }
    ],
    "sg:phone":"+44 1224 582186",
    "sg:postcode":"AB11 6EH",
    "sg:province":"Aberdeen City",
    "sg:tags":[
        "printer"
    ],
    "wof:name":"Douglas Pirie & Co",
    "wof:placetype":"venue"
},
  "geometry": {"coordinates":[-2.1064939499,57.1440849304],"type":"Point"}
}