{
  "type": "Feature",
  "properties": {
    "addr:full":"6b Dicconson Mill, Mill Lane, Aspull Wigan Lancashire WN2 1QF",
    "addr:housenumber":"6b",
    "addr:postcode":"wn2 1qf",
    "addr:street":"Dicconson Mill Mill Lane",
    "iso:country":"GB",
    "sg:address":"6b Dicconson Mill, Mill Lane, Aspull",
    "sg:city":"Wigan",
    "sg:classifiers":[
        {
            "category":"Shopping",
            "subcategory":"Musical Instruments",
            "type":"Retail Goods"
        }
    ],
    "sg:phone":"+44 1942 833978",
    "sg:postcode":"WN2 1QF",
    "sg:province":"Lancashire",
    "wof:name":"Giraffe Music Stands Ltd.",
    "wof:placetype":"venue"
},
  "geometry": {"coordinates":[-2.5847139359,53.5694503784],"type":"Point"}
}