{
  "type": "Feature",
  "properties": {
    "addr:full":"80 Penn Hill Avenue Poole Dorset BH14 9NA",
    "addr:housenumber":"80",
    "addr:postcode":"bh14 9na",
    "addr:street":"Penn Hill Avenue",
    "iso:country":"GB",
    "sg:address":"80 Penn Hill Avenue",
    "sg:city":"Poole",
    "sg:classifiers":[
        {
            "category":"Professional",
            "subcategory":"Art Services",
            "type":"Services"
        }
    ],
    "sg:phone":"+44 1202 744799",
    "sg:postcode":"BH14 9NA",
    "sg:province":"Dorset",
    "sg:tags":[
        "graphic",
        "designer"
    ],
    "wof:name":"D Campbell & Co",
    "wof:placetype":"venue"
},
  "geometry": {"coordinates":[-1.93013,50.722672],"type":"Point"}
}