{
  "type": "Feature",
  "properties": {
    "addr:full":"1a Wellington Road, Hampton Hill Hampton Greater London TW12 1JP",
    "addr:housenumber":"1a",
    "addr:postcode":"tw12 1jp",
    "addr:street":"Wellington Road",
    "iso:country":"GB",
    "sg:address":"1a Wellington Road, Hampton Hill",
    "sg:city":"Hampton",
    "sg:classifiers":[
        {
            "category":"Building & Trades",
            "subcategory":"Plumbing",
            "type":"Services"
        }
    ],
    "sg:postcode":"TW12 1JP",
    "sg:province":"Greater London",
    "sg:tags":[
        "heating"
    ],
    "wof:name":"Swift Heating & Plumbing",
    "wof:placetype":"venue"
},
  "geometry": {"coordinates":[-0.353718,51.430183],"type":"Point"}
}