{
  "type": "Feature",
  "properties": {
    "iso:country":"GB",
    "sg:address":"4 Main Street, Langar",
    "sg:city":"Nottingham",
    "sg:classifiers":[
        {
            "category":"Professional",
            "subcategory":"Art Services",
            "type":"Services"
        }
    ],
    "sg:phone":"+44 1949 861147",
    "sg:postcode":"NG13 9HE",
    "sg:province":"Leicestershire",
    "sg:tags":[
        "graphic",
        "designer"
    ],
    "wof:name":"Emmo Communications",
    "wof:placetype":"venue"
},
  "geometry": {"coordinates":[-0.8961390257,52.9549293518],"type":"Point"}
}