{
  "type": "Feature",
  "properties": {
    "addr:full":"Sadler Dr Middlesbrough North Yorkshire TS7 8HJ",
    "addr:postcode":"ts7 8hj",
    "addr:street":"Sadler Dr",
    "iso:country":"GB",
    "sg:address":"Sadler Dr",
    "sg:city":"Middlesbrough",
    "sg:classifiers":[
        {
            "category":"Building & Trades",
            "subcategory":"Construction",
            "type":"Services"
        }
    ],
    "sg:phone":"+44 1642 327292",
    "sg:postcode":"TS7 8HJ",
    "sg:province":"North Yorkshire",
    "sg:tags":[
        "builder"
    ],
    "wof:name":"Bryant Homes",
    "wof:placetype":"venue"
},
  "geometry": {"coordinates":[-1.211316,54.531429],"type":"Point"}
}