{
  "type": "Feature",
  "properties": {
    "iso:country":"GB",
    "sg:address":"46 Baker Street",
    "sg:city":"Brighton",
    "sg:classifiers":[
        {
            "category":"Shopping",
            "subcategory":"Department Store",
            "type":"Retail Goods"
        },
        {
            "category":"Shopping",
            "subcategory":"Comic Books",
            "type":"Retail Goods"
        }
    ],
    "sg:phone":"+44 1273 695950",
    "sg:postcode":"BN1 4JN",
    "sg:province":"East Sussex",
    "sg:tags":[
        "jeweller"
    ],
    "wof:name":"The Wishing Well",
    "wof:placetype":"venue"
},
  "geometry": {"coordinates":[-0.135225,50.831715],"type":"Point"}
}