{
  "type": "Feature",
  "properties": {
    "addr:full":"54-56 Hillary St Walsall West Midlands WS2 9BS",
    "addr:housenumber":"54-56",
    "addr:postcode":"ws2 9bs",
    "addr:street":"Hillary St",
    "iso:country":"GB",
    "sg:address":"54-56 Hillary St",
    "sg:city":"Walsall",
    "sg:classifiers":[
        {
            "category":"Home & Garden",
            "subcategory":"Household Appliances",
            "type":"Retail Goods"
        }
    ],
    "sg:phone":"+44 1922 633836",
    "sg:postcode":"WS2 9BS",
    "sg:province":"West Midlands",
    "sg:tags":[
        "refrigeration",
        "air conditioning"
    ],
    "wof:name":"Hollingsworth Associates",
    "wof:placetype":"venue"
},
  "geometry": {"coordinates":[-1.9990340471,52.5718040466],"type":"Point"}
}