{
  "type": "Feature",
  "properties": {
    "iso:country":"GB",
    "sg:address":"80 Brewer Street",
    "sg:city":"London",
    "sg:classifiers":[
        {
            "category":"Manufacturing",
            "subcategory":"Textiles",
            "type":"Manufacturing & Wholesale Goods"
        }
    ],
    "sg:phone":"+44 20 7437 6417",
    "sg:postcode":"W1F 9TZ",
    "sg:province":"Greater London",
    "sg:tags":[
        "knitwear"
    ],
    "wof:name":"G L Houghton Ltd.",
    "wof:placetype":"venue"
},
  "geometry": {"coordinates":[-0.136849001,51.5108299255],"type":"Point"}
}