{
  "type": "Feature",
  "properties": {
    "iso:country":"GB",
    "sg:address":"4 Cressing Road",
    "sg:city":"Braintree",
    "sg:classifiers":[
        {
            "category":"Building & Trades",
            "subcategory":"Construction",
            "type":"Services"
        },
        {
            "category":"Government",
            "subcategory":"Customs House",
            "type":"Public Place"
        }
    ],
    "sg:postcode":"CM7 3PP",
    "sg:province":"Essex",
    "sg:tags":[
        "builder",
        "clearance"
    ],
    "wof:name":"Potter's Emporium",
    "wof:placetype":"venue"
},
  "geometry": {"coordinates":[0.56537,51.880405],"type":"Point"}
}