{
  "type": "Feature",
  "properties": {
    "iso:country":"GB",
    "sg:address":"20 Juniper Close",
    "sg:city":"Lutterworth",
    "sg:classifiers":[
        {
            "category":"Building & Trades",
            "subcategory":"Cleaning & Sanitation",
            "type":"Services"
        }
    ],
    "sg:phone":"+44 1455 556840",
    "sg:postcode":"LE17 4US",
    "sg:province":"Leicestershire",
    "sg:tags":[
        "commercial"
    ],
    "wof:name":"Concept Cleaning Services",
    "wof:placetype":"venue"
},
  "geometry": {"coordinates":[-1.212577,52.461342],"type":"Point"}
}