{
  "type": "Feature",
  "properties": {
    "addr:full":"Park House, 158-160 Arthur Road London Greater London SW19 8AQ",
    "addr:housenumber":"158-160",
    "addr:postcode":"sw19 8aq",
    "addr:street":"Arthur Road",
    "iso:country":"GB",
    "sg:address":"Park House, 158-160 Arthur Road",
    "sg:city":"London",
    "sg:classifiers":[
        {
            "category":"Professional",
            "subcategory":"Accounting & Tax Preparation",
            "type":"Services"
        }
    ],
    "sg:postcode":"SW19 8AQ",
    "sg:province":"Greater London",
    "sg:tags":[
        "consultant"
    ],
    "wof:name":"B Davis & Co. Chartered Accountants",
    "wof:placetype":"venue"
},
  "geometry": {"coordinates":[-0.1974249929,51.4348487854],"type":"Point"}
}