{
  "type": "Feature",
  "properties": {
    "addr:full":"Wormiston, Crail Anstruther Fife KY10 3XH",
    "addr:postcode":"ky10 3xh",
    "iso:country":"GB",
    "sg:address":"Wormiston, Crail",
    "sg:city":"Anstruther",
    "sg:classifiers":[
        {
            "category":"Real Estate",
            "subcategory":"Architect",
            "type":"Services"
        }
    ],
    "sg:phone":"+44 1333 450965",
    "sg:postcode":"KY10 3XH",
    "sg:province":"Fife",
    "wof:name":"Wormiston Consultants",
    "wof:placetype":"venue"
},
  "geometry": {"coordinates":[-2.7009840012,56.2228851318],"type":"Point"}
}