{
  "type": "Feature",
  "properties": {
    "addr:full":"Lime Tree Cottage, Ellerigg Rd Ambleside Cumbria LA22 9EU",
    "addr:postcode":"la22 9eu",
    "addr:street":"Lime;Ellerigg Rd",
    "iso:country":"GB",
    "sg:address":"Lime Tree Cottage, Ellerigg Rd",
    "sg:city":"Ambleside",
    "sg:classifiers":[
        {
            "category":"Professional",
            "subcategory":"Art Services",
            "type":"Services"
        }
    ],
    "sg:phone":"+44 15394 32054",
    "sg:postcode":"LA22 9EU",
    "sg:province":"Cumbria",
    "sg:tags":[
        "photographer"
    ],
    "wof:name":"Tom Houghton",
    "wof:placetype":"venue"
},
  "geometry": {"coordinates":[-2.9630889893,54.4326057434],"type":"Point"}
}