{
  "type": "Feature",
  "properties": {
    "addr:full":"11-13 Lion Road Twickenham Greater London TW1 4JF",
    "addr:housenumber":"11-13",
    "addr:postcode":"tw1 4jf",
    "addr:street":"Lion Road",
    "iso:country":"GB",
    "sg:address":"11-13 Lion Road",
    "sg:city":"Twickenham",
    "sg:classifiers":[
        {
            "category":"Shopping",
            "subcategory":"Computers & Home Electronics",
            "type":"Retail Goods"
        }
    ],
    "sg:phone":"+44 20 8744 0701",
    "sg:postcode":"TW1 4JF",
    "sg:province":"Greater London",
    "sg:tags":[
        "electrical"
    ],
    "wof:name":"Simon Perry",
    "wof:placetype":"venue"
},
  "geometry": {"coordinates":[-0.3378869891,51.4456787109],"type":"Point"}
}