{
  "type": "Feature",
  "properties": {
    "addr:full":"Earlstrees Industrial Estate, 5 Godwin Road Corby Northamptonshire NN17 4DS",
    "addr:housenumber":"5",
    "addr:postcode":"nn17 4ds",
    "addr:street":"Estate;Godwin Road",
    "iso:country":"GB",
    "sg:address":"Earlstrees Industrial Estate, 5 Godwin Road",
    "sg:city":"Corby",
    "sg:classifiers":[
        {
            "category":"Wholesale",
            "subcategory":"Office Equipment",
            "type":"Manufacturing & Wholesale Goods"
        },
        {
            "category":"Professional",
            "type":"Services"
        }
    ],
    "sg:phone":"+44 1536 401345",
    "sg:postcode":"NN17 4DS",
    "sg:province":"Northamptonshire",
    "sg:tags":[
        "control",
        "system"
    ],
    "wof:name":"Watford Control Instruments Ltd",
    "wof:placetype":"venue"
},
  "geometry": {"coordinates":[-0.7026,52.485977],"type":"Point"}
}