{
  "type": "Feature",
  "properties": {
    "addr:full":"80 The Green Southall Greater London UB2 4BG",
    "addr:housenumber":"80",
    "addr:postcode":"ub2 4bg",
    "addr:street":"The Green",
    "iso:country":"GB",
    "sg:address":"80 The Green",
    "sg:city":"Southall",
    "sg:classifiers":[
        {
            "category":"Home & Garden",
            "subcategory":"Household Appliances",
            "type":"Retail Goods"
        },
        {
            "category":"Home & Garden",
            "subcategory":"Kitchen Supply",
            "type":"Retail Goods"
        }
    ],
    "sg:phone":"+44 20 8571 6571",
    "sg:postcode":"UB2 4BG",
    "sg:province":"Greater London",
    "sg:tags":[
        "ware",
        "kitchenware"
    ],
    "wof:name":"Mita Emporium",
    "wof:placetype":"venue"
},
  "geometry": {"coordinates":[-0.381271,51.502792],"type":"Point"}
}