{
  "type": "Feature",
  "properties": {
    "addr:full":"81-83 Hills Road Cambridge Cambridgeshire CB2 1PG",
    "addr:housenumber":"81-83",
    "addr:postcode":"cb2 1pg",
    "addr:street":"Hills Road",
    "iso:country":"GB",
    "sg:address":"81-83 Hills Road",
    "sg:city":"Cambridge",
    "sg:classifiers":[
        {
            "category":"Education",
            "subcategory":"Special Training",
            "type":"Public Place"
        }
    ],
    "sg:phone":"+44 1223 321084",
    "sg:postcode":"CB2 1PG",
    "sg:province":"Cambridgeshire",
    "sg:tags":[
        "school",
        "language"
    ],
    "wof:name":"O I S E Cambridge",
    "wof:placetype":"venue"
},
  "geometry": {"coordinates":[0.1323850006,52.1942481995],"type":"Point"}
}