{
  "type": "Feature",
  "properties": {
    "addr:full":"3 Forest Rd Torquay Devon TQ1 4JP",
    "addr:housenumber":"3",
    "addr:postcode":"tq1 4jp",
    "addr:street":"Forest Rd",
    "iso:country":"GB",
    "sg:address":"3 Forest Rd",
    "sg:city":"Torquay",
    "sg:classifiers":[
        {
            "category":"Retail",
            "subcategory":"Repair Shop",
            "type":"Services"
        }
    ],
    "sg:phone":"+44 1803 312296",
    "sg:postcode":"TQ1 4JP",
    "sg:province":"Devon",
    "sg:tags":[
        "furniture"
    ],
    "wof:name":"G Frost",
    "wof:placetype":"venue"
},
  "geometry": {"coordinates":[-3.53023,50.476833],"type":"Point"}
}