{
  "type": "Feature",
  "properties": {
    "iso:country":"GB",
    "sg:address":"C L C House, 29 Dyfrig Road",
    "sg:city":"Cardiff",
    "sg:classifiers":[
        {
            "category":"Wholesale",
            "subcategory":"Construction Materials",
            "type":"Manufacturing & Wholesale Goods"
        }
    ],
    "sg:phone":"+44 29 2040 4404",
    "sg:postcode":"CF5 5AD",
    "sg:province":"Cardiff",
    "sg:tags":[
        "lift"
    ],
    "wof:name":"Cardiff Lift Co.",
    "wof:placetype":"venue"
},
  "geometry": {"coordinates":[-3.228749,51.482121],"type":"Point"}
}