{
  "type": "Feature",
  "properties": {
    "addr:full":"21 Cowley Road, Marton Blackpool Lancashire FY4 4NE",
    "addr:housenumber":"21",
    "addr:postcode":"fy4 4ne",
    "addr:street":"Cowley Road",
    "iso:country":"GB",
    "sg:address":"21 Cowley Road, Marton",
    "sg:city":"Blackpool",
    "sg:classifiers":[
        {
            "category":"Professional",
            "subcategory":"Engineering",
            "type":"Services"
        }
    ],
    "sg:phone":"+44 1253 761661",
    "sg:postcode":"FY4 4NE",
    "sg:province":"Lancashire",
    "sg:tags":[
        "precision",
        "engineer"
    ],
    "wof:name":"Beswick Engineering Co. Ltd.",
    "wof:placetype":"venue"
},
  "geometry": {"coordinates":[-3.021525,53.796741],"type":"Point"}
}