{
  "type": "Feature",
  "properties": {
    "iso:country":"GB",
    "sg:address":"47 Raven Row",
    "sg:city":"London",
    "sg:classifiers":[
        {
            "category":"Building & Trades",
            "subcategory":"Construction",
            "type":"Services"
        }
    ],
    "sg:phone":"+44 800 783 6729",
    "sg:postcode":"E1 2EG",
    "sg:province":"Greater London",
    "sg:tags":[
        "builder"
    ],
    "wof:name":"Premier Maintenance Direct",
    "wof:placetype":"venue"
},
  "geometry": {"coordinates":[-0.056221,51.519352],"type":"Point"}
}