{
  "type": "Feature",
  "properties": {
    "addr:full":"Flat 10,  Syon Court, Park View Close, At. Albans St. Albans Hertfordshire AL1 5TP",
    "addr:housenumber":"flat 10",
    "addr:postcode":"al1 5tp",
    "addr:street":"Syon Court Park View Close At. Albans",
    "iso:country":"GB",
    "sg:address":"Flat 10,  Syon Court, Park View Close, At. Albans",
    "sg:city":"St. Albans",
    "sg:classifiers":[
        {
            "category":"Social Services",
            "subcategory":"Job Training",
            "type":"Services"
        }
    ],
    "sg:phone":"+44 1462 676801",
    "sg:postcode":"AL1 5TP",
    "sg:province":"Hertfordshire",
    "sg:tags":[
        "translator",
        "interpreter"
    ],
    "wof:name":"Intrex",
    "wof:placetype":"venue"
},
  "geometry": {"coordinates":[-0.3180699944,51.7478790283],"type":"Point"}
}