{
  "type": "Feature",
  "properties": {
    "iso:country":"GB",
    "sg:address":"Braeside, Athelstaneford",
    "sg:city":"North Berwick",
    "sg:classifiers":[
        {
            "category":"Real Estate",
            "subcategory":"Architect",
            "type":"Services"
        }
    ],
    "sg:postcode":"EH39 5BE",
    "sg:province":"East Lothian",
    "wof:name":"SOMNER MACDONALD",
    "wof:placetype":"venue"
},
  "geometry": {"coordinates":[-2.745578,55.987156],"type":"Point"}
}