{
  "type": "Feature",
  "properties": {
    "iso:country":"GB",
    "sg:address":"5 Cheltenham Crescent",
    "sg:city":"Harrogate",
    "sg:classifiers":[
        {
            "category":"Personal",
            "subcategory":"Beauty Salon",
            "type":"Services"
        },
        {
            "category":"Personal",
            "subcategory":"Barber",
            "type":"Services"
        }
    ],
    "sg:phone":"+44 1423 565000",
    "sg:postcode":"HG1 1DH",
    "sg:province":"North Yorkshire",
    "sg:tags":[
        "unisex",
        "hairdresser"
    ],
    "wof:name":"John Hardy",
    "wof:placetype":"venue"
},
  "geometry": {"coordinates":[-1.5417330265,53.9944343567],"type":"Point"}
}