{
  "type": "Feature",
  "properties": {
    "iso:country":"GB",
    "sg:address":"Bishops Courtyard, 69-71 Latimer Road",
    "sg:city":"Luton",
    "sg:classifiers":[
        {
            "category":"Professional",
            "subcategory":"Art Services",
            "type":"Services"
        }
    ],
    "sg:phone":"+44 1582 487580",
    "sg:postcode":"LU1 3XD",
    "sg:province":"Bedfordshire",
    "sg:tags":[
        "graphic",
        "designer"
    ],
    "wof:name":"White Knight Design Ltd.",
    "wof:placetype":"venue"
},
  "geometry": {"coordinates":[-0.4156149924,51.8813362122],"type":"Point"}
}