{
  "type": "Feature",
  "properties": {
    "addr:full":"Amersham Hospital, Whielden Street Amersham Buckinghamshire HP7 0JD",
    "addr:postcode":"hp7 0jd",
    "addr:street":"Whielden Street",
    "iso:country":"GB",
    "sg:address":"Amersham Hospital, Whielden Street",
    "sg:city":"Amersham",
    "sg:classifiers":[
        {
            "category":"Organizations",
            "subcategory":"Non-profit Organization",
            "type":"Services"
        }
    ],
    "sg:phone":"+44 1494 727752",
    "sg:postcode":"HP7 0JD",
    "sg:province":"Buckinghamshire",
    "sg:tags":[
        "organisation",
        "voluntary",
        "charity"
    ],
    "wof:name":"Scannappeal",
    "wof:placetype":"venue"
},
  "geometry": {"coordinates":[-0.6209700108,51.6627883911],"type":"Point"}
}