{
  "type": "Feature",
  "properties": {
    "addr:full":"Toad Hall, Norwich Rd, Mulbarton Norwich Norfolk NR14 8JT",
    "addr:postcode":"nr14 8jt",
    "addr:street":"Norwich Rd;Norwich",
    "iso:country":"GB",
    "sg:address":"Toad Hall, Norwich Rd, Mulbarton",
    "sg:city":"Norwich",
    "sg:classifiers":[
        {
            "category":"Professional",
            "subcategory":"Computer Services",
            "type":"Services"
        }
    ],
    "sg:phone":"+44 1508 570538",
    "sg:postcode":"NR14 8JT",
    "sg:province":"Norfolk",
    "sg:tags":[
        "system",
        "software"
    ],
    "wof:name":"Acumen Consultants",
    "wof:placetype":"venue"
},
  "geometry": {"coordinates":[1.2374670506,52.5583190918],"type":"Point"}
}