{
  "type": "Feature",
  "properties": {
    "iso:country":"GB",
    "sg:address":"Plawsworth Rd",
    "sg:city":"Durham",
    "sg:classifiers":[
        {
            "category":"Place Of Worship",
            "type":"Public Place"
        }
    ],
    "sg:phone":"+44 191 371 0337",
    "sg:postcode":"DH7 6PE",
    "sg:province":"Durham",
    "wof:name":"Nettlesworth Methodist Church",
    "wof:placetype":"venue"
},
  "geometry": {"coordinates":[-1.621499,54.820034],"type":"Point"}
}