{
  "type": "Feature",
  "properties": {
    "iso:country":"GB",
    "sg:address":"63 St Pauls Square",
    "sg:city":"Birmingham",
    "sg:classifiers":[
        {
            "category":"Real Estate",
            "subcategory":"Surveying",
            "type":"Services"
        }
    ],
    "sg:phone":"+44 121 236 5252",
    "sg:postcode":"B3 1QS",
    "sg:province":"West Midlands",
    "sg:tags":[
        "surveyor",
        "valuer"
    ],
    "wof:name":"Fleurets Ltd.",
    "wof:placetype":"venue"
},
  "geometry": {"coordinates":[-1.905166,52.484646],"type":"Point"}
}