{
  "type": "Feature",
  "properties": {
    "addr:full":"35 Roker Park Road, Roker Sunderland Tyne and Wear SR6 9PL",
    "addr:housenumber":"35",
    "addr:postcode":"sr6 9pl",
    "addr:street":"Roker Park Road",
    "iso:country":"GB",
    "sg:address":"35 Roker Park Road, Roker",
    "sg:city":"Sunderland",
    "sg:classifiers":[
        {
            "category":"Retail",
            "subcategory":"Veterinary Services",
            "type":"Services"
        }
    ],
    "sg:phone":"+44 191 516 0056",
    "sg:postcode":"SR6 9PL",
    "sg:province":"Tyne and Wear",
    "sg:tags":[
        "surgeon"
    ],
    "wof:name":"Roker Park Veterinary Center",
    "wof:placetype":"venue"
},
  "geometry": {"coordinates":[-1.3710860014,54.9252319336],"type":"Point"}
}