{
  "type": "Feature",
  "properties": {
    "addr:full":"Central Court, North Road St Helens Merseyside WA10 2TJ",
    "addr:postcode":"wa10 2tj",
    "addr:street":"Central Court North Road",
    "iso:country":"GB",
    "sg:address":"Central Court, North Road",
    "sg:city":"St Helens",
    "sg:classifiers":[
        {
            "category":"Education",
            "subcategory":"Special Training",
            "type":"Public Place"
        }
    ],
    "sg:phone":"+44 1744 454218",
    "sg:postcode":"WA10 2TJ",
    "sg:province":"Merseyside",
    "sg:tags":[
        "product",
        "centre"
    ],
    "wof:name":"St Helens Y M C A Foyerproject",
    "wof:placetype":"venue"
},
  "geometry": {"coordinates":[-2.740194,53.459301],"type":"Point"}
}