{
  "type": "Feature",
  "properties": {
    "addr:full":"19 Townsend, Soham Ely Cambridgeshire CB7 5DD",
    "addr:housenumber":"19",
    "addr:postcode":"cb7 5dd",
    "addr:street":"Townsend Soham",
    "iso:country":"GB",
    "sg:address":"19 Townsend, Soham",
    "sg:city":"Ely",
    "sg:classifiers":[
        {
            "category":"Shopping",
            "subcategory":"Hobbies, Toys, & Games",
            "type":"Retail Goods"
        }
    ],
    "sg:phone":"+44 1353 624321",
    "sg:postcode":"CB7 5DD",
    "sg:province":"Cambridgeshire",
    "sg:tags":[
        "gunsmith"
    ],
    "wof:name":"L R S Ltd.",
    "wof:placetype":"venue"
},
  "geometry": {"coordinates":[0.3494099975,52.3348388672],"type":"Point"}
}