{
  "type": "Feature",
  "properties": {
    "addr:full":"Unit 4, Penketh Business Park, Cleveleys Rd, Great Sankey Warrington Cheshire WA5 2TJ",
    "addr:housenumber":"unit 4 penketh",
    "addr:postcode":"wa5 2tj",
    "addr:street":"Business Park Cleveleys Rd",
    "iso:country":"GB",
    "sg:address":"Unit 4, Penketh Business Park, Cleveleys Rd, Great Sankey",
    "sg:city":"Warrington",
    "sg:classifiers":[
        {
            "category":"Communications",
            "type":"Services"
        }
    ],
    "sg:phone":"+44 1925 444427",
    "sg:postcode":"WA5 2TJ",
    "sg:province":"Cheshire",
    "sg:tags":[
        "data",
        "network"
    ],
    "wof:name":"Shred-it",
    "wof:placetype":"venue"
},
  "geometry": {"coordinates":[-2.6385300159,53.3864212036],"type":"Point"}
}