{
  "type": "Feature",
  "properties": {
    "iso:country":"GB",
    "sg:address":"Venus Cottage, Ansford Rd",
    "sg:city":"Castle Cary",
    "sg:classifiers":[
        {
            "category":"Building & Trades",
            "subcategory":"Construction",
            "type":"Services"
        }
    ],
    "sg:phone":"+44 1963 350684",
    "sg:postcode":"BA7 7HH",
    "sg:province":"Somerset",
    "sg:tags":[
        "joiner",
        "carpenter"
    ],
    "wof:name":"Pitman H J F",
    "wof:placetype":"venue"
},
  "geometry": {"coordinates":[-2.518086,51.089069],"type":"Point"}
}