{
  "type": "Feature",
  "properties": {
    "addr:full":"10 Prince St Bacup Lancashire OL13 9SN",
    "addr:housenumber":"10",
    "addr:postcode":"ol13 9sn",
    "addr:street":"Prince St",
    "iso:country":"GB",
    "sg:address":"10 Prince St",
    "sg:city":"Bacup",
    "sg:classifiers":[
        {
            "category":"Museum",
            "subcategory":"Zoo",
            "type":"Entertainment"
        }
    ],
    "sg:phone":"+44 1706 874395",
    "sg:postcode":"OL13 9SN",
    "sg:province":"Lancashire",
    "sg:tags":[
        "cat"
    ],
    "wof:name":"Milifiori Persians",
    "wof:placetype":"venue"
},
  "geometry": {"coordinates":[-2.173668,53.689243],"type":"Point"}
}