{
  "type": "Feature",
  "properties": {
    "iso:country":"GB",
    "sg:address":"56 Donnington Drive, Higher Compton",
    "sg:city":"Plymouth",
    "sg:classifiers":[
        {
            "category":"Building & Trades",
            "subcategory":"Construction",
            "type":"Services"
        }
    ],
    "sg:postcode":"PL3 6QT",
    "sg:province":"Devon",
    "sg:tags":[
        "decorator",
        "painter"
    ],
    "wof:name":"Best Southern Interiors",
    "wof:placetype":"venue"
},
  "geometry": {"coordinates":[-4.111266,50.394066],"type":"Point"}
}