{
  "type": "Feature",
  "properties": {
    "iso:country":"GB",
    "sg:address":"24-26 Baltic Street West",
    "sg:city":"London",
    "sg:classifiers":[
        {
            "category":"Freight",
            "type":"Transportation"
        }
    ],
    "sg:postcode":"EC1Y 0UL",
    "sg:province":"Greater London",
    "sg:tags":[
        "shipping"
    ],
    "wof:name":"Global Maritime Services Ltd",
    "wof:placetype":"venue"
},
  "geometry": {"coordinates":[-0.097046,51.523319],"type":"Point"}
}