{
  "type": "Feature",
  "properties": {
    "addr:full":"Cooting Road, Aylesham Canterbury Kent CT3 3EP",
    "addr:postcode":"ct3 3ep",
    "addr:street":"Cooting Road",
    "iso:country":"GB",
    "sg:address":"Cooting Road, Aylesham",
    "sg:city":"Canterbury",
    "sg:classifiers":[
        {
            "category":"Retail",
            "subcategory":"Storage",
            "type":"Services"
        }
    ],
    "sg:phone":"+44 1304 840733",
    "sg:postcode":"CT3 3EP",
    "sg:province":"Kent",
    "sg:tags":[
        "household",
        "removal"
    ],
    "wof:name":"Pickfords Removals",
    "wof:placetype":"venue"
},
  "geometry": {"coordinates":[1.20096,51.226166],"type":"Point"}
}