{
  "type": "Feature",
  "properties": {
    "addr:full":"6 Westerleigh Road, Combe Down Bath Somerset BA2 5JE",
    "addr:housenumber":"6",
    "addr:postcode":"ba2 5je",
    "addr:street":"Westerleigh Road",
    "iso:country":"GB",
    "sg:address":"6 Westerleigh Road, Combe Down",
    "sg:city":"Bath",
    "sg:classifiers":[
        {
            "category":"Home & Garden",
            "subcategory":"Carpets & Floor Coverings",
            "type":"Retail Goods"
        }
    ],
    "sg:phone":"+44 1225 840327",
    "sg:postcode":"BA2 5JE",
    "sg:province":"Somerset",
    "sg:tags":[
        "cleaner",
        "upholstery"
    ],
    "wof:name":"P M W Commercial Carpet Cleaners",
    "wof:placetype":"venue"
},
  "geometry": {"coordinates":[-2.34938097,51.3605651855],"type":"Point"}
}