{
  "type": "Feature",
  "properties": {
    "addr:full":"Tyson Street, Cheetham Hill Manchester Greater Manchester M8 5DJ",
    "addr:postcode":"m8 5dj",
    "addr:street":"Tyson Street",
    "iso:country":"GB",
    "sg:address":"Tyson Street, Cheetham Hill",
    "sg:city":"Manchester",
    "sg:classifiers":[
        {
            "category":"Professional",
            "subcategory":"Detective & Security Services",
            "type":"Services"
        }
    ],
    "sg:phone":"+44 161 740 0398",
    "sg:postcode":"M8 5DJ",
    "sg:province":"Greater Manchester",
    "sg:tags":[
        "car"
    ],
    "wof:name":"United in Safety",
    "wof:placetype":"venue"
},
  "geometry": {"coordinates":[-2.2444450855,53.5127296448],"type":"Point"}
}