{
  "type": "Feature",
  "properties": {
    "iso:country":"GB",
    "sg:address":"8 Wendell Road",
    "sg:city":"London",
    "sg:classifiers":[
        {
            "category":"Real Estate",
            "subcategory":"Architect",
            "type":"Services"
        }
    ],
    "sg:phone":"+44 20 8740 9894",
    "sg:postcode":"W12 9RT",
    "sg:province":"Greater London",
    "wof:name":"David Robson",
    "wof:placetype":"venue"
},
  "geometry": {"coordinates":[-0.243809998,51.5023612976],"type":"Point"}
}