{
  "type": "Feature",
  "properties": {
    "iso:country":"GB",
    "sg:address":"39 Royal Terrace",
    "sg:city":"Thurso",
    "sg:classifiers":[
        {
            "category":"Military Area",
            "subcategory":"Air Force Base",
            "type":"Public Place"
        }
    ],
    "sg:phone":"+44 1847 892827",
    "sg:postcode":"KW14 8NW",
    "sg:province":"Highland",
    "sg:tags":[
        "taxi",
        "hire",
        "private"
    ],
    "wof:name":"Meiklejohn Taxis",
    "wof:placetype":"venue"
},
  "geometry": {"coordinates":[-3.511503,58.590317],"type":"Point"}
}