{
  "type": "Feature",
  "properties": {
    "addr:full":"614-616 Liverpool Road, Eccles Manchester Greater Manchester M30 7NA",
    "addr:housenumber":"614-616",
    "addr:postcode":"m30 7na",
    "addr:street":"Liverpool Road",
    "iso:country":"GB",
    "sg:address":"614-616 Liverpool Road, Eccles",
    "sg:city":"Manchester",
    "sg:classifiers":[
        {
            "category":"Sports & Exercise",
            "subcategory":"Gym",
            "type":"Entertainment"
        }
    ],
    "sg:phone":"+44 161 789 4646",
    "sg:postcode":"M30 7NA",
    "sg:province":"Greater Manchester",
    "sg:tags":[
        "club",
        "fitness",
        "health",
        "centre"
    ],
    "wof:name":"The Brooke Health & Beauty Clinic",
    "wof:placetype":"venue"
},
  "geometry": {"coordinates":[-2.3689351082,53.4772644043],"type":"Point"}
}