{
  "type": "Feature",
  "properties": {
    "addr:full":"11 Tudhoe Lane Spennymoor Durham DL16 6LL",
    "addr:housenumber":"11",
    "addr:postcode":"dl16 6ll",
    "addr:street":"Tudhoe Lane",
    "iso:country":"GB",
    "sg:address":"11 Tudhoe Lane",
    "sg:city":"Spennymoor",
    "sg:classifiers":[
        {
            "category":"Freight",
            "type":"Transportation"
        }
    ],
    "sg:phone":"+44 1388 817159",
    "sg:postcode":"DL16 6LL",
    "sg:province":"Durham",
    "sg:tags":[
        "haulage",
        "road"
    ],
    "wof:name":"Dale Harrison Haulage",
    "wof:placetype":"venue"
},
  "geometry": {"coordinates":[-1.5897079706,54.7126235962],"type":"Point"}
}