{
  "type": "Feature",
  "properties": {
    "iso:country":"GB",
    "sg:address":"Central Works Depot, Cargo Fleet Lane",
    "sg:city":"Middlesbrough",
    "sg:classifiers":[
        {
            "category":"Social Services",
            "type":"Services"
        }
    ],
    "sg:phone":"+44 1642 230726",
    "sg:postcode":"TS3 8DQ",
    "sg:province":"North Yorkshire",
    "sg:tags":[
        "need",
        "disability",
        "special"
    ],
    "wof:name":"Dial A Ride (Middlesbrough) Ltd.",
    "wof:placetype":"venue"
},
  "geometry": {"coordinates":[-1.197291,54.57373],"type":"Point"}
}