{
  "type": "Feature",
  "properties": {
    "iso:country":"GB",
    "sg:address":"Unit 11 Staceys Industrial Estate, Silchester Road",
    "sg:city":"Tadley",
    "sg:classifiers":[
        {
            "category":"Autos & Motor Vehicles",
            "subcategory":"Auto Supplies",
            "type":"Retail Goods"
        }
    ],
    "sg:phone":"+44 118 981 5611",
    "sg:postcode":"RG26 3PX",
    "sg:province":"Berkshire",
    "sg:tags":[
        "tyre"
    ],
    "wof:name":"Tadley Tyre & Exhaust",
    "wof:placetype":"venue"
},
  "geometry": {"coordinates":[-1.137541,51.350163],"type":"Point"}
}