{
  "type": "Feature",
  "properties": {
    "addr:full":"Merlins Cross, Lower Lamphey Road Pembroke Pembrokeshire SA71 4AG",
    "addr:postcode":"sa71 4ag",
    "addr:street":"Lower Lamphey Road",
    "iso:country":"GB",
    "sg:address":"Merlins Cross, Lower Lamphey Road",
    "sg:city":"Pembroke",
    "sg:classifiers":[
        {
            "category":"Professional",
            "subcategory":"Engineering",
            "type":"Services"
        }
    ],
    "sg:phone":"+44 1646 685169",
    "sg:postcode":"SA71 4AG",
    "sg:province":"Pembrokeshire",
    "wof:name":"Mark Atherton & Ralph Morris",
    "wof:placetype":"venue"
},
  "geometry": {"coordinates":[-4.9052348137,51.67212677],"type":"Point"}
}