{
  "type": "Feature",
  "properties": {
    "iso:country":"GB",
    "sg:address":"Faversham Garden Centre, London Rd",
    "sg:city":"Sittingbourne",
    "sg:classifiers":[
        {
            "category":"Shopping",
            "subcategory":"Crafts & Fabrics",
            "type":"Retail Goods"
        }
    ],
    "sg:phone":"+44 1795 520655",
    "sg:postcode":"ME9 9JY",
    "sg:province":"Kent",
    "sg:tags":[
        "shop",
        "needlecraft",
        "wool"
    ],
    "wof:name":"Jean's Knit & Sew",
    "wof:placetype":"venue"
},
  "geometry": {"coordinates":[0.82268,51.321171],"type":"Point"}
}