{
  "type": "Feature",
  "properties": {
    "addr:full":"25 Barley Clo Peacehaven East Sussex BN10 7JQ",
    "addr:housenumber":"25",
    "addr:postcode":"bn10 7jq",
    "addr:street":"Barley Clo Peacehaven",
    "iso:country":"GB",
    "sg:address":"25 Barley Clo",
    "sg:city":"Peacehaven",
    "sg:classifiers":[
        {
            "category":"Manufacturing",
            "subcategory":"Petroleum Products",
            "type":"Manufacturing & Wholesale Goods"
        }
    ],
    "sg:phone":"+44 1273 588451",
    "sg:postcode":"BN10 7JQ",
    "sg:province":"East Sussex",
    "sg:tags":[
        "double",
        "glazing"
    ],
    "wof:name":"Samuel D I",
    "wof:placetype":"venue"
},
  "geometry": {"coordinates":[-0.005505,50.805588],"type":"Point"}
}