{
  "type": "Feature",
  "properties": {
    "addr:full":"8 Littletowns Estate, Blandford Heights Blandford Forum Dorset DT11 7UR",
    "addr:housenumber":"8",
    "addr:postcode":"dorset dt11 7ur",
    "addr:street":"Littletowns Estate",
    "iso:country":"GB",
    "sg:address":"8 Littletowns Estate, Blandford Heights",
    "sg:city":"Blandford Forum",
    "sg:classifiers":[
        {
            "category":"Manufacturing",
            "subcategory":"Glass & Minerals",
            "type":"Manufacturing & Wholesale Goods"
        }
    ],
    "sg:phone":"+44 1258 459703",
    "sg:postcode":"DT11 7UR",
    "sg:province":"Dorset",
    "sg:tags":[
        "fibre",
        "glassware",
        "moulding",
        "china",
        "mnfr"
    ],
    "wof:name":"Bill Dibden G R P",
    "wof:placetype":"venue"
},
  "geometry": {"coordinates":[-2.159419,50.868595],"type":"Point"}
}