{
  "type": "Feature",
  "properties": {
    "iso:country":"GB",
    "sg:address":"24 Lovell Road, Oakley",
    "sg:city":"Bedford",
    "sg:classifiers":[
        {
            "category":"Professional",
            "subcategory":"Business Services",
            "type":"Services"
        },
        {
            "category":"Building & Trades",
            "subcategory":"Construction",
            "type":"Services"
        }
    ],
    "sg:phone":"+44 1234 824211",
    "sg:postcode":"MK43 7RZ",
    "sg:province":"Bedfordshire",
    "sg:tags":[
        "builder",
        "holding"
    ],
    "wof:name":"Parrott Holdings Ltd.",
    "wof:placetype":"venue"
},
  "geometry": {"coordinates":[-0.5188289881,52.1662788391],"type":"Point"}
}