{
  "type": "Feature",
  "properties": {
    "addr:full":"Bryn Y Groes, Plas Yw Farm Road, Nannerch Mold Denbighshire CH7 5QS",
    "addr:housenumber":"yw",
    "addr:postcode":"ch7 5qs",
    "addr:street":"Bryn Y Groes Plas;Farm Road",
    "iso:country":"GB",
    "sg:address":"Bryn Y Groes, Plas Yw Farm Road, Nannerch",
    "sg:city":"Mold",
    "sg:classifiers":[
        {
            "category":"Shopping",
            "subcategory":"Gifts & Souvenirs",
            "type":"Retail Goods"
        }
    ],
    "sg:phone":"+44 1352 740018",
    "sg:postcode":"CH7 5QS",
    "sg:province":"Denbighshire",
    "sg:tags":[
        "greeting",
        "card"
    ],
    "wof:name":"Perspectives Photographics",
    "wof:placetype":"venue"
},
  "geometry": {"coordinates":[-3.2446830273,53.2161445618],"type":"Point"}
}