{
  "type": "Feature",
  "properties": {
    "iso:country":"GB",
    "sg:address":"Tuscor House, Enterprise Trading Estate, Guiness Road",
    "sg:city":"Manchester",
    "sg:classifiers":[
        {
            "category":"Freight",
            "type":"Transportation"
        }
    ],
    "sg:phone":"+44 161 868 6000",
    "sg:postcode":"M17 1SD",
    "sg:province":"Cheshire",
    "sg:tags":[
        "forwarders"
    ],
    "wof:name":"Tuscor Lloyds (U K) Ltd.",
    "wof:placetype":"venue"
},
  "geometry": {"coordinates":[-2.3187789917,53.4654083252],"type":"Point"}
}