{
  "type": "Feature",
  "properties": {
    "addr:full":"9 Merlewood, Dickleburgh Diss Norfolk IP21 4PL",
    "addr:housenumber":"9",
    "addr:postcode":"ip21 4pl",
    "addr:street":"Merlewood Dickleburgh",
    "iso:country":"GB",
    "sg:address":"9 Merlewood, Dickleburgh",
    "sg:city":"Diss",
    "sg:classifiers":[
        {
            "category":"Banks & Credit Unions",
            "subcategory":"Bank",
            "type":"Services"
        }
    ],
    "sg:phone":"+44 1379 741527",
    "sg:postcode":"IP21 4PL",
    "sg:province":"Norfolk",
    "sg:tags":[
        "broker",
        "mortgage"
    ],
    "wof:name":"Pean Finance",
    "wof:placetype":"venue"
},
  "geometry": {"coordinates":[1.196272,52.396557],"type":"Point"}
}