{
  "type": "Feature",
  "properties": {
    "iso:country":"GB",
    "sg:address":"5 Commercial Road",
    "sg:city":"Shepton Mallet",
    "sg:classifiers":[
        {
            "category":"Personal",
            "subcategory":"Beauty Salon",
            "type":"Services"
        }
    ],
    "sg:phone":"+44 1749 342550",
    "sg:postcode":"BA4 5BU",
    "sg:province":"Somerset",
    "sg:tags":[
        "unisex",
        "hairdresser"
    ],
    "wof:name":"G J's",
    "wof:placetype":"venue"
},
  "geometry": {"coordinates":[-2.548068,51.189896],"type":"Point"}
}