{
  "type": "Feature",
  "properties": {
    "iso:country":"GB",
    "sg:address":"East End, Toynton St. Peter",
    "sg:city":"Spilsby",
    "sg:classifiers":[
        {
            "category":"Utilities",
            "subcategory":"Refuse",
            "type":"Services"
        }
    ],
    "sg:phone":"+44 1754 830484",
    "sg:postcode":"PE23 5AT",
    "sg:province":"Lincolnshire",
    "sg:tags":[
        "disposal",
        "waste",
        "retail"
    ],
    "wof:name":"Ely's",
    "wof:placetype":"venue"
},
  "geometry": {"coordinates":[0.0924699977,53.1738014221],"type":"Point"}
}