{
  "type": "Feature",
  "properties": {
    "iso:country":"GB",
    "sg:address":"Woodlands Road",
    "sg:city":"Isleworth",
    "sg:classifiers":[
        {
            "category":"Education",
            "subcategory":"School",
            "type":"Public Place"
        }
    ],
    "sg:phone":"+44 20 8560 3569",
    "sg:postcode":"TW7 6JZ",
    "sg:province":"Greater London",
    "sg:tags":[
        "local",
        "authority"
    ],
    "wof:name":"Oaklands School",
    "wof:placetype":"venue"
},
  "geometry": {"coordinates":[-0.337991,51.472786],"type":"Point"}
}