{
  "type": "Feature",
  "properties": {
    "addr:full":"1 Pitreavie Court, South Pitreavie Business Park Dunfermline Fife KY11 5PU",
    "addr:housenumber":"1",
    "addr:postcode":"ky11 5pu",
    "addr:street":"Pitreavie Court South Pitreavie Business Park Dunfermline",
    "iso:country":"GB",
    "sg:address":"1 Pitreavie Court, South Pitreavie Business Park",
    "sg:city":"Dunfermline",
    "sg:classifiers":[
        {
            "category":"Professional",
            "subcategory":"Computer Services",
            "type":"Services"
        }
    ],
    "sg:phone":"+44 1383 627300",
    "sg:postcode":"KY11 5PU",
    "sg:province":"Fife",
    "sg:tags":[
        "system",
        "software"
    ],
    "wof:name":"Myrica (U K) Ltd.",
    "wof:placetype":"venue"
},
  "geometry": {"coordinates":[-3.4613699913,56.0748405457],"type":"Point"}
}