{
  "type": "Feature",
  "properties": {
    "iso:country":"GB",
    "sg:address":"884 Rosendale Rd, Herne Hill",
    "sg:city":"Herne Hill",
    "sg:classifiers":[
        {
            "category":"Retail",
            "subcategory":"Storage",
            "type":"Services"
        }
    ],
    "sg:phone":"+44 20 8761 2970",
    "sg:postcode":"SE24 9EH",
    "sg:province":"Greater London",
    "sg:tags":[
        "household",
        "removal"
    ],
    "wof:name":"Dulwich Removals",
    "wof:placetype":"venue"
},
  "geometry": {"coordinates":[-0.102269,51.448429],"type":"Point"}
}