{
  "type": "Feature",
  "properties": {
    "addr:full":"11 Mendip Close, Flitwick Bedford Bedfordshire MK45 1TT",
    "addr:housenumber":"11",
    "addr:postcode":"mk45 1tt",
    "addr:street":"Mendip Close",
    "iso:country":"GB",
    "sg:address":"11 Mendip Close, Flitwick",
    "sg:city":"Bedford",
    "sg:classifiers":[
        {
            "category":"Home & Garden",
            "subcategory":"Household Appliances",
            "type":"Retail Goods"
        }
    ],
    "sg:postcode":"MK45 1TT",
    "sg:province":"Bedfordshire",
    "sg:tags":[
        "electrical"
    ],
    "wof:name":"A1 Washing Machine Repairs",
    "wof:placetype":"venue"
},
  "geometry": {"coordinates":[-0.5083420277,52.0014877319],"type":"Point"}
}