{
  "type": "Feature",
  "properties": {
    "iso:country":"GB",
    "sg:address":"Darren House, High St",
    "sg:city":"Bridgend",
    "sg:classifiers":[
        {
            "category":"Manufacturing",
            "subcategory":"Building Materials",
            "type":"Manufacturing & Wholesale Goods"
        }
    ],
    "sg:phone":"+44 1656 865334",
    "sg:postcode":"CF35 6HR",
    "sg:province":"Bridgend",
    "sg:tags":[
        "tile",
        "mnfrs"
    ],
    "wof:name":"Ceramic Tiling",
    "wof:placetype":"venue"
},
  "geometry": {"coordinates":[-3.521673,51.549187],"type":"Point"}
}