{
  "type": "Feature",
  "properties": {
    "addr:full":"Link House, Link Place Brighton East Sussex BN1 7DX",
    "addr:postcode":"bn1 7dx",
    "addr:street":"Link Place",
    "iso:country":"GB",
    "sg:address":"Link House, Link Place",
    "sg:city":"Brighton",
    "sg:classifiers":[
        {
            "category":"Freight",
            "type":"Transportation"
        },
        {
            "category":"Government",
            "subcategory":"Post Office",
            "type":"Public Place"
        }
    ],
    "sg:phone":"+44 1273 550999",
    "sg:postcode":"BN1 7DX",
    "sg:province":"East Sussex",
    "sg:tags":[
        "haulage",
        "messenger",
        "courier",
        "road"
    ],
    "wof:name":"B B A Express Courier (Manchester) Ltd.",
    "wof:placetype":"venue"
},
  "geometry": {"coordinates":[-0.127425,50.842293],"type":"Point"}
}