{
  "type": "Feature",
  "properties": {
    "addr:full":"Threeways, Charing Hill Ashford Kent TN27 0NL",
    "addr:postcode":"tn27 0nl",
    "addr:street":"Charing Hill",
    "iso:country":"GB",
    "sg:address":"Threeways, Charing Hill",
    "sg:city":"Ashford",
    "sg:classifiers":[
        {
            "category":"Sports & Exercise",
            "subcategory":"Tennis Court",
            "type":"Entertainment"
        }
    ],
    "sg:phone":"+44 1233 713222",
    "sg:postcode":"TN27 0NL",
    "sg:province":"Kent",
    "sg:tags":[
        "breakdown",
        "recovery"
    ],
    "wof:name":"Ashford Recovery",
    "wof:placetype":"venue"
},
  "geometry": {"coordinates":[0.790926,51.211514],"type":"Point"}
}