{
  "type": "Feature",
  "properties": {
    "iso:country":"GB",
    "sg:address":"Tenersshire Yard, Mill Parade",
    "sg:city":"Newport",
    "sg:classifiers":[
        {
            "category":"Professional",
            "subcategory":"Printing & Photocopies",
            "type":"Services"
        }
    ],
    "sg:postcode":"NP20 2JR",
    "sg:province":"Newport",
    "sg:tags":[
        "trophy"
    ],
    "wof:name":"Discount Trophies",
    "wof:placetype":"venue"
},
  "geometry": {"coordinates":[-2.9865698814,51.5729217529],"type":"Point"}
}