{
  "type": "Feature",
  "properties": {
    "addr:full":"The Bonded Warehouse, Hulkes La Rochester Kent ME1 1EE",
    "addr:postcode":"me1 1ee",
    "addr:street":"La",
    "iso:country":"GB",
    "sg:address":"The Bonded Warehouse, Hulkes La",
    "sg:city":"Rochester",
    "sg:classifiers":[
        {
            "category":"Health Services",
            "subcategory":"Clinic",
            "type":"Services"
        }
    ],
    "sg:postcode":"ME1 1EE",
    "sg:province":"Kent",
    "sg:tags":[
        "medical"
    ],
    "wof:name":"C & C Technical Services",
    "wof:placetype":"venue"
},
  "geometry": {"coordinates":[0.50467,51.38884],"type":"Point"}
}