{
  "type": "Feature",
  "properties": {
    "iso:country":"GB",
    "sg:address":"19 Edwin St",
    "sg:city":"Boston",
    "sg:classifiers":[
        {
            "category":"Home & Garden",
            "subcategory":"Furniture",
            "type":"Retail Goods"
        }
    ],
    "sg:postcode":"PE21 8TF",
    "sg:province":"Lincolnshire",
    "wof:name":"Ward,Michael Richard,",
    "wof:placetype":"venue"
},
  "geometry": {"coordinates":[-0.02393,52.972797],"type":"Point"}
}