{
  "type": "Feature",
  "properties": {
    "addr:full":"47 Old Town London Greater London SW4 0JL",
    "addr:housenumber":"47",
    "addr:postcode":"sw4 0jl",
    "addr:street":"Old Town",
    "iso:country":"GB",
    "sg:address":"47 Old Town",
    "sg:city":"London",
    "sg:classifiers":[
        {
            "category":"Bars & Pubs",
            "type":"Food & Drink"
        }
    ],
    "sg:phone":"+44 20 7622 4980",
    "sg:postcode":"SW4 0JL",
    "sg:province":"Greater London",
    "sg:tags":[
        "pubs",
        "inn"
    ],
    "wof:name":"The Sun",
    "wof:placetype":"venue"
},
  "geometry": {"coordinates":[-0.1409250051,51.4639015198],"type":"Point"}
}