{
  "type": "Feature",
  "properties": {
    "iso:country":"GB",
    "sg:address":"Rosesuggan Farm, Trekenning",
    "sg:city":"Newquay",
    "sg:classifiers":[
        {
            "category":"Banks & Credit Unions",
            "subcategory":"Investment Brokerage",
            "type":"Services"
        },
        {
            "category":"Real Estate",
            "subcategory":"Real Estate Agent",
            "type":"Services"
        }
    ],
    "sg:phone":"+44 1637 880453",
    "sg:postcode":"TR8 4JD",
    "sg:province":"Cornwall",
    "sg:tags":[
        "contractor"
    ],
    "wof:name":"Alan James Richards",
    "wof:placetype":"venue"
},
  "geometry": {"coordinates":[-4.948103,50.424538],"type":"Point"}
}