{
  "type": "Feature",
  "properties": {
    "iso:country":"GB",
    "sg:address":"40 Cold Bath Road",
    "sg:city":"Harrogate",
    "sg:classifiers":[
        {
            "category":"Retail",
            "subcategory":"Laundry & Dry Cleaning",
            "type":"Services"
        }
    ],
    "sg:phone":"+44 1423 504214",
    "sg:postcode":"HG2 0NX",
    "sg:province":"North Yorkshire",
    "sg:tags":[
        "cleaner",
        "alteration"
    ],
    "wof:name":"Prontaclean",
    "wof:placetype":"venue"
},
  "geometry": {"coordinates":[-1.5494829416,53.9886932373],"type":"Point"}
}