{
  "type": "Feature",
  "properties": {
    "addr:full":"1097 Pollokshaws Road Glasgow Glasgow City G41 3YG",
    "addr:housenumber":"1097",
    "addr:postcode":"g41 3yg",
    "addr:street":"Pollokshaws Road",
    "iso:country":"GB",
    "sg:address":"1097 Pollokshaws Road",
    "sg:city":"Glasgow",
    "sg:classifiers":[
        {
            "category":"Bars & Pubs",
            "type":"Food & Drink"
        },
        {
            "category":"Community Center",
            "subcategory":"Social",
            "type":"Public Place"
        }
    ],
    "sg:phone":"+44 141 632 2317",
    "sg:postcode":"G41 3YG",
    "sg:province":"Glasgow City",
    "sg:tags":[
        "pubs",
        "house",
        "inn",
        "activity"
    ],
    "wof:name":"Georgic Bar",
    "wof:placetype":"venue"
},
  "geometry": {"coordinates":[-4.2798919678,55.8309364319],"type":"Point"}
}