{
  "type": "Feature",
  "properties": {
    "iso:country":"GB",
    "sg:address":"Whitehill Farm, Head Of Muir",
    "sg:city":"Denny",
    "sg:classifiers":[
        {
            "category":"Retail",
            "subcategory":"Auto Repair",
            "type":"Services"
        }
    ],
    "sg:phone":"+44 1324 841515",
    "sg:postcode":"FK6 5NA",
    "sg:province":"Falkirk",
    "sg:tags":[
        "bodybuilder",
        "repairer"
    ],
    "wof:name":"James Ritchie Commercial Body Builders",
    "wof:placetype":"venue"
},
  "geometry": {"coordinates":[-3.916404,56.014584],"type":"Point"}
}