{
  "type": "Feature",
  "properties": {
    "iso:country":"GB",
    "sg:address":"Post House Wynd",
    "sg:city":"Darlington",
    "sg:classifiers":[
        {
            "category":"Bars & Pubs",
            "type":"Food & Drink"
        }
    ],
    "sg:phone":"+44 1325 460458",
    "sg:postcode":"DL3 7LU",
    "sg:province":"Durham",
    "sg:tags":[
        "pubs",
        "inn"
    ],
    "wof:name":"Old Dunn Cow Inn",
    "wof:placetype":"venue"
},
  "geometry": {"coordinates":[-1.55657,54.52491],"type":"Point"}
}