{
  "type": "Feature",
  "properties": {
    "addr:full":"3 Norman Road Ilford Essex IG1 2NH",
    "addr:housenumber":"3",
    "addr:postcode":"ig1 2nh",
    "addr:street":"Norman Road",
    "iso:country":"GB",
    "sg:address":"3 Norman Road",
    "sg:city":"Ilford",
    "sg:classifiers":[
        {
            "category":"Place Of Worship",
            "type":"Public Place"
        }
    ],
    "sg:phone":"+44 20 8514 4781",
    "sg:postcode":"IG1 2NH",
    "sg:province":"Essex",
    "wof:name":"Shree Sanatan Dharm Mandal",
    "wof:placetype":"venue"
},
  "geometry": {"coordinates":[0.0763359964,51.546585083],"type":"Point"}
}