{
  "type": "Feature",
  "properties": {
    "iso:country":"GB",
    "sg:address":"11 West Street",
    "sg:city":"Hereford",
    "sg:classifiers":[
        {
            "category":"Restaurant",
            "type":"Food & Drink"
        }
    ],
    "sg:phone":"+44 1432 266582",
    "sg:postcode":"HR4 0BX",
    "sg:province":"Herefordshire",
    "wof:name":"The Kingfisher Restaurant",
    "wof:placetype":"venue"
},
  "geometry": {"coordinates":[-2.71788,52.055843],"type":"Point"}
}