{
  "type": "Feature",
  "properties": {
    "addr:full":"2c Hunstanton Commercial Park, Kings Lynn Road Hunstanton Norfolk PE36 5JQ",
    "addr:housenumber":"2c",
    "addr:postcode":"pe36 5jq",
    "addr:street":"Hunstanton Commercial Park Kings Lynn Road",
    "iso:country":"GB",
    "sg:address":"2c Hunstanton Commercial Park, Kings Lynn Road",
    "sg:city":"Hunstanton",
    "sg:classifiers":[
        {
            "category":"Home & Garden",
            "subcategory":"Hardware",
            "type":"Retail Goods"
        }
    ],
    "sg:phone":"+44 1485 571471",
    "sg:postcode":"PE36 5JQ",
    "sg:province":"Norfolk",
    "sg:tags":[
        "heat",
        "mech",
        "exchanger"
    ],
    "wof:name":"Delta Catering Equipment",
    "wof:placetype":"venue"
},
  "geometry": {"coordinates":[0.4944050014,52.9371604919],"type":"Point"}
}