{
  "type": "Feature",
  "properties": {
    "addr:full":"3 Queen Street Deal Kent CT14 6ET",
    "addr:housenumber":"3",
    "addr:postcode":"ct14 6et",
    "addr:street":"Queen Street Deal",
    "iso:country":"GB",
    "sg:address":"3 Queen Street",
    "sg:city":"Deal",
    "sg:classifiers":[
        {
            "category":"Shopping",
            "subcategory":"Music",
            "type":"Retail Goods"
        }
    ],
    "sg:phone":"+44 1304 380859",
    "sg:postcode":"CT14 6ET",
    "sg:province":"Kent",
    "sg:tags":[
        "record",
        "tape",
        "cd"
    ],
    "wof:name":"Harry's Records",
    "wof:placetype":"venue"
},
  "geometry": {"coordinates":[1.4033210278,51.2229919434],"type":"Point"}
}