{
  "type": "Feature",
  "properties": {
    "addr:full":"7 St Stephens Court, 15-17 St Stephens Road Bournemouth Dorset BH2 6LA",
    "addr:housenumber":"7;15-17",
    "addr:postcode":"bh2 6la",
    "addr:street":"St Stephens Court;St Stephens Road",
    "iso:country":"GB",
    "sg:address":"7 St Stephens Court, 15-17 St Stephens Road",
    "sg:city":"Bournemouth",
    "sg:classifiers":[
        {
            "category":"Professional",
            "subcategory":"Computer Services",
            "type":"Services"
        }
    ],
    "sg:phone":"+44 7973 400258",
    "sg:postcode":"BH2 6LA",
    "sg:province":"Dorset",
    "sg:tags":[
        "system",
        "software"
    ],
    "wof:name":"Arena Qs Ltd.",
    "wof:placetype":"venue"
},
  "geometry": {"coordinates":[-1.880916,50.720406],"type":"Point"}
}