{
  "type": "Feature",
  "properties": {
    "addr:full":"Dean Basingstoke Hampshire RG25 3AX",
    "addr:postcode":"rg25 3ax",
    "iso:country":"GB",
    "sg:address":"Dean",
    "sg:city":"Basingstoke",
    "sg:classifiers":[
        {
            "category":"Place Of Worship",
            "type":"Public Place"
        }
    ],
    "sg:postcode":"RG25 3AX",
    "sg:province":"Hampshire",
    "wof:name":"All Saints C of E Church",
    "wof:placetype":"venue"
},
  "geometry": {"coordinates":[-1.255949,51.24308],"type":"Point"}
}