{
  "type": "Feature",
  "properties": {
    "iso:country":"GB",
    "sg:address":"Kingsland Avenue",
    "sg:city":"Coventry",
    "sg:classifiers":[
        {
            "category":"Place Of Worship",
            "type":"Public Place"
        },
        {
            "category":"Organizations",
            "subcategory":"Non-profit Organization",
            "type":"Services"
        }
    ],
    "sg:phone":"+44 24 7667 4161",
    "sg:postcode":"CV5 8DX",
    "sg:province":"West Midlands",
    "sg:tags":[
        "charitable",
        "organisation",
        "charity"
    ],
    "wof:name":"All Souls Catholic Church",
    "wof:placetype":"venue"
},
  "geometry": {"coordinates":[-1.537704,52.407318],"type":"Point"}
}