{
  "type": "Feature",
  "properties": {
    "iso:country":"GB",
    "sg:address":"239a Broadway",
    "sg:city":"Bexleyheath",
    "sg:classifiers":[
        {
            "category":"Manufacturing",
            "subcategory":"Petroleum Products",
            "type":"Manufacturing & Wholesale Goods"
        },
        {
            "category":"Building & Trades",
            "subcategory":"Construction",
            "type":"Services"
        }
    ],
    "sg:phone":"+44 20 8298 0068",
    "sg:postcode":"DA6 8DB",
    "sg:province":"Kent",
    "sg:tags":[
        "double",
        "glazing",
        "installers"
    ],
    "wof:name":"Briar Windows",
    "wof:placetype":"venue"
},
  "geometry": {"coordinates":[0.1383700073,51.4574661255],"type":"Point"}
}