{
  "type": "Feature",
  "properties": {
    "iso:country":"GB",
    "sg:address":"397 Sheldon Heath Road",
    "sg:city":"Birmingham",
    "sg:classifiers":[
        {
            "category":"Fast Food",
            "type":"Food & Drink"
        }
    ],
    "sg:phone":"+44 121 743 4649",
    "sg:postcode":"B26 2UB",
    "sg:province":"West Midlands",
    "sg:tags":[
        "away",
        "take"
    ],
    "wof:name":"Luk Wing Chinese Take Away",
    "wof:placetype":"venue"
},
  "geometry": {"coordinates":[-1.776919,52.464569],"type":"Point"}
}