{
  "type": "Feature",
  "properties": {
    "iso:country":"GB",
    "sg:address":"64 Brentwood Road",
    "sg:city":"Romford",
    "sg:classifiers":[
        {
            "category":"Fast Food",
            "type":"Food & Drink"
        }
    ],
    "sg:phone":"+44 1708 766350",
    "sg:postcode":"RM1 2EP",
    "sg:province":"Essex",
    "sg:tags":[
        "away",
        "take"
    ],
    "wof:name":"New Lee Ho Fook",
    "wof:placetype":"venue"
},
  "geometry": {"coordinates":[0.1876949966,51.571434021],"type":"Point"}
}