{
  "type": "Feature",
  "properties": {
    "addr:full":"York Street Bingley West Yorkshire BD16 2QW",
    "addr:postcode":"bd16 2qw",
    "addr:street":"York Street",
    "iso:country":"GB",
    "sg:address":"York Street",
    "sg:city":"Bingley",
    "sg:classifiers":[
        {
            "category":"Organizations",
            "subcategory":"Community Association",
            "type":"Services"
        },
        {
            "category":"Organizations",
            "subcategory":"Membership Organization",
            "type":"Services"
        }
    ],
    "sg:phone":"+44 1274 564318",
    "sg:postcode":"BD16 2QW",
    "sg:province":"West Yorkshire",
    "sg:tags":[
        "club",
        "social"
    ],
    "wof:name":"Bingley & District Working Mens Club",
    "wof:placetype":"venue"
},
  "geometry": {"coordinates":[-1.833534,53.84676],"type":"Point"}
}