{
  "type": "Feature",
  "properties": {
    "iso:country":"GB",
    "sg:address":"1 Bathgate Road, Armadale",
    "sg:city":"Bathgate",
    "sg:classifiers":[
        {
            "category":"Wholesale",
            "subcategory":"Auto Parts",
            "type":"Manufacturing & Wholesale Goods"
        }
    ],
    "sg:phone":"+44 1501 734111",
    "sg:postcode":"EH48 2PE",
    "sg:province":"West Lothian",
    "sg:tags":[
        "wholesaler",
        "tyre"
    ],
    "wof:name":"C P K Auto Products Ltd.",
    "wof:placetype":"venue"
},
  "geometry": {"coordinates":[-3.696744,55.89893],"type":"Point"}
}