{
  "type": "Feature",
  "properties": {
    "iso:country":"GB",
    "sg:address":"Marshman, Blackmill Farm, Acle New Road",
    "sg:city":"Great Yarmouth",
    "sg:classifiers":[
        {
            "category":"Farming",
            "subcategory":"Livestock Farm",
            "type":"Manufacturing & Wholesale Goods"
        }
    ],
    "sg:phone":"+44 1493 843463",
    "sg:postcode":"NR30 1TH",
    "sg:province":"Norfolk",
    "sg:tags":[
        "others"
    ],
    "wof:name":"Lord Fairhaven",
    "wof:placetype":"venue"
},
  "geometry": {"coordinates":[1.72399,52.612415],"type":"Point"}
}