{
  "type": "Feature",
  "properties": {
    "iso:country":"GB",
    "sg:address":"22-26 Boswell Square, Hillington Industrial Estate",
    "sg:city":"Glasgow",
    "sg:classifiers":[
        {
            "category":"Autos & Motor Vehicles",
            "subcategory":"Boat Sales",
            "type":"Retail Goods"
        }
    ],
    "sg:phone":"+44 141 883 8723",
    "sg:postcode":"G52 4BQ",
    "sg:province":"Glasgow City",
    "sg:tags":[
        "equipment"
    ],
    "wof:name":"Marinac Yacht Fittings Ltd.",
    "wof:placetype":"venue"
},
  "geometry": {"coordinates":[-4.369834,55.856514],"type":"Point"}
}