{
  "type": "Feature",
  "properties": {
    "addr:full":"12 Allenby Road Lytham St Annes Lancashire FY8 2DG",
    "addr:housenumber":"12",
    "addr:postcode":"fy8 2dg",
    "addr:street":"Allenby Road",
    "iso:country":"GB",
    "sg:address":"12 Allenby Road",
    "sg:city":"Lytham St Annes",
    "sg:classifiers":[
        {
            "category":"Professional",
            "subcategory":"Art Services",
            "type":"Services"
        },
        {
            "category":"Building & Trades",
            "subcategory":"Construction",
            "type":"Services"
        },
        {
            "category":"Manufacturing",
            "subcategory":"Paper Products",
            "type":"Manufacturing & Wholesale Goods"
        }
    ],
    "sg:phone":"+44 1253 727684",
    "sg:postcode":"FY8 2DG",
    "sg:province":"Lancashire",
    "sg:tags":[
        "cardboard",
        "decorator",
        "painter"
    ],
    "wof:name":"A Mattison",
    "wof:placetype":"venue"
},
  "geometry": {"coordinates":[-3.032662,53.757111],"type":"Point"}
}