{
  "type": "Feature",
  "properties": {
    "addr:full":"St Peters Road Milford Haven Pembrokeshire SA73 2BU",
    "addr:postcode":"sa73 2bu",
    "addr:street":"St Peters Road",
    "iso:country":"GB",
    "sg:address":"St Peters Road",
    "sg:city":"Milford Haven",
    "sg:classifiers":[
        {
            "category":"Community Center",
            "type":"Public Place"
        },
        {
            "category":"Government",
            "subcategory":"Office",
            "type":"Public Place"
        }
    ],
    "sg:phone":"+44 1646 693727",
    "sg:postcode":"SA73 2BU",
    "sg:province":"Pembrokeshire",
    "sg:tags":[
        "local",
        "centre"
    ],
    "wof:name":"Milford Haven Community Education Centre",
    "wof:placetype":"venue"
},
  "geometry": {"coordinates":[-5.040476,51.715981],"type":"Point"}
}