{
  "type": "Feature",
  "properties": {
    "iso:country":"GB",
    "sg:address":"55 Fairlawn Drive",
    "sg:city":"East Grinstead",
    "sg:classifiers":[
        {
            "category":"Food & Beverages",
            "subcategory":"Liquor & Beverages",
            "type":"Retail Goods"
        }
    ],
    "sg:phone":"+44 1342 324663",
    "sg:postcode":"RH19 1NS",
    "sg:province":"East Sussex",
    "sg:tags":[
        "beer",
        "spirit",
        "wines"
    ],
    "wof:name":"Pedro Romero Sherry",
    "wof:placetype":"venue"
},
  "geometry": {"coordinates":[-0.032335,51.129486],"type":"Point"}
}