{
  "type": "Feature",
  "properties": {
    "iso:country":"GB",
    "sg:address":"43 Burnt Oak Broadway",
    "sg:city":"Edgware",
    "sg:classifiers":[
        {
            "category":"Real Estate",
            "subcategory":"Real Estate Agent",
            "type":"Services"
        }
    ],
    "sg:postcode":"HA8 5JZ",
    "sg:province":"Greater London",
    "wof:name":"Mohan Properties Ltd",
    "wof:placetype":"venue"
},
  "geometry": {"coordinates":[-0.266966,51.599987],"type":"Point"}
}