{
  "type": "Feature",
  "properties": {
    "addr:full":"16 Osborne Av Doncaster North Yorkshire DN6 7SY",
    "addr:housenumber":"16",
    "addr:postcode":"dn6 7sy",
    "addr:street":"Osborne Av Doncaster",
    "iso:country":"GB",
    "sg:address":"16 Osborne Av",
    "sg:city":"Doncaster",
    "sg:classifiers":[
        {
            "category":"Building & Trades",
            "subcategory":"Landscaping Services",
            "type":"Services"
        }
    ],
    "sg:phone":"+44 1302 727770",
    "sg:postcode":"DN6 7SY",
    "sg:province":"North Yorkshire",
    "sg:tags":[
        "horticultural",
        "consultant"
    ],
    "wof:name":"Plantcare",
    "wof:placetype":"venue"
},
  "geometry": {"coordinates":[-1.2025079727,53.5682678223],"type":"Point"}
}