{
  "type": "Feature",
  "properties": {
    "addr:full":"2 Vinson Close Orpington Kent BR6 0PP",
    "addr:housenumber":"2",
    "addr:postcode":"br6 0pp",
    "addr:street":"Vinson Close",
    "iso:country":"GB",
    "sg:address":"2 Vinson Close",
    "sg:city":"Orpington",
    "sg:classifiers":[
        {
            "category":"Professional",
            "subcategory":"Business Services",
            "type":"Services"
        }
    ],
    "sg:phone":"+44 1689 877799",
    "sg:postcode":"BR6 0PP",
    "sg:province":"Kent",
    "sg:tags":[
        "import",
        "export",
        "agent"
    ],
    "wof:name":"S&B Herba Foods Ltd.",
    "wof:placetype":"venue"
},
  "geometry": {"coordinates":[0.097765,51.375568],"type":"Point"}
}