{
  "type": "Feature",
  "properties": {
    "addr:full":"Aberdeen Nde Centre Aberdeen Aberdeen City AB23 8JW",
    "addr:postcode":"ab23 8jw",
    "addr:street":"Aberdeen",
    "iso:country":"GB",
    "sg:address":"Aberdeen Nde Centre",
    "sg:city":"Aberdeen",
    "sg:classifiers":[
        {
            "category":"Professional",
            "type":"Services"
        },
        {
            "category":"Professional",
            "subcategory":"Testing Lab",
            "type":"Services"
        }
    ],
    "sg:phone":"+44 1224 822251",
    "sg:postcode":"AB23 8JW",
    "sg:province":"Aberdeen City",
    "sg:tags":[
        "equipment",
        "inspection",
        "calibration"
    ],
    "sg:website":"http://www.talonndt.com",
    "wof:name":"Talon NDT Ltd",
    "wof:placetype":"venue"
},
  "geometry": {"coordinates":[-2.0931,57.196758],"type":"Point"}
}