{
  "type": "Feature",
  "properties": {
    "addr:full":"176 Bredhurst Road Gillingham Kent ME8 0QX",
    "addr:housenumber":"176",
    "addr:postcode":"me8 0qx",
    "addr:street":"Bredhurst Road",
    "iso:country":"GB",
    "sg:address":"176 Bredhurst Road",
    "sg:city":"Gillingham",
    "sg:classifiers":[
        {
            "category":"Building & Trades",
            "subcategory":"Plumbing",
            "type":"Services"
        }
    ],
    "sg:postcode":"ME8 0QX",
    "sg:province":"Kent",
    "sg:tags":[
        "plumber",
        "heating"
    ],
    "wof:name":"Applied Plumbing Services",
    "wof:placetype":"venue"
},
  "geometry": {"coordinates":[0.583619,51.345085],"type":"Point"}
}