{
  "type": "Feature",
  "properties": {
    "iso:country":"GB",
    "sg:address":"99 Picasso Way, Shoeburyness",
    "sg:city":"Southend-on-sea",
    "sg:classifiers":[
        {
            "category":"Building & Trades",
            "subcategory":"Construction",
            "type":"Services"
        }
    ],
    "sg:phone":"+44 1702 295602",
    "sg:postcode":"SS3 9UZ",
    "sg:province":"Essex",
    "sg:tags":[
        "builder"
    ],
    "wof:name":"Bannister Property Services",
    "wof:placetype":"venue"
},
  "geometry": {"coordinates":[0.802044,51.540886],"type":"Point"}
}