{
  "type": "Feature",
  "properties": {
    "addr:full":"102 Queens Court, Queens Road, Clifton Bristol City of Bristol BS8 1NB",
    "addr:housenumber":"102",
    "addr:postcode":"bs8 1nb",
    "addr:street":"Queens Court Queens Road",
    "iso:country":"GB",
    "sg:address":"102 Queens Court, Queens Road, Clifton",
    "sg:city":"Bristol",
    "sg:classifiers":[
        {
            "category":"Personal",
            "subcategory":"Beauty Salon",
            "type":"Services"
        }
    ],
    "sg:phone":"+44 117 973 1351",
    "sg:postcode":"BS8 1NB",
    "sg:province":"City of Bristol",
    "sg:tags":[
        "unisex",
        "hairdresser"
    ],
    "wof:name":"Court Hairdressing",
    "wof:placetype":"venue"
},
  "geometry": {"coordinates":[-2.6116158962,51.4581298828],"type":"Point"}
}