{
  "type": "Feature",
  "properties": {
    "addr:full":"99 St Johns Hill Battersea Greater London SW11 1SY",
    "addr:housenumber":"99",
    "addr:postcode":"sw11 1sy",
    "addr:street":"St Johns Hill",
    "iso:country":"GB",
    "sg:address":"99 St Johns Hill",
    "sg:city":"Battersea",
    "sg:classifiers":[
        {
            "category":"Museum",
            "subcategory":"Art Museum",
            "type":"Entertainment"
        }
    ],
    "sg:phone":"+44 20 7350 2545",
    "sg:postcode":"SW11 1SY",
    "sg:province":"Greater London",
    "sg:tags":[
        "gallery"
    ],
    "wof:name":"Raw Art",
    "wof:placetype":"venue"
},
  "geometry": {"coordinates":[-0.1738449931,51.4614334106],"type":"Point"}
}