{
  "type": "Feature",
  "properties": {
    "addr:full":"Harveys Farm, Plush Dorchester Dorset DT2 7RJ",
    "addr:postcode":"dt2 7rj",
    "addr:street":"Dorset",
    "iso:country":"GB",
    "sg:address":"Harveys Farm, Plush",
    "sg:city":"Dorchester",
    "sg:classifiers":[
        {
            "category":"Professional",
            "type":"Services"
        },
        {
            "category":"Farming",
            "subcategory":"Dairy Farm",
            "type":"Manufacturing & Wholesale Goods"
        }
    ],
    "sg:phone":"+44 1300 348216",
    "sg:postcode":"DT2 7RJ",
    "sg:province":"Dorset",
    "sg:tags":[
        "agricultural",
        "contractor"
    ],
    "wof:name":"C R & D J Cake",
    "wof:placetype":"venue"
},
  "geometry": {"coordinates":[-2.407223,50.818035],"type":"Point"}
}