{
  "type": "Feature",
  "properties": {
    "addr:full":"81 Battersea Rise London Greater London SW11 1HN",
    "addr:housenumber":"81",
    "addr:postcode":"sw11 1hn",
    "addr:street":"Battersea Rise",
    "iso:country":"GB",
    "sg:address":"81 Battersea Rise",
    "sg:city":"London",
    "sg:classifiers":[
        {
            "category":"Real Estate",
            "subcategory":"Real Estate Operator",
            "type":"Services"
        },
        {
            "category":"Professional",
            "subcategory":"Employment Agencies",
            "type":"Services"
        }
    ],
    "sg:postcode":"SW11 1HN",
    "sg:province":"Greater London",
    "sg:tags":[
        "letting",
        "consultant",
        "agent"
    ],
    "wof:name":"Rise Employment Bureau",
    "wof:placetype":"venue"
},
  "geometry": {"coordinates":[-0.167667,51.460636],"type":"Point"}
}