{
  "type": "Feature",
  "properties": {
    "addr:full":"87b Evelt Bridge Durham Durham DH1 3AG",
    "addr:housenumber":"87b",
    "addr:postcode":"dh1 3ag",
    "addr:street":"Evelt Bridge",
    "iso:country":"GB",
    "sg:address":"87b Evelt Bridge",
    "sg:city":"Durham",
    "sg:classifiers":[
        {
            "category":"Shopping",
            "subcategory":"Antiques",
            "type":"Retail Goods"
        }
    ],
    "sg:phone":"+44 191 386 0728",
    "sg:postcode":"DH1 3AG",
    "sg:province":"Durham",
    "wof:name":"Old & Gold",
    "wof:placetype":"venue"
},
  "geometry": {"coordinates":[-1.572175,54.775715],"type":"Point"}
}