{
  "type": "Feature",
  "properties": {
    "iso:country":"GB",
    "sg:address":"36 The Crescent",
    "sg:city":"Farnham",
    "sg:classifiers":[
        {
            "category":"Manufacturing",
            "subcategory":"Metals",
            "type":"Manufacturing & Wholesale Goods"
        }
    ],
    "sg:phone":"+44 1252 313302",
    "sg:postcode":"GU9 0LG",
    "sg:province":"Surrey",
    "sg:tags":[
        "steel",
        "fabricator",
        "erectors"
    ],
    "wof:name":"Evesham Industrial Supplies Ltd",
    "wof:placetype":"venue"
},
  "geometry": {"coordinates":[-0.791273,51.238827],"type":"Point"}
}