{
  "type": "Feature",
  "properties": {
    "addr:full":"Unit 12, Ashfield Road Trad Est, Ashfield Rd Salisbury Wiltshire SP2 7HL",
    "addr:housenumber":"unit 12",
    "addr:postcode":"sp2 7hl",
    "addr:street":"Ashfield Road Trad Est Ashfield Rd",
    "iso:country":"GB",
    "sg:address":"Unit 12, Ashfield Road Trad Est, Ashfield Rd",
    "sg:city":"Salisbury",
    "sg:classifiers":[
        {
            "category":"Professional",
            "subcategory":"Printing & Photocopies",
            "type":"Services"
        }
    ],
    "sg:phone":"+44 1722 327888",
    "sg:postcode":"SP2 7HL",
    "sg:province":"Wiltshire",
    "sg:tags":[
        "process",
        "screen",
        "printer"
    ],
    "wof:name":"Durrington Press Ltd",
    "wof:placetype":"venue"
},
  "geometry": {"coordinates":[-1.8133440018,51.0714302063],"type":"Point"}
}