{
  "type": "Feature",
  "properties": {
    "iso:country":"GB",
    "sg:address":"11 Afon Terrace, Croesyceiliog",
    "sg:city":"Cwmbran",
    "sg:classifiers":[
        {
            "category":"Recreation",
            "subcategory":"Dog Park",
            "type":"Entertainment"
        }
    ],
    "sg:postcode":"NP44 2JZ",
    "sg:province":"Monmouthshire",
    "wof:name":"Val's Dog Salon",
    "wof:placetype":"venue"
},
  "geometry": {"coordinates":[-3.0143859386,51.6596221924],"type":"Point"}
}