{
  "type": "Feature",
  "properties": {
    "iso:country":"GB",
    "sg:address":"29-31 Green St",
    "sg:city":"Burnley",
    "sg:classifiers":[
        {
            "category":"Shopping",
            "subcategory":"Catalog Store",
            "type":"Retail Goods"
        }
    ],
    "sg:postcode":"BB10 1UZ",
    "sg:province":"Lancashire",
    "sg:tags":[
        "mail",
        "order"
    ],
    "wof:name":"Stowell,Christine,",
    "wof:placetype":"venue"
},
  "geometry": {"coordinates":[-2.2315289974,53.8040390015],"type":"Point"}
}