{
  "type": "Feature",
  "properties": {
    "addr:full":"214 Northwood Road Uxbridge Buckinghamshire UB9 6PT",
    "addr:housenumber":"214",
    "addr:postcode":"ub9 6pt",
    "addr:street":"Northwood Road",
    "iso:country":"GB",
    "sg:address":"214 Northwood Road",
    "sg:city":"Uxbridge",
    "sg:classifiers":[
        {
            "category":"Home & Garden",
            "subcategory":"Building Materials",
            "type":"Retail Goods"
        }
    ],
    "sg:postcode":"UB9 6PT",
    "sg:province":"Buckinghamshire",
    "sg:tags":[
        "gate",
        "door",
        "barrier"
    ],
    "wof:name":"Piper Fabrications & Fencing Supplies Ltd.",
    "wof:placetype":"venue"
},
  "geometry": {"coordinates":[-0.4655840099,51.6098899841],"type":"Point"}
}