{
  "type": "Feature",
  "properties": {
    "addr:full":"Cresswell Morpeth Northumberland NE61 5JT",
    "addr:postcode":"ne61 5jt",
    "addr:street":"Northumberland",
    "iso:country":"GB",
    "sg:address":"Cresswell",
    "sg:city":"Morpeth",
    "sg:classifiers":[
        {
            "category":"Recreation",
            "subcategory":"Campground",
            "type":"Entertainment"
        }
    ],
    "sg:phone":"+44 1670 860411",
    "sg:postcode":"NE61 5JT",
    "sg:province":"Northumberland",
    "sg:tags":[
        "holiday",
        "centre",
        "camp"
    ],
    "wof:name":"Cresswell Towers",
    "wof:placetype":"venue"
},
  "geometry": {"coordinates":[-1.5440599918,55.2334594727],"type":"Point"}
}