{
  "type": "Feature",
  "properties": {
    "addr:full":"15 Queens Road, Seaton Sluice Whitley Bay Northumberland NE26 4DS",
    "addr:housenumber":"15",
    "addr:postcode":"ne26 4ds",
    "addr:street":"Queens Road",
    "iso:country":"GB",
    "sg:address":"15 Queens Road, Seaton Sluice",
    "sg:city":"Whitley Bay",
    "sg:classifiers":[
        {
            "category":"Retail",
            "subcategory":"Driving School",
            "type":"Services"
        }
    ],
    "sg:phone":"+44 191 237 2552",
    "sg:postcode":"NE26 4DS",
    "sg:province":"Northumberland",
    "wof:name":"Roadtest",
    "wof:placetype":"venue"
},
  "geometry": {"coordinates":[-1.4747270346,55.0825843811],"type":"Point"}
}