{
  "type": "Feature",
  "properties": {
    "addr:full":"European Business Park, Taylors Line Oldbury West Midlands B69 2BN",
    "addr:postcode":"b69 2bn",
    "addr:street":"Taylors Line",
    "iso:country":"GB",
    "sg:address":"European Business Park, Taylors Line",
    "sg:city":"Oldbury",
    "sg:classifiers":[
        {
            "category":"Utilities",
            "subcategory":"Natural Gas",
            "type":"Services"
        }
    ],
    "sg:postcode":"B69 2BN",
    "sg:province":"West Midlands",
    "sg:tags":[
        "welding"
    ],
    "wof:name":"Bohler Thyssen Welding (U K) Ltd.",
    "wof:placetype":"venue"
},
  "geometry": {"coordinates":[-2.0298399925,52.5016517639],"type":"Point"}
}