{
  "type": "Feature",
  "properties": {
    "iso:country":"GB",
    "sg:address":"58b Crawford Street",
    "sg:city":"London",
    "sg:classifiers":[
        {
            "category":"Health Services",
            "subcategory":"Doctor",
            "type":"Services"
        }
    ],
    "sg:phone":"+44 20 7723 6324",
    "sg:postcode":"W1H 1HS",
    "sg:province":"Greater London",
    "sg:tags":[
        "practitioners"
    ],
    "wof:name":"Wong & Amakye Dr S S.K & J",
    "wof:placetype":"venue"
},
  "geometry": {"coordinates":[-0.160299,51.519661],"type":"Point"}
}