{
  "type": "Feature",
  "properties": {
    "iso:country":"GB",
    "sg:address":"348 Dewsbury Road",
    "sg:city":"Leeds",
    "sg:classifiers":[
        {
            "category":"Travel",
            "subcategory":"Hotels & Motels",
            "type":"Entertainment"
        }
    ],
    "sg:postcode":"LS11 7BD",
    "sg:province":"West Yorkshire",
    "sg:tags":[
        "house",
        "guest"
    ],
    "wof:name":"Park House",
    "wof:placetype":"venue"
},
  "geometry": {"coordinates":[-1.5535900593,53.7682876587],"type":"Point"}
}