{
  "type": "Feature",
  "properties": {
    "addr:full":"244 Chiswick High Road London Greater London W4 1PD",
    "addr:housenumber":"244",
    "addr:postcode":"w4 1pd",
    "addr:street":"Chiswick High Road",
    "iso:country":"GB",
    "sg:address":"244 Chiswick High Road",
    "sg:city":"London",
    "sg:classifiers":[
        {
            "category":"Banks & Credit Unions",
            "subcategory":"Bureau De Change",
            "type":"Services"
        }
    ],
    "sg:phone":"+44 20 8987 8766",
    "sg:postcode":"W4 1PD",
    "sg:province":"Greater London",
    "wof:name":"American Express Europe Ltd.",
    "wof:placetype":"venue"
},
  "geometry": {"coordinates":[-0.258132,51.492634],"type":"Point"}
}