{
  "type": "Feature",
  "properties": {
    "addr:full":"3 Way Motors, Brompton Road Northallerton North Yorkshire DL6 1DY",
    "addr:housenumber":"3",
    "addr:postcode":"dl6 1dy",
    "addr:street":"Brompton Road",
    "iso:country":"GB",
    "sg:address":"3 Way Motors, Brompton Road",
    "sg:city":"Northallerton",
    "sg:classifiers":[
        {
            "category":"Autos & Motor Vehicles",
            "subcategory":"Automobile Sales",
            "type":"Retail Goods"
        }
    ],
    "sg:phone":"+44 1609 766999",
    "sg:postcode":"DL6 1DY",
    "sg:province":"North Yorkshire",
    "sg:tags":[
        "car"
    ],
    "wof:name":"Vendesi",
    "wof:placetype":"venue"
},
  "geometry": {"coordinates":[-1.431524,54.338367],"type":"Point"}
}