{
  "type": "Feature",
  "properties": {
    "iso:country":"GB",
    "sg:address":"37 West High St",
    "sg:city":"Lauder",
    "sg:classifiers":[
        {
            "category":"Retail",
            "subcategory":"Auto Repair",
            "type":"Services"
        }
    ],
    "sg:phone":"+44 1578 722383",
    "sg:postcode":"TD2 6TF",
    "sg:province":"Scottish Borders",
    "sg:tags":[
        "modification",
        "garage"
    ],
    "wof:name":"Fortune's Garage",
    "wof:placetype":"venue"
},
  "geometry": {"coordinates":[-2.7499990463,55.7202606201],"type":"Point"}
}