{
  "type": "Feature",
  "properties": {
    "addr:full":"Muir Of Pert Farm, Crail Anstruther Fife KY10 3XL",
    "addr:postcode":"ky10 3xl",
    "addr:street":"Crail",
    "iso:country":"GB",
    "sg:address":"Muir Of Pert Farm, Crail",
    "sg:city":"Anstruther",
    "sg:classifiers":[
        {
            "category":"Farming",
            "subcategory":"Livestock Farm",
            "type":"Manufacturing & Wholesale Goods"
        }
    ],
    "sg:phone":"+44 1307 468831",
    "sg:postcode":"KY10 3XL",
    "sg:province":"Fife",
    "sg:tags":[
        "others"
    ],
    "wof:name":"David I Robertson (Farms) Ltd.",
    "wof:placetype":"venue"
},
  "geometry": {"coordinates":[-2.7009840012,56.2228851318],"type":"Point"}
}