{
  "type": "Feature",
  "properties": {
    "iso:country":"GB",
    "sg:address":"138 Park View Rd",
    "sg:city":"Welling",
    "sg:classifiers":[
        {
            "category":"Shopping",
            "subcategory":"Mobile Phones",
            "type":"Retail Goods"
        }
    ],
    "sg:phone":"+44 20 8304 3332",
    "sg:postcode":"DA16 1SJ",
    "sg:province":"Kent",
    "wof:name":"Dial Communications",
    "wof:placetype":"venue"
},
  "geometry": {"coordinates":[0.120995,51.460319519],"type":"Point"}
}