{
  "type": "Feature",
  "properties": {
    "iso:country":"GB",
    "sg:address":"13 Church Road",
    "sg:city":"Redditch",
    "sg:classifiers":[
        {
            "category":"Government",
            "subcategory":"Court House",
            "type":"Public Place"
        }
    ],
    "sg:phone":"+44 1527 67822",
    "sg:postcode":"B97 4AB",
    "sg:province":"Warwickshire",
    "wof:name":"County Court",
    "wof:placetype":"venue"
},
  "geometry": {"coordinates":[-1.9423079491,52.3079490662],"type":"Point"}
}