{
  "type": "Feature",
  "properties": {
    "iso:country":"GB",
    "sg:address":"172-174 Prince Consort Rd",
    "sg:city":"Gateshead",
    "sg:classifiers":[
        {
            "category":"Food & Beverages",
            "subcategory":"Groceries & Convenience Stores",
            "type":"Retail Goods"
        }
    ],
    "sg:phone":"+44 191 477 2473",
    "sg:postcode":"NE8 4DU",
    "sg:province":"Tyne and Wear",
    "wof:name":"Greenalls Food Store",
    "wof:placetype":"venue"
},
  "geometry": {"coordinates":[-1.6023130417,54.9540748596],"type":"Point"}
}