{
  "type": "Feature",
  "properties": {
    "addr:full":"168 Wills Crescent Hounslow Greater London TW3 2JD",
    "addr:housenumber":"168",
    "addr:postcode":"tw3 2jd",
    "addr:street":"Wills Crescent",
    "iso:country":"GB",
    "sg:address":"168 Wills Crescent",
    "sg:city":"Hounslow",
    "sg:classifiers":[
        {
            "category":"Building & Trades",
            "subcategory":"Construction",
            "type":"Services"
        }
    ],
    "sg:phone":"+44 20 8894 1511",
    "sg:postcode":"TW3 2JD",
    "sg:province":"Greater London",
    "sg:tags":[
        "builder"
    ],
    "wof:name":"W Munday & Son",
    "wof:placetype":"venue"
},
  "geometry": {"coordinates":[-0.36568,51.45496],"type":"Point"}
}