{
  "type": "Feature",
  "properties": {
    "addr:full":"Watling House, Sutherland Street Stoke-on-trent Staffordshire ST4 4HS",
    "addr:postcode":"st4 4hs",
    "addr:street":"Sutherland Street",
    "iso:country":"GB",
    "sg:address":"Watling House, Sutherland Street",
    "sg:city":"Stoke-on-trent",
    "sg:classifiers":[
        {
            "category":"Manufacturing",
            "subcategory":"Motor Vehicles & Parts",
            "type":"Manufacturing & Wholesale Goods"
        }
    ],
    "sg:phone":"+44 1782 846216",
    "sg:postcode":"ST4 4HS",
    "sg:province":"Staffordshire",
    "sg:tags":[
        "bearing"
    ],
    "wof:name":"Bearing Transmission Supplies Ltd.",
    "wof:placetype":"venue"
},
  "geometry": {"coordinates":[-2.1756839752,52.9988708496],"type":"Point"}
}