{
  "type": "Feature",
  "properties": {
    "iso:country":"GB",
    "sg:address":"40-44 Watermoor Road",
    "sg:city":"Cirencester",
    "sg:classifiers":[
        {
            "category":"Autos & Motor Vehicles",
            "subcategory":"Motorcycle Sales",
            "type":"Retail Goods"
        },
        {
            "category":"Personal",
            "subcategory":"Skin Care",
            "type":"Services"
        },
        {
            "category":"Social Services",
            "subcategory":"Retirement Home",
            "type":"Services"
        }
    ],
    "sg:phone":"+44 1285 652467",
    "sg:postcode":"GL7 1LD",
    "sg:province":"Gloucestershire",
    "sg:tags":[
        "residential",
        "part",
        "manufacturer",
        "accessory"
    ],
    "wof:name":"Peter Hammond Motor Cycles Ltd.",
    "wof:placetype":"venue"
},
  "geometry": {"coordinates":[-1.961608,51.710091],"type":"Point"}
}