{
  "type": "Feature",
  "properties": {
    "addr:full":"214 East Wood Mains Road, Clarkston Glasgow East Renfrewshire G76 7HA",
    "addr:housenumber":"214",
    "addr:postcode":"g76 7ha",
    "addr:street":"East Wood Mains Road",
    "iso:country":"GB",
    "sg:address":"214 East Wood Mains Road, Clarkston",
    "sg:city":"Glasgow",
    "sg:classifiers":[
        {
            "category":"Real Estate",
            "subcategory":"Real Estate Agent",
            "type":"Services"
        }
    ],
    "sg:phone":"+44 141 638 7083",
    "sg:postcode":"G76 7HA",
    "sg:province":"East Renfrewshire",
    "wof:name":"Bradford & Bingley Dormant 15 Ltd.",
    "wof:placetype":"venue"
},
  "geometry": {"coordinates":[-4.2756938934,55.7833061218],"type":"Point"}
}