{
  "type": "Feature",
  "properties": {
    "addr:full":"Brooke Trading Estate, Lyon Road Brentwood Essex RM1 2AT",
    "addr:postcode":"rm1 2at",
    "addr:street":"Lyon Road",
    "iso:country":"GB",
    "sg:address":"Brooke Trading Estate, Lyon Road",
    "sg:city":"Brentwood",
    "sg:classifiers":[
        {
            "category":"Professional",
            "subcategory":"Engineering",
            "type":"Services"
        }
    ],
    "sg:phone":"+44 1708 736600",
    "sg:postcode":"RM1 2AT",
    "sg:province":"Essex",
    "sg:tags":[
        "precision",
        "engineer"
    ],
    "wof:name":"Brennan Tool & Engineering Co. Ltd.",
    "wof:placetype":"venue"
},
  "geometry": {"coordinates":[0.1893399954,51.569770813],"type":"Point"}
}