{
  "type": "Feature",
  "properties": {
    "iso:country":"GB",
    "sg:address":"Jubilee House, 7a Hill Street",
    "sg:city":"Saffron Walden",
    "sg:classifiers":[
        {
            "category":"Home & Garden",
            "subcategory":"Furniture",
            "type":"Retail Goods"
        }
    ],
    "sg:phone":"+44 1799 520957",
    "sg:postcode":"CB10 1EH",
    "sg:province":"Cambridgeshire",
    "sg:tags":[
        "bed",
        "mattress"
    ],
    "wof:name":"E Q U Ltd.",
    "wof:placetype":"venue"
},
  "geometry": {"coordinates":[0.2413990051,52.0229072571],"type":"Point"}
}