{
  "type": "Feature",
  "properties": {
    "addr:full":"10 Claremont Newport Newport NP20 6PJ",
    "addr:housenumber":"10",
    "addr:postcode":"np20 6pj",
    "addr:street":"Claremont",
    "iso:country":"GB",
    "sg:address":"10 Claremont",
    "sg:city":"Newport",
    "sg:classifiers":[
        {
            "category":"Utilities",
            "subcategory":"Fuel Oil & Lpg",
            "type":"Services"
        }
    ],
    "sg:phone":"+44 1633 853914",
    "sg:postcode":"NP20 6PJ",
    "sg:province":"Newport",
    "sg:tags":[
        "coal",
        "smokeless"
    ],
    "wof:name":"Mel Swift & Son",
    "wof:placetype":"venue"
},
  "geometry": {"coordinates":[-3.001760006,51.6185188293],"type":"Point"}
}