{
  "type": "Feature",
  "properties": {
    "addr:full":"Norman Way Industrial Estate, Norman Way Cambridge Cambridgeshire CB4 5QE",
    "addr:housenumber":"estate",
    "addr:postcode":"cb4 5qe",
    "addr:street":"Norman Way Industrial;Norman Way",
    "iso:country":"GB",
    "sg:address":"Norman Way Industrial Estate, Norman Way",
    "sg:city":"Cambridge",
    "sg:classifiers":[
        {
            "category":"Professional",
            "subcategory":"Engineering",
            "type":"Services"
        }
    ],
    "sg:phone":"+44 1954 230018",
    "sg:postcode":"CB4 5QE",
    "sg:province":"Cambridgeshire",
    "sg:tags":[
        "precision",
        "engineer"
    ],
    "wof:name":"Ford Cliff Precision Engineering",
    "wof:placetype":"venue"
},
  "geometry": {"coordinates":[0.02027,52.304962],"type":"Point"}
}