{
  "type": "Feature",
  "properties": {
    "addr:full":"5 Bridge Street, Nungate Haddington East Lothian EH41 4AU",
    "addr:housenumber":"5",
    "addr:postcode":"eh41 4au",
    "addr:street":"Bridge Street Nungate Haddington",
    "iso:country":"GB",
    "sg:address":"5 Bridge Street, Nungate",
    "sg:city":"Haddington",
    "sg:classifiers":[
        {
            "category":"Bars & Pubs",
            "type":"Food & Drink"
        }
    ],
    "sg:phone":"+44 1620 822327",
    "sg:postcode":"EH41 4AU",
    "sg:province":"East Lothian",
    "sg:tags":[
        "pubs",
        "inn"
    ],
    "wof:name":"The Tall Bridge",
    "wof:placetype":"venue"
},
  "geometry": {"coordinates":[-2.7695589066,55.9546051025],"type":"Point"}
}