{
  "type": "Feature",
  "properties": {
    "addr:full":"29 Burnley Road East, Waterfoot Rossendale Lancashire BB4 9AG",
    "addr:housenumber":"29",
    "addr:postcode":"bb4 9ag",
    "addr:street":"Burnley Road East",
    "iso:country":"GB",
    "sg:address":"29 Burnley Road East, Waterfoot",
    "sg:city":"Rossendale",
    "sg:classifiers":[
        {
            "category":"Professional",
            "subcategory":"Management & Consulting",
            "type":"Services"
        }
    ],
    "sg:phone":"+44 1706 226662",
    "sg:postcode":"BB4 9AG",
    "sg:province":"Lancashire",
    "sg:tags":[
        "consultant",
        "business"
    ],
    "wof:name":"Judicious Management Consulting",
    "wof:placetype":"venue"
},
  "geometry": {"coordinates":[-2.2524020672,53.6941108704],"type":"Point"}
}