{
  "type": "Feature",
  "properties": {
    "addr:full":"Saywells Yard, Cromwell Road St Neots Bedfordshire PE19 2EU",
    "addr:postcode":"pe19 2eu",
    "addr:street":"Cromwell Road",
    "iso:country":"GB",
    "sg:address":"Saywells Yard, Cromwell Road",
    "sg:city":"St Neots",
    "sg:classifiers":[
        {
            "category":"Retail",
            "subcategory":"Auto Repair",
            "type":"Services"
        }
    ],
    "sg:phone":"+44 1480 213345",
    "sg:postcode":"PE19 2EU",
    "sg:province":"Bedfordshire",
    "sg:tags":[
        "body",
        "car",
        "repairer"
    ],
    "wof:name":"J D Autos",
    "wof:placetype":"venue"
},
  "geometry": {"coordinates":[-0.261874,52.227879],"type":"Point"}
}