{
  "type": "Feature",
  "properties": {
    "addr:full":"27 Kingshill Road Dursley Gloucestershire GL11 4BJ",
    "addr:housenumber":"27",
    "addr:postcode":"gl11 4bj",
    "addr:street":"Kingshill Road",
    "iso:country":"GB",
    "sg:address":"27 Kingshill Road",
    "sg:city":"Dursley",
    "sg:classifiers":[
        {
            "category":"Autos & Motor Vehicles",
            "subcategory":"Fuel & Gas Station",
            "type":"Retail Goods"
        }
    ],
    "sg:phone":"+44 1453 545896",
    "sg:postcode":"GL11 4BJ",
    "sg:province":"Gloucestershire",
    "sg:tags":[
        "hr",
        "filling",
        "petrol"
    ],
    "wof:name":"Wild Goose Garage",
    "wof:placetype":"venue"
},
  "geometry": {"coordinates":[-2.361699,51.689083],"type":"Point"}
}