{
  "type": "Feature",
  "properties": {
    "addr:full":"Ellison Street Jarrow Tyne and Wear NE32 3JU",
    "addr:postcode":"ne32 3ju",
    "addr:street":"Ellison Street",
    "iso:country":"GB",
    "sg:address":"Ellison Street",
    "sg:city":"Jarrow",
    "sg:classifiers":[
        {
            "category":"Freight",
            "type":"Transportation"
        },
        {
            "category":"Manufacturing",
            "subcategory":"Wood Products",
            "type":"Manufacturing & Wholesale Goods"
        }
    ],
    "sg:phone":"+44 191 483 2290",
    "sg:postcode":"NE32 3JU",
    "sg:province":"Tyne and Wear",
    "sg:tags":[
        "haulage",
        "packaging",
        "crate",
        "road",
        "pallets"
    ],
    "wof:name":"Valenbeck Ltd.",
    "wof:placetype":"venue"
},
  "geometry": {"coordinates":[-1.490955,54.982407],"type":"Point"}
}