{
  "type": "Feature",
  "properties": {
    "addr:full":"11 Church Rd Poole Dorset BH14 8UF",
    "addr:housenumber":"11",
    "addr:postcode":"bh14 8uf",
    "addr:street":"Church Rd",
    "iso:country":"GB",
    "sg:address":"11 Church Rd",
    "sg:city":"Poole",
    "sg:classifiers":[
        {
            "category":"Professional",
            "subcategory":"Engineering",
            "type":"Services"
        }
    ],
    "sg:phone":"+44 1202 710000",
    "sg:postcode":"BH14 8UF",
    "sg:province":"Dorset",
    "sg:tags":[
        "engineer",
        "structural"
    ],
    "wof:name":"Bourne Steel Ltd: Special Works Division",
    "wof:placetype":"venue"
},
  "geometry": {"coordinates":[-1.949352,50.723713],"type":"Point"}
}