{
  "type": "Feature",
  "properties": {
    "iso:country":"GB",
    "sg:address":"29 Maritime View",
    "sg:city":"Birkenhead",
    "sg:classifiers":[
        {
            "category":"Organizations",
            "subcategory":"Community Association",
            "type":"Services"
        }
    ],
    "sg:phone":"+44 151 653 8288",
    "sg:postcode":"L42 7LP",
    "sg:province":"Merseyside",
    "sg:tags":[
        "society",
        "housing"
    ],
    "wof:name":"Maritime View",
    "wof:placetype":"venue"
},
  "geometry": {"coordinates":[-3.0331950188,53.3877296448],"type":"Point"}
}