{
  "type": "Feature",
  "properties": {
    "addr:full":"Cronton Farm, Cronton Road Widnes Cheshire WA8 5PX",
    "addr:housenumber":"cronton",
    "addr:postcode":"wa8 5px",
    "addr:street":"Cronton Road",
    "iso:country":"GB",
    "sg:address":"Cronton Farm, Cronton Road",
    "sg:city":"Widnes",
    "sg:classifiers":[
        {
            "category":"Farming",
            "subcategory":"Livestock Farm",
            "type":"Manufacturing & Wholesale Goods"
        }
    ],
    "sg:phone":"+44 151 424 3987",
    "sg:postcode":"WA8 5PX",
    "sg:province":"Cheshire",
    "sg:tags":[
        "others"
    ],
    "wof:name":"R Almond",
    "wof:placetype":"venue"
},
  "geometry": {"coordinates":[-2.7604589462,53.3892211914],"type":"Point"}
}