{
  "type": "Feature",
  "properties": {
    "addr:full":"5 Fordwich Road Welwyn Garden City Hertfordshire AL8 6EX",
    "addr:housenumber":"5",
    "addr:postcode":"al8 6ex",
    "addr:street":"Fordwich Road",
    "iso:country":"GB",
    "sg:address":"5 Fordwich Road",
    "sg:city":"Welwyn Garden City",
    "sg:classifiers":[
        {
            "category":"Building & Trades",
            "subcategory":"Landscaping Services",
            "type":"Services"
        }
    ],
    "sg:phone":"+44 1707 339087",
    "sg:postcode":"AL8 6EX",
    "sg:province":"Hertfordshire",
    "sg:tags":[
        "landscape",
        "contractor"
    ],
    "wof:name":"Paul Lambert Lanscape Gardener",
    "wof:placetype":"venue"
},
  "geometry": {"coordinates":[-0.2112659961,51.7943611145],"type":"Point"}
}