{
  "type": "Feature",
  "properties": {
    "addr:full":"Pentrebach Merthyr Tydfil Caerphilly CF48 4TU",
    "addr:postcode":"cf48 4tu",
    "addr:street":"Pentrebach",
    "iso:country":"GB",
    "sg:address":"Pentrebach",
    "sg:city":"Merthyr Tydfil",
    "sg:classifiers":[
        {
            "category":"Home & Garden",
            "subcategory":"Household Appliances",
            "type":"Retail Goods"
        },
        {
            "category":"Retail",
            "subcategory":"Repair Shop",
            "type":"Services"
        },
        {
            "category":"Shopping",
            "subcategory":"Computers & Home Electronics",
            "type":"Retail Goods"
        }
    ],
    "sg:phone":"+44 1685 721222",
    "sg:postcode":"CF48 4TU",
    "sg:province":"Caerphilly",
    "sg:tags":[
        "electrial",
        "electrical"
    ],
    "wof:name":"HOOVER LTD",
    "wof:placetype":"venue"
},
  "geometry": {"coordinates":[-3.36622,51.728149],"type":"Point"}
}