{
  "type": "Feature",
  "properties": {
    "iso:country":"GB",
    "sg:address":"18 Marmion Rd",
    "sg:city":"Southsea",
    "sg:classifiers":[
        {
            "category":"Shopping",
            "subcategory":"Thrift Store",
            "type":"Retail Goods"
        },
        {
            "category":"Organizations",
            "subcategory":"Membership Organization",
            "type":"Services"
        }
    ],
    "sg:phone":"+44 23 9287 0288",
    "sg:postcode":"PO5 2BA",
    "sg:province":"Hampshire",
    "sg:tags":[
        "shop",
        "club",
        "charity",
        "social"
    ],
    "wof:name":"Peoples Dispensary for Sick Animals",
    "wof:placetype":"venue"
},
  "geometry": {"coordinates":[-1.0875639915,50.7864112854],"type":"Point"}
}