{
  "type": "Feature",
  "properties": {
    "addr:full":"Heol Deg, Tonteg Pontypridd Rhondda, Cynon, Taff CF38 1EU",
    "addr:postcode":"cf38 1eu",
    "addr:street":"Heol Deg Tonteg",
    "iso:country":"GB",
    "sg:address":"Heol Deg, Tonteg",
    "sg:city":"Pontypridd",
    "sg:classifiers":[
        {
            "category":"Education",
            "subcategory":"School",
            "type":"Public Place"
        }
    ],
    "sg:phone":"+44 1443 202432",
    "sg:postcode":"CF38 1EU",
    "sg:province":"Rhondda, Cynon, Taff",
    "sg:tags":[
        "local",
        "authority"
    ],
    "wof:name":"Gwauncelyn Infant School",
    "wof:placetype":"venue"
},
  "geometry": {"coordinates":[-3.3077020645,51.5715637207],"type":"Point"}
}