{
  "type": "Feature",
  "properties": {
    "iso:country":"GB",
    "sg:address":"232 Hall Street",
    "sg:city":"Warrington",
    "sg:classifiers":[
        {
            "category":"Shopping",
            "subcategory":"Stationery & Office Supplies",
            "type":"Retail Goods"
        }
    ],
    "sg:phone":"+44 1925 634567",
    "sg:postcode":"WA1 2BY",
    "sg:province":"Cheshire",
    "sg:tags":[
        "equipment"
    ],
    "wof:name":"K Donoghue Ltd.",
    "wof:placetype":"venue"
},
  "geometry": {"coordinates":[-2.585549,53.38718],"type":"Point"}
}