{
  "type": "Feature",
  "properties": {
    "iso:country":"GB",
    "sg:address":"Edmonstone Road, Danderhall",
    "sg:city":"Dalkeith",
    "sg:classifiers":[
        {
            "category":"Arena",
            "subcategory":"Sports Club",
            "type":"Entertainment"
        },
        {
            "category":"Government",
            "subcategory":"Office",
            "type":"Public Place"
        }
    ],
    "sg:phone":"+44 131 654 1031",
    "sg:postcode":"EH22 1QG",
    "sg:province":"City of Edinburgh",
    "sg:tags":[
        "local",
        "ground"
    ],
    "wof:name":"Danderhall Pavilion",
    "wof:placetype":"venue"
},
  "geometry": {"coordinates":[-3.0686130524,55.8928794861],"type":"Point"}
}