{
  "type": "Feature",
  "properties": {
    "iso:country":"GB",
    "sg:address":"Towngate, Mapplewell",
    "sg:city":"Barnsley",
    "sg:classifiers":[
        {
            "category":"Bars & Pubs",
            "type":"Food & Drink"
        }
    ],
    "sg:phone":"+44 1226 385629",
    "sg:postcode":"S75 6AS",
    "sg:province":"South Yorkshire",
    "sg:tags":[
        "pubs",
        "inn"
    ],
    "wof:name":"Talbot Inn Bar & Restaurant",
    "wof:placetype":"venue"
},
  "geometry": {"coordinates":[-1.507604,53.582924],"type":"Point"}
}