{
  "type": "Feature",
  "properties": {
    "addr:full":"182 Thorn Road, Grangeway Runcorn Cheshire WA7 5JG",
    "addr:housenumber":"182",
    "addr:postcode":"wa7 5jg",
    "addr:street":"Thorn Road Grangeway",
    "iso:country":"GB",
    "sg:address":"182 Thorn Road, Grangeway",
    "sg:city":"Runcorn",
    "sg:classifiers":[
        {
            "category":"Retail",
            "subcategory":"Driving School",
            "type":"Services"
        }
    ],
    "sg:phone":"+44 1928 564868",
    "sg:postcode":"WA7 5JG",
    "sg:province":"Cheshire",
    "wof:name":"Grange School of Motoring",
    "wof:placetype":"venue"
},
  "geometry": {"coordinates":[-2.712654,53.327702],"type":"Point"}
}