{
  "type": "Feature",
  "properties": {
    "iso:country":"GB",
    "sg:address":"27 Penhill Road",
    "sg:city":"Bexley",
    "sg:classifiers":[
        {
            "category":"Taxi",
            "type":"Transportation"
        }
    ],
    "sg:postcode":"DA5 3EP",
    "sg:province":"Kent",
    "sg:tags":[
        "toastmaster"
    ],
    "wof:name":"Brian Hazelwood",
    "wof:placetype":"venue"
},
  "geometry": {"coordinates":[0.119347997,51.4464416504],"type":"Point"}
}