{
  "type": "Feature",
  "properties": {
    "addr:full":"Bryn Ynys Abererch Road Pwllheli Gwynedd LL53 6YP",
    "addr:postcode":"ll53 6yp",
    "addr:street":"Bryn;Abererch Road",
    "iso:country":"GB",
    "sg:address":"Bryn Ynys Abererch Road",
    "sg:city":"Pwllheli",
    "sg:classifiers":[
        {
            "category":"Health Services",
            "subcategory":"Podiatrist",
            "type":"Services"
        }
    ],
    "sg:phone":"+44 1758 614235",
    "sg:postcode":"LL53 6YP",
    "sg:province":"Gwynedd",
    "sg:tags":[
        "podiatrists",
        "chiropodist"
    ],
    "wof:name":"Elizabeth Ann Pugh",
    "wof:placetype":"venue"
},
  "geometry": {"coordinates":[-4.3814592361,52.9040031433],"type":"Point"}
}