{
  "type": "Feature",
  "properties": {
    "addr:full":"81 Foxberry Rd Brockley Greater London SE4 2SF",
    "addr:housenumber":"81",
    "addr:postcode":"se4 2sf",
    "addr:street":"Foxberry Rd",
    "iso:country":"GB",
    "sg:address":"81 Foxberry Rd",
    "sg:city":"Brockley",
    "sg:classifiers":[
        {
            "category":"Retail",
            "subcategory":"Storage",
            "type":"Services"
        }
    ],
    "sg:phone":"+44 20 8290 0181",
    "sg:postcode":"SE4 2SF",
    "sg:province":"Greater London",
    "sg:tags":[
        "household",
        "removal"
    ],
    "wof:name":"M.H. Removals",
    "wof:placetype":"venue"
},
  "geometry": {"coordinates":[-0.0362589993,51.4616088867],"type":"Point"}
}