{
  "type": "Feature",
  "properties": {
    "iso:country":"GB",
    "sg:address":"Unit 8 Marshalls Yard, Winchelsea Road",
    "sg:city":"Eastbourne",
    "sg:classifiers":[
        {
            "category":"Retail",
            "subcategory":"Auto Repair",
            "type":"Services"
        }
    ],
    "sg:phone":"+44 1323 430709",
    "sg:postcode":"BN22 7QE",
    "sg:province":"East Sussex",
    "sg:tags":[
        "modification",
        "garage"
    ],
    "wof:name":"Andrews Mechanical Services",
    "wof:placetype":"venue"
},
  "geometry": {"coordinates":[0.30585,50.78307],"type":"Point"}
}