{
  "type": "Feature",
  "properties": {
    "iso:country":"GB",
    "sg:address":", Starcross",
    "sg:city":"Exeter",
    "sg:classifiers":[
        {
            "category":"Retail",
            "subcategory":"Auto Repair",
            "type":"Services"
        }
    ],
    "sg:phone":"+44 1626 890315",
    "sg:postcode":"EX6 8QZ",
    "sg:province":"Devon",
    "sg:tags":[
        "modification",
        "garage"
    ],
    "wof:name":"Cockwood Service Station",
    "wof:placetype":"venue"
},
  "geometry": {"coordinates":[-3.447669,50.627014],"type":"Point"}
}