{
  "type": "Feature",
  "properties": {
    "iso:country":"GB",
    "sg:address":"8 Market Mews, Mayfair",
    "sg:city":"London",
    "sg:classifiers":[
        {
            "category":"Travel",
            "subcategory":"Travel Agent",
            "type":"Entertainment"
        }
    ],
    "sg:postcode":"W1J 7BZ",
    "sg:province":"Greater London",
    "wof:name":"Globeworth Ltd.",
    "wof:placetype":"venue"
},
  "geometry": {"coordinates":[-0.148108,51.506432],"type":"Point"}
}