{
  "type": "Feature",
  "properties": {
    "addr:full":"7 Prinknash Rd Bedford Bedfordshire MK41 8DJ",
    "addr:housenumber":"7",
    "addr:postcode":"mk41 8dj",
    "addr:street":"Prinknash Rd",
    "iso:country":"GB",
    "sg:address":"7 Prinknash Rd",
    "sg:city":"Bedford",
    "sg:classifiers":[
        {
            "category":"Professional",
            "subcategory":"Engineering",
            "type":"Services"
        }
    ],
    "sg:phone":"+44 1234 350430",
    "sg:postcode":"MK41 8DJ",
    "sg:province":"Bedfordshire",
    "sg:tags":[
        "contractor",
        "electrical",
        "engineer"
    ],
    "wof:name":"R O Jones",
    "wof:placetype":"venue"
},
  "geometry": {"coordinates":[-0.4441969991,52.1565093994],"type":"Point"}
}