{
  "type": "Feature",
  "properties": {
    "addr:full":"London Regional Office, 137-139 Brent Street London Greater London NW4 4DB",
    "addr:housenumber":"137-139",
    "addr:postcode":"nw4 4db",
    "addr:street":"Brent Street",
    "iso:country":"GB",
    "sg:address":"London Regional Office, 137-139 Brent Street",
    "sg:city":"London",
    "sg:classifiers":[
        {
            "category":"Building & Trades",
            "subcategory":"Construction",
            "type":"Services"
        }
    ],
    "sg:phone":"+44 20 7467 1000",
    "sg:postcode":"NW4 4DB",
    "sg:province":"Greater London",
    "sg:tags":[
        "contractor"
    ],
    "wof:name":"John Laing Construction Ltd.",
    "wof:placetype":"venue"
},
  "geometry": {"coordinates":[-0.231279999,51.5892791748],"type":"Point"}
}