{
  "type": "Feature",
  "properties": {
    "addr:full":"49 Stanmore Rd Stevenage Hertfordshire SG1 3QA",
    "addr:housenumber":"49",
    "addr:postcode":"sg1 3qa",
    "addr:street":"Stanmore Rd",
    "iso:country":"GB",
    "sg:address":"49 Stanmore Rd",
    "sg:city":"Stevenage",
    "sg:classifiers":[
        {
            "category":"Building & Trades",
            "subcategory":"Construction",
            "type":"Services"
        }
    ],
    "sg:phone":"+44 1438 352122",
    "sg:postcode":"SG1 3QA",
    "sg:province":"Hertfordshire",
    "sg:tags":[
        "builder"
    ],
    "wof:name":"Andrew Yates Builders",
    "wof:placetype":"venue"
},
  "geometry": {"coordinates":[-0.2044010013,51.9133377075],"type":"Point"}
}