{
  "type": "Feature",
  "properties": {
    "iso:country":"GB",
    "sg:address":"299 Brook St, Broughty Ferry",
    "sg:city":"Dundee",
    "sg:classifiers":[
        {
            "category":"Fast Food",
            "type":"Food & Drink"
        }
    ],
    "sg:phone":"+44 1382 738128",
    "sg:postcode":"DD5 2DS",
    "sg:province":"Angus",
    "sg:tags":[
        "away",
        "take"
    ],
    "wof:name":"The Chinese Cottage",
    "wof:placetype":"venue"
},
  "geometry": {"coordinates":[-2.8723740578,56.4670753479],"type":"Point"}
}