{
  "type": "Feature",
  "properties": {
    "addr:full":"15-17 Perry Common Road Birmingham West Midlands B23 7AB",
    "addr:housenumber":"15-17",
    "addr:postcode":"b23 7ab",
    "addr:street":"Perry Common Road",
    "iso:country":"GB",
    "sg:address":"15-17 Perry Common Road",
    "sg:city":"Birmingham",
    "sg:classifiers":[
        {
            "category":"Professional",
            "subcategory":"Testing Lab",
            "type":"Services"
        }
    ],
    "sg:phone":"+44 121 243 7896",
    "sg:postcode":"B23 7AB",
    "sg:province":"West Midlands",
    "sg:tags":[
        "mot"
    ],
    "wof:name":"Perry Common Mot Centre",
    "wof:placetype":"venue"
},
  "geometry": {"coordinates":[-1.8618940115,52.5319213867],"type":"Point"}
}