{
  "type": "Feature",
  "properties": {
    "addr:full":"Unit 4c Bonnington Industrial Estate, Newhaven Road Edinburgh City of Edinburgh EH6 5PY",
    "addr:housenumber":"unit 4c",
    "addr:postcode":"eh6 5py",
    "addr:street":"Bonnington Industrial Estate Newhaven Road",
    "iso:country":"GB",
    "sg:address":"Unit 4c Bonnington Industrial Estate, Newhaven Road",
    "sg:city":"Edinburgh",
    "sg:classifiers":[
        {
            "category":"Professional",
            "subcategory":"Engineering",
            "type":"Services"
        }
    ],
    "sg:phone":"+44 131 554 5700",
    "sg:postcode":"EH6 5PY",
    "sg:province":"City of Edinburgh",
    "sg:tags":[
        "contractor",
        "electrical",
        "engineer"
    ],
    "wof:name":"J A Buckley Technical Services Ltd.",
    "wof:placetype":"venue"
},
  "geometry": {"coordinates":[-3.18045,55.970161],"type":"Point"}
}