{
  "type": "Feature",
  "properties": {
    "addr:full":"Ty Isa, Trofarth Abergele Conwy LL22 8BD",
    "addr:postcode":"ll22 8bd",
    "addr:street":"Trofarth",
    "iso:country":"GB",
    "sg:address":"Ty Isa, Trofarth",
    "sg:city":"Abergele",
    "sg:classifiers":[
        {
            "category":"Farming",
            "subcategory":"Livestock Farm",
            "type":"Manufacturing & Wholesale Goods"
        }
    ],
    "sg:phone":"+44 1745 860664",
    "sg:postcode":"LL22 8BD",
    "sg:province":"Conwy",
    "sg:tags":[
        "others"
    ],
    "wof:name":"J E Williams",
    "wof:placetype":"venue"
},
  "geometry": {"coordinates":[-3.717229,53.23056],"type":"Point"}
}