{
  "type": "Feature",
  "properties": {
    "addr:full":"48 The Pantiles Tunbridge Wells East Sussex TN2 5TN",
    "addr:housenumber":"48",
    "addr:postcode":"tn2 5tn",
    "addr:street":"The Pantiles",
    "iso:country":"GB",
    "sg:address":"48 The Pantiles",
    "sg:city":"Tunbridge Wells",
    "sg:classifiers":[
        {
            "category":"Manufacturing",
            "subcategory":"Metals",
            "type":"Manufacturing & Wholesale Goods"
        },
        {
            "category":"Professional",
            "subcategory":"Business Services",
            "type":"Services"
        },
        {
            "category":"Shopping",
            "type":"Retail Goods"
        }
    ],
    "sg:phone":"+44 1892 522684",
    "sg:postcode":"TN2 5TN",
    "sg:province":"East Sussex",
    "sg:tags":[
        "steel",
        "shop",
        "import",
        "agent",
        "new age",
        "export",
        "fabricator"
    ],
    "wof:name":"G & B Butler",
    "wof:placetype":"venue"
},
  "geometry": {"coordinates":[0.2572839856,51.1256790161],"type":"Point"}
}