{
  "type": "Feature",
  "properties": {
    "iso:country":"GB",
    "sg:address":"153 East Parade",
    "sg:city":"Keighley",
    "sg:classifiers":[
        {
            "category":"Personal",
            "subcategory":"Beauty Salon",
            "type":"Services"
        }
    ],
    "sg:phone":"+44 1535 604959",
    "sg:postcode":"BD21 5HX",
    "sg:province":"West Yorkshire",
    "sg:tags":[
        "lady",
        "hairdresser"
    ],
    "wof:name":"Upper Cut",
    "wof:placetype":"venue"
},
  "geometry": {"coordinates":[-1.9035509825,53.8674163818],"type":"Point"}
}