{
  "type": "Feature",
  "properties": {
    "iso:country":"GB",
    "sg:address":"25 Shaftesbury Ave",
    "sg:city":"London",
    "sg:classifiers":[
        {
            "category":"Restaurant",
            "type":"Food & Drink"
        }
    ],
    "sg:postcode":"W1D 7EQ",
    "sg:province":"Greater London",
    "wof:name":"Timeweald Ltd",
    "wof:placetype":"venue"
},
  "geometry": {"coordinates":[-0.133742,51.51107],"type":"Point"}
}