{
  "type": "Feature",
  "properties": {
    "iso:country":"GB",
    "sg:address":"19 High Street, Kimbolton",
    "sg:city":"Huntingdon",
    "sg:classifiers":[
        {
            "category":"Restaurant",
            "type":"Food & Drink"
        }
    ],
    "sg:phone":"+44 1480 861587",
    "sg:postcode":"PE28 0HB",
    "sg:province":"Bedfordshire",
    "sg:tags":[
        "french"
    ],
    "wof:name":"la Cote D'Or",
    "wof:placetype":"venue"
},
  "geometry": {"coordinates":[-0.406389,52.346031],"type":"Point"}
}