{
  "type": "Feature",
  "properties": {
    "iso:country":"GB",
    "sg:address":"131 Palmerston Road, Southgate",
    "sg:city":"London",
    "sg:classifiers":[
        {
            "category":"Place Of Worship",
            "type":"Public Place"
        }
    ],
    "sg:phone":"+44 20 8888 4339",
    "sg:postcode":"N22 8QX",
    "sg:province":"Greater London",
    "wof:name":"Christian Science",
    "wof:placetype":"venue"
},
  "geometry": {"coordinates":[-0.114185,51.610989],"type":"Point"}
}