{
  "type": "Feature",
  "properties": {
    "iso:country":"GB",
    "sg:address":"141 South St",
    "sg:city":"Romford",
    "sg:classifiers":[
        {
            "category":"Bars & Pubs",
            "type":"Food & Drink"
        }
    ],
    "sg:phone":"+44 1708 730534",
    "sg:postcode":"RM1 1PL",
    "sg:province":"Essex",
    "sg:tags":[
        "pubs",
        "inn"
    ],
    "wof:name":"Temptations",
    "wof:placetype":"venue"
},
  "geometry": {"coordinates":[0.1837639958,51.5749664307],"type":"Point"}
}