{
  "type": "Feature",
  "properties": {
    "addr:full":"9 Clayton Rd Bradford West Yorkshire BD7 2LT",
    "addr:housenumber":"9",
    "addr:postcode":"bd7 2lt",
    "addr:street":"Clayton Rd",
    "iso:country":"GB",
    "sg:address":"9 Clayton Rd",
    "sg:city":"Bradford",
    "sg:classifiers":[
        {
            "category":"Restaurant",
            "type":"Food & Drink"
        }
    ],
    "sg:phone":"+44 1274 574773",
    "sg:postcode":"BD7 2LT",
    "sg:province":"West Yorkshire",
    "sg:tags":[
        "indian"
    ],
    "wof:name":"Pirmahall",
    "wof:placetype":"venue"
},
  "geometry": {"coordinates":[-1.7896449566,53.78698349],"type":"Point"}
}