{
  "type": "Feature",
  "properties": {
    "addr:full":"Marle Street Castle Douglas Dumfries and Galloway DG7 1DN",
    "addr:postcode":"dg7 1dn",
    "addr:street":"Marle Street",
    "iso:country":"GB",
    "sg:address":"Marle Street",
    "sg:city":"Castle Douglas",
    "sg:classifiers":[
        {
            "category":"Utilities",
            "subcategory":"Fuel Oil & Lpg",
            "type":"Services"
        }
    ],
    "sg:phone":"+44 1556 502918",
    "sg:postcode":"DG7 1DN",
    "sg:province":"Dumfries and Galloway",
    "sg:tags":[
        "distributor"
    ],
    "wof:name":"Uk Petroleum Products",
    "wof:placetype":"venue"
},
  "geometry": {"coordinates":[-3.9347438812,54.938041687],"type":"Point"}
}