{
  "type": "Feature",
  "properties": {
    "addr:full":"5 Longhurst Burgess Hill East Sussex RH15 0TG",
    "addr:housenumber":"5",
    "addr:postcode":"rh15 0tg",
    "addr:street":"Longhurst",
    "iso:country":"GB",
    "sg:address":"5 Longhurst",
    "sg:city":"Burgess Hill",
    "sg:classifiers":[
        {
            "category":"Communications",
            "type":"Services"
        }
    ],
    "sg:phone":"+44 1444 247444",
    "sg:postcode":"RH15 0TG",
    "sg:province":"East Sussex",
    "sg:tags":[
        "audio-visual"
    ],
    "wof:name":"Concept Video Productions",
    "wof:placetype":"venue"
},
  "geometry": {"coordinates":[-0.113375,50.953754],"type":"Point"}
}