{
  "type": "Feature",
  "properties": {
    "addr:full":"P O Box 700 Manchester Greater Manchester M60 3DZ",
    "addr:housenumber":"700",
    "addr:postcode":"m60 3dz",
    "addr:street":"P O Box",
    "iso:country":"GB",
    "sg:address":"P O Box 700",
    "sg:city":"Manchester",
    "sg:classifiers":[
        {
            "category":"Building & Trades",
            "subcategory":"Construction",
            "type":"Services"
        }
    ],
    "sg:phone":"+44 161 228 5551",
    "sg:postcode":"M60 3DZ",
    "sg:province":"Greater Manchester",
    "sg:tags":[
        "builder",
        "contractor"
    ],
    "wof:name":"Fastline Ltd.",
    "wof:placetype":"venue"
},
  "geometry": {"coordinates":[-2.2534999847,53.4796104431],"type":"Point"}
}