{
  "type": "Feature",
  "properties": {
    "addr:full":"21 Bushmead Avenue Bedford Bedfordshire MK40 3QJ",
    "addr:housenumber":"21",
    "addr:postcode":"mk40 3qj",
    "addr:street":"Bushmead Avenue",
    "iso:country":"GB",
    "sg:address":"21 Bushmead Avenue",
    "sg:city":"Bedford",
    "sg:classifiers":[
        {
            "category":"Health Services",
            "subcategory":"Doctor",
            "type":"Services"
        }
    ],
    "sg:phone":"+44 1234 349191",
    "sg:postcode":"MK40 3QJ",
    "sg:province":"Bedfordshire",
    "sg:tags":[
        "practitioners"
    ],
    "wof:name":"R F Jackson",
    "wof:placetype":"venue"
},
  "geometry": {"coordinates":[-0.456702,52.138489],"type":"Point"}
}