{
  "type": "Feature",
  "properties": {
    "addr:full":"18 Grasmere Road Bromley Kent BR1 4BA",
    "addr:housenumber":"18",
    "addr:postcode":"br1 4ba",
    "addr:street":"Grasmere Road",
    "iso:country":"GB",
    "sg:address":"18 Grasmere Road",
    "sg:city":"Bromley",
    "sg:classifiers":[
        {
            "category":"Shopping",
            "subcategory":"Pharmacy",
            "type":"Retail Goods"
        }
    ],
    "sg:phone":"+44 20 8464 9927",
    "sg:postcode":"BR1 4BA",
    "sg:province":"Kent",
    "sg:tags":[
        "medicine",
        "therapy"
    ],
    "wof:name":"Feng Shui Experience Ltd.",
    "wof:placetype":"venue"
},
  "geometry": {"coordinates":[0.005989,51.411598],"type":"Point"}
}