{
  "type": "Feature",
  "properties": {
    "addr:full":"49-50 Baxtergate Whitby North Yorkshire YO21 1BL",
    "addr:housenumber":"49-50",
    "addr:postcode":"yo21 1bl",
    "addr:street":"Baxtergate",
    "iso:country":"GB",
    "sg:address":"49-50 Baxtergate",
    "sg:city":"Whitby",
    "sg:classifiers":[
        {
            "category":"Shopping",
            "subcategory":"Pets & Pet Supplies",
            "type":"Retail Goods"
        }
    ],
    "sg:phone":"+44 1947 605970",
    "sg:postcode":"YO21 1BL",
    "sg:province":"North Yorkshire",
    "sg:tags":[
        "shop"
    ],
    "wof:name":"Whitby Aquatics",
    "wof:placetype":"venue"
},
  "geometry": {"coordinates":[-0.6162559986,54.4856147766],"type":"Point"}
}