{
  "type": "Feature",
  "properties": {
    "addr:full":"267 Chillingham Rd Newcastle Upon Tyne Tyne and Wear NE6 5LL",
    "addr:housenumber":"267",
    "addr:postcode":"ne6 5ll",
    "addr:street":"Chillingham Rd",
    "iso:country":"GB",
    "sg:address":"267 Chillingham Rd",
    "sg:city":"Newcastle Upon Tyne",
    "sg:classifiers":[
        {
            "category":"Autos & Motor Vehicles",
            "subcategory":"Automobile Sales",
            "type":"Retail Goods"
        }
    ],
    "sg:phone":"+44 191 265 5295",
    "sg:postcode":"NE6 5LL",
    "sg:province":"Tyne and Wear",
    "sg:tags":[
        "car"
    ],
    "wof:name":"Tynemouth Motor Co",
    "wof:placetype":"venue"
},
  "geometry": {"coordinates":[-1.5774760246,54.9873924255],"type":"Point"}
}