{
  "type": "Feature",
  "properties": {
    "addr:full":"57 West Street Sittingbourne Kent ME10 1AN",
    "addr:housenumber":"57",
    "addr:postcode":"me10 1an",
    "addr:street":"West Street",
    "iso:country":"GB",
    "sg:address":"57 West Street",
    "sg:city":"Sittingbourne",
    "sg:classifiers":[
        {
            "category":"Real Estate",
            "subcategory":"Real Estate Operator",
            "type":"Services"
        }
    ],
    "sg:postcode":"ME10 1AN",
    "sg:province":"Kent",
    "sg:tags":[
        "letting",
        "agent"
    ],
    "wof:name":"Lynden Associates Ltd.",
    "wof:placetype":"venue"
},
  "geometry": {"coordinates":[0.729564,51.341003],"type":"Point"}
}