{
  "type": "Feature",
  "properties": {
    "iso:country":"GB",
    "sg:address":"13 Pier Street",
    "sg:city":"Plymouth",
    "sg:classifiers":[
        {
            "category":"Travel",
            "subcategory":"Hotels & Motels",
            "type":"Entertainment"
        }
    ],
    "sg:postcode":"PL1 3BS",
    "sg:province":"Devon",
    "sg:tags":[
        "house",
        "guest"
    ],
    "wof:name":"The Firs",
    "wof:placetype":"venue"
},
  "geometry": {"coordinates":[-4.148535,50.364677],"type":"Point"}
}