{
  "type": "Feature",
  "properties": {
    "iso:country":"GB",
    "sg:address":"Badyen Farm, Cardross",
    "sg:city":"Dumbarton",
    "sg:classifiers":[
        {
            "category":"Farming",
            "subcategory":"Dairy Farm",
            "type":"Manufacturing & Wholesale Goods"
        },
        {
            "category":"Farming",
            "subcategory":"Livestock Farm",
            "type":"Manufacturing & Wholesale Goods"
        }
    ],
    "sg:phone":"+44 1389 841224",
    "sg:postcode":"G82 5HN",
    "sg:province":"Argyll and Bute",
    "wof:name":"James C McIntyre",
    "wof:placetype":"venue"
},
  "geometry": {"coordinates":[-4.654734,55.963436],"type":"Point"}
}