{
  "type": "Feature",
  "properties": {
    "addr:full":"Croft Farm, Banbury Road Stratford-upon-avon Warwickshire CV37 7NF",
    "addr:postcode":"cv37 7nf",
    "addr:street":"Banbury Road",
    "iso:country":"GB",
    "sg:address":"Croft Farm, Banbury Road",
    "sg:city":"Stratford-upon-avon",
    "sg:classifiers":[
        {
            "category":"Farming",
            "subcategory":"Crops",
            "type":"Manufacturing & Wholesale Goods"
        },
        {
            "category":"Farming",
            "subcategory":"Livestock Farm",
            "type":"Manufacturing & Wholesale Goods"
        }
    ],
    "sg:phone":"+44 1789 292159",
    "sg:postcode":"CV37 7NF",
    "sg:province":"Warwickshire",
    "sg:tags":[
        "arable",
        "others"
    ],
    "wof:name":"E J & S J Davies",
    "wof:placetype":"venue"
},
  "geometry": {"coordinates":[-1.707269,52.194134],"type":"Point"}
}