{
  "type": "Feature",
  "properties": {
    "iso:country":"GB",
    "sg:address":"75b Beatrice Street",
    "sg:city":"Oswestry",
    "sg:classifiers":[
        {
            "category":"Professional",
            "subcategory":"Computer Services",
            "type":"Services"
        }
    ],
    "sg:postcode":"SY11 1QR",
    "sg:province":"Shropshire",
    "sg:tags":[
        "system",
        "software"
    ],
    "wof:name":"K D Computers",
    "wof:placetype":"venue"
},
  "geometry": {"coordinates":[-3.0518,52.862221],"type":"Point"}
}