{
  "type": "Feature",
  "properties": {
    "iso:country":"GB",
    "sg:address":"20 Sedgebrook",
    "sg:city":"Swindon",
    "sg:classifiers":[
        {
            "category":"Manufacturing",
            "subcategory":"Petroleum Products",
            "type":"Manufacturing & Wholesale Goods"
        },
        {
            "category":"Building & Trades",
            "subcategory":"Construction",
            "type":"Services"
        }
    ],
    "sg:phone":"+44 1793 618418",
    "sg:postcode":"SN3 6EY",
    "sg:province":"Wiltshire",
    "sg:tags":[
        "double",
        "builder",
        "glazing"
    ],
    "wof:name":"Pace Construction",
    "wof:placetype":"venue"
},
  "geometry": {"coordinates":[-1.7316839695,51.5448379517],"type":"Point"}
}