{
  "type": "Feature",
  "properties": {
    "iso:country":"GB",
    "sg:address":"Unit 2 Hinchcliffe Yard Church Lane, Maltby",
    "sg:city":"Rotherham",
    "sg:classifiers":[
        {
            "category":"Building & Trades",
            "subcategory":"Cleaning & Sanitation",
            "type":"Services"
        }
    ],
    "sg:phone":"+44 1709 815863",
    "sg:postcode":"S66 8JB",
    "sg:province":"South Yorkshire",
    "sg:tags":[
        "blast"
    ],
    "wof:name":"D B Blasting Services",
    "wof:placetype":"venue"
},
  "geometry": {"coordinates":[-1.2069900036,53.4216499329],"type":"Point"}
}