{
  "type": "Feature",
  "properties": {
    "addr:full":"4 Walkergate Cornhill-on-tweed Northumberland TD15 1DB",
    "addr:housenumber":"4;cornhill-on-tweed",
    "addr:postcode":"td15 1db",
    "addr:street":"Walkergate;Northumberland",
    "iso:country":"GB",
    "sg:address":"4 Walkergate",
    "sg:city":"Cornhill-on-tweed",
    "sg:classifiers":[
        {
            "category":"Fast Food",
            "type":"Food & Drink"
        }
    ],
    "sg:phone":"+44 1289 331238",
    "sg:postcode":"TD15 1DB",
    "sg:province":"Northumberland",
    "sg:tags":[
        "away",
        "take"
    ],
    "wof:name":"New China Palace",
    "wof:placetype":"venue"
},
  "geometry": {"coordinates":[-2.007024,55.771435],"type":"Point"}
}