{
  "type": "Feature",
  "properties": {
    "addr:full":"Eagle Wharf, 59 Lafone St London Greater London SE1 2LX",
    "addr:housenumber":"59",
    "addr:postcode":"se1 2lx",
    "addr:street":"Eagle;Lafone St",
    "iso:country":"GB",
    "sg:address":"Eagle Wharf, 59 Lafone St",
    "sg:city":"London",
    "sg:classifiers":[
        {
            "category":"Autos & Motor Vehicles",
            "subcategory":"Auto Supplies",
            "type":"Retail Goods"
        }
    ],
    "sg:postcode":"SE1 2LX",
    "sg:province":"Greater London",
    "sg:tags":[
        "transmission",
        "equipment",
        "power"
    ],
    "wof:name":"Borma International Ltd",
    "wof:placetype":"venue"
},
  "geometry": {"coordinates":[-0.074500002,51.5035705566],"type":"Point"}
}