{
  "type": "Feature",
  "properties": {
    "addr:full":"50 High St Windsor Berkshire SL4 6BL",
    "addr:housenumber":"50",
    "addr:postcode":"sl4 6bl",
    "addr:street":"High St",
    "iso:country":"GB",
    "sg:address":"50 High St",
    "sg:city":"Windsor",
    "sg:classifiers":[
        {
            "category":"Shopping",
            "subcategory":"Antiques",
            "type":"Retail Goods"
        }
    ],
    "sg:phone":"+44 1753 860337",
    "sg:postcode":"SL4 6BL",
    "sg:province":"Berkshire",
    "wof:name":"Eaton's Of Eton Ltd",
    "wof:placetype":"venue"
},
  "geometry": {"coordinates":[-0.6086829901,51.4873809814],"type":"Point"}
}