{
  "type": "Feature",
  "properties": {
    "addr:full":"100 Cricklewood Bdwy London Greater London NW2 2EL",
    "addr:housenumber":"100",
    "addr:postcode":"nw2 2el",
    "addr:street":"Cricklewood Bdwy",
    "iso:country":"GB",
    "sg:address":"100 Cricklewood Bdwy",
    "sg:city":"London",
    "sg:classifiers":[
        {
            "category":"Autos & Motor Vehicles",
            "subcategory":"Auto Supplies",
            "type":"Retail Goods"
        }
    ],
    "sg:phone":"+44 20 8450 7683",
    "sg:postcode":"NW2 2EL",
    "sg:province":"Greater London",
    "sg:tags":[
        "tyre"
    ],
    "wof:name":"Grays Tyre & Exhaust Centres Ltd.",
    "wof:placetype":"venue"
},
  "geometry": {"coordinates":[-0.20446,51.561298],"type":"Point"}
}