{
  "type": "Feature",
  "properties": {
    "iso:country":"GB",
    "sg:address":"Salts Mill Road",
    "sg:city":"Shipley",
    "sg:classifiers":[
        {
            "category":"Travel",
            "subcategory":"Hotels & Motels",
            "type":"Entertainment"
        }
    ],
    "sg:phone":"+44 1274 589333",
    "sg:postcode":"BD18 3TT",
    "sg:province":"West Yorkshire",
    "wof:name":"Holiday Inn Express",
    "wof:placetype":"venue"
},
  "geometry": {"coordinates":[-1.783774,53.836895],"type":"Point"}
}