{
  "type": "Feature",
  "properties": {
    "iso:country":"GB",
    "sg:address":"Fowlswick Farm",
    "sg:city":"Chippenham",
    "sg:classifiers":[
        {
            "category":"Utilities",
            "subcategory":"Refuse",
            "type":"Services"
        }
    ],
    "sg:postcode":"SN14 6LT",
    "sg:province":"Gloucestershire",
    "sg:tags":[
        "skip",
        "hire"
    ],
    "wof:name":"North Wiltshire Skip Hire",
    "wof:placetype":"venue"
},
  "geometry": {"coordinates":[-2.17074,51.480438],"type":"Point"}
}