{
  "type": "Feature",
  "properties": {
    "addr:full":"11 Bath St Ilkeston Derbyshire DE7 8AH",
    "addr:housenumber":"11",
    "addr:postcode":"de7 8ah",
    "addr:street":"Bath St",
    "iso:country":"GB",
    "sg:address":"11 Bath St",
    "sg:city":"Ilkeston",
    "sg:classifiers":[
        {
            "category":"Shopping",
            "subcategory":"Florist",
            "type":"Retail Goods"
        }
    ],
    "sg:phone":"+44 115 944 0042",
    "sg:postcode":"DE7 8AH",
    "sg:province":"Derbyshire",
    "wof:name":"Selby Flowers & Plants",
    "wof:placetype":"venue"
},
  "geometry": {"coordinates":[-1.3091230392,52.9733734131],"type":"Point"}
}