{
  "type": "Feature",
  "properties": {
    "addr:full":"1 Victoria Gardens, Newton Grange Dalkeith City of Edinburgh EH22 4NL",
    "addr:housenumber":"1",
    "addr:postcode":"eh22 4nl",
    "addr:street":"Victoria Gardens",
    "iso:country":"GB",
    "sg:address":"1 Victoria Gardens, Newton Grange",
    "sg:city":"Dalkeith",
    "sg:classifiers":[
        {
            "category":"Building & Trades",
            "subcategory":"Construction",
            "type":"Services"
        }
    ],
    "sg:postcode":"EH22 4NL",
    "sg:province":"City of Edinburgh",
    "sg:tags":[
        "decorator",
        "painter"
    ],
    "wof:name":"Kenneth Thomson",
    "wof:placetype":"venue"
},
  "geometry": {"coordinates":[-3.0738229752,55.869468689],"type":"Point"}
}