{
  "type": "Feature",
  "properties": {
    "iso:country":"GB",
    "sg:address":"39 Westwood View",
    "sg:city":"Ryton",
    "sg:classifiers":[
        {
            "category":"Professional",
            "type":"Services"
        }
    ],
    "sg:phone":"+44 191 413 2893",
    "sg:postcode":"NE40 4HR",
    "sg:province":"Tyne and Wear",
    "sg:tags":[
        "entertainer"
    ],
    "wof:name":"Sadie Lee Enterprises",
    "wof:placetype":"venue"
},
  "geometry": {"coordinates":[-1.789985,54.961445],"type":"Point"}
}