{
  "type": "Feature",
  "properties": {
    "iso:country":"GB",
    "sg:address":"Unit 4 Bay Clo",
    "sg:city":"Morecambe",
    "sg:classifiers":[
        {
            "category":"Professional",
            "subcategory":"Business Services",
            "type":"Services"
        }
    ],
    "sg:phone":"+44 1524 852005",
    "sg:postcode":"LA3 2XS",
    "sg:province":"Lancashire",
    "sg:tags":[
        "distribution"
    ],
    "wof:name":"Mac Transport",
    "wof:placetype":"venue"
},
  "geometry": {"coordinates":[-2.908544,54.03756],"type":"Point"}
}