{
  "type": "Feature",
  "properties": {
    "addr:full":"173 Radley Road Abingdon Oxfordshire OX14 3RZ",
    "addr:housenumber":"173",
    "addr:postcode":"ox14 3rz",
    "addr:street":"Radley Road",
    "iso:country":"GB",
    "sg:address":"173 Radley Road",
    "sg:city":"Abingdon",
    "sg:classifiers":[
        {
            "category":"Manufacturing",
            "subcategory":"Tools & Machinery",
            "type":"Manufacturing & Wholesale Goods"
        },
        {
            "category":"Home & Garden",
            "subcategory":"Hardware",
            "type":"Retail Goods"
        }
    ],
    "sg:phone":"+44 1235 538888",
    "sg:postcode":"OX14 3RZ",
    "sg:province":"Oxfordshire",
    "sg:tags":[
        "machine",
        "equipment",
        "welding",
        "manufacturer"
    ],
    "wof:name":"Alpha Engineering Supplies",
    "wof:placetype":"venue"
},
  "geometry": {"coordinates":[-1.2655260563,51.6786193848],"type":"Point"}
}