{
  "type": "Feature",
  "properties": {
    "iso:country":"GB",
    "sg:address":"Unit 3, 25 Castle Street, Grosvenor Centre",
    "sg:city":"Macclesfield",
    "sg:classifiers":[
        {
            "category":"Health Services",
            "subcategory":"Optometrist",
            "type":"Services"
        }
    ],
    "sg:phone":"+44 1625 501111",
    "sg:postcode":"SK11 6AJ",
    "sg:province":"Cheshire",
    "sg:tags":[
        "optician"
    ],
    "wof:name":"Specsavers",
    "wof:placetype":"venue"
},
  "geometry": {"coordinates":[-2.125756,53.255669],"type":"Point"}
}