{
  "type": "Feature",
  "properties": {
    "addr:full":"63-65 Clerk Street Loanhead Midlothian EH20 9RE",
    "addr:housenumber":"63-65",
    "addr:postcode":"eh20 9re",
    "addr:street":"Clerk Street",
    "iso:country":"GB",
    "sg:address":"63-65 Clerk Street",
    "sg:city":"Loanhead",
    "sg:classifiers":[
        {
            "category":"Bars & Pubs",
            "type":"Food & Drink"
        },
        {
            "category":"Community Center",
            "subcategory":"Social",
            "type":"Public Place"
        }
    ],
    "sg:phone":"+44 131 440 0386",
    "sg:postcode":"EH20 9RE",
    "sg:province":"Midlothian",
    "sg:tags":[
        "pubs",
        "house",
        "inn",
        "activity"
    ],
    "wof:name":"The Forrester Arms",
    "wof:placetype":"venue"
},
  "geometry": {"coordinates":[-3.149523,55.878544],"type":"Point"}
}