{
  "type": "Feature",
  "properties": {
    "addr:full":"Euroway Trading Estate, Roydsdale Way Bradford West Yorkshire BD4 6SE",
    "addr:postcode":"bd4 6se",
    "addr:street":"Roydsdale Way",
    "iso:country":"GB",
    "sg:address":"Euroway Trading Estate, Roydsdale Way",
    "sg:city":"Bradford",
    "sg:classifiers":[
        {
            "category":"Retail",
            "subcategory":"Repair Shop",
            "type":"Services"
        }
    ],
    "sg:phone":"+44 1274 651165",
    "sg:postcode":"BD4 6SE",
    "sg:province":"West Yorkshire",
    "sg:tags":[
        "upholsterer"
    ],
    "wof:name":"Stag Group Upholstery",
    "wof:placetype":"venue"
},
  "geometry": {"coordinates":[-1.7378499508,53.7556381226],"type":"Point"}
}