{
  "type": "Feature",
  "properties": {
    "addr:full":"Heathland St Aldershot Hampshire GU11 1NS",
    "addr:postcode":"gu11 1ns",
    "addr:street":"Heathland St",
    "iso:country":"GB",
    "sg:address":"Heathland St",
    "sg:city":"Aldershot",
    "sg:classifiers":[
        {
            "category":"Manufacturing",
            "subcategory":"Petroleum Products",
            "type":"Manufacturing & Wholesale Goods"
        }
    ],
    "sg:phone":"+44 1252 338358",
    "sg:postcode":"GU11 1NS",
    "sg:province":"Hampshire",
    "sg:tags":[
        "double",
        "glazing"
    ],
    "wof:name":"D G Unit Repairers",
    "wof:placetype":"venue"
},
  "geometry": {"coordinates":[-0.7649890184,51.2483711243],"type":"Point"}
}