{
  "type": "Feature",
  "properties": {
    "addr:full":"Calthorpe House, 30 Hagley Road, Edgbaston Birmingham West Midlands B16 8QY",
    "addr:housenumber":"30",
    "addr:postcode":"b16 8qy",
    "addr:street":"Hagley Road",
    "iso:country":"GB",
    "sg:address":"Calthorpe House, 30 Hagley Road, Edgbaston",
    "sg:city":"Birmingham",
    "sg:classifiers":[
        {
            "category":"Education",
            "subcategory":"Special Training",
            "type":"Public Place"
        }
    ],
    "sg:phone":"+44 121 605 6866",
    "sg:postcode":"B16 8QY",
    "sg:province":"West Midlands",
    "sg:tags":[
        "product",
        "centre"
    ],
    "wof:name":"Pitman Training Centre",
    "wof:placetype":"venue"
},
  "geometry": {"coordinates":[-1.9202690125,52.472202301],"type":"Point"}
}