{
  "type": "Feature",
  "properties": {
    "iso:country":"GB",
    "sg:address":"Barrack Road",
    "sg:city":"Christchurch",
    "sg:classifiers":[
        {
            "category":"Bars & Pubs",
            "type":"Food & Drink"
        }
    ],
    "sg:phone":"+44 1202 485215",
    "sg:postcode":"BH23 2BN",
    "sg:province":"Dorset",
    "sg:tags":[
        "pubs",
        "inn"
    ],
    "wof:name":"Bailey Bridge Brewers Fayre & Travel Inn",
    "wof:placetype":"venue"
},
  "geometry": {"coordinates":[-1.8010480404,50.7427940369],"type":"Point"}
}