{
  "type": "Feature",
  "properties": {
    "addr:full":"Water-ma-trout Industrial Estate Helston Cornwall TR13 0LW",
    "addr:postcode":"tr13 0lw",
    "addr:street":"Estate",
    "iso:country":"GB",
    "sg:address":"Water-ma-trout Industrial Estate",
    "sg:city":"Helston",
    "sg:classifiers":[
        {
            "category":"Building & Trades",
            "subcategory":"Construction",
            "type":"Services"
        }
    ],
    "sg:postcode":"TR13 0LW",
    "sg:province":"Cornwall",
    "sg:tags":[
        "joinery"
    ],
    "wof:name":"Garfield Keverne",
    "wof:placetype":"venue"
},
  "geometry": {"coordinates":[-5.269809,50.113869],"type":"Point"}
}