{
  "type": "Feature",
  "properties": {
    "addr:full":"34 Woodley Lane Romsey Hampshire SO51 7JN",
    "addr:housenumber":"34",
    "addr:postcode":"so51 7jn",
    "addr:street":"Woodley Lane",
    "iso:country":"GB",
    "sg:address":"34 Woodley Lane",
    "sg:city":"Romsey",
    "sg:classifiers":[
        {
            "category":"Building & Trades",
            "subcategory":"Construction",
            "type":"Services"
        }
    ],
    "sg:postcode":"SO51 7JN",
    "sg:province":"Hampshire",
    "sg:tags":[
        "builder"
    ],
    "wof:name":"Abbey Builders",
    "wof:placetype":"venue"
},
  "geometry": {"coordinates":[-1.4815050364,50.9969787598],"type":"Point"}
}