{
  "type": "Feature",
  "properties": {
    "addr:full":"Care Of Asda, Newtown Road Nuneaton Leicestershire CV11 4FL",
    "addr:postcode":"cv11 4fl",
    "addr:street":"Newtown Road",
    "iso:country":"GB",
    "sg:address":"Care Of Asda, Newtown Road",
    "sg:city":"Nuneaton",
    "sg:classifiers":[
        {
            "category":"Food & Beverages",
            "subcategory":"Candy",
            "type":"Retail Goods"
        }
    ],
    "sg:postcode":"CV11 4FL",
    "sg:province":"Leicestershire",
    "sg:tags":[
        "confectioner"
    ],
    "wof:name":"Bayley's",
    "wof:placetype":"venue"
},
  "geometry": {"coordinates":[-1.46445,52.52137],"type":"Point"}
}