{
  "type": "Feature",
  "properties": {
    "iso:country":"GB",
    "sg:address":"Edale",
    "sg:city":"Hope Valley",
    "sg:classifiers":[
        {
            "category":"Farming",
            "subcategory":"Livestock Farm",
            "type":"Manufacturing & Wholesale Goods"
        }
    ],
    "sg:phone":"+44 1433 670261",
    "sg:postcode":"S33 7ZB",
    "sg:province":"Derbyshire",
    "sg:tags":[
        "others"
    ],
    "wof:name":"Frank S Wilson",
    "wof:placetype":"venue"
},
  "geometry": {"coordinates":[-1.742539,53.3484],"type":"Point"}
}