{
  "type": "Feature",
  "properties": {
    "iso:country":"GB",
    "sg:address":"405 Herries Road",
    "sg:city":"Sheffield",
    "sg:classifiers":[
        {
            "category":"Bars & Pubs",
            "type":"Food & Drink"
        }
    ],
    "sg:phone":"+44 114 242 5273",
    "sg:postcode":"S5 7HE",
    "sg:province":"South Yorkshire",
    "sg:tags":[
        "pubs",
        "inn"
    ],
    "wof:name":"The Devonshire Arms",
    "wof:placetype":"venue"
},
  "geometry": {"coordinates":[-1.471289,53.413231],"type":"Point"}
}