{
  "type": "Feature",
  "properties": {
    "addr:full":"13 Hillside Road Southminster Essex CM0 7AL",
    "addr:housenumber":"13",
    "addr:postcode":"cm0 7al",
    "addr:street":"Hillside Road",
    "iso:country":"GB",
    "sg:address":"13 Hillside Road",
    "sg:city":"Southminster",
    "sg:classifiers":[
        {
            "category":"Professional",
            "subcategory":"Management & Consulting",
            "type":"Services"
        }
    ],
    "sg:postcode":"CM0 7AL",
    "sg:province":"Essex",
    "sg:tags":[
        "consultant",
        "business"
    ],
    "wof:name":"Tab Ltd",
    "wof:placetype":"venue"
},
  "geometry": {"coordinates":[0.8221409917,51.6644172668],"type":"Point"}
}