{
  "type": "Feature",
  "properties": {
    "iso:country":"GB",
    "sg:address":"South Dock",
    "sg:city":"Sunderland",
    "sg:classifiers":[
        {
            "category":"Manufacturing",
            "subcategory":"Watercraft",
            "type":"Manufacturing & Wholesale Goods"
        }
    ],
    "sg:phone":"+44 191 567 4749",
    "sg:postcode":"SR1 2EE",
    "sg:province":"Tyne and Wear",
    "sg:tags":[
        "repair",
        "ship",
        "builder"
    ],
    "wof:name":"Wear Dockyard Ltd",
    "wof:placetype":"venue"
},
  "geometry": {"coordinates":[-1.36123,54.912399],"type":"Point"}
}