{
  "type": "Feature",
  "properties": {
    "addr:full":"91 Hunters Race Chichester West Sussex PO19 5UD",
    "addr:housenumber":"91",
    "addr:postcode":"po19 5ud",
    "addr:street":"Hunters Race",
    "iso:country":"GB",
    "sg:address":"91 Hunters Race",
    "sg:city":"Chichester",
    "sg:classifiers":[
        {
            "category":"Retail",
            "subcategory":"Auto Repair",
            "type":"Services"
        }
    ],
    "sg:postcode":"PO19 5UD",
    "sg:province":"West Sussex",
    "sg:tags":[
        "modification",
        "garage"
    ],
    "wof:name":"Daryl O'Flanagan",
    "wof:placetype":"venue"
},
  "geometry": {"coordinates":[-0.797416985,50.8578605652],"type":"Point"}
}