{
  "type": "Feature",
  "properties": {
    "addr:full":"Unit 10, Priors Haw Road Corby Northamptonshire NN17 5JG",
    "addr:housenumber":"unit 10",
    "addr:postcode":"nn17 5jg",
    "addr:street":"Priors Haw Road",
    "iso:country":"GB",
    "sg:address":"Unit 10, Priors Haw Road",
    "sg:city":"Corby",
    "sg:classifiers":[
        {
            "category":"Professional",
            "subcategory":"Engineering",
            "type":"Services"
        }
    ],
    "sg:postcode":"NN17 5JG",
    "sg:province":"Northamptonshire",
    "sg:tags":[
        "engineer"
    ],
    "wof:name":"Sawford Engineering Ltd.",
    "wof:placetype":"venue"
},
  "geometry": {"coordinates":[-0.6450989842,52.5022468567],"type":"Point"}
}