{
  "type": "Feature",
  "properties": {
    "iso:country":"GB",
    "sg:address":"2 The Cloisters, Great Western Street",
    "sg:city":"Aylesbury",
    "sg:classifiers":[
        {
            "category":"Professional",
            "subcategory":"Computer Services",
            "type":"Services"
        }
    ],
    "sg:phone":"+44 1296 481458",
    "sg:postcode":"HP20 2PU",
    "sg:province":"Buckinghamshire",
    "sg:tags":[
        "system",
        "software"
    ],
    "wof:name":"Lessoft",
    "wof:placetype":"venue"
},
  "geometry": {"coordinates":[-0.814318,51.815033],"type":"Point"}
}