{
  "type": "Feature",
  "properties": {
    "addr:full":"74-76 Wellington Street Kettering Northamptonshire NN16 8RQ",
    "addr:housenumber":"74-76",
    "addr:postcode":"nn16 8rq",
    "addr:street":"Wellington Street",
    "iso:country":"GB",
    "sg:address":"74-76 Wellington Street",
    "sg:city":"Kettering",
    "sg:classifiers":[
        {
            "category":"Personal",
            "subcategory":"Beauty Salon",
            "type":"Services"
        },
        {
            "category":"Personal",
            "subcategory":"Barber",
            "type":"Services"
        }
    ],
    "sg:phone":"+44 1536 482072",
    "sg:postcode":"NN16 8RQ",
    "sg:province":"Northamptonshire",
    "sg:tags":[
        "unisex",
        "hairdresser"
    ],
    "wof:name":"Leading Lady Hair Fashions",
    "wof:placetype":"venue"
},
  "geometry": {"coordinates":[-0.721945,52.403954],"type":"Point"}
}