{
  "type": "Feature",
  "properties": {
    "addr:full":"115 High Street Newcastle Staffordshire ST5 1PS",
    "addr:housenumber":"115",
    "addr:postcode":"st5 1ps",
    "addr:street":"High Street",
    "iso:country":"GB",
    "sg:address":"115 High Street",
    "sg:city":"Newcastle",
    "sg:classifiers":[
        {
            "category":"Cafe",
            "type":"Food & Drink"
        }
    ],
    "sg:phone":"+44 1782 710077",
    "sg:postcode":"ST5 1PS",
    "sg:province":"Staffordshire",
    "sg:tags":[
        "tea",
        "room"
    ],
    "wof:name":"Brassingtons Cafe Bar Ltd.",
    "wof:placetype":"venue"
},
  "geometry": {"coordinates":[-2.2252540588,53.0096931458],"type":"Point"}
}