{
  "type": "Feature",
  "properties": {
    "iso:country":"GB",
    "sg:address":"3 Victoria Avenue, Broadgreen",
    "sg:city":"Liverpool",
    "sg:classifiers":[
        {
            "category":"Professional",
            "subcategory":"Engineering",
            "type":"Services"
        },
        {
            "category":"Building & Trades",
            "subcategory":"Electrical",
            "type":"Services"
        }
    ],
    "sg:phone":"+44 151 228 8894",
    "sg:postcode":"L14 3LR",
    "sg:province":"Merseyside",
    "sg:tags":[
        "engineer",
        "electrician",
        "contractor"
    ],
    "wof:name":"Hyton Electric",
    "wof:placetype":"venue"
},
  "geometry": {"coordinates":[-2.8931999207,53.4086227417],"type":"Point"}
}