{
  "type": "Feature",
  "properties": {
    "addr:full":"Unit 17 Totman Crescent, Brook Road Industrial Estate Rayleigh Essex SS6 7UY",
    "addr:housenumber":"unit 17",
    "addr:postcode":"ss6 7uy",
    "addr:street":"Totman Crescent Brook Road Industrial Estate",
    "iso:country":"GB",
    "sg:address":"Unit 17 Totman Crescent, Brook Road Industrial Estate",
    "sg:city":"Rayleigh",
    "sg:classifiers":[
        {
            "category":"Building & Trades",
            "subcategory":"Construction",
            "type":"Services"
        }
    ],
    "sg:phone":"+44 1268 778111",
    "sg:postcode":"SS6 7UY",
    "sg:province":"Essex",
    "sg:tags":[
        "glazier"
    ],
    "wof:name":"United Glass Contracts Ltd.",
    "wof:placetype":"venue"
},
  "geometry": {"coordinates":[0.6046299934,51.5780181885],"type":"Point"}
}