{
  "type": "Feature",
  "properties": {
    "addr:full":"Love La, Betchton Sandbach Cheshire CW11 2TS",
    "addr:postcode":"cw11 2ts",
    "iso:country":"GB",
    "sg:address":"Love La, Betchton",
    "sg:city":"Sandbach",
    "sg:classifiers":[
        {
            "category":"Building & Trades",
            "subcategory":"Landscaping Services",
            "type":"Services"
        }
    ],
    "sg:phone":"+44 1477 500255",
    "sg:postcode":"CW11 2TS",
    "sg:province":"Cheshire",
    "sg:tags":[
        "irrigation",
        "system"
    ],
    "wof:name":"Turf Irrigation Services Ltd",
    "wof:placetype":"venue"
},
  "geometry": {"coordinates":[-2.309457,53.128059],"type":"Point"}
}