{
  "type": "Feature",
  "properties": {
    "iso:country":"GB",
    "sg:address":"56 Scholes Lane",
    "sg:city":"Manchester",
    "sg:classifiers":[
        {
            "category":"Home & Garden",
            "subcategory":"Home Furnishings",
            "type":"Retail Goods"
        }
    ],
    "sg:phone":"+44 161 798 7008",
    "sg:postcode":"M25 0AY",
    "sg:province":"Greater Manchester",
    "sg:tags":[
        "furnishers",
        "planner",
        "kitchen"
    ],
    "wof:name":"Kitchen Kraft Kitchens & Bedrooms",
    "wof:placetype":"venue"
},
  "geometry": {"coordinates":[-2.161971,53.521339],"type":"Point"}
}