{
  "type": "Feature",
  "properties": {
    "addr:full":"40-42 Regent Street Swindon Wiltshire SN1 1JL",
    "addr:housenumber":"40-42",
    "addr:postcode":"sn1 1jl",
    "addr:street":"Regent Street",
    "iso:country":"GB",
    "sg:address":"40-42 Regent Street",
    "sg:city":"Swindon",
    "sg:classifiers":[
        {
            "category":"Bars & Pubs",
            "type":"Food & Drink"
        }
    ],
    "sg:phone":"+44 1793 529240",
    "sg:postcode":"SN1 1JL",
    "sg:province":"Wiltshire",
    "sg:tags":[
        "pubs",
        "inn"
    ],
    "wof:name":"The Rifleman",
    "wof:placetype":"venue"
},
  "geometry": {"coordinates":[-1.782455,51.559685],"type":"Point"}
}