{
  "type": "Feature",
  "properties": {
    "iso:country":"GB",
    "sg:address":"40-42 Regent Street",
    "sg:city":"Swindon",
    "sg:classifiers":[
        {
            "category":"Bars & Pubs",
            "type":"Food & Drink"
        }
    ],
    "sg:phone":"+44 1793 529240",
    "sg:postcode":"SN1 1JL",
    "sg:province":"Wiltshire",
    "sg:tags":[
        "pubs",
        "inn"
    ],
    "wof:name":"The Rifleman",
    "wof:placetype":"venue"
},
  "geometry": {"coordinates":[-1.782455,51.559685],"type":"Point"}
}