{
  "type": "Feature",
  "properties": {
    "iso:country":"GB",
    "sg:address":"8 Boundary Street",
    "sg:city":"Liverpool",
    "sg:classifiers":[
        {
            "category":"Freight",
            "type":"Transportation"
        },
        {
            "category":"Retail",
            "subcategory":"Auto Rental",
            "type":"Services"
        }
    ],
    "sg:phone":"+44 151 207 1441",
    "sg:postcode":"L5 9UF",
    "sg:province":"Merseyside",
    "sg:tags":[
        "hire",
        "van",
        "haulage",
        "truck",
        "road",
        "transport"
    ],
    "wof:name":"Tilly Trucks Ltd.",
    "wof:placetype":"venue"
},
  "geometry": {"coordinates":[-2.997784,53.427174],"type":"Point"}
}