{
  "type": "Feature",
  "properties": {
    "addr:full":"6 Epsom Downs Metro Centre, Waterfield Tadworth Surrey KT20 5HT",
    "addr:housenumber":"6",
    "addr:postcode":"kt20 5ht",
    "addr:street":"Epsom Downs;Tadworth",
    "iso:country":"GB",
    "sg:address":"6 Epsom Downs Metro Centre, Waterfield",
    "sg:city":"Tadworth",
    "sg:classifiers":[
        {
            "category":"Home & Garden",
            "subcategory":"Household Appliances",
            "type":"Retail Goods"
        }
    ],
    "sg:phone":"+44 1737 371688",
    "sg:postcode":"KT20 5HT",
    "sg:province":"Surrey",
    "sg:tags":[
        "refrigeration",
        "air conditioning"
    ],
    "wof:name":"Flexible Space Management Ltd",
    "wof:placetype":"venue"
},
  "geometry": {"coordinates":[-0.235149,51.291538],"type":"Point"}
}