{
  "type": "Feature",
  "properties": {
    "iso:country":"GB",
    "sg:address":"97a Mornington Rd",
    "sg:city":"Stoke-on-trent",
    "sg:classifiers":[
        {
            "category":"Building & Trades",
            "subcategory":"Landscaping Services",
            "type":"Services"
        },
        {
            "category":"Farming",
            "subcategory":"Livestock Farm",
            "type":"Manufacturing & Wholesale Goods"
        }
    ],
    "sg:postcode":"ST1 6EN",
    "sg:province":"Staffordshire",
    "sg:tags":[
        "pond",
        "aquarium",
        "others"
    ],
    "wof:name":"Whetnall,Martin Lee,",
    "wof:placetype":"venue"
},
  "geometry": {"coordinates":[-2.166043,53.04607],"type":"Point"}
}