{
  "type": "Feature",
  "properties": {
    "iso:country":"GB",
    "sg:address":"201 Hern Road, Ramsey St Marys",
    "sg:city":"Huntingdon",
    "sg:classifiers":[
        {
            "category":"Bars & Pubs",
            "type":"Food & Drink"
        }
    ],
    "sg:postcode":"PE26 2TB",
    "sg:province":"Cambridgeshire",
    "sg:tags":[
        "pubs",
        "inn"
    ],
    "wof:name":"The Lion",
    "wof:placetype":"venue"
},
  "geometry": {"coordinates":[-0.143123,52.511818],"type":"Point"}
}