{
  "type": "Feature",
  "properties": {
    "iso:country":"GB",
    "sg:address":"Sunnyside",
    "sg:city":"Bridgend",
    "sg:classifiers":[
        {
            "category":"Government",
            "subcategory":"Court House",
            "type":"Public Place"
        }
    ],
    "sg:phone":"+44 1656 750443",
    "sg:postcode":"CF31 4AJ",
    "sg:province":"Bridgend",
    "wof:name":"Magistrates Courts",
    "wof:placetype":"venue"
},
  "geometry": {"coordinates":[-3.5813939571,51.5059089661],"type":"Point"}
}