{
  "type": "Feature",
  "properties": {
    "iso:country":"GB",
    "sg:address":"M C F Complex, New Road",
    "sg:city":"Kidderminster",
    "sg:classifiers":[
        {
            "category":"Home & Garden",
            "subcategory":"Carpets & Floor Coverings",
            "type":"Retail Goods"
        }
    ],
    "sg:phone":"+44 1562 754031",
    "sg:postcode":"DY10 1AL",
    "sg:province":"Staffordshire",
    "sg:tags":[
        "carpets",
        "rug",
        "matting"
    ],
    "wof:name":"Hobbs Carpet Sales Ltd.",
    "wof:placetype":"venue"
},
  "geometry": {"coordinates":[-2.2490839958,52.3881111145],"type":"Point"}
}