{
  "type": "Feature",
  "properties": {
    "addr:full":"19 Goldhurst Terrace London Greater London NW6 3HX",
    "addr:housenumber":"19",
    "addr:postcode":"nw6 3hx",
    "addr:street":"Goldhurst Terrace",
    "iso:country":"GB",
    "sg:address":"19 Goldhurst Terrace",
    "sg:city":"London",
    "sg:classifiers":[
        {
            "category":"Personal",
            "subcategory":"Beauty Salon",
            "type":"Services"
        }
    ],
    "sg:postcode":"NW6 3HX",
    "sg:province":"Greater London",
    "wof:name":"Legendry Hair & Beauty Craft",
    "wof:placetype":"venue"
},
  "geometry": {"coordinates":[-0.179784,51.54557],"type":"Point"}
}