{
  "type": "Feature",
  "properties": {
    "addr:full":"2 Exeter Road Braunton Devon EX33 2JL",
    "addr:housenumber":"2",
    "addr:postcode":"ex33 2jl",
    "addr:street":"Exeter Road",
    "iso:country":"GB",
    "sg:address":"2 Exeter Road",
    "sg:city":"Braunton",
    "sg:classifiers":[
        {
            "category":"Home & Garden",
            "subcategory":"Furniture",
            "type":"Retail Goods"
        }
    ],
    "sg:postcode":"EX33 2JL",
    "sg:province":"Devon",
    "wof:name":"Braunton Linen",
    "wof:placetype":"venue"
},
  "geometry": {"coordinates":[-4.15873909,51.1038856506],"type":"Point"}
}