{
  "type": "Feature",
  "properties": {
    "addr:full":"106 Albion St Wallasey Merseyside L45 9JH",
    "addr:housenumber":"106",
    "addr:postcode":"l45 9jh",
    "addr:street":"Albion St",
    "iso:country":"GB",
    "sg:address":"106 Albion St",
    "sg:city":"Wallasey",
    "sg:classifiers":[
        {
            "category":"Home & Garden",
            "subcategory":"Kitchen Supply",
            "type":"Retail Goods"
        }
    ],
    "sg:phone":"+44 151 639 0118",
    "sg:postcode":"L45 9JH",
    "sg:province":"Merseyside",
    "sg:tags":[
        "equipment",
        "catering"
    ],
    "wof:name":"Radtech",
    "wof:placetype":"venue"
},
  "geometry": {"coordinates":[-3.0545289516,53.4359703064],"type":"Point"}
}