{
  "type": "Feature",
  "properties": {
    "iso:country":"GB",
    "sg:address":"72 Cwmfelin Road, Bynea",
    "sg:city":"Llanelli",
    "sg:classifiers":[
        {
            "category":"Bus Charters",
            "type":"Transportation"
        }
    ],
    "sg:phone":"+44 1554 758663",
    "sg:postcode":"SA14 9LR",
    "sg:province":"Carmarthenshire",
    "sg:tags":[
        "hire",
        "coach"
    ],
    "wof:name":"T & M Private Hire",
    "wof:placetype":"venue"
},
  "geometry": {"coordinates":[-4.100309,51.672554],"type":"Point"}
}