{
  "type": "Feature",
  "properties": {
    "iso:country":"GB",
    "sg:address":"1 Dell Court, Onslow Road",
    "sg:city":"Salcombe",
    "sg:classifiers":[
        {
            "category":"Building & Trades",
            "subcategory":"Equipment Rental",
            "type":"Services"
        }
    ],
    "sg:postcode":"TQ8 8BW",
    "sg:province":"Devon",
    "sg:tags":[
        "diver"
    ],
    "wof:name":"Seaway Direct Ltd",
    "wof:placetype":"venue"
},
  "geometry": {"coordinates":[-3.7747991085,50.237865448],"type":"Point"}
}