{
  "type": "Feature",
  "properties": {
    "addr:full":"180 Porchester Road Nottingham Nottinghamshire NG3 6LG",
    "addr:housenumber":"180",
    "addr:postcode":"ng3 6lg",
    "addr:street":"Porchester Road",
    "iso:country":"GB",
    "sg:address":"180 Porchester Road",
    "sg:city":"Nottingham",
    "sg:classifiers":[
        {
            "category":"Building & Trades",
            "subcategory":"Construction",
            "type":"Services"
        }
    ],
    "sg:phone":"+44 115 950 1629",
    "sg:postcode":"NG3 6LG",
    "sg:province":"Nottinghamshire",
    "sg:tags":[
        "builder"
    ],
    "wof:name":"F Holmes & Sons (Porchester) Ltd.",
    "wof:placetype":"venue"
},
  "geometry": {"coordinates":[-1.119747,52.970882],"type":"Point"}
}