{
  "type": "Feature",
  "properties": {
    "addr:full":"8 Trafalgar Rd Wallasey Merseyside L44 0EA",
    "addr:housenumber":"8",
    "addr:postcode":"l44 0ea",
    "addr:street":"Trafalgar Rd",
    "iso:country":"GB",
    "sg:address":"8 Trafalgar Rd",
    "sg:city":"Wallasey",
    "sg:classifiers":[
        {
            "category":"Social Services",
            "subcategory":"Adult Care",
            "type":"Services"
        }
    ],
    "sg:phone":"+44 151 630 1722",
    "sg:postcode":"L44 0EA",
    "sg:province":"Merseyside",
    "sg:tags":[
        "housing",
        "sheltered"
    ],
    "wof:name":"Jean Hickson",
    "wof:placetype":"venue"
},
  "geometry": {"coordinates":[-3.0306560993,53.4221572876],"type":"Point"}
}