{
  "type": "Feature",
  "properties": {
    "addr:full":"160-166 Kensington High Street London W8 7RG",
    "addr:housenumber":"160-166",
    "addr:postcode":"w8 7rg",
    "addr:street":"Kensington High Street",
    "iso:country":"GB",
    "sg:address":"160-166 Kensington High Street",
    "sg:city":"London",
    "sg:classifiers":[
        {
            "category":"Professional",
            "subcategory":"Computer Services",
            "type":"Services"
        }
    ],
    "sg:postcode":"W8 7RG",
    "sg:tags":[
        "business-card",
        "plug-in"
    ],
    "sg:website":"http://www.retaggr.com",
    "wof:name":"retaggr",
    "wof:placetype":"venue"
},
  "geometry": {"coordinates":[-0.24233,51.549167],"type":"Point"}
}