{
  "type": "Feature",
  "properties": {
    "addr:full":"Hynards, Harrow Street, Leavenheath Colchester Essex CO6 4PN",
    "addr:postcode":"co6 4pn",
    "addr:street":"Harrow Street",
    "iso:country":"GB",
    "sg:address":"Hynards, Harrow Street, Leavenheath",
    "sg:city":"Colchester",
    "sg:classifiers":[
        {
            "category":"Banks & Credit Unions",
            "subcategory":"Financial Services",
            "type":"Services"
        }
    ],
    "sg:phone":"+44 1787 211933",
    "sg:postcode":"CO6 4PN",
    "sg:province":"Essex",
    "sg:tags":[
        "adviser"
    ],
    "wof:name":"Hansen Lloyd Asset Management Ltd.",
    "wof:placetype":"venue"
},
  "geometry": {"coordinates":[0.8442999721,51.9915008545],"type":"Point"}
}