{
  "type": "Feature",
  "properties": {
    "addr:full":"Bucknall Service Station, Dividy Road, Bucknall Stoke-on-trent Staffordshire ST2 9JA",
    "addr:postcode":"staffordshire st2 9ja",
    "addr:street":"Dividy Road",
    "iso:country":"GB",
    "sg:address":"Bucknall Service Station, Dividy Road, Bucknall",
    "sg:city":"Stoke-on-trent",
    "sg:classifiers":[
        {
            "category":"Retail",
            "subcategory":"Auto Rental",
            "type":"Services"
        }
    ],
    "sg:phone":"+44 1782 281000",
    "sg:postcode":"ST2 9JA",
    "sg:province":"Staffordshire",
    "sg:tags":[
        "truck",
        "hire",
        "van"
    ],
    "wof:name":"M Way Vehicle Rentals Ltd.",
    "wof:placetype":"venue"
},
  "geometry": {"coordinates":[-2.1439499855,53.0216217041],"type":"Point"}
}