{
  "type": "Feature",
  "properties": {
    "iso:country":"GB",
    "sg:address":"3 Haven Road",
    "sg:city":"Hayling Island",
    "sg:classifiers":[
        {
            "category":"Recreation",
            "subcategory":"Dog Park",
            "type":"Entertainment"
        }
    ],
    "sg:phone":"+44 23 9246 6371",
    "sg:postcode":"PO11 9QX",
    "sg:province":"Hampshire",
    "wof:name":"Susan Neale",
    "wof:placetype":"venue"
},
  "geometry": {"coordinates":[-0.9513279796,50.7813339233],"type":"Point"}
}