{
  "type": "Feature",
  "properties": {
    "addr:full":"4 Market Place Cannock Staffordshire WS11 1DD",
    "addr:housenumber":"4",
    "addr:postcode":"ws11 1dd",
    "addr:street":"Market Place",
    "iso:country":"GB",
    "sg:address":"4 Market Place",
    "sg:city":"Cannock",
    "sg:classifiers":[
        {
            "category":"Shopping",
            "subcategory":"News",
            "type":"Retail Goods"
        }
    ],
    "sg:phone":"+44 1543 502545",
    "sg:postcode":"WS11 1DD",
    "sg:province":"Staffordshire",
    "sg:tags":[
        "newsagent"
    ],
    "wof:name":"Martin Newsagents",
    "wof:placetype":"venue"
},
  "geometry": {"coordinates":[-2.030544,52.689056],"type":"Point"}
}