{
  "type": "Feature",
  "properties": {
    "iso:country":"GB",
    "sg:address":"Bolton's Lane, Ingoldmells",
    "sg:city":"Skegness",
    "sg:classifiers":[
        {
            "category":"Park",
            "subcategory":"Provincial",
            "type":"Public Place"
        },
        {
            "category":"Restaurant",
            "type":"Food & Drink"
        },
        {
            "category":"Recreation",
            "subcategory":"Campground",
            "type":"Entertainment"
        }
    ],
    "sg:phone":"+44 1754 872263",
    "sg:postcode":"PE25 1JJ",
    "sg:province":"Lincolnshire",
    "sg:tags":[
        "holiday",
        "camp",
        "centre"
    ],
    "wof:name":"Greenacres Caravan & Camping Site",
    "wof:placetype":"venue"
},
  "geometry": {"coordinates":[0.3359099925,53.188331604],"type":"Point"}
}