{
  "type": "Feature",
  "properties": {
    "iso:country":"GB",
    "sg:address":"53 Cheylesmore Drive, Frimley",
    "sg:city":"Camberley",
    "sg:classifiers":[
        {
            "category":"Social Services",
            "subcategory":"Adult Care",
            "type":"Services"
        }
    ],
    "sg:postcode":"GU16 5BN",
    "sg:province":"Hampshire",
    "sg:tags":[
        "domestic",
        "cleaning"
    ],
    "wof:name":"Sparkles",
    "wof:placetype":"venue"
},
  "geometry": {"coordinates":[-0.7143,51.30394],"type":"Point"}
}