{
  "type": "Feature",
  "properties": {
    "iso:country":"GB",
    "sg:address":"105 Farm Road, Kendray",
    "sg:city":"Barnsley",
    "sg:classifiers":[
        {
            "category":"Manufacturing",
            "subcategory":"Building Materials",
            "type":"Manufacturing & Wholesale Goods"
        }
    ],
    "sg:postcode":"S70 3DL",
    "sg:province":"South Yorkshire",
    "sg:tags":[
        "gate",
        "mnfrs"
    ],
    "wof:name":"Bricol Gate Doctors",
    "wof:placetype":"venue"
},
  "geometry": {"coordinates":[-1.4536269903,53.5389671326],"type":"Point"}
}