{
  "type": "Feature",
  "properties": {
    "addr:full":"2 Anson Rd Manchester Greater Manchester M14 5BG",
    "addr:housenumber":"2",
    "addr:postcode":"m14 5bg",
    "addr:street":"Anson Rd",
    "iso:country":"GB",
    "sg:address":"2 Anson Rd",
    "sg:city":"Manchester",
    "sg:classifiers":[
        {
            "category":"Social Services",
            "subcategory":"Retirement Home",
            "type":"Services"
        }
    ],
    "sg:phone":"+44 161 224 7409",
    "sg:postcode":"M14 5BG",
    "sg:province":"Greater Manchester",
    "sg:tags":[
        "rest"
    ],
    "wof:name":"African Missions Society",
    "wof:placetype":"venue"
},
  "geometry": {"coordinates":[-2.2190630436,53.4580802917],"type":"Point"}
}