{
  "type": "Feature",
  "properties": {
    "addr:full":"30 Gail Rise, Llangwm Haverfordwest Pembrokeshire SA62 4HW",
    "addr:housenumber":"30",
    "addr:postcode":"sa62 4hw",
    "addr:street":"Gail Rise",
    "iso:country":"GB",
    "sg:address":"30 Gail Rise, Llangwm",
    "sg:city":"Haverfordwest",
    "sg:classifiers":[
        {
            "category":"Communications",
            "type":"Services"
        }
    ],
    "sg:postcode":"SA62 4HW",
    "sg:province":"Pembrokeshire",
    "sg:tags":[
        "tv",
        "video",
        "radio"
    ],
    "wof:name":"Satellite & Aerial Services",
    "wof:placetype":"venue"
},
  "geometry": {"coordinates":[-4.9159078598,51.751247406],"type":"Point"}
}