{
  "type": "Feature",
  "properties": {
    "addr:full":"55 James Street Louth Lincolnshire LN11 0JN",
    "addr:housenumber":"55",
    "addr:postcode":"ln11 0jn",
    "addr:street":"James Street Louth",
    "iso:country":"GB",
    "sg:address":"55 James Street",
    "sg:city":"Louth",
    "sg:classifiers":[
        {
            "category":"Wholesale",
            "subcategory":"Construction Materials",
            "type":"Manufacturing & Wholesale Goods"
        },
        {
            "category":"Professional",
            "subcategory":"Business Services",
            "type":"Services"
        }
    ],
    "sg:phone":"+44 1507 602300",
    "sg:postcode":"LN11 0JN",
    "sg:province":"Lincolnshire",
    "sg:tags":[
        "tile",
        "wholesaler",
        "supplier",
        "stockist"
    ],
    "wof:name":"Dial A Tile",
    "wof:placetype":"venue"
},
  "geometry": {"coordinates":[-0.000975,53.369141],"type":"Point"}
}