{
  "type": "Feature",
  "properties": {
    "addr:full":"Unit 1, Hoobrook Trading Estate Kidderminster Staffordshire DY10 1HY",
    "addr:housenumber":"unit 1",
    "addr:postcode":"dy10 1hy",
    "addr:street":"Trading Estate",
    "iso:country":"GB",
    "sg:address":"Unit 1, Hoobrook Trading Estate",
    "sg:city":"Kidderminster",
    "sg:classifiers":[
        {
            "category":"Freight",
            "type":"Transportation"
        }
    ],
    "sg:phone":"+44 1562 743808",
    "sg:postcode":"DY10 1HY",
    "sg:province":"Staffordshire",
    "sg:tags":[
        "haulage",
        "road"
    ],
    "wof:name":"John Shepherd Transport",
    "wof:placetype":"venue"
},
  "geometry": {"coordinates":[-2.248729,52.371986],"type":"Point"}
}