{
  "type": "Feature",
  "properties": {
    "iso:country":"GB",
    "sg:address":"4 Hill Street",
    "sg:city":"London",
    "sg:classifiers":[
        {
            "category":"Organizations",
            "subcategory":"Membership Organization",
            "type":"Services"
        }
    ],
    "sg:phone":"+44 20 7514 0550",
    "sg:postcode":"W1J 5NE",
    "sg:province":"Greater London",
    "sg:tags":[
        "club"
    ],
    "wof:name":"Integrated Asset Management Plc",
    "wof:placetype":"venue"
},
  "geometry": {"coordinates":[-0.147732,51.509228],"type":"Point"}
}