{
  "type": "Feature",
  "properties": {
    "addr:full":"22 St John Street Lichfield Staffordshire WS13 6PB",
    "addr:housenumber":"22",
    "addr:postcode":"ws13 6pb",
    "addr:street":"St John Street",
    "iso:country":"GB",
    "sg:address":"22 St John Street",
    "sg:city":"Lichfield",
    "sg:classifiers":[
        {
            "category":"Manufacturing",
            "subcategory":"Tools & Machinery",
            "type":"Manufacturing & Wholesale Goods"
        }
    ],
    "sg:phone":"+44 1543 255441",
    "sg:postcode":"WS13 6PB",
    "sg:province":"Staffordshire",
    "sg:tags":[
        "society",
        "friendly"
    ],
    "wof:name":"Churchill Insurance Services",
    "wof:placetype":"venue"
},
  "geometry": {"coordinates":[-1.8286219835,52.6813697815],"type":"Point"}
}