{
  "type": "Feature",
  "properties": {
    "iso:country":"GB",
    "sg:address":"Belvedere Mill, Chalford",
    "sg:city":"Stroud",
    "sg:classifiers":[
        {
            "category":"Professional",
            "subcategory":"Engineering",
            "type":"Services"
        }
    ],
    "sg:phone":"+44 1453 886000",
    "sg:postcode":"GL6 8NT",
    "sg:province":"Gloucestershire",
    "sg:tags":[
        "electronic",
        "engineer"
    ],
    "wof:name":"Heber Ltd.",
    "wof:placetype":"venue"
},
  "geometry": {"coordinates":[-2.155396,51.721848],"type":"Point"}
}