{
  "type": "Feature",
  "properties": {
    "iso:country":"GB",
    "sg:address":"Unit 4-6 Wrynose Road Old Hall Industria, Ust Estate",
    "sg:city":"Wirral",
    "sg:classifiers":[
        {
            "category":"Manufacturing",
            "subcategory":"Petroleum Products",
            "type":"Manufacturing & Wholesale Goods"
        }
    ],
    "sg:phone":"+44 151 346 1211",
    "sg:postcode":"CH62 3QA",
    "sg:province":"Cheshire",
    "sg:tags":[
        "double",
        "glazing"
    ],
    "wof:name":"Magnet Glass",
    "wof:placetype":"venue"
},
  "geometry": {"coordinates":[-2.9715640545,53.3291893005],"type":"Point"}
}