{
  "type": "Feature",
  "properties": {
    "iso:country":"GB",
    "sg:address":"Sheinton Hall Farm, Cressage",
    "sg:city":"Shrewsbury",
    "sg:classifiers":[
        {
            "category":"Farming",
            "subcategory":"Farm",
            "type":"Manufacturing & Wholesale Goods"
        }
    ],
    "sg:postcode":"SY5 6DN",
    "sg:province":"Shropshire",
    "sg:tags":[
        "mixed",
        "crop"
    ],
    "wof:name":"John C Taylor",
    "wof:placetype":"venue"
},
  "geometry": {"coordinates":[-2.604337,52.63147],"type":"Point"}
}