{
  "type": "Feature",
  "properties": {
    "addr:full":"132a Wayhill Road Andover Hampshire SP10 3BE",
    "addr:housenumber":"132a",
    "addr:postcode":"sp10 3be",
    "addr:street":"Wayhill Road",
    "iso:country":"GB",
    "sg:address":"132a Wayhill Road",
    "sg:city":"Andover",
    "sg:classifiers":[
        {
            "category":"Autos & Motor Vehicles",
            "subcategory":"Automobile Sales",
            "type":"Retail Goods"
        }
    ],
    "sg:phone":"+44 1264 320320",
    "sg:postcode":"SP10 3BE",
    "sg:province":"Hampshire",
    "sg:tags":[
        "car"
    ],
    "wof:name":"Andover Ford",
    "wof:placetype":"venue"
},
  "geometry": {"coordinates":[-1.4767789841,51.2064933777],"type":"Point"}
}