{
  "type": "Feature",
  "properties": {
    "addr:full":"12 Market Place, Long Eaton Nottingham Derbyshire NG10 1LS",
    "addr:housenumber":"12",
    "addr:postcode":"ng10 1ls",
    "addr:street":"Market Place",
    "iso:country":"GB",
    "sg:address":"12 Market Place, Long Eaton",
    "sg:city":"Nottingham",
    "sg:classifiers":[
        {
            "category":"Education",
            "subcategory":"Dance Studio",
            "type":"Public Place"
        }
    ],
    "sg:postcode":"NG10 1LS",
    "sg:province":"Derbyshire",
    "sg:tags":[
        "ballet",
        "school"
    ],
    "wof:name":"The Judith Tugby School of Dancing",
    "wof:placetype":"venue"
},
  "geometry": {"coordinates":[-1.2707070112,52.8978652954],"type":"Point"}
}