{
  "type": "Feature",
  "properties": {
    "addr:full":"Unit 19, Headley Road East Reading Berkshire RG5 4SW",
    "addr:housenumber":"unit 19",
    "addr:postcode":"rg5 4sw",
    "addr:street":"Headley Road East",
    "iso:country":"GB",
    "sg:address":"Unit 19, Headley Road East",
    "sg:city":"Reading",
    "sg:classifiers":[
        {
            "category":"Professional",
            "subcategory":"Printing & Photocopies",
            "type":"Services"
        }
    ],
    "sg:phone":"+44 118 969 5808",
    "sg:postcode":"RG5 4SW",
    "sg:province":"Berkshire",
    "sg:tags":[
        "printer"
    ],
    "wof:name":"Anchor Lithographic Ltd.",
    "wof:placetype":"venue"
},
  "geometry": {"coordinates":[-0.8905190229,51.454624176],"type":"Point"}
}