{
  "type": "Feature",
  "properties": {
    "iso:country":"GB",
    "sg:address":"1 Lanadwell Street",
    "sg:city":"Padstow",
    "sg:classifiers":[
        {
            "category":"Food & Beverages",
            "subcategory":"Bakery",
            "type":"Retail Goods"
        }
    ],
    "sg:postcode":"PL28 8AN",
    "sg:province":"Cornwall",
    "sg:tags":[
        "baker"
    ],
    "wof:name":"Corner House (Padstow) Ltd.",
    "wof:placetype":"venue"
},
  "geometry": {"coordinates":[-4.93915,50.541],"type":"Point"}
}