{
  "type": "Feature",
  "properties": {
    "addr:full":"52 High Street Grantown-on-spey Highland PH26 3EH",
    "addr:housenumber":"52",
    "addr:postcode":"ph26 3eh",
    "addr:street":"High Street",
    "iso:country":"GB",
    "sg:address":"52 High Street",
    "sg:city":"Grantown-on-spey",
    "sg:classifiers":[
        {
            "category":"Shopping",
            "subcategory":"Clothing, Apparel, & Fashions",
            "type":"Retail Goods"
        }
    ],
    "sg:phone":"+44 1479 872014",
    "sg:postcode":"PH26 3EH",
    "sg:province":"Highland",
    "sg:tags":[
        "shop"
    ],
    "wof:name":"Mackintosh & Cumming",
    "wof:placetype":"venue"
},
  "geometry": {"coordinates":[-3.6093149185,57.3296852112],"type":"Point"}
}