{
  "type": "Feature",
  "properties": {
    "addr:full":"Shrubbery Garage Lyme Regis Devon DT7 3XW",
    "addr:postcode":"dt7 3xw",
    "iso:country":"GB",
    "sg:address":"Shrubbery Garage",
    "sg:city":"Lyme Regis",
    "sg:classifiers":[
        {
            "category":"Retail",
            "subcategory":"Auto Repair",
            "type":"Services"
        }
    ],
    "sg:phone":"+44 1297 442046",
    "sg:postcode":"DT7 3XW",
    "sg:province":"Devon",
    "sg:tags":[
        "modification",
        "garage"
    ],
    "wof:name":"Kevin J Salter",
    "wof:placetype":"venue"
},
  "geometry": {"coordinates":[-2.943625927,50.7278938293],"type":"Point"}
}