{
  "type": "Feature",
  "properties": {
    "addr:full":"246 Newark Rd Lincoln Lincolnshire LN6 8RW",
    "addr:housenumber":"246",
    "addr:postcode":"ln6 8rw",
    "addr:street":"Newark Rd",
    "iso:country":"GB",
    "sg:address":"246 Newark Rd",
    "sg:city":"Lincoln",
    "sg:classifiers":[
        {
            "category":"Home & Garden",
            "subcategory":"Carpets & Floor Coverings",
            "type":"Retail Goods"
        }
    ],
    "sg:phone":"+44 1522 544480",
    "sg:postcode":"LN6 8RW",
    "sg:province":"Lincolnshire",
    "sg:tags":[
        "carpets",
        "rug",
        "matting"
    ],
    "wof:name":"Ashtons The Carpet Centre",
    "wof:placetype":"venue"
},
  "geometry": {"coordinates":[-0.556305,53.202042],"type":"Point"}
}