{
  "type": "Feature",
  "properties": {
    "addr:full":"75 Almondvale Centre, Almondvale South Livingston West Lothian EH54 6HR",
    "addr:housenumber":"75",
    "addr:postcode":"eh54 6hr",
    "addr:street":"Almondvale Centre Almondvale South",
    "iso:country":"GB",
    "sg:address":"75 Almondvale Centre, Almondvale South",
    "sg:city":"Livingston",
    "sg:classifiers":[
        {
            "category":"Banks & Credit Unions",
            "subcategory":"Bank",
            "type":"Services"
        }
    ],
    "sg:phone":"+44 845 303 0109",
    "sg:postcode":"EH54 6HR",
    "sg:province":"West Lothian",
    "sg:tags":[
        "financial",
        "institution"
    ],
    "sg:website":"http://www.lloydstsb.com",
    "wof:name":"Lloyds T S B Bank Plc",
    "wof:placetype":"venue"
},
  "geometry": {"coordinates":[-3.518484,55.884075],"type":"Point"}
}