{
  "type": "Feature",
  "properties": {
    "addr:full":"Abbey Street Melrose Scottish Borders TD6 9PX",
    "addr:postcode":"td6 9px",
    "addr:street":"Abbey Street",
    "iso:country":"GB",
    "sg:address":"Abbey Street",
    "sg:city":"Melrose",
    "sg:classifiers":[
        {
            "category":"Shopping",
            "subcategory":"Gifts & Souvenirs",
            "type":"Retail Goods"
        }
    ],
    "sg:phone":"+44 1896 823455",
    "sg:postcode":"TD6 9PX",
    "sg:province":"Scottish Borders",
    "sg:tags":[
        "shop"
    ],
    "wof:name":"Sugar & Spice",
    "wof:placetype":"venue"
},
  "geometry": {"coordinates":[-2.719219,55.59985],"type":"Point"}
}