{
  "type": "Feature",
  "properties": {
    "addr:full":"Rotary House, Chantry Court, Chester West Employment Park Chester Cheshire CH1 4QN",
    "addr:postcode":"ch1 4qn",
    "addr:street":"Chantry Court;Employment Park",
    "iso:country":"GB",
    "sg:address":"Rotary House, Chantry Court, Chester West Employment Park",
    "sg:city":"Chester",
    "sg:classifiers":[
        {
            "category":"Professional",
            "subcategory":"Engineering",
            "type":"Services"
        }
    ],
    "sg:phone":"+44 1244 382233",
    "sg:postcode":"CH1 4QN",
    "sg:province":"Cheshire",
    "sg:tags":[
        "engineer",
        "mechanical"
    ],
    "wof:name":"Rotary North West Ltd.",
    "wof:placetype":"venue"
},
  "geometry": {"coordinates":[-2.927282,53.193825],"type":"Point"}
}