{
  "type": "Feature",
  "properties": {
    "iso:country":"GB",
    "sg:address":"14 High Street, Tettenhall",
    "sg:city":"Wolverhampton",
    "sg:classifiers":[
        {
            "category":"Shopping",
            "subcategory":"Antiques",
            "type":"Retail Goods"
        }
    ],
    "sg:phone":"+44 1902 745608",
    "sg:postcode":"WV6 8QT",
    "sg:province":"Shropshire",
    "wof:name":"Woodward Antique Clocks Ltd.",
    "wof:placetype":"venue"
},
  "geometry": {"coordinates":[-2.1682860851,52.5980529785],"type":"Point"}
}