{
  "type": "Feature",
  "properties": {
    "addr:full":"62 Hope Street Liverpool Merseyside L1 9BZ",
    "addr:housenumber":"62",
    "addr:postcode":"l1 9bz",
    "addr:street":"Hope Street",
    "iso:country":"GB",
    "sg:address":"62 Hope Street",
    "sg:city":"Liverpool",
    "sg:classifiers":[
        {
            "category":"Professional",
            "type":"Services"
        },
        {
            "category":"Conference Center",
            "type":"Public Place"
        }
    ],
    "sg:phone":"+44 151 709 8979",
    "sg:postcode":"L1 9BZ",
    "sg:province":"Merseyside",
    "sg:tags":[
        "related"
    ],
    "wof:name":"Sterling Events Ltd",
    "wof:placetype":"venue"
},
  "geometry": {"coordinates":[-2.9714341164,53.4000816345],"type":"Point"}
}