{
  "type": "Feature",
  "properties": {
    "iso:country":"GB",
    "sg:address":"Unit 114 Middlemore Rd",
    "sg:city":"Birmingham",
    "sg:classifiers":[
        {
            "category":"Wholesale",
            "subcategory":"Construction Materials",
            "type":"Manufacturing & Wholesale Goods"
        }
    ],
    "sg:phone":"+44 121 555 5825",
    "sg:postcode":"B21 0AY",
    "sg:province":"West Midlands",
    "sg:tags":[
        "coating",
        "powder"
    ],
    "wof:name":"Kwikcoat",
    "wof:placetype":"venue"
},
  "geometry": {"coordinates":[-1.961174,52.50676],"type":"Point"}
}