{
  "type": "Feature",
  "properties": {
    "iso:country":"GB",
    "sg:address":"305 Wellingborough Road",
    "sg:city":"Northampton",
    "sg:classifiers":[
        {
            "category":"Communications",
            "type":"Services"
        }
    ],
    "sg:phone":"+44 1604 637722",
    "sg:postcode":"NN1 4EW",
    "sg:province":"Northamptonshire",
    "sg:tags":[
        "tv",
        "video",
        "radio"
    ],
    "wof:name":"Blasons Sound & Vision Centre",
    "wof:placetype":"venue"
},
  "geometry": {"coordinates":[-0.873656,52.24308],"type":"Point"}
}