{
  "type": "Feature",
  "properties": {
    "addr:full":"147 Forton Road Gosport Hampshire PO12 3HB",
    "addr:housenumber":"147",
    "addr:postcode":"po12 3hb",
    "addr:street":"Forton Road",
    "iso:country":"GB",
    "sg:address":"147 Forton Road",
    "sg:city":"Gosport",
    "sg:classifiers":[
        {
            "category":"Personal",
            "subcategory":"Tattoo Parlor",
            "type":"Services"
        }
    ],
    "sg:phone":"+44 23 9258 2795",
    "sg:postcode":"PO12 3HB",
    "sg:province":"Hampshire",
    "sg:tags":[
        "tattooing",
        "piercing",
        "artist"
    ],
    "wof:name":"Marks Of Distinction",
    "wof:placetype":"venue"
},
  "geometry": {"coordinates":[-1.1411349773,50.8003921509],"type":"Point"}
}