{
  "type": "Feature",
  "properties": {
    "iso:country":"GB",
    "sg:address":"Belle Isle Street",
    "sg:city":"Workington",
    "sg:classifiers":[
        {
            "category":"Travel",
            "subcategory":"Hotels & Motels",
            "type":"Entertainment"
        }
    ],
    "sg:phone":"+44 1900 64401",
    "sg:postcode":"CA14 2XQ",
    "sg:province":"Cumbria",
    "wof:name":"The Cumberland Hotel",
    "wof:placetype":"venue"
},
  "geometry": {"coordinates":[-3.55776,54.64436],"type":"Point"}
}