{
  "type": "Feature",
  "properties": {
    "addr:full":"Kelham Hills Farm, Kelham Newark Lincolnshire NG23 5RY",
    "addr:postcode":"ng23 5ry",
    "addr:street":"Kelham Hills",
    "iso:country":"GB",
    "sg:address":"Kelham Hills Farm, Kelham",
    "sg:city":"Newark",
    "sg:classifiers":[
        {
            "category":"Farming",
            "subcategory":"Farm",
            "type":"Manufacturing & Wholesale Goods"
        }
    ],
    "sg:postcode":"NG23 5RY",
    "sg:province":"Lincolnshire",
    "sg:tags":[
        "mixed",
        "crop"
    ],
    "wof:name":"R G Staniforth",
    "wof:placetype":"venue"
},
  "geometry": {"coordinates":[-0.845589,53.092945],"type":"Point"}
}