{
  "type": "Feature",
  "properties": {
    "addr:full":"143 Colyers Lane Erith Kent DA8 3PB",
    "addr:housenumber":"143",
    "addr:postcode":"da8 3pb",
    "addr:street":"Colyers Lane",
    "iso:country":"GB",
    "sg:address":"143 Colyers Lane",
    "sg:city":"Erith",
    "sg:classifiers":[
        {
            "category":"Shopping",
            "subcategory":"Used Merchandise",
            "type":"Retail Goods"
        }
    ],
    "sg:postcode":"DA8 3PB",
    "sg:province":"Kent",
    "sg:tags":[
        "furniture"
    ],
    "wof:name":"Terry Goode",
    "wof:placetype":"venue"
},
  "geometry": {"coordinates":[0.174031,51.470676],"type":"Point"}
}