{
  "type": "Feature",
  "properties": {
    "addr:full":"4 Frederick Close, Thackley Bradford West Yorkshire BD10 0SW",
    "addr:housenumber":"4",
    "addr:postcode":"bd10 0sw",
    "addr:street":"Frederick Close",
    "iso:country":"GB",
    "sg:address":"4 Frederick Close, Thackley",
    "sg:city":"Bradford",
    "sg:classifiers":[
        {
            "category":"Professional",
            "subcategory":"Art Services",
            "type":"Services"
        }
    ],
    "sg:phone":"+44 1274 412223",
    "sg:postcode":"BD10 0SW",
    "sg:province":"West Yorkshire",
    "sg:tags":[
        "picture",
        "restoration"
    ],
    "wof:name":"Frame World",
    "wof:placetype":"venue"
},
  "geometry": {"coordinates":[-1.7465920448,53.8416137695],"type":"Point"}
}