{
  "type": "Feature",
  "properties": {
    "addr:full":"Monmouth Street Bridgwater Somerset TA6 5EQ",
    "addr:postcode":"ta6 5eq",
    "addr:street":"Monmouth Street",
    "iso:country":"GB",
    "sg:address":"Monmouth Street",
    "sg:city":"Bridgwater",
    "sg:classifiers":[
        {
            "category":"Government",
            "subcategory":"Post Office",
            "type":"Public Place"
        }
    ],
    "sg:phone":"+44 1278 423282",
    "sg:postcode":"TA6 5EQ",
    "sg:province":"Somerset",
    "wof:name":"Monmouth Street Post Office",
    "wof:placetype":"venue"
},
  "geometry": {"coordinates":[-2.996673,51.129868],"type":"Point"}
}