{
  "type": "Feature",
  "properties": {
    "iso:country":"GB",
    "sg:address":"7 Cleeve House, Lambourne Crescent, Llanishen",
    "sg:city":"Cardiff",
    "sg:classifiers":[
        {
            "category":"Social Services",
            "type":"Services"
        },
        {
            "category":"Professional",
            "subcategory":"Lawyer & Legal Services",
            "type":"Services"
        }
    ],
    "sg:phone":"+44 29 2076 1155",
    "sg:postcode":"CF14 5GP",
    "sg:province":"Cardiff",
    "sg:tags":[
        "advice",
        "ds",
        "counselling"
    ],
    "wof:name":"BRITISH ASSOCIATION FOR ADOPTION & FOSTERING",
    "wof:placetype":"venue"
},
  "geometry": {"coordinates":[-3.190309,51.52272],"type":"Point"}
}