{
  "type": "Feature",
  "properties": {
    "iso:country":"GB",
    "sg:address":"Manchester Road, Audenshaw",
    "sg:city":"Manchester",
    "sg:classifiers":[
        {
            "category":"Community Center",
            "type":"Public Place"
        }
    ],
    "sg:phone":"+44 161 370 4315",
    "sg:postcode":"M34 2GJ",
    "sg:province":"Greater Manchester",
    "sg:tags":[
        "centre"
    ],
    "wof:name":"Ryecroft Hall Community Association",
    "wof:placetype":"venue"
},
  "geometry": {"coordinates":[-2.1505379677,53.4575805664],"type":"Point"}
}