{
  "type": "Feature",
  "properties": {
    "iso:country":"GB",
    "sg:address":"16 Heulwen Close, Hope",
    "sg:city":"Wrexham",
    "sg:classifiers":[
        {
            "category":"Social Services",
            "subcategory":"Adult Care",
            "type":"Services"
        },
        {
            "category":"Social Services",
            "subcategory":"Retirement Home",
            "type":"Services"
        }
    ],
    "sg:phone":"+44 1978 760045",
    "sg:postcode":"LL12 9PR",
    "sg:province":"Wrexham",
    "sg:tags":[
        "housing",
        "sheltered",
        "accommodation"
    ],
    "wof:name":"Heulwen Close Sheltered Housing",
    "wof:placetype":"venue"
},
  "geometry": {"coordinates":[-3.033464,53.111542],"type":"Point"}
}