{
  "type": "Feature",
  "properties": {
    "addr:full":"309 Hagley Rd Stourbridge West Midlands DY9 0RQ",
    "addr:housenumber":"309",
    "addr:postcode":"dy9 0rq",
    "addr:street":"Hagley Rd",
    "iso:country":"GB",
    "sg:address":"309 Hagley Rd",
    "sg:city":"Stourbridge",
    "sg:classifiers":[
        {
            "category":"Bars & Pubs",
            "type":"Food & Drink"
        }
    ],
    "sg:phone":"+44 1562 883106",
    "sg:postcode":"DY9 0RQ",
    "sg:province":"West Midlands",
    "sg:tags":[
        "pubs",
        "inn"
    ],
    "wof:name":"Foley Arms The",
    "wof:placetype":"venue"
},
  "geometry": {"coordinates":[-2.1327860355,52.4375839233],"type":"Point"}
}