{
  "type": "Feature",
  "properties": {
    "iso:country":"GB",
    "sg:address":"North Lodge, North Drive",
    "sg:city":"New Milton",
    "sg:classifiers":[
        {
            "category":"Building & Trades",
            "subcategory":"Construction",
            "type":"Services"
        }
    ],
    "sg:postcode":"BH25 5TJ",
    "sg:province":"Hampshire",
    "sg:tags":[
        "builder"
    ],
    "wof:name":"First Main",
    "wof:placetype":"venue"
},
  "geometry": {"coordinates":[-1.6716519594,50.7576179504],"type":"Point"}
}