{
  "type": "Feature",
  "properties": {
    "iso:country":"GB",
    "sg:address":"48 Huddersfield Rd, Holmfirth",
    "sg:city":"Huddersfield",
    "sg:classifiers":[
        {
            "category":"Shopping",
            "subcategory":"Florist",
            "type":"Retail Goods"
        }
    ],
    "sg:phone":"+44 1484 682822",
    "sg:postcode":"HD7 1JH",
    "sg:province":"West Yorkshire",
    "wof:name":"Hobson,E,& Son",
    "wof:placetype":"venue"
},
  "geometry": {"coordinates":[-1.78268,53.64695],"type":"Point"}
}