{
  "type": "Feature",
  "properties": {
    "iso:country":"GB",
    "sg:address":"52 High Street, Irchester",
    "sg:city":"Wellingborough",
    "sg:classifiers":[
        {
            "category":"Insurance",
            "subcategory":"Insurance Agent",
            "type":"Services"
        }
    ],
    "sg:phone":"+44 1933 410665",
    "sg:postcode":"NN29 7AB",
    "sg:province":"Bedfordshire",
    "wof:name":"Profile Insurance Services",
    "wof:placetype":"venue"
},
  "geometry": {"coordinates":[-0.707498,52.274551],"type":"Point"}
}