{
  "type": "Feature",
  "properties": {
    "addr:full":"26 Beaufort Close Guisborough North Yorkshire TS14 7PW",
    "addr:housenumber":"26",
    "addr:postcode":"ts14 7pw",
    "addr:street":"Beaufort Close",
    "iso:country":"GB",
    "sg:address":"26 Beaufort Close",
    "sg:city":"Guisborough",
    "sg:classifiers":[
        {
            "category":"Building & Trades",
            "subcategory":"Construction",
            "type":"Services"
        }
    ],
    "sg:postcode":"TS14 7PW",
    "sg:province":"North Yorkshire",
    "sg:tags":[
        "decorator",
        "painter"
    ],
    "wof:name":"Country Decor",
    "wof:placetype":"venue"
},
  "geometry": {"coordinates":[-1.05926,54.524963],"type":"Point"}
}