{
  "type": "Feature",
  "properties": {
    "addr:full":"Drake Street, Bill Quay Gateshead Tyne and Wear NE10 0UT",
    "addr:postcode":"ne10 0ut",
    "addr:street":"Drake Street",
    "iso:country":"GB",
    "sg:address":"Drake Street, Bill Quay",
    "sg:city":"Gateshead",
    "sg:classifiers":[
        {
            "category":"Wholesale",
            "subcategory":"Scrap",
            "type":"Manufacturing & Wholesale Goods"
        }
    ],
    "sg:phone":"+44 191 438 3032",
    "sg:postcode":"NE10 0UT",
    "sg:province":"Tyne and Wear",
    "sg:tags":[
        "breaker",
        "dismantlers"
    ],
    "wof:name":"Bill Quay Auto Salvage",
    "wof:placetype":"venue"
},
  "geometry": {"coordinates":[-1.538874,54.958752],"type":"Point"}
}