{
  "type": "Feature",
  "properties": {
    "addr:full":"957 Lincoln Road, Walton Peterborough Cambridgeshire PE4 6AF",
    "addr:housenumber":"957",
    "addr:postcode":"pe4 6af",
    "addr:street":"Lincoln Road",
    "iso:country":"GB",
    "sg:address":"957 Lincoln Road, Walton",
    "sg:city":"Peterborough",
    "sg:classifiers":[
        {
            "category":"Food & Beverages",
            "subcategory":"Bakery",
            "type":"Retail Goods"
        }
    ],
    "sg:phone":"+44 1733 777111",
    "sg:postcode":"PE4 6AF",
    "sg:province":"Cambridgeshire",
    "sg:tags":[
        "pizza"
    ],
    "wof:name":"Papa Luigi Dial-A-Pizza",
    "wof:placetype":"venue"
},
  "geometry": {"coordinates":[-0.264849,52.601013],"type":"Point"}
}