{
  "type": "Feature",
  "properties": {
    "addr:full":"Unit 18, Thruxtun Industrial Estate Andover Hampshire SP11 8PW",
    "addr:housenumber":"unit 18;estate",
    "addr:postcode":"sp11 8pw",
    "addr:street":"Thruxtun Industrial",
    "iso:country":"GB",
    "sg:address":"Unit 18, Thruxtun Industrial Estate",
    "sg:city":"Andover",
    "sg:classifiers":[
        {
            "category":"Home & Garden",
            "subcategory":"Hardware",
            "type":"Retail Goods"
        }
    ],
    "sg:postcode":"SP11 8PW",
    "sg:province":"Hampshire",
    "sg:tags":[
        "generator"
    ],
    "wof:name":"Advance Generators",
    "wof:placetype":"venue"
},
  "geometry": {"coordinates":[-1.6000699997,51.206199646],"type":"Point"}
}