{
  "type": "Feature",
  "properties": {
    "addr:full":"Howard Town Mill, Victoria St Glossop Derbyshire SK13 8HT",
    "addr:postcode":"sk13 8ht",
    "addr:street":"Victoria St",
    "iso:country":"GB",
    "sg:address":"Howard Town Mill, Victoria St",
    "sg:city":"Glossop",
    "sg:classifiers":[
        {
            "category":"Manufacturing",
            "subcategory":"Rubber & Plastics",
            "type":"Manufacturing & Wholesale Goods"
        }
    ],
    "sg:postcode":"SK13 8HT",
    "sg:province":"Derbyshire",
    "sg:tags":[
        "injection",
        "moulding"
    ],
    "wof:name":"Parkin,John,",
    "wof:placetype":"venue"
},
  "geometry": {"coordinates":[-1.9465700388,53.4433364868],"type":"Point"}
}