{
  "type": "Feature",
  "properties": {
    "addr:full":"Unit 23 Armley Workshops, Pickering St Leeds West Yorkshire LS12 2QG",
    "addr:housenumber":"unit 23",
    "addr:postcode":"ls12 2qg",
    "addr:street":"Workshops Pickering St",
    "iso:country":"GB",
    "sg:address":"Unit 23 Armley Workshops, Pickering St",
    "sg:city":"Leeds",
    "sg:classifiers":[
        {
            "category":"Building & Trades",
            "subcategory":"Cleaning & Sanitation",
            "type":"Services"
        }
    ],
    "sg:phone":"+44 113 231 9800",
    "sg:postcode":"LS12 2QG",
    "sg:province":"West Yorkshire",
    "sg:tags":[
        "commercial"
    ],
    "wof:name":"Clean Fun Co Ltd The",
    "wof:placetype":"venue"
},
  "geometry": {"coordinates":[-1.5465869904,53.7944946289],"type":"Point"}
}