{
  "type": "Feature",
  "properties": {
    "addr:full":"7 Trafford Road Rushden Bedfordshire NN10 0JF",
    "addr:housenumber":"7",
    "addr:postcode":"nn10 0jf",
    "addr:street":"Trafford Road",
    "iso:country":"GB",
    "sg:address":"7 Trafford Road",
    "sg:city":"Rushden",
    "sg:classifiers":[
        {
            "category":"Personal",
            "type":"Services"
        }
    ],
    "sg:phone":"+44 1933 395774",
    "sg:postcode":"NN10 0JF",
    "sg:province":"Bedfordshire",
    "sg:tags":[
        "wedding"
    ],
    "wof:name":"Face To Face Mobile Make-up",
    "wof:placetype":"venue"
},
  "geometry": {"coordinates":[-0.588059,52.289673],"type":"Point"}
}