{
  "type": "Feature",
  "properties": {
    "addr:full":"673 Holloway Road London Greater London N19 5SE",
    "addr:housenumber":"673",
    "addr:postcode":"n19 5se",
    "addr:street":"Holloway Road",
    "iso:country":"GB",
    "sg:address":"673 Holloway Road",
    "sg:city":"London",
    "sg:classifiers":[
        {
            "category":"Cafe",
            "type":"Food & Drink"
        }
    ],
    "sg:phone":"+44 20 7272 1392",
    "sg:postcode":"N19 5SE",
    "sg:province":"Greater London",
    "sg:tags":[
        "tea",
        "room"
    ],
    "wof:name":"Don's Cafe",
    "wof:placetype":"venue"
},
  "geometry": {"coordinates":[-0.13349,51.564999],"type":"Point"}
}