{
  "type": "Feature",
  "properties": {
    "addr:full":"26 Felpham Road, Felpham Bognor Regis West Sussex PO22 7AZ",
    "addr:housenumber":"26",
    "addr:postcode":"po22 7az",
    "addr:street":"Felpham Road",
    "iso:country":"GB",
    "sg:address":"26 Felpham Road, Felpham",
    "sg:city":"Bognor Regis",
    "sg:classifiers":[
        {
            "category":"Home & Garden",
            "subcategory":"Home Furnishings",
            "type":"Retail Goods"
        }
    ],
    "sg:postcode":"PO22 7AZ",
    "sg:province":"West Sussex",
    "sg:tags":[
        "mantelpiece",
        "fireplace"
    ],
    "wof:name":"The Boiler & Stove Centre",
    "wof:placetype":"venue"
},
  "geometry": {"coordinates":[-0.655862987,50.7876014709],"type":"Point"}
}