{
  "type": "Feature",
  "properties": {
    "addr:full":"51 Two Mile Hill Road, Kingswood Bristol City of Bristol BS15 1BS",
    "addr:housenumber":"51",
    "addr:postcode":"bs15 1bs",
    "addr:street":"Two Mile Hill Road",
    "iso:country":"GB",
    "sg:address":"51 Two Mile Hill Road, Kingswood",
    "sg:city":"Bristol",
    "sg:classifiers":[
        {
            "category":"Shopping",
            "subcategory":"Stationery & Office Supplies",
            "type":"Retail Goods"
        }
    ],
    "sg:phone":"+44 117 960 4145",
    "sg:postcode":"BS15 1BS",
    "sg:province":"City of Bristol",
    "sg:tags":[
        "equipment"
    ],
    "wof:name":"Briony Designs Ltd.",
    "wof:placetype":"venue"
},
  "geometry": {"coordinates":[-2.514919,51.463234],"type":"Point"}
}