{
  "type": "Feature",
  "properties": {
    "iso:country":"GB",
    "sg:address":"15 Glencoe Avenue",
    "sg:city":"Ilford",
    "sg:classifiers":[
        {
            "category":"Retail",
            "subcategory":"Repair Shop",
            "type":"Services"
        }
    ],
    "sg:phone":"+44 20 8599 2391",
    "sg:postcode":"IG2 7AJ",
    "sg:province":"Essex",
    "sg:tags":[
        "television",
        "good",
        "video",
        "servicing",
        "maintenance",
        "radio"
    ],
    "wof:name":"Leo's Electronics",
    "wof:placetype":"venue"
},
  "geometry": {"coordinates":[0.0930659994,51.5678901672],"type":"Point"}
}