{
  "type": "Feature",
  "properties": {
    "iso:country":"GB",
    "sg:address":"4 Braeview Pl",
    "sg:city":"Glasgow",
    "sg:classifiers":[
        {
            "category":"Retail",
            "subcategory":"Auto Rental",
            "type":"Services"
        }
    ],
    "sg:phone":"+44 1355 268123",
    "sg:postcode":"G74 3XH",
    "sg:province":"South Lanarkshire",
    "sg:tags":[
        "car",
        "hire",
        "truck"
    ],
    "wof:name":"City Contracts",
    "wof:placetype":"venue"
},
  "geometry": {"coordinates":[-4.161233,55.777706],"type":"Point"}
}