{
  "type": "Feature",
  "properties": {
    "addr:full":"170 Putney High Street London Greater London SW15 1RS",
    "addr:housenumber":"170",
    "addr:postcode":"sw15 1rs",
    "addr:street":"Putney High Street",
    "iso:country":"GB",
    "sg:address":"170 Putney High Street",
    "sg:city":"London",
    "sg:classifiers":[
        {
            "category":"Real Estate",
            "subcategory":"Real Estate Operator",
            "type":"Services"
        }
    ],
    "sg:phone":"+44 20 8780 2233",
    "sg:postcode":"SW15 1RS",
    "sg:province":"Greater London",
    "sg:tags":[
        "letting",
        "agent"
    ],
    "wof:name":"Andrews & Partners",
    "wof:placetype":"venue"
},
  "geometry": {"coordinates":[-0.2168470025,51.4618530273],"type":"Point"}
}