{
  "type": "Feature",
  "properties": {
    "addr:full":"Holt Rd, North Elmham Dereham Norfolk NR20 5JQ",
    "addr:postcode":"nr20 5jq",
    "addr:street":"Holt Rd",
    "iso:country":"GB",
    "sg:address":"Holt Rd, North Elmham",
    "sg:city":"Dereham",
    "sg:classifiers":[
        {
            "category":"Education",
            "subcategory":"School",
            "type":"Public Place"
        }
    ],
    "sg:phone":"+44 1362 668241",
    "sg:postcode":"NR20 5JQ",
    "sg:province":"Norfolk",
    "sg:tags":[
        "local",
        "authority"
    ],
    "wof:name":"Elmham P.O",
    "wof:placetype":"venue"
},
  "geometry": {"coordinates":[0.9618620276,52.7922973633],"type":"Point"}
}