{
  "type": "Feature",
  "properties": {
    "addr:full":"42 Wood St Bilston West Midlands WV14 0BQ",
    "addr:housenumber":"42",
    "addr:postcode":"wv14 0bq",
    "addr:street":"Wood St",
    "iso:country":"GB",
    "sg:address":"42 Wood St",
    "sg:city":"Bilston",
    "sg:classifiers":[
        {
            "category":"Professional",
            "subcategory":"Business Services",
            "type":"Services"
        }
    ],
    "sg:postcode":"WV14 0BQ",
    "sg:province":"West Midlands",
    "sg:tags":[
        "bookmaker"
    ],
    "wof:name":"Meeley,D,",
    "wof:placetype":"venue"
},
  "geometry": {"coordinates":[-2.075834,52.565468],"type":"Point"}
}