{
  "type": "Feature",
  "properties": {
    "addr:full":"94 Myvod Road Wednesbury West Midlands WS10 9QE",
    "addr:housenumber":"94",
    "addr:postcode":"ws10 9qe",
    "addr:street":"Myvod Road",
    "iso:country":"GB",
    "sg:address":"94 Myvod Road",
    "sg:city":"Wednesbury",
    "sg:classifiers":[
        {
            "category":"Building & Trades",
            "subcategory":"Construction",
            "type":"Services"
        }
    ],
    "sg:phone":"+44 121 556 0046",
    "sg:postcode":"WS10 9QE",
    "sg:province":"West Midlands",
    "sg:tags":[
        "decorator",
        "painter"
    ],
    "wof:name":"R D Gayden & Son",
    "wof:placetype":"venue"
},
  "geometry": {"coordinates":[-2.011993,52.56266],"type":"Point"}
}