{
  "type": "Feature",
  "properties": {
    "iso:country":"GB",
    "sg:address":"Sea Mark Farm, Haighton Green Lane, Haighton",
    "sg:city":"Preston",
    "sg:classifiers":[
        {
            "category":"Farming",
            "subcategory":"Livestock Farm",
            "type":"Manufacturing & Wholesale Goods"
        }
    ],
    "sg:phone":"+44 1772 651245",
    "sg:postcode":"PR2 5SR",
    "sg:province":"Lancashire",
    "sg:tags":[
        "others"
    ],
    "wof:name":"D W & S Clarke & Son",
    "wof:placetype":"venue"
},
  "geometry": {"coordinates":[-2.652544,53.809696],"type":"Point"}
}