{
  "type": "Feature",
  "properties": {
    "iso:country":"GB",
    "sg:address":"20 Foan Hill, Swannington",
    "sg:city":"Coalville",
    "sg:classifiers":[
        {
            "category":"Manufacturing",
            "subcategory":"Petroleum Products",
            "type":"Manufacturing & Wholesale Goods"
        }
    ],
    "sg:postcode":"LE67 8RD",
    "sg:province":"Leicestershire",
    "sg:tags":[
        "double",
        "glazing"
    ],
    "wof:name":"Garrigian,Paul Vincent,",
    "wof:placetype":"venue"
},
  "geometry": {"coordinates":[-1.383089,52.740829],"type":"Point"}
}