{
  "type": "Feature",
  "properties": {
    "addr:full":"3 Sea Reach Leigh-on-sea Essex SS9 1BL",
    "addr:housenumber":"3",
    "addr:postcode":"ss9 1bl",
    "addr:street":"Sea Reach",
    "iso:country":"GB",
    "sg:address":"3 Sea Reach",
    "sg:city":"Leigh-on-sea",
    "sg:classifiers":[
        {
            "category":"Banks & Credit Unions",
            "subcategory":"Financial Services",
            "type":"Services"
        }
    ],
    "sg:phone":"+44 1702 712662",
    "sg:postcode":"SS9 1BL",
    "sg:province":"Essex",
    "sg:tags":[
        "consultant"
    ],
    "wof:name":"Warrior Finance Co. Ltd.",
    "wof:placetype":"venue"
},
  "geometry": {"coordinates":[0.655604,51.54023],"type":"Point"}
}