{
  "type": "Feature",
  "properties": {
    "iso:country":"GB",
    "sg:address":"20 Owen Street",
    "sg:city":"Wellington",
    "sg:classifiers":[
        {
            "category":"Building & Trades",
            "subcategory":"Construction",
            "type":"Services"
        }
    ],
    "sg:phone":"+44 1823 666660",
    "sg:postcode":"TA21 8JY",
    "sg:province":"Devon",
    "sg:tags":[
        "joinery",
        "joiner",
        "carpenter",
        "carpentry"
    ],
    "wof:name":"Beaverwood Craft",
    "wof:placetype":"venue"
},
  "geometry": {"coordinates":[-3.236099,50.981808],"type":"Point"}
}