{
  "type": "Feature",
  "properties": {
    "iso:country":"GB",
    "sg:address":"Hungerford Road Service Station",
    "sg:city":"Crewe",
    "sg:classifiers":[
        {
            "category":"Military Area",
            "subcategory":"Air Force Base",
            "type":"Public Place"
        }
    ],
    "sg:phone":"+44 1270 257588",
    "sg:postcode":"CW1 6EJ",
    "sg:province":"Cheshire",
    "sg:tags":[
        "taxi",
        "hire",
        "private"
    ],
    "wof:name":"Sledge Taxis",
    "wof:placetype":"venue"
},
  "geometry": {"coordinates":[-2.4297890663,53.097530365],"type":"Point"}
}