{
  "type": "Feature",
  "properties": {
    "iso:country":"GB",
    "sg:address":"West View Farm, Red Cow Drove, Moulton Marsh",
    "sg:city":"Spalding",
    "sg:classifiers":[
        {
            "category":"Farming",
            "subcategory":"Livestock Farm",
            "type":"Manufacturing & Wholesale Goods"
        }
    ],
    "sg:phone":"+44 1205 260253",
    "sg:postcode":"PE12 6LW",
    "sg:province":"Cambridgeshire",
    "sg:tags":[
        "others"
    ],
    "wof:name":"A Rains & Son",
    "wof:placetype":"venue"
},
  "geometry": {"coordinates":[-0.037501,52.863529],"type":"Point"}
}