{
  "type": "Feature",
  "properties": {
    "addr:full":"New Barn Works, Count Street Rochdale Lancashire OL16 5LP",
    "addr:postcode":"ol16 5lp",
    "addr:street":"Count Street",
    "iso:country":"GB",
    "sg:address":"New Barn Works, Count Street",
    "sg:city":"Rochdale",
    "sg:classifiers":[
        {
            "category":"Social Services",
            "type":"Services"
        }
    ],
    "sg:phone":"+44 1706 759119",
    "sg:postcode":"OL16 5LP",
    "sg:province":"Lancashire",
    "sg:tags":[
        "disability"
    ],
    "wof:name":"Spacefinder",
    "wof:placetype":"venue"
},
  "geometry": {"coordinates":[-2.1463229656,53.6045570374],"type":"Point"}
}