{
  "type": "Feature",
  "properties": {
    "iso:country":"GB",
    "sg:address":"32 Peascod Street",
    "sg:city":"Windsor",
    "sg:classifiers":[
        {
            "category":"Shopping",
            "subcategory":"Clothing, Apparel, & Fashions",
            "type":"Retail Goods"
        }
    ],
    "sg:phone":"+44 1753 854345",
    "sg:postcode":"SL4 1EA",
    "sg:province":"Berkshire",
    "sg:tags":[
        "shop"
    ],
    "wof:name":"Laura Ashley Ltd.",
    "wof:placetype":"venue"
},
  "geometry": {"coordinates":[-0.609822,51.481449],"type":"Point"}
}