{
  "type": "Feature",
  "properties": {
    "iso:country":"GB",
    "sg:address":"118b Front Street",
    "sg:city":"Chester-le-street",
    "sg:classifiers":[
        {
            "category":"Shopping",
            "subcategory":"Jewelry",
            "type":"Retail Goods"
        },
        {
            "category":"Shopping",
            "subcategory":"Comic Books",
            "type":"Retail Goods"
        }
    ],
    "sg:phone":"+44 191 388 0500",
    "sg:postcode":"DH3 3BA",
    "sg:province":"Durham",
    "sg:tags":[
        "jeweller",
        "sale",
        "jewellery"
    ],
    "wof:name":"Alan Ward",
    "wof:placetype":"venue"
},
  "geometry": {"coordinates":[-1.5735629797,54.8552589417],"type":"Point"}
}