{
  "type": "Feature",
  "properties": {
    "addr:full":"Joseph Adamson Ind Est, Croft St Hyde Cheshire SK14 1EE",
    "addr:postcode":"sk14 1ee",
    "addr:street":"Croft St",
    "iso:country":"GB",
    "sg:address":"Joseph Adamson Ind Est, Croft St",
    "sg:city":"Hyde",
    "sg:classifiers":[
        {
            "category":"Professional",
            "subcategory":"Computer Services",
            "type":"Services"
        }
    ],
    "sg:phone":"+44 161 351 9622",
    "sg:postcode":"SK14 1EE",
    "sg:province":"Cheshire",
    "sg:tags":[
        "aided",
        "design"
    ],
    "wof:name":"Caddraw",
    "wof:placetype":"venue"
},
  "geometry": {"coordinates":[-2.084293,53.448269],"type":"Point"}
}