{
  "type": "Feature",
  "properties": {
    "iso:country":"GB",
    "sg:address":"37 Stonegate",
    "sg:city":"York",
    "sg:classifiers":[
        {
            "category":"Manufacturing",
            "subcategory":"Textiles",
            "type":"Manufacturing & Wholesale Goods"
        }
    ],
    "sg:phone":"+44 1904 644799",
    "sg:postcode":"YO1 8AW",
    "sg:province":"North Yorkshire",
    "sg:tags":[
        "knitwear"
    ],
    "wof:name":"Pitlochry Knitwear Co",
    "wof:placetype":"venue"
},
  "geometry": {"coordinates":[-1.083031,53.96093],"type":"Point"}
}