{
  "type": "Feature",
  "properties": {
    "addr:full":"35 James Square Crieff Perth and Kinross PH7 3EY",
    "addr:housenumber":"35",
    "addr:postcode":"ph7 3ey",
    "addr:street":"James Square",
    "iso:country":"GB",
    "sg:address":"35 James Square",
    "sg:city":"Crieff",
    "sg:classifiers":[
        {
            "category":"Bars & Pubs",
            "subcategory":"Nightclub",
            "type":"Food & Drink"
        }
    ],
    "sg:phone":"+44 1764 654772",
    "sg:postcode":"PH7 3EY",
    "sg:province":"Perth and Kinross",
    "sg:tags":[
        "club",
        "night"
    ],
    "wof:name":"Scorpios Night Club",
    "wof:placetype":"venue"
},
  "geometry": {"coordinates":[-3.841482,56.372757],"type":"Point"}
}