{
  "type": "Feature",
  "properties": {
    "addr:full":"1 The Pastures, Cheriton Alresford Hampshire SO24 0PS",
    "addr:housenumber":"1",
    "addr:postcode":"so24 0ps",
    "addr:street":"The Pastures",
    "iso:country":"GB",
    "sg:address":"1 The Pastures, Cheriton",
    "sg:city":"Alresford",
    "sg:classifiers":[
        {
            "category":"Building & Trades",
            "subcategory":"Construction",
            "type":"Services"
        }
    ],
    "sg:phone":"+44 1962 771657",
    "sg:postcode":"SO24 0PS",
    "sg:province":"Hampshire",
    "sg:tags":[
        "decorator",
        "painter"
    ],
    "wof:name":"G & J Barnard",
    "wof:placetype":"venue"
},
  "geometry": {"coordinates":[-1.1709530354,51.0543937683],"type":"Point"}
}