{
  "type": "Feature",
  "properties": {
    "addr:full":"61 Clifton Rd Lossiemouth Moray IV31 6DP",
    "addr:housenumber":"61",
    "addr:postcode":"iv31 6dp",
    "addr:street":"Clifton Rd",
    "iso:country":"GB",
    "sg:address":"61 Clifton Rd",
    "sg:city":"Lossiemouth",
    "sg:classifiers":[
        {
            "category":"Shopping",
            "subcategory":"Computers & Home Electronics",
            "type":"Retail Goods"
        },
        {
            "category":"Communications",
            "type":"Services"
        }
    ],
    "sg:phone":"+44 1343 813273",
    "sg:postcode":"IV31 6DP",
    "sg:province":"Moray",
    "sg:tags":[
        "tv",
        "radio",
        "television",
        "video",
        "sale"
    ],
    "wof:name":"C & I Morgan",
    "wof:placetype":"venue"
},
  "geometry": {"coordinates":[-3.2918870449,57.7160644531],"type":"Point"}
}