{
  "type": "Feature",
  "properties": {
    "iso:country":"GB",
    "sg:address":"Kings Court, 170 High Street",
    "sg:city":"Uckfield",
    "sg:classifiers":[
        {
            "category":"Personal",
            "subcategory":"Beauty Salon",
            "type":"Services"
        }
    ],
    "sg:phone":"+44 1825 766476",
    "sg:postcode":"TN22 1AU",
    "sg:province":"East Sussex",
    "wof:name":"Circe Health & Beauty Clinic",
    "wof:placetype":"venue"
},
  "geometry": {"coordinates":[0.096912,50.971947],"type":"Point"}
}