{
  "type": "Feature",
  "properties": {
    "addr:full":"67 High Grn Cannock Staffordshire WS11 1BN",
    "addr:housenumber":"67",
    "addr:postcode":"ws11 1bn",
    "addr:street":"High Grn",
    "iso:country":"GB",
    "sg:address":"67 High Grn",
    "sg:city":"Cannock",
    "sg:classifiers":[
        {
            "category":"Real Estate",
            "subcategory":"Real Estate Agent",
            "type":"Services"
        }
    ],
    "sg:phone":"+44 1543 572251",
    "sg:postcode":"WS11 1BN",
    "sg:province":"Staffordshire",
    "wof:name":"D S G Retail Ltd.",
    "wof:placetype":"venue"
},
  "geometry": {"coordinates":[-2.0327239037,52.6896324158],"type":"Point"}
}