{
  "type": "Feature",
  "properties": {
    "addr:full":"14 St Mary's Street Edinburgh City of Edinburgh EH1 1SU",
    "addr:housenumber":"14",
    "addr:postcode":"eh1 1su",
    "addr:street":"St Mary'S Street",
    "iso:country":"GB",
    "sg:address":"14 St Mary's Street",
    "sg:city":"Edinburgh",
    "sg:classifiers":[
        {
            "category":"Shopping",
            "subcategory":"Clothing, Apparel, & Fashions",
            "type":"Retail Goods"
        }
    ],
    "sg:phone":"+44 131 556 2532",
    "sg:postcode":"EH1 1SU",
    "sg:province":"City of Edinburgh",
    "sg:tags":[
        "shop"
    ],
    "wof:name":"Cruise Clothes",
    "wof:placetype":"venue"
},
  "geometry": {"coordinates":[-3.187214,55.949116],"type":"Point"}
}