{
  "type": "Feature",
  "properties": {
    "addr:full":"13a High Street Leigh-on-sea Essex SS9 2EN",
    "addr:housenumber":"13a",
    "addr:postcode":"ss9 2en",
    "addr:street":"High Street",
    "iso:country":"GB",
    "sg:address":"13a High Street",
    "sg:city":"Leigh-on-sea",
    "sg:classifiers":[
        {
            "category":"Museum",
            "subcategory":"Art Museum",
            "type":"Entertainment"
        }
    ],
    "sg:phone":"+44 1702 470834",
    "sg:postcode":"SS9 2EN",
    "sg:province":"Essex",
    "sg:tags":[
        "gallery"
    ],
    "wof:name":"The Leigh Heritage Centre Ltd.",
    "wof:placetype":"venue"
},
  "geometry": {"coordinates":[0.6502799988,51.5401496887],"type":"Point"}
}