{
  "type": "Feature",
  "properties": {
    "iso:country":"GB",
    "sg:address":"73 Cherry Gardens",
    "sg:city":"Herne Bay",
    "sg:classifiers":[
        {
            "category":"Banks & Credit Unions",
            "subcategory":"Bank",
            "type":"Services"
        }
    ],
    "sg:phone":"+44 1227 368391",
    "sg:postcode":"CT6 5QY",
    "sg:province":"Kent",
    "sg:tags":[
        "stocktaking",
        "inventory"
    ],
    "wof:name":"L A Mortimer",
    "wof:placetype":"venue"
},
  "geometry": {"coordinates":[1.123161,51.364738],"type":"Point"}
}