{
  "type": "Feature",
  "properties": {
    "addr:full":"Hallmark House, Glendale Business Park Deeside Flintshire CH5 2LR",
    "addr:postcode":"ch5 2lr",
    "addr:street":"Deeside",
    "iso:country":"GB",
    "sg:address":"Hallmark House, Glendale Business Park",
    "sg:city":"Deeside",
    "sg:classifiers":[
        {
            "category":"Autos & Motor Vehicles",
            "subcategory":"Boat Sales",
            "type":"Retail Goods"
        }
    ],
    "sg:phone":"+44 1244 539100",
    "sg:postcode":"CH5 2LR",
    "sg:province":"Flintshire",
    "sg:tags":[
        "repair",
        "builder"
    ],
    "wof:name":"Hallmark Narrowboats",
    "wof:placetype":"venue"
},
  "geometry": {"coordinates":[-3.024987936,53.2024803162],"type":"Point"}
}