{
  "type": "Feature",
  "properties": {
    "addr:full":"The Butts Clinic, The Butts, Barnoldswick Colne Lancashire BB18 5HP",
    "addr:postcode":"bb18 5hp",
    "addr:street":"The;The;Colne",
    "iso:country":"GB",
    "sg:address":"The Butts Clinic, The Butts, Barnoldswick",
    "sg:city":"Colne",
    "sg:classifiers":[
        {
            "category":"Organizations",
            "subcategory":"Non-profit Organization",
            "type":"Services"
        }
    ],
    "sg:phone":"+44 1282 850494",
    "sg:postcode":"BB18 5HP",
    "sg:province":"Lancashire",
    "sg:tags":[
        "organisation",
        "voluntary",
        "charity"
    ],
    "wof:name":"Age Concern England (National Council of",
    "wof:placetype":"venue"
},
  "geometry": {"coordinates":[-2.188259,53.917412],"type":"Point"}
}