{
  "type": "Feature",
  "properties": {
    "iso:country":"GB",
    "sg:address":"71 Cookridge Avenue",
    "sg:city":"Leeds",
    "sg:classifiers":[
        {
            "category":"Professional",
            "subcategory":"Engineering",
            "type":"Services"
        },
        {
            "category":"Building & Trades",
            "subcategory":"Electrical",
            "type":"Services"
        }
    ],
    "sg:phone":"+44 113 230 0042",
    "sg:postcode":"LS16 7NA",
    "sg:province":"West Yorkshire",
    "sg:tags":[
        "engineer",
        "electrician",
        "contractor"
    ],
    "wof:name":"D J & M A Walker Electrical Contractors",
    "wof:placetype":"venue"
},
  "geometry": {"coordinates":[-1.619531,53.866268],"type":"Point"}
}