{
  "type": "Feature",
  "properties": {
    "addr:full":"103 Gattison Lane, New Rossington Doncaster South Yorkshire DN11 0NS",
    "addr:housenumber":"103",
    "addr:postcode":"dn11 0ns",
    "addr:street":"Gattison Lane",
    "iso:country":"GB",
    "sg:address":"103 Gattison Lane, New Rossington",
    "sg:city":"Doncaster",
    "sg:classifiers":[
        {
            "category":"Health Services",
            "subcategory":"Dentist",
            "type":"Services"
        }
    ],
    "sg:phone":"+44 1302 863091",
    "sg:postcode":"DN11 0NS",
    "sg:province":"South Yorkshire",
    "wof:name":"B.J Julius",
    "wof:placetype":"venue"
},
  "geometry": {"coordinates":[-1.070145,53.471714],"type":"Point"}
}