{
  "type": "Feature",
  "properties": {
    "iso:country":"GB",
    "sg:address":"Uncouth Rd",
    "sg:city":"Rochdale",
    "sg:classifiers":[
        {
            "category":"Communications",
            "subcategory":"Film & Video Production",
            "type":"Services"
        },
        {
            "category":"Wholesale",
            "subcategory":"Metals & Minerals",
            "type":"Manufacturing & Wholesale Goods"
        }
    ],
    "sg:phone":"+44 1706 638842",
    "sg:postcode":"OL16 3DD",
    "sg:province":"Lancashire",
    "sg:tags":[
        "non-ferrous",
        "ferrous"
    ],
    "wof:name":"Monarch Metals Ltd",
    "wof:placetype":"venue"
},
  "geometry": {"coordinates":[-2.1206519604,53.6166687012],"type":"Point"}
}