{
  "type": "Feature",
  "properties": {
    "iso:country":"GB",
    "sg:address":"Allington Road",
    "sg:city":"Gillingham",
    "sg:classifiers":[
        {
            "category":"Education",
            "subcategory":"School",
            "type":"Public Place"
        }
    ],
    "sg:phone":"+44 1634 231072",
    "sg:postcode":"ME8 6PD",
    "sg:province":"Kent",
    "sg:tags":[
        "local",
        "authority"
    ],
    "wof:name":"Featherby Infant School Nursery Unit",
    "wof:placetype":"venue"
},
  "geometry": {"coordinates":[0.5748850107,51.3772506714],"type":"Point"}
}