{
  "type": "Feature",
  "properties": {
    "iso:country":"GB",
    "sg:address":"58 Commonside",
    "sg:city":"Lytham St Annes",
    "sg:classifiers":[
        {
            "category":"Retail",
            "subcategory":"Laundry & Dry Cleaning",
            "type":"Services"
        }
    ],
    "sg:phone":"+44 1253 734510",
    "sg:postcode":"FY8 4EX",
    "sg:province":"Lancashire",
    "sg:tags":[
        "launderette"
    ],
    "wof:name":"Easy Clean Laundrette",
    "wof:placetype":"venue"
},
  "geometry": {"coordinates":[-2.9908940792,53.7433128357],"type":"Point"}
}