{
  "type": "Feature",
  "properties": {
    "addr:full":"Shoppping Centre, Victoria Street Crewe Cheshire CW1 2NG",
    "addr:postcode":"cw1 2ng",
    "addr:street":"Victoria Street",
    "iso:country":"GB",
    "sg:address":"Shoppping Centre, Victoria Street",
    "sg:city":"Crewe",
    "sg:classifiers":[
        {
            "category":"Transit Center",
            "subcategory":"Freight",
            "type":"Transportation"
        },
        {
            "category":"Commercial Area",
            "type":"Public Place"
        }
    ],
    "sg:phone":"+44 1270 256942",
    "sg:postcode":"CW1 2NG",
    "sg:province":"Cheshire",
    "sg:tags":[
        "shop",
        "shopping",
        "centre"
    ],
    "sg:website":"http://www.themarketcentre.co.uk",
    "wof:name":"The Market Centre",
    "wof:placetype":"venue"
},
  "geometry": {"coordinates":[-2.4461050034,53.1005783081],"type":"Point"}
}