{
  "type": "Feature",
  "properties": {
    "addr:full":"443 Calder Rd Edinburgh City of Edinburgh EH11 4AN",
    "addr:housenumber":"443",
    "addr:postcode":"eh11 4an",
    "addr:street":"Calder Rd",
    "iso:country":"GB",
    "sg:address":"443 Calder Rd",
    "sg:city":"Edinburgh",
    "sg:classifiers":[
        {
            "category":"Professional",
            "subcategory":"Secretarial Services",
            "type":"Services"
        }
    ],
    "sg:phone":"+44 131 476 2653",
    "sg:postcode":"EH11 4AN",
    "sg:province":"City of Edinburgh",
    "wof:name":"C V Services",
    "wof:placetype":"venue"
},
  "geometry": {"coordinates":[-3.292299,55.924416],"type":"Point"}
}