{
  "type": "Feature",
  "properties": {
    "iso:country":"GB",
    "sg:address":"Deysbrook Way",
    "sg:city":"Liverpool",
    "sg:classifiers":[
        {
            "category":"Community Center",
            "type":"Public Place"
        }
    ],
    "sg:phone":"+44 151 283 3048",
    "sg:postcode":"L12 4XE",
    "sg:province":"Merseyside",
    "sg:tags":[
        "centre"
    ],
    "wof:name":"Deysrbook Community Centre",
    "wof:placetype":"venue"
},
  "geometry": {"coordinates":[-2.8925690651,53.4352798462],"type":"Point"}
}