{
  "type": "Feature",
  "properties": {
    "iso:country":"GB",
    "sg:address":"Lydon House, Potters Brook",
    "sg:city":"Lancaster",
    "sg:classifiers":[
        {
            "category":"Professional",
            "subcategory":"Engineering",
            "type":"Services"
        }
    ],
    "sg:postcode":"LA2 0HW",
    "sg:province":"Lancashire",
    "sg:tags":[
        "engineer",
        "mechanical"
    ],
    "wof:name":"Design Support Technology Ltd.",
    "wof:placetype":"venue"
},
  "geometry": {"coordinates":[-2.78037,53.965874],"type":"Point"}
}