{
  "type": "Feature",
  "properties": {
    "addr:full":"1 Park Row Leeds West Yorkshire LS1 5NR",
    "addr:housenumber":"1",
    "addr:postcode":"ls1 5nr",
    "addr:street":"Park Row",
    "iso:country":"GB",
    "sg:address":"1 Park Row",
    "sg:city":"Leeds",
    "sg:classifiers":[
        {
            "category":"Banks & Credit Unions",
            "subcategory":"Bank",
            "type":"Services"
        }
    ],
    "sg:phone":"+44 113 242 8180",
    "sg:postcode":"LS1 5NR",
    "sg:province":"West Yorkshire",
    "sg:tags":[
        "discounting",
        "invoice"
    ],
    "wof:name":"New Court Commercial Finance",
    "wof:placetype":"venue"
},
  "geometry": {"coordinates":[-1.5465199947,53.7962036133],"type":"Point"}
}