{
  "type": "Feature",
  "properties": {
    "iso:country":"GB",
    "sg:address":"2 Hostmoor Avenue",
    "sg:city":"March",
    "sg:classifiers":[
        {
            "category":"Food & Beverages",
            "subcategory":"Supermarket",
            "type":"Retail Goods"
        }
    ],
    "sg:phone":"+44 1354 725400",
    "sg:postcode":"PE15 0AX",
    "sg:province":"Cambridgeshire",
    "wof:name":"Tesco Stores Ltd.",
    "wof:placetype":"venue"
},
  "geometry": {"coordinates":[0.070145,52.562778],"type":"Point"}
}