{
  "type": "Feature",
  "properties": {
    "addr:full":"884 Ecclesall Road Sheffield Derbyshire S11 8TP",
    "addr:housenumber":"884",
    "addr:postcode":"s11 8tp",
    "addr:street":"Ecclesall Road",
    "iso:country":"GB",
    "sg:address":"884 Ecclesall Road",
    "sg:city":"Sheffield",
    "sg:classifiers":[
        {
            "category":"Shopping",
            "subcategory":"Florist",
            "type":"Retail Goods"
        }
    ],
    "sg:postcode":"S11 8TP",
    "sg:province":"Derbyshire",
    "wof:name":"West End Florists",
    "wof:placetype":"venue"
},
  "geometry": {"coordinates":[-1.5084480047,53.3627128601],"type":"Point"}
}