{
  "type": "Feature",
  "properties": {
    "addr:full":"Church Street, Binsted Alton Hampshire GU34 4NX",
    "addr:postcode":"gu34 4nx",
    "addr:street":"Church Street",
    "iso:country":"GB",
    "sg:address":"Church Street, Binsted",
    "sg:city":"Alton",
    "sg:classifiers":[
        {
            "category":"Education",
            "subcategory":"School",
            "type":"Public Place"
        },
        {
            "category":"Government",
            "subcategory":"Office",
            "type":"Public Place"
        }
    ],
    "sg:phone":"+44 1420 23200",
    "sg:postcode":"GU34 4NX",
    "sg:province":"Hampshire",
    "sg:tags":[
        "local",
        "authority"
    ],
    "wof:name":"Binsted C of E Primary School",
    "wof:placetype":"venue"
},
  "geometry": {"coordinates":[-0.9062569737,51.1646385193],"type":"Point"}
}