{
  "type": "Feature",
  "properties": {
    "addr:full":"245 Main Rd Sheffield South Yorkshire S9 4QD",
    "addr:housenumber":"245",
    "addr:postcode":"s9 4qd",
    "addr:street":"Main Rd",
    "iso:country":"GB",
    "sg:address":"245 Main Rd",
    "sg:city":"Sheffield",
    "sg:classifiers":[
        {
            "category":"Bars & Pubs",
            "type":"Food & Drink"
        }
    ],
    "sg:postcode":"S9 4QD",
    "sg:province":"South Yorkshire",
    "sg:tags":[
        "pubs",
        "inn"
    ],
    "wof:name":"Connelly's",
    "wof:placetype":"venue"
},
  "geometry": {"coordinates":[-1.409364,53.385414],"type":"Point"}
}