{
  "type": "Feature",
  "properties": {
    "iso:country":"GB",
    "sg:address":"25 Bridge Street",
    "sg:city":"Blyth",
    "sg:classifiers":[
        {
            "category":"Fast Food",
            "type":"Food & Drink"
        }
    ],
    "sg:phone":"+44 1670 360428",
    "sg:postcode":"NE24 2AA",
    "sg:province":"Northumberland",
    "sg:tags":[
        "away",
        "meal",
        "outlet",
        "take"
    ],
    "wof:name":"Sandwich Station",
    "wof:placetype":"venue"
},
  "geometry": {"coordinates":[-1.504578948,55.1279983521],"type":"Point"}
}