{
  "type": "Feature",
  "properties": {
    "addr:full":"Priory House, High St Reigate Surrey RH2 9RU",
    "addr:postcode":"rh2 9ru",
    "addr:street":"High St",
    "iso:country":"GB",
    "sg:address":"Priory House, High St",
    "sg:city":"Reigate",
    "sg:classifiers":[
        {
            "category":"Professional",
            "subcategory":"Engineering",
            "type":"Services"
        }
    ],
    "sg:phone":"+44 1737 223697",
    "sg:postcode":"RH2 9RU",
    "sg:province":"Surrey",
    "sg:tags":[
        "design",
        "engineer"
    ],
    "wof:name":"Aspen Burrow Crocker Ltd",
    "wof:placetype":"venue"
},
  "geometry": {"coordinates":[-0.209989,51.238029],"type":"Point"}
}