{
  "type": "Feature",
  "properties": {
    "iso:country":"GB",
    "sg:address":"4 Tranters Yard, Whitehorse St",
    "sg:city":"Baldock",
    "sg:classifiers":[
        {
            "category":"Health Services",
            "subcategory":"Dentist",
            "type":"Services"
        }
    ],
    "sg:phone":"+44 1462 896200",
    "sg:postcode":"SG7 6QF",
    "sg:province":"Bedfordshire",
    "sg:tags":[
        "technician",
        "dental"
    ],
    "wof:name":"Protecs",
    "wof:placetype":"venue"
},
  "geometry": {"coordinates":[-0.187854,51.98877],"type":"Point"}
}