{
  "type": "Feature",
  "properties": {
    "addr:full":"Units 4 & 5, New Parkway Market Sheffield South Yorkshire S9 4TY",
    "addr:housenumber":"units 4 & 5",
    "addr:postcode":"s9 4ty",
    "addr:street":"New Parkway",
    "iso:country":"GB",
    "sg:address":"Units 4 & 5, New Parkway Market",
    "sg:city":"Sheffield",
    "sg:classifiers":[
        {
            "category":"Food & Beverages",
            "subcategory":"Meat & Fish",
            "type":"Retail Goods"
        }
    ],
    "sg:postcode":"S9 4TY",
    "sg:province":"South Yorkshire",
    "sg:tags":[
        "merchant"
    ],
    "wof:name":"W C Lidgard & Sons Ltd.",
    "wof:placetype":"venue"
},
  "geometry": {"coordinates":[-1.357093,53.428932],"type":"Point"}
}