{
  "type": "Feature",
  "properties": {
    "iso:country":"GB",
    "sg:address":"Clockhouse",
    "sg:city":"Farnham",
    "sg:classifiers":[
        {
            "category":"Banks & Credit Unions",
            "subcategory":"Investment Brokerage",
            "type":"Services"
        }
    ],
    "sg:phone":"+44 1252 713723",
    "sg:postcode":"GU9 7UD",
    "sg:province":"Surrey",
    "sg:tags":[
        "stockbroker"
    ],
    "wof:name":"Sheppards & Chase Ltd.",
    "wof:placetype":"venue"
},
  "geometry": {"coordinates":[-0.800837,51.214321],"type":"Point"}
}