{
  "type": "Feature",
  "properties": {
    "addr:full":"118 Putney High Street London Greater London SW15 1RG",
    "addr:housenumber":"118",
    "addr:postcode":"sw15 1rg",
    "addr:street":"Putney High Street",
    "iso:country":"GB",
    "sg:address":"118 Putney High Street",
    "sg:city":"London",
    "sg:classifiers":[
        {
            "category":"Shopping",
            "subcategory":"Clothing, Apparel, & Fashions",
            "type":"Retail Goods"
        }
    ],
    "sg:phone":"+44 20 8789 9509",
    "sg:postcode":"SW15 1RG",
    "sg:province":"Greater London",
    "sg:tags":[
        "shop"
    ],
    "wof:name":"Kookai",
    "wof:placetype":"venue"
},
  "geometry": {"coordinates":[-0.2163619995,51.4627723694],"type":"Point"}
}