{
  "type": "Feature",
  "properties": {
    "iso:country":"GB",
    "sg:address":"2 Ladyhill Drive, Baillieston",
    "sg:city":"Glasgow",
    "sg:classifiers":[
        {
            "category":"Health Services",
            "subcategory":"Dentist",
            "type":"Services"
        }
    ],
    "sg:phone":"+44 141 773 2496",
    "sg:postcode":"G69 7NJ",
    "sg:province":"East Dunbartonshire",
    "wof:name":"Patricia Wilson",
    "wof:placetype":"venue"
},
  "geometry": {"coordinates":[-4.12122,55.849941],"type":"Point"}
}