{
  "type": "Feature",
  "properties": {
    "iso:country":"GB",
    "sg:address":"12 Higher Broadpark",
    "sg:city":"Dartmouth",
    "sg:classifiers":[
        {
            "category":"Manufacturing",
            "subcategory":"Petroleum Products",
            "type":"Manufacturing & Wholesale Goods"
        }
    ],
    "sg:postcode":"TQ6 9HA",
    "sg:province":"Devon",
    "sg:tags":[
        "double",
        "glazing"
    ],
    "wof:name":"The Window Man",
    "wof:placetype":"venue"
},
  "geometry": {"coordinates":[-3.590069,50.350929],"type":"Point"}
}