{
  "type": "Feature",
  "properties": {
    "iso:country":"GB",
    "sg:address":"Ford House New Road, Rumney",
    "sg:city":"Cardiff",
    "sg:classifiers":[
        {
            "category":"Building & Trades",
            "subcategory":"Construction",
            "type":"Services"
        }
    ],
    "sg:phone":"+44 29 2036 0512",
    "sg:postcode":"CF3 3BP",
    "sg:province":"Caerphilly",
    "sg:tags":[
        "tiling",
        "contractor"
    ],
    "wof:name":"Paul M Laws",
    "wof:placetype":"venue"
},
  "geometry": {"coordinates":[-3.1216850281,51.5043678284],"type":"Point"}
}