{
  "type": "Feature",
  "properties": {
    "iso:country":"GB",
    "sg:address":"21 Turbine Way",
    "sg:city":"Swaffham",
    "sg:classifiers":[
        {
            "category":"Manufacturing",
            "subcategory":"Rubber & Plastics",
            "type":"Manufacturing & Wholesale Goods"
        }
    ],
    "sg:postcode":"PE37 7XD",
    "sg:province":"Norfolk",
    "sg:tags":[
        "product"
    ],
    "wof:name":"Saf-T-Glo Ltd.",
    "wof:placetype":"venue"
},
  "geometry": {"coordinates":[0.68516,52.653355],"type":"Point"}
}