{
  "type": "Feature",
  "properties": {
    "iso:country":"GB",
    "sg:address":"75 St Margarets Avenue, Whetstone",
    "sg:city":"London",
    "sg:classifiers":[
        {
            "category":"Professional",
            "subcategory":"Business Services",
            "type":"Services"
        }
    ],
    "sg:phone":"+44 20 8446 6766",
    "sg:postcode":"N20 9LD",
    "sg:province":"Greater London",
    "sg:tags":[
        "operator",
        "market"
    ],
    "wof:name":"Harmer Market Trading (London) Ltd.",
    "wof:placetype":"venue"
},
  "geometry": {"coordinates":[-0.1758249998,51.632522583],"type":"Point"}
}