{
  "type": "Feature",
  "properties": {
    "addr:full":"47 High Street Sanquhar Dumfries and Galloway DG4 6DJ",
    "addr:housenumber":"47",
    "addr:postcode":"dg4 6dj",
    "addr:street":"High Street",
    "iso:country":"GB",
    "sg:address":"47 High Street",
    "sg:city":"Sanquhar",
    "sg:classifiers":[
        {
            "category":"Professional",
            "subcategory":"Lawyer & Legal Services",
            "type":"Services"
        }
    ],
    "sg:phone":"+44 1659 50251",
    "sg:postcode":"DG4 6DJ",
    "sg:province":"Dumfries and Galloway",
    "sg:tags":[
        "solicitor"
    ],
    "wof:name":"Robert Wilson & Son",
    "wof:placetype":"venue"
},
  "geometry": {"coordinates":[-3.923157,55.367599],"type":"Point"}
}