{
  "type": "Feature",
  "properties": {
    "addr:full":"Unit 1 Chalwyn Indust Estate, Old Wareham Road Poole Dorset BH12 4PE",
    "addr:housenumber":"unit 1;estate",
    "addr:postcode":"bh12 4pe",
    "addr:street":"Indust;Old Wareham Road",
    "iso:country":"GB",
    "sg:address":"Unit 1 Chalwyn Indust Estate, Old Wareham Road",
    "sg:city":"Poole",
    "sg:classifiers":[
        {
            "category":"Government",
            "subcategory":"Post Office",
            "type":"Public Place"
        }
    ],
    "sg:phone":"+44 1202 718885",
    "sg:postcode":"BH12 4PE",
    "sg:province":"Dorset",
    "sg:tags":[
        "messenger",
        "courier"
    ],
    "wof:name":"1st Class Couriers",
    "wof:placetype":"venue"
},
  "geometry": {"coordinates":[-1.9546840191,50.7401847839],"type":"Point"}
}