{
  "type": "Feature",
  "properties": {
    "addr:full":"P D Centre, Mold Road Wrexham Wrexham LL12 9UL",
    "addr:housenumber":"p d",
    "addr:postcode":"ll12 9ul",
    "addr:street":"Mold Road",
    "iso:country":"GB",
    "sg:address":"P D Centre, Mold Road",
    "sg:city":"Wrexham",
    "sg:classifiers":[
        {
            "category":"Wholesale",
            "subcategory":"Electrical",
            "type":"Manufacturing & Wholesale Goods"
        }
    ],
    "sg:phone":"+44 1286 871871",
    "sg:postcode":"LL12 9UL",
    "sg:province":"Wrexham",
    "sg:tags":[
        "equipment",
        "refrigeration"
    ],
    "wof:name":"Eurocool Ltd.",
    "wof:placetype":"venue"
},
  "geometry": {"coordinates":[-3.03152,53.09956],"type":"Point"}
}