{
  "type": "Feature",
  "properties": {
    "addr:full":"97 Stanley Park Road Carshalton Surrey SM5 3HX",
    "addr:housenumber":"97",
    "addr:postcode":"sm5 3hx",
    "addr:street":"Stanley Park Road",
    "iso:country":"GB",
    "sg:address":"97 Stanley Park Road",
    "sg:city":"Carshalton",
    "sg:classifiers":[
        {
            "category":"Home & Garden",
            "subcategory":"Hardware",
            "type":"Retail Goods"
        }
    ],
    "sg:phone":"+44 1233 633556",
    "sg:postcode":"SM5 3HX",
    "sg:province":"Surrey",
    "sg:tags":[
        "equipment",
        "heating"
    ],
    "wof:name":"Rymor Electrical Ltd.",
    "wof:placetype":"venue"
},
  "geometry": {"coordinates":[-0.1613029987,51.3550071716],"type":"Point"}
}