{
  "type": "Feature",
  "properties": {
    "iso:country":"GB",
    "sg:address":"75 Brookers Close",
    "sg:city":"Ashtead",
    "sg:classifiers":[
        {
            "category":"Building & Trades",
            "subcategory":"Plumbing",
            "type":"Services"
        }
    ],
    "sg:postcode":"KT21 2JT",
    "sg:province":"Surrey",
    "sg:tags":[
        "plumber",
        "heating"
    ],
    "wof:name":"DAVID J KELLY",
    "wof:placetype":"venue"
},
  "geometry": {"coordinates":[-0.3150559962,51.3138084412],"type":"Point"}
}