{
  "type": "Feature",
  "properties": {
    "iso:country":"GB",
    "sg:address":"Unit 2a Brook House, Demmings Road",
    "sg:city":"Cheadle",
    "sg:classifiers":[
        {
            "category":"Retail",
            "subcategory":"Auto Repair",
            "type":"Services"
        }
    ],
    "sg:postcode":"SK8 2PE",
    "sg:province":"Cheshire",
    "sg:tags":[
        "modification",
        "garage"
    ],
    "wof:name":"Scorpio Motors",
    "wof:placetype":"venue"
},
  "geometry": {"coordinates":[-2.200623,53.391624],"type":"Point"}
}