{
  "type": "Feature",
  "properties": {
    "iso:country":"GB",
    "sg:address":"Hurworth Grange, Croft Rd, Hurworth",
    "sg:city":"Darlington",
    "sg:classifiers":[
        {
            "category":"Shopping",
            "subcategory":"Used Merchandise",
            "type":"Retail Goods"
        }
    ],
    "sg:postcode":"DL2 2HD",
    "sg:province":"Durham",
    "sg:tags":[
        "shop",
        "second-hand"
    ],
    "wof:name":"Nott,John,",
    "wof:placetype":"venue"
},
  "geometry": {"coordinates":[-1.546129,54.483631],"type":"Point"}
}