{
  "type": "Feature",
  "properties": {
    "iso:country":"GB",
    "sg:address":"P O Box 312",
    "sg:city":"Harrogate",
    "sg:classifiers":[
        {
            "category":"Recreation",
            "subcategory":"Amusement Park",
            "type":"Entertainment"
        }
    ],
    "sg:phone":"+44 1423 541867",
    "sg:postcode":"HG1 5ZE",
    "sg:province":"North Yorkshire",
    "sg:tags":[
        "arcade"
    ],
    "wof:name":"Galaxy",
    "wof:placetype":"venue"
},
  "geometry": {"coordinates":[-1.544524,53.99469],"type":"Point"}
}