{
  "type": "Feature",
  "properties": {
    "iso:country":"GB",
    "sg:address":"3a Hop Row, Haddenham",
    "sg:city":"Ely",
    "sg:classifiers":[
        {
            "category":"Food & Beverages",
            "subcategory":"Fruits & Vegetables",
            "type":"Retail Goods"
        }
    ],
    "sg:phone":"+44 1353 740385",
    "sg:postcode":"CB6 3SR",
    "sg:province":"Cambridgeshire",
    "sg:tags":[
        "greengrocer"
    ],
    "wof:name":"M J Smith",
    "wof:placetype":"venue"
},
  "geometry": {"coordinates":[0.148838,52.357845],"type":"Point"}
}