{
  "type": "Feature",
  "properties": {
    "addr:full":"25 Horatius Way Croydon Surrey CR0 4RU",
    "addr:housenumber":"25",
    "addr:postcode":"cr0 4ru",
    "addr:street":"Horatius Way",
    "iso:country":"GB",
    "sg:address":"25 Horatius Way",
    "sg:city":"Croydon",
    "sg:classifiers":[
        {
            "category":"Retail",
            "subcategory":"Auto Repair",
            "type":"Services"
        }
    ],
    "sg:phone":"+44 20 8680 6959",
    "sg:postcode":"CR0 4RU",
    "sg:province":"Surrey",
    "sg:tags":[
        "modification",
        "garage"
    ],
    "wof:name":"Mark Pearcy",
    "wof:placetype":"venue"
},
  "geometry": {"coordinates":[-0.124021,51.360268],"type":"Point"}
}