{
  "type": "Feature",
  "properties": {
    "addr:full":"9 Holmrook Rd Preston Lancashire PR1 6SR",
    "addr:housenumber":"9",
    "addr:postcode":"pr1 6sr",
    "addr:street":"Holmrook Rd",
    "iso:country":"GB",
    "sg:address":"9 Holmrook Rd",
    "sg:city":"Preston",
    "sg:classifiers":[
        {
            "category":"Shopping",
            "subcategory":"Clothing, Apparel, & Fashions",
            "type":"Retail Goods"
        }
    ],
    "sg:phone":"+44 1772 821729",
    "sg:postcode":"PR1 6SR",
    "sg:province":"Lancashire",
    "sg:tags":[
        "shop"
    ],
    "wof:name":"City Look",
    "wof:placetype":"venue"
},
  "geometry": {"coordinates":[-2.689958,53.76857],"type":"Point"}
}