{
  "type": "Feature",
  "properties": {
    "addr:full":"Unit 222, Foley Industrial Estate Kidderminster Staffordshire DY11 7DH",
    "addr:housenumber":"222",
    "addr:postcode":"dy11 7dh",
    "addr:street":"Foley Industrial Estate",
    "iso:country":"GB",
    "sg:address":"Unit 222, Foley Industrial Estate",
    "sg:city":"Kidderminster",
    "sg:classifiers":[
        {
            "category":"Education",
            "subcategory":"Special Training",
            "type":"Public Place"
        }
    ],
    "sg:phone":"+44 1562 755155",
    "sg:postcode":"DY11 7DH",
    "sg:province":"Staffordshire",
    "sg:tags":[
        "product",
        "centre"
    ],
    "wof:name":"Chemco Ltd.",
    "wof:placetype":"venue"
},
  "geometry": {"coordinates":[-2.262257,52.367664],"type":"Point"}
}