{
  "type": "Feature",
  "properties": {
    "addr:full":"22 High Street Lanark South Lanarkshire ML11 7EX",
    "addr:housenumber":"22",
    "addr:postcode":"ml11 7ex",
    "addr:street":"High Street",
    "iso:country":"GB",
    "sg:address":"22 High Street",
    "sg:city":"Lanark",
    "sg:classifiers":[
        {
            "category":"Building & Trades",
            "subcategory":"Construction",
            "type":"Services"
        }
    ],
    "sg:postcode":"ML11 7EX",
    "sg:province":"South Lanarkshire",
    "sg:tags":[
        "decorator",
        "painter"
    ],
    "wof:name":"Alec Barrie & Sons",
    "wof:placetype":"venue"
},
  "geometry": {"coordinates":[-3.7792348862,55.673576355],"type":"Point"}
}