{
  "type": "Feature",
  "properties": {
    "iso:country":"GB",
    "sg:address":"North Heath, Chieveley",
    "sg:city":"Newbury",
    "sg:classifiers":[
        {
            "category":"Travel",
            "subcategory":"Hotels & Motels",
            "type":"Entertainment"
        }
    ],
    "sg:phone":"+44 1635 248236",
    "sg:postcode":"RG20 8UE",
    "sg:province":"Berkshire",
    "wof:name":"The Blue Boar Inn",
    "wof:placetype":"venue"
},
  "geometry": {"coordinates":[-1.3166630268,51.4626464844],"type":"Point"}
}