{
  "type": "Feature",
  "properties": {
    "iso:country":"GB",
    "sg:address":"7-11 Midland Road",
    "sg:city":"Bedford",
    "sg:classifiers":[
        {
            "category":"Shopping",
            "subcategory":"Department Store",
            "type":"Retail Goods"
        }
    ],
    "sg:phone":"+44 1234 354083",
    "sg:postcode":"MK40 1PN",
    "sg:province":"Bedfordshire",
    "wof:name":"Woolworths Plc",
    "wof:placetype":"venue"
},
  "geometry": {"coordinates":[-0.4690049887,52.1369018555],"type":"Point"}
}