{
  "type": "Feature",
  "properties": {
    "iso:country":"GB",
    "sg:address":"Will Steel House, 109 Grosvenor Road, Aston",
    "sg:city":"Birmingham",
    "sg:classifiers":[
        {
            "category":"Organizations",
            "subcategory":"Non-profit Organization",
            "type":"Services"
        }
    ],
    "sg:phone":"+44 121 328 6248",
    "sg:postcode":"B6 7LZ",
    "sg:province":"West Midlands",
    "sg:tags":[
        "organisation",
        "voluntary",
        "charity"
    ],
    "wof:name":"Y M C A",
    "wof:placetype":"venue"
},
  "geometry": {"coordinates":[-1.873479,52.50489],"type":"Point"}
}