{
  "type": "Feature",
  "properties": {
    "iso:country":"GB",
    "sg:address":"50 Shakespeare Road",
    "sg:city":"Gillingham",
    "sg:classifiers":[
        {
            "category":"Food & Beverages",
            "subcategory":"Bakery",
            "type":"Retail Goods"
        }
    ],
    "sg:phone":"+44 1634 851723",
    "sg:postcode":"ME7 5QN",
    "sg:province":"Kent",
    "sg:tags":[
        "shop",
        "baker"
    ],
    "wof:name":"Beaneys",
    "wof:placetype":"venue"
},
  "geometry": {"coordinates":[0.545608,51.379032],"type":"Point"}
}