{
  "type": "Feature",
  "properties": {
    "iso:country":"GB",
    "sg:address":"Crosshayes",
    "sg:city":"Malmesbury",
    "sg:classifiers":[
        {
            "category":"Manufacturing",
            "subcategory":"Electronics",
            "type":"Manufacturing & Wholesale Goods"
        }
    ],
    "sg:phone":"+44 1666 822991",
    "sg:postcode":"SN16 9AU",
    "sg:province":"Wiltshire",
    "sg:tags":[
        "control",
        "component",
        "-",
        "electronic"
    ],
    "wof:name":"Loadpoint Ltd.",
    "wof:placetype":"venue"
},
  "geometry": {"coordinates":[-2.096637,51.583164],"type":"Point"}
}