{
  "type": "Feature",
  "properties": {
    "iso:country":"GB",
    "sg:address":"87 Moors Lane",
    "sg:city":"Birmingham",
    "sg:classifiers":[
        {
            "category":"Building & Trades",
            "subcategory":"Construction",
            "type":"Services"
        }
    ],
    "sg:phone":"+44 121 476 2794",
    "sg:postcode":"B31 1DQ",
    "sg:province":"West Midlands",
    "sg:tags":[
        "decorator",
        "painter"
    ],
    "wof:name":"Arrington Painters & Decorators",
    "wof:placetype":"venue"
},
  "geometry": {"coordinates":[-1.985847,52.430805],"type":"Point"}
}