{
  "type": "Feature",
  "properties": {
    "iso:country":"GB",
    "sg:address":"19 Clay Street, Histon",
    "sg:city":"Cambridge",
    "sg:classifiers":[
        {
            "category":"Building & Trades",
            "subcategory":"Construction",
            "type":"Services"
        }
    ],
    "sg:postcode":"CB4 9EY",
    "sg:province":"Cambridgeshire",
    "sg:tags":[
        "builder"
    ],
    "wof:name":"P & O Building Services",
    "wof:placetype":"venue"
},
  "geometry": {"coordinates":[0.105708003,52.2561454773],"type":"Point"}
}