{
  "type": "Feature",
  "properties": {
    "iso:country":"GB",
    "sg:address":"Commercial Yard, Rear Of Galgate",
    "sg:city":"Barnard Castle",
    "sg:classifiers":[
        {
            "category":"Autos & Motor Vehicles",
            "subcategory":"Automobile Sales",
            "type":"Retail Goods"
        }
    ],
    "sg:postcode":"DL12 8EQ",
    "sg:province":"Cumbria",
    "sg:tags":[
        "car",
        "specialist",
        "sales",
        "classic"
    ],
    "wof:name":"Chattery Antiques & Furnishings",
    "wof:placetype":"venue"
},
  "geometry": {"coordinates":[-1.923809,54.543152],"type":"Point"}
}