{
  "type": "Feature",
  "properties": {
    "addr:full":"Kingston House, The Courtyard, Kingston Bagpuize Abingdon Oxfordshire OX13 5AX",
    "addr:postcode":"ox13 5ax",
    "addr:street":"The Courtyard",
    "iso:country":"GB",
    "sg:address":"Kingston House, The Courtyard, Kingston Bagpuize",
    "sg:city":"Abingdon",
    "sg:classifiers":[
        {
            "category":"Professional",
            "type":"Services"
        }
    ],
    "sg:phone":"+44 1865 821888",
    "sg:postcode":"OX13 5AX",
    "sg:province":"Oxfordshire",
    "sg:tags":[
        "interior",
        "furnishers",
        "designer"
    ],
    "wof:name":"Braziers of Oxford",
    "wof:placetype":"venue"
},
  "geometry": {"coordinates":[-1.411105,51.681404],"type":"Point"}
}