{
  "type": "Feature",
  "properties": {
    "iso:country":"GB",
    "sg:address":"Agriculture Bldg(s), Lower Road, Layer Breton",
    "sg:city":"Colchester",
    "sg:classifiers":[
        {
            "category":"Home & Garden",
            "subcategory":"Garden Supply",
            "type":"Retail Goods"
        },
        {
            "category":"Farming",
            "subcategory":"Livestock Farm",
            "type":"Manufacturing & Wholesale Goods"
        }
    ],
    "sg:phone":"+44 1206 331356",
    "sg:postcode":"CO2 0PX",
    "sg:province":"Essex",
    "sg:tags":[
        "bulb",
        "grower",
        "others"
    ],
    "wof:name":"J W Pulford",
    "wof:placetype":"venue"
},
  "geometry": {"coordinates":[0.821992,51.827663],"type":"Point"}
}