{
  "type": "Feature",
  "properties": {
    "addr:full":"Lon Sarn Bach, Abersoch Pwllheli Gwynedd LL53 7EE",
    "addr:postcode":"ll53 7ee",
    "addr:street":"Lon Sarn Bach;Pwllheli",
    "iso:country":"GB",
    "sg:address":"Lon Sarn Bach, Abersoch",
    "sg:city":"Pwllheli",
    "sg:classifiers":[
        {
            "category":"Travel",
            "subcategory":"Hotels & Motels",
            "type":"Entertainment"
        }
    ],
    "sg:phone":"+44 1758 712121",
    "sg:postcode":"LL53 7EE",
    "sg:province":"Gwynedd",
    "wof:name":"Belmont Guest House",
    "wof:placetype":"venue"
},
  "geometry": {"coordinates":[-4.505129,52.827404],"type":"Point"}
}