{
  "type": "Feature",
  "properties": {
    "addr:full":"Ruan High Lane Truro Cornwall TR2 5JR",
    "addr:postcode":"tr2 5jr",
    "addr:street":"High Lane",
    "iso:country":"GB",
    "sg:address":"Ruan High Lane",
    "sg:city":"Truro",
    "sg:classifiers":[
        {
            "category":"Retail",
            "subcategory":"Auto Repair",
            "type":"Services"
        }
    ],
    "sg:phone":"+44 1872 501801",
    "sg:postcode":"TR2 5JR",
    "sg:province":"Cornwall",
    "sg:tags":[
        "modification",
        "garage"
    ],
    "wof:name":"Wayside Garage",
    "wof:placetype":"venue"
},
  "geometry": {"coordinates":[-4.94056,50.222881],"type":"Point"}
}