{
  "type": "Feature",
  "properties": {
    "addr:full":"9 Ringwood Highway Coventry Warwickshire CV2 2GG",
    "addr:housenumber":"9",
    "addr:postcode":"cv2 2gg",
    "addr:street":"Ringwood Highway",
    "iso:country":"GB",
    "sg:address":"9 Ringwood Highway",
    "sg:city":"Coventry",
    "sg:classifiers":[
        {
            "category":"Food & Beverages",
            "subcategory":"Groceries & Convenience Stores",
            "type":"Retail Goods"
        }
    ],
    "sg:phone":"+44 24 7660 2075",
    "sg:postcode":"CV2 2GG",
    "sg:province":"Warwickshire",
    "wof:name":"Ringwood Mini Market",
    "wof:placetype":"venue"
},
  "geometry": {"coordinates":[-1.450652,52.438305],"type":"Point"}
}