{
  "type": "Feature",
  "properties": {
    "iso:country":"GB",
    "sg:address":"20 Ripon Close, Chadderton",
    "sg:city":"Oldham",
    "sg:classifiers":[
        {
            "category":"Building & Trades",
            "subcategory":"Construction",
            "type":"Services"
        }
    ],
    "sg:phone":"+44 161 633 6371",
    "sg:postcode":"OL9 8QN",
    "sg:province":"Lancashire",
    "sg:tags":[
        "bricklayer",
        "builder"
    ],
    "wof:name":"Ian Baxendale",
    "wof:placetype":"venue"
},
  "geometry": {"coordinates":[-2.1400740147,53.5381393433],"type":"Point"}
}