{
  "type": "Feature",
  "properties": {
    "iso:country":"GB",
    "sg:address":"Old Southend Road A129",
    "sg:city":"Billericay",
    "sg:classifiers":[
        {
            "category":"Food & Beverages",
            "subcategory":"Fruits & Vegetables",
            "type":"Retail Goods"
        }
    ],
    "sg:postcode":"CM11 2UD",
    "sg:province":"Essex",
    "sg:tags":[
        "greengrocer"
    ],
    "wof:name":"Barleylands Farm Shop",
    "wof:placetype":"venue"
},
  "geometry": {"coordinates":[0.429649,51.614201],"type":"Point"}
}