{
  "type": "Feature",
  "properties": {
    "iso:country":"GB",
    "sg:address":"574 Retford Rd",
    "sg:city":"Sheffield",
    "sg:classifiers":[
        {
            "category":"Building & Trades",
            "subcategory":"Construction",
            "type":"Services"
        }
    ],
    "sg:phone":"+44 114 269 3648",
    "sg:postcode":"S13 9WF",
    "sg:province":"South Yorkshire",
    "sg:tags":[
        "builder"
    ],
    "wof:name":"Project Builders",
    "wof:placetype":"venue"
},
  "geometry": {"coordinates":[-1.355589,53.366085],"type":"Point"}
}