{
  "type": "Feature",
  "properties": {
    "addr:full":"58 Park Road, Keynsham Bristol City of Bristol BS31 1BU",
    "addr:housenumber":"58",
    "addr:postcode":"bs31 1bu",
    "addr:street":"Park Road",
    "iso:country":"GB",
    "sg:address":"58 Park Road, Keynsham",
    "sg:city":"Bristol",
    "sg:classifiers":[
        {
            "category":"Professional",
            "subcategory":"Accounting & Tax Preparation",
            "type":"Services"
        }
    ],
    "sg:postcode":"BS31 1BU",
    "sg:province":"City of Bristol",
    "sg:tags":[
        "accountant"
    ],
    "wof:name":"David Floyd",
    "wof:placetype":"venue"
},
  "geometry": {"coordinates":[-2.5025029182,51.4112167358],"type":"Point"}
}