{
  "type": "Feature",
  "properties": {
    "addr:full":"4 Duke Street South Molton Devon EX36 3AL",
    "addr:housenumber":"4",
    "addr:postcode":"ex36 3al",
    "addr:street":"Duke Street South",
    "iso:country":"GB",
    "sg:address":"4 Duke Street",
    "sg:city":"South Molton",
    "sg:classifiers":[
        {
            "category":"Restaurant",
            "type":"Food & Drink"
        }
    ],
    "sg:phone":"+44 1769 573123",
    "sg:postcode":"EX36 3AL",
    "sg:province":"Devon",
    "sg:tags":[
        "-",
        "english"
    ],
    "wof:name":"Duchess Restaurant",
    "wof:placetype":"venue"
},
  "geometry": {"coordinates":[-3.8341629505,51.0183181763],"type":"Point"}
}