{
  "type": "Feature",
  "properties": {
    "addr:full":"777 Manchester Road Rochdale Lancashire OL11 3AH",
    "addr:housenumber":"777",
    "addr:postcode":"ol11 3ah",
    "addr:street":"Manchester Road",
    "iso:country":"GB",
    "sg:address":"777 Manchester Road",
    "sg:city":"Rochdale",
    "sg:classifiers":[
        {
            "category":"Communications",
            "type":"Services"
        }
    ],
    "sg:phone":"+44 1706 633653",
    "sg:postcode":"OL11 3AH",
    "sg:province":"Lancashire",
    "sg:tags":[
        "tv",
        "video",
        "radio"
    ],
    "wof:name":"Graham E & Joan Jackson",
    "wof:placetype":"venue"
},
  "geometry": {"coordinates":[-2.1804900169,53.5930671692],"type":"Point"}
}