{
  "type": "Feature",
  "properties": {
    "iso:country":"GB",
    "sg:address":"13a Pavilion Square",
    "sg:city":"Scarborough",
    "sg:classifiers":[
        {
            "category":"Taxi",
            "type":"Transportation"
        },
        {
            "category":"Military Area",
            "subcategory":"Air Force Base",
            "type":"Public Place"
        }
    ],
    "sg:phone":"+44 1723 366666",
    "sg:postcode":"YO11 2JN",
    "sg:province":"North Yorkshire",
    "sg:tags":[
        "hire",
        "private"
    ],
    "wof:name":"Beeline Taxis",
    "wof:placetype":"venue"
},
  "geometry": {"coordinates":[-0.403369993,54.2801589966],"type":"Point"}
}