{
  "type": "Feature",
  "properties": {
    "iso:country":"GB",
    "sg:address":"7 Silverhill Drive",
    "sg:city":"Newcastle-upon-tyne",
    "sg:classifiers":[
        {
            "category":"Utilities",
            "subcategory":"Telephone",
            "type":"Services"
        }
    ],
    "sg:postcode":"NE5 2EJ",
    "sg:province":"Tyne and Wear",
    "sg:tags":[
        "telecommunication"
    ],
    "wof:name":"Comsec North East",
    "wof:placetype":"venue"
},
  "geometry": {"coordinates":[-1.675733,54.980839],"type":"Point"}
}