{
  "type": "Feature",
  "properties": {
    "addr:full":"67 Long Fallow St Albans Hertfordshire AL2 3ED",
    "addr:housenumber":"67",
    "addr:postcode":"al2 3ed",
    "addr:street":"Long Fallow",
    "iso:country":"GB",
    "sg:address":"67 Long Fallow",
    "sg:city":"St Albans",
    "sg:classifiers":[
        {
            "category":"Personal",
            "type":"Services"
        }
    ],
    "sg:postcode":"AL2 3ED",
    "sg:province":"Hertfordshire",
    "sg:tags":[
        "wedding"
    ],
    "wof:name":"Forget-Me-Not Flowers in Silk",
    "wof:placetype":"venue"
},
  "geometry": {"coordinates":[-0.363499,51.722725],"type":"Point"}
}