{
  "type": "Feature",
  "properties": {
    "iso:country":"GB",
    "sg:address":"Rawlinson Street, Horwich",
    "sg:city":"Bolton",
    "sg:classifiers":[
        {
            "category":"Retail",
            "subcategory":"Auto Repair",
            "type":"Services"
        }
    ],
    "sg:phone":"+44 1204 667665",
    "sg:postcode":"BL6 7NP",
    "sg:province":"Lancashire",
    "sg:tags":[
        "modification",
        "garage"
    ],
    "wof:name":"Spring Gardens Garage",
    "wof:placetype":"venue"
},
  "geometry": {"coordinates":[-2.547814,53.599159],"type":"Point"}
}