{
  "type": "Feature",
  "properties": {
    "addr:full":"Forest Farm, Pewsham Chippenham Wiltshire SN15 3RP",
    "addr:postcode":"sn15 3rp",
    "addr:street":"Forest;Pewsham",
    "iso:country":"GB",
    "sg:address":"Forest Farm, Pewsham",
    "sg:city":"Chippenham",
    "sg:classifiers":[
        {
            "category":"Farming",
            "subcategory":"Dairy Farm",
            "type":"Manufacturing & Wholesale Goods"
        }
    ],
    "sg:phone":"+44 1249 652623",
    "sg:postcode":"SN15 3RP",
    "sg:province":"Wiltshire",
    "wof:name":"W Gough (Farms) Ltd.",
    "wof:placetype":"venue"
},
  "geometry": {"coordinates":[-2.104792,51.451763],"type":"Point"}
}