{
  "type": "Feature",
  "properties": {
    "iso:country":"GB",
    "sg:address":"42 Evesham Road, Bishops Cleeve",
    "sg:city":"Cheltenham",
    "sg:classifiers":[
        {
            "category":"Farming",
            "subcategory":"Nursery",
            "type":"Manufacturing & Wholesale Goods"
        }
    ],
    "sg:phone":"+44 1242 672215",
    "sg:postcode":"GL52 8SA",
    "sg:province":"Gloucestershire",
    "sg:tags":[
        "creche"
    ],
    "wof:name":"Linneth Cottage Day Nursery",
    "wof:placetype":"venue"
},
  "geometry": {"coordinates":[-2.064009,51.950623],"type":"Point"}
}