{
  "type": "Feature",
  "properties": {
    "addr:full":"Rawlyn Road Torquay Devon TQ2 6PQ",
    "addr:postcode":"tq2 6pq",
    "addr:street":"Rawlyn Road",
    "iso:country":"GB",
    "sg:address":"Rawlyn Road",
    "sg:city":"Torquay",
    "sg:classifiers":[
        {
            "category":"Social Services",
            "subcategory":"Retirement Home",
            "type":"Services"
        }
    ],
    "sg:phone":"+44 1803 607604",
    "sg:postcode":"TQ2 6PQ",
    "sg:province":"Devon",
    "sg:tags":[
        "residential",
        "care"
    ],
    "wof:name":"Eclipse Lodge",
    "wof:placetype":"venue"
},
  "geometry": {"coordinates":[-3.548942,50.461842],"type":"Point"}
}