{
  "type": "Feature",
  "properties": {
    "addr:full":"Caudle House, Welham Road, Thorpe Langton Market Harborough Leicestershire LE16 7TU",
    "addr:postcode":"le16 7tu",
    "addr:street":"Welham Road",
    "iso:country":"GB",
    "sg:address":"Caudle House, Welham Road, Thorpe Langton",
    "sg:city":"Market Harborough",
    "sg:classifiers":[
        {
            "category":"Professional",
            "subcategory":"Art Services",
            "type":"Services"
        }
    ],
    "sg:postcode":"LE16 7TU",
    "sg:province":"Leicestershire",
    "sg:tags":[
        "consultant",
        "design"
    ],
    "wof:name":"M D Design",
    "wof:placetype":"venue"
},
  "geometry": {"coordinates":[-0.900309,52.49691],"type":"Point"}
}