{
  "type": "Feature",
  "properties": {
    "addr:full":"357 Bideford Green Leighton Buzzard Bedfordshire LU7 2TX",
    "addr:housenumber":"357",
    "addr:postcode":"lu7 2tx",
    "addr:street":"Bideford Green",
    "iso:country":"GB",
    "sg:address":"357 Bideford Green",
    "sg:city":"Leighton Buzzard",
    "sg:classifiers":[
        {
            "category":"Building & Trades",
            "subcategory":"Construction",
            "type":"Services"
        }
    ],
    "sg:postcode":"LU7 2TX",
    "sg:province":"Bedfordshire",
    "sg:tags":[
        "joiner",
        "carpenter"
    ],
    "wof:name":"Nicholas Han",
    "wof:placetype":"venue"
},
  "geometry": {"coordinates":[-0.6864389777,51.9201011658],"type":"Point"}
}