{
  "type": "Feature",
  "properties": {
    "iso:country":"GB",
    "sg:address":"8 King Street",
    "sg:city":"Hereford",
    "sg:classifiers":[
        {
            "category":"Banks & Credit Unions",
            "subcategory":"Bank",
            "type":"Services"
        }
    ],
    "sg:phone":"+44 1432 342200",
    "sg:postcode":"HR4 9BT",
    "sg:province":"Herefordshire",
    "sg:tags":[
        "broker",
        "mortgage"
    ],
    "wof:name":"Countrywide Estate Agents",
    "wof:placetype":"venue"
},
  "geometry": {"coordinates":[-2.71796,52.054367],"type":"Point"}
}