{
  "type": "Feature",
  "properties": {
    "addr:full":"69 Wellingborough Rd Wellingborough Northamptonshire NN9 5JT",
    "addr:housenumber":"69",
    "addr:postcode":"nn9 5jt",
    "addr:street":"Wellingborough Rd",
    "iso:country":"GB",
    "sg:address":"69 Wellingborough Rd",
    "sg:city":"Wellingborough",
    "sg:classifiers":[
        {
            "category":"Food & Beverages",
            "subcategory":"Bakery",
            "type":"Retail Goods"
        }
    ],
    "sg:postcode":"NN9 5JT",
    "sg:province":"Northamptonshire",
    "sg:tags":[
        "baker"
    ],
    "wof:name":"Crusty's of Finedon",
    "wof:placetype":"venue"
},
  "geometry": {"coordinates":[-0.650742,52.338619],"type":"Point"}
}