{
  "type": "Feature",
  "properties": {
    "addr:full":"67 High Street Northallerton North Yorkshire DL7 8EG",
    "addr:housenumber":"67",
    "addr:postcode":"dl7 8eg",
    "addr:street":"High Street",
    "iso:country":"GB",
    "sg:address":"67 High Street",
    "sg:city":"Northallerton",
    "sg:classifiers":[
        {
            "category":"Organizations",
            "subcategory":"Political Organization",
            "type":"Services"
        }
    ],
    "sg:phone":"+44 1609 772060",
    "sg:postcode":"DL7 8EG",
    "sg:province":"North Yorkshire",
    "sg:tags":[
        "party"
    ],
    "wof:name":"Richmond Conservative Association",
    "wof:placetype":"venue"
},
  "geometry": {"coordinates":[-1.436252,54.342583],"type":"Point"}
}