{
  "type": "Feature",
  "properties": {
    "iso:country":"GB",
    "sg:address":"13 Station Road, Finchley",
    "sg:city":"London",
    "sg:classifiers":[
        {
            "category":"Professional",
            "subcategory":"Management & Consulting",
            "type":"Services"
        }
    ],
    "sg:postcode":"N3 2SB",
    "sg:province":"Greater London",
    "sg:tags":[
        "consultant",
        "business"
    ],
    "wof:name":"Lars Weibull Ltd",
    "wof:placetype":"venue"
},
  "geometry": {"coordinates":[-0.1930299997,51.6004638672],"type":"Point"}
}