{
  "type": "Feature",
  "properties": {
    "addr:full":"Unit B2, Baird Court Wellingborough Northamptonshire NN8 6QJ",
    "addr:postcode":"nn8 6qj",
    "addr:street":"Baird Court",
    "iso:country":"GB",
    "sg:address":"Unit B2, Baird Court",
    "sg:city":"Wellingborough",
    "sg:classifiers":[
        {
            "category":"Building & Trades",
            "subcategory":"Equipment Rental",
            "type":"Services"
        }
    ],
    "sg:postcode":"NN8 6QJ",
    "sg:province":"Northamptonshire",
    "sg:tags":[
        "hire",
        "catering"
    ],
    "wof:name":"White Stone Catering Equipment Hire",
    "wof:placetype":"venue"
},
  "geometry": {"coordinates":[-0.7293080091,52.3102493286],"type":"Point"}
}