{
  "type": "Feature",
  "properties": {
    "iso:country":"GB",
    "sg:address":"32 Cross Hayes",
    "sg:city":"Malmesbury",
    "sg:classifiers":[
        {
            "category":"Professional",
            "subcategory":"Management & Consulting",
            "type":"Services"
        }
    ],
    "sg:phone":"+44 1666 822551",
    "sg:postcode":"SN16 9BG",
    "sg:province":"Wiltshire",
    "sg:tags":[
        "marketing",
        "consultant"
    ],
    "wof:name":"Youth Promotions Agency",
    "wof:placetype":"venue"
},
  "geometry": {"coordinates":[-2.096619,51.582821],"type":"Point"}
}