{
  "type": "Feature",
  "properties": {
    "iso:country":"GB",
    "sg:address":"Shaw Place Farm, Nickleton Brow",
    "sg:city":"Chorley",
    "sg:classifiers":[
        {
            "category":"Farming",
            "subcategory":"Dairy Farm",
            "type":"Manufacturing & Wholesale Goods"
        }
    ],
    "sg:phone":"+44 1257 480273",
    "sg:postcode":"PR6 9EZ",
    "sg:province":"Lancashire",
    "wof:name":"J Smith & Sons (Chorley) Ltd.",
    "wof:placetype":"venue"
},
  "geometry": {"coordinates":[-2.5854799747,53.6285209656],"type":"Point"}
}