{
  "type": "Feature",
  "properties": {
    "iso:country":"GB",
    "sg:address":"27 Villiers Road",
    "sg:city":"Watford",
    "sg:classifiers":[
        {
            "category":"Food & Beverages",
            "subcategory":"Fruits & Vegetables",
            "type":"Retail Goods"
        }
    ],
    "sg:phone":"+44 1923 443033",
    "sg:postcode":"WD19 4AL",
    "sg:province":"Hertfordshire",
    "sg:tags":[
        "greengrocer"
    ],
    "wof:name":"Sally's Fruit & Veg",
    "wof:placetype":"venue"
},
  "geometry": {"coordinates":[-0.3813979924,51.6448020935],"type":"Point"}
}