{
  "type": "Feature",
  "properties": {
    "addr:full":"Wellhill Farm House, Dyke Forres Moray IV36 2TG",
    "addr:postcode":"iv36 2tg",
    "addr:street":"Dyke",
    "iso:country":"GB",
    "sg:address":"Wellhill Farm House, Dyke",
    "sg:city":"Forres",
    "sg:classifiers":[
        {
            "category":"Farming",
            "subcategory":"Crops",
            "type":"Manufacturing & Wholesale Goods"
        },
        {
            "category":"Farming",
            "subcategory":"Farm",
            "type":"Manufacturing & Wholesale Goods"
        }
    ],
    "sg:phone":"+44 1309 641228",
    "sg:postcode":"IV36 2TG",
    "sg:province":"Moray",
    "sg:tags":[
        "mixed",
        "arable"
    ],
    "wof:name":"James Taylor & Son",
    "wof:placetype":"venue"
},
  "geometry": {"coordinates":[-3.710614,57.593037],"type":"Point"}
}