{
  "type": "Feature",
  "properties": {
    "addr:full":"13 Columbus Courtyard, Canary Wharf London Greater London E14 4DA",
    "addr:housenumber":"13",
    "addr:postcode":"e14 4da",
    "addr:street":"Columbus Courtyard",
    "iso:country":"GB",
    "sg:address":"13 Columbus Courtyard, Canary Wharf",
    "sg:city":"London",
    "sg:classifiers":[
        {
            "category":"Farming",
            "subcategory":"Nursery",
            "type":"Manufacturing & Wholesale Goods"
        },
        {
            "category":"Social Services",
            "subcategory":"Child Care",
            "type":"Services"
        }
    ],
    "sg:phone":"+44 20 7513 0505",
    "sg:postcode":"E14 4DA",
    "sg:province":"Greater London",
    "sg:tags":[
        "creche"
    ],
    "wof:name":"Unicorn Day Nursery",
    "wof:placetype":"venue"
},
  "geometry": {"coordinates":[-0.0252139997,51.5056304932],"type":"Point"}
}