{
  "type": "Feature",
  "properties": {
    "iso:country":"GB",
    "sg:address":"2 Arbury Court",
    "sg:city":"Cambridge",
    "sg:classifiers":[
        {
            "category":"Retail",
            "subcategory":"Photofinishing",
            "type":"Services"
        }
    ],
    "sg:phone":"+44 1223 360110",
    "sg:postcode":"CB4 2JH",
    "sg:province":"Cambridgeshire",
    "sg:tags":[
        "photographic",
        "processor"
    ],
    "wof:name":"Foto Stop Express",
    "wof:placetype":"venue"
},
  "geometry": {"coordinates":[0.128545,52.224411],"type":"Point"}
}