{
  "type": "Feature",
  "properties": {
    "iso:country":"GB",
    "sg:address":"Court St",
    "sg:city":"Leamington Spa",
    "sg:classifiers":[
        {
            "category":"Building & Trades",
            "subcategory":"Construction",
            "type":"Services"
        }
    ],
    "sg:phone":"+44 1926 886500",
    "sg:postcode":"CV31 1NH",
    "sg:province":"Warwickshire",
    "sg:tags":[
        "builder"
    ],
    "wof:name":"Dumore Improvements",
    "wof:placetype":"venue"
},
  "geometry": {"coordinates":[-1.5306309462,52.2836914062],"type":"Point"}
}