{
  "type": "Feature",
  "properties": {
    "addr:full":"76 Stockheath Way Havant Hampshire PO9 2DT",
    "addr:housenumber":"76",
    "addr:postcode":"po9 2dt",
    "addr:street":"Stockheath Way",
    "iso:country":"GB",
    "sg:address":"76 Stockheath Way",
    "sg:city":"Havant",
    "sg:classifiers":[
        {
            "category":"Retail",
            "subcategory":"Auto Repair",
            "type":"Services"
        }
    ],
    "sg:phone":"+44 23 9245 4414",
    "sg:postcode":"PO9 2DT",
    "sg:province":"Hampshire",
    "sg:tags":[
        "modification",
        "garage"
    ],
    "wof:name":"Master Mechanic",
    "wof:placetype":"venue"
},
  "geometry": {"coordinates":[-0.978713,50.864719],"type":"Point"}
}