{
  "type": "Feature",
  "properties": {
    "addr:full":"2 Claremont Avenue Woking Surrey GU22 7SG",
    "addr:housenumber":"2",
    "addr:postcode":"gu22 7sg",
    "addr:street":"Claremont Avenue",
    "iso:country":"GB",
    "sg:address":"2 Claremont Avenue",
    "sg:city":"Woking",
    "sg:classifiers":[
        {
            "category":"Retail",
            "subcategory":"Repair Shop",
            "type":"Services"
        }
    ],
    "sg:phone":"+44 1483 722133",
    "sg:postcode":"GU22 7SG",
    "sg:province":"Surrey",
    "sg:tags":[
        "upholstering",
        "upholsterer"
    ],
    "wof:name":"Are You Sitting Comfortably",
    "wof:placetype":"venue"
},
  "geometry": {"coordinates":[-0.5613,51.310593],"type":"Point"}
}