{
  "type": "Feature",
  "properties": {
    "addr:full":"Moorclose Est Workington Cumbria CA14 3LL",
    "addr:postcode":"ca14 3ll",
    "addr:street":"Moorclose",
    "iso:country":"GB",
    "sg:address":"Moorclose Est",
    "sg:city":"Workington",
    "sg:classifiers":[
        {
            "category":"Community Center",
            "type":"Public Place"
        }
    ],
    "sg:phone":"+44 1900 61771",
    "sg:postcode":"CA14 3LL",
    "sg:province":"Cumbria",
    "sg:tags":[
        "recreation",
        "leisure",
        "centre"
    ],
    "wof:name":"Workington Sports Centre",
    "wof:placetype":"venue"
},
  "geometry": {"coordinates":[-3.551221,54.625813],"type":"Point"}
}