{
  "type": "Feature",
  "properties": {
    "iso:country":"GB",
    "sg:address":"38 Archibald Road",
    "sg:city":"Exeter",
    "sg:classifiers":[
        {
            "category":"Building & Trades",
            "subcategory":"Plumbing",
            "type":"Services"
        }
    ],
    "sg:phone":"+44 1392 427515",
    "sg:postcode":"EX1 1SA",
    "sg:province":"Devon",
    "sg:tags":[
        "drain",
        "clearance",
        "sewer"
    ],
    "wof:name":"All Points Plumbing & Draining",
    "wof:placetype":"venue"
},
  "geometry": {"coordinates":[-3.523167,50.723942],"type":"Point"}
}