{
  "type": "Feature",
  "properties": {
    "addr:full":"7 Arundel St, Mossley Ashton-under-lyne Greater Manchester OL5 0NY",
    "addr:housenumber":"7",
    "addr:postcode":"ol5 0ny",
    "addr:street":"Arundel St",
    "iso:country":"GB",
    "sg:address":"7 Arundel St, Mossley",
    "sg:city":"Ashton-under-lyne",
    "sg:classifiers":[
        {
            "category":"Shopping",
            "subcategory":"Bicycles & Sporting Goods",
            "type":"Retail Goods"
        }
    ],
    "sg:postcode":"OL5 0NY",
    "sg:province":"Greater Manchester",
    "sg:tags":[
        "riding",
        "saddlery",
        "wear"
    ],
    "wof:name":"Phillips,Marie,",
    "wof:placetype":"venue"
},
  "geometry": {"coordinates":[-2.0466840267,53.5191307068],"type":"Point"}
}