{
  "type": "Feature",
  "properties": {
    "iso:country":"GB",
    "sg:address":"207 Victoria Avenue, Borrowash",
    "sg:city":"Derby",
    "sg:classifiers":[
        {
            "category":"Health Services",
            "subcategory":"Doctor",
            "type":"Services"
        },
        {
            "category":"Health Services",
            "subcategory":"Clinic",
            "type":"Services"
        }
    ],
    "sg:phone":"+44 1332 280800",
    "sg:postcode":"DE72 3HG",
    "sg:province":"Derbyshire",
    "sg:tags":[
        "nh"
    ],
    "wof:name":"Overdale Medical Practice",
    "wof:placetype":"venue"
},
  "geometry": {"coordinates":[-1.377967,52.9123764038],"type":"Point"}
}