{
  "type": "Feature",
  "properties": {
    "iso:country":"GB",
    "sg:address":"2-26 Victoria Street, Shirebrook",
    "sg:city":"Mansfield",
    "sg:classifiers":[
        {
            "category":"Food & Beverages",
            "subcategory":"Supermarket",
            "type":"Retail Goods"
        }
    ],
    "sg:phone":"+44 1623 746056",
    "sg:postcode":"NG20 8AQ",
    "sg:province":"Derbyshire",
    "wof:name":"Greater Nottingham Co-Op",
    "wof:placetype":"venue"
},
  "geometry": {"coordinates":[-1.2133690119,53.2038002014],"type":"Point"}
}