{
  "type": "Feature",
  "properties": {
    "iso:country":"GB",
    "sg:address":"138 Southampton Road",
    "sg:city":"Eastleigh",
    "sg:classifiers":[
        {
            "category":"Personal",
            "type":"Services"
        }
    ],
    "sg:phone":"+44 23 8061 8598",
    "sg:postcode":"SO50 5QX",
    "sg:province":"Hampshire",
    "sg:tags":[
        "wedding"
    ],
    "wof:name":"Just Weddings",
    "wof:placetype":"venue"
},
  "geometry": {"coordinates":[-1.351271,50.965652],"type":"Point"}
}