{
  "type": "Feature",
  "properties": {
    "addr:full":"46 Cardiff Road, Llandaff Cardiff Cardiff CF5 2DT",
    "addr:housenumber":"46",
    "addr:postcode":"cf5 2dt",
    "addr:street":"Cardiff Road",
    "iso:country":"GB",
    "sg:address":"46 Cardiff Road, Llandaff",
    "sg:city":"Cardiff",
    "sg:classifiers":[
        {
            "category":"Communications",
            "type":"Services"
        }
    ],
    "sg:phone":"+44 29 2057 3900",
    "sg:postcode":"CF5 2DT",
    "sg:province":"Cardiff",
    "sg:tags":[
        "audio-visual"
    ],
    "wof:name":"Mwnci Cyfyngedig",
    "wof:placetype":"venue"
},
  "geometry": {"coordinates":[-3.220193,51.493587],"type":"Point"}
}