{
  "type": "Feature",
  "properties": {
    "iso:country":"GB",
    "sg:address":"12 Mountain Crescent",
    "sg:city":"Perth",
    "sg:classifiers":[
        {
            "category":"Building & Trades",
            "subcategory":"Construction",
            "type":"Services"
        }
    ],
    "sg:phone":"+44 1738 634237",
    "sg:postcode":"PH2 8AY",
    "sg:province":"Perth and Kinross",
    "sg:tags":[
        "roofing",
        "contracting"
    ],
    "wof:name":"J Fletcher & Son",
    "wof:placetype":"venue"
},
  "geometry": {"coordinates":[-3.4324140549,56.3960533142],"type":"Point"}
}