{
  "type": "Feature",
  "properties": {
    "iso:country":"GB",
    "sg:address":"4 Commercial Street, Pontnewydd",
    "sg:city":"Cwmbran",
    "sg:classifiers":[
        {
            "category":"Home & Garden",
            "subcategory":"Carpets & Floor Coverings",
            "type":"Retail Goods"
        }
    ],
    "sg:phone":"+44 1633 877500",
    "sg:postcode":"NP44 2QF",
    "sg:province":"Monmouthshire",
    "sg:tags":[
        "carpets",
        "rug",
        "matting"
    ],
    "wof:name":"Blind Shop",
    "wof:placetype":"venue"
},
  "geometry": {"coordinates":[-3.025864,51.657467],"type":"Point"}
}