{
  "type": "Feature",
  "properties": {
    "iso:country":"GB",
    "sg:address":"Park House Farm, Aberford Road",
    "sg:city":"Leeds",
    "sg:classifiers":[
        {
            "category":"Farming",
            "subcategory":"Farm",
            "type":"Manufacturing & Wholesale Goods"
        }
    ],
    "sg:phone":"+44 113 281 3611",
    "sg:postcode":"LS25 3DH",
    "sg:province":"North Yorkshire",
    "sg:tags":[
        "agricultural"
    ],
    "wof:name":"Northern Handlers Ltd.",
    "wof:placetype":"venue"
},
  "geometry": {"coordinates":[-1.343052,53.829151],"type":"Point"}
}