{
  "type": "Feature",
  "properties": {
    "addr:full":"56 Demesne Road Wallington Surrey SM6 8PP",
    "addr:housenumber":"56",
    "addr:postcode":"sm6 8pp",
    "addr:street":"Demesne Road",
    "iso:country":"GB",
    "sg:address":"56 Demesne Road",
    "sg:city":"Wallington",
    "sg:classifiers":[
        {
            "category":"Food & Beverages",
            "subcategory":"Liquor & Beverages",
            "type":"Retail Goods"
        }
    ],
    "sg:postcode":"SM6 8PP",
    "sg:province":"Surrey",
    "sg:tags":[
        "beer",
        "spirit",
        "wines"
    ],
    "wof:name":"Bottle & Basket",
    "wof:placetype":"venue"
},
  "geometry": {"coordinates":[-0.1401389986,51.3618431091],"type":"Point"}
}