{
  "type": "Feature",
  "properties": {
    "iso:country":"GB",
    "sg:address":"99 Hartforde Road",
    "sg:city":"Borehamwood",
    "sg:classifiers":[
        {
            "category":"Shopping",
            "subcategory":"Bicycles & Sporting Goods",
            "type":"Retail Goods"
        }
    ],
    "sg:postcode":"WD6 5HY",
    "sg:province":"Hertfordshire",
    "sg:tags":[
        "riding",
        "saddlery",
        "wear"
    ],
    "wof:name":"Field Sports",
    "wof:placetype":"venue"
},
  "geometry": {"coordinates":[-0.2695780098,51.6656608582],"type":"Point"}
}