{
  "type": "Feature",
  "properties": {
    "iso:country":"GB",
    "sg:address":"Maidencroft Farm, Wick",
    "sg:city":"Glastonbury",
    "sg:classifiers":[
        {
            "category":"Organizations",
            "subcategory":"Non-profit Organization",
            "type":"Services"
        }
    ],
    "sg:phone":"+44 1458 835292",
    "sg:postcode":"BA6 8JN",
    "sg:province":"Somerset",
    "sg:tags":[
        "organisation",
        "voluntary",
        "charity"
    ],
    "wof:name":"British Trust for Conservation Volunteers",
    "wof:placetype":"venue"
},
  "geometry": {"coordinates":[-2.6993319988,51.1519737244],"type":"Point"}
}