{
  "type": "Feature",
  "properties": {
    "iso:country":"GB",
    "sg:address":"89 Heathfield Avenue",
    "sg:city":"Dover",
    "sg:classifiers":[
        {
            "category":"Arts & Performance",
            "subcategory":"Music",
            "type":"Entertainment"
        }
    ],
    "sg:phone":"+44 1304 210581",
    "sg:postcode":"CT16 2PD",
    "sg:province":"Kent",
    "sg:tags":[
        "mobile",
        "disco"
    ],
    "wof:name":"Stampede Disco",
    "wof:placetype":"venue"
},
  "geometry": {"coordinates":[1.300579,51.137009],"type":"Point"}
}