{
  "type": "Feature",
  "properties": {
    "addr:full":"36 The Dell Bradford West Yorkshire BD13 5AH",
    "addr:housenumber":"36",
    "addr:postcode":"bd13 5ah",
    "addr:street":"The Dell Bradford West",
    "iso:country":"GB",
    "sg:address":"36 The Dell",
    "sg:city":"Bradford",
    "sg:classifiers":[
        {
            "category":"Education",
            "subcategory":"College",
            "type":"Public Place"
        }
    ],
    "sg:phone":"+44 1535 272753",
    "sg:postcode":"BD13 5AH",
    "sg:province":"West Yorkshire",
    "sg:tags":[
        "school"
    ],
    "wof:name":"Term Time Wear",
    "wof:placetype":"venue"
},
  "geometry": {"coordinates":[-1.893789053,53.8285446167],"type":"Point"}
}