{
  "type": "Feature",
  "properties": {
    "iso:country":"GB",
    "sg:address":"1 Cole Road",
    "sg:city":"Bristol",
    "sg:classifiers":[
        {
            "category":"Manufacturing",
            "subcategory":"Building Materials",
            "type":"Manufacturing & Wholesale Goods"
        }
    ],
    "sg:phone":"+44 117 971 7341",
    "sg:postcode":"BS2 0UG",
    "sg:province":"City of Bristol",
    "sg:tags":[
        "merchant",
        "builder"
    ],
    "wof:name":"H J Chard & Sons",
    "wof:placetype":"venue"
},
  "geometry": {"coordinates":[-2.5637779236,51.4504928589],"type":"Point"}
}