{
  "type": "Feature",
  "properties": {
    "iso:country":"GB",
    "sg:address":"71 Montagu Road, Datchet",
    "sg:city":"Slough",
    "sg:classifiers":[
        {
            "category":"Professional",
            "subcategory":"Engineering",
            "type":"Services"
        }
    ],
    "sg:phone":"+44 1753 620300",
    "sg:postcode":"SL3 9DX",
    "sg:province":"Berkshire",
    "sg:tags":[
        "contractor",
        "electrical",
        "engineer"
    ],
    "wof:name":"Brown Electrical Services",
    "wof:placetype":"venue"
},
  "geometry": {"coordinates":[-0.5739279985,51.4789733887],"type":"Point"}
}