{
  "type": "Feature",
  "properties": {
    "addr:full":"Ostend Place Newcastle Staffordshire ST5 2QY",
    "addr:postcode":"st5 2qy",
    "addr:street":"Ostend Place",
    "iso:country":"GB",
    "sg:address":"Ostend Place",
    "sg:city":"Newcastle",
    "sg:classifiers":[
        {
            "category":"Education",
            "subcategory":"School",
            "type":"Public Place"
        }
    ],
    "sg:phone":"+44 1782 610580",
    "sg:postcode":"ST5 2QY",
    "sg:province":"Staffordshire",
    "sg:tags":[
        "local",
        "authority"
    ],
    "wof:name":"Westlands County Primary School",
    "wof:placetype":"venue"
},
  "geometry": {"coordinates":[-2.2470319271,53.0027389526],"type":"Point"}
}