{
  "type": "Feature",
  "properties": {
    "iso:country":"GB",
    "sg:address":"77 Newman Street",
    "sg:city":"London",
    "sg:classifiers":[
        {
            "category":"Real Estate",
            "subcategory":"Real Estate Agent",
            "type":"Services"
        }
    ],
    "sg:phone":"+44 20 7307 9230",
    "sg:postcode":"W1T 3EW",
    "sg:province":"Greater London",
    "wof:name":"Noel St.Properties Ltd.",
    "wof:placetype":"venue"
},
  "geometry": {"coordinates":[-0.135756,51.517384],"type":"Point"}
}