{
  "type": "Feature",
  "properties": {
    "iso:country":"GB",
    "sg:address":"180 Whitehall Road, Drighlington",
    "sg:city":"Bradford",
    "sg:classifiers":[
        {
            "category":"Shopping",
            "subcategory":"Photographic Equipment",
            "type":"Retail Goods"
        }
    ],
    "sg:phone":"+44 113 285 4711",
    "sg:postcode":"BD11 1AU",
    "sg:province":"West Yorkshire",
    "wof:name":"Picture Perfect Studio",
    "wof:placetype":"venue"
},
  "geometry": {"coordinates":[-1.663558,53.75639],"type":"Point"}
}