{
  "type": "Feature",
  "properties": {
    "addr:full":"42 Newman St West End Hampshire W1P 3PA",
    "addr:housenumber":"42",
    "addr:postcode":"w1p 3pa",
    "addr:street":"Newman St",
    "iso:country":"GB",
    "sg:address":"42 Newman St",
    "sg:city":"West End",
    "sg:classifiers":[
        {
            "category":"Travel",
            "subcategory":"Travel Agent",
            "type":"Entertainment"
        }
    ],
    "sg:phone":"+44 20 7636 3191",
    "sg:postcode":"W1P 3PA",
    "sg:province":"Hampshire",
    "wof:name":"Metro Travel & Tours",
    "wof:placetype":"venue"
},
  "geometry": {"coordinates":[-0.136534,51.518833],"type":"Point"}
}