{
  "type": "Feature",
  "properties": {
    "addr:full":"1 Wedderburn Road Harrogate North Yorkshire HG2 7QH",
    "addr:housenumber":"1",
    "addr:postcode":"hg2 7qh",
    "addr:street":"Wedderburn Road",
    "iso:country":"GB",
    "sg:address":"1 Wedderburn Road",
    "sg:city":"Harrogate",
    "sg:classifiers":[
        {
            "category":"Shopping",
            "subcategory":"Department Store",
            "type":"Retail Goods"
        },
        {
            "category":"Wholesale",
            "subcategory":"Sporting Goods",
            "type":"Manufacturing & Wholesale Goods"
        },
        {
            "category":"Shopping",
            "subcategory":"Bicycles & Sporting Goods",
            "type":"Retail Goods"
        }
    ],
    "sg:phone":"+44 1423 887003",
    "sg:postcode":"HG2 7QH",
    "sg:province":"North Yorkshire",
    "sg:tags":[
        "shop",
        "wholesaler",
        "cycle",
        "mnfrs"
    ],
    "wof:name":"Spa Cycle Supplies",
    "wof:placetype":"venue"
},
  "geometry": {"coordinates":[-1.509381,53.989883],"type":"Point"}
}