{
  "type": "Feature",
  "properties": {
    "iso:country":"GB",
    "sg:address":"6 Bloomsbury Square",
    "sg:city":"Bloomsbury",
    "sg:classifiers":[
        {
            "category":"Professional",
            "subcategory":"Management & Consulting",
            "type":"Services"
        }
    ],
    "sg:phone":"+44 20 7242 2358",
    "sg:postcode":"WC1A 2LP",
    "sg:province":"Greater London",
    "sg:tags":[
        "sport"
    ],
    "wof:name":"Panix Promotions",
    "wof:placetype":"venue"
},
  "geometry": {"coordinates":[-0.123089,51.518288],"type":"Point"}
}