{
  "type": "Feature",
  "properties": {
    "addr:full":"Ribblesdale Service Stn, Liverpool New R, Much Hoole Preston Lancashire PR4 5JX",
    "addr:postcode":"pr4 5jx",
    "addr:street":"R",
    "iso:country":"GB",
    "sg:address":"Ribblesdale Service Stn, Liverpool New R, Much Hoole",
    "sg:city":"Preston",
    "sg:classifiers":[
        {
            "category":"Retail",
            "subcategory":"Auto Repair",
            "type":"Services"
        }
    ],
    "sg:postcode":"PR4 5JX",
    "sg:province":"Lancashire",
    "sg:tags":[
        "modification",
        "garage"
    ],
    "wof:name":"Davies,Anthony,",
    "wof:placetype":"venue"
},
  "geometry": {"coordinates":[-2.800909996,53.7039413452],"type":"Point"}
}