{
  "type": "Feature",
  "properties": {
    "iso:country":"GB",
    "sg:address":"61c High Street",
    "sg:city":"Burnham-on-crouch",
    "sg:classifiers":[
        {
            "category":"Manufacturing",
            "subcategory":"Watercraft",
            "type":"Manufacturing & Wholesale Goods"
        }
    ],
    "sg:phone":"+44 1621 786200",
    "sg:postcode":"CM0 8AH",
    "sg:province":"Essex",
    "sg:tags":[
        "manufacture",
        "repairer",
        "sail",
        "sailmaker"
    ],
    "wof:name":"Lonton & Gray Sailmakers",
    "wof:placetype":"venue"
},
  "geometry": {"coordinates":[0.819495,51.625172],"type":"Point"}
}