{
  "type": "Feature",
  "properties": {
    "addr:full":"61c High Street Burnham-on-crouch Essex CM0 8AH",
    "addr:housenumber":"61c",
    "addr:postcode":"cm0 8ah",
    "addr:street":"High Street",
    "iso:country":"GB",
    "sg:address":"61c High Street",
    "sg:city":"Burnham-on-crouch",
    "sg:classifiers":[
        {
            "category":"Manufacturing",
            "subcategory":"Watercraft",
            "type":"Manufacturing & Wholesale Goods"
        }
    ],
    "sg:phone":"+44 1621 786200",
    "sg:postcode":"CM0 8AH",
    "sg:province":"Essex",
    "sg:tags":[
        "manufacture",
        "repairer",
        "sail",
        "sailmaker"
    ],
    "wof:name":"Lonton & Gray Sailmakers",
    "wof:placetype":"venue"
},
  "geometry": {"coordinates":[0.819495,51.625172],"type":"Point"}
}