{
  "type": "Feature",
  "properties": {
    "iso:country":"GB",
    "sg:address":"St Georges Centre, Front Street",
    "sg:city":"East Boldon",
    "sg:classifiers":[
        {
            "category":"Farming",
            "subcategory":"Nursery",
            "type":"Manufacturing & Wholesale Goods"
        }
    ],
    "sg:phone":"+44 191 519 3824",
    "sg:postcode":"NE36 0SW",
    "sg:province":"Tyne and Wear",
    "sg:tags":[
        "creche"
    ],
    "wof:name":"Little Acorns",
    "wof:placetype":"venue"
},
  "geometry": {"coordinates":[-1.423244,54.945065],"type":"Point"}
}