{
  "type": "Feature",
  "properties": {
    "addr:full":"27 Shortlands Road Bromley Kent BR2 0JG",
    "addr:housenumber":"27",
    "addr:postcode":"br2 0jg",
    "addr:street":"Shortlands Road",
    "iso:country":"GB",
    "sg:address":"27 Shortlands Road",
    "sg:city":"Bromley",
    "sg:classifiers":[
        {
            "category":"Home & Garden",
            "subcategory":"Home Furnishings",
            "type":"Retail Goods"
        }
    ],
    "sg:postcode":"BR2 0JG",
    "sg:province":"Kent",
    "sg:tags":[
        "furnishers",
        "planner",
        "kitchen"
    ],
    "wof:name":"Kitchen Harmony",
    "wof:placetype":"venue"
},
  "geometry": {"coordinates":[0.0041390001,51.4074554443],"type":"Point"}
}