{
  "type": "Feature",
  "properties": {
    "addr:full":"Bethesda Street Merthyr Tydfil Merthyr Tydfil CF47 8LL",
    "addr:postcode":"cf47 8ll",
    "addr:street":"Bethesda Street",
    "iso:country":"GB",
    "sg:address":"Bethesda Street",
    "sg:city":"Merthyr Tydfil",
    "sg:classifiers":[
        {
            "category":"Restaurant",
            "type":"Food & Drink"
        }
    ],
    "sg:phone":"+44 1685 370770",
    "sg:postcode":"CF47 8LL",
    "sg:province":"Merthyr Tydfil",
    "wof:name":"The Rooms Pub",
    "wof:placetype":"venue"
},
  "geometry": {"coordinates":[-3.3837239742,51.7491798401],"type":"Point"}
}