{
  "type": "Feature",
  "properties": {
    "iso:country":"GB",
    "sg:address":"45 Eastern Street",
    "sg:city":"Portland",
    "sg:classifiers":[
        {
            "category":"Real Estate",
            "subcategory":"Real Estate Agent",
            "type":"Services"
        }
    ],
    "sg:phone":"+44 1305 821500",
    "sg:postcode":"DT5 1BS",
    "sg:province":"Dorset",
    "wof:name":"Timms Direct",
    "wof:placetype":"venue"
},
  "geometry": {"coordinates":[-2.43618,50.546925],"type":"Point"}
}