{
  "type": "Feature",
  "properties": {
    "addr:full":"Aldine Ho, 9-15 Aldine St Shepherd's Bush Greater London W12 8AW",
    "addr:housenumber":"9-15",
    "addr:postcode":"w12 8aw",
    "addr:street":"Aldine St",
    "iso:country":"GB",
    "sg:address":"Aldine Ho, 9-15 Aldine St",
    "sg:city":"Shepherd's Bush",
    "sg:classifiers":[
        {
            "category":"Wholesale",
            "subcategory":"Books, Periodicals, & Newspapers",
            "type":"Manufacturing & Wholesale Goods"
        }
    ],
    "sg:phone":"+44 20 8740 2277",
    "sg:postcode":"W12 8AW",
    "sg:province":"Greater London",
    "sg:tags":[
        "publishing"
    ],
    "wof:name":"Blackstone Press Ltd",
    "wof:placetype":"venue"
},
  "geometry": {"coordinates":[-0.22245,51.505089],"type":"Point"}
}