{
  "type": "Feature",
  "properties": {
    "addr:full":"49 Cleaver Square London Greater London SE11 4EA",
    "addr:housenumber":"49",
    "addr:postcode":"se11 4ea",
    "addr:street":"Cleaver Square",
    "iso:country":"GB",
    "sg:address":"49 Cleaver Square",
    "sg:city":"London",
    "sg:classifiers":[
        {
            "category":"Home & Garden",
            "subcategory":"Home Furnishings",
            "type":"Retail Goods"
        },
        {
            "category":"Manufacturing",
            "subcategory":"Furniture",
            "type":"Manufacturing & Wholesale Goods"
        }
    ],
    "sg:phone":"+44 20 7587 0221",
    "sg:postcode":"SE11 4EA",
    "sg:province":"Greater London",
    "sg:tags":[
        "furnishers",
        "planner",
        "designer",
        "kitchen"
    ],
    "wof:name":"Weston Pardy Design Consultancy",
    "wof:placetype":"venue"
},
  "geometry": {"coordinates":[-0.10873,51.488091],"type":"Point"}
}