{
  "type": "Feature",
  "properties": {
    "iso:country":"GB",
    "sg:address":"70-72 Greenwood Road",
    "sg:city":"London",
    "sg:classifiers":[
        {
            "category":"Travel",
            "subcategory":"Hostel",
            "type":"Entertainment"
        },
        {
            "category":"Government",
            "subcategory":"Office",
            "type":"Public Place"
        }
    ],
    "sg:phone":"+44 20 7923 4800",
    "sg:postcode":"E8 1NE",
    "sg:province":"Greater London",
    "sg:tags":[
        "local"
    ],
    "wof:name":"Greenwood Road Mental Health Hostel",
    "wof:placetype":"venue"
},
  "geometry": {"coordinates":[-0.063609,51.545929],"type":"Point"}
}