{
  "type": "Feature",
  "properties": {
    "iso:country":"GB",
    "sg:address":"38 Dartford Rd",
    "sg:city":"Sevenoaks",
    "sg:classifiers":[
        {
            "category":"Professional",
            "subcategory":"Business Services",
            "type":"Services"
        }
    ],
    "sg:phone":"+44 1732 455200",
    "sg:postcode":"TN13 3TQ",
    "sg:province":"Kent",
    "sg:tags":[
        "transfer",
        "agent"
    ],
    "wof:name":"Everett Masson & Furby",
    "wof:placetype":"venue"
},
  "geometry": {"coordinates":[0.1944980025,51.2811164856],"type":"Point"}
}