{
  "type": "Feature",
  "properties": {
    "addr:full":"Old Station Yard, Station Rd Shipston On Stour Warwickshire CV36 4BW",
    "addr:postcode":"cv36 4bw",
    "addr:street":"Old Station;Station Rd",
    "iso:country":"GB",
    "sg:address":"Old Station Yard, Station Rd",
    "sg:city":"Shipston On Stour",
    "sg:classifiers":[
        {
            "category":"Utilities",
            "subcategory":"Fuel Oil & Lpg",
            "type":"Services"
        }
    ],
    "sg:phone":"+44 1608 661432",
    "sg:postcode":"CV36 4BW",
    "sg:province":"Warwickshire",
    "sg:tags":[
        "coal",
        "smokeless"
    ],
    "wof:name":"Compton Solid Fuels",
    "wof:placetype":"venue"
},
  "geometry": {"coordinates":[-1.6271339655,52.0622711182],"type":"Point"}
}