{
  "type": "Feature",
  "properties": {
    "addr:full":"6 Charlotte Street Melton Mowbray Leicestershire LE13 1NA",
    "addr:housenumber":"6",
    "addr:postcode":"le13 1na",
    "addr:street":"Charlotte Street",
    "iso:country":"GB",
    "sg:address":"6 Charlotte Street",
    "sg:city":"Melton Mowbray",
    "sg:classifiers":[
        {
            "category":"Manufacturing",
            "subcategory":"Metals",
            "type":"Manufacturing & Wholesale Goods"
        },
        {
            "category":"Real Estate",
            "subcategory":"Architect",
            "type":"Services"
        }
    ],
    "sg:phone":"+44 1664 562219",
    "sg:postcode":"LE13 1NA",
    "sg:province":"Leicestershire",
    "sg:tags":[
        "steel",
        "fabricator",
        "erectors"
    ],
    "wof:name":"J Hill & Co. (Engineers Melton Mowbray) Ltd.",
    "wof:placetype":"venue"
},
  "geometry": {"coordinates":[-0.8861389756,52.7670898438],"type":"Point"}
}