{
  "type": "Feature",
  "properties": {
    "iso:country":"GB",
    "sg:address":"88 Victoria Chase",
    "sg:city":"Colchester",
    "sg:classifiers":[
        {
            "category":"Education",
            "subcategory":"Dance Studio",
            "type":"Public Place"
        }
    ],
    "sg:phone":"+44 1206 548151",
    "sg:postcode":"CO1 1WN",
    "sg:province":"Essex",
    "sg:tags":[
        "school",
        "dancing"
    ],
    "wof:name":"T Parkes",
    "wof:placetype":"venue"
},
  "geometry": {"coordinates":[0.8939070106,51.8948249817],"type":"Point"}
}