{
  "type": "Feature",
  "properties": {
    "iso:country":"GB",
    "sg:address":"39a Peel Street, Morley",
    "sg:city":"Leeds",
    "sg:classifiers":[
        {
            "category":"Food & Beverages",
            "subcategory":"Liquor & Beverages",
            "type":"Retail Goods"
        }
    ],
    "sg:postcode":"LS27 8RG",
    "sg:province":"West Yorkshire",
    "sg:tags":[
        "beer",
        "spirit",
        "wines"
    ],
    "wof:name":"R H Stores",
    "wof:placetype":"venue"
},
  "geometry": {"coordinates":[-1.594094038,53.7464752197],"type":"Point"}
}