{
  "type": "Feature",
  "properties": {
    "addr:full":"Glasgow Road Clydebank East Dunbartonshire G81 1YA",
    "addr:postcode":"g81 1ya",
    "addr:street":"Glasgow Road",
    "iso:country":"GB",
    "sg:address":"Glasgow Road",
    "sg:city":"Clydebank",
    "sg:classifiers":[
        {
            "category":"Travel",
            "subcategory":"Travel Agent",
            "type":"Entertainment"
        }
    ],
    "sg:phone":"+44 141 952 0381",
    "sg:postcode":"G81 1YA",
    "sg:province":"East Dunbartonshire",
    "wof:name":"Cunard Business Travel",
    "wof:placetype":"venue"
},
  "geometry": {"coordinates":[-4.3921837807,55.8934593201],"type":"Point"}
}