{
  "type": "Feature",
  "properties": {
    "addr:full":"113 Northenden Road, Sale Moor Sale Cheshire M33 3HF",
    "addr:housenumber":"113",
    "addr:postcode":"m33 3hf",
    "addr:street":"Northenden Road;Sale Cheshire",
    "iso:country":"GB",
    "sg:address":"113 Northenden Road, Sale Moor",
    "sg:city":"Sale",
    "sg:classifiers":[
        {
            "category":"Shopping",
            "subcategory":"Florist",
            "type":"Retail Goods"
        }
    ],
    "sg:postcode":"M33 3HF",
    "sg:province":"Cheshire",
    "wof:name":"Fleur de Vie",
    "wof:placetype":"venue"
},
  "geometry": {"coordinates":[-2.30513,53.420425],"type":"Point"}
}