{
  "type": "Feature",
  "properties": {
    "iso:country":"GB",
    "sg:address":"Unit 10 Castle Meadow Retail Park, Castle Bridge Rd",
    "sg:city":"Nottingham",
    "sg:classifiers":[
        {
            "category":"Professional",
            "subcategory":"Computer Services",
            "type":"Services"
        }
    ],
    "sg:phone":"+44 115 950 6666",
    "sg:postcode":"NG7 1GX",
    "sg:province":"Nottinghamshire",
    "sg:tags":[
        "system",
        "software"
    ],
    "wof:name":"Byte Computer Superstore",
    "wof:placetype":"venue"
},
  "geometry": {"coordinates":[-1.160122,52.945518],"type":"Point"}
}