{
  "type": "Feature",
  "properties": {
    "iso:country":"GB",
    "sg:address":"The Natural Health Centre, 33 Pound Street",
    "sg:city":"Newbury",
    "sg:classifiers":[
        {
            "category":"Health Services",
            "subcategory":"Health Practitioner",
            "type":"Services"
        },
        {
            "category":"Health Services",
            "subcategory":"Podiatrist",
            "type":"Services"
        }
    ],
    "sg:phone":"+44 1635 580200",
    "sg:postcode":"RG14 6AE",
    "sg:province":"Berkshire",
    "sg:tags":[
        "podiatrists",
        "osteopath",
        "chiropodist"
    ],
    "wof:name":"The Natural Health Centre",
    "wof:placetype":"venue"
},
  "geometry": {"coordinates":[-1.3258719444,51.405872345],"type":"Point"}
}