{
  "type": "Feature",
  "properties": {
    "addr:full":"24 Deerdykes View, Westfield Ind Est, Cumbernauld Glasgow East Dunbartonshire G68 9HN",
    "addr:housenumber":"24",
    "addr:postcode":"g68 9hn",
    "addr:street":"Deerdykes View",
    "iso:country":"GB",
    "sg:address":"24 Deerdykes View, Westfield Ind Est, Cumbernauld",
    "sg:city":"Glasgow",
    "sg:classifiers":[
        {
            "category":"Retail",
            "subcategory":"Auto Repair",
            "type":"Services"
        }
    ],
    "sg:phone":"+44 1236 781811",
    "sg:postcode":"G68 9HN",
    "sg:province":"East Dunbartonshire",
    "sg:tags":[
        "car",
        "servicing",
        "radiator"
    ],
    "wof:name":"Caledonian Radiators Ltd",
    "wof:placetype":"venue"
},
  "geometry": {"coordinates":[-4.0532441139,55.9283027649],"type":"Point"}
}