{
  "type": "Feature",
  "properties": {
    "addr:full":"Forewood Lane, Crowhurst Battle East Sussex TN33 9AB",
    "addr:postcode":"tn33 9ab",
    "addr:street":"Forewood Lane;Battle",
    "iso:country":"GB",
    "sg:address":"Forewood Lane, Crowhurst",
    "sg:city":"Battle",
    "sg:classifiers":[
        {
            "category":"Recreation",
            "subcategory":"Campground",
            "type":"Entertainment"
        }
    ],
    "sg:phone":"+44 1424 830322",
    "sg:postcode":"TN33 9AB",
    "sg:province":"East Sussex",
    "sg:tags":[
        "site",
        "camping"
    ],
    "wof:name":"Brakes Coppice Park",
    "wof:placetype":"venue"
},
  "geometry": {"coordinates":[0.499597,50.890072],"type":"Point"}
}