{
  "type": "Feature",
  "properties": {
    "addr:full":"7a Clarendon Road Weston-super-mare Somerset BS23 3EE",
    "addr:housenumber":"7a",
    "addr:postcode":"bs23 3ee",
    "addr:street":"Clarendon Road",
    "iso:country":"GB",
    "sg:address":"7a Clarendon Road",
    "sg:city":"Weston-super-mare",
    "sg:classifiers":[
        {
            "category":"Retail",
            "subcategory":"Auto Repair",
            "type":"Services"
        }
    ],
    "sg:phone":"+44 1934 626673",
    "sg:postcode":"BS23 3EE",
    "sg:province":"Somerset",
    "sg:tags":[
        "body",
        "garage",
        "modification",
        "car"
    ],
    "wof:name":"Ashcombe Motors",
    "wof:placetype":"venue"
},
  "geometry": {"coordinates":[-2.968154,51.348774],"type":"Point"}
}