{
  "type": "Feature",
  "properties": {
    "iso:country":"GB",
    "sg:address":"Oaklands, Hackney Lane",
    "sg:city":"Dronfield",
    "sg:classifiers":[
        {
            "category":"Shopping",
            "subcategory":"Music",
            "type":"Retail Goods"
        }
    ],
    "sg:phone":"+44 114 289 1246",
    "sg:postcode":"S18 7TD",
    "sg:province":"Derbyshire",
    "sg:tags":[
        "record",
        "tape",
        "cd"
    ],
    "wof:name":"Keepsake Productions Ltd.",
    "wof:placetype":"venue"
},
  "geometry": {"coordinates":[-1.469424,53.304729],"type":"Point"}
}