{
  "type": "Feature",
  "properties": {
    "iso:country":"GB",
    "sg:address":"107 Queensway",
    "sg:city":"Orpington",
    "sg:classifiers":[
        {
            "category":"Fast Food",
            "type":"Food & Drink"
        }
    ],
    "sg:postcode":"BR5 1DG",
    "sg:province":"Kent",
    "sg:tags":[
        "away",
        "take"
    ],
    "wof:name":"Euro 2000 Trading Ltd.",
    "wof:placetype":"venue"
},
  "geometry": {"coordinates":[0.072299,51.389175],"type":"Point"}
}