{
  "type": "Feature",
  "properties": {
    "addr:full":"Oakwood House, 526 Purley Way Croydon Surrey CR0 4RE",
    "addr:housenumber":"526",
    "addr:postcode":"cr0 4re",
    "addr:street":"Purley Way",
    "iso:country":"GB",
    "sg:address":"Oakwood House, 526 Purley Way",
    "sg:city":"Croydon",
    "sg:classifiers":[
        {
            "category":"Building & Trades",
            "subcategory":"Construction",
            "type":"Services"
        }
    ],
    "sg:phone":"+44 20 8296 1800",
    "sg:postcode":"CR0 4RE",
    "sg:province":"Surrey",
    "sg:tags":[
        "restoration",
        "refurbishment"
    ],
    "wof:name":"I T C Concepts Ltd.",
    "wof:placetype":"venue"
},
  "geometry": {"coordinates":[-0.118138,51.369232],"type":"Point"}
}