{
  "type": "Feature",
  "properties": {
    "iso:country":"GB",
    "sg:address":"151 Epsom Road",
    "sg:city":"Sutton",
    "sg:classifiers":[
        {
            "category":"Retail",
            "subcategory":"Funeral Services",
            "type":"Services"
        }
    ],
    "sg:phone":"+44 20 8644 8603",
    "sg:postcode":"SM3 9EY",
    "sg:province":"Surrey",
    "sg:tags":[
        "director"
    ],
    "wof:name":"Frederick W Paine",
    "wof:placetype":"venue"
},
  "geometry": {"coordinates":[-0.210623,51.386204],"type":"Point"}
}