{
  "type": "Feature",
  "properties": {
    "iso:country":"GB",
    "sg:address":"2 Larch Street",
    "sg:city":"Southport",
    "sg:classifiers":[
        {
            "category":"Retail",
            "subcategory":"Storage",
            "type":"Services"
        }
    ],
    "sg:phone":"+44 1704 544057",
    "sg:postcode":"PR8 6DP",
    "sg:province":"Lancashire",
    "sg:tags":[
        "household",
        "removal"
    ],
    "wof:name":"Lloyds Removals",
    "wof:placetype":"venue"
},
  "geometry": {"coordinates":[-2.979765,53.640732],"type":"Point"}
}