{
  "type": "Feature",
  "properties": {
    "iso:country":"GB",
    "sg:address":"St Nons Retreat",
    "sg:city":"Haverfordwest",
    "sg:classifiers":[
        {
            "category":"Organizations",
            "subcategory":"Religious Organization",
            "type":"Services"
        }
    ],
    "sg:phone":"+44 1437 720161",
    "sg:postcode":"SA62 6BN",
    "sg:province":"Pembrokeshire",
    "sg:tags":[
        "organisation"
    ],
    "wof:name":"Sisters Of Mercy",
    "wof:placetype":"venue"
},
  "geometry": {"coordinates":[-5.2705187798,51.8797035217],"type":"Point"}
}