{
  "type": "Feature",
  "properties": {
    "iso:country":"GB",
    "sg:address":"Toft Cottage, Main Rd, Friskney",
    "sg:city":"Boston",
    "sg:classifiers":[
        {
            "category":"Food & Beverages",
            "subcategory":"Groceries & Convenience Stores",
            "type":"Retail Goods"
        }
    ],
    "sg:phone":"+44 1754 820338",
    "sg:postcode":"PE22 8QU",
    "sg:province":"Lincolnshire",
    "sg:tags":[
        "merchant",
        "potato"
    ],
    "wof:name":"Tuplin & Son",
    "wof:placetype":"venue"
},
  "geometry": {"coordinates":[0.179487,53.077427],"type":"Point"}
}