{
  "type": "Feature",
  "properties": {
    "iso:country":"GB",
    "sg:address":"Mill Brow, Skelwith Bridge",
    "sg:city":"Ambleside",
    "sg:classifiers":[
        {
            "category":"Farming",
            "subcategory":"Livestock Farm",
            "type":"Manufacturing & Wholesale Goods"
        }
    ],
    "sg:postcode":"LA22 9NH",
    "sg:province":"Cumbria",
    "sg:tags":[
        "others"
    ],
    "wof:name":"G & P Long Farmers",
    "wof:placetype":"venue"
},
  "geometry": {"coordinates":[-2.963089,54.432606],"type":"Point"}
}