{
  "type": "Feature",
  "properties": {
    "addr:full":"The Dunraven 3 Blackmill Road, Bryncethin Bridgend Bridgend CF32 9YW",
    "addr:housenumber":"3",
    "addr:postcode":"cf32 9yw",
    "addr:street":"Blackmill Road",
    "iso:country":"GB",
    "sg:address":"The Dunraven 3 Blackmill Road, Bryncethin",
    "sg:city":"Bridgend",
    "sg:classifiers":[
        {
            "category":"Bars & Pubs",
            "type":"Food & Drink"
        }
    ],
    "sg:postcode":"CF32 9YW",
    "sg:province":"Bridgend",
    "sg:tags":[
        "pubs",
        "inn"
    ],
    "wof:name":"Icelane Ltd",
    "wof:placetype":"venue"
},
  "geometry": {"coordinates":[-3.566116,51.547226],"type":"Point"}
}