{
  "type": "Feature",
  "properties": {
    "addr:full":"Unit 1 Glasgow Glasgow City G31 2UH",
    "addr:housenumber":"unit 1",
    "addr:postcode":"g31 2uh",
    "iso:country":"GB",
    "sg:address":"Unit 1",
    "sg:city":"Glasgow",
    "sg:classifiers":[
        {
            "category":"Retail",
            "subcategory":"Auto Repair",
            "type":"Services"
        }
    ],
    "sg:phone":"+44 141 554 1910",
    "sg:postcode":"G31 2UH",
    "sg:province":"Glasgow City",
    "sg:tags":[
        "modification",
        "garage",
        "related"
    ],
    "wof:name":"LEO'S GARAGE",
    "wof:placetype":"venue"
},
  "geometry": {"coordinates":[-4.21,55.86137],"type":"Point"}
}