{
  "type": "Feature",
  "properties": {
    "addr:full":"The Oakley, Kidderminster Road Droitwich Worcestershire WR9 9AY",
    "addr:postcode":"wr9 9ay",
    "addr:street":"Kidderminster Road",
    "iso:country":"GB",
    "sg:address":"The Oakley, Kidderminster Road",
    "sg:city":"Droitwich",
    "sg:classifiers":[
        {
            "category":"Professional",
            "subcategory":"Management & Consulting",
            "type":"Services"
        }
    ],
    "sg:phone":"+44 1386 423423",
    "sg:postcode":"WR9 9AY",
    "sg:province":"Worcestershire",
    "sg:tags":[
        "consultant"
    ],
    "wof:name":"Beacon Communications Ltd.",
    "wof:placetype":"venue"
},
  "geometry": {"coordinates":[-2.1537868977,52.2715950012],"type":"Point"}
}