{
  "type": "Feature",
  "properties": {
    "addr:full":"155 Locking Road Weston-super-mare Somerset BS23 3ER",
    "addr:housenumber":"155",
    "addr:postcode":"bs23 3er",
    "addr:street":"Locking Road",
    "iso:country":"GB",
    "sg:address":"155 Locking Road",
    "sg:city":"Weston-super-mare",
    "sg:classifiers":[
        {
            "category":"Travel",
            "subcategory":"Hotels & Motels",
            "type":"Entertainment"
        }
    ],
    "sg:phone":"+44 1934 621017",
    "sg:postcode":"BS23 3ER",
    "sg:province":"Somerset",
    "sg:tags":[
        "house",
        "guest"
    ],
    "wof:name":"The Ashcroft Guest House",
    "wof:placetype":"venue"
},
  "geometry": {"coordinates":[-2.962082,51.345772],"type":"Point"}
}