{
  "type": "Feature",
  "properties": {
    "addr:full":"56-58 Parliament Street Harrogate North Yorkshire HG1 2RL",
    "addr:housenumber":"56-58",
    "addr:postcode":"hg1 2rl",
    "addr:street":"Parliament Street",
    "iso:country":"GB",
    "sg:address":"56-58 Parliament Street",
    "sg:city":"Harrogate",
    "sg:classifiers":[
        {
            "category":"Shopping",
            "subcategory":"Clothing, Apparel, & Fashions",
            "type":"Retail Goods"
        }
    ],
    "sg:postcode":"HG1 2RL",
    "sg:province":"North Yorkshire",
    "sg:tags":[
        "menswear"
    ],
    "wof:name":"The Rhodes-Wood Co. Ltd.",
    "wof:placetype":"venue"
},
  "geometry": {"coordinates":[-1.5438619852,53.994758606],"type":"Point"}
}