{
  "type": "Feature",
  "properties": {
    "addr:full":"The Brambles, Grinfield Avenue Bristol City of Bristol BS13 0TB",
    "addr:postcode":"bs13 0tb",
    "addr:street":"Grinfield Avenue",
    "iso:country":"GB",
    "sg:address":"The Brambles, Grinfield Avenue",
    "sg:city":"Bristol",
    "sg:classifiers":[
        {
            "category":"Social Services",
            "subcategory":"Adult Care",
            "type":"Services"
        },
        {
            "category":"Government",
            "subcategory":"Office",
            "type":"Public Place"
        }
    ],
    "sg:phone":"+44 117 964 5781",
    "sg:postcode":"BS13 0TB",
    "sg:province":"City of Bristol",
    "sg:tags":[
        "housing",
        "local",
        "sheltered"
    ],
    "wof:name":"The Brambles",
    "wof:placetype":"venue"
},
  "geometry": {"coordinates":[-2.591429,51.453667],"type":"Point"}
}