{
  "type": "Feature",
  "properties": {
    "addr:full":"14a Dean Close Windsor Berkshire SL4 4PL",
    "addr:housenumber":"14a",
    "addr:postcode":"sl4 4pl",
    "addr:street":"Dean Close",
    "iso:country":"GB",
    "sg:address":"14a Dean Close",
    "sg:city":"Windsor",
    "sg:classifiers":[
        {
            "category":"Professional",
            "subcategory":"Engineering",
            "type":"Services"
        }
    ],
    "sg:phone":"+44 1753 841052",
    "sg:postcode":"SL4 4PL",
    "sg:province":"Berkshire",
    "sg:tags":[
        "contractor",
        "electrical",
        "engineer"
    ],
    "wof:name":"Moss Switchgear Services Ltd.",
    "wof:placetype":"venue"
},
  "geometry": {"coordinates":[-0.6506029963,51.4745788574],"type":"Point"}
}