{
  "type": "Feature",
  "properties": {
    "addr:full":"22 Tuke Avenue York North Yorkshire YO10 3RN",
    "addr:housenumber":"22",
    "addr:postcode":"yo10 3rn",
    "addr:street":"Tuke Avenue",
    "iso:country":"GB",
    "sg:address":"22 Tuke Avenue",
    "sg:city":"York",
    "sg:classifiers":[
        {
            "category":"Building & Trades",
            "subcategory":"Construction",
            "type":"Services"
        }
    ],
    "sg:phone":"+44 1904 412477",
    "sg:postcode":"YO10 3RN",
    "sg:province":"North Yorkshire",
    "sg:tags":[
        "roofing"
    ],
    "wof:name":"Raymond Walton Mastic Asphalt Services",
    "wof:placetype":"venue"
},
  "geometry": {"coordinates":[-1.047283,53.95726],"type":"Point"}
}