{
  "type": "Feature",
  "properties": {
    "iso:country":"GB",
    "sg:address":"52 Little Carter Lane",
    "sg:city":"Mansfield",
    "sg:classifiers":[
        {
            "category":"Building & Trades",
            "subcategory":"Construction",
            "type":"Services"
        }
    ],
    "sg:phone":"+44 1623 632703",
    "sg:postcode":"NG18 3AB",
    "sg:province":"Nottinghamshire",
    "sg:tags":[
        "builder"
    ],
    "wof:name":"R D B Builder",
    "wof:placetype":"venue"
},
  "geometry": {"coordinates":[-1.1769189835,53.1432762146],"type":"Point"}
}