{
  "type": "Feature",
  "properties": {
    "iso:country":"GB",
    "sg:address":"215 Grimsby Road",
    "sg:city":"Cleethorpes",
    "sg:classifiers":[
        {
            "category":"Insurance",
            "subcategory":"Insurance Agent",
            "type":"Services"
        }
    ],
    "sg:phone":"+44 1472 691542",
    "sg:postcode":"DN35 7HB",
    "sg:province":"Lincolnshire",
    "wof:name":"North Lincs Insurance Brokers",
    "wof:placetype":"venue"
},
  "geometry": {"coordinates":[-0.045402,53.568291],"type":"Point"}
}