{
  "type": "Feature",
  "properties": {
    "addr:full":"Meadow Farm, Corkhill Lane, Kirklington Newark Nottinghamshire NG22 8NW",
    "addr:postcode":"ng22 8nw",
    "addr:street":"Meadow;Corkhill Lane",
    "iso:country":"GB",
    "sg:address":"Meadow Farm, Corkhill Lane, Kirklington",
    "sg:city":"Newark",
    "sg:classifiers":[
        {
            "category":"Farming",
            "subcategory":"Farm",
            "type":"Manufacturing & Wholesale Goods"
        }
    ],
    "sg:phone":"+44 1636 816500",
    "sg:postcode":"NG22 8NW",
    "sg:province":"Nottinghamshire",
    "sg:tags":[
        "mixed",
        "crop"
    ],
    "wof:name":"Meadow Farm",
    "wof:placetype":"venue"
},
  "geometry": {"coordinates":[-0.9899889827,53.1116943359],"type":"Point"}
}