{
  "type": "Feature",
  "properties": {
    "addr:full":"124 Camley Street, Elm Village Industrial Estate London Greater London NW1 0PG",
    "addr:housenumber":"124",
    "addr:postcode":"nw1 0pg",
    "addr:street":"Camley Street Elm Village Industrial Estate",
    "iso:country":"GB",
    "sg:address":"124 Camley Street, Elm Village Industrial Estate",
    "sg:city":"London",
    "sg:classifiers":[
        {
            "category":"Retail",
            "subcategory":"Auto Repair",
            "type":"Services"
        }
    ],
    "sg:phone":"+44 20 7284 2254",
    "sg:postcode":"NW1 0PG",
    "sg:province":"Greater London",
    "sg:tags":[
        "modification",
        "garage"
    ],
    "wof:name":"T & S Coachworks Ltd.",
    "wof:placetype":"venue"
},
  "geometry": {"coordinates":[-0.1316100061,51.5410690308],"type":"Point"}
}