{
  "type": "Feature",
  "properties": {
    "iso:country":"GB",
    "sg:address":"Jobswell Road",
    "sg:city":"Carmarthen",
    "sg:classifiers":[
        {
            "category":"Health Services",
            "subcategory":"Hospital",
            "type":"Services"
        }
    ],
    "sg:phone":"+44 1267 237481",
    "sg:postcode":"SA31 3HB",
    "sg:province":"Carmarthenshire",
    "wof:name":"Pembrokeshire & Derwyn Nhs Trust",
    "wof:placetype":"venue"
},
  "geometry": {"coordinates":[-4.331251,51.859135],"type":"Point"}
}