{
  "type": "Feature",
  "properties": {
    "addr:full":"1 High St Leominster Herefordshire HR6 8LZ",
    "addr:housenumber":"1",
    "addr:postcode":"hr6 8lz",
    "addr:street":"High St",
    "iso:country":"GB",
    "sg:address":"1 High St",
    "sg:city":"Leominster",
    "sg:classifiers":[
        {
            "category":"Arts & Performance",
            "subcategory":"Art Gallery",
            "type":"Entertainment"
        }
    ],
    "sg:phone":"+44 1568 611413",
    "sg:postcode":"HR6 8LZ",
    "sg:province":"Herefordshire",
    "wof:name":"Farmers Gallery",
    "wof:placetype":"venue"
},
  "geometry": {"coordinates":[-2.7387039661,52.2278137207],"type":"Point"}
}