{
  "type": "Feature",
  "properties": {
    "iso:country":"GB",
    "sg:address":"Hutton Conyers",
    "sg:city":"Ripon",
    "sg:classifiers":[
        {
            "category":"Farming",
            "subcategory":"Livestock Farm",
            "type":"Manufacturing & Wholesale Goods"
        }
    ],
    "sg:postcode":"HG4 5NA",
    "sg:province":"North Yorkshire",
    "sg:tags":[
        "others"
    ],
    "wof:name":"B W Barker",
    "wof:placetype":"venue"
},
  "geometry": {"coordinates":[-1.4843699932,54.1684112549],"type":"Point"}
}