{
  "type": "Feature",
  "properties": {
    "addr:full":"58 Buddle La Exeter Devon EX4 1JJ",
    "addr:housenumber":"58",
    "addr:postcode":"ex4 1jj",
    "addr:street":"Buddle La Exeter",
    "iso:country":"GB",
    "sg:address":"58 Buddle La",
    "sg:city":"Exeter",
    "sg:classifiers":[
        {
            "category":"Building & Trades",
            "subcategory":"Construction",
            "type":"Services"
        }
    ],
    "sg:postcode":"EX4 1JJ",
    "sg:province":"Devon",
    "sg:tags":[
        "joiner",
        "carpenter"
    ],
    "wof:name":"Attexe Loft Conversions",
    "wof:placetype":"venue"
},
  "geometry": {"coordinates":[-3.548224,50.717499],"type":"Point"}
}