{
  "type": "Feature",
  "properties": {
    "addr:full":"45 High Street Bruton Somerset BA10 0AW",
    "addr:housenumber":"45",
    "addr:postcode":"ba10 0aw",
    "addr:street":"High Street",
    "iso:country":"GB",
    "sg:address":"45 High Street",
    "sg:city":"Bruton",
    "sg:classifiers":[
        {
            "category":"Bars & Pubs",
            "type":"Food & Drink"
        }
    ],
    "sg:phone":"+44 1749 812211",
    "sg:postcode":"BA10 0AW",
    "sg:province":"Somerset",
    "sg:tags":[
        "pubs",
        "inn"
    ],
    "wof:name":"Castle Inns",
    "wof:placetype":"venue"
},
  "geometry": {"coordinates":[-2.456019,51.111622],"type":"Point"}
}