{
  "type": "Feature",
  "properties": {
    "addr:full":"Edinburgh Castle, Castlehill Edinburgh City of Edinburgh EH1 2YT",
    "addr:postcode":"eh1 2yt",
    "addr:street":"Castlehill",
    "iso:country":"GB",
    "sg:address":"Edinburgh Castle, Castlehill",
    "sg:city":"Edinburgh",
    "sg:classifiers":[
        {
            "category":"Restaurant",
            "type":"Food & Drink"
        }
    ],
    "sg:phone":"+44 131 225 9746",
    "sg:postcode":"EH1 2YT",
    "sg:province":"City of Edinburgh",
    "wof:name":"Edinburgh Castle Cafe",
    "wof:placetype":"venue"
},
  "geometry": {"coordinates":[-3.20149,55.949009],"type":"Point"}
}