{
  "type": "Feature",
  "properties": {
    "iso:country":"GB",
    "sg:address":"51 London Road",
    "sg:city":"Alderley Edge",
    "sg:classifiers":[
        {
            "category":"Building & Trades",
            "subcategory":"Cleaning & Sanitation",
            "type":"Services"
        },
        {
            "category":"Professional",
            "subcategory":"Art Services",
            "type":"Services"
        }
    ],
    "sg:postcode":"SK9 7DY",
    "sg:province":"Cheshire",
    "sg:tags":[
        "commercial",
        "framing"
    ],
    "wof:name":"Alderley Park Executive Contract Services",
    "wof:placetype":"venue"
},
  "geometry": {"coordinates":[-2.236111,53.301601],"type":"Point"}
}