{
  "type": "Feature",
  "properties": {
    "addr:full":"Brook St Nelson Lancashire BB9 9PU",
    "addr:postcode":"bb9 9pu",
    "addr:street":"Brook St",
    "iso:country":"GB",
    "sg:address":"Brook St",
    "sg:city":"Nelson",
    "sg:classifiers":[
        {
            "category":"Home & Garden",
            "subcategory":"Furniture",
            "type":"Retail Goods"
        }
    ],
    "sg:phone":"+44 1282 613031",
    "sg:postcode":"BB9 9PU",
    "sg:province":"Lancashire",
    "sg:tags":[
        "bed",
        "mattress"
    ],
    "wof:name":"Sleep Rest Products Ltd",
    "wof:placetype":"venue"
},
  "geometry": {"coordinates":[-2.208026,53.834743],"type":"Point"}
}