{
  "type": "Feature",
  "properties": {
    "addr:full":"50 Fordham Rd Ely Cambridgeshire CB7 5AH",
    "addr:housenumber":"50",
    "addr:postcode":"cb7 5ah",
    "addr:street":"Fordham Rd",
    "iso:country":"GB",
    "sg:address":"50 Fordham Rd",
    "sg:city":"Ely",
    "sg:classifiers":[
        {
            "category":"Professional",
            "type":"Services"
        }
    ],
    "sg:phone":"+44 1353 722377",
    "sg:postcode":"CB7 5AH",
    "sg:province":"Cambridgeshire",
    "sg:tags":[
        "caterer"
    ],
    "wof:name":"Appertize Ice Cream",
    "wof:placetype":"venue"
},
  "geometry": {"coordinates":[0.346024,52.326851],"type":"Point"}
}