{
  "type": "Feature",
  "properties": {
    "addr:full":"83 Pryor Road Oldbury West Midlands B68 9QJ",
    "addr:housenumber":"83",
    "addr:postcode":"b68 9qj",
    "addr:street":"Pryor Road",
    "iso:country":"GB",
    "sg:address":"83 Pryor Road",
    "sg:city":"Oldbury",
    "sg:classifiers":[
        {
            "category":"Building & Trades",
            "subcategory":"Construction",
            "type":"Services"
        }
    ],
    "sg:phone":"+44 121 552 4578",
    "sg:postcode":"B68 9QJ",
    "sg:province":"West Midlands",
    "sg:tags":[
        "flooring"
    ],
    "wof:name":"T & M Flooring Contractors",
    "wof:placetype":"venue"
},
  "geometry": {"coordinates":[-1.9962249994,52.4846153259],"type":"Point"}
}