{
  "type": "Feature",
  "properties": {
    "addr:full":"21 Manor Road Torquay Devon TQ1 3JX",
    "addr:housenumber":"21",
    "addr:postcode":"tq1 3jx",
    "addr:street":"Manor Road",
    "iso:country":"GB",
    "sg:address":"21 Manor Road",
    "sg:city":"Torquay",
    "sg:classifiers":[
        {
            "category":"Social Services",
            "subcategory":"Retirement Home",
            "type":"Services"
        }
    ],
    "sg:phone":"+44 1803 312759",
    "sg:postcode":"TQ1 3JX",
    "sg:province":"Devon",
    "sg:tags":[
        "rest"
    ],
    "wof:name":"Manor House",
    "wof:placetype":"venue"
},
  "geometry": {"coordinates":[-3.5235590935,50.4801292419],"type":"Point"}
}