{
  "type": "Feature",
  "properties": {
    "iso:country":"GB",
    "sg:address":"Lindfield Rd",
    "sg:city":"Ealing",
    "sg:classifiers":[
        {
            "category":"Place Of Worship",
            "type":"Public Place"
        }
    ],
    "sg:phone":"+44 20 8567 9360",
    "sg:postcode":"W5 1QS",
    "sg:province":"Greater London",
    "wof:name":"Pitshanger Methodist Church",
    "wof:placetype":"venue"
},
  "geometry": {"coordinates":[-0.3126490116,51.527305603],"type":"Point"}
}