{
  "type": "Feature",
  "properties": {
    "addr:full":"Market Hall Leeds West Yorkshire LS2 7HJ",
    "addr:postcode":"ls2 7hj",
    "addr:street":"Leeds West",
    "iso:country":"GB",
    "sg:address":"Market Hall",
    "sg:city":"Leeds",
    "sg:classifiers":[
        {
            "category":"Shopping",
            "subcategory":"Baby Store",
            "type":"Retail Goods"
        }
    ],
    "sg:phone":"+44 113 243 1350",
    "sg:postcode":"LS2 7HJ",
    "sg:province":"West Yorkshire",
    "sg:tags":[
        "babywear",
        "childrens"
    ],
    "wof:name":"Anne Louise Childrens Wear",
    "wof:placetype":"venue"
},
  "geometry": {"coordinates":[-1.53911,53.797218],"type":"Point"}
}