{
  "type": "Feature",
  "properties": {
    "addr:full":"Solent Business Centre, Millbrook Rd West Southampton Hampshire SO15 0HW",
    "addr:postcode":"so15 0hw",
    "addr:street":"Millbrook Rd West",
    "iso:country":"GB",
    "sg:address":"Solent Business Centre, Millbrook Rd West",
    "sg:city":"Southampton",
    "sg:classifiers":[
        {
            "category":"Autos & Motor Vehicles",
            "subcategory":"Auto Supplies",
            "type":"Retail Goods"
        }
    ],
    "sg:phone":"+44 23 8051 3009",
    "sg:postcode":"SO15 0HW",
    "sg:province":"Hampshire",
    "sg:tags":[
        "car",
        "component"
    ],
    "wof:name":"P.S.J Autolec Services",
    "wof:placetype":"venue"
},
  "geometry": {"coordinates":[-1.4073189497,50.9099388123],"type":"Point"}
}