{
  "type": "Feature",
  "properties": {
    "iso:country":"GB",
    "sg:address":"Marsland Road",
    "sg:city":"Sale",
    "sg:classifiers":[
        {
            "category":"Autos & Motor Vehicles",
            "subcategory":"Fuel & Gas Station",
            "type":"Retail Goods"
        }
    ],
    "sg:phone":"+44 161 972 0300",
    "sg:postcode":"M33 3NA",
    "sg:province":"Cheshire",
    "sg:tags":[
        "petrol",
        "filling"
    ],
    "wof:name":"Marsland Road Service Station",
    "wof:placetype":"venue"
},
  "geometry": {"coordinates":[-2.304211,53.419655],"type":"Point"}
}