{
  "type": "Feature",
  "properties": {
    "iso:country":"GB",
    "sg:address":"4 Broad Street, Congresbury",
    "sg:city":"Bristol",
    "sg:classifiers":[
        {
            "category":"Personal",
            "subcategory":"Beauty Salon",
            "type":"Services"
        }
    ],
    "sg:phone":"+44 1934 833690",
    "sg:postcode":"BS49 5DG",
    "sg:province":"Somerset",
    "sg:tags":[
        "unisex",
        "hairdresser"
    ],
    "wof:name":"Broad Street Hair Co.",
    "wof:placetype":"venue"
},
  "geometry": {"coordinates":[-2.8103199005,51.3701286316],"type":"Point"}
}