{
  "type": "Feature",
  "properties": {
    "addr:full":"The Gallery Kitchen And Bedroom, Studio, Hadfield Road Cardiff Cardiff CF11 8AQ",
    "addr:postcode":"cf11 8aq",
    "addr:street":"Hadfield Road",
    "iso:country":"GB",
    "sg:address":"The Gallery Kitchen And Bedroom, Studio, Hadfield Road",
    "sg:city":"Cardiff",
    "sg:classifiers":[
        {
            "category":"Home & Garden",
            "subcategory":"Home Furnishings",
            "type":"Retail Goods"
        }
    ],
    "sg:phone":"+44 29 2037 3268",
    "sg:postcode":"CF11 8AQ",
    "sg:province":"Cardiff",
    "sg:tags":[
        "furnishers",
        "planner",
        "bedroom"
    ],
    "wof:name":"Exclusive Bedroom Centre",
    "wof:placetype":"venue"
},
  "geometry": {"coordinates":[-3.2072799206,51.4694786072],"type":"Point"}
}