{
  "type": "Feature",
  "properties": {
    "iso:country":"GB",
    "sg:address":"Scott Ho, 5 Whitsome Village",
    "sg:city":"Duns",
    "sg:classifiers":[
        {
            "category":"Professional",
            "type":"Services"
        }
    ],
    "sg:postcode":"TD11 3NB",
    "sg:province":"East Lothian",
    "sg:tags":[
        "aircraft",
        "maintenance"
    ],
    "wof:name":"Is-Aviation Ltd",
    "wof:placetype":"venue"
},
  "geometry": {"coordinates":[-2.341107,55.775776],"type":"Point"}
}