{
  "type": "Feature",
  "properties": {
    "iso:country":"GB",
    "sg:address":"49 High St",
    "sg:city":"Pershore",
    "sg:classifiers":[
        {
            "category":"Professional",
            "subcategory":"Employment Agencies",
            "type":"Services"
        }
    ],
    "sg:phone":"+44 1386 556899",
    "sg:postcode":"WR10 1EU",
    "sg:province":"Worcestershire",
    "sg:tags":[
        "consultant"
    ],
    "wof:name":"Transport Support Services",
    "wof:placetype":"venue"
},
  "geometry": {"coordinates":[-2.0757379532,52.1119232178],"type":"Point"}
}