{
  "type": "Feature",
  "properties": {
    "addr:full":"Park House Farm, Staveley Kendal Cumbria LA8 9QY",
    "addr:housenumber":"staveley",
    "addr:postcode":"la8 9qy",
    "addr:street":"Kendal",
    "iso:country":"GB",
    "sg:address":"Park House Farm, Staveley",
    "sg:city":"Kendal",
    "sg:classifiers":[
        {
            "category":"Farming",
            "subcategory":"Livestock Farm",
            "type":"Manufacturing & Wholesale Goods"
        }
    ],
    "sg:phone":"+44 1539 821200",
    "sg:postcode":"LA8 9QY",
    "sg:province":"Cumbria",
    "sg:tags":[
        "others"
    ],
    "wof:name":"T E Wilson",
    "wof:placetype":"venue"
},
  "geometry": {"coordinates":[-2.819247,54.372185],"type":"Point"}
}