{
  "type": "Feature",
  "properties": {
    "addr:full":"100 Mickleham Road Orpington Kent BR5 2TL",
    "addr:housenumber":"100",
    "addr:postcode":"br5 2tl",
    "addr:street":"Mickleham Road",
    "iso:country":"GB",
    "sg:address":"100 Mickleham Road",
    "sg:city":"Orpington",
    "sg:classifiers":[
        {
            "category":"Health Services",
            "subcategory":"Nursing And Care Facility",
            "type":"Services"
        },
        {
            "category":"Social Services",
            "subcategory":"Retirement Home",
            "type":"Services"
        }
    ],
    "sg:phone":"+44 20 8300 0108",
    "sg:postcode":"BR5 2TL",
    "sg:province":"Kent",
    "sg:tags":[
        "residential"
    ],
    "wof:name":"Bellgrove Residential Home",
    "wof:placetype":"venue"
},
  "geometry": {"coordinates":[0.103183,51.404202],"type":"Point"}
}