{
  "type": "Feature",
  "properties": {
    "addr:full":"Unit 505, Eskdale Road Wokingham Berkshire RG41 5TU",
    "addr:housenumber":"505",
    "addr:postcode":"rg41 5tu",
    "addr:street":"Eskdale Road",
    "iso:country":"GB",
    "sg:address":"Unit 505, Eskdale Road",
    "sg:city":"Wokingham",
    "sg:classifiers":[
        {
            "category":"Manufacturing",
            "subcategory":"Electronics",
            "type":"Manufacturing & Wholesale Goods"
        },
        {
            "category":"Professional",
            "subcategory":"Computer Services",
            "type":"Services"
        }
    ],
    "sg:phone":"+44 20 7300 7000",
    "sg:postcode":"RG41 5TU",
    "sg:province":"Berkshire",
    "sg:tags":[
        "mnfr",
        "component",
        "system",
        "electronic",
        "software"
    ],
    "wof:name":"Arizona Microchip Technology Ltd.",
    "wof:placetype":"venue"
},
  "geometry": {"coordinates":[-0.883379,51.438564],"type":"Point"}
}