{
  "type": "Feature",
  "properties": {
    "addr:full":"The Gatehouse, Priory Wharf Birkenhead Merseyside L41 5LB",
    "addr:postcode":"l41 5lb",
    "addr:street":"Priory Wharf",
    "iso:country":"GB",
    "sg:address":"The Gatehouse, Priory Wharf",
    "sg:city":"Birkenhead",
    "sg:classifiers":[
        {
            "category":"Professional",
            "subcategory":"Management & Consulting",
            "type":"Services"
        }
    ],
    "sg:phone":"+44 151 650 0821",
    "sg:postcode":"L41 5LB",
    "sg:province":"Merseyside",
    "sg:tags":[
        "consultant",
        "business"
    ],
    "wof:name":"Priory Wharf Management Co",
    "wof:placetype":"venue"
},
  "geometry": {"coordinates":[-3.0254900455,53.3925590515],"type":"Point"}
}