{
  "type": "Feature",
  "properties": {
    "iso:country":"GB",
    "sg:address":"Corn Exhange Market Place, Hadleigh",
    "sg:city":"Ipswich",
    "sg:classifiers":[
        {
            "category":"Government",
            "subcategory":"Office",
            "type":"Public Place"
        }
    ],
    "sg:phone":"+44 1473 823948",
    "sg:postcode":"IP7 5DN",
    "sg:province":"Suffolk",
    "sg:tags":[
        "local"
    ],
    "wof:name":"Suffolk County Council",
    "wof:placetype":"venue"
},
  "geometry": {"coordinates":[0.9528999925,52.0448646545],"type":"Point"}
}