{
  "type": "Feature",
  "properties": {
    "addr:full":"34 Deerhill, Dechmont Broxburn City of Edinburgh EH52 6LY",
    "addr:housenumber":"34",
    "addr:postcode":"eh52 6ly",
    "addr:street":"Deerhill Dechmont",
    "iso:country":"GB",
    "sg:address":"34 Deerhill, Dechmont",
    "sg:city":"Broxburn",
    "sg:classifiers":[
        {
            "category":"Shopping",
            "subcategory":"Stationery & Office Supplies",
            "type":"Retail Goods"
        }
    ],
    "sg:phone":"+44 1506 811432",
    "sg:postcode":"EH52 6LY",
    "sg:province":"City of Edinburgh",
    "sg:tags":[
        "recording",
        "machine",
        "time"
    ],
    "wof:name":"John Gemmell",
    "wof:placetype":"venue"
},
  "geometry": {"coordinates":[-3.5375030041,55.9204597473],"type":"Point"}
}