{
  "type": "Feature",
  "properties": {
    "addr:full":"50 Tintagel Rd Orpington Kent BR5 4LQ",
    "addr:housenumber":"50",
    "addr:postcode":"br5 4lq",
    "addr:street":"Tintagel Rd",
    "iso:country":"GB",
    "sg:address":"50 Tintagel Rd",
    "sg:city":"Orpington",
    "sg:classifiers":[
        {
            "category":"Professional",
            "subcategory":"Accounting & Tax Preparation",
            "type":"Services"
        }
    ],
    "sg:phone":"+44 1689 828711",
    "sg:postcode":"BR5 4LQ",
    "sg:province":"Kent",
    "sg:tags":[
        "accountant"
    ],
    "wof:name":"R F Miller",
    "wof:placetype":"venue"
},
  "geometry": {"coordinates":[0.1155349985,51.3735809326],"type":"Point"}
}