{
  "type": "Feature",
  "properties": {
    "addr:full":"118 Beech Avenue, Newton Mearns Glasgow East Ayrshire G77 5BL",
    "addr:housenumber":"118",
    "addr:postcode":"g77 5bl",
    "addr:street":"Beech Avenue",
    "iso:country":"GB",
    "sg:address":"118 Beech Avenue, Newton Mearns",
    "sg:city":"Glasgow",
    "sg:classifiers":[
        {
            "category":"Professional",
            "subcategory":"Management & Consulting",
            "type":"Services"
        }
    ],
    "sg:phone":"+44 141 639 7477",
    "sg:postcode":"G77 5BL",
    "sg:province":"East Ayrshire",
    "sg:tags":[
        "consultant",
        "specialist"
    ],
    "wof:name":"Beauty for All Seasons",
    "wof:placetype":"venue"
},
  "geometry": {"coordinates":[-4.33006,55.771397],"type":"Point"}
}