{
  "type": "Feature",
  "properties": {
    "addr:full":"Kincardine Road, Torphins Banchory Aberdeen City AB31 4HH",
    "addr:postcode":"ab31 4hh",
    "addr:street":"Kincardine Road",
    "iso:country":"GB",
    "sg:address":"Kincardine Road, Torphins",
    "sg:city":"Banchory",
    "sg:classifiers":[
        {
            "category":"Building & Trades",
            "subcategory":"Construction",
            "type":"Services"
        }
    ],
    "sg:postcode":"AB31 4HH",
    "sg:province":"Aberdeen City",
    "sg:tags":[
        "builder"
    ],
    "wof:name":"P R Leslie",
    "wof:placetype":"venue"
},
  "geometry": {"coordinates":[-2.6231338978,57.1046714783],"type":"Point"}
}