{
  "type": "Feature",
  "properties": {
    "addr:full":"Unit 6 Liberty Centre Wembley Greater London HA0 1TX",
    "addr:housenumber":"unit 6;centre",
    "addr:postcode":"ha0 1tx",
    "addr:street":"Liberty",
    "iso:country":"GB",
    "sg:address":"Unit 6 Liberty Centre",
    "sg:city":"Wembley",
    "sg:classifiers":[
        {
            "category":"Professional",
            "subcategory":"Business Services",
            "type":"Services"
        }
    ],
    "sg:phone":"+44 20 8900 1300",
    "sg:postcode":"HA0 1TX",
    "sg:province":"Greater London",
    "sg:tags":[
        "import",
        "export",
        "agent"
    ],
    "wof:name":"Ballward Ltd.",
    "wof:placetype":"venue"
},
  "geometry": {"coordinates":[-0.28928,51.5406],"type":"Point"}
}