{
  "type": "Feature",
  "properties": {
    "iso:country":"GB",
    "sg:address":"276 Milkwood Road",
    "sg:city":"London",
    "sg:classifiers":[
        {
            "category":"Home & Garden",
            "subcategory":"Carpets & Floor Coverings",
            "type":"Retail Goods"
        }
    ],
    "sg:phone":"+44 20 7738 4601",
    "sg:postcode":"SE24 0EZ",
    "sg:province":"Greater London",
    "sg:tags":[
        "carpets",
        "rug",
        "matting"
    ],
    "wof:name":"R P E Flooring",
    "wof:placetype":"venue"
},
  "geometry": {"coordinates":[-0.103245,51.455185],"type":"Point"}
}