{
  "type": "Feature",
  "properties": {
    "addr:full":"Special Needs Early Years Support Team, Wood End Rd Wolverhampton Staffordshire WV11 1YG",
    "addr:postcode":"wv11 1yg",
    "addr:street":"Wood End Rd",
    "iso:country":"GB",
    "sg:address":"Special Needs Early Years Support Team, Wood End Rd",
    "sg:city":"Wolverhampton",
    "sg:classifiers":[
        {
            "category":"Government",
            "subcategory":"Office",
            "type":"Public Place"
        }
    ],
    "sg:phone":"+44 1902 558406",
    "sg:postcode":"WV11 1YG",
    "sg:province":"Staffordshire",
    "sg:tags":[
        "local"
    ],
    "wof:name":"Wolverhampton Borough Council",
    "wof:placetype":"venue"
},
  "geometry": {"coordinates":[-2.121669,52.58865],"type":"Point"}
}