{
  "type": "Feature",
  "properties": {
    "iso:country":"GB",
    "sg:address":"Path House, Nether Street",
    "sg:city":"Kirkcaldy",
    "sg:classifiers":[
        {
            "category":"Health Services",
            "subcategory":"Doctor",
            "type":"Services"
        },
        {
            "category":"Health Services",
            "subcategory":"Clinic",
            "type":"Services"
        }
    ],
    "sg:phone":"+44 1592 644533",
    "sg:postcode":"KY1 2PG",
    "sg:province":"Fife",
    "sg:tags":[
        "nh",
        "practitioners"
    ],
    "wof:name":"Path House Medical Practice",
    "wof:placetype":"venue"
},
  "geometry": {"coordinates":[-3.142694,56.120911],"type":"Point"}
}