{
  "type": "Feature",
  "properties": {
    "iso:country":"GB",
    "sg:address":"Stanbridge Pk, Staplefield La, Staplefield",
    "sg:city":"Haywards Heath",
    "sg:classifiers":[
        {
            "category":"Shopping",
            "subcategory":"Books",
            "type":"Retail Goods"
        }
    ],
    "sg:postcode":"RH17 6AS",
    "sg:province":"East Sussex",
    "wof:name":"Openeye Publishing",
    "wof:placetype":"venue"
},
  "geometry": {"coordinates":[-0.082399,51.044895],"type":"Point"}
}