{
  "type": "Feature",
  "properties": {
    "iso:country":"GB",
    "sg:address":"564 Warwick Rd",
    "sg:city":"Birmingham",
    "sg:classifiers":[
        {
            "category":"Professional",
            "subcategory":"Detective & Security Services",
            "type":"Services"
        }
    ],
    "sg:phone":"+44 121 706 6511",
    "sg:postcode":"B11 2HR",
    "sg:province":"West Midlands",
    "wof:name":"Crownworld Ltd",
    "wof:placetype":"venue"
},
  "geometry": {"coordinates":[-1.849182,52.453403],"type":"Point"}
}