{
  "type": "Feature",
  "properties": {
    "addr:full":"230-232 Ellerburn Avenue Hull East Riding of Yorkshire HU6 9RR",
    "addr:housenumber":"230-232",
    "addr:postcode":"hu6 9rr",
    "addr:street":"Ellerburn Avenue",
    "iso:country":"GB",
    "sg:address":"230-232 Ellerburn Avenue",
    "sg:city":"Hull",
    "sg:classifiers":[
        {
            "category":"Shopping",
            "subcategory":"News",
            "type":"Retail Goods"
        }
    ],
    "sg:phone":"+44 1482 801129",
    "sg:postcode":"HU6 9RR",
    "sg:province":"East Riding of Yorkshire",
    "sg:tags":[
        "newsagent"
    ],
    "wof:name":"United News Shops",
    "wof:placetype":"venue"
},
  "geometry": {"coordinates":[-0.377524,53.788723],"type":"Point"}
}