{
  "type": "Feature",
  "properties": {
    "addr:full":"11 St Aldates Gloucester Gloucestershire GL1 1RP",
    "addr:housenumber":"11",
    "addr:postcode":"gl1 1rp",
    "addr:street":"St Aldates",
    "iso:country":"GB",
    "sg:address":"11 St Aldates",
    "sg:city":"Gloucester",
    "sg:classifiers":[
        {
            "category":"Professional",
            "subcategory":"Printing & Photocopies",
            "type":"Services"
        }
    ],
    "sg:phone":"+44 1452 502024",
    "sg:postcode":"GL1 1RP",
    "sg:province":"Gloucestershire",
    "sg:tags":[
        "plate",
        "lithographic",
        "maker"
    ],
    "wof:name":"Gloucestershire Cobblers",
    "wof:placetype":"venue"
},
  "geometry": {"coordinates":[-2.2435460091,51.8663330078],"type":"Point"}
}