{
  "type": "Feature",
  "properties": {
    "addr:full":"23 Ravenscroft Avenue Golders Green Greater London NW11 8BH",
    "addr:housenumber":"23",
    "addr:postcode":"nw11 8bh",
    "addr:street":"Ravenscroft Avenue",
    "iso:country":"GB",
    "sg:address":"23 Ravenscroft Avenue",
    "sg:city":"Golders Green",
    "sg:classifiers":[
        {
            "category":"Food & Beverages",
            "subcategory":"Supermarket",
            "type":"Retail Goods"
        }
    ],
    "sg:phone":"+44 20 8905 5700",
    "sg:postcode":"NW11 8BH",
    "sg:province":"Greater London",
    "sg:tags":[
        "frozen"
    ],
    "wof:name":"T Choithram & Son",
    "wof:placetype":"venue"
},
  "geometry": {"coordinates":[-0.200867,51.575912],"type":"Point"}
}