{
  "type": "Feature",
  "properties": {
    "addr:full":"11 Hardinge St Whitechapel Greater London E1 0DZ",
    "addr:housenumber":"11",
    "addr:postcode":"e1 0dz",
    "addr:street":"Hardinge St",
    "iso:country":"GB",
    "sg:address":"11 Hardinge St",
    "sg:city":"Whitechapel",
    "sg:classifiers":[
        {
            "category":"Shopping",
            "subcategory":"Photographic Equipment",
            "type":"Retail Goods"
        }
    ],
    "sg:phone":"+44 20 7790 7785",
    "sg:postcode":"E1 0DZ",
    "sg:province":"Greater London",
    "wof:name":"Family Photo's",
    "wof:placetype":"venue"
},
  "geometry": {"coordinates":[-0.0504940003,51.5115318298],"type":"Point"}
}