{
  "type": "Feature",
  "properties": {
    "iso:country":"GB",
    "sg:address":"34 High St",
    "sg:city":"Solihull",
    "sg:classifiers":[
        {
            "category":"Professional",
            "subcategory":"Employment Agencies",
            "type":"Services"
        }
    ],
    "sg:phone":"+44 1675 443727",
    "sg:postcode":"B92 0AA",
    "sg:province":"West Midlands",
    "sg:tags":[
        "consultant"
    ],
    "wof:name":"Action Recruitment Europe",
    "wof:placetype":"venue"
},
  "geometry": {"coordinates":[-1.702335,52.425541],"type":"Point"}
}