{
  "type": "Feature",
  "properties": {
    "iso:country":"GB",
    "sg:address":"12 Fernie Brae, Gardenstown",
    "sg:city":"Banff",
    "sg:classifiers":[
        {
            "category":"Building & Trades",
            "subcategory":"Construction",
            "type":"Services"
        }
    ],
    "sg:phone":"+44 1261 851319",
    "sg:postcode":"AB45 3YL",
    "sg:province":"Aberdeenshire",
    "sg:tags":[
        "joiner",
        "carpenter"
    ],
    "wof:name":"William.A West",
    "wof:placetype":"venue"
},
  "geometry": {"coordinates":[-2.3386359215,57.6690063477],"type":"Point"}
}