{
  "type": "Feature",
  "properties": {
    "iso:country":"GB",
    "sg:address":"Lower Farm, Langford",
    "sg:city":"Lechlade",
    "sg:classifiers":[
        {
            "category":"Farming",
            "subcategory":"Livestock Farm",
            "type":"Manufacturing & Wholesale Goods"
        }
    ],
    "sg:phone":"+44 1367 860038",
    "sg:postcode":"GL7 3LQ",
    "sg:province":"Gloucestershire",
    "sg:tags":[
        "others"
    ],
    "wof:name":"R N T Farming Co. Ltd.",
    "wof:placetype":"venue"
},
  "geometry": {"coordinates":[-1.6919089556,51.6940765381],"type":"Point"}
}