{
  "type": "Feature",
  "properties": {
    "addr:full":"74 George St Hove East Sussex BN3 3YE",
    "addr:housenumber":"74",
    "addr:postcode":"bn3 3ye",
    "addr:street":"George St",
    "iso:country":"GB",
    "sg:address":"74 George St",
    "sg:city":"Hove",
    "sg:classifiers":[
        {
            "category":"Food & Beverages",
            "subcategory":"Fruits & Vegetables",
            "type":"Retail Goods"
        }
    ],
    "sg:postcode":"BN3 3YE",
    "sg:province":"East Sussex",
    "sg:tags":[
        "greengrocer"
    ],
    "wof:name":"Jenkins,Jeff,",
    "wof:placetype":"venue"
},
  "geometry": {"coordinates":[-0.1733479947,50.8303871155],"type":"Point"}
}