{
  "type": "Feature",
  "properties": {
    "addr:full":"6 Bishopstone Aylesbury Buckinghamshire HP17 8SE",
    "addr:housenumber":"6",
    "addr:postcode":"hp17 8se",
    "addr:street":"Bishopstone Aylesbury",
    "iso:country":"GB",
    "sg:address":"6 Bishopstone",
    "sg:city":"Aylesbury",
    "sg:classifiers":[
        {
            "category":"Professional",
            "type":"Services"
        }
    ],
    "sg:phone":"+44 1296 748711",
    "sg:postcode":"HP17 8SE",
    "sg:province":"Buckinghamshire",
    "sg:tags":[
        "repair",
        "tech",
        "maintenance"
    ],
    "wof:name":"Intec Computer Systems",
    "wof:placetype":"venue"
},
  "geometry": {"coordinates":[-0.83894,51.788116],"type":"Point"}
}