{
  "type": "Feature",
  "properties": {
    "addr:full":"83 Sandford Rd Winscombe Somerset BS25 1JJ",
    "addr:housenumber":"83",
    "addr:postcode":"bs25 1jj",
    "addr:street":"Sandford Rd",
    "iso:country":"GB",
    "sg:address":"83 Sandford Rd",
    "sg:city":"Winscombe",
    "sg:classifiers":[
        {
            "category":"Professional",
            "subcategory":"Engineering",
            "type":"Services"
        }
    ],
    "sg:phone":"+44 1934 844253",
    "sg:postcode":"BS25 1JJ",
    "sg:province":"Somerset",
    "sg:tags":[
        "contractor",
        "electrical",
        "engineer"
    ],
    "wof:name":"K O Attwood",
    "wof:placetype":"venue"
},
  "geometry": {"coordinates":[-2.8361721039,51.3237342834],"type":"Point"}
}