{
  "type": "Feature",
  "properties": {
    "addr:full":"Unit 7 West Rd Harlow Essex CM20 2BU",
    "addr:housenumber":"unit 7",
    "addr:postcode":"cm20 2bu",
    "addr:street":"West Rd",
    "iso:country":"GB",
    "sg:address":"Unit 7 West Rd",
    "sg:city":"Harlow",
    "sg:classifiers":[
        {
            "category":"Professional",
            "subcategory":"Advertising",
            "type":"Services"
        }
    ],
    "sg:phone":"+44 1279 625625",
    "sg:postcode":"CM20 2BU",
    "sg:province":"Essex",
    "sg:tags":[
        "mail",
        "direct"
    ],
    "wof:name":"Capital Direct Mail PLC",
    "wof:placetype":"venue"
},
  "geometry": {"coordinates":[0.1166749969,51.7839164734],"type":"Point"}
}