{
  "type": "Feature",
  "properties": {
    "iso:country":"GB",
    "sg:address":"Wern Works, Briton Ferry",
    "sg:city":"Neath",
    "sg:classifiers":[
        {
            "category":"Manufacturing",
            "subcategory":"Metals",
            "type":"Manufacturing & Wholesale Goods"
        }
    ],
    "sg:postcode":"SA11 2JX",
    "sg:province":"Neath Port Talbot",
    "sg:tags":[
        "steel",
        "mnfrs"
    ],
    "wof:name":"Stelax (U K) Ltd.",
    "wof:placetype":"venue"
},
  "geometry": {"coordinates":[-3.817644,51.635368],"type":"Point"}
}