{
  "type": "Feature",
  "properties": {
    "iso:country":"GB",
    "sg:address":"First Floor Carlton Ho, Hemnall St",
    "sg:city":"Epping",
    "sg:classifiers":[
        {
            "category":"Freight",
            "type":"Transportation"
        }
    ],
    "sg:phone":"+44 1992 561762",
    "sg:postcode":"CM16 4NQ",
    "sg:province":"Essex",
    "sg:tags":[
        "shipping"
    ],
    "wof:name":"Clarehaven Ltd",
    "wof:placetype":"venue"
},
  "geometry": {"coordinates":[0.1116589978,51.6992988586],"type":"Point"}
}