{
  "type": "Feature",
  "properties": {
    "iso:country":"GB",
    "sg:address":"26 Hamlet Court Road",
    "sg:city":"Westcliff-on-sea",
    "sg:classifiers":[
        {
            "category":"Banks & Credit Unions",
            "subcategory":"Financial Services",
            "type":"Services"
        }
    ],
    "sg:phone":"+44 1702 347734",
    "sg:postcode":"SS0 7LX",
    "sg:province":"Essex",
    "sg:tags":[
        "consultant"
    ],
    "wof:name":"Essex Financial Planners",
    "wof:placetype":"venue"
},
  "geometry": {"coordinates":[0.692824,51.537834],"type":"Point"}
}