{
  "type": "Feature",
  "properties": {
    "addr:full":"Orchard St, Kempston Bedford Bedfordshire MK42 7LJ",
    "addr:postcode":"mk42 7lj",
    "addr:street":"Orchard St",
    "iso:country":"GB",
    "sg:address":"Orchard St, Kempston",
    "sg:city":"Bedford",
    "sg:classifiers":[
        {
            "category":"Education",
            "subcategory":"School",
            "type":"Public Place"
        }
    ],
    "sg:phone":"+44 1234 306000",
    "sg:postcode":"MK42 7LJ",
    "sg:province":"Bedfordshire",
    "sg:tags":[
        "local",
        "authority"
    ],
    "wof:name":"Springfield Lower School",
    "wof:placetype":"venue"
},
  "geometry": {"coordinates":[-0.5050669909,52.1148414612],"type":"Point"}
}