{
  "type": "Feature",
  "properties": {
    "addr:full":"Westfield Wagon Works, 322 Moss Bay Road Workington Cumbria CA14 5DR",
    "addr:housenumber":"322",
    "addr:postcode":"ca14 5dr",
    "addr:street":"Moss Bay Road",
    "iso:country":"GB",
    "sg:address":"Westfield Wagon Works, 322 Moss Bay Road",
    "sg:city":"Workington",
    "sg:classifiers":[
        {
            "category":"Retail",
            "subcategory":"Auto Repair",
            "type":"Services"
        }
    ],
    "sg:phone":"+44 1900 61220",
    "sg:postcode":"CA14 5DR",
    "sg:province":"Cumbria",
    "sg:tags":[
        "body",
        "car"
    ],
    "wof:name":"Irving Engineering",
    "wof:placetype":"venue"
},
  "geometry": {"coordinates":[-3.550002,54.638981],"type":"Point"}
}