{
  "type": "Feature",
  "properties": {
    "iso:country":"GB",
    "sg:address":"345 Garratt La",
    "sg:city":"London",
    "sg:classifiers":[
        {
            "category":"Professional",
            "subcategory":"Art Services",
            "type":"Services"
        }
    ],
    "sg:postcode":"SW18 4DX",
    "sg:province":"Greater London",
    "sg:tags":[
        "framing"
    ],
    "wof:name":"White House Gallery",
    "wof:placetype":"venue"
},
  "geometry": {"coordinates":[-0.18917,51.44603],"type":"Point"}
}