{
  "type": "Feature",
  "properties": {
    "addr:full":"260 Rotherwood Avenue Glasgow Glasgow City G13 2AY",
    "addr:housenumber":"260",
    "addr:postcode":"g13 2ay",
    "addr:street":"Rotherwood Avenue",
    "iso:country":"GB",
    "sg:address":"260 Rotherwood Avenue",
    "sg:city":"Glasgow",
    "sg:classifiers":[
        {
            "category":"Farming",
            "subcategory":"Nursery",
            "type":"Manufacturing & Wholesale Goods"
        },
        {
            "category":"Education",
            "subcategory":"Preschool",
            "type":"Public Place"
        }
    ],
    "sg:phone":"+44 141 958 0555",
    "sg:postcode":"G13 2AY",
    "sg:province":"Glasgow City",
    "sg:tags":[
        "school",
        "creche"
    ],
    "wof:name":"Step by Step Nursery",
    "wof:placetype":"venue"
},
  "geometry": {"coordinates":[-4.34749,55.905361],"type":"Point"}
}