{
  "type": "Feature",
  "properties": {
    "iso:country":"GB",
    "sg:address":"Llandogo",
    "sg:city":"Monmouth",
    "sg:classifiers":[
        {
            "category":"Health Services",
            "subcategory":"Nursing And Care Facility",
            "type":"Services"
        }
    ],
    "sg:phone":"+44 1594 530581",
    "sg:postcode":"NP25 4TP",
    "sg:province":"Gloucestershire",
    "sg:tags":[
        "home"
    ],
    "wof:name":"Priory Nursing & Residential Home",
    "wof:placetype":"venue"
},
  "geometry": {"coordinates":[-2.6876709461,51.7337913513],"type":"Point"}
}