{
  "type": "Feature",
  "properties": {
    "iso:country":"GB",
    "sg:address":"Ollerton Rd, Tuxford",
    "sg:city":"Newark",
    "sg:classifiers":[
        {
            "category":"Communications",
            "subcategory":"Film & Video Production",
            "type":"Services"
        }
    ],
    "sg:phone":"+44 1777 872364",
    "sg:postcode":"NG22 0PQ",
    "sg:province":"Nottinghamshire",
    "sg:tags":[
        "recording",
        "studio"
    ],
    "wof:name":"Fineline Studio",
    "wof:placetype":"venue"
},
  "geometry": {"coordinates":[-0.9000679851,53.2315483093],"type":"Point"}
}