{
  "type": "Feature",
  "properties": {
    "iso:country":"GB",
    "sg:address":"Nantybeinon, Llandeilo'r Fan",
    "sg:city":"Brecon",
    "sg:classifiers":[
        {
            "category":"Farming",
            "subcategory":"Livestock Farm",
            "type":"Manufacturing & Wholesale Goods"
        },
        {
            "category":"Farming",
            "subcategory":"Farm",
            "type":"Manufacturing & Wholesale Goods"
        }
    ],
    "sg:phone":"+44 1874 636482",
    "sg:postcode":"LD3 8UD",
    "sg:province":"Powys",
    "sg:tags":[
        "mixed",
        "crop",
        "others"
    ],
    "wof:name":"R I Phillips",
    "wof:placetype":"venue"
},
  "geometry": {"coordinates":[-3.59984,51.994179],"type":"Point"}
}