{
  "type": "Feature",
  "properties": {
    "addr:full":"26 High Street Halesowen West Midlands B63 3BB",
    "addr:housenumber":"26",
    "addr:postcode":"b63 3bb",
    "addr:street":"High Street",
    "iso:country":"GB",
    "sg:address":"26 High Street",
    "sg:city":"Halesowen",
    "sg:classifiers":[
        {
            "category":"Insurance",
            "subcategory":"Insurance Agent",
            "type":"Services"
        }
    ],
    "sg:phone":"+44 121 585 9596",
    "sg:postcode":"B63 3BB",
    "sg:province":"West Midlands",
    "sg:tags":[
        "broker"
    ],
    "wof:name":"S Turner & Associates Ltd.",
    "wof:placetype":"venue"
},
  "geometry": {"coordinates":[-2.051494,52.450546],"type":"Point"}
}