{
  "type": "Feature",
  "properties": {
    "addr:full":"Grimes Gate, Diseworth Derby Leicestershire DE74 2QD",
    "addr:postcode":"de74 2qd",
    "addr:street":"Grimes Gate",
    "iso:country":"GB",
    "sg:address":"Grimes Gate, Diseworth",
    "sg:city":"Derby",
    "sg:classifiers":[
        {
            "category":"Education",
            "subcategory":"School",
            "type":"Public Place"
        }
    ],
    "sg:phone":"+44 1332 810208",
    "sg:postcode":"DE74 2QD",
    "sg:province":"Leicestershire",
    "sg:tags":[
        "local",
        "authority"
    ],
    "wof:name":"Diseworth C Of E Primary School",
    "wof:placetype":"venue"
},
  "geometry": {"coordinates":[-1.3330440521,52.8141098022],"type":"Point"}
}