{
  "type": "Feature",
  "properties": {
    "iso:country":"GB",
    "sg:address":"5a-5b Forest Rd, Garden La",
    "sg:city":"South Shields",
    "sg:classifiers":[
        {
            "category":"Home & Garden",
            "subcategory":"Building Materials",
            "type":"Retail Goods"
        }
    ],
    "sg:postcode":"NE33 1PT",
    "sg:province":"Tyne and Wear",
    "sg:tags":[
        "shutter",
        "door"
    ],
    "wof:name":"Allied Door Services",
    "wof:placetype":"venue"
},
  "geometry": {"coordinates":[-1.433285,54.995918],"type":"Point"}
}