{
  "type": "Feature",
  "properties": {
    "iso:country":"GB",
    "sg:address":"Unit 4 Hambledon House Broad Street",
    "sg:city":"Wolverhampton",
    "sg:classifiers":[
        {
            "category":"Government",
            "subcategory":"Office",
            "type":"Public Place"
        }
    ],
    "sg:phone":"+44 1902 710896",
    "sg:postcode":"WV1 1JA",
    "sg:province":"West Midlands",
    "sg:tags":[
        "local"
    ],
    "wof:name":"Sam Sharp Project",
    "wof:placetype":"venue"
},
  "geometry": {"coordinates":[-2.124759,52.587494],"type":"Point"}
}