{
  "type": "Feature",
  "properties": {
    "iso:country":"GB",
    "sg:address":"Evenwood Lane",
    "sg:city":"Bishop Auckland",
    "sg:classifiers":[
        {
            "category":"Manufacturing",
            "subcategory":"Metals",
            "type":"Manufacturing & Wholesale Goods"
        }
    ],
    "sg:postcode":"DL14 9NJ",
    "sg:province":"Durham",
    "sg:tags":[
        "work",
        "sheet"
    ],
    "wof:name":"Evenwood Engineering Ltd.",
    "wof:placetype":"venue"
},
  "geometry": {"coordinates":[-1.7596939802,54.6178894043],"type":"Point"}
}