{
  "type": "Feature",
  "properties": {
    "addr:full":"1-2 Bridewell Lane Bath Bath and North East Somerset BA1 1EA",
    "addr:housenumber":"1-2",
    "addr:postcode":"ba1 1ea",
    "addr:street":"Bridewell Lane",
    "iso:country":"GB",
    "sg:address":"1-2 Bridewell Lane",
    "sg:city":"Bath",
    "sg:classifiers":[
        {
            "category":"Organizations",
            "subcategory":"Non-profit Organization",
            "type":"Services"
        }
    ],
    "sg:phone":"+44 1225 444347",
    "sg:postcode":"BA1 1EA",
    "sg:province":"Bath and North East Somerset",
    "sg:tags":[
        "organisation",
        "voluntary",
        "charity"
    ],
    "wof:name":"Terance Higgins Trust",
    "wof:placetype":"venue"
},
  "geometry": {"coordinates":[-2.361907,51.38205],"type":"Point"}
}