{
  "type": "Feature",
  "properties": {
    "addr:full":"Unit 31, Walthamstow Bus  Centre, Clifford Rd, Walthamstow London Greater London E17 4SX",
    "addr:housenumber":"unit 31",
    "addr:postcode":"centre;e17 4sx",
    "addr:street":"Clifford Rd",
    "iso:country":"GB",
    "sg:address":"Unit 31, Walthamstow Bus  Centre, Clifford Rd, Walthamstow",
    "sg:city":"London",
    "sg:classifiers":[
        {
            "category":"Professional",
            "subcategory":"Art Services",
            "type":"Services"
        }
    ],
    "sg:postcode":"E17 4SX",
    "sg:province":"Greater London",
    "sg:tags":[
        "framing"
    ],
    "wof:name":"Read,Delysia,",
    "wof:placetype":"venue"
},
  "geometry": {"coordinates":[-0.0167839993,51.6009750366],"type":"Point"}
}