{
  "type": "Feature",
  "properties": {
    "iso:country":"GB",
    "sg:address":"99 Canterbury Road",
    "sg:city":"Whitstable",
    "sg:classifiers":[
        {
            "category":"Shopping",
            "subcategory":"Stationery & Office Supplies",
            "type":"Retail Goods"
        }
    ],
    "sg:phone":"+44 1227 274942",
    "sg:postcode":"CT5 4HG",
    "sg:province":"Kent",
    "sg:tags":[
        "equipment"
    ],
    "wof:name":"Canterbury Business Equipment Ltd.",
    "wof:placetype":"venue"
},
  "geometry": {"coordinates":[1.023696,51.352104],"type":"Point"}
}