{
  "type": "Feature",
  "properties": {
    "iso:country":"GB",
    "sg:address":"643c Fulham Road",
    "sg:city":"London",
    "sg:classifiers":[
        {
            "category":"Shopping",
            "subcategory":"Antiques",
            "type":"Retail Goods"
        }
    ],
    "sg:phone":"+44 20 7736 7088",
    "sg:postcode":"SW6 5PU",
    "sg:province":"Greater London",
    "wof:name":"Laccademia Antiques",
    "wof:placetype":"venue"
},
  "geometry": {"coordinates":[-0.199095,51.479473],"type":"Point"}
}