{
  "type": "Feature",
  "properties": {
    "iso:country":"GB",
    "sg:address":"155 Stockport Rd",
    "sg:city":"Altrincham",
    "sg:classifiers":[
        {
            "category":"Autos & Motor Vehicles",
            "subcategory":"Fuel & Gas Station",
            "type":"Retail Goods"
        }
    ],
    "sg:postcode":"WA15 7LT",
    "sg:province":"Cheshire",
    "sg:tags":[
        "petrol",
        "filling"
    ],
    "wof:name":"Mikon Garages (Altrincham) Ltd",
    "wof:placetype":"venue"
},
  "geometry": {"coordinates":[-2.3299849033,53.3917045593],"type":"Point"}
}