{
  "type": "Feature",
  "properties": {
    "addr:full":"23 The Green Carlisle Cumbria CA3 0NF",
    "addr:housenumber":"23",
    "addr:postcode":"ca3 0nf",
    "addr:street":"The Green",
    "iso:country":"GB",
    "sg:address":"23 The Green",
    "sg:city":"Carlisle",
    "sg:classifiers":[
        {
            "category":"Personal",
            "subcategory":"Beauty Salon",
            "type":"Services"
        }
    ],
    "sg:phone":"+44 1228 525762",
    "sg:postcode":"CA3 0NF",
    "sg:province":"Cumbria",
    "sg:tags":[
        "unisex",
        "hairdresser"
    ],
    "wof:name":"Town & Country Hairdressers",
    "wof:placetype":"venue"
},
  "geometry": {"coordinates":[-2.9200069904,54.9251785278],"type":"Point"}
}