{
  "type": "Feature",
  "properties": {
    "iso:country":"GB",
    "sg:address":"Kensington Drive, Great Holm",
    "sg:city":"Milton Keynes",
    "sg:classifiers":[
        {
            "category":"Health Services",
            "subcategory":"Doctor",
            "type":"Services"
        },
        {
            "category":"Health Services",
            "subcategory":"Clinic",
            "type":"Services"
        }
    ],
    "sg:phone":"+44 1908 568446",
    "sg:postcode":"MK8 9HN",
    "sg:province":"Buckinghamshire",
    "sg:tags":[
        "nh",
        "practitioners"
    ],
    "wof:name":"HILLTOPS MEDICAL CENTRE",
    "wof:placetype":"venue"
},
  "geometry": {"coordinates":[-0.797326,52.036182],"type":"Point"}
}