{
  "type": "Feature",
  "properties": {
    "iso:country":"GB",
    "sg:address":"Ripley Road, Sawmills",
    "sg:city":"Belper",
    "sg:classifiers":[
        {
            "category":"Retail",
            "subcategory":"Auto Repair",
            "type":"Services"
        }
    ],
    "sg:postcode":"DE56 2JR",
    "sg:province":"Derbyshire",
    "sg:tags":[
        "body",
        "car"
    ],
    "wof:name":"Heage Road Vehicle Services Ltd.",
    "wof:placetype":"venue"
},
  "geometry": {"coordinates":[-1.467645,53.064896],"type":"Point"}
}