{
  "type": "Feature",
  "properties": {
    "addr:full":"Granville Chambers, 3 Midland Road Wellingborough Northamptonshire NN8 1HA",
    "addr:housenumber":"3",
    "addr:postcode":"nn8 1ha",
    "addr:street":"Midland Road",
    "iso:country":"GB",
    "sg:address":"Granville Chambers, 3 Midland Road",
    "sg:city":"Wellingborough",
    "sg:classifiers":[
        {
            "category":"Professional",
            "subcategory":"Art Services",
            "type":"Services"
        }
    ],
    "sg:postcode":"NN8 1HA",
    "sg:province":"Northamptonshire",
    "sg:tags":[
        "consultant",
        "design"
    ],
    "wof:name":"M R Designs",
    "wof:placetype":"venue"
},
  "geometry": {"coordinates":[-0.6962959766,52.3024215698],"type":"Point"}
}