{
  "type": "Feature",
  "properties": {
    "iso:country":"GB",
    "sg:address":"245 Camden Road",
    "sg:city":"London",
    "sg:classifiers":[
        {
            "category":"Social Services",
            "subcategory":"Adult Care",
            "type":"Services"
        },
        {
            "category":"Social Services",
            "subcategory":"Retirement Home",
            "type":"Services"
        }
    ],
    "sg:phone":"+44 20 7609 0492",
    "sg:postcode":"N7 0HL",
    "sg:province":"Greater London",
    "sg:tags":[
        "housing",
        "sheltered",
        "accommodation"
    ],
    "wof:name":"Belmore House",
    "wof:placetype":"venue"
},
  "geometry": {"coordinates":[-0.128069,51.549709],"type":"Point"}
}