{
  "type": "Feature",
  "properties": {
    "iso:country":"GB",
    "sg:address":"Central House 32-66 High St, Stratford",
    "sg:city":"London",
    "sg:classifiers":[
        {
            "category":"Organizations",
            "subcategory":"Community Association",
            "type":"Services"
        }
    ],
    "sg:postcode":"E15 2PD",
    "sg:province":"Greater London",
    "sg:tags":[
        "society",
        "housing"
    ],
    "wof:name":"English Churches Housing Group Ltd",
    "wof:placetype":"venue"
},
  "geometry": {"coordinates":[-0.009471,51.532536],"type":"Point"}
}