{
  "type": "Feature",
  "properties": {
    "iso:country":"GB",
    "sg:address":"100 Kings Road, North Ormesby",
    "sg:city":"Middlesbrough",
    "sg:classifiers":[
        {
            "category":"Fast Food",
            "type":"Food & Drink"
        }
    ],
    "sg:phone":"+44 1642 249684",
    "sg:postcode":"TS3 6EU",
    "sg:province":"North Yorkshire",
    "sg:tags":[
        "away",
        "meal",
        "outlet",
        "take"
    ],
    "wof:name":"The Sunflower Chop Suey House",
    "wof:placetype":"venue"
},
  "geometry": {"coordinates":[-1.210124,54.567696],"type":"Point"}
}