{
  "type": "Feature",
  "properties": {
    "addr:full":"48 Hazeldene Road Stoke-on-trent Staffordshire ST4 8DN",
    "addr:housenumber":"48",
    "addr:postcode":"st4 8dn",
    "addr:street":"Hazeldene Road",
    "iso:country":"GB",
    "sg:address":"48 Hazeldene Road",
    "sg:city":"Stoke-on-trent",
    "sg:classifiers":[
        {
            "category":"Building & Trades",
            "subcategory":"Construction",
            "type":"Services"
        }
    ],
    "sg:postcode":"ST4 8DN",
    "sg:province":"Staffordshire",
    "sg:tags":[
        "decorator",
        "painter"
    ],
    "wof:name":"John R Gamble",
    "wof:placetype":"venue"
},
  "geometry": {"coordinates":[-2.176684,52.969288],"type":"Point"}
}