{
  "type": "Feature",
  "properties": {
    "addr:full":"Blanche Lane Farm House, Blanche Lane, South Mimms Potters Bar Greater London EN6 3LF",
    "addr:postcode":"en6 3lf",
    "addr:street":"Blanche Lane;Blanche Lane",
    "iso:country":"GB",
    "sg:address":"Blanche Lane Farm House, Blanche Lane, South Mimms",
    "sg:city":"Potters Bar",
    "sg:classifiers":[
        {
            "category":"Building & Trades",
            "subcategory":"Cleaning & Sanitation",
            "type":"Services"
        }
    ],
    "sg:phone":"+44 1707 661621",
    "sg:postcode":"EN6 3LF",
    "sg:province":"Greater London",
    "sg:tags":[
        "commercial"
    ],
    "wof:name":"Grade A Cleaning Services",
    "wof:placetype":"venue"
},
  "geometry": {"coordinates":[-0.234305,51.692196],"type":"Point"}
}