{
  "type": "Feature",
  "properties": {
    "addr:full":"7 Salvington Rd, Bewbush Crawley West Sussex RH11 8XE",
    "addr:housenumber":"7",
    "addr:postcode":"rh11 8xe",
    "addr:street":"Salvington Rd",
    "iso:country":"GB",
    "sg:address":"7 Salvington Rd, Bewbush",
    "sg:city":"Crawley",
    "sg:classifiers":[
        {
            "category":"Home & Garden",
            "subcategory":"Building Materials",
            "type":"Retail Goods"
        }
    ],
    "sg:postcode":"RH11 8XE",
    "sg:province":"West Sussex",
    "sg:tags":[
        "gate",
        "door",
        "barrier"
    ],
    "wof:name":"Waller,Neil,",
    "wof:placetype":"venue"
},
  "geometry": {"coordinates":[-0.2169809937,51.1016426086],"type":"Point"}
}