{
  "type": "Feature",
  "properties": {
    "iso:country":"GB",
    "sg:address":"54 Old Torquay Road, Preston",
    "sg:city":"Paignton",
    "sg:classifiers":[
        {
            "category":"Travel",
            "subcategory":"Hotels & Motels",
            "type":"Entertainment"
        }
    ],
    "sg:postcode":"TQ3 2RD",
    "sg:province":"Devon",
    "sg:tags":[
        "house",
        "guest"
    ],
    "wof:name":"Mary Molloy",
    "wof:placetype":"venue"
},
  "geometry": {"coordinates":[-3.560683,50.446667],"type":"Point"}
}