{
  "type": "Feature",
  "properties": {
    "addr:full":"34 South Parade, Summertown Oxford Oxfordshire OX2 7JN",
    "addr:housenumber":"34",
    "addr:postcode":"ox2 7jn",
    "addr:street":"South Parade",
    "iso:country":"GB",
    "sg:address":"34 South Parade, Summertown",
    "sg:city":"Oxford",
    "sg:classifiers":[
        {
            "category":"Real Estate",
            "subcategory":"Real Estate Agent",
            "type":"Services"
        }
    ],
    "sg:phone":"+44 1865 511333",
    "sg:postcode":"OX2 7JN",
    "sg:province":"Oxfordshire",
    "wof:name":"Paul Murray (Town & Country Property) Ltd.",
    "wof:placetype":"venue"
},
  "geometry": {"coordinates":[-1.268812,51.777607],"type":"Point"}
}