{
  "type": "Feature",
  "properties": {
    "iso:country":"GB",
    "sg:address":"148 Windsor Rd",
    "sg:city":"Torquay",
    "sg:classifiers":[
        {
            "category":"Professional",
            "subcategory":"Management & Consulting",
            "type":"Services"
        }
    ],
    "sg:postcode":"TQ1 1SR",
    "sg:province":"Devon",
    "sg:tags":[
        "consultant",
        "specialist"
    ],
    "wof:name":"Lane,Esme,",
    "wof:placetype":"venue"
},
  "geometry": {"coordinates":[-3.517127,50.472805],"type":"Point"}
}