{
  "type": "Feature",
  "properties": {
    "addr:full":"226 Whitehorse Road Croydon Surrey CR9 2NR",
    "addr:housenumber":"226",
    "addr:postcode":"cr9 2nr",
    "addr:street":"Whitehorse Road",
    "iso:country":"GB",
    "sg:address":"226 Whitehorse Road",
    "sg:city":"Croydon",
    "sg:classifiers":[
        {
            "category":"Shopping",
            "subcategory":"Clothing, Apparel, & Fashions",
            "type":"Retail Goods"
        }
    ],
    "sg:phone":"+44 20 8684 8881",
    "sg:postcode":"CR9 2NR",
    "sg:province":"Surrey",
    "sg:tags":[
        "workwear",
        "protective"
    ],
    "wof:name":"Sunlight Service Group",
    "wof:placetype":"venue"
},
  "geometry": {"coordinates":[-0.094588,51.390373],"type":"Point"}
}