{
  "type": "Feature",
  "properties": {
    "iso:country":"GB",
    "sg:address":"Visitors Centre, Ashridge Estate",
    "sg:city":"Berkhamsted",
    "sg:classifiers":[
        {
            "category":"Landmark",
            "subcategory":"Tourist Attraction",
            "type":"Public Place"
        }
    ],
    "sg:phone":"+44 1442 851227",
    "sg:postcode":"HP4 1LX",
    "sg:province":"Bedfordshire",
    "sg:tags":[
        "interest"
    ],
    "wof:name":"The National Trust",
    "wof:placetype":"venue"
},
  "geometry": {"coordinates":[-0.564559,51.760414],"type":"Point"}
}