{
  "type": "Feature",
  "properties": {
    "iso:country":"GB",
    "sg:address":"Poolsbrook Road, Duckmanton",
    "sg:city":"Chesterfield",
    "sg:classifiers":[
        {
            "category":"Shopping",
            "subcategory":"News",
            "type":"Retail Goods"
        }
    ],
    "sg:phone":"+44 1246 823348",
    "sg:postcode":"S44 5EA",
    "sg:province":"Derbyshire",
    "sg:tags":[
        "newsagent"
    ],
    "wof:name":"Duckmanton Post Office",
    "wof:placetype":"venue"
},
  "geometry": {"coordinates":[-1.340418,53.24826],"type":"Point"}
}