{
  "type": "Feature",
  "properties": {
    "addr:full":"94 Owen Road Wolverhampton Staffordshire WV3 0AL",
    "addr:housenumber":"94",
    "addr:postcode":"wv3 0al",
    "addr:street":"Owen Road",
    "iso:country":"GB",
    "sg:address":"94 Owen Road",
    "sg:city":"Wolverhampton",
    "sg:classifiers":[
        {
            "category":"Shopping",
            "subcategory":"Clothing, Apparel, & Fashions",
            "type":"Retail Goods"
        }
    ],
    "sg:phone":"+44 1902 420707",
    "sg:postcode":"WV3 0AL",
    "sg:province":"Staffordshire",
    "sg:tags":[
        "clothing",
        "fabric"
    ],
    "wof:name":"H S Gill & Co Manufacturing",
    "wof:placetype":"venue"
},
  "geometry": {"coordinates":[-2.144373,52.580868],"type":"Point"}
}