{
  "type": "Feature",
  "properties": {
    "addr:full":"Unit E, Heath Place Bognor Regis West Sussex PO22 9SL",
    "addr:postcode":"po22 9sl",
    "addr:street":"Heath Place",
    "iso:country":"GB",
    "sg:address":"Unit E, Heath Place",
    "sg:city":"Bognor Regis",
    "sg:classifiers":[
        {
            "category":"Retail",
            "subcategory":"Auto Repair",
            "type":"Services"
        }
    ],
    "sg:phone":"+44 1243 841672",
    "sg:postcode":"PO22 9SL",
    "sg:province":"West Sussex",
    "sg:tags":[
        "modification",
        "garage",
        "related"
    ],
    "wof:name":"N D Autos",
    "wof:placetype":"venue"
},
  "geometry": {"coordinates":[-0.67398,50.801788],"type":"Point"}
}