{
  "type": "Feature",
  "properties": {
    "iso:country":"GB",
    "sg:address":"St Saviours Road",
    "sg:city":"Bath",
    "sg:classifiers":[
        {
            "category":"Retail",
            "subcategory":"Auto Repair",
            "type":"Services"
        }
    ],
    "sg:phone":"+44 1225 422804",
    "sg:postcode":"BA1 6RT",
    "sg:province":"Bath and North East Somerset",
    "sg:tags":[
        "modification",
        "garage"
    ],
    "wof:name":"Larkhall Garage",
    "wof:placetype":"venue"
},
  "geometry": {"coordinates":[-2.346769,51.394791],"type":"Point"}
}