{
  "type": "Feature",
  "properties": {
    "addr:full":"Broad Lane, North Curry Taunton Devon TA3 6EE",
    "addr:postcode":"ta3 6ee",
    "addr:street":"Broad Lane North",
    "iso:country":"GB",
    "sg:address":"Broad Lane, North Curry",
    "sg:city":"Taunton",
    "sg:classifiers":[
        {
            "category":"Community Center",
            "type":"Public Place"
        }
    ],
    "sg:postcode":"TA3 6EE",
    "sg:province":"Devon",
    "sg:tags":[
        "nursery",
        "centre"
    ],
    "wof:name":"Top Plants",
    "wof:placetype":"venue"
},
  "geometry": {"coordinates":[-2.951081,51.027611],"type":"Point"}
}