{
  "type": "Feature",
  "properties": {
    "iso:country":"GB",
    "sg:address":"Fromeside, Doctor Newtons Way",
    "sg:city":"Stroud",
    "sg:classifiers":[
        {
            "category":"Autos & Motor Vehicles",
            "subcategory":"Auto Supplies",
            "type":"Retail Goods"
        },
        {
            "category":"Shopping",
            "subcategory":"Computers & Home Electronics",
            "type":"Retail Goods"
        }
    ],
    "sg:phone":"+44 1453 768888",
    "sg:postcode":"GL5 3JX",
    "sg:province":"Gloucestershire",
    "sg:tags":[
        "electrical",
        "tyre"
    ],
    "wof:name":"Severn Electrical Wholesale Ltd.",
    "wof:placetype":"venue"
},
  "geometry": {"coordinates":[-2.2324409485,51.744934082],"type":"Point"}
}