{
  "type": "Feature",
  "properties": {
    "addr:full":"159 High Street Guildford Surrey GU1 3AJ",
    "addr:housenumber":"159",
    "addr:postcode":"gu1 3aj",
    "addr:street":"High Street",
    "iso:country":"GB",
    "sg:address":"159 High Street",
    "sg:city":"Guildford",
    "sg:classifiers":[
        {
            "category":"Shopping",
            "subcategory":"Clothing, Apparel, & Fashions",
            "type":"Retail Goods"
        }
    ],
    "sg:phone":"+44 1483 536866",
    "sg:postcode":"GU1 3AJ",
    "sg:province":"Surrey",
    "sg:tags":[
        "ladieswear"
    ],
    "wof:name":"Country Casual",
    "wof:placetype":"venue"
},
  "geometry": {"coordinates":[-0.5709350109,51.2362480164],"type":"Point"}
}