{
  "type": "Feature",
  "properties": {
    "addr:full":"Field Avenue, Hatton Derby Derbyshire DE65 5EQ",
    "addr:postcode":"de65 5eq",
    "addr:street":"Field Avenue",
    "iso:country":"GB",
    "sg:address":"Field Avenue, Hatton",
    "sg:city":"Derby",
    "sg:classifiers":[
        {
            "category":"Education",
            "subcategory":"School",
            "type":"Public Place"
        }
    ],
    "sg:phone":"+44 1283 813255",
    "sg:postcode":"DE65 5EQ",
    "sg:province":"Derbyshire",
    "sg:tags":[
        "local",
        "authority"
    ],
    "wof:name":"Heath Fields Primary School",
    "wof:placetype":"venue"
},
  "geometry": {"coordinates":[-1.681264,52.86586],"type":"Point"}
}