{
  "type": "Feature",
  "properties": {
    "addr:full":"Newcombe Way, Orton Southgate Peterborough Cambridgeshire PE2 6SR",
    "addr:postcode":"pe2 6sr",
    "addr:street":"Newcombe Way",
    "iso:country":"GB",
    "sg:address":"Newcombe Way, Orton Southgate",
    "sg:city":"Peterborough",
    "sg:classifiers":[
        {
            "category":"Manufacturing",
            "subcategory":"Wood Products",
            "type":"Manufacturing & Wholesale Goods"
        }
    ],
    "sg:phone":"+44 1733 233883",
    "sg:postcode":"PE2 6SR",
    "sg:province":"Cambridgeshire",
    "sg:tags":[
        "packaging",
        "crate",
        "pallets"
    ],
    "wof:name":"Smurfit Corrugated U K Ltd.",
    "wof:placetype":"venue"
},
  "geometry": {"coordinates":[-0.319989,52.537899],"type":"Point"}
}