{
  "type": "Feature",
  "properties": {
    "addr:full":"104-104a Darlington Street Wolverhampton West Midlands WV1 4EX",
    "addr:housenumber":"104-104a",
    "addr:postcode":"wv1 4ex",
    "addr:street":"Darlington Street",
    "iso:country":"GB",
    "sg:address":"104-104a Darlington Street",
    "sg:city":"Wolverhampton",
    "sg:classifiers":[
        {
            "category":"Banks & Credit Unions",
            "subcategory":"Financial Services",
            "type":"Services"
        }
    ],
    "sg:phone":"+44 1902 562900",
    "sg:postcode":"WV1 4EX",
    "sg:province":"West Midlands",
    "sg:tags":[
        "cashing",
        "cheque"
    ],
    "wof:name":"Cheque Cashing Wolverhampton",
    "wof:placetype":"venue"
},
  "geometry": {"coordinates":[-2.1295800209,52.5857391357],"type":"Point"}
}