{
  "type": "Feature",
  "properties": {
    "addr:full":"8 Bridge Street Fakenham Norfolk NR21 9AQ",
    "addr:housenumber":"8",
    "addr:postcode":"nr21 9aq",
    "addr:street":"Bridge Street",
    "iso:country":"GB",
    "sg:address":"8 Bridge Street",
    "sg:city":"Fakenham",
    "sg:classifiers":[
        {
            "category":"Shopping",
            "subcategory":"Computers & Home Electronics",
            "type":"Retail Goods"
        },
        {
            "category":"Professional",
            "subcategory":"Computer Services",
            "type":"Services"
        }
    ],
    "sg:phone":"+44 1328 851665",
    "sg:postcode":"NR21 9AQ",
    "sg:province":"Norfolk",
    "sg:tags":[
        "software",
        "sales",
        "system"
    ],
    "wof:name":"The Computer Shop",
    "wof:placetype":"venue"
},
  "geometry": {"coordinates":[0.8483809829,52.8299484253],"type":"Point"}
}