{
  "type": "Feature",
  "properties": {
    "iso:country":"GB",
    "sg:address":"Studio 2, 21 Clerkenwell Grn",
    "sg:city":"London",
    "sg:classifiers":[
        {
            "category":"Manufacturing",
            "subcategory":"Jewelry",
            "type":"Manufacturing & Wholesale Goods"
        },
        {
            "category":"Shopping",
            "subcategory":"Comic Books",
            "type":"Retail Goods"
        }
    ],
    "sg:postcode":"EC1R 0DP",
    "sg:province":"Greater London",
    "sg:tags":[
        "repair",
        "jeweller",
        "jewellery"
    ],
    "wof:name":"Dominic Walmsley Jewellery",
    "wof:placetype":"venue"
},
  "geometry": {"coordinates":[-0.1054800004,51.5225791931],"type":"Point"}
}