{
  "type": "Feature",
  "properties": {
    "addr:full":"Willowbrook, Barlestone Road, Newbold Verdon Leicester Leicestershire LE9 9NE",
    "addr:postcode":"le9 9ne",
    "addr:street":"Barlestone Road",
    "iso:country":"GB",
    "sg:address":"Willowbrook, Barlestone Road, Newbold Verdon",
    "sg:city":"Leicester",
    "sg:classifiers":[
        {
            "category":"Farming",
            "subcategory":"Livestock Farm",
            "type":"Manufacturing & Wholesale Goods"
        }
    ],
    "sg:phone":"+44 1455 822397",
    "sg:postcode":"LE9 9NE",
    "sg:province":"Leicestershire",
    "sg:tags":[
        "others"
    ],
    "wof:name":"T B Bates & Son",
    "wof:placetype":"venue"
},
  "geometry": {"coordinates":[-1.3365169764,52.6315383911],"type":"Point"}
}