{
  "type": "Feature",
  "properties": {
    "addr:full":"73 Skinnergate Darlington Durham DL3 7LL",
    "addr:housenumber":"73",
    "addr:postcode":"dl3 7ll",
    "addr:street":"Skinnergate Darlington",
    "iso:country":"GB",
    "sg:address":"73 Skinnergate",
    "sg:city":"Darlington",
    "sg:classifiers":[
        {
            "category":"Shopping",
            "subcategory":"Gifts & Souvenirs",
            "type":"Retail Goods"
        }
    ],
    "sg:phone":"+44 1325 462211",
    "sg:postcode":"DL3 7LL",
    "sg:province":"Durham",
    "sg:tags":[
        "shop"
    ],
    "wof:name":"Hills Wholesale-Replicas",
    "wof:placetype":"venue"
},
  "geometry": {"coordinates":[-1.557319,54.524876],"type":"Point"}
}