{
  "type": "Feature",
  "properties": {
    "addr:full":"10 The Centre Margate Kent CT9 1JG",
    "addr:housenumber":"10",
    "addr:postcode":"ct9 1jg",
    "addr:street":"The Centre Margate",
    "iso:country":"GB",
    "sg:address":"10 The Centre",
    "sg:city":"Margate",
    "sg:classifiers":[
        {
            "category":"Food & Beverages",
            "subcategory":"Specialty",
            "type":"Retail Goods"
        }
    ],
    "sg:phone":"+44 1843 228131",
    "sg:postcode":"CT9 1JG",
    "sg:province":"Kent",
    "sg:tags":[
        "retailer",
        "product",
        "health"
    ],
    "wof:name":"Holland & Barrett Ltd",
    "wof:placetype":"venue"
},
  "geometry": {"coordinates":[1.379247,51.386662],"type":"Point"}
}