{
  "type": "Feature",
  "properties": {
    "iso:country":"GB",
    "sg:address":"12 Bridge Park",
    "sg:city":"Newcastle Upon Tyne",
    "sg:classifiers":[
        {
            "category":"Real Estate",
            "subcategory":"Architect",
            "type":"Services"
        }
    ],
    "sg:phone":"+44 191 285 2185",
    "sg:postcode":"NE3 2DX",
    "sg:province":"Tyne and Wear",
    "sg:tags":[
        "architectural"
    ],
    "wof:name":"Given Design Co",
    "wof:placetype":"venue"
},
  "geometry": {"coordinates":[-1.6247559786,55.0197105408],"type":"Point"}
}