{
  "type": "Feature",
  "properties": {
    "addr:full":"Unit 4 The Galleries, 17-19 Station Rd, Cheadle Hulme Cheadle Cheshire SK8 5AF",
    "addr:housenumber":"unit 4 the galleries 17-19",
    "addr:postcode":"sk8 5af",
    "addr:street":"Station Rd",
    "iso:country":"GB",
    "sg:address":"Unit 4 The Galleries, 17-19 Station Rd, Cheadle Hulme",
    "sg:city":"Cheadle",
    "sg:classifiers":[
        {
            "category":"Personal",
            "subcategory":"Barber",
            "type":"Services"
        }
    ],
    "sg:postcode":"SK8 5AF",
    "sg:province":"Cheshire",
    "sg:tags":[
        "men's",
        "hairdresser"
    ],
    "wof:name":"McCardle,Helen,",
    "wof:placetype":"venue"
},
  "geometry": {"coordinates":[-2.1914739609,53.3778610229],"type":"Point"}
}