{
  "type": "Feature",
  "properties": {
    "addr:full":"1-14 John Jarvie Square, Kilsyth Glasgow East Dunbartonshire G65 0HJ",
    "addr:housenumber":"1-14",
    "addr:postcode":"g65 0hj",
    "addr:street":"John Jarvie Square",
    "iso:country":"GB",
    "sg:address":"1-14 John Jarvie Square, Kilsyth",
    "sg:city":"Glasgow",
    "sg:classifiers":[
        {
            "category":"Social Services",
            "subcategory":"Adult Care",
            "type":"Services"
        },
        {
            "category":"Government",
            "subcategory":"Office",
            "type":"Public Place"
        }
    ],
    "sg:phone":"+44 1236 822487",
    "sg:postcode":"G65 0HJ",
    "sg:province":"East Dunbartonshire",
    "sg:tags":[
        "housing",
        "local",
        "sheltered"
    ],
    "wof:name":"John Jarvie Square",
    "wof:placetype":"venue"
},
  "geometry": {"coordinates":[-4.0569438934,55.9778556824],"type":"Point"}
}