{
  "type": "Feature",
  "properties": {
    "addr:full":"Kiltarlity Beauly Highland IV4 7HG",
    "addr:postcode":"iv4 7hg",
    "iso:country":"GB",
    "sg:address":"Kiltarlity",
    "sg:city":"Beauly",
    "sg:classifiers":[
        {
            "category":"Food & Beverages",
            "subcategory":"Fruits & Vegetables",
            "type":"Retail Goods"
        }
    ],
    "sg:phone":"+44 1463 741228",
    "sg:postcode":"IV4 7HG",
    "sg:province":"Highland",
    "sg:tags":[
        "greengrocer"
    ],
    "wof:name":"Allarburn Bar & Stores",
    "wof:placetype":"venue"
},
  "geometry": {"coordinates":[-4.4607567787,57.4829177856],"type":"Point"}
}