{
  "type": "Feature",
  "properties": {
    "addr:full":"Minto Avenue, Altens Industrial Estate Aberdeen Aberdeen City AB12 3JZ",
    "addr:postcode":"ab12 3jz",
    "addr:street":"Minto Avenue Altens Industrial Estate",
    "iso:country":"GB",
    "sg:address":"Minto Avenue, Altens Industrial Estate",
    "sg:city":"Aberdeen",
    "sg:classifiers":[
        {
            "category":"Freight",
            "type":"Transportation"
        }
    ],
    "sg:phone":"+44 1224 891321",
    "sg:postcode":"AB12 3JZ",
    "sg:province":"Aberdeen City",
    "sg:tags":[
        "overseas",
        "shipping",
        "removal"
    ],
    "wof:name":"Allied Pickfords",
    "wof:placetype":"venue"
},
  "geometry": {"coordinates":[-2.080849,57.109871],"type":"Point"}
}