{
  "type": "Feature",
  "properties": {
    "iso:country":"GB",
    "sg:address":"Welch Way",
    "sg:city":"Witney",
    "sg:classifiers":[
        {
            "category":"Government",
            "subcategory":"Office",
            "type":"Public Place"
        }
    ],
    "sg:phone":"+44 1993 703062",
    "sg:postcode":"OX28 6JH",
    "sg:province":"Oxfordshire",
    "sg:tags":[
        "marriage",
        "death",
        "births"
    ],
    "wof:name":"Oxfordshire County Council",
    "wof:placetype":"venue"
},
  "geometry": {"coordinates":[-1.4905190468,51.786895752],"type":"Point"}
}