{
  "type": "Feature",
  "properties": {
    "addr:full":"5 Chard Road Exeter Devon EX1 3AY",
    "addr:housenumber":"5",
    "addr:postcode":"ex1 3ay",
    "addr:street":"Chard Road",
    "iso:country":"GB",
    "sg:address":"5 Chard Road",
    "sg:city":"Exeter",
    "sg:classifiers":[
        {
            "category":"Sports & Exercise",
            "subcategory":"Bowling",
            "type":"Entertainment"
        }
    ],
    "sg:phone":"+44 1392 436281",
    "sg:postcode":"EX1 3AY",
    "sg:province":"Devon",
    "wof:name":"Heavitree Bowling Club",
    "wof:placetype":"venue"
},
  "geometry": {"coordinates":[-3.501553,50.725883],"type":"Point"}
}