{
  "type": "Feature",
  "properties": {
    "addr:full":"6 Heworth Rd, Concord Washington Tyne and Wear NE37 2PY",
    "addr:housenumber":"6",
    "addr:postcode":"tyne and;ne37 2py",
    "addr:street":"Heworth Rd",
    "iso:country":"GB",
    "sg:address":"6 Heworth Rd, Concord",
    "sg:city":"Washington",
    "sg:classifiers":[
        {
            "category":"Retail",
            "subcategory":"Repair Shop",
            "type":"Services"
        }
    ],
    "sg:postcode":"NE37 2PY",
    "sg:province":"Tyne and Wear",
    "sg:tags":[
        "radio",
        "television",
        "video"
    ],
    "wof:name":"Aafingwood,John Roy,",
    "wof:placetype":"venue"
},
  "geometry": {"coordinates":[-1.525166,54.91396],"type":"Point"}
}