{
  "type": "Feature",
  "properties": {
    "addr:full":"97 Exeter Road Exmouth Devon EX8 1QE",
    "addr:housenumber":"97",
    "addr:postcode":"ex8 1qe",
    "addr:street":"Exeter Road",
    "iso:country":"GB",
    "sg:address":"97 Exeter Road",
    "sg:city":"Exmouth",
    "sg:classifiers":[
        {
            "category":"Food & Beverages",
            "subcategory":"Liquor & Beverages",
            "type":"Retail Goods"
        }
    ],
    "sg:phone":"+44 1395 274011",
    "sg:postcode":"EX8 1QE",
    "sg:province":"Devon",
    "sg:tags":[
        "beer",
        "spirit",
        "wines"
    ],
    "wof:name":"Thresher",
    "wof:placetype":"venue"
},
  "geometry": {"coordinates":[-3.4110720158,50.6246528625],"type":"Point"}
}