{
  "type": "Feature",
  "properties": {
    "iso:country":"GB",
    "sg:address":"Spendlove Centre Enstone Road, Charlbury",
    "sg:city":"Chipping Norton",
    "sg:classifiers":[
        {
            "category":"Insurance",
            "subcategory":"Insurance Agent",
            "type":"Services"
        }
    ],
    "sg:phone":"+44 1608 811310",
    "sg:postcode":"OX7 3PQ",
    "sg:province":"Gloucestershire",
    "sg:tags":[
        "broker"
    ],
    "wof:name":"Lycetts",
    "wof:placetype":"venue"
},
  "geometry": {"coordinates":[-1.4756430387,51.8729782104],"type":"Point"}
}