{
  "type": "Feature",
  "properties": {
    "addr:full":"Woodcroft, Frosterley Bishop Auckland Durham DL13 2TQ",
    "addr:postcode":"dl13 2tq",
    "addr:street":"Bishop Auckland",
    "iso:country":"GB",
    "sg:address":"Woodcroft, Frosterley",
    "sg:city":"Bishop Auckland",
    "sg:classifiers":[
        {
            "category":"Farming",
            "subcategory":"Livestock Farm",
            "type":"Manufacturing & Wholesale Goods"
        }
    ],
    "sg:phone":"+44 1388 528572",
    "sg:postcode":"DL13 2TQ",
    "sg:province":"Durham",
    "sg:tags":[
        "others"
    ],
    "wof:name":"Alec & Nicholas Peart",
    "wof:placetype":"venue"
},
  "geometry": {"coordinates":[-1.954984,54.727264],"type":"Point"}
}