{
  "type": "Feature",
  "properties": {
    "addr:full":"Po Box 5, Beddws Nuneaton Warwickshire CV12 9HT",
    "addr:housenumber":"po;5",
    "addr:postcode":"cv12 9ht",
    "addr:street":"Box",
    "iso:country":"GB",
    "sg:address":"Po Box 5, Beddws",
    "sg:city":"Nuneaton",
    "sg:classifiers":[
        {
            "category":"Retail",
            "subcategory":"Storage",
            "type":"Services"
        }
    ],
    "sg:phone":"+44 24 7631 9828",
    "sg:postcode":"CV12 9HT",
    "sg:province":"Warwickshire",
    "sg:tags":[
        "household",
        "removal"
    ],
    "wof:name":"T M Palmer & Son Removals",
    "wof:placetype":"venue"
},
  "geometry": {"coordinates":[-1.44672,52.49268],"type":"Point"}
}