{
  "type": "Feature",
  "properties": {
    "iso:country":"GB",
    "sg:address":"88 Redworth Rd",
    "sg:city":"Shildon",
    "sg:classifiers":[
        {
            "category":"Wholesale",
            "subcategory":"Chemicals & Plastics",
            "type":"Manufacturing & Wholesale Goods"
        }
    ],
    "sg:phone":"+44 1388 776665",
    "sg:postcode":"DL4 2JS",
    "sg:province":"Durham",
    "sg:tags":[
        "retail",
        "freezer",
        "refrigerator"
    ],
    "wof:name":"Abtech",
    "wof:placetype":"venue"
},
  "geometry": {"coordinates":[-1.641518,54.62381],"type":"Point"}
}