{
  "type": "Feature",
  "properties": {
    "iso:country":"GB",
    "sg:address":"The Brickyard, Preston-on-stour",
    "sg:city":"Stratford-upon-avon",
    "sg:classifiers":[
        {
            "category":"Organizations",
            "subcategory":"Labor Organization",
            "type":"Services"
        }
    ],
    "sg:phone":"+44 20 8858 7328",
    "sg:postcode":"CV37 8BN",
    "sg:province":"Warwickshire",
    "sg:tags":[
        "woodworking",
        "machinery"
    ],
    "wof:name":"Clock Robin",
    "wof:placetype":"venue"
},
  "geometry": {"coordinates":[-1.701201,52.145737],"type":"Point"}
}