{
  "type": "Feature",
  "properties": {
    "addr:full":"C/o Caroline Sands & Associates, 46 Holway Road Sheringham Norfolk NR26 8LJ",
    "addr:housenumber":"/ o;46",
    "addr:postcode":"nr26 8lj",
    "addr:street":"C;Caroline;Holway Road",
    "iso:country":"GB",
    "sg:address":"C/o Caroline Sands & Associates, 46 Holway Road",
    "sg:city":"Sheringham",
    "sg:classifiers":[
        {
            "category":"Organizations",
            "subcategory":"Membership Organization",
            "type":"Services"
        }
    ],
    "sg:postcode":"NR26 8LJ",
    "sg:province":"Norfolk",
    "sg:tags":[
        "club"
    ],
    "wof:name":"Bedford Mews Residents Association (Sher",
    "wof:placetype":"venue"
},
  "geometry": {"coordinates":[1.2084439993,52.93932724],"type":"Point"}
}