{
  "type": "Feature",
  "properties": {
    "iso:country":"GB",
    "sg:address":"30b Hart St",
    "sg:city":"Henley-on-thames",
    "sg:classifiers":[
        {
            "category":"Professional",
            "subcategory":"Accounting & Tax Preparation",
            "type":"Services"
        }
    ],
    "sg:postcode":"RG9 2AU",
    "sg:province":"Berkshire",
    "sg:tags":[
        "accountant"
    ],
    "wof:name":"Setchell,Davdi C,",
    "wof:placetype":"venue"
},
  "geometry": {"coordinates":[-0.902777,51.537556],"type":"Point"}
}