{
  "type": "Feature",
  "properties": {
    "iso:country":"GB",
    "sg:address":"Keenans Mill, Lord Street",
    "sg:city":"Lytham St Annes",
    "sg:classifiers":[
        {
            "category":"Wholesale",
            "subcategory":"Books, Periodicals, & Newspapers",
            "type":"Manufacturing & Wholesale Goods"
        }
    ],
    "sg:phone":"+44 1253 722142",
    "sg:postcode":"FY8 2DF",
    "sg:province":"Lancashire",
    "sg:tags":[
        "publishing"
    ],
    "wof:name":"Neighbourhood Direct Ltd.",
    "wof:placetype":"venue"
},
  "geometry": {"coordinates":[-2.991574,53.749516],"type":"Point"}
}