{
  "type": "Feature",
  "properties": {
    "addr:full":"Ashby Garages, Ashby Rd London Greater London SE4 1TB",
    "addr:postcode":"se4 1tb",
    "addr:street":"Ashby Rd",
    "iso:country":"GB",
    "sg:address":"Ashby Garages, Ashby Rd",
    "sg:city":"London",
    "sg:classifiers":[
        {
            "category":"Retail",
            "subcategory":"Auto Repair",
            "type":"Services"
        }
    ],
    "sg:postcode":"SE4 1TB",
    "sg:province":"Greater London",
    "sg:tags":[
        "modification",
        "garage"
    ],
    "wof:name":"Pepperell,C,",
    "wof:placetype":"venue"
},
  "geometry": {"coordinates":[-0.03232,51.46793],"type":"Point"}
}