{
  "type": "Feature",
  "properties": {
    "iso:country":"GB",
    "sg:address":"190 Lower Road, Hullbridge",
    "sg:city":"Hockley",
    "sg:classifiers":[
        {
            "category":"Shopping",
            "type":"Retail Goods"
        }
    ],
    "sg:phone":"+44 1702 230268",
    "sg:postcode":"SS5 6BD",
    "sg:province":"Essex",
    "sg:tags":[
        "part",
        "accessory"
    ],
    "wof:name":"Nevendon South East Cars",
    "wof:placetype":"venue"
},
  "geometry": {"coordinates":[0.6238200068,51.6174201965],"type":"Point"}
}