{
  "type": "Feature",
  "properties": {
    "iso:country":"GB",
    "sg:address":"117a Ipswich Road",
    "sg:city":"Norwich",
    "sg:classifiers":[
        {
            "category":"Shopping",
            "subcategory":"Clothing, Apparel, & Fashions",
            "type":"Retail Goods"
        }
    ],
    "sg:phone":"+44 1603 452305",
    "sg:postcode":"NR4 6LD",
    "sg:province":"Norfolk",
    "sg:tags":[
        "shop"
    ],
    "wof:name":"Vanilla",
    "wof:placetype":"venue"
},
  "geometry": {"coordinates":[1.279425,52.605904],"type":"Point"}
}