{
  "type": "Feature",
  "properties": {
    "iso:country":"GB",
    "sg:address":"177 New Rd",
    "sg:city":"Neath",
    "sg:classifiers":[
        {
            "category":"Manufacturing",
            "subcategory":"Tools & Machinery",
            "type":"Manufacturing & Wholesale Goods"
        }
    ],
    "sg:phone":"+44 1792 816696",
    "sg:postcode":"SA10 6HD",
    "sg:province":"Neath Port Talbot",
    "sg:tags":[
        "society",
        "friendly"
    ],
    "wof:name":"Res-Assure Ltd",
    "wof:placetype":"venue"
},
  "geometry": {"coordinates":[-3.84622,51.660725],"type":"Point"}
}