{
  "type": "Feature",
  "properties": {
    "addr:full":"Unit 2 Stadium Way Retail World, Parkgate Rotherham South Yorkshire S60 1TG",
    "addr:housenumber":"unit 2",
    "addr:postcode":"s60 1tg",
    "addr:street":"Stadium Way;Parkgate",
    "iso:country":"GB",
    "sg:address":"Unit 2 Stadium Way Retail World, Parkgate",
    "sg:city":"Rotherham",
    "sg:classifiers":[
        {
            "category":"Shopping",
            "subcategory":"Clothing, Apparel, & Fashions",
            "type":"Retail Goods"
        }
    ],
    "sg:phone":"+44 1709 780684",
    "sg:postcode":"S60 1TG",
    "sg:province":"South Yorkshire",
    "sg:tags":[
        "shop"
    ],
    "wof:name":"What Everyone Wants Ltd.",
    "wof:placetype":"venue"
},
  "geometry": {"coordinates":[-1.3429039717,53.4451713562],"type":"Point"}
}