{
  "type": "Feature",
  "properties": {
    "addr:full":"Mount Pleasant Farm, 30 Bath Road, Longwell Green Bristol Gloucestershire BS30 9DG",
    "addr:housenumber":"30",
    "addr:postcode":"bs30 9dg",
    "addr:street":"Bath Road",
    "iso:country":"GB",
    "sg:address":"Mount Pleasant Farm, 30 Bath Road, Longwell Green",
    "sg:city":"Bristol",
    "sg:classifiers":[
        {
            "category":"Farming",
            "subcategory":"Dairy Farm",
            "type":"Manufacturing & Wholesale Goods"
        }
    ],
    "sg:postcode":"BS30 9DG",
    "sg:province":"Gloucestershire",
    "wof:name":"H Hooper & Sons",
    "wof:placetype":"venue"
},
  "geometry": {"coordinates":[-2.4954,51.439178],"type":"Point"}
}