{
  "type": "Feature",
  "properties": {
    "addr:full":"Claydon Dr Croydon Surrey CR0 4QX",
    "addr:postcode":"cr0 4qx",
    "addr:street":"Claydon Dr",
    "iso:country":"GB",
    "sg:address":"Claydon Dr",
    "sg:city":"Croydon",
    "sg:classifiers":[
        {
            "category":"Professional",
            "subcategory":"Accounting & Tax Preparation",
            "type":"Services"
        }
    ],
    "sg:phone":"+44 20 8781 0606",
    "sg:postcode":"CR0 4QX",
    "sg:province":"Surrey",
    "sg:tags":[
        "consultant"
    ],
    "wof:name":"Oakwood Taxation & Accounting Services",
    "wof:placetype":"venue"
},
  "geometry": {"coordinates":[-0.127545,51.366203],"type":"Point"}
}