{
  "type": "Feature",
  "properties": {
    "iso:country":"GB",
    "sg:address":"Unit 16 Regents Studios, Ada Workshops",
    "sg:city":"London",
    "sg:classifiers":[
        {
            "category":"Professional",
            "subcategory":"Printing & Photocopies",
            "type":"Services"
        }
    ],
    "sg:postcode":"E8 4QN",
    "sg:province":"Greater London",
    "sg:tags":[
        "printer"
    ],
    "wof:name":"Datchet Press & Publishing Ltd",
    "wof:placetype":"venue"
},
  "geometry": {"coordinates":[-0.05951,51.534458],"type":"Point"}
}