{
  "type": "Feature",
  "properties": {
    "addr:full":"48 High St Skegness Lincolnshire PE25 3NW",
    "addr:housenumber":"48",
    "addr:postcode":"pe25 3nw",
    "addr:street":"High St",
    "iso:country":"GB",
    "sg:address":"48 High St",
    "sg:city":"Skegness",
    "sg:classifiers":[
        {
            "category":"Shopping",
            "subcategory":"Hobbies, Toys, & Games",
            "type":"Retail Goods"
        }
    ],
    "sg:phone":"+44 1754 762392",
    "sg:postcode":"PE25 3NW",
    "sg:province":"Lincolnshire",
    "sg:tags":[
        "shop",
        "toy"
    ],
    "wof:name":"Fantasy Island Toys",
    "wof:placetype":"venue"
},
  "geometry": {"coordinates":[0.3377560079,53.1427383423],"type":"Point"}
}