{
  "type": "Feature",
  "properties": {
    "iso:country":"GB",
    "sg:address":"24 Park La, Meadowhall Centre",
    "sg:city":"Sheffield",
    "sg:classifiers":[
        {
            "category":"Shopping",
            "subcategory":"Shoes",
            "type":"Retail Goods"
        }
    ],
    "sg:phone":"+44 114 256 8521",
    "sg:postcode":"S9 1EL",
    "sg:province":"South Yorkshire",
    "sg:tags":[
        "shop"
    ],
    "wof:name":"Nine West",
    "wof:placetype":"venue"
},
  "geometry": {"coordinates":[-1.406079,53.41412],"type":"Point"}
}