{
  "type": "Feature",
  "properties": {
    "iso:country":"GB",
    "sg:address":"Bridge Road South, Wrexham Industrial Estate",
    "sg:city":"Wrexham",
    "sg:classifiers":[
        {
            "category":"Freight",
            "type":"Transportation"
        }
    ],
    "sg:phone":"+44 1978 661751",
    "sg:postcode":"LL13 9SQ",
    "sg:province":"Wrexham",
    "sg:tags":[
        "haulage",
        "road"
    ],
    "wof:name":"F Lloyd (Penley) Ltd.",
    "wof:placetype":"venue"
},
  "geometry": {"coordinates":[-2.938319,53.030312],"type":"Point"}
}