{
  "type": "Feature",
  "properties": {
    "addr:full":"261 High Street Cowdenbeath Fife KY4 9QH",
    "addr:housenumber":"261",
    "addr:postcode":"ky4 9qh",
    "addr:street":"High Street",
    "iso:country":"GB",
    "sg:address":"261 High Street",
    "sg:city":"Cowdenbeath",
    "sg:classifiers":[
        {
            "category":"Bars & Pubs",
            "type":"Food & Drink"
        }
    ],
    "sg:phone":"+44 1383 511350",
    "sg:postcode":"KY4 9QH",
    "sg:province":"Fife",
    "sg:tags":[
        "pubs",
        "inn"
    ],
    "wof:name":"The New Goth",
    "wof:placetype":"venue"
},
  "geometry": {"coordinates":[-3.343611,56.111065],"type":"Point"}
}