{
  "type": "Feature",
  "properties": {
    "addr:full":"43 Rectory Road, Wanlip Leicester Leicestershire LE7 4PL",
    "addr:housenumber":"43",
    "addr:postcode":"le7 4pl",
    "addr:street":"Rectory Road",
    "iso:country":"GB",
    "sg:address":"43 Rectory Road, Wanlip",
    "sg:city":"Leicester",
    "sg:classifiers":[
        {
            "category":"Shopping",
            "subcategory":"Stationery & Office Supplies",
            "type":"Retail Goods"
        }
    ],
    "sg:phone":"+44 116 267 3362",
    "sg:postcode":"LE7 4PL",
    "sg:province":"Leicestershire",
    "sg:tags":[
        "item",
        "promotional"
    ],
    "wof:name":"Copperfield Promotions",
    "wof:placetype":"venue"
},
  "geometry": {"coordinates":[-1.114054,52.692394],"type":"Point"}
}