{
  "type": "Feature",
  "properties": {
    "iso:country":"GB",
    "sg:address":"Wintershill Farm, Wintershill, Durley",
    "sg:city":"Southampton",
    "sg:classifiers":[
        {
            "category":"Farming",
            "subcategory":"Farm",
            "type":"Manufacturing & Wholesale Goods"
        }
    ],
    "sg:phone":"+44 1489 860200",
    "sg:postcode":"SO32 2AH",
    "sg:province":"Hampshire",
    "sg:tags":[
        "mixed",
        "crop"
    ],
    "wof:name":"Winters Hill Estate",
    "wof:placetype":"venue"
},
  "geometry": {"coordinates":[-1.259031,50.947273],"type":"Point"}
}