{
  "type": "Feature",
  "properties": {
    "addr:full":"Diplocks Way, Hailsham Industrial Park Hailsham East Sussex BN27 3JF",
    "addr:postcode":"bn27 3jf",
    "addr:street":"Diplocks Way;Industrial Park",
    "iso:country":"GB",
    "sg:address":"Diplocks Way, Hailsham Industrial Park",
    "sg:city":"Hailsham",
    "sg:classifiers":[
        {
            "category":"Home & Garden",
            "subcategory":"Home Furnishings",
            "type":"Retail Goods"
        }
    ],
    "sg:phone":"+44 1323 847323",
    "sg:postcode":"BN27 3JF",
    "sg:province":"East Sussex",
    "sg:tags":[
        "tube",
        "fitting",
        "stockist"
    ],
    "wof:name":"Philmac Pty Ltd.",
    "wof:placetype":"venue"
},
  "geometry": {"coordinates":[0.244859,50.861858],"type":"Point"}
}