{
  "type": "Feature",
  "properties": {
    "iso:country":"GB",
    "sg:address":"Unit 7f Hewlett House, 5 Havelock Terrace",
    "sg:city":"London",
    "sg:classifiers":[
        {
            "category":"Professional",
            "subcategory":"Printing & Photocopies",
            "type":"Services"
        }
    ],
    "sg:phone":"+44 20 7622 9874",
    "sg:postcode":"SW8 4AS",
    "sg:province":"Greater London",
    "sg:tags":[
        "printer"
    ],
    "wof:name":"G A Litho Services",
    "wof:placetype":"venue"
},
  "geometry": {"coordinates":[-0.143662,51.477043],"type":"Point"}
}