{
  "type": "Feature",
  "properties": {
    "addr:full":"111a Church Rd, Tranmere Birkenhead Birkenhead Merseyside CH42 5LF",
    "addr:housenumber":"111a",
    "addr:postcode":"ch42 5lf",
    "addr:street":"Church Rd",
    "iso:country":"GB",
    "sg:address":"111a Church Rd, Tranmere Birkenhead",
    "sg:city":"Birkenhead",
    "sg:classifiers":[
        {
            "category":"Retail",
            "subcategory":"Auto Repair",
            "type":"Services"
        }
    ],
    "sg:phone":"+44 151 650 1400",
    "sg:postcode":"CH42 5LF",
    "sg:province":"Merseyside",
    "sg:tags":[
        "modification",
        "garage"
    ],
    "wof:name":"The Clutch Care Centre",
    "wof:placetype":"venue"
},
  "geometry": {"coordinates":[-3.0251090527,53.37890625],"type":"Point"}
}