{
  "type": "Feature",
  "properties": {
    "iso:country":"GB",
    "sg:address":"105 South Avenue, Blairhall",
    "sg:city":"Dunfermline",
    "sg:classifiers":[
        {
            "category":"Government",
            "subcategory":"Post Office",
            "type":"Public Place"
        }
    ],
    "sg:phone":"+44 1383 850222",
    "sg:postcode":"KY12 9PH",
    "sg:province":"Fife",
    "wof:name":"Blairhall PO",
    "wof:placetype":"venue"
},
  "geometry": {"coordinates":[-3.6047170162,56.0862579346],"type":"Point"}
}