{
  "type": "Feature",
  "properties": {
    "addr:full":"Lilac Farm, 19 Mill Lane, Cottesmore Oakham Leicestershire LE15 7DL",
    "addr:housenumber":"19",
    "addr:postcode":"le15 7dl",
    "addr:street":"Mill Lane",
    "iso:country":"GB",
    "sg:address":"Lilac Farm, 19 Mill Lane, Cottesmore",
    "sg:city":"Oakham",
    "sg:classifiers":[
        {
            "category":"Home & Garden",
            "subcategory":"Garden Supply",
            "type":"Retail Goods"
        },
        {
            "category":"Farming",
            "subcategory":"Farm",
            "type":"Manufacturing & Wholesale Goods"
        }
    ],
    "sg:postcode":"LE15 7DL",
    "sg:province":"Leicestershire",
    "sg:tags":[
        "mixed",
        "bulb",
        "crop",
        "grower"
    ],
    "wof:name":"W Faulkner & Son",
    "wof:placetype":"venue"
},
  "geometry": {"coordinates":[-0.665494,52.712471],"type":"Point"}
}