{
  "type": "Feature",
  "properties": {
    "iso:country":"GB",
    "sg:address":"Imperial Studios, Maxwell Rd",
    "sg:city":"Borehamwood",
    "sg:classifiers":[
        {
            "category":"Sports & Exercise",
            "subcategory":"Bowling",
            "type":"Entertainment"
        }
    ],
    "sg:phone":"+44 20 8953 5545",
    "sg:postcode":"WD6 1WE",
    "sg:province":"Hertfordshire",
    "sg:tags":[
        "photography"
    ],
    "wof:name":"Landsdowne (Vaults) Ltd",
    "wof:placetype":"venue"
},
  "geometry": {"coordinates":[-0.275754,51.655819],"type":"Point"}
}