{
  "type": "Feature",
  "properties": {
    "iso:country":"GB",
    "sg:address":"Verna House",
    "sg:city":"Aylesbury",
    "sg:classifiers":[
        {
            "category":"Professional",
            "subcategory":"Accounting & Tax Preparation",
            "type":"Services"
        }
    ],
    "sg:phone":"+44 1296 399159",
    "sg:postcode":"HP19 9AG",
    "sg:province":"Buckinghamshire",
    "sg:tags":[
        "accountant"
    ],
    "wof:name":"Alan Green & Co",
    "wof:placetype":"venue"
},
  "geometry": {"coordinates":[-0.81824,51.821259],"type":"Point"}
}