{
  "type": "Feature",
  "properties": {
    "addr:full":"Sandhurst Street, Oadby Leicester Leicestershire LE2 5AR",
    "addr:postcode":"le2 5ar",
    "addr:street":"Sandhurst Street",
    "iso:country":"GB",
    "sg:address":"Sandhurst Street, Oadby",
    "sg:city":"Leicester",
    "sg:classifiers":[
        {
            "category":"Education",
            "subcategory":"Library",
            "type":"Public Place"
        }
    ],
    "sg:phone":"+44 116 271 5066",
    "sg:postcode":"LE2 5AR",
    "sg:province":"Leicestershire",
    "sg:tags":[
        "book"
    ],
    "wof:name":"Oadby Library",
    "wof:placetype":"venue"
},
  "geometry": {"coordinates":[-1.0850100517,52.6005020142],"type":"Point"}
}