{
  "type": "Feature",
  "properties": {
    "iso:country":"GB",
    "sg:address":"7 Waverley Road",
    "sg:city":"Innerleithen",
    "sg:classifiers":[
        {
            "category":"Professional",
            "subcategory":"Art Services",
            "type":"Services"
        }
    ],
    "sg:phone":"+44 1896 831000",
    "sg:postcode":"EH44 6QN",
    "sg:province":"Scottish Borders",
    "sg:tags":[
        "picture",
        "framing"
    ],
    "wof:name":"Adam Watt & Sons",
    "wof:placetype":"venue"
},
  "geometry": {"coordinates":[-3.06256,55.619007],"type":"Point"}
}