{
  "type": "Feature",
  "properties": {
    "iso:country":"GB",
    "sg:address":"Unit 8a The Old School, Station Road",
    "sg:city":"Narberth",
    "sg:classifiers":[
        {
            "category":"Retail",
            "subcategory":"Repair Shop",
            "type":"Services"
        }
    ],
    "sg:phone":"+44 1834 869001",
    "sg:postcode":"SA67 7DU",
    "sg:province":"Carmarthenshire",
    "sg:tags":[
        "upholsterer"
    ],
    "wof:name":"Upholstery by Mary",
    "wof:placetype":"venue"
},
  "geometry": {"coordinates":[-4.744227,51.80117],"type":"Point"}
}