{
  "type": "Feature",
  "properties": {
    "addr:full":"Unit 2a Pincents Kiln, Calcot Reading Berkshire RG31 7SB",
    "addr:housenumber":"unit 2a",
    "addr:postcode":"rg31 7sb",
    "addr:street":"Pincents",
    "iso:country":"GB",
    "sg:address":"Unit 2a Pincents Kiln, Calcot",
    "sg:city":"Reading",
    "sg:classifiers":[
        {
            "category":"Wholesale",
            "subcategory":"Medical Equipment & Supplies",
            "type":"Manufacturing & Wholesale Goods"
        },
        {
            "category":"Shopping",
            "subcategory":"Pharmacy",
            "type":"Retail Goods"
        }
    ],
    "sg:phone":"+44 118 930 5686",
    "sg:postcode":"RG31 7SB",
    "sg:province":"Berkshire",
    "sg:tags":[
        "pharmaceutical",
        "hospital"
    ],
    "wof:name":"Ecosse Hospital Products Ltd.",
    "wof:placetype":"venue"
},
  "geometry": {"coordinates":[-1.0611180067,51.4416160583],"type":"Point"}
}