{
  "type": "Feature",
  "properties": {
    "iso:country":"GB",
    "sg:address":"130 Turves Road, Cheadle Hulme",
    "sg:city":"Cheadle",
    "sg:classifiers":[
        {
            "category":"Shopping",
            "subcategory":"Pharmacy",
            "type":"Retail Goods"
        }
    ],
    "sg:phone":"+44 161 485 2693",
    "sg:postcode":"SK8 6AW",
    "sg:province":"Cheshire",
    "sg:tags":[
        "pharmacist",
        "chemist"
    ],
    "wof:name":"Aubrey Glass Ltd.",
    "wof:placetype":"venue"
},
  "geometry": {"coordinates":[-2.206046,53.373466],"type":"Point"}
}