{
  "type": "Feature",
  "properties": {
    "iso:country":"GB",
    "sg:address":"46 Leonard Rd",
    "sg:city":"Gosport",
    "sg:classifiers":[
        {
            "category":"Professional",
            "subcategory":"Engineering",
            "type":"Services"
        }
    ],
    "sg:postcode":"PO12 4TJ",
    "sg:province":"Hampshire",
    "sg:tags":[
        "contractor",
        "electrical",
        "engineer"
    ],
    "wof:name":"Horne,Terry John,",
    "wof:placetype":"venue"
},
  "geometry": {"coordinates":[-1.131939,50.798805],"type":"Point"}
}