{
  "type": "Feature",
  "properties": {
    "addr:full":"30 Mayfair House, Town Centre Basingstoke Hampshire RG21 7JY",
    "addr:housenumber":"30",
    "addr:postcode":"rg21 7jy",
    "addr:street":"Mayfair",
    "iso:country":"GB",
    "sg:address":"30 Mayfair House, Town Centre",
    "sg:city":"Basingstoke",
    "sg:classifiers":[
        {
            "category":"Shopping",
            "subcategory":"Gifts & Souvenirs",
            "type":"Retail Goods"
        }
    ],
    "sg:phone":"+44 1256 354338",
    "sg:postcode":"RG21 7JY",
    "sg:province":"Hampshire",
    "sg:tags":[
        "poster",
        "card"
    ],
    "wof:name":"Card Fayre",
    "wof:placetype":"venue"
},
  "geometry": {"coordinates":[-1.083088994,51.2624435425],"type":"Point"}
}