{
  "type": "Feature",
  "properties": {
    "addr:full":"24 Fairways Chelmsford Essex CM3 6JJ",
    "addr:housenumber":"24",
    "addr:postcode":"cm3 6jj",
    "addr:street":"Fairways",
    "iso:country":"GB",
    "sg:address":"24 Fairways",
    "sg:city":"Chelmsford",
    "sg:classifiers":[
        {
            "category":"Social Services",
            "subcategory":"Child Care",
            "type":"Services"
        }
    ],
    "sg:phone":"+44 1621 828090",
    "sg:postcode":"CM3 6JJ",
    "sg:province":"Essex",
    "sg:tags":[
        "agency",
        "nanny"
    ],
    "wof:name":"Tinies Nanny Agency",
    "wof:placetype":"venue"
},
  "geometry": {"coordinates":[0.7392399907,51.6678886414],"type":"Point"}
}