{
  "type": "Feature",
  "properties": {
    "iso:country":"GB",
    "sg:address":"Goodwood Crescent",
    "sg:city":"Gravesend",
    "sg:classifiers":[
        {
            "category":"Health Services",
            "subcategory":"Nursing And Care Facility",
            "type":"Services"
        },
        {
            "category":"Social Services",
            "subcategory":"Retirement Home",
            "type":"Services"
        }
    ],
    "sg:phone":"+44 1474 363690",
    "sg:postcode":"DA12 5EY",
    "sg:province":"Kent",
    "sg:tags":[
        "residential"
    ],
    "wof:name":"Hevercourt",
    "wof:placetype":"venue"
},
  "geometry": {"coordinates":[0.374935,51.414276],"type":"Point"}
}