{
  "type": "Feature",
  "properties": {
    "addr:full":"6 Hazelwood Road Northampton Northamptonshire NN1 1LW",
    "addr:housenumber":"6",
    "addr:postcode":"nn1 1lw",
    "addr:street":"Hazelwood Road",
    "iso:country":"GB",
    "sg:address":"6 Hazelwood Road",
    "sg:city":"Northampton",
    "sg:classifiers":[
        {
            "category":"Home & Garden",
            "subcategory":"Home Furnishings",
            "type":"Retail Goods"
        }
    ],
    "sg:phone":"+44 1604 845840",
    "sg:postcode":"NN1 1LW",
    "sg:province":"Northamptonshire",
    "sg:tags":[
        "furnishers",
        "planner",
        "kitchen"
    ],
    "wof:name":"Sherrington Interiors Ltd.",
    "wof:placetype":"venue"
},
  "geometry": {"coordinates":[-0.8907170296,52.2361373901],"type":"Point"}
}