{
  "type": "Feature",
  "properties": {
    "addr:full":"65 St. Giles St Northampton Northamptonshire NN1 1JF",
    "addr:housenumber":"65",
    "addr:postcode":"nn1 1jf",
    "addr:street":"St. Giles St",
    "iso:country":"GB",
    "sg:address":"65 St. Giles St",
    "sg:city":"Northampton",
    "sg:classifiers":[
        {
            "category":"Real Estate",
            "subcategory":"Real Estate Agent",
            "type":"Services"
        }
    ],
    "sg:postcode":"NN1 1JF",
    "sg:province":"Northamptonshire",
    "wof:name":"Tony Wilson Estate Agents",
    "wof:placetype":"venue"
},
  "geometry": {"coordinates":[-0.891715,52.237736],"type":"Point"}
}