{
  "type": "Feature",
  "properties": {
    "iso:country":"GB",
    "sg:address":"3 St Williams Way, Thorpe St Andrew",
    "sg:city":"Norwich",
    "sg:classifiers":[
        {
            "category":"Government",
            "subcategory":"Fire Station",
            "type":"Public Place"
        }
    ],
    "sg:phone":"+44 1603 431122",
    "sg:postcode":"NR7 0AH",
    "sg:province":"Norfolk",
    "sg:tags":[
        "security"
    ],
    "wof:name":"St.Andrews Fire Equipment Ltd.",
    "wof:placetype":"venue"
},
  "geometry": {"coordinates":[1.329516,52.636967],"type":"Point"}
}