{
  "type": "Feature",
  "properties": {
    "iso:country":"GB",
    "sg:address":"Christchurch Road",
    "sg:city":"New Milton",
    "sg:classifiers":[
        {
            "category":"Travel",
            "subcategory":"Hotels & Motels",
            "type":"Entertainment"
        }
    ],
    "sg:postcode":"BH25 6QQ",
    "sg:province":"Hampshire",
    "sg:tags":[
        "house",
        "guest"
    ],
    "wof:name":"Tower House",
    "wof:placetype":"venue"
},
  "geometry": {"coordinates":[-1.6708120108,50.7455406189],"type":"Point"}
}