{
  "type": "Feature",
  "properties": {
    "addr:full":"510 Roman Road London Greater London E3 5ES",
    "addr:housenumber":"510",
    "addr:postcode":"e3 5es",
    "addr:street":"Roman Road",
    "iso:country":"GB",
    "sg:address":"510 Roman Road",
    "sg:city":"London",
    "sg:classifiers":[
        {
            "category":"Fast Food",
            "type":"Food & Drink"
        }
    ],
    "sg:phone":"+44 20 8980 0481",
    "sg:postcode":"E3 5ES",
    "sg:province":"Greater London",
    "sg:tags":[
        "away",
        "meal",
        "outlet",
        "take"
    ],
    "wof:name":"The Roman",
    "wof:placetype":"venue"
},
  "geometry": {"coordinates":[-0.032016,51.532265],"type":"Point"}
}