{
  "type": "Feature",
  "properties": {
    "addr:full":"Arden Street Stratford-upon-avon Warwickshire CV37 6NU",
    "addr:postcode":"cv37 6nu",
    "addr:street":"Arden Street",
    "iso:country":"GB",
    "sg:address":"Arden Street",
    "sg:city":"Stratford-upon-avon",
    "sg:classifiers":[
        {
            "category":"Autos & Motor Vehicles",
            "subcategory":"Automobile Sales",
            "type":"Retail Goods"
        }
    ],
    "sg:phone":"+44 1789 267446",
    "sg:postcode":"CV37 6NU",
    "sg:province":"Warwickshire",
    "sg:tags":[
        "car"
    ],
    "wof:name":"Arden Fleet Management Ltd.",
    "wof:placetype":"venue"
},
  "geometry": {"coordinates":[-1.7123880386,52.193687439],"type":"Point"}
}