{
  "type": "Feature",
  "properties": {
    "addr:full":"52 Cowick Street Exeter Devon EX4 1AP",
    "addr:housenumber":"52",
    "addr:postcode":"ex4 1ap",
    "addr:street":"Cowick Street",
    "iso:country":"GB",
    "sg:address":"52 Cowick Street",
    "sg:city":"Exeter",
    "sg:classifiers":[
        {
            "category":"Manufacturing",
            "subcategory":"Tools & Machinery",
            "type":"Manufacturing & Wholesale Goods"
        }
    ],
    "sg:phone":"+44 1392 219744",
    "sg:postcode":"EX4 1AP",
    "sg:province":"Devon",
    "sg:tags":[
        "society",
        "friendly"
    ],
    "wof:name":"Clatworthy & Webber",
    "wof:placetype":"venue"
},
  "geometry": {"coordinates":[-3.54318,50.715405],"type":"Point"}
}