{
  "type": "Feature",
  "properties": {
    "iso:country":"GB",
    "sg:address":"Unit 400, Montrose Ave, Slough Trad Est",
    "sg:city":"Slough",
    "sg:classifiers":[
        {
            "category":"Building & Trades",
            "subcategory":"Construction",
            "type":"Services"
        }
    ],
    "sg:postcode":"SL1 4TJ",
    "sg:province":"Berkshire",
    "sg:tags":[
        "restoration",
        "refurbishment"
    ],
    "wof:name":"I D Corporate Ltd",
    "wof:placetype":"venue"
},
  "geometry": {"coordinates":[-0.6177510023,51.5240936279],"type":"Point"}
}