{
  "type": "Feature",
  "properties": {
    "addr:full":"14 The Green London Greater London N21 1AY",
    "addr:housenumber":"14",
    "addr:postcode":"n21 1ay",
    "addr:street":"The Green",
    "iso:country":"GB",
    "sg:address":"14 The Green",
    "sg:city":"London",
    "sg:classifiers":[
        {
            "category":"Shopping",
            "subcategory":"Antiques",
            "type":"Retail Goods"
        }
    ],
    "sg:phone":"+44 20 8882 4800",
    "sg:postcode":"N21 1AY",
    "sg:province":"Greater London",
    "wof:name":"Winchmore Antiques",
    "wof:placetype":"venue"
},
  "geometry": {"coordinates":[-0.102318,51.634216],"type":"Point"}
}