{
  "type": "Feature",
  "properties": {
    "iso:country":"GB",
    "sg:address":"123 Main Street, Milngavie",
    "sg:city":"Glasgow",
    "sg:classifiers":[
        {
            "category":"Manufacturing",
            "subcategory":"Lumber",
            "type":"Manufacturing & Wholesale Goods"
        }
    ],
    "sg:phone":"+44 141 956 5183",
    "sg:postcode":"G62 6JA",
    "sg:province":"East Dunbartonshire",
    "sg:tags":[
        "merchant",
        "merchants",
        "importer",
        "agent",
        "timber"
    ],
    "wof:name":"Kelvin Timber (West) Ltd.",
    "wof:placetype":"venue"
},
  "geometry": {"coordinates":[-4.316209,55.932026],"type":"Point"}
}