{
  "type": "Feature",
  "properties": {
    "addr:full":"88 Holywell Close Farnborough Hampshire GU14 8TT",
    "addr:housenumber":"88",
    "addr:postcode":"gu14 8tt",
    "addr:street":"Holywell Close",
    "iso:country":"GB",
    "sg:address":"88 Holywell Close",
    "sg:city":"Farnborough",
    "sg:classifiers":[
        {
            "category":"Building & Trades",
            "subcategory":"Plumbing",
            "type":"Services"
        }
    ],
    "sg:phone":"+44 1252 546806",
    "sg:postcode":"GU14 8TT",
    "sg:province":"Hampshire",
    "sg:tags":[
        "plumber",
        "heating"
    ],
    "wof:name":"Arrow Plumbing & Heating",
    "wof:placetype":"venue"
},
  "geometry": {"coordinates":[-0.7623710036,51.3069763184],"type":"Point"}
}