{
  "type": "Feature",
  "properties": {
    "addr:full":"Old N C B Laboratories, Derllwyn Road, Tondu Bridgend Bridgend CF32 9HD",
    "addr:postcode":"cf32 9hd",
    "addr:street":"Old N C;Derllwyn Road",
    "iso:country":"GB",
    "sg:address":"Old N C B Laboratories, Derllwyn Road, Tondu",
    "sg:city":"Bridgend",
    "sg:classifiers":[
        {
            "category":"Manufacturing",
            "subcategory":"Glass & Minerals",
            "type":"Manufacturing & Wholesale Goods"
        }
    ],
    "sg:phone":"+44 1656 721520",
    "sg:postcode":"CF32 9HD",
    "sg:province":"Bridgend",
    "sg:tags":[
        "fibre",
        "moulding"
    ],
    "wof:name":"G G F",
    "wof:placetype":"venue"
},
  "geometry": {"coordinates":[-3.5998370647,51.5499343872],"type":"Point"}
}