{
  "type": "Feature",
  "properties": {
    "addr:full":"Raworth House, 36 Sydenham Road Croydon Surrey CR0 2EF",
    "addr:housenumber":"36",
    "addr:postcode":"cr0 2ef",
    "addr:street":"Sydenham Road",
    "iso:country":"GB",
    "sg:address":"Raworth House, 36 Sydenham Road",
    "sg:city":"Croydon",
    "sg:classifiers":[
        {
            "category":"Professional",
            "subcategory":"Lawyer & Legal Services",
            "type":"Services"
        },
        {
            "category":"Real Estate",
            "subcategory":"Real Estate Agent",
            "type":"Services"
        }
    ],
    "sg:phone":"+44 20 8688 8318",
    "sg:postcode":"CR0 2EF",
    "sg:province":"Surrey",
    "sg:tags":[
        "patent",
        "trademark"
    ],
    "wof:name":"Raworth Moss & Cook",
    "wof:placetype":"venue"
},
  "geometry": {"coordinates":[-0.0947439969,51.3798828125],"type":"Point"}
}