{
  "type": "Feature",
  "properties": {
    "addr:full":"Television Ho, 269 Field End Rd Ruislip Greater London HA4 9LS",
    "addr:housenumber":"269",
    "addr:postcode":"ha4 9ls",
    "addr:street":"Field End Rd",
    "iso:country":"GB",
    "sg:address":"Television Ho, 269 Field End Rd",
    "sg:city":"Ruislip",
    "sg:classifiers":[
        {
            "category":"Professional",
            "subcategory":"Business Services",
            "type":"Services"
        }
    ],
    "sg:phone":"+44 20 8868 4461",
    "sg:postcode":"HA4 9LS",
    "sg:province":"Greater London",
    "sg:tags":[
        "food",
        "import",
        "export",
        "agent"
    ],
    "wof:name":"American Snack Food",
    "wof:placetype":"venue"
},
  "geometry": {"coordinates":[-0.426279,51.575886],"type":"Point"}
}