{
  "type": "Feature",
  "properties": {
    "addr:full":"Castle Road Colchester Essex CO1 1UW",
    "addr:postcode":"co1 1uw",
    "addr:street":"Castle Road Colchester",
    "iso:country":"GB",
    "sg:address":"Castle Road",
    "sg:city":"Colchester",
    "sg:classifiers":[
        {
            "category":"Bars & Pubs",
            "type":"Food & Drink"
        }
    ],
    "sg:phone":"+44 1206 542646",
    "sg:postcode":"CO1 1UW",
    "sg:province":"Essex",
    "sg:tags":[
        "pubs",
        "inn"
    ],
    "wof:name":"The Foresters Arms",
    "wof:placetype":"venue"
},
  "geometry": {"coordinates":[0.9061329961,51.8915023804],"type":"Point"}
}