{
  "type": "Feature",
  "properties": {
    "addr:full":"2 Cavendish Court, Cardigan Road Richmond Greater London TW10 6BL",
    "addr:housenumber":"2",
    "addr:postcode":"tw10 6bl",
    "addr:street":"Cavendish Court Cardigan Road",
    "iso:country":"GB",
    "sg:address":"2 Cavendish Court, Cardigan Road",
    "sg:city":"Richmond",
    "sg:classifiers":[
        {
            "category":"Professional",
            "subcategory":"Accounting & Tax Preparation",
            "type":"Services"
        }
    ],
    "sg:postcode":"TW10 6BL",
    "sg:province":"Greater London",
    "sg:tags":[
        "accountant"
    ],
    "wof:name":"Lundin Accounting Ltd",
    "wof:placetype":"venue"
},
  "geometry": {"coordinates":[-0.299,51.45507],"type":"Point"}
}