{
  "type": "Feature",
  "properties": {
    "addr:full":"230 Northdown Road, Cliftonville Margate Kent CT9 2QD",
    "addr:housenumber":"230",
    "addr:postcode":"ct9 2qd",
    "addr:street":"Northdown Road;Margate",
    "iso:country":"GB",
    "sg:address":"230 Northdown Road, Cliftonville",
    "sg:city":"Margate",
    "sg:classifiers":[
        {
            "category":"Shopping",
            "subcategory":"Thrift Store",
            "type":"Retail Goods"
        }
    ],
    "sg:phone":"+44 1843 230069",
    "sg:postcode":"CT9 2QD",
    "sg:province":"Kent",
    "sg:tags":[
        "shop",
        "charity"
    ],
    "wof:name":"Sue Ryder Foundation",
    "wof:placetype":"venue"
},
  "geometry": {"coordinates":[1.3964099884,51.3879585266],"type":"Point"}
}