{
  "type": "Feature",
  "properties": {
    "addr:full":"3 Shortlands London Greater London W6 8EZ",
    "addr:housenumber":"3",
    "addr:postcode":"w6 8ez",
    "addr:street":"Shortlands",
    "iso:country":"GB",
    "sg:address":"3 Shortlands",
    "sg:city":"London",
    "sg:classifiers":[
        {
            "category":"Building & Trades",
            "subcategory":"Construction",
            "type":"Services"
        }
    ],
    "sg:phone":"+44 20 8748 2000",
    "sg:postcode":"W6 8EZ",
    "sg:province":"Greater London",
    "sg:tags":[
        "builder"
    ],
    "wof:name":"McLean Homes Southern Ltd.",
    "wof:placetype":"venue"
},
  "geometry": {"coordinates":[-0.219564,51.492577],"type":"Point"}
}