{
  "type": "Feature",
  "properties": {
    "iso:country":"GB",
    "sg:address":"154 Commercial Rd",
    "sg:city":"Whitechapel",
    "sg:classifiers":[
        {
            "category":"Autos & Motor Vehicles",
            "subcategory":"Motorcycle Sales",
            "type":"Retail Goods"
        }
    ],
    "sg:phone":"+44 20 7702 9292",
    "sg:postcode":"E1 1NL",
    "sg:province":"Greater London",
    "sg:tags":[
        "chauffeur",
        "driven",
        "car"
    ],
    "wof:name":"City Express Car Service",
    "wof:placetype":"venue"
},
  "geometry": {"coordinates":[-0.0623290017,51.5147514343],"type":"Point"}
}