{
  "type": "Feature",
  "properties": {
    "addr:full":"16 St John Street Perth Perth and Kinross PH1 5SP",
    "addr:housenumber":"16",
    "addr:postcode":"ph1 5sp",
    "addr:street":"St John Street",
    "iso:country":"GB",
    "sg:address":"16 St John Street",
    "sg:city":"Perth",
    "sg:classifiers":[
        {
            "category":"Food & Beverages",
            "subcategory":"Specialty",
            "type":"Retail Goods"
        }
    ],
    "sg:phone":"+44 1738 628102",
    "sg:postcode":"PH1 5SP",
    "sg:province":"Perth and Kinross",
    "sg:tags":[
        "product",
        "health"
    ],
    "wof:name":"Highland Health Store",
    "wof:placetype":"venue"
},
  "geometry": {"coordinates":[-3.427264,56.396545],"type":"Point"}
}