{
  "type": "Feature",
  "properties": {
    "iso:country":"GB",
    "sg:address":"59 Eastfield Side",
    "sg:city":"Sutton-in-ashfield",
    "sg:classifiers":[
        {
            "category":"Professional",
            "subcategory":"Engineering",
            "type":"Services"
        }
    ],
    "sg:phone":"+44 1623 551954",
    "sg:postcode":"NG17 4JW",
    "sg:province":"Nottinghamshire",
    "sg:tags":[
        "precision",
        "engineer"
    ],
    "wof:name":"Ashfield Precision Engineering Ltd.",
    "wof:placetype":"venue"
},
  "geometry": {"coordinates":[-1.247771,53.131191],"type":"Point"}
}