{
  "type": "Feature",
  "properties": {
    "iso:country":"GB",
    "sg:address":"17 Creswick Way",
    "sg:city":"Burnham-on-sea",
    "sg:classifiers":[
        {
            "category":"Building & Trades",
            "subcategory":"Landscaping Services",
            "type":"Services"
        }
    ],
    "sg:phone":"+44 1278 784445",
    "sg:postcode":"TA8 2EH",
    "sg:province":"Somerset",
    "sg:tags":[
        "gardening"
    ],
    "wof:name":"J R C Garden Landscapes",
    "wof:placetype":"venue"
},
  "geometry": {"coordinates":[-2.985989,51.244453],"type":"Point"}
}