{
  "type": "Feature",
  "properties": {
    "addr:full":"Braxted Park Witham Essex CM8 3EN",
    "addr:postcode":"cm8 3en",
    "addr:street":"Park",
    "iso:country":"GB",
    "sg:address":"Braxted Park",
    "sg:city":"Witham",
    "sg:classifiers":[
        {
            "category":"Personal",
            "type":"Services"
        },
        {
            "category":"Sports & Exercise",
            "subcategory":"Golf",
            "type":"Entertainment"
        }
    ],
    "sg:phone":"+44 1621 892305",
    "sg:postcode":"CM8 3EN",
    "sg:province":"Essex",
    "sg:tags":[
        "club",
        "course",
        "wedding"
    ],
    "wof:name":"Braxted Park Estate",
    "wof:placetype":"venue"
},
  "geometry": {"coordinates":[0.7018229961,51.7937965393],"type":"Point"}
}