{
  "type": "Feature",
  "properties": {
    "iso:country":"GB",
    "sg:address":"Hereford Road",
    "sg:city":"Shrewsbury",
    "sg:classifiers":[
        {
            "category":"Autos & Motor Vehicles",
            "subcategory":"Auto Supplies",
            "type":"Retail Goods"
        }
    ],
    "sg:phone":"+44 1743 355851",
    "sg:postcode":"SY3 7QZ",
    "sg:province":"Shropshire",
    "sg:tags":[
        "caravan",
        "accessory"
    ],
    "wof:name":"Salop Caravans Ltd.",
    "wof:placetype":"venue"
},
  "geometry": {"coordinates":[-2.751425,52.696369],"type":"Point"}
}