{
  "type": "Feature",
  "properties": {
    "iso:country":"GB",
    "sg:address":"17a High Street",
    "sg:city":"Gosport",
    "sg:classifiers":[
        {
            "category":"Recreation",
            "type":"Entertainment"
        }
    ],
    "sg:phone":"+44 23 9252 5022",
    "sg:postcode":"PO12 1BX",
    "sg:province":"Hampshire",
    "sg:tags":[
        "snooker",
        "billiards",
        "hall",
        "pool"
    ],
    "wof:name":"147 Snooker Club",
    "wof:placetype":"venue"
},
  "geometry": {"coordinates":[-1.125223,50.794983],"type":"Point"}
}