{
  "type": "Feature",
  "properties": {
    "addr:full":"3 Bradenham Walk Aylesbury Buckinghamshire HP21 9DZ",
    "addr:housenumber":"3",
    "addr:postcode":"hp21 9dz",
    "addr:street":"Bradenham Walk",
    "iso:country":"GB",
    "sg:address":"3 Bradenham Walk",
    "sg:city":"Aylesbury",
    "sg:classifiers":[
        {
            "category":"Wholesale",
            "subcategory":"Vending Machines",
            "type":"Manufacturing & Wholesale Goods"
        }
    ],
    "sg:phone":"+44 1296 337026",
    "sg:postcode":"HP21 9DZ",
    "sg:province":"Buckinghamshire",
    "sg:tags":[
        "business"
    ],
    "wof:name":"Equipment Exchange Ltd",
    "wof:placetype":"venue"
},
  "geometry": {"coordinates":[-0.8052530289,51.7962188721],"type":"Point"}
}