{
  "type": "Feature",
  "properties": {
    "addr:full":"21 Market Row London Greater London SW9 8LB",
    "addr:housenumber":"21",
    "addr:postcode":"sw9 8lb",
    "addr:street":"Market Row",
    "iso:country":"GB",
    "sg:address":"21 Market Row",
    "sg:city":"London",
    "sg:classifiers":[
        {
            "category":"Shopping",
            "subcategory":"Gifts & Souvenirs",
            "type":"Retail Goods"
        }
    ],
    "sg:postcode":"SW9 8LB",
    "sg:province":"Greater London",
    "sg:tags":[
        "poster",
        "card"
    ],
    "wof:name":"Michelle Gibbs",
    "wof:placetype":"venue"
},
  "geometry": {"coordinates":[-0.113649,51.461979],"type":"Point"}
}