{
  "type": "Feature",
  "properties": {
    "addr:full":"279c Finchley Road London Greater London NW3 6LY",
    "addr:housenumber":"279c",
    "addr:postcode":"nw3 6ly",
    "addr:street":"Finchley Road",
    "iso:country":"GB",
    "sg:address":"279c Finchley Road",
    "sg:city":"London",
    "sg:classifiers":[
        {
            "category":"Restaurant",
            "type":"Food & Drink"
        }
    ],
    "sg:phone":"+44 20 7435 2188",
    "sg:postcode":"NW3 6LY",
    "sg:province":"Greater London",
    "sg:tags":[
        "oriental"
    ],
    "wof:name":"Singapore Orchard",
    "wof:placetype":"venue"
},
  "geometry": {"coordinates":[-0.181532,51.549126],"type":"Point"}
}