{
  "type": "Feature",
  "properties": {
    "iso:country":"GB",
    "sg:address":"Langleybury Lane",
    "sg:city":"King's Langley",
    "sg:classifiers":[
        {
            "category":"Farming",
            "subcategory":"Livestock Farm",
            "type":"Manufacturing & Wholesale Goods"
        }
    ],
    "sg:phone":"+44 1923 264773",
    "sg:postcode":"WD4 8RW",
    "sg:province":"Hertfordshire",
    "sg:tags":[
        "others"
    ],
    "wof:name":"Berry Bushes Farm",
    "wof:placetype":"venue"
},
  "geometry": {"coordinates":[-0.4454300106,51.6901283264],"type":"Point"}
}