{
  "type": "Feature",
  "properties": {
    "addr:full":"Hursts Yard, Rear Of 3 Bank Street, Cheadle Stoke-on-trent Staffordshire ST10 1NR",
    "addr:housenumber":"3",
    "addr:postcode":"st10 1nr",
    "addr:street":"Rear Of;Bank Street Cheadle",
    "iso:country":"GB",
    "sg:address":"Hursts Yard, Rear Of 3 Bank Street, Cheadle",
    "sg:city":"Stoke-on-trent",
    "sg:classifiers":[
        {
            "category":"Retail",
            "subcategory":"Auto Repair",
            "type":"Services"
        }
    ],
    "sg:postcode":"ST10 1NR",
    "sg:province":"Staffordshire",
    "sg:tags":[
        "body",
        "car"
    ],
    "wof:name":"Manifold Motors",
    "wof:placetype":"venue"
},
  "geometry": {"coordinates":[-1.987234,52.988312],"type":"Point"}
}