{
  "type": "Feature",
  "properties": {
    "iso:country":"GB",
    "sg:address":"Unit 46 Atcham Industrial Estate, Atcham",
    "sg:city":"Shrewsbury",
    "sg:classifiers":[
        {
            "category":"Professional",
            "type":"Services"
        }
    ],
    "sg:phone":"+44 1743 761100",
    "sg:postcode":"SY4 4UG",
    "sg:province":"Shropshire",
    "sg:tags":[
        "exhibition"
    ],
    "wof:name":"Quartz Presentations",
    "wof:placetype":"venue"
},
  "geometry": {"coordinates":[-2.636718,52.68829],"type":"Point"}
}