{
  "type": "Feature",
  "properties": {
    "iso:country":"GB",
    "sg:address":"Unit3 Harleston St",
    "sg:city":"Sheffield",
    "sg:classifiers":[
        {
            "category":"Home & Garden",
            "subcategory":"Home Furnishings",
            "type":"Retail Goods"
        }
    ],
    "sg:phone":"+44 114 272 9865",
    "sg:postcode":"S4 7QB",
    "sg:province":"South Yorkshire",
    "sg:tags":[
        "furnishers",
        "planner",
        "bedroom"
    ],
    "wof:name":"J A Horne - Starlight",
    "wof:placetype":"venue"
},
  "geometry": {"coordinates":[-1.4513,53.3951],"type":"Point"}
}