{
  "type": "Feature",
  "properties": {
    "addr:full":"Gravel Pit Farm, Foston York North Yorkshire YO60 7QD",
    "addr:postcode":"yo60 7qd",
    "iso:country":"GB",
    "sg:address":"Gravel Pit Farm, Foston",
    "sg:city":"York",
    "sg:classifiers":[
        {
            "category":"Personal",
            "subcategory":"Adult",
            "type":"Services"
        }
    ],
    "sg:postcode":"YO60 7QD",
    "sg:province":"North Yorkshire",
    "sg:tags":[
        "equestrian"
    ],
    "wof:name":"C B B Booth",
    "wof:placetype":"venue"
},
  "geometry": {"coordinates":[-0.9354940057,54.0774307251],"type":"Point"}
}