{
  "type": "Feature",
  "properties": {
    "iso:country":"GB",
    "sg:address":"P O Box 20, Alldridge",
    "sg:city":"Walsall",
    "sg:classifiers":[
        {
            "category":"Banks & Credit Unions",
            "subcategory":"Financial Services",
            "type":"Services"
        }
    ],
    "sg:phone":"+44 1922 453900",
    "sg:postcode":"WS9 8YR",
    "sg:province":"Staffordshire",
    "sg:tags":[
        "consultant"
    ],
    "wof:name":"Cathedral Finance Co. Ltd.",
    "wof:placetype":"venue"
},
  "geometry": {"coordinates":[-1.920439,52.609718],"type":"Point"}
}