{
  "type": "Feature",
  "properties": {
    "iso:country":"GB",
    "sg:address":"3a Fishwifes Causeway",
    "sg:city":"Edinburgh",
    "sg:classifiers":[
        {
            "category":"Home & Garden",
            "subcategory":"Building Materials",
            "type":"Retail Goods"
        }
    ],
    "sg:phone":"+44 131 657 2157",
    "sg:postcode":"EH15 1DF",
    "sg:province":"City of Edinburgh",
    "sg:tags":[
        "brick"
    ],
    "wof:name":"Alpha Marble Importers",
    "wof:placetype":"venue"
},
  "geometry": {"coordinates":[-3.119455,55.955429],"type":"Point"}
}