{
  "type": "Feature",
  "properties": {
    "addr:full":"30a Stoughton Drive North Leicester Leicestershire LE5 5UB",
    "addr:housenumber":"30a",
    "addr:postcode":"le5 5ub",
    "addr:street":"Stoughton Drive North",
    "iso:country":"GB",
    "sg:address":"30a Stoughton Drive North",
    "sg:city":"Leicester",
    "sg:classifiers":[
        {
            "category":"Autos & Motor Vehicles",
            "subcategory":"Automobile Sales",
            "type":"Retail Goods"
        }
    ],
    "sg:postcode":"LE5 5UB",
    "sg:province":"Leicestershire",
    "sg:tags":[
        "car"
    ],
    "wof:name":"Clarke,Paul,",
    "wof:placetype":"venue"
},
  "geometry": {"coordinates":[-1.101584,52.622028],"type":"Point"}
}