{
  "type": "Feature",
  "properties": {
    "addr:full":"10 West Road Congleton Cheshire CW12 4ER",
    "addr:housenumber":"10",
    "addr:postcode":"cw12 4er",
    "addr:street":"West Road",
    "iso:country":"GB",
    "sg:address":"10 West Road",
    "sg:city":"Congleton",
    "sg:classifiers":[
        {
            "category":"Shopping",
            "type":"Retail Goods"
        }
    ],
    "sg:postcode":"CW12 4ER",
    "sg:province":"Cheshire",
    "sg:tags":[
        "part",
        "accessory"
    ],
    "wof:name":"L A C Autoparts",
    "wof:placetype":"venue"
},
  "geometry": {"coordinates":[-2.2212510109,53.1646385193],"type":"Point"}
}