{
  "type": "Feature",
  "properties": {
    "iso:country":"GB",
    "sg:address":"72 Sydney Road",
    "sg:city":"Watford",
    "sg:classifiers":[
        {
            "category":"Manufacturing",
            "subcategory":"Metals",
            "type":"Manufacturing & Wholesale Goods"
        }
    ],
    "sg:phone":"+44 1923 211116",
    "sg:postcode":"WD18 7PX",
    "sg:province":"Hertfordshire",
    "wof:name":"B & S Polishing",
    "wof:placetype":"venue"
},
  "geometry": {"coordinates":[-0.4187699854,51.6505775452],"type":"Point"}
}