{
  "type": "Feature",
  "properties": {
    "iso:country":"GB",
    "sg:address":"24 Wharf Street",
    "sg:city":"Sowerby Bridge",
    "sg:classifiers":[
        {
            "category":"Food & Beverages",
            "subcategory":"Meat & Fish",
            "type":"Retail Goods"
        }
    ],
    "sg:phone":"+44 1422 839511",
    "sg:postcode":"HX6 2AE",
    "sg:province":"West Yorkshire",
    "sg:tags":[
        "chip"
    ],
    "wof:name":"Central Fisheries",
    "wof:placetype":"venue"
},
  "geometry": {"coordinates":[-1.908087,53.709209],"type":"Point"}
}