{
  "type": "Feature",
  "properties": {
    "iso:country":"GB",
    "sg:address":"2 Emersons Avenue",
    "sg:city":"Swanley",
    "sg:classifiers":[
        {
            "category":"Banks & Credit Unions",
            "subcategory":"Investment Brokerage",
            "type":"Services"
        }
    ],
    "sg:phone":"+44 1322 665657",
    "sg:postcode":"BR8 7WS",
    "sg:province":"Kent",
    "wof:name":"P D Wheatley",
    "wof:placetype":"venue"
},
  "geometry": {"coordinates":[0.182948,51.4095],"type":"Point"}
}