{
  "type": "Feature",
  "properties": {
    "addr:full":"9 Market Street, Atherton Manchester Greater Manchester M46 0DW",
    "addr:housenumber":"9",
    "addr:postcode":"m46 0dw",
    "addr:street":"Market Street",
    "iso:country":"GB",
    "sg:address":"9 Market Street, Atherton",
    "sg:city":"Manchester",
    "sg:classifiers":[
        {
            "category":"Home & Garden",
            "subcategory":"Carpets & Floor Coverings",
            "type":"Retail Goods"
        }
    ],
    "sg:postcode":"M46 0DW",
    "sg:province":"Greater Manchester",
    "sg:tags":[
        "carpets",
        "rug",
        "matting"
    ],
    "wof:name":"Custom Carpet",
    "wof:placetype":"venue"
},
  "geometry": {"coordinates":[-2.490868,53.523766],"type":"Point"}
}