{
  "type": "Feature",
  "properties": {
    "addr:full":"19-21 Pancras Road London Greater London NW1 2QB",
    "addr:housenumber":"19-21",
    "addr:postcode":"nw1 2qb",
    "addr:street":"Pancras Road",
    "iso:country":"GB",
    "sg:address":"19-21 Pancras Road",
    "sg:city":"London",
    "sg:classifiers":[
        {
            "category":"Autos & Motor Vehicles",
            "subcategory":"Automobile Sales",
            "type":"Retail Goods"
        }
    ],
    "sg:postcode":"NW1 2QB",
    "sg:province":"Greater London",
    "sg:tags":[
        "car"
    ],
    "wof:name":"London Taxi Market",
    "wof:placetype":"venue"
},
  "geometry": {"coordinates":[-0.1246860027,51.5307006836],"type":"Point"}
}