{
  "type": "Feature",
  "properties": {
    "iso:country":"GB",
    "sg:address":"23 Chieveley Clo, Etchinghill",
    "sg:city":"Rugeley",
    "sg:classifiers":[
        {
            "category":"Transit Center",
            "subcategory":"Passenger",
            "type":"Transportation"
        }
    ],
    "sg:postcode":"WS15 2TF",
    "sg:province":"Staffordshire",
    "sg:tags":[
        "airport"
    ],
    "wof:name":"P & B Travel",
    "wof:placetype":"venue"
},
  "geometry": {"coordinates":[-1.9535599947,52.76197052],"type":"Point"}
}