{
  "type": "Feature",
  "properties": {
    "iso:country":"GB",
    "sg:address":"28 New Cavendish Street",
    "sg:city":"London",
    "sg:classifiers":[
        {
            "category":"Fast Food",
            "type":"Food & Drink"
        }
    ],
    "sg:phone":"+44 20 7487 3623",
    "sg:postcode":"W1G 8TZ",
    "sg:province":"Greater London",
    "sg:tags":[
        "away",
        "take"
    ],
    "wof:name":"The Cavendish Sandwich Bar",
    "wof:placetype":"venue"
},
  "geometry": {"coordinates":[-0.15036,51.518665],"type":"Point"}
}