{
  "type": "Feature",
  "properties": {
    "iso:country":"GB",
    "sg:address":"Unit 2b Colmworth Business Park, Off Great North Road, Eaton Socan",
    "sg:city":"St Neots",
    "sg:classifiers":[
        {
            "category":"Freight",
            "type":"Transportation"
        }
    ],
    "sg:phone":"+44 1480 211194",
    "sg:postcode":"PE19 8YH",
    "sg:province":"Bedfordshire",
    "sg:tags":[
        "haulage",
        "road"
    ],
    "wof:name":"Himelink Ltd.",
    "wof:placetype":"venue"
},
  "geometry": {"coordinates":[-0.2916,52.220402],"type":"Point"}
}