{
  "type": "Feature",
  "properties": {
    "addr:full":"Rudland House, Railway Street Bishop Auckland Durham DL14 7LR",
    "addr:postcode":"dl14 7lr",
    "addr:street":"Railway Street",
    "iso:country":"GB",
    "sg:address":"Rudland House, Railway Street",
    "sg:city":"Bishop Auckland",
    "sg:classifiers":[
        {
            "category":"Utilities",
            "subcategory":"Natural Gas",
            "type":"Services"
        }
    ],
    "sg:phone":"+44 1388 603793",
    "sg:postcode":"DL14 7LR",
    "sg:province":"Durham",
    "sg:tags":[
        "supplier"
    ],
    "wof:name":"M G Calor Drinks Dispense Service",
    "wof:placetype":"venue"
},
  "geometry": {"coordinates":[-1.6756540537,54.6591186523],"type":"Point"}
}