{
  "type": "Feature",
  "properties": {
    "iso:country":"GB",
    "sg:address":"35 Greenleafe Drive",
    "sg:city":"Ilford",
    "sg:classifiers":[
        {
            "category":"Travel",
            "subcategory":"Travel Agent",
            "type":"Entertainment"
        }
    ],
    "sg:phone":"+44 20 8220 5484",
    "sg:postcode":"IG6 1LN",
    "sg:province":"Essex",
    "wof:name":"Geoff Moss",
    "wof:placetype":"venue"
},
  "geometry": {"coordinates":[0.074645,51.587749],"type":"Point"}
}