{
  "type": "Feature",
  "properties": {
    "iso:country":"GB",
    "sg:address":"552 London Road",
    "sg:city":"Isleworth",
    "sg:classifiers":[
        {
            "category":"Restaurant",
            "type":"Food & Drink"
        }
    ],
    "sg:phone":"+44 20 8560 8284",
    "sg:postcode":"TW7 4EP",
    "sg:province":"Greater London",
    "sg:tags":[
        "indian"
    ],
    "wof:name":"Khyber Pass",
    "wof:placetype":"venue"
},
  "geometry": {"coordinates":[-0.344297,51.474377],"type":"Point"}
}