{
  "type": "Feature",
  "properties": {
    "iso:country":"GB",
    "sg:address":"Hilliers Garden Centre, Farnham Road",
    "sg:city":"Liss",
    "sg:classifiers":[
        {
            "category":"Education",
            "subcategory":"Music School",
            "type":"Public Place"
        }
    ],
    "sg:postcode":"GU33 6LJ",
    "sg:province":"Hampshire",
    "sg:tags":[
        "conservatory"
    ],
    "wof:name":"Creative Conservatories",
    "wof:placetype":"venue"
},
  "geometry": {"coordinates":[-0.8926500082,51.0430259705],"type":"Point"}
}