{
  "type": "Feature",
  "properties": {
    "addr:full":"65 Great Stone Road, Stretford Manchester Cheshire M32 8GR",
    "addr:housenumber":"65",
    "addr:postcode":"m32 8gr",
    "addr:street":"Great Stone Road",
    "iso:country":"GB",
    "sg:address":"65 Great Stone Road, Stretford",
    "sg:city":"Manchester",
    "sg:classifiers":[
        {
            "category":"Fast Food",
            "type":"Food & Drink"
        }
    ],
    "sg:phone":"+44 161 862 9284",
    "sg:postcode":"M32 8GR",
    "sg:province":"Cheshire",
    "sg:tags":[
        "away",
        "take"
    ],
    "wof:name":"Four Ways",
    "wof:placetype":"venue"
},
  "geometry": {"coordinates":[-2.2868199348,53.4530677795],"type":"Point"}
}