{
  "type": "Feature",
  "properties": {
    "iso:country":"GB",
    "sg:address":"95 Market Stalls",
    "sg:city":"Plymouth",
    "sg:classifiers":[
        {
            "category":"Food & Beverages",
            "subcategory":"Bakery",
            "type":"Retail Goods"
        }
    ],
    "sg:postcode":"PL1 1PR",
    "sg:province":"Devon",
    "sg:tags":[
        "baker"
    ],
    "wof:name":"Passey,V S,",
    "wof:placetype":"venue"
},
  "geometry": {"coordinates":[-4.147079,50.372261],"type":"Point"}
}