{
  "type": "Feature",
  "properties": {
    "addr:full":"Church House Surgery, 3 Church Pass, Wood St Barnet Hertfordshire EN5 4QS",
    "addr:housenumber":"3",
    "addr:postcode":"en5 4qs",
    "addr:street":"Church Pass Wood St",
    "iso:country":"GB",
    "sg:address":"Church House Surgery, 3 Church Pass, Wood St",
    "sg:city":"Barnet",
    "sg:classifiers":[
        {
            "category":"Health Services",
            "subcategory":"Doctor",
            "type":"Services"
        }
    ],
    "sg:phone":"+44 20 8449 9622",
    "sg:postcode":"EN5 4QS",
    "sg:province":"Hertfordshire",
    "sg:tags":[
        "practitioners"
    ],
    "wof:name":"Ranasinghe, N",
    "wof:placetype":"venue"
},
  "geometry": {"coordinates":[-0.2049989998,51.6587257385],"type":"Point"}
}