{
  "type": "Feature",
  "properties": {
    "addr:full":"5 Cavendish Street Ipswich Suffolk IP3 8AX",
    "addr:housenumber":"5",
    "addr:postcode":"ip3 8ax",
    "addr:street":"Cavendish Street",
    "iso:country":"GB",
    "sg:address":"5 Cavendish Street",
    "sg:city":"Ipswich",
    "sg:classifiers":[
        {
            "category":"Wholesale",
            "subcategory":"Electrical",
            "type":"Manufacturing & Wholesale Goods"
        },
        {
            "category":"Shopping",
            "subcategory":"Computers & Home Electronics",
            "type":"Retail Goods"
        }
    ],
    "sg:phone":"+44 1473 230404",
    "sg:postcode":"IP3 8AX",
    "sg:province":"Suffolk",
    "sg:tags":[
        "wholesaler"
    ],
    "wof:name":"Newey & Eyre Ltd.",
    "wof:placetype":"venue"
},
  "geometry": {"coordinates":[1.1684420109,52.0512695312],"type":"Point"}
}