{
  "type": "Feature",
  "properties": {
    "addr:full":"9 Park Hill London Greater London SW4 9NS",
    "addr:housenumber":"9",
    "addr:postcode":"sw4 9ns",
    "addr:street":"Park",
    "iso:country":"GB",
    "sg:address":"9 Park Hill",
    "sg:city":"London",
    "sg:classifiers":[
        {
            "category":"Real Estate",
            "subcategory":"Surveying",
            "type":"Services"
        }
    ],
    "sg:phone":"+44 20 7978 2140",
    "sg:postcode":"SW4 9NS",
    "sg:province":"Greater London",
    "sg:tags":[
        "surveyor",
        "land"
    ],
    "wof:name":"John Foord & Co.",
    "wof:placetype":"venue"
},
  "geometry": {"coordinates":[-0.1331119984,51.4589500427],"type":"Point"}
}