{
  "type": "Feature",
  "properties": {
    "iso:country":"GB",
    "sg:address":"Coate",
    "sg:city":"Swindon",
    "sg:classifiers":[
        {
            "category":"Professional",
            "subcategory":"Engineering",
            "type":"Services"
        }
    ],
    "sg:phone":"+44 1793 614494",
    "sg:postcode":"SN3 6AA",
    "sg:province":"Wiltshire",
    "sg:tags":[
        "precision",
        "engineer"
    ],
    "wof:name":"Chapel Engineering",
    "wof:placetype":"venue"
},
  "geometry": {"coordinates":[-1.7337299585,51.5432395935],"type":"Point"}
}