{
  "type": "Feature",
  "properties": {
    "iso:country":"GB",
    "sg:address":"Unit 2 & 3 Boarshaw Trading Estate, Boarshaw Road, Middleton",
    "sg:city":"Manchester",
    "sg:classifiers":[
        {
            "category":"Professional",
            "subcategory":"Engineering",
            "type":"Services"
        }
    ],
    "sg:phone":"+44 161 653 8705",
    "sg:postcode":"M24 6EQ",
    "sg:province":"Greater Manchester",
    "sg:tags":[
        "contractor",
        "electrical",
        "engineer"
    ],
    "wof:name":"Hazleden Electrical Co",
    "wof:placetype":"venue"
},
  "geometry": {"coordinates":[-2.19719,53.561432],"type":"Point"}
}