{
  "type": "Feature",
  "properties": {
    "addr:full":"Trevena Terrace Newquay Cornwall TR7 1LD",
    "addr:postcode":"tr7 1ld",
    "addr:street":"Trevena Terrace",
    "iso:country":"GB",
    "sg:address":"Trevena Terrace",
    "sg:city":"Newquay",
    "sg:classifiers":[
        {
            "category":"Organizations",
            "subcategory":"Membership Organization",
            "type":"Services"
        }
    ],
    "sg:phone":"+44 1637 872461",
    "sg:postcode":"TR7 1LD",
    "sg:province":"Cornwall",
    "sg:tags":[
        "club"
    ],
    "wof:name":"Royal British Legion Club Newquay Ltd.",
    "wof:placetype":"venue"
},
  "geometry": {"coordinates":[-5.088989,50.414715],"type":"Point"}
}