{
  "type": "Feature",
  "properties": {
    "addr:full":"36 Glenburn Road, College Milton North, East Kilbride Glasgow South Lanarkshire G74 5BA",
    "addr:housenumber":"36",
    "addr:postcode":"g74 5ba",
    "addr:street":"Glenburn Road;East",
    "iso:country":"GB",
    "sg:address":"36 Glenburn Road, College Milton North, East Kilbride",
    "sg:city":"Glasgow",
    "sg:classifiers":[
        {
            "category":"Shopping",
            "subcategory":"Clothing, Apparel, & Fashions",
            "type":"Retail Goods"
        },
        {
            "category":"Shopping",
            "type":"Retail Goods"
        }
    ],
    "sg:phone":"+44 1355 222273",
    "sg:postcode":"G74 5BA",
    "sg:province":"South Lanarkshire",
    "sg:tags":[
        "equipment",
        "workwear",
        "protective",
        "safety",
        "clothing"
    ],
    "wof:name":"Corton Sinclair Ltd",
    "wof:placetype":"venue"
},
  "geometry": {"coordinates":[-4.2164859772,55.770198822],"type":"Point"}
}