{
  "type": "Feature",
  "properties": {
    "iso:country":"GB",
    "sg:address":"Frances Street",
    "sg:city":"Truro",
    "sg:classifiers":[
        {
            "category":"Bars & Pubs",
            "type":"Food & Drink"
        }
    ],
    "sg:postcode":"TR1 3DP",
    "sg:province":"Cornwall",
    "sg:tags":[
        "pubs",
        "inn"
    ],
    "wof:name":"The Wig & Pen",
    "wof:placetype":"venue"
},
  "geometry": {"coordinates":[-5.055929,50.263615],"type":"Point"}
}