{
  "type": "Feature",
  "properties": {
    "iso:country":"GB",
    "sg:address":"20 Waverley Terrace",
    "sg:city":"Shildon",
    "sg:classifiers":[
        {
            "category":"Personal",
            "type":"Services"
        }
    ],
    "sg:postcode":"DL4 2HQ",
    "sg:province":"Durham",
    "sg:tags":[
        "consultant",
        "fitness"
    ],
    "wof:name":"Tony Pearson Health & Fitness Consultant",
    "wof:placetype":"venue"
},
  "geometry": {"coordinates":[-1.651709,54.628571],"type":"Point"}
}