{
  "type": "Feature",
  "properties": {
    "addr:full":"6 The Balustrade, London Road Bath Bath and North East Somerset BA1 6QA",
    "addr:housenumber":"6",
    "addr:postcode":"ba1 6qa",
    "addr:street":"The Balustrade London Road",
    "iso:country":"GB",
    "sg:address":"6 The Balustrade, London Road",
    "sg:city":"Bath",
    "sg:classifiers":[
        {
            "category":"Shopping",
            "type":"Retail Goods"
        }
    ],
    "sg:postcode":"BA1 6QA",
    "sg:province":"Bath and North East Somerset",
    "sg:tags":[
        "part",
        "accessory"
    ],
    "wof:name":"London Road Motor Spares",
    "wof:placetype":"venue"
},
  "geometry": {"coordinates":[-2.34719,51.394001],"type":"Point"}
}