{
  "type": "Feature",
  "properties": {
    "addr:full":"35a Brookfield Road London Greater London E9 5AH",
    "addr:housenumber":"35a",
    "addr:postcode":"e9 5ah",
    "addr:street":"Brookfield Road",
    "iso:country":"GB",
    "sg:address":"35a Brookfield Road",
    "sg:city":"London",
    "sg:classifiers":[
        {
            "category":"Taxi",
            "type":"Transportation"
        },
        {
            "category":"Military Area",
            "subcategory":"Air Force Base",
            "type":"Public Place"
        }
    ],
    "sg:phone":"+44 20 8985 7261",
    "sg:postcode":"E9 5AH",
    "sg:province":"Greater London",
    "sg:tags":[
        "mini",
        "hire",
        "private",
        "cab"
    ],
    "wof:name":"Kwick Cars",
    "wof:placetype":"venue"
},
  "geometry": {"coordinates":[-0.035866,51.54493],"type":"Point"}
}