{
  "type": "Feature",
  "properties": {
    "iso:country":"GB",
    "sg:address":"45 Barn Drive",
    "sg:city":"Maidenhead",
    "sg:classifiers":[
        {
            "category":"Professional",
            "subcategory":"Printing & Photocopies",
            "type":"Services"
        }
    ],
    "sg:phone":"+44 1628 680881",
    "sg:postcode":"SL6 3PR",
    "sg:province":"Berkshire",
    "sg:tags":[
        "tag",
        "label"
    ],
    "wof:name":"Lancer Labels",
    "wof:placetype":"venue"
},
  "geometry": {"coordinates":[-0.7615259886,51.508895874],"type":"Point"}
}