{
  "type": "Feature",
  "properties": {
    "addr:full":"Devonshire Buildings, Works Road, Hollingwood Chesterfield Derbyshire S43 2PE",
    "addr:postcode":"s43 2pe",
    "addr:street":"Works Road",
    "iso:country":"GB",
    "sg:address":"Devonshire Buildings, Works Road, Hollingwood",
    "sg:city":"Chesterfield",
    "sg:classifiers":[
        {
            "category":"Sports & Exercise",
            "subcategory":"Gym",
            "type":"Entertainment"
        }
    ],
    "sg:phone":"+44 1246 471041",
    "sg:postcode":"S43 2PE",
    "sg:province":"Derbyshire",
    "sg:tags":[
        "fitness",
        "health",
        "centre"
    ],
    "wof:name":"Body Base Gym",
    "wof:placetype":"venue"
},
  "geometry": {"coordinates":[-1.376959,53.263435],"type":"Point"}
}