{
  "type": "Feature",
  "properties": {
    "addr:full":"16 East Street Sittingbourne Kent ME10 4RT",
    "addr:housenumber":"16",
    "addr:postcode":"me10 4rt",
    "addr:street":"East Street",
    "iso:country":"GB",
    "sg:address":"16 East Street",
    "sg:city":"Sittingbourne",
    "sg:classifiers":[
        {
            "category":"Personal",
            "subcategory":"Beauty Salon",
            "type":"Services"
        },
        {
            "category":"Personal",
            "subcategory":"Barber",
            "type":"Services"
        }
    ],
    "sg:phone":"+44 1795 426070",
    "sg:postcode":"ME10 4RT",
    "sg:province":"Kent",
    "sg:tags":[
        "unisex",
        "hairdresser"
    ],
    "wof:name":"Hairzone 16",
    "wof:placetype":"venue"
},
  "geometry": {"coordinates":[0.741248,51.339001],"type":"Point"}
}