{
  "type": "Feature",
  "properties": {
    "addr:full":"65 The Oaks, Burrage Road London Greater London SE18 7JS",
    "addr:housenumber":"65",
    "addr:postcode":"se18 7js",
    "addr:street":"The Oaks Burrage Road",
    "iso:country":"GB",
    "sg:address":"65 The Oaks, Burrage Road",
    "sg:city":"London",
    "sg:classifiers":[
        {
            "category":"Retail",
            "subcategory":"Driving School",
            "type":"Services"
        }
    ],
    "sg:postcode":"SE18 7JS",
    "sg:province":"Greater London",
    "wof:name":"Malcolm Clark School of Motoring",
    "wof:placetype":"venue"
},
  "geometry": {"coordinates":[0.074188,51.482723],"type":"Point"}
}