{
  "type": "Feature",
  "properties": {
    "addr:full":"6 Glendale Avenue Edgware Greater London HA8 8HG",
    "addr:housenumber":"6",
    "addr:postcode":"ha8 8hg",
    "addr:street":"Glendale Avenue",
    "iso:country":"GB",
    "sg:address":"6 Glendale Avenue",
    "sg:city":"Edgware",
    "sg:classifiers":[
        {
            "category":"Airport",
            "subcategory":"General Aviation",
            "type":"Transportation"
        }
    ],
    "sg:phone":"+44 20 8905 3311",
    "sg:postcode":"HA8 8HG",
    "sg:province":"Greater London",
    "sg:tags":[
        "consultant"
    ],
    "wof:name":"The A B S Consultancy",
    "wof:placetype":"venue"
},
  "geometry": {"coordinates":[-0.279260993,51.6189117432],"type":"Point"}
}