{
  "type": "Feature",
  "properties": {
    "addr:full":"187 Plumstead Common Rd Woolwich Greater London SE18 2UJ",
    "addr:housenumber":"187",
    "addr:postcode":"se18 2uj",
    "addr:street":"Plumstead Common Rd",
    "iso:country":"GB",
    "sg:address":"187 Plumstead Common Rd",
    "sg:city":"Woolwich",
    "sg:classifiers":[
        {
            "category":"Fast Food",
            "type":"Food & Drink"
        }
    ],
    "sg:phone":"+44 20 8854 4110",
    "sg:postcode":"SE18 2UJ",
    "sg:province":"Greater London",
    "sg:tags":[
        "away",
        "take"
    ],
    "wof:name":"New Sun Wah",
    "wof:placetype":"venue"
},
  "geometry": {"coordinates":[0.079496,51.481071],"type":"Point"}
}