{
  "type": "Feature",
  "properties": {
    "iso:country":"GB",
    "sg:address":"The Lawns, Northwood",
    "sg:city":"Shrewsbury",
    "sg:classifiers":[
        {
            "category":"Farming",
            "subcategory":"Livestock Farm",
            "type":"Manufacturing & Wholesale Goods"
        },
        {
            "category":"Farming",
            "subcategory":"Farm",
            "type":"Manufacturing & Wholesale Goods"
        }
    ],
    "sg:phone":"+44 1948 710218",
    "sg:postcode":"SY4 5NP",
    "sg:province":"Shropshire",
    "sg:tags":[
        "mixed",
        "crop",
        "others"
    ],
    "wof:name":"N C Lockett & Partners",
    "wof:placetype":"venue"
},
  "geometry": {"coordinates":[-2.797055006,52.8946418762],"type":"Point"}
}