{
  "type": "Feature",
  "properties": {
    "iso:country":"GB",
    "sg:address":"Dormleigh, Holton",
    "sg:city":"Wincanton",
    "sg:classifiers":[
        {
            "category":"Professional",
            "type":"Services"
        },
        {
            "category":"Fast Food",
            "type":"Food & Drink"
        }
    ],
    "sg:phone":"+44 1963 32429",
    "sg:postcode":"BA9 8AE",
    "sg:province":"Somerset",
    "sg:tags":[
        "away",
        "take",
        "caterer"
    ],
    "wof:name":"Southfield Caterers",
    "wof:placetype":"venue"
},
  "geometry": {"coordinates":[-2.449406,51.040585],"type":"Point"}
}