{
  "type": "Feature",
  "properties": {
    "iso:country":"GB",
    "sg:address":"Hamble Lodge, 20 Hamble Lane, Bursledon",
    "sg:city":"Southampton",
    "sg:classifiers":[
        {
            "category":"Organizations",
            "subcategory":"Non-profit Organization",
            "type":"Services"
        }
    ],
    "sg:phone":"+44 23 8040 6385",
    "sg:postcode":"SO31 8BR",
    "sg:province":"Hampshire",
    "sg:tags":[
        "organisation",
        "voluntary",
        "charity"
    ],
    "wof:name":"Streams in the Desert",
    "wof:placetype":"venue"
},
  "geometry": {"coordinates":[-1.315344,50.889721],"type":"Point"}
}