{
  "type": "Feature",
  "properties": {
    "addr:full":"Townend Lane, North Cave Brough East Riding of Yorkshire HU15 2LZ",
    "addr:postcode":"hu15 2lz",
    "addr:street":"Townend Lane",
    "iso:country":"GB",
    "sg:address":"Townend Lane, North Cave",
    "sg:city":"Brough",
    "sg:classifiers":[
        {
            "category":"Community Center",
            "type":"Public Place"
        }
    ],
    "sg:phone":"+44 1430 421378",
    "sg:postcode":"HU15 2LZ",
    "sg:province":"East Riding of Yorkshire",
    "sg:tags":[
        "recreation",
        "leisure",
        "centre"
    ],
    "wof:name":"North Cave Indoor Bowls Centre",
    "wof:placetype":"venue"
},
  "geometry": {"coordinates":[-0.652048,53.783436],"type":"Point"}
}