{
  "type": "Feature",
  "properties": {
    "iso:country":"GB",
    "sg:address":"232a Royal College St",
    "sg:city":"Camden",
    "sg:classifiers":[
        {
            "category":"Autos & Motor Vehicles",
            "subcategory":"Motorcycle Sales",
            "type":"Retail Goods"
        }
    ],
    "sg:phone":"+44 20 7209 1212",
    "sg:postcode":"NW1 9NJ",
    "sg:province":"Greater London",
    "wof:name":"North London Moped Centre",
    "wof:placetype":"venue"
},
  "geometry": {"coordinates":[-0.139196,51.54298],"type":"Point"}
}