{
  "type": "Feature",
  "properties": {
    "addr:full":"77 Mount Wise Newquay Cornwall TR7 2BP",
    "addr:housenumber":"77",
    "addr:postcode":"tr7 2bp",
    "addr:street":"Mount",
    "iso:country":"GB",
    "sg:address":"77 Mount Wise",
    "sg:city":"Newquay",
    "sg:classifiers":[
        {
            "category":"Travel",
            "subcategory":"Hotels & Motels",
            "type":"Entertainment"
        }
    ],
    "sg:postcode":"TR7 2BP",
    "sg:province":"Cornwall",
    "wof:name":"The Quay View Hotel",
    "wof:placetype":"venue"
},
  "geometry": {"coordinates":[-5.0839848518,50.4113273621],"type":"Point"}
}