{
  "type": "Feature",
  "properties": {
    "addr:full":"5 Brooklands Avenue Sheffield South Yorkshire S10 4GA",
    "addr:housenumber":"5",
    "addr:postcode":"s10 4ga",
    "addr:street":"Brooklands Avenue",
    "iso:country":"GB",
    "sg:address":"5 Brooklands Avenue",
    "sg:city":"Sheffield",
    "sg:classifiers":[
        {
            "category":"Shopping",
            "subcategory":"Department Store",
            "type":"Retail Goods"
        },
        {
            "category":"Government",
            "subcategory":"Post Office",
            "type":"Public Place"
        }
    ],
    "sg:phone":"+44 114 230 1311",
    "sg:postcode":"S10 4GA",
    "sg:province":"South Yorkshire",
    "wof:name":"Fulwood Post Office",
    "wof:placetype":"venue"
},
  "geometry": {"coordinates":[-1.545667,53.363804],"type":"Point"}
}