{
  "type": "Feature",
  "properties": {
    "addr:full":"Ryton Hall, Ryton Shifnal Shropshire TF11 9JL",
    "addr:postcode":"tf11 9jl",
    "addr:street":"Shifnal Shropshire",
    "iso:country":"GB",
    "sg:address":"Ryton Hall, Ryton",
    "sg:city":"Shifnal",
    "sg:classifiers":[
        {
            "category":"Real Estate",
            "subcategory":"Developer",
            "type":"Services"
        }
    ],
    "sg:phone":"+44 1952 750482",
    "sg:postcode":"TF11 9JL",
    "sg:province":"Shropshire",
    "sg:tags":[
        "property"
    ],
    "wof:name":"Chadwell Securities",
    "wof:placetype":"venue"
},
  "geometry": {"coordinates":[-2.3727788925,52.6654853821],"type":"Point"}
}