{
  "type": "Feature",
  "properties": {
    "addr:full":"43 Klea Avenue Clapham Greater London SW4 9HG",
    "addr:housenumber":"43",
    "addr:postcode":"sw4 9hg",
    "addr:street":"Klea Avenue",
    "iso:country":"GB",
    "sg:address":"43 Klea Avenue",
    "sg:city":"Clapham",
    "sg:classifiers":[
        {
            "category":"Communications",
            "type":"Services"
        }
    ],
    "sg:phone":"+44 20 8673 2801",
    "sg:postcode":"SW4 9HG",
    "sg:province":"Greater London",
    "sg:tags":[
        "audio-visual"
    ],
    "wof:name":"Comm HQ Ltd",
    "wof:placetype":"venue"
},
  "geometry": {"coordinates":[-0.141409,51.454151],"type":"Point"}
}