{
  "type": "Feature",
  "properties": {
    "addr:full":"Stuston Pla, Bury Road, Stuston Diss Norfolk IP21 4AD",
    "addr:postcode":"ip21 4ad",
    "addr:street":"Stuston Pla Bury Road",
    "iso:country":"GB",
    "sg:address":"Stuston Pla, Bury Road, Stuston",
    "sg:city":"Diss",
    "sg:classifiers":[
        {
            "category":"Farming",
            "subcategory":"Livestock Farm",
            "type":"Manufacturing & Wholesale Goods"
        }
    ],
    "sg:postcode":"IP21 4AD",
    "sg:province":"Norfolk",
    "sg:tags":[
        "others"
    ],
    "wof:name":"D Laurie",
    "wof:placetype":"venue"
},
  "geometry": {"coordinates":[1.1318750381,52.3599967957],"type":"Point"}
}