{
  "type": "Feature",
  "properties": {
    "iso:country":"GB",
    "sg:address":"The Grn, Great Tew",
    "sg:city":"Chipping Norton",
    "sg:classifiers":[
        {
            "category":"Education",
            "subcategory":"School",
            "type":"Public Place"
        }
    ],
    "sg:phone":"+44 1608 683642",
    "sg:postcode":"OX7 4DB",
    "sg:province":"Gloucestershire",
    "sg:tags":[
        "local",
        "authority"
    ],
    "wof:name":"Great Tew Primary School",
    "wof:placetype":"venue"
},
  "geometry": {"coordinates":[-1.429839,51.959015],"type":"Point"}
}