{
  "type": "Feature",
  "properties": {
    "addr:full":"48 High St Brandon Norfolk IP27 0AQ",
    "addr:housenumber":"48",
    "addr:postcode":"ip27 0aq",
    "addr:street":"High St",
    "iso:country":"GB",
    "sg:address":"48 High St",
    "sg:city":"Brandon",
    "sg:classifiers":[
        {
            "category":"Bars & Pubs",
            "type":"Food & Drink"
        }
    ],
    "sg:phone":"+44 1842 810465",
    "sg:postcode":"IP27 0AQ",
    "sg:province":"Norfolk",
    "sg:tags":[
        "pubs",
        "inn"
    ],
    "wof:name":"Bell Inn",
    "wof:placetype":"venue"
},
  "geometry": {"coordinates":[0.6233400106,52.448802948],"type":"Point"}
}