{
  "type": "Feature",
  "properties": {
    "addr:full":"6 Fleethall Road Rochford Essex SS4 1NF",
    "addr:housenumber":"6",
    "addr:postcode":"ss4 1nf",
    "addr:street":"Fleethall Road",
    "iso:country":"GB",
    "sg:address":"6 Fleethall Road",
    "sg:city":"Rochford",
    "sg:classifiers":[
        {
            "category":"Manufacturing",
            "subcategory":"Wood Products",
            "type":"Manufacturing & Wholesale Goods"
        }
    ],
    "sg:phone":"+44 1702 548418",
    "sg:postcode":"SS4 1NF",
    "sg:province":"Essex",
    "sg:tags":[
        "packaging",
        "crate",
        "pallets"
    ],
    "wof:name":"Direct Packaging Ltd.",
    "wof:placetype":"venue"
},
  "geometry": {"coordinates":[0.7164250016,51.5752792358],"type":"Point"}
}