{
  "type": "Feature",
  "properties": {
    "addr:full":"2a Button End, Harston Cambridge Cambridgeshire CB2 5NX",
    "addr:housenumber":"2a",
    "addr:postcode":"cb2 5nx",
    "addr:street":"Button End Harston",
    "iso:country":"GB",
    "sg:address":"2a Button End, Harston",
    "sg:city":"Cambridge",
    "sg:classifiers":[
        {
            "category":"Shopping",
            "subcategory":"Gifts & Souvenirs",
            "type":"Retail Goods"
        }
    ],
    "sg:phone":"+44 1223 870587",
    "sg:postcode":"CB2 5NX",
    "sg:province":"Cambridgeshire",
    "sg:tags":[
        "ducting"
    ],
    "wof:name":"Barjek (Ductwork & Fabrication) Ltd",
    "wof:placetype":"venue"
},
  "geometry": {"coordinates":[0.072995998,52.1403427124],"type":"Point"}
}