{
  "type": "Feature",
  "properties": {
    "iso:country":"GB",
    "sg:address":"4 Briar Court, New Ollerton",
    "sg:city":"Newark",
    "sg:classifiers":[
        {
            "category":"Building & Trades",
            "subcategory":"Construction",
            "type":"Services"
        }
    ],
    "sg:phone":"+44 1623 863776",
    "sg:postcode":"NG22 9SR",
    "sg:province":"Nottinghamshire",
    "sg:tags":[
        "roofing"
    ],
    "wof:name":"S & F",
    "wof:placetype":"venue"
},
  "geometry": {"coordinates":[-1.006446,53.205368],"type":"Point"}
}