{
  "type": "Feature",
  "properties": {
    "addr:full":"Radclyffe Lower School, Broadway Chadderton Oldham Lancashire OL9 0LS",
    "addr:postcode":"ol9 0ls",
    "addr:street":"Broadway",
    "iso:country":"GB",
    "sg:address":"Radclyffe Lower School, Broadway Chadderton",
    "sg:city":"Oldham",
    "sg:classifiers":[
        {
            "category":"Government",
            "subcategory":"Office",
            "type":"Public Place"
        }
    ],
    "sg:phone":"+44 161 624 6587",
    "sg:postcode":"OL9 0LS",
    "sg:province":"Lancashire",
    "sg:tags":[
        "local"
    ],
    "wof:name":"School Meals Special Catering Unit",
    "wof:placetype":"venue"
},
  "geometry": {"coordinates":[-2.138214,53.546467],"type":"Point"}
}