{
  "type": "Feature",
  "properties": {
    "addr:full":"Picket Post Warminster Somerset BA12 7JS",
    "addr:postcode":"ba12 7js",
    "addr:street":"Picket Post",
    "iso:country":"GB",
    "sg:address":"Picket Post",
    "sg:city":"Warminster",
    "sg:classifiers":[
        {
            "category":"Home & Garden",
            "subcategory":"Building Materials",
            "type":"Retail Goods"
        },
        {
            "category":"Utilities",
            "subcategory":"Fuel Oil & Lpg",
            "type":"Services"
        }
    ],
    "sg:phone":"+44 1985 213507",
    "sg:postcode":"BA12 7JS",
    "sg:province":"Somerset",
    "sg:tags":[
        "supplier",
        "gate",
        "firewood",
        "door",
        "barrier"
    ],
    "wof:name":"Longleat Forestry",
    "wof:placetype":"venue"
},
  "geometry": {"coordinates":[-2.1831250191,51.2053642273],"type":"Point"}
}