{
  "type": "Feature",
  "properties": {
    "addr:full":"8 Dukes Ride Crowthorne Berkshire RG45 6LT",
    "addr:housenumber":"8",
    "addr:postcode":"rg45 6lt",
    "addr:street":"Dukes Ride",
    "iso:country":"GB",
    "sg:address":"8 Dukes Ride",
    "sg:city":"Crowthorne",
    "sg:classifiers":[
        {
            "category":"Shopping",
            "subcategory":"Florist",
            "type":"Retail Goods"
        }
    ],
    "sg:phone":"+44 1344 772921",
    "sg:postcode":"RG45 6LT",
    "sg:province":"Berkshire",
    "wof:name":"The Flower Basket",
    "wof:placetype":"venue"
},
  "geometry": {"coordinates":[-0.7922350168,51.3705482483],"type":"Point"}
}