{
  "type": "Feature",
  "properties": {
    "addr:full":"Police Station, Hunter Lane Penrith Cumbria CA11 7UT",
    "addr:postcode":"ca11 7ut",
    "addr:street":"Hunter Lane",
    "iso:country":"GB",
    "sg:address":"Police Station, Hunter Lane",
    "sg:city":"Penrith",
    "sg:classifiers":[
        {
            "category":"Professional",
            "subcategory":"Lawyer & Legal Services",
            "type":"Services"
        }
    ],
    "sg:phone":"+44 1768 899934",
    "sg:postcode":"CA11 7UT",
    "sg:province":"Cumbria",
    "sg:tags":[
        "advice",
        "counselling"
    ],
    "wof:name":"Cumbria North & East Branch",
    "wof:placetype":"venue"
},
  "geometry": {"coordinates":[-2.7574689388,54.6643028259],"type":"Point"}
}