{
  "type": "Feature",
  "properties": {
    "addr:full":"48 Madeira Street Edinburgh City of Edinburgh EH6 4AL",
    "addr:housenumber":"48",
    "addr:postcode":"eh6 4al",
    "addr:street":"Madeira Street",
    "iso:country":"GB",
    "sg:address":"48 Madeira Street",
    "sg:city":"Edinburgh",
    "sg:classifiers":[
        {
            "category":"Food & Beverages",
            "subcategory":"Supermarket",
            "type":"Retail Goods"
        },
        {
            "category":"Food & Beverages",
            "subcategory":"Meat & Fish",
            "type":"Retail Goods"
        }
    ],
    "sg:postcode":"EH6 4AL",
    "sg:province":"City of Edinburgh",
    "sg:tags":[
        "butcher"
    ],
    "wof:name":"John's Corner Shop",
    "wof:placetype":"venue"
},
  "geometry": {"coordinates":[-3.182393,55.976204],"type":"Point"}
}