{
  "type": "Feature",
  "properties": {
    "iso:country":"GB",
    "sg:address":"Dale House, Smeeton Road",
    "sg:city":"Leicester",
    "sg:classifiers":[
        {
            "category":"Building & Trades",
            "subcategory":"Cleaning & Sanitation",
            "type":"Services"
        }
    ],
    "sg:phone":"+44 116 240 4789",
    "sg:postcode":"LE8 0QT",
    "sg:province":"Leicestershire",
    "sg:tags":[
        "commercial"
    ],
    "wof:name":"Merry Maid of South Leicestershire",
    "wof:placetype":"venue"
},
  "geometry": {"coordinates":[-0.997329,52.535671],"type":"Point"}
}