{
  "type": "Feature",
  "properties": {
    "iso:country":"GB",
    "sg:address":"29 Kings Road West",
    "sg:city":"Swanage",
    "sg:classifiers":[
        {
            "category":"Travel",
            "subcategory":"Hotels & Motels",
            "type":"Entertainment"
        }
    ],
    "sg:phone":"+44 1929 422306",
    "sg:postcode":"BH19 1HF",
    "sg:province":"Dorset",
    "sg:tags":[
        "house",
        "guest"
    ],
    "wof:name":"Terry & Lyn Persence",
    "wof:placetype":"venue"
},
  "geometry": {"coordinates":[-1.9599230289,50.6093292236],"type":"Point"}
}