{
  "type": "Feature",
  "properties": {
    "addr:full":"3a Lidice Road Goole East Riding of Yorkshire DN14 6XL",
    "addr:housenumber":"3a",
    "addr:postcode":"dn14 6xl",
    "addr:street":"Lidice Road",
    "iso:country":"GB",
    "sg:address":"3a Lidice Road",
    "sg:city":"Goole",
    "sg:classifiers":[
        {
            "category":"Professional",
            "subcategory":"Engineering",
            "type":"Services"
        }
    ],
    "sg:postcode":"DN14 6XL",
    "sg:province":"East Riding of Yorkshire",
    "wof:name":"Yorkshire Engineering Services",
    "wof:placetype":"venue"
},
  "geometry": {"coordinates":[-0.900482,53.704769],"type":"Point"}
}