{
  "type": "Feature",
  "properties": {
    "addr:full":"206 London Road Grays Essex RM17 5YP",
    "addr:housenumber":"206",
    "addr:postcode":"rm17 5yp",
    "addr:street":"London Road",
    "iso:country":"GB",
    "sg:address":"206 London Road",
    "sg:city":"Grays",
    "sg:classifiers":[
        {
            "category":"Retail",
            "subcategory":"Laundry & Dry Cleaning",
            "type":"Services"
        }
    ],
    "sg:phone":"+44 1375 372075",
    "sg:postcode":"RM17 5YP",
    "sg:province":"Essex",
    "sg:tags":[
        "launderette"
    ],
    "wof:name":"London Road Launderette",
    "wof:placetype":"venue"
},
  "geometry": {"coordinates":[0.3202700019,51.4780883789],"type":"Point"}
}