{
  "type": "Feature",
  "properties": {
    "iso:country":"GB",
    "sg:address":"Bank Top Farm, Marston Montgomery",
    "sg:city":"Ashbourne",
    "sg:classifiers":[
        {
            "category":"Farming",
            "subcategory":"Livestock Farm",
            "type":"Manufacturing & Wholesale Goods"
        }
    ],
    "sg:phone":"+44 1889 590239",
    "sg:postcode":"DE6 2FE",
    "sg:province":"Derbyshire",
    "sg:tags":[
        "others"
    ],
    "wof:name":"T W & G T FOUNTAIN",
    "wof:placetype":"venue"
},
  "geometry": {"coordinates":[-1.801449,52.937634],"type":"Point"}
}