{
  "type": "Feature",
  "properties": {
    "iso:country":"GB",
    "sg:address":"119 South Street",
    "sg:city":"Eastbourne",
    "sg:classifiers":[
        {
            "category":"Shopping",
            "subcategory":"Department Store",
            "type":"Retail Goods"
        }
    ],
    "sg:phone":"+44 1323 410414",
    "sg:postcode":"BN21 4LU",
    "sg:province":"East Sussex",
    "wof:name":"Peter T Mockford",
    "wof:placetype":"venue"
},
  "geometry": {"coordinates":[0.284354,50.766575],"type":"Point"}
}