{
  "type": "Feature",
  "properties": {
    "addr:full":"31 Watlands Avenue Newcastle Staffordshire ST5 8AS",
    "addr:housenumber":"31",
    "addr:postcode":"st5 8as",
    "addr:street":"Watlands Avenue",
    "iso:country":"GB",
    "sg:address":"31 Watlands Avenue",
    "sg:city":"Newcastle",
    "sg:classifiers":[
        {
            "category":"Building & Trades",
            "subcategory":"Construction",
            "type":"Services"
        }
    ],
    "sg:phone":"+44 1782 628833",
    "sg:postcode":"ST5 8AS",
    "sg:province":"Staffordshire",
    "sg:tags":[
        "decorator",
        "painter"
    ],
    "wof:name":"Watlands Design",
    "wof:placetype":"venue"
},
  "geometry": {"coordinates":[-2.223777,53.033611],"type":"Point"}
}