{
  "type": "Feature",
  "properties": {
    "iso:country":"GB",
    "sg:address":"Hall Gate Lane, Stalmine",
    "sg:city":"Poulton-le-fylde",
    "sg:classifiers":[
        {
            "category":"Arena",
            "subcategory":"Sports Club",
            "type":"Entertainment"
        }
    ],
    "sg:phone":"+44 1253 701468",
    "sg:postcode":"FY6 0LD",
    "sg:province":"Lancashire",
    "wof:name":"Wyre Villa Football Club",
    "wof:placetype":"venue"
},
  "geometry": {"coordinates":[-2.95252,53.900791],"type":"Point"}
}