{
  "type": "Feature",
  "properties": {
    "addr:full":"Accurist Ho, 44 Baker St London Greater London W1U 7BR",
    "addr:housenumber":"44",
    "addr:postcode":"w1u 7br",
    "addr:street":"Baker St",
    "iso:country":"GB",
    "sg:address":"Accurist Ho, 44 Baker St",
    "sg:city":"London",
    "sg:classifiers":[
        {
            "category":"Shopping",
            "subcategory":"Clothing, Apparel, & Fashions",
            "type":"Retail Goods"
        }
    ],
    "sg:postcode":"W1U 7BR",
    "sg:province":"Greater London",
    "sg:tags":[
        "shop"
    ],
    "wof:name":"Yazz International Ltd",
    "wof:placetype":"venue"
},
  "geometry": {"coordinates":[-0.1557500064,51.5185012817],"type":"Point"}
}