{
  "type": "Feature",
  "properties": {
    "iso:country":"GB",
    "sg:address":"Unit 39 Second Avenue, The Pensnett Estate, Kingswinford",
    "sg:city":"Brierley Hill",
    "sg:classifiers":[
        {
            "category":"Manufacturing",
            "subcategory":"Metals",
            "type":"Manufacturing & Wholesale Goods"
        }
    ],
    "sg:phone":"+44 1384 291900",
    "sg:postcode":"DY6 7PP",
    "sg:province":"Staffordshire",
    "sg:tags":[
        "fabricator",
        "aluminium",
        "mnfrs"
    ],
    "wof:name":"A S P Components Ltd.",
    "wof:placetype":"venue"
},
  "geometry": {"coordinates":[-2.151539,52.505814],"type":"Point"}
}