{
  "type": "Feature",
  "properties": {
    "iso:country":"GB",
    "sg:address":"Grove Farm, Medstead",
    "sg:city":"Alton",
    "sg:classifiers":[
        {
            "category":"Freight",
            "type":"Transportation"
        }
    ],
    "sg:phone":"+44 1420 563166",
    "sg:postcode":"GU34 5NE",
    "sg:province":"Hampshire",
    "sg:tags":[
        "haulage",
        "road"
    ],
    "wof:name":"A S Rawlings Ltd.",
    "wof:placetype":"venue"
},
  "geometry": {"coordinates":[-1.0648150444,51.1295471191],"type":"Point"}
}