{
  "type": "Feature",
  "properties": {
    "addr:full":"The Yews, Southampton Rd A336, Cadnam Southampton Hampshire SO40 2NG",
    "addr:postcode":"so40 2ng",
    "addr:street":"Southampton Rd;Cadnam",
    "iso:country":"GB",
    "sg:address":"The Yews, Southampton Rd A336, Cadnam",
    "sg:city":"Southampton",
    "sg:classifiers":[
        {
            "category":"Retail",
            "subcategory":"Auto Rental",
            "type":"Services"
        }
    ],
    "sg:postcode":"SO40 2NG",
    "sg:province":"Hampshire",
    "sg:tags":[
        "car"
    ],
    "wof:name":"New Forest Car Hire",
    "wof:placetype":"venue"
},
  "geometry": {"coordinates":[-1.564484,50.91769],"type":"Point"}
}