{
  "type": "Feature",
  "properties": {
    "addr:full":"Unit 1ac Leaton Industrial Estat, E Leaton, Bomere Heath Shrewsbury Shropshire SY4 3AP",
    "addr:housenumber":"unit 1ac",
    "addr:postcode":"sy4 3ap",
    "addr:street":"Leaton Industrial Estat E Leaton Bomere Heath",
    "iso:country":"GB",
    "sg:address":"Unit 1ac Leaton Industrial Estat, E Leaton, Bomere Heath",
    "sg:city":"Shrewsbury",
    "sg:classifiers":[
        {
            "category":"Home & Garden",
            "subcategory":"Hardware",
            "type":"Retail Goods"
        },
        {
            "category":"Manufacturing",
            "subcategory":"Textiles",
            "type":"Manufacturing & Wholesale Goods"
        }
    ],
    "sg:phone":"+44 1939 290692",
    "sg:postcode":"SY4 3AP",
    "sg:province":"Shropshire",
    "sg:tags":[
        "made-up",
        "tarpaulin"
    ],
    "wof:name":"Shrewsbury Tarpaulins Ltd.",
    "wof:placetype":"venue"
},
  "geometry": {"coordinates":[-2.7780840397,52.7729072571],"type":"Point"}
}