{
  "type": "Feature",
  "properties": {
    "iso:country":"GB",
    "sg:address":"5 Llewelyn Road",
    "sg:city":"Colwyn Bay",
    "sg:classifiers":[
        {
            "category":"Manufacturing",
            "subcategory":"Tools & Machinery",
            "type":"Manufacturing & Wholesale Goods"
        }
    ],
    "sg:postcode":"LL29 7AP",
    "sg:province":"Conwy",
    "sg:tags":[
        "power"
    ],
    "wof:name":"Fixit Power Tools",
    "wof:placetype":"venue"
},
  "geometry": {"coordinates":[-3.729006,53.295288],"type":"Point"}
}