{
  "type": "Feature",
  "properties": {
    "addr:full":"36 West Clyde Street Helensburgh Argyll and Bute G84 8AW",
    "addr:housenumber":"36",
    "addr:postcode":"g84 8aw",
    "addr:street":"West Clyde Street",
    "iso:country":"GB",
    "sg:address":"36 West Clyde Street",
    "sg:city":"Helensburgh",
    "sg:classifiers":[
        {
            "category":"Health Services",
            "subcategory":"Dentist",
            "type":"Services"
        }
    ],
    "sg:phone":"+44 1436 673856",
    "sg:postcode":"G84 8AW",
    "sg:province":"Argyll and Bute",
    "wof:name":"John R K Lamont",
    "wof:placetype":"venue"
},
  "geometry": {"coordinates":[-4.7368378639,56.0036048889],"type":"Point"}
}