{
  "type": "Feature",
  "properties": {
    "iso:country":"GB",
    "sg:address":"45 Biddisham Walk",
    "sg:city":"Manchester",
    "sg:classifiers":[
        {
            "category":"Building & Trades",
            "subcategory":"Pest Control",
            "type":"Services"
        }
    ],
    "sg:phone":"+44 161 205 5929",
    "sg:postcode":"M40 8LR",
    "sg:province":"Greater Manchester",
    "sg:tags":[
        "vermin"
    ],
    "wof:name":"Anthony Andrews Pest & Vermin Control",
    "wof:placetype":"venue"
},
  "geometry": {"coordinates":[-2.216646,53.498249],"type":"Point"}
}