{
  "type": "Feature",
  "properties": {
    "addr:full":"Tuition Ho, 6th Floor, 27-37 St. Georges Rd Wimbledon Greater London SW19 4DS",
    "addr:housenumber":"6th floor 27-37",
    "addr:postcode":"sw19 4ds",
    "addr:street":"St. Georges Rd",
    "iso:country":"GB",
    "sg:address":"Tuition Ho, 6th Floor, 27-37 St. Georges Rd",
    "sg:city":"Wimbledon",
    "sg:classifiers":[
        {
            "category":"Professional",
            "subcategory":"Business Services",
            "type":"Services"
        }
    ],
    "sg:phone":"+44 20 8879 0022",
    "sg:postcode":"SW19 4DS",
    "sg:province":"Greater London",
    "sg:tags":[
        "food",
        "import",
        "export",
        "agent"
    ],
    "wof:name":"Oram Food Ltd",
    "wof:placetype":"venue"
},
  "geometry": {"coordinates":[-0.2070239931,51.4209976196],"type":"Point"}
}