{
  "type": "Feature",
  "properties": {
    "iso:country":"GB",
    "sg:address":"4 Spring Hill",
    "sg:city":"Blackburn",
    "sg:classifiers":[
        {
            "category":"Shopping",
            "subcategory":"Gifts & Souvenirs",
            "type":"Retail Goods"
        }
    ],
    "sg:phone":"+44 1254 677308",
    "sg:postcode":"BB1 7JB",
    "sg:province":"Lancashire",
    "sg:tags":[
        "poster",
        "card"
    ],
    "wof:name":"Paperchain",
    "wof:placetype":"venue"
},
  "geometry": {"coordinates":[-2.506273,53.740116],"type":"Point"}
}