{
  "type": "Feature",
  "properties": {
    "addr:full":"Unit 1 Caldy Valley Road, Great Boughton Chester Cheshire CH3 5PR",
    "addr:housenumber":"unit 1",
    "addr:postcode":"ch3 5pr",
    "addr:street":"Caldy Valley Road",
    "iso:country":"GB",
    "sg:address":"Unit 1 Caldy Valley Road, Great Boughton",
    "sg:city":"Chester",
    "sg:classifiers":[
        {
            "category":"Shopping",
            "subcategory":"Pets & Pet Supplies",
            "type":"Retail Goods"
        }
    ],
    "sg:phone":"+44 1244 351192",
    "sg:postcode":"CH3 5PR",
    "sg:province":"Cheshire",
    "wof:name":"Petsmart",
    "wof:placetype":"venue"
},
  "geometry": {"coordinates":[-2.854619,53.187729],"type":"Point"}
}