{
  "type": "Feature",
  "properties": {
    "iso:country":"GB",
    "sg:address":"Hale Lane, Frithville",
    "sg:city":"Boston",
    "sg:classifiers":[
        {
            "category":"Building & Trades",
            "subcategory":"Construction",
            "type":"Services"
        }
    ],
    "sg:phone":"+44 1205 750093",
    "sg:postcode":"PE22 7EE",
    "sg:province":"Lincolnshire",
    "sg:tags":[
        "joinery",
        "joiner",
        "carpenter",
        "carpentry"
    ],
    "wof:name":"D Smith & C Peltell",
    "wof:placetype":"venue"
},
  "geometry": {"coordinates":[-0.031014,53.034698],"type":"Point"}
}