{
  "type": "Feature",
  "properties": {
    "addr:full":"Unit 1 Groveley Business Centre, Groveley Road Christchurch Dorset BH23 3HB",
    "addr:housenumber":"unit 1",
    "addr:postcode":"bh23 3hb",
    "addr:street":"Groveley Business Centre Groveley Road",
    "iso:country":"GB",
    "sg:address":"Unit 1 Groveley Business Centre, Groveley Road",
    "sg:city":"Christchurch",
    "sg:classifiers":[
        {
            "category":"Retail",
            "subcategory":"Auto Repair",
            "type":"Services"
        }
    ],
    "sg:phone":"+44 1202 475750",
    "sg:postcode":"BH23 3HB",
    "sg:province":"Dorset",
    "sg:tags":[
        "modification",
        "garage",
        "related"
    ],
    "wof:name":"Super Service",
    "wof:placetype":"venue"
},
  "geometry": {"coordinates":[-1.776564002,50.7340698242],"type":"Point"}
}