{
  "type": "Feature",
  "properties": {
    "addr:full":"Upper Holland Road Sutton Coldfield West Midlands B72 1RB",
    "addr:postcode":"b72 1rb",
    "addr:street":"Upper Holland Road",
    "iso:country":"GB",
    "sg:address":"Upper Holland Road",
    "sg:city":"Sutton Coldfield",
    "sg:classifiers":[
        {
            "category":"Education",
            "subcategory":"School",
            "type":"Public Place"
        },
        {
            "category":"Government",
            "subcategory":"Office",
            "type":"Public Place"
        }
    ],
    "sg:postcode":"B72 1RB",
    "sg:province":"West Midlands",
    "sg:tags":[
        "local",
        "authority"
    ],
    "wof:name":"Plantsbrook Secondary School",
    "wof:placetype":"venue"
},
  "geometry": {"coordinates":[-1.8204300404,52.5590324402],"type":"Point"}
}