{
  "type": "Feature",
  "properties": {
    "iso:country":"GB",
    "sg:address":"12 Water Lane, Totton",
    "sg:city":"Southampton",
    "sg:classifiers":[
        {
            "category":"Real Estate",
            "subcategory":"Real Estate Agent",
            "type":"Services"
        }
    ],
    "sg:phone":"+44 23 8087 3040",
    "sg:postcode":"SO40 3DP",
    "sg:province":"Hampshire",
    "wof:name":"Connell Estate Agents",
    "wof:placetype":"venue"
},
  "geometry": {"coordinates":[-1.491097,50.918877],"type":"Point"}
}