{
  "type": "Feature",
  "properties": {
    "addr:full":"15 Northridge Road Gravesend Kent DA12 5AZ",
    "addr:housenumber":"15",
    "addr:postcode":"da12 5az",
    "addr:street":"Northridge Road",
    "iso:country":"GB",
    "sg:address":"15 Northridge Road",
    "sg:city":"Gravesend",
    "sg:classifiers":[
        {
            "category":"Professional",
            "subcategory":"Art Services",
            "type":"Services"
        },
        {
            "category":"Building & Trades",
            "subcategory":"Construction",
            "type":"Services"
        }
    ],
    "sg:phone":"+44 1474 533127",
    "sg:postcode":"DA12 5AZ",
    "sg:province":"Kent",
    "sg:tags":[
        "decorator",
        "painter"
    ],
    "wof:name":"PHILIP J BUSWELL",
    "wof:placetype":"venue"
},
  "geometry": {"coordinates":[0.373017,51.426929],"type":"Point"}
}