{
  "type": "Feature",
  "properties": {
    "iso:country":"GB",
    "sg:address":"64 Beckhampton Rd",
    "sg:city":"Bath",
    "sg:classifiers":[
        {
            "category":"Professional",
            "type":"Services"
        }
    ],
    "sg:phone":"+44 1225 315353",
    "sg:postcode":"BA2 3LN",
    "sg:province":"Somerset",
    "sg:tags":[
        "repair",
        "tech",
        "maintenance"
    ],
    "wof:name":"Compusolve",
    "wof:placetype":"venue"
},
  "geometry": {"coordinates":[-2.3781220913,51.3759918213],"type":"Point"}
}