{
  "type": "Feature",
  "properties": {
    "iso:country":"GB",
    "sg:address":"Lower Victoria Street, Chadderton",
    "sg:city":"Oldham",
    "sg:classifiers":[
        {
            "category":"Building & Trades",
            "subcategory":"Construction",
            "type":"Services"
        }
    ],
    "sg:phone":"+44 161 626 9175",
    "sg:postcode":"OL9 9TU",
    "sg:province":"Lancashire",
    "sg:tags":[
        "heating",
        "contractor"
    ],
    "wof:name":"Harry Long (Oldham) Ltd.",
    "wof:placetype":"venue"
},
  "geometry": {"coordinates":[-2.140574,53.544945],"type":"Point"}
}