{
  "type": "Feature",
  "properties": {
    "iso:country":"GB",
    "sg:address":"Leigh Road, Atherton",
    "sg:city":"Manchester",
    "sg:classifiers":[
        {
            "category":"Autos & Motor Vehicles",
            "subcategory":"Automobile Sales",
            "type":"Retail Goods"
        },
        {
            "category":"Sports & Exercise",
            "subcategory":"Tennis Court",
            "type":"Entertainment"
        }
    ],
    "sg:phone":"+44 1942 884532",
    "sg:postcode":"M46 0RN",
    "sg:province":"Greater Manchester",
    "sg:tags":[
        "breakdown",
        "car",
        "used",
        "recovery"
    ],
    "wof:name":"Salford Tech Services Ltd",
    "wof:placetype":"venue"
},
  "geometry": {"coordinates":[-2.4987740517,53.5228309631],"type":"Point"}
}