{
  "type": "Feature",
  "properties": {
    "addr:full":"26 Sun Street Lancaster Lancashire LA1 1EW",
    "addr:housenumber":"26",
    "addr:postcode":"la1 1ew",
    "addr:street":"Sun Street",
    "iso:country":"GB",
    "sg:address":"26 Sun Street",
    "sg:city":"Lancaster",
    "sg:classifiers":[
        {
            "category":"Professional",
            "subcategory":"Lawyer & Legal Services",
            "type":"Services"
        }
    ],
    "sg:postcode":"LA1 1EW",
    "sg:province":"Lancashire",
    "sg:tags":[
        "solicitor"
    ],
    "wof:name":"Elaine Maxwell & Co.",
    "wof:placetype":"venue"
},
  "geometry": {"coordinates":[-2.802821,54.049236],"type":"Point"}
}