{
  "type": "Feature",
  "properties": {
    "addr:full":"Open House Centre Manvers Street Bath Bath and North East Somerset BA1 1JW",
    "addr:postcode":"ba1 1jw",
    "addr:street":"Manvers Street",
    "iso:country":"GB",
    "sg:address":"Open House Centre Manvers Street",
    "sg:city":"Bath",
    "sg:classifiers":[
        {
            "category":"Organizations",
            "subcategory":"Non-profit Organization",
            "type":"Services"
        }
    ],
    "sg:phone":"+44 1225 335551",
    "sg:postcode":"BA1 1JW",
    "sg:province":"Bath and North East Somerset",
    "sg:tags":[
        "organisation",
        "voluntary",
        "charity"
    ],
    "wof:name":"Off the Record - Bath & North East Somerset",
    "wof:placetype":"venue"
},
  "geometry": {"coordinates":[-2.357044,51.378284],"type":"Point"}
}