{
  "type": "Feature",
  "properties": {
    "addr:full":"67 Stonecot Hill Sutton Surrey SM3 9HJ",
    "addr:housenumber":"67",
    "addr:postcode":"sm3 9hj",
    "addr:street":"Stonecot Hill",
    "iso:country":"GB",
    "sg:address":"67 Stonecot Hill",
    "sg:city":"Sutton",
    "sg:classifiers":[
        {
            "category":"Personal",
            "subcategory":"Beauty Salon",
            "type":"Services"
        },
        {
            "category":"Personal",
            "subcategory":"Barber",
            "type":"Services"
        }
    ],
    "sg:phone":"+44 20 8644 9414",
    "sg:postcode":"SM3 9HJ",
    "sg:province":"Surrey",
    "sg:tags":[
        "unisex",
        "hairdresser"
    ],
    "wof:name":"Prima Donna",
    "wof:placetype":"venue"
},
  "geometry": {"coordinates":[-0.2136459947,51.3836135864],"type":"Point"}
}