{
  "type": "Feature",
  "properties": {
    "iso:country":"GB",
    "sg:address":"12 Norfolk Street",
    "sg:city":"Cambridge",
    "sg:classifiers":[
        {
            "category":"Restaurant",
            "type":"Food & Drink"
        }
    ],
    "sg:phone":"+44 1223 503334",
    "sg:postcode":"CB1 2LF",
    "sg:province":"Cambridgeshire",
    "wof:name":"Palm Tree Caribbean Restaurant",
    "wof:placetype":"venue"
},
  "geometry": {"coordinates":[0.137006,52.204758],"type":"Point"}
}