{
  "type": "Feature",
  "properties": {
    "iso:country":"GB",
    "sg:address":"140-142 Ocean Road",
    "sg:city":"South Shields",
    "sg:classifiers":[
        {
            "category":"Bars & Pubs",
            "type":"Food & Drink"
        },
        {
            "category":"Travel",
            "subcategory":"Hotels & Motels",
            "type":"Entertainment"
        }
    ],
    "sg:phone":"+44 191 456 7176",
    "sg:postcode":"NE33 2JF",
    "sg:province":"Tyne and Wear",
    "sg:tags":[
        "pubs",
        "house",
        "inn",
        "guest"
    ],
    "wof:name":"Pier Guest House",
    "wof:placetype":"venue"
},
  "geometry": {"coordinates":[-1.4268440008,54.9998321533],"type":"Point"}
}