{
  "type": "Feature",
  "properties": {
    "addr:full":"8 Weaponness Valley Close Scarborough North Yorkshire YO11 2JJ",
    "addr:housenumber":"8",
    "addr:postcode":"yo11 2jj",
    "addr:street":"Weaponness Valley Close",
    "iso:country":"GB",
    "sg:address":"8 Weaponness Valley Close",
    "sg:city":"Scarborough",
    "sg:classifiers":[
        {
            "category":"Building & Trades",
            "subcategory":"Plumbing",
            "type":"Services"
        }
    ],
    "sg:phone":"+44 1723 369027",
    "sg:postcode":"YO11 2JJ",
    "sg:province":"North Yorkshire",
    "sg:tags":[
        "heating"
    ],
    "wof:name":"County Heating",
    "wof:placetype":"venue"
},
  "geometry": {"coordinates":[-0.411958009,54.2699050903],"type":"Point"}
}