{
  "type": "Feature",
  "properties": {
    "iso:country":"GB",
    "sg:address":"65 Spinney Road",
    "sg:city":"Norwich",
    "sg:classifiers":[
        {
            "category":"Food & Beverages",
            "subcategory":"Bakery",
            "type":"Retail Goods"
        }
    ],
    "sg:phone":"+44 1603 466366",
    "sg:postcode":"NR7 0PJ",
    "sg:province":"Norfolk",
    "sg:tags":[
        "shop",
        "baker"
    ],
    "wof:name":"Kelly's Bakery",
    "wof:placetype":"venue"
},
  "geometry": {"coordinates":[1.35031,52.638065],"type":"Point"}
}