{
  "type": "Feature",
  "properties": {
    "iso:country":"GB",
    "sg:address":"4 Peel Precinct",
    "sg:city":"London",
    "sg:classifiers":[
        {
            "category":"Shopping",
            "subcategory":"Pharmacy",
            "type":"Retail Goods"
        }
    ],
    "sg:postcode":"NW6 5RE",
    "sg:province":"Greater London",
    "sg:tags":[
        "pharmacist",
        "chemist"
    ],
    "wof:name":"Peel Chemist",
    "wof:placetype":"venue"
},
  "geometry": {"coordinates":[-0.198511,51.532997],"type":"Point"}
}