{
  "type": "Feature",
  "properties": {
    "addr:full":"181 South Liberty Lane Bristol City of Bristol BS3 2TN",
    "addr:housenumber":"181",
    "addr:postcode":"bs3 2tn",
    "addr:street":"South Liberty Lane",
    "iso:country":"GB",
    "sg:address":"181 South Liberty Lane",
    "sg:city":"Bristol",
    "sg:classifiers":[
        {
            "category":"Building & Trades",
            "subcategory":"Construction",
            "type":"Services"
        }
    ],
    "sg:phone":"+44 117 966 0819",
    "sg:postcode":"BS3 2TN",
    "sg:province":"City of Bristol",
    "sg:tags":[
        "roofing"
    ],
    "wof:name":"Ashcroft Services Ltd.",
    "wof:placetype":"venue"
},
  "geometry": {"coordinates":[-2.6119139194,51.4325447083],"type":"Point"}
}