{
  "type": "Feature",
  "properties": {
    "addr:full":"High Hoyland Barnsley South Yorkshire S75 4BE",
    "addr:postcode":"s75 4be",
    "addr:street":"Yorkshire",
    "iso:country":"GB",
    "sg:address":"High Hoyland",
    "sg:city":"Barnsley",
    "sg:classifiers":[
        {
            "category":"Bars & Pubs",
            "type":"Food & Drink"
        }
    ],
    "sg:phone":"+44 1226 382541",
    "sg:postcode":"S75 4BE",
    "sg:province":"South Yorkshire",
    "sg:tags":[
        "pubs",
        "inn"
    ],
    "wof:name":"The Cherry Tree Inn",
    "wof:placetype":"venue"
},
  "geometry": {"coordinates":[-1.5885,53.58675],"type":"Point"}
}