{
  "type": "Feature",
  "properties": {
    "addr:full":"35 Eskdale Rise, Allerton Bradford West Yorkshire BD15 7UG",
    "addr:housenumber":"35",
    "addr:postcode":"bd15 7ug",
    "addr:street":"Eskdale Rise",
    "iso:country":"GB",
    "sg:address":"35 Eskdale Rise, Allerton",
    "sg:city":"Bradford",
    "sg:classifiers":[
        {
            "category":"Retail",
            "subcategory":"Driving School",
            "type":"Services"
        }
    ],
    "sg:postcode":"BD15 7UG",
    "sg:province":"West Yorkshire",
    "wof:name":"Eric's School of Motoring",
    "wof:placetype":"venue"
},
  "geometry": {"coordinates":[-1.8183399439,53.7985267639],"type":"Point"}
}