{
  "type": "Feature",
  "properties": {
    "iso:country":"GB",
    "sg:address":"Bowyer Street",
    "sg:city":"Birmingham",
    "sg:classifiers":[
        {
            "category":"Shopping",
            "subcategory":"Musical Instruments",
            "type":"Retail Goods"
        }
    ],
    "sg:phone":"+44 121 773 5711",
    "sg:postcode":"B10 0SA",
    "sg:province":"West Midlands",
    "wof:name":"Jay Dee Custom Guitars Ltd.",
    "wof:placetype":"venue"
},
  "geometry": {"coordinates":[-1.8771090508,52.4732437134],"type":"Point"}
}