{
  "type": "Feature",
  "properties": {
    "addr:full":"28 Frenchfield Gardens Penrith Cumbria CA11 8TX",
    "addr:housenumber":"28",
    "addr:postcode":"ca11 8tx",
    "addr:street":"Frenchfield Gardens",
    "iso:country":"GB",
    "sg:address":"28 Frenchfield Gardens",
    "sg:city":"Penrith",
    "sg:classifiers":[
        {
            "category":"Professional",
            "subcategory":"Detective & Security Services",
            "type":"Services"
        }
    ],
    "sg:postcode":"CA11 8TX",
    "sg:province":"Cumbria",
    "sg:tags":[
        "agency"
    ],
    "wof:name":"Chris Rebanks Investigations",
    "wof:placetype":"venue"
},
  "geometry": {"coordinates":[-2.729438,54.662281],"type":"Point"}
}