{
  "type": "Feature",
  "properties": {
    "addr:full":"Unit 2 1 Long St Bethnal Green Greater London E2 8HJ",
    "addr:housenumber":"unit;1",
    "addr:postcode":"e2 8hj",
    "addr:street":"Long St",
    "iso:country":"GB",
    "sg:address":"Unit 2 1 Long St",
    "sg:city":"Bethnal Green",
    "sg:classifiers":[
        {
            "category":"Personal",
            "subcategory":"Skin Care",
            "type":"Services"
        }
    ],
    "sg:phone":"+44 20 7739 4734",
    "sg:postcode":"E2 8HJ",
    "sg:province":"Greater London",
    "sg:tags":[
        "leather",
        "merchant"
    ],
    "wof:name":"Tura Import & Export",
    "wof:placetype":"venue"
},
  "geometry": {"coordinates":[-0.0764650032,51.5285835266],"type":"Point"}
}