{
  "type": "Feature",
  "properties": {
    "addr:full":"2 Landscape Rd Woodford Green Essex IG8 9AU",
    "addr:housenumber":"2",
    "addr:postcode":"ig8 9au",
    "addr:street":"Landscape Rd",
    "iso:country":"GB",
    "sg:address":"2 Landscape Rd",
    "sg:city":"Woodford Green",
    "sg:classifiers":[
        {
            "category":"Professional",
            "subcategory":"Business Services",
            "type":"Services"
        }
    ],
    "sg:postcode":"IG8 9AU",
    "sg:province":"Essex",
    "sg:tags":[
        "import",
        "export",
        "agent"
    ],
    "wof:name":"International Exports",
    "wof:placetype":"venue"
},
  "geometry": {"coordinates":[0.0313020013,51.6027030945],"type":"Point"}
}