{
  "type": "Feature",
  "properties": {
    "iso:country":"GB",
    "sg:address":"The Naffi Family Shop, Goodwin Close",
    "sg:city":"Warminster",
    "sg:classifiers":[
        {
            "category":"Organizations",
            "subcategory":"Membership Organization",
            "type":"Services"
        }
    ],
    "sg:phone":"+44 1985 212411",
    "sg:postcode":"BA12 0DF",
    "sg:province":"Somerset",
    "sg:tags":[
        "club"
    ],
    "wof:name":"Navy Army & Air Force Institutes",
    "wof:placetype":"venue"
},
  "geometry": {"coordinates":[-2.183125,51.205364],"type":"Point"}
}