{
  "type": "Feature",
  "properties": {
    "addr:full":"9 Johnson Park Aberdare Neath Port Talbot CF44 9NB",
    "addr:housenumber":"9",
    "addr:postcode":"cf44 9nb",
    "addr:street":"Johnson Park",
    "iso:country":"GB",
    "sg:address":"9 Johnson Park",
    "sg:city":"Aberdare",
    "sg:classifiers":[
        {
            "category":"Banks & Credit Unions",
            "subcategory":"Financial Services",
            "type":"Services"
        }
    ],
    "sg:phone":"+44 1685 812432",
    "sg:postcode":"CF44 9NB",
    "sg:province":"Neath Port Talbot",
    "sg:tags":[
        "consultant"
    ],
    "wof:name":"Abbex Business Consultants",
    "wof:placetype":"venue"
},
  "geometry": {"coordinates":[-3.506361,51.735317],"type":"Point"}
}