{
  "type": "Feature",
  "properties": {
    "iso:country":"GB",
    "sg:address":"884 Old Lode La",
    "sg:city":"Solihull",
    "sg:classifiers":[
        {
            "category":"Restaurant",
            "type":"Food & Drink"
        }
    ],
    "sg:phone":"+44 121 743 7883",
    "sg:postcode":"B92 8LW",
    "sg:province":"West Midlands",
    "sg:tags":[
        "indian"
    ],
    "wof:name":"Selecta Balti House",
    "wof:placetype":"venue"
},
  "geometry": {"coordinates":[-1.777344,52.446045],"type":"Point"}
}