{
  "type": "Feature",
  "properties": {
    "addr:full":"The Hucknall Window Centre, 178 Portland Road Nottingham Nottinghamshire NG15 7RW",
    "addr:housenumber":"178",
    "addr:postcode":"ng15 7rw",
    "addr:street":"Portland Road",
    "iso:country":"GB",
    "sg:address":"The Hucknall Window Centre, 178 Portland Road",
    "sg:city":"Nottingham",
    "sg:classifiers":[
        {
            "category":"Manufacturing",
            "subcategory":"Petroleum Products",
            "type":"Manufacturing & Wholesale Goods"
        }
    ],
    "sg:phone":"+44 115 968 0380",
    "sg:postcode":"NG15 7RW",
    "sg:province":"Nottinghamshire",
    "sg:tags":[
        "double",
        "glazing"
    ],
    "wof:name":"East Midland Windows Ltd.",
    "wof:placetype":"venue"
},
  "geometry": {"coordinates":[-1.1439239979,52.9492263794],"type":"Point"}
}