{
  "type": "Feature",
  "properties": {
    "iso:country":"GB",
    "sg:address":"The Galleries Centre 31-32 Cast, Le Gallery",
    "sg:city":"Bristol",
    "sg:classifiers":[
        {
            "category":"Shopping",
            "subcategory":"Clothing, Apparel, & Fashions",
            "type":"Retail Goods"
        }
    ],
    "sg:phone":"+44 117 930 4404",
    "sg:postcode":"BS1 3XE",
    "sg:province":"City of Bristol",
    "sg:tags":[
        "shop"
    ],
    "wof:name":"T K Maxx",
    "wof:placetype":"venue"
},
  "geometry": {"coordinates":[-2.591429,51.453667],"type":"Point"}
}