{
  "type": "Feature",
  "properties": {
    "addr:full":"27 Gabalfa Rd Cardiff Cardiff CF14 2JJ",
    "addr:housenumber":"27",
    "addr:postcode":"cf14 2jj",
    "addr:street":"Gabalfa Rd",
    "iso:country":"GB",
    "sg:address":"27 Gabalfa Rd",
    "sg:city":"Cardiff",
    "sg:classifiers":[
        {
            "category":"Food & Beverages",
            "subcategory":"Candy",
            "type":"Retail Goods"
        }
    ],
    "sg:phone":"+44 29 2056 8502",
    "sg:postcode":"CF14 2JJ",
    "sg:province":"Cardiff",
    "sg:tags":[
        "confectionery"
    ],
    "wof:name":"Cakes'nIce",
    "wof:placetype":"venue"
},
  "geometry": {"coordinates":[-3.2242739201,51.5007667542],"type":"Point"}
}