{
  "type": "Feature",
  "properties": {
    "addr:full":"76 Pilsdon Drive Poole Dorset BH17 9HS",
    "addr:housenumber":"76",
    "addr:postcode":"bh17 9hs",
    "addr:street":"Pilsdon Drive",
    "iso:country":"GB",
    "sg:address":"76 Pilsdon Drive",
    "sg:city":"Poole",
    "sg:classifiers":[
        {
            "category":"Professional",
            "subcategory":"Advertising",
            "type":"Services"
        },
        {
            "category":"Manufacturing",
            "subcategory":"Signs",
            "type":"Manufacturing & Wholesale Goods"
        }
    ],
    "sg:phone":"+44 1202 697769",
    "sg:postcode":"BH17 9HS",
    "sg:province":"Dorset",
    "sg:tags":[
        "writer",
        "signwriters"
    ],
    "wof:name":"Lionel R Vine",
    "wof:placetype":"venue"
},
  "geometry": {"coordinates":[-1.966077,50.756107],"type":"Point"}
}