{
  "type": "Feature",
  "properties": {
    "addr:full":"2 Union Street Plymouth Devon PL1 2SR",
    "addr:housenumber":"2",
    "addr:postcode":"pl1 2sr",
    "addr:street":"Union Street",
    "iso:country":"GB",
    "sg:address":"2 Union Street",
    "sg:city":"Plymouth",
    "sg:classifiers":[
        {
            "category":"Shopping",
            "subcategory":"News",
            "type":"Retail Goods"
        }
    ],
    "sg:phone":"+44 1752 660900",
    "sg:postcode":"PL1 2SR",
    "sg:province":"Devon",
    "sg:tags":[
        "newsagent"
    ],
    "wof:name":"Sparrow & Son",
    "wof:placetype":"venue"
},
  "geometry": {"coordinates":[-4.146652,50.370049],"type":"Point"}
}