{
  "type": "Feature",
  "properties": {
    "iso:country":"GB",
    "sg:address":"12 Lockett Street",
    "sg:city":"Manchester",
    "sg:classifiers":[
        {
            "category":"Shopping",
            "subcategory":"Clothing, Apparel, & Fashions",
            "type":"Retail Goods"
        }
    ],
    "sg:postcode":"M8 8EE",
    "sg:province":"Greater Manchester",
    "sg:tags":[
        "clothing"
    ],
    "wof:name":"Imatex Clothing",
    "wof:placetype":"venue"
},
  "geometry": {"coordinates":[-2.25083,53.493652],"type":"Point"}
}