{
  "type": "Feature",
  "properties": {
    "iso:country":"GB",
    "sg:address":"Scot Lane",
    "sg:city":"Wigan",
    "sg:classifiers":[
        {
            "category":"Place Of Worship",
            "type":"Public Place"
        },
        {
            "category":"Education",
            "subcategory":"School",
            "type":"Public Place"
        },
        {
            "category":"Organizations",
            "subcategory":"Membership Organization",
            "type":"Services"
        }
    ],
    "sg:phone":"+44 1942 708242",
    "sg:postcode":"WN5 0UA",
    "sg:province":"Lancashire",
    "sg:tags":[
        "club",
        "local",
        "authority"
    ],
    "wof:name":"St.Edwards",
    "wof:placetype":"venue"
},
  "geometry": {"coordinates":[-2.66531,53.55217],"type":"Point"}
}