{
  "type": "Feature",
  "properties": {
    "addr:full":"7 Perth Street Blairgowrie Perth and Kinross PH10 6DQ",
    "addr:housenumber":"7",
    "addr:postcode":"ph10 6dq",
    "addr:street":"Perth Street",
    "iso:country":"GB",
    "sg:address":"7 Perth Street",
    "sg:city":"Blairgowrie",
    "sg:classifiers":[
        {
            "category":"Shopping",
            "subcategory":"News",
            "type":"Retail Goods"
        }
    ],
    "sg:phone":"+44 1250 872822",
    "sg:postcode":"PH10 6DQ",
    "sg:province":"Perth and Kinross",
    "sg:tags":[
        "newsagent"
    ],
    "wof:name":"Essentials",
    "wof:placetype":"venue"
},
  "geometry": {"coordinates":[-3.3413209915,56.590877533],"type":"Point"}
}