{
  "type": "Feature",
  "properties": {
    "addr:full":"Brookside Works, School Lane Ongar Essex CM5 0PF",
    "addr:postcode":"cm5 0pf",
    "addr:street":"School Lane",
    "iso:country":"GB",
    "sg:address":"Brookside Works, School Lane",
    "sg:city":"Ongar",
    "sg:classifiers":[
        {
            "category":"Professional",
            "subcategory":"Engineering",
            "type":"Services"
        }
    ],
    "sg:phone":"+44 1279 876201",
    "sg:postcode":"CM5 0PF",
    "sg:province":"Essex",
    "wof:name":"Walter Reynolds Ltd",
    "wof:placetype":"venue"
},
  "geometry": {"coordinates":[0.24517,51.706131],"type":"Point"}
}