{
  "type": "Feature",
  "properties": {
    "addr:full":"Flat 2 181 Redland Road Bristol City of Bristol BS6 6YQ",
    "addr:housenumber":"181",
    "addr:postcode":"bs6 6yq",
    "addr:street":"Redland Road",
    "iso:country":"GB",
    "sg:address":"Flat 2 181 Redland Road",
    "sg:city":"Bristol",
    "sg:classifiers":[
        {
            "category":"Professional",
            "subcategory":"Computer Services",
            "type":"Services"
        }
    ],
    "sg:postcode":"BS6 6YQ",
    "sg:province":"City of Bristol",
    "sg:tags":[
        "system",
        "software"
    ],
    "wof:name":"Serversoft Contracting Ltd",
    "wof:placetype":"venue"
},
  "geometry": {"coordinates":[-2.6109700203,51.4727783203],"type":"Point"}
}