{
  "type": "Feature",
  "properties": {
    "iso:country":"GB",
    "sg:address":"14a High Street, Toddington",
    "sg:city":"Dunstable",
    "sg:classifiers":[
        {
            "category":"Personal",
            "subcategory":"Beauty Salon",
            "type":"Services"
        }
    ],
    "sg:phone":"+44 1525 873031",
    "sg:postcode":"LU5 6BY",
    "sg:province":"Bedfordshire",
    "sg:tags":[
        "ladies",
        "lady",
        "hairdresser"
    ],
    "wof:name":"Panache Ladies Hair & Beauty Salon",
    "wof:placetype":"venue"
},
  "geometry": {"coordinates":[-0.532774,51.948273],"type":"Point"}
}