{
  "type": "Feature",
  "properties": {
    "addr:full":"Sudley Chambers, 8 Sudley Rd Bognor Regis West Sussex PO21 1EU",
    "addr:housenumber":"8",
    "addr:postcode":"po21 1eu",
    "addr:street":"Sudley Rd",
    "iso:country":"GB",
    "sg:address":"Sudley Chambers, 8 Sudley Rd",
    "sg:city":"Bognor Regis",
    "sg:classifiers":[
        {
            "category":"Professional",
            "subcategory":"Accounting & Tax Preparation",
            "type":"Services"
        }
    ],
    "sg:phone":"+44 1903 209679",
    "sg:postcode":"PO21 1EU",
    "sg:province":"West Sussex",
    "sg:tags":[
        "accountant"
    ],
    "wof:name":"Link Data",
    "wof:placetype":"venue"
},
  "geometry": {"coordinates":[-0.6753489971,50.7829666138],"type":"Point"}
}