{
  "type": "Feature",
  "properties": {
    "addr:full":"4 Coopers Cottages Hailsham East Sussex BN27 3QE",
    "addr:housenumber":"4",
    "addr:postcode":"bn27 3qe",
    "addr:street":"Coopers Cottages Hailsham",
    "iso:country":"GB",
    "sg:address":"4 Coopers Cottages",
    "sg:city":"Hailsham",
    "sg:classifiers":[
        {
            "category":"Building & Trades",
            "subcategory":"Plumbing",
            "type":"Services"
        }
    ],
    "sg:phone":"+44 1323 848385",
    "sg:postcode":"BN27 3QE",
    "sg:province":"East Sussex",
    "sg:tags":[
        "heating"
    ],
    "wof:name":"B L Simpson",
    "wof:placetype":"venue"
},
  "geometry": {"coordinates":[0.2444760054,50.8567504883],"type":"Point"}
}