{
  "type": "Feature",
  "properties": {
    "iso:country":"GB",
    "sg:address":"824-826 Harrow Road, Sudbury",
    "sg:city":"Wembley",
    "sg:classifiers":[
        {
            "category":"Retail",
            "subcategory":"Auto Repair",
            "type":"Services"
        }
    ],
    "sg:phone":"+44 20 8902 5131",
    "sg:postcode":"HA0 3EN",
    "sg:province":"Greater London",
    "sg:tags":[
        "modification",
        "garage"
    ],
    "wof:name":"Needleholm Ltd.",
    "wof:placetype":"venue"
},
  "geometry": {"coordinates":[-0.31612,51.555538],"type":"Point"}
}