{
  "type": "Feature",
  "properties": {
    "addr:full":"Connaught Plane Attleborough Norfolk NR17 2EG",
    "addr:postcode":"nr17 2eg",
    "addr:street":"Connaught Plane Attleborough",
    "iso:country":"GB",
    "sg:address":"Connaught Plane",
    "sg:city":"Attleborough",
    "sg:classifiers":[
        {
            "category":"Banks & Credit Unions",
            "subcategory":"Bank",
            "type":"Services"
        }
    ],
    "sg:phone":"+44 1953 457555",
    "sg:postcode":"NR17 2EG",
    "sg:province":"Norfolk",
    "sg:tags":[
        "broker",
        "mortgage"
    ],
    "wof:name":"Attleborough Mortgage Centre",
    "wof:placetype":"venue"
},
  "geometry": {"coordinates":[1.0144350529,52.5190544128],"type":"Point"}
}