{
  "type": "Feature",
  "properties": {
    "addr:full":"30 Fourth Street Peterlee Durham SR8 4LD",
    "addr:housenumber":"30",
    "addr:postcode":"sr8 4ld",
    "addr:street":"Fourth Street",
    "iso:country":"GB",
    "sg:address":"30 Fourth Street",
    "sg:city":"Peterlee",
    "sg:classifiers":[
        {
            "category":"Home & Garden",
            "subcategory":"Carpets & Floor Coverings",
            "type":"Retail Goods"
        }
    ],
    "sg:phone":"+44 191 587 2591",
    "sg:postcode":"SR8 4LD",
    "sg:province":"Durham",
    "sg:tags":[
        "carpets",
        "rug",
        "matting"
    ],
    "wof:name":"Factory Carpets Direct",
    "wof:placetype":"venue"
},
  "geometry": {"coordinates":[-1.312799,54.76395],"type":"Point"}
}