{
  "type": "Feature",
  "properties": {
    "addr:full":"Ness Road, Slade Grn Erith Kent DA8 2LD",
    "addr:postcode":"da8 2ld",
    "addr:street":"Ness Road",
    "iso:country":"GB",
    "sg:address":"Ness Road, Slade Grn",
    "sg:city":"Erith",
    "sg:classifiers":[
        {
            "category":"Manufacturing",
            "subcategory":"Lumber",
            "type":"Manufacturing & Wholesale Goods"
        }
    ],
    "sg:phone":"+44 1322 333088",
    "sg:postcode":"DA8 2LD",
    "sg:province":"Kent",
    "sg:tags":[
        "importer",
        "merchants",
        "agent",
        "timber"
    ],
    "wof:name":"E Jones & Sons (Slade Green) Ltd.",
    "wof:placetype":"venue"
},
  "geometry": {"coordinates":[0.2110719979,51.4770698547],"type":"Point"}
}