{
  "type": "Feature",
  "properties": {
    "addr:full":"The Grain Silo's Weyhill Road Andover Hampshire SP10 3NT",
    "addr:postcode":"sp10 3nt",
    "addr:street":"Weyhill Road",
    "iso:country":"GB",
    "sg:address":"The Grain Silo's Weyhill Road",
    "sg:city":"Andover",
    "sg:classifiers":[
        {
            "category":"Wholesale",
            "subcategory":"Farm Supplies",
            "type":"Manufacturing & Wholesale Goods"
        }
    ],
    "sg:phone":"+44 1264 388000",
    "sg:postcode":"SP10 3NT",
    "sg:province":"Hampshire",
    "sg:tags":[
        "merchant",
        "grain"
    ],
    "wof:name":"Banks Southern",
    "wof:placetype":"venue"
},
  "geometry": {"coordinates":[-1.50487,51.206909],"type":"Point"}
}