{
  "type": "Feature",
  "properties": {
    "addr:full":"47 High St Birmingham West Midlands B17 9NT",
    "addr:housenumber":"47",
    "addr:postcode":"b17 9nt",
    "addr:street":"High St",
    "iso:country":"GB",
    "sg:address":"47 High St",
    "sg:city":"Birmingham",
    "sg:classifiers":[
        {
            "category":"Shopping",
            "subcategory":"Music",
            "type":"Retail Goods"
        }
    ],
    "sg:phone":"+44 121 428 3138",
    "sg:postcode":"B17 9NT",
    "sg:province":"West Midlands",
    "sg:tags":[
        "record",
        "tape",
        "cd"
    ],
    "wof:name":"Highway 61",
    "wof:placetype":"venue"
},
  "geometry": {"coordinates":[-1.9443049431,52.4606971741],"type":"Point"}
}