{
  "type": "Feature",
  "properties": {
    "iso:country":"GB",
    "sg:address":"69 Fountains Crescent",
    "sg:city":"London",
    "sg:classifiers":[
        {
            "category":"Building & Trades",
            "subcategory":"Construction",
            "type":"Services"
        }
    ],
    "sg:phone":"+44 20 8882 3125",
    "sg:postcode":"N14 6BD",
    "sg:province":"Greater London",
    "sg:tags":[
        "joinery",
        "joiner",
        "carpenter",
        "carpentry"
    ],
    "wof:name":"T J Barrett (Carpentry & Joinery) Ltd.",
    "wof:placetype":"venue"
},
  "geometry": {"coordinates":[-0.120251,51.638474],"type":"Point"}
}