{
  "type": "Feature",
  "properties": {
    "addr:full":"1a Dudley Gardens, Ealing London Greater London W13 9LU",
    "addr:housenumber":"1a",
    "addr:postcode":"w13 9lu",
    "addr:street":"Dudley Gardens",
    "iso:country":"GB",
    "sg:address":"1a Dudley Gardens, Ealing",
    "sg:city":"London",
    "sg:classifiers":[
        {
            "category":"Farming",
            "subcategory":"Nursery",
            "type":"Manufacturing & Wholesale Goods"
        }
    ],
    "sg:phone":"+44 20 8566 3349",
    "sg:postcode":"W13 9LU",
    "sg:province":"Greater London",
    "sg:tags":[
        "creche"
    ],
    "wof:name":"Little Angels Day Nurseries",
    "wof:placetype":"venue"
},
  "geometry": {"coordinates":[-0.3184849918,51.5044021606],"type":"Point"}
}