{
  "type": "Feature",
  "properties": {
    "addr:full":"12 Dolphin Mews, Holywell Hill St Albans Hertfordshire AL1 1EZ",
    "addr:housenumber":"12",
    "addr:postcode":"al1 1ez",
    "addr:street":"Dolphin Mews Holywell Hill",
    "iso:country":"GB",
    "sg:address":"12 Dolphin Mews, Holywell Hill",
    "sg:city":"St Albans",
    "sg:classifiers":[
        {
            "category":"Organizations",
            "subcategory":"Community Association",
            "type":"Services"
        }
    ],
    "sg:phone":"+44 1727 836238",
    "sg:postcode":"AL1 1EZ",
    "sg:province":"Hertfordshire",
    "sg:tags":[
        "relation",
        "public"
    ],
    "wof:name":"Project 100",
    "wof:placetype":"venue"
},
  "geometry": {"coordinates":[-0.337752,51.753189],"type":"Point"}
}