{
  "type": "Feature",
  "properties": {
    "iso:country":"GB",
    "sg:address":"158 Werrington Rd",
    "sg:city":"Stoke-on-trent",
    "sg:classifiers":[
        {
            "category":"Home & Garden",
            "subcategory":"Home Furnishings",
            "type":"Retail Goods"
        }
    ],
    "sg:postcode":"ST2 9AW",
    "sg:province":"Staffordshire",
    "sg:tags":[
        "furnishers",
        "planner",
        "kitchen"
    ],
    "wof:name":"Qualifit Kitchens & Bedrooms",
    "wof:placetype":"venue"
},
  "geometry": {"coordinates":[-2.1432271004,53.0248985291],"type":"Point"}
}