{
  "type": "Feature",
  "properties": {
    "iso:country":"GB",
    "sg:address":"Gainsborough Drive",
    "sg:city":"Wolverhampton",
    "sg:classifiers":[
        {
            "category":"Education",
            "subcategory":"School",
            "type":"Public Place"
        }
    ],
    "sg:phone":"+44 1902 758244",
    "sg:postcode":"WV6 7NR",
    "sg:province":"Shropshire",
    "sg:tags":[
        "local",
        "authority"
    ],
    "wof:name":"Perton Middle School",
    "wof:placetype":"venue"
},
  "geometry": {"coordinates":[-2.1926269531,52.5977706909],"type":"Point"}
}