{
  "type": "Feature",
  "properties": {
    "addr:full":"90 Heol Uchaf Cardiff Cardiff CF14 6SR",
    "addr:housenumber":"90",
    "addr:postcode":"cf14 6sr",
    "addr:street":"Heol Uchaf",
    "iso:country":"GB",
    "sg:address":"90 Heol Uchaf",
    "sg:city":"Cardiff",
    "sg:classifiers":[
        {
            "category":"Building & Trades",
            "subcategory":"Plumbing",
            "type":"Services"
        }
    ],
    "sg:phone":"+44 29 2061 7059",
    "sg:postcode":"CF14 6SR",
    "sg:province":"Cardiff",
    "sg:tags":[
        "central",
        "heating"
    ],
    "wof:name":"Edwin David Lampert",
    "wof:placetype":"venue"
},
  "geometry": {"coordinates":[-3.211403,51.531582],"type":"Point"}
}