{
  "type": "Feature",
  "properties": {
    "iso:country":"GB",
    "sg:address":"Dale Road, Marple",
    "sg:city":"Stockport",
    "sg:classifiers":[
        {
            "category":"Farming",
            "subcategory":"Livestock Farm",
            "type":"Manufacturing & Wholesale Goods"
        }
    ],
    "sg:phone":"+44 161 427 1136",
    "sg:postcode":"SK6 6NL",
    "sg:province":"Cheshire",
    "sg:tags":[
        "others"
    ],
    "wof:name":"Tim K Clark",
    "wof:placetype":"venue"
},
  "geometry": {"coordinates":[-2.0698690414,53.3956108093],"type":"Point"}
}