{
  "type": "Feature",
  "properties": {
    "addr:full":"47a Elmer Rd Bognor Regis West Sussex PO22 6DZ",
    "addr:housenumber":"47a",
    "addr:postcode":"po22 6dz",
    "addr:street":"Elmer Rd",
    "iso:country":"GB",
    "sg:address":"47a Elmer Rd",
    "sg:city":"Bognor Regis",
    "sg:classifiers":[
        {
            "category":"Food & Beverages",
            "subcategory":"Meat & Fish",
            "type":"Retail Goods"
        }
    ],
    "sg:phone":"+44 1243 586553",
    "sg:postcode":"PO22 6DZ",
    "sg:province":"West Sussex",
    "sg:tags":[
        "butcher"
    ],
    "wof:name":"T W Lawrence",
    "wof:placetype":"venue"
},
  "geometry": {"coordinates":[-0.617099,50.795025],"type":"Point"}
}