{
  "type": "Feature",
  "properties": {
    "iso:country":"GB",
    "sg:address":"83 Park Street",
    "sg:city":"Luton",
    "sg:classifiers":[
        {
            "category":"Fast Food",
            "type":"Food & Drink"
        }
    ],
    "sg:phone":"+44 7946 758821",
    "sg:postcode":"LU1 3HG",
    "sg:province":"Bedfordshire",
    "sg:tags":[
        "away",
        "meal",
        "outlet",
        "take"
    ],
    "wof:name":"Saregama Indian Cuisine",
    "wof:placetype":"venue"
},
  "geometry": {"coordinates":[-0.4126339853,51.8781890869],"type":"Point"}
}