{
  "type": "Feature",
  "properties": {
    "iso:country":"GB",
    "sg:address":"Reculver Lane, Reculver",
    "sg:city":"Herne Bay",
    "sg:classifiers":[
        {
            "category":"Recreation",
            "subcategory":"Campground",
            "type":"Entertainment"
        }
    ],
    "sg:phone":"+44 1227 375406",
    "sg:postcode":"CT6 6SS",
    "sg:province":"Kent",
    "sg:tags":[
        "caravan",
        "park"
    ],
    "wof:name":"Blue Dolphin Park",
    "wof:placetype":"venue"
},
  "geometry": {"coordinates":[1.197978,51.378696],"type":"Point"}
}