{
  "type": "Feature",
  "properties": {
    "addr:full":"Hargrave Mansions, Hargrave Rd Archway Greater London N19 5SR",
    "addr:postcode":"n19 5sr",
    "addr:street":"Hargrave Rd",
    "iso:country":"GB",
    "sg:address":"Hargrave Mansions, Hargrave Rd",
    "sg:city":"Archway",
    "sg:classifiers":[
        {
            "category":"Education",
            "subcategory":"Preschool",
            "type":"Public Place"
        }
    ],
    "sg:phone":"+44 20 7272 5699",
    "sg:postcode":"N19 5SR",
    "sg:province":"Greater London",
    "sg:tags":[
        "pre-school",
        "playgroups"
    ],
    "wof:name":"Rocking Horse Playgroup",
    "wof:placetype":"venue"
},
  "geometry": {"coordinates":[-0.13283,51.563938],"type":"Point"}
}