{
  "type": "Feature",
  "properties": {
    "iso:country":"GB",
    "sg:address":"125 Turnpike Lane",
    "sg:city":"London",
    "sg:classifiers":[
        {
            "category":"Fast Food",
            "type":"Food & Drink"
        },
        {
            "category":"Restaurant",
            "type":"Food & Drink"
        }
    ],
    "sg:phone":"+44 20 8340 0673",
    "sg:postcode":"N8 0DU",
    "sg:province":"Greater London",
    "sg:tags":[
        "away",
        "meal",
        "outlet",
        "take"
    ],
    "wof:name":"MOHAMED SALIM",
    "wof:placetype":"venue"
},
  "geometry": {"coordinates":[-0.109472,51.588898],"type":"Point"}
}