{
  "type": "Feature",
  "properties": {
    "iso:country":"GB",
    "sg:address":"Shopping Centre, Glenloy Road, Caol",
    "sg:city":"Fort William",
    "sg:classifiers":[
        {
            "category":"Shopping",
            "subcategory":"Thrift Store",
            "type":"Retail Goods"
        }
    ],
    "sg:phone":"+44 1397 701516",
    "sg:postcode":"PH33 7DR",
    "sg:province":"Highland",
    "sg:tags":[
        "shop",
        "charity"
    ],
    "wof:name":"Blythswood Charity Shop",
    "wof:placetype":"venue"
},
  "geometry": {"coordinates":[-5.102344,56.838356],"type":"Point"}
}