{
  "type": "Feature",
  "properties": {
    "addr:full":"82 High Road, Carlton-in-lindrick Worksop Nottinghamshire S81 9EA",
    "addr:housenumber":"82",
    "addr:postcode":"s81 9ea",
    "addr:street":"High Road Carlton-In-Lindrick",
    "iso:country":"GB",
    "sg:address":"82 High Road, Carlton-in-lindrick",
    "sg:city":"Worksop",
    "sg:classifiers":[
        {
            "category":"Personal",
            "subcategory":"Beauty Salon",
            "type":"Services"
        }
    ],
    "sg:phone":"+44 1909 732696",
    "sg:postcode":"S81 9EA",
    "sg:province":"Nottinghamshire",
    "sg:tags":[
        "unisex",
        "hairdresser"
    ],
    "wof:name":"Headways",
    "wof:placetype":"venue"
},
  "geometry": {"coordinates":[-1.1133710146,53.3528060913],"type":"Point"}
}