{
  "type": "Feature",
  "properties": {
    "addr:full":"Within Anglo Service Station, Uttoxeter Rd Stoke On Trent Staffordshire ST3 1PX",
    "addr:postcode":"st3 1px",
    "addr:street":"Uttoxeter Rd",
    "iso:country":"GB",
    "sg:address":"Within Anglo Service Station, Uttoxeter Rd",
    "sg:city":"Stoke On Trent",
    "sg:classifiers":[
        {
            "category":"Autos & Motor Vehicles",
            "subcategory":"Automobile Sales",
            "type":"Retail Goods"
        }
    ],
    "sg:phone":"+44 1782 596022",
    "sg:postcode":"ST3 1PX",
    "sg:province":"Staffordshire",
    "sg:tags":[
        "commercial"
    ],
    "wof:name":"Kevin Turner Cars",
    "wof:placetype":"venue"
},
  "geometry": {"coordinates":[-2.1266400814,52.9847488403],"type":"Point"}
}