{
  "type": "Feature",
  "properties": {
    "iso:country":"GB",
    "sg:address":"5a Jewry Street",
    "sg:city":"Winchester",
    "sg:classifiers":[
        {
            "category":"Retail",
            "subcategory":"Event Space",
            "type":"Services"
        }
    ],
    "sg:phone":"+44 1962 849841",
    "sg:postcode":"SO23 8RZ",
    "sg:province":"Hampshire",
    "sg:tags":[
        "exhibition",
        "organiser"
    ],
    "wof:name":"Hat Fair",
    "wof:placetype":"venue"
},
  "geometry": {"coordinates":[-1.316402,51.063847],"type":"Point"}
}