{
  "type": "Feature",
  "properties": {
    "addr:full":"5 Broadmeadow Ride, St. Ippolyts Hitchin Hertfordshire SG4 7ST",
    "addr:housenumber":"5",
    "addr:postcode":"sg4 7st",
    "addr:street":"Broadmeadow Ride",
    "iso:country":"GB",
    "sg:address":"5 Broadmeadow Ride, St. Ippolyts",
    "sg:city":"Hitchin",
    "sg:classifiers":[
        {
            "category":"Home & Garden",
            "subcategory":"Household Appliances",
            "type":"Retail Goods"
        }
    ],
    "sg:phone":"+44 1462 621144",
    "sg:postcode":"SG4 7ST",
    "sg:province":"Hertfordshire",
    "sg:tags":[
        "equipment",
        "air conditioning"
    ],
    "wof:name":"M.J Dennis & Partner",
    "wof:placetype":"venue"
},
  "geometry": {"coordinates":[-0.268318,51.935837],"type":"Point"}
}