{
  "type": "Feature",
  "properties": {
    "addr:full":"128 Broughton Street Manchester Greater Manchester M8 8AN",
    "addr:housenumber":"128",
    "addr:postcode":"m8 8an",
    "addr:street":"Broughton Street",
    "iso:country":"GB",
    "sg:address":"128 Broughton Street",
    "sg:city":"Manchester",
    "sg:classifiers":[
        {
            "category":"Manufacturing",
            "subcategory":"Textiles",
            "type":"Manufacturing & Wholesale Goods"
        },
        {
            "category":"Home & Garden",
            "subcategory":"Carpets & Floor Coverings",
            "type":"Retail Goods"
        }
    ],
    "sg:phone":"+44 161 835 3211",
    "sg:postcode":"M8 8AN",
    "sg:province":"Greater Manchester",
    "sg:tags":[
        "merchant",
        "agent"
    ],
    "wof:name":"Rialto Textiles Ltd.",
    "wof:placetype":"venue"
},
  "geometry": {"coordinates":[-2.24553895,53.4969406128],"type":"Point"}
}