{
  "type": "Feature",
  "properties": {
    "addr:full":"St Georges Buildings, 5 St Vincent Place Glasgow Glasgow City G1 2DH",
    "addr:housenumber":"5",
    "addr:postcode":"g1 2dh",
    "addr:street":"St Georges Buildings;St Vincent Place",
    "iso:country":"GB",
    "sg:address":"St Georges Buildings, 5 St Vincent Place",
    "sg:city":"Glasgow",
    "sg:classifiers":[
        {
            "category":"Professional",
            "subcategory":"Lawyer & Legal Services",
            "type":"Services"
        }
    ],
    "sg:phone":"+44 141 221 9981",
    "sg:postcode":"G1 2DH",
    "sg:province":"Glasgow City",
    "sg:tags":[
        "solicitor"
    ],
    "wof:name":"John Mcgovern & Co",
    "wof:placetype":"venue"
},
  "geometry": {"coordinates":[-4.2522602081,55.8608589172],"type":"Point"}
}