{
  "type": "Feature",
  "properties": {
    "iso:country":"GB",
    "sg:address":"Ability Ho, 242 Gosport Rd",
    "sg:city":"Fareham",
    "sg:classifiers":[
        {
            "category":"Social Services",
            "type":"Services"
        }
    ],
    "sg:phone":"+44 1329 828444",
    "sg:postcode":"PO16 0SS",
    "sg:province":"Hampshire",
    "sg:tags":[
        "disability"
    ],
    "wof:name":"Quest Enabling Designs Ltd",
    "wof:placetype":"venue"
},
  "geometry": {"coordinates":[-1.174099,50.852734],"type":"Point"}
}