{
  "type": "Feature",
  "properties": {
    "addr:full":"28 Anson Road, Martlesham Heath Ipswich Suffolk IP5 3RG",
    "addr:housenumber":"28",
    "addr:postcode":"ip5 3rg",
    "addr:street":"Anson Road",
    "iso:country":"GB",
    "sg:address":"28 Anson Road, Martlesham Heath",
    "sg:city":"Ipswich",
    "sg:classifiers":[
        {
            "category":"Building & Trades",
            "subcategory":"Plumbing",
            "type":"Services"
        }
    ],
    "sg:phone":"+44 1473 611744",
    "sg:postcode":"IP5 3RG",
    "sg:province":"Suffolk",
    "sg:tags":[
        "repair",
        "heating",
        "servicing",
        "boiler"
    ],
    "wof:name":"John T Wilding (Maintenance) Ltd.",
    "wof:placetype":"venue"
},
  "geometry": {"coordinates":[1.2814760208,52.0625038147],"type":"Point"}
}