{
  "type": "Feature",
  "properties": {
    "addr:full":"2 Barnfield Cotts, Poltimore Exeter Devon EX4 0AL",
    "addr:housenumber":"2;cotts",
    "addr:postcode":"ex4 0al",
    "addr:street":"Barnfield",
    "iso:country":"GB",
    "sg:address":"2 Barnfield Cotts, Poltimore",
    "sg:city":"Exeter",
    "sg:classifiers":[
        {
            "category":"Retail",
            "subcategory":"Auto Repair",
            "type":"Services"
        }
    ],
    "sg:phone":"+44 1392 461427",
    "sg:postcode":"EX4 0AL",
    "sg:province":"Devon",
    "sg:tags":[
        "modification",
        "garage"
    ],
    "wof:name":"T J & W A Howe",
    "wof:placetype":"venue"
},
  "geometry": {"coordinates":[-3.4684939384,50.7626190186],"type":"Point"}
}