{
  "type": "Feature",
  "properties": {
    "iso:country":"GB",
    "sg:address":"55 Adelaide Rd",
    "sg:city":"Southall",
    "sg:classifiers":[
        {
            "category":"Personal",
            "subcategory":"Beauty Salon",
            "type":"Services"
        }
    ],
    "sg:postcode":"UB2 5PY",
    "sg:province":"Greater London",
    "sg:tags":[
        "lady",
        "hairdresser"
    ],
    "wof:name":"Sweales,Lynne A,",
    "wof:placetype":"venue"
},
  "geometry": {"coordinates":[-0.3834039867,51.4974861145],"type":"Point"}
}