{
  "type": "Feature",
  "properties": {
    "addr:full":"75 Westgate Worksop Nottinghamshire S80 1LW",
    "addr:housenumber":"75",
    "addr:postcode":"s80 1lw",
    "addr:street":"Westgate",
    "iso:country":"GB",
    "sg:address":"75 Westgate",
    "sg:city":"Worksop",
    "sg:classifiers":[
        {
            "category":"Professional",
            "subcategory":"Detective & Security Services",
            "type":"Services"
        }
    ],
    "sg:postcode":"S80 1LW",
    "sg:province":"Nottinghamshire",
    "sg:tags":[
        "locksmith"
    ],
    "wof:name":"Stapleton Lock & Save",
    "wof:placetype":"venue"
},
  "geometry": {"coordinates":[-1.128096,53.302364],"type":"Point"}
}