{
  "type": "Feature",
  "properties": {
    "addr:full":"7 Town Square Northwich Cheshire CW9 5AR",
    "addr:housenumber":"7",
    "addr:postcode":"cw9 5ar",
    "addr:street":"Town Square",
    "iso:country":"GB",
    "sg:address":"7 Town Square",
    "sg:city":"Northwich",
    "sg:classifiers":[
        {
            "category":"Professional",
            "subcategory":"Art Services",
            "type":"Services"
        }
    ],
    "sg:phone":"+44 1606 350220",
    "sg:postcode":"CW9 5AR",
    "sg:province":"Cheshire",
    "sg:tags":[
        "framing"
    ],
    "wof:name":"The Picture & Mirror Shop",
    "wof:placetype":"venue"
},
  "geometry": {"coordinates":[-2.514174,53.261517],"type":"Point"}
}