{
  "type": "Feature",
  "properties": {
    "iso:country":"GB",
    "sg:address":"49 Heath Street, Golborne",
    "sg:city":"Warrington",
    "sg:classifiers":[
        {
            "category":"Building & Trades",
            "subcategory":"Construction",
            "type":"Services"
        }
    ],
    "sg:phone":"+44 1942 720445",
    "sg:postcode":"WA3 3BS",
    "sg:province":"Cheshire",
    "sg:tags":[
        "pipework",
        "contractor"
    ],
    "wof:name":"J L J Engineering Services Ltd.",
    "wof:placetype":"venue"
},
  "geometry": {"coordinates":[-2.5997540951,53.4767875671],"type":"Point"}
}