{
  "type": "Feature",
  "properties": {
    "addr:full":"The Vicarage, Front St Durham Durham DH6 2UA",
    "addr:postcode":"dh6 2ua",
    "addr:street":"Front St",
    "iso:country":"GB",
    "sg:address":"The Vicarage, Front St",
    "sg:city":"Durham",
    "sg:classifiers":[
        {
            "category":"Place Of Worship",
            "type":"Public Place"
        }
    ],
    "sg:phone":"+44 191 526 1157",
    "sg:postcode":"DH6 2UA",
    "sg:province":"Durham",
    "wof:name":"Holy Trinity C Of E Church",
    "wof:placetype":"venue"
},
  "geometry": {"coordinates":[-1.3976390362,54.7965202332],"type":"Point"}
}