{
  "type": "Feature",
  "properties": {
    "iso:country":"GB",
    "sg:address":"30 Hanson Dr",
    "sg:city":"Loughton",
    "sg:classifiers":[
        {
            "category":"Building & Trades",
            "subcategory":"Construction",
            "type":"Services"
        }
    ],
    "sg:phone":"+44 20 8508 0669",
    "sg:postcode":"IG10 2EB",
    "sg:province":"Essex",
    "sg:tags":[
        "dry",
        "lining",
        "plasterers",
        "screeders"
    ],
    "wof:name":"Hanson Decorators",
    "wof:placetype":"venue"
},
  "geometry": {"coordinates":[0.081781,51.653809],"type":"Point"}
}