{
  "type": "Feature",
  "properties": {
    "iso:country":"GB",
    "sg:address":"322h Mayoral Way, Team Valley Trading Estate",
    "sg:city":"Gateshead",
    "sg:classifiers":[
        {
            "category":"Retail",
            "subcategory":"Event Space",
            "type":"Services"
        },
        {
            "category":"Shopping",
            "subcategory":"Computers & Home Electronics",
            "type":"Retail Goods"
        }
    ],
    "sg:phone":"+44 191 491 3939",
    "sg:postcode":"NE11 0RT",
    "sg:province":"Tyne and Wear",
    "sg:tags":[
        "product",
        "electrical",
        "sales"
    ],
    "wof:name":"Bondgate Electrical Distribution Ltd",
    "wof:placetype":"venue"
},
  "geometry": {"coordinates":[-1.6171289682,54.9254417419],"type":"Point"}
}