{
  "type": "Feature",
  "properties": {
    "iso:country":"GB",
    "sg:address":"Roselea House, Pencoed Lane, Llanmartin",
    "sg:city":"Newport",
    "sg:classifiers":[
        {
            "category":"Shopping",
            "subcategory":"Bicycles & Sporting Goods",
            "type":"Retail Goods"
        }
    ],
    "sg:phone":"+44 1633 413377",
    "sg:postcode":"NP18 2ED",
    "sg:province":"Monmouthshire",
    "sg:tags":[
        "equipment",
        "marine",
        "supply"
    ],
    "wof:name":"T S 2",
    "wof:placetype":"venue"
},
  "geometry": {"coordinates":[-2.871293,51.600029],"type":"Point"}
}