{
  "type": "Feature",
  "properties": {
    "iso:country":"GB",
    "sg:address":"135 Buchanan St",
    "sg:city":"Glasgow",
    "sg:classifiers":[
        {
            "category":"Real Estate",
            "subcategory":"Developer",
            "type":"Services"
        }
    ],
    "sg:phone":"+44 141 221 8288",
    "sg:postcode":"G1 2JA",
    "sg:province":"Glasgow City",
    "sg:tags":[
        "property"
    ],
    "wof:name":"Buchanan Partnership",
    "wof:placetype":"venue"
},
  "geometry": {"coordinates":[-4.2540588379,55.8610649109],"type":"Point"}
}