{
  "type": "Feature",
  "properties": {
    "addr:full":"Peas Hill Road March Cambridgeshire PE15 8HE",
    "addr:postcode":"pe15 8he",
    "addr:street":"Peas Hill Road",
    "iso:country":"GB",
    "sg:address":"Peas Hill Road",
    "sg:city":"March",
    "sg:classifiers":[
        {
            "category":"Farming",
            "subcategory":"Dairy Farm",
            "type":"Manufacturing & Wholesale Goods"
        },
        {
            "category":"Food & Beverages",
            "subcategory":"Groceries & Convenience Stores",
            "type":"Retail Goods"
        }
    ],
    "sg:postcode":"PE15 8HE",
    "sg:province":"Cambridgeshire",
    "wof:name":"Baxters Dairy",
    "wof:placetype":"venue"
},
  "geometry": {"coordinates":[0.067925,52.55619],"type":"Point"}
}