{
  "type": "Feature",
  "properties": {
    "addr:full":"Wards Farm, Chittlehamholt Umberleigh Devon EX37 9PB",
    "addr:housenumber":"chittlehamholt",
    "addr:postcode":"ex37 9pb",
    "addr:street":"Umberleigh",
    "iso:country":"GB",
    "sg:address":"Wards Farm, Chittlehamholt",
    "sg:city":"Umberleigh",
    "sg:classifiers":[
        {
            "category":"Farming",
            "subcategory":"Farm",
            "type":"Manufacturing & Wholesale Goods"
        }
    ],
    "sg:postcode":"EX37 9PB",
    "sg:province":"Devon",
    "sg:tags":[
        "mixed",
        "crop"
    ],
    "wof:name":"Frank Congram",
    "wof:placetype":"venue"
},
  "geometry": {"coordinates":[-3.9853448868,50.9958152771],"type":"Point"}
}