{
  "type": "Feature",
  "properties": {
    "addr:full":"19 Buxton Rd East Sheen Greater London SW14 8SY",
    "addr:housenumber":"19",
    "addr:postcode":"sw14 8sy",
    "addr:street":"Buxton Rd",
    "iso:country":"GB",
    "sg:address":"19 Buxton Rd",
    "sg:city":"East Sheen",
    "sg:classifiers":[
        {
            "category":"Shopping",
            "subcategory":"Musical Instruments",
            "type":"Retail Goods"
        }
    ],
    "sg:phone":"+44 20 8876 1496",
    "sg:postcode":"SW14 8SY",
    "sg:province":"Greater London",
    "wof:name":"Harpsichord Services of London",
    "wof:placetype":"venue"
},
  "geometry": {"coordinates":[-0.2545489967,51.4669723511],"type":"Point"}
}