{
  "type": "Feature",
  "properties": {
    "iso:country":"GB",
    "sg:address":"41 Edgeley Road, Countesthorpe",
    "sg:city":"Leicester",
    "sg:classifiers":[
        {
            "category":"Professional",
            "subcategory":"Management & Consulting",
            "type":"Services"
        }
    ],
    "sg:postcode":"LE8 5QN",
    "sg:province":"Leicestershire",
    "sg:tags":[
        "consultant",
        "training"
    ],
    "wof:name":"T W Associates",
    "wof:placetype":"venue"
},
  "geometry": {"coordinates":[-1.1383320093,52.5577926636],"type":"Point"}
}