{
  "type": "Feature",
  "properties": {
    "iso:country":"GB",
    "sg:address":"31 Mayflower Way",
    "sg:city":"Beaconsfield",
    "sg:classifiers":[
        {
            "category":"Manufacturing",
            "subcategory":"Petroleum Products",
            "type":"Manufacturing & Wholesale Goods"
        }
    ],
    "sg:phone":"+44 1494 672924",
    "sg:postcode":"HP9 1UG",
    "sg:province":"Buckinghamshire",
    "sg:tags":[
        "double",
        "glazing"
    ],
    "wof:name":"Warwick Doors",
    "wof:placetype":"venue"
},
  "geometry": {"coordinates":[-0.6647850275,51.6010780334],"type":"Point"}
}