{
  "type": "Feature",
  "properties": {
    "iso:country":"GB",
    "sg:address":"7 Romsey Road, Shirley",
    "sg:city":"Southampton",
    "sg:classifiers":[
        {
            "category":"Food & Beverages",
            "subcategory":"Meat & Fish",
            "type":"Retail Goods"
        }
    ],
    "sg:postcode":"SO16 4BY",
    "sg:province":"Hampshire",
    "sg:tags":[
        "chip"
    ],
    "wof:name":"Jim's Fish Bar & Cafe",
    "wof:placetype":"venue"
},
  "geometry": {"coordinates":[-1.435472,50.924042],"type":"Point"}
}