{
  "type": "Feature",
  "properties": {
    "addr:full":"10a New Street, Barlestone Nuneaton Leicestershire CV13 0EA",
    "addr:housenumber":"10a",
    "addr:postcode":"cv13 0ea",
    "addr:street":"New Street",
    "iso:country":"GB",
    "sg:address":"10a New Street, Barlestone",
    "sg:city":"Nuneaton",
    "sg:classifiers":[
        {
            "category":"Building & Trades",
            "subcategory":"Electrical",
            "type":"Services"
        },
        {
            "category":"Organizations",
            "subcategory":"Non-profit Organization",
            "type":"Services"
        }
    ],
    "sg:phone":"+44 1455 292700",
    "sg:postcode":"CV13 0EA",
    "sg:province":"Leicestershire",
    "sg:tags":[
        "alarm",
        "electrician",
        "system",
        "contractor"
    ],
    "wof:name":"A B Electrical & Security",
    "wof:placetype":"venue"
},
  "geometry": {"coordinates":[-1.369204998,52.6468238831],"type":"Point"}
}