{
  "type": "Feature",
  "properties": {
    "addr:full":"246 Upton Road Ryde Isle of Wight PO33 3JG",
    "addr:housenumber":"246",
    "addr:postcode":"po33 3jg",
    "addr:street":"Upton Road",
    "iso:country":"GB",
    "sg:address":"246 Upton Road",
    "sg:city":"Ryde",
    "sg:classifiers":[
        {
            "category":"Government",
            "subcategory":"Post Office",
            "type":"Public Place"
        }
    ],
    "sg:phone":"+44 1983 615435",
    "sg:postcode":"PO33 3JG",
    "sg:province":"Isle of Wight",
    "wof:name":"Mary A & Leonard Monk",
    "wof:placetype":"venue"
},
  "geometry": {"coordinates":[-1.177364,50.715553],"type":"Point"}
}