{
  "type": "Feature",
  "properties": {
    "iso:country":"GB",
    "sg:address":"Brickfield Business Centre, 60 Manchester Rd",
    "sg:city":"Northwich",
    "sg:classifiers":[
        {
            "category":"Professional",
            "subcategory":"Computer Services",
            "type":"Services"
        }
    ],
    "sg:phone":"+44 1606 47004",
    "sg:postcode":"CW9 7LS",
    "sg:province":"Cheshire",
    "sg:tags":[
        "system",
        "software"
    ],
    "wof:name":"Torex BIT",
    "wof:placetype":"venue"
},
  "geometry": {"coordinates":[-2.511999,53.260471],"type":"Point"}
}