{
  "type": "Feature",
  "properties": {
    "iso:country":"GB",
    "sg:address":"N C C, Armstrong House, Oxford Road",
    "sg:city":"Manchester",
    "sg:classifiers":[
        {
            "category":"Organizations",
            "subcategory":"Non-profit Organization",
            "type":"Services"
        }
    ],
    "sg:phone":"+44 161 242 2316",
    "sg:postcode":"M1 7ED",
    "sg:province":"Greater Manchester",
    "sg:tags":[
        "charitable",
        "organisation",
        "voluntary",
        "charity"
    ],
    "wof:name":"THE ROYAL NATIONAL INSTITUTE FOR DEAF PEOPLE",
    "wof:placetype":"venue"
},
  "geometry": {"coordinates":[-2.237589,53.470684],"type":"Point"}
}