{
  "type": "Feature",
  "properties": {
    "addr:full":"474 Bethnal Green Road London Greater London E2 0EA",
    "addr:housenumber":"474",
    "addr:postcode":"e2 0ea",
    "addr:street":"Bethnal Green Road",
    "iso:country":"GB",
    "sg:address":"474 Bethnal Green Road",
    "sg:city":"London",
    "sg:classifiers":[
        {
            "category":"Food & Beverages",
            "subcategory":"Meat & Fish",
            "type":"Retail Goods"
        },
        {
            "category":"Food & Beverages",
            "subcategory":"Groceries & Convenience Stores",
            "type":"Retail Goods"
        }
    ],
    "sg:phone":"+44 20 7739 9426",
    "sg:postcode":"E2 0EA",
    "sg:province":"Greater London",
    "sg:tags":[
        "shop",
        "chip"
    ],
    "wof:name":"Regal Fish Bar",
    "wof:placetype":"venue"
},
  "geometry": {"coordinates":[-0.057638,51.527218],"type":"Point"}
}