{
  "type": "Feature",
  "properties": {
    "addr:full":"8 The Shrubberies, George Lane London Greater London E18 1BD",
    "addr:housenumber":"8",
    "addr:postcode":"e18 1bd",
    "addr:street":"The Shrubberies George Lane",
    "iso:country":"GB",
    "sg:address":"8 The Shrubberies, George Lane",
    "sg:city":"London",
    "sg:classifiers":[
        {
            "category":"Professional",
            "subcategory":"Accounting & Tax Preparation",
            "type":"Services"
        }
    ],
    "sg:postcode":"E18 1BD",
    "sg:province":"Greater London",
    "sg:tags":[
        "accountant"
    ],
    "wof:name":"Mark Smith & Co",
    "wof:placetype":"venue"
},
  "geometry": {"coordinates":[0.0246530008,51.5942993164],"type":"Point"}
}