{
  "type": "Feature",
  "properties": {
    "iso:country":"GB",
    "sg:address":"330 Killinghall Rd",
    "sg:city":"Bradford",
    "sg:classifiers":[
        {
            "category":"Travel",
            "subcategory":"Hotels & Motels",
            "type":"Entertainment"
        }
    ],
    "sg:phone":"+44 1274 640398",
    "sg:postcode":"BD2 4SE",
    "sg:province":"West Yorkshire",
    "sg:tags":[
        "house",
        "guest"
    ],
    "wof:name":"Guest House The",
    "wof:placetype":"venue"
},
  "geometry": {"coordinates":[-1.726511,53.806004],"type":"Point"}
}