{
  "type": "Feature",
  "properties": {
    "iso:country":"GB",
    "sg:address":"74 Scrub Rise",
    "sg:city":"Billericay",
    "sg:classifiers":[
        {
            "category":"Personal",
            "type":"Services"
        },
        {
            "category":"Professional",
            "subcategory":"Lawyer & Legal Services",
            "type":"Services"
        }
    ],
    "sg:phone":"+44 1277 654455",
    "sg:postcode":"CM12 9PE",
    "sg:province":"Essex",
    "sg:tags":[
        "advice",
        "counselling"
    ],
    "wof:name":"Dial A Bible Message Ministry",
    "wof:placetype":"venue"
},
  "geometry": {"coordinates":[0.40899,51.617485],"type":"Point"}
}