{
  "type": "Feature",
  "properties": {
    "addr:full":"St Johns Hill, Clapham Battersea Greater London SW11 1SD",
    "addr:postcode":"sw11 1sd",
    "addr:street":"St Johns Hill",
    "iso:country":"GB",
    "sg:address":"St Johns Hill, Clapham",
    "sg:city":"Battersea",
    "sg:classifiers":[
        {
            "category":"Organizations",
            "subcategory":"Political Organization",
            "type":"Services"
        }
    ],
    "sg:phone":"+44 20 7228 5266",
    "sg:postcode":"SW11 1SD",
    "sg:province":"Greater London",
    "sg:tags":[
        "promoter",
        "pool"
    ],
    "wof:name":"Gala Clubs",
    "wof:placetype":"venue"
},
  "geometry": {"coordinates":[-0.1696559936,51.4627189636],"type":"Point"}
}