{
  "type": "Feature",
  "properties": {
    "addr:full":"78 Raeburn Place Edinburgh City of Edinburgh EH4 1HJ",
    "addr:housenumber":"78",
    "addr:postcode":"eh4 1hj",
    "addr:street":"Raeburn Place Edinburgh",
    "iso:country":"GB",
    "sg:address":"78 Raeburn Place",
    "sg:city":"Edinburgh",
    "sg:classifiers":[
        {
            "category":"Retail",
            "subcategory":"Repair Shop",
            "type":"Services"
        }
    ],
    "sg:phone":"+44 131 332 1647",
    "sg:postcode":"EH4 1HJ",
    "sg:province":"City of Edinburgh",
    "sg:tags":[
        "clocks",
        "watch"
    ],
    "wof:name":"A B Aitchison Watchmaker & Jewellers",
    "wof:placetype":"venue"
},
  "geometry": {"coordinates":[-3.2130799294,55.9591445923],"type":"Point"}
}