{
  "type": "Feature",
  "properties": {
    "iso:country":"GB",
    "sg:address":"137 Madresfield Rd",
    "sg:city":"Malvern",
    "sg:classifiers":[
        {
            "category":"Place Of Worship",
            "type":"Public Place"
        }
    ],
    "sg:phone":"+44 1684 575994",
    "sg:postcode":"WR14 2HD",
    "sg:province":"Herefordshire",
    "wof:name":"St Marys House",
    "wof:placetype":"venue"
},
  "geometry": {"coordinates":[-2.304192,52.11515],"type":"Point"}
}