{
  "type": "Feature",
  "properties": {
    "addr:full":"23 Kettlehouse Road Birmingham West Midlands B44 9JH",
    "addr:housenumber":"23",
    "addr:postcode":"b44 9jh",
    "addr:street":"Kettlehouse Road",
    "iso:country":"GB",
    "sg:address":"23 Kettlehouse Road",
    "sg:city":"Birmingham",
    "sg:classifiers":[
        {
            "category":"Shopping",
            "subcategory":"Florist",
            "type":"Retail Goods"
        }
    ],
    "sg:postcode":"B44 9JH",
    "sg:province":"West Midlands",
    "wof:name":"Kingstanding Mayfair Flowers",
    "wof:placetype":"venue"
},
  "geometry": {"coordinates":[-1.8851389885,52.5540885925],"type":"Point"}
}