{
  "type": "Feature",
  "properties": {
    "addr:full":"27 Lower Parrock Road, Carr Hall, Barrowford Nelson Lancashire BB9 6DQ",
    "addr:housenumber":"27",
    "addr:postcode":"bb9 6dq",
    "addr:street":"Lower Parrock Road Carr Hall",
    "iso:country":"GB",
    "sg:address":"27 Lower Parrock Road, Carr Hall, Barrowford",
    "sg:city":"Nelson",
    "sg:classifiers":[
        {
            "category":"Building & Trades",
            "subcategory":"Plumbing",
            "type":"Services"
        }
    ],
    "sg:phone":"+44 1282 693481",
    "sg:postcode":"BB9 6DQ",
    "sg:province":"Lancashire",
    "sg:tags":[
        "heating"
    ],
    "wof:name":"G R Holden & Co",
    "wof:placetype":"venue"
},
  "geometry": {"coordinates":[-2.227995,53.841591],"type":"Point"}
}