{
  "type": "Feature",
  "properties": {
    "addr:full":"Long Trods Selby East Riding of Yorkshire YO8 3YU",
    "addr:postcode":"yo8 3yu",
    "addr:street":"Selby",
    "iso:country":"GB",
    "sg:address":"Long Trods",
    "sg:city":"Selby",
    "sg:classifiers":[
        {
            "category":"Retail",
            "subcategory":"Auto Repair",
            "type":"Services"
        }
    ],
    "sg:phone":"+44 1757 212486",
    "sg:postcode":"YO8 3YU",
    "sg:province":"East Riding of Yorkshire",
    "sg:tags":[
        "modification",
        "garage"
    ],
    "wof:name":"J J Motors",
    "wof:placetype":"venue"
},
  "geometry": {"coordinates":[-1.0740540028,53.7867698669],"type":"Point"}
}