{
  "type": "Feature",
  "properties": {
    "addr:full":"Walton High School, The Rise, Walton On The Hill Stafford Staffordshire ST17 0LJ",
    "addr:postcode":"st17 0lj",
    "addr:street":"The Rise",
    "iso:country":"GB",
    "sg:address":"Walton High School, The Rise, Walton On The Hill",
    "sg:city":"Stafford",
    "sg:classifiers":[
        {
            "category":"Community Center",
            "subcategory":"Youth",
            "type":"Public Place"
        },
        {
            "category":"Government",
            "subcategory":"Office",
            "type":"Public Place"
        }
    ],
    "sg:phone":"+44 1785 663593",
    "sg:postcode":"ST17 0LJ",
    "sg:province":"Staffordshire",
    "sg:tags":[
        "organisation",
        "local",
        "centre"
    ],
    "wof:name":"Walton Youth & Community Centre",
    "wof:placetype":"venue"
},
  "geometry": {"coordinates":[-2.0638940334,52.7885742188],"type":"Point"}
}