{
  "type": "Feature",
  "properties": {
    "addr:full":"9 Charlotte Street Lerwick Shetland Islands ZE1 0JL",
    "addr:housenumber":"9",
    "addr:postcode":"ze1 0jl",
    "addr:street":"Charlotte Street;Shetland",
    "iso:country":"GB",
    "sg:address":"9 Charlotte Street",
    "sg:city":"Lerwick",
    "sg:classifiers":[
        {
            "category":"Organizations",
            "subcategory":"Non-profit Organization",
            "type":"Services"
        }
    ],
    "sg:phone":"+44 1595 692100",
    "sg:postcode":"ZE1 0JL",
    "sg:province":"Shetland Islands",
    "sg:tags":[
        "organisation",
        "voluntary",
        "charity"
    ],
    "wof:name":"Havly Centre",
    "wof:placetype":"venue"
},
  "geometry": {"coordinates":[-1.1454019547,60.1548538208],"type":"Point"}
}