{
  "type": "Feature",
  "properties": {
    "addr:full":"40 Lyndhurst Road Worthing West Sussex BN11 2DF",
    "addr:housenumber":"40",
    "addr:postcode":"bn11 2df",
    "addr:street":"Lyndhurst Road",
    "iso:country":"GB",
    "sg:address":"40 Lyndhurst Road",
    "sg:city":"Worthing",
    "sg:classifiers":[
        {
            "category":"Fast Food",
            "type":"Food & Drink"
        }
    ],
    "sg:phone":"+44 1903 208730",
    "sg:postcode":"BN11 2DF",
    "sg:province":"West Sussex",
    "sg:tags":[
        "away",
        "take"
    ],
    "wof:name":"The Golden Bengal",
    "wof:placetype":"venue"
},
  "geometry": {"coordinates":[-0.3588509858,50.8160858154],"type":"Point"}
}