{
  "type": "Feature",
  "properties": {
    "iso:country":"GB",
    "sg:address":"2 New Moorhead Dr, Crawley Rd",
    "sg:city":"Horsham",
    "sg:classifiers":[
        {
            "category":"Communications",
            "subcategory":"News Services",
            "type":"Services"
        }
    ],
    "sg:phone":"+44 1403 241339",
    "sg:postcode":"RH12 4RX",
    "sg:province":"West Sussex",
    "sg:tags":[
        "illustrator"
    ],
    "wof:name":"C A D Services",
    "wof:placetype":"venue"
},
  "geometry": {"coordinates":[-0.287889,51.081356],"type":"Point"}
}