{
  "type": "Feature",
  "properties": {
    "iso:country":"GB",
    "sg:address":"139 London Road",
    "sg:city":"Newcastle",
    "sg:classifiers":[
        {
            "category":"Food & Beverages",
            "subcategory":"Fruits & Vegetables",
            "type":"Retail Goods"
        }
    ],
    "sg:postcode":"ST5 7JD",
    "sg:province":"Staffordshire",
    "sg:tags":[
        "greengrocer"
    ],
    "wof:name":"The Veg Plot",
    "wof:placetype":"venue"
},
  "geometry": {"coordinates":[-2.24836,53.03878],"type":"Point"}
}