{
  "type": "Feature",
  "properties": {
    "addr:full":"38 Clouston Street Glasgow Glasgow City G20 8QX",
    "addr:housenumber":"38",
    "addr:postcode":"g20 8qx",
    "addr:street":"Clouston Street",
    "iso:country":"GB",
    "sg:address":"38 Clouston Street",
    "sg:city":"Glasgow",
    "sg:classifiers":[
        {
            "category":"Communications",
            "type":"Services"
        }
    ],
    "sg:postcode":"G20 8QX",
    "sg:province":"Glasgow City",
    "sg:tags":[
        "broadcasting"
    ],
    "wof:name":"Glasgow Television Productions",
    "wof:placetype":"venue"
},
  "geometry": {"coordinates":[-4.287374,55.88171],"type":"Point"}
}