{
  "type": "Feature",
  "properties": {
    "iso:country":"GB",
    "sg:address":"Edinburgh House First Floor, 40 Great Portland Street",
    "sg:city":"London",
    "sg:classifiers":[
        {
            "category":"Real Estate",
            "subcategory":"Real Estate Agent",
            "type":"Services"
        }
    ],
    "sg:postcode":"W1W 7LZ",
    "sg:province":"Greater London",
    "wof:name":"Apres Estates Ltd",
    "wof:placetype":"venue"
},
  "geometry": {"coordinates":[-0.141629,51.517601],"type":"Point"}
}