{
  "type": "Feature",
  "properties": {
    "addr:full":"119 Birchwood, Shadwell Leeds North Yorkshire LS17 8NT",
    "addr:housenumber":"119",
    "addr:postcode":"ls17 8nt",
    "addr:street":"Birchwood",
    "iso:country":"GB",
    "sg:address":"119 Birchwood, Shadwell",
    "sg:city":"Leeds",
    "sg:classifiers":[
        {
            "category":"Retail",
            "subcategory":"Funeral Services",
            "type":"Services"
        }
    ],
    "sg:phone":"+44 113 266 2122",
    "sg:postcode":"LS17 8NT",
    "sg:province":"North Yorkshire",
    "sg:tags":[
        "cemetery",
        "crematorium"
    ],
    "wof:name":"Ellis Clarkson Ltd",
    "wof:placetype":"venue"
},
  "geometry": {"coordinates":[-1.5141960382,53.8519744873],"type":"Point"}
}