{
  "type": "Feature",
  "properties": {
    "iso:country":"GB",
    "sg:address":"Unit 13 Newhold Industrial Estate, Garforth",
    "sg:city":"Leeds",
    "sg:classifiers":[
        {
            "category":"Shopping",
            "subcategory":"Bicycles & Sporting Goods",
            "type":"Retail Goods"
        }
    ],
    "sg:postcode":"LS25 2LD",
    "sg:province":"North Yorkshire",
    "sg:tags":[
        "water",
        "cooler"
    ],
    "wof:name":"Aquarius Water Services Ltd.",
    "wof:placetype":"venue"
},
  "geometry": {"coordinates":[-1.375119,53.796974],"type":"Point"}
}