{
  "type": "Feature",
  "properties": {
    "addr:full":"27 Bridge St Row Chester Cheshire CH1 1NW",
    "addr:housenumber":"27",
    "addr:postcode":"ch1 1nw",
    "addr:street":"Bridge St Row",
    "iso:country":"GB",
    "sg:address":"27 Bridge St Row",
    "sg:city":"Chester",
    "sg:classifiers":[
        {
            "category":"Shopping",
            "subcategory":"Gifts & Souvenirs",
            "type":"Retail Goods"
        }
    ],
    "sg:phone":"+44 1244 401148",
    "sg:postcode":"CH1 1NW",
    "sg:province":"Cheshire",
    "sg:tags":[
        "shop"
    ],
    "wof:name":"M E & A C Porritt",
    "wof:placetype":"venue"
},
  "geometry": {"coordinates":[-2.891167,53.189583],"type":"Point"}
}