{
  "type": "Feature",
  "properties": {
    "addr:full":"Beechwood Play & Community Centre, Fifth Av Birkenhead Merseyside L43 9LB",
    "addr:postcode":"l43 9lb",
    "addr:street":"Fifth Av",
    "iso:country":"GB",
    "sg:address":"Beechwood Play & Community Centre, Fifth Av",
    "sg:city":"Birkenhead",
    "sg:classifiers":[
        {
            "category":"Government",
            "subcategory":"Office",
            "type":"Public Place"
        }
    ],
    "sg:phone":"+44 151 678 3939",
    "sg:postcode":"L43 9LB",
    "sg:province":"Merseyside",
    "sg:tags":[
        "local"
    ],
    "wof:name":"Metropolitan Borough of Wirral",
    "wof:placetype":"venue"
},
  "geometry": {"coordinates":[-3.083231926,53.3946418762],"type":"Point"}
}