{
  "type": "Feature",
  "properties": {
    "addr:full":"Launch Pad (the), Dower House Gatton Park Reigate Surrey RH2 0TA",
    "addr:postcode":"rh2 0ta",
    "addr:street":"Launch Pad The;Gatton Park",
    "iso:country":"GB",
    "sg:address":"Launch Pad (the), Dower House Gatton Park",
    "sg:city":"Reigate",
    "sg:classifiers":[
        {
            "category":"Communications",
            "type":"Services"
        }
    ],
    "sg:phone":"+44 1737 643731",
    "sg:postcode":"RH2 0TA",
    "sg:province":"Surrey",
    "sg:tags":[
        "audio-visual"
    ],
    "wof:name":"Groovy Movies Ltd.",
    "wof:placetype":"venue"
},
  "geometry": {"coordinates":[-0.1839659959,51.2489852905],"type":"Point"}
}