{
  "type": "Feature",
  "properties": {
    "addr:full":"Willow Farm, Chadbury Lane, Lenchwick Evesham Gloucestershire WR11 4TE",
    "addr:postcode":"wr11 4te",
    "addr:street":"Chadbury Lane Lenchwick",
    "iso:country":"GB",
    "sg:address":"Willow Farm, Chadbury Lane, Lenchwick",
    "sg:city":"Evesham",
    "sg:classifiers":[
        {
            "category":"Retail",
            "subcategory":"Animal Services",
            "type":"Services"
        }
    ],
    "sg:phone":"+44 1386 871011",
    "sg:postcode":"WR11 4TE",
    "sg:province":"Gloucestershire",
    "sg:tags":[
        "carrier"
    ],
    "wof:name":"Pershore Transport Ltd.",
    "wof:placetype":"venue"
},
  "geometry": {"coordinates":[-1.9439690113,52.1063919067],"type":"Point"}
}