{
  "type": "Feature",
  "properties": {
    "iso:country":"GB",
    "sg:address":"Church St",
    "sg:city":"Mexborough",
    "sg:classifiers":[
        {
            "category":"Bars & Pubs",
            "type":"Food & Drink"
        }
    ],
    "sg:phone":"+44 1709 572101",
    "sg:postcode":"S64 8DQ",
    "sg:province":"South Yorkshire",
    "sg:tags":[
        "pubs",
        "inn"
    ],
    "wof:name":"Gate Inn The",
    "wof:placetype":"venue"
},
  "geometry": {"coordinates":[-1.324564,53.488525],"type":"Point"}
}