{
  "type": "Feature",
  "properties": {
    "addr:full":"Thorpe Green House, Colchester Road, Thorpe Le Soken Clacton-on-sea Essex CO16 0AB",
    "addr:postcode":"co16 0ab",
    "addr:street":"Colchester Road",
    "iso:country":"GB",
    "sg:address":"Thorpe Green House, Colchester Road, Thorpe Le Soken",
    "sg:city":"Clacton-on-sea",
    "sg:classifiers":[
        {
            "category":"Professional",
            "subcategory":"Management & Consulting",
            "type":"Services"
        }
    ],
    "sg:postcode":"CO16 0AB",
    "sg:province":"Essex",
    "sg:tags":[
        "marketing",
        "consultant"
    ],
    "wof:name":"Pringle Pearey Associates",
    "wof:placetype":"venue"
},
  "geometry": {"coordinates":[1.1323590279,51.9014701843],"type":"Point"}
}