{
  "type": "Feature",
  "properties": {
    "addr:full":"Church Farm, Copp La, Gt Eccleston Preston Lancashire PR3 0ZN",
    "addr:postcode":"pr3 0zn",
    "addr:street":"Copp",
    "iso:country":"GB",
    "sg:address":"Church Farm, Copp La, Gt Eccleston",
    "sg:city":"Preston",
    "sg:classifiers":[
        {
            "category":"Farming",
            "subcategory":"Farm",
            "type":"Manufacturing & Wholesale Goods"
        }
    ],
    "sg:postcode":"PR3 0ZN",
    "sg:province":"Lancashire",
    "sg:tags":[
        "mixed",
        "crop"
    ],
    "wof:name":"Jemson,W & A,",
    "wof:placetype":"venue"
},
  "geometry": {"coordinates":[-2.7420670986,53.8530197144],"type":"Point"}
}