{
  "type": "Feature",
  "properties": {
    "addr:full":"Old Causeway Kinross Clackmannanshire KY13 8EZ",
    "addr:postcode":"ky13 8ez",
    "addr:street":"Old Causeway",
    "iso:country":"GB",
    "sg:address":"Old Causeway",
    "sg:city":"Kinross",
    "sg:classifiers":[
        {
            "category":"Building & Trades",
            "subcategory":"Plumbing",
            "type":"Services"
        }
    ],
    "sg:phone":"+44 1577 863223",
    "sg:postcode":"KY13 8EZ",
    "sg:province":"Clackmannanshire",
    "sg:tags":[
        "heating"
    ],
    "wof:name":"Robert Sandilands & Sons Ltd.",
    "wof:placetype":"venue"
},
  "geometry": {"coordinates":[-3.420484,56.20303],"type":"Point"}
}