{
  "type": "Feature",
  "properties": {
    "iso:country":"GB",
    "sg:address":"Yeomans Court, Ware Road",
    "sg:city":"Hertford",
    "sg:classifiers":[
        {
            "category":"Building & Trades",
            "subcategory":"Landscaping Services",
            "type":"Services"
        },
        {
            "category":"Building & Trades",
            "subcategory":"Construction",
            "type":"Services"
        }
    ],
    "sg:phone":"+44 1992 515300",
    "sg:postcode":"SG13 7HJ",
    "sg:province":"Hertfordshire",
    "sg:tags":[
        "gardening",
        "landscape",
        "contractor"
    ],
    "wof:name":"Highground Accord Ltd.",
    "wof:placetype":"venue"
},
  "geometry": {"coordinates":[-0.0605689995,51.7999649048],"type":"Point"}
}