{
  "type": "Feature",
  "properties": {
    "iso:country":"GB",
    "sg:address":"28 Church Street, Wellington",
    "sg:city":"Telford",
    "sg:classifiers":[
        {
            "category":"Professional",
            "subcategory":"Lawyer & Legal Services",
            "type":"Services"
        }
    ],
    "sg:phone":"+44 1952 272026",
    "sg:postcode":"TF1 1DS",
    "sg:province":"Shropshire",
    "sg:tags":[
        "advice",
        "counselling"
    ],
    "wof:name":"Counselling & Therapy Centre Co. Ltd.",
    "wof:placetype":"venue"
},
  "geometry": {"coordinates":[-2.518305,52.70319],"type":"Point"}
}