{
  "type": "Feature",
  "properties": {
    "addr:full":"13 Henrietta Street, Hockley Birmingham West Midlands B19 3QD",
    "addr:housenumber":"13",
    "addr:postcode":"b19 3qd",
    "addr:street":"Henrietta Street",
    "iso:country":"GB",
    "sg:address":"13 Henrietta Street, Hockley",
    "sg:city":"Birmingham",
    "sg:classifiers":[
        {
            "category":"Wholesale",
            "subcategory":"Apparel",
            "type":"Manufacturing & Wholesale Goods"
        },
        {
            "category":"Wholesale",
            "subcategory":"Wine & Distilled Alcoholic Beverages",
            "type":"Manufacturing & Wholesale Goods"
        }
    ],
    "sg:phone":"+44 121 236 8660",
    "sg:postcode":"B19 3QD",
    "sg:province":"West Midlands",
    "sg:tags":[
        "w'sale",
        "lady",
        "fashionwear",
        "ladieswear"
    ],
    "wof:name":"Sonia Fashions",
    "wof:placetype":"venue"
},
  "geometry": {"coordinates":[-1.9007589817,52.4879417419],"type":"Point"}
}