{
  "type": "Feature",
  "properties": {
    "iso:country":"GB",
    "sg:address":"234 East Rd, Tylorstown",
    "sg:city":"Ferndale",
    "sg:classifiers":[
        {
            "category":"Food & Beverages",
            "subcategory":"Meat & Fish",
            "type":"Retail Goods"
        }
    ],
    "sg:postcode":"CF43 3DA",
    "sg:province":"Rhondda, Cynon, Taff",
    "sg:tags":[
        "butcher"
    ],
    "wof:name":"Roberts,J E,& Sons",
    "wof:placetype":"venue"
},
  "geometry": {"coordinates":[-3.4319250584,51.6474876404],"type":"Point"}
}