{
  "type": "Feature",
  "properties": {
    "addr:full":"37 Fore Street Ilfracombe Devon EX34 9DJ",
    "addr:housenumber":"37",
    "addr:postcode":"ex34 9dj",
    "addr:street":"Fore Street",
    "iso:country":"GB",
    "sg:address":"37 Fore Street",
    "sg:city":"Ilfracombe",
    "sg:classifiers":[
        {
            "category":"Professional",
            "subcategory":"Printing & Photocopies",
            "type":"Services"
        }
    ],
    "sg:phone":"+44 1271 866655",
    "sg:postcode":"EX34 9DJ",
    "sg:province":"Devon",
    "sg:tags":[
        "embroiderer"
    ],
    "wof:name":"Excel Embroidery",
    "wof:placetype":"venue"
},
  "geometry": {"coordinates":[-4.1199598312,51.2091751099],"type":"Point"}
}