{
  "type": "Feature",
  "properties": {
    "addr:full":"Kingsley Road Bideford Devon EX39 2QQ",
    "addr:postcode":"ex39 2qq",
    "addr:street":"Kingsley Road",
    "iso:country":"GB",
    "sg:address":"Kingsley Road",
    "sg:city":"Bideford",
    "sg:classifiers":[
        {
            "category":"Landmark",
            "subcategory":"Tourist Information",
            "type":"Public Place"
        }
    ],
    "sg:phone":"+44 1237 477676",
    "sg:postcode":"EX39 2QQ",
    "sg:province":"Devon",
    "wof:name":"Tourist Information Centre",
    "wof:placetype":"venue"
},
  "geometry": {"coordinates":[-4.209719,51.024067],"type":"Point"}
}