{
  "type": "Feature",
  "properties": {
    "iso:country":"GB",
    "sg:address":"Afrex House, Beresford Avenue",
    "sg:city":"Wembley",
    "sg:classifiers":[
        {
            "category":"Professional",
            "subcategory":"Business Services",
            "type":"Services"
        }
    ],
    "sg:phone":"+44 20 8903 9877",
    "sg:postcode":"HA0 1NX",
    "sg:province":"Greater London",
    "sg:tags":[
        "distribution"
    ],
    "wof:name":"Africa Import Export Co. Ltd.",
    "wof:placetype":"venue"
},
  "geometry": {"coordinates":[-0.278964,51.54158],"type":"Point"}
}