{
  "type": "Feature",
  "properties": {
    "addr:full":"William Street Redditch Warwickshire B97 4AJ",
    "addr:postcode":"b97 4aj",
    "addr:street":"William Street",
    "iso:country":"GB",
    "sg:address":"William Street",
    "sg:city":"Redditch",
    "sg:classifiers":[
        {
            "category":"Health Services",
            "subcategory":"Doctor",
            "type":"Services"
        }
    ],
    "sg:phone":"+44 1527 62285",
    "sg:postcode":"B97 4AJ",
    "sg:province":"Warwickshire",
    "sg:tags":[
        "practitioners"
    ],
    "wof:name":"Bromsgrove & Redditch Health Authority",
    "wof:placetype":"venue"
},
  "geometry": {"coordinates":[-1.9426039457,52.3076324463],"type":"Point"}
}