{
  "type": "Feature",
  "properties": {
    "addr:full":"First Floor, Brassey House Walton-on-thames Surrey KT12 1QD",
    "addr:postcode":"kt12 1qd",
    "addr:street":"Walton-On-Thames",
    "iso:country":"GB",
    "sg:address":"First Floor, Brassey House",
    "sg:city":"Walton-on-thames",
    "sg:classifiers":[
        {
            "category":"Professional",
            "subcategory":"Engineering",
            "type":"Services"
        }
    ],
    "sg:postcode":"KT12 1QD",
    "sg:province":"Surrey",
    "sg:tags":[
        "engineer"
    ],
    "wof:name":"Drakewoods Ltd.",
    "wof:placetype":"venue"
},
  "geometry": {"coordinates":[-0.4207040071,51.3843460083],"type":"Point"}
}