{
  "type": "Feature",
  "properties": {
    "addr:full":"Units 6 - 8 Shails Lane Industrial E, St, River Way Trowbridge Wiltshire BA14 8NS",
    "addr:housenumber":"units 6 8",
    "addr:postcode":"ba14 8ns",
    "addr:street":"Shails Lane Industrial E St River Way",
    "iso:country":"GB",
    "sg:address":"Units 6 - 8 Shails Lane Industrial E, St, River Way",
    "sg:city":"Trowbridge",
    "sg:classifiers":[
        {
            "category":"Wholesale",
            "subcategory":"Vending Machines",
            "type":"Manufacturing & Wholesale Goods"
        }
    ],
    "sg:phone":"+44 1225 769244",
    "sg:postcode":"BA14 8NS",
    "sg:province":"Wiltshire",
    "sg:tags":[
        "sale"
    ],
    "wof:name":"Hilton Vending Services & Equipment Ltd.",
    "wof:placetype":"venue"
},
  "geometry": {"coordinates":[-2.2121,51.322239],"type":"Point"}
}