{
  "type": "Feature",
  "properties": {
    "addr:full":"Edenhurst Court, Dinas Lane, Huyton Liverpool Merseyside L36 2NL",
    "addr:postcode":"l36 2nl",
    "addr:street":"Edenhurst Court Dinas Lane",
    "iso:country":"GB",
    "sg:address":"Edenhurst Court, Dinas Lane, Huyton",
    "sg:city":"Liverpool",
    "sg:classifiers":[
        {
            "category":"Social Services",
            "subcategory":"Retirement Home",
            "type":"Services"
        }
    ],
    "sg:phone":"+44 151 480 4020",
    "sg:postcode":"L36 2NL",
    "sg:province":"Merseyside",
    "sg:tags":[
        "residential",
        "care"
    ],
    "wof:name":"Edenhurst Court",
    "wof:placetype":"venue"
},
  "geometry": {"coordinates":[-2.865999,53.418846],"type":"Point"}
}