{
  "type": "Feature",
  "properties": {
    "addr:full":"Bridge House, Underhill, Lympstone Exmouth Devon EX8 5HH",
    "addr:postcode":"ex8 5hh",
    "iso:country":"GB",
    "sg:address":"Bridge House, Underhill, Lympstone",
    "sg:city":"Exmouth",
    "sg:classifiers":[
        {
            "category":"Education",
            "subcategory":"School",
            "type":"Public Place"
        }
    ],
    "sg:phone":"+44 1395 227333",
    "sg:postcode":"EX8 5HH",
    "sg:province":"Devon",
    "sg:tags":[
        "local",
        "authority"
    ],
    "wof:name":"The Lympstone Language School Ltd.",
    "wof:placetype":"venue"
},
  "geometry": {"coordinates":[-3.4176390171,50.6496391296],"type":"Point"}
}