{
  "type": "Feature",
  "properties": {
    "iso:country":"GB",
    "sg:address":"St Peters Street",
    "sg:city":"Blackburn",
    "sg:classifiers":[
        {
            "category":"Social Services",
            "subcategory":"Retirement Home",
            "type":"Services"
        }
    ],
    "sg:phone":"+44 1254 680985",
    "sg:postcode":"BB2 2LZ",
    "sg:province":"Lancashire",
    "sg:tags":[
        "residential",
        "care"
    ],
    "wof:name":"Byrom House Community Care Ltd.",
    "wof:placetype":"venue"
},
  "geometry": {"coordinates":[-2.48515,53.745846],"type":"Point"}
}