{
  "type": "Feature",
  "properties": {
    "iso:country":"GB",
    "sg:address":"P S A Compound, R A F Lossiemouth",
    "sg:city":"Lossiemouth",
    "sg:classifiers":[
        {
            "category":"Professional",
            "subcategory":"Engineering",
            "type":"Services"
        }
    ],
    "sg:phone":"+44 1343 814807",
    "sg:postcode":"IV31 6SD",
    "sg:province":"Moray",
    "sg:tags":[
        "contractor",
        "electrical",
        "engineer"
    ],
    "wof:name":"N G Bailey",
    "wof:placetype":"venue"
},
  "geometry": {"coordinates":[-3.289304018,57.716709137],"type":"Point"}
}