{
  "type": "Feature",
  "properties": {
    "addr:full":"418 High Road, Tottenham London Greater London N17 9JB",
    "addr:housenumber":"418",
    "addr:postcode":"n17 9jb",
    "addr:street":"High Road",
    "iso:country":"GB",
    "sg:address":"418 High Road, Tottenham",
    "sg:city":"London",
    "sg:classifiers":[
        {
            "category":"Shopping",
            "subcategory":"Computers & Home Electronics",
            "type":"Retail Goods"
        }
    ],
    "sg:phone":"+44 20 8885 3619",
    "sg:postcode":"N17 9JB",
    "sg:province":"Greater London",
    "sg:tags":[
        "hi-fi",
        "centre"
    ],
    "wof:name":"Knightronics",
    "wof:placetype":"venue"
},
  "geometry": {"coordinates":[-0.0696349964,51.5918693542],"type":"Point"}
}