{
  "type": "Feature",
  "properties": {
    "addr:full":"Cairnhall Cottage, Sykeside Rd Airdrie North Lanarkshire ML6 9RQ",
    "addr:postcode":"ml6 9rq",
    "addr:street":"Sykeside Rd",
    "iso:country":"GB",
    "sg:address":"Cairnhall Cottage, Sykeside Rd",
    "sg:city":"Airdrie",
    "sg:classifiers":[
        {
            "category":"Utilities",
            "subcategory":"Refuse",
            "type":"Services"
        }
    ],
    "sg:phone":"+44 1236 768254",
    "sg:postcode":"ML6 9RQ",
    "sg:province":"North Lanarkshire",
    "sg:tags":[
        "skip",
        "hire"
    ],
    "wof:name":"J H Skips",
    "wof:placetype":"venue"
},
  "geometry": {"coordinates":[-3.980729,55.863274],"type":"Point"}
}