{
  "type": "Feature",
  "properties": {
    "iso:country":"GB",
    "sg:address":"Bristol Parkway Railway Station",
    "sg:city":"Bristol",
    "sg:classifiers":[
        {
            "category":"Cafe",
            "type":"Food & Drink"
        }
    ],
    "sg:phone":"+44 117 931 1652",
    "sg:postcode":"BS12 6PU",
    "sg:province":"City of Bristol",
    "sg:tags":[
        "tea",
        "room"
    ],
    "wof:name":"Select Service Partner Ltd",
    "wof:placetype":"venue"
},
  "geometry": {"coordinates":[-2.5323829651,51.5179519653],"type":"Point"}
}