{
  "type": "Feature",
  "properties": {
    "iso:country":"GB",
    "sg:address":"72-74 West Port",
    "sg:city":"Edinburgh",
    "sg:classifiers":[
        {
            "category":"Shopping",
            "subcategory":"Used Merchandise",
            "type":"Retail Goods"
        }
    ],
    "sg:phone":"+44 131 229 5927",
    "sg:postcode":"EH1 2LE",
    "sg:province":"City of Edinburgh",
    "sg:tags":[
        "shop",
        "book",
        "second-hand",
        "secondhand"
    ],
    "wof:name":"Armchair Books",
    "wof:placetype":"venue"
},
  "geometry": {"coordinates":[-3.2006530762,55.9460906982],"type":"Point"}
}