{
  "type": "Feature",
  "properties": {
    "addr:full":"387 Tong Street, Dudley Hill Bradford West Yorkshire BD4 9RU",
    "addr:housenumber":"387",
    "addr:postcode":"bd4 9ru",
    "addr:street":"Tong Street",
    "iso:country":"GB",
    "sg:address":"387 Tong Street, Dudley Hill",
    "sg:city":"Bradford",
    "sg:classifiers":[
        {
            "category":"Military Area",
            "subcategory":"Air Force Base",
            "type":"Public Place"
        }
    ],
    "sg:phone":"+44 1274 653033",
    "sg:postcode":"BD4 9RU",
    "sg:province":"West Yorkshire",
    "sg:tags":[
        "taxi",
        "hire",
        "private"
    ],
    "wof:name":"Tong & Birkenshaw Private Hire",
    "wof:placetype":"venue"
},
  "geometry": {"coordinates":[-1.711149,53.768211],"type":"Point"}
}