{
  "type": "Feature",
  "properties": {
    "addr:full":"63 Stokewood Road Bournemouth Dorset BH3 7NE",
    "addr:housenumber":"63",
    "addr:postcode":"bh3 7ne",
    "addr:street":"Stokewood Road",
    "iso:country":"GB",
    "sg:address":"63 Stokewood Road",
    "sg:city":"Bournemouth",
    "sg:classifiers":[
        {
            "category":"Education",
            "subcategory":"Dance Studio",
            "type":"Public Place"
        }
    ],
    "sg:postcode":"BH3 7NE",
    "sg:province":"Dorset",
    "sg:tags":[
        "school",
        "dancing"
    ],
    "wof:name":"Academy of Ballet & Performing Arts",
    "wof:placetype":"venue"
},
  "geometry": {"coordinates":[-1.8740539551,50.7377090454],"type":"Point"}
}