{
  "type": "Feature",
  "properties": {
    "addr:full":"73 Nordley Common Bridgnorth Shropshire WV16 4TB",
    "addr:housenumber":"73",
    "addr:postcode":"wv16 4tb",
    "addr:street":"Nordley Common",
    "iso:country":"GB",
    "sg:address":"73 Nordley Common",
    "sg:city":"Bridgnorth",
    "sg:classifiers":[
        {
            "category":"Manufacturing",
            "subcategory":"Lumber",
            "type":"Manufacturing & Wholesale Goods"
        }
    ],
    "sg:phone":"+44 1746 764014",
    "sg:postcode":"WV16 4TB",
    "sg:province":"Shropshire",
    "sg:tags":[
        "importer",
        "merchants",
        "agent",
        "timber"
    ],
    "wof:name":"S & R Davies",
    "wof:placetype":"venue"
},
  "geometry": {"coordinates":[-2.4204790592,52.536819458],"type":"Point"}
}