{
  "type": "Feature",
  "properties": {
    "iso:country":"GB",
    "sg:address":"Unit 1 Peckleton Lane Business Park, Peckleton Common, Earl Shilton",
    "sg:city":"Leicester",
    "sg:classifiers":[
        {
            "category":"Shopping",
            "subcategory":"Stationery & Office Supplies",
            "type":"Retail Goods"
        },
        {
            "category":"Professional",
            "subcategory":"Business Services",
            "type":"Services"
        }
    ],
    "sg:phone":"+44 1455 822664",
    "sg:postcode":"LE9 7RN",
    "sg:province":"Leicestershire",
    "sg:tags":[
        "box",
        "carton",
        "manufacturer"
    ],
    "wof:name":"J F D Cartons Ltd.",
    "wof:placetype":"venue"
},
  "geometry": {"coordinates":[-1.281237,52.609066],"type":"Point"}
}