{
  "type": "Feature",
  "properties": {
    "addr:full":"Unit 7, Watton Industrial Estate, Norwich Road Thetford Norfolk IP25 6DR",
    "addr:housenumber":"unit 7",
    "addr:postcode":"ip25 6dr",
    "addr:street":"Watton Industrial Estate Norwich Road",
    "iso:country":"GB",
    "sg:address":"Unit 7, Watton Industrial Estate, Norwich Road",
    "sg:city":"Thetford",
    "sg:classifiers":[
        {
            "category":"Autos & Motor Vehicles",
            "subcategory":"Auto Supplies",
            "type":"Retail Goods"
        }
    ],
    "sg:phone":"+44 1953 881299",
    "sg:postcode":"IP25 6DR",
    "sg:province":"Norfolk",
    "sg:tags":[
        "tyre"
    ],
    "wof:name":"Holburn Tyres",
    "wof:placetype":"venue"
},
  "geometry": {"coordinates":[0.8033400178,52.568523407],"type":"Point"}
}