{
  "type": "Feature",
  "properties": {
    "addr:full":"102 Dog Kennel Hill London Greater London SE22 8BE",
    "addr:housenumber":"102",
    "addr:postcode":"se22 8be",
    "addr:street":"Dog Kennel Hill",
    "iso:country":"GB",
    "sg:address":"102 Dog Kennel Hill",
    "sg:city":"London",
    "sg:classifiers":[
        {
            "category":"Food & Beverages",
            "subcategory":"Meat & Fish",
            "type":"Retail Goods"
        }
    ],
    "sg:phone":"+44 20 7738 3087",
    "sg:postcode":"SE22 8BE",
    "sg:province":"Greater London",
    "sg:tags":[
        "chip"
    ],
    "wof:name":"Wo Hing",
    "wof:placetype":"venue"
},
  "geometry": {"coordinates":[-0.0819609985,51.4626426697],"type":"Point"}
}