{
  "type": "Feature",
  "properties": {
    "iso:country":"GB",
    "sg:address":"35 Denmark Rd",
    "sg:city":"Norwich",
    "sg:classifiers":[
        {
            "category":"Shopping",
            "subcategory":"Catalog Store",
            "type":"Retail Goods"
        }
    ],
    "sg:phone":"+44 1603 415733",
    "sg:postcode":"NR3 4JW",
    "sg:province":"Norfolk",
    "sg:tags":[
        "mail",
        "order"
    ],
    "wof:name":"Adams Mail Order",
    "wof:placetype":"venue"
},
  "geometry": {"coordinates":[1.299667,52.644573],"type":"Point"}
}