{
  "type": "Feature",
  "properties": {
    "addr:full":"Ledian Farm Industrial Estate, Upper Street, Leeds Maidstone Kent ME17 1RZ",
    "addr:housenumber":"estate",
    "addr:postcode":"me17 1rz",
    "addr:street":"Upper Street",
    "iso:country":"GB",
    "sg:address":"Ledian Farm Industrial Estate, Upper Street, Leeds",
    "sg:city":"Maidstone",
    "sg:classifiers":[
        {
            "category":"Professional",
            "subcategory":"Management & Consulting",
            "type":"Services"
        }
    ],
    "sg:phone":"+44 1622 861350",
    "sg:postcode":"ME17 1RZ",
    "sg:province":"Kent",
    "sg:tags":[
        "consultant",
        "investigation",
        "site"
    ],
    "wof:name":"Soiltec Soils & Gas Ltd.",
    "wof:placetype":"venue"
},
  "geometry": {"coordinates":[0.6117730141,51.2487258911],"type":"Point"}
}