{
  "type": "Feature",
  "properties": {
    "addr:full":"12 Old Racecourse Road, Maghull Liverpool Lancashire L31 8AW",
    "addr:housenumber":"12",
    "addr:postcode":"l31 8aw",
    "addr:street":"Old Racecourse Road",
    "iso:country":"GB",
    "sg:address":"12 Old Racecourse Road, Maghull",
    "sg:city":"Liverpool",
    "sg:classifiers":[
        {
            "category":"Building & Trades",
            "subcategory":"Construction",
            "type":"Services"
        }
    ],
    "sg:postcode":"L31 8AW",
    "sg:province":"Lancashire",
    "sg:tags":[
        "decorator",
        "painter"
    ],
    "wof:name":"Ron Seddon Painter & Decorator",
    "wof:placetype":"venue"
},
  "geometry": {"coordinates":[-2.9556849003,53.5065803528],"type":"Point"}
}