{
  "type": "Feature",
  "properties": {
    "addr:full":"481 Meanwood Rd Leeds West Yorkshire LS6 2BH",
    "addr:housenumber":"481",
    "addr:postcode":"ls6 2bh",
    "addr:street":"Meanwood Rd",
    "iso:country":"GB",
    "sg:address":"481 Meanwood Rd",
    "sg:city":"Leeds",
    "sg:classifiers":[
        {
            "category":"Parking",
            "type":"Transportation"
        }
    ],
    "sg:phone":"+44 7850 641079",
    "sg:postcode":"LS6 2BH",
    "sg:province":"West Yorkshire",
    "sg:tags":[
        "car",
        "valet"
    ],
    "wof:name":"Scruffy's Valeting Service",
    "wof:placetype":"venue"
},
  "geometry": {"coordinates":[-1.5596419573,53.821723938],"type":"Point"}
}