{
  "type": "Feature",
  "properties": {
    "addr:full":"55 Eastmead Avenue Greenford Greater London UB6 9RF",
    "addr:housenumber":"55",
    "addr:postcode":"ub6 9rf",
    "addr:street":"Eastmead Avenue",
    "iso:country":"GB",
    "sg:address":"55 Eastmead Avenue",
    "sg:city":"Greenford",
    "sg:classifiers":[
        {
            "category":"Farming",
            "subcategory":"Nursery",
            "type":"Manufacturing & Wholesale Goods"
        }
    ],
    "sg:phone":"+44 20 8813 0147",
    "sg:postcode":"UB6 9RF",
    "sg:province":"Greater London",
    "sg:tags":[
        "creche"
    ],
    "wof:name":"Year of the Child Day Nursery",
    "wof:placetype":"venue"
},
  "geometry": {"coordinates":[-0.3626359999,51.5329093933],"type":"Point"}
}