{
  "type": "Feature",
  "properties": {
    "iso:country":"GB",
    "sg:address":"175 Borough High St",
    "sg:city":"London",
    "sg:classifiers":[
        {
            "category":"Professional",
            "subcategory":"Business Services",
            "type":"Services"
        }
    ],
    "sg:postcode":"SE1 1XP",
    "sg:province":"Greater London",
    "sg:tags":[
        "holding"
    ],
    "wof:name":"Hearn Holdings Ltd",
    "wof:placetype":"venue"
},
  "geometry": {"coordinates":[-0.091962,51.502666],"type":"Point"}
}