{
  "type": "Feature",
  "properties": {
    "iso:country":"GB",
    "sg:address":"29 Parklands",
    "sg:city":"Totnes",
    "sg:classifiers":[
        {
            "category":"Building & Trades",
            "subcategory":"Construction",
            "type":"Services"
        }
    ],
    "sg:phone":"+44 1803 867485",
    "sg:postcode":"TQ9 5HZ",
    "sg:province":"Devon",
    "sg:tags":[
        "decorator",
        "painter"
    ],
    "wof:name":"S Palfrey",
    "wof:placetype":"venue"
},
  "geometry": {"coordinates":[-3.685104,50.434464],"type":"Point"}
}