{
  "type": "Feature",
  "properties": {
    "addr:full":"9 Sandford Street Lichfield Staffordshire WS13 6QA",
    "addr:housenumber":"9",
    "addr:postcode":"ws13 6qa",
    "addr:street":"Sandford Street",
    "iso:country":"GB",
    "sg:address":"9 Sandford Street",
    "sg:city":"Lichfield",
    "sg:classifiers":[
        {
            "category":"Fast Food",
            "type":"Food & Drink"
        }
    ],
    "sg:phone":"+44 1543 256889",
    "sg:postcode":"WS13 6QA",
    "sg:province":"Staffordshire",
    "sg:tags":[
        "away",
        "take"
    ],
    "wof:name":"Lichfield House",
    "wof:placetype":"venue"
},
  "geometry": {"coordinates":[-1.831482,52.681877],"type":"Point"}
}