{
  "type": "Feature",
  "properties": {
    "iso:country":"GB",
    "sg:address":"Bow Street",
    "sg:city":"Aberystwyth",
    "sg:classifiers":[
        {
            "category":"Shopping",
            "subcategory":"Bicycles & Sporting Goods",
            "type":"Retail Goods"
        },
        {
            "category":"Shopping",
            "type":"Retail Goods"
        }
    ],
    "sg:phone":"+44 1970 828680",
    "sg:postcode":"SY24 5BH",
    "sg:province":"Ceredigion",
    "sg:tags":[
        "merchant",
        "sport",
        "sale"
    ],
    "wof:name":"Rogers & Taylor Agricultural Supplies",
    "wof:placetype":"venue"
},
  "geometry": {"coordinates":[-4.03381,52.441269],"type":"Point"}
}