{
  "type": "Feature",
  "properties": {
    "iso:country":"GB",
    "sg:address":"Burton Resource & Development Centre, Grange Street",
    "sg:city":"Burton On Trent",
    "sg:classifiers":[
        {
            "category":"Government",
            "subcategory":"Office",
            "type":"Public Place"
        }
    ],
    "sg:phone":"+44 1283 545771",
    "sg:postcode":"DE14 2ER",
    "sg:province":"Derbyshire",
    "sg:tags":[
        "education",
        "agency",
        "authority"
    ],
    "wof:name":"Special Education Needs Support Service",
    "wof:placetype":"venue"
},
  "geometry": {"coordinates":[-1.64812,52.809799],"type":"Point"}
}