{
  "type": "Feature",
  "properties": {
    "addr:full":"86 Hardys Rd Cleethorpes Lincolnshire DN35 0DW",
    "addr:housenumber":"86",
    "addr:postcode":"dn35 0dw",
    "addr:street":"Hardys Rd",
    "iso:country":"GB",
    "sg:address":"86 Hardys Rd",
    "sg:city":"Cleethorpes",
    "sg:classifiers":[
        {
            "category":"Retail",
            "subcategory":"Veterinary Services",
            "type":"Services"
        }
    ],
    "sg:phone":"+44 1472 694721",
    "sg:postcode":"DN35 0DW",
    "sg:province":"Lincolnshire",
    "sg:tags":[
        "surgeon",
        "activity"
    ],
    "wof:name":"Eastfield Veterinary Clinic",
    "wof:placetype":"venue"
},
  "geometry": {"coordinates":[-0.023763,53.547909],"type":"Point"}
}