{
  "type": "Feature",
  "properties": {
    "addr:full":"Canada Lane Brigg Road, Caistor Market Rasen Lincolnshire LN7 6RZ",
    "addr:postcode":"ln7 6rz",
    "addr:street":"Canada Lane Brigg Road Caistor Market Rasen",
    "iso:country":"GB",
    "sg:address":"Canada Lane Brigg Road, Caistor",
    "sg:city":"Market Rasen",
    "sg:classifiers":[
        {
            "category":"Food & Beverages",
            "subcategory":"Candy",
            "type":"Retail Goods"
        }
    ],
    "sg:postcode":"LN7 6RZ",
    "sg:province":"Lincolnshire",
    "sg:tags":[
        "confectionery"
    ],
    "wof:name":"Wolds Confectionery Co  Ltd",
    "wof:placetype":"venue"
},
  "geometry": {"coordinates":[-0.305434,53.50198],"type":"Point"}
}