{
  "type": "Feature",
  "properties": {
    "addr:full":"Archway House Bedale North Yorkshire DL8 1AF",
    "addr:postcode":"dl8 1af",
    "iso:country":"GB",
    "sg:address":"Archway House",
    "sg:city":"Bedale",
    "sg:classifiers":[
        {
            "category":"Government",
            "subcategory":"Office",
            "type":"Public Place"
        }
    ],
    "sg:phone":"+44 1677 422517",
    "sg:postcode":"DL8 1AF",
    "sg:province":"North Yorkshire",
    "sg:tags":[
        "chamber",
        "commerce"
    ],
    "wof:name":"National Farmers Union",
    "wof:placetype":"venue"
},
  "geometry": {"coordinates":[-1.592346,54.288811],"type":"Point"}
}