{
  "type": "Feature",
  "properties": {
    "addr:full":"15 Kennington Road, Nuffield Industrial Estate Poole Dorset BH17 0GF",
    "addr:housenumber":"15",
    "addr:postcode":"bh17 0gf",
    "addr:street":"Kennington Road;Industrial",
    "iso:country":"GB",
    "sg:address":"15 Kennington Road, Nuffield Industrial Estate",
    "sg:city":"Poole",
    "sg:classifiers":[
        {
            "category":"Professional",
            "subcategory":"Engineering",
            "type":"Services"
        }
    ],
    "sg:postcode":"BH17 0GF",
    "sg:province":"Dorset",
    "sg:tags":[
        "precision",
        "engineer"
    ],
    "wof:name":"Dave Wynn Engineering",
    "wof:placetype":"venue"
},
  "geometry": {"coordinates":[-1.9775500298,50.7424507141],"type":"Point"}
}