{
  "type": "Feature",
  "properties": {
    "iso:country":"GB",
    "sg:address":"Oxmuir, Greenlaw",
    "sg:city":"Duns",
    "sg:classifiers":[
        {
            "category":"Farming",
            "subcategory":"Dairy Farm",
            "type":"Manufacturing & Wholesale Goods"
        }
    ],
    "sg:postcode":"TD10 6UW",
    "sg:province":"Scottish Borders",
    "wof:name":"R G Laing",
    "wof:placetype":"venue"
},
  "geometry": {"coordinates":[-2.462528944,55.7065162659],"type":"Point"}
}