{
  "type": "Feature",
  "properties": {
    "addr:full":"119 High Street West Wickham Kent BR4 0LT",
    "addr:housenumber":"119",
    "addr:postcode":"br4 0lt",
    "addr:street":"High Street",
    "iso:country":"GB",
    "sg:address":"119 High Street",
    "sg:city":"West Wickham",
    "sg:classifiers":[
        {
            "category":"Personal",
            "subcategory":"Nail Salon",
            "type":"Services"
        }
    ],
    "sg:phone":"+44 20 8776 0881",
    "sg:postcode":"BR4 0LT",
    "sg:province":"Kent",
    "sg:tags":[
        "solarium",
        "tanning"
    ],
    "wof:name":"Sun Island Tanning Salon",
    "wof:placetype":"venue"
},
  "geometry": {"coordinates":[-0.0201389994,51.3769073486],"type":"Point"}
}