{
  "type": "Feature",
  "properties": {
    "iso:country":"GB",
    "sg:address":"22a Oxford St",
    "sg:city":"Harrogate",
    "sg:classifiers":[
        {
            "category":"Building & Trades",
            "subcategory":"Construction",
            "type":"Services"
        }
    ],
    "sg:postcode":"HG1 1PU",
    "sg:province":"North Yorkshire",
    "sg:tags":[
        "roofing"
    ],
    "wof:name":"Howarth,D,",
    "wof:placetype":"venue"
},
  "geometry": {"coordinates":[-1.5409,53.994102],"type":"Point"}
}