{
  "type": "Feature",
  "properties": {
    "iso:country":"GB",
    "sg:address":"Unit 2 Lyon Way",
    "sg:city":"St Albans",
    "sg:classifiers":[
        {
            "category":"Food & Beverages",
            "subcategory":"Bakery",
            "type":"Retail Goods"
        }
    ],
    "sg:phone":"+44 1727 818000",
    "sg:postcode":"AL4 0LQ",
    "sg:province":"Hertfordshire",
    "sg:tags":[
        "confectionery"
    ],
    "wof:name":"The Bread Roll Co. Ltd.",
    "wof:placetype":"venue"
},
  "geometry": {"coordinates":[-0.275359,51.752274],"type":"Point"}
}