{
  "type": "Feature",
  "properties": {
    "addr:full":"Unit 2 South Parks Indstl Est Peebles Scottish Borders EH45 9ED",
    "addr:housenumber":"unit 2",
    "addr:postcode":"eh45 9ed",
    "addr:street":"South Parks Indstl Est",
    "iso:country":"GB",
    "sg:address":"Unit 2 South Parks Indstl Est",
    "sg:city":"Peebles",
    "sg:classifiers":[
        {
            "category":"Building & Trades",
            "subcategory":"Landscaping Services",
            "type":"Services"
        }
    ],
    "sg:postcode":"EH45 9ED",
    "sg:province":"Scottish Borders",
    "sg:tags":[
        "horticultural"
    ],
    "wof:name":"Crane,Douglas,",
    "wof:placetype":"venue"
},
  "geometry": {"coordinates":[-3.199942,55.649883],"type":"Point"}
}