{
  "type": "Feature",
  "properties": {
    "iso:country":"GB",
    "sg:address":"7 Charlotte Street",
    "sg:city":"Brighton",
    "sg:classifiers":[
        {
            "category":"Travel",
            "subcategory":"Hotels & Motels",
            "type":"Entertainment"
        }
    ],
    "sg:postcode":"BN2 1AG",
    "sg:province":"East Sussex",
    "wof:name":"Bighton Pavilions",
    "wof:placetype":"venue"
},
  "geometry": {"coordinates":[-0.1278,50.819096],"type":"Point"}
}