{
  "type": "Feature",
  "properties": {
    "addr:full":"Unit 6 Merton Industrial Park, Lee Road London Greater London SW19 3XX",
    "addr:housenumber":"unit 6",
    "addr:postcode":"sw19 3xx",
    "addr:street":"Merton Industrial Park Lee Road",
    "iso:country":"GB",
    "sg:address":"Unit 6 Merton Industrial Park, Lee Road",
    "sg:city":"London",
    "sg:classifiers":[
        {
            "category":"Professional",
            "subcategory":"Art Services",
            "type":"Services"
        }
    ],
    "sg:postcode":"SW19 3XX",
    "sg:province":"Greater London",
    "sg:tags":[
        "graphic",
        "designer"
    ],
    "wof:name":"Barefoot",
    "wof:placetype":"venue"
},
  "geometry": {"coordinates":[-0.19033,51.412498],"type":"Point"}
}