{
  "type": "Feature",
  "properties": {
    "iso:country":"GB",
    "sg:address":"Mount Avenue, Hutton",
    "sg:city":"Brentwood",
    "sg:classifiers":[
        {
            "category":"Retail",
            "subcategory":"Event Space",
            "type":"Services"
        }
    ],
    "sg:phone":"+44 1277 211549",
    "sg:postcode":"CM13 2NS",
    "sg:province":"Essex",
    "sg:tags":[
        "function",
        "hire",
        "banqueting",
        "room"
    ],
    "wof:name":"Mount Avenue Banqueting Suite",
    "wof:placetype":"venue"
},
  "geometry": {"coordinates":[0.333945,51.629536],"type":"Point"}
}