{
  "type": "Feature",
  "properties": {
    "addr:full":"7 Meadow Cotts, Little Kingshill Great Missenden Buckinghamshire HP16 0DX",
    "addr:housenumber":"7;cotts",
    "addr:postcode":"hp16 0dx",
    "addr:street":"Meadow;Little",
    "iso:country":"GB",
    "sg:address":"7 Meadow Cotts, Little Kingshill",
    "sg:city":"Great Missenden",
    "sg:classifiers":[
        {
            "category":"Building & Trades",
            "subcategory":"Construction",
            "type":"Services"
        }
    ],
    "sg:postcode":"HP16 0DX",
    "sg:province":"Buckinghamshire",
    "sg:tags":[
        "builder"
    ],
    "wof:name":"Meadow Construction",
    "wof:placetype":"venue"
},
  "geometry": {"coordinates":[-0.709043026,51.7040672302],"type":"Point"}
}