{
  "type": "Feature",
  "properties": {
    "addr:full":"62 Westfield Street St Helens Merseyside WA10 1QJ",
    "addr:housenumber":"62",
    "addr:postcode":"wa10 1qj",
    "addr:street":"Westfield Street",
    "iso:country":"GB",
    "sg:address":"62 Westfield Street",
    "sg:city":"St Helens",
    "sg:classifiers":[
        {
            "category":"Fast Food",
            "type":"Food & Drink"
        }
    ],
    "sg:phone":"+44 1744 22661",
    "sg:postcode":"WA10 1QJ",
    "sg:province":"Merseyside",
    "sg:tags":[
        "away",
        "take"
    ],
    "wof:name":"Tandoori Ghar",
    "wof:placetype":"venue"
},
  "geometry": {"coordinates":[-2.7416059971,53.4533843994],"type":"Point"}
}