{
  "type": "Feature",
  "properties": {
    "iso:country":"GB",
    "sg:address":"105 Hampton Road",
    "sg:city":"Southport",
    "sg:classifiers":[
        {
            "category":"Building & Trades",
            "subcategory":"Landscaping Services",
            "type":"Services"
        }
    ],
    "sg:phone":"+44 1704 541733",
    "sg:postcode":"PR8 5DY",
    "sg:province":"Lancashire",
    "sg:tags":[
        "gardening",
        "landscape",
        "contractor"
    ],
    "wof:name":"Robert Wright",
    "wof:placetype":"venue"
},
  "geometry": {"coordinates":[-3.000053,53.637348],"type":"Point"}
}