{
  "type": "Feature",
  "properties": {
    "addr:full":"87 Moss Lane West, Moss Side Manchester Cheshire M15 5PE",
    "addr:housenumber":"87",
    "addr:postcode":"m15 5pe",
    "addr:street":"Moss Lane West",
    "iso:country":"GB",
    "sg:address":"87 Moss Lane West, Moss Side",
    "sg:city":"Manchester",
    "sg:classifiers":[
        {
            "category":"Government",
            "subcategory":"Police Station",
            "type":"Public Place"
        }
    ],
    "sg:phone":"+44 161 226 3515",
    "sg:postcode":"M15 5PE",
    "sg:province":"Cheshire",
    "sg:tags":[
        "support"
    ],
    "wof:name":"The Probation Service",
    "wof:placetype":"venue"
},
  "geometry": {"coordinates":[-2.253769,53.459949],"type":"Point"}
}