{
  "type": "Feature",
  "properties": {
    "iso:country":"GB",
    "sg:address":"Herdwick Croft, Bassenthwaite",
    "sg:city":"Keswick",
    "sg:classifiers":[
        {
            "category":"Retail",
            "subcategory":"Auto Repair",
            "type":"Services"
        }
    ],
    "sg:phone":"+44 17687 76605",
    "sg:postcode":"CA12 4RD",
    "sg:province":"Cumbria",
    "sg:tags":[
        "modification",
        "garage",
        "related"
    ],
    "wof:name":"Derwent Motor Bodies",
    "wof:placetype":"venue"
},
  "geometry": {"coordinates":[-3.195458,54.679028],"type":"Point"}
}