{
  "type": "Feature",
  "properties": {
    "addr:full":"Bedford St London Greater London WC2E 9ED",
    "addr:postcode":"wc2e 9ed",
    "addr:street":"Bedford St",
    "iso:country":"GB",
    "sg:address":"Bedford St",
    "sg:city":"London",
    "sg:classifiers":[
        {
            "category":"Professional",
            "subcategory":"Accounting & Tax Preparation",
            "type":"Services"
        }
    ],
    "sg:postcode":"WC2E 9ED",
    "sg:province":"Greater London",
    "sg:tags":[
        "consultant"
    ],
    "wof:name":"Harper,Jack,& Co,",
    "wof:placetype":"venue"
},
  "geometry": {"coordinates":[-0.124998,51.511227],"type":"Point"}
}