{
  "type": "Feature",
  "properties": {
    "iso:country":"GB",
    "sg:address":"Unit 15 Hayward Industrial Park, Thameside Drive",
    "sg:city":"Birmingham",
    "sg:classifiers":[
        {
            "category":"Shopping",
            "subcategory":"Computers & Home Electronics",
            "type":"Retail Goods"
        }
    ],
    "sg:phone":"+44 121 749 2240",
    "sg:postcode":"B35 7BT",
    "sg:province":"West Midlands",
    "sg:tags":[
        "equipment",
        "audio-visual"
    ],
    "wof:name":"Path Group Plc",
    "wof:placetype":"venue"
},
  "geometry": {"coordinates":[-1.8044179678,52.5120277405],"type":"Point"}
}