{
  "type": "Feature",
  "properties": {
    "addr:full":"85 High Street, Eye Peterborough Cambridgeshire PE6 7UX",
    "addr:housenumber":"85",
    "addr:postcode":"pe6 7ux",
    "addr:street":"High Street",
    "iso:country":"GB",
    "sg:address":"85 High Street, Eye",
    "sg:city":"Peterborough",
    "sg:classifiers":[
        {
            "category":"Professional",
            "subcategory":"Engineering",
            "type":"Services"
        }
    ],
    "sg:phone":"+44 1733 222770",
    "sg:postcode":"PE6 7UX",
    "sg:province":"Cambridgeshire",
    "sg:tags":[
        "contractor",
        "electrical",
        "engineer"
    ],
    "wof:name":"S D Electrics",
    "wof:placetype":"venue"
},
  "geometry": {"coordinates":[-0.1920929998,52.6084861755],"type":"Point"}
}