{
  "type": "Feature",
  "properties": {
    "addr:full":"178 Sladepool Farm Road Birmingham West Midlands B14 5EE",
    "addr:housenumber":"178",
    "addr:postcode":"b14 5ee",
    "addr:street":"Sladepool Farm Road",
    "iso:country":"GB",
    "sg:address":"178 Sladepool Farm Road",
    "sg:city":"Birmingham",
    "sg:classifiers":[
        {
            "category":"Retail",
            "subcategory":"Auto Repair",
            "type":"Services"
        }
    ],
    "sg:postcode":"B14 5EE",
    "sg:province":"West Midlands",
    "sg:tags":[
        "modification",
        "garage"
    ],
    "wof:name":"Neil Dearn",
    "wof:placetype":"venue"
},
  "geometry": {"coordinates":[-1.880316,52.407295],"type":"Point"}
}