{
  "type": "Feature",
  "properties": {
    "addr:full":"12 Whiteacre Wigan Lancashire WN6 0SH",
    "addr:housenumber":"12",
    "addr:postcode":"wn6 0sh",
    "addr:street":"Whiteacre Wigan",
    "iso:country":"GB",
    "sg:address":"12 Whiteacre",
    "sg:city":"Wigan",
    "sg:classifiers":[
        {
            "category":"Building & Trades",
            "subcategory":"Construction",
            "type":"Services"
        }
    ],
    "sg:phone":"+44 1257 472748",
    "sg:postcode":"WN6 0SH",
    "sg:province":"Lancashire",
    "sg:tags":[
        "flooring"
    ],
    "wof:name":"Floor Coverings International",
    "wof:placetype":"venue"
},
  "geometry": {"coordinates":[-2.691375,53.591496],"type":"Point"}
}