{
  "type": "Feature",
  "properties": {
    "addr:full":"44-48 Field Lane, Kessingland Lowestoft Suffolk NR33 7QA",
    "addr:housenumber":"44-48",
    "addr:postcode":"nr33 7qa",
    "addr:street":"Field Lane",
    "iso:country":"GB",
    "sg:address":"44-48 Field Lane, Kessingland",
    "sg:city":"Lowestoft",
    "sg:classifiers":[
        {
            "category":"Food & Beverages",
            "subcategory":"Groceries & Convenience Stores",
            "type":"Retail Goods"
        }
    ],
    "sg:phone":"+44 1502 740548",
    "sg:postcode":"NR33 7QA",
    "sg:province":"Suffolk",
    "wof:name":"Budgems Local",
    "wof:placetype":"venue"
},
  "geometry": {"coordinates":[1.71744,52.420609],"type":"Point"}
}