{
  "type": "Feature",
  "properties": {
    "addr:full":"40 Belgrave Rd Margate Kent CT9 1XG",
    "addr:housenumber":"40",
    "addr:postcode":"ct9 1xg",
    "addr:street":"Belgrave Rd Margate",
    "iso:country":"GB",
    "sg:address":"40 Belgrave Rd",
    "sg:city":"Margate",
    "sg:classifiers":[
        {
            "category":"Personal",
            "subcategory":"Barber",
            "type":"Services"
        }
    ],
    "sg:phone":"+44 1843 292474",
    "sg:postcode":"CT9 1XG",
    "sg:province":"Kent",
    "sg:tags":[
        "men's",
        "hairdresser"
    ],
    "wof:name":"Andrew's",
    "wof:placetype":"venue"
},
  "geometry": {"coordinates":[1.3795160055,51.3855628967],"type":"Point"}
}