{
  "type": "Feature",
  "properties": {
    "addr:full":"21 Pavilion Way East Grinstead East Sussex RH19 4SS",
    "addr:housenumber":"21",
    "addr:postcode":"rh19 4ss",
    "addr:street":"Pavilion Way",
    "iso:country":"GB",
    "sg:address":"21 Pavilion Way",
    "sg:city":"East Grinstead",
    "sg:classifiers":[
        {
            "category":"Retail",
            "subcategory":"Driving School",
            "type":"Services"
        }
    ],
    "sg:postcode":"RH19 4SS",
    "sg:province":"East Sussex",
    "wof:name":"Wells School of Motoring",
    "wof:placetype":"venue"
},
  "geometry": {"coordinates":[-0.0125000002,51.1229667664],"type":"Point"}
}