{
  "type": "Feature",
  "properties": {
    "iso:country":"GB",
    "sg:address":"859 Wimborne Rd",
    "sg:city":"Bournemouth",
    "sg:classifiers":[
        {
            "category":"Shopping",
            "subcategory":"Used Merchandise",
            "type":"Retail Goods"
        }
    ],
    "sg:postcode":"BH9 2BG",
    "sg:province":"Dorset",
    "sg:tags":[
        "furniture"
    ],
    "wof:name":"House,Chris,",
    "wof:placetype":"venue"
},
  "geometry": {"coordinates":[-1.8759130239,50.7528076172],"type":"Point"}
}