{
  "type": "Feature",
  "properties": {
    "iso:country":"GB",
    "sg:address":"Implement Road, West Barns",
    "sg:city":"Dunbar",
    "sg:classifiers":[
        {
            "category":"Autos & Motor Vehicles",
            "subcategory":"Auto Supplies",
            "type":"Retail Goods"
        }
    ],
    "sg:postcode":"EH42 1UN",
    "sg:province":"East Lothian",
    "sg:tags":[
        "tyre"
    ],
    "wof:name":"Tyreforce",
    "wof:placetype":"venue"
},
  "geometry": {"coordinates":[-2.555789,55.994705],"type":"Point"}
}