{
  "type": "Feature",
  "properties": {
    "iso:country":"GB",
    "sg:address":"Bramble Lane Garage, Bramble Lane, Wye",
    "sg:city":"Ashford",
    "sg:classifiers":[
        {
            "category":"Autos & Motor Vehicles",
            "subcategory":"Automobile Sales",
            "type":"Retail Goods"
        }
    ],
    "sg:phone":"+44 1233 812812",
    "sg:postcode":"TN25 5EH",
    "sg:province":"Kent",
    "sg:tags":[
        "car"
    ],
    "wof:name":"Wye Car Sales",
    "wof:placetype":"venue"
},
  "geometry": {"coordinates":[0.928025,51.186546],"type":"Point"}
}