{
  "type": "Feature",
  "properties": {
    "addr:full":"Unit 1, Flowerhill Industrial Estate, Flowerhill Street Airdrie North Lanarkshire ML6 6AP",
    "addr:housenumber":"unit 1",
    "addr:postcode":"ml6 6ap",
    "addr:street":"Flowerhill Industrial Estate Flowerhill Street",
    "iso:country":"GB",
    "sg:address":"Unit 1, Flowerhill Industrial Estate, Flowerhill Street",
    "sg:city":"Airdrie",
    "sg:classifiers":[
        {
            "category":"Building & Trades",
            "subcategory":"Construction",
            "type":"Services"
        }
    ],
    "sg:phone":"+44 1236 764867",
    "sg:postcode":"ML6 6AP",
    "sg:province":"North Lanarkshire",
    "sg:tags":[
        "surfacing",
        "road"
    ],
    "wof:name":"G & B Roadmarking",
    "wof:placetype":"venue"
},
  "geometry": {"coordinates":[-3.9807839394,55.8658638],"type":"Point"}
}