{
  "type": "Feature",
  "properties": {
    "addr:full":"265 Chells Way Stevenage Hertfordshire SG2 0HN",
    "addr:housenumber":"265",
    "addr:postcode":"sg2 0hn",
    "addr:street":"Chells Way",
    "iso:country":"GB",
    "sg:address":"265 Chells Way",
    "sg:city":"Stevenage",
    "sg:classifiers":[
        {
            "category":"Health Services",
            "subcategory":"Doctor",
            "type":"Services"
        }
    ],
    "sg:phone":"+44 1438 313001",
    "sg:postcode":"SG2 0HN",
    "sg:province":"Hertfordshire",
    "sg:tags":[
        "practitioners"
    ],
    "wof:name":"Salter, D H R",
    "wof:placetype":"venue"
},
  "geometry": {"coordinates":[-0.1778170019,51.9121208191],"type":"Point"}
}