{
  "type": "Feature",
  "properties": {
    "addr:full":"26a Stour Street Canterbury Kent CT1 2NZ",
    "addr:housenumber":"26a",
    "addr:postcode":"ct1 2nz",
    "addr:street":"Stour Street",
    "iso:country":"GB",
    "sg:address":"26a Stour Street",
    "sg:city":"Canterbury",
    "sg:classifiers":[
        {
            "category":"Organizations",
            "subcategory":"Non-profit Organization",
            "type":"Services"
        }
    ],
    "sg:phone":"+44 1227 760078",
    "sg:postcode":"CT1 2NZ",
    "sg:province":"Kent",
    "sg:tags":[
        "organisation",
        "voluntary",
        "charity"
    ],
    "wof:name":"Canterbury Cyrenians",
    "wof:placetype":"venue"
},
  "geometry": {"coordinates":[1.07718,51.27829],"type":"Point"}
}