{
  "type": "Feature",
  "properties": {
    "addr:full":"Unit 6 Park Mews Small Business Centre, Croxted Road London Greater London SE24 9DB",
    "addr:housenumber":"unit 6",
    "addr:postcode":"se24 9db",
    "addr:street":"Park Mews;Croxted Road",
    "iso:country":"GB",
    "sg:address":"Unit 6 Park Mews Small Business Centre, Croxted Road",
    "sg:city":"London",
    "sg:classifiers":[
        {
            "category":"Shopping",
            "subcategory":"Gifts & Souvenirs",
            "type":"Retail Goods"
        }
    ],
    "sg:postcode":"SE24 9DB",
    "sg:province":"Greater London",
    "sg:tags":[
        "giftware"
    ],
    "wof:name":"Richard Pell Creative Metalwork",
    "wof:placetype":"venue"
},
  "geometry": {"coordinates":[-0.09959,51.449459],"type":"Point"}
}