{
  "type": "Feature",
  "properties": {
    "addr:full":"Grosvenor Road Seaford East Sussex BN25 2BQ",
    "addr:postcode":"bn25 2bq",
    "addr:street":"Grosvenor Road",
    "iso:country":"GB",
    "sg:address":"Grosvenor Road",
    "sg:city":"Seaford",
    "sg:classifiers":[
        {
            "category":"Social Services",
            "subcategory":"Adult Care",
            "type":"Services"
        }
    ],
    "sg:phone":"+44 1323 892856",
    "sg:postcode":"BN25 2BQ",
    "sg:province":"East Sussex",
    "sg:tags":[
        "housing",
        "sheltered"
    ],
    "wof:name":"Hometye House",
    "wof:placetype":"venue"
},
  "geometry": {"coordinates":[0.09921,50.776875],"type":"Point"}
}