{
  "type": "Feature",
  "properties": {
    "addr:full":"Gallards Almshouses, London Road, Southborough Tunbridge Wells Kent TN4 0NB",
    "addr:postcode":"tn4 0nb",
    "addr:street":"London Road",
    "iso:country":"GB",
    "sg:address":"Gallards Almshouses, London Road, Southborough",
    "sg:city":"Tunbridge Wells",
    "sg:classifiers":[
        {
            "category":"Organizations",
            "subcategory":"Non-profit Organization",
            "type":"Services"
        }
    ],
    "sg:phone":"+44 1892 528437",
    "sg:postcode":"TN4 0NB",
    "sg:province":"Kent",
    "sg:tags":[
        "charitable",
        "organisation",
        "voluntary",
        "charity"
    ],
    "wof:name":"Gallards Almhouses",
    "wof:placetype":"venue"
},
  "geometry": {"coordinates":[0.2599489987,51.1558914185],"type":"Point"}
}