{
  "type": "Feature",
  "properties": {
    "addr:full":"57 South St Ilkeston Derbyshire DE7 5QT",
    "addr:housenumber":"57",
    "addr:postcode":"de7 5qt",
    "addr:street":"South St",
    "iso:country":"GB",
    "sg:address":"57 South St",
    "sg:city":"Ilkeston",
    "sg:classifiers":[
        {
            "category":"Shopping",
            "subcategory":"Baby Store",
            "type":"Retail Goods"
        }
    ],
    "sg:phone":"+44 115 930 8161",
    "sg:postcode":"DE7 5QT",
    "sg:province":"Derbyshire",
    "sg:tags":[
        "nursery",
        "accessory"
    ],
    "wof:name":"Stork Talk",
    "wof:placetype":"venue"
},
  "geometry": {"coordinates":[-1.3087970018,52.9690055847],"type":"Point"}
}