{
  "type": "Feature",
  "properties": {
    "iso:country":"GB",
    "sg:address":"5 Madoc Street",
    "sg:city":"Llandudno",
    "sg:classifiers":[
        {
            "category":"Personal",
            "subcategory":"Beauty Salon",
            "type":"Services"
        }
    ],
    "sg:phone":"+44 1492 874767",
    "sg:postcode":"LL30 2TL",
    "sg:province":"Conwy",
    "wof:name":"The Beauty Salon",
    "wof:placetype":"venue"
},
  "geometry": {"coordinates":[-3.8311860561,53.3233757019],"type":"Point"}
}