{
  "type": "Feature",
  "properties": {
    "iso:country":"GB",
    "sg:address":"The Green",
    "sg:city":"Darwen",
    "sg:classifiers":[
        {
            "category":"Personal",
            "type":"Services"
        }
    ],
    "sg:phone":"+44 1254 705040",
    "sg:postcode":"BB3 1PW",
    "sg:province":"Lancashire",
    "sg:tags":[
        "wedding"
    ],
    "wof:name":"Marigold Entertainments Ltd.",
    "wof:placetype":"venue"
},
  "geometry": {"coordinates":[-2.469289,53.695839],"type":"Point"}
}