{
  "type": "Feature",
  "properties": {
    "addr:full":"Lower Road Hockley Essex SS5 5NL",
    "addr:postcode":"ss5 5nl",
    "addr:street":"Lower Road Hockley",
    "iso:country":"GB",
    "sg:address":"Lower Road",
    "sg:city":"Hockley",
    "sg:classifiers":[
        {
            "category":"Home & Garden",
            "subcategory":"Garden Supply",
            "type":"Retail Goods"
        }
    ],
    "sg:phone":"+44 1702 201029",
    "sg:postcode":"SS5 5NL",
    "sg:province":"Essex",
    "sg:tags":[
        "nursery",
        "centre"
    ],
    "wof:name":"Joseph Walker & Chrisitine Leigh",
    "wof:placetype":"venue"
},
  "geometry": {"coordinates":[0.654267,51.619591],"type":"Point"}
}