{
  "type": "Feature",
  "properties": {
    "iso:country":"GB",
    "sg:address":"5 Berkeley Av",
    "sg:city":"Birkenhead",
    "sg:classifiers":[
        {
            "category":"Building & Trades",
            "subcategory":"Plumbing",
            "type":"Services"
        }
    ],
    "sg:phone":"+44 151 608 7294",
    "sg:postcode":"L43 3AJ",
    "sg:province":"Merseyside",
    "sg:tags":[
        "heating"
    ],
    "wof:name":"D J Gregson",
    "wof:placetype":"venue"
},
  "geometry": {"coordinates":[-3.0610029697,53.3699645996],"type":"Point"}
}