{
  "type": "Feature",
  "properties": {
    "addr:full":"637 High Road London Greater London E10 6RF",
    "addr:housenumber":"637",
    "addr:postcode":"e10 6rf",
    "addr:street":"High Road",
    "iso:country":"GB",
    "sg:address":"637 High Road",
    "sg:city":"London",
    "sg:classifiers":[
        {
            "category":"Government",
            "subcategory":"Post Office",
            "type":"Public Place"
        }
    ],
    "sg:phone":"+44 20 8539 7696",
    "sg:postcode":"E10 6RF",
    "sg:province":"Greater London",
    "sg:tags":[
        "messenger",
        "courier"
    ],
    "wof:name":"Midland Couriers Ltd.",
    "wof:placetype":"venue"
},
  "geometry": {"coordinates":[-0.0083170002,51.5697593689],"type":"Point"}
}