{
  "type": "Feature",
  "properties": {
    "iso:country":"GB",
    "sg:address":"3 Valley Mills, Southfield Street",
    "sg:city":"Nelson",
    "sg:classifiers":[
        {
            "category":"Home & Garden",
            "subcategory":"Hardware",
            "type":"Retail Goods"
        },
        {
            "category":"Shopping",
            "subcategory":"Discount & Variety Stores",
            "type":"Retail Goods"
        }
    ],
    "sg:phone":"+44 1282 613013",
    "sg:postcode":"BB9 0LD",
    "sg:province":"Lancashire",
    "sg:tags":[
        "equipment",
        "material",
        "cleaning",
        "supply"
    ],
    "wof:name":"Moornate Chemists Ltd.",
    "wof:placetype":"venue"
},
  "geometry": {"coordinates":[-2.21334,53.835968],"type":"Point"}
}