{
  "type": "Feature",
  "properties": {
    "addr:full":"3 Market Place Barton Upon Humber Lincolnshire DN18 5DA",
    "addr:housenumber":"3",
    "addr:postcode":"dn18 5da",
    "addr:street":"Market Place Barton",
    "iso:country":"GB",
    "sg:address":"3 Market Place",
    "sg:city":"Barton Upon Humber",
    "sg:classifiers":[
        {
            "category":"Real Estate",
            "subcategory":"Developer",
            "type":"Services"
        }
    ],
    "sg:postcode":"DN18 5DA",
    "sg:province":"Lincolnshire",
    "sg:tags":[
        "property"
    ],
    "wof:name":"Saleview Ltd",
    "wof:placetype":"venue"
},
  "geometry": {"coordinates":[-0.4392780066,53.6830177307],"type":"Point"}
}