{
  "type": "Feature",
  "properties": {
    "iso:country":"GB",
    "sg:address":"240 Chatsworth Road",
    "sg:city":"Chesterfield",
    "sg:classifiers":[
        {
            "category":"Insurance",
            "subcategory":"Insurance Agent",
            "type":"Services"
        }
    ],
    "sg:phone":"+44 1246 275244",
    "sg:postcode":"S40 3BQ",
    "sg:province":"Derbyshire",
    "wof:name":"National Farmers Union",
    "wof:placetype":"venue"
},
  "geometry": {"coordinates":[-1.454269,53.232079],"type":"Point"}
}