{
  "type": "Feature",
  "properties": {
    "addr:full":"36 Falmouth Gardens Ilford Essex IG4 5JU",
    "addr:housenumber":"36",
    "addr:postcode":"ig4 5ju",
    "addr:street":"Falmouth Gardens",
    "iso:country":"GB",
    "sg:address":"36 Falmouth Gardens",
    "sg:city":"Ilford",
    "sg:classifiers":[
        {
            "category":"Building & Trades",
            "subcategory":"Construction",
            "type":"Services"
        }
    ],
    "sg:phone":"+44 20 8551 5541",
    "sg:postcode":"IG4 5JU",
    "sg:province":"Essex",
    "sg:tags":[
        "builder"
    ],
    "wof:name":"J & N Contractors",
    "wof:placetype":"venue"
},
  "geometry": {"coordinates":[0.0501330011,51.5793075562],"type":"Point"}
}