{
  "type": "Feature",
  "properties": {
    "addr:full":"Station Road Wooler Northumberland NE71 6SP",
    "addr:postcode":"ne71 6sp",
    "addr:street":"Station Road",
    "iso:country":"GB",
    "sg:address":"Station Road",
    "sg:city":"Wooler",
    "sg:classifiers":[
        {
            "category":"Autos & Motor Vehicles",
            "subcategory":"Automobile Sales",
            "type":"Retail Goods"
        },
        {
            "category":"Retail",
            "subcategory":"Auto Repair",
            "type":"Services"
        }
    ],
    "sg:phone":"+44 1668 281193",
    "sg:postcode":"NE71 6SP",
    "sg:province":"Northumberland",
    "sg:tags":[
        "modification",
        "car",
        "related",
        "garage"
    ],
    "wof:name":"Anthony Hall",
    "wof:placetype":"venue"
},
  "geometry": {"coordinates":[-2.0122,55.55003],"type":"Point"}
}