{
  "type": "Feature",
  "properties": {
    "addr:full":"39 Bradford St Bolton Lancashire BL2 1HT",
    "addr:housenumber":"39",
    "addr:postcode":"bl2 1ht",
    "addr:street":"Bradford St",
    "iso:country":"GB",
    "sg:address":"39 Bradford St",
    "sg:city":"Bolton",
    "sg:classifiers":[
        {
            "category":"Social Services",
            "subcategory":"Retirement Home",
            "type":"Services"
        }
    ],
    "sg:postcode":"BL2 1HT",
    "sg:province":"Lancashire",
    "sg:tags":[
        "residential",
        "care"
    ],
    "wof:name":"Balgownie",
    "wof:placetype":"venue"
},
  "geometry": {"coordinates":[-2.417957,53.576904],"type":"Point"}
}