{
  "type": "Feature",
  "properties": {
    "iso:country":"GB",
    "sg:address":"Northbrook Pool, Beacon Lane",
    "sg:city":"Exeter",
    "sg:classifiers":[
        {
            "category":"Community Center",
            "type":"Public Place"
        },
        {
            "category":"Sports & Exercise",
            "subcategory":"Swimming Pool",
            "type":"Entertainment"
        }
    ],
    "sg:phone":"+44 1392 667020",
    "sg:postcode":"EX4 8LZ",
    "sg:province":"Devon",
    "sg:tags":[
        "leisure",
        "centre"
    ],
    "wof:name":"Northbrook Swimming Pool",
    "wof:placetype":"venue"
},
  "geometry": {"coordinates":[-3.494919,50.73951],"type":"Point"}
}