{
  "type": "Feature",
  "properties": {
    "addr:full":"31 Quay Street Newport Isle of Wight PO30 5BA",
    "addr:housenumber":"31",
    "addr:postcode":"po30 5ba",
    "addr:street":"Quay Street",
    "iso:country":"GB",
    "sg:address":"31 Quay Street",
    "sg:city":"Newport",
    "sg:classifiers":[
        {
            "category":"Social Services",
            "type":"Services"
        }
    ],
    "sg:phone":"+44 1983 530530",
    "sg:postcode":"PO30 5BA",
    "sg:province":"Isle of Wight",
    "sg:tags":[
        "helplines"
    ],
    "wof:name":"Iow Victim Support Scheme",
    "wof:placetype":"venue"
},
  "geometry": {"coordinates":[-1.2931879759,50.7006912231],"type":"Point"}
}