{
  "type": "Feature",
  "properties": {
    "addr:full":"1 Crucible Road Corby Northamptonshire NN17 5TS",
    "addr:housenumber":"1",
    "addr:postcode":"nn17 5ts",
    "addr:street":"Crucible Road",
    "iso:country":"GB",
    "sg:address":"1 Crucible Road",
    "sg:city":"Corby",
    "sg:classifiers":[
        {
            "category":"Retail",
            "subcategory":"Auto Repair",
            "type":"Services"
        }
    ],
    "sg:postcode":"NN17 5TS",
    "sg:province":"Northamptonshire",
    "sg:tags":[
        "modification",
        "garage"
    ],
    "wof:name":"Motoryard U K",
    "wof:placetype":"venue"
},
  "geometry": {"coordinates":[-0.678999,52.494301],"type":"Point"}
}