{
  "type": "Feature",
  "properties": {
    "addr:full":"2 The Wharf Sowerby Bridge West Yorkshire HX6 2AG",
    "addr:housenumber":"2",
    "addr:postcode":"hx6 2ag",
    "addr:street":"The Wharf",
    "iso:country":"GB",
    "sg:address":"2 The Wharf",
    "sg:city":"Sowerby Bridge",
    "sg:classifiers":[
        {
            "category":"Home & Garden",
            "subcategory":"Carpets & Floor Coverings",
            "type":"Retail Goods"
        }
    ],
    "sg:phone":"+44 1422 316300",
    "sg:postcode":"HX6 2AG",
    "sg:province":"West Yorkshire",
    "sg:tags":[
        "carpets",
        "rug",
        "matting"
    ],
    "wof:name":"Toucan Natural Flooring",
    "wof:placetype":"venue"
},
  "geometry": {"coordinates":[-1.908874,53.709061],"type":"Point"}
}