{
  "type": "Feature",
  "properties": {
    "iso:country":"GB",
    "sg:address":"11 Elmridge",
    "sg:city":"Skelmersdale",
    "sg:classifiers":[
        {
            "category":"Government",
            "subcategory":"Post Office",
            "type":"Public Place"
        }
    ],
    "sg:postcode":"WN8 6DF",
    "sg:province":"Lancashire",
    "wof:name":"Tamhouse Post Office",
    "wof:placetype":"venue"
},
  "geometry": {"coordinates":[-2.760681,53.548359],"type":"Point"}
}