{
  "type": "Feature",
  "properties": {
    "iso:country":"GB",
    "sg:address":"102 Broadgate Lane, Horsforth",
    "sg:city":"Leeds",
    "sg:classifiers":[
        {
            "category":"Building & Trades",
            "subcategory":"Plumbing",
            "type":"Services"
        }
    ],
    "sg:postcode":"LS18 4BS",
    "sg:province":"West Yorkshire",
    "sg:tags":[
        "heating"
    ],
    "wof:name":"J R Turner Plumbing & Heating",
    "wof:placetype":"venue"
},
  "geometry": {"coordinates":[-1.628261,53.837994],"type":"Point"}
}