{
  "type": "Feature",
  "properties": {
    "iso:country":"GB",
    "sg:address":"Orchard House, 17 Church Street",
    "sg:city":"Broadstairs",
    "sg:classifiers":[
        {
            "category":"Health Services",
            "subcategory":"Nursing And Care Facility",
            "type":"Services"
        },
        {
            "category":"Social Services",
            "subcategory":"Adult Care",
            "type":"Services"
        }
    ],
    "sg:phone":"+44 1843 604777",
    "sg:postcode":"CT10 2TT",
    "sg:province":"Kent",
    "sg:tags":[
        "mental",
        "day",
        "centre"
    ],
    "wof:name":"Orchard House",
    "wof:placetype":"venue"
},
  "geometry": {"coordinates":[1.419735,51.365726],"type":"Point"}
}