{
  "type": "Feature",
  "properties": {
    "addr:full":"22 Strood Rd St Leonards On Sea East Sussex TN37 6PN",
    "addr:housenumber":"22",
    "addr:postcode":"tn37 6pn",
    "addr:street":"Strood Rd St",
    "iso:country":"GB",
    "sg:address":"22 Strood Rd",
    "sg:city":"St Leonards On Sea",
    "sg:classifiers":[
        {
            "category":"Health Services",
            "subcategory":"Dentist",
            "type":"Services"
        }
    ],
    "sg:phone":"+44 1424 429160",
    "sg:postcode":"TN37 6PN",
    "sg:province":"East Sussex",
    "wof:name":"S J Carruthers",
    "wof:placetype":"venue"
},
  "geometry": {"coordinates":[0.5569630265,50.8680038452],"type":"Point"}
}