{
  "type": "Feature",
  "properties": {
    "addr:full":"West View Gallery, South Terrace Windermere Cumbria LA23 3AH",
    "addr:postcode":"la23 3ah",
    "addr:street":"South Terrace",
    "iso:country":"GB",
    "sg:address":"West View Gallery, South Terrace",
    "sg:city":"Windermere",
    "sg:classifiers":[
        {
            "category":"Building & Trades",
            "subcategory":"Construction",
            "type":"Services"
        }
    ],
    "sg:phone":"+44 15394 42643",
    "sg:postcode":"LA23 3AH",
    "sg:province":"Cumbria",
    "sg:tags":[
        "glazier"
    ],
    "wof:name":"Bowness Models",
    "wof:placetype":"venue"
},
  "geometry": {"coordinates":[-2.9224359989,54.3628692627],"type":"Point"}
}