{
  "type": "Feature",
  "properties": {
    "iso:country":"GB",
    "sg:address":"2 Cotswold Close, Chesterton",
    "sg:city":"Cirencester",
    "sg:classifiers":[
        {
            "category":"Building & Trades",
            "subcategory":"Construction",
            "type":"Services"
        }
    ],
    "sg:phone":"+44 1285 658292",
    "sg:postcode":"GL7 1XR",
    "sg:province":"Gloucestershire",
    "sg:tags":[
        "dry",
        "plastering",
        "plasterers",
        "lining",
        "related",
        "screeders"
    ],
    "wof:name":"T E Millard",
    "wof:placetype":"venue"
},
  "geometry": {"coordinates":[-1.972701,51.709873],"type":"Point"}
}