{
  "type": "Feature",
  "properties": {
    "iso:country":"GB",
    "sg:address":"24 Parsonage Road, Heaton Moor",
    "sg:city":"Stockport",
    "sg:classifiers":[
        {
            "category":"Health Services",
            "subcategory":"Doctor",
            "type":"Services"
        }
    ],
    "sg:postcode":"SK4 4JR",
    "sg:province":"Cheshire",
    "sg:tags":[
        "practitioners"
    ],
    "wof:name":"C Summerton",
    "wof:placetype":"venue"
},
  "geometry": {"coordinates":[-2.18282,53.420776],"type":"Point"}
}