{
  "type": "Feature",
  "properties": {
    "iso:country":"GB",
    "sg:address":"152 Alum Rock Road",
    "sg:city":"Birmingham",
    "sg:classifiers":[
        {
            "category":"Professional",
            "subcategory":"Printing & Photocopies",
            "type":"Services"
        }
    ],
    "sg:postcode":"B8 1HU",
    "sg:province":"West Midlands",
    "sg:tags":[
        "printer"
    ],
    "wof:name":"KHYBER PRINTING PRESS",
    "wof:placetype":"venue"
},
  "geometry": {"coordinates":[-1.852773,52.489586],"type":"Point"}
}