{
  "type": "Feature",
  "properties": {
    "iso:country":"GB",
    "sg:address":"Alpha House, Tyssen Street",
    "sg:city":"London",
    "sg:classifiers":[
        {
            "category":"Shopping",
            "subcategory":"Luggage & Leather Goods",
            "type":"Retail Goods"
        }
    ],
    "sg:phone":"+44 20 7249 3168",
    "sg:postcode":"E8 2ND",
    "sg:province":"Greater London",
    "wof:name":"Cambay Ltd.",
    "wof:placetype":"venue"
},
  "geometry": {"coordinates":[-0.06468,51.54845],"type":"Point"}
}