{
  "type": "Feature",
  "properties": {
    "iso:country":"GB",
    "sg:address":"Middlesex House, 34-42 Cleveland St",
    "sg:city":"West End",
    "sg:classifiers":[
        {
            "category":"Professional",
            "subcategory":"Advertising",
            "type":"Services"
        }
    ],
    "sg:phone":"+44 20 7637 7393",
    "sg:postcode":"W1P 5FB",
    "sg:province":"Hampshire",
    "sg:tags":[
        "agency"
    ],
    "wof:name":"Rainey Kelly Campbell Roalfe",
    "wof:placetype":"venue"
},
  "geometry": {"coordinates":[-0.182068,51.515945],"type":"Point"}
}