{
  "type": "Feature",
  "properties": {
    "iso:country":"GB",
    "sg:address":"373 Benton Road, Four Lane Ends, Long Benton",
    "sg:city":"Newcastle-upon-tyne",
    "sg:classifiers":[
        {
            "category":"Community Center",
            "subcategory":"Social",
            "type":"Public Place"
        }
    ],
    "sg:phone":"+44 191 270 1752",
    "sg:postcode":"NE7 7EE",
    "sg:province":"Tyne and Wear",
    "sg:tags":[
        "frozen",
        "food",
        "freezer",
        "centre"
    ],
    "wof:name":"Iceland Frozen Foods",
    "wof:placetype":"venue"
},
  "geometry": {"coordinates":[-1.578776,55.008884],"type":"Point"}
}