{
  "type": "Feature",
  "properties": {
    "addr:full":"48 Culvert Road London Greater London SW11 5BB",
    "addr:housenumber":"48",
    "addr:postcode":"sw11 5bb",
    "addr:street":"Culvert Road",
    "iso:country":"GB",
    "sg:address":"48 Culvert Road",
    "sg:city":"London",
    "sg:classifiers":[
        {
            "category":"Community Center",
            "type":"Public Place"
        },
        {
            "category":"Government",
            "subcategory":"Office",
            "type":"Public Place"
        }
    ],
    "sg:phone":"+44 20 8871 8172",
    "sg:postcode":"SW11 5BB",
    "sg:province":"Greater London",
    "sg:tags":[
        "local",
        "centre"
    ],
    "wof:name":"Wilditch Community Centre",
    "wof:placetype":"venue"
},
  "geometry": {"coordinates":[-0.1597860008,51.4719429016],"type":"Point"}
}