{
  "type": "Feature",
  "properties": {
    "addr:full":"Stoney Lane, Galgate Lancaster Lancashire LA2 0QY",
    "addr:postcode":"la2 0qy",
    "addr:street":"Stoney Lane Galgate",
    "iso:country":"GB",
    "sg:address":"Stoney Lane, Galgate",
    "sg:city":"Lancaster",
    "sg:classifiers":[
        {
            "category":"Food & Beverages",
            "subcategory":"Supermarket",
            "type":"Retail Goods"
        }
    ],
    "sg:phone":"+44 1524 751347",
    "sg:postcode":"LA2 0QY",
    "sg:province":"Lancashire",
    "sg:tags":[
        "frozen"
    ],
    "wof:name":"Honeycomb Co. Ltd.",
    "wof:placetype":"venue"
},
  "geometry": {"coordinates":[-2.785147,53.990753],"type":"Point"}
}