{
  "type": "Feature",
  "properties": {
    "addr:full":"62a Chester Road West Deeside Flintshire CH5 1BY",
    "addr:housenumber":"62a",
    "addr:postcode":"ch5 1by",
    "addr:street":"Chester Road West",
    "iso:country":"GB",
    "sg:address":"62a Chester Road West",
    "sg:city":"Deeside",
    "sg:classifiers":[
        {
            "category":"Food & Beverages",
            "subcategory":"Specialty",
            "type":"Retail Goods"
        }
    ],
    "sg:phone":"+44 1244 830702",
    "sg:postcode":"CH5 1BY",
    "sg:province":"Flintshire",
    "sg:tags":[
        "product",
        "health"
    ],
    "wof:name":"Shotton Health Foods",
    "wof:placetype":"venue"
},
  "geometry": {"coordinates":[-3.04042,53.209972],"type":"Point"}
}