{
  "type": "Feature",
  "properties": {
    "addr:full":"The Business Centre, Normanby Rd Scunthorpe Lincolnshire DN15 8QZ",
    "addr:postcode":"dn15 8qz",
    "addr:street":"Normanby Rd",
    "iso:country":"GB",
    "sg:address":"The Business Centre, Normanby Rd",
    "sg:city":"Scunthorpe",
    "sg:classifiers":[
        {
            "category":"Banks & Credit Unions",
            "subcategory":"Financial Services",
            "type":"Services"
        }
    ],
    "sg:phone":"+44 1724 855666",
    "sg:postcode":"DN15 8QZ",
    "sg:province":"Lincolnshire",
    "sg:tags":[
        "consultant"
    ],
    "wof:name":"Victor Finance Group",
    "wof:placetype":"venue"
},
  "geometry": {"coordinates":[-0.651811,53.586502],"type":"Point"}
}