{
  "type": "Feature",
  "properties": {
    "addr:full":"1 Petherton Rd Bridgwater Somerset TA7 0BD",
    "addr:housenumber":"1",
    "addr:postcode":"ta7 0bd",
    "addr:street":"Petherton Rd",
    "iso:country":"GB",
    "sg:address":"1 Petherton Rd",
    "sg:city":"Bridgwater",
    "sg:classifiers":[
        {
            "category":"Building & Trades",
            "subcategory":"Landscaping Services",
            "type":"Services"
        }
    ],
    "sg:phone":"+44 1278 662103",
    "sg:postcode":"TA7 0BD",
    "sg:province":"Somerset",
    "sg:tags":[
        "forestry",
        "tree"
    ],
    "wof:name":"M Duddridge",
    "wof:placetype":"venue"
},
  "geometry": {"coordinates":[-3.002425909,51.073841095],"type":"Point"}
}