{
  "type": "Feature",
  "properties": {
    "addr:full":"17-21 Redhills Road, South Woodham Ferrers Chelmsford Essex CM3 5UL",
    "addr:housenumber":"17-21",
    "addr:postcode":"cm3 5ul",
    "addr:street":"Redhills Road",
    "iso:country":"GB",
    "sg:address":"17-21 Redhills Road, South Woodham Ferrers",
    "sg:city":"Chelmsford",
    "sg:classifiers":[
        {
            "category":"Professional",
            "subcategory":"Printing & Photocopies",
            "type":"Services"
        }
    ],
    "sg:phone":"+44 1245 325249",
    "sg:postcode":"CM3 5UL",
    "sg:province":"Essex",
    "sg:tags":[
        "computer",
        "tag",
        "label"
    ],
    "wof:name":"Label Trading Co",
    "wof:placetype":"venue"
},
  "geometry": {"coordinates":[0.6221849918,51.6503982544],"type":"Point"}
}