{
  "type": "Feature",
  "properties": {
    "addr:full":"22 Watermill Way, Hanmorth Feltham Greater London TW13 5NG",
    "addr:housenumber":"22",
    "addr:postcode":"tw13 5ng",
    "addr:street":"Watermill Way Hanmorth",
    "iso:country":"GB",
    "sg:address":"22 Watermill Way, Hanmorth",
    "sg:city":"Feltham",
    "sg:classifiers":[
        {
            "category":"Building & Trades",
            "subcategory":"Construction",
            "type":"Services"
        }
    ],
    "sg:postcode":"TW13 5NG",
    "sg:province":"Greater London",
    "sg:tags":[
        "builder"
    ],
    "wof:name":"Colt Plastering Services",
    "wof:placetype":"venue"
},
  "geometry": {"coordinates":[-0.376664,51.441528],"type":"Point"}
}