{
  "type": "Feature",
  "properties": {
    "iso:country":"GB",
    "sg:address":"67 Kelvin Road",
    "sg:city":"Leamington Spa",
    "sg:classifiers":[
        {
            "category":"Shopping",
            "subcategory":"News",
            "type":"Retail Goods"
        }
    ],
    "sg:postcode":"CV32 7TG",
    "sg:province":"Warwickshire",
    "sg:tags":[
        "newsagent"
    ],
    "wof:name":"S A News",
    "wof:placetype":"venue"
},
  "geometry": {"coordinates":[-1.516605,52.312847],"type":"Point"}
}