{
  "type": "Feature",
  "properties": {
    "iso:country":"GB",
    "sg:address":"18 North Street",
    "sg:city":"Hornchurch",
    "sg:classifiers":[
        {
            "category":"Real Estate",
            "subcategory":"Real Estate Agent",
            "type":"Services"
        }
    ],
    "sg:phone":"+44 1708 457916",
    "sg:postcode":"RM11 1QP",
    "sg:province":"Essex",
    "wof:name":"Hilbery Chaplin Residential",
    "wof:placetype":"venue"
},
  "geometry": {"coordinates":[0.2204049975,51.5630493164],"type":"Point"}
}