{
  "type": "Feature",
  "properties": {
    "addr:full":"20 Gerard Road Rotherham South Yorkshire S60 2QE",
    "addr:housenumber":"20",
    "addr:postcode":"s60 2qe",
    "addr:street":"Gerard Road",
    "iso:country":"GB",
    "sg:address":"20 Gerard Road",
    "sg:city":"Rotherham",
    "sg:classifiers":[
        {
            "category":"Shopping",
            "subcategory":"Department Store",
            "type":"Retail Goods"
        }
    ],
    "sg:phone":"+44 1709 363365",
    "sg:postcode":"S60 2QE",
    "sg:province":"South Yorkshire",
    "wof:name":"Bostan & Sons",
    "wof:placetype":"venue"
},
  "geometry": {"coordinates":[-1.348506,53.426533],"type":"Point"}
}