{
  "type": "Feature",
  "properties": {
    "iso:country":"GB",
    "sg:address":"27 Barrowden Rd, Ketton",
    "sg:city":"Stamford",
    "sg:classifiers":[
        {
            "category":"Retail",
            "subcategory":"Storage",
            "type":"Services"
        }
    ],
    "sg:postcode":"PE9 3RJ",
    "sg:province":"Cambridgeshire",
    "sg:tags":[
        "household",
        "removal"
    ],
    "wof:name":"Ross,John,",
    "wof:placetype":"venue"
},
  "geometry": {"coordinates":[-0.560245,52.616104],"type":"Point"}
}