{
  "type": "Feature",
  "properties": {
    "addr:full":"39 Masefield Avenue Borehamwood Hertfordshire WD6 2HH",
    "addr:housenumber":"39",
    "addr:postcode":"wd6 2hh",
    "addr:street":"Masefield Avenue Borehamwood",
    "iso:country":"GB",
    "sg:address":"39 Masefield Avenue",
    "sg:city":"Borehamwood",
    "sg:classifiers":[
        {
            "category":"Manufacturing",
            "subcategory":"Wood Products",
            "type":"Manufacturing & Wholesale Goods"
        }
    ],
    "sg:postcode":"WD6 2HH",
    "sg:province":"Hertfordshire",
    "sg:tags":[
        "maker",
        "cabinet"
    ],
    "wof:name":"R Cabinet Making Johnson",
    "wof:placetype":"venue"
},
  "geometry": {"coordinates":[-0.2691510022,51.6479225159],"type":"Point"}
}