{
  "type": "Feature",
  "properties": {
    "addr:full":"3 Graham Road, Wealdstone Harrow Greater London HA3 5RP",
    "addr:housenumber":"3",
    "addr:postcode":"ha3 5rp",
    "addr:street":"Graham Road",
    "iso:country":"GB",
    "sg:address":"3 Graham Road, Wealdstone",
    "sg:city":"Harrow",
    "sg:classifiers":[
        {
            "category":"Shopping",
            "subcategory":"Optical Goods",
            "type":"Retail Goods"
        }
    ],
    "sg:phone":"+44 20 8861 2424",
    "sg:postcode":"HA3 5RP",
    "sg:province":"Greater London",
    "sg:tags":[
        "medical"
    ],
    "wof:name":"Global Optic International Ltd.",
    "wof:placetype":"venue"
},
  "geometry": {"coordinates":[-0.3369710147,51.5974769592],"type":"Point"}
}