{
  "type": "Feature",
  "properties": {
    "iso:country":"GB",
    "sg:address":"48 High Road",
    "sg:city":"London",
    "sg:classifiers":[
        {
            "category":"Organizations",
            "subcategory":"Non-profit Organization",
            "type":"Services"
        }
    ],
    "sg:phone":"+44 20 8444 6290",
    "sg:postcode":"N2 9PJ",
    "sg:province":"Greater London",
    "sg:tags":[
        "charitable",
        "organisation",
        "voluntary",
        "charity"
    ],
    "wof:name":"Animal Aid & Advice",
    "wof:placetype":"venue"
},
  "geometry": {"coordinates":[-0.1639100015,51.5884170532],"type":"Point"}
}