{
  "type": "Feature",
  "properties": {
    "iso:country":"GB",
    "sg:address":"225 High Street, Tunstall",
    "sg:city":"Stoke-on-trent",
    "sg:classifiers":[
        {
            "category":"Professional",
            "subcategory":"Computer Services",
            "type":"Services"
        }
    ],
    "sg:phone":"+44 1782 575550",
    "sg:postcode":"ST6 5EG",
    "sg:province":"Staffordshire",
    "sg:tags":[
        "system",
        "software"
    ],
    "wof:name":"Wilton Photomech Ltd.",
    "wof:placetype":"venue"
},
  "geometry": {"coordinates":[-2.2108049393,53.060710907],"type":"Point"}
}