{
  "type": "Feature",
  "properties": {
    "addr:full":"4-6 Front Rd Ashford Kent TN26 3QE",
    "addr:housenumber":"4-6",
    "addr:postcode":"tn26 3qe",
    "addr:street":"Front Rd",
    "iso:country":"GB",
    "sg:address":"4-6 Front Rd",
    "sg:city":"Ashford",
    "sg:classifiers":[
        {
            "category":"Real Estate",
            "subcategory":"Real Estate Agent",
            "type":"Services"
        }
    ],
    "sg:phone":"+44 1233 861460",
    "sg:postcode":"TN26 3QE",
    "sg:province":"Kent",
    "wof:name":"Mealham Estate",
    "wof:placetype":"venue"
},
  "geometry": {"coordinates":[0.772390008,51.0804710388],"type":"Point"}
}