{
  "type": "Feature",
  "properties": {
    "addr:full":"102 Collier Row Lane Romford Essex RM5 3DT",
    "addr:housenumber":"102",
    "addr:postcode":"rm5 3dt",
    "addr:street":"Collier Row Lane",
    "iso:country":"GB",
    "sg:address":"102 Collier Row Lane",
    "sg:city":"Romford",
    "sg:classifiers":[
        {
            "category":"Personal",
            "subcategory":"Beauty Salon",
            "type":"Services"
        }
    ],
    "sg:phone":"+44 1708 741771",
    "sg:postcode":"RM5 3DT",
    "sg:province":"Essex",
    "sg:tags":[
        "unisex",
        "hairdresser"
    ],
    "wof:name":"Sisto's",
    "wof:placetype":"venue"
},
  "geometry": {"coordinates":[0.1666170061,51.5909156799],"type":"Point"}
}