{
  "type": "Feature",
  "properties": {
    "addr:full":"12 Polbathic Rd Redruth Cornwall TR15 1PZ",
    "addr:housenumber":"12",
    "addr:postcode":"tr15 1pz",
    "addr:street":"Polbathic Rd",
    "iso:country":"GB",
    "sg:address":"12 Polbathic Rd",
    "sg:city":"Redruth",
    "sg:classifiers":[
        {
            "category":"Retail",
            "subcategory":"Driving School",
            "type":"Services"
        }
    ],
    "sg:phone":"+44 1209 217005",
    "sg:postcode":"TR15 1PZ",
    "sg:province":"Cornwall",
    "wof:name":"Anne's Driving School",
    "wof:placetype":"venue"
},
  "geometry": {"coordinates":[-5.220102,50.23806],"type":"Point"}
}