{
  "type": "Feature",
  "properties": {
    "addr:full":"117 Fordway Avenue Blackpool Lancashire FY3 8LG",
    "addr:housenumber":"117",
    "addr:postcode":"fy3 8lg",
    "addr:street":"Fordway Avenue",
    "iso:country":"GB",
    "sg:address":"117 Fordway Avenue",
    "sg:city":"Blackpool",
    "sg:classifiers":[
        {
            "category":"Building & Trades",
            "subcategory":"Construction",
            "type":"Services"
        }
    ],
    "sg:phone":"+44 1253 392165",
    "sg:postcode":"FY3 8LG",
    "sg:province":"Lancashire",
    "sg:tags":[
        "decorator",
        "painter"
    ],
    "wof:name":"H Southworth",
    "wof:placetype":"venue"
},
  "geometry": {"coordinates":[-3.023444891,53.8232192993],"type":"Point"}
}