{
  "type": "Feature",
  "properties": {
    "addr:full":"22 Albert Street St Albans Hertfordshire AL1 1RU",
    "addr:housenumber":"22",
    "addr:postcode":"al1 1ru",
    "addr:street":"Albert Street",
    "iso:country":"GB",
    "sg:address":"22 Albert Street",
    "sg:city":"St Albans",
    "sg:classifiers":[
        {
            "category":"Retail",
            "subcategory":"Auto Repair",
            "type":"Services"
        }
    ],
    "sg:phone":"+44 1727 856543",
    "sg:postcode":"AL1 1RU",
    "sg:province":"Hertfordshire",
    "sg:tags":[
        "modification",
        "garage"
    ],
    "wof:name":"Robert Nissen",
    "wof:placetype":"venue"
},
  "geometry": {"coordinates":[-0.33950001,51.7490615845],"type":"Point"}
}