{
  "type": "Feature",
  "properties": {
    "addr:full":"43 High Street, Swallownest Sheffield South Yorkshire S26 4TT",
    "addr:housenumber":"43",
    "addr:postcode":"s26 4tt",
    "addr:street":"High Street",
    "iso:country":"GB",
    "sg:address":"43 High Street, Swallownest",
    "sg:city":"Sheffield",
    "sg:classifiers":[
        {
            "category":"Banks & Credit Unions",
            "subcategory":"Bank",
            "type":"Services"
        }
    ],
    "sg:phone":"+44 114 287 2413",
    "sg:postcode":"S26 4TT",
    "sg:province":"South Yorkshire",
    "wof:name":"The Royal Bank of Scotland Plc",
    "wof:placetype":"venue"
},
  "geometry": {"coordinates":[-1.3218690157,53.3635482788],"type":"Point"}
}