{
  "type": "Feature",
  "properties": {
    "addr:full":"Stapleton Presteigne Herefordshire LD8 2LP",
    "addr:postcode":"ld8 2lp",
    "addr:street":"Herefordshire",
    "iso:country":"GB",
    "sg:address":"Stapleton",
    "sg:city":"Presteigne",
    "sg:classifiers":[
        {
            "category":"Communications",
            "subcategory":"Newspaper",
            "type":"Services"
        }
    ],
    "sg:postcode":"LD8 2LP",
    "sg:province":"Herefordshire",
    "sg:tags":[
        "magazine"
    ],
    "wof:name":"Bryansground Press",
    "wof:placetype":"venue"
},
  "geometry": {"coordinates":[-3.0044538975,52.2702064514],"type":"Point"}
}