{
  "type": "Feature",
  "properties": {
    "addr:full":"Bays, 1 &, 2 Block, Mill, Race Lane Stourbridge Staffordshire DY8 1JN",
    "addr:housenumber":"bays 1 & 2",
    "addr:postcode":"dy8 1jn",
    "addr:street":"Block Mill Race Lane",
    "iso:country":"GB",
    "sg:address":"Bays, 1 &, 2 Block, Mill, Race Lane",
    "sg:city":"Stourbridge",
    "sg:classifiers":[
        {
            "category":"Government",
            "subcategory":"Post Office",
            "type":"Public Place"
        }
    ],
    "sg:phone":"+44 1384 377001",
    "sg:postcode":"DY8 1JN",
    "sg:province":"Staffordshire",
    "sg:tags":[
        "copper",
        "brass"
    ],
    "wof:name":"Allied Copper",
    "wof:placetype":"venue"
},
  "geometry": {"coordinates":[-2.14657,52.46014],"type":"Point"}
}