{
  "type": "Feature",
  "properties": {
    "addr:full":"Sunnyside Cottage, Lonmay Fraserburgh Aberdeenshire AB43 8ST",
    "addr:postcode":"ab43 8st",
    "addr:street":"Lonmay",
    "iso:country":"GB",
    "sg:address":"Sunnyside Cottage, Lonmay",
    "sg:city":"Fraserburgh",
    "sg:classifiers":[
        {
            "category":"Retail",
            "subcategory":"Repair Shop",
            "type":"Services"
        },
        {
            "category":"Manufacturing",
            "subcategory":"Furniture",
            "type":"Manufacturing & Wholesale Goods"
        }
    ],
    "sg:phone":"+44 1346 532939",
    "sg:postcode":"AB43 8ST",
    "sg:province":"Aberdeenshire",
    "sg:tags":[
        "restored"
    ],
    "wof:name":"Renovations",
    "wof:placetype":"venue"
},
  "geometry": {"coordinates":[-1.9717390537,57.6195793152],"type":"Point"}
}