{
  "type": "Feature",
  "properties": {
    "addr:full":"Euro Park, Redwick Newport Monmouthshire NP26 3TS",
    "addr:postcode":"np26 3ts",
    "iso:country":"GB",
    "sg:address":"Euro Park, Redwick",
    "sg:city":"Newport",
    "sg:classifiers":[
        {
            "category":"Professional",
            "subcategory":"Business Services",
            "type":"Services"
        }
    ],
    "sg:phone":"+44 1633 207100",
    "sg:postcode":"NP26 3TS",
    "sg:province":"Monmouthshire",
    "sg:tags":[
        "distribution"
    ],
    "wof:name":"Tesco R D C",
    "wof:placetype":"venue"
},
  "geometry": {"coordinates":[-2.8205499649,51.5873985291],"type":"Point"}
}