{
  "type": "Feature",
  "properties": {
    "addr:full":"159 High Street Epsom Surrey KT19 8EW",
    "addr:housenumber":"159",
    "addr:postcode":"kt19 8ew",
    "addr:street":"High Street",
    "iso:country":"GB",
    "sg:address":"159 High Street",
    "sg:city":"Epsom",
    "sg:classifiers":[
        {
            "category":"Professional",
            "type":"Services"
        }
    ],
    "sg:phone":"+44 1372 721773",
    "sg:postcode":"KT19 8EW",
    "sg:province":"Surrey",
    "sg:tags":[
        "interior",
        "furnishers",
        "designer"
    ],
    "wof:name":"J Decor Interiors Ltd.",
    "wof:placetype":"venue"
},
  "geometry": {"coordinates":[-0.2701539993,51.3327140808],"type":"Point"}
}