{
  "type": "Feature",
  "properties": {
    "addr:full":"40 Bowling Green Lane London Greater London EC1R 0NE",
    "addr:housenumber":"40",
    "addr:postcode":"ec1r 0ne",
    "addr:street":"Bowling Green Lane",
    "iso:country":"GB",
    "sg:address":"40 Bowling Green Lane",
    "sg:city":"London",
    "sg:classifiers":[
        {
            "category":"Professional",
            "subcategory":"Computer Services",
            "type":"Services"
        }
    ],
    "sg:phone":"+44 70 0246 6682",
    "sg:postcode":"EC1R 0NE",
    "sg:province":"Greater London",
    "sg:tags":[
        "consultant"
    ],
    "wof:name":"Advanced Solutions Development Ltd.",
    "wof:placetype":"venue"
},
  "geometry": {"coordinates":[-0.107356,51.524761],"type":"Point"}
}