{
  "type": "Feature",
  "properties": {
    "iso:country":"GB",
    "sg:address":"207 Daniells",
    "sg:city":"Welwyn Garden City",
    "sg:classifiers":[
        {
            "category":"Home & Garden",
            "subcategory":"Household Appliances",
            "type":"Retail Goods"
        },
        {
            "category":"Retail",
            "subcategory":"Repair Shop",
            "type":"Services"
        }
    ],
    "sg:phone":"+44 1707 390800",
    "sg:postcode":"AL7 1QH",
    "sg:province":"Hertfordshire",
    "sg:tags":[
        "machine",
        "electrical",
        "washing"
    ],
    "wof:name":"K S D Domestics",
    "wof:placetype":"venue"
},
  "geometry": {"coordinates":[-0.181604,51.804684],"type":"Point"}
}