{
  "type": "Feature",
  "properties": {
    "addr:full":"133 Bloomsbury Lane, Timperley Altrincham Cheshire WA15 6NS",
    "addr:housenumber":"133",
    "addr:postcode":"wa15 6ns",
    "addr:street":"Bloomsbury Lane",
    "iso:country":"GB",
    "sg:address":"133 Bloomsbury Lane, Timperley",
    "sg:city":"Altrincham",
    "sg:classifiers":[
        {
            "category":"Retail",
            "subcategory":"Driving School",
            "type":"Services"
        }
    ],
    "sg:phone":"+44 161 980 8847",
    "sg:postcode":"WA15 6NS",
    "sg:province":"Cheshire",
    "wof:name":"Bloomsbury School of Motoring",
    "wof:placetype":"venue"
},
  "geometry": {"coordinates":[-2.3240170479,53.3961677551],"type":"Point"}
}