{
  "type": "Feature",
  "properties": {
    "iso:country":"GB",
    "sg:address":"34 High Street, Llandaff",
    "sg:city":"Cardiff",
    "sg:classifiers":[
        {
            "category":"Real Estate",
            "subcategory":"Real Estate Agent",
            "type":"Services"
        }
    ],
    "sg:phone":"+44 29 2056 1947",
    "sg:postcode":"CF5 2DZ",
    "sg:province":"Cardiff",
    "wof:name":"F Carey Jones",
    "wof:placetype":"venue"
},
  "geometry": {"coordinates":[-3.219478,51.493855],"type":"Point"}
}