{
  "type": "Feature",
  "properties": {
    "iso:country":"GB",
    "sg:address":"Unit 23, Woods Way, The Martlets Trading Estate",
    "sg:city":"Worthing",
    "sg:classifiers":[
        {
            "category":"Building & Trades",
            "subcategory":"Construction",
            "type":"Services"
        }
    ],
    "sg:phone":"+44 1903 506946",
    "sg:postcode":"BN12 4QY",
    "sg:province":"West Sussex",
    "sg:tags":[
        "window",
        "replacement"
    ],
    "wof:name":"Glasstec",
    "wof:placetype":"venue"
},
  "geometry": {"coordinates":[-0.4231590033,50.8170661926],"type":"Point"}
}