{
  "type": "Feature",
  "properties": {
    "addr:full":"68 Pathfield Road London Greater London SW16 5NY",
    "addr:housenumber":"68",
    "addr:postcode":"sw16 5ny",
    "addr:street":"Pathfield Road",
    "iso:country":"GB",
    "sg:address":"68 Pathfield Road",
    "sg:city":"London",
    "sg:classifiers":[
        {
            "category":"Professional",
            "subcategory":"Computer Services",
            "type":"Services"
        }
    ],
    "sg:postcode":"SW16 5NY",
    "sg:province":"Greater London",
    "sg:tags":[
        "system",
        "software"
    ],
    "wof:name":"Blackbird Data Services Ltd",
    "wof:placetype":"venue"
},
  "geometry": {"coordinates":[-0.132081002,51.4207267761],"type":"Point"}
}