{
  "type": "Feature",
  "properties": {
    "addr:full":"1 Vale Av Wantage Berkshire OX12 7LU",
    "addr:housenumber":"1",
    "addr:postcode":"ox12 7lu",
    "addr:street":"Vale Av Wantage",
    "iso:country":"GB",
    "sg:address":"1 Vale Av",
    "sg:city":"Wantage",
    "sg:classifiers":[
        {
            "category":"Health Services",
            "subcategory":"Dentist",
            "type":"Services"
        }
    ],
    "sg:phone":"+44 1235 763322",
    "sg:postcode":"OX12 7LU",
    "sg:province":"Berkshire",
    "wof:name":"A J Atkins",
    "wof:placetype":"venue"
},
  "geometry": {"coordinates":[-1.4190340042,51.6094703674],"type":"Point"}
}