{
  "type": "Feature",
  "properties": {
    "iso:country":"GB",
    "sg:address":"Unit 11 Dunton Trading Estate, Mount Street",
    "sg:city":"Birmingham",
    "sg:classifiers":[
        {
            "category":"Shopping",
            "subcategory":"Stationery & Office Supplies",
            "type":"Retail Goods"
        },
        {
            "category":"Wholesale",
            "subcategory":"Office Equipment",
            "type":"Manufacturing & Wholesale Goods"
        }
    ],
    "sg:phone":"+44 121 327 7070",
    "sg:postcode":"B7 5QL",
    "sg:province":"West Midlands",
    "sg:tags":[
        "supplier",
        "furniture"
    ],
    "wof:name":"Guardian Office Supplies Ltd",
    "wof:placetype":"venue"
},
  "geometry": {"coordinates":[-1.861209,52.500881],"type":"Point"}
}