{
  "type": "Feature",
  "properties": {
    "iso:country":"GB",
    "sg:address":"1 Collingwood Road",
    "sg:city":"Horsham",
    "sg:classifiers":[
        {
            "category":"Real Estate",
            "subcategory":"Real Estate Agent",
            "type":"Services"
        }
    ],
    "sg:postcode":"RH12 2QN",
    "sg:province":"West Sussex",
    "wof:name":"Domina House (Commercial)",
    "wof:placetype":"venue"
},
  "geometry": {"coordinates":[-0.330575,51.073215],"type":"Point"}
}