{
  "type": "Feature",
  "properties": {
    "addr:full":"16-18 Lensfield Road Cambridge Cambridgeshire CB2 1EG",
    "addr:housenumber":"16-18",
    "addr:postcode":"cb2 1eg",
    "addr:street":"Lensfield Road",
    "iso:country":"GB",
    "sg:address":"16-18 Lensfield Road",
    "sg:city":"Cambridge",
    "sg:classifiers":[
        {
            "category":"Shopping",
            "subcategory":"Antiques",
            "type":"Retail Goods"
        }
    ],
    "sg:postcode":"CB2 1EG",
    "sg:province":"Cambridgeshire",
    "wof:name":"Cottage Antiques",
    "wof:placetype":"venue"
},
  "geometry": {"coordinates":[0.126365006,52.1988296509],"type":"Point"}
}