{
  "type": "Feature",
  "properties": {
    "iso:country":"GB",
    "sg:address":"109 Portland Street",
    "sg:city":"Manchester",
    "sg:classifiers":[
        {
            "category":"Communications",
            "subcategory":"Film & Video Production",
            "type":"Services"
        }
    ],
    "sg:postcode":"M1 6DN",
    "sg:province":"Greater Manchester",
    "sg:tags":[
        "recording",
        "studio"
    ],
    "wof:name":"Riff Raff",
    "wof:placetype":"venue"
},
  "geometry": {"coordinates":[-2.240446,53.477196],"type":"Point"}
}