{
  "type": "Feature",
  "properties": {
    "iso:country":"GB",
    "sg:address":"West Park Farm North Retail Park, Park Farm Road",
    "sg:city":"Folkestone",
    "sg:classifiers":[
        {
            "category":"Autos & Motor Vehicles",
            "subcategory":"Auto Supplies",
            "type":"Retail Goods"
        },
        {
            "category":"Shopping",
            "type":"Retail Goods"
        }
    ],
    "sg:phone":"+44 1303 251101",
    "sg:postcode":"CT19 5DS",
    "sg:province":"Kent",
    "sg:tags":[
        "car",
        "part",
        "accessory"
    ],
    "wof:name":"Halfords Ltd",
    "wof:placetype":"venue"
},
  "geometry": {"coordinates":[1.1749500036,51.087928772],"type":"Point"}
}