{
  "type": "Feature",
  "properties": {
    "addr:full":"2 Campion Way Morecambe Lancashire LA3 3QE",
    "addr:housenumber":"2",
    "addr:postcode":"la3 3qe",
    "addr:street":"Campion Way",
    "iso:country":"GB",
    "sg:address":"2 Campion Way",
    "sg:city":"Morecambe",
    "sg:classifiers":[
        {
            "category":"Building & Trades",
            "subcategory":"Cleaning & Sanitation",
            "type":"Services"
        }
    ],
    "sg:postcode":"LA3 3QE",
    "sg:province":"Lancashire",
    "sg:tags":[
        "sweep",
        "chimney"
    ],
    "wof:name":"E Taylor",
    "wof:placetype":"venue"
},
  "geometry": {"coordinates":[-2.8616919518,54.0590171814],"type":"Point"}
}