{
  "type": "Feature",
  "properties": {
    "addr:full":"Unit 2 National Trading Estate, Bramhall Moor Lane, Hazel Gro Stockport Cheshire SK7 5AA",
    "addr:housenumber":"unit 2",
    "addr:postcode":"sk7 5aa",
    "addr:street":"National Trading Estate;Moor Lane",
    "iso:country":"GB",
    "sg:address":"Unit 2 National Trading Estate, Bramhall Moor Lane, Hazel Gro",
    "sg:city":"Stockport",
    "sg:classifiers":[
        {
            "category":"Utilities",
            "subcategory":"Refuse",
            "type":"Services"
        },
        {
            "category":"Utilities",
            "subcategory":"Recycling",
            "type":"Services"
        }
    ],
    "sg:phone":"+44 161 456 0102",
    "sg:postcode":"SK7 5AA",
    "sg:province":"Cheshire",
    "sg:tags":[
        "disposal",
        "processing",
        "machiney",
        "waste"
    ],
    "wof:name":"Bernard McCartney Ltd.",
    "wof:placetype":"venue"
},
  "geometry": {"coordinates":[-2.130544,53.382225],"type":"Point"}
}