{
  "type": "Feature",
  "properties": {
    "iso:country":"GB",
    "sg:address":"8 Carlton Street",
    "sg:city":"Castleford",
    "sg:classifiers":[
        {
            "category":"Fast Food",
            "type":"Food & Drink"
        }
    ],
    "sg:phone":"+44 1977 552096",
    "sg:postcode":"WF10 1AY",
    "sg:province":"West Yorkshire",
    "sg:tags":[
        "away",
        "meal",
        "outlet",
        "take"
    ],
    "wof:name":"Mayfair Chop Suey Bar",
    "wof:placetype":"venue"
},
  "geometry": {"coordinates":[-1.349532,53.726906],"type":"Point"}
}