{
  "type": "Feature",
  "properties": {
    "addr:full":"Unit 3, Nat Lane Winsford Cheshire CW7 3BS",
    "addr:housenumber":"unit 3",
    "addr:postcode":"cw7 3bs",
    "addr:street":"Nat Lane",
    "iso:country":"GB",
    "sg:address":"Unit 3, Nat Lane",
    "sg:city":"Winsford",
    "sg:classifiers":[
        {
            "category":"Home & Garden",
            "subcategory":"Home Furnishings",
            "type":"Retail Goods"
        }
    ],
    "sg:phone":"+44 1606 554667",
    "sg:postcode":"CW7 3BS",
    "sg:province":"Cheshire",
    "sg:tags":[
        "homefurnishings"
    ],
    "wof:name":"Tommy Bird",
    "wof:placetype":"venue"
},
  "geometry": {"coordinates":[-2.5129089355,53.1992492676],"type":"Point"}
}