{
  "type": "Feature",
  "properties": {
    "addr:full":"Masters Ho, Bexton Rd Knutsford Cheshire WA16 0BU",
    "addr:postcode":"wa16 0bu",
    "addr:street":"Bexton Rd",
    "iso:country":"GB",
    "sg:address":"Masters Ho, Bexton Rd",
    "sg:city":"Knutsford",
    "sg:classifiers":[
        {
            "category":"Building & Trades",
            "subcategory":"Cleaning & Sanitation",
            "type":"Services"
        }
    ],
    "sg:phone":"+44 1565 633396",
    "sg:postcode":"WA16 0BU",
    "sg:province":"Cheshire",
    "sg:tags":[
        "commercial"
    ],
    "wof:name":"Commercial Facilities",
    "wof:placetype":"venue"
},
  "geometry": {"coordinates":[-2.37624,53.304203],"type":"Point"}
}