{
  "type": "Feature",
  "properties": {
    "addr:full":"22 Springfield Close Corsham Wiltshire SN13 0JP",
    "addr:housenumber":"22",
    "addr:postcode":"sn13 0jp",
    "addr:street":"Springfield Close",
    "iso:country":"GB",
    "sg:address":"22 Springfield Close",
    "sg:city":"Corsham",
    "sg:classifiers":[
        {
            "category":"Military Area",
            "subcategory":"Air Force Base",
            "type":"Public Place"
        }
    ],
    "sg:phone":"+44 1225 810985",
    "sg:postcode":"SN13 0JP",
    "sg:province":"Wiltshire",
    "sg:tags":[
        "taxi",
        "hire",
        "private"
    ],
    "wof:name":"Michael's Taxis",
    "wof:placetype":"venue"
},
  "geometry": {"coordinates":[-2.224678,51.424107],"type":"Point"}
}