{
  "type": "Feature",
  "properties": {
    "iso:country":"GB",
    "sg:address":"5 Timberley Lane",
    "sg:city":"Birmingham",
    "sg:classifiers":[
        {
            "category":"Fast Food",
            "type":"Food & Drink"
        },
        {
            "category":"Food & Beverages",
            "subcategory":"Bakery",
            "type":"Retail Goods"
        }
    ],
    "sg:phone":"+44 121 747 7000",
    "sg:postcode":"B34 7ED",
    "sg:province":"West Midlands",
    "sg:tags":[
        "away",
        "pizza",
        "meal",
        "outlet",
        "take"
    ],
    "wof:name":"Snappy Tomato Pizza Ltd.",
    "wof:placetype":"venue"
},
  "geometry": {"coordinates":[-1.7719819546,52.5009918213],"type":"Point"}
}