{
  "type": "Feature",
  "properties": {
    "iso:country":"GB",
    "sg:address":"Princess Avenue",
    "sg:city":"Ilfracombe",
    "sg:classifiers":[
        {
            "category":"Education",
            "subcategory":"School",
            "type":"Public Place"
        }
    ],
    "sg:phone":"+44 1271 863463",
    "sg:postcode":"EX34 9LW",
    "sg:province":"Devon",
    "sg:tags":[
        "local",
        "authority"
    ],
    "wof:name":"Ilfracombe Junior School",
    "wof:placetype":"venue"
},
  "geometry": {"coordinates":[-4.120626,51.206654],"type":"Point"}
}