{
  "type": "Feature",
  "properties": {
    "addr:full":"161 Wareham Road, Corfe Mullen Wimborne Dorset BH21 3LB",
    "addr:housenumber":"161",
    "addr:postcode":"bh21 3lb",
    "addr:street":"Wareham Road",
    "iso:country":"GB",
    "sg:address":"161 Wareham Road, Corfe Mullen",
    "sg:city":"Wimborne",
    "sg:classifiers":[
        {
            "category":"Food & Beverages",
            "subcategory":"Fruits & Vegetables",
            "type":"Retail Goods"
        },
        {
            "category":"Wholesale",
            "subcategory":"Fruits & Vegetables",
            "type":"Manufacturing & Wholesale Goods"
        }
    ],
    "sg:postcode":"BH21 3LB",
    "sg:province":"Dorset",
    "sg:tags":[
        "greengrocer"
    ],
    "wof:name":"Franbar",
    "wof:placetype":"venue"
},
  "geometry": {"coordinates":[-2.0221030712,50.7641830444],"type":"Point"}
}