{
  "type": "Feature",
  "properties": {
    "iso:country":"GB",
    "sg:address":"Unit C, Canal Street",
    "sg:city":"Burton-on-trent",
    "sg:classifiers":[
        {
            "category":"Food & Beverages",
            "subcategory":"Bakery",
            "type":"Retail Goods"
        }
    ],
    "sg:phone":"+44 1283 562090",
    "sg:postcode":"DE14 3TB",
    "sg:province":"Derbyshire",
    "sg:tags":[
        "confectionery"
    ],
    "wof:name":"Bates Home Bakery",
    "wof:placetype":"venue"
},
  "geometry": {"coordinates":[-1.6426,52.801102],"type":"Point"}
}