{
  "type": "Feature",
  "properties": {
    "iso:country":"GB",
    "sg:address":"Unit 25, Queens Market, Sussex Street",
    "sg:city":"Rhyl",
    "sg:classifiers":[
        {
            "category":"Shopping",
            "subcategory":"Pets & Pet Supplies",
            "type":"Retail Goods"
        }
    ],
    "sg:phone":"+44 1745 339332",
    "sg:postcode":"LL18 1SE",
    "sg:province":"Conwy",
    "wof:name":"Frank & Glens Pet Supplies",
    "wof:placetype":"venue"
},
  "geometry": {"coordinates":[-3.493139,53.321106],"type":"Point"}
}