{
  "type": "Feature",
  "properties": {
    "addr:full":"24 Brox Rd, Ottershaw Chertsey Surrey KT16 0HL",
    "addr:housenumber":"24",
    "addr:postcode":"kt16 0hl",
    "addr:street":"Brox Rd",
    "iso:country":"GB",
    "sg:address":"24 Brox Rd, Ottershaw",
    "sg:city":"Chertsey",
    "sg:classifiers":[
        {
            "category":"Real Estate",
            "subcategory":"Surveying",
            "type":"Services"
        }
    ],
    "sg:phone":"+44 1932 875050",
    "sg:postcode":"KT16 0HL",
    "sg:province":"Surrey",
    "sg:tags":[
        "surveyor",
        "quantity"
    ],
    "wof:name":"C G Salmon & Associates",
    "wof:placetype":"venue"
},
  "geometry": {"coordinates":[-0.5314459801,51.3651542664],"type":"Point"}
}