{
  "type": "Feature",
  "properties": {
    "addr:full":"Mitchell Park Farm, Northchapel Petworth West Sussex GU28 9LB",
    "addr:postcode":"gu28 9lb",
    "iso:country":"GB",
    "sg:address":"Mitchell Park Farm, Northchapel",
    "sg:city":"Petworth",
    "sg:classifiers":[
        {
            "category":"Farming",
            "subcategory":"Livestock Farm",
            "type":"Manufacturing & Wholesale Goods"
        }
    ],
    "sg:phone":"+44 1428 707240",
    "sg:postcode":"GU28 9LB",
    "sg:province":"West Sussex",
    "sg:tags":[
        "others"
    ],
    "wof:name":"E A Green",
    "wof:placetype":"venue"
},
  "geometry": {"coordinates":[-0.644059,51.055706],"type":"Point"}
}