{
  "type": "Feature",
  "properties": {
    "iso:country":"GB",
    "sg:address":"12 Kingsman Parade",
    "sg:city":"London",
    "sg:classifiers":[
        {
            "category":"Shopping",
            "subcategory":"Pharmacy",
            "type":"Retail Goods"
        }
    ],
    "sg:phone":"+44 20 8317 8720",
    "sg:postcode":"SE18 5QE",
    "sg:province":"Greater London",
    "sg:tags":[
        "pharmacist",
        "chemist"
    ],
    "wof:name":"N S Warwick",
    "wof:placetype":"venue"
},
  "geometry": {"coordinates":[0.057824,51.49073],"type":"Point"}
}