{
  "type": "Feature",
  "properties": {
    "iso:country":"GB",
    "sg:address":"50 Hope Street",
    "sg:city":"Wrexham",
    "sg:classifiers":[
        {
            "category":"Communications",
            "type":"Services"
        }
    ],
    "sg:phone":"+44 1978 314614",
    "sg:postcode":"LL11 1BE",
    "sg:province":"Wrexham",
    "sg:tags":[
        "telecommunication"
    ],
    "wof:name":"The Mobile Phone Store Ltd.",
    "wof:placetype":"venue"
},
  "geometry": {"coordinates":[-2.993509,53.045792],"type":"Point"}
}