{
  "type": "Feature",
  "properties": {
    "addr:full":"20 Mansionhouse Road Edinburgh City of Edinburgh EH9 1TZ",
    "addr:housenumber":"20",
    "addr:postcode":"eh9 1tz",
    "addr:street":"Mansionhouse Road",
    "iso:country":"GB",
    "sg:address":"20 Mansionhouse Road",
    "sg:city":"Edinburgh",
    "sg:classifiers":[
        {
            "category":"Wholesale",
            "subcategory":"Computers",
            "type":"Manufacturing & Wholesale Goods"
        },
        {
            "category":"Professional",
            "subcategory":"Computer Services",
            "type":"Services"
        }
    ],
    "sg:phone":"+44 131 226 4846",
    "sg:postcode":"EH9 1TZ",
    "sg:province":"City of Edinburgh",
    "sg:tags":[
        "supplier",
        "consumables",
        "system",
        "software"
    ],
    "wof:name":"DELPHI COMPUTER CONSULTANTS LTD",
    "wof:placetype":"venue"
},
  "geometry": {"coordinates":[-3.189023,55.935936],"type":"Point"}
}