{
  "type": "Feature",
  "properties": {
    "iso:country":"GB",
    "sg:address":"4a Wellesley Road",
    "sg:city":"Eastbourne",
    "sg:classifiers":[
        {
            "category":"Food & Beverages",
            "subcategory":"Supermarket",
            "type":"Retail Goods"
        }
    ],
    "sg:postcode":"BN21 3RJ",
    "sg:province":"East Sussex",
    "sg:tags":[
        "frozen"
    ],
    "wof:name":"Hempstead Fine Foods",
    "wof:placetype":"venue"
},
  "geometry": {"coordinates":[0.2885810137,50.7705497742],"type":"Point"}
}