{
  "type": "Feature",
  "properties": {
    "addr:full":"14 Hawthorne Gro, Heworth York North Yorkshire YO31 7XZ",
    "addr:housenumber":"14",
    "addr:postcode":"yo31 7xz",
    "addr:street":"Hawthorne Gro",
    "iso:country":"GB",
    "sg:address":"14 Hawthorne Gro, Heworth",
    "sg:city":"York",
    "sg:classifiers":[
        {
            "category":"Real Estate",
            "subcategory":"Architect",
            "type":"Services"
        }
    ],
    "sg:phone":"+44 1904 430333",
    "sg:postcode":"YO31 7XZ",
    "sg:province":"North Yorkshire",
    "wof:name":"Ward Ruddick & Haldane",
    "wof:placetype":"venue"
},
  "geometry": {"coordinates":[-1.068194,53.964214],"type":"Point"}
}