{
  "type": "Feature",
  "properties": {
    "addr:full":"Red Bank Farm, The Shore, Bolton Le Sands Carnforth Cumbria LA5 8JR",
    "addr:postcode":"la5 8jr",
    "addr:street":"The",
    "iso:country":"GB",
    "sg:address":"Red Bank Farm, The Shore, Bolton Le Sands",
    "sg:city":"Carnforth",
    "sg:classifiers":[
        {
            "category":"Farming",
            "subcategory":"Livestock Farm",
            "type":"Manufacturing & Wholesale Goods"
        }
    ],
    "sg:phone":"+44 1524 823196",
    "sg:postcode":"LA5 8JR",
    "sg:province":"Cumbria",
    "sg:tags":[
        "others"
    ],
    "wof:name":"M Archer & Son",
    "wof:placetype":"venue"
},
  "geometry": {"coordinates":[-2.7976989746,54.099861145],"type":"Point"}
}