{
  "type": "Feature",
  "properties": {
    "addr:full":"Wembley Commercial, East Lane Wembley Greater London HA9 7UR",
    "addr:postcode":"ha9 7ur",
    "addr:street":"East Lane",
    "iso:country":"GB",
    "sg:address":"Wembley Commercial, East Lane",
    "sg:city":"Wembley",
    "sg:classifiers":[
        {
            "category":"Professional",
            "subcategory":"Printing & Photocopies",
            "type":"Services"
        }
    ],
    "sg:phone":"+44 20 8904 7110",
    "sg:postcode":"HA9 7UR",
    "sg:province":"Greater London",
    "sg:tags":[
        "printer"
    ],
    "wof:name":"J J Proofing",
    "wof:placetype":"venue"
},
  "geometry": {"coordinates":[-0.295539,51.552963],"type":"Point"}
}