{
  "type": "Feature",
  "properties": {
    "iso:country":"GB",
    "sg:address":"326 York Rd",
    "sg:city":"Leeds",
    "sg:classifiers":[
        {
            "category":"Military Area",
            "subcategory":"Air Force Base",
            "type":"Public Place"
        }
    ],
    "sg:phone":"+44 113 294 2947",
    "sg:postcode":"LS9 9DN",
    "sg:province":"West Yorkshire",
    "sg:tags":[
        "taxi",
        "hire",
        "private"
    ],
    "wof:name":"A & J Contract Hire",
    "wof:placetype":"venue"
},
  "geometry": {"coordinates":[-1.505357,53.799759],"type":"Point"}
}