{
  "type": "Feature",
  "properties": {
    "iso:country":"GB",
    "sg:address":"43 Landcross Drive",
    "sg:city":"Northampton",
    "sg:classifiers":[
        {
            "category":"Shopping",
            "subcategory":"Clothing, Apparel, & Fashions",
            "type":"Retail Goods"
        }
    ],
    "sg:phone":"+44 1604 624882",
    "sg:postcode":"NN3 3LN",
    "sg:province":"Northamptonshire",
    "sg:tags":[
        "shop"
    ],
    "wof:name":"The Wardrobe",
    "wof:placetype":"venue"
},
  "geometry": {"coordinates":[-0.856545,52.242374],"type":"Point"}
}