{
  "type": "Feature",
  "properties": {
    "addr:full":"Ross Ho, Wickham Rd Grimsby Lincolnshire DN31 3SW",
    "addr:postcode":"dn31 3sw",
    "addr:street":"Wickham Rd",
    "iso:country":"GB",
    "sg:address":"Ross Ho, Wickham Rd",
    "sg:city":"Grimsby",
    "sg:classifiers":[
        {
            "category":"Food & Beverages",
            "subcategory":"Supermarket",
            "type":"Retail Goods"
        }
    ],
    "sg:phone":"+44 1472 359311",
    "sg:postcode":"DN31 3SW",
    "sg:province":"Lincolnshire",
    "sg:tags":[
        "frozen"
    ],
    "wof:name":"Youngs",
    "wof:placetype":"venue"
},
  "geometry": {"coordinates":[-0.0592890009,53.5756835938],"type":"Point"}
}