{
  "type": "Feature",
  "properties": {
    "addr:full":"26 Richmond Road Barnet Hertfordshire EN5 1SB",
    "addr:housenumber":"26",
    "addr:postcode":"en5 1sb",
    "addr:street":"Richmond Road",
    "iso:country":"GB",
    "sg:address":"26 Richmond Road",
    "sg:city":"Barnet",
    "sg:classifiers":[
        {
            "category":"Organizations",
            "subcategory":"Membership Organization",
            "type":"Services"
        }
    ],
    "sg:phone":"+44 20 8449 6427",
    "sg:postcode":"EN5 1SB",
    "sg:province":"Hertfordshire",
    "sg:tags":[
        "club"
    ],
    "wof:name":"Lyonsdown Club",
    "wof:placetype":"venue"
},
  "geometry": {"coordinates":[-0.177092,51.646778],"type":"Point"}
}