{
  "type": "Feature",
  "properties": {
    "addr:full":"27 High Street Westbury Wiltshire BA13 3BN",
    "addr:housenumber":"27",
    "addr:postcode":"ba13 3bn",
    "addr:street":"High Street",
    "iso:country":"GB",
    "sg:address":"27 High Street",
    "sg:city":"Westbury",
    "sg:classifiers":[
        {
            "category":"Shopping",
            "subcategory":"Department Store",
            "type":"Retail Goods"
        }
    ],
    "sg:postcode":"BA13 3BN",
    "sg:province":"Wiltshire",
    "wof:name":"Diane W Levy",
    "wof:placetype":"venue"
},
  "geometry": {"coordinates":[-2.1849548817,51.260471344],"type":"Point"}
}