{
  "type": "Feature",
  "properties": {
    "addr:full":"36 Ferry Rd Edinburgh City of Edinburgh EH6 4AE",
    "addr:housenumber":"36",
    "addr:postcode":"eh6 4ae",
    "addr:street":"Ferry Rd",
    "iso:country":"GB",
    "sg:address":"36 Ferry Rd",
    "sg:city":"Edinburgh",
    "sg:classifiers":[
        {
            "category":"Shopping",
            "subcategory":"Pharmacy",
            "type":"Retail Goods"
        }
    ],
    "sg:postcode":"EH6 4AE",
    "sg:province":"City of Edinburgh",
    "sg:tags":[
        "store",
        "drug"
    ],
    "wof:name":"Clark,I A,",
    "wof:placetype":"venue"
},
  "geometry": {"coordinates":[-3.1805241108,55.9752731323],"type":"Point"}
}