{
  "type": "Feature",
  "properties": {
    "addr:full":"The Old School House, Fisherhead, Robin Hoods Bay Whitby North Yorkshire YO22 4ST",
    "addr:postcode":"yo22 4st",
    "addr:street":"Fisherhead;Hoods Bay",
    "iso:country":"GB",
    "sg:address":"The Old School House, Fisherhead, Robin Hoods Bay",
    "sg:city":"Whitby",
    "sg:classifiers":[
        {
            "category":"Education",
            "subcategory":"School",
            "type":"Public Place"
        }
    ],
    "sg:phone":"+44 1947 880723",
    "sg:postcode":"YO22 4ST",
    "sg:province":"North Yorkshire",
    "sg:tags":[
        "independent",
        "preparatory"
    ],
    "wof:name":"Old School House",
    "wof:placetype":"venue"
},
  "geometry": {"coordinates":[-0.5842760205,54.4242858887],"type":"Point"}
}