{
  "type": "Feature",
  "properties": {
    "addr:full":"6 Grove Place Bedford Bedfordshire MK40 3JJ",
    "addr:housenumber":"6",
    "addr:postcode":"mk40 3jj",
    "addr:street":"Grove Place",
    "iso:country":"GB",
    "sg:address":"6 Grove Place",
    "sg:city":"Bedford",
    "sg:classifiers":[
        {
            "category":"Professional",
            "subcategory":"Secretarial Services",
            "type":"Services"
        }
    ],
    "sg:postcode":"MK40 3JJ",
    "sg:province":"Bedfordshire",
    "wof:name":"Accurate Typing Service",
    "wof:placetype":"venue"
},
  "geometry": {"coordinates":[-0.4621730149,52.1383361816],"type":"Point"}
}