{
  "type": "Feature",
  "properties": {
    "addr:full":"Unit 45 Bank Quay Trading Estate, Slutchers Lane Warrington Cheshire WA1 1PJ",
    "addr:housenumber":"unit 45",
    "addr:postcode":"wa1 1pj",
    "addr:street":"Bank Quay Trading Estate Slutchers Lane",
    "iso:country":"GB",
    "sg:address":"Unit 45 Bank Quay Trading Estate, Slutchers Lane",
    "sg:city":"Warrington",
    "sg:classifiers":[
        {
            "category":"Professional",
            "subcategory":"Art Services",
            "type":"Services"
        }
    ],
    "sg:phone":"+44 1925 575888",
    "sg:postcode":"WA1 1PJ",
    "sg:province":"Cheshire",
    "sg:tags":[
        "photographer"
    ],
    "wof:name":"Sherratt's Photographic Studio's",
    "wof:placetype":"venue"
},
  "geometry": {"coordinates":[-2.60435,53.383549],"type":"Point"}
}