{
  "type": "Feature",
  "properties": {
    "iso:country":"GB",
    "sg:address":"Lime Avenue, Lillington",
    "sg:city":"Leamington Spa",
    "sg:classifiers":[
        {
            "category":"Arena",
            "subcategory":"Sports Club",
            "type":"Entertainment"
        }
    ],
    "sg:phone":"+44 1926 423696",
    "sg:postcode":"CV32 7DB",
    "sg:province":"Warwickshire",
    "wof:name":"Lillington Bowling Club",
    "wof:placetype":"venue"
},
  "geometry": {"coordinates":[-1.5272730589,52.3087425232],"type":"Point"}
}