{
  "type": "Feature",
  "properties": {
    "iso:country":"GB",
    "sg:address":"Sheerlands Rd, Finchampstead",
    "sg:city":"Wokingham",
    "sg:classifiers":[
        {
            "category":"Professional",
            "subcategory":"Printing & Photocopies",
            "type":"Services"
        }
    ],
    "sg:phone":"+44 118 973 6768",
    "sg:postcode":"RG40 4QY",
    "sg:province":"Berkshire",
    "sg:tags":[
        "plate",
        "printer",
        "lithographic",
        "maker"
    ],
    "wof:name":"Ospec Printing Ltd",
    "wof:placetype":"venue"
},
  "geometry": {"coordinates":[-0.9019910097,51.3761520386],"type":"Point"}
}