{
  "type": "Feature",
  "properties": {
    "addr:full":"77 Cooden Sea Road Bexhill-on-sea East Sussex TN39 4SL",
    "addr:housenumber":"77",
    "addr:postcode":"tn39 4sl",
    "addr:street":"Cooden Sea Road",
    "iso:country":"GB",
    "sg:address":"77 Cooden Sea Road",
    "sg:city":"Bexhill-on-sea",
    "sg:classifiers":[
        {
            "category":"Shopping",
            "subcategory":"Pharmacy",
            "type":"Retail Goods"
        }
    ],
    "sg:phone":"+44 1424 843080",
    "sg:postcode":"TN39 4SL",
    "sg:province":"East Sussex",
    "sg:tags":[
        "pharmacist",
        "dispensing",
        "chemist"
    ],
    "wof:name":"Little Common Pharmacy",
    "wof:placetype":"venue"
},
  "geometry": {"coordinates":[0.4338960052,50.8429718018],"type":"Point"}
}