{
  "type": "Feature",
  "properties": {
    "addr:full":"72 Fielding Rd, Chiswick London Greater London W4 1DB",
    "addr:housenumber":"72",
    "addr:postcode":"w4 1db",
    "addr:street":"Fielding Rd",
    "iso:country":"GB",
    "sg:address":"72 Fielding Rd, Chiswick",
    "sg:city":"London",
    "sg:classifiers":[
        {
            "category":"Real Estate",
            "subcategory":"Real Estate Agent",
            "type":"Services"
        }
    ],
    "sg:postcode":"W4 1DB",
    "sg:province":"Greater London",
    "wof:name":"Devcor Properties Ltd",
    "wof:placetype":"venue"
},
  "geometry": {"coordinates":[-0.257059,51.500534],"type":"Point"}
}