{
  "type": "Feature",
  "properties": {
    "iso:country":"GB",
    "sg:address":"20 Castle Hill Road",
    "sg:city":"Bury",
    "sg:classifiers":[
        {
            "category":"Retail",
            "subcategory":"Driving School",
            "type":"Services"
        }
    ],
    "sg:phone":"+44 161 761 5775",
    "sg:postcode":"BL9 7RN",
    "sg:province":"Lancashire",
    "wof:name":"Swift Driving School",
    "wof:placetype":"venue"
},
  "geometry": {"coordinates":[-2.2612099648,53.6020584106],"type":"Point"}
}