{
  "type": "Feature",
  "properties": {
    "addr:full":"Downacre, Doggetts Wood Lane Chalfont St Giles Buckinghamshire HP8 4TH",
    "addr:postcode":"hp8 4th",
    "addr:street":"Wood Lane",
    "iso:country":"GB",
    "sg:address":"Downacre, Doggetts Wood Lane",
    "sg:city":"Chalfont St Giles",
    "sg:classifiers":[
        {
            "category":"Health Services",
            "subcategory":"Clinic",
            "type":"Services"
        }
    ],
    "sg:postcode":"HP8 4TH",
    "sg:province":"Buckinghamshire",
    "sg:tags":[
        "aromatherapy"
    ],
    "wof:name":"Jacqueline Holland",
    "wof:placetype":"venue"
},
  "geometry": {"coordinates":[-0.572024,51.658653],"type":"Point"}
}