{
  "type": "Feature",
  "properties": {
    "iso:country":"GB",
    "sg:address":"45-51 Shakespeare Street",
    "sg:city":"Southport",
    "sg:classifiers":[
        {
            "category":"Home & Garden",
            "subcategory":"Carpets & Floor Coverings",
            "type":"Retail Goods"
        }
    ],
    "sg:phone":"+44 1704 549996",
    "sg:postcode":"PR8 5AB",
    "sg:province":"Lancashire",
    "sg:tags":[
        "carpets",
        "rug",
        "matting"
    ],
    "wof:name":"Erazma Ltd.",
    "wof:placetype":"venue"
},
  "geometry": {"coordinates":[-3.003376,53.640083],"type":"Point"}
}