{
  "type": "Feature",
  "properties": {
    "iso:country":"GB",
    "sg:address":"Durkan House, North Terrace, Seghill",
    "sg:city":"Morpeth",
    "sg:classifiers":[
        {
            "category":"Utilities",
            "subcategory":"Telephone",
            "type":"Services"
        }
    ],
    "sg:phone":"+44 191 237 7977",
    "sg:postcode":"NE23 7EB",
    "sg:province":"Northumberland",
    "sg:tags":[
        "telecommunication"
    ],
    "wof:name":"Gibson Communications Ltd.",
    "wof:placetype":"venue"
},
  "geometry": {"coordinates":[-1.5499,55.0634],"type":"Point"}
}