{
  "type": "Feature",
  "properties": {
    "iso:country":"GB",
    "sg:address":"651 Manchester Road, Mills Bridge",
    "sg:city":"Huddersfield",
    "sg:classifiers":[
        {
            "category":"Manufacturing",
            "subcategory":"Wood Products",
            "type":"Manufacturing & Wholesale Goods"
        }
    ],
    "sg:phone":"+44 1484 654059",
    "sg:postcode":"HD4 5SF",
    "sg:province":"West Yorkshire",
    "sg:tags":[
        "maker",
        "cabinet"
    ],
    "wof:name":"Pogson Joinery",
    "wof:placetype":"venue"
},
  "geometry": {"coordinates":[-1.816586,53.63792],"type":"Point"}
}