{
  "type": "Feature",
  "properties": {
    "iso:country":"GB",
    "sg:address":"Unit 7 Ashton Industrial Units, Ashton Road, Marsh Barton Trading Estate",
    "sg:city":"Exeter",
    "sg:classifiers":[
        {
            "category":"Building & Trades",
            "subcategory":"Construction",
            "type":"Services"
        }
    ],
    "sg:phone":"+44 1392 422495",
    "sg:postcode":"EX2 8LN",
    "sg:province":"Devon",
    "sg:tags":[
        "window",
        "replacement"
    ],
    "wof:name":"Doors & Windows Exeter",
    "wof:placetype":"venue"
},
  "geometry": {"coordinates":[-3.5303490162,50.7085609436],"type":"Point"}
}