{
  "type": "Feature",
  "properties": {
    "addr:full":"Old Foundry, Stanghow Rd Saltburn By The Sea North Yorkshire TS12 3ED",
    "addr:postcode":"ts12 3ed",
    "addr:street":"Old;Stanghow Rd",
    "iso:country":"GB",
    "sg:address":"Old Foundry, Stanghow Rd",
    "sg:city":"Saltburn By The Sea",
    "sg:classifiers":[
        {
            "category":"Manufacturing",
            "subcategory":"Metals",
            "type":"Manufacturing & Wholesale Goods"
        }
    ],
    "sg:phone":"+44 1287 653636",
    "sg:postcode":"TS12 3ED",
    "sg:province":"North Yorkshire",
    "sg:tags":[
        "work",
        "sheet"
    ],
    "wof:name":"Cleveland Metalworkers",
    "wof:placetype":"venue"
},
  "geometry": {"coordinates":[-0.9583839774,54.5314941406],"type":"Point"}
}