{
  "type": "Feature",
  "properties": {
    "addr:full":"3 Seamer Road, Kimberley Nottingham Derbyshire NG16 2TF",
    "addr:housenumber":"3",
    "addr:postcode":"ng16 2tf",
    "addr:street":"Seamer Road",
    "iso:country":"GB",
    "sg:address":"3 Seamer Road, Kimberley",
    "sg:city":"Nottingham",
    "sg:classifiers":[
        {
            "category":"Education",
            "subcategory":"Music School",
            "type":"Public Place"
        }
    ],
    "sg:phone":"+44 115 945 8113",
    "sg:postcode":"NG16 2TF",
    "sg:province":"Derbyshire",
    "sg:tags":[
        "teacher"
    ],
    "wof:name":"Michelle Beeton",
    "wof:placetype":"venue"
},
  "geometry": {"coordinates":[-1.259197,53.003456],"type":"Point"}
}