{
  "type": "Feature",
  "properties": {
    "iso:country":"GB",
    "sg:address":"30 Liverpool Road, Penwortham",
    "sg:city":"Preston",
    "sg:classifiers":[
        {
            "category":"Shopping",
            "subcategory":"Optician",
            "type":"Retail Goods"
        }
    ],
    "sg:phone":"+44 1772 747004",
    "sg:postcode":"PR1 0DQ",
    "sg:province":"Lancashire",
    "wof:name":"Peter Booth Opticians",
    "wof:placetype":"venue"
},
  "geometry": {"coordinates":[-2.7305800915,53.7499961853],"type":"Point"}
}