{
  "type": "Feature",
  "properties": {
    "addr:full":"Warcop Tower, Warcop Appleby-in-westmorland Cumbria CA16 6PL",
    "addr:housenumber":"warcop",
    "addr:postcode":"ca16 6pl",
    "iso:country":"GB",
    "sg:address":"Warcop Tower, Warcop",
    "sg:city":"Appleby-in-westmorland",
    "sg:classifiers":[
        {
            "category":"Home & Garden",
            "subcategory":"Garden Supply",
            "type":"Retail Goods"
        },
        {
            "category":"Farming",
            "subcategory":"Livestock Farm",
            "type":"Manufacturing & Wholesale Goods"
        }
    ],
    "sg:phone":"+44 17683 41386",
    "sg:postcode":"CA16 6PL",
    "sg:province":"Cumbria",
    "sg:tags":[
        "bulb",
        "grower"
    ],
    "wof:name":"J W & L Harrison",
    "wof:placetype":"venue"
},
  "geometry": {"coordinates":[-2.4874300957,54.5773086548],"type":"Point"}
}