{
  "type": "Feature",
  "properties": {
    "addr:full":"Ancaster Way Cambridge Cambridgeshire CB1 3TT",
    "addr:postcode":"cb1 3tt",
    "addr:street":"Ancaster Way",
    "iso:country":"GB",
    "sg:address":"Ancaster Way",
    "sg:city":"Cambridge",
    "sg:classifiers":[
        {
            "category":"Place Of Worship",
            "type":"Public Place"
        }
    ],
    "sg:phone":"+44 1223 245838",
    "sg:postcode":"CB1 3TT",
    "sg:province":"Cambridgeshire",
    "wof:name":"St Thomas's Hall",
    "wof:placetype":"venue"
},
  "geometry": {"coordinates":[0.1566590071,52.1919441223],"type":"Point"}
}