{
  "type": "Feature",
  "properties": {
    "iso:country":"GB",
    "sg:address":"8 Courthope Road",
    "sg:city":"Greenford",
    "sg:classifiers":[
        {
            "category":"Education",
            "subcategory":"Special Training",
            "type":"Public Place"
        }
    ],
    "sg:postcode":"UB6 8PZ",
    "sg:province":"Greater London",
    "sg:tags":[
        "product",
        "centre"
    ],
    "wof:name":"Avrora It Training",
    "wof:placetype":"venue"
},
  "geometry": {"coordinates":[-0.34806,51.538269],"type":"Point"}
}