{
  "type": "Feature",
  "properties": {
    "addr:full":"3 Gibbon Lane, North Hill Plymouth Devon PL4 8BS",
    "addr:housenumber":"3",
    "addr:postcode":"pl4 8bs",
    "addr:street":"Gibbon Lane",
    "iso:country":"GB",
    "sg:address":"3 Gibbon Lane, North Hill",
    "sg:city":"Plymouth",
    "sg:classifiers":[
        {
            "category":"Building & Trades",
            "subcategory":"Construction",
            "type":"Services"
        }
    ],
    "sg:phone":"+44 1752 220909",
    "sg:postcode":"PL4 8BS",
    "sg:province":"Devon",
    "sg:tags":[
        "flooring"
    ],
    "wof:name":"FTI RENZI",
    "wof:placetype":"venue"
},
  "geometry": {"coordinates":[-4.135099,50.374722],"type":"Point"}
}