{
  "type": "Feature",
  "properties": {
    "addr:full":"22 The Stirrup, Cashesgreen Stroud Gloucestershire GL5 4SG",
    "addr:housenumber":"22",
    "addr:postcode":"gl5 4sg",
    "addr:street":"The Stirrup Cashesgreen",
    "iso:country":"GB",
    "sg:address":"22 The Stirrup, Cashesgreen",
    "sg:city":"Stroud",
    "sg:classifiers":[
        {
            "category":"Building & Trades",
            "subcategory":"Construction",
            "type":"Services"
        }
    ],
    "sg:postcode":"GL5 4SG",
    "sg:province":"Gloucestershire",
    "sg:tags":[
        "builder"
    ],
    "wof:name":"A G S Building Services",
    "wof:placetype":"venue"
},
  "geometry": {"coordinates":[-2.251297,51.746731],"type":"Point"}
}