{
  "type": "Feature",
  "properties": {
    "addr:full":"Queen Ave Macclesfield Cheshire SK10 2BN",
    "addr:postcode":"sk10 2bn",
    "addr:street":"Queen Ave",
    "iso:country":"GB",
    "sg:address":"Queen Ave",
    "sg:city":"Macclesfield",
    "sg:classifiers":[
        {
            "category":"Manufacturing",
            "subcategory":"Rubber & Plastics",
            "type":"Manufacturing & Wholesale Goods"
        }
    ],
    "sg:postcode":"SK10 2BN",
    "sg:province":"Cheshire",
    "sg:tags":[
        "product"
    ],
    "wof:name":"Charter Way Mouldings Ltd",
    "wof:placetype":"venue"
},
  "geometry": {"coordinates":[-2.117979,53.269821],"type":"Point"}
}