{
  "type": "Feature",
  "properties": {
    "addr:full":"16-18 Mayall Street East Oldham Lancashire OL4 3EN",
    "addr:housenumber":"16-18",
    "addr:postcode":"ol4 3en",
    "addr:street":"Mayall Street East",
    "iso:country":"GB",
    "sg:address":"16-18 Mayall Street East",
    "sg:city":"Oldham",
    "sg:classifiers":[
        {
            "category":"Social Services",
            "type":"Services"
        },
        {
            "category":"Travel",
            "subcategory":"Hostel",
            "type":"Entertainment"
        },
        {
            "category":"Government",
            "subcategory":"Office",
            "type":"Public Place"
        }
    ],
    "sg:phone":"+44 161 624 1569",
    "sg:postcode":"OL4 3EN",
    "sg:province":"Lancashire",
    "sg:tags":[
        "local",
        "ds"
    ],
    "wof:name":"Mayall Street Hostel",
    "wof:placetype":"venue"
},
  "geometry": {"coordinates":[-2.085191,53.544678],"type":"Point"}
}