{
  "type": "Feature",
  "properties": {
    "addr:full":"Lonfield Poultry Farm, Fen Rd, Stickford Boston Lincolnshire PE22 8HD",
    "addr:postcode":"pe22 8hd",
    "addr:street":"Fen Rd",
    "iso:country":"GB",
    "sg:address":"Lonfield Poultry Farm, Fen Rd, Stickford",
    "sg:city":"Boston",
    "sg:classifiers":[
        {
            "category":"Farming",
            "subcategory":"Poultry Farm",
            "type":"Manufacturing & Wholesale Goods"
        }
    ],
    "sg:postcode":"PE22 8HD",
    "sg:province":"Lincolnshire",
    "sg:tags":[
        "game"
    ],
    "wof:name":"Panton Bros",
    "wof:placetype":"venue"
},
  "geometry": {"coordinates":[0.0264,53.121906],"type":"Point"}
}