{
  "type": "Feature",
  "properties": {
    "addr:full":"Upper Cyrus St Manchester Greater Manchester M40 7FD",
    "addr:postcode":"m40 7fd",
    "addr:street":"Upper Cyrus St",
    "iso:country":"GB",
    "sg:address":"Upper Cyrus St",
    "sg:city":"Manchester",
    "sg:classifiers":[
        {
            "category":"Shopping",
            "type":"Retail Goods"
        }
    ],
    "sg:phone":"+44 161 273 8502",
    "sg:postcode":"M40 7FD",
    "sg:province":"Greater Manchester",
    "sg:tags":[
        "part",
        "accessory"
    ],
    "wof:name":"Jamie Rowlands",
    "wof:placetype":"venue"
},
  "geometry": {"coordinates":[-2.210119,53.485214],"type":"Point"}
}