{
  "type": "Feature",
  "properties": {
    "addr:full":"10-12 Arthur St Newton Stewart Dumfries and Galloway DG8 6DE",
    "addr:housenumber":"10-12",
    "addr:postcode":"dg8 6de",
    "addr:street":"Arthur St",
    "iso:country":"GB",
    "sg:address":"10-12 Arthur St",
    "sg:city":"Newton Stewart",
    "sg:classifiers":[
        {
            "category":"Government",
            "subcategory":"Office",
            "type":"Public Place"
        }
    ],
    "sg:postcode":"DG8 6DE",
    "sg:province":"Dumfries and Galloway",
    "sg:tags":[
        "development",
        "agency"
    ],
    "wof:name":"Groundbase Ltd",
    "wof:placetype":"venue"
},
  "geometry": {"coordinates":[-4.483579,54.96003],"type":"Point"}
}