{
  "type": "Feature",
  "properties": {
    "addr:full":"471 Preston Old Rd Blackburn Lancashire BB2 5ND",
    "addr:housenumber":"471",
    "addr:postcode":"bb2 5nd",
    "addr:street":"Preston Old Rd",
    "iso:country":"GB",
    "sg:address":"471 Preston Old Rd",
    "sg:city":"Blackburn",
    "sg:classifiers":[
        {
            "category":"Building & Trades",
            "subcategory":"Construction",
            "type":"Services"
        }
    ],
    "sg:postcode":"BB2 5ND",
    "sg:province":"Lancashire",
    "sg:tags":[
        "builder"
    ],
    "wof:name":"Clovelly Building Services",
    "wof:placetype":"venue"
},
  "geometry": {"coordinates":[-2.525112,53.730137],"type":"Point"}
}