{
  "type": "Feature",
  "properties": {
    "iso:country":"GB",
    "sg:address":"Bank House, 1 High Street",
    "sg:city":"Stroud",
    "sg:classifiers":[
        {
            "category":"Shopping",
            "subcategory":"Department Store",
            "type":"Retail Goods"
        }
    ],
    "sg:postcode":"GL5 1AU",
    "sg:province":"Gloucestershire",
    "wof:name":"Look Around It's All A Pound",
    "wof:placetype":"venue"
},
  "geometry": {"coordinates":[-2.217254,51.745872],"type":"Point"}
}