{
  "type": "Feature",
  "properties": {
    "addr:full":"235 Duckworth St Darwen Lancashire BB3 1AU",
    "addr:housenumber":"235",
    "addr:postcode":"bb3 1au",
    "addr:street":"Duckworth St",
    "iso:country":"GB",
    "sg:address":"235 Duckworth St",
    "sg:city":"Darwen",
    "sg:classifiers":[
        {
            "category":"Food & Beverages",
            "subcategory":"Bakery",
            "type":"Retail Goods"
        }
    ],
    "sg:postcode":"BB3 1AU",
    "sg:province":"Lancashire",
    "sg:tags":[
        "baker"
    ],
    "wof:name":"Cheadle,C,& Sons",
    "wof:placetype":"venue"
},
  "geometry": {"coordinates":[-2.4687149525,53.6968269348],"type":"Point"}
}