{
  "type": "Feature",
  "properties": {
    "addr:full":"9 Stafford Street Market Drayton Shropshire TF9 1HX",
    "addr:housenumber":"9",
    "addr:postcode":"tf9 1hx",
    "addr:street":"Stafford Street",
    "iso:country":"GB",
    "sg:address":"9 Stafford Street",
    "sg:city":"Market Drayton",
    "sg:classifiers":[
        {
            "category":"Fast Food",
            "type":"Food & Drink"
        },
        {
            "category":"Food & Beverages",
            "subcategory":"Meat & Fish",
            "type":"Retail Goods"
        }
    ],
    "sg:phone":"+44 1630 652708",
    "sg:postcode":"TF9 1HX",
    "sg:province":"Shropshire",
    "sg:tags":[
        "shop",
        "chip"
    ],
    "wof:name":"Tudor Cafe",
    "wof:placetype":"venue"
},
  "geometry": {"coordinates":[-2.483556,52.904732],"type":"Point"}
}