{
  "type": "Feature",
  "properties": {
    "iso:country":"GB",
    "sg:address":"282 Skipton Road",
    "sg:city":"Harrogate",
    "sg:classifiers":[
        {
            "category":"Farming",
            "subcategory":"Nursery",
            "type":"Manufacturing & Wholesale Goods"
        }
    ],
    "sg:postcode":"HG1 3HE",
    "sg:province":"North Yorkshire",
    "sg:tags":[
        "creche"
    ],
    "wof:name":"Rainbow Nursery",
    "wof:placetype":"venue"
},
  "geometry": {"coordinates":[-1.5470149517,54.0068740845],"type":"Point"}
}