{
  "type": "Feature",
  "properties": {
    "addr:full":"First Floor Brighton Ho, 23-25 High St Epsom Surrey KT17 1SB",
    "addr:housenumber":"23-25",
    "addr:postcode":"kt17 1sb",
    "addr:street":"High St",
    "iso:country":"GB",
    "sg:address":"First Floor Brighton Ho, 23-25 High St",
    "sg:city":"Epsom",
    "sg:classifiers":[
        {
            "category":"Professional",
            "subcategory":"Research",
            "type":"Services"
        }
    ],
    "sg:phone":"+44 20 8224 4809",
    "sg:postcode":"KT17 1SB",
    "sg:province":"Surrey",
    "sg:tags":[
        "market"
    ],
    "wof:name":"International Partnership The",
    "wof:placetype":"venue"
},
  "geometry": {"coordinates":[-0.24913,51.349461],"type":"Point"}
}