{
  "type": "Feature",
  "properties": {
    "addr:full":"35 Castle St Guildford Surrey GU1 3UQ",
    "addr:housenumber":"35",
    "addr:postcode":"gu1 3uq",
    "addr:street":"Castle St",
    "iso:country":"GB",
    "sg:address":"35 Castle St",
    "sg:city":"Guildford",
    "sg:classifiers":[
        {
            "category":"Restaurant",
            "type":"Food & Drink"
        }
    ],
    "sg:phone":"+44 1483 534896",
    "sg:postcode":"GU1 3UQ",
    "sg:province":"Surrey",
    "wof:name":"Cafe De Paris",
    "wof:placetype":"venue"
},
  "geometry": {"coordinates":[-0.5733879805,51.2345161438],"type":"Point"}
}