{
  "type": "Feature",
  "properties": {
    "addr:full":"17 The Birtles, Wythenshawe Manchester Greater Manchester M22 5RF",
    "addr:housenumber":"17",
    "addr:postcode":"m22 5rf",
    "addr:street":"The Birtles",
    "iso:country":"GB",
    "sg:address":"17 The Birtles, Wythenshawe",
    "sg:city":"Manchester",
    "sg:classifiers":[
        {
            "category":"Shopping",
            "subcategory":"Optician",
            "type":"Retail Goods"
        }
    ],
    "sg:phone":"+44 161 437 7396",
    "sg:postcode":"M22 5RF",
    "sg:province":"Greater Manchester",
    "wof:name":"Look Right (Distributors) Ltd.",
    "wof:placetype":"venue"
},
  "geometry": {"coordinates":[-2.26189,53.379978],"type":"Point"}
}