{
  "type": "Feature",
  "properties": {
    "iso:country":"GB",
    "sg:address":"1 Hamilton Mews",
    "sg:city":"London",
    "sg:classifiers":[
        {
            "category":"Professional",
            "type":"Services"
        }
    ],
    "sg:phone":"+44 20 7489 2016",
    "sg:postcode":"W1V 9FF",
    "sg:province":"Greater London",
    "sg:tags":[
        "repair",
        "tech",
        "maintenance"
    ],
    "wof:name":"Internet Com Ltd.",
    "wof:placetype":"venue"
},
  "geometry": {"coordinates":[-0.150129,51.503777],"type":"Point"}
}