{
  "type": "Feature",
  "properties": {
    "addr:full":"97 Ipswich Street Stowmarket Suffolk IP14 1BB",
    "addr:housenumber":"97",
    "addr:postcode":"ip14 1bb",
    "addr:street":"Ipswich Street",
    "iso:country":"GB",
    "sg:address":"97 Ipswich Street",
    "sg:city":"Stowmarket",
    "sg:classifiers":[
        {
            "category":"Fast Food",
            "type":"Food & Drink"
        }
    ],
    "sg:phone":"+44 1449 615448",
    "sg:postcode":"IP14 1BB",
    "sg:province":"Suffolk",
    "sg:tags":[
        "away",
        "take"
    ],
    "wof:name":"Bamboo House",
    "wof:placetype":"venue"
},
  "geometry": {"coordinates":[0.999028,52.18565],"type":"Point"}
}