{
  "type": "Feature",
  "properties": {
    "addr:full":"F A C S House, Holmesdale Road, North Holmwood Dorking Surrey RH5 4HS",
    "addr:postcode":"rh5 4hs",
    "addr:street":"F;C;Holmesdale Road North",
    "iso:country":"GB",
    "sg:address":"F A C S House, Holmesdale Road, North Holmwood",
    "sg:city":"Dorking",
    "sg:classifiers":[
        {
            "category":"Freight",
            "type":"Transportation"
        },
        {
            "category":"Retail",
            "subcategory":"Storage",
            "type":"Services"
        }
    ],
    "sg:phone":"+44 1306 880124",
    "sg:postcode":"RH5 4HS",
    "sg:province":"Surrey",
    "sg:tags":[
        "haulage",
        "household",
        "road",
        "transport",
        "removal"
    ],
    "wof:name":"City Space Storage",
    "wof:placetype":"venue"
},
  "geometry": {"coordinates":[-0.318534,51.180553],"type":"Point"}
}