{
  "type": "Feature",
  "properties": {
    "iso:country":"GB",
    "sg:address":"Unit 15 Argyle Street",
    "sg:city":"Hull",
    "sg:classifiers":[
        {
            "category":"Professional",
            "subcategory":"Computer Services",
            "type":"Services"
        }
    ],
    "sg:phone":"+44 1482 323891",
    "sg:postcode":"HU3 1HD",
    "sg:province":"East Riding of Yorkshire",
    "sg:tags":[
        "system",
        "software"
    ],
    "wof:name":"Humber Computer Systems",
    "wof:placetype":"venue"
},
  "geometry": {"coordinates":[-0.359279,53.746845],"type":"Point"}
}