{
  "type": "Feature",
  "properties": {
    "iso:country":"GB",
    "sg:address":"Power Ho, P O Box 15",
    "sg:city":"Romford",
    "sg:classifiers":[
        {
            "category":"Organizations",
            "subcategory":"Membership Organization",
            "type":"Services"
        }
    ],
    "sg:phone":"+44 1708 378577",
    "sg:postcode":"RM3 9RE",
    "sg:province":"Essex",
    "sg:tags":[
        "organisation",
        "consumer"
    ],
    "wof:name":"Power Dividend Ltd",
    "wof:placetype":"venue"
},
  "geometry": {"coordinates":[0.23866,51.606281],"type":"Point"}
}