{
  "type": "Feature",
  "properties": {
    "iso:country":"GB",
    "sg:address":"33 Sanstone Road East",
    "sg:city":"Liverpool",
    "sg:classifiers":[
        {
            "category":"Utilities",
            "subcategory":"Natural Gas",
            "type":"Services"
        }
    ],
    "sg:phone":"+44 151 259 3053",
    "sg:postcode":"L13 6QX",
    "sg:province":"Merseyside",
    "sg:tags":[
        "supplier"
    ],
    "wof:name":"M M C Bottled Gas",
    "wof:placetype":"venue"
},
  "geometry": {"coordinates":[-2.916059,53.418434],"type":"Point"}
}