{
  "type": "Feature",
  "properties": {
    "iso:country":"GB",
    "sg:address":"17a Ann St",
    "sg:city":"Newcastle Upon Tyne",
    "sg:classifiers":[
        {
            "category":"Real Estate",
            "subcategory":"Surveying",
            "type":"Services"
        }
    ],
    "sg:phone":"+44 191 253 4970",
    "sg:postcode":"NE27 0QR",
    "sg:province":"Northumberland",
    "sg:tags":[
        "surveyor",
        "quantity"
    ],
    "wof:name":"G W Hunter",
    "wof:placetype":"venue"
},
  "geometry": {"coordinates":[-1.525017,54.979603],"type":"Point"}
}