{
  "type": "Feature",
  "properties": {
    "iso:country":"GB",
    "sg:address":"24 Chatsworth Drive",
    "sg:city":"Enfield",
    "sg:classifiers":[
        {
            "category":"Home & Garden",
            "subcategory":"Household Appliances",
            "type":"Retail Goods"
        }
    ],
    "sg:phone":"+44 20 8367 1063",
    "sg:postcode":"EN1 1EX",
    "sg:province":"Greater London",
    "sg:tags":[
        "electrical"
    ],
    "wof:name":"S & J Domestics",
    "wof:placetype":"venue"
},
  "geometry": {"coordinates":[-0.062252,51.6394805908],"type":"Point"}
}