{
  "type": "Feature",
  "properties": {
    "iso:country":"GB",
    "sg:address":"Glanduar Garage",
    "sg:city":"Llanybydder",
    "sg:classifiers":[
        {
            "category":"Professional",
            "subcategory":"Engineering",
            "type":"Services"
        }
    ],
    "sg:phone":"+44 1570 480531",
    "sg:postcode":"SA40 9RN",
    "sg:province":"Carmarthenshire",
    "wof:name":"Evans,Ieuan,& Sons",
    "wof:placetype":"venue"
},
  "geometry": {"coordinates":[-4.158361,52.073936],"type":"Point"}
}