{
  "type": "Feature",
  "properties": {
    "iso:country":"GB",
    "sg:address":"82 Aylsham Road",
    "sg:city":"Norwich",
    "sg:classifiers":[
        {
            "category":"Manufacturing",
            "subcategory":"Furniture",
            "type":"Manufacturing & Wholesale Goods"
        }
    ],
    "sg:phone":"+44 1603 407221",
    "sg:postcode":"NR3 2HN",
    "sg:province":"Norfolk",
    "sg:tags":[
        "polishing",
        "french"
    ],
    "wof:name":"Alan John Coe",
    "wof:placetype":"venue"
},
  "geometry": {"coordinates":[1.285614,52.643429],"type":"Point"}
}