{
  "type": "Feature",
  "properties": {
    "addr:full":"83 Williamson Road, Kempston Bedford Bedfordshire MK42 7HR",
    "addr:housenumber":"83",
    "addr:postcode":"mk42 7hr",
    "addr:street":"Williamson Road",
    "iso:country":"GB",
    "sg:address":"83 Williamson Road, Kempston",
    "sg:city":"Bedford",
    "sg:classifiers":[
        {
            "category":"Personal",
            "subcategory":"Beauty Salon",
            "type":"Services"
        }
    ],
    "sg:postcode":"MK42 7HR",
    "sg:province":"Bedfordshire",
    "sg:tags":[
        "unisex",
        "hairdresser"
    ],
    "wof:name":"Silhouette",
    "wof:placetype":"venue"
},
  "geometry": {"coordinates":[-0.5053089857,52.1109962463],"type":"Point"}
}