{
  "type": "Feature",
  "properties": {
    "addr:full":"Unit 14, Withambrook Park, Londonthorpe Road Grantham Lincolnshire NG31 9ST",
    "addr:housenumber":"unit 14",
    "addr:postcode":"ng31 9st",
    "addr:street":"Withambrook Park Londonthorpe Road",
    "iso:country":"GB",
    "sg:address":"Unit 14, Withambrook Park, Londonthorpe Road",
    "sg:city":"Grantham",
    "sg:classifiers":[
        {
            "category":"Professional",
            "subcategory":"Engineering",
            "type":"Services"
        }
    ],
    "sg:phone":"+44 1476 565228",
    "sg:postcode":"NG31 9ST",
    "sg:province":"Lincolnshire",
    "sg:tags":[
        "engineer",
        "mechanical"
    ],
    "wof:name":"Curtis Vibrators Grantham Ltd",
    "wof:placetype":"venue"
},
  "geometry": {"coordinates":[-0.6094920039,52.9260559082],"type":"Point"}
}