{
  "type": "Feature",
  "properties": {
    "addr:full":"380 Green Lanes London Greater London N13 5PB",
    "addr:housenumber":"380",
    "addr:postcode":"n13 5pb",
    "addr:street":"Green Lanes",
    "iso:country":"GB",
    "sg:address":"380 Green Lanes",
    "sg:city":"London",
    "sg:classifiers":[
        {
            "category":"Restaurant",
            "type":"Food & Drink"
        }
    ],
    "sg:postcode":"N13 5PB",
    "sg:province":"Greater London",
    "wof:name":"Troodos",
    "wof:placetype":"venue"
},
  "geometry": {"coordinates":[-0.105784,51.621124],"type":"Point"}
}