{
  "type": "Feature",
  "properties": {
    "iso:country":"GB",
    "sg:address":"17 Roseneath St",
    "sg:city":"Edinburgh",
    "sg:classifiers":[
        {
            "category":"Retail",
            "subcategory":"Laundry & Dry Cleaning",
            "type":"Services"
        }
    ],
    "sg:phone":"+44 131 229 2137",
    "sg:postcode":"EH9 1JH",
    "sg:province":"City of Edinburgh",
    "sg:tags":[
        "launderette"
    ],
    "wof:name":"Sundial Launderettes",
    "wof:placetype":"venue"
},
  "geometry": {"coordinates":[-3.188699,55.938049],"type":"Point"}
}