{
  "type": "Feature",
  "properties": {
    "iso:country":"GB",
    "sg:address":"Gordon House, 3-5 Leicester Street",
    "sg:city":"Southport",
    "sg:classifiers":[
        {
            "category":"Government",
            "subcategory":"Court House",
            "type":"Public Place"
        }
    ],
    "sg:phone":"+44 1704 531643",
    "sg:postcode":"PR9 0ER",
    "sg:province":"Lancashire",
    "wof:name":"The Hm Coroner",
    "wof:placetype":"venue"
},
  "geometry": {"coordinates":[-2.999893,53.652782],"type":"Point"}
}