{
  "type": "Feature",
  "properties": {
    "addr:full":"112 Wyke Road Trowbridge Wiltshire BA14 7NR",
    "addr:housenumber":"112",
    "addr:postcode":"ba14 7nr",
    "addr:street":"Wyke Road",
    "iso:country":"GB",
    "sg:address":"112 Wyke Road",
    "sg:city":"Trowbridge",
    "sg:classifiers":[
        {
            "category":"Retail",
            "subcategory":"Driving School",
            "type":"Services"
        }
    ],
    "sg:postcode":"BA14 7NR",
    "sg:province":"Wiltshire",
    "wof:name":"D Emm",
    "wof:placetype":"venue"
},
  "geometry": {"coordinates":[-2.1997718811,51.3352584839],"type":"Point"}
}