{
  "type": "Feature",
  "properties": {
    "iso:country":"GB",
    "sg:address":"Bridge Wharf Ho, The Quay",
    "sg:city":"Sandwich",
    "sg:classifiers":[
        {
            "category":"Building & Trades",
            "subcategory":"Cleaning & Sanitation",
            "type":"Services"
        }
    ],
    "sg:phone":"+44 1304 620855",
    "sg:postcode":"CT13 9EN",
    "sg:province":"Kent",
    "sg:tags":[
        "door",
        "manufacturer"
    ],
    "wof:name":"Porte Rush",
    "wof:placetype":"venue"
},
  "geometry": {"coordinates":[1.342304,51.276169],"type":"Point"}
}