{
  "type": "Feature",
  "properties": {
    "iso:country":"GB",
    "sg:address":"33 London Road",
    "sg:city":"Chelmsford",
    "sg:classifiers":[
        {
            "category":"Health Services",
            "subcategory":"Dentist",
            "type":"Services"
        }
    ],
    "sg:phone":"+44 1279 435440",
    "sg:postcode":"CM17 0DB",
    "sg:province":"Essex",
    "wof:name":"Dental Surgery",
    "wof:placetype":"venue"
},
  "geometry": {"coordinates":[0.217505,51.78804],"type":"Point"}
}