{
  "type": "Feature",
  "properties": {
    "addr:full":"Optimum Ho, 28 Moss St Prescot Merseyside L34 6HL",
    "addr:housenumber":"28",
    "addr:postcode":"l34 6hl",
    "addr:street":"Moss St",
    "iso:country":"GB",
    "sg:address":"Optimum Ho, 28 Moss St",
    "sg:city":"Prescot",
    "sg:classifiers":[
        {
            "category":"Professional",
            "subcategory":"Employment Agencies",
            "type":"Services"
        }
    ],
    "sg:phone":"+44 151 426 1000",
    "sg:postcode":"L34 6HL",
    "sg:province":"Merseyside",
    "sg:tags":[
        "consultant"
    ],
    "wof:name":"Optimum Recruitment",
    "wof:placetype":"venue"
},
  "geometry": {"coordinates":[-2.803034,53.430275],"type":"Point"}
}