{
  "type": "Feature",
  "properties": {
    "addr:full":"Unit 3 Gwent Court, Victoria Park Ebbw Vale Blaenau Gwent NP23 8AN",
    "addr:housenumber":"unit 3",
    "addr:postcode":"np23 8an",
    "addr:street":"Gwent Court",
    "iso:country":"GB",
    "sg:address":"Unit 3 Gwent Court, Victoria Park",
    "sg:city":"Ebbw Vale",
    "sg:classifiers":[
        {
            "category":"Professional",
            "type":"Services"
        }
    ],
    "sg:postcode":"NP23 8AN",
    "sg:province":"Blaenau Gwent",
    "sg:tags":[
        "repair",
        "tech",
        "maintenance"
    ],
    "wof:name":"Asutec Ltd",
    "wof:placetype":"venue"
},
  "geometry": {"coordinates":[-3.206215,51.770226],"type":"Point"}
}