{
  "type": "Feature",
  "properties": {
    "iso:country":"GB",
    "sg:address":"20 Court Street",
    "sg:city":"Haddington",
    "sg:classifiers":[
        {
            "category":"Banks & Credit Unions",
            "subcategory":"Bank",
            "type":"Services"
        },
        {
            "category":"Real Estate",
            "subcategory":"Real Estate Agent",
            "type":"Services"
        }
    ],
    "sg:phone":"+44 1620 825555",
    "sg:postcode":"EH41 3JA",
    "sg:province":"East Lothian",
    "sg:tags":[
        "financial",
        "institution"
    ],
    "wof:name":"PROPERTY & MORTGAGE PARTNERSHIP",
    "wof:placetype":"venue"
},
  "geometry": {"coordinates":[-2.7797570229,55.9557342529],"type":"Point"}
}