{
  "type": "Feature",
  "properties": {
    "iso:country":"GB",
    "sg:address":"115-122 Snowsfields",
    "sg:city":"Southwark",
    "sg:classifiers":[
        {
            "category":"Health Services",
            "subcategory":"Hospital",
            "type":"Services"
        }
    ],
    "sg:phone":"+44 20 7955 4780",
    "sg:postcode":"SE1 3SS",
    "sg:province":"Greater London",
    "wof:name":"Ronald McDonald House",
    "wof:placetype":"venue"
},
  "geometry": {"coordinates":[-0.0853940025,51.5021095276],"type":"Point"}
}