{
  "type": "Feature",
  "properties": {
    "addr:full":"38a Northbrook Street Newbury Berkshire RG14 1DT",
    "addr:housenumber":"38a",
    "addr:postcode":"rg14 1dt",
    "addr:street":"Northbrook Street",
    "iso:country":"GB",
    "sg:address":"38a Northbrook Street",
    "sg:city":"Newbury",
    "sg:classifiers":[
        {
            "category":"Travel",
            "subcategory":"Travel Agent",
            "type":"Entertainment"
        }
    ],
    "sg:phone":"+44 1635 46222",
    "sg:postcode":"RG14 1DT",
    "sg:province":"Berkshire",
    "wof:name":"Going Places Leisure Travel",
    "wof:placetype":"venue"
},
  "geometry": {"coordinates":[-1.3244459629,51.4043083191],"type":"Point"}
}