{
  "type": "Feature",
  "properties": {
    "addr:full":"4 Drakes Approach Clacton On Sea Essex CO15 2PX",
    "addr:housenumber":"4",
    "addr:postcode":"co15 2px",
    "addr:street":"Drakes Approach;Sea",
    "iso:country":"GB",
    "sg:address":"4 Drakes Approach",
    "sg:city":"Clacton On Sea",
    "sg:classifiers":[
        {
            "category":"Manufacturing",
            "subcategory":"Signs",
            "type":"Manufacturing & Wholesale Goods"
        }
    ],
    "sg:phone":"+44 1255 427709",
    "sg:postcode":"CO15 2PX",
    "sg:province":"Essex",
    "sg:tags":[
        "writer"
    ],
    "wof:name":"Raymond Jessup",
    "wof:placetype":"venue"
},
  "geometry": {"coordinates":[1.1188659668,51.7864570618],"type":"Point"}
}