{
  "type": "Feature",
  "properties": {
    "addr:full":"Slade Oak Lane Gerrards Cross Buckinghamshire SL9 0QE",
    "addr:postcode":"sl9 0qe",
    "addr:street":"Slade Oak Lane",
    "iso:country":"GB",
    "sg:address":"Slade Oak Lane",
    "sg:city":"Gerrards Cross",
    "sg:classifiers":[
        {
            "category":"Retail",
            "subcategory":"Auto Repair",
            "type":"Services"
        }
    ],
    "sg:phone":"+44 1753 882164",
    "sg:postcode":"SL9 0QE",
    "sg:province":"Buckinghamshire",
    "sg:tags":[
        "modification",
        "garage"
    ],
    "wof:name":"Automobile Services",
    "wof:placetype":"venue"
},
  "geometry": {"coordinates":[-0.534394,51.59956],"type":"Point"}
}