{
  "type": "Feature",
  "properties": {
    "addr:full":"38 Burrows Road, Skewen Neath Neath Port Talbot SA10 6AB",
    "addr:housenumber":"38",
    "addr:postcode":"sa10 6ab",
    "addr:street":"Burrows Road",
    "iso:country":"GB",
    "sg:address":"38 Burrows Road, Skewen",
    "sg:city":"Neath",
    "sg:classifiers":[
        {
            "category":"Building & Trades",
            "subcategory":"Construction",
            "type":"Services"
        }
    ],
    "sg:postcode":"SA10 6AB",
    "sg:province":"Neath Port Talbot",
    "sg:tags":[
        "builder"
    ],
    "wof:name":"K Oakley Son",
    "wof:placetype":"venue"
},
  "geometry": {"coordinates":[-3.8424720764,51.6577835083],"type":"Point"}
}