{
  "type": "Feature",
  "properties": {
    "iso:country":"GB",
    "sg:address":"Castlecary Rd, Wardpark Indust Est",
    "sg:city":"Glasgow",
    "sg:classifiers":[
        {
            "category":"Freight",
            "type":"Transportation"
        }
    ],
    "sg:phone":"+44 1236 453284",
    "sg:postcode":"G68 0DB",
    "sg:province":"East Dunbartonshire",
    "sg:tags":[
        "haulage",
        "road"
    ],
    "wof:name":"T D G Williams",
    "wof:placetype":"venue"
},
  "geometry": {"coordinates":[-3.944996,55.98254],"type":"Point"}
}