{
  "type": "Feature",
  "properties": {
    "addr:full":"31 Sycamore Road Amersham Buckinghamshire HP6 5EQ",
    "addr:housenumber":"31",
    "addr:postcode":"hp6 5eq",
    "addr:street":"Sycamore Road",
    "iso:country":"GB",
    "sg:address":"31 Sycamore Road",
    "sg:city":"Amersham",
    "sg:classifiers":[
        {
            "category":"Shopping",
            "subcategory":"Shoes",
            "type":"Retail Goods"
        }
    ],
    "sg:phone":"+44 1494 433689",
    "sg:postcode":"HP6 5EQ",
    "sg:province":"Buckinghamshire",
    "sg:tags":[
        "shop"
    ],
    "wof:name":"Milwards Shoes",
    "wof:placetype":"venue"
},
  "geometry": {"coordinates":[-0.606670022,51.6777801514],"type":"Point"}
}