{
  "type": "Feature",
  "properties": {
    "iso:country":"GB",
    "sg:address":"P O Box 332",
    "sg:city":"Doncaster",
    "sg:classifiers":[
        {
            "category":"Manufacturing",
            "subcategory":"Chemicals & Compounds",
            "type":"Manufacturing & Wholesale Goods"
        }
    ],
    "sg:postcode":"DN4 6YD",
    "sg:province":"South Yorkshire",
    "sg:tags":[
        "pesticide"
    ],
    "wof:name":"Superior Marketing",
    "wof:placetype":"venue"
},
  "geometry": {"coordinates":[-1.0688890219,53.5054283142],"type":"Point"}
}