{
  "type": "Feature",
  "properties": {
    "addr:full":"92a Old Tiverton Road Exeter Devon EX4 6LQ",
    "addr:housenumber":"92a",
    "addr:postcode":"ex4 6lq",
    "addr:street":"Old Tiverton Road",
    "iso:country":"GB",
    "sg:address":"92a Old Tiverton Road",
    "sg:city":"Exeter",
    "sg:classifiers":[
        {
            "category":"Home & Garden",
            "subcategory":"Carpets & Floor Coverings",
            "type":"Retail Goods"
        }
    ],
    "sg:phone":"+44 1392 493084",
    "sg:postcode":"EX4 6LQ",
    "sg:province":"Devon",
    "sg:tags":[
        "carpets",
        "rug",
        "matting"
    ],
    "wof:name":"The Exeter Carpet Co. Ltd.",
    "wof:placetype":"venue"
},
  "geometry": {"coordinates":[-3.518746,50.731113],"type":"Point"}
}