{
  "type": "Feature",
  "properties": {
    "iso:country":"GB",
    "sg:address":"5 St Olaves Road",
    "sg:city":"Norwich",
    "sg:classifiers":[
        {
            "category":"Building & Trades",
            "subcategory":"Construction",
            "type":"Services"
        }
    ],
    "sg:postcode":"NR3 4QB",
    "sg:province":"Norfolk",
    "sg:tags":[
        "decorator",
        "painter"
    ],
    "wof:name":"Painters Plus",
    "wof:placetype":"venue"
},
  "geometry": {"coordinates":[1.300361,52.641479],"type":"Point"}
}