{
  "type": "Feature",
  "properties": {
    "iso:country":"GB",
    "sg:address":"210 Broadway",
    "sg:city":"Didcot",
    "sg:classifiers":[
        {
            "category":"Real Estate",
            "subcategory":"Real Estate Agent",
            "type":"Services"
        }
    ],
    "sg:phone":"+44 1235 811991",
    "sg:postcode":"OX11 8SQ",
    "sg:province":"Oxfordshire",
    "wof:name":"Buckell & Ballard",
    "wof:placetype":"venue"
},
  "geometry": {"coordinates":[-1.240218997,51.6062011719],"type":"Point"}
}