{
  "type": "Feature",
  "properties": {
    "iso:country":"GB",
    "sg:address":"C/o Seymour Taylor & Co, 57 London Road",
    "sg:city":"High Wycombe",
    "sg:classifiers":[
        {
            "category":"Building & Trades",
            "subcategory":"Construction",
            "type":"Services"
        }
    ],
    "sg:postcode":"HP11 1BS",
    "sg:province":"Buckinghamshire",
    "sg:tags":[
        "fork",
        "lift",
        "truck"
    ],
    "wof:name":"M & K Mechanical Handling Ltd.",
    "wof:placetype":"venue"
},
  "geometry": {"coordinates":[-0.7387819886,51.626209259],"type":"Point"}
}