{
  "type": "Feature",
  "properties": {
    "addr:full":"Unit P, The Old Imperial Laundry, 71 Warriner Gardens London Greater London SW11 4XW",
    "addr:housenumber":"71",
    "addr:postcode":"sw11 4xw",
    "addr:street":"Warriner Gardens",
    "iso:country":"GB",
    "sg:address":"Unit P, The Old Imperial Laundry, 71 Warriner Gardens",
    "sg:city":"London",
    "sg:classifiers":[
        {
            "category":"Professional",
            "type":"Services"
        },
        {
            "category":"Home & Garden",
            "subcategory":"Home Furnishings",
            "type":"Retail Goods"
        }
    ],
    "sg:phone":"+44 20 7627 5077",
    "sg:postcode":"SW11 4XW",
    "sg:province":"Greater London",
    "sg:tags":[
        "blind",
        "designer",
        "furnishers",
        "fitting",
        "interior",
        "curtain"
    ],
    "sg:website":"http://www.mckinney.co.uk",
    "wof:name":"S McKinney & Co. Ltd.",
    "wof:placetype":"venue"
},
  "geometry": {"coordinates":[-0.1571349949,51.4746398926],"type":"Point"}
}