{
  "type": "Feature",
  "properties": {
    "addr:full":"14 Cork Street London Greater London W1S 3NS",
    "addr:housenumber":"14",
    "addr:postcode":"w1s 3ns",
    "addr:street":"Cork Street",
    "iso:country":"GB",
    "sg:address":"14 Cork Street",
    "sg:city":"London",
    "sg:classifiers":[
        {
            "category":"Professional",
            "subcategory":"Business Services",
            "type":"Services"
        }
    ],
    "sg:phone":"+44 20 7629 4384",
    "sg:postcode":"W1S 3NS",
    "sg:province":"Greater London",
    "sg:tags":[
        "trade"
    ],
    "wof:name":"The Scotch Whisky Association",
    "wof:placetype":"venue"
},
  "geometry": {"coordinates":[-0.141321,51.509888],"type":"Point"}
}