{
  "type": "Feature",
  "properties": {
    "addr:full":"23 Bromley Gardens, South Beach Estate Blyth Northumberland NE24 3TU",
    "addr:housenumber":"23",
    "addr:postcode":"ne24 3tu",
    "addr:street":"Bromley Gardens",
    "iso:country":"GB",
    "sg:address":"23 Bromley Gardens, South Beach Estate",
    "sg:city":"Blyth",
    "sg:classifiers":[
        {
            "category":"Retail",
            "subcategory":"Auto Repair",
            "type":"Services"
        }
    ],
    "sg:phone":"+44 1670 351375",
    "sg:postcode":"NE24 3TU",
    "sg:province":"Northumberland",
    "sg:tags":[
        "modification",
        "garage"
    ],
    "wof:name":"Steve Howe Mobile Mechanic",
    "wof:placetype":"venue"
},
  "geometry": {"coordinates":[-1.512996,55.114182],"type":"Point"}
}