{
  "type": "Feature",
  "properties": {
    "iso:country":"GB",
    "sg:address":"Offenham Garage, Ferry Lane",
    "sg:city":"Evesham",
    "sg:classifiers":[
        {
            "category":"Retail",
            "subcategory":"Auto Repair",
            "type":"Services"
        }
    ],
    "sg:postcode":"WR11 8RT",
    "sg:province":"Gloucestershire",
    "sg:tags":[
        "modification",
        "garage"
    ],
    "wof:name":"Bernard Harris & Co.",
    "wof:placetype":"venue"
},
  "geometry": {"coordinates":[-1.921346,52.111675],"type":"Point"}
}