{
  "type": "Feature",
  "properties": {
    "addr:full":"27 St Lukes Road Tunbridge Wells Kent TN4 9JH",
    "addr:housenumber":"27",
    "addr:postcode":"tn4 9jh",
    "addr:street":"St Lukes Road",
    "iso:country":"GB",
    "sg:address":"27 St Lukes Road",
    "sg:city":"Tunbridge Wells",
    "sg:classifiers":[
        {
            "category":"Building & Trades",
            "subcategory":"Construction",
            "type":"Services"
        }
    ],
    "sg:phone":"+44 1892 540306",
    "sg:postcode":"TN4 9JH",
    "sg:province":"Kent",
    "sg:tags":[
        "builder"
    ],
    "wof:name":"Crowhurst Builders",
    "wof:placetype":"venue"
},
  "geometry": {"coordinates":[0.2693609893,51.1455078125],"type":"Point"}
}