{
  "type": "Feature",
  "properties": {
    "addr:full":"Hopwood Arms Hotel, Bottomgate Blackburn Lancashire BB1 3AD",
    "addr:postcode":"bb1 3ad",
    "addr:street":"Bottomgate",
    "iso:country":"GB",
    "sg:address":"Hopwood Arms Hotel, Bottomgate",
    "sg:city":"Blackburn",
    "sg:classifiers":[
        {
            "category":"Home & Garden",
            "subcategory":"Carpets & Floor Coverings",
            "type":"Retail Goods"
        }
    ],
    "sg:phone":"+44 1254 675058",
    "sg:postcode":"BB1 3AD",
    "sg:province":"Lancashire",
    "sg:tags":[
        "carpets",
        "rug",
        "matting"
    ],
    "wof:name":"Carpets Direct",
    "wof:placetype":"venue"
},
  "geometry": {"coordinates":[-2.4803988934,53.7485160828],"type":"Point"}
}