{
  "type": "Feature",
  "properties": {
    "addr:full":"172 Walsall Rd, Perry Barr Birmingham West Midlands B42 1UD",
    "addr:housenumber":"172",
    "addr:postcode":"b42 1ud",
    "addr:street":"Walsall Rd",
    "iso:country":"GB",
    "sg:address":"172 Walsall Rd, Perry Barr",
    "sg:city":"Birmingham",
    "sg:classifiers":[
        {
            "category":"Manufacturing",
            "subcategory":"Apparel",
            "type":"Manufacturing & Wholesale Goods"
        }
    ],
    "sg:phone":"+44 121 356 3337",
    "sg:postcode":"B42 1UD",
    "sg:province":"West Midlands",
    "sg:tags":[
        "shirt",
        "maker"
    ],
    "wof:name":"Unleaded Clothing Co",
    "wof:placetype":"venue"
},
  "geometry": {"coordinates":[-1.901911974,52.5229034424],"type":"Point"}
}