{
  "type": "Feature",
  "properties": {
    "addr:full":"205 Farnborough Road Farnborough Hampshire GU14 7JT",
    "addr:housenumber":"205",
    "addr:postcode":"gu14 7jt",
    "addr:street":"Farnborough Road",
    "iso:country":"GB",
    "sg:address":"205 Farnborough Road",
    "sg:city":"Farnborough",
    "sg:classifiers":[
        {
            "category":"Autos & Motor Vehicles",
            "subcategory":"Fuel & Gas Station",
            "type":"Retail Goods"
        }
    ],
    "sg:phone":"+44 1252 522072",
    "sg:postcode":"GU14 7JT",
    "sg:province":"Hampshire",
    "sg:tags":[
        "hr",
        "petrol"
    ],
    "wof:name":"Kingsmead Motoring Centre",
    "wof:placetype":"venue"
},
  "geometry": {"coordinates":[-0.7536150217,51.2903747559],"type":"Point"}
}