{
  "type": "Feature",
  "properties": {
    "iso:country":"GB",
    "sg:address":"9 George St",
    "sg:city":"Hastings",
    "sg:classifiers":[
        {
            "category":"Restaurant",
            "type":"Food & Drink"
        }
    ],
    "sg:phone":"+44 1424 429211",
    "sg:postcode":"TN34 3EG",
    "sg:province":"East Sussex",
    "sg:tags":[
        "italian"
    ],
    "wof:name":"Bella Napoli Italian Restaurant",
    "wof:placetype":"venue"
},
  "geometry": {"coordinates":[0.588623,50.863831],"type":"Point"}
}