{
  "type": "Feature",
  "properties": {
    "addr:full":"124a Brettenham Rd Upper Edmonton Greater London N18 2HD",
    "addr:housenumber":"124a",
    "addr:postcode":"n18 2hd",
    "addr:street":"Brettenham Rd",
    "iso:country":"GB",
    "sg:address":"124a Brettenham Rd",
    "sg:city":"Upper Edmonton",
    "sg:classifiers":[
        {
            "category":"Wholesale",
            "subcategory":"Scrap",
            "type":"Manufacturing & Wholesale Goods"
        }
    ],
    "sg:phone":"+44 20 8350 9291",
    "sg:postcode":"N18 2HD",
    "sg:province":"Greater London",
    "sg:tags":[
        "waste",
        "metal"
    ],
    "wof:name":"D.K. Metals",
    "wof:placetype":"venue"
},
  "geometry": {"coordinates":[-0.0556819998,51.617149353],"type":"Point"}
}