{
  "type": "Feature",
  "properties": {
    "addr:full":"3 The Lanchesters, 162 Fulham Palace Road London Greater London W6 9ER",
    "addr:housenumber":"3;162",
    "addr:postcode":"w6 9er",
    "addr:street":"The Lanchesters;Fulham Palace Road",
    "iso:country":"GB",
    "sg:address":"3 The Lanchesters, 162 Fulham Palace Road",
    "sg:city":"London",
    "sg:classifiers":[
        {
            "category":"Shopping",
            "subcategory":"Books",
            "type":"Retail Goods"
        },
        {
            "category":"Wholesale",
            "subcategory":"Books, Periodicals, & Newspapers",
            "type":"Manufacturing & Wholesale Goods"
        }
    ],
    "sg:phone":"+44 20 8741 3663",
    "sg:postcode":"W6 9ER",
    "sg:province":"Greater London",
    "sg:tags":[
        "publisher"
    ],
    "wof:name":"Constable & Robinson Ltd.",
    "wof:placetype":"venue"
},
  "geometry": {"coordinates":[-0.220553,51.485752],"type":"Point"}
}