{
  "type": "Feature",
  "properties": {
    "iso:country":"GB",
    "sg:address":"135 Epping New Rd",
    "sg:city":"Buckhurst Hill",
    "sg:classifiers":[
        {
            "category":"Arts & Performance",
            "subcategory":"Theater",
            "type":"Entertainment"
        }
    ],
    "sg:phone":"+44 20 8502 9691",
    "sg:postcode":"IG9 5TZ",
    "sg:province":"Essex",
    "sg:tags":[
        "theatre"
    ],
    "wof:name":"Opening Night Productions Ltd",
    "wof:placetype":"venue"
},
  "geometry": {"coordinates":[0.031123,51.630142],"type":"Point"}
}