{
  "type": "Feature",
  "properties": {
    "addr:full":"32 Bell Hall Terrace Halifax West Yorkshire HX1 3EE",
    "addr:housenumber":"32",
    "addr:postcode":"hx1 3ee",
    "addr:street":"Bell Hall Terrace",
    "iso:country":"GB",
    "sg:address":"32 Bell Hall Terrace",
    "sg:city":"Halifax",
    "sg:classifiers":[
        {
            "category":"Personal",
            "subcategory":"Beauty Salon",
            "type":"Services"
        }
    ],
    "sg:postcode":"HX1 3EE",
    "sg:province":"West Yorkshire",
    "sg:tags":[
        "unisex",
        "hairdresser"
    ],
    "wof:name":"Heidi's",
    "wof:placetype":"venue"
},
  "geometry": {"coordinates":[-1.873075,53.7132],"type":"Point"}
}