{
  "type": "Feature",
  "properties": {
    "addr:full":"Dawson Road, Mount Farm, Bletchley Milton Keynes Buckinghamshire MK1 1JN",
    "addr:postcode":"mk1 1jn",
    "addr:street":"Dawson Road Mount",
    "iso:country":"GB",
    "sg:address":"Dawson Road, Mount Farm, Bletchley",
    "sg:city":"Milton Keynes",
    "sg:classifiers":[
        {
            "category":"Farming",
            "subcategory":"Dairy Farm",
            "type":"Manufacturing & Wholesale Goods"
        }
    ],
    "sg:phone":"+44 1908 374484",
    "sg:postcode":"MK1 1JN",
    "sg:province":"Buckinghamshire",
    "wof:name":"Taylors Dairies (Milton Keynes) Ltd.",
    "wof:placetype":"venue"
},
  "geometry": {"coordinates":[-0.722764,52.01041],"type":"Point"}
}