{
  "type": "Feature",
  "properties": {
    "addr:full":"70 Pope Lane, Penwortham Preston Lancashire PR1 9DA",
    "addr:housenumber":"70",
    "addr:postcode":"pr1 9da",
    "addr:street":"Pope Lane",
    "iso:country":"GB",
    "sg:address":"70 Pope Lane, Penwortham",
    "sg:city":"Preston",
    "sg:classifiers":[
        {
            "category":"Personal",
            "subcategory":"Beauty Salon",
            "type":"Services"
        },
        {
            "category":"Personal",
            "subcategory":"Barber",
            "type":"Services"
        }
    ],
    "sg:phone":"+44 1772 742080",
    "sg:postcode":"PR1 9DA",
    "sg:province":"Lancashire",
    "sg:tags":[
        "unisex",
        "hairdresser"
    ],
    "wof:name":"Studio 2 Hair",
    "wof:placetype":"venue"
},
  "geometry": {"coordinates":[-2.7218658924,53.7369651794],"type":"Point"}
}