{
  "type": "Feature",
  "properties": {
    "iso:country":"GB",
    "sg:address":"10 Honeyfields, Birchheath Rd",
    "sg:city":"Tarporley",
    "sg:classifiers":[
        {
            "category":"Professional",
            "subcategory":"Management & Consulting",
            "type":"Services"
        },
        {
            "category":"Manufacturing",
            "subcategory":"Building Materials",
            "type":"Manufacturing & Wholesale Goods"
        }
    ],
    "sg:postcode":"CW6 9XA",
    "sg:province":"Cheshire",
    "sg:tags":[
        "concrete",
        "product",
        "business",
        "consultant"
    ],
    "wof:name":"Fenwick,R G,",
    "wof:placetype":"venue"
},
  "geometry": {"coordinates":[-2.6696670055,53.1539001465],"type":"Point"}
}