{
  "type": "Feature",
  "properties": {
    "iso:country":"GB",
    "sg:address":"The Priests House, Caesars Camp Road",
    "sg:city":"Camberley",
    "sg:classifiers":[
        {
            "category":"Place Of Worship",
            "type":"Public Place"
        }
    ],
    "sg:phone":"+44 1276 63813",
    "sg:postcode":"GU15 4ED",
    "sg:province":"Berkshire",
    "wof:name":"St. Peter's & St. John's Church",
    "wof:placetype":"venue"
},
  "geometry": {"coordinates":[-0.723503,51.348419],"type":"Point"}
}