{
  "type": "Feature",
  "properties": {
    "addr:full":"23-25 Dale Street Liverpool Merseyside L2 2EZ",
    "addr:housenumber":"23-25",
    "addr:postcode":"l2 2ez",
    "addr:street":"Dale Street",
    "iso:country":"GB",
    "sg:address":"23-25 Dale Street",
    "sg:city":"Liverpool",
    "sg:classifiers":[
        {
            "category":"Bars & Pubs",
            "type":"Food & Drink"
        },
        {
            "category":"Community Center",
            "subcategory":"Social",
            "type":"Public Place"
        }
    ],
    "sg:phone":"+44 151 236 1486",
    "sg:postcode":"L2 2EZ",
    "sg:province":"Merseyside",
    "sg:tags":[
        "pubs",
        "house",
        "inn",
        "activity"
    ],
    "wof:name":"Rigby's Public House",
    "wof:placetype":"venue"
},
  "geometry": {"coordinates":[-2.989638,53.407673],"type":"Point"}
}