{
  "type": "Feature",
  "properties": {
    "addr:full":"29 Sidelands Road Stratford-upon-avon Warwickshire CV37 9DT",
    "addr:housenumber":"29",
    "addr:postcode":"cv37 9dt",
    "addr:street":"Sidelands Road",
    "iso:country":"GB",
    "sg:address":"29 Sidelands Road",
    "sg:city":"Stratford-upon-avon",
    "sg:classifiers":[
        {
            "category":"Manufacturing",
            "subcategory":"Food",
            "type":"Manufacturing & Wholesale Goods"
        },
        {
            "category":"Food & Beverages",
            "subcategory":"Specialty",
            "type":"Retail Goods"
        }
    ],
    "sg:postcode":"CV37 9DT",
    "sg:province":"Warwickshire",
    "sg:tags":[
        "consultant",
        "technologist"
    ],
    "wof:name":"G T Parslow",
    "wof:placetype":"venue"
},
  "geometry": {"coordinates":[-1.731392,52.197021],"type":"Point"}
}