{
  "type": "Feature",
  "properties": {
    "addr:full":"4 Church Street Ossett West Yorkshire WF5 9DE",
    "addr:housenumber":"4",
    "addr:postcode":"wf5 9de",
    "addr:street":"Church Street",
    "iso:country":"GB",
    "sg:address":"4 Church Street",
    "sg:city":"Ossett",
    "sg:classifiers":[
        {
            "category":"Shopping",
            "subcategory":"Clothing, Apparel, & Fashions",
            "type":"Retail Goods"
        }
    ],
    "sg:phone":"+44 1924 263931",
    "sg:postcode":"WF5 9DE",
    "sg:province":"West Yorkshire",
    "sg:tags":[
        "menswear"
    ],
    "wof:name":"Carl Stuart Ltd.",
    "wof:placetype":"venue"
},
  "geometry": {"coordinates":[-1.582119,53.684139],"type":"Point"}
}