{
  "type": "Feature",
  "properties": {
    "addr:full":"Black Scotch La Mansfield Nottinghamshire NG18 4JW",
    "addr:postcode":"ng18 4jw",
    "iso:country":"GB",
    "sg:address":"Black Scotch La",
    "sg:city":"Mansfield",
    "sg:classifiers":[
        {
            "category":"Education",
            "subcategory":"School",
            "type":"Public Place"
        }
    ],
    "sg:phone":"+44 1623 621023",
    "sg:postcode":"NG18 4JW",
    "sg:province":"Nottinghamshire",
    "sg:tags":[
        "local",
        "authority"
    ],
    "wof:name":"Berry Hill Middle School",
    "wof:placetype":"venue"
},
  "geometry": {"coordinates":[-1.171955,53.130787],"type":"Point"}
}