{
  "type": "Feature",
  "properties": {
    "iso:country":"GB",
    "sg:address":"6 St. Edmund St",
    "sg:city":"Weymouth",
    "sg:classifiers":[
        {
            "category":"Military Area",
            "subcategory":"Air Force Base",
            "type":"Public Place"
        }
    ],
    "sg:phone":"+44 1305 769900",
    "sg:postcode":"DT4 8AR",
    "sg:province":"Dorset",
    "sg:tags":[
        "taxi",
        "hire",
        "private"
    ],
    "wof:name":"Direct Taxis",
    "wof:placetype":"venue"
},
  "geometry": {"coordinates":[-2.454987,50.607658],"type":"Point"}
}