{
  "type": "Feature",
  "properties": {
    "addr:full":"Unit 23c Oak Rd, West Chirton North Inds North Shields Tyne and Wear NE29 8SF",
    "addr:housenumber":"unit 23c",
    "addr:postcode":"ne29 8sf",
    "addr:street":"Oak Rd West",
    "iso:country":"GB",
    "sg:address":"Unit 23c Oak Rd, West Chirton North Inds",
    "sg:city":"North Shields",
    "sg:classifiers":[
        {
            "category":"Shopping",
            "subcategory":"Gifts & Souvenirs",
            "type":"Retail Goods"
        }
    ],
    "sg:postcode":"NE29 8SF",
    "sg:province":"Tyne and Wear",
    "sg:tags":[
        "ducting"
    ],
    "wof:name":"Alliance (Ventilation) Systems Ltd",
    "wof:placetype":"venue"
},
  "geometry": {"coordinates":[-1.49151,55.016602],"type":"Point"}
}