{
  "type": "Feature",
  "properties": {
    "addr:full":"15 School Grn, Pontesbury Shrewsbury Shropshire SY5 0PR",
    "addr:housenumber":"15",
    "addr:postcode":"sy5 0pr",
    "addr:street":"School Grn",
    "iso:country":"GB",
    "sg:address":"15 School Grn, Pontesbury",
    "sg:city":"Shrewsbury",
    "sg:classifiers":[
        {
            "category":"Freight",
            "type":"Transportation"
        }
    ],
    "sg:postcode":"SY5 0PR",
    "sg:province":"Shropshire",
    "sg:tags":[
        "haulage",
        "road"
    ],
    "wof:name":"B & C Direct Deliveries Nationwide",
    "wof:placetype":"venue"
},
  "geometry": {"coordinates":[-2.8898611069,52.6486854553],"type":"Point"}
}