{
  "type": "Feature",
  "properties": {
    "addr:full":"School Farm, Church Road, Colmworth Bedford Bedfordshire MK44 2JX",
    "addr:postcode":"mk44 2jx",
    "addr:street":"Church Road",
    "iso:country":"GB",
    "sg:address":"School Farm, Church Road, Colmworth",
    "sg:city":"Bedford",
    "sg:classifiers":[
        {
            "category":"Home & Garden",
            "subcategory":"Garden Supply",
            "type":"Retail Goods"
        },
        {
            "category":"Farming",
            "subcategory":"Livestock Farm",
            "type":"Manufacturing & Wholesale Goods"
        }
    ],
    "sg:postcode":"MK44 2JX",
    "sg:province":"Bedfordshire",
    "sg:tags":[
        "bulb",
        "grower",
        "others"
    ],
    "wof:name":"J & V A Chamberlain",
    "wof:placetype":"venue"
},
  "geometry": {"coordinates":[-0.385804,52.211391],"type":"Point"}
}