{
  "type": "Feature",
  "properties": {
    "addr:full":"4 Heronswood Stafford Staffordshire ST17 4QE",
    "addr:housenumber":"4",
    "addr:postcode":"st17 4qe",
    "addr:street":"Heronswood",
    "iso:country":"GB",
    "sg:address":"4 Heronswood",
    "sg:city":"Stafford",
    "sg:classifiers":[
        {
            "category":"Home & Garden",
            "subcategory":"Household Appliances",
            "type":"Retail Goods"
        }
    ],
    "sg:phone":"+44 1785 661095",
    "sg:postcode":"ST17 4QE",
    "sg:province":"Staffordshire",
    "sg:tags":[
        "electrical"
    ],
    "wof:name":"BK Coldcraft",
    "wof:placetype":"venue"
},
  "geometry": {"coordinates":[-2.088091,52.789436],"type":"Point"}
}