{
  "type": "Feature",
  "properties": {
    "addr:full":"Sandy Lane Cobham Surrey KT11 2ES",
    "addr:postcode":"kt11 2es",
    "addr:street":"Sandy Lane",
    "iso:country":"GB",
    "sg:address":"Sandy Lane",
    "sg:city":"Cobham",
    "sg:classifiers":[
        {
            "category":"Organizations",
            "subcategory":"Non-profit Organization",
            "type":"Services"
        }
    ],
    "sg:phone":"+44 1932 868622",
    "sg:postcode":"KT11 2ES",
    "sg:province":"Surrey",
    "sg:tags":[
        "organisation",
        "voluntary",
        "charity"
    ],
    "wof:name":"Royal Wanstead Foundation",
    "wof:placetype":"venue"
},
  "geometry": {"coordinates":[-0.377353,51.340729],"type":"Point"}
}