{
  "type": "Feature",
  "properties": {
    "addr:full":"24 High Street, Barford Warwick Warwickshire CV35 8BU",
    "addr:housenumber":"24",
    "addr:postcode":"cv35 8bu",
    "addr:street":"High Street",
    "iso:country":"GB",
    "sg:address":"24 High Street, Barford",
    "sg:city":"Warwick",
    "sg:classifiers":[
        {
            "category":"Professional",
            "subcategory":"Art Services",
            "type":"Services"
        }
    ],
    "sg:phone":"+44 1926 624584",
    "sg:postcode":"CV35 8BU",
    "sg:province":"Warwickshire",
    "sg:tags":[
        "consultant",
        "design"
    ],
    "wof:name":"Sadler Studio",
    "wof:placetype":"venue"
},
  "geometry": {"coordinates":[-1.59849,52.248081],"type":"Point"}
}