{
  "type": "Feature",
  "properties": {
    "iso:country":"GB",
    "sg:address":"25a Brook Street",
    "sg:city":"Ilkley",
    "sg:classifiers":[
        {
            "category":"Professional",
            "subcategory":"Management & Consulting",
            "type":"Services"
        }
    ],
    "sg:phone":"+44 1943 816545",
    "sg:postcode":"LS29 8AA",
    "sg:province":"North Yorkshire",
    "sg:tags":[
        "consultant",
        "business"
    ],
    "wof:name":"The Laundry Technology Centre",
    "wof:placetype":"venue"
},
  "geometry": {"coordinates":[-1.8235750198,53.9255180359],"type":"Point"}
}