{
  "type": "Feature",
  "properties": {
    "addr:full":"Holbeach Manor, Fleet Road, Holbeach Spalding Cambridgeshire PE12 7AX",
    "addr:housenumber":"holbeach",
    "addr:postcode":"pe12 7ax",
    "addr:street":"Manor Fleet Road;Spalding",
    "iso:country":"GB",
    "sg:address":"Holbeach Manor, Fleet Road, Holbeach",
    "sg:city":"Spalding",
    "sg:classifiers":[
        {
            "category":"Building & Trades",
            "subcategory":"Construction",
            "type":"Services"
        }
    ],
    "sg:postcode":"PE12 7AX",
    "sg:province":"Cambridgeshire",
    "sg:tags":[
        "builder"
    ],
    "wof:name":"Kings Quality Homes",
    "wof:placetype":"venue"
},
  "geometry": {"coordinates":[0.0144999996,52.8039665222],"type":"Point"}
}