{
  "type": "Feature",
  "properties": {
    "addr:full":"Hazeldon Farm, Wardour, Tisbury Salisbury Wiltshire SP3 6RD",
    "addr:postcode":"sp3 6rd",
    "addr:street":"Wardour",
    "iso:country":"GB",
    "sg:address":"Hazeldon Farm, Wardour, Tisbury",
    "sg:city":"Salisbury",
    "sg:classifiers":[
        {
            "category":"Farming",
            "subcategory":"Farm",
            "type":"Manufacturing & Wholesale Goods"
        }
    ],
    "sg:postcode":"SP3 6RD",
    "sg:province":"Wiltshire",
    "sg:tags":[
        "mixed",
        "crop"
    ],
    "wof:name":"Burt,F J,",
    "wof:placetype":"venue"
},
  "geometry": {"coordinates":[-2.080324,51.066849],"type":"Point"}
}