{
  "type": "Feature",
  "properties": {
    "addr:full":"32a Central Road Worcester Park Surrey KT4 8HZ",
    "addr:housenumber":"32a",
    "addr:postcode":"kt4 8hz",
    "addr:street":"Central Road",
    "iso:country":"GB",
    "sg:address":"32a Central Road",
    "sg:city":"Worcester Park",
    "sg:classifiers":[
        {
            "category":"Recreation",
            "subcategory":"Gun Range",
            "type":"Entertainment"
        }
    ],
    "sg:postcode":"KT4 8HZ",
    "sg:province":"Surrey",
    "sg:tags":[
        "operator",
        "tour"
    ],
    "wof:name":"AIRSUN HOLIDAYS",
    "wof:placetype":"venue"
},
  "geometry": {"coordinates":[-0.238684997,51.3771743774],"type":"Point"}
}