{
  "type": "Feature",
  "properties": {
    "addr:full":"Chamusca Farm, Tharston Norwich Norfolk NR15 2YL",
    "addr:postcode":"nr15 2yl",
    "addr:street":"Tharston Norwich",
    "iso:country":"GB",
    "sg:address":"Chamusca Farm, Tharston",
    "sg:city":"Norwich",
    "sg:classifiers":[
        {
            "category":"Farming",
            "subcategory":"Dairy Farm",
            "type":"Manufacturing & Wholesale Goods"
        }
    ],
    "sg:postcode":"NR15 2YL",
    "sg:province":"Norfolk",
    "wof:name":"D G & J M Brighton",
    "wof:placetype":"venue"
},
  "geometry": {"coordinates":[1.2241309881,52.5041236877],"type":"Point"}
}