{
  "type": "Feature",
  "properties": {
    "iso:country":"GB",
    "sg:address":"53 Bradford Rd",
    "sg:city":"Shipley",
    "sg:classifiers":[
        {
            "category":"Fast Food",
            "type":"Food & Drink"
        }
    ],
    "sg:phone":"+44 1274 533253",
    "sg:postcode":"BD18 3DS",
    "sg:province":"West Yorkshire",
    "sg:tags":[
        "away",
        "take"
    ],
    "wof:name":"Basement Sandwich Shop,the",
    "wof:placetype":"venue"
},
  "geometry": {"coordinates":[-1.783077,53.831043],"type":"Point"}
}