{
  "type": "Feature",
  "properties": {
    "addr:full":"Newmarket Road Royston Bedfordshire SG8 7PN",
    "addr:postcode":"sg8 7pn",
    "addr:street":"Newmarket Road",
    "iso:country":"GB",
    "sg:address":"Newmarket Road",
    "sg:city":"Royston",
    "sg:classifiers":[
        {
            "category":"Travel",
            "subcategory":"Hotels & Motels",
            "type":"Entertainment"
        }
    ],
    "sg:phone":"+44 1763 208272",
    "sg:postcode":"SG8 7PN",
    "sg:province":"Bedfordshire",
    "wof:name":"The Aris Inn Hotel",
    "wof:placetype":"venue"
},
  "geometry": {"coordinates":[-0.0085,52.049217],"type":"Point"}
}