{
  "type": "Feature",
  "properties": {
    "iso:country":"GB",
    "sg:address":"840-842 Newport Rd",
    "sg:city":"Cardiff",
    "sg:classifiers":[
        {
            "category":"Health Services",
            "subcategory":"Doctor",
            "type":"Services"
        }
    ],
    "sg:phone":"+44 29 2079 7751",
    "sg:postcode":"CF3 8LH",
    "sg:province":"Caerphilly",
    "sg:tags":[
        "practitioners"
    ],
    "wof:name":"Corbett, J",
    "wof:placetype":"venue"
},
  "geometry": {"coordinates":[-3.129634,51.50996],"type":"Point"}
}