{
  "type": "Feature",
  "properties": {
    "addr:full":"402 Farnham Road Slough Berkshire SL2 1JD",
    "addr:housenumber":"402",
    "addr:postcode":"sl2 1jd",
    "addr:street":"Farnham Road",
    "iso:country":"GB",
    "sg:address":"402 Farnham Road",
    "sg:city":"Slough",
    "sg:classifiers":[
        {
            "category":"Food & Beverages",
            "subcategory":"Liquor & Beverages",
            "type":"Retail Goods"
        }
    ],
    "sg:phone":"+44 1753 575559",
    "sg:postcode":"SL2 1JD",
    "sg:province":"Berkshire",
    "sg:tags":[
        "beer",
        "wine",
        "spirit",
        "wines"
    ],
    "wof:name":"One Stop Liquor Store",
    "wof:placetype":"venue"
},
  "geometry": {"coordinates":[-0.6165789962,51.5286750793],"type":"Point"}
}