{
  "type": "Feature",
  "properties": {
    "addr:full":"Berkeley House, Falcon Close, Quedgeley Gloucester Gloucestershire GL2 4LY",
    "addr:postcode":"gl2 4ly",
    "addr:street":"Falcon Close",
    "iso:country":"GB",
    "sg:address":"Berkeley House, Falcon Close, Quedgeley",
    "sg:city":"Gloucester",
    "sg:classifiers":[
        {
            "category":"Bars & Pubs",
            "type":"Food & Drink"
        }
    ],
    "sg:phone":"+44 1452 887222",
    "sg:postcode":"GL2 4LY",
    "sg:province":"Gloucestershire",
    "sg:tags":[
        "pubs",
        "inn"
    ],
    "wof:name":"Mill House Inns (Leaseholds) Ltd.",
    "wof:placetype":"venue"
},
  "geometry": {"coordinates":[-2.278019,51.833565],"type":"Point"}
}