{
  "type": "Feature",
  "properties": {
    "addr:full":"Hill Top Farm, Main Street, Catcliffe Rotherham South Yorkshire S60 5SR",
    "addr:postcode":"s60 5sr",
    "addr:street":"Main Street",
    "iso:country":"GB",
    "sg:address":"Hill Top Farm, Main Street, Catcliffe",
    "sg:city":"Rotherham",
    "sg:classifiers":[
        {
            "category":"Home & Garden",
            "subcategory":"Home Furnishings",
            "type":"Retail Goods"
        }
    ],
    "sg:phone":"+44 1709 371326",
    "sg:postcode":"S60 5SR",
    "sg:province":"South Yorkshire",
    "sg:tags":[
        "furnishers",
        "planner",
        "kitchen"
    ],
    "wof:name":"Hilltop Kitchens",
    "wof:placetype":"venue"
},
  "geometry": {"coordinates":[-1.361244,53.392403],"type":"Point"}
}