{
  "type": "Feature",
  "properties": {
    "addr:full":"98-100 High Street Sidmouth Devon EX10 8EF",
    "addr:housenumber":"98-100",
    "addr:postcode":"ex10 8ef",
    "addr:street":"High Street",
    "iso:country":"GB",
    "sg:address":"98-100 High Street",
    "sg:city":"Sidmouth",
    "sg:classifiers":[
        {
            "category":"Real Estate",
            "subcategory":"Real Estate Agent",
            "type":"Services"
        }
    ],
    "sg:phone":"+44 1395 512552",
    "sg:postcode":"EX10 8EF",
    "sg:province":"Devon",
    "wof:name":"Peter Eley",
    "wof:placetype":"venue"
},
  "geometry": {"coordinates":[-3.237842,50.681755],"type":"Point"}
}