{
  "type": "Feature",
  "properties": {
    "addr:full":"6 Brinkley Way Felixstowe Suffolk IP11 9TX",
    "addr:housenumber":"6",
    "addr:postcode":"ip11 9tx",
    "addr:street":"Brinkley Way",
    "iso:country":"GB",
    "sg:address":"6 Brinkley Way",
    "sg:city":"Felixstowe",
    "sg:classifiers":[
        {
            "category":"Freight",
            "type":"Transportation"
        },
        {
            "category":"Professional",
            "subcategory":"Business Services",
            "type":"Services"
        }
    ],
    "sg:phone":"+44 1394 272725",
    "sg:postcode":"IP11 9TX",
    "sg:province":"Suffolk",
    "sg:tags":[
        "import",
        "export",
        "agent",
        "forwarders"
    ],
    "wof:name":"Trax Cargo Ltd",
    "wof:placetype":"venue"
},
  "geometry": {"coordinates":[1.375835,51.977325],"type":"Point"}
}