{
  "type": "Feature",
  "properties": {
    "iso:country":"GB",
    "sg:address":"81 Gipsy Lane",
    "sg:city":"Leicester",
    "sg:classifiers":[
        {
            "category":"Organizations",
            "subcategory":"Community Association",
            "type":"Services"
        }
    ],
    "sg:phone":"+44 116 266 1439",
    "sg:postcode":"LE4 6RH",
    "sg:province":"Leicestershire",
    "sg:tags":[
        "co-operatives",
        "society",
        "housing",
        "trust"
    ],
    "wof:name":"William Sutton Trust",
    "wof:placetype":"venue"
},
  "geometry": {"coordinates":[-1.106935,52.654804],"type":"Point"}
}