{
  "type": "Feature",
  "properties": {
    "addr:full":"Units 2/3 Littletowns Industrial Estate, Blandford Heights Blandford Forum Dorset DT11 7RU",
    "addr:housenumber":"units 2 / 3",
    "addr:postcode":"dorset dt11 7ru",
    "addr:street":"Littletowns Industrial Estate",
    "iso:country":"GB",
    "sg:address":"Units 2/3 Littletowns Industrial Estate, Blandford Heights",
    "sg:city":"Blandford Forum",
    "sg:classifiers":[
        {
            "category":"Military Area",
            "subcategory":"Air Force Base",
            "type":"Public Place"
        }
    ],
    "sg:phone":"+44 1258 456832",
    "sg:postcode":"DT11 7RU",
    "sg:province":"Dorset",
    "sg:tags":[
        "taxi",
        "hire",
        "private"
    ],
    "wof:name":"Blandford Belvedere Taxis",
    "wof:placetype":"venue"
},
  "geometry": {"coordinates":[-2.158819,50.862644],"type":"Point"}
}