{
  "type": "Feature",
  "properties": {
    "addr:full":"Scurragh Lane, Skeeby Richmond North Yorkshire DL10 5EF",
    "addr:postcode":"dl10 5ef",
    "addr:street":"Scurragh Lane",
    "iso:country":"GB",
    "sg:address":"Scurragh Lane, Skeeby",
    "sg:city":"Richmond",
    "sg:classifiers":[
        {
            "category":"Travel",
            "subcategory":"Hotels & Motels",
            "type":"Entertainment"
        }
    ],
    "sg:postcode":"DL10 5EF",
    "sg:province":"North Yorkshire",
    "sg:tags":[
        "house",
        "guest"
    ],
    "wof:name":"Skeeby Lodge",
    "wof:placetype":"venue"
},
  "geometry": {"coordinates":[-1.6830170155,54.424697876],"type":"Point"}
}