{
  "type": "Feature",
  "properties": {
    "addr:full":"Unit 5 Kings Road Melton Mowbray Leicestershire LE13 1QF",
    "addr:housenumber":"unit 5",
    "addr:postcode":"le13 1qf",
    "addr:street":"Kings Road",
    "iso:country":"GB",
    "sg:address":"Unit 5 Kings Road",
    "sg:city":"Melton Mowbray",
    "sg:classifiers":[
        {
            "category":"Sports & Exercise",
            "subcategory":"Tennis Court",
            "type":"Entertainment"
        }
    ],
    "sg:phone":"+44 1664 411854",
    "sg:postcode":"LE13 1QF",
    "sg:province":"Leicestershire",
    "sg:tags":[
        "breakdown",
        "recovery"
    ],
    "wof:name":"Ponton Main Services",
    "wof:placetype":"venue"
},
  "geometry": {"coordinates":[-0.878359,52.767891],"type":"Point"}
}