{
  "type": "Feature",
  "properties": {
    "iso:country":"GB",
    "sg:address":"7 Eastgate",
    "sg:city":"Aberystwyth",
    "sg:classifiers":[
        {
            "category":"Personal",
            "subcategory":"Beauty Salon",
            "type":"Services"
        },
        {
            "category":"Personal",
            "subcategory":"Barber",
            "type":"Services"
        }
    ],
    "sg:phone":"+44 1970 623414",
    "sg:postcode":"SY23 2AR",
    "sg:province":"Ceredigion",
    "sg:tags":[
        "unisex",
        "hairdresser"
    ],
    "wof:name":"Thatch Hairdressers",
    "wof:placetype":"venue"
},
  "geometry": {"coordinates":[-4.085045,52.415592],"type":"Point"}
}