{
  "type": "Feature",
  "properties": {
    "addr:full":"The Coach House, 1a Tyn-y-coed Place, Roath Cardiff Cardiff CF24 4TX",
    "addr:housenumber":"1a",
    "addr:postcode":"cf24 4tx",
    "addr:street":"Tyn-Y-Coed Place",
    "iso:country":"GB",
    "sg:address":"The Coach House, 1a Tyn-y-coed Place, Roath",
    "sg:city":"Cardiff",
    "sg:classifiers":[
        {
            "category":"Real Estate",
            "subcategory":"Developer",
            "type":"Services"
        }
    ],
    "sg:postcode":"CF24 4TX",
    "sg:province":"Cardiff",
    "sg:tags":[
        "property"
    ],
    "wof:name":"S W Developments Ltd.",
    "wof:placetype":"venue"
},
  "geometry": {"coordinates":[-3.172262,51.497124],"type":"Point"}
}