{
  "type": "Feature",
  "properties": {
    "iso:country":"GB",
    "sg:address":"New Hill, Walesby",
    "sg:city":"Newark",
    "sg:classifiers":[
        {
            "category":"Government",
            "subcategory":"City Hall",
            "type":"Public Place"
        },
        {
            "category":"Retail",
            "subcategory":"Event Space",
            "type":"Services"
        }
    ],
    "sg:phone":"+44 1623 835463",
    "sg:postcode":"NG22 9PB",
    "sg:province":"Nottinghamshire",
    "sg:tags":[
        "function",
        "hire",
        "room"
    ],
    "wof:name":"Walesby Village Hall",
    "wof:placetype":"venue"
},
  "geometry": {"coordinates":[-0.983429,53.229553],"type":"Point"}
}