{
  "type": "Feature",
  "properties": {
    "iso:country":"GB",
    "sg:address":"Priory Chambers",
    "sg:city":"Weybridge",
    "sg:classifiers":[
        {
            "category":"Professional",
            "subcategory":"Management & Consulting",
            "type":"Services"
        }
    ],
    "sg:phone":"+44 1932 828354",
    "sg:postcode":"KT13 8DQ",
    "sg:province":"Surrey",
    "sg:tags":[
        "consultant",
        "business"
    ],
    "wof:name":"Sales & Marketing Associates Ltd.",
    "wof:placetype":"venue"
},
  "geometry": {"coordinates":[-0.4580650032,51.3727493286],"type":"Point"}
}