{
  "type": "Feature",
  "properties": {
    "addr:full":"College Rd Skelmersdale Lancashire WN8 0PZ",
    "addr:postcode":"wn8 0pz",
    "addr:street":"College Rd",
    "iso:country":"GB",
    "sg:address":"College Rd",
    "sg:city":"Skelmersdale",
    "sg:classifiers":[
        {
            "category":"Place Of Worship",
            "type":"Public Place"
        }
    ],
    "sg:phone":"+44 1695 625255",
    "sg:postcode":"WN8 0PZ",
    "sg:province":"Lancashire",
    "wof:name":"St Josephs Upholland",
    "wof:placetype":"venue"
},
  "geometry": {"coordinates":[-2.726669,53.549541],"type":"Point"}
}