{
  "type": "Feature",
  "properties": {
    "addr:full":"Church Street, Eckington Sheffield Derbyshire S21 4BH",
    "addr:postcode":"s21 4bh",
    "addr:street":"Church Street",
    "iso:country":"GB",
    "sg:address":"Church Street, Eckington",
    "sg:city":"Sheffield",
    "sg:classifiers":[
        {
            "category":"Shopping",
            "subcategory":"Computers & Home Electronics",
            "type":"Retail Goods"
        }
    ],
    "sg:phone":"+44 1246 436361",
    "sg:postcode":"S21 4BH",
    "sg:province":"Derbyshire",
    "sg:tags":[
        "electrical"
    ],
    "wof:name":"Bradley Lomas Electrolok Ltd.",
    "wof:placetype":"venue"
},
  "geometry": {"coordinates":[-1.3642810583,53.3077774048],"type":"Point"}
}