{
  "type": "Feature",
  "properties": {
    "addr:full":"Vulcan Road South Norwich Norfolk NR6 6AF",
    "addr:postcode":"nr6 6af",
    "addr:street":"Vulcan Road South Norwich Norfolk",
    "iso:country":"GB",
    "sg:address":"Vulcan Road South",
    "sg:city":"Norwich",
    "sg:classifiers":[
        {
            "category":"Shopping",
            "type":"Retail Goods"
        }
    ],
    "sg:postcode":"NR6 6AF",
    "sg:province":"Norfolk",
    "sg:tags":[
        "part",
        "accessory"
    ],
    "wof:name":"C T C Autofashion",
    "wof:placetype":"venue"
},
  "geometry": {"coordinates":[1.2842400074,52.6607551575],"type":"Point"}
}