{
  "type": "Feature",
  "properties": {
    "iso:country":"GB",
    "sg:address":"1 Fountains Way",
    "sg:city":"Brough",
    "sg:classifiers":[
        {
            "category":"Shopping",
            "subcategory":"Stationery & Office Supplies",
            "type":"Retail Goods"
        }
    ],
    "sg:phone":"+44 1430 424788",
    "sg:postcode":"HU15 2NW",
    "sg:province":"East Riding of Yorkshire",
    "sg:tags":[
        "printers'"
    ],
    "wof:name":"Humberside Offset Services",
    "wof:placetype":"venue"
},
  "geometry": {"coordinates":[-0.642194,53.779266],"type":"Point"}
}