{
  "type": "Feature",
  "properties": {
    "addr:full":"Unit 7/9 Stanley Lane Industrial, Estate Stanley L Bridgnorth Shropshire WV16 4SF",
    "addr:housenumber":"unit 7 / 9;estate",
    "addr:postcode":"wv16 4sf",
    "addr:street":"Stanley Lane Industrial;Stanley L Bridgnorth",
    "iso:country":"GB",
    "sg:address":"Unit 7/9 Stanley Lane Industrial, Estate Stanley L",
    "sg:city":"Bridgnorth",
    "sg:classifiers":[
        {
            "category":"Professional",
            "subcategory":"Engineering",
            "type":"Services"
        }
    ],
    "sg:phone":"+44 1746 766154",
    "sg:postcode":"WV16 4SF",
    "sg:province":"Shropshire",
    "sg:tags":[
        "precision",
        "engineer"
    ],
    "wof:name":"Catherwell Engineering Co. Ltd.",
    "wof:placetype":"venue"
},
  "geometry": {"coordinates":[-2.413145,52.547783],"type":"Point"}
}