{
  "type": "Feature",
  "properties": {
    "iso:country":"GB",
    "sg:address":"63 Queens Rd",
    "sg:city":"Walton On Thames",
    "sg:classifiers":[
        {
            "category":"Place Of Worship",
            "type":"Public Place"
        }
    ],
    "sg:phone":"+44 1932 223244",
    "sg:postcode":"KT12 5NF",
    "sg:province":"Surrey",
    "wof:name":"Trinity United Reformed Church",
    "wof:placetype":"venue"
},
  "geometry": {"coordinates":[-0.405204,51.367573],"type":"Point"}
}