{
  "type": "Feature",
  "properties": {
    "iso:country":"GB",
    "sg:address":"Unit 3/5 Corse Industrial Estate, Gloucester Road, Staunton",
    "sg:city":"Gloucester",
    "sg:classifiers":[
        {
            "category":"Shopping",
            "subcategory":"Optical Goods",
            "type":"Retail Goods"
        }
    ],
    "sg:phone":"+44 1452 840771",
    "sg:postcode":"GL19 3RD",
    "sg:province":"Gloucestershire",
    "wof:name":"Sinclair Optical Services Co. Ltd.",
    "wof:placetype":"venue"
},
  "geometry": {"coordinates":[-2.3044140339,51.9583244324],"type":"Point"}
}