{
  "type": "Feature",
  "properties": {
    "addr:full":"15-17 Portland Pl Stalybridge Greater Manchester SK15 3AD",
    "addr:housenumber":"15-17",
    "addr:postcode":"sk15 3ad",
    "addr:street":"Portland Pl",
    "iso:country":"GB",
    "sg:address":"15-17 Portland Pl",
    "sg:city":"Stalybridge",
    "sg:classifiers":[
        {
            "category":"Professional",
            "subcategory":"Lawyer & Legal Services",
            "type":"Services"
        }
    ],
    "sg:phone":"+44 161 303 7895",
    "sg:postcode":"SK15 3AD",
    "sg:province":"Greater Manchester",
    "sg:tags":[
        "solicitor"
    ],
    "wof:name":"Yates Ardern",
    "wof:placetype":"venue"
},
  "geometry": {"coordinates":[-2.0526530743,53.483757019],"type":"Point"}
}