{
  "type": "Feature",
  "properties": {
    "addr:full":"9 Canterbury Road Margate Kent CT9 5AQ",
    "addr:housenumber":"9",
    "addr:postcode":"ct9 5aq",
    "addr:street":"Canterbury Road",
    "iso:country":"GB",
    "sg:address":"9 Canterbury Road",
    "sg:city":"Margate",
    "sg:classifiers":[
        {
            "category":"Travel",
            "subcategory":"Hotels & Motels",
            "type":"Entertainment"
        }
    ],
    "sg:phone":"+44 1843 224401",
    "sg:postcode":"CT9 5AQ",
    "sg:province":"Kent",
    "wof:name":"SOMERVILLE HOTEL",
    "wof:placetype":"venue"
},
  "geometry": {"coordinates":[1.371055,51.386372],"type":"Point"}
}