{
  "type": "Feature",
  "properties": {
    "addr:full":"3 Flemingate Beverley East Riding of Yorkshire HU17 0NP",
    "addr:housenumber":"3",
    "addr:postcode":"hu17 0np",
    "addr:street":"Flemingate Beverley",
    "iso:country":"GB",
    "sg:address":"3 Flemingate",
    "sg:city":"Beverley",
    "sg:classifiers":[
        {
            "category":"Shopping",
            "subcategory":"News",
            "type":"Retail Goods"
        }
    ],
    "sg:phone":"+44 1482 882653",
    "sg:postcode":"HU17 0NP",
    "sg:province":"East Riding of Yorkshire",
    "sg:tags":[
        "newsagent"
    ],
    "wof:name":"Minster News & Tackle",
    "wof:placetype":"venue"
},
  "geometry": {"coordinates":[-0.4233399928,53.8393058777],"type":"Point"}
}