{
  "type": "Feature",
  "properties": {
    "addr:full":"I Brickyard Cotts, Redwall Lane, Hunton Maidstone Kent ME15 0RJ",
    "addr:postcode":"me15 0rj",
    "addr:street":"Redwall Lane",
    "iso:country":"GB",
    "sg:address":"I Brickyard Cotts, Redwall Lane, Hunton",
    "sg:city":"Maidstone",
    "sg:classifiers":[
        {
            "category":"Professional",
            "subcategory":"Computer Services",
            "type":"Services"
        }
    ],
    "sg:phone":"+44 1622 820688",
    "sg:postcode":"ME15 0RJ",
    "sg:province":"Kent",
    "sg:tags":[
        "consultant"
    ],
    "wof:name":"Systems Analysis Design & Support Ltd.",
    "wof:placetype":"venue"
},
  "geometry": {"coordinates":[0.4585449994,51.2175064087],"type":"Point"}
}