{
  "type": "Feature",
  "properties": {
    "iso:country":"GB",
    "sg:address":"77 Church Rd",
    "sg:city":"Ashford",
    "sg:classifiers":[
        {
            "category":"Real Estate",
            "subcategory":"Real Estate Agent",
            "type":"Services"
        }
    ],
    "sg:phone":"+44 1784 252202",
    "sg:postcode":"TW15 2PE",
    "sg:province":"Greater London",
    "wof:name":"Aspen Estate Agents",
    "wof:placetype":"venue"
},
  "geometry": {"coordinates":[-0.4600819945,51.4321289062],"type":"Point"}
}