{
  "type": "Feature",
  "properties": {
    "iso:country":"GB",
    "sg:address":"Water Lane",
    "sg:city":"Lowestoft",
    "sg:classifiers":[
        {
            "category":"Community Center",
            "type":"Public Place"
        }
    ],
    "sg:phone":"+44 1502 569116",
    "sg:postcode":"NR32 2NH",
    "sg:province":"Suffolk",
    "sg:tags":[
        "recreation",
        "leisure",
        "centre"
    ],
    "sg:website":"http://www.waveney.gov.uk",
    "wof:name":"Waveney Sports & Leisure Centre",
    "wof:placetype":"venue"
},
  "geometry": {"coordinates":[1.7463350296,52.4831085205],"type":"Point"}
}