{
  "type": "Feature",
  "properties": {
    "addr:full":"238 Canterbury Road Margate Kent CT9 5JB",
    "addr:housenumber":"238",
    "addr:postcode":"ct9 5jb",
    "addr:street":"Canterbury Road",
    "iso:country":"GB",
    "sg:address":"238 Canterbury Road",
    "sg:city":"Margate",
    "sg:classifiers":[
        {
            "category":"Education",
            "subcategory":"Library",
            "type":"Public Place"
        },
        {
            "category":"Manufacturing",
            "subcategory":"Furniture",
            "type":"Manufacturing & Wholesale Goods"
        }
    ],
    "sg:phone":"+44 1843 832186",
    "sg:postcode":"CT9 5JB",
    "sg:province":"Kent",
    "sg:tags":[
        "reproduction"
    ],
    "wof:name":"C D MCCARTHY",
    "wof:placetype":"venue"
},
  "geometry": {"coordinates":[1.371055,51.386372],"type":"Point"}
}