{
  "type": "Feature",
  "properties": {
    "iso:country":"GB",
    "sg:address":"32 Trinity Road, Rothwell",
    "sg:city":"Kettering",
    "sg:classifiers":[
        {
            "category":"Professional",
            "subcategory":"Art Services",
            "type":"Services"
        }
    ],
    "sg:phone":"+44 1536 712601",
    "sg:postcode":"NN14 6HY",
    "sg:province":"Northamptonshire",
    "sg:tags":[
        "consultant",
        "design"
    ],
    "wof:name":"Zeller Design",
    "wof:placetype":"venue"
},
  "geometry": {"coordinates":[-0.811678,52.419384],"type":"Point"}
}