{
  "type": "Feature",
  "properties": {
    "iso:country":"GB",
    "sg:address":"189 Nottingham Road, Somercotes",
    "sg:city":"Alfreton",
    "sg:classifiers":[
        {
            "category":"Cinema",
            "subcategory":"Movie Rental",
            "type":"Entertainment"
        }
    ],
    "sg:phone":"+44 1773 540755",
    "sg:postcode":"DE55 4JG",
    "sg:province":"Derbyshire",
    "sg:tags":[
        "video",
        "library"
    ],
    "wof:name":"Premiere Video Hire",
    "wof:placetype":"venue"
},
  "geometry": {"coordinates":[-1.3696449995,53.0809211731],"type":"Point"}
}