{
  "type": "Feature",
  "properties": {
    "addr:full":"September Lodge, Potash Rd Harlow Essex CM17 0QF",
    "addr:postcode":"cm17 0qf",
    "addr:street":"Potash Rd",
    "iso:country":"GB",
    "sg:address":"September Lodge, Potash Rd",
    "sg:city":"Harlow",
    "sg:classifiers":[
        {
            "category":"Shopping",
            "subcategory":"Florist",
            "type":"Retail Goods"
        }
    ],
    "sg:phone":"+44 1279 731285",
    "sg:postcode":"CM17 0QF",
    "sg:province":"Essex",
    "wof:name":"Edwins",
    "wof:placetype":"venue"
},
  "geometry": {"coordinates":[0.2269099951,51.7782096863],"type":"Point"}
}