{
  "type": "Feature",
  "properties": {
    "iso:country":"GB",
    "sg:address":"33 Kingsley Cres, Armthorpe",
    "sg:city":"Doncaster",
    "sg:classifiers":[
        {
            "category":"Building & Trades",
            "subcategory":"Landscaping Services",
            "type":"Services"
        }
    ],
    "sg:postcode":"DN3 3JG",
    "sg:province":"South Yorkshire",
    "sg:tags":[
        "gardening"
    ],
    "wof:name":"Bennett,Robert E,",
    "wof:placetype":"venue"
},
  "geometry": {"coordinates":[-1.049804,53.535526],"type":"Point"}
}