{
  "type": "Feature",
  "properties": {
    "iso:country":"GB",
    "sg:address":"Bridge House, 1 Stuart Road, Budbury",
    "sg:city":"Stockport",
    "sg:classifiers":[
        {
            "category":"Professional",
            "subcategory":"Engineering",
            "type":"Services"
        }
    ],
    "sg:phone":"+44 161 292 9004",
    "sg:postcode":"SK6 2QN",
    "sg:province":"Cheshire",
    "sg:tags":[
        "electrical",
        "engineer"
    ],
    "wof:name":"Chambers O'Neill Ltd.",
    "wof:placetype":"venue"
},
  "geometry": {"coordinates":[-2.122784,53.43121],"type":"Point"}
}