{
  "type": "Feature",
  "properties": {
    "addr:full":"95 Deansgate Manchester Greater Manchester M3 2BQ",
    "addr:housenumber":"95",
    "addr:postcode":"m3 2bq",
    "addr:street":"Deansgate",
    "iso:country":"GB",
    "sg:address":"95 Deansgate",
    "sg:city":"Manchester",
    "sg:classifiers":[
        {
            "category":"Coffee & Tea",
            "type":"Food & Drink"
        }
    ],
    "sg:phone":"+44 161 839 6102",
    "sg:postcode":"M3 2BQ",
    "sg:province":"Greater Manchester",
    "wof:name":"Whittards of Chelsea Ltd",
    "wof:placetype":"venue"
},
  "geometry": {"coordinates":[-2.24761796,53.4813461304],"type":"Point"}
}