{
  "type": "Feature",
  "properties": {
    "iso:country":"GB",
    "sg:address":"Downham Road",
    "sg:city":"Ely",
    "sg:classifiers":[
        {
            "category":"Education",
            "subcategory":"University",
            "type":"Public Place"
        }
    ],
    "sg:phone":"+44 1353 667763",
    "sg:postcode":"CB6 1BD",
    "sg:province":"Cambridgeshire",
    "sg:tags":[
        "higher"
    ],
    "wof:name":"Ely Sixth Form Centre",
    "wof:placetype":"venue"
},
  "geometry": {"coordinates":[0.257082,52.404392],"type":"Point"}
}