{
  "type": "Feature",
  "properties": {
    "addr:full":"111 Green Street London Greater London E7 8JF",
    "addr:housenumber":"111",
    "addr:postcode":"e7 8jf",
    "addr:street":"Green Street",
    "iso:country":"GB",
    "sg:address":"111 Green Street",
    "sg:city":"London",
    "sg:classifiers":[
        {
            "category":"Real Estate",
            "subcategory":"Developer",
            "type":"Services"
        }
    ],
    "sg:phone":"+44 20 8472 7827",
    "sg:postcode":"E7 8JF",
    "sg:province":"Greater London",
    "sg:tags":[
        "property"
    ],
    "wof:name":"Progressive Property Investments",
    "wof:placetype":"venue"
},
  "geometry": {"coordinates":[0.0322670005,51.5443763733],"type":"Point"}
}