{
  "type": "Feature",
  "properties": {
    "iso:country":"GB",
    "sg:address":"170 East Road",
    "sg:city":"Cambridge",
    "sg:classifiers":[
        {
            "category":"Community Center",
            "type":"Public Place"
        }
    ],
    "sg:phone":"+44 1223 508533",
    "sg:postcode":"CB1 1DB",
    "sg:province":"Cambridgeshire",
    "sg:tags":[
        "centre",
        "entertainment"
    ],
    "wof:name":"The Boat Race",
    "wof:placetype":"venue"
},
  "geometry": {"coordinates":[0.134062,52.20533],"type":"Point"}
}