{
  "type": "Feature",
  "properties": {
    "addr:full":"82 Holmfield Road Blackpool Lancashire FY2 9RS",
    "addr:housenumber":"82",
    "addr:postcode":"fy2 9rs",
    "addr:street":"Holmfield Road",
    "iso:country":"GB",
    "sg:address":"82 Holmfield Road",
    "sg:city":"Blackpool",
    "sg:classifiers":[
        {
            "category":"Home & Garden",
            "subcategory":"Hardware",
            "type":"Retail Goods"
        }
    ],
    "sg:phone":"+44 1253 354869",
    "sg:postcode":"FY2 9RS",
    "sg:province":"Lancashire",
    "wof:name":"Colin E Briggs",
    "wof:placetype":"venue"
},
  "geometry": {"coordinates":[-3.052499,53.838196],"type":"Point"}
}