{
  "type": "Feature",
  "properties": {
    "addr:full":"133 Caerleon Road Newport Newport NP19 7BZ",
    "addr:housenumber":"133",
    "addr:postcode":"np19 7bz",
    "addr:street":"Caerleon Road",
    "iso:country":"GB",
    "sg:address":"133 Caerleon Road",
    "sg:city":"Newport",
    "sg:classifiers":[
        {
            "category":"Autos & Motor Vehicles",
            "subcategory":"Motorcycle Sales",
            "type":"Retail Goods"
        }
    ],
    "sg:postcode":"NP19 7BZ",
    "sg:province":"Newport",
    "wof:name":"Ken Roberts (Motor Cycles)",
    "wof:placetype":"venue"
},
  "geometry": {"coordinates":[-2.983232975,51.5955848694],"type":"Point"}
}