{
  "type": "Feature",
  "properties": {
    "iso:country":"GB",
    "sg:address":"6 Brunnel Way",
    "sg:city":"Glasgow",
    "sg:classifiers":[
        {
            "category":"Farming",
            "subcategory":"Nursery",
            "type":"Manufacturing & Wholesale Goods"
        },
        {
            "category":"Social Services",
            "subcategory":"Child Care",
            "type":"Services"
        }
    ],
    "sg:phone":"+44 1355 227711",
    "sg:postcode":"G75 0LD",
    "sg:province":"South Lanarkshire",
    "sg:tags":[
        "creche"
    ],
    "wof:name":"Harlequin Kindergarten",
    "wof:placetype":"venue"
},
  "geometry": {"coordinates":[-4.171267,55.756474],"type":"Point"}
}