{
  "type": "Feature",
  "properties": {
    "iso:country":"GB",
    "sg:address":"17 Lyndhurst Avenue",
    "sg:city":"Sunbury-on-thames",
    "sg:classifiers":[
        {
            "category":"Banks & Credit Unions",
            "subcategory":"Financial Services",
            "type":"Services"
        }
    ],
    "sg:postcode":"TW16 6QZ",
    "sg:province":"Surrey",
    "sg:tags":[
        "consultant"
    ],
    "wof:name":"T M C Development Finance Ltd.",
    "wof:placetype":"venue"
},
  "geometry": {"coordinates":[-0.416006,51.407486],"type":"Point"}
}