{
  "type": "Feature",
  "properties": {
    "addr:full":"80 Meredith Rd Stevenage Hertfordshire SG1 5QS",
    "addr:housenumber":"80",
    "addr:postcode":"sg1 5qs",
    "addr:street":"Meredith Rd",
    "iso:country":"GB",
    "sg:address":"80 Meredith Rd",
    "sg:city":"Stevenage",
    "sg:classifiers":[
        {
            "category":"Real Estate",
            "subcategory":"Developer",
            "type":"Services"
        }
    ],
    "sg:phone":"+44 1438 724509",
    "sg:postcode":"SG1 5QS",
    "sg:province":"Hertfordshire",
    "sg:tags":[
        "calligrapher"
    ],
    "wof:name":"Peter Good",
    "wof:placetype":"venue"
},
  "geometry": {"coordinates":[-0.1833429933,51.9140625],"type":"Point"}
}