{
  "type": "Feature",
  "properties": {
    "iso:country":"GB",
    "sg:address":"6 Sunny Bank",
    "sg:city":"Worksop",
    "sg:classifiers":[
        {
            "category":"Retail",
            "subcategory":"Driving School",
            "type":"Services"
        }
    ],
    "sg:postcode":"S81 0BG",
    "sg:province":"Nottinghamshire",
    "wof:name":"Street Wise",
    "wof:placetype":"venue"
},
  "geometry": {"coordinates":[-1.1126029491,53.3121109009],"type":"Point"}
}