{
  "type": "Feature",
  "properties": {
    "iso:country":"GB",
    "sg:address":"1 Lyon Street",
    "sg:city":"Bognor Regis",
    "sg:classifiers":[
        {
            "category":"Building & Trades",
            "subcategory":"Construction",
            "type":"Services"
        }
    ],
    "sg:postcode":"PO20 1JG",
    "sg:province":"West Sussex",
    "sg:tags":[
        "roofing"
    ],
    "wof:name":"The Monumental Co.",
    "wof:placetype":"venue"
},
  "geometry": {"coordinates":[-0.674359,50.78627],"type":"Point"}
}