{
  "type": "Feature",
  "properties": {
    "iso:country":"GB",
    "sg:address":"The Auction Ho's Station Road, Stokesley",
    "sg:city":"Middlesbrough",
    "sg:classifiers":[
        {
            "category":"Professional",
            "type":"Services"
        }
    ],
    "sg:phone":"+44 1642 710158",
    "sg:postcode":"TS9 7AB",
    "sg:province":"North Yorkshire",
    "sg:tags":[
        "auctioneer"
    ],
    "wof:name":"Lithgow Sons & Partners",
    "wof:placetype":"venue"
},
  "geometry": {"coordinates":[-1.18087,54.45977],"type":"Point"}
}