{
  "type": "Feature",
  "properties": {
    "addr:full":"Gate End, Low Burgage, Winteringham Scunthorpe Lincolnshire DN15 9PF",
    "addr:postcode":"dn15 9pf",
    "addr:street":"Gate",
    "iso:country":"GB",
    "sg:address":"Gate End, Low Burgage, Winteringham",
    "sg:city":"Scunthorpe",
    "sg:classifiers":[
        {
            "category":"Travel",
            "subcategory":"Hotels & Motels",
            "type":"Entertainment"
        }
    ],
    "sg:phone":"+44 1724 733096",
    "sg:postcode":"DN15 9PF",
    "sg:province":"Lincolnshire",
    "wof:name":"Winteringham Fields Restaurant",
    "wof:placetype":"venue"
},
  "geometry": {"coordinates":[-0.590726,53.687515],"type":"Point"}
}