{
  "type": "Feature",
  "properties": {
    "addr:full":"33 Severn Close, Stretton Burton-on-trent Derbyshire DE13 0YB",
    "addr:housenumber":"33",
    "addr:postcode":"de13 0yb",
    "addr:street":"Severn Close",
    "iso:country":"GB",
    "sg:address":"33 Severn Close, Stretton",
    "sg:city":"Burton-on-trent",
    "sg:classifiers":[
        {
            "category":"Professional",
            "subcategory":"Lawyer & Legal Services",
            "type":"Services"
        }
    ],
    "sg:phone":"+44 1283 542219",
    "sg:postcode":"DE13 0YB",
    "sg:province":"Derbyshire",
    "wof:name":"Search Partnership Ltd.",
    "wof:placetype":"venue"
},
  "geometry": {"coordinates":[-1.643194,52.834476],"type":"Point"}
}