{
  "type": "Feature",
  "properties": {
    "addr:full":"Lakeside Care Centre, Chapel Rd Ashford Kent TN25 4LN",
    "addr:postcode":"tn25 4ln",
    "addr:street":"Chapel Rd",
    "iso:country":"GB",
    "sg:address":"Lakeside Care Centre, Chapel Rd",
    "sg:city":"Ashford",
    "sg:classifiers":[
        {
            "category":"Social Services",
            "subcategory":"Retirement Home",
            "type":"Services"
        }
    ],
    "sg:phone":"+44 1233 713604",
    "sg:postcode":"TN25 4LN",
    "sg:province":"Kent",
    "sg:tags":[
        "care"
    ],
    "wof:name":"Bevanpark Community Care Services Ltd",
    "wof:placetype":"venue"
},
  "geometry": {"coordinates":[0.81538,51.18259],"type":"Point"}
}