{
  "type": "Feature",
  "properties": {
    "addr:full":"Old Brook Hall Farm, Warrington Road Widnes Cheshire WA8 5UX",
    "addr:postcode":"wa8 5ux",
    "addr:street":"Old Brook Hall;Warrington Road",
    "iso:country":"GB",
    "sg:address":"Old Brook Hall Farm, Warrington Road",
    "sg:city":"Widnes",
    "sg:classifiers":[
        {
            "category":"Farming",
            "subcategory":"Farm",
            "type":"Manufacturing & Wholesale Goods"
        }
    ],
    "sg:postcode":"WA8 5UX",
    "sg:province":"Cheshire",
    "sg:tags":[
        "mixed",
        "crop"
    ],
    "wof:name":"J N Beckett",
    "wof:placetype":"venue"
},
  "geometry": {"coordinates":[-2.762844,53.392296],"type":"Point"}
}