{
  "type": "Feature",
  "properties": {
    "iso:country":"GB",
    "sg:address":"27 Long Rd",
    "sg:city":"Lowestoft",
    "sg:classifiers":[
        {
            "category":"Shopping",
            "subcategory":"Used Merchandise",
            "type":"Retail Goods"
        }
    ],
    "sg:postcode":"NR33 9DB",
    "sg:province":"Suffolk",
    "sg:tags":[
        "shop",
        "second-hand"
    ],
    "wof:name":"Jolly Joe's Secondhand Mart",
    "wof:placetype":"venue"
},
  "geometry": {"coordinates":[1.7273030281,52.4637298584],"type":"Point"}
}