{
  "type": "Feature",
  "properties": {
    "addr:full":"280a Penn Rd Wolverhampton Staffordshire WV4 4AD",
    "addr:housenumber":"280a",
    "addr:postcode":"wv4 4ad",
    "addr:street":"Penn Rd",
    "iso:country":"GB",
    "sg:address":"280a Penn Rd",
    "sg:city":"Wolverhampton",
    "sg:classifiers":[
        {
            "category":"Health Services",
            "subcategory":"Nursing And Care Facility",
            "type":"Services"
        }
    ],
    "sg:phone":"+44 1902 621840",
    "sg:postcode":"WV4 4AD",
    "sg:province":"Staffordshire",
    "sg:tags":[
        "home"
    ],
    "wof:name":"Aldergrove Manor",
    "wof:placetype":"venue"
},
  "geometry": {"coordinates":[-2.1465609074,52.5659828186],"type":"Point"}
}