{
  "type": "Feature",
  "properties": {
    "addr:full":"24 High Street, Newport Saffron Walden Essex CB11 3PH",
    "addr:housenumber":"24",
    "addr:postcode":"cb11 3ph",
    "addr:street":"High Street",
    "iso:country":"GB",
    "sg:address":"24 High Street, Newport",
    "sg:city":"Saffron Walden",
    "sg:classifiers":[
        {
            "category":"Manufacturing",
            "subcategory":"Petroleum Products",
            "type":"Manufacturing & Wholesale Goods"
        }
    ],
    "sg:postcode":"CB11 3PH",
    "sg:province":"Essex",
    "sg:tags":[
        "double",
        "glazing"
    ],
    "wof:name":"Euro Glaze",
    "wof:placetype":"venue"
},
  "geometry": {"coordinates":[0.213376,51.981728],"type":"Point"}
}