{
  "type": "Feature",
  "properties": {
    "addr:full":"26 Great Queen Street London Greater London WC2B 5BB",
    "addr:housenumber":"26",
    "addr:postcode":"wc2b 5bb",
    "addr:street":"Great Queen Street",
    "iso:country":"GB",
    "sg:address":"26 Great Queen Street",
    "sg:city":"London",
    "sg:classifiers":[
        {
            "category":"Organizations",
            "subcategory":"Non-profit Organization",
            "type":"Services"
        }
    ],
    "sg:postcode":"WC2B 5BB",
    "sg:province":"Greater London",
    "sg:tags":[
        "organisation",
        "voluntary",
        "charity"
    ],
    "wof:name":"The New Masonic Samaritan Fund Investmen",
    "wof:placetype":"venue"
},
  "geometry": {"coordinates":[-0.12133,51.515514],"type":"Point"}
}