{
  "type": "Feature",
  "properties": {
    "addr:full":"126 High Street Oxford Oxfordshire OX1 4DF",
    "addr:housenumber":"126",
    "addr:postcode":"ox1 4df",
    "addr:street":"High Street",
    "iso:country":"GB",
    "sg:address":"126 High Street",
    "sg:city":"Oxford",
    "sg:classifiers":[
        {
            "category":"Fast Food",
            "type":"Food & Drink"
        }
    ],
    "sg:phone":"+44 1865 249043",
    "sg:postcode":"OX1 4DF",
    "sg:province":"Oxfordshire",
    "sg:tags":[
        "away",
        "take"
    ],
    "wof:name":"Bonjour Rapide",
    "wof:placetype":"venue"
},
  "geometry": {"coordinates":[-1.2561990023,51.7520484924],"type":"Point"}
}