{
  "type": "Feature",
  "properties": {
    "addr:full":"287 Mitcham Rd London Greater London SW17 9JQ",
    "addr:housenumber":"287",
    "addr:postcode":"sw17 9jq",
    "addr:street":"Mitcham Rd",
    "iso:country":"GB",
    "sg:address":"287 Mitcham Rd",
    "sg:city":"London",
    "sg:classifiers":[
        {
            "category":"Food & Beverages",
            "subcategory":"Bakery",
            "type":"Retail Goods"
        }
    ],
    "sg:postcode":"SW17 9JQ",
    "sg:province":"Greater London",
    "sg:tags":[
        "baker"
    ],
    "wof:name":"J T S Webber Ltd",
    "wof:placetype":"venue"
},
  "geometry": {"coordinates":[-0.160844,51.420834],"type":"Point"}
}