{
  "type": "Feature",
  "properties": {
    "addr:full":"9a High Street Malmesbury Wiltshire SN16 9AA",
    "addr:housenumber":"9a",
    "addr:postcode":"sn16 9aa",
    "addr:street":"High Street",
    "iso:country":"GB",
    "sg:address":"9a High Street",
    "sg:city":"Malmesbury",
    "sg:classifiers":[
        {
            "category":"Shopping",
            "subcategory":"Books",
            "type":"Retail Goods"
        }
    ],
    "sg:phone":"+44 1666 826656",
    "sg:postcode":"SN16 9AA",
    "sg:province":"Wiltshire",
    "sg:tags":[
        "bookseller"
    ],
    "wof:name":"Malmesbury Book Shop",
    "wof:placetype":"venue"
},
  "geometry": {"coordinates":[-2.098046,51.583157],"type":"Point"}
}