{
  "type": "Feature",
  "properties": {
    "iso:country":"GB",
    "sg:address":"97 High Street",
    "sg:city":"Cradley Heath",
    "sg:classifiers":[
        {
            "category":"Shopping",
            "subcategory":"Thrift Store",
            "type":"Retail Goods"
        }
    ],
    "sg:phone":"+44 1384 566464",
    "sg:postcode":"B64 5HE",
    "sg:province":"West Midlands",
    "sg:tags":[
        "shop",
        "charity"
    ],
    "wof:name":"The Mary Stevens Hospice Trading Company Ltd",
    "wof:placetype":"venue"
},
  "geometry": {"coordinates":[-2.0838339329,52.4715881348],"type":"Point"}
}