{
  "type": "Feature",
  "properties": {
    "iso:country":"GB",
    "sg:address":"32 Westway, Maghull",
    "sg:city":"Liverpool",
    "sg:classifiers":[
        {
            "category":"Cinema",
            "subcategory":"Movie Rental",
            "type":"Entertainment"
        }
    ],
    "sg:phone":"+44 151 526 4267",
    "sg:postcode":"L31 0DQ",
    "sg:province":"Lancashire",
    "sg:tags":[
        "video",
        "library"
    ],
    "wof:name":"Blockbuster Video",
    "wof:placetype":"venue"
},
  "geometry": {"coordinates":[-2.942416,53.51646],"type":"Point"}
}