{
  "type": "Feature",
  "properties": {
    "addr:full":"4 Fewston Avenue Leeds West Yorkshire LS9 0BE",
    "addr:housenumber":"4",
    "addr:postcode":"ls9 0be",
    "addr:street":"Fewston Avenue",
    "iso:country":"GB",
    "sg:address":"4 Fewston Avenue",
    "sg:city":"Leeds",
    "sg:classifiers":[
        {
            "category":"Building & Trades",
            "subcategory":"Construction",
            "type":"Services"
        }
    ],
    "sg:phone":"+44 113 249 7388",
    "sg:postcode":"LS9 0BE",
    "sg:province":"West Yorkshire",
    "sg:tags":[
        "double",
        "window",
        "glazing",
        "installers",
        "replacement"
    ],
    "wof:name":"Allerton Glass",
    "wof:placetype":"venue"
},
  "geometry": {"coordinates":[-1.5184149742,53.7907714844],"type":"Point"}
}