{
  "type": "Feature",
  "properties": {
    "addr:full":"Unit 3, Forest Court Solihull Warwickshire B93 8HN",
    "addr:housenumber":"unit 3",
    "addr:postcode":"b93 8hn",
    "addr:street":"Forest Court",
    "iso:country":"GB",
    "sg:address":"Unit 3, Forest Court",
    "sg:city":"Solihull",
    "sg:classifiers":[
        {
            "category":"Home & Garden",
            "subcategory":"Home Furnishings",
            "type":"Retail Goods"
        },
        {
            "category":"Home & Garden",
            "subcategory":"Building Materials",
            "type":"Retail Goods"
        }
    ],
    "sg:phone":"+44 1564 773389",
    "sg:postcode":"B93 8HN",
    "sg:province":"Warwickshire",
    "sg:tags":[
        "installers",
        "planner",
        "kitchen",
        "furnishers"
    ],
    "wof:name":"Kitchen Gallery Ltd.",
    "wof:placetype":"venue"
},
  "geometry": {"coordinates":[-1.7518190145,52.3735466003],"type":"Point"}
}