{
  "type": "Feature",
  "properties": {
    "iso:country":"GB",
    "sg:address":"St Andrews House Southam Road, Radford Semele",
    "sg:city":"Leamington Spa",
    "sg:classifiers":[
        {
            "category":"Building & Trades",
            "subcategory":"Cleaning & Sanitation",
            "type":"Services"
        }
    ],
    "sg:phone":"+44 1926 451525",
    "sg:postcode":"CV31 1TF",
    "sg:province":"Warwickshire",
    "sg:tags":[
        "commercial"
    ],
    "wof:name":"Fabriclean Ltd.",
    "wof:placetype":"venue"
},
  "geometry": {"coordinates":[-1.501554966,52.2797164917],"type":"Point"}
}