{
  "type": "Feature",
  "properties": {
    "iso:country":"GB",
    "sg:address":"78 Charles Street",
    "sg:city":"Trowbridge",
    "sg:classifiers":[
        {
            "category":"Food & Beverages",
            "subcategory":"Meat & Fish",
            "type":"Retail Goods"
        },
        {
            "category":"Food & Beverages",
            "subcategory":"Groceries & Convenience Stores",
            "type":"Retail Goods"
        }
    ],
    "sg:phone":"+44 1225 765446",
    "sg:postcode":"BA14 8ND",
    "sg:province":"Wiltshire",
    "sg:tags":[
        "shop",
        "chip"
    ],
    "wof:name":"The Oyster Fish Bar",
    "wof:placetype":"venue"
},
  "geometry": {"coordinates":[-2.211435,51.326275],"type":"Point"}
}