{
  "type": "Feature",
  "properties": {
    "iso:country":"GB",
    "sg:address":"Fayre Oaks Caravan Site, Kings Acre Road",
    "sg:city":"Hereford",
    "sg:classifiers":[
        {
            "category":"Recreation",
            "subcategory":"Campground",
            "type":"Entertainment"
        }
    ],
    "sg:phone":"+44 1432 266687",
    "sg:postcode":"HR4 0SX",
    "sg:province":"Herefordshire",
    "sg:tags":[
        "caravan",
        "park"
    ],
    "wof:name":"Cross Country Caravans (Hereford)",
    "wof:placetype":"venue"
},
  "geometry": {"coordinates":[-2.7317609787,52.0592041016],"type":"Point"}
}