{
  "type": "Feature",
  "properties": {
    "addr:full":"8 Auchmill Road Aberdeen Aberdeen City AB21 9LD",
    "addr:housenumber":"8",
    "addr:postcode":"ab21 9ld",
    "addr:street":"Auchmill Road",
    "iso:country":"GB",
    "sg:address":"8 Auchmill Road",
    "sg:city":"Aberdeen",
    "sg:classifiers":[
        {
            "category":"Home & Garden",
            "subcategory":"Hardware",
            "type":"Retail Goods"
        }
    ],
    "sg:postcode":"AB21 9LD",
    "sg:province":"Aberdeen City",
    "sg:tags":[
        "retailer",
        "diy"
    ],
    "wof:name":"Bucksburn D I Y Centre",
    "wof:placetype":"venue"
},
  "geometry": {"coordinates":[-2.169588,57.176991],"type":"Point"}
}