{
  "type": "Feature",
  "properties": {
    "iso:country":"GB",
    "sg:address":"18-19 Wind Street",
    "sg:city":"Swansea",
    "sg:classifiers":[
        {
            "category":"Bars & Pubs",
            "type":"Food & Drink"
        }
    ],
    "sg:phone":"+44 1792 641430",
    "sg:postcode":"SA1 1DY",
    "sg:province":"Neath Port Talbot",
    "sg:tags":[
        "pubs",
        "inn"
    ],
    "wof:name":"Rat & Carrot (Adelphi)",
    "wof:placetype":"venue"
},
  "geometry": {"coordinates":[-3.9401290417,51.6193809509],"type":"Point"}
}