{
  "type": "Feature",
  "properties": {
    "iso:country":"GB",
    "sg:address":"Treorchy Delivery Office, 21-23 High Street",
    "sg:city":"Treorchy",
    "sg:classifiers":[
        {
            "category":"Personal",
            "type":"Services"
        }
    ],
    "sg:phone":"+44 1443 772203",
    "sg:postcode":"CF42 6NP",
    "sg:province":"Rhondda, Cynon, Taff",
    "sg:tags":[
        "delivery"
    ],
    "wof:name":"Royal Mail Letters",
    "wof:placetype":"venue"
},
  "geometry": {"coordinates":[-3.505229,51.659664],"type":"Point"}
}