{
  "type": "Feature",
  "properties": {
    "iso:country":"GB",
    "sg:address":"164 Brockworth, Yate",
    "sg:city":"Bristol",
    "sg:classifiers":[
        {
            "category":"Professional",
            "subcategory":"Engineering",
            "type":"Services"
        }
    ],
    "sg:phone":"+44 1454 881418",
    "sg:postcode":"BS37 8SP",
    "sg:province":"Gloucestershire",
    "sg:tags":[
        "merchant",
        "engineer",
        "engineers'"
    ],
    "wof:name":"Avon Engineering Supplies",
    "wof:placetype":"venue"
},
  "geometry": {"coordinates":[-2.4315869808,51.5261993408],"type":"Point"}
}