{
  "type": "Feature",
  "properties": {
    "addr:full":"4 Southport Road Chorley Lancashire PR7 1LD",
    "addr:housenumber":"4",
    "addr:postcode":"pr7 1ld",
    "addr:street":"Southport Road",
    "iso:country":"GB",
    "sg:address":"4 Southport Road",
    "sg:city":"Chorley",
    "sg:classifiers":[
        {
            "category":"Professional",
            "subcategory":"Lawyer & Legal Services",
            "type":"Services"
        }
    ],
    "sg:postcode":"PR7 1LD",
    "sg:province":"Lancashire",
    "wof:name":"Forensic Link Ltd.",
    "wof:placetype":"venue"
},
  "geometry": {"coordinates":[-2.637889,53.653599],"type":"Point"}
}