{
  "type": "Feature",
  "properties": {
    "addr:full":"26 Molrams Lane Chelmsford Essex CM2 7AH",
    "addr:housenumber":"26",
    "addr:postcode":"cm2 7ah",
    "addr:street":"Molrams Lane",
    "iso:country":"GB",
    "sg:address":"26 Molrams Lane",
    "sg:city":"Chelmsford",
    "sg:classifiers":[
        {
            "category":"Retail",
            "subcategory":"Driving School",
            "type":"Services"
        }
    ],
    "sg:phone":"+44 1245 474718",
    "sg:postcode":"CM2 7AH",
    "sg:province":"Essex",
    "wof:name":"Approved School Of Motoring",
    "wof:placetype":"venue"
},
  "geometry": {"coordinates":[0.5140240192,51.7147483826],"type":"Point"}
}