{
  "type": "Feature",
  "properties": {
    "addr:full":"Ryder Street Stourbridge Staffordshire DY8 5AY",
    "addr:postcode":"dy8 5ay",
    "addr:street":"Ryder Street",
    "iso:country":"GB",
    "sg:address":"Ryder Street",
    "sg:city":"Stourbridge",
    "sg:classifiers":[
        {
            "category":"Bars & Pubs",
            "type":"Food & Drink"
        }
    ],
    "sg:phone":"+44 1384 278416",
    "sg:postcode":"DY8 5AY",
    "sg:province":"Staffordshire",
    "sg:tags":[
        "pubs",
        "house",
        "inn",
        "public",
        "activity"
    ],
    "wof:name":"Gibbs Mew Ltd",
    "wof:placetype":"venue"
},
  "geometry": {"coordinates":[-2.1663661003,52.478931427],"type":"Point"}
}