{
  "type": "Feature",
  "properties": {
    "addr:full":"28-29 St Mary Street Southampton Hampshire SO14 1NP",
    "addr:housenumber":"28-29",
    "addr:postcode":"so14 1np",
    "addr:street":"St Mary Street",
    "iso:country":"GB",
    "sg:address":"28-29 St Mary Street",
    "sg:city":"Southampton",
    "sg:classifiers":[
        {
            "category":"Education",
            "subcategory":"Special Training",
            "type":"Public Place"
        },
        {
            "category":"Government",
            "subcategory":"Office",
            "type":"Public Place"
        }
    ],
    "sg:phone":"+44 23 8063 8966",
    "sg:postcode":"SO14 1NP",
    "sg:province":"Hampshire",
    "sg:tags":[
        "product",
        "local",
        "centre"
    ],
    "wof:name":"Southampton Information Technology Centre",
    "wof:placetype":"venue"
},
  "geometry": {"coordinates":[-1.3976370096,50.9030609131],"type":"Point"}
}