{
  "type": "Feature",
  "properties": {
    "iso:country":"GB",
    "sg:address":"Cross Roads Fisheries, Hayfield Lane",
    "sg:city":"Doncaster",
    "sg:classifiers":[
        {
            "category":"Food & Beverages",
            "subcategory":"Meat & Fish",
            "type":"Retail Goods"
        }
    ],
    "sg:postcode":"DN9 3NB",
    "sg:province":"Lincolnshire",
    "sg:tags":[
        "chip"
    ],
    "wof:name":"The Flying Fish Bar",
    "wof:placetype":"venue"
},
  "geometry": {"coordinates":[-1.02327,53.489799],"type":"Point"}
}