{
  "type": "Feature",
  "properties": {
    "iso:country":"GB",
    "sg:address":"6 Fore Street",
    "sg:city":"Torpoint",
    "sg:classifiers":[
        {
            "category":"Professional",
            "subcategory":"Accounting & Tax Preparation",
            "type":"Services"
        }
    ],
    "sg:phone":"+44 1752 815541",
    "sg:postcode":"PL11 2AA",
    "sg:province":"Cornwall",
    "sg:tags":[
        "accountant"
    ],
    "wof:name":"Powell & Co",
    "wof:placetype":"venue"
},
  "geometry": {"coordinates":[-4.197075,50.376598],"type":"Point"}
}