{
  "type": "Feature",
  "properties": {
    "addr:full":"Cedars Link Road Stowmarket Suffolk IP14 5BE",
    "addr:postcode":"ip14 5be",
    "addr:street":"Link Road",
    "iso:country":"GB",
    "sg:address":"Cedars Link Road",
    "sg:city":"Stowmarket",
    "sg:classifiers":[
        {
            "category":"Food & Beverages",
            "subcategory":"Supermarket",
            "type":"Retail Goods"
        }
    ],
    "sg:phone":"+44 1449 627400",
    "sg:postcode":"IP14 5BE",
    "sg:province":"Suffolk",
    "wof:name":"Tesco Stores Ltd.",
    "wof:placetype":"venue"
},
  "geometry": {"coordinates":[0.996769011,52.1886253357],"type":"Point"}
}