{
  "type": "Feature",
  "properties": {
    "addr:full":"259 Selby Road Leeds West Yorkshire LS15 7JR",
    "addr:housenumber":"259",
    "addr:postcode":"ls15 7jr",
    "addr:street":"Selby Road",
    "iso:country":"GB",
    "sg:address":"259 Selby Road",
    "sg:city":"Leeds",
    "sg:classifiers":[
        {
            "category":"Travel",
            "subcategory":"Travel Agent",
            "type":"Entertainment"
        }
    ],
    "sg:phone":"+44 113 232 6023",
    "sg:postcode":"LS15 7JR",
    "sg:province":"West Yorkshire",
    "wof:name":"Co-Op Travelwide",
    "wof:placetype":"venue"
},
  "geometry": {"coordinates":[-1.470186,53.796131],"type":"Point"}
}