{
  "type": "Feature",
  "properties": {
    "iso:country":"GB",
    "sg:address":"263 Frodingham Road",
    "sg:city":"Scunthorpe",
    "sg:classifiers":[
        {
            "category":"Organizations",
            "subcategory":"Community Association",
            "type":"Services"
        }
    ],
    "sg:phone":"+44 1724 275804",
    "sg:postcode":"DN15 7NS",
    "sg:province":"Lincolnshire",
    "sg:tags":[
        "co-operatives",
        "society",
        "housing",
        "trust"
    ],
    "wof:name":"Northern Counties Housing Association Ltd",
    "wof:placetype":"venue"
},
  "geometry": {"coordinates":[-0.6560840011,53.5976829529],"type":"Point"}
}