{
  "type": "Feature",
  "properties": {
    "iso:country":"GB",
    "sg:address":"23 Wentworth Clo",
    "sg:city":"Woking",
    "sg:classifiers":[
        {
            "category":"Building & Trades",
            "subcategory":"Plumbing",
            "type":"Services"
        }
    ],
    "sg:phone":"+44 1483 211808",
    "sg:postcode":"GU23 6DB",
    "sg:province":"Surrey",
    "sg:tags":[
        "merchant",
        "plumbers'"
    ],
    "wof:name":"Splash Supplies",
    "wof:placetype":"venue"
},
  "geometry": {"coordinates":[-0.495771,51.299843],"type":"Point"}
}