{
  "type": "Feature",
  "properties": {
    "addr:full":"Russell Sq Leicester Leicestershire LE1 2DS",
    "addr:postcode":"le1 2ds",
    "addr:street":"Russell Sq",
    "iso:country":"GB",
    "sg:address":"Russell Sq",
    "sg:city":"Leicester",
    "sg:classifiers":[
        {
            "category":"Professional",
            "subcategory":"Printing & Photocopies",
            "type":"Services"
        }
    ],
    "sg:postcode":"LE1 2DS",
    "sg:province":"Leicestershire",
    "sg:tags":[
        "plate",
        "lithographic",
        "maker"
    ],
    "wof:name":"Cree,Terance Stanley,",
    "wof:placetype":"venue"
},
  "geometry": {"coordinates":[-1.1261390448,52.6421012878],"type":"Point"}
}