{
  "type": "Feature",
  "properties": {
    "addr:full":"5/6 Titmore Court, Titmore Green, Little Wymondley Hitchin Hertfordshire SG4 7JT",
    "addr:housenumber":"5 / 6",
    "addr:postcode":"sg4 7jt",
    "addr:street":"Titmore Court Titmore Green Little",
    "iso:country":"GB",
    "sg:address":"5/6 Titmore Court, Titmore Green, Little Wymondley",
    "sg:city":"Hitchin",
    "sg:classifiers":[
        {
            "category":"Professional",
            "subcategory":"Management & Consulting",
            "type":"Services"
        }
    ],
    "sg:phone":"+44 1438 759255",
    "sg:postcode":"SG4 7JT",
    "sg:province":"Hertfordshire",
    "sg:tags":[
        "fire",
        "consultant",
        "protection"
    ],
    "wof:name":"Lexicom Fire Systems",
    "wof:placetype":"venue"
},
  "geometry": {"coordinates":[-0.233029,51.93211],"type":"Point"}
}