{
  "type": "Feature",
  "properties": {
    "iso:country":"GB",
    "sg:address":"132 Widnes Road",
    "sg:city":"Widnes",
    "sg:classifiers":[
        {
            "category":"Shopping",
            "subcategory":"Comic Books",
            "type":"Retail Goods"
        }
    ],
    "sg:phone":"+44 151 424 4529",
    "sg:postcode":"WA8 6AX",
    "sg:province":"Cheshire",
    "sg:tags":[
        "jeweller"
    ],
    "wof:name":"Palmers Jewellery",
    "wof:placetype":"venue"
},
  "geometry": {"coordinates":[-2.7279829979,53.3667144775],"type":"Point"}
}