{
  "type": "Feature",
  "properties": {
    "addr:full":"Southampton House, 317 High Holborn London Greater London WC1V 7NL",
    "addr:housenumber":"317",
    "addr:postcode":"wc1v 7nl",
    "addr:street":"High Holborn",
    "iso:country":"GB",
    "sg:address":"Southampton House, 317 High Holborn",
    "sg:city":"London",
    "sg:classifiers":[
        {
            "category":"Banks & Credit Unions",
            "subcategory":"Financial Services",
            "type":"Services"
        }
    ],
    "sg:postcode":"WC1V 7NL",
    "sg:province":"Greater London",
    "sg:tags":[
        "consultant"
    ],
    "wof:name":"Maitland Securities Limited",
    "wof:placetype":"venue"
},
  "geometry": {"coordinates":[-0.11316,51.518002],"type":"Point"}
}