{
  "type": "Feature",
  "properties": {
    "addr:full":"Woodland Terr Charlton Greater London SE7 8DD",
    "addr:postcode":"se7 8dd",
    "addr:street":"Woodland Terr",
    "iso:country":"GB",
    "sg:address":"Woodland Terr",
    "sg:city":"Charlton",
    "sg:classifiers":[
        {
            "category":"Social Services",
            "subcategory":"Retirement Home",
            "type":"Services"
        }
    ],
    "sg:phone":"+44 20 8854 4507",
    "sg:postcode":"SE7 8DD",
    "sg:province":"Greater London",
    "sg:tags":[
        "residential",
        "care"
    ],
    "wof:name":"Bryceson",
    "wof:placetype":"venue"
},
  "geometry": {"coordinates":[0.0470530018,51.4893875122],"type":"Point"}
}