{
  "type": "Feature",
  "properties": {
    "addr:full":"58 Beech Avenue, Hazel Gro Stockport Cheshire SK7 4QP",
    "addr:housenumber":"58",
    "addr:postcode":"sk7 4qp",
    "addr:street":"Beech Avenue",
    "iso:country":"GB",
    "sg:address":"58 Beech Avenue, Hazel Gro",
    "sg:city":"Stockport",
    "sg:classifiers":[
        {
            "category":"Professional",
            "subcategory":"Art Services",
            "type":"Services"
        }
    ],
    "sg:phone":"+44 161 456 5959",
    "sg:postcode":"SK7 4QP",
    "sg:province":"Cheshire",
    "sg:tags":[
        "photographer"
    ],
    "wof:name":"Michael Prince Photography",
    "wof:placetype":"venue"
},
  "geometry": {"coordinates":[-2.1150319576,53.3787689209],"type":"Point"}
}