{
  "type": "Feature",
  "properties": {
    "addr:full":"Lilburn Place, Southwick Sunderland Tyne and Wear SR5 2AF",
    "addr:postcode":"sr5 2af",
    "addr:street":"Lilburn Place",
    "iso:country":"GB",
    "sg:address":"Lilburn Place, Southwick",
    "sg:city":"Sunderland",
    "sg:classifiers":[
        {
            "category":"Social Services",
            "subcategory":"Retirement Home",
            "type":"Services"
        }
    ],
    "sg:phone":"+44 191 549 6331",
    "sg:postcode":"SR5 2AF",
    "sg:province":"Tyne and Wear",
    "sg:tags":[
        "residential",
        "care"
    ],
    "wof:name":"Fife Nursing Homes Ltd.",
    "wof:placetype":"venue"
},
  "geometry": {"coordinates":[-1.40185,54.918499],"type":"Point"}
}