{
  "type": "Feature",
  "properties": {
    "addr:full":"Traquair Road Innerleithen Scottish Borders EH44 6PD",
    "addr:postcode":"eh44 6pd",
    "addr:street":"Traquair Road",
    "iso:country":"GB",
    "sg:address":"Traquair Road",
    "sg:city":"Innerleithen",
    "sg:classifiers":[
        {
            "category":"Travel",
            "subcategory":"Hotels & Motels",
            "type":"Entertainment"
        }
    ],
    "sg:phone":"+44 1896 830229",
    "sg:postcode":"EH44 6PD",
    "sg:province":"Scottish Borders",
    "wof:name":"Traquair Arms Hotel",
    "wof:placetype":"venue"
},
  "geometry": {"coordinates":[-3.0654389858,55.6171989441],"type":"Point"}
}