{
  "type": "Feature",
  "properties": {
    "addr:full":"The Old Cottage, Dane Rd Seaford East Sussex BN25 1DJ",
    "addr:postcode":"bn25 1dj",
    "addr:street":"Dane Rd",
    "iso:country":"GB",
    "sg:address":"The Old Cottage, Dane Rd",
    "sg:city":"Seaford",
    "sg:classifiers":[
        {
            "category":"Health Services",
            "subcategory":"Optometrist",
            "type":"Services"
        }
    ],
    "sg:phone":"+44 1323 898777",
    "sg:postcode":"BN25 1DJ",
    "sg:province":"East Sussex",
    "sg:tags":[
        "optician"
    ],
    "wof:name":"Barraclough Stiles & Partners",
    "wof:placetype":"venue"
},
  "geometry": {"coordinates":[0.1014100015,50.7729148865],"type":"Point"}
}