{
  "type": "Feature",
  "properties": {
    "iso:country":"GB",
    "sg:address":"15 Ardingly",
    "sg:city":"Bracknell",
    "sg:classifiers":[
        {
            "category":"Building & Trades",
            "subcategory":"Plumbing",
            "type":"Services"
        }
    ],
    "sg:phone":"+44 1344 302026",
    "sg:postcode":"RG12 8XR",
    "sg:province":"Berkshire",
    "sg:tags":[
        "plumber",
        "heating"
    ],
    "wof:name":"Paul Colley Services",
    "wof:placetype":"venue"
},
  "geometry": {"coordinates":[-0.764305,51.400295],"type":"Point"}
}