{
  "type": "Feature",
  "properties": {
    "iso:country":"GB",
    "sg:address":"Tremorvah Lodge, Tregolls Road",
    "sg:city":"Truro",
    "sg:classifiers":[
        {
            "category":"Organizations",
            "subcategory":"Membership Organization",
            "type":"Services"
        }
    ],
    "sg:postcode":"TR1 1NW",
    "sg:province":"Cornwall",
    "sg:tags":[
        "club"
    ],
    "wof:name":"Duchy Healers Association",
    "wof:placetype":"venue"
},
  "geometry": {"coordinates":[-5.045949,50.268002],"type":"Point"}
}