{
  "type": "Feature",
  "properties": {
    "addr:full":"St Georges Ho, 195-203 Waterloo Rd Southwark Greater London SE1 8XJ",
    "addr:postcode":"195-203;se1 8xj",
    "addr:street":"St;Waterloo Rd",
    "iso:country":"GB",
    "sg:address":"St Georges Ho, 195-203 Waterloo Rd",
    "sg:city":"Southwark",
    "sg:classifiers":[
        {
            "category":"Building & Trades",
            "subcategory":"Construction",
            "type":"Services"
        }
    ],
    "sg:phone":"+44 20 7633 9625",
    "sg:postcode":"SE1 8XJ",
    "sg:province":"Greater London",
    "sg:tags":[
        "heating",
        "contractor"
    ],
    "wof:name":"GLEEN",
    "wof:placetype":"venue"
},
  "geometry": {"coordinates":[-0.1094390005,51.5017585754],"type":"Point"}
}