{
  "type": "Feature",
  "properties": {
    "addr:full":"Unit B Kershaw Mill, Baldwin St Bolton Lancashire BL3 5DA",
    "addr:postcode":"bl3 5da",
    "addr:street":"Baldwin St",
    "iso:country":"GB",
    "sg:address":"Unit B Kershaw Mill, Baldwin St",
    "sg:city":"Bolton",
    "sg:classifiers":[
        {
            "category":"Home & Garden",
            "subcategory":"Hardware",
            "type":"Retail Goods"
        }
    ],
    "sg:postcode":"BL3 5DA",
    "sg:province":"Lancashire",
    "sg:tags":[
        "retailer",
        "diy"
    ],
    "wof:name":"Entwhistle,David,",
    "wof:placetype":"venue"
},
  "geometry": {"coordinates":[-2.440349,53.570782],"type":"Point"}
}