{
  "type": "Feature",
  "properties": {
    "addr:full":"Unit 1 Lincoln Business Park, Lincoln Road, Cressex High Wycombe Buckinghamshire HP12 3RD",
    "addr:housenumber":"unit 1",
    "addr:postcode":"hp12 3rd",
    "addr:street":"Lincoln Business Park Lincoln Road Cressex",
    "iso:country":"GB",
    "sg:address":"Unit 1 Lincoln Business Park, Lincoln Road, Cressex",
    "sg:city":"High Wycombe",
    "sg:classifiers":[
        {
            "category":"Farming",
            "subcategory":"Farm & Veterinary Services",
            "type":"Manufacturing & Wholesale Goods"
        }
    ],
    "sg:phone":"+44 1494 464363",
    "sg:postcode":"HP12 3RD",
    "sg:province":"Buckinghamshire",
    "sg:tags":[
        "lampshade",
        "mnfs",
        "distributor"
    ],
    "wof:name":"Peter Martin Lighting Design Ltd.",
    "wof:placetype":"venue"
},
  "geometry": {"coordinates":[-0.773434,51.62553],"type":"Point"}
}