{
  "type": "Feature",
  "properties": {
    "iso:country":"GB",
    "sg:address":"63 Eccleston Square",
    "sg:city":"London",
    "sg:classifiers":[
        {
            "category":"Real Estate",
            "subcategory":"Surveying",
            "type":"Services"
        }
    ],
    "sg:phone":"+44 20 7828 0322",
    "sg:postcode":"SW1V 1PH",
    "sg:province":"Greater London",
    "sg:tags":[
        "surveyor",
        "valuer"
    ],
    "wof:name":"John Tall",
    "wof:placetype":"venue"
},
  "geometry": {"coordinates":[-0.143425,51.491924],"type":"Point"}
}