{
  "type": "Feature",
  "properties": {
    "iso:country":"GB",
    "sg:address":"Swingbridge Rd",
    "sg:city":"Grantham",
    "sg:classifiers":[
        {
            "category":"Professional",
            "subcategory":"Business Services",
            "type":"Services"
        }
    ],
    "sg:phone":"+44 1476 570071",
    "sg:postcode":"NG31 7XT",
    "sg:province":"Lincolnshire",
    "sg:tags":[
        "import",
        "export",
        "agent"
    ],
    "wof:name":"Anglocentrop Ltd",
    "wof:placetype":"venue"
},
  "geometry": {"coordinates":[-0.662512,52.900082],"type":"Point"}
}