{
  "type": "Feature",
  "properties": {
    "iso:country":"GB",
    "sg:address":"Mickle Hill, Blackhall Rocks",
    "sg:city":"Hartlepool",
    "sg:classifiers":[
        {
            "category":"Professional",
            "subcategory":"Business Services",
            "type":"Services"
        }
    ],
    "sg:phone":"+44 191 586 4789",
    "sg:postcode":"TS27 4DF",
    "sg:province":"Durham",
    "sg:tags":[
        "bookmaker"
    ],
    "wof:name":"Arthur Turner Bookmakers",
    "wof:placetype":"venue"
},
  "geometry": {"coordinates":[-1.276761,54.740417],"type":"Point"}
}