{
  "type": "Feature",
  "properties": {
    "addr:full":"278 Milton Road Weston-super-mare Somerset BS22 8EN",
    "addr:housenumber":"278",
    "addr:postcode":"bs22 8en",
    "addr:street":"Milton Road",
    "iso:country":"GB",
    "sg:address":"278 Milton Road",
    "sg:city":"Weston-super-mare",
    "sg:classifiers":[
        {
            "category":"Building & Trades",
            "subcategory":"Plumbing",
            "type":"Services"
        }
    ],
    "sg:phone":"+44 1934 628073",
    "sg:postcode":"BS22 8EN",
    "sg:province":"Somerset",
    "sg:tags":[
        "heating"
    ],
    "wof:name":"Basham's Plumbing & Heating Services",
    "wof:placetype":"venue"
},
  "geometry": {"coordinates":[-2.942761898,51.3543128967],"type":"Point"}
}