{
  "type": "Feature",
  "properties": {
    "iso:country":"GB",
    "sg:address":"425 Bilston Road",
    "sg:city":"Wolverhampton",
    "sg:classifiers":[
        {
            "category":"Professional",
            "subcategory":"Testing Lab",
            "type":"Services"
        }
    ],
    "sg:phone":"+44 1902 403433",
    "sg:postcode":"WV2 2NN",
    "sg:province":"West Midlands",
    "sg:tags":[
        "mot"
    ],
    "wof:name":"Bilston Auto Services",
    "wof:placetype":"venue"
},
  "geometry": {"coordinates":[-2.0967450142,52.5728569031],"type":"Point"}
}