{
  "type": "Feature",
  "properties": {
    "iso:country":"GB",
    "sg:address":"4 Eastgate",
    "sg:city":"Basildon",
    "sg:classifiers":[
        {
            "category":"Shopping",
            "subcategory":"Mobile Phones",
            "type":"Retail Goods"
        }
    ],
    "sg:phone":"+44 1268 288888",
    "sg:postcode":"SS14 1JJ",
    "sg:province":"Essex",
    "wof:name":"Mobile Phone Centre",
    "wof:placetype":"venue"
},
  "geometry": {"coordinates":[0.4622,51.569038],"type":"Point"}
}