{
  "type": "Feature",
  "properties": {
    "addr:full":"95 Trelawney Estate, Paragon Road London Greater London E9 6PG",
    "addr:housenumber":"95",
    "addr:postcode":"e9 6pg",
    "addr:street":"Trelawney Estate Paragon Road",
    "iso:country":"GB",
    "sg:address":"95 Trelawney Estate, Paragon Road",
    "sg:city":"London",
    "sg:classifiers":[
        {
            "category":"Transit Center",
            "subcategory":"Freight",
            "type":"Transportation"
        },
        {
            "category":"Education",
            "subcategory":"School",
            "type":"Public Place"
        }
    ],
    "sg:phone":"+44 20 8533 0061",
    "sg:postcode":"E9 6PG",
    "sg:province":"Greater London",
    "sg:tags":[
        "piano",
        "accessory",
        "private",
        "tuition"
    ],
    "wof:name":"Euro Piano",
    "wof:placetype":"venue"
},
  "geometry": {"coordinates":[-0.0528010018,51.5460395813],"type":"Point"}
}