{
  "type": "Feature",
  "properties": {
    "addr:full":"Southampton General Hospital, Tremona Road Southampton Hampshire SO16 6YD",
    "addr:postcode":"so16 6yd",
    "addr:street":"Tremona Road",
    "iso:country":"GB",
    "sg:address":"Southampton General Hospital, Tremona Road",
    "sg:city":"Southampton",
    "sg:classifiers":[
        {
            "category":"Organizations",
            "subcategory":"Non-profit Organization",
            "type":"Services"
        }
    ],
    "sg:phone":"+44 23 8079 6528",
    "sg:postcode":"SO16 6YD",
    "sg:province":"Hampshire",
    "sg:tags":[
        "organisation",
        "voluntary",
        "charity"
    ],
    "wof:name":"Leukaemia Busters",
    "wof:placetype":"venue"
},
  "geometry": {"coordinates":[-1.43511,50.932961],"type":"Point"}
}