{
  "type": "Feature",
  "properties": {
    "addr:full":"2a Chapel St Sandbach Cheshire CW11 1DS",
    "addr:housenumber":"2a",
    "addr:postcode":"cw11 1ds",
    "addr:street":"Chapel St",
    "iso:country":"GB",
    "sg:address":"2a Chapel St",
    "sg:city":"Sandbach",
    "sg:classifiers":[
        {
            "category":"Building & Trades",
            "subcategory":"Plumbing",
            "type":"Services"
        }
    ],
    "sg:phone":"+44 1270 765229",
    "sg:postcode":"CW11 1DS",
    "sg:province":"Cheshire",
    "sg:tags":[
        "central",
        "heating"
    ],
    "wof:name":"Sandbach Heating Services",
    "wof:placetype":"venue"
},
  "geometry": {"coordinates":[-2.3658208847,53.1453285217],"type":"Point"}
}