{
  "type": "Feature",
  "properties": {
    "addr:full":"13 Dale St Liverpool Merseyside L2 2EZ",
    "addr:housenumber":"13",
    "addr:postcode":"l2 2ez",
    "addr:street":"Dale St",
    "iso:country":"GB",
    "sg:address":"13 Dale St",
    "sg:city":"Liverpool",
    "sg:classifiers":[
        {
            "category":"Bars & Pubs",
            "type":"Food & Drink"
        }
    ],
    "sg:phone":"+44 151 236 9403",
    "sg:postcode":"L2 2EZ",
    "sg:province":"Merseyside",
    "sg:tags":[
        "pubs",
        "inn"
    ],
    "wof:name":"The Saddle",
    "wof:placetype":"venue"
},
  "geometry": {"coordinates":[-2.98978,53.407635],"type":"Point"}
}