{
  "type": "Feature",
  "properties": {
    "iso:country":"GB",
    "sg:address":"Stalker Cottage, Ettymore Road, Sedgley",
    "sg:city":"Dudley",
    "sg:classifiers":[
        {
            "category":"Building & Trades",
            "subcategory":"Construction",
            "type":"Services"
        }
    ],
    "sg:postcode":"DY3 3SG",
    "sg:province":"Staffordshire",
    "sg:tags":[
        "builder"
    ],
    "wof:name":"Mr Building Services",
    "wof:placetype":"venue"
},
  "geometry": {"coordinates":[-2.12411,52.541401],"type":"Point"}
}