{
  "type": "Feature",
  "properties": {
    "iso:country":"GB",
    "sg:address":"2a Cross Lane",
    "sg:city":"Andover",
    "sg:classifiers":[
        {
            "category":"Professional",
            "subcategory":"Computer Services",
            "type":"Services"
        }
    ],
    "sg:phone":"+44 1264 362336",
    "sg:postcode":"SP10 3JE",
    "sg:province":"Hampshire",
    "sg:tags":[
        "system",
        "software"
    ],
    "wof:name":"Garnett Brown Associates Ltd.",
    "wof:placetype":"venue"
},
  "geometry": {"coordinates":[-1.489238,51.211403],"type":"Point"}
}