{
  "type": "Feature",
  "properties": {
    "iso:country":"GB",
    "sg:address":"4 The Cedars",
    "sg:city":"Buckhurst Hill",
    "sg:classifiers":[
        {
            "category":"Real Estate",
            "subcategory":"Real Estate Agent",
            "type":"Services"
        }
    ],
    "sg:phone":"+44 20 8505 1820",
    "sg:postcode":"IG9 5TS",
    "sg:province":"Essex",
    "wof:name":"Smith Bros & Co(Printers)Ltd.",
    "wof:placetype":"venue"
},
  "geometry": {"coordinates":[0.026316,51.628437],"type":"Point"}
}