{
  "type": "Feature",
  "properties": {
    "addr:full":"Sandy Road Llanelli Carmarthenshire SA15 3UL",
    "addr:postcode":"sa15 3ul",
    "addr:street":"Sandy Road",
    "iso:country":"GB",
    "sg:address":"Sandy Road",
    "sg:city":"Llanelli",
    "sg:classifiers":[
        {
            "category":"Autos & Motor Vehicles",
            "subcategory":"Automobile Sales",
            "type":"Retail Goods"
        }
    ],
    "sg:phone":"+44 1554 777033",
    "sg:postcode":"SA15 3UL",
    "sg:province":"Carmarthenshire",
    "sg:tags":[
        "car"
    ],
    "wof:name":"C E M Day",
    "wof:placetype":"venue"
},
  "geometry": {"coordinates":[-4.184531,51.685135],"type":"Point"}
}