{
  "type": "Feature",
  "properties": {
    "addr:full":"Suite 14, Shire Hall Complex Newport Newport NP20 5HB",
    "addr:postcode":"np20 5hb",
    "addr:street":"Suite 14 Shire",
    "iso:country":"GB",
    "sg:address":"Suite 14, Shire Hall Complex",
    "sg:city":"Newport",
    "sg:classifiers":[
        {
            "category":"Professional",
            "subcategory":"Management & Consulting",
            "type":"Services"
        },
        {
            "category":"Manufacturing",
            "subcategory":"Building Materials",
            "type":"Manufacturing & Wholesale Goods"
        }
    ],
    "sg:phone":"+44 1633 265544",
    "sg:postcode":"NP20 5HB",
    "sg:province":"Newport",
    "sg:tags":[
        "supp",
        "marketing",
        "shutter",
        "door",
        "consultant"
    ],
    "wof:name":"Akers Uk Ltd.",
    "wof:placetype":"venue"
},
  "geometry": {"coordinates":[-2.999119997,51.5903091431],"type":"Point"}
}