{
  "type": "Feature",
  "properties": {
    "iso:country":"GB",
    "sg:address":"Abbey Walk",
    "sg:city":"St Andrews",
    "sg:classifiers":[
        {
            "category":"Health Services",
            "subcategory":"Hospital",
            "type":"Services"
        }
    ],
    "sg:phone":"+44 1334 472327",
    "sg:postcode":"KY16 9LG",
    "sg:province":"Fife",
    "wof:name":"Memorial Hospital",
    "wof:placetype":"venue"
},
  "geometry": {"coordinates":[-2.7857310772,56.3369216919],"type":"Point"}
}