{
  "type": "Feature",
  "properties": {
    "addr:full":"Unit 2, Station Lane, New Whittington Chesterfield Derbyshire S43 2AF",
    "addr:housenumber":"unit 2",
    "addr:postcode":"s43 2af",
    "addr:street":"Station Lane",
    "iso:country":"GB",
    "sg:address":"Unit 2, Station Lane, New Whittington",
    "sg:city":"Chesterfield",
    "sg:classifiers":[
        {
            "category":"Manufacturing",
            "subcategory":"Wood Products",
            "type":"Manufacturing & Wholesale Goods"
        }
    ],
    "sg:phone":"+44 1246 452010",
    "sg:postcode":"S43 2AF",
    "sg:province":"Derbyshire",
    "sg:tags":[
        "packaging",
        "crate",
        "pallets"
    ],
    "wof:name":"Leross Services",
    "wof:placetype":"venue"
},
  "geometry": {"coordinates":[-1.4034240246,53.2720794678],"type":"Point"}
}