{
  "type": "Feature",
  "properties": {
    "addr:full":"31 Sadler Street Wells Somerset BA5 2RR",
    "addr:housenumber":"31",
    "addr:postcode":"ba5 2rr",
    "addr:street":"Sadler Street",
    "iso:country":"GB",
    "sg:address":"31 Sadler Street",
    "sg:city":"Wells",
    "sg:classifiers":[
        {
            "category":"Insurance",
            "subcategory":"Insurance Agent",
            "type":"Services"
        }
    ],
    "sg:phone":"+44 1749 673335",
    "sg:postcode":"BA5 2RR",
    "sg:province":"Somerset",
    "wof:name":"Britannic Assurance Plc",
    "wof:placetype":"venue"
},
  "geometry": {"coordinates":[-2.646826,51.210361],"type":"Point"}
}