{
  "type": "Feature",
  "properties": {
    "addr:full":"27 Portia Terrace Swansea Neath Port Talbot SA1 6XW",
    "addr:housenumber":"27",
    "addr:postcode":"sa1 6xw",
    "addr:street":"Portia Terrace",
    "iso:country":"GB",
    "sg:address":"27 Portia Terrace",
    "sg:city":"Swansea",
    "sg:classifiers":[
        {
            "category":"Health Services",
            "subcategory":"Health Practitioner",
            "type":"Services"
        }
    ],
    "sg:phone":"+44 1792 419699",
    "sg:postcode":"SA1 6XW",
    "sg:province":"Neath Port Talbot",
    "sg:tags":[
        "homoeopathic"
    ],
    "wof:name":"Siobhan Haynes",
    "wof:placetype":"venue"
},
  "geometry": {"coordinates":[-3.9481720924,51.6247940063],"type":"Point"}
}