{
  "type": "Feature",
  "properties": {
    "addr:full":"43 Clifton St Roath Cardiff Cardiff CF24 1LS",
    "addr:housenumber":"43",
    "addr:postcode":"cf24 1ls",
    "addr:street":"Clifton St",
    "iso:country":"GB",
    "sg:address":"43 Clifton St Roath",
    "sg:city":"Cardiff",
    "sg:classifiers":[
        {
            "category":"Restaurant",
            "type":"Food & Drink"
        }
    ],
    "sg:phone":"+44 29 2049 2596",
    "sg:postcode":"CF24 1LS",
    "sg:province":"Cardiff",
    "sg:tags":[
        "indian"
    ],
    "wof:name":"Ahad Miah",
    "wof:placetype":"venue"
},
  "geometry": {"coordinates":[-3.1569890976,51.4848365784],"type":"Point"}
}