{
  "type": "Feature",
  "properties": {
    "addr:full":"7 Wedgewood Road Bicester Oxfordshire OX25 5LU",
    "addr:housenumber":"7",
    "addr:postcode":"ox25 5lu",
    "addr:street":"Wedgewood Road",
    "iso:country":"GB",
    "sg:address":"7 Wedgewood Road",
    "sg:city":"Bicester",
    "sg:classifiers":[
        {
            "category":"Retail",
            "subcategory":"Auto Repair",
            "type":"Services"
        }
    ],
    "sg:phone":"+44 1869 250270",
    "sg:postcode":"OX25 5LU",
    "sg:province":"Oxfordshire",
    "sg:tags":[
        "car",
        "specialist",
        "customizing"
    ],
    "wof:name":"Arrowstar Racing",
    "wof:placetype":"venue"
},
  "geometry": {"coordinates":[-1.2766280174,51.9287185669],"type":"Point"}
}