{
  "type": "Feature",
  "properties": {
    "iso:country":"GB",
    "sg:address":"195 Bellhouse Road",
    "sg:city":"Sheffield",
    "sg:classifiers":[
        {
            "category":"Utilities",
            "subcategory":"Natural Gas",
            "type":"Services"
        }
    ],
    "sg:postcode":"S5 6HQ",
    "sg:province":"South Yorkshire",
    "sg:tags":[
        "control",
        "energy",
        "management",
        "system"
    ],
    "wof:name":"K Ambler Plumbing & Heating",
    "wof:placetype":"venue"
},
  "geometry": {"coordinates":[-1.4438309669,53.4222068787],"type":"Point"}
}