{
  "type": "Feature",
  "properties": {
    "addr:full":"Unit 6 Viscount Court, South Way Andover Hampshire SP10 5NW",
    "addr:housenumber":"unit 6",
    "addr:postcode":"sp10 5nw",
    "addr:street":"Viscount Court South Way",
    "iso:country":"GB",
    "sg:address":"Unit 6 Viscount Court, South Way",
    "sg:city":"Andover",
    "sg:classifiers":[
        {
            "category":"Manufacturing",
            "subcategory":"Buildings",
            "type":"Manufacturing & Wholesale Goods"
        }
    ],
    "sg:postcode":"SP10 5NW",
    "sg:province":"Hampshire",
    "sg:tags":[
        "system",
        "air conditioning"
    ],
    "wof:name":"Puma Products Ltd.",
    "wof:placetype":"venue"
},
  "geometry": {"coordinates":[-1.476779,51.206493],"type":"Point"}
}