{
  "type": "Feature",
  "properties": {
    "addr:full":"31 Warwick Square London Greater London SW1V 2AF",
    "addr:housenumber":"31",
    "addr:postcode":"sw1v 2af",
    "addr:street":"Warwick Square",
    "iso:country":"GB",
    "sg:address":"31 Warwick Square",
    "sg:city":"London",
    "sg:classifiers":[
        {
            "category":"Professional",
            "subcategory":"Lawyer & Legal Services",
            "type":"Services"
        }
    ],
    "sg:phone":"+44 20 7828 8685",
    "sg:postcode":"SW1V 2AF",
    "sg:province":"Greater London",
    "sg:tags":[
        "solicitor"
    ],
    "wof:name":"Piper Smith & Basham",
    "wof:placetype":"venue"
},
  "geometry": {"coordinates":[-0.142721,51.489914],"type":"Point"}
}