{
  "type": "Feature",
  "properties": {
    "iso:country":"GB",
    "sg:address":"2 Upper Green",
    "sg:city":"Wolverhampton",
    "sg:classifiers":[
        {
            "category":"Food & Beverages",
            "subcategory":"Fruits & Vegetables",
            "type":"Retail Goods"
        }
    ],
    "sg:phone":"+44 1902 755448",
    "sg:postcode":"WV6 8QQ",
    "sg:province":"Shropshire",
    "sg:tags":[
        "greengrocer"
    ],
    "wof:name":"Billies",
    "wof:placetype":"venue"
},
  "geometry": {"coordinates":[-2.1688640118,52.5980834961],"type":"Point"}
}