{
  "type": "Feature",
  "properties": {
    "addr:full":"Station Road, Scarcliffe Chesterfield Derbyshire S44 6TG",
    "addr:postcode":"s44 6tg",
    "addr:street":"Station Road",
    "iso:country":"GB",
    "sg:address":"Station Road, Scarcliffe",
    "sg:city":"Chesterfield",
    "sg:classifiers":[
        {
            "category":"Bars & Pubs",
            "type":"Food & Drink"
        }
    ],
    "sg:phone":"+44 1246 823213",
    "sg:postcode":"S44 6TG",
    "sg:province":"Derbyshire",
    "sg:tags":[
        "pubs",
        "inn"
    ],
    "wof:name":"The Elm Tree Inn",
    "wof:placetype":"venue"
},
  "geometry": {"coordinates":[-1.2666679621,53.2154350281],"type":"Point"}
}