{
  "type": "Feature",
  "properties": {
    "addr:full":"8a New St Burton On Trent Derbyshire DE14 3QN",
    "addr:housenumber":"8a",
    "addr:postcode":"de14 3qn",
    "addr:street":"New St",
    "iso:country":"GB",
    "sg:address":"8a New St",
    "sg:city":"Burton On Trent",
    "sg:classifiers":[
        {
            "category":"Personal",
            "subcategory":"Beauty Salon",
            "type":"Services"
        }
    ],
    "sg:phone":"+44 1283 536876",
    "sg:postcode":"DE14 3QN",
    "sg:province":"Derbyshire",
    "sg:tags":[
        "unisex",
        "hairdresser"
    ],
    "wof:name":"Louise Fell",
    "wof:placetype":"venue"
},
  "geometry": {"coordinates":[-1.6321150064,52.8010139465],"type":"Point"}
}