{
  "type": "Feature",
  "properties": {
    "iso:country":"GB",
    "sg:address":"Greenfield Business Centre, Greenfield",
    "sg:city":"Holywell",
    "sg:classifiers":[
        {
            "category":"Professional",
            "subcategory":"Engineering",
            "type":"Services"
        }
    ],
    "sg:phone":"+44 1352 718061",
    "sg:postcode":"CH8 7GR",
    "sg:province":"Denbighshire",
    "sg:tags":[
        "consulting",
        "engineer"
    ],
    "wof:name":"Dynaseq Vibration Monitoring",
    "wof:placetype":"venue"
},
  "geometry": {"coordinates":[-3.225195,53.274548],"type":"Point"}
}