{
  "type": "Feature",
  "properties": {
    "iso:country":"GB",
    "sg:address":"3 Kiln Road, Sherborne St John",
    "sg:city":"Basingstoke",
    "sg:classifiers":[
        {
            "category":"Bars & Pubs",
            "type":"Food & Drink"
        }
    ],
    "sg:phone":"+44 1256 850165",
    "sg:postcode":"RG24 9HS",
    "sg:province":"Hampshire",
    "sg:tags":[
        "pubs",
        "inn"
    ],
    "wof:name":"The Swan",
    "wof:placetype":"venue"
},
  "geometry": {"coordinates":[-1.104125,51.293041],"type":"Point"}
}