{
  "type": "Feature",
  "properties": {
    "iso:country":"GB",
    "sg:address":"35 Ironmarket",
    "sg:city":"Newcastle",
    "sg:classifiers":[
        {
            "category":"Real Estate",
            "subcategory":"Surveying",
            "type":"Services"
        }
    ],
    "sg:phone":"+44 1782 615530",
    "sg:postcode":"ST5 1RP",
    "sg:province":"Staffordshire",
    "sg:tags":[
        "surveyor",
        "valuer"
    ],
    "wof:name":"Roger Follwell & Partner",
    "wof:placetype":"venue"
},
  "geometry": {"coordinates":[-2.2246720791,53.0128250122],"type":"Point"}
}