{
  "type": "Feature",
  "properties": {
    "iso:country":"GB",
    "sg:address":"16 Gloucester Road, Almondsbury",
    "sg:city":"Bristol",
    "sg:classifiers":[
        {
            "category":"Shopping",
            "subcategory":"Department Store",
            "type":"Retail Goods"
        }
    ],
    "sg:postcode":"BS32 4AA",
    "sg:province":"Gloucestershire",
    "wof:name":"Hill Stores",
    "wof:placetype":"venue"
},
  "geometry": {"coordinates":[-2.557035,51.561279],"type":"Point"}
}