{
  "type": "Feature",
  "properties": {
    "addr:full":"94a Bethune Rd Stoke Newington Greater London N16 5BA",
    "addr:housenumber":"94a",
    "addr:postcode":"n16 5ba",
    "addr:street":"Bethune Rd",
    "iso:country":"GB",
    "sg:address":"94a Bethune Rd",
    "sg:city":"Stoke Newington",
    "sg:classifiers":[
        {
            "category":"Professional",
            "subcategory":"Management & Consulting",
            "type":"Services"
        }
    ],
    "sg:phone":"+44 20 7359 5844",
    "sg:postcode":"N16 5BA",
    "sg:province":"Greater London",
    "sg:tags":[
        "consultant",
        "business"
    ],
    "wof:name":"Piers Myers Associates",
    "wof:placetype":"venue"
},
  "geometry": {"coordinates":[-0.079997,51.569916],"type":"Point"}
}