{
  "type": "Feature",
  "properties": {
    "addr:full":"7 Albert Street Fraserburgh Aberdeenshire AB43 9JJ",
    "addr:housenumber":"7",
    "addr:postcode":"ab43 9jj",
    "addr:street":"Albert Street",
    "iso:country":"GB",
    "sg:address":"7 Albert Street",
    "sg:city":"Fraserburgh",
    "sg:classifiers":[
        {
            "category":"Government",
            "subcategory":"Office",
            "type":"Public Place"
        }
    ],
    "sg:phone":"+44 1346 518177",
    "sg:postcode":"AB43 9JJ",
    "sg:province":"Aberdeenshire",
    "sg:tags":[
        "local"
    ],
    "wof:name":"Building Maintenance Section",
    "wof:placetype":"venue"
},
  "geometry": {"coordinates":[-2.0131599903,57.6939811707],"type":"Point"}
}