{
  "type": "Feature",
  "properties": {
    "addr:full":"26 Market Square Dover Kent CT16 1NG",
    "addr:housenumber":"26",
    "addr:postcode":"ct16 1ng",
    "addr:street":"Market Square Dover",
    "iso:country":"GB",
    "sg:address":"26 Market Square",
    "sg:city":"Dover",
    "sg:classifiers":[
        {
            "category":"Shopping",
            "subcategory":"Clothing, Apparel, & Fashions",
            "type":"Retail Goods"
        }
    ],
    "sg:phone":"+44 1304 206017",
    "sg:postcode":"CT16 1NG",
    "sg:province":"Kent",
    "sg:tags":[
        "menswear"
    ],
    "wof:name":"Burton Menswear Ltd",
    "wof:placetype":"venue"
},
  "geometry": {"coordinates":[1.313380003,51.1250343323],"type":"Point"}
}