{
  "type": "Feature",
  "properties": {
    "iso:country":"GB",
    "sg:address":"Unit 14 Westfield Trading Estate, Midsomer Norton",
    "sg:city":"Bath",
    "sg:classifiers":[
        {
            "category":"Autos & Motor Vehicles",
            "subcategory":"Automobile Sales",
            "type":"Retail Goods"
        },
        {
            "category":"Retail",
            "subcategory":"Auto Repair",
            "type":"Services"
        }
    ],
    "sg:postcode":"BA3 4BS",
    "sg:province":"Somerset",
    "sg:tags":[
        "modification",
        "garage",
        "car"
    ],
    "wof:name":"D J Haines Motoring Engineers",
    "wof:placetype":"venue"
},
  "geometry": {"coordinates":[-2.4682900906,51.2801094055],"type":"Point"}
}