{
  "type": "Feature",
  "properties": {
    "addr:full":"65a Mere Rd Leicester Leicestershire LE5 3HT",
    "addr:housenumber":"65a",
    "addr:postcode":"le5 3ht",
    "addr:street":"Mere Rd",
    "iso:country":"GB",
    "sg:address":"65a Mere Rd",
    "sg:city":"Leicester",
    "sg:classifiers":[
        {
            "category":"Professional",
            "subcategory":"Detective & Security Services",
            "type":"Services"
        }
    ],
    "sg:phone":"+44 116 251 4507",
    "sg:postcode":"LE5 3HT",
    "sg:province":"Leicestershire",
    "sg:tags":[
        "car"
    ],
    "wof:name":"J.C.A Security Systems",
    "wof:placetype":"venue"
},
  "geometry": {"coordinates":[-1.1086540222,52.6368484497],"type":"Point"}
}