{
  "type": "Feature",
  "properties": {
    "addr:full":"Station House, Station Road, Alvechurch Birmingham Worcestershire B48 7SE",
    "addr:postcode":"b48 7se",
    "addr:street":"Station Road",
    "iso:country":"GB",
    "sg:address":"Station House, Station Road, Alvechurch",
    "sg:city":"Birmingham",
    "sg:classifiers":[
        {
            "category":"Professional",
            "subcategory":"Engineering",
            "type":"Services"
        }
    ],
    "sg:phone":"+44 121 447 7181",
    "sg:postcode":"B48 7SE",
    "sg:province":"Worcestershire",
    "sg:tags":[
        "contractor",
        "electrical",
        "engineer"
    ],
    "wof:name":"R & J Electrical Ltd.",
    "wof:placetype":"venue"
},
  "geometry": {"coordinates":[-1.9680839777,52.3476333618],"type":"Point"}
}