{
  "type": "Feature",
  "properties": {
    "addr:full":"18 Llyn Onn, Llangian Pwllheli Gwynedd LL53 7LU",
    "addr:housenumber":"18",
    "addr:postcode":"ll53 7lu",
    "addr:street":"Llyn Onn Llangian Pwllheli",
    "iso:country":"GB",
    "sg:address":"18 Llyn Onn, Llangian",
    "sg:city":"Pwllheli",
    "sg:classifiers":[
        {
            "category":"Building & Trades",
            "subcategory":"Landscaping Services",
            "type":"Services"
        },
        {
            "category":"Military Area",
            "subcategory":"Air Force Base",
            "type":"Public Place"
        }
    ],
    "sg:phone":"+44 1758 730493",
    "sg:postcode":"LL53 7LU",
    "sg:province":"Gwynedd",
    "sg:tags":[
        "taxi",
        "hire",
        "gardening",
        "private"
    ],
    "wof:name":"Busy B Garden Services",
    "wof:placetype":"venue"
},
  "geometry": {"coordinates":[-4.5280818939,52.8331375122],"type":"Point"}
}