{
  "type": "Feature",
  "properties": {
    "iso:country":"GB",
    "sg:address":"Temple Cottage, 164 Oxford Road, Cowley",
    "sg:city":"Oxford",
    "sg:classifiers":[
        {
            "category":"Government",
            "subcategory":"Office",
            "type":"Public Place"
        }
    ],
    "sg:phone":"+44 1865 775482",
    "sg:postcode":"OX4 2LA",
    "sg:province":"Oxfordshire",
    "sg:tags":[
        "central"
    ],
    "wof:name":"The Probation Service",
    "wof:placetype":"venue"
},
  "geometry": {"coordinates":[-1.2100139856,51.7337532043],"type":"Point"}
}