{
  "type": "Feature",
  "properties": {
    "addr:full":"41-43 Stourbridge Road Dudley West Midlands DY1 2DH",
    "addr:housenumber":"41-43",
    "addr:postcode":"dy1 2dh",
    "addr:street":"Stourbridge Road",
    "iso:country":"GB",
    "sg:address":"41-43 Stourbridge Road",
    "sg:city":"Dudley",
    "sg:classifiers":[
        {
            "category":"Social Services",
            "subcategory":"Retirement Home",
            "type":"Services"
        }
    ],
    "sg:phone":"+44 1384 211850",
    "sg:postcode":"DY1 2DH",
    "sg:province":"West Midlands",
    "sg:tags":[
        "residential",
        "care"
    ],
    "wof:name":"Belvidere Homes Ltd.",
    "wof:placetype":"venue"
},
  "geometry": {"coordinates":[-2.1014969349,52.5037231445],"type":"Point"}
}