{
  "type": "Feature",
  "properties": {
    "addr:full":"3a The Colonnade, 123-151 Buckingham Palace Rd Westminster Greater London SW1W 9RZ",
    "addr:housenumber":"3a;123-151",
    "addr:postcode":"sw1w 9rz",
    "addr:street":"Buckingham Palace Rd",
    "iso:country":"GB",
    "sg:address":"3a The Colonnade, 123-151 Buckingham Palace Rd",
    "sg:city":"Westminster",
    "sg:classifiers":[
        {
            "category":"Food & Beverages",
            "subcategory":"Specialty",
            "type":"Retail Goods"
        }
    ],
    "sg:phone":"+44 20 7976 6615",
    "sg:postcode":"SW1W 9RZ",
    "sg:province":"Greater London",
    "sg:tags":[
        "product",
        "health"
    ],
    "wof:name":"Revital Health Place",
    "wof:placetype":"venue"
},
  "geometry": {"coordinates":[-0.1467300057,51.4942016602],"type":"Point"}
}