{
  "type": "Feature",
  "properties": {
    "addr:full":"31-35 Linom Rd Clapham Greater London SW4 7PB",
    "addr:housenumber":"31-35",
    "addr:postcode":"sw4 7pb",
    "addr:street":"Linom Rd",
    "iso:country":"GB",
    "sg:address":"31-35 Linom Rd",
    "sg:city":"Clapham",
    "sg:classifiers":[
        {
            "category":"Health Services",
            "subcategory":"Doctor",
            "type":"Services"
        }
    ],
    "sg:phone":"+44 20 7274 4220",
    "sg:postcode":"SW4 7PB",
    "sg:province":"Greater London",
    "sg:tags":[
        "practitioners"
    ],
    "wof:name":"Burton, C A L",
    "wof:placetype":"venue"
},
  "geometry": {"coordinates":[-0.139234,51.460979],"type":"Point"}
}