{
  "type": "Feature",
  "properties": {
    "iso:country":"GB",
    "sg:address":"6 Bancroft Way, Gosforth",
    "sg:city":"Newcastle-upon-tyne",
    "sg:classifiers":[
        {
            "category":"Building & Trades",
            "subcategory":"Construction",
            "type":"Services"
        }
    ],
    "sg:phone":"+44 191 285 5438",
    "sg:postcode":"NE3 2BX",
    "sg:province":"Tyne and Wear",
    "sg:tags":[
        "builder"
    ],
    "wof:name":"Clarkson & Davis Ltd.",
    "wof:placetype":"venue"
},
  "geometry": {"coordinates":[-1.6490199566,55.0200004578],"type":"Point"}
}