{
  "type": "Feature",
  "properties": {
    "iso:country":"GB",
    "sg:address":"1 Manor Rd, Mundesley",
    "sg:city":"Norwich",
    "sg:classifiers":[
        {
            "category":"Home & Garden",
            "subcategory":"Building Materials",
            "type":"Retail Goods"
        }
    ],
    "sg:phone":"+44 1263 721232",
    "sg:postcode":"NR11 8AX",
    "sg:province":"Norfolk",
    "sg:tags":[
        "ironwork",
        "wrought"
    ],
    "wof:name":"Manor Metalcraft",
    "wof:placetype":"venue"
},
  "geometry": {"coordinates":[1.432297945,52.878818512],"type":"Point"}
}