{
  "type": "Feature",
  "properties": {
    "iso:country":"GB",
    "sg:address":"17 Eastgate Square, East Street",
    "sg:city":"Chichester",
    "sg:classifiers":[
        {
            "category":"Shopping",
            "subcategory":"Photographic Equipment",
            "type":"Retail Goods"
        }
    ],
    "sg:phone":"+44 1243 531536",
    "sg:postcode":"PO19 1JL",
    "sg:province":"West Sussex",
    "sg:tags":[
        "supply"
    ],
    "wof:name":"Alan Chase Ltd.",
    "wof:placetype":"venue"
},
  "geometry": {"coordinates":[-0.775429,50.836166],"type":"Point"}
}