{
  "type": "Feature",
  "properties": {
    "addr:full":"Unity Street, St Philipse Bristol City of Bristol BS2 0HN",
    "addr:postcode":"bs2 0hn",
    "addr:street":"Unity Street",
    "iso:country":"GB",
    "sg:address":"Unity Street, St Philipse",
    "sg:city":"Bristol",
    "sg:classifiers":[
        {
            "category":"Professional",
            "subcategory":"Management & Consulting",
            "type":"Services"
        }
    ],
    "sg:phone":"+44 117 927 7271",
    "sg:postcode":"BS2 0HN",
    "sg:province":"City of Bristol",
    "sg:tags":[
        "fire",
        "consultant",
        "protection"
    ],
    "wof:name":"Wormald Fire Systems",
    "wof:placetype":"venue"
},
  "geometry": {"coordinates":[-2.580039978,51.4552078247],"type":"Point"}
}