{
  "type": "Feature",
  "properties": {
    "addr:full":"115 Lower Richmond Road, Putney London Greater London SW15 1EX",
    "addr:housenumber":"115",
    "addr:postcode":"sw15 1ex",
    "addr:street":"Lower Richmond Road",
    "iso:country":"GB",
    "sg:address":"115 Lower Richmond Road, Putney",
    "sg:city":"London",
    "sg:classifiers":[
        {
            "category":"Shopping",
            "subcategory":"Pharmacy",
            "type":"Retail Goods"
        }
    ],
    "sg:phone":"+44 20 8788 6869",
    "sg:postcode":"SW15 1EX",
    "sg:province":"Greater London",
    "sg:tags":[
        "pharmacist",
        "chemist"
    ],
    "wof:name":"Simmonds Chemist",
    "wof:placetype":"venue"
},
  "geometry": {"coordinates":[-0.221591,51.467697],"type":"Point"}
}