{
  "type": "Feature",
  "properties": {
    "iso:country":"GB",
    "sg:address":"Straight Ash, Culmstock",
    "sg:city":"Cullompton",
    "sg:classifiers":[
        {
            "category":"Farming",
            "subcategory":"Livestock Farm",
            "type":"Manufacturing & Wholesale Goods"
        }
    ],
    "sg:phone":"+44 1823 680283",
    "sg:postcode":"EX15 3JX",
    "sg:province":"Devon",
    "sg:tags":[
        "others"
    ],
    "wof:name":"Henry J Alford",
    "wof:placetype":"venue"
},
  "geometry": {"coordinates":[-3.279414,50.914421],"type":"Point"}
}