{
  "type": "Feature",
  "properties": {
    "iso:country":"GB",
    "sg:address":", Bridestowe",
    "sg:city":"Okehampton",
    "sg:classifiers":[
        {
            "category":"Social Services",
            "subcategory":"Retirement Home",
            "type":"Services"
        }
    ],
    "sg:phone":"+44 1837 861467",
    "sg:postcode":"EX20 4ER",
    "sg:province":"Devon",
    "sg:tags":[
        "residential",
        "care"
    ],
    "wof:name":"Springfield Residential Home",
    "wof:placetype":"venue"
},
  "geometry": {"coordinates":[-4.120169,50.679871],"type":"Point"}
}