{
  "type": "Feature",
  "properties": {
    "addr:full":"31 Queens Road Shanklin Isle of Wight PO37 6DQ",
    "addr:housenumber":"31",
    "addr:postcode":"po37 6dq",
    "addr:street":"Queens Road",
    "iso:country":"GB",
    "sg:address":"31 Queens Road",
    "sg:city":"Shanklin",
    "sg:classifiers":[
        {
            "category":"Travel",
            "subcategory":"Hotels & Motels",
            "type":"Entertainment"
        }
    ],
    "sg:phone":"+44 1983 862930",
    "sg:postcode":"PO37 6DQ",
    "sg:province":"Isle of Wight",
    "sg:tags":[
        "house",
        "guest"
    ],
    "wof:name":"Edgecombe Private Hotel",
    "wof:placetype":"venue"
},
  "geometry": {"coordinates":[-1.174938,50.631649],"type":"Point"}
}