{
  "type": "Feature",
  "properties": {
    "iso:country":"GB",
    "sg:address":"Ram Meadow, Cotton La",
    "sg:city":"Bury St Edmunds",
    "sg:classifiers":[
        {
            "category":"Organizations",
            "subcategory":"Membership Organization",
            "type":"Services"
        }
    ],
    "sg:phone":"+44 1284 754721",
    "sg:postcode":"IP33 1XT",
    "sg:province":"Suffolk",
    "sg:tags":[
        "club"
    ],
    "wof:name":"Bury Town Football Club",
    "wof:placetype":"venue"
},
  "geometry": {"coordinates":[0.70932,52.249905],"type":"Point"}
}