{
  "type": "Feature",
  "properties": {
    "addr:full":"Llanrwst Road Conwy Conwy LL32 8QE",
    "addr:postcode":"ll32 8qe",
    "addr:street":"Llanrwst Road",
    "iso:country":"GB",
    "sg:address":"Llanrwst Road",
    "sg:city":"Conwy",
    "sg:classifiers":[
        {
            "category":"Education",
            "subcategory":"School",
            "type":"Public Place"
        },
        {
            "category":"Government",
            "subcategory":"Office",
            "type":"Public Place"
        }
    ],
    "sg:phone":"+44 1492 660216",
    "sg:postcode":"LL32 8QE",
    "sg:province":"Conwy",
    "sg:tags":[
        "local",
        "authority"
    ],
    "wof:name":"Dolgarrog Primary School",
    "wof:placetype":"venue"
},
  "geometry": {"coordinates":[-3.8266320229,53.2800064087],"type":"Point"}
}