{
  "type": "Feature",
  "properties": {
    "addr:full":"180 Wilmslow Rd Wilmslow Cheshire SK9 3LG",
    "addr:housenumber":"180",
    "addr:postcode":"sk9 3lg",
    "addr:street":"Wilmslow Rd",
    "iso:country":"GB",
    "sg:address":"180 Wilmslow Rd",
    "sg:city":"Wilmslow",
    "sg:classifiers":[
        {
            "category":"Travel",
            "subcategory":"Hotels & Motels",
            "type":"Entertainment"
        }
    ],
    "sg:phone":"+44 1625 529211",
    "sg:postcode":"SK9 3LG",
    "sg:province":"Cheshire",
    "wof:name":"Thistle Hotel The",
    "wof:placetype":"venue"
},
  "geometry": {"coordinates":[-2.215279,53.347279],"type":"Point"}
}