{
  "type": "Feature",
  "properties": {
    "iso:country":"GB",
    "sg:address":"4 Murray Road",
    "sg:city":"Workington",
    "sg:classifiers":[
        {
            "category":"Shopping",
            "subcategory":"Discount & Variety Stores",
            "type":"Retail Goods"
        }
    ],
    "sg:phone":"+44 1900 603280",
    "sg:postcode":"CA14 2AD",
    "sg:province":"Cumbria",
    "sg:tags":[
        "centre"
    ],
    "wof:name":"Your More Store Ltd.",
    "wof:placetype":"venue"
},
  "geometry": {"coordinates":[-3.548455,54.643642],"type":"Point"}
}