{
  "type": "Feature",
  "properties": {
    "addr:full":"11-13 Queens Road, Clifton Bristol City of Bristol BS8 1QF",
    "addr:housenumber":"11-13",
    "addr:postcode":"bs8 1qf",
    "addr:street":"Queens Road",
    "iso:country":"GB",
    "sg:address":"11-13 Queens Road, Clifton",
    "sg:city":"Bristol",
    "sg:classifiers":[
        {
            "category":"Shopping",
            "subcategory":"Pharmacy",
            "type":"Retail Goods"
        }
    ],
    "sg:phone":"+44 117 926 4083",
    "sg:postcode":"BS8 1QF",
    "sg:province":"City of Bristol",
    "sg:tags":[
        "pharmacist",
        "chemist"
    ],
    "wof:name":"Boots the Chemists",
    "wof:placetype":"venue"
},
  "geometry": {"coordinates":[-2.6051850319,51.4558067322],"type":"Point"}
}