{
  "type": "Feature",
  "properties": {
    "iso:country":"GB",
    "sg:address":"3 Cook Street, Avonmouth",
    "sg:city":"Bristol",
    "sg:classifiers":[
        {
            "category":"Building & Trades",
            "subcategory":"Construction",
            "type":"Services"
        }
    ],
    "sg:postcode":"BS11 9JY",
    "sg:province":"City of Bristol",
    "sg:tags":[
        "builder"
    ],
    "wof:name":"Leading Leadwork Ltd",
    "wof:placetype":"venue"
},
  "geometry": {"coordinates":[-2.6916809082,51.4977264404],"type":"Point"}
}