{
  "type": "Feature",
  "properties": {
    "iso:country":"GB",
    "sg:address":"10 Norwood Gardens",
    "sg:city":"Ashford",
    "sg:classifiers":[
        {
            "category":"Utilities",
            "type":"Services"
        }
    ],
    "sg:postcode":"TN23 1JP",
    "sg:province":"Kent",
    "sg:tags":[
        "internet"
    ],
    "wof:name":"A.A.G. Design & Consultancy Ltd",
    "wof:placetype":"venue"
},
  "geometry": {"coordinates":[0.8672580123,51.1501350403],"type":"Point"}
}