{
  "type": "Feature",
  "properties": {
    "addr:full":"Unit 2ba, Pleasley Vale Mills Business Park Mansfield Derbyshire NG19 8RL",
    "addr:postcode":"ng19 8rl",
    "addr:street":"Vale Mills Business Park",
    "iso:country":"GB",
    "sg:address":"Unit 2ba, Pleasley Vale Mills Business Park",
    "sg:city":"Mansfield",
    "sg:classifiers":[
        {
            "category":"Professional",
            "subcategory":"Secretarial Services",
            "type":"Services"
        }
    ],
    "sg:phone":"+44 1623 812612",
    "sg:postcode":"NG19 8RL",
    "sg:province":"Derbyshire",
    "wof:name":"Image Promotions",
    "wof:placetype":"venue"
},
  "geometry": {"coordinates":[-1.2266299725,53.1788482666],"type":"Point"}
}