{
  "type": "Feature",
  "properties": {
    "addr:full":"Mompesson House, The Close Salisbury Wiltshire SP1 2EL",
    "addr:postcode":"sp1 2el",
    "addr:street":"The Close",
    "iso:country":"GB",
    "sg:address":"Mompesson House, The Close",
    "sg:city":"Salisbury",
    "sg:classifiers":[
        {
            "category":"Landmark",
            "subcategory":"Tourist Attraction",
            "type":"Public Place"
        }
    ],
    "sg:phone":"+44 1722 335659",
    "sg:postcode":"SP1 2EL",
    "sg:province":"Wiltshire",
    "sg:tags":[
        "interest"
    ],
    "wof:name":"The National Trust",
    "wof:placetype":"venue"
},
  "geometry": {"coordinates":[-1.7922600508,51.0653953552],"type":"Point"}
}