{
  "type": "Feature",
  "properties": {
    "addr:full":"Ruthrieston Depot, Ruthrieston Rd Aberdeen Aberdeen City AB10 7JR",
    "addr:postcode":"ab10 7jr",
    "addr:street":"Ruthrieston Rd",
    "iso:country":"GB",
    "sg:address":"Ruthrieston Depot, Ruthrieston Rd",
    "sg:city":"Aberdeen",
    "sg:classifiers":[
        {
            "category":"Government",
            "subcategory":"Office",
            "type":"Public Place"
        }
    ],
    "sg:phone":"+44 1224 584060",
    "sg:postcode":"AB10 7JR",
    "sg:province":"Aberdeen City",
    "sg:tags":[
        "local"
    ],
    "wof:name":"Aberdeen City Council",
    "wof:placetype":"venue"
},
  "geometry": {"coordinates":[-2.123509,57.122719],"type":"Point"}
}