{
  "type": "Feature",
  "properties": {
    "iso:country":"GB",
    "sg:address":"7-12 Dock Place",
    "sg:city":"Edinburgh",
    "sg:classifiers":[
        {
            "category":"Food & Beverages",
            "subcategory":"Liquor & Beverages",
            "type":"Retail Goods"
        },
        {
            "category":"Bars & Pubs",
            "subcategory":"Wine Bar",
            "type":"Food & Drink"
        }
    ],
    "sg:phone":"+44 131 555 3344",
    "sg:postcode":"EH6 6LU",
    "sg:province":"City of Edinburgh",
    "sg:tags":[
        "beer",
        "spirit"
    ],
    "wof:name":"Bar Sirius",
    "wof:placetype":"venue"
},
  "geometry": {"coordinates":[-3.171827,55.977383],"type":"Point"}
}