{
  "type": "Feature",
  "properties": {
    "addr:full":"Main Road Boston Lincolnshire PE22 0TW",
    "addr:postcode":"pe22 0tw",
    "addr:street":"Main Road",
    "iso:country":"GB",
    "sg:address":"Main Road",
    "sg:city":"Boston",
    "sg:classifiers":[
        {
            "category":"Building & Trades",
            "subcategory":"Construction",
            "type":"Services"
        }
    ],
    "sg:phone":"+44 1205 750488",
    "sg:postcode":"PE22 0TW",
    "sg:province":"Lincolnshire",
    "sg:tags":[
        "builder"
    ],
    "wof:name":"John Upsall",
    "wof:placetype":"venue"
},
  "geometry": {"coordinates":[0.015512,53.062572],"type":"Point"}
}