{
  "type": "Feature",
  "properties": {
    "addr:full":"1 Roberts Rd Exeter Devon EX2 4HB",
    "addr:housenumber":"1",
    "addr:postcode":"ex2 4hb",
    "addr:street":"Roberts Rd",
    "iso:country":"GB",
    "sg:address":"1 Roberts Rd",
    "sg:city":"Exeter",
    "sg:classifiers":[
        {
            "category":"Shopping",
            "subcategory":"News",
            "type":"Retail Goods"
        }
    ],
    "sg:phone":"+44 1392 255133",
    "sg:postcode":"EX2 4HB",
    "sg:province":"Devon",
    "sg:tags":[
        "newsagent"
    ],
    "wof:name":"Larkbeare Bridge News",
    "wof:placetype":"venue"
},
  "geometry": {"coordinates":[-3.5257399082,50.7181816101],"type":"Point"}
}