{
  "type": "Feature",
  "properties": {
    "iso:country":"GB",
    "sg:address":"27 High Street",
    "sg:city":"Thornton Heath",
    "sg:classifiers":[
        {
            "category":"Shopping",
            "subcategory":"Pharmacy",
            "type":"Retail Goods"
        }
    ],
    "sg:phone":"+44 20 8684 4185",
    "sg:postcode":"CR7 8RU",
    "sg:province":"Surrey",
    "sg:tags":[
        "pharmacist",
        "chemist"
    ],
    "wof:name":"Zina Chemist Ltd.",
    "wof:placetype":"venue"
},
  "geometry": {"coordinates":[-0.094311,51.398216],"type":"Point"}
}