{
  "type": "Feature",
  "properties": {
    "addr:full":"Unit E2 Seedbed Centre, Langston Road Loughton Essex IG10 3TQ",
    "addr:housenumber":"e2",
    "addr:postcode":"ig10 3tq",
    "addr:street":"Seedbed Centre Langston Road",
    "iso:country":"GB",
    "sg:address":"Unit E2 Seedbed Centre, Langston Road",
    "sg:city":"Loughton",
    "sg:classifiers":[
        {
            "category":"Professional",
            "type":"Services"
        }
    ],
    "sg:phone":"+44 20 8508 6344",
    "sg:postcode":"IG10 3TQ",
    "sg:province":"Essex",
    "sg:tags":[
        "directory",
        "pub"
    ],
    "wof:name":"20/20 Publications",
    "wof:placetype":"venue"
},
  "geometry": {"coordinates":[0.055179,51.647373],"type":"Point"}
}