{
  "type": "Feature",
  "properties": {
    "addr:full":"1a Bank St Newton Abbot Devon TQ12 2JL",
    "addr:housenumber":"1a",
    "addr:postcode":"tq12 2jl",
    "addr:street":"Bank St",
    "iso:country":"GB",
    "sg:address":"1a Bank St",
    "sg:city":"Newton Abbot",
    "sg:classifiers":[
        {
            "category":"Shopping",
            "subcategory":"Optical Goods",
            "type":"Retail Goods"
        }
    ],
    "sg:phone":"+44 1626 363534",
    "sg:postcode":"TQ12 2JL",
    "sg:province":"Devon",
    "wof:name":"B & T Optical Laboratories",
    "wof:placetype":"venue"
},
  "geometry": {"coordinates":[-3.612393,50.529625],"type":"Point"}
}