{
  "type": "Feature",
  "properties": {
    "addr:full":"42 Heatherset Way, Red Lodge Bury St Edmunds Cambridgeshire IP28 8JR",
    "addr:housenumber":"42",
    "addr:postcode":"ip28 8jr",
    "addr:street":"Heatherset Way;St",
    "iso:country":"GB",
    "sg:address":"42 Heatherset Way, Red Lodge",
    "sg:city":"Bury St Edmunds",
    "sg:classifiers":[
        {
            "category":"Organizations",
            "subcategory":"Non-profit Organization",
            "type":"Services"
        }
    ],
    "sg:phone":"+44 1638 751110",
    "sg:postcode":"IP28 8JR",
    "sg:province":"Cambridgeshire",
    "sg:tags":[
        "organisation",
        "voluntary",
        "charity"
    ],
    "wof:name":"St John Ambulance",
    "wof:placetype":"venue"
},
  "geometry": {"coordinates":[0.4914039969,52.3043022156],"type":"Point"}
}