{
  "type": "Feature",
  "properties": {
    "addr:full":"Toot Baldon Oxford Oxfordshire OX44 9NG",
    "addr:postcode":"ox44 9ng",
    "iso:country":"GB",
    "sg:address":"Toot Baldon",
    "sg:city":"Oxford",
    "sg:classifiers":[
        {
            "category":"Bars & Pubs",
            "type":"Food & Drink"
        }
    ],
    "sg:postcode":"OX44 9NG",
    "sg:province":"Oxfordshire",
    "sg:tags":[
        "pubs",
        "inn"
    ],
    "wof:name":"The Crown Inn",
    "wof:placetype":"venue"
},
  "geometry": {"coordinates":[-1.18014,51.702431],"type":"Point"}
}