{
  "type": "Feature",
  "properties": {
    "addr:full":"124 Nathan Way, Thames Mead London Greater London SE28 0AU",
    "addr:housenumber":"124",
    "addr:postcode":"se28 0au",
    "addr:street":"Nathan Way Thames Mead",
    "iso:country":"GB",
    "sg:address":"124 Nathan Way, Thames Mead",
    "sg:city":"London",
    "sg:classifiers":[
        {
            "category":"Sports & Exercise",
            "subcategory":"Tennis Court",
            "type":"Entertainment"
        }
    ],
    "sg:phone":"+44 20 8855 5544",
    "sg:postcode":"SE28 0AU",
    "sg:province":"Greater London",
    "sg:tags":[
        "breakdown",
        "recovery"
    ],
    "wof:name":"Ontime (Kenfield) Rescue & Recovery Ltd.",
    "wof:placetype":"venue"
},
  "geometry": {"coordinates":[0.095246,51.493961],"type":"Point"}
}