{
  "type": "Feature",
  "properties": {
    "addr:full":"28 Hobbs La Bristol City of Bristol BS1 5ED",
    "addr:housenumber":"28",
    "addr:postcode":"bs1 5ed",
    "addr:street":"Hobbs La",
    "iso:country":"GB",
    "sg:address":"28 Hobbs La",
    "sg:city":"Bristol",
    "sg:classifiers":[
        {
            "category":"Organizations",
            "subcategory":"Non-profit Organization",
            "type":"Services"
        }
    ],
    "sg:postcode":"BS1 5ED",
    "sg:province":"City of Bristol",
    "sg:tags":[
        "organisation",
        "voluntary",
        "charity"
    ],
    "wof:name":"Tree Aid",
    "wof:placetype":"venue"
},
  "geometry": {"coordinates":[-2.599555,51.453732],"type":"Point"}
}