{
  "type": "Feature",
  "properties": {
    "addr:full":"32 Southwark Street Nottingham Nottinghamshire NG6 0DA",
    "addr:housenumber":"32",
    "addr:postcode":"ng6 0da",
    "addr:street":"Southwark Street",
    "iso:country":"GB",
    "sg:address":"32 Southwark Street",
    "sg:city":"Nottingham",
    "sg:classifiers":[
        {
            "category":"Fast Food",
            "type":"Food & Drink"
        }
    ],
    "sg:phone":"+44 115 942 0074",
    "sg:postcode":"NG6 0DA",
    "sg:province":"Nottinghamshire",
    "sg:tags":[
        "away",
        "take"
    ],
    "wof:name":"San-San Gardens",
    "wof:placetype":"venue"
},
  "geometry": {"coordinates":[-1.18052,52.986313],"type":"Point"}
}