{
  "type": "Feature",
  "properties": {
    "iso:country":"GB",
    "sg:address":"Christchurch Centre, Milman Road",
    "sg:city":"Reading",
    "sg:classifiers":[
        {
            "category":"Social Services",
            "type":"Services"
        }
    ],
    "sg:phone":"+44 118 987 6633",
    "sg:postcode":"RG2 0AY",
    "sg:province":"Berkshire",
    "sg:tags":[
        "need",
        "disability",
        "special"
    ],
    "wof:name":"Stepping Stones",
    "wof:placetype":"venue"
},
  "geometry": {"coordinates":[-0.966989994,51.4436988831],"type":"Point"}
}