{
  "type": "Feature",
  "properties": {
    "iso:country":"GB",
    "sg:address":"107 Wellington Road, Bollington",
    "sg:city":"Macclesfield",
    "sg:classifiers":[
        {
            "category":"Manufacturing",
            "subcategory":"Petroleum Products",
            "type":"Manufacturing & Wholesale Goods"
        }
    ],
    "sg:phone":"+44 1625 572664",
    "sg:postcode":"SK10 5HT",
    "sg:province":"Cheshire",
    "sg:tags":[
        "double",
        "glazing"
    ],
    "wof:name":"Premier Plastics",
    "wof:placetype":"venue"
},
  "geometry": {"coordinates":[-2.1104409695,53.2942619324],"type":"Point"}
}