{
  "type": "Feature",
  "properties": {
    "iso:country":"GB",
    "sg:address":"140 Battersea Park Road",
    "sg:city":"London",
    "sg:classifiers":[
        {
            "category":"Professional",
            "subcategory":"Business Services",
            "type":"Services"
        }
    ],
    "sg:phone":"+44 20 7622 5511",
    "sg:postcode":"SW11 4NB",
    "sg:province":"Greater London",
    "sg:tags":[
        "accomodation"
    ],
    "wof:name":"Southbank Commercial Centre",
    "wof:placetype":"venue"
},
  "geometry": {"coordinates":[-0.157707,51.474255],"type":"Point"}
}