{
  "type": "Feature",
  "properties": {
    "addr:full":"Hornersquoy Broughton, Westray Orkney Orkney Islands KW17 2DA",
    "addr:postcode":"kw17 2da",
    "iso:country":"GB",
    "sg:address":"Hornersquoy Broughton, Westray",
    "sg:city":"Orkney",
    "sg:classifiers":[
        {
            "category":"Bus Charters",
            "type":"Transportation"
        }
    ],
    "sg:phone":"+44 1857 677355",
    "sg:postcode":"KW17 2DA",
    "sg:province":"Orkney Islands",
    "sg:tags":[
        "coach"
    ],
    "wof:name":"A Costie",
    "wof:placetype":"venue"
},
  "geometry": {"coordinates":[-2.990348,59.319221],"type":"Point"}
}