{
  "type": "Feature",
  "properties": {
    "iso:country":"GB",
    "sg:address":"17-25 Scarborough Street",
    "sg:city":"Hartlepool",
    "sg:classifiers":[
        {
            "category":"Professional",
            "subcategory":"Accounting & Tax Preparation",
            "type":"Services"
        }
    ],
    "sg:phone":"+44 1429 272109",
    "sg:postcode":"TS24 7DA",
    "sg:province":"Durham",
    "sg:tags":[
        "accountant"
    ],
    "wof:name":"Walker Tindle",
    "wof:placetype":"venue"
},
  "geometry": {"coordinates":[-1.2076840401,54.6855278015],"type":"Point"}
}