{
  "type": "Feature",
  "properties": {
    "addr:full":"211 Lockwood Rd, Lockwood Huddersfield West Yorkshire HD1 3TG",
    "addr:housenumber":"211",
    "addr:postcode":"hd1 3tg",
    "addr:street":"Lockwood Rd;West",
    "iso:country":"GB",
    "sg:address":"211 Lockwood Rd, Lockwood",
    "sg:city":"Huddersfield",
    "sg:classifiers":[
        {
            "category":"Organizations",
            "subcategory":"Professional Association",
            "type":"Services"
        }
    ],
    "sg:phone":"+44 1484 517140",
    "sg:postcode":"HD1 3TG",
    "sg:province":"West Yorkshire",
    "sg:tags":[
        "union",
        "trade"
    ],
    "wof:name":"Transport & General Workers Union",
    "wof:placetype":"venue"
},
  "geometry": {"coordinates":[-1.794383,53.633553],"type":"Point"}
}