{
  "type": "Feature",
  "properties": {
    "addr:full":"15 Lindholme Skelmersdale Lancashire WN8 6TP",
    "addr:housenumber":"15",
    "addr:postcode":"wn8 6tp",
    "addr:street":"Lindholme Skelmersdale",
    "iso:country":"GB",
    "sg:address":"15 Lindholme",
    "sg:city":"Skelmersdale",
    "sg:classifiers":[
        {
            "category":"Building & Trades",
            "subcategory":"Construction",
            "type":"Services"
        }
    ],
    "sg:postcode":"WN8 6TP",
    "sg:province":"Lancashire",
    "sg:tags":[
        "dry",
        "lining",
        "plasterers",
        "screeders"
    ],
    "wof:name":"Sparkes,Peter,",
    "wof:placetype":"venue"
},
  "geometry": {"coordinates":[-2.770371,53.561573],"type":"Point"}
}