{
  "type": "Feature",
  "properties": {
    "iso:country":"GB",
    "sg:address":"Dale Gardens",
    "sg:city":"Plymouth",
    "sg:classifiers":[
        {
            "category":"Retail",
            "subcategory":"Auto Repair",
            "type":"Services"
        }
    ],
    "sg:postcode":"PL4 6PX",
    "sg:province":"Devon",
    "sg:tags":[
        "electrical",
        "centre"
    ],
    "wof:name":"Alto Start",
    "wof:placetype":"venue"
},
  "geometry": {"coordinates":[-4.142223835,50.3812294006],"type":"Point"}
}