{
  "type": "Feature",
  "properties": {
    "addr:full":"Battersea Arts Centre, Lavender Hill London Greater London SW11 5TN",
    "addr:postcode":"sw11 5tn",
    "addr:street":"Lavender Hill",
    "iso:country":"GB",
    "sg:address":"Battersea Arts Centre, Lavender Hill",
    "sg:city":"London",
    "sg:classifiers":[
        {
            "category":"Professional",
            "subcategory":"Computer Services",
            "type":"Services"
        }
    ],
    "sg:phone":"+44 20 7228 5335",
    "sg:postcode":"SW11 5TN",
    "sg:province":"Greater London",
    "sg:tags":[
        "information"
    ],
    "wof:name":"The Puppet Centre Trust",
    "wof:placetype":"venue"
},
  "geometry": {"coordinates":[-0.1610199958,51.4654998779],"type":"Point"}
}