{
  "type": "Feature",
  "properties": {
    "iso:country":"GB",
    "sg:address":"17 Penel Orlieu",
    "sg:city":"Bridgwater",
    "sg:classifiers":[
        {
            "category":"Fast Food",
            "type":"Food & Drink"
        }
    ],
    "sg:phone":"+44 1278 452385",
    "sg:postcode":"TA6 3PF",
    "sg:province":"Somerset",
    "sg:tags":[
        "away",
        "take"
    ],
    "wof:name":"Vivaldi",
    "wof:placetype":"venue"
},
  "geometry": {"coordinates":[-3.007929,51.127689],"type":"Point"}
}