{
  "type": "Feature",
  "properties": {
    "iso:country":"GB",
    "sg:address":"134 Blackburn Road",
    "sg:city":"Bolton",
    "sg:classifiers":[
        {
            "category":"Cafe",
            "type":"Food & Drink"
        }
    ],
    "sg:postcode":"BL1 8DW",
    "sg:province":"Lancashire",
    "sg:tags":[
        "tea",
        "room"
    ],
    "wof:name":"S Eggleston",
    "wof:placetype":"venue"
},
  "geometry": {"coordinates":[-2.430551,53.590168],"type":"Point"}
}