{
  "type": "Feature",
  "properties": {
    "iso:country":"GB",
    "sg:address":"Manchester Road",
    "sg:city":"Glossop",
    "sg:classifiers":[
        {
            "category":"Retail",
            "subcategory":"Auto Repair",
            "type":"Services"
        }
    ],
    "sg:phone":"+44 1457 852844",
    "sg:postcode":"SK13 1LW",
    "sg:province":"Derbyshire",
    "sg:tags":[
        "modification",
        "garage"
    ],
    "wof:name":"Tintwistle Garage",
    "wof:placetype":"venue"
},
  "geometry": {"coordinates":[-1.973553,53.472084],"type":"Point"}
}