{
  "type": "Feature",
  "properties": {
    "iso:country":"GB",
    "sg:address":"684 High Road, Leyton",
    "sg:city":"London",
    "sg:classifiers":[
        {
            "category":"Home & Garden",
            "subcategory":"Household Appliances",
            "type":"Retail Goods"
        }
    ],
    "sg:phone":"+44 20 8539 7262",
    "sg:postcode":"E10 6JP",
    "sg:province":"Greater London",
    "sg:tags":[
        "electrical"
    ],
    "wof:name":"Leyton Domestic Appliances",
    "wof:placetype":"venue"
},
  "geometry": {"coordinates":[-0.00821,51.570869],"type":"Point"}
}