{
  "type": "Feature",
  "properties": {
    "addr:full":"41 Elmbank Street Glasgow Glasgow City G2 4PG",
    "addr:housenumber":"41",
    "addr:postcode":"g2 4pg",
    "addr:street":"Elmbank Street",
    "iso:country":"GB",
    "sg:address":"41 Elmbank Street",
    "sg:city":"Glasgow",
    "sg:classifiers":[
        {
            "category":"Autos & Motor Vehicles",
            "subcategory":"Fuel & Gas Station",
            "type":"Retail Goods"
        }
    ],
    "sg:phone":"+44 141 248 6450",
    "sg:postcode":"G2 4PG",
    "sg:province":"Glasgow City",
    "sg:tags":[
        "petrol",
        "filling"
    ],
    "wof:name":"Elmbank Service Station",
    "wof:placetype":"venue"
},
  "geometry": {"coordinates":[-4.268433094,55.8642921448],"type":"Point"}
}