{
  "type": "Feature",
  "properties": {
    "addr:full":"117 High Street Aldershot Hampshire GU11 1TT",
    "addr:housenumber":"117",
    "addr:postcode":"gu11 1tt",
    "addr:street":"High Street",
    "iso:country":"GB",
    "sg:address":"117 High Street",
    "sg:city":"Aldershot",
    "sg:classifiers":[
        {
            "category":"Real Estate",
            "subcategory":"Real Estate Agent",
            "type":"Services"
        }
    ],
    "sg:phone":"+44 1252 316111",
    "sg:postcode":"GU11 1TT",
    "sg:province":"Hampshire",
    "wof:name":"Bourke's Estate Agents Ltd.",
    "wof:placetype":"venue"
},
  "geometry": {"coordinates":[-0.7609480023,51.2498893738],"type":"Point"}
}