{
  "type": "Feature",
  "properties": {
    "addr:full":"7 Oakfield Rd, East Wittering Chichester West Sussex PO20 8RP",
    "addr:housenumber":"7",
    "addr:postcode":"po20 8rp",
    "addr:street":"Oakfield Rd",
    "iso:country":"GB",
    "sg:address":"7 Oakfield Rd, East Wittering",
    "sg:city":"Chichester",
    "sg:classifiers":[
        {
            "category":"Shopping",
            "subcategory":"Shoes",
            "type":"Retail Goods"
        }
    ],
    "sg:postcode":"PO20 8RP",
    "sg:province":"West Sussex",
    "sg:tags":[
        "shop"
    ],
    "wof:name":"Emjays Direct Ltd",
    "wof:placetype":"venue"
},
  "geometry": {"coordinates":[-0.8719930053,50.7685317993],"type":"Point"}
}