{
  "type": "Feature",
  "properties": {
    "iso:country":"GB",
    "sg:address":"Wesley Ho, 1-7 Wesley Ave, Park Royal",
    "sg:city":"London",
    "sg:classifiers":[
        {
            "category":"Government",
            "subcategory":"Post Office",
            "type":"Public Place"
        }
    ],
    "sg:phone":"+44 20 8961 0666",
    "sg:postcode":"NW10 7BZ",
    "sg:province":"Greater London",
    "sg:tags":[
        "messenger",
        "courier"
    ],
    "wof:name":"Delta Air & Road Transport Ltd",
    "wof:placetype":"venue"
},
  "geometry": {"coordinates":[-0.267534,51.527725],"type":"Point"}
}