{
  "type": "Feature",
  "properties": {
    "addr:full":"81 Witton St Northwich Cheshire CW9 5DR",
    "addr:housenumber":"81",
    "addr:postcode":"cw9 5dr",
    "addr:street":"Witton St",
    "iso:country":"GB",
    "sg:address":"81 Witton St",
    "sg:city":"Northwich",
    "sg:classifiers":[
        {
            "category":"Real Estate",
            "subcategory":"Real Estate Agent",
            "type":"Services"
        }
    ],
    "sg:phone":"+44 1606 48433",
    "sg:postcode":"CW9 5DR",
    "sg:province":"Cheshire",
    "wof:name":"Bridgfords",
    "wof:placetype":"venue"
},
  "geometry": {"coordinates":[-2.5086679459,53.2621421814],"type":"Point"}
}