{
  "type": "Feature",
  "properties": {
    "addr:full":"1 Riding House Street West End Hampshire W1P 7PA",
    "addr:housenumber":"1",
    "addr:postcode":"w1p 7pa",
    "addr:street":"Riding House Street",
    "iso:country":"GB",
    "sg:address":"1 Riding House Street",
    "sg:city":"West End",
    "sg:classifiers":[
        {
            "category":"Professional",
            "subcategory":"Business Services",
            "type":"Services"
        }
    ],
    "sg:postcode":"W1P 7PA",
    "sg:province":"Hampshire",
    "sg:tags":[
        "trade"
    ],
    "wof:name":"S&w International",
    "wof:placetype":"venue"
},
  "geometry": {"coordinates":[-0.1431329995,51.5180130005],"type":"Point"}
}