{
  "type": "Feature",
  "properties": {
    "iso:country":"GB",
    "sg:address":"88 Stafford Street",
    "sg:city":"Willenhall",
    "sg:classifiers":[
        {
            "category":"Bus Charters",
            "type":"Transportation"
        }
    ],
    "sg:phone":"+44 1902 635462",
    "sg:postcode":"WV13 1RT",
    "sg:province":"West Midlands",
    "sg:tags":[
        "hire",
        "coach"
    ],
    "wof:name":"Modern Travel",
    "wof:placetype":"venue"
},
  "geometry": {"coordinates":[-2.056168,52.584686],"type":"Point"}
}