{
  "type": "Feature",
  "properties": {
    "addr:full":"London Street Fairford Gloucestershire GL7 4AQ",
    "addr:postcode":"gl7 4aq",
    "addr:street":"London Street",
    "iso:country":"GB",
    "sg:address":"London Street",
    "sg:city":"Fairford",
    "sg:classifiers":[
        {
            "category":"Bars & Pubs",
            "type":"Food & Drink"
        }
    ],
    "sg:phone":"+44 1285 712409",
    "sg:postcode":"GL7 4AQ",
    "sg:province":"Gloucestershire",
    "sg:tags":[
        "pubs",
        "inn"
    ],
    "wof:name":"The Plough Inn",
    "wof:placetype":"venue"
},
  "geometry": {"coordinates":[-1.76782,51.709686],"type":"Point"}
}