{
  "type": "Feature",
  "properties": {
    "iso:country":"GB",
    "sg:address":"Pensilva, Goon Gumpas, St Day",
    "sg:city":"Redruth",
    "sg:classifiers":[
        {
            "category":"Freight",
            "type":"Transportation"
        }
    ],
    "sg:phone":"+44 1209 820287",
    "sg:postcode":"TR16 5JL",
    "sg:province":"Cornwall",
    "sg:tags":[
        "haulage",
        "road"
    ],
    "wof:name":"Rowlands Haulage",
    "wof:placetype":"venue"
},
  "geometry": {"coordinates":[-5.16764,50.239128],"type":"Point"}
}