{
  "type": "Feature",
  "properties": {
    "addr:full":"Unit 4 Hallcroft Indust Est Retford Nottinghamshire DN22 7SS",
    "addr:housenumber":"unit 4",
    "addr:postcode":"dn22 7ss",
    "addr:street":"Hallcroft Indust Est",
    "iso:country":"GB",
    "sg:address":"Unit 4 Hallcroft Indust Est",
    "sg:city":"Retford",
    "sg:classifiers":[
        {
            "category":"Manufacturing",
            "subcategory":"Signs",
            "type":"Manufacturing & Wholesale Goods"
        }
    ],
    "sg:phone":"+44 1777 707124",
    "sg:postcode":"DN22 7SS",
    "sg:province":"Nottinghamshire",
    "sg:tags":[
        "nameplate"
    ],
    "wof:name":"J J'S Auto Style",
    "wof:placetype":"venue"
},
  "geometry": {"coordinates":[-0.9536989927,53.3363265991],"type":"Point"}
}