{
  "type": "Feature",
  "properties": {
    "addr:full":"90 Whitchurch Rd, Cathays Cardiff Cardiff CF14 3LY",
    "addr:housenumber":"90",
    "addr:postcode":"cf14 3ly",
    "addr:street":"Whitchurch Rd",
    "iso:country":"GB",
    "sg:address":"90 Whitchurch Rd, Cathays",
    "sg:city":"Cardiff",
    "sg:classifiers":[
        {
            "category":"Shopping",
            "subcategory":"Crafts & Fabrics",
            "type":"Retail Goods"
        }
    ],
    "sg:postcode":"CF14 3LY",
    "sg:province":"Cardiff",
    "sg:tags":[
        "merchant",
        "wool"
    ],
    "wof:name":"Falkland Islands Wool Marketing Ltd",
    "wof:placetype":"venue"
},
  "geometry": {"coordinates":[-3.187253,51.500721],"type":"Point"}
}