{
  "type": "Feature",
  "properties": {
    "iso:country":"GB",
    "sg:address":"19 The Broadway",
    "sg:city":"Southgate",
    "sg:classifiers":[
        {
            "category":"Professional",
            "subcategory":"Computer Services",
            "type":"Services"
        }
    ],
    "sg:phone":"+44 20 8882 4942",
    "sg:postcode":"N14 6PH",
    "sg:province":"Greater London",
    "sg:tags":[
        "system",
        "software"
    ],
    "wof:name":"Southgate Discount Computers",
    "wof:placetype":"venue"
},
  "geometry": {"coordinates":[-0.12685,51.632431],"type":"Point"}
}