{
  "type": "Feature",
  "properties": {
    "addr:full":"2c Coleford Clo Camberley Hampshire GU16 6DX",
    "addr:housenumber":"2c",
    "addr:postcode":"gu16 6dx",
    "addr:street":"Coleford Clo",
    "iso:country":"GB",
    "sg:address":"2c Coleford Clo",
    "sg:city":"Camberley",
    "sg:classifiers":[
        {
            "category":"Home & Garden",
            "subcategory":"Home Furnishings",
            "type":"Retail Goods"
        }
    ],
    "sg:phone":"+44 1252 375037",
    "sg:postcode":"GU16 6DX",
    "sg:province":"Hampshire",
    "sg:tags":[
        "furnishers",
        "planner",
        "kitchen"
    ],
    "wof:name":"Orchard Kitchens",
    "wof:placetype":"venue"
},
  "geometry": {"coordinates":[-0.728617,51.290672],"type":"Point"}
}