{
  "type": "Feature",
  "properties": {
    "addr:full":"Old Pearl Lane, Off Tarvin Road Chester Cheshire CH3 5NS",
    "addr:postcode":"ch3 5ns",
    "addr:street":"Old Pearl Lane Off Tarvin Road",
    "iso:country":"GB",
    "sg:address":"Old Pearl Lane, Off Tarvin Road",
    "sg:city":"Chester",
    "sg:classifiers":[
        {
            "category":"Home & Garden",
            "subcategory":"Furniture",
            "type":"Retail Goods"
        }
    ],
    "sg:postcode":"CH3 5NS",
    "sg:province":"Cheshire",
    "wof:name":"Mill Reproduction Furniture",
    "wof:placetype":"venue"
},
  "geometry": {"coordinates":[-2.855686903,53.1925468445],"type":"Point"}
}