{
  "type": "Feature",
  "properties": {
    "iso:country":"GB",
    "sg:address":"6 Langdale Street",
    "sg:city":"Bootle",
    "sg:classifiers":[
        {
            "category":"Personal",
            "type":"Services"
        }
    ],
    "sg:phone":"+44 151 933 5097",
    "sg:postcode":"L20 3BX",
    "sg:province":"Merseyside",
    "sg:tags":[
        "wedding"
    ],
    "wof:name":"Peter Barrington",
    "wof:placetype":"venue"
},
  "geometry": {"coordinates":[-2.9866828918,53.4494132996],"type":"Point"}
}