{
  "type": "Feature",
  "properties": {
    "addr:full":"6 Cooper Street Chichester West Sussex PO19 1EB",
    "addr:housenumber":"6",
    "addr:postcode":"po19 1eb",
    "addr:street":"Cooper Street",
    "iso:country":"GB",
    "sg:address":"6 Cooper Street",
    "sg:city":"Chichester",
    "sg:classifiers":[
        {
            "category":"Personal",
            "subcategory":"Beauty Salon",
            "type":"Services"
        }
    ],
    "sg:phone":"+44 1243 782440",
    "sg:postcode":"PO19 1EB",
    "sg:province":"West Sussex",
    "sg:tags":[
        "unisex",
        "hairdresser"
    ],
    "wof:name":"The Beauty Room At Emiles Hair Design",
    "wof:placetype":"venue"
},
  "geometry": {"coordinates":[-0.778803,50.835804],"type":"Point"}
}