{
  "type": "Feature",
  "properties": {
    "addr:full":"13 Anderson Drive Renfrew Renfrewshire PA4 8PL",
    "addr:housenumber":"13",
    "addr:postcode":"pa4 8pl",
    "addr:street":"Anderson Drive",
    "iso:country":"GB",
    "sg:address":"13 Anderson Drive",
    "sg:city":"Renfrew",
    "sg:classifiers":[
        {
            "category":"Building & Trades",
            "subcategory":"Construction",
            "type":"Services"
        }
    ],
    "sg:phone":"+44 141 886 7083",
    "sg:postcode":"PA4 8PL",
    "sg:province":"Renfrewshire",
    "sg:tags":[
        "joiner",
        "carpenter"
    ],
    "wof:name":"Blackstoun Builders",
    "wof:placetype":"venue"
},
  "geometry": {"coordinates":[-4.388759,55.879253],"type":"Point"}
}