{
  "type": "Feature",
  "properties": {
    "addr:full":"University Of London Woburn Square London Greater London WC1H 0AB",
    "addr:postcode":"wc1h 0ab",
    "addr:street":"Square",
    "iso:country":"GB",
    "sg:address":"University Of London Woburn Square",
    "sg:city":"London",
    "sg:classifiers":[
        {
            "category":"Education",
            "subcategory":"University",
            "type":"Public Place"
        }
    ],
    "sg:phone":"+44 20 7862 8949",
    "sg:postcode":"WC1H 0AB",
    "sg:province":"Greater London",
    "sg:tags":[
        "medical",
        "school"
    ],
    "wof:name":"Warburg Institute",
    "wof:placetype":"venue"
},
  "geometry": {"coordinates":[-0.1306100041,51.5232200623],"type":"Point"}
}