{
  "type": "Feature",
  "properties": {
    "iso:country":"GB",
    "sg:address":"3 Traquair Park West",
    "sg:city":"Edinburgh",
    "sg:classifiers":[
        {
            "category":"Communications",
            "subcategory":"Film & Video Production",
            "type":"Services"
        }
    ],
    "sg:postcode":"EH12 7AN",
    "sg:province":"City of Edinburgh",
    "sg:tags":[
        "illustrator",
        "artist"
    ],
    "wof:name":"Carol Barrett",
    "wof:placetype":"venue"
},
  "geometry": {"coordinates":[-3.2781391144,55.9404945374],"type":"Point"}
}