{
  "type": "Feature",
  "properties": {
    "addr:full":"Rooms 2-3 Gresham Chambers, 14 Lichfield Wolverhampton West Midlands WV1 1DP",
    "addr:housenumber":"2-3;14",
    "addr:postcode":"wv1 1dp",
    "iso:country":"GB",
    "sg:address":"Rooms 2-3 Gresham Chambers, 14 Lichfield",
    "sg:city":"Wolverhampton",
    "sg:classifiers":[
        {
            "category":"Organizations",
            "subcategory":"Political Organization",
            "type":"Services"
        }
    ],
    "sg:postcode":"WV1 1DP",
    "sg:province":"West Midlands",
    "sg:tags":[
        "party"
    ],
    "wof:name":"Murphy,Simon,",
    "wof:placetype":"venue"
},
  "geometry": {"coordinates":[-2.1261119843,52.5891456604],"type":"Point"}
}