{
  "type": "Feature",
  "properties": {
    "iso:country":"GB",
    "sg:address":"Fairlawns, Newton On The Moor",
    "sg:city":"Morpeth",
    "sg:classifiers":[
        {
            "category":"Professional",
            "subcategory":"Engineering",
            "type":"Services"
        }
    ],
    "sg:phone":"+44 1665 575532",
    "sg:postcode":"NE65 9JY",
    "sg:province":"Northumberland",
    "sg:tags":[
        "civil",
        "engineer"
    ],
    "wof:name":"Denis W Fife",
    "wof:placetype":"venue"
},
  "geometry": {"coordinates":[-1.7322800159,55.3414802551],"type":"Point"}
}