{
  "type": "Feature",
  "properties": {
    "addr:full":"2 Montpelier Vale London Greater London SE3 0TA",
    "addr:housenumber":"2",
    "addr:postcode":"se3 0ta",
    "addr:street":"Montpelier Vale",
    "iso:country":"GB",
    "sg:address":"2 Montpelier Vale",
    "sg:city":"London",
    "sg:classifiers":[
        {
            "category":"Real Estate",
            "subcategory":"Real Estate Agent",
            "type":"Services"
        }
    ],
    "sg:phone":"+44 20 8318 9666",
    "sg:postcode":"SE3 0TA",
    "sg:province":"Greater London",
    "wof:name":"Comber & Co",
    "wof:placetype":"venue"
},
  "geometry": {"coordinates":[0.008754,51.467129],"type":"Point"}
}