{
  "type": "Feature",
  "properties": {
    "addr:full":"23 Church Lane, Nether Heyford Northampton Buckinghamshire NN7 3LQ",
    "addr:housenumber":"23",
    "addr:postcode":"nn7 3lq",
    "addr:street":"Church Lane",
    "iso:country":"GB",
    "sg:address":"23 Church Lane, Nether Heyford",
    "sg:city":"Northampton",
    "sg:classifiers":[
        {
            "category":"Home & Garden",
            "subcategory":"Home Furnishings",
            "type":"Retail Goods"
        }
    ],
    "sg:phone":"+44 1327 340991",
    "sg:postcode":"NN7 3LQ",
    "sg:province":"Buckinghamshire",
    "sg:tags":[
        "blind",
        "curtain",
        "fitting"
    ],
    "wof:name":"Swains Blinds",
    "wof:placetype":"venue"
},
  "geometry": {"coordinates":[-1.039326,52.223007],"type":"Point"}
}