{
  "type": "Feature",
  "properties": {
    "iso:country":"GB",
    "sg:address":"Fore Street",
    "sg:city":"North Tawton",
    "sg:classifiers":[
        {
            "category":"Bars & Pubs",
            "type":"Food & Drink"
        }
    ],
    "sg:phone":"+44 1837 82357",
    "sg:postcode":"EX20 2ED",
    "sg:province":"Devon",
    "sg:tags":[
        "pubs",
        "inn"
    ],
    "wof:name":"The Copper Key Inn",
    "wof:placetype":"venue"
},
  "geometry": {"coordinates":[-3.899937,50.800095],"type":"Point"}
}