{
  "type": "Feature",
  "properties": {
    "addr:full":"3a Crossley House Industrial Estate, Leyland Road, Penwithum Preston Lancashire PR1 9QP",
    "addr:housenumber":"3a",
    "addr:postcode":"pr1 9qp",
    "addr:street":"Estate Leyland Road Penwithum",
    "iso:country":"GB",
    "sg:address":"3a Crossley House Industrial Estate, Leyland Road, Penwithum",
    "sg:city":"Preston",
    "sg:classifiers":[
        {
            "category":"Professional",
            "subcategory":"Detective & Security Services",
            "type":"Services"
        }
    ],
    "sg:postcode":"PR1 9QP",
    "sg:province":"Lancashire",
    "sg:tags":[
        "equipment",
        "installers"
    ],
    "wof:name":"Workform",
    "wof:placetype":"venue"
},
  "geometry": {"coordinates":[-2.70685,53.743721],"type":"Point"}
}