{
  "type": "Feature",
  "properties": {
    "addr:full":"Civic Way Swadlincote Derbyshire DE11 0AD",
    "addr:postcode":"de11 0ad",
    "addr:street":"Civic Way",
    "iso:country":"GB",
    "sg:address":"Civic Way",
    "sg:city":"Swadlincote",
    "sg:classifiers":[
        {
            "category":"Home & Garden",
            "subcategory":"Furniture",
            "type":"Retail Goods"
        }
    ],
    "sg:postcode":"DE11 0AD",
    "sg:province":"Derbyshire",
    "wof:name":"Roger James Furnishers",
    "wof:placetype":"venue"
},
  "geometry": {"coordinates":[-1.557774,52.774803],"type":"Point"}
}