{
  "type": "Feature",
  "properties": {
    "iso:country":"GB",
    "sg:address":"Sabir House, Overt St Off Milkstone Road",
    "sg:city":"Rochdale",
    "sg:classifiers":[
        {
            "category":"Shopping",
            "subcategory":"Clothing, Apparel, & Fashions",
            "type":"Retail Goods"
        }
    ],
    "sg:postcode":"OL11 1PW",
    "sg:province":"Lancashire",
    "sg:tags":[
        "shop"
    ],
    "wof:name":"Capricorn Manufacturing Co.",
    "wof:placetype":"venue"
},
  "geometry": {"coordinates":[-2.1544239521,53.6072273254],"type":"Point"}
}