{
  "type": "Feature",
  "properties": {
    "iso:country":"GB",
    "sg:address":"Spectators Lounge, South Terminal, London Gatwick Airport",
    "sg:city":"Gatwick",
    "sg:classifiers":[
        {
            "category":"Utilities",
            "type":"Services"
        }
    ],
    "sg:phone":"+44 1293 568400",
    "sg:postcode":"RH6 0NN",
    "sg:province":"Surrey",
    "sg:tags":[
        "internet"
    ],
    "wof:name":"Cafe Internet",
    "wof:placetype":"venue"
},
  "geometry": {"coordinates":[-0.1723539978,51.1617736816],"type":"Point"}
}