{
  "type": "Feature",
  "properties": {
    "addr:full":"Deepdale, Westerham Hill Westerham Kent TN16 2EB",
    "addr:postcode":"tn16 2eb",
    "addr:street":"Westerham Hill Westerham",
    "iso:country":"GB",
    "sg:address":"Deepdale, Westerham Hill",
    "sg:city":"Westerham",
    "sg:classifiers":[
        {
            "category":"Organizations",
            "subcategory":"Non-profit Organization",
            "type":"Services"
        }
    ],
    "sg:phone":"+44 1959 562547",
    "sg:postcode":"TN16 2EB",
    "sg:province":"Kent",
    "sg:tags":[
        "organisation",
        "voluntary",
        "charity"
    ],
    "wof:name":"Cancer Research Campaign",
    "wof:placetype":"venue"
},
  "geometry": {"coordinates":[0.05888,51.289017],"type":"Point"}
}