{
  "type": "Feature",
  "properties": {
    "addr:full":"Hambridge Farm, Martley Worcester Herefordshire WR6 6QT",
    "addr:postcode":"wr6 6qt",
    "iso:country":"GB",
    "sg:address":"Hambridge Farm, Martley",
    "sg:city":"Worcester",
    "sg:classifiers":[
        {
            "category":"Banks & Credit Unions",
            "subcategory":"Investment Brokerage",
            "type":"Services"
        }
    ],
    "sg:phone":"+44 1886 812228",
    "sg:postcode":"WR6 6QT",
    "sg:province":"Herefordshire",
    "sg:tags":[
        "contractor"
    ],
    "wof:name":"Brian S R Wickens",
    "wof:placetype":"venue"
},
  "geometry": {"coordinates":[-2.3633608818,52.2360458374],"type":"Point"}
}