{
  "type": "Feature",
  "properties": {
    "addr:full":"19 Eagle Close Fareham Hampshire PO16 8QX",
    "addr:housenumber":"19",
    "addr:postcode":"po16 8qx",
    "addr:street":"Eagle Close",
    "iso:country":"GB",
    "sg:address":"19 Eagle Close",
    "sg:city":"Fareham",
    "sg:classifiers":[
        {
            "category":"Manufacturing",
            "subcategory":"Wood Products",
            "type":"Manufacturing & Wholesale Goods"
        }
    ],
    "sg:phone":"+44 1329 310209",
    "sg:postcode":"PO16 8QX",
    "sg:province":"Hampshire",
    "sg:tags":[
        "packaging",
        "crate",
        "pallets"
    ],
    "wof:name":"R J C Packaging Services",
    "wof:placetype":"venue"
},
  "geometry": {"coordinates":[-1.152915,50.848167],"type":"Point"}
}