{
  "type": "Feature",
  "properties": {
    "addr:full":"London Road Westcliff-on-sea Essex SS0 8NB",
    "addr:postcode":"ss0 8nb",
    "addr:street":"London Road",
    "iso:country":"GB",
    "sg:address":"London Road",
    "sg:city":"Westcliff-on-sea",
    "sg:classifiers":[
        {
            "category":"Retail",
            "subcategory":"Event Space",
            "type":"Services"
        }
    ],
    "sg:phone":"+44 1702 480194",
    "sg:postcode":"SS0 8NB",
    "sg:province":"Essex",
    "sg:tags":[
        "banqueting",
        "room"
    ],
    "wof:name":"Chalkwell Park Rooms",
    "wof:placetype":"venue"
},
  "geometry": {"coordinates":[0.6927599907,51.5436859131],"type":"Point"}
}