{
  "type": "Feature",
  "properties": {
    "addr:full":"Valley Road, Harmans Cross Swanage Dorset BH19 3DZ",
    "addr:postcode":"bh19 3dz",
    "addr:street":"Valley Road Harmans Cross",
    "iso:country":"GB",
    "sg:address":"Valley Road, Harmans Cross",
    "sg:city":"Swanage",
    "sg:classifiers":[
        {
            "category":"Autos & Motor Vehicles",
            "subcategory":"Automobile Sales",
            "type":"Retail Goods"
        }
    ],
    "sg:postcode":"BH19 3DZ",
    "sg:province":"Dorset",
    "sg:tags":[
        "car"
    ],
    "wof:name":"Foleys Garage",
    "wof:placetype":"venue"
},
  "geometry": {"coordinates":[-2.0211400986,50.6224403381],"type":"Point"}
}