{
  "type": "Feature",
  "properties": {
    "addr:full":"Copp Lane, Great Eccleston Preston Lancashire PR3 0ZN",
    "addr:postcode":"pr3 0zn",
    "addr:street":"Copp Lane",
    "iso:country":"GB",
    "sg:address":"Copp Lane, Great Eccleston",
    "sg:city":"Preston",
    "sg:classifiers":[
        {
            "category":"Education",
            "subcategory":"School",
            "type":"Public Place"
        },
        {
            "category":"Government",
            "subcategory":"Office",
            "type":"Public Place"
        }
    ],
    "sg:phone":"+44 1995 670969",
    "sg:postcode":"PR3 0ZN",
    "sg:province":"Lancashire",
    "sg:tags":[
        "local",
        "authority"
    ],
    "wof:name":"Great Eccleston Copp C of E Primary School",
    "wof:placetype":"venue"
},
  "geometry": {"coordinates":[-2.8737540245,53.853263855],"type":"Point"}
}