{
  "type": "Feature",
  "properties": {
    "iso:country":"GB",
    "sg:address":"22d Damson Way, Dragonville Indstl Est, Gilesgate",
    "sg:city":"Durham",
    "sg:classifiers":[
        {
            "category":"Building & Trades",
            "subcategory":"Cleaning & Sanitation",
            "type":"Services"
        }
    ],
    "sg:postcode":"DH1 2YN",
    "sg:province":"Durham",
    "sg:tags":[
        "blast"
    ],
    "wof:name":"Fastblast",
    "wof:placetype":"venue"
},
  "geometry": {"coordinates":[-1.5351690054,54.7759361267],"type":"Point"}
}