{
  "type": "Feature",
  "properties": {
    "iso:country":"GB",
    "sg:address":"2 Longthornton Road, Streatham",
    "sg:city":"London",
    "sg:classifiers":[
        {
            "category":"Home & Garden",
            "subcategory":"Kitchen Supply",
            "type":"Retail Goods"
        }
    ],
    "sg:phone":"+44 20 8679 7706",
    "sg:postcode":"SW16 5QD",
    "sg:province":"Greater London",
    "sg:tags":[
        "equipment",
        "catering"
    ],
    "wof:name":"Catersales Ltd.",
    "wof:placetype":"venue"
},
  "geometry": {"coordinates":[-0.141267,51.409336],"type":"Point"}
}