{
  "type": "Feature",
  "properties": {
    "addr:full":"25 Ely Place London Greater London EC1N 6TD",
    "addr:housenumber":"25",
    "addr:postcode":"ec1n 6td",
    "addr:street":"Ely Place",
    "iso:country":"GB",
    "sg:address":"25 Ely Place",
    "sg:city":"London",
    "sg:classifiers":[
        {
            "category":"Building & Trades",
            "subcategory":"Cleaning & Sanitation",
            "type":"Services"
        }
    ],
    "sg:phone":"+44 20 7405 2211",
    "sg:postcode":"EC1N 6TD",
    "sg:province":"Greater London",
    "sg:tags":[
        "facility"
    ],
    "wof:name":"Mowlem Aqumen Managed Services Ltd.",
    "wof:placetype":"venue"
},
  "geometry": {"coordinates":[-0.1068079993,51.5188484192],"type":"Point"}
}