{
  "type": "Feature",
  "properties": {
    "iso:country":"GB",
    "sg:address":"Hanover Court",
    "sg:city":"Banchory",
    "sg:classifiers":[
        {
            "category":"Organizations",
            "subcategory":"Community Association",
            "type":"Services"
        }
    ],
    "sg:phone":"+44 1330 822921",
    "sg:postcode":"AB31 5ZA",
    "sg:province":"Aberdeen City",
    "sg:tags":[
        "co-operatives",
        "society",
        "housing",
        "trust"
    ],
    "sg:website":"http://www.hsha.org.uk",
    "wof:name":"Hanover Scotland Housing Association Ltd",
    "wof:placetype":"venue"
},
  "geometry": {"coordinates":[-2.5013890266,57.0511741638],"type":"Point"}
}