{
  "type": "Feature",
  "properties": {
    "iso:country":"GB",
    "sg:address":"2 Brook Hill",
    "sg:city":"Sheffield",
    "sg:classifiers":[
        {
            "category":"Social Services",
            "subcategory":"Job Training",
            "type":"Services"
        }
    ],
    "sg:phone":"+44 1226 370227",
    "sg:postcode":"S36 4TB",
    "sg:province":"South Yorkshire",
    "sg:tags":[
        "translator",
        "interpreter"
    ],
    "wof:name":"Metier Language Facility",
    "wof:placetype":"venue"
},
  "geometry": {"coordinates":[-1.7430440187,53.5246162415],"type":"Point"}
}