{
  "type": "Feature",
  "properties": {
    "addr:full":"28 Station Road, Bentham Lancaster Lancashire LA2 7LF",
    "addr:housenumber":"28",
    "addr:postcode":"la2 7lf",
    "addr:street":"Station Road",
    "iso:country":"GB",
    "sg:address":"28 Station Road, Bentham",
    "sg:city":"Lancaster",
    "sg:classifiers":[
        {
            "category":"Building & Trades",
            "subcategory":"Plumbing",
            "type":"Services"
        }
    ],
    "sg:phone":"+44 15242 61294",
    "sg:postcode":"LA2 7LF",
    "sg:province":"Lancashire",
    "sg:tags":[
        "plumber",
        "heating"
    ],
    "wof:name":"T Cowgill & Sons",
    "wof:placetype":"venue"
},
  "geometry": {"coordinates":[-2.510361,54.116047],"type":"Point"}
}