{
  "type": "Feature",
  "properties": {
    "iso:country":"GB",
    "sg:address":"Ionian Studios, Halliwell Indust Est, Rossini St",
    "sg:city":"Bolton",
    "sg:classifiers":[
        {
            "category":"Shopping",
            "subcategory":"Musical Instruments",
            "type":"Retail Goods"
        }
    ],
    "sg:phone":"+44 1204 846635",
    "sg:postcode":"BL1 8DL",
    "sg:province":"Lancashire",
    "wof:name":"O J Luthier",
    "wof:placetype":"venue"
},
  "geometry": {"coordinates":[-2.440869,53.595276],"type":"Point"}
}