{
  "type": "Feature",
  "properties": {
    "iso:country":"GB",
    "sg:address":"Units 1, 2 & 3 Treeton Centre",
    "sg:city":"Rotherham",
    "sg:classifiers":[
        {
            "category":"Professional",
            "subcategory":"Printing & Photocopies",
            "type":"Services"
        }
    ],
    "sg:postcode":"S60 5QY",
    "sg:province":"South Yorkshire",
    "sg:tags":[
        "printer"
    ],
    "wof:name":"Pega Print Ltd.",
    "wof:placetype":"venue"
},
  "geometry": {"coordinates":[-1.357093,53.428932],"type":"Point"}
}