{
  "type": "Feature",
  "properties": {
    "addr:full":"8 High Newham Court Stockton-on-tees Durham TS19 8PD",
    "addr:housenumber":"8",
    "addr:postcode":"ts19 8pd",
    "addr:street":"High Newham Court",
    "iso:country":"GB",
    "sg:address":"8 High Newham Court",
    "sg:city":"Stockton-on-tees",
    "sg:classifiers":[
        {
            "category":"Government",
            "subcategory":"Post Office",
            "type":"Public Place"
        }
    ],
    "sg:phone":"+44 1642 601088",
    "sg:postcode":"TS19 8PD",
    "sg:province":"Durham",
    "wof:name":"Hardwick Estate Post Office",
    "wof:placetype":"venue"
},
  "geometry": {"coordinates":[-1.353164,54.583145],"type":"Point"}
}