{
  "type": "Feature",
  "properties": {
    "iso:country":"GB",
    "sg:address":"36 Station Road, Carcroft",
    "sg:city":"Doncaster",
    "sg:classifiers":[
        {
            "category":"Home & Garden",
            "subcategory":"Carpets & Floor Coverings",
            "type":"Retail Goods"
        }
    ],
    "sg:phone":"+44 1302 726399",
    "sg:postcode":"DN6 8DB",
    "sg:province":"North Yorkshire",
    "sg:tags":[
        "carpets",
        "rug",
        "matting"
    ],
    "wof:name":"Square Deal Carpets & Contract Floors Ltd.",
    "wof:placetype":"venue"
},
  "geometry": {"coordinates":[-1.1772760153,53.5807266235],"type":"Point"}
}