{
  "type": "Feature",
  "properties": {
    "addr:full":"20 Fennel Gro South Shields Tyne and Wear NE34 8TH",
    "addr:housenumber":"20",
    "addr:postcode":"ne34 8th",
    "addr:street":"Fennel Gro",
    "iso:country":"GB",
    "sg:address":"20 Fennel Gro",
    "sg:city":"South Shields",
    "sg:classifiers":[
        {
            "category":"Professional",
            "subcategory":"Employment Agencies",
            "type":"Services"
        }
    ],
    "sg:phone":"+44 191 426 2296",
    "sg:postcode":"NE34 8TH",
    "sg:province":"Tyne and Wear",
    "sg:tags":[
        "pair",
        "au"
    ],
    "wof:name":"Brittannia International Au Pair Agency",
    "wof:placetype":"venue"
},
  "geometry": {"coordinates":[-1.4202500582,54.9628715515],"type":"Point"}
}