{
  "type": "Feature",
  "properties": {
    "addr:full":"Oxford Road, Chapel Lane Chipping Norton Gloucestershire OX7 4LT",
    "addr:postcode":"ox7 4lt",
    "addr:street":"Oxford Road Chapel Lane",
    "iso:country":"GB",
    "sg:address":"Oxford Road, Chapel Lane",
    "sg:city":"Chipping Norton",
    "sg:classifiers":[
        {
            "category":"Shopping",
            "subcategory":"Department Store",
            "type":"Retail Goods"
        }
    ],
    "sg:postcode":"OX7 4LT",
    "sg:province":"Gloucestershire",
    "wof:name":"John Cockerill",
    "wof:placetype":"venue"
},
  "geometry": {"coordinates":[-1.457072,51.918789],"type":"Point"}
}