{
  "type": "Feature",
  "properties": {
    "addr:full":"22 Kinkell Avenue Glenrothes Fife KY7 4QG",
    "addr:housenumber":"22",
    "addr:postcode":"ky7 4qg",
    "addr:street":"Kinkell Avenue",
    "iso:country":"GB",
    "sg:address":"22 Kinkell Avenue",
    "sg:city":"Glenrothes",
    "sg:classifiers":[
        {
            "category":"Professional",
            "subcategory":"Accounting & Tax Preparation",
            "type":"Services"
        }
    ],
    "sg:phone":"+44 1592 771217",
    "sg:postcode":"KY7 4QG",
    "sg:province":"Fife",
    "sg:tags":[
        "accountant"
    ],
    "wof:name":"James M Boyd",
    "wof:placetype":"venue"
},
  "geometry": {"coordinates":[-3.169731,56.188953],"type":"Point"}
}