{
  "type": "Feature",
  "properties": {
    "addr:full":"1 Spring Bank Place Stockport Cheshire SK1 3TG",
    "addr:housenumber":"1",
    "addr:postcode":"sk1 3tg",
    "addr:street":"Spring Bank Place",
    "iso:country":"GB",
    "sg:address":"1 Spring Bank Place",
    "sg:city":"Stockport",
    "sg:classifiers":[
        {
            "category":"Manufacturing",
            "subcategory":"Signs",
            "type":"Manufacturing & Wholesale Goods"
        }
    ],
    "sg:postcode":"SK1 3TG",
    "sg:province":"Cheshire",
    "sg:tags":[
        "poster",
        "writer"
    ],
    "wof:name":"Electric Poster Co",
    "wof:placetype":"venue"
},
  "geometry": {"coordinates":[-2.1598289013,53.4066047668],"type":"Point"}
}