{
  "type": "Feature",
  "properties": {
    "addr:full":"18 Thorny Croft Road, Wavertree Liverpool Merseyside L15 0EW",
    "addr:housenumber":"18",
    "addr:postcode":"l15 0ew",
    "addr:street":"Thorny Croft Road",
    "iso:country":"GB",
    "sg:address":"18 Thorny Croft Road, Wavertree",
    "sg:city":"Liverpool",
    "sg:classifiers":[
        {
            "category":"Real Estate",
            "subcategory":"Real Estate Operator",
            "type":"Services"
        }
    ],
    "sg:phone":"+44 151 733 9796",
    "sg:postcode":"L15 0EW",
    "sg:province":"Merseyside",
    "sg:tags":[
        "letting",
        "agent"
    ],
    "wof:name":"Universal Property Services",
    "wof:placetype":"venue"
},
  "geometry": {"coordinates":[-2.9347839355,53.3943252563],"type":"Point"}
}