{
  "type": "Feature",
  "properties": {
    "iso:country":"GB",
    "sg:address":"37 Reddown Road",
    "sg:city":"Coulsdon",
    "sg:classifiers":[
        {
            "category":"Social Services",
            "subcategory":"Retirement Home",
            "type":"Services"
        }
    ],
    "sg:postcode":"CR5 1AN",
    "sg:province":"Surrey",
    "sg:tags":[
        "residential",
        "care"
    ],
    "wof:name":"Agora Lodge",
    "wof:placetype":"venue"
},
  "geometry": {"coordinates":[-0.140171,51.312263],"type":"Point"}
}