{
  "type": "Feature",
  "properties": {
    "iso:country":"GB",
    "sg:address":"Roe Hill, Woodborough",
    "sg:city":"Nottingham",
    "sg:classifiers":[
        {
            "category":"Social Services",
            "subcategory":"Adult Care",
            "type":"Services"
        },
        {
            "category":"Government",
            "subcategory":"Office",
            "type":"Public Place"
        }
    ],
    "sg:postcode":"NG14 6DS",
    "sg:province":"Nottinghamshire",
    "sg:tags":[
        "housing",
        "local",
        "sheltered"
    ],
    "wof:name":"Roe Hill Sheltered Housing",
    "wof:placetype":"venue"
},
  "geometry": {"coordinates":[-1.0604640245,53.0251617432],"type":"Point"}
}