{
  "type": "Feature",
  "properties": {
    "addr:full":"9 Nevada St Greenwich Greater London SE10 9JL",
    "addr:housenumber":"9",
    "addr:postcode":"se10 9jl",
    "addr:street":"Nevada St",
    "iso:country":"GB",
    "sg:address":"9 Nevada St",
    "sg:city":"Greenwich",
    "sg:classifiers":[
        {
            "category":"Arts & Performance",
            "subcategory":"Art Gallery",
            "type":"Entertainment"
        }
    ],
    "sg:phone":"+44 20 8305 1666",
    "sg:postcode":"SE10 9JL",
    "sg:province":"Greater London",
    "wof:name":"Greenwich Gallery",
    "wof:placetype":"venue"
},
  "geometry": {"coordinates":[-0.00784,51.479698],"type":"Point"}
}