{
  "type": "Feature",
  "properties": {
    "addr:full":"Alexandra House, 307-315 Cowbridge Road East Cardiff Cardiff CF5 1JD",
    "addr:housenumber":"307-315",
    "addr:postcode":"cf5 1jd",
    "addr:street":"Cowbridge Road East",
    "iso:country":"GB",
    "sg:address":"Alexandra House, 307-315 Cowbridge Road East",
    "sg:city":"Cardiff",
    "sg:classifiers":[
        {
            "category":"Professional",
            "subcategory":"Engineering",
            "type":"Services"
        }
    ],
    "sg:phone":"+44 29 2023 3503",
    "sg:postcode":"CF5 1JD",
    "sg:province":"Cardiff",
    "sg:tags":[
        "consulting",
        "design",
        "engineer"
    ],
    "wof:name":"Babtie Group Ltd.",
    "wof:placetype":"venue"
},
  "geometry": {"coordinates":[-3.2039830685,51.4817123413],"type":"Point"}
}