{
  "type": "Feature",
  "properties": {
    "iso:country":"GB",
    "sg:address":"140 East Street",
    "sg:city":"South Molton",
    "sg:classifiers":[
        {
            "category":"Shopping",
            "subcategory":"News",
            "type":"Retail Goods"
        }
    ],
    "sg:postcode":"EX36 3BU",
    "sg:province":"Devon",
    "sg:tags":[
        "newsagent"
    ],
    "wof:name":"The Little Shop",
    "wof:placetype":"venue"
},
  "geometry": {"coordinates":[-3.832943,51.018085],"type":"Point"}
}