{
  "type": "Feature",
  "properties": {
    "iso:country":"GB",
    "sg:address":"7 Derry Hill, Menston",
    "sg:city":"Ilkley",
    "sg:classifiers":[
        {
            "category":"Food & Beverages",
            "subcategory":"Bakery",
            "type":"Retail Goods"
        }
    ],
    "sg:phone":"+44 1943 877673",
    "sg:postcode":"LS29 6NE",
    "sg:province":"North Yorkshire",
    "sg:tags":[
        "shop",
        "baker"
    ],
    "wof:name":"Jepsons Bakery",
    "wof:placetype":"venue"
},
  "geometry": {"coordinates":[-1.746071,53.891109],"type":"Point"}
}