{
  "type": "Feature",
  "properties": {
    "addr:full":"7 Quarry Lane Wirral Merseyside CH61 7XA",
    "addr:housenumber":"7",
    "addr:postcode":"ch61 7xa",
    "addr:street":"Quarry Lane",
    "iso:country":"GB",
    "sg:address":"7 Quarry Lane",
    "sg:city":"Wirral",
    "sg:classifiers":[
        {
            "category":"Professional",
            "subcategory":"Business Services",
            "type":"Services"
        }
    ],
    "sg:phone":"+44 151 648 7341",
    "sg:postcode":"CH61 7XA",
    "sg:province":"Merseyside",
    "sg:tags":[
        "hospitality",
        "corporate"
    ],
    "wof:name":"Wirral Sporting Developments",
    "wof:placetype":"venue"
},
  "geometry": {"coordinates":[-3.093143,53.35331],"type":"Point"}
}