{
  "type": "Feature",
  "properties": {
    "addr:full":"35 Priestlands Park Road Sidcup Kent DA15 7HJ",
    "addr:housenumber":"35",
    "addr:postcode":"da15 7hj",
    "addr:street":"Priestlands Park Road",
    "iso:country":"GB",
    "sg:address":"35 Priestlands Park Road",
    "sg:city":"Sidcup",
    "sg:classifiers":[
        {
            "category":"Health Services",
            "subcategory":"Nursing And Care Facility",
            "type":"Services"
        }
    ],
    "sg:phone":"+44 20 8300 4285",
    "sg:postcode":"DA15 7HJ",
    "sg:province":"Kent",
    "sg:tags":[
        "home",
        "agency"
    ],
    "wof:name":"ST AUBYNS NURSING HOME",
    "wof:placetype":"venue"
},
  "geometry": {"coordinates":[0.096139,51.429493],"type":"Point"}
}