{
  "type": "Feature",
  "properties": {
    "iso:country":"GB",
    "sg:address":"82 Earlham Road",
    "sg:city":"Norwich",
    "sg:classifiers":[
        {
            "category":"Professional",
            "subcategory":"Computer Services",
            "type":"Services"
        }
    ],
    "sg:phone":"+44 1603 766550",
    "sg:postcode":"NR2 3HA",
    "sg:province":"Norfolk",
    "sg:tags":[
        "system",
        "software"
    ],
    "wof:name":"Durrant Software Ltd.",
    "wof:placetype":"venue"
},
  "geometry": {"coordinates":[1.2751259804,52.6303062439],"type":"Point"}
}