{
  "type": "Feature",
  "properties": {
    "iso:country":"GB",
    "sg:address":"Upper Llantydwell House, Tavernspite",
    "sg:city":"Whitland",
    "sg:classifiers":[
        {
            "category":"Building & Trades",
            "subcategory":"Construction",
            "type":"Services"
        }
    ],
    "sg:phone":"+44 1834 831183",
    "sg:postcode":"SA34 0NR",
    "sg:province":"Carmarthenshire",
    "sg:tags":[
        "builder"
    ],
    "wof:name":"A.J.T. Building Ltd",
    "wof:placetype":"venue"
},
  "geometry": {"coordinates":[-4.612054,51.819256],"type":"Point"}
}