{
  "type": "Feature",
  "properties": {
    "addr:full":"Unit 1 Leyton Avenue, Mildenhall Bury St Edmunds Cambridgeshire IP28 7BL",
    "addr:housenumber":"unit 1",
    "addr:postcode":"ip28 7bl",
    "addr:street":"Leyton Avenue;St",
    "iso:country":"GB",
    "sg:address":"Unit 1 Leyton Avenue, Mildenhall",
    "sg:city":"Bury St Edmunds",
    "sg:classifiers":[
        {
            "category":"Building & Trades",
            "subcategory":"Cleaning & Sanitation",
            "type":"Services"
        }
    ],
    "sg:phone":"+44 1638 712954",
    "sg:postcode":"IP28 7BL",
    "sg:province":"Cambridgeshire",
    "sg:tags":[
        "door",
        "manufacturer"
    ],
    "wof:name":"Assured Doors",
    "wof:placetype":"venue"
},
  "geometry": {"coordinates":[0.507379,52.354568],"type":"Point"}
}