{
  "type": "Feature",
  "properties": {
    "iso:country":"GB",
    "sg:address":"The Crescent, Hetton-le-hole",
    "sg:city":"Houghton-le-spring",
    "sg:classifiers":[
        {
            "category":"Personal",
            "subcategory":"Beauty Salon",
            "type":"Services"
        }
    ],
    "sg:postcode":"DH5 9JS",
    "sg:province":"Durham",
    "sg:tags":[
        "unisex",
        "hairdresser"
    ],
    "wof:name":"Uppercut",
    "wof:placetype":"venue"
},
  "geometry": {"coordinates":[-1.455419,54.818199],"type":"Point"}
}