{
  "type": "Feature",
  "properties": {
    "addr:full":"19 High Street Banstead Surrey SM7 2NE",
    "addr:housenumber":"19",
    "addr:postcode":"sm7 2ne",
    "addr:street":"High Street",
    "iso:country":"GB",
    "sg:address":"19 High Street",
    "sg:city":"Banstead",
    "sg:classifiers":[
        {
            "category":"Personal",
            "subcategory":"Barber",
            "type":"Services"
        }
    ],
    "sg:phone":"+44 1737 371644",
    "sg:postcode":"SM7 2NE",
    "sg:province":"Surrey",
    "sg:tags":[
        "men's",
        "hairdresser"
    ],
    "wof:name":"The Barbers Room",
    "wof:placetype":"venue"
},
  "geometry": {"coordinates":[-0.203652,51.322281],"type":"Point"}
}