{
  "type": "Feature",
  "properties": {
    "addr:full":"Vicarage Lane, Hoo Rochester Kent ME3 9LB",
    "addr:postcode":"me3 9lb",
    "addr:street":"Vicarage Lane",
    "iso:country":"GB",
    "sg:address":"Vicarage Lane, Hoo",
    "sg:city":"Rochester",
    "sg:classifiers":[
        {
            "category":"Education",
            "subcategory":"Special Training",
            "type":"Public Place"
        }
    ],
    "sg:phone":"+44 1634 252250",
    "sg:postcode":"ME3 9LB",
    "sg:province":"Kent",
    "sg:tags":[
        "product",
        "centre"
    ],
    "wof:name":"Safe Handling",
    "wof:placetype":"venue"
},
  "geometry": {"coordinates":[0.564301,51.419312],"type":"Point"}
}