{
  "type": "Feature",
  "properties": {
    "iso:country":"GB",
    "sg:address":"Wallace Walk, Pococks Lane, Eton",
    "sg:city":"Windsor",
    "sg:classifiers":[
        {
            "category":"Community Center",
            "type":"Public Place"
        }
    ],
    "sg:phone":"+44 1753 770037",
    "sg:postcode":"SL4 6HN",
    "sg:province":"Berkshire",
    "sg:tags":[
        "recreation",
        "leisure",
        "centre"
    ],
    "wof:name":"Thames Valley Athletics Centre",
    "wof:placetype":"venue"
},
  "geometry": {"coordinates":[-0.609369,51.49192],"type":"Point"}
}