{
  "type": "Feature",
  "properties": {
    "iso:country":"GB",
    "sg:address":"The Workshop, Green St",
    "sg:city":"Huddersfield",
    "sg:classifiers":[
        {
            "category":"Community Center",
            "subcategory":"Youth",
            "type":"Public Place"
        }
    ],
    "sg:phone":"+44 1484 851685",
    "sg:postcode":"HD7 3NP",
    "sg:province":"West Yorkshire",
    "sg:tags":[
        "children's",
        "activity"
    ],
    "wof:name":"Little Nippers Play Gym",
    "wof:placetype":"venue"
},
  "geometry": {"coordinates":[-1.78268,53.64695],"type":"Point"}
}