{
  "type": "Feature",
  "properties": {
    "addr:full":"6 Orchard Avenue, Bothwell Glasgow Glasgow City G71 8NF",
    "addr:housenumber":"6",
    "addr:postcode":"g71 8nf",
    "addr:street":"Orchard Avenue",
    "iso:country":"GB",
    "sg:address":"6 Orchard Avenue, Bothwell",
    "sg:city":"Glasgow",
    "sg:classifiers":[
        {
            "category":"Education",
            "subcategory":"Special Training",
            "type":"Public Place"
        },
        {
            "category":"Professional",
            "subcategory":"Employment Agencies",
            "type":"Services"
        }
    ],
    "sg:postcode":"G71 8NF",
    "sg:province":"Glasgow City",
    "sg:tags":[
        "consultant",
        "product",
        "centre"
    ],
    "wof:name":"Microcom (Scotland) Ltd.",
    "wof:placetype":"venue"
},
  "geometry": {"coordinates":[-4.0626950264,55.7994041443],"type":"Point"}
}