{
  "type": "Feature",
  "properties": {
    "addr:full":"1 Eastern Road, Walthamstow London Greater London E17 9DU",
    "addr:housenumber":"1",
    "addr:postcode":"e17 9du",
    "addr:street":"Eastern Road",
    "iso:country":"GB",
    "sg:address":"1 Eastern Road, Walthamstow",
    "sg:city":"London",
    "sg:classifiers":[
        {
            "category":"Building & Trades",
            "subcategory":"Plumbing",
            "type":"Services"
        }
    ],
    "sg:postcode":"E17 9DU",
    "sg:province":"Greater London",
    "sg:tags":[
        "central",
        "heating"
    ],
    "wof:name":"Jeff Britten",
    "wof:placetype":"venue"
},
  "geometry": {"coordinates":[-0.003213,51.581074],"type":"Point"}
}