{
  "type": "Feature",
  "properties": {
    "addr:full":"Cameron House, 9 Thorne Road Doncaster South Yorkshire DN1 2HP",
    "addr:housenumber":"9",
    "addr:postcode":"dn1 2hp",
    "addr:street":"Cameron;Thorne Road",
    "iso:country":"GB",
    "sg:address":"Cameron House, 9 Thorne Road",
    "sg:city":"Doncaster",
    "sg:classifiers":[
        {
            "category":"Banks & Credit Unions",
            "subcategory":"Investment Brokerage",
            "type":"Services"
        }
    ],
    "sg:postcode":"DN1 2HP",
    "sg:province":"South Yorkshire",
    "sg:tags":[
        "stockbroker"
    ],
    "wof:name":"Nicholson Barber & Co.",
    "wof:placetype":"venue"
},
  "geometry": {"coordinates":[-1.1278500557,53.5235214233],"type":"Point"}
}