{
  "type": "Feature",
  "properties": {
    "addr:full":"33 Hamilton St Saltcoats North Ayrshire KA21 5DT",
    "addr:housenumber":"33",
    "addr:postcode":"ka21 5dt",
    "addr:street":"Hamilton St",
    "iso:country":"GB",
    "sg:address":"33 Hamilton St",
    "sg:city":"Saltcoats",
    "sg:classifiers":[
        {
            "category":"Home & Garden",
            "subcategory":"Furniture",
            "type":"Retail Goods"
        }
    ],
    "sg:postcode":"KA21 5DT",
    "sg:province":"North Ayrshire",
    "wof:name":"Ayrshire Discount Furniture",
    "wof:placetype":"venue"
},
  "geometry": {"coordinates":[-4.7904238701,55.6346244812],"type":"Point"}
}