{
  "type": "Feature",
  "properties": {
    "addr:full":"30-34 Langham Street London Greater London W1W 7AW",
    "addr:housenumber":"30-34",
    "addr:postcode":"w1w 7aw",
    "addr:street":"Langham Street",
    "iso:country":"GB",
    "sg:address":"30-34 Langham Street",
    "sg:city":"London",
    "sg:classifiers":[
        {
            "category":"Communications",
            "type":"Services"
        },
        {
            "category":"Utilities",
            "type":"Services"
        }
    ],
    "sg:postcode":"W1W 7AW",
    "sg:province":"Greater London",
    "sg:tags":[
        "internet",
        "audio-visual"
    ],
    "wof:name":"2 C S Communications Ltd.",
    "wof:placetype":"venue"
},
  "geometry": {"coordinates":[-0.137379,51.518715],"type":"Point"}
}