{
  "type": "Feature",
  "properties": {
    "addr:full":"23 Stonecot Hill Sutton Surrey SM3 9HB",
    "addr:housenumber":"23",
    "addr:postcode":"sm3 9hb",
    "addr:street":"Stonecot Hill",
    "iso:country":"GB",
    "sg:address":"23 Stonecot Hill",
    "sg:city":"Sutton",
    "sg:classifiers":[
        {
            "category":"Restaurant",
            "type":"Food & Drink"
        }
    ],
    "sg:phone":"+44 20 8644 7743",
    "sg:postcode":"SM3 9HB",
    "sg:province":"Surrey",
    "wof:name":"Partners Brasserie",
    "wof:placetype":"venue"
},
  "geometry": {"coordinates":[-0.2118899971,51.3850631714],"type":"Point"}
}