{
  "type": "Feature",
  "properties": {
    "iso:country":"GB",
    "sg:address":"37 Westow Hill",
    "sg:city":"Upper Norwood",
    "sg:classifiers":[
        {
            "category":"Travel",
            "subcategory":"Travel Agent",
            "type":"Entertainment"
        }
    ],
    "sg:phone":"+44 20 8670 8282",
    "sg:postcode":"SE19 1TQ",
    "sg:province":"Greater London",
    "wof:name":"Thorn & Young Ltd",
    "wof:placetype":"venue"
},
  "geometry": {"coordinates":[-0.0811989978,51.4197311401],"type":"Point"}
}