{
  "type": "Feature",
  "properties": {
    "addr:full":"67 Perry Street Billericay Essex CM12 0NA",
    "addr:housenumber":"67",
    "addr:postcode":"cm12 0na",
    "addr:street":"Perry Street",
    "iso:country":"GB",
    "sg:address":"67 Perry Street",
    "sg:city":"Billericay",
    "sg:classifiers":[
        {
            "category":"Farming",
            "subcategory":"Nursery",
            "type":"Manufacturing & Wholesale Goods"
        },
        {
            "category":"Education",
            "subcategory":"Preschool",
            "type":"Public Place"
        }
    ],
    "sg:phone":"+44 1277 633055",
    "sg:postcode":"CM12 0NA",
    "sg:province":"Essex",
    "sg:tags":[
        "school",
        "creche"
    ],
    "wof:name":"H U Din",
    "wof:placetype":"venue"
},
  "geometry": {"coordinates":[0.4108119905,51.6345558167],"type":"Point"}
}