{
  "type": "Feature",
  "properties": {
    "addr:full":"6 Ferry Road, Hollybank, Hythe Southampton Hampshire SO45 5GD",
    "addr:housenumber":"6",
    "addr:postcode":"so45 5gd",
    "addr:street":"Ferry Road",
    "iso:country":"GB",
    "sg:address":"6 Ferry Road, Hollybank, Hythe",
    "sg:city":"Southampton",
    "sg:classifiers":[
        {
            "category":"Education",
            "subcategory":"Dance Studio",
            "type":"Public Place"
        }
    ],
    "sg:postcode":"SO45 5GD",
    "sg:province":"Hampshire",
    "sg:tags":[
        "toning"
    ],
    "wof:name":"Eden Health & Beauty",
    "wof:placetype":"venue"
},
  "geometry": {"coordinates":[-1.40532,50.865372],"type":"Point"}
}