{
  "type": "Feature",
  "properties": {
    "addr:full":"P O Box 3388, Rednal Birmingham West Midlands B45 9PL",
    "addr:housenumber":"p o;3388",
    "addr:postcode":"b45 9pl",
    "addr:street":"Rednal",
    "iso:country":"GB",
    "sg:address":"P O Box 3388, Rednal",
    "sg:city":"Birmingham",
    "sg:classifiers":[
        {
            "category":"Travel",
            "subcategory":"Travel Agent",
            "type":"Entertainment"
        }
    ],
    "sg:phone":"+44 121 457 8897",
    "sg:postcode":"B45 9PL",
    "sg:province":"West Midlands",
    "wof:name":"Wingspan Worldwide",
    "wof:placetype":"venue"
},
  "geometry": {"coordinates":[-2.020222,52.392189],"type":"Point"}
}