{
  "type": "Feature",
  "properties": {
    "iso:country":"GB",
    "sg:address":"Rear Of 132 Osborne Road",
    "sg:city":"Pontypool",
    "sg:classifiers":[
        {
            "category":"Wholesale",
            "subcategory":"Fruits & Vegetables",
            "type":"Manufacturing & Wholesale Goods"
        }
    ],
    "sg:postcode":"NP4 6LT",
    "sg:province":"Monmouthshire",
    "wof:name":"Riverside Fresh Produce",
    "wof:placetype":"venue"
},
  "geometry": {"coordinates":[-3.0431900024,51.703086853],"type":"Point"}
}