{
  "type": "Feature",
  "properties": {
    "addr:full":"45 Kingston Road Portsmouth Hampshire PO2 7DP",
    "addr:housenumber":"45",
    "addr:postcode":"hampshire po2 7dp",
    "addr:street":"Kingston Road",
    "iso:country":"GB",
    "sg:address":"45 Kingston Road",
    "sg:city":"Portsmouth",
    "sg:classifiers":[
        {
            "category":"Shopping",
            "subcategory":"Antiques",
            "type":"Retail Goods"
        }
    ],
    "sg:phone":"+44 23 9275 2557",
    "sg:postcode":"PO2 7DP",
    "sg:province":"Hampshire",
    "wof:name":"Squirrels",
    "wof:placetype":"venue"
},
  "geometry": {"coordinates":[-1.077489,50.808079],"type":"Point"}
}