{
  "type": "Feature",
  "properties": {
    "addr:full":"Tun Abdul Razak Laboratory, Brickendonbury Hertford Hertfordshire SG13 8NL",
    "addr:postcode":"sg13 8nl",
    "addr:street":"Hertford",
    "iso:country":"GB",
    "sg:address":"Tun Abdul Razak Laboratory, Brickendonbury",
    "sg:city":"Hertford",
    "sg:classifiers":[
        {
            "category":"Professional",
            "subcategory":"Printing & Photocopies",
            "type":"Services"
        }
    ],
    "sg:phone":"+44 1992 554657",
    "sg:postcode":"SG13 8NL",
    "sg:province":"Hertfordshire",
    "sg:tags":[
        "rubber",
        "stamp"
    ],
    "wof:name":"Tun Abdul Razak Research Centre",
    "wof:placetype":"venue"
},
  "geometry": {"coordinates":[-0.084236,51.755196],"type":"Point"}
}