{
  "type": "Feature",
  "properties": {
    "addr:full":"39 Heath Road Twickenham Greater London TW1 4AW",
    "addr:housenumber":"39",
    "addr:postcode":"tw1 4aw",
    "addr:street":"Heath Road",
    "iso:country":"GB",
    "sg:address":"39 Heath Road",
    "sg:city":"Twickenham",
    "sg:classifiers":[
        {
            "category":"Restaurant",
            "type":"Food & Drink"
        }
    ],
    "sg:phone":"+44 20 8892 5815",
    "sg:postcode":"TW1 4AW",
    "sg:province":"Greater London",
    "wof:name":"Wineland Steakhouse",
    "wof:placetype":"venue"
},
  "geometry": {"coordinates":[-0.332296,51.445011],"type":"Point"}
}