{
  "type": "Feature",
  "properties": {
    "iso:country":"GB",
    "sg:address":"113 Bromley Rd",
    "sg:city":"Colchester",
    "sg:classifiers":[
        {
            "category":"Bars & Pubs",
            "type":"Food & Drink"
        }
    ],
    "sg:phone":"+44 1206 863667",
    "sg:postcode":"CO4 3JG",
    "sg:province":"Essex",
    "sg:tags":[
        "pubs",
        "inn"
    ],
    "wof:name":"The Beehive Inn",
    "wof:placetype":"venue"
},
  "geometry": {"coordinates":[0.948083,51.897007],"type":"Point"}
}