{
  "type": "Feature",
  "properties": {
    "addr:full":"Wheats Close Widnes Cheshire WA8 9LE",
    "addr:postcode":"wa8 9le",
    "addr:street":"Wheats Close",
    "iso:country":"GB",
    "sg:address":"Wheats Close",
    "sg:city":"Widnes",
    "sg:classifiers":[
        {
            "category":"Bars & Pubs",
            "type":"Food & Drink"
        }
    ],
    "sg:phone":"+44 151 424 8063",
    "sg:postcode":"WA8 9LE",
    "sg:province":"Cheshire",
    "sg:tags":[
        "pubs",
        "inn"
    ],
    "wof:name":"8 Towers",
    "wof:placetype":"venue"
},
  "geometry": {"coordinates":[-2.7332439423,53.3740310669],"type":"Point"}
}