{
  "type": "Feature",
  "properties": {
    "iso:country":"GB",
    "sg:address":"1 Braganza Street",
    "sg:city":"London",
    "sg:classifiers":[
        {
            "category":"Food & Beverages",
            "subcategory":"Liquor & Beverages",
            "type":"Retail Goods"
        }
    ],
    "sg:phone":"+44 20 7735 9898",
    "sg:postcode":"SE17 3RD",
    "sg:province":"Greater London",
    "sg:tags":[
        "beer",
        "spirit",
        "wines"
    ],
    "wof:name":"B D Wines",
    "wof:placetype":"venue"
},
  "geometry": {"coordinates":[-0.105424,51.48822],"type":"Point"}
}