{
  "type": "Feature",
  "properties": {
    "addr:full":"Eccles Road, Hunters Quay Dunoon Argyll and Bute PA23 8LB",
    "addr:postcode":"pa23 8lb",
    "addr:street":"Eccles Road",
    "iso:country":"GB",
    "sg:address":"Eccles Road, Hunters Quay",
    "sg:city":"Dunoon",
    "sg:classifiers":[
        {
            "category":"Social Services",
            "subcategory":"Retirement Home",
            "type":"Services"
        }
    ],
    "sg:phone":"+44 1369 705211",
    "sg:postcode":"PA23 8LB",
    "sg:province":"Argyll and Bute",
    "sg:tags":[
        "residential",
        "care"
    ],
    "wof:name":"Holly Lodge Residential Home",
    "wof:placetype":"venue"
},
  "geometry": {"coordinates":[-4.921698,55.952366],"type":"Point"}
}