{
  "type": "Feature",
  "properties": {
    "addr:full":"191 Broomloan Rd, Govan Glasgow Glasgow City G51 2JE",
    "addr:housenumber":"191",
    "addr:postcode":"g51 2je",
    "addr:street":"Broomloan Rd",
    "iso:country":"GB",
    "sg:address":"191 Broomloan Rd, Govan",
    "sg:city":"Glasgow",
    "sg:classifiers":[
        {
            "category":"Building & Trades",
            "subcategory":"Construction",
            "type":"Services"
        }
    ],
    "sg:phone":"+44 141 445 0111",
    "sg:postcode":"G51 2JE",
    "sg:province":"Glasgow City",
    "sg:tags":[
        "builder"
    ],
    "wof:name":"Waterbay Ltd",
    "wof:placetype":"venue"
},
  "geometry": {"coordinates":[-4.310888,55.855663],"type":"Point"}
}