{
  "type": "Feature",
  "properties": {
    "addr:full":"57 Station Road, Longfield Dartford Kent DA3 7QA",
    "addr:housenumber":"57",
    "addr:postcode":"da3 7qa",
    "addr:street":"Station Road",
    "iso:country":"GB",
    "sg:address":"57 Station Road, Longfield",
    "sg:city":"Dartford",
    "sg:classifiers":[
        {
            "category":"Home & Garden",
            "subcategory":"Home Furnishings",
            "type":"Retail Goods"
        },
        {
            "category":"Home & Garden",
            "subcategory":"Building Materials",
            "type":"Retail Goods"
        }
    ],
    "sg:phone":"+44 1474 705511",
    "sg:postcode":"DA3 7QA",
    "sg:province":"Kent",
    "sg:tags":[
        "installers",
        "planner",
        "kitchen",
        "furnishers"
    ],
    "wof:name":"Family Kitchens",
    "wof:placetype":"venue"
},
  "geometry": {"coordinates":[0.3000130057,51.3971939087],"type":"Point"}
}