{
  "type": "Feature",
  "properties": {
    "addr:full":"9 Heyes Terrace, Old Heyes Road Altrincham Cheshire WA15 6EN",
    "addr:housenumber":"9",
    "addr:postcode":"wa15 6en",
    "addr:street":"Heyes Terrace Old Heyes Road",
    "iso:country":"GB",
    "sg:address":"9 Heyes Terrace, Old Heyes Road",
    "sg:city":"Altrincham",
    "sg:classifiers":[
        {
            "category":"Professional",
            "subcategory":"Engineering",
            "type":"Services"
        }
    ],
    "sg:postcode":"WA15 6EN",
    "sg:province":"Cheshire",
    "sg:tags":[
        "contractor",
        "electrical",
        "engineer"
    ],
    "wof:name":"Donald G Gollings",
    "wof:placetype":"venue"
},
  "geometry": {"coordinates":[-2.3241500854,53.4015464783],"type":"Point"}
}