{
  "type": "Feature",
  "properties": {
    "addr:full":"3 Ocean Park, Burrfields Road Portsmouth Hampshire PO3 5NP",
    "addr:housenumber":"3",
    "addr:postcode":"hampshire po3 5np",
    "addr:street":"Ocean Park Burrfields Road",
    "iso:country":"GB",
    "sg:address":"3 Ocean Park, Burrfields Road",
    "sg:city":"Portsmouth",
    "sg:classifiers":[
        {
            "category":"Home & Garden",
            "subcategory":"Hardware",
            "type":"Retail Goods"
        }
    ],
    "sg:phone":"+44 23 9269 1217",
    "sg:postcode":"PO3 5NP",
    "sg:province":"Hampshire",
    "sg:tags":[
        "shop",
        "retailer",
        "diy"
    ],
    "sg:website":"http://www.homebase.co.uk",
    "wof:name":"Homebase Ltd",
    "wof:placetype":"venue"
},
  "geometry": {"coordinates":[-1.0641059875,50.8171539307],"type":"Point"}
}