{
  "type": "Feature",
  "properties": {
    "addr:full":"4 Brian Close Chelmsford Essex CM2 9EA",
    "addr:housenumber":"4",
    "addr:postcode":"cm2 9ea",
    "addr:street":"Brian Close",
    "iso:country":"GB",
    "sg:address":"4 Brian Close",
    "sg:city":"Chelmsford",
    "sg:classifiers":[
        {
            "category":"Fast Food",
            "type":"Food & Drink"
        }
    ],
    "sg:postcode":"CM2 9EA",
    "sg:province":"Essex",
    "sg:tags":[
        "away",
        "take"
    ],
    "wof:name":"Stuart Kendrew",
    "wof:placetype":"venue"
},
  "geometry": {"coordinates":[0.471743,51.716866],"type":"Point"}
}