{
  "type": "Feature",
  "properties": {
    "iso:country":"GB",
    "sg:address":"171 South St",
    "sg:city":"Romford",
    "sg:classifiers":[
        {
            "category":"Bus Charters",
            "type":"Transportation"
        }
    ],
    "sg:phone":"+44 1708 747874",
    "sg:postcode":"RM1 1PS",
    "sg:province":"Essex",
    "sg:tags":[
        "coach"
    ],
    "wof:name":"Frontrunner Buses Ltd",
    "wof:placetype":"venue"
},
  "geometry": {"coordinates":[0.184098,51.57362],"type":"Point"}
}