{
  "type": "Feature",
  "properties": {
    "iso:country":"GB",
    "sg:address":"Hall House Indust Est, Beehive La",
    "sg:city":"Kendal",
    "sg:classifiers":[
        {
            "category":"Professional",
            "subcategory":"Art Services",
            "type":"Services"
        }
    ],
    "sg:phone":"+44 1539 720007",
    "sg:postcode":"LA8 0AH",
    "sg:province":"Cumbria",
    "sg:tags":[
        "photographer"
    ],
    "wof:name":"Mayo Photography",
    "wof:placetype":"venue"
},
  "geometry": {"coordinates":[-2.69111,54.317139],"type":"Point"}
}