{
  "type": "Feature",
  "properties": {
    "iso:country":"GB",
    "sg:address":"42 High Street, Gatehouse Of Fleet",
    "sg:city":"Castle Douglas",
    "sg:classifiers":[
        {
            "category":"Shopping",
            "subcategory":"Department Store",
            "type":"Retail Goods"
        },
        {
            "category":"Transit Center",
            "subcategory":"Freight",
            "type":"Transportation"
        }
    ],
    "sg:phone":"+44 1557 814482",
    "sg:postcode":"DG7 2HP",
    "sg:province":"Dumfries and Galloway",
    "sg:tags":[
        "shop",
        "craft",
        "centre"
    ],
    "wof:name":"Kaleidoscope",
    "wof:placetype":"venue"
},
  "geometry": {"coordinates":[-4.183027,54.882366],"type":"Point"}
}