{
  "type": "Feature",
  "properties": {
    "addr:full":"1 Frilsham Park, Yattendon Newbury Berkshire RG18 0XT",
    "addr:housenumber":"1",
    "addr:postcode":"rg18 0xt",
    "addr:street":"Frilsham Park",
    "iso:country":"GB",
    "sg:address":"1 Frilsham Park, Yattendon",
    "sg:city":"Newbury",
    "sg:classifiers":[
        {
            "category":"Professional",
            "subcategory":"Management & Consulting",
            "type":"Services"
        }
    ],
    "sg:phone":"+44 1635 201971",
    "sg:postcode":"RG18 0XT",
    "sg:province":"Berkshire",
    "sg:tags":[
        "marketing",
        "consultant"
    ],
    "wof:name":"Highfield Marketing",
    "wof:placetype":"venue"
},
  "geometry": {"coordinates":[-1.20576,51.465862],"type":"Point"}
}