{
  "type": "Feature",
  "properties": {
    "addr:full":"Leonard Works, First Avenue, Trafford Park Manchester Cheshire M17 1JZ",
    "addr:postcode":"m17 1jz",
    "addr:street":"First Avenue",
    "iso:country":"GB",
    "sg:address":"Leonard Works, First Avenue, Trafford Park",
    "sg:city":"Manchester",
    "sg:classifiers":[
        {
            "category":"Professional",
            "subcategory":"Engineering",
            "type":"Services"
        },
        {
            "category":"Building & Trades",
            "subcategory":"Electrical",
            "type":"Services"
        }
    ],
    "sg:phone":"+44 161 872 3802",
    "sg:postcode":"M17 1JZ",
    "sg:province":"Cheshire",
    "sg:tags":[
        "engineer",
        "electrician",
        "contractor"
    ],
    "wof:name":"M & H TECHNICAL SERVICES LTD",
    "wof:placetype":"venue"
},
  "geometry": {"coordinates":[-2.3196790218,53.4674415588],"type":"Point"}
}