{
  "type": "Feature",
  "properties": {
    "addr:full":"7-8 Lowther Street Whitehaven Cumbria CA28 7AL",
    "addr:housenumber":"7-8",
    "addr:postcode":"ca28 7al",
    "addr:street":"Lowther Street",
    "iso:country":"GB",
    "sg:address":"7-8 Lowther Street",
    "sg:city":"Whitehaven",
    "sg:classifiers":[
        {
            "category":"Shopping",
            "subcategory":"Clothing, Apparel, & Fashions",
            "type":"Retail Goods"
        }
    ],
    "sg:phone":"+44 1946 692033",
    "sg:postcode":"CA28 7AL",
    "sg:province":"Cumbria",
    "sg:tags":[
        "shop"
    ],
    "wof:name":"Top Shop-Top Man",
    "wof:placetype":"venue"
},
  "geometry": {"coordinates":[-3.586531,54.54715],"type":"Point"}
}