{
  "type": "Feature",
  "properties": {
    "addr:full":"72 Low Petergate York North Yorkshire YO1 7HZ",
    "addr:housenumber":"72",
    "addr:postcode":"yo1 7hz",
    "addr:street":"Low Petergate",
    "iso:country":"GB",
    "sg:address":"72 Low Petergate",
    "sg:city":"York",
    "sg:classifiers":[
        {
            "category":"Banks & Credit Unions",
            "subcategory":"Financial Services",
            "type":"Services"
        }
    ],
    "sg:phone":"+44 1904 627253",
    "sg:postcode":"YO1 7HZ",
    "sg:province":"North Yorkshire",
    "sg:tags":[
        "consultant"
    ],
    "wof:name":"Hambro Countrywide",
    "wof:placetype":"venue"
},
  "geometry": {"coordinates":[-1.080717,53.960739],"type":"Point"}
}