{
  "type": "Feature",
  "properties": {
    "addr:full":"Farm House Jedburgh Scottish Borders TD8 6QX",
    "addr:postcode":"td8 6qx",
    "addr:street":"Jedburgh",
    "iso:country":"GB",
    "sg:address":"Farm House",
    "sg:city":"Jedburgh",
    "sg:classifiers":[
        {
            "category":"Building & Trades",
            "subcategory":"Equipment Rental",
            "type":"Services"
        }
    ],
    "sg:postcode":"TD8 6QX",
    "sg:province":"Scottish Borders",
    "sg:tags":[
        "plant",
        "machinery"
    ],
    "wof:name":"Dawson Plant Hire",
    "wof:placetype":"venue"
},
  "geometry": {"coordinates":[-2.554624,55.477718],"type":"Point"}
}