{
  "type": "Feature",
  "properties": {
    "iso:country":"GB",
    "sg:address":"1163-1165 London Rd",
    "sg:city":"Leigh On Sea",
    "sg:classifiers":[
        {
            "category":"Autos & Motor Vehicles",
            "subcategory":"Auto Supplies",
            "type":"Retail Goods"
        }
    ],
    "sg:phone":"+44 1702 474208",
    "sg:postcode":"SS9 3JE",
    "sg:province":"Essex",
    "sg:tags":[
        "component"
    ],
    "wof:name":"Brown Bros Group",
    "wof:placetype":"venue"
},
  "geometry": {"coordinates":[0.658649,51.547863],"type":"Point"}
}