{
  "type": "Feature",
  "properties": {
    "addr:full":"30-40 Elcho St Battersea Greater London SW11 4AU",
    "addr:housenumber":"30-40",
    "addr:postcode":"sw11 4au",
    "addr:street":"Elcho St",
    "iso:country":"GB",
    "sg:address":"30-40 Elcho St",
    "sg:city":"Battersea",
    "sg:classifiers":[
        {
            "category":"Wholesale",
            "subcategory":"Books, Periodicals, & Newspapers",
            "type":"Manufacturing & Wholesale Goods"
        }
    ],
    "sg:phone":"+44 20 7924 2266",
    "sg:postcode":"SW11 4AU",
    "sg:province":"Greater London",
    "sg:tags":[
        "publishing"
    ],
    "wof:name":"Felicia Law Publishing",
    "wof:placetype":"venue"
},
  "geometry": {"coordinates":[-0.1690260023,51.4796524048],"type":"Point"}
}