{
  "type": "Feature",
  "properties": {
    "addr:full":"2 The Precinct Swansea Swansea SA2 7BA",
    "addr:housenumber":"2",
    "addr:postcode":"sa2 7ba",
    "addr:street":"The Precinct Swansea",
    "iso:country":"GB",
    "sg:address":"2 The Precinct",
    "sg:city":"Swansea",
    "sg:classifiers":[
        {
            "category":"Recreation",
            "subcategory":"Water Park",
            "type":"Entertainment"
        }
    ],
    "sg:phone":"+44 1792 281138",
    "sg:postcode":"SA2 7BA",
    "sg:province":"Swansea",
    "sg:tags":[
        "sport"
    ],
    "wof:name":"Magua",
    "wof:placetype":"venue"
},
  "geometry": {"coordinates":[-4.0233249664,51.6139678955],"type":"Point"}
}