{
  "type": "Feature",
  "properties": {
    "addr:full":"165 Barton Street Gloucester Gloucestershire GL1 4HT",
    "addr:housenumber":"165",
    "addr:postcode":"gl1 4ht",
    "addr:street":"Barton Street",
    "iso:country":"GB",
    "sg:address":"165 Barton Street",
    "sg:city":"Gloucester",
    "sg:classifiers":[
        {
            "category":"Personal",
            "subcategory":"Beauty Salon",
            "type":"Services"
        },
        {
            "category":"Personal",
            "subcategory":"Barber",
            "type":"Services"
        }
    ],
    "sg:phone":"+44 1452 522949",
    "sg:postcode":"GL1 4HT",
    "sg:province":"Gloucestershire",
    "sg:tags":[
        "unisex",
        "hairdresser"
    ],
    "wof:name":"Academy Hair",
    "wof:placetype":"venue"
},
  "geometry": {"coordinates":[-2.23548,51.860134],"type":"Point"}
}