{
  "type": "Feature",
  "properties": {
    "iso:country":"GB",
    "sg:address":"Irk Mill, Oldham Road",
    "sg:city":"Manchester",
    "sg:classifiers":[
        {
            "category":"Retail",
            "subcategory":"Repair Shop",
            "type":"Services"
        }
    ],
    "sg:postcode":"M24 1AZ",
    "sg:province":"Greater Manchester",
    "sg:tags":[
        "upholsterer"
    ],
    "wof:name":"I S M Upholstery",
    "wof:placetype":"venue"
},
  "geometry": {"coordinates":[-2.1972699165,53.5472602844],"type":"Point"}
}