{
  "type": "Feature",
  "properties": {
    "iso:country":"GB",
    "sg:address":"90 Sydenham Road, Sydenham",
    "sg:city":"London",
    "sg:classifiers":[
        {
            "category":"Home & Garden",
            "subcategory":"Carpets & Floor Coverings",
            "type":"Retail Goods"
        }
    ],
    "sg:phone":"+44 20 8778 6946",
    "sg:postcode":"SE26 5JX",
    "sg:province":"Greater London",
    "sg:tags":[
        "carpets",
        "rug",
        "matting"
    ],
    "wof:name":"K C Lloyds",
    "wof:placetype":"venue"
},
  "geometry": {"coordinates":[-0.0487210006,51.4256401062],"type":"Point"}
}