{
  "type": "Feature",
  "properties": {
    "iso:country":"GB",
    "sg:address":"6 The Fairway",
    "sg:city":"Abbots Langley",
    "sg:classifiers":[
        {
            "category":"Building & Trades",
            "subcategory":"Plumbing",
            "type":"Services"
        }
    ],
    "sg:phone":"+44 1923 265319",
    "sg:postcode":"WD5 0JT",
    "sg:province":"Hertfordshire",
    "sg:tags":[
        "drain",
        "clearance",
        "sewer"
    ],
    "wof:name":"Ram Rod",
    "wof:placetype":"venue"
},
  "geometry": {"coordinates":[-0.427176,51.698383],"type":"Point"}
}