{
  "type": "Feature",
  "properties": {
    "iso:country":"GB",
    "sg:address":"32 Ernest Avenue",
    "sg:city":"London",
    "sg:classifiers":[
        {
            "category":"Manufacturing",
            "subcategory":"Signs",
            "type":"Manufacturing & Wholesale Goods"
        }
    ],
    "sg:phone":"+44 20 8670 3362",
    "sg:postcode":"SE27 0DJ",
    "sg:province":"Greater London",
    "sg:tags":[
        "writer"
    ],
    "wof:name":"Butler Associates",
    "wof:placetype":"venue"
},
  "geometry": {"coordinates":[-0.103264,51.429874],"type":"Point"}
}