{
  "type": "Feature",
  "properties": {
    "iso:country":"GB",
    "sg:address":"Bray Shop",
    "sg:city":"Callington",
    "sg:classifiers":[
        {
            "category":"Farming",
            "subcategory":"Livestock Farm",
            "type":"Manufacturing & Wholesale Goods"
        }
    ],
    "sg:phone":"+44 1579 370381",
    "sg:postcode":"PL17 8QH",
    "sg:province":"Cornwall",
    "sg:tags":[
        "others"
    ],
    "wof:name":"Dinnis & Sons",
    "wof:placetype":"venue"
},
  "geometry": {"coordinates":[-4.3104901314,50.5004081726],"type":"Point"}
}