{
  "type": "Feature",
  "properties": {
    "addr:full":"Whetstone Hill Road Oldham Lancashire OL1 4NA",
    "addr:postcode":"ol1 4na",
    "addr:street":"Whetstone Hill Road",
    "iso:country":"GB",
    "sg:address":"Whetstone Hill Road",
    "sg:city":"Oldham",
    "sg:classifiers":[
        {
            "category":"Education",
            "subcategory":"School",
            "type":"Public Place"
        }
    ],
    "sg:phone":"+44 161 911 3173",
    "sg:postcode":"OL1 4NA",
    "sg:province":"Lancashire",
    "sg:tags":[
        "local",
        "authority"
    ],
    "wof:name":"Oldham Metropolitan Borough Council",
    "wof:placetype":"venue"
},
  "geometry": {"coordinates":[-2.094194,53.555592],"type":"Point"}
}