{
  "type": "Feature",
  "properties": {
    "iso:country":"GB",
    "sg:address":"High Lane",
    "sg:city":"Stockport",
    "sg:classifiers":[
        {
            "category":"Retail",
            "subcategory":"Funeral Services",
            "type":"Services"
        }
    ],
    "sg:phone":"+44 1663 766998",
    "sg:postcode":"SK6 1BA",
    "sg:province":"Cheshire",
    "wof:name":"Brian Sharples & Son",
    "wof:placetype":"venue"
},
  "geometry": {"coordinates":[-2.095816,53.425201],"type":"Point"}
}