{
  "type": "Feature",
  "properties": {
    "addr:full":"1 High St South London Greater London E6 4EN",
    "addr:housenumber":"1",
    "addr:postcode":"e6 4en",
    "addr:street":"High St",
    "iso:country":"GB",
    "sg:address":"1 High St South",
    "sg:city":"London",
    "sg:classifiers":[
        {
            "category":"Autos & Motor Vehicles",
            "subcategory":"Automobile Sales",
            "type":"Retail Goods"
        }
    ],
    "sg:postcode":"E6 4EN",
    "sg:province":"Greater London",
    "sg:tags":[
        "car"
    ],
    "wof:name":"G & G Motors",
    "wof:placetype":"venue"
},
  "geometry": {"coordinates":[0.0555850007,51.5317611694],"type":"Point"}
}