{
  "type": "Feature",
  "properties": {
    "iso:country":"GB",
    "sg:address":"38b West Street",
    "sg:city":"Fishguard",
    "sg:classifiers":[
        {
            "category":"Personal",
            "subcategory":"Barber",
            "type":"Services"
        }
    ],
    "sg:postcode":"SA65 9AD",
    "sg:province":"Pembrokeshire",
    "sg:tags":[
        "men's",
        "hairdresser"
    ],
    "wof:name":"John's Barbers Shop",
    "wof:placetype":"venue"
},
  "geometry": {"coordinates":[-4.97862,51.995274],"type":"Point"}
}