{
  "type": "Feature",
  "properties": {
    "addr:full":"38b West Street Fishguard Pembrokeshire SA65 9AD",
    "addr:housenumber":"38b",
    "addr:postcode":"sa65 9ad",
    "addr:street":"West Street",
    "iso:country":"GB",
    "sg:address":"38b West Street",
    "sg:city":"Fishguard",
    "sg:classifiers":[
        {
            "category":"Personal",
            "subcategory":"Barber",
            "type":"Services"
        }
    ],
    "sg:postcode":"SA65 9AD",
    "sg:province":"Pembrokeshire",
    "sg:tags":[
        "men's",
        "hairdresser"
    ],
    "wof:name":"John's Barbers Shop",
    "wof:placetype":"venue"
},
  "geometry": {"coordinates":[-4.97862,51.995274],"type":"Point"}
}