{
  "type": "Feature",
  "properties": {
    "addr:full":"37 Trelawny Road, Plympton Plymouth Devon PL7 4LJ",
    "addr:housenumber":"37",
    "addr:postcode":"pl7 4lj",
    "addr:street":"Trelawny Road",
    "iso:country":"GB",
    "sg:address":"37 Trelawny Road, Plympton",
    "sg:city":"Plymouth",
    "sg:classifiers":[
        {
            "category":"Building & Trades",
            "subcategory":"Plumbing",
            "type":"Services"
        }
    ],
    "sg:phone":"+44 1752 343614",
    "sg:postcode":"PL7 4LJ",
    "sg:province":"Devon",
    "sg:tags":[
        "plumber",
        "heating"
    ],
    "wof:name":"Abbey Plumbing & Heating",
    "wof:placetype":"venue"
},
  "geometry": {"coordinates":[-4.0641012192,50.3942451477],"type":"Point"}
}