{
  "type": "Feature",
  "properties": {
    "addr:full":"Cliff Bridge Studio, Cliff Bridge Terrace Scarborough North Yorkshire YO11 2HA",
    "addr:postcode":"yo11 2ha",
    "addr:street":"Cliff;Cliff Bridge Terrace",
    "iso:country":"GB",
    "sg:address":"Cliff Bridge Studio, Cliff Bridge Terrace",
    "sg:city":"Scarborough",
    "sg:classifiers":[
        {
            "category":"Real Estate",
            "subcategory":"Architect",
            "type":"Services"
        }
    ],
    "sg:postcode":"YO11 2HA",
    "sg:province":"North Yorkshire",
    "wof:name":"Alan Campbell Architects",
    "wof:placetype":"venue"
},
  "geometry": {"coordinates":[-0.392203,54.266281],"type":"Point"}
}