{
  "type": "Feature",
  "properties": {
    "addr:full":"Unit F7, Halesfields 23 Telford Shropshire TF7 4NY",
    "addr:housenumber":"f7;23",
    "addr:postcode":"tf7 4ny",
    "addr:street":"Halesfields",
    "iso:country":"GB",
    "sg:address":"Unit F7, Halesfields 23",
    "sg:city":"Telford",
    "sg:classifiers":[
        {
            "category":"Building & Trades",
            "subcategory":"Plumbing",
            "type":"Services"
        }
    ],
    "sg:phone":"+44 1952 582975",
    "sg:postcode":"TF7 4NY",
    "sg:province":"Shropshire",
    "sg:tags":[
        "heating"
    ],
    "wof:name":"W B Thermo Plastics",
    "wof:placetype":"venue"
},
  "geometry": {"coordinates":[-2.4238569736,52.6487541199],"type":"Point"}
}