{
  "type": "Feature",
  "properties": {
    "addr:full":"342 Edgware Road London Greater London W2 1EA",
    "addr:housenumber":"342",
    "addr:postcode":"w2 1ea",
    "addr:street":"Edgware Road",
    "iso:country":"GB",
    "sg:address":"342 Edgware Road",
    "sg:city":"London",
    "sg:classifiers":[
        {
            "category":"Restaurant",
            "type":"Food & Drink"
        }
    ],
    "sg:postcode":"W2 1EA",
    "sg:province":"Greater London",
    "wof:name":"H Aksu",
    "wof:placetype":"venue"
},
  "geometry": {"coordinates":[-0.1712390035,51.5210418701],"type":"Point"}
}