{
  "type": "Feature",
  "properties": {
    "addr:full":"11 Harthall Ayr South Ayrshire KA8 0PA",
    "addr:housenumber":"11",
    "addr:postcode":"ka8 0pa",
    "addr:street":"Harthall",
    "iso:country":"GB",
    "sg:address":"11 Harthall",
    "sg:city":"Ayr",
    "sg:classifiers":[
        {
            "category":"Real Estate",
            "subcategory":"Architect",
            "type":"Services"
        }
    ],
    "sg:postcode":"KA8 0PA",
    "sg:province":"South Ayrshire",
    "wof:name":"John Simpson",
    "wof:placetype":"venue"
},
  "geometry": {"coordinates":[-4.5931959152,55.4703483582],"type":"Point"}
}