{
  "type": "Feature",
  "properties": {
    "addr:full":"Meadoway, The Drove, West End Southampton Hampshire SO30 2EF",
    "addr:postcode":"so30 2ef",
    "addr:street":"Meadoway The Drove",
    "iso:country":"GB",
    "sg:address":"Meadoway, The Drove, West End",
    "sg:city":"Southampton",
    "sg:classifiers":[
        {
            "category":"Building & Trades",
            "subcategory":"Construction",
            "type":"Services"
        }
    ],
    "sg:phone":"+44 23 8047 6251",
    "sg:postcode":"SO30 2EF",
    "sg:province":"Hampshire",
    "sg:tags":[
        "joiner",
        "carpenter"
    ],
    "wof:name":"J.S Phillimore",
    "wof:placetype":"venue"
},
  "geometry": {"coordinates":[-1.32121,50.932941],"type":"Point"}
}