{
  "type": "Feature",
  "properties": {
    "addr:full":"168 Watkin Walk, Hedge End Southampton Hampshire SO30 2TB",
    "addr:housenumber":"168",
    "addr:postcode":"so30 2tb",
    "addr:street":"Watkin Walk",
    "iso:country":"GB",
    "sg:address":"168 Watkin Walk, Hedge End",
    "sg:city":"Southampton",
    "sg:classifiers":[
        {
            "category":"Building & Trades",
            "subcategory":"Construction",
            "type":"Services"
        }
    ],
    "sg:postcode":"SO30 2TB",
    "sg:province":"Hampshire",
    "sg:tags":[
        "builder"
    ],
    "wof:name":"Bovis Homes Ltd",
    "wof:placetype":"venue"
},
  "geometry": {"coordinates":[-1.29279,50.929798],"type":"Point"}
}