{
  "type": "Feature",
  "properties": {
    "iso:country":"GB",
    "sg:address":"Wood, Bottom Garage, Marsden",
    "sg:city":"Huddersfield",
    "sg:classifiers":[
        {
            "category":"Retail",
            "subcategory":"Auto Repair",
            "type":"Services"
        }
    ],
    "sg:phone":"+44 1484 844008",
    "sg:postcode":"HD7 6NE",
    "sg:province":"West Yorkshire",
    "sg:tags":[
        "modification",
        "garage"
    ],
    "wof:name":"John Martindale",
    "wof:placetype":"venue"
},
  "geometry": {"coordinates":[-1.921244,53.602139],"type":"Point"}
}