{
  "type": "Feature",
  "properties": {
    "iso:country":"GB",
    "sg:address":"10 Crossfield Close, Oxenhope",
    "sg:city":"Keighley",
    "sg:classifiers":[
        {
            "category":"Building & Trades",
            "subcategory":"Construction",
            "type":"Services"
        }
    ],
    "sg:postcode":"BD22 9SE",
    "sg:province":"North Yorkshire",
    "sg:tags":[
        "joiner",
        "carpenter"
    ],
    "wof:name":"Eric Whitehead",
    "wof:placetype":"venue"
},
  "geometry": {"coordinates":[-1.956474,53.81546],"type":"Point"}
}