{
  "type": "Feature",
  "properties": {
    "addr:full":"166 Thurncourt Road Leicester Leicestershire LE5 2NG",
    "addr:housenumber":"166",
    "addr:postcode":"le5 2ng",
    "addr:street":"Thurncourt Road",
    "iso:country":"GB",
    "sg:address":"166 Thurncourt Road",
    "sg:city":"Leicester",
    "sg:classifiers":[
        {
            "category":"Food & Beverages",
            "subcategory":"Supermarket",
            "type":"Retail Goods"
        }
    ],
    "sg:phone":"+44 116 243 3030",
    "sg:postcode":"LE5 2NG",
    "sg:province":"Leicestershire",
    "wof:name":"Midlands Co-Operative Society Ltd.",
    "wof:placetype":"venue"
},
  "geometry": {"coordinates":[-1.0584789515,52.6381607056],"type":"Point"}
}