{
  "type": "Feature",
  "properties": {
    "addr:full":"36 Porchester Road, Bayswater London Greater London W2 6ES",
    "addr:housenumber":"36",
    "addr:postcode":"w2 6es",
    "addr:street":"Porchester Road",
    "iso:country":"GB",
    "sg:address":"36 Porchester Road, Bayswater",
    "sg:city":"London",
    "sg:classifiers":[
        {
            "category":"Personal",
            "subcategory":"Beauty Salon",
            "type":"Services"
        }
    ],
    "sg:phone":"+44 20 7221 4560",
    "sg:postcode":"W2 6ES",
    "sg:province":"Greater London",
    "sg:tags":[
        "unisex",
        "hairdresser"
    ],
    "wof:name":"Crops & Bobbers",
    "wof:placetype":"venue"
},
  "geometry": {"coordinates":[-0.187998,51.517208],"type":"Point"}
}