{
  "type": "Feature",
  "properties": {
    "iso:country":"GB",
    "sg:address":"Unit 5 & 6, Tomlington Rd Buiness Park, Tomlington Rd Leyland",
    "sg:city":"Preston",
    "sg:classifiers":[
        {
            "category":"Food & Beverages",
            "subcategory":"Dairy",
            "type":"Retail Goods"
        }
    ],
    "sg:phone":"+44 1772 324811",
    "sg:postcode":"PR5 1DD",
    "sg:province":"Lancashire",
    "sg:tags":[
        "produce"
    ],
    "wof:name":"Bamber Dairy Products",
    "wof:placetype":"venue"
},
  "geometry": {"coordinates":[-2.693417,53.727013],"type":"Point"}
}