{
  "type": "Feature",
  "properties": {
    "iso:country":"GB",
    "sg:address":"42-44 High Street, Harborne",
    "sg:city":"Birmingham",
    "sg:classifiers":[
        {
            "category":"Food & Beverages",
            "subcategory":"Bakery",
            "type":"Retail Goods"
        }
    ],
    "sg:phone":"+44 121 428 2636",
    "sg:postcode":"B17 9NE",
    "sg:province":"West Midlands",
    "sg:tags":[
        "pizza"
    ],
    "wof:name":"California Pizza Factory Ltd.",
    "wof:placetype":"venue"
},
  "geometry": {"coordinates":[-1.9444329739,52.4603729248],"type":"Point"}
}