{
  "type": "Feature",
  "properties": {
    "addr:full":"25 Hereward Cross Peterborough Cambridgeshire PE1 1TE",
    "addr:housenumber":"25",
    "addr:postcode":"pe1 1te",
    "addr:street":"Hereward Cross",
    "iso:country":"GB",
    "sg:address":"25 Hereward Cross",
    "sg:city":"Peterborough",
    "sg:classifiers":[
        {
            "category":"Shopping",
            "subcategory":"Clothing, Apparel, & Fashions",
            "type":"Retail Goods"
        }
    ],
    "sg:phone":"+44 1733 562834",
    "sg:postcode":"PE1 1TE",
    "sg:province":"Cambridgeshire",
    "sg:tags":[
        "workwear",
        "protective"
    ],
    "wof:name":"Morleys Leisurewear Centres Ltd.",
    "wof:placetype":"venue"
},
  "geometry": {"coordinates":[-0.241794,52.574455],"type":"Point"}
}