{
  "type": "Feature",
  "properties": {
    "addr:full":"57 Tollgate Road, Colney Heath St Albans Hertfordshire AL4 0PX",
    "addr:housenumber":"57",
    "addr:postcode":"al4 0px",
    "addr:street":"Tollgate Road",
    "iso:country":"GB",
    "sg:address":"57 Tollgate Road, Colney Heath",
    "sg:city":"St Albans",
    "sg:classifiers":[
        {
            "category":"Professional",
            "subcategory":"Engineering",
            "type":"Services"
        }
    ],
    "sg:postcode":"AL4 0PX",
    "sg:province":"Hertfordshire",
    "sg:tags":[
        "contractor",
        "electrical",
        "engineer"
    ],
    "wof:name":"R S L Electrical",
    "wof:placetype":"venue"
},
  "geometry": {"coordinates":[-0.250253,51.736767],"type":"Point"}
}