{
  "type": "Feature",
  "properties": {
    "iso:country":"GB",
    "sg:address":"The Brewery, High St, Twyford",
    "sg:city":"Winchester",
    "sg:classifiers":[
        {
            "category":"Home & Garden",
            "subcategory":"Kitchen Supply",
            "type":"Retail Goods"
        }
    ],
    "sg:phone":"+44 1962 714777",
    "sg:postcode":"SO21 1RG",
    "sg:province":"Hampshire",
    "sg:tags":[
        "equipment",
        "catering"
    ],
    "wof:name":"Wessex Catering & Bar Supplies",
    "wof:placetype":"venue"
},
  "geometry": {"coordinates":[-1.3127390146,51.0235900879],"type":"Point"}
}