{
  "type": "Feature",
  "properties": {
    "addr:full":"Fenn Lane, Dadlington Nuneaton Leicestershire CV13 6DS",
    "addr:postcode":"cv13 6ds",
    "addr:street":"Fenn Lane",
    "iso:country":"GB",
    "sg:address":"Fenn Lane, Dadlington",
    "sg:city":"Nuneaton",
    "sg:classifiers":[
        {
            "category":"Farming",
            "subcategory":"Nursery",
            "type":"Manufacturing & Wholesale Goods"
        },
        {
            "category":"Community Center",
            "type":"Public Place"
        }
    ],
    "sg:phone":"+44 1455 213800",
    "sg:postcode":"CV13 6DS",
    "sg:province":"Leicestershire",
    "sg:tags":[
        "centre"
    ],
    "wof:name":"Soarmill Nursery",
    "wof:placetype":"venue"
},
  "geometry": {"coordinates":[-1.4754459858,52.5717735291],"type":"Point"}
}