{
  "type": "Feature",
  "properties": {
    "iso:country":"GB",
    "sg:address":"357-359 Walworth Road",
    "sg:city":"London",
    "sg:classifiers":[
        {
            "category":"Shopping",
            "subcategory":"Clothing, Apparel, & Fashions",
            "type":"Retail Goods"
        }
    ],
    "sg:phone":"+44 20 7703 9519",
    "sg:postcode":"SE17 2AL",
    "sg:province":"Greater London",
    "sg:tags":[
        "menswear"
    ],
    "wof:name":"Blakes Menswear",
    "wof:placetype":"venue"
},
  "geometry": {"coordinates":[-0.0938709974,51.4857177734],"type":"Point"}
}