{
  "type": "Feature",
  "properties": {
    "addr:full":"Hindpool Rd Barrow In Furness Cumbria LA14 2NE",
    "addr:postcode":"la14 2ne",
    "addr:street":"Hindpool Rd",
    "iso:country":"GB",
    "sg:address":"Hindpool Rd",
    "sg:city":"Barrow In Furness",
    "sg:classifiers":[
        {
            "category":"Home & Garden",
            "subcategory":"Home Furnishings",
            "type":"Retail Goods"
        }
    ],
    "sg:phone":"+44 1229 821662",
    "sg:postcode":"LA14 2NE",
    "sg:province":"Cumbria",
    "sg:tags":[
        "wall",
        "wallpaper",
        "covering"
    ],
    "wof:name":"Homestyle By Fads",
    "wof:placetype":"venue"
},
  "geometry": {"coordinates":[-3.2309989929,54.1113052368],"type":"Point"}
}