{
  "type": "Feature",
  "properties": {
    "iso:country":"GB",
    "sg:address":"80 Chelston Road",
    "sg:city":"Birmingham",
    "sg:classifiers":[
        {
            "category":"Building & Trades",
            "subcategory":"Construction",
            "type":"Services"
        }
    ],
    "sg:phone":"+44 121 476 0218",
    "sg:postcode":"B31 5BT",
    "sg:province":"West Midlands",
    "sg:tags":[
        "builder"
    ],
    "wof:name":"Joe Slater & Son's",
    "wof:placetype":"venue"
},
  "geometry": {"coordinates":[-1.982708,52.406406],"type":"Point"}
}