{
  "type": "Feature",
  "properties": {
    "iso:country":"GB",
    "sg:address":"Unit 17 Lansdowne Mews, Charlton",
    "sg:city":"London",
    "sg:classifiers":[
        {
            "category":"Building & Trades",
            "subcategory":"Construction",
            "type":"Services"
        }
    ],
    "sg:phone":"+44 20 8858 5900",
    "sg:postcode":"SE7 8AZ",
    "sg:province":"Greater London",
    "sg:tags":[
        "joiner",
        "carpenter"
    ],
    "wof:name":"Valley Interiors Ltd.",
    "wof:placetype":"venue"
},
  "geometry": {"coordinates":[0.037945,51.485516],"type":"Point"}
}