{
  "type": "Feature",
  "properties": {
    "addr:full":"128-129, Middleton Grange Shopping Centre Hartlepool Durham TS24 7RG",
    "addr:housenumber":"128-129",
    "addr:postcode":"ts24 7rg",
    "addr:street":"Middleton Grange Shopping",
    "iso:country":"GB",
    "sg:address":"128-129, Middleton Grange Shopping Centre",
    "sg:city":"Hartlepool",
    "sg:classifiers":[
        {
            "category":"Shopping",
            "subcategory":"Clothing, Apparel, & Fashions",
            "type":"Retail Goods"
        }
    ],
    "sg:phone":"+44 1429 278099",
    "sg:postcode":"TS24 7RG",
    "sg:province":"Durham",
    "sg:tags":[
        "menswear"
    ],
    "wof:name":"The Officers Club Ltd.",
    "wof:placetype":"venue"
},
  "geometry": {"coordinates":[-1.214119,54.685406],"type":"Point"}
}