{
  "type": "Feature",
  "properties": {
    "addr:full":"21 Tabernacle Street Aberaeron Ceredigion SA46 0BN",
    "addr:housenumber":"21",
    "addr:postcode":"sa46 0bn",
    "addr:street":"Tabernacle Street",
    "iso:country":"GB",
    "sg:address":"21 Tabernacle Street",
    "sg:city":"Aberaeron",
    "sg:classifiers":[
        {
            "category":"Building & Trades",
            "subcategory":"Construction",
            "type":"Services"
        }
    ],
    "sg:phone":"+44 1545 570425",
    "sg:postcode":"SA46 0BN",
    "sg:province":"Ceredigion",
    "sg:tags":[
        "monumental",
        "mason"
    ],
    "wof:name":"Aberaeron Monumental Works",
    "wof:placetype":"venue"
},
  "geometry": {"coordinates":[-4.262419,52.244202],"type":"Point"}
}