{
  "type": "Feature",
  "properties": {
    "addr:full":"163 St Helens Road Swansea Neath Port Talbot SA1 4DT",
    "addr:housenumber":"163",
    "addr:postcode":"sa1 4dt",
    "addr:street":"St Helens Road",
    "iso:country":"GB",
    "sg:address":"163 St Helens Road",
    "sg:city":"Swansea",
    "sg:classifiers":[
        {
            "category":"Manufacturing",
            "subcategory":"Tools & Machinery",
            "type":"Manufacturing & Wholesale Goods"
        }
    ],
    "sg:phone":"+44 1792 462544",
    "sg:postcode":"SA1 4DT",
    "sg:province":"Neath Port Talbot",
    "sg:tags":[
        "society",
        "friendly"
    ],
    "wof:name":"General Accident Financial Services",
    "wof:placetype":"venue"
},
  "geometry": {"coordinates":[-3.951924,51.61869],"type":"Point"}
}