{
  "type": "Feature",
  "properties": {
    "iso:country":"GB",
    "sg:address":"7 Higher Green",
    "sg:city":"Poulton Le Fylde",
    "sg:classifiers":[
        {
            "category":"Professional",
            "type":"Services"
        }
    ],
    "sg:phone":"+44 1253 896106",
    "sg:postcode":"FY6 7BL",
    "sg:province":"Lancashire",
    "sg:tags":[
        "repair",
        "tech",
        "maintenance"
    ],
    "wof:name":"Computech",
    "wof:placetype":"venue"
},
  "geometry": {"coordinates":[-2.990513,53.84647],"type":"Point"}
}