{
  "type": "Feature",
  "properties": {
    "addr:full":"16 Hemdean Rise, Caversham Reading Berkshire RG4 7SA",
    "addr:housenumber":"16",
    "addr:postcode":"rg4 7sa",
    "addr:street":"Hemdean Rise",
    "iso:country":"GB",
    "sg:address":"16 Hemdean Rise, Caversham",
    "sg:city":"Reading",
    "sg:classifiers":[
        {
            "category":"Building & Trades",
            "subcategory":"Construction",
            "type":"Services"
        }
    ],
    "sg:phone":"+44 118 947 3675",
    "sg:postcode":"RG4 7SA",
    "sg:province":"Berkshire",
    "sg:tags":[
        "repair",
        "guttering"
    ],
    "wof:name":"Reading Guttering Services",
    "wof:placetype":"venue"
},
  "geometry": {"coordinates":[-0.9754220247,51.4707984924],"type":"Point"}
}