{
  "type": "Feature",
  "properties": {
    "iso:country":"GB",
    "sg:address":"130 Gloucester Road North, Filton",
    "sg:city":"Bristol",
    "sg:classifiers":[
        {
            "category":"Professional",
            "subcategory":"Lawyer & Legal Services",
            "type":"Services"
        }
    ],
    "sg:phone":"+44 117 969 2773",
    "sg:postcode":"BS34 7BQ",
    "sg:province":"Gloucestershire",
    "sg:tags":[
        "solicitor"
    ],
    "wof:name":"Michael Barnard",
    "wof:placetype":"venue"
},
  "geometry": {"coordinates":[-2.5751459599,51.5087547302],"type":"Point"}
}