{
  "type": "Feature",
  "properties": {
    "addr:full":"Montrose Avenue Glasgow Glasgow City G52 4LA",
    "addr:postcode":"g52 4la",
    "addr:street":"Montrose Avenue",
    "iso:country":"GB",
    "sg:address":"Montrose Avenue",
    "sg:city":"Glasgow",
    "sg:classifiers":[
        {
            "category":"Arena",
            "subcategory":"Sports Club",
            "type":"Entertainment"
        }
    ],
    "sg:phone":"+44 141 882 1738",
    "sg:postcode":"G52 4LA",
    "sg:province":"Glasgow City",
    "wof:name":"Hillington Estate Bowling Club",
    "wof:placetype":"venue"
},
  "geometry": {"coordinates":[-4.374399,55.863674],"type":"Point"}
}