{
  "type": "Feature",
  "properties": {
    "iso:country":"GB",
    "sg:address":"Southgate",
    "sg:city":"Aberystwyth",
    "sg:classifiers":[
        {
            "category":"Recreation",
            "subcategory":"Campground",
            "type":"Entertainment"
        }
    ],
    "sg:postcode":"SY23 4DX",
    "sg:province":"Ceredigion",
    "sg:tags":[
        "caravan",
        "park"
    ],
    "wof:name":"Midfield Caravan Park",
    "wof:placetype":"venue"
},
  "geometry": {"coordinates":[-4.0645999908,52.3977813721],"type":"Point"}
}