{
  "type": "Feature",
  "properties": {
    "iso:country":"GB",
    "sg:address":"39 Jewry Street",
    "sg:city":"Winchester",
    "sg:classifiers":[
        {
            "category":"Shopping",
            "subcategory":"Gifts & Souvenirs",
            "type":"Retail Goods"
        },
        {
            "category":"Home & Garden",
            "subcategory":"Furniture",
            "type":"Retail Goods"
        }
    ],
    "sg:phone":"+44 1962 870102",
    "sg:postcode":"SO23 8RY",
    "sg:province":"Hampshire",
    "sg:tags":[
        "shop"
    ],
    "wof:name":"The Pine Cellars",
    "wof:placetype":"venue"
},
  "geometry": {"coordinates":[-1.315724,51.064236],"type":"Point"}
}