{
  "type": "Feature",
  "properties": {
    "iso:country":"GB",
    "sg:address":"Newilton House, Derngate",
    "sg:city":"Northampton",
    "sg:classifiers":[
        {
            "category":"Organizations",
            "subcategory":"Non-profit Organization",
            "type":"Services"
        }
    ],
    "sg:phone":"+44 1604 634224",
    "sg:postcode":"NN1 1TY",
    "sg:province":"Northamptonshire",
    "sg:tags":[
        "organisation",
        "voluntary",
        "charity"
    ],
    "wof:name":"Progressive People",
    "wof:placetype":"venue"
},
  "geometry": {"coordinates":[-0.893044,52.236633],"type":"Point"}
}