{
  "type": "Feature",
  "properties": {
    "addr:full":"168 Ifield Road London Greater London SW10 9AF",
    "addr:housenumber":"168",
    "addr:postcode":"sw10 9af",
    "addr:street":"Ifield Road",
    "iso:country":"GB",
    "sg:address":"168 Ifield Road",
    "sg:city":"London",
    "sg:classifiers":[
        {
            "category":"Restaurant",
            "type":"Food & Drink"
        }
    ],
    "sg:phone":"+44 20 7835 0874",
    "sg:postcode":"SW10 9AF",
    "sg:province":"Greater London",
    "sg:tags":[
        "-",
        "pizza"
    ],
    "wof:name":"Chez Max Restaurant",
    "wof:placetype":"venue"
},
  "geometry": {"coordinates":[-0.1901230067,51.4862251282],"type":"Point"}
}