{
  "type": "Feature",
  "properties": {
    "addr:full":"20 Hatfield Close, Rainworth Mansfield Nottinghamshire NG21 0LL",
    "addr:housenumber":"20",
    "addr:postcode":"ng21 0ll",
    "addr:street":"Hatfield Close",
    "iso:country":"GB",
    "sg:address":"20 Hatfield Close, Rainworth",
    "sg:city":"Mansfield",
    "sg:classifiers":[
        {
            "category":"Health Services",
            "subcategory":"Health Practitioner",
            "type":"Services"
        }
    ],
    "sg:phone":"+44 1623 798119",
    "sg:postcode":"NG21 0LL",
    "sg:province":"Nottinghamshire",
    "sg:tags":[
        "hypnotherapists"
    ],
    "wof:name":"Cheryl Pugh",
    "wof:placetype":"venue"
},
  "geometry": {"coordinates":[-1.1048150063,53.117477417],"type":"Point"}
}