{
  "type": "Feature",
  "properties": {
    "iso:country":"GB",
    "sg:address":"Unit 8, Washington Centre, Halesowen Road",
    "sg:city":"Dudley",
    "sg:classifiers":[
        {
            "category":"Autos & Motor Vehicles",
            "subcategory":"Automobile Sales",
            "type":"Retail Goods"
        }
    ],
    "sg:phone":"+44 1384 243243",
    "sg:postcode":"DY2 9RE",
    "sg:province":"West Midlands",
    "sg:tags":[
        "truck",
        "maker",
        "barrow"
    ],
    "wof:name":"Haemmerlin Ltd.",
    "wof:placetype":"venue"
},
  "geometry": {"coordinates":[-2.077639,52.486069],"type":"Point"}
}