{
  "type": "Feature",
  "properties": {
    "addr:full":"107 Bohemia Road St Leonards-on-sea East Sussex TN37 6RL",
    "addr:housenumber":"107",
    "addr:postcode":"leonards-on-sea;tn37 6rl",
    "addr:street":"Bohemia Road St",
    "iso:country":"GB",
    "sg:address":"107 Bohemia Road",
    "sg:city":"St Leonards-on-sea",
    "sg:classifiers":[
        {
            "category":"Retail",
            "subcategory":"Repair Shop",
            "type":"Services"
        }
    ],
    "sg:phone":"+44 1424 712060",
    "sg:postcode":"TN37 6RL",
    "sg:province":"East Sussex",
    "sg:tags":[
        "radio",
        "television",
        "video"
    ],
    "wof:name":"Vision-Right",
    "wof:placetype":"venue"
},
  "geometry": {"coordinates":[0.560413003,50.8618774414],"type":"Point"}
}