{
  "type": "Feature",
  "properties": {
    "addr:full":"20 Somerville Court, Waddington Lincoln Lincolnshire LN5 9QX",
    "addr:housenumber":"20",
    "addr:postcode":"ln5 9qx",
    "addr:street":"Somerville Court",
    "iso:country":"GB",
    "sg:address":"20 Somerville Court, Waddington",
    "sg:city":"Lincoln",
    "sg:classifiers":[
        {
            "category":"Personal",
            "type":"Services"
        },
        {
            "category":"Bus Charters",
            "type":"Transportation"
        }
    ],
    "sg:phone":"+44 1522 721517",
    "sg:postcode":"LN5 9QX",
    "sg:province":"Lincolnshire",
    "sg:tags":[
        "coach",
        "wedding"
    ],
    "wof:name":"A Limo",
    "wof:placetype":"venue"
},
  "geometry": {"coordinates":[-0.5552629828,53.1752319336],"type":"Point"}
}