{
  "type": "Feature",
  "properties": {
    "addr:full":"87a Elton Road, Stibbington Peterborough Cambridgeshire PE8 6JX",
    "addr:housenumber":"87a",
    "addr:postcode":"pe8 6jx",
    "addr:street":"Elton Road Stibbington Peterborough",
    "iso:country":"GB",
    "sg:address":"87a Elton Road, Stibbington",
    "sg:city":"Peterborough",
    "sg:classifiers":[
        {
            "category":"Manufacturing",
            "subcategory":"Rubber & Plastics",
            "type":"Manufacturing & Wholesale Goods"
        },
        {
            "category":"Professional",
            "subcategory":"Management & Consulting",
            "type":"Services"
        }
    ],
    "sg:postcode":"PE8 6JX",
    "sg:province":"Cambridgeshire",
    "sg:tags":[
        "product",
        "holding",
        "activity"
    ],
    "wof:name":"AVONDYKE HOLDINGS LTD",
    "wof:placetype":"venue"
},
  "geometry": {"coordinates":[-0.40266,52.565872],"type":"Point"}
}