{
  "type": "Feature",
  "properties": {
    "iso:country":"GB",
    "sg:address":"80 Sopers Lane",
    "sg:city":"Poole",
    "sg:classifiers":[
        {
            "category":"Social Services",
            "subcategory":"Job Training",
            "type":"Services"
        }
    ],
    "sg:phone":"+44 1202 252742",
    "sg:postcode":"BH17 7EU",
    "sg:province":"Dorset",
    "sg:tags":[
        "translator",
        "interpreter"
    ],
    "wof:name":"Euro-Languages",
    "wof:placetype":"venue"
},
  "geometry": {"coordinates":[-1.996912,50.74749],"type":"Point"}
}