{
  "type": "Feature",
  "properties": {
    "iso:country":"GB",
    "sg:address":"Homebank Farm, Manley Lane, Manley",
    "sg:city":"Warrington",
    "sg:classifiers":[
        {
            "category":"Transit Center",
            "subcategory":"Passenger",
            "type":"Transportation"
        }
    ],
    "sg:postcode":"WA6 0PF",
    "sg:province":"Cheshire",
    "sg:tags":[
        "boarding",
        "kennel",
        "catteries"
    ],
    "wof:name":"Manley Boarding Kennels & Cattery",
    "wof:placetype":"venue"
},
  "geometry": {"coordinates":[-2.76931,53.24007],"type":"Point"}
}