{
  "type": "Feature",
  "properties": {
    "iso:country":"GB",
    "sg:address":"Westcott Street",
    "sg:city":"Swindon",
    "sg:classifiers":[
        {
            "category":"Education",
            "subcategory":"School",
            "type":"Public Place"
        },
        {
            "category":"Government",
            "subcategory":"Office",
            "type":"Public Place"
        }
    ],
    "sg:phone":"+44 1793 523119",
    "sg:postcode":"SN1 5HS",
    "sg:province":"Wiltshire",
    "sg:tags":[
        "local",
        "authority"
    ],
    "wof:name":"Le Kyng Robert Primary School",
    "wof:placetype":"venue"
},
  "geometry": {"coordinates":[-1.7969119549,51.5573196411],"type":"Point"}
}