{
  "type": "Feature",
  "properties": {
    "addr:full":"2 Church Cottages, Church La Ilkeston Derbyshire DE7 6DE",
    "addr:housenumber":"2",
    "addr:postcode":"de7 6de",
    "addr:street":"Church;La",
    "iso:country":"GB",
    "sg:address":"2 Church Cottages, Church La",
    "sg:city":"Ilkeston",
    "sg:classifiers":[
        {
            "category":"Professional",
            "subcategory":"Lawyer & Legal Services",
            "type":"Services"
        }
    ],
    "sg:phone":"+44 1332 834733",
    "sg:postcode":"DE7 6DE",
    "sg:province":"Derbyshire",
    "sg:tags":[
        "solicitor"
    ],
    "wof:name":"John Last",
    "wof:placetype":"venue"
},
  "geometry": {"coordinates":[-1.353533,52.982002],"type":"Point"}
}