{
  "type": "Feature",
  "properties": {
    "iso:country":"GB",
    "sg:address":"Studio 612b The Bid Peg, 120 Vyse St, The Jewelry Quarter,hockley",
    "sg:city":"Birmingham",
    "sg:classifiers":[
        {
            "category":"Professional",
            "subcategory":"Employment Agencies",
            "type":"Services"
        }
    ],
    "sg:postcode":"B18 6NF",
    "sg:province":"West Midlands",
    "sg:tags":[
        "modelling"
    ],
    "wof:name":"Wellington,Tony,",
    "wof:placetype":"venue"
},
  "geometry": {"coordinates":[-1.91242,52.487411],"type":"Point"}
}