{
  "type": "Feature",
  "properties": {
    "addr:full":"75a Town Lane, Benington Stevenage Hertfordshire SG2 7BT",
    "addr:housenumber":"75a",
    "addr:postcode":"sg2 7bt",
    "addr:street":"Town Lane",
    "iso:country":"GB",
    "sg:address":"75a Town Lane, Benington",
    "sg:city":"Stevenage",
    "sg:classifiers":[
        {
            "category":"Building & Trades",
            "subcategory":"Construction",
            "type":"Services"
        }
    ],
    "sg:phone":"+44 1438 869179",
    "sg:postcode":"SG2 7BT",
    "sg:province":"Hertfordshire",
    "sg:tags":[
        "contractor"
    ],
    "wof:name":"Ashbourne Construction Co",
    "wof:placetype":"venue"
},
  "geometry": {"coordinates":[-0.1053799987,51.8948974609],"type":"Point"}
}