{
  "type": "Feature",
  "properties": {
    "addr:full":"81 Station Rd, Castle Donnington Derby Leicestershire DE74 2NL",
    "addr:housenumber":"81",
    "addr:postcode":"de74 2nl",
    "addr:street":"Station Rd",
    "iso:country":"GB",
    "sg:address":"81 Station Rd, Castle Donnington",
    "sg:city":"Derby",
    "sg:classifiers":[
        {
            "category":"Professional",
            "subcategory":"Art Services",
            "type":"Services"
        },
        {
            "category":"Organizations",
            "subcategory":"Community Association",
            "type":"Services"
        }
    ],
    "sg:phone":"+44 1332 814440",
    "sg:postcode":"DE74 2NL",
    "sg:province":"Leicestershire",
    "sg:tags":[
        "photographer",
        "relation",
        "public"
    ],
    "wof:name":"Arrow,Anthony,",
    "wof:placetype":"venue"
},
  "geometry": {"coordinates":[-1.2739729881,52.8402862549],"type":"Point"}
}