{
  "type": "Feature",
  "properties": {
    "iso:country":"GB",
    "sg:address":"Beacon View Farm, Farley Way, Quorn",
    "sg:city":"Loughborough",
    "sg:classifiers":[
        {
            "category":"Shopping",
            "subcategory":"Musical Instruments",
            "type":"Retail Goods"
        }
    ],
    "sg:phone":"+44 1509 621611",
    "sg:postcode":"LE12 8RB",
    "sg:province":"Leicestershire",
    "wof:name":"Alexander Accessories",
    "wof:placetype":"venue"
},
  "geometry": {"coordinates":[-1.17994,52.741081],"type":"Point"}
}