{
  "type": "Feature",
  "properties": {
    "iso:country":"GB",
    "sg:address":"The Cottage, 30 Moor La",
    "sg:city":"Preston",
    "sg:classifiers":[
        {
            "category":"Personal",
            "subcategory":"Psychics & Astrologers",
            "type":"Services"
        }
    ],
    "sg:phone":"+44 1772 614441",
    "sg:postcode":"PR4 5SE",
    "sg:province":"Lancashire",
    "sg:tags":[
        "clairvoyant",
        "palmist"
    ],
    "wof:name":"Ramona",
    "wof:placetype":"venue"
},
  "geometry": {"coordinates":[-2.76046,53.73217],"type":"Point"}
}