{
  "type": "Feature",
  "properties": {
    "iso:country":"GB",
    "sg:address":"Poors Farm, Wall Hill Road",
    "sg:city":"Coventry",
    "sg:classifiers":[
        {
            "category":"Farming",
            "subcategory":"Livestock Farm",
            "type":"Manufacturing & Wholesale Goods"
        }
    ],
    "sg:postcode":"CV5 9EL",
    "sg:province":"West Midlands",
    "sg:tags":[
        "others"
    ],
    "wof:name":"J Elliott",
    "wof:placetype":"venue"
},
  "geometry": {"coordinates":[-1.55572,52.445889],"type":"Point"}
}