{
  "type": "Feature",
  "properties": {
    "addr:full":"21 St Georges Hill, Easton In Gordano Bristol Somerset BS20 0PS",
    "addr:housenumber":"21",
    "addr:postcode":"bs20 0ps",
    "addr:street":"St Georges Hill",
    "iso:country":"GB",
    "sg:address":"21 St Georges Hill, Easton In Gordano",
    "sg:city":"Bristol",
    "sg:classifiers":[
        {
            "category":"Personal",
            "subcategory":"Beauty Salon",
            "type":"Services"
        }
    ],
    "sg:phone":"+44 1275 374287",
    "sg:postcode":"BS20 0PS",
    "sg:province":"Somerset",
    "sg:tags":[
        "unisex",
        "hairdresser"
    ],
    "wof:name":"Arena Hair Design",
    "wof:placetype":"venue"
},
  "geometry": {"coordinates":[-2.700645,51.474758],"type":"Point"}
}