{
  "type": "Feature",
  "properties": {
    "iso:country":"GB",
    "sg:address":"16 High St",
    "sg:city":"Llanerchymedd",
    "sg:classifiers":[
        {
            "category":"Food & Beverages",
            "subcategory":"Meat & Fish",
            "type":"Retail Goods"
        }
    ],
    "sg:phone":"+44 1248 470215",
    "sg:postcode":"LL71 8EA",
    "sg:province":"Isle of Anglesey",
    "sg:tags":[
        "butcher"
    ],
    "wof:name":"T Roberts",
    "wof:placetype":"venue"
},
  "geometry": {"coordinates":[-4.375994,53.330456],"type":"Point"}
}