{
  "type": "Feature",
  "properties": {
    "addr:full":"13 The Green Richmond Greater London TW9 1PX",
    "addr:housenumber":"13",
    "addr:postcode":"tw9 1px",
    "addr:street":"The Green",
    "iso:country":"GB",
    "sg:address":"13 The Green",
    "sg:city":"Richmond",
    "sg:classifiers":[
        {
            "category":"Food & Beverages",
            "subcategory":"Candy",
            "type":"Retail Goods"
        }
    ],
    "sg:phone":"+44 20 8332 1503",
    "sg:postcode":"TW9 1PX",
    "sg:province":"Greater London",
    "sg:tags":[
        "confectioner"
    ],
    "wof:name":"The House of Chocolates",
    "wof:placetype":"venue"
},
  "geometry": {"coordinates":[-0.307279,51.460644],"type":"Point"}
}