{
  "type": "Feature",
  "properties": {
    "iso:country":"GB",
    "sg:address":"27 Moorfield Walk, Urmston",
    "sg:city":"Manchester",
    "sg:classifiers":[
        {
            "category":"Professional",
            "subcategory":"Business Services",
            "type":"Services"
        }
    ],
    "sg:phone":"+44 161 748 4359",
    "sg:postcode":"M41 0TT",
    "sg:province":"Cheshire",
    "sg:tags":[
        "bookmaker"
    ],
    "wof:name":"Stanley Racing Ltd.",
    "wof:placetype":"venue"
},
  "geometry": {"coordinates":[-2.35448,53.449261],"type":"Point"}
}