{
  "type": "Feature",
  "properties": {
    "iso:country":"GB",
    "sg:address":"Unit 1 Gidleys Meadow, Christow",
    "sg:city":"Exeter",
    "sg:classifiers":[
        {
            "category":"Wholesale",
            "subcategory":"Groceries",
            "type":"Manufacturing & Wholesale Goods"
        }
    ],
    "sg:postcode":"EX6 7QB",
    "sg:province":"Devon",
    "sg:tags":[
        "food",
        "supplier",
        "drink"
    ],
    "wof:name":"Sweet Sensations",
    "wof:placetype":"venue"
},
  "geometry": {"coordinates":[-3.6526100636,50.6527557373],"type":"Point"}
}