{
  "type": "Feature",
  "properties": {
    "addr:full":"Doncaster Road Selby East Riding of Yorkshire YO8 9BX",
    "addr:postcode":"yo8 9bx",
    "addr:street":"Doncaster Road",
    "iso:country":"GB",
    "sg:address":"Doncaster Road",
    "sg:city":"Selby",
    "sg:classifiers":[
        {
            "category":"Health Services",
            "subcategory":"Hospital",
            "type":"Services"
        }
    ],
    "sg:phone":"+44 1757 702664",
    "sg:postcode":"YO8 9BX",
    "sg:province":"East Riding of Yorkshire",
    "wof:name":"Selby War Memorial Hospital",
    "wof:placetype":"venue"
},
  "geometry": {"coordinates":[-1.0766589642,53.7790794373],"type":"Point"}
}