{
  "type": "Feature",
  "properties": {
    "iso:country":"GB",
    "sg:address":"146 Welling Way",
    "sg:city":"Welling",
    "sg:classifiers":[
        {
            "category":"Professional",
            "subcategory":"Business Services",
            "type":"Services"
        }
    ],
    "sg:phone":"+44 20 8856 9798",
    "sg:postcode":"DA16 2RS",
    "sg:province":"Kent",
    "sg:tags":[
        "organisation",
        "trade"
    ],
    "wof:name":"National Association Of The Launderette Industry",
    "wof:placetype":"venue"
},
  "geometry": {"coordinates":[0.0852240026,51.4619903564],"type":"Point"}
}