{
  "type": "Feature",
  "properties": {
    "addr:full":"19 Owen Drive Liverpool Merseyside L24 1YL",
    "addr:housenumber":"19",
    "addr:postcode":"l24 1yl",
    "addr:street":"Owen Drive",
    "iso:country":"GB",
    "sg:address":"19 Owen Drive",
    "sg:city":"Liverpool",
    "sg:classifiers":[
        {
            "category":"Home & Garden",
            "subcategory":"Building Materials",
            "type":"Retail Goods"
        }
    ],
    "sg:phone":"+44 151 486 9808",
    "sg:postcode":"L24 1YL",
    "sg:province":"Merseyside",
    "sg:tags":[
        "plaster",
        "ware"
    ],
    "wof:name":"Draco Mouldings",
    "wof:placetype":"venue"
},
  "geometry": {"coordinates":[-2.859612,53.340698],"type":"Point"}
}