{
  "type": "Feature",
  "properties": {
    "addr:full":"Kiosk 2 St Nicholas Shopping C, Entre, St Nicholas Way Sutton Surrey SM1 1AY",
    "addr:housenumber":"2",
    "addr:postcode":"sm1 1ay",
    "addr:street":"St;Entre St Nicholas Way",
    "iso:country":"GB",
    "sg:address":"Kiosk 2 St Nicholas Shopping C, Entre, St Nicholas Way",
    "sg:city":"Sutton",
    "sg:classifiers":[
        {
            "category":"Shopping",
            "subcategory":"Comic Books",
            "type":"Retail Goods"
        }
    ],
    "sg:phone":"+44 20 8643 9092",
    "sg:postcode":"SM1 1AY",
    "sg:province":"Surrey",
    "sg:tags":[
        "jeweller"
    ],
    "wof:name":"H Purchen",
    "wof:placetype":"venue"
},
  "geometry": {"coordinates":[-0.19478,51.364731],"type":"Point"}
}