{
  "type": "Feature",
  "properties": {
    "addr:full":"216 Shear Brow Blackburn Lancashire BB1 8DS",
    "addr:housenumber":"216",
    "addr:postcode":"bb1 8ds",
    "addr:street":"Shear Brow",
    "iso:country":"GB",
    "sg:address":"216 Shear Brow",
    "sg:city":"Blackburn",
    "sg:classifiers":[
        {
            "category":"Shopping",
            "subcategory":"News",
            "type":"Retail Goods"
        }
    ],
    "sg:phone":"+44 1254 55581",
    "sg:postcode":"BB1 8DS",
    "sg:province":"Lancashire",
    "sg:tags":[
        "newsagent"
    ],
    "wof:name":"United News Shops Ltd",
    "wof:placetype":"venue"
},
  "geometry": {"coordinates":[-2.4875130653,53.7606697083],"type":"Point"}
}