{
  "type": "Feature",
  "properties": {
    "addr:full":"Green Lane, Maghull Liverpool Lancashire L31 8BD",
    "addr:postcode":"l31 8bd",
    "addr:street":"Green Lane",
    "iso:country":"GB",
    "sg:address":"Green Lane, Maghull",
    "sg:city":"Liverpool",
    "sg:classifiers":[
        {
            "category":"Place Of Worship",
            "type":"Public Place"
        },
        {
            "category":"Organizations",
            "subcategory":"Non-profit Organization",
            "type":"Services"
        }
    ],
    "sg:phone":"+44 151 526 6626",
    "sg:postcode":"L31 8BD",
    "sg:province":"Lancashire",
    "sg:tags":[
        "charitable",
        "organisation",
        "charity"
    ],
    "wof:name":"St James C of E Church",
    "wof:placetype":"venue"
},
  "geometry": {"coordinates":[-2.9524641037,53.5195198059],"type":"Point"}
}