{
  "type": "Feature",
  "properties": {
    "iso:country":"GB",
    "sg:address":"Dumbryden Gardens",
    "sg:city":"Edinburgh",
    "sg:classifiers":[
        {
            "category":"Education",
            "subcategory":"School",
            "type":"Public Place"
        },
        {
            "category":"Government",
            "subcategory":"Office",
            "type":"Public Place"
        }
    ],
    "sg:phone":"+44 131 453 5686",
    "sg:postcode":"EH14 2NZ",
    "sg:province":"City of Edinburgh",
    "sg:tags":[
        "local",
        "authority"
    ],
    "wof:name":"Dumbryden Primary School",
    "wof:placetype":"venue"
},
  "geometry": {"coordinates":[-3.273814,55.921776],"type":"Point"}
}