{
  "type": "Feature",
  "properties": {
    "addr:full":"7 Exeter Parade, Exeter Road London Greater London NW2 3UH",
    "addr:housenumber":"7",
    "addr:postcode":"nw2 3uh",
    "addr:street":"Exeter Parade Exeter Road",
    "iso:country":"GB",
    "sg:address":"7 Exeter Parade, Exeter Road",
    "sg:city":"London",
    "sg:classifiers":[
        {
            "category":"Taxi",
            "type":"Transportation"
        }
    ],
    "sg:postcode":"NW2 3UH",
    "sg:province":"Greater London",
    "sg:tags":[
        "mini",
        "cab"
    ],
    "wof:name":"Princeps Couriers",
    "wof:placetype":"venue"
},
  "geometry": {"coordinates":[-0.2072190046,51.5477294922],"type":"Point"}
}