{
  "type": "Feature",
  "properties": {
    "addr:full":"30a Dundas Street Edinburgh City of Edinburgh EH3 6JN",
    "addr:housenumber":"30a",
    "addr:postcode":"eh3 6jn",
    "addr:street":"Dundas Street",
    "iso:country":"GB",
    "sg:address":"30a Dundas Street",
    "sg:city":"Edinburgh",
    "sg:classifiers":[
        {
            "category":"Home & Garden",
            "subcategory":"Home Furnishings",
            "type":"Retail Goods"
        },
        {
            "category":"Shopping",
            "subcategory":"Crafts & Fabrics",
            "type":"Retail Goods"
        }
    ],
    "sg:postcode":"EH3 6JN",
    "sg:province":"City of Edinburgh",
    "sg:tags":[
        "beds",
        "linen",
        "bedding",
        "blanket"
    ],
    "wof:name":"RMK (SCOTLAND) LTD",
    "wof:placetype":"venue"
},
  "geometry": {"coordinates":[-3.199469,55.957157],"type":"Point"}
}