{
  "type": "Feature",
  "properties": {
    "addr:full":"19 Barns St Ayr South Ayrshire KA7 1XB",
    "addr:housenumber":"19",
    "addr:postcode":"ka7 1xb",
    "addr:street":"Barns St",
    "iso:country":"GB",
    "sg:address":"19 Barns St",
    "sg:city":"Ayr",
    "sg:classifiers":[
        {
            "category":"Health Services",
            "subcategory":"Dentist",
            "type":"Services"
        }
    ],
    "sg:phone":"+44 1292 265167",
    "sg:postcode":"KA7 1XB",
    "sg:province":"South Ayrshire",
    "wof:name":"Gordon Hunter",
    "wof:placetype":"venue"
},
  "geometry": {"coordinates":[-4.6336898804,55.4607200623],"type":"Point"}
}