{
  "type": "Feature",
  "properties": {
    "addr:full":"66 Washington Gro Doncaster South Yorkshire DN5 9RL",
    "addr:housenumber":"66",
    "addr:postcode":"dn5 9rl",
    "addr:street":"Washington Gro Doncaster South",
    "iso:country":"GB",
    "sg:address":"66 Washington Gro",
    "sg:city":"Doncaster",
    "sg:classifiers":[
        {
            "category":"Professional",
            "type":"Services"
        }
    ],
    "sg:phone":"+44 1302 875878",
    "sg:postcode":"DN5 9RL",
    "sg:province":"South Yorkshire",
    "sg:tags":[
        "reflexologists"
    ],
    "wof:name":"Susan Bani",
    "wof:placetype":"venue"
},
  "geometry": {"coordinates":[-1.1516489983,53.5395698547],"type":"Point"}
}