{
  "type": "Feature",
  "properties": {
    "addr:full":"Tecan Way, Granby Industrial Estate Weymouth Dorset DT4 9TU",
    "addr:housenumber":"estate",
    "addr:postcode":"dt4 9tu",
    "addr:street":"Tecan Way;Industrial",
    "iso:country":"GB",
    "sg:address":"Tecan Way, Granby Industrial Estate",
    "sg:city":"Weymouth",
    "sg:classifiers":[
        {
            "category":"Manufacturing",
            "subcategory":"Wood Products",
            "type":"Manufacturing & Wholesale Goods"
        }
    ],
    "sg:phone":"+44 1305 765400",
    "sg:postcode":"DT4 9TU",
    "sg:province":"Dorset",
    "wof:name":"Tecfoil",
    "wof:placetype":"venue"
},
  "geometry": {"coordinates":[-2.4860210419,50.6115341187],"type":"Point"}
}