{
  "type": "Feature",
  "properties": {
    "iso:country":"GB",
    "sg:address":"Vicarage",
    "sg:city":"Congleton",
    "sg:classifiers":[
        {
            "category":"Place Of Worship",
            "type":"Public Place"
        }
    ],
    "sg:phone":"+44 1260 279863",
    "sg:postcode":"CW12 2JQ",
    "sg:province":"Cheshire",
    "wof:name":"St Michael C Of E Church",
    "wof:placetype":"venue"
},
  "geometry": {"coordinates":[-2.196499,53.18705],"type":"Point"}
}