{
  "type": "Feature",
  "properties": {
    "iso:country":"GB",
    "sg:address":"24 Aursbridge Drive, Barrhead",
    "sg:city":"Glasgow",
    "sg:classifiers":[
        {
            "category":"Freight",
            "type":"Transportation"
        }
    ],
    "sg:postcode":"G78 2TH",
    "sg:province":"East Ayrshire",
    "sg:tags":[
        "haulage",
        "road"
    ],
    "wof:name":"Brian Missud",
    "wof:placetype":"venue"
},
  "geometry": {"coordinates":[-4.382152,55.80035],"type":"Point"}
}