{
  "type": "Feature",
  "properties": {
    "addr:full":"24 Aursbridge Drive, Barrhead Glasgow East Ayrshire G78 2TH",
    "addr:housenumber":"24",
    "addr:postcode":"g78 2th",
    "addr:street":"Aursbridge Drive",
    "iso:country":"GB",
    "sg:address":"24 Aursbridge Drive, Barrhead",
    "sg:city":"Glasgow",
    "sg:classifiers":[
        {
            "category":"Freight",
            "type":"Transportation"
        }
    ],
    "sg:postcode":"G78 2TH",
    "sg:province":"East Ayrshire",
    "sg:tags":[
        "haulage",
        "road"
    ],
    "wof:name":"Brian Missud",
    "wof:placetype":"venue"
},
  "geometry": {"coordinates":[-4.382152,55.80035],"type":"Point"}
}