{
  "type": "Feature",
  "properties": {
    "iso:country":"GB",
    "sg:address":"34 Elm Grove South, Barnham",
    "sg:city":"Bognor Regis",
    "sg:classifiers":[
        {
            "category":"Health Services",
            "subcategory":"Podiatrist",
            "type":"Services"
        },
        {
            "category":"Health Services",
            "subcategory":"Chiropractor",
            "type":"Services"
        }
    ],
    "sg:phone":"+44 1243 552899",
    "sg:postcode":"PO22 0EL",
    "sg:province":"West Sussex",
    "sg:tags":[
        "podiatrists",
        "chiropodist"
    ],
    "wof:name":"Keith Bates",
    "wof:placetype":"venue"
},
  "geometry": {"coordinates":[-0.6464949846,50.8348426819],"type":"Point"}
}