{
  "type": "Feature",
  "properties": {
    "addr:full":"5-6 Underhill Street, 10a Cunningham Place London Greater London NW1 7HS",
    "addr:housenumber":"5-6;10a",
    "addr:postcode":"nw1 7hs",
    "addr:street":"Underhill Street;Place",
    "iso:country":"GB",
    "sg:address":"5-6 Underhill Street, 10a Cunningham Place",
    "sg:city":"London",
    "sg:classifiers":[
        {
            "category":"Professional",
            "type":"Services"
        }
    ],
    "sg:phone":"+44 20 7485 5151",
    "sg:postcode":"NW1 7HS",
    "sg:province":"Greater London",
    "sg:tags":[
        "interior",
        "furnishers",
        "designer"
    ],
    "wof:name":"Landseer Design Ltd.",
    "wof:placetype":"venue"
},
  "geometry": {"coordinates":[-0.1429499984,51.5377388],"type":"Point"}
}