{
  "type": "Feature",
  "properties": {
    "addr:full":"19-21 Upper George Street Luton Bedfordshire LU1 2RD",
    "addr:housenumber":"19-21",
    "addr:postcode":"lu1 2rd",
    "addr:street":"Upper George Street",
    "iso:country":"GB",
    "sg:address":"19-21 Upper George Street",
    "sg:city":"Luton",
    "sg:classifiers":[
        {
            "category":"Fast Food",
            "type":"Food & Drink"
        }
    ],
    "sg:phone":"+44 1582 413450",
    "sg:postcode":"LU1 2RD",
    "sg:province":"Bedfordshire",
    "sg:tags":[
        "away",
        "meal",
        "outlet",
        "take"
    ],
    "wof:name":"The Sandwich Shop",
    "wof:placetype":"venue"
},
  "geometry": {"coordinates":[-0.419511,51.879642],"type":"Point"}
}