{
  "type": "Feature",
  "properties": {
    "addr:full":"5 Elstree Gate, Elstree Way Borehamwood Hertfordshire WD6 1JD",
    "addr:housenumber":"5",
    "addr:postcode":"wd6 1jd",
    "addr:street":"Elstree Gate Elstree Way",
    "iso:country":"GB",
    "sg:address":"5 Elstree Gate, Elstree Way",
    "sg:city":"Borehamwood",
    "sg:classifiers":[
        {
            "category":"Banks & Credit Unions",
            "subcategory":"Financial Services",
            "type":"Services"
        }
    ],
    "sg:phone":"+44 20 8207 4860",
    "sg:postcode":"WD6 1JD",
    "sg:province":"Hertfordshire",
    "sg:tags":[
        "consultant"
    ],
    "wof:name":"Delta Financial Management Plc",
    "wof:placetype":"venue"
},
  "geometry": {"coordinates":[-0.257637,51.659252],"type":"Point"}
}