{
  "type": "Feature",
  "properties": {
    "iso:country":"GB",
    "sg:address":"Bridge Street",
    "sg:city":"Abertillery",
    "sg:classifiers":[
        {
            "category":"Bars & Pubs",
            "type":"Food & Drink"
        }
    ],
    "sg:phone":"+44 1495 212732",
    "sg:postcode":"NP13 1UB",
    "sg:province":"Blaenau Gwent",
    "sg:tags":[
        "pubs",
        "inn"
    ],
    "wof:name":"The Railway Inn",
    "wof:placetype":"venue"
},
  "geometry": {"coordinates":[-3.139297,51.73053],"type":"Point"}
}