{
  "type": "Feature",
  "properties": {
    "iso:country":"GB",
    "sg:address":"53 Wostenholm Rd, Nether Edge",
    "sg:city":"Sheffield",
    "sg:classifiers":[
        {
            "category":"Professional",
            "subcategory":"Computer Services",
            "type":"Services"
        }
    ],
    "sg:phone":"+44 114 250 8905",
    "sg:postcode":"S7 1LG",
    "sg:province":"South Yorkshire",
    "sg:tags":[
        "system",
        "software"
    ],
    "wof:name":"Kpmd Solutions Ltd",
    "wof:placetype":"venue"
},
  "geometry": {"coordinates":[-1.481,53.365372],"type":"Point"}
}