{
  "type": "Feature",
  "properties": {
    "iso:country":"GB",
    "sg:address":"3 High Buildings, Kilmichael Glassary",
    "sg:city":"Lochgilphead",
    "sg:classifiers":[
        {
            "category":"Food & Beverages",
            "subcategory":"Meat & Fish",
            "type":"Retail Goods"
        }
    ],
    "sg:phone":"+44 1546 606965",
    "sg:postcode":"PA31 8QA",
    "sg:province":"Argyll and Bute",
    "sg:tags":[
        "merchant"
    ],
    "wof:name":"Haz Fyne",
    "wof:placetype":"venue"
},
  "geometry": {"coordinates":[-5.4318242073,56.0361061096],"type":"Point"}
}