{
  "type": "Feature",
  "properties": {
    "addr:full":"Park Works Manchester Greater Manchester M40 2BA",
    "addr:postcode":"m40 2ba",
    "addr:street":"Park",
    "iso:country":"GB",
    "sg:address":"Park Works",
    "sg:city":"Manchester",
    "sg:classifiers":[
        {
            "category":"Professional",
            "subcategory":"Engineering",
            "type":"Services"
        }
    ],
    "sg:phone":"+44 1730 262244",
    "sg:postcode":"M40 2BA",
    "sg:province":"Greater Manchester",
    "wof:name":"Weir T P Ltd.",
    "wof:placetype":"venue"
},
  "geometry": {"coordinates":[-2.192779,53.497509],"type":"Point"}
}