{
  "type": "Feature",
  "properties": {
    "addr:full":"189a Liverpool Rd Southport Lancashire PR8 4NZ",
    "addr:housenumber":"189a",
    "addr:postcode":"pr8 4nz",
    "addr:street":"Liverpool Rd",
    "iso:country":"GB",
    "sg:address":"189a Liverpool Rd",
    "sg:city":"Southport",
    "sg:classifiers":[
        {
            "category":"Personal",
            "subcategory":"Barber",
            "type":"Services"
        }
    ],
    "sg:phone":"+44 1704 565938",
    "sg:postcode":"PR8 4NZ",
    "sg:province":"Lancashire",
    "sg:tags":[
        "men's",
        "hairdresser"
    ],
    "wof:name":"Aimie's Barbers",
    "wof:placetype":"venue"
},
  "geometry": {"coordinates":[-3.012417,53.62199],"type":"Point"}
}