{
  "type": "Feature",
  "properties": {
    "addr:full":"Henley House, Coventry Street Southam Warwickshire CV33 0EA",
    "addr:postcode":"cv33 0ea",
    "addr:street":"Coventry Street",
    "iso:country":"GB",
    "sg:address":"Henley House, Coventry Street",
    "sg:city":"Southam",
    "sg:classifiers":[
        {
            "category":"Shopping",
            "subcategory":"News",
            "type":"Retail Goods"
        }
    ],
    "sg:phone":"+44 1926 817360",
    "sg:postcode":"CV33 0EA",
    "sg:province":"Warwickshire",
    "sg:tags":[
        "newsagent"
    ],
    "wof:name":"Martin Retail Group Ltd.",
    "wof:placetype":"venue"
},
  "geometry": {"coordinates":[-1.3880790472,52.2555618286],"type":"Point"}
}