{
  "type": "Feature",
  "properties": {
    "addr:full":"70 London Road Sawbridgeworth Essex CM21 9JN",
    "addr:housenumber":"70",
    "addr:postcode":"cm21 9jn",
    "addr:street":"London Road",
    "iso:country":"GB",
    "sg:address":"70 London Road",
    "sg:city":"Sawbridgeworth",
    "sg:classifiers":[
        {
            "category":"Professional",
            "subcategory":"Printing & Photocopies",
            "type":"Services"
        }
    ],
    "sg:phone":"+44 1279 600681",
    "sg:postcode":"CM21 9JN",
    "sg:province":"Essex",
    "sg:tags":[
        "trophy"
    ],
    "wof:name":"Prized Awards",
    "wof:placetype":"venue"
},
  "geometry": {"coordinates":[0.148196,51.814411],"type":"Point"}
}