{
  "type": "Feature",
  "properties": {
    "addr:full":"Medical Centre, Egmanton Road, Meden Vale Mansfield Derbyshire NG20 9QN",
    "addr:postcode":"ng20 9qn",
    "addr:street":"Egmanton Road Meden",
    "iso:country":"GB",
    "sg:address":"Medical Centre, Egmanton Road, Meden Vale",
    "sg:city":"Mansfield",
    "sg:classifiers":[
        {
            "category":"Health Services",
            "subcategory":"Doctor",
            "type":"Services"
        }
    ],
    "sg:phone":"+44 1623 845694",
    "sg:postcode":"NG20 9QN",
    "sg:province":"Derbyshire",
    "sg:tags":[
        "practitioners"
    ],
    "wof:name":"Mansfield District Primary Care Trust",
    "wof:placetype":"venue"
},
  "geometry": {"coordinates":[-1.127532,53.222408],"type":"Point"}
}