{
  "type": "Feature",
  "properties": {
    "addr:full":"The Hillier Garden Centre, Hermitage Newbury Berkshire RG18 9TG",
    "addr:postcode":"rg18 9tg",
    "addr:street":"Newbury",
    "iso:country":"GB",
    "sg:address":"The Hillier Garden Centre, Hermitage",
    "sg:city":"Newbury",
    "sg:classifiers":[
        {
            "category":"Home & Garden",
            "subcategory":"Hardware",
            "type":"Retail Goods"
        }
    ],
    "sg:phone":"+44 1635 201623",
    "sg:postcode":"RG18 9TG",
    "sg:province":"Berkshire",
    "sg:tags":[
        "lawnmowers",
        "machinery"
    ],
    "wof:name":"Kalehurst Garden Machinery Ltd.",
    "wof:placetype":"venue"
},
  "geometry": {"coordinates":[-1.271127,51.454067],"type":"Point"}
}