{
  "type": "Feature",
  "properties": {
    "iso:country":"GB",
    "sg:address":"Mayfields, South Hanningfield Road",
    "sg:city":"Wickford",
    "sg:classifiers":[
        {
            "category":"Building & Trades",
            "subcategory":"Construction",
            "type":"Services"
        }
    ],
    "sg:postcode":"SS11 7PF",
    "sg:province":"Essex",
    "sg:tags":[
        "joiner",
        "carpenter"
    ],
    "wof:name":"Mayfield Interiors Ltd.",
    "wof:placetype":"venue"
},
  "geometry": {"coordinates":[0.527545,51.625999],"type":"Point"}
}