{
  "type": "Feature",
  "properties": {
    "addr:full":"23 Quality St Edinburgh City of Edinburgh EH4 5HP",
    "addr:housenumber":"23",
    "addr:postcode":"eh4 5hp",
    "addr:street":"Quality St",
    "iso:country":"GB",
    "sg:address":"23 Quality St",
    "sg:city":"Edinburgh",
    "sg:classifiers":[
        {
            "category":"Organizations",
            "subcategory":"Non-profit Organization",
            "type":"Services"
        }
    ],
    "sg:postcode":"EH4 5HP",
    "sg:province":"City of Edinburgh",
    "sg:tags":[
        "alarm",
        "system"
    ],
    "wof:name":"Edinburgh Security Systems",
    "wof:placetype":"venue"
},
  "geometry": {"coordinates":[-3.2735691071,55.9640731812],"type":"Point"}
}