{
  "type": "Feature",
  "properties": {
    "addr:full":"7/9 Willow Dale Centre Wickford Essex SS12 0RA",
    "addr:housenumber":"7 / 9",
    "addr:postcode":"ss12 0ra",
    "addr:street":"Willow Dale Centre",
    "iso:country":"GB",
    "sg:address":"7/9 Willow Dale Centre",
    "sg:city":"Wickford",
    "sg:classifiers":[
        {
            "category":"Shopping",
            "subcategory":"Pharmacy",
            "type":"Retail Goods"
        }
    ],
    "sg:phone":"+44 1268 762605",
    "sg:postcode":"SS12 0RA",
    "sg:province":"Essex",
    "sg:tags":[
        "pharmacist",
        "chemist"
    ],
    "wof:name":"Co-Op Pharmacy",
    "wof:placetype":"venue"
},
  "geometry": {"coordinates":[0.5189149976,51.6114349365],"type":"Point"}
}