{
  "type": "Feature",
  "properties": {
    "iso:country":"GB",
    "sg:address":"43 Frederick Street",
    "sg:city":"Birmingham",
    "sg:classifiers":[
        {
            "category":"Professional",
            "subcategory":"Printing & Photocopies",
            "type":"Services"
        }
    ],
    "sg:phone":"+44 121 212 0803",
    "sg:postcode":"B1 3HN",
    "sg:province":"West Midlands",
    "sg:tags":[
        "emblem",
        "wholesale",
        "badge"
    ],
    "wof:name":"Midland Badge Co. Ltd.",
    "wof:placetype":"venue"
},
  "geometry": {"coordinates":[-1.912465,52.486172],"type":"Point"}
}