{
  "type": "Feature",
  "properties": {
    "addr:full":"Ar Tigh, Kinellar Aberdeen Aberdeen City AB21 0SS",
    "addr:postcode":"ab21 0ss",
    "iso:country":"GB",
    "sg:address":"Ar Tigh, Kinellar",
    "sg:city":"Aberdeen",
    "sg:classifiers":[
        {
            "category":"Education",
            "subcategory":"School",
            "type":"Public Place"
        },
        {
            "category":"Government",
            "subcategory":"Office",
            "type":"Public Place"
        }
    ],
    "sg:phone":"+44 1224 790235",
    "sg:postcode":"AB21 0SS",
    "sg:province":"Aberdeen City",
    "sg:tags":[
        "local",
        "authority"
    ],
    "wof:name":"Kinellar Primary School",
    "wof:placetype":"venue"
},
  "geometry": {"coordinates":[-2.3451750278,57.2167320251],"type":"Point"}
}