{
  "type": "Feature",
  "properties": {
    "iso:country":"GB",
    "sg:address":"60 Shepherd Cross St",
    "sg:city":"Bolton",
    "sg:classifiers":[
        {
            "category":"Sports & Exercise",
            "subcategory":"Tennis Court",
            "type":"Entertainment"
        }
    ],
    "sg:phone":"+44 1204 457458",
    "sg:postcode":"BL1 3BY",
    "sg:province":"Lancashire",
    "sg:tags":[
        "breakdown",
        "recovery"
    ],
    "wof:name":"Ricks Recoveries",
    "wof:placetype":"venue"
},
  "geometry": {"coordinates":[-2.449013,53.587204],"type":"Point"}
}