{
  "type": "Feature",
  "properties": {
    "addr:full":"6 Killoch Place Ayr South Ayrshire KA7 2EA",
    "addr:housenumber":"6",
    "addr:postcode":"ka7 2ea",
    "addr:street":"Killoch Place",
    "iso:country":"GB",
    "sg:address":"6 Killoch Place",
    "sg:city":"Ayr",
    "sg:classifiers":[
        {
            "category":"Professional",
            "subcategory":"Lawyer & Legal Services",
            "type":"Services"
        }
    ],
    "sg:phone":"+44 1292 611177",
    "sg:postcode":"KA7 2EA",
    "sg:province":"South Ayrshire",
    "sg:tags":[
        "solicitor"
    ],
    "wof:name":"Wallace Hodge & Co.",
    "wof:placetype":"venue"
},
  "geometry": {"coordinates":[-4.6290941238,55.4582595825],"type":"Point"}
}