{
  "type": "Feature",
  "properties": {
    "addr:full":"93-105 Blenheim St Newcastle-upon-tyne Tyne and Wear NE1 4HD",
    "addr:housenumber":"93-105",
    "addr:postcode":"ne1 4hd",
    "addr:street":"Blenheim St",
    "iso:country":"GB",
    "sg:address":"93-105 Blenheim St",
    "sg:city":"Newcastle-upon-tyne",
    "sg:classifiers":[
        {
            "category":"Building & Trades",
            "subcategory":"Construction",
            "type":"Services"
        }
    ],
    "sg:phone":"+44 191 222 9200",
    "sg:postcode":"NE1 4HD",
    "sg:province":"Tyne and Wear",
    "sg:tags":[
        "builder"
    ],
    "wof:name":"Haden Young Ltd",
    "wof:placetype":"venue"
},
  "geometry": {"coordinates":[-1.6234489679,54.96692276],"type":"Point"}
}