{
  "type": "Feature",
  "properties": {
    "addr:full":"19 Beaufort Drive, Kittle Swansea Swansea SA3 3LD",
    "addr:housenumber":"19",
    "addr:postcode":"sa3 3ld",
    "addr:street":"Beaufort Drive",
    "iso:country":"GB",
    "sg:address":"19 Beaufort Drive, Kittle",
    "sg:city":"Swansea",
    "sg:classifiers":[
        {
            "category":"Professional",
            "subcategory":"Engineering",
            "type":"Services"
        }
    ],
    "sg:phone":"+44 1792 232445",
    "sg:postcode":"SA3 3LD",
    "sg:province":"Swansea",
    "sg:tags":[
        "contractor",
        "electrical",
        "engineer"
    ],
    "wof:name":"Brian Mogridge",
    "wof:placetype":"venue"
},
  "geometry": {"coordinates":[-4.060539,51.584396],"type":"Point"}
}