{
  "type": "Feature",
  "properties": {
    "addr:full":"Elmlea, Arnolds La Dartford Kent DA4 9HE",
    "addr:postcode":"da4 9he",
    "iso:country":"GB",
    "sg:address":"Elmlea, Arnolds La",
    "sg:city":"Dartford",
    "sg:classifiers":[
        {
            "category":"Real Estate",
            "subcategory":"Developer",
            "type":"Services"
        }
    ],
    "sg:phone":"+44 1322 225980",
    "sg:postcode":"DA4 9HE",
    "sg:province":"Kent",
    "sg:tags":[
        "property"
    ],
    "wof:name":"Kent Hayes Developments Ltd",
    "wof:placetype":"venue"
},
  "geometry": {"coordinates":[0.2336540073,51.415309906],"type":"Point"}
}