{
  "type": "Feature",
  "properties": {
    "iso:country":"GB",
    "sg:address":"14 Holly Clo",
    "sg:city":"Weston Super Mare",
    "sg:classifiers":[
        {
            "category":"Home & Garden",
            "subcategory":"Household Appliances",
            "type":"Retail Goods"
        }
    ],
    "sg:phone":"+44 1934 520605",
    "sg:postcode":"BS22 6RS",
    "sg:province":"Somerset",
    "sg:tags":[
        "electrical"
    ],
    "wof:name":"Security Electrical Services",
    "wof:placetype":"venue"
},
  "geometry": {"coordinates":[-2.916637,51.355873],"type":"Point"}
}