{
  "type": "Feature",
  "properties": {
    "iso:country":"GB",
    "sg:address":"152 Amery Gardens",
    "sg:city":"Romford",
    "sg:classifiers":[
        {
            "category":"Professional",
            "subcategory":"Detective & Security Services",
            "type":"Services"
        }
    ],
    "sg:postcode":"RM2 6RR",
    "sg:province":"Essex",
    "sg:tags":[
        "agency"
    ],
    "wof:name":"Michael Cutbush Detective Agencies",
    "wof:placetype":"venue"
},
  "geometry": {"coordinates":[0.218974,51.588329],"type":"Point"}
}