{
  "type": "Feature",
  "properties": {
    "iso:country":"GB",
    "sg:address":"91 Ingram Road",
    "sg:city":"Gillingham",
    "sg:classifiers":[
        {
            "category":"Social Services",
            "subcategory":"Retirement Home",
            "type":"Services"
        }
    ],
    "sg:postcode":"ME7 1SH",
    "sg:province":"Kent",
    "sg:tags":[
        "residential",
        "care"
    ],
    "wof:name":"Strand House",
    "wof:placetype":"venue"
},
  "geometry": {"coordinates":[0.560189,51.390179],"type":"Point"}
}