{
  "type": "Feature",
  "properties": {
    "addr:full":"1 Fiveways Parade, Hazel Gro Stockport Cheshire SK7 6DG",
    "addr:housenumber":"1",
    "addr:postcode":"sk7 6dg",
    "addr:street":"Fiveways Parade",
    "iso:country":"GB",
    "sg:address":"1 Fiveways Parade, Hazel Gro",
    "sg:city":"Stockport",
    "sg:classifiers":[
        {
            "category":"Shopping",
            "subcategory":"News",
            "type":"Retail Goods"
        }
    ],
    "sg:phone":"+44 1625 873697",
    "sg:postcode":"SK7 6DG",
    "sg:province":"Cheshire",
    "sg:tags":[
        "newsagent"
    ],
    "wof:name":"M & S M Packun",
    "wof:placetype":"venue"
},
  "geometry": {"coordinates":[-2.114199,53.367744],"type":"Point"}
}