{
  "type": "Feature",
  "properties": {
    "iso:country":"GB",
    "sg:address":"11 Nightingale Close",
    "sg:city":"Pinner",
    "sg:classifiers":[
        {
            "category":"Professional",
            "subcategory":"Management & Consulting",
            "type":"Services"
        }
    ],
    "sg:postcode":"HA5 2TN",
    "sg:province":"Greater London",
    "sg:tags":[
        "marketing",
        "consultant"
    ],
    "wof:name":"Richard Woolfe & Associates",
    "wof:placetype":"venue"
},
  "geometry": {"coordinates":[-0.396859,51.585529],"type":"Point"}
}