{
  "type": "Feature",
  "properties": {
    "iso:country":"GB",
    "sg:address":"1 Morgan St",
    "sg:city":"Cardigan",
    "sg:classifiers":[
        {
            "category":"Professional",
            "subcategory":"Management & Consulting",
            "type":"Services"
        }
    ],
    "sg:postcode":"SA43 1DF",
    "sg:province":"Ceredigion",
    "sg:tags":[
        "music"
    ],
    "wof:name":"Davies,Ian,",
    "wof:placetype":"venue"
},
  "geometry": {"coordinates":[-4.658642,52.083233],"type":"Point"}
}