{
  "type": "Feature",
  "properties": {
    "iso:country":"GB",
    "sg:address":"18th Floor, St Alphage Ho, 2 Fore St",
    "sg:city":"London",
    "sg:classifiers":[
        {
            "category":"Professional",
            "type":"Services"
        }
    ],
    "sg:phone":"+44 20 7628 4610",
    "sg:postcode":"EC2Y 5DA",
    "sg:province":"Greater London",
    "sg:tags":[
        "leasing"
    ],
    "wof:name":"Chartertech Leasing Ltd",
    "wof:placetype":"venue"
},
  "geometry": {"coordinates":[-0.091671,51.518066],"type":"Point"}
}