{
  "type": "Feature",
  "properties": {
    "addr:full":"45 Drum Street Edinburgh City of Edinburgh EH17 8RQ",
    "addr:housenumber":"45",
    "addr:postcode":"eh17 8rq",
    "addr:street":"Drum Street",
    "iso:country":"GB",
    "sg:address":"45 Drum Street",
    "sg:city":"Edinburgh",
    "sg:classifiers":[
        {
            "category":"Shopping",
            "subcategory":"Florist",
            "type":"Retail Goods"
        }
    ],
    "sg:postcode":"EH17 8RQ",
    "sg:province":"City of Edinburgh",
    "wof:name":"Gilmerton Flower Shop",
    "wof:placetype":"venue"
},
  "geometry": {"coordinates":[-3.132283926,55.905456543],"type":"Point"}
}