{
  "type": "Feature",
  "properties": {
    "addr:full":"54-56 Junction Road Kirkwall Orkney Islands KW15 1AW",
    "addr:housenumber":"54-56",
    "addr:postcode":"kw15 1aw",
    "addr:street":"Junction Road",
    "iso:country":"GB",
    "sg:address":"54-56 Junction Road",
    "sg:city":"Kirkwall",
    "sg:classifiers":[
        {
            "category":"Professional",
            "subcategory":"Management & Consulting",
            "type":"Services"
        }
    ],
    "sg:phone":"+44 1856 875302",
    "sg:postcode":"KW15 1AW",
    "sg:province":"Orkney Islands",
    "sg:tags":[
        "conservation"
    ],
    "wof:name":"Scottish Natural Heritage",
    "wof:placetype":"venue"
},
  "geometry": {"coordinates":[-2.96356,58.980434],"type":"Point"}
}