{
  "type": "Feature",
  "properties": {
    "addr:full":"Unit 4a, Wandle Way Mitcham Greater London CR4 4NB",
    "addr:housenumber":"unit 4a",
    "addr:postcode":"cr4 4nb",
    "addr:street":"Wandle Way",
    "iso:country":"GB",
    "sg:address":"Unit 4a, Wandle Way",
    "sg:city":"Mitcham",
    "sg:classifiers":[
        {
            "category":"Retail",
            "subcategory":"Auto Repair",
            "type":"Services"
        }
    ],
    "sg:phone":"+44 20 8640 5050",
    "sg:postcode":"CR4 4NB",
    "sg:province":"Greater London",
    "sg:tags":[
        "modification",
        "garage",
        "related"
    ],
    "wof:name":"Associated Motor Services",
    "wof:placetype":"venue"
},
  "geometry": {"coordinates":[-0.166722998,51.3953666687],"type":"Point"}
}