{
  "type": "Feature",
  "properties": {
    "addr:full":"146 Rectory Rd Worthing West Sussex BN14 7PJ",
    "addr:housenumber":"146",
    "addr:postcode":"bn14 7pj",
    "addr:street":"Rectory Rd",
    "iso:country":"GB",
    "sg:address":"146 Rectory Rd",
    "sg:city":"Worthing",
    "sg:classifiers":[
        {
            "category":"Bars & Pubs",
            "type":"Food & Drink"
        }
    ],
    "sg:phone":"+44 1903 266643",
    "sg:postcode":"BN14 7PJ",
    "sg:province":"West Sussex",
    "sg:tags":[
        "pubs",
        "inn"
    ],
    "wof:name":"Thomas A'becket",
    "wof:placetype":"venue"
},
  "geometry": {"coordinates":[-0.3921389878,50.8298606873],"type":"Point"}
}