{
  "type": "Feature",
  "properties": {
    "addr:full":"52 High Street, Botley Southampton Hampshire SO30 2EA",
    "addr:housenumber":"52",
    "addr:postcode":"so30 2ea",
    "addr:street":"High Street",
    "iso:country":"GB",
    "sg:address":"52 High Street, Botley",
    "sg:city":"Southampton",
    "sg:classifiers":[
        {
            "category":"Education",
            "subcategory":"School",
            "type":"Public Place"
        }
    ],
    "sg:phone":"+44 1489 782308",
    "sg:postcode":"SO30 2EA",
    "sg:province":"Hampshire",
    "sg:tags":[
        "local",
        "authority"
    ],
    "wof:name":"Botley C of E Primary School",
    "wof:placetype":"venue"
},
  "geometry": {"coordinates":[-1.276602,50.915577],"type":"Point"}
}