{
  "type": "Feature",
  "properties": {
    "iso:country":"GB",
    "sg:address":"Saltmeadows Rd",
    "sg:city":"Gateshead",
    "sg:classifiers":[
        {
            "category":"Professional",
            "subcategory":"Engineering",
            "type":"Services"
        }
    ],
    "sg:phone":"+44 191 477 0288",
    "sg:postcode":"NE8 1YZ",
    "sg:province":"Tyne and Wear",
    "sg:tags":[
        "industrial",
        "engineer"
    ],
    "wof:name":"Rolls Royce Nuclear Engineering Serivces",
    "wof:placetype":"venue"
},
  "geometry": {"coordinates":[-1.60634,54.957809],"type":"Point"}
}