{
  "type": "Feature",
  "properties": {
    "addr:full":"Hobson House, 155 Gower St Bloomsbury Greater London WC1E 6BH",
    "addr:housenumber":"155",
    "addr:postcode":"wc1e 6bh",
    "addr:street":"Gower St",
    "iso:country":"GB",
    "sg:address":"Hobson House, 155 Gower St",
    "sg:city":"Bloomsbury",
    "sg:classifiers":[
        {
            "category":"Professional",
            "subcategory":"Accounting & Tax Preparation",
            "type":"Services"
        }
    ],
    "sg:phone":"+44 20 7728 0000",
    "sg:postcode":"WC1E 6BH",
    "sg:province":"Greater London",
    "sg:tags":[
        "accountant"
    ],
    "wof:name":"Casson Beckman & Partners",
    "wof:placetype":"venue"
},
  "geometry": {"coordinates":[-0.1357389987,51.5253486633],"type":"Point"}
}