{
  "type": "Feature",
  "properties": {
    "iso:country":"GB",
    "sg:address":"47 Mansel St",
    "sg:city":"Swansea",
    "sg:classifiers":[
        {
            "category":"Fast Food",
            "type":"Food & Drink"
        }
    ],
    "sg:phone":"+44 1792 456267",
    "sg:postcode":"SA1 5SW",
    "sg:province":"Neath Port Talbot",
    "sg:tags":[
        "away",
        "take"
    ],
    "wof:name":"The Upper Crust",
    "wof:placetype":"venue"
},
  "geometry": {"coordinates":[-3.9519279003,51.6202774048],"type":"Point"}
}