{
  "type": "Feature",
  "properties": {
    "addr:full":"240 Whitchurch Road Cardiff Cardiff CF14 3ND",
    "addr:housenumber":"240",
    "addr:postcode":"cf14 3nd",
    "addr:street":"Whitchurch Road",
    "iso:country":"GB",
    "sg:address":"240 Whitchurch Road",
    "sg:city":"Cardiff",
    "sg:classifiers":[
        {
            "category":"Arena",
            "subcategory":"Sports Club",
            "type":"Entertainment"
        }
    ],
    "sg:phone":"+44 29 2061 9637",
    "sg:postcode":"CF14 3ND",
    "sg:province":"Cardiff",
    "wof:name":"Ski Council of Wales",
    "wof:placetype":"venue"
},
  "geometry": {"coordinates":[-3.192045927,51.5034103394],"type":"Point"}
}