{
  "type": "Feature",
  "properties": {
    "iso:country":"GB",
    "sg:address":"Cecil Street, Rothwell",
    "sg:city":"Kettering",
    "sg:classifiers":[
        {
            "category":"Arena",
            "subcategory":"Sports Club",
            "type":"Entertainment"
        }
    ],
    "sg:phone":"+44 1536 710694",
    "sg:postcode":"NN14 6EZ",
    "sg:province":"Northamptonshire",
    "wof:name":"Rothwell Town Football Club",
    "wof:placetype":"venue"
},
  "geometry": {"coordinates":[-0.803138,52.422359],"type":"Point"}
}