{
  "type": "Feature",
  "properties": {
    "iso:country":"GB",
    "sg:address":"3 Summerheath Road",
    "sg:city":"Hailsham",
    "sg:classifiers":[
        {
            "category":"Building & Trades",
            "subcategory":"Plumbing",
            "type":"Services"
        }
    ],
    "sg:postcode":"BN27 3DS",
    "sg:province":"East Sussex",
    "sg:tags":[
        "central",
        "heating"
    ],
    "wof:name":"March Plumbing & Heating",
    "wof:placetype":"venue"
},
  "geometry": {"coordinates":[0.254336,50.8657],"type":"Point"}
}