{
  "type": "Feature",
  "properties": {
    "addr:full":"Unit 3 58 Orchard Ple London Greater London E14 0JW",
    "addr:housenumber":"unit;58",
    "addr:postcode":"e14 0jw",
    "addr:street":"Orchard Ple",
    "iso:country":"GB",
    "sg:address":"Unit 3 58 Orchard Ple",
    "sg:city":"London",
    "sg:classifiers":[
        {
            "category":"Building & Trades",
            "subcategory":"Construction",
            "type":"Services"
        }
    ],
    "sg:phone":"+44 20 7515 3191",
    "sg:postcode":"E14 0JW",
    "sg:province":"Greater London",
    "sg:tags":[
        "builder"
    ],
    "wof:name":"Gladstone Commercial Property Service",
    "wof:placetype":"venue"
},
  "geometry": {"coordinates":[-0.007683,51.511738],"type":"Point"}
}