{
  "type": "Feature",
  "properties": {
    "addr:full":"Berkshire House, 252-256 Kings Road Reading Berkshire RG1 4HP",
    "addr:housenumber":"252-256",
    "addr:postcode":"rg1 4hp",
    "addr:street":"Kings Road",
    "iso:country":"GB",
    "sg:address":"Berkshire House, 252-256 Kings Road",
    "sg:city":"Reading",
    "sg:classifiers":[
        {
            "category":"Organizations",
            "subcategory":"Membership Organization",
            "type":"Services"
        }
    ],
    "sg:postcode":"RG1 4HP",
    "sg:province":"Berkshire",
    "sg:tags":[
        "club"
    ],
    "wof:name":"Praxis Claims Management Ltd",
    "wof:placetype":"venue"
},
  "geometry": {"coordinates":[-0.960239,51.453899],"type":"Point"}
}