{
  "type": "Feature",
  "properties": {
    "iso:country":"GB",
    "sg:address":"57 Sherbrooke Rd",
    "sg:city":"Nottingham",
    "sg:classifiers":[
        {
            "category":"Building & Trades",
            "subcategory":"Plumbing",
            "type":"Services"
        }
    ],
    "sg:postcode":"NG5 2BE",
    "sg:province":"Nottinghamshire",
    "sg:tags":[
        "heating"
    ],
    "wof:name":"Bradley,Keith,",
    "wof:placetype":"venue"
},
  "geometry": {"coordinates":[-1.1532640457,52.9746170044],"type":"Point"}
}