{
  "type": "Feature",
  "properties": {
    "iso:country":"GB",
    "sg:address":"428 Carlton Road",
    "sg:city":"Barnsley",
    "sg:classifiers":[
        {
            "category":"Building & Trades",
            "subcategory":"Equipment Rental",
            "type":"Services"
        },
        {
            "category":"Home & Garden",
            "subcategory":"Building Materials",
            "type":"Retail Goods"
        }
    ],
    "sg:phone":"+44 1226 700079",
    "sg:postcode":"S71 3HX",
    "sg:province":"South Yorkshire",
    "sg:tags":[
        "access",
        "renting",
        "scaffold"
    ],
    "sg:website":"http://www.apollocradles.co.uk",
    "wof:name":"Apollo Cradles Ltd",
    "wof:placetype":"venue"
},
  "geometry": {"coordinates":[-1.453853,53.583153],"type":"Point"}
}