{
  "type": "Feature",
  "properties": {
    "addr:full":"Rear Of 103 Fore Street, Barton Torquay Devon TQ2 8BN",
    "addr:postcode":"tq2 8bn",
    "addr:street":"Fore Street",
    "iso:country":"GB",
    "sg:address":"Rear Of 103 Fore Street, Barton",
    "sg:city":"Torquay",
    "sg:classifiers":[
        {
            "category":"Retail",
            "subcategory":"Auto Repair",
            "type":"Services"
        }
    ],
    "sg:postcode":"TQ2 8BN",
    "sg:province":"Devon",
    "sg:tags":[
        "modification",
        "garage"
    ],
    "wof:name":"Monty William Wills",
    "wof:placetype":"venue"
},
  "geometry": {"coordinates":[-3.540626049,50.4952316284],"type":"Point"}
}