{
  "type": "Feature",
  "properties": {
    "addr:full":"51 Broad Street Teddington Greater London TW11 8QZ",
    "addr:housenumber":"51",
    "addr:postcode":"tw11 8qz",
    "addr:street":"Broad Street",
    "iso:country":"GB",
    "sg:address":"51 Broad Street",
    "sg:city":"Teddington",
    "sg:classifiers":[
        {
            "category":"Retail",
            "subcategory":"Laundry & Dry Cleaning",
            "type":"Services"
        }
    ],
    "sg:phone":"+44 20 8977 3496",
    "sg:postcode":"TW11 8QZ",
    "sg:province":"Greater London",
    "sg:tags":[
        "alteration"
    ],
    "wof:name":"Johnson Cleaners U K Ltd.",
    "wof:placetype":"venue"
},
  "geometry": {"coordinates":[-0.3376039863,51.4260902405],"type":"Point"}
}