{
  "type": "Feature",
  "properties": {
    "iso:country":"GB",
    "sg:address":"29b Cormer Industrial Park, Middleton",
    "sg:city":"Manchester",
    "sg:classifiers":[
        {
            "category":"Home & Garden",
            "subcategory":"Kitchen Supply",
            "type":"Retail Goods"
        }
    ],
    "sg:phone":"+44 1706 639082",
    "sg:postcode":"M24 2LE",
    "sg:province":"Greater Manchester",
    "sg:tags":[
        "bar",
        "accessory"
    ],
    "wof:name":"Core Supplies",
    "wof:placetype":"venue"
},
  "geometry": {"coordinates":[-2.191324,53.5494],"type":"Point"}
}