{
  "type": "Feature",
  "properties": {
    "addr:full":"Primrose Cottage, New Close Lane Doncaster North Yorkshire DN6 8NA",
    "addr:postcode":"dn6 8na",
    "addr:street":"New Close Lane",
    "iso:country":"GB",
    "sg:address":"Primrose Cottage, New Close Lane",
    "sg:city":"Doncaster",
    "sg:classifiers":[
        {
            "category":"Utilities",
            "subcategory":"Fuel Oil & Lpg",
            "type":"Services"
        }
    ],
    "sg:phone":"+44 1302 723626",
    "sg:postcode":"DN6 8NA",
    "sg:province":"North Yorkshire",
    "sg:tags":[
        "coal",
        "smokeless"
    ],
    "wof:name":"T Bridges & Sons",
    "wof:placetype":"venue"
},
  "geometry": {"coordinates":[-1.2198400497,53.608089447],"type":"Point"}
}