{
  "type": "Feature",
  "properties": {
    "iso:country":"GB",
    "sg:address":"Askern Saw Mills Ltd High Street, Askern",
    "sg:city":"Doncaster",
    "sg:classifiers":[
        {
            "category":"Manufacturing",
            "subcategory":"Lumber",
            "type":"Manufacturing & Wholesale Goods"
        }
    ],
    "sg:phone":"+44 1302 702963",
    "sg:postcode":"DN6 0AA",
    "sg:province":"North Yorkshire",
    "sg:tags":[
        "importer",
        "merchants",
        "agent",
        "timber"
    ],
    "wof:name":"Timber & Board Sales",
    "wof:placetype":"venue"
},
  "geometry": {"coordinates":[-1.145399,53.616341],"type":"Point"}
}