{
  "type": "Feature",
  "properties": {
    "addr:full":"20 Rookwood Way Haverhill Essex CB9 8PB",
    "addr:housenumber":"20",
    "addr:postcode":"cb9 8pb",
    "addr:street":"Rookwood Way",
    "iso:country":"GB",
    "sg:address":"20 Rookwood Way",
    "sg:city":"Haverhill",
    "sg:classifiers":[
        {
            "category":"Manufacturing",
            "subcategory":"Glass & Minerals",
            "type":"Manufacturing & Wholesale Goods"
        }
    ],
    "sg:phone":"+44 1440 703769",
    "sg:postcode":"CB9 8PB",
    "sg:province":"Essex",
    "sg:tags":[
        "vessel",
        "product",
        "manufacturer"
    ],
    "wof:name":"Glassfusion Ltd",
    "wof:placetype":"venue"
},
  "geometry": {"coordinates":[0.437797,52.07613],"type":"Point"}
}