{
  "type": "Feature",
  "properties": {
    "addr:full":"Lace Walk Car Park, Dowell Street Honiton Devon EX14 1LT",
    "addr:postcode":"ex14 1lt",
    "addr:street":"Lace;Dowell Street",
    "iso:country":"GB",
    "sg:address":"Lace Walk Car Park, Dowell Street",
    "sg:city":"Honiton",
    "sg:classifiers":[
        {
            "category":"Landmark",
            "subcategory":"Tourist Information",
            "type":"Public Place"
        }
    ],
    "sg:phone":"+44 1404 43716",
    "sg:postcode":"EX14 1LT",
    "sg:province":"Devon",
    "wof:name":"Tourist Information Centre",
    "wof:placetype":"venue"
},
  "geometry": {"coordinates":[-3.196906,50.797386],"type":"Point"}
}