{
  "type": "Feature",
  "properties": {
    "addr:full":"84 Middleton Hall Road, Kings Norton Birmingham West Midlands B30 1DG",
    "addr:housenumber":"84",
    "addr:postcode":"b30 1dg",
    "addr:street":"Middleton Hall Road",
    "iso:country":"GB",
    "sg:address":"84 Middleton Hall Road, Kings Norton",
    "sg:city":"Birmingham",
    "sg:classifiers":[
        {
            "category":"Building & Trades",
            "subcategory":"Construction",
            "type":"Services"
        }
    ],
    "sg:phone":"+44 121 458 1692",
    "sg:postcode":"B30 1DG",
    "sg:province":"West Midlands",
    "sg:tags":[
        "roofing"
    ],
    "wof:name":"Devine Roofing Services",
    "wof:placetype":"venue"
},
  "geometry": {"coordinates":[-1.936276,52.41526],"type":"Point"}
}