{
  "type": "Feature",
  "properties": {
    "iso:country":"GB",
    "sg:address":"The Workshop",
    "sg:city":"Whitstable",
    "sg:classifiers":[
        {
            "category":"Professional",
            "subcategory":"Art Services",
            "type":"Services"
        }
    ],
    "sg:phone":"+44 1227 263974",
    "sg:postcode":"CT5 1NA",
    "sg:province":"Kent",
    "sg:tags":[
        "framing"
    ],
    "wof:name":"Carfrae Framing",
    "wof:placetype":"venue"
},
  "geometry": {"coordinates":[1.026406,51.362247],"type":"Point"}
}