{
  "type": "Feature",
  "properties": {
    "addr:full":"28 Vincent St Yeovil Somerset BA20 1JQ",
    "addr:housenumber":"28",
    "addr:postcode":"ba20 1jq",
    "addr:street":"Vincent St",
    "iso:country":"GB",
    "sg:address":"28 Vincent St",
    "sg:city":"Yeovil",
    "sg:classifiers":[
        {
            "category":"Professional",
            "subcategory":"Art Services",
            "type":"Services"
        }
    ],
    "sg:phone":"+44 1935 478899",
    "sg:postcode":"BA20 1JQ",
    "sg:province":"Somerset",
    "sg:tags":[
        "picture",
        "restoration"
    ],
    "wof:name":"Macandrew Art & Frames",
    "wof:placetype":"venue"
},
  "geometry": {"coordinates":[-2.628419,50.942982],"type":"Point"}
}