{
  "type": "Feature",
  "properties": {
    "iso:country":"GB",
    "sg:address":"21 Woodbridge Hill",
    "sg:city":"Guildford",
    "sg:classifiers":[
        {
            "category":"Fast Food",
            "type":"Food & Drink"
        }
    ],
    "sg:phone":"+44 1483 564464",
    "sg:postcode":"GU2 9AA",
    "sg:province":"Surrey",
    "sg:tags":[
        "away",
        "take"
    ],
    "wof:name":"Fai Kee Chinese Takeaway",
    "wof:placetype":"venue"
},
  "geometry": {"coordinates":[-0.584908,51.24855],"type":"Point"}
}