{
  "type": "Feature",
  "properties": {
    "iso:country":"GB",
    "sg:address":"Hostingley Lane, Middlestown",
    "sg:city":"Wakefield",
    "sg:classifiers":[
        {
            "category":"Shopping",
            "subcategory":"Bicycles & Sporting Goods",
            "type":"Retail Goods"
        },
        {
            "category":"Wholesale",
            "subcategory":"Sporting Goods",
            "type":"Manufacturing & Wholesale Goods"
        }
    ],
    "sg:phone":"+44 1924 272877",
    "sg:postcode":"WF4 4PZ",
    "sg:province":"West Yorkshire",
    "sg:tags":[
        "supplier",
        "equipment",
        "camping"
    ],
    "wof:name":"Mitchells Practical Campers Ltd",
    "wof:placetype":"venue"
},
  "geometry": {"coordinates":[-1.604879,53.65033],"type":"Point"}
}