{
  "type": "Feature",
  "properties": {
    "iso:country":"GB",
    "sg:address":"7-9 Kingston Road",
    "sg:city":"Portsmouth",
    "sg:classifiers":[
        {
            "category":"Shopping",
            "subcategory":"Department Store",
            "type":"Retail Goods"
        },
        {
            "category":"Shopping",
            "subcategory":"Music",
            "type":"Retail Goods"
        }
    ],
    "sg:phone":"+44 23 9283 0955",
    "sg:postcode":"PO1 5RX",
    "sg:province":"Hampshire",
    "sg:tags":[
        "dvd",
        "tape",
        "vinyl",
        "cd"
    ],
    "wof:name":"Ross Records Ltd.",
    "wof:placetype":"venue"
},
  "geometry": {"coordinates":[-1.077416,50.807171],"type":"Point"}
}