{
  "type": "Feature",
  "properties": {
    "iso:country":"GB",
    "sg:address":"9 Lwr Bridge St",
    "sg:city":"Chester",
    "sg:classifiers":[
        {
            "category":"Professional",
            "subcategory":"Advertising",
            "type":"Services"
        }
    ],
    "sg:phone":"+44 1244 351122",
    "sg:postcode":"CH1 1RS",
    "sg:province":"Cheshire",
    "sg:tags":[
        "telemarketing"
    ],
    "wof:name":"Universal Promotions",
    "wof:placetype":"venue"
},
  "geometry": {"coordinates":[-2.890609026,53.1883964539],"type":"Point"}
}