{
  "type": "Feature",
  "properties": {
    "addr:full":"34 Brookmeadow Road, Shelfield Walsall West Midlands WS4 1TL",
    "addr:housenumber":"34",
    "addr:postcode":"ws4 1tl",
    "addr:street":"Brookmeadow Road",
    "iso:country":"GB",
    "sg:address":"34 Brookmeadow Road, Shelfield",
    "sg:city":"Walsall",
    "sg:classifiers":[
        {
            "category":"Building & Trades",
            "subcategory":"Construction",
            "type":"Services"
        }
    ],
    "sg:phone":"+44 1922 694532",
    "sg:postcode":"WS4 1TL",
    "sg:province":"West Midlands",
    "sg:tags":[
        "builder"
    ],
    "wof:name":"Saxonworld",
    "wof:placetype":"venue"
},
  "geometry": {"coordinates":[-1.9499850273,52.6142578125],"type":"Point"}
}