{
  "type": "Feature",
  "properties": {
    "iso:country":"GB",
    "sg:address":"125-127 London Road",
    "sg:city":"Oldham",
    "sg:classifiers":[
        {
            "category":"Food & Beverages",
            "subcategory":"Fruits & Vegetables",
            "type":"Retail Goods"
        },
        {
            "category":"Food & Beverages",
            "subcategory":"Groceries & Convenience Stores",
            "type":"Retail Goods"
        }
    ],
    "sg:phone":"+44 161 624 5846",
    "sg:postcode":"OL1 4BW",
    "sg:province":"Lancashire",
    "sg:tags":[
        "grocer",
        "greengrocer"
    ],
    "wof:name":"Singh's Supersave",
    "wof:placetype":"venue"
},
  "geometry": {"coordinates":[-2.0972249508,53.5511207581],"type":"Point"}
}