{
  "type": "Feature",
  "properties": {
    "iso:country":"GB",
    "sg:address":"19 Torvill Drive, Wollaton",
    "sg:city":"Nottingham",
    "sg:classifiers":[
        {
            "category":"Professional",
            "subcategory":"Engineering",
            "type":"Services"
        },
        {
            "category":"Real Estate",
            "subcategory":"Architect",
            "type":"Services"
        }
    ],
    "sg:phone":"+44 7973 890219",
    "sg:postcode":"NG8 2BU",
    "sg:province":"Nottinghamshire",
    "sg:tags":[
        "civil",
        "engineer"
    ],
    "wof:name":"Cooper Rail Ltd.",
    "wof:placetype":"venue"
},
  "geometry": {"coordinates":[-1.2266769409,52.9573669434],"type":"Point"}
}