{
  "type": "Feature",
  "properties": {
    "addr:full":"92 Barrow Road, Quorn Loughborough Leicestershire LE12 8DL",
    "addr:housenumber":"92",
    "addr:postcode":"le12 8dl",
    "addr:street":"Barrow Road",
    "iso:country":"GB",
    "sg:address":"92 Barrow Road, Quorn",
    "sg:city":"Loughborough",
    "sg:classifiers":[
        {
            "category":"Building & Trades",
            "subcategory":"Construction",
            "type":"Services"
        }
    ],
    "sg:postcode":"LE12 8DL",
    "sg:province":"Leicestershire",
    "sg:tags":[
        "builder"
    ],
    "wof:name":"Michael P Lee",
    "wof:placetype":"venue"
},
  "geometry": {"coordinates":[-1.1725180149,52.7476768494],"type":"Point"}
}