{
  "type": "Feature",
  "properties": {
    "addr:full":"Chesterton Road South Shields Tyne and Wear NE34 9SP",
    "addr:postcode":"ne34 9sp",
    "addr:street":"Chesterton Road",
    "iso:country":"GB",
    "sg:address":"Chesterton Road",
    "sg:city":"South Shields",
    "sg:classifiers":[
        {
            "category":"Education",
            "subcategory":"School",
            "type":"Public Place"
        },
        {
            "category":"Government",
            "subcategory":"Office",
            "type":"Public Place"
        }
    ],
    "sg:phone":"+44 191 536 2186",
    "sg:postcode":"NE34 9SP",
    "sg:province":"Tyne and Wear",
    "sg:tags":[
        "local",
        "authority"
    ],
    "wof:name":"Biddick Hall Junior Mixed School",
    "wof:placetype":"venue"
},
  "geometry": {"coordinates":[-1.4449490309,54.9651260376],"type":"Point"}
}