{
  "type": "Feature",
  "properties": {
    "addr:full":"50 High St, Erdington Birmingham West Midlands B23 6RH",
    "addr:housenumber":"50",
    "addr:postcode":"b23 6rh",
    "addr:street":"High St",
    "iso:country":"GB",
    "sg:address":"50 High St, Erdington",
    "sg:city":"Birmingham",
    "sg:classifiers":[
        {
            "category":"Fast Food",
            "type":"Food & Drink"
        }
    ],
    "sg:postcode":"B23 6RH",
    "sg:province":"West Midlands",
    "sg:tags":[
        "away",
        "take"
    ],
    "wof:name":"Homer,David,",
    "wof:placetype":"venue"
},
  "geometry": {"coordinates":[-1.836914,52.526176],"type":"Point"}
}