{
  "type": "Feature",
  "properties": {
    "iso:country":"GB",
    "sg:address":"10 Chapel Street",
    "sg:city":"Birmingham",
    "sg:classifiers":[
        {
            "category":"Manufacturing",
            "subcategory":"Tools & Machinery",
            "type":"Manufacturing & Wholesale Goods"
        }
    ],
    "sg:postcode":"B21 0PA",
    "sg:province":"West Midlands",
    "sg:tags":[
        "design",
        "maker"
    ],
    "wof:name":"A & I Brown Taylor",
    "wof:placetype":"venue"
},
  "geometry": {"coordinates":[-1.949389,52.50222],"type":"Point"}
}