{
  "type": "Feature",
  "properties": {
    "iso:country":"GB",
    "sg:address":"21 Riverview Dr",
    "sg:city":"Glasgow",
    "sg:classifiers":[
        {
            "category":"Building & Trades",
            "subcategory":"Plumbing",
            "type":"Services"
        }
    ],
    "sg:phone":"+44 141 429 5047",
    "sg:postcode":"G40 2PE",
    "sg:province":"Glasgow City",
    "sg:tags":[
        "central",
        "heating"
    ],
    "wof:name":"J M K Domestic Heating Services",
    "wof:placetype":"venue"
},
  "geometry": {"coordinates":[-4.22302,55.855061],"type":"Point"}
}