{
  "type": "Feature",
  "properties": {
    "addr:full":"Southbank, Crockhurst Hill Worthing West Sussex BN13 3EE",
    "addr:postcode":"bn13 3ee",
    "addr:street":"Hill",
    "iso:country":"GB",
    "sg:address":"Southbank, Crockhurst Hill",
    "sg:city":"Worthing",
    "sg:classifiers":[
        {
            "category":"Manufacturing",
            "subcategory":"Signs",
            "type":"Manufacturing & Wholesale Goods"
        }
    ],
    "sg:phone":"+44 1903 264656",
    "sg:postcode":"BN13 3EE",
    "sg:province":"West Sussex",
    "sg:tags":[
        "writer"
    ],
    "wof:name":"Global Graphics",
    "wof:placetype":"venue"
},
  "geometry": {"coordinates":[-0.3974100053,50.8382797241],"type":"Point"}
}