{
  "type": "Feature",
  "properties": {
    "addr:full":"6 Brodick Road Kirkcaldy Fife KY2 6EY",
    "addr:housenumber":"6",
    "addr:postcode":"ky2 6ey",
    "addr:street":"Brodick Road",
    "iso:country":"GB",
    "sg:address":"6 Brodick Road",
    "sg:city":"Kirkcaldy",
    "sg:classifiers":[
        {
            "category":"Shopping",
            "subcategory":"Department Store",
            "type":"Retail Goods"
        }
    ],
    "sg:phone":"+44 1592 269884",
    "sg:postcode":"KY2 6EY",
    "sg:province":"Fife",
    "wof:name":"Mubarik Ali",
    "wof:placetype":"venue"
},
  "geometry": {"coordinates":[-3.18447,56.125687],"type":"Point"}
}