{
  "type": "Feature",
  "properties": {
    "addr:full":"77 Birch Hill, Fox Mills Est, Tonedale Wellington Devon TA21 0AW",
    "addr:housenumber":"77",
    "addr:postcode":"ta21 0aw",
    "addr:street":"Birch Hill Fox Mills Est",
    "iso:country":"GB",
    "sg:address":"77 Birch Hill, Fox Mills Est, Tonedale",
    "sg:city":"Wellington",
    "sg:classifiers":[
        {
            "category":"Autos & Motor Vehicles",
            "subcategory":"Auto Supplies",
            "type":"Retail Goods"
        }
    ],
    "sg:postcode":"TA21 0AW",
    "sg:province":"Devon",
    "sg:tags":[
        "tyre"
    ],
    "wof:name":"Reynolds,Michael,",
    "wof:placetype":"venue"
},
  "geometry": {"coordinates":[-3.244552,50.987171],"type":"Point"}
}