{
  "type": "Feature",
  "properties": {
    "addr:full":"120 Northumberland Street Norwich Norfolk NR2 4EH",
    "addr:housenumber":"120",
    "addr:postcode":"nr2 4eh",
    "addr:street":"Northumberland Street",
    "iso:country":"GB",
    "sg:address":"120 Northumberland Street",
    "sg:city":"Norwich",
    "sg:classifiers":[
        {
            "category":"Manufacturing",
            "subcategory":"Metals",
            "type":"Manufacturing & Wholesale Goods"
        },
        {
            "category":"Wholesale",
            "subcategory":"Scrap",
            "type":"Manufacturing & Wholesale Goods"
        }
    ],
    "sg:phone":"+44 1603 620694",
    "sg:postcode":"NR2 4EH",
    "sg:province":"Norfolk",
    "sg:tags":[
        "car",
        "breaker",
        "dismantlers"
    ],
    "wof:name":"C W Cuff",
    "wof:placetype":"venue"
},
  "geometry": {"coordinates":[1.2729279995,52.6373786926],"type":"Point"}
}