{
  "type": "Feature",
  "properties": {
    "addr:full":"1 Park Dr Ascot Berkshire SL5 0BB",
    "addr:housenumber":"1",
    "addr:postcode":"sl5 0bb",
    "addr:street":"Park Dr",
    "iso:country":"GB",
    "sg:address":"1 Park Dr",
    "sg:city":"Ascot",
    "sg:classifiers":[
        {
            "category":"Shopping",
            "subcategory":"Clothing, Apparel, & Fashions",
            "type":"Retail Goods"
        }
    ],
    "sg:postcode":"SL5 0BB",
    "sg:province":"Berkshire",
    "sg:tags":[
        "shop",
        "dress",
        "fancy"
    ],
    "wof:name":"Needful Things",
    "wof:placetype":"venue"
},
  "geometry": {"coordinates":[-0.641288,51.3988],"type":"Point"}
}