{
  "type": "Feature",
  "properties": {
    "iso:country":"GB",
    "sg:address":"Waterloo Street",
    "sg:city":"Bolton",
    "sg:classifiers":[
        {
            "category":"Shopping",
            "subcategory":"Beauty & Cosmetics",
            "type":"Retail Goods"
        }
    ],
    "sg:phone":"+44 1204 386511",
    "sg:postcode":"BL1 8HU",
    "sg:province":"Lancashire",
    "sg:tags":[
        "equipment",
        "hairdressing",
        "hairdresser",
        "supply"
    ],
    "wof:name":"Alan Howard",
    "wof:placetype":"venue"
},
  "geometry": {"coordinates":[-2.429064,53.588192],"type":"Point"}
}