{
  "type": "Feature",
  "properties": {
    "addr:full":"17 Grove Rd Chichester West Sussex PO20 0AS",
    "addr:housenumber":"17",
    "addr:postcode":"po20 0as",
    "addr:street":"Grove Rd",
    "iso:country":"GB",
    "sg:address":"17 Grove Rd",
    "sg:city":"Chichester",
    "sg:classifiers":[
        {
            "category":"Professional",
            "subcategory":"Engineering",
            "type":"Services"
        }
    ],
    "sg:phone":"+44 1243 602185",
    "sg:postcode":"PO20 0AS",
    "sg:province":"West Sussex",
    "sg:tags":[
        "contractor",
        "electrical",
        "engineer"
    ],
    "wof:name":"J & D Electrical Selsey",
    "wof:placetype":"venue"
},
  "geometry": {"coordinates":[-0.788263,50.729012],"type":"Point"}
}