{
  "type": "Feature",
  "properties": {
    "addr:full":"70 Hunt Court, Gallery Gardens Northolt Greater London UB5 5PB",
    "addr:housenumber":"70",
    "addr:postcode":"ub5 5pb",
    "addr:street":"Hunt Court;Gardens",
    "iso:country":"GB",
    "sg:address":"70 Hunt Court, Gallery Gardens",
    "sg:city":"Northolt",
    "sg:classifiers":[
        {
            "category":"Building & Trades",
            "subcategory":"Construction",
            "type":"Services"
        }
    ],
    "sg:phone":"+44 20 8841 7718",
    "sg:postcode":"UB5 5PB",
    "sg:province":"Greater London",
    "sg:tags":[
        "decorator",
        "painter"
    ],
    "wof:name":"Mark Bevan",
    "wof:placetype":"venue"
},
  "geometry": {"coordinates":[-0.3744400144,51.5441055298],"type":"Point"}
}