{
  "type": "Feature",
  "properties": {
    "iso:country":"GB",
    "sg:address":"18 River Street",
    "sg:city":"Truro",
    "sg:classifiers":[
        {
            "category":"Shopping",
            "subcategory":"Baby Store",
            "type":"Retail Goods"
        }
    ],
    "sg:phone":"+44 1872 263656",
    "sg:postcode":"TR1 2SQ",
    "sg:province":"Cornwall",
    "sg:tags":[
        "babywear",
        "childrens"
    ],
    "wof:name":"Rainbow's End",
    "wof:placetype":"venue"
},
  "geometry": {"coordinates":[-5.054929,50.26339],"type":"Point"}
}