{
  "type": "Feature",
  "properties": {
    "addr:full":"The Docks Fowey Cornwall PL23 1DH",
    "addr:postcode":"pl23 1dh",
    "iso:country":"GB",
    "sg:address":"The Docks",
    "sg:city":"Fowey",
    "sg:classifiers":[
        {
            "category":"Organizations",
            "subcategory":"Non-profit Organization",
            "type":"Services"
        }
    ],
    "sg:phone":"+44 1726 833505",
    "sg:postcode":"PL23 1DH",
    "sg:province":"Cornwall",
    "sg:tags":[
        "organisation",
        "voluntary",
        "charity"
    ],
    "wof:name":"Missions To Seamen",
    "wof:placetype":"venue"
},
  "geometry": {"coordinates":[-4.639648,50.336273],"type":"Point"}
}