{
  "type": "Feature",
  "properties": {
    "addr:full":"1 Hill View, Bollington Macclesfield Cheshire SK10 5DU",
    "addr:housenumber":"1",
    "addr:postcode":"sk10 5du",
    "addr:street":"Hill View",
    "iso:country":"GB",
    "sg:address":"1 Hill View, Bollington",
    "sg:city":"Macclesfield",
    "sg:classifiers":[
        {
            "category":"Professional",
            "type":"Services"
        }
    ],
    "sg:phone":"+44 1625 573540",
    "sg:postcode":"SK10 5DU",
    "sg:province":"Cheshire",
    "sg:tags":[
        "writer"
    ],
    "wof:name":"Chris Ward Associates",
    "wof:placetype":"venue"
},
  "geometry": {"coordinates":[-2.110369,53.293388],"type":"Point"}
}