{
  "type": "Feature",
  "properties": {
    "addr:full":"58 Britwell Road, Burnham Slough Berkshire SL1 8DH",
    "addr:housenumber":"58",
    "addr:postcode":"sl1 8dh",
    "addr:street":"Britwell Road",
    "iso:country":"GB",
    "sg:address":"58 Britwell Road, Burnham",
    "sg:city":"Slough",
    "sg:classifiers":[
        {
            "category":"Building & Trades",
            "subcategory":"Construction",
            "type":"Services"
        }
    ],
    "sg:phone":"+44 1628 663438",
    "sg:postcode":"SL1 8DH",
    "sg:province":"Berkshire",
    "sg:tags":[
        "builder"
    ],
    "wof:name":"D L Chamberlain",
    "wof:placetype":"venue"
},
  "geometry": {"coordinates":[-0.648063004,51.5361862183],"type":"Point"}
}