{
  "type": "Feature",
  "properties": {
    "addr:full":"28-29 Great Western Arcade Birmingham West Midlands B2 5HU",
    "addr:housenumber":"28-29",
    "addr:postcode":"5hu",
    "addr:street":"Great Western Arcade",
    "iso:country":"GB",
    "sg:address":"28-29 Great Western Arcade",
    "sg:city":"Birmingham",
    "sg:classifiers":[
        {
            "category":"Shopping",
            "subcategory":"Pharmacy",
            "type":"Retail Goods"
        }
    ],
    "sg:phone":"+44 121 233 3538",
    "sg:postcode":"B2 5HU",
    "sg:province":"West Midlands",
    "sg:tags":[
        "pharmacist",
        "chemist"
    ],
    "wof:name":"Boots the Chemists",
    "wof:placetype":"venue"
},
  "geometry": {"coordinates":[-1.8970799446,52.4818305969],"type":"Point"}
}