{
  "type": "Feature",
  "properties": {
    "addr:full":"6 Queens Promenade Blackpool Lancashire FY2 9SQ",
    "addr:housenumber":"6",
    "addr:postcode":"fy2 9sq",
    "addr:street":"Queens Promenade",
    "iso:country":"GB",
    "sg:address":"6 Queens Promenade",
    "sg:city":"Blackpool",
    "sg:classifiers":[
        {
            "category":"Travel",
            "subcategory":"Hotels & Motels",
            "type":"Entertainment"
        },
        {
            "category":"Bars & Pubs",
            "subcategory":"Hookah Bar",
            "type":"Food & Drink"
        }
    ],
    "sg:phone":"+44 1253 351244",
    "sg:postcode":"FY2 9SQ",
    "sg:province":"Lancashire",
    "sg:tags":[
        "house",
        "self",
        "holiday",
        "guest",
        "catering"
    ],
    "wof:name":"Berkeley Holiday Flats",
    "wof:placetype":"venue"
},
  "geometry": {"coordinates":[-3.054674,53.834663],"type":"Point"}
}