{
  "type": "Feature",
  "properties": {
    "iso:country":"GB",
    "sg:address":"Southbourne, London Road",
    "sg:city":"Salisbury",
    "sg:classifiers":[
        {
            "category":"Utilities",
            "subcategory":"Refuse",
            "type":"Services"
        }
    ],
    "sg:phone":"+44 1722 320544",
    "sg:postcode":"SP1 3YU",
    "sg:province":"Wiltshire",
    "sg:tags":[
        "skip",
        "hire"
    ],
    "wof:name":"C B Skips",
    "wof:placetype":"venue"
},
  "geometry": {"coordinates":[-1.7719299793,51.087638855],"type":"Point"}
}