{
  "type": "Feature",
  "properties": {
    "addr:full":"20 Market Way Poplar Greater London E14 6AH",
    "addr:housenumber":"20",
    "addr:postcode":"e14 6ah",
    "addr:street":"Market Way",
    "iso:country":"GB",
    "sg:address":"20 Market Way",
    "sg:city":"Poplar",
    "sg:classifiers":[
        {
            "category":"Shopping",
            "subcategory":"Clothing, Apparel, & Fashions",
            "type":"Retail Goods"
        }
    ],
    "sg:phone":"+44 20 7538 0455",
    "sg:postcode":"E14 6AH",
    "sg:province":"Greater London",
    "sg:tags":[
        "menswear"
    ],
    "wof:name":"Reaction",
    "wof:placetype":"venue"
},
  "geometry": {"coordinates":[-0.0150410002,51.5130119324],"type":"Point"}
}