{
  "type": "Feature",
  "properties": {
    "iso:country":"GB",
    "sg:address":"Old Norwich Road",
    "sg:city":"Ipswich",
    "sg:classifiers":[
        {
            "category":"Bars & Pubs",
            "type":"Food & Drink"
        }
    ],
    "sg:postcode":"IP1 6LE",
    "sg:province":"Suffolk",
    "sg:tags":[
        "pubs",
        "inn"
    ],
    "wof:name":"G R S Inns",
    "wof:placetype":"venue"
},
  "geometry": {"coordinates":[1.12309,52.08564],"type":"Point"}
}