{
  "type": "Feature",
  "properties": {
    "iso:country":"GB",
    "sg:address":"121 Baginton Rd",
    "sg:city":"Coventry",
    "sg:classifiers":[
        {
            "category":"Building & Trades",
            "subcategory":"Cleaning & Sanitation",
            "type":"Services"
        }
    ],
    "sg:phone":"+44 24 7669 0099",
    "sg:postcode":"CV3 6FY",
    "sg:province":"Warwickshire",
    "sg:tags":[
        "commercial"
    ],
    "wof:name":"Flowline U K Ltd",
    "wof:placetype":"venue"
},
  "geometry": {"coordinates":[-1.5119379759,52.3832130432],"type":"Point"}
}