{
  "type": "Feature",
  "properties": {
    "iso:country":"GB",
    "sg:address":"St Thomas Street",
    "sg:city":"Winchester",
    "sg:classifiers":[
        {
            "category":"Real Estate",
            "subcategory":"Architect",
            "type":"Services"
        }
    ],
    "sg:phone":"+44 1962 842200",
    "sg:postcode":"SO23 9HD",
    "sg:province":"Hampshire",
    "wof:name":"Architecture P L B Ltd.",
    "wof:placetype":"venue"
},
  "geometry": {"coordinates":[-1.315969,51.062614],"type":"Point"}
}