{
  "type": "Feature",
  "properties": {
    "addr:full":"639 Bath Road Bristol City of Bristol BS4 3LF",
    "addr:housenumber":"639",
    "addr:postcode":"bs4 3lf",
    "addr:street":"Bath Road",
    "iso:country":"GB",
    "sg:address":"639 Bath Road",
    "sg:city":"Bristol",
    "sg:classifiers":[
        {
            "category":"Government",
            "subcategory":"Post Office",
            "type":"Public Place"
        }
    ],
    "sg:postcode":"BS4 3LF",
    "sg:province":"City of Bristol",
    "wof:name":"Kensington Hill Sub Post Office",
    "wof:placetype":"venue"
},
  "geometry": {"coordinates":[-2.553372,51.435829],"type":"Point"}
}