{
  "type": "Feature",
  "properties": {
    "addr:full":"14 Quarry Wood Industrial Estate Aylesford Kent ME20 7NA",
    "addr:housenumber":"14;estate",
    "addr:postcode":"me20 7na",
    "addr:street":"Quarry Wood Industrial",
    "iso:country":"GB",
    "sg:address":"14 Quarry Wood Industrial Estate",
    "sg:city":"Aylesford",
    "sg:classifiers":[
        {
            "category":"Autos & Motor Vehicles",
            "subcategory":"Auto Supplies",
            "type":"Retail Goods"
        }
    ],
    "sg:phone":"+44 1622 790993",
    "sg:postcode":"ME20 7NA",
    "sg:province":"Kent",
    "sg:tags":[
        "component"
    ],
    "wof:name":"E D W Realisations Ltd.",
    "wof:placetype":"venue"
},
  "geometry": {"coordinates":[0.4803699851,51.3036308289],"type":"Point"}
}