{
  "type": "Feature",
  "properties": {
    "addr:full":"14 Orchard Way Luton Bedfordshire LU4 9LT",
    "addr:housenumber":"14",
    "addr:postcode":"lu4 9lt",
    "addr:street":"Orchard Way",
    "iso:country":"GB",
    "sg:address":"14 Orchard Way",
    "sg:city":"Luton",
    "sg:classifiers":[
        {
            "category":"Museum",
            "subcategory":"Art Museum",
            "type":"Entertainment"
        }
    ],
    "sg:phone":"+44 1582 562020",
    "sg:postcode":"LU4 9LT",
    "sg:province":"Bedfordshire",
    "sg:tags":[
        "gallery"
    ],
    "wof:name":"Elizabeth Page Gallery",
    "wof:placetype":"venue"
},
  "geometry": {"coordinates":[-0.4689890146,51.9026947021],"type":"Point"}
}