{
  "type": "Feature",
  "properties": {
    "addr:full":"60 Coalway Road, Pennfields Wolverhampton Staffordshire WV3 7LZ",
    "addr:housenumber":"60",
    "addr:postcode":"wv3 7lz",
    "addr:street":"Coalway Road Pennfields",
    "iso:country":"GB",
    "sg:address":"60 Coalway Road, Pennfields",
    "sg:city":"Wolverhampton",
    "sg:classifiers":[
        {
            "category":"Organizations",
            "subcategory":"Membership Organization",
            "type":"Services"
        }
    ],
    "sg:phone":"+44 1902 331550",
    "sg:postcode":"WV3 7LZ",
    "sg:province":"Staffordshire",
    "sg:tags":[
        "club"
    ],
    "wof:name":"Pennfields Bowling & Social Club",
    "wof:placetype":"venue"
},
  "geometry": {"coordinates":[-2.152107,52.569221],"type":"Point"}
}