{
  "type": "Feature",
  "properties": {
    "addr:full":"96 Keighley Road Skipton Lancashire BD23 2RA",
    "addr:housenumber":"96",
    "addr:postcode":"bd23 2ra",
    "addr:street":"Keighley Road",
    "iso:country":"GB",
    "sg:address":"96 Keighley Road",
    "sg:city":"Skipton",
    "sg:classifiers":[
        {
            "category":"Shopping",
            "subcategory":"Computers & Home Electronics",
            "type":"Retail Goods"
        }
    ],
    "sg:phone":"+44 1756 795040",
    "sg:postcode":"BD23 2RA",
    "sg:province":"Lancashire",
    "wof:name":"Alpha Hairstyles",
    "wof:placetype":"venue"
},
  "geometry": {"coordinates":[-2.012504,53.939087],"type":"Point"}
}