{
  "type": "Feature",
  "properties": {
    "iso:country":"GB",
    "sg:address":"Brynteg School, Victoria Road",
    "sg:city":"Wrexham",
    "sg:classifiers":[
        {
            "category":"Shopping",
            "subcategory":"Clothing, Apparel, & Fashions",
            "type":"Retail Goods"
        }
    ],
    "sg:postcode":"LL11 6NG",
    "sg:province":"Wrexham",
    "sg:tags":[
        "shop"
    ],
    "wof:name":"Family Fashions",
    "wof:placetype":"venue"
},
  "geometry": {"coordinates":[-3.0365989208,53.0644645691],"type":"Point"}
}