{
  "type": "Feature",
  "properties": {
    "iso:country":"GB",
    "sg:address":"1 North Close, Shornecliffe Industrial",
    "sg:city":"Folkestone",
    "sg:classifiers":[
        {
            "category":"Shopping",
            "subcategory":"Discount & Variety Stores",
            "type":"Retail Goods"
        }
    ],
    "sg:phone":"+44 1303 226611",
    "sg:postcode":"CT20 3UH",
    "sg:province":"Kent",
    "sg:tags":[
        "cleaning",
        "supply"
    ],
    "wof:name":"Westbourne Cleaning Services & Supplies",
    "wof:placetype":"venue"
},
  "geometry": {"coordinates":[1.144819,51.07386],"type":"Point"}
}