{
  "type": "Feature",
  "properties": {
    "addr:full":"Cherry Tree Farm, Ten Mile Bank Downham Market Cambridgeshire PE38 0EU",
    "addr:postcode":"pe38 0eu",
    "addr:street":"Ten;Downham Market",
    "iso:country":"GB",
    "sg:address":"Cherry Tree Farm, Ten Mile Bank",
    "sg:city":"Downham Market",
    "sg:classifiers":[
        {
            "category":"Farming",
            "subcategory":"Livestock Farm",
            "type":"Manufacturing & Wholesale Goods"
        }
    ],
    "sg:postcode":"PE38 0EU",
    "sg:province":"Cambridgeshire",
    "sg:tags":[
        "others"
    ],
    "wof:name":"George William Reed",
    "wof:placetype":"venue"
},
  "geometry": {"coordinates":[0.3590910137,52.5357208252],"type":"Point"}
}