{
  "type": "Feature",
  "properties": {
    "addr:full":"Westbourne Road Huddersfield West Yorkshire HD1 4LE",
    "addr:postcode":"hd1 4le",
    "addr:street":"Westbourne Road",
    "iso:country":"GB",
    "sg:address":"Westbourne Road",
    "sg:city":"Huddersfield",
    "sg:classifiers":[
        {
            "category":"Autos & Motor Vehicles",
            "subcategory":"Fuel & Gas Station",
            "type":"Retail Goods"
        }
    ],
    "sg:phone":"+44 1484 557030",
    "sg:postcode":"HD1 4LE",
    "sg:province":"West Yorkshire",
    "sg:tags":[
        "hr",
        "filling",
        "petrol"
    ],
    "wof:name":"Shell Huddersfield",
    "wof:placetype":"venue"
},
  "geometry": {"coordinates":[-1.803624,53.651642],"type":"Point"}
}