{
  "type": "Feature",
  "properties": {
    "addr:full":"Warren Farm, Savernake Marlborough Berkshire SN8 3BQ",
    "addr:postcode":"sn8 3bq",
    "addr:street":"Warren",
    "iso:country":"GB",
    "sg:address":"Warren Farm, Savernake",
    "sg:city":"Marlborough",
    "sg:classifiers":[
        {
            "category":"Farming",
            "subcategory":"Livestock Farm",
            "type":"Manufacturing & Wholesale Goods"
        }
    ],
    "sg:phone":"+44 1672 870339",
    "sg:postcode":"SN8 3BQ",
    "sg:province":"Berkshire",
    "sg:tags":[
        "others"
    ],
    "wof:name":"Benash Warren Ltd.",
    "wof:placetype":"venue"
},
  "geometry": {"coordinates":[-1.664574,51.398964],"type":"Point"}
}