{
  "type": "Feature",
  "properties": {
    "addr:full":"7 Hornby Street Heywood Lancashire OL10 1AA",
    "addr:housenumber":"7",
    "addr:postcode":"ol10 1aa",
    "addr:street":"Hornby Street",
    "iso:country":"GB",
    "sg:address":"7 Hornby Street",
    "sg:city":"Heywood",
    "sg:classifiers":[
        {
            "category":"Professional",
            "subcategory":"Accounting & Tax Preparation",
            "type":"Services"
        },
        {
            "category":"Shopping",
            "subcategory":"Clothing, Apparel, & Fashions",
            "type":"Retail Goods"
        }
    ],
    "sg:postcode":"OL10 1AA",
    "sg:province":"Lancashire",
    "sg:tags":[
        "accountant",
        "babywear",
        "child"
    ],
    "wof:name":"DAMANI CHILDRENSWEAR LTD",
    "wof:placetype":"venue"
},
  "geometry": {"coordinates":[-2.2166209221,53.5923805237],"type":"Point"}
}