{
  "type": "Feature",
  "properties": {
    "iso:country":"GB",
    "sg:address":"12-12a Cheltenham Crescent",
    "sg:city":"Harrogate",
    "sg:classifiers":[
        {
            "category":"Shopping",
            "subcategory":"Books",
            "type":"Retail Goods"
        }
    ],
    "sg:phone":"+44 1423 561867",
    "sg:postcode":"HG1 1DH",
    "sg:province":"North Yorkshire",
    "sg:tags":[
        "second-hand"
    ],
    "wof:name":"Richard Axe Rare & Out of Print Books",
    "wof:placetype":"venue"
},
  "geometry": {"coordinates":[-1.5417619944,53.9947357178],"type":"Point"}
}