{
  "type": "Feature",
  "properties": {
    "iso:country":"GB",
    "sg:address":"Standby Studios, Wincelow Hall Road, Hempstead",
    "sg:city":"Saffron Walden",
    "sg:classifiers":[
        {
            "category":"Communications",
            "type":"Services"
        }
    ],
    "sg:phone":"+44 1799 599350",
    "sg:postcode":"CB10 2PJ",
    "sg:province":"Cambridgeshire",
    "sg:tags":[
        "broadcasting",
        "audio-visual"
    ],
    "wof:name":"Channel 6 Productions",
    "wof:placetype":"venue"
},
  "geometry": {"coordinates":[0.3792099953,52.0168113708],"type":"Point"}
}