{
  "type": "Feature",
  "properties": {
    "addr:full":"15 Albert Square Widnes Cheshire WA8 6JW",
    "addr:housenumber":"15",
    "addr:postcode":"wa8 6jw",
    "addr:street":"Albert Square",
    "iso:country":"GB",
    "sg:address":"15 Albert Square",
    "sg:city":"Widnes",
    "sg:classifiers":[
        {
            "category":"Shopping",
            "subcategory":"Clothing, Apparel, & Fashions",
            "type":"Retail Goods"
        }
    ],
    "sg:phone":"+44 151 420 2325",
    "sg:postcode":"WA8 6JW",
    "sg:province":"Cheshire",
    "sg:tags":[
        "shop"
    ],
    "wof:name":"Girls Choice",
    "wof:placetype":"venue"
},
  "geometry": {"coordinates":[-2.725469,53.369099],"type":"Point"}
}