{
  "type": "Feature",
  "properties": {
    "iso:country":"GB",
    "sg:address":"The Church Of Unity, Rye Crescent",
    "sg:city":"Orpington",
    "sg:classifiers":[
        {
            "category":"Education",
            "subcategory":"Preschool",
            "type":"Public Place"
        }
    ],
    "sg:phone":"+44 1689 871371",
    "sg:postcode":"BR5 4NH",
    "sg:province":"Kent",
    "sg:tags":[
        "pre-school",
        "playgroups"
    ],
    "wof:name":"Avalon Playgroup",
    "wof:placetype":"venue"
},
  "geometry": {"coordinates":[0.1207000017,51.3754501343],"type":"Point"}
}