{
  "type": "Feature",
  "properties": {
    "addr:full":"4 Block C, Cowdray Centre Colchester Essex CO1 1BN",
    "addr:housenumber":"4;c",
    "addr:postcode":"co1 1bn",
    "addr:street":"Block;Cowdray Centre Colchester",
    "iso:country":"GB",
    "sg:address":"4 Block C, Cowdray Centre",
    "sg:city":"Colchester",
    "sg:classifiers":[
        {
            "category":"Manufacturing",
            "subcategory":"Chemicals & Compounds",
            "type":"Manufacturing & Wholesale Goods"
        },
        {
            "category":"Banks & Credit Unions",
            "subcategory":"Investment Brokerage",
            "type":"Services"
        }
    ],
    "sg:phone":"+44 1206 760500",
    "sg:postcode":"CO1 1BN",
    "sg:province":"Essex",
    "sg:tags":[
        "abrasive",
        "product",
        "production",
        "-",
        "cleaning"
    ],
    "wof:name":"Alpha Finishing Supplies Ltd",
    "wof:placetype":"venue"
},
  "geometry": {"coordinates":[0.9038569927,51.898311615],"type":"Point"}
}