{
  "type": "Feature",
  "properties": {
    "iso:country":"GB",
    "sg:address":"Sutton Cheney Wharf, Wharf Lane, Sutton Cheney",
    "sg:city":"Nuneaton",
    "sg:classifiers":[
        {
            "category":"Recreation",
            "subcategory":"Sailing Club",
            "type":"Entertainment"
        }
    ],
    "sg:phone":"+44 1455 213838",
    "sg:postcode":"CV13 0AL",
    "sg:province":"Leicestershire",
    "wof:name":"The Ashby Trip",
    "wof:placetype":"venue"
},
  "geometry": {"coordinates":[-1.385714,52.599773],"type":"Point"}
}