{
  "type": "Feature",
  "properties": {
    "addr:full":"Unit 1 8 Pritchards Rd Bethnal Green Greater London E2 9AP",
    "addr:housenumber":"unit;8",
    "addr:postcode":"e2 9ap",
    "addr:street":"Pritchards Rd",
    "iso:country":"GB",
    "sg:address":"Unit 1 8 Pritchards Rd",
    "sg:city":"Bethnal Green",
    "sg:classifiers":[
        {
            "category":"Building & Trades",
            "subcategory":"Cleaning & Sanitation",
            "type":"Services"
        }
    ],
    "sg:phone":"+44 20 7739 4461",
    "sg:postcode":"E2 9AP",
    "sg:province":"Greater London",
    "sg:tags":[
        "blast"
    ],
    "wof:name":"London Sand Blast Co Ltd",
    "wof:placetype":"venue"
},
  "geometry": {"coordinates":[-0.0614320002,51.5324668884],"type":"Point"}
}