{
  "type": "Feature",
  "properties": {
    "addr:full":"Unit 4, Tregoniggie Industrial Estate Falmouth Cornwall TR11 4SN",
    "addr:housenumber":"unit 4;estate",
    "addr:postcode":"tr11 4sn",
    "addr:street":"Tregoniggie Industrial",
    "iso:country":"GB",
    "sg:address":"Unit 4, Tregoniggie Industrial Estate",
    "sg:city":"Falmouth",
    "sg:classifiers":[
        {
            "category":"Wholesale",
            "subcategory":"Metals & Minerals",
            "type":"Manufacturing & Wholesale Goods"
        }
    ],
    "sg:phone":"+44 1326 378811",
    "sg:postcode":"TR11 4SN",
    "sg:province":"Cornwall",
    "sg:tags":[
        "non-ferrous"
    ],
    "wof:name":"A B S Metals Ltd.",
    "wof:placetype":"venue"
},
  "geometry": {"coordinates":[-5.0800328255,50.1522064209],"type":"Point"}
}