{
  "type": "Feature",
  "properties": {
    "addr:full":"4 Middleton Road New Malden Surrey KT3 3ES",
    "addr:housenumber":"4",
    "addr:postcode":"kt3 3es",
    "addr:street":"Middleton Road",
    "iso:country":"GB",
    "sg:address":"4 Middleton Road",
    "sg:city":"New Malden",
    "sg:classifiers":[
        {
            "category":"Building & Trades",
            "subcategory":"Construction",
            "type":"Services"
        }
    ],
    "sg:phone":"+44 20 8949 7567",
    "sg:postcode":"KT3 3ES",
    "sg:province":"Surrey",
    "sg:tags":[
        "builder"
    ],
    "wof:name":"Day & Co",
    "wof:placetype":"venue"
},
  "geometry": {"coordinates":[-0.272864,51.407265],"type":"Point"}
}