{
  "type": "Feature",
  "properties": {
    "iso:country":"GB",
    "sg:address":"Old Post Office Cottage",
    "sg:city":"Chichester",
    "sg:classifiers":[
        {
            "category":"Shopping",
            "subcategory":"Shoes",
            "type":"Retail Goods"
        }
    ],
    "sg:phone":"+44 1243 535305",
    "sg:postcode":"PO18 9HU",
    "sg:province":"West Sussex",
    "sg:tags":[
        "shop"
    ],
    "wof:name":"Ideal Footwear",
    "wof:placetype":"venue"
},
  "geometry": {"coordinates":[-0.81656,50.922611],"type":"Point"}
}