{
  "type": "Feature",
  "properties": {
    "addr:full":"660 Balmore Rd Glasgow Glasgow City G22 6QS",
    "addr:housenumber":"660",
    "addr:postcode":"g22 6qs",
    "addr:street":"Balmore Rd",
    "iso:country":"GB",
    "sg:address":"660 Balmore Rd",
    "sg:city":"Glasgow",
    "sg:classifiers":[
        {
            "category":"Farming",
            "subcategory":"Nursery",
            "type":"Manufacturing & Wholesale Goods"
        }
    ],
    "sg:postcode":"G22 6QS",
    "sg:province":"Glasgow City",
    "sg:tags":[
        "creche"
    ],
    "wof:name":"Balmore Nursery School",
    "wof:placetype":"venue"
},
  "geometry": {"coordinates":[-4.2629699707,55.8957252502],"type":"Point"}
}