{
  "type": "Feature",
  "properties": {
    "iso:country":"GB",
    "sg:address":"122 Mill Lane",
    "sg:city":"Liverpool",
    "sg:classifiers":[
        {
            "category":"Arts & Performance",
            "subcategory":"Music",
            "type":"Entertainment"
        }
    ],
    "sg:phone":"+44 151 220 4609",
    "sg:postcode":"L13 4AH",
    "sg:province":"Merseyside",
    "sg:tags":[
        "mobile",
        "disco"
    ],
    "wof:name":"B & S Sound & Lighting",
    "wof:placetype":"venue"
},
  "geometry": {"coordinates":[-2.914193,53.406948],"type":"Point"}
}