{
  "type": "Feature",
  "properties": {
    "iso:country":"GB",
    "sg:address":"25a Lions Rd",
    "sg:city":"Croydon",
    "sg:classifiers":[
        {
            "category":"Building & Trades",
            "subcategory":"Construction",
            "type":"Services"
        }
    ],
    "sg:phone":"+44 181 665 5511",
    "sg:postcode":"CR0 2HF",
    "sg:province":"Surrey",
    "sg:tags":[
        "builder"
    ],
    "wof:name":"Blackbow Slingsby Ltd",
    "wof:placetype":"venue"
},
  "geometry": {"coordinates":[-0.1005489975,51.3915481567],"type":"Point"}
}