{
  "type": "Feature",
  "properties": {
    "addr:full":"5 School Road, Tilehurst Reading Berkshire RG31 5AR",
    "addr:housenumber":"5",
    "addr:postcode":"rg31 5ar",
    "addr:street":"School Road",
    "iso:country":"GB",
    "sg:address":"5 School Road, Tilehurst",
    "sg:city":"Reading",
    "sg:classifiers":[
        {
            "category":"Real Estate",
            "subcategory":"Real Estate Operator",
            "type":"Services"
        }
    ],
    "sg:phone":"+44 118 941 6111",
    "sg:postcode":"RG31 5AR",
    "sg:province":"Berkshire",
    "sg:tags":[
        "letting",
        "agent"
    ],
    "wof:name":"Turrill Management",
    "wof:placetype":"venue"
},
  "geometry": {"coordinates":[-1.0397449732,51.4584960938],"type":"Point"}
}