{
  "type": "Feature",
  "properties": {
    "iso:country":"GB",
    "sg:address":"Ahed Building",
    "sg:city":"Stockton-on-tees",
    "sg:classifiers":[
        {
            "category":"Professional",
            "subcategory":"Management & Consulting",
            "type":"Services"
        }
    ],
    "sg:phone":"+44 1642 602721",
    "sg:postcode":"TS18 2EX",
    "sg:province":"Durham",
    "sg:tags":[
        "consultant",
        "business"
    ],
    "wof:name":"K T Associates",
    "wof:placetype":"venue"
},
  "geometry": {"coordinates":[-1.274499,54.573956],"type":"Point"}
}