{
  "type": "Feature",
  "properties": {
    "iso:country":"GB",
    "sg:address":"Telegraph Street",
    "sg:city":"Cambridge",
    "sg:classifiers":[
        {
            "category":"Home & Garden",
            "subcategory":"Building Materials",
            "type":"Retail Goods"
        }
    ],
    "sg:phone":"+44 1954 230024",
    "sg:postcode":"CB4 8QU",
    "sg:province":"Cambridgeshire",
    "sg:tags":[
        "gate",
        "door",
        "barrier"
    ],
    "wof:name":"Access Control Ltd.",
    "wof:placetype":"venue"
},
  "geometry": {"coordinates":[0.12694,52.287342],"type":"Point"}
}