{
  "type": "Feature",
  "properties": {
    "iso:country":"GB",
    "sg:address":"48 Leeds Road, Oulton",
    "sg:city":"Leeds",
    "sg:classifiers":[
        {
            "category":"Professional",
            "subcategory":"Engineering",
            "type":"Services"
        }
    ],
    "sg:phone":"+44 113 282 7957",
    "sg:postcode":"LS26 8JY",
    "sg:province":"West Yorkshire",
    "sg:tags":[
        "contractor",
        "electrical",
        "engineer"
    ],
    "wof:name":"E I C Ltd.",
    "wof:placetype":"venue"
},
  "geometry": {"coordinates":[-1.456504,53.750004],"type":"Point"}
}