{
  "type": "Feature",
  "properties": {
    "iso:country":"GB",
    "sg:address":"Norwich Union House, 3-5 Eastern Road",
    "sg:city":"Romford",
    "sg:classifiers":[
        {
            "category":"Manufacturing",
            "subcategory":"Tools & Machinery",
            "type":"Manufacturing & Wholesale Goods"
        }
    ],
    "sg:phone":"+44 1708 814646",
    "sg:postcode":"RM1 3JB",
    "sg:province":"Essex",
    "sg:tags":[
        "society",
        "friendly"
    ],
    "wof:name":"The Scottish Life Assurance",
    "wof:placetype":"venue"
},
  "geometry": {"coordinates":[0.18417,51.575481],"type":"Point"}
}