{
  "type": "Feature",
  "properties": {
    "iso:country":"GB",
    "sg:address":"31 Hazelwood",
    "sg:city":"Loughton",
    "sg:classifiers":[
        {
            "category":"Real Estate",
            "subcategory":"Architect",
            "type":"Services"
        }
    ],
    "sg:postcode":"IG10 4ET",
    "sg:province":"Essex",
    "sg:tags":[
        "architectural"
    ],
    "wof:name":"Roding Architectural Services",
    "wof:placetype":"venue"
},
  "geometry": {"coordinates":[0.0476659983,51.6431541443],"type":"Point"}
}