{
  "type": "Feature",
  "properties": {
    "addr:full":"39 Wells Court Rochester Kent ME2 2PW",
    "addr:housenumber":"39",
    "addr:postcode":"me2 2pw",
    "addr:street":"Wells Court",
    "iso:country":"GB",
    "sg:address":"39 Wells Court",
    "sg:city":"Rochester",
    "sg:classifiers":[
        {
            "category":"Shopping",
            "subcategory":"News",
            "type":"Retail Goods"
        }
    ],
    "sg:phone":"+44 1634 727548",
    "sg:postcode":"ME2 2PW",
    "sg:province":"Kent",
    "sg:tags":[
        "newsagent"
    ],
    "wof:name":"Grimps Newsagents",
    "wof:placetype":"venue"
},
  "geometry": {"coordinates":[0.468327,51.388184],"type":"Point"}
}