{
  "type": "Feature",
  "properties": {
    "addr:full":"Loch Sunart Acharacle Argyll and Bute PH36 4JH",
    "addr:postcode":"ph36 4jh",
    "addr:street":"Loch;Acharacle",
    "iso:country":"GB",
    "sg:address":"Loch Sunart",
    "sg:city":"Acharacle",
    "sg:classifiers":[
        {
            "category":"Travel",
            "subcategory":"Hotels & Motels",
            "type":"Entertainment"
        }
    ],
    "sg:phone":"+44 1967 431263",
    "sg:postcode":"PH36 4JH",
    "sg:province":"Argyll and Bute",
    "sg:tags":[
        "self",
        "catering"
    ],
    "wof:name":"Glencripesdale House",
    "wof:placetype":"venue"
},
  "geometry": {"coordinates":[-5.802459,56.748371],"type":"Point"}
}