{
  "type": "Feature",
  "properties": {
    "iso:country":"GB",
    "sg:address":"52 Craven Rd",
    "sg:city":"Ealing",
    "sg:classifiers":[
        {
            "category":"Arts & Performance",
            "subcategory":"Music",
            "type":"Entertainment"
        }
    ],
    "sg:phone":"+44 20 8958 9891",
    "sg:postcode":"W5 2UA",
    "sg:province":"Greater London",
    "sg:tags":[
        "mobile",
        "disco"
    ],
    "wof:name":"Ace Discos & Equipmnet Hire",
    "wof:placetype":"venue"
},
  "geometry": {"coordinates":[-0.3107909858,51.5134887695],"type":"Point"}
}