{
  "type": "Feature",
  "properties": {
    "addr:full":"155 Kendal Way Cambridge Cambridgeshire CB4 1LS",
    "addr:housenumber":"155",
    "addr:postcode":"cb4 1ls",
    "addr:street":"Kendal Way",
    "iso:country":"GB",
    "sg:address":"155 Kendal Way",
    "sg:city":"Cambridge",
    "sg:classifiers":[
        {
            "category":"Home & Garden",
            "subcategory":"Household Appliances",
            "type":"Retail Goods"
        }
    ],
    "sg:phone":"+44 1223 423993",
    "sg:postcode":"CB4 1LS",
    "sg:province":"Cambridgeshire",
    "sg:tags":[
        "electrical"
    ],
    "wof:name":"Cambridge & Area Domestic Appliance Repairs",
    "wof:placetype":"venue"
},
  "geometry": {"coordinates":[0.1448639929,52.2238464355],"type":"Point"}
}