{
  "type": "Feature",
  "properties": {
    "iso:country":"GB",
    "sg:address":"66 Belgrave Road, Mutley",
    "sg:city":"Plymouth",
    "sg:classifiers":[
        {
            "category":"Building & Trades",
            "subcategory":"Plumbing",
            "type":"Services"
        }
    ],
    "sg:postcode":"PL4 7DR",
    "sg:province":"Devon",
    "sg:tags":[
        "heating"
    ],
    "wof:name":"Arthur H Knight",
    "wof:placetype":"venue"
},
  "geometry": {"coordinates":[-4.130758,50.383007],"type":"Point"}
}