{
  "type": "Feature",
  "properties": {
    "addr:full":"Studio, 13 Fullerton Square, Rivergate Centre Irvine North Ayrshire KA12 8EH",
    "addr:housenumber":"13",
    "addr:postcode":"ka12 8eh",
    "addr:street":"Fullerton Square;Centre",
    "iso:country":"GB",
    "sg:address":"Studio, 13 Fullerton Square, Rivergate Centre",
    "sg:city":"Irvine",
    "sg:classifiers":[
        {
            "category":"Professional",
            "subcategory":"Art Services",
            "type":"Services"
        }
    ],
    "sg:phone":"+44 1294 276751",
    "sg:postcode":"KA12 8EH",
    "sg:province":"North Ayrshire",
    "sg:tags":[
        "photographer"
    ],
    "wof:name":"Venture Portraits",
    "wof:placetype":"venue"
},
  "geometry": {"coordinates":[-4.668434,55.6035],"type":"Point"}
}