{
  "type": "Feature",
  "properties": {
    "addr:full":"6 York Road Malton North Yorkshire YO17 6AX",
    "addr:housenumber":"6",
    "addr:postcode":"yo17 6ax",
    "addr:street":"York Road",
    "iso:country":"GB",
    "sg:address":"6 York Road",
    "sg:city":"Malton",
    "sg:classifiers":[
        {
            "category":"Health Services",
            "subcategory":"Nursing And Care Facility",
            "type":"Services"
        },
        {
            "category":"Social Services",
            "subcategory":"Retirement Home",
            "type":"Services"
        }
    ],
    "sg:phone":"+44 1653 692981",
    "sg:postcode":"YO17 6AX",
    "sg:province":"North Yorkshire",
    "sg:tags":[
        "residential"
    ],
    "wof:name":"Autumn Lodge",
    "wof:placetype":"venue"
},
  "geometry": {"coordinates":[-0.805504024,54.1329345703],"type":"Point"}
}