{
  "type": "Feature",
  "properties": {
    "addr:full":"Units 1 & 3 Green Park, Coedcae Lane Indust Est Pontyclun Bridgend CF72 9GP",
    "addr:housenumber":"units 1 & 3",
    "addr:postcode":"cf72 9gp",
    "addr:street":"Green Park Coedcae Lane",
    "iso:country":"GB",
    "sg:address":"Units 1 & 3 Green Park, Coedcae Lane Indust Est",
    "sg:city":"Pontyclun",
    "sg:classifiers":[
        {
            "category":"Home & Garden",
            "subcategory":"Carpets & Floor Coverings",
            "type":"Retail Goods"
        }
    ],
    "sg:phone":"+44 1443 224417",
    "sg:postcode":"CF72 9GP",
    "sg:province":"Bridgend",
    "sg:tags":[
        "cleaner",
        "upholstery"
    ],
    "wof:name":"Rainbow International",
    "wof:placetype":"venue"
},
  "geometry": {"coordinates":[-3.38025,51.535118],"type":"Point"}
}