{
  "type": "Feature",
  "properties": {
    "addr:full":"Membership Secretary, 1 Ashfield Pl, Huby Leeds North Yorkshire LS17 0EB",
    "addr:housenumber":"1",
    "addr:postcode":"ls17 0eb",
    "addr:street":"Ashfield Pl",
    "iso:country":"GB",
    "sg:address":"Membership Secretary, 1 Ashfield Pl, Huby",
    "sg:city":"Leeds",
    "sg:classifiers":[
        {
            "category":"Professional",
            "subcategory":"Business Services",
            "type":"Services"
        }
    ],
    "sg:phone":"+44 1423 734861",
    "sg:postcode":"LS17 0EB",
    "sg:province":"North Yorkshire",
    "sg:tags":[
        "trade"
    ],
    "wof:name":"Federation Of Small Businesses",
    "wof:placetype":"venue"
},
  "geometry": {"coordinates":[-1.5816229582,53.9258232117],"type":"Point"}
}