{
  "type": "Feature",
  "properties": {
    "addr:full":"13 Auchingramont Road Hamilton South Lanarkshire ML3 6JP",
    "addr:housenumber":"13",
    "addr:postcode":"ml3 6jp",
    "addr:street":"Auchingramont Road",
    "iso:country":"GB",
    "sg:address":"13 Auchingramont Road",
    "sg:city":"Hamilton",
    "sg:classifiers":[
        {
            "category":"Real Estate",
            "subcategory":"Real Estate Agent",
            "type":"Services"
        }
    ],
    "sg:phone":"+44 1698 286652",
    "sg:postcode":"ML3 6JP",
    "sg:province":"South Lanarkshire",
    "wof:name":"The Rented Property Co",
    "wof:placetype":"venue"
},
  "geometry": {"coordinates":[-4.042596817,55.7765617371],"type":"Point"}
}