{
  "type": "Feature",
  "properties": {
    "iso:country":"GB",
    "sg:address":"74 Whitehill Road",
    "sg:city":"Gravesend",
    "sg:classifiers":[
        {
            "category":"Professional",
            "subcategory":"Detective & Security Services",
            "type":"Services"
        },
        {
            "category":"Building & Trades",
            "subcategory":"Electrical",
            "type":"Services"
        }
    ],
    "sg:phone":"+44 1474 534554",
    "sg:postcode":"DA12 5PH",
    "sg:province":"Kent",
    "sg:tags":[
        "contractor",
        "electrician",
        "locksmith"
    ],
    "wof:name":"Ford Security Supplies",
    "wof:placetype":"venue"
},
  "geometry": {"coordinates":[0.377427,51.428082],"type":"Point"}
}