{
  "type": "Feature",
  "properties": {
    "addr:full":"1 Salop Road Oswestry Shropshire SY11 2NR",
    "addr:housenumber":"1",
    "addr:postcode":"sy11 2nr",
    "addr:street":"Salop Road",
    "iso:country":"GB",
    "sg:address":"1 Salop Road",
    "sg:city":"Oswestry",
    "sg:classifiers":[
        {
            "category":"Travel",
            "subcategory":"Hotels & Motels",
            "type":"Entertainment"
        }
    ],
    "sg:phone":"+44 1691 652093",
    "sg:postcode":"SY11 2NR",
    "sg:province":"Shropshire",
    "wof:name":"The Bear Hotel",
    "wof:placetype":"venue"
},
  "geometry": {"coordinates":[-3.053279,52.859077],"type":"Point"}
}