{
  "type": "Feature",
  "properties": {
    "addr:full":"12 Woodlands Close, Cotebrook Tarporley Cheshire CW6 9DU",
    "addr:housenumber":"12",
    "addr:postcode":"cw6 9du",
    "addr:street":"Woodlands Close",
    "iso:country":"GB",
    "sg:address":"12 Woodlands Close, Cotebrook",
    "sg:city":"Tarporley",
    "sg:classifiers":[
        {
            "category":"Building & Trades",
            "subcategory":"Construction",
            "type":"Services"
        }
    ],
    "sg:phone":"+44 1829 760478",
    "sg:postcode":"CW6 9DU",
    "sg:province":"Cheshire",
    "sg:tags":[
        "builder"
    ],
    "wof:name":"Greenway & Craven",
    "wof:placetype":"venue"
},
  "geometry": {"coordinates":[-2.6399760246,53.1852035522],"type":"Point"}
}