{
  "type": "Feature",
  "properties": {
    "addr:full":"Paragon Bath Bath and North East Somerset BA1 5LX",
    "addr:postcode":"ba1 5lx",
    "addr:street":"Bath",
    "iso:country":"GB",
    "sg:address":"Paragon",
    "sg:city":"Bath",
    "sg:classifiers":[
        {
            "category":"Place Of Worship",
            "type":"Public Place"
        }
    ],
    "sg:phone":"+44 1225 427910",
    "sg:postcode":"BA1 5LX",
    "sg:province":"Bath and North East Somerset",
    "wof:name":"St Swithins C of E Church",
    "wof:placetype":"venue"
},
  "geometry": {"coordinates":[-2.3595020771,51.3887023926],"type":"Point"}
}