{
  "type": "Feature",
  "properties": {
    "iso:country":"GB",
    "sg:address":"Pymore Mills, Pymore",
    "sg:city":"Bridport",
    "sg:classifiers":[
        {
            "category":"Building & Trades",
            "subcategory":"Construction",
            "type":"Services"
        }
    ],
    "sg:phone":"+44 1308 422478",
    "sg:postcode":"DT6 5PJ",
    "sg:province":"Dorset",
    "sg:tags":[
        "builder"
    ],
    "wof:name":"Matthew C Harvey",
    "wof:placetype":"venue"
},
  "geometry": {"coordinates":[-2.748899,50.749905],"type":"Point"}
}