{
  "type": "Feature",
  "properties": {
    "iso:country":"GB",
    "sg:address":"19 Templars Square, Cowley",
    "sg:city":"Oxford",
    "sg:classifiers":[
        {
            "category":"Food & Beverages",
            "subcategory":"Fruits & Vegetables",
            "type":"Retail Goods"
        }
    ],
    "sg:phone":"+44 1865 779107",
    "sg:postcode":"OX4 3UZ",
    "sg:province":"Oxfordshire",
    "sg:tags":[
        "greengrocer"
    ],
    "wof:name":"Stokes Plc",
    "wof:placetype":"venue"
},
  "geometry": {"coordinates":[-1.215386,51.731785],"type":"Point"}
}