{
  "type": "Feature",
  "properties": {
    "addr:full":"Unit 15, The Belvoir Shopping Centre Coalville Leicestershire LE67 3XE",
    "addr:housenumber":"unit 15",
    "addr:postcode":"le67 3xe",
    "addr:street":"The;Shopping",
    "iso:country":"GB",
    "sg:address":"Unit 15, The Belvoir Shopping Centre",
    "sg:city":"Coalville",
    "sg:classifiers":[
        {
            "category":"Home & Garden",
            "subcategory":"Household Appliances",
            "type":"Retail Goods"
        }
    ],
    "sg:phone":"+44 1530 832630",
    "sg:postcode":"LE67 3XE",
    "sg:province":"Leicestershire",
    "sg:tags":[
        "electrical",
        "domestic"
    ],
    "wof:name":"Currys",
    "wof:placetype":"venue"
},
  "geometry": {"coordinates":[-1.3723059893,52.7187843323],"type":"Point"}
}