{
  "type": "Feature",
  "properties": {
    "iso:country":"GB",
    "sg:address":"Ferguson Building, Craibston Estate",
    "sg:city":"Aberdeen",
    "sg:classifiers":[
        {
            "category":"Manufacturing",
            "subcategory":"Petroleum Products",
            "type":"Manufacturing & Wholesale Goods"
        },
        {
            "category":"Building & Trades",
            "subcategory":"Construction",
            "type":"Services"
        }
    ],
    "sg:phone":"+44 1224 710005",
    "sg:postcode":"AB21 9PR",
    "sg:province":"Aberdeen City",
    "sg:tags":[
        "joinery",
        "glazing",
        "double"
    ],
    "wof:name":"Ergon Profiles Ltd.",
    "wof:placetype":"venue"
},
  "geometry": {"coordinates":[-2.19124,57.175678],"type":"Point"}
}