{
  "type": "Feature",
  "properties": {
    "iso:country":"GB",
    "sg:address":"Geddes House, Kirkton North",
    "sg:city":"Livingston",
    "sg:classifiers":[
        {
            "category":"Banks & Credit Unions",
            "subcategory":"Financial Services",
            "type":"Services"
        }
    ],
    "sg:phone":"+44 1506 415144",
    "sg:postcode":"EH54 7AN",
    "sg:province":"West Lothian",
    "sg:tags":[
        "consultant"
    ],
    "wof:name":"Lothian Enterprise",
    "wof:placetype":"venue"
},
  "geometry": {"coordinates":[-3.549849,55.887306],"type":"Point"}
}