{
  "type": "Feature",
  "properties": {
    "iso:country":"GB",
    "sg:address":"133-135 Cockley Hill Lane",
    "sg:city":"Huddersfield",
    "sg:classifiers":[
        {
            "category":"Home & Garden",
            "subcategory":"Garden Supply",
            "type":"Retail Goods"
        },
        {
            "category":"Food & Beverages",
            "subcategory":"Fruits & Vegetables",
            "type":"Retail Goods"
        }
    ],
    "sg:phone":"+44 1484 428401",
    "sg:postcode":"HD5 0PF",
    "sg:province":"West Yorkshire",
    "sg:tags":[
        "greengrocer",
        "nursery",
        "centre"
    ],
    "wof:name":"J & W Gibb & Sons Ltd.",
    "wof:placetype":"venue"
},
  "geometry": {"coordinates":[-1.7151880264,53.6584396362],"type":"Point"}
}