{
  "type": "Feature",
  "properties": {
    "addr:full":"Pool House, Bancrift Road Reigate Surrey RH2 7RP",
    "addr:postcode":"rh2 7rp",
    "addr:street":"Bancrift Road",
    "iso:country":"GB",
    "sg:address":"Pool House, Bancrift Road",
    "sg:city":"Reigate",
    "sg:classifiers":[
        {
            "category":"Professional",
            "subcategory":"Management & Consulting",
            "type":"Services"
        }
    ],
    "sg:phone":"+44 1737 240888",
    "sg:postcode":"RH2 7RP",
    "sg:province":"Surrey",
    "sg:tags":[
        "consultant",
        "business"
    ],
    "wof:name":"Avondale Business Consultants Ltd.",
    "wof:placetype":"venue"
},
  "geometry": {"coordinates":[-0.204779,51.235744],"type":"Point"}
}