{
  "type": "Feature",
  "properties": {
    "addr:full":"Northwick Road, Mark Highbridge Somerset TA9 4PG",
    "addr:postcode":"ta9 4pg",
    "addr:street":"Northwick Road",
    "iso:country":"GB",
    "sg:address":"Northwick Road, Mark",
    "sg:city":"Highbridge",
    "sg:classifiers":[
        {
            "category":"Farming",
            "subcategory":"Livestock Farm",
            "type":"Manufacturing & Wholesale Goods"
        }
    ],
    "sg:phone":"+44 1278 641228",
    "sg:postcode":"TA9 4PG",
    "sg:province":"Somerset",
    "sg:tags":[
        "others"
    ],
    "wof:name":"A Slocombe",
    "wof:placetype":"venue"
},
  "geometry": {"coordinates":[-2.895636,51.227692],"type":"Point"}
}