{
  "type": "Feature",
  "properties": {
    "iso:country":"GB",
    "sg:address":"House Of Commons",
    "sg:city":"London",
    "sg:classifiers":[
        {
            "category":"Government",
            "subcategory":"Office",
            "type":"Public Place"
        }
    ],
    "sg:phone":"+44 20 7219 6226",
    "sg:postcode":"SW1A 0AA",
    "sg:province":"Greater London",
    "sg:tags":[
        "mp",
        "meps"
    ],
    "wof:name":"Charles Kennedy",
    "wof:placetype":"venue"
},
  "geometry": {"coordinates":[-0.12482,51.500469],"type":"Point"}
}