{
  "type": "Feature",
  "properties": {
    "addr:full":"18 Silver Street Cambridge Cambridgeshire CB3 9EL",
    "addr:housenumber":"18",
    "addr:postcode":"cb3 9el",
    "addr:street":"Silver Street",
    "iso:country":"GB",
    "sg:address":"18 Silver Street",
    "sg:city":"Cambridge",
    "sg:classifiers":[
        {
            "category":"Education",
            "subcategory":"University",
            "type":"Public Place"
        }
    ],
    "sg:phone":"+44 1223 353518",
    "sg:postcode":"CB3 9EL",
    "sg:province":"Cambridgeshire",
    "sg:tags":[
        "activties",
        "school",
        "medical"
    ],
    "wof:name":"University Accommodation Service",
    "wof:placetype":"venue"
},
  "geometry": {"coordinates":[0.1161290035,52.2020225525],"type":"Point"}
}