{
  "type": "Feature",
  "properties": {
    "addr:full":"51-53 The Causeway Staines Berkshire TW18 3AX",
    "addr:housenumber":"51-53",
    "addr:postcode":"tw18 3ax",
    "addr:street":"The Causeway",
    "iso:country":"GB",
    "sg:address":"51-53 The Causeway",
    "sg:city":"Staines",
    "sg:classifiers":[
        {
            "category":"Autos & Motor Vehicles",
            "subcategory":"Auto Supplies",
            "type":"Retail Goods"
        }
    ],
    "sg:phone":"+44 1784 459152",
    "sg:postcode":"TW18 3AX",
    "sg:province":"Berkshire",
    "sg:tags":[
        "exhaust",
        "absorber",
        "shock"
    ],
    "wof:name":"Kwik-Fit",
    "wof:placetype":"venue"
},
  "geometry": {"coordinates":[-0.5291320086,51.4343795776],"type":"Point"}
}