{
  "type": "Feature",
  "properties": {
    "addr:full":"84 Silver Street Enfield Greater London EN1 3EP",
    "addr:housenumber":"84",
    "addr:postcode":"en1 3ep",
    "addr:street":"Silver Street",
    "iso:country":"GB",
    "sg:address":"84 Silver Street",
    "sg:city":"Enfield",
    "sg:classifiers":[
        {
            "category":"Organizations",
            "subcategory":"Non-profit Organization",
            "type":"Services"
        }
    ],
    "sg:phone":"+44 1235 442900",
    "sg:postcode":"EN1 3EP",
    "sg:province":"Greater London",
    "sg:tags":[
        "organisation",
        "voluntary",
        "charity"
    ],
    "wof:name":"W R V S",
    "wof:placetype":"venue"
},
  "geometry": {"coordinates":[-0.0807209983,51.6542129517],"type":"Point"}
}