{
  "type": "Feature",
  "properties": {
    "addr:full":"Care Of 25 Redditch Bracknell Berkshire RG12 0TT",
    "addr:postcode":"rg12 0tt",
    "iso:country":"GB",
    "sg:address":"Care Of 25 Redditch",
    "sg:city":"Bracknell",
    "sg:classifiers":[
        {
            "category":"Community Center",
            "subcategory":"Youth",
            "type":"Public Place"
        }
    ],
    "sg:phone":"+44 1344 451276",
    "sg:postcode":"RG12 0TT",
    "sg:province":"Berkshire",
    "sg:tags":[
        "organisation",
        "centre"
    ],
    "wof:name":"Guide Association The",
    "wof:placetype":"venue"
},
  "geometry": {"coordinates":[-0.7381,51.39473],"type":"Point"}
}