{
  "type": "Feature",
  "properties": {
    "addr:full":"Unit 4 Aber Ct Swansea Swansea SA6 8QN",
    "addr:housenumber":"unit 4",
    "addr:postcode":"sa6 8qn",
    "addr:street":"Aber Ct",
    "iso:country":"GB",
    "sg:address":"Unit 4 Aber Ct",
    "sg:city":"Swansea",
    "sg:classifiers":[
        {
            "category":"Wholesale",
            "subcategory":"Office Equipment",
            "type":"Manufacturing & Wholesale Goods"
        }
    ],
    "sg:phone":"+44 1792 796969",
    "sg:postcode":"SA6 8QN",
    "sg:province":"Swansea",
    "sg:tags":[
        "agency",
        "business",
        "enterprise"
    ],
    "wof:name":"Swansea Enterprise Park",
    "wof:placetype":"venue"
},
  "geometry": {"coordinates":[-3.9158670902,51.65782547],"type":"Point"}
}