{
  "type": "Feature",
  "properties": {
    "iso:country":"GB",
    "sg:address":"203 Strathmartine Road",
    "sg:city":"Dundee",
    "sg:classifiers":[
        {
            "category":"Professional",
            "subcategory":"Engineering",
            "type":"Services"
        }
    ],
    "sg:phone":"+44 1382 858947",
    "sg:postcode":"DD3 8PH",
    "sg:province":"Dundee City",
    "wof:name":"E M S Euroweld Ltd.",
    "wof:placetype":"venue"
},
  "geometry": {"coordinates":[-2.984494,56.479397],"type":"Point"}
}