{
  "type": "Feature",
  "properties": {
    "addr:full":"56 Doncaster Road Barnsley South Yorkshire S70 1TL",
    "addr:housenumber":"56",
    "addr:postcode":"s70 1tl",
    "addr:street":"Doncaster Road;Yorkshire",
    "iso:country":"GB",
    "sg:address":"56 Doncaster Road",
    "sg:city":"Barnsley",
    "sg:classifiers":[
        {
            "category":"Food & Beverages",
            "subcategory":"Meat & Fish",
            "type":"Retail Goods"
        }
    ],
    "sg:phone":"+44 1226 203403",
    "sg:postcode":"S70 1TL",
    "sg:province":"South Yorkshire",
    "sg:tags":[
        "butcher"
    ],
    "wof:name":"J Charlesworth",
    "wof:placetype":"venue"
},
  "geometry": {"coordinates":[-1.474869,53.5499],"type":"Point"}
}