{
  "type": "Feature",
  "properties": {
    "addr:full":"Wilfred Street, Swinton Manchester Greater Manchester M27 6LN",
    "addr:postcode":"m27 6ln",
    "addr:street":"Wilfred Street",
    "iso:country":"GB",
    "sg:address":"Wilfred Street, Swinton",
    "sg:city":"Manchester",
    "sg:classifiers":[
        {
            "category":"Home & Garden",
            "subcategory":"Hardware",
            "type":"Retail Goods"
        }
    ],
    "sg:phone":"+44 161 794 8411",
    "sg:postcode":"M27 6LN",
    "sg:province":"Greater Manchester",
    "sg:tags":[
        "retailer",
        "diy"
    ],
    "wof:name":"B & Q Diy Supercentre",
    "wof:placetype":"venue"
},
  "geometry": {"coordinates":[-2.3371589184,53.5143318176],"type":"Point"}
}