{
  "type": "Feature",
  "properties": {
    "addr:full":"Acanthus Court 59 Leckhampton Road Cheltenham Gloucestershire GL53 0BS",
    "addr:housenumber":"59",
    "addr:postcode":"gl53 0bs",
    "addr:street":"Acanthus;Leckhampton Road",
    "iso:country":"GB",
    "sg:address":"Acanthus Court 59 Leckhampton Road",
    "sg:city":"Cheltenham",
    "sg:classifiers":[
        {
            "category":"Travel",
            "subcategory":"Hotels & Motels",
            "type":"Entertainment"
        }
    ],
    "sg:phone":"+44 1242 576083",
    "sg:postcode":"GL53 0BS",
    "sg:province":"Gloucestershire",
    "wof:name":"The Acanthus Consultancy Ltd.",
    "wof:placetype":"venue"
},
  "geometry": {"coordinates":[-2.0792870522,51.8827362061],"type":"Point"}
}