{
  "type": "Feature",
  "properties": {
    "iso:country":"GB",
    "sg:address":"Unit 1/2 Newport Road",
    "sg:city":"Hayes",
    "sg:classifiers":[
        {
            "category":"Professional",
            "subcategory":"Engineering",
            "type":"Services"
        }
    ],
    "sg:phone":"+44 20 8561 2442",
    "sg:postcode":"UB4 8JZ",
    "sg:province":"Greater London",
    "sg:tags":[
        "precision",
        "engineer"
    ],
    "wof:name":"Mule Engineering",
    "wof:placetype":"venue"
},
  "geometry": {"coordinates":[-0.433508,51.525784],"type":"Point"}
}