{
  "type": "Feature",
  "properties": {
    "iso:country":"GB",
    "sg:address":"Unit 8 Brindley Road, Reginald Road Industrial Estate",
    "sg:city":"St Helens",
    "sg:classifiers":[
        {
            "category":"Manufacturing",
            "subcategory":"Glass & Minerals",
            "type":"Manufacturing & Wholesale Goods"
        }
    ],
    "sg:phone":"+44 1744 819596",
    "sg:postcode":"WA9 4HY",
    "sg:province":"Cheshire",
    "sg:tags":[
        "product"
    ],
    "wof:name":"P&R Distillex Ltd.",
    "wof:placetype":"venue"
},
  "geometry": {"coordinates":[-2.703046,53.429977],"type":"Point"}
}