{
  "type": "Feature",
  "properties": {
    "addr:full":"13 Princes Avenue Nuneaton Leicestershire CV11 5NT",
    "addr:housenumber":"13",
    "addr:postcode":"cv11 5nt",
    "addr:street":"Princes Avenue",
    "iso:country":"GB",
    "sg:address":"13 Princes Avenue",
    "sg:city":"Nuneaton",
    "sg:classifiers":[
        {
            "category":"Professional",
            "subcategory":"Engineering",
            "type":"Services"
        },
        {
            "category":"Building & Trades",
            "subcategory":"Electrical",
            "type":"Services"
        }
    ],
    "sg:phone":"+44 24 7638 5651",
    "sg:postcode":"CV11 5NT",
    "sg:province":"Leicestershire",
    "sg:tags":[
        "engineer",
        "electrician",
        "contractor"
    ],
    "wof:name":"Associated Electrical Services Ltd",
    "wof:placetype":"venue"
},
  "geometry": {"coordinates":[-1.473263,52.519405],"type":"Point"}
}