{
  "type": "Feature",
  "properties": {
    "addr:full":"Rowan House, Gwernymynydd Mold Denbighshire CH7 4DS",
    "addr:postcode":"ch7 4ds",
    "iso:country":"GB",
    "sg:address":"Rowan House, Gwernymynydd",
    "sg:city":"Mold",
    "sg:classifiers":[
        {
            "category":"Professional",
            "subcategory":"Management & Consulting",
            "type":"Services"
        }
    ],
    "sg:phone":"+44 1352 759993",
    "sg:postcode":"CH7 4DS",
    "sg:province":"Denbighshire",
    "sg:tags":[
        "consultant",
        "safety"
    ],
    "wof:name":"Moffatt Associates Ltd.",
    "wof:placetype":"venue"
},
  "geometry": {"coordinates":[-3.117239,53.114929],"type":"Point"}
}