{
  "type": "Feature",
  "properties": {
    "addr:full":"Bury Family Centre, Tenters Street Bury Lancashire BL9 0HX",
    "addr:postcode":"bl9 0hx",
    "addr:street":"Tenters Street",
    "iso:country":"GB",
    "sg:address":"Bury Family Centre, Tenters Street",
    "sg:city":"Bury",
    "sg:classifiers":[
        {
            "category":"Organizations",
            "subcategory":"Non-profit Organization",
            "type":"Services"
        }
    ],
    "sg:phone":"+44 161 764 4811",
    "sg:postcode":"BL9 0HX",
    "sg:province":"Lancashire",
    "sg:tags":[
        "organisation",
        "voluntary",
        "charity"
    ],
    "wof:name":"N C H Action for Children",
    "wof:placetype":"venue"
},
  "geometry": {"coordinates":[-2.301054,53.589733],"type":"Point"}
}