{
  "type": "Feature",
  "properties": {
    "addr:full":"36 High Street, Llanberis Caernarfon Gwynedd LL55 4EU",
    "addr:housenumber":"36",
    "addr:postcode":"ll55 4eu",
    "addr:street":"High Street",
    "iso:country":"GB",
    "sg:address":"36 High Street, Llanberis",
    "sg:city":"Caernarfon",
    "sg:classifiers":[
        {
            "category":"Government",
            "subcategory":"Post Office",
            "type":"Public Place"
        }
    ],
    "sg:phone":"+44 1286 870201",
    "sg:postcode":"LL55 4EU",
    "sg:province":"Gwynedd",
    "wof:name":"Llanberis Post Office",
    "wof:placetype":"venue"
},
  "geometry": {"coordinates":[-4.1314439774,53.1246109009],"type":"Point"}
}