{
  "type": "Feature",
  "properties": {
    "iso:country":"GB",
    "sg:address":"4 Beaconsfield Terrace Road",
    "sg:city":"London",
    "sg:classifiers":[
        {
            "category":"Social Services",
            "subcategory":"Job Training",
            "type":"Services"
        }
    ],
    "sg:phone":"+44 20 7602 0222",
    "sg:postcode":"W14 0PP",
    "sg:province":"Greater London",
    "sg:tags":[
        "translator",
        "interpreter"
    ],
    "wof:name":"Iranian Translation Services",
    "wof:placetype":"venue"
},
  "geometry": {"coordinates":[-0.212178,51.497185],"type":"Point"}
}