{
  "type": "Feature",
  "properties": {
    "addr:full":"Heathhall Industrial Estate Dumfries Dumfries and Galloway DG1 3PH",
    "addr:postcode":"dg1 3ph",
    "addr:street":"Estate",
    "iso:country":"GB",
    "sg:address":"Heathhall Industrial Estate",
    "sg:city":"Dumfries",
    "sg:classifiers":[
        {
            "category":"Shopping",
            "subcategory":"Computers & Home Electronics",
            "type":"Retail Goods"
        }
    ],
    "sg:phone":"+44 1387 247100",
    "sg:postcode":"DG1 3PH",
    "sg:province":"Dumfries and Galloway",
    "wof:name":"Dawnhill Furniture",
    "wof:placetype":"venue"
},
  "geometry": {"coordinates":[-3.5796699524,55.0959510803],"type":"Point"}
}