{
  "type": "Feature",
  "properties": {
    "addr:full":"48 Clyston Street London Greater London SW8 4TX",
    "addr:housenumber":"48",
    "addr:postcode":"sw8 4tx",
    "addr:street":"Clyston Street",
    "iso:country":"GB",
    "sg:address":"48 Clyston Street",
    "sg:city":"London",
    "sg:classifiers":[
        {
            "category":"Manufacturing",
            "subcategory":"Wood Products",
            "type":"Manufacturing & Wholesale Goods"
        }
    ],
    "sg:phone":"+44 20 7498 1398",
    "sg:postcode":"SW8 4TX",
    "sg:province":"Greater London",
    "sg:tags":[
        "maker",
        "cabinet"
    ],
    "wof:name":"Dakin Ltd.",
    "wof:placetype":"venue"
},
  "geometry": {"coordinates":[-0.1369840056,51.4722442627],"type":"Point"}
}