{
  "type": "Feature",
  "properties": {
    "iso:country":"GB",
    "sg:address":"12 Wellington Street",
    "sg:city":"Ashton Under Lyne",
    "sg:classifiers":[
        {
            "category":"Shopping",
            "subcategory":"Antiques",
            "type":"Retail Goods"
        }
    ],
    "sg:phone":"+44 161 343 2548",
    "sg:postcode":"OL6 6AJ",
    "sg:province":"Greater Manchester",
    "wof:name":"Sally's Antiques",
    "wof:placetype":"venue"
},
  "geometry": {"coordinates":[-2.0932819843,53.4880599976],"type":"Point"}
}