{
  "type": "Feature",
  "properties": {
    "addr:full":"2 Church Hill, Little Waltham Chelmsford Essex CM3 3LR",
    "addr:housenumber":"2",
    "addr:postcode":"cm3 3lr",
    "addr:street":"Church Hill",
    "iso:country":"GB",
    "sg:address":"2 Church Hill, Little Waltham",
    "sg:city":"Chelmsford",
    "sg:classifiers":[
        {
            "category":"Professional",
            "subcategory":"Management & Consulting",
            "type":"Services"
        }
    ],
    "sg:postcode":"CM3 3LR",
    "sg:province":"Essex",
    "sg:tags":[
        "consultant",
        "specialist"
    ],
    "wof:name":"Louise Aston Mobile Beauty",
    "wof:placetype":"venue"
},
  "geometry": {"coordinates":[0.4782420099,51.7879524231],"type":"Point"}
}