{
  "type": "Feature",
  "properties": {
    "addr:full":"17 Heath Park Avenue Cardiff Cardiff CF14 3RF",
    "addr:housenumber":"17",
    "addr:postcode":"cf14 3rf",
    "addr:street":"Heath Park Avenue",
    "iso:country":"GB",
    "sg:address":"17 Heath Park Avenue",
    "sg:city":"Cardiff",
    "sg:classifiers":[
        {
            "category":"Health Services",
            "subcategory":"Health Practitioner",
            "type":"Services"
        }
    ],
    "sg:phone":"+44 29 2075 1407",
    "sg:postcode":"CF14 3RF",
    "sg:province":"Cardiff",
    "sg:tags":[
        "physiotherapist"
    ],
    "wof:name":"NORMAN HOPKINS",
    "wof:placetype":"venue"
},
  "geometry": {"coordinates":[-3.1821279526,51.51146698],"type":"Point"}
}