{
  "type": "Feature",
  "properties": {
    "addr:full":"Watkins Hall Farm, Watton At Stone Hertford Hertfordshire SG14 2RJ",
    "addr:postcode":"sg14 2rj",
    "addr:street":"Hertford",
    "iso:country":"GB",
    "sg:address":"Watkins Hall Farm, Watton At Stone",
    "sg:city":"Hertford",
    "sg:classifiers":[
        {
            "category":"Farming",
            "subcategory":"Livestock Farm",
            "type":"Manufacturing & Wholesale Goods"
        }
    ],
    "sg:phone":"+44 1920 830214",
    "sg:postcode":"SG14 2RJ",
    "sg:province":"Hertfordshire",
    "sg:tags":[
        "others"
    ],
    "wof:name":"Alan J Pearman",
    "wof:placetype":"venue"
},
  "geometry": {"coordinates":[-0.082699,51.796341],"type":"Point"}
}