{
  "type": "Feature",
  "properties": {
    "iso:country":"GB",
    "sg:address":"Vaulken House Farm, Coopers Green",
    "sg:city":"Uckfield",
    "sg:classifiers":[
        {
            "category":"Manufacturing",
            "subcategory":"Wood Products",
            "type":"Manufacturing & Wholesale Goods"
        }
    ],
    "sg:phone":"+44 1825 733361",
    "sg:postcode":"TN22 4AT",
    "sg:province":"East Sussex",
    "wof:name":"Clarendon Equestrian Ltd.",
    "wof:placetype":"venue"
},
  "geometry": {"coordinates":[0.09665,50.971813],"type":"Point"}
}