{
  "type": "Feature",
  "properties": {
    "addr:full":"46 White Apron Street Pontefract West Yorkshire WF9 3LH",
    "addr:housenumber":"46",
    "addr:postcode":"wf9 3lh",
    "addr:street":"White Apron Street",
    "iso:country":"GB",
    "sg:address":"46 White Apron Street",
    "sg:city":"Pontefract",
    "sg:classifiers":[
        {
            "category":"Shopping",
            "type":"Retail Goods"
        }
    ],
    "sg:phone":"+44 1977 645454",
    "sg:postcode":"WF9 3LH",
    "sg:province":"West Yorkshire",
    "sg:tags":[
        "part",
        "accessory"
    ],
    "wof:name":"Partwell Motor Spares Ltd.",
    "wof:placetype":"venue"
},
  "geometry": {"coordinates":[-1.324369,53.593254],"type":"Point"}
}