{
  "type": "Feature",
  "properties": {
    "iso:country":"GB",
    "sg:address":"Higher Town, Malborough",
    "sg:city":"Kingsbridge",
    "sg:classifiers":[
        {
            "category":"Education",
            "subcategory":"School",
            "type":"Public Place"
        }
    ],
    "sg:phone":"+44 1548 561444",
    "sg:postcode":"TQ7 3RN",
    "sg:province":"Devon",
    "sg:tags":[
        "local",
        "authority"
    ],
    "wof:name":"Malborough Primary School",
    "wof:placetype":"venue"
},
  "geometry": {"coordinates":[-3.8121159077,50.244178772],"type":"Point"}
}