{
  "type": "Feature",
  "properties": {
    "addr:full":"2 Sackville Road Hove East Sussex BN3 3FA",
    "addr:housenumber":"2",
    "addr:postcode":"bn3 3fa",
    "addr:street":"Sackville Road",
    "iso:country":"GB",
    "sg:address":"2 Sackville Road",
    "sg:city":"Hove",
    "sg:classifiers":[
        {
            "category":"Health Services",
            "subcategory":"Nursing And Care Facility",
            "type":"Services"
        }
    ],
    "sg:phone":"+44 1273 775577",
    "sg:postcode":"BN3 3FA",
    "sg:province":"East Sussex",
    "sg:tags":[
        "home"
    ],
    "wof:name":"Sackville Nursing Home",
    "wof:placetype":"venue"
},
  "geometry": {"coordinates":[-0.178412,50.830124],"type":"Point"}
}