{
  "type": "Feature",
  "properties": {
    "iso:country":"GB",
    "sg:address":"70 High St",
    "sg:city":"Sheerness",
    "sg:classifiers":[
        {
            "category":"Home & Garden",
            "subcategory":"Household Appliances",
            "type":"Retail Goods"
        }
    ],
    "sg:postcode":"ME12 1NL",
    "sg:province":"Kent",
    "sg:tags":[
        "electrical"
    ],
    "wof:name":"French,Eamonn,",
    "wof:placetype":"venue"
},
  "geometry": {"coordinates":[0.761734,51.440277],"type":"Point"}
}