{
  "type": "Feature",
  "properties": {
    "addr:full":"Angel Place, Castle Street Neath Neath Port Talbot SA11 1RS",
    "addr:postcode":"sa11 1rs",
    "addr:street":"Angel Place Castle Street",
    "iso:country":"GB",
    "sg:address":"Angel Place, Castle Street",
    "sg:city":"Neath",
    "sg:classifiers":[
        {
            "category":"Autos & Motor Vehicles",
            "subcategory":"Fuel & Gas Station",
            "type":"Retail Goods"
        },
        {
            "category":"Food & Beverages",
            "subcategory":"Supermarket",
            "type":"Retail Goods"
        }
    ],
    "sg:phone":"+44 1639 634288",
    "sg:postcode":"SA11 1RS",
    "sg:province":"Neath Port Talbot",
    "sg:tags":[
        "petrol",
        "filling"
    ],
    "wof:name":"Safeway Stores Ltd.",
    "wof:placetype":"venue"
},
  "geometry": {"coordinates":[-3.805893898,51.6645202637],"type":"Point"}
}