{
  "type": "Feature",
  "properties": {
    "addr:full":"6 Mill Street, Ensham Witney Oxfordshire OX29 4JS",
    "addr:housenumber":"6",
    "addr:postcode":"ox29 4js",
    "addr:street":"Mill Street",
    "iso:country":"GB",
    "sg:address":"6 Mill Street, Ensham",
    "sg:city":"Witney",
    "sg:classifiers":[
        {
            "category":"Retail",
            "subcategory":"Photofinishing",
            "type":"Services"
        }
    ],
    "sg:phone":"+44 1865 883511",
    "sg:postcode":"OX29 4JS",
    "sg:province":"Oxfordshire",
    "sg:tags":[
        "photographic",
        "processor"
    ],
    "wof:name":"Crown Prints of Ensham",
    "wof:placetype":"venue"
},
  "geometry": {"coordinates":[-1.37418,51.781158],"type":"Point"}
}