{
  "type": "Feature",
  "properties": {
    "iso:country":"GB",
    "sg:address":"Priests House, Station Road",
    "sg:city":"Mayfield",
    "sg:classifiers":[
        {
            "category":"Place Of Worship",
            "type":"Public Place"
        }
    ],
    "sg:phone":"+44 1435 872381",
    "sg:postcode":"TN20 6BU",
    "sg:province":"East Sussex",
    "wof:name":"St Thomas Of Canterbury R C Church",
    "wof:placetype":"venue"
},
  "geometry": {"coordinates":[0.2544800043,51.0196762085],"type":"Point"}
}