{
  "type": "Feature",
  "properties": {
    "iso:country":"GB",
    "sg:address":"100 Beaconsfield Rd, Tottenham",
    "sg:city":"Seven Sisters",
    "sg:classifiers":[
        {
            "category":"Building & Trades",
            "subcategory":"Construction",
            "type":"Services"
        }
    ],
    "sg:phone":"+44 20 8809 4333",
    "sg:postcode":"N15 4SQ",
    "sg:province":"Greater London",
    "sg:tags":[
        "roofing"
    ],
    "wof:name":"Cliton Wild (Builders) Ltd",
    "wof:placetype":"venue"
},
  "geometry": {"coordinates":[-0.075999,51.587345],"type":"Point"}
}