{
  "type": "Feature",
  "properties": {
    "addr:full":"11 Nottingham Road, Cropwell Bishop Nottingham Nottinghamshire NG12 3BP",
    "addr:housenumber":"11",
    "addr:postcode":"ng12 3bp",
    "addr:street":"Nottingham Road",
    "iso:country":"GB",
    "sg:address":"11 Nottingham Road, Cropwell Bishop",
    "sg:city":"Nottingham",
    "sg:classifiers":[
        {
            "category":"Food & Beverages",
            "subcategory":"Meat & Fish",
            "type":"Retail Goods"
        }
    ],
    "sg:phone":"+44 115 989 2244",
    "sg:postcode":"NG12 3BP",
    "sg:province":"Nottinghamshire",
    "sg:tags":[
        "butcher"
    ],
    "wof:name":"H Barlow & Son",
    "wof:placetype":"venue"
},
  "geometry": {"coordinates":[-0.9848300219,52.9125671387],"type":"Point"}
}