{
  "type": "Feature",
  "properties": {
    "iso:country":"GB",
    "sg:address":"The Surgery, Station Road",
    "sg:city":"York",
    "sg:classifiers":[
        {
            "category":"Retail",
            "subcategory":"Veterinary Services",
            "type":"Services"
        }
    ],
    "sg:postcode":"YO62 5BZ",
    "sg:province":"North Yorkshire",
    "sg:tags":[
        "surgeon"
    ],
    "wof:name":"Four Dales Veterinary Practice",
    "wof:placetype":"venue"
},
  "geometry": {"coordinates":[-1.05534,54.244492],"type":"Point"}
}