{
  "type": "Feature",
  "properties": {
    "addr:full":"4 Graingers Lane, Cradley Heath Cradley Heath West Midlands B64 6AH",
    "addr:housenumber":"4",
    "addr:postcode":"b64 6ah",
    "addr:street":"Graingers Lane",
    "iso:country":"GB",
    "sg:address":"4 Graingers Lane, Cradley Heath",
    "sg:city":"Cradley Heath",
    "sg:classifiers":[
        {
            "category":"Banks & Credit Unions",
            "subcategory":"Financial Services",
            "type":"Services"
        }
    ],
    "sg:phone":"+44 1384 566289",
    "sg:postcode":"B64 6AH",
    "sg:province":"West Midlands",
    "sg:tags":[
        "adviser"
    ],
    "wof:name":"Broad Securities Ltd",
    "wof:placetype":"venue"
},
  "geometry": {"coordinates":[-2.0833740234,52.4705314636],"type":"Point"}
}