{
  "type": "Feature",
  "properties": {
    "iso:country":"GB",
    "sg:address":"Trumpington Rd",
    "sg:city":"Cambridge",
    "sg:classifiers":[
        {
            "category":"Building & Trades",
            "subcategory":"Landscaping Services",
            "type":"Services"
        }
    ],
    "sg:phone":"+44 1223 315628",
    "sg:postcode":"CB2 2AG",
    "sg:province":"Cambridgeshire",
    "sg:tags":[
        "contractor",
        "sport",
        "ground"
    ],
    "wof:name":"Cambridge Football Stadium",
    "wof:placetype":"venue"
},
  "geometry": {"coordinates":[0.122732,52.190174],"type":"Point"}
}