{
  "type": "Feature",
  "properties": {
    "addr:full":"89 Streatham High Road London Greater London SW16 1PH",
    "addr:housenumber":"89",
    "addr:postcode":"sw16 1ph",
    "addr:street":"Streatham High Road",
    "iso:country":"GB",
    "sg:address":"89 Streatham High Road",
    "sg:city":"London",
    "sg:classifiers":[
        {
            "category":"Shopping",
            "subcategory":"Clothing, Apparel, & Fashions",
            "type":"Retail Goods"
        }
    ],
    "sg:phone":"+44 20 8769 0292",
    "sg:postcode":"SW16 1PH",
    "sg:province":"Greater London",
    "sg:tags":[
        "menswear"
    ],
    "wof:name":"Parksons",
    "wof:placetype":"venue"
},
  "geometry": {"coordinates":[-0.1295319945,51.431930542],"type":"Point"}
}