{
  "type": "Feature",
  "properties": {
    "addr:full":"Po Box 160, Whitley Village Coventry Warwickshire CV3 4HZ",
    "addr:housenumber":"po",
    "addr:postcode":"cv3 4hz",
    "addr:street":"Box 160 Whitley Village",
    "iso:country":"GB",
    "sg:address":"Po Box 160, Whitley Village",
    "sg:city":"Coventry",
    "sg:classifiers":[
        {
            "category":"Real Estate",
            "subcategory":"Developer",
            "type":"Services"
        },
        {
            "category":"Organizations",
            "subcategory":"Community Association",
            "type":"Services"
        }
    ],
    "sg:phone":"+44 24 7650 7100",
    "sg:postcode":"CV3 4HZ",
    "sg:province":"Warwickshire",
    "sg:tags":[
        "society",
        "housing",
        "property"
    ],
    "wof:name":"Touchstone Housing Association Head Office",
    "wof:placetype":"venue"
},
  "geometry": {"coordinates":[-1.4876899719,52.3880004883],"type":"Point"}
}