{
  "type": "Feature",
  "properties": {
    "iso:country":"GB",
    "sg:address":"Church House, 19 Otley Street",
    "sg:city":"Skipton",
    "sg:classifiers":[
        {
            "category":"Organizations",
            "subcategory":"Political Organization",
            "type":"Services"
        }
    ],
    "sg:postcode":"BD23 1DY",
    "sg:province":"Lancashire",
    "sg:tags":[
        "party"
    ],
    "wof:name":"Skipton & Ripon Conservative Association",
    "wof:placetype":"venue"
},
  "geometry": {"coordinates":[-2.0154929161,53.9616661072],"type":"Point"}
}