{
  "type": "Feature",
  "properties": {
    "addr:full":"30 Bridge Street Uttoxeter Derbyshire ST14 8AP",
    "addr:housenumber":"30",
    "addr:postcode":"st14 8ap",
    "addr:street":"Bridge Street",
    "iso:country":"GB",
    "sg:address":"30 Bridge Street",
    "sg:city":"Uttoxeter",
    "sg:classifiers":[
        {
            "category":"Shopping",
            "subcategory":"Antiques",
            "type":"Retail Goods"
        }
    ],
    "sg:phone":"+44 1889 567717",
    "sg:postcode":"ST14 8AP",
    "sg:province":"Derbyshire",
    "wof:name":"Heathfield Antiques",
    "wof:placetype":"venue"
},
  "geometry": {"coordinates":[-1.8617789745,52.8974113464],"type":"Point"}
}