{
  "type": "Feature",
  "properties": {
    "addr:full":"102 Oxlow La Dagenham Essex RM9 5XD",
    "addr:housenumber":"102",
    "addr:postcode":"rm9 5xd",
    "addr:street":"Oxlow La Dagenham",
    "iso:country":"GB",
    "sg:address":"102 Oxlow La",
    "sg:city":"Dagenham",
    "sg:classifiers":[
        {
            "category":"Professional",
            "subcategory":"Secretarial Services",
            "type":"Services"
        }
    ],
    "sg:postcode":"RM9 5XD",
    "sg:province":"Essex",
    "wof:name":"Edwards,Colleen,",
    "wof:placetype":"venue"
},
  "geometry": {"coordinates":[0.1466899961,51.550994873],"type":"Point"}
}