{
  "type": "Feature",
  "properties": {
    "addr:full":"133 Barnards Green Road, Barnards Grn Malvern Herefordshire WR14 3LT",
    "addr:housenumber":"133",
    "addr:postcode":"wr14 3lt",
    "addr:street":"Barnards Green Road Barnards Grn;Herefordshire",
    "iso:country":"GB",
    "sg:address":"133 Barnards Green Road, Barnards Grn",
    "sg:city":"Malvern",
    "sg:classifiers":[
        {
            "category":"Professional",
            "subcategory":"Lawyer & Legal Services",
            "type":"Services"
        }
    ],
    "sg:phone":"+44 1684 574263",
    "sg:postcode":"WR14 3LT",
    "sg:province":"Herefordshire",
    "sg:tags":[
        "solicitor"
    ],
    "wof:name":"Owen Gaynor-Smith & Co.",
    "wof:placetype":"venue"
},
  "geometry": {"coordinates":[-2.309948,52.108585],"type":"Point"}
}