{
  "type": "Feature",
  "properties": {
    "iso:country":"GB",
    "sg:address":"St Aldates Court, Gartland Road",
    "sg:city":"Sunderland",
    "sg:classifiers":[
        {
            "category":"Organizations",
            "subcategory":"Community Association",
            "type":"Services"
        }
    ],
    "sg:phone":"+44 191 534 3549",
    "sg:postcode":"SR4 9LT",
    "sg:province":"Tyne and Wear",
    "sg:tags":[
        "society",
        "housing"
    ],
    "wof:name":"Anchor Housing Trust",
    "wof:placetype":"venue"
},
  "geometry": {"coordinates":[-1.4501899481,54.8885192871],"type":"Point"}
}