{
  "type": "Feature",
  "properties": {
    "addr:full":"282 Broadwater Crescent Stevenage Hertfordshire SG2 8AQ",
    "addr:housenumber":"282",
    "addr:postcode":"sg2 8aq",
    "addr:street":"Broadwater Crescent",
    "iso:country":"GB",
    "sg:address":"282 Broadwater Crescent",
    "sg:city":"Stevenage",
    "sg:classifiers":[
        {
            "category":"Autos & Motor Vehicles",
            "subcategory":"Automobile Sales",
            "type":"Retail Goods"
        }
    ],
    "sg:phone":"+44 1438 747477",
    "sg:postcode":"SG2 8AQ",
    "sg:province":"Hertfordshire",
    "sg:tags":[
        "car"
    ],
    "wof:name":"Premier Cars",
    "wof:placetype":"venue"
},
  "geometry": {"coordinates":[-0.180663,51.882011],"type":"Point"}
}