{
  "type": "Feature",
  "properties": {
    "addr:full":"Unit 7 Carlton Miniott Business, Park Carlton Road Thirsk North Yorkshire YO7 4NF",
    "addr:housenumber":"unit 7",
    "addr:postcode":"yo7 4nf",
    "addr:street":"Carlton Miniott Business Park Carlton Road",
    "iso:country":"GB",
    "sg:address":"Unit 7 Carlton Miniott Business, Park Carlton Road",
    "sg:city":"Thirsk",
    "sg:classifiers":[
        {
            "category":"Autos & Motor Vehicles",
            "subcategory":"Auto Supplies",
            "type":"Retail Goods"
        }
    ],
    "sg:phone":"+44 1845 525250",
    "sg:postcode":"YO7 4NF",
    "sg:province":"North Yorkshire",
    "sg:tags":[
        "towing",
        "eqpt",
        "trailer"
    ],
    "wof:name":"Duraloc Ltd.",
    "wof:placetype":"venue"
},
  "geometry": {"coordinates":[-1.342253,54.232689],"type":"Point"}
}