{
  "type": "Feature",
  "properties": {
    "addr:full":"Concorde House, 79-83 Holloway Head Birmingham West Midlands B1 1QP",
    "addr:housenumber":"79-83",
    "addr:postcode":"b1 1qp",
    "addr:street":"Holloway Head",
    "iso:country":"GB",
    "sg:address":"Concorde House, 79-83 Holloway Head",
    "sg:city":"Birmingham",
    "sg:classifiers":[
        {
            "category":"Retail",
            "subcategory":"Storage",
            "type":"Services"
        }
    ],
    "sg:phone":"+44 121 643 7975",
    "sg:postcode":"B1 1QP",
    "sg:province":"West Midlands",
    "sg:tags":[
        "household",
        "removal"
    ],
    "wof:name":"Landvan Ltd.",
    "wof:placetype":"venue"
},
  "geometry": {"coordinates":[-1.905099,52.473267],"type":"Point"}
}