{
  "type": "Feature",
  "properties": {
    "addr:full":"253 Newchurch Road, Stacksteads Bacup Lancashire OL13 0UG",
    "addr:housenumber":"253",
    "addr:postcode":"ol13 0ug",
    "addr:street":"Newchurch Road Stacksteads Bacup",
    "iso:country":"GB",
    "sg:address":"253 Newchurch Road, Stacksteads",
    "sg:city":"Bacup",
    "sg:classifiers":[
        {
            "category":"Professional",
            "subcategory":"Printing & Photocopies",
            "type":"Services"
        }
    ],
    "sg:postcode":"OL13 0UG",
    "sg:province":"Lancashire",
    "sg:tags":[
        "printer"
    ],
    "wof:name":"Hitchen Printers",
    "wof:placetype":"venue"
},
  "geometry": {"coordinates":[-2.228219,53.691689],"type":"Point"}
}