{
  "type": "Feature",
  "properties": {
    "addr:full":"Unit A3 Dart Marine Park Totnes Devon TQ9 5AL",
    "addr:housenumber":"a3",
    "addr:postcode":"tq9 5al",
    "iso:country":"GB",
    "sg:address":"Unit A3 Dart Marine Park",
    "sg:city":"Totnes",
    "sg:classifiers":[
        {
            "category":"Manufacturing",
            "subcategory":"Electronics",
            "type":"Manufacturing & Wholesale Goods"
        }
    ],
    "sg:postcode":"TQ9 5AL",
    "sg:province":"Devon",
    "sg:tags":[
        "control",
        "component",
        "-",
        "electronic"
    ],
    "wof:name":"Dart Sensors Ltd.",
    "wof:placetype":"venue"
},
  "geometry": {"coordinates":[-3.688093,50.434147],"type":"Point"}
}