{
  "type": "Feature",
  "properties": {
    "addr:full":"Lower Trewern, Newbridge Penzance Cornwall TR20 8PB",
    "addr:postcode":"tr20 8pb",
    "iso:country":"GB",
    "sg:address":"Lower Trewern, Newbridge",
    "sg:city":"Penzance",
    "sg:classifiers":[
        {
            "category":"Farming",
            "subcategory":"Livestock Farm",
            "type":"Manufacturing & Wholesale Goods"
        }
    ],
    "sg:phone":"+44 1736 364283",
    "sg:postcode":"TR20 8PB",
    "sg:province":"Cornwall",
    "sg:tags":[
        "others"
    ],
    "wof:name":"P A & Fa Jenkin",
    "wof:placetype":"venue"
},
  "geometry": {"coordinates":[-5.605119,50.128651],"type":"Point"}
}