{
  "type": "Feature",
  "properties": {
    "addr:full":"1 James Watt Place, College Milton North Glasgow South Lanarkshire G74 5HG",
    "addr:housenumber":"1",
    "addr:postcode":"g74 5hg",
    "addr:street":"James Watt Place",
    "iso:country":"GB",
    "sg:address":"1 James Watt Place, College Milton North",
    "sg:city":"Glasgow",
    "sg:classifiers":[
        {
            "category":"Professional",
            "subcategory":"Engineering",
            "type":"Services"
        }
    ],
    "sg:phone":"+44 1355 268660",
    "sg:postcode":"G74 5HG",
    "sg:province":"South Lanarkshire",
    "sg:tags":[
        "hydraulic",
        "engineer"
    ],
    "wof:name":"Brimac Hydraulics Ltd.",
    "wof:placetype":"venue"
},
  "geometry": {"coordinates":[-4.2072110176,55.7712364197],"type":"Point"}
}