{
  "type": "Feature",
  "properties": {
    "addr:full":"21 Westland Drive, Brookmans Ok Hatfield Hertfordshire AL9 7UG",
    "addr:housenumber":"21",
    "addr:postcode":"al9 7ug",
    "addr:street":"Westland Drive",
    "iso:country":"GB",
    "sg:address":"21 Westland Drive, Brookmans Ok",
    "sg:city":"Hatfield",
    "sg:classifiers":[
        {
            "category":"Building & Trades",
            "subcategory":"Construction",
            "type":"Services"
        }
    ],
    "sg:phone":"+44 1707 647508",
    "sg:postcode":"AL9 7UG",
    "sg:province":"Hertfordshire",
    "sg:tags":[
        "builder"
    ],
    "wof:name":"Wheeler Builders",
    "wof:placetype":"venue"
},
  "geometry": {"coordinates":[-0.203719,51.71888],"type":"Point"}
}