{
  "type": "Feature",
  "properties": {
    "iso:country":"GB",
    "sg:address":"26 Victoria Road",
    "sg:city":"Horley",
    "sg:classifiers":[
        {
            "category":"Food & Beverages",
            "subcategory":"Supermarket",
            "type":"Retail Goods"
        }
    ],
    "sg:phone":"+44 1293 820002",
    "sg:postcode":"RH6 7PZ",
    "sg:province":"Surrey",
    "wof:name":"Waitrose Supermarkets",
    "wof:placetype":"venue"
},
  "geometry": {"coordinates":[-0.1619890034,51.1700286865],"type":"Point"}
}