{
  "type": "Feature",
  "properties": {
    "addr:full":"Unit 3 Pegasus Court, 27 Herschel Street Slough Berkshire SL1 1PA",
    "addr:housenumber":"unit 3;27",
    "addr:postcode":"sl1 1pa",
    "addr:street":"Pegasus;Herschel Street",
    "iso:country":"GB",
    "sg:address":"Unit 3 Pegasus Court, 27 Herschel Street",
    "sg:city":"Slough",
    "sg:classifiers":[
        {
            "category":"Professional",
            "subcategory":"Employment Agencies",
            "type":"Services"
        }
    ],
    "sg:postcode":"SL1 1PA",
    "sg:province":"Berkshire",
    "sg:tags":[
        "consultant"
    ],
    "wof:name":"M T S  Group Ltd.",
    "wof:placetype":"venue"
},
  "geometry": {"coordinates":[-0.5895529985,51.5071983337],"type":"Point"}
}