{
  "type": "Feature",
  "properties": {
    "addr:full":"6 Bachefield Avenue Chester Cheshire CH3 6DA",
    "addr:housenumber":"6",
    "addr:postcode":"ch3 6da",
    "addr:street":"Bachefield Avenue",
    "iso:country":"GB",
    "sg:address":"6 Bachefield Avenue",
    "sg:city":"Chester",
    "sg:classifiers":[
        {
            "category":"Building & Trades",
            "subcategory":"Construction",
            "type":"Services"
        }
    ],
    "sg:postcode":"CH3 6DA",
    "sg:province":"Cheshire",
    "sg:tags":[
        "builder"
    ],
    "wof:name":"R Landry",
    "wof:placetype":"venue"
},
  "geometry": {"coordinates":[-2.868172,53.176167],"type":"Point"}
}