{
  "type": "Feature",
  "properties": {
    "addr:full":"27 Old Church Road, Chingford London Greater London E4 6SJ",
    "addr:housenumber":"27",
    "addr:postcode":"e4 6sj",
    "addr:street":"Old Church Road",
    "iso:country":"GB",
    "sg:address":"27 Old Church Road, Chingford",
    "sg:city":"London",
    "sg:classifiers":[
        {
            "category":"Banks & Credit Unions",
            "subcategory":"Bank",
            "type":"Services"
        }
    ],
    "sg:phone":"+44 20 8301 7386",
    "sg:postcode":"E4 6SJ",
    "sg:province":"Greater London",
    "wof:name":"Woolwich Ltd.",
    "wof:placetype":"venue"
},
  "geometry": {"coordinates":[-0.0172569994,51.6181335449],"type":"Point"}
}