{
  "type": "Feature",
  "properties": {
    "addr:full":"427b Oakleigh Rd North Totteridge Greater London N20 0RU",
    "addr:housenumber":"427b",
    "addr:postcode":"n20 0ru",
    "addr:street":"Oakleigh Rd",
    "iso:country":"GB",
    "sg:address":"427b Oakleigh Rd North",
    "sg:city":"Totteridge",
    "sg:classifiers":[
        {
            "category":"Autos & Motor Vehicles",
            "subcategory":"Automobile Sales",
            "type":"Retail Goods"
        }
    ],
    "sg:phone":"+44 20 8361 6203",
    "sg:postcode":"N20 0RU",
    "sg:province":"Greater London",
    "sg:tags":[
        "car"
    ],
    "wof:name":"Alan Lloyd Jones & Co",
    "wof:placetype":"venue"
},
  "geometry": {"coordinates":[-0.1536989957,51.6236991882],"type":"Point"}
}