{
  "type": "Feature",
  "properties": {
    "iso:country":"GB",
    "sg:address":"Llwyndu Mawr, Carmel Road, Penygroes",
    "sg:city":"Caernarfon",
    "sg:classifiers":[
        {
            "category":"Travel",
            "subcategory":"Hotels & Motels",
            "type":"Entertainment"
        }
    ],
    "sg:phone":"+44 1286 880419",
    "sg:postcode":"LL54 6PU",
    "sg:province":"Gwynedd",
    "sg:tags":[
        "house",
        "guest"
    ],
    "wof:name":"Elna Enterprises",
    "wof:placetype":"venue"
},
  "geometry": {"coordinates":[-4.2837,53.054615],"type":"Point"}
}