{
  "type": "Feature",
  "properties": {
    "iso:country":"GB",
    "sg:address":"City Libary, Princes Square",
    "sg:city":"Newcastle-upon-tyne",
    "sg:classifiers":[
        {
            "category":"Landmark",
            "subcategory":"Tourist Information",
            "type":"Public Place"
        }
    ],
    "sg:phone":"+44 191 261 0610",
    "sg:postcode":"NE99 1DX",
    "sg:province":"Tyne and Wear",
    "wof:name":"Tourist Information Centre",
    "wof:placetype":"venue"
},
  "geometry": {"coordinates":[-1.61577,54.967739],"type":"Point"}
}