{
  "type": "Feature",
  "properties": {
    "addr:full":"101 Upper Selsdon Road South Croydon Surrey CR2 0DP",
    "addr:housenumber":"101",
    "addr:postcode":"cr2 0dp",
    "addr:street":"Upper Selsdon Road",
    "iso:country":"GB",
    "sg:address":"101 Upper Selsdon Road",
    "sg:city":"South Croydon",
    "sg:classifiers":[
        {
            "category":"Communications",
            "type":"Services"
        }
    ],
    "sg:postcode":"CR2 0DP",
    "sg:province":"Surrey",
    "sg:tags":[
        "telecommunication"
    ],
    "wof:name":"Newpace Communications Ltd",
    "wof:placetype":"venue"
},
  "geometry": {"coordinates":[-0.071585,51.346481],"type":"Point"}
}