{
  "type": "Feature",
  "properties": {
    "iso:country":"GB",
    "sg:address":"School Way",
    "sg:city":"Okehampton",
    "sg:classifiers":[
        {
            "category":"Retail",
            "subcategory":"Auto Repair",
            "type":"Services"
        }
    ],
    "sg:phone":"+44 1837 54387",
    "sg:postcode":"EX20 1EU",
    "sg:province":"Devon",
    "sg:tags":[
        "modification",
        "garage"
    ],
    "wof:name":"Transmobile",
    "wof:placetype":"venue"
},
  "geometry": {"coordinates":[-4.003729,50.740349],"type":"Point"}
}