{
  "type": "Feature",
  "properties": {
    "iso:country":"GB",
    "sg:address":"Mayfields, Dyson Lane, Barningham Road",
    "sg:city":"Richmond",
    "sg:classifiers":[
        {
            "category":"Bus Charters",
            "type":"Transportation"
        }
    ],
    "sg:postcode":"DL11 7QT",
    "sg:province":"Durham",
    "sg:tags":[
        "hire",
        "coach"
    ],
    "wof:name":"Burrells Mini Coaches",
    "wof:placetype":"venue"
},
  "geometry": {"coordinates":[-1.871034,54.489166],"type":"Point"}
}