{
  "type": "Feature",
  "properties": {
    "addr:full":"Unit 10 Block D, Ongar Enterprise Centre Ongar Essex CM5 0AW",
    "addr:housenumber":"unit 10 block d;enterprise centre",
    "addr:postcode":"cm5 0aw",
    "addr:street":"Ongar",
    "iso:country":"GB",
    "sg:address":"Unit 10 Block D, Ongar Enterprise Centre",
    "sg:city":"Ongar",
    "sg:classifiers":[
        {
            "category":"Professional",
            "subcategory":"Art Services",
            "type":"Services"
        }
    ],
    "sg:postcode":"CM5 0AW",
    "sg:province":"Essex",
    "sg:tags":[
        "graphic",
        "designer"
    ],
    "wof:name":"Wot Image Works Design Services",
    "wof:placetype":"venue"
},
  "geometry": {"coordinates":[0.2451699972,51.7061309814],"type":"Point"}
}