{
  "type": "Feature",
  "properties": {
    "addr:full":"Square Court, St Catherine Street Carmarthen Carmarthenshire SA31 3DZ",
    "addr:postcode":"sa31 3dz",
    "addr:street":"Square Court St Catherine Street",
    "iso:country":"GB",
    "sg:address":"Square Court, St Catherine Street",
    "sg:city":"Carmarthen",
    "sg:classifiers":[
        {
            "category":"Autos & Motor Vehicles",
            "subcategory":"Automobile Sales",
            "type":"Retail Goods"
        }
    ],
    "sg:phone":"+44 1267 233371",
    "sg:postcode":"SA31 3DZ",
    "sg:province":"Carmarthenshire",
    "sg:tags":[
        "car"
    ],
    "wof:name":"Ceir Cawdor Cars",
    "wof:placetype":"venue"
},
  "geometry": {"coordinates":[-4.3146791458,51.8565864563],"type":"Point"}
}