{
  "type": "Feature",
  "properties": {
    "addr:full":"Peel Av Altrincham Cheshire WA14 2UG",
    "addr:postcode":"wa14 2ug",
    "addr:street":"Peel Av Altrincham",
    "iso:country":"GB",
    "sg:address":"Peel Av",
    "sg:city":"Altrincham",
    "sg:classifiers":[
        {
            "category":"Manufacturing",
            "subcategory":"Furniture",
            "type":"Manufacturing & Wholesale Goods"
        }
    ],
    "sg:phone":"+44 7710 950897",
    "sg:postcode":"WA14 2UG",
    "sg:province":"Cheshire",
    "sg:tags":[
        "polishing",
        "french"
    ],
    "wof:name":"Affordable Antiques Workshop",
    "wof:placetype":"venue"
},
  "geometry": {"coordinates":[-2.3507130146,53.3784141541],"type":"Point"}
}