{
  "type": "Feature",
  "properties": {
    "addr:full":"Earlswood Trading Estate, Poolhead Lane, Earlswood Solihull Warwickshire B94 5EW",
    "addr:postcode":"b94 5ew",
    "addr:street":"Poolhead Lane",
    "iso:country":"GB",
    "sg:address":"Earlswood Trading Estate, Poolhead Lane, Earlswood",
    "sg:city":"Solihull",
    "sg:classifiers":[
        {
            "category":"Professional",
            "subcategory":"Accounting & Tax Preparation",
            "type":"Services"
        },
        {
            "category":"Retail",
            "subcategory":"Auto Repair",
            "type":"Services"
        }
    ],
    "sg:phone":"+44 1564 703665",
    "sg:postcode":"B94 5EW",
    "sg:province":"Warwickshire",
    "sg:tags":[
        "modification",
        "garage",
        "sport",
        "motor"
    ],
    "wof:name":"G T Services",
    "wof:placetype":"venue"
},
  "geometry": {"coordinates":[-1.86315,52.352879],"type":"Point"}
}