{
  "type": "Feature",
  "properties": {
    "addr:full":"4 Wallis Court, James Carter Road Bury St Edmunds Cambridgeshire IP28 7DD",
    "addr:housenumber":"4",
    "addr:postcode":"ip28 7dd",
    "addr:street":"Wallis Court James Carter Road",
    "iso:country":"GB",
    "sg:address":"4 Wallis Court, James Carter Road",
    "sg:city":"Bury St Edmunds",
    "sg:classifiers":[
        {
            "category":"Professional",
            "subcategory":"Engineering",
            "type":"Services"
        }
    ],
    "sg:phone":"+44 1638 714188",
    "sg:postcode":"IP28 7DD",
    "sg:province":"Cambridgeshire",
    "wof:name":"M & D Engineering Installations Ltd.",
    "wof:placetype":"venue"
},
  "geometry": {"coordinates":[0.49937,52.353722],"type":"Point"}
}