{
  "type": "Feature",
  "properties": {
    "addr:full":"27 Hoades Wood Road, Sturry Canterbury Kent CT2 0LY",
    "addr:housenumber":"27",
    "addr:postcode":"ct2 0ly",
    "addr:street":"Hoades Wood Road",
    "iso:country":"GB",
    "sg:address":"27 Hoades Wood Road, Sturry",
    "sg:city":"Canterbury",
    "sg:classifiers":[
        {
            "category":"Food & Beverages",
            "subcategory":"Meat & Fish",
            "type":"Retail Goods"
        },
        {
            "category":"Food & Beverages",
            "subcategory":"Groceries & Convenience Stores",
            "type":"Retail Goods"
        }
    ],
    "sg:phone":"+44 1227 710434",
    "sg:postcode":"CT2 0LY",
    "sg:province":"Kent",
    "sg:tags":[
        "shop",
        "chip"
    ],
    "wof:name":"Sturry Fish Bar",
    "wof:placetype":"venue"
},
  "geometry": {"coordinates":[1.1319930553,51.3067855835],"type":"Point"}
}