{
  "type": "Feature",
  "properties": {
    "addr:full":"5 Halstead Road Harrogate North Yorkshire HG2 8BP",
    "addr:housenumber":"5",
    "addr:postcode":"hg2 8bp",
    "addr:street":"Halstead Road",
    "iso:country":"GB",
    "sg:address":"5 Halstead Road",
    "sg:city":"Harrogate",
    "sg:classifiers":[
        {
            "category":"Building & Trades",
            "subcategory":"Construction",
            "type":"Services"
        }
    ],
    "sg:phone":"+44 1423 879255",
    "sg:postcode":"HG2 8BP",
    "sg:province":"North Yorkshire",
    "sg:tags":[
        "roofing",
        "contracting"
    ],
    "wof:name":"I S Green Felt Roofing",
    "wof:placetype":"venue"
},
  "geometry": {"coordinates":[-1.5286999941,53.9792938232],"type":"Point"}
}