{
  "type": "Feature",
  "properties": {
    "iso:country":"GB",
    "sg:address":"352 Carlton Hill, Carlton",
    "sg:city":"Nottingham",
    "sg:classifiers":[
        {
            "category":"Social Services",
            "subcategory":"Adult Care",
            "type":"Services"
        }
    ],
    "sg:phone":"+44 115 940 2246",
    "sg:postcode":"NG4 1BG",
    "sg:province":"Nottinghamshire",
    "sg:tags":[
        "day",
        "centre"
    ],
    "wof:name":"Carlton Hill Crest Day Centre",
    "wof:placetype":"venue"
},
  "geometry": {"coordinates":[-1.1101930141,52.9660263062],"type":"Point"}
}