{
  "type": "Feature",
  "properties": {
    "iso:country":"GB",
    "sg:address":"2a-50 Sawday St",
    "sg:city":"Leicester",
    "sg:classifiers":[
        {
            "category":"Shopping",
            "subcategory":"Clothing, Apparel, & Fashions",
            "type":"Retail Goods"
        }
    ],
    "sg:phone":"+44 116 285 4679",
    "sg:postcode":"LE2 7JW",
    "sg:province":"Leicestershire",
    "sg:tags":[
        "clothing",
        "fabric"
    ],
    "wof:name":"United Fabrics Leicester Ltd",
    "wof:placetype":"venue"
},
  "geometry": {"coordinates":[-1.135293,52.622856],"type":"Point"}
}