{
  "type": "Feature",
  "properties": {
    "addr:full":"P O Box 100 Shrewsbury Shropshire SY4 4WF",
    "addr:housenumber":"100",
    "addr:postcode":"sy4 4wf",
    "addr:street":"P O Box",
    "iso:country":"GB",
    "sg:address":"P O Box 100",
    "sg:city":"Shrewsbury",
    "sg:classifiers":[
        {
            "category":"Retail",
            "subcategory":"Event Space",
            "type":"Services"
        }
    ],
    "sg:phone":"+44 1743 270000",
    "sg:postcode":"SY4 4WF",
    "sg:province":"Shropshire",
    "sg:tags":[
        "exhibition",
        "organiser"
    ],
    "wof:name":"S S R T V Associates",
    "wof:placetype":"venue"
},
  "geometry": {"coordinates":[-2.662329,52.763042],"type":"Point"}
}