{
  "type": "Feature",
  "properties": {
    "addr:full":"South Hetton Road, Easington Lane Houghton-le-spring Durham DH5 0LG",
    "addr:postcode":"dh5 0lg",
    "addr:street":"South Hetton Road;Lane",
    "iso:country":"GB",
    "sg:address":"South Hetton Road, Easington Lane",
    "sg:city":"Houghton-le-spring",
    "sg:classifiers":[
        {
            "category":"Autos & Motor Vehicles",
            "subcategory":"Automobile Sales",
            "type":"Retail Goods"
        }
    ],
    "sg:phone":"+44 191 526 2310",
    "sg:postcode":"DH5 0LG",
    "sg:province":"Durham",
    "sg:tags":[
        "car"
    ],
    "wof:name":"Snippersgate '88 Ltd.",
    "wof:placetype":"venue"
},
  "geometry": {"coordinates":[-1.433519,54.80735],"type":"Point"}
}