{
  "type": "Feature",
  "properties": {
    "iso:country":"GB",
    "sg:address":"Shakespeare House, 29a Warwick Road Wellesbourne",
    "sg:city":"Warwick",
    "sg:classifiers":[
        {
            "category":"Retail",
            "subcategory":"Auto Repair",
            "type":"Services"
        }
    ],
    "sg:phone":"+44 1784 70444",
    "sg:postcode":"CV35 9NA",
    "sg:province":"Warwickshire",
    "sg:tags":[
        "modification",
        "garage"
    ],
    "wof:name":"Markpage Ltd.",
    "wof:placetype":"venue"
},
  "geometry": {"coordinates":[-1.593404,52.197659],"type":"Point"}
}