{
  "type": "Feature",
  "properties": {
    "iso:country":"GB",
    "sg:address":"7 Beech Way",
    "sg:city":"Epsom",
    "sg:classifiers":[
        {
            "category":"Home & Garden",
            "subcategory":"Building Materials",
            "type":"Retail Goods"
        }
    ],
    "sg:phone":"+44 1372 722881",
    "sg:postcode":"KT17 4NG",
    "sg:province":"Surrey",
    "sg:tags":[
        "fencing"
    ],
    "wof:name":"Parkside Fencing",
    "wof:placetype":"venue"
},
  "geometry": {"coordinates":[-0.251902,51.323044],"type":"Point"}
}