{
  "type": "Feature",
  "properties": {
    "addr:full":"1 Leece Street Liverpool Merseyside L1 2TR",
    "addr:housenumber":"1",
    "addr:postcode":"l1 2tr",
    "addr:street":"Leece Street",
    "iso:country":"GB",
    "sg:address":"1 Leece Street",
    "sg:city":"Liverpool",
    "sg:classifiers":[
        {
            "category":"Restaurant",
            "type":"Food & Drink"
        }
    ],
    "sg:phone":"+44 151 709 0190",
    "sg:postcode":"L1 2TR",
    "sg:province":"Merseyside",
    "sg:tags":[
        "greek"
    ],
    "wof:name":"Zorba Kebab House Ltd.",
    "wof:placetype":"venue"
},
  "geometry": {"coordinates":[-2.974869,53.40218],"type":"Point"}
}