{
  "type": "Feature",
  "properties": {
    "addr:full":"18 High Street, Watton Thetford Norfolk IP25 6AE",
    "addr:housenumber":"18",
    "addr:postcode":"ip25 6ae",
    "addr:street":"High Street",
    "iso:country":"GB",
    "sg:address":"18 High Street, Watton",
    "sg:city":"Thetford",
    "sg:classifiers":[
        {
            "category":"Fast Food",
            "type":"Food & Drink"
        }
    ],
    "sg:phone":"+44 1953 882753",
    "sg:postcode":"IP25 6AE",
    "sg:province":"Norfolk",
    "sg:tags":[
        "away",
        "meal",
        "outlet",
        "take"
    ],
    "wof:name":"Golden Lantern",
    "wof:placetype":"venue"
},
  "geometry": {"coordinates":[0.8242279887,52.5715255737],"type":"Point"}
}