{
  "type": "Feature",
  "properties": {
    "addr:full":"54 Peffermill Road Edinburgh City of Edinburgh EH16 5NN",
    "addr:housenumber":"54",
    "addr:postcode":"eh16 5nn",
    "addr:street":"Peffermill Road",
    "iso:country":"GB",
    "sg:address":"54 Peffermill Road",
    "sg:city":"Edinburgh",
    "sg:classifiers":[
        {
            "category":"Wholesale",
            "subcategory":"Scrap",
            "type":"Manufacturing & Wholesale Goods"
        }
    ],
    "sg:postcode":"EH16 5NN",
    "sg:province":"City of Edinburgh",
    "sg:tags":[
        "breaker",
        "dismantlers"
    ],
    "wof:name":"Transport Services",
    "wof:placetype":"venue"
},
  "geometry": {"coordinates":[-3.155369,55.93203],"type":"Point"}
}