{
  "type": "Feature",
  "properties": {
    "addr:full":"Stall 51 Peterborough Mkt, Cattle Market Rd Peterborough Cambridgeshire PE1 1TW",
    "addr:housenumber":"51;mkt",
    "addr:postcode":"pe1 1tw",
    "addr:street":"Stall;Cattle Market Rd",
    "iso:country":"GB",
    "sg:address":"Stall 51 Peterborough Mkt, Cattle Market Rd",
    "sg:city":"Peterborough",
    "sg:classifiers":[
        {
            "category":"Shopping",
            "subcategory":"Crafts & Fabrics",
            "type":"Retail Goods"
        }
    ],
    "sg:postcode":"PE1 1TW",
    "sg:province":"Cambridgeshire",
    "sg:tags":[
        "upholsterers'",
        "supply"
    ],
    "wof:name":"Tedstill,Karen,Foam & Upholstery Supplie",
    "wof:placetype":"venue"
},
  "geometry": {"coordinates":[-0.24057,52.575352],"type":"Point"}
}