{
  "type": "Feature",
  "properties": {
    "iso:country":"GB",
    "sg:address":"Unit D1 Nimrod Way",
    "sg:city":"Ferndown",
    "sg:classifiers":[
        {
            "category":"Food & Beverages",
            "subcategory":"Supermarket",
            "type":"Retail Goods"
        }
    ],
    "sg:phone":"+44 1202 854774",
    "sg:postcode":"BH21 7SH",
    "sg:province":"Dorset",
    "sg:tags":[
        "frozen"
    ],
    "wof:name":"Sandwich Fillers",
    "wof:placetype":"venue"
},
  "geometry": {"coordinates":[-1.92136,50.807781],"type":"Point"}
}