{
  "type": "Feature",
  "properties": {
    "iso:country":"GB",
    "sg:address":"Liveridge Hill, Birmingham Rd",
    "sg:city":"Solihull",
    "sg:classifiers":[
        {
            "category":"Manufacturing",
            "subcategory":"Buildings",
            "type":"Manufacturing & Wholesale Goods"
        }
    ],
    "sg:phone":"+44 1564 794950",
    "sg:postcode":"B95 5QR",
    "sg:province":"Warwickshire",
    "sg:tags":[
        "portable"
    ],
    "wof:name":"Midland Stabling-Sectional Buildings",
    "wof:placetype":"venue"
},
  "geometry": {"coordinates":[-1.7694489956,52.3215103149],"type":"Point"}
}