{
  "type": "Feature",
  "properties": {
    "iso:country":"GB",
    "sg:address":"27 Laburnum Road, Lowton",
    "sg:city":"Warrington",
    "sg:classifiers":[
        {
            "category":"Professional",
            "subcategory":"Engineering",
            "type":"Services"
        }
    ],
    "sg:phone":"+44 1942 261498",
    "sg:postcode":"WA3 2NL",
    "sg:province":"Cheshire",
    "sg:tags":[
        "gas",
        "engineer"
    ],
    "wof:name":"Domestic Gas Services",
    "wof:placetype":"venue"
},
  "geometry": {"coordinates":[-2.5636088848,53.4723129272],"type":"Point"}
}