{
  "type": "Feature",
  "properties": {
    "iso:country":"GB",
    "sg:address":"368 Bath Rd",
    "sg:city":"Worcester",
    "sg:classifiers":[
        {
            "category":"Building & Trades",
            "subcategory":"Construction",
            "type":"Services"
        }
    ],
    "sg:postcode":"WR5 3HB",
    "sg:province":"Worcestershire",
    "sg:tags":[
        "builder"
    ],
    "wof:name":"Ideal Builders",
    "wof:placetype":"venue"
},
  "geometry": {"coordinates":[-2.213775,52.169304],"type":"Point"}
}