{
  "type": "Feature",
  "properties": {
    "addr:full":"233 Hollins Rd Oldham Lancashire OL8 3AA",
    "addr:housenumber":"233",
    "addr:postcode":"ol8 3aa",
    "addr:street":"Hollins Rd",
    "iso:country":"GB",
    "sg:address":"233 Hollins Rd",
    "sg:city":"Oldham",
    "sg:classifiers":[
        {
            "category":"Professional",
            "subcategory":"Business Services",
            "type":"Services"
        }
    ],
    "sg:postcode":"OL8 3AA",
    "sg:province":"Lancashire",
    "sg:tags":[
        "import",
        "export",
        "agent"
    ],
    "wof:name":"Chat-Away",
    "wof:placetype":"venue"
},
  "geometry": {"coordinates":[-2.1195480824,53.5251312256],"type":"Point"}
}