{
  "type": "Feature",
  "properties": {
    "addr:full":"1 Riverview Place Ellon Aberdeenshire AB41 9NW",
    "addr:housenumber":"1",
    "addr:postcode":"ab41 9nw",
    "addr:street":"Riverview Place",
    "iso:country":"GB",
    "sg:address":"1 Riverview Place",
    "sg:city":"Ellon",
    "sg:classifiers":[
        {
            "category":"Personal",
            "type":"Services"
        },
        {
            "category":"Shopping",
            "subcategory":"Bridal",
            "type":"Retail Goods"
        }
    ],
    "sg:postcode":"AB41 9NW",
    "sg:province":"Aberdeenshire",
    "sg:tags":[
        "shop",
        "gown",
        "wedding"
    ],
    "wof:name":"ELAINE ADAMSON BRIDAL",
    "wof:placetype":"venue"
},
  "geometry": {"coordinates":[-2.0832879543,57.3591308594],"type":"Point"}
}