{
  "type": "Feature",
  "properties": {
    "iso:country":"GB",
    "sg:address":"17a Chestergate",
    "sg:city":"Macclesfield",
    "sg:classifiers":[
        {
            "category":"Shopping",
            "subcategory":"Clothing, Apparel, & Fashions",
            "type":"Retail Goods"
        }
    ],
    "sg:postcode":"SK11 6BX",
    "sg:province":"Cheshire",
    "sg:tags":[
        "shop"
    ],
    "wof:name":"Worsleywear",
    "wof:placetype":"venue"
},
  "geometry": {"coordinates":[-2.1269450188,53.2569961548],"type":"Point"}
}