{
  "type": "Feature",
  "properties": {
    "addr:full":"40 Great Close, Chapel Brampton Northampton Northamptonshire NN6 8AN",
    "addr:housenumber":"40",
    "addr:postcode":"nn6 8an",
    "addr:street":"Great Close",
    "iso:country":"GB",
    "sg:address":"40 Great Close, Chapel Brampton",
    "sg:city":"Northampton",
    "sg:classifiers":[
        {
            "category":"Professional",
            "subcategory":"Management & Consulting",
            "type":"Services"
        }
    ],
    "sg:phone":"+44 1604 847620",
    "sg:postcode":"NN6 8AN",
    "sg:province":"Northamptonshire",
    "sg:tags":[
        "consultant",
        "business"
    ],
    "wof:name":"Steven Brown",
    "wof:placetype":"venue"
},
  "geometry": {"coordinates":[-0.9362810254,52.2906532288],"type":"Point"}
}