{
  "type": "Feature",
  "properties": {
    "addr:full":"86 Regent Drive Skipton Lancashire BD23 1BB",
    "addr:housenumber":"86",
    "addr:postcode":"bd23 1bb",
    "addr:street":"Regent Drive",
    "iso:country":"GB",
    "sg:address":"86 Regent Drive",
    "sg:city":"Skipton",
    "sg:classifiers":[
        {
            "category":"Professional",
            "subcategory":"Engineering",
            "type":"Services"
        }
    ],
    "sg:phone":"+44 1756 792631",
    "sg:postcode":"BD23 1BB",
    "sg:province":"Lancashire",
    "sg:tags":[
        "design",
        "engineer"
    ],
    "wof:name":"Bullivant Design Services Ltd.",
    "wof:placetype":"venue"
},
  "geometry": {"coordinates":[-2.00216,53.965637],"type":"Point"}
}