{
  "type": "Feature",
  "properties": {
    "iso:country":"GB",
    "sg:address":"59-61 Norman Road",
    "sg:city":"St Leonards-on-sea",
    "sg:classifiers":[
        {
            "category":"Shopping",
            "subcategory":"Antiques",
            "type":"Retail Goods"
        }
    ],
    "sg:postcode":"TN38 0EG",
    "sg:province":"East Sussex",
    "wof:name":"Hastings Antiques Centre",
    "wof:placetype":"venue"
},
  "geometry": {"coordinates":[0.559204,50.852135],"type":"Point"}
}