{
  "type": "Feature",
  "properties": {
    "addr:full":"40 Queen St Pembroke Dock Pembrokeshire SA72 6JE",
    "addr:housenumber":"40",
    "addr:postcode":"sa72 6je",
    "addr:street":"Queen St",
    "iso:country":"GB",
    "sg:address":"40 Queen St",
    "sg:city":"Pembroke Dock",
    "sg:classifiers":[
        {
            "category":"Health Services",
            "subcategory":"Dentist",
            "type":"Services"
        }
    ],
    "sg:phone":"+44 1646 685026",
    "sg:postcode":"SA72 6JE",
    "sg:province":"Pembrokeshire",
    "wof:name":"H Jaakola Family Dental Care",
    "wof:placetype":"venue"
},
  "geometry": {"coordinates":[-4.9432659149,51.6937408447],"type":"Point"}
}