{
  "type": "Feature",
  "properties": {
    "addr:full":"21 Sunnyside Road Weston-super-mare Somerset BS23 3QD",
    "addr:housenumber":"21",
    "addr:postcode":"bs23 3qd",
    "addr:street":"Sunnyside Road",
    "iso:country":"GB",
    "sg:address":"21 Sunnyside Road",
    "sg:city":"Weston-super-mare",
    "sg:classifiers":[
        {
            "category":"Home & Garden",
            "subcategory":"Household Appliances",
            "type":"Retail Goods"
        },
        {
            "category":"Retail",
            "subcategory":"Repair Shop",
            "type":"Services"
        }
    ],
    "sg:postcode":"BS23 3QD",
    "sg:province":"Somerset",
    "sg:tags":[
        "electrical",
        "television",
        "video",
        "radio"
    ],
    "wof:name":"David J Kingcott",
    "wof:placetype":"venue"
},
  "geometry": {"coordinates":[-2.971077919,51.337928772],"type":"Point"}
}