{
  "type": "Feature",
  "properties": {
    "addr:full":"20 Institute Road Swanage Dorset BH19 1BX",
    "addr:housenumber":"20",
    "addr:postcode":"bh19 1bx",
    "addr:street":"Institute Road",
    "iso:country":"GB",
    "sg:address":"20 Institute Road",
    "sg:city":"Swanage",
    "sg:classifiers":[
        {
            "category":"Shopping",
            "subcategory":"Department Store",
            "type":"Retail Goods"
        }
    ],
    "sg:phone":"+44 1929 427995",
    "sg:postcode":"BH19 1BX",
    "sg:province":"Dorset",
    "wof:name":"Costcutter",
    "wof:placetype":"venue"
},
  "geometry": {"coordinates":[-1.9569749832,50.6085662842],"type":"Point"}
}