{
  "type": "Feature",
  "properties": {
    "addr:full":"3 Finsbury Sq Moorgate Greater London EC2A 1LL",
    "addr:housenumber":"3",
    "addr:postcode":"ec2a 1ll",
    "addr:street":"Finsbury Sq",
    "iso:country":"GB",
    "sg:address":"3 Finsbury Sq",
    "sg:city":"Moorgate",
    "sg:classifiers":[
        {
            "category":"Insurance",
            "subcategory":"Insurance Agent",
            "type":"Services"
        }
    ],
    "sg:phone":"+44 20 7614 2700",
    "sg:postcode":"EC2A 1LL",
    "sg:province":"Greater London",
    "wof:name":"Legal & General Insurance",
    "wof:placetype":"venue"
},
  "geometry": {"coordinates":[-0.0874269977,51.5207481384],"type":"Point"}
}