{
  "type": "Feature",
  "properties": {
    "iso:country":"GB",
    "sg:address":"Willowgarth",
    "sg:city":"Rotherham",
    "sg:classifiers":[
        {
            "category":"Organizations",
            "subcategory":"Membership Organization",
            "type":"Services"
        }
    ],
    "sg:phone":"+44 1709 522771",
    "sg:postcode":"S62 5RB",
    "sg:province":"South Yorkshire",
    "sg:tags":[
        "club"
    ],
    "wof:name":"Rawmarsh Progressive Club & Institute",
    "wof:placetype":"venue"
},
  "geometry": {"coordinates":[-1.337366,53.465622],"type":"Point"}
}