{
  "type": "Feature",
  "properties": {
    "addr:full":"Unit 5 Ford Farm, Braintree Rd Clacton-on-sea Essex CM6 1HU",
    "addr:housenumber":"unit 5 ford farm",
    "addr:postcode":"cm6 1hu",
    "addr:street":"Braintree Rd",
    "iso:country":"GB",
    "sg:address":"Unit 5 Ford Farm, Braintree Rd",
    "sg:city":"Clacton-on-sea",
    "sg:classifiers":[
        {
            "category":"Retail",
            "subcategory":"Auto Rental",
            "type":"Services"
        }
    ],
    "sg:postcode":"CM6 1HU",
    "sg:province":"Essex",
    "sg:tags":[
        "car"
    ],
    "wof:name":"Thorn,Adrian,",
    "wof:placetype":"venue"
},
  "geometry": {"coordinates":[0.3774400055,51.8733482361],"type":"Point"}
}