{
  "type": "Feature",
  "properties": {
    "addr:full":"1 Lamb Street Hamilton South Lanarkshire ML3 6AH",
    "addr:housenumber":"1",
    "addr:postcode":"ml3 6ah",
    "addr:street":"Lamb Street",
    "iso:country":"GB",
    "sg:address":"1 Lamb Street",
    "sg:city":"Hamilton",
    "sg:classifiers":[
        {
            "category":"Professional",
            "subcategory":"Printing & Photocopies",
            "type":"Services"
        }
    ],
    "sg:phone":"+44 1698 281430",
    "sg:postcode":"ML3 6AH",
    "sg:province":"South Lanarkshire",
    "sg:tags":[
        "trophy"
    ],
    "wof:name":"B H Pringle (Wholesale) Ltd.",
    "wof:placetype":"venue"
},
  "geometry": {"coordinates":[-4.037902,55.774738],"type":"Point"}
}