{
  "type": "Feature",
  "properties": {
    "addr:full":"2 Carlisle Avenue, Penwortham Preston Lancashire PR1 0QP",
    "addr:housenumber":"2",
    "addr:postcode":"pr1 0qp",
    "addr:street":"Carlisle Avenue",
    "iso:country":"GB",
    "sg:address":"2 Carlisle Avenue, Penwortham",
    "sg:city":"Preston",
    "sg:classifiers":[
        {
            "category":"Retail",
            "subcategory":"Auto Repair",
            "type":"Services"
        }
    ],
    "sg:phone":"+44 1772 742214",
    "sg:postcode":"PR1 0QP",
    "sg:province":"Lancashire",
    "sg:tags":[
        "modification",
        "garage"
    ],
    "wof:name":"Richard Malinowski",
    "wof:placetype":"venue"
},
  "geometry": {"coordinates":[-2.7406640053,53.7449531555],"type":"Point"}
}