{
  "type": "Feature",
  "properties": {
    "addr:full":"36-60 Pear Tree Road Derby Derbyshire DE23 6PZ",
    "addr:housenumber":"36-60",
    "addr:postcode":"de23 6pz",
    "addr:street":"Pear Tree Road",
    "iso:country":"GB",
    "sg:address":"36-60 Pear Tree Road",
    "sg:city":"Derby",
    "sg:classifiers":[
        {
            "category":"Retail",
            "subcategory":"Auto Repair",
            "type":"Services"
        }
    ],
    "sg:phone":"+44 1332 385965",
    "sg:postcode":"DE23 6PZ",
    "sg:province":"Derbyshire",
    "sg:tags":[
        "modification",
        "garage"
    ],
    "wof:name":"Peartree Service Station",
    "wof:placetype":"venue"
},
  "geometry": {"coordinates":[-1.478707,52.907814],"type":"Point"}
}