{
  "type": "Feature",
  "properties": {
    "addr:full":"17 Wensley Gardens Emsworth Hampshire PO10 7RA",
    "addr:housenumber":"17",
    "addr:postcode":"po10 7ra",
    "addr:street":"Wensley Gardens",
    "iso:country":"GB",
    "sg:address":"17 Wensley Gardens",
    "sg:city":"Emsworth",
    "sg:classifiers":[
        {
            "category":"Retail",
            "subcategory":"Funeral Services",
            "type":"Services"
        }
    ],
    "sg:postcode":"PO10 7RA",
    "sg:province":"Hampshire",
    "wof:name":"Human Ceremonies",
    "wof:placetype":"venue"
},
  "geometry": {"coordinates":[-0.937834,50.858074],"type":"Point"}
}