{
  "type": "Feature",
  "properties": {
    "addr:full":"15 Falkland Square Crewkerne Dorset TA18 7JS",
    "addr:housenumber":"15",
    "addr:postcode":"ta18 7js",
    "addr:street":"Falkland Square",
    "iso:country":"GB",
    "sg:address":"15 Falkland Square",
    "sg:city":"Crewkerne",
    "sg:classifiers":[
        {
            "category":"Shopping",
            "subcategory":"Books",
            "type":"Retail Goods"
        }
    ],
    "sg:postcode":"TA18 7JS",
    "sg:province":"Dorset",
    "sg:tags":[
        "second-hand"
    ],
    "wof:name":"The Bookshop",
    "wof:placetype":"venue"
},
  "geometry": {"coordinates":[-2.7960140705,50.8843269348],"type":"Point"}
}