{
  "type": "Feature",
  "properties": {
    "iso:country":"GB",
    "sg:address":"1 Salisbury Rd",
    "sg:city":"Harpenden",
    "sg:classifiers":[
        {
            "category":"Building & Trades",
            "subcategory":"Construction",
            "type":"Services"
        }
    ],
    "sg:postcode":"AL5 5AR",
    "sg:province":"Hertfordshire",
    "sg:tags":[
        "builder"
    ],
    "wof:name":"Construction Stationery Co Ltd (The)",
    "wof:placetype":"venue"
},
  "geometry": {"coordinates":[-0.339213,51.825287],"type":"Point"}
}