{
  "type": "Feature",
  "properties": {
    "addr:full":"7 Mayflower Way Harleston Norfolk IP20 9EB",
    "addr:housenumber":"7",
    "addr:postcode":"ip20 9eb",
    "addr:street":"Mayflower Way",
    "iso:country":"GB",
    "sg:address":"7 Mayflower Way",
    "sg:city":"Harleston",
    "sg:classifiers":[
        {
            "category":"Autos & Motor Vehicles",
            "subcategory":"Motorcycle Sales",
            "type":"Retail Goods"
        }
    ],
    "sg:phone":"+44 1379 854644",
    "sg:postcode":"IP20 9EB",
    "sg:province":"Norfolk",
    "sg:tags":[
        "scooter",
        "cycle"
    ],
    "wof:name":"M R MOTORCYCLES",
    "wof:placetype":"venue"
},
  "geometry": {"coordinates":[1.305641,52.396259],"type":"Point"}
}