{
  "type": "Feature",
  "properties": {
    "addr:full":"21 Wynyard Gro Durham Durham DH1 2QJ",
    "addr:housenumber":"21",
    "addr:postcode":"dh1 2qj",
    "addr:street":"Wynyard Gro",
    "iso:country":"GB",
    "sg:address":"21 Wynyard Gro",
    "sg:city":"Durham",
    "sg:classifiers":[
        {
            "category":"Shopping",
            "subcategory":"News",
            "type":"Retail Goods"
        }
    ],
    "sg:phone":"+44 191 384 3794",
    "sg:postcode":"DH1 2QJ",
    "sg:province":"Durham",
    "sg:tags":[
        "newsagent"
    ],
    "wof:name":"Newsmarket",
    "wof:placetype":"venue"
},
  "geometry": {"coordinates":[-1.5438840389,54.7763748169],"type":"Point"}
}