{
  "type": "Feature",
  "properties": {
    "addr:full":"72 Palmersfield Rd Banstead Surrey SM7 2LD",
    "addr:housenumber":"72",
    "addr:postcode":"sm7 2ld",
    "addr:street":"Palmersfield Rd",
    "iso:country":"GB",
    "sg:address":"72 Palmersfield Rd",
    "sg:city":"Banstead",
    "sg:classifiers":[
        {
            "category":"Real Estate",
            "subcategory":"Architect",
            "type":"Services"
        }
    ],
    "sg:phone":"+44 1737 352904",
    "sg:postcode":"SM7 2LD",
    "sg:province":"Surrey",
    "wof:name":"Interway Engineering Ltd",
    "wof:placetype":"venue"
},
  "geometry": {"coordinates":[-0.197151,51.328331],"type":"Point"}
}