{
  "type": "Feature",
  "properties": {
    "iso:country":"GB",
    "sg:address":"Wolverhampton St, Darlaston",
    "sg:city":"Wednesbury",
    "sg:classifiers":[
        {
            "category":"Community Center",
            "type":"Public Place"
        }
    ],
    "sg:phone":"+44 121 568 6105",
    "sg:postcode":"WS10 8UE",
    "sg:province":"West Midlands",
    "sg:tags":[
        "nursery",
        "centre"
    ],
    "wof:name":"George Rose Park",
    "wof:placetype":"venue"
},
  "geometry": {"coordinates":[-2.0478689671,52.5711708069],"type":"Point"}
}