{
  "type": "Feature",
  "properties": {
    "addr:full":"21 St Augustines Gate, Hedon Hull East Riding of Yorkshire HU12 8EU",
    "addr:housenumber":"21",
    "addr:postcode":"hu12 8eu",
    "addr:street":"St Augustines Gate Hedon",
    "iso:country":"GB",
    "sg:address":"21 St Augustines Gate, Hedon",
    "sg:city":"Hull",
    "sg:classifiers":[
        {
            "category":"Real Estate",
            "subcategory":"Real Estate Agent",
            "type":"Services"
        }
    ],
    "sg:phone":"+44 1482 897129",
    "sg:postcode":"HU12 8EU",
    "sg:province":"East Riding of Yorkshire",
    "wof:name":"John P Dennis & Son Ltd.",
    "wof:placetype":"venue"
},
  "geometry": {"coordinates":[-0.1990640014,53.7404060364],"type":"Point"}
}