{
  "type": "Feature",
  "properties": {
    "addr:full":"436 Mosspark Boulevard Glasgow Glasgow City G52 1HX",
    "addr:housenumber":"436",
    "addr:postcode":"g52 1hx",
    "addr:street":"Mosspark Boulevard",
    "iso:country":"GB",
    "sg:address":"436 Mosspark Boulevard",
    "sg:city":"Glasgow",
    "sg:classifiers":[
        {
            "category":"Health Services",
            "subcategory":"Doctor",
            "type":"Services"
        }
    ],
    "sg:phone":"+44 141 882 5494",
    "sg:postcode":"G52 1HX",
    "sg:province":"Glasgow City",
    "sg:tags":[
        "practitioners"
    ],
    "wof:name":"Finney, A",
    "wof:placetype":"venue"
},
  "geometry": {"coordinates":[-4.32932,55.844131],"type":"Point"}
}