{
  "type": "Feature",
  "properties": {
    "iso:country":"GB",
    "sg:address":"Hurdles Priorsfield Road",
    "sg:city":"Godalming",
    "sg:classifiers":[
        {
            "category":"Professional",
            "subcategory":"Accounting & Tax Preparation",
            "type":"Services"
        }
    ],
    "sg:phone":"+44 1483 810334",
    "sg:postcode":"GU7 2RQ",
    "sg:province":"Surrey",
    "sg:tags":[
        "consultant"
    ],
    "wof:name":"Eurotax Consultants Ltd.",
    "wof:placetype":"venue"
},
  "geometry": {"coordinates":[-0.6421589851,51.2096099854],"type":"Point"}
}