{
  "type": "Feature",
  "properties": {
    "addr:full":"190 Eaves La Chorley Lancashire PR6 0AU",
    "addr:housenumber":"190",
    "addr:postcode":"pr6 0au",
    "addr:street":"Eaves La Chorley",
    "iso:country":"GB",
    "sg:address":"190 Eaves La",
    "sg:city":"Chorley",
    "sg:classifiers":[
        {
            "category":"Shopping",
            "subcategory":"Bicycles & Sporting Goods",
            "type":"Retail Goods"
        }
    ],
    "sg:phone":"+44 1257 415002",
    "sg:postcode":"PR6 0AU",
    "sg:province":"Lancashire",
    "sg:tags":[
        "cycle",
        "accessory"
    ],
    "wof:name":"Cycle Shack The",
    "wof:placetype":"venue"
},
  "geometry": {"coordinates":[-2.6189980507,53.6569213867],"type":"Point"}
}