{
  "type": "Feature",
  "properties": {
    "iso:country":"GB",
    "sg:address":"78 Telford Rd, Cumbernauld",
    "sg:city":"Glasgow",
    "sg:classifiers":[
        {
            "category":"Manufacturing",
            "subcategory":"Metals",
            "type":"Manufacturing & Wholesale Goods"
        }
    ],
    "sg:postcode":"G67 2NJ",
    "sg:province":"Falkirk",
    "sg:tags":[
        "work",
        "sheet"
    ],
    "wof:name":"A & B Metal Fabrications Ltd",
    "wof:placetype":"venue"
},
  "geometry": {"coordinates":[-3.9838349819,55.9401016235],"type":"Point"}
}