{
  "type": "Feature",
  "properties": {
    "iso:country":"GB",
    "sg:address":"50 Wallasey Village",
    "sg:city":"Wallasey",
    "sg:classifiers":[
        {
            "category":"Health Services",
            "subcategory":"Doctor",
            "type":"Services"
        }
    ],
    "sg:phone":"+44 151 691 2088",
    "sg:postcode":"L45 3LQ",
    "sg:province":"Merseyside",
    "sg:tags":[
        "practitioners"
    ],
    "wof:name":"Swift, N D",
    "wof:placetype":"venue"
},
  "geometry": {"coordinates":[-3.065079,53.423382],"type":"Point"}
}