{
  "type": "Feature",
  "properties": {
    "addr:full":"2 Manor Cotts, Manor Road, Wickhamford Evesham Gloucestershire WR11 7SA",
    "addr:housenumber":"2",
    "addr:postcode":"wr11 7sa",
    "addr:street":"Manor Cotts Manor Road",
    "iso:country":"GB",
    "sg:address":"2 Manor Cotts, Manor Road, Wickhamford",
    "sg:city":"Evesham",
    "sg:classifiers":[
        {
            "category":"Military Area",
            "subcategory":"Air Force Base",
            "type":"Public Place"
        }
    ],
    "sg:postcode":"WR11 7SA",
    "sg:province":"Gloucestershire",
    "sg:tags":[
        "taxi",
        "hire",
        "private"
    ],
    "wof:name":"Manor Cottage Guest House",
    "wof:placetype":"venue"
},
  "geometry": {"coordinates":[-1.9030729532,52.0694313049],"type":"Point"}
}