{
  "type": "Feature",
  "properties": {
    "addr:full":"126 Caldmore Rd Walsall West Midlands WS1 3RF",
    "addr:housenumber":"126",
    "addr:postcode":"ws1 3rf",
    "addr:street":"Caldmore Rd",
    "iso:country":"GB",
    "sg:address":"126 Caldmore Rd",
    "sg:city":"Walsall",
    "sg:classifiers":[
        {
            "category":"Shopping",
            "subcategory":"Books",
            "type":"Retail Goods"
        }
    ],
    "sg:postcode":"WS1 3RF",
    "sg:province":"West Midlands",
    "sg:tags":[
        "bookseller"
    ],
    "wof:name":"Latif,Mohammed,",
    "wof:placetype":"venue"
},
  "geometry": {"coordinates":[-1.9820899963,52.5776367188],"type":"Point"}
}