{
  "type": "Feature",
  "properties": {
    "iso:country":"GB",
    "sg:address":"17 Kensington Park Road",
    "sg:city":"London",
    "sg:classifiers":[
        {
            "category":"Communications",
            "type":"Services"
        }
    ],
    "sg:phone":"+44 20 7229 8427",
    "sg:postcode":"W11 2EU",
    "sg:province":"Greater London",
    "sg:tags":[
        "broadcasting"
    ],
    "wof:name":"Robot Television Network Ltd.",
    "wof:placetype":"venue"
},
  "geometry": {"coordinates":[-0.2056369931,51.5149459839],"type":"Point"}
}