{
  "type": "Feature",
  "properties": {
    "addr:full":"97 Tithebarn Road Southport Lancashire PR8 6AG",
    "addr:housenumber":"97",
    "addr:postcode":"pr8 6ag",
    "addr:street":"Tithebarn Road",
    "iso:country":"GB",
    "sg:address":"97 Tithebarn Road",
    "sg:city":"Southport",
    "sg:classifiers":[
        {
            "category":"Manufacturing",
            "subcategory":"Tools & Machinery",
            "type":"Manufacturing & Wholesale Goods"
        }
    ],
    "sg:phone":"+44 1704 546161",
    "sg:postcode":"PR8 6AG",
    "sg:province":"Lancashire",
    "sg:tags":[
        "monitoring",
        "temperature",
        "thermometer"
    ],
    "wof:name":"Sensing Devices Ltd.",
    "wof:placetype":"venue"
},
  "geometry": {"coordinates":[-2.981141,53.645584],"type":"Point"}
}