{
  "type": "Feature",
  "properties": {
    "addr:full":"Avenue Road Broseley Shropshire TF12 5DL",
    "addr:postcode":"tf12 5dl",
    "addr:street":"Avenue Road",
    "iso:country":"GB",
    "sg:address":"Avenue Road",
    "sg:city":"Broseley",
    "sg:classifiers":[
        {
            "category":"Bars & Pubs",
            "type":"Food & Drink"
        }
    ],
    "sg:phone":"+44 1952 884088",
    "sg:postcode":"TF12 5DL",
    "sg:province":"Shropshire",
    "sg:tags":[
        "pubs",
        "inn"
    ],
    "wof:name":"Angela Hammond",
    "wof:placetype":"venue"
},
  "geometry": {"coordinates":[-2.47634,52.607868],"type":"Point"}
}