{
  "type": "Feature",
  "properties": {
    "addr:full":"Birchfield House Ifield Road, Charlwood Horley Surrey RH6 0DR",
    "addr:postcode":"rh6 0dr",
    "addr:street":"Ifield Road",
    "iso:country":"GB",
    "sg:address":"Birchfield House Ifield Road, Charlwood",
    "sg:city":"Horley",
    "sg:classifiers":[
        {
            "category":"Freight",
            "type":"Transportation"
        }
    ],
    "sg:phone":"+44 1293 825835",
    "sg:postcode":"RH6 0DR",
    "sg:province":"Surrey",
    "sg:tags":[
        "forwarders"
    ],
    "wof:name":"Sayva Trek Ltd.",
    "wof:placetype":"venue"
},
  "geometry": {"coordinates":[-0.224629,51.154335],"type":"Point"}
}