{
  "type": "Feature",
  "properties": {
    "iso:country":"GB",
    "sg:address":"Unit 2 Cockerell Close, Segensworth West",
    "sg:city":"Fareham",
    "sg:classifiers":[
        {
            "category":"Manufacturing",
            "subcategory":"Glass & Minerals",
            "type":"Manufacturing & Wholesale Goods"
        }
    ],
    "sg:phone":"+44 1489 589838",
    "sg:postcode":"PO15 5SR",
    "sg:province":"Hampshire",
    "sg:tags":[
        "fibre",
        "material"
    ],
    "wof:name":"Scott Bader Co. Ltd.",
    "wof:placetype":"venue"
},
  "geometry": {"coordinates":[-1.2597939968,50.8729286194],"type":"Point"}
}