{
  "type": "Feature",
  "properties": {
    "iso:country":"GB",
    "sg:address":"Hull Rd, Coniston",
    "sg:city":"Hull",
    "sg:classifiers":[
        {
            "category":"Bars & Pubs",
            "type":"Food & Drink"
        }
    ],
    "sg:postcode":"HU11 5AE",
    "sg:province":"East Riding of Yorkshire",
    "sg:tags":[
        "pubs",
        "inn"
    ],
    "wof:name":"Gardeners Arms",
    "wof:placetype":"venue"
},
  "geometry": {"coordinates":[-0.25092,53.821884],"type":"Point"}
}