{
  "type": "Feature",
  "properties": {
    "addr:full":"71 Yewfield Road, Willesdon London Greater London NW10 9TD",
    "addr:housenumber":"71",
    "addr:postcode":"nw10 9td",
    "addr:street":"Yewfield Road",
    "iso:country":"GB",
    "sg:address":"71 Yewfield Road, Willesdon",
    "sg:city":"London",
    "sg:classifiers":[
        {
            "category":"Building & Trades",
            "subcategory":"Equipment Rental",
            "type":"Services"
        }
    ],
    "sg:postcode":"NW10 9TD",
    "sg:province":"Greater London",
    "sg:tags":[
        "hire",
        "centre"
    ],
    "wof:name":"Shah Enterprises Ltd",
    "wof:placetype":"venue"
},
  "geometry": {"coordinates":[-0.2454899997,51.5470924377],"type":"Point"}
}