{
  "type": "Feature",
  "properties": {
    "addr:full":"Unit 8, Berry Hill Road, Fenton Stoke-on-trent Staffordshire ST4 2NL",
    "addr:housenumber":"unit 8",
    "addr:postcode":"staffordshire st4 2nl",
    "addr:street":"Berry Hill Road",
    "iso:country":"GB",
    "sg:address":"Unit 8, Berry Hill Road, Fenton",
    "sg:city":"Stoke-on-trent",
    "sg:classifiers":[
        {
            "category":"Bars & Pubs",
            "subcategory":"Wine Bar",
            "type":"Food & Drink"
        }
    ],
    "sg:phone":"+44 1782 285700",
    "sg:postcode":"ST4 2NL",
    "sg:province":"Staffordshire",
    "sg:tags":[
        "industrial",
        "aerosol"
    ],
    "wof:name":"Aerosol & Fluid Technology Ltd.",
    "wof:placetype":"venue"
},
  "geometry": {"coordinates":[-2.166092,53.013199],"type":"Point"}
}