{
  "type": "Feature",
  "properties": {
    "iso:country":"GB",
    "sg:address":"55-57 Ravensdale Road",
    "sg:city":"London",
    "sg:classifiers":[
        {
            "category":"Organizations",
            "subcategory":"Religious Organization",
            "type":"Services"
        }
    ],
    "sg:phone":"+44 20 8809 4256",
    "sg:postcode":"N16 6TJ",
    "sg:province":"Greater London",
    "sg:tags":[
        "organisation",
        "place",
        "worship"
    ],
    "wof:name":"Northwold Road Synagogue",
    "wof:placetype":"venue"
},
  "geometry": {"coordinates":[-0.0689349994,51.5751838684],"type":"Point"}
}