{
  "type": "Feature",
  "properties": {
    "addr:full":"1 Cardiff Road, Creigiau Cardiff Caerphilly CF15 9NL",
    "addr:housenumber":"1",
    "addr:postcode":"cf15 9nl",
    "addr:street":"Cardiff Road Creigiau",
    "iso:country":"GB",
    "sg:address":"1 Cardiff Road, Creigiau",
    "sg:city":"Cardiff",
    "sg:classifiers":[
        {
            "category":"Autos & Motor Vehicles",
            "subcategory":"Fuel & Gas Station",
            "type":"Retail Goods"
        }
    ],
    "sg:phone":"+44 29 2089 2100",
    "sg:postcode":"CF15 9NL",
    "sg:province":"Caerphilly",
    "sg:tags":[
        "petrol",
        "filling"
    ],
    "wof:name":"Creigiau Motors",
    "wof:placetype":"venue"
},
  "geometry": {"coordinates":[-3.321144,51.520977],"type":"Point"}
}