{
  "type": "Feature",
  "properties": {
    "addr:full":"100 Edge Hill, Panteland Newcastle-upon-tyne Northumberland NE20 9JQ",
    "addr:housenumber":"100",
    "addr:postcode":"ne20 9jq",
    "addr:street":"Edge;Panteland",
    "iso:country":"GB",
    "sg:address":"100 Edge Hill, Panteland",
    "sg:city":"Newcastle-upon-tyne",
    "sg:classifiers":[
        {
            "category":"Professional",
            "subcategory":"Engineering",
            "type":"Services"
        }
    ],
    "sg:phone":"+44 1661 822266",
    "sg:postcode":"NE20 9JQ",
    "sg:province":"Northumberland",
    "sg:tags":[
        "contractor",
        "electrical",
        "engineer"
    ],
    "wof:name":"W S Arrowsmith & Son",
    "wof:placetype":"venue"
},
  "geometry": {"coordinates":[-1.7658840418,55.0280303955],"type":"Point"}
}