{
  "type": "Feature",
  "properties": {
    "iso:country":"GB",
    "sg:address":"4 The Parade, Colchester Road, Harold Park",
    "sg:city":"Romford",
    "sg:classifiers":[
        {
            "category":"Home & Garden",
            "subcategory":"Hardware",
            "type":"Retail Goods"
        }
    ],
    "sg:phone":"+44 1708 374500",
    "sg:postcode":"RM3 0AQ",
    "sg:province":"Essex",
    "sg:tags":[
        "part",
        "accessory"
    ],
    "wof:name":"Mayland Motorcycles Ltd.",
    "wof:placetype":"venue"
},
  "geometry": {"coordinates":[0.242013,51.60104],"type":"Point"}
}