{
  "type": "Feature",
  "properties": {
    "iso:country":"GB",
    "sg:address":"670 Pollokshaws Road",
    "sg:city":"Glasgow",
    "sg:classifiers":[
        {
            "category":"Home & Garden",
            "subcategory":"Household Appliances",
            "type":"Retail Goods"
        }
    ],
    "sg:phone":"+44 141 423 6020",
    "sg:postcode":"G41 2QE",
    "sg:province":"Glasgow City",
    "sg:tags":[
        "electrical",
        "domestic"
    ],
    "wof:name":"Audio Vision Centre",
    "wof:placetype":"venue"
},
  "geometry": {"coordinates":[-4.26893,55.83773],"type":"Point"}
}