{
  "type": "Feature",
  "properties": {
    "iso:country":"GB",
    "sg:address":"41-43 Poole Hill",
    "sg:city":"Bournemouth",
    "sg:classifiers":[
        {
            "category":"Autos & Motor Vehicles",
            "subcategory":"Automobile Sales",
            "type":"Retail Goods"
        }
    ],
    "sg:phone":"+44 1202 780743",
    "sg:postcode":"BH2 5PW",
    "sg:province":"Dorset",
    "sg:tags":[
        "car"
    ],
    "wof:name":"Westcliffe Motors",
    "wof:placetype":"venue"
},
  "geometry": {"coordinates":[-1.8880039454,50.7196655273],"type":"Point"}
}