{
  "type": "Feature",
  "properties": {
    "iso:country":"GB",
    "sg:address":"20 Nursery Hollow",
    "sg:city":"Ilkeston",
    "sg:classifiers":[
        {
            "category":"Professional",
            "subcategory":"Accounting & Tax Preparation",
            "type":"Services"
        }
    ],
    "sg:phone":"+44 115 930 3802",
    "sg:postcode":"DE7 4LQ",
    "sg:province":"Derbyshire",
    "sg:tags":[
        "accountant"
    ],
    "wof:name":"J L Attewell",
    "wof:placetype":"venue"
},
  "geometry": {"coordinates":[-1.3095289469,52.9621887207],"type":"Point"}
}