{
  "type": "Feature",
  "properties": {
    "iso:country":"GB",
    "sg:address":"257 Battle Road",
    "sg:city":"St Leonards-on-sea",
    "sg:classifiers":[
        {
            "category":"Shopping",
            "type":"Retail Goods"
        }
    ],
    "sg:postcode":"TN37 7AN",
    "sg:province":"East Sussex",
    "sg:tags":[
        "part",
        "accessory"
    ],
    "wof:name":"Roadhog",
    "wof:placetype":"venue"
},
  "geometry": {"coordinates":[0.5518,50.875416],"type":"Point"}
}