{
  "type": "Feature",
  "properties": {
    "iso:country":"GB",
    "sg:address":"Kexwith, Marske",
    "sg:city":"Richmond",
    "sg:classifiers":[
        {
            "category":"Farming",
            "subcategory":"Livestock Farm",
            "type":"Manufacturing & Wholesale Goods"
        }
    ],
    "sg:phone":"+44 1833 621449",
    "sg:postcode":"DL11 7EG",
    "sg:province":"Durham",
    "sg:tags":[
        "others"
    ],
    "wof:name":"R K Ridley",
    "wof:placetype":"venue"
},
  "geometry": {"coordinates":[-1.8290389776,54.3857460022],"type":"Point"}
}