{
  "type": "Feature",
  "properties": {
    "addr:full":"155 Indoor Market Hall, Bull Ring Birmingham West Midlands B5 4PN",
    "addr:postcode":"b5 4pn",
    "addr:street":"Bull Ring",
    "iso:country":"GB",
    "sg:address":"155 Indoor Market Hall, Bull Ring",
    "sg:city":"Birmingham",
    "sg:classifiers":[
        {
            "category":"Shopping",
            "subcategory":"Beauty & Cosmetics",
            "type":"Retail Goods"
        }
    ],
    "sg:phone":"+44 121 643 6867",
    "sg:postcode":"B5 4PN",
    "sg:province":"West Midlands",
    "sg:tags":[
        "wig",
        "hairpiece"
    ],
    "wof:name":"Maria's Wigs",
    "wof:placetype":"venue"
},
  "geometry": {"coordinates":[-1.8983000517,52.4758110046],"type":"Point"}
}