{
  "type": "Feature",
  "properties": {
    "iso:country":"GB",
    "sg:address":"Turnberry House, Main Road, Elvaston",
    "sg:city":"Derby",
    "sg:classifiers":[
        {
            "category":"Travel",
            "subcategory":"Hotels & Motels",
            "type":"Entertainment"
        },
        {
            "category":"Recreation",
            "subcategory":"Campground",
            "type":"Entertainment"
        }
    ],
    "sg:postcode":"DE72 3EQ",
    "sg:province":"Derbyshire",
    "sg:tags":[
        "self",
        "site",
        "camping",
        "catering"
    ],
    "wof:name":"Turnberry House Caravan Park",
    "wof:placetype":"venue"
},
  "geometry": {"coordinates":[-1.390232,52.889778],"type":"Point"}
}