{
  "type": "Feature",
  "properties": {
    "iso:country":"GB",
    "sg:address":"636b Green Lanes",
    "sg:city":"Hornsey",
    "sg:classifiers":[
        {
            "category":"Health Services",
            "subcategory":"Dentist",
            "type":"Services"
        }
    ],
    "sg:phone":"+44 20 8889 1439",
    "sg:postcode":"N8 0SD",
    "sg:province":"Greater London",
    "wof:name":"H.I Adali",
    "wof:placetype":"venue"
},
  "geometry": {"coordinates":[-0.1003659964,51.5857467651],"type":"Point"}
}