{
  "type": "Feature",
  "properties": {
    "iso:country":"GB",
    "sg:address":"The Boot Hole, 82 South Street",
    "sg:city":"Dorking",
    "sg:classifiers":[
        {
            "category":"Professional",
            "subcategory":"Printing & Photocopies",
            "type":"Services"
        },
        {
            "category":"Shopping",
            "subcategory":"Shoes",
            "type":"Retail Goods"
        }
    ],
    "sg:phone":"+44 1306 884960",
    "sg:postcode":"RH4 2HD",
    "sg:province":"Surrey",
    "sg:tags":[
        "engraving",
        "engraver"
    ],
    "wof:name":"Engraving By Karen",
    "wof:placetype":"venue"
},
  "geometry": {"coordinates":[-0.3288139999,51.233341217],"type":"Point"}
}