{
  "type": "Feature",
  "properties": {
    "iso:country":"GB",
    "sg:address":"7 Station Buildings, Birmingham Road, Water Orton",
    "sg:city":"Birmingham",
    "sg:classifiers":[
        {
            "category":"Manufacturing",
            "subcategory":"Tools & Machinery",
            "type":"Manufacturing & Wholesale Goods"
        }
    ],
    "sg:postcode":"B46 1SR",
    "sg:province":"Warwickshire",
    "sg:tags":[
        "society",
        "friendly"
    ],
    "wof:name":"Waterloo Insurance Services Ltd.",
    "wof:placetype":"venue"
},
  "geometry": {"coordinates":[-1.737806,52.517654],"type":"Point"}
}