{
  "type": "Feature",
  "properties": {
    "iso:country":"GB",
    "sg:address":"Blandford House, Church Walk, Combe",
    "sg:city":"Witney",
    "sg:classifiers":[
        {
            "category":"Professional",
            "subcategory":"Accounting & Tax Preparation",
            "type":"Services"
        }
    ],
    "sg:postcode":"OX29 8NQ",
    "sg:province":"Oxfordshire",
    "sg:tags":[
        "accountant"
    ],
    "wof:name":"Tadmans",
    "wof:placetype":"venue"
},
  "geometry": {"coordinates":[-1.403484,51.843609],"type":"Point"}
}