{
  "type": "Feature",
  "properties": {
    "addr:full":"38 West Street Berwick-upon-tweed Northumberland TD15 1AS",
    "addr:housenumber":"38",
    "addr:postcode":"td15 1as",
    "addr:street":"West Street;Northumberland",
    "iso:country":"GB",
    "sg:address":"38 West Street",
    "sg:city":"Berwick-upon-tweed",
    "sg:classifiers":[
        {
            "category":"Shopping",
            "subcategory":"Discount & Variety Stores",
            "type":"Retail Goods"
        }
    ],
    "sg:postcode":"TD15 1AS",
    "sg:province":"Northumberland",
    "sg:tags":[
        "surplus"
    ],
    "wof:name":"Government Surplus Store",
    "wof:placetype":"venue"
},
  "geometry": {"coordinates":[-2.004923,55.769512],"type":"Point"}
}