{
  "type": "Feature",
  "properties": {
    "iso:country":"GB",
    "sg:address":"45 Admiralty St, Stonehouse",
    "sg:city":"Plymouth",
    "sg:classifiers":[
        {
            "category":"Retail",
            "subcategory":"Auto Repair",
            "type":"Services"
        }
    ],
    "sg:phone":"+44 1752 227789",
    "sg:postcode":"PL1 3RU",
    "sg:province":"Devon",
    "sg:tags":[
        "car",
        "upholsterer"
    ],
    "wof:name":"Classic & Sports Car Interiors",
    "wof:placetype":"venue"
},
  "geometry": {"coordinates":[-4.1605792046,50.3646621704],"type":"Point"}
}