{
  "type": "Feature",
  "properties": {
    "addr:full":"Old Acres, Station Lane Newark Nottinghamshire NG22 8LB",
    "addr:postcode":"ng22 8lb",
    "addr:street":"Old;Station Lane",
    "iso:country":"GB",
    "sg:address":"Old Acres, Station Lane",
    "sg:city":"Newark",
    "sg:classifiers":[
        {
            "category":"Shopping",
            "subcategory":"Pharmacy",
            "type":"Retail Goods"
        }
    ],
    "sg:postcode":"NG22 8LB",
    "sg:province":"Nottinghamshire",
    "sg:tags":[
        "medicine",
        "therapy"
    ],
    "wof:name":"Lifesource Ltd.",
    "wof:placetype":"venue"
},
  "geometry": {"coordinates":[-1.0404100418,53.1074485779],"type":"Point"}
}