{
  "type": "Feature",
  "properties": {
    "iso:country":"GB",
    "sg:address":"Unit 2 Montgomery Road, Wath Upon Dearne",
    "sg:city":"Rotherham",
    "sg:classifiers":[
        {
            "category":"Deli",
            "type":"Food & Drink"
        }
    ],
    "sg:phone":"+44 1709 878606",
    "sg:postcode":"S63 7QP",
    "sg:province":"South Yorkshire",
    "sg:tags":[
        "delicatessen"
    ],
    "wof:name":"Pastures Green",
    "wof:placetype":"venue"
},
  "geometry": {"coordinates":[-1.346544,53.503216],"type":"Point"}
}