{
  "type": "Feature",
  "properties": {
    "addr:full":"98 Grove Lane, Headingley Leeds West Yorkshire LS6 2BG",
    "addr:housenumber":"98",
    "addr:postcode":"ls6 2bg",
    "addr:street":"Grove Lane",
    "iso:country":"GB",
    "sg:address":"98 Grove Lane, Headingley",
    "sg:city":"Leeds",
    "sg:classifiers":[
        {
            "category":"Professional",
            "subcategory":"Accounting & Tax Preparation",
            "type":"Services"
        }
    ],
    "sg:phone":"+44 113 278 7900",
    "sg:postcode":"LS6 2BG",
    "sg:province":"West Yorkshire",
    "sg:tags":[
        "accountant"
    ],
    "wof:name":"K S Cooper",
    "wof:placetype":"venue"
},
  "geometry": {"coordinates":[-1.5697989464,53.8239097595],"type":"Point"}
}