{
  "type": "Feature",
  "properties": {
    "addr:full":"Unit 216 Springvale Indust Est Cwmbran Monmouthshire NP44 5BE",
    "addr:housenumber":"216",
    "addr:postcode":"np44 5be",
    "addr:street":"Springvale Indust Est",
    "iso:country":"GB",
    "sg:address":"Unit 216 Springvale Indust Est",
    "sg:city":"Cwmbran",
    "sg:classifiers":[
        {
            "category":"Personal",
            "type":"Services"
        }
    ],
    "sg:phone":"+44 1633 871155",
    "sg:postcode":"NP44 5BE",
    "sg:province":"Monmouthshire",
    "sg:tags":[
        "delivery"
    ],
    "wof:name":"Target Worldwide Express",
    "wof:placetype":"venue"
},
  "geometry": {"coordinates":[-3.0367639065,51.656703949],"type":"Point"}
}