{
  "type": "Feature",
  "properties": {
    "addr:full":"Manor Farm, Goadby Leicester Leicestershire LE7 9EE",
    "addr:housenumber":"goadby",
    "addr:postcode":"le7 9ee",
    "addr:street":"Manor",
    "iso:country":"GB",
    "sg:address":"Manor Farm, Goadby",
    "sg:city":"Leicester",
    "sg:classifiers":[
        {
            "category":"Farming",
            "subcategory":"Livestock Farm",
            "type":"Manufacturing & Wholesale Goods"
        }
    ],
    "sg:postcode":"LE7 9EE",
    "sg:province":"Leicestershire",
    "sg:tags":[
        "others"
    ],
    "wof:name":"Sidney Michael Toone",
    "wof:placetype":"venue"
},
  "geometry": {"coordinates":[-0.8933529854,52.5864028931],"type":"Point"}
}