{
  "type": "Feature",
  "properties": {
    "addr:full":"3 Castlehythe Ely Cambridgeshire CB7 4BU",
    "addr:housenumber":"3",
    "addr:postcode":"cb7 4bu",
    "addr:street":"Castlehythe Ely",
    "iso:country":"GB",
    "sg:address":"3 Castlehythe",
    "sg:city":"Ely",
    "sg:classifiers":[
        {
            "category":"Retail",
            "subcategory":"Auto Repair",
            "type":"Services"
        }
    ],
    "sg:phone":"+44 1353 662247",
    "sg:postcode":"CB7 4BU",
    "sg:province":"Cambridgeshire",
    "sg:tags":[
        "modification",
        "garage"
    ],
    "wof:name":"St. Peter's Garage (Ely)",
    "wof:placetype":"venue"
},
  "geometry": {"coordinates":[0.2656669915,52.3937644958],"type":"Point"}
}