{
  "type": "Feature",
  "properties": {
    "addr:full":"17 Conway Road Chippenham Gloucestershire SN14 0PW",
    "addr:housenumber":"17",
    "addr:postcode":"sn14 0pw",
    "addr:street":"Conway Road",
    "iso:country":"GB",
    "sg:address":"17 Conway Road",
    "sg:city":"Chippenham",
    "sg:classifiers":[
        {
            "category":"Food & Beverages",
            "subcategory":"Supermarket",
            "type":"Retail Goods"
        }
    ],
    "sg:phone":"+44 1249 650103",
    "sg:postcode":"SN14 0PW",
    "sg:province":"Gloucestershire",
    "wof:name":"Park Stores",
    "wof:placetype":"venue"
},
  "geometry": {"coordinates":[-2.143181,51.456303],"type":"Point"}
}