{
  "type": "Feature",
  "properties": {
    "iso:country":"GB",
    "sg:address":"2 Pratt Street, Soham",
    "sg:city":"Ely",
    "sg:classifiers":[
        {
            "category":"Shopping",
            "subcategory":"Department Store",
            "type":"Retail Goods"
        },
        {
            "category":"Food & Beverages",
            "subcategory":"Groceries & Convenience Stores",
            "type":"Retail Goods"
        }
    ],
    "sg:phone":"+44 1353 720462",
    "sg:postcode":"CB7 5BH",
    "sg:province":"Cambridgeshire",
    "wof:name":"Soham Off Licence",
    "wof:placetype":"venue"
},
  "geometry": {"coordinates":[0.336861,52.335724],"type":"Point"}
}