{
  "type": "Feature",
  "properties": {
    "iso:country":"GB",
    "sg:address":"73 Bodrigan Road",
    "sg:city":"Looe",
    "sg:classifiers":[
        {
            "category":"Travel",
            "subcategory":"Hotels & Motels",
            "type":"Entertainment"
        },
        {
            "category":"Bars & Pubs",
            "subcategory":"Hookah Bar",
            "type":"Food & Drink"
        }
    ],
    "sg:phone":"+44 1503 262736",
    "sg:postcode":"PL13 1EH",
    "sg:province":"Cornwall",
    "sg:tags":[
        "self",
        "holiday",
        "catering"
    ],
    "wof:name":"Cornish Collection",
    "wof:placetype":"venue"
},
  "geometry": {"coordinates":[-4.4498071671,50.3616294861],"type":"Point"}
}