{
  "type": "Feature",
  "properties": {
    "addr:full":"23 Brougham Street Greenock Inverclyde PA16 8AB",
    "addr:housenumber":"23",
    "addr:postcode":"pa16 8ab",
    "addr:street":"Brougham Street Greenock",
    "iso:country":"GB",
    "sg:address":"23 Brougham Street",
    "sg:city":"Greenock",
    "sg:classifiers":[
        {
            "category":"Government",
            "subcategory":"Post Office",
            "type":"Public Place"
        }
    ],
    "sg:phone":"+44 1475 723510",
    "sg:postcode":"PA16 8AB",
    "sg:province":"Inverclyde",
    "wof:name":"Brougham Street Post Office",
    "wof:placetype":"venue"
},
  "geometry": {"coordinates":[-4.768065,55.954758],"type":"Point"}
}