{
  "type": "Feature",
  "properties": {
    "addr:full":"Suite 211 Marlborough House, 159 High Street Wealdstone Harrow Greater London HA3 5DX",
    "addr:housenumber":"suite 211;159",
    "addr:postcode":"ha3 5dx",
    "addr:street":"Marlborough;High Street",
    "iso:country":"GB",
    "sg:address":"Suite 211 Marlborough House, 159 High Street Wealdstone",
    "sg:city":"Harrow",
    "sg:classifiers":[
        {
            "category":"Shopping",
            "subcategory":"Clothing, Apparel, & Fashions",
            "type":"Retail Goods"
        }
    ],
    "sg:postcode":"HA3 5DX",
    "sg:province":"Greater London",
    "sg:tags":[
        "clothing",
        "fabric"
    ],
    "wof:name":"House of Fashions Ltd",
    "wof:placetype":"venue"
},
  "geometry": {"coordinates":[-0.337401,51.598225],"type":"Point"}
}