{
  "type": "Feature",
  "properties": {
    "iso:country":"GB",
    "sg:address":"1 Burnside Avenue, Easthouses",
    "sg:city":"Dalkeith",
    "sg:classifiers":[
        {
            "category":"Building & Trades",
            "subcategory":"Construction",
            "type":"Services"
        }
    ],
    "sg:phone":"+44 131 663 0028",
    "sg:postcode":"EH22 4JB",
    "sg:province":"City of Edinburgh",
    "sg:tags":[
        "dry",
        "plastering",
        "plasterers",
        "lining",
        "related",
        "screeders"
    ],
    "wof:name":"Leonard C Ewington",
    "wof:placetype":"venue"
},
  "geometry": {"coordinates":[-3.0477519035,55.8764533997],"type":"Point"}
}