{
  "type": "Feature",
  "properties": {
    "iso:country":"GB",
    "sg:address":"50 Atholl Road",
    "sg:city":"Pitlochry",
    "sg:classifiers":[
        {
            "category":"Home & Garden",
            "subcategory":"Household Appliances",
            "type":"Retail Goods"
        },
        {
            "category":"Retail",
            "subcategory":"Event Space",
            "type":"Services"
        }
    ],
    "sg:phone":"+44 1796 472760",
    "sg:postcode":"PH16 5BX",
    "sg:province":"Perth and Kinross",
    "sg:tags":[
        "electrical",
        "product",
        "domestic",
        "sales"
    ],
    "wof:name":"Ian Kemp Electrical",
    "wof:placetype":"venue"
},
  "geometry": {"coordinates":[-3.732688,56.702641],"type":"Point"}
}