{
  "type": "Feature",
  "properties": {
    "addr:full":"183 Mount Pleasant Rd Wallasey Merseyside L45 5HS",
    "addr:housenumber":"183",
    "addr:postcode":"l45 5hs",
    "addr:street":"Mount Pleasant Rd",
    "iso:country":"GB",
    "sg:address":"183 Mount Pleasant Rd",
    "sg:city":"Wallasey",
    "sg:classifiers":[
        {
            "category":"Building & Trades",
            "subcategory":"Cleaning & Sanitation",
            "type":"Services"
        }
    ],
    "sg:phone":"+44 151 639 9916",
    "sg:postcode":"L45 5HS",
    "sg:province":"Merseyside",
    "sg:tags":[
        "steam"
    ],
    "wof:name":"B I C S Industrial Cleaning Services",
    "wof:placetype":"venue"
},
  "geometry": {"coordinates":[-3.050755024,53.4289054871],"type":"Point"}
}