{
  "type": "Feature",
  "properties": {
    "iso:country":"GB",
    "sg:address":"7 The Parade",
    "sg:city":"Leamington Spa",
    "sg:classifiers":[
        {
            "category":"Arts & Performance",
            "subcategory":"Art Gallery",
            "type":"Entertainment"
        }
    ],
    "sg:postcode":"CV32 7LS",
    "sg:province":"Warwickshire",
    "wof:name":"Edward Fitzpatrick",
    "wof:placetype":"venue"
},
  "geometry": {"coordinates":[-1.510065,52.300762],"type":"Point"}
}