{
  "type": "Feature",
  "properties": {
    "addr:full":"237 Croydon Road Beckenham Kent BR3 3PT",
    "addr:housenumber":"237",
    "addr:postcode":"br3 3pt",
    "addr:street":"Croydon Road",
    "iso:country":"GB",
    "sg:address":"237 Croydon Road",
    "sg:city":"Beckenham",
    "sg:classifiers":[
        {
            "category":"Autos & Motor Vehicles",
            "subcategory":"Automobile Sales",
            "type":"Retail Goods"
        }
    ],
    "sg:phone":"+44 20 8658 0191",
    "sg:postcode":"BR3 3PT",
    "sg:province":"Kent",
    "sg:tags":[
        "car"
    ],
    "wof:name":"S G Smith (Motors) Beckenham",
    "wof:placetype":"venue"
},
  "geometry": {"coordinates":[-0.0339189991,51.4055099487],"type":"Point"}
}