{
  "type": "Feature",
  "properties": {
    "iso:country":"GB",
    "sg:address":"27 Roxy Av",
    "sg:city":"Romford",
    "sg:classifiers":[
        {
            "category":"Building & Trades",
            "subcategory":"Construction",
            "type":"Services"
        }
    ],
    "sg:phone":"+44 7831 132427",
    "sg:postcode":"RM6 4AW",
    "sg:province":"Essex",
    "sg:tags":[
        "builder"
    ],
    "wof:name":"S D Brown",
    "wof:placetype":"venue"
},
  "geometry": {"coordinates":[0.122711,51.571247],"type":"Point"}
}