{
  "type": "Feature",
  "properties": {
    "addr:full":"18-22 Bridge Street Manchester Greater Manchester M3 3DS",
    "addr:housenumber":"18-22",
    "addr:postcode":"m3 3ds",
    "addr:street":"Bridge Street",
    "iso:country":"GB",
    "sg:address":"18-22 Bridge Street",
    "sg:city":"Manchester",
    "sg:classifiers":[
        {
            "category":"Personal",
            "subcategory":"Beauty Salon",
            "type":"Services"
        }
    ],
    "sg:phone":"+44 161 832 5025",
    "sg:postcode":"M3 3DS",
    "sg:province":"Greater Manchester",
    "sg:tags":[
        "unisex",
        "hairdresser"
    ],
    "wof:name":"The New Figaro",
    "wof:placetype":"venue"
},
  "geometry": {"coordinates":[-2.250109,53.479568],"type":"Point"}
}