{
  "type": "Feature",
  "properties": {
    "addr:full":"4 Silver Street Cirencester Gloucestershire GL7 2BL",
    "addr:housenumber":"4",
    "addr:postcode":"gl7 2bl",
    "addr:street":"Silver Street",
    "iso:country":"GB",
    "sg:address":"4 Silver Street",
    "sg:city":"Cirencester",
    "sg:classifiers":[
        {
            "category":"Real Estate",
            "subcategory":"Architect",
            "type":"Services"
        }
    ],
    "sg:phone":"+44 1285 644460",
    "sg:postcode":"GL7 2BL",
    "sg:province":"Gloucestershire",
    "sg:tags":[
        "architectural"
    ],
    "wof:name":"Abberley Design",
    "wof:placetype":"venue"
},
  "geometry": {"coordinates":[-1.9695370197,51.7168731689],"type":"Point"}
}