{
  "type": "Feature",
  "properties": {
    "addr:full":"Tudmore Cottage, South Cerney Cirencester Gloucestershire GL7 6DA",
    "addr:postcode":"gl7 6da",
    "iso:country":"GB",
    "sg:address":"Tudmore Cottage, South Cerney",
    "sg:city":"Cirencester",
    "sg:classifiers":[
        {
            "category":"Building & Trades",
            "subcategory":"Construction",
            "type":"Services"
        }
    ],
    "sg:phone":"+44 7836 248651",
    "sg:postcode":"GL7 6DA",
    "sg:province":"Gloucestershire",
    "sg:tags":[
        "builder"
    ],
    "wof:name":"Clive Chick Building Consultants",
    "wof:placetype":"venue"
},
  "geometry": {"coordinates":[-1.9535410404,51.718547821],"type":"Point"}
}