{
  "type": "Feature",
  "properties": {
    "addr:full":"4 The Square, Magor Caldicot Monmouthshire NP26 3HY",
    "addr:housenumber":"4",
    "addr:postcode":"np26 3hy",
    "addr:street":"The Square",
    "iso:country":"GB",
    "sg:address":"4 The Square, Magor",
    "sg:city":"Caldicot",
    "sg:classifiers":[
        {
            "category":"Professional",
            "subcategory":"Management & Consulting",
            "type":"Services"
        }
    ],
    "sg:postcode":"NP26 3HY",
    "sg:province":"Monmouthshire",
    "sg:tags":[
        "consultant",
        "business"
    ],
    "wof:name":"Aydon Consultants Ltd.",
    "wof:placetype":"venue"
},
  "geometry": {"coordinates":[-2.8311800957,51.579990387],"type":"Point"}
}