{
  "type": "Feature",
  "properties": {
    "addr:full":"40 High Street Downham Market Cambridgeshire PE38 9HF",
    "addr:housenumber":"40",
    "addr:postcode":"pe38 9hf",
    "addr:street":"High Street",
    "iso:country":"GB",
    "sg:address":"40 High Street",
    "sg:city":"Downham Market",
    "sg:classifiers":[
        {
            "category":"Shopping",
            "subcategory":"Shoes",
            "type":"Retail Goods"
        }
    ],
    "sg:phone":"+44 1366 384926",
    "sg:postcode":"PE38 9HF",
    "sg:province":"Cambridgeshire",
    "sg:tags":[
        "shop"
    ],
    "wof:name":"D Steer",
    "wof:placetype":"venue"
},
  "geometry": {"coordinates":[0.3783310056,52.6032371521],"type":"Point"}
}