{
  "type": "Feature",
  "properties": {
    "iso:country":"GB",
    "sg:address":"Unit 3b Moss Mill, Woodbine St East",
    "sg:city":"Rochdale",
    "sg:classifiers":[
        {
            "category":"Shopping",
            "subcategory":"Clothing, Apparel, & Fashions",
            "type":"Retail Goods"
        }
    ],
    "sg:phone":"+44 1706 715512",
    "sg:postcode":"OL16 5LB",
    "sg:province":"Lancashire",
    "sg:tags":[
        "clothing",
        "fabric"
    ],
    "wof:name":"H M Clothing Co.",
    "wof:placetype":"venue"
},
  "geometry": {"coordinates":[-2.1392390728,53.6077804565],"type":"Point"}
}