{
  "type": "Feature",
  "properties": {
    "addr:full":"110 Leyland Road Southport Lancashire PR9 0JG",
    "addr:housenumber":"110",
    "addr:postcode":"pr9 0jg",
    "addr:street":"Leyland Road",
    "iso:country":"GB",
    "sg:address":"110 Leyland Road",
    "sg:city":"Southport",
    "sg:classifiers":[
        {
            "category":"Travel",
            "subcategory":"Hotels & Motels",
            "type":"Entertainment"
        }
    ],
    "sg:phone":"+44 1704 535554",
    "sg:postcode":"PR9 0JG",
    "sg:province":"Lancashire",
    "wof:name":"Gables Private Hotel",
    "wof:placetype":"venue"
},
  "geometry": {"coordinates":[-2.9969420433,53.6575546265],"type":"Point"}
}