{
  "type": "Feature",
  "properties": {
    "addr:full":"Breach Lane, Newington Sittingbourne Kent ME9 7PE",
    "addr:postcode":"me9 7pe",
    "addr:street":"Breach Lane",
    "iso:country":"GB",
    "sg:address":"Breach Lane, Newington",
    "sg:city":"Sittingbourne",
    "sg:classifiers":[
        {
            "category":"Manufacturing",
            "subcategory":"Wood Products",
            "type":"Manufacturing & Wholesale Goods"
        }
    ],
    "sg:phone":"+44 1795 844232",
    "sg:postcode":"ME9 7PE",
    "sg:province":"Kent",
    "sg:tags":[
        "packaging",
        "crate",
        "pallets"
    ],
    "wof:name":"Newington Foods Ltd.",
    "wof:placetype":"venue"
},
  "geometry": {"coordinates":[0.6662920117,51.3522071838],"type":"Point"}
}