{
  "type": "Feature",
  "properties": {
    "addr:full":"1 Youngs Terrace, Maria Street Kirkcaldy Fife KY1 1BU",
    "addr:housenumber":"1",
    "addr:postcode":"ky1 1bu",
    "addr:street":"Youngs Terrace Maria Street",
    "iso:country":"GB",
    "sg:address":"1 Youngs Terrace, Maria Street",
    "sg:city":"Kirkcaldy",
    "sg:classifiers":[
        {
            "category":"Professional",
            "subcategory":"Secretarial Services",
            "type":"Services"
        }
    ],
    "sg:phone":"+44 1592 260585",
    "sg:postcode":"KY1 1BU",
    "sg:province":"Fife",
    "sg:tags":[
        "processing",
        "word"
    ],
    "wof:name":"Adam Moffat",
    "wof:placetype":"venue"
},
  "geometry": {"coordinates":[-3.1630289555,56.1095962524],"type":"Point"}
}