{
  "type": "Feature",
  "properties": {
    "addr:full":"2 Montagu Street Kettering Northamptonshire NN16 8RU",
    "addr:housenumber":"2",
    "addr:postcode":"nn16 8ru",
    "addr:street":"Montagu Street",
    "iso:country":"GB",
    "sg:address":"2 Montagu Street",
    "sg:city":"Kettering",
    "sg:classifiers":[
        {
            "category":"Shopping",
            "subcategory":"Crafts & Fabrics",
            "type":"Retail Goods"
        }
    ],
    "sg:phone":"+44 1536 513287",
    "sg:postcode":"NN16 8RU",
    "sg:province":"Northamptonshire",
    "sg:tags":[
        "shop"
    ],
    "wof:name":"A G Frith Fabrics",
    "wof:placetype":"venue"
},
  "geometry": {"coordinates":[-0.725434,52.400871],"type":"Point"}
}