{
  "type": "Feature",
  "properties": {
    "addr:full":"376 Grove Rd Mitcham Greater London CR4 1AB",
    "addr:housenumber":"376",
    "addr:postcode":"cr4 1ab",
    "addr:street":"Grove Rd",
    "iso:country":"GB",
    "sg:address":"376 Grove Rd",
    "sg:city":"Mitcham",
    "sg:classifiers":[
        {
            "category":"Fast Food",
            "type":"Food & Drink"
        }
    ],
    "sg:postcode":"CR4 1AB",
    "sg:province":"Greater London",
    "sg:tags":[
        "away",
        "take"
    ],
    "wof:name":"Xin's Kitchens",
    "wof:placetype":"venue"
},
  "geometry": {"coordinates":[-0.145129,51.4123],"type":"Point"}
}