{
  "type": "Feature",
  "properties": {
    "addr:full":"53 Corkscrew Hill West Wickham Kent BR4 9BA",
    "addr:housenumber":"53",
    "addr:postcode":"br4 9ba",
    "addr:street":"Corkscrew Hill",
    "iso:country":"GB",
    "sg:address":"53 Corkscrew Hill",
    "sg:city":"West Wickham",
    "sg:classifiers":[
        {
            "category":"Professional",
            "type":"Services"
        }
    ],
    "sg:phone":"+44 20 8777 0900",
    "sg:postcode":"BR4 9BA",
    "sg:province":"Kent",
    "sg:tags":[
        "shopfitters"
    ],
    "wof:name":"D K Interiors",
    "wof:placetype":"venue"
},
  "geometry": {"coordinates":[-0.010455,51.371605],"type":"Point"}
}