{
  "type": "Feature",
  "properties": {
    "iso:country":"GB",
    "sg:address":"200 Brentwood Road, Herongate",
    "sg:city":"Brentwood",
    "sg:classifiers":[
        {
            "category":"Retail",
            "subcategory":"Laundry & Dry Cleaning",
            "type":"Services"
        },
        {
            "category":"Banks & Credit Unions",
            "subcategory":"Investment Brokerage",
            "type":"Services"
        }
    ],
    "sg:phone":"+44 1277 812626",
    "sg:postcode":"CM13 3PN",
    "sg:province":"Essex",
    "sg:tags":[
        "cleaner",
        "sales",
        "equipment"
    ],
    "wof:name":"Unit Steam Engineering Ltd.",
    "wof:placetype":"venue"
},
  "geometry": {"coordinates":[0.353674,51.593102],"type":"Point"}
}