{
  "type": "Feature",
  "properties": {
    "addr:full":"Carrhill Road, Mossley Ashton-under-lyne Greater Manchester OL5 0BL",
    "addr:postcode":"ol5 0bl",
    "addr:street":"Carrhill Road",
    "iso:country":"GB",
    "sg:address":"Carrhill Road, Mossley",
    "sg:city":"Ashton-under-lyne",
    "sg:classifiers":[
        {
            "category":"Bars & Pubs",
            "type":"Food & Drink"
        },
        {
            "category":"Organizations",
            "subcategory":"Community Association",
            "type":"Services"
        }
    ],
    "sg:phone":"+44 1457 832295",
    "sg:postcode":"OL5 0BL",
    "sg:province":"Greater Manchester",
    "sg:tags":[
        "club",
        "pubs",
        "inn",
        "social"
    ],
    "wof:name":"Yorkshire Ward Conservative Club",
    "wof:placetype":"venue"
},
  "geometry": {"coordinates":[-2.0374250412,53.5228843689],"type":"Point"}
}