{
  "type": "Feature",
  "properties": {
    "iso:country":"GB",
    "sg:address":"156 Corn Street",
    "sg:city":"Witney",
    "sg:classifiers":[
        {
            "category":"Shopping",
            "subcategory":"Antiques",
            "type":"Retail Goods"
        }
    ],
    "sg:phone":"+44 1993 704749",
    "sg:postcode":"OX28 6BY",
    "sg:province":"Oxfordshire",
    "wof:name":"J Wilkins",
    "wof:placetype":"venue"
},
  "geometry": {"coordinates":[-1.493268,51.78495],"type":"Point"}
}