{
  "type": "Feature",
  "properties": {
    "addr:full":"Unit 3, 35a Stanbridge Road Leighton Buzzard Bedfordshire LU7 4PZ",
    "addr:housenumber":"unit;35a",
    "addr:postcode":"lu7 4pz",
    "addr:street":"Stanbridge Road",
    "iso:country":"GB",
    "sg:address":"Unit 3, 35a Stanbridge Road",
    "sg:city":"Leighton Buzzard",
    "sg:classifiers":[
        {
            "category":"Manufacturing",
            "subcategory":"Signs",
            "type":"Manufacturing & Wholesale Goods"
        }
    ],
    "sg:phone":"+44 1525 382111",
    "sg:postcode":"LU7 4PZ",
    "sg:province":"Bedfordshire",
    "sg:tags":[
        "writer"
    ],
    "wof:name":"Technosign Ltd.",
    "wof:placetype":"venue"
},
  "geometry": {"coordinates":[-0.652647,51.913807],"type":"Point"}
}