{
  "type": "Feature",
  "properties": {
    "addr:full":"Berristow Lane, Hilcote Derby Derbyshire DE55 5JB",
    "addr:postcode":"de55 5jb",
    "addr:street":"Berristow Lane",
    "iso:country":"GB",
    "sg:address":"Berristow Lane, Hilcote",
    "sg:city":"Derby",
    "sg:classifiers":[
        {
            "category":"Manufacturing",
            "subcategory":"Metals",
            "type":"Manufacturing & Wholesale Goods"
        }
    ],
    "sg:postcode":"DE55 5JB",
    "sg:province":"Derbyshire",
    "sg:tags":[
        "fab",
        "foundry"
    ],
    "wof:name":"Auto Alloys (Foundries) Ltd.",
    "wof:placetype":"venue"
},
  "geometry": {"coordinates":[-1.3264960051,53.117641449],"type":"Point"}
}