{
  "type": "Feature",
  "properties": {
    "addr:full":"Medical Centre, Main Rd Ashbourne Derbyshire DE6 3EA",
    "addr:postcode":"de6 3ea",
    "addr:street":"Main Rd",
    "iso:country":"GB",
    "sg:address":"Medical Centre, Main Rd",
    "sg:city":"Ashbourne",
    "sg:classifiers":[
        {
            "category":"Health Services",
            "subcategory":"Doctor",
            "type":"Services"
        }
    ],
    "sg:phone":"+44 1335 370482",
    "sg:postcode":"DE6 3EA",
    "sg:province":"Derbyshire",
    "sg:tags":[
        "practitioners"
    ],
    "wof:name":"Bates, B J",
    "wof:placetype":"venue"
},
  "geometry": {"coordinates":[-1.732564,53.01828],"type":"Point"}
}