{
  "type": "Feature",
  "properties": {
    "addr:full":"25 Anchor Reach Chelmsford Essex CM3 5GS",
    "addr:housenumber":"25",
    "addr:postcode":"cm3 5gs",
    "addr:street":"Anchor Reach",
    "iso:country":"GB",
    "sg:address":"25 Anchor Reach",
    "sg:city":"Chelmsford",
    "sg:classifiers":[
        {
            "category":"Home & Garden",
            "subcategory":"Household Appliances",
            "type":"Retail Goods"
        }
    ],
    "sg:phone":"+44 1245 323255",
    "sg:postcode":"CM3 5GS",
    "sg:province":"Essex",
    "sg:tags":[
        "refrigeration",
        "air conditioning"
    ],
    "wof:name":"Phoenix Envirotec Ltd",
    "wof:placetype":"venue"
},
  "geometry": {"coordinates":[0.618816,51.63681],"type":"Point"}
}