{
  "type": "Feature",
  "properties": {
    "addr:full":"12 Kirkwall Corby Northamptonshire NN17 2QZ",
    "addr:housenumber":"12",
    "addr:postcode":"nn17 2qz",
    "addr:street":"Kirkwall",
    "iso:country":"GB",
    "sg:address":"12 Kirkwall",
    "sg:city":"Corby",
    "sg:classifiers":[
        {
            "category":"Building & Trades",
            "subcategory":"Pest Control",
            "type":"Services"
        }
    ],
    "sg:phone":"+44 1536 264600",
    "sg:postcode":"NN17 2QZ",
    "sg:province":"Northamptonshire",
    "sg:tags":[
        "vermin"
    ],
    "wof:name":"Ace Environmental Services",
    "wof:placetype":"venue"
},
  "geometry": {"coordinates":[-0.7167789936,52.5021286011],"type":"Point"}
}