{
  "type": "Feature",
  "properties": {
    "addr:full":"Sea View Road West Sunderland Tyne and Wear SR2 9LH",
    "addr:postcode":"sr2 9lh",
    "addr:street":"Sea View Road West",
    "iso:country":"GB",
    "sg:address":"Sea View Road West",
    "sg:city":"Sunderland",
    "sg:classifiers":[
        {
            "category":"Government",
            "subcategory":"Office",
            "type":"Public Place"
        }
    ],
    "sg:phone":"+44 191 511 6000",
    "sg:postcode":"SR2 9LH",
    "sg:province":"Tyne and Wear",
    "sg:tags":[
        "local"
    ],
    "wof:name":"Wearside College of Further Education",
    "wof:placetype":"venue"
},
  "geometry": {"coordinates":[-1.3772089481,54.8866844177],"type":"Point"}
}