{
  "type": "Feature",
  "properties": {
    "iso:country":"GB",
    "sg:address":"Glen Eden House, Bottom Street, Witham On The Hill",
    "sg:city":"Bourne",
    "sg:classifiers":[
        {
            "category":"Education",
            "subcategory":"Preschool",
            "type":"Public Place"
        }
    ],
    "sg:phone":"+44 1778 590225",
    "sg:postcode":"PE10 0JP",
    "sg:province":"Lincolnshire",
    "sg:tags":[
        "pre-school",
        "playgroups"
    ],
    "wof:name":"Fenland Tumbletots",
    "wof:placetype":"venue"
},
  "geometry": {"coordinates":[-0.441555,52.734989],"type":"Point"}
}