{
  "type": "Feature",
  "properties": {
    "iso:country":"GB",
    "sg:address":"Unit B6, Warhurst Road, Lowfields Business Park",
    "sg:city":"Elland",
    "sg:classifiers":[
        {
            "category":"Wholesale",
            "subcategory":"Construction Materials",
            "type":"Manufacturing & Wholesale Goods"
        }
    ],
    "sg:phone":"+44 1422 377335",
    "sg:postcode":"HX5 9DF",
    "sg:province":"West Yorkshire",
    "sg:tags":[
        "distributor",
        "spring"
    ],
    "wof:name":"Lesjofors Springs Ltd.",
    "wof:placetype":"venue"
},
  "geometry": {"coordinates":[-1.827649,53.690987],"type":"Point"}
}