{
  "type": "Feature",
  "properties": {
    "addr:full":"22 Uxbridge Street Burton-on-trent Derbyshire DE14 3JR",
    "addr:housenumber":"22",
    "addr:postcode":"de14 3jr",
    "addr:street":"Uxbridge Street",
    "iso:country":"GB",
    "sg:address":"22 Uxbridge Street",
    "sg:city":"Burton-on-trent",
    "sg:classifiers":[
        {
            "category":"Personal",
            "subcategory":"Beauty Salon",
            "type":"Services"
        }
    ],
    "sg:phone":"+44 1283 517247",
    "sg:postcode":"DE14 3JR",
    "sg:province":"Derbyshire",
    "sg:tags":[
        "unisex",
        "hairdresser"
    ],
    "wof:name":"Enhance Hair Design",
    "wof:placetype":"venue"
},
  "geometry": {"coordinates":[-1.6390750408,52.8008880615],"type":"Point"}
}