{
  "type": "Feature",
  "properties": {
    "addr:full":"Belver, 19a Woodlands Avenue Durham Durham DH6 3JY",
    "addr:housenumber":"19a",
    "addr:postcode":"dh6 3jy",
    "addr:street":"Belver;Woodlands Avenue",
    "iso:country":"GB",
    "sg:address":"Belver, 19a Woodlands Avenue",
    "sg:city":"Durham",
    "sg:classifiers":[
        {
            "category":"Manufacturing",
            "subcategory":"Signs",
            "type":"Manufacturing & Wholesale Goods"
        }
    ],
    "sg:postcode":"DH6 3JY",
    "sg:province":"Durham",
    "sg:tags":[
        "writer"
    ],
    "wof:name":"G Barratt",
    "wof:placetype":"venue"
},
  "geometry": {"coordinates":[-1.4154399633,54.7431602478],"type":"Point"}
}