{
  "type": "Feature",
  "properties": {
    "addr:full":"Lluest Newydd, Nebo Llanon Ceredigion SY23 5LE",
    "addr:postcode":"sy23 5le",
    "iso:country":"GB",
    "sg:address":"Lluest Newydd, Nebo",
    "sg:city":"Llanon",
    "sg:classifiers":[
        {
            "category":"Professional",
            "subcategory":"Engineering",
            "type":"Services"
        }
    ],
    "sg:phone":"+44 1974 272112",
    "sg:postcode":"SY23 5LE",
    "sg:province":"Ceredigion",
    "wof:name":"John Pickering",
    "wof:placetype":"venue"
},
  "geometry": {"coordinates":[-4.1316599846,52.2645225525],"type":"Point"}
}