{
  "type": "Feature",
  "properties": {
    "addr:full":"Unit 6 Grove Park, Mill La Alton Hampshire GU34 2QG",
    "addr:housenumber":"unit 6",
    "addr:postcode":"gu34 2qg",
    "addr:street":"Grove Park Mill La Alton",
    "iso:country":"GB",
    "sg:address":"Unit 6 Grove Park, Mill La",
    "sg:city":"Alton",
    "sg:classifiers":[
        {
            "category":"Wholesale",
            "subcategory":"Chemicals & Plastics",
            "type":"Manufacturing & Wholesale Goods"
        }
    ],
    "sg:phone":"+44 1420 82503",
    "sg:postcode":"GU34 2QG",
    "sg:province":"Hampshire",
    "sg:tags":[
        "product",
        "allied"
    ],
    "wof:name":"Pronova Biopolymer Ltd",
    "wof:placetype":"venue"
},
  "geometry": {"coordinates":[-0.9679549932,51.1515617371],"type":"Point"}
}