{
  "type": "Feature",
  "properties": {
    "addr:full":"The Gables, 13 Mountain View Clo Deeside Flintshire CH5 4HH",
    "addr:housenumber":"13",
    "addr:postcode":"ch5 4hh",
    "addr:street":"Mountain View Clo",
    "iso:country":"GB",
    "sg:address":"The Gables, 13 Mountain View Clo",
    "sg:city":"Deeside",
    "sg:classifiers":[
        {
            "category":"Health Services",
            "subcategory":"Clinic",
            "type":"Services"
        }
    ],
    "sg:phone":"+44 1244 836615",
    "sg:postcode":"CH5 4HH",
    "sg:province":"Flintshire",
    "sg:tags":[
        "aromatherapy"
    ],
    "wof:name":"Simply Natural",
    "wof:placetype":"venue"
},
  "geometry": {"coordinates":[-3.024988,53.20248],"type":"Point"}
}