{
  "type": "Feature",
  "properties": {
    "addr:full":"17 George St Dover Kent CT17 0EG",
    "addr:housenumber":"17",
    "addr:postcode":"ct17 0eg",
    "addr:street":"George St",
    "iso:country":"GB",
    "sg:address":"17 George St",
    "sg:city":"Dover",
    "sg:classifiers":[
        {
            "category":"Shopping",
            "subcategory":"Hobbies, Toys, & Games",
            "type":"Retail Goods"
        }
    ],
    "sg:phone":"+44 1304 207523",
    "sg:postcode":"CT17 0EG",
    "sg:province":"Kent",
    "sg:tags":[
        "gunsmith"
    ],
    "wof:name":"Apollo Gun Cabinets",
    "wof:placetype":"venue"
},
  "geometry": {"coordinates":[1.300521,51.132668],"type":"Point"}
}