{
  "type": "Feature",
  "properties": {
    "addr:full":"28 Petty Cury Cambridge Cambridgeshire CB2 3ND",
    "addr:housenumber":"28",
    "addr:postcode":"cb2 3nd",
    "addr:street":"Petty Cury",
    "iso:country":"GB",
    "sg:address":"28 Petty Cury",
    "sg:city":"Cambridge",
    "sg:classifiers":[
        {
            "category":"Health Services",
            "subcategory":"Optometrist",
            "type":"Services"
        }
    ],
    "sg:phone":"+44 1223 366104",
    "sg:postcode":"CB2 3ND",
    "sg:province":"Cambridgeshire",
    "sg:tags":[
        "optician"
    ],
    "wof:name":"Boots Opticians Ltd.",
    "wof:placetype":"venue"
},
  "geometry": {"coordinates":[0.1205990016,52.205280304],"type":"Point"}
}