{
  "type": "Feature",
  "properties": {
    "iso:country":"GB",
    "sg:address":"Stafford Rd",
    "sg:city":"Stafford",
    "sg:classifiers":[
        {
            "category":"Autos & Motor Vehicles",
            "subcategory":"Automobile Sales",
            "type":"Retail Goods"
        }
    ],
    "sg:phone":"+44 1785 714600",
    "sg:postcode":"ST19 5AS",
    "sg:province":"Shropshire",
    "sg:tags":[
        "car"
    ],
    "wof:name":"Hodson & Son Ltd",
    "wof:placetype":"venue"
},
  "geometry": {"coordinates":[-2.1338329315,52.6859664917],"type":"Point"}
}