{
  "type": "Feature",
  "properties": {
    "addr:full":"1 Buckingham Parade, Kempshott Basingstoke Hampshire RG22 5NZ",
    "addr:housenumber":"1",
    "addr:postcode":"rg22 5nz",
    "addr:street":"Buckingham Parade Kempshott",
    "iso:country":"GB",
    "sg:address":"1 Buckingham Parade, Kempshott",
    "sg:city":"Basingstoke",
    "sg:classifiers":[
        {
            "category":"Personal",
            "subcategory":"Beauty Salon",
            "type":"Services"
        }
    ],
    "sg:phone":"+44 1256 323125",
    "sg:postcode":"RG22 5NZ",
    "sg:province":"Hampshire",
    "sg:tags":[
        "unisex",
        "hairdresser"
    ],
    "wof:name":"Jesta Hairdressing",
    "wof:placetype":"venue"
},
  "geometry": {"coordinates":[-1.139155,51.246502],"type":"Point"}
}