{
  "type": "Feature",
  "properties": {
    "addr:full":"Blackwater Truro Cornwall TR4 8EQ",
    "addr:postcode":"tr4 8eq",
    "addr:street":"Blackwater",
    "iso:country":"GB",
    "sg:address":"Blackwater",
    "sg:city":"Truro",
    "sg:classifiers":[
        {
            "category":"Retail",
            "subcategory":"Auto Repair",
            "type":"Services"
        }
    ],
    "sg:phone":"+44 1872 560333",
    "sg:postcode":"TR4 8EQ",
    "sg:province":"Cornwall",
    "sg:tags":[
        "modification",
        "garage"
    ],
    "wof:name":"Chapel Garage",
    "wof:placetype":"venue"
},
  "geometry": {"coordinates":[-5.1781201363,50.2724609375],"type":"Point"}
}