{
  "type": "Feature",
  "properties": {
    "addr:full":"147 Reddenhill Road Torquay Devon TQ1 3NT",
    "addr:housenumber":"147",
    "addr:postcode":"tq1 3nt",
    "addr:street":"Reddenhill Road",
    "iso:country":"GB",
    "sg:address":"147 Reddenhill Road",
    "sg:city":"Torquay",
    "sg:classifiers":[
        {
            "category":"Cafe",
            "type":"Food & Drink"
        }
    ],
    "sg:postcode":"TQ1 3NT",
    "sg:province":"Devon",
    "sg:tags":[
        "tea",
        "room"
    ],
    "wof:name":"Meeting Room Coffee Shop",
    "wof:placetype":"venue"
},
  "geometry": {"coordinates":[-3.5152320862,50.4782905579],"type":"Point"}
}