{
  "type": "Feature",
  "properties": {
    "iso:country":"GB",
    "sg:address":"226 Southchurch Road",
    "sg:city":"Southend-on-sea",
    "sg:classifiers":[
        {
            "category":"Social Services",
            "subcategory":"Retirement Home",
            "type":"Services"
        }
    ],
    "sg:phone":"+44 1702 462541",
    "sg:postcode":"SS1 2LS",
    "sg:province":"Essex",
    "sg:tags":[
        "residential",
        "care"
    ],
    "wof:name":"Abbotts Wood Lodge",
    "wof:placetype":"venue"
},
  "geometry": {"coordinates":[0.7204040289,51.5399284363],"type":"Point"}
}