{
  "type": "Feature",
  "properties": {
    "iso:country":"GB",
    "sg:address":"1 Hodgkinson Road",
    "sg:city":"Felixstowe",
    "sg:classifiers":[
        {
            "category":"Freight",
            "type":"Transportation"
        }
    ],
    "sg:phone":"+44 1394 674125",
    "sg:postcode":"IP11 3QT",
    "sg:province":"Suffolk",
    "sg:tags":[
        "haulage",
        "road"
    ],
    "wof:name":"James Kemball Ltd.",
    "wof:placetype":"venue"
},
  "geometry": {"coordinates":[1.318015,51.960754],"type":"Point"}
}