{
  "type": "Feature",
  "properties": {
    "iso:country":"GB",
    "sg:address":"404 Liverpool Road, Platt Bridge",
    "sg:city":"Wigan",
    "sg:classifiers":[
        {
            "category":"Manufacturing",
            "subcategory":"Textiles",
            "type":"Manufacturing & Wholesale Goods"
        }
    ],
    "sg:phone":"+44 1942 866057",
    "sg:postcode":"WN2 3UE",
    "sg:province":"Lancashire",
    "sg:tags":[
        "knitwear"
    ],
    "wof:name":"R Kuit & Ashley Ltd.",
    "wof:placetype":"venue"
},
  "geometry": {"coordinates":[-2.586549,53.527359],"type":"Point"}
}