{
  "type": "Feature",
  "properties": {
    "iso:country":"GB",
    "sg:address":"16a Commercial St",
    "sg:city":"Camborne",
    "sg:classifiers":[
        {
            "category":"Real Estate",
            "subcategory":"Surveying",
            "type":"Services"
        }
    ],
    "sg:postcode":"TR14 8JY",
    "sg:province":"Cornwall",
    "sg:tags":[
        "surveyor",
        "quantity"
    ],
    "wof:name":"Young,David John,",
    "wof:placetype":"venue"
},
  "geometry": {"coordinates":[-5.3006930351,50.2133865356],"type":"Point"}
}