{
  "type": "Feature",
  "properties": {
    "addr:full":"36 Tong Moorside Bradford West Yorkshire BD4 0SH",
    "addr:housenumber":"36;bradford",
    "addr:postcode":"yorkshire bd4 0sh",
    "addr:street":"Tong Moorside",
    "iso:country":"GB",
    "sg:address":"36 Tong Moorside",
    "sg:city":"Bradford",
    "sg:classifiers":[
        {
            "category":"Food & Beverages",
            "subcategory":"Groceries & Convenience Stores",
            "type":"Retail Goods"
        }
    ],
    "sg:phone":"+44 1274 681905",
    "sg:postcode":"BD4 0SH",
    "sg:province":"West Yorkshire",
    "wof:name":"R I Pickles",
    "wof:placetype":"venue"
},
  "geometry": {"coordinates":[-1.6637639999,53.7720909119],"type":"Point"}
}