{
  "type": "Feature",
  "properties": {
    "addr:full":"Kemys Street, Griffithstown Pontypool Monmouthshire NP4 5DJ",
    "addr:postcode":"np4 5dj",
    "addr:street":"Kemys Street",
    "iso:country":"GB",
    "sg:address":"Kemys Street, Griffithstown",
    "sg:city":"Pontypool",
    "sg:classifiers":[
        {
            "category":"Health Services",
            "subcategory":"Doctor",
            "type":"Services"
        }
    ],
    "sg:phone":"+44 1495 763608",
    "sg:postcode":"NP4 5DJ",
    "sg:province":"Monmouthshire",
    "sg:tags":[
        "practitioners"
    ],
    "wof:name":"Panteg Health Centre",
    "wof:placetype":"venue"
},
  "geometry": {"coordinates":[-3.0293738842,51.6881752014],"type":"Point"}
}