{
  "type": "Feature",
  "properties": {
    "addr:full":"19 Ruddpark Road Manchester Greater Manchester M22 0FH",
    "addr:housenumber":"19",
    "addr:postcode":"m22 0fh",
    "addr:street":"Ruddpark Road",
    "iso:country":"GB",
    "sg:address":"19 Ruddpark Road",
    "sg:city":"Manchester",
    "sg:classifiers":[
        {
            "category":"Food & Beverages",
            "subcategory":"Meat & Fish",
            "type":"Retail Goods"
        }
    ],
    "sg:postcode":"M22 0FH",
    "sg:province":"Greater Manchester",
    "sg:tags":[
        "chip"
    ],
    "wof:name":"The Golden Palace",
    "wof:placetype":"venue"
},
  "geometry": {"coordinates":[-2.260051012,53.3740921021],"type":"Point"}
}