{
  "type": "Feature",
  "properties": {
    "addr:full":"8 Snowdon Road Middlesbrough Durham TS2 1LP",
    "addr:housenumber":"8",
    "addr:postcode":"ts2 1lp",
    "addr:street":"Snowdon Road",
    "iso:country":"GB",
    "sg:address":"8 Snowdon Road",
    "sg:city":"Middlesbrough",
    "sg:classifiers":[
        {
            "category":"Building & Trades",
            "subcategory":"Locksmith",
            "type":"Services"
        }
    ],
    "sg:postcode":"TS2 1LP",
    "sg:province":"Durham",
    "sg:tags":[
        "steeplejack"
    ],
    "wof:name":"H & A Height Services Ltd.",
    "wof:placetype":"venue"
},
  "geometry": {"coordinates":[-1.2373789549,54.5847358704],"type":"Point"}
}