{
  "type": "Feature",
  "properties": {
    "addr:full":"Unit 31 Gilwilly Road, Gilwilly Industrial Estate Penrith Cumbria CA11 9BF",
    "addr:housenumber":"unit 31",
    "addr:postcode":"ca11 9bf",
    "addr:street":"Gilwilly Road Gilwilly Industrial Estate",
    "iso:country":"GB",
    "sg:address":"Unit 31 Gilwilly Road, Gilwilly Industrial Estate",
    "sg:city":"Penrith",
    "sg:classifiers":[
        {
            "category":"Retail",
            "subcategory":"Auto Repair",
            "type":"Services"
        }
    ],
    "sg:postcode":"CA11 9BF",
    "sg:province":"Cumbria",
    "sg:tags":[
        "body",
        "car"
    ],
    "wof:name":"Penrith Body Repairs",
    "wof:placetype":"venue"
},
  "geometry": {"coordinates":[-2.7619490623,54.6670417786],"type":"Point"}
}