{
  "type": "Feature",
  "properties": {
    "addr:full":"85 Owen Street Tipton West Midlands DY4 8EX",
    "addr:housenumber":"85",
    "addr:postcode":"dy4 8ex",
    "addr:street":"Owen Street",
    "iso:country":"GB",
    "sg:address":"85 Owen Street",
    "sg:city":"Tipton",
    "sg:classifiers":[
        {
            "category":"Organizations",
            "subcategory":"Non-profit Organization",
            "type":"Services"
        }
    ],
    "sg:postcode":"DY4 8EX",
    "sg:province":"West Midlands",
    "sg:tags":[
        "organisation",
        "voluntary",
        "charity"
    ],
    "wof:name":"National Council of Young Men's Christian Associations (Incorporatedp",
    "wof:placetype":"venue"
},
  "geometry": {"coordinates":[-2.068214,52.529408],"type":"Point"}
}