{
  "type": "Feature",
  "properties": {
    "addr:full":"15 Ashcroft Gro Newcastle Staffordshire ST5 8ES",
    "addr:housenumber":"15",
    "addr:postcode":"st5 8es",
    "addr:street":"Gro",
    "iso:country":"GB",
    "sg:address":"15 Ashcroft Gro",
    "sg:city":"Newcastle",
    "sg:classifiers":[
        {
            "category":"Professional",
            "subcategory":"Engineering",
            "type":"Services"
        }
    ],
    "sg:phone":"+44 1782 619436",
    "sg:postcode":"ST5 8ES",
    "sg:province":"Staffordshire",
    "sg:tags":[
        "gas",
        "engineer"
    ],
    "wof:name":"Griffiths Gas",
    "wof:placetype":"venue"
},
  "geometry": {"coordinates":[-2.230911,53.036205],"type":"Point"}
}