{
  "type": "Feature",
  "properties": {
    "addr:full":"Trafalgar Trading Estate, Jeffreys Road Enfield Greater London EN3 7TY",
    "addr:postcode":"en3 7ty",
    "addr:street":"Trading Estate Jeffreys Road",
    "iso:country":"GB",
    "sg:address":"Trafalgar Trading Estate, Jeffreys Road",
    "sg:city":"Enfield",
    "sg:classifiers":[
        {
            "category":"Autos & Motor Vehicles",
            "subcategory":"Auto Supplies",
            "type":"Retail Goods"
        }
    ],
    "sg:phone":"+44 20 8443 4377",
    "sg:postcode":"EN3 7TY",
    "sg:province":"Greater London",
    "sg:tags":[
        "tyre"
    ],
    "wof:name":"National Tyres and Autocare",
    "wof:placetype":"venue"
},
  "geometry": {"coordinates":[-0.0286699999,51.6498603821],"type":"Point"}
}