{
  "type": "Feature",
  "properties": {
    "iso:country":"GB",
    "sg:address":"39 George Street",
    "sg:city":"Stranraer",
    "sg:classifiers":[
        {
            "category":"Professional",
            "subcategory":"Art Services",
            "type":"Services"
        }
    ],
    "sg:phone":"+44 1776 703286",
    "sg:postcode":"DG9 7RJ",
    "sg:province":"Dumfries and Galloway",
    "sg:tags":[
        "picture",
        "framing"
    ],
    "wof:name":"Baxters",
    "wof:placetype":"venue"
},
  "geometry": {"coordinates":[-5.027394,54.904587],"type":"Point"}
}