{
  "type": "Feature",
  "properties": {
    "iso:country":"GB",
    "sg:address":"18 Moat Rd",
    "sg:city":"Walsall",
    "sg:classifiers":[
        {
            "category":"Wholesale",
            "subcategory":"Toys & Hobbies",
            "type":"Manufacturing & Wholesale Goods"
        }
    ],
    "sg:postcode":"WS2 9PJ",
    "sg:province":"West Midlands",
    "sg:tags":[
        "balloon",
        "novelty"
    ],
    "wof:name":"Balloons for All Occasions",
    "wof:placetype":"venue"
},
  "geometry": {"coordinates":[-1.996263,52.584591],"type":"Point"}
}