{
  "type": "Feature",
  "properties": {
    "addr:full":"Church Rd Liverpool Merseyside L25 6HT",
    "addr:postcode":"l25 6ht",
    "addr:street":"Church Rd",
    "iso:country":"GB",
    "sg:address":"Church Rd",
    "sg:city":"Liverpool",
    "sg:classifiers":[
        {
            "category":"Organizations",
            "subcategory":"Religious Organization",
            "type":"Services"
        }
    ],
    "sg:phone":"+44 151 421 0717",
    "sg:postcode":"L25 6HT",
    "sg:province":"Merseyside",
    "sg:tags":[
        "organisation",
        "place",
        "worship"
    ],
    "wof:name":"St Gabriel's Convent",
    "wof:placetype":"venue"
},
  "geometry": {"coordinates":[-2.874181,53.381577],"type":"Point"}
}