{
  "type": "Feature",
  "properties": {
    "addr:full":"43 Durham Way Harrogate North Yorkshire HG3 2TA",
    "addr:housenumber":"43",
    "addr:postcode":"hg3 2ta",
    "addr:street":"Durham Way",
    "iso:country":"GB",
    "sg:address":"43 Durham Way",
    "sg:city":"Harrogate",
    "sg:classifiers":[
        {
            "category":"Manufacturing",
            "subcategory":"Petroleum Products",
            "type":"Manufacturing & Wholesale Goods"
        },
        {
            "category":"Building & Trades",
            "subcategory":"Construction",
            "type":"Services"
        }
    ],
    "sg:phone":"+44 1423 565123",
    "sg:postcode":"HG3 2TA",
    "sg:province":"North Yorkshire",
    "sg:tags":[
        "repair",
        "window",
        "glazing",
        "replacement",
        "double"
    ],
    "wof:name":"Hallmark Windows Harrogate",
    "wof:placetype":"venue"
},
  "geometry": {"coordinates":[-1.56883,54.006447],"type":"Point"}
}