{
  "type": "Feature",
  "properties": {
    "addr:full":"58a High Street Bognor Regis West Sussex PO21 1SP",
    "addr:housenumber":"58a",
    "addr:postcode":"po21 1sp",
    "addr:street":"High Street",
    "iso:country":"GB",
    "sg:address":"58a High Street",
    "sg:city":"Bognor Regis",
    "sg:classifiers":[
        {
            "category":"Real Estate",
            "subcategory":"Real Estate Agent",
            "type":"Services"
        }
    ],
    "sg:postcode":"PO21 1SP",
    "sg:province":"West Sussex",
    "wof:name":"Dunedin Property Services",
    "wof:placetype":"venue"
},
  "geometry": {"coordinates":[-0.6738619804,50.7832527161],"type":"Point"}
}