{
  "type": "Feature",
  "properties": {
    "iso:country":"GB",
    "sg:address":"Fleet House, Fleet Street",
    "sg:city":"Preston",
    "sg:classifiers":[
        {
            "category":"Real Estate",
            "subcategory":"Real Estate Operator",
            "type":"Services"
        },
        {
            "category":"Real Estate",
            "subcategory":"Real Estate Agent",
            "type":"Services"
        }
    ],
    "sg:phone":"+44 1772 883188",
    "sg:postcode":"PR1 2UT",
    "sg:province":"Lancashire",
    "sg:tags":[
        "letting"
    ],
    "sg:website":"http://www.gw-online.co.uk",
    "wof:name":"Garside Waddingham",
    "wof:placetype":"venue"
},
  "geometry": {"coordinates":[-2.703832,53.75909],"type":"Point"}
}