{
  "type": "Feature",
  "properties": {
    "iso:country":"GB",
    "sg:address":"Skipton Rd",
    "sg:city":"Colne",
    "sg:classifiers":[
        {
            "category":"Autos & Motor Vehicles",
            "subcategory":"Automobile Sales",
            "type":"Retail Goods"
        }
    ],
    "sg:phone":"+44 1282 862884",
    "sg:postcode":"BB8 0NQ",
    "sg:province":"Lancashire",
    "sg:tags":[
        "car"
    ],
    "wof:name":"Atlas Garage",
    "wof:placetype":"venue"
},
  "geometry": {"coordinates":[-2.165417,53.86478],"type":"Point"}
}