{
  "type": "Feature",
  "properties": {
    "iso:country":"GB",
    "sg:address":"3 Heol Y Gog, Gowerton",
    "sg:city":"Swansea",
    "sg:classifiers":[
        {
            "category":"Wholesale",
            "subcategory":"Books, Periodicals, & Newspapers",
            "type":"Manufacturing & Wholesale Goods"
        }
    ],
    "sg:postcode":"SA4 3BX",
    "sg:province":"Carmarthenshire",
    "sg:tags":[
        "publishing"
    ],
    "wof:name":"Island Products Ltd",
    "wof:placetype":"venue"
},
  "geometry": {"coordinates":[-4.04233,51.648598],"type":"Point"}
}