{
  "type": "Feature",
  "properties": {
    "iso:country":"GB",
    "sg:address":"61 London Road",
    "sg:city":"Bognor Regis",
    "sg:classifiers":[
        {
            "category":"Shopping",
            "subcategory":"Baby Store",
            "type":"Retail Goods"
        }
    ],
    "sg:phone":"+44 1243 822242",
    "sg:postcode":"PO21 1DF",
    "sg:province":"West Sussex",
    "sg:tags":[
        "babywear",
        "childrens"
    ],
    "wof:name":"Tiny Tots",
    "wof:placetype":"venue"
},
  "geometry": {"coordinates":[-0.673993,50.786625],"type":"Point"}
}