{
  "type": "Feature",
  "properties": {
    "addr:full":"28 Wigginton Road Tamworth Staffordshire B79 8RH",
    "addr:housenumber":"28",
    "addr:postcode":"b79 8rh",
    "addr:street":"Wigginton Road",
    "iso:country":"GB",
    "sg:address":"28 Wigginton Road",
    "sg:city":"Tamworth",
    "sg:classifiers":[
        {
            "category":"Social Services",
            "subcategory":"Job Training",
            "type":"Services"
        },
        {
            "category":"Education",
            "subcategory":"Special Training",
            "type":"Public Place"
        }
    ],
    "sg:phone":"+44 1827 62482",
    "sg:postcode":"B79 8RH",
    "sg:province":"Staffordshire",
    "sg:tags":[
        "product",
        "centre"
    ],
    "wof:name":"TRANSWORLD PUBLICATIONS SERVICES LTD",
    "wof:placetype":"venue"
},
  "geometry": {"coordinates":[-1.6931890249,52.6428070068],"type":"Point"}
}