{
  "type": "Feature",
  "properties": {
    "iso:country":"GB",
    "sg:address":"Unit 5c Gatehouse Trading Estate, Lichfield Road, Brownhills",
    "sg:city":"Walsall",
    "sg:classifiers":[
        {
            "category":"Professional",
            "subcategory":"Testing Lab",
            "type":"Services"
        }
    ],
    "sg:phone":"+44 1543 452630",
    "sg:postcode":"WS8 6JZ",
    "sg:province":"Staffordshire",
    "sg:tags":[
        "mot"
    ],
    "wof:name":"Fitch Autos",
    "wof:placetype":"venue"
},
  "geometry": {"coordinates":[-1.92062,52.65295],"type":"Point"}
}