{
  "type": "Feature",
  "properties": {
    "iso:country":"GB",
    "sg:address":"128 Worcester Road",
    "sg:city":"Droitwich",
    "sg:classifiers":[
        {
            "category":"Shopping",
            "subcategory":"Antiques",
            "type":"Retail Goods"
        }
    ],
    "sg:phone":"+44 1905 772320",
    "sg:postcode":"WR9 8AN",
    "sg:province":"Worcestershire",
    "wof:name":"Robert Belcher Antiques",
    "wof:placetype":"venue"
},
  "geometry": {"coordinates":[-2.1534099579,52.2609481812],"type":"Point"}
}