{
  "type": "Feature",
  "properties": {
    "addr:full":"Badger Moor Farm Badger Moor Road Ashbourne Derbyshire DE6 1PW",
    "addr:postcode":"de6 1pw",
    "addr:street":"Moor;Badger Moor Road",
    "iso:country":"GB",
    "sg:address":"Badger Moor Farm Badger Moor Road",
    "sg:city":"Ashbourne",
    "sg:classifiers":[
        {
            "category":"Manufacturing",
            "subcategory":"Wood Products",
            "type":"Manufacturing & Wholesale Goods"
        },
        {
            "category":"Wholesale",
            "subcategory":"Scrap",
            "type":"Manufacturing & Wholesale Goods"
        }
    ],
    "sg:phone":"+44 1335 370790",
    "sg:postcode":"DE6 1PW",
    "sg:province":"Derbyshire",
    "sg:tags":[
        "sawdust",
        "agric",
        "shaving"
    ],
    "wof:name":"R Swindell & Sons Ltd",
    "wof:placetype":"venue"
},
  "geometry": {"coordinates":[-1.732564,53.01828],"type":"Point"}
}