{
  "type": "Feature",
  "properties": {
    "iso:country":"GB",
    "sg:address":"23 Hawden Close, Hildenborough",
    "sg:city":"Tonbridge",
    "sg:classifiers":[
        {
            "category":"Sports & Exercise",
            "subcategory":"Sports Center",
            "type":"Entertainment"
        }
    ],
    "sg:postcode":"TN11 9BP",
    "sg:province":"Kent",
    "sg:tags":[
        "coaching"
    ],
    "wof:name":"Aqua School of Swimming",
    "wof:placetype":"venue"
},
  "geometry": {"coordinates":[0.256925,51.206745],"type":"Point"}
}