{
  "type": "Feature",
  "properties": {
    "addr:full":"21 Upland Court Road Romford Essex RM3 0TT",
    "addr:housenumber":"21",
    "addr:postcode":"rm3 0tt",
    "addr:street":"Upland Court Road",
    "iso:country":"GB",
    "sg:address":"21 Upland Court Road",
    "sg:city":"Romford",
    "sg:classifiers":[
        {
            "category":"Retail",
            "subcategory":"Driving School",
            "type":"Services"
        }
    ],
    "sg:postcode":"RM3 0TT",
    "sg:province":"Essex",
    "wof:name":"Harold Wood School of Motoring",
    "wof:placetype":"venue"
},
  "geometry": {"coordinates":[0.232367,51.588341],"type":"Point"}
}