{
  "type": "Feature",
  "properties": {
    "addr:full":"44 Oxford Street Ripley Derbyshire DE5 3AP",
    "addr:housenumber":"44",
    "addr:postcode":"de5 3ap",
    "addr:street":"Oxford Street",
    "iso:country":"GB",
    "sg:address":"44 Oxford Street",
    "sg:city":"Ripley",
    "sg:classifiers":[
        {
            "category":"Food & Beverages",
            "subcategory":"Specialty",
            "type":"Retail Goods"
        }
    ],
    "sg:postcode":"DE5 3AP",
    "sg:province":"Derbyshire",
    "sg:tags":[
        "product",
        "health"
    ],
    "wof:name":"Natural Choice",
    "wof:placetype":"venue"
},
  "geometry": {"coordinates":[-1.4042710066,53.0501403809],"type":"Point"}
}