{
  "type": "Feature",
  "properties": {
    "iso:country":"GB",
    "sg:address":"Pangbourne Junior School, Kennedy Drive, Pangbourne",
    "sg:city":"Reading",
    "sg:classifiers":[
        {
            "category":"Education",
            "subcategory":"School",
            "type":"Public Place"
        },
        {
            "category":"Government",
            "subcategory":"Office",
            "type":"Public Place"
        }
    ],
    "sg:phone":"+44 118 984 2315",
    "sg:postcode":"RG8 7LB",
    "sg:province":"Berkshire",
    "sg:tags":[
        "local",
        "authority"
    ],
    "wof:name":"Pangbourne Junior School",
    "wof:placetype":"venue"
},
  "geometry": {"coordinates":[-1.087338,51.482208],"type":"Point"}
}