{
  "type": "Feature",
  "properties": {
    "addr:full":"59 Newborough Scarborough North Yorkshire YO11 1ET",
    "addr:housenumber":"59",
    "addr:postcode":"yo11 1et",
    "addr:street":"Newborough",
    "iso:country":"GB",
    "sg:address":"59 Newborough",
    "sg:city":"Scarborough",
    "sg:classifiers":[
        {
            "category":"Shopping",
            "subcategory":"Discount & Variety Stores",
            "type":"Retail Goods"
        }
    ],
    "sg:phone":"+44 1723 503503",
    "sg:postcode":"YO11 1ET",
    "sg:province":"North Yorkshire",
    "sg:tags":[
        "shop",
        "model"
    ],
    "wof:name":"Arrow Models",
    "wof:placetype":"venue"
},
  "geometry": {"coordinates":[-0.398472,54.283112],"type":"Point"}
}