{
  "type": "Feature",
  "properties": {
    "addr:full":"258-260 Bedfont Lane Feltham Greater London TW14 9NU",
    "addr:housenumber":"258-260",
    "addr:postcode":"tw14 9nu",
    "addr:street":"Bedfont Lane",
    "iso:country":"GB",
    "sg:address":"258-260 Bedfont Lane",
    "sg:city":"Feltham",
    "sg:classifiers":[
        {
            "category":"Place Of Worship",
            "type":"Public Place"
        }
    ],
    "sg:phone":"+44 20 8844 2152",
    "sg:postcode":"TW14 9NU",
    "sg:province":"Greater London",
    "wof:name":"Calvary Baptist Church",
    "wof:placetype":"venue"
},
  "geometry": {"coordinates":[-0.4207819998,51.4505462646],"type":"Point"}
}