{
  "type": "Feature",
  "properties": {
    "addr:full":"52 Albany Park Road Kingston-upon-thames Greater London KT2 5SU",
    "addr:housenumber":"52",
    "addr:postcode":"kt2 5su",
    "addr:street":"Albany Park Road",
    "iso:country":"GB",
    "sg:address":"52 Albany Park Road",
    "sg:city":"Kingston-upon-thames",
    "sg:classifiers":[
        {
            "category":"Professional",
            "subcategory":"Business Services",
            "type":"Services"
        }
    ],
    "sg:phone":"+44 20 8546 3235",
    "sg:postcode":"KT2 5SU",
    "sg:province":"Greater London",
    "sg:tags":[
        "import",
        "export",
        "agent"
    ],
    "wof:name":"Kay Electronics",
    "wof:placetype":"venue"
},
  "geometry": {"coordinates":[-0.3042770028,51.4229202271],"type":"Point"}
}