{
  "type": "Feature",
  "properties": {
    "addr:full":"Unit 3a Beechwood, Chineham Business Park, Chineham Basingstoke Hampshire RG24 8WA",
    "addr:housenumber":"unit 3a",
    "addr:postcode":"rg24 8wa",
    "addr:street":"Business Park",
    "iso:country":"GB",
    "sg:address":"Unit 3a Beechwood, Chineham Business Park, Chineham",
    "sg:city":"Basingstoke",
    "sg:classifiers":[
        {
            "category":"Manufacturing",
            "subcategory":"Tools & Machinery",
            "type":"Manufacturing & Wholesale Goods"
        }
    ],
    "sg:phone":"+44 1256 708087",
    "sg:postcode":"RG24 8WA",
    "sg:province":"Hampshire",
    "wof:name":"Pullmax Ltd.",
    "wof:placetype":"venue"
},
  "geometry": {"coordinates":[-1.052407,51.289032],"type":"Point"}
}