{
  "type": "Feature",
  "properties": {
    "iso:country":"GB",
    "sg:address":"35 Birchwood Lane, Somercotes",
    "sg:city":"Alfreton",
    "sg:classifiers":[
        {
            "category":"Food & Beverages",
            "subcategory":"Supermarket",
            "type":"Retail Goods"
        },
        {
            "category":"Food & Beverages",
            "subcategory":"Fruits & Vegetables",
            "type":"Retail Goods"
        }
    ],
    "sg:phone":"+44 1773 606284",
    "sg:postcode":"DE55 4ND",
    "sg:province":"Derbyshire",
    "sg:tags":[
        "greengrocer"
    ],
    "wof:name":"Bailey's",
    "wof:placetype":"venue"
},
  "geometry": {"coordinates":[-1.3657879829,53.0808868408],"type":"Point"}
}