{
  "type": "Feature",
  "properties": {
    "addr:full":"Lickhill Stourport On Severn Worcestershire DY13 8RL",
    "addr:postcode":"dy13 8rl",
    "iso:country":"GB",
    "sg:address":"Lickhill",
    "sg:city":"Stourport On Severn",
    "sg:classifiers":[
        {
            "category":"Health Services",
            "subcategory":"Nursing And Care Facility",
            "type":"Services"
        }
    ],
    "sg:phone":"+44 1299 827790",
    "sg:postcode":"DY13 8RL",
    "sg:province":"Worcestershire",
    "sg:tags":[
        "home"
    ],
    "wof:name":"Lickhill Manor Nursing Home",
    "wof:placetype":"venue"
},
  "geometry": {"coordinates":[-2.283696,52.342346],"type":"Point"}
}