{
  "type": "Feature",
  "properties": {
    "addr:full":"36 Hunters Way Uckfield East Sussex TN22 2BB",
    "addr:housenumber":"36",
    "addr:postcode":"tn22 2bb",
    "addr:street":"Hunters Way",
    "iso:country":"GB",
    "sg:address":"36 Hunters Way",
    "sg:city":"Uckfield",
    "sg:classifiers":[
        {
            "category":"Professional",
            "subcategory":"Art Services",
            "type":"Services"
        }
    ],
    "sg:phone":"+44 1825 761031",
    "sg:postcode":"TN22 2BB",
    "sg:province":"East Sussex",
    "sg:tags":[
        "photographer"
    ],
    "wof:name":"J R M Photography",
    "wof:placetype":"venue"
},
  "geometry": {"coordinates":[0.092432,50.977039],"type":"Point"}
}