{
  "type": "Feature",
  "properties": {
    "iso:country":"GB",
    "sg:address":"51 Goldsworthy Road, Flixton",
    "sg:city":"Manchester",
    "sg:classifiers":[
        {
            "category":"Parking",
            "type":"Transportation"
        }
    ],
    "sg:postcode":"M41 8TF",
    "sg:province":"Cheshire",
    "sg:tags":[
        "car",
        "valet"
    ],
    "wof:name":"Autosheen",
    "wof:placetype":"venue"
},
  "geometry": {"coordinates":[-2.389569,53.451038],"type":"Point"}
}