{
  "type": "Feature",
  "properties": {
    "iso:country":"GB",
    "sg:address":"174 Sloane Street",
    "sg:city":"London",
    "sg:classifiers":[
        {
            "category":"Shopping",
            "subcategory":"Clothing, Apparel, & Fashions",
            "type":"Retail Goods"
        }
    ],
    "sg:phone":"+44 20 7235 5855",
    "sg:postcode":"SW1X 9QG",
    "sg:province":"Greater London",
    "sg:tags":[
        "shop"
    ],
    "wof:name":"Tuula Fashion House Ltd.",
    "wof:placetype":"venue"
},
  "geometry": {"coordinates":[-0.1595419943,51.5000457764],"type":"Point"}
}