{
  "type": "Feature",
  "properties": {
    "iso:country":"GB",
    "sg:address":"20 Peninsula Sq",
    "sg:city":"Winchester",
    "sg:classifiers":[
        {
            "category":"Communications",
            "type":"Services"
        }
    ],
    "sg:phone":"+44 1962 842771",
    "sg:postcode":"SO23 8GJ",
    "sg:province":"Hampshire",
    "sg:tags":[
        "data",
        "network"
    ],
    "wof:name":"Aztec International Ltd",
    "wof:placetype":"venue"
},
  "geometry": {"coordinates":[-1.321392,51.061489],"type":"Point"}
}