{
  "type": "Feature",
  "properties": {
    "addr:full":"Springburn Depot, 79 Charles St Glasgow East Dunbartonshire G21 2PS",
    "addr:housenumber":"79",
    "addr:postcode":"g21 2ps",
    "addr:street":"Charles St",
    "iso:country":"GB",
    "sg:address":"Springburn Depot, 79 Charles St",
    "sg:city":"Glasgow",
    "sg:classifiers":[
        {
            "category":"Train Station",
            "subcategory":"Rail",
            "type":"Transportation"
        }
    ],
    "sg:phone":"+44 141 335 2782",
    "sg:postcode":"G21 2PS",
    "sg:province":"East Dunbartonshire",
    "sg:tags":[
        "railway"
    ],
    "wof:name":"Railcare",
    "wof:placetype":"venue"
},
  "geometry": {"coordinates":[-4.2313799858,55.8708000183],"type":"Point"}
}