{
  "type": "Feature",
  "properties": {
    "addr:full":"194 Port Road East Barry The Vale of Glamorgan CF62 9PZ",
    "addr:housenumber":"194",
    "addr:postcode":"cf62 9pz",
    "addr:street":"Port Road East;Vale",
    "iso:country":"GB",
    "sg:address":"194 Port Road East",
    "sg:city":"Barry",
    "sg:classifiers":[
        {
            "category":"Home & Garden",
            "subcategory":"Home Furnishings",
            "type":"Retail Goods"
        },
        {
            "category":"Home & Garden",
            "subcategory":"Building Materials",
            "type":"Retail Goods"
        }
    ],
    "sg:phone":"+44 1446 737380",
    "sg:postcode":"CF62 9PZ",
    "sg:province":"The Vale of Glamorgan",
    "sg:tags":[
        "installers",
        "planner",
        "kitchen",
        "furnishers"
    ],
    "wof:name":"Tony Dutton Kitchens",
    "wof:placetype":"venue"
},
  "geometry": {"coordinates":[-3.2719891071,51.42552948],"type":"Point"}
}