{
  "type": "Feature",
  "properties": {
    "addr:full":"21 Birch Ave, Haslingden Rossendale Lancashire BB4 5NF",
    "addr:housenumber":"21",
    "addr:postcode":"bb4 5nf",
    "addr:street":"Birch Ave",
    "iso:country":"GB",
    "sg:address":"21 Birch Ave, Haslingden",
    "sg:city":"Rossendale",
    "sg:classifiers":[
        {
            "category":"Fast Food",
            "type":"Food & Drink"
        },
        {
            "category":"Food & Beverages",
            "subcategory":"Meat & Fish",
            "type":"Retail Goods"
        }
    ],
    "sg:postcode":"BB4 5NF",
    "sg:province":"Lancashire",
    "sg:tags":[
        "chip",
        "away",
        "take"
    ],
    "wof:name":"Desai,S,",
    "wof:placetype":"venue"
},
  "geometry": {"coordinates":[-2.318787,53.703972],"type":"Point"}
}