{
  "type": "Feature",
  "properties": {
    "addr:full":"97 Hobs Moat Road Solihull West Midlands B92 8JL",
    "addr:housenumber":"97",
    "addr:postcode":"b92 8jl",
    "addr:street":"Hobs Moat Road",
    "iso:country":"GB",
    "sg:address":"97 Hobs Moat Road",
    "sg:city":"Solihull",
    "sg:classifiers":[
        {
            "category":"Wholesale",
            "subcategory":"Electrical",
            "type":"Manufacturing & Wholesale Goods"
        },
        {
            "category":"Shopping",
            "subcategory":"Computers & Home Electronics",
            "type":"Retail Goods"
        }
    ],
    "sg:phone":"+44 121 743 9990",
    "sg:postcode":"B92 8JL",
    "sg:province":"West Midlands",
    "sg:tags":[
        "wholesaler"
    ],
    "wof:name":"Electric Centre Ltd",
    "wof:placetype":"venue"
},
  "geometry": {"coordinates":[-1.785223,52.44397],"type":"Point"}
}