{
  "type": "Feature",
  "properties": {
    "addr:full":"Roath House, 100 Pen-y-lan Road, Roath Park Cardiff Cardiff CF23 5RH",
    "addr:housenumber":"100",
    "addr:postcode":"cf23 5rh",
    "addr:street":"Pen-Y-Lan Road Roath Park",
    "iso:country":"GB",
    "sg:address":"Roath House, 100 Pen-y-lan Road, Roath Park",
    "sg:city":"Cardiff",
    "sg:classifiers":[
        {
            "category":"Health Services",
            "subcategory":"Doctor",
            "type":"Services"
        }
    ],
    "sg:phone":"+44 29 2046 1100",
    "sg:postcode":"CF23 5RH",
    "sg:province":"Cardiff",
    "sg:tags":[
        "practitioners"
    ],
    "wof:name":"ROATH HOUSE SURGERY",
    "wof:placetype":"venue"
},
  "geometry": {"coordinates":[-3.1620481014,51.4988059998],"type":"Point"}
}