{
  "type": "Feature",
  "properties": {
    "iso:country":"GB",
    "sg:address":"Broadview, Warkleigh",
    "sg:city":"Umberleigh",
    "sg:classifiers":[
        {
            "category":"Farming",
            "subcategory":"Livestock Farm",
            "type":"Manufacturing & Wholesale Goods"
        },
        {
            "category":"Farming",
            "subcategory":"Farm",
            "type":"Manufacturing & Wholesale Goods"
        }
    ],
    "sg:postcode":"EX37 9DW",
    "sg:province":"Devon",
    "sg:tags":[
        "mixed",
        "crop",
        "others"
    ],
    "wof:name":"Colin C Hammett",
    "wof:placetype":"venue"
},
  "geometry": {"coordinates":[-3.9853448868,50.9958152771],"type":"Point"}
}