{
  "type": "Feature",
  "properties": {
    "iso:country":"GB",
    "sg:address":"Redbrook Lane Ind Est, Redbrook Lane, Brereton",
    "sg:city":"Rugeley",
    "sg:classifiers":[
        {
            "category":"Wholesale",
            "subcategory":"Meat",
            "type":"Manufacturing & Wholesale Goods"
        }
    ],
    "sg:phone":"+44 1283 533207",
    "sg:postcode":"WS15 1QU",
    "sg:province":"Staffordshire",
    "sg:tags":[
        "product"
    ],
    "wof:name":"PAUL SEAL COOKED MEATS",
    "wof:placetype":"venue"
},
  "geometry": {"coordinates":[-1.924724,52.748409],"type":"Point"}
}