{
  "type": "Feature",
  "properties": {
    "addr:full":"76 Doncaster Rd Barnsley South Yorkshire S70 1TW",
    "addr:housenumber":"76",
    "addr:postcode":"s70 1tw",
    "addr:street":"Doncaster Rd;Yorkshire",
    "iso:country":"GB",
    "sg:address":"76 Doncaster Rd",
    "sg:city":"Barnsley",
    "sg:classifiers":[
        {
            "category":"Building & Trades",
            "subcategory":"Construction",
            "type":"Services"
        }
    ],
    "sg:postcode":"S70 1TW",
    "sg:province":"South Yorkshire",
    "sg:tags":[
        "demolition",
        "contractor"
    ],
    "wof:name":"Autogel Ltd",
    "wof:placetype":"venue"
},
  "geometry": {"coordinates":[-1.473616,53.549446],"type":"Point"}
}