{
  "type": "Feature",
  "properties": {
    "addr:full":"1 Brymore Close Bridgwater Somerset TA6 7PL",
    "addr:housenumber":"1",
    "addr:postcode":"ta6 7pl",
    "addr:street":"Brymore Close",
    "iso:country":"GB",
    "sg:address":"1 Brymore Close",
    "sg:city":"Bridgwater",
    "sg:classifiers":[
        {
            "category":"Building & Trades",
            "subcategory":"Construction",
            "type":"Services"
        }
    ],
    "sg:phone":"+44 1278 427837",
    "sg:postcode":"TA6 7PL",
    "sg:province":"Somerset",
    "sg:tags":[
        "decorator",
        "painter"
    ],
    "wof:name":"Dave Handel",
    "wof:placetype":"venue"
},
  "geometry": {"coordinates":[-3.018835,51.127876],"type":"Point"}
}