{
  "type": "Feature",
  "properties": {
    "iso:country":"GB",
    "sg:address":"Tilehurst Surgery, Tylers Pl",
    "sg:city":"Reading",
    "sg:classifiers":[
        {
            "category":"Health Services",
            "subcategory":"Doctor",
            "type":"Services"
        }
    ],
    "sg:phone":"+44 118 942 7528",
    "sg:postcode":"RG30 6BW",
    "sg:province":"Berkshire",
    "sg:tags":[
        "practitioners"
    ],
    "wof:name":"Boulos, G",
    "wof:placetype":"venue"
},
  "geometry": {"coordinates":[-0.96301,51.453522],"type":"Point"}
}