{
  "type": "Feature",
  "properties": {
    "addr:full":"Welsh House Farm Road Birmingham West Midlands B32 2NG",
    "addr:postcode":"b32 2ng",
    "addr:street":"Farm Road",
    "iso:country":"GB",
    "sg:address":"Welsh House Farm Road",
    "sg:city":"Birmingham",
    "sg:classifiers":[
        {
            "category":"Education",
            "subcategory":"School",
            "type":"Public Place"
        },
        {
            "category":"Government",
            "subcategory":"Office",
            "type":"Public Place"
        }
    ],
    "sg:phone":"+44 121 427 4355",
    "sg:postcode":"B32 2NG",
    "sg:province":"West Midlands",
    "sg:tags":[
        "local",
        "authority"
    ],
    "wof:name":"Welsh House Farm Junior & Infant School",
    "wof:placetype":"venue"
},
  "geometry": {"coordinates":[-1.969869,52.45541],"type":"Point"}
}