{
  "type": "Feature",
  "properties": {
    "addr:full":"70 Charlotte Street London Greater London W1T 4QG",
    "addr:housenumber":"70",
    "addr:postcode":"w1t 4qg",
    "addr:street":"Charlotte Street",
    "iso:country":"GB",
    "sg:address":"70 Charlotte Street",
    "sg:city":"London",
    "sg:classifiers":[
        {
            "category":"Professional",
            "subcategory":"Lawyer & Legal Services",
            "type":"Services"
        }
    ],
    "sg:phone":"+44 20 7323 6450",
    "sg:postcode":"W1T 4QG",
    "sg:province":"Greater London",
    "sg:tags":[
        "solicitor"
    ],
    "wof:name":"Fuglers",
    "wof:placetype":"venue"
},
  "geometry": {"coordinates":[-0.136536,51.520458],"type":"Point"}
}