{
  "type": "Feature",
  "properties": {
    "iso:country":"GB",
    "sg:address":"The Lodge, Sutton Bassett",
    "sg:city":"Market Harborough",
    "sg:classifiers":[
        {
            "category":"Organizations",
            "subcategory":"Membership Organization",
            "type":"Services"
        }
    ],
    "sg:postcode":"LE16 8HL",
    "sg:province":"Leicestershire",
    "sg:tags":[
        "club"
    ],
    "wof:name":"The British Berrichon du Cher Sheep Society Ltd.",
    "wof:placetype":"venue"
},
  "geometry": {"coordinates":[-0.86887,52.493938],"type":"Point"}
}