{
  "type": "Feature",
  "properties": {
    "addr:full":"8 Spring Villa Road Edgware Greater London HA8 7XT",
    "addr:housenumber":"8",
    "addr:postcode":"ha8 7xt",
    "addr:street":"Spring Villa Road",
    "iso:country":"GB",
    "sg:address":"8 Spring Villa Road",
    "sg:city":"Edgware",
    "sg:classifiers":[
        {
            "category":"Wholesale",
            "subcategory":"Furniture",
            "type":"Manufacturing & Wholesale Goods"
        },
        {
            "category":"Building & Trades",
            "subcategory":"Equipment Rental",
            "type":"Services"
        }
    ],
    "sg:phone":"+44 20 8951 5188",
    "sg:postcode":"HA8 7XT",
    "sg:province":"Greater London",
    "sg:tags":[
        "supply"
    ],
    "wof:name":"United Jewellery Trading Ltd",
    "wof:placetype":"venue"
},
  "geometry": {"coordinates":[-0.278626,51.608654],"type":"Point"}
}