{
  "type": "Feature",
  "properties": {
    "addr:full":"90 Bramshott Road Southsea Hampshire PO4 8AW",
    "addr:housenumber":"90",
    "addr:postcode":"po4 8aw",
    "addr:street":"Bramshott Road",
    "iso:country":"GB",
    "sg:address":"90 Bramshott Road",
    "sg:city":"Southsea",
    "sg:classifiers":[
        {
            "category":"Building & Trades",
            "subcategory":"Construction",
            "type":"Services"
        }
    ],
    "sg:phone":"+44 23 9278 0479",
    "sg:postcode":"PO4 8AW",
    "sg:province":"Hampshire",
    "sg:tags":[
        "tiling",
        "contractor"
    ],
    "wof:name":"S W Ceramics",
    "wof:placetype":"venue"
},
  "geometry": {"coordinates":[-1.063614,50.792862],"type":"Point"}
}