{
  "type": "Feature",
  "properties": {
    "iso:country":"GB",
    "sg:address":"73 Outgang Road, Aspatria",
    "sg:city":"Wigton",
    "sg:classifiers":[
        {
            "category":"Freight",
            "type":"Transportation"
        }
    ],
    "sg:phone":"+44 16973 20901",
    "sg:postcode":"CA7 3HZ",
    "sg:province":"Cumbria",
    "sg:tags":[
        "haulage",
        "transport",
        "road"
    ],
    "wof:name":"J I Mccracken",
    "wof:placetype":"venue"
},
  "geometry": {"coordinates":[-3.3301069736,54.7680511475],"type":"Point"}
}