{
  "type": "Feature",
  "properties": {
    "addr:full":"3 Woodgate Loughborough Leicestershire LE11 2TY",
    "addr:housenumber":"3",
    "addr:postcode":"le11 2ty",
    "addr:street":"Woodgate",
    "iso:country":"GB",
    "sg:address":"3 Woodgate",
    "sg:city":"Loughborough",
    "sg:classifiers":[
        {
            "category":"Professional",
            "type":"Services"
        }
    ],
    "sg:phone":"+44 1509 216005",
    "sg:postcode":"LE11 2TY",
    "sg:province":"Leicestershire",
    "sg:tags":[
        "shopfitters"
    ],
    "wof:name":"K S Services (U K) Ltd.",
    "wof:placetype":"venue"
},
  "geometry": {"coordinates":[-1.18511,52.827049],"type":"Point"}
}