{
  "type": "Feature",
  "properties": {
    "addr:full":"70-72 High Street Daventry Northamptonshire NN11 4HU",
    "addr:housenumber":"70-72",
    "addr:postcode":"nn11 4hu",
    "addr:street":"High Street",
    "iso:country":"GB",
    "sg:address":"70-72 High Street",
    "sg:city":"Daventry",
    "sg:classifiers":[
        {
            "category":"Restaurant",
            "type":"Food & Drink"
        }
    ],
    "sg:phone":"+44 1327 876028",
    "sg:postcode":"NN11 4HU",
    "sg:province":"Northamptonshire",
    "wof:name":"Good Luck Cantonese",
    "wof:placetype":"venue"
},
  "geometry": {"coordinates":[-1.1637979746,52.2578239441],"type":"Point"}
}