{
  "type": "Feature",
  "properties": {
    "addr:full":"90 Barry Rd East Dulwich Greater London SE22 0HP",
    "addr:housenumber":"90",
    "addr:postcode":"se22 0hp",
    "addr:street":"Barry Rd",
    "iso:country":"GB",
    "sg:address":"90 Barry Rd",
    "sg:city":"East Dulwich",
    "sg:classifiers":[
        {
            "category":"Health Services",
            "subcategory":"Health Practitioner",
            "type":"Services"
        }
    ],
    "sg:phone":"+44 20 8693 6621",
    "sg:postcode":"SE22 0HP",
    "sg:province":"Greater London",
    "sg:tags":[
        "therapist",
        "speech"
    ],
    "wof:name":"The Dulwich Art Therapy Practice",
    "wof:placetype":"venue"
},
  "geometry": {"coordinates":[-0.0686490014,51.4557952881],"type":"Point"}
}