{
  "type": "Feature",
  "properties": {
    "addr:full":"2 Oak Grn, Winchester Road, Four Marks Alton Hampshire GU34 5HQ",
    "addr:housenumber":"2",
    "addr:postcode":"gu34 5hq",
    "addr:street":"Oak Grn Winchester Road",
    "iso:country":"GB",
    "sg:address":"2 Oak Grn, Winchester Road, Four Marks",
    "sg:city":"Alton",
    "sg:classifiers":[
        {
            "category":"Retail",
            "subcategory":"Repair Shop",
            "type":"Services"
        }
    ],
    "sg:phone":"+44 1420 563652",
    "sg:postcode":"GU34 5HQ",
    "sg:province":"Hampshire",
    "sg:tags":[
        "radio",
        "television",
        "video"
    ],
    "wof:name":"Hillary Services Ltd.",
    "wof:placetype":"venue"
},
  "geometry": {"coordinates":[-1.0418640375,51.1129951477],"type":"Point"}
}