{
  "type": "Feature",
  "properties": {
    "addr:full":"Hellaby Lane Business Park, Hellaby Rotherham South Yorkshire S66 8HN",
    "addr:postcode":"s66 8hn",
    "addr:street":"Hellaby Lane Business Park",
    "iso:country":"GB",
    "sg:address":"Hellaby Lane Business Park, Hellaby",
    "sg:city":"Rotherham",
    "sg:classifiers":[
        {
            "category":"Autos & Motor Vehicles",
            "subcategory":"Automobile Sales",
            "type":"Retail Goods"
        }
    ],
    "sg:phone":"+44 1709 533747",
    "sg:postcode":"S66 8HN",
    "sg:province":"South Yorkshire",
    "sg:tags":[
        "commercial"
    ],
    "wof:name":"Autotec Vehicles Ltd.",
    "wof:placetype":"venue"
},
  "geometry": {"coordinates":[-1.243719,53.422825],"type":"Point"}
}