{
  "type": "Feature",
  "properties": {
    "iso:country":"GB",
    "sg:address":"22 New Street",
    "sg:city":"Chipping Norton",
    "sg:classifiers":[
        {
            "category":"Cafe",
            "type":"Food & Drink"
        }
    ],
    "sg:phone":"+44 1608 641100",
    "sg:postcode":"OX7 5LJ",
    "sg:province":"Gloucestershire",
    "sg:tags":[
        "tea",
        "room"
    ],
    "wof:name":"Jj Diner",
    "wof:placetype":"venue"
},
  "geometry": {"coordinates":[-1.547013,51.941341],"type":"Point"}
}