{
  "type": "Feature",
  "properties": {
    "iso:country":"GB",
    "sg:address":"9 Boltyon Road, Silsden",
    "sg:city":"Bradford",
    "sg:classifiers":[
        {
            "category":"Home & Garden",
            "subcategory":"Furniture",
            "type":"Retail Goods"
        }
    ],
    "sg:phone":"+44 1535 655599",
    "sg:postcode":"BD20 0JY",
    "sg:province":"North Yorkshire",
    "wof:name":"Jay-Pine",
    "wof:placetype":"venue"
},
  "geometry": {"coordinates":[-1.9373049736,53.915309906],"type":"Point"}
}