{
  "type": "Feature",
  "properties": {
    "addr:full":"5 Church Street Hereford Herefordshire HR1 2LT",
    "addr:housenumber":"5",
    "addr:postcode":"hr1 2lt",
    "addr:street":"Church Street",
    "iso:country":"GB",
    "sg:address":"5 Church Street",
    "sg:city":"Hereford",
    "sg:classifiers":[
        {
            "category":"Shopping",
            "subcategory":"Tobacco",
            "type":"Retail Goods"
        }
    ],
    "sg:postcode":"HR1 2LT",
    "sg:province":"Herefordshire",
    "sg:tags":[
        "product",
        "tobacconist",
        "sale"
    ],
    "wof:name":"Peter Brundrett",
    "wof:placetype":"venue"
},
  "geometry": {"coordinates":[-2.715970993,52.0557060242],"type":"Point"}
}