{
  "type": "Feature",
  "properties": {
    "addr:full":"Thirlmere Suite,50 Lakes Rd, Derwent Howe Workington Cumbria CA14 3YP",
    "addr:housenumber":"50",
    "addr:postcode":"ca14 3yp",
    "addr:street":"Lakes Rd",
    "iso:country":"GB",
    "sg:address":"Thirlmere Suite,50 Lakes Rd, Derwent Howe",
    "sg:city":"Workington",
    "sg:classifiers":[
        {
            "category":"Social Services",
            "subcategory":"Job Training",
            "type":"Services"
        }
    ],
    "sg:phone":"+44 1900 871117",
    "sg:postcode":"CA14 3YP",
    "sg:province":"Cumbria",
    "sg:tags":[
        "draughtsman",
        "drawing"
    ],
    "wof:name":"Embee Draughting Services Ltd",
    "wof:placetype":"venue"
},
  "geometry": {"coordinates":[-3.542458,54.635746],"type":"Point"}
}