{
  "type": "Feature",
  "properties": {
    "addr:full":"Unit 5 Yeoman Street London Greater London SE8 5DU",
    "addr:housenumber":"unit 5",
    "addr:postcode":"se8 5du",
    "addr:street":"Yeoman Street",
    "iso:country":"GB",
    "sg:address":"Unit 5 Yeoman Street",
    "sg:city":"London",
    "sg:classifiers":[
        {
            "category":"Manufacturing",
            "subcategory":"Building Materials",
            "type":"Manufacturing & Wholesale Goods"
        }
    ],
    "sg:phone":"+44 20 8450 8161",
    "sg:postcode":"SE8 5DU",
    "sg:province":"Greater London",
    "sg:tags":[
        "mnfr",
        "marble",
        "specialist"
    ],
    "wof:name":"Trans-am Contracting Ltd.",
    "wof:placetype":"venue"
},
  "geometry": {"coordinates":[-0.04024,51.492481],"type":"Point"}
}