{
  "type": "Feature",
  "properties": {
    "iso:country":"GB",
    "sg:address":"9 Cavendish Place",
    "sg:city":"London",
    "sg:classifiers":[
        {
            "category":"Building & Trades",
            "subcategory":"Construction",
            "type":"Services"
        }
    ],
    "sg:phone":"+44 20 7323 0203",
    "sg:postcode":"W1G 0NQ",
    "sg:province":"Greater London",
    "sg:tags":[
        "builder"
    ],
    "wof:name":"Nishimatsu Construction Co. Ltd.",
    "wof:placetype":"venue"
},
  "geometry": {"coordinates":[-0.144269,51.516876],"type":"Point"}
}