{
  "type": "Feature",
  "properties": {
    "addr:full":"Three Ashes Hereford Herefordshire HR2 8LX",
    "addr:postcode":"hr2 8lx",
    "iso:country":"GB",
    "sg:address":"Three Ashes",
    "sg:city":"Hereford",
    "sg:classifiers":[
        {
            "category":"Home & Garden",
            "subcategory":"Garden Supply",
            "type":"Retail Goods"
        }
    ],
    "sg:phone":"+44 1981 580100",
    "sg:postcode":"HR2 8LX",
    "sg:province":"Herefordshire",
    "sg:tags":[
        "nursery",
        "centre"
    ],
    "wof:name":"Premier Plant Centre Ltd",
    "wof:placetype":"venue"
},
  "geometry": {"coordinates":[-2.70998,51.903049],"type":"Point"}
}