{
  "type": "Feature",
  "properties": {
    "addr:full":"1 Clifton Rd Bournemouth Dorset BH6 3NZ",
    "addr:housenumber":"1",
    "addr:postcode":"bh6 3nz",
    "addr:street":"Clifton Rd",
    "iso:country":"GB",
    "sg:address":"1 Clifton Rd",
    "sg:city":"Bournemouth",
    "sg:classifiers":[
        {
            "category":"Health Services",
            "subcategory":"Nursing And Care Facility",
            "type":"Services"
        }
    ],
    "sg:phone":"+44 1202 428132",
    "sg:postcode":"BH6 3NZ",
    "sg:province":"Dorset",
    "sg:tags":[
        "home"
    ],
    "wof:name":"Seabourne Nursing Home",
    "wof:placetype":"venue"
},
  "geometry": {"coordinates":[-1.8072249889,50.7234077454],"type":"Point"}
}