{
  "type": "Feature",
  "properties": {
    "iso:country":"GB",
    "sg:address":"74 Queensland Drive",
    "sg:city":"Colchester",
    "sg:classifiers":[
        {
            "category":"Shopping",
            "subcategory":"Photographic Equipment",
            "type":"Retail Goods"
        }
    ],
    "sg:phone":"+44 1206 762090",
    "sg:postcode":"CO2 8UQ",
    "sg:province":"Essex",
    "wof:name":"A.C.M. Photography",
    "wof:placetype":"venue"
},
  "geometry": {"coordinates":[0.9101449847,51.8648223877],"type":"Point"}
}