{
  "type": "Feature",
  "properties": {
    "addr:full":"Hill Top Farm, Stoke Prior Leominster Herefordshire HR6 0LH",
    "addr:postcode":"hr6 0lh",
    "addr:street":"Stoke Prior",
    "iso:country":"GB",
    "sg:address":"Hill Top Farm, Stoke Prior",
    "sg:city":"Leominster",
    "sg:classifiers":[
        {
            "category":"Farming",
            "subcategory":"Livestock Farm",
            "type":"Manufacturing & Wholesale Goods"
        }
    ],
    "sg:phone":"+44 1568 760657",
    "sg:postcode":"HR6 0LH",
    "sg:province":"Herefordshire",
    "sg:tags":[
        "others"
    ],
    "wof:name":"Arnold J Godfrey",
    "wof:placetype":"venue"
},
  "geometry": {"coordinates":[-2.7021501064,52.206161499],"type":"Point"}
}