{
  "type": "Feature",
  "properties": {
    "addr:full":"12 Linden Road, Denton Manchester Greater Manchester M34 6EF",
    "addr:housenumber":"12",
    "addr:postcode":"m34 6ef",
    "addr:street":"Linden Road",
    "iso:country":"GB",
    "sg:address":"12 Linden Road, Denton",
    "sg:city":"Manchester",
    "sg:classifiers":[
        {
            "category":"Building & Trades",
            "subcategory":"Construction",
            "type":"Services"
        }
    ],
    "sg:phone":"+44 161 320 8438",
    "sg:postcode":"M34 6EF",
    "sg:province":"Greater Manchester",
    "sg:tags":[
        "builder"
    ],
    "wof:name":"P & A Smith Joiners & Builders",
    "wof:placetype":"venue"
},
  "geometry": {"coordinates":[-2.102416,53.45541],"type":"Point"}
}