{
  "type": "Feature",
  "properties": {
    "addr:full":"59 Broomlands Street Paisley Renfrewshire PA1 2NH",
    "addr:housenumber":"59",
    "addr:postcode":"pa1 2nh",
    "addr:street":"Broomlands Street",
    "iso:country":"GB",
    "sg:address":"59 Broomlands Street",
    "sg:city":"Paisley",
    "sg:classifiers":[
        {
            "category":"Fast Food",
            "type":"Food & Drink"
        },
        {
            "category":"Restaurant",
            "type":"Food & Drink"
        }
    ],
    "sg:phone":"+44 141 889 9325",
    "sg:postcode":"PA1 2NH",
    "sg:province":"Renfrewshire",
    "sg:tags":[
        "away",
        "indian",
        "meal",
        "outlet",
        "take"
    ],
    "wof:name":"RESTAURANT MIRAGE LTD",
    "wof:placetype":"venue"
},
  "geometry": {"coordinates":[-4.443954,55.842068],"type":"Point"}
}