{
  "type": "Feature",
  "properties": {
    "addr:full":"23 North Dean Maidenhead Berkshire SL6 7JD",
    "addr:housenumber":"23",
    "addr:postcode":"sl6 7jd",
    "addr:street":"North Dean",
    "iso:country":"GB",
    "sg:address":"23 North Dean",
    "sg:city":"Maidenhead",
    "sg:classifiers":[
        {
            "category":"Education",
            "subcategory":"Music School",
            "type":"Public Place"
        }
    ],
    "sg:phone":"+44 1628 629944",
    "sg:postcode":"SL6 7JD",
    "sg:province":"Berkshire",
    "sg:tags":[
        "teacher"
    ],
    "wof:name":"Denise Baldwin",
    "wof:placetype":"venue"
},
  "geometry": {"coordinates":[-0.7196840048,51.5301322937],"type":"Point"}
}