{
  "type": "Feature",
  "properties": {
    "iso:country":"GB",
    "sg:address":"2 West Canal Street",
    "sg:city":"Coatbridge",
    "sg:classifiers":[
        {
            "category":"Military Area",
            "subcategory":"Air Force Base",
            "type":"Public Place"
        }
    ],
    "sg:phone":"+44 1236 434343",
    "sg:postcode":"ML5 1QB",
    "sg:province":"North Lanarkshire",
    "sg:tags":[
        "taxi",
        "hire",
        "private"
    ],
    "wof:name":"Fountain Radio Cars",
    "wof:placetype":"venue"
},
  "geometry": {"coordinates":[-4.0334558487,55.8618278503],"type":"Point"}
}