{
  "type": "Feature",
  "properties": {
    "iso:country":"GB",
    "sg:address":"25-35 Ridgeway",
    "sg:city":"Rotherham",
    "sg:classifiers":[
        {
            "category":"Food & Beverages",
            "subcategory":"Groceries & Convenience Stores",
            "type":"Retail Goods"
        }
    ],
    "sg:phone":"+44 1709 850650",
    "sg:postcode":"S65 3PF",
    "sg:province":"South Yorkshire",
    "wof:name":"Gilberts",
    "wof:placetype":"venue"
},
  "geometry": {"coordinates":[-1.3183050156,53.4355430603],"type":"Point"}
}