{
  "type": "Feature",
  "properties": {
    "iso:country":"GB",
    "sg:address":"Swan House, Saddlers Row",
    "sg:city":"Petworth",
    "sg:classifiers":[
        {
            "category":"Personal",
            "subcategory":"Beauty Salon",
            "type":"Services"
        }
    ],
    "sg:postcode":"GU28 0AN",
    "sg:province":"West Sussex",
    "sg:tags":[
        "unisex",
        "hairdresser"
    ],
    "wof:name":"Elite Hair Studio",
    "wof:placetype":"venue"
},
  "geometry": {"coordinates":[-0.610806,50.986027],"type":"Point"}
}