{
  "type": "Feature",
  "properties": {
    "addr:full":"6 Hightown Road Luton Bedfordshire LU2 0DD",
    "addr:housenumber":"6",
    "addr:postcode":"lu2 0dd",
    "addr:street":"Hightown Road",
    "iso:country":"GB",
    "sg:address":"6 Hightown Road",
    "sg:city":"Luton",
    "sg:classifiers":[
        {
            "category":"Bus Charters",
            "type":"Transportation"
        },
        {
            "category":"Retail",
            "subcategory":"Storage",
            "type":"Services"
        }
    ],
    "sg:phone":"+44 1582 592728",
    "sg:postcode":"LU2 0DD",
    "sg:province":"Bedfordshire",
    "sg:tags":[
        "coach",
        "domestic",
        "activity",
        "removal"
    ],
    "wof:name":"Lutonian Buses Ltd.",
    "wof:placetype":"venue"
},
  "geometry": {"coordinates":[-0.4088590145,51.8863182068],"type":"Point"}
}