{
  "type": "Feature",
  "properties": {
    "iso:country":"GB",
    "sg:address":"8 Fellside Rd",
    "sg:city":"Newcastle Upon Tyne",
    "sg:classifiers":[
        {
            "category":"Professional",
            "type":"Services"
        }
    ],
    "sg:phone":"+44 191 496 0707",
    "sg:postcode":"NE16 4JX",
    "sg:province":"Durham",
    "sg:tags":[
        "specialist",
        "coating"
    ],
    "wof:name":"Premier Coating UK Ltd",
    "wof:placetype":"venue"
},
  "geometry": {"coordinates":[-1.683506,54.945038],"type":"Point"}
}