{
  "type": "Feature",
  "properties": {
    "addr:full":"298 Radford Road Nottingham Nottinghamshire NG7 5GN",
    "addr:housenumber":"298",
    "addr:postcode":"ng7 5gn",
    "addr:street":"Radford Road",
    "iso:country":"GB",
    "sg:address":"298 Radford Road",
    "sg:city":"Nottingham",
    "sg:classifiers":[
        {
            "category":"Utilities",
            "subcategory":"Telephone",
            "type":"Services"
        }
    ],
    "sg:phone":"+44 115 978 0754",
    "sg:postcode":"NG7 5GN",
    "sg:province":"Nottinghamshire",
    "sg:tags":[
        "telecommunication"
    ],
    "wof:name":"Telcom Services",
    "wof:placetype":"venue"
},
  "geometry": {"coordinates":[-1.1732490063,52.969203949],"type":"Point"}
}