{
  "type": "Feature",
  "properties": {
    "addr:full":"Cefn Coch, Llanrhydd Ruthin Denbighshire LL15 2UP",
    "addr:postcode":"ll15 2up",
    "iso:country":"GB",
    "sg:address":"Cefn Coch, Llanrhydd",
    "sg:city":"Ruthin",
    "sg:classifiers":[
        {
            "category":"Farming",
            "subcategory":"Livestock Farm",
            "type":"Manufacturing & Wholesale Goods"
        }
    ],
    "sg:phone":"+44 1824 702848",
    "sg:postcode":"LL15 2UP",
    "sg:province":"Denbighshire",
    "sg:tags":[
        "others"
    ],
    "wof:name":"E Edwards",
    "wof:placetype":"venue"
},
  "geometry": {"coordinates":[-3.283339,53.109943],"type":"Point"}
}