{
  "type": "Feature",
  "properties": {
    "iso:country":"GB",
    "sg:address":"Westbar",
    "sg:city":"Chesterfield",
    "sg:classifiers":[
        {
            "category":"Travel",
            "subcategory":"Hotels & Motels",
            "type":"Entertainment"
        }
    ],
    "sg:phone":"+44 1246 234502",
    "sg:postcode":"S40 1AY",
    "sg:province":"Derbyshire",
    "wof:name":"Portland Hotel",
    "wof:placetype":"venue"
},
  "geometry": {"coordinates":[-1.436529,53.235725],"type":"Point"}
}