{
  "type": "Feature",
  "properties": {
    "iso:country":"GB",
    "sg:address":"Po Box 246",
    "sg:city":"Aberdeen",
    "sg:classifiers":[
        {
            "category":"Professional",
            "subcategory":"Engineering",
            "type":"Services"
        }
    ],
    "sg:phone":"+44 1224 624466",
    "sg:postcode":"AB10 1PX",
    "sg:province":"Aberdeen City",
    "sg:tags":[
        "consulting",
        "design",
        "engineer"
    ],
    "wof:name":"Igl Consultants Ltd.",
    "wof:placetype":"venue"
},
  "geometry": {"coordinates":[-2.1095,57.145802],"type":"Point"}
}