{
  "type": "Feature",
  "properties": {
    "addr:full":"5 Regent Street Mansfield Nottinghamshire NG18 1ST",
    "addr:housenumber":"5",
    "addr:postcode":"ng18 1st",
    "addr:street":"Regent Street",
    "iso:country":"GB",
    "sg:address":"5 Regent Street",
    "sg:city":"Mansfield",
    "sg:classifiers":[
        {
            "category":"Shopping",
            "subcategory":"Clothing, Apparel, & Fashions",
            "type":"Retail Goods"
        }
    ],
    "sg:phone":"+44 1623 660300",
    "sg:postcode":"NG18 1ST",
    "sg:province":"Nottinghamshire",
    "sg:tags":[
        "shop"
    ],
    "wof:name":"Labrix Ltd.",
    "wof:placetype":"venue"
},
  "geometry": {"coordinates":[-1.19661,53.145096],"type":"Point"}
}