{
  "type": "Feature",
  "properties": {
    "addr:full":"Park Garage, Grampound Road Truro Cornwall TR2 4DP",
    "addr:postcode":"tr2 4dp",
    "addr:street":"Grampound Road",
    "iso:country":"GB",
    "sg:address":"Park Garage, Grampound Road",
    "sg:city":"Truro",
    "sg:classifiers":[
        {
            "category":"Retail",
            "subcategory":"Auto Repair",
            "type":"Services"
        }
    ],
    "sg:postcode":"TR2 4DP",
    "sg:province":"Cornwall",
    "sg:tags":[
        "modification",
        "garage"
    ],
    "wof:name":"D J Horton",
    "wof:placetype":"venue"
},
  "geometry": {"coordinates":[-4.929894,50.318291],"type":"Point"}
}