{
  "type": "Feature",
  "properties": {
    "addr:full":"Kings Chambers, 34 Queen Street Derby Derbyshire DE1 3DS",
    "addr:housenumber":"34",
    "addr:postcode":"de1 3ds",
    "addr:street":"Queen Street",
    "iso:country":"GB",
    "sg:address":"Kings Chambers, 34 Queen Street",
    "sg:city":"Derby",
    "sg:classifiers":[
        {
            "category":"Real Estate",
            "subcategory":"Surveying",
            "type":"Services"
        }
    ],
    "sg:postcode":"DE1 3DS",
    "sg:province":"Derbyshire",
    "sg:tags":[
        "surveyor",
        "valuer"
    ],
    "wof:name":"Steve Butler Chartered Surveyor",
    "wof:placetype":"venue"
},
  "geometry": {"coordinates":[-1.4836839437,52.9251708984],"type":"Point"}
}