{
  "type": "Feature",
  "properties": {
    "addr:full":"2 Page Road Clacton-on-sea Essex CO15 3AE",
    "addr:housenumber":"2",
    "addr:postcode":"co15 3ae",
    "addr:street":"Page Road",
    "iso:country":"GB",
    "sg:address":"2 Page Road",
    "sg:city":"Clacton-on-sea",
    "sg:classifiers":[
        {
            "category":"Building & Trades",
            "subcategory":"Landscaping Services",
            "type":"Services"
        }
    ],
    "sg:phone":"+44 1255 426864",
    "sg:postcode":"CO15 3AE",
    "sg:province":"Essex",
    "sg:tags":[
        "landscape",
        "contractor"
    ],
    "wof:name":"Clacton Landscapes",
    "wof:placetype":"venue"
},
  "geometry": {"coordinates":[1.1513409615,51.7938117981],"type":"Point"}
}