{
  "type": "Feature",
  "properties": {
    "iso:country":"GB",
    "sg:address":"Unit 4c, Ryknild Factory Estate",
    "sg:city":"Burton-on-trent",
    "sg:classifiers":[
        {
            "category":"Professional",
            "subcategory":"Printing & Photocopies",
            "type":"Services"
        }
    ],
    "sg:phone":"+44 1283 532771",
    "sg:postcode":"DE14 1RZ",
    "sg:province":"Derbyshire",
    "sg:tags":[
        "process",
        "screen",
        "printer"
    ],
    "wof:name":"Scorpion Display Advertising",
    "wof:placetype":"venue"
},
  "geometry": {"coordinates":[-1.625929,52.820694],"type":"Point"}
}