{
  "type": "Feature",
  "properties": {
    "addr:full":"79 St Audrey Avenue Bexleyheath Kent DA7 5DA",
    "addr:housenumber":"79",
    "addr:postcode":"da7 5da",
    "addr:street":"St Audrey Avenue",
    "iso:country":"GB",
    "sg:address":"79 St Audrey Avenue",
    "sg:city":"Bexleyheath",
    "sg:classifiers":[
        {
            "category":"Communications",
            "type":"Services"
        }
    ],
    "sg:phone":"+44 20 8304 2393",
    "sg:postcode":"DA7 5DA",
    "sg:province":"Kent",
    "sg:tags":[
        "telecommunication"
    ],
    "wof:name":"Sparkes Installation",
    "wof:placetype":"venue"
},
  "geometry": {"coordinates":[0.150838,51.468063],"type":"Point"}
}