{
  "type": "Feature",
  "properties": {
    "iso:country":"GB",
    "sg:address":"18 Gresham Road",
    "sg:city":"Brentwood",
    "sg:classifiers":[
        {
            "category":"Autos & Motor Vehicles",
            "subcategory":"Auto Supplies",
            "type":"Retail Goods"
        }
    ],
    "sg:phone":"+44 1277 215521",
    "sg:postcode":"CM14 4HN",
    "sg:province":"Essex",
    "sg:tags":[
        "tyre"
    ],
    "wof:name":"Brentwood Tyres Ltd.",
    "wof:placetype":"venue"
},
  "geometry": {"coordinates":[0.3011,51.6152],"type":"Point"}
}