{
  "type": "Feature",
  "properties": {
    "addr:full":"Station Rd, Whitecross Linlithgow Falkirk EH49 6JQ",
    "addr:postcode":"eh49 6jq",
    "addr:street":"Station Rd",
    "iso:country":"GB",
    "sg:address":"Station Rd, Whitecross",
    "sg:city":"Linlithgow",
    "sg:classifiers":[
        {
            "category":"Government",
            "subcategory":"Post Office",
            "type":"Public Place"
        }
    ],
    "sg:phone":"+44 1506 848162",
    "sg:postcode":"EH49 6JQ",
    "sg:province":"Falkirk",
    "wof:name":"Whitecross P.O",
    "wof:placetype":"venue"
},
  "geometry": {"coordinates":[-3.6540489197,55.9740715027],"type":"Point"}
}