{
  "type": "Feature",
  "properties": {
    "addr:full":"Aberavon Gas Works Estate, Victoria Road Port Talbot Neath Port Talbot SA12 6DB",
    "addr:housenumber":"estate",
    "addr:postcode":"sa12 6db",
    "addr:street":"Victoria Road",
    "iso:country":"GB",
    "sg:address":"Aberavon Gas Works Estate, Victoria Road",
    "sg:city":"Port Talbot",
    "sg:classifiers":[
        {
            "category":"Wholesale",
            "subcategory":"Chemicals & Plastics",
            "type":"Manufacturing & Wholesale Goods"
        }
    ],
    "sg:phone":"+44 1639 886236",
    "sg:postcode":"SA12 6DB",
    "sg:province":"Neath Port Talbot",
    "sg:tags":[
        "product",
        "allied"
    ],
    "wof:name":"Celtic Chemicals Ltd.",
    "wof:placetype":"venue"
},
  "geometry": {"coordinates":[-3.802369,51.591385],"type":"Point"}
}