{
  "type": "Feature",
  "properties": {
    "addr:full":"Hawthorn Terrace, New Earswick York North Yorkshire YO32 4BY",
    "addr:postcode":"yo32 4by",
    "addr:street":"Hawthorn Terrace",
    "iso:country":"GB",
    "sg:address":"Hawthorn Terrace, New Earswick",
    "sg:city":"York",
    "sg:classifiers":[
        {
            "category":"Education",
            "subcategory":"School",
            "type":"Public Place"
        }
    ],
    "sg:phone":"+44 1904 768228",
    "sg:postcode":"YO32 4BY",
    "sg:province":"North Yorkshire",
    "sg:tags":[
        "local",
        "authority"
    ],
    "wof:name":"New Earswick Undenominational Primary School",
    "wof:placetype":"venue"
},
  "geometry": {"coordinates":[-1.0724090338,53.9915885925],"type":"Point"}
}