{
  "type": "Feature",
  "properties": {
    "addr:full":"681 Southchurch Road Southend-on-sea Essex SS1 2PW",
    "addr:housenumber":"681",
    "addr:postcode":"ss1 2pw",
    "addr:street":"Southchurch Road",
    "iso:country":"GB",
    "sg:address":"681 Southchurch Road",
    "sg:city":"Southend-on-sea",
    "sg:classifiers":[
        {
            "category":"Food & Beverages",
            "subcategory":"Bakery",
            "type":"Retail Goods"
        }
    ],
    "sg:phone":"+44 1702 467621",
    "sg:postcode":"SS1 2PW",
    "sg:province":"Essex",
    "sg:tags":[
        "baker"
    ],
    "wof:name":"Baldwins Bakery",
    "wof:placetype":"venue"
},
  "geometry": {"coordinates":[0.7329419851,51.5406265259],"type":"Point"}
}