{
  "type": "Feature",
  "properties": {
    "iso:country":"GB",
    "sg:address":"4 Mill Street, Crosland Moor",
    "sg:city":"Huddersfield",
    "sg:classifiers":[
        {
            "category":"Shopping",
            "subcategory":"Department Store",
            "type":"Retail Goods"
        }
    ],
    "sg:postcode":"HD4 5AT",
    "sg:province":"West Yorkshire",
    "wof:name":"Lahore Foods Store",
    "wof:placetype":"venue"
},
  "geometry": {"coordinates":[-1.803344965,53.6390762329],"type":"Point"}
}