{
  "type": "Feature",
  "properties": {
    "addr:full":"15 Ninth Av Hayes Greater London UB3 2HH",
    "addr:housenumber":"15",
    "addr:postcode":"ub3 2hh",
    "addr:street":"Ninth Av",
    "iso:country":"GB",
    "sg:address":"15 Ninth Av",
    "sg:city":"Hayes",
    "sg:classifiers":[
        {
            "category":"Building & Trades",
            "subcategory":"Construction",
            "type":"Services"
        }
    ],
    "sg:phone":"+44 20 8573 9537",
    "sg:postcode":"UB3 2HH",
    "sg:province":"Greater London",
    "sg:tags":[
        "builder"
    ],
    "wof:name":"Brown S Builders",
    "wof:placetype":"venue"
},
  "geometry": {"coordinates":[-0.414236,51.513218],"type":"Point"}
}