{
  "type": "Feature",
  "properties": {
    "addr:full":"19 High Street, Whitchurch Aylesbury Buckinghamshire HP22 4JU",
    "addr:housenumber":"19",
    "addr:postcode":"hp22 4ju",
    "addr:street":"High Street",
    "iso:country":"GB",
    "sg:address":"19 High Street, Whitchurch",
    "sg:city":"Aylesbury",
    "sg:classifiers":[
        {
            "category":"Shopping",
            "subcategory":"Baby Store",
            "type":"Retail Goods"
        }
    ],
    "sg:postcode":"HP22 4JU",
    "sg:province":"Buckinghamshire",
    "sg:tags":[
        "babywear",
        "childrens"
    ],
    "wof:name":"Kooshies",
    "wof:placetype":"venue"
},
  "geometry": {"coordinates":[-0.8199219704,51.8565635681],"type":"Point"}
}