{
  "type": "Feature",
  "properties": {
    "addr:full":"9 Churchill Drive Crediton Devon EX17 2DW",
    "addr:housenumber":"9",
    "addr:postcode":"ex17 2dw",
    "addr:street":"Churchill Drive",
    "iso:country":"GB",
    "sg:address":"9 Churchill Drive",
    "sg:city":"Crediton",
    "sg:classifiers":[
        {
            "category":"Arts & Performance",
            "subcategory":"Music",
            "type":"Entertainment"
        }
    ],
    "sg:postcode":"EX17 2DW",
    "sg:province":"Devon",
    "sg:tags":[
        "mobile",
        "disco"
    ],
    "wof:name":"Night Lights",
    "wof:placetype":"venue"
},
  "geometry": {"coordinates":[-3.664496,50.792988],"type":"Point"}
}