{
  "type": "Feature",
  "properties": {
    "iso:country":"GB",
    "sg:address":"Willow Wood, London Road East",
    "sg:city":"Amersham",
    "sg:classifiers":[
        {
            "category":"Building & Trades",
            "subcategory":"Construction",
            "type":"Services"
        }
    ],
    "sg:phone":"+44 1494 725469",
    "sg:postcode":"HP7 9DH",
    "sg:province":"Buckinghamshire",
    "sg:tags":[
        "builder"
    ],
    "wof:name":"Clayfield",
    "wof:placetype":"venue"
},
  "geometry": {"coordinates":[-0.5983489752,51.6624946594],"type":"Point"}
}