{
  "type": "Feature",
  "properties": {
    "addr:full":"84a Boldmere Road Sutton Coldfield West Midlands B73 5TJ",
    "addr:housenumber":"84a",
    "addr:postcode":"b73 5tj",
    "addr:street":"Boldmere Road",
    "iso:country":"GB",
    "sg:address":"84a Boldmere Road",
    "sg:city":"Sutton Coldfield",
    "sg:classifiers":[
        {
            "category":"Shopping",
            "subcategory":"Clothing, Apparel, & Fashions",
            "type":"Retail Goods"
        }
    ],
    "sg:postcode":"B73 5TJ",
    "sg:province":"West Midlands",
    "sg:tags":[
        "shop"
    ],
    "wof:name":"Ritz",
    "wof:placetype":"venue"
},
  "geometry": {"coordinates":[-1.8413699865,52.548412323],"type":"Point"}
}