{
  "type": "Feature",
  "properties": {
    "addr:full":"Brenchley Rd, Matfield Tonbridge Kent TN12 7PL",
    "addr:postcode":"tn12 7pl",
    "addr:street":"Brenchley Rd",
    "iso:country":"GB",
    "sg:address":"Brenchley Rd, Matfield",
    "sg:city":"Tonbridge",
    "sg:classifiers":[
        {
            "category":"Bars & Pubs",
            "type":"Food & Drink"
        }
    ],
    "sg:postcode":"TN12 7PL",
    "sg:province":"Kent",
    "sg:tags":[
        "pubs",
        "inn"
    ],
    "wof:name":"Walnut Tree (The)",
    "wof:placetype":"venue"
},
  "geometry": {"coordinates":[0.400162,51.151306],"type":"Point"}
}