{
  "type": "Feature",
  "properties": {
    "addr:full":"21 Merchant Street Peterhead Aberdeenshire AB42 1DU",
    "addr:housenumber":"21",
    "addr:postcode":"ab42 1du",
    "addr:street":"Merchant Street",
    "iso:country":"GB",
    "sg:address":"21 Merchant Street",
    "sg:city":"Peterhead",
    "sg:classifiers":[
        {
            "category":"Personal",
            "subcategory":"Beauty Salon",
            "type":"Services"
        }
    ],
    "sg:phone":"+44 1779 478629",
    "sg:postcode":"AB42 1DU",
    "sg:province":"Aberdeenshire",
    "sg:tags":[
        "unisex",
        "hairdresser"
    ],
    "wof:name":"Unisex Hair Studio",
    "wof:placetype":"venue"
},
  "geometry": {"coordinates":[-1.7774699926,57.5039482117],"type":"Point"}
}