{
  "type": "Feature",
  "properties": {
    "addr:full":"160 Old Woolwich Road, Greenwich London Greater London SE10 9PR",
    "addr:housenumber":"160",
    "addr:postcode":"se10 9pr",
    "addr:street":"Old Woolwich Road",
    "iso:country":"GB",
    "sg:address":"160 Old Woolwich Road, Greenwich",
    "sg:city":"London",
    "sg:classifiers":[
        {
            "category":"Bus Charters",
            "type":"Transportation"
        }
    ],
    "sg:phone":"+44 20 8858 8177",
    "sg:postcode":"SE10 9PR",
    "sg:province":"Greater London",
    "sg:tags":[
        "hire",
        "coach"
    ],
    "wof:name":"B J Coach Tours",
    "wof:placetype":"venue"
},
  "geometry": {"coordinates":[0.0034139999,51.485042572],"type":"Point"}
}