{
  "type": "Feature",
  "properties": {
    "addr:full":"37 Dowbeck Road Carlisle Cumbria CA2 7BX",
    "addr:housenumber":"37",
    "addr:postcode":"ca2 7bx",
    "addr:street":"Dowbeck Road",
    "iso:country":"GB",
    "sg:address":"37 Dowbeck Road",
    "sg:city":"Carlisle",
    "sg:classifiers":[
        {
            "category":"Building & Trades",
            "subcategory":"Construction",
            "type":"Services"
        }
    ],
    "sg:phone":"+44 1228 548591",
    "sg:postcode":"CA2 7BX",
    "sg:province":"Cumbria",
    "sg:tags":[
        "roofing",
        "contracting"
    ],
    "wof:name":"Jackson Roofing",
    "wof:placetype":"venue"
},
  "geometry": {"coordinates":[-2.9509310722,54.8899421692],"type":"Point"}
}