{
  "type": "Feature",
  "properties": {
    "addr:full":"194-196 High Rd Ilford Essex IG1 1LR",
    "addr:housenumber":"194-196",
    "addr:postcode":"ig1 1lr",
    "addr:street":"High Rd",
    "iso:country":"GB",
    "sg:address":"194-196 High Rd",
    "sg:city":"Ilford",
    "sg:classifiers":[
        {
            "category":"Home & Garden",
            "subcategory":"Furniture",
            "type":"Retail Goods"
        }
    ],
    "sg:phone":"+44 20 8514 2705",
    "sg:postcode":"IG1 1LR",
    "sg:province":"Essex",
    "wof:name":"DURHAM PINE",
    "wof:placetype":"venue"
},
  "geometry": {"coordinates":[0.076194,51.559437],"type":"Point"}
}