{
  "type": "Feature",
  "properties": {
    "addr:full":"50 Camden Passage London Greater London N1 8AE",
    "addr:housenumber":"50",
    "addr:postcode":"n1 8ae",
    "addr:street":"Camden Passage",
    "iso:country":"GB",
    "sg:address":"50 Camden Passage",
    "sg:city":"London",
    "sg:classifiers":[
        {
            "category":"Shopping",
            "subcategory":"Antiques",
            "type":"Retail Goods"
        }
    ],
    "sg:phone":"+44 20 7354 1047",
    "sg:postcode":"N1 8AE",
    "sg:province":"Greater London",
    "wof:name":"Furniture Vault",
    "wof:placetype":"venue"
},
  "geometry": {"coordinates":[-0.103394,51.535572],"type":"Point"}
}