{
  "type": "Feature",
  "properties": {
    "iso:country":"GB",
    "sg:address":"32 Princes Avenue",
    "sg:city":"Orpington",
    "sg:classifiers":[
        {
            "category":"Building & Trades",
            "subcategory":"Construction",
            "type":"Services"
        }
    ],
    "sg:postcode":"BR5 1QS",
    "sg:province":"Kent",
    "sg:tags":[
        "builder"
    ],
    "wof:name":"Beale Builders",
    "wof:placetype":"venue"
},
  "geometry": {"coordinates":[0.0850950032,51.3890953064],"type":"Point"}
}