{
  "type": "Feature",
  "properties": {
    "iso:country":"GB",
    "sg:address":"45 Hollingdene Road",
    "sg:city":"Brighton",
    "sg:classifiers":[
        {
            "category":"Autos & Motor Vehicles",
            "subcategory":"Automobile Sales",
            "type":"Retail Goods"
        }
    ],
    "sg:phone":"+44 1273 693123",
    "sg:postcode":"BN2 4AA",
    "sg:province":"East Sussex",
    "sg:tags":[
        "car",
        "used"
    ],
    "sg:website":"http://www.abbottcarsales.co.uk",
    "wof:name":"Abbott & Son",
    "wof:placetype":"venue"
},
  "geometry": {"coordinates":[-0.125969,50.837936],"type":"Point"}
}