{
  "type": "Feature",
  "properties": {
    "addr:full":"50 Hill Street Manchester Greater Manchester M20 3HA",
    "addr:housenumber":"50",
    "addr:postcode":"m20 3ha",
    "addr:street":"Hill Street",
    "iso:country":"GB",
    "sg:address":"50 Hill Street",
    "sg:city":"Manchester",
    "sg:classifiers":[
        {
            "category":"Professional",
            "subcategory":"Advertising",
            "type":"Services"
        }
    ],
    "sg:phone":"+44 161 445 0501",
    "sg:postcode":"M20 3HA",
    "sg:province":"Greater Manchester",
    "sg:tags":[
        "agency"
    ],
    "wof:name":"Derek J Roe Advertising Agency",
    "wof:placetype":"venue"
},
  "geometry": {"coordinates":[-2.2278690338,53.4346084595],"type":"Point"}
}