{
  "type": "Feature",
  "properties": {
    "iso:country":"GB",
    "sg:address":"14 Lower St",
    "sg:city":"Stansted",
    "sg:classifiers":[
        {
            "category":"Cafe",
            "type":"Food & Drink"
        }
    ],
    "sg:phone":"+44 1279 817755",
    "sg:postcode":"CM24 8LP",
    "sg:province":"Essex",
    "sg:tags":[
        "tea",
        "room"
    ],
    "wof:name":"BANG ON",
    "wof:placetype":"venue"
},
  "geometry": {"coordinates":[0.19951,51.902172],"type":"Point"}
}