{
  "type": "Feature",
  "properties": {
    "iso:country":"GB",
    "sg:address":"Rickmansworth Road",
    "sg:city":"Northwood",
    "sg:classifiers":[
        {
            "category":"Education",
            "subcategory":"School",
            "type":"Public Place"
        },
        {
            "category":"Government",
            "subcategory":"Office",
            "type":"Public Place"
        }
    ],
    "sg:phone":"+44 1923 822529",
    "sg:postcode":"HA6 2RH",
    "sg:province":"Greater London",
    "sg:tags":[
        "local",
        "authority"
    ],
    "wof:name":"Holy Trinity C Of E Junior & Infant School",
    "wof:placetype":"venue"
},
  "geometry": {"coordinates":[-0.426386,51.606323],"type":"Point"}
}