{
  "type": "Feature",
  "properties": {
    "addr:full":"85e Milton Park Abingdon Oxfordshire OX14 4RY",
    "addr:housenumber":"85e",
    "addr:postcode":"ox14 4ry",
    "addr:street":"Milton Park",
    "iso:country":"GB",
    "sg:address":"85e Milton Park",
    "sg:city":"Abingdon",
    "sg:classifiers":[
        {
            "category":"Shopping",
            "subcategory":"Pharmacy",
            "type":"Retail Goods"
        }
    ],
    "sg:phone":"+44 1235 443600",
    "sg:postcode":"OX14 4RY",
    "sg:province":"Oxfordshire",
    "sg:tags":[
        "pharmaceutical"
    ],
    "wof:name":"Sterilox Medical (Europe) Ltd.",
    "wof:placetype":"venue"
},
  "geometry": {"coordinates":[-1.286847949,51.6321716309],"type":"Point"}
}