{
  "type": "Feature",
  "properties": {
    "addr:full":"460 Lickey Road Birmingham West Midlands B45 8UU",
    "addr:housenumber":"460",
    "addr:postcode":"8uu",
    "addr:street":"Lickey Road",
    "iso:country":"GB",
    "sg:address":"460 Lickey Road",
    "sg:city":"Birmingham",
    "sg:classifiers":[
        {
            "category":"Food & Beverages",
            "subcategory":"Meat & Fish",
            "type":"Retail Goods"
        }
    ],
    "sg:postcode":"B45 8UU",
    "sg:province":"West Midlands",
    "sg:tags":[
        "chip"
    ],
    "wof:name":"Lickey Hills Fish Bar",
    "wof:placetype":"venue"
},
  "geometry": {"coordinates":[-2.002462,52.383553],"type":"Point"}
}