{
  "type": "Feature",
  "properties": {
    "iso:country":"GB",
    "sg:address":"Unit 10 Bell Tower Indust Est, Roedean Rd",
    "sg:city":"Brighton",
    "sg:classifiers":[
        {
            "category":"Personal",
            "type":"Services"
        }
    ],
    "sg:phone":"+44 1273 606576",
    "sg:postcode":"BN2 5RU",
    "sg:province":"East Sussex",
    "sg:tags":[
        "delivery"
    ],
    "wof:name":"Whitehawk Freight",
    "wof:placetype":"venue"
},
  "geometry": {"coordinates":[-0.091444,50.812279],"type":"Point"}
}