{
  "type": "Feature",
  "properties": {
    "iso:country":"GB",
    "sg:address":"567 Wilbraham Road, Chorlton-cum-hardy",
    "sg:city":"Manchester",
    "sg:classifiers":[
        {
            "category":"Shopping",
            "subcategory":"Stationery & Office Supplies",
            "type":"Retail Goods"
        }
    ],
    "sg:phone":"+44 161 881 4076",
    "sg:postcode":"M21 1AE",
    "sg:province":"Cheshire",
    "wof:name":"Quarmby's (Stationers) Ltd.",
    "wof:placetype":"venue"
},
  "geometry": {"coordinates":[-2.27657,53.44252],"type":"Point"}
}