{
  "type": "Feature",
  "properties": {
    "iso:country":"GB",
    "sg:address":"42 Arden Avenue, Thornebank",
    "sg:city":"Glasgow",
    "sg:classifiers":[
        {
            "category":"Retail",
            "subcategory":"Driving School",
            "type":"Services"
        }
    ],
    "sg:postcode":"G46 8PZ",
    "sg:province":"East Renfrewshire",
    "wof:name":"Helen Sirman",
    "wof:placetype":"venue"
},
  "geometry": {"coordinates":[-4.3266839981,55.8007736206],"type":"Point"}
}