{
  "type": "Feature",
  "properties": {
    "addr:full":"19 St. Cross Rd Winchester Hampshire SO23 9JA",
    "addr:housenumber":"19",
    "addr:postcode":"so23 9ja",
    "addr:street":"St. Cross Rd",
    "iso:country":"GB",
    "sg:address":"19 St. Cross Rd",
    "sg:city":"Winchester",
    "sg:classifiers":[
        {
            "category":"Health Services",
            "subcategory":"Nursing And Care Facility",
            "type":"Services"
        }
    ],
    "sg:phone":"+44 1962 852253",
    "sg:postcode":"SO23 9JA",
    "sg:province":"Hampshire",
    "sg:tags":[
        "home"
    ],
    "wof:name":"Friary Nursing Home",
    "wof:placetype":"venue"
},
  "geometry": {"coordinates":[-1.318579,51.059921],"type":"Point"}
}