{
  "type": "Feature",
  "properties": {
    "addr:full":"112 Kingston Road London Greater London SW19 1LX",
    "addr:housenumber":"112",
    "addr:postcode":"sw19 1lx",
    "addr:street":"Kingston Road",
    "iso:country":"GB",
    "sg:address":"112 Kingston Road",
    "sg:city":"London",
    "sg:classifiers":[
        {
            "category":"Fast Food",
            "type":"Food & Drink"
        }
    ],
    "sg:phone":"+44 20 8543 0422",
    "sg:postcode":"SW19 1LX",
    "sg:province":"Greater London",
    "sg:tags":[
        "away",
        "take"
    ],
    "wof:name":"Hopewell",
    "wof:placetype":"venue"
},
  "geometry": {"coordinates":[-0.1982109994,51.4152183533],"type":"Point"}
}