{
  "type": "Feature",
  "properties": {
    "addr:full":"61 High Street, Prestwood Great Missenden Buckinghamshire HP16 9EJ",
    "addr:housenumber":"61",
    "addr:postcode":"hp16 9ej",
    "addr:street":"High Street Prestwood",
    "iso:country":"GB",
    "sg:address":"61 High Street, Prestwood",
    "sg:city":"Great Missenden",
    "sg:classifiers":[
        {
            "category":"Personal",
            "subcategory":"Beauty Salon",
            "type":"Services"
        }
    ],
    "sg:phone":"+44 1494 866797",
    "sg:postcode":"HP16 9EJ",
    "sg:province":"Buckinghamshire",
    "sg:tags":[
        "unisex",
        "hairdresser"
    ],
    "wof:name":"Waves Unisex Hair Design",
    "wof:placetype":"venue"
},
  "geometry": {"coordinates":[-0.735130012,51.6995697021],"type":"Point"}
}