{
  "type": "Feature",
  "properties": {
    "addr:full":"12-14 Back Wynd Aberdeen Aberdeen City AB1 1JN",
    "addr:housenumber":"12-14",
    "addr:postcode":"ab1 1jn",
    "addr:street":"Back Wynd",
    "iso:country":"GB",
    "sg:address":"12-14 Back Wynd",
    "sg:city":"Aberdeen",
    "sg:classifiers":[
        {
            "category":"Personal",
            "subcategory":"Beauty Salon",
            "type":"Services"
        }
    ],
    "sg:phone":"+44 1224 637283",
    "sg:postcode":"AB1 1JN",
    "sg:province":"Aberdeen City",
    "sg:tags":[
        "unisex",
        "hairdresser"
    ],
    "wof:name":"Cut of Excellence",
    "wof:placetype":"venue"
},
  "geometry": {"coordinates":[-2.100315094,57.1471748352],"type":"Point"}
}