{
  "type": "Feature",
  "properties": {
    "iso:country":"GB",
    "sg:address":"188 Bath Road",
    "sg:city":"Slough",
    "sg:classifiers":[
        {
            "category":"Building & Trades",
            "subcategory":"Landscaping Services",
            "type":"Services"
        },
        {
            "category":"Wholesale",
            "subcategory":"Plants",
            "type":"Manufacturing & Wholesale Goods"
        }
    ],
    "sg:phone":"+44 1753 695555",
    "sg:postcode":"SL1 3GA",
    "sg:province":"Berkshire",
    "sg:tags":[
        "horticultural",
        "consultant"
    ],
    "wof:name":"Unatrac Ltd.",
    "wof:placetype":"venue"
},
  "geometry": {"coordinates":[-0.615768,51.513294],"type":"Point"}
}