{
  "type": "Feature",
  "properties": {
    "addr:full":"103 Lynn Rd Downham Market Cambridgeshire PE38 9QE",
    "addr:housenumber":"103",
    "addr:postcode":"pe38 9qe",
    "addr:street":"Lynn Rd",
    "iso:country":"GB",
    "sg:address":"103 Lynn Rd",
    "sg:city":"Downham Market",
    "sg:classifiers":[
        {
            "category":"Social Services",
            "subcategory":"Job Training",
            "type":"Services"
        }
    ],
    "sg:phone":"+44 1366 382280",
    "sg:postcode":"PE38 9QE",
    "sg:province":"Cambridgeshire",
    "sg:tags":[
        "translator",
        "interpreter"
    ],
    "wof:name":"Jonathan Toye",
    "wof:placetype":"venue"
},
  "geometry": {"coordinates":[0.384851,52.608372],"type":"Point"}
}