{
  "type": "Feature",
  "properties": {
    "addr:full":"5 Gloucester Road, Rishton Blackburn Lancashire BB1 4BN",
    "addr:housenumber":"5",
    "addr:postcode":"bb1 4bn",
    "addr:street":"Gloucester Road",
    "iso:country":"GB",
    "sg:address":"5 Gloucester Road, Rishton",
    "sg:city":"Blackburn",
    "sg:classifiers":[
        {
            "category":"Professional",
            "subcategory":"Management & Consulting",
            "type":"Services"
        },
        {
            "category":"Arts & Performance",
            "subcategory":"Music",
            "type":"Entertainment"
        }
    ],
    "sg:postcode":"BB1 4BN",
    "sg:province":"Lancashire",
    "sg:tags":[
        "mobile",
        "consultant",
        "safety",
        "disco"
    ],
    "wof:name":"A C Roadshow",
    "wof:placetype":"venue"
},
  "geometry": {"coordinates":[-2.4262850285,53.7654647827],"type":"Point"}
}