{
  "type": "Feature",
  "properties": {
    "iso:country":"GB",
    "sg:address":"97 Nelson Road, Whitton",
    "sg:city":"Twickenham",
    "sg:classifiers":[
        {
            "category":"Building & Trades",
            "subcategory":"Construction",
            "type":"Services"
        }
    ],
    "sg:postcode":"TW2 7AZ",
    "sg:province":"Greater London",
    "sg:tags":[
        "decorator",
        "painter"
    ],
    "wof:name":"Stuart's Decorators",
    "wof:placetype":"venue"
},
  "geometry": {"coordinates":[-0.356791,51.4534],"type":"Point"}
}