{
  "type": "Feature",
  "properties": {
    "iso:country":"GB",
    "sg:address":"36 Sandhurst Clo",
    "sg:city":"Redditch",
    "sg:classifiers":[
        {
            "category":"Shopping",
            "subcategory":"Computers & Home Electronics",
            "type":"Retail Goods"
        }
    ],
    "sg:phone":"+44 1527 66089",
    "sg:postcode":"B98 9JY",
    "sg:province":"Warwickshire",
    "sg:tags":[
        "aerial",
        "television",
        "radio"
    ],
    "wof:name":"Aerial Installations",
    "wof:placetype":"venue"
},
  "geometry": {"coordinates":[-1.906334,52.318089],"type":"Point"}
}