{
  "type": "Feature",
  "properties": {
    "addr:full":"11 East Howe Lane Bournemouth Dorset BH10 5HX",
    "addr:housenumber":"11",
    "addr:postcode":"bh10 5hx",
    "addr:street":"East Howe Lane",
    "iso:country":"GB",
    "sg:address":"11 East Howe Lane",
    "sg:city":"Bournemouth",
    "sg:classifiers":[
        {
            "category":"Fast Food",
            "type":"Food & Drink"
        }
    ],
    "sg:phone":"+44 1202 572527",
    "sg:postcode":"BH10 5HX",
    "sg:province":"Dorset",
    "sg:tags":[
        "away",
        "meal",
        "outlet",
        "take"
    ],
    "wof:name":"Golden Sand",
    "wof:placetype":"venue"
},
  "geometry": {"coordinates":[-1.8995939493,50.7586975098],"type":"Point"}
}