{
  "type": "Feature",
  "properties": {
    "iso:country":"GB",
    "sg:address":"The Gables, Hodnet Court, Hodnet Market Drayton",
    "sg:city":"Market Drayton",
    "sg:classifiers":[
        {
            "category":"Professional",
            "type":"Services"
        }
    ],
    "sg:phone":"+44 1823 490888",
    "sg:postcode":"TF9 3NH",
    "sg:province":"Shropshire",
    "sg:tags":[
        "entertainer"
    ],
    "wof:name":"Dermot Reeve O.B.E",
    "wof:placetype":"venue"
},
  "geometry": {"coordinates":[-2.486172,52.904091],"type":"Point"}
}