{
  "type": "Feature",
  "properties": {
    "addr:full":"55 Norfolk Street Boston Lincolnshire PE21 6PE",
    "addr:housenumber":"55",
    "addr:postcode":"pe21 6pe",
    "addr:street":"Norfolk Street",
    "iso:country":"GB",
    "sg:address":"55 Norfolk Street",
    "sg:city":"Boston",
    "sg:classifiers":[
        {
            "category":"Government",
            "subcategory":"Court House",
            "type":"Public Place"
        }
    ],
    "sg:phone":"+44 1205 366080",
    "sg:postcode":"PE21 6PE",
    "sg:province":"Lincolnshire",
    "wof:name":"The Boston County Court",
    "wof:placetype":"venue"
},
  "geometry": {"coordinates":[-0.024447,52.983189],"type":"Point"}
}