{
  "type": "Feature",
  "properties": {
    "iso:country":"GB",
    "sg:address":"Browning Rd",
    "sg:city":"Rotherham",
    "sg:classifiers":[
        {
            "category":"Education",
            "subcategory":"Library",
            "type":"Public Place"
        }
    ],
    "sg:phone":"+44 1709 382952",
    "sg:postcode":"S65 2LG",
    "sg:province":"South Yorkshire",
    "sg:tags":[
        "book"
    ],
    "wof:name":"Herringthorpe Branch Library",
    "wof:placetype":"venue"
},
  "geometry": {"coordinates":[-1.330104,53.429741],"type":"Point"}
}