{
  "type": "Feature",
  "properties": {
    "addr:full":"34 Hoades Wood Road, Sturry Canterbury Kent CT2 0LZ",
    "addr:housenumber":"34",
    "addr:postcode":"ct2 0lz",
    "addr:street":"Hoades Wood Road",
    "iso:country":"GB",
    "sg:address":"34 Hoades Wood Road, Sturry",
    "sg:city":"Canterbury",
    "sg:classifiers":[
        {
            "category":"Professional",
            "subcategory":"Engineering",
            "type":"Services"
        }
    ],
    "sg:phone":"+44 1227 711288",
    "sg:postcode":"CT2 0LZ",
    "sg:province":"Kent",
    "sg:tags":[
        "contractor",
        "electrical",
        "engineer"
    ],
    "wof:name":"C M W Contractors",
    "wof:placetype":"venue"
},
  "geometry": {"coordinates":[1.132562995,51.3064651489],"type":"Point"}
}