{
  "type": "Feature",
  "properties": {
    "addr:full":"Timbers, East Taphouse Liskeard Cornwall PL14 4NJ",
    "addr:postcode":"pl14 4nj",
    "iso:country":"GB",
    "sg:address":"Timbers, East Taphouse",
    "sg:city":"Liskeard",
    "sg:classifiers":[
        {
            "category":"Retail",
            "subcategory":"Funeral Services",
            "type":"Services"
        }
    ],
    "sg:phone":"+44 1579 320235",
    "sg:postcode":"PL14 4NJ",
    "sg:province":"Cornwall",
    "wof:name":"G W K Pearse Funeral Directors",
    "wof:placetype":"venue"
},
  "geometry": {"coordinates":[-4.465834,50.453796],"type":"Point"}
}