{
  "type": "Feature",
  "properties": {
    "iso:country":"GB",
    "sg:address":"46 Hamilton Square",
    "sg:city":"Birkenhead",
    "sg:classifiers":[
        {
            "category":"Organizations",
            "subcategory":"Non-profit Organization",
            "type":"Services"
        }
    ],
    "sg:phone":"+44 151 647 0647",
    "sg:postcode":"CH41 5AR",
    "sg:province":"Merseyside",
    "sg:tags":[
        "organisation",
        "voluntary",
        "charity"
    ],
    "wof:name":"Merseyside Autistic Childrens Society",
    "wof:placetype":"venue"
},
  "geometry": {"coordinates":[-3.0162079334,53.3928413391],"type":"Point"}
}