{
  "type": "Feature",
  "properties": {
    "iso:country":"GB",
    "sg:address":"Badminton Road, Chipping Sodbury",
    "sg:city":"Bristol",
    "sg:classifiers":[
        {
            "category":"Autos & Motor Vehicles",
            "subcategory":"Auto Supplies",
            "type":"Retail Goods"
        }
    ],
    "sg:phone":"+44 1454 321556",
    "sg:postcode":"BS37 6LL",
    "sg:province":"Gloucestershire",
    "sg:tags":[
        "tyre"
    ],
    "wof:name":"Manor Motoring Centre",
    "wof:placetype":"venue"
},
  "geometry": {"coordinates":[-2.3861138821,51.5355415344],"type":"Point"}
}