{
  "type": "Feature",
  "properties": {
    "addr:full":"Croft Stairs City Road Newcastle-upon-tyne Tyne and Wear NE1 2HG",
    "addr:postcode":"ne1 2hg",
    "addr:street":"Croft;City Road",
    "iso:country":"GB",
    "sg:address":"Croft Stairs City Road",
    "sg:city":"Newcastle-upon-tyne",
    "sg:classifiers":[
        {
            "category":"Building & Trades",
            "subcategory":"Construction",
            "type":"Services"
        }
    ],
    "sg:phone":"+44 191 233 1626",
    "sg:postcode":"NE1 2HG",
    "sg:province":"Tyne and Wear",
    "sg:tags":[
        "consultant",
        "lighting",
        "design"
    ],
    "wof:name":"Hughes Audio Engineering Ltd.",
    "wof:placetype":"venue"
},
  "geometry": {"coordinates":[-1.6062890291,54.9712409973],"type":"Point"}
}