{
  "type": "Feature",
  "properties": {
    "addr:full":"8 Wood Gdns Alderley Edge Cheshire SK9 7PL",
    "addr:housenumber":"8",
    "addr:postcode":"sk9 7pl",
    "addr:street":"Wood Gdns",
    "iso:country":"GB",
    "sg:address":"8 Wood Gdns",
    "sg:city":"Alderley Edge",
    "sg:classifiers":[
        {
            "category":"Shopping",
            "subcategory":"News",
            "type":"Retail Goods"
        }
    ],
    "sg:postcode":"SK9 7PL",
    "sg:province":"Cheshire",
    "sg:tags":[
        "newsagent"
    ],
    "wof:name":"Hall,James,",
    "wof:placetype":"venue"
},
  "geometry": {"coordinates":[-2.2316770554,53.3077545166],"type":"Point"}
}