{
  "type": "Feature",
  "properties": {
    "addr:full":"65-67 King Street Leicester Leicestershire LE1 6RP",
    "addr:housenumber":"65-67",
    "addr:postcode":"le1 6rp",
    "addr:street":"King Street",
    "iso:country":"GB",
    "sg:address":"65-67 King Street",
    "sg:city":"Leicester",
    "sg:classifiers":[
        {
            "category":"Professional",
            "subcategory":"Lawyer & Legal Services",
            "type":"Services"
        }
    ],
    "sg:phone":"+44 116 254 7710",
    "sg:postcode":"LE1 6RP",
    "sg:province":"Leicestershire",
    "sg:tags":[
        "barrister"
    ],
    "wof:name":"King Street Barristers Chambers",
    "wof:placetype":"venue"
},
  "geometry": {"coordinates":[-1.131600976,52.6294975281],"type":"Point"}
}