{
  "type": "Feature",
  "properties": {
    "iso:country":"GB",
    "sg:address":"Highgate Studios",
    "sg:city":"London",
    "sg:classifiers":[
        {
            "category":"Organizations",
            "subcategory":"Non-profit Organization",
            "type":"Services"
        }
    ],
    "sg:phone":"+44 20 7284 6040",
    "sg:postcode":"NW5 1TL",
    "sg:province":"Greater London",
    "sg:tags":[
        "organisation",
        "voluntary",
        "charity"
    ],
    "wof:name":"Brook Advisory Centres",
    "wof:placetype":"venue"
},
  "geometry": {"coordinates":[-0.147484,51.557625],"type":"Point"}
}