{
  "type": "Feature",
  "properties": {
    "addr:full":"Bell House Tamworth Staffordshire B79 7AL",
    "addr:postcode":"b79 7al",
    "addr:street":"Staffordshire",
    "iso:country":"GB",
    "sg:address":"Bell House",
    "sg:city":"Tamworth",
    "sg:classifiers":[
        {
            "category":"Home & Garden",
            "subcategory":"Furniture",
            "type":"Retail Goods"
        }
    ],
    "sg:phone":"+44 1827 50482",
    "sg:postcode":"B79 7AL",
    "sg:province":"Staffordshire",
    "wof:name":"Bodilsen (U K) Ltd.",
    "wof:placetype":"venue"
},
  "geometry": {"coordinates":[-1.687684,52.634094],"type":"Point"}
}