{
  "type": "Feature",
  "properties": {
    "iso:country":"GB",
    "sg:address":"Royal Edward Dock, Avonmouth",
    "sg:city":"Bristol",
    "sg:classifiers":[
        {
            "category":"Manufacturing",
            "subcategory":"Building Materials",
            "type":"Manufacturing & Wholesale Goods"
        }
    ],
    "sg:phone":"+44 117 982 8599",
    "sg:postcode":"BS11 9BT",
    "sg:province":"City of Bristol",
    "sg:tags":[
        "distributor",
        "mnfrs",
        "cement"
    ],
    "wof:name":"Castle Cement Ltd.",
    "wof:placetype":"venue"
},
  "geometry": {"coordinates":[-2.694124,51.498917],"type":"Point"}
}