{
  "type": "Feature",
  "properties": {
    "iso:country":"GB",
    "sg:address":"1 Bosinney Ct, 124-126 Stockbridge Rd",
    "sg:city":"Winchester",
    "sg:classifiers":[
        {
            "category":"Professional",
            "subcategory":"Advertising",
            "type":"Services"
        }
    ],
    "sg:postcode":"SO22 6RN",
    "sg:province":"Hampshire",
    "sg:tags":[
        "telemarketing"
    ],
    "wof:name":"Holdsworth,G,",
    "wof:placetype":"venue"
},
  "geometry": {"coordinates":[-1.32414,51.067268],"type":"Point"}
}