{
  "type": "Feature",
  "properties": {
    "iso:country":"GB",
    "sg:address":"Po Box 3, Upton",
    "sg:city":"Wirral",
    "sg:classifiers":[
        {
            "category":"Professional",
            "subcategory":"Lawyer & Legal Services",
            "type":"Services"
        }
    ],
    "sg:phone":"+44 151 653 0773",
    "sg:postcode":"CH49 6NY",
    "sg:province":"Merseyside",
    "sg:tags":[
        "advice",
        "counselling"
    ],
    "wof:name":"True Freedom Trust",
    "wof:placetype":"venue"
},
  "geometry": {"coordinates":[-3.113029,53.381016],"type":"Point"}
}