{
  "type": "Feature",
  "properties": {
    "iso:country":"GB",
    "sg:address":"Unit 2 130 Wicker",
    "sg:city":"Sheffield",
    "sg:classifiers":[
        {
            "category":"Personal",
            "subcategory":"Tattoo Parlor",
            "type":"Services"
        }
    ],
    "sg:phone":"+44 114 249 3624",
    "sg:postcode":"S3 8JD",
    "sg:province":"South Yorkshire",
    "sg:tags":[
        "tattooing",
        "piercing"
    ],
    "wof:name":"Jesters Court",
    "wof:placetype":"venue"
},
  "geometry": {"coordinates":[-1.461493,53.387341],"type":"Point"}
}