{
  "type": "Feature",
  "properties": {
    "addr:full":"Suite 6 Carlton Chambers, 5 Station Road Shortlands Bromley Kent BR2 0EY",
    "addr:housenumber":"suite 6;5",
    "addr:postcode":"br2 0ey",
    "addr:street":"Carlton Chambers;Station Road",
    "iso:country":"GB",
    "sg:address":"Suite 6 Carlton Chambers, 5 Station Road Shortlands",
    "sg:city":"Bromley",
    "sg:classifiers":[
        {
            "category":"Professional",
            "subcategory":"Detective & Security Services",
            "type":"Services"
        }
    ],
    "sg:postcode":"BR2 0EY",
    "sg:province":"Kent",
    "sg:tags":[
        "agency"
    ],
    "wof:name":"Mid Ken (Uk) Ltd",
    "wof:placetype":"venue"
},
  "geometry": {"coordinates":[-0.000114,51.40398],"type":"Point"}
}