{
  "type": "Feature",
  "properties": {
    "addr:full":"Barbeth Farm, Cumbernauld Glasgow East Dunbartonshire G68 9BA",
    "addr:postcode":"g68 9ba",
    "iso:country":"GB",
    "sg:address":"Barbeth Farm, Cumbernauld",
    "sg:city":"Glasgow",
    "sg:classifiers":[
        {
            "category":"Farming",
            "subcategory":"Livestock Farm",
            "type":"Manufacturing & Wholesale Goods"
        }
    ],
    "sg:postcode":"G68 9BA",
    "sg:province":"East Dunbartonshire",
    "sg:tags":[
        "others"
    ],
    "wof:name":"Gavin W Paterson",
    "wof:placetype":"venue"
},
  "geometry": {"coordinates":[-4.0295357704,55.9377861023],"type":"Point"}
}