{
  "type": "Feature",
  "properties": {
    "iso:country":"GB",
    "sg:address":"233 Worcester Road",
    "sg:city":"Bromsgrove",
    "sg:classifiers":[
        {
            "category":"Manufacturing",
            "subcategory":"Building Materials",
            "type":"Manufacturing & Wholesale Goods"
        }
    ],
    "sg:phone":"+44 1527 833198",
    "sg:postcode":"B61 7JA",
    "sg:province":"Worcestershire",
    "sg:tags":[
        "concrete",
        "product"
    ],
    "wof:name":"Bromsgrove Guild Ltd.",
    "wof:placetype":"venue"
},
  "geometry": {"coordinates":[-2.080841,52.316132],"type":"Point"}
}