{
  "type": "Feature",
  "properties": {
    "addr:full":"18 Tennant St Edinburgh City of Edinburgh EH6 5ND",
    "addr:housenumber":"18",
    "addr:postcode":"eh6 5nd",
    "addr:street":"Tennant St Edinburgh",
    "iso:country":"GB",
    "sg:address":"18 Tennant St",
    "sg:city":"Edinburgh",
    "sg:classifiers":[
        {
            "category":"Home & Garden",
            "subcategory":"Household Appliances",
            "type":"Retail Goods"
        }
    ],
    "sg:phone":"+44 131 554 6563",
    "sg:postcode":"EH6 5ND",
    "sg:province":"City of Edinburgh",
    "sg:tags":[
        "electrical"
    ],
    "wof:name":"M D A",
    "wof:placetype":"venue"
},
  "geometry": {"coordinates":[-3.17771101,55.9706344604],"type":"Point"}
}