{
  "type": "Feature",
  "properties": {
    "iso:country":"GB",
    "sg:address":"53 Havelock St",
    "sg:city":"Kettering",
    "sg:classifiers":[
        {
            "category":"Home & Garden",
            "subcategory":"Home Furnishings",
            "type":"Retail Goods"
        }
    ],
    "sg:phone":"+44 1536 510522",
    "sg:postcode":"NN16 9PZ",
    "sg:province":"Northamptonshire",
    "sg:tags":[
        "mantelpiece",
        "fireplace"
    ],
    "wof:name":"Classic Homes",
    "wof:placetype":"venue"
},
  "geometry": {"coordinates":[-0.724905,52.405972],"type":"Point"}
}