{
  "type": "Feature",
  "properties": {
    "iso:country":"GB",
    "sg:address":"8 Belle Vue",
    "sg:city":"Bude",
    "sg:classifiers":[
        {
            "category":"Professional",
            "type":"Services"
        },
        {
            "category":"Real Estate",
            "subcategory":"Real Estate Agent",
            "type":"Services"
        }
    ],
    "sg:phone":"+44 1288 359999",
    "sg:postcode":"EX23 8JL",
    "sg:province":"Cornwall",
    "sg:tags":[
        "auctioneer"
    ],
    "wof:name":"KIVELL & SONS",
    "wof:placetype":"venue"
},
  "geometry": {"coordinates":[-4.5448579788,50.8299827576],"type":"Point"}
}