{
  "type": "Feature",
  "properties": {
    "addr:full":"98a Painswick Road Gloucester Gloucestershire GL4 6PT",
    "addr:housenumber":"98a",
    "addr:postcode":"gl4 6pt",
    "addr:street":"Painswick Road",
    "iso:country":"GB",
    "sg:address":"98a Painswick Road",
    "sg:city":"Gloucester",
    "sg:classifiers":[
        {
            "category":"Communications",
            "type":"Services"
        }
    ],
    "sg:phone":"+44 1452 524559",
    "sg:postcode":"GL4 6PT",
    "sg:province":"Gloucestershire",
    "sg:tags":[
        "tv",
        "video",
        "radio"
    ],
    "wof:name":"Payne's",
    "wof:placetype":"venue"
},
  "geometry": {"coordinates":[-2.226029,51.851048],"type":"Point"}
}