{
  "type": "Feature",
  "properties": {
    "addr:full":"Grn Lane Farm, Neasham Road Darlington Durham DL2 1QE",
    "addr:postcode":"dl2 1qe",
    "addr:street":"Grn Lane;Neasham Road",
    "iso:country":"GB",
    "sg:address":"Grn Lane Farm, Neasham Road",
    "sg:city":"Darlington",
    "sg:classifiers":[
        {
            "category":"Professional",
            "subcategory":"Business Services",
            "type":"Services"
        }
    ],
    "sg:phone":"+44 1325 466710",
    "sg:postcode":"DL2 1QE",
    "sg:province":"Durham",
    "sg:tags":[
        "import",
        "export",
        "agent"
    ],
    "wof:name":"Margaret Smith",
    "wof:placetype":"venue"
},
  "geometry": {"coordinates":[-1.491787,54.488289],"type":"Point"}
}