{
  "type": "Feature",
  "properties": {
    "addr:full":"81 Swansea Road, Pontlliw Swansea Carmarthenshire SA4 9EF",
    "addr:housenumber":"81",
    "addr:postcode":"sa4 9ef",
    "addr:street":"Swansea Road",
    "iso:country":"GB",
    "sg:address":"81 Swansea Road, Pontlliw",
    "sg:city":"Swansea",
    "sg:classifiers":[
        {
            "category":"Autos & Motor Vehicles",
            "subcategory":"Fuel & Gas Station",
            "type":"Retail Goods"
        }
    ],
    "sg:phone":"+44 1792 892020",
    "sg:postcode":"SA4 9EF",
    "sg:province":"Carmarthenshire",
    "sg:tags":[
        "petrol",
        "filling"
    ],
    "wof:name":"Pontlliw Service Station",
    "wof:placetype":"venue"
},
  "geometry": {"coordinates":[-4.0124268532,51.688129425],"type":"Point"}
}