{
  "type": "Feature",
  "properties": {
    "iso:country":"GB",
    "sg:address":"St Mary Street",
    "sg:city":"Chippenham",
    "sg:classifiers":[
        {
            "category":"Social Services",
            "subcategory":"Retirement Home",
            "type":"Services"
        }
    ],
    "sg:postcode":"SN15 3JW",
    "sg:province":"Wiltshire",
    "sg:tags":[
        "residential",
        "care"
    ],
    "wof:name":"The Old Vicarage Residential Home",
    "wof:placetype":"venue"
},
  "geometry": {"coordinates":[-2.1119439602,51.4577827454],"type":"Point"}
}