{
  "type": "Feature",
  "properties": {
    "iso:country":"GB",
    "sg:address":"Unit 15 Rose Heyworth Business Park",
    "sg:city":"Abertillery",
    "sg:classifiers":[
        {
            "category":"Wholesale",
            "subcategory":"Chemicals & Plastics",
            "type":"Manufacturing & Wholesale Goods"
        }
    ],
    "sg:phone":"+44 1495 320327",
    "sg:postcode":"NP3 1SP",
    "sg:province":"Blaenau Gwent",
    "sg:tags":[
        "product",
        "allied"
    ],
    "wof:name":"Micronaid Trading Ltd",
    "wof:placetype":"venue"
},
  "geometry": {"coordinates":[-3.153494,51.744965],"type":"Point"}
}