{
  "type": "Feature",
  "properties": {
    "addr:full":"75 Gloucester Hall London Greater London SW7 4SS",
    "addr:housenumber":"75",
    "addr:postcode":"sw7 4ss",
    "addr:street":"Gloucester Hall",
    "iso:country":"GB",
    "sg:address":"75 Gloucester Hall",
    "sg:city":"London",
    "sg:classifiers":[
        {
            "category":"Shopping",
            "subcategory":"Pharmacy",
            "type":"Retail Goods"
        }
    ],
    "sg:phone":"+44 20 7373 7833",
    "sg:postcode":"SW7 4SS",
    "sg:province":"Greater London",
    "sg:tags":[
        "medicine",
        "therapy"
    ],
    "wof:name":"Colonic Irrigation (Hydrotherapy) Clinic",
    "wof:placetype":"venue"
},
  "geometry": {"coordinates":[-0.182513,51.494881],"type":"Point"}
}