{
  "type": "Feature",
  "properties": {
    "iso:country":"GB",
    "sg:address":"The Cidery Lower Church Farm, Church Street Barton St David",
    "sg:city":"Somerton",
    "sg:classifiers":[
        {
            "category":"Professional",
            "subcategory":"Computer Services",
            "type":"Services"
        }
    ],
    "sg:phone":"+44 1458 850124",
    "sg:postcode":"TA11 6BU",
    "sg:province":"Somerset",
    "sg:tags":[
        "system",
        "software"
    ],
    "wof:name":"Wraith Technology Ltd.",
    "wof:placetype":"venue"
},
  "geometry": {"coordinates":[-2.734899,51.054165],"type":"Point"}
}