{
  "type": "Feature",
  "properties": {
    "iso:country":"GB",
    "sg:address":"Bolt Edge Farm, Dove Holes",
    "sg:city":"Buxton",
    "sg:classifiers":[
        {
            "category":"Farming",
            "subcategory":"Livestock Farm",
            "type":"Manufacturing & Wholesale Goods"
        }
    ],
    "sg:phone":"+44 1298 812369",
    "sg:postcode":"SK17 8EY",
    "sg:province":"Derbyshire",
    "sg:tags":[
        "others"
    ],
    "wof:name":"F A Moorcroft",
    "wof:placetype":"venue"
},
  "geometry": {"coordinates":[-1.8863799572,53.3013763428],"type":"Point"}
}