{
  "type": "Feature",
  "properties": {
    "addr:full":"Putney Park House, Pleasance Road, Roehampton London Greater London SW15 5HJ",
    "addr:postcode":"sw15 5hj",
    "addr:street":"Putney;Pleasance Road",
    "iso:country":"GB",
    "sg:address":"Putney Park House, Pleasance Road, Roehampton",
    "sg:city":"London",
    "sg:classifiers":[
        {
            "category":"Organizations",
            "subcategory":"Membership Organization",
            "type":"Services"
        }
    ],
    "sg:phone":"+44 20 8876 9549",
    "sg:postcode":"SW15 5HJ",
    "sg:province":"Greater London",
    "sg:tags":[
        "club"
    ],
    "wof:name":"Roehampton Estates Tenants' Association Ltd.",
    "wof:placetype":"venue"
},
  "geometry": {"coordinates":[-0.243099,51.455521],"type":"Point"}
}