{
  "type": "Feature",
  "properties": {
    "addr:full":"11 Godfrey Road Newport Newport NP20 4NX",
    "addr:housenumber":"11",
    "addr:postcode":"np20 4nx",
    "addr:street":"Godfrey Road",
    "iso:country":"GB",
    "sg:address":"11 Godfrey Road",
    "sg:city":"Newport",
    "sg:classifiers":[
        {
            "category":"Education",
            "subcategory":"Special Training",
            "type":"Public Place"
        }
    ],
    "sg:phone":"+44 1633 259547",
    "sg:postcode":"NP20 4NX",
    "sg:province":"Newport",
    "sg:tags":[
        "product",
        "centre"
    ],
    "wof:name":"S W A T Ltd.",
    "wof:placetype":"venue"
},
  "geometry": {"coordinates":[-3.003454,51.587975],"type":"Point"}
}