{
  "type": "Feature",
  "properties": {
    "addr:full":"45 Mount Pleasant Road Tunbridge Wells Kent TN1 1PN",
    "addr:housenumber":"45",
    "addr:postcode":"tn1 1pn",
    "addr:street":"Mount Pleasant Road",
    "iso:country":"GB",
    "sg:address":"45 Mount Pleasant Road",
    "sg:city":"Tunbridge Wells",
    "sg:classifiers":[
        {
            "category":"Food & Beverages",
            "subcategory":"Bakery",
            "type":"Retail Goods"
        }
    ],
    "sg:phone":"+44 1892 515685",
    "sg:postcode":"TN1 1PN",
    "sg:province":"Kent",
    "sg:tags":[
        "pizza"
    ],
    "wof:name":"Pizza Hut",
    "wof:placetype":"venue"
},
  "geometry": {"coordinates":[0.2631599903,51.1317634583],"type":"Point"}
}