{
  "type": "Feature",
  "properties": {
    "addr:full":"35 Market Place Boston Lincolnshire PE21 6NH",
    "addr:housenumber":"35",
    "addr:postcode":"pe21 6nh",
    "addr:street":"Market Place",
    "iso:country":"GB",
    "sg:address":"35 Market Place",
    "sg:city":"Boston",
    "sg:classifiers":[
        {
            "category":"Insurance",
            "subcategory":"Insurance Agent",
            "type":"Services"
        },
        {
            "category":"Banks & Credit Unions",
            "subcategory":"Financial Services",
            "type":"Services"
        }
    ],
    "sg:phone":"+44 1205 360000",
    "sg:postcode":"PE21 6NH",
    "sg:province":"Lincolnshire",
    "sg:tags":[
        "adviser",
        "broker"
    ],
    "wof:name":"BARCLAYS INSURANCE BROKERS",
    "wof:placetype":"venue"
},
  "geometry": {"coordinates":[-0.0233709998,52.9771308899],"type":"Point"}
}