{
  "type": "Feature",
  "properties": {
    "addr:full":"Forest Ho, 21-27 York Rd Ilford Essex IG1 3AD",
    "addr:housenumber":"21-27",
    "addr:postcode":"ig1 3ad",
    "addr:street":"York Rd",
    "iso:country":"GB",
    "sg:address":"Forest Ho, 21-27 York Rd",
    "sg:city":"Ilford",
    "sg:classifiers":[
        {
            "category":"Banks & Credit Unions",
            "subcategory":"Bank",
            "type":"Services"
        }
    ],
    "sg:phone":"+44 20 8514 8129",
    "sg:postcode":"IG1 3AD",
    "sg:province":"Essex",
    "sg:tags":[
        "broker",
        "mortgage"
    ],
    "wof:name":"Duncans Property & Financial Services Lt",
    "wof:placetype":"venue"
},
  "geometry": {"coordinates":[0.0671150014,51.5637512207],"type":"Point"}
}