{
  "type": "Feature",
  "properties": {
    "addr:full":"250 Whitehill Rd, Kidsgrove Stoke On Trent Cheshire ST7 4DU",
    "addr:housenumber":"250",
    "addr:postcode":"st7 4du",
    "addr:street":"Whitehill Rd;Stoke On Trent",
    "iso:country":"GB",
    "sg:address":"250 Whitehill Rd, Kidsgrove",
    "sg:city":"Stoke On Trent",
    "sg:classifiers":[
        {
            "category":"Communications",
            "subcategory":"Film & Video Production",
            "type":"Services"
        }
    ],
    "sg:phone":"+44 1782 772585",
    "sg:postcode":"ST7 4DU",
    "sg:province":"Cheshire",
    "sg:tags":[
        "tv",
        "radio"
    ],
    "wof:name":"Area Communication Services",
    "wof:placetype":"venue"
},
  "geometry": {"coordinates":[-2.2207911015,53.0916824341],"type":"Point"}
}