{
  "type": "Feature",
  "properties": {
    "addr:full":"Lower Swell Cheltenham Gloucestershire GL54 1LF",
    "addr:postcode":"gl54 1lf",
    "addr:street":"Lower Swell",
    "iso:country":"GB",
    "sg:address":"Lower Swell",
    "sg:city":"Cheltenham",
    "sg:classifiers":[
        {
            "category":"Travel",
            "subcategory":"Hotels & Motels",
            "type":"Entertainment"
        }
    ],
    "sg:phone":"+44 1451 830232",
    "sg:postcode":"GL54 1LF",
    "sg:province":"Gloucestershire",
    "sg:tags":[
        "house",
        "guest"
    ],
    "wof:name":"Mellowstone Hotels Ltd.",
    "wof:placetype":"venue"
},
  "geometry": {"coordinates":[-1.719122,51.928192],"type":"Point"}
}