{
  "type": "Feature",
  "properties": {
    "addr:full":"Causeway Grn Centre, Sandwell Oldbury West Midlands B68 8LE",
    "addr:postcode":"b68 8le",
    "addr:street":"Causeway Grn Centre",
    "iso:country":"GB",
    "sg:address":"Causeway Grn Centre, Sandwell",
    "sg:city":"Oldbury",
    "sg:classifiers":[
        {
            "category":"Social Services",
            "type":"Services"
        }
    ],
    "sg:postcode":"B68 8LE",
    "sg:province":"West Midlands",
    "wof:name":"Sandwell Social Services",
    "wof:placetype":"venue"
},
  "geometry": {"coordinates":[-2.0129489899,52.486114502],"type":"Point"}
}