{
  "type": "Feature",
  "properties": {
    "addr:full":"34 Maiden Lane Liverpool Merseyside L13 9AW",
    "addr:housenumber":"34",
    "addr:postcode":"l13 9aw",
    "addr:street":"Maiden Lane",
    "iso:country":"GB",
    "sg:address":"34 Maiden Lane",
    "sg:city":"Liverpool",
    "sg:classifiers":[
        {
            "category":"Organizations",
            "subcategory":"Non-profit Organization",
            "type":"Services"
        }
    ],
    "sg:phone":"+44 151 226 4600",
    "sg:postcode":"L13 9AW",
    "sg:province":"Merseyside",
    "sg:tags":[
        "organisation",
        "voluntary",
        "charity"
    ],
    "wof:name":"Liverpool Mencap Homes Foundation",
    "wof:placetype":"venue"
},
  "geometry": {"coordinates":[-2.9356999397,53.4329376221],"type":"Point"}
}