{
  "type": "Feature",
  "properties": {
    "iso:country":"GB",
    "sg:address":"Highfield Road South",
    "sg:city":"Chorley",
    "sg:classifiers":[
        {
            "category":"Education",
            "subcategory":"School",
            "type":"Public Place"
        },
        {
            "category":"Government",
            "subcategory":"Office",
            "type":"Public Place"
        }
    ],
    "sg:phone":"+44 1257 262940",
    "sg:postcode":"PR7 1RB",
    "sg:province":"Lancashire",
    "sg:tags":[
        "local",
        "authority"
    ],
    "sg:website":"http://www.st-laurence.lancs.sch.uk",
    "wof:name":"St Laurence C Of E Primary School",
    "wof:placetype":"venue"
},
  "geometry": {"coordinates":[-2.631791,53.660328],"type":"Point"}
}