{
  "type": "Feature",
  "properties": {
    "addr:full":"Concord Ho, 454-458 London Rd Croydon Surrey CR9 2RG",
    "addr:housenumber":"454-458",
    "addr:postcode":"cr9 2rg",
    "addr:street":"London Rd",
    "iso:country":"GB",
    "sg:address":"Concord Ho, 454-458 London Rd",
    "sg:city":"Croydon",
    "sg:classifiers":[
        {
            "category":"Social Services",
            "type":"Services"
        }
    ],
    "sg:phone":"+44 20 8710 5600",
    "sg:postcode":"CR9 2RG",
    "sg:province":"Surrey",
    "sg:tags":[
        "benefit",
        "agency"
    ],
    "wof:name":"Benefits Agency",
    "wof:placetype":"venue"
},
  "geometry": {"coordinates":[-0.099451,51.372349],"type":"Point"}
}