{
  "type": "Feature",
  "properties": {
    "iso:country":"GB",
    "sg:address":"36 Piccadilly",
    "sg:city":"Stoke-on-trent",
    "sg:classifiers":[
        {
            "category":"Shopping",
            "subcategory":"Clothing, Apparel, & Fashions",
            "type":"Retail Goods"
        }
    ],
    "sg:postcode":"ST1 1EG",
    "sg:province":"Staffordshire",
    "sg:tags":[
        "menswear"
    ],
    "wof:name":"Rescue",
    "wof:placetype":"venue"
},
  "geometry": {"coordinates":[-2.1772089005,53.0250244141],"type":"Point"}
}