{
  "type": "Feature",
  "properties": {
    "addr:full":"3-3a Caston Industrial Estate Norwich Norfolk NR7 9AQ",
    "addr:housenumber":"3-3a",
    "addr:postcode":"nr7 9aq",
    "addr:street":"Caston Industrial Estate Norwich Norfolk",
    "iso:country":"GB",
    "sg:address":"3-3a Caston Industrial Estate",
    "sg:city":"Norwich",
    "sg:classifiers":[
        {
            "category":"Retail",
            "subcategory":"Auto Repair",
            "type":"Services"
        }
    ],
    "sg:phone":"+44 1603 431424",
    "sg:postcode":"NR7 9AQ",
    "sg:province":"Norfolk",
    "sg:tags":[
        "body",
        "car"
    ],
    "wof:name":"Thorpe Body Repairs",
    "wof:placetype":"venue"
},
  "geometry": {"coordinates":[1.3477699757,52.6402015686],"type":"Point"}
}