{
  "type": "Feature",
  "properties": {
    "iso:country":"GB",
    "sg:address":"Unit 4 Sandy Hill Lane, Overstone Road, Moulton",
    "sg:city":"Northampton",
    "sg:classifiers":[
        {
            "category":"Retail",
            "subcategory":"Auto Repair",
            "type":"Services"
        }
    ],
    "sg:postcode":"NN3 7JB",
    "sg:province":"Northamptonshire",
    "sg:tags":[
        "modification",
        "garage"
    ],
    "wof:name":"A H Autos",
    "wof:placetype":"venue"
},
  "geometry": {"coordinates":[-0.842276,52.290173],"type":"Point"}
}