{
  "type": "Feature",
  "properties": {
    "addr:full":"82 Cooden Sea Rd Bexhill On Sea East Sussex TN39 4SP",
    "addr:housenumber":"82",
    "addr:postcode":"tn39 4sp",
    "addr:street":"Cooden Sea Rd",
    "iso:country":"GB",
    "sg:address":"82 Cooden Sea Rd",
    "sg:city":"Bexhill On Sea",
    "sg:classifiers":[
        {
            "category":"Health Services",
            "subcategory":"Doctor",
            "type":"Services"
        }
    ],
    "sg:phone":"+44 1424 845477",
    "sg:postcode":"TN39 4SP",
    "sg:province":"East Sussex",
    "sg:tags":[
        "practitioners"
    ],
    "wof:name":"Dewhurst, P D",
    "wof:placetype":"venue"
},
  "geometry": {"coordinates":[0.4335680008,50.842212677],"type":"Point"}
}