{
  "type": "Feature",
  "properties": {
    "addr:full":"341a Seven Sisters Road London Greater London N15 6RD",
    "addr:housenumber":"341a",
    "addr:postcode":"n15 6rd",
    "addr:street":"Seven Sisters Road",
    "iso:country":"GB",
    "sg:address":"341a Seven Sisters Road",
    "sg:city":"London",
    "sg:classifiers":[
        {
            "category":"Organizations",
            "subcategory":"Community Association",
            "type":"Services"
        }
    ],
    "sg:phone":"+44 20 8800 2744",
    "sg:postcode":"N15 6RD",
    "sg:province":"Greater London",
    "sg:tags":[
        "associations",
        "housing",
        "co-operatives",
        "society",
        "trust",
        "societies"
    ],
    "wof:name":"Cara Irish Housing Association",
    "wof:placetype":"venue"
},
  "geometry": {"coordinates":[-0.0856989995,51.5750389099],"type":"Point"}
}