{
  "type": "Feature",
  "properties": {
    "addr:full":"14 Hughenden Yard Marlborough Berkshire SN8 1LT",
    "addr:housenumber":"14",
    "addr:postcode":"sn8 1lt",
    "addr:street":"Hughenden Yard",
    "iso:country":"GB",
    "sg:address":"14 Hughenden Yard",
    "sg:city":"Marlborough",
    "sg:classifiers":[
        {
            "category":"Professional",
            "subcategory":"Computer Services",
            "type":"Services"
        }
    ],
    "sg:phone":"+44 1672 511094",
    "sg:postcode":"SN8 1LT",
    "sg:province":"Berkshire",
    "sg:tags":[
        "system",
        "software"
    ],
    "wof:name":"Net Shift Software Ltd",
    "wof:placetype":"venue"
},
  "geometry": {"coordinates":[-1.73318398,51.4195365906],"type":"Point"}
}