{
  "type": "Feature",
  "properties": {
    "iso:country":"GB",
    "sg:address":"Penhurst Close, Weavering",
    "sg:city":"Maidstone",
    "sg:classifiers":[
        {
            "category":"Real Estate",
            "subcategory":"Architect",
            "type":"Services"
        },
        {
            "category":"Health Services",
            "subcategory":"Dentist",
            "type":"Services"
        }
    ],
    "sg:phone":"+44 1622 737666",
    "sg:postcode":"ME14 5BT",
    "sg:province":"Kent",
    "wof:name":"The Grove Green Orthodontic Centre",
    "wof:placetype":"venue"
},
  "geometry": {"coordinates":[0.55752,51.274261],"type":"Point"}
}