{
  "type": "Feature",
  "properties": {
    "addr:full":"83-84 Buckingham Street Birmingham West Midlands B19 3HU",
    "addr:housenumber":"83-84",
    "addr:postcode":"b19 3hu",
    "addr:street":"Buckingham Street",
    "iso:country":"GB",
    "sg:address":"83-84 Buckingham Street",
    "sg:city":"Birmingham",
    "sg:classifiers":[
        {
            "category":"Shopping",
            "subcategory":"Gifts & Souvenirs",
            "type":"Retail Goods"
        }
    ],
    "sg:phone":"+44 121 233 1077",
    "sg:postcode":"B19 3HU",
    "sg:province":"West Midlands",
    "sg:tags":[
        "ducting"
    ],
    "wof:name":"R J Plastics",
    "wof:placetype":"venue"
},
  "geometry": {"coordinates":[-1.905066967,52.4894142151],"type":"Point"}
}