{
  "type": "Feature",
  "properties": {
    "addr:full":"Tosca High Wycombe Buckinghamshire HP12 4QJ",
    "addr:postcode":"hp12 4qj",
    "iso:country":"GB",
    "sg:address":"Tosca",
    "sg:city":"High Wycombe",
    "sg:classifiers":[
        {
            "category":"Home & Garden",
            "subcategory":"Garden Supply",
            "type":"Retail Goods"
        },
        {
            "category":"Professional",
            "subcategory":"Secretarial Services",
            "type":"Services"
        }
    ],
    "sg:postcode":"HP12 4QJ",
    "sg:province":"Buckinghamshire",
    "sg:tags":[
        "sand",
        "gravel"
    ],
    "wof:name":"Gerry Rance Haulage",
    "wof:placetype":"venue"
},
  "geometry": {"coordinates":[-0.797274,51.631386],"type":"Point"}
}