{
  "type": "Feature",
  "properties": {
    "iso:country":"GB",
    "sg:address":"3 Northwood",
    "sg:city":"Bolton",
    "sg:classifiers":[
        {
            "category":"Manufacturing",
            "subcategory":"Building Materials",
            "type":"Manufacturing & Wholesale Goods"
        }
    ],
    "sg:postcode":"BL2 3LL",
    "sg:province":"Lancashire",
    "sg:tags":[
        "tile",
        "mnfrs"
    ],
    "wof:name":"G & F Houghton",
    "wof:placetype":"venue"
},
  "geometry": {"coordinates":[-2.3954389095,53.6047706604],"type":"Point"}
}