{
  "type": "Feature",
  "properties": {
    "iso:country":"GB",
    "sg:address":"Cross House Farm, Moss Side La",
    "sg:city":"Preston",
    "sg:classifiers":[
        {
            "category":"Farming",
            "subcategory":"Livestock Farm",
            "type":"Manufacturing & Wholesale Goods"
        }
    ],
    "sg:phone":"+44 1995 640590",
    "sg:postcode":"PR3 0US",
    "sg:province":"Lancashire",
    "sg:tags":[
        "others"
    ],
    "wof:name":"W B Armistead",
    "wof:placetype":"venue"
},
  "geometry": {"coordinates":[-2.846708,53.853737],"type":"Point"}
}