{
  "type": "Feature",
  "properties": {
    "addr:full":"Factory Rd Bristol City of Bristol BS17 1QL",
    "addr:postcode":"bs17 1ql",
    "addr:street":"Factory Rd",
    "iso:country":"GB",
    "sg:address":"Factory Rd",
    "sg:city":"Bristol",
    "sg:classifiers":[
        {
            "category":"Place Of Worship",
            "type":"Public Place"
        }
    ],
    "sg:phone":"+44 1454 775576",
    "sg:postcode":"BS17 1QL",
    "sg:province":"City of Bristol",
    "wof:name":"Salem Methodist Church",
    "wof:placetype":"venue"
},
  "geometry": {"coordinates":[-2.4945349693,51.527431488],"type":"Point"}
}