{
  "type": "Feature",
  "properties": {
    "addr:full":"13 The Square Llanerchymedd Isle of Anglesey LL71 8DY",
    "addr:housenumber":"13",
    "addr:postcode":"ll71 8dy",
    "addr:street":"The Square Llanerchymedd",
    "iso:country":"GB",
    "sg:address":"13 The Square",
    "sg:city":"Llanerchymedd",
    "sg:classifiers":[
        {
            "category":"Shopping",
            "subcategory":"News",
            "type":"Retail Goods"
        }
    ],
    "sg:postcode":"LL71 8DY",
    "sg:province":"Isle of Anglesey",
    "sg:tags":[
        "newsagent"
    ],
    "wof:name":"J H Jones",
    "wof:placetype":"venue"
},
  "geometry": {"coordinates":[-4.376363,53.330353],"type":"Point"}
}