{
  "type": "Feature",
  "properties": {
    "iso:country":"GB",
    "sg:address":"Pedmore Road, Lye",
    "sg:city":"Stourbridge",
    "sg:classifiers":[
        {
            "category":"Bars & Pubs",
            "type":"Food & Drink"
        }
    ],
    "sg:phone":"+44 1384 422238",
    "sg:postcode":"DY9 7DZ",
    "sg:province":"West Midlands",
    "sg:tags":[
        "pubs",
        "inn"
    ],
    "wof:name":"The Bulls Head",
    "wof:placetype":"venue"
},
  "geometry": {"coordinates":[-2.119344,52.455143],"type":"Point"}
}