{
  "type": "Feature",
  "properties": {
    "iso:country":"GB",
    "sg:address":"Langthorpe, Boroughbridge",
    "sg:city":"York",
    "sg:classifiers":[
        {
            "category":"Bars & Pubs",
            "type":"Food & Drink"
        }
    ],
    "sg:phone":"+44 1423 323675",
    "sg:postcode":"YO51 9BP",
    "sg:province":"North Yorkshire",
    "sg:tags":[
        "pubs",
        "inn"
    ],
    "wof:name":"Anchor Inn",
    "wof:placetype":"venue"
},
  "geometry": {"coordinates":[-1.395458,54.097652],"type":"Point"}
}