{
  "type": "Feature",
  "properties": {
    "addr:full":"7 North Parade Chessington Surrey KT9 1QL",
    "addr:housenumber":"7",
    "addr:postcode":"kt9 1ql",
    "addr:street":"North Parade",
    "iso:country":"GB",
    "sg:address":"7 North Parade",
    "sg:city":"Chessington",
    "sg:classifiers":[
        {
            "category":"Autos & Motor Vehicles",
            "subcategory":"Motorcycle Sales",
            "type":"Retail Goods"
        }
    ],
    "sg:postcode":"KT9 1QL",
    "sg:province":"Surrey",
    "sg:tags":[
        "chauffeur",
        "driven",
        "car"
    ],
    "wof:name":"Abbotsbury Chauffeurs",
    "wof:placetype":"venue"
},
  "geometry": {"coordinates":[-0.299047,51.364395],"type":"Point"}
}