{
  "type": "Feature",
  "properties": {
    "addr:full":"28 Oxford Street Ripley Derbyshire DE5 3AP",
    "addr:housenumber":"28",
    "addr:postcode":"de5 3ap",
    "addr:street":"Oxford Street",
    "iso:country":"GB",
    "sg:address":"28 Oxford Street",
    "sg:city":"Ripley",
    "sg:classifiers":[
        {
            "category":"Travel",
            "subcategory":"Travel Agent",
            "type":"Entertainment"
        }
    ],
    "sg:phone":"+44 1773 570900",
    "sg:postcode":"DE5 3AP",
    "sg:province":"Derbyshire",
    "wof:name":"United Norwest Co-Operatives Ltd.",
    "wof:placetype":"venue"
},
  "geometry": {"coordinates":[-1.4052300453,53.0499572754],"type":"Point"}
}