{
  "type": "Feature",
  "properties": {
    "iso:country":"GB",
    "sg:address":"4 St Andrews Street",
    "sg:city":"Blackburn",
    "sg:classifiers":[
        {
            "category":"Professional",
            "subcategory":"Business Services",
            "type":"Services"
        }
    ],
    "sg:phone":"+44 1254 580248",
    "sg:postcode":"BB1 8AE",
    "sg:province":"Lancashire",
    "sg:tags":[
        "organisation",
        "trade"
    ],
    "sg:website":"http://www.ltma.co.uk",
    "wof:name":"Lancashire Textile Manufacturers Association",
    "wof:placetype":"venue"
},
  "geometry": {"coordinates":[-2.486892,53.752548],"type":"Point"}
}