{
  "type": "Feature",
  "properties": {
    "iso:country":"GB",
    "sg:address":"Drellingore Farm, Stombers Lane, Drellingore",
    "sg:city":"Folkestone",
    "sg:classifiers":[
        {
            "category":"Home & Garden",
            "subcategory":"Garden Supply",
            "type":"Retail Goods"
        },
        {
            "category":"Farming",
            "subcategory":"Farm",
            "type":"Manufacturing & Wholesale Goods"
        }
    ],
    "sg:postcode":"CT18 7ER",
    "sg:province":"Kent",
    "sg:tags":[
        "mixed",
        "bulb",
        "crop",
        "grower"
    ],
    "wof:name":"D S Osborne",
    "wof:placetype":"venue"
},
  "geometry": {"coordinates":[1.203420043,51.1263694763],"type":"Point"}
}