{
  "type": "Feature",
  "properties": {
    "iso:country":"GB",
    "sg:address":"Moss Lane, Newbold On Stour",
    "sg:city":"Stratford-upon-avon",
    "sg:classifiers":[
        {
            "category":"Education",
            "subcategory":"School",
            "type":"Public Place"
        }
    ],
    "sg:phone":"+44 1789 450349",
    "sg:postcode":"CV37 8TU",
    "sg:province":"Warwickshire",
    "sg:tags":[
        "local",
        "authority"
    ],
    "wof:name":"Newbold & Tredington Junior & Infant School",
    "wof:placetype":"venue"
},
  "geometry": {"coordinates":[-1.6414029598,52.113986969],"type":"Point"}
}