{
  "type": "Feature",
  "properties": {
    "iso:country":"GB",
    "sg:address":"11 Taff Vale Precinct, Taff St",
    "sg:city":"Pontypridd",
    "sg:classifiers":[
        {
            "category":"Communications",
            "type":"Services"
        }
    ],
    "sg:postcode":"CF37 4TG",
    "sg:province":"Caerphilly",
    "sg:tags":[
        "tv",
        "video",
        "radio"
    ],
    "wof:name":"Digital Window Computer Centre",
    "wof:placetype":"venue"
},
  "geometry": {"coordinates":[-3.3405919075,51.6033401489],"type":"Point"}
}