{
  "type": "Feature",
  "properties": {
    "iso:country":"GB",
    "sg:address":"194a Kilburn High Rd",
    "sg:city":"Kilburn",
    "sg:classifiers":[
        {
            "category":"Professional",
            "subcategory":"Lawyer & Legal Services",
            "type":"Services"
        }
    ],
    "sg:phone":"+44 20 7624 2077",
    "sg:postcode":"NW6 4JD",
    "sg:province":"Greater London",
    "sg:tags":[
        "advice",
        "counselling"
    ],
    "wof:name":"Drugs And Alcohol Service",
    "wof:placetype":"venue"
},
  "geometry": {"coordinates":[-0.197642,51.541431],"type":"Point"}
}