{
  "type": "Feature",
  "properties": {
    "iso:country":"GB",
    "sg:address":"6 Windsor Rd",
    "sg:city":"Worthing",
    "sg:classifiers":[
        {
            "category":"Travel",
            "subcategory":"Hotels & Motels",
            "type":"Entertainment"
        }
    ],
    "sg:phone":"+44 1903 235163",
    "sg:postcode":"BN11 2LX",
    "sg:province":"West Sussex",
    "sg:tags":[
        "house",
        "guest"
    ],
    "wof:name":"Burcott",
    "wof:placetype":"venue"
},
  "geometry": {"coordinates":[-0.354588,50.813282],"type":"Point"}
}