{
  "type": "Feature",
  "properties": {
    "addr:full":"Unit 1 Princes Square, East Kilbride Glasgow South Lanarkshire G74 1LJ",
    "addr:housenumber":"unit 1",
    "addr:postcode":"g74 1lj",
    "addr:street":"Princes Square",
    "iso:country":"GB",
    "sg:address":"Unit 1 Princes Square, East Kilbride",
    "sg:city":"Glasgow",
    "sg:classifiers":[
        {
            "category":"Shopping",
            "subcategory":"Books",
            "type":"Retail Goods"
        }
    ],
    "sg:phone":"+44 1355 271835",
    "sg:postcode":"G74 1LJ",
    "sg:province":"South Lanarkshire",
    "sg:tags":[
        "bookseller"
    ],
    "wof:name":"Ottakars",
    "wof:placetype":"venue"
},
  "geometry": {"coordinates":[-4.17768,55.761189],"type":"Point"}
}