{
  "type": "Feature",
  "properties": {
    "addr:full":"550 Bradgate Road, Newtown Linford Leicester Leicestershire LE6 0HB",
    "addr:housenumber":"550",
    "addr:postcode":"le6 0hb",
    "addr:street":"Bradgate Road",
    "iso:country":"GB",
    "sg:address":"550 Bradgate Road, Newtown Linford",
    "sg:city":"Leicester",
    "sg:classifiers":[
        {
            "category":"Shopping",
            "subcategory":"Department Store",
            "type":"Retail Goods"
        },
        {
            "category":"Government",
            "subcategory":"Post Office",
            "type":"Public Place"
        }
    ],
    "sg:phone":"+44 1530 242709",
    "sg:postcode":"LE6 0HB",
    "sg:province":"Leicestershire",
    "wof:name":"Newtown Linford Post Office",
    "wof:placetype":"venue"
},
  "geometry": {"coordinates":[-1.2301030159,52.6830062866],"type":"Point"}
}