{
  "type": "Feature",
  "properties": {
    "addr:full":"Corner Shop Stonehaven Aberdeenshire AB39 2BE",
    "addr:postcode":"ab39 2be",
    "addr:street":"Stonehaven",
    "iso:country":"GB",
    "sg:address":"Corner Shop",
    "sg:city":"Stonehaven",
    "sg:classifiers":[
        {
            "category":"Food & Beverages",
            "subcategory":"Fruits & Vegetables",
            "type":"Retail Goods"
        }
    ],
    "sg:phone":"+44 1569 763181",
    "sg:postcode":"AB39 2BE",
    "sg:province":"Aberdeenshire",
    "sg:tags":[
        "greengrocer"
    ],
    "wof:name":"The Shoppe",
    "wof:placetype":"venue"
},
  "geometry": {"coordinates":[-2.2242391109,56.959980011],"type":"Point"}
}