{
  "type": "Feature",
  "properties": {
    "addr:full":"Unit 5 Shawbridge Industrial Estate Glasgow Glasgow City G43 1QN",
    "addr:housenumber":"unit 5",
    "addr:postcode":"g43 1qn",
    "addr:street":"Shawbridge Industrial Estate",
    "iso:country":"GB",
    "sg:address":"Unit 5 Shawbridge Industrial Estate",
    "sg:city":"Glasgow",
    "sg:classifiers":[
        {
            "category":"Retail",
            "subcategory":"Auto Repair",
            "type":"Services"
        }
    ],
    "sg:postcode":"G43 1QN",
    "sg:province":"Glasgow City",
    "sg:tags":[
        "modification",
        "garage"
    ],
    "wof:name":"Jack Moretti",
    "wof:placetype":"venue"
},
  "geometry": {"coordinates":[-4.2955408096,55.8248519897],"type":"Point"}
}