{
  "type": "Feature",
  "properties": {
    "iso:country":"GB",
    "sg:address":"1 Victoria Buildings, Lower Bristol Rd",
    "sg:city":"Bath",
    "sg:classifiers":[
        {
            "category":"Recreation",
            "type":"Entertainment"
        }
    ],
    "sg:phone":"+44 1225 401332",
    "sg:postcode":"BA2 3EH",
    "sg:province":"Somerset",
    "sg:tags":[
        "corporate",
        "leisure"
    ],
    "wof:name":"Creative Celebrations Co",
    "wof:placetype":"venue"
},
  "geometry": {"coordinates":[-2.3779199123,51.3791427612],"type":"Point"}
}