{
  "type": "Feature",
  "properties": {
    "iso:country":"GB",
    "sg:address":"Sutherland House, Matlock Road",
    "sg:city":"Coventry",
    "sg:classifiers":[
        {
            "category":"Professional",
            "type":"Services"
        },
        {
            "category":"Government",
            "subcategory":"Post Office",
            "type":"Public Place"
        }
    ],
    "sg:phone":"+44 845 607 0809",
    "sg:postcode":"CV1 4JQ",
    "sg:province":"West Midlands",
    "sg:tags":[
        "delivery",
        "good",
        "messenger",
        "courier"
    ],
    "wof:name":"Federal Express Europe Inc",
    "wof:placetype":"venue"
},
  "geometry": {"coordinates":[-1.505541,52.422848],"type":"Point"}
}