{
  "type": "Feature",
  "properties": {
    "addr:full":"13 Hatton Street London Greater London NW8 8PL",
    "addr:housenumber":"13",
    "addr:postcode":"nw8 8pl",
    "addr:street":"Hatton Street",
    "iso:country":"GB",
    "sg:address":"13 Hatton Street",
    "sg:city":"London",
    "sg:classifiers":[
        {
            "category":"Manufacturing",
            "subcategory":"Textiles",
            "type":"Manufacturing & Wholesale Goods"
        }
    ],
    "sg:phone":"+44 20 7482 1769",
    "sg:postcode":"NW8 8PL",
    "sg:province":"Greater London",
    "sg:tags":[
        "merchant",
        "agent"
    ],
    "wof:name":"Lionel Newman Ltd.",
    "wof:placetype":"venue"
},
  "geometry": {"coordinates":[-0.173607,51.523323],"type":"Point"}
}