{
  "type": "Feature",
  "properties": {
    "iso:country":"GB",
    "sg:address":"22 Trinity St",
    "sg:city":"Stalybridge",
    "sg:classifiers":[
        {
            "category":"Shopping",
            "subcategory":"Baby Store",
            "type":"Retail Goods"
        }
    ],
    "sg:postcode":"SK15 2BN",
    "sg:province":"Greater Manchester",
    "sg:tags":[
        "babywear",
        "childrens"
    ],
    "wof:name":"Goodwin,Brian,",
    "wof:placetype":"venue"
},
  "geometry": {"coordinates":[-2.056288,53.482792],"type":"Point"}
}