{
  "type": "Feature",
  "properties": {
    "addr:full":"Works Rd Letchworth Hertfordshire SG6 1JU",
    "addr:postcode":"sg6 1ju",
    "addr:street":"Works Rd",
    "iso:country":"GB",
    "sg:address":"Works Rd",
    "sg:city":"Letchworth",
    "sg:classifiers":[
        {
            "category":"Autos & Motor Vehicles",
            "subcategory":"Automobile Sales",
            "type":"Retail Goods"
        }
    ],
    "sg:postcode":"SG6 1JU",
    "sg:province":"Hertfordshire",
    "sg:tags":[
        "car"
    ],
    "wof:name":"Woodland Auto Point",
    "wof:placetype":"venue"
},
  "geometry": {"coordinates":[-0.2030690014,51.9860916138],"type":"Point"}
}