{
  "type": "Feature",
  "properties": {
    "addr:full":"1 High Street, St Davids Haverfordwest Pembrokeshire SA62 6SA",
    "addr:housenumber":"1",
    "addr:postcode":"sa62 6sa",
    "addr:street":"High Street St",
    "iso:country":"GB",
    "sg:address":"1 High Street, St Davids",
    "sg:city":"Haverfordwest",
    "sg:classifiers":[
        {
            "category":"Shopping",
            "subcategory":"Bicycles & Sporting Goods",
            "type":"Retail Goods"
        },
        {
            "category":"Community Center",
            "type":"Public Place"
        }
    ],
    "sg:phone":"+44 1437 721611",
    "sg:postcode":"SA62 6SA",
    "sg:province":"Pembrokeshire",
    "sg:tags":[
        "equipment",
        "recreation",
        "leisure",
        "camping",
        "centre"
    ],
    "wof:name":"T Y F Adventure",
    "wof:placetype":"venue"
},
  "geometry": {"coordinates":[-5.1936221123,51.8735237122],"type":"Point"}
}