{
  "type": "Feature",
  "properties": {
    "addr:full":"260 Banbury Rd Oxford Oxfordshire OX2 7DX",
    "addr:housenumber":"260",
    "addr:postcode":"ox2 7dx",
    "addr:street":"Banbury Rd",
    "iso:country":"GB",
    "sg:address":"260 Banbury Rd",
    "sg:city":"Oxford",
    "sg:classifiers":[
        {
            "category":"Restaurant",
            "type":"Food & Drink"
        }
    ],
    "sg:phone":"+44 1865 554117",
    "sg:postcode":"OX2 7DX",
    "sg:province":"Oxfordshire",
    "sg:tags":[
        "italian"
    ],
    "wof:name":"Tiberio Italian Restaurant",
    "wof:placetype":"venue"
},
  "geometry": {"coordinates":[-1.2647279501,51.7774658203],"type":"Point"}
}