{
  "type": "Feature",
  "properties": {
    "iso:country":"GB",
    "sg:address":"Unit 8, Cribbs Causeway Lysander Road We",
    "sg:city":"Bristol",
    "sg:classifiers":[
        {
            "category":"Wholesale",
            "subcategory":"Non-durable Goods",
            "type":"Manufacturing & Wholesale Goods"
        }
    ],
    "sg:phone":"+44 117 959 1262",
    "sg:postcode":"BS10 7TZ",
    "sg:province":"City of Bristol",
    "sg:tags":[
        "carry",
        "cash"
    ],
    "wof:name":"Makro",
    "wof:placetype":"venue"
},
  "geometry": {"coordinates":[-2.609929,51.529774],"type":"Point"}
}