{
  "type": "Feature",
  "properties": {
    "addr:full":"208 Collis Street Stourbridge Staffordshire DY8 4EQ",
    "addr:housenumber":"208",
    "addr:postcode":"dy8 4eq",
    "addr:street":"Collis Street",
    "iso:country":"GB",
    "sg:address":"208 Collis Street",
    "sg:city":"Stourbridge",
    "sg:classifiers":[
        {
            "category":"Building & Trades",
            "subcategory":"Construction",
            "type":"Services"
        }
    ],
    "sg:phone":"+44 1384 77338",
    "sg:postcode":"DY8 4EQ",
    "sg:province":"Staffordshire",
    "sg:tags":[
        "builder"
    ],
    "wof:name":"Bretcroft Ltd.",
    "wof:placetype":"venue"
},
  "geometry": {"coordinates":[-2.1461849213,52.4712142944],"type":"Point"}
}