{
  "type": "Feature",
  "properties": {
    "addr:full":"19 Oxford Street, Kingsdown Bristol City of Bristol BS2 8HH",
    "addr:housenumber":"19",
    "addr:postcode":"bs2 8hh",
    "addr:street":"Oxford Street",
    "iso:country":"GB",
    "sg:address":"19 Oxford Street, Kingsdown",
    "sg:city":"Bristol",
    "sg:classifiers":[
        {
            "category":"Retail",
            "subcategory":"Auto Repair",
            "type":"Services"
        }
    ],
    "sg:phone":"+44 117 929 1188",
    "sg:postcode":"BS2 8HH",
    "sg:province":"City of Bristol",
    "sg:tags":[
        "modification",
        "garage"
    ],
    "wof:name":"Royal Park Garage",
    "wof:placetype":"venue"
},
  "geometry": {"coordinates":[-2.6012480259,51.4621200562],"type":"Point"}
}