{
  "type": "Feature",
  "properties": {
    "addr:full":"Unit 21 J B J Business Pk Northampton Rd, Blisworth Northampton Buckinghamshire NN7 3DW",
    "addr:housenumber":"unit 21 j",
    "addr:postcode":"nn7 3dw",
    "addr:street":"B J Business Pk Northampton Rd",
    "iso:country":"GB",
    "sg:address":"Unit 21 J B J Business Pk Northampton Rd, Blisworth",
    "sg:city":"Northampton",
    "sg:classifiers":[
        {
            "category":"Home & Garden",
            "subcategory":"Hardware",
            "type":"Retail Goods"
        }
    ],
    "sg:postcode":"NN7 3DW",
    "sg:province":"Buckinghamshire",
    "sg:tags":[
        "fixing",
        "nuts",
        "bolt"
    ],
    "wof:name":"Dee,S,",
    "wof:placetype":"venue"
},
  "geometry": {"coordinates":[-0.939309001,52.1747512817],"type":"Point"}
}