{
  "type": "Feature",
  "properties": {
    "iso:country":"GB",
    "sg:address":"1 Queens Road",
    "sg:city":"Southend-on-sea",
    "sg:classifiers":[
        {
            "category":"Shopping",
            "subcategory":"Pharmacy",
            "type":"Retail Goods"
        }
    ],
    "sg:phone":"+44 1702 390194",
    "sg:postcode":"SS1 1LT",
    "sg:province":"Essex",
    "sg:tags":[
        "store",
        "drug"
    ],
    "wof:name":"Superdrug Stores Plc",
    "wof:placetype":"venue"
},
  "geometry": {"coordinates":[0.709439,51.539295],"type":"Point"}
}