{
  "type": "Feature",
  "properties": {
    "addr:full":"91 Queensway Orpington Kent BR5 1DQ",
    "addr:housenumber":"91",
    "addr:postcode":"br5 1dq",
    "addr:street":"Queensway Orpington",
    "iso:country":"GB",
    "sg:address":"91 Queensway",
    "sg:city":"Orpington",
    "sg:classifiers":[
        {
            "category":"Personal",
            "subcategory":"Barber",
            "type":"Services"
        }
    ],
    "sg:phone":"+44 1689 897499",
    "sg:postcode":"BR5 1DQ",
    "sg:province":"Kent",
    "sg:tags":[
        "men's",
        "hairdresser"
    ],
    "wof:name":"John Graeme",
    "wof:placetype":"venue"
},
  "geometry": {"coordinates":[0.072586,51.388824],"type":"Point"}
}