{
  "type": "Feature",
  "properties": {
    "addr:full":"23 Le Brun Road Eastbourne East Sussex BN21 2HZ",
    "addr:housenumber":"23",
    "addr:postcode":"bn21 2hz",
    "addr:street":"Le Brun Road",
    "iso:country":"GB",
    "sg:address":"23 Le Brun Road",
    "sg:city":"Eastbourne",
    "sg:classifiers":[
        {
            "category":"Home & Garden",
            "subcategory":"Home Furnishings",
            "type":"Retail Goods"
        }
    ],
    "sg:postcode":"BN21 2HZ",
    "sg:province":"East Sussex",
    "sg:tags":[
        "blind",
        "curtain",
        "fitting"
    ],
    "wof:name":"Quendacraft Interiors",
    "wof:placetype":"venue"
},
  "geometry": {"coordinates":[0.276808,50.778046],"type":"Point"}
}