{
  "type": "Feature",
  "properties": {
    "addr:full":"East Park, Eastville Bristol City of Bristol BS5 6YA",
    "addr:postcode":"bs5 6ya",
    "addr:street":"Park",
    "iso:country":"GB",
    "sg:address":"East Park, Eastville",
    "sg:city":"Bristol",
    "sg:classifiers":[
        {
            "category":"Health Services",
            "subcategory":"Doctor",
            "type":"Services"
        },
        {
            "category":"Health Services",
            "subcategory":"Clinic",
            "type":"Services"
        }
    ],
    "sg:phone":"+44 117 951 2692",
    "sg:postcode":"BS5 6YA",
    "sg:province":"City of Bristol",
    "sg:tags":[
        "nh",
        "practitioners"
    ],
    "wof:name":"Eastville Health Centre",
    "wof:placetype":"venue"
},
  "geometry": {"coordinates":[-2.5569190979,51.4734954834],"type":"Point"}
}