{
  "type": "Feature",
  "properties": {
    "iso:country":"GB",
    "sg:address":"439 Hedon Road",
    "sg:city":"Hull",
    "sg:classifiers":[
        {
            "category":"Retail",
            "subcategory":"Auto Repair",
            "type":"Services"
        }
    ],
    "sg:phone":"+44 1482 325612",
    "sg:postcode":"HU9 1RA",
    "sg:province":"East Riding of Yorkshire",
    "sg:tags":[
        "modification",
        "garage",
        "electrician"
    ],
    "wof:name":"Victoria Auto Electrical",
    "wof:placetype":"venue"
},
  "geometry": {"coordinates":[-0.301384,53.747768],"type":"Point"}
}