{
  "type": "Feature",
  "properties": {
    "addr:full":"24 High St Chesterfield Derbyshire S45 9DY",
    "addr:housenumber":"24",
    "addr:postcode":"s45 9dy",
    "addr:street":"High St",
    "iso:country":"GB",
    "sg:address":"24 High St",
    "sg:city":"Chesterfield",
    "sg:classifiers":[
        {
            "category":"Communications",
            "type":"Services"
        }
    ],
    "sg:phone":"+44 1246 862220",
    "sg:postcode":"S45 9DY",
    "sg:province":"Derbyshire",
    "sg:tags":[
        "tv",
        "video",
        "radio"
    ],
    "wof:name":"Marshalls Electrical Discount Store",
    "wof:placetype":"venue"
},
  "geometry": {"coordinates":[-1.4157149792,53.1681556702],"type":"Point"}
}