{
  "type": "Feature",
  "properties": {
    "iso:country":"GB",
    "sg:address":"28 Deanston Dr",
    "sg:city":"Glasgow",
    "sg:classifiers":[
        {
            "category":"Building & Trades",
            "subcategory":"Construction",
            "type":"Services"
        }
    ],
    "sg:phone":"+44 141 636 5863",
    "sg:postcode":"G41 3AD",
    "sg:province":"Glasgow City",
    "sg:tags":[
        "joiner",
        "carpenter"
    ],
    "wof:name":"Acorn Joiners",
    "wof:placetype":"venue"
},
  "geometry": {"coordinates":[-4.27975,55.829796],"type":"Point"}
}