{
  "type": "Feature",
  "properties": {
    "iso:country":"GB",
    "sg:address":"110 Greenway Rd",
    "sg:city":"Runcorn",
    "sg:classifiers":[
        {
            "category":"Personal",
            "subcategory":"Beauty Salon",
            "type":"Services"
        }
    ],
    "sg:phone":"+44 1928 577731",
    "sg:postcode":"WA7 5BS",
    "sg:province":"Cheshire",
    "sg:tags":[
        "unisex",
        "hairdresser"
    ],
    "wof:name":"Spoilt Incorporated Hair Design",
    "wof:placetype":"venue"
},
  "geometry": {"coordinates":[-2.735947,53.336552],"type":"Point"}
}