{
  "type": "Feature",
  "properties": {
    "iso:country":"GB",
    "sg:address":"51 Norris Street",
    "sg:city":"Warrington",
    "sg:classifiers":[
        {
            "category":"Personal",
            "subcategory":"Barber",
            "type":"Services"
        }
    ],
    "sg:phone":"+44 1925 630158",
    "sg:postcode":"WA2 7RJ",
    "sg:province":"Cheshire",
    "sg:tags":[
        "men's",
        "hairdresser"
    ],
    "wof:name":"Manstyle",
    "wof:placetype":"venue"
},
  "geometry": {"coordinates":[-2.580139,53.401741],"type":"Point"}
}