{
  "type": "Feature",
  "properties": {
    "iso:country":"GB",
    "sg:address":"Bones Hill Cottage, West Meon",
    "sg:city":"Petersfield",
    "sg:classifiers":[
        {
            "category":"Home & Garden",
            "subcategory":"Building Materials",
            "type":"Retail Goods"
        },
        {
            "category":"Building & Trades",
            "subcategory":"Construction",
            "type":"Services"
        }
    ],
    "sg:phone":"+44 1730 829342",
    "sg:postcode":"GU32 1NB",
    "sg:province":"Hampshire",
    "sg:tags":[
        "fencing",
        "contractor"
    ],
    "wof:name":"DON TUTT",
    "wof:placetype":"venue"
},
  "geometry": {"coordinates":[-1.088351,51.011459],"type":"Point"}
}