{
  "type": "Feature",
  "properties": {
    "iso:country":"GB",
    "sg:address":"Union Bridge Farm, Finger House Lane",
    "sg:city":"Widnes",
    "sg:classifiers":[
        {
            "category":"Shopping",
            "subcategory":"Computers & Home Electronics",
            "type":"Retail Goods"
        }
    ],
    "sg:phone":"+44 1744 812901",
    "sg:postcode":"WA8 3XF",
    "sg:province":"Cheshire",
    "sg:tags":[
        "aerial",
        "television",
        "radio"
    ],
    "wof:name":"Forber Bros",
    "wof:placetype":"venue"
},
  "geometry": {"coordinates":[-2.701942,53.397743],"type":"Point"}
}