{
  "type": "Feature",
  "properties": {
    "addr:full":"Rose Villas, Prince Alfred Road Liverpool Merseyside L15 8HH",
    "addr:postcode":"l15 8hh",
    "addr:street":"Alfred Road",
    "iso:country":"GB",
    "sg:address":"Rose Villas, Prince Alfred Road",
    "sg:city":"Liverpool",
    "sg:classifiers":[
        {
            "category":"Health Services",
            "subcategory":"Nursing And Care Facility",
            "type":"Services"
        }
    ],
    "sg:phone":"+44 151 734 2587",
    "sg:postcode":"L15 8HH",
    "sg:province":"Merseyside",
    "sg:tags":[
        "home"
    ],
    "wof:name":"Prince Alfred Nursing Home",
    "wof:placetype":"venue"
},
  "geometry": {"coordinates":[-2.918734,53.397839],"type":"Point"}
}