{
  "type": "Feature",
  "properties": {
    "addr:full":"1 Ware Road Hertford Hertfordshire SG13 7DY",
    "addr:housenumber":"1",
    "addr:postcode":"sg13 7dy",
    "addr:street":"Ware Road",
    "iso:country":"GB",
    "sg:address":"1 Ware Road",
    "sg:city":"Hertford",
    "sg:classifiers":[
        {
            "category":"Professional",
            "subcategory":"Printing & Photocopies",
            "type":"Services"
        }
    ],
    "sg:postcode":"SG13 7DY",
    "sg:province":"Hertfordshire",
    "sg:tags":[
        "trophy"
    ],
    "wof:name":"Bidline Ltd.",
    "wof:placetype":"venue"
},
  "geometry": {"coordinates":[-0.071238,51.797764],"type":"Point"}
}