{
  "type": "Feature",
  "properties": {
    "iso:country":"GB",
    "sg:address":"113 Springbank Road, Hither Grn",
    "sg:city":"London",
    "sg:classifiers":[
        {
            "category":"Personal",
            "subcategory":"Beauty Salon",
            "type":"Services"
        }
    ],
    "sg:phone":"+44 20 8698 6974",
    "sg:postcode":"SE13 6SS",
    "sg:province":"Greater London",
    "sg:tags":[
        "unisex",
        "hairdresser"
    ],
    "wof:name":"Making Waves",
    "wof:placetype":"venue"
},
  "geometry": {"coordinates":[0.001265,51.448948],"type":"Point"}
}