{
  "type": "Feature",
  "properties": {
    "addr:full":"Cottage Farm, Cacketts Lane, Cudham Sevenoaks Kent TN14 7QG",
    "addr:postcode":"tn14 7qg",
    "addr:street":"Cacketts Lane",
    "iso:country":"GB",
    "sg:address":"Cottage Farm, Cacketts Lane, Cudham",
    "sg:city":"Sevenoaks",
    "sg:classifiers":[
        {
            "category":"Farming",
            "subcategory":"Poultry Farm",
            "type":"Manufacturing & Wholesale Goods"
        }
    ],
    "sg:phone":"+44 1959 532506",
    "sg:postcode":"TN14 7QG",
    "sg:province":"Kent",
    "sg:tags":[
        "game"
    ],
    "wof:name":"Cottage Farm Turkeys",
    "wof:placetype":"venue"
},
  "geometry": {"coordinates":[0.074925,51.315716],"type":"Point"}
}