{
  "type": "Feature",
  "properties": {
    "iso:country":"GB",
    "sg:address":"33 Parr Street",
    "sg:city":"Poole",
    "sg:classifiers":[
        {
            "category":"Personal",
            "subcategory":"Beauty Salon",
            "type":"Services"
        },
        {
            "category":"Personal",
            "subcategory":"Barber",
            "type":"Services"
        }
    ],
    "sg:phone":"+44 1202 717918",
    "sg:postcode":"BH14 0JX",
    "sg:province":"Dorset",
    "sg:tags":[
        "unisex",
        "hairdresser"
    ],
    "wof:name":"The Hair Craft Studio",
    "wof:placetype":"venue"
},
  "geometry": {"coordinates":[-1.952926,50.724079],"type":"Point"}
}