{
  "type": "Feature",
  "properties": {
    "addr:full":"44 Duff Street Macduff Aberdeenshire AB44 1LN",
    "addr:housenumber":"44",
    "addr:postcode":"ab44 1ln",
    "addr:street":"Duff Street",
    "iso:country":"GB",
    "sg:address":"44 Duff Street",
    "sg:city":"Macduff",
    "sg:classifiers":[
        {
            "category":"Communications",
            "subcategory":"Film & Video Production",
            "type":"Services"
        }
    ],
    "sg:postcode":"AB44 1LN",
    "sg:province":"Aberdeenshire",
    "sg:tags":[
        "tv",
        "studio"
    ],
    "wof:name":"Edward Meldrun",
    "wof:placetype":"venue"
},
  "geometry": {"coordinates":[-2.4950919151,57.6692619324],"type":"Point"}
}