{
  "type": "Feature",
  "properties": {
    "addr:full":"West Farm, Yeovil Marsh Yeovil Somerset BA21 3QF",
    "addr:housenumber":"yeovil",
    "addr:postcode":"ba21 3qf",
    "addr:street":"Marsh",
    "iso:country":"GB",
    "sg:address":"West Farm, Yeovil Marsh",
    "sg:city":"Yeovil",
    "sg:classifiers":[
        {
            "category":"Shopping",
            "subcategory":"Jewelry",
            "type":"Retail Goods"
        }
    ],
    "sg:phone":"+44 1935 413300",
    "sg:postcode":"BA21 3QF",
    "sg:province":"Somerset",
    "sg:tags":[
        "gold",
        "silversmith"
    ],
    "wof:name":"Sue Walsh Designs Ltd",
    "wof:placetype":"venue"
},
  "geometry": {"coordinates":[-2.6392920017,50.9484405518],"type":"Point"}
}