{
  "type": "Feature",
  "properties": {
    "iso:country":"GB",
    "sg:address":"158 Bridge Road, Sutton Bridge",
    "sg:city":"Spalding",
    "sg:classifiers":[
        {
            "category":"Government",
            "subcategory":"Post Office",
            "type":"Public Place"
        }
    ],
    "sg:phone":"+44 1406 350350",
    "sg:postcode":"PE12 9SF",
    "sg:province":"Cambridgeshire",
    "wof:name":"Sutton Bridge Post Office",
    "wof:placetype":"venue"
},
  "geometry": {"coordinates":[0.181016,52.77103],"type":"Point"}
}