{
  "type": "Feature",
  "properties": {
    "iso:country":"GB",
    "sg:address":"Clarence Esp",
    "sg:city":"Southsea",
    "sg:classifiers":[
        {
            "category":"Ferry",
            "type":"Transportation"
        }
    ],
    "sg:phone":"+44 1705 29988",
    "sg:postcode":"PO5 3AD",
    "sg:province":"Hampshire",
    "wof:name":"Hovertravel Ltd",
    "wof:placetype":"venue"
},
  "geometry": {"coordinates":[-1.099929,50.785961],"type":"Point"}
}