{
  "type": "Feature",
  "properties": {
    "iso:country":"GB",
    "sg:address":"296 Ewell Road",
    "sg:city":"Surbiton",
    "sg:classifiers":[
        {
            "category":"Real Estate",
            "subcategory":"Developer",
            "type":"Services"
        }
    ],
    "sg:postcode":"KT6 7AQ",
    "sg:province":"Surrey",
    "sg:tags":[
        "property"
    ],
    "wof:name":"L & S Land Consultants Ltd",
    "wof:placetype":"venue"
},
  "geometry": {"coordinates":[-0.292573,51.384262],"type":"Point"}
}