{
  "type": "Feature",
  "properties": {
    "addr:full":"Keepers Lodge, Mill Lane, Rickinghall Diss Norfolk IP22 1HG",
    "addr:postcode":"ip22 1hg",
    "addr:street":"Mill Lane",
    "iso:country":"GB",
    "sg:address":"Keepers Lodge, Mill Lane, Rickinghall",
    "sg:city":"Diss",
    "sg:classifiers":[
        {
            "category":"Building & Trades",
            "subcategory":"Construction",
            "type":"Services"
        }
    ],
    "sg:phone":"+44 1379 890062",
    "sg:postcode":"IP22 1HG",
    "sg:province":"Norfolk",
    "sg:tags":[
        "builder"
    ],
    "wof:name":"P J Kenny",
    "wof:placetype":"venue"
},
  "geometry": {"coordinates":[0.9982150197,52.3388595581],"type":"Point"}
}