{
  "type": "Feature",
  "properties": {
    "iso:country":"GB",
    "sg:address":"Argoed Road",
    "sg:city":"Buckley",
    "sg:classifiers":[
        {
            "category":"Professional",
            "subcategory":"Computer Services",
            "type":"Services"
        }
    ],
    "sg:phone":"+44 1244 544063",
    "sg:postcode":"CH7 3HZ",
    "sg:province":"Denbighshire",
    "sg:tags":[
        "system",
        "software"
    ],
    "wof:name":"M C B Computers",
    "wof:placetype":"venue"
},
  "geometry": {"coordinates":[-3.081413,53.169437],"type":"Point"}
}