{
  "type": "Feature",
  "properties": {
    "iso:country":"GB",
    "sg:address":"2 Allington Close",
    "sg:city":"London",
    "sg:classifiers":[
        {
            "category":"Professional",
            "subcategory":"Art Services",
            "type":"Services"
        }
    ],
    "sg:phone":"+44 20 8944 1992",
    "sg:postcode":"SW19 5AP",
    "sg:province":"Greater London",
    "sg:tags":[
        "graphic",
        "designer"
    ],
    "wof:name":"S M S Design Alliance Ltd.",
    "wof:placetype":"venue"
},
  "geometry": {"coordinates":[-0.218649,51.425098],"type":"Point"}
}