{
  "type": "Feature",
  "properties": {
    "addr:full":"Alcheringa, Newton Rd, Bovey Tracey Newton Abbot Devon TQ13 9DX",
    "addr:postcode":"tq13 9dx",
    "addr:street":"Newton Rd",
    "iso:country":"GB",
    "sg:address":"Alcheringa, Newton Rd, Bovey Tracey",
    "sg:city":"Newton Abbot",
    "sg:classifiers":[
        {
            "category":"Recreation",
            "subcategory":"Dog Park",
            "type":"Entertainment"
        }
    ],
    "sg:postcode":"TQ13 9DX",
    "sg:province":"Devon",
    "wof:name":"Klippers",
    "wof:placetype":"venue"
},
  "geometry": {"coordinates":[-3.6750590801,50.593208313],"type":"Point"}
}