{
  "type": "Feature",
  "properties": {
    "iso:country":"GB",
    "sg:address":"Read St, Clayton-le-moors",
    "sg:city":"Accrington",
    "sg:classifiers":[
        {
            "category":"Retail",
            "subcategory":"Auto Repair",
            "type":"Services"
        }
    ],
    "sg:postcode":"BB5 5LL",
    "sg:province":"Lancashire",
    "sg:tags":[
        "modification",
        "garage"
    ],
    "wof:name":"Atlas Car & Commercial",
    "wof:placetype":"venue"
},
  "geometry": {"coordinates":[-2.383839,53.778107],"type":"Point"}
}