{
  "type": "Feature",
  "properties": {
    "iso:country":"GB",
    "sg:address":"Thirkleby Manor, Kirby Grindalythe",
    "sg:city":"Malton",
    "sg:classifiers":[
        {
            "category":"Farming",
            "subcategory":"Farm",
            "type":"Manufacturing & Wholesale Goods"
        }
    ],
    "sg:phone":"+44 1944 738221",
    "sg:postcode":"YO17 8DF",
    "sg:province":"North Yorkshire",
    "sg:tags":[
        "mixed",
        "crop"
    ],
    "wof:name":"Sawdon Bros",
    "wof:placetype":"venue"
},
  "geometry": {"coordinates":[-0.617129,54.096786],"type":"Point"}
}