{
  "type": "Feature",
  "properties": {
    "addr:full":"3 Friars Lane Barrow In Furness Cumbria LA13 9NP",
    "addr:housenumber":"3",
    "addr:postcode":"la13 9np",
    "addr:street":"Friars Lane",
    "iso:country":"GB",
    "sg:address":"3 Friars Lane",
    "sg:city":"Barrow In Furness",
    "sg:classifiers":[
        {
            "category":"Recreation",
            "subcategory":"Arcade",
            "type":"Entertainment"
        }
    ],
    "sg:phone":"+44 1229 830272",
    "sg:postcode":"LA13 9NP",
    "sg:province":"Cumbria",
    "sg:tags":[
        "machine",
        "amusement"
    ],
    "wof:name":"Cumbria Electrics & Automatics",
    "wof:placetype":"venue"
},
  "geometry": {"coordinates":[-3.2031040192,54.1135482788],"type":"Point"}
}