{
  "type": "Feature",
  "properties": {
    "addr:full":"Woodfield Park Amersham Buckinghamshire HP6 5QQ",
    "addr:postcode":"hp6 5qq",
    "addr:street":"Park Amersham",
    "iso:country":"GB",
    "sg:address":"Woodfield Park",
    "sg:city":"Amersham",
    "sg:classifiers":[
        {
            "category":"Government",
            "subcategory":"City Hall",
            "type":"Public Place"
        },
        {
            "category":"Arena",
            "subcategory":"Sports Club",
            "type":"Entertainment"
        }
    ],
    "sg:phone":"+44 1494 433330",
    "sg:postcode":"HP6 5QQ",
    "sg:province":"Buckinghamshire",
    "wof:name":"Chesham Boys Tennis & Squash Club",
    "wof:placetype":"venue"
},
  "geometry": {"coordinates":[-0.618186,51.682945],"type":"Point"}
}