{
  "type": "Feature",
  "properties": {
    "iso:country":"GB",
    "sg:address":"205 Nottingham Road",
    "sg:city":"Mansfield",
    "sg:classifiers":[
        {
            "category":"Farming",
            "subcategory":"Nursery",
            "type":"Manufacturing & Wholesale Goods"
        }
    ],
    "sg:postcode":"NG18 4AA",
    "sg:province":"Nottinghamshire",
    "sg:tags":[
        "creche"
    ],
    "wof:name":"Maypole Day Nursery",
    "wof:placetype":"venue"
},
  "geometry": {"coordinates":[-1.1958639622,53.1310844421],"type":"Point"}
}