{
  "type": "Feature",
  "properties": {
    "addr:full":"Units 9 & 10, Enterprise Park, Grovehill Industrial Estate Beverley East Riding of Yorkshire HU17 0JT",
    "addr:housenumber":"units 9 & 10",
    "addr:postcode":"hu17 0jt",
    "addr:street":"Enterprise Park Grovehill Industrial Estate",
    "iso:country":"GB",
    "sg:address":"Units 9 & 10, Enterprise Park, Grovehill Industrial Estate",
    "sg:city":"Beverley",
    "sg:classifiers":[
        {
            "category":"Retail",
            "subcategory":"Auto Repair",
            "type":"Services"
        }
    ],
    "sg:phone":"+44 1482 887021",
    "sg:postcode":"HU17 0JT",
    "sg:province":"East Riding of Yorkshire",
    "sg:tags":[
        "modification",
        "garage"
    ],
    "wof:name":"Andrews Motor Engineers",
    "wof:placetype":"venue"
},
  "geometry": {"coordinates":[-0.40385,53.839989],"type":"Point"}
}