{
  "type": "Feature",
  "properties": {
    "addr:full":"Unit 9 Riverside Industrial Estate, South Street Rochford Essex SS4 1BS",
    "addr:housenumber":"unit 9;estate",
    "addr:postcode":"ss4 1bs",
    "addr:street":"Riverside Industrial;South Street",
    "iso:country":"GB",
    "sg:address":"Unit 9 Riverside Industrial Estate, South Street",
    "sg:city":"Rochford",
    "sg:classifiers":[
        {
            "category":"Professional",
            "type":"Services"
        }
    ],
    "sg:phone":"+44 1702 540055",
    "sg:postcode":"SS4 1BS",
    "sg:province":"Essex",
    "sg:tags":[
        "shopfitters"
    ],
    "wof:name":"Becmor Contractors Ltd.",
    "wof:placetype":"venue"
},
  "geometry": {"coordinates":[0.701389,51.583221],"type":"Point"}
}