{
  "type": "Feature",
  "properties": {
    "iso:country":"GB",
    "sg:address":"Sutton Road, Huthwaite",
    "sg:city":"Sutton-in-ashfield",
    "sg:classifiers":[
        {
            "category":"Home & Garden",
            "subcategory":"Household Appliances",
            "type":"Retail Goods"
        },
        {
            "category":"Retail",
            "subcategory":"Event Space",
            "type":"Services"
        },
        {
            "category":"Communications",
            "type":"Services"
        }
    ],
    "sg:phone":"+44 1623 553434",
    "sg:postcode":"NG17 2NZ",
    "sg:province":"Nottinghamshire",
    "sg:tags":[
        "product",
        "tv",
        "domestic",
        "sales",
        "video",
        "radio",
        "electrical"
    ],
    "wof:name":"Fishers Electrical Discount Ltd.",
    "wof:placetype":"venue"
},
  "geometry": {"coordinates":[-1.304059,53.127041],"type":"Point"}
}