{
  "type": "Feature",
  "properties": {
    "addr:full":"20 Tivoli Road Margate Kent CT9 5SE",
    "addr:housenumber":"20",
    "addr:postcode":"ct9 5se",
    "addr:street":"Tivoli Road",
    "iso:country":"GB",
    "sg:address":"20 Tivoli Road",
    "sg:city":"Margate",
    "sg:classifiers":[
        {
            "category":"Bars & Pubs",
            "type":"Food & Drink"
        },
        {
            "category":"Community Center",
            "subcategory":"Social",
            "type":"Public Place"
        }
    ],
    "sg:phone":"+44 1843 223944",
    "sg:postcode":"CT9 5SE",
    "sg:province":"Kent",
    "sg:tags":[
        "pubs",
        "house",
        "inn",
        "activity"
    ],
    "wof:name":"The Princess of Wales",
    "wof:placetype":"venue"
},
  "geometry": {"coordinates":[1.380518,51.381512],"type":"Point"}
}