{
  "type": "Feature",
  "properties": {
    "addr:full":"8 Princess Street Wigan Lancashire WN3 4HW",
    "addr:housenumber":"8",
    "addr:postcode":"wn3 4hw",
    "addr:street":"Princess Street",
    "iso:country":"GB",
    "sg:address":"8 Princess Street",
    "sg:city":"Wigan",
    "sg:classifiers":[
        {
            "category":"Professional",
            "type":"Services"
        }
    ],
    "sg:phone":"+44 1942 205565",
    "sg:postcode":"WN3 4HW",
    "sg:province":"Lancashire",
    "sg:tags":[
        "shopfitters"
    ],
    "wof:name":"Roba Joinery",
    "wof:placetype":"venue"
},
  "geometry": {"coordinates":[-2.6328029633,53.5419807434],"type":"Point"}
}