{
  "type": "Feature",
  "properties": {
    "addr:full":"895 Fulham Road London Greater London SW6 5HU",
    "addr:housenumber":"895",
    "addr:postcode":"sw6 5hu",
    "addr:street":"Fulham Road",
    "iso:country":"GB",
    "sg:address":"895 Fulham Road",
    "sg:city":"London",
    "sg:classifiers":[
        {
            "category":"Food & Beverages",
            "subcategory":"Bakery",
            "type":"Retail Goods"
        }
    ],
    "sg:phone":"+44 20 7731 3117",
    "sg:postcode":"SW6 5HU",
    "sg:province":"Greater London",
    "sg:tags":[
        "pizza"
    ],
    "wof:name":"Pizzaexpress (Restaurants) Ltd.",
    "wof:placetype":"venue"
},
  "geometry": {"coordinates":[-0.2081390023,51.4732322693],"type":"Point"}
}