{
  "type": "Feature",
  "properties": {
    "iso:country":"GB",
    "sg:address":"106 Kingrosia Park, Clydach",
    "sg:city":"Swansea",
    "sg:classifiers":[
        {
            "category":"Shopping",
            "subcategory":"Computers & Home Electronics",
            "type":"Retail Goods"
        }
    ],
    "sg:postcode":"SA6 5PJ",
    "sg:province":"Swansea",
    "sg:tags":[
        "aerial",
        "television",
        "radio"
    ],
    "wof:name":"Direct Aerials",
    "wof:placetype":"venue"
},
  "geometry": {"coordinates":[-3.881366,51.700386],"type":"Point"}
}