{
  "type": "Feature",
  "properties": {
    "iso:country":"GB",
    "sg:address":"Hamley Farm, Appleton-le-moors",
    "sg:city":"York",
    "sg:classifiers":[
        {
            "category":"Farming",
            "subcategory":"Farm",
            "type":"Manufacturing & Wholesale Goods"
        }
    ],
    "sg:postcode":"YO62 6TG",
    "sg:province":"North Yorkshire",
    "sg:tags":[
        "mixed",
        "crop"
    ],
    "wof:name":"Carter & Feaster",
    "wof:placetype":"venue"
},
  "geometry": {"coordinates":[-0.8723289967,54.2813568115],"type":"Point"}
}