{
  "type": "Feature",
  "properties": {
    "iso:country":"GB",
    "sg:address":"The Surgery, 4 Gwylym Rd",
    "sg:city":"Swansea",
    "sg:classifiers":[
        {
            "category":"Health Services",
            "subcategory":"Doctor",
            "type":"Services"
        }
    ],
    "sg:phone":"+44 1639 830204",
    "sg:postcode":"SA9 2GH",
    "sg:province":"Carmarthenshire",
    "sg:tags":[
        "practitioners"
    ],
    "wof:name":"A.G Gilbey",
    "wof:placetype":"venue"
},
  "geometry": {"coordinates":[-3.81852,51.79829],"type":"Point"}
}