{
  "type": "Feature",
  "properties": {
    "addr:full":"Vauxhall Rd Llanelli Carmarthenshire SA15 3BD",
    "addr:postcode":"sa15 3bd",
    "addr:street":"Vauxhall Rd",
    "iso:country":"GB",
    "sg:address":"Vauxhall Rd",
    "sg:city":"Llanelli",
    "sg:classifiers":[
        {
            "category":"Autos & Motor Vehicles",
            "subcategory":"Automobile Sales",
            "type":"Retail Goods"
        }
    ],
    "sg:postcode":"SA15 3BD",
    "sg:province":"Carmarthenshire",
    "sg:tags":[
        "car"
    ],
    "wof:name":"Howards of Llanelli Ltd",
    "wof:placetype":"venue"
},
  "geometry": {"coordinates":[-4.163899,51.683846],"type":"Point"}
}