{
  "type": "Feature",
  "properties": {
    "addr:full":"2 Pound House, Market Place Holt Norfolk NR25 6BW",
    "addr:housenumber":"2",
    "addr:postcode":"nr25 6bw",
    "addr:street":"Pound;Market Place Holt",
    "iso:country":"GB",
    "sg:address":"2 Pound House, Market Place",
    "sg:city":"Holt",
    "sg:classifiers":[
        {
            "category":"Shopping",
            "subcategory":"Gifts & Souvenirs",
            "type":"Retail Goods"
        }
    ],
    "sg:postcode":"NR25 6BW",
    "sg:province":"Norfolk",
    "sg:tags":[
        "poster",
        "card"
    ],
    "wof:name":"Selections",
    "wof:placetype":"venue"
},
  "geometry": {"coordinates":[1.0899460316,52.9030570984],"type":"Point"}
}