{
  "type": "Feature",
  "properties": {
    "addr:full":"75-79 Glasgow Road Edinburgh City of Edinburgh EH12 8LJ",
    "addr:housenumber":"75-79",
    "addr:postcode":"eh12 8lj",
    "addr:street":"Glasgow Road",
    "iso:country":"GB",
    "sg:address":"75-79 Glasgow Road",
    "sg:city":"Edinburgh",
    "sg:classifiers":[
        {
            "category":"Place Of Worship",
            "type":"Public Place"
        }
    ],
    "sg:phone":"+44 131 316 4292",
    "sg:postcode":"EH12 8LJ",
    "sg:province":"City of Edinburgh",
    "wof:name":"SCOTTISH EPISCOPAL CHURCH",
    "wof:placetype":"venue"
},
  "geometry": {"coordinates":[-3.3020620346,55.9414291382],"type":"Point"}
}