{
  "type": "Feature",
  "properties": {
    "iso:country":"GB",
    "sg:address":"100 Front Street",
    "sg:city":"Newbiggin-by-the-sea",
    "sg:classifiers":[
        {
            "category":"Shopping",
            "subcategory":"Clothing, Apparel, & Fashions",
            "type":"Retail Goods"
        }
    ],
    "sg:postcode":"NE64 6AA",
    "sg:province":"Northumberland",
    "sg:tags":[
        "shop"
    ],
    "wof:name":"Spend-Save",
    "wof:placetype":"venue"
},
  "geometry": {"coordinates":[-1.510189,55.185589],"type":"Point"}
}