{
  "type": "Feature",
  "properties": {
    "addr:full":"61 Main Street, Hotham York East Riding of Yorkshire YO43 4UB",
    "addr:housenumber":"61",
    "addr:postcode":"yo43 4ub",
    "addr:street":"Main Street",
    "iso:country":"GB",
    "sg:address":"61 Main Street, Hotham",
    "sg:city":"York",
    "sg:classifiers":[
        {
            "category":"Farming",
            "subcategory":"Farm",
            "type":"Manufacturing & Wholesale Goods"
        }
    ],
    "sg:postcode":"YO43 4UB",
    "sg:province":"East Riding of Yorkshire",
    "sg:tags":[
        "mixed",
        "crop"
    ],
    "wof:name":"H P Lawson & Son",
    "wof:placetype":"venue"
},
  "geometry": {"coordinates":[-0.6443,53.796276],"type":"Point"}
}