{
  "type": "Feature",
  "properties": {
    "addr:full":"11 Harrowby Close Tiverton Devon EX16 4BQ",
    "addr:housenumber":"11",
    "addr:postcode":"ex16 4bq",
    "addr:street":"Harrowby Close",
    "iso:country":"GB",
    "sg:address":"11 Harrowby Close",
    "sg:city":"Tiverton",
    "sg:classifiers":[
        {
            "category":"Arts & Performance",
            "subcategory":"Music",
            "type":"Entertainment"
        }
    ],
    "sg:postcode":"EX16 4BQ",
    "sg:province":"Devon",
    "sg:tags":[
        "mobile",
        "disco"
    ],
    "wof:name":"Ace Discos",
    "wof:placetype":"venue"
},
  "geometry": {"coordinates":[-3.4736759663,50.9035415649],"type":"Point"}
}