{
  "type": "Feature",
  "properties": {
    "iso:country":"GB",
    "sg:address":"1077 Kingsbury Road, Castlevale",
    "sg:city":"Birmingham",
    "sg:classifiers":[
        {
            "category":"Home & Garden",
            "subcategory":"Home Furnishings",
            "type":"Retail Goods"
        }
    ],
    "sg:phone":"+44 121 749 2623",
    "sg:postcode":"B35 6AJ",
    "sg:province":"West Midlands",
    "sg:tags":[
        "household",
        "furniture"
    ],
    "wof:name":"Heartlands Carpets",
    "wof:placetype":"venue"
},
  "geometry": {"coordinates":[-1.798178,52.520046],"type":"Point"}
}