{
  "type": "Feature",
  "properties": {
    "addr:full":"6 William Street Holyhead Isle of Anglesey LL65 1RN",
    "addr:housenumber":"6",
    "addr:postcode":"ll65 1rn",
    "addr:street":"William Street",
    "iso:country":"GB",
    "sg:address":"6 William Street",
    "sg:city":"Holyhead",
    "sg:classifiers":[
        {
            "category":"Health Services",
            "subcategory":"Optometrist",
            "type":"Services"
        },
        {
            "category":"Shopping",
            "subcategory":"Optician",
            "type":"Retail Goods"
        }
    ],
    "sg:phone":"+44 1407 762332",
    "sg:postcode":"LL65 1RN",
    "sg:province":"Isle of Anglesey",
    "sg:tags":[
        "ophthalmic"
    ],
    "wof:name":"R H Gray Morris",
    "wof:placetype":"venue"
},
  "geometry": {"coordinates":[-4.6339149475,53.3103904724],"type":"Point"}
}