{
  "type": "Feature",
  "properties": {
    "addr:full":"9 Wellington Road Poole Dorset BH14 9LF",
    "addr:housenumber":"9",
    "addr:postcode":"bh14 9lf",
    "addr:street":"Wellington Road",
    "iso:country":"GB",
    "sg:address":"9 Wellington Road",
    "sg:city":"Poole",
    "sg:classifiers":[
        {
            "category":"Building & Trades",
            "subcategory":"Construction",
            "type":"Services"
        }
    ],
    "sg:postcode":"BH14 9LF",
    "sg:province":"Dorset",
    "sg:tags":[
        "decorator",
        "painter"
    ],
    "wof:name":"Colin Higgins",
    "wof:placetype":"venue"
},
  "geometry": {"coordinates":[-1.940119,50.721588],"type":"Point"}
}