{
  "type": "Feature",
  "properties": {
    "addr:full":"87 Praed St Bayswater Greater London W2 1NT",
    "addr:housenumber":"87",
    "addr:postcode":"w2 1nt",
    "addr:street":"Praed St",
    "iso:country":"GB",
    "sg:address":"87 Praed St",
    "sg:city":"Bayswater",
    "sg:classifiers":[
        {
            "category":"Shopping",
            "subcategory":"News",
            "type":"Retail Goods"
        }
    ],
    "sg:phone":"+44 20 7723 2892",
    "sg:postcode":"W2 1NT",
    "sg:province":"Greater London",
    "sg:tags":[
        "newsagent"
    ],
    "wof:name":"Capital News",
    "wof:placetype":"venue"
},
  "geometry": {"coordinates":[-0.17259,51.517151],"type":"Point"}
}