{
  "type": "Feature",
  "properties": {
    "iso:country":"GB",
    "sg:address":"1337 Stratford Rd",
    "sg:city":"Birmingham",
    "sg:classifiers":[
        {
            "category":"Farming",
            "subcategory":"Fish & Marine Products",
            "type":"Manufacturing & Wholesale Goods"
        }
    ],
    "sg:postcode":"B28 9HW",
    "sg:province":"West Midlands",
    "sg:tags":[
        "fishmonger"
    ],
    "wof:name":"Edgar,A R,",
    "wof:placetype":"venue"
},
  "geometry": {"coordinates":[-1.8424619436,52.4278831482],"type":"Point"}
}