{
  "type": "Feature",
  "properties": {
    "addr:full":"8 Kingsway House, Kingsway Team Valley Trading Estate Gateshead Tyne and Wear NE11 0HW",
    "addr:housenumber":"8;house",
    "addr:postcode":"ne11 0hw",
    "addr:street":"Kingsway;Kingsway",
    "iso:country":"GB",
    "sg:address":"8 Kingsway House, Kingsway Team Valley Trading Estate",
    "sg:city":"Gateshead",
    "sg:classifiers":[
        {
            "category":"Home & Garden",
            "subcategory":"Home Furnishings",
            "type":"Retail Goods"
        }
    ],
    "sg:postcode":"NE11 0HW",
    "sg:province":"Tyne and Wear",
    "sg:tags":[
        "tube",
        "fitting",
        "stockist"
    ],
    "wof:name":"R T R Handelsgesellschaf Ries-Thiel-Ruser G M B H & Co.",
    "wof:placetype":"venue"
},
  "geometry": {"coordinates":[-1.6203989983,54.9331130981],"type":"Point"}
}