{
  "type": "Feature",
  "properties": {
    "addr:full":"26 Lydgate Road Sale Cheshire M33 3LW",
    "addr:housenumber":"26",
    "addr:postcode":"m33 3lw",
    "addr:street":"Lydgate Road",
    "iso:country":"GB",
    "sg:address":"26 Lydgate Road",
    "sg:city":"Sale",
    "sg:classifiers":[
        {
            "category":"Professional",
            "subcategory":"Art Services",
            "type":"Services"
        }
    ],
    "sg:postcode":"M33 3LW",
    "sg:province":"Cheshire",
    "sg:tags":[
        "photographer"
    ],
    "wof:name":"Ray Dale Photography",
    "wof:placetype":"venue"
},
  "geometry": {"coordinates":[-2.3132579327,53.4121742249],"type":"Point"}
}