{
  "type": "Feature",
  "properties": {
    "iso:country":"GB",
    "sg:address":"7 Tolcarne Rd",
    "sg:city":"Newquay",
    "sg:classifiers":[
        {
            "category":"Travel",
            "subcategory":"Hotels & Motels",
            "type":"Entertainment"
        }
    ],
    "sg:phone":"+44 1637 878344",
    "sg:postcode":"TR7 2NQ",
    "sg:province":"Cornwall",
    "sg:tags":[
        "house",
        "guest"
    ],
    "wof:name":"Avondales Guest House",
    "wof:placetype":"venue"
},
  "geometry": {"coordinates":[-5.074748,50.415817],"type":"Point"}
}