{
  "type": "Feature",
  "properties": {
    "iso:country":"GB",
    "sg:address":"P O Box 14",
    "sg:city":"Romford",
    "sg:classifiers":[
        {
            "category":"Professional",
            "subcategory":"Computer Services",
            "type":"Services"
        }
    ],
    "sg:phone":"+44 1708 386393",
    "sg:postcode":"RM3 8EQ",
    "sg:province":"Essex",
    "sg:tags":[
        "bureau",
        "facility"
    ],
    "wof:name":"Centrobe",
    "wof:placetype":"venue"
},
  "geometry": {"coordinates":[0.21781,51.598301],"type":"Point"}
}