{
  "type": "Feature",
  "properties": {
    "addr:full":"Market Square Ebbw Vale Blaenau Gwent NP23 4AJ",
    "addr:postcode":"np23 4aj",
    "addr:street":"Market Square",
    "iso:country":"GB",
    "sg:address":"Market Square",
    "sg:city":"Ebbw Vale",
    "sg:classifiers":[
        {
            "category":"Social Services",
            "subcategory":"Adult Care",
            "type":"Services"
        },
        {
            "category":"Community Center",
            "type":"Public Place"
        }
    ],
    "sg:phone":"+44 1495 310315",
    "sg:postcode":"NP23 4AJ",
    "sg:province":"Blaenau Gwent",
    "sg:tags":[
        "day",
        "centre"
    ],
    "wof:name":"Brynmawr Community Education Centre",
    "wof:placetype":"venue"
},
  "geometry": {"coordinates":[-3.1740210056,51.7981071472],"type":"Point"}
}