{
  "type": "Feature",
  "properties": {
    "iso:country":"GB",
    "sg:address":"Govan Subway Kiosk, Govan Road",
    "sg:city":"Glasgow",
    "sg:classifiers":[
        {
            "category":"Shopping",
            "subcategory":"News",
            "type":"Retail Goods"
        }
    ],
    "sg:phone":"+44 141 445 4536",
    "sg:postcode":"G51 2YJ",
    "sg:province":"Glasgow City",
    "sg:tags":[
        "newsagent"
    ],
    "wof:name":"M Kur",
    "wof:placetype":"venue"
},
  "geometry": {"coordinates":[-4.3099298477,55.8620300293],"type":"Point"}
}