{
  "type": "Feature",
  "properties": {
    "iso:country":"GB",
    "sg:address":"191 Mount Pleasant Lane",
    "sg:city":"London",
    "sg:classifiers":[
        {
            "category":"Food & Beverages",
            "subcategory":"Fruits & Vegetables",
            "type":"Retail Goods"
        }
    ],
    "sg:phone":"+44 20 8806 2021",
    "sg:postcode":"E5 9JG",
    "sg:province":"Greater London",
    "sg:tags":[
        "greengrocer"
    ],
    "wof:name":"Jay & Sons",
    "wof:placetype":"venue"
},
  "geometry": {"coordinates":[-0.054219,51.566719],"type":"Point"}
}