{
  "type": "Feature",
  "properties": {
    "addr:full":"Barnmead Road Dagenham Essex RM9 5DX",
    "addr:postcode":"rm9 5dx",
    "addr:street":"Barnmead Road",
    "iso:country":"GB",
    "sg:address":"Barnmead Road",
    "sg:city":"Dagenham",
    "sg:classifiers":[
        {
            "category":"Social Services",
            "subcategory":"Child Care",
            "type":"Services"
        },
        {
            "category":"Social Services",
            "subcategory":"Adult Care",
            "type":"Services"
        }
    ],
    "sg:phone":"+44 20 8270 4244",
    "sg:postcode":"RM9 5DX",
    "sg:province":"Essex",
    "sg:tags":[
        "day",
        "centre"
    ],
    "wof:name":"Fanshawe Luncheon & Leisure Centre",
    "wof:placetype":"venue"
},
  "geometry": {"coordinates":[0.1454769969,51.5471916199],"type":"Point"}
}