{
  "type": "Feature",
  "properties": {
    "iso:country":"GB",
    "sg:address":"Langley Common Road",
    "sg:city":"Wokingham",
    "sg:classifiers":[
        {
            "category":"Shopping",
            "subcategory":"Hobbies, Toys, & Games",
            "type":"Retail Goods"
        }
    ],
    "sg:phone":"+44 1734 760222",
    "sg:postcode":"RG40 4TS",
    "sg:province":"Berkshire",
    "sg:tags":[
        "toy"
    ],
    "wof:name":"John R Campbell",
    "wof:placetype":"venue"
},
  "geometry": {"coordinates":[-0.895271,51.392479],"type":"Point"}
}