{
  "type": "Feature",
  "properties": {
    "addr:full":"32 Barton Street Bath Bath and North East Somerset BA1 1HH",
    "addr:housenumber":"32",
    "addr:postcode":"ba1 1hh",
    "addr:street":"Barton Street",
    "iso:country":"GB",
    "sg:address":"32 Barton Street",
    "sg:city":"Bath",
    "sg:classifiers":[
        {
            "category":"Recreation",
            "subcategory":"Gun Range",
            "type":"Entertainment"
        }
    ],
    "sg:postcode":"BA1 1HH",
    "sg:province":"Bath and North East Somerset",
    "sg:tags":[
        "operator",
        "tour"
    ],
    "wof:name":"G Pharoh",
    "wof:placetype":"venue"
},
  "geometry": {"coordinates":[-2.362759,51.383083],"type":"Point"}
}