{
  "type": "Feature",
  "properties": {
    "iso:country":"GB",
    "sg:address":"320 Normanton Road",
    "sg:city":"Derby",
    "sg:classifiers":[
        {
            "category":"Professional",
            "subcategory":"Lawyer & Legal Services",
            "type":"Services"
        }
    ],
    "sg:postcode":"DE23 6WE",
    "sg:province":"Derbyshire",
    "sg:tags":[
        "solicitor"
    ],
    "wof:name":"David D Douce & Co",
    "wof:placetype":"venue"
},
  "geometry": {"coordinates":[-1.478447,52.910011],"type":"Point"}
}