{
  "type": "Feature",
  "properties": {
    "addr:full":"9 Townsend Avenue St Albans Hertfordshire AL1 3SL",
    "addr:housenumber":"9",
    "addr:postcode":"al1 3sl",
    "addr:street":"Townsend Avenue",
    "iso:country":"GB",
    "sg:address":"9 Townsend Avenue",
    "sg:city":"St Albans",
    "sg:classifiers":[
        {
            "category":"Professional",
            "subcategory":"Management & Consulting",
            "type":"Services"
        }
    ],
    "sg:phone":"+44 1727 859196",
    "sg:postcode":"AL1 3SL",
    "sg:province":"Hertfordshire",
    "sg:tags":[
        "consultant",
        "business"
    ],
    "wof:name":"Barcroft Partnership Ltd.",
    "wof:placetype":"venue"
},
  "geometry": {"coordinates":[-0.332159996,51.7560424805],"type":"Point"}
}