{
  "type": "Feature",
  "properties": {
    "iso:country":"GB",
    "sg:address":"109 Imperial Ave, Mayland",
    "sg:city":"Chelmsford",
    "sg:classifiers":[
        {
            "category":"Real Estate",
            "subcategory":"Real Estate Agent",
            "type":"Services"
        }
    ],
    "sg:postcode":"CM3 6AJ",
    "sg:province":"Essex",
    "wof:name":"Sanjivi,M,",
    "wof:placetype":"venue"
},
  "geometry": {"coordinates":[0.750126,51.686893],"type":"Point"}
}