{
  "type": "Feature",
  "properties": {
    "iso:country":"GB",
    "sg:address":"Balliol Road, Kempston",
    "sg:city":"Bedford",
    "sg:classifiers":[
        {
            "category":"Education",
            "subcategory":"School",
            "type":"Public Place"
        },
        {
            "category":"Government",
            "subcategory":"Office",
            "type":"Public Place"
        }
    ],
    "sg:phone":"+44 1234 300601",
    "sg:postcode":"MK42 7ER",
    "sg:province":"Bedfordshire",
    "sg:tags":[
        "local",
        "authority"
    ],
    "wof:name":"Balliol Lower School",
    "wof:placetype":"venue"
},
  "geometry": {"coordinates":[-0.500764,52.113781],"type":"Point"}
}