{
  "type": "Feature",
  "properties": {
    "addr:full":"Bishops Road, Outer Circle Road Lincoln Lincolnshire LN2 4JZ",
    "addr:postcode":"ln2 4jz",
    "addr:street":"Bishops Road Outer Circle Road",
    "iso:country":"GB",
    "sg:address":"Bishops Road, Outer Circle Road",
    "sg:city":"Lincoln",
    "sg:classifiers":[
        {
            "category":"Professional",
            "subcategory":"Engineering",
            "type":"Services"
        }
    ],
    "sg:phone":"+44 1522 569569",
    "sg:postcode":"LN2 4JZ",
    "sg:province":"Lincolnshire",
    "sg:tags":[
        "contractor",
        "electrical",
        "engineer"
    ],
    "wof:name":"Daubney Holdings Ltd.",
    "wof:placetype":"venue"
},
  "geometry": {"coordinates":[-0.512149,53.238049],"type":"Point"}
}