{
  "type": "Feature",
  "properties": {
    "addr:full":"Gervas Ho, Long Leys Ho Lincoln Lincolnshire LN1 1EF",
    "addr:postcode":"ln1 1ef",
    "addr:street":"Long Leys Ho Lincoln",
    "iso:country":"GB",
    "sg:address":"Gervas Ho, Long Leys Ho",
    "sg:city":"Lincoln",
    "sg:classifiers":[
        {
            "category":"Health Services",
            "subcategory":"Hospital",
            "type":"Services"
        }
    ],
    "sg:phone":"+44 1522 546546",
    "sg:postcode":"LN1 1EF",
    "sg:province":"Lincolnshire",
    "wof:name":"Lincoln District Healthcare N H S Trust",
    "wof:placetype":"venue"
},
  "geometry": {"coordinates":[-0.5578290224,53.2421607971],"type":"Point"}
}