{
  "type": "Feature",
  "properties": {
    "iso:country":"GB",
    "sg:address":"30 Croft Gardens, Birkby",
    "sg:city":"Huddersfield",
    "sg:classifiers":[
        {
            "category":"Building & Trades",
            "subcategory":"Landscaping Services",
            "type":"Services"
        }
    ],
    "sg:phone":"+44 1484 542841",
    "sg:postcode":"HD2 2FL",
    "sg:province":"West Yorkshire",
    "sg:tags":[
        "forestry",
        "tree"
    ],
    "wof:name":"Birkby Tree Services",
    "wof:placetype":"venue"
},
  "geometry": {"coordinates":[-1.7987869978,53.662563324],"type":"Point"}
}