{
  "type": "Feature",
  "properties": {
    "addr:full":"New Rectory East Road, Kilkhampton Bude Cornwall EX23 9QS",
    "addr:postcode":"ex23 9qs",
    "addr:street":"East Road",
    "iso:country":"GB",
    "sg:address":"New Rectory East Road, Kilkhampton",
    "sg:city":"Bude",
    "sg:classifiers":[
        {
            "category":"Place Of Worship",
            "type":"Public Place"
        }
    ],
    "sg:postcode":"EX23 9QS",
    "sg:province":"Cornwall",
    "wof:name":"St.James Church",
    "wof:placetype":"venue"
},
  "geometry": {"coordinates":[-4.484374,50.873714],"type":"Point"}
}