{
  "type": "Feature",
  "properties": {
    "iso:country":"GB",
    "sg:address":"27 Bridge Street",
    "sg:city":"Abingdon",
    "sg:classifiers":[
        {
            "category":"Personal",
            "type":"Services"
        },
        {
            "category":"Professional",
            "subcategory":"Lawyer & Legal Services",
            "type":"Services"
        }
    ],
    "sg:phone":"+44 1235 522375",
    "sg:postcode":"OX14 3HN",
    "sg:province":"Oxfordshire",
    "sg:tags":[
        "advice",
        "counselling"
    ],
    "wof:name":"Abingdon Bridge Information & Support For Young People",
    "wof:placetype":"venue"
},
  "geometry": {"coordinates":[-1.280381,51.669518],"type":"Point"}
}