{
  "type": "Feature",
  "properties": {
    "addr:full":"Brookside Business Centre, Northway Lane Tewkesbury Gloucestershire GL20 8JG",
    "addr:postcode":"gl20 8jg",
    "addr:street":"Northway Lane",
    "iso:country":"GB",
    "sg:address":"Brookside Business Centre, Northway Lane",
    "sg:city":"Tewkesbury",
    "sg:classifiers":[
        {
            "category":"Professional",
            "subcategory":"Art Services",
            "type":"Services"
        }
    ],
    "sg:postcode":"GL20 8JG",
    "sg:province":"Gloucestershire",
    "sg:tags":[
        "photographer"
    ],
    "wof:name":"Posers Photographic Studios",
    "wof:placetype":"venue"
},
  "geometry": {"coordinates":[-2.1038041115,51.9978027344],"type":"Point"}
}