{
  "type": "Feature",
  "properties": {
    "iso:country":"GB",
    "sg:address":"187 Front Street",
    "sg:city":"Chester-le-street",
    "sg:classifiers":[
        {
            "category":"Autos & Motor Vehicles",
            "subcategory":"Automobile Sales",
            "type":"Retail Goods"
        }
    ],
    "sg:phone":"+44 191 388 4221",
    "sg:postcode":"DH3 3AP",
    "sg:province":"Durham",
    "sg:tags":[
        "car"
    ],
    "wof:name":"Wheelers of Chester Le Street",
    "wof:placetype":"venue"
},
  "geometry": {"coordinates":[-1.573573947,54.8531990051],"type":"Point"}
}