{
  "type": "Feature",
  "properties": {
    "addr:full":"2 Swinton Square Knutsford Cheshire WA16 6HH",
    "addr:housenumber":"2",
    "addr:postcode":"wa16 6hh",
    "addr:street":"Swinton Square",
    "iso:country":"GB",
    "sg:address":"2 Swinton Square",
    "sg:city":"Knutsford",
    "sg:classifiers":[
        {
            "category":"Real Estate",
            "subcategory":"Architect",
            "type":"Services"
        }
    ],
    "sg:postcode":"WA16 6HH",
    "sg:province":"Cheshire",
    "wof:name":"Johnstone Godfrey & Associates",
    "wof:placetype":"venue"
},
  "geometry": {"coordinates":[-2.3713419437,53.303478241],"type":"Point"}
}