{
  "type": "Feature",
  "properties": {
    "iso:country":"GB",
    "sg:address":"46 Harbour Hill Road",
    "sg:city":"Poole",
    "sg:classifiers":[
        {
            "category":"Retail",
            "subcategory":"Auto Repair",
            "type":"Services"
        }
    ],
    "sg:phone":"+44 1202 676911",
    "sg:postcode":"BH15 3PZ",
    "sg:province":"Dorset",
    "sg:tags":[
        "body",
        "car"
    ],
    "wof:name":"Philip N Stuckey Engineer",
    "wof:placetype":"venue"
},
  "geometry": {"coordinates":[-1.969156,50.729053],"type":"Point"}
}