{
  "type": "Feature",
  "properties": {
    "iso:country":"GB",
    "sg:address":"4a Albion Ho, High St",
    "sg:city":"Holsworthy",
    "sg:classifiers":[
        {
            "category":"Health Services",
            "subcategory":"Dentist",
            "type":"Services"
        }
    ],
    "sg:phone":"+44 1409 254706",
    "sg:postcode":"EX22 6EL",
    "sg:province":"Cornwall",
    "wof:name":"Andrew Brown & Team",
    "wof:placetype":"venue"
},
  "geometry": {"coordinates":[-4.3527340889,50.8100128174],"type":"Point"}
}