{
  "type": "Feature",
  "properties": {
    "addr:full":"Unit 4b Marchfields Way Weston-super-mare Somerset BS23 3YY",
    "addr:housenumber":"unit 4b",
    "addr:postcode":"bs23 3yy",
    "addr:street":"Marchfields Way",
    "iso:country":"GB",
    "sg:address":"Unit 4b Marchfields Way",
    "sg:city":"Weston-super-mare",
    "sg:classifiers":[
        {
            "category":"Home & Garden",
            "subcategory":"Carpets & Floor Coverings",
            "type":"Retail Goods"
        }
    ],
    "sg:phone":"+44 1934 419100",
    "sg:postcode":"BS23 3YY",
    "sg:province":"Somerset",
    "sg:tags":[
        "carpets",
        "rug",
        "matting"
    ],
    "wof:name":"Carpet Right",
    "wof:placetype":"venue"
},
  "geometry": {"coordinates":[-2.965884,51.342613],"type":"Point"}
}