{
  "type": "Feature",
  "properties": {
    "iso:country":"GB",
    "sg:address":"Unit 20 Pipers Industrial Estate, Pipers Lane",
    "sg:city":"Thatcham",
    "sg:classifiers":[
        {
            "category":"Manufacturing",
            "subcategory":"Glass & Minerals",
            "type":"Manufacturing & Wholesale Goods"
        }
    ],
    "sg:phone":"+44 1635 871340",
    "sg:postcode":"RG19 4NA",
    "sg:province":"Berkshire",
    "sg:tags":[
        "fibre",
        "moulding"
    ],
    "wof:name":"Sonning Reinforced Plastics",
    "wof:placetype":"venue"
},
  "geometry": {"coordinates":[-1.24073,51.39521],"type":"Point"}
}