{
  "type": "Feature",
  "properties": {
    "addr:full":"Felstead St London Greater London E9 5LG",
    "addr:postcode":"e9 5lg",
    "addr:street":"Felstead St",
    "iso:country":"GB",
    "sg:address":"Felstead St",
    "sg:city":"London",
    "sg:classifiers":[
        {
            "category":"Professional",
            "subcategory":"Art Services",
            "type":"Services"
        }
    ],
    "sg:postcode":"E9 5LG",
    "sg:province":"Greater London",
    "sg:tags":[
        "photographer"
    ],
    "wof:name":"Aitken,Alexander,",
    "wof:placetype":"venue"
},
  "geometry": {"coordinates":[-0.025647,51.544521],"type":"Point"}
}