{
  "type": "Feature",
  "properties": {
    "iso:country":"GB",
    "sg:address":"34 Argyll Arcade",
    "sg:city":"Glasgow",
    "sg:classifiers":[
        {
            "category":"Professional",
            "subcategory":"Accounting & Tax Preparation",
            "type":"Services"
        }
    ],
    "sg:phone":"+44 141 221 8155",
    "sg:postcode":"G2 8BD",
    "sg:province":"Glasgow City",
    "sg:tags":[
        "accountant",
        "activites",
        "primarily",
        "bookeeping"
    ],
    "wof:name":"ACE ACCOUNTING SERVICES",
    "wof:placetype":"venue"
},
  "geometry": {"coordinates":[-4.260089,55.85865],"type":"Point"}
}