{
  "type": "Feature",
  "properties": {
    "addr:full":"73 The Ridge Hastings East Sussex TN34 2AB",
    "addr:housenumber":"73",
    "addr:postcode":"tn34 2ab",
    "addr:street":"The Ridge",
    "iso:country":"GB",
    "sg:address":"73 The Ridge",
    "sg:city":"Hastings",
    "sg:classifiers":[
        {
            "category":"Building & Trades",
            "subcategory":"Construction",
            "type":"Services"
        }
    ],
    "sg:postcode":"TN34 2AB",
    "sg:province":"East Sussex",
    "sg:tags":[
        "dry",
        "lining",
        "plasterers",
        "screeders"
    ],
    "wof:name":"Bartholomew Plastering",
    "wof:placetype":"venue"
},
  "geometry": {"coordinates":[0.602076,50.876034],"type":"Point"}
}