{
  "type": "Feature",
  "properties": {
    "iso:country":"GB",
    "sg:address":"Woodhead Road",
    "sg:city":"Huddersfield",
    "sg:classifiers":[
        {
            "category":"Autos & Motor Vehicles",
            "subcategory":"Fuel & Gas Station",
            "type":"Retail Goods"
        }
    ],
    "sg:phone":"+44 1484 426080",
    "sg:postcode":"HD4 6EP",
    "sg:province":"West Yorkshire",
    "sg:tags":[
        "petrol",
        "filling"
    ],
    "wof:name":"Jet Filling Station",
    "wof:placetype":"venue"
},
  "geometry": {"coordinates":[-1.7945590019,53.6314353943],"type":"Point"}
}