{
  "type": "Feature",
  "properties": {
    "iso:country":"GB",
    "sg:address":"30 Highfield Avenue, Farington",
    "sg:city":"Preston",
    "sg:classifiers":[
        {
            "category":"Building & Trades",
            "subcategory":"Construction",
            "type":"Services"
        }
    ],
    "sg:phone":"+44 1772 465347",
    "sg:postcode":"PR5 2GP",
    "sg:province":"Lancashire",
    "sg:tags":[
        "dry",
        "lining",
        "plasterers",
        "screeders"
    ],
    "wof:name":"Martin Jay",
    "wof:placetype":"venue"
},
  "geometry": {"coordinates":[-2.68437,53.701889],"type":"Point"}
}