{
  "type": "Feature",
  "properties": {
    "addr:full":"33 Watford Way, Hendon London Greater London NW4 3JH",
    "addr:housenumber":"33",
    "addr:postcode":"nw4 3jh",
    "addr:street":"Watford Way",
    "iso:country":"GB",
    "sg:address":"33 Watford Way, Hendon",
    "sg:city":"London",
    "sg:classifiers":[
        {
            "category":"Restaurant",
            "type":"Food & Drink"
        }
    ],
    "sg:phone":"+44 1628 891655",
    "sg:postcode":"NW4 3JH",
    "sg:province":"Greater London",
    "wof:name":"Wimpy International Ltd.",
    "wof:placetype":"venue"
},
  "geometry": {"coordinates":[-0.2284300029,51.5837478638],"type":"Point"}
}