{
  "type": "Feature",
  "properties": {
    "iso:country":"GB",
    "sg:address":"3 Albany Mews, Montagu Avenue",
    "sg:city":"Newcastle-upon-tyne",
    "sg:classifiers":[
        {
            "category":"Real Estate",
            "subcategory":"Developer",
            "type":"Services"
        }
    ],
    "sg:phone":"+44 191 213 2509",
    "sg:postcode":"NE3 4JW",
    "sg:province":"Tyne and Wear",
    "sg:tags":[
        "property"
    ],
    "wof:name":"Bassenhall Ltd.",
    "wof:placetype":"venue"
},
  "geometry": {"coordinates":[-1.640255,54.996506],"type":"Point"}
}