{
  "type": "Feature",
  "properties": {
    "iso:country":"GB",
    "sg:address":"36 Locksgreen Crescent",
    "sg:city":"Swindon",
    "sg:classifiers":[
        {
            "category":"Taxi",
            "type":"Transportation"
        }
    ],
    "sg:phone":"+44 1793 702000",
    "sg:postcode":"SN25 3HR",
    "sg:province":"Wiltshire",
    "sg:tags":[
        "mini",
        "cab"
    ],
    "wof:name":"Airports Connect Ltd.",
    "wof:placetype":"venue"
},
  "geometry": {"coordinates":[-1.8131680489,51.5863456726],"type":"Point"}
}