{
  "type": "Feature",
  "properties": {
    "addr:full":"397 Acton Lane, Acton London Greater London W3 8NP",
    "addr:housenumber":"397",
    "addr:postcode":"w3 8np",
    "addr:street":"Acton Lane",
    "iso:country":"GB",
    "sg:address":"397 Acton Lane, Acton",
    "sg:city":"London",
    "sg:classifiers":[
        {
            "category":"Wholesale",
            "subcategory":"Non-durable Goods",
            "type":"Manufacturing & Wholesale Goods"
        }
    ],
    "sg:phone":"+44 20 8993 1397",
    "sg:postcode":"W3 8NP",
    "sg:province":"Greater London",
    "sg:tags":[
        "carry",
        "cash"
    ],
    "wof:name":"West London Cash & Carry Ltd.",
    "wof:placetype":"venue"
},
  "geometry": {"coordinates":[-0.266088,51.506001],"type":"Point"}
}