{
  "type": "Feature",
  "properties": {
    "iso:country":"GB",
    "sg:address":"152 Ladbroke Gro",
    "sg:city":"London",
    "sg:classifiers":[
        {
            "category":"Food & Beverages",
            "subcategory":"Liquor & Beverages",
            "type":"Retail Goods"
        }
    ],
    "sg:postcode":"W10 5NA",
    "sg:province":"Greater London",
    "sg:tags":[
        "beer",
        "spirit",
        "wines"
    ],
    "wof:name":"Universal Store",
    "wof:placetype":"venue"
},
  "geometry": {"coordinates":[-0.210472,51.51836],"type":"Point"}
}