{
  "type": "Feature",
  "properties": {
    "iso:country":"GB",
    "sg:address":"Unit 2, New York Way, New York Industrial Park",
    "sg:city":"Newcastle-upon-tyne",
    "sg:classifiers":[
        {
            "category":"Professional",
            "subcategory":"Printing & Photocopies",
            "type":"Services"
        }
    ],
    "sg:phone":"+44 191 293 1000",
    "sg:postcode":"NE27 0QF",
    "sg:province":"Northumberland",
    "sg:tags":[
        "process",
        "screen",
        "printer"
    ],
    "wof:name":"Nor-Screen Ltd.",
    "wof:placetype":"venue"
},
  "geometry": {"coordinates":[-1.4984439611,55.0218849182],"type":"Point"}
}