{
  "type": "Feature",
  "properties": {
    "addr:full":"Unit A, 10 Salamons Way, Ferry Lane Rainham Essex RM13 9UL",
    "addr:housenumber":"unit a 10",
    "addr:postcode":"rm13 9ul",
    "addr:street":"Salamons Way Ferry Lane",
    "iso:country":"GB",
    "sg:address":"Unit A, 10 Salamons Way, Ferry Lane",
    "sg:city":"Rainham",
    "sg:classifiers":[
        {
            "category":"Freight",
            "type":"Transportation"
        }
    ],
    "sg:phone":"+44 1708 553845",
    "sg:postcode":"RM13 9UL",
    "sg:province":"Essex",
    "sg:tags":[
        "haulage",
        "road"
    ],
    "wof:name":"Listrel Ltd.",
    "wof:placetype":"venue"
},
  "geometry": {"coordinates":[0.190426,51.517914],"type":"Point"}
}