{
  "type": "Feature",
  "properties": {
    "addr:full":"Three Corners Garage, Ploughley Road Bicester Oxfordshire OX25 2LU",
    "addr:postcode":"ox25 2lu",
    "addr:street":"Ploughley Road",
    "iso:country":"GB",
    "sg:address":"Three Corners Garage, Ploughley Road",
    "sg:city":"Bicester",
    "sg:classifiers":[
        {
            "category":"Autos & Motor Vehicles",
            "subcategory":"Automobile Sales",
            "type":"Retail Goods"
        }
    ],
    "sg:postcode":"OX25 2LU",
    "sg:province":"Oxfordshire",
    "sg:tags":[
        "car"
    ],
    "wof:name":"C & D Labross",
    "wof:placetype":"venue"
},
  "geometry": {"coordinates":[-1.12216,51.869541],"type":"Point"}
}