{
  "type": "Feature",
  "properties": {
    "addr:full":"601 Lordship Lane London Greater London N22 5LG",
    "addr:housenumber":"601",
    "addr:postcode":"n22 5lg",
    "addr:street":"Lordship Lane",
    "iso:country":"GB",
    "sg:address":"601 Lordship Lane",
    "sg:city":"London",
    "sg:classifiers":[
        {
            "category":"Organizations",
            "subcategory":"Community Association",
            "type":"Services"
        },
        {
            "category":"Organizations",
            "subcategory":"Non-profit Organization",
            "type":"Services"
        }
    ],
    "sg:phone":"+44 870 190 4440",
    "sg:postcode":"N22 5LG",
    "sg:province":"Greater London",
    "sg:tags":[
        "organisation",
        "care",
        "animal",
        "welfare"
    ],
    "wof:name":"Wood Green Animal Shelters",
    "wof:placetype":"venue"
},
  "geometry": {"coordinates":[-0.101465,51.599182],"type":"Point"}
}