{
  "type": "Feature",
  "properties": {
    "iso:country":"GB",
    "sg:address":"115 Lowmoor Road, Kirkby In Ashfield",
    "sg:city":"Nottingham",
    "sg:classifiers":[
        {
            "category":"Retail",
            "subcategory":"Auto Repair",
            "type":"Services"
        }
    ],
    "sg:phone":"+44 1623 756669",
    "sg:postcode":"NG17 7BH",
    "sg:province":"Nottinghamshire",
    "sg:tags":[
        "body",
        "car"
    ],
    "wof:name":"D B S Bodystyles",
    "wof:placetype":"venue"
},
  "geometry": {"coordinates":[-1.24442,53.111523],"type":"Point"}
}