{
  "type": "Feature",
  "properties": {
    "addr:full":"Houghton House, Wessington Way Sunderland Tyne and Wear SR5 3RJ",
    "addr:postcode":"sr5 3rj",
    "addr:street":"Wessington Way",
    "iso:country":"GB",
    "sg:address":"Houghton House, Wessington Way",
    "sg:city":"Sunderland",
    "sg:classifiers":[
        {
            "category":"Travel",
            "subcategory":"Travel Agent",
            "type":"Entertainment"
        }
    ],
    "sg:phone":"+44 191 525 3000",
    "sg:postcode":"SR5 3RJ",
    "sg:province":"Tyne and Wear",
    "wof:name":"Trust Holidays Ltd.",
    "wof:placetype":"venue"
},
  "geometry": {"coordinates":[-1.4304130077,54.9190368652],"type":"Point"}
}