{
  "type": "Feature",
  "properties": {
    "iso:country":"GB",
    "sg:address":"Units 3 -5, Wainman Rd, Woodston Indstl Est",
    "sg:city":"Peterborough",
    "sg:classifiers":[
        {
            "category":"Utilities",
            "subcategory":"Natural Gas",
            "type":"Services"
        }
    ],
    "sg:postcode":"PE2 7BU",
    "sg:province":"Cambridgeshire",
    "sg:tags":[
        "supplier",
        "industrial"
    ],
    "wof:name":"Crane,C,",
    "wof:placetype":"venue"
},
  "geometry": {"coordinates":[-0.26655,52.553459],"type":"Point"}
}