{
  "type": "Feature",
  "properties": {
    "addr:full":"Units 3 -5, Wainman Rd, Woodston Indstl Est Peterborough Cambridgeshire PE2 7BU",
    "addr:housenumber":"units 3 -5",
    "addr:postcode":"pe2 7bu",
    "addr:street":"Wainman Rd;Indstl Est",
    "iso:country":"GB",
    "sg:address":"Units 3 -5, Wainman Rd, Woodston Indstl Est",
    "sg:city":"Peterborough",
    "sg:classifiers":[
        {
            "category":"Utilities",
            "subcategory":"Natural Gas",
            "type":"Services"
        }
    ],
    "sg:postcode":"PE2 7BU",
    "sg:province":"Cambridgeshire",
    "sg:tags":[
        "supplier",
        "industrial"
    ],
    "wof:name":"Crane,C,",
    "wof:placetype":"venue"
},
  "geometry": {"coordinates":[-0.26655,52.553459],"type":"Point"}
}