{
  "type": "Feature",
  "properties": {
    "addr:full":"T R House, 134/138 Borough High Street London Greater London SE1 1LB",
    "addr:housenumber":"134 / 138",
    "addr:postcode":"se1 1lb",
    "addr:street":"Borough High Street",
    "iso:country":"GB",
    "sg:address":"T R House, 134/138 Borough High Street",
    "sg:city":"London",
    "sg:classifiers":[
        {
            "category":"Freight",
            "type":"Transportation"
        }
    ],
    "sg:phone":"+44 20 7799 2424",
    "sg:postcode":"SE1 1LB",
    "sg:province":"Greater London",
    "sg:tags":[
        "shipping"
    ],
    "wof:name":"Islamic Republic of Iran Shipping Lines",
    "wof:placetype":"venue"
},
  "geometry": {"coordinates":[-0.092399,51.502514],"type":"Point"}
}