{
  "type": "Feature",
  "properties": {
    "addr:full":"128 Luton Rd Chatham Kent ME4 5AD",
    "addr:housenumber":"128",
    "addr:postcode":"me4 5ad",
    "addr:street":"Luton Rd",
    "iso:country":"GB",
    "sg:address":"128 Luton Rd",
    "sg:city":"Chatham",
    "sg:classifiers":[
        {
            "category":"Shopping",
            "subcategory":"Pharmacy",
            "type":"Retail Goods"
        }
    ],
    "sg:phone":"+44 1634 842129",
    "sg:postcode":"ME4 5AD",
    "sg:province":"Kent",
    "sg:tags":[
        "pharmacist",
        "chemist"
    ],
    "wof:name":"Co-op Pharmacy",
    "wof:placetype":"venue"
},
  "geometry": {"coordinates":[0.5381109715,51.3754920959],"type":"Point"}
}