{
  "type": "Feature",
  "properties": {
    "addr:full":"Hyperbarrick Medical Centre, Derriford Rd Plymouth Devon PL6 8BQ",
    "addr:postcode":"pl6 8bq",
    "addr:street":"Derriford Rd",
    "iso:country":"GB",
    "sg:address":"Hyperbarrick Medical Centre, Derriford Rd",
    "sg:city":"Plymouth",
    "sg:classifiers":[
        {
            "category":"Government",
            "subcategory":"Post Office",
            "type":"Public Place"
        }
    ],
    "sg:phone":"+44 1752 703224",
    "sg:postcode":"PL6 8BQ",
    "sg:province":"Devon",
    "sg:tags":[
        "organisation",
        "soc",
        "research"
    ],
    "wof:name":"Partners In Clinical Research",
    "wof:placetype":"venue"
},
  "geometry": {"coordinates":[-4.11761,50.418743],"type":"Point"}
}