{
  "type": "Feature",
  "properties": {
    "iso:country":"GB",
    "sg:address":"28 Oakwood Hill Industrial Estat, E Oakwood Hill",
    "sg:city":"Loughton",
    "sg:classifiers":[
        {
            "category":"Building & Trades",
            "subcategory":"Plumbing",
            "type":"Services"
        }
    ],
    "sg:phone":"+44 20 8502 1931",
    "sg:postcode":"IG10 3TZ",
    "sg:province":"Essex",
    "sg:tags":[
        "heating"
    ],
    "wof:name":"D B J (Woodford) Ltd.",
    "wof:placetype":"venue"
},
  "geometry": {"coordinates":[0.063364,51.63961],"type":"Point"}
}