{
  "type": "Feature",
  "properties": {
    "iso:country":"GB",
    "sg:address":"Greenbank Business Centre, Greenbank Road",
    "sg:city":"Aberdeen",
    "sg:classifiers":[
        {
            "category":"Building & Trades",
            "subcategory":"Cleaning & Sanitation",
            "type":"Services"
        }
    ],
    "sg:phone":"+44 1224 248030",
    "sg:postcode":"AB12 3BN",
    "sg:province":"Aberdeen City",
    "sg:tags":[
        "commercial"
    ],
    "wof:name":"Internal Pipeline Inspections",
    "wof:placetype":"venue"
},
  "geometry": {"coordinates":[-2.0886800289,57.1257095337],"type":"Point"}
}