{
  "type": "Feature",
  "properties": {
    "addr:full":"8 Lansdowne Street Leamington Spa Warwickshire CV32 4SP",
    "addr:housenumber":"8",
    "addr:postcode":"cv32 4sp",
    "addr:street":"Lansdowne Street",
    "iso:country":"GB",
    "sg:address":"8 Lansdowne Street",
    "sg:city":"Leamington Spa",
    "sg:classifiers":[
        {
            "category":"Food & Beverages",
            "subcategory":"Meat & Fish",
            "type":"Retail Goods"
        }
    ],
    "sg:postcode":"CV32 4SP",
    "sg:province":"Warwickshire",
    "sg:tags":[
        "chip"
    ],
    "wof:name":"Lansdowne Fish Shop",
    "wof:placetype":"venue"
},
  "geometry": {"coordinates":[-1.5305249691,52.293674469],"type":"Point"}
}