{
  "type": "Feature",
  "properties": {
    "iso:country":"GB",
    "sg:address":"Brunswick House, 26 Mount Sion",
    "sg:city":"Tunbridge Wells",
    "sg:classifiers":[
        {
            "category":"Real Estate",
            "subcategory":"Architect",
            "type":"Services"
        }
    ],
    "sg:phone":"+44 1908 393151",
    "sg:postcode":"TN1 1TW",
    "sg:province":"Kent",
    "wof:name":"Robert Brown Consultancy",
    "wof:placetype":"venue"
},
  "geometry": {"coordinates":[0.262534,51.12616],"type":"Point"}
}