{
  "type": "Feature",
  "properties": {
    "addr:full":"95 Chatsworth Rd Clapton Greater London E5 0LH",
    "addr:housenumber":"95",
    "addr:postcode":"e5 0lh",
    "addr:street":"Chatsworth Rd",
    "iso:country":"GB",
    "sg:address":"95 Chatsworth Rd",
    "sg:city":"Clapton",
    "sg:classifiers":[
        {
            "category":"Personal",
            "type":"Services"
        }
    ],
    "sg:phone":"+44 20 8985 4794",
    "sg:postcode":"E5 0LH",
    "sg:province":"Greater London",
    "sg:tags":[
        "dressmaker"
    ],
    "wof:name":"Elimode Ltd",
    "wof:placetype":"venue"
},
  "geometry": {"coordinates":[-0.0458710007,51.5552558899],"type":"Point"}
}