{
  "type": "Feature",
  "properties": {
    "iso:country":"GB",
    "sg:address":"25 Bell Street",
    "sg:city":"Sawbridgeworth",
    "sg:classifiers":[
        {
            "category":"Professional",
            "subcategory":"Lawyer & Legal Services",
            "type":"Services"
        }
    ],
    "sg:phone":"+44 1279 722453",
    "sg:postcode":"CM21 9AS",
    "sg:province":"Essex",
    "sg:tags":[
        "solicitor"
    ],
    "wof:name":"David A Barley",
    "wof:placetype":"venue"
},
  "geometry": {"coordinates":[0.149292,51.81282],"type":"Point"}
}