{
  "type": "Feature",
  "properties": {
    "iso:country":"GB",
    "sg:address":"256 Sturry Road",
    "sg:city":"Canterbury",
    "sg:classifiers":[
        {
            "category":"Utilities",
            "subcategory":"Mobile Phone",
            "type":"Services"
        }
    ],
    "sg:postcode":"CT1 1HQ",
    "sg:province":"Kent",
    "sg:tags":[
        "battery",
        "supplier"
    ],
    "wof:name":"Halls Batteries",
    "wof:placetype":"venue"
},
  "geometry": {"coordinates":[1.102941,51.291485],"type":"Point"}
}