{
  "type": "Feature",
  "properties": {
    "addr:full":"Unit 6ab Ormlie Industrial Estate Thurso Highland KW14 7BY",
    "addr:postcode":"kw14 7by",
    "addr:street":"Industrial Estate",
    "iso:country":"GB",
    "sg:address":"Unit 6ab Ormlie Industrial Estate",
    "sg:city":"Thurso",
    "sg:classifiers":[
        {
            "category":"Professional",
            "subcategory":"Engineering",
            "type":"Services"
        }
    ],
    "sg:phone":"+44 1847 895328",
    "sg:postcode":"KW14 7BY",
    "sg:province":"Highland",
    "sg:tags":[
        "precision",
        "engineer"
    ],
    "wof:name":"Highland Precision Ltd.",
    "wof:placetype":"venue"
},
  "geometry": {"coordinates":[-3.5258669853,58.5965652466],"type":"Point"}
}