{
  "type": "Feature",
  "properties": {
    "iso:country":"GB",
    "sg:address":"Unit 19 Bukta Garage, Romiley Street",
    "sg:city":"Stockport",
    "sg:classifiers":[
        {
            "category":"Manufacturing",
            "subcategory":"Buildings",
            "type":"Manufacturing & Wholesale Goods"
        }
    ],
    "sg:phone":"+44 161 480 2406",
    "sg:postcode":"SK1 2LB",
    "sg:province":"Cheshire",
    "sg:tags":[
        "system",
        "air conditioning"
    ],
    "wof:name":"Auto Climate Services",
    "wof:placetype":"venue"
},
  "geometry": {"coordinates":[-2.1430799961,53.4158096313],"type":"Point"}
}