{
  "type": "Feature",
  "properties": {
    "iso:country":"GB",
    "sg:address":"Wetherby Road",
    "sg:city":"Harrogate",
    "sg:classifiers":[
        {
            "category":"Building & Trades",
            "subcategory":"Construction",
            "type":"Services"
        }
    ],
    "sg:postcode":"HG3 1DE",
    "sg:province":"North Yorkshire",
    "sg:tags":[
        "monumental",
        "mason"
    ],
    "wof:name":"Stephenson's Memorial Works",
    "wof:placetype":"venue"
},
  "geometry": {"coordinates":[-1.4971139431,53.9858055115],"type":"Point"}
}