{
  "type": "Feature",
  "properties": {
    "addr:full":"1 Church Gate, Kegworth Derby Leicestershire DE74 2ED",
    "addr:housenumber":"1",
    "addr:postcode":"de74 2ed",
    "addr:street":"Church Gate",
    "iso:country":"GB",
    "sg:address":"1 Church Gate, Kegworth",
    "sg:city":"Derby",
    "sg:classifiers":[
        {
            "category":"Fast Food",
            "type":"Food & Drink"
        }
    ],
    "sg:postcode":"DE74 2ED",
    "sg:province":"Leicestershire",
    "sg:tags":[
        "away",
        "take"
    ],
    "wof:name":"Kegworth Chop Suey House",
    "wof:placetype":"venue"
},
  "geometry": {"coordinates":[-1.3375279903,52.8423881531],"type":"Point"}
}