{
  "type": "Feature",
  "properties": {
    "iso:country":"GB",
    "sg:address":"Castlemains Farm, Dirleton",
    "sg:city":"North Berwick",
    "sg:classifiers":[
        {
            "category":"Farming",
            "subcategory":"Farm",
            "type":"Manufacturing & Wholesale Goods"
        }
    ],
    "sg:phone":"+44 1620 850224",
    "sg:postcode":"EH39 5EF",
    "sg:province":"East Lothian",
    "sg:tags":[
        "mixed",
        "crop"
    ],
    "wof:name":"W J Simpson & Son",
    "wof:placetype":"venue"
},
  "geometry": {"coordinates":[-2.775815,56.047764],"type":"Point"}
}