{
  "type": "Feature",
  "properties": {
    "addr:full":"49 Burgate Canterbury Kent CT1 2HW",
    "addr:housenumber":"49",
    "addr:postcode":"ct1 2hw",
    "addr:street":"Burgate Canterbury",
    "iso:country":"GB",
    "sg:address":"49 Burgate",
    "sg:city":"Canterbury",
    "sg:classifiers":[
        {
            "category":"Travel",
            "subcategory":"Travel Agent",
            "type":"Entertainment"
        }
    ],
    "sg:phone":"+44 1227 459975",
    "sg:postcode":"CT1 2HW",
    "sg:province":"Kent",
    "wof:name":"Worldchoice Carlson",
    "wof:placetype":"venue"
},
  "geometry": {"coordinates":[1.082379,51.278603],"type":"Point"}
}