{
  "type": "Feature",
  "properties": {
    "addr:full":"10 Juniper Close, Chineham Basingstoke Hampshire RG24 8XH",
    "addr:housenumber":"10",
    "addr:postcode":"rg24 8xh",
    "addr:street":"Juniper Close",
    "iso:country":"GB",
    "sg:address":"10 Juniper Close, Chineham",
    "sg:city":"Basingstoke",
    "sg:classifiers":[
        {
            "category":"Building & Trades",
            "subcategory":"Construction",
            "type":"Services"
        }
    ],
    "sg:phone":"+44 1256 461326",
    "sg:postcode":"RG24 8XH",
    "sg:province":"Hampshire",
    "sg:tags":[
        "joiner",
        "carpenter"
    ],
    "wof:name":"R A Mitchell",
    "wof:placetype":"venue"
},
  "geometry": {"coordinates":[-1.0505850315,51.297077179],"type":"Point"}
}