{
  "type": "Feature",
  "properties": {
    "iso:country":"GB",
    "sg:address":"28 Middle Way",
    "sg:city":"Lewes",
    "sg:classifiers":[
        {
            "category":"Professional",
            "subcategory":"Engineering",
            "type":"Services"
        }
    ],
    "sg:postcode":"BN7 1NH",
    "sg:province":"East Sussex",
    "sg:tags":[
        "contractor",
        "electrical",
        "engineer"
    ],
    "wof:name":"R J Turk Electrical",
    "wof:placetype":"venue"
},
  "geometry": {"coordinates":[-0.0087240003,50.8761863708],"type":"Point"}
}