{
  "type": "Feature",
  "properties": {
    "addr:full":"473 Caerleon Road Newport Newport NP19 7LX",
    "addr:housenumber":"473",
    "addr:postcode":"np19 7lx",
    "addr:street":"Caerleon Road",
    "iso:country":"GB",
    "sg:address":"473 Caerleon Road",
    "sg:city":"Newport",
    "sg:classifiers":[
        {
            "category":"Professional",
            "subcategory":"Management & Consulting",
            "type":"Services"
        }
    ],
    "sg:phone":"+44 1633 668193",
    "sg:postcode":"NP19 7LX",
    "sg:province":"Newport",
    "sg:tags":[
        "consultant",
        "specialist"
    ],
    "wof:name":"Back Sratch Nails",
    "wof:placetype":"venue"
},
  "geometry": {"coordinates":[-2.9744050503,51.6039886475],"type":"Point"}
}