{
  "type": "Feature",
  "properties": {
    "addr:full":"93b Hospital Street Nantwich Cheshire CW5 5RU",
    "addr:housenumber":"93b",
    "addr:postcode":"cw5 5ru",
    "addr:street":"Hospital Street",
    "iso:country":"GB",
    "sg:address":"93b Hospital Street",
    "sg:city":"Nantwich",
    "sg:classifiers":[
        {
            "category":"Retail",
            "subcategory":"Auto Repair",
            "type":"Services"
        }
    ],
    "sg:postcode":"CW5 5RU",
    "sg:province":"Cheshire",
    "sg:tags":[
        "modification",
        "garage"
    ],
    "wof:name":"Brunt Motor Car Repairs",
    "wof:placetype":"venue"
},
  "geometry": {"coordinates":[-2.5164480209,53.0660247803],"type":"Point"}
}