{
  "type": "Feature",
  "properties": {
    "addr:full":"55 King Street Southwell Nottinghamshire NG25 0EH",
    "addr:housenumber":"55",
    "addr:postcode":"ng25 0eh",
    "addr:street":"King Street",
    "iso:country":"GB",
    "sg:address":"55 King Street",
    "sg:city":"Southwell",
    "sg:classifiers":[
        {
            "category":"Shopping",
            "subcategory":"News",
            "type":"Retail Goods"
        }
    ],
    "sg:phone":"+44 1636 813279",
    "sg:postcode":"NG25 0EH",
    "sg:province":"Nottinghamshire",
    "sg:tags":[
        "newsagent"
    ],
    "wof:name":"One Stop Convenience",
    "wof:placetype":"venue"
},
  "geometry": {"coordinates":[-0.952735,53.079342],"type":"Point"}
}