{
  "type": "Feature",
  "properties": {
    "iso:country":"GB",
    "sg:address":"11 Chapelton Avenue",
    "sg:city":"Glasgow",
    "sg:classifiers":[
        {
            "category":"Professional",
            "subcategory":"Management & Consulting",
            "type":"Services"
        },
        {
            "category":"Government",
            "subcategory":"Post Office",
            "type":"Public Place"
        }
    ],
    "sg:phone":"+44 141 942 5391",
    "sg:postcode":"G61 2RE",
    "sg:province":"East Dunbartonshire",
    "sg:tags":[
        "consultant",
        "business",
        "sculptor",
        "activity"
    ],
    "wof:name":"Sculpted Pewter Products",
    "wof:placetype":"venue"
},
  "geometry": {"coordinates":[-4.327373,55.915474],"type":"Point"}
}