{
  "type": "Feature",
  "properties": {
    "addr:full":"Unit 20, Acton Park Industrial Estate, The Vale London Greater London W3 7QE",
    "addr:housenumber":"unit 20",
    "addr:postcode":"w3 7qe",
    "addr:street":"Park Industrial;The",
    "iso:country":"GB",
    "sg:address":"Unit 20, Acton Park Industrial Estate, The Vale",
    "sg:city":"London",
    "sg:classifiers":[
        {
            "category":"Deli",
            "type":"Food & Drink"
        }
    ],
    "sg:phone":"+44 20 8749 2123",
    "sg:postcode":"W3 7QE",
    "sg:province":"Greater London",
    "sg:tags":[
        "delicatessen"
    ],
    "wof:name":"Roman (Delicatessen Merchants) Ltd.",
    "wof:placetype":"venue"
},
  "geometry": {"coordinates":[-0.2454600036,51.5068511963],"type":"Point"}
}