{
  "type": "Feature",
  "properties": {
    "iso:country":"GB",
    "sg:address":"76 Witton Street",
    "sg:city":"Northwich",
    "sg:classifiers":[
        {
            "category":"Shopping",
            "subcategory":"Hobbies, Toys, & Games",
            "type":"Retail Goods"
        }
    ],
    "sg:phone":"+44 1606 45053",
    "sg:postcode":"CW9 5AE",
    "sg:province":"Cheshire",
    "sg:tags":[
        "computer"
    ],
    "wof:name":"Level 1",
    "wof:placetype":"venue"
},
  "geometry": {"coordinates":[-2.50877,53.262135],"type":"Point"}
}