{
  "type": "Feature",
  "properties": {
    "addr:full":"25 Camellia Crescent Clacton-on-sea Essex CO16 7EU",
    "addr:housenumber":"25",
    "addr:postcode":"co16 7eu",
    "addr:street":"Camellia Crescent",
    "iso:country":"GB",
    "sg:address":"25 Camellia Crescent",
    "sg:city":"Clacton-on-sea",
    "sg:classifiers":[
        {
            "category":"Home & Garden",
            "subcategory":"Household Appliances",
            "type":"Retail Goods"
        },
        {
            "category":"Manufacturing",
            "subcategory":"Food",
            "type":"Manufacturing & Wholesale Goods"
        }
    ],
    "sg:phone":"+44 1255 435700",
    "sg:postcode":"CO16 7EU",
    "sg:province":"Essex",
    "sg:tags":[
        "supplier",
        "domestic",
        "oven",
        "microwave",
        "manufacturer"
    ],
    "wof:name":"Microwave Oven Services",
    "wof:placetype":"venue"
},
  "geometry": {"coordinates":[1.133246,51.80114],"type":"Point"}
}