{
  "type": "Feature",
  "properties": {
    "addr:full":"Unit 14, Avon Business Park Lodge, Lodge Causeway Bristol City of Bristol BS16 3JP",
    "addr:housenumber":"unit 14",
    "addr:postcode":"bs16 3jp",
    "addr:street":"Avon Business Park;Lodge Causeway",
    "iso:country":"GB",
    "sg:address":"Unit 14, Avon Business Park Lodge, Lodge Causeway",
    "sg:city":"Bristol",
    "sg:classifiers":[
        {
            "category":"Military Area",
            "subcategory":"Air Force Base",
            "type":"Public Place"
        }
    ],
    "sg:phone":"+44 117 965 7002",
    "sg:postcode":"BS16 3JP",
    "sg:province":"City of Bristol",
    "sg:tags":[
        "cutting",
        "laser"
    ],
    "wof:name":"Laserline Engineering Ltd.",
    "wof:placetype":"venue"
},
  "geometry": {"coordinates":[-2.591429,51.453667],"type":"Point"}
}