{
  "type": "Feature",
  "properties": {
    "addr:full":"82 Market Gate Arbroath Angus DD11 1AT",
    "addr:housenumber":"82",
    "addr:postcode":"dd11 1at",
    "addr:street":"Market Gate",
    "iso:country":"GB",
    "sg:address":"82 Market Gate",
    "sg:city":"Arbroath",
    "sg:classifiers":[
        {
            "category":"Bars & Pubs",
            "type":"Food & Drink"
        }
    ],
    "sg:phone":"+44 1241 873505",
    "sg:postcode":"DD11 1AT",
    "sg:province":"Angus",
    "sg:tags":[
        "pubs",
        "inn"
    ],
    "wof:name":"Central Bar",
    "wof:placetype":"venue"
},
  "geometry": {"coordinates":[-2.5829789639,56.5574989319],"type":"Point"}
}