{
  "type": "Feature",
  "properties": {
    "addr:full":"32 Great Underbank Stockport Cheshire SK1 1NB",
    "addr:housenumber":"32",
    "addr:postcode":"sk1 1nb",
    "addr:street":"Great Underbank",
    "iso:country":"GB",
    "sg:address":"32 Great Underbank",
    "sg:city":"Stockport",
    "sg:classifiers":[
        {
            "category":"Professional",
            "type":"Services"
        }
    ],
    "sg:phone":"+44 161 477 7907",
    "sg:postcode":"SK1 1NB",
    "sg:province":"Cheshire",
    "sg:tags":[
        "caterer"
    ],
    "wof:name":"Mersey Catering Services Ltd",
    "wof:placetype":"venue"
},
  "geometry": {"coordinates":[-2.159231,53.410809],"type":"Point"}
}