{
  "type": "Feature",
  "properties": {
    "iso:country":"GB",
    "sg:address":"6 Warbreck Hill Road",
    "sg:city":"Blackpool",
    "sg:classifiers":[
        {
            "category":"Travel",
            "subcategory":"Hotels & Motels",
            "type":"Entertainment"
        },
        {
            "category":"Bars & Pubs",
            "subcategory":"Hookah Bar",
            "type":"Food & Drink"
        }
    ],
    "sg:phone":"+44 1253 354151",
    "sg:postcode":"FY2 9SP",
    "sg:province":"Lancashire",
    "sg:tags":[
        "self",
        "holiday",
        "catering"
    ],
    "wof:name":"WESTHOLME HOLIDAY FLATS",
    "wof:placetype":"venue"
},
  "geometry": {"coordinates":[-3.0519399643,53.8336791992],"type":"Point"}
}