{
  "type": "Feature",
  "properties": {
    "addr:full":"28 Osmaston Road Derby Derbyshire DE1 2HR",
    "addr:housenumber":"28",
    "addr:postcode":"de1 2hr",
    "addr:street":"Osmaston Road",
    "iso:country":"GB",
    "sg:address":"28 Osmaston Road",
    "sg:city":"Derby",
    "sg:classifiers":[
        {
            "category":"Professional",
            "subcategory":"Printing & Photocopies",
            "type":"Services"
        }
    ],
    "sg:phone":"+44 1332 372437",
    "sg:postcode":"DE1 2HR",
    "sg:province":"Derbyshire",
    "sg:tags":[
        "printer"
    ],
    "wof:name":"Prontaprint Ltd.",
    "wof:placetype":"venue"
},
  "geometry": {"coordinates":[-1.475043,52.918488],"type":"Point"}
}