{
  "type": "Feature",
  "properties": {
    "addr:full":"Coniscliffe Road Darlington Durham DL3 7RL",
    "addr:postcode":"dl3 7rl",
    "addr:street":"Coniscliffe Road",
    "iso:country":"GB",
    "sg:address":"Coniscliffe Road",
    "sg:city":"Darlington",
    "sg:classifiers":[
        {
            "category":"Government",
            "subcategory":"Court House",
            "type":"Public Place"
        }
    ],
    "sg:phone":"+44 1325 463224",
    "sg:postcode":"DL3 7RL",
    "sg:province":"Durham",
    "wof:name":"Darlington County Court",
    "wof:placetype":"venue"
},
  "geometry": {"coordinates":[-1.559106,54.523453],"type":"Point"}
}