{
  "type": "Feature",
  "properties": {
    "addr:full":"Clive Road, Failsworth Manchester Lancashire M35 0NN",
    "addr:postcode":"m35 0nn",
    "addr:street":"Clive Road",
    "iso:country":"GB",
    "sg:address":"Clive Road, Failsworth",
    "sg:city":"Manchester",
    "sg:classifiers":[
        {
            "category":"Education",
            "subcategory":"School",
            "type":"Public Place"
        },
        {
            "category":"Government",
            "subcategory":"Office",
            "type":"Public Place"
        }
    ],
    "sg:phone":"+44 161 681 6663",
    "sg:postcode":"M35 0NN",
    "sg:province":"Lancashire",
    "sg:tags":[
        "local",
        "authority"
    ],
    "wof:name":"St. Mary's R C Primary School",
    "wof:placetype":"venue"
},
  "geometry": {"coordinates":[-2.163374,53.508461],"type":"Point"}
}