{
  "type": "Feature",
  "properties": {
    "iso:country":"GB",
    "sg:address":"Muir St",
    "sg:city":"Larkhall",
    "sg:classifiers":[
        {
            "category":"Organizations",
            "subcategory":"Non-profit Organization",
            "type":"Services"
        }
    ],
    "sg:phone":"+44 1698 881770",
    "sg:postcode":"ML9 2BG",
    "sg:province":"South Lanarkshire",
    "sg:tags":[
        "organisation",
        "voluntary",
        "charity"
    ],
    "wof:name":"Lanarkshire Association For Mental Health",
    "wof:placetype":"venue"
},
  "geometry": {"coordinates":[-3.969734,55.739948],"type":"Point"}
}