{
  "type": "Feature",
  "properties": {
    "iso:country":"GB",
    "sg:address":"25 Warley Hill",
    "sg:city":"Brentwood",
    "sg:classifiers":[
        {
            "category":"Wholesale",
            "subcategory":"Office Equipment",
            "type":"Manufacturing & Wholesale Goods"
        }
    ],
    "sg:phone":"+44 1277 225661",
    "sg:postcode":"CM14 5HR",
    "sg:province":"Essex",
    "sg:tags":[
        "partition",
        "cubicle"
    ],
    "wof:name":"Boon Group Interiors",
    "wof:placetype":"venue"
},
  "geometry": {"coordinates":[0.298687,51.612526],"type":"Point"}
}