{
  "type": "Feature",
  "properties": {
    "addr:full":"70 Main Street Doune Stirling FK16 6BW",
    "addr:housenumber":"70",
    "addr:postcode":"fk16 6bw",
    "addr:street":"Main Street",
    "iso:country":"GB",
    "sg:address":"70 Main Street",
    "sg:city":"Doune",
    "sg:classifiers":[
        {
            "category":"Retail",
            "subcategory":"Veterinary Services",
            "type":"Services"
        }
    ],
    "sg:phone":"+44 1786 841304",
    "sg:postcode":"FK16 6BW",
    "sg:province":"Stirling",
    "sg:tags":[
        "surgeon",
        "activity"
    ],
    "wof:name":"Struthers & Scott",
    "wof:placetype":"venue"
},
  "geometry": {"coordinates":[-4.049265,56.188759],"type":"Point"}
}