{
  "type": "Feature",
  "properties": {
    "addr:full":"Llanharan, Brynna Pontyclun Bridgend CF72 9QT",
    "addr:postcode":"cf72 9qt",
    "iso:country":"GB",
    "sg:address":"Llanharan, Brynna",
    "sg:city":"Pontyclun",
    "sg:classifiers":[
        {
            "category":"Farming",
            "subcategory":"Livestock Farm",
            "type":"Manufacturing & Wholesale Goods"
        },
        {
            "category":"Farming",
            "subcategory":"Farm",
            "type":"Manufacturing & Wholesale Goods"
        }
    ],
    "sg:phone":"+44 1443 237396",
    "sg:postcode":"CF72 9QT",
    "sg:province":"Bridgend",
    "sg:tags":[
        "mixed",
        "crop",
        "others"
    ],
    "wof:name":"L & C Howell",
    "wof:placetype":"venue"
},
  "geometry": {"coordinates":[-3.3920590878,51.5222854614],"type":"Point"}
}