{
  "type": "Feature",
  "properties": {
    "addr:full":"Markfield Court, Ratby Lane Markfield Leicestershire LE67 9RJ",
    "addr:postcode":"le67 9rj",
    "addr:street":"Markfield Court Ratby Lane",
    "iso:country":"GB",
    "sg:address":"Markfield Court, Ratby Lane",
    "sg:city":"Markfield",
    "sg:classifiers":[
        {
            "category":"Health Services",
            "subcategory":"Nursing And Care Facility",
            "type":"Services"
        }
    ],
    "sg:phone":"+44 1530 242595",
    "sg:postcode":"LE67 9RJ",
    "sg:province":"Leicestershire",
    "sg:tags":[
        "home"
    ],
    "wof:name":"Ashbourne Homes Ltd.",
    "wof:placetype":"venue"
},
  "geometry": {"coordinates":[-1.266359,52.683464],"type":"Point"}
}