{
  "type": "Feature",
  "properties": {
    "iso:country":"GB",
    "sg:address":"Newton Ho, Newton Rd",
    "sg:city":"Hinckley",
    "sg:classifiers":[
        {
            "category":"Wholesale",
            "subcategory":"Furniture",
            "type":"Manufacturing & Wholesale Goods"
        }
    ],
    "sg:phone":"+44 1455 890890",
    "sg:postcode":"LE10 3DS",
    "sg:province":"Leicestershire",
    "sg:tags":[
        "shop",
        "fitting"
    ],
    "wof:name":"Ryking Shop Fronts",
    "wof:placetype":"venue"
},
  "geometry": {"coordinates":[-1.408809,52.537529],"type":"Point"}
}