{
  "type": "Feature",
  "properties": {
    "iso:country":"GB",
    "sg:address":"57 Tailors Court",
    "sg:city":"Southend-on-sea",
    "sg:classifiers":[
        {
            "category":"Wholesale",
            "subcategory":"Motor Vehicles",
            "type":"Manufacturing & Wholesale Goods"
        }
    ],
    "sg:postcode":"SS2 5SX",
    "sg:province":"Essex",
    "sg:tags":[
        "aircraft",
        "spare"
    ],
    "wof:name":"Avocet Aviation Ltd.",
    "wof:placetype":"venue"
},
  "geometry": {"coordinates":[0.71049,51.562279],"type":"Point"}
}