{
  "type": "Feature",
  "properties": {
    "iso:country":"GB",
    "sg:address":"5 Rosemary Close",
    "sg:city":"Peacehaven",
    "sg:classifiers":[
        {
            "category":"Building & Trades",
            "subcategory":"Construction",
            "type":"Services"
        }
    ],
    "sg:phone":"+44 1273 586891",
    "sg:postcode":"BN10 8BY",
    "sg:province":"East Sussex",
    "sg:tags":[
        "dry",
        "lining",
        "builder",
        "plasterers",
        "screeders"
    ],
    "wof:name":"N D T Building & Plastering Contractors",
    "wof:placetype":"venue"
},
  "geometry": {"coordinates":[0.003958,50.800537],"type":"Point"}
}