{
  "type": "Feature",
  "properties": {
    "addr:full":"York Road, Bedminster Bristol City of Bristol BS3 4AB",
    "addr:postcode":"bs3 4ab",
    "addr:street":"York Road",
    "iso:country":"GB",
    "sg:address":"York Road, Bedminster",
    "sg:city":"Bristol",
    "sg:classifiers":[
        {
            "category":"Autos & Motor Vehicles",
            "subcategory":"Fuel & Gas Station",
            "type":"Retail Goods"
        }
    ],
    "sg:phone":"+44 117 971 7132",
    "sg:postcode":"BS3 4AB",
    "sg:province":"City of Bristol",
    "sg:tags":[
        "hr",
        "petrol"
    ],
    "wof:name":"Texaco Service Station",
    "wof:placetype":"venue"
},
  "geometry": {"coordinates":[-2.5859160423,51.4451065063],"type":"Point"}
}