{
  "type": "Feature",
  "properties": {
    "addr:full":"47 Market Street Cleethorpes Lincolnshire DN35 8LY",
    "addr:housenumber":"47",
    "addr:postcode":"dn35 8ly",
    "addr:street":"Market Street",
    "iso:country":"GB",
    "sg:address":"47 Market Street",
    "sg:city":"Cleethorpes",
    "sg:classifiers":[
        {
            "category":"Restaurant",
            "type":"Food & Drink"
        }
    ],
    "sg:postcode":"DN35 8LY",
    "sg:province":"Lincolnshire",
    "wof:name":"Palm Grill House",
    "wof:placetype":"venue"
},
  "geometry": {"coordinates":[-0.0311890002,53.5598983765],"type":"Point"}
}