{
  "type": "Feature",
  "properties": {
    "iso:country":"GB",
    "sg:address":"Southgate Office Village, 286b Chase Rd, Southgate",
    "sg:city":"London",
    "sg:classifiers":[
        {
            "category":"Shopping",
            "subcategory":"Clothing, Apparel, & Fashions",
            "type":"Retail Goods"
        }
    ],
    "sg:postcode":"N14 6HF",
    "sg:province":"Greater London",
    "sg:tags":[
        "clothing",
        "fabric"
    ],
    "wof:name":"Goodrange Ltd",
    "wof:placetype":"venue"
},
  "geometry": {"coordinates":[-0.12667,51.63356],"type":"Point"}
}