{
  "type": "Feature",
  "properties": {
    "addr:full":"40 High Road London Greater London N2 9PJ",
    "addr:housenumber":"40",
    "addr:postcode":"n2 9pj",
    "addr:street":"High Road",
    "iso:country":"GB",
    "sg:address":"40 High Road",
    "sg:city":"London",
    "sg:classifiers":[
        {
            "category":"Real Estate",
            "subcategory":"Real Estate Agent",
            "type":"Services"
        }
    ],
    "sg:phone":"+44 20 8883 9090",
    "sg:postcode":"N2 9PJ",
    "sg:province":"Greater London",
    "wof:name":"Prime Locations",
    "wof:placetype":"venue"
},
  "geometry": {"coordinates":[-0.1639609933,51.5881004333],"type":"Point"}
}