{
  "type": "Feature",
  "properties": {
    "addr:full":"16 Main Street, Deans Livingston West Lothian EH54 8DF",
    "addr:housenumber":"16",
    "addr:postcode":"eh54 8df",
    "addr:street":"Main Street",
    "iso:country":"GB",
    "sg:address":"16 Main Street, Deans",
    "sg:city":"Livingston",
    "sg:classifiers":[
        {
            "category":"Food & Beverages",
            "subcategory":"Supermarket",
            "type":"Retail Goods"
        }
    ],
    "sg:postcode":"EH54 8DF",
    "sg:province":"West Lothian",
    "wof:name":"DEANS SUPERSTORE",
    "wof:placetype":"venue"
},
  "geometry": {"coordinates":[-3.567036,55.900883],"type":"Point"}
}