{
  "type": "Feature",
  "properties": {
    "iso:country":"GB",
    "sg:address":"1 Cranes Close",
    "sg:city":"Basildon",
    "sg:classifiers":[
        {
            "category":"Wholesale",
            "subcategory":"Furniture",
            "type":"Manufacturing & Wholesale Goods"
        }
    ],
    "sg:postcode":"SS14 3JB",
    "sg:province":"Essex",
    "sg:tags":[
        "shop",
        "fitting"
    ],
    "wof:name":"Integrated Storage Systems Ltd.",
    "wof:placetype":"venue"
},
  "geometry": {"coordinates":[0.493799001,51.5871086121],"type":"Point"}
}