{
  "type": "Feature",
  "properties": {
    "iso:country":"GB",
    "sg:address":"King Street, Belper",
    "sg:city":"Derby",
    "sg:classifiers":[
        {
            "category":"Personal",
            "subcategory":"Beauty Salon",
            "type":"Services"
        }
    ],
    "sg:phone":"+44 1773 823110",
    "sg:postcode":"DE1 3DZ",
    "sg:province":"Derbyshire",
    "sg:tags":[
        "unisex",
        "hairdresser"
    ],
    "wof:name":"Paul Mark Hair Fashions",
    "wof:placetype":"venue"
},
  "geometry": {"coordinates":[-1.4813870192,52.9280967712],"type":"Point"}
}