{
  "type": "Feature",
  "properties": {
    "iso:country":"GB",
    "sg:address":"Woodend Farm",
    "sg:city":"Kidderminster",
    "sg:classifiers":[
        {
            "category":"Farming",
            "subcategory":"Farm",
            "type":"Manufacturing & Wholesale Goods"
        }
    ],
    "sg:phone":"+44 1299 270689",
    "sg:postcode":"DY14 8LR",
    "sg:province":"Shropshire",
    "sg:tags":[
        "mixed",
        "crop"
    ],
    "wof:name":"I P Price",
    "wof:placetype":"venue"
},
  "geometry": {"coordinates":[-2.477194,52.382854],"type":"Point"}
}