{
  "type": "Feature",
  "properties": {
    "addr:full":"35 George Street Stranraer Dumfries and Galloway DG9 7RJ",
    "addr:housenumber":"35",
    "addr:postcode":"dg9 7rj",
    "addr:street":"George Street",
    "iso:country":"GB",
    "sg:address":"35 George Street",
    "sg:city":"Stranraer",
    "sg:classifiers":[
        {
            "category":"Shopping",
            "subcategory":"Clothing, Apparel, & Fashions",
            "type":"Retail Goods"
        }
    ],
    "sg:phone":"+44 1776 703938",
    "sg:postcode":"DG9 7RJ",
    "sg:province":"Dumfries and Galloway",
    "sg:tags":[
        "ladieswear"
    ],
    "wof:name":"Nowadays",
    "wof:placetype":"venue"
},
  "geometry": {"coordinates":[-5.027337,54.904598],"type":"Point"}
}