{
  "type": "Feature",
  "properties": {
    "addr:full":"14 Riverside Quay Haverfordwest Pembrokeshire SA61 2LJ",
    "addr:housenumber":"14",
    "addr:postcode":"sa61 2lj",
    "addr:street":"Riverside Quay",
    "iso:country":"GB",
    "sg:address":"14 Riverside Quay",
    "sg:city":"Haverfordwest",
    "sg:classifiers":[
        {
            "category":"Shopping",
            "subcategory":"Gifts & Souvenirs",
            "type":"Retail Goods"
        }
    ],
    "sg:phone":"+44 1437 764340",
    "sg:postcode":"SA61 2LJ",
    "sg:province":"Pembrokeshire",
    "sg:tags":[
        "poster",
        "card"
    ],
    "wof:name":"Clinton Cards",
    "wof:placetype":"venue"
},
  "geometry": {"coordinates":[-4.977350235,51.7987632751],"type":"Point"}
}