{
  "type": "Feature",
  "properties": {
    "addr:full":"Terraine, Pontsmill Par Cornwall PL24 2RR",
    "addr:postcode":"pl24 2rr",
    "iso:country":"GB",
    "sg:address":"Terraine, Pontsmill",
    "sg:city":"Par",
    "sg:classifiers":[
        {
            "category":"Shopping",
            "subcategory":"Pets & Pet Supplies",
            "type":"Retail Goods"
        }
    ],
    "sg:phone":"+44 1726 813975",
    "sg:postcode":"PL24 2RR",
    "sg:province":"Cornwall",
    "sg:tags":[
        "cemetery",
        "crematorium"
    ],
    "wof:name":"Pontsmill Pet Cemetery & Human Green Burial",
    "wof:placetype":"venue"
},
  "geometry": {"coordinates":[-4.7062888145,50.3717536926],"type":"Point"}
}