{
  "type": "Feature",
  "properties": {
    "addr:full":"106 Eaton Sq Westminster Greater London SW1W 9AD",
    "addr:housenumber":"106",
    "addr:postcode":"sw1w 9ad",
    "addr:street":"Eaton Sq",
    "iso:country":"GB",
    "sg:address":"106 Eaton Sq",
    "sg:city":"Westminster",
    "sg:classifiers":[
        {
            "category":"Government",
            "subcategory":"Embassy",
            "type":"Public Place"
        }
    ],
    "sg:phone":"+44 20 7235 4255",
    "sg:postcode":"SW1W 9AD",
    "sg:province":"Greater London",
    "sg:tags":[
        "consulate"
    ],
    "wof:name":"Bolivian Consulate",
    "wof:placetype":"venue"
},
  "geometry": {"coordinates":[-0.1541389972,51.4943504333],"type":"Point"}
}