{
  "type": "Feature",
  "properties": {
    "addr:full":"Marsh End, Lords Meadow Industrial Estate Crediton Devon EX17 1DN",
    "addr:postcode":"ex17 1dn",
    "addr:street":"Marsh End Lords Meadow Industrial Estate",
    "iso:country":"GB",
    "sg:address":"Marsh End, Lords Meadow Industrial Estate",
    "sg:city":"Crediton",
    "sg:classifiers":[
        {
            "category":"Manufacturing",
            "subcategory":"Metals",
            "type":"Manufacturing & Wholesale Goods"
        }
    ],
    "sg:phone":"+44 1363 773562",
    "sg:postcode":"EX17 1DN",
    "sg:province":"Devon",
    "sg:tags":[
        "work",
        "sheet"
    ],
    "wof:name":"Penton Coated Products Ltd.",
    "wof:placetype":"venue"
},
  "geometry": {"coordinates":[-3.637249,50.791576],"type":"Point"}
}