{
  "type": "Feature",
  "properties": {
    "iso:country":"GB",
    "sg:address":"Middlefield, Caulfield Road North, Cradlehall",
    "sg:city":"Inverness",
    "sg:classifiers":[
        {
            "category":"Building & Trades",
            "subcategory":"Construction",
            "type":"Services"
        }
    ],
    "sg:phone":"+44 1463 791524",
    "sg:postcode":"IV2 5NQ",
    "sg:province":"Highland",
    "sg:tags":[
        "builder"
    ],
    "wof:name":"David A West",
    "wof:placetype":"venue"
},
  "geometry": {"coordinates":[-4.161759,57.474716],"type":"Point"}
}