{
  "type": "Feature",
  "properties": {
    "addr:full":"Unit Ap4e, Millshaw Park Avenue Leeds West Yorkshire LS11 0LR",
    "addr:postcode":"ls11 0lr",
    "addr:street":"Park Avenue",
    "iso:country":"GB",
    "sg:address":"Unit Ap4e, Millshaw Park Avenue",
    "sg:city":"Leeds",
    "sg:classifiers":[
        {
            "category":"Shopping",
            "subcategory":"Stationery & Office Supplies",
            "type":"Retail Goods"
        }
    ],
    "sg:postcode":"LS11 0LR",
    "sg:province":"West Yorkshire",
    "sg:tags":[
        "packaging",
        "material"
    ],
    "wof:name":"Notem Ltd.",
    "wof:placetype":"venue"
},
  "geometry": {"coordinates":[-1.5792870522,53.7640190125],"type":"Point"}
}