{
  "type": "Feature",
  "properties": {
    "iso:country":"GB",
    "sg:address":"11 Brampton Avenue, Hall Grn",
    "sg:city":"Birmingham",
    "sg:classifiers":[
        {
            "category":"Building & Trades",
            "subcategory":"Construction",
            "type":"Services"
        }
    ],
    "sg:phone":"+44 121 745 3921",
    "sg:postcode":"B28 9LG",
    "sg:province":"West Midlands",
    "sg:tags":[
        "builder"
    ],
    "wof:name":"Farmac Contractors Ltd.",
    "wof:placetype":"venue"
},
  "geometry": {"coordinates":[-1.837075,52.426521],"type":"Point"}
}