{
  "type": "Feature",
  "properties": {
    "addr:full":"3 Wallace Parade, Goring Road Worthing West Sussex BN12 4AL",
    "addr:housenumber":"3",
    "addr:postcode":"bn12 4al",
    "addr:street":"Wallace Parade Goring Road",
    "iso:country":"GB",
    "sg:address":"3 Wallace Parade, Goring Road",
    "sg:city":"Worthing",
    "sg:classifiers":[
        {
            "category":"Personal",
            "subcategory":"Beauty Salon",
            "type":"Services"
        },
        {
            "category":"Personal",
            "subcategory":"Barber",
            "type":"Services"
        }
    ],
    "sg:phone":"+44 1903 505801",
    "sg:postcode":"BN12 4AL",
    "sg:province":"West Sussex",
    "sg:tags":[
        "men's",
        "lady",
        "hairdresser"
    ],
    "wof:name":"Anthony Michael",
    "wof:placetype":"venue"
},
  "geometry": {"coordinates":[-0.4009099901,50.8134117126],"type":"Point"}
}