{
  "type": "Feature",
  "properties": {
    "addr:full":"Haverfield Road, Mile End London Greater London E3 5BE",
    "addr:postcode":"e3 5be",
    "addr:street":"Haverfield Road",
    "iso:country":"GB",
    "sg:address":"Haverfield Road, Mile End",
    "sg:city":"London",
    "sg:classifiers":[
        {
            "category":"Community Center",
            "type":"Public Place"
        }
    ],
    "sg:phone":"+44 20 8980 0289",
    "sg:postcode":"E3 5BE",
    "sg:province":"Greater London",
    "sg:tags":[
        "recreation",
        "leisure",
        "centre"
    ],
    "wof:name":"Mile End Climbing Wall",
    "wof:placetype":"venue"
},
  "geometry": {"coordinates":[-0.0390399992,51.5284385681],"type":"Point"}
}