{
  "type": "Feature",
  "properties": {
    "addr:full":"Boardbay Central Office London Greater London SE1 1NX",
    "addr:postcode":"se1 1nx",
    "iso:country":"GB",
    "sg:address":"Boardbay Central Office",
    "sg:city":"London",
    "sg:classifiers":[
        {
            "category":"Organizations",
            "subcategory":"Non-profit Organization",
            "type":"Services"
        }
    ],
    "sg:phone":"+44 20 7089 9500",
    "sg:postcode":"SE1 1NX",
    "sg:province":"Greater London",
    "sg:tags":[
        "organisation",
        "voluntary",
        "charity"
    ],
    "wof:name":"Housing Services Agency Ltd.",
    "wof:placetype":"venue"
},
  "geometry": {"coordinates":[-0.08915,51.504108],"type":"Point"}
}