{
  "type": "Feature",
  "properties": {
    "iso:country":"GB",
    "sg:address":"26-32 Store Street",
    "sg:city":"Manchester",
    "sg:classifiers":[
        {
            "category":"Retail",
            "subcategory":"Auto Repair",
            "type":"Services"
        }
    ],
    "sg:phone":"+44 161 273 1058",
    "sg:postcode":"M1 2WD",
    "sg:province":"Greater Manchester",
    "sg:tags":[
        "modification",
        "garage"
    ],
    "wof:name":"Central Motor Services",
    "wof:placetype":"venue"
},
  "geometry": {"coordinates":[-2.225519,53.480335],"type":"Point"}
}