{
  "type": "Feature",
  "properties": {
    "addr:full":"Unit 6a Wansbeck Business Park, Rotary Parkway Ashington Northumberland NE63 8QW",
    "addr:housenumber":"unit 6a wansbeck business",
    "addr:postcode":"ne63 8qw",
    "addr:street":"Park Rotary Parkway;Northumberland",
    "iso:country":"GB",
    "sg:address":"Unit 6a Wansbeck Business Park, Rotary Parkway",
    "sg:city":"Ashington",
    "sg:classifiers":[
        {
            "category":"Shopping",
            "subcategory":"Gifts & Souvenirs",
            "type":"Retail Goods"
        }
    ],
    "sg:phone":"+44 1670 857989",
    "sg:postcode":"NE63 8QW",
    "sg:province":"Northumberland",
    "sg:tags":[
        "giftware"
    ],
    "wof:name":"Gate Gallery Ltd.",
    "wof:placetype":"venue"
},
  "geometry": {"coordinates":[-1.5826400518,55.1876106262],"type":"Point"}
}