{
  "type": "Feature",
  "properties": {
    "addr:full":"Prospect Terrace, Kibblesworth Gateshead Tyne and Wear NE11 0YD",
    "addr:postcode":"ne11 0yd",
    "addr:street":"Prospect Terrace Kibblesworth",
    "iso:country":"GB",
    "sg:address":"Prospect Terrace, Kibblesworth",
    "sg:city":"Gateshead",
    "sg:classifiers":[
        {
            "category":"Place Of Worship",
            "type":"Public Place"
        }
    ],
    "sg:phone":"+44 191 420 2820",
    "sg:postcode":"NE11 0YD",
    "sg:province":"Tyne and Wear",
    "wof:name":"Kibblesworth Methodist Church",
    "wof:placetype":"venue"
},
  "geometry": {"coordinates":[-1.62051,54.905289],"type":"Point"}
}