{
  "type": "Feature",
  "properties": {
    "iso:country":"GB",
    "sg:address":"Unit 4 Hollybrook Way, Littleover",
    "sg:city":"Derby",
    "sg:classifiers":[
        {
            "category":"Fast Food",
            "type":"Food & Drink"
        },
        {
            "category":"Food & Beverages",
            "subcategory":"Meat & Fish",
            "type":"Retail Goods"
        }
    ],
    "sg:phone":"+44 1332 512600",
    "sg:postcode":"DE23 3TU",
    "sg:province":"Derbyshire",
    "sg:tags":[
        "chip",
        "away",
        "take"
    ],
    "wof:name":"Heatherton Fish Bar",
    "wof:placetype":"venue"
},
  "geometry": {"coordinates":[-1.5268089771,52.891960144],"type":"Point"}
}