{
  "type": "Feature",
  "properties": {
    "addr:full":"31a George Street Tamworth Staffordshire B79 7LJ",
    "addr:housenumber":"31a",
    "addr:postcode":"b79 7lj",
    "addr:street":"George Street",
    "iso:country":"GB",
    "sg:address":"31a George Street",
    "sg:city":"Tamworth",
    "sg:classifiers":[
        {
            "category":"Shopping",
            "subcategory":"Department Store",
            "type":"Retail Goods"
        },
        {
            "category":"Building & Trades",
            "subcategory":"Plumbing",
            "type":"Services"
        }
    ],
    "sg:phone":"+44 1827 310006",
    "sg:postcode":"B79 7LJ",
    "sg:province":"Staffordshire",
    "sg:tags":[
        "central",
        "heating"
    ],
    "wof:name":"R A & C R Brown",
    "wof:placetype":"venue"
},
  "geometry": {"coordinates":[-1.693874,52.63303],"type":"Point"}
}