{
  "type": "Feature",
  "properties": {
    "iso:country":"GB",
    "sg:address":"Church Street, Tempsford",
    "sg:city":"Sandy",
    "sg:classifiers":[
        {
            "category":"Transit Center",
            "subcategory":"Passenger",
            "type":"Transportation"
        }
    ],
    "sg:phone":"+44 1767 640227",
    "sg:postcode":"SG19 2AN",
    "sg:province":"Bedfordshire",
    "sg:tags":[
        "boarding",
        "kennel",
        "catteries"
    ],
    "wof:name":"Ouseland Cattery",
    "wof:placetype":"venue"
},
  "geometry": {"coordinates":[-0.296319,52.170605],"type":"Point"}
}