{
  "type": "Feature",
  "properties": {
    "iso:country":"GB",
    "sg:address":"4 & 6 Abergarw Road",
    "sg:city":"Bridgend",
    "sg:classifiers":[
        {
            "category":"Government",
            "subcategory":"Post Office",
            "type":"Public Place"
        }
    ],
    "sg:phone":"+44 1656 720275",
    "sg:postcode":"CF32 9LF",
    "sg:province":"Bridgend",
    "wof:name":"Brynmenyn Sub Post Office",
    "wof:placetype":"venue"
},
  "geometry": {"coordinates":[-3.577988,51.551804],"type":"Point"}
}