{
  "type": "Feature",
  "properties": {
    "addr:full":"Upper Whiston Farm, Upper Whiston Rotherham South Yorkshire S60 4NG",
    "addr:postcode":"s60 4ng",
    "addr:street":"Upper Whiston Farm Upper",
    "iso:country":"GB",
    "sg:address":"Upper Whiston Farm, Upper Whiston",
    "sg:city":"Rotherham",
    "sg:classifiers":[
        {
            "category":"Farming",
            "subcategory":"Livestock Farm",
            "type":"Manufacturing & Wholesale Goods"
        }
    ],
    "sg:postcode":"S60 4NG",
    "sg:province":"South Yorkshire",
    "sg:tags":[
        "others"
    ],
    "wof:name":"R & A Wyles",
    "wof:placetype":"venue"
},
  "geometry": {"coordinates":[-1.3096840382,53.4077415466],"type":"Point"}
}