{
  "type": "Feature",
  "properties": {
    "addr:full":"135 Barkers Butts Lane Coventry Warwickshire CV6 1EB",
    "addr:housenumber":"135",
    "addr:postcode":"cv6 1eb",
    "addr:street":"Barkers Butts Lane",
    "iso:country":"GB",
    "sg:address":"135 Barkers Butts Lane",
    "sg:city":"Coventry",
    "sg:classifiers":[
        {
            "category":"Retail",
            "subcategory":"Auto Repair",
            "type":"Services"
        }
    ],
    "sg:phone":"+44 24 7659 3646",
    "sg:postcode":"CV6 1EB",
    "sg:province":"Warwickshire",
    "sg:tags":[
        "modification",
        "garage"
    ],
    "wof:name":"Ledbrooks Garage",
    "wof:placetype":"venue"
},
  "geometry": {"coordinates":[-1.5294029713,52.4189338684],"type":"Point"}
}