{
  "type": "Feature",
  "properties": {
    "iso:country":"GB",
    "sg:address":"92 Station Road, Woburn Sands",
    "sg:city":"Milton Keynes",
    "sg:classifiers":[
        {
            "category":"Professional",
            "subcategory":"Art Services",
            "type":"Services"
        },
        {
            "category":"Shopping",
            "subcategory":"Crafts & Fabrics",
            "type":"Retail Goods"
        }
    ],
    "sg:phone":"+44 1908 586900",
    "sg:postcode":"MK17 8SB",
    "sg:province":"Bedfordshire",
    "sg:tags":[
        "interior",
        "material",
        "designer"
    ],
    "wof:name":"La Maison",
    "wof:placetype":"venue"
},
  "geometry": {"coordinates":[-0.6504899859,52.0164871216],"type":"Point"}
}