{
  "type": "Feature",
  "properties": {
    "iso:country":"GB",
    "sg:address":"7 Grammar School Road",
    "sg:city":"Warrington",
    "sg:classifiers":[
        {
            "category":"Health Services",
            "subcategory":"Health Practitioner",
            "type":"Services"
        }
    ],
    "sg:phone":"+44 1925 635662",
    "sg:postcode":"WA4 1JN",
    "sg:province":"Cheshire",
    "sg:tags":[
        "hypnotherapists"
    ],
    "wof:name":"Communicate",
    "wof:placetype":"venue"
},
  "geometry": {"coordinates":[-2.5635919571,53.3801727295],"type":"Point"}
}