{
  "type": "Feature",
  "properties": {
    "addr:full":"15 Station Street Cockermouth Cumbria CA13 9LE",
    "addr:housenumber":"15",
    "addr:postcode":"ca13 9le",
    "addr:street":"Station Street",
    "iso:country":"GB",
    "sg:address":"15 Station Street",
    "sg:city":"Cockermouth",
    "sg:classifiers":[
        {
            "category":"Shopping",
            "subcategory":"Books",
            "type":"Retail Goods"
        }
    ],
    "sg:phone":"+44 1900 827702",
    "sg:postcode":"CA13 9LE",
    "sg:province":"Cumbria",
    "sg:tags":[
        "bookseller"
    ],
    "wof:name":"Kings Church",
    "wof:placetype":"venue"
},
  "geometry": {"coordinates":[-3.3641560078,54.6631813049],"type":"Point"}
}