{
  "type": "Feature",
  "properties": {
    "addr:full":"Bath Spa Railway Station, Dorchester Street Bath Bath and North East Somerset BA1 1SU",
    "addr:postcode":"ba1 1su",
    "addr:street":"Dorchester Street",
    "iso:country":"GB",
    "sg:address":"Bath Spa Railway Station, Dorchester Street",
    "sg:city":"Bath",
    "sg:classifiers":[
        {
            "category":"Retail",
            "subcategory":"Auto Rental",
            "type":"Services"
        }
    ],
    "sg:phone":"+44 1225 442911",
    "sg:postcode":"BA1 1SU",
    "sg:province":"Bath and North East Somerset",
    "sg:tags":[
        "car"
    ],
    "wof:name":"Hertz Rent A Car",
    "wof:placetype":"venue"
},
  "geometry": {"coordinates":[-2.361166954,51.3850708008],"type":"Point"}
}