{
  "type": "Feature",
  "properties": {
    "iso:country":"GB",
    "sg:address":"115 Alpha Road",
    "sg:city":"London",
    "sg:classifiers":[
        {
            "category":"Social Services",
            "subcategory":"Adult Care",
            "type":"Services"
        },
        {
            "category":"Social Services",
            "subcategory":"Retirement Home",
            "type":"Services"
        }
    ],
    "sg:phone":"+44 20 8524 7191",
    "sg:postcode":"E4 6TE",
    "sg:province":"Greater London",
    "sg:tags":[
        "housing",
        "sheltered",
        "accommodation"
    ],
    "wof:name":"Winters Court",
    "wof:placetype":"venue"
},
  "geometry": {"coordinates":[-0.0120400004,51.6203117371],"type":"Point"}
}