{
  "type": "Feature",
  "properties": {
    "addr:full":"51 Bowling Street Mansfield Nottinghamshire NG18 2LH",
    "addr:housenumber":"51",
    "addr:postcode":"ng18 2lh",
    "addr:street":"Bowling Street",
    "iso:country":"GB",
    "sg:address":"51 Bowling Street",
    "sg:city":"Mansfield",
    "sg:classifiers":[
        {
            "category":"Shopping",
            "subcategory":"Computers & Home Electronics",
            "type":"Retail Goods"
        },
        {
            "category":"Professional",
            "subcategory":"Computer Services",
            "type":"Services"
        }
    ],
    "sg:postcode":"NG18 2LH",
    "sg:province":"Nottinghamshire",
    "sg:tags":[
        "software",
        "sales",
        "system"
    ],
    "wof:name":"HISTORICAL 8-BIT SOFTWARE",
    "wof:placetype":"venue"
},
  "geometry": {"coordinates":[-1.186034,53.142597],"type":"Point"}
}