{
  "type": "Feature",
  "properties": {
    "iso:country":"GB",
    "sg:address":"50 Chelmorton Rd, Great Barr",
    "sg:city":"Birmingham",
    "sg:classifiers":[
        {
            "category":"Real Estate",
            "subcategory":"Surveying",
            "type":"Services"
        }
    ],
    "sg:phone":"+44 121 693 3063",
    "sg:postcode":"B42 2QT",
    "sg:province":"West Midlands",
    "sg:tags":[
        "surveyor",
        "quantity"
    ],
    "wof:name":"D.T Jarvis",
    "wof:placetype":"venue"
},
  "geometry": {"coordinates":[-1.9058519602,52.5390968323],"type":"Point"}
}