{
  "type": "Feature",
  "properties": {
    "iso:country":"GB",
    "sg:address":"Gartshore Road, Kirkintilloch",
    "sg:city":"Glasgow",
    "sg:classifiers":[
        {
            "category":"Education",
            "subcategory":"School",
            "type":"Public Place"
        },
        {
            "category":"Government",
            "subcategory":"Office",
            "type":"Public Place"
        }
    ],
    "sg:phone":"+44 141 776 1598",
    "sg:postcode":"G66 3TH",
    "sg:province":"East Dunbartonshire",
    "sg:tags":[
        "local",
        "authority"
    ],
    "wof:name":"St. Agatha's Primary School",
    "wof:placetype":"venue"
},
  "geometry": {"coordinates":[-4.1537089348,55.9334411621],"type":"Point"}
}