{
  "type": "Feature",
  "properties": {
    "iso:country":"GB",
    "sg:address":"Waterloo Road",
    "sg:city":"Poole",
    "sg:classifiers":[
        {
            "category":"Wholesale",
            "subcategory":"Machinery & Supplies",
            "type":"Manufacturing & Wholesale Goods"
        }
    ],
    "sg:phone":"+44 1202 627500",
    "sg:postcode":"BH17 7LB",
    "sg:province":"Dorset",
    "sg:tags":[
        "system",
        "hydraulic"
    ],
    "wof:name":"David Brown Hydraulics",
    "wof:placetype":"venue"
},
  "geometry": {"coordinates":[-1.983321,50.749809],"type":"Point"}
}