{
  "type": "Feature",
  "properties": {
    "iso:country":"GB",
    "sg:address":"Selsey Arms, Coolham",
    "sg:city":"Horsham",
    "sg:classifiers":[
        {
            "category":"Bars & Pubs",
            "type":"Food & Drink"
        }
    ],
    "sg:phone":"+44 1403 741537",
    "sg:postcode":"RH13 8QJ",
    "sg:province":"West Sussex",
    "sg:tags":[
        "pubs",
        "inn"
    ],
    "wof:name":"The Selsey Arms",
    "wof:placetype":"venue"
},
  "geometry": {"coordinates":[-0.40319,50.993069],"type":"Point"}
}