{
  "type": "Feature",
  "properties": {
    "iso:country":"GB",
    "sg:address":"10 High Street, Ynysybwl",
    "sg:city":"Pontypridd",
    "sg:classifiers":[
        {
            "category":"Cafe",
            "type":"Food & Drink"
        }
    ],
    "sg:phone":"+44 1443 403134",
    "sg:postcode":"CF37 3EE",
    "sg:province":"Caerphilly",
    "sg:tags":[
        "tea",
        "snack",
        "bar",
        "room"
    ],
    "wof:name":"THE DAIRY SHOP",
    "wof:placetype":"venue"
},
  "geometry": {"coordinates":[-3.359046,51.63768],"type":"Point"}
}