{
  "type": "Feature",
  "properties": {
    "addr:full":"290 Stonelaw Road Glasgow Glasgow City G73 3RP",
    "addr:housenumber":"290",
    "addr:postcode":"g73 3rp",
    "addr:street":"Stonelaw Road",
    "iso:country":"GB",
    "sg:address":"290 Stonelaw Road",
    "sg:city":"Glasgow",
    "sg:classifiers":[
        {
            "category":"Insurance",
            "subcategory":"Insurance Agent",
            "type":"Services"
        },
        {
            "category":"Banks & Credit Unions",
            "subcategory":"Financial Services",
            "type":"Services"
        }
    ],
    "sg:phone":"+44 141 647 2967",
    "sg:postcode":"G73 3RP",
    "sg:province":"Glasgow City",
    "sg:tags":[
        "broker"
    ],
    "wof:name":"Neill & Co Financial Services Ltd",
    "wof:placetype":"venue"
},
  "geometry": {"coordinates":[-4.201759,55.81765],"type":"Point"}
}