{
  "type": "Feature",
  "properties": {
    "addr:full":"Lee Farm Nursery, Botley Road Chesham Buckinghamshire HP5 1XU",
    "addr:postcode":"hp5 1xu",
    "addr:street":"Lee;Botley Road",
    "iso:country":"GB",
    "sg:address":"Lee Farm Nursery, Botley Road",
    "sg:city":"Chesham",
    "sg:classifiers":[
        {
            "category":"Wholesale",
            "subcategory":"Fruits & Vegetables",
            "type":"Manufacturing & Wholesale Goods"
        }
    ],
    "sg:postcode":"HP5 1XU",
    "sg:province":"Buckinghamshire",
    "wof:name":"Richard Birch",
    "wof:placetype":"venue"
},
  "geometry": {"coordinates":[-0.609333,51.710537],"type":"Point"}
}