{
  "type": "Feature",
  "properties": {
    "addr:full":"Block 3 Unit 9, Cannock Chase Enterprise Centre, Walkers Rise Cannock Staffordshire WS12 5QU",
    "addr:housenumber":"unit 9",
    "addr:postcode":"ws12 5qu",
    "addr:street":"Walkers Rise",
    "iso:country":"GB",
    "sg:address":"Block 3 Unit 9, Cannock Chase Enterprise Centre, Walkers Rise",
    "sg:city":"Cannock",
    "sg:classifiers":[
        {
            "category":"Home & Garden",
            "subcategory":"Home Furnishings",
            "type":"Retail Goods"
        }
    ],
    "sg:phone":"+44 1543 451001",
    "sg:postcode":"WS12 5QU",
    "sg:province":"Staffordshire",
    "sg:tags":[
        "racking",
        "shelving",
        "diy"
    ],
    "wof:name":"Plandeck Ltd.",
    "wof:placetype":"venue"
},
  "geometry": {"coordinates":[-1.98951,52.724998],"type":"Point"}
}