{
  "type": "Feature",
  "properties": {
    "addr:full":"21 East Street, Oadby Leicester Leicestershire LE2 5AF",
    "addr:housenumber":"21",
    "addr:postcode":"le2 5af",
    "addr:street":"East Street",
    "iso:country":"GB",
    "sg:address":"21 East Street, Oadby",
    "sg:city":"Leicester",
    "sg:classifiers":[
        {
            "category":"Education",
            "subcategory":"School",
            "type":"Public Place"
        },
        {
            "category":"Education",
            "subcategory":"University",
            "type":"Public Place"
        }
    ],
    "sg:phone":"+44 116 271 5958",
    "sg:postcode":"LE2 5AF",
    "sg:province":"Leicestershire",
    "sg:tags":[
        "private",
        "tuition"
    ],
    "wof:name":"Leicester Tutorial",
    "wof:placetype":"venue"
},
  "geometry": {"coordinates":[-1.0834120512,52.6008453369],"type":"Point"}
}