{
  "type": "Feature",
  "properties": {
    "addr:full":"34 Corbets Tey Rd Upminster Essex RM14 2AD",
    "addr:housenumber":"34",
    "addr:postcode":"rm14 2ad",
    "addr:street":"Corbets Tey Rd",
    "iso:country":"GB",
    "sg:address":"34 Corbets Tey Rd",
    "sg:city":"Upminster",
    "sg:classifiers":[
        {
            "category":"Shopping",
            "subcategory":"Clothing, Apparel, & Fashions",
            "type":"Retail Goods"
        }
    ],
    "sg:phone":"+44 1708 223119",
    "sg:postcode":"RM14 2AD",
    "sg:province":"Essex",
    "sg:tags":[
        "shop"
    ],
    "wof:name":"Emporium The",
    "wof:placetype":"venue"
},
  "geometry": {"coordinates":[0.2478629947,51.5541534424],"type":"Point"}
}