{
  "type": "Feature",
  "properties": {
    "iso:country":"GB",
    "sg:address":"32a Herbert Street",
    "sg:city":"Loughborough",
    "sg:classifiers":[
        {
            "category":"Manufacturing",
            "subcategory":"Wood Products",
            "type":"Manufacturing & Wholesale Goods"
        },
        {
            "category":"Building & Trades",
            "subcategory":"Construction",
            "type":"Services"
        }
    ],
    "sg:phone":"+44 1509 262447",
    "sg:postcode":"LE11 1NX",
    "sg:province":"Leicestershire",
    "sg:tags":[
        "joinery",
        "manufacturer"
    ],
    "wof:name":"P & R Hunt",
    "wof:placetype":"venue"
},
  "geometry": {"coordinates":[-1.2047120333,52.7767028809],"type":"Point"}
}