{
  "type": "Feature",
  "properties": {
    "iso:country":"GB",
    "sg:address":"6 Yeaman Pl",
    "sg:city":"Edinburgh",
    "sg:classifiers":[
        {
            "category":"Farming",
            "subcategory":"Fish & Marine Products",
            "type":"Manufacturing & Wholesale Goods"
        }
    ],
    "sg:postcode":"EH11 1BX",
    "sg:province":"City of Edinburgh",
    "sg:tags":[
        "fishmonger"
    ],
    "wof:name":"Toulin,B,",
    "wof:placetype":"venue"
},
  "geometry": {"coordinates":[-3.219381,55.939808],"type":"Point"}
}