{
  "type": "Feature",
  "properties": {
    "addr:full":"12 Market Street, Clay Cross Chesterfield Derbyshire S45 9JE",
    "addr:housenumber":"12",
    "addr:postcode":"s45 9je",
    "addr:street":"Market Street",
    "iso:country":"GB",
    "sg:address":"12 Market Street, Clay Cross",
    "sg:city":"Chesterfield",
    "sg:classifiers":[
        {
            "category":"Bars & Pubs",
            "type":"Food & Drink"
        }
    ],
    "sg:phone":"+44 1246 861075",
    "sg:postcode":"S45 9JE",
    "sg:province":"Derbyshire",
    "sg:tags":[
        "pubs",
        "inn"
    ],
    "wof:name":"Albion Pub Management",
    "wof:placetype":"venue"
},
  "geometry": {"coordinates":[-1.4153319597,53.1668052673],"type":"Point"}
}