{
  "type": "Feature",
  "properties": {
    "iso:country":"GB",
    "sg:address":"8-16 Princes Square",
    "sg:city":"London",
    "sg:classifiers":[
        {
            "category":"Travel",
            "subcategory":"Hotels & Motels",
            "type":"Entertainment"
        }
    ],
    "sg:phone":"+44 20 7727 8621",
    "sg:postcode":"W2 4NT",
    "sg:province":"Greater London",
    "wof:name":"Bayswater Inns Ltd.",
    "wof:placetype":"venue"
},
  "geometry": {"coordinates":[-0.192437,51.512669],"type":"Point"}
}