{
  "type": "Feature",
  "properties": {
    "addr:full":"16 Matilda Street Sheffield South Yorkshire S1 4QD",
    "addr:housenumber":"16",
    "addr:postcode":"s1 4qd",
    "addr:street":"Matilda Street",
    "iso:country":"GB",
    "sg:address":"16 Matilda Street",
    "sg:city":"Sheffield",
    "sg:classifiers":[
        {
            "category":"Education",
            "subcategory":"Special Training",
            "type":"Public Place"
        }
    ],
    "sg:phone":"+44 114 281 7666",
    "sg:postcode":"S1 4QD",
    "sg:province":"South Yorkshire",
    "sg:tags":[
        "product",
        "centre"
    ],
    "wof:name":"Roger Worth Training Ltd.",
    "wof:placetype":"venue"
},
  "geometry": {"coordinates":[-1.471869,53.376736],"type":"Point"}
}