{
  "type": "Feature",
  "properties": {
    "iso:country":"GB",
    "sg:address":"258 Main Rd",
    "sg:city":"Emsworth",
    "sg:classifiers":[
        {
            "category":"Shopping",
            "subcategory":"Musical Instruments",
            "type":"Retail Goods"
        }
    ],
    "sg:phone":"+44 1243 379330",
    "sg:postcode":"PO10 8JL",
    "sg:province":"Hampshire",
    "sg:tags":[
        "music",
        "sheet"
    ],
    "wof:name":"Watershed Instrument Rental",
    "wof:placetype":"venue"
},
  "geometry": {"coordinates":[-0.911676,50.845112],"type":"Point"}
}