{
  "type": "Feature",
  "properties": {
    "addr:full":"Lightmoor, Pilford Court, Leckhampton Cheltenham Gloucestershire GL53 9BB",
    "addr:postcode":"gl53 9bb",
    "iso:country":"GB",
    "sg:address":"Lightmoor, Pilford Court, Leckhampton",
    "sg:city":"Cheltenham",
    "sg:classifiers":[
        {
            "category":"Real Estate",
            "subcategory":"Developer",
            "type":"Services"
        },
        {
            "category":"Building & Trades",
            "subcategory":"Construction",
            "type":"Services"
        }
    ],
    "sg:phone":"+44 1242 241520",
    "sg:postcode":"GL53 9BB",
    "sg:province":"Gloucestershire",
    "sg:tags":[
        "residential",
        "builder",
        "property"
    ],
    "wof:name":"Lightmoor Homes Ltd",
    "wof:placetype":"venue"
},
  "geometry": {"coordinates":[-2.075483,51.871468],"type":"Point"}
}