{
  "type": "Feature",
  "properties": {
    "addr:full":"12 Queen Square Brighton East Sussex BN1 3FD",
    "addr:housenumber":"12",
    "addr:postcode":"bn1 3fd",
    "addr:street":"Queen Square",
    "iso:country":"GB",
    "sg:address":"12 Queen Square",
    "sg:city":"Brighton",
    "sg:classifiers":[
        {
            "category":"Professional",
            "subcategory":"Business Services",
            "type":"Services"
        },
        {
            "category":"Organizations",
            "subcategory":"Non-profit Organization",
            "type":"Services"
        }
    ],
    "sg:phone":"+44 1273 777688",
    "sg:postcode":"BN1 3FD",
    "sg:province":"East Sussex",
    "sg:tags":[
        "voluntary",
        "organisation",
        "agent",
        "export",
        "import",
        "charity"
    ],
    "wof:name":"Viva-Vegetarians International Voice for Animals",
    "wof:placetype":"venue"
},
  "geometry": {"coordinates":[-0.144141,50.824436],"type":"Point"}
}