{
  "type": "Feature",
  "properties": {
    "iso:country":"GB",
    "sg:address":"C/o Neighbourhood Offices, 27 Brockburn Road, Pollok",
    "sg:city":"Glasgow",
    "sg:classifiers":[
        {
            "category":"Organizations",
            "subcategory":"Non-profit Organization",
            "type":"Services"
        }
    ],
    "sg:phone":"+44 141 882 6245",
    "sg:postcode":"G53 5BQ",
    "sg:province":"East Renfrewshire",
    "sg:tags":[
        "charitable",
        "organisation",
        "voluntary",
        "charity"
    ],
    "wof:name":"Pollok Voluntary Care",
    "wof:placetype":"venue"
},
  "geometry": {"coordinates":[-4.3471198082,55.8258018494],"type":"Point"}
}