{
  "type": "Feature",
  "properties": {
    "addr:full":"87-91 Newland Street Witham Essex CM8 1AD",
    "addr:housenumber":"87-91",
    "addr:postcode":"cm8 1ad",
    "addr:street":"Newland Street",
    "iso:country":"GB",
    "sg:address":"87-91 Newland Street",
    "sg:city":"Witham",
    "sg:classifiers":[
        {
            "category":"Professional",
            "subcategory":"Lawyer & Legal Services",
            "type":"Services"
        }
    ],
    "sg:phone":"+44 1376 520655",
    "sg:postcode":"CM8 1AD",
    "sg:province":"Essex",
    "sg:tags":[
        "solicitor"
    ],
    "wof:name":"C Hayward & G Poulter & J Flynn",
    "wof:placetype":"venue"
},
  "geometry": {"coordinates":[0.6388149858,51.7985687256],"type":"Point"}
}