{
  "type": "Feature",
  "properties": {
    "iso:country":"GB",
    "sg:address":"Railton Avenue",
    "sg:city":"Crewe",
    "sg:classifiers":[
        {
            "category":"Community Center",
            "subcategory":"Youth",
            "type":"Public Place"
        },
        {
            "category":"Government",
            "subcategory":"Office",
            "type":"Public Place"
        }
    ],
    "sg:phone":"+44 1270 255901",
    "sg:postcode":"CW1 3QH",
    "sg:province":"Cheshire",
    "sg:tags":[
        "organisation",
        "local",
        "centre"
    ],
    "wof:name":"Cheshire County Council",
    "wof:placetype":"venue"
},
  "geometry": {"coordinates":[-2.461852,53.110432],"type":"Point"}
}