{
  "type": "Feature",
  "properties": {
    "addr:full":"45 Caldercroft Elland West Yorkshire HX5 9AY",
    "addr:housenumber":"45",
    "addr:postcode":"hx5 9ay",
    "addr:street":"Caldercroft Elland West",
    "iso:country":"GB",
    "sg:address":"45 Caldercroft",
    "sg:city":"Elland",
    "sg:classifiers":[
        {
            "category":"Building & Trades",
            "subcategory":"Construction",
            "type":"Services"
        }
    ],
    "sg:postcode":"HX5 9AY",
    "sg:province":"West Yorkshire",
    "sg:tags":[
        "decorator",
        "painter"
    ],
    "wof:name":"John M Jackson",
    "wof:placetype":"venue"
},
  "geometry": {"coordinates":[-1.8269319534,53.6827011108],"type":"Point"}
}