{
  "type": "Feature",
  "properties": {
    "iso:country":"GB",
    "sg:address":"65 Kirkleatham Lane",
    "sg:city":"Redcar",
    "sg:classifiers":[
        {
            "category":"Building & Trades",
            "subcategory":"Landscaping Services",
            "type":"Services"
        }
    ],
    "sg:postcode":"TS10 1NT",
    "sg:province":"North Yorkshire",
    "sg:tags":[
        "landscape",
        "contractor"
    ],
    "wof:name":"Barkers Garden Services",
    "wof:placetype":"venue"
},
  "geometry": {"coordinates":[-1.0833469629,54.6096878052],"type":"Point"}
}