{
  "type": "Feature",
  "properties": {
    "iso:country":"GB",
    "sg:address":"114 Mount Pleasant",
    "sg:city":"Liverpool",
    "sg:classifiers":[
        {
            "category":"Organizations",
            "subcategory":"Professional Association",
            "type":"Services"
        }
    ],
    "sg:phone":"+44 151 709 9125",
    "sg:postcode":"L3 5SR",
    "sg:province":"Merseyside",
    "sg:tags":[
        "institute"
    ],
    "wof:name":"The Liverpool Medical Institution",
    "wof:placetype":"venue"
},
  "geometry": {"coordinates":[-2.9691889286,53.4033966064],"type":"Point"}
}