{
  "type": "Feature",
  "properties": {
    "addr:full":"122-124 Dock Street Fleetwood Lancashire FY7 6JL",
    "addr:housenumber":"122-124",
    "addr:postcode":"fy7 6jl",
    "addr:street":"Dock Street",
    "iso:country":"GB",
    "sg:address":"122-124 Dock Street",
    "sg:city":"Fleetwood",
    "sg:classifiers":[
        {
            "category":"Bars & Pubs",
            "type":"Food & Drink"
        }
    ],
    "sg:phone":"+44 1253 773330",
    "sg:postcode":"FY7 6JL",
    "sg:province":"Lancashire",
    "sg:tags":[
        "pubs",
        "inn"
    ],
    "wof:name":"The Cove",
    "wof:placetype":"venue"
},
  "geometry": {"coordinates":[-3.009482,53.921894],"type":"Point"}
}