{
  "type": "Feature",
  "properties": {
    "addr:full":"Suite 4a The Steam Mill, Steam Mill Street Chester Cheshire CH3 5AN",
    "addr:housenumber":"suite 4a",
    "addr:postcode":"ch3 5an",
    "addr:street":"The;Steam Mill Street",
    "iso:country":"GB",
    "sg:address":"Suite 4a The Steam Mill, Steam Mill Street",
    "sg:city":"Chester",
    "sg:classifiers":[
        {
            "category":"Professional",
            "subcategory":"Employment Agencies",
            "type":"Services"
        }
    ],
    "sg:postcode":"CH3 5AN",
    "sg:province":"Cheshire",
    "sg:tags":[
        "consultant"
    ],
    "wof:name":"Ian Goodall",
    "wof:placetype":"venue"
},
  "geometry": {"coordinates":[-2.8802750111,53.1931266785],"type":"Point"}
}