{
  "type": "Feature",
  "properties": {
    "addr:full":"5 St Marys Grn Newcastle-upon-tyne Durham NE16 4DN",
    "addr:housenumber":"5",
    "addr:postcode":"ne16 4dn",
    "addr:street":"St Marys Grn",
    "iso:country":"GB",
    "sg:address":"5 St Marys Grn",
    "sg:city":"Newcastle-upon-tyne",
    "sg:classifiers":[
        {
            "category":"Food & Beverages",
            "subcategory":"Fruits & Vegetables",
            "type":"Retail Goods"
        }
    ],
    "sg:phone":"+44 191 420 0377",
    "sg:postcode":"NE16 4DN",
    "sg:province":"Durham",
    "sg:tags":[
        "greengrocer"
    ],
    "wof:name":"Walkers Of Whickham",
    "wof:placetype":"venue"
},
  "geometry": {"coordinates":[-1.6768889427,54.9460334778],"type":"Point"}
}