{
  "type": "Feature",
  "properties": {
    "addr:full":"25 Bradford Rd Dewsbury West Yorkshire WF13 2DU",
    "addr:housenumber":"25",
    "addr:postcode":"wf13 2du",
    "addr:street":"Bradford Rd",
    "iso:country":"GB",
    "sg:address":"25 Bradford Rd",
    "sg:city":"Dewsbury",
    "sg:classifiers":[
        {
            "category":"Shopping",
            "subcategory":"Clothing, Apparel, & Fashions",
            "type":"Retail Goods"
        }
    ],
    "sg:phone":"+44 1924 439060",
    "sg:postcode":"WF13 2DU",
    "sg:province":"West Yorkshire",
    "sg:tags":[
        "workwear",
        "protective"
    ],
    "wof:name":"Kingsley Supplies",
    "wof:placetype":"venue"
},
  "geometry": {"coordinates":[-1.63164,53.69561],"type":"Point"}
}