{
  "type": "Feature",
  "properties": {
    "addr:full":"7 Broad Street Deal Kent CT14 6ER",
    "addr:housenumber":"7",
    "addr:postcode":"ct14 6er",
    "addr:street":"Broad Street Deal",
    "iso:country":"GB",
    "sg:address":"7 Broad Street",
    "sg:city":"Deal",
    "sg:classifiers":[
        {
            "category":"Shopping",
            "subcategory":"Books",
            "type":"Retail Goods"
        }
    ],
    "sg:phone":"+44 1304 366084",
    "sg:postcode":"CT14 6ER",
    "sg:province":"Kent",
    "sg:tags":[
        "bookseller",
        "retailer"
    ],
    "wof:name":"The Deal Bookshop",
    "wof:placetype":"venue"
},
  "geometry": {"coordinates":[1.4039230347,51.2232017517],"type":"Point"}
}