{
  "type": "Feature",
  "properties": {
    "iso:country":"GB",
    "sg:address":"1-19 Romford Rd, Stratford",
    "sg:city":"Stratford",
    "sg:classifiers":[
        {
            "category":"Government",
            "subcategory":"Office",
            "type":"Public Place"
        }
    ],
    "sg:phone":"+44 20 8534 6601",
    "sg:postcode":"E15 4LJ",
    "sg:province":"Greater London",
    "sg:tags":[
        "central"
    ],
    "wof:name":"Crown Prosecution Service",
    "wof:placetype":"venue"
},
  "geometry": {"coordinates":[0.006266,51.542381],"type":"Point"}
}