{
  "type": "Feature",
  "properties": {
    "addr:full":"124 Elm Park Mansions, Park Walk London Greater London SW10 0AR",
    "addr:housenumber":"124",
    "addr:postcode":"sw10 0ar",
    "addr:street":"Elm Park Mansions Park Walk",
    "iso:country":"GB",
    "sg:address":"124 Elm Park Mansions, Park Walk",
    "sg:city":"London",
    "sg:classifiers":[
        {
            "category":"Communications",
            "subcategory":"Film & Video Production",
            "type":"Services"
        },
        {
            "category":"Professional",
            "subcategory":"Art Services",
            "type":"Services"
        }
    ],
    "sg:phone":"+44 20 7352 6890",
    "sg:postcode":"SW10 0AR",
    "sg:province":"Greater London",
    "sg:tags":[
        "illustrator",
        "artist"
    ],
    "wof:name":"Associated Freelance Artists Ltd.",
    "wof:placetype":"venue"
},
  "geometry": {"coordinates":[-0.1793760061,51.4846839905],"type":"Point"}
}