{
  "type": "Feature",
  "properties": {
    "iso:country":"GB",
    "sg:address":"27 High Street, Ruskington",
    "sg:city":"Sleaford",
    "sg:classifiers":[
        {
            "category":"Fast Food",
            "type":"Food & Drink"
        }
    ],
    "sg:postcode":"NG34 9DY",
    "sg:province":"Lincolnshire",
    "sg:tags":[
        "away",
        "take"
    ],
    "wof:name":"Golden Phoenix",
    "wof:placetype":"venue"
},
  "geometry": {"coordinates":[-0.298228,52.980263],"type":"Point"}
}