{
  "type": "Feature",
  "properties": {
    "iso:country":"GB",
    "sg:address":"10 Ashkirk Way,, Seaton Deleval,",
    "sg:city":"Whitley Bay",
    "sg:classifiers":[
        {
            "category":"Professional",
            "subcategory":"Engineering",
            "type":"Services"
        }
    ],
    "sg:postcode":"NE25 0JU",
    "sg:province":"Northumberland",
    "sg:tags":[
        "electrical",
        "engineer"
    ],
    "wof:name":"System Design & Integration Ltd",
    "wof:placetype":"venue"
},
  "geometry": {"coordinates":[-1.522051,55.064854],"type":"Point"}
}