{
  "type": "Feature",
  "properties": {
    "addr:full":"137 Clydesdale Rd Bellshill North Lanarkshire ML4 2QH",
    "addr:housenumber":"137",
    "addr:postcode":"ml4 2qh",
    "addr:street":"Clydesdale Rd",
    "iso:country":"GB",
    "sg:address":"137 Clydesdale Rd",
    "sg:city":"Bellshill",
    "sg:classifiers":[
        {
            "category":"Restaurant",
            "type":"Food & Drink"
        }
    ],
    "sg:postcode":"ML4 2QH",
    "sg:province":"North Lanarkshire",
    "sg:tags":[
        "indian"
    ],
    "wof:name":"Club India",
    "wof:placetype":"venue"
},
  "geometry": {"coordinates":[-3.995081,55.816521],"type":"Point"}
}