{
  "type": "Feature",
  "properties": {
    "iso:country":"GB",
    "sg:address":"305-307 Neasden Lane",
    "sg:city":"London",
    "sg:classifiers":[
        {
            "category":"Shopping",
            "subcategory":"Mobile Phones",
            "type":"Retail Goods"
        }
    ],
    "sg:phone":"+44 20 8450 2960",
    "sg:postcode":"NW10 1QR",
    "sg:province":"Greater London",
    "wof:name":"Tagrose Ltd.",
    "wof:placetype":"venue"
},
  "geometry": {"coordinates":[-0.2525910139,51.5601158142],"type":"Point"}
}