{
  "type": "Feature",
  "properties": {
    "addr:full":"126 Rodway Road, Patchway Bristol Gloucestershire BS34 5PF",
    "addr:housenumber":"126",
    "addr:postcode":"bs34 5pf",
    "addr:street":"Rodway Road",
    "iso:country":"GB",
    "sg:address":"126 Rodway Road, Patchway",
    "sg:city":"Bristol",
    "sg:classifiers":[
        {
            "category":"Food & Beverages",
            "subcategory":"Groceries & Convenience Stores",
            "type":"Retail Goods"
        }
    ],
    "sg:phone":"+44 117 969 4751",
    "sg:postcode":"BS34 5PF",
    "sg:province":"Gloucestershire",
    "wof:name":"Spar",
    "wof:placetype":"venue"
},
  "geometry": {"coordinates":[-2.5774400234,51.53150177],"type":"Point"}
}