{
  "type": "Feature",
  "properties": {
    "addr:full":"52 Upper Brook St West End Hampshire W1Y 1PG",
    "addr:housenumber":"52",
    "addr:postcode":"w1y 1pg",
    "addr:street":"Upper Brook St",
    "iso:country":"GB",
    "sg:address":"52 Upper Brook St",
    "sg:city":"West End",
    "sg:classifiers":[
        {
            "category":"Professional",
            "subcategory":"Management & Consulting",
            "type":"Services"
        }
    ],
    "sg:phone":"+44 20 7493 9286",
    "sg:postcode":"W1Y 1PG",
    "sg:province":"Hampshire",
    "sg:tags":[
        "consultant",
        "business"
    ],
    "wof:name":"InterResearch",
    "wof:placetype":"venue"
},
  "geometry": {"coordinates":[-0.154179,51.51144],"type":"Point"}
}