{
  "type": "Feature",
  "properties": {
    "addr:full":"A3 Telford Pl Glasgow Falkirk G67 2NH",
    "addr:postcode":"g67 2nh",
    "addr:street":"Telford Pl",
    "iso:country":"GB",
    "sg:address":"A3 Telford Pl",
    "sg:city":"Glasgow",
    "sg:classifiers":[
        {
            "category":"Shopping",
            "subcategory":"Pharmacy",
            "type":"Retail Goods"
        }
    ],
    "sg:phone":"+44 1236 733900",
    "sg:postcode":"G67 2NH",
    "sg:province":"Falkirk",
    "sg:tags":[
        "toiletry"
    ],
    "wof:name":"Lang Co Toiletries Ltd",
    "wof:placetype":"venue"
},
  "geometry": {"coordinates":[-3.9844999313,55.9391212463],"type":"Point"}
}