{
  "type": "Feature",
  "properties": {
    "addr:full":"11 Fosse Way Leicester Leicestershire LE7 1NF",
    "addr:housenumber":"11",
    "addr:postcode":"le7 1nf",
    "addr:street":"Fosse Way",
    "iso:country":"GB",
    "sg:address":"11 Fosse Way",
    "sg:city":"Leicester",
    "sg:classifiers":[
        {
            "category":"Banks & Credit Unions",
            "subcategory":"Investment Brokerage",
            "type":"Services"
        }
    ],
    "sg:phone":"+44 116 260 5361",
    "sg:postcode":"LE7 1NF",
    "sg:province":"Leicestershire",
    "sg:tags":[
        "additive",
        "colouring",
        "flavouring"
    ],
    "wof:name":"Perfect Polymer Systems Ltd.",
    "wof:placetype":"venue"
},
  "geometry": {"coordinates":[-1.090073,52.69046],"type":"Point"}
}