{
  "type": "Feature",
  "properties": {
    "addr:full":"Blackpool Road, Ashton On Ribble Preston Lancashire PR2 2DQ",
    "addr:postcode":"pr2 2dq",
    "addr:street":"Blackpool Road",
    "iso:country":"GB",
    "sg:address":"Blackpool Road, Ashton On Ribble",
    "sg:city":"Preston",
    "sg:classifiers":[
        {
            "category":"Wholesale",
            "subcategory":"Construction Materials",
            "type":"Manufacturing & Wholesale Goods"
        },
        {
            "category":"Building & Trades",
            "subcategory":"Equipment Rental",
            "type":"Services"
        }
    ],
    "sg:phone":"+44 1772 722500",
    "sg:postcode":"PR2 2DQ",
    "sg:province":"Lancashire",
    "sg:tags":[
        "lift",
        "lifting"
    ],
    "sg:website":"http://www.hss.com",
    "wof:name":"H S S Lift & Shift",
    "wof:placetype":"venue"
},
  "geometry": {"coordinates":[-2.7196540833,53.7725296021],"type":"Point"}
}