{
  "type": "Feature",
  "properties": {
    "addr:full":"Fulwell Road Sunderland Tyne and Wear SR6 9QU",
    "addr:postcode":"sr6 9qu",
    "addr:street":"Fulwell Road",
    "iso:country":"GB",
    "sg:address":"Fulwell Road",
    "sg:city":"Sunderland",
    "sg:classifiers":[
        {
            "category":"Education",
            "subcategory":"School",
            "type":"Public Place"
        }
    ],
    "sg:postcode":"SR6 9QU",
    "sg:province":"Tyne and Wear",
    "sg:tags":[
        "local",
        "authority"
    ],
    "wof:name":"St.Benets R C Primary School",
    "wof:placetype":"venue"
},
  "geometry": {"coordinates":[-1.3814059496,54.9291343689],"type":"Point"}
}