{
  "type": "Feature",
  "properties": {
    "addr:full":"4 Oldway Park Wellington Devon TA21 8EB",
    "addr:housenumber":"4",
    "addr:postcode":"ta21 8eb",
    "addr:street":"Oldway Park Wellington",
    "iso:country":"GB",
    "sg:address":"4 Oldway Park",
    "sg:city":"Wellington",
    "sg:classifiers":[
        {
            "category":"Building & Trades",
            "subcategory":"Construction",
            "type":"Services"
        }
    ],
    "sg:phone":"+44 1823 662310",
    "sg:postcode":"TA21 8EB",
    "sg:province":"Devon",
    "sg:tags":[
        "contractor",
        "paving",
        "driveway"
    ],
    "wof:name":"Wellington Slabs",
    "wof:placetype":"venue"
},
  "geometry": {"coordinates":[-3.2178659439,50.9713745117],"type":"Point"}
}