{
  "type": "Feature",
  "properties": {
    "iso:country":"GB",
    "sg:address":"Rickmansworth Park",
    "sg:city":"Rickmansworth",
    "sg:classifiers":[
        {
            "category":"Education",
            "subcategory":"School",
            "type":"Public Place"
        }
    ],
    "sg:phone":"+44 1923 773168",
    "sg:postcode":"WD3 4HF",
    "sg:province":"Hertfordshire",
    "sg:tags":[
        "independent",
        "preparatory"
    ],
    "wof:name":"The Royal Masonic School for Girls",
    "wof:placetype":"venue"
},
  "geometry": {"coordinates":[-0.493139,51.654957],"type":"Point"}
}