{
  "type": "Feature",
  "properties": {
    "addr:full":"29 Stockwell Dr Bristol City of Bristol BS17 3DW",
    "addr:housenumber":"29",
    "addr:postcode":"bs17 3dw",
    "addr:street":"Stockwell Dr",
    "iso:country":"GB",
    "sg:address":"29 Stockwell Dr",
    "sg:city":"Bristol",
    "sg:classifiers":[
        {
            "category":"Shopping",
            "subcategory":"Department Store",
            "type":"Retail Goods"
        }
    ],
    "sg:phone":"+44 117 975 4030",
    "sg:postcode":"BS17 3DW",
    "sg:province":"City of Bristol",
    "wof:name":"Janet & Bobs Food Store",
    "wof:placetype":"venue"
},
  "geometry": {"coordinates":[-2.489303112,51.4902496338],"type":"Point"}
}