{
  "type": "Feature",
  "properties": {
    "addr:full":"5 West Ashton Street Salford Greater Manchester M5 2XS",
    "addr:housenumber":"5",
    "addr:postcode":"m5 2xs",
    "addr:street":"West Ashton Street",
    "iso:country":"GB",
    "sg:address":"5 West Ashton Street",
    "sg:city":"Salford",
    "sg:classifiers":[
        {
            "category":"Manufacturing",
            "subcategory":"Metals",
            "type":"Manufacturing & Wholesale Goods"
        }
    ],
    "sg:phone":"+44 161 736 0099",
    "sg:postcode":"M5 2XS",
    "sg:province":"Greater Manchester",
    "sg:tags":[
        "steel",
        "stockholder"
    ],
    "wof:name":"Jenkinson Steel Ltd.",
    "wof:placetype":"venue"
},
  "geometry": {"coordinates":[-2.290934,53.479282],"type":"Point"}
}