{
  "type": "Feature",
  "properties": {
    "addr:full":"53 Alkham Rd Stoke Newington Greater London N16 7AA",
    "addr:housenumber":"53",
    "addr:postcode":"n16 7aa",
    "addr:street":"Alkham Rd",
    "iso:country":"GB",
    "sg:address":"53 Alkham Rd",
    "sg:city":"Stoke Newington",
    "sg:classifiers":[
        {
            "category":"Real Estate",
            "subcategory":"Architect",
            "type":"Services"
        }
    ],
    "sg:phone":"+44 20 8880 0600",
    "sg:postcode":"N16 7AA",
    "sg:province":"Greater London",
    "wof:name":"Barker Shorten Architects",
    "wof:placetype":"venue"
},
  "geometry": {"coordinates":[-0.0695689991,51.5648612976],"type":"Point"}
}