{
  "type": "Feature",
  "properties": {
    "addr:full":"Unit 8 Leaside North, Aycliffe Industrial Estate Newton Aycliffe Durham DL5 6HX",
    "addr:housenumber":"unit 8",
    "addr:postcode":"dl5 6hx",
    "addr:street":"Leaside North Aycliffe Industrial Estate;Aycliffe",
    "iso:country":"GB",
    "sg:address":"Unit 8 Leaside North, Aycliffe Industrial Estate",
    "sg:city":"Newton Aycliffe",
    "sg:classifiers":[
        {
            "category":"Home & Garden",
            "subcategory":"Hardware",
            "type":"Retail Goods"
        }
    ],
    "sg:phone":"+44 1325 301666",
    "sg:postcode":"DL5 6HX",
    "sg:province":"Durham",
    "sg:tags":[
        "equipment",
        "welding"
    ],
    "wof:name":"Speedarc Ltd.",
    "wof:placetype":"venue"
},
  "geometry": {"coordinates":[-1.563024044,54.5962715149],"type":"Point"}
}