{
  "type": "Feature",
  "properties": {
    "iso:country":"GB",
    "sg:address":"Lower Larchfield Works, Walton St",
    "sg:city":"Dundee",
    "sg:classifiers":[
        {
            "category":"Building & Trades",
            "subcategory":"Cleaning & Sanitation",
            "type":"Services"
        }
    ],
    "sg:phone":"+44 1382 223255",
    "sg:postcode":"DD1 5BL",
    "sg:province":"Dundee City",
    "sg:tags":[
        "blast"
    ],
    "wof:name":"AUTOBLAST SERVICES DUNDEE",
    "wof:placetype":"venue"
},
  "geometry": {"coordinates":[-2.967609,56.461376],"type":"Point"}
}