{
  "type": "Feature",
  "properties": {
    "addr:full":"18 Commercial St Trimdon Station Durham TS29 6LF",
    "addr:housenumber":"18",
    "addr:postcode":"ts29 6lf",
    "addr:street":"Commercial St",
    "iso:country":"GB",
    "sg:address":"18 Commercial St",
    "sg:city":"Trimdon Station",
    "sg:classifiers":[
        {
            "category":"Home & Garden",
            "subcategory":"Hardware",
            "type":"Retail Goods"
        }
    ],
    "sg:postcode":"TS29 6LF",
    "sg:province":"Durham",
    "sg:tags":[
        "retailer",
        "diy"
    ],
    "wof:name":"P T S Timber & Hardware Supplies",
    "wof:placetype":"venue"
},
  "geometry": {"coordinates":[-1.411373,54.71727],"type":"Point"}
}