{
  "type": "Feature",
  "properties": {
    "iso:country":"GB",
    "sg:address":"Snape Hill Road, Darfield",
    "sg:city":"Barnsley",
    "sg:classifiers":[
        {
            "category":"Education",
            "subcategory":"School",
            "type":"Public Place"
        }
    ],
    "sg:phone":"+44 1226 753149",
    "sg:postcode":"S73 9LT",
    "sg:province":"South Yorkshire",
    "sg:tags":[
        "local",
        "authority"
    ],
    "wof:name":"Darfield Valley Primary School",
    "wof:placetype":"venue"
},
  "geometry": {"coordinates":[-1.377324,53.533455],"type":"Point"}
}