{
  "type": "Feature",
  "properties": {
    "addr:full":"57 Dairyground Road Stockport Cheshire SK7 2QW",
    "addr:housenumber":"57",
    "addr:postcode":"sk7 2qw",
    "addr:street":"Dairyground Road",
    "iso:country":"GB",
    "sg:address":"57 Dairyground Road",
    "sg:city":"Stockport",
    "sg:classifiers":[
        {
            "category":"Fast Food",
            "type":"Food & Drink"
        }
    ],
    "sg:phone":"+44 161 439 1051",
    "sg:postcode":"SK7 2QW",
    "sg:province":"Cheshire",
    "sg:tags":[
        "away",
        "take"
    ],
    "wof:name":"Eastern Pearl Take Away",
    "wof:placetype":"venue"
},
  "geometry": {"coordinates":[-2.1571519375,53.3652648926],"type":"Point"}
}