{
  "type": "Feature",
  "properties": {
    "iso:country":"GB",
    "sg:address":"2 Westgate",
    "sg:city":"Ripon",
    "sg:classifiers":[
        {
            "category":"Autos & Motor Vehicles",
            "subcategory":"Auto Supplies",
            "type":"Retail Goods"
        },
        {
            "category":"Shopping",
            "type":"Retail Goods"
        }
    ],
    "sg:phone":"+44 1765 606600",
    "sg:postcode":"HG4 2AT",
    "sg:province":"North Yorkshire",
    "sg:tags":[
        "car",
        "part",
        "accessory"
    ],
    "wof:name":"Motor World Ltd",
    "wof:placetype":"venue"
},
  "geometry": {"coordinates":[-1.524762,54.136341],"type":"Point"}
}