{
  "type": "Feature",
  "properties": {
    "addr:full":"19 Market Sq London Greater London E14 6AQ",
    "addr:housenumber":"19",
    "addr:postcode":"e14 6aq",
    "addr:street":"Market Sq",
    "iso:country":"GB",
    "sg:address":"19 Market Sq",
    "sg:city":"London",
    "sg:classifiers":[
        {
            "category":"Shopping",
            "subcategory":"Music",
            "type":"Retail Goods"
        },
        {
            "category":"Building & Trades",
            "subcategory":"Construction",
            "type":"Services"
        }
    ],
    "sg:postcode":"E14 6AQ",
    "sg:province":"Greater London",
    "sg:tags":[
        "record",
        "builder",
        "tape",
        "cd"
    ],
    "wof:name":"R & D Developments",
    "wof:placetype":"venue"
},
  "geometry": {"coordinates":[0.0568160005,51.530872345],"type":"Point"}
}