{
  "type": "Feature",
  "properties": {
    "iso:country":"GB",
    "sg:address":"11 Robin Court, Lupus Street",
    "sg:city":"London",
    "sg:classifiers":[
        {
            "category":"Government",
            "subcategory":"Office",
            "type":"Public Place"
        }
    ],
    "sg:postcode":"SW1V 3ED",
    "sg:province":"Greater London",
    "sg:tags":[
        "education",
        "agency",
        "authority"
    ],
    "wof:name":"Diana Page Associates Ltd.",
    "wof:placetype":"venue"
},
  "geometry": {"coordinates":[-0.136223,51.488655],"type":"Point"}
}