{
  "type": "Feature",
  "properties": {
    "addr:full":"44 Breamwater Gardens, Ham Richmond Greater London TW10 7SH",
    "addr:housenumber":"44",
    "addr:postcode":"tw10 7sh",
    "addr:street":"Breamwater Gardens",
    "iso:country":"GB",
    "sg:address":"44 Breamwater Gardens, Ham",
    "sg:city":"Richmond",
    "sg:classifiers":[
        {
            "category":"Building & Trades",
            "subcategory":"Construction",
            "type":"Services"
        }
    ],
    "sg:phone":"+44 20 8940 3041",
    "sg:postcode":"TW10 7SH",
    "sg:province":"Greater London",
    "sg:tags":[
        "decorator",
        "painter"
    ],
    "wof:name":"N J Decor",
    "wof:placetype":"venue"
},
  "geometry": {"coordinates":[-0.321721,51.438435],"type":"Point"}
}