{
  "type": "Feature",
  "properties": {
    "addr:full":"76-80 Bridge Street Derby Derbyshire DE1 3LA",
    "addr:housenumber":"76-80",
    "addr:postcode":"de1 3la",
    "addr:street":"Bridge Street",
    "iso:country":"GB",
    "sg:address":"76-80 Bridge Street",
    "sg:city":"Derby",
    "sg:classifiers":[
        {
            "category":"Bars & Pubs",
            "type":"Food & Drink"
        }
    ],
    "sg:phone":"+44 1332 332910",
    "sg:postcode":"DE1 3LA",
    "sg:province":"Derbyshire",
    "sg:tags":[
        "pubs",
        "inn"
    ],
    "wof:name":"The Woodlark Inn",
    "wof:placetype":"venue"
},
  "geometry": {"coordinates":[-1.4858930111,52.9264907837],"type":"Point"}
}