{
  "type": "Feature",
  "properties": {
    "iso:country":"GB",
    "sg:address":"Telephone Exchange, Leapale Road",
    "sg:city":"Guildford",
    "sg:classifiers":[
        {
            "category":"Manufacturing",
            "subcategory":"Motor Vehicles & Parts",
            "type":"Manufacturing & Wholesale Goods"
        }
    ],
    "sg:phone":"+44 1483 454849",
    "sg:postcode":"GU1 4BD",
    "sg:province":"Surrey",
    "sg:tags":[
        "bearing"
    ],
    "wof:name":"John Beaney & Robert Cook",
    "wof:placetype":"venue"
},
  "geometry": {"coordinates":[-0.5705159903,51.2370872498],"type":"Point"}
}