{
  "type": "Feature",
  "properties": {
    "addr:full":"51a Tanner Street London Greater London SE1 3PL",
    "addr:housenumber":"51a",
    "addr:postcode":"se1 3pl",
    "addr:street":"Tanner Street",
    "iso:country":"GB",
    "sg:address":"51a Tanner Street",
    "sg:city":"London",
    "sg:classifiers":[
        {
            "category":"Professional",
            "subcategory":"Art Services",
            "type":"Services"
        }
    ],
    "sg:phone":"+44 20 7357 8715",
    "sg:postcode":"SE1 3PL",
    "sg:province":"Greater London",
    "sg:tags":[
        "graphic",
        "designer"
    ],
    "wof:name":"Viewpad Ltd.",
    "wof:placetype":"venue"
},
  "geometry": {"coordinates":[-0.0777620003,51.4999389648],"type":"Point"}
}