{
  "type": "Feature",
  "properties": {
    "addr:full":"25 Sywell Close Sutton-in-ashfield Nottinghamshire NG17 4NN",
    "addr:housenumber":"25",
    "addr:postcode":"ng17 4nn",
    "addr:street":"Sywell Close",
    "iso:country":"GB",
    "sg:address":"25 Sywell Close",
    "sg:city":"Sutton-in-ashfield",
    "sg:classifiers":[
        {
            "category":"Retail",
            "subcategory":"Storage",
            "type":"Services"
        }
    ],
    "sg:postcode":"NG17 4NN",
    "sg:province":"Nottinghamshire",
    "sg:tags":[
        "household",
        "removal"
    ],
    "wof:name":"Humpers Removals",
    "wof:placetype":"venue"
},
  "geometry": {"coordinates":[-1.258187,53.136711],"type":"Point"}
}