{
  "type": "Feature",
  "properties": {
    "addr:full":"169 Ock Street Abingdon Oxfordshire OX14 5DW",
    "addr:housenumber":"169",
    "addr:postcode":"ox14 5dw",
    "addr:street":"Ock Street",
    "iso:country":"GB",
    "sg:address":"169 Ock Street",
    "sg:city":"Abingdon",
    "sg:classifiers":[
        {
            "category":"Bars & Pubs",
            "type":"Food & Drink"
        }
    ],
    "sg:phone":"+44 1235 523453",
    "sg:postcode":"OX14 5DW",
    "sg:province":"Oxfordshire",
    "sg:tags":[
        "pubs",
        "inn"
    ],
    "wof:name":"The Air Balloon",
    "wof:placetype":"venue"
},
  "geometry": {"coordinates":[-1.2932269573,51.6693725586],"type":"Point"}
}