{
  "type": "Feature",
  "properties": {
    "addr:full":"6 Manor Rd Cheadle Cheshire SK8 7DQ",
    "addr:housenumber":"6",
    "addr:postcode":"sk8 7dq",
    "addr:street":"Manor Rd Cheadle",
    "iso:country":"GB",
    "sg:address":"6 Manor Rd",
    "sg:city":"Cheadle",
    "sg:classifiers":[
        {
            "category":"Social Services",
            "subcategory":"Child Care",
            "type":"Services"
        }
    ],
    "sg:phone":"+44 161 485 1957",
    "sg:postcode":"SK8 7DQ",
    "sg:province":"Cheshire",
    "sg:tags":[
        "baby",
        "sitter"
    ],
    "wof:name":"Babysitting Services",
    "wof:placetype":"venue"
},
  "geometry": {"coordinates":[-2.1814289093,53.3717384338],"type":"Point"}
}