{
  "type": "Feature",
  "properties": {
    "addr:full":"140 Boythorpe Rd Chesterfield Derbyshire S40 2LR",
    "addr:housenumber":"140",
    "addr:postcode":"s40 2lr",
    "addr:street":"Boythorpe Rd",
    "iso:country":"GB",
    "sg:address":"140 Boythorpe Rd",
    "sg:city":"Chesterfield",
    "sg:classifiers":[
        {
            "category":"Food & Beverages",
            "subcategory":"Liquor & Beverages",
            "type":"Retail Goods"
        }
    ],
    "sg:postcode":"S40 2LR",
    "sg:province":"Derbyshire",
    "sg:tags":[
        "beer",
        "spirit",
        "wines"
    ],
    "wof:name":"Moreira,Norberto,",
    "wof:placetype":"venue"
},
  "geometry": {"coordinates":[-1.434018,53.225128],"type":"Point"}
}