{
  "type": "Feature",
  "properties": {
    "addr:full":"25 Tithe Close, Thringstone Coalville Leicestershire LE67 8LZ",
    "addr:housenumber":"25",
    "addr:postcode":"le67 8lz",
    "addr:street":"Tithe Close",
    "iso:country":"GB",
    "sg:address":"25 Tithe Close, Thringstone",
    "sg:city":"Coalville",
    "sg:classifiers":[
        {
            "category":"Professional",
            "subcategory":"Engineering",
            "type":"Services"
        }
    ],
    "sg:phone":"+44 1530 457869",
    "sg:postcode":"LE67 8LZ",
    "sg:province":"Leicestershire",
    "sg:tags":[
        "contractor",
        "electrical",
        "engineer"
    ],
    "wof:name":"C L Perrett",
    "wof:placetype":"venue"
},
  "geometry": {"coordinates":[-1.3729239702,52.7562103271],"type":"Point"}
}