{
  "type": "Feature",
  "properties": {
    "addr:full":"Lower Moor Rd Coalville Leicestershire LE67 8FN",
    "addr:postcode":"le67 8fn",
    "addr:street":"Lower Moor Rd",
    "iso:country":"GB",
    "sg:address":"Lower Moor Rd",
    "sg:city":"Coalville",
    "sg:classifiers":[
        {
            "category":"Place Of Worship",
            "type":"Public Place"
        }
    ],
    "sg:phone":"+44 1530 412298",
    "sg:postcode":"LE67 8FN",
    "sg:province":"Leicestershire",
    "wof:name":"Coleorton Methodist Church",
    "wof:placetype":"venue"
},
  "geometry": {"coordinates":[-1.405452,52.758839],"type":"Point"}
}