{
  "type": "Feature",
  "properties": {
    "addr:full":"41 Masons Hill Bromley Kent BR2 8JE",
    "addr:housenumber":"41",
    "addr:postcode":"br2 8je",
    "addr:street":"Masons Hill",
    "iso:country":"GB",
    "sg:address":"41 Masons Hill",
    "sg:city":"Bromley",
    "sg:classifiers":[
        {
            "category":"Taxi",
            "type":"Transportation"
        }
    ],
    "sg:phone":"+44 44208650 x5050",
    "sg:postcode":"BR2 8JE",
    "sg:province":"Kent",
    "sg:tags":[
        "mini",
        "cab"
    ],
    "wof:name":"Circuit Car Hire",
    "wof:placetype":"venue"
},
  "geometry": {"coordinates":[0.018276,51.398907],"type":"Point"}
}