{
  "type": "Feature",
  "properties": {
    "addr:full":"Studio 12 The Mill, Warmingham Sandbach Cheshire CW11 3QW",
    "addr:housenumber":"12",
    "addr:postcode":"cw11 3qw",
    "addr:street":"The Mill",
    "iso:country":"GB",
    "sg:address":"Studio 12 The Mill, Warmingham",
    "sg:city":"Sandbach",
    "sg:classifiers":[
        {
            "category":"Shopping",
            "subcategory":"Pets & Pet Supplies",
            "type":"Retail Goods"
        }
    ],
    "sg:postcode":"CW11 3QW",
    "sg:province":"Cheshire",
    "wof:name":"A E Collars",
    "wof:placetype":"venue"
},
  "geometry": {"coordinates":[-2.3936190605,53.1422996521],"type":"Point"}
}