{
  "type": "Feature",
  "properties": {
    "addr:full":"Cranbourne Rd Gosport Hampshire PO12 1RL",
    "addr:postcode":"po12 1rl",
    "addr:street":"Cranbourne Rd",
    "iso:country":"GB",
    "sg:address":"Cranbourne Rd",
    "sg:city":"Gosport",
    "sg:classifiers":[
        {
            "category":"Professional",
            "subcategory":"Engineering",
            "type":"Services"
        }
    ],
    "sg:phone":"+44 23 9250 1050",
    "sg:postcode":"PO12 1RL",
    "sg:province":"Hampshire",
    "sg:tags":[
        "engineer"
    ],
    "wof:name":"Limburn Industrial Heating Services",
    "wof:placetype":"venue"
},
  "geometry": {"coordinates":[-1.132209,50.791176],"type":"Point"}
}