{
  "type": "Feature",
  "properties": {
    "addr:full":"3 Royal Buildings Penarth The Vale of Glamorgan CF64 3EB",
    "addr:housenumber":"3",
    "addr:postcode":"cf64 3eb",
    "addr:street":"Royal Buildings;Vale",
    "iso:country":"GB",
    "sg:address":"3 Royal Buildings",
    "sg:city":"Penarth",
    "sg:classifiers":[
        {
            "category":"Shopping",
            "subcategory":"Pharmacy",
            "type":"Retail Goods"
        }
    ],
    "sg:phone":"+44 29 2070 8313",
    "sg:postcode":"CF64 3EB",
    "sg:province":"The Vale of Glamorgan",
    "sg:tags":[
        "pharmacist",
        "chemist"
    ],
    "wof:name":"Ivor Owen Ltd.",
    "wof:placetype":"venue"
},
  "geometry": {"coordinates":[-3.1788289547,51.4429206848],"type":"Point"}
}