{
  "type": "Feature",
  "properties": {
    "iso:country":"GB",
    "sg:address":"124 Childs Avenue",
    "sg:city":"Bilston",
    "sg:classifiers":[
        {
            "category":"Food & Beverages",
            "subcategory":"Meat & Fish",
            "type":"Retail Goods"
        }
    ],
    "sg:postcode":"WV14 9XB",
    "sg:province":"West Midlands",
    "sg:tags":[
        "butcher"
    ],
    "wof:name":"Chris Caddick",
    "wof:placetype":"venue"
},
  "geometry": {"coordinates":[-2.100713,52.551151],"type":"Point"}
}