{
  "type": "Feature",
  "properties": {
    "addr:full":"8 Randall Drive Hornchurch Essex RM12 6SX",
    "addr:housenumber":"8",
    "addr:postcode":"rm12 6sx",
    "addr:street":"Randall Drive",
    "iso:country":"GB",
    "sg:address":"8 Randall Drive",
    "sg:city":"Hornchurch",
    "sg:classifiers":[
        {
            "category":"Freight",
            "type":"Transportation"
        }
    ],
    "sg:phone":"+44 1708 444538",
    "sg:postcode":"RM12 6SX",
    "sg:province":"Essex",
    "sg:tags":[
        "haulage",
        "road"
    ],
    "wof:name":"H.B Tuvey",
    "wof:placetype":"venue"
},
  "geometry": {"coordinates":[0.2175139934,51.5519142151],"type":"Point"}
}