{
  "type": "Feature",
  "properties": {
    "addr:full":"69 Rosemount Place Aberdeen Aberdeen City AB25 2XL",
    "addr:housenumber":"69",
    "addr:postcode":"ab25 2xl",
    "addr:street":"Rosemount Place",
    "iso:country":"GB",
    "sg:address":"69 Rosemount Place",
    "sg:city":"Aberdeen",
    "sg:classifiers":[
        {
            "category":"Social Services",
            "subcategory":"Adult Care",
            "type":"Services"
        }
    ],
    "sg:phone":"+44 1224 646633",
    "sg:postcode":"AB25 2XL",
    "sg:province":"Aberdeen City",
    "sg:tags":[
        "mnfr",
        "aid",
        "hearing"
    ],
    "wof:name":"Better Hearing",
    "wof:placetype":"venue"
},
  "geometry": {"coordinates":[-2.113101,57.150238],"type":"Point"}
}