{
  "type": "Feature",
  "properties": {
    "iso:country":"GB",
    "sg:address":"Anstey La",
    "sg:city":"Alton",
    "sg:classifiers":[
        {
            "category":"Government",
            "subcategory":"Post Office",
            "type":"Public Place"
        }
    ],
    "sg:phone":"+44 1420 80525",
    "sg:postcode":"GU34 2NF",
    "sg:province":"Hampshire",
    "wof:name":"Manor Estate Post Office",
    "wof:placetype":"venue"
},
  "geometry": {"coordinates":[-0.9711689949,51.1625862122],"type":"Point"}
}