{
  "type": "Feature",
  "properties": {
    "addr:full":"Wiltshire Road, Chaddesden Derby Derbyshire DE21 6EZ",
    "addr:postcode":"de21 6ez",
    "addr:street":"Wiltshire Road",
    "iso:country":"GB",
    "sg:address":"Wiltshire Road, Chaddesden",
    "sg:city":"Derby",
    "sg:classifiers":[
        {
            "category":"Shopping",
            "subcategory":"Clothing, Apparel, & Fashions",
            "type":"Retail Goods"
        }
    ],
    "sg:phone":"+44 1332 670619",
    "sg:postcode":"DE21 6EZ",
    "sg:province":"Derbyshire",
    "sg:tags":[
        "haberdasher"
    ],
    "wof:name":"Derby Braid & Trimming Co",
    "wof:placetype":"venue"
},
  "geometry": {"coordinates":[-1.434409,52.928822],"type":"Point"}
}