{
  "type": "Feature",
  "properties": {
    "iso:country":"GB",
    "sg:address":"Buxton Park Hotel",
    "sg:city":"Uckfield",
    "sg:classifiers":[
        {
            "category":"Travel",
            "subcategory":"Hotels & Motels",
            "type":"Entertainment"
        }
    ],
    "sg:phone":"+44 1732 471000",
    "sg:postcode":"TN22 4AY",
    "sg:province":"East Sussex",
    "wof:name":"Buxted Park Hotel Ltd.",
    "wof:placetype":"venue"
},
  "geometry": {"coordinates":[0.09665,50.971813],"type":"Point"}
}