{
  "type": "Feature",
  "properties": {
    "addr:full":"4 The Mall, London Rd Swanley Kent BR8 7WL",
    "addr:housenumber":"4",
    "addr:postcode":"br8 7wl",
    "addr:street":"The Mall London Rd",
    "iso:country":"GB",
    "sg:address":"4 The Mall, London Rd",
    "sg:city":"Swanley",
    "sg:classifiers":[
        {
            "category":"Real Estate",
            "subcategory":"Real Estate Agent",
            "type":"Services"
        }
    ],
    "sg:phone":"+44 1322 614434",
    "sg:postcode":"BR8 7WL",
    "sg:province":"Kent",
    "wof:name":"Kings",
    "wof:placetype":"venue"
},
  "geometry": {"coordinates":[0.18665,51.391949],"type":"Point"}
}