{
  "type": "Feature",
  "properties": {
    "addr:full":"Donington Park, Castle Donington Derby Leicestershire DE74 2RP",
    "addr:postcode":"de74 2rp",
    "addr:street":"Park",
    "iso:country":"GB",
    "sg:address":"Donington Park, Castle Donington",
    "sg:city":"Derby",
    "sg:classifiers":[
        {
            "category":"Parking",
            "type":"Transportation"
        }
    ],
    "sg:phone":"+44 1332 853686",
    "sg:postcode":"DE74 2RP",
    "sg:province":"Leicestershire",
    "sg:tags":[
        "car",
        "park"
    ],
    "wof:name":"Airparks Services Ltd.",
    "wof:placetype":"venue"
},
  "geometry": {"coordinates":[-1.3373839855,52.8448791504],"type":"Point"}
}