{
  "type": "Feature",
  "properties": {
    "iso:country":"GB",
    "sg:address":"1 Cotswold House, Cheltenham Road",
    "sg:city":"Portsmouth",
    "sg:classifiers":[
        {
            "category":"Food & Beverages",
            "subcategory":"Fruits & Vegetables",
            "type":"Retail Goods"
        }
    ],
    "sg:phone":"+44 23 9232 6935",
    "sg:postcode":"PO6 3QA",
    "sg:province":"Hampshire",
    "sg:tags":[
        "greengrocer"
    ],
    "wof:name":"A J 'S Pantry",
    "wof:placetype":"venue"
},
  "geometry": {"coordinates":[-1.08512,50.847549],"type":"Point"}
}