{
  "type": "Feature",
  "properties": {
    "addr:full":"Halden House, High Halden Ashford Kent TN26 3BT",
    "addr:postcode":"tn26 3bt",
    "iso:country":"GB",
    "sg:address":"Halden House, High Halden",
    "sg:city":"Ashford",
    "sg:classifiers":[
        {
            "category":"Insurance",
            "subcategory":"Insurance Agent",
            "type":"Services"
        }
    ],
    "sg:phone":"+44 1233 649000",
    "sg:postcode":"TN26 3BT",
    "sg:province":"Kent",
    "sg:tags":[
        "broker"
    ],
    "wof:name":"Bishops Plc Insurance & Risk Management",
    "wof:placetype":"venue"
},
  "geometry": {"coordinates":[0.681311,51.110252],"type":"Point"}
}