{
  "type": "Feature",
  "properties": {
    "iso:country":"GB",
    "sg:address":"53 Church Road, St Annes",
    "sg:city":"Lytham St Annes",
    "sg:classifiers":[
        {
            "category":"Building & Trades",
            "subcategory":"Construction",
            "type":"Services"
        }
    ],
    "sg:phone":"+44 1253 728368",
    "sg:postcode":"FY8 3TL",
    "sg:province":"Lancashire",
    "sg:tags":[
        "joinery",
        "joiner",
        "carpenter",
        "carpentry"
    ],
    "wof:name":"A Birtwistle & Son",
    "wof:placetype":"venue"
},
  "geometry": {"coordinates":[-3.018103,53.755684],"type":"Point"}
}