{
  "type": "Feature",
  "properties": {
    "addr:full":"Bucklands End La Birmingham West Midlands B34 6BP",
    "addr:postcode":"6bp",
    "addr:street":"Bucklands End La Birmingham",
    "iso:country":"GB",
    "sg:address":"Bucklands End La",
    "sg:city":"Birmingham",
    "sg:classifiers":[
        {
            "category":"Home & Garden",
            "subcategory":"Carpets & Floor Coverings",
            "type":"Retail Goods"
        }
    ],
    "sg:phone":"+44 121 730 1634",
    "sg:postcode":"B34 6BP",
    "sg:province":"West Midlands",
    "sg:tags":[
        "carpets",
        "rug",
        "matting"
    ],
    "wof:name":"Bucklands End Carpets",
    "wof:placetype":"venue"
},
  "geometry": {"coordinates":[-1.803094,52.498825],"type":"Point"}
}