{
  "type": "Feature",
  "properties": {
    "addr:full":"Station Works, Rye Lane Dunton Green Sevenoaks Kent TN14 5HD",
    "addr:postcode":"tn14 5hd",
    "addr:street":"Rye Lane Dunton Green",
    "iso:country":"GB",
    "sg:address":"Station Works, Rye Lane Dunton Green",
    "sg:city":"Sevenoaks",
    "sg:classifiers":[
        {
            "category":"Manufacturing",
            "subcategory":"Rubber & Plastics",
            "type":"Manufacturing & Wholesale Goods"
        }
    ],
    "sg:phone":"+44 1732 462656",
    "sg:postcode":"TN14 5HD",
    "sg:province":"Kent",
    "sg:tags":[
        "product"
    ],
    "wof:name":"Technical Treatments Ltd.",
    "wof:placetype":"venue"
},
  "geometry": {"coordinates":[0.17244,51.29335],"type":"Point"}
}