{
  "type": "Feature",
  "properties": {
    "addr:full":"The Lodge Mill Lane, Wetley Rocks Stoke-on-trent Staffordshire ST9 0BN",
    "addr:postcode":"staffordshire st9 0bn",
    "addr:street":"Mill Lane",
    "iso:country":"GB",
    "sg:address":"The Lodge Mill Lane, Wetley Rocks",
    "sg:city":"Stoke-on-trent",
    "sg:classifiers":[
        {
            "category":"Banks & Credit Unions",
            "subcategory":"Bank",
            "type":"Services"
        }
    ],
    "sg:phone":"+44 1782 550834",
    "sg:postcode":"ST9 0BN",
    "sg:province":"Staffordshire",
    "sg:tags":[
        "stocktaking",
        "inventory"
    ],
    "wof:name":"G W Corfield",
    "wof:placetype":"venue"
},
  "geometry": {"coordinates":[-2.0533440113,53.0395812988],"type":"Point"}
}