{
  "type": "Feature",
  "properties": {
    "addr:full":"24 Convent Gardens, Ealing London Greater London W5 4UT",
    "addr:housenumber":"24",
    "addr:postcode":"w5 4ut",
    "addr:street":"Convent Gardens",
    "iso:country":"GB",
    "sg:address":"24 Convent Gardens, Ealing",
    "sg:city":"London",
    "sg:classifiers":[
        {
            "category":"Professional",
            "subcategory":"Accounting & Tax Preparation",
            "type":"Services"
        }
    ],
    "sg:postcode":"W5 4UT",
    "sg:province":"Greater London",
    "sg:tags":[
        "accountant"
    ],
    "wof:name":"Samurai Accounting Ltd",
    "wof:placetype":"venue"
},
  "geometry": {"coordinates":[-0.312737,51.495712],"type":"Point"}
}