{
  "type": "Feature",
  "properties": {
    "iso:country":"GB",
    "sg:address":"Workshop Del Baron, Chertsey Road",
    "sg:city":"Shepperton",
    "sg:classifiers":[
        {
            "category":"Building & Trades",
            "subcategory":"Construction",
            "type":"Services"
        }
    ],
    "sg:postcode":"TW17 0JS",
    "sg:province":"Surrey",
    "sg:tags":[
        "monumental",
        "mason"
    ],
    "wof:name":"Ashley Taylor",
    "wof:placetype":"venue"
},
  "geometry": {"coordinates":[-0.463516,51.40115],"type":"Point"}
}