{
  "type": "Feature",
  "properties": {
    "addr:full":"13 Brook Pde, High Rd Chigwell Essex IG7 6PF",
    "addr:housenumber":"13",
    "addr:postcode":"ig7 6pf",
    "addr:street":"Brook Pde High Rd",
    "iso:country":"GB",
    "sg:address":"13 Brook Pde, High Rd",
    "sg:city":"Chigwell",
    "sg:classifiers":[
        {
            "category":"Arts & Performance",
            "subcategory":"Art Gallery",
            "type":"Entertainment"
        }
    ],
    "sg:phone":"+44 20 8501 4545",
    "sg:postcode":"IG7 6PF",
    "sg:province":"Essex",
    "wof:name":"Brook Gallery",
    "wof:placetype":"venue"
},
  "geometry": {"coordinates":[0.075095,51.618946],"type":"Point"}
}