{
  "type": "Feature",
  "properties": {
    "addr:full":"St Peters Autocentre, Rosemead Drive, Oadby Leicester Leicestershire LE2 5SF",
    "addr:postcode":"le2 5sf",
    "addr:street":"Rosemead Drive",
    "iso:country":"GB",
    "sg:address":"St Peters Autocentre, Rosemead Drive, Oadby",
    "sg:city":"Leicester",
    "sg:classifiers":[
        {
            "category":"Autos & Motor Vehicles",
            "subcategory":"Auto Supplies",
            "type":"Retail Goods"
        }
    ],
    "sg:phone":"+44 116 271 7116",
    "sg:postcode":"LE2 5SF",
    "sg:province":"Leicestershire",
    "sg:tags":[
        "component"
    ],
    "wof:name":"R J S Valeters",
    "wof:placetype":"venue"
},
  "geometry": {"coordinates":[-1.0840640068,52.5961456299],"type":"Point"}
}