{
  "type": "Feature",
  "properties": {
    "iso:country":"GB",
    "sg:address":"Peebles Rd",
    "sg:city":"Innerleithen",
    "sg:classifiers":[
        {
            "category":"Government",
            "subcategory":"Police Station",
            "type":"Public Place"
        }
    ],
    "sg:phone":"+44 1896 830217",
    "sg:postcode":"EH44 6QY",
    "sg:province":"Scottish Borders",
    "sg:tags":[
        "support"
    ],
    "wof:name":"Innerleithen Police Station",
    "wof:placetype":"venue"
},
  "geometry": {"coordinates":[-3.062119,55.619659],"type":"Point"}
}