{
  "type": "Feature",
  "properties": {
    "iso:country":"GB",
    "sg:address":"Heather Ridge Arc",
    "sg:city":"Camberley",
    "sg:classifiers":[
        {
            "category":"Government",
            "subcategory":"Post Office",
            "type":"Public Place"
        }
    ],
    "sg:phone":"+44 1276 692405",
    "sg:postcode":"GU15 1AX",
    "sg:province":"Berkshire",
    "wof:name":"Heatherside Sub Post Office",
    "wof:placetype":"venue"
},
  "geometry": {"coordinates":[-0.7342299819,51.3362159729],"type":"Point"}
}