{
  "type": "Feature",
  "properties": {
    "addr:full":"9 Mansfield Road Chessington Surrey KT9 2PJ",
    "addr:housenumber":"9",
    "addr:postcode":"kt9 2pj",
    "addr:street":"Mansfield Road",
    "iso:country":"GB",
    "sg:address":"9 Mansfield Road",
    "sg:city":"Chessington",
    "sg:classifiers":[
        {
            "category":"Health Services",
            "subcategory":"Health Practitioner",
            "type":"Services"
        }
    ],
    "sg:phone":"+44 20 8397 8629",
    "sg:postcode":"KT9 2PJ",
    "sg:province":"Surrey",
    "sg:tags":[
        "osteopath"
    ],
    "wof:name":"Osteopathic Centre",
    "wof:placetype":"venue"
},
  "geometry": {"coordinates":[-0.3092449903,51.3631706238],"type":"Point"}
}