{
  "type": "Feature",
  "properties": {
    "iso:country":"GB",
    "sg:address":"Waterloo Street",
    "sg:city":"Bangor",
    "sg:classifiers":[
        {
            "category":"Food & Beverages",
            "subcategory":"Bakery",
            "type":"Retail Goods"
        }
    ],
    "sg:phone":"+44 1248 370385",
    "sg:postcode":"LL57 1DS",
    "sg:province":"Gwynedd",
    "sg:tags":[
        "baker"
    ],
    "wof:name":"Pantri Tangwen",
    "wof:placetype":"venue"
},
  "geometry": {"coordinates":[-4.126214,53.226616],"type":"Point"}
}