{
  "type": "Feature",
  "properties": {
    "addr:full":"14 Cawnpore Street London Greater London SE19 1PF",
    "addr:housenumber":"14",
    "addr:postcode":"se19 1pf",
    "addr:street":"Cawnpore Street",
    "iso:country":"GB",
    "sg:address":"14 Cawnpore Street",
    "sg:city":"London",
    "sg:classifiers":[
        {
            "category":"Bars & Pubs",
            "type":"Food & Drink"
        }
    ],
    "sg:phone":"+44 20 8670 2844",
    "sg:postcode":"SE19 1PF",
    "sg:province":"Greater London",
    "sg:tags":[
        "pubs",
        "inn"
    ],
    "wof:name":"The Railway Bell",
    "wof:placetype":"venue"
},
  "geometry": {"coordinates":[-0.0815460011,51.4224281311],"type":"Point"}
}