{
  "type": "Feature",
  "properties": {
    "addr:full":"11 Olympia Arcade, High St Kirkcaldy Fife KY1 1QF",
    "addr:housenumber":"11",
    "addr:postcode":"ky1 1qf",
    "addr:street":"Olympia;High St",
    "iso:country":"GB",
    "sg:address":"11 Olympia Arcade, High St",
    "sg:city":"Kirkcaldy",
    "sg:classifiers":[
        {
            "category":"Shopping",
            "subcategory":"Department Store",
            "type":"Retail Goods"
        }
    ],
    "sg:postcode":"KY1 1QF",
    "sg:province":"Fife",
    "wof:name":"Living Room Crafts",
    "wof:placetype":"venue"
},
  "geometry": {"coordinates":[-3.1630289555,56.1095962524],"type":"Point"}
}