{
  "type": "Feature",
  "properties": {
    "addr:full":"M1 Motorway Southbound Sheffield South Yorkshire S26 7XR",
    "addr:postcode":"s26 7xr",
    "addr:street":"M1 Motorway Southbound",
    "iso:country":"GB",
    "sg:address":"M1 Motorway Southbound",
    "sg:city":"Sheffield",
    "sg:classifiers":[
        {
            "category":"Autos & Motor Vehicles",
            "subcategory":"Fuel & Gas Station",
            "type":"Retail Goods"
        }
    ],
    "sg:phone":"+44 114 251 1035",
    "sg:postcode":"S26 7XR",
    "sg:province":"South Yorkshire",
    "sg:tags":[
        "hr",
        "petrol"
    ],
    "wof:name":"Woodall South",
    "wof:placetype":"venue"
},
  "geometry": {"coordinates":[-1.283904,53.310024],"type":"Point"}
}