{
  "type": "Feature",
  "properties": {
    "addr:full":"Admin Buildings, Admin Road, Knowsley Industrial Park North Liverpool Lancashire L33 7TX",
    "addr:postcode":"l33 7tx",
    "addr:street":"Admin Road;Industrial Park North",
    "iso:country":"GB",
    "sg:address":"Admin Buildings, Admin Road, Knowsley Industrial Park North",
    "sg:city":"Liverpool",
    "sg:classifiers":[
        {
            "category":"Communications",
            "subcategory":"Newspaper",
            "type":"Services"
        }
    ],
    "sg:phone":"+44 151 547 2000",
    "sg:postcode":"L33 7TX",
    "sg:province":"Lancashire",
    "sg:tags":[
        "magazine"
    ],
    "wof:name":"C O S Distribution",
    "wof:placetype":"venue"
},
  "geometry": {"coordinates":[-2.8572440147,53.4785346985],"type":"Point"}
}