{
  "type": "Feature",
  "properties": {
    "addr:full":"234a Old Christchurch Road Bournemouth Dorset BH1 1PE",
    "addr:housenumber":"234a",
    "addr:postcode":"bh1 1pe",
    "addr:street":"Old Christchurch Road",
    "iso:country":"GB",
    "sg:address":"234a Old Christchurch Road",
    "sg:city":"Bournemouth",
    "sg:classifiers":[
        {
            "category":"Home & Garden",
            "subcategory":"Kitchen Supply",
            "type":"Retail Goods"
        }
    ],
    "sg:phone":"+44 1202 293455",
    "sg:postcode":"BH1 1PE",
    "sg:province":"Dorset",
    "sg:tags":[
        "equipment",
        "bakery"
    ],
    "wof:name":"Timothy Bye",
    "wof:placetype":"venue"
},
  "geometry": {"coordinates":[-1.86942,50.722195],"type":"Point"}
}