{
  "type": "Feature",
  "properties": {
    "addr:full":"The Maltings, Shaddongate Carlisle Cumbria CA2 5TU",
    "addr:postcode":"ca2 5tu",
    "addr:street":"The;Shaddongate",
    "iso:country":"GB",
    "sg:address":"The Maltings, Shaddongate",
    "sg:city":"Carlisle",
    "sg:classifiers":[
        {
            "category":"Home & Garden",
            "subcategory":"Furniture",
            "type":"Retail Goods"
        }
    ],
    "sg:phone":"+44 1228 598889",
    "sg:postcode":"CA2 5TU",
    "sg:province":"Cumbria",
    "wof:name":"Charles Smith",
    "wof:placetype":"venue"
},
  "geometry": {"coordinates":[-2.9461688995,54.8911552429],"type":"Point"}
}