{
  "type": "Feature",
  "properties": {
    "addr:full":"119 Charles Street Leicester Leicestershire LE1 1FA",
    "addr:housenumber":"119",
    "addr:postcode":"le1 1fa",
    "addr:street":"Charles Street",
    "iso:country":"GB",
    "sg:address":"119 Charles Street",
    "sg:city":"Leicester",
    "sg:classifiers":[
        {
            "category":"Shopping",
            "subcategory":"Clothing, Apparel, & Fashions",
            "type":"Retail Goods"
        },
        {
            "category":"Shopping",
            "subcategory":"Beauty & Cosmetics",
            "type":"Retail Goods"
        }
    ],
    "sg:phone":"+44 116 251 4393",
    "sg:postcode":"LE1 1FA",
    "sg:province":"Leicestershire",
    "sg:tags":[
        "product",
        "accessory"
    ],
    "wof:name":"Stabana Cultural Products",
    "wof:placetype":"venue"
},
  "geometry": {"coordinates":[-1.1295820475,52.6341781616],"type":"Point"}
}