{
  "type": "Feature",
  "properties": {
    "addr:full":"8 The Meads East Grinstead East Sussex RH19 4DF",
    "addr:housenumber":"8",
    "addr:postcode":"rh19 4df",
    "addr:street":"The Meads",
    "iso:country":"GB",
    "sg:address":"8 The Meads",
    "sg:city":"East Grinstead",
    "sg:classifiers":[
        {
            "category":"Professional",
            "subcategory":"Accounting & Tax Preparation",
            "type":"Services"
        }
    ],
    "sg:phone":"+44 1342 322648",
    "sg:postcode":"RH19 4DF",
    "sg:province":"East Sussex",
    "sg:tags":[
        "accountant"
    ],
    "wof:name":"Peter Roberts Accounting Services",
    "wof:placetype":"venue"
},
  "geometry": {"coordinates":[-0.01237,51.116348],"type":"Point"}
}