{
  "type": "Feature",
  "properties": {
    "iso:country":"GB",
    "sg:address":"Yews Farm, Seighford",
    "sg:city":"Stafford",
    "sg:classifiers":[
        {
            "category":"Home & Garden",
            "subcategory":"Garden Supply",
            "type":"Retail Goods"
        },
        {
            "category":"Farming",
            "subcategory":"Farm",
            "type":"Manufacturing & Wholesale Goods"
        }
    ],
    "sg:phone":"+44 1785 282321",
    "sg:postcode":"ST18 9PQ",
    "sg:province":"Staffordshire",
    "sg:tags":[
        "mixed",
        "bulb",
        "crop",
        "grower"
    ],
    "wof:name":"Fred C Waterfall",
    "wof:placetype":"venue"
},
  "geometry": {"coordinates":[-2.177216,52.822403],"type":"Point"}
}