{
  "type": "Feature",
  "properties": {
    "iso:country":"GB",
    "sg:address":"110 -111 Northgate",
    "sg:city":"Canterbury",
    "sg:classifiers":[
        {
            "category":"Personal",
            "subcategory":"Beauty Salon",
            "type":"Services"
        }
    ],
    "sg:phone":"+44 1227 762831",
    "sg:postcode":"CT1 1BH",
    "sg:province":"Kent",
    "sg:tags":[
        "unisex",
        "hairdresser"
    ],
    "wof:name":"Geneve Hair Salon",
    "wof:placetype":"venue"
},
  "geometry": {"coordinates":[1.0851329565,51.2830657959],"type":"Point"}
}