{
  "type": "Feature",
  "properties": {
    "addr:full":"132-134 High Street, Harborne Birmingham West Midlands B17 9NN",
    "addr:housenumber":"132-134",
    "addr:postcode":"b17 9nn",
    "addr:street":"High Street",
    "iso:country":"GB",
    "sg:address":"132-134 High Street, Harborne",
    "sg:city":"Birmingham",
    "sg:classifiers":[
        {
            "category":"Fast Food",
            "type":"Food & Drink"
        },
        {
            "category":"Restaurant",
            "type":"Food & Drink"
        }
    ],
    "sg:phone":"+44 121 427 8303",
    "sg:postcode":"B17 9NN",
    "sg:province":"West Midlands",
    "sg:tags":[
        "away",
        "-",
        "american",
        "take"
    ],
    "wof:name":"McDonald's Restaurants Ltd",
    "wof:placetype":"venue"
},
  "geometry": {"coordinates":[-1.9471440315,52.4592323303],"type":"Point"}
}