{
  "type": "Feature",
  "properties": {
    "addr:full":"14 Crouchmans Av Southend On Sea Essex SS3 0DQ",
    "addr:housenumber":"14",
    "addr:postcode":"ss3 0dq",
    "addr:street":"Av Southend On Sea",
    "iso:country":"GB",
    "sg:address":"14 Crouchmans Av",
    "sg:city":"Southend On Sea",
    "sg:classifiers":[
        {
            "category":"Home & Garden",
            "subcategory":"Carpets & Floor Coverings",
            "type":"Retail Goods"
        }
    ],
    "sg:phone":"+44 1702 219745",
    "sg:postcode":"SS3 0DQ",
    "sg:province":"Essex",
    "sg:tags":[
        "carpets",
        "rug",
        "matting"
    ],
    "wof:name":"Peter Fitz-Gibbon",
    "wof:placetype":"venue"
},
  "geometry": {"coordinates":[0.802954,51.552582],"type":"Point"}
}