{
  "type": "Feature",
  "properties": {
    "iso:country":"GB",
    "sg:address":"42 Crumstone Court, Longmeadows Estate",
    "sg:city":"Newcastle-upon-tyne",
    "sg:classifiers":[
        {
            "category":"Utilities",
            "subcategory":"Recycling",
            "type":"Services"
        },
        {
            "category":"Home & Garden",
            "subcategory":"Hardware",
            "type":"Retail Goods"
        }
    ],
    "sg:phone":"+44 191 268 9483",
    "sg:postcode":"NE12 6SZ",
    "sg:province":"Tyne and Wear",
    "sg:tags":[
        "equipment",
        "heating",
        "sale"
    ],
    "wof:name":"J R Maintenance",
    "wof:placetype":"venue"
},
  "geometry": {"coordinates":[-1.5585520267,55.0376205444],"type":"Point"}
}