{
  "type": "Feature",
  "properties": {
    "iso:country":"GB",
    "sg:address":"Box Office, 31 Coventry Street",
    "sg:city":"London",
    "sg:classifiers":[
        {
            "category":"Arts & Performance",
            "subcategory":"Theater",
            "type":"Entertainment"
        }
    ],
    "sg:phone":"+44 20 7839 5972",
    "sg:postcode":"W1D 6AS",
    "sg:province":"Greater London",
    "sg:tags":[
        "hall",
        "theatre",
        "concert"
    ],
    "wof:name":"Prince of Wales Theatre",
    "wof:placetype":"venue"
},
  "geometry": {"coordinates":[-0.131599,51.510281],"type":"Point"}
}