{
  "type": "Feature",
  "properties": {
    "addr:full":"2 Blackmoor Bideford Somerset BS22 6LB",
    "addr:housenumber":"2",
    "addr:postcode":"bs22 6lb",
    "addr:street":"Blackmoor",
    "iso:country":"GB",
    "sg:address":"2 Blackmoor",
    "sg:city":"Bideford",
    "sg:classifiers":[
        {
            "category":"Professional",
            "subcategory":"Management & Consulting",
            "type":"Services"
        }
    ],
    "sg:postcode":"BS22 6LB",
    "sg:province":"Somerset",
    "sg:tags":[
        "consultant",
        "business"
    ],
    "wof:name":"A.P. Gilbert Consultancy Ltd",
    "wof:placetype":"venue"
},
  "geometry": {"coordinates":[-2.92166,51.360088],"type":"Point"}
}