{
  "type": "Feature",
  "properties": {
    "addr:full":"Unit 4b Newbury Berkshire RG14 5RQ",
    "addr:housenumber":"unit 4b",
    "addr:postcode":"rg14 5rq",
    "iso:country":"GB",
    "sg:address":"Unit 4b",
    "sg:city":"Newbury",
    "sg:classifiers":[
        {
            "category":"Manufacturing",
            "subcategory":"Petroleum Products",
            "type":"Manufacturing & Wholesale Goods"
        }
    ],
    "sg:postcode":"RG14 5RQ",
    "sg:province":"Berkshire",
    "sg:tags":[
        "double",
        "glazing"
    ],
    "wof:name":"Chevron Systems (Southern) Ltd.",
    "wof:placetype":"venue"
},
  "geometry": {"coordinates":[-1.3258719444,51.405872345],"type":"Point"}
}