{
  "type": "Feature",
  "properties": {
    "addr:full":"70 Market Street Penryn Cornwall TR10 8BH",
    "addr:housenumber":"70",
    "addr:postcode":"tr10 8bh",
    "addr:street":"Market Street",
    "iso:country":"GB",
    "sg:address":"70 Market Street",
    "sg:city":"Penryn",
    "sg:classifiers":[
        {
            "category":"Food & Beverages",
            "subcategory":"Fruits & Vegetables",
            "type":"Retail Goods"
        }
    ],
    "sg:phone":"+44 1326 373815",
    "sg:postcode":"TR10 8BH",
    "sg:province":"Cornwall",
    "sg:tags":[
        "greengrocer"
    ],
    "wof:name":"The Orange Pip",
    "wof:placetype":"venue"
},
  "geometry": {"coordinates":[-5.104809,50.168575],"type":"Point"}
}