{
  "type": "Feature",
  "properties": {
    "addr:full":"Hurst Farm, Lower Hirst Huddersfield West Yorkshire HD3 3TG",
    "addr:housenumber":"hurst",
    "addr:postcode":"hd3 3tg",
    "addr:street":"Lower;West",
    "iso:country":"GB",
    "sg:address":"Hurst Farm, Lower Hirst",
    "sg:city":"Huddersfield",
    "sg:classifiers":[
        {
            "category":"Home & Garden",
            "subcategory":"Garden Supply",
            "type":"Retail Goods"
        }
    ],
    "sg:phone":"+44 1484 653617",
    "sg:postcode":"HD3 3TG",
    "sg:province":"West Yorkshire",
    "sg:tags":[
        "turfing"
    ],
    "wof:name":"Whitakers Turf Supplies Ltd.",
    "wof:placetype":"venue"
},
  "geometry": {"coordinates":[-1.85718,53.65757],"type":"Point"}
}