{
  "type": "Feature",
  "properties": {
    "addr:full":"Nursery Lane, Fengate Peterborough Cambridgeshire PE1 4BU",
    "addr:postcode":"pe1 4bu",
    "addr:street":"Nursery Lane Fengate",
    "iso:country":"GB",
    "sg:address":"Nursery Lane, Fengate",
    "sg:city":"Peterborough",
    "sg:classifiers":[
        {
            "category":"Retail",
            "subcategory":"Auto Rental",
            "type":"Services"
        },
        {
            "category":"Retail",
            "subcategory":"Storage",
            "type":"Services"
        }
    ],
    "sg:phone":"+44 1733 555661",
    "sg:postcode":"PE1 4BU",
    "sg:province":"Cambridgeshire",
    "sg:tags":[
        "truck",
        "hire",
        "van",
        "household",
        "removal"
    ],
    "wof:name":"Peterborough Self Storage Centre Ltd.",
    "wof:placetype":"venue"
},
  "geometry": {"coordinates":[-0.2248000056,52.5923995972],"type":"Point"}
}