{
  "type": "Feature",
  "properties": {
    "iso:country":"GB",
    "sg:address":"Unit 6 1 & 6 2 Trostre Industrial Park",
    "sg:city":"Llanelli",
    "sg:classifiers":[
        {
            "category":"Food & Beverages",
            "subcategory":"Bakery",
            "type":"Retail Goods"
        }
    ],
    "sg:phone":"+44 1554 773923",
    "sg:postcode":"SA14 9UU",
    "sg:province":"Carmarthenshire",
    "sg:tags":[
        "shop",
        "baker"
    ],
    "wof:name":"David Jenkins Ltd",
    "wof:placetype":"venue"
},
  "geometry": {"coordinates":[-4.146611,51.678715],"type":"Point"}
}