{
  "type": "Feature",
  "properties": {
    "addr:full":"Prestwood Road Wolverhampton Staffordshire WV11 1RD",
    "addr:postcode":"wv11 1rd",
    "addr:street":"Prestwood Road",
    "iso:country":"GB",
    "sg:address":"Prestwood Road",
    "sg:city":"Wolverhampton",
    "sg:classifiers":[
        {
            "category":"Education",
            "subcategory":"School",
            "type":"Public Place"
        },
        {
            "category":"Government",
            "subcategory":"Office",
            "type":"Public Place"
        }
    ],
    "sg:postcode":"WV11 1RD",
    "sg:province":"Staffordshire",
    "sg:tags":[
        "local",
        "authority"
    ],
    "wof:name":"Wolverhampton City Council",
    "wof:placetype":"venue"
},
  "geometry": {"coordinates":[-2.0986089706,52.6034660339],"type":"Point"}
}