{
  "type": "Feature",
  "properties": {
    "iso:country":"GB",
    "sg:address":"113 Doncaster Road",
    "sg:city":"Barnsley",
    "sg:classifiers":[
        {
            "category":"Shopping",
            "subcategory":"Used Merchandise",
            "type":"Retail Goods"
        }
    ],
    "sg:phone":"+44 1226 206611",
    "sg:postcode":"S70 1UF",
    "sg:province":"South Yorkshire",
    "sg:tags":[
        "furniture"
    ],
    "wof:name":"Used Furniture Centre",
    "wof:placetype":"venue"
},
  "geometry": {"coordinates":[-1.469168,53.547916],"type":"Point"}
}