{
  "type": "Feature",
  "properties": {
    "iso:country":"GB",
    "sg:address":"2 Queens Terrace",
    "sg:city":"Ayr",
    "sg:classifiers":[
        {
            "category":"Education",
            "subcategory":"Music School",
            "type":"Public Place"
        }
    ],
    "sg:postcode":"KA7 1DU",
    "sg:province":"South Ayrshire",
    "wof:name":"The Music Box",
    "wof:placetype":"venue"
},
  "geometry": {"coordinates":[-4.640018,55.461876],"type":"Point"}
}