{
  "type": "Feature",
  "properties": {
    "addr:full":"Clinton Rd Redruth Cornwall TR15 2LP",
    "addr:postcode":"tr15 2lp",
    "addr:street":"Clinton Rd",
    "iso:country":"GB",
    "sg:address":"Clinton Rd",
    "sg:city":"Redruth",
    "sg:classifiers":[
        {
            "category":"Place Of Worship",
            "type":"Public Place"
        }
    ],
    "sg:phone":"+44 1209 215258",
    "sg:postcode":"TR15 2LP",
    "sg:province":"Cornwall",
    "wof:name":"St Andrews C Of E Church",
    "wof:placetype":"venue"
},
  "geometry": {"coordinates":[-5.2251491547,50.2306594849],"type":"Point"}
}