{
  "type": "Feature",
  "properties": {
    "addr:full":"Brewery Road Cambridge Cambridgeshire CB2 4HG",
    "addr:postcode":"cb2 4hg",
    "addr:street":"Brewery Road",
    "iso:country":"GB",
    "sg:address":"Brewery Road",
    "sg:city":"Cambridge",
    "sg:classifiers":[
        {
            "category":"Professional",
            "subcategory":"Management & Consulting",
            "type":"Services"
        },
        {
            "category":"Professional",
            "subcategory":"Engineering",
            "type":"Services"
        }
    ],
    "sg:phone":"+44 1223 832851",
    "sg:postcode":"CB2 4HG",
    "sg:province":"Cambridgeshire",
    "sg:tags":[
        "fire",
        "consultant",
        "protection"
    ],
    "wof:name":"Dixon International Group Ltd.",
    "wof:placetype":"venue"
},
  "geometry": {"coordinates":[0.1842000037,52.1110191345],"type":"Point"}
}