{
  "type": "Feature",
  "properties": {
    "iso:country":"GB",
    "sg:address":"94 Boldon Lane",
    "sg:city":"South Shields",
    "sg:classifiers":[
        {
            "category":"Communications",
            "type":"Services"
        }
    ],
    "sg:phone":"+44 191 455 9493",
    "sg:postcode":"NE34 0AT",
    "sg:province":"Tyne and Wear",
    "sg:tags":[
        "tv",
        "video",
        "radio"
    ],
    "wof:name":"Grahams T V",
    "wof:placetype":"venue"
},
  "geometry": {"coordinates":[-1.43989,54.972916],"type":"Point"}
}