{
  "type": "Feature",
  "properties": {
    "addr:full":"Fieldhead Shopping Centre, 16 Legrams Lane Bradford West Yorkshire BD7 1ND",
    "addr:housenumber":"16",
    "addr:postcode":"bd7 1nd",
    "addr:street":"Legrams Lane",
    "iso:country":"GB",
    "sg:address":"Fieldhead Shopping Centre, 16 Legrams Lane",
    "sg:city":"Bradford",
    "sg:classifiers":[
        {
            "category":"Food & Beverages",
            "subcategory":"Supermarket",
            "type":"Retail Goods"
        }
    ],
    "sg:phone":"+44 1274 371113",
    "sg:postcode":"BD7 1ND",
    "sg:province":"West Yorkshire",
    "wof:name":"Haqs International Ltd.",
    "wof:placetype":"venue"
},
  "geometry": {"coordinates":[-1.77171,53.793079],"type":"Point"}
}