{
  "type": "Feature",
  "properties": {
    "addr:full":"28-30 Camden High Street London Greater London NW1 0JH",
    "addr:housenumber":"28-30",
    "addr:postcode":"nw1 0jh",
    "addr:street":"Camden High Street",
    "iso:country":"GB",
    "sg:address":"28-30 Camden High Street",
    "sg:city":"London",
    "sg:classifiers":[
        {
            "category":"Bars & Pubs",
            "type":"Food & Drink"
        }
    ],
    "sg:phone":"+44 20 7209 2472",
    "sg:postcode":"NW1 0JH",
    "sg:province":"Greater London",
    "sg:tags":[
        "pubs",
        "inn"
    ],
    "wof:name":"Cobden Arms",
    "wof:placetype":"venue"
},
  "geometry": {"coordinates":[-0.135838,51.536129],"type":"Point"}
}