{
  "type": "Feature",
  "properties": {
    "addr:full":"Tithe Farm, Laxfield Road, Fressingfield Diss Norfolk IP21 5PY",
    "addr:housenumber":"tithe",
    "addr:postcode":"ip21 5py",
    "addr:street":"Laxfield Road",
    "iso:country":"GB",
    "sg:address":"Tithe Farm, Laxfield Road, Fressingfield",
    "sg:city":"Diss",
    "sg:classifiers":[
        {
            "category":"Farming",
            "subcategory":"Livestock Farm",
            "type":"Manufacturing & Wholesale Goods"
        }
    ],
    "sg:phone":"+44 1379 586297",
    "sg:postcode":"IP21 5PY",
    "sg:province":"Norfolk",
    "sg:tags":[
        "others"
    ],
    "wof:name":"I Smith",
    "wof:placetype":"venue"
},
  "geometry": {"coordinates":[1.318783,52.347141],"type":"Point"}
}