{
  "type": "Feature",
  "properties": {
    "addr:full":"60 Eastbank Street Southport Lancashire PR8 1ES",
    "addr:housenumber":"60",
    "addr:postcode":"pr8 1es",
    "addr:street":"Eastbank Street",
    "iso:country":"GB",
    "sg:address":"60 Eastbank Street",
    "sg:city":"Southport",
    "sg:classifiers":[
        {
            "category":"Cinema",
            "subcategory":"Movie Rental",
            "type":"Entertainment"
        }
    ],
    "sg:postcode":"PR8 1ES",
    "sg:province":"Lancashire",
    "sg:tags":[
        "video",
        "library"
    ],
    "wof:name":"Videoworld",
    "wof:placetype":"venue"
},
  "geometry": {"coordinates":[-3.004014,53.644379],"type":"Point"}
}