{
  "type": "Feature",
  "properties": {
    "iso:country":"GB",
    "sg:address":"Kings Valley Trading Estate, Yew Street",
    "sg:city":"Stockport",
    "sg:classifiers":[
        {
            "category":"Wholesale",
            "subcategory":"Non-durable Goods",
            "type":"Manufacturing & Wholesale Goods"
        }
    ],
    "sg:phone":"+44 161 476 4618",
    "sg:postcode":"SK4 2JZ",
    "sg:province":"Cheshire",
    "sg:tags":[
        "carry",
        "wholesaler",
        "cash"
    ],
    "wof:name":"Booker Cash & Carry Ltd",
    "wof:placetype":"venue"
},
  "geometry": {"coordinates":[-2.1772389412,53.4094963074],"type":"Point"}
}