{
  "type": "Feature",
  "properties": {
    "iso:country":"GB",
    "sg:address":"83a Stockport Rd",
    "sg:city":"Cheadle",
    "sg:classifiers":[
        {
            "category":"Autos & Motor Vehicles",
            "subcategory":"Fuel & Gas Station",
            "type":"Retail Goods"
        }
    ],
    "sg:phone":"+44 161 428 7351",
    "sg:postcode":"SK8 2AJ",
    "sg:province":"Cheshire",
    "sg:tags":[
        "petrol",
        "filling"
    ],
    "wof:name":"Red Lion Filling Station",
    "wof:placetype":"venue"
},
  "geometry": {"coordinates":[-2.207755,53.395412],"type":"Point"}
}