{
  "type": "Feature",
  "properties": {
    "addr:full":"Marine House, 63 Popham Street Nottingham Nottinghamshire NG1 7JD",
    "addr:housenumber":"63",
    "addr:postcode":"ng1 7jd",
    "addr:street":"Popham Street",
    "iso:country":"GB",
    "sg:address":"Marine House, 63 Popham Street",
    "sg:city":"Nottingham",
    "sg:classifiers":[
        {
            "category":"Professional",
            "subcategory":"Management & Consulting",
            "type":"Services"
        }
    ],
    "sg:phone":"+44 115 958 2829",
    "sg:postcode":"NG1 7JD",
    "sg:province":"Nottinghamshire",
    "sg:tags":[
        "consultant",
        "business"
    ],
    "wof:name":"J D F Group Ltd.",
    "wof:placetype":"venue"
},
  "geometry": {"coordinates":[-1.144659,52.949245],"type":"Point"}
}