{
  "type": "Feature",
  "properties": {
    "iso:country":"GB",
    "sg:address":"Dolcoed",
    "sg:city":"Llanrhystud",
    "sg:classifiers":[
        {
            "category":"Building & Trades",
            "subcategory":"Equipment Rental",
            "type":"Services"
        }
    ],
    "sg:postcode":"SY23 5DN",
    "sg:province":"Ceredigion",
    "sg:tags":[
        "plant",
        "machinery"
    ],
    "wof:name":"H A Jones",
    "wof:placetype":"venue"
},
  "geometry": {"coordinates":[-4.1406488419,52.3066596985],"type":"Point"}
}