{
  "type": "Feature",
  "properties": {
    "iso:country":"GB",
    "sg:address":"11 Hawley Road, Wilmington",
    "sg:city":"Dartford",
    "sg:classifiers":[
        {
            "category":"Shopping",
            "subcategory":"News",
            "type":"Retail Goods"
        }
    ],
    "sg:postcode":"DA1 1NP",
    "sg:province":"Kent",
    "sg:tags":[
        "newsagent"
    ],
    "wof:name":"Umar Enterprises",
    "wof:placetype":"venue"
},
  "geometry": {"coordinates":[0.215546,51.43404],"type":"Point"}
}