{
  "type": "Feature",
  "properties": {
    "addr:full":"15 Commodore Road Lowestoft Suffolk NR32 3NE",
    "addr:housenumber":"15",
    "addr:postcode":"nr32 3ne",
    "addr:street":"Commodore Road",
    "iso:country":"GB",
    "sg:address":"15 Commodore Road",
    "sg:city":"Lowestoft",
    "sg:classifiers":[
        {
            "category":"Bars & Pubs",
            "type":"Food & Drink"
        },
        {
            "category":"Community Center",
            "subcategory":"Social",
            "type":"Public Place"
        }
    ],
    "sg:phone":"+44 1502 565955",
    "sg:postcode":"NR32 3NE",
    "sg:province":"Suffolk",
    "sg:tags":[
        "pubs",
        "house",
        "inn",
        "activity"
    ],
    "wof:name":"The Commodore",
    "wof:placetype":"venue"
},
  "geometry": {"coordinates":[1.7138409615,52.4775047302],"type":"Point"}
}