{
  "type": "Feature",
  "properties": {
    "iso:country":"GB",
    "sg:address":"105 High Street",
    "sg:city":"Honiton",
    "sg:classifiers":[
        {
            "category":"Real Estate",
            "subcategory":"Real Estate Agent",
            "type":"Services"
        }
    ],
    "sg:phone":"+44 1404 42456",
    "sg:postcode":"EX14 1PE",
    "sg:province":"Devon",
    "wof:name":"Humberts",
    "wof:placetype":"venue"
},
  "geometry": {"coordinates":[-3.189011097,50.7998161316],"type":"Point"}
}