{
  "type": "Feature",
  "properties": {
    "addr:full":"111 Churchfield Harlow Essex CM20 3DF",
    "addr:housenumber":"111",
    "addr:postcode":"cm20 3df",
    "addr:street":"Churchfield",
    "iso:country":"GB",
    "sg:address":"111 Churchfield",
    "sg:city":"Harlow",
    "sg:classifiers":[
        {
            "category":"Building & Trades",
            "subcategory":"Plumbing",
            "type":"Services"
        }
    ],
    "sg:postcode":"CM20 3DF",
    "sg:province":"Essex",
    "sg:tags":[
        "heating"
    ],
    "wof:name":"A Atlas",
    "wof:placetype":"venue"
},
  "geometry": {"coordinates":[0.123453,51.774734],"type":"Point"}
}