{
  "type": "Feature",
  "properties": {
    "iso:country":"GB",
    "sg:address":"Belle Isle",
    "sg:city":"Windermere",
    "sg:classifiers":[
        {
            "category":"Banks & Credit Unions",
            "subcategory":"Financial Services",
            "type":"Services"
        }
    ],
    "sg:phone":"+44 15394 48730",
    "sg:postcode":"LA23 1BG",
    "sg:province":"Cumbria",
    "sg:tags":[
        "consultant"
    ],
    "wof:name":"Repair Invoice Discounting Ltd.",
    "wof:placetype":"venue"
},
  "geometry": {"coordinates":[-2.911915,54.391647],"type":"Point"}
}