{
  "type": "Feature",
  "properties": {
    "addr:full":"The Lodge, Dooley Lane, Marple Stockport Cheshire SK6 7EJ",
    "addr:postcode":"sk6 7ej",
    "addr:street":"Dooley Lane",
    "iso:country":"GB",
    "sg:address":"The Lodge, Dooley Lane, Marple",
    "sg:city":"Stockport",
    "sg:classifiers":[
        {
            "category":"Transit Center",
            "subcategory":"Passenger",
            "type":"Transportation"
        },
        {
            "category":"Retail",
            "subcategory":"Pet Boarding",
            "type":"Services"
        }
    ],
    "sg:phone":"+44 161 427 7858",
    "sg:postcode":"SK6 7EJ",
    "sg:province":"Cheshire",
    "sg:tags":[
        "kennel",
        "catteries"
    ],
    "wof:name":"Lodge Boarding",
    "wof:placetype":"venue"
},
  "geometry": {"coordinates":[-2.0948638916,53.3958053589],"type":"Point"}
}