{
  "type": "Feature",
  "properties": {
    "addr:full":"63a London Rd Sevenoaks Kent TN13 1AU",
    "addr:housenumber":"63a",
    "addr:postcode":"tn13 1au",
    "addr:street":"London Rd",
    "iso:country":"GB",
    "sg:address":"63a London Rd",
    "sg:city":"Sevenoaks",
    "sg:classifiers":[
        {
            "category":"Professional",
            "subcategory":"Business Services",
            "type":"Services"
        }
    ],
    "sg:phone":"+44 1732 740430",
    "sg:postcode":"TN13 1AU",
    "sg:province":"Kent",
    "sg:tags":[
        "import",
        "export",
        "agent"
    ],
    "wof:name":"Richard.H Lacey",
    "wof:placetype":"venue"
},
  "geometry": {"coordinates":[0.1902740002,51.2720184326],"type":"Point"}
}