{
  "type": "Feature",
  "properties": {
    "addr:full":"Hilltown Farm, Peter Tavy Tavistock Devon PL19 9NB",
    "addr:housenumber":"tavy",
    "addr:postcode":"pl19 9nb",
    "addr:street":"Hilltown",
    "iso:country":"GB",
    "sg:address":"Hilltown Farm, Peter Tavy",
    "sg:city":"Tavistock",
    "sg:classifiers":[
        {
            "category":"Farming",
            "subcategory":"Livestock Farm",
            "type":"Manufacturing & Wholesale Goods"
        }
    ],
    "sg:postcode":"PL19 9NB",
    "sg:province":"Devon",
    "sg:tags":[
        "others"
    ],
    "wof:name":"R A Littlejohns",
    "wof:placetype":"venue"
},
  "geometry": {"coordinates":[-4.100562,50.579411],"type":"Point"}
}