{
  "type": "Feature",
  "properties": {
    "addr:full":"58 Warton Road London Greater London E15 2JY",
    "addr:housenumber":"58",
    "addr:postcode":"e15 2jy",
    "addr:street":"Warton Road",
    "iso:country":"GB",
    "sg:address":"58 Warton Road",
    "sg:city":"London",
    "sg:classifiers":[
        {
            "category":"Shopping",
            "type":"Retail Goods"
        }
    ],
    "sg:postcode":"E15 2JY",
    "sg:province":"Greater London",
    "sg:tags":[
        "part",
        "accessory"
    ],
    "wof:name":"Multi Car Spares",
    "wof:placetype":"venue"
},
  "geometry": {"coordinates":[-0.0082660001,51.5366096497],"type":"Point"}
}