{
  "type": "Feature",
  "properties": {
    "iso:country":"GB",
    "sg:address":"2 Waterloo Terrace",
    "sg:city":"Bridgnorth",
    "sg:classifiers":[
        {
            "category":"Professional",
            "subcategory":"Art Services",
            "type":"Services"
        }
    ],
    "sg:postcode":"WV16 4EG",
    "sg:province":"Shropshire",
    "sg:tags":[
        "framing"
    ],
    "wof:name":"Maws Gallery",
    "wof:placetype":"venue"
},
  "geometry": {"coordinates":[-2.443159,52.539619],"type":"Point"}
}