{
  "type": "Feature",
  "properties": {
    "addr:full":"12 Sandhill Rise, Auckley Doncaster Lincolnshire DN9 3PD",
    "addr:housenumber":"12",
    "addr:postcode":"dn9 3pd",
    "addr:street":"Sandhill Rise",
    "iso:country":"GB",
    "sg:address":"12 Sandhill Rise, Auckley",
    "sg:city":"Doncaster",
    "sg:classifiers":[
        {
            "category":"Professional",
            "subcategory":"Art Services",
            "type":"Services"
        },
        {
            "category":"Building & Trades",
            "subcategory":"Construction",
            "type":"Services"
        }
    ],
    "sg:phone":"+44 1302 770092",
    "sg:postcode":"DN9 3PD",
    "sg:province":"Lincolnshire",
    "sg:tags":[
        "decorator",
        "painter"
    ],
    "wof:name":"Peter Chatfield",
    "wof:placetype":"venue"
},
  "geometry": {"coordinates":[-1.0214600563,53.5049362183],"type":"Point"}
}