{
  "type": "Feature",
  "properties": {
    "iso:country":"GB",
    "sg:address":"357 Grn Lanes, Palmers Grn",
    "sg:city":"London",
    "sg:classifiers":[
        {
            "category":"Professional",
            "subcategory":"Business Services",
            "type":"Services"
        }
    ],
    "sg:phone":"+44 20 8882 5191",
    "sg:postcode":"N13 4JG",
    "sg:province":"Greater London",
    "sg:tags":[
        "tile",
        "stockist"
    ],
    "wof:name":"Tile King Ltd",
    "wof:placetype":"venue"
},
  "geometry": {"coordinates":[-0.10767,51.619041],"type":"Point"}
}