{
  "type": "Feature",
  "properties": {
    "addr:full":"The Red And White House, 1 Hope Drive, The Park Nottingham Nottinghamshire NG7 1DL",
    "addr:housenumber":"1",
    "addr:postcode":"ng7 1dl",
    "addr:street":"Hope Drive",
    "iso:country":"GB",
    "sg:address":"The Red And White House, 1 Hope Drive, The Park",
    "sg:city":"Nottingham",
    "sg:classifiers":[
        {
            "category":"Real Estate",
            "subcategory":"Architect",
            "type":"Services"
        }
    ],
    "sg:phone":"+44 115 950 9450",
    "sg:postcode":"NG7 1DL",
    "sg:province":"Nottinghamshire",
    "wof:name":"Bsp Architects Ltd.",
    "wof:placetype":"venue"
},
  "geometry": {"coordinates":[-1.1568369865,52.9482841492],"type":"Point"}
}