{
  "type": "Feature",
  "properties": {
    "iso:country":"GB",
    "sg:address":"83 Fore Street, Bovey Tracey",
    "sg:city":"Newton Abbot",
    "sg:classifiers":[
        {
            "category":"Bars & Pubs",
            "type":"Food & Drink"
        }
    ],
    "sg:phone":"+44 1626 832248",
    "sg:postcode":"TQ13 9AB",
    "sg:province":"Devon",
    "sg:tags":[
        "pubs",
        "inn"
    ],
    "wof:name":"The King of Prussia",
    "wof:placetype":"venue"
},
  "geometry": {"coordinates":[-3.672963,50.594517],"type":"Point"}
}