{
  "type": "Feature",
  "properties": {
    "addr:full":"Over Hailes Haddington East Lothian EH41 3SB",
    "addr:postcode":"eh41 3sb",
    "addr:street":"Over Hailes",
    "iso:country":"GB",
    "sg:address":"Over Hailes",
    "sg:city":"Haddington",
    "sg:classifiers":[
        {
            "category":"Freight",
            "type":"Transportation"
        }
    ],
    "sg:phone":"+44 1620 861515",
    "sg:postcode":"EH41 3SB",
    "sg:province":"East Lothian",
    "sg:tags":[
        "haulage",
        "road"
    ],
    "wof:name":"Lothian Lift & Shift",
    "wof:placetype":"venue"
},
  "geometry": {"coordinates":[-2.776574,55.955471],"type":"Point"}
}