{
  "type": "Feature",
  "properties": {
    "addr:full":"34 Market Street Wellingborough Northamptonshire NN8 1AT",
    "addr:housenumber":"34",
    "addr:postcode":"nn8 1at",
    "addr:street":"Market Street",
    "iso:country":"GB",
    "sg:address":"34 Market Street",
    "sg:city":"Wellingborough",
    "sg:classifiers":[
        {
            "category":"Shopping",
            "subcategory":"Clothing, Apparel, & Fashions",
            "type":"Retail Goods"
        }
    ],
    "sg:phone":"+44 1933 223216",
    "sg:postcode":"NN8 1AT",
    "sg:province":"Northamptonshire",
    "sg:tags":[
        "wear",
        "leisure"
    ],
    "wof:name":"Alan George Menswear Ltd.",
    "wof:placetype":"venue"
},
  "geometry": {"coordinates":[-0.692041,52.302052],"type":"Point"}
}