{
  "type": "Feature",
  "properties": {
    "iso:country":"GB",
    "sg:address":"89 Leigh Park Road",
    "sg:city":"Bradford-on-avon",
    "sg:classifiers":[
        {
            "category":"Shopping",
            "subcategory":"Tobacco",
            "type":"Retail Goods"
        }
    ],
    "sg:postcode":"BA15 1TG",
    "sg:province":"Wiltshire",
    "sg:tags":[
        "confectioner",
        "tobacconist"
    ],
    "wof:name":"Deals of Devizes Ltd",
    "wof:placetype":"venue"
},
  "geometry": {"coordinates":[-2.251578,51.35434],"type":"Point"}
}