{
  "type": "Feature",
  "properties": {
    "addr:full":"38 Briar Gro Leigh Lancashire WN7 5QZ",
    "addr:housenumber":"38",
    "addr:postcode":"wn7 5qz",
    "addr:street":"Briar Gro Leigh",
    "iso:country":"GB",
    "sg:address":"38 Briar Gro",
    "sg:city":"Leigh",
    "sg:classifiers":[
        {
            "category":"Building & Trades",
            "subcategory":"Construction",
            "type":"Services"
        }
    ],
    "sg:phone":"+44 1942 673355",
    "sg:postcode":"WN7 5QZ",
    "sg:province":"Lancashire",
    "sg:tags":[
        "decorator",
        "painter"
    ],
    "wof:name":"W A Coan & Son",
    "wof:placetype":"venue"
},
  "geometry": {"coordinates":[-2.5226039886,53.5099906921],"type":"Point"}
}