{
  "type": "Feature",
  "properties": {
    "iso:country":"GB",
    "sg:address":"121 Carsic Rd",
    "sg:city":"Sutton In Ashfield",
    "sg:classifiers":[
        {
            "category":"Building & Trades",
            "subcategory":"Construction",
            "type":"Services"
        }
    ],
    "sg:phone":"+44 1623 517244",
    "sg:postcode":"NG17 2BQ",
    "sg:province":"Nottinghamshire",
    "sg:tags":[
        "decorator",
        "painter"
    ],
    "wof:name":"G T Decor",
    "wof:placetype":"venue"
},
  "geometry": {"coordinates":[-1.2692240477,53.1333274841],"type":"Point"}
}