{
  "type": "Feature",
  "properties": {
    "iso:country":"GB",
    "sg:address":"86 Hoe Street, Walthamstow",
    "sg:city":"London",
    "sg:classifiers":[
        {
            "category":"Food & Beverages",
            "subcategory":"Specialty",
            "type":"Retail Goods"
        },
        {
            "category":"Health Services",
            "subcategory":"Podiatrist",
            "type":"Services"
        }
    ],
    "sg:phone":"+44 20 8520 6016",
    "sg:postcode":"E17 4QS",
    "sg:province":"Greater London",
    "sg:tags":[
        "podiatrists",
        "retailer",
        "chiropodist"
    ],
    "wof:name":"C B Morris",
    "wof:placetype":"venue"
},
  "geometry": {"coordinates":[-0.0203750003,51.5887336731],"type":"Point"}
}