{
  "type": "Feature",
  "properties": {
    "addr:full":"23 High Street, Wroughton Swindon Wiltshire SN4 9JX",
    "addr:housenumber":"23",
    "addr:postcode":"sn4 9jx",
    "addr:street":"High Street",
    "iso:country":"GB",
    "sg:address":"23 High Street, Wroughton",
    "sg:city":"Swindon",
    "sg:classifiers":[
        {
            "category":"Real Estate",
            "subcategory":"Surveying",
            "type":"Services"
        }
    ],
    "sg:phone":"+44 1793 813110",
    "sg:postcode":"SN4 9JX",
    "sg:province":"Wiltshire",
    "sg:tags":[
        "surveyor",
        "quantity"
    ],
    "wof:name":"H M W Consultants",
    "wof:placetype":"venue"
},
  "geometry": {"coordinates":[-1.7962470055,51.5226402283],"type":"Point"}
}