{
  "type": "Feature",
  "properties": {
    "addr:full":"21 The Parade, Swinton Shop Centre Manchester Greater Manchester M27 4BH",
    "addr:housenumber":"21;shop",
    "addr:postcode":"m27 4bh",
    "addr:street":"The Parade",
    "iso:country":"GB",
    "sg:address":"21 The Parade, Swinton Shop Centre",
    "sg:city":"Manchester",
    "sg:classifiers":[
        {
            "category":"Food & Beverages",
            "subcategory":"Liquor & Beverages",
            "type":"Retail Goods"
        }
    ],
    "sg:phone":"+44 161 793 1141",
    "sg:postcode":"M27 4BH",
    "sg:province":"Greater Manchester",
    "sg:tags":[
        "beer",
        "spirit",
        "wines"
    ],
    "wof:name":"LiquorZone",
    "wof:placetype":"venue"
},
  "geometry": {"coordinates":[-2.338889,53.511478],"type":"Point"}
}