{
  "type": "Feature",
  "properties": {
    "addr:full":"Channelsea Business Centre, Canning Road London Greater London E15 3ND",
    "addr:postcode":"e15 3nd",
    "addr:street":"Canning Road",
    "iso:country":"GB",
    "sg:address":"Channelsea Business Centre, Canning Road",
    "sg:city":"London",
    "sg:classifiers":[
        {
            "category":"Banks & Credit Unions",
            "subcategory":"Bank",
            "type":"Services"
        },
        {
            "category":"Banks & Credit Unions",
            "subcategory":"Financial Services",
            "type":"Services"
        }
    ],
    "sg:phone":"+44 1245 281098",
    "sg:postcode":"E15 3ND",
    "sg:province":"Greater London",
    "sg:tags":[
        "adviser",
        "institution"
    ],
    "wof:name":"Lau's Finance & Property",
    "wof:placetype":"venue"
},
  "geometry": {"coordinates":[0.00396,51.530529],"type":"Point"}
}