{
  "type": "Feature",
  "properties": {
    "addr:full":"76 Maes-ty-canol, Baglan Port Talbot Neath Port Talbot SA12 8UP",
    "addr:housenumber":"76",
    "addr:postcode":"sa12 8up",
    "addr:street":"Maes-Ty-Canol Baglan Port Talbot",
    "iso:country":"GB",
    "sg:address":"76 Maes-ty-canol, Baglan",
    "sg:city":"Port Talbot",
    "sg:classifiers":[
        {
            "category":"Professional",
            "subcategory":"Computer Services",
            "type":"Services"
        }
    ],
    "sg:phone":"+44 1639 822049",
    "sg:postcode":"SA12 8UP",
    "sg:province":"Neath Port Talbot",
    "sg:tags":[
        "system",
        "software"
    ],
    "wof:name":"J.P Surridge",
    "wof:placetype":"venue"
},
  "geometry": {"coordinates":[-3.8018898964,51.613407135],"type":"Point"}
}