{
  "type": "Feature",
  "properties": {
    "addr:full":"Smoke House Yard, 44-46 St John Street London Greater London EC1M 4DF",
    "addr:housenumber":"44-46",
    "addr:postcode":"ec1m 4df",
    "addr:street":"St John Street",
    "iso:country":"GB",
    "sg:address":"Smoke House Yard, 44-46 St John Street",
    "sg:city":"London",
    "sg:classifiers":[
        {
            "category":"Professional",
            "subcategory":"Advertising",
            "type":"Services"
        }
    ],
    "sg:phone":"+44 20 7250 1144",
    "sg:postcode":"EC1M 4DF",
    "sg:province":"Greater London",
    "sg:tags":[
        "agency"
    ],
    "wof:name":"The Porter Partnership Ltd.",
    "wof:placetype":"venue"
},
  "geometry": {"coordinates":[-0.1012099981,51.5209388733],"type":"Point"}
}