{
  "type": "Feature",
  "properties": {
    "addr:full":"30 Victoria Street, Shirebrook Mansfield Derbyshire NG20 8AQ",
    "addr:housenumber":"30",
    "addr:postcode":"ng20 8aq",
    "addr:street":"Victoria Street",
    "iso:country":"GB",
    "sg:address":"30 Victoria Street, Shirebrook",
    "sg:city":"Mansfield",
    "sg:classifiers":[
        {
            "category":"Shopping",
            "subcategory":"Clothing, Apparel, & Fashions",
            "type":"Retail Goods"
        }
    ],
    "sg:phone":"+44 1623 742603",
    "sg:postcode":"NG20 8AQ",
    "sg:province":"Derbyshire",
    "sg:tags":[
        "shop"
    ],
    "wof:name":"Carousel Fashions",
    "wof:placetype":"venue"
},
  "geometry": {"coordinates":[-1.2137099504,53.2041358948],"type":"Point"}
}