{
  "type": "Feature",
  "properties": {
    "iso:country":"GB",
    "sg:address":"Trewilym Uchaf, Eglwyswrw",
    "sg:city":"Crymych",
    "sg:classifiers":[
        {
            "category":"Farming",
            "subcategory":"Livestock Farm",
            "type":"Manufacturing & Wholesale Goods"
        },
        {
            "category":"Farming",
            "subcategory":"Farm",
            "type":"Manufacturing & Wholesale Goods"
        }
    ],
    "sg:phone":"+44 1239 891213",
    "sg:postcode":"SA41 3PY",
    "sg:province":"Pembrokeshire",
    "sg:tags":[
        "mixed",
        "crop",
        "others"
    ],
    "wof:name":"R K Davies",
    "wof:placetype":"venue"
},
  "geometry": {"coordinates":[-4.648454,51.971241],"type":"Point"}
}