{
  "type": "Feature",
  "properties": {
    "iso:country":"GB",
    "sg:address":"Manor Farm, Langrick",
    "sg:city":"Boston",
    "sg:classifiers":[
        {
            "category":"Farming",
            "subcategory":"Livestock Farm",
            "type":"Manufacturing & Wholesale Goods"
        }
    ],
    "sg:phone":"+44 1205 280251",
    "sg:postcode":"PE22 7AB",
    "sg:province":"Lincolnshire",
    "sg:tags":[
        "others"
    ],
    "wof:name":"Langrick Piggeries Ltd",
    "wof:placetype":"venue"
},
  "geometry": {"coordinates":[-0.1071270034,53.0221481323],"type":"Point"}
}