{
  "type": "Feature",
  "properties": {
    "iso:country":"GB",
    "sg:address":"76 Crown Road",
    "sg:city":"Great Yarmouth",
    "sg:classifiers":[
        {
            "category":"Travel",
            "subcategory":"Hotels & Motels",
            "type":"Entertainment"
        }
    ],
    "sg:phone":"+44 1493 857182",
    "sg:postcode":"NR30 2JH",
    "sg:province":"Norfolk",
    "sg:tags":[
        "house",
        "guest"
    ],
    "wof:name":"Trelawne Guest House",
    "wof:placetype":"venue"
},
  "geometry": {"coordinates":[1.734173,52.606083],"type":"Point"}
}