{
  "type": "Feature",
  "properties": {
    "iso:country":"GB",
    "sg:address":"12 Conway Road",
    "sg:city":"Maidstone",
    "sg:classifiers":[
        {
            "category":"Travel",
            "subcategory":"Hotels & Motels",
            "type":"Entertainment"
        }
    ],
    "sg:phone":"+44 1622 688287",
    "sg:postcode":"ME16 0HD",
    "sg:province":"Kent",
    "sg:tags":[
        "house",
        "guest"
    ],
    "wof:name":"Conway House",
    "wof:placetype":"venue"
},
  "geometry": {"coordinates":[0.493738,51.283966],"type":"Point"}
}