{
  "type": "Feature",
  "properties": {
    "addr:full":"Norwich House, Commerical Road Southampton Hampshire SO15 1GX",
    "addr:postcode":"so15 1gx",
    "addr:street":"Commerical Road",
    "iso:country":"GB",
    "sg:address":"Norwich House, Commerical Road",
    "sg:city":"Southampton",
    "sg:classifiers":[
        {
            "category":"Banks & Credit Unions",
            "subcategory":"Bank",
            "type":"Services"
        }
    ],
    "sg:phone":"+44 23 8072 3287",
    "sg:postcode":"SO15 1GX",
    "sg:province":"Hampshire",
    "wof:name":"H S B C Bank Plc",
    "wof:placetype":"venue"
},
  "geometry": {"coordinates":[-1.407319,50.909939],"type":"Point"}
}