{
  "type": "Feature",
  "properties": {
    "iso:country":"GB",
    "sg:address":"8 Whitehall Street",
    "sg:city":"Dundee",
    "sg:classifiers":[
        {
            "category":"Home & Garden",
            "subcategory":"Home Furnishings",
            "type":"Retail Goods"
        },
        {
            "category":"Home & Garden",
            "subcategory":"Building Materials",
            "type":"Retail Goods"
        }
    ],
    "sg:phone":"+44 1382 203698",
    "sg:postcode":"DD1 4AF",
    "sg:province":"Dundee City",
    "sg:tags":[
        "furnishers",
        "bathroom",
        "planner",
        "kitchen"
    ],
    "wof:name":"Dolphin Bathrooms",
    "wof:placetype":"venue"
},
  "geometry": {"coordinates":[-2.9706149101,56.4598960876],"type":"Point"}
}