{
  "type": "Feature",
  "properties": {
    "iso:country":"GB",
    "sg:address":"23 Champneys Walk Grange Rd, Newnham",
    "sg:city":"Cambridge",
    "sg:classifiers":[
        {
            "category":"Professional",
            "subcategory":"Lawyer & Legal Services",
            "type":"Services"
        }
    ],
    "sg:phone":"+44 1223 367267",
    "sg:postcode":"CB3 9AW",
    "sg:province":"Cambridgeshire",
    "sg:tags":[
        "solicitor"
    ],
    "wof:name":"Bracher Rawlins Partnership",
    "wof:placetype":"venue"
},
  "geometry": {"coordinates":[0.1064559966,52.1982688904],"type":"Point"}
}