{
  "type": "Feature",
  "properties": {
    "addr:full":"114-116 Birmingham Road Bromsgrove Worcestershire B61 0DE",
    "addr:housenumber":"114-116",
    "addr:postcode":"b61 0de",
    "addr:street":"Birmingham Road",
    "iso:country":"GB",
    "sg:address":"114-116 Birmingham Road",
    "sg:city":"Bromsgrove",
    "sg:classifiers":[
        {
            "category":"Autos & Motor Vehicles",
            "subcategory":"Automobile Sales",
            "type":"Retail Goods"
        }
    ],
    "sg:phone":"+44 1527 575957",
    "sg:postcode":"B61 0DE",
    "sg:province":"Worcestershire",
    "sg:tags":[
        "car"
    ],
    "wof:name":"Johnsons Cars Ltd.",
    "wof:placetype":"venue"
},
  "geometry": {"coordinates":[-2.052832,52.341091],"type":"Point"}
}