{
  "type": "Feature",
  "properties": {
    "addr:full":"32-36 Low Glencairn Street Kilmarnock East Ayrshire KA1 4DD",
    "addr:housenumber":"32-36",
    "addr:postcode":"ka1 4dd",
    "addr:street":"Low Glencairn Street",
    "iso:country":"GB",
    "sg:address":"32-36 Low Glencairn Street",
    "sg:city":"Kilmarnock",
    "sg:classifiers":[
        {
            "category":"Autos & Motor Vehicles",
            "subcategory":"Auto Supplies",
            "type":"Retail Goods"
        }
    ],
    "sg:phone":"+44 1563 523536",
    "sg:postcode":"KA1 4DD",
    "sg:province":"East Ayrshire",
    "sg:tags":[
        "exhaust",
        "absorber",
        "shock"
    ],
    "wof:name":"Kwik-Fit",
    "wof:placetype":"venue"
},
  "geometry": {"coordinates":[-4.496969223,55.5999984741],"type":"Point"}
}