{
  "type": "Feature",
  "properties": {
    "addr:full":"Chaucer House London Greater London W1S 3NS",
    "addr:postcode":"w1s 3ns",
    "iso:country":"GB",
    "sg:address":"Chaucer House",
    "sg:city":"London",
    "sg:classifiers":[
        {
            "category":"Landmark",
            "subcategory":"Tourist Information",
            "type":"Public Place"
        }
    ],
    "sg:phone":"+44 20 7629 0461",
    "sg:postcode":"W1S 3NS",
    "sg:province":"Greater London",
    "wof:name":"Austrian National Tourist Office",
    "wof:placetype":"venue"
},
  "geometry": {"coordinates":[-0.087914,51.50737],"type":"Point"}
}