{
  "type": "Feature",
  "properties": {
    "iso:country":"GB",
    "sg:address":"The Coach Ho, 55 Drayton Green",
    "sg:city":"West Ealing",
    "sg:classifiers":[
        {
            "category":"Utilities",
            "type":"Services"
        }
    ],
    "sg:phone":"+44 20 8998 2969",
    "sg:postcode":"W13 0JE",
    "sg:province":"Greater London",
    "sg:tags":[
        "internet"
    ],
    "wof:name":"Swim Communications",
    "wof:placetype":"venue"
},
  "geometry": {"coordinates":[-0.31995,51.51366],"type":"Point"}
}