{
  "type": "Feature",
  "properties": {
    "addr:full":"13 Bondgate Derby Leicestershire DE74 2NS",
    "addr:housenumber":"13",
    "addr:postcode":"de74 2ns",
    "addr:street":"Bondgate",
    "iso:country":"GB",
    "sg:address":"13 Bondgate",
    "sg:city":"Derby",
    "sg:classifiers":[
        {
            "category":"Manufacturing",
            "subcategory":"Building Materials",
            "type":"Manufacturing & Wholesale Goods"
        }
    ],
    "sg:phone":"+44 1332 812813",
    "sg:postcode":"DE74 2NS",
    "sg:province":"Leicestershire",
    "sg:tags":[
        "extrusion"
    ],
    "wof:name":"Terraplaf",
    "wof:placetype":"venue"
},
  "geometry": {"coordinates":[-1.3405040503,52.841960907],"type":"Point"}
}