{
  "type": "Feature",
  "properties": {
    "iso:country":"GB",
    "sg:address":"1 Homs Road",
    "sg:city":"Ross-on-wye",
    "sg:classifiers":[
        {
            "category":"Building & Trades",
            "subcategory":"Equipment Rental",
            "type":"Services"
        }
    ],
    "sg:phone":"+44 1989 767654",
    "sg:postcode":"HR9 7DE",
    "sg:province":"Gloucestershire",
    "sg:tags":[
        "hire",
        "centre"
    ],
    "wof:name":"Brandon Hire Plc",
    "wof:placetype":"venue"
},
  "geometry": {"coordinates":[-2.58639,51.919044],"type":"Point"}
}