{
  "type": "Feature",
  "properties": {
    "iso:country":"GB",
    "sg:address":"1 High Street, Milford On Sea",
    "sg:city":"Lymington",
    "sg:classifiers":[
        {
            "category":"Restaurant",
            "type":"Food & Drink"
        }
    ],
    "sg:phone":"+44 1590 642611",
    "sg:postcode":"SO41 0QF",
    "sg:province":"Hampshire",
    "sg:tags":[
        "french"
    ],
    "wof:name":"The Mill House Restaurant",
    "wof:placetype":"venue"
},
  "geometry": {"coordinates":[-1.591711,50.725292],"type":"Point"}
}