{
  "type": "Feature",
  "properties": {
    "iso:country":"GB",
    "sg:address":"Unit 1 Thornhill, Hull Road, Grimston",
    "sg:city":"York",
    "sg:classifiers":[
        {
            "category":"Manufacturing",
            "subcategory":"Rubber & Plastics",
            "type":"Manufacturing & Wholesale Goods"
        }
    ],
    "sg:phone":"+44 1904 488733",
    "sg:postcode":"YO19 5HE",
    "sg:province":"North Yorkshire",
    "sg:tags":[
        "product"
    ],
    "wof:name":"Boretree Plastics",
    "wof:placetype":"venue"
},
  "geometry": {"coordinates":[-1.007034,53.956921],"type":"Point"}
}