{
  "type": "Feature",
  "properties": {
    "addr:full":"22 Clover Road, Market Deeping Peterborough Cambridgeshire PE6 8JU",
    "addr:housenumber":"22",
    "addr:postcode":"pe6 8ju",
    "addr:street":"Clover Road Market",
    "iso:country":"GB",
    "sg:address":"22 Clover Road, Market Deeping",
    "sg:city":"Peterborough",
    "sg:classifiers":[
        {
            "category":"Retail",
            "subcategory":"Driving School",
            "type":"Services"
        }
    ],
    "sg:phone":"+44 1778 346656",
    "sg:postcode":"PE6 8JU",
    "sg:province":"Cambridgeshire",
    "wof:name":"Steven Boyd",
    "wof:placetype":"venue"
},
  "geometry": {"coordinates":[-0.3146379888,52.6765823364],"type":"Point"}
}