{
  "type": "Feature",
  "properties": {
    "addr:full":"50 Plymouth Road Buckfastleigh Devon TQ11 0DH",
    "addr:housenumber":"50",
    "addr:postcode":"tq11 0dh",
    "addr:street":"Plymouth Road",
    "iso:country":"GB",
    "sg:address":"50 Plymouth Road",
    "sg:city":"Buckfastleigh",
    "sg:classifiers":[
        {
            "category":"Bars & Pubs",
            "type":"Food & Drink"
        }
    ],
    "sg:postcode":"TQ11 0DH",
    "sg:province":"Devon",
    "sg:tags":[
        "pubs",
        "inn"
    ],
    "wof:name":"The George",
    "wof:placetype":"venue"
},
  "geometry": {"coordinates":[-3.7848789692,50.4750862122],"type":"Point"}
}