{
  "type": "Feature",
  "properties": {
    "addr:full":"Telford Town Centre Telford Shropshire TF3 4JQ",
    "addr:postcode":"tf3 4jq",
    "iso:country":"GB",
    "sg:address":"Telford Town Centre",
    "sg:city":"Telford",
    "sg:classifiers":[
        {
            "category":"Sports & Exercise",
            "subcategory":"Ice Rink",
            "type":"Entertainment"
        },
        {
            "category":"Government",
            "subcategory":"Office",
            "type":"Public Place"
        }
    ],
    "sg:phone":"+44 1952 291511",
    "sg:postcode":"TF3 4JQ",
    "sg:province":"Shropshire",
    "sg:tags":[
        "skating",
        "local"
    ],
    "wof:name":"Telford Ice Rink",
    "wof:placetype":"venue"
},
  "geometry": {"coordinates":[-2.4441590309,52.6739387512],"type":"Point"}
}