{
  "type": "Feature",
  "properties": {
    "addr:full":"2 The Square, Riverhead Sevenoaks Kent TN13 2AA",
    "addr:housenumber":"2",
    "addr:postcode":"tn13 2aa",
    "addr:street":"The Square",
    "iso:country":"GB",
    "sg:address":"2 The Square, Riverhead",
    "sg:city":"Sevenoaks",
    "sg:classifiers":[
        {
            "category":"Shopping",
            "subcategory":"Pharmacy",
            "type":"Retail Goods"
        }
    ],
    "sg:postcode":"TN13 2AA",
    "sg:province":"Kent",
    "sg:tags":[
        "pharmacist",
        "chemist"
    ],
    "wof:name":"Tayzana Ltd.",
    "wof:placetype":"venue"
},
  "geometry": {"coordinates":[0.1696549952,51.2836608887],"type":"Point"}
}