{
  "type": "Feature",
  "properties": {
    "addr:full":"5 Woodfield Street, Morriston Swansea Swansea SA6 8AQ",
    "addr:housenumber":"5",
    "addr:postcode":"sa6 8aq",
    "addr:street":"Woodfield Street",
    "iso:country":"GB",
    "sg:address":"5 Woodfield Street, Morriston",
    "sg:city":"Swansea",
    "sg:classifiers":[
        {
            "category":"Home & Garden",
            "subcategory":"Household Appliances",
            "type":"Retail Goods"
        }
    ],
    "sg:phone":"+44 1792 702319",
    "sg:postcode":"SA6 8AQ",
    "sg:province":"Swansea",
    "sg:tags":[
        "electrical"
    ],
    "wof:name":"C Williams",
    "wof:placetype":"venue"
},
  "geometry": {"coordinates":[-3.924624,51.666187],"type":"Point"}
}