{
  "type": "Feature",
  "properties": {
    "iso:country":"GB",
    "sg:address":"12 Huntsman Wood",
    "sg:city":"Liverpool",
    "sg:classifiers":[
        {
            "category":"Building & Trades",
            "subcategory":"Construction",
            "type":"Services"
        }
    ],
    "sg:phone":"+44 151 259 6102",
    "sg:postcode":"L12 0HY",
    "sg:province":"Merseyside",
    "sg:tags":[
        "roofing",
        "contracting"
    ],
    "wof:name":"Stormcheck Roofing Systems",
    "wof:placetype":"venue"
},
  "geometry": {"coordinates":[-2.885798,53.437702],"type":"Point"}
}