{
  "type": "Feature",
  "properties": {
    "iso:country":"GB",
    "sg:address":"12 Newland Gro, Holly Hall",
    "sg:city":"Dudley",
    "sg:classifiers":[
        {
            "category":"Retail",
            "subcategory":"Storage",
            "type":"Services"
        }
    ],
    "sg:phone":"+44 1384 76868",
    "sg:postcode":"DY2 0TJ",
    "sg:province":"West Midlands",
    "sg:tags":[
        "household",
        "activity",
        "domestic",
        "removal"
    ],
    "wof:name":"Dudley Removals",
    "wof:placetype":"venue"
},
  "geometry": {"coordinates":[-2.107965,52.499447],"type":"Point"}
}