{
  "type": "Feature",
  "properties": {
    "iso:country":"GB",
    "sg:address":"25 Ashacre Lane",
    "sg:city":"Worthing",
    "sg:classifiers":[
        {
            "category":"Manufacturing",
            "subcategory":"Wood Products",
            "type":"Manufacturing & Wholesale Goods"
        }
    ],
    "sg:phone":"+44 1903 691212",
    "sg:postcode":"BN13 2DA",
    "sg:province":"West Sussex",
    "sg:tags":[
        "maker",
        "cabinet"
    ],
    "wof:name":"M G Hurst",
    "wof:placetype":"venue"
},
  "geometry": {"coordinates":[-0.394,50.833755],"type":"Point"}
}