{
  "type": "Feature",
  "properties": {
    "addr:full":"Unit B3, Nore Industrial Estate, Hovefields Avenue Basildon Essex SS13 1EB",
    "addr:postcode":"ss13 1eb",
    "addr:street":"Nore Industrial Estate Hovefields Avenue",
    "iso:country":"GB",
    "sg:address":"Unit B3, Nore Industrial Estate, Hovefields Avenue",
    "sg:city":"Basildon",
    "sg:classifiers":[
        {
            "category":"Government",
            "subcategory":"Post Office",
            "type":"Public Place"
        }
    ],
    "sg:phone":"+44 1268 728724",
    "sg:postcode":"SS13 1EB",
    "sg:province":"Essex",
    "sg:tags":[
        "messenger",
        "courier"
    ],
    "wof:name":"Initial Ciy Link Basildon",
    "wof:placetype":"venue"
},
  "geometry": {"coordinates":[0.5189800262,51.5889816284],"type":"Point"}
}