{
  "type": "Feature",
  "properties": {
    "iso:country":"GB",
    "sg:address":"Cops Side Farm, Amsty",
    "sg:city":"Salisbury",
    "sg:classifiers":[
        {
            "category":"Utilities",
            "subcategory":"Refuse",
            "type":"Services"
        }
    ],
    "sg:phone":"+44 1747 871464",
    "sg:postcode":"SP3 5PS",
    "sg:province":"Wiltshire",
    "sg:tags":[
        "disposal",
        "waste"
    ],
    "wof:name":"Rob Beale Liquid Waste",
    "wof:placetype":"venue"
},
  "geometry": {"coordinates":[-2.06244,51.028679],"type":"Point"}
}