{
  "type": "Feature",
  "properties": {
    "addr:full":"50 Great Charles Street Queensway Birmingham West Midlands B3 2BE",
    "addr:housenumber":"50",
    "addr:postcode":"b3 2be",
    "addr:street":"Great Charles Street Queensway",
    "iso:country":"GB",
    "sg:address":"50 Great Charles Street Queensway",
    "sg:city":"Birmingham",
    "sg:classifiers":[
        {
            "category":"Education",
            "subcategory":"Special Training",
            "type":"Public Place"
        }
    ],
    "sg:phone":"+44 121 200 2422",
    "sg:postcode":"B3 2BE",
    "sg:province":"West Midlands",
    "sg:tags":[
        "school",
        "language"
    ],
    "wof:name":"Communicaid-Brunner",
    "wof:placetype":"venue"
},
  "geometry": {"coordinates":[-1.902155,52.482998],"type":"Point"}
}