{
  "type": "Feature",
  "properties": {
    "addr:full":"15 Hope Street Filey North Yorkshire YO14 9DJ",
    "addr:housenumber":"15",
    "addr:postcode":"yo14 9dj",
    "addr:street":"Hope Street",
    "iso:country":"GB",
    "sg:address":"15 Hope Street",
    "sg:city":"Filey",
    "sg:classifiers":[
        {
            "category":"Farming",
            "subcategory":"Fish & Marine Products",
            "type":"Manufacturing & Wholesale Goods"
        }
    ],
    "sg:postcode":"YO14 9DJ",
    "sg:province":"North Yorkshire",
    "sg:tags":[
        "fishmonger"
    ],
    "wof:name":"Ben C Jenkinson",
    "wof:placetype":"venue"
},
  "geometry": {"coordinates":[-0.287191,54.209557],"type":"Point"}
}