{
  "type": "Feature",
  "properties": {
    "iso:country":"GB",
    "sg:address":"Cromwell House, Mill Street",
    "sg:city":"Cannock",
    "sg:classifiers":[
        {
            "category":"Manufacturing",
            "subcategory":"Tools & Machinery",
            "type":"Manufacturing & Wholesale Goods"
        }
    ],
    "sg:postcode":"WS11 3DP",
    "sg:province":"Staffordshire",
    "sg:tags":[
        "society",
        "friendly"
    ],
    "wof:name":"Ancient Order of Foresters",
    "wof:placetype":"venue"
},
  "geometry": {"coordinates":[-2.024399,52.68763],"type":"Point"}
}