{
  "type": "Feature",
  "properties": {
    "iso:country":"GB",
    "sg:address":"All Seasons Nursery, Folkes Lane",
    "sg:city":"Upminster",
    "sg:classifiers":[
        {
            "category":"Building & Trades",
            "subcategory":"Landscaping Services",
            "type":"Services"
        },
        {
            "category":"Building & Trades",
            "subcategory":"Construction",
            "type":"Services"
        }
    ],
    "sg:phone":"+44 1277 225793",
    "sg:postcode":"RM14 1TE",
    "sg:province":"Essex",
    "sg:tags":[
        "contractor",
        "landscape",
        "pool",
        "swimming"
    ],
    "wof:name":"Capital Landscapes",
    "wof:placetype":"venue"
},
  "geometry": {"coordinates":[0.24926,51.556339],"type":"Point"}
}