{
  "type": "Feature",
  "properties": {
    "addr:full":"End House, Field Rd, Ramsey Huntingdon Cambridgeshire PE17 1JH",
    "addr:postcode":"pe17 1jh",
    "addr:street":"Field Rd",
    "iso:country":"GB",
    "sg:address":"End House, Field Rd, Ramsey",
    "sg:city":"Huntingdon",
    "sg:classifiers":[
        {
            "category":"Shopping",
            "type":"Retail Goods"
        }
    ],
    "sg:phone":"+44 1487 710462",
    "sg:postcode":"PE17 1JH",
    "sg:province":"Cambridgeshire",
    "sg:tags":[
        "scientific",
        "apparatus"
    ],
    "wof:name":"Fearn Intracellular Products Ltd",
    "wof:placetype":"venue"
},
  "geometry": {"coordinates":[-0.1069,52.448151],"type":"Point"}
}