{
  "type": "Feature",
  "properties": {
    "iso:country":"GB",
    "sg:address":"31 Leigham Court Road, Streatham",
    "sg:city":"London",
    "sg:classifiers":[
        {
            "category":"Building & Trades",
            "subcategory":"Construction",
            "type":"Services"
        }
    ],
    "sg:postcode":"SW16 2ND",
    "sg:province":"Greater London",
    "sg:tags":[
        "builder"
    ],
    "wof:name":"Ej Prestige Builders Ltd.",
    "wof:placetype":"venue"
},
  "geometry": {"coordinates":[-0.126028,51.437466],"type":"Point"}
}