{
  "type": "Feature",
  "properties": {
    "iso:country":"GB",
    "sg:address":"6 Broadway",
    "sg:city":"Sheerness",
    "sg:classifiers":[
        {
            "category":"Professional",
            "type":"Services"
        }
    ],
    "sg:postcode":"ME12 1AF",
    "sg:province":"Kent",
    "sg:tags":[
        "aircraft",
        "maintenance"
    ],
    "wof:name":"First Professional Aerospace",
    "wof:placetype":"venue"
},
  "geometry": {"coordinates":[0.7624559999,51.4398040771],"type":"Point"}
}