{
  "type": "Feature",
  "properties": {
    "iso:country":"GB",
    "sg:address":"4th Floor",
    "sg:city":"Woking",
    "sg:classifiers":[
        {
            "category":"Professional",
            "subcategory":"Management & Consulting",
            "type":"Services"
        }
    ],
    "sg:postcode":"GU21 5AB",
    "sg:province":"Surrey",
    "sg:tags":[
        "consultant",
        "business"
    ],
    "wof:name":"Jem Management Ltd.",
    "wof:placetype":"venue"
},
  "geometry": {"coordinates":[-0.535919,51.32811],"type":"Point"}
}