{
  "type": "Feature",
  "properties": {
    "iso:country":"GB",
    "sg:address":"Unit 28, Earith Business Park, Meadow Drove",
    "sg:city":"Huntingdon",
    "sg:classifiers":[
        {
            "category":"Building & Trades",
            "subcategory":"Construction",
            "type":"Services"
        }
    ],
    "sg:phone":"+44 1487 741010",
    "sg:postcode":"PE28 3QF",
    "sg:province":"Bedfordshire",
    "sg:tags":[
        "welder"
    ],
    "wof:name":"Fusion Services Ltd.",
    "wof:placetype":"venue"
},
  "geometry": {"coordinates":[0.0441699997,52.3603439331],"type":"Point"}
}