{
  "type": "Feature",
  "properties": {
    "iso:country":"GB",
    "sg:address":"Unit 3, Kents Avenue",
    "sg:city":"Hemel Hempstead",
    "sg:classifiers":[
        {
            "category":"Manufacturing",
            "subcategory":"Wood Products",
            "type":"Manufacturing & Wholesale Goods"
        }
    ],
    "sg:postcode":"HP3 9XH",
    "sg:province":"Hertfordshire",
    "sg:tags":[
        "packaging",
        "crate",
        "pallets"
    ],
    "wof:name":"Kingfisher Tapes Ltd.",
    "wof:placetype":"venue"
},
  "geometry": {"coordinates":[-0.4689339995,51.7361793518],"type":"Point"}
}