{
  "type": "Feature",
  "properties": {
    "iso:country":"GB",
    "sg:address":"Moss Rd",
    "sg:city":"Tillicoultry",
    "sg:classifiers":[
        {
            "category":"Government",
            "subcategory":"Police Station",
            "type":"Public Place"
        }
    ],
    "sg:phone":"+44 1259 750222",
    "sg:postcode":"FK13 6NS",
    "sg:province":"Clackmannanshire",
    "sg:tags":[
        "support"
    ],
    "wof:name":"Tillicoultry Police Station",
    "wof:placetype":"venue"
},
  "geometry": {"coordinates":[-3.74211,56.153267],"type":"Point"}
}