{
  "type": "Feature",
  "properties": {
    "iso:country":"GB",
    "sg:address":"Unit 1 Bowen Indstl Est, Aberbargoed",
    "sg:city":"Bargoed",
    "sg:classifiers":[
        {
            "category":"Building & Trades",
            "subcategory":"Cleaning & Sanitation",
            "type":"Services"
        },
        {
            "category":"Building & Trades",
            "subcategory":"Construction",
            "type":"Services"
        }
    ],
    "sg:postcode":"CF81 9EP",
    "sg:province":"Caerphilly",
    "sg:tags":[
        "builder",
        "steam"
    ],
    "wof:name":"Jenkins,William F,",
    "wof:placetype":"venue"
},
  "geometry": {"coordinates":[-3.221308,51.690517],"type":"Point"}
}