{
  "type": "Feature",
  "properties": {
    "addr:full":"Pearson Road, Sonning Reading Berkshire RG4 6UL",
    "addr:postcode":"rg4 6ul",
    "addr:street":"Pearson Road",
    "iso:country":"GB",
    "sg:address":"Pearson Road, Sonning",
    "sg:city":"Reading",
    "sg:classifiers":[
        {
            "category":"Organizations",
            "subcategory":"Membership Organization",
            "type":"Services"
        }
    ],
    "sg:phone":"+44 118 969 3939",
    "sg:postcode":"RG4 6UL",
    "sg:province":"Berkshire",
    "sg:tags":[
        "club"
    ],
    "wof:name":"Sonning Working Mens Club",
    "wof:placetype":"venue"
},
  "geometry": {"coordinates":[-0.9072849751,51.4730873108],"type":"Point"}
}