{
  "type": "Feature",
  "properties": {
    "iso:country":"GB",
    "sg:address":"Unit 1a Dunkirk Avenue, Greets Grn",
    "sg:city":"West Bromwich",
    "sg:classifiers":[
        {
            "category":"Manufacturing",
            "subcategory":"Metals",
            "type":"Manufacturing & Wholesale Goods"
        }
    ],
    "sg:postcode":"B70 0EP",
    "sg:province":"West Midlands",
    "sg:tags":[
        "steel",
        "stockholder"
    ],
    "wof:name":"D L V Steels Ltd.",
    "wof:placetype":"venue"
},
  "geometry": {"coordinates":[-2.031439,52.521801],"type":"Point"}
}