{
  "type": "Feature",
  "properties": {
    "iso:country":"GB",
    "sg:address":"14 Bower Rd",
    "sg:city":"Harrogate",
    "sg:classifiers":[
        {
            "category":"Professional",
            "subcategory":"Lawyer & Legal Services",
            "type":"Services"
        }
    ],
    "sg:phone":"+44 1423 524174",
    "sg:postcode":"HG1 1BA",
    "sg:province":"North Yorkshire",
    "sg:tags":[
        "advice",
        "counselling"
    ],
    "wof:name":"Youth Enquiry Service",
    "wof:placetype":"venue"
},
  "geometry": {"coordinates":[-1.5383950472,53.9957084656],"type":"Point"}
}