{
  "type": "Feature",
  "properties": {
    "iso:country":"GB",
    "sg:address":"18 Wrawby Street",
    "sg:city":"Brigg",
    "sg:classifiers":[
        {
            "category":"Food & Beverages",
            "subcategory":"Meat & Fish",
            "type":"Retail Goods"
        }
    ],
    "sg:phone":"+44 1652 653111",
    "sg:postcode":"DN20 8JJ",
    "sg:province":"Lincolnshire",
    "sg:tags":[
        "butcher"
    ],
    "wof:name":"Waters & Sons",
    "wof:placetype":"venue"
},
  "geometry": {"coordinates":[-0.4903280139,53.5524024963],"type":"Point"}
}