{
  "type": "Feature",
  "properties": {
    "iso:country":"GB",
    "sg:address":"134 Leylands Road",
    "sg:city":"Burgess Hill",
    "sg:classifiers":[
        {
            "category":"Bars & Pubs",
            "type":"Food & Drink"
        }
    ],
    "sg:phone":"+44 1444 235537",
    "sg:postcode":"RH15 8AB",
    "sg:province":"East Sussex",
    "sg:tags":[
        "pubs",
        "house",
        "inn",
        "public",
        "activity"
    ],
    "wof:name":"The Windmill Inn",
    "wof:placetype":"venue"
},
  "geometry": {"coordinates":[-0.12927,50.963501],"type":"Point"}
}