{
  "type": "Feature",
  "properties": {
    "addr:full":"9 Endcliffe Vale Avenue Sheffield Derbyshire S11 8RX",
    "addr:housenumber":"9",
    "addr:postcode":"s11 8rx",
    "addr:street":"Endcliffe Vale Avenue",
    "iso:country":"GB",
    "sg:address":"9 Endcliffe Vale Avenue",
    "sg:city":"Sheffield",
    "sg:classifiers":[
        {
            "category":"Professional",
            "subcategory":"Management & Consulting",
            "type":"Services"
        }
    ],
    "sg:phone":"+44 114 266 3431",
    "sg:postcode":"S11 8RX",
    "sg:province":"Derbyshire",
    "sg:tags":[
        "consultant",
        "business"
    ],
    "wof:name":"Hotwood Consulting Ltd.",
    "wof:placetype":"venue"
},
  "geometry": {"coordinates":[-1.5044330359,53.3696937561],"type":"Point"}
}