{
  "type": "Feature",
  "properties": {
    "addr:full":"195 Chapel House Road Nelson Lancashire BB9 0QP",
    "addr:housenumber":"195",
    "addr:postcode":"bb9 0qp",
    "addr:street":"Chapel House Road",
    "iso:country":"GB",
    "sg:address":"195 Chapel House Road",
    "sg:city":"Nelson",
    "sg:classifiers":[
        {
            "category":"Shopping",
            "subcategory":"Department Store",
            "type":"Retail Goods"
        },
        {
            "category":"Food & Beverages",
            "subcategory":"Groceries & Convenience Stores",
            "type":"Retail Goods"
        }
    ],
    "sg:phone":"+44 1282 603821",
    "sg:postcode":"BB9 0QP",
    "sg:province":"Lancashire",
    "wof:name":"KEENE'S KORNER",
    "wof:placetype":"venue"
},
  "geometry": {"coordinates":[-2.212818,53.829971],"type":"Point"}
}