{
  "type": "Feature",
  "properties": {
    "iso:country":"GB",
    "sg:address":"Mount Surgery, Margam Rd",
    "sg:city":"Port Talbot",
    "sg:classifiers":[
        {
            "category":"Health Services",
            "subcategory":"Doctor",
            "type":"Services"
        }
    ],
    "sg:phone":"+44 1639 884111",
    "sg:postcode":"SA13 2BN",
    "sg:province":"Neath Port Talbot",
    "sg:tags":[
        "practitioners"
    ],
    "wof:name":"Llewelyn, M H",
    "wof:placetype":"venue"
},
  "geometry": {"coordinates":[-3.7547540665,51.5717315674],"type":"Point"}
}