{
  "type": "Feature",
  "properties": {
    "addr:full":"Gloster Road, Martlesham Heath Ipswich Suffolk IP5 3RJ",
    "addr:postcode":"ip5 3rj",
    "addr:street":"Gloster Road",
    "iso:country":"GB",
    "sg:address":"Gloster Road, Martlesham Heath",
    "sg:city":"Ipswich",
    "sg:classifiers":[
        {
            "category":"Sports & Exercise",
            "subcategory":"Ice Rink",
            "type":"Entertainment"
        },
        {
            "category":"Community Center",
            "type":"Public Place"
        }
    ],
    "sg:phone":"+44 1473 611333",
    "sg:postcode":"IP5 3RJ",
    "sg:province":"Suffolk",
    "sg:tags":[
        "skating",
        "recreation",
        "leisure",
        "centre"
    ],
    "wof:name":"Roller King Kidz Kingdom",
    "wof:placetype":"venue"
},
  "geometry": {"coordinates":[1.2787599564,52.0633583069],"type":"Point"}
}