{
  "type": "Feature",
  "properties": {
    "iso:country":"GB",
    "sg:address":"Office 1 Magistrates Court, Bargate",
    "sg:city":"Christchurch",
    "sg:classifiers":[
        {
            "category":"Organizations",
            "subcategory":"Non-profit Organization",
            "type":"Services"
        }
    ],
    "sg:phone":"+44 1202 484079",
    "sg:postcode":"BH23 1PY",
    "sg:province":"Dorset",
    "sg:tags":[
        "organisation",
        "voluntary",
        "charity"
    ],
    "wof:name":"National Literacy Association",
    "wof:placetype":"venue"
},
  "geometry": {"coordinates":[-1.782179,50.738667],"type":"Point"}
}