{
  "type": "Feature",
  "properties": {
    "iso:country":"GB",
    "sg:address":"16 Bouverie Place, Paddington",
    "sg:city":"London",
    "sg:classifiers":[
        {
            "category":"Bars & Pubs",
            "type":"Food & Drink"
        }
    ],
    "sg:phone":"+44 20 7723 6061",
    "sg:postcode":"W2 1RB",
    "sg:province":"Greater London",
    "sg:tags":[
        "pubs",
        "house",
        "inn",
        "public",
        "activity"
    ],
    "wof:name":"Gresham Inns Ltd",
    "wof:placetype":"venue"
},
  "geometry": {"coordinates":[-0.171651,51.517197],"type":"Point"}
}