{
  "type": "Feature",
  "properties": {
    "iso:country":"GB",
    "sg:address":"Chosen View Road",
    "sg:city":"Cheltenham",
    "sg:classifiers":[
        {
            "category":"Utilities",
            "subcategory":"Refuse",
            "type":"Services"
        }
    ],
    "sg:phone":"+44 1242 520762",
    "sg:postcode":"GL51 9LT",
    "sg:province":"Gloucestershire",
    "sg:tags":[
        "skip",
        "hire"
    ],
    "wof:name":"Ace Mini Skips",
    "wof:placetype":"venue"
},
  "geometry": {"coordinates":[-2.092718,51.916916],"type":"Point"}
}