{
  "type": "Feature",
  "properties": {
    "addr:full":"45 Cotswold Crescent Bury Lancashire BL8 1QF",
    "addr:housenumber":"45",
    "addr:postcode":"bl8 1qf",
    "addr:street":"Cotswold Crescent",
    "iso:country":"GB",
    "sg:address":"45 Cotswold Crescent",
    "sg:city":"Bury",
    "sg:classifiers":[
        {
            "category":"Shopping",
            "subcategory":"Computers & Home Electronics",
            "type":"Retail Goods"
        }
    ],
    "sg:phone":"+44 161 797 9294",
    "sg:postcode":"BL8 1QF",
    "sg:province":"Lancashire",
    "sg:tags":[
        "aerial",
        "television",
        "radio"
    ],
    "wof:name":"D N Installations",
    "wof:placetype":"venue"
},
  "geometry": {"coordinates":[-2.323919,53.597973],"type":"Point"}
}