{
  "type": "Feature",
  "properties": {
    "addr:full":"32 St. Davids Arcade, The Quadrant Swansea Neath Port Talbot SA1 3QW",
    "addr:housenumber":"32",
    "addr:postcode":"sa1 3qw",
    "addr:street":"St. Davids;The Quadrant",
    "iso:country":"GB",
    "sg:address":"32 St. Davids Arcade, The Quadrant",
    "sg:city":"Swansea",
    "sg:classifiers":[
        {
            "category":"Sports & Exercise",
            "subcategory":"Sports Center",
            "type":"Entertainment"
        }
    ],
    "sg:phone":"+44 1792 473552",
    "sg:postcode":"SA1 3QW",
    "sg:province":"Neath Port Talbot",
    "sg:tags":[
        "shop",
        "good"
    ],
    "wof:name":"Nike Shop",
    "wof:placetype":"venue"
},
  "geometry": {"coordinates":[-3.941879034,51.6180801392],"type":"Point"}
}