{
  "type": "Feature",
  "properties": {
    "iso:country":"GB",
    "sg:address":"44 Otley Road, Guiseley",
    "sg:city":"Leeds",
    "sg:classifiers":[
        {
            "category":"Food & Beverages",
            "subcategory":"Meat & Fish",
            "type":"Retail Goods"
        }
    ],
    "sg:phone":"+44 1943 873337",
    "sg:postcode":"LS20 8AH",
    "sg:province":"West Yorkshire",
    "sg:tags":[
        "butcher"
    ],
    "wof:name":"Tony Woods Quality Butchers",
    "wof:placetype":"venue"
},
  "geometry": {"coordinates":[-1.7117029428,53.8736381531],"type":"Point"}
}