{
  "type": "Feature",
  "properties": {
    "addr:full":"Basford House, 29 Augusta Street Llandudno Conwy LL30 2AE",
    "addr:housenumber":"29",
    "addr:postcode":"ll30 2ae",
    "addr:street":"Augusta Street",
    "iso:country":"GB",
    "sg:address":"Basford House, 29 Augusta Street",
    "sg:city":"Llandudno",
    "sg:classifiers":[
        {
            "category":"Professional",
            "subcategory":"Accounting & Tax Preparation",
            "type":"Services"
        }
    ],
    "sg:phone":"+44 1492 870575",
    "sg:postcode":"LL30 2AE",
    "sg:province":"Conwy",
    "sg:tags":[
        "accountant",
        "chartered",
        "activity"
    ],
    "wof:name":"John Pratt & Co",
    "wof:placetype":"venue"
},
  "geometry": {"coordinates":[-3.8187639713,53.3224334717],"type":"Point"}
}