{
  "type": "Feature",
  "properties": {
    "addr:full":"15 The Broadway Loughton Essex IG10 3SP",
    "addr:housenumber":"15",
    "addr:postcode":"ig10 3sp",
    "addr:street":"The Broadway",
    "iso:country":"GB",
    "sg:address":"15 The Broadway",
    "sg:city":"Loughton",
    "sg:classifiers":[
        {
            "category":"Home & Garden",
            "subcategory":"Kitchen Supply",
            "type":"Retail Goods"
        }
    ],
    "sg:phone":"+44 20 8508 7397",
    "sg:postcode":"IG10 3SP",
    "sg:province":"Essex",
    "sg:tags":[
        "equipment",
        "bakery"
    ],
    "wof:name":"Laws The Bakers",
    "wof:placetype":"venue"
},
  "geometry": {"coordinates":[0.082281,51.647369],"type":"Point"}
}