{
  "type": "Feature",
  "properties": {
    "addr:full":"71 Mogul Lane Halesowen West Midlands B63 2QG",
    "addr:housenumber":"71",
    "addr:postcode":"b63 2qg",
    "addr:street":"Mogul Lane",
    "iso:country":"GB",
    "sg:address":"71 Mogul Lane",
    "sg:city":"Halesowen",
    "sg:classifiers":[
        {
            "category":"Shopping",
            "subcategory":"News",
            "type":"Retail Goods"
        }
    ],
    "sg:phone":"+44 1384 566691",
    "sg:postcode":"B63 2QG",
    "sg:province":"West Midlands",
    "sg:tags":[
        "newsagent"
    ],
    "wof:name":"J W & A Green",
    "wof:placetype":"venue"
},
  "geometry": {"coordinates":[-2.102046,52.466064],"type":"Point"}
}