{
  "type": "Feature",
  "properties": {
    "iso:country":"GB",
    "sg:address":"The Grange, 18-21 Church Gate",
    "sg:city":"Newbury",
    "sg:classifiers":[
        {
            "category":"Professional",
            "subcategory":"Management & Consulting",
            "type":"Services"
        }
    ],
    "sg:postcode":"RG13 4PH",
    "sg:province":"Berkshire",
    "sg:tags":[
        "consultant",
        "training"
    ],
    "wof:name":"Media First Ltd.",
    "wof:placetype":"venue"
},
  "geometry": {"coordinates":[-1.32587,51.405869],"type":"Point"}
}