{
  "type": "Feature",
  "properties": {
    "addr:full":"10 Haynes Road Worthing West Sussex BN14 7JY",
    "addr:housenumber":"10",
    "addr:postcode":"bn14 7jy",
    "addr:street":"Haynes Road",
    "iso:country":"GB",
    "sg:address":"10 Haynes Road",
    "sg:city":"Worthing",
    "sg:classifiers":[
        {
            "category":"Building & Trades",
            "subcategory":"Plumbing",
            "type":"Services"
        }
    ],
    "sg:phone":"+44 1903 212627",
    "sg:postcode":"BN14 7JY",
    "sg:province":"West Sussex",
    "sg:tags":[
        "heating"
    ],
    "wof:name":"Robert R Jones",
    "wof:placetype":"venue"
},
  "geometry": {"coordinates":[-0.391259,50.822758],"type":"Point"}
}