{
  "type": "Feature",
  "properties": {
    "iso:country":"GB",
    "sg:address":"252 Newton Road",
    "sg:city":"Rushden",
    "sg:classifiers":[
        {
            "category":"Building & Trades",
            "subcategory":"Construction",
            "type":"Services"
        }
    ],
    "sg:postcode":"NN10 0SY",
    "sg:province":"Bedfordshire",
    "sg:tags":[
        "contractor",
        "paving",
        "driveway"
    ],
    "wof:name":"A W Fuller Groundworks",
    "wof:placetype":"venue"
},
  "geometry": {"coordinates":[-0.569774,52.279732],"type":"Point"}
}