{
  "type": "Feature",
  "properties": {
    "addr:full":"30 Station Street Swaffham Norfolk PE37 7HP",
    "addr:housenumber":"30",
    "addr:postcode":"pe37 7hp",
    "addr:street":"Station Street",
    "iso:country":"GB",
    "sg:address":"30 Station Street",
    "sg:city":"Swaffham",
    "sg:classifiers":[
        {
            "category":"Restaurant",
            "type":"Food & Drink"
        }
    ],
    "sg:phone":"+44 1760 725326",
    "sg:postcode":"PE37 7HP",
    "sg:province":"Norfolk",
    "sg:tags":[
        "indian",
        "-"
    ],
    "wof:name":"Village Tandoori Restaurant",
    "wof:placetype":"venue"
},
  "geometry": {"coordinates":[0.688515,52.650791],"type":"Point"}
}