{
  "type": "Feature",
  "properties": {
    "addr:full":"109 Wilderness Road, Earley Reading Berkshire RG6 5RE",
    "addr:housenumber":"109",
    "addr:postcode":"rg6 5re",
    "addr:street":"Wilderness Road",
    "iso:country":"GB",
    "sg:address":"109 Wilderness Road, Earley",
    "sg:city":"Reading",
    "sg:classifiers":[
        {
            "category":"Health Services",
            "subcategory":"Nursing And Care Facility",
            "type":"Services"
        }
    ],
    "sg:phone":"+44 118 986 1890",
    "sg:postcode":"RG6 5RE",
    "sg:province":"Berkshire",
    "sg:tags":[
        "home"
    ],
    "wof:name":"Court Housing",
    "wof:placetype":"venue"
},
  "geometry": {"coordinates":[-0.9372010231,51.4358825684],"type":"Point"}
}