{
  "type": "Feature",
  "properties": {
    "iso:country":"GB",
    "sg:address":"63 Hilltop Road",
    "sg:city":"Dronfield",
    "sg:classifiers":[
        {
            "category":"Health Services",
            "subcategory":"Health Practitioner",
            "type":"Services"
        }
    ],
    "sg:phone":"+44 1246 414603",
    "sg:postcode":"S18 1UJ",
    "sg:province":"Derbyshire",
    "sg:tags":[
        "physiotherapist"
    ],
    "wof:name":"David Tow",
    "wof:placetype":"venue"
},
  "geometry": {"coordinates":[-1.470055,53.292873],"type":"Point"}
}