{
  "type": "Feature",
  "properties": {
    "iso:country":"GB",
    "sg:address":"70 Queen Street, Morley",
    "sg:city":"Leeds",
    "sg:classifiers":[
        {
            "category":"Personal",
            "subcategory":"Beauty Salon",
            "type":"Services"
        },
        {
            "category":"Personal",
            "subcategory":"Barber",
            "type":"Services"
        }
    ],
    "sg:phone":"+44 113 253 3286",
    "sg:postcode":"LS27 9BP",
    "sg:province":"West Yorkshire",
    "sg:tags":[
        "unisex",
        "hairdresser"
    ],
    "wof:name":"Mayfair Hair Stylists",
    "wof:placetype":"venue"
},
  "geometry": {"coordinates":[-1.604728,53.743805],"type":"Point"}
}