{
  "type": "Feature",
  "properties": {
    "addr:full":"Oxford House, Oxford Chambers Llandrindod Wells Powys LD1 6AG",
    "addr:postcode":"ld1 6ag",
    "iso:country":"GB",
    "sg:address":"Oxford House, Oxford Chambers",
    "sg:city":"Llandrindod Wells",
    "sg:classifiers":[
        {
            "category":"Organizations",
            "subcategory":"Non-profit Organization",
            "type":"Services"
        }
    ],
    "sg:phone":"+44 1597 825020",
    "sg:postcode":"LD1 6AG",
    "sg:province":"Powys",
    "sg:tags":[
        "charitable",
        "organisation",
        "voluntary",
        "charity"
    ],
    "wof:name":"THE LLANDRINDOD WELLS VOLUNTEER BUREAU",
    "wof:placetype":"venue"
},
  "geometry": {"coordinates":[-3.382024,52.241196],"type":"Point"}
}