{
  "type": "Feature",
  "properties": {
    "iso:country":"GB",
    "sg:address":"2 St Giles St",
    "sg:city":"Northampton",
    "sg:classifiers":[
        {
            "category":"Professional",
            "subcategory":"Employment Agencies",
            "type":"Services"
        }
    ],
    "sg:phone":"+44 1604 604646",
    "sg:postcode":"NN1 1JA",
    "sg:province":"Northamptonshire",
    "sg:tags":[
        "consultant"
    ],
    "wof:name":"Barclay West Associates",
    "wof:placetype":"venue"
},
  "geometry": {"coordinates":[-0.89445,52.237068],"type":"Point"}
}