{
  "type": "Feature",
  "properties": {
    "iso:country":"GB",
    "sg:address":"31 Market Place",
    "sg:city":"Poulton-le-fylde",
    "sg:classifiers":[
        {
            "category":"Health Services",
            "subcategory":"Optometrist",
            "type":"Services"
        },
        {
            "category":"Shopping",
            "subcategory":"Optician",
            "type":"Retail Goods"
        }
    ],
    "sg:phone":"+44 1253 882266",
    "sg:postcode":"FY6 7BS",
    "sg:province":"Lancashire",
    "sg:tags":[
        "ophthalmic"
    ],
    "wof:name":"Thomson's Opticians",
    "wof:placetype":"venue"
},
  "geometry": {"coordinates":[-2.992715,53.846462],"type":"Point"}
}