{
  "type": "Feature",
  "properties": {
    "iso:country":"GB",
    "sg:address":"19 St Johns",
    "sg:city":"Worcester",
    "sg:classifiers":[
        {
            "category":"Home & Garden",
            "subcategory":"Carpets & Floor Coverings",
            "type":"Retail Goods"
        }
    ],
    "sg:postcode":"WR2 5AE",
    "sg:province":"Worcestershire",
    "sg:tags":[
        "carpets",
        "rug",
        "matting"
    ],
    "wof:name":"Empsons Carpets",
    "wof:placetype":"venue"
},
  "geometry": {"coordinates":[-2.234354,52.188393],"type":"Point"}
}