{
  "type": "Feature",
  "properties": {
    "iso:country":"GB",
    "sg:address":"Jaguar House, Columbus Quay, Riverside Drive",
    "sg:city":"Liverpool",
    "sg:classifiers":[
        {
            "category":"Autos & Motor Vehicles",
            "subcategory":"Automobile Sales",
            "type":"Retail Goods"
        }
    ],
    "sg:phone":"+44 151 728 2000",
    "sg:postcode":"L3 4ED",
    "sg:province":"Merseyside",
    "sg:tags":[
        "commercial"
    ],
    "wof:name":"Jaguar House (Liverpool) Ltd.",
    "wof:placetype":"venue"
},
  "geometry": {"coordinates":[-2.973139,53.37928],"type":"Point"}
}