{
  "type": "Feature",
  "properties": {
    "addr:full":"52 Denby Grange, Church Langley Harlow Essex CM17 9PZ",
    "addr:housenumber":"52",
    "addr:postcode":"cm17 9pz",
    "addr:street":"Denby Grange",
    "iso:country":"GB",
    "sg:address":"52 Denby Grange, Church Langley",
    "sg:city":"Harlow",
    "sg:classifiers":[
        {
            "category":"Professional",
            "type":"Services"
        }
    ],
    "sg:phone":"+44 1279 320020",
    "sg:postcode":"CM17 9PZ",
    "sg:province":"Essex",
    "sg:tags":[
        "interior",
        "furnishers",
        "designer"
    ],
    "wof:name":"Deborah Montlake Interiors Ltd.",
    "wof:placetype":"venue"
},
  "geometry": {"coordinates":[0.1464699954,51.7676734924],"type":"Point"}
}