{
  "type": "Feature",
  "properties": {
    "addr:full":"2 Pannier Mkt, High St Honiton Devon EX14 1LS",
    "addr:housenumber":"2;mkt",
    "addr:postcode":"ex14 1ls",
    "addr:street":"Pannier;High St",
    "iso:country":"GB",
    "sg:address":"2 Pannier Mkt, High St",
    "sg:city":"Honiton",
    "sg:classifiers":[
        {
            "category":"Shopping",
            "subcategory":"Clothing, Apparel, & Fashions",
            "type":"Retail Goods"
        }
    ],
    "sg:postcode":"EX14 1LS",
    "sg:province":"Devon",
    "sg:tags":[
        "ladieswear"
    ],
    "wof:name":"Wilkinson,O M,",
    "wof:placetype":"venue"
},
  "geometry": {"coordinates":[-3.1969060898,50.7973861694],"type":"Point"}
}