{
  "type": "Feature",
  "properties": {
    "iso:country":"GB",
    "sg:address":"Unit 12 Redbrook Business Park, Wilthorpe Rd",
    "sg:city":"Barnsley",
    "sg:classifiers":[
        {
            "category":"Home & Garden",
            "subcategory":"Building Materials",
            "type":"Retail Goods"
        }
    ],
    "sg:phone":"+44 1226 280833",
    "sg:postcode":"S75 1JN",
    "sg:province":"South Yorkshire",
    "sg:tags":[
        "resin",
        "gum"
    ],
    "wof:name":"Moria Carbotech Ltd",
    "wof:placetype":"venue"
},
  "geometry": {"coordinates":[-1.5020840168,53.5647201538],"type":"Point"}
}