{
  "type": "Feature",
  "properties": {
    "addr:full":"Bromham Rd Bedford Bedfordshire MK40 4AF",
    "addr:postcode":"mk40 4af",
    "addr:street":"Bromham Rd",
    "iso:country":"GB",
    "sg:address":"Bromham Rd",
    "sg:city":"Bedford",
    "sg:classifiers":[
        {
            "category":"Sports & Exercise",
            "subcategory":"Golf",
            "type":"Entertainment"
        }
    ],
    "sg:phone":"+44 1234 353653",
    "sg:postcode":"MK40 4AF",
    "sg:province":"Bedfordshire",
    "sg:tags":[
        "equipment"
    ],
    "wof:name":"Gary Buckle Professional Shop",
    "wof:placetype":"venue"
},
  "geometry": {"coordinates":[-0.485352993,52.1392173767],"type":"Point"}
}