{
  "type": "Feature",
  "properties": {
    "addr:full":"46 Potters Lane, Kiln Farm Milton Keynes Buckinghamshire MK11 3HQ",
    "addr:housenumber":"46",
    "addr:postcode":"mk11 3hq",
    "addr:street":"Potters Lane",
    "iso:country":"GB",
    "sg:address":"46 Potters Lane, Kiln Farm",
    "sg:city":"Milton Keynes",
    "sg:classifiers":[
        {
            "category":"Manufacturing",
            "subcategory":"Metals",
            "type":"Manufacturing & Wholesale Goods"
        }
    ],
    "sg:phone":"+44 1908 319408",
    "sg:postcode":"MK11 3HQ",
    "sg:province":"Buckinghamshire",
    "sg:tags":[
        "work",
        "sheet"
    ],
    "wof:name":"Laserworks Ltd.",
    "wof:placetype":"venue"
},
  "geometry": {"coordinates":[-0.820303,52.048199],"type":"Point"}
}