{
  "type": "Feature",
  "properties": {
    "addr:full":"8 The Boulevard, Balham High Road London Greater London SW17 7BW",
    "addr:housenumber":"8",
    "addr:postcode":"sw17 7bw",
    "addr:street":"The Boulevard;High Road",
    "iso:country":"GB",
    "sg:address":"8 The Boulevard, Balham High Road",
    "sg:city":"London",
    "sg:classifiers":[
        {
            "category":"Real Estate",
            "subcategory":"Real Estate Agent",
            "type":"Services"
        }
    ],
    "sg:phone":"+44 20 8673 8555",
    "sg:postcode":"SW17 7BW",
    "sg:province":"Greater London",
    "wof:name":"Regency Estate Agents",
    "wof:placetype":"venue"
},
  "geometry": {"coordinates":[-0.1547199935,51.440738678],"type":"Point"}
}