{
  "type": "Feature",
  "properties": {
    "iso:country":"GB",
    "sg:address":"136a High Rd",
    "sg:city":"Wood Green",
    "sg:classifiers":[
        {
            "category":"Shopping",
            "subcategory":"Clothing, Apparel, & Fashions",
            "type":"Retail Goods"
        }
    ],
    "sg:phone":"+44 20 8889 9163",
    "sg:postcode":"N22 6EB",
    "sg:province":"Greater London",
    "sg:tags":[
        "shop"
    ],
    "wof:name":"Unisex Jeans Centre",
    "wof:placetype":"venue"
},
  "geometry": {"coordinates":[-0.1082860008,51.5945129395],"type":"Point"}
}