{
  "type": "Feature",
  "properties": {
    "addr:full":"Spode Works, Church Street Stoke-on-trent Staffordshire ST4 1BX",
    "addr:postcode":"st4 1bx",
    "addr:street":"Church Street",
    "iso:country":"GB",
    "sg:address":"Spode Works, Church Street",
    "sg:city":"Stoke-on-trent",
    "sg:classifiers":[
        {
            "category":"Manufacturing",
            "subcategory":"Glass & Minerals",
            "type":"Manufacturing & Wholesale Goods"
        }
    ],
    "sg:phone":"+44 1782 572538",
    "sg:postcode":"ST4 1BX",
    "sg:province":"Staffordshire",
    "sg:tags":[
        "mnfr",
        "glassware",
        "china"
    ],
    "wof:name":"Cgl Realisations Ltd.",
    "wof:placetype":"venue"
},
  "geometry": {"coordinates":[-2.1854600906,53.0051498413],"type":"Point"}
}