{
  "type": "Feature",
  "properties": {
    "addr:full":"12 Lewin Road, Streatham London Greater London SW16 6JR",
    "addr:housenumber":"12",
    "addr:postcode":"sw16 6jr",
    "addr:street":"Lewin Road",
    "iso:country":"GB",
    "sg:address":"12 Lewin Road, Streatham",
    "sg:city":"London",
    "sg:classifiers":[
        {
            "category":"Building & Trades",
            "subcategory":"Cleaning & Sanitation",
            "type":"Services"
        }
    ],
    "sg:phone":"+44 20 8696 7740",
    "sg:postcode":"SW16 6JR",
    "sg:province":"Greater London",
    "sg:tags":[
        "commercial"
    ],
    "wof:name":"Express Cleaning Ltd.",
    "wof:placetype":"venue"
},
  "geometry": {"coordinates":[-0.130695,51.423054],"type":"Point"}
}