{
  "type": "Feature",
  "properties": {
    "addr:full":"8 Rackham Drive Luton Bedfordshire LU3 2AF",
    "addr:housenumber":"8",
    "addr:postcode":"lu3 2af",
    "addr:street":"Rackham Drive",
    "iso:country":"GB",
    "sg:address":"8 Rackham Drive",
    "sg:city":"Luton",
    "sg:classifiers":[
        {
            "category":"Wholesale",
            "subcategory":"Meat",
            "type":"Manufacturing & Wholesale Goods"
        }
    ],
    "sg:phone":"+44 1582 570077",
    "sg:postcode":"LU3 2AF",
    "sg:province":"Bedfordshire",
    "sg:tags":[
        "-"
    ],
    "wof:name":"Acadamy Industrial Supplies",
    "wof:placetype":"venue"
},
  "geometry": {"coordinates":[-0.4287439883,51.9063568115],"type":"Point"}
}