{
  "type": "Feature",
  "properties": {
    "iso:country":"GB",
    "sg:address":"20 East Hill",
    "sg:city":"St Austell",
    "sg:classifiers":[
        {
            "category":"Professional",
            "subcategory":"Lawyer & Legal Services",
            "type":"Services"
        }
    ],
    "sg:phone":"+44 1726 68033",
    "sg:postcode":"PL25 4TR",
    "sg:province":"Cornwall",
    "sg:tags":[
        "solicitor"
    ],
    "wof:name":"Jane David",
    "wof:placetype":"venue"
},
  "geometry": {"coordinates":[-4.789982,50.337608],"type":"Point"}
}