{
  "type": "Feature",
  "properties": {
    "iso:country":"GB",
    "sg:address":"The Workshop, Gilly Lane, Whitecross",
    "sg:city":"Penzance",
    "sg:classifiers":[
        {
            "category":"Health Services",
            "subcategory":"Medical Lab",
            "type":"Services"
        }
    ],
    "sg:phone":"+44 1736 740896",
    "sg:postcode":"TR20 8BZ",
    "sg:province":"Cornwall",
    "sg:tags":[
        "dental"
    ],
    "wof:name":"Kerakraft Dental Laboratory",
    "wof:placetype":"venue"
},
  "geometry": {"coordinates":[-5.464374,50.159645],"type":"Point"}
}