{
  "type": "Feature",
  "properties": {
    "iso:country":"GB",
    "sg:address":"Unit 1 & 2, Monastery Business Centre",
    "sg:city":"Neath",
    "sg:classifiers":[
        {
            "category":"Professional",
            "subcategory":"Engineering",
            "type":"Services"
        }
    ],
    "sg:phone":"+44 1792 815740",
    "sg:postcode":"SA10 7DH",
    "sg:province":"Neath Port Talbot",
    "sg:tags":[
        "contractor",
        "electrical",
        "engineer"
    ],
    "wof:name":"Hayes Electrical Contractors",
    "wof:placetype":"venue"
},
  "geometry": {"coordinates":[-3.827286,51.661556],"type":"Point"}
}