{
  "type": "Feature",
  "properties": {
    "iso:country":"GB",
    "sg:address":"30 Gresham Street",
    "sg:city":"London",
    "sg:classifiers":[
        {
            "category":"Banks & Credit Unions",
            "subcategory":"Investment Brokerage",
            "type":"Services"
        }
    ],
    "sg:phone":"+44 20 7606 6064",
    "sg:postcode":"EC2V 7HT",
    "sg:province":"Greater London",
    "sg:tags":[
        "stockbroker"
    ],
    "wof:name":"Cater Allen Ltd.",
    "wof:placetype":"venue"
},
  "geometry": {"coordinates":[-0.093359,51.515419],"type":"Point"}
}