{
  "type": "Feature",
  "properties": {
    "addr:full":"Unit 40 Argyle Industrial Estate, Appin Road Birkenhead Merseyside CH41 9HH",
    "addr:housenumber":"unit 40",
    "addr:postcode":"ch41 9hh",
    "addr:street":"Argyle Industrial Estate Appin Road",
    "iso:country":"GB",
    "sg:address":"Unit 40 Argyle Industrial Estate, Appin Road",
    "sg:city":"Birkenhead",
    "sg:classifiers":[
        {
            "category":"Building & Trades",
            "subcategory":"Construction",
            "type":"Services"
        }
    ],
    "sg:phone":"+44 151 666 1334",
    "sg:postcode":"CH41 9HH",
    "sg:province":"Merseyside",
    "sg:tags":[
        "builder"
    ],
    "wof:name":"Graham Morgan",
    "wof:placetype":"venue"
},
  "geometry": {"coordinates":[-3.022124052,53.3867149353],"type":"Point"}
}