{
  "type": "Feature",
  "properties": {
    "addr:full":"91 Southfield Road Northampton Northamptonshire NN5 6HJ",
    "addr:housenumber":"91",
    "addr:postcode":"nn5 6hj",
    "addr:street":"Southfield Road",
    "iso:country":"GB",
    "sg:address":"91 Southfield Road",
    "sg:city":"Northampton",
    "sg:classifiers":[
        {
            "category":"Health Services",
            "subcategory":"Medical Lab",
            "type":"Services"
        },
        {
            "category":"Shopping",
            "subcategory":"Pharmacy",
            "type":"Retail Goods"
        }
    ],
    "sg:phone":"+44 1604 759995",
    "sg:postcode":"NN5 6HJ",
    "sg:province":"Northamptonshire",
    "sg:tags":[
        "medicine",
        "alternative",
        "therapy",
        "treatment"
    ],
    "wof:name":"G K M ENTERPRISE",
    "wof:placetype":"venue"
},
  "geometry": {"coordinates":[-0.946080029,52.2402763367],"type":"Point"}
}