{
  "type": "Feature",
  "properties": {
    "iso:country":"GB",
    "sg:address":"6 Main St",
    "sg:city":"Rotherham",
    "sg:classifiers":[
        {
            "category":"Professional",
            "subcategory":"Business Services",
            "type":"Services"
        }
    ],
    "sg:phone":"+44 1709 368710",
    "sg:postcode":"S60 1AJ",
    "sg:province":"South Yorkshire",
    "sg:tags":[
        "tile",
        "stockist"
    ],
    "wof:name":"Ceramtile",
    "wof:placetype":"venue"
},
  "geometry": {"coordinates":[-1.35776,53.42955],"type":"Point"}
}