{
  "type": "Feature",
  "properties": {
    "iso:country":"GB",
    "sg:address":"Unit 47, Salthouse Mills Industrial Estate, Salthouse Road",
    "sg:city":"Barrow In Furness",
    "sg:classifiers":[
        {
            "category":"Professional",
            "subcategory":"Engineering",
            "type":"Services"
        },
        {
            "category":"Utilities",
            "subcategory":"Natural Gas",
            "type":"Services"
        }
    ],
    "sg:phone":"+44 1229 431618",
    "sg:postcode":"LA13 0DH",
    "sg:province":"Cumbria",
    "sg:tags":[
        "blacksmith",
        "engineer"
    ],
    "wof:name":"Dixons Forge",
    "wof:placetype":"venue"
},
  "geometry": {"coordinates":[-3.1938149929,54.1358528137],"type":"Point"}
}