{
  "type": "Feature",
  "properties": {
    "addr:full":"Unit 2 Watson Road, Nechells Birmingham West Midlands B7 5SB",
    "addr:housenumber":"unit 2",
    "addr:postcode":"b7 5sb",
    "addr:street":"Watson Road",
    "iso:country":"GB",
    "sg:address":"Unit 2 Watson Road, Nechells",
    "sg:city":"Birmingham",
    "sg:classifiers":[
        {
            "category":"Building & Trades",
            "subcategory":"Construction",
            "type":"Services"
        }
    ],
    "sg:phone":"+44 121 236 6301",
    "sg:postcode":"B7 5SB",
    "sg:province":"West Midlands",
    "sg:tags":[
        "worker",
        "metal"
    ],
    "wof:name":"Savada Metal Finishing Ltd.",
    "wof:placetype":"venue"
},
  "geometry": {"coordinates":[-1.8568789959,52.5034408569],"type":"Point"}
}