{
  "type": "Feature",
  "properties": {
    "addr:full":"17a Cults Av Aberdeen Aberdeen City AB15 9TB",
    "addr:housenumber":"17a",
    "addr:postcode":"ab15 9tb",
    "addr:street":"Cults Av",
    "iso:country":"GB",
    "sg:address":"17a Cults Av",
    "sg:city":"Aberdeen",
    "sg:classifiers":[
        {
            "category":"Transit Center",
            "subcategory":"Passenger",
            "type":"Transportation"
        }
    ],
    "sg:phone":"+44 1224 868503",
    "sg:postcode":"AB15 9TB",
    "sg:province":"Aberdeen City",
    "sg:tags":[
        "boarding",
        "kennel",
        "catteries"
    ],
    "wof:name":"D Armstrong",
    "wof:placetype":"venue"
},
  "geometry": {"coordinates":[-2.1844489574,57.1161308289],"type":"Point"}
}