{
  "type": "Feature",
  "properties": {
    "addr:full":"11 Kelsull Croft Birmingham West Midlands B37 5HH",
    "addr:housenumber":"11",
    "addr:postcode":"b37 5hh",
    "addr:street":"Kelsull Croft",
    "iso:country":"GB",
    "sg:address":"11 Kelsull Croft",
    "sg:city":"Birmingham",
    "sg:classifiers":[
        {
            "category":"Building & Trades",
            "subcategory":"Construction",
            "type":"Services"
        }
    ],
    "sg:phone":"+44 121 681 8448",
    "sg:postcode":"B37 5HH",
    "sg:province":"West Midlands",
    "sg:tags":[
        "joiner",
        "carpenter"
    ],
    "wof:name":"Design Wood",
    "wof:placetype":"venue"
},
  "geometry": {"coordinates":[-1.7486909628,52.4762535095],"type":"Point"}
}