{
  "type": "Feature",
  "properties": {
    "addr:full":"10 The Dell, Yateley Camberley Hampshire GU17 7EL",
    "addr:housenumber":"10",
    "addr:postcode":"gu17 7el",
    "addr:street":"The Dell",
    "iso:country":"GB",
    "sg:address":"10 The Dell, Yateley",
    "sg:city":"Camberley",
    "sg:classifiers":[
        {
            "category":"Home & Garden",
            "subcategory":"Household Appliances",
            "type":"Retail Goods"
        }
    ],
    "sg:postcode":"GU17 7EL",
    "sg:province":"Hampshire",
    "sg:tags":[
        "electrical"
    ],
    "wof:name":"Morse,B,",
    "wof:placetype":"venue"
},
  "geometry": {"coordinates":[-0.81166,51.321602],"type":"Point"}
}