{
  "type": "Feature",
  "properties": {
    "addr:full":"5 Westminster Bridge Road London Greater London SE1 7XW",
    "addr:housenumber":"5",
    "addr:postcode":"se1 7xw",
    "addr:street":"Westminster Bridge Road",
    "iso:country":"GB",
    "sg:address":"5 Westminster Bridge Road",
    "sg:city":"London",
    "sg:classifiers":[
        {
            "category":"Organizations",
            "subcategory":"Non-profit Organization",
            "type":"Services"
        }
    ],
    "sg:phone":"+44 20 7620 1430",
    "sg:postcode":"SE1 7XW",
    "sg:province":"Greater London",
    "sg:tags":[
        "organisation",
        "voluntary",
        "charity"
    ],
    "wof:name":"Ghana Refugee Welfare Group",
    "wof:placetype":"venue"
},
  "geometry": {"coordinates":[-0.105655998,51.4984703064],"type":"Point"}
}