{
  "type": "Feature",
  "properties": {
    "addr:full":"68 Russell Avenue Aylesbury Buckinghamshire HP21 8ND",
    "addr:housenumber":"68",
    "addr:postcode":"hp21 8nd",
    "addr:street":"Russell Avenue",
    "iso:country":"GB",
    "sg:address":"68 Russell Avenue",
    "sg:city":"Aylesbury",
    "sg:classifiers":[
        {
            "category":"Building & Trades",
            "subcategory":"Construction",
            "type":"Services"
        }
    ],
    "sg:phone":"+44 1296 486895",
    "sg:postcode":"HP21 8ND",
    "sg:province":"Buckinghamshire",
    "sg:tags":[
        "dry",
        "lining",
        "plasterers",
        "screeders"
    ],
    "wof:name":"E.G Bright",
    "wof:placetype":"venue"
},
  "geometry": {"coordinates":[-0.826539,51.809917],"type":"Point"}
}