{
  "type": "Feature",
  "properties": {
    "addr:full":"Guild Street Aberdeen Aberdeen City AB11 6LT",
    "addr:postcode":"ab11 6lt",
    "addr:street":"Guild Street",
    "iso:country":"GB",
    "sg:address":"Guild Street",
    "sg:city":"Aberdeen",
    "sg:classifiers":[
        {
            "category":"Professional",
            "type":"Services"
        }
    ],
    "sg:phone":"+44 1224 211051",
    "sg:postcode":"AB11 6LT",
    "sg:province":"Aberdeen City",
    "sg:tags":[
        "caterer"
    ],
    "wof:name":"Commercial Catering Group",
    "wof:placetype":"venue"
},
  "geometry": {"coordinates":[-2.0966589451,57.1451568604],"type":"Point"}
}