{
  "type": "Feature",
  "properties": {
    "iso:country":"GB",
    "sg:address":"Lichfield Road, Barton-under-needwooroad",
    "sg:city":"Burton-on-trent",
    "sg:classifiers":[
        {
            "category":"Utilities",
            "subcategory":"Fuel Oil & Lpg",
            "type":"Services"
        }
    ],
    "sg:postcode":"DE13 8EH",
    "sg:province":"Derbyshire",
    "sg:tags":[
        "distributor"
    ],
    "wof:name":"Central Fuel Oils",
    "wof:placetype":"venue"
},
  "geometry": {"coordinates":[-1.7070389986,52.757850647],"type":"Point"}
}