{
  "type": "Feature",
  "properties": {
    "addr:full":"Henfield Road, Albourne Hassocks East Sussex BN6 9DS",
    "addr:postcode":"bn6 9ds",
    "addr:street":"Henfield Road",
    "iso:country":"GB",
    "sg:address":"Henfield Road, Albourne",
    "sg:city":"Hassocks",
    "sg:classifiers":[
        {
            "category":"Military Area",
            "subcategory":"Air Force Base",
            "type":"Public Place"
        }
    ],
    "sg:phone":"+44 1273 833800",
    "sg:postcode":"BN6 9DS",
    "sg:province":"East Sussex",
    "sg:tags":[
        "taxi",
        "hire",
        "private"
    ],
    "wof:name":"Maxi Taxi",
    "wof:placetype":"venue"
},
  "geometry": {"coordinates":[-0.2015070021,50.9333686829],"type":"Point"}
}