{
  "type": "Feature",
  "properties": {
    "addr:full":"71 East Street, Selsey Chichester West Sussex PO20 0BU",
    "addr:housenumber":"71",
    "addr:postcode":"po20 0bu",
    "addr:street":"East Street",
    "iso:country":"GB",
    "sg:address":"71 East Street, Selsey",
    "sg:city":"Chichester",
    "sg:classifiers":[
        {
            "category":"Bars & Pubs",
            "type":"Food & Drink"
        }
    ],
    "sg:phone":"+44 1243 602121",
    "sg:postcode":"PO20 0BU",
    "sg:province":"West Sussex",
    "sg:tags":[
        "pubs",
        "house",
        "inn",
        "public",
        "activity"
    ],
    "wof:name":"Shelia Lynch",
    "wof:placetype":"venue"
},
  "geometry": {"coordinates":[-0.78540802,50.7308502197],"type":"Point"}
}