{
  "type": "Feature",
  "properties": {
    "iso:country":"GB",
    "sg:address":"Cornish Way West, Galmington Trading Estate",
    "sg:city":"Taunton",
    "sg:classifiers":[
        {
            "category":"Retail",
            "subcategory":"Auto Repair",
            "type":"Services"
        }
    ],
    "sg:postcode":"TA1 5NA",
    "sg:province":"Somerset",
    "sg:tags":[
        "modification",
        "garage"
    ],
    "wof:name":"Taunton Auto Factors Ltd.",
    "wof:placetype":"venue"
},
  "geometry": {"coordinates":[-3.131149,51.011471],"type":"Point"}
}