{
  "type": "Feature",
  "properties": {
    "iso:country":"GB",
    "sg:address":"60 Trinity Road",
    "sg:city":"London",
    "sg:classifiers":[
        {
            "category":"Retail",
            "subcategory":"Auto Repair",
            "type":"Services"
        }
    ],
    "sg:postcode":"SW17 7RH",
    "sg:province":"Greater London",
    "sg:tags":[
        "modification",
        "garage"
    ],
    "wof:name":"Burt's Garage",
    "wof:placetype":"venue"
},
  "geometry": {"coordinates":[-0.1613730043,51.4369544983],"type":"Point"}
}