{
  "type": "Feature",
  "properties": {
    "addr:full":"Unit 19 Creech Paper Mill, Creech St Michael Taunton Devon TA3 5PX",
    "addr:housenumber":"unit 19 creech",
    "addr:postcode":"ta3 5px",
    "addr:street":"Creech",
    "iso:country":"GB",
    "sg:address":"Unit 19 Creech Paper Mill, Creech St Michael",
    "sg:city":"Taunton",
    "sg:classifiers":[
        {
            "category":"Professional",
            "type":"Services"
        }
    ],
    "sg:phone":"+44 1823 443342",
    "sg:postcode":"TA3 5PX",
    "sg:province":"Devon",
    "sg:tags":[
        "specialist",
        "coating"
    ],
    "wof:name":"Ceramicoat Ltd.",
    "wof:placetype":"venue"
},
  "geometry": {"coordinates":[-3.0427000523,51.0232391357],"type":"Point"}
}