{
  "type": "Feature",
  "properties": {
    "addr:full":"1 Swanscombe Business Centre, London Road Swanscombe Kent DA10 0LH",
    "addr:housenumber":"1",
    "addr:postcode":"da10 0lh",
    "addr:street":"Swanscombe Business Centre London Road",
    "iso:country":"GB",
    "sg:address":"1 Swanscombe Business Centre, London Road",
    "sg:city":"Swanscombe",
    "sg:classifiers":[
        {
            "category":"Building & Trades",
            "subcategory":"Construction",
            "type":"Services"
        }
    ],
    "sg:phone":"+44 1322 370055",
    "sg:postcode":"DA10 0LH",
    "sg:province":"Kent",
    "sg:tags":[
        "builder"
    ],
    "wof:name":"P & N Building Services",
    "wof:placetype":"venue"
},
  "geometry": {"coordinates":[0.308545,51.450146],"type":"Point"}
}