{
  "type": "Feature",
  "properties": {
    "addr:full":"The Clubhouse, Recreation Ground Ilminster Somerset TA19 0EZ",
    "addr:postcode":"ta19 0ez",
    "addr:street":"Recreation;Ilminster",
    "iso:country":"GB",
    "sg:address":"The Clubhouse, Recreation Ground",
    "sg:city":"Ilminster",
    "sg:classifiers":[
        {
            "category":"Arena",
            "subcategory":"Sports Club",
            "type":"Entertainment"
        }
    ],
    "sg:phone":"+44 1460 54756",
    "sg:postcode":"TA19 0EZ",
    "sg:province":"Somerset",
    "wof:name":"Ilminster Sports Club",
    "wof:placetype":"venue"
},
  "geometry": {"coordinates":[-2.91753,50.928669],"type":"Point"}
}