{
  "type": "Feature",
  "properties": {
    "addr:full":"Coronation Road Woodhall Spa Lincolnshire LN10 6QD",
    "addr:postcode":"ln10 6qd",
    "addr:street":"Coronation Road",
    "iso:country":"GB",
    "sg:address":"Coronation Road",
    "sg:city":"Woodhall Spa",
    "sg:classifiers":[
        {
            "category":"Restaurant",
            "type":"Food & Drink"
        }
    ],
    "sg:phone":"+44 1526 354455",
    "sg:postcode":"LN10 6QD",
    "sg:province":"Lincolnshire",
    "wof:name":"Tea House in the Woods",
    "wof:placetype":"venue"
},
  "geometry": {"coordinates":[-0.2135429978,53.1551094055],"type":"Point"}
}