{
  "type": "Feature",
  "properties": {
    "addr:full":"Cranmere Bank, Stableford Bridgnorth Shropshire WV15 5LP",
    "addr:postcode":"wv15 5lp",
    "iso:country":"GB",
    "sg:address":"Cranmere Bank, Stableford",
    "sg:city":"Bridgnorth",
    "sg:classifiers":[
        {
            "category":"Building & Trades",
            "subcategory":"Construction",
            "type":"Services"
        }
    ],
    "sg:phone":"+44 1746 783220",
    "sg:postcode":"WV15 5LP",
    "sg:province":"Shropshire",
    "sg:tags":[
        "joiner",
        "carpenter"
    ],
    "wof:name":"Wilfred Reginald Plain",
    "wof:placetype":"venue"
},
  "geometry": {"coordinates":[-2.3573589325,52.5827789307],"type":"Point"}
}