{
  "type": "Feature",
  "properties": {
    "iso:country":"GB",
    "sg:address":"Rugeley Power Station",
    "sg:city":"Rugeley",
    "sg:classifiers":[
        {
            "category":"Sports & Exercise",
            "subcategory":"Golf",
            "type":"Entertainment"
        }
    ],
    "sg:phone":"+44 1889 575667",
    "sg:postcode":"WS15 1PR",
    "sg:province":"Staffordshire",
    "sg:tags":[
        "club",
        "course"
    ],
    "wof:name":"Lakeside Golf Club",
    "wof:placetype":"venue"
},
  "geometry": {"coordinates":[-1.9268480539,52.7580871582],"type":"Point"}
}