{
  "type": "Feature",
  "properties": {
    "iso:country":"GB",
    "sg:address":"Vicarage La",
    "sg:city":"Brierley Hill",
    "sg:classifiers":[
        {
            "category":"Place Of Worship",
            "type":"Public Place"
        }
    ],
    "sg:phone":"+44 1384 262666",
    "sg:postcode":"DY5 4JH",
    "sg:province":"West Midlands",
    "wof:name":"St Marks C Of E Church",
    "wof:placetype":"venue"
},
  "geometry": {"coordinates":[-2.125811,52.502411],"type":"Point"}
}