{
  "type": "Feature",
  "properties": {
    "addr:full":"Old Methodist Chapel, Central Lydbrook Lydbrook Gloucestershire GL17 9PP",
    "addr:postcode":"gl17 9pp",
    "iso:country":"GB",
    "sg:address":"Old Methodist Chapel, Central Lydbrook",
    "sg:city":"Lydbrook",
    "sg:classifiers":[
        {
            "category":"Professional",
            "type":"Services"
        }
    ],
    "sg:phone":"+44 1594 861499",
    "sg:postcode":"GL17 9PP",
    "sg:province":"Gloucestershire",
    "sg:tags":[
        "display",
        "maker"
    ],
    "wof:name":"Centre Piece Exhibition Displays",
    "wof:placetype":"venue"
},
  "geometry": {"coordinates":[-2.580163,51.839935],"type":"Point"}
}