{
  "type": "Feature",
  "properties": {
    "iso:country":"GB",
    "sg:address":"Hawthorn Street",
    "sg:city":"Blackburn",
    "sg:classifiers":[
        {
            "category":"Education",
            "subcategory":"School",
            "type":"Public Place"
        }
    ],
    "sg:phone":"+44 1254 261609",
    "sg:postcode":"BB1 9TH",
    "sg:province":"Lancashire",
    "sg:tags":[
        "local",
        "authority"
    ],
    "wof:name":"Cedars County Infant School",
    "wof:placetype":"venue"
},
  "geometry": {"coordinates":[-2.4733190536,53.7627105713],"type":"Point"}
}