{
  "type": "Feature",
  "properties": {
    "addr:full":"39 Marlow Copse Chatham Kent ME5 9DR",
    "addr:housenumber":"39",
    "addr:postcode":"me5 9dr",
    "addr:street":"Marlow Copse",
    "iso:country":"GB",
    "sg:address":"39 Marlow Copse",
    "sg:city":"Chatham",
    "sg:classifiers":[
        {
            "category":"Building & Trades",
            "subcategory":"Cleaning & Sanitation",
            "type":"Services"
        }
    ],
    "sg:postcode":"ME5 9DR",
    "sg:province":"Kent",
    "sg:tags":[
        "commercial"
    ],
    "wof:name":"Gem Cleaning Services",
    "wof:placetype":"venue"
},
  "geometry": {"coordinates":[0.525667,51.334309],"type":"Point"}
}