{
  "type": "Feature",
  "properties": {
    "iso:country":"GB",
    "sg:address":"Station Forecourt, Station App",
    "sg:city":"Maidenhead",
    "sg:classifiers":[
        {
            "category":"Military Area",
            "subcategory":"Air Force Base",
            "type":"Public Place"
        }
    ],
    "sg:phone":"+44 1628 634311",
    "sg:postcode":"SL6 1EW",
    "sg:province":"Berkshire",
    "sg:tags":[
        "taxi",
        "hire",
        "private"
    ],
    "wof:name":"Maidenhead Cab Rank",
    "wof:placetype":"venue"
},
  "geometry": {"coordinates":[-0.727257,51.522373],"type":"Point"}
}