{
  "type": "Feature",
  "properties": {
    "addr:full":"74 Staithe Street Wells-next-the-sea Norfolk NR23 1AQ",
    "addr:housenumber":"74",
    "addr:postcode":"nr23 1aq",
    "addr:street":"Staithe Street",
    "iso:country":"GB",
    "sg:address":"74 Staithe Street",
    "sg:city":"Wells-next-the-sea",
    "sg:classifiers":[
        {
            "category":"Shopping",
            "subcategory":"Computers & Home Electronics",
            "type":"Retail Goods"
        },
        {
            "category":"Communications",
            "type":"Services"
        }
    ],
    "sg:phone":"+44 1328 710311",
    "sg:postcode":"NR23 1AQ",
    "sg:province":"Norfolk",
    "sg:tags":[
        "tv",
        "radio",
        "television",
        "video",
        "sale"
    ],
    "wof:name":"Cadamys Ltd",
    "wof:placetype":"venue"
},
  "geometry": {"coordinates":[0.852525,52.956718],"type":"Point"}
}