{
  "type": "Feature",
  "properties": {
    "addr:full":"76 Mersey Street Warrington Cheshire WA1 2BP",
    "addr:housenumber":"76",
    "addr:postcode":"wa1 2bp",
    "addr:street":"Mersey Street",
    "iso:country":"GB",
    "sg:address":"76 Mersey Street",
    "sg:city":"Warrington",
    "sg:classifiers":[
        {
            "category":"Fast Food",
            "type":"Food & Drink"
        }
    ],
    "sg:phone":"+44 1925 235370",
    "sg:postcode":"WA1 2BP",
    "sg:province":"Cheshire",
    "sg:tags":[
        "away",
        "take"
    ],
    "wof:name":"Warrington Tandooriland",
    "wof:placetype":"venue"
},
  "geometry": {"coordinates":[-2.588791,53.38826],"type":"Point"}
}