{
  "type": "Feature",
  "properties": {
    "iso:country":"GB",
    "sg:address":"107-111 Fleet Street",
    "sg:city":"London",
    "sg:classifiers":[
        {
            "category":"Home & Garden",
            "subcategory":"Household Appliances",
            "type":"Retail Goods"
        }
    ],
    "sg:phone":"+44 20 7936 9063",
    "sg:postcode":"EC4A 2AB",
    "sg:province":"Greater London",
    "sg:tags":[
        "electrical",
        "domestic"
    ],
    "wof:name":"Ectaco (Uk) Ltd.",
    "wof:placetype":"venue"
},
  "geometry": {"coordinates":[-0.104652,51.51421],"type":"Point"}
}