{
  "type": "Feature",
  "properties": {
    "addr:full":"Corbett Ho, Avonvale Rd Bristol City of Bristol BS5 9QX",
    "addr:postcode":"bs5 9qx",
    "addr:street":"Avonvale Rd",
    "iso:country":"GB",
    "sg:address":"Corbett Ho, Avonvale Rd",
    "sg:city":"Bristol",
    "sg:classifiers":[
        {
            "category":"Health Services",
            "subcategory":"Doctor",
            "type":"Services"
        }
    ],
    "sg:phone":"+44 117 955 7474",
    "sg:postcode":"BS5 9QX",
    "sg:province":"City of Bristol",
    "sg:tags":[
        "practitioners"
    ],
    "wof:name":"Rees, J",
    "wof:placetype":"venue"
},
  "geometry": {"coordinates":[-2.561202,51.455257],"type":"Point"}
}