{
  "type": "Feature",
  "properties": {
    "iso:country":"GB",
    "sg:address":"Thomas Bullock Primary School, Pound Gre, Shipdham",
    "sg:city":"Thetford",
    "sg:classifiers":[
        {
            "category":"Social Services",
            "subcategory":"Adult Care",
            "type":"Services"
        },
        {
            "category":"Organizations",
            "subcategory":"Community Association",
            "type":"Services"
        },
        {
            "category":"Education",
            "subcategory":"School",
            "type":"Public Place"
        }
    ],
    "sg:phone":"+44 1362 821046",
    "sg:postcode":"IP25 7LF",
    "sg:province":"Norfolk",
    "sg:tags":[
        "associations",
        "centre",
        "housing",
        "authority",
        "co-operatives",
        "trust",
        "local",
        "day",
        "societies"
    ],
    "wof:name":"Norfolk County Council",
    "wof:placetype":"venue"
},
  "geometry": {"coordinates":[0.897466,52.62994],"type":"Point"}
}