{
  "type": "Feature",
  "properties": {
    "addr:full":"43 Sussex Avenue, Gawsworth Macclesfield Cheshire SK11 7UT",
    "addr:housenumber":"43",
    "addr:postcode":"sk11 7ut",
    "addr:street":"Sussex Avenue",
    "iso:country":"GB",
    "sg:address":"43 Sussex Avenue, Gawsworth",
    "sg:city":"Macclesfield",
    "sg:classifiers":[
        {
            "category":"Industrial Area",
            "type":"Public Place"
        }
    ],
    "sg:phone":"+44 1625 430352",
    "sg:postcode":"SK11 7UT",
    "sg:province":"Cheshire",
    "sg:tags":[
        "consultant"
    ],
    "wof:name":"John Michelle",
    "wof:placetype":"venue"
},
  "geometry": {"coordinates":[-2.150113,53.246288],"type":"Point"}
}