{
  "type": "Feature",
  "properties": {
    "addr:full":"3 Alum Chine Road, Westbourne Bournemouth Dorset BH4 8DT",
    "addr:housenumber":"3",
    "addr:postcode":"bh4 8dt",
    "addr:street":"Alum Chine Road",
    "iso:country":"GB",
    "sg:address":"3 Alum Chine Road, Westbourne",
    "sg:city":"Bournemouth",
    "sg:classifiers":[
        {
            "category":"Professional",
            "subcategory":"Employment Agencies",
            "type":"Services"
        }
    ],
    "sg:phone":"+44 1202 752955",
    "sg:postcode":"BH4 8DT",
    "sg:province":"Dorset",
    "sg:tags":[
        "consultant",
        "recruitment"
    ],
    "wof:name":"Towngate Personnel Ltd",
    "wof:placetype":"venue"
},
  "geometry": {"coordinates":[-1.901704,50.721931],"type":"Point"}
}