{
  "type": "Feature",
  "properties": {
    "iso:country":"GB",
    "sg:address":"61 Broad Street",
    "sg:city":"Bristol",
    "sg:classifiers":[
        {
            "category":"Retail",
            "subcategory":"Laundry & Dry Cleaning",
            "type":"Services"
        }
    ],
    "sg:phone":"+44 117 929 3834",
    "sg:postcode":"BS1 2EJ",
    "sg:province":"City of Bristol",
    "sg:tags":[
        "alteration"
    ],
    "wof:name":"K's Specialist Dry Cleaners",
    "wof:placetype":"venue"
},
  "geometry": {"coordinates":[-2.593129,51.455166],"type":"Point"}
}