{
  "type": "Feature",
  "properties": {
    "iso:country":"GB",
    "sg:address":"6 Hunters La",
    "sg:city":"Oldham",
    "sg:classifiers":[
        {
            "category":"Organizations",
            "subcategory":"Community Association",
            "type":"Services"
        }
    ],
    "sg:phone":"+44 161 620 4645",
    "sg:postcode":"OL1 1QU",
    "sg:province":"Lancashire",
    "sg:tags":[
        "society",
        "housing"
    ],
    "wof:name":"South East Lancashire Housing Associatio",
    "wof:placetype":"venue"
},
  "geometry": {"coordinates":[-2.1103680134,53.5414352417],"type":"Point"}
}