{
  "type": "Feature",
  "properties": {
    "addr:full":"102 Station Road Llanelli Carmarthenshire SA15 1YU",
    "addr:housenumber":"102",
    "addr:postcode":"sa15 1yu",
    "addr:street":"Station Road",
    "iso:country":"GB",
    "sg:address":"102 Station Road",
    "sg:city":"Llanelli",
    "sg:classifiers":[
        {
            "category":"Personal",
            "subcategory":"Beauty Salon",
            "type":"Services"
        },
        {
            "category":"Personal",
            "subcategory":"Barber",
            "type":"Services"
        }
    ],
    "sg:phone":"+44 1554 772320",
    "sg:postcode":"SA15 1YU",
    "sg:province":"Carmarthenshire",
    "sg:tags":[
        "unisex",
        "hairdresser"
    ],
    "wof:name":"Michael's Hairstylist",
    "wof:placetype":"venue"
},
  "geometry": {"coordinates":[-4.1603021622,51.674243927],"type":"Point"}
}