{
  "type": "Feature",
  "properties": {
    "addr:full":"48 Portland Place London Greater London W1B 1AJ",
    "addr:housenumber":"48",
    "addr:postcode":"w1b 1aj",
    "addr:street":"Portland Place",
    "iso:country":"GB",
    "sg:address":"48 Portland Place",
    "sg:city":"London",
    "sg:classifiers":[
        {
            "category":"Professional",
            "subcategory":"Accounting & Tax Preparation",
            "type":"Services"
        }
    ],
    "sg:phone":"+44 20 7467 4000",
    "sg:postcode":"W1B 1AJ",
    "sg:province":"Greater London",
    "sg:tags":[
        "accountant"
    ],
    "wof:name":"Jason Newman",
    "wof:placetype":"venue"
},
  "geometry": {"coordinates":[-0.1459120065,51.5215950012],"type":"Point"}
}