{
  "type": "Feature",
  "properties": {
    "addr:full":"123 Nethergate Dundee Dundee City DD1 4DW",
    "addr:housenumber":"123",
    "addr:postcode":"dd1 4dw",
    "addr:street":"Nethergate",
    "iso:country":"GB",
    "sg:address":"123 Nethergate",
    "sg:city":"Dundee",
    "sg:classifiers":[
        {
            "category":"Government",
            "subcategory":"Post Office",
            "type":"Public Place"
        }
    ],
    "sg:phone":"+44 1382 322740",
    "sg:postcode":"DD1 4DW",
    "sg:province":"Dundee City",
    "wof:name":"NETHERGATE POST OFFICE",
    "wof:placetype":"venue"
},
  "geometry": {"coordinates":[-2.9758400917,56.4575805664],"type":"Point"}
}