{
  "type": "Feature",
  "properties": {
    "addr:full":"Kingsley Close, East Way, Lee Mill Ivybridge Devon PL21 9GD",
    "addr:postcode":"pl21 9gd",
    "addr:street":"Kingsley Close East Way Lee",
    "iso:country":"GB",
    "sg:address":"Kingsley Close, East Way, Lee Mill",
    "sg:city":"Ivybridge",
    "sg:classifiers":[
        {
            "category":"Professional",
            "subcategory":"Accounting & Tax Preparation",
            "type":"Services"
        }
    ],
    "sg:phone":"+44 1752 205204",
    "sg:postcode":"PL21 9GD",
    "sg:province":"Devon",
    "sg:tags":[
        "accountant"
    ],
    "wof:name":"Pfs Asset Management Ltd.",
    "wof:placetype":"venue"
},
  "geometry": {"coordinates":[-3.9290390015,50.3872642517],"type":"Point"}
}