{
  "type": "Feature",
  "properties": {
    "iso:country":"GB",
    "sg:address":"Capp House, 96 South End",
    "sg:city":"Croydon",
    "sg:classifiers":[
        {
            "category":"Professional",
            "subcategory":"Engineering",
            "type":"Services"
        }
    ],
    "sg:postcode":"CR0 1DQ",
    "sg:province":"Surrey",
    "sg:tags":[
        "contractor",
        "electrical",
        "engineer"
    ],
    "wof:name":"J B Electrical Services (London) Ltd.",
    "wof:placetype":"venue"
},
  "geometry": {"coordinates":[-0.0990900025,51.3645782471],"type":"Point"}
}