{
  "type": "Feature",
  "properties": {
    "addr:full":"Odds Farmhouse, Wooburn Common High Wycombe Buckinghamshire HP10 0LA",
    "addr:postcode":"hp10 0la",
    "addr:street":"Wooburn Common",
    "iso:country":"GB",
    "sg:address":"Odds Farmhouse, Wooburn Common",
    "sg:city":"High Wycombe",
    "sg:classifiers":[
        {
            "category":"Farming",
            "subcategory":"Livestock Farm",
            "type":"Manufacturing & Wholesale Goods"
        }
    ],
    "sg:phone":"+44 1628 523905",
    "sg:postcode":"HP10 0LA",
    "sg:province":"Buckinghamshire",
    "sg:tags":[
        "others"
    ],
    "wof:name":"L & A M House",
    "wof:placetype":"venue"
},
  "geometry": {"coordinates":[-0.6727190018,51.5812454224],"type":"Point"}
}