{
  "type": "Feature",
  "properties": {
    "iso:country":"GB",
    "sg:address":"Cornish Works, Green Lane",
    "sg:city":"Sheffield",
    "sg:classifiers":[
        {
            "category":"Manufacturing",
            "subcategory":"Metals",
            "type":"Manufacturing & Wholesale Goods"
        }
    ],
    "sg:postcode":"S3 8SE",
    "sg:province":"South Yorkshire",
    "sg:tags":[
        "steel",
        "stockholder"
    ],
    "wof:name":"Baruser Stocks Ltd.",
    "wof:placetype":"venue"
},
  "geometry": {"coordinates":[-1.474965,53.389275],"type":"Point"}
}