{
  "type": "Feature",
  "properties": {
    "iso:country":"GB",
    "sg:address":"Haverton Hill Road, Haverton Hill",
    "sg:city":"Billingham",
    "sg:classifiers":[
        {
            "category":"Building & Trades",
            "subcategory":"Cleaning & Sanitation",
            "type":"Services"
        }
    ],
    "sg:phone":"+44 1642 564400",
    "sg:postcode":"TS23 1PY",
    "sg:province":"Durham",
    "sg:tags":[
        "repairing",
        "tank"
    ],
    "wof:name":"Interflow Technical Services Ltd.",
    "wof:placetype":"venue"
},
  "geometry": {"coordinates":[-1.2652800083,54.5904579163],"type":"Point"}
}