{
  "type": "Feature",
  "properties": {
    "iso:country":"GB",
    "sg:address":"262-264 Barnsley Road, Cudworth",
    "sg:city":"Barnsley",
    "sg:classifiers":[
        {
            "category":"Fast Food",
            "type":"Food & Drink"
        },
        {
            "category":"Restaurant",
            "type":"Food & Drink"
        }
    ],
    "sg:phone":"+44 1226 710870",
    "sg:postcode":"S72 8SU",
    "sg:province":"South Yorkshire",
    "sg:tags":[
        "away",
        "take"
    ],
    "wof:name":"Yung's Chop Suey House",
    "wof:placetype":"venue"
},
  "geometry": {"coordinates":[-1.4167610407,53.5778770447],"type":"Point"}
}