{
  "type": "Feature",
  "properties": {
    "addr:full":"Common Road, Hopton Diss Norfolk IP22 2QU",
    "addr:postcode":"ip22 2qu",
    "addr:street":"Common Road",
    "iso:country":"GB",
    "sg:address":"Common Road, Hopton",
    "sg:city":"Diss",
    "sg:classifiers":[
        {
            "category":"Home & Garden",
            "subcategory":"Home Furnishings",
            "type":"Retail Goods"
        },
        {
            "category":"Communications",
            "type":"Services"
        }
    ],
    "sg:postcode":"IP22 2QU",
    "sg:province":"Norfolk",
    "sg:tags":[
        "planner",
        "tv",
        "furnishers",
        "video",
        "radio",
        "kitchen"
    ],
    "wof:name":"Tollgate Kitchens",
    "wof:placetype":"venue"
},
  "geometry": {"coordinates":[0.9276850224,52.3734817505],"type":"Point"}
}