{
  "type": "Feature",
  "properties": {
    "addr:full":"79-91 High St Falkirk Falkirk FK1 1ES",
    "addr:housenumber":"79-91",
    "addr:postcode":"fk1 1es",
    "addr:street":"High St",
    "iso:country":"GB",
    "sg:address":"79-91 High St",
    "sg:city":"Falkirk",
    "sg:classifiers":[
        {
            "category":"Building & Trades",
            "subcategory":"Cleaning & Sanitation",
            "type":"Services"
        }
    ],
    "sg:phone":"+44 1324 630917",
    "sg:postcode":"FK1 1ES",
    "sg:province":"Falkirk",
    "sg:tags":[
        "facility"
    ],
    "wof:name":"Tarmac Facilities Management",
    "wof:placetype":"venue"
},
  "geometry": {"coordinates":[-3.7806239128,55.9986495972],"type":"Point"}
}