{
  "type": "Feature",
  "properties": {
    "addr:full":"33 Broad Street Newtown Powys SY16 2BQ",
    "addr:housenumber":"33",
    "addr:postcode":"sy16 2bq",
    "addr:street":"Broad Street",
    "iso:country":"GB",
    "sg:address":"33 Broad Street",
    "sg:city":"Newtown",
    "sg:classifiers":[
        {
            "category":"Banks & Credit Unions",
            "subcategory":"Financial Services",
            "type":"Services"
        }
    ],
    "sg:phone":"+44 1686 625999",
    "sg:postcode":"SY16 2BQ",
    "sg:province":"Powys",
    "sg:tags":[
        "building",
        "society"
    ],
    "wof:name":"West Bromwich Building Society",
    "wof:placetype":"venue"
},
  "geometry": {"coordinates":[-3.315927,52.516392],"type":"Point"}
}