{
  "type": "Feature",
  "properties": {
    "addr:full":"St. Michaels La Kidlington Buckinghamshire OX5 1RT",
    "addr:postcode":"ox5 1rt",
    "addr:street":"La Kidlington",
    "iso:country":"GB",
    "sg:address":"St. Michaels La",
    "sg:city":"Kidlington",
    "sg:classifiers":[
        {
            "category":"Place Of Worship",
            "type":"Public Place"
        }
    ],
    "sg:phone":"+44 1865 375749",
    "sg:postcode":"OX5 1RT",
    "sg:province":"Buckinghamshire",
    "wof:name":"St Michael C of E Church",
    "wof:placetype":"venue"
},
  "geometry": {"coordinates":[-1.321756,51.821621],"type":"Point"}
}