{
  "type": "Feature",
  "properties": {
    "iso:country":"GB",
    "sg:address":"Hil Green Lane, Peasmore",
    "sg:city":"Newbury",
    "sg:classifiers":[
        {
            "category":"Restaurant",
            "type":"Food & Drink"
        }
    ],
    "sg:phone":"+44 1635 248252",
    "sg:postcode":"RG20 7JN",
    "sg:province":"Berkshire",
    "wof:name":"Fox & Hounds",
    "wof:placetype":"venue"
},
  "geometry": {"coordinates":[-1.3444869518,51.4933357239],"type":"Point"}
}