{
  "type": "Feature",
  "properties": {
    "iso:country":"GB",
    "sg:address":"Off Wrenthorpe La",
    "sg:city":"Wakefield",
    "sg:classifiers":[
        {
            "category":"Community Center",
            "type":"Public Place"
        }
    ],
    "sg:phone":"+44 1924 378409",
    "sg:postcode":"WF2 0NE",
    "sg:province":"West Yorkshire",
    "sg:tags":[
        "centre"
    ],
    "wof:name":"Valley Crescent Centre",
    "wof:placetype":"venue"
},
  "geometry": {"coordinates":[-1.525762,53.698265],"type":"Point"}
}