{
  "type": "Feature",
  "properties": {
    "addr:full":"15 Bunns Bank Industrial Estate, Old Buckenham Road Attleborough Norfolk NR17 1QD",
    "addr:housenumber":"15",
    "addr:postcode":"nr17 1qd",
    "addr:street":"Bunns Bank Industrial Estate Old Buckenham Road",
    "iso:country":"GB",
    "sg:address":"15 Bunns Bank Industrial Estate, Old Buckenham Road",
    "sg:city":"Attleborough",
    "sg:classifiers":[
        {
            "category":"Building & Trades",
            "subcategory":"Construction",
            "type":"Services"
        }
    ],
    "sg:phone":"+44 1953 454573",
    "sg:postcode":"NR17 1QD",
    "sg:province":"Norfolk",
    "sg:tags":[
        "welder"
    ],
    "wof:name":"Competition Fabrications",
    "wof:placetype":"venue"
},
  "geometry": {"coordinates":[1.0343,52.480099],"type":"Point"}
}