{
  "type": "Feature",
  "properties": {
    "iso:country":"GB",
    "sg:address":"20-21 Grange Lane",
    "sg:city":"Doncaster",
    "sg:classifiers":[
        {
            "category":"Restaurant",
            "type":"Food & Drink"
        }
    ],
    "sg:phone":"+44 1302 868812",
    "sg:postcode":"DN11 0LN",
    "sg:province":"South Yorkshire",
    "wof:name":"Lucky 11",
    "wof:placetype":"venue"
},
  "geometry": {"coordinates":[-1.078878,53.473862],"type":"Point"}
}