{
  "type": "Feature",
  "properties": {
    "addr:full":"Haven Hill, Hodsoll St, Wrotham Sevenoaks Kent TN15 7LL",
    "addr:postcode":"tn15 7ll",
    "addr:street":"Haven;Hodsoll St",
    "iso:country":"GB",
    "sg:address":"Haven Hill, Hodsoll St, Wrotham",
    "sg:city":"Sevenoaks",
    "sg:classifiers":[
        {
            "category":"Building & Trades",
            "subcategory":"Landscaping Services",
            "type":"Services"
        }
    ],
    "sg:phone":"+44 1732 824211",
    "sg:postcode":"TN15 7LL",
    "sg:province":"Kent",
    "sg:tags":[
        "landscape",
        "contractor"
    ],
    "wof:name":"Gurney Landscapes Ltd",
    "wof:placetype":"venue"
},
  "geometry": {"coordinates":[0.3143320084,51.3473014832],"type":"Point"}
}