{
  "type": "Feature",
  "properties": {
    "addr:full":"116 The Street, Hawkinge Folkestone Kent CT18 7DF",
    "addr:housenumber":"116",
    "addr:postcode":"ct18 7df",
    "addr:street":"The Street",
    "iso:country":"GB",
    "sg:address":"116 The Street, Hawkinge",
    "sg:city":"Folkestone",
    "sg:classifiers":[
        {
            "category":"Home & Garden",
            "subcategory":"Garden Supply",
            "type":"Retail Goods"
        }
    ],
    "sg:postcode":"CT18 7DF",
    "sg:province":"Kent",
    "sg:tags":[
        "turfing"
    ],
    "wof:name":"Hawkinge Turf Co.",
    "wof:placetype":"venue"
},
  "geometry": {"coordinates":[1.1722619534,51.1220970154],"type":"Point"}
}