{
  "type": "Feature",
  "properties": {
    "addr:full":"36 High Street Cowes Isle of Wight PO31 7RS",
    "addr:housenumber":"36",
    "addr:postcode":"po31 7rs",
    "addr:street":"High Street",
    "iso:country":"GB",
    "sg:address":"36 High Street",
    "sg:city":"Cowes",
    "sg:classifiers":[
        {
            "category":"Shopping",
            "subcategory":"Hobbies, Toys, & Games",
            "type":"Retail Goods"
        }
    ],
    "sg:phone":"+44 1983 294173",
    "sg:postcode":"PO31 7RS",
    "sg:province":"Isle of Wight",
    "sg:tags":[
        "shop",
        "toy",
        "sale"
    ],
    "wof:name":"Pit Stop",
    "wof:placetype":"venue"
},
  "geometry": {"coordinates":[-1.2979580164,50.7630310059],"type":"Point"}
}