{
  "type": "Feature",
  "properties": {
    "iso:country":"GB",
    "sg:address":"Oldham Road, Shaw",
    "sg:city":"Oldham",
    "sg:classifiers":[
        {
            "category":"Bars & Pubs",
            "type":"Food & Drink"
        }
    ],
    "sg:postcode":"OL2 8RZ",
    "sg:province":"Lancashire",
    "sg:tags":[
        "pubs",
        "inn"
    ],
    "wof:name":"Kings Arms",
    "wof:placetype":"venue"
},
  "geometry": {"coordinates":[-2.097932,53.573437],"type":"Point"}
}