{
  "type": "Feature",
  "properties": {
    "iso:country":"GB",
    "sg:address":"125 Canongate",
    "sg:city":"Edinburgh",
    "sg:classifiers":[
        {
            "category":"Manufacturing",
            "subcategory":"Textiles",
            "type":"Manufacturing & Wholesale Goods"
        }
    ],
    "sg:phone":"+44 131 556 2186",
    "sg:postcode":"EH8 8BP",
    "sg:province":"City of Edinburgh",
    "sg:tags":[
        "knitwear"
    ],
    "wof:name":"Old Town Knitwear",
    "wof:placetype":"venue"
},
  "geometry": {"coordinates":[-3.1795420647,55.9515075684],"type":"Point"}
}