{
  "type": "Feature",
  "properties": {
    "iso:country":"GB",
    "sg:address":"88 Abington St",
    "sg:city":"Northampton",
    "sg:classifiers":[
        {
            "category":"Travel",
            "subcategory":"Travel Agent",
            "type":"Entertainment"
        }
    ],
    "sg:phone":"+44 1604 441500",
    "sg:postcode":"NN1 2BT",
    "sg:province":"Northamptonshire",
    "wof:name":"Thomas Cook Travel",
    "wof:placetype":"venue"
},
  "geometry": {"coordinates":[-0.890687,52.239014],"type":"Point"}
}