{
  "type": "Feature",
  "properties": {
    "iso:country":"GB",
    "sg:address":"Unit 1 Woodhall Road",
    "sg:city":"Wishaw",
    "sg:classifiers":[
        {
            "category":"Retail",
            "subcategory":"Auto Repair",
            "type":"Services"
        }
    ],
    "sg:phone":"+44 1698 386726",
    "sg:postcode":"ML2 8PY",
    "sg:province":"North Lanarkshire",
    "sg:tags":[
        "modification",
        "garage",
        "related"
    ],
    "wof:name":"GARY & MARK GRIER",
    "wof:placetype":"venue"
},
  "geometry": {"coordinates":[-3.8887588978,55.7781448364],"type":"Point"}
}