{
  "type": "Feature",
  "properties": {
    "addr:full":"9 Weatheroak Close Redditch Warwickshire B97 5TF",
    "addr:housenumber":"9",
    "addr:postcode":"b97 5tf",
    "addr:street":"Weatheroak Close",
    "iso:country":"GB",
    "sg:address":"9 Weatheroak Close",
    "sg:city":"Redditch",
    "sg:classifiers":[
        {
            "category":"Building & Trades",
            "subcategory":"Construction",
            "type":"Services"
        }
    ],
    "sg:postcode":"B97 5TF",
    "sg:province":"Warwickshire",
    "sg:tags":[
        "joiner",
        "carpenter"
    ],
    "wof:name":"Act Fast Services",
    "wof:placetype":"venue"
},
  "geometry": {"coordinates":[-1.9679640532,52.2947921753],"type":"Point"}
}