{
  "type": "Feature",
  "properties": {
    "addr:full":"The Pavilion 1a 1a South Street Huntingdon Bedfordshire PE19 2BW",
    "addr:housenumber":"1a 1a",
    "addr:postcode":"pe19 2bw",
    "addr:street":"South Street",
    "iso:country":"GB",
    "sg:address":"The Pavilion 1a 1a South Street",
    "sg:city":"Huntingdon",
    "sg:classifiers":[
        {
            "category":"Professional",
            "subcategory":"Lawyer & Legal Services",
            "type":"Services"
        }
    ],
    "sg:phone":"+44 1480 474661",
    "sg:postcode":"PE19 2BW",
    "sg:province":"Bedfordshire",
    "sg:tags":[
        "solicitor"
    ],
    "wof:name":"Leeds Day",
    "wof:placetype":"venue"
},
  "geometry": {"coordinates":[-0.2691999972,52.2276992798],"type":"Point"}
}