{
  "type": "Feature",
  "properties": {
    "iso:country":"GB",
    "sg:address":"6 Priory Street",
    "sg:city":"Monmouth",
    "sg:classifiers":[
        {
            "category":"Professional",
            "subcategory":"Lawyer & Legal Services",
            "type":"Services"
        }
    ],
    "sg:phone":"+44 1600 716660",
    "sg:postcode":"NP25 3BR",
    "sg:province":"Gloucestershire",
    "sg:tags":[
        "solicitor"
    ],
    "wof:name":"Kenneth Hurley & Co",
    "wof:placetype":"venue"
},
  "geometry": {"coordinates":[-2.715034008,51.8131217957],"type":"Point"}
}