{
  "type": "Feature",
  "properties": {
    "addr:full":"Lord Street, St Nicholas Industrial Estate Carlisle Cumbria CA1 1TB",
    "addr:postcode":"ca1 1tb",
    "addr:street":"Lord Street St;Industrial Estate",
    "iso:country":"GB",
    "sg:address":"Lord Street, St Nicholas Industrial Estate",
    "sg:city":"Carlisle",
    "sg:classifiers":[
        {
            "category":"Retail",
            "subcategory":"Funeral Services",
            "type":"Services"
        }
    ],
    "sg:phone":"+44 1228 521363",
    "sg:postcode":"CA1 1TB",
    "sg:province":"Cumbria",
    "wof:name":"John J Graham",
    "wof:placetype":"venue"
},
  "geometry": {"coordinates":[-2.9282000065,54.8878898621],"type":"Point"}
}