{
  "type": "Feature",
  "properties": {
    "iso:country":"GB",
    "sg:address":"Unit C, Cross Green Close, Crooss Green Industrial Estate",
    "sg:city":"Leeds",
    "sg:classifiers":[
        {
            "category":"Manufacturing",
            "subcategory":"Lumber",
            "type":"Manufacturing & Wholesale Goods"
        },
        {
            "category":"Manufacturing",
            "subcategory":"Building Materials",
            "type":"Manufacturing & Wholesale Goods"
        }
    ],
    "sg:phone":"+44 113 217 7177",
    "sg:postcode":"LS9 0RY",
    "sg:province":"West Yorkshire",
    "sg:tags":[
        "merchant",
        "builder",
        "timber"
    ],
    "sg:website":"http://www.lawcris.co.uk",
    "wof:name":"Lawcris Panel Products Ltd",
    "wof:placetype":"venue"
},
  "geometry": {"coordinates":[-1.5131590366,53.7865562439],"type":"Point"}
}