{
  "type": "Feature",
  "properties": {
    "addr:full":"The Firs, Culmhead House, Culmhead Taunton Devon TA3 7DU",
    "addr:postcode":"ta3 7du",
    "addr:street":"Culmhead;Devon",
    "iso:country":"GB",
    "sg:address":"The Firs, Culmhead House, Culmhead",
    "sg:city":"Taunton",
    "sg:classifiers":[
        {
            "category":"Building & Trades",
            "subcategory":"Landscaping Services",
            "type":"Services"
        }
    ],
    "sg:phone":"+44 1823 421468",
    "sg:postcode":"TA3 7DU",
    "sg:province":"Devon",
    "sg:tags":[
        "gardening"
    ],
    "wof:name":"Somerset Garden Contractors",
    "wof:placetype":"venue"
},
  "geometry": {"coordinates":[-3.12671,50.943935],"type":"Point"}
}