{
  "type": "Feature",
  "properties": {
    "addr:full":"School Road Kilbirnie North Ayrshire KA25 7AX",
    "addr:postcode":"ka25 7ax",
    "addr:street":"School Road",
    "iso:country":"GB",
    "sg:address":"School Road",
    "sg:city":"Kilbirnie",
    "sg:classifiers":[
        {
            "category":"Education",
            "subcategory":"School",
            "type":"Public Place"
        }
    ],
    "sg:phone":"+44 1505 682685",
    "sg:postcode":"KA25 7AX",
    "sg:province":"North Ayrshire",
    "sg:tags":[
        "local",
        "authority"
    ],
    "wof:name":"Garnock Academy",
    "wof:placetype":"venue"
},
  "geometry": {"coordinates":[-4.6886382103,55.7560501099],"type":"Point"}
}