{
  "type": "Feature",
  "properties": {
    "iso:country":"GB",
    "sg:address":"158 Main Street, Baillieston",
    "sg:city":"Glasgow",
    "sg:classifiers":[
        {
            "category":"Personal",
            "subcategory":"Beauty Salon",
            "type":"Services"
        }
    ],
    "sg:phone":"+44 141 773 2080",
    "sg:postcode":"G69 6AH",
    "sg:province":"East Dunbartonshire",
    "wof:name":"The Bodyworx Tanning & Beauty Salon",
    "wof:placetype":"venue"
},
  "geometry": {"coordinates":[-4.1086001396,55.8510627747],"type":"Point"}
}