{
  "type": "Feature",
  "properties": {
    "iso:country":"GB",
    "sg:address":"172 South Street",
    "sg:city":"Liverpool",
    "sg:classifiers":[
        {
            "category":"Retail",
            "subcategory":"Auto Repair",
            "type":"Services"
        }
    ],
    "sg:phone":"+44 151 726 0634",
    "sg:postcode":"L8 3TZ",
    "sg:province":"Merseyside",
    "sg:tags":[
        "body",
        "car"
    ],
    "wof:name":"T R Motors",
    "wof:placetype":"venue"
},
  "geometry": {"coordinates":[-2.956135,53.389286],"type":"Point"}
}