{
  "type": "Feature",
  "properties": {
    "addr:full":"172 South Street Liverpool Merseyside L8 3TZ",
    "addr:housenumber":"172",
    "addr:postcode":"l8 3tz",
    "addr:street":"South Street",
    "iso:country":"GB",
    "sg:address":"172 South Street",
    "sg:city":"Liverpool",
    "sg:classifiers":[
        {
            "category":"Retail",
            "subcategory":"Auto Repair",
            "type":"Services"
        }
    ],
    "sg:phone":"+44 151 726 0634",
    "sg:postcode":"L8 3TZ",
    "sg:province":"Merseyside",
    "sg:tags":[
        "body",
        "car"
    ],
    "wof:name":"T R Motors",
    "wof:placetype":"venue"
},
  "geometry": {"coordinates":[-2.956135,53.389286],"type":"Point"}
}