{
  "type": "Feature",
  "properties": {
    "addr:full":"46 Chanel Street Galashiels Scottish Borders TD1 1BA",
    "addr:housenumber":"46",
    "addr:postcode":"td1 1ba",
    "addr:street":"Chanel Street",
    "iso:country":"GB",
    "sg:address":"46 Chanel Street",
    "sg:city":"Galashiels",
    "sg:classifiers":[
        {
            "category":"Shopping",
            "subcategory":"Department Store",
            "type":"Retail Goods"
        },
        {
            "category":"Wholesale",
            "subcategory":"Books, Periodicals, & Newspapers",
            "type":"Manufacturing & Wholesale Goods"
        }
    ],
    "sg:phone":"+44 1896 752202",
    "sg:postcode":"TD1 1BA",
    "sg:province":"Scottish Borders",
    "sg:tags":[
        "publishing"
    ],
    "wof:name":"Lothian Borders & Angus Co-Operative Society Ltd.",
    "wof:placetype":"venue"
},
  "geometry": {"coordinates":[-2.8084990978,55.6171798706],"type":"Point"}
}