{
  "type": "Feature",
  "properties": {
    "addr:full":"187 Roker Avenue Sunderland Tyne and Wear SR6 0BS",
    "addr:housenumber":"187",
    "addr:postcode":"sr6 0bs",
    "addr:street":"Roker Avenue",
    "iso:country":"GB",
    "sg:address":"187 Roker Avenue",
    "sg:city":"Sunderland",
    "sg:classifiers":[
        {
            "category":"Government",
            "subcategory":"Post Office",
            "type":"Public Place"
        }
    ],
    "sg:phone":"+44 191 565 6621",
    "sg:postcode":"SR6 0BS",
    "sg:province":"Tyne and Wear",
    "wof:name":"Roker Avenue Post Office",
    "wof:placetype":"venue"
},
  "geometry": {"coordinates":[-1.3785990477,54.9154586792],"type":"Point"}
}