{
  "type": "Feature",
  "properties": {
    "iso:country":"GB",
    "sg:address":"Hall Rd",
    "sg:city":"Norwich",
    "sg:classifiers":[
        {
            "category":"Manufacturing",
            "subcategory":"Apparel",
            "type":"Manufacturing & Wholesale Goods"
        }
    ],
    "sg:phone":"+44 1603 226040",
    "sg:postcode":"NR4 6DP",
    "sg:province":"Norfolk",
    "sg:tags":[
        "mnfr",
        "footwear"
    ],
    "wof:name":"Bally Outlet Store",
    "wof:placetype":"venue"
},
  "geometry": {"coordinates":[1.28964,52.609615],"type":"Point"}
}