{
  "type": "Feature",
  "properties": {
    "iso:country":"GB",
    "sg:address":"49 Whitechapel",
    "sg:city":"Liverpool",
    "sg:classifiers":[
        {
            "category":"Professional",
            "subcategory":"Art Services",
            "type":"Services"
        }
    ],
    "sg:postcode":"L1 6DT",
    "sg:province":"Merseyside",
    "sg:tags":[
        "photographer"
    ],
    "wof:name":"Turner,Lee,",
    "wof:placetype":"venue"
},
  "geometry": {"coordinates":[-2.9848520756,53.4069862366],"type":"Point"}
}