{
  "type": "Feature",
  "properties": {
    "addr:full":"6 Headley Road, Woodley Reading Berkshire RG5 4JA",
    "addr:housenumber":"6",
    "addr:postcode":"rg5 4ja",
    "addr:street":"Headley Road",
    "iso:country":"GB",
    "sg:address":"6 Headley Road, Woodley",
    "sg:city":"Reading",
    "sg:classifiers":[
        {
            "category":"Food & Beverages",
            "subcategory":"Supermarket",
            "type":"Retail Goods"
        }
    ],
    "sg:phone":"+44 118 969 2143",
    "sg:postcode":"RG5 4JA",
    "sg:province":"Berkshire",
    "wof:name":"Crs",
    "wof:placetype":"venue"
},
  "geometry": {"coordinates":[-0.8886229992,51.4561347961],"type":"Point"}
}