{
  "type": "Feature",
  "properties": {
    "iso:country":"GB",
    "sg:address":"67-73 Southfields Drive",
    "sg:city":"Leicester",
    "sg:classifiers":[
        {
            "category":"Government",
            "subcategory":"Post Office",
            "type":"Public Place"
        }
    ],
    "sg:phone":"+44 116 283 8729",
    "sg:postcode":"LE2 6QT",
    "sg:province":"Leicestershire",
    "wof:name":"Southfields Drive Post Office",
    "wof:placetype":"venue"
},
  "geometry": {"coordinates":[-1.1336359978,52.5970687866],"type":"Point"}
}