{
  "type": "Feature",
  "properties": {
    "addr:full":"1 Prospect Arcade, Prospect Street Bridlington East Riding of Yorkshire YO15 2AL",
    "addr:housenumber":"1;arcade",
    "addr:postcode":"yo15 2al",
    "addr:street":"Prospect;Prospect Street",
    "iso:country":"GB",
    "sg:address":"1 Prospect Arcade, Prospect Street",
    "sg:city":"Bridlington",
    "sg:classifiers":[
        {
            "category":"Shopping",
            "subcategory":"News",
            "type":"Retail Goods"
        }
    ],
    "sg:phone":"+44 1262 604759",
    "sg:postcode":"YO15 2AL",
    "sg:province":"East Riding of Yorkshire",
    "sg:tags":[
        "newsagent"
    ],
    "wof:name":"The New Town Crier",
    "wof:placetype":"venue"
},
  "geometry": {"coordinates":[-0.192425,54.083179],"type":"Point"}
}