{
  "type": "Feature",
  "properties": {
    "iso:country":"GB",
    "sg:address":"Room 2 First Floor, Northam Comm Ctr, Kent Street",
    "sg:city":"Southampton",
    "sg:classifiers":[
        {
            "category":"Organizations",
            "subcategory":"Non-profit Organization",
            "type":"Services"
        }
    ],
    "sg:phone":"+44 23 8033 7067",
    "sg:postcode":"SO14 5SP",
    "sg:province":"Hampshire",
    "sg:tags":[
        "organisation",
        "voluntary",
        "charity"
    ],
    "wof:name":"Pre School Learning Alliance",
    "wof:placetype":"venue"
},
  "geometry": {"coordinates":[-1.3880699873,50.9095611572],"type":"Point"}
}