{
  "type": "Feature",
  "properties": {
    "addr:full":"62 Trevithick Rd St. Austell Cornwall PL25 4RJ",
    "addr:housenumber":"62",
    "addr:postcode":"pl25 4rj",
    "addr:street":"Trevithick Rd",
    "iso:country":"GB",
    "sg:address":"62 Trevithick Rd",
    "sg:city":"St. Austell",
    "sg:classifiers":[
        {
            "category":"Building & Trades",
            "subcategory":"Construction",
            "type":"Services"
        }
    ],
    "sg:phone":"+44 1726 73621",
    "sg:postcode":"PL25 4RJ",
    "sg:province":"Cornwall",
    "sg:tags":[
        "builder"
    ],
    "wof:name":"Fox's",
    "wof:placetype":"venue"
},
  "geometry": {"coordinates":[-4.780571,50.336498],"type":"Point"}
}