{
  "type": "Feature",
  "properties": {
    "addr:full":"364 Halifax Road Keighley West Yorkshire BD21 5HW",
    "addr:housenumber":"364",
    "addr:postcode":"bd21 5hw",
    "addr:street":"Halifax Road",
    "iso:country":"GB",
    "sg:address":"364 Halifax Road",
    "sg:city":"Keighley",
    "sg:classifiers":[
        {
            "category":"Building & Trades",
            "subcategory":"Equipment Rental",
            "type":"Services"
        }
    ],
    "sg:postcode":"BD21 5HW",
    "sg:province":"West Yorkshire",
    "sg:tags":[
        "plant",
        "machinery"
    ],
    "wof:name":"Ian F Smith",
    "wof:placetype":"venue"
},
  "geometry": {"coordinates":[-1.9226510525,53.8441505432],"type":"Point"}
}