{
  "type": "Feature",
  "properties": {
    "addr:full":"6-8 Angel Crescent Bridgwater Somerset TA6 3EW",
    "addr:housenumber":"6-8",
    "addr:postcode":"ta6 3ew",
    "addr:street":"Angel Crescent",
    "iso:country":"GB",
    "sg:address":"6-8 Angel Crescent",
    "sg:city":"Bridgwater",
    "sg:classifiers":[
        {
            "category":"Real Estate",
            "subcategory":"Architect",
            "type":"Services"
        }
    ],
    "sg:phone":"+44 1278 457298",
    "sg:postcode":"TA6 3EW",
    "sg:province":"Somerset",
    "sg:tags":[
        "technologist",
        "architectural"
    ],
    "wof:name":"G & H Building Design Partnership",
    "wof:placetype":"venue"
},
  "geometry": {"coordinates":[-3.00567,51.129135],"type":"Point"}
}