{
  "type": "Feature",
  "properties": {
    "iso:country":"GB",
    "sg:address":"Ashvale, Nanty Bwch",
    "sg:city":"Tredegar",
    "sg:classifiers":[
        {
            "category":"Bars & Pubs",
            "type":"Food & Drink"
        }
    ],
    "sg:phone":"+44 1495 722176",
    "sg:postcode":"NP22 4AQ",
    "sg:province":"Blaenau Gwent",
    "sg:tags":[
        "pubs",
        "inn"
    ],
    "wof:name":"The Crown Inn",
    "wof:placetype":"venue"
},
  "geometry": {"coordinates":[-3.257397,51.784595],"type":"Point"}
}