{
  "type": "Feature",
  "properties": {
    "addr:full":"302 Ruislip Rd Greenford Greater London UB6 9RR",
    "addr:housenumber":"302",
    "addr:postcode":"ub6 9rr",
    "addr:street":"Ruislip Rd",
    "iso:country":"GB",
    "sg:address":"302 Ruislip Rd",
    "sg:city":"Greenford",
    "sg:classifiers":[
        {
            "category":"Building & Trades",
            "subcategory":"Cleaning & Sanitation",
            "type":"Services"
        }
    ],
    "sg:phone":"+44 70 5022 5003",
    "sg:postcode":"UB6 9RR",
    "sg:province":"Greater London",
    "sg:tags":[
        "commercial"
    ],
    "wof:name":"Pro-Clenze",
    "wof:placetype":"venue"
},
  "geometry": {"coordinates":[-0.3708620071,51.5328063965],"type":"Point"}
}