{
  "type": "Feature",
  "properties": {
    "iso:country":"GB",
    "sg:address":"141 Liverpool Road, Longton",
    "sg:city":"Preston",
    "sg:classifiers":[
        {
            "category":"Personal",
            "subcategory":"Beauty Salon",
            "type":"Services"
        }
    ],
    "sg:phone":"+44 1772 613556",
    "sg:postcode":"PR4 5AB",
    "sg:province":"Lancashire",
    "sg:tags":[
        "unisex",
        "hairdresser"
    ],
    "wof:name":"Michael Douglas Hair & Beauty",
    "wof:placetype":"venue"
},
  "geometry": {"coordinates":[-2.764959,53.732891],"type":"Point"}
}