{
  "type": "Feature",
  "properties": {
    "iso:country":"GB",
    "sg:address":"4 Etnam Street",
    "sg:city":"Leominster",
    "sg:classifiers":[
        {
            "category":"Social Services",
            "subcategory":"Child Care",
            "type":"Services"
        },
        {
            "category":"Retail",
            "subcategory":"Repair Shop",
            "type":"Services"
        }
    ],
    "sg:phone":"+44 1568 612069",
    "sg:postcode":"HR6 8AQ",
    "sg:province":"Herefordshire",
    "sg:tags":[
        "television",
        "good",
        "video",
        "servicing",
        "maintenance",
        "radio"
    ],
    "wof:name":"Inivision",
    "wof:placetype":"venue"
},
  "geometry": {"coordinates":[-2.738598,52.225956],"type":"Point"}
}