{
  "type": "Feature",
  "properties": {
    "addr:full":"Unit 1 Gro Park, North Street, Bridgtown Cannock Staffordshire WS11 3AZ",
    "addr:housenumber":"unit 1",
    "addr:postcode":"ws11 3az",
    "addr:street":"Gro Park North Street",
    "iso:country":"GB",
    "sg:address":"Unit 1 Gro Park, North Street, Bridgtown",
    "sg:city":"Cannock",
    "sg:classifiers":[
        {
            "category":"Home & Garden",
            "subcategory":"Home Furnishings",
            "type":"Retail Goods"
        }
    ],
    "sg:phone":"+44 1543 503392",
    "sg:postcode":"WS11 3AZ",
    "sg:province":"Staffordshire",
    "sg:tags":[
        "merchant",
        "diy",
        "decorators'"
    ],
    "wof:name":"S J Dixon & Son Ltd.",
    "wof:placetype":"venue"
},
  "geometry": {"coordinates":[-2.025671,52.683681],"type":"Point"}
}