{
  "type": "Feature",
  "properties": {
    "iso:country":"GB",
    "sg:address":"35 Chalk Farm Road",
    "sg:city":"London",
    "sg:classifiers":[
        {
            "category":"Bars & Pubs",
            "type":"Food & Drink"
        }
    ],
    "sg:phone":"+44 20 7485 0909",
    "sg:postcode":"NW1 8AJ",
    "sg:province":"Greater London",
    "sg:tags":[
        "pubs",
        "inn"
    ],
    "wof:name":"The Lock Tavern",
    "wof:placetype":"venue"
},
  "geometry": {"coordinates":[-0.1478189975,51.5427207947],"type":"Point"}
}