{
  "type": "Feature",
  "properties": {
    "iso:country":"GB",
    "sg:address":"236 Main Rd, Gidea Park",
    "sg:city":"Romford",
    "sg:classifiers":[
        {
            "category":"Building & Trades",
            "subcategory":"Construction",
            "type":"Services"
        }
    ],
    "sg:postcode":"RM2 5HA",
    "sg:province":"Essex",
    "sg:tags":[
        "builder"
    ],
    "wof:name":"Skillsector Ltd",
    "wof:placetype":"venue"
},
  "geometry": {"coordinates":[0.201865,51.586926],"type":"Point"}
}