{
  "type": "Feature",
  "properties": {
    "addr:full":"Springfields, Ely Road Ely Cambridgeshire CB6 3HJ",
    "addr:postcode":"cb6 3hj",
    "addr:street":"Springfields Ely Road",
    "iso:country":"GB",
    "sg:address":"Springfields, Ely Road",
    "sg:city":"Ely",
    "sg:classifiers":[
        {
            "category":"Building & Trades",
            "subcategory":"Plumbing",
            "type":"Services"
        }
    ],
    "sg:postcode":"CB6 3HJ",
    "sg:province":"Cambridgeshire",
    "sg:tags":[
        "consultant",
        "heating"
    ],
    "wof:name":"Bailey & Biggadike",
    "wof:placetype":"venue"
},
  "geometry": {"coordinates":[0.243509993,52.3712882996],"type":"Point"}
}