{
  "type": "Feature",
  "properties": {
    "iso:country":"GB",
    "sg:address":"191 Park Road",
    "sg:city":"Barnsley",
    "sg:classifiers":[
        {
            "category":"Home & Garden",
            "subcategory":"Household Appliances",
            "type":"Retail Goods"
        }
    ],
    "sg:phone":"+44 1226 201092",
    "sg:postcode":"S70 1YL",
    "sg:province":"South Yorkshire",
    "sg:tags":[
        "repairs",
        "domestic",
        "servicing",
        "centre"
    ],
    "wof:name":"Universal Appliances",
    "wof:placetype":"venue"
},
  "geometry": {"coordinates":[-1.4836729765,53.5448608398],"type":"Point"}
}