{
  "type": "Feature",
  "properties": {
    "iso:country":"GB",
    "sg:address":"Walton Church Post Office, 201-203 County Road, Walton",
    "sg:city":"Liverpool",
    "sg:classifiers":[
        {
            "category":"Government",
            "subcategory":"Post Office",
            "type":"Public Place"
        }
    ],
    "sg:phone":"+44 151 525 1461",
    "sg:postcode":"L4 5PB",
    "sg:province":"Merseyside",
    "wof:name":"WALTON CHURCH POST OFFICE",
    "wof:placetype":"venue"
},
  "geometry": {"coordinates":[-2.969639,53.444099],"type":"Point"}
}