{
  "type": "Feature",
  "properties": {
    "addr:full":"10 Bridge Street Godalming Surrey GU7 1HY",
    "addr:housenumber":"10",
    "addr:postcode":"gu7 1hy",
    "addr:street":"Bridge Street",
    "iso:country":"GB",
    "sg:address":"10 Bridge Street",
    "sg:city":"Godalming",
    "sg:classifiers":[
        {
            "category":"Fast Food",
            "type":"Food & Drink"
        }
    ],
    "sg:phone":"+44 1483 425406",
    "sg:postcode":"GU7 1HY",
    "sg:province":"Surrey",
    "sg:tags":[
        "away",
        "take"
    ],
    "wof:name":"Mogul Spices",
    "wof:placetype":"venue"
},
  "geometry": {"coordinates":[-0.6094790101,51.1863327026],"type":"Point"}
}