{
  "type": "Feature",
  "properties": {
    "iso:country":"GB",
    "sg:address":"67 High St",
    "sg:city":"Stourbridge",
    "sg:classifiers":[
        {
            "category":"Manufacturing",
            "subcategory":"Tools & Machinery",
            "type":"Manufacturing & Wholesale Goods"
        }
    ],
    "sg:phone":"+44 1384 401322",
    "sg:postcode":"DY8 5SE",
    "sg:province":"Staffordshire",
    "sg:tags":[
        "society",
        "friendly"
    ],
    "wof:name":"Independent Floorcovering Assessors",
    "wof:placetype":"venue"
},
  "geometry": {"coordinates":[-2.1606259346,52.4785346985],"type":"Point"}
}