{
  "type": "Feature",
  "properties": {
    "addr:full":"Swan Centre Birmingham West Midlands B26 1AJ",
    "addr:postcode":"b26 1aj",
    "iso:country":"GB",
    "sg:address":"Swan Centre",
    "sg:city":"Birmingham",
    "sg:classifiers":[
        {
            "category":"Shopping",
            "subcategory":"Mobile Phones",
            "type":"Retail Goods"
        }
    ],
    "sg:phone":"+44 121 694 5333",
    "sg:postcode":"B26 1AJ",
    "sg:province":"West Midlands",
    "wof:name":"Fone Shop The",
    "wof:placetype":"venue"
},
  "geometry": {"coordinates":[-1.8140389919,52.4612007141],"type":"Point"}
}