{
  "type": "Feature",
  "properties": {
    "iso:country":"GB",
    "sg:address":"P O Box 96, 6 Stortford Road",
    "sg:city":"Dunmow",
    "sg:classifiers":[
        {
            "category":"Professional",
            "subcategory":"Advertising",
            "type":"Services"
        }
    ],
    "sg:phone":"+44 1371 874152",
    "sg:postcode":"CM6 1UA",
    "sg:province":"Essex",
    "sg:tags":[
        "agency"
    ],
    "wof:name":"M D A (Marketing Services) Ltd.",
    "wof:placetype":"venue"
},
  "geometry": {"coordinates":[0.3649770021,51.8706130981],"type":"Point"}
}