{
  "type": "Feature",
  "properties": {
    "addr:full":"29 Lockwood Rd, Goldthorpe Rotherham South Yorkshire S63 9JY",
    "addr:housenumber":"29",
    "addr:postcode":"s63 9jy",
    "addr:street":"Lockwood Rd",
    "iso:country":"GB",
    "sg:address":"29 Lockwood Rd, Goldthorpe",
    "sg:city":"Rotherham",
    "sg:classifiers":[
        {
            "category":"Professional",
            "subcategory":"Management & Consulting",
            "type":"Services"
        }
    ],
    "sg:phone":"+44 1709 895725",
    "sg:postcode":"S63 9JY",
    "sg:province":"South Yorkshire",
    "sg:tags":[
        "fire",
        "consultant",
        "protection"
    ],
    "wof:name":"Aarresta Fire Ltd",
    "wof:placetype":"venue"
},
  "geometry": {"coordinates":[-1.302798,53.536621],"type":"Point"}
}