{
  "type": "Feature",
  "properties": {
    "iso:country":"GB",
    "sg:address":"2b Swinton Meadows Industrial Estate, Meadow Way, Swinton",
    "sg:city":"Mexborough",
    "sg:classifiers":[
        {
            "category":"Manufacturing",
            "subcategory":"Rubber & Plastics",
            "type":"Manufacturing & Wholesale Goods"
        }
    ],
    "sg:postcode":"S64 8AB",
    "sg:province":"South Yorkshire",
    "sg:tags":[
        "product"
    ],
    "wof:name":"Pace Packaging Supplies",
    "wof:placetype":"venue"
},
  "geometry": {"coordinates":[-1.2999429703,53.4887924194],"type":"Point"}
}