{
  "type": "Feature",
  "properties": {
    "iso:country":"GB",
    "sg:address":"240 Sidegate Lane",
    "sg:city":"Ipswich",
    "sg:classifiers":[
        {
            "category":"Health Services",
            "subcategory":"Health Practitioner",
            "type":"Services"
        }
    ],
    "sg:phone":"+44 1473 726902",
    "sg:postcode":"IP4 3DH",
    "sg:province":"Suffolk",
    "sg:tags":[
        "homoeopathic",
        "herbalist"
    ],
    "wof:name":"Stephen Kippax",
    "wof:placetype":"venue"
},
  "geometry": {"coordinates":[1.1829249859,52.0702171326],"type":"Point"}
}