{
  "type": "Feature",
  "properties": {
    "iso:country":"GB",
    "sg:address":"Canal Works, Effingham Road",
    "sg:city":"Sheffield",
    "sg:classifiers":[
        {
            "category":"Manufacturing",
            "subcategory":"Metals",
            "type":"Manufacturing & Wholesale Goods"
        }
    ],
    "sg:phone":"+44 114 273 1893",
    "sg:postcode":"S4 7ZB",
    "sg:province":"South Yorkshire",
    "sg:tags":[
        "steel",
        "stockholder"
    ],
    "wof:name":"Taylor Forgings",
    "wof:placetype":"venue"
},
  "geometry": {"coordinates":[-1.4601800442,53.3876113892],"type":"Point"}
}