{
  "type": "Feature",
  "properties": {
    "addr:full":"10-12 Fiveways Parade, Hazel Gro Stockport Cheshire SK7 6DG",
    "addr:housenumber":"10-12",
    "addr:postcode":"sk7 6dg",
    "addr:street":"Fiveways Parade",
    "iso:country":"GB",
    "sg:address":"10-12 Fiveways Parade, Hazel Gro",
    "sg:city":"Stockport",
    "sg:classifiers":[
        {
            "category":"Food & Beverages",
            "subcategory":"Groceries & Convenience Stores",
            "type":"Retail Goods"
        }
    ],
    "sg:phone":"+44 1625 872407",
    "sg:postcode":"SK7 6DG",
    "sg:province":"Cheshire",
    "wof:name":"Spar 8 Till Late",
    "wof:placetype":"venue"
},
  "geometry": {"coordinates":[-2.11422,53.367908],"type":"Point"}
}