{
  "type": "Feature",
  "properties": {
    "addr:full":"Enquiries Beaumaris Isle of Anglesey LL58 8AL",
    "addr:postcode":"ll58 8al",
    "addr:street":"Beaumaris",
    "iso:country":"GB",
    "sg:address":"Enquiries",
    "sg:city":"Beaumaris",
    "sg:classifiers":[
        {
            "category":"Health Services",
            "subcategory":"Clinic",
            "type":"Services"
        }
    ],
    "sg:phone":"+44 1248 810818",
    "sg:postcode":"LL58 8AL",
    "sg:province":"Isle of Anglesey",
    "sg:tags":[
        "nh"
    ],
    "wof:name":"Beaumaris Health Centre",
    "wof:placetype":"venue"
},
  "geometry": {"coordinates":[-4.101129055,53.2770805359],"type":"Point"}
}