{
  "type": "Feature",
  "properties": {
    "iso:country":"GB",
    "sg:address":"Britannia Chambers, 18a Horsemarket",
    "sg:city":"Barnard Castle",
    "sg:classifiers":[
        {
            "category":"Professional",
            "type":"Services"
        }
    ],
    "sg:phone":"+44 1833 630125",
    "sg:postcode":"DL12 8LZ",
    "sg:province":"Cumbria",
    "sg:tags":[
        "archaeologist"
    ],
    "wof:name":"The Brigantia Archaelogists Practice",
    "wof:placetype":"venue"
},
  "geometry": {"coordinates":[-1.9238090515,54.5431518555],"type":"Point"}
}