{
  "type": "Feature",
  "properties": {
    "addr:full":"41 Maiden Lane, Covent Garden London Greater London WC2E 7LJ",
    "addr:housenumber":"41",
    "addr:postcode":"wc2e 7lj",
    "addr:street":"Maiden Lane",
    "iso:country":"GB",
    "sg:address":"41 Maiden Lane, Covent Garden",
    "sg:city":"London",
    "sg:classifiers":[
        {
            "category":"Building & Trades",
            "subcategory":"Construction",
            "type":"Services"
        }
    ],
    "sg:phone":"+44 20 7240 0461",
    "sg:postcode":"WC2E 7LJ",
    "sg:province":"Greater London",
    "sg:tags":[
        "builder"
    ],
    "wof:name":"Education Project Services Ltd.",
    "wof:placetype":"venue"
},
  "geometry": {"coordinates":[-0.126397,51.542717],"type":"Point"}
}