{
  "type": "Feature",
  "properties": {
    "addr:full":"170 Gt Portland St London Greater London W1W 5QD",
    "addr:housenumber":"170",
    "addr:postcode":"w1w 5qd",
    "addr:street":"Gt Portland St",
    "iso:country":"GB",
    "sg:address":"170 Gt Portland St",
    "sg:city":"London",
    "sg:classifiers":[
        {
            "category":"Restaurant",
            "type":"Food & Drink"
        }
    ],
    "sg:phone":"+44 20 7631 3131",
    "sg:postcode":"W1W 5QD",
    "sg:province":"Greater London",
    "wof:name":"Villandry Ltd",
    "wof:placetype":"venue"
},
  "geometry": {"coordinates":[-0.1460489929,51.5229110718],"type":"Point"}
}