{
  "type": "Feature",
  "properties": {
    "addr:full":"Standbrook Ho, 1st Floor Suite D, 2-5 Old Bond St West End Hampshire W1X 3TB",
    "addr:housenumber":"1st floor suite d 2-5",
    "addr:postcode":"w1x 3tb",
    "addr:street":"Old Bond St",
    "iso:country":"GB",
    "sg:address":"Standbrook Ho, 1st Floor Suite D, 2-5 Old Bond St",
    "sg:city":"West End",
    "sg:classifiers":[
        {
            "category":"Banks & Credit Unions",
            "subcategory":"Financial Services",
            "type":"Services"
        }
    ],
    "sg:phone":"+44 20 7491 0201",
    "sg:postcode":"W1X 3TB",
    "sg:province":"Hampshire",
    "sg:tags":[
        "consultant"
    ],
    "wof:name":"Pixpalm Financial Services Ltd",
    "wof:placetype":"venue"
},
  "geometry": {"coordinates":[-0.1389899999,51.5075798035],"type":"Point"}
}