{
  "type": "Feature",
  "properties": {
    "iso:country":"GB",
    "sg:address":"Brocket Grn, Rhinefield Road",
    "sg:city":"Brockenhurst",
    "sg:classifiers":[
        {
            "category":"Health Services",
            "subcategory":"Doctor",
            "type":"Services"
        }
    ],
    "sg:phone":"+44 1590 622168",
    "sg:postcode":"SO42 7SR",
    "sg:province":"Hampshire",
    "sg:tags":[
        "surgeon"
    ],
    "wof:name":"J F Miller",
    "wof:placetype":"venue"
},
  "geometry": {"coordinates":[-1.572004,50.818642],"type":"Point"}
}