{
  "type": "Feature",
  "properties": {
    "addr:full":"19 Edenhurst Drive Liverpool Lancashire L37 2LH",
    "addr:housenumber":"19",
    "addr:postcode":"l37 2lh",
    "addr:street":"Edenhurst Drive",
    "iso:country":"GB",
    "sg:address":"19 Edenhurst Drive",
    "sg:city":"Liverpool",
    "sg:classifiers":[
        {
            "category":"Organizations",
            "subcategory":"Non-profit Organization",
            "type":"Services"
        }
    ],
    "sg:phone":"+44 1704 878818",
    "sg:postcode":"L37 2LH",
    "sg:province":"Lancashire",
    "sg:tags":[
        "charitable",
        "organisation",
        "voluntary",
        "charity"
    ],
    "wof:name":"Royal National Lifeboat Institution",
    "wof:placetype":"venue"
},
  "geometry": {"coordinates":[-3.0855019093,53.5546607971],"type":"Point"}
}