{
  "type": "Feature",
  "properties": {
    "addr:full":"Unit 28d, Watness Avenue, Skelton Industrial Estate Saltburn-by-the-sea North Yorkshire TS12 2LQ",
    "addr:housenumber":"28d",
    "addr:postcode":"ts12 2lq",
    "addr:street":"Watness Avenue;Industrial",
    "iso:country":"GB",
    "sg:address":"Unit 28d, Watness Avenue, Skelton Industrial Estate",
    "sg:city":"Saltburn-by-the-sea",
    "sg:classifiers":[
        {
            "category":"Home & Garden",
            "subcategory":"Home Furnishings",
            "type":"Retail Goods"
        }
    ],
    "sg:postcode":"TS12 2LQ",
    "sg:province":"North Yorkshire",
    "sg:tags":[
        "awning",
        "canopy",
        "blinds"
    ],
    "wof:name":"Blindspot",
    "wof:placetype":"venue"
},
  "geometry": {"coordinates":[-0.9641389847,54.5638961792],"type":"Point"}
}