{
  "type": "Feature",
  "properties": {
    "addr:full":"44 College Hill Road Harrow Greater London HA3 7HE",
    "addr:housenumber":"44",
    "addr:postcode":"ha3 7he",
    "addr:street":"College Hill Road",
    "iso:country":"GB",
    "sg:address":"44 College Hill Road",
    "sg:city":"Harrow",
    "sg:classifiers":[
        {
            "category":"Professional",
            "subcategory":"Computer Services",
            "type":"Services"
        }
    ],
    "sg:postcode":"HA3 7HE",
    "sg:province":"Greater London",
    "sg:tags":[
        "system",
        "software"
    ],
    "wof:name":"Nubicom Ltd",
    "wof:placetype":"venue"
},
  "geometry": {"coordinates":[-0.330556,51.603725],"type":"Point"}
}