{
  "type": "Feature",
  "properties": {
    "iso:country":"GB",
    "sg:address":"67 Lower Bristol Road",
    "sg:city":"Bath",
    "sg:classifiers":[
        {
            "category":"Manufacturing",
            "subcategory":"Signs",
            "type":"Manufacturing & Wholesale Goods"
        }
    ],
    "sg:phone":"+44 1225 422688",
    "sg:postcode":"BA2 3BG",
    "sg:province":"Somerset",
    "sg:tags":[
        "nameplate"
    ],
    "wof:name":"Coppermere Trading Ltd.",
    "wof:placetype":"venue"
},
  "geometry": {"coordinates":[-2.370207,51.379353],"type":"Point"}
}