{
  "type": "Feature",
  "properties": {
    "iso:country":"GB",
    "sg:address":"38 St John Street",
    "sg:city":"Bridgwater",
    "sg:classifiers":[
        {
            "category":"Fast Food",
            "type":"Food & Drink"
        }
    ],
    "sg:phone":"+44 1278 433505",
    "sg:postcode":"TA6 5HS",
    "sg:province":"Somerset",
    "sg:tags":[
        "away",
        "take"
    ],
    "wof:name":"Carnivores",
    "wof:placetype":"venue"
},
  "geometry": {"coordinates":[-2.995495,51.128376],"type":"Point"}
}