{
  "type": "Feature",
  "properties": {
    "iso:country":"GB",
    "sg:address":"Unit 15 Martis Mills",
    "sg:city":"Stroud",
    "sg:classifiers":[
        {
            "category":"Building & Trades",
            "subcategory":"Construction",
            "type":"Services"
        }
    ],
    "sg:phone":"+44 1453 834450",
    "sg:postcode":"GL5 5EU",
    "sg:province":"Gloucestershire",
    "sg:tags":[
        "builder",
        "contractor"
    ],
    "wof:name":"Turnkey Construction Ltd",
    "wof:placetype":"venue"
},
  "geometry": {"coordinates":[-2.2219181061,51.722328186],"type":"Point"}
}