{
  "type": "Feature",
  "properties": {
    "iso:country":"GB",
    "sg:address":"5 Tradecroft",
    "sg:city":"Portland",
    "sg:classifiers":[
        {
            "category":"Shopping",
            "subcategory":"Hobbies, Toys, & Games",
            "type":"Retail Goods"
        }
    ],
    "sg:phone":"+44 1305 823286",
    "sg:postcode":"DT5 2LN",
    "sg:province":"Dorset",
    "sg:tags":[
        "toy"
    ],
    "wof:name":"Puffin Wooden Games",
    "wof:placetype":"venue"
},
  "geometry": {"coordinates":[-2.444312,50.550224],"type":"Point"}
}