{
  "type": "Feature",
  "properties": {
    "addr:full":"Elder Road, Cobridge Stoke-on-trent Staffordshire ST6 2BU",
    "addr:postcode":"st6 2bu",
    "addr:street":"Elder Road",
    "iso:country":"GB",
    "sg:address":"Elder Road, Cobridge",
    "sg:city":"Stoke-on-trent",
    "sg:classifiers":[
        {
            "category":"Autos & Motor Vehicles",
            "subcategory":"Auto Supplies",
            "type":"Retail Goods"
        }
    ],
    "sg:phone":"+44 1782 834215",
    "sg:postcode":"ST6 2BU",
    "sg:province":"Staffordshire",
    "sg:tags":[
        "tyre"
    ],
    "wof:name":"The Harris Motor Co. Ltd.",
    "wof:placetype":"venue"
},
  "geometry": {"coordinates":[-2.188064,53.041073],"type":"Point"}
}