{
  "type": "Feature",
  "properties": {
    "addr:full":"5 Central Avenue Carlisle Cumbria CA1 3QB",
    "addr:housenumber":"5",
    "addr:postcode":"ca1 3qb",
    "addr:street":"Central Avenue",
    "iso:country":"GB",
    "sg:address":"5 Central Avenue",
    "sg:city":"Carlisle",
    "sg:classifiers":[
        {
            "category":"Food & Beverages",
            "subcategory":"Groceries & Convenience Stores",
            "type":"Retail Goods"
        }
    ],
    "sg:postcode":"CA1 3QB",
    "sg:province":"Cumbria",
    "wof:name":"Mace Food Store",
    "wof:placetype":"venue"
},
  "geometry": {"coordinates":[-2.9018919468,54.8816566467],"type":"Point"}
}