{
  "type": "Feature",
  "properties": {
    "addr:full":"9a-11 Raeburn Place Edinburgh City of Edinburgh EH4 1HU",
    "addr:housenumber":"9a-11",
    "addr:postcode":"eh4 1hu",
    "addr:street":"Raeburn Place Edinburgh",
    "iso:country":"GB",
    "sg:address":"9a-11 Raeburn Place",
    "sg:city":"Edinburgh",
    "sg:classifiers":[
        {
            "category":"Shopping",
            "subcategory":"Department Store",
            "type":"Retail Goods"
        },
        {
            "category":"Food & Beverages",
            "subcategory":"Groceries & Convenience Stores",
            "type":"Retail Goods"
        }
    ],
    "sg:phone":"+44 131 315 2107",
    "sg:postcode":"EH4 1HU",
    "sg:province":"City of Edinburgh",
    "wof:name":"Stevie's General Store",
    "wof:placetype":"venue"
},
  "geometry": {"coordinates":[-3.2105619907,55.958782196],"type":"Point"}
}