{
  "type": "Feature",
  "properties": {
    "addr:full":"20 Pike Law Lane Huddersfield West Yorkshire HD7 4PL",
    "addr:housenumber":"20",
    "addr:postcode":"hd7 4pl",
    "addr:street":"Pike Law Lane",
    "iso:country":"GB",
    "sg:address":"20 Pike Law Lane",
    "sg:city":"Huddersfield",
    "sg:classifiers":[
        {
            "category":"Building & Trades",
            "subcategory":"Construction",
            "type":"Services"
        }
    ],
    "sg:phone":"+44 1484 641504",
    "sg:postcode":"HD7 4PL",
    "sg:province":"West Yorkshire",
    "sg:tags":[
        "joinery"
    ],
    "wof:name":"Gill Joinery",
    "wof:placetype":"venue"
},
  "geometry": {"coordinates":[-1.868074,53.643276],"type":"Point"}
}