{
  "type": "Feature",
  "properties": {
    "addr:full":"Wakefield Road Cockermouth Cumbria CA13 0HZ",
    "addr:postcode":"ca13 0hz",
    "addr:street":"Wakefield Road",
    "iso:country":"GB",
    "sg:address":"Wakefield Road",
    "sg:city":"Cockermouth",
    "sg:classifiers":[
        {
            "category":"Health Services",
            "subcategory":"Doctor",
            "type":"Services"
        }
    ],
    "sg:phone":"+44 1900 324100",
    "sg:postcode":"CA13 0HZ",
    "sg:province":"Cumbria",
    "sg:tags":[
        "practitioners"
    ],
    "wof:name":"Derwent House Surgery",
    "wof:placetype":"venue"
},
  "geometry": {"coordinates":[-3.3694839478,54.6654052734],"type":"Point"}
}