{
  "type": "Feature",
  "properties": {
    "addr:full":"15a Lowtown Pudsey West Yorkshire LS28 7BQ",
    "addr:housenumber":"15a",
    "addr:postcode":"ls28 7bq",
    "addr:street":"West",
    "iso:country":"GB",
    "sg:address":"15a Lowtown",
    "sg:city":"Pudsey",
    "sg:classifiers":[
        {
            "category":"Organizations",
            "subcategory":"Membership Organization",
            "type":"Services"
        }
    ],
    "sg:phone":"+44 113 255 8459",
    "sg:postcode":"LS28 7BQ",
    "sg:province":"West Yorkshire",
    "sg:tags":[
        "club"
    ],
    "wof:name":"Pudsey Liberal Club Building Co. Ltd.",
    "wof:placetype":"venue"
},
  "geometry": {"coordinates":[-1.66099,53.797283],"type":"Point"}
}