{
  "type": "Feature",
  "properties": {
    "addr:full":"Baltimore Road, Great Barr Birmingham West Midlands B42 1DD",
    "addr:postcode":"b42 1dd",
    "addr:street":"Baltimore Road",
    "iso:country":"GB",
    "sg:address":"Baltimore Road, Great Barr",
    "sg:city":"Birmingham",
    "sg:classifiers":[
        {
            "category":"Manufacturing",
            "subcategory":"Building Materials",
            "type":"Manufacturing & Wholesale Goods"
        }
    ],
    "sg:phone":"+44 121 356 5575",
    "sg:postcode":"B42 1DD",
    "sg:province":"West Midlands",
    "sg:tags":[
        "merchant",
        "builder"
    ],
    "wof:name":"Concrete Developments (Great Barr) Ltd.",
    "wof:placetype":"venue"
},
  "geometry": {"coordinates":[-1.9264090061,52.5304679871],"type":"Point"}
}