{
  "type": "Feature",
  "properties": {
    "addr:full":"10 Metcalfe Road, Skippers Lane Industrial Estate Middlesbrough North Yorkshire TS6 6PT",
    "addr:housenumber":"10",
    "addr:postcode":"ts6 6pt",
    "addr:street":"Metcalfe Road Skippers Lane Industrial Estate",
    "iso:country":"GB",
    "sg:address":"10 Metcalfe Road, Skippers Lane Industrial Estate",
    "sg:city":"Middlesbrough",
    "sg:classifiers":[
        {
            "category":"Home & Garden",
            "subcategory":"Home Furnishings",
            "type":"Retail Goods"
        }
    ],
    "sg:phone":"+44 1642 440340",
    "sg:postcode":"TS6 6PT",
    "sg:province":"North Yorkshire",
    "sg:tags":[
        "merchant",
        "diy",
        "decorators'"
    ],
    "wof:name":"Crown Brolac Decorator Centre",
    "wof:placetype":"venue"
},
  "geometry": {"coordinates":[-1.187089,54.574585],"type":"Point"}
}