{
  "type": "Feature",
  "properties": {
    "addr:full":"28 Market Street Tamworth Staffordshire B79 7LR",
    "addr:housenumber":"28",
    "addr:postcode":"b79 7lr",
    "addr:street":"Market Street",
    "iso:country":"GB",
    "sg:address":"28 Market Street",
    "sg:city":"Tamworth",
    "sg:classifiers":[
        {
            "category":"Shopping",
            "subcategory":"Gifts & Souvenirs",
            "type":"Retail Goods"
        }
    ],
    "sg:phone":"+44 1827 68291",
    "sg:postcode":"B79 7LR",
    "sg:province":"Staffordshire",
    "sg:tags":[
        "shop"
    ],
    "wof:name":"Just Imagine (Tamworth)",
    "wof:placetype":"venue"
},
  "geometry": {"coordinates":[-1.695549,52.633137],"type":"Point"}
}