{
  "type": "Feature",
  "properties": {
    "addr:full":"Whalley Rd Burnley Lancashire BB12 7PN",
    "addr:postcode":"bb12 7pn",
    "addr:street":"Whalley Rd",
    "iso:country":"GB",
    "sg:address":"Whalley Rd",
    "sg:city":"Burnley",
    "sg:classifiers":[
        {
            "category":"Arena",
            "subcategory":"Sports Club",
            "type":"Entertainment"
        }
    ],
    "sg:phone":"+44 1282 771515",
    "sg:postcode":"BB12 7PN",
    "sg:province":"Lancashire",
    "wof:name":"Read Cricket & Bowling Club",
    "wof:placetype":"venue"
},
  "geometry": {"coordinates":[-2.3305230141,53.8027763367],"type":"Point"}
}