{
  "type": "Feature",
  "properties": {
    "addr:full":"Unit 1, Spires Buss Units, Mugiemoss Road Aberdeen Aberdeen City AB21 9UR",
    "addr:housenumber":"unit 1",
    "addr:postcode":"ab21 9ur",
    "addr:street":"Mugiemoss Road",
    "iso:country":"GB",
    "sg:address":"Unit 1, Spires Buss Units, Mugiemoss Road",
    "sg:city":"Aberdeen",
    "sg:classifiers":[
        {
            "category":"Retail",
            "subcategory":"Auto Repair",
            "type":"Services"
        }
    ],
    "sg:phone":"+44 1224 681391",
    "sg:postcode":"AB21 9UR",
    "sg:province":"Aberdeen City",
    "sg:tags":[
        "modification",
        "garage"
    ],
    "wof:name":"Granite City Motors",
    "wof:placetype":"venue"
},
  "geometry": {"coordinates":[-2.14812994,57.174331665],"type":"Point"}
}