{
  "type": "Feature",
  "properties": {
    "addr:full":"Maitland St Stockport Cheshire SK1 4ND",
    "addr:postcode":"sk1 4nd",
    "addr:street":"Maitland St",
    "iso:country":"GB",
    "sg:address":"Maitland St",
    "sg:city":"Stockport",
    "sg:classifiers":[
        {
            "category":"Place Of Worship",
            "type":"Public Place"
        }
    ],
    "sg:phone":"+44 1625 584225",
    "sg:postcode":"SK1 4ND",
    "sg:province":"Cheshire",
    "wof:name":"Union United Reformed Church",
    "wof:placetype":"venue"
},
  "geometry": {"coordinates":[-2.143939,53.401295],"type":"Point"}
}