{
  "type": "Feature",
  "properties": {
    "iso:country":"GB",
    "sg:address":"Unit 4 James Farm James Lane",
    "sg:city":"Reading",
    "sg:classifiers":[
        {
            "category":"Building & Trades",
            "subcategory":"Construction",
            "type":"Services"
        }
    ],
    "sg:phone":"+44 118 983 3180",
    "sg:postcode":"RG7 1ND",
    "sg:province":"Berkshire",
    "sg:tags":[
        "roofing"
    ],
    "wof:name":"Evans & Sons",
    "wof:placetype":"venue"
},
  "geometry": {"coordinates":[-1.030205,51.401558],"type":"Point"}
}