{
  "type": "Feature",
  "properties": {
    "addr:full":"591-595 Mansfield Rd Nottingham Nottinghamshire NG5 2FW",
    "addr:housenumber":"591-595",
    "addr:postcode":"ng5 2fw",
    "addr:street":"Mansfield Rd",
    "iso:country":"GB",
    "sg:address":"591-595 Mansfield Rd",
    "sg:city":"Nottingham",
    "sg:classifiers":[
        {
            "category":"Shopping",
            "subcategory":"Thrift Store",
            "type":"Retail Goods"
        }
    ],
    "sg:phone":"+44 115 969 1766",
    "sg:postcode":"NG5 2FW",
    "sg:province":"Nottinghamshire",
    "sg:tags":[
        "shop",
        "charity"
    ],
    "wof:name":"Imperial Cancer Research Fund",
    "wof:placetype":"venue"
},
  "geometry": {"coordinates":[-1.145759,52.98241],"type":"Point"}
}