{
  "type": "Feature",
  "properties": {
    "addr:full":"1 Mill Parade Newport Newport NP20 2JQ",
    "addr:housenumber":"1",
    "addr:postcode":"np20 2jq",
    "addr:street":"Mill Parade",
    "iso:country":"GB",
    "sg:address":"1 Mill Parade",
    "sg:city":"Newport",
    "sg:classifiers":[
        {
            "category":"Retail",
            "subcategory":"Auto Repair",
            "type":"Services"
        }
    ],
    "sg:postcode":"NP20 2JQ",
    "sg:province":"Newport",
    "sg:tags":[
        "modification",
        "garage",
        "related"
    ],
    "wof:name":"EVANS & WATKINS MOTOR ENGINEERS",
    "wof:placetype":"venue"
},
  "geometry": {"coordinates":[-2.987644,51.57494],"type":"Point"}
}