{
  "type": "Feature",
  "properties": {
    "addr:full":"13 Station Road Ilkeston Derbyshire DE7 5LY",
    "addr:housenumber":"13",
    "addr:postcode":"de7 5ly",
    "addr:street":"Station Road",
    "iso:country":"GB",
    "sg:address":"13 Station Road",
    "sg:city":"Ilkeston",
    "sg:classifiers":[
        {
            "category":"Home & Garden",
            "subcategory":"Carpets & Floor Coverings",
            "type":"Retail Goods"
        }
    ],
    "sg:phone":"+44 115 944 0424",
    "sg:postcode":"DE7 5LY",
    "sg:province":"Derbyshire",
    "sg:tags":[
        "carpets",
        "rug",
        "matting"
    ],
    "wof:name":"Noritake Collectors Club (U K ) Ltd.",
    "wof:placetype":"venue"
},
  "geometry": {"coordinates":[-1.3074500561,52.9750480652],"type":"Point"}
}