{
  "type": "Feature",
  "properties": {
    "iso:country":"GB",
    "sg:address":"706 Harvey Road",
    "sg:city":"Derby",
    "sg:classifiers":[
        {
            "category":"Shopping",
            "subcategory":"News",
            "type":"Retail Goods"
        }
    ],
    "sg:phone":"+44 1332 571359",
    "sg:postcode":"DE24 0EG",
    "sg:province":"Derbyshire",
    "sg:tags":[
        "newsagent"
    ],
    "wof:name":"Harvey Rd News",
    "wof:placetype":"venue"
},
  "geometry": {"coordinates":[-1.437367,52.8932],"type":"Point"}
}