{
  "type": "Feature",
  "properties": {
    "addr:full":"1 Brothock Meadows, Letham Grange Arbroath Angus DD11 4QN",
    "addr:housenumber":"1",
    "addr:postcode":"dd11 4qn",
    "addr:street":"Brothock Meadows",
    "iso:country":"GB",
    "sg:address":"1 Brothock Meadows, Letham Grange",
    "sg:city":"Arbroath",
    "sg:classifiers":[
        {
            "category":"Utilities",
            "subcategory":"Fuel Oil & Lpg",
            "type":"Services"
        }
    ],
    "sg:phone":"+44 1241 890726",
    "sg:postcode":"DD11 4QN",
    "sg:province":"Angus",
    "sg:tags":[
        "distributor"
    ],
    "wof:name":"Campbell's Global Consulting Ltd.",
    "wof:placetype":"venue"
},
  "geometry": {"coordinates":[-2.580585,56.574612],"type":"Point"}
}