{
  "type": "Feature",
  "properties": {
    "addr:full":"34 Park Street Bristol City of Bristol BS1 5BQ",
    "addr:housenumber":"34",
    "addr:postcode":"bs1 5bq",
    "addr:street":"Park Street",
    "iso:country":"GB",
    "sg:address":"34 Park Street",
    "sg:city":"Bristol",
    "sg:classifiers":[
        {
            "category":"Personal",
            "subcategory":"Tattoo Parlor",
            "type":"Services"
        }
    ],
    "sg:phone":"+44 117 930 0611",
    "sg:postcode":"BS1 5BQ",
    "sg:province":"City of Bristol",
    "sg:tags":[
        "tattooing",
        "piercing"
    ],
    "wof:name":"Pierced Up",
    "wof:placetype":"venue"
},
  "geometry": {"coordinates":[-2.6019670963,51.4540939331],"type":"Point"}
}