{
  "type": "Feature",
  "properties": {
    "iso:country":"GB",
    "sg:address":"31 Bradstock Road",
    "sg:city":"London",
    "sg:classifiers":[
        {
            "category":"Food & Beverages",
            "subcategory":"Liquor & Beverages",
            "type":"Retail Goods"
        }
    ],
    "sg:phone":"+44 20 8985 3827",
    "sg:postcode":"E9 5BH",
    "sg:province":"Greater London",
    "sg:tags":[
        "beer",
        "spirit",
        "wines"
    ],
    "wof:name":"Bradstock Stores",
    "wof:placetype":"venue"
},
  "geometry": {"coordinates":[-0.042227,51.54443],"type":"Point"}
}