{
  "type": "Feature",
  "properties": {
    "addr:full":"Saltby Airfield Grantham Leicestershire NG33 5HL",
    "addr:postcode":"ng33 5hl",
    "iso:country":"GB",
    "sg:address":"Saltby Airfield",
    "sg:city":"Grantham",
    "sg:classifiers":[
        {
            "category":"Arena",
            "subcategory":"Sports Club",
            "type":"Entertainment"
        }
    ],
    "sg:phone":"+44 1476 860385",
    "sg:postcode":"NG33 5HL",
    "sg:province":"Leicestershire",
    "wof:name":"Buckminster Gliding Club",
    "wof:placetype":"venue"
},
  "geometry": {"coordinates":[-0.70352,52.825119],"type":"Point"}
}