{
  "type": "Feature",
  "properties": {
    "addr:full":"Unit 3 Breckenwood Rd, Fulbourn Cambridge Cambridgeshire CB1 5DQ",
    "addr:housenumber":"unit 3",
    "addr:postcode":"cb1 5dq",
    "addr:street":"Breckenwood Rd",
    "iso:country":"GB",
    "sg:address":"Unit 3 Breckenwood Rd, Fulbourn",
    "sg:city":"Cambridge",
    "sg:classifiers":[
        {
            "category":"Manufacturing",
            "subcategory":"Rubber & Plastics",
            "type":"Manufacturing & Wholesale Goods"
        },
        {
            "category":"Manufacturing",
            "subcategory":"Petroleum Products",
            "type":"Manufacturing & Wholesale Goods"
        }
    ],
    "sg:postcode":"CB1 5DQ",
    "sg:province":"Cambridgeshire",
    "sg:tags":[
        "double",
        "injection",
        "moulding",
        "glazing"
    ],
    "wof:name":"Plastic Surgery",
    "wof:placetype":"venue"
},
  "geometry": {"coordinates":[0.208100006,52.1874084473],"type":"Point"}
}