{
  "type": "Feature",
  "properties": {
    "addr:full":"734 Chesterfield Road Sheffield Derbyshire S8 0SE",
    "addr:housenumber":"734",
    "addr:postcode":"s8 0se",
    "addr:street":"Chesterfield Road",
    "iso:country":"GB",
    "sg:address":"734 Chesterfield Road",
    "sg:city":"Sheffield",
    "sg:classifiers":[
        {
            "category":"Shopping",
            "subcategory":"Florist",
            "type":"Retail Goods"
        }
    ],
    "sg:phone":"+44 114 258 3231",
    "sg:postcode":"S8 0SE",
    "sg:province":"Derbyshire",
    "wof:name":"Hollyhocks",
    "wof:placetype":"venue"
},
  "geometry": {"coordinates":[-1.478159,53.343098],"type":"Point"}
}