{
  "type": "Feature",
  "properties": {
    "addr:full":"Douglas Buildings, Royal Stuart Lane Cardiff Cardiff CF10 5EL",
    "addr:postcode":"cf10 5el",
    "addr:street":"Stuart Lane",
    "iso:country":"GB",
    "sg:address":"Douglas Buildings, Royal Stuart Lane",
    "sg:city":"Cardiff",
    "sg:classifiers":[
        {
            "category":"Government",
            "subcategory":"Post Office",
            "type":"Public Place"
        }
    ],
    "sg:postcode":"CF10 5EL",
    "sg:province":"Cardiff",
    "sg:tags":[
        "messenger",
        "courier"
    ],
    "wof:name":"Cycle Despatch",
    "wof:placetype":"venue"
},
  "geometry": {"coordinates":[-3.1806690693,51.4812583923],"type":"Point"}
}