{
  "type": "Feature",
  "properties": {
    "iso:country":"GB",
    "sg:address":"1 Prospect Street",
    "sg:city":"Bridlington",
    "sg:classifiers":[
        {
            "category":"Shopping",
            "subcategory":"Baby Store",
            "type":"Retail Goods"
        }
    ],
    "sg:postcode":"YO15 2AE",
    "sg:province":"East Riding of Yorkshire",
    "sg:tags":[
        "babywear",
        "childrens"
    ],
    "wof:name":"Stylish Kids",
    "wof:placetype":"venue"
},
  "geometry": {"coordinates":[-0.192425,54.083179],"type":"Point"}
}