{
  "type": "Feature",
  "properties": {
    "addr:full":"8 Clonmel Street Llandudno Conwy LL30 2LE",
    "addr:housenumber":"8",
    "addr:postcode":"ll30 2le",
    "addr:street":"Clonmel Street",
    "iso:country":"GB",
    "sg:address":"8 Clonmel Street",
    "sg:city":"Llandudno",
    "sg:classifiers":[
        {
            "category":"Personal",
            "subcategory":"Beauty Salon",
            "type":"Services"
        }
    ],
    "sg:phone":"+44 7930 854973",
    "sg:postcode":"LL30 2LE",
    "sg:province":"Conwy",
    "sg:tags":[
        "unisex",
        "hairdresser"
    ],
    "wof:name":"D W Hair Studio",
    "wof:placetype":"venue"
},
  "geometry": {"coordinates":[-3.8270790577,53.3232078552],"type":"Point"}
}