{
  "type": "Feature",
  "properties": {
    "iso:country":"GB",
    "sg:address":"Unit 5 Saxon Centre, Bedford Road, Kempston",
    "sg:city":"Bedford",
    "sg:classifiers":[
        {
            "category":"Shopping",
            "subcategory":"Shoes",
            "type":"Retail Goods"
        }
    ],
    "sg:phone":"+44 1234 855655",
    "sg:postcode":"MK42 8QA",
    "sg:province":"Bedfordshire",
    "sg:tags":[
        "shop"
    ],
    "wof:name":"Jonathan James (Mansfield) Ltd.",
    "wof:placetype":"venue"
},
  "geometry": {"coordinates":[-0.4947339892,52.1183738708],"type":"Point"}
}