{
  "type": "Feature",
  "properties": {
    "iso:country":"GB",
    "sg:address":"West Midlands House, Gipsy Lane",
    "sg:city":"Willenhall",
    "sg:classifiers":[
        {
            "category":"Social Services",
            "subcategory":"Retirement Home",
            "type":"Services"
        }
    ],
    "sg:phone":"+44 121 609 7164",
    "sg:postcode":"WV13 2HA",
    "sg:province":"West Midlands",
    "sg:tags":[
        "care"
    ],
    "wof:name":"Acorn Home Care Ltd.",
    "wof:placetype":"venue"
},
  "geometry": {"coordinates":[-2.047673,52.582958],"type":"Point"}
}