{
  "type": "Feature",
  "properties": {
    "iso:country":"GB",
    "sg:address":"Meridian House",
    "sg:city":"Kidlington",
    "sg:classifiers":[
        {
            "category":"Shopping",
            "subcategory":"Mobile Phones",
            "type":"Retail Goods"
        }
    ],
    "sg:phone":"+44 1869 342120",
    "sg:postcode":"OX25 3SX",
    "sg:province":"Oxfordshire",
    "wof:name":"The Mobile Phone Co. Ltd.",
    "wof:placetype":"venue"
},
  "geometry": {"coordinates":[-1.226959,51.86425],"type":"Point"}
}