{
  "type": "Feature",
  "properties": {
    "addr:full":"Suite B Third Floor, Teresa Gavin House Woodford Green Essex IG8 8FB",
    "addr:housenumber":"suite b third floor teresa",
    "addr:postcode":"ig8 8fb",
    "addr:street":"Woodford Green",
    "iso:country":"GB",
    "sg:address":"Suite B Third Floor, Teresa Gavin House",
    "sg:city":"Woodford Green",
    "sg:classifiers":[
        {
            "category":"Professional",
            "subcategory":"Accounting & Tax Preparation",
            "type":"Services"
        }
    ],
    "sg:phone":"+44 20 8551 2323",
    "sg:postcode":"IG8 8FB",
    "sg:province":"Essex",
    "sg:tags":[
        "accountant"
    ],
    "wof:name":"Ashton Hart David Lee Ltd.",
    "wof:placetype":"venue"
},
  "geometry": {"coordinates":[0.0289820004,51.6043891907],"type":"Point"}
}