{
  "type": "Feature",
  "properties": {
    "addr:full":"55 Station Road Ely Cambridgeshire CB7 4BW",
    "addr:housenumber":"55",
    "addr:postcode":"cb7 4bw",
    "addr:street":"Station Road",
    "iso:country":"GB",
    "sg:address":"55 Station Road",
    "sg:city":"Ely",
    "sg:classifiers":[
        {
            "category":"Retail",
            "subcategory":"Auto Rental",
            "type":"Services"
        }
    ],
    "sg:phone":"+44 1353 669269",
    "sg:postcode":"CB7 4BW",
    "sg:province":"Cambridgeshire",
    "sg:tags":[
        "car"
    ],
    "wof:name":"Hertz Rent A Car",
    "wof:placetype":"venue"
},
  "geometry": {"coordinates":[0.2670179904,52.3921585083],"type":"Point"}
}