{
  "type": "Feature",
  "properties": {
    "iso:country":"GB",
    "sg:address":"29 Norton Road",
    "sg:city":"Walsall",
    "sg:classifiers":[
        {
            "category":"Shopping",
            "subcategory":"Shoes",
            "type":"Retail Goods"
        }
    ],
    "sg:postcode":"WS3 4AY",
    "sg:province":"Staffordshire",
    "sg:tags":[
        "shop"
    ],
    "wof:name":"Lloyds Footwear",
    "wof:placetype":"venue"
},
  "geometry": {"coordinates":[-1.9667010307,52.6296577454],"type":"Point"}
}