{
  "type": "Feature",
  "properties": {
    "addr:full":"1 The Square, Abertridwr Caerphilly Caerphilly CF83 4DH",
    "addr:housenumber":"1",
    "addr:postcode":"cf83 4dh",
    "addr:street":"The Square",
    "iso:country":"GB",
    "sg:address":"1 The Square, Abertridwr",
    "sg:city":"Caerphilly",
    "sg:classifiers":[
        {
            "category":"Organizations",
            "subcategory":"Membership Organization",
            "type":"Services"
        }
    ],
    "sg:phone":"+44 29 2083 1439",
    "sg:postcode":"CF83 4DH",
    "sg:province":"Caerphilly",
    "sg:tags":[
        "club"
    ],
    "wof:name":"R A O B Club",
    "wof:placetype":"venue"
},
  "geometry": {"coordinates":[-3.272010088,51.5960845947],"type":"Point"}
}