{
  "type": "Feature",
  "properties": {
    "addr:full":"Penderyn Quarry, Penderyn Aberdare Neath Port Talbot CF44 0TX",
    "addr:postcode":"cf44 0tx",
    "addr:street":"Penderyn Quarry Penderyn",
    "iso:country":"GB",
    "sg:address":"Penderyn Quarry, Penderyn",
    "sg:city":"Aberdare",
    "sg:classifiers":[
        {
            "category":"Manufacturing",
            "subcategory":"Glass & Minerals",
            "type":"Manufacturing & Wholesale Goods"
        }
    ],
    "sg:phone":"+44 1685 813179",
    "sg:postcode":"CF44 0TX",
    "sg:province":"Neath Port Talbot",
    "sg:tags":[
        "chalk",
        "stone",
        "slate"
    ],
    "wof:name":"Hanson Aggregates South Wales Ltd.",
    "wof:placetype":"venue"
},
  "geometry": {"coordinates":[-3.4459540844,51.7124595642],"type":"Point"}
}