{
  "type": "Feature",
  "properties": {
    "addr:full":"146 Totteridge Road High Wycombe Buckinghamshire HP13 7LB",
    "addr:housenumber":"146",
    "addr:postcode":"hp13 7lb",
    "addr:street":"Totteridge Road",
    "iso:country":"GB",
    "sg:address":"146 Totteridge Road",
    "sg:city":"High Wycombe",
    "sg:classifiers":[
        {
            "category":"Wholesale",
            "subcategory":"Scrap",
            "type":"Manufacturing & Wholesale Goods"
        }
    ],
    "sg:phone":"+44 1494 448266",
    "sg:postcode":"HP13 7LB",
    "sg:province":"Buckinghamshire",
    "sg:tags":[
        "waste",
        "metal"
    ],
    "wof:name":"Lane End Transport",
    "wof:placetype":"venue"
},
  "geometry": {"coordinates":[-0.734925,51.630775],"type":"Point"}
}