{
  "type": "Feature",
  "properties": {
    "addr:full":"4 St Marys Place St Andrews Fife KY16 9UY",
    "addr:housenumber":"4",
    "addr:postcode":"ky16 9uy",
    "addr:street":"St Marys Place",
    "iso:country":"GB",
    "sg:address":"4 St Marys Place",
    "sg:city":"St Andrews",
    "sg:classifiers":[
        {
            "category":"Health Services",
            "subcategory":"Dentist",
            "type":"Services"
        }
    ],
    "sg:phone":"+44 1334 473237",
    "sg:postcode":"KY16 9UY",
    "sg:province":"Fife",
    "wof:name":"The Inchcape Practice",
    "wof:placetype":"venue"
},
  "geometry": {"coordinates":[-2.8000190258,56.3403587341],"type":"Point"}
}