{
  "type": "Feature",
  "properties": {
    "iso:country":"GB",
    "sg:address":"20 Broad Row",
    "sg:city":"Great Yarmouth",
    "sg:classifiers":[
        {
            "category":"Personal",
            "subcategory":"Barber",
            "type":"Services"
        }
    ],
    "sg:phone":"+44 1493 850572",
    "sg:postcode":"NR30 1HT",
    "sg:province":"Norfolk",
    "sg:tags":[
        "men's",
        "gents",
        "hairdresser"
    ],
    "wof:name":"Hair for Men",
    "wof:placetype":"venue"
},
  "geometry": {"coordinates":[1.72399,52.612415],"type":"Point"}
}