{
  "type": "Feature",
  "properties": {
    "iso:country":"GB",
    "sg:address":"Gore Pit Garage, Feering Hill, Feering",
    "sg:city":"Colchester",
    "sg:classifiers":[
        {
            "category":"Autos & Motor Vehicles",
            "subcategory":"Automobile Sales",
            "type":"Retail Goods"
        }
    ],
    "sg:phone":"+44 1376 573070",
    "sg:postcode":"CO5 9SD",
    "sg:province":"Essex",
    "sg:tags":[
        "car"
    ],
    "wof:name":"Kelvedon Motor Co",
    "wof:placetype":"venue"
},
  "geometry": {"coordinates":[0.7166919708,51.8445854187],"type":"Point"}
}