{
  "type": "Feature",
  "properties": {
    "addr:full":"42 Chatterton Road Bromley Kent BR2 9QE",
    "addr:housenumber":"42",
    "addr:postcode":"br2 9qe",
    "addr:street":"Chatterton Road",
    "iso:country":"GB",
    "sg:address":"42 Chatterton Road",
    "sg:city":"Bromley",
    "sg:classifiers":[
        {
            "category":"Shopping",
            "subcategory":"Department Store",
            "type":"Retail Goods"
        }
    ],
    "sg:postcode":"BR2 9QE",
    "sg:province":"Kent",
    "wof:name":"Londis",
    "wof:placetype":"venue"
},
  "geometry": {"coordinates":[0.035704,51.392002],"type":"Point"}
}