{
  "type": "Feature",
  "properties": {
    "iso:country":"GB",
    "sg:address":"Greenhill House Thorpe Road",
    "sg:city":"Peterborough",
    "sg:classifiers":[
        {
            "category":"Autos & Motor Vehicles",
            "subcategory":"Automobile Sales",
            "type":"Retail Goods"
        }
    ],
    "sg:phone":"+44 1733 331495",
    "sg:postcode":"PE3 6RU",
    "sg:province":"Cambridgeshire",
    "sg:tags":[
        "car"
    ],
    "wof:name":"Quotus Ltd.",
    "wof:placetype":"venue"
},
  "geometry": {"coordinates":[-0.253024,52.572441],"type":"Point"}
}