{
  "type": "Feature",
  "properties": {
    "iso:country":"GB",
    "sg:address":"20 High Street, Clee Hill",
    "sg:city":"Ludlow",
    "sg:classifiers":[
        {
            "category":"Shopping",
            "subcategory":"Department Store",
            "type":"Retail Goods"
        }
    ],
    "sg:phone":"+44 1584 890605",
    "sg:postcode":"SY8 3LZ",
    "sg:province":"Herefordshire",
    "wof:name":"R E Tennant",
    "wof:placetype":"venue"
},
  "geometry": {"coordinates":[-2.598756,52.374371],"type":"Point"}
}