{
  "type": "Feature",
  "properties": {
    "iso:country":"GB",
    "sg:address":"36 Haverhill Road, Stapleford",
    "sg:city":"Cambridge",
    "sg:classifiers":[
        {
            "category":"Shopping",
            "subcategory":"Pharmacy",
            "type":"Retail Goods"
        }
    ],
    "sg:postcode":"CB2 5BX",
    "sg:province":"Cambridgeshire",
    "sg:tags":[
        "medicine",
        "therapy"
    ],
    "wof:name":"Sue",
    "wof:placetype":"venue"
},
  "geometry": {"coordinates":[0.156534,52.144783],"type":"Point"}
}