{
  "type": "Feature",
  "properties": {
    "iso:country":"GB",
    "sg:address":"25 The Broadway",
    "sg:city":"St Ives",
    "sg:classifiers":[
        {
            "category":"Arena",
            "subcategory":"Sports Club",
            "type":"Entertainment"
        }
    ],
    "sg:phone":"+44 1480 492384",
    "sg:postcode":"PE27 5BX",
    "sg:province":"Cambridgeshire",
    "wof:name":"St.Ives Rowing Club",
    "wof:placetype":"venue"
},
  "geometry": {"coordinates":[-0.0760879964,52.3247680664],"type":"Point"}
}