{
  "type": "Feature",
  "properties": {
    "addr:full":"1 Tile Row, Moats Tye, Combs Stowmarket Suffolk IP14 2EP",
    "addr:housenumber":"1",
    "addr:postcode":"ip14 2ep",
    "addr:street":"Tile Row",
    "iso:country":"GB",
    "sg:address":"1 Tile Row, Moats Tye, Combs",
    "sg:city":"Stowmarket",
    "sg:classifiers":[
        {
            "category":"Retail",
            "subcategory":"Storage",
            "type":"Services"
        }
    ],
    "sg:postcode":"IP14 2EP",
    "sg:province":"Suffolk",
    "sg:tags":[
        "hire",
        "container"
    ],
    "wof:name":"Container Options Ltd.",
    "wof:placetype":"venue"
},
  "geometry": {"coordinates":[0.9871510267,52.1694717407],"type":"Point"}
}