{
  "type": "Feature",
  "properties": {
    "addr:full":"Ystrad Fai Farm, Felinfoel Llanelli Carmarthenshire SA14 8NQ",
    "addr:postcode":"sa14 8nq",
    "iso:country":"GB",
    "sg:address":"Ystrad Fai Farm, Felinfoel",
    "sg:city":"Llanelli",
    "sg:classifiers":[
        {
            "category":"Farming",
            "subcategory":"Livestock Farm",
            "type":"Manufacturing & Wholesale Goods"
        }
    ],
    "sg:phone":"+44 1554 773746",
    "sg:postcode":"SA14 8NQ",
    "sg:province":"Carmarthenshire",
    "sg:tags":[
        "others"
    ],
    "wof:name":"Vincent Davies",
    "wof:placetype":"venue"
},
  "geometry": {"coordinates":[-4.144001,51.697731],"type":"Point"}
}