{
  "type": "Feature",
  "properties": {
    "iso:country":"GB",
    "sg:address":"129 St Margarets Road",
    "sg:city":"Twickenham",
    "sg:classifiers":[
        {
            "category":"Food & Beverages",
            "subcategory":"Supermarket",
            "type":"Retail Goods"
        }
    ],
    "sg:phone":"+44 20 8891 5767",
    "sg:postcode":"TW1 1RG",
    "sg:province":"Greater London",
    "wof:name":"Olivers Food & Wine",
    "wof:placetype":"venue"
},
  "geometry": {"coordinates":[-0.3204340041,51.4553718567],"type":"Point"}
}