{
  "type": "Feature",
  "properties": {
    "addr:full":"7 Llantrisant Road Pontyclun Bridgend CF72 9DP",
    "addr:housenumber":"7",
    "addr:postcode":"cf72 9dp",
    "addr:street":"Llantrisant Road",
    "iso:country":"GB",
    "sg:address":"7 Llantrisant Road",
    "sg:city":"Pontyclun",
    "sg:classifiers":[
        {
            "category":"Communications",
            "subcategory":"Film & Video Production",
            "type":"Services"
        },
        {
            "category":"Retail",
            "subcategory":"Repair Shop",
            "type":"Services"
        }
    ],
    "sg:phone":"+44 1443 225332",
    "sg:postcode":"CF72 9DP",
    "sg:province":"Bridgend",
    "sg:tags":[
        "tv",
        "radio",
        "television",
        "studio"
    ],
    "wof:name":"Southgate Rentals Video Clinic",
    "wof:placetype":"venue"
},
  "geometry": {"coordinates":[-3.3905949593,51.5238418579],"type":"Point"}
}