{
  "type": "Feature",
  "properties": {
    "addr:full":"Bourne Street, Hollinwood Oldham Lancashire OL9 7LX",
    "addr:postcode":"ol9 7lx",
    "addr:street":"Bourne Street",
    "iso:country":"GB",
    "sg:address":"Bourne Street, Hollinwood",
    "sg:city":"Oldham",
    "sg:classifiers":[
        {
            "category":"Building & Trades",
            "subcategory":"Electrical",
            "type":"Services"
        }
    ],
    "sg:phone":"+44 161 683 4298",
    "sg:postcode":"OL9 7LX",
    "sg:province":"Lancashire",
    "sg:tags":[
        "lighting"
    ],
    "wof:name":"Metcraft (Lighting) Ltd.",
    "wof:placetype":"venue"
},
  "geometry": {"coordinates":[-2.1437089443,53.5220832825],"type":"Point"}
}