{
  "type": "Feature",
  "properties": {
    "iso:country":"GB",
    "sg:address":"Bradford Road",
    "sg:city":"Melksham",
    "sg:classifiers":[
        {
            "category":"Shopping",
            "type":"Retail Goods"
        }
    ],
    "sg:phone":"+44 1225 701438",
    "sg:postcode":"SN12 8LQ",
    "sg:province":"Wiltshire",
    "sg:tags":[
        "merchant"
    ],
    "wof:name":"Countrywide Farmers Plc",
    "wof:placetype":"venue"
},
  "geometry": {"coordinates":[-2.143702,51.376045],"type":"Point"}
}