{
  "type": "Feature",
  "properties": {
    "addr:full":"1 Tollgate Drive, Tollgate Industrial Estate Stafford Staffordshire ST16 3HS",
    "addr:housenumber":"1",
    "addr:postcode":"st16 3hs",
    "addr:street":"Tollgate Drive Tollgate Industrial Estate",
    "iso:country":"GB",
    "sg:address":"1 Tollgate Drive, Tollgate Industrial Estate",
    "sg:city":"Stafford",
    "sg:classifiers":[
        {
            "category":"Manufacturing",
            "subcategory":"Glass & Minerals",
            "type":"Manufacturing & Wholesale Goods"
        }
    ],
    "sg:phone":"+44 1785 609900",
    "sg:postcode":"ST16 3HS",
    "sg:province":"Staffordshire",
    "sg:tags":[
        "product"
    ],
    "wof:name":"Q V F Process Systems Ltd.",
    "wof:placetype":"venue"
},
  "geometry": {"coordinates":[-2.1076900959,52.8257827759],"type":"Point"}
}