{
  "type": "Feature",
  "properties": {
    "iso:country":"GB",
    "sg:address":"Sentinel House, Sutton Court Rd",
    "sg:city":"Sutton",
    "sg:classifiers":[
        {
            "category":"Government",
            "subcategory":"Office",
            "type":"Public Place"
        }
    ],
    "sg:phone":"+44 20 8652 1700",
    "sg:postcode":"SM1 4SU",
    "sg:province":"Surrey",
    "sg:tags":[
        "local"
    ],
    "wof:name":"Inland Revenue",
    "wof:placetype":"venue"
},
  "geometry": {"coordinates":[-0.188079,51.360867],"type":"Point"}
}