{
  "type": "Feature",
  "properties": {
    "iso:country":"GB",
    "sg:address":"114 Shenley Road",
    "sg:city":"Borehamwood",
    "sg:classifiers":[
        {
            "category":"Fast Food",
            "type":"Food & Drink"
        }
    ],
    "sg:phone":"+44 20 8207 6139",
    "sg:postcode":"WD6 1EF",
    "sg:province":"Hertfordshire",
    "sg:tags":[
        "away",
        "take"
    ],
    "wof:name":"Lots of Rice",
    "wof:placetype":"venue"
},
  "geometry": {"coordinates":[-0.2735640109,51.6566429138],"type":"Point"}
}