{
  "type": "Feature",
  "properties": {
    "addr:full":"Silverdale Park, Station Lane Chester Cheshire CH2 4TA",
    "addr:postcode":"ch2 4ta",
    "addr:street":"Park Station Lane",
    "iso:country":"GB",
    "sg:address":"Silverdale Park, Station Lane",
    "sg:city":"Chester",
    "sg:classifiers":[
        {
            "category":"Autos & Motor Vehicles",
            "subcategory":"Fuel & Gas Station",
            "type":"Retail Goods"
        },
        {
            "category":"Shopping",
            "type":"Retail Goods"
        }
    ],
    "sg:postcode":"CH2 4TA",
    "sg:province":"Cheshire",
    "sg:tags":[
        "petrol",
        "merchant",
        "filling"
    ],
    "wof:name":"Auto Parts World",
    "wof:placetype":"venue"
},
  "geometry": {"coordinates":[-2.83,53.216301],"type":"Point"}
}