{
  "type": "Feature",
  "properties": {
    "iso:country":"GB",
    "sg:address":"7 Bedford Hill",
    "sg:city":"London",
    "sg:classifiers":[
        {
            "category":"Shopping",
            "subcategory":"Beauty & Cosmetics",
            "type":"Retail Goods"
        }
    ],
    "sg:phone":"+44 20 8673 5762",
    "sg:postcode":"SW12 9ET",
    "sg:province":"Greater London",
    "sg:tags":[
        "equipment",
        "supply",
        "hairdressing"
    ],
    "wof:name":"Catford Agencies",
    "wof:placetype":"venue"
},
  "geometry": {"coordinates":[-0.150912,51.445011],"type":"Point"}
}