{
  "type": "Feature",
  "properties": {
    "addr:full":"7 Bedford Hill London Greater London SW12 9ET",
    "addr:housenumber":"7",
    "addr:postcode":"sw12 9et",
    "addr:street":"Bedford Hill",
    "iso:country":"GB",
    "sg:address":"7 Bedford Hill",
    "sg:city":"London",
    "sg:classifiers":[
        {
            "category":"Shopping",
            "subcategory":"Beauty & Cosmetics",
            "type":"Retail Goods"
        }
    ],
    "sg:phone":"+44 20 8673 5762",
    "sg:postcode":"SW12 9ET",
    "sg:province":"Greater London",
    "sg:tags":[
        "equipment",
        "supply",
        "hairdressing"
    ],
    "wof:name":"Catford Agencies",
    "wof:placetype":"venue"
},
  "geometry": {"coordinates":[-0.150912,51.445011],"type":"Point"}
}