{
  "type": "Feature",
  "properties": {
    "iso:country":"GB",
    "sg:address":"Linnburn House, Drybridge",
    "sg:city":"Buckie",
    "sg:classifiers":[
        {
            "category":"Professional",
            "subcategory":"Engineering",
            "type":"Services"
        },
        {
            "category":"Travel",
            "subcategory":"Hotels & Motels",
            "type":"Entertainment"
        }
    ],
    "sg:phone":"+44 1542 835191",
    "sg:postcode":"AB56 5JL",
    "sg:province":"Moray",
    "sg:tags":[
        "self",
        "catering",
        "hydraulic",
        "engineer"
    ],
    "wof:name":"Gas & Hydraulics Ltd.",
    "wof:placetype":"venue"
},
  "geometry": {"coordinates":[-2.957613,57.654591],"type":"Point"}
}