{
  "type": "Feature",
  "properties": {
    "addr:full":"291 High Street Epping Essex CM16 4DA",
    "addr:housenumber":"291",
    "addr:postcode":"cm16 4da",
    "addr:street":"High Street",
    "iso:country":"GB",
    "sg:address":"291 High Street",
    "sg:city":"Epping",
    "sg:classifiers":[
        {
            "category":"Personal",
            "subcategory":"Beauty Salon",
            "type":"Services"
        }
    ],
    "sg:phone":"+44 1992 575893",
    "sg:postcode":"CM16 4DA",
    "sg:province":"Essex",
    "sg:tags":[
        "ladies",
        "lady",
        "hairdresser"
    ],
    "wof:name":"The Butterfly Room",
    "wof:placetype":"venue"
},
  "geometry": {"coordinates":[0.11338,51.7007026672],"type":"Point"}
}