{
  "type": "Feature",
  "properties": {
    "addr:full":"Unit 39/40, Bookham Industrial Estate, Bookham Leatherhead Surrey KT23 3EU",
    "addr:housenumber":"unit 39 / 40",
    "addr:postcode":"kt23 3eu",
    "addr:street":"Industrial Estate",
    "iso:country":"GB",
    "sg:address":"Unit 39/40, Bookham Industrial Estate, Bookham",
    "sg:city":"Leatherhead",
    "sg:classifiers":[
        {
            "category":"Home & Garden",
            "subcategory":"Kitchen Supply",
            "type":"Retail Goods"
        }
    ],
    "sg:phone":"+44 1372 450855",
    "sg:postcode":"KT23 3EU",
    "sg:province":"Surrey",
    "sg:tags":[
        "equipment",
        "catering"
    ],
    "wof:name":"R V Rutland (U K) Ltd.",
    "wof:placetype":"venue"
},
  "geometry": {"coordinates":[-0.3867970109,51.2851791382],"type":"Point"}
}