{
  "type": "Feature",
  "properties": {
    "addr:full":"25-29 Gun Lane, Strood Rochester Kent ME2 4UJ",
    "addr:housenumber":"25-29",
    "addr:postcode":"me2 4uj",
    "addr:street":"Gun Lane",
    "iso:country":"GB",
    "sg:address":"25-29 Gun Lane, Strood",
    "sg:city":"Rochester",
    "sg:classifiers":[
        {
            "category":"Government",
            "subcategory":"City Hall",
            "type":"Public Place"
        }
    ],
    "sg:postcode":"ME2 4UJ",
    "sg:province":"Kent",
    "wof:name":"Dancing Feet Ltd.",
    "wof:placetype":"venue"
},
  "geometry": {"coordinates":[0.494933,51.397804],"type":"Point"}
}