{
  "type": "Feature",
  "properties": {
    "addr:full":"65 Booth Rise Northampton Northamptonshire NN3 6HP",
    "addr:housenumber":"65",
    "addr:postcode":"nn3 6hp",
    "addr:street":"Booth Rise",
    "iso:country":"GB",
    "sg:address":"65 Booth Rise",
    "sg:city":"Northampton",
    "sg:classifiers":[
        {
            "category":"Building & Trades",
            "subcategory":"Construction",
            "type":"Services"
        }
    ],
    "sg:postcode":"NN3 6HP",
    "sg:province":"Northamptonshire",
    "sg:tags":[
        "contractor",
        "paving",
        "driveway"
    ],
    "wof:name":"Blockways",
    "wof:placetype":"venue"
},
  "geometry": {"coordinates":[-0.8495910168,52.2762260437],"type":"Point"}
}