{
  "type": "Feature",
  "properties": {
    "addr:full":"Maes Derw Conwy Conwy LL31 9AL",
    "addr:postcode":"ll31 9al",
    "addr:street":"Maes Derw",
    "iso:country":"GB",
    "sg:address":"Maes Derw",
    "sg:city":"Conwy",
    "sg:classifiers":[
        {
            "category":"Health Services",
            "subcategory":"Dentist",
            "type":"Services"
        }
    ],
    "sg:phone":"+44 1492 582208",
    "sg:postcode":"LL31 9AL",
    "sg:province":"Conwy",
    "wof:name":"Gwynedd Community Health Trust",
    "wof:placetype":"venue"
},
  "geometry": {"coordinates":[-3.835559,53.302662],"type":"Point"}
}