{
  "type": "Feature",
  "properties": {
    "addr:full":"600 Bearwood Rd Smethwick West Midlands B66 4BW",
    "addr:housenumber":"600",
    "addr:postcode":"b66 4bw",
    "addr:street":"Bearwood Rd",
    "iso:country":"GB",
    "sg:address":"600 Bearwood Rd",
    "sg:city":"Smethwick",
    "sg:classifiers":[
        {
            "category":"Building & Trades",
            "subcategory":"Construction",
            "type":"Services"
        }
    ],
    "sg:phone":"+44 121 429 4808",
    "sg:postcode":"B66 4BW",
    "sg:province":"West Midlands",
    "sg:tags":[
        "decorator",
        "painter"
    ],
    "wof:name":"OTC",
    "wof:placetype":"venue"
},
  "geometry": {"coordinates":[-1.9689309597,52.4732055664],"type":"Point"}
}