{
  "type": "Feature",
  "properties": {
    "addr:full":"82 Bootham York North Yorkshire YO30 7DF",
    "addr:housenumber":"82",
    "addr:postcode":"yo30 7df",
    "addr:street":"Bootham",
    "iso:country":"GB",
    "sg:address":"82 Bootham",
    "sg:city":"York",
    "sg:classifiers":[
        {
            "category":"Organizations",
            "subcategory":"Non-profit Organization",
            "type":"Services"
        }
    ],
    "sg:phone":"+44 1904 634500",
    "sg:postcode":"YO30 7DF",
    "sg:province":"North Yorkshire",
    "sg:tags":[
        "charitable",
        "organisation",
        "voluntary",
        "charity"
    ],
    "wof:name":"The W R V S Association",
    "wof:placetype":"venue"
},
  "geometry": {"coordinates":[-1.089722991,53.9651679993],"type":"Point"}
}