{
  "type": "Feature",
  "properties": {
    "iso:country":"GB",
    "sg:address":"412 Woodbridge Road",
    "sg:city":"Ipswich",
    "sg:classifiers":[
        {
            "category":"Retail",
            "subcategory":"Veterinary Services",
            "type":"Services"
        }
    ],
    "sg:phone":"+44 1473 274040",
    "sg:postcode":"IP4 4EJ",
    "sg:province":"Suffolk",
    "sg:tags":[
        "surgeon",
        "activity"
    ],
    "wof:name":"Smith Ryder-Davies & Partners",
    "wof:placetype":"venue"
},
  "geometry": {"coordinates":[1.1789439917,52.0616416931],"type":"Point"}
}