{
  "type": "Feature",
  "properties": {
    "iso:country":"GB",
    "sg:address":"Long Cross, Lawrence Weston",
    "sg:city":"Bristol",
    "sg:classifiers":[
        {
            "category":"Bars & Pubs",
            "type":"Food & Drink"
        }
    ],
    "sg:phone":"+44 117 982 6053",
    "sg:postcode":"BS11 0SJ",
    "sg:province":"City of Bristol",
    "sg:tags":[
        "pubs",
        "inn"
    ],
    "wof:name":"The Long Cross",
    "wof:placetype":"venue"
},
  "geometry": {"coordinates":[-2.661348,51.500225],"type":"Point"}
}