{
  "type": "Feature",
  "properties": {
    "addr:full":"Jewison La Bridlington East Riding of Yorkshire YO16 5YG",
    "addr:postcode":"yo16 5yg",
    "addr:street":"La Bridlington",
    "iso:country":"GB",
    "sg:address":"Jewison La",
    "sg:city":"Bridlington",
    "sg:classifiers":[
        {
            "category":"Recreation",
            "subcategory":"Campground",
            "type":"Entertainment"
        }
    ],
    "sg:phone":"+44 1262 676442",
    "sg:postcode":"YO16 5YG",
    "sg:province":"East Riding of Yorkshire",
    "sg:tags":[
        "caravan",
        "park"
    ],
    "wof:name":"Shirley Caravan Park",
    "wof:placetype":"venue"
},
  "geometry": {"coordinates":[-0.23709,54.104671],"type":"Point"}
}