{
  "type": "Feature",
  "properties": {
    "iso:country":"GB",
    "sg:address":"51-52 Hill Road",
    "sg:city":"Tonbridge",
    "sg:classifiers":[
        {
            "category":"Bars & Pubs",
            "type":"Food & Drink"
        }
    ],
    "sg:postcode":"TN9 2RT",
    "sg:province":"Kent",
    "sg:tags":[
        "pubs",
        "inn"
    ],
    "wof:name":"Shepherd Neame Ltd.",
    "wof:placetype":"venue"
},
  "geometry": {"coordinates":[0.268161,51.188232],"type":"Point"}
}