{
  "type": "Feature",
  "properties": {
    "iso:country":"GB",
    "sg:address":"High Rd",
    "sg:city":"Stanford Le Hope",
    "sg:classifiers":[
        {
            "category":"Place Of Worship",
            "type":"Public Place"
        }
    ],
    "sg:phone":"+44 1375 372924",
    "sg:postcode":"SS17 8PZ",
    "sg:province":"Essex",
    "wof:name":"Horndon Methodist Church",
    "wof:placetype":"venue"
},
  "geometry": {"coordinates":[0.4058449864,51.5237884521],"type":"Point"}
}