{
  "type": "Feature",
  "properties": {
    "iso:country":"GB",
    "sg:address":"20 Boxworth End, Swavesey",
    "sg:city":"Cambridge",
    "sg:classifiers":[
        {
            "category":"Social Services",
            "subcategory":"Retirement Home",
            "type":"Services"
        }
    ],
    "sg:phone":"+44 1954 230382",
    "sg:postcode":"CB4 5RA",
    "sg:province":"Cambridgeshire",
    "sg:tags":[
        "residential",
        "care"
    ],
    "wof:name":"Brent House",
    "wof:placetype":"venue"
},
  "geometry": {"coordinates":[-0.002558,52.290676],"type":"Point"}
}