{
  "type": "Feature",
  "properties": {
    "addr:full":"22 Willow Way Manchester Greater Manchester M20 6JS",
    "addr:housenumber":"22",
    "addr:postcode":"m20 6js",
    "addr:street":"Willow Way",
    "iso:country":"GB",
    "sg:address":"22 Willow Way",
    "sg:city":"Manchester",
    "sg:classifiers":[
        {
            "category":"Building & Trades",
            "subcategory":"Construction",
            "type":"Services"
        }
    ],
    "sg:phone":"+44 161 445 8873",
    "sg:postcode":"M20 6JS",
    "sg:province":"Greater Manchester",
    "sg:tags":[
        "dry",
        "lining",
        "plasterers",
        "screeders"
    ],
    "wof:name":"D Lowndes",
    "wof:placetype":"venue"
},
  "geometry": {"coordinates":[-2.222105,53.418083],"type":"Point"}
}