{
  "type": "Feature",
  "properties": {
    "addr:full":"13 Soundwell Road Bristol City of Bristol BS16 4QG",
    "addr:housenumber":"13",
    "addr:postcode":"bs16 4qg",
    "addr:street":"Soundwell Road",
    "iso:country":"GB",
    "sg:address":"13 Soundwell Road",
    "sg:city":"Bristol",
    "sg:classifiers":[
        {
            "category":"Shopping",
            "subcategory":"Stationery & Office Supplies",
            "type":"Retail Goods"
        }
    ],
    "sg:phone":"+44 117 957 1415",
    "sg:postcode":"BS16 4QG",
    "sg:province":"City of Bristol",
    "sg:tags":[
        "equipment"
    ],
    "wof:name":"D S S Sales & Services Ltd.",
    "wof:placetype":"venue"
},
  "geometry": {"coordinates":[-2.5067501068,51.4802970886],"type":"Point"}
}