{
  "type": "Feature",
  "properties": {
    "iso:country":"GB",
    "sg:address":"20 Pangbourne Rd, Thurnscoe",
    "sg:city":"Rotherham",
    "sg:classifiers":[
        {
            "category":"Building & Trades",
            "subcategory":"Construction",
            "type":"Services"
        }
    ],
    "sg:postcode":"S63 0LQ",
    "sg:province":"South Yorkshire",
    "sg:tags":[
        "builder"
    ],
    "wof:name":"Gillian,John",
    "wof:placetype":"venue"
},
  "geometry": {"coordinates":[-1.317557,53.549572],"type":"Point"}
}