{
  "type": "Feature",
  "properties": {
    "iso:country":"GB",
    "sg:address":"Upperwake Hill Cottage, Kingston",
    "sg:city":"Ilminster",
    "sg:classifiers":[
        {
            "category":"Building & Trades",
            "subcategory":"Construction",
            "type":"Services"
        }
    ],
    "sg:phone":"+44 1460 54792",
    "sg:postcode":"TA19 0NR",
    "sg:province":"Somerset",
    "sg:tags":[
        "roofing",
        "craft",
        "thatching",
        "conservation"
    ],
    "wof:name":"Adrian J Ward",
    "wof:placetype":"venue"
},
  "geometry": {"coordinates":[-2.91753,50.928669],"type":"Point"}
}