{
  "type": "Feature",
  "properties": {
    "addr:full":"2a Wotton Road London Greater London NW2 6PX",
    "addr:housenumber":"2a",
    "addr:postcode":"nw2 6px",
    "addr:street":"Wotton Road",
    "iso:country":"GB",
    "sg:address":"2a Wotton Road",
    "sg:city":"London",
    "sg:classifiers":[
        {
            "category":"Building & Trades",
            "subcategory":"Construction",
            "type":"Services"
        }
    ],
    "sg:phone":"+44 20 8452 7203",
    "sg:postcode":"NW2 6PX",
    "sg:province":"Greater London",
    "sg:tags":[
        "tiling",
        "contractor"
    ],
    "wof:name":"Continental Tilers & Decorators",
    "wof:placetype":"venue"
},
  "geometry": {"coordinates":[-0.223651,51.5602],"type":"Point"}
}