{
  "type": "Feature",
  "properties": {
    "addr:full":"Unit S1, Inchbrook Trading Estate, Bath Road Stroud Gloucestershire GL5 5EY",
    "addr:postcode":"gl5 5ey",
    "addr:street":"Bath Road",
    "iso:country":"GB",
    "sg:address":"Unit S1, Inchbrook Trading Estate, Bath Road",
    "sg:city":"Stroud",
    "sg:classifiers":[
        {
            "category":"Shopping",
            "subcategory":"Computers & Home Electronics",
            "type":"Retail Goods"
        }
    ],
    "sg:postcode":"GL5 5EY",
    "sg:province":"Gloucestershire",
    "sg:tags":[
        "equipment",
        "audio-visual"
    ],
    "wof:name":"Carousel Tapes",
    "wof:placetype":"venue"
},
  "geometry": {"coordinates":[-2.2324409485,51.744934082],"type":"Point"}
}