{
  "type": "Feature",
  "properties": {
    "addr:full":"Priestpopple Hexham Northumberland NE46 1PA",
    "addr:postcode":"ne46 1pa",
    "addr:street":"Priestpopple",
    "iso:country":"GB",
    "sg:address":"Priestpopple",
    "sg:city":"Hexham",
    "sg:classifiers":[
        {
            "category":"Banks & Credit Unions",
            "subcategory":"Bank",
            "type":"Services"
        }
    ],
    "sg:phone":"+44 845 072 3333",
    "sg:postcode":"NE46 1PA",
    "sg:province":"Northumberland",
    "wof:name":"Lloyds Tsb Bank Plc",
    "wof:placetype":"venue"
},
  "geometry": {"coordinates":[-2.097539,54.970318],"type":"Point"}
}