{
  "type": "Feature",
  "properties": {
    "addr:full":"Baines House, 17 Station Parade Harrogate North Yorkshire HG1 1UF",
    "addr:housenumber":"17",
    "addr:postcode":"hg1 1uf",
    "addr:street":"Station Parade",
    "iso:country":"GB",
    "sg:address":"Baines House, 17 Station Parade",
    "sg:city":"Harrogate",
    "sg:classifiers":[
        {
            "category":"Sports & Exercise",
            "subcategory":"Gym",
            "type":"Entertainment"
        },
        {
            "category":"Organizations",
            "subcategory":"Membership Organization",
            "type":"Services"
        }
    ],
    "sg:phone":"+44 1423 565330",
    "sg:postcode":"HG1 1UF",
    "sg:province":"North Yorkshire",
    "sg:tags":[
        "club",
        "fitness",
        "health",
        "centre"
    ],
    "wof:name":"Bodyworks",
    "wof:placetype":"venue"
},
  "geometry": {"coordinates":[-1.536361,53.989441],"type":"Point"}
}