{
  "type": "Feature",
  "properties": {
    "iso:country":"GB",
    "sg:address":"Grinstead Lane",
    "sg:city":"Lancing",
    "sg:classifiers":[
        {
            "category":"Education",
            "subcategory":"School",
            "type":"Public Place"
        }
    ],
    "sg:phone":"+44 1903 753753",
    "sg:postcode":"BN15 9DP",
    "sg:province":"West Sussex",
    "sg:tags":[
        "local",
        "authority"
    ],
    "wof:name":"Freshbrook County First School",
    "wof:placetype":"venue"
},
  "geometry": {"coordinates":[-0.317424,50.836426],"type":"Point"}
}