{
  "type": "Feature",
  "properties": {
    "addr:full":"20 Market St, Hoyland Barnsley South Yorkshire S74 9QR",
    "addr:housenumber":"20",
    "addr:postcode":"s74 9qr",
    "addr:street":"Market St;Yorkshire",
    "iso:country":"GB",
    "sg:address":"20 Market St, Hoyland",
    "sg:city":"Barnsley",
    "sg:classifiers":[
        {
            "category":"Shopping",
            "subcategory":"Florist",
            "type":"Retail Goods"
        }
    ],
    "sg:phone":"+44 1226 744819",
    "sg:postcode":"S74 9QR",
    "sg:province":"South Yorkshire",
    "wof:name":"Cottage Flowers",
    "wof:placetype":"venue"
},
  "geometry": {"coordinates":[-1.4388810396,53.501449585],"type":"Point"}
}