{
  "type": "Feature",
  "properties": {
    "iso:country":"GB",
    "sg:address":"Unit 4 South Road Industrial Estate",
    "sg:city":"Alnwick",
    "sg:classifiers":[
        {
            "category":"Shopping",
            "subcategory":"Bicycles & Sporting Goods",
            "type":"Retail Goods"
        }
    ],
    "sg:phone":"+44 1665 604857",
    "sg:postcode":"NE66 2NN",
    "sg:province":"Northumberland",
    "sg:tags":[
        "equipment",
        "leisure"
    ],
    "wof:name":"Searchwise Ltd.",
    "wof:placetype":"venue"
},
  "geometry": {"coordinates":[-1.6935139894,55.4078903198],"type":"Point"}
}