{
  "type": "Feature",
  "properties": {
    "iso:country":"GB",
    "sg:address":"81 Swallow Way, Duffryn",
    "sg:city":"Newport",
    "sg:classifiers":[
        {
            "category":"Arts & Performance",
            "subcategory":"Music",
            "type":"Entertainment"
        }
    ],
    "sg:phone":"+44 1633 660760",
    "sg:postcode":"NP10 8WL",
    "sg:province":"Caerphilly",
    "sg:tags":[
        "mobile",
        "disco"
    ],
    "wof:name":"Dial-A-Disco",
    "wof:placetype":"venue"
},
  "geometry": {"coordinates":[-3.01984,51.564621],"type":"Point"}
}