{
  "type": "Feature",
  "properties": {
    "iso:country":"GB",
    "sg:address":"68 Church Drive, Daybrook",
    "sg:city":"Nottingham",
    "sg:classifiers":[
        {
            "category":"Professional",
            "subcategory":"Printing & Photocopies",
            "type":"Services"
        }
    ],
    "sg:phone":"+44 115 960 2348",
    "sg:postcode":"NG5 6LD",
    "sg:province":"Nottinghamshire",
    "sg:tags":[
        "plate",
        "lithographic",
        "maker"
    ],
    "wof:name":"Sutton Print Ltd.",
    "wof:placetype":"venue"
},
  "geometry": {"coordinates":[-1.133459,53.001511],"type":"Point"}
}