{
  "type": "Feature",
  "properties": {
    "addr:full":"12 Upper King Street Norwich Norfolk NR3 1HA",
    "addr:housenumber":"12",
    "addr:postcode":"nr3 1ha",
    "addr:street":"Upper King Street",
    "iso:country":"GB",
    "sg:address":"12 Upper King Street",
    "sg:city":"Norwich",
    "sg:classifiers":[
        {
            "category":"Real Estate",
            "subcategory":"Real Estate Agent",
            "type":"Services"
        }
    ],
    "sg:phone":"+44 1603 765858",
    "sg:postcode":"NR3 1HA",
    "sg:province":"Norfolk",
    "wof:name":"Nelldale Properties Ltd.",
    "wof:placetype":"venue"
},
  "geometry": {"coordinates":[1.298575,52.630154],"type":"Point"}
}