{
  "type": "Feature",
  "properties": {
    "addr:full":"62 Drayton Park Highbury Greater London N5 1ND",
    "addr:housenumber":"62",
    "addr:postcode":"n5 1nd",
    "addr:street":"Drayton Park",
    "iso:country":"GB",
    "sg:address":"62 Drayton Park",
    "sg:city":"Highbury",
    "sg:classifiers":[
        {
            "category":"Building & Trades",
            "subcategory":"Plumbing",
            "type":"Services"
        }
    ],
    "sg:phone":"+44 20 7226 2188",
    "sg:postcode":"N5 1ND",
    "sg:province":"Greater London",
    "sg:tags":[
        "merchant",
        "plumbers'"
    ],
    "wof:name":"Premier Plumbing & Heating Merchants",
    "wof:placetype":"venue"
},
  "geometry": {"coordinates":[-0.1047170013,51.5533294678],"type":"Point"}
}