{
  "type": "Feature",
  "properties": {
    "addr:full":"297 Birmingham Rd, Wylde Green Sutton Coldfield West Midlands B72 1ED",
    "addr:housenumber":"297",
    "addr:postcode":"b72 1ed",
    "addr:street":"Birmingham Rd",
    "iso:country":"GB",
    "sg:address":"297 Birmingham Rd, Wylde Green",
    "sg:city":"Sutton Coldfield",
    "sg:classifiers":[
        {
            "category":"Health Services",
            "subcategory":"Podiatrist",
            "type":"Services"
        }
    ],
    "sg:phone":"+44 121 382 5089",
    "sg:postcode":"B72 1ED",
    "sg:province":"West Midlands",
    "sg:tags":[
        "podiatrists",
        "chiropodist"
    ],
    "wof:name":"Mary Warrilow S.R.Ch. M.Ch.S. D.Pod.M.",
    "wof:placetype":"venue"
},
  "geometry": {"coordinates":[-1.8247179985,52.5432434082],"type":"Point"}
}