{
  "type": "Feature",
  "properties": {
    "iso:country":"GB",
    "sg:address":"21 Crewe Rd",
    "sg:city":"Crewe",
    "sg:classifiers":[
        {
            "category":"Professional",
            "subcategory":"Computer Services",
            "type":"Services"
        }
    ],
    "sg:phone":"+44 1270 753335",
    "sg:postcode":"CW1 6DT",
    "sg:province":"Cheshire",
    "sg:tags":[
        "system",
        "software"
    ],
    "wof:name":"G D Computer Supplies",
    "wof:placetype":"venue"
},
  "geometry": {"coordinates":[-2.427865,53.091141],"type":"Point"}
}