{
  "type": "Feature",
  "properties": {
    "iso:country":"GB",
    "sg:address":"44 Perry Street",
    "sg:city":"Northampton",
    "sg:classifiers":[
        {
            "category":"Building & Trades",
            "subcategory":"Construction",
            "type":"Services"
        }
    ],
    "sg:phone":"+44 1604 635135",
    "sg:postcode":"NN1 4HW",
    "sg:province":"Northamptonshire",
    "sg:tags":[
        "builder"
    ],
    "wof:name":"A D Alcock",
    "wof:placetype":"venue"
},
  "geometry": {"coordinates":[-0.878978,52.245296],"type":"Point"}
}