{
  "type": "Feature",
  "properties": {
    "addr:full":"Liverpool Road Barton Moss, Eccles Manchester Greater Manchester M30 7RT",
    "addr:postcode":"m30 7rt",
    "addr:street":"Liverpool Road",
    "iso:country":"GB",
    "sg:address":"Liverpool Road Barton Moss, Eccles",
    "sg:city":"Manchester",
    "sg:classifiers":[
        {
            "category":"Manufacturing",
            "subcategory":"Chemicals & Compounds",
            "type":"Manufacturing & Wholesale Goods"
        }
    ],
    "sg:phone":"+44 161 910 8800",
    "sg:postcode":"M30 7RT",
    "sg:province":"Greater Manchester",
    "wof:name":"Rhodia Ltd.",
    "wof:placetype":"venue"
},
  "geometry": {"coordinates":[-2.363704,53.479343],"type":"Point"}
}