{
  "type": "Feature",
  "properties": {
    "addr:full":"Collegiate School, Castle Street Berkhamsted Bedfordshire HP4 2BB",
    "addr:postcode":"hp4 2bb",
    "addr:street":"Castle Street",
    "iso:country":"GB",
    "sg:address":"Collegiate School, Castle Street",
    "sg:city":"Berkhamsted",
    "sg:classifiers":[
        {
            "category":"Sports & Exercise",
            "subcategory":"Gym",
            "type":"Entertainment"
        }
    ],
    "sg:phone":"+44 1442 864353",
    "sg:postcode":"HP4 2BB",
    "sg:province":"Bedfordshire",
    "sg:tags":[
        "fitness",
        "health",
        "centre"
    ],
    "wof:name":"Berkhamsted Health & Fitness Centre",
    "wof:placetype":"venue"
},
  "geometry": {"coordinates":[-0.5645589828,51.7604141235],"type":"Point"}
}