{
  "type": "Feature",
  "properties": {
    "addr:full":"46 Cardiff Rd, Llandaff Cardiff Cardiff CF5 2DT",
    "addr:housenumber":"46",
    "addr:postcode":"cf5 2dt",
    "addr:street":"Cardiff Rd",
    "iso:country":"GB",
    "sg:address":"46 Cardiff Rd, Llandaff",
    "sg:city":"Cardiff",
    "sg:classifiers":[
        {
            "category":"Professional",
            "subcategory":"Art Services",
            "type":"Services"
        }
    ],
    "sg:phone":"+44 29 2057 1180",
    "sg:postcode":"CF5 2DT",
    "sg:province":"Cardiff",
    "sg:tags":[
        "graphic",
        "designer"
    ],
    "wof:name":"Elf Designs Ltd",
    "wof:placetype":"venue"
},
  "geometry": {"coordinates":[-3.220193,51.493587],"type":"Point"}
}