{
  "type": "Feature",
  "properties": {
    "addr:full":"Straw Yard, Swan Street, Sible Hedingham Halstead Essex CO9 3RE",
    "addr:postcode":"co9 3re",
    "addr:street":"Straw;Swan Street",
    "iso:country":"GB",
    "sg:address":"Straw Yard, Swan Street, Sible Hedingham",
    "sg:city":"Halstead",
    "sg:classifiers":[
        {
            "category":"Retail",
            "subcategory":"Laundry & Dry Cleaning",
            "type":"Services"
        }
    ],
    "sg:postcode":"CO9 3RE",
    "sg:province":"Essex",
    "sg:tags":[
        "home",
        "ironing"
    ],
    "wof:name":"The Ironing Parlour",
    "wof:placetype":"venue"
},
  "geometry": {"coordinates":[0.592345,51.978249],"type":"Point"}
}