{
  "type": "Feature",
  "properties": {
    "addr:full":"Winchester House, 76 Coton Hill Shrewsbury Shropshire SY1 2DP",
    "addr:housenumber":"76",
    "addr:postcode":"sy1 2dp",
    "addr:street":"Coton Hill",
    "iso:country":"GB",
    "sg:address":"Winchester House, 76 Coton Hill",
    "sg:city":"Shrewsbury",
    "sg:classifiers":[
        {
            "category":"Health Services",
            "subcategory":"Dentist",
            "type":"Services"
        }
    ],
    "sg:postcode":"SY1 2DP",
    "sg:province":"Shropshire",
    "sg:tags":[
        "technician",
        "dental"
    ],
    "wof:name":"Ashley Ceramics",
    "wof:placetype":"venue"
},
  "geometry": {"coordinates":[-2.752479,52.714123],"type":"Point"}
}