{
  "type": "Feature",
  "properties": {
    "addr:full":"1 Western Park Rd Leicester Leicestershire LE3 6HQ",
    "addr:housenumber":"1",
    "addr:postcode":"le3 6hq",
    "addr:street":"Western Park Rd",
    "iso:country":"GB",
    "sg:address":"1 Western Park Rd",
    "sg:city":"Leicester",
    "sg:classifiers":[
        {
            "category":"Retail",
            "subcategory":"Veterinary Services",
            "type":"Services"
        }
    ],
    "sg:phone":"+44 116 276 7982",
    "sg:postcode":"LE3 6HQ",
    "sg:province":"Leicestershire",
    "sg:tags":[
        "surgeon"
    ],
    "wof:name":"Vivian J S",
    "wof:placetype":"venue"
},
  "geometry": {"coordinates":[-1.1712880135,52.633480072],"type":"Point"}
}