{
  "type": "Feature",
  "properties": {
    "addr:full":"678 Uppingham Road, Thurnby Leicester Leicestershire LE7 9RN",
    "addr:housenumber":"678",
    "addr:postcode":"le7 9rn",
    "addr:street":"Uppingham Road",
    "iso:country":"GB",
    "sg:address":"678 Uppingham Road, Thurnby",
    "sg:city":"Leicester",
    "sg:classifiers":[
        {
            "category":"Professional",
            "subcategory":"Printing & Photocopies",
            "type":"Services"
        }
    ],
    "sg:postcode":"LE7 9RN",
    "sg:province":"Leicestershire",
    "sg:tags":[
        "duplicating",
        "copying"
    ],
    "wof:name":"Micro Print",
    "wof:placetype":"venue"
},
  "geometry": {"coordinates":[-1.0435450077,52.6314353943],"type":"Point"}
}