{
  "type": "Feature",
  "properties": {
    "iso:country":"GB",
    "sg:address":"9 Sheppard Way, Minchinhampton",
    "sg:city":"Stroud",
    "sg:classifiers":[
        {
            "category":"Professional",
            "type":"Services"
        }
    ],
    "sg:postcode":"GL6 9BZ",
    "sg:province":"Gloucestershire",
    "sg:tags":[
        "entertainer"
    ],
    "wof:name":"It's Magic",
    "wof:placetype":"venue"
},
  "geometry": {"coordinates":[-2.1973469257,51.7080192566],"type":"Point"}
}