{
  "type": "Feature",
  "properties": {
    "addr:full":"Lakers, Furze La Buckingham Buckinghamshire MK18 3NB",
    "addr:postcode":"mk18 3nb",
    "addr:street":"Furze La Buckingham",
    "iso:country":"GB",
    "sg:address":"Lakers, Furze La",
    "sg:city":"Buckingham",
    "sg:classifiers":[
        {
            "category":"Building & Trades",
            "subcategory":"Construction",
            "type":"Services"
        }
    ],
    "sg:phone":"+44 1296 712592",
    "sg:postcode":"MK18 3NB",
    "sg:province":"Buckinghamshire",
    "sg:tags":[
        "joiner",
        "carpenter"
    ],
    "wof:name":"Kevin Weakley",
    "wof:placetype":"venue"
},
  "geometry": {"coordinates":[-0.9864789844,52.0007514954],"type":"Point"}
}