{
  "type": "Feature",
  "properties": {
    "addr:full":"148 Pole Barn Lane Frinton-on-sea Essex CO13 9NG",
    "addr:housenumber":"148",
    "addr:postcode":"co13 9ng",
    "addr:street":"Pole Barn Lane",
    "iso:country":"GB",
    "sg:address":"148 Pole Barn Lane",
    "sg:city":"Frinton-on-sea",
    "sg:classifiers":[
        {
            "category":"Insurance",
            "subcategory":"Insurance Agent",
            "type":"Services"
        }
    ],
    "sg:phone":"+44 1255 670500",
    "sg:postcode":"CO13 9NG",
    "sg:province":"Essex",
    "wof:name":"John Kerry",
    "wof:placetype":"venue"
},
  "geometry": {"coordinates":[1.2454199791,51.8374023438],"type":"Point"}
}