{
  "type": "Feature",
  "properties": {
    "iso:country":"GB",
    "sg:address":"Sandpiper House, Beaumont Close",
    "sg:city":"Banbury",
    "sg:classifiers":[
        {
            "category":"Professional",
            "type":"Services"
        },
        {
            "category":"Home & Garden",
            "subcategory":"Building Materials",
            "type":"Retail Goods"
        },
        {
            "category":"Personal",
            "subcategory":"Shoe Repair & Shine",
            "type":"Services"
        },
        {
            "category":"Wholesale",
            "subcategory":"Home Furnishings",
            "type":"Manufacturing & Wholesale Goods"
        }
    ],
    "sg:phone":"+44 1295 279595",
    "sg:postcode":"OX16 1TG",
    "sg:province":"Oxfordshire",
    "sg:tags":[
        "shop",
        "installers",
        "fixture",
        "maker",
        "equipment",
        "fitting",
        "display"
    ],
    "wof:name":"Brightstyle Midlands",
    "wof:placetype":"venue"
},
  "geometry": {"coordinates":[-1.3399159908,52.0777664185],"type":"Point"}
}