{
  "type": "Feature",
  "properties": {
    "addr:full":"59 Southlands Road Bromley Kent BR2 9QR",
    "addr:housenumber":"59",
    "addr:postcode":"br2 9qr",
    "addr:street":"Southlands Road",
    "iso:country":"GB",
    "sg:address":"59 Southlands Road",
    "sg:city":"Bromley",
    "sg:classifiers":[
        {
            "category":"Government",
            "subcategory":"Post Office",
            "type":"Public Place"
        }
    ],
    "sg:phone":"+44 20 8464 0942",
    "sg:postcode":"BR2 9QR",
    "sg:province":"Kent",
    "sg:tags":[
        "fax",
        "bureau",
        "telex"
    ],
    "wof:name":"Telex Answering & Communications Services",
    "wof:placetype":"venue"
},
  "geometry": {"coordinates":[0.0336299986,51.3943634033],"type":"Point"}
}