{
  "type": "Feature",
  "properties": {
    "iso:country":"GB",
    "sg:address":"Watchyard Lane, Formby",
    "sg:city":"Liverpool",
    "sg:classifiers":[
        {
            "category":"Education",
            "subcategory":"School",
            "type":"Public Place"
        }
    ],
    "sg:phone":"+44 1704 876567",
    "sg:postcode":"L37 3JT",
    "sg:province":"Lancashire",
    "sg:tags":[
        "local",
        "authority"
    ],
    "wof:name":"Freshfield County Primary School",
    "wof:placetype":"venue"
},
  "geometry": {"coordinates":[-3.0497469902,53.5629844666],"type":"Point"}
}