{
  "type": "Feature",
  "properties": {
    "iso:country":"GB",
    "sg:address":"6 Spinney Avenue, Countesthorpe",
    "sg:city":"Leicester",
    "sg:classifiers":[
        {
            "category":"Building & Trades",
            "subcategory":"Construction",
            "type":"Services"
        }
    ],
    "sg:phone":"+44 116 277 3223",
    "sg:postcode":"LE8 5RJ",
    "sg:province":"Leicestershire",
    "sg:tags":[
        "builder"
    ],
    "wof:name":"Welford Contractors",
    "wof:placetype":"venue"
},
  "geometry": {"coordinates":[-1.136831,52.556438],"type":"Point"}
}