{
  "type": "Feature",
  "properties": {
    "addr:full":"5 Moorview End, Marldon Paignton Devon TQ3 1PJ",
    "addr:housenumber":"5",
    "addr:postcode":"tq3 1pj",
    "addr:street":"Moorview End",
    "iso:country":"GB",
    "sg:address":"5 Moorview End, Marldon",
    "sg:city":"Paignton",
    "sg:classifiers":[
        {
            "category":"Building & Trades",
            "subcategory":"Construction",
            "type":"Services"
        }
    ],
    "sg:postcode":"TQ3 1PJ",
    "sg:province":"Devon",
    "sg:tags":[
        "roofing"
    ],
    "wof:name":"Marldon Roofing",
    "wof:placetype":"venue"
},
  "geometry": {"coordinates":[-3.599179,50.456619],"type":"Point"}
}