{
  "type": "Feature",
  "properties": {
    "iso:country":"GB",
    "sg:address":"Unit 7 8 9, Station Close",
    "sg:city":"Daventry",
    "sg:classifiers":[
        {
            "category":"Building & Trades",
            "subcategory":"Electrical",
            "type":"Services"
        }
    ],
    "sg:postcode":"NN11 5AA",
    "sg:province":"Northamptonshire",
    "sg:tags":[
        "lighting"
    ],
    "wof:name":"Studio 17 Lighting",
    "wof:placetype":"venue"
},
  "geometry": {"coordinates":[-1.156291,52.257759],"type":"Point"}
}