{
  "type": "Feature",
  "properties": {
    "addr:full":"151 High Street Ongar Essex CM5 9JD",
    "addr:housenumber":"151",
    "addr:postcode":"cm5 9jd",
    "addr:street":"High Street",
    "iso:country":"GB",
    "sg:address":"151 High Street",
    "sg:city":"Ongar",
    "sg:classifiers":[
        {
            "category":"Home & Garden",
            "subcategory":"Carpets & Floor Coverings",
            "type":"Retail Goods"
        }
    ],
    "sg:phone":"+44 1277 365288",
    "sg:postcode":"CM5 9JD",
    "sg:province":"Essex",
    "sg:tags":[
        "carpets",
        "rug",
        "matting"
    ],
    "wof:name":"Collop Carpets",
    "wof:placetype":"venue"
},
  "geometry": {"coordinates":[0.245374,51.703999],"type":"Point"}
}