{
  "type": "Feature",
  "properties": {
    "iso:country":"GB",
    "sg:address":"117 Walton Street",
    "sg:city":"London",
    "sg:classifiers":[
        {
            "category":"Shopping",
            "subcategory":"Beauty & Cosmetics",
            "type":"Retail Goods"
        }
    ],
    "sg:phone":"+44 20 7460 6600",
    "sg:postcode":"SW3 2HP",
    "sg:province":"Greater London",
    "sg:tags":[
        "product"
    ],
    "wof:name":"Farmacia Ltd.",
    "wof:placetype":"venue"
},
  "geometry": {"coordinates":[-0.167817,51.493828],"type":"Point"}
}