{
  "type": "Feature",
  "properties": {
    "addr:full":"1 Marsh Farm, Marsh Farm, Clenchwarton King's Lynn Lincolnshire PE34 4AZ",
    "addr:housenumber":"1;marsh farm clenchwarton",
    "addr:postcode":"pe34 4az",
    "addr:street":"Marsh Farm",
    "iso:country":"GB",
    "sg:address":"1 Marsh Farm, Marsh Farm, Clenchwarton",
    "sg:city":"King's Lynn",
    "sg:classifiers":[
        {
            "category":"Farming",
            "subcategory":"Livestock Farm",
            "type":"Manufacturing & Wholesale Goods"
        }
    ],
    "sg:postcode":"PE34 4AZ",
    "sg:province":"Lincolnshire",
    "sg:tags":[
        "others"
    ],
    "wof:name":"Alec Hurn",
    "wof:placetype":"venue"
},
  "geometry": {"coordinates":[0.35754,52.768742],"type":"Point"}
}