{
  "type": "Feature",
  "properties": {
    "addr:full":"33 New Barn St Plaistow Greater London E13 8JZ",
    "addr:housenumber":"33",
    "addr:postcode":"e13 8jz",
    "addr:street":"New Barn St",
    "iso:country":"GB",
    "sg:address":"33 New Barn St",
    "sg:city":"Plaistow",
    "sg:classifiers":[
        {
            "category":"Freight",
            "type":"Transportation"
        }
    ],
    "sg:phone":"+44 20 7476 2133",
    "sg:postcode":"E13 8JZ",
    "sg:province":"Greater London",
    "sg:tags":[
        "haulage",
        "road"
    ],
    "wof:name":"Essex Machinery & Haulage Ltd",
    "wof:placetype":"venue"
},
  "geometry": {"coordinates":[0.023945,51.5211982727],"type":"Point"}
}