{
  "type": "Feature",
  "properties": {
    "addr:full":"3a Newnham St Bedford Bedfordshire MK40 1RJ",
    "addr:housenumber":"3a",
    "addr:postcode":"mk40 1rj",
    "addr:street":"Newnham St",
    "iso:country":"GB",
    "sg:address":"3a Newnham St",
    "sg:city":"Bedford",
    "sg:classifiers":[
        {
            "category":"Real Estate",
            "subcategory":"Real Estate Operator",
            "type":"Services"
        }
    ],
    "sg:postcode":"MK40 1RJ",
    "sg:province":"Bedfordshire",
    "sg:tags":[
        "letting",
        "agent"
    ],
    "wof:name":"Bedford Letting Services Ltd",
    "wof:placetype":"venue"
},
  "geometry": {"coordinates":[-0.4624870121,52.1372795105],"type":"Point"}
}