{
  "type": "Feature",
  "properties": {
    "addr:full":"Chapel House, Burnett, Keynsham Bristol City of Bristol BS31 2TQ",
    "addr:postcode":"bs31 2tq",
    "addr:street":"Burnett",
    "iso:country":"GB",
    "sg:address":"Chapel House, Burnett, Keynsham",
    "sg:city":"Bristol",
    "sg:classifiers":[
        {
            "category":"Professional",
            "subcategory":"Computer Services",
            "type":"Services"
        }
    ],
    "sg:postcode":"BS31 2TQ",
    "sg:province":"City of Bristol",
    "sg:tags":[
        "system",
        "software"
    ],
    "wof:name":"Multinet Network Services",
    "wof:placetype":"venue"
},
  "geometry": {"coordinates":[-2.4835250378,51.389125824],"type":"Point"}
}