{
  "type": "Feature",
  "properties": {
    "iso:country":"GB",
    "sg:address":"76 Regent Street",
    "sg:city":"Leamington Spa",
    "sg:classifiers":[
        {
            "category":"Personal",
            "subcategory":"Beauty Salon",
            "type":"Services"
        }
    ],
    "sg:postcode":"CV32 4NS",
    "sg:province":"Warwickshire",
    "sg:tags":[
        "unisex",
        "hairdresser"
    ],
    "wof:name":"Capelli-Blaze Ltd.",
    "wof:placetype":"venue"
},
  "geometry": {"coordinates":[-1.53518,52.290257],"type":"Point"}
}