{
  "type": "Feature",
  "properties": {
    "iso:country":"GB",
    "sg:address":"38b Crewe Road, Alsager",
    "sg:city":"Stoke-on-trent",
    "sg:classifiers":[
        {
            "category":"Home & Garden",
            "subcategory":"Home Furnishings",
            "type":"Retail Goods"
        }
    ],
    "sg:phone":"+44 1270 884429",
    "sg:postcode":"ST7 2ET",
    "sg:province":"Cheshire",
    "sg:tags":[
        "furnishers",
        "planner",
        "kitchen"
    ],
    "wof:name":"Kempsons Kitchens and Bedrooms",
    "wof:placetype":"venue"
},
  "geometry": {"coordinates":[-2.308043,53.095665],"type":"Point"}
}