{
  "type": "Feature",
  "properties": {
    "addr:full":"26 Rubislaw Terrace Aberdeen Aberdeen City AB10 1XE",
    "addr:housenumber":"26",
    "addr:postcode":"ab10 1xe",
    "addr:street":"Rubislaw Terrace",
    "iso:country":"GB",
    "sg:address":"26 Rubislaw Terrace",
    "sg:city":"Aberdeen",
    "sg:classifiers":[
        {
            "category":"Professional",
            "subcategory":"Engineering",
            "type":"Services"
        }
    ],
    "sg:phone":"+44 1224 631122",
    "sg:postcode":"AB10 1XE",
    "sg:province":"Aberdeen City",
    "sg:tags":[
        "consulting",
        "engineer"
    ],
    "wof:name":"Arch Henderson L L P",
    "wof:placetype":"venue"
},
  "geometry": {"coordinates":[-2.1188418865,57.1434936523],"type":"Point"}
}