{
  "type": "Feature",
  "properties": {
    "iso:country":"GB",
    "sg:address":"Town Hall, St Ives Road",
    "sg:city":"Maidenhead",
    "sg:classifiers":[
        {
            "category":"Government",
            "subcategory":"Office",
            "type":"Public Place"
        }
    ],
    "sg:phone":"+44 1628 796422",
    "sg:postcode":"SL6 1RF",
    "sg:province":"Berkshire",
    "sg:tags":[
        "death",
        "births",
        "marriage",
        "birth",
        "registration",
        "local"
    ],
    "wof:name":"Registration Of Births Deaths & Marriages",
    "wof:placetype":"venue"
},
  "geometry": {"coordinates":[-0.718073,51.521969],"type":"Point"}
}