{
  "type": "Feature",
  "properties": {
    "iso:country":"GB",
    "sg:address":"11 Tabley Rd",
    "sg:city":"Holloway",
    "sg:classifiers":[
        {
            "category":"Shopping",
            "subcategory":"Beauty & Cosmetics",
            "type":"Retail Goods"
        }
    ],
    "sg:phone":"+44 20 7607 8431",
    "sg:postcode":"N7 0NA",
    "sg:province":"Greater London",
    "sg:tags":[
        "equipment",
        "supply",
        "hairdressing"
    ],
    "wof:name":"Norville Supply Co",
    "wof:placetype":"venue"
},
  "geometry": {"coordinates":[-0.123086,51.556393],"type":"Point"}
}