{
  "type": "Feature",
  "properties": {
    "addr:full":"Sneaton Lane Whitby North Yorkshire YO22 5HL",
    "addr:postcode":"yo22 5hl",
    "addr:street":"Sneaton Lane",
    "iso:country":"GB",
    "sg:address":"Sneaton Lane",
    "sg:city":"Whitby",
    "sg:classifiers":[
        {
            "category":"Professional",
            "subcategory":"Engineering",
            "type":"Services"
        }
    ],
    "sg:postcode":"YO22 5HL",
    "sg:province":"North Yorkshire",
    "wof:name":"Eskdale Agricultural Engineering Co. Ltd.",
    "wof:placetype":"venue"
},
  "geometry": {"coordinates":[-0.6258590221,54.4579048157],"type":"Point"}
}