{
  "type": "Feature",
  "properties": {
    "addr:full":"11 Locket Street Manchester Greater Manchester M8 8EE",
    "addr:housenumber":"11",
    "addr:postcode":"m8 8ee",
    "addr:street":"Locket Street",
    "iso:country":"GB",
    "sg:address":"11 Locket Street",
    "sg:city":"Manchester",
    "sg:classifiers":[
        {
            "category":"Shopping",
            "subcategory":"Clothing, Apparel, & Fashions",
            "type":"Retail Goods"
        }
    ],
    "sg:phone":"+44 161 832 7168",
    "sg:postcode":"M8 8EE",
    "sg:province":"Greater Manchester",
    "sg:tags":[
        "clothing",
        "fabric"
    ],
    "wof:name":"K C Weather Gear",
    "wof:placetype":"venue"
},
  "geometry": {"coordinates":[-2.25115,53.493862],"type":"Point"}
}