{
  "type": "Feature",
  "properties": {
    "iso:country":"GB",
    "sg:address":"Westgate Point, 30 Westgate",
    "sg:city":"Leeds",
    "sg:classifiers":[
        {
            "category":"Insurance",
            "subcategory":"Life Insurance",
            "type":"Services"
        }
    ],
    "sg:postcode":"LS1 2QZ",
    "sg:province":"West Yorkshire",
    "sg:tags":[
        "assurance"
    ],
    "wof:name":"Equitable Life Assurance Society (The)",
    "wof:placetype":"venue"
},
  "geometry": {"coordinates":[-1.546587,53.794495],"type":"Point"}
}