{
  "type": "Feature",
  "properties": {
    "addr:full":"13 Front Street, Leadgate Consett Durham DH8 7SA",
    "addr:housenumber":"13",
    "addr:postcode":"dh8 7sa",
    "addr:street":"Front Street Leadgate Consett",
    "iso:country":"GB",
    "sg:address":"13 Front Street, Leadgate",
    "sg:city":"Consett",
    "sg:classifiers":[
        {
            "category":"Bars & Pubs",
            "type":"Food & Drink"
        }
    ],
    "sg:phone":"+44 1207 502933",
    "sg:postcode":"DH8 7SA",
    "sg:province":"Durham",
    "sg:tags":[
        "pubs",
        "inn"
    ],
    "wof:name":"The Wheatsheaf Inn",
    "wof:placetype":"venue"
},
  "geometry": {"coordinates":[-1.808523,54.859497],"type":"Point"}
}