{
  "type": "Feature",
  "properties": {
    "addr:full":"74 Brookwood Road London Greater London SW18 5BY",
    "addr:housenumber":"74",
    "addr:postcode":"sw18 5by",
    "addr:street":"Brookwood Road",
    "iso:country":"GB",
    "sg:address":"74 Brookwood Road",
    "sg:city":"London",
    "sg:classifiers":[
        {
            "category":"Retail",
            "subcategory":"Repair Shop",
            "type":"Services"
        }
    ],
    "sg:phone":"+44 20 8874 7062",
    "sg:postcode":"SW18 5BY",
    "sg:province":"Greater London",
    "sg:tags":[
        "radio",
        "television",
        "video"
    ],
    "wof:name":"Witham Radio & Photographic",
    "wof:placetype":"venue"
},
  "geometry": {"coordinates":[-0.202061,51.443447],"type":"Point"}
}