{
  "type": "Feature",
  "properties": {
    "iso:country":"GB",
    "sg:address":"3-7 Alderson Road",
    "sg:city":"Sheffield",
    "sg:classifiers":[
        {
            "category":"Shopping",
            "subcategory":"Pharmacy",
            "type":"Retail Goods"
        }
    ],
    "sg:phone":"+44 114 258 4116",
    "sg:postcode":"S2 4UA",
    "sg:province":"South Yorkshire",
    "sg:tags":[
        "pharmacist",
        "chemist"
    ],
    "wof:name":"Lloyds Chemist",
    "wof:placetype":"venue"
},
  "geometry": {"coordinates":[-1.476364,53.368702],"type":"Point"}
}