{
  "type": "Feature",
  "properties": {
    "addr:full":"Temple House, 25 High Street Lewes East Sussex BN7 2LU",
    "addr:housenumber":"25",
    "addr:postcode":"bn7 2lu",
    "addr:street":"High Street",
    "iso:country":"GB",
    "sg:address":"Temple House, 25 High Street",
    "sg:city":"Lewes",
    "sg:classifiers":[
        {
            "category":"Shopping",
            "subcategory":"Books",
            "type":"Retail Goods"
        }
    ],
    "sg:phone":"+44 1273 472534",
    "sg:postcode":"BN7 2LU",
    "sg:province":"East Sussex",
    "wof:name":"The Book Guild Ltd.",
    "wof:placetype":"venue"
},
  "geometry": {"coordinates":[0.0127990004,50.8736953735],"type":"Point"}
}