{
  "type": "Feature",
  "properties": {
    "iso:country":"GB",
    "sg:address":"Po Box 26119, 27 Canmore Street",
    "sg:city":"Dunfermline",
    "sg:classifiers":[
        {
            "category":"Professional",
            "subcategory":"Accounting & Tax Preparation",
            "type":"Services"
        }
    ],
    "sg:postcode":"KY12 7WH",
    "sg:province":"Fife",
    "sg:tags":[
        "accountant"
    ],
    "wof:name":"M & S Accounting & Taxation Services",
    "wof:placetype":"venue"
},
  "geometry": {"coordinates":[-3.461374,56.074844],"type":"Point"}
}