{
  "type": "Feature",
  "properties": {
    "addr:full":"Po Box 859 Maidenhead Berkshire SL6 8LZ",
    "addr:housenumber":"po",
    "addr:postcode":"sl6 8lz",
    "addr:street":"Box 859",
    "iso:country":"GB",
    "sg:address":"Po Box 859",
    "sg:city":"Maidenhead",
    "sg:classifiers":[
        {
            "category":"Professional",
            "subcategory":"Accounting & Tax Preparation",
            "type":"Services"
        }
    ],
    "sg:phone":"+44 1628 770640",
    "sg:postcode":"SL6 8LZ",
    "sg:province":"Berkshire",
    "sg:tags":[
        "accountant"
    ],
    "wof:name":"Graham Rogers",
    "wof:placetype":"venue"
},
  "geometry": {"coordinates":[-0.7272570133,51.5223731995],"type":"Point"}
}