{
  "type": "Feature",
  "properties": {
    "iso:country":"GB",
    "sg:address":"Bodena Workshops, Horsepool Street",
    "sg:city":"Brixham",
    "sg:classifiers":[
        {
            "category":"Shopping",
            "subcategory":"Party Supplies",
            "type":"Retail Goods"
        }
    ],
    "sg:phone":"+44 1803 855746",
    "sg:postcode":"TQ5 9LD",
    "sg:province":"Devon",
    "sg:tags":[
        "equipment",
        "disco"
    ],
    "wof:name":"Traxs",
    "wof:placetype":"venue"
},
  "geometry": {"coordinates":[-3.517744,50.39407],"type":"Point"}
}