{
  "type": "Feature",
  "properties": {
    "addr:full":"22-28 Ryefield Crescent, Northwood Hills Northwood Greater London HA6 1LT",
    "addr:housenumber":"22-28",
    "addr:postcode":"ha6 1lt",
    "addr:street":"Ryefield Crescent;Hills",
    "iso:country":"GB",
    "sg:address":"22-28 Ryefield Crescent, Northwood Hills",
    "sg:city":"Northwood",
    "sg:classifiers":[
        {
            "category":"Manufacturing",
            "subcategory":"Metals",
            "type":"Manufacturing & Wholesale Goods"
        },
        {
            "category":"Wholesale",
            "subcategory":"Metals & Minerals",
            "type":"Manufacturing & Wholesale Goods"
        }
    ],
    "sg:phone":"+44 1923 829916",
    "sg:postcode":"HA6 1LT",
    "sg:province":"Greater London",
    "sg:tags":[
        "fabricator",
        "work",
        "sheet"
    ],
    "wof:name":"T C Engineering",
    "wof:placetype":"venue"
},
  "geometry": {"coordinates":[-0.409062,51.599827],"type":"Point"}
}