{
  "type": "Feature",
  "properties": {
    "addr:full":"5 Love La Cirencester Gloucestershire GL7 1YG",
    "addr:housenumber":"5",
    "addr:postcode":"gl7 1yg",
    "addr:street":"Love La Cirencester",
    "iso:country":"GB",
    "sg:address":"5 Love La",
    "sg:city":"Cirencester",
    "sg:classifiers":[
        {
            "category":"Professional",
            "subcategory":"Detective & Security Services",
            "type":"Services"
        }
    ],
    "sg:phone":"+44 1285 642111",
    "sg:postcode":"GL7 1YG",
    "sg:province":"Gloucestershire",
    "sg:tags":[
        "equipment"
    ],
    "wof:name":"Bewator Division-Metric Security",
    "wof:placetype":"venue"
},
  "geometry": {"coordinates":[-1.96109,51.705173],"type":"Point"}
}