{
  "type": "Feature",
  "properties": {
    "iso:country":"GB",
    "sg:address":"220 Burton Road",
    "sg:city":"Manchester",
    "sg:classifiers":[
        {
            "category":"Cafe",
            "type":"Food & Drink"
        }
    ],
    "sg:phone":"+44 161 445 2479",
    "sg:postcode":"M20 2LW",
    "sg:province":"Greater Manchester",
    "sg:tags":[
        "tea",
        "snack",
        "bar",
        "room"
    ],
    "wof:name":"Cachumba Cafe",
    "wof:placetype":"venue"
},
  "geometry": {"coordinates":[-2.2432661057,53.4264564514],"type":"Point"}
}