{
  "type": "Feature",
  "properties": {
    "addr:full":"38-40 Leslie Street Eastbourne East Sussex BN22 8JB",
    "addr:housenumber":"38-40",
    "addr:postcode":"bn22 8jb",
    "addr:street":"Leslie Street",
    "iso:country":"GB",
    "sg:address":"38-40 Leslie Street",
    "sg:city":"Eastbourne",
    "sg:classifiers":[
        {
            "category":"Shopping",
            "subcategory":"Mobile Phones",
            "type":"Retail Goods"
        }
    ],
    "sg:phone":"+44 1323 646647",
    "sg:postcode":"BN22 8JB",
    "sg:province":"East Sussex",
    "wof:name":"Sell-Line Corporation Ltd.",
    "wof:placetype":"venue"
},
  "geometry": {"coordinates":[0.2953340113,50.7755241394],"type":"Point"}
}