{
  "type": "Feature",
  "properties": {
    "addr:full":"27 Balmain Street Bristol City of Bristol BS4 3DB",
    "addr:housenumber":"27",
    "addr:postcode":"bs4 3db",
    "addr:street":"Balmain Street",
    "iso:country":"GB",
    "sg:address":"27 Balmain Street",
    "sg:city":"Bristol",
    "sg:classifiers":[
        {
            "category":"Shopping",
            "subcategory":"Discount & Variety Stores",
            "type":"Retail Goods"
        }
    ],
    "sg:phone":"+44 117 977 7683",
    "sg:postcode":"BS4 3DB",
    "sg:province":"City of Bristol",
    "sg:tags":[
        "cleaning",
        "supply"
    ],
    "wof:name":"Peter John Thorpe",
    "wof:placetype":"venue"
},
  "geometry": {"coordinates":[-2.5711209774,51.4410972595],"type":"Point"}
}