{
  "type": "Feature",
  "properties": {
    "addr:full":"Smythen Farm, Sterridge Valley, Berrynarbor Ilfracombe Devon EX34 9TB",
    "addr:housenumber":"berrynarbor ilfracombe",
    "addr:postcode":"ex34 9tb",
    "addr:street":"Sterridge",
    "iso:country":"GB",
    "sg:address":"Smythen Farm, Sterridge Valley, Berrynarbor",
    "sg:city":"Ilfracombe",
    "sg:classifiers":[
        {
            "category":"Farming",
            "subcategory":"Farm",
            "type":"Manufacturing & Wholesale Goods"
        }
    ],
    "sg:postcode":"EX34 9TB",
    "sg:province":"Devon",
    "sg:tags":[
        "mixed",
        "crop"
    ],
    "wof:name":"Brian A W Irwin",
    "wof:placetype":"venue"
},
  "geometry": {"coordinates":[-4.123554,51.20816],"type":"Point"}
}