{
  "type": "Feature",
  "properties": {
    "iso:country":"GB",
    "sg:address":"23-24 Castlegate Shopping Centre, Walker House",
    "sg:city":"Stockton-on-tees",
    "sg:classifiers":[
        {
            "category":"Food & Beverages",
            "subcategory":"Bakery",
            "type":"Retail Goods"
        }
    ],
    "sg:postcode":"TS18 1BG",
    "sg:province":"Durham",
    "sg:tags":[
        "baker"
    ],
    "wof:name":"The Bun Shop",
    "wof:placetype":"venue"
},
  "geometry": {"coordinates":[-1.3123699427,54.5625801086],"type":"Point"}
}