{
  "type": "Feature",
  "properties": {
    "iso:country":"GB",
    "sg:address":"Unit 5, Chettles Industrial Estate",
    "sg:city":"Nottingham",
    "sg:classifiers":[
        {
            "category":"Retail",
            "subcategory":"Auto Repair",
            "type":"Services"
        }
    ],
    "sg:postcode":"NG7 3EP",
    "sg:province":"Nottinghamshire",
    "sg:tags":[
        "modification",
        "garage"
    ],
    "wof:name":"Margin Motors",
    "wof:placetype":"venue"
},
  "geometry": {"coordinates":[-1.1623,52.955841],"type":"Point"}
}