{
  "type": "Feature",
  "properties": {
    "addr:full":"Redvers Ho, Union Rd Crediton Devon EX17 3AW",
    "addr:postcode":"ex17 3aw",
    "addr:street":"Union Rd",
    "iso:country":"GB",
    "sg:address":"Redvers Ho, Union Rd",
    "sg:city":"Crediton",
    "sg:classifiers":[
        {
            "category":"Social Services",
            "subcategory":"Adult Care",
            "type":"Services"
        },
        {
            "category":"Social Services",
            "subcategory":"Retirement Home",
            "type":"Services"
        }
    ],
    "sg:phone":"+44 1363 775513",
    "sg:postcode":"EX17 3AW",
    "sg:province":"Devon",
    "sg:tags":[
        "housing",
        "sheltered",
        "accommodation"
    ],
    "wof:name":"The Sheltered Accommodation For The Elderly",
    "wof:placetype":"venue"
},
  "geometry": {"coordinates":[-3.6614038944,50.7908363342],"type":"Point"}
}