{
  "type": "Feature",
  "properties": {
    "iso:country":"GB",
    "sg:address":"Beeching Clo",
    "sg:city":"Chard",
    "sg:classifiers":[
        {
            "category":"Utilities",
            "subcategory":"Fuel Oil & Lpg",
            "type":"Services"
        }
    ],
    "sg:phone":"+44 1460 63377",
    "sg:postcode":"TA20 1BB",
    "sg:province":"Devon",
    "sg:tags":[
        "coal",
        "smokeless"
    ],
    "wof:name":"Charringtons Solid Fuel",
    "wof:placetype":"venue"
},
  "geometry": {"coordinates":[-2.9516839981,50.8818473816],"type":"Point"}
}