{
  "type": "Feature",
  "properties": {
    "addr:full":"796 Fulham Road London Greater London SW6 5SL",
    "addr:housenumber":"796",
    "addr:postcode":"sw6 5sl",
    "addr:street":"Fulham Road",
    "iso:country":"GB",
    "sg:address":"796 Fulham Road",
    "sg:city":"London",
    "sg:classifiers":[
        {
            "category":"Taxi",
            "type":"Transportation"
        }
    ],
    "sg:phone":"+44 20 7373 8000",
    "sg:postcode":"SW6 5SL",
    "sg:province":"Greater London",
    "sg:tags":[
        "mini",
        "cab"
    ],
    "wof:name":"Palace Radio Cars",
    "wof:placetype":"venue"
},
  "geometry": {"coordinates":[-0.2110490054,51.4717559814],"type":"Point"}
}