{
  "type": "Feature",
  "properties": {
    "addr:full":"14a Winchester Walk London Greater London SE1 9AG",
    "addr:housenumber":"14a",
    "addr:postcode":"se1 9ag",
    "addr:street":"Winchester Walk",
    "iso:country":"GB",
    "sg:address":"14a Winchester Walk",
    "sg:city":"London",
    "sg:classifiers":[
        {
            "category":"Cafe",
            "type":"Food & Drink"
        }
    ],
    "sg:phone":"+44 20 7407 0557",
    "sg:postcode":"SE1 9AG",
    "sg:province":"Greater London",
    "sg:tags":[
        "tea",
        "room"
    ],
    "wof:name":"Jubilee Cafe",
    "wof:placetype":"venue"
},
  "geometry": {"coordinates":[-0.0904880017,51.5062904358],"type":"Point"}
}