{
  "type": "Feature",
  "properties": {
    "iso:country":"GB",
    "sg:address":"Unit 2, Autopark Eastgate St",
    "sg:city":"Bury St Edmunds",
    "sg:classifiers":[
        {
            "category":"Manufacturing",
            "subcategory":"Building Materials",
            "type":"Manufacturing & Wholesale Goods"
        }
    ],
    "sg:phone":"+44 1284 704187",
    "sg:postcode":"IP33 1YQ",
    "sg:province":"Suffolk",
    "sg:tags":[
        "tile",
        "mnfrs"
    ],
    "wof:name":"Aztec",
    "wof:placetype":"venue"
},
  "geometry": {"coordinates":[0.7274670005,52.2487678528],"type":"Point"}
}