{
  "type": "Feature",
  "properties": {
    "addr:full":"16 Cowley Drive, Chapeltown Sheffield South Yorkshire S35 1SW",
    "addr:housenumber":"16",
    "addr:postcode":"s35 1sw",
    "addr:street":"Cowley Drive",
    "iso:country":"GB",
    "sg:address":"16 Cowley Drive, Chapeltown",
    "sg:city":"Sheffield",
    "sg:classifiers":[
        {
            "category":"Real Estate",
            "subcategory":"Architect",
            "type":"Services"
        }
    ],
    "sg:phone":"+44 114 245 4876",
    "sg:postcode":"S35 1SW",
    "sg:province":"South Yorkshire",
    "wof:name":"Antony R Bingham",
    "wof:placetype":"venue"
},
  "geometry": {"coordinates":[-1.4550340176,53.456867218],"type":"Point"}
}