{
  "type": "Feature",
  "properties": {
    "addr:full":"4 West End, Osmotherley Northallerton North Yorkshire DL6 3AA",
    "addr:housenumber":"4",
    "addr:postcode":"dl6 3aa",
    "addr:street":"West End",
    "iso:country":"GB",
    "sg:address":"4 West End, Osmotherley",
    "sg:city":"Northallerton",
    "sg:classifiers":[
        {
            "category":"Government",
            "subcategory":"Post Office",
            "type":"Public Place"
        }
    ],
    "sg:phone":"+44 1609 883201",
    "sg:postcode":"DL6 3AA",
    "sg:province":"North Yorkshire",
    "wof:name":"Osmotherley Post Office",
    "wof:placetype":"venue"
},
  "geometry": {"coordinates":[-1.299489975,54.3687667847],"type":"Point"}
}