{
  "type": "Feature",
  "properties": {
    "iso:country":"GB",
    "sg:address":"3 High Street",
    "sg:city":"East Grinstead",
    "sg:classifiers":[
        {
            "category":"Communications",
            "subcategory":"Newspaper",
            "type":"Services"
        }
    ],
    "sg:phone":"+44 1342 312333",
    "sg:postcode":"RH19 3AF",
    "sg:province":"East Sussex",
    "sg:tags":[
        "magazine"
    ],
    "wof:name":"The Advantage",
    "wof:placetype":"venue"
},
  "geometry": {"coordinates":[-0.008026,51.124126],"type":"Point"}
}