{
  "type": "Feature",
  "properties": {
    "addr:full":"Unit 9 Foxhunters Trading Estate Whitley Bay Northumberland NE25 8UG",
    "addr:housenumber":"unit 9",
    "addr:postcode":"ne25 8ug",
    "addr:street":"Trading Estate",
    "iso:country":"GB",
    "sg:address":"Unit 9 Foxhunters Trading Estate",
    "sg:city":"Whitley Bay",
    "sg:classifiers":[
        {
            "category":"Manufacturing",
            "subcategory":"Metals",
            "type":"Manufacturing & Wholesale Goods"
        }
    ],
    "sg:postcode":"NE25 8UG",
    "sg:province":"Northumberland",
    "sg:tags":[
        "work",
        "sheet"
    ],
    "wof:name":"J Hind Sheet Metals",
    "wof:placetype":"venue"
},
  "geometry": {"coordinates":[-1.4555439949,55.0339202881],"type":"Point"}
}