{
  "type": "Feature",
  "properties": {
    "addr:full":"Rear Of 2a Lansdowne Road London Greater London N17 9XE",
    "addr:housenumber":"rear of 2a",
    "addr:postcode":"n17 9xe",
    "addr:street":"Lansdowne Road",
    "iso:country":"GB",
    "sg:address":"Rear Of 2a Lansdowne Road",
    "sg:city":"London",
    "sg:classifiers":[
        {
            "category":"Retail",
            "subcategory":"Auto Repair",
            "type":"Services"
        }
    ],
    "sg:postcode":"N17 9XE",
    "sg:province":"Greater London",
    "sg:tags":[
        "modification",
        "garage"
    ],
    "wof:name":"Mr Fixit Garage",
    "wof:placetype":"venue"
},
  "geometry": {"coordinates":[-0.06793,51.598511],"type":"Point"}
}