{
  "type": "Feature",
  "properties": {
    "iso:country":"GB",
    "sg:address":"Unit 4 Discovery Works, Trafford Park Road",
    "sg:city":"Manchester",
    "sg:classifiers":[
        {
            "category":"Building & Trades",
            "subcategory":"Cleaning & Sanitation",
            "type":"Services"
        }
    ],
    "sg:phone":"+44 161 872 5878",
    "sg:postcode":"M17 1WL",
    "sg:province":"Cheshire",
    "sg:tags":[
        "steam"
    ],
    "wof:name":"Wildgoose Cleaning Systems",
    "wof:placetype":"venue"
},
  "geometry": {"coordinates":[-2.2488100529,53.4796218872],"type":"Point"}
}