{
  "type": "Feature",
  "properties": {
    "iso:country":"GB",
    "sg:address":"Splashes Leisure Pool, Bloors Lane, Rainham",
    "sg:city":"Gillingham",
    "sg:classifiers":[
        {
            "category":"Government",
            "subcategory":"City Hall",
            "type":"Public Place"
        },
        {
            "category":"Professional",
            "subcategory":"Management & Consulting",
            "type":"Services"
        }
    ],
    "sg:phone":"+44 1634 373996",
    "sg:postcode":"ME8 7EG",
    "sg:province":"Kent",
    "sg:tags":[
        "consultant",
        "business"
    ],
    "wof:name":"Courtesy Leisure Ltd.",
    "wof:placetype":"venue"
},
  "geometry": {"coordinates":[0.5964599848,51.367061615],"type":"Point"}
}