{
  "type": "Feature",
  "properties": {
    "addr:full":"11 Beaumont Road, Chiswick London Greater London W4 5AL",
    "addr:housenumber":"11",
    "addr:postcode":"w4 5al",
    "addr:street":"Beaumont Road",
    "iso:country":"GB",
    "sg:address":"11 Beaumont Road, Chiswick",
    "sg:city":"London",
    "sg:classifiers":[
        {
            "category":"Organizations",
            "subcategory":"Community Association",
            "type":"Services"
        }
    ],
    "sg:phone":"+44 20 8742 7858",
    "sg:postcode":"W4 5AL",
    "sg:province":"Greater London",
    "sg:tags":[
        "society",
        "housing"
    ],
    "wof:name":"Argyle Crescent Hotel Ltd.",
    "wof:placetype":"venue"
},
  "geometry": {"coordinates":[-0.267102,51.500652],"type":"Point"}
}