{
  "type": "Feature",
  "properties": {
    "iso:country":"GB",
    "sg:address":"Private Road No 4, Colwick Industrial Estate",
    "sg:city":"Nottingham",
    "sg:classifiers":[
        {
            "category":"Wholesale",
            "subcategory":"Construction Materials",
            "type":"Manufacturing & Wholesale Goods"
        }
    ],
    "sg:phone":"+44 115 940 0171",
    "sg:postcode":"NG4 2JT",
    "sg:province":"Nottinghamshire",
    "sg:tags":[
        "whole",
        "asphalt",
        "macadam"
    ],
    "wof:name":"Nottingham Coated Stone",
    "wof:placetype":"venue"
},
  "geometry": {"coordinates":[-1.0613520145,52.9537200928],"type":"Point"}
}