{
  "type": "Feature",
  "properties": {
    "addr:full":"Westholme Road, Bidford On Avon Alcester Warwickshire B50 4AL",
    "addr:postcode":"avon;b50 4al",
    "addr:street":"Westholme Road",
    "iso:country":"GB",
    "sg:address":"Westholme Road, Bidford On Avon",
    "sg:city":"Alcester",
    "sg:classifiers":[
        {
            "category":"Social Services",
            "subcategory":"Adult Care",
            "type":"Services"
        }
    ],
    "sg:phone":"+44 1789 778822",
    "sg:postcode":"B50 4AL",
    "sg:province":"Warwickshire",
    "sg:tags":[
        "housing",
        "sheltered"
    ],
    "wof:name":"Westholme Court Sheltered Housing Scheme",
    "wof:placetype":"venue"
},
  "geometry": {"coordinates":[-1.8623950481,52.1674194336],"type":"Point"}
}