{
  "type": "Feature",
  "properties": {
    "iso:country":"GB",
    "sg:address":"Priory Tec Park, Saxon Way, Hessle",
    "sg:city":"Hull",
    "sg:classifiers":[
        {
            "category":"Professional",
            "subcategory":"Engineering",
            "type":"Services"
        }
    ],
    "sg:phone":"+44 1482 627963",
    "sg:postcode":"HU13 9PB",
    "sg:province":"East Riding of Yorkshire",
    "sg:tags":[
        "consulting",
        "engineer"
    ],
    "wof:name":"Gabbitas Gill Partnership Ltd.",
    "wof:placetype":"venue"
},
  "geometry": {"coordinates":[-0.4290199876,53.7210769653],"type":"Point"}
}