{
  "type": "Feature",
  "properties": {
    "iso:country":"GB",
    "sg:address":"Spedition House, Pike Road Industrial Estate",
    "sg:city":"Dover",
    "sg:classifiers":[
        {
            "category":"Professional",
            "subcategory":"Business Services",
            "type":"Services"
        }
    ],
    "sg:phone":"+44 1303 246239",
    "sg:postcode":"CT15 4ND",
    "sg:province":"Kent",
    "sg:tags":[
        "holding"
    ],
    "wof:name":"Gaski Holdings Ltd.",
    "wof:placetype":"venue"
},
  "geometry": {"coordinates":[1.2790490389,51.2122192383],"type":"Point"}
}