{
  "type": "Feature",
  "properties": {
    "iso:country":"GB",
    "sg:address":"Unit 8 Shannon Square",
    "sg:city":"Canvey Island",
    "sg:classifiers":[
        {
            "category":"Professional",
            "subcategory":"Engineering",
            "type":"Services"
        }
    ],
    "sg:phone":"+44 1268 515130",
    "sg:postcode":"SS8 0PE",
    "sg:province":"Essex",
    "sg:tags":[
        "contractor",
        "electrical",
        "engineer"
    ],
    "wof:name":"Southern Thermal Mechanical & Electrical Services Ltd.",
    "wof:placetype":"venue"
},
  "geometry": {"coordinates":[0.5594699979,51.5197715759],"type":"Point"}
}