{
  "type": "Feature",
  "properties": {
    "addr:full":"Unit 1/2 Chailey Industrial Esta, Te Pump Lane Hayes Greater London UB3 3NB",
    "addr:housenumber":"unit 1 / 2",
    "addr:postcode":"ub3 3nb",
    "addr:street":"Chailey Industrial Esta Te Pump Lane",
    "iso:country":"GB",
    "sg:address":"Unit 1/2 Chailey Industrial Esta, Te Pump Lane",
    "sg:city":"Hayes",
    "sg:classifiers":[
        {
            "category":"Wholesale",
            "subcategory":"Non-durable Goods",
            "type":"Manufacturing & Wholesale Goods"
        }
    ],
    "sg:phone":"+44 20 8573 2975",
    "sg:postcode":"UB3 3NB",
    "sg:province":"Greater London",
    "sg:tags":[
        "carry",
        "cash"
    ],
    "wof:name":"Abbey Cards",
    "wof:placetype":"venue"
},
  "geometry": {"coordinates":[-0.4247559905,51.5015525818],"type":"Point"}
}