{
  "type": "Feature",
  "properties": {
    "iso:country":"GB",
    "sg:address":"Bodefryd, Ffestiniog",
    "sg:city":"Blaenau Ffestiniog",
    "sg:classifiers":[
        {
            "category":"Taxi",
            "type":"Transportation"
        },
        {
            "category":"Military Area",
            "subcategory":"Air Force Base",
            "type":"Public Place"
        }
    ],
    "sg:phone":"+44 1766 762465",
    "sg:postcode":"LL41 4LR",
    "sg:province":"Gwynedd",
    "sg:tags":[
        "mini",
        "hire",
        "private",
        "cab"
    ],
    "wof:name":"Neville & Theresa Williams",
    "wof:placetype":"venue"
},
  "geometry": {"coordinates":[-3.931559,52.961349],"type":"Point"}
}