{
  "type": "Feature",
  "properties": {
    "addr:full":"11 Beeding Clo, Southern Cross Trading Est Bognor Regis West Sussex PO22 9TS",
    "addr:housenumber":"11",
    "addr:postcode":"po22 9ts",
    "addr:street":"Beeding Clo Southern Cross Trading Est",
    "iso:country":"GB",
    "sg:address":"11 Beeding Clo, Southern Cross Trading Est",
    "sg:city":"Bognor Regis",
    "sg:classifiers":[
        {
            "category":"Manufacturing",
            "subcategory":"Building Materials",
            "type":"Manufacturing & Wholesale Goods"
        }
    ],
    "sg:phone":"+44 1243 863181",
    "sg:postcode":"PO22 9TS",
    "sg:province":"West Sussex",
    "sg:tags":[
        "merchant",
        "builder"
    ],
    "wof:name":"Hall & Co Ltd",
    "wof:placetype":"venue"
},
  "geometry": {"coordinates":[-0.6619150043,50.8038482666],"type":"Point"}
}