{
  "type": "Feature",
  "properties": {
    "addr:full":"Unit 4, Endeavour Close, Purcell Avenue Port Talbot Neath Port Talbot SA12 7PT",
    "addr:housenumber":"unit 4",
    "addr:postcode":"sa12 7pt",
    "addr:street":"Endeavour Close Purcell Avenue",
    "iso:country":"GB",
    "sg:address":"Unit 4, Endeavour Close, Purcell Avenue",
    "sg:city":"Port Talbot",
    "sg:classifiers":[
        {
            "category":"Home & Garden",
            "subcategory":"Home Furnishings",
            "type":"Retail Goods"
        }
    ],
    "sg:phone":"+44 1639 883544",
    "sg:postcode":"SA12 7PT",
    "sg:province":"Neath Port Talbot",
    "sg:tags":[
        "homefurnishings"
    ],
    "wof:name":"1st Class Furniture",
    "wof:placetype":"venue"
},
  "geometry": {"coordinates":[-3.831829071,51.605266571],"type":"Point"}
}