{
  "type": "Feature",
  "properties": {
    "addr:full":"99 Princess Road East Leicester Leicestershire LE1 7LF",
    "addr:housenumber":"99",
    "addr:postcode":"le1 7lf",
    "addr:street":"Princess Road",
    "iso:country":"GB",
    "sg:address":"99 Princess Road East",
    "sg:city":"Leicester",
    "sg:classifiers":[
        {
            "category":"Professional",
            "subcategory":"Lawyer & Legal Services",
            "type":"Services"
        }
    ],
    "sg:phone":"+44 116 254 2698",
    "sg:postcode":"LE1 7LF",
    "sg:province":"Leicestershire",
    "sg:tags":[
        "solicitor"
    ],
    "wof:name":"Headleys",
    "wof:placetype":"venue"
},
  "geometry": {"coordinates":[-1.124301,52.627396],"type":"Point"}
}