{
  "type": "Feature",
  "properties": {
    "addr:full":"93 Dalston Lane London Greater London E8 2NG",
    "addr:housenumber":"93",
    "addr:postcode":"e8 2ng",
    "addr:street":"Dalston Lane",
    "iso:country":"GB",
    "sg:address":"93 Dalston Lane",
    "sg:city":"London",
    "sg:classifiers":[
        {
            "category":"Personal",
            "subcategory":"Beauty Salon",
            "type":"Services"
        }
    ],
    "sg:phone":"+44 20 7249 3074",
    "sg:postcode":"E8 2NG",
    "sg:province":"Greater London",
    "sg:tags":[
        "unisex",
        "hairdresser"
    ],
    "wof:name":"Hibiscus",
    "wof:placetype":"venue"
},
  "geometry": {"coordinates":[-0.070409,51.546219],"type":"Point"}
}