{
  "type": "Feature",
  "properties": {
    "addr:full":"Unit 59, The Exchange Ilford Essex IG1 1AS",
    "addr:housenumber":"unit 59",
    "addr:postcode":"ig1 1as",
    "addr:street":"The Exchange",
    "iso:country":"GB",
    "sg:address":"Unit 59, The Exchange",
    "sg:city":"Ilford",
    "sg:classifiers":[
        {
            "category":"Shopping",
            "subcategory":"Clothing, Apparel, & Fashions",
            "type":"Retail Goods"
        }
    ],
    "sg:phone":"+44 20 8478 8807",
    "sg:postcode":"IG1 1AS",
    "sg:province":"Essex",
    "sg:tags":[
        "menswear"
    ],
    "wof:name":"Nickleby's",
    "wof:placetype":"venue"
},
  "geometry": {"coordinates":[0.0671150014,51.5637512207],"type":"Point"}
}