{
  "type": "Feature",
  "properties": {
    "addr:full":"Castlehill Farm, Balmore, Torrance Glasgow East Dunbartonshire G64 4AX",
    "addr:postcode":"g64 4ax",
    "addr:street":"Castlehill;Balmore",
    "iso:country":"GB",
    "sg:address":"Castlehill Farm, Balmore, Torrance",
    "sg:city":"Glasgow",
    "sg:classifiers":[
        {
            "category":"Farming",
            "subcategory":"Livestock Farm",
            "type":"Manufacturing & Wholesale Goods"
        }
    ],
    "sg:postcode":"G64 4AX",
    "sg:province":"East Dunbartonshire",
    "sg:tags":[
        "others"
    ],
    "wof:name":"D A Ralston",
    "wof:placetype":"venue"
},
  "geometry": {"coordinates":[-4.2124137878,55.9382743835],"type":"Point"}
}