{
  "type": "Feature",
  "properties": {
    "addr:full":"1 Glenwood Gardens Taunton Somerset TA2 7PA",
    "addr:housenumber":"1",
    "addr:postcode":"ta2 7pa",
    "addr:street":"Glenwood Gardens",
    "iso:country":"GB",
    "sg:address":"1 Glenwood Gardens",
    "sg:city":"Taunton",
    "sg:classifiers":[
        {
            "category":"Building & Trades",
            "subcategory":"Construction",
            "type":"Services"
        }
    ],
    "sg:phone":"+44 1823 274577",
    "sg:postcode":"TA2 7PA",
    "sg:province":"Somerset",
    "sg:tags":[
        "heating",
        "contractor"
    ],
    "wof:name":"C Hawkings",
    "wof:placetype":"venue"
},
  "geometry": {"coordinates":[-3.1045,51.036381],"type":"Point"}
}