{
  "type": "Feature",
  "properties": {
    "iso:country":"GB",
    "sg:address":"Unit 22-23 Bradley Hall Trading Estate, Bradley Lane, Standish",
    "sg:city":"Wigan",
    "sg:classifiers":[
        {
            "category":"Utilities",
            "subcategory":"Fuel Oil & Lpg",
            "type":"Services"
        }
    ],
    "sg:phone":"+44 1257 427008",
    "sg:postcode":"WN6 0XQ",
    "sg:province":"Lancashire",
    "sg:tags":[
        "coal",
        "smokeless"
    ],
    "wof:name":"Cheetham E & Son",
    "wof:placetype":"venue"
},
  "geometry": {"coordinates":[-2.663401,53.586021],"type":"Point"}
}