{
  "type": "Feature",
  "properties": {
    "iso:country":"GB",
    "sg:address":"63 Cambridge Drive, Woodley",
    "sg:city":"Stockport",
    "sg:classifiers":[
        {
            "category":"Education",
            "subcategory":"Music School",
            "type":"Public Place"
        }
    ],
    "sg:postcode":"SK6 1HZ",
    "sg:province":"Cheshire",
    "sg:tags":[
        "teacher"
    ],
    "wof:name":"Nancy Tindall",
    "wof:placetype":"venue"
},
  "geometry": {"coordinates":[-2.0892488956,53.4251213074],"type":"Point"}
}