{
  "type": "Feature",
  "properties": {
    "addr:full":"35-37 Parker Lane Burnley Lancashire BB11 2BU",
    "addr:housenumber":"35-37",
    "addr:postcode":"bb11 2bu",
    "addr:street":"Parker Lane",
    "iso:country":"GB",
    "sg:address":"35-37 Parker Lane",
    "sg:city":"Burnley",
    "sg:classifiers":[
        {
            "category":"Utilities",
            "subcategory":"Mobile Phone",
            "type":"Services"
        },
        {
            "category":"Communications",
            "type":"Services"
        }
    ],
    "sg:phone":"+44 1282 420795",
    "sg:postcode":"BB11 2BU",
    "sg:province":"Lancashire",
    "sg:tags":[
        "sound",
        "installation",
        "system",
        "equipment",
        "music",
        "address",
        "rental",
        "public"
    ],
    "wof:name":"Opus Pro-Audio",
    "wof:placetype":"venue"
},
  "geometry": {"coordinates":[-2.242751,53.787376],"type":"Point"}
}