{
  "type": "Feature",
  "properties": {
    "iso:country":"GB",
    "sg:address":"9 Pillory Street",
    "sg:city":"Nantwich",
    "sg:classifiers":[
        {
            "category":"Personal",
            "subcategory":"Beauty Salon",
            "type":"Services"
        }
    ],
    "sg:phone":"+44 1270 628285",
    "sg:postcode":"CW5 5BZ",
    "sg:province":"Cheshire",
    "sg:tags":[
        "unisex",
        "hairdresser"
    ],
    "wof:name":"Francesco Group",
    "wof:placetype":"venue"
},
  "geometry": {"coordinates":[-2.5217010975,53.0662345886],"type":"Point"}
}