{
  "type": "Feature",
  "properties": {
    "iso:country":"GB",
    "sg:address":"39 Cambridge Road",
    "sg:city":"Hastings",
    "sg:classifiers":[
        {
            "category":"Insurance",
            "subcategory":"Insurance Agent",
            "type":"Services"
        }
    ],
    "sg:postcode":"TN34 1DJ",
    "sg:province":"East Sussex",
    "wof:name":"Swinton",
    "wof:placetype":"venue"
},
  "geometry": {"coordinates":[0.576489985,50.8554840088],"type":"Point"}
}