{
  "type": "Feature",
  "properties": {
    "addr:full":"39 Cambridge Road Hastings East Sussex TN34 1DJ",
    "addr:housenumber":"39",
    "addr:postcode":"tn34 1dj",
    "addr:street":"Cambridge Road",
    "iso:country":"GB",
    "sg:address":"39 Cambridge Road",
    "sg:city":"Hastings",
    "sg:classifiers":[
        {
            "category":"Insurance",
            "subcategory":"Insurance Agent",
            "type":"Services"
        }
    ],
    "sg:postcode":"TN34 1DJ",
    "sg:province":"East Sussex",
    "wof:name":"Swinton",
    "wof:placetype":"venue"
},
  "geometry": {"coordinates":[0.576489985,50.8554840088],"type":"Point"}
}