{
  "type": "Feature",
  "properties": {
    "addr:full":"Fogwatt Garage, Longmorn Elgin Moray IV30 8SL",
    "addr:postcode":"iv30 8sl",
    "iso:country":"GB",
    "sg:address":"Fogwatt Garage, Longmorn",
    "sg:city":"Elgin",
    "sg:classifiers":[
        {
            "category":"Autos & Motor Vehicles",
            "subcategory":"Automobile Sales",
            "type":"Retail Goods"
        },
        {
            "category":"Retail",
            "subcategory":"Auto Repair",
            "type":"Services"
        }
    ],
    "sg:postcode":"IV30 8SL",
    "sg:province":"Moray",
    "sg:tags":[
        "modification",
        "garage",
        "car"
    ],
    "wof:name":"Neil Miller",
    "wof:placetype":"venue"
},
  "geometry": {"coordinates":[-3.2833,57.608089],"type":"Point"}
}