{
  "type": "Feature",
  "properties": {
    "iso:country":"GB",
    "sg:address":"Oatlands Avenue, Whitchurch",
    "sg:city":"Bristol",
    "sg:classifiers":[
        {
            "category":"Retail",
            "subcategory":"Auto Repair",
            "type":"Services"
        }
    ],
    "sg:phone":"+44 1275 839746",
    "sg:postcode":"BS14 0ST",
    "sg:province":"City of Bristol",
    "sg:tags":[
        "modification",
        "garage"
    ],
    "wof:name":"M & M Autocare",
    "wof:placetype":"venue"
},
  "geometry": {"coordinates":[-2.551225,51.405033],"type":"Point"}
}