{
  "type": "Feature",
  "properties": {
    "addr:full":"83 Hufling Lane Burnley Lancashire BB11 3QH",
    "addr:housenumber":"83",
    "addr:postcode":"bb11 3qh",
    "addr:street":"Hufling Lane",
    "iso:country":"GB",
    "sg:address":"83 Hufling Lane",
    "sg:city":"Burnley",
    "sg:classifiers":[
        {
            "category":"Bars & Pubs",
            "type":"Food & Drink"
        },
        {
            "category":"Community Center",
            "subcategory":"Social",
            "type":"Public Place"
        }
    ],
    "sg:phone":"+44 1282 438959",
    "sg:postcode":"BB11 3QH",
    "sg:province":"Lancashire",
    "sg:tags":[
        "pubs",
        "house",
        "inn",
        "activity"
    ],
    "wof:name":"Royal Butterfly Hotel",
    "wof:placetype":"venue"
},
  "geometry": {"coordinates":[-2.2356779575,53.7798538208],"type":"Point"}
}