{
  "type": "Feature",
  "properties": {
    "iso:country":"GB",
    "sg:address":"162 Kingswell Road, Ensbury Park",
    "sg:city":"Bournemouth",
    "sg:classifiers":[
        {
            "category":"Building & Trades",
            "subcategory":"Construction",
            "type":"Services"
        }
    ],
    "sg:postcode":"BH10 5DW",
    "sg:province":"Dorset",
    "sg:tags":[
        "builder",
        "repairer",
        "chimney"
    ],
    "wof:name":"A1 Chimney Repairs by Rouse & Son",
    "wof:placetype":"venue"
},
  "geometry": {"coordinates":[-1.902081,50.754211],"type":"Point"}
}