{
  "type": "Feature",
  "properties": {
    "addr:full":"Bishopswood, Kingsmead, Wickham Fareham Hampshire PO17 5AU",
    "addr:postcode":"po17 5au",
    "iso:country":"GB",
    "sg:address":"Bishopswood, Kingsmead, Wickham",
    "sg:city":"Fareham",
    "sg:classifiers":[
        {
            "category":"Building & Trades",
            "subcategory":"Plumbing",
            "type":"Services"
        }
    ],
    "sg:postcode":"PO17 5AU",
    "sg:province":"Hampshire",
    "sg:tags":[
        "heating"
    ],
    "wof:name":"Kingsmead Property Services",
    "wof:placetype":"venue"
},
  "geometry": {"coordinates":[-1.1891089678,50.8998184204],"type":"Point"}
}