{
  "type": "Feature",
  "properties": {
    "addr:full":"Mugiemoss Rd Aberdeen Aberdeen City AB21 9US",
    "addr:postcode":"ab21 9us",
    "addr:street":"Mugiemoss Rd",
    "iso:country":"GB",
    "sg:address":"Mugiemoss Rd",
    "sg:city":"Aberdeen",
    "sg:classifiers":[
        {
            "category":"Health Services",
            "subcategory":"Nursing And Care Facility",
            "type":"Services"
        }
    ],
    "sg:phone":"+44 1224 662400",
    "sg:postcode":"AB21 9US",
    "sg:province":"Aberdeen City",
    "sg:tags":[
        "home"
    ],
    "wof:name":"Woodside Nursing Home",
    "wof:placetype":"venue"
},
  "geometry": {"coordinates":[-2.1721339226,57.1801490784],"type":"Point"}
}