{
  "type": "Feature",
  "properties": {
    "addr:full":"8b Accommodation Road Golders Green Greater London NW11 8ED",
    "addr:postcode":"nw11 8ed",
    "addr:street":"Accommodation Road",
    "iso:country":"GB",
    "sg:address":"8b Accommodation Road",
    "sg:city":"Golders Green",
    "sg:classifiers":[
        {
            "category":"Retail",
            "subcategory":"Storage",
            "type":"Services"
        }
    ],
    "sg:phone":"+44 20 7792 4083",
    "sg:postcode":"NW11 8ED",
    "sg:province":"Greater London",
    "sg:tags":[
        "household",
        "removal"
    ],
    "wof:name":"Stores (uk) Ltd",
    "wof:placetype":"venue"
},
  "geometry": {"coordinates":[-0.1979759932,51.5718383789],"type":"Point"}
}