{
  "type": "Feature",
  "properties": {
    "addr:full":"Briggate, Silsden Keighley North Yorkshire BD20 9JS",
    "addr:postcode":"bd20 9js",
    "addr:street":"Briggate",
    "iso:country":"GB",
    "sg:address":"Briggate, Silsden",
    "sg:city":"Keighley",
    "sg:classifiers":[
        {
            "category":"Place Of Worship",
            "type":"Public Place"
        }
    ],
    "sg:postcode":"BD20 9JS",
    "sg:province":"North Yorkshire",
    "wof:name":"St. James Church",
    "wof:placetype":"venue"
},
  "geometry": {"coordinates":[-1.938558,53.914921],"type":"Point"}
}