{
  "type": "Feature",
  "properties": {
    "iso:country":"GB",
    "sg:address":"242 Wellington Road, Perrybarr",
    "sg:city":"Birmingham",
    "sg:classifiers":[
        {
            "category":"Manufacturing",
            "subcategory":"Textiles",
            "type":"Manufacturing & Wholesale Goods"
        }
    ],
    "sg:phone":"+44 121 331 4334",
    "sg:postcode":"B20 2QL",
    "sg:province":"West Midlands",
    "sg:tags":[
        "printer"
    ],
    "wof:name":"Screen Print Direct Ltd",
    "wof:placetype":"venue"
},
  "geometry": {"coordinates":[-1.903966,52.515656],"type":"Point"}
}