{
  "type": "Feature",
  "properties": {
    "iso:country":"GB",
    "sg:address":"Unit 4 Factory Lane, Beestow",
    "sg:city":"Nottingham",
    "sg:classifiers":[
        {
            "category":"Professional",
            "subcategory":"Printing & Photocopies",
            "type":"Services"
        }
    ],
    "sg:postcode":"NG9 4AA",
    "sg:province":"Nottinghamshire",
    "sg:tags":[
        "embroiderer"
    ],
    "wof:name":"Extreme Logos",
    "wof:placetype":"venue"
},
  "geometry": {"coordinates":[-1.221079,52.92165],"type":"Point"}
}