{
  "type": "Feature",
  "properties": {
    "addr:full":"48 Brixton Water La Brixton Greater London SW2 1QE",
    "addr:housenumber":"48",
    "addr:postcode":"sw2 1qe",
    "addr:street":"Brixton Water",
    "iso:country":"GB",
    "sg:address":"48 Brixton Water La",
    "sg:city":"Brixton",
    "sg:classifiers":[
        {
            "category":"Health Services",
            "subcategory":"Doctor",
            "type":"Services"
        }
    ],
    "sg:phone":"+44 20 7274 1521",
    "sg:postcode":"SW2 1QE",
    "sg:province":"Greater London",
    "sg:tags":[
        "practitioners"
    ],
    "wof:name":"Flinders, S A",
    "wof:placetype":"venue"
},
  "geometry": {"coordinates":[-0.1120240018,51.45520401],"type":"Point"}
}