{
  "type": "Feature",
  "properties": {
    "iso:country":"GB",
    "sg:address":"70 Croydon Road",
    "sg:city":"West Wickham",
    "sg:classifiers":[
        {
            "category":"Home & Garden",
            "subcategory":"Home Furnishings",
            "type":"Retail Goods"
        }
    ],
    "sg:phone":"+44 20 8462 0444",
    "sg:postcode":"BR4 9HY",
    "sg:province":"Kent",
    "sg:tags":[
        "furnishers",
        "planner",
        "kitchen"
    ],
    "wof:name":"Coney Hall Designs Ltd.",
    "wof:placetype":"venue"
},
  "geometry": {"coordinates":[0.0020940001,51.3697242737],"type":"Point"}
}