{
  "type": "Feature",
  "properties": {
    "addr:full":"4 Peabody Road, North Camp Farnborough Hampshire GU14 6EY",
    "addr:housenumber":"4",
    "addr:postcode":"gu14 6ey",
    "addr:street":"Peabody Road North",
    "iso:country":"GB",
    "sg:address":"4 Peabody Road, North Camp",
    "sg:city":"Farnborough",
    "sg:classifiers":[
        {
            "category":"Personal",
            "subcategory":"Barber",
            "type":"Services"
        }
    ],
    "sg:phone":"+44 1252 512187",
    "sg:postcode":"GU14 6EY",
    "sg:province":"Hampshire",
    "sg:tags":[
        "men's",
        "hairdresser"
    ],
    "wof:name":"Mr H",
    "wof:placetype":"venue"
},
  "geometry": {"coordinates":[-0.744841,51.275154],"type":"Point"}
}