{
  "type": "Feature",
  "properties": {
    "iso:country":"GB",
    "sg:address":"309 Lower Addiscombe Rd",
    "sg:city":"Croydon",
    "sg:classifiers":[
        {
            "category":"Shopping",
            "subcategory":"News",
            "type":"Retail Goods"
        }
    ],
    "sg:postcode":"CR0 6RF",
    "sg:province":"Surrey",
    "sg:tags":[
        "newsagent"
    ],
    "wof:name":"Gandecha",
    "wof:placetype":"venue"
},
  "geometry": {"coordinates":[-0.06995,51.381756],"type":"Point"}
}