{
  "type": "Feature",
  "properties": {
    "iso:country":"GB",
    "sg:address":"Melrose, St Brides Wentlooge",
    "sg:city":"Newport",
    "sg:classifiers":[
        {
            "category":"Building & Trades",
            "subcategory":"Cleaning & Sanitation",
            "type":"Services"
        }
    ],
    "sg:postcode":"NP10 8SF",
    "sg:province":"Caerphilly",
    "sg:tags":[
        "commercial"
    ],
    "wof:name":"Gibson Cleaning Services",
    "wof:placetype":"venue"
},
  "geometry": {"coordinates":[-3.01912,51.533531],"type":"Point"}
}