{
  "type": "Feature",
  "properties": {
    "iso:country":"GB",
    "sg:address":"100 Fenwick Road, Giftknock",
    "sg:city":"Glasgow",
    "sg:classifiers":[
        {
            "category":"Food & Beverages",
            "subcategory":"Liquor & Beverages",
            "type":"Retail Goods"
        }
    ],
    "sg:phone":"+44 141 637 9036",
    "sg:postcode":"G46 6AA",
    "sg:province":"East Renfrewshire",
    "sg:tags":[
        "beer",
        "wine",
        "spirit",
        "wines"
    ],
    "wof:name":"Majestic Wine Warehouses Ltd.",
    "wof:placetype":"venue"
},
  "geometry": {"coordinates":[-4.294369,55.806179],"type":"Point"}
}