{
  "type": "Feature",
  "properties": {
    "iso:country":"GB",
    "sg:address":"34 Alexander St",
    "sg:city":"Clydebank",
    "sg:classifiers":[
        {
            "category":"Shopping",
            "subcategory":"Baby Store",
            "type":"Retail Goods"
        }
    ],
    "sg:postcode":"G81 1RZ",
    "sg:province":"East Dunbartonshire",
    "sg:tags":[
        "nursery",
        "accessory"
    ],
    "wof:name":"Cina,Harold,",
    "wof:placetype":"venue"
},
  "geometry": {"coordinates":[-4.4045810699,55.9010314941],"type":"Point"}
}