{
  "type": "Feature",
  "properties": {
    "iso:country":"GB",
    "sg:address":"Deyes Lane, Maghull",
    "sg:city":"Liverpool",
    "sg:classifiers":[
        {
            "category":"Sports & Exercise",
            "subcategory":"Swimming Pool",
            "type":"Entertainment"
        }
    ],
    "sg:phone":"+44 151 531 0933",
    "sg:postcode":"L31 6DJ",
    "sg:province":"Lancashire",
    "wof:name":"Deyes Lane Pool",
    "wof:placetype":"venue"
},
  "geometry": {"coordinates":[-2.930919,53.515751],"type":"Point"}
}