{
  "type": "Feature",
  "properties": {
    "addr:full":"52 - 54 King Edwards Drive Harrogate North Yorkshire HG1 4HL",
    "addr:housenumber":"54",
    "addr:postcode":"hg1 4hl",
    "addr:street":"King Edwards Drive",
    "iso:country":"GB",
    "sg:address":"52 - 54 King Edwards Drive",
    "sg:city":"Harrogate",
    "sg:classifiers":[
        {
            "category":"Shopping",
            "subcategory":"Pharmacy",
            "type":"Retail Goods"
        }
    ],
    "sg:phone":"+44 1423 503472",
    "sg:postcode":"HG1 4HL",
    "sg:province":"North Yorkshire",
    "sg:tags":[
        "pharmacist",
        "chemist"
    ],
    "wof:name":"Wright's Chemists Ltd.",
    "wof:placetype":"venue"
},
  "geometry": {"coordinates":[-1.5333909988,54.006023407],"type":"Point"}
}