{
  "type": "Feature",
  "properties": {
    "iso:country":"GB",
    "sg:address":"Thorns House, Thorns Road Quarry Bank",
    "sg:city":"Dudley",
    "sg:classifiers":[
        {
            "category":"Farming",
            "subcategory":"Dairy Farm",
            "type":"Manufacturing & Wholesale Goods"
        },
        {
            "category":"Food & Beverages",
            "subcategory":"Groceries & Convenience Stores",
            "type":"Retail Goods"
        }
    ],
    "sg:phone":"+44 1384 77007",
    "sg:postcode":"DY5 2JS",
    "sg:province":"West Midlands",
    "wof:name":"B & S Dairy Foods",
    "wof:placetype":"venue"
},
  "geometry": {"coordinates":[-2.110864,52.470692],"type":"Point"}
}