{
  "type": "Feature",
  "properties": {
    "iso:country":"GB",
    "sg:address":"Parkgate Road",
    "sg:city":"Chester",
    "sg:classifiers":[
        {
            "category":"Community Center",
            "type":"Public Place"
        },
        {
            "category":"Conference Center",
            "type":"Public Place"
        }
    ],
    "sg:phone":"+44 1244 375444",
    "sg:postcode":"CH1 4BJ",
    "sg:province":"Cheshire",
    "sg:tags":[
        "facility",
        "room",
        "centre"
    ],
    "sg:website":"http://www.Chester.Ac.Uk",
    "wof:name":"Chester College Conferences Ltd",
    "wof:placetype":"venue"
},
  "geometry": {"coordinates":[-2.900499,53.203403],"type":"Point"}
}