{
  "type": "Feature",
  "properties": {
    "addr:full":"210 High Road London Greater London N22 8HH",
    "addr:housenumber":"210",
    "addr:postcode":"n22 8hh",
    "addr:street":"High Road",
    "iso:country":"GB",
    "sg:address":"210 High Road",
    "sg:city":"London",
    "sg:classifiers":[
        {
            "category":"Personal",
            "subcategory":"Beauty Salon",
            "type":"Services"
        },
        {
            "category":"Personal",
            "subcategory":"Barber",
            "type":"Services"
        }
    ],
    "sg:phone":"+44 20 8889 0072",
    "sg:postcode":"N22 8HH",
    "sg:province":"Greater London",
    "sg:tags":[
        "men's",
        "hairdresser"
    ],
    "wof:name":"Chris's Hairdressers",
    "wof:placetype":"venue"
},
  "geometry": {"coordinates":[-0.1102019995,51.597869873],"type":"Point"}
}