{
  "type": "Feature",
  "properties": {
    "addr:full":"46 Sincil Street Lincoln Lincolnshire LN5 7ET",
    "addr:housenumber":"46",
    "addr:postcode":"ln5 7et",
    "addr:street":"Sincil Street",
    "iso:country":"GB",
    "sg:address":"46 Sincil Street",
    "sg:city":"Lincoln",
    "sg:classifiers":[
        {
            "category":"Shopping",
            "subcategory":"Shoes",
            "type":"Retail Goods"
        }
    ],
    "sg:phone":"+44 1522 536705",
    "sg:postcode":"LN5 7ET",
    "sg:province":"Lincolnshire",
    "sg:tags":[
        "shop"
    ],
    "wof:name":"Raw Shoe Corporation",
    "wof:placetype":"venue"
},
  "geometry": {"coordinates":[-0.538456,53.227894],"type":"Point"}
}