{
  "type": "Feature",
  "properties": {
    "iso:country":"GB",
    "sg:address":"1 Kingsland High Street",
    "sg:city":"Hackney",
    "sg:classifiers":[
        {
            "category":"Wholesale",
            "subcategory":"Office Equipment",
            "type":"Manufacturing & Wholesale Goods"
        }
    ],
    "sg:phone":"+44 20 7254 9595",
    "sg:postcode":"E8 2JS",
    "sg:province":"Greater London",
    "sg:tags":[
        "agency",
        "business",
        "enterprise"
    ],
    "wof:name":"Hackney Business Venture",
    "wof:placetype":"venue"
},
  "geometry": {"coordinates":[-0.075825,51.546261],"type":"Point"}
}