{
  "type": "Feature",
  "properties": {
    "addr:full":"18a Brock St Lancaster Lancashire LA1 1UU",
    "addr:housenumber":"18a",
    "addr:postcode":"la1 1uu",
    "addr:street":"Brock St",
    "iso:country":"GB",
    "sg:address":"18a Brock St",
    "sg:city":"Lancaster",
    "sg:classifiers":[
        {
            "category":"Shopping",
            "subcategory":"Antiques",
            "type":"Retail Goods"
        }
    ],
    "sg:postcode":"LA1 1UU",
    "sg:province":"Lancashire",
    "wof:name":"Vicary",
    "wof:placetype":"venue"
},
  "geometry": {"coordinates":[-2.7984609604,54.0473518372],"type":"Point"}
}