{
  "type": "Feature",
  "properties": {
    "iso:country":"GB",
    "sg:address":"14 Dean Street",
    "sg:city":"Ilkley",
    "sg:classifiers":[
        {
            "category":"Building & Trades",
            "subcategory":"Plumbing",
            "type":"Services"
        }
    ],
    "sg:phone":"+44 1943 600385",
    "sg:postcode":"LS29 8JR",
    "sg:province":"North Yorkshire",
    "sg:tags":[
        "heating"
    ],
    "wof:name":"C King Plumbing Contractor",
    "wof:placetype":"venue"
},
  "geometry": {"coordinates":[-1.814097,53.928249],"type":"Point"}
}