{
  "type": "Feature",
  "properties": {
    "iso:country":"GB",
    "sg:address":"111 Milton Street",
    "sg:city":"Brixham",
    "sg:classifiers":[
        {
            "category":"Building & Trades",
            "subcategory":"Landscaping Services",
            "type":"Services"
        }
    ],
    "sg:phone":"+44 1803 857986",
    "sg:postcode":"TQ5 0AS",
    "sg:province":"Devon",
    "sg:tags":[
        "landscape",
        "contractor"
    ],
    "wof:name":"C J Jackson",
    "wof:placetype":"venue"
},
  "geometry": {"coordinates":[-3.52854,50.381664],"type":"Point"}
}