{
  "type": "Feature",
  "properties": {
    "addr:full":"Unit C Nepshaw Lane South, Gildersome, Morley Leeds West Yorkshire LS27 7JQ",
    "addr:housenumber":"unit c",
    "addr:postcode":"ls27 7jq",
    "addr:street":"Nepshaw Lane South",
    "iso:country":"GB",
    "sg:address":"Unit C Nepshaw Lane South, Gildersome, Morley",
    "sg:city":"Leeds",
    "sg:classifiers":[
        {
            "category":"Manufacturing",
            "subcategory":"Tools & Machinery",
            "type":"Manufacturing & Wholesale Goods"
        },
        {
            "category":"Shopping",
            "subcategory":"Jewelry",
            "type":"Retail Goods"
        }
    ],
    "sg:phone":"+44 113 289 7461",
    "sg:postcode":"LS27 7JQ",
    "sg:province":"West Yorkshire",
    "sg:tags":[
        "cutting",
        "stone",
        "diamond"
    ],
    "wof:name":"Nimbus Diamond Tools",
    "wof:placetype":"venue"
},
  "geometry": {"coordinates":[-1.63317,53.759445],"type":"Point"}
}