{
  "type": "Feature",
  "properties": {
    "addr:full":"Acorn Business Centre, 30 Lawrence Street York North Yorkshire YO10 3BN",
    "addr:housenumber":"30",
    "addr:postcode":"yo10 3bn",
    "addr:street":"Lawrence Street",
    "iso:country":"GB",
    "sg:address":"Acorn Business Centre, 30 Lawrence Street",
    "sg:city":"York",
    "sg:classifiers":[
        {
            "category":"Professional",
            "subcategory":"Computer Services",
            "type":"Services"
        }
    ],
    "sg:postcode":"YO10 3BN",
    "sg:province":"North Yorkshire",
    "sg:tags":[
        "consultant"
    ],
    "wof:name":"Clive Jevons",
    "wof:placetype":"venue"
},
  "geometry": {"coordinates":[-1.06958,53.954781],"type":"Point"}
}