{
  "type": "Feature",
  "properties": {
    "iso:country":"GB",
    "sg:address":"Elcon House, Cambridge Road, Orwell",
    "sg:city":"Royston",
    "sg:classifiers":[
        {
            "category":"Professional",
            "subcategory":"Computer Services",
            "type":"Services"
        }
    ],
    "sg:postcode":"SG8 5QD",
    "sg:province":"Bedfordshire",
    "sg:tags":[
        "system",
        "software"
    ],
    "wof:name":"Systems Revival Ltd.",
    "wof:placetype":"venue"
},
  "geometry": {"coordinates":[-0.050892,52.121964],"type":"Point"}
}