{
  "type": "Feature",
  "properties": {
    "iso:country":"GB",
    "sg:address":"2 Sheep Street",
    "sg:city":"Stratford-upon-avon",
    "sg:classifiers":[
        {
            "category":"Professional",
            "subcategory":"Lawyer & Legal Services",
            "type":"Services"
        }
    ],
    "sg:phone":"+44 1789 292238",
    "sg:postcode":"CV37 6EJ",
    "sg:province":"Warwickshire",
    "sg:tags":[
        "solicitor"
    ],
    "wof:name":"Robert Lunn & Lowth",
    "wof:placetype":"venue"
},
  "geometry": {"coordinates":[-1.706586957,52.1916694641],"type":"Point"}
}