{
  "type": "Feature",
  "properties": {
    "addr:full":"British Library Sound Archive, 96 Euston Road London Greater London NW1 2DB",
    "addr:housenumber":"96",
    "addr:postcode":"nw1 2db",
    "addr:street":"Euston Road",
    "iso:country":"GB",
    "sg:address":"British Library Sound Archive, 96 Euston Road",
    "sg:city":"London",
    "sg:classifiers":[
        {
            "category":"Education",
            "subcategory":"Library",
            "type":"Public Place"
        }
    ],
    "sg:phone":"+44 20 7412 7404",
    "sg:postcode":"NW1 2DB",
    "sg:province":"Greater London",
    "sg:tags":[
        "book"
    ],
    "wof:name":"The National Life Story Collection",
    "wof:placetype":"venue"
},
  "geometry": {"coordinates":[-0.12694,51.52898],"type":"Point"}
}