{
  "type": "Feature",
  "properties": {
    "addr:full":"165 High Street Hornchurch Essex RM11 3XF",
    "addr:housenumber":"165",
    "addr:postcode":"rm11 3xf",
    "addr:street":"High Street",
    "iso:country":"GB",
    "sg:address":"165 High Street",
    "sg:city":"Hornchurch",
    "sg:classifiers":[
        {
            "category":"Sports & Exercise",
            "subcategory":"Sports Center",
            "type":"Entertainment"
        }
    ],
    "sg:phone":"+44 1708 456327",
    "sg:postcode":"RM11 3XF",
    "sg:province":"Essex",
    "sg:tags":[
        "shop",
        "good"
    ],
    "wof:name":"Sportspride Ltd.",
    "wof:placetype":"venue"
},
  "geometry": {"coordinates":[0.220907,51.561768],"type":"Point"}
}