{
  "type": "Feature",
  "properties": {
    "iso:country":"GB",
    "sg:address":"Mackenzie House, Coach & Horses Passage",
    "sg:city":"Tunbridge Wells",
    "sg:classifiers":[
        {
            "category":"Professional",
            "subcategory":"Accounting & Tax Preparation",
            "type":"Services"
        }
    ],
    "sg:phone":"+44 1892 514451",
    "sg:postcode":"TN2 5NP",
    "sg:province":"East Sussex",
    "sg:tags":[
        "accountant"
    ],
    "wof:name":"Ward Mackenzie Accountants",
    "wof:placetype":"venue"
},
  "geometry": {"coordinates":[0.25839,51.12587],"type":"Point"}
}