{
  "type": "Feature",
  "properties": {
    "addr:full":"7 Biddenden Way, Istead Rise, Northfleet Hill Gravesend Kent DA13 9DE",
    "addr:housenumber":"7",
    "addr:postcode":"da13 9de",
    "addr:street":"Biddenden Way Istead Rise Northfleet Hill",
    "iso:country":"GB",
    "sg:address":"7 Biddenden Way, Istead Rise, Northfleet Hill",
    "sg:city":"Gravesend",
    "sg:classifiers":[
        {
            "category":"Building & Trades",
            "subcategory":"Construction",
            "type":"Services"
        }
    ],
    "sg:phone":"+44 1474 832046",
    "sg:postcode":"DA13 9DE",
    "sg:province":"Kent",
    "sg:tags":[
        "joiner",
        "carpenter"
    ],
    "wof:name":"Thornton Home Improvements",
    "wof:placetype":"venue"
},
  "geometry": {"coordinates":[0.347429,51.404858],"type":"Point"}
}