{
  "type": "Feature",
  "properties": {
    "addr:full":"168 High Street, Yiewsley West Drayton Greater London UB7 7BE",
    "addr:housenumber":"168",
    "addr:postcode":"ub7 7be",
    "addr:street":"High Street",
    "iso:country":"GB",
    "sg:address":"168 High Street, Yiewsley",
    "sg:city":"West Drayton",
    "sg:classifiers":[
        {
            "category":"Personal",
            "subcategory":"Beauty Salon",
            "type":"Services"
        },
        {
            "category":"Retail",
            "subcategory":"Auto Repair",
            "type":"Services"
        }
    ],
    "sg:phone":"+44 1895 444946",
    "sg:postcode":"UB7 7BE",
    "sg:province":"Greater London",
    "sg:tags":[
        "modification",
        "garage",
        "hairdresser",
        "unisex"
    ],
    "wof:name":"Matties",
    "wof:placetype":"venue"
},
  "geometry": {"coordinates":[-0.474023,51.51506],"type":"Point"}
}