{
  "type": "Feature",
  "properties": {
    "iso:country":"GB",
    "sg:address":"The Old Bakery, Market Place, Deddington",
    "sg:city":"Banbury",
    "sg:classifiers":[
        {
            "category":"Real Estate",
            "subcategory":"Real Estate Agent",
            "type":"Services"
        }
    ],
    "sg:phone":"+44 1869 337001",
    "sg:postcode":"OX15 0SE",
    "sg:province":"Oxfordshire",
    "wof:name":"Hayward White",
    "wof:placetype":"venue"
},
  "geometry": {"coordinates":[-1.323404,51.981804],"type":"Point"}
}