{
  "type": "Feature",
  "properties": {
    "iso:country":"GB",
    "sg:address":"53 Shore Street",
    "sg:city":"Inverness",
    "sg:classifiers":[
        {
            "category":"Manufacturing",
            "subcategory":"Lumber",
            "type":"Manufacturing & Wholesale Goods"
        }
    ],
    "sg:phone":"+44 1463 233013",
    "sg:postcode":"IV1 1NY",
    "sg:province":"Highland",
    "sg:tags":[
        "importer",
        "merchants",
        "agent",
        "timber"
    ],
    "wof:name":"John Fleming & Co",
    "wof:placetype":"venue"
},
  "geometry": {"coordinates":[-4.229781,57.484062],"type":"Point"}
}