{
  "type": "Feature",
  "properties": {
    "iso:country":"GB",
    "sg:address":"Cambria, The Reddings",
    "sg:city":"Cheltenham",
    "sg:classifiers":[
        {
            "category":"Home & Garden",
            "subcategory":"Furniture",
            "type":"Retail Goods"
        }
    ],
    "sg:postcode":"GL51 6RL",
    "sg:province":"Gloucestershire",
    "wof:name":"Lightmaster (Direct) Ltd",
    "wof:placetype":"venue"
},
  "geometry": {"coordinates":[-2.133139,51.887733],"type":"Point"}
}