{
  "type": "Feature",
  "properties": {
    "iso:country":"GB",
    "sg:address":"64 Horsefair Street, Charlton Kings",
    "sg:city":"Cheltenham",
    "sg:classifiers":[
        {
            "category":"Retail",
            "subcategory":"Animal Services",
            "type":"Services"
        },
        {
            "category":"Personal",
            "subcategory":"Adult",
            "type":"Services"
        }
    ],
    "sg:phone":"+44 1242 243663",
    "sg:postcode":"GL53 8JH",
    "sg:province":"Gloucestershire",
    "sg:tags":[
        "farrier",
        "equestrian"
    ],
    "wof:name":"Richard Knight",
    "wof:placetype":"venue"
},
  "geometry": {"coordinates":[-2.0534958839,51.8822784424],"type":"Point"}
}