{
  "type": "Feature",
  "properties": {
    "addr:full":"4 North Street Rhayader Powys LD6 5BU",
    "addr:housenumber":"4",
    "addr:postcode":"ld6 5bu",
    "addr:street":"North Street",
    "iso:country":"GB",
    "sg:address":"4 North Street",
    "sg:city":"Rhayader",
    "sg:classifiers":[
        {
            "category":"Real Estate",
            "subcategory":"Real Estate Agent",
            "type":"Services"
        }
    ],
    "sg:phone":"+44 1597 810457",
    "sg:postcode":"LD6 5BU",
    "sg:province":"Powys",
    "wof:name":"Russell Baldwin & Bright",
    "wof:placetype":"venue"
},
  "geometry": {"coordinates":[-3.51131,52.301464],"type":"Point"}
}