{
  "type": "Feature",
  "properties": {
    "iso:country":"GB",
    "sg:address":"Horns Rd, Hawkhurst",
    "sg:city":"Cranbrook",
    "sg:classifiers":[
        {
            "category":"Autos & Motor Vehicles",
            "subcategory":"Fuel & Gas Station",
            "type":"Retail Goods"
        }
    ],
    "sg:phone":"+44 1580 752020",
    "sg:postcode":"TN18 4QT",
    "sg:province":"East Sussex",
    "sg:tags":[
        "petrol",
        "filling"
    ],
    "wof:name":"Hawkhurst Service Station",
    "wof:placetype":"venue"
},
  "geometry": {"coordinates":[0.4857189953,51.0387001038],"type":"Point"}
}