{
  "type": "Feature",
  "properties": {
    "iso:country":"GB",
    "sg:address":"11 Oaklands Road",
    "sg:city":"Bury",
    "sg:classifiers":[
        {
            "category":"Personal",
            "type":"Services"
        }
    ],
    "sg:postcode":"BL0 0LR",
    "sg:province":"Lancashire",
    "sg:tags":[
        "wedding"
    ],
    "wof:name":"Steve Anderton Catering",
    "wof:placetype":"venue"
},
  "geometry": {"coordinates":[-2.309528,53.665451],"type":"Point"}
}