{
  "type": "Feature",
  "properties": {
    "addr:full":"1 High Street Crickhowell Monmouthshire NP8 1BD",
    "addr:housenumber":"1",
    "addr:postcode":"np8 1bd",
    "addr:street":"High Street",
    "iso:country":"GB",
    "sg:address":"1 High Street",
    "sg:city":"Crickhowell",
    "sg:classifiers":[
        {
            "category":"Professional",
            "subcategory":"Lawyer & Legal Services",
            "type":"Services"
        }
    ],
    "sg:phone":"+44 1873 810220",
    "sg:postcode":"NP8 1BD",
    "sg:province":"Monmouthshire",
    "sg:tags":[
        "solicitor"
    ],
    "wof:name":"David Hutton",
    "wof:placetype":"venue"
},
  "geometry": {"coordinates":[-3.1371290684,51.8590316772],"type":"Point"}
}