{
  "type": "Feature",
  "properties": {
    "addr:full":"Heatherbarn, Salt La Godalming Surrey GU8 4DH",
    "addr:postcode":"gu8 4dh",
    "addr:street":"La Godalming",
    "iso:country":"GB",
    "sg:address":"Heatherbarn, Salt La",
    "sg:city":"Godalming",
    "sg:classifiers":[
        {
            "category":"Communications",
            "subcategory":"News Services",
            "type":"Services"
        }
    ],
    "sg:phone":"+44 1483 860321",
    "sg:postcode":"GU8 4DH",
    "sg:province":"Surrey",
    "sg:tags":[
        "illustrator"
    ],
    "wof:name":"J Gordon Duff",
    "wof:placetype":"venue"
},
  "geometry": {"coordinates":[-0.60867,51.154449],"type":"Point"}
}