{
  "type": "Feature",
  "properties": {
    "iso:country":"GB",
    "sg:address":"132 Grahams Road, Bankside",
    "sg:city":"Falkirk",
    "sg:classifiers":[
        {
            "category":"Military Area",
            "subcategory":"Air Force Base",
            "type":"Public Place"
        }
    ],
    "sg:phone":"+44 1324 619333",
    "sg:postcode":"FK2 7BZ",
    "sg:province":"Falkirk",
    "sg:tags":[
        "taxi",
        "hire",
        "private"
    ],
    "wof:name":"Five Star Travel",
    "wof:placetype":"venue"
},
  "geometry": {"coordinates":[-3.784625,56.006882],"type":"Point"}
}