{
  "type": "Feature",
  "properties": {
    "iso:country":"GB",
    "sg:address":"6 Brendon Rd",
    "sg:city":"Watchet",
    "sg:classifiers":[
        {
            "category":"Professional",
            "subcategory":"Computer Services",
            "type":"Services"
        }
    ],
    "sg:phone":"+44 1984 634903",
    "sg:postcode":"TA23 0AU",
    "sg:province":"Somerset",
    "sg:tags":[
        "development",
        "system",
        "software"
    ],
    "wof:name":"Treasures",
    "wof:placetype":"venue"
},
  "geometry": {"coordinates":[-3.330807,51.179577],"type":"Point"}
}