{
  "type": "Feature",
  "properties": {
    "addr:full":"6 Oak Piece, North Weald Epping Essex CM16 6JJ",
    "addr:housenumber":"6",
    "addr:postcode":"cm16 6jj",
    "addr:street":"Oak Piece North",
    "iso:country":"GB",
    "sg:address":"6 Oak Piece, North Weald",
    "sg:city":"Epping",
    "sg:classifiers":[
        {
            "category":"Wholesale",
            "subcategory":"Machinery & Supplies",
            "type":"Manufacturing & Wholesale Goods"
        }
    ],
    "sg:phone":"+44 1992 523840",
    "sg:postcode":"CM16 6JJ",
    "sg:province":"Essex",
    "wof:name":"R C Eckley Agricultural Repair Service",
    "wof:placetype":"venue"
},
  "geometry": {"coordinates":[0.07914,51.7266311646],"type":"Point"}
}