{
  "type": "Feature",
  "properties": {
    "iso:country":"GB",
    "sg:address":"7a Simpson Road, East Mains Industrial Estate",
    "sg:city":"Broxburn",
    "sg:classifiers":[
        {
            "category":"Wholesale",
            "subcategory":"Electrical",
            "type":"Manufacturing & Wholesale Goods"
        }
    ],
    "sg:phone":"+44 1506 859000",
    "sg:postcode":"EH52 5NP",
    "sg:province":"City of Edinburgh",
    "sg:tags":[
        "equipment",
        "refrigeration"
    ],
    "wof:name":"Capital Cooling Ltd.",
    "wof:placetype":"venue"
},
  "geometry": {"coordinates":[-3.450083,55.940331],"type":"Point"}
}