{
  "type": "Feature",
  "properties": {
    "addr:full":"Centrepoint, 103 New Oxford Street London Greater London WC1A 1QF",
    "addr:housenumber":"103",
    "addr:postcode":"wc1a 1qf",
    "addr:street":"New Oxford Street",
    "iso:country":"GB",
    "sg:address":"Centrepoint, 103 New Oxford Street",
    "sg:city":"London",
    "sg:classifiers":[
        {
            "category":"Professional",
            "subcategory":"Business Services",
            "type":"Services"
        }
    ],
    "sg:postcode":"WC1A 1QF",
    "sg:province":"Greater London",
    "sg:tags":[
        "holding"
    ],
    "wof:name":"L F G Holdings Ltd.",
    "wof:placetype":"venue"
},
  "geometry": {"coordinates":[-0.14439,51.514931],"type":"Point"}
}