{
  "type": "Feature",
  "properties": {
    "addr:full":"19 Kiln Fields Haslemere Hampshire GU27 1AY",
    "addr:housenumber":"19",
    "addr:postcode":"gu27 1ay",
    "addr:street":"Kiln Fields",
    "iso:country":"GB",
    "sg:address":"19 Kiln Fields",
    "sg:city":"Haslemere",
    "sg:classifiers":[
        {
            "category":"Building & Trades",
            "subcategory":"Construction",
            "type":"Services"
        }
    ],
    "sg:phone":"+44 1428 652173",
    "sg:postcode":"GU27 1AY",
    "sg:province":"Hampshire",
    "sg:tags":[
        "bricklaying"
    ],
    "wof:name":"B Brown",
    "wof:placetype":"venue"
},
  "geometry": {"coordinates":[-0.7117379904,51.0939712524],"type":"Point"}
}