{
  "type": "Feature",
  "properties": {
    "addr:full":"118 Higher Road, Urmston, Trafford Manchester Cheshire M41 9AZ",
    "addr:housenumber":"118",
    "addr:postcode":"m41 9az",
    "addr:street":"Higher Road",
    "iso:country":"GB",
    "sg:address":"118 Higher Road, Urmston, Trafford",
    "sg:city":"Manchester",
    "sg:classifiers":[
        {
            "category":"Real Estate",
            "subcategory":"Surveying",
            "type":"Services"
        }
    ],
    "sg:phone":"+44 161 747 0693",
    "sg:postcode":"M41 9AZ",
    "sg:province":"Cheshire",
    "sg:tags":[
        "building",
        "quantity",
        "surveyor"
    ],
    "wof:name":"POUNDALL P J & ASSOCIATES",
    "wof:placetype":"venue"
},
  "geometry": {"coordinates":[-2.346049,53.448425],"type":"Point"}
}