{
  "type": "Feature",
  "properties": {
    "addr:full":"Bishop Street Portsmouth Hampshire PO1 3DA",
    "addr:postcode":"hampshire po1 3da",
    "addr:street":"Bishop Street",
    "iso:country":"GB",
    "sg:address":"Bishop Street",
    "sg:city":"Portsmouth",
    "sg:classifiers":[
        {
            "category":"Museum",
            "subcategory":"Art Museum",
            "type":"Entertainment"
        }
    ],
    "sg:phone":"+44 23 9282 4745",
    "sg:postcode":"PO1 3DA",
    "sg:province":"Hampshire",
    "sg:tags":[
        "gallery"
    ],
    "wof:name":"Treadgold Industrial Heritage Museum",
    "wof:placetype":"venue"
},
  "geometry": {"coordinates":[-1.1015390158,50.7989082336],"type":"Point"}
}