{
  "type": "Feature",
  "properties": {
    "iso:country":"GB",
    "sg:address":"41 Spring Gro",
    "sg:city":"Hebden Bridge",
    "sg:classifiers":[
        {
            "category":"Education",
            "subcategory":"Music School",
            "type":"Public Place"
        }
    ],
    "sg:postcode":"HX7 8LR",
    "sg:province":"West Yorkshire",
    "sg:tags":[
        "conservatory"
    ],
    "wof:name":"S J Craven",
    "wof:placetype":"venue"
},
  "geometry": {"coordinates":[-2.013729,53.746853],"type":"Point"}
}