{
  "type": "Feature",
  "properties": {
    "addr:full":"Hollyhouse Farm, Horseway Chatteris Cambridgeshire PE16 6XQ",
    "addr:postcode":"pe16 6xq",
    "iso:country":"GB",
    "sg:address":"Hollyhouse Farm, Horseway",
    "sg:city":"Chatteris",
    "sg:classifiers":[
        {
            "category":"Building & Trades",
            "subcategory":"Landscaping Services",
            "type":"Services"
        },
        {
            "category":"Professional",
            "subcategory":"Engineering",
            "type":"Services"
        }
    ],
    "sg:phone":"+44 1354 695919",
    "sg:postcode":"PE16 6XQ",
    "sg:province":"Cambridgeshire",
    "sg:tags":[
        "horticultural"
    ],
    "wof:name":"S G Smith Agricultural Repairs",
    "wof:placetype":"venue"
},
  "geometry": {"coordinates":[0.0486660004,52.4536323547],"type":"Point"}
}