{
  "type": "Feature",
  "properties": {
    "addr:full":"Elamine, Five Oak Grn Tonbridge Kent TN12 6RE",
    "addr:postcode":"tn12 6re",
    "addr:street":"Oak Grn Tonbridge",
    "iso:country":"GB",
    "sg:address":"Elamine, Five Oak Grn",
    "sg:city":"Tonbridge",
    "sg:classifiers":[
        {
            "category":"Retail",
            "subcategory":"Auto Repair",
            "type":"Services"
        }
    ],
    "sg:phone":"+44 1892 832112",
    "sg:postcode":"TN12 6RE",
    "sg:province":"Kent",
    "sg:tags":[
        "bodybuilder",
        "repairer"
    ],
    "wof:name":"Ellis & Son (Vehicle Builders) Ltd.",
    "wof:placetype":"venue"
},
  "geometry": {"coordinates":[0.357145,51.183479],"type":"Point"}
}