{
  "type": "Feature",
  "properties": {
    "iso:country":"GB",
    "sg:address":"Oathill, Enstone",
    "sg:city":"Chipping Norton",
    "sg:classifiers":[
        {
            "category":"Building & Trades",
            "subcategory":"Construction",
            "type":"Services"
        },
        {
            "category":"Manufacturing",
            "subcategory":"Building Materials",
            "type":"Manufacturing & Wholesale Goods"
        }
    ],
    "sg:postcode":"OX7 4ED",
    "sg:province":"Gloucestershire",
    "sg:tags":[
        "driveway",
        "concrete",
        "product",
        "paving",
        "contractor"
    ],
    "wof:name":"Andrew Henderson (Paving) Ltd.",
    "wof:placetype":"venue"
},
  "geometry": {"coordinates":[-1.443284,51.95195],"type":"Point"}
}