{
  "type": "Feature",
  "properties": {
    "addr:full":"Unit 19, Guildhall Centre, Market Place Stafford Staffordshire ST16 2BB",
    "addr:housenumber":"unit 19",
    "addr:postcode":"st16 2bb",
    "addr:street":"Guildhall Centre Market Place",
    "iso:country":"GB",
    "sg:address":"Unit 19, Guildhall Centre, Market Place",
    "sg:city":"Stafford",
    "sg:classifiers":[
        {
            "category":"Shopping",
            "subcategory":"Mobile Phones",
            "type":"Retail Goods"
        }
    ],
    "sg:phone":"+44 1785 222244",
    "sg:postcode":"ST16 2BB",
    "sg:province":"Staffordshire",
    "wof:name":"The Pocketphone Shop Ltd.",
    "wof:placetype":"venue"
},
  "geometry": {"coordinates":[-2.1217679977,52.8039588928],"type":"Point"}
}