{
  "type": "Feature",
  "properties": {
    "iso:country":"GB",
    "sg:address":"P O Box 3",
    "sg:city":"Ipswich",
    "sg:classifiers":[
        {
            "category":"Professional",
            "subcategory":"Employment Agencies",
            "type":"Services"
        }
    ],
    "sg:postcode":"IP7 6EP",
    "sg:province":"Suffolk",
    "sg:tags":[
        "agricultural",
        "advice"
    ],
    "wof:name":"Hadleigh Farmers' Agricultural Association",
    "wof:placetype":"venue"
},
  "geometry": {"coordinates":[0.9471300244,52.0550498962],"type":"Point"}
}