{
  "type": "Feature",
  "properties": {
    "iso:country":"GB",
    "sg:address":"21 Blyth Road, Maltby",
    "sg:city":"Rotherham",
    "sg:classifiers":[
        {
            "category":"Organizations",
            "subcategory":"Membership Organization",
            "type":"Services"
        }
    ],
    "sg:postcode":"S66 8HX",
    "sg:province":"South Yorkshire",
    "sg:tags":[
        "club"
    ],
    "wof:name":"Maltby Ex-Service & Social Club Ltd.",
    "wof:placetype":"venue"
},
  "geometry": {"coordinates":[-1.206054,53.422112],"type":"Point"}
}