{
  "type": "Feature",
  "properties": {
    "addr:full":"Unit 9, Grange Lane, Beenham Reading Berkshire RG7 5PP",
    "addr:housenumber":"unit 9",
    "addr:postcode":"rg7 5pp",
    "addr:street":"Grange Lane",
    "iso:country":"GB",
    "sg:address":"Unit 9, Grange Lane, Beenham",
    "sg:city":"Reading",
    "sg:classifiers":[
        {
            "category":"Home & Garden",
            "subcategory":"Kitchen Supply",
            "type":"Retail Goods"
        }
    ],
    "sg:phone":"+44 118 971 4420",
    "sg:postcode":"RG7 5PP",
    "sg:province":"Berkshire",
    "sg:tags":[
        "equipment",
        "brewer"
    ],
    "wof:name":"Techni-Cool Ltd.",
    "wof:placetype":"venue"
},
  "geometry": {"coordinates":[-1.1452740431,51.4063987732],"type":"Point"}
}