{
  "type": "Feature",
  "properties": {
    "addr:full":"Infant Site, Backhold La Halifax West Yorkshire HX3 9DL",
    "addr:postcode":"hx3 9dl",
    "addr:street":"La;West",
    "iso:country":"GB",
    "sg:address":"Infant Site, Backhold La",
    "sg:city":"Halifax",
    "sg:classifiers":[
        {
            "category":"Education",
            "subcategory":"School",
            "type":"Public Place"
        }
    ],
    "sg:phone":"+44 1422 353989",
    "sg:postcode":"HX3 9DL",
    "sg:province":"West Yorkshire",
    "sg:tags":[
        "local",
        "authority"
    ],
    "wof:name":"Siddal Primary School",
    "wof:placetype":"venue"
},
  "geometry": {"coordinates":[-1.84739,53.70369],"type":"Point"}
}