{
  "type": "Feature",
  "properties": {
    "addr:full":"Hill Farm, Knights Grn Dymock Gloucestershire GL18 2DF",
    "addr:postcode":"gl18 2df",
    "addr:street":"Hill;Knights Grn",
    "iso:country":"GB",
    "sg:address":"Hill Farm, Knights Grn",
    "sg:city":"Dymock",
    "sg:classifiers":[
        {
            "category":"Farming",
            "subcategory":"Crops",
            "type":"Manufacturing & Wholesale Goods"
        },
        {
            "category":"Farming",
            "subcategory":"Livestock Farm",
            "type":"Manufacturing & Wholesale Goods"
        }
    ],
    "sg:phone":"+44 1531 890215",
    "sg:postcode":"GL18 2DF",
    "sg:province":"Gloucestershire",
    "sg:tags":[
        "arable",
        "others"
    ],
    "wof:name":"E & M Lewis",
    "wof:placetype":"venue"
},
  "geometry": {"coordinates":[-2.4397089481,51.9788093567],"type":"Point"}
}