{
  "type": "Feature",
  "properties": {
    "iso:country":"GB",
    "sg:address":"3 Banner Street, Leeds Road",
    "sg:city":"Bradford",
    "sg:classifiers":[
        {
            "category":"Professional",
            "subcategory":"Printing & Photocopies",
            "type":"Services"
        }
    ],
    "sg:phone":"+44 1274 390567",
    "sg:postcode":"BD3 9RH",
    "sg:province":"West Yorkshire",
    "sg:tags":[
        "printer"
    ],
    "wof:name":"The Club Press",
    "wof:placetype":"venue"
},
  "geometry": {"coordinates":[-1.7372089624,53.7926216125],"type":"Point"}
}