{
  "type": "Feature",
  "properties": {
    "iso:country":"GB",
    "sg:address":"28 Upper Hamilton Rd",
    "sg:city":"Brighton",
    "sg:classifiers":[
        {
            "category":"Bars & Pubs",
            "type":"Food & Drink"
        }
    ],
    "sg:postcode":"BN1 5DF",
    "sg:province":"East Sussex",
    "sg:tags":[
        "pubs",
        "inn"
    ],
    "wof:name":"Vane,Maureen Juliet,",
    "wof:placetype":"venue"
},
  "geometry": {"coordinates":[-0.148668,50.835247],"type":"Point"}
}