{
  "type": "Feature",
  "properties": {
    "addr:full":"151 Westwood Hill Glasgow South Lanarkshire G75 8QA",
    "addr:housenumber":"151",
    "addr:postcode":"g75 8qa",
    "addr:street":"Westwood Hill",
    "iso:country":"GB",
    "sg:address":"151 Westwood Hill",
    "sg:city":"Glasgow",
    "sg:classifiers":[
        {
            "category":"Place Of Worship",
            "type":"Public Place"
        }
    ],
    "sg:phone":"+44 1355 239608",
    "sg:postcode":"G75 8QA",
    "sg:province":"South Lanarkshire",
    "wof:name":"Lutheran Church St Columba",
    "wof:placetype":"venue"
},
  "geometry": {"coordinates":[-4.2077388763,55.7553710938],"type":"Point"}
}