{
  "type": "Feature",
  "properties": {
    "addr:full":"3 Station Road, Barrow Hill Chesterfield Derbyshire S43 2PG",
    "addr:housenumber":"3",
    "addr:postcode":"s43 2pg",
    "addr:street":"Station Road",
    "iso:country":"GB",
    "sg:address":"3 Station Road, Barrow Hill",
    "sg:city":"Chesterfield",
    "sg:classifiers":[
        {
            "category":"Organizations",
            "subcategory":"Membership Organization",
            "type":"Services"
        }
    ],
    "sg:phone":"+44 1246 472227",
    "sg:postcode":"S43 2PG",
    "sg:province":"Derbyshire",
    "sg:tags":[
        "club"
    ],
    "wof:name":"Barrow Hill Memorial Club",
    "wof:placetype":"venue"
},
  "geometry": {"coordinates":[-1.37631,53.273506],"type":"Point"}
}