{
  "type": "Feature",
  "properties": {
    "iso:country":"GB",
    "sg:address":"8 Flemish Field",
    "sg:city":"Chertsey",
    "sg:classifiers":[
        {
            "category":"Building & Trades",
            "subcategory":"Construction",
            "type":"Services"
        }
    ],
    "sg:postcode":"KT16 8EQ",
    "sg:province":"Surrey",
    "sg:tags":[
        "decorator",
        "painter"
    ],
    "wof:name":"Chertsey Decor",
    "wof:placetype":"venue"
},
  "geometry": {"coordinates":[-0.501323,51.389339],"type":"Point"}
}