{
  "type": "Feature",
  "properties": {
    "addr:full":"Doncaster Road Scunthorpe Lincolnshire DN15 7DF",
    "addr:postcode":"dn15 7df",
    "addr:street":"Doncaster Road",
    "iso:country":"GB",
    "sg:address":"Doncaster Road",
    "sg:city":"Scunthorpe",
    "sg:classifiers":[
        {
            "category":"Education",
            "subcategory":"School",
            "type":"Public Place"
        },
        {
            "category":"Government",
            "subcategory":"Office",
            "type":"Public Place"
        }
    ],
    "sg:phone":"+44 1724 842447",
    "sg:postcode":"DN15 7DF",
    "sg:province":"Lincolnshire",
    "sg:tags":[
        "local",
        "authority"
    ],
    "wof:name":"High Ridge School Specialist Sports College",
    "wof:placetype":"venue"
},
  "geometry": {"coordinates":[-0.6547340155,53.5909309387],"type":"Point"}
}