{
  "type": "Feature",
  "properties": {
    "iso:country":"GB",
    "sg:address":"Spring Mill, Earby",
    "sg:city":"Barnoldswick",
    "sg:classifiers":[
        {
            "category":"Travel",
            "subcategory":"Hotels & Motels",
            "type":"Entertainment"
        }
    ],
    "sg:phone":"+44 1282 844555",
    "sg:postcode":"BB18 6RN",
    "sg:province":"Lancashire",
    "sg:tags":[
        "self",
        "catering"
    ],
    "wof:name":"Country Holidays Ltd",
    "wof:placetype":"venue"
},
  "geometry": {"coordinates":[-2.146198988,53.9144859314],"type":"Point"}
}