{
  "type": "Feature",
  "properties": {
    "addr:full":"Unit 1a, Dewhurst Row, Bamber Bridge Preston Lancashire PR5 6BB",
    "addr:housenumber":"unit 1a",
    "addr:postcode":"pr5 6bb",
    "addr:street":"Dewhurst Row",
    "iso:country":"GB",
    "sg:address":"Unit 1a, Dewhurst Row, Bamber Bridge",
    "sg:city":"Preston",
    "sg:classifiers":[
        {
            "category":"Shopping",
            "subcategory":"Optician",
            "type":"Retail Goods"
        }
    ],
    "sg:phone":"+44 1772 312213",
    "sg:postcode":"PR5 6BB",
    "sg:province":"Lancashire",
    "wof:name":"The Spectacle Factory Ltd.",
    "wof:placetype":"venue"
},
  "geometry": {"coordinates":[-2.671749,53.722801],"type":"Point"}
}