{
  "type": "Feature",
  "properties": {
    "addr:full":"28 Carleton Glen Pontefract North Yorkshire WF8 2RT",
    "addr:housenumber":"28",
    "addr:postcode":"wf8 2rt",
    "addr:street":"Carleton Glen Pontefract",
    "iso:country":"GB",
    "sg:address":"28 Carleton Glen",
    "sg:city":"Pontefract",
    "sg:classifiers":[
        {
            "category":"Retail",
            "subcategory":"Storage",
            "type":"Services"
        }
    ],
    "sg:phone":"+44 1977 602744",
    "sg:postcode":"WF8 2RT",
    "sg:province":"North Yorkshire",
    "sg:tags":[
        "household",
        "removal"
    ],
    "wof:name":"C & J Transport",
    "wof:placetype":"venue"
},
  "geometry": {"coordinates":[-1.3084000349,53.6848068237],"type":"Point"}
}