{
  "type": "Feature",
  "properties": {
    "addr:full":"3 Alexandra Gardens Ventnor Isle of Wight PO38 1EE",
    "addr:housenumber":"3",
    "addr:postcode":"po38 1ee",
    "addr:street":"Alexandra Gardens",
    "iso:country":"GB",
    "sg:address":"3 Alexandra Gardens",
    "sg:city":"Ventnor",
    "sg:classifiers":[
        {
            "category":"Travel",
            "subcategory":"Hotels & Motels",
            "type":"Entertainment"
        }
    ],
    "sg:postcode":"PO38 1EE",
    "sg:province":"Isle of Wight",
    "sg:tags":[
        "house",
        "guest"
    ],
    "wof:name":"Bermuda Guest House",
    "wof:placetype":"venue"
},
  "geometry": {"coordinates":[-1.204144,50.593964],"type":"Point"}
}