{
  "type": "Feature",
  "properties": {
    "addr:full":"38 Arno Vale Road, Woodthorpe Nottingham Nottinghamshire NG5 4JJ",
    "addr:housenumber":"38",
    "addr:postcode":"ng5 4jj",
    "addr:street":"Arno Vale Road",
    "iso:country":"GB",
    "sg:address":"38 Arno Vale Road, Woodthorpe",
    "sg:city":"Nottingham",
    "sg:classifiers":[
        {
            "category":"Organizations",
            "subcategory":"Non-profit Organization",
            "type":"Services"
        }
    ],
    "sg:phone":"+44 115 926 4701",
    "sg:postcode":"NG5 4JJ",
    "sg:province":"Nottinghamshire",
    "sg:tags":[
        "organisation",
        "voluntary",
        "charity"
    ],
    "wof:name":"The Compassionate Friends",
    "wof:placetype":"venue"
},
  "geometry": {"coordinates":[-1.1255600452,52.9931678772],"type":"Point"}
}