{
  "type": "Feature",
  "properties": {
    "addr:full":"The Old School House, 9 Ellison Street, Wolstanton Newcastle Staffordshire ST5 0BL",
    "addr:housenumber":"9",
    "addr:postcode":"st5 0bl",
    "addr:street":"Ellison Street",
    "iso:country":"GB",
    "sg:address":"The Old School House, 9 Ellison Street, Wolstanton",
    "sg:city":"Newcastle",
    "sg:classifiers":[
        {
            "category":"Education",
            "subcategory":"Preschool",
            "type":"Public Place"
        }
    ],
    "sg:phone":"+44 1782 619378",
    "sg:postcode":"ST5 0BL",
    "sg:province":"Staffordshire",
    "sg:tags":[
        "pre-school",
        "playgroups"
    ],
    "wof:name":"Wolstanton Kindergarten",
    "wof:placetype":"venue"
},
  "geometry": {"coordinates":[-2.216561079,53.0322799683],"type":"Point"}
}