{
  "type": "Feature",
  "properties": {
    "iso:country":"GB",
    "sg:address":"251 Main Road, Glascote",
    "sg:city":"Tamworth",
    "sg:classifiers":[
        {
            "category":"Food & Beverages",
            "subcategory":"Liquor & Beverages",
            "type":"Retail Goods"
        },
        {
            "category":"Food & Beverages",
            "subcategory":"Fruits & Vegetables",
            "type":"Retail Goods"
        }
    ],
    "sg:phone":"+44 1827 62525",
    "sg:postcode":"B77 2AU",
    "sg:province":"Staffordshire",
    "sg:tags":[
        "beer",
        "wine",
        "greengrocer",
        "spirit"
    ],
    "wof:name":"Tamworth Co-Operative Society Ltd",
    "wof:placetype":"venue"
},
  "geometry": {"coordinates":[-1.661954,52.624771],"type":"Point"}
}