{
  "type": "Feature",
  "properties": {
    "addr:full":"10 Churchfield Court Nottingham Nottinghamshire NG5 9JL",
    "addr:housenumber":"10",
    "addr:postcode":"ng5 9jl",
    "addr:street":"Churchfield Court",
    "iso:country":"GB",
    "sg:address":"10 Churchfield Court",
    "sg:city":"Nottingham",
    "sg:classifiers":[
        {
            "category":"Professional",
            "subcategory":"Engineering",
            "type":"Services"
        }
    ],
    "sg:phone":"+44 115 993 1331",
    "sg:postcode":"NG5 9JL",
    "sg:province":"Nottinghamshire",
    "sg:tags":[
        "precision",
        "engineer"
    ],
    "wof:name":"Sehmi Engs and Fabricators",
    "wof:placetype":"venue"
},
  "geometry": {"coordinates":[-1.159479022,53.0097007751],"type":"Point"}
}