{
  "type": "Feature",
  "properties": {
    "iso:country":"GB",
    "sg:address":"3 Normandy Close",
    "sg:city":"Lymington",
    "sg:classifiers":[
        {
            "category":"Building & Trades",
            "subcategory":"Construction",
            "type":"Services"
        }
    ],
    "sg:phone":"+44 1590 682762",
    "sg:postcode":"SO41 6EF",
    "sg:province":"Hampshire",
    "sg:tags":[
        "builder"
    ],
    "wof:name":"Don A Etheridge",
    "wof:placetype":"venue"
},
  "geometry": {"coordinates":[-1.612977,50.787586],"type":"Point"}
}