{
  "type": "Feature",
  "properties": {
    "addr:full":"88 Giillespie Rd, Edmonton London Greater London N5 1LN",
    "addr:housenumber":"88",
    "addr:postcode":"n5 1ln",
    "addr:street":"Giillespie Rd",
    "iso:country":"GB",
    "sg:address":"88 Giillespie Rd, Edmonton",
    "sg:city":"London",
    "sg:classifiers":[
        {
            "category":"Communications",
            "type":"Services"
        }
    ],
    "sg:postcode":"N5 1LN",
    "sg:province":"Greater London",
    "sg:tags":[
        "tv",
        "video",
        "radio"
    ],
    "wof:name":"Universal Satellites",
    "wof:placetype":"venue"
},
  "geometry": {"coordinates":[-0.1023700014,51.5595779419],"type":"Point"}
}