{
  "type": "Feature",
  "properties": {
    "iso:country":"GB",
    "sg:address":"Po Box 32, Rose Cottage, Penalt",
    "sg:city":"Monmouth",
    "sg:classifiers":[
        {
            "category":"Communications",
            "type":"Services"
        }
    ],
    "sg:phone":"+44 1600 869090",
    "sg:postcode":"NP25 4RY",
    "sg:province":"Gloucestershire",
    "sg:tags":[
        "telecommunication"
    ],
    "wof:name":"Gemcom Ltd",
    "wof:placetype":"venue"
},
  "geometry": {"coordinates":[-2.69241,51.769249],"type":"Point"}
}