{
  "type": "Feature",
  "properties": {
    "iso:country":"GB",
    "sg:address":"135 Castle Road",
    "sg:city":"Bedford",
    "sg:classifiers":[
        {
            "category":"Shopping",
            "subcategory":"News",
            "type":"Retail Goods"
        },
        {
            "category":"Government",
            "subcategory":"Post Office",
            "type":"Public Place"
        }
    ],
    "sg:phone":"+44 1234 353048",
    "sg:postcode":"MK40 3RF",
    "sg:province":"Bedfordshire",
    "sg:tags":[
        "newsagent"
    ],
    "wof:name":"Pembroke Street Post Office",
    "wof:placetype":"venue"
},
  "geometry": {"coordinates":[-0.4528859854,52.1371421814],"type":"Point"}
}