{
  "type": "Feature",
  "properties": {
    "iso:country":"GB",
    "sg:address":"15 Honeys Green Precinct",
    "sg:city":"Liverpool",
    "sg:classifiers":[
        {
            "category":"Sports & Exercise",
            "subcategory":"Gym",
            "type":"Entertainment"
        }
    ],
    "sg:phone":"+44 151 280 4664",
    "sg:postcode":"L12 9JH",
    "sg:province":"Merseyside",
    "sg:tags":[
        "fitness",
        "health",
        "centre"
    ],
    "wof:name":"Bulldog Gym The",
    "wof:placetype":"venue"
},
  "geometry": {"coordinates":[-2.895323,53.421917],"type":"Point"}
}