{
  "type": "Feature",
  "properties": {
    "iso:country":"GB",
    "sg:address":"Southampton Road",
    "sg:city":"Salisbury",
    "sg:classifiers":[
        {
            "category":"Autos & Motor Vehicles",
            "subcategory":"Fuel & Gas Station",
            "type":"Retail Goods"
        }
    ],
    "sg:phone":"+44 1722 333729",
    "sg:postcode":"SP1 2LL",
    "sg:province":"Wiltshire",
    "sg:tags":[
        "hr",
        "petrol"
    ],
    "wof:name":"New Sarum Service Station",
    "wof:placetype":"venue"
},
  "geometry": {"coordinates":[-1.77758,51.061256],"type":"Point"}
}