{
  "type": "Feature",
  "properties": {
    "addr:full":"32 Sotherton Road Norwich Norfolk NR4 7DB",
    "addr:housenumber":"32",
    "addr:postcode":"nr4 7db",
    "addr:street":"Sotherton Road Norwich Norfolk",
    "iso:country":"GB",
    "sg:address":"32 Sotherton Road",
    "sg:city":"Norwich",
    "sg:classifiers":[
        {
            "category":"Professional",
            "type":"Services"
        }
    ],
    "sg:phone":"+44 1603 250981",
    "sg:postcode":"NR4 7DB",
    "sg:province":"Norfolk",
    "sg:tags":[
        "entertainer"
    ],
    "sg:website":"http://www.misterfied.com",
    "wof:name":"Mister Fied",
    "wof:placetype":"venue"
},
  "geometry": {"coordinates":[1.260198,52.618351],"type":"Point"}
}