{
  "type": "Feature",
  "properties": {
    "addr:full":"69 Westdown Road Plymouth Devon PL2 3HG",
    "addr:housenumber":"69",
    "addr:postcode":"pl2 3hg",
    "addr:street":"Westdown Road",
    "iso:country":"GB",
    "sg:address":"69 Westdown Road",
    "sg:city":"Plymouth",
    "sg:classifiers":[
        {
            "category":"Professional",
            "subcategory":"Management & Consulting",
            "type":"Services"
        }
    ],
    "sg:postcode":"PL2 3HG",
    "sg:province":"Devon",
    "sg:tags":[
        "consultant",
        "business"
    ],
    "wof:name":"Plansource Ltd",
    "wof:placetype":"venue"
},
  "geometry": {"coordinates":[-4.1607460976,50.3909378052],"type":"Point"}
}