{
  "type": "Feature",
  "properties": {
    "addr:full":"St Asaph Road, Trefnant Denbigh Conwy LL16 5UD",
    "addr:postcode":"ll16 5ud",
    "addr:street":"St Asaph Road",
    "iso:country":"GB",
    "sg:address":"St Asaph Road, Trefnant",
    "sg:city":"Denbigh",
    "sg:classifiers":[
        {
            "category":"Travel",
            "subcategory":"Hotels & Motels",
            "type":"Entertainment"
        }
    ],
    "sg:postcode":"LL16 5UD",
    "sg:province":"Conwy",
    "wof:name":"BRYN GLAS HOTEL",
    "wof:placetype":"venue"
},
  "geometry": {"coordinates":[-3.4228138924,53.2254142761],"type":"Point"}
}