{
  "type": "Feature",
  "properties": {
    "iso:country":"GB",
    "sg:address":"Tilstock Lodge, Tilstock",
    "sg:city":"Whitchurch",
    "sg:classifiers":[
        {
            "category":"Building & Trades",
            "subcategory":"Equipment Rental",
            "type":"Services"
        }
    ],
    "sg:phone":"+44 1948 880345",
    "sg:postcode":"SY13 3JW",
    "sg:province":"Cheshire",
    "sg:tags":[
        "plant",
        "machinery"
    ],
    "wof:name":"Tilstock Tractor Hire",
    "wof:placetype":"venue"
},
  "geometry": {"coordinates":[-2.68313694,52.9344940186],"type":"Point"}
}