{
  "type": "Feature",
  "properties": {
    "iso:country":"GB",
    "sg:address":"Celyn Mawr",
    "sg:city":"Oswestry",
    "sg:classifiers":[
        {
            "category":"Farming",
            "subcategory":"Livestock Farm",
            "type":"Manufacturing & Wholesale Goods"
        },
        {
            "category":"Farming",
            "subcategory":"Farm",
            "type":"Manufacturing & Wholesale Goods"
        }
    ],
    "sg:phone":"+44 1691 870666",
    "sg:postcode":"SY10 0NN",
    "sg:province":"Shropshire",
    "sg:tags":[
        "mixed",
        "crop",
        "others"
    ],
    "wof:name":"Thomas H G Davies",
    "wof:placetype":"venue"
},
  "geometry": {"coordinates":[-3.3486070633,52.8142967224],"type":"Point"}
}