{
  "type": "Feature",
  "properties": {
    "iso:country":"GB",
    "sg:address":"121 Moorgate",
    "sg:city":"Retford",
    "sg:classifiers":[
        {
            "category":"Education",
            "subcategory":"Special Training",
            "type":"Public Place"
        }
    ],
    "sg:phone":"+44 1777 709993",
    "sg:postcode":"DN22 6RS",
    "sg:province":"Nottinghamshire",
    "sg:tags":[
        "product",
        "centre"
    ],
    "wof:name":"Medicaid Training",
    "wof:placetype":"venue"
},
  "geometry": {"coordinates":[-0.9368739724,53.3278503418],"type":"Point"}
}