{
  "type": "Feature",
  "properties": {
    "addr:full":"Unit 6 Lion Works, Palatine Street, Denton Manchester Greater Manchester M34 3LY",
    "addr:housenumber":"unit 6;works",
    "addr:postcode":"m34 3ly",
    "addr:street":"Lion;Palatine Street",
    "iso:country":"GB",
    "sg:address":"Unit 6 Lion Works, Palatine Street, Denton",
    "sg:city":"Manchester",
    "sg:classifiers":[
        {
            "category":"Shopping",
            "subcategory":"Used Merchandise",
            "type":"Retail Goods"
        }
    ],
    "sg:phone":"+44 7968 651972",
    "sg:postcode":"M34 3LY",
    "sg:province":"Greater Manchester",
    "sg:tags":[
        "furniture"
    ],
    "wof:name":"Mike's Furniture",
    "wof:placetype":"venue"
},
  "geometry": {"coordinates":[-2.1165299416,53.460018158],"type":"Point"}
}