{
  "type": "Feature",
  "properties": {
    "iso:country":"GB",
    "sg:address":"Psychology Department, Ashley House, Hatherton Road",
    "sg:city":"Walsall",
    "sg:classifiers":[
        {
            "category":"Health Services",
            "subcategory":"Health Practitioner",
            "type":"Services"
        }
    ],
    "sg:phone":"+44 1922 858450",
    "sg:postcode":"WS1 1XS",
    "sg:province":"West Midlands",
    "sg:tags":[
        "psychologist"
    ],
    "wof:name":"Walsall Community Health Trust",
    "wof:placetype":"venue"
},
  "geometry": {"coordinates":[-1.9824969769,52.5856971741],"type":"Point"}
}