{
  "type": "Feature",
  "properties": {
    "iso:country":"GB",
    "sg:address":"53 Midland Road",
    "sg:city":"Walsall",
    "sg:classifiers":[
        {
            "category":"Wholesale",
            "subcategory":"Scrap",
            "type":"Manufacturing & Wholesale Goods"
        }
    ],
    "sg:phone":"+44 1922 632261",
    "sg:postcode":"WS1 3QQ",
    "sg:province":"West Midlands",
    "sg:tags":[
        "breaker",
        "dismantlers"
    ],
    "wof:name":"Just Renault",
    "wof:placetype":"venue"
},
  "geometry": {"coordinates":[-1.9844419956,52.5824737549],"type":"Point"}
}