{
  "type": "Feature",
  "properties": {
    "addr:full":"63 Queen Street Maidenhead Berkshire SL6 1LT",
    "addr:housenumber":"63",
    "addr:postcode":"sl6 1lt",
    "addr:street":"Queen Street",
    "iso:country":"GB",
    "sg:address":"63 Queen Street",
    "sg:city":"Maidenhead",
    "sg:classifiers":[
        {
            "category":"Shopping",
            "subcategory":"Musical Instruments",
            "type":"Retail Goods"
        },
        {
            "category":"Education",
            "subcategory":"Music School",
            "type":"Public Place"
        }
    ],
    "sg:postcode":"SL6 1LT",
    "sg:province":"Berkshire",
    "sg:tags":[
        "sheet",
        "teacher"
    ],
    "wof:name":"Music Machine",
    "wof:placetype":"venue"
},
  "geometry": {"coordinates":[-0.7201529741,51.5208473206],"type":"Point"}
}