{
  "type": "Feature",
  "properties": {
    "addr:full":"Unit 8, Crossfield Road Industrial Estate Lichfield Staffordshire WS13 6RJ",
    "addr:housenumber":"unit 8",
    "addr:postcode":"ws13 6rj",
    "addr:street":"Crossfield Road Industrial Estate",
    "iso:country":"GB",
    "sg:address":"Unit 8, Crossfield Road Industrial Estate",
    "sg:city":"Lichfield",
    "sg:classifiers":[
        {
            "category":"Retail",
            "subcategory":"Auto Repair",
            "type":"Services"
        }
    ],
    "sg:phone":"+44 1543 411412",
    "sg:postcode":"WS13 6RJ",
    "sg:province":"Staffordshire",
    "sg:tags":[
        "modification",
        "garage"
    ],
    "wof:name":"Mackenzies Volkswagen Specialists",
    "wof:placetype":"venue"
},
  "geometry": {"coordinates":[-1.803779,52.687031],"type":"Point"}
}