{
  "type": "Feature",
  "properties": {
    "addr:full":"Buckhurst Lane Wadhurst East Sussex TN5 6JY",
    "addr:postcode":"tn5 6jy",
    "addr:street":"Buckhurst Lane",
    "iso:country":"GB",
    "sg:address":"Buckhurst Lane",
    "sg:city":"Wadhurst",
    "sg:classifiers":[
        {
            "category":"Travel",
            "subcategory":"Hotels & Motels",
            "type":"Entertainment"
        }
    ],
    "sg:postcode":"TN5 6JY",
    "sg:province":"East Sussex",
    "wof:name":"Buckhurst Place Hotel",
    "wof:placetype":"venue"
},
  "geometry": {"coordinates":[0.293904,51.060192],"type":"Point"}
}