{
  "type": "Feature",
  "properties": {
    "addr:full":"Prior Ho, 6 Tilbury Pl Brighton East Sussex BN2 2GY",
    "addr:housenumber":"6",
    "addr:postcode":"bn2 2gy",
    "addr:street":"Tilbury Pl",
    "iso:country":"GB",
    "sg:address":"Prior Ho, 6 Tilbury Pl",
    "sg:city":"Brighton",
    "sg:classifiers":[
        {
            "category":"Organizations",
            "subcategory":"Non-profit Organization",
            "type":"Services"
        }
    ],
    "sg:phone":"+44 1273 671213",
    "sg:postcode":"BN2 2GY",
    "sg:province":"East Sussex",
    "sg:tags":[
        "organisation",
        "voluntary",
        "charity"
    ],
    "wof:name":"Family's Project",
    "wof:placetype":"venue"
},
  "geometry": {"coordinates":[-0.134491,50.828217],"type":"Point"}
}