{
  "type": "Feature",
  "properties": {
    "iso:country":"GB",
    "sg:address":"Booth Ho, 1 Booth Lane North",
    "sg:city":"Northampton",
    "sg:classifiers":[
        {
            "category":"Building & Trades",
            "subcategory":"Plumbing",
            "type":"Services"
        }
    ],
    "sg:phone":"+44 1604 642274",
    "sg:postcode":"NN3 6JE",
    "sg:province":"Northamptonshire",
    "sg:tags":[
        "drain",
        "clearance",
        "sewer"
    ],
    "wof:name":"Sewer Renovations Systems Ltd",
    "wof:placetype":"venue"
},
  "geometry": {"coordinates":[-0.8530200124,52.2713813782],"type":"Point"}
}