{
  "type": "Feature",
  "properties": {
    "addr:full":"A19 Wellfield House Bangor Gwynedd LL57 1ER",
    "addr:postcode":"ll57 1er",
    "iso:country":"GB",
    "sg:address":"A19 Wellfield House",
    "sg:city":"Bangor",
    "sg:classifiers":[
        {
            "category":"Shopping",
            "subcategory":"Shoes",
            "type":"Retail Goods"
        }
    ],
    "sg:phone":"+44 1248 352383",
    "sg:postcode":"LL57 1ER",
    "sg:province":"Gwynedd",
    "wof:name":"Timpson Shoe Repairs",
    "wof:placetype":"venue"
},
  "geometry": {"coordinates":[-4.1260638237,53.2295951843],"type":"Point"}
}