{
  "type": "Feature",
  "properties": {
    "addr:full":"70 Laindon Road Billericay Essex CM12 9LD",
    "addr:housenumber":"70",
    "addr:postcode":"cm12 9ld",
    "addr:street":"Laindon Road",
    "iso:country":"GB",
    "sg:address":"70 Laindon Road",
    "sg:city":"Billericay",
    "sg:classifiers":[
        {
            "category":"Real Estate",
            "subcategory":"Architect",
            "type":"Services"
        }
    ],
    "sg:phone":"+44 1277 632306",
    "sg:postcode":"CM12 9LD",
    "sg:province":"Essex",
    "wof:name":"L A P Architect & Interior Desginer Ltd.",
    "wof:placetype":"venue"
},
  "geometry": {"coordinates":[0.4162429869,51.6183662415],"type":"Point"}
}