{
  "type": "Feature",
  "properties": {
    "iso:country":"GB",
    "sg:address":"Conyer Quay",
    "sg:city":"Sittingbourne",
    "sg:classifiers":[
        {
            "category":"Bars & Pubs",
            "type":"Food & Drink"
        }
    ],
    "sg:phone":"+44 1795 520778",
    "sg:postcode":"ME9 9HR",
    "sg:province":"Kent",
    "sg:tags":[
        "pubs",
        "inn"
    ],
    "wof:name":"County Inns & Taverns Ltd.",
    "wof:placetype":"venue"
},
  "geometry": {"coordinates":[0.8151,51.348831],"type":"Point"}
}