{
  "type": "Feature",
  "properties": {
    "addr:full":"127 Berwyn Way Nuneaton Leicestershire CV10 8QW",
    "addr:housenumber":"127",
    "addr:postcode":"cv10 8qw",
    "addr:street":"Berwyn Way",
    "iso:country":"GB",
    "sg:address":"127 Berwyn Way",
    "sg:city":"Nuneaton",
    "sg:classifiers":[
        {
            "category":"Real Estate",
            "subcategory":"Surveying",
            "type":"Services"
        }
    ],
    "sg:postcode":"CV10 8QW",
    "sg:province":"Leicestershire",
    "sg:tags":[
        "surveyor",
        "quantity"
    ],
    "wof:name":"Jack Bridge",
    "wof:placetype":"venue"
},
  "geometry": {"coordinates":[-1.5112370253,52.5213432312],"type":"Point"}
}