{
  "type": "Feature",
  "properties": {
    "iso:country":"GB",
    "sg:address":"332 High Road, Leytonstone",
    "sg:city":"London",
    "sg:classifiers":[
        {
            "category":"Shopping",
            "subcategory":"Department Store",
            "type":"Retail Goods"
        },
        {
            "category":"Food & Beverages",
            "subcategory":"Groceries & Convenience Stores",
            "type":"Retail Goods"
        }
    ],
    "sg:phone":"+44 20 8519 8234",
    "sg:postcode":"E11 3HR",
    "sg:province":"Greater London",
    "wof:name":"A & S Grocers",
    "wof:placetype":"venue"
},
  "geometry": {"coordinates":[0.0063299998,51.5569190979],"type":"Point"}
}