{
  "type": "Feature",
  "properties": {
    "iso:country":"GB",
    "sg:address":"75-76 Dovecote Street",
    "sg:city":"Stockton-on-tees",
    "sg:classifiers":[
        {
            "category":"Communications",
            "subcategory":"Film & Video Production",
            "type":"Services"
        }
    ],
    "sg:phone":"+44 1642 606969",
    "sg:postcode":"TS18 1HA",
    "sg:province":"Durham",
    "sg:tags":[
        "recording",
        "studio"
    ],
    "wof:name":"Oblivion Music Ltd.",
    "wof:placetype":"venue"
},
  "geometry": {"coordinates":[-1.3179630041,54.5641899109],"type":"Point"}
}