{
  "type": "Feature",
  "properties": {
    "iso:country":"GB",
    "sg:address":"18 Glyn Vale, Bedminster",
    "sg:city":"Bristol",
    "sg:classifiers":[
        {
            "category":"Food & Beverages",
            "subcategory":"Liquor & Beverages",
            "type":"Retail Goods"
        }
    ],
    "sg:phone":"+44 117 963 1080",
    "sg:postcode":"BS3 5JG",
    "sg:province":"City of Bristol",
    "sg:tags":[
        "beer",
        "spirit",
        "wines"
    ],
    "wof:name":"Marsh's Off Licence",
    "wof:placetype":"venue"
},
  "geometry": {"coordinates":[-2.5886371136,51.432598114],"type":"Point"}
}