{
  "type": "Feature",
  "properties": {
    "addr:full":"54 Baker Street London Greater London W1U 7BU",
    "addr:housenumber":"54",
    "addr:postcode":"w1u 7bu",
    "addr:street":"Baker Street",
    "iso:country":"GB",
    "sg:address":"54 Baker Street",
    "sg:city":"London",
    "sg:classifiers":[
        {
            "category":"Banks & Credit Unions",
            "subcategory":"Financial Services",
            "type":"Services"
        }
    ],
    "sg:postcode":"W1U 7BU",
    "sg:province":"Greater London",
    "sg:tags":[
        "consultant"
    ],
    "wof:name":"Castlehaven Property Investments Ltd.",
    "wof:placetype":"venue"
},
  "geometry": {"coordinates":[-0.1559689939,51.518699646],"type":"Point"}
}