{
  "type": "Feature",
  "properties": {
    "iso:country":"GB",
    "sg:address":"37 East Castle Street",
    "sg:city":"London",
    "sg:classifiers":[
        {
            "category":"Shopping",
            "subcategory":"Clothing, Apparel, & Fashions",
            "type":"Retail Goods"
        }
    ],
    "sg:phone":"+44 20 7637 1242",
    "sg:postcode":"W1W 8DR",
    "sg:province":"Greater London",
    "sg:tags":[
        "clothing",
        "fabric"
    ],
    "wof:name":"Societe Cylsa London Ltd.",
    "wof:placetype":"venue"
},
  "geometry": {"coordinates":[-0.1392139941,51.5165672302],"type":"Point"}
}