{
  "type": "Feature",
  "properties": {
    "iso:country":"GB",
    "sg:address":"224 Dunsbury Way, Leigh Park",
    "sg:city":"Havant",
    "sg:classifiers":[
        {
            "category":"Retail",
            "subcategory":"Funeral Services",
            "type":"Services"
        }
    ],
    "sg:postcode":"PO9 5BQ",
    "sg:province":"Hampshire",
    "wof:name":"Co-Operative Funeral Directors",
    "wof:placetype":"venue"
},
  "geometry": {"coordinates":[-0.988157,50.868938],"type":"Point"}
}