{
  "type": "Feature",
  "properties": {
    "iso:country":"GB",
    "sg:address":"19 Rookery Street, Wednesfield",
    "sg:city":"Wolverhampton",
    "sg:classifiers":[
        {
            "category":"Autos & Motor Vehicles",
            "subcategory":"Automobile Sales",
            "type":"Retail Goods"
        }
    ],
    "sg:phone":"+44 1902 864524",
    "sg:postcode":"WV11 1UN",
    "sg:province":"Staffordshire",
    "sg:tags":[
        "car"
    ],
    "wof:name":"Redhead Motors",
    "wof:placetype":"venue"
},
  "geometry": {"coordinates":[-2.085986,52.598774],"type":"Point"}
}