{
  "type": "Feature",
  "properties": {
    "iso:country":"GB",
    "sg:address":"Beare, Broadclyst",
    "sg:city":"Exeter",
    "sg:classifiers":[
        {
            "category":"Utilities",
            "subcategory":"Fuel Oil & Lpg",
            "type":"Services"
        }
    ],
    "sg:phone":"+44 1392 881429",
    "sg:postcode":"EX5 3JX",
    "sg:province":"Devon",
    "wof:name":"Watson Petroleum Ltd.",
    "wof:placetype":"venue"
},
  "geometry": {"coordinates":[-3.442204,50.760498],"type":"Point"}
}