{
  "type": "Feature",
  "properties": {
    "addr:full":"18 Old Gate Lane, Thrybergh Rotherham South Yorkshire S65 4JT",
    "addr:housenumber":"18",
    "addr:postcode":"s65 4jt",
    "addr:street":"Old Gate Lane",
    "iso:country":"GB",
    "sg:address":"18 Old Gate Lane, Thrybergh",
    "sg:city":"Rotherham",
    "sg:classifiers":[
        {
            "category":"Personal",
            "subcategory":"Beauty Salon",
            "type":"Services"
        }
    ],
    "sg:phone":"+44 1709 850349",
    "sg:postcode":"S65 4JT",
    "sg:province":"South Yorkshire",
    "sg:tags":[
        "unisex",
        "hairdresser"
    ],
    "wof:name":"Leslie's",
    "wof:placetype":"venue"
},
  "geometry": {"coordinates":[-1.3014290333,53.446231842],"type":"Point"}
}