{
  "type": "Feature",
  "properties": {
    "addr:full":"Unit 3b West Point, 39-40 Warple Way London Greater London W3 0RG",
    "addr:housenumber":"unit 3b",
    "addr:postcode":"39-40;w3 0rg",
    "addr:street":"West;Warple Way",
    "iso:country":"GB",
    "sg:address":"Unit 3b West Point, 39-40 Warple Way",
    "sg:city":"London",
    "sg:classifiers":[
        {
            "category":"Real Estate",
            "subcategory":"Architect",
            "type":"Services"
        }
    ],
    "sg:postcode":"W3 0RG",
    "sg:province":"Greater London",
    "wof:name":"Bienkowski,Jan,",
    "wof:placetype":"venue"
},
  "geometry": {"coordinates":[-0.2554799914,51.5043106079],"type":"Point"}
}