{
  "type": "Feature",
  "properties": {
    "iso:country":"GB",
    "sg:address":"Ashley Close, Wrenthorpe",
    "sg:city":"Wakefield",
    "sg:classifiers":[
        {
            "category":"Shopping",
            "subcategory":"Party Supplies",
            "type":"Retail Goods"
        }
    ],
    "sg:phone":"+44 1924 376209",
    "sg:postcode":"WF2 0JU",
    "sg:province":"West Yorkshire",
    "sg:tags":[
        "inflatables",
        "bouncy",
        "castle"
    ],
    "wof:name":"Bounce Away Bouncy Castles",
    "wof:placetype":"venue"
},
  "geometry": {"coordinates":[-1.525762,53.698265],"type":"Point"}
}