{
  "type": "Feature",
  "properties": {
    "iso:country":"GB",
    "sg:address":"128 Elm Gro",
    "sg:city":"Southsea",
    "sg:classifiers":[
        {
            "category":"Bars & Pubs",
            "type":"Food & Drink"
        }
    ],
    "sg:phone":"+44 23 9282 4295",
    "sg:postcode":"PO5 1LR",
    "sg:province":"Hampshire",
    "sg:tags":[
        "pubs",
        "inn"
    ],
    "wof:name":"The Elms",
    "wof:placetype":"venue"
},
  "geometry": {"coordinates":[-1.0840369463,50.78931427],"type":"Point"}
}