{
  "type": "Feature",
  "properties": {
    "iso:country":"GB",
    "sg:address":"Chacombe Lodge Farm, Chacombe",
    "sg:city":"Banbury",
    "sg:classifiers":[
        {
            "category":"Wholesale",
            "subcategory":"Non-durable Goods",
            "type":"Manufacturing & Wholesale Goods"
        }
    ],
    "sg:phone":"+44 1295 710375",
    "sg:postcode":"OX17 2EP",
    "sg:province":"Northamptonshire",
    "sg:tags":[
        "carry",
        "cash"
    ],
    "wof:name":"Tustian,J,",
    "wof:placetype":"venue"
},
  "geometry": {"coordinates":[-1.283126,52.090832],"type":"Point"}
}