{
  "type": "Feature",
  "properties": {
    "iso:country":"GB",
    "sg:address":"Optimum Ho, P O Box 61",
    "sg:city":"Manchester",
    "sg:classifiers":[
        {
            "category":"Professional",
            "subcategory":"Management & Consulting",
            "type":"Services"
        }
    ],
    "sg:phone":"+44 161 339 0952",
    "sg:postcode":"M22 4XL",
    "sg:province":"Greater Manchester",
    "sg:tags":[
        "consultant",
        "training"
    ],
    "wof:name":"Optimum Training Consultancy",
    "wof:placetype":"venue"
},
  "geometry": {"coordinates":[-2.257139,53.396969],"type":"Point"}
}