{
  "type": "Feature",
  "properties": {
    "addr:full":"317 High St Cheltenham Gloucestershire GL50 3HW",
    "addr:housenumber":"317",
    "addr:postcode":"gl50 3hw",
    "addr:street":"High St",
    "iso:country":"GB",
    "sg:address":"317 High St",
    "sg:city":"Cheltenham",
    "sg:classifiers":[
        {
            "category":"Banks & Credit Unions",
            "subcategory":"Bureau De Change",
            "type":"Services"
        }
    ],
    "sg:phone":"+44 1242 226196",
    "sg:postcode":"GL50 3HW",
    "sg:province":"Gloucestershire",
    "sg:tags":[
        "town",
        "consultant",
        "planning"
    ],
    "wof:name":"Land Planning Associates",
    "wof:placetype":"venue"
},
  "geometry": {"coordinates":[-2.079243,51.903301],"type":"Point"}
}