{
  "type": "Feature",
  "properties": {
    "iso:country":"GB",
    "sg:address":"1 Moor View",
    "sg:city":"Truro",
    "sg:classifiers":[
        {
            "category":"Restaurant",
            "type":"Food & Drink"
        }
    ],
    "sg:phone":"+44 1726 883033",
    "sg:postcode":"TR2 4RT",
    "sg:province":"Cornwall",
    "sg:tags":[
        "chinese"
    ],
    "wof:name":"Eastern Promise Chinese Restaurant",
    "wof:placetype":"venue"
},
  "geometry": {"coordinates":[-4.946276,50.292767],"type":"Point"}
}