{
  "type": "Feature",
  "properties": {
    "addr:full":"Unit 2 Blackpole Trading Estate Worcester Worcestershire WR3 8SG",
    "addr:housenumber":"unit 2;estate",
    "addr:postcode":"wr3 8sg",
    "addr:street":"Trading",
    "iso:country":"GB",
    "sg:address":"Unit 2 Blackpole Trading Estate",
    "sg:city":"Worcester",
    "sg:classifiers":[
        {
            "category":"Shopping",
            "subcategory":"Pets & Pet Supplies",
            "type":"Retail Goods"
        }
    ],
    "sg:phone":"+44 1905 754250",
    "sg:postcode":"WR3 8SG",
    "sg:province":"Worcestershire",
    "wof:name":"Petsmart",
    "wof:placetype":"venue"
},
  "geometry": {"coordinates":[-2.199034,52.221554],"type":"Point"}
}