{
  "type": "Feature",
  "properties": {
    "iso:country":"GB",
    "sg:address":"138 Main Road, Elderslie",
    "sg:city":"Johnstone",
    "sg:classifiers":[
        {
            "category":"Retail",
            "subcategory":"Auto Repair",
            "type":"Services"
        }
    ],
    "sg:phone":"+44 1505 322261",
    "sg:postcode":"PA5 9AY",
    "sg:province":"Renfrewshire",
    "sg:tags":[
        "modification",
        "garage"
    ],
    "wof:name":"Arnold Clark Automobiles",
    "wof:placetype":"venue"
},
  "geometry": {"coordinates":[-4.48023,55.837734],"type":"Point"}
}