{
  "type": "Feature",
  "properties": {
    "iso:country":"GB",
    "sg:address":"Bromley Rd",
    "sg:city":"London",
    "sg:classifiers":[
        {
            "category":"Autos & Motor Vehicles",
            "subcategory":"Automobile Sales",
            "type":"Retail Goods"
        }
    ],
    "sg:postcode":"N17 0AR",
    "sg:province":"Greater London",
    "sg:tags":[
        "car"
    ],
    "wof:name":"Five Star Car Repairs",
    "wof:placetype":"venue"
},
  "geometry": {"coordinates":[-0.0654890016,51.6019935608],"type":"Point"}
}