{
  "type": "Feature",
  "properties": {
    "addr:full":"C C E Business Park, Windmill Lane, Denton Manchester Greater Manchester M34 3QS",
    "addr:postcode":"m34 3qs",
    "addr:street":"C C E Business Park Windmill Lane",
    "iso:country":"GB",
    "sg:address":"C C E Business Park, Windmill Lane, Denton",
    "sg:city":"Manchester",
    "sg:classifiers":[
        {
            "category":"Manufacturing",
            "subcategory":"Tools & Machinery",
            "type":"Manufacturing & Wholesale Goods"
        },
        {
            "category":"Home & Garden",
            "subcategory":"Hardware",
            "type":"Retail Goods"
        }
    ],
    "sg:phone":"+44 161 336 6334",
    "sg:postcode":"M34 3QS",
    "sg:province":"Greater Manchester",
    "sg:tags":[
        "machine",
        "equipment",
        "welding",
        "manufacturer"
    ],
    "wof:name":"Arco stud Welding Ltd.",
    "wof:placetype":"venue"
},
  "geometry": {"coordinates":[-2.248809,53.479622],"type":"Point"}
}