{
  "type": "Feature",
  "properties": {
    "addr:full":"Maydon Villa, Broadgate Boston Lincolnshire PE22 9DY",
    "addr:postcode":"pe22 9dy",
    "addr:street":"Broadgate",
    "iso:country":"GB",
    "sg:address":"Maydon Villa, Broadgate",
    "sg:city":"Boston",
    "sg:classifiers":[
        {
            "category":"Bus Charters",
            "type":"Transportation"
        }
    ],
    "sg:phone":"+44 1205 870633",
    "sg:postcode":"PE22 9DY",
    "sg:province":"Lincolnshire",
    "sg:tags":[
        "hire",
        "coach"
    ],
    "wof:name":"D & J Dickinson Coaches",
    "wof:placetype":"venue"
},
  "geometry": {"coordinates":[0.12808,53.055511],"type":"Point"}
}