{
  "type": "Feature",
  "properties": {
    "addr:full":"4 Bacon Hill Olney Buckinghamshire MK46 5QJ",
    "addr:housenumber":"4",
    "addr:postcode":"mk46 5qj",
    "addr:street":"Bacon Hill",
    "iso:country":"GB",
    "sg:address":"4 Bacon Hill",
    "sg:city":"Olney",
    "sg:classifiers":[
        {
            "category":"Professional",
            "subcategory":"Computer Services",
            "type":"Services"
        }
    ],
    "sg:postcode":"MK46 5QJ",
    "sg:province":"Buckinghamshire",
    "sg:tags":[
        "system",
        "software"
    ],
    "wof:name":"Visual Solutions U K Ltd.",
    "wof:placetype":"venue"
},
  "geometry": {"coordinates":[-0.713321,52.15464],"type":"Point"}
}