{
  "type": "Feature",
  "properties": {
    "iso:country":"GB",
    "sg:address":"40 Ash Road, Denton",
    "sg:city":"Manchester",
    "sg:classifiers":[
        {
            "category":"Freight",
            "type":"Transportation"
        }
    ],
    "sg:postcode":"M34 2NH",
    "sg:province":"Greater Manchester",
    "sg:tags":[
        "haulage",
        "road"
    ],
    "wof:name":"Tabois Transport Ltd",
    "wof:placetype":"venue"
},
  "geometry": {"coordinates":[-2.155841,53.454414],"type":"Point"}
}