{
  "type": "Feature",
  "properties": {
    "iso:country":"GB",
    "sg:address":"West Lodge Bartley Lodge, Cadnam",
    "sg:city":"Southampton",
    "sg:classifiers":[
        {
            "category":"Building & Trades",
            "subcategory":"Plumbing",
            "type":"Services"
        }
    ],
    "sg:phone":"+44 23 8081 3672",
    "sg:postcode":"SO40 2NR",
    "sg:province":"Hampshire",
    "sg:tags":[
        "merchant",
        "plumbers'"
    ],
    "wof:name":"M B Tools",
    "wof:placetype":"venue"
},
  "geometry": {"coordinates":[-1.5611,50.916615],"type":"Point"}
}