{
  "type": "Feature",
  "properties": {
    "iso:country":"GB",
    "sg:address":"6 Choumert Rd, Peckham",
    "sg:city":"Peckham",
    "sg:classifiers":[
        {
            "category":"Shopping",
            "subcategory":"Music",
            "type":"Retail Goods"
        }
    ],
    "sg:phone":"+44 20 7639 2475",
    "sg:postcode":"SE15 4SE",
    "sg:province":"Greater London",
    "sg:tags":[
        "record",
        "tape",
        "cd"
    ],
    "wof:name":"Jay Gees Records",
    "wof:placetype":"venue"
},
  "geometry": {"coordinates":[-0.0676899999,51.4683036804],"type":"Point"}
}