{
  "type": "Feature",
  "properties": {
    "addr:full":"76 Belville Street Greenock Inverclyde PA15 4SY",
    "addr:housenumber":"76",
    "addr:postcode":"pa15 4sy",
    "addr:street":"Belville Street Greenock",
    "iso:country":"GB",
    "sg:address":"76 Belville Street",
    "sg:city":"Greenock",
    "sg:classifiers":[
        {
            "category":"Food & Beverages",
            "subcategory":"Supermarket",
            "type":"Retail Goods"
        },
        {
            "category":"Shopping",
            "subcategory":"Discount & Variety Stores",
            "type":"Retail Goods"
        }
    ],
    "sg:phone":"+44 1475 721104",
    "sg:postcode":"PA15 4SY",
    "sg:province":"Inverclyde",
    "sg:tags":[
        "centre"
    ],
    "wof:name":"Naureen's Store",
    "wof:placetype":"venue"
},
  "geometry": {"coordinates":[-4.737179,55.942104],"type":"Point"}
}