{
  "type": "Feature",
  "properties": {
    "addr:full":"479 Wilmslow Road Manchester Greater Manchester M20 4AN",
    "addr:housenumber":"479",
    "addr:postcode":"m20 4an",
    "addr:street":"Wilmslow Road",
    "iso:country":"GB",
    "sg:address":"479 Wilmslow Road",
    "sg:city":"Manchester",
    "sg:classifiers":[
        {
            "category":"Shopping",
            "subcategory":"Department Store",
            "type":"Retail Goods"
        }
    ],
    "sg:postcode":"M20 4AN",
    "sg:province":"Greater Manchester",
    "wof:name":"Northern Sports",
    "wof:placetype":"venue"
},
  "geometry": {"coordinates":[-2.2283120155,53.4337272644],"type":"Point"}
}