{
  "type": "Feature",
  "properties": {
    "iso:country":"GB",
    "sg:address":"High Sunderland",
    "sg:city":"Galashiels",
    "sg:classifiers":[
        {
            "category":"Professional",
            "subcategory":"Computer Services",
            "type":"Services"
        }
    ],
    "sg:phone":"+44 1896 758991",
    "sg:postcode":"TD1 3PL",
    "sg:province":"Scottish Borders",
    "sg:tags":[
        "information"
    ],
    "wof:name":"Scottish Borders Studio",
    "wof:placetype":"venue"
},
  "geometry": {"coordinates":[-2.802979,55.612156],"type":"Point"}
}