{
  "type": "Feature",
  "properties": {
    "addr:full":"Cavendish Bridge Derby Derbyshire DE72 2HL",
    "addr:postcode":"de72 2hl",
    "iso:country":"GB",
    "sg:address":"Cavendish Bridge",
    "sg:city":"Derby",
    "sg:classifiers":[
        {
            "category":"Autos & Motor Vehicles",
            "subcategory":"Automobile Sales",
            "type":"Retail Goods"
        }
    ],
    "sg:phone":"+44 1332 799003",
    "sg:postcode":"DE72 2HL",
    "sg:province":"Derbyshire",
    "sg:tags":[
        "car"
    ],
    "wof:name":"Shardlow Landrover Centre",
    "wof:placetype":"venue"
},
  "geometry": {"coordinates":[-1.3402819633,52.87109375],"type":"Point"}
}