{
  "type": "Feature",
  "properties": {
    "addr:full":"479 Crewe Road, Wheelock Sandbach Cheshire CW11 3RT",
    "addr:housenumber":"479",
    "addr:postcode":"cw11 3rt",
    "addr:street":"Crewe Road",
    "iso:country":"GB",
    "sg:address":"479 Crewe Road, Wheelock",
    "sg:city":"Sandbach",
    "sg:classifiers":[
        {
            "category":"Professional",
            "subcategory":"Art Services",
            "type":"Services"
        }
    ],
    "sg:postcode":"CW11 3RT",
    "sg:province":"Cheshire",
    "sg:tags":[
        "picture",
        "restoration",
        "cleaning"
    ],
    "wof:name":"The Village Gallery",
    "wof:placetype":"venue"
},
  "geometry": {"coordinates":[-2.363648,53.142208],"type":"Point"}
}