{
  "type": "Feature",
  "properties": {
    "addr:full":"1 Church Street High Wycombe Buckinghamshire HP11 2DE",
    "addr:housenumber":"1",
    "addr:postcode":"hp11 2de",
    "addr:street":"Church Street",
    "iso:country":"GB",
    "sg:address":"1 Church Street",
    "sg:city":"High Wycombe",
    "sg:classifiers":[
        {
            "category":"Banks & Credit Unions",
            "subcategory":"Bank",
            "type":"Services"
        }
    ],
    "sg:phone":"+44 1494 446603",
    "sg:postcode":"HP11 2DE",
    "sg:province":"Buckinghamshire",
    "sg:tags":[
        "financial",
        "institution"
    ],
    "wof:name":"Cheltenham & Gloucester plc",
    "wof:placetype":"venue"
},
  "geometry": {"coordinates":[-0.751542,51.629623],"type":"Point"}
}