{
  "type": "Feature",
  "properties": {
    "addr:full":"Whalebone Lane North Romford Essex RM6 5QX",
    "addr:postcode":"rm6 5qx",
    "addr:street":"Whalebone Lane North",
    "iso:country":"GB",
    "sg:address":"Whalebone Lane North",
    "sg:city":"Romford",
    "sg:classifiers":[
        {
            "category":"Autos & Motor Vehicles",
            "subcategory":"Fuel & Gas Station",
            "type":"Retail Goods"
        }
    ],
    "sg:phone":"+44 20 8597 5999",
    "sg:postcode":"RM6 5QX",
    "sg:province":"Essex",
    "sg:tags":[
        "petrol",
        "filling"
    ],
    "wof:name":"Cranbrook Service Station",
    "wof:placetype":"venue"
},
  "geometry": {"coordinates":[0.141375,51.582134],"type":"Point"}
}