{
  "type": "Feature",
  "properties": {
    "addr:full":"Lawton Street, Stalybridge Hyde Cheshire SK14 2JT",
    "addr:postcode":"sk14 2jt",
    "addr:street":"Lawton Street",
    "iso:country":"GB",
    "sg:address":"Lawton Street, Stalybridge",
    "sg:city":"Hyde",
    "sg:classifiers":[
        {
            "category":"Freight",
            "type":"Transportation"
        }
    ],
    "sg:postcode":"SK14 2JT",
    "sg:province":"Cheshire",
    "sg:tags":[
        "haulage",
        "road"
    ],
    "wof:name":"McLaughlin Haulage Services",
    "wof:placetype":"venue"
},
  "geometry": {"coordinates":[-2.0808839798,53.4543113708],"type":"Point"}
}