{
  "type": "Feature",
  "properties": {
    "iso:country":"GB",
    "sg:address":"Queensgate Centre",
    "sg:city":"Peterborough",
    "sg:classifiers":[
        {
            "category":"Shopping",
            "subcategory":"Clothing, Apparel, & Fashions",
            "type":"Retail Goods"
        }
    ],
    "sg:phone":"+44 1733 346991",
    "sg:postcode":"PE1 1NN",
    "sg:province":"Cambridgeshire",
    "sg:tags":[
        "shop"
    ],
    "wof:name":"C & A",
    "wof:placetype":"venue"
},
  "geometry": {"coordinates":[-0.2465150058,52.5738983154],"type":"Point"}
}