{
  "type": "Feature",
  "properties": {
    "addr:full":"2 Catherine Place, Westminster London Greater London SW1E 6HF",
    "addr:housenumber":"2",
    "addr:postcode":"sw1e 6hf",
    "addr:street":"Catherine Place",
    "iso:country":"GB",
    "sg:address":"2 Catherine Place, Westminster",
    "sg:city":"London",
    "sg:classifiers":[
        {
            "category":"Professional",
            "subcategory":"Business Services",
            "type":"Services"
        }
    ],
    "sg:phone":"+44 20 7233 7900",
    "sg:postcode":"SW1E 6HF",
    "sg:province":"Greater London",
    "sg:tags":[
        "trade"
    ],
    "wof:name":"National Federation of Self Employed & Small Businesses Ltd.",
    "wof:placetype":"venue"
},
  "geometry": {"coordinates":[-0.1409070045,51.4987220764],"type":"Point"}
}