{
  "type": "Feature",
  "properties": {
    "iso:country":"GB",
    "sg:address":"249 Laird St",
    "sg:city":"Birkenhead",
    "sg:classifiers":[
        {
            "category":"Bars & Pubs",
            "type":"Food & Drink"
        }
    ],
    "sg:phone":"+44 151 652 7817",
    "sg:postcode":"L41 0AB",
    "sg:province":"Merseyside",
    "sg:tags":[
        "pubs",
        "inn"
    ],
    "wof:name":"North Star The",
    "wof:placetype":"venue"
},
  "geometry": {"coordinates":[-3.0525560379,53.3999519348],"type":"Point"}
}