{
  "type": "Feature",
  "properties": {
    "iso:country":"GB",
    "sg:address":"2 Central Avenue",
    "sg:city":"Ardrossan",
    "sg:classifiers":[
        {
            "category":"Food & Beverages",
            "subcategory":"Supermarket",
            "type":"Retail Goods"
        }
    ],
    "sg:phone":"+44 1294 463062",
    "sg:postcode":"KA22 7DX",
    "sg:province":"North Ayrshire",
    "wof:name":"Scottish Co-Op Food Stores",
    "wof:placetype":"venue"
},
  "geometry": {"coordinates":[-4.806246,55.650379],"type":"Point"}
}