{
  "type": "Feature",
  "properties": {
    "addr:full":"Southcroft, Inkerman Hill, Hazlemere High Wycombe Buckinghamshire HP15 7JH",
    "addr:postcode":"hp15 7jh",
    "addr:street":"Inkerman Hill",
    "iso:country":"GB",
    "sg:address":"Southcroft, Inkerman Hill, Hazlemere",
    "sg:city":"High Wycombe",
    "sg:classifiers":[
        {
            "category":"Retail",
            "subcategory":"Repair Shop",
            "type":"Services"
        }
    ],
    "sg:phone":"+44 1494 715540",
    "sg:postcode":"HP15 7JH",
    "sg:province":"Buckinghamshire",
    "sg:tags":[
        "radio",
        "television",
        "video"
    ],
    "wof:name":"Stag Rental Co",
    "wof:placetype":"venue"
},
  "geometry": {"coordinates":[-0.708729,51.651031],"type":"Point"}
}