{
  "type": "Feature",
  "properties": {
    "addr:full":"21 Walmer Avenue Bishop Auckland Durham DL14 6NW",
    "addr:housenumber":"21",
    "addr:postcode":"dl14 6nw",
    "addr:street":"Walmer Avenue",
    "iso:country":"GB",
    "sg:address":"21 Walmer Avenue",
    "sg:city":"Bishop Auckland",
    "sg:classifiers":[
        {
            "category":"Building & Trades",
            "subcategory":"Construction",
            "type":"Services"
        }
    ],
    "sg:phone":"+44 1388 450019",
    "sg:postcode":"DL14 6NW",
    "sg:province":"Durham",
    "sg:tags":[
        "builder"
    ],
    "wof:name":"Moffett & March",
    "wof:placetype":"venue"
},
  "geometry": {"coordinates":[-1.6822429895,54.6530227661],"type":"Point"}
}