{
  "type": "Feature",
  "properties": {
    "addr:full":"16 Riverside Shopping Centre, Southgate Sleaford Lincolnshire NG34 7PD",
    "addr:housenumber":"16",
    "addr:postcode":"ng34 7pd",
    "addr:street":"Riverside Shopping Centre Southgate Sleaford",
    "iso:country":"GB",
    "sg:address":"16 Riverside Shopping Centre, Southgate",
    "sg:city":"Sleaford",
    "sg:classifiers":[
        {
            "category":"Shopping",
            "subcategory":"Crafts & Fabrics",
            "type":"Retail Goods"
        }
    ],
    "sg:phone":"+44 1529 413143",
    "sg:postcode":"NG34 7PD",
    "sg:province":"Lincolnshire",
    "sg:tags":[
        "shop",
        "needlecraft",
        "wool",
        "retailer"
    ],
    "wof:name":"A & B Woolshop",
    "wof:placetype":"venue"
},
  "geometry": {"coordinates":[-0.412369,52.99736],"type":"Point"}
}