{
  "type": "Feature",
  "properties": {
    "iso:country":"GB",
    "sg:address":"Suite 28 Castle Circus House, 136 Union St",
    "sg:city":"Torquay",
    "sg:classifiers":[
        {
            "category":"Professional",
            "subcategory":"Lawyer & Legal Services",
            "type":"Services"
        }
    ],
    "sg:phone":"+44 1803 299956",
    "sg:postcode":"TQ2 5QB",
    "sg:province":"Devon",
    "wof:name":"The National Association of Paralegals",
    "wof:placetype":"venue"
},
  "geometry": {"coordinates":[-3.531751,50.46793],"type":"Point"}
}