{
  "type": "Feature",
  "properties": {
    "iso:country":"GB",
    "sg:address":"Stratton Way",
    "sg:city":"Abingdon",
    "sg:classifiers":[
        {
            "category":"Community Center",
            "subcategory":"Youth",
            "type":"Public Place"
        }
    ],
    "sg:phone":"+44 1235 521469",
    "sg:postcode":"OX14 3RG",
    "sg:province":"Oxfordshire",
    "sg:tags":[
        "organisation",
        "centre"
    ],
    "wof:name":"Abingdon Youth & Community Centre",
    "wof:placetype":"venue"
},
  "geometry": {"coordinates":[-1.2824139595,51.6726722717],"type":"Point"}
}