{
  "type": "Feature",
  "properties": {
    "addr:full":"Unit 11, Prospect Business Park, Langston Road Loughton Essex IG10 3TR",
    "addr:housenumber":"unit 11",
    "addr:postcode":"ig10 3tr",
    "addr:street":"Prospect Business Park Langston Road",
    "iso:country":"GB",
    "sg:address":"Unit 11, Prospect Business Park, Langston Road",
    "sg:city":"Loughton",
    "sg:classifiers":[
        {
            "category":"Organizations",
            "subcategory":"Non-profit Organization",
            "type":"Services"
        }
    ],
    "sg:phone":"+44 20 8502 3504",
    "sg:postcode":"IG10 3TR",
    "sg:province":"Essex",
    "sg:tags":[
        "charitable",
        "organisation",
        "voluntary",
        "charity"
    ],
    "wof:name":"The South American Mission Society",
    "wof:placetype":"venue"
},
  "geometry": {"coordinates":[0.089624,51.645],"type":"Point"}
}