{
  "type": "Feature",
  "properties": {
    "iso:country":"GB",
    "sg:address":"57 Liberty Avenue",
    "sg:city":"London",
    "sg:classifiers":[
        {
            "category":"Shopping",
            "subcategory":"News",
            "type":"Retail Goods"
        }
    ],
    "sg:phone":"+44 20 8646 7360",
    "sg:postcode":"SW19 2QS",
    "sg:province":"Greater London",
    "sg:tags":[
        "newsagent"
    ],
    "wof:name":"Liberty Enterprises",
    "wof:placetype":"venue"
},
  "geometry": {"coordinates":[-0.1807290018,51.4119796753],"type":"Point"}
}