{
  "type": "Feature",
  "properties": {
    "addr:full":"Lindsaylands Cottage Biggar Dumfries and Galloway ML12 6NR",
    "addr:postcode":"ml12 6nr",
    "iso:country":"GB",
    "sg:address":"Lindsaylands Cottage",
    "sg:city":"Biggar",
    "sg:classifiers":[
        {
            "category":"Professional",
            "type":"Services"
        }
    ],
    "sg:phone":"+44 1899 220471",
    "sg:postcode":"ML12 6NR",
    "sg:province":"Dumfries and Galloway",
    "sg:tags":[
        "entertainer"
    ],
    "wof:name":"Mr Boom-Children's One Man Band",
    "wof:placetype":"venue"
},
  "geometry": {"coordinates":[-3.523019,55.62442],"type":"Point"}
}