{
  "type": "Feature",
  "properties": {
    "addr:full":"4 Gro House, Church Road Ashford Greater London TW15 2UD",
    "addr:housenumber":"4;house",
    "addr:postcode":"tw15 2ud",
    "addr:street":"Gro;Church Road",
    "iso:country":"GB",
    "sg:address":"4 Gro House, Church Road",
    "sg:city":"Ashford",
    "sg:classifiers":[
        {
            "category":"Shopping",
            "subcategory":"Florist",
            "type":"Retail Goods"
        }
    ],
    "sg:postcode":"TW15 2UD",
    "sg:province":"Greater London",
    "wof:name":"Brockwells of Ashford",
    "wof:placetype":"venue"
},
  "geometry": {"coordinates":[-0.462444,51.432976],"type":"Point"}
}