{
  "type": "Feature",
  "properties": {
    "iso:country":"GB",
    "sg:address":"Tynant Nursery, Main Road, Morganstown",
    "sg:city":"Cardiff",
    "sg:classifiers":[
        {
            "category":"Shopping",
            "subcategory":"Department Store",
            "type":"Retail Goods"
        }
    ],
    "sg:postcode":"CF15 8LJ",
    "sg:province":"Caerphilly",
    "wof:name":"Thomas A Husband",
    "wof:placetype":"venue"
},
  "geometry": {"coordinates":[-3.2593870163,51.527973175],"type":"Point"}
}