{
  "type": "Feature",
  "properties": {
    "iso:country":"GB",
    "sg:address":"78-80 Kingsland High Street",
    "sg:city":"London",
    "sg:classifiers":[
        {
            "category":"Taxi",
            "type":"Transportation"
        }
    ],
    "sg:phone":"+44 20 7275 8900",
    "sg:postcode":"E8 2NS",
    "sg:province":"Greater London",
    "sg:tags":[
        "mini",
        "cab"
    ],
    "wof:name":"MARKET CARS",
    "wof:placetype":"venue"
},
  "geometry": {"coordinates":[-0.075572,51.548965],"type":"Point"}
}