{
  "type": "Feature",
  "properties": {
    "addr:full":"17 Pump Street Worcester Worcestershire WR1 2QX",
    "addr:housenumber":"17",
    "addr:postcode":"wr1 2qx",
    "addr:street":"Pump Street",
    "iso:country":"GB",
    "sg:address":"17 Pump Street",
    "sg:city":"Worcester",
    "sg:classifiers":[
        {
            "category":"Shopping",
            "subcategory":"Thrift Store",
            "type":"Retail Goods"
        }
    ],
    "sg:phone":"+44 1905 24800",
    "sg:postcode":"WR1 2QX",
    "sg:province":"Worcestershire",
    "sg:tags":[
        "shop",
        "charity"
    ],
    "wof:name":"Imperial Cancer Research Fund",
    "wof:placetype":"venue"
},
  "geometry": {"coordinates":[-2.219866991,52.1909446716],"type":"Point"}
}