{
  "type": "Feature",
  "properties": {
    "iso:country":"GB",
    "sg:address":"8a Brookside Red Marsh Ind Est",
    "sg:city":"Thornton Cleveleys",
    "sg:classifiers":[
        {
            "category":"Personal",
            "subcategory":"Sauna",
            "type":"Services"
        }
    ],
    "sg:phone":"+44 1253 869047",
    "sg:postcode":"FY5 4JT",
    "sg:province":"Lancashire",
    "sg:tags":[
        "equipment",
        "sunbed"
    ],
    "wof:name":"The New Palm Beach Sunbed Rental",
    "wof:placetype":"venue"
},
  "geometry": {"coordinates":[-3.001364,53.870968],"type":"Point"}
}