{
  "type": "Feature",
  "properties": {
    "addr:full":"998 Stockport Road Manchester Greater Manchester M19 3WN",
    "addr:housenumber":"998",
    "addr:postcode":"m19 3wn",
    "addr:street":"Stockport Road",
    "iso:country":"GB",
    "sg:address":"998 Stockport Road",
    "sg:city":"Manchester",
    "sg:classifiers":[
        {
            "category":"Fast Food",
            "type":"Food & Drink"
        }
    ],
    "sg:phone":"+44 161 248 9889",
    "sg:postcode":"M19 3WN",
    "sg:province":"Greater Manchester",
    "sg:tags":[
        "away",
        "meal",
        "outlet",
        "take"
    ],
    "wof:name":"Abduls Take Away",
    "wof:placetype":"venue"
},
  "geometry": {"coordinates":[-2.191589,53.444855],"type":"Point"}
}