{
  "type": "Feature",
  "properties": {
    "iso:country":"GB",
    "sg:address":"45 Liverpool Road",
    "sg:city":"Stoke-on-trent",
    "sg:classifiers":[
        {
            "category":"Fast Food",
            "type":"Food & Drink"
        }
    ],
    "sg:phone":"+44 1782 776933",
    "sg:postcode":"ST7 1EA",
    "sg:province":"Cheshire",
    "sg:tags":[
        "away",
        "take"
    ],
    "wof:name":"Joyous Feast",
    "wof:placetype":"venue"
},
  "geometry": {"coordinates":[-2.242051,53.087074],"type":"Point"}
}