{
  "type": "Feature",
  "properties": {
    "iso:country":"GB",
    "sg:address":"Riverside Farm, Rodley",
    "sg:city":"Westbury-on-severn",
    "sg:classifiers":[
        {
            "category":"Farming",
            "subcategory":"Crops",
            "type":"Manufacturing & Wholesale Goods"
        },
        {
            "category":"Farming",
            "subcategory":"Farm",
            "type":"Manufacturing & Wholesale Goods"
        }
    ],
    "sg:phone":"+44 1452 760254",
    "sg:postcode":"GL14 1RE",
    "sg:province":"Gloucestershire",
    "sg:tags":[
        "mixed",
        "arable"
    ],
    "wof:name":"R H Williams",
    "wof:placetype":"venue"
},
  "geometry": {"coordinates":[-2.412947,51.825058],"type":"Point"}
}