{
  "type": "Feature",
  "properties": {
    "iso:country":"GB",
    "sg:address":"South Kingennie Farm Cottage, Callas, By Broughty Ferry",
    "sg:city":"Dundee",
    "sg:classifiers":[
        {
            "category":"Restaurant",
            "type":"Food & Drink"
        }
    ],
    "sg:postcode":"DD5 3PA",
    "sg:province":"Angus",
    "wof:name":"South Kingennie House Restaurant",
    "wof:placetype":"venue"
},
  "geometry": {"coordinates":[-2.85947,56.50489],"type":"Point"}
}