{
  "type": "Feature",
  "properties": {
    "addr:full":"9-10 Harvey Road Cambridge Cambridgeshire CB1 2ET",
    "addr:housenumber":"9-10",
    "addr:postcode":"cb1 2et",
    "addr:street":"Harvey Road",
    "iso:country":"GB",
    "sg:address":"9-10 Harvey Road",
    "sg:city":"Cambridge",
    "sg:classifiers":[
        {
            "category":"Farming",
            "subcategory":"Nursery",
            "type":"Manufacturing & Wholesale Goods"
        },
        {
            "category":"Organizations",
            "subcategory":"Community Association",
            "type":"Services"
        }
    ],
    "sg:phone":"+44 1223 306520",
    "sg:postcode":"CB1 2ET",
    "sg:province":"Cambridgeshire",
    "sg:tags":[
        "society",
        "housing",
        "creche"
    ],
    "wof:name":"The Harvey Road Day Nursery",
    "wof:placetype":"venue"
},
  "geometry": {"coordinates":[0.130359,52.199211],"type":"Point"}
}