{
  "type": "Feature",
  "properties": {
    "iso:country":"GB",
    "sg:address":"26 St John Street",
    "sg:city":"Perth",
    "sg:classifiers":[
        {
            "category":"Personal",
            "subcategory":"Beauty Salon",
            "type":"Services"
        }
    ],
    "sg:phone":"+44 1738 624068",
    "sg:postcode":"PH1 5SP",
    "sg:province":"Perth and Kinross",
    "sg:tags":[
        "unisex",
        "hairdresser"
    ],
    "wof:name":"John Gillespie Hair Salon",
    "wof:placetype":"venue"
},
  "geometry": {"coordinates":[-3.427258,56.396381],"type":"Point"}
}