{
  "type": "Feature",
  "properties": {
    "addr:full":"19 Peel Street, Marsden Huddersfield West Yorkshire HD7 6BW",
    "addr:housenumber":"19",
    "addr:postcode":"hd7 6bw",
    "addr:street":"Peel Street;West",
    "iso:country":"GB",
    "sg:address":"19 Peel Street, Marsden",
    "sg:city":"Huddersfield",
    "sg:classifiers":[
        {
            "category":"Shopping",
            "subcategory":"Stationery & Office Supplies",
            "type":"Retail Goods"
        }
    ],
    "sg:phone":"+44 1484 845039",
    "sg:postcode":"HD7 6BW",
    "sg:province":"West Yorkshire",
    "sg:tags":[
        "equipment",
        "school"
    ],
    "wof:name":"Didactec",
    "wof:placetype":"venue"
},
  "geometry": {"coordinates":[-1.9261850119,53.6006622314],"type":"Point"}
}