{
  "type": "Feature",
  "properties": {
    "iso:country":"GB",
    "sg:address":"9 Grange Road",
    "sg:city":"Ramsgate",
    "sg:classifiers":[
        {
            "category":"Travel",
            "subcategory":"Hotels & Motels",
            "type":"Entertainment"
        }
    ],
    "sg:postcode":"CT11 9NG",
    "sg:province":"Kent",
    "wof:name":"Westcliff Hotel",
    "wof:placetype":"venue"
},
  "geometry": {"coordinates":[1.408068,51.330051],"type":"Point"}
}