{
  "type": "Feature",
  "properties": {
    "addr:full":"39 Holburn Street Aberdeen Aberdeen City AB10 6BS",
    "addr:housenumber":"39",
    "addr:postcode":"ab10 6bs",
    "addr:street":"Holburn Street",
    "iso:country":"GB",
    "sg:address":"39 Holburn Street",
    "sg:city":"Aberdeen",
    "sg:classifiers":[
        {
            "category":"Bars & Pubs",
            "type":"Food & Drink"
        },
        {
            "category":"Community Center",
            "subcategory":"Social",
            "type":"Public Place"
        }
    ],
    "sg:phone":"+44 1224 589839",
    "sg:postcode":"AB10 6BS",
    "sg:province":"Aberdeen City",
    "sg:tags":[
        "pubs",
        "house",
        "inn",
        "activity"
    ],
    "wof:name":"Glentanar Bar Lounge",
    "wof:placetype":"venue"
},
  "geometry": {"coordinates":[-2.112293,57.142124],"type":"Point"}
}