{
  "type": "Feature",
  "properties": {
    "iso:country":"GB",
    "sg:address":"158 Sussex Rd",
    "sg:city":"Southport",
    "sg:classifiers":[
        {
            "category":"Home & Garden",
            "subcategory":"Carpets & Floor Coverings",
            "type":"Retail Goods"
        }
    ],
    "sg:phone":"+44 1704 536973",
    "sg:postcode":"PR8 6DE",
    "sg:province":"Lancashire",
    "sg:tags":[
        "cleaner",
        "upholstery"
    ],
    "wof:name":"N Marshall",
    "wof:placetype":"venue"
},
  "geometry": {"coordinates":[-2.979153,53.643082],"type":"Point"}
}