{
  "type": "Feature",
  "properties": {
    "addr:full":"206 Wellington Rd Bilston West Midlands WV14 6BG",
    "addr:housenumber":"206",
    "addr:postcode":"wv14 6bg",
    "addr:street":"Wellington Rd",
    "iso:country":"GB",
    "sg:address":"206 Wellington Rd",
    "sg:city":"Bilston",
    "sg:classifiers":[
        {
            "category":"Sports & Exercise",
            "subcategory":"Tennis Court",
            "type":"Entertainment"
        }
    ],
    "sg:phone":"+44 1902 498535",
    "sg:postcode":"WV14 6BG",
    "sg:province":"West Midlands",
    "sg:tags":[
        "breakdown",
        "recovery"
    ],
    "wof:name":"D & E Transport Services",
    "wof:placetype":"venue"
},
  "geometry": {"coordinates":[-2.090141,52.570251],"type":"Point"}
}