{
  "type": "Feature",
  "properties": {
    "addr:full":"10c Church La London Greater London E11 1HG",
    "addr:housenumber":"10c",
    "addr:postcode":"e11 1hg",
    "addr:street":"Church La",
    "iso:country":"GB",
    "sg:address":"10c Church La",
    "sg:city":"London",
    "sg:classifiers":[
        {
            "category":"Professional",
            "subcategory":"Accounting & Tax Preparation",
            "type":"Services"
        }
    ],
    "sg:phone":"+44 20 8556 1976",
    "sg:postcode":"E11 1HG",
    "sg:province":"Greater London",
    "sg:tags":[
        "accountant"
    ],
    "wof:name":"Powell,D F,",
    "wof:placetype":"venue"
},
  "geometry": {"coordinates":[0.0105830003,51.5682029724],"type":"Point"}
}