{
  "type": "Feature",
  "properties": {
    "iso:country":"GB",
    "sg:address":"114 Newton Road",
    "sg:city":"Burton-on-trent",
    "sg:classifiers":[
        {
            "category":"Bars & Pubs",
            "type":"Food & Drink"
        }
    ],
    "sg:phone":"+44 1283 546380",
    "sg:postcode":"DE15 0TT",
    "sg:province":"Derbyshire",
    "sg:tags":[
        "pubs",
        "inn"
    ],
    "wof:name":"Royal Oak Inn",
    "wof:placetype":"venue"
},
  "geometry": {"coordinates":[-1.611285,52.813187],"type":"Point"}
}