{
  "type": "Feature",
  "properties": {
    "addr:full":"25 Hanover Place Canterbury Kent CT2 7HA",
    "addr:housenumber":"25",
    "addr:postcode":"ct2 7ha",
    "addr:street":"Hanover Place",
    "iso:country":"GB",
    "sg:address":"25 Hanover Place",
    "sg:city":"Canterbury",
    "sg:classifiers":[
        {
            "category":"Building & Trades",
            "subcategory":"Construction",
            "type":"Services"
        }
    ],
    "sg:phone":"+44 1227 760483",
    "sg:postcode":"CT2 7HA",
    "sg:province":"Kent",
    "sg:tags":[
        "glazier",
        "decorator",
        "painter"
    ],
    "wof:name":"J C & Son Rowland",
    "wof:placetype":"venue"
},
  "geometry": {"coordinates":[1.0765229464,51.2868690491],"type":"Point"}
}