{
  "type": "Feature",
  "properties": {
    "addr:full":"6a The Park London Greater London W5 5NE",
    "addr:housenumber":"6a",
    "addr:postcode":"w5 5ne",
    "addr:street":"The",
    "iso:country":"GB",
    "sg:address":"6a The Park",
    "sg:city":"London",
    "sg:classifiers":[
        {
            "category":"Health Services",
            "subcategory":"Health Practitioner",
            "type":"Services"
        }
    ],
    "sg:postcode":"W5 5NE",
    "sg:province":"Greater London",
    "sg:tags":[
        "psychotherapist"
    ],
    "wof:name":"Reliberate",
    "wof:placetype":"venue"
},
  "geometry": {"coordinates":[-0.302727,51.507843],"type":"Point"}
}