{
  "type": "Feature",
  "properties": {
    "addr:full":"Colzie Cottage, East Links Leven Fife KY8 4RF",
    "addr:postcode":"ky8 4rf",
    "addr:street":"East Links Leven",
    "iso:country":"GB",
    "sg:address":"Colzie Cottage, East Links",
    "sg:city":"Leven",
    "sg:classifiers":[
        {
            "category":"Building & Trades",
            "subcategory":"Construction",
            "type":"Services"
        }
    ],
    "sg:phone":"+44 1333 426887",
    "sg:postcode":"KY8 4RF",
    "sg:province":"Fife",
    "sg:tags":[
        "heating",
        "contractor"
    ],
    "wof:name":"Simpson A T Heating & Ventilation Engineers",
    "wof:placetype":"venue"
},
  "geometry": {"coordinates":[-2.9987869263,56.1944007874],"type":"Point"}
}