{
  "type": "Feature",
  "properties": {
    "addr:full":"32 Hewitt Lane Wymondham Norfolk NR18 0JA",
    "addr:housenumber":"32",
    "addr:postcode":"nr18 0ja",
    "addr:street":"Hewitt Lane",
    "iso:country":"GB",
    "sg:address":"32 Hewitt Lane",
    "sg:city":"Wymondham",
    "sg:classifiers":[
        {
            "category":"Wholesale",
            "subcategory":"Books, Periodicals, & Newspapers",
            "type":"Manufacturing & Wholesale Goods"
        }
    ],
    "sg:postcode":"NR18 0JA",
    "sg:province":"Norfolk",
    "sg:tags":[
        "publishing"
    ],
    "wof:name":"Horizon Scientific Press",
    "wof:placetype":"venue"
},
  "geometry": {"coordinates":[1.117405,52.580231],"type":"Point"}
}