{
  "type": "Feature",
  "properties": {
    "addr:full":"18 Bullion Lane Chester-le-street Durham DH2 2AL",
    "addr:housenumber":"18",
    "addr:postcode":"dh2 2al",
    "addr:street":"Bullion Lane",
    "iso:country":"GB",
    "sg:address":"18 Bullion Lane",
    "sg:city":"Chester-le-street",
    "sg:classifiers":[
        {
            "category":"Shopping",
            "subcategory":"News",
            "type":"Retail Goods"
        }
    ],
    "sg:phone":"+44 191 388 3138",
    "sg:postcode":"DH2 2AL",
    "sg:province":"Durham",
    "sg:tags":[
        "newsagent"
    ],
    "wof:name":"Baxters",
    "wof:placetype":"venue"
},
  "geometry": {"coordinates":[-1.580556035,54.854095459],"type":"Point"}
}