{
  "type": "Feature",
  "properties": {
    "iso:country":"GB",
    "sg:address":"Unit 3 6, Wembley Commercial Centre",
    "sg:city":"Wembley",
    "sg:classifiers":[
        {
            "category":"Shopping",
            "subcategory":"Musical Instruments",
            "type":"Retail Goods"
        }
    ],
    "sg:phone":"+44 20 8908 2323",
    "sg:postcode":"HA9 7XJ",
    "sg:province":"Greater London",
    "wof:name":"Brandoni Music Ltd.",
    "wof:placetype":"venue"
},
  "geometry": {"coordinates":[-0.2955389917,51.5529632568],"type":"Point"}
}