{
  "type": "Feature",
  "properties": {
    "iso:country":"GB",
    "sg:address":"Blaston Lodge, Blaston Road, Blaston",
    "sg:city":"Market Harborough",
    "sg:classifiers":[
        {
            "category":"Wholesale",
            "subcategory":"Machinery & Supplies",
            "type":"Manufacturing & Wholesale Goods"
        },
        {
            "category":"Farming",
            "subcategory":"Livestock Farm",
            "type":"Manufacturing & Wholesale Goods"
        }
    ],
    "sg:phone":"+44 1858 555688",
    "sg:postcode":"LE16 8DB",
    "sg:province":"Leicestershire",
    "sg:tags":[
        "pump",
        "others"
    ],
    "wof:name":"Blaston Lodge Farm",
    "wof:placetype":"venue"
},
  "geometry": {"coordinates":[-0.8000699878,52.5589408875],"type":"Point"}
}