{
  "type": "Feature",
  "properties": {
    "addr:full":"19 Grey St Newcastle Upon Tyne NE1 6EE",
    "addr:housenumber":"19",
    "addr:postcode":"ne1 6ee",
    "addr:street":"Grey St",
    "iso:country":"GB",
    "sg:address":"19 Grey St",
    "sg:city":"Newcastle Upon Tyne",
    "sg:classifiers":[
        {
            "category":"Professional",
            "subcategory":"Computer Services",
            "type":"Services"
        }
    ],
    "sg:postcode":"NE1 6EE",
    "sg:tags":[
        "music",
        "discovery",
        "marketplace"
    ],
    "sg:website":"http://amazingtunes.com",
    "wof:name":"amazingtunes",
    "wof:placetype":"venue"
},
  "geometry": {"coordinates":[-1.611141,54.971346],"type":"Point"}
}