{
  "type": "Feature",
  "properties": {
    "addr:full":"The Corner House, Main Road, Dorrington Shrewsbury Shropshire SY5 7JW",
    "addr:postcode":"sy5 7jw",
    "addr:street":"Main Road",
    "iso:country":"GB",
    "sg:address":"The Corner House, Main Road, Dorrington",
    "sg:city":"Shrewsbury",
    "sg:classifiers":[
        {
            "category":"Manufacturing",
            "subcategory":"Building Materials",
            "type":"Manufacturing & Wholesale Goods"
        }
    ],
    "sg:phone":"+44 1743 719250",
    "sg:postcode":"SY5 7JW",
    "sg:province":"Shropshire",
    "sg:tags":[
        "tarmac",
        "asphalt"
    ],
    "wof:name":"Macadam Surfacing (Midlands) Ltd.",
    "wof:placetype":"venue"
},
  "geometry": {"coordinates":[-2.772761,52.621876],"type":"Point"}
}