{
  "type": "Feature",
  "properties": {
    "iso:country":"GB",
    "sg:address":"Lloyd Crescent",
    "sg:city":"Coventry",
    "sg:classifiers":[
        {
            "category":"Social Services",
            "subcategory":"Child Care",
            "type":"Services"
        },
        {
            "category":"Government",
            "subcategory":"Office",
            "type":"Public Place"
        }
    ],
    "sg:phone":"+44 24 7645 1010",
    "sg:postcode":"CV2 5NY",
    "sg:province":"Warwickshire",
    "sg:tags":[
        "home",
        "local",
        "children's"
    ],
    "wof:name":"Stoke House",
    "wof:placetype":"venue"
},
  "geometry": {"coordinates":[-1.454359,52.408344],"type":"Point"}
}