{
  "type": "Feature",
  "properties": {
    "addr:full":"18 Upper Tooting Road London Greater London SW17 7PG",
    "addr:housenumber":"18",
    "addr:postcode":"sw17 7pg",
    "addr:street":"Upper Tooting Road",
    "iso:country":"GB",
    "sg:address":"18 Upper Tooting Road",
    "sg:city":"London",
    "sg:classifiers":[
        {
            "category":"Shopping",
            "subcategory":"Pharmacy",
            "type":"Retail Goods"
        }
    ],
    "sg:phone":"+44 20 8672 2524",
    "sg:postcode":"SW17 7PG",
    "sg:province":"Greater London",
    "sg:tags":[
        "pharmacist",
        "chemist"
    ],
    "wof:name":"N S K Ltd.",
    "wof:placetype":"venue"
},
  "geometry": {"coordinates":[-0.160830006,51.4352493286],"type":"Point"}
}