{
  "type": "Feature",
  "properties": {
    "iso:country":"GB",
    "sg:address":"Winmarleigh Street",
    "sg:city":"Warrington",
    "sg:classifiers":[
        {
            "category":"Government",
            "subcategory":"Court House",
            "type":"Public Place"
        }
    ],
    "sg:phone":"+44 1925 653136",
    "sg:postcode":"WA1 1PB",
    "sg:province":"Cheshire",
    "wof:name":"Warrington Magistrates Court",
    "wof:placetype":"venue"
},
  "geometry": {"coordinates":[-2.599379,53.387989],"type":"Point"}
}