{
  "type": "Feature",
  "properties": {
    "iso:country":"GB",
    "sg:address":"74 Woodland Drive",
    "sg:city":"St Albans",
    "sg:classifiers":[
        {
            "category":"Professional",
            "subcategory":"Engineering",
            "type":"Services"
        }
    ],
    "sg:postcode":"AL4 0ET",
    "sg:province":"Hertfordshire",
    "sg:tags":[
        "contractor",
        "electrical",
        "engineer"
    ],
    "wof:name":"R McRae Domestic Electrical Contractor",
    "wof:placetype":"venue"
},
  "geometry": {"coordinates":[-0.3046829998,51.7572097778],"type":"Point"}
}