{
  "type": "Feature",
  "properties": {
    "iso:country":"GB",
    "sg:address":"Commercial Road",
    "sg:city":"Dereham",
    "sg:classifiers":[
        {
            "category":"Arena",
            "subcategory":"Sports Club",
            "type":"Entertainment"
        }
    ],
    "sg:postcode":"NR19 1AE",
    "sg:province":"Norfolk",
    "wof:name":"G & N Bowlers Ltd.",
    "wof:placetype":"venue"
},
  "geometry": {"coordinates":[0.94396,52.679867],"type":"Point"}
}