{
  "type": "Feature",
  "properties": {
    "iso:country":"GB",
    "sg:address":"16-18 Bath Rd",
    "sg:city":"Bristol",
    "sg:classifiers":[
        {
            "category":"Autos & Motor Vehicles",
            "subcategory":"Auto Supplies",
            "type":"Retail Goods"
        }
    ],
    "sg:phone":"+44 117 986 2622",
    "sg:postcode":"BS18 1NW",
    "sg:province":"City of Bristol",
    "sg:tags":[
        "tyre"
    ],
    "wof:name":"Autospeed Tyre & Exhaust Centres",
    "wof:placetype":"venue"
},
  "geometry": {"coordinates":[-2.5815429688,51.4468002319],"type":"Point"}
}