{
  "type": "Feature",
  "properties": {
    "iso:country":"GB",
    "sg:address":"15 Holmwood Dr",
    "sg:city":"Gloucester",
    "sg:classifiers":[
        {
            "category":"Health Services",
            "subcategory":"Nursing And Care Facility",
            "type":"Services"
        }
    ],
    "sg:phone":"+44 1452 522847",
    "sg:postcode":"GL4 0PS",
    "sg:province":"Gloucestershire",
    "sg:tags":[
        "home"
    ],
    "wof:name":"The Grange Nursing Home",
    "wof:placetype":"venue"
},
  "geometry": {"coordinates":[-2.255377,51.830696],"type":"Point"}
}