{
  "type": "Feature",
  "properties": {
    "iso:country":"GB",
    "sg:address":"Cannon Road",
    "sg:city":"London",
    "sg:classifiers":[
        {
            "category":"Government",
            "subcategory":"Office",
            "type":"Public Place"
        }
    ],
    "sg:phone":"+44 20 8886 9400",
    "sg:postcode":"N14 7HE",
    "sg:province":"Greater London",
    "sg:tags":[
        "local"
    ],
    "wof:name":"St Monica S Scout & Guide Headquaters",
    "wof:placetype":"venue"
},
  "geometry": {"coordinates":[-0.120804,51.62278],"type":"Point"}
}