{
  "type": "Feature",
  "properties": {
    "iso:country":"GB",
    "sg:address":"206 Park Street La, Park St",
    "sg:city":"St Albans",
    "sg:classifiers":[
        {
            "category":"Shopping",
            "subcategory":"Computers & Home Electronics",
            "type":"Retail Goods"
        }
    ],
    "sg:postcode":"AL2 2AQ",
    "sg:province":"Hertfordshire",
    "wof:name":"Pacific Pc Ltd",
    "wof:placetype":"venue"
},
  "geometry": {"coordinates":[-0.3536559939,51.7122116089],"type":"Point"}
}