{
  "type": "Feature",
  "properties": {
    "iso:country":"GB",
    "sg:address":"21 Moordown",
    "sg:city":"Woolwich",
    "sg:classifiers":[
        {
            "category":"Professional",
            "subcategory":"Computer Services",
            "type":"Services"
        }
    ],
    "sg:phone":"+44 70 7188 0334",
    "sg:postcode":"SE18 3LY",
    "sg:province":"Greater London",
    "sg:tags":[
        "system",
        "software"
    ],
    "wof:name":"Technology Works",
    "wof:placetype":"venue"
},
  "geometry": {"coordinates":[0.066434,51.475357],"type":"Point"}
}