{
  "type": "Feature",
  "properties": {
    "iso:country":"GB",
    "sg:address":"1 Hyde Court, Market Place",
    "sg:city":"Leek",
    "sg:classifiers":[
        {
            "category":"Health Services",
            "subcategory":"Podiatrist",
            "type":"Services"
        }
    ],
    "sg:phone":"+44 1538 399727",
    "sg:postcode":"ST13 5HH",
    "sg:province":"Staffordshire",
    "sg:tags":[
        "podiatrists",
        "chiropodist"
    ],
    "wof:name":"Paul A Edwards",
    "wof:placetype":"venue"
},
  "geometry": {"coordinates":[-2.020884,53.106476],"type":"Point"}
}