{
  "type": "Feature",
  "properties": {
    "addr:full":"6 Hollyberry Av Solihull West Midlands B91 3UA",
    "addr:housenumber":"6",
    "addr:postcode":"b91 3ua",
    "addr:street":"Hollyberry Av Solihull",
    "iso:country":"GB",
    "sg:address":"6 Hollyberry Av",
    "sg:city":"Solihull",
    "sg:classifiers":[
        {
            "category":"Professional",
            "subcategory":"Printing & Photocopies",
            "type":"Services"
        }
    ],
    "sg:phone":"+44 121 704 3280",
    "sg:postcode":"B91 3UA",
    "sg:province":"West Midlands",
    "sg:tags":[
        "embroiderer"
    ],
    "wof:name":"Frog Star",
    "wof:placetype":"venue"
},
  "geometry": {"coordinates":[-1.792693,52.398502],"type":"Point"}
}