{
  "type": "Feature",
  "properties": {
    "iso:country":"GB",
    "sg:address":"72 High Street",
    "sg:city":"Auchterarder",
    "sg:classifiers":[
        {
            "category":"Shopping",
            "subcategory":"Clothing, Apparel, & Fashions",
            "type":"Retail Goods"
        }
    ],
    "sg:phone":"+44 1764 664112",
    "sg:postcode":"PH3 1BN",
    "sg:province":"Perth and Kinross",
    "sg:tags":[
        "shop"
    ],
    "wof:name":"Catherine McGraw",
    "wof:placetype":"venue"
},
  "geometry": {"coordinates":[-3.7052929401,56.2967185974],"type":"Point"}
}