{
  "type": "Feature",
  "properties": {
    "iso:country":"GB",
    "sg:address":"14 Redwood Close, Kings Norton",
    "sg:city":"Birmingham",
    "sg:classifiers":[
        {
            "category":"Professional",
            "subcategory":"Accounting & Tax Preparation",
            "type":"Services"
        }
    ],
    "sg:phone":"+44 121 683 0063",
    "sg:postcode":"B30 1AU",
    "sg:province":"West Midlands",
    "sg:tags":[
        "accountant"
    ],
    "wof:name":"Financial Record Service",
    "wof:placetype":"venue"
},
  "geometry": {"coordinates":[-1.939591,52.414528],"type":"Point"}
}