{
  "type": "Feature",
  "properties": {
    "iso:country":"GB",
    "sg:address":"365 Station Road",
    "sg:city":"Harrow",
    "sg:classifiers":[
        {
            "category":"Communications",
            "type":"Services"
        }
    ],
    "sg:phone":"+44 20 8861 5500",
    "sg:postcode":"HA1 2AW",
    "sg:province":"Greater London",
    "sg:tags":[
        "telecommunication"
    ],
    "wof:name":"F1 Communications Ltd.",
    "wof:placetype":"venue"
},
  "geometry": {"coordinates":[-0.334257,51.579678],"type":"Point"}
}