{
  "type": "Feature",
  "properties": {
    "iso:country":"GB",
    "sg:address":"Unit 23 Chase Lane",
    "sg:city":"Gloucester",
    "sg:classifiers":[
        {
            "category":"Professional",
            "subcategory":"Printing & Photocopies",
            "type":"Services"
        }
    ],
    "sg:phone":"+44 1452 331693",
    "sg:postcode":"GL4 6PH",
    "sg:province":"Gloucestershire",
    "sg:tags":[
        "plate",
        "lithographic",
        "maker"
    ],
    "wof:name":"L P Print Ltd.",
    "wof:placetype":"venue"
},
  "geometry": {"coordinates":[-2.22517,51.853088],"type":"Point"}
}