{
  "type": "Feature",
  "properties": {
    "addr:full":"Valley Cottage, Windsor Road Gerrards Cross Buckinghamshire SL9 8SW",
    "addr:postcode":"sl9 8sw",
    "addr:street":"Windsor Road",
    "iso:country":"GB",
    "sg:address":"Valley Cottage, Windsor Road",
    "sg:city":"Gerrards Cross",
    "sg:classifiers":[
        {
            "category":"Retail",
            "subcategory":"Auto Repair",
            "type":"Services"
        }
    ],
    "sg:phone":"+44 1753 663233",
    "sg:postcode":"SL9 8SW",
    "sg:province":"Buckinghamshire",
    "sg:tags":[
        "modification",
        "garage"
    ],
    "wof:name":"J & J Motors",
    "wof:placetype":"venue"
},
  "geometry": {"coordinates":[-0.5625789762,51.5789756775],"type":"Point"}
}