{
  "type": "Feature",
  "properties": {
    "addr:full":"19-21 White Hart Street High Wycombe Buckinghamshire HP11 2HL",
    "addr:housenumber":"19-21",
    "addr:postcode":"hp11 2hl",
    "addr:street":"White Hart Street",
    "iso:country":"GB",
    "sg:address":"19-21 White Hart Street",
    "sg:city":"High Wycombe",
    "sg:classifiers":[
        {
            "category":"Shopping",
            "subcategory":"Photographic Equipment",
            "type":"Retail Goods"
        }
    ],
    "sg:postcode":"HP11 2HL",
    "sg:province":"Buckinghamshire",
    "sg:tags":[
        "supply"
    ],
    "wof:name":"M W Keen Ltd.",
    "wof:placetype":"venue"
},
  "geometry": {"coordinates":[-0.752518,51.629803],"type":"Point"}
}