{
  "type": "Feature",
  "properties": {
    "addr:full":"101 Bartholomew Street Newbury Berkshire RG14 5DY",
    "addr:housenumber":"101",
    "addr:postcode":"rg14 5dy",
    "addr:street":"Bartholomew Street",
    "iso:country":"GB",
    "sg:address":"101 Bartholomew Street",
    "sg:city":"Newbury",
    "sg:classifiers":[
        {
            "category":"Professional",
            "subcategory":"Engineering",
            "type":"Services"
        }
    ],
    "sg:phone":"+44 1635 43365",
    "sg:postcode":"RG14 5DY",
    "sg:province":"Berkshire",
    "sg:tags":[
        "contractor",
        "electrical",
        "engineer"
    ],
    "wof:name":"Baker's (Newbury) Ltd.",
    "wof:placetype":"venue"
},
  "geometry": {"coordinates":[-1.326573,51.398365],"type":"Point"}
}