{
  "type": "Feature",
  "properties": {
    "iso:country":"GB",
    "sg:address":"18 Church Road",
    "sg:city":"Burgess Hill",
    "sg:classifiers":[
        {
            "category":"Shopping",
            "subcategory":"Antiques",
            "type":"Retail Goods"
        }
    ],
    "sg:phone":"+44 1444 235747",
    "sg:postcode":"RH15 9AE",
    "sg:province":"East Sussex",
    "wof:name":"The Collector",
    "wof:placetype":"venue"
},
  "geometry": {"coordinates":[-0.129137,50.955032],"type":"Point"}
}