{
  "type": "Feature",
  "properties": {
    "addr:full":"34 Croft Rd Wimbledon Greater London SW19 2NF",
    "addr:housenumber":"34",
    "addr:postcode":"sw19 2nf",
    "addr:street":"Croft Rd",
    "iso:country":"GB",
    "sg:address":"34 Croft Rd",
    "sg:city":"Wimbledon",
    "sg:classifiers":[
        {
            "category":"Professional",
            "subcategory":"Engineering",
            "type":"Services"
        }
    ],
    "sg:phone":"+44 20 8543 5156",
    "sg:postcode":"SW19 2NF",
    "sg:province":"Greater London",
    "sg:tags":[
        "gas",
        "engineer"
    ],
    "wof:name":"Hart Heating",
    "wof:placetype":"venue"
},
  "geometry": {"coordinates":[-0.1844319999,51.4154777527],"type":"Point"}
}