{
  "type": "Feature",
  "properties": {
    "iso:country":"GB",
    "sg:address":"7 Cardross Road",
    "sg:city":"Dumbarton",
    "sg:classifiers":[
        {
            "category":"Place Of Worship",
            "type":"Public Place"
        }
    ],
    "sg:phone":"+44 1389 762709",
    "sg:postcode":"G82 4JE",
    "sg:province":"Argyll and Bute",
    "wof:name":"St.Michael S Presbytery",
    "wof:placetype":"venue"
},
  "geometry": {"coordinates":[-4.584959,55.97504],"type":"Point"}
}