{
  "type": "Feature",
  "properties": {
    "iso:country":"GB",
    "sg:address":"Howley Quay, Howley Lane",
    "sg:city":"Warrington",
    "sg:classifiers":[
        {
            "category":"Wholesale",
            "subcategory":"Construction Materials",
            "type":"Manufacturing & Wholesale Goods"
        },
        {
            "category":"Building & Trades",
            "subcategory":"Equipment Rental",
            "type":"Services"
        }
    ],
    "sg:phone":"+44 1925 414825",
    "sg:postcode":"WA1 2DZ",
    "sg:province":"Cheshire",
    "sg:tags":[
        "lift",
        "lifting"
    ],
    "sg:website":"http://www.lymmlifting.co.uk",
    "wof:name":"Lymm Lifting & Engineering Services",
    "wof:placetype":"venue"
},
  "geometry": {"coordinates":[-2.578874,53.389469],"type":"Point"}
}