{
  "type": "Feature",
  "properties": {
    "iso:country":"GB",
    "sg:address":"King Street, Brynmawr",
    "sg:city":"Ebbw Vale",
    "sg:classifiers":[
        {
            "category":"Retail",
            "subcategory":"Auto Repair",
            "type":"Services"
        }
    ],
    "sg:phone":"+44 1495 310265",
    "sg:postcode":"NP23 4SU",
    "sg:province":"Blaenau Gwent",
    "sg:tags":[
        "engine",
        "specialist",
        "garage",
        "related",
        "car"
    ],
    "wof:name":"Merthyr Road Garage",
    "wof:placetype":"venue"
},
  "geometry": {"coordinates":[-3.167534,51.801968],"type":"Point"}
}