{
  "type": "Feature",
  "properties": {
    "addr:full":"17 Station Road Longfield Kent DA3 7QD",
    "addr:housenumber":"17",
    "addr:postcode":"da3 7qd",
    "addr:street":"Station Road",
    "iso:country":"GB",
    "sg:address":"17 Station Road",
    "sg:city":"Longfield",
    "sg:classifiers":[
        {
            "category":"Fast Food",
            "type":"Food & Drink"
        }
    ],
    "sg:phone":"+44 1474 702323",
    "sg:postcode":"DA3 7QD",
    "sg:province":"Kent",
    "sg:tags":[
        "away",
        "meal",
        "outlet",
        "take"
    ],
    "wof:name":"S W Ho",
    "wof:placetype":"venue"
},
  "geometry": {"coordinates":[0.3004570007,51.3982963562],"type":"Point"}
}