{
  "type": "Feature",
  "properties": {
    "iso:country":"GB",
    "sg:address":"48 Tolmers Road, Cuffley",
    "sg:city":"Potters Bar",
    "sg:classifiers":[
        {
            "category":"Professional",
            "subcategory":"Engineering",
            "type":"Services"
        }
    ],
    "sg:phone":"+44 1707 876993",
    "sg:postcode":"EN6 4JF",
    "sg:province":"Greater London",
    "sg:tags":[
        "contractor",
        "electrical",
        "engineer"
    ],
    "wof:name":"Alsen Electrical",
    "wof:placetype":"venue"
},
  "geometry": {"coordinates":[-0.111381,51.710178],"type":"Point"}
}