{
  "type": "Feature",
  "properties": {
    "addr:full":"Priory Road Clinic, Priory Road Swindon Wiltshire SN3 2EZ",
    "addr:postcode":"sn3 2ez",
    "addr:street":"Priory;Priory Road",
    "iso:country":"GB",
    "sg:address":"Priory Road Clinic, Priory Road",
    "sg:city":"Swindon",
    "sg:classifiers":[
        {
            "category":"Health Services",
            "subcategory":"Clinic",
            "type":"Services"
        }
    ],
    "sg:phone":"+44 1793 642411",
    "sg:postcode":"SN3 2EZ",
    "sg:province":"Wiltshire",
    "sg:tags":[
        "nh"
    ],
    "wof:name":"The Community Dental Service",
    "wof:placetype":"venue"
},
  "geometry": {"coordinates":[-1.747201,51.55241],"type":"Point"}
}