{
  "type": "Feature",
  "properties": {
    "addr:full":"Unit 15a Clos Y Nant, Plasmawr Rd Cardiff Cardiff CF5 3JP",
    "addr:housenumber":"unit 15a",
    "addr:postcode":"cf5 3jp",
    "addr:street":"Clos Y;Plasmawr Rd",
    "iso:country":"GB",
    "sg:address":"Unit 15a Clos Y Nant, Plasmawr Rd",
    "sg:city":"Cardiff",
    "sg:classifiers":[
        {
            "category":"Professional",
            "type":"Services"
        }
    ],
    "sg:phone":"+44 29 2055 5155",
    "sg:postcode":"CF5 3JP",
    "sg:province":"Cardiff",
    "sg:tags":[
        "repair",
        "tech",
        "maintenance"
    ],
    "wof:name":"Calcom Systems Maintenance",
    "wof:placetype":"venue"
},
  "geometry": {"coordinates":[-3.2422139645,51.4920310974],"type":"Point"}
}