{
  "type": "Feature",
  "properties": {
    "iso:country":"GB",
    "sg:address":"The Pump House, Farleigh Lane, East Farleigh",
    "sg:city":"Maidstone",
    "sg:classifiers":[
        {
            "category":"Shopping",
            "subcategory":"Computers & Home Electronics",
            "type":"Retail Goods"
        }
    ],
    "sg:phone":"+44 1622 721444",
    "sg:postcode":"ME16 8NB",
    "sg:province":"Kent",
    "sg:tags":[
        "hi-fi",
        "equipment",
        "mnfr"
    ],
    "wof:name":"Chord Electronics Ltd.",
    "wof:placetype":"venue"
},
  "geometry": {"coordinates":[0.5037099719,51.2679214478],"type":"Point"}
}