{
  "type": "Feature",
  "properties": {
    "iso:country":"GB",
    "sg:address":"Hilton Lane, Prestwich",
    "sg:city":"Manchester",
    "sg:classifiers":[
        {
            "category":"Social Services",
            "subcategory":"Retirement Home",
            "type":"Services"
        },
        {
            "category":"Government",
            "subcategory":"Office",
            "type":"Public Place"
        }
    ],
    "sg:postcode":"M25 9NL",
    "sg:province":"Greater Manchester",
    "sg:tags":[
        "residential",
        "local",
        "care"
    ],
    "wof:name":"Redcliffe",
    "wof:placetype":"venue"
},
  "geometry": {"coordinates":[-2.2778460979,53.5219955444],"type":"Point"}
}