{
  "type": "Feature",
  "properties": {
    "iso:country":"GB",
    "sg:address":"48 Amber Crescent, Walton",
    "sg:city":"Chesterfield",
    "sg:classifiers":[
        {
            "category":"Building & Trades",
            "subcategory":"Construction",
            "type":"Services"
        }
    ],
    "sg:phone":"+44 1246 273039",
    "sg:postcode":"S40 3DH",
    "sg:province":"Derbyshire",
    "sg:tags":[
        "window",
        "glazier",
        "replacement"
    ],
    "wof:name":"Four Seasons Upvc Window Centre",
    "wof:placetype":"venue"
},
  "geometry": {"coordinates":[-1.456814,53.227451],"type":"Point"}
}