{
  "type": "Feature",
  "properties": {
    "addr:full":"Catterick Road, Walkerville Industrial Estate Catterick Garrison North Yorkshire DL9 4RR",
    "addr:postcode":"dl9 4rr",
    "addr:street":"Catterick Road;Industrial Estate",
    "iso:country":"GB",
    "sg:address":"Catterick Road, Walkerville Industrial Estate",
    "sg:city":"Catterick Garrison",
    "sg:classifiers":[
        {
            "category":"Retail",
            "subcategory":"Event Space",
            "type":"Services"
        }
    ],
    "sg:phone":"+44 1748 834577",
    "sg:postcode":"DL9 4RR",
    "sg:province":"North Yorkshire",
    "sg:tags":[
        "pipeline"
    ],
    "wof:name":"International Pipeline Products Ltd.",
    "wof:placetype":"venue"
},
  "geometry": {"coordinates":[-1.69105196,54.377986908],"type":"Point"}
}