{
  "type": "Feature",
  "properties": {
    "iso:country":"GB",
    "sg:address":"60 High Street, Dawley",
    "sg:city":"Telford",
    "sg:classifiers":[
        {
            "category":"Professional",
            "subcategory":"Lawyer & Legal Services",
            "type":"Services"
        }
    ],
    "sg:postcode":"TF4 2EX",
    "sg:province":"Shropshire",
    "sg:tags":[
        "solicitor"
    ],
    "wof:name":"Griffiths & Co",
    "wof:placetype":"venue"
},
  "geometry": {"coordinates":[-2.466889,52.66367],"type":"Point"}
}