{
  "type": "Feature",
  "properties": {
    "iso:country":"GB",
    "sg:address":"11 Exeter Road",
    "sg:city":"Exmouth",
    "sg:classifiers":[
        {
            "category":"Shopping",
            "subcategory":"Baby Store",
            "type":"Retail Goods"
        }
    ],
    "sg:phone":"+44 1395 225660",
    "sg:postcode":"EX8 1PN",
    "sg:province":"Devon",
    "sg:tags":[
        "nursery",
        "accessory"
    ],
    "wof:name":"Scooters",
    "wof:placetype":"venue"
},
  "geometry": {"coordinates":[-3.411867,50.620926],"type":"Point"}
}