{
  "type": "Feature",
  "properties": {
    "iso:country":"GB",
    "sg:address":"126 Barnsbury Road",
    "sg:city":"London",
    "sg:classifiers":[
        {
            "category":"Real Estate",
            "subcategory":"Architect",
            "type":"Services"
        }
    ],
    "sg:phone":"+44 20 7278 3533",
    "sg:postcode":"N1 0ER",
    "sg:province":"Greater London",
    "wof:name":"John Olley",
    "wof:placetype":"venue"
},
  "geometry": {"coordinates":[-0.110439,51.537426],"type":"Point"}
}