{
  "type": "Feature",
  "properties": {
    "iso:country":"GB",
    "sg:address":"The Barracks, Bridport Road",
    "sg:city":"Dorchester",
    "sg:classifiers":[
        {
            "category":"Professional",
            "subcategory":"Management & Consulting",
            "type":"Services"
        }
    ],
    "sg:phone":"+44 1305 266920",
    "sg:postcode":"DT1 1RN",
    "sg:province":"Dorset",
    "sg:tags":[
        "conservation"
    ],
    "wof:name":"Dorset Countryside Ranger Service",
    "wof:placetype":"venue"
},
  "geometry": {"coordinates":[-2.441564,50.711906],"type":"Point"}
}