{
  "type": "Feature",
  "properties": {
    "addr:full":"4th Floor Scotia Bank House, 6 South Charlotte Street Edinburgh City of Edinburgh EH2 4AW",
    "addr:housenumber":"4th floor scotia;6",
    "addr:postcode":"eh2 4aw",
    "addr:street":"South Charlotte Street",
    "iso:country":"GB",
    "sg:address":"4th Floor Scotia Bank House, 6 South Charlotte Street",
    "sg:city":"Edinburgh",
    "sg:classifiers":[
        {
            "category":"Organizations",
            "subcategory":"Non-profit Organization",
            "type":"Services"
        }
    ],
    "sg:phone":"+44 131 473 7170",
    "sg:postcode":"EH2 4AW",
    "sg:province":"City of Edinburgh",
    "sg:tags":[
        "organisation",
        "voluntary",
        "charity"
    ],
    "wof:name":"Shelter Scotland Ltd.",
    "wof:placetype":"venue"
},
  "geometry": {"coordinates":[-3.20619,55.950771],"type":"Point"}
}