{
  "type": "Feature",
  "properties": {
    "addr:full":"Flat 24 The Colonnades, 8 Wren Road London Greater London SE5 8QS",
    "addr:housenumber":"flat 24;8",
    "addr:postcode":"se5 8qs",
    "addr:street":"The Colonnades;Wren Road",
    "iso:country":"GB",
    "sg:address":"Flat 24 The Colonnades, 8 Wren Road",
    "sg:city":"London",
    "sg:classifiers":[
        {
            "category":"Professional",
            "subcategory":"Management & Consulting",
            "type":"Services"
        }
    ],
    "sg:phone":"+44 20 7703 2258",
    "sg:postcode":"SE5 8QS",
    "sg:province":"Greater London",
    "sg:tags":[
        "music"
    ],
    "wof:name":"24/7 Productions Ltd.",
    "wof:placetype":"venue"
},
  "geometry": {"coordinates":[-0.091335997,51.4729652405],"type":"Point"}
}