{
  "type": "Feature",
  "properties": {
    "addr:full":"London Road Staines Berkshire TW18 4HN",
    "addr:postcode":"tw18 4hn",
    "addr:street":"London Road",
    "iso:country":"GB",
    "sg:address":"London Road",
    "sg:city":"Staines",
    "sg:classifiers":[
        {
            "category":"Autos & Motor Vehicles",
            "subcategory":"Fuel & Gas Station",
            "type":"Retail Goods"
        }
    ],
    "sg:phone":"+44 1784 441020",
    "sg:postcode":"TW18 4HN",
    "sg:province":"Berkshire",
    "sg:tags":[
        "petrol",
        "filling"
    ],
    "wof:name":"City Petroleum (Shell of Staines) Co",
    "wof:placetype":"venue"
},
  "geometry": {"coordinates":[-0.4889219999,51.4393692017],"type":"Point"}
}