{
  "type": "Feature",
  "properties": {
    "iso:country":"GB",
    "sg:address":"2 Akarit Road, Stenhousemuir",
    "sg:city":"Larbert",
    "sg:classifiers":[
        {
            "category":"Building & Trades",
            "subcategory":"Construction",
            "type":"Services"
        }
    ],
    "sg:postcode":"FK5 4BY",
    "sg:province":"Falkirk",
    "sg:tags":[
        "dry",
        "lining",
        "plasterers",
        "screeders"
    ],
    "wof:name":"The Cornice Co.",
    "wof:placetype":"venue"
},
  "geometry": {"coordinates":[-3.8073620796,56.0269966125],"type":"Point"}
}