{
  "type": "Feature",
  "properties": {
    "iso:country":"GB",
    "sg:address":"48-50 Mitchell St",
    "sg:city":"Chester Le Street",
    "sg:classifiers":[
        {
            "category":"Building & Trades",
            "subcategory":"Plumbing",
            "type":"Services"
        }
    ],
    "sg:phone":"+44 191 410 0188",
    "sg:postcode":"DH3 1ER",
    "sg:province":"Durham",
    "sg:tags":[
        "heating"
    ],
    "wof:name":"J G Oliver",
    "wof:placetype":"venue"
},
  "geometry": {"coordinates":[-1.5798139572,54.8981704712],"type":"Point"}
}