{
  "type": "Feature",
  "properties": {
    "addr:full":"52 High St, Henley In Arden Solihull Warwickshire B95 5AN",
    "addr:housenumber":"52",
    "addr:postcode":"b95 5an",
    "addr:street":"High St",
    "iso:country":"GB",
    "sg:address":"52 High St, Henley In Arden",
    "sg:city":"Solihull",
    "sg:classifiers":[
        {
            "category":"Professional",
            "subcategory":"Management & Consulting",
            "type":"Services"
        }
    ],
    "sg:postcode":"B95 5AN",
    "sg:province":"Warwickshire",
    "sg:tags":[
        "consultant",
        "business"
    ],
    "wof:name":"Fintrac Overseas Ltd",
    "wof:placetype":"venue"
},
  "geometry": {"coordinates":[-1.7792129517,52.2942848206],"type":"Point"}
}