{
  "type": "Feature",
  "properties": {
    "addr:full":"8a Shooters Hill, Pangbourne Reading Berkshire RG8 7DU",
    "addr:housenumber":"8a",
    "addr:postcode":"rg8 7du",
    "addr:street":"Shooters Hill",
    "iso:country":"GB",
    "sg:address":"8a Shooters Hill, Pangbourne",
    "sg:city":"Reading",
    "sg:classifiers":[
        {
            "category":"Professional",
            "subcategory":"Computer Services",
            "type":"Services"
        }
    ],
    "sg:phone":"+44 118 984 1988",
    "sg:postcode":"RG8 7DU",
    "sg:province":"Berkshire",
    "sg:tags":[
        "system",
        "software"
    ],
    "wof:name":"I T Centre Ltd.",
    "wof:placetype":"venue"
},
  "geometry": {"coordinates":[-1.0914640427,51.4863014221],"type":"Point"}
}