{
  "type": "Feature",
  "properties": {
    "addr:full":"Braithwell Rd Rotherham South Yorkshire S66 8AE",
    "addr:postcode":"s66 8ae",
    "addr:street":"Braithwell Rd",
    "iso:country":"GB",
    "sg:address":"Braithwell Rd",
    "sg:city":"Rotherham",
    "sg:classifiers":[
        {
            "category":"Autos & Motor Vehicles",
            "subcategory":"Fuel & Gas Station",
            "type":"Retail Goods"
        }
    ],
    "sg:phone":"+44 1709 812070",
    "sg:postcode":"S66 8AE",
    "sg:province":"South Yorkshire",
    "sg:tags":[
        "petrol",
        "filling"
    ],
    "wof:name":"Manor Service Staion",
    "wof:placetype":"venue"
},
  "geometry": {"coordinates":[-1.2071989775,53.4303855896],"type":"Point"}
}