{
  "type": "Feature",
  "properties": {
    "addr:full":"42-43 North Road Ripon North Yorkshire HG4 1JR",
    "addr:housenumber":"42-43",
    "addr:postcode":"hg4 1jr",
    "addr:street":"North Road",
    "iso:country":"GB",
    "sg:address":"42-43 North Road",
    "sg:city":"Ripon",
    "sg:classifiers":[
        {
            "category":"Shopping",
            "subcategory":"Department Store",
            "type":"Retail Goods"
        },
        {
            "category":"Arts & Performance",
            "subcategory":"Theater",
            "type":"Entertainment"
        }
    ],
    "sg:postcode":"HG4 1JR",
    "sg:province":"North Yorkshire",
    "sg:tags":[
        "theatrical",
        "agency"
    ],
    "wof:name":"North Bridge Post Office",
    "wof:placetype":"venue"
},
  "geometry": {"coordinates":[-1.5209709406,54.1421394348],"type":"Point"}
}