{
  "type": "Feature",
  "properties": {
    "addr:full":"Boston Rd, Holbeach Spalding Cambridgeshire PE12 7LR",
    "addr:postcode":"pe12 7lr",
    "addr:street":"Boston Rd;Spalding",
    "iso:country":"GB",
    "sg:address":"Boston Rd, Holbeach",
    "sg:city":"Spalding",
    "sg:classifiers":[
        {
            "category":"Community Center",
            "subcategory":"Youth",
            "type":"Public Place"
        }
    ],
    "sg:phone":"+44 1406 422305",
    "sg:postcode":"PE12 7LR",
    "sg:province":"Cambridgeshire",
    "sg:tags":[
        "organisation",
        "centre"
    ],
    "wof:name":"Holbeach Youth Centre",
    "wof:placetype":"venue"
},
  "geometry": {"coordinates":[0.0144999996,52.8039665222],"type":"Point"}
}