{
  "type": "Feature",
  "properties": {
    "iso:country":"GB",
    "sg:address":"1 Tyn Y Coed Mews, High Street",
    "sg:city":"Barmouth",
    "sg:classifiers":[
        {
            "category":"Food & Beverages",
            "subcategory":"Liquor & Beverages",
            "type":"Retail Goods"
        }
    ],
    "sg:postcode":"LL42 1DS",
    "sg:province":"Gwynedd",
    "sg:tags":[
        "beer",
        "spirit",
        "wines"
    ],
    "wof:name":"R Evans & Co.",
    "wof:placetype":"venue"
},
  "geometry": {"coordinates":[-4.055159,52.722664],"type":"Point"}
}