{
  "type": "Feature",
  "properties": {
    "iso:country":"GB",
    "sg:address":"85 Somers Road",
    "sg:city":"Rugby",
    "sg:classifiers":[
        {
            "category":"Retail",
            "subcategory":"Auto Repair",
            "type":"Services"
        }
    ],
    "sg:phone":"+44 1788 543094",
    "sg:postcode":"CV22 7DG",
    "sg:province":"Warwickshire",
    "sg:tags":[
        "modification",
        "garage",
        "related"
    ],
    "wof:name":"R B S Motor Services (Rugby) Ltd.",
    "wof:placetype":"venue"
},
  "geometry": {"coordinates":[-1.285858,52.371883],"type":"Point"}
}