{
  "type": "Feature",
  "properties": {
    "iso:country":"GB",
    "sg:address":"37 Arnison Avenue",
    "sg:city":"High Wycombe",
    "sg:classifiers":[
        {
            "category":"Shopping",
            "subcategory":"Gifts & Souvenirs",
            "type":"Retail Goods"
        },
        {
            "category":"Manufacturing",
            "subcategory":"Glass & Minerals",
            "type":"Manufacturing & Wholesale Goods"
        },
        {
            "category":"Professional",
            "subcategory":"Lawyer & Legal Services",
            "type":"Services"
        }
    ],
    "sg:postcode":"HP13 6DB",
    "sg:province":"Buckinghamshire",
    "sg:tags":[
        "product",
        "mfrs",
        "counselling",
        "advice",
        "leaded",
        "window"
    ],
    "wof:name":"Evans Glass",
    "wof:placetype":"venue"
},
  "geometry": {"coordinates":[-0.7354339957,51.638420105],"type":"Point"}
}