{
  "type": "Feature",
  "properties": {
    "iso:country":"GB",
    "sg:address":"101a Sun Lane",
    "sg:city":"Gravesend",
    "sg:classifiers":[
        {
            "category":"Manufacturing",
            "subcategory":"Jewelry",
            "type":"Manufacturing & Wholesale Goods"
        }
    ],
    "sg:phone":"+44 1474 355334",
    "sg:postcode":"DA12 5HW",
    "sg:province":"Kent",
    "sg:tags":[
        "manufacture",
        "repair",
        "jewellery"
    ],
    "wof:name":"D'Arcy Jewellery Repair Centre",
    "wof:placetype":"venue"
},
  "geometry": {"coordinates":[0.3759709895,51.4275512695],"type":"Point"}
}