{
  "type": "Feature",
  "properties": {
    "iso:country":"GB",
    "sg:address":"277 Sandy Lane, Droylsden",
    "sg:city":"Manchester",
    "sg:classifiers":[
        {
            "category":"Building & Trades",
            "subcategory":"Construction",
            "type":"Services"
        }
    ],
    "sg:phone":"+44 161 371 8843",
    "sg:postcode":"M43 7JU",
    "sg:province":"Greater Manchester",
    "sg:tags":[
        "dry",
        "plastering",
        "plasterers",
        "lining",
        "related",
        "screeders"
    ],
    "wof:name":"D Ratchford",
    "wof:placetype":"venue"
},
  "geometry": {"coordinates":[-2.130265,53.48772],"type":"Point"}
}