{
  "type": "Feature",
  "properties": {
    "iso:country":"GB",
    "sg:address":"Unit 5 Bellbrook Enterprise Cent, Re Bell Lane, Bellbrook Industrial Estate",
    "sg:city":"Uckfield",
    "sg:classifiers":[
        {
            "category":"Professional",
            "subcategory":"Printing & Photocopies",
            "type":"Services"
        }
    ],
    "sg:phone":"+44 1825 765222",
    "sg:postcode":"TN22 1QL",
    "sg:province":"East Sussex",
    "sg:tags":[
        "print",
        "finisher"
    ],
    "sg:website":"http://www.odpf.co.uk",
    "wof:name":"O'Donnell Print Finishers Ltd.",
    "wof:placetype":"venue"
},
  "geometry": {"coordinates":[0.0966499969,50.9718132019],"type":"Point"}
}