{
  "type": "Feature",
  "properties": {
    "iso:country":"GB",
    "sg:address":"Silver Street",
    "sg:city":"Lyme Regis",
    "sg:classifiers":[
        {
            "category":"Bars & Pubs",
            "type":"Food & Drink"
        }
    ],
    "sg:phone":"+44 1297 442312",
    "sg:postcode":"DT7 3HS",
    "sg:province":"Devon",
    "sg:tags":[
        "pubs",
        "inn"
    ],
    "wof:name":"The Nags Head",
    "wof:placetype":"venue"
},
  "geometry": {"coordinates":[-2.938714,50.726002],"type":"Point"}
}