{
  "type": "Feature",
  "properties": {
    "addr:full":"20 Abbey Road Smethwick West Midlands B67 5RD",
    "addr:housenumber":"20",
    "addr:postcode":"b67 5rd",
    "addr:street":"Abbey Road",
    "iso:country":"GB",
    "sg:address":"20 Abbey Road",
    "sg:city":"Smethwick",
    "sg:classifiers":[
        {
            "category":"Real Estate",
            "subcategory":"Surveying",
            "type":"Services"
        }
    ],
    "sg:postcode":"B67 5RD",
    "sg:province":"West Midlands",
    "sg:tags":[
        "surveyor",
        "quantity"
    ],
    "wof:name":"Mfp Ltd.",
    "wof:placetype":"venue"
},
  "geometry": {"coordinates":[-1.9755170345,52.4773788452],"type":"Point"}
}