{
  "type": "Feature",
  "properties": {
    "addr:full":"Enterprise House, Main Road Shrewsbury Shropshire SY5 0PY",
    "addr:postcode":"sy5 0py",
    "addr:street":"Main Road",
    "iso:country":"GB",
    "sg:address":"Enterprise House, Main Road",
    "sg:city":"Shrewsbury",
    "sg:classifiers":[
        {
            "category":"Personal",
            "subcategory":"Beauty Salon",
            "type":"Services"
        }
    ],
    "sg:phone":"+44 1743 790386",
    "sg:postcode":"SY5 0PY",
    "sg:province":"Shropshire",
    "sg:tags":[
        "unisex",
        "hairdresser"
    ],
    "wof:name":"David Jones Hairdressing",
    "wof:placetype":"venue"
},
  "geometry": {"coordinates":[-2.8908379078,52.6496391296],"type":"Point"}
}