{
  "type": "Feature",
  "properties": {
    "iso:country":"GB",
    "sg:address":"2 Church St",
    "sg:city":"Peterborough",
    "sg:classifiers":[
        {
            "category":"Military Area",
            "subcategory":"Air Force Base",
            "type":"Public Place"
        }
    ],
    "sg:phone":"+44 1733 555225",
    "sg:postcode":"PE2 8HE",
    "sg:province":"Cambridgeshire",
    "sg:tags":[
        "taxi",
        "hire",
        "private"
    ],
    "wof:name":"1st 1 Bizzy Lizzy Cars",
    "wof:placetype":"venue"
},
  "geometry": {"coordinates":[-0.22883,52.558762],"type":"Point"}
}