{
  "type": "Feature",
  "properties": {
    "addr:full":"298 Abbeydale Road Sheffield South Yorkshire S7 1FL",
    "addr:housenumber":"298",
    "addr:postcode":"s7 1fl",
    "addr:street":"Abbeydale Road",
    "iso:country":"GB",
    "sg:address":"298 Abbeydale Road",
    "sg:city":"Sheffield",
    "sg:classifiers":[
        {
            "category":"Shopping",
            "subcategory":"Antiques",
            "type":"Retail Goods"
        }
    ],
    "sg:postcode":"S7 1FL",
    "sg:province":"South Yorkshire",
    "wof:name":"Acorn Antiques",
    "wof:placetype":"venue"
},
  "geometry": {"coordinates":[-1.478892,53.361576],"type":"Point"}
}