{
  "type": "Feature",
  "properties": {
    "addr:full":"25 Fishescoates Avenue, Rutherglen Glasgow Glasgow City G73 5DG",
    "addr:housenumber":"25",
    "addr:postcode":"g73 5dg",
    "addr:street":"Fishescoates Avenue",
    "iso:country":"GB",
    "sg:address":"25 Fishescoates Avenue, Rutherglen",
    "sg:city":"Glasgow",
    "sg:classifiers":[
        {
            "category":"Professional",
            "subcategory":"Engineering",
            "type":"Services"
        }
    ],
    "sg:postcode":"G73 5DG",
    "sg:province":"Glasgow City",
    "sg:tags":[
        "contractor",
        "electrical",
        "engineer"
    ],
    "wof:name":"Hugh McElhone",
    "wof:placetype":"venue"
},
  "geometry": {"coordinates":[-4.195923,55.81385],"type":"Point"}
}