{
  "type": "Feature",
  "properties": {
    "addr:full":"Pedmore Valley Nottingham Nottinghamshire NG5 5NN",
    "addr:postcode":"ng5 5nn",
    "addr:street":"Valley",
    "iso:country":"GB",
    "sg:address":"Pedmore Valley",
    "sg:city":"Nottingham",
    "sg:classifiers":[
        {
            "category":"Health Services",
            "subcategory":"Doctor",
            "type":"Services"
        }
    ],
    "sg:phone":"+44 115 920 8781",
    "sg:postcode":"NG5 5NN",
    "sg:province":"Nottinghamshire",
    "sg:tags":[
        "practitioners"
    ],
    "wof:name":"Halstead, P",
    "wof:placetype":"venue"
},
  "geometry": {"coordinates":[-1.157799,53.002403],"type":"Point"}
}