{
  "type": "Feature",
  "properties": {
    "addr:full":"9 The Square Sevenoaks Kent TN13 2AB",
    "addr:housenumber":"9",
    "addr:postcode":"tn13 2ab",
    "addr:street":"The Square",
    "iso:country":"GB",
    "sg:address":"9 The Square",
    "sg:city":"Sevenoaks",
    "sg:classifiers":[
        {
            "category":"Banks & Credit Unions",
            "subcategory":"Investment Brokerage",
            "type":"Services"
        }
    ],
    "sg:phone":"+44 1732 746628",
    "sg:postcode":"TN13 2AB",
    "sg:province":"Kent",
    "sg:tags":[
        "stockbroker"
    ],
    "wof:name":"Edward Jones Ltd.",
    "wof:placetype":"venue"
},
  "geometry": {"coordinates":[0.1696549952,51.2836608887],"type":"Point"}
}