{
  "type": "Feature",
  "properties": {
    "iso:country":"GB",
    "sg:address":"Creaton Rd, Brixworth",
    "sg:city":"Northampton",
    "sg:classifiers":[
        {
            "category":"Organizations",
            "subcategory":"Non-profit Organization",
            "type":"Services"
        }
    ],
    "sg:phone":"+44 1604 880003",
    "sg:postcode":"NN6 9BW",
    "sg:province":"Northamptonshire",
    "sg:tags":[
        "organisation",
        "animal",
        "welfare"
    ],
    "wof:name":"Jay Gee Sanctuary For Dogs",
    "wof:placetype":"venue"
},
  "geometry": {"coordinates":[-0.903534,52.329048],"type":"Point"}
}