{
  "type": "Feature",
  "properties": {
    "iso:country":"GB",
    "sg:address":"Unit 2, 19c Aston Road",
    "sg:city":"Waterlooville",
    "sg:classifiers":[
        {
            "category":"Shopping",
            "subcategory":"Clothing, Apparel, & Fashions",
            "type":"Retail Goods"
        }
    ],
    "sg:phone":"+44 23 9225 3700",
    "sg:postcode":"PO7 7XE",
    "sg:province":"Hampshire",
    "sg:tags":[
        "accessory"
    ],
    "wof:name":"Nick Rees Designs Ltd.",
    "wof:placetype":"venue"
},
  "geometry": {"coordinates":[-1.035399,50.884735],"type":"Point"}
}