{
  "type": "Feature",
  "properties": {
    "iso:country":"GB",
    "sg:address":"Wentworth Rd, Swinton",
    "sg:city":"Manchester",
    "sg:classifiers":[
        {
            "category":"Community Center",
            "type":"Public Place"
        }
    ],
    "sg:phone":"+44 161 727 8462",
    "sg:postcode":"M27 0BB",
    "sg:province":"Greater Manchester",
    "sg:tags":[
        "recreation",
        "leisure",
        "centre"
    ],
    "wof:name":"Moorside Leisure Centre",
    "wof:placetype":"venue"
},
  "geometry": {"coordinates":[-2.350505,53.505638],"type":"Point"}
}