{
  "type": "Feature",
  "properties": {
    "iso:country":"GB",
    "sg:address":"225 Seabank Rd",
    "sg:city":"Wallasey",
    "sg:classifiers":[
        {
            "category":"Restaurant",
            "type":"Food & Drink"
        }
    ],
    "sg:phone":"+44 151 691 1919",
    "sg:postcode":"L45 1HE",
    "sg:province":"Merseyside",
    "sg:tags":[
        "indian"
    ],
    "wof:name":"Kayum Tandoori & Indian Restaurant",
    "wof:placetype":"venue"
},
  "geometry": {"coordinates":[-3.0396020412,53.4312324524],"type":"Point"}
}