{
  "type": "Feature",
  "properties": {
    "addr:full":"126 Long Acre London Greater London WC2E 9PE",
    "addr:housenumber":"126",
    "addr:postcode":"wc2e 9pe",
    "addr:street":"Long Acre",
    "iso:country":"GB",
    "sg:address":"126 Long Acre",
    "sg:city":"London",
    "sg:classifiers":[
        {
            "category":"Social Services",
            "subcategory":"Adult Care",
            "type":"Services"
        }
    ],
    "sg:phone":"+44 20 7240 2724",
    "sg:postcode":"WC2E 9PE",
    "sg:province":"Greater London",
    "sg:tags":[
        "domestic",
        "cleaning"
    ],
    "wof:name":"Dustbusters (Uk) Ltd",
    "wof:placetype":"venue"
},
  "geometry": {"coordinates":[-0.125632,51.512539],"type":"Point"}
}