{
  "type": "Feature",
  "properties": {
    "iso:country":"GB",
    "sg:address":"Rolle Road",
    "sg:city":"Budleigh Salterton",
    "sg:classifiers":[
        {
            "category":"Restaurant",
            "type":"Food & Drink"
        }
    ],
    "sg:postcode":"EX9 6JZ",
    "sg:province":"Devon",
    "wof:name":"Thorneys",
    "wof:placetype":"venue"
},
  "geometry": {"coordinates":[-3.325299,50.62904],"type":"Point"}
}