{
  "type": "Feature",
  "properties": {
    "addr:full":"78 Marston Lane, Bedworth Nuneaton Warwickshire CV12 8DJ",
    "addr:housenumber":"78",
    "addr:postcode":"cv12 8dj",
    "addr:street":"Marston Lane",
    "iso:country":"GB",
    "sg:address":"78 Marston Lane, Bedworth",
    "sg:city":"Nuneaton",
    "sg:classifiers":[
        {
            "category":"Shopping",
            "subcategory":"Department Store",
            "type":"Retail Goods"
        }
    ],
    "sg:postcode":"CV12 8DJ",
    "sg:province":"Warwickshire",
    "wof:name":"Terry Haskins",
    "wof:placetype":"venue"
},
  "geometry": {"coordinates":[-1.4705820084,52.4869003296],"type":"Point"}
}