{
  "type": "Feature",
  "properties": {
    "addr:full":"18 Colwill Road, Gabalfa Cardiff Cardiff CF4 2QQ",
    "addr:housenumber":"18",
    "addr:postcode":"cf4 2qq",
    "addr:street":"Colwill Road",
    "iso:country":"GB",
    "sg:address":"18 Colwill Road, Gabalfa",
    "sg:city":"Cardiff",
    "sg:classifiers":[
        {
            "category":"Place Of Worship",
            "type":"Public Place"
        }
    ],
    "sg:postcode":"CF4 2QQ",
    "sg:province":"Cardiff",
    "wof:name":"Our Lady of Lourdes",
    "wof:placetype":"venue"
},
  "geometry": {"coordinates":[-3.19893,51.50061],"type":"Point"}
}