{
  "type": "Feature",
  "properties": {
    "iso:country":"GB",
    "sg:address":"72 Danecroft Rd",
    "sg:city":"Herne Hill",
    "sg:classifiers":[
        {
            "category":"Retail",
            "subcategory":"Storage",
            "type":"Services"
        }
    ],
    "sg:phone":"+44 20 7207 7066",
    "sg:postcode":"SE24 9NZ",
    "sg:province":"Greater London",
    "sg:tags":[
        "household",
        "removal"
    ],
    "wof:name":"AUSTIN REMOVALS",
    "wof:placetype":"venue"
},
  "geometry": {"coordinates":[-0.0931769982,51.4557037354],"type":"Point"}
}