{
  "type": "Feature",
  "properties": {
    "iso:country":"GB",
    "sg:address":"44 The Terrace",
    "sg:city":"Torquay",
    "sg:classifiers":[
        {
            "category":"Building & Trades",
            "subcategory":"Landscaping Services",
            "type":"Services"
        }
    ],
    "sg:phone":"+44 1803 201515",
    "sg:postcode":"TQ1 1DE",
    "sg:province":"Devon",
    "sg:tags":[
        "landscape",
        "contractor"
    ],
    "wof:name":"Westward Landscapes",
    "wof:placetype":"venue"
},
  "geometry": {"coordinates":[-3.524213,50.462055],"type":"Point"}
}