{
  "type": "Feature",
  "properties": {
    "iso:country":"GB",
    "sg:address":"Slaytor House, 22 Stanley Street",
    "sg:city":"Rotherham",
    "sg:classifiers":[
        {
            "category":"Organizations",
            "subcategory":"Political Organization",
            "type":"Services"
        }
    ],
    "sg:phone":"+44 1709 363295",
    "sg:postcode":"S60 2DP",
    "sg:province":"South Yorkshire",
    "sg:tags":[
        "party"
    ],
    "wof:name":"WENTWORTH CONSERVATIVE ASSOCIATION",
    "wof:placetype":"venue"
},
  "geometry": {"coordinates":[-1.354379,53.42844],"type":"Point"}
}