{
  "type": "Feature",
  "properties": {
    "addr:full":"33 Mill La Stockport Cheshire SK6 1QJ",
    "addr:housenumber":"33",
    "addr:postcode":"sk6 1qj",
    "addr:street":"Mill La Stockport",
    "iso:country":"GB",
    "sg:address":"33 Mill La",
    "sg:city":"Stockport",
    "sg:classifiers":[
        {
            "category":"Professional",
            "subcategory":"Engineering",
            "type":"Services"
        }
    ],
    "sg:phone":"+44 161 430 6034",
    "sg:postcode":"SK6 1QJ",
    "sg:province":"Cheshire",
    "sg:tags":[
        "contractor",
        "electrical",
        "engineer"
    ],
    "wof:name":"D W Sawyer",
    "wof:placetype":"venue"
},
  "geometry": {"coordinates":[-2.1043329239,53.4265403748],"type":"Point"}
}