{
  "type": "Feature",
  "properties": {
    "iso:country":"GB",
    "sg:address":"92 County Road, Walton",
    "sg:city":"Liverpool",
    "sg:classifiers":[
        {
            "category":"Retail",
            "subcategory":"Laundry & Dry Cleaning",
            "type":"Services"
        }
    ],
    "sg:postcode":"L4 3QN",
    "sg:province":"Merseyside",
    "sg:tags":[
        "alteration"
    ],
    "wof:name":"Cliff's Cleaners",
    "wof:placetype":"venue"
},
  "geometry": {"coordinates":[-2.970666,53.440849],"type":"Point"}
}