{
  "type": "Feature",
  "properties": {
    "addr:full":"38 Bicker Rd, Donington Spalding Lincolnshire PE11 4XP",
    "addr:housenumber":"38",
    "addr:postcode":"pe11 4xp",
    "addr:street":"Bicker Rd",
    "iso:country":"GB",
    "sg:address":"38 Bicker Rd, Donington",
    "sg:city":"Spalding",
    "sg:classifiers":[
        {
            "category":"Farming",
            "subcategory":"Farm",
            "type":"Manufacturing & Wholesale Goods"
        }
    ],
    "sg:postcode":"PE11 4XP",
    "sg:province":"Lincolnshire",
    "sg:tags":[
        "mixed",
        "crop"
    ],
    "wof:name":"Stanley,John,",
    "wof:placetype":"venue"
},
  "geometry": {"coordinates":[-0.1994979978,52.9095306396],"type":"Point"}
}