{
  "type": "Feature",
  "properties": {
    "addr:full":"Cannock Chase Hospital, Brunswick Rd Cannock Staffordshire WS11 2XY",
    "addr:postcode":"ws11 2xy",
    "addr:street":"Brunswick Rd",
    "iso:country":"GB",
    "sg:address":"Cannock Chase Hospital, Brunswick Rd",
    "sg:city":"Cannock",
    "sg:classifiers":[
        {
            "category":"Health Services",
            "subcategory":"Doctor",
            "type":"Services"
        }
    ],
    "sg:phone":"+44 1543 576660",
    "sg:postcode":"WS11 2XY",
    "sg:province":"Staffordshire",
    "sg:tags":[
        "practitioners"
    ],
    "wof:name":"Myint, K",
    "wof:placetype":"venue"
},
  "geometry": {"coordinates":[-2.016234,52.702381],"type":"Point"}
}