{
  "type": "Feature",
  "properties": {
    "addr:full":"24 Martin Ct, Avyton Washington Durham NE38 0EP",
    "addr:housenumber":"24",
    "addr:postcode":"ne38 0ep",
    "addr:street":"Martin Ct",
    "iso:country":"GB",
    "sg:address":"24 Martin Ct, Avyton",
    "sg:city":"Washington",
    "sg:classifiers":[
        {
            "category":"Building & Trades",
            "subcategory":"Construction",
            "type":"Services"
        }
    ],
    "sg:postcode":"NE38 0EP",
    "sg:province":"Durham",
    "sg:tags":[
        "builder"
    ],
    "wof:name":"Connolly,Les,",
    "wof:placetype":"venue"
},
  "geometry": {"coordinates":[-1.553056,54.887867],"type":"Point"}
}