{
  "type": "Feature",
  "properties": {
    "iso:country":"GB",
    "sg:address":"26 Midland Road, Llansamlet",
    "sg:city":"Swansea",
    "sg:classifiers":[
        {
            "category":"Building & Trades",
            "subcategory":"Construction",
            "type":"Services"
        }
    ],
    "sg:phone":"+44 1792 700700",
    "sg:postcode":"SA4 9QY",
    "sg:province":"Carmarthenshire",
    "sg:tags":[
        "builder"
    ],
    "wof:name":"Elfin Projects Ltd.",
    "wof:placetype":"venue"
},
  "geometry": {"coordinates":[-4.0001997948,51.6826400757],"type":"Point"}
}