{
  "type": "Feature",
  "properties": {
    "iso:country":"GB",
    "sg:address":"232 New London Road",
    "sg:city":"Chelmsford",
    "sg:classifiers":[
        {
            "category":"Bars & Pubs",
            "type":"Food & Drink"
        },
        {
            "category":"Community Center",
            "subcategory":"Social",
            "type":"Public Place"
        }
    ],
    "sg:phone":"+44 1245 600071",
    "sg:postcode":"CM2 9AE",
    "sg:province":"Essex",
    "sg:tags":[
        "pubs",
        "house",
        "inn",
        "activity"
    ],
    "wof:name":"Rising Sun",
    "wof:placetype":"venue"
},
  "geometry": {"coordinates":[0.461089,51.723007],"type":"Point"}
}