{
  "type": "Feature",
  "properties": {
    "addr:full":"99 Wilsthorpe Road, Long Eaton Nottingham Derbyshire NG10 3LE",
    "addr:housenumber":"99",
    "addr:postcode":"ng10 3le",
    "addr:street":"Wilsthorpe Road",
    "iso:country":"GB",
    "sg:address":"99 Wilsthorpe Road, Long Eaton",
    "sg:city":"Nottingham",
    "sg:classifiers":[
        {
            "category":"Shopping",
            "subcategory":"Stationery & Office Supplies",
            "type":"Retail Goods"
        }
    ],
    "sg:postcode":"NG10 3LE",
    "sg:province":"Derbyshire",
    "sg:tags":[
        "printers'"
    ],
    "wof:name":"F R Arnott & Co Headband Manufacturers",
    "wof:placetype":"venue"
},
  "geometry": {"coordinates":[-1.2886550426,52.8884925842],"type":"Point"}
}