{
  "type": "Feature",
  "properties": {
    "addr:full":"Po Box 101 Corby Northamptonshire NN17 5UA",
    "addr:housenumber":"po",
    "addr:postcode":"nn17 5ua",
    "addr:street":"Box 101",
    "iso:country":"GB",
    "sg:address":"Po Box 101",
    "sg:city":"Corby",
    "sg:classifiers":[
        {
            "category":"Professional",
            "subcategory":"Business Services",
            "type":"Services"
        }
    ],
    "sg:phone":"+44 1536 266840",
    "sg:postcode":"NN17 5UA",
    "sg:province":"Northamptonshire",
    "sg:tags":[
        "distribution"
    ],
    "wof:name":"P C Howard Ltd.",
    "wof:placetype":"venue"
},
  "geometry": {"coordinates":[-0.670229,52.499401],"type":"Point"}
}