{
  "type": "Feature",
  "properties": {
    "iso:country":"GB",
    "sg:address":"20-22 The Pentagon",
    "sg:city":"Chatham",
    "sg:classifiers":[
        {
            "category":"Shopping",
            "subcategory":"Books",
            "type":"Retail Goods"
        }
    ],
    "sg:phone":"+44 1634 405149",
    "sg:postcode":"ME4 4DP",
    "sg:province":"Kent",
    "sg:tags":[
        "bookseller",
        "retailer"
    ],
    "sg:website":"http://www.whsmith.co.uk",
    "wof:name":"W H Smith",
    "wof:placetype":"venue"
},
  "geometry": {"coordinates":[0.529696,51.394276],"type":"Point"}
}