{
  "type": "Feature",
  "properties": {
    "addr:full":"Staines Library, Thames St Staines Berkshire TW18 4PG",
    "addr:postcode":"tw18 4pg",
    "addr:street":"Thames St",
    "iso:country":"GB",
    "sg:address":"Staines Library, Thames St",
    "sg:city":"Staines",
    "sg:classifiers":[
        {
            "category":"Organizations",
            "subcategory":"Non-profit Organization",
            "type":"Services"
        }
    ],
    "sg:phone":"+44 1784 453372",
    "sg:postcode":"TW18 4PG",
    "sg:province":"Berkshire",
    "sg:tags":[
        "organisation",
        "voluntary",
        "charity"
    ],
    "wof:name":"Spelthorne & District Volunteer Bureau",
    "wof:placetype":"venue"
},
  "geometry": {"coordinates":[-0.5005540252,51.4372253418],"type":"Point"}
}