{
  "type": "Feature",
  "properties": {
    "addr:full":"386-396 Great Horton Road Bradford West Yorkshire BD7 3HS",
    "addr:housenumber":"386-396",
    "addr:postcode":"bd7 3hs",
    "addr:street":"Great Horton Road",
    "iso:country":"GB",
    "sg:address":"386-396 Great Horton Road",
    "sg:city":"Bradford",
    "sg:classifiers":[
        {
            "category":"Restaurant",
            "type":"Food & Drink"
        }
    ],
    "sg:phone":"+44 1274 571861",
    "sg:postcode":"BD7 3HS",
    "sg:province":"West Yorkshire",
    "sg:tags":[
        "indian",
        "-"
    ],
    "wof:name":"Mumtaz Paan House Ltd",
    "wof:placetype":"venue"
},
  "geometry": {"coordinates":[-1.7755260468,53.786403656],"type":"Point"}
}