{
  "type": "Feature",
  "properties": {
    "addr:full":"53 Gawsworth Road Sale Cheshire M33 2UZ",
    "addr:housenumber":"53",
    "addr:postcode":"m33 2uz",
    "addr:street":"Gawsworth Road",
    "iso:country":"GB",
    "sg:address":"53 Gawsworth Road",
    "sg:city":"Sale",
    "sg:classifiers":[
        {
            "category":"Building & Trades",
            "subcategory":"Landscaping Services",
            "type":"Services"
        }
    ],
    "sg:phone":"+44 161 973 3685",
    "sg:postcode":"M33 2UZ",
    "sg:province":"Cheshire",
    "sg:tags":[
        "gardening"
    ],
    "wof:name":"Garden Control",
    "wof:placetype":"venue"
},
  "geometry": {"coordinates":[-2.297495,53.411133],"type":"Point"}
}