{
  "type": "Feature",
  "properties": {
    "addr:full":"77 Twyford Avenue Portsmouth Hampshire PO2 8DG",
    "addr:housenumber":"77",
    "addr:postcode":"po2 8dg",
    "addr:street":"Twyford Avenue",
    "iso:country":"GB",
    "sg:address":"77 Twyford Avenue",
    "sg:city":"Portsmouth",
    "sg:classifiers":[
        {
            "category":"Food & Beverages",
            "subcategory":"Meat & Fish",
            "type":"Retail Goods"
        }
    ],
    "sg:phone":"+44 23 9266 5882",
    "sg:postcode":"PO2 8DG",
    "sg:province":"Hampshire",
    "sg:tags":[
        "chip"
    ],
    "wof:name":"Bento Box",
    "wof:placetype":"venue"
},
  "geometry": {"coordinates":[-1.085221,50.815742],"type":"Point"}
}