{
  "type": "Feature",
  "properties": {
    "addr:full":"44 Goathland Drive Sunderland Tyne and Wear SR3 2BZ",
    "addr:housenumber":"44",
    "addr:postcode":"sr3 2bz",
    "addr:street":"Goathland Drive",
    "iso:country":"GB",
    "sg:address":"44 Goathland Drive",
    "sg:city":"Sunderland",
    "sg:classifiers":[
        {
            "category":"Shopping",
            "subcategory":"Computers & Home Electronics",
            "type":"Retail Goods"
        }
    ],
    "sg:postcode":"SR3 2BZ",
    "sg:province":"Tyne and Wear",
    "sg:tags":[
        "electrical"
    ],
    "wof:name":"Ross Electrical Services",
    "wof:placetype":"venue"
},
  "geometry": {"coordinates":[-1.3926210403,54.8706893921],"type":"Point"}
}