{
  "type": "Feature",
  "properties": {
    "addr:full":"Wellhead Farm, Park Lane, Cowling Keighley North Yorkshire BD22 0NH",
    "addr:postcode":"bd22 0nh",
    "addr:street":"Park Lane",
    "iso:country":"GB",
    "sg:address":"Wellhead Farm, Park Lane, Cowling",
    "sg:city":"Keighley",
    "sg:classifiers":[
        {
            "category":"Building & Trades",
            "subcategory":"Plumbing",
            "type":"Services"
        }
    ],
    "sg:phone":"+44 1535 637057",
    "sg:postcode":"BD22 0NH",
    "sg:province":"North Yorkshire",
    "sg:tags":[
        "plumber",
        "heating"
    ],
    "wof:name":"H Hawker Plumbing & Heating",
    "wof:placetype":"venue"
},
  "geometry": {"coordinates":[-2.0406939983,53.8850631714],"type":"Point"}
}