{
  "type": "Feature",
  "properties": {
    "addr:full":"21 Lonsdale Rd Kilburn Greater London NW6 6RA",
    "addr:housenumber":"21",
    "addr:postcode":"nw6 6ra",
    "addr:street":"Lonsdale Rd",
    "iso:country":"GB",
    "sg:address":"21 Lonsdale Rd",
    "sg:city":"Kilburn",
    "sg:classifiers":[
        {
            "category":"Communications",
            "subcategory":"Film & Video Production",
            "type":"Services"
        }
    ],
    "sg:phone":"+44 20 7328 9019",
    "sg:postcode":"NW6 6RA",
    "sg:province":"Greater London",
    "sg:tags":[
        "illustrator",
        "artist"
    ],
    "wof:name":"Mikki Rain",
    "wof:placetype":"venue"
},
  "geometry": {"coordinates":[-0.203215,51.537144],"type":"Point"}
}