{
  "type": "Feature",
  "properties": {
    "addr:full":"10 Denham Drive Basingstoke Hampshire RG22 6LR",
    "addr:housenumber":"10",
    "addr:postcode":"rg22 6lr",
    "addr:street":"Denham Drive",
    "iso:country":"GB",
    "sg:address":"10 Denham Drive",
    "sg:city":"Basingstoke",
    "sg:classifiers":[
        {
            "category":"Wholesale",
            "subcategory":"Books, Periodicals, & Newspapers",
            "type":"Manufacturing & Wholesale Goods"
        }
    ],
    "sg:postcode":"RG22 6LR",
    "sg:province":"Hampshire",
    "sg:tags":[
        "publishing"
    ],
    "wof:name":"E P Market Intelligence",
    "wof:placetype":"venue"
},
  "geometry": {"coordinates":[-1.122647,51.253368],"type":"Point"}
}