{
  "type": "Feature",
  "properties": {
    "addr:full":"97 Middleton Park Road Leeds West Yorkshire LS10 4LS",
    "addr:housenumber":"97",
    "addr:postcode":"ls10 4ls",
    "addr:street":"Middleton Park Road",
    "iso:country":"GB",
    "sg:address":"97 Middleton Park Road",
    "sg:city":"Leeds",
    "sg:classifiers":[
        {
            "category":"Personal",
            "type":"Services"
        }
    ],
    "sg:phone":"+44 1924 273177",
    "sg:postcode":"LS10 4LS",
    "sg:province":"West Yorkshire",
    "sg:tags":[
        "wedding"
    ],
    "wof:name":"Leeds Wedding Warehouse",
    "wof:placetype":"venue"
},
  "geometry": {"coordinates":[-1.548909,53.748161],"type":"Point"}
}