{
  "type": "Feature",
  "properties": {
    "iso:country":"GB",
    "sg:address":"7 Delaware Dr",
    "sg:city":"Milton Keynes",
    "sg:classifiers":[
        {
            "category":"Manufacturing",
            "subcategory":"Food",
            "type":"Manufacturing & Wholesale Goods"
        }
    ],
    "sg:phone":"+44 1908 210828",
    "sg:postcode":"MK15 8HG",
    "sg:province":"Buckinghamshire",
    "sg:tags":[
        "mnfr",
        "drink",
        "soft"
    ],
    "wof:name":"Coca Cola & Schweppes Beverages Ltd",
    "wof:placetype":"venue"
},
  "geometry": {"coordinates":[-0.732181,52.067032],"type":"Point"}
}