{
  "type": "Feature",
  "properties": {
    "addr:full":"33/34 Rathbone Place London Greater London W1T 1JQ",
    "addr:housenumber":"33 / 34",
    "addr:postcode":"w1t 1jq",
    "addr:street":"Rathbone Place",
    "iso:country":"GB",
    "sg:address":"33/34 Rathbone Place",
    "sg:city":"London",
    "sg:classifiers":[
        {
            "category":"Professional",
            "subcategory":"Art Services",
            "type":"Services"
        }
    ],
    "sg:phone":"+44 20 7636 1303",
    "sg:postcode":"W1T 1JQ",
    "sg:province":"Greater London",
    "sg:tags":[
        "graphic",
        "designer"
    ],
    "wof:name":"Frameline Productions Ltd.",
    "wof:placetype":"venue"
},
  "geometry": {"coordinates":[-0.1340730041,51.5175132751],"type":"Point"}
}