{
  "type": "Feature",
  "properties": {
    "addr:full":"19 Jbilee Drive Loughborough Leicestershire LE11 5TS",
    "addr:housenumber":"19",
    "addr:postcode":"le11 5ts",
    "addr:street":"Jbilee Drive",
    "iso:country":"GB",
    "sg:address":"19 Jbilee Drive",
    "sg:city":"Loughborough",
    "sg:classifiers":[
        {
            "category":"Shopping",
            "subcategory":"Stationery & Office Supplies",
            "type":"Retail Goods"
        }
    ],
    "sg:phone":"+44 1509 211811",
    "sg:postcode":"LE11 5TS",
    "sg:province":"Leicestershire",
    "wof:name":"D P I-Systems Ltd.",
    "wof:placetype":"venue"
},
  "geometry": {"coordinates":[-1.208921,52.780331],"type":"Point"}
}