{
  "type": "Feature",
  "properties": {
    "iso:country":"GB",
    "sg:address":"Prescriptions, Dovercourt Surgery, 309 City Rd",
    "sg:city":"Sheffield",
    "sg:classifiers":[
        {
            "category":"Health Services",
            "subcategory":"Doctor",
            "type":"Services"
        }
    ],
    "sg:phone":"+44 114 270 0976",
    "sg:postcode":"S2 5HJ",
    "sg:province":"South Yorkshire",
    "sg:tags":[
        "practitioners"
    ],
    "wof:name":"Brown, M",
    "wof:placetype":"venue"
},
  "geometry": {"coordinates":[-1.4451999664,53.3733100891],"type":"Point"}
}