{
  "type": "Feature",
  "properties": {
    "addr:full":"17 St Owen Street Hereford Herefordshire HR1 2JB",
    "addr:housenumber":"17",
    "addr:postcode":"hr1 2jb",
    "addr:street":"St Owen Street",
    "iso:country":"GB",
    "sg:address":"17 St Owen Street",
    "sg:city":"Hereford",
    "sg:classifiers":[
        {
            "category":"Government",
            "subcategory":"Office",
            "type":"Public Place"
        }
    ],
    "sg:phone":"+44 1432 273353",
    "sg:postcode":"HR1 2JB",
    "sg:province":"Herefordshire",
    "sg:tags":[
        "local"
    ],
    "wof:name":"Leader Ii Teme Valley",
    "wof:placetype":"venue"
},
  "geometry": {"coordinates":[-2.7133591175,52.0558509827],"type":"Point"}
}