{
  "type": "Feature",
  "properties": {
    "addr:full":"Mantle Lane, Coalville Leicester Leicestershire LE67 3DW",
    "addr:postcode":"le67 3dw",
    "addr:street":"Mantle Lane",
    "iso:country":"GB",
    "sg:address":"Mantle Lane, Coalville",
    "sg:city":"Leicester",
    "sg:classifiers":[
        {
            "category":"Conference Center",
            "type":"Public Place"
        }
    ],
    "sg:phone":"+44 1530 839531",
    "sg:postcode":"LE67 3DW",
    "sg:province":"Leicestershire",
    "sg:tags":[
        "business",
        "centre"
    ],
    "wof:name":"The Springboard Centre (Coalville) Ltd.",
    "wof:placetype":"venue"
},
  "geometry": {"coordinates":[-1.3723059893,52.7187843323],"type":"Point"}
}