{
  "type": "Feature",
  "properties": {
    "addr:full":"20 Hunloke Road Chesterfield Derbyshire S40 2NU",
    "addr:housenumber":"20",
    "addr:postcode":"s40 2nu",
    "addr:street":"Hunloke Road",
    "iso:country":"GB",
    "sg:address":"20 Hunloke Road",
    "sg:city":"Chesterfield",
    "sg:classifiers":[
        {
            "category":"Personal",
            "subcategory":"Beauty Salon",
            "type":"Services"
        }
    ],
    "sg:postcode":"S40 2NU",
    "sg:province":"Derbyshire",
    "sg:tags":[
        "unisex",
        "hairdresser"
    ],
    "wof:name":"Margaret",
    "wof:placetype":"venue"
},
  "geometry": {"coordinates":[-1.437433,53.229465],"type":"Point"}
}