{
  "type": "Feature",
  "properties": {
    "iso:country":"GB",
    "sg:address":"47 Castle Street",
    "sg:city":"Liverpool",
    "sg:classifiers":[
        {
            "category":"Real Estate",
            "subcategory":"Real Estate Agent",
            "type":"Services"
        }
    ],
    "sg:postcode":"L2 9TQ",
    "sg:province":"Merseyside",
    "wof:name":"The District Estates Ltd.",
    "wof:placetype":"venue"
},
  "geometry": {"coordinates":[-2.990311,53.405712],"type":"Point"}
}