{
  "type": "Feature",
  "properties": {
    "iso:country":"GB",
    "sg:address":"The Chantry, Hadham Rd",
    "sg:city":"Bishop's Stortford",
    "sg:classifiers":[
        {
            "category":"Home & Garden",
            "subcategory":"Home Furnishings",
            "type":"Retail Goods"
        }
    ],
    "sg:phone":"+44 1279 465010",
    "sg:postcode":"CM23 2QR",
    "sg:province":"Essex",
    "sg:tags":[
        "furnishers",
        "planner",
        "kitchen"
    ],
    "wof:name":"In-toto Kitchens",
    "wof:placetype":"venue"
},
  "geometry": {"coordinates":[0.1579400003,51.8729515076],"type":"Point"}
}