{
  "type": "Feature",
  "properties": {
    "addr:full":"59 Coronation Rd, Crosby Liverpool Merseyside L23 5RE",
    "addr:housenumber":"59",
    "addr:postcode":"l23 5re",
    "addr:street":"Coronation Rd",
    "iso:country":"GB",
    "sg:address":"59 Coronation Rd, Crosby",
    "sg:city":"Liverpool",
    "sg:classifiers":[
        {
            "category":"Communications",
            "type":"Services"
        }
    ],
    "sg:phone":"+44 151 924 7701",
    "sg:postcode":"L23 5RE",
    "sg:province":"Merseyside",
    "sg:tags":[
        "tv",
        "video",
        "radio"
    ],
    "wof:name":"Sound & Vision",
    "wof:placetype":"venue"
},
  "geometry": {"coordinates":[-3.0283060074,53.4904022217],"type":"Point"}
}