{
  "type": "Feature",
  "properties": {
    "addr:full":"9 Bridgwater Court, Oldmixon Crescent Weston-super-mare Somerset BS24 9AY",
    "addr:postcode":"bs24 9ay",
    "addr:street":"Bridgwater Court Oldmixon Crescent",
    "iso:country":"GB",
    "sg:address":"9 Bridgwater Court, Oldmixon Crescent",
    "sg:city":"Weston-super-mare",
    "sg:classifiers":[
        {
            "category":"Home & Garden",
            "subcategory":"Home Furnishings",
            "type":"Retail Goods"
        }
    ],
    "sg:phone":"+44 1934 413456",
    "sg:postcode":"BS24 9AY",
    "sg:province":"Somerset",
    "sg:tags":[
        "furnishers",
        "planner",
        "kitchen"
    ],
    "wof:name":"Boulevard Kitchen & Appliance Centre Ltd.",
    "wof:placetype":"venue"
},
  "geometry": {"coordinates":[-2.957914114,51.3271064758],"type":"Point"}
}