{
  "type": "Feature",
  "properties": {
    "addr:full":"Prospect Ho, 25 The Spain Petersfield Hampshire GU32 3JZ",
    "addr:housenumber":"25;spain",
    "addr:postcode":"gu32 3jz",
    "addr:street":"The",
    "iso:country":"GB",
    "sg:address":"Prospect Ho, 25 The Spain",
    "sg:city":"Petersfield",
    "sg:classifiers":[
        {
            "category":"Manufacturing",
            "subcategory":"Wood Products",
            "type":"Manufacturing & Wholesale Goods"
        }
    ],
    "sg:postcode":"GU32 3JZ",
    "sg:province":"Hampshire",
    "sg:tags":[
        "maker",
        "cabinet"
    ],
    "wof:name":"Hart,Robin,",
    "wof:placetype":"venue"
},
  "geometry": {"coordinates":[-0.945779,51.005039],"type":"Point"}
}