{
  "type": "Feature",
  "properties": {
    "iso:country":"GB",
    "sg:address":"Prospect Ho, 25 The Spain",
    "sg:city":"Petersfield",
    "sg:classifiers":[
        {
            "category":"Manufacturing",
            "subcategory":"Wood Products",
            "type":"Manufacturing & Wholesale Goods"
        }
    ],
    "sg:postcode":"GU32 3JZ",
    "sg:province":"Hampshire",
    "sg:tags":[
        "maker",
        "cabinet"
    ],
    "wof:name":"Hart,Robin,",
    "wof:placetype":"venue"
},
  "geometry": {"coordinates":[-0.945779,51.005039],"type":"Point"}
}