{
  "type": "Feature",
  "properties": {
    "addr:full":"Brome Eye Norfolk IP21 4BB",
    "addr:postcode":"ip21 4bb",
    "iso:country":"GB",
    "sg:address":"Brome",
    "sg:city":"Eye",
    "sg:classifiers":[
        {
            "category":"Retail",
            "subcategory":"Auto Repair",
            "type":"Services"
        }
    ],
    "sg:phone":"+44 1379 740248",
    "sg:postcode":"IP21 4BB",
    "sg:province":"Norfolk",
    "sg:tags":[
        "modification",
        "garage",
        "related"
    ],
    "wof:name":"Devils Handbasin Garage",
    "wof:placetype":"venue"
},
  "geometry": {"coordinates":[1.1461349726,52.3294410706],"type":"Point"}
}