{
  "type": "Feature",
  "properties": {
    "addr:full":"London House, Oxford Road High Wycombe Buckinghamshire HP14 3SX",
    "addr:postcode":"hp14 3sx",
    "addr:street":"Oxford Road",
    "iso:country":"GB",
    "sg:address":"London House, Oxford Road",
    "sg:city":"High Wycombe",
    "sg:classifiers":[
        {
            "category":"Government",
            "subcategory":"Post Office",
            "type":"Public Place"
        }
    ],
    "sg:phone":"+44 845 722 3344",
    "sg:postcode":"HP14 3SX",
    "sg:province":"Buckinghamshire",
    "wof:name":"Stockenchurch Post Office",
    "wof:placetype":"venue"
},
  "geometry": {"coordinates":[-0.833164,51.641525],"type":"Point"}
}