{
  "type": "Feature",
  "properties": {
    "iso:country":"GB",
    "sg:address":"44 Uxbridge St",
    "sg:city":"Kensington",
    "sg:classifiers":[
        {
            "category":"Real Estate",
            "subcategory":"Architect",
            "type":"Services"
        }
    ],
    "sg:phone":"+44 20 7229 9520",
    "sg:postcode":"W8 7TG",
    "sg:province":"Greater London",
    "wof:name":"Barry Russell",
    "wof:placetype":"venue"
},
  "geometry": {"coordinates":[-0.196679,51.508583],"type":"Point"}
}