{
  "type": "Feature",
  "properties": {
    "iso:country":"GB",
    "sg:address":"Suite 32 Challenge House, Sherwood Drive, Bletchley",
    "sg:city":"Milton Keynes",
    "sg:classifiers":[
        {
            "category":"Shopping",
            "subcategory":"Stationery & Office Supplies",
            "type":"Retail Goods"
        }
    ],
    "sg:phone":"+44 1908 366033",
    "sg:postcode":"MK3 6DR",
    "sg:province":"Buckinghamshire",
    "sg:tags":[
        "merchant",
        "paper"
    ],
    "wof:name":"Premier Paper Group",
    "wof:placetype":"venue"
},
  "geometry": {"coordinates":[-0.7381759882,51.9985198975],"type":"Point"}
}