{
  "type": "Feature",
  "properties": {
    "iso:country":"GB",
    "sg:address":"26 Jacinth Drive, Bobbing",
    "sg:city":"Sittingbourne",
    "sg:classifiers":[
        {
            "category":"Professional",
            "subcategory":"Computer Services",
            "type":"Services"
        }
    ],
    "sg:postcode":"ME10 5JA",
    "sg:province":"Kent",
    "sg:tags":[
        "consultant"
    ],
    "wof:name":"Bridgwater Ltd",
    "wof:placetype":"venue"
},
  "geometry": {"coordinates":[0.7379099727,51.3408203125],"type":"Point"}
}