{
  "type": "Feature",
  "properties": {
    "addr:full":"35 Pinnington Road Prescot Cheshire L35 3TY",
    "addr:housenumber":"35",
    "addr:postcode":"l35 3ty",
    "addr:street":"Pinnington Road",
    "iso:country":"GB",
    "sg:address":"35 Pinnington Road",
    "sg:city":"Prescot",
    "sg:classifiers":[
        {
            "category":"Professional",
            "type":"Services"
        }
    ],
    "sg:phone":"+44 151 493 2138",
    "sg:postcode":"L35 3TY",
    "sg:province":"Cheshire",
    "sg:tags":[
        "entertainer"
    ],
    "wof:name":"Night-Time Entertainments",
    "wof:placetype":"venue"
},
  "geometry": {"coordinates":[-2.7965700626,53.4142494202],"type":"Point"}
}