{
  "type": "Feature",
  "properties": {
    "iso:country":"GB",
    "sg:address":"29 Castle Street",
    "sg:city":"Conwy",
    "sg:classifiers":[
        {
            "category":"Professional",
            "subcategory":"Accounting & Tax Preparation",
            "type":"Services"
        }
    ],
    "sg:phone":"+44 1492 593345",
    "sg:postcode":"LL32 8AY",
    "sg:province":"Conwy",
    "sg:tags":[
        "accountant"
    ],
    "wof:name":"Gareth Hughes & Co",
    "wof:placetype":"venue"
},
  "geometry": {"coordinates":[-3.826988,53.28088],"type":"Point"}
}