{
  "type": "Feature",
  "properties": {
    "addr:full":"Unit 10 Underwood Business Park, Underwood La Crewe Cheshire CW1 3TJ",
    "addr:housenumber":"unit 10;business",
    "addr:postcode":"cw1 3tj",
    "addr:street":"Park Underwood La Crewe",
    "iso:country":"GB",
    "sg:address":"Unit 10 Underwood Business Park, Underwood La",
    "sg:city":"Crewe",
    "sg:classifiers":[
        {
            "category":"Manufacturing",
            "subcategory":"Wood Products",
            "type":"Manufacturing & Wholesale Goods"
        }
    ],
    "sg:phone":"+44 1270 212136",
    "sg:postcode":"CW1 3TJ",
    "sg:province":"Cheshire",
    "sg:tags":[
        "packaging",
        "crate",
        "pallets"
    ],
    "wof:name":"Cliffe Industrial Fabrics Ltd",
    "wof:placetype":"venue"
},
  "geometry": {"coordinates":[-2.446105,53.100578],"type":"Point"}
}