{
  "type": "Feature",
  "properties": {
    "addr:full":"The Garage, Llanrhaeadr Denbigh Conwy LL16 4PF",
    "addr:postcode":"ll16 4pf",
    "addr:street":"Denbigh",
    "iso:country":"GB",
    "sg:address":"The Garage, Llanrhaeadr",
    "sg:city":"Denbigh",
    "sg:classifiers":[
        {
            "category":"Building & Trades",
            "subcategory":"Construction",
            "type":"Services"
        }
    ],
    "sg:phone":"+44 1745 890688",
    "sg:postcode":"LL16 4PF",
    "sg:province":"Conwy",
    "sg:tags":[
        "equipment"
    ],
    "wof:name":"Mike Terzo",
    "wof:placetype":"venue"
},
  "geometry": {"coordinates":[-3.3733239174,53.1590652466],"type":"Point"}
}