{
  "type": "Feature",
  "properties": {
    "addr:full":"The Gables, Broadoak Bridport Dorset DT6 5NL",
    "addr:postcode":"dt6 5nl",
    "iso:country":"GB",
    "sg:address":"The Gables, Broadoak",
    "sg:city":"Bridport",
    "sg:classifiers":[
        {
            "category":"Professional",
            "subcategory":"Printing & Photocopies",
            "type":"Services"
        }
    ],
    "sg:phone":"+44 1308 423411",
    "sg:postcode":"DT6 5NL",
    "sg:province":"Dorset",
    "sg:tags":[
        "printer"
    ],
    "wof:name":"Creeds The Printers",
    "wof:placetype":"venue"
},
  "geometry": {"coordinates":[-2.8025329113,50.7664413452],"type":"Point"}
}