{
  "type": "Feature",
  "properties": {
    "iso:country":"GB",
    "sg:address":"Waterside, Framilode Passage, Saul",
    "sg:city":"Gloucester",
    "sg:classifiers":[
        {
            "category":"Building & Trades",
            "subcategory":"Cleaning & Sanitation",
            "type":"Services"
        }
    ],
    "sg:phone":"+44 1452 740502",
    "sg:postcode":"GL2 7LF",
    "sg:province":"Gloucestershire",
    "sg:tags":[
        "commercial",
        "sweep",
        "chimney"
    ],
    "wof:name":"N J Bowkett",
    "wof:placetype":"venue"
},
  "geometry": {"coordinates":[-2.372701,51.792171],"type":"Point"}
}