{
  "type": "Feature",
  "properties": {
    "addr:full":"89 Crayford Rd Holloway Greater London N7 0NE",
    "addr:housenumber":"89",
    "addr:postcode":"n7 0ne",
    "addr:street":"Crayford Rd",
    "iso:country":"GB",
    "sg:address":"89 Crayford Rd",
    "sg:city":"Holloway",
    "sg:classifiers":[
        {
            "category":"Military Area",
            "subcategory":"Air Force Base",
            "type":"Public Place"
        }
    ],
    "sg:phone":"+44 20 7607 4282",
    "sg:postcode":"N7 0NE",
    "sg:province":"Greater London",
    "sg:tags":[
        "taxi",
        "hire",
        "private"
    ],
    "wof:name":"Crayford Taxi Garage",
    "wof:placetype":"venue"
},
  "geometry": {"coordinates":[-0.125769,51.556419],"type":"Point"}
}