{
  "type": "Feature",
  "properties": {
    "iso:country":"GB",
    "sg:address":"87 Queen Street",
    "sg:city":"Cardiff",
    "sg:classifiers":[
        {
            "category":"Shopping",
            "subcategory":"Clothing, Apparel, & Fashions",
            "type":"Retail Goods"
        }
    ],
    "sg:phone":"+44 29 2022 9051",
    "sg:postcode":"CF10 2BE",
    "sg:province":"Cardiff",
    "sg:tags":[
        "shop"
    ],
    "wof:name":"River Island Clothing Co. Ltd.",
    "wof:placetype":"venue"
},
  "geometry": {"coordinates":[-3.1802,51.486301],"type":"Point"}
}