{
  "type": "Feature",
  "properties": {
    "addr:full":"Smithy House, Lundie Dundee Dundee City DD2 5NW",
    "addr:postcode":"dd2 5nw",
    "addr:street":"Lundie",
    "iso:country":"GB",
    "sg:address":"Smithy House, Lundie",
    "sg:city":"Dundee",
    "sg:classifiers":[
        {
            "category":"Professional",
            "subcategory":"Engineering",
            "type":"Services"
        }
    ],
    "sg:phone":"+44 1382 581378",
    "sg:postcode":"DD2 5NW",
    "sg:province":"Dundee City",
    "sg:tags":[
        "electrical",
        "engineer"
    ],
    "wof:name":"Mobile Electronic Repair Service",
    "wof:placetype":"venue"
},
  "geometry": {"coordinates":[-3.1544749737,56.5160751343],"type":"Point"}
}