{
  "type": "Feature",
  "properties": {
    "addr:full":"Ground Floor, Bridge Works, Southwark Street Nottingham Nottinghamshire NG6 0DA",
    "addr:postcode":"ng6 0da",
    "addr:street":"Ground Floor Bridge Works Southwark Street",
    "iso:country":"GB",
    "sg:address":"Ground Floor, Bridge Works, Southwark Street",
    "sg:city":"Nottingham",
    "sg:classifiers":[
        {
            "category":"Shopping",
            "subcategory":"Thrift Store",
            "type":"Retail Goods"
        }
    ],
    "sg:phone":"+44 115 942 4619",
    "sg:postcode":"NG6 0DA",
    "sg:province":"Nottinghamshire",
    "sg:tags":[
        "shop",
        "charity"
    ],
    "wof:name":"Mary Magdalen Foundation",
    "wof:placetype":"venue"
},
  "geometry": {"coordinates":[-1.18068,52.98605],"type":"Point"}
}