{
  "type": "Feature",
  "properties": {
    "addr:full":"Huntsman Drive, Northbank Industrial Estate, Irlam Manchester Greater Manchester M44 5EG",
    "addr:postcode":"m44 5eg",
    "addr:street":"Huntsman Drive Northbank Industrial Estate",
    "iso:country":"GB",
    "sg:address":"Huntsman Drive, Northbank Industrial Estate, Irlam",
    "sg:city":"Manchester",
    "sg:classifiers":[
        {
            "category":"Bus Stop",
            "subcategory":"None",
            "type":"Transportation"
        }
    ],
    "sg:phone":"+44 161 777 9500",
    "sg:postcode":"M44 5EG",
    "sg:province":"Greater Manchester",
    "sg:tags":[
        "filter"
    ],
    "wof:name":"Allied Filter Products Ltd.",
    "wof:placetype":"venue"
},
  "geometry": {"coordinates":[-2.426136,53.435112],"type":"Point"}
}