{
  "type": "Feature",
  "properties": {
    "iso:country":"GB",
    "sg:address":"26 Market Street",
    "sg:city":"Ebbw Vale",
    "sg:classifiers":[
        {
            "category":"Food & Beverages",
            "subcategory":"Liquor & Beverages",
            "type":"Retail Goods"
        }
    ],
    "sg:phone":"+44 1495 350235",
    "sg:postcode":"NP23 6HL",
    "sg:province":"Blaenau Gwent",
    "sg:tags":[
        "beer",
        "spirit",
        "wines"
    ],
    "wof:name":"First Quench Retailing Ltd.",
    "wof:placetype":"venue"
},
  "geometry": {"coordinates":[-3.205969,51.781429],"type":"Point"}
}