{
  "type": "Feature",
  "properties": {
    "iso:country":"GB",
    "sg:address":"Unit 3a, Parkdale Ind Est, Howley",
    "sg:city":"Warrington",
    "sg:classifiers":[
        {
            "category":"Building & Trades",
            "subcategory":"Construction",
            "type":"Services"
        }
    ],
    "sg:phone":"+44 1925 445715",
    "sg:postcode":"WA1 2RT",
    "sg:province":"Cheshire",
    "sg:tags":[
        "roofing"
    ],
    "wof:name":"M Baker",
    "wof:placetype":"venue"
},
  "geometry": {"coordinates":[-2.5805981159,53.385269165],"type":"Point"}
}