{
  "type": "Feature",
  "properties": {
    "iso:country":"GB",
    "sg:address":"135 Stockwell Road",
    "sg:city":"London",
    "sg:classifiers":[
        {
            "category":"Social Services",
            "subcategory":"Job Training",
            "type":"Services"
        }
    ],
    "sg:phone":"+44 20 7737 6260",
    "sg:postcode":"SW9 9TN",
    "sg:province":"Greater London",
    "sg:tags":[
        "translator",
        "interpreter"
    ],
    "wof:name":"J C Portuguese Community",
    "wof:placetype":"venue"
},
  "geometry": {"coordinates":[-0.1174869984,51.467212677],"type":"Point"}
}