{
  "type": "Feature",
  "properties": {
    "iso:country":"GB",
    "sg:address":"54 Bell Street",
    "sg:city":"Princes Risborough",
    "sg:classifiers":[
        {
            "category":"Personal",
            "subcategory":"Barber",
            "type":"Services"
        }
    ],
    "sg:phone":"+44 1844 347492",
    "sg:postcode":"HP27 0AD",
    "sg:province":"Buckinghamshire",
    "sg:tags":[
        "men's",
        "gents",
        "hairdresser"
    ],
    "wof:name":"Classic Barbers",
    "wof:placetype":"venue"
},
  "geometry": {"coordinates":[-0.8301590085,51.7228775024],"type":"Point"}
}