{
  "type": "Feature",
  "properties": {
    "iso:country":"GB",
    "sg:address":"Arden House, 172 Manchester Road",
    "sg:city":"Bury",
    "sg:classifiers":[
        {
            "category":"Education",
            "subcategory":"School",
            "type":"Public Place"
        }
    ],
    "sg:phone":"+44 161 764 2346",
    "sg:postcode":"BL9 9BH",
    "sg:province":"Lancashire",
    "sg:tags":[
        "independent",
        "preparatory"
    ],
    "wof:name":"Bury Catholic Preparatory School Ltd.",
    "wof:placetype":"venue"
},
  "geometry": {"coordinates":[-2.299099,53.583561],"type":"Point"}
}