{
  "type": "Feature",
  "properties": {
    "iso:country":"GB",
    "sg:address":"16 Boswedden Terrace, St Just",
    "sg:city":"Penzance",
    "sg:classifiers":[
        {
            "category":"Building & Trades",
            "subcategory":"Landscaping Services",
            "type":"Services"
        }
    ],
    "sg:postcode":"TR19 7NF",
    "sg:province":"Cornwall",
    "sg:tags":[
        "forestry",
        "tree"
    ],
    "wof:name":"A & M Common",
    "wof:placetype":"venue"
},
  "geometry": {"coordinates":[-5.689679,50.12484],"type":"Point"}
}