{
  "type": "Feature",
  "properties": {
    "addr:full":"Watnall Road, Hucknall Nottingham Nottinghamshire NG15 6DW",
    "addr:postcode":"ng15 6dw",
    "addr:street":"Watnall Road",
    "iso:country":"GB",
    "sg:address":"Watnall Road, Hucknall",
    "sg:city":"Nottingham",
    "sg:classifiers":[
        {
            "category":"Utilities",
            "type":"Services"
        }
    ],
    "sg:phone":"+44 115 964 0040",
    "sg:postcode":"NG15 6DW",
    "sg:province":"Nottinghamshire",
    "sg:tags":[
        "connection",
        "provider",
        "internet"
    ],
    "wof:name":"Easisurf Ltd.",
    "wof:placetype":"venue"
},
  "geometry": {"coordinates":[-1.209909,53.031876],"type":"Point"}
}