{
  "type": "Feature",
  "properties": {
    "iso:country":"GB",
    "sg:address":"Tott Farm, Hassocks Road",
    "sg:city":"Hassocks",
    "sg:classifiers":[
        {
            "category":"Farming",
            "subcategory":"Farm",
            "type":"Manufacturing & Wholesale Goods"
        }
    ],
    "sg:postcode":"BN6 9QW",
    "sg:province":"East Sussex",
    "sg:tags":[
        "mixed",
        "crop"
    ],
    "wof:name":"Donald G Blake",
    "wof:placetype":"venue"
},
  "geometry": {"coordinates":[-0.1402689964,50.9239959717],"type":"Point"}
}