{
  "type": "Feature",
  "properties": {
    "iso:country":"GB",
    "sg:address":"Tai Ffolt, Mynydd Nefyn",
    "sg:city":"Pwllheli",
    "sg:classifiers":[
        {
            "category":"Wholesale",
            "subcategory":"Medical Equipment & Supplies",
            "type":"Manufacturing & Wholesale Goods"
        }
    ],
    "sg:phone":"+44 1758 721255",
    "sg:postcode":"LL53 6TW",
    "sg:province":"Gwynedd",
    "sg:tags":[
        "hospital"
    ],
    "wof:name":"Sheridan Fabrics of Wales",
    "wof:placetype":"venue"
},
  "geometry": {"coordinates":[-4.498009,52.927368],"type":"Point"}
}