{
  "type": "Feature",
  "properties": {
    "addr:full":"Lower Milehouse Lane Newcastle Staffordshire ST5 9BQ",
    "addr:postcode":"st5 9bq",
    "addr:street":"Lower Milehouse Lane",
    "iso:country":"GB",
    "sg:address":"Lower Milehouse Lane",
    "sg:city":"Newcastle",
    "sg:classifiers":[
        {
            "category":"Retail",
            "subcategory":"Auto Repair",
            "type":"Services"
        }
    ],
    "sg:phone":"+44 1782 712299",
    "sg:postcode":"ST5 9BQ",
    "sg:province":"Staffordshire",
    "sg:tags":[
        "car",
        "upholsterer"
    ],
    "wof:name":"Collins & Aikman Automotive Carpet Products (U K) Ltd.",
    "wof:placetype":"venue"
},
  "geometry": {"coordinates":[-2.2349441051,53.0248413086],"type":"Point"}
}