{
  "type": "Feature",
  "properties": {
    "iso:country":"GB",
    "sg:address":"10 Mountbatten Avenue",
    "sg:city":"Romsey",
    "sg:classifiers":[
        {
            "category":"Wholesale",
            "subcategory":"Toys & Hobbies",
            "type":"Manufacturing & Wholesale Goods"
        }
    ],
    "sg:postcode":"SO51 8DZ",
    "sg:province":"Hampshire",
    "sg:tags":[
        "balloon",
        "novelty"
    ],
    "wof:name":"Balloon Fantasia",
    "wof:placetype":"venue"
},
  "geometry": {"coordinates":[-1.493599,50.991444],"type":"Point"}
}