{
  "type": "Feature",
  "properties": {
    "addr:full":"30 Foundry Lane, Caeglas Welshpool Shropshire SY21 7TR",
    "addr:housenumber":"30",
    "addr:postcode":"sy21 7tr",
    "addr:street":"Foundry Lane Caeglas",
    "iso:country":"GB",
    "sg:address":"30 Foundry Lane, Caeglas",
    "sg:city":"Welshpool",
    "sg:classifiers":[
        {
            "category":"Building & Trades",
            "subcategory":"Construction",
            "type":"Services"
        }
    ],
    "sg:phone":"+44 1933 855482",
    "sg:postcode":"SY21 7TR",
    "sg:province":"Shropshire",
    "sg:tags":[
        "welder"
    ],
    "wof:name":"Steven Thomas Kaye",
    "wof:placetype":"venue"
},
  "geometry": {"coordinates":[-3.1383519173,52.6608009338],"type":"Point"}
}