{
  "type": "Feature",
  "properties": {
    "addr:full":"38 Whitfield Terrace Dundee Dundee City DD4 0BR",
    "addr:housenumber":"38",
    "addr:postcode":"dd4 0br",
    "addr:street":"Whitfield Terrace",
    "iso:country":"GB",
    "sg:address":"38 Whitfield Terrace",
    "sg:city":"Dundee",
    "sg:classifiers":[
        {
            "category":"Food & Beverages",
            "subcategory":"Supermarket",
            "type":"Retail Goods"
        },
        {
            "category":"Food & Beverages",
            "subcategory":"Groceries & Convenience Stores",
            "type":"Retail Goods"
        }
    ],
    "sg:phone":"+44 1382 508994",
    "sg:postcode":"DD4 0BR",
    "sg:province":"Dundee City",
    "sg:tags":[
        "grocer"
    ],
    "wof:name":"Ahmad Grocers",
    "wof:placetype":"venue"
},
  "geometry": {"coordinates":[-2.9228210449,56.4879760742],"type":"Point"}
}