{
  "type": "Feature",
  "properties": {
    "addr:full":"50 Wykeham Park Thame Buckinghamshire OX9 3JU",
    "addr:housenumber":"50",
    "addr:postcode":"ox9 3ju",
    "addr:street":"Wykeham Park",
    "iso:country":"GB",
    "sg:address":"50 Wykeham Park",
    "sg:city":"Thame",
    "sg:classifiers":[
        {
            "category":"Building & Trades",
            "subcategory":"Construction",
            "type":"Services"
        },
        {
            "category":"Sports & Exercise",
            "subcategory":"Playing Field",
            "type":"Entertainment"
        }
    ],
    "sg:phone":"+44 1844 214239",
    "sg:postcode":"OX9 3JU",
    "sg:province":"Buckinghamshire",
    "sg:tags":[
        "conservation",
        "builder",
        "thatching",
        "craft",
        "related"
    ],
    "wof:name":"William John Cross",
    "wof:placetype":"venue"
},
  "geometry": {"coordinates":[-0.971066,51.744831],"type":"Point"}
}