{
  "type": "Feature",
  "properties": {
    "addr:full":"1 Park Square East Leeds West Yorkshire LS1 2NE",
    "addr:housenumber":"1",
    "addr:postcode":"ls1 2ne",
    "addr:street":"Park Square East Leeds West",
    "iso:country":"GB",
    "sg:address":"1 Park Square East",
    "sg:city":"Leeds",
    "sg:classifiers":[
        {
            "category":"Professional",
            "subcategory":"Management & Consulting",
            "type":"Services"
        }
    ],
    "sg:phone":"+44 113 246 5017",
    "sg:postcode":"LS1 2NE",
    "sg:province":"West Yorkshire",
    "sg:tags":[
        "consultant",
        "business"
    ],
    "wof:name":"Red Uk",
    "wof:placetype":"venue"
},
  "geometry": {"coordinates":[-1.5506249666,53.7994728088],"type":"Point"}
}