{
  "type": "Feature",
  "properties": {
    "addr:full":"10 Greyhound Street Nottingham Nottinghamshire NG1 2DP",
    "addr:housenumber":"10",
    "addr:postcode":"ng1 2dp",
    "addr:street":"Greyhound Street",
    "iso:country":"GB",
    "sg:address":"10 Greyhound Street",
    "sg:city":"Nottingham",
    "sg:classifiers":[
        {
            "category":"Shopping",
            "subcategory":"Baby Store",
            "type":"Retail Goods"
        }
    ],
    "sg:postcode":"NG1 2DP",
    "sg:province":"Nottinghamshire",
    "sg:tags":[
        "babywear",
        "childrens"
    ],
    "wof:name":"Cashe",
    "wof:placetype":"venue"
},
  "geometry": {"coordinates":[-1.1494890451,52.9542503357],"type":"Point"}
}