{
  "type": "Feature",
  "properties": {
    "iso:country":"GB",
    "sg:address":"10 The Precinct, Off Candleby Avenue",
    "sg:city":"Nottingham",
    "sg:classifiers":[
        {
            "category":"Food & Beverages",
            "subcategory":"Meat & Fish",
            "type":"Retail Goods"
        }
    ],
    "sg:phone":"+44 115 989 3518",
    "sg:postcode":"NG12 3JQ",
    "sg:province":"Nottinghamshire",
    "sg:tags":[
        "chip"
    ],
    "wof:name":"Cotgrave Fish Bar",
    "wof:placetype":"venue"
},
  "geometry": {"coordinates":[-1.0380899906,52.9048500061],"type":"Point"}
}