{
  "type": "Feature",
  "properties": {
    "iso:country":"GB",
    "sg:address":"31 Wyndham St",
    "sg:city":"Bridgend",
    "sg:classifiers":[
        {
            "category":"Shopping",
            "subcategory":"Baby Store",
            "type":"Retail Goods"
        }
    ],
    "sg:postcode":"CF31 1EB",
    "sg:province":"Bridgend",
    "sg:tags":[
        "nursery",
        "accessory"
    ],
    "wof:name":"Stephanie Frances Boutique Collection",
    "wof:placetype":"venue"
},
  "geometry": {"coordinates":[-3.577758,51.507801],"type":"Point"}
}