{
  "type": "Feature",
  "properties": {
    "iso:country":"GB",
    "sg:address":"10 Victoria Arc, Union St",
    "sg:city":"Ryde",
    "sg:classifiers":[
        {
            "category":"Shopping",
            "subcategory":"Books",
            "type":"Retail Goods"
        }
    ],
    "sg:phone":"+44 1983 812026",
    "sg:postcode":"PO33 2LQ",
    "sg:province":"Isle of Wight",
    "sg:tags":[
        "bookseller"
    ],
    "wof:name":"Pickwick Bookshops",
    "wof:placetype":"venue"
},
  "geometry": {"coordinates":[-1.164664,50.728619],"type":"Point"}
}