{
  "type": "Feature",
  "properties": {
    "iso:country":"GB",
    "sg:address":"134 Blackstock Road",
    "sg:city":"London",
    "sg:classifiers":[
        {
            "category":"Fast Food",
            "type":"Food & Drink"
        }
    ],
    "sg:postcode":"N4 2DX",
    "sg:province":"Greater London",
    "sg:tags":[
        "away",
        "take"
    ],
    "wof:name":"My Way Takeaway",
    "wof:placetype":"venue"
},
  "geometry": {"coordinates":[-0.0994559973,51.5612640381],"type":"Point"}
}