{
  "type": "Feature",
  "properties": {
    "addr:full":"Independent House Wallsend Tyne and Wear NE28 6AB",
    "addr:postcode":"ne28 6ab",
    "iso:country":"GB",
    "sg:address":"Independent House",
    "sg:city":"Wallsend",
    "sg:classifiers":[
        {
            "category":"Building & Trades",
            "subcategory":"Construction",
            "type":"Services"
        }
    ],
    "sg:phone":"+44 191 263 3654",
    "sg:postcode":"NE28 6AB",
    "sg:province":"Tyne and Wear",
    "sg:tags":[
        "platform",
        "work",
        "scaffolding"
    ],
    "wof:name":"Independent Scaffolding Ltd.",
    "wof:placetype":"venue"
},
  "geometry": {"coordinates":[-1.533224,54.99128],"type":"Point"}
}