{
  "type": "Feature",
  "properties": {
    "addr:full":"8 The Viaduct, St James Lane London Greater London N10 3QX",
    "addr:housenumber":"8",
    "addr:postcode":"n10 3qx",
    "addr:street":"The Viaduct St James Lane",
    "iso:country":"GB",
    "sg:address":"8 The Viaduct, St James Lane",
    "sg:city":"London",
    "sg:classifiers":[
        {
            "category":"Professional",
            "subcategory":"Printing & Photocopies",
            "type":"Services"
        }
    ],
    "sg:phone":"+44 20 8883 6518",
    "sg:postcode":"N10 3QX",
    "sg:province":"Greater London",
    "sg:tags":[
        "printer"
    ],
    "wof:name":"T White Printers",
    "wof:placetype":"venue"
},
  "geometry": {"coordinates":[-0.14169,51.58886],"type":"Point"}
}