{
  "type": "Feature",
  "properties": {
    "addr:full":"31 Bath St Ilkeston Derbyshire DE7 8BP",
    "addr:housenumber":"31",
    "addr:postcode":"de7 8bp",
    "addr:street":"Bath St",
    "iso:country":"GB",
    "sg:address":"31 Bath St",
    "sg:city":"Ilkeston",
    "sg:classifiers":[
        {
            "category":"Travel",
            "subcategory":"Travel Agent",
            "type":"Entertainment"
        }
    ],
    "sg:phone":"+44 115 944 0232",
    "sg:postcode":"DE7 8BP",
    "sg:province":"Derbyshire",
    "wof:name":"Woodcock Travel",
    "wof:placetype":"venue"
},
  "geometry": {"coordinates":[-1.309072,52.972816],"type":"Point"}
}