{
  "type": "Feature",
  "properties": {
    "iso:country":"GB",
    "sg:address":"16-18 Lansdowne Avenue",
    "sg:city":"Slough",
    "sg:classifiers":[
        {
            "category":"Health Services",
            "subcategory":"Doctor",
            "type":"Services"
        }
    ],
    "sg:phone":"+44 1753 533857",
    "sg:postcode":"SL1 3SJ",
    "sg:province":"Berkshire",
    "sg:tags":[
        "practitioners"
    ],
    "wof:name":"Dr M.L.H Kumar",
    "wof:placetype":"venue"
},
  "geometry": {"coordinates":[-0.6005280018,51.5117111206],"type":"Point"}
}