{
  "type": "Feature",
  "properties": {
    "addr:full":"5/7 Mill Street, Bedworth Nuneaton Warwickshire CV12 8JX",
    "addr:housenumber":"5 / 7",
    "addr:postcode":"cv12 8jx",
    "addr:street":"Mill Street",
    "iso:country":"GB",
    "sg:address":"5/7 Mill Street, Bedworth",
    "sg:city":"Nuneaton",
    "sg:classifiers":[
        {
            "category":"Community Center",
            "subcategory":"Social",
            "type":"Public Place"
        }
    ],
    "sg:phone":"+44 24 7631 8520",
    "sg:postcode":"CV12 8JX",
    "sg:province":"Warwickshire",
    "sg:tags":[
        "frozen",
        "food",
        "freezer",
        "centre"
    ],
    "wof:name":"Iceland Foods Plc",
    "wof:placetype":"venue"
},
  "geometry": {"coordinates":[-1.473851,52.480576],"type":"Point"}
}