{
  "type": "Feature",
  "properties": {
    "iso:country":"GB",
    "sg:address":"5 Greenacres Hillend Road, Twyning",
    "sg:city":"Tewkesbury",
    "sg:classifiers":[
        {
            "category":"Professional",
            "subcategory":"Accounting & Tax Preparation",
            "type":"Services"
        }
    ],
    "sg:postcode":"GL20 6JD",
    "sg:province":"Gloucestershire",
    "sg:tags":[
        "accountant"
    ],
    "wof:name":"Twyning Code Ltd",
    "wof:placetype":"venue"
},
  "geometry": {"coordinates":[-2.147644043,52.0293464661],"type":"Point"}
}