{
  "type": "Feature",
  "properties": {
    "addr:full":"Port Charlotte Port Charlotte Argyll and Bute PA48 7UD",
    "addr:postcode":"pa48 7ud",
    "iso:country":"GB",
    "sg:address":"Port Charlotte",
    "sg:city":"Port Charlotte",
    "sg:classifiers":[
        {
            "category":"Travel",
            "subcategory":"Hotels & Motels",
            "type":"Entertainment"
        }
    ],
    "sg:postcode":"PA48 7UD",
    "sg:province":"Argyll and Bute",
    "sg:tags":[
        "self",
        "catering"
    ],
    "wof:name":"Lorgba Holiday Cottages",
    "wof:placetype":"venue"
},
  "geometry": {"coordinates":[-6.379129,55.738575],"type":"Point"}
}