{
  "type": "Feature",
  "properties": {
    "addr:full":"Forge House, 34 High Street Broadway Gloucestershire WR12 7DT",
    "addr:housenumber":"34",
    "addr:postcode":"wr12 7dt",
    "addr:street":"High Street",
    "iso:country":"GB",
    "sg:address":"Forge House, 34 High Street",
    "sg:city":"Broadway",
    "sg:classifiers":[
        {
            "category":"Professional",
            "type":"Services"
        }
    ],
    "sg:postcode":"WR12 7DT",
    "sg:province":"Gloucestershire",
    "sg:tags":[
        "interior",
        "furnishers",
        "designer"
    ],
    "wof:name":"Interiors by Constance of Harfield",
    "wof:placetype":"venue"
},
  "geometry": {"coordinates":[-1.8615829945,52.0361328125],"type":"Point"}
}