{
  "type": "Feature",
  "properties": {
    "addr:full":"223 Albany Rd, Earlsdon Coventry West Midlands CV5 6NF",
    "addr:housenumber":"223",
    "addr:postcode":"cv5 6nf",
    "addr:street":"Albany Rd",
    "iso:country":"GB",
    "sg:address":"223 Albany Rd, Earlsdon",
    "sg:city":"Coventry",
    "sg:classifiers":[
        {
            "category":"Professional",
            "subcategory":"Art Services",
            "type":"Services"
        }
    ],
    "sg:phone":"+44 24 7667 4883",
    "sg:postcode":"CV5 6NF",
    "sg:province":"West Midlands",
    "sg:tags":[
        "picture",
        "restoration",
        "framing",
        "cleaning"
    ],
    "wof:name":"Friswells Picture Gallery",
    "wof:placetype":"venue"
},
  "geometry": {"coordinates":[-1.530162,52.399937],"type":"Point"}
}