{
  "type": "Feature",
  "properties": {
    "addr:full":"27 Castle Street Cirencester Gloucestershire GL7 1QD",
    "addr:housenumber":"27",
    "addr:postcode":"gl7 1qd",
    "addr:street":"Castle Street",
    "iso:country":"GB",
    "sg:address":"27 Castle Street",
    "sg:city":"Cirencester",
    "sg:classifiers":[
        {
            "category":"Fast Food",
            "type":"Food & Drink"
        },
        {
            "category":"Restaurant",
            "type":"Food & Drink"
        }
    ],
    "sg:phone":"+44 1285 653529",
    "sg:postcode":"GL7 1QD",
    "sg:province":"Gloucestershire",
    "sg:tags":[
        "away",
        "-",
        "take",
        "chinese"
    ],
    "sg:website":"http://www.tatyans.com",
    "wof:name":"Tatyans Restaurant",
    "wof:placetype":"venue"
},
  "geometry": {"coordinates":[-1.970298,51.716133],"type":"Point"}
}