{
  "type": "Feature",
  "properties": {
    "addr:full":"51 Holt Road, Higher Tranmere Birkenhead Merseyside CH41 9EW",
    "addr:housenumber":"51;tranmere",
    "addr:postcode":"ch41 9ew",
    "addr:street":"Holt Road",
    "iso:country":"GB",
    "sg:address":"51 Holt Road, Higher Tranmere",
    "sg:city":"Birkenhead",
    "sg:classifiers":[
        {
            "category":"Home & Garden",
            "subcategory":"Building Materials",
            "type":"Retail Goods"
        }
    ],
    "sg:phone":"+44 151 647 4536",
    "sg:postcode":"CH41 9EW",
    "sg:province":"Merseyside",
    "sg:tags":[
        "insulation",
        "installers"
    ],
    "wof:name":"Wirral Thermal Insulations Ltd.",
    "wof:placetype":"venue"
},
  "geometry": {"coordinates":[-3.020016,53.380768],"type":"Point"}
}