{
  "type": "Feature",
  "properties": {
    "addr:full":"Arndale House, Arndale Centre Headingley Leeds West Yorkshire LS6 2UU",
    "addr:postcode":"ls6 2uu",
    "addr:street":"Arndale Centre",
    "iso:country":"GB",
    "sg:address":"Arndale House, Arndale Centre Headingley",
    "sg:city":"Leeds",
    "sg:classifiers":[
        {
            "category":"Professional",
            "subcategory":"Advertising",
            "type":"Services"
        }
    ],
    "sg:phone":"+44 113 275 3399",
    "sg:postcode":"LS6 2UU",
    "sg:province":"West Yorkshire",
    "sg:tags":[
        "agency"
    ],
    "wof:name":"Cravens Advertising Ltd.",
    "wof:placetype":"venue"
},
  "geometry": {"coordinates":[-1.57869,53.822632],"type":"Point"}
}