{
  "type": "Feature",
  "properties": {
    "iso:country":"GB",
    "sg:address":"23a Guildhall St",
    "sg:city":"Lincoln",
    "sg:classifiers":[
        {
            "category":"Professional",
            "subcategory":"Employment Agencies",
            "type":"Services"
        }
    ],
    "sg:phone":"+44 1522 539888",
    "sg:postcode":"LN1 1TR",
    "sg:province":"Lincolnshire",
    "sg:tags":[
        "consultant"
    ],
    "wof:name":"Manpower Employment Services Co",
    "wof:placetype":"venue"
},
  "geometry": {"coordinates":[-0.541109,53.22942],"type":"Point"}
}