{
  "type": "Feature",
  "properties": {
    "addr:full":"241b Uppingham Road Leicester Leicestershire LE5 4DG",
    "addr:housenumber":"241b",
    "addr:postcode":"le5 4dg",
    "addr:street":"Uppingham Road",
    "iso:country":"GB",
    "sg:address":"241b Uppingham Road",
    "sg:city":"Leicester",
    "sg:classifiers":[
        {
            "category":"Shopping",
            "type":"Retail Goods"
        }
    ],
    "sg:phone":"+44 116 276 9292",
    "sg:postcode":"LE5 4DG",
    "sg:province":"Leicestershire",
    "sg:tags":[
        "part",
        "accessory"
    ],
    "wof:name":"Karr Parts",
    "wof:placetype":"venue"
},
  "geometry": {"coordinates":[-1.0899889469,52.6420555115],"type":"Point"}
}