{
  "type": "Feature",
  "properties": {
    "addr:full":"3 Borough (the) Hinckley Leicestershire LE10 1NL",
    "addr:housenumber":"3",
    "addr:postcode":"le10 1nl",
    "addr:street":"Borough The",
    "iso:country":"GB",
    "sg:address":"3 Borough (the)",
    "sg:city":"Hinckley",
    "sg:classifiers":[
        {
            "category":"Shopping",
            "subcategory":"Gifts & Souvenirs",
            "type":"Retail Goods"
        },
        {
            "category":"Professional",
            "subcategory":"Art Services",
            "type":"Services"
        }
    ],
    "sg:phone":"+44 1455 615364",
    "sg:postcode":"LE10 1NL",
    "sg:province":"Leicestershire",
    "sg:tags":[
        "shop",
        "framing"
    ],
    "wof:name":"Contactus",
    "wof:placetype":"venue"
},
  "geometry": {"coordinates":[-1.372799,52.541313],"type":"Point"}
}