{
  "type": "Feature",
  "properties": {
    "iso:country":"GB",
    "sg:address":"The Old Institute, Town Hall Sq",
    "sg:city":"Cowbridge",
    "sg:classifiers":[
        {
            "category":"Fast Food",
            "type":"Food & Drink"
        }
    ],
    "sg:phone":"+44 1446 773232",
    "sg:postcode":"CF71 7DD",
    "sg:province":"The Vale of Glamorgan",
    "sg:tags":[
        "away",
        "take"
    ],
    "wof:name":"China City",
    "wof:placetype":"venue"
},
  "geometry": {"coordinates":[-3.4504249096,51.4623908997],"type":"Point"}
}