{
  "type": "Feature",
  "properties": {
    "iso:country":"GB",
    "sg:address":"Crookham",
    "sg:city":"Berwick-upon-tweed",
    "sg:classifiers":[
        {
            "category":"Farming",
            "subcategory":"Dairy Farm",
            "type":"Manufacturing & Wholesale Goods"
        }
    ],
    "sg:phone":"+44 1890 820263",
    "sg:postcode":"TD15 2PX",
    "sg:province":"Northumberland",
    "wof:name":"Ford Dairy",
    "wof:placetype":"venue"
},
  "geometry": {"coordinates":[-2.08654,55.630089],"type":"Point"}
}