{
  "type": "Feature",
  "properties": {
    "addr:full":"Gable Ho, Church Rd, Wanborough Swindon Wiltshire SN4 0BZ",
    "addr:postcode":"sn4 0bz",
    "addr:street":"Church Rd",
    "iso:country":"GB",
    "sg:address":"Gable Ho, Church Rd, Wanborough",
    "sg:city":"Swindon",
    "sg:classifiers":[
        {
            "category":"Professional",
            "subcategory":"Business Services",
            "type":"Services"
        }
    ],
    "sg:postcode":"SN4 0BZ",
    "sg:province":"Wiltshire",
    "sg:tags":[
        "holding"
    ],
    "wof:name":"Business Performance (Holdings) Ltd",
    "wof:placetype":"venue"
},
  "geometry": {"coordinates":[-1.7006950378,51.5422477722],"type":"Point"}
}