{
  "type": "Feature",
  "properties": {
    "addr:full":"17 Monsal Avenue Ferndown Dorset BH22 8LA",
    "addr:housenumber":"17",
    "addr:postcode":"bh22 8la",
    "addr:street":"Monsal Avenue",
    "iso:country":"GB",
    "sg:address":"17 Monsal Avenue",
    "sg:city":"Ferndown",
    "sg:classifiers":[
        {
            "category":"Building & Trades",
            "subcategory":"Construction",
            "type":"Services"
        }
    ],
    "sg:postcode":"BH22 8LA",
    "sg:province":"Dorset",
    "sg:tags":[
        "joinery",
        "joiner",
        "carpenter",
        "carpentry"
    ],
    "wof:name":"Interior Fit Ltd.",
    "wof:placetype":"venue"
},
  "geometry": {"coordinates":[-1.8950510025,50.7935295105],"type":"Point"}
}