{
  "type": "Feature",
  "properties": {
    "addr:full":"4 Standard Street Crickhowell Monmouthshire NP8 1BP",
    "addr:housenumber":"4",
    "addr:postcode":"np8 1bp",
    "addr:street":"Standard Street",
    "iso:country":"GB",
    "sg:address":"4 Standard Street",
    "sg:city":"Crickhowell",
    "sg:classifiers":[
        {
            "category":"Food & Beverages",
            "subcategory":"Meat & Fish",
            "type":"Retail Goods"
        }
    ],
    "sg:phone":"+44 1873 810391",
    "sg:postcode":"NP8 1BP",
    "sg:province":"Monmouthshire",
    "sg:tags":[
        "chip"
    ],
    "wof:name":"Stephens Fish Bar",
    "wof:placetype":"venue"
},
  "geometry": {"coordinates":[-3.1361811161,51.8589897156],"type":"Point"}
}