{
  "type": "Feature",
  "properties": {
    "addr:full":"159 Rushey Grn London Greater London SE6 4BJ",
    "addr:housenumber":"159",
    "addr:postcode":"se6 4bj",
    "addr:street":"Rushey Grn",
    "iso:country":"GB",
    "sg:address":"159 Rushey Grn",
    "sg:city":"London",
    "sg:classifiers":[
        {
            "category":"Banks & Credit Unions",
            "subcategory":"Bank",
            "type":"Services"
        }
    ],
    "sg:phone":"+44 1322 294567",
    "sg:postcode":"SE6 4BJ",
    "sg:province":"Greater London",
    "wof:name":"National Westminster Bank Plc",
    "wof:placetype":"venue"
},
  "geometry": {"coordinates":[-0.0196189992,51.4453582764],"type":"Point"}
}