{
  "type": "Feature",
  "properties": {
    "addr:full":"1 Nuttall Street London Greater London N1 5LZ",
    "addr:housenumber":"1",
    "addr:postcode":"n1 5lz",
    "addr:street":"Nuttall Street",
    "iso:country":"GB",
    "sg:address":"1 Nuttall Street",
    "sg:city":"London",
    "sg:classifiers":[
        {
            "category":"Social Services",
            "type":"Services"
        }
    ],
    "sg:phone":"+44 20 7613 3560",
    "sg:postcode":"N1 5LZ",
    "sg:province":"Greater London",
    "wof:name":"Peggy Edwards Day Centre",
    "wof:placetype":"venue"
},
  "geometry": {"coordinates":[-0.077264,51.534534],"type":"Point"}
}