{
  "type": "Feature",
  "properties": {
    "addr:full":"Priory Drive Seaview Isle of Wight PO34 5EA",
    "addr:postcode":"po34 5ea",
    "addr:street":"Priory Drive",
    "iso:country":"GB",
    "sg:address":"Priory Drive",
    "sg:city":"Seaview",
    "sg:classifiers":[
        {
            "category":"Building & Trades",
            "subcategory":"Plumbing",
            "type":"Services"
        }
    ],
    "sg:phone":"+44 1983 616940",
    "sg:postcode":"PO34 5EA",
    "sg:province":"Isle of Wight",
    "sg:tags":[
        "central",
        "heating"
    ],
    "wof:name":"Heatco Ltd",
    "wof:placetype":"venue"
},
  "geometry": {"coordinates":[-1.110274,50.719559],"type":"Point"}
}