{
  "type": "Feature",
  "properties": {
    "addr:full":"Hillside Ho, 2-6 Friern Pk, North Finchley London Greater London N12 9BY",
    "addr:housenumber":"2-6",
    "addr:postcode":"n12 9by",
    "addr:street":"Friern Pk",
    "iso:country":"GB",
    "sg:address":"Hillside Ho, 2-6 Friern Pk, North Finchley",
    "sg:city":"London",
    "sg:classifiers":[
        {
            "category":"Professional",
            "subcategory":"Art Services",
            "type":"Services"
        }
    ],
    "sg:postcode":"N12 9BY",
    "sg:province":"Greater London",
    "sg:tags":[
        "graphic",
        "designer"
    ],
    "wof:name":"Proxima Centauri Ltd",
    "wof:placetype":"venue"
},
  "geometry": {"coordinates":[-0.176764,51.615898],"type":"Point"}
}