{
  "type": "Feature",
  "properties": {
    "addr:full":"George Street, Compstall Stockport Cheshire SK6 5JD",
    "addr:postcode":"sk6 5jd",
    "addr:street":"George Street",
    "iso:country":"GB",
    "sg:address":"George Street, Compstall",
    "sg:city":"Stockport",
    "sg:classifiers":[
        {
            "category":"Bars & Pubs",
            "type":"Food & Drink"
        }
    ],
    "sg:phone":"+44 161 427 2281",
    "sg:postcode":"SK6 5JD",
    "sg:province":"Cheshire",
    "sg:tags":[
        "pubs",
        "inn"
    ],
    "wof:name":"The Andrew Arms",
    "wof:placetype":"venue"
},
  "geometry": {"coordinates":[-2.0565290451,53.4154891968],"type":"Point"}
}