{
  "type": "Feature",
  "properties": {
    "addr:full":"4 Dundee Rd Leicester Leicestershire LE8 4AH",
    "addr:housenumber":"4",
    "addr:postcode":"le8 4ah",
    "addr:street":"Dundee Rd",
    "iso:country":"GB",
    "sg:address":"4 Dundee Rd",
    "sg:city":"Leicester",
    "sg:classifiers":[
        {
            "category":"Home & Garden",
            "subcategory":"Household Appliances",
            "type":"Retail Goods"
        }
    ],
    "sg:phone":"+44 116 277 8002",
    "sg:postcode":"LE8 4AH",
    "sg:province":"Leicestershire",
    "sg:tags":[
        "electrical"
    ],
    "wof:name":"B & M Domestic",
    "wof:placetype":"venue"
},
  "geometry": {"coordinates":[-1.164813,52.566402],"type":"Point"}
}