{
  "type": "Feature",
  "properties": {
    "addr:full":"The Old Press House, Irwell Vale Road, Ewood Bridge Rossendale Lancashire BB4 6LF",
    "addr:postcode":"bb4 6lf",
    "addr:street":"Irwell Vale Road",
    "iso:country":"GB",
    "sg:address":"The Old Press House, Irwell Vale Road, Ewood Bridge",
    "sg:city":"Rossendale",
    "sg:classifiers":[
        {
            "category":"Manufacturing",
            "subcategory":"Metals",
            "type":"Manufacturing & Wholesale Goods"
        }
    ],
    "sg:phone":"+44 1706 219997",
    "sg:postcode":"BB4 6LF",
    "sg:province":"Lancashire",
    "sg:tags":[
        "steel",
        "stockholder"
    ],
    "wof:name":"Classic Steels Ltd.",
    "wof:placetype":"venue"
},
  "geometry": {"coordinates":[-2.312334,53.683949],"type":"Point"}
}