{
  "type": "Feature",
  "properties": {
    "iso:country":"GB",
    "sg:address":"Manor Ct, 12 St Margarets St",
    "sg:city":"Ipswich",
    "sg:classifiers":[
        {
            "category":"Professional",
            "subcategory":"Printing & Photocopies",
            "type":"Services"
        }
    ],
    "sg:phone":"+44 70 4135 1055",
    "sg:postcode":"IP4 2AT",
    "sg:province":"Suffolk",
    "sg:tags":[
        "printer"
    ],
    "wof:name":"Leaside Associates Ltd",
    "wof:placetype":"venue"
},
  "geometry": {"coordinates":[1.1598900557,52.057510376],"type":"Point"}
}