{
  "type": "Feature",
  "properties": {
    "iso:country":"GB",
    "sg:address":"10 Hodge Lane, Amington",
    "sg:city":"Tamworth",
    "sg:classifiers":[
        {
            "category":"Building & Trades",
            "subcategory":"Construction",
            "type":"Services"
        }
    ],
    "sg:phone":"+44 7768 465911",
    "sg:postcode":"B77 4AN",
    "sg:province":"Staffordshire",
    "sg:tags":[
        "builder"
    ],
    "wof:name":"Lyndhurst Contractors Ltd.",
    "wof:placetype":"venue"
},
  "geometry": {"coordinates":[-1.648819,52.638241],"type":"Point"}
}