{
  "type": "Feature",
  "properties": {
    "addr:full":"28 Louise Street Dudley Staffordshire DY3 2UB",
    "addr:housenumber":"28",
    "addr:postcode":"dy3 2ub",
    "addr:street":"Louise Street",
    "iso:country":"GB",
    "sg:address":"28 Louise Street",
    "sg:city":"Dudley",
    "sg:classifiers":[
        {
            "category":"Food & Beverages",
            "subcategory":"Fruits & Vegetables",
            "type":"Retail Goods"
        }
    ],
    "sg:postcode":"DY3 2UB",
    "sg:province":"Staffordshire",
    "sg:tags":[
        "greengrocer"
    ],
    "wof:name":"Val & Derek Clarke",
    "wof:placetype":"venue"
},
  "geometry": {"coordinates":[-2.132259,52.517521],"type":"Point"}
}