{
  "type": "Feature",
  "properties": {
    "addr:full":"Solway Street, Silloth Wigton Cumbria CA7 4AS",
    "addr:postcode":"ca7 4as",
    "addr:street":"Solway Street",
    "iso:country":"GB",
    "sg:address":"Solway Street, Silloth",
    "sg:city":"Wigton",
    "sg:classifiers":[
        {
            "category":"Bars & Pubs",
            "type":"Food & Drink"
        }
    ],
    "sg:postcode":"CA7 4AS",
    "sg:province":"Cumbria",
    "sg:tags":[
        "pubs",
        "inn"
    ],
    "wof:name":"The Huntsman",
    "wof:placetype":"venue"
},
  "geometry": {"coordinates":[-3.3855040073,54.8709640503],"type":"Point"}
}