{
  "type": "Feature",
  "properties": {
    "iso:country":"GB",
    "sg:address":"Cocker Avenue",
    "sg:city":"Poulton-le-fylde",
    "sg:classifiers":[
        {
            "category":"Home & Garden",
            "subcategory":"Carpets & Floor Coverings",
            "type":"Retail Goods"
        }
    ],
    "sg:phone":"+44 1253 886070",
    "sg:postcode":"FY6 8JU",
    "sg:province":"Lancashire",
    "sg:tags":[
        "textile",
        "floorcoverings"
    ],
    "wof:name":"The Wood Floor Store",
    "wof:placetype":"venue"
},
  "geometry": {"coordinates":[-2.973364,53.842911],"type":"Point"}
}