{
  "type": "Feature",
  "properties": {
    "addr:full":"The Old Brickworks Bratch Lane, Dinton Salisbury Wiltshire SP3 5EB",
    "addr:postcode":"sp3 5eb",
    "addr:street":"Bratch Lane",
    "iso:country":"GB",
    "sg:address":"The Old Brickworks Bratch Lane, Dinton",
    "sg:city":"Salisbury",
    "sg:classifiers":[
        {
            "category":"Building & Trades",
            "subcategory":"Construction",
            "type":"Services"
        }
    ],
    "sg:phone":"+44 1722 716565",
    "sg:postcode":"SP3 5EB",
    "sg:province":"Wiltshire",
    "sg:tags":[
        "joiner",
        "carpenter"
    ],
    "wof:name":"Shayne Ferguson",
    "wof:placetype":"venue"
},
  "geometry": {"coordinates":[-1.979668,51.083214],"type":"Point"}
}