{
  "type": "Feature",
  "properties": {
    "addr:full":"Ham Green, Holt Trowbridge Wiltshire BA14 6PY",
    "addr:postcode":"ba14 6py",
    "addr:street":"Ham Green Holt",
    "iso:country":"GB",
    "sg:address":"Ham Green, Holt",
    "sg:city":"Trowbridge",
    "sg:classifiers":[
        {
            "category":"Bars & Pubs",
            "type":"Food & Drink"
        }
    ],
    "sg:postcode":"BA14 6PY",
    "sg:province":"Wiltshire",
    "sg:tags":[
        "pubs",
        "inn"
    ],
    "wof:name":"Hawke,Ted,",
    "wof:placetype":"venue"
},
  "geometry": {"coordinates":[-2.1979389191,51.3568458557],"type":"Point"}
}