{
  "type": "Feature",
  "properties": {
    "addr:full":"Tallon Rd, Hutton Ind Est Brentwood Essex CM13 1TG",
    "addr:postcode":"cm13 1tg",
    "addr:street":"Tallon Rd",
    "iso:country":"GB",
    "sg:address":"Tallon Rd, Hutton Ind Est",
    "sg:city":"Brentwood",
    "sg:classifiers":[
        {
            "category":"Retail",
            "subcategory":"Photofinishing",
            "type":"Services"
        }
    ],
    "sg:phone":"+44 1277 261361",
    "sg:postcode":"CM13 1TG",
    "sg:province":"Essex",
    "sg:tags":[
        "photographic",
        "processor"
    ],
    "wof:name":"CPL Ltd",
    "wof:placetype":"venue"
},
  "geometry": {"coordinates":[0.3558380008,51.6332130432],"type":"Point"}
}