{
  "type": "Feature",
  "properties": {
    "addr:full":"Anchor House, Netherhampton Road, Harnham Salisbury Wiltshire SP2 8RA",
    "addr:postcode":"sp2 8ra",
    "addr:street":"Netherhampton Road",
    "iso:country":"GB",
    "sg:address":"Anchor House, Netherhampton Road, Harnham",
    "sg:city":"Salisbury",
    "sg:classifiers":[
        {
            "category":"Home & Garden",
            "subcategory":"Hardware",
            "type":"Retail Goods"
        }
    ],
    "sg:phone":"+44 1722 412233",
    "sg:postcode":"SP2 8RA",
    "sg:province":"Wiltshire",
    "sg:tags":[
        "retailer",
        "diy"
    ],
    "wof:name":"In Excess",
    "wof:placetype":"venue"
},
  "geometry": {"coordinates":[-1.8490840197,51.0673484802],"type":"Point"}
}