{
  "type": "Feature",
  "properties": {
    "iso:country":"GB",
    "sg:address":"92 Elmers End Road",
    "sg:city":"Beckenham",
    "sg:classifiers":[
        {
            "category":"Retail",
            "subcategory":"Laundry & Dry Cleaning",
            "type":"Services"
        }
    ],
    "sg:phone":"+44 20 8659 7199",
    "sg:postcode":"BR3 4TA",
    "sg:province":"Kent",
    "sg:tags":[
        "alteration"
    ],
    "wof:name":"Jays",
    "wof:placetype":"venue"
},
  "geometry": {"coordinates":[-0.0417219996,51.393409729],"type":"Point"}
}