{
  "type": "Feature",
  "properties": {
    "addr:full":"Gatwick Village, South Terminal, London Gatwick Airport Gatwick Surrey RH6 0NN",
    "addr:postcode":"rh6 0nn",
    "addr:street":"Gatwick Village South;Airport Gatwick",
    "iso:country":"GB",
    "sg:address":"Gatwick Village, South Terminal, London Gatwick Airport",
    "sg:city":"Gatwick",
    "sg:classifiers":[
        {
            "category":"Food & Beverages",
            "subcategory":"Candy",
            "type":"Retail Goods"
        }
    ],
    "sg:phone":"+44 1293 507404",
    "sg:postcode":"RH6 0NN",
    "sg:province":"Surrey",
    "sg:tags":[
        "confectioner"
    ],
    "wof:name":"Cadburys Shop",
    "wof:placetype":"venue"
},
  "geometry": {"coordinates":[-0.1723539978,51.1617736816],"type":"Point"}
}