{
  "type": "Feature",
  "properties": {
    "addr:full":"191b Portobello Rd Notting Hill Greater London W11 2ED",
    "addr:housenumber":"191b",
    "addr:postcode":"w11 2ed",
    "addr:street":"Portobello Rd",
    "iso:country":"GB",
    "sg:address":"191b Portobello Rd",
    "sg:city":"Notting Hill",
    "sg:classifiers":[
        {
            "category":"Shopping",
            "subcategory":"Department Store",
            "type":"Retail Goods"
        }
    ],
    "sg:phone":"+44 20 7229 4705",
    "sg:postcode":"W11 2ED",
    "sg:province":"Greater London",
    "wof:name":"Saveway",
    "wof:placetype":"venue"
},
  "geometry": {"coordinates":[-0.2050220072,51.5155563354],"type":"Point"}
}