{
  "type": "Feature",
  "properties": {
    "iso:country":"GB",
    "sg:address":"20 Poplar Rd, Kensworth",
    "sg:city":"Dunstable",
    "sg:classifiers":[
        {
            "category":"Communications",
            "type":"Services"
        }
    ],
    "sg:postcode":"LU6 3RS",
    "sg:province":"Bedfordshire",
    "sg:tags":[
        "system",
        "music",
        "public",
        "address"
    ],
    "wof:name":"Hofer,David J,",
    "wof:placetype":"venue"
},
  "geometry": {"coordinates":[-0.5052160025,51.8508453369],"type":"Point"}
}