{
  "type": "Feature",
  "properties": {
    "addr:full":"52 Granby St Leicester Leicestershire LE1 1DH",
    "addr:housenumber":"52",
    "addr:postcode":"le1 1dh",
    "addr:street":"Granby St",
    "iso:country":"GB",
    "sg:address":"52 Granby St",
    "sg:city":"Leicester",
    "sg:classifiers":[
        {
            "category":"Government",
            "subcategory":"Office",
            "type":"Public Place"
        }
    ],
    "sg:phone":"+44 116 254 3113",
    "sg:postcode":"LE1 1DH",
    "sg:province":"Leicestershire",
    "sg:tags":[
        "education",
        "agency",
        "authority"
    ],
    "wof:name":"Select Education",
    "wof:placetype":"venue"
},
  "geometry": {"coordinates":[-1.1311990023,52.6342010498],"type":"Point"}
}