{
  "type": "Feature",
  "properties": {
    "iso:country":"GB",
    "sg:address":"Unit 7 Mudlands Estate, Manor Way",
    "sg:city":"Rainham",
    "sg:classifiers":[
        {
            "category":"Personal",
            "type":"Services"
        }
    ],
    "sg:phone":"+44 1708 555112",
    "sg:postcode":"RM13 8RH",
    "sg:province":"Essex",
    "sg:tags":[
        "delivery"
    ],
    "wof:name":"G Aspray Transport",
    "wof:placetype":"venue"
},
  "geometry": {"coordinates":[0.1904260069,51.5179138184],"type":"Point"}
}