{
  "type": "Feature",
  "properties": {
    "addr:full":"Swan House, New Mill Road, St Pauls Cray Orpington Kent BR5 3QD",
    "addr:postcode":"br5 3qd",
    "addr:street":"New Mill Road",
    "iso:country":"GB",
    "sg:address":"Swan House, New Mill Road, St Pauls Cray",
    "sg:city":"Orpington",
    "sg:classifiers":[
        {
            "category":"Wholesale",
            "subcategory":"Non-durable Goods",
            "type":"Manufacturing & Wholesale Goods"
        }
    ],
    "sg:phone":"+44 1689 301201",
    "sg:postcode":"BR5 3QD",
    "sg:province":"Kent",
    "sg:tags":[
        "carry",
        "cash"
    ],
    "wof:name":"Country Choice Foods Ltd.",
    "wof:placetype":"venue"
},
  "geometry": {"coordinates":[0.116606,51.406052],"type":"Point"}
}