{
  "type": "Feature",
  "properties": {
    "addr:full":"1 Harwich Rd Colchester Essex CO4 3BP",
    "addr:housenumber":"1",
    "addr:postcode":"co4 3bp",
    "addr:street":"Harwich Rd",
    "iso:country":"GB",
    "sg:address":"1 Harwich Rd",
    "sg:city":"Colchester",
    "sg:classifiers":[
        {
            "category":"Home & Garden",
            "subcategory":"Home Furnishings",
            "type":"Retail Goods"
        }
    ],
    "sg:phone":"+44 1206 795000",
    "sg:postcode":"CO4 3BP",
    "sg:province":"Essex",
    "sg:tags":[
        "furnishers",
        "planner",
        "kitchen"
    ],
    "wof:name":"Master Kitchens Ltd",
    "wof:placetype":"venue"
},
  "geometry": {"coordinates":[0.9203680158,51.8902854919],"type":"Point"}
}