{
  "type": "Feature",
  "properties": {
    "iso:country":"GB",
    "sg:address":"97 Vaughan Dr",
    "sg:city":"Sittingbourne",
    "sg:classifiers":[
        {
            "category":"Military Area",
            "subcategory":"Air Force Base",
            "type":"Public Place"
        }
    ],
    "sg:phone":"+44 1795 430505",
    "sg:postcode":"ME10 2UB",
    "sg:province":"Kent",
    "sg:tags":[
        "water",
        "treatment"
    ],
    "wof:name":"Elite Waterworld The",
    "wof:placetype":"venue"
},
  "geometry": {"coordinates":[0.741994977,51.3564300537],"type":"Point"}
}