{
  "type": "Feature",
  "properties": {
    "addr:full":"200 St Vincent Street West, Ladywood Birmingham West Midlands B16 8EB",
    "addr:housenumber":"200",
    "addr:postcode":"b16 8eb",
    "addr:street":"St Vincent Street West",
    "iso:country":"GB",
    "sg:address":"200 St Vincent Street West, Ladywood",
    "sg:city":"Birmingham",
    "sg:classifiers":[
        {
            "category":"Farming",
            "subcategory":"Fish & Marine Products",
            "type":"Manufacturing & Wholesale Goods"
        }
    ],
    "sg:postcode":"B16 8EB",
    "sg:province":"West Midlands",
    "sg:tags":[
        "fishmonger"
    ],
    "wof:name":"Gourley,Michael,",
    "wof:placetype":"venue"
},
  "geometry": {"coordinates":[-1.9229539633,52.477771759],"type":"Point"}
}