{
  "type": "Feature",
  "properties": {
    "iso:country":"GB",
    "sg:address":"325 Willow Road",
    "sg:city":"Enfield",
    "sg:classifiers":[
        {
            "category":"Health Services",
            "subcategory":"Podiatrist",
            "type":"Services"
        }
    ],
    "sg:phone":"+44 20 8364 6868",
    "sg:postcode":"EN1 3BX",
    "sg:province":"Greater London",
    "sg:tags":[
        "podiatrists",
        "chiropodist"
    ],
    "wof:name":"David Holmes Chiropody",
    "wof:placetype":"venue"
},
  "geometry": {"coordinates":[-0.076783,51.652603],"type":"Point"}
}