{
  "type": "Feature",
  "properties": {
    "addr:full":"47 Smithmoor Crescent West Bromwich West Midlands B71 3EY",
    "addr:housenumber":"47",
    "addr:postcode":"b71 3ey",
    "addr:street":"Smithmoor Crescent",
    "iso:country":"GB",
    "sg:address":"47 Smithmoor Crescent",
    "sg:city":"West Bromwich",
    "sg:classifiers":[
        {
            "category":"Building & Trades",
            "subcategory":"Construction",
            "type":"Services"
        }
    ],
    "sg:phone":"+44 121 567 5456",
    "sg:postcode":"B71 3EY",
    "sg:province":"West Midlands",
    "sg:tags":[
        "roofing"
    ],
    "wof:name":"Complex Roofing & Cladding",
    "wof:placetype":"venue"
},
  "geometry": {"coordinates":[-1.9735399485,52.5438575745],"type":"Point"}
}