{
  "type": "Feature",
  "properties": {
    "iso:country":"GB",
    "sg:address":"Holbrook House, Horsham Road, Shalford",
    "sg:city":"Guildford",
    "sg:classifiers":[
        {
            "category":"Insurance",
            "subcategory":"Insurance Agent",
            "type":"Services"
        }
    ],
    "sg:phone":"+44 1483 505932",
    "sg:postcode":"GU4 8EJ",
    "sg:province":"Surrey",
    "sg:tags":[
        "broker"
    ],
    "wof:name":"Holbrook Insurance Brokers Ltd.",
    "wof:placetype":"venue"
},
  "geometry": {"coordinates":[-0.567944,51.213917],"type":"Point"}
}