{
  "type": "Feature",
  "properties": {
    "iso:country":"GB",
    "sg:address":"Unit 4 & 5 Forest Of Dean Business Est, Stepbridge Rd",
    "sg:city":"Coleford",
    "sg:classifiers":[
        {
            "category":"Home & Garden",
            "subcategory":"Hardware",
            "type":"Retail Goods"
        }
    ],
    "sg:phone":"+44 1594 835678",
    "sg:postcode":"GL16 8PJ",
    "sg:province":"Gloucestershire",
    "sg:tags":[
        "wheel",
        "castor"
    ],
    "wof:name":"Wheelmasters (Uk)",
    "wof:placetype":"venue"
},
  "geometry": {"coordinates":[-2.6065099239,51.7844810486],"type":"Point"}
}