{
  "type": "Feature",
  "properties": {
    "iso:country":"GB",
    "sg:address":"Spode Avenue",
    "sg:city":"Rugeley",
    "sg:classifiers":[
        {
            "category":"Education",
            "subcategory":"School",
            "type":"Public Place"
        }
    ],
    "sg:phone":"+44 1543 490616",
    "sg:postcode":"WS15 4EU",
    "sg:province":"Staffordshire",
    "sg:tags":[
        "local",
        "authority"
    ],
    "wof:name":"The Hayes Meadow Primary School",
    "wof:placetype":"venue"
},
  "geometry": {"coordinates":[-1.862539053,52.7394218445],"type":"Point"}
}