{
  "type": "Feature",
  "properties": {
    "addr:full":"Vinvillar Tonbridge Close, Woodmansterne Banstead Surrey SM7 3JD",
    "addr:postcode":"sm7 3jd",
    "addr:street":"Vinvillar Tonbridge Close",
    "iso:country":"GB",
    "sg:address":"Vinvillar Tonbridge Close, Woodmansterne",
    "sg:city":"Banstead",
    "sg:classifiers":[
        {
            "category":"Building & Trades",
            "subcategory":"Construction",
            "type":"Services"
        }
    ],
    "sg:postcode":"SM7 3JD",
    "sg:province":"Surrey",
    "sg:tags":[
        "builder"
    ],
    "wof:name":"D W Vincent & Co.",
    "wof:placetype":"venue"
},
  "geometry": {"coordinates":[-0.1699890047,51.3245506287],"type":"Point"}
}