{
  "type": "Feature",
  "properties": {
    "iso:country":"GB",
    "sg:address":"138 Tottenham Lane",
    "sg:city":"London",
    "sg:classifiers":[
        {
            "category":"Shopping",
            "subcategory":"Florist",
            "type":"Retail Goods"
        }
    ],
    "sg:phone":"+44 20 8341 6422",
    "sg:postcode":"N8 8SE",
    "sg:province":"Greater London",
    "wof:name":"Hart To Hart",
    "wof:placetype":"venue"
},
  "geometry": {"coordinates":[-0.121079,51.58165],"type":"Point"}
}