{
  "type": "Feature",
  "properties": {
    "addr:full":"2 Crofts Road Lauder Scottish Borders TD2 6QJ",
    "addr:housenumber":"2",
    "addr:postcode":"td2 6qj",
    "addr:street":"Crofts Road",
    "iso:country":"GB",
    "sg:address":"2 Crofts Road",
    "sg:city":"Lauder",
    "sg:classifiers":[
        {
            "category":"Education",
            "subcategory":"School",
            "type":"Public Place"
        },
        {
            "category":"Government",
            "subcategory":"Office",
            "type":"Public Place"
        }
    ],
    "sg:phone":"+44 1578 722346",
    "sg:postcode":"TD2 6QJ",
    "sg:province":"Scottish Borders",
    "sg:tags":[
        "local",
        "authority"
    ],
    "wof:name":"Lauder Primary School",
    "wof:placetype":"venue"
},
  "geometry": {"coordinates":[-2.752191,55.72113],"type":"Point"}
}