{
  "type": "Feature",
  "properties": {
    "iso:country":"GB",
    "sg:address":"Voel",
    "sg:city":"Meifod",
    "sg:classifiers":[
        {
            "category":"Building & Trades",
            "subcategory":"Construction",
            "type":"Services"
        }
    ],
    "sg:phone":"+44 1938 500458",
    "sg:postcode":"SY22 6JJ",
    "sg:province":"Shropshire",
    "sg:tags":[
        "contractor",
        "paving",
        "driveway"
    ],
    "wof:name":"G L Breese (Plant Hire) Ltd.",
    "wof:placetype":"venue"
},
  "geometry": {"coordinates":[-3.252824,52.710423],"type":"Point"}
}