{
  "type": "Feature",
  "properties": {
    "addr:full":"Penroc, Marine Terrace Aberystwyth Ceredigion SY23 2AZ",
    "addr:postcode":"sy23 2az",
    "addr:street":"Terrace",
    "iso:country":"GB",
    "sg:address":"Penroc, Marine Terrace",
    "sg:city":"Aberystwyth",
    "sg:classifiers":[
        {
            "category":"Organizations",
            "subcategory":"Non-profit Organization",
            "type":"Services"
        },
        {
            "category":"Organizations",
            "subcategory":"Political Organization",
            "type":"Services"
        }
    ],
    "sg:phone":"+44 1970 624501",
    "sg:postcode":"SY23 2AZ",
    "sg:province":"Ceredigion",
    "sg:tags":[
        "charitable",
        "organisation",
        "charity",
        "party"
    ],
    "sg:website":"http://www.cymdeithas.com",
    "wof:name":"Cymdeithas Yr Iaith Gymraeg",
    "wof:placetype":"venue"
},
  "geometry": {"coordinates":[-4.077869,52.41605],"type":"Point"}
}