{
  "type": "Feature",
  "properties": {
    "iso:country":"GB",
    "sg:address":"Torrington Sorting Office, 6 Fore Street",
    "sg:city":"Torrington",
    "sg:classifiers":[
        {
            "category":"Government",
            "subcategory":"Post Office",
            "type":"Public Place"
        }
    ],
    "sg:phone":"+44 1805 622209",
    "sg:postcode":"EX38 8HT",
    "sg:province":"Devon",
    "wof:name":"Royal Mail",
    "wof:placetype":"venue"
},
  "geometry": {"coordinates":[-4.142255,50.953152],"type":"Point"}
}