{
  "type": "Feature",
  "properties": {
    "addr:full":"57 Marsh Hill, Erdington Birmingham West Midlands B23 7DS",
    "addr:housenumber":"57",
    "addr:postcode":"b23 7ds",
    "addr:street":"Marsh Hill",
    "iso:country":"GB",
    "sg:address":"57 Marsh Hill, Erdington",
    "sg:city":"Birmingham",
    "sg:classifiers":[
        {
            "category":"Shopping",
            "subcategory":"Florist",
            "type":"Retail Goods"
        }
    ],
    "sg:postcode":"B23 7DS",
    "sg:province":"West Midlands",
    "wof:name":"Helens Flowers",
    "wof:placetype":"venue"
},
  "geometry": {"coordinates":[-1.8622039557,52.5249443054],"type":"Point"}
}