{
  "type": "Feature",
  "properties": {
    "iso:country":"GB",
    "sg:address":"Llannoy, Croesgoch",
    "sg:city":"Haverfordwest",
    "sg:classifiers":[
        {
            "category":"Farming",
            "subcategory":"Farm",
            "type":"Manufacturing & Wholesale Goods"
        }
    ],
    "sg:postcode":"SA62 5JU",
    "sg:province":"Pembrokeshire",
    "sg:tags":[
        "mixed",
        "crop"
    ],
    "wof:name":"W H C Thomas & Sons",
    "wof:placetype":"venue"
},
  "geometry": {"coordinates":[-5.160846,51.928043],"type":"Point"}
}