{
  "type": "Feature",
  "properties": {
    "iso:country":"GB",
    "sg:address":"5 Woodlands Terrace, Edlington",
    "sg:city":"Doncaster",
    "sg:classifiers":[
        {
            "category":"Organizations",
            "subcategory":"Political Organization",
            "type":"Services"
        }
    ],
    "sg:phone":"+44 1709 866685",
    "sg:postcode":"DN12 1LG",
    "sg:province":"South Yorkshire",
    "sg:tags":[
        "party"
    ],
    "wof:name":"Liberal Democrats",
    "wof:placetype":"venue"
},
  "geometry": {"coordinates":[-1.1910389662,53.481086731],"type":"Point"}
}