{
  "type": "Feature",
  "properties": {
    "iso:country":"GB",
    "sg:address":"Ashley House",
    "sg:city":"Lutterworth",
    "sg:classifiers":[
        {
            "category":"Home & Garden",
            "subcategory":"Building Materials",
            "type":"Retail Goods"
        }
    ],
    "sg:phone":"+44 1455 553579",
    "sg:postcode":"LE17 5PN",
    "sg:province":"Leicestershire",
    "sg:tags":[
        "fencing"
    ],
    "wof:name":"Broughton-Hall Automation Ltd.",
    "wof:placetype":"venue"
},
  "geometry": {"coordinates":[-1.1999289989,52.507068634],"type":"Point"}
}