{
  "type": "Feature",
  "properties": {
    "addr:full":"107 Warwick Rd Carlisle Cumbria CA1 1EA",
    "addr:housenumber":"107",
    "addr:postcode":"ca1 1ea",
    "addr:street":"Warwick Rd",
    "iso:country":"GB",
    "sg:address":"107 Warwick Rd",
    "sg:city":"Carlisle",
    "sg:classifiers":[
        {
            "category":"Travel",
            "subcategory":"Hotels & Motels",
            "type":"Entertainment"
        }
    ],
    "sg:postcode":"CA1 1EA",
    "sg:province":"Cumbria",
    "sg:tags":[
        "house",
        "guest"
    ],
    "wof:name":"Cornerways Guest House",
    "wof:placetype":"venue"
},
  "geometry": {"coordinates":[-2.9266979694,54.894203186],"type":"Point"}
}