{
  "type": "Feature",
  "properties": {
    "addr:full":"38 High St, Caergwrle Wrexham Wrexham LL12 9ET",
    "addr:housenumber":"38",
    "addr:postcode":"ll12 9et",
    "addr:street":"High St",
    "iso:country":"GB",
    "sg:address":"38 High St, Caergwrle",
    "sg:city":"Wrexham",
    "sg:classifiers":[
        {
            "category":"Shopping",
            "subcategory":"Pharmacy",
            "type":"Retail Goods"
        }
    ],
    "sg:postcode":"LL12 9ET",
    "sg:province":"Wrexham",
    "sg:tags":[
        "pharmacist",
        "chemist"
    ],
    "wof:name":"Jones,O J,",
    "wof:placetype":"venue"
},
  "geometry": {"coordinates":[-3.040069,53.110443],"type":"Point"}
}