{
  "type": "Feature",
  "properties": {
    "addr:full":"3-5 Duke Street Reading Berkshire RG1 4SA",
    "addr:housenumber":"3-5",
    "addr:postcode":"rg1 4sa",
    "addr:street":"Duke Street",
    "iso:country":"GB",
    "sg:address":"3-5 Duke Street",
    "sg:city":"Reading",
    "sg:classifiers":[
        {
            "category":"Shopping",
            "subcategory":"Stationery & Office Supplies",
            "type":"Retail Goods"
        }
    ],
    "sg:phone":"+44 118 950 0493",
    "sg:postcode":"RG1 4SA",
    "sg:province":"Berkshire",
    "wof:name":"Ryman Stationers",
    "wof:placetype":"venue"
},
  "geometry": {"coordinates":[-0.968799,51.454723],"type":"Point"}
}