{
  "type": "Feature",
  "properties": {
    "addr:full":"Tottington Barn, Truleigh Hill Shoreham-by-sea West Sussex BN43 5FB",
    "addr:housenumber":"tottington",
    "addr:postcode":"bn43 5fb",
    "addr:street":"Truleigh Hill Shoreham-By-Sea",
    "iso:country":"GB",
    "sg:address":"Tottington Barn, Truleigh Hill",
    "sg:city":"Shoreham-by-sea",
    "sg:classifiers":[
        {
            "category":"Travel",
            "subcategory":"Hostel",
            "type":"Entertainment"
        }
    ],
    "sg:phone":"+44 1903 813419",
    "sg:postcode":"BN43 5FB",
    "sg:province":"West Sussex",
    "sg:tags":[
        "youth"
    ],
    "wof:name":"Youth Hostels Association (England & Wales)",
    "wof:placetype":"venue"
},
  "geometry": {"coordinates":[-0.276469,50.831917],"type":"Point"}
}