{
  "type": "Feature",
  "properties": {
    "addr:full":"91-95 High Street Herne Bay Kent CT6 5LQ",
    "addr:housenumber":"91-95",
    "addr:postcode":"ct6 5lq",
    "addr:street":"High Street",
    "iso:country":"GB",
    "sg:address":"91-95 High Street",
    "sg:city":"Herne Bay",
    "sg:classifiers":[
        {
            "category":"Professional",
            "subcategory":"Accounting & Tax Preparation",
            "type":"Services"
        }
    ],
    "sg:postcode":"CT6 5LQ",
    "sg:province":"Kent",
    "sg:tags":[
        "accountant"
    ],
    "wof:name":"Hilary Adams",
    "wof:placetype":"venue"
},
  "geometry": {"coordinates":[1.1257640123,51.3713722229],"type":"Point"}
}