{
  "type": "Feature",
  "properties": {
    "iso:country":"GB",
    "sg:address":"Agricultural & Rural Life Museum, Bedlam Court Lane, Minster",
    "sg:city":"Ramsgate",
    "sg:classifiers":[
        {
            "category":"Shopping",
            "subcategory":"Jewelry",
            "type":"Retail Goods"
        }
    ],
    "sg:postcode":"CT12 4HQ",
    "sg:province":"Kent",
    "sg:tags":[
        "gold",
        "silversmith"
    ],
    "wof:name":"Rayment & Hull",
    "wof:placetype":"venue"
},
  "geometry": {"coordinates":[1.32274,51.333511],"type":"Point"}
}