{
  "type": "Feature",
  "properties": {
    "iso:country":"GB",
    "sg:address":"10a Station Road",
    "sg:city":"Hayes",
    "sg:classifiers":[
        {
            "category":"Travel",
            "subcategory":"Travel Agent",
            "type":"Entertainment"
        }
    ],
    "sg:phone":"+44 20 8573 2233",
    "sg:postcode":"UB3 4DA",
    "sg:province":"Greater London",
    "wof:name":"Lunn Poly Ltd.",
    "wof:placetype":"venue"
},
  "geometry": {"coordinates":[-0.4192720056,51.5063705444],"type":"Point"}
}