{
  "type": "Feature",
  "properties": {
    "iso:country":"GB",
    "sg:address":"Unit 8-9 Bristol Phoenix, South Liberty Lane",
    "sg:city":"Bristol",
    "sg:classifiers":[
        {
            "category":"Professional",
            "subcategory":"Detective & Security Services",
            "type":"Services"
        }
    ],
    "sg:phone":"+44 117 953 7700",
    "sg:postcode":"BS3 2SE",
    "sg:province":"City of Bristol",
    "wof:name":"Security Express",
    "wof:placetype":"venue"
},
  "geometry": {"coordinates":[-2.618729,51.4352],"type":"Point"}
}