{
  "type": "Feature",
  "properties": {
    "iso:country":"GB",
    "sg:address":"3 Riversdale Road, West Cross",
    "sg:city":"Swansea",
    "sg:classifiers":[
        {
            "category":"Shopping",
            "subcategory":"News",
            "type":"Retail Goods"
        }
    ],
    "sg:postcode":"SA3 5PU",
    "sg:province":"Swansea",
    "sg:tags":[
        "newsagent"
    ],
    "wof:name":"Riversdale Newsagent",
    "wof:placetype":"venue"
},
  "geometry": {"coordinates":[-4.009303093,51.5813598633],"type":"Point"}
}