{
  "type": "Feature",
  "properties": {
    "iso:country":"GB",
    "sg:address":"725-729 Stockport Road, Levenshulme",
    "sg:city":"Manchester",
    "sg:classifiers":[
        {
            "category":"Shopping",
            "subcategory":"Pets & Pet Supplies",
            "type":"Retail Goods"
        }
    ],
    "sg:phone":"+44 161 224 0121",
    "sg:postcode":"M19 3AR",
    "sg:province":"Greater Manchester",
    "wof:name":"Gaylyfe Pets & Aquatics",
    "wof:placetype":"venue"
},
  "geometry": {"coordinates":[-2.1917829514,53.4483833313],"type":"Point"}
}