{
  "type": "Feature",
  "properties": {
    "iso:country":"GB",
    "sg:address":"524 Oxford St",
    "sg:city":"West End",
    "sg:classifiers":[
        {
            "category":"Banks & Credit Unions",
            "subcategory":"Bureau De Change",
            "type":"Services"
        }
    ],
    "sg:phone":"+44 20 7499 0570",
    "sg:postcode":"W1N 9HH",
    "sg:province":"Hampshire",
    "wof:name":"Citi Forex Ltd",
    "wof:placetype":"venue"
},
  "geometry": {"coordinates":[-0.157011,51.513741],"type":"Point"}
}