{
  "type": "Feature",
  "properties": {
    "addr:full":"19 The Ladysmith Oldham Greater Manchester OL6 9AP",
    "addr:housenumber":"19",
    "addr:postcode":"ol6 9ap",
    "addr:street":"The",
    "iso:country":"GB",
    "sg:address":"19 The Ladysmith",
    "sg:city":"Oldham",
    "sg:classifiers":[
        {
            "category":"Manufacturing",
            "subcategory":"Textiles",
            "type":"Manufacturing & Wholesale Goods"
        }
    ],
    "sg:postcode":"OL6 9AP",
    "sg:province":"Greater Manchester",
    "sg:tags":[
        "made-up"
    ],
    "wof:name":"John Martin",
    "wof:placetype":"venue"
},
  "geometry": {"coordinates":[-2.0665900707,53.4987792969],"type":"Point"}
}