{
  "type": "Feature",
  "properties": {
    "addr:full":"Guildford Place, 124 Guildford Street Chertsey Surrey KT16 9AH",
    "addr:housenumber":"124",
    "addr:postcode":"kt16 9ah",
    "addr:street":"Guildford Street",
    "iso:country":"GB",
    "sg:address":"Guildford Place, 124 Guildford Street",
    "sg:city":"Chertsey",
    "sg:classifiers":[
        {
            "category":"Professional",
            "subcategory":"Business Services",
            "type":"Services"
        }
    ],
    "sg:postcode":"KT16 9AH",
    "sg:province":"Surrey",
    "sg:tags":[
        "import",
        "export",
        "agent"
    ],
    "wof:name":"General Consolidated Impex Co  Ltd",
    "wof:placetype":"venue"
},
  "geometry": {"coordinates":[-0.5082539916,51.3881988525],"type":"Point"}
}