{
  "type": "Feature",
  "properties": {
    "iso:country":"GB",
    "sg:address":"2 Goldstone Street",
    "sg:city":"Hove",
    "sg:classifiers":[
        {
            "category":"Shopping",
            "subcategory":"Stationery & Office Supplies",
            "type":"Retail Goods"
        }
    ],
    "sg:postcode":"BN3 3RJ",
    "sg:province":"East Sussex",
    "sg:tags":[
        "printers'"
    ],
    "wof:name":"Delta Press",
    "wof:placetype":"venue"
},
  "geometry": {"coordinates":[-0.174542,50.832226],"type":"Point"}
}