{
  "type": "Feature",
  "properties": {
    "iso:country":"GB",
    "sg:address":"5 Hazelbank Close",
    "sg:city":"Liphook",
    "sg:classifiers":[
        {
            "category":"Building & Trades",
            "subcategory":"Plumbing",
            "type":"Services"
        }
    ],
    "sg:postcode":"GU30 7BY",
    "sg:province":"Hampshire",
    "sg:tags":[
        "heating"
    ],
    "wof:name":"Plumbing & Heating Services",
    "wof:placetype":"venue"
},
  "geometry": {"coordinates":[-0.790501,51.077354],"type":"Point"}
}