{
  "type": "Feature",
  "properties": {
    "addr:full":"23 Rutland St Stoke On Trent Staffordshire ST1 5JG",
    "addr:housenumber":"23",
    "addr:postcode":"st1 5jg",
    "addr:street":"Rutland St",
    "iso:country":"GB",
    "sg:address":"23 Rutland St",
    "sg:city":"Stoke On Trent",
    "sg:classifiers":[
        {
            "category":"Professional",
            "subcategory":"Art Services",
            "type":"Services"
        }
    ],
    "sg:phone":"+44 1782 272439",
    "sg:postcode":"ST1 5JG",
    "sg:province":"Staffordshire",
    "sg:tags":[
        "photographer"
    ],
    "wof:name":"D B Graphics",
    "wof:placetype":"venue"
},
  "geometry": {"coordinates":[-2.1853730679,53.0302200317],"type":"Point"}
}