{
  "type": "Feature",
  "properties": {
    "iso:country":"GB",
    "sg:address":"Helions Service Road",
    "sg:city":"Haverhill",
    "sg:classifiers":[
        {
            "category":"Wholesale",
            "subcategory":"Machinery & Supplies",
            "type":"Manufacturing & Wholesale Goods"
        }
    ],
    "sg:postcode":"CB9 8DL",
    "sg:province":"Essex",
    "wof:name":"Farmpartcentres",
    "wof:placetype":"venue"
},
  "geometry": {"coordinates":[0.439705,52.08102],"type":"Point"}
}