{
  "type": "Feature",
  "properties": {
    "iso:country":"GB",
    "sg:address":"Pennine House, Russell Street",
    "sg:city":"Leeds",
    "sg:classifiers":[
        {
            "category":"Professional",
            "subcategory":"Business Services",
            "type":"Services"
        }
    ],
    "sg:phone":"+44 113 245 9667",
    "sg:postcode":"LS1 5RN",
    "sg:province":"West Yorkshire",
    "sg:tags":[
        "transfer",
        "agent"
    ],
    "wof:name":"Christie & Co",
    "wof:placetype":"venue"
},
  "geometry": {"coordinates":[-1.5478440523,53.7980690002],"type":"Point"}
}