{
  "type": "Feature",
  "properties": {
    "addr:full":"13 Strand St Sandwich Kent CT13 9DX",
    "addr:housenumber":"13",
    "addr:postcode":"ct13 9dx",
    "addr:street":"Strand St",
    "iso:country":"GB",
    "sg:address":"13 Strand St",
    "sg:city":"Sandwich",
    "sg:classifiers":[
        {
            "category":"Shopping",
            "subcategory":"Antiques",
            "type":"Retail Goods"
        }
    ],
    "sg:postcode":"CT13 9DX",
    "sg:province":"Kent",
    "wof:name":"Shirleys Antiques",
    "wof:placetype":"venue"
},
  "geometry": {"coordinates":[1.340873,51.275814],"type":"Point"}
}