{
  "type": "Feature",
  "properties": {
    "addr:full":"36-38 Queenstown Road London Greater London SW8 3RY",
    "addr:housenumber":"36-38",
    "addr:postcode":"sw8 3ry",
    "addr:street":"Queenstown Road",
    "iso:country":"GB",
    "sg:address":"36-38 Queenstown Road",
    "sg:city":"London",
    "sg:classifiers":[
        {
            "category":"Restaurant",
            "type":"Food & Drink"
        }
    ],
    "sg:phone":"+44 20 7622 2618",
    "sg:postcode":"SW8 3RY",
    "sg:province":"Greater London",
    "sg:tags":[
        "french"
    ],
    "wof:name":"le Bouchon Lyonnais",
    "wof:placetype":"venue"
},
  "geometry": {"coordinates":[-0.1504909992,51.4676475525],"type":"Point"}
}