{
  "type": "Feature",
  "properties": {
    "addr:full":"21 Replingham Road London Greater London SW18 5LT",
    "addr:housenumber":"21",
    "addr:postcode":"sw18 5lt",
    "addr:street":"Replingham Road",
    "iso:country":"GB",
    "sg:address":"21 Replingham Road",
    "sg:city":"London",
    "sg:classifiers":[
        {
            "category":"Real Estate",
            "subcategory":"Real Estate Agent",
            "type":"Services"
        }
    ],
    "sg:postcode":"SW18 5LT",
    "sg:province":"Greater London",
    "wof:name":"McKenzies Estate Agents",
    "wof:placetype":"venue"
},
  "geometry": {"coordinates":[-0.20529,51.444908],"type":"Point"}
}