{
  "type": "Feature",
  "properties": {
    "iso:country":"GB",
    "sg:address":"Arboretum Gate, 88-90 North Sherwood Street",
    "sg:city":"Nottingham",
    "sg:classifiers":[
        {
            "category":"Professional",
            "subcategory":"Computer Services",
            "type":"Services"
        }
    ],
    "sg:phone":"+44 115 959 7000",
    "sg:postcode":"NG1 4EE",
    "sg:province":"Nottinghamshire",
    "sg:tags":[
        "system",
        "software"
    ],
    "wof:name":"Protocol Systems Ltd.",
    "wof:placetype":"venue"
},
  "geometry": {"coordinates":[-1.143924,52.949226],"type":"Point"}
}