{
  "type": "Feature",
  "properties": {
    "iso:country":"GB",
    "sg:address":"45-47 High Street",
    "sg:city":"Newport",
    "sg:classifiers":[
        {
            "category":"Professional",
            "type":"Services"
        },
        {
            "category":"Real Estate",
            "subcategory":"Real Estate Agent",
            "type":"Services"
        }
    ],
    "sg:phone":"+44 1952 811003",
    "sg:postcode":"TF10 7AT",
    "sg:province":"Shropshire",
    "sg:tags":[
        "auctioneer"
    ],
    "wof:name":"Davies White & Perry",
    "wof:placetype":"venue"
},
  "geometry": {"coordinates":[-2.378181,52.768368],"type":"Point"}
}