{
  "type": "Feature",
  "properties": {
    "iso:country":"GB",
    "sg:address":"1 Allan Court, High Street",
    "sg:city":"Burntisland",
    "sg:classifiers":[
        {
            "category":"Social Services",
            "subcategory":"Adult Care",
            "type":"Services"
        },
        {
            "category":"Government",
            "subcategory":"Office",
            "type":"Public Place"
        }
    ],
    "sg:phone":"+44 1592 872088",
    "sg:postcode":"KY3 9AJ",
    "sg:province":"Fife",
    "sg:tags":[
        "housing",
        "local",
        "sheltered"
    ],
    "wof:name":"Allan Court Sheltered Housing",
    "wof:placetype":"venue"
},
  "geometry": {"coordinates":[-3.234709,56.059174],"type":"Point"}
}