{
  "type": "Feature",
  "properties": {
    "addr:full":"63 Mansell Street London Greater London E1 8AN",
    "addr:housenumber":"63",
    "addr:postcode":"e1 8an",
    "addr:street":"Mansell Street",
    "iso:country":"GB",
    "sg:address":"63 Mansell Street",
    "sg:city":"London",
    "sg:classifiers":[
        {
            "category":"Insurance",
            "subcategory":"Insurance Agent",
            "type":"Services"
        }
    ],
    "sg:postcode":"E1 8AN",
    "sg:province":"Greater London",
    "wof:name":"Everitt Boles Ltd.",
    "wof:placetype":"venue"
},
  "geometry": {"coordinates":[-0.072936,51.512501],"type":"Point"}
}