{
  "type": "Feature",
  "properties": {
    "addr:full":"Oxford Lane, Siddal Halifax West Yorkshire HX3 9LA",
    "addr:postcode":"hx3 9la",
    "addr:street":"Oxford Lane",
    "iso:country":"GB",
    "sg:address":"Oxford Lane, Siddal",
    "sg:city":"Halifax",
    "sg:classifiers":[
        {
            "category":"Education",
            "subcategory":"School",
            "type":"Public Place"
        },
        {
            "category":"Government",
            "subcategory":"Office",
            "type":"Public Place"
        }
    ],
    "sg:phone":"+44 1422 353989",
    "sg:postcode":"HX3 9LA",
    "sg:province":"West Yorkshire",
    "sg:tags":[
        "local",
        "authority"
    ],
    "wof:name":"Siddal Junior School",
    "wof:placetype":"venue"
},
  "geometry": {"coordinates":[-1.848894,53.704464],"type":"Point"}
}