{
  "type": "Feature",
  "properties": {
    "iso:country":"GB",
    "sg:address":"Ardwyn Terrace, Resolven",
    "sg:city":"Neath",
    "sg:classifiers":[
        {
            "category":"Professional",
            "subcategory":"Business Services",
            "type":"Services"
        }
    ],
    "sg:phone":"+44 1639 710291",
    "sg:postcode":"SA11 4LY",
    "sg:province":"Neath Port Talbot",
    "sg:tags":[
        "bookmaker"
    ],
    "wof:name":"C Cuke",
    "wof:placetype":"venue"
},
  "geometry": {"coordinates":[-3.697003,51.712475],"type":"Point"}
}