{
  "type": "Feature",
  "properties": {
    "addr:full":"153 Stamford Rd Oldham Lancashire OL4 3NB",
    "addr:housenumber":"153",
    "addr:postcode":"ol4 3nb",
    "addr:street":"Stamford Rd",
    "iso:country":"GB",
    "sg:address":"153 Stamford Rd",
    "sg:city":"Oldham",
    "sg:classifiers":[
        {
            "category":"Professional",
            "type":"Services"
        }
    ],
    "sg:phone":"+44 161 624 2851",
    "sg:postcode":"OL4 3NB",
    "sg:province":"Lancashire",
    "sg:tags":[
        "caterer"
    ],
    "wof:name":"Foods For Thought Of Greenfield",
    "wof:placetype":"venue"
},
  "geometry": {"coordinates":[-2.068844,53.546993],"type":"Point"}
}