{
  "type": "Feature",
  "properties": {
    "iso:country":"GB",
    "sg:address":"166 Fitches Crescent",
    "sg:city":"Maldon",
    "sg:classifiers":[
        {
            "category":"Real Estate",
            "subcategory":"Developer",
            "type":"Services"
        }
    ],
    "sg:phone":"+44 1621 858678",
    "sg:postcode":"CM9 5JF",
    "sg:province":"Essex",
    "sg:tags":[
        "property",
        "land"
    ],
    "wof:name":"Essex Sight Finders",
    "wof:placetype":"venue"
},
  "geometry": {"coordinates":[0.687499,51.725494],"type":"Point"}
}