{
  "type": "Feature",
  "properties": {
    "addr:full":"36 Greville Street London Greater London EC1N 8TB",
    "addr:housenumber":"36",
    "addr:postcode":"ec1n 8tb",
    "addr:street":"Greville Street",
    "iso:country":"GB",
    "sg:address":"36 Greville Street",
    "sg:city":"London",
    "sg:classifiers":[
        {
            "category":"Shopping",
            "subcategory":"Comic Books",
            "type":"Retail Goods"
        }
    ],
    "sg:phone":"+44 20 7404 1283",
    "sg:postcode":"EC1N 8TB",
    "sg:province":"Greater London",
    "sg:tags":[
        "jeweller"
    ],
    "wof:name":"Haltons Ltd.",
    "wof:placetype":"venue"
},
  "geometry": {"coordinates":[-0.107969,51.519474],"type":"Point"}
}