{
  "type": "Feature",
  "properties": {
    "iso:country":"GB",
    "sg:address":"The Garages, 29 Hazelwood Lane",
    "sg:city":"London",
    "sg:classifiers":[
        {
            "category":"Retail",
            "subcategory":"Auto Repair",
            "type":"Services"
        }
    ],
    "sg:postcode":"N13 5EZ",
    "sg:province":"Greater London",
    "sg:tags":[
        "body",
        "car"
    ],
    "wof:name":"C C Autos",
    "wof:placetype":"venue"
},
  "geometry": {"coordinates":[-0.104295,51.619164],"type":"Point"}
}