{
  "type": "Feature",
  "properties": {
    "iso:country":"GB",
    "sg:address":"1159 Bristol Road South",
    "sg:city":"Birmingham",
    "sg:classifiers":[
        {
            "category":"Communications",
            "type":"Services"
        }
    ],
    "sg:phone":"+44 121 475 3111",
    "sg:postcode":"B31 2SL",
    "sg:province":"West Midlands",
    "sg:tags":[
        "data",
        "network"
    ],
    "wof:name":"Datapower Installations",
    "wof:placetype":"venue"
},
  "geometry": {"coordinates":[-1.978605,52.405506],"type":"Point"}
}