{
  "type": "Feature",
  "properties": {
    "addr:full":"Meadow Street, Pontycymer Bridgend Bridgend CF32 8HG",
    "addr:postcode":"cf32 8hg",
    "addr:street":"Meadow Street",
    "iso:country":"GB",
    "sg:address":"Meadow Street, Pontycymer",
    "sg:city":"Bridgend",
    "sg:classifiers":[
        {
            "category":"Education",
            "subcategory":"Library",
            "type":"Public Place"
        }
    ],
    "sg:phone":"+44 1656 871581",
    "sg:postcode":"CF32 8HG",
    "sg:province":"Bridgend",
    "sg:tags":[
        "book"
    ],
    "wof:name":"Pontycymmer Library",
    "wof:placetype":"venue"
},
  "geometry": {"coordinates":[-3.5850141048,51.6132774353],"type":"Point"}
}