{
  "type": "Feature",
  "properties": {
    "addr:full":"The Yard, Grove Lane Thetford Norfolk IP24 2HY",
    "addr:postcode":"ip24 2hy",
    "addr:street":"Grove Lane",
    "iso:country":"GB",
    "sg:address":"The Yard, Grove Lane",
    "sg:city":"Thetford",
    "sg:classifiers":[
        {
            "category":"Building & Trades",
            "subcategory":"Construction",
            "type":"Services"
        }
    ],
    "sg:phone":"+44 1842 751812",
    "sg:postcode":"IP24 2HY",
    "sg:province":"Norfolk",
    "sg:tags":[
        "builder"
    ],
    "wof:name":"T R C Builders",
    "wof:placetype":"venue"
},
  "geometry": {"coordinates":[0.75148,52.415421],"type":"Point"}
}