{
  "type": "Feature",
  "properties": {
    "addr:full":"Hilton Farm Perth Perth and Kinross PH2 8PY",
    "addr:postcode":"ph2 8py",
    "iso:country":"GB",
    "sg:address":"Hilton Farm",
    "sg:city":"Perth",
    "sg:classifiers":[
        {
            "category":"Recreation",
            "type":"Entertainment"
        }
    ],
    "sg:phone":"+44 1738 813450",
    "sg:postcode":"PH2 8PY",
    "sg:province":"Perth and Kinross",
    "sg:tags":[
        "outdoor",
        "pursuit"
    ],
    "wof:name":"Smash Hitz Leisure",
    "wof:placetype":"venue"
},
  "geometry": {"coordinates":[-3.4324140549,56.3960533142],"type":"Point"}
}