{
  "type": "Feature",
  "properties": {
    "iso:country":"GB",
    "sg:address":"Bingleys, Pashley Road",
    "sg:city":"Wadhurst",
    "sg:classifiers":[
        {
            "category":"Professional",
            "type":"Services"
        }
    ],
    "sg:phone":"+44 1580 201144",
    "sg:postcode":"TN5 7HE",
    "sg:province":"East Sussex",
    "sg:tags":[
        "exhibition"
    ],
    "wof:name":"First Impressions",
    "wof:placetype":"venue"
},
  "geometry": {"coordinates":[0.339718,51.062008],"type":"Point"}
}