{
  "type": "Feature",
  "properties": {
    "addr:full":"171 Albert Road, Farnworth Bolton Lancashire BL4 9HP",
    "addr:housenumber":"171",
    "addr:postcode":"bl4 9hp",
    "addr:street":"Albert Road",
    "iso:country":"GB",
    "sg:address":"171 Albert Road, Farnworth",
    "sg:city":"Bolton",
    "sg:classifiers":[
        {
            "category":"Home & Garden",
            "subcategory":"Household Appliances",
            "type":"Retail Goods"
        }
    ],
    "sg:phone":"+44 1204 706814",
    "sg:postcode":"BL4 9HP",
    "sg:province":"Lancashire",
    "sg:tags":[
        "domestic",
        "centre"
    ],
    "wof:name":"A B P Domestic Appliances Warehouse Ltd.",
    "wof:placetype":"venue"
},
  "geometry": {"coordinates":[-2.399420023,53.5450019836],"type":"Point"}
}