{
  "type": "Feature",
  "properties": {
    "iso:country":"GB",
    "sg:address":"3 Lockwood House, Kennington Park Rd, Kennington",
    "sg:city":"Lambeth",
    "sg:classifiers":[
        {
            "category":"Health Services",
            "subcategory":"Health Practitioner",
            "type":"Services"
        }
    ],
    "sg:phone":"+44 20 7207 4171",
    "sg:postcode":"SE11 5SZ",
    "sg:province":"Greater London",
    "sg:tags":[
        "psychologist"
    ],
    "wof:name":"Psyche Information Enterprise",
    "wof:placetype":"venue"
},
  "geometry": {"coordinates":[-0.11291,51.48307],"type":"Point"}
}