{
  "type": "Feature",
  "properties": {
    "iso:country":"GB",
    "sg:address":"Unit 8-10 Joanna House, 34 Central Road",
    "sg:city":"Worcester Park",
    "sg:classifiers":[
        {
            "category":"Professional",
            "subcategory":"Engineering",
            "type":"Services"
        }
    ],
    "sg:postcode":"KT4 8JB",
    "sg:province":"Surrey",
    "sg:tags":[
        "consulting",
        "engineer"
    ],
    "wof:name":"Anthony Wynn Associates",
    "wof:placetype":"venue"
},
  "geometry": {"coordinates":[-0.234934,51.375065],"type":"Point"}
}