{
  "type": "Feature",
  "properties": {
    "iso:country":"GB",
    "sg:address":"12 Station Road",
    "sg:city":"Leeds",
    "sg:classifiers":[
        {
            "category":"Communications",
            "type":"Services"
        }
    ],
    "sg:phone":"+44 113 232 8400",
    "sg:postcode":"LS15 7JX",
    "sg:province":"West Yorkshire",
    "sg:tags":[
        "tv",
        "video",
        "radio"
    ],
    "wof:name":"Thomas Beaumont",
    "wof:placetype":"venue"
},
  "geometry": {"coordinates":[-1.452271,53.804306],"type":"Point"}
}