{
  "type": "Feature",
  "properties": {
    "iso:country":"GB",
    "sg:address":"Hillend Of Lownie Farm",
    "sg:city":"Forfar",
    "sg:classifiers":[
        {
            "category":"Professional",
            "subcategory":"Art Services",
            "type":"Services"
        }
    ],
    "sg:postcode":"DD8 2NT",
    "sg:province":"Angus",
    "sg:tags":[
        "framing"
    ],
    "wof:name":"Hunter Mitchell",
    "wof:placetype":"venue"
},
  "geometry": {"coordinates":[-2.889001,56.648251],"type":"Point"}
}