{
  "type": "Feature",
  "properties": {
    "addr:full":"Deva Centre, 49 Bury St Salford Greater Manchester M3 7AZ",
    "addr:housenumber":"49",
    "addr:postcode":"m3 7az",
    "addr:street":"Bury St",
    "iso:country":"GB",
    "sg:address":"Deva Centre, 49 Bury St",
    "sg:city":"Salford",
    "sg:classifiers":[
        {
            "category":"Shopping",
            "subcategory":"Stationery & Office Supplies",
            "type":"Retail Goods"
        }
    ],
    "sg:phone":"+44 161 834 0435",
    "sg:postcode":"M3 7AZ",
    "sg:province":"Greater Manchester",
    "wof:name":"Staples The Office Superstore",
    "wof:placetype":"venue"
},
  "geometry": {"coordinates":[-2.25378,53.485298],"type":"Point"}
}