{
  "type": "Feature",
  "properties": {
    "addr:full":"3 Church Street Ellesmere Shropshire SY12 0HD",
    "addr:housenumber":"3",
    "addr:postcode":"sy12 0hd",
    "addr:street":"Church Street",
    "iso:country":"GB",
    "sg:address":"3 Church Street",
    "sg:city":"Ellesmere",
    "sg:classifiers":[
        {
            "category":"Home & Garden",
            "subcategory":"Hardware",
            "type":"Retail Goods"
        }
    ],
    "sg:phone":"+44 1691 624973",
    "sg:postcode":"SY12 0HD",
    "sg:province":"Shropshire",
    "sg:tags":[
        "lawnmowers",
        "machinery"
    ],
    "wof:name":"Mowrite",
    "wof:placetype":"venue"
},
  "geometry": {"coordinates":[-2.8907089233,52.9084091187],"type":"Point"}
}