{
  "type": "Feature",
  "properties": {
    "iso:country":"GB",
    "sg:address":"15 Station Rd",
    "sg:city":"Scunthorpe",
    "sg:classifiers":[
        {
            "category":"Personal",
            "subcategory":"Beauty Salon",
            "type":"Services"
        }
    ],
    "sg:phone":"+44 1724 782367",
    "sg:postcode":"DN17 3BT",
    "sg:province":"Lincolnshire",
    "sg:tags":[
        "unisex",
        "hairdresser"
    ],
    "wof:name":"Deb-On-Hair",
    "wof:placetype":"venue"
},
  "geometry": {"coordinates":[-0.7368320227,53.5857315063],"type":"Point"}
}