{
  "type": "Feature",
  "properties": {
    "iso:country":"GB",
    "sg:address":"27 Cross La",
    "sg:city":"Stockport",
    "sg:classifiers":[
        {
            "category":"Building & Trades",
            "subcategory":"Construction",
            "type":"Services"
        }
    ],
    "sg:phone":"+44 161 427 5214",
    "sg:postcode":"SK6 6DJ",
    "sg:province":"Cheshire",
    "sg:tags":[
        "decorator",
        "painter"
    ],
    "wof:name":"M Walton",
    "wof:placetype":"venue"
},
  "geometry": {"coordinates":[-2.07164,53.394569],"type":"Point"}
}