{
  "type": "Feature",
  "properties": {
    "iso:country":"GB",
    "sg:address":"147 Pleckgate Road",
    "sg:city":"Blackburn",
    "sg:classifiers":[
        {
            "category":"Freight",
            "type":"Transportation"
        }
    ],
    "sg:postcode":"BB1 8QR",
    "sg:province":"Lancashire",
    "sg:tags":[
        "haulage",
        "road"
    ],
    "wof:name":"R W Haulage",
    "wof:placetype":"venue"
},
  "geometry": {"coordinates":[-2.486741066,53.7692337036],"type":"Point"}
}