{
  "type": "Feature",
  "properties": {
    "addr:full":"76 Silver St, Irlam Manchester Greater Manchester M44 6HR",
    "addr:housenumber":"76",
    "addr:postcode":"m44 6hr",
    "addr:street":"Silver St",
    "iso:country":"GB",
    "sg:address":"76 Silver St, Irlam",
    "sg:city":"Manchester",
    "sg:classifiers":[
        {
            "category":"Freight",
            "type":"Transportation"
        }
    ],
    "sg:phone":"+44 161 775 6402",
    "sg:postcode":"M44 6HR",
    "sg:province":"Greater Manchester",
    "sg:tags":[
        "haulage",
        "road"
    ],
    "wof:name":"Wilmo Transport",
    "wof:placetype":"venue"
},
  "geometry": {"coordinates":[-2.4135830402,53.4545783997],"type":"Point"}
}