{
  "type": "Feature",
  "properties": {
    "addr:full":"51 West Street Leominster Herefordshire HR6 8EP",
    "addr:housenumber":"51",
    "addr:postcode":"hr6 8ep",
    "addr:street":"West Street",
    "iso:country":"GB",
    "sg:address":"51 West Street",
    "sg:city":"Leominster",
    "sg:classifiers":[
        {
            "category":"Retail",
            "subcategory":"Funeral Services",
            "type":"Services"
        }
    ],
    "sg:phone":"+44 1568 612358",
    "sg:postcode":"HR6 8EP",
    "sg:province":"Herefordshire",
    "sg:tags":[
        "director"
    ],
    "wof:name":"R W Mann & Son",
    "wof:placetype":"venue"
},
  "geometry": {"coordinates":[-2.741661,52.226826],"type":"Point"}
}