{
  "type": "Feature",
  "properties": {
    "iso:country":"GB",
    "sg:address":"7 Emlyn Road",
    "sg:city":"Shepherd's Bush",
    "sg:classifiers":[
        {
            "category":"Health Services",
            "subcategory":"Doctor",
            "type":"Services"
        }
    ],
    "sg:phone":"+44 20 8749 4411",
    "sg:postcode":"W12 9TF",
    "sg:province":"Greater London",
    "sg:tags":[
        "practitioners"
    ],
    "wof:name":"Richardson Consulting",
    "wof:placetype":"venue"
},
  "geometry": {"coordinates":[-0.2488539964,51.4979095459],"type":"Point"}
}