{
  "type": "Feature",
  "properties": {
    "addr:full":"Cambridge Rd, Barton Cambridge Cambridgeshire CB3 7AR",
    "addr:postcode":"cb3 7ar",
    "addr:street":"Cambridge Rd",
    "iso:country":"GB",
    "sg:address":"Cambridge Rd, Barton",
    "sg:city":"Cambridge",
    "sg:classifiers":[
        {
            "category":"Retail",
            "subcategory":"Auto Repair",
            "type":"Services"
        }
    ],
    "sg:phone":"+44 1223 264344",
    "sg:postcode":"CB3 7AR",
    "sg:province":"Cambridgeshire",
    "sg:tags":[
        "modification",
        "garage"
    ],
    "wof:name":"R.B Autos",
    "wof:placetype":"venue"
},
  "geometry": {"coordinates":[0.0677400008,52.183391571],"type":"Point"}
}