{
  "type": "Feature",
  "properties": {
    "addr:full":"47 Church Walk Church Park, Euxton Chorley Lancashire PR7 6HL",
    "addr:housenumber":"47",
    "addr:postcode":"pr7 6hl",
    "addr:street":"Church Walk Church Park",
    "iso:country":"GB",
    "sg:address":"47 Church Walk Church Park, Euxton",
    "sg:city":"Chorley",
    "sg:classifiers":[
        {
            "category":"Manufacturing",
            "subcategory":"Rubber & Plastics",
            "type":"Manufacturing & Wholesale Goods"
        }
    ],
    "sg:phone":"+44 1257 267165",
    "sg:postcode":"PR7 6HL",
    "sg:province":"Lancashire",
    "sg:tags":[
        "product"
    ],
    "wof:name":"Neoplex A S",
    "wof:placetype":"venue"
},
  "geometry": {"coordinates":[-2.6800301075,53.6633682251],"type":"Point"}
}