{
  "type": "Feature",
  "properties": {
    "iso:country":"GB",
    "sg:address":"5 Cedar Rd",
    "sg:city":"Rochester",
    "sg:classifiers":[
        {
            "category":"Professional",
            "subcategory":"Business Services",
            "type":"Services"
        }
    ],
    "sg:phone":"+44 1634 718008",
    "sg:postcode":"ME2 2HB",
    "sg:province":"Kent",
    "sg:tags":[
        "import",
        "export",
        "agent"
    ],
    "wof:name":"P V A International",
    "wof:placetype":"venue"
},
  "geometry": {"coordinates":[0.4841549993,51.3927497864],"type":"Point"}
}