{
  "type": "Feature",
  "properties": {
    "addr:full":"42 Leatherhead Rd Chessington Surrey KT9 2HW",
    "addr:housenumber":"42",
    "addr:postcode":"kt9 2hw",
    "addr:street":"Leatherhead Rd",
    "iso:country":"GB",
    "sg:address":"42 Leatherhead Rd",
    "sg:city":"Chessington",
    "sg:classifiers":[
        {
            "category":"Professional",
            "subcategory":"Detective & Security Services",
            "type":"Services"
        }
    ],
    "sg:phone":"+44 7973 313330",
    "sg:postcode":"KT9 2HW",
    "sg:province":"Surrey",
    "sg:tags":[
        "agency"
    ],
    "wof:name":"Nulli Secundus",
    "wof:placetype":"venue"
},
  "geometry": {"coordinates":[-0.309289,51.361481],"type":"Point"}
}