{
  "type": "Feature",
  "properties": {
    "iso:country":"GB",
    "sg:address":"Blenheim Way, Yaxley",
    "sg:city":"Peterborough",
    "sg:classifiers":[
        {
            "category":"Social Services",
            "subcategory":"Adult Care",
            "type":"Services"
        }
    ],
    "sg:phone":"+44 1733 243104",
    "sg:postcode":"PE7 3YL",
    "sg:province":"Cambridgeshire",
    "sg:tags":[
        "housing",
        "sheltered"
    ],
    "wof:name":"Snow Hills Sheltered Accomodation",
    "wof:placetype":"venue"
},
  "geometry": {"coordinates":[-0.255084,52.518589],"type":"Point"}
}