{
  "type": "Feature",
  "properties": {
    "addr:full":"Hyper Hyper, 26-40 Kensington High St London Greater London W8 4PF",
    "addr:housenumber":"26-40",
    "addr:postcode":"w8 4pf",
    "addr:street":"Kensington High St",
    "iso:country":"GB",
    "sg:address":"Hyper Hyper, 26-40 Kensington High St",
    "sg:city":"London",
    "sg:classifiers":[
        {
            "category":"Shopping",
            "subcategory":"Event Tickets",
            "type":"Retail Goods"
        }
    ],
    "sg:postcode":"W8 4PF",
    "sg:province":"Greater London",
    "sg:tags":[
        "agency"
    ],
    "wof:name":"Advanced Tickets",
    "wof:placetype":"venue"
},
  "geometry": {"coordinates":[-0.1893299967,51.5023803711],"type":"Point"}
}