{
  "type": "Feature",
  "properties": {
    "iso:country":"GB",
    "sg:address":"15 Catford Hill",
    "sg:city":"London",
    "sg:classifiers":[
        {
            "category":"Cafe",
            "type":"Food & Drink"
        }
    ],
    "sg:postcode":"SE6 4NU",
    "sg:province":"Greater London",
    "sg:tags":[
        "tea",
        "snack",
        "bar",
        "room"
    ],
    "wof:name":"B Bicane",
    "wof:placetype":"venue"
},
  "geometry": {"coordinates":[-0.027097,51.442924],"type":"Point"}
}