{
  "type": "Feature",
  "properties": {
    "addr:full":"Lawrence House, City Road Manchester Cheshire M15 4DE",
    "addr:postcode":"m15 4de",
    "addr:street":"City Road",
    "iso:country":"GB",
    "sg:address":"Lawrence House, City Road",
    "sg:city":"Manchester",
    "sg:classifiers":[
        {
            "category":"Organizations",
            "subcategory":"Non-profit Organization",
            "type":"Services"
        }
    ],
    "sg:phone":"+44 161 873 8100",
    "sg:postcode":"M15 4DE",
    "sg:province":"Cheshire",
    "sg:tags":[
        "charitable",
        "organisation",
        "voluntary",
        "charity"
    ],
    "wof:name":"Body Positive North West Ltd.",
    "wof:placetype":"venue"
},
  "geometry": {"coordinates":[-2.2486979961,53.4727401733],"type":"Point"}
}