{
  "type": "Feature",
  "properties": {
    "addr:full":"Strathmartine Court, Strathmartine Road Dundee Dundee City DD3 9DG",
    "addr:postcode":"dd3 9dg",
    "addr:street":"Strathmartine Court Strathmartine Road",
    "iso:country":"GB",
    "sg:address":"Strathmartine Court, Strathmartine Road",
    "sg:city":"Dundee",
    "sg:classifiers":[
        {
            "category":"Organizations",
            "subcategory":"Community Association",
            "type":"Services"
        }
    ],
    "sg:phone":"+44 1382 858438",
    "sg:postcode":"DD3 9DG",
    "sg:province":"Dundee City",
    "sg:tags":[
        "co-operatives",
        "society",
        "housing",
        "trust"
    ],
    "sg:website":"http://www.bield.co.uk",
    "wof:name":"Bield Housing Association Ltd",
    "wof:placetype":"venue"
},
  "geometry": {"coordinates":[-3.0042390823,56.4979667664],"type":"Point"}
}