{
  "type": "Feature",
  "properties": {
    "iso:country":"GB",
    "sg:address":"Unit 2 Mancetter Sq, Lincoln Rd, Werrington",
    "sg:city":"Peterborough",
    "sg:classifiers":[
        {
            "category":"Sports & Exercise",
            "subcategory":"Gym",
            "type":"Entertainment"
        }
    ],
    "sg:postcode":"PE4 6BX",
    "sg:province":"Cambridgeshire",
    "sg:tags":[
        "fitness",
        "health",
        "centre"
    ],
    "wof:name":"Body Titan Health & Fitness Centre",
    "wof:placetype":"venue"
},
  "geometry": {"coordinates":[-0.2710889876,52.6142539978],"type":"Point"}
}