{
  "type": "Feature",
  "properties": {
    "iso:country":"GB",
    "sg:address":"24 Bailey St",
    "sg:city":"Manchester",
    "sg:classifiers":[
        {
            "category":"Professional",
            "subcategory":"Engineering",
            "type":"Services"
        }
    ],
    "sg:phone":"+44 161 371 7759",
    "sg:postcode":"M11 4PJ",
    "sg:province":"Greater Manchester",
    "sg:tags":[
        "contractor",
        "electrical",
        "engineer"
    ],
    "wof:name":"Fenton Security",
    "wof:placetype":"venue"
},
  "geometry": {"coordinates":[-2.1672439575,53.4805755615],"type":"Point"}
}