{
  "type": "Feature",
  "properties": {
    "addr:full":"276 Broadway Bexleyheath Kent DA6 8BE",
    "addr:housenumber":"276",
    "addr:postcode":"da6 8be",
    "addr:street":"Broadway",
    "iso:country":"GB",
    "sg:address":"276 Broadway",
    "sg:city":"Bexleyheath",
    "sg:classifiers":[
        {
            "category":"Professional",
            "subcategory":"Art Services",
            "type":"Services"
        }
    ],
    "sg:phone":"+44 20 8303 1052",
    "sg:postcode":"DA6 8BE",
    "sg:province":"Kent",
    "sg:tags":[
        "photographer"
    ],
    "wof:name":"Ebdon Studios",
    "wof:placetype":"venue"
},
  "geometry": {"coordinates":[0.1351889968,51.4580574036],"type":"Point"}
}