{
  "type": "Feature",
  "properties": {
    "iso:country":"GB",
    "sg:address":"Thorp Arch Trading Estate",
    "sg:city":"Wetherby",
    "sg:classifiers":[
        {
            "category":"Home & Garden",
            "subcategory":"Home Furnishings",
            "type":"Retail Goods"
        }
    ],
    "sg:phone":"+44 1937 844288",
    "sg:postcode":"LS23 7BJ",
    "sg:province":"West Yorkshire",
    "sg:tags":[
        "furnishers",
        "planner",
        "kitchen"
    ],
    "wof:name":"Buywell Kitchens",
    "wof:placetype":"venue"
},
  "geometry": {"coordinates":[-1.3422989845,53.9077148438],"type":"Point"}
}