{
  "type": "Feature",
  "properties": {
    "addr:full":"5 The Coda Centre, Munster Rd Fulham Greater London SW6 6AW",
    "addr:housenumber":"5",
    "addr:postcode":"sw6 6aw",
    "addr:street":"The;Munster Rd",
    "iso:country":"GB",
    "sg:address":"5 The Coda Centre, Munster Rd",
    "sg:city":"Fulham",
    "sg:classifiers":[
        {
            "category":"Professional",
            "subcategory":"Business Services",
            "type":"Services"
        }
    ],
    "sg:phone":"+44 20 7386 1948",
    "sg:postcode":"SW6 6AW",
    "sg:province":"Greater London",
    "sg:tags":[
        "import",
        "export",
        "agent"
    ],
    "wof:name":"Tinnis International Ltd",
    "wof:placetype":"venue"
},
  "geometry": {"coordinates":[-0.211964,51.47834],"type":"Point"}
}