{
  "type": "Feature",
  "properties": {
    "addr:full":"Unit 4 61 Spencer Road Bradford West Yorkshire BD7 2HD",
    "addr:housenumber":"unit;61",
    "addr:postcode":"bd7 2hd",
    "addr:street":"Spencer Road",
    "iso:country":"GB",
    "sg:address":"Unit 4 61 Spencer Road",
    "sg:city":"Bradford",
    "sg:classifiers":[
        {
            "category":"Manufacturing",
            "subcategory":"Signs",
            "type":"Manufacturing & Wholesale Goods"
        }
    ],
    "sg:postcode":"BD7 2HD",
    "sg:province":"West Yorkshire",
    "sg:tags":[
        "writer"
    ],
    "wof:name":"Daymonds of Bradford",
    "wof:placetype":"venue"
},
  "geometry": {"coordinates":[-1.7865070105,53.7851142883],"type":"Point"}
}