{
  "type": "Feature",
  "properties": {
    "addr:full":"8 Brooklands Terrace Rossendale Lancashire BB4 7DP",
    "addr:housenumber":"8",
    "addr:postcode":"bb4 7dp",
    "addr:street":"Brooklands Terrace",
    "iso:country":"GB",
    "sg:address":"8 Brooklands Terrace",
    "sg:city":"Rossendale",
    "sg:classifiers":[
        {
            "category":"Professional",
            "subcategory":"Engineering",
            "type":"Services"
        }
    ],
    "sg:phone":"+44 1706 211422",
    "sg:postcode":"BB4 7DP",
    "sg:province":"Lancashire",
    "sg:tags":[
        "consultant",
        "structural"
    ],
    "wof:name":"Impact Analysis Services Ltd.",
    "wof:placetype":"venue"
},
  "geometry": {"coordinates":[-2.250734,53.686924],"type":"Point"}
}