{
  "type": "Feature",
  "properties": {
    "addr:full":"9 St Wilfrids Park Lancaster Lancashire LA2 6PN",
    "addr:housenumber":"9",
    "addr:postcode":"la2 6pn",
    "addr:street":"St Wilfrids Park",
    "iso:country":"GB",
    "sg:address":"9 St Wilfrids Park",
    "sg:city":"Lancaster",
    "sg:classifiers":[
        {
            "category":"Shopping",
            "subcategory":"News",
            "type":"Retail Goods"
        }
    ],
    "sg:phone":"+44 1524 811507",
    "sg:postcode":"LA2 6PN",
    "sg:province":"Lancashire",
    "sg:tags":[
        "newsagent"
    ],
    "wof:name":"Halton Stores",
    "wof:placetype":"venue"
},
  "geometry": {"coordinates":[-2.7631819248,54.0781364441],"type":"Point"}
}