{
  "type": "Feature",
  "properties": {
    "addr:full":"58 Church Street, Ruddington Nottingham Nottinghamshire NG11 6HD",
    "addr:housenumber":"58",
    "addr:postcode":"ng11 6hd",
    "addr:street":"Church Street",
    "iso:country":"GB",
    "sg:address":"58 Church Street, Ruddington",
    "sg:city":"Nottingham",
    "sg:classifiers":[
        {
            "category":"Food & Beverages",
            "subcategory":"Bakery",
            "type":"Retail Goods"
        }
    ],
    "sg:phone":"+44 115 921 6802",
    "sg:postcode":"NG11 6HD",
    "sg:province":"Nottinghamshire",
    "sg:tags":[
        "baker"
    ],
    "wof:name":"Horspools Bakery Ltd.",
    "wof:placetype":"venue"
},
  "geometry": {"coordinates":[-1.1510829926,52.8908805847],"type":"Point"}
}