{
  "type": "Feature",
  "properties": {
    "addr:full":"High Street Doncaster North Yorkshire DN6 9EL",
    "addr:postcode":"dn6 9el",
    "addr:street":"High Street",
    "iso:country":"GB",
    "sg:address":"High Street",
    "sg:city":"Doncaster",
    "sg:classifiers":[
        {
            "category":"Communications",
            "type":"Services"
        },
        {
            "category":"Home & Garden",
            "subcategory":"Furniture",
            "type":"Retail Goods"
        }
    ],
    "sg:phone":"+44 1302 701002",
    "sg:postcode":"DN6 9EL",
    "sg:province":"North Yorkshire",
    "sg:tags":[
        "tv",
        "video",
        "radio"
    ],
    "wof:name":"Stables Antique Shop",
    "wof:placetype":"venue"
},
  "geometry": {"coordinates":[-1.1830179691,53.6185455322],"type":"Point"}
}