{
  "type": "Feature",
  "properties": {
    "addr:full":"60 Manor Avenue, Brockley London Greater London SE4 1TE",
    "addr:housenumber":"60",
    "addr:postcode":"se4 1te",
    "addr:street":"Manor Avenue",
    "iso:country":"GB",
    "sg:address":"60 Manor Avenue, Brockley",
    "sg:city":"London",
    "sg:classifiers":[
        {
            "category":"Organizations",
            "subcategory":"Membership Organization",
            "type":"Services"
        }
    ],
    "sg:phone":"+44 20 8692 3445",
    "sg:postcode":"SE4 1TE",
    "sg:province":"Greater London",
    "sg:tags":[
        "club"
    ],
    "wof:name":"United Services",
    "wof:placetype":"venue"
},
  "geometry": {"coordinates":[-0.031534,51.467987],"type":"Point"}
}