{
  "type": "Feature",
  "properties": {
    "iso:country":"GB",
    "sg:address":"12 Montpelier Road",
    "sg:city":"Brighton",
    "sg:classifiers":[
        {
            "category":"Travel",
            "subcategory":"Hotels & Motels",
            "type":"Entertainment"
        }
    ],
    "sg:postcode":"BN1 2LQ",
    "sg:province":"East Sussex",
    "sg:tags":[
        "house",
        "guest"
    ],
    "wof:name":"Whitburn Lodge Guest House",
    "wof:placetype":"venue"
},
  "geometry": {"coordinates":[-0.1536570042,50.8238105774],"type":"Point"}
}