{
  "type": "Feature",
  "properties": {
    "iso:country":"GB",
    "sg:address":"6 Downsview Drive",
    "sg:city":"Midhurst",
    "sg:classifiers":[
        {
            "category":"Building & Trades",
            "subcategory":"Construction",
            "type":"Services"
        }
    ],
    "sg:postcode":"GU29 9LW",
    "sg:province":"West Sussex",
    "sg:tags":[
        "decorator",
        "painter"
    ],
    "wof:name":"H & L Etherington & Son",
    "wof:placetype":"venue"
},
  "geometry": {"coordinates":[-0.745343,50.97673],"type":"Point"}
}