{
  "type": "Feature",
  "properties": {
    "iso:country":"GB",
    "sg:address":"Leggsheath La",
    "sg:city":"East Grinstead",
    "sg:classifiers":[
        {
            "category":"Building & Trades",
            "subcategory":"Construction",
            "type":"Services"
        }
    ],
    "sg:phone":"+44 1342 836606",
    "sg:postcode":"RH19 4JN",
    "sg:province":"East Sussex",
    "sg:tags":[
        "builder"
    ],
    "wof:name":"Badger Construction",
    "wof:placetype":"venue"
},
  "geometry": {"coordinates":[-0.025828,51.089462],"type":"Point"}
}