{
  "type": "Feature",
  "properties": {
    "iso:country":"GB",
    "sg:address":"49 High St, Needingworth St Ives",
    "sg:city":"Huntingdon",
    "sg:classifiers":[
        {
            "category":"Building & Trades",
            "subcategory":"Construction",
            "type":"Services"
        }
    ],
    "sg:phone":"+44 1480 463034",
    "sg:postcode":"PE17 3SB",
    "sg:province":"Cambridgeshire",
    "sg:tags":[
        "decorator",
        "painter"
    ],
    "wof:name":"E.J Parish & Son",
    "wof:placetype":"venue"
},
  "geometry": {"coordinates":[-0.0304000005,52.3305702209],"type":"Point"}
}