{
  "type": "Feature",
  "properties": {
    "iso:country":"GB",
    "sg:address":"1 Tynewydd Road",
    "sg:city":"Barry",
    "sg:classifiers":[
        {
            "category":"Travel",
            "subcategory":"Travel Agent",
            "type":"Entertainment"
        }
    ],
    "sg:phone":"+44 1446 734249",
    "sg:postcode":"CF62 8HB",
    "sg:province":"The Vale of Glamorgan",
    "wof:name":"Mytravel",
    "wof:placetype":"venue"
},
  "geometry": {"coordinates":[-3.267316103,51.4064369202],"type":"Point"}
}