{
  "type": "Feature",
  "properties": {
    "iso:country":"GB",
    "sg:address":"32 Jamaica St",
    "sg:city":"Bristol",
    "sg:classifiers":[
        {
            "category":"Professional",
            "subcategory":"Art Services",
            "type":"Services"
        }
    ],
    "sg:postcode":"BS2 8JW",
    "sg:province":"City of Bristol",
    "sg:tags":[
        "photographer"
    ],
    "wof:name":"Holliday,Garry,",
    "wof:placetype":"venue"
},
  "geometry": {"coordinates":[-2.5906839371,51.4622612],"type":"Point"}
}