{
  "type": "Feature",
  "properties": {
    "iso:country":"GB",
    "sg:address":"84 Harley Street",
    "sg:city":"London",
    "sg:classifiers":[
        {
            "category":"Health Services",
            "subcategory":"Doctor",
            "type":"Services"
        }
    ],
    "sg:phone":"+44 20 7079 4214",
    "sg:postcode":"W1G 7HW",
    "sg:province":"Greater London",
    "sg:tags":[
        "surgeon"
    ],
    "wof:name":"Kenneth J Waters",
    "wof:placetype":"venue"
},
  "geometry": {"coordinates":[-0.1473390013,51.5203208923],"type":"Point"}
}