{
  "type": "Feature",
  "properties": {
    "iso:country":"GB",
    "sg:address":"17 Georges Hill",
    "sg:city":"High Wycombe",
    "sg:classifiers":[
        {
            "category":"Home & Garden",
            "subcategory":"Carpets & Floor Coverings",
            "type":"Retail Goods"
        }
    ],
    "sg:postcode":"HP15 6BE",
    "sg:province":"Buckinghamshire",
    "sg:tags":[
        "carpets",
        "rug",
        "matting"
    ],
    "wof:name":"S T F Flooring",
    "wof:placetype":"venue"
},
  "geometry": {"coordinates":[-0.720312,51.663467],"type":"Point"}
}