{
  "type": "Feature",
  "properties": {
    "addr:full":"88 Gloucester Road Brighton East Sussex BN1 4AP",
    "addr:housenumber":"88",
    "addr:postcode":"bn1 4ap",
    "addr:street":"Gloucester Road",
    "iso:country":"GB",
    "sg:address":"88 Gloucester Road",
    "sg:city":"Brighton",
    "sg:classifiers":[
        {
            "category":"Shopping",
            "subcategory":"Antiques",
            "type":"Retail Goods"
        }
    ],
    "sg:postcode":"BN1 4AP",
    "sg:province":"East Sussex",
    "wof:name":"Anthony White",
    "wof:placetype":"venue"
},
  "geometry": {"coordinates":[-0.1399810016,50.8271369934],"type":"Point"}
}