{
  "type": "Feature",
  "properties": {
    "iso:country":"GB",
    "sg:address":"136 Neilston Road",
    "sg:city":"Paisley",
    "sg:classifiers":[
        {
            "category":"Retail",
            "subcategory":"Auto Repair",
            "type":"Services"
        }
    ],
    "sg:phone":"+44 141 580 1070",
    "sg:postcode":"PA2 6QH",
    "sg:province":"East Renfrewshire",
    "sg:tags":[
        "modification",
        "garage"
    ],
    "wof:name":"William Waddell",
    "wof:placetype":"venue"
},
  "geometry": {"coordinates":[-4.4230232239,55.8306159973],"type":"Point"}
}