{
  "type": "Feature",
  "properties": {
    "addr:full":"Unit 3 Dulwich Business Centre, 70 Malham Rd Forest Hill Greater London SE23 1AH",
    "addr:housenumber":"unit 3;70",
    "addr:postcode":"se23 1ah",
    "addr:street":"Dulwich Business;Malham Rd",
    "iso:country":"GB",
    "sg:address":"Unit 3 Dulwich Business Centre, 70 Malham Rd",
    "sg:city":"Forest Hill",
    "sg:classifiers":[
        {
            "category":"Retail",
            "subcategory":"Repair Shop",
            "type":"Services"
        }
    ],
    "sg:phone":"+44 20 8291 6888",
    "sg:postcode":"SE23 1AH",
    "sg:province":"Greater London",
    "sg:tags":[
        "upholsterer"
    ],
    "wof:name":"Roy Alan Upholstery",
    "wof:placetype":"venue"
},
  "geometry": {"coordinates":[-0.0481129996,51.4410514832],"type":"Point"}
}