{
  "type": "Feature",
  "properties": {
    "addr:full":"Far Corkhill Farm, Corkhill Lane, Kirklington Newark Nottinghamshire NG22 8NP",
    "addr:postcode":"ng22 8np",
    "addr:street":"Corkhill Lane",
    "iso:country":"GB",
    "sg:address":"Far Corkhill Farm, Corkhill Lane, Kirklington",
    "sg:city":"Newark",
    "sg:classifiers":[
        {
            "category":"Farming",
            "subcategory":"Crops",
            "type":"Manufacturing & Wholesale Goods"
        },
        {
            "category":"Farming",
            "subcategory":"Farm",
            "type":"Manufacturing & Wholesale Goods"
        }
    ],
    "sg:phone":"+44 1636 813328",
    "sg:postcode":"NG22 8NP",
    "sg:province":"Nottinghamshire",
    "sg:tags":[
        "mixed",
        "arable"
    ],
    "wof:name":"J B & M E ASHWORTH",
    "wof:placetype":"venue"
},
  "geometry": {"coordinates":[-0.989989,53.111694],"type":"Point"}
}