{
  "type": "Feature",
  "properties": {
    "iso:country":"GB",
    "sg:address":"10 The Hyde",
    "sg:city":"Stevenage",
    "sg:classifiers":[
        {
            "category":"Shopping",
            "subcategory":"Discount & Variety Stores",
            "type":"Retail Goods"
        }
    ],
    "sg:phone":"+44 1438 740404",
    "sg:postcode":"SG2 9SE",
    "sg:province":"Hertfordshire",
    "sg:tags":[
        "shop",
        "model"
    ],
    "wof:name":"Models in Motion",
    "wof:placetype":"venue"
},
  "geometry": {"coordinates":[-0.169568,51.892418],"type":"Point"}
}