{
  "type": "Feature",
  "properties": {
    "iso:country":"GB",
    "sg:address":"17 St John's Lane",
    "sg:city":"Gloucester",
    "sg:classifiers":[
        {
            "category":"Professional",
            "subcategory":"Lawyer & Legal Services",
            "type":"Services"
        }
    ],
    "sg:phone":"+44 1452 525351",
    "sg:postcode":"GL1 2AZ",
    "sg:province":"Gloucestershire",
    "sg:tags":[
        "solicitor"
    ],
    "wof:name":"Treasures",
    "wof:placetype":"venue"
},
  "geometry": {"coordinates":[-2.24541,51.866508],"type":"Point"}
}