{
  "type": "Feature",
  "properties": {
    "addr:full":"20 Windrush Clo, Bramley Guildford Surrey GU5 0BB",
    "addr:housenumber":"20;clo",
    "addr:postcode":"gu5 0bb",
    "addr:street":"Bramley",
    "iso:country":"GB",
    "sg:address":"20 Windrush Clo, Bramley",
    "sg:city":"Guildford",
    "sg:classifiers":[
        {
            "category":"Education",
            "subcategory":"University",
            "type":"Public Place"
        }
    ],
    "sg:postcode":"GU5 0BB",
    "sg:province":"Surrey",
    "sg:tags":[
        "higher"
    ],
    "wof:name":"Thomas,Sian,",
    "wof:placetype":"venue"
},
  "geometry": {"coordinates":[-0.5559729934,51.1936798096],"type":"Point"}
}