{
  "type": "Feature",
  "properties": {
    "iso:country":"GB",
    "sg:address":"42 Victoria St",
    "sg:city":"Oldham",
    "sg:classifiers":[
        {
            "category":"Professional",
            "subcategory":"Engineering",
            "type":"Services"
        }
    ],
    "sg:phone":"+44 161 652 5404",
    "sg:postcode":"OL9 0HQ",
    "sg:province":"Lancashire",
    "sg:tags":[
        "contractor",
        "electrical",
        "engineer"
    ],
    "wof:name":"Alan Malpass Electrical Services",
    "wof:placetype":"venue"
},
  "geometry": {"coordinates":[-2.137346983,53.5458145142],"type":"Point"}
}