{
  "type": "Feature",
  "properties": {
    "addr:full":"769 Becontree Avenue Dagenham Essex RM8 3HH",
    "addr:housenumber":"769",
    "addr:postcode":"rm8 3hh",
    "addr:street":"Becontree Avenue",
    "iso:country":"GB",
    "sg:address":"769 Becontree Avenue",
    "sg:city":"Dagenham",
    "sg:classifiers":[
        {
            "category":"Real Estate",
            "subcategory":"Real Estate Agent",
            "type":"Services"
        }
    ],
    "sg:phone":"+44 20 8984 7050",
    "sg:postcode":"RM8 3HH",
    "sg:province":"Essex",
    "wof:name":"Courtney Rose Williams",
    "wof:placetype":"venue"
},
  "geometry": {"coordinates":[0.146861,51.560513],"type":"Point"}
}