{
  "type": "Feature",
  "properties": {
    "addr:full":"6 Market Square Lytham St Annes Lancashire FY8 5LW",
    "addr:housenumber":"6",
    "addr:postcode":"fy8 5lw",
    "addr:street":"Market Square;St",
    "iso:country":"GB",
    "sg:address":"6 Market Square",
    "sg:city":"Lytham St Annes",
    "sg:classifiers":[
        {
            "category":"Organizations",
            "subcategory":"Non-profit Organization",
            "type":"Services"
        }
    ],
    "sg:phone":"+44 1253 794980",
    "sg:postcode":"FY8 5LW",
    "sg:province":"Lancashire",
    "sg:tags":[
        "charitable",
        "organisation",
        "voluntary",
        "charity"
    ],
    "wof:name":"THE CANCER RESEARCH CAMPAIGN",
    "wof:placetype":"venue"
},
  "geometry": {"coordinates":[-2.963962,53.737011],"type":"Point"}
}