{
  "type": "Feature",
  "properties": {
    "iso:country":"GB",
    "sg:address":"Stocksbridge Golf Club, 30 Royd Lane",
    "sg:city":"Sheffield",
    "sg:classifiers":[
        {
            "category":"Sports & Exercise",
            "subcategory":"Golf",
            "type":"Entertainment"
        }
    ],
    "sg:phone":"+44 114 288 2779",
    "sg:postcode":"S36 2RZ",
    "sg:province":"South Yorkshire",
    "sg:tags":[
        "club",
        "course",
        "equipment"
    ],
    "wof:name":"Professional Shop",
    "wof:placetype":"venue"
},
  "geometry": {"coordinates":[-1.57929,53.471291],"type":"Point"}
}