{
  "type": "Feature",
  "properties": {
    "iso:country":"GB",
    "sg:address":"Saracens Ho, 25 St. Margarets Grn",
    "sg:city":"Ipswich",
    "sg:classifiers":[
        {
            "category":"Professional",
            "subcategory":"Business Services",
            "type":"Services"
        }
    ],
    "sg:postcode":"IP4 2BN",
    "sg:province":"Suffolk",
    "sg:tags":[
        "shop",
        "cleaning"
    ],
    "wof:name":"Professional Cleaning Services",
    "wof:placetype":"venue"
},
  "geometry": {"coordinates":[1.1584299803,52.0591011047],"type":"Point"}
}