{
  "type": "Feature",
  "properties": {
    "iso:country":"GB",
    "sg:address":"35 Woodville Gardens, Ealing",
    "sg:city":"London",
    "sg:classifiers":[
        {
            "category":"Professional",
            "subcategory":"Accounting & Tax Preparation",
            "type":"Services"
        }
    ],
    "sg:postcode":"W5 2LL",
    "sg:province":"Greater London",
    "sg:tags":[
        "accountant"
    ],
    "wof:name":"Davidson's",
    "wof:placetype":"venue"
},
  "geometry": {"coordinates":[-0.293065,51.518303],"type":"Point"}
}