{
  "type": "Feature",
  "properties": {
    "iso:country":"GB",
    "sg:address":"20 Bracebridge Street",
    "sg:city":"Nuneaton",
    "sg:classifiers":[
        {
            "category":"Retail",
            "subcategory":"Auto Repair",
            "type":"Services"
        }
    ],
    "sg:phone":"+44 24 7664 1186",
    "sg:postcode":"CV11 5PA",
    "sg:province":"Leicestershire",
    "sg:tags":[
        "car",
        "upholsterer"
    ],
    "wof:name":"Pro-Trim",
    "wof:placetype":"venue"
},
  "geometry": {"coordinates":[-1.475624,52.521614],"type":"Point"}
}