{
  "type": "Feature",
  "properties": {
    "iso:country":"GB",
    "sg:address":"43 Whitefields Road",
    "sg:city":"Solihull",
    "sg:classifiers":[
        {
            "category":"Shopping",
            "subcategory":"Bicycles & Sporting Goods",
            "type":"Retail Goods"
        },
        {
            "category":"Sports & Exercise",
            "subcategory":"Sports Center",
            "type":"Entertainment"
        }
    ],
    "sg:phone":"+44 121 711 4349",
    "sg:postcode":"B91 3NX",
    "sg:province":"West Midlands",
    "sg:tags":[
        "shop",
        "sale"
    ],
    "wof:name":"Quick String",
    "wof:placetype":"venue"
},
  "geometry": {"coordinates":[-1.78216,52.406837],"type":"Point"}
}