{
  "type": "Feature",
  "properties": {
    "addr:full":"Unit 11, Withy Wells Farm, Spetchley Worcester Worcestershire WR5 1RW",
    "addr:housenumber":"unit 11 withy",
    "addr:postcode":"wr5 1rw",
    "addr:street":"Wells Farm",
    "iso:country":"GB",
    "sg:address":"Unit 11, Withy Wells Farm, Spetchley",
    "sg:city":"Worcester",
    "sg:classifiers":[
        {
            "category":"Retail",
            "subcategory":"Storage",
            "type":"Services"
        }
    ],
    "sg:phone":"+44 1905 345488",
    "sg:postcode":"WR5 1RW",
    "sg:province":"Worcestershire",
    "sg:tags":[
        "household",
        "removal"
    ],
    "wof:name":"Phil the Van",
    "wof:placetype":"venue"
},
  "geometry": {"coordinates":[-2.156856,52.184364],"type":"Point"}
}