{
  "type": "Feature",
  "properties": {
    "iso:country":"GB",
    "sg:address":"Unit 1, Monyneux Court, Radford Way",
    "sg:city":"Billericay",
    "sg:classifiers":[
        {
            "category":"Building & Trades",
            "subcategory":"Construction",
            "type":"Services"
        }
    ],
    "sg:phone":"+44 1277 633400",
    "sg:postcode":"CM12 0BT",
    "sg:province":"Essex",
    "sg:tags":[
        "restoration",
        "refurbishment"
    ],
    "wof:name":"M J Ferguson Ltd.",
    "wof:placetype":"venue"
},
  "geometry": {"coordinates":[0.416556,51.629608],"type":"Point"}
}