{
  "type": "Feature",
  "properties": {
    "addr:full":"193 Queens Cres Kentish Town Greater London NW5 4DS",
    "addr:housenumber":"193",
    "addr:postcode":"nw5 4ds",
    "addr:street":"Queens Cres",
    "iso:country":"GB",
    "sg:address":"193 Queens Cres",
    "sg:city":"Kentish Town",
    "sg:classifiers":[
        {
            "category":"Professional",
            "type":"Services"
        }
    ],
    "sg:phone":"+44 20 7267 3691",
    "sg:postcode":"NW5 4DS",
    "sg:province":"Greater London",
    "sg:tags":[
        "interior",
        "furnishers",
        "designer"
    ],
    "wof:name":"VOG Design Ltd",
    "wof:placetype":"venue"
},
  "geometry": {"coordinates":[-0.149659,51.550831],"type":"Point"}
}