{
  "type": "Feature",
  "properties": {
    "iso:country":"GB",
    "sg:address":"54 Wandsworth Rd, South Lambeth",
    "sg:city":"South Lambeth",
    "sg:classifiers":[
        {
            "category":"Autos & Motor Vehicles",
            "subcategory":"Fuel & Gas Station",
            "type":"Retail Goods"
        }
    ],
    "sg:phone":"+44 20 7622 2373",
    "sg:postcode":"SW8 2LF",
    "sg:province":"Greater London",
    "sg:tags":[
        "hr",
        "petrol"
    ],
    "wof:name":"Nine Elms Service Station",
    "wof:placetype":"venue"
},
  "geometry": {"coordinates":[-0.132441,51.474663],"type":"Point"}
}