{
  "type": "Feature",
  "properties": {
    "addr:full":"40 Waterloo Road Blackpool Lancashire FY4 1AD",
    "addr:housenumber":"40",
    "addr:postcode":"fy4 1ad",
    "addr:street":"Waterloo Road",
    "iso:country":"GB",
    "sg:address":"40 Waterloo Road",
    "sg:city":"Blackpool",
    "sg:classifiers":[
        {
            "category":"Shopping",
            "subcategory":"Department Store",
            "type":"Retail Goods"
        }
    ],
    "sg:phone":"+44 1253 402227",
    "sg:postcode":"FY4 1AD",
    "sg:province":"Lancashire",
    "wof:name":"Spar Post Office",
    "wof:placetype":"venue"
},
  "geometry": {"coordinates":[-3.053271,53.798851],"type":"Point"}
}