{
  "type": "Feature",
  "properties": {
    "addr:full":"43 Rose Bank Terrace Aberdeen Aberdeen City AB11 6LQ",
    "addr:housenumber":"43",
    "addr:postcode":"ab11 6lq",
    "addr:street":"Rose Bank Terrace",
    "iso:country":"GB",
    "sg:address":"43 Rose Bank Terrace",
    "sg:city":"Aberdeen",
    "sg:classifiers":[
        {
            "category":"Professional",
            "subcategory":"Detective & Security Services",
            "type":"Services"
        }
    ],
    "sg:phone":"+44 1224 594200",
    "sg:postcode":"AB11 6LQ",
    "sg:province":"Aberdeen City",
    "sg:tags":[
        "locksmith"
    ],
    "wof:name":"J L M Security",
    "wof:placetype":"venue"
},
  "geometry": {"coordinates":[-2.1043539047,57.1400871277],"type":"Point"}
}