{
  "type": "Feature",
  "properties": {
    "iso:country":"GB",
    "sg:address":"14 Beeches Walk",
    "sg:city":"Sutton Coldfield",
    "sg:classifiers":[
        {
            "category":"Shopping",
            "subcategory":"Mobile Phones",
            "type":"Retail Goods"
        }
    ],
    "sg:postcode":"B73 6HN",
    "sg:province":"West Midlands",
    "sg:tags":[
        "supplier"
    ],
    "wof:name":"Intercity Mobile Communications Ltd",
    "wof:placetype":"venue"
},
  "geometry": {"coordinates":[-1.8284070492,52.5544548035],"type":"Point"}
}