{
  "type": "Feature",
  "properties": {
    "addr:full":"Mill Garage, Maryland Wells Next The Sea Norfolk NR23 1LX",
    "addr:postcode":"nr23 1lx",
    "addr:street":"The",
    "iso:country":"GB",
    "sg:address":"Mill Garage, Maryland",
    "sg:city":"Wells Next The Sea",
    "sg:classifiers":[
        {
            "category":"Professional",
            "type":"Services"
        }
    ],
    "sg:phone":"+44 1328 710117",
    "sg:postcode":"NR23 1LX",
    "sg:province":"Norfolk",
    "sg:tags":[
        "marine"
    ],
    "wof:name":"Wells Marine Services",
    "wof:placetype":"venue"
},
  "geometry": {"coordinates":[0.8558099866,52.9526443481],"type":"Point"}
}