{
  "type": "Feature",
  "properties": {
    "addr:full":"Pack Horse Court Keswick Cumbria CA12 5JB",
    "addr:postcode":"ca12 5jb",
    "addr:street":"Court",
    "iso:country":"GB",
    "sg:address":"Pack Horse Court",
    "sg:city":"Keswick",
    "sg:classifiers":[
        {
            "category":"Bars & Pubs",
            "type":"Food & Drink"
        },
        {
            "category":"Community Center",
            "subcategory":"Social",
            "type":"Public Place"
        }
    ],
    "sg:phone":"+44 871 529 8049",
    "sg:postcode":"CA12 5JB",
    "sg:province":"Cumbria",
    "sg:tags":[
        "pubs",
        "house",
        "inn",
        "activity"
    ],
    "wof:name":"Pack Horse Inn",
    "wof:placetype":"venue"
},
  "geometry": {"coordinates":[-3.1389639378,54.6017303467],"type":"Point"}
}