{
  "type": "Feature",
  "properties": {
    "addr:full":"5 Harrow Close Chessington Surrey KT9 2HR",
    "addr:housenumber":"5",
    "addr:postcode":"kt9 2hr",
    "addr:street":"Harrow Close",
    "iso:country":"GB",
    "sg:address":"5 Harrow Close",
    "sg:city":"Chessington",
    "sg:classifiers":[
        {
            "category":"Building & Trades",
            "subcategory":"Landscaping Services",
            "type":"Services"
        }
    ],
    "sg:postcode":"KT9 2HR",
    "sg:province":"Surrey",
    "sg:tags":[
        "gardening"
    ],
    "wof:name":"Intelligent Donkeys",
    "wof:placetype":"venue"
},
  "geometry": {"coordinates":[-0.310372,51.357841],"type":"Point"}
}