{
  "type": "Feature",
  "properties": {
    "addr:full":"14 Market Place Coleford Gloucestershire GL16 8AW",
    "addr:housenumber":"14",
    "addr:postcode":"gl16 8aw",
    "addr:street":"Market Place",
    "iso:country":"GB",
    "sg:address":"14 Market Place",
    "sg:city":"Coleford",
    "sg:classifiers":[
        {
            "category":"Social Services",
            "type":"Services"
        },
        {
            "category":"Shopping",
            "subcategory":"Thrift Store",
            "type":"Retail Goods"
        }
    ],
    "sg:phone":"+44 1594 836043",
    "sg:postcode":"GL16 8AW",
    "sg:province":"Gloucestershire",
    "sg:tags":[
        "shop",
        "ds",
        "charity"
    ],
    "wof:name":"VOLUNTARY SOCIAL AID",
    "wof:placetype":"venue"
},
  "geometry": {"coordinates":[-2.617001,51.793873],"type":"Point"}
}