{
  "type": "Feature",
  "properties": {
    "iso:country":"GB",
    "sg:address":"Unit 1 Dunstan Place, Dunstan Road, Whittington Moor",
    "sg:city":"Chesterfield",
    "sg:classifiers":[
        {
            "category":"Professional",
            "subcategory":"Engineering",
            "type":"Services"
        }
    ],
    "sg:phone":"+44 1246 268678",
    "sg:postcode":"S41 8XA",
    "sg:province":"Derbyshire",
    "sg:tags":[
        "contractor",
        "electrical",
        "engineer"
    ],
    "wof:name":"E M E G Electrical Ltd.",
    "wof:placetype":"venue"
},
  "geometry": {"coordinates":[-1.432029,53.260101],"type":"Point"}
}