{
  "type": "Feature",
  "properties": {
    "addr:full":"Linthouse Lane Wolverhampton Staffordshire WV11 3EA",
    "addr:postcode":"wv11 3ea",
    "addr:street":"Linthouse Lane",
    "iso:country":"GB",
    "sg:address":"Linthouse Lane",
    "sg:city":"Wolverhampton",
    "sg:classifiers":[
        {
            "category":"Professional",
            "subcategory":"Business Services",
            "type":"Services"
        }
    ],
    "sg:phone":"+44 1902 737444",
    "sg:postcode":"WV11 3EA",
    "sg:province":"Staffordshire",
    "sg:tags":[
        "bookmaker"
    ],
    "wof:name":"Star Racing",
    "wof:placetype":"venue"
},
  "geometry": {"coordinates":[-2.0719940662,52.6127281189],"type":"Point"}
}