{
  "type": "Feature",
  "properties": {
    "addr:full":"2 Towerfield Close, Shoeburyness Southend-on-sea Essex SS3 9QP",
    "addr:housenumber":"2",
    "addr:postcode":"ss3 9qp",
    "addr:street":"Towerfield Close",
    "iso:country":"GB",
    "sg:address":"2 Towerfield Close, Shoeburyness",
    "sg:city":"Southend-on-sea",
    "sg:classifiers":[
        {
            "category":"Manufacturing",
            "subcategory":"Metals",
            "type":"Manufacturing & Wholesale Goods"
        }
    ],
    "sg:postcode":"SS3 9QP",
    "sg:province":"Essex",
    "wof:name":"Towerfield Plating & Anodising",
    "wof:placetype":"venue"
},
  "geometry": {"coordinates":[0.788076,51.531799],"type":"Point"}
}