{
  "type": "Feature",
  "properties": {
    "iso:country":"GB",
    "sg:address":"New Shop, St. Buryan",
    "sg:city":"Penzance",
    "sg:classifiers":[
        {
            "category":"Building & Trades",
            "subcategory":"Construction",
            "type":"Services"
        }
    ],
    "sg:phone":"+44 1736 871210",
    "sg:postcode":"TR19 6JA",
    "sg:province":"Cornwall",
    "sg:tags":[
        "joiner",
        "carpenter"
    ],
    "wof:name":"W.C Matthews & Son",
    "wof:placetype":"venue"
},
  "geometry": {"coordinates":[-5.637521,50.053276],"type":"Point"}
}