{
  "type": "Feature",
  "properties": {
    "addr:full":"Holybourne Avenue London Greater London SW15 4JE",
    "addr:postcode":"sw15 4je",
    "addr:street":"Holybourne Avenue",
    "iso:country":"GB",
    "sg:address":"Holybourne Avenue",
    "sg:city":"London",
    "sg:classifiers":[
        {
            "category":"Community Center",
            "subcategory":"Youth",
            "type":"Public Place"
        }
    ],
    "sg:phone":"+44 20 8788 3377",
    "sg:postcode":"SW15 4JE",
    "sg:province":"Greater London",
    "sg:tags":[
        "organisation",
        "centre"
    ],
    "wof:name":"Roehampton Boys Youth Club",
    "wof:placetype":"venue"
},
  "geometry": {"coordinates":[-0.241489,51.448185],"type":"Point"}
}