{
  "type": "Feature",
  "properties": {
    "addr:full":"Ginnel, Ash Street Windermere Cumbria LA23 3EB",
    "addr:postcode":"la23 3eb",
    "addr:street":"Ash Street",
    "iso:country":"GB",
    "sg:address":"Ginnel, Ash Street",
    "sg:city":"Windermere",
    "sg:classifiers":[
        {
            "category":"Shopping",
            "subcategory":"Gifts & Souvenirs",
            "type":"Retail Goods"
        }
    ],
    "sg:phone":"+44 15394 46298",
    "sg:postcode":"LA23 3EB",
    "sg:province":"Cumbria",
    "sg:tags":[
        "shop"
    ],
    "wof:name":"Things",
    "wof:placetype":"venue"
},
  "geometry": {"coordinates":[-2.9224359989,54.3628692627],"type":"Point"}
}