{
  "type": "Feature",
  "properties": {
    "iso:country":"GB",
    "sg:address":"44 Reinden Gro, Otham",
    "sg:city":"Maidstone",
    "sg:classifiers":[
        {
            "category":"Autos & Motor Vehicles",
            "subcategory":"Auto Supplies",
            "type":"Retail Goods"
        },
        {
            "category":"Retail",
            "subcategory":"Auto Repair",
            "type":"Services"
        }
    ],
    "sg:postcode":"ME15 8TH",
    "sg:province":"Kent",
    "sg:tags":[
        "modification",
        "garage",
        "windscreen"
    ],
    "wof:name":"Grela,Lee,",
    "wof:placetype":"venue"
},
  "geometry": {"coordinates":[0.56316,51.260151],"type":"Point"}
}