{
  "type": "Feature",
  "properties": {
    "addr:full":"301 Ferry Road, Hullbridge Hockley Essex SS5 6NA",
    "addr:housenumber":"301",
    "addr:postcode":"ss5 6na",
    "addr:street":"Ferry Road;Hockley",
    "iso:country":"GB",
    "sg:address":"301 Ferry Road, Hullbridge",
    "sg:city":"Hockley",
    "sg:classifiers":[
        {
            "category":"Restaurant",
            "type":"Food & Drink"
        }
    ],
    "sg:phone":"+44 1702 231523",
    "sg:postcode":"SS5 6NA",
    "sg:province":"Essex",
    "sg:tags":[
        "indian"
    ],
    "wof:name":"Simla Tandoori",
    "wof:placetype":"venue"
},
  "geometry": {"coordinates":[0.6135010123,51.6290435791],"type":"Point"}
}