{
  "type": "Feature",
  "properties": {
    "addr:full":"53 Fore Street Trowbridge Wiltshire BA14 8ES",
    "addr:housenumber":"53",
    "addr:postcode":"ba14 8es",
    "addr:street":"Fore Street",
    "iso:country":"GB",
    "sg:address":"53 Fore Street",
    "sg:city":"Trowbridge",
    "sg:classifiers":[
        {
            "category":"Professional",
            "subcategory":"Art Services",
            "type":"Services"
        }
    ],
    "sg:phone":"+44 1225 774949",
    "sg:postcode":"BA14 8ES",
    "sg:province":"Wiltshire",
    "sg:tags":[
        "photographer"
    ],
    "wof:name":"P L M Studio",
    "wof:placetype":"venue"
},
  "geometry": {"coordinates":[-2.20784,51.321201],"type":"Point"}
}