{
  "type": "Feature",
  "properties": {
    "addr:full":"Moira Rd Ashby De La Zouch Derbyshire LE65 2GB",
    "addr:postcode":"le65 2gb",
    "addr:street":"Moira Rd",
    "iso:country":"GB",
    "sg:address":"Moira Rd",
    "sg:city":"Ashby De La Zouch",
    "sg:classifiers":[
        {
            "category":"Place Of Worship",
            "type":"Public Place"
        }
    ],
    "sg:phone":"+44 1530 412298",
    "sg:postcode":"LE65 2GB",
    "sg:province":"Derbyshire",
    "wof:name":"Moira Road Methodist Church",
    "wof:placetype":"venue"
},
  "geometry": {"coordinates":[-1.484678,52.745956],"type":"Point"}
}