{
  "type": "Feature",
  "properties": {
    "iso:country":"GB",
    "sg:address":"Unit M Quarry Road",
    "sg:city":"Newhaven",
    "sg:classifiers":[
        {
            "category":"Retail",
            "subcategory":"Auto Rental",
            "type":"Services"
        }
    ],
    "sg:postcode":"BN9 9DG",
    "sg:province":"East Sussex",
    "sg:tags":[
        "car"
    ],
    "wof:name":"Select Self Drive",
    "wof:placetype":"venue"
},
  "geometry": {"coordinates":[0.046175,50.795036],"type":"Point"}
}