{
  "type": "Feature",
  "properties": {
    "iso:country":"GB",
    "sg:address":"28 Dereham Road, Pudding Norton",
    "sg:city":"Fakenham",
    "sg:classifiers":[
        {
            "category":"Building & Trades",
            "subcategory":"Landscaping Services",
            "type":"Services"
        }
    ],
    "sg:phone":"+44 1328 855600",
    "sg:postcode":"NR21 7NA",
    "sg:province":"Norfolk",
    "sg:tags":[
        "forestry",
        "surgeon",
        "tree"
    ],
    "wof:name":"Rissmann & Sons",
    "wof:placetype":"venue"
},
  "geometry": {"coordinates":[0.8479210138,52.8144073486],"type":"Point"}
}