{
  "type": "Feature",
  "properties": {
    "addr:full":"11 Burtonwood Industrial Centre, Phipps Lane, Burtonwood Warrington Cheshire WA5 4HX",
    "addr:housenumber":"11",
    "addr:postcode":"wa5 4hx",
    "addr:street":"Burtonwood;Phipps Lane",
    "iso:country":"GB",
    "sg:address":"11 Burtonwood Industrial Centre, Phipps Lane, Burtonwood",
    "sg:city":"Warrington",
    "sg:classifiers":[
        {
            "category":"Professional",
            "subcategory":"Engineering",
            "type":"Services"
        }
    ],
    "sg:postcode":"WA5 4HX",
    "sg:province":"Cheshire",
    "sg:tags":[
        "engineer",
        "mechanical"
    ],
    "wof:name":"C & P Services (Northern) Ltd.",
    "wof:placetype":"venue"
},
  "geometry": {"coordinates":[-2.6593739986,53.4310760498],"type":"Point"}
}