{
  "type": "Feature",
  "properties": {
    "addr:full":"Diamond House, Blyburgate Beccles Norfolk NR34 9TQ",
    "addr:postcode":"nr34 9tq",
    "addr:street":"Blyburgate",
    "iso:country":"GB",
    "sg:address":"Diamond House, Blyburgate",
    "sg:city":"Beccles",
    "sg:classifiers":[
        {
            "category":"Bars & Pubs",
            "type":"Food & Drink"
        }
    ],
    "sg:phone":"+44 1502 710184",
    "sg:postcode":"NR34 9TQ",
    "sg:province":"Norfolk",
    "sg:tags":[
        "pubs",
        "inn"
    ],
    "wof:name":"Stephen Warman",
    "wof:placetype":"venue"
},
  "geometry": {"coordinates":[1.5643750429,52.4567260742],"type":"Point"}
}