{
  "type": "Feature",
  "properties": {
    "iso:country":"GB",
    "sg:address":"159 Old Monkland Road",
    "sg:city":"Coatbridge",
    "sg:classifiers":[
        {
            "category":"Manufacturing",
            "subcategory":"Signs",
            "type":"Manufacturing & Wholesale Goods"
        }
    ],
    "sg:postcode":"ML5 5EU",
    "sg:province":"North Lanarkshire",
    "sg:tags":[
        "nameplate"
    ],
    "wof:name":"G E Packer & Sons",
    "wof:placetype":"venue"
},
  "geometry": {"coordinates":[-4.048808,55.847126],"type":"Point"}
}