{
  "type": "Feature",
  "properties": {
    "addr:full":"9 Coombe Place, Oadby Leicester Leicestershire LE2 5TH",
    "addr:housenumber":"9",
    "addr:postcode":"le2 5th",
    "addr:street":"Coombe Place",
    "iso:country":"GB",
    "sg:address":"9 Coombe Place, Oadby",
    "sg:city":"Leicester",
    "sg:classifiers":[
        {
            "category":"Home & Garden",
            "subcategory":"Hardware",
            "type":"Retail Goods"
        }
    ],
    "sg:postcode":"LE2 5TH",
    "sg:province":"Leicestershire",
    "sg:tags":[
        "equipment",
        "heating"
    ],
    "wof:name":"Bernard Lloyd Technical Services",
    "wof:placetype":"venue"
},
  "geometry": {"coordinates":[-1.07316,52.59037],"type":"Point"}
}