{
  "type": "Feature",
  "properties": {
    "iso:country":"GB",
    "sg:address":"53-59 Hewell Road",
    "sg:city":"Birmingham",
    "sg:classifiers":[
        {
            "category":"Shopping",
            "subcategory":"Clothing, Apparel, & Fashions",
            "type":"Retail Goods"
        }
    ],
    "sg:postcode":"B45 8NL",
    "sg:province":"West Midlands",
    "sg:tags":[
        "shop"
    ],
    "wof:name":"Jill Scott Ltd.",
    "wof:placetype":"venue"
},
  "geometry": {"coordinates":[-1.990102,52.361702],"type":"Point"}
}