{
  "type": "Feature",
  "properties": {
    "iso:country":"GB",
    "sg:address":"Trafalgar House, 171-173 Charles Street",
    "sg:city":"Leicester",
    "sg:classifiers":[
        {
            "category":"Real Estate",
            "subcategory":"Developer",
            "type":"Services"
        }
    ],
    "sg:phone":"+44 116 255 8200",
    "sg:postcode":"LE1 1LA",
    "sg:province":"Leicestershire",
    "sg:tags":[
        "property"
    ],
    "wof:name":"The Cathco Property Group Ltd.",
    "wof:placetype":"venue"
},
  "geometry": {"coordinates":[-1.1281399727,52.6334838867],"type":"Point"}
}