{
  "type": "Feature",
  "properties": {
    "addr:full":"142 Whitley Road Eastbourne East Sussex BN22 8LT",
    "addr:housenumber":"142",
    "addr:postcode":"bn22 8lt",
    "addr:street":"Whitley Road",
    "iso:country":"GB",
    "sg:address":"142 Whitley Road",
    "sg:city":"Eastbourne",
    "sg:classifiers":[
        {
            "category":"Education",
            "subcategory":"Special Training",
            "type":"Public Place"
        }
    ],
    "sg:phone":"+44 1323 411517",
    "sg:postcode":"BN22 8LT",
    "sg:province":"East Sussex",
    "sg:tags":[
        "product",
        "centre"
    ],
    "wof:name":"Heathercroft Training Services Ltd.",
    "wof:placetype":"venue"
},
  "geometry": {"coordinates":[0.2904320061,50.7766838074],"type":"Point"}
}