{
  "type": "Feature",
  "properties": {
    "addr:full":"289 Preston Road, Grimsargh Preston Lancashire PR2 5JR",
    "addr:housenumber":"289",
    "addr:postcode":"pr2 5jr",
    "addr:street":"Preston Road",
    "iso:country":"GB",
    "sg:address":"289 Preston Road, Grimsargh",
    "sg:city":"Preston",
    "sg:classifiers":[
        {
            "category":"Professional",
            "subcategory":"Management & Consulting",
            "type":"Services"
        }
    ],
    "sg:postcode":"PR2 5JR",
    "sg:province":"Lancashire",
    "sg:tags":[
        "fire",
        "consultant",
        "protection",
        "business"
    ],
    "wof:name":"Red Rose Fire Extinguishers",
    "wof:placetype":"venue"
},
  "geometry": {"coordinates":[-2.6209900379,53.8055801392],"type":"Point"}
}