{
  "type": "Feature",
  "properties": {
    "addr:full":"84 New Road Porthcawl Bridgend CF36 5DE",
    "addr:housenumber":"84",
    "addr:postcode":"cf36 5de",
    "addr:street":"New Road",
    "iso:country":"GB",
    "sg:address":"84 New Road",
    "sg:city":"Porthcawl",
    "sg:classifiers":[
        {
            "category":"Communications",
            "type":"Services"
        }
    ],
    "sg:phone":"+44 1656 773834",
    "sg:postcode":"CF36 5DE",
    "sg:province":"Bridgend",
    "sg:tags":[
        "tv",
        "video",
        "radio"
    ],
    "wof:name":"Tele-Video Services",
    "wof:placetype":"venue"
},
  "geometry": {"coordinates":[-3.696212,51.481819],"type":"Point"}
}