{
  "type": "Feature",
  "properties": {
    "addr:full":"42 Boswell Road, Castle Park Inverness Highland IV2 3EJ",
    "addr:housenumber":"42",
    "addr:postcode":"iv2 3ej",
    "addr:street":"Boswell Road Castle Park",
    "iso:country":"GB",
    "sg:address":"42 Boswell Road, Castle Park",
    "sg:city":"Inverness",
    "sg:classifiers":[
        {
            "category":"Retail",
            "subcategory":"Auto Repair",
            "type":"Services"
        }
    ],
    "sg:postcode":"IV2 3EJ",
    "sg:province":"Highland",
    "sg:tags":[
        "body",
        "car"
    ],
    "wof:name":"Chipsaway",
    "wof:placetype":"venue"
},
  "geometry": {"coordinates":[-4.1938462257,57.4574050903],"type":"Point"}
}