{
  "type": "Feature",
  "properties": {
    "iso:country":"GB",
    "sg:address":"5 Anstice Sq",
    "sg:city":"Telford",
    "sg:classifiers":[
        {
            "category":"Retail",
            "subcategory":"Repair Shop",
            "type":"Services"
        }
    ],
    "sg:phone":"+44 1952 580571",
    "sg:postcode":"TF7 5BD",
    "sg:province":"Shropshire",
    "sg:tags":[
        "upholsterer"
    ],
    "wof:name":"Madeley Upholstery",
    "wof:placetype":"venue"
},
  "geometry": {"coordinates":[-2.4543039799,52.6338691711],"type":"Point"}
}