{
  "type": "Feature",
  "properties": {
    "iso:country":"GB",
    "sg:address":"7 Well Close",
    "sg:city":"Camberley",
    "sg:classifiers":[
        {
            "category":"Professional",
            "subcategory":"Management & Consulting",
            "type":"Services"
        }
    ],
    "sg:phone":"+44 1276 507567",
    "sg:postcode":"GU15 3NL",
    "sg:province":"Berkshire",
    "sg:tags":[
        "consultant",
        "business"
    ],
    "wof:name":"Pennyford Consultants Ltd.",
    "wof:placetype":"venue"
},
  "geometry": {"coordinates":[-0.753862977,51.33070755],"type":"Point"}
}