{
  "type": "Feature",
  "properties": {
    "addr:full":"98 Britannia Rd, Morley Leeds West Yorkshire LS27 0DT",
    "addr:housenumber":"98",
    "addr:postcode":"ls27 0dt",
    "addr:street":"Britannia Rd",
    "iso:country":"GB",
    "sg:address":"98 Britannia Rd, Morley",
    "sg:city":"Leeds",
    "sg:classifiers":[
        {
            "category":"Autos & Motor Vehicles",
            "subcategory":"Automobile Sales",
            "type":"Retail Goods"
        }
    ],
    "sg:phone":"+44 113 252 0045",
    "sg:postcode":"LS27 0DT",
    "sg:province":"West Yorkshire",
    "sg:tags":[
        "commercial"
    ],
    "wof:name":"High & Low Car Co Ltd",
    "wof:placetype":"venue"
},
  "geometry": {"coordinates":[-1.607969,53.737091],"type":"Point"}
}