{
  "type": "Feature",
  "properties": {
    "addr:full":"9 Great Russell Court, Fieldhead Business Centre Bradford West Yorkshire BD7 1JZ",
    "addr:housenumber":"9;business centre",
    "addr:postcode":"bd7 1jz",
    "addr:street":"Great Russell Court Fieldhead;Bradford West",
    "iso:country":"GB",
    "sg:address":"9 Great Russell Court, Fieldhead Business Centre",
    "sg:city":"Bradford",
    "sg:classifiers":[
        {
            "category":"Transit Center",
            "subcategory":"Passenger",
            "type":"Transportation"
        },
        {
            "category":"Professional",
            "subcategory":"Business Services",
            "type":"Services"
        }
    ],
    "sg:phone":"+44 1274 720367",
    "sg:postcode":"BD7 1JZ",
    "sg:province":"West Yorkshire",
    "sg:tags":[
        "accomodation",
        "centre",
        "commerce"
    ],
    "wof:name":"Fieldhead Business Centre",
    "wof:placetype":"venue"
},
  "geometry": {"coordinates":[-1.771713,53.794407],"type":"Point"}
}