{
  "type": "Feature",
  "properties": {
    "addr:full":"Mill Lane Tamworth Staffordshire B79 7JA",
    "addr:postcode":"b79 7ja",
    "addr:street":"Mill Lane",
    "iso:country":"GB",
    "sg:address":"Mill Lane",
    "sg:city":"Tamworth",
    "sg:classifiers":[
        {
            "category":"Cinema",
            "subcategory":"Movie Rental",
            "type":"Entertainment"
        }
    ],
    "sg:phone":"+44 1827 313488",
    "sg:postcode":"B79 7JA",
    "sg:province":"Staffordshire",
    "sg:tags":[
        "video",
        "library"
    ],
    "wof:name":"Blockbuster Video",
    "wof:placetype":"venue"
},
  "geometry": {"coordinates":[-1.6906930208,52.6336936951],"type":"Point"}
}