{
  "type": "Feature",
  "properties": {
    "addr:full":"229 Edward Road, Balsall Heath Birmingham West Midlands B12 9LH",
    "addr:housenumber":"229",
    "addr:postcode":"b12 9lh",
    "addr:street":"Edward Road",
    "iso:country":"GB",
    "sg:address":"229 Edward Road, Balsall Heath",
    "sg:city":"Birmingham",
    "sg:classifiers":[
        {
            "category":"Taxi",
            "type":"Transportation"
        },
        {
            "category":"Military Area",
            "subcategory":"Air Force Base",
            "type":"Public Place"
        }
    ],
    "sg:phone":"+44 121 440 3323",
    "sg:postcode":"B12 9LH",
    "sg:province":"West Midlands",
    "sg:tags":[
        "hire",
        "private",
        "vehicle"
    ],
    "wof:name":"Heath Cabs",
    "wof:placetype":"venue"
},
  "geometry": {"coordinates":[-1.8960490227,52.4582862854],"type":"Point"}
}