{
  "type": "Feature",
  "properties": {
    "addr:full":"55 York Road Hull East Riding of Yorkshire HU6 9QJ",
    "addr:housenumber":"55",
    "addr:postcode":"hu6 9qj",
    "addr:street":"York Road",
    "iso:country":"GB",
    "sg:address":"55 York Road",
    "sg:city":"Hull",
    "sg:classifiers":[
        {
            "category":"Building & Trades",
            "subcategory":"Construction",
            "type":"Services"
        }
    ],
    "sg:phone":"+44 1482 809217",
    "sg:postcode":"HU6 9QJ",
    "sg:province":"East Riding of Yorkshire",
    "sg:tags":[
        "roofing"
    ],
    "wof:name":"D Smith & Son",
    "wof:placetype":"venue"
},
  "geometry": {"coordinates":[-0.3800199926,53.7844390869],"type":"Point"}
}