{
  "type": "Feature",
  "properties": {
    "iso:country":"GB",
    "sg:address":"274 Davidson Road",
    "sg:city":"Croydon",
    "sg:classifiers":[
        {
            "category":"Autos & Motor Vehicles",
            "subcategory":"Auto Supplies",
            "type":"Retail Goods"
        }
    ],
    "sg:phone":"+44 20 8684 1602",
    "sg:postcode":"CR0 6DF",
    "sg:province":"Surrey",
    "sg:tags":[
        "component"
    ],
    "wof:name":"Automotive Transmissions Ltd.",
    "wof:placetype":"venue"
},
  "geometry": {"coordinates":[-0.083976,51.385876],"type":"Point"}
}