{
  "type": "Feature",
  "properties": {
    "addr:full":"The Old Hay Barns, Upper Aston Farm, Upper Aston Wolverhampton Shropshire WV5 7EE",
    "addr:postcode":"wv5 7ee",
    "addr:street":"Upper Aston;Upper Aston",
    "iso:country":"GB",
    "sg:address":"The Old Hay Barns, Upper Aston Farm, Upper Aston",
    "sg:city":"Wolverhampton",
    "sg:classifiers":[
        {
            "category":"Home & Garden",
            "subcategory":"Furniture",
            "type":"Retail Goods"
        }
    ],
    "sg:phone":"+44 1746 710081",
    "sg:postcode":"WV5 7EE",
    "sg:province":"Shropshire",
    "wof:name":"Claverley Furniture Co",
    "wof:placetype":"venue"
},
  "geometry": {"coordinates":[-2.301534,52.538101],"type":"Point"}
}