{
  "type": "Feature",
  "properties": {
    "addr:full":"593 Uxbridge Road Hayes Greater London UB4 8HR",
    "addr:housenumber":"593",
    "addr:postcode":"ub4 8hr",
    "addr:street":"Uxbridge Road",
    "iso:country":"GB",
    "sg:address":"593 Uxbridge Road",
    "sg:city":"Hayes",
    "sg:classifiers":[
        {
            "category":"Shopping",
            "type":"Retail Goods"
        }
    ],
    "sg:postcode":"UB4 8HR",
    "sg:province":"Greater London",
    "sg:tags":[
        "part",
        "accessory"
    ],
    "wof:name":"M G M Motor Spares",
    "wof:placetype":"venue"
},
  "geometry": {"coordinates":[-0.428748,51.523945],"type":"Point"}
}