{
  "type": "Feature",
  "properties": {
    "iso:country":"GB",
    "sg:address":"11 Pentland Close",
    "sg:city":"North Shields",
    "sg:classifiers":[
        {
            "category":"Professional",
            "subcategory":"Accounting & Tax Preparation",
            "type":"Services"
        }
    ],
    "sg:phone":"+44 191 296 0937",
    "sg:postcode":"NE29 9ED",
    "sg:province":"Tyne and Wear",
    "sg:tags":[
        "payroll"
    ],
    "wof:name":"L A J Business Services",
    "wof:placetype":"venue"
},
  "geometry": {"coordinates":[-1.4606930017,55.0263519287],"type":"Point"}
}