{
  "type": "Feature",
  "properties": {
    "addr:full":"169 Peckham Rye London Greater London SE15 3HZ",
    "addr:housenumber":"169",
    "addr:postcode":"se15 3hz",
    "addr:street":"Peckham Rye",
    "iso:country":"GB",
    "sg:address":"169 Peckham Rye",
    "sg:city":"London",
    "sg:classifiers":[
        {
            "category":"Health Services",
            "subcategory":"Health Practitioner",
            "type":"Services"
        }
    ],
    "sg:postcode":"SE15 3HZ",
    "sg:province":"Greater London",
    "sg:tags":[
        "psychotherapist"
    ],
    "wof:name":"Martin Dr Stanton",
    "wof:placetype":"venue"
},
  "geometry": {"coordinates":[-0.060602,51.460506],"type":"Point"}
}