{
  "type": "Feature",
  "properties": {
    "addr:full":"11 Buckingham Rise Dudley West Midlands DY1 2TS",
    "addr:housenumber":"11",
    "addr:postcode":"dy1 2ts",
    "addr:street":"Buckingham Rise",
    "iso:country":"GB",
    "sg:address":"11 Buckingham Rise",
    "sg:city":"Dudley",
    "sg:classifiers":[
        {
            "category":"Real Estate",
            "subcategory":"Real Estate Agent",
            "type":"Services"
        }
    ],
    "sg:postcode":"DY1 2TS",
    "sg:province":"West Midlands",
    "wof:name":"Array Properties Ltd",
    "wof:placetype":"venue"
},
  "geometry": {"coordinates":[-2.116483,52.515438],"type":"Point"}
}