{
  "type": "Feature",
  "properties": {
    "iso:country":"GB",
    "sg:address":"51 Crossroad",
    "sg:city":"Maldon",
    "sg:classifiers":[
        {
            "category":"Building & Trades",
            "subcategory":"Construction",
            "type":"Services"
        }
    ],
    "sg:phone":"+44 1621 852975",
    "sg:postcode":"CM9 5ED",
    "sg:province":"Essex",
    "sg:tags":[
        "roofing"
    ],
    "wof:name":"M Barter",
    "wof:placetype":"venue"
},
  "geometry": {"coordinates":[0.68184,51.727871],"type":"Point"}
}