{
  "type": "Feature",
  "properties": {
    "addr:full":"Windmill Hill Leamington Spa Warwickshire CV32 7LN",
    "addr:postcode":"cv32 7ln",
    "addr:street":"Windmill Hill",
    "iso:country":"GB",
    "sg:address":"Windmill Hill",
    "sg:city":"Leamington Spa",
    "sg:classifiers":[
        {
            "category":"Education",
            "subcategory":"School",
            "type":"Public Place"
        }
    ],
    "sg:phone":"+44 1926 424420",
    "sg:postcode":"CV32 7LN",
    "sg:province":"Warwickshire",
    "sg:tags":[
        "local",
        "authority"
    ],
    "wof:name":"Our Lady & St Teresa's R C Combined School",
    "wof:placetype":"venue"
},
  "geometry": {"coordinates":[-1.507324,52.312286],"type":"Point"}
}