{
  "type": "Feature",
  "properties": {
    "addr:full":"17 Oaktree Close Ivybridge Devon PL21 9RJ",
    "addr:housenumber":"17",
    "addr:postcode":"pl21 9rj",
    "addr:street":"Oaktree Close",
    "iso:country":"GB",
    "sg:address":"17 Oaktree Close",
    "sg:city":"Ivybridge",
    "sg:classifiers":[
        {
            "category":"Building & Trades",
            "subcategory":"Plumbing",
            "type":"Services"
        }
    ],
    "sg:phone":"+44 1752 690881",
    "sg:postcode":"PL21 9RJ",
    "sg:province":"Devon",
    "sg:tags":[
        "plumber",
        "heating"
    ],
    "wof:name":"PETER BATE",
    "wof:placetype":"venue"
},
  "geometry": {"coordinates":[-3.9381899834,50.3917388916],"type":"Point"}
}