{
  "type": "Feature",
  "properties": {
    "addr:full":"237 Main Street, Stanton-under-bardonmain Markfield Leicestershire LE67 9TQ",
    "addr:housenumber":"237",
    "addr:postcode":"le67 9tq",
    "addr:street":"Main Street",
    "iso:country":"GB",
    "sg:address":"237 Main Street, Stanton-under-bardonmain",
    "sg:city":"Markfield",
    "sg:classifiers":[
        {
            "category":"Professional",
            "type":"Services"
        }
    ],
    "sg:phone":"+44 1530 243325",
    "sg:postcode":"LE67 9TQ",
    "sg:province":"Leicestershire",
    "sg:tags":[
        "interior",
        "furnishers",
        "designer"
    ],
    "wof:name":"Philip Botterill Soft Furnishings",
    "wof:placetype":"venue"
},
  "geometry": {"coordinates":[-1.311346,52.688175],"type":"Point"}
}