{
  "type": "Feature",
  "properties": {
    "addr:full":"173 Fulham Palace Road London Greater London W6 8QT",
    "addr:housenumber":"173",
    "addr:postcode":"w6 8qt",
    "addr:street":"Fulham Palace Road",
    "iso:country":"GB",
    "sg:address":"173 Fulham Palace Road",
    "sg:city":"London",
    "sg:classifiers":[
        {
            "category":"Health Services",
            "subcategory":"Health Practitioner",
            "type":"Services"
        }
    ],
    "sg:postcode":"W6 8QT",
    "sg:province":"Greater London",
    "sg:tags":[
        "homoeopathic"
    ],
    "wof:name":"Minerva Homeopathic Centre",
    "wof:placetype":"venue"
},
  "geometry": {"coordinates":[-0.2199549973,51.4851112366],"type":"Point"}
}