{
  "type": "Feature",
  "properties": {
    "iso:country":"GB",
    "sg:address":"The Manor House, High Street",
    "sg:city":"Honiton",
    "sg:classifiers":[
        {
            "category":"Health Services",
            "subcategory":"Nursing And Care Facility",
            "type":"Services"
        }
    ],
    "sg:phone":"+44 1404 46626",
    "sg:postcode":"EX14 1LJ",
    "sg:province":"Devon",
    "sg:tags":[
        "agency"
    ],
    "wof:name":"Care Initiative",
    "wof:placetype":"venue"
},
  "geometry": {"coordinates":[-3.183674,50.80122],"type":"Point"}
}