{
  "type": "Feature",
  "properties": {
    "addr:full":"37 Whittlesey Road, Stanground Peterborough Cambridgeshire PE2 8RL",
    "addr:housenumber":"37",
    "addr:postcode":"pe2 8rl",
    "addr:street":"Whittlesey Road",
    "iso:country":"GB",
    "sg:address":"37 Whittlesey Road, Stanground",
    "sg:city":"Peterborough",
    "sg:classifiers":[
        {
            "category":"Professional",
            "subcategory":"Engineering",
            "type":"Services"
        }
    ],
    "sg:phone":"+44 1733 562971",
    "sg:postcode":"PE2 8RL",
    "sg:province":"Cambridgeshire",
    "sg:tags":[
        "contractor",
        "electrical",
        "engineer"
    ],
    "wof:name":"Norman H Daft",
    "wof:placetype":"venue"
},
  "geometry": {"coordinates":[-0.2208050042,52.5509490967],"type":"Point"}
}