{
  "type": "Feature",
  "properties": {
    "addr:full":"12 Sibthorpe Drive, Sudbrooke Lincoln Lincolnshire LN2 2RQ",
    "addr:housenumber":"12",
    "addr:postcode":"ln2 2rq",
    "addr:street":"Sibthorpe Drive",
    "iso:country":"GB",
    "sg:address":"12 Sibthorpe Drive, Sudbrooke",
    "sg:city":"Lincoln",
    "sg:classifiers":[
        {
            "category":"Bakery",
            "type":"Food & Drink"
        },
        {
            "category":"Home & Garden",
            "subcategory":"Kitchen Supply",
            "type":"Retail Goods"
        }
    ],
    "sg:phone":"+44 1522 753149",
    "sg:postcode":"LN2 2RQ",
    "sg:province":"Lincolnshire",
    "sg:tags":[
        "cake",
        "equipment",
        "maker"
    ],
    "wof:name":"Valbarr Celebration Cake Service",
    "wof:placetype":"venue"
},
  "geometry": {"coordinates":[-0.447723,53.267166],"type":"Point"}
}