{
  "type": "Feature",
  "properties": {
    "iso:country":"GB",
    "sg:address":"99 Ock Street, Abingdon",
    "sg:city":"Oxford",
    "sg:classifiers":[
        {
            "category":"Professional",
            "subcategory":"Printing & Photocopies",
            "type":"Services"
        }
    ],
    "sg:phone":"+44 1235 534798",
    "sg:postcode":"OX14 5DQ",
    "sg:province":"Oxfordshire",
    "sg:tags":[
        "trophy"
    ],
    "wof:name":"Staticoin Ltd.",
    "wof:placetype":"venue"
},
  "geometry": {"coordinates":[-1.288781,51.66964],"type":"Point"}
}