{
  "type": "Feature",
  "properties": {
    "iso:country":"GB",
    "sg:address":"15 South Fork",
    "sg:city":"Newcastle-upon-tyne",
    "sg:classifiers":[
        {
            "category":"Retail",
            "subcategory":"Storage",
            "type":"Services"
        }
    ],
    "sg:phone":"+44 191 267 8670",
    "sg:postcode":"NE15 8TZ",
    "sg:province":"Northumberland",
    "sg:tags":[
        "household",
        "activity",
        "domestic",
        "removal"
    ],
    "wof:name":"Alan Rutherford",
    "wof:placetype":"venue"
},
  "geometry": {"coordinates":[-1.7183799744,54.9851951599],"type":"Point"}
}