{
  "type": "Feature",
  "properties": {
    "iso:country":"GB",
    "sg:address":"1 Charmbury Rise",
    "sg:city":"Luton",
    "sg:classifiers":[
        {
            "category":"Home & Garden",
            "subcategory":"Household Appliances",
            "type":"Retail Goods"
        },
        {
            "category":"Retail",
            "subcategory":"Repair Shop",
            "type":"Services"
        }
    ],
    "sg:phone":"+44 1582 733415",
    "sg:postcode":"LU2 7XR",
    "sg:province":"Bedfordshire",
    "sg:tags":[
        "electrical",
        "television",
        "video",
        "radio"
    ],
    "wof:name":"F J Bush",
    "wof:placetype":"venue"
},
  "geometry": {"coordinates":[-0.4012599885,51.9008750916],"type":"Point"}
}