{
  "type": "Feature",
  "properties": {
    "addr:full":"3 King Street Lancaster Lancashire LA1 1JN",
    "addr:housenumber":"3",
    "addr:postcode":"la1 1jn",
    "addr:street":"King Street",
    "iso:country":"GB",
    "sg:address":"3 King Street",
    "sg:city":"Lancaster",
    "sg:classifiers":[
        {
            "category":"Health Services",
            "subcategory":"Optometrist",
            "type":"Services"
        },
        {
            "category":"Shopping",
            "subcategory":"Optician",
            "type":"Retail Goods"
        }
    ],
    "sg:phone":"+44 1524 64151",
    "sg:postcode":"LA1 1JN",
    "sg:province":"Lancashire",
    "sg:tags":[
        "ophthalmic"
    ],
    "wof:name":"Welbourne Opticians",
    "wof:placetype":"venue"
},
  "geometry": {"coordinates":[-2.802143,54.04797],"type":"Point"}
}