{
  "type": "Feature",
  "properties": {
    "addr:full":"35 High Street High Wycombe Buckinghamshire HP11 2AG",
    "addr:housenumber":"35",
    "addr:postcode":"hp11 2ag",
    "addr:street":"High Street",
    "iso:country":"GB",
    "sg:address":"35 High Street",
    "sg:city":"High Wycombe",
    "sg:classifiers":[
        {
            "category":"Bars & Pubs",
            "type":"Food & Drink"
        }
    ],
    "sg:phone":"+44 1494 526533",
    "sg:postcode":"HP11 2AG",
    "sg:province":"Buckinghamshire",
    "sg:tags":[
        "pubs",
        "inn"
    ],
    "wof:name":"The Hobgoblin",
    "wof:placetype":"venue"
},
  "geometry": {"coordinates":[-0.750102,51.628834],"type":"Point"}
}