{
  "type": "Feature",
  "properties": {
    "addr:full":"Denton Island Newhaven East Sussex BN9 9BA",
    "addr:postcode":"bn9 9ba",
    "addr:street":"Denton Island",
    "iso:country":"GB",
    "sg:address":"Denton Island",
    "sg:city":"Newhaven",
    "sg:classifiers":[
        {
            "category":"Professional",
            "type":"Services"
        }
    ],
    "sg:phone":"+44 1273 514907",
    "sg:postcode":"BN9 9BA",
    "sg:province":"East Sussex",
    "sg:tags":[
        "marine"
    ],
    "wof:name":"Meeching Boats",
    "wof:placetype":"venue"
},
  "geometry": {"coordinates":[0.046175,50.795036],"type":"Point"}
}