{
  "type": "Feature",
  "properties": {
    "iso:country":"GB",
    "sg:address":"7 Scafell Avenue",
    "sg:city":"Fareham",
    "sg:classifiers":[
        {
            "category":"Building & Trades",
            "subcategory":"Construction",
            "type":"Services"
        }
    ],
    "sg:phone":"+44 1329 284791",
    "sg:postcode":"PO14 1SQ",
    "sg:province":"Hampshire",
    "sg:tags":[
        "ceiling",
        "contractor"
    ],
    "wof:name":"Gosport & Fareham Artexing",
    "wof:placetype":"venue"
},
  "geometry": {"coordinates":[-1.209376,50.847389],"type":"Point"}
}