{
  "type": "Feature",
  "properties": {
    "iso:country":"GB",
    "sg:address":"258 Wallasey Village",
    "sg:city":"Wallasey",
    "sg:classifiers":[
        {
            "category":"Fast Food",
            "type":"Food & Drink"
        }
    ],
    "sg:phone":"+44 151 637 1371",
    "sg:postcode":"L45 3HB",
    "sg:province":"Merseyside",
    "sg:tags":[
        "away",
        "take"
    ],
    "wof:name":"Mak Syed Indian Take-away",
    "wof:placetype":"venue"
},
  "geometry": {"coordinates":[-3.067761898,53.4280967712],"type":"Point"}
}