{
  "type": "Feature",
  "properties": {
    "iso:country":"GB",
    "sg:address":"Burley Park Medical Centre, 273 Burley Rd",
    "sg:city":"Leeds",
    "sg:classifiers":[
        {
            "category":"Health Services",
            "subcategory":"Doctor",
            "type":"Services"
        }
    ],
    "sg:phone":"+44 113 295 3850",
    "sg:postcode":"LS4 2EL",
    "sg:province":"West Yorkshire",
    "sg:tags":[
        "practitioners"
    ],
    "wof:name":"Hall, R B",
    "wof:placetype":"venue"
},
  "geometry": {"coordinates":[-1.5794999599,53.8076400757],"type":"Point"}
}