{
  "type": "Feature",
  "properties": {
    "addr:full":"338 Bristol Rd Gloucester Gloucestershire GL2 6DH",
    "addr:housenumber":"338",
    "addr:postcode":"gl2 6dh",
    "addr:street":"Bristol Rd",
    "iso:country":"GB",
    "sg:address":"338 Bristol Rd",
    "sg:city":"Gloucester",
    "sg:classifiers":[
        {
            "category":"Wholesale",
            "subcategory":"Construction Materials",
            "type":"Manufacturing & Wholesale Goods"
        }
    ],
    "sg:postcode":"GL2 6DH",
    "sg:province":"Gloucestershire",
    "sg:tags":[
        "merchant",
        "stone"
    ],
    "wof:name":"Disc Buildings",
    "wof:placetype":"venue"
},
  "geometry": {"coordinates":[-2.279472,51.818508],"type":"Point"}
}