{
  "type": "Feature",
  "properties": {
    "iso:country":"GB",
    "sg:address":"5 Pensford Close",
    "sg:city":"Crowthorne",
    "sg:classifiers":[
        {
            "category":"Travel",
            "subcategory":"Travel Agent",
            "type":"Entertainment"
        }
    ],
    "sg:phone":"+44 1344 773112",
    "sg:postcode":"RG45 6QR",
    "sg:province":"Berkshire",
    "sg:tags":[
        "agency",
        "activity"
    ],
    "wof:name":"Gemini Holidays",
    "wof:placetype":"venue"
},
  "geometry": {"coordinates":[-0.800399,51.378399],"type":"Point"}
}