{
  "type": "Feature",
  "properties": {
    "iso:country":"GB",
    "sg:address":"8 Viewfield Rd",
    "sg:city":"Ballater",
    "sg:classifiers":[
        {
            "category":"Taxi",
            "type":"Transportation"
        },
        {
            "category":"Military Area",
            "subcategory":"Air Force Base",
            "type":"Public Place"
        }
    ],
    "sg:postcode":"AB35 5RD",
    "sg:province":"Aberdeenshire",
    "sg:tags":[
        "mini",
        "hire",
        "private",
        "cab"
    ],
    "wof:name":"Nicol,Cyril R,",
    "wof:placetype":"venue"
},
  "geometry": {"coordinates":[-3.041605,57.049545],"type":"Point"}
}