{
  "type": "Feature",
  "properties": {
    "addr:full":"Hillcrest Centre Hillcrest Road Newhaven East Sussex BN9 9EA",
    "addr:postcode":"bn9 9ea",
    "addr:street":"Hillcrest Road",
    "iso:country":"GB",
    "sg:address":"Hillcrest Centre Hillcrest Road",
    "sg:city":"Newhaven",
    "sg:classifiers":[
        {
            "category":"Organizations",
            "subcategory":"Non-profit Organization",
            "type":"Services"
        }
    ],
    "sg:phone":"+44 1273 517332",
    "sg:postcode":"BN9 9EA",
    "sg:province":"East Sussex",
    "sg:tags":[
        "organisation",
        "voluntary",
        "charity"
    ],
    "wof:name":"Community Transport Lewes Area Ltd.",
    "wof:placetype":"venue"
},
  "geometry": {"coordinates":[0.046175,50.795036],"type":"Point"}
}