{
  "type": "Feature",
  "properties": {
    "addr:full":"2 Grand Parade, 380 Ewell Road, Tolworth Surbiton Surrey KT6 7BE",
    "addr:housenumber":"2;380",
    "addr:postcode":"kt6 7be",
    "addr:street":"Grand Parade;Ewell Road",
    "iso:country":"GB",
    "sg:address":"2 Grand Parade, 380 Ewell Road, Tolworth",
    "sg:city":"Surbiton",
    "sg:classifiers":[
        {
            "category":"Home & Garden",
            "subcategory":"Home Furnishings",
            "type":"Retail Goods"
        },
        {
            "category":"Social Services",
            "subcategory":"Adult Care",
            "type":"Services"
        }
    ],
    "sg:phone":"+44 20 8399 9779",
    "sg:postcode":"KT6 7BE",
    "sg:province":"Surrey",
    "sg:tags":[
        "merchant",
        "decorator",
        "diy",
        "decorators'"
    ],
    "wof:name":"Trade Paints",
    "wof:placetype":"venue"
},
  "geometry": {"coordinates":[-0.3069489896,51.3920593262],"type":"Point"}
}