{
  "type": "Feature",
  "properties": {
    "iso:country":"GB",
    "sg:address":"1 Stoney Road, Dunkirk",
    "sg:city":"Faversham",
    "sg:classifiers":[
        {
            "category":"Building & Trades",
            "subcategory":"Construction",
            "type":"Services"
        }
    ],
    "sg:phone":"+44 1227 751219",
    "sg:postcode":"ME13 9TN",
    "sg:province":"Kent",
    "sg:tags":[
        "roofing",
        "contracting"
    ],
    "wof:name":"Abbey Roofing",
    "wof:placetype":"venue"
},
  "geometry": {"coordinates":[0.966198,51.295654],"type":"Point"}
}