{
  "type": "Feature",
  "properties": {
    "addr:full":"Main Road, Hathersage, Hope Valley Sheffield Derbyshire S32 1BR",
    "addr:postcode":"s32 1br",
    "addr:street":"Main Road",
    "iso:country":"GB",
    "sg:address":"Main Road, Hathersage, Hope Valley",
    "sg:city":"Sheffield",
    "sg:classifiers":[
        {
            "category":"Education",
            "subcategory":"Special Training",
            "type":"Public Place"
        }
    ],
    "sg:phone":"+44 1433 650065",
    "sg:postcode":"S32 1BR",
    "sg:province":"Derbyshire",
    "sg:tags":[
        "product",
        "centre"
    ],
    "wof:name":"Brookfield Manor Ltd.",
    "wof:placetype":"venue"
},
  "geometry": {"coordinates":[-1.654051,53.330402],"type":"Point"}
}