{
  "type": "Feature",
  "properties": {
    "addr:full":"Unit 31, Clarke St Derby Derbyshire DE1 2BU",
    "addr:housenumber":"unit 31",
    "addr:postcode":"de1 2bu",
    "addr:street":"Clarke St",
    "iso:country":"GB",
    "sg:address":"Unit 31, Clarke St",
    "sg:city":"Derby",
    "sg:classifiers":[
        {
            "category":"Manufacturing",
            "subcategory":"Aerospace",
            "type":"Manufacturing & Wholesale Goods"
        }
    ],
    "sg:phone":"+44 1332 258700",
    "sg:postcode":"DE1 2BU",
    "sg:province":"Derbyshire",
    "sg:tags":[
        "aircraft",
        "component"
    ],
    "wof:name":"Pattonair Logistics",
    "wof:placetype":"venue"
},
  "geometry": {"coordinates":[-1.4688390493,52.9274291992],"type":"Point"}
}