{
  "type": "Feature",
  "properties": {
    "iso:country":"GB",
    "sg:address":"5 Central Square, Suffolk Street Queensway",
    "sg:city":"Birmingham",
    "sg:classifiers":[
        {
            "category":"Personal",
            "subcategory":"Nail Salon",
            "type":"Services"
        }
    ],
    "sg:phone":"+44 121 643 7778",
    "sg:postcode":"B1 1UA",
    "sg:province":"West Midlands",
    "sg:tags":[
        "solarium",
        "tanning"
    ],
    "wof:name":"Futuresun Ltd.",
    "wof:placetype":"venue"
},
  "geometry": {"coordinates":[-1.900703,52.475594],"type":"Point"}
}