{
  "type": "Feature",
  "properties": {
    "addr:full":"128-132 Calmore Service Stn, Calmore Rd, Totton Southampton Hampshire SO40 8GQ",
    "addr:postcode":"128-132;so40 8gq",
    "addr:street":"Calmore;Calmore Rd",
    "iso:country":"GB",
    "sg:address":"128-132 Calmore Service Stn, Calmore Rd, Totton",
    "sg:city":"Southampton",
    "sg:classifiers":[
        {
            "category":"Autos & Motor Vehicles",
            "subcategory":"Fuel & Gas Station",
            "type":"Retail Goods"
        }
    ],
    "sg:postcode":"SO40 8GQ",
    "sg:province":"Hampshire",
    "sg:tags":[
        "petrol",
        "filling"
    ],
    "wof:name":"Kuwait Petroleum (G B) Ltd",
    "wof:placetype":"venue"
},
  "geometry": {"coordinates":[-1.51472,50.92308],"type":"Point"}
}