{
  "type": "Feature",
  "properties": {
    "iso:country":"GB",
    "sg:address":"152 Beacon Road, Great Barr",
    "sg:city":"Birmingham",
    "sg:classifiers":[
        {
            "category":"Shopping",
            "subcategory":"Florist",
            "type":"Retail Goods"
        }
    ],
    "sg:postcode":"B43 7BN",
    "sg:province":"West Midlands",
    "wof:name":"Collingwood Florists",
    "wof:placetype":"venue"
},
  "geometry": {"coordinates":[-1.911567,52.557697],"type":"Point"}
}