{
  "type": "Feature",
  "properties": {
    "iso:country":"GB",
    "sg:address":"Sadlers Barnfarm, Cleobury Mortimer",
    "sg:city":"Kidderminster",
    "sg:classifiers":[
        {
            "category":"Farming",
            "subcategory":"Farm",
            "type":"Manufacturing & Wholesale Goods"
        }
    ],
    "sg:postcode":"DY14 8QL",
    "sg:province":"Shropshire",
    "sg:tags":[
        "mixed",
        "crop"
    ],
    "wof:name":"Pain & Clark",
    "wof:placetype":"venue"
},
  "geometry": {"coordinates":[-2.482934,52.378525],"type":"Point"}
}