{
  "type": "Feature",
  "properties": {
    "iso:country":"GB",
    "sg:address":"Meikle Endovie",
    "sg:city":"Alford",
    "sg:classifiers":[
        {
            "category":"Farming",
            "subcategory":"Crops",
            "type":"Manufacturing & Wholesale Goods"
        },
        {
            "category":"Farming",
            "subcategory":"Farm",
            "type":"Manufacturing & Wholesale Goods"
        }
    ],
    "sg:phone":"+44 1975 562384",
    "sg:postcode":"AB33 8EE",
    "sg:province":"Aberdeenshire",
    "sg:tags":[
        "mixed",
        "arable"
    ],
    "wof:name":"C P Mathers & Son",
    "wof:placetype":"venue"
},
  "geometry": {"coordinates":[-2.705489,57.234138],"type":"Point"}
}