{
  "type": "Feature",
  "properties": {
    "iso:country":"GB",
    "sg:address":"32 South Road",
    "sg:city":"Saffron Walden",
    "sg:classifiers":[
        {
            "category":"Shopping",
            "subcategory":"Books",
            "type":"Retail Goods"
        },
        {
            "category":"Wholesale",
            "subcategory":"Books, Periodicals, & Newspapers",
            "type":"Manufacturing & Wholesale Goods"
        }
    ],
    "sg:phone":"+44 1799 502665",
    "sg:postcode":"CB11 3DN",
    "sg:province":"Essex",
    "sg:tags":[
        "publisher"
    ],
    "wof:name":"U K Media Directories Ltd",
    "wof:placetype":"venue"
},
  "geometry": {"coordinates":[0.245105,52.018219],"type":"Point"}
}