{
  "type": "Feature",
  "properties": {
    "iso:country":"GB",
    "sg:address":"117 Topping Street",
    "sg:city":"Blackpool",
    "sg:classifiers":[
        {
            "category":"Food & Beverages",
            "subcategory":"Meat & Fish",
            "type":"Retail Goods"
        },
        {
            "category":"Food & Beverages",
            "subcategory":"Groceries & Convenience Stores",
            "type":"Retail Goods"
        }
    ],
    "sg:phone":"+44 1253 296700",
    "sg:postcode":"FY1 3AA",
    "sg:province":"Lancashire",
    "sg:tags":[
        "shop",
        "chip"
    ],
    "wof:name":"Tower Fisheries",
    "wof:placetype":"venue"
},
  "geometry": {"coordinates":[-3.049769,53.818176],"type":"Point"}
}