{
  "type": "Feature",
  "properties": {
    "addr:full":"Cherry Orchard, Ash Lane Wells Somerset BA5 2RU",
    "addr:postcode":"ba5 2ru",
    "addr:street":"Cherry Orchard Ash Lane",
    "iso:country":"GB",
    "sg:address":"Cherry Orchard, Ash Lane",
    "sg:city":"Wells",
    "sg:classifiers":[
        {
            "category":"Home & Garden",
            "subcategory":"Garden Supply",
            "type":"Retail Goods"
        }
    ],
    "sg:phone":"+44 1749 672394",
    "sg:postcode":"BA5 2RU",
    "sg:province":"Somerset",
    "sg:tags":[
        "nursery",
        "centre"
    ],
    "wof:name":"Mogg's Of Wells Ltd",
    "wof:placetype":"venue"
},
  "geometry": {"coordinates":[-2.656179,51.214165],"type":"Point"}
}