{
  "type": "Feature",
  "properties": {
    "iso:country":"GB",
    "sg:address":"5 Wheatley Cl, Honeywell",
    "sg:city":"Barnsley",
    "sg:classifiers":[
        {
            "category":"Professional",
            "type":"Services"
        }
    ],
    "sg:postcode":"S71 1QJ",
    "sg:province":"South Yorkshire",
    "sg:tags":[
        "repair",
        "tech",
        "maintenance"
    ],
    "wof:name":"Wood,John,",
    "wof:placetype":"venue"
},
  "geometry": {"coordinates":[-1.478296,53.563686],"type":"Point"}
}