{
  "type": "Feature",
  "properties": {
    "addr:full":"Unit 16 Northfield Industrial Estate, Beresford Avenue Wembley Greater London HA0 1YH",
    "addr:housenumber":"unit 16;estate",
    "addr:postcode":"ha0 1yh",
    "addr:street":"Northfield Industrial;Beresford Avenue",
    "iso:country":"GB",
    "sg:address":"Unit 16 Northfield Industrial Estate, Beresford Avenue",
    "sg:city":"Wembley",
    "sg:classifiers":[
        {
            "category":"Conference Center",
            "type":"Public Place"
        }
    ],
    "sg:phone":"+44 20 8900 2777",
    "sg:postcode":"HA0 1YH",
    "sg:province":"Greater London",
    "wof:name":"Klein Communications",
    "wof:placetype":"venue"
},
  "geometry": {"coordinates":[-0.2832700014,51.5401382446],"type":"Point"}
}