{
  "type": "Feature",
  "properties": {
    "addr:full":"22 Spencers Road Maidenhead Berkshire SL6 6LN",
    "addr:housenumber":"22",
    "addr:postcode":"sl6 6ln",
    "addr:street":"Spencers Road",
    "iso:country":"GB",
    "sg:address":"22 Spencers Road",
    "sg:city":"Maidenhead",
    "sg:classifiers":[
        {
            "category":"Shopping",
            "subcategory":"Crafts & Fabrics",
            "type":"Retail Goods"
        },
        {
            "category":"Government",
            "subcategory":"Post Office",
            "type":"Public Place"
        }
    ],
    "sg:postcode":"SL6 6LN",
    "sg:province":"Berkshire",
    "sg:tags":[
        "shop",
        "needlecraft",
        "wool"
    ],
    "wof:name":"Spencers Road Post Office",
    "wof:placetype":"venue"
},
  "geometry": {"coordinates":[-0.7385230064,51.526550293],"type":"Point"}
}