{
  "type": "Feature",
  "properties": {
    "addr:full":"65 Somerset Road Folkestone Kent CT19 4NW",
    "addr:housenumber":"65",
    "addr:postcode":"ct19 4nw",
    "addr:street":"Somerset Road",
    "iso:country":"GB",
    "sg:address":"65 Somerset Road",
    "sg:city":"Folkestone",
    "sg:classifiers":[
        {
            "category":"Organizations",
            "subcategory":"Political Organization",
            "type":"Services"
        }
    ],
    "sg:phone":"+44 1303 276120",
    "sg:postcode":"CT19 4NW",
    "sg:province":"Kent",
    "sg:tags":[
        "party"
    ],
    "wof:name":"Folkestone & Hythe Labour Party",
    "wof:placetype":"venue"
},
  "geometry": {"coordinates":[1.1437079906,51.0897712708],"type":"Point"}
}