{
  "type": "Feature",
  "properties": {
    "addr:full":"6 Woodlands Parade Aylesford Kent ME20 6HE",
    "addr:housenumber":"6",
    "addr:postcode":"me20 6he",
    "addr:street":"Woodlands Parade",
    "iso:country":"GB",
    "sg:address":"6 Woodlands Parade",
    "sg:city":"Aylesford",
    "sg:classifiers":[
        {
            "category":"Food & Beverages",
            "subcategory":"Meat & Fish",
            "type":"Retail Goods"
        }
    ],
    "sg:postcode":"ME20 6HE",
    "sg:province":"Kent",
    "sg:tags":[
        "butcher"
    ],
    "wof:name":"John Millard",
    "wof:placetype":"venue"
},
  "geometry": {"coordinates":[0.454009,51.296684],"type":"Point"}
}