{
  "type": "Feature",
  "properties": {
    "addr:full":"224 Beaumont Road Plymouth Devon PL4 9EQ",
    "addr:housenumber":"224",
    "addr:postcode":"pl4 9eq",
    "addr:street":"Beaumont Road",
    "iso:country":"GB",
    "sg:address":"224 Beaumont Road",
    "sg:city":"Plymouth",
    "sg:classifiers":[
        {
            "category":"Food & Beverages",
            "subcategory":"Meat & Fish",
            "type":"Retail Goods"
        }
    ],
    "sg:postcode":"PL4 9EQ",
    "sg:province":"Devon",
    "sg:tags":[
        "butcher"
    ],
    "wof:name":"E J Brimacombe & Son",
    "wof:placetype":"venue"
},
  "geometry": {"coordinates":[-4.1175818443,50.3758926392],"type":"Point"}
}