{
  "type": "Feature",
  "properties": {
    "iso:country":"GB",
    "sg:address":"29-31 London Road",
    "sg:city":"Enfield",
    "sg:classifiers":[
        {
            "category":"Banks & Credit Unions",
            "subcategory":"Financial Services",
            "type":"Services"
        }
    ],
    "sg:phone":"+44 20 8367 2027",
    "sg:postcode":"EN2 6DR",
    "sg:province":"Greater London",
    "sg:tags":[
        "building",
        "society"
    ],
    "wof:name":"Bristol & West Plc",
    "wof:placetype":"venue"
},
  "geometry": {"coordinates":[-0.0805559978,51.6508674622],"type":"Point"}
}