{
  "type": "Feature",
  "properties": {
    "addr:full":"Glebe Pl, The Green, Wetheral Carlisle Cumbria CA4 8ET",
    "addr:postcode":"ca4 8et",
    "addr:street":"Glebe Pl The Green",
    "iso:country":"GB",
    "sg:address":"Glebe Pl, The Green, Wetheral",
    "sg:city":"Carlisle",
    "sg:classifiers":[
        {
            "category":"Real Estate",
            "subcategory":"Developer",
            "type":"Services"
        }
    ],
    "sg:phone":"+44 1228 409898",
    "sg:postcode":"CA4 8ET",
    "sg:province":"Cumbria",
    "sg:tags":[
        "property"
    ],
    "wof:name":"Anderson,W B,& Sons Ltd",
    "wof:placetype":"venue"
},
  "geometry": {"coordinates":[-2.831733942,54.8800048828],"type":"Point"}
}