{
  "type": "Feature",
  "properties": {
    "addr:full":"Southbourne Methodist Church, 5 Carbery Gardens Bournemouth Dorset BH6 3LS",
    "addr:housenumber":"5",
    "addr:postcode":"bh6 3ls",
    "addr:street":"Carbery Gardens",
    "iso:country":"GB",
    "sg:address":"Southbourne Methodist Church, 5 Carbery Gardens",
    "sg:city":"Bournemouth",
    "sg:classifiers":[
        {
            "category":"Place Of Worship",
            "type":"Public Place"
        }
    ],
    "sg:phone":"+44 1202 424085",
    "sg:postcode":"BH6 3LS",
    "sg:province":"Dorset",
    "wof:name":"Rev V Bircumshaw",
    "wof:placetype":"venue"
},
  "geometry": {"coordinates":[-1.7999099493,50.7275505066],"type":"Point"}
}