{
  "type": "Feature",
  "properties": {
    "addr:full":"161-163 St Johns Road, New Bold Chesterfield Derbyshire S41 8PE",
    "addr:housenumber":"161-163",
    "addr:postcode":"s41 8pe",
    "addr:street":"St Johns Road New",
    "iso:country":"GB",
    "sg:address":"161-163 St Johns Road, New Bold",
    "sg:city":"Chesterfield",
    "sg:classifiers":[
        {
            "category":"Retail",
            "subcategory":"Veterinary Services",
            "type":"Services"
        }
    ],
    "sg:phone":"+44 1246 455333",
    "sg:postcode":"S41 8PE",
    "sg:province":"Derbyshire",
    "sg:tags":[
        "surgeon"
    ],
    "wof:name":"I K Taylor",
    "wof:placetype":"venue"
},
  "geometry": {"coordinates":[-1.4415160418,53.2570877075],"type":"Point"}
}