{
  "type": "Feature",
  "properties": {
    "iso:country":"GB",
    "sg:address":"St Annes Road",
    "sg:city":"Bridlington",
    "sg:classifiers":[
        {
            "category":"Health Services",
            "subcategory":"Nursing And Care Facility",
            "type":"Services"
        },
        {
            "category":"Social Services",
            "subcategory":"Retirement Home",
            "type":"Services"
        }
    ],
    "sg:phone":"+44 1262 676836",
    "sg:postcode":"YO15 2JB",
    "sg:province":"East Riding of Yorkshire",
    "sg:tags":[
        "residential"
    ],
    "wof:name":"HUMBERSIDE INDEPENDENT CARE ASSOCIATION LTD",
    "wof:placetype":"venue"
},
  "geometry": {"coordinates":[-0.183211,54.088547],"type":"Point"}
}