{
  "type": "Feature",
  "properties": {
    "addr:full":"Unit 1 Moorland Laundry, Devonshire Road Weston-super-mare Somerset BS23 4EF",
    "addr:housenumber":"unit 1",
    "addr:postcode":"bs23 4ef",
    "addr:street":"Devonshire Road",
    "iso:country":"GB",
    "sg:address":"Unit 1 Moorland Laundry, Devonshire Road",
    "sg:city":"Weston-super-mare",
    "sg:classifiers":[
        {
            "category":"Professional",
            "subcategory":"Testing Lab",
            "type":"Services"
        },
        {
            "category":"Retail",
            "subcategory":"Auto Repair",
            "type":"Services"
        }
    ],
    "sg:phone":"+44 1934 622637",
    "sg:postcode":"BS23 4EF",
    "sg:province":"Somerset",
    "sg:tags":[
        "body",
        "car",
        "mot"
    ],
    "wof:name":"Alternative Car Hire",
    "wof:placetype":"venue"
},
  "geometry": {"coordinates":[-2.977184,51.346191],"type":"Point"}
}