{
  "type": "Feature",
  "properties": {
    "addr:full":"43 Waterhouse La Tadworth Surrey KT20 6EB",
    "addr:housenumber":"43",
    "addr:postcode":"kt20 6eb",
    "addr:street":"Waterhouse La Tadworth",
    "iso:country":"GB",
    "sg:address":"43 Waterhouse La",
    "sg:city":"Tadworth",
    "sg:classifiers":[
        {
            "category":"Social Services",
            "subcategory":"Retirement Home",
            "type":"Services"
        }
    ],
    "sg:phone":"+44 1737 359097",
    "sg:postcode":"KT20 6EB",
    "sg:province":"Surrey",
    "sg:tags":[
        "care"
    ],
    "wof:name":"Caring Group The",
    "wof:placetype":"venue"
},
  "geometry": {"coordinates":[-0.2131000012,51.2950782776],"type":"Point"}
}