{
  "type": "Feature",
  "properties": {
    "iso:country":"GB",
    "sg:address":"Unit 23-24 The Enterprise Centre, Station Parade",
    "sg:city":"Eastbourne",
    "sg:classifiers":[
        {
            "category":"Home & Garden",
            "subcategory":"Home Furnishings",
            "type":"Retail Goods"
        }
    ],
    "sg:phone":"+44 1323 431657",
    "sg:postcode":"BN21 1BD",
    "sg:province":"East Sussex",
    "sg:tags":[
        "blind",
        "curtain",
        "fitting"
    ],
    "wof:name":"Keber Curtains",
    "wof:placetype":"venue"
},
  "geometry": {"coordinates":[0.28535,50.766911],"type":"Point"}
}