{
  "type": "Feature",
  "properties": {
    "iso:country":"GB",
    "sg:address":"29 Lake Rd",
    "sg:city":"Bristol",
    "sg:classifiers":[
        {
            "category":"Wholesale",
            "subcategory":"Machinery & Supplies",
            "type":"Manufacturing & Wholesale Goods"
        }
    ],
    "sg:phone":"+44 117 940 9550",
    "sg:postcode":"BS10 5HY",
    "sg:province":"City of Bristol",
    "sg:tags":[
        "hydraulic"
    ],
    "wof:name":"G E Hydraulic Services",
    "wof:placetype":"venue"
},
  "geometry": {"coordinates":[-2.593529,51.500191],"type":"Point"}
}