{
  "type": "Feature",
  "properties": {
    "addr:full":"437 Crow Rd Glasgow Glasgow City G11 7DZ",
    "addr:housenumber":"437",
    "addr:postcode":"g11 7dz",
    "addr:street":"Crow Rd",
    "iso:country":"GB",
    "sg:address":"437 Crow Rd",
    "sg:city":"Glasgow",
    "sg:classifiers":[
        {
            "category":"Health Services",
            "subcategory":"Dentist",
            "type":"Services"
        }
    ],
    "sg:phone":"+44 141 339 4907",
    "sg:postcode":"G11 7DZ",
    "sg:province":"Glasgow City",
    "wof:name":"Clive R Bell B.D.S",
    "wof:placetype":"venue"
},
  "geometry": {"coordinates":[-4.325512,55.880264],"type":"Point"}
}