{
  "type": "Feature",
  "properties": {
    "iso:country":"GB",
    "sg:address":"Primrose Farm, Shelton",
    "sg:city":"Norwich",
    "sg:classifiers":[
        {
            "category":"Farming",
            "subcategory":"Farm",
            "type":"Manufacturing & Wholesale Goods"
        }
    ],
    "sg:postcode":"NR15 2SG",
    "sg:province":"Norfolk",
    "sg:tags":[
        "mixed",
        "crop"
    ],
    "wof:name":"D R Bartrum",
    "wof:placetype":"venue"
},
  "geometry": {"coordinates":[1.267129,52.470108],"type":"Point"}
}