{
  "type": "Feature",
  "properties": {
    "iso:country":"GB",
    "sg:address":"1 Capel Cres",
    "sg:city":"Newport",
    "sg:classifiers":[
        {
            "category":"Retail",
            "subcategory":"Auto Repair",
            "type":"Services"
        }
    ],
    "sg:postcode":"NP20 2FT",
    "sg:province":"Newport",
    "sg:tags":[
        "modification",
        "garage"
    ],
    "wof:name":"Isaacs,Dave, Cars",
    "wof:placetype":"venue"
},
  "geometry": {"coordinates":[-2.989859,51.57803],"type":"Point"}
}