{
  "type": "Feature",
  "properties": {
    "addr:full":"19 Wigmore Road, Broadwater Worthing West Sussex BN14 9HH",
    "addr:housenumber":"19",
    "addr:postcode":"bn14 9hh",
    "addr:street":"Wigmore Road",
    "iso:country":"GB",
    "sg:address":"19 Wigmore Road, Broadwater",
    "sg:city":"Worthing",
    "sg:classifiers":[
        {
            "category":"Building & Trades",
            "subcategory":"Construction",
            "type":"Services"
        }
    ],
    "sg:postcode":"BN14 9HH",
    "sg:province":"West Sussex",
    "sg:tags":[
        "decorator",
        "painter"
    ],
    "wof:name":"D T Decorations",
    "wof:placetype":"venue"
},
  "geometry": {"coordinates":[-0.3687979877,50.8300361633],"type":"Point"}
}