{
  "type": "Feature",
  "properties": {
    "addr:full":"Birling Gap, East Dean Eastbourne East Sussex BN20 0AB",
    "addr:postcode":"bn20 0ab",
    "addr:street":"Birling Gap East",
    "iso:country":"GB",
    "sg:address":"Birling Gap, East Dean",
    "sg:city":"Eastbourne",
    "sg:classifiers":[
        {
            "category":"Travel",
            "subcategory":"Hotels & Motels",
            "type":"Entertainment"
        }
    ],
    "sg:phone":"+44 1323 423197",
    "sg:postcode":"BN20 0AB",
    "sg:province":"East Sussex",
    "wof:name":"The Birling Gap Hotel Ltd.",
    "wof:placetype":"venue"
},
  "geometry": {"coordinates":[0.20818,50.759411],"type":"Point"}
}