{
  "type": "Feature",
  "properties": {
    "addr:full":"2lower Square, Civic Centre, St Nicholas Sutton Surrey SM1 1EA",
    "addr:postcode":"sm1 1ea",
    "addr:street":"2Lower Square",
    "iso:country":"GB",
    "sg:address":"2lower Square, Civic Centre, St Nicholas",
    "sg:city":"Sutton",
    "sg:classifiers":[
        {
            "category":"Organizations",
            "subcategory":"Non-profit Organization",
            "type":"Services"
        }
    ],
    "sg:phone":"+44 20 8770 4090",
    "sg:postcode":"SM1 1EA",
    "sg:province":"Surrey",
    "sg:tags":[
        "organisation",
        "voluntary",
        "charity"
    ],
    "wof:name":"Age Concern Sutton Borough",
    "wof:placetype":"venue"
},
  "geometry": {"coordinates":[-0.19643,51.36779],"type":"Point"}
}