{
  "type": "Feature",
  "properties": {
    "addr:full":"Unit B2, Prenton Way, North Chestshire Trading Estate Birkenhead Merseyside CH43 3DU",
    "addr:postcode":"ch43 3du",
    "addr:street":"Prenton Way North Chestshire Trading Estate",
    "iso:country":"GB",
    "sg:address":"Unit B2, Prenton Way, North Chestshire Trading Estate",
    "sg:city":"Birkenhead",
    "sg:classifiers":[
        {
            "category":"Professional",
            "subcategory":"Engineering",
            "type":"Services"
        }
    ],
    "sg:phone":"+44 151 608 8666",
    "sg:postcode":"CH43 3DU",
    "sg:province":"Merseyside",
    "sg:tags":[
        "precision",
        "engineer"
    ],
    "wof:name":"Goodwin Technology Ltd.",
    "wof:placetype":"venue"
},
  "geometry": {"coordinates":[-3.0698740482,53.368888855],"type":"Point"}
}