{
  "type": "Feature",
  "properties": {
    "addr:full":"Braunston Milton Keynes Buckinghamshire MK6 3AU",
    "addr:postcode":"mk6 3au",
    "iso:country":"GB",
    "sg:address":"Braunston",
    "sg:city":"Milton Keynes",
    "sg:classifiers":[
        {
            "category":"Place Of Worship",
            "type":"Public Place"
        }
    ],
    "sg:phone":"+44 1908 674742",
    "sg:postcode":"MK6 3AU",
    "sg:province":"Buckinghamshire",
    "wof:name":"St Mary's Church",
    "wof:placetype":"venue"
},
  "geometry": {"coordinates":[-0.721053,52.022587],"type":"Point"}
}