{
  "type": "Feature",
  "properties": {
    "iso:country":"GB",
    "sg:address":"Willows, Cherry Tree Road, Farnham Royal",
    "sg:city":"Slough",
    "sg:classifiers":[
        {
            "category":"Manufacturing",
            "subcategory":"Tools & Machinery",
            "type":"Manufacturing & Wholesale Goods"
        }
    ],
    "sg:phone":"+44 1753 643528",
    "sg:postcode":"SL2 3EF",
    "sg:province":"Berkshire",
    "sg:tags":[
        "society",
        "friendly"
    ],
    "wof:name":"Stephens & Partners",
    "wof:placetype":"venue"
},
  "geometry": {"coordinates":[-0.616684,51.539555],"type":"Point"}
}