{
  "type": "Feature",
  "properties": {
    "addr:full":"36 Longcause Street, Plympton Plymouth Devon PL7 1JB",
    "addr:housenumber":"36",
    "addr:postcode":"pl7 1jb",
    "addr:street":"Longcause Street",
    "iso:country":"GB",
    "sg:address":"36 Longcause Street, Plympton",
    "sg:city":"Plymouth",
    "sg:classifiers":[
        {
            "category":"Building & Trades",
            "subcategory":"Construction",
            "type":"Services"
        }
    ],
    "sg:postcode":"PL7 1JB",
    "sg:province":"Devon",
    "sg:tags":[
        "builder"
    ],
    "wof:name":"Peter Clayton Building Contractors",
    "wof:placetype":"venue"
},
  "geometry": {"coordinates":[-4.043639183,50.3837203979],"type":"Point"}
}