{
  "type": "Feature",
  "properties": {
    "addr:full":"2 Fife St, Barrowford Nelson Lancashire BB9 6DD",
    "addr:housenumber":"2",
    "addr:postcode":"bb9 6dd",
    "addr:street":"Fife St",
    "iso:country":"GB",
    "sg:address":"2 Fife St, Barrowford",
    "sg:city":"Nelson",
    "sg:classifiers":[
        {
            "category":"Government",
            "subcategory":"Post Office",
            "type":"Public Place"
        }
    ],
    "sg:postcode":"BB9 6DD",
    "sg:province":"Lancashire",
    "wof:name":"Drake,Margaret,",
    "wof:placetype":"venue"
},
  "geometry": {"coordinates":[-2.231744,53.841331],"type":"Point"}
}