{
  "type": "Feature",
  "properties": {
    "iso:country":"GB",
    "sg:address":"1 Bayliss Centre, 147 High Street",
    "sg:city":"Street",
    "sg:classifiers":[
        {
            "category":"Arts & Performance",
            "subcategory":"Art Gallery",
            "type":"Entertainment"
        }
    ],
    "sg:phone":"+44 1458 447722",
    "sg:postcode":"BA16 0EX",
    "sg:province":"Somerset",
    "wof:name":"The Street Gallery",
    "wof:placetype":"venue"
},
  "geometry": {"coordinates":[-2.74872,51.127872],"type":"Point"}
}