{
  "type": "Feature",
  "properties": {
    "addr:full":"College Farm, West Markham Retford Nottinghamshire DN22 6PJ",
    "addr:postcode":"dn22 6pj",
    "addr:street":"West",
    "iso:country":"GB",
    "sg:address":"College Farm, West Markham",
    "sg:city":"Retford",
    "sg:classifiers":[
        {
            "category":"Building & Trades",
            "subcategory":"Cleaning & Sanitation",
            "type":"Services"
        }
    ],
    "sg:phone":"+44 1777 703820",
    "sg:postcode":"DN22 6PJ",
    "sg:province":"Nottinghamshire",
    "sg:tags":[
        "dry",
        "control",
        "damp",
        "rot"
    ],
    "wof:name":"Damp Proofing Systems",
    "wof:placetype":"venue"
},
  "geometry": {"coordinates":[-0.945728004,53.3251838684],"type":"Point"}
}