{
  "type": "Feature",
  "properties": {
    "addr:full":"176 Crookes Sheffield South Yorkshire S10 1UH",
    "addr:housenumber":"176",
    "addr:postcode":"s10 1uh",
    "addr:street":"Crookes",
    "iso:country":"GB",
    "sg:address":"176 Crookes",
    "sg:city":"Sheffield",
    "sg:classifiers":[
        {
            "category":"Restaurant",
            "type":"Food & Drink"
        }
    ],
    "sg:phone":"+44 114 266 6052",
    "sg:postcode":"S10 1UH",
    "sg:province":"South Yorkshire",
    "sg:tags":[
        "indian",
        "-"
    ],
    "wof:name":"Indian Chef",
    "wof:placetype":"venue"
},
  "geometry": {"coordinates":[-1.5079330206,53.3844108582],"type":"Point"}
}