{
  "type": "Feature",
  "properties": {
    "iso:country":"GB",
    "sg:address":"8 School Street, Wolston",
    "sg:city":"Coventry",
    "sg:classifiers":[
        {
            "category":"Personal",
            "subcategory":"Beauty Salon",
            "type":"Services"
        }
    ],
    "sg:phone":"+44 24 7654 5277",
    "sg:postcode":"CV8 3HF",
    "sg:province":"Warwickshire",
    "sg:tags":[
        "unisex",
        "hairdresser"
    ],
    "wof:name":"Krazy Kutz",
    "wof:placetype":"venue"
},
  "geometry": {"coordinates":[-1.394436,52.37582],"type":"Point"}
}