{
  "type": "Feature",
  "properties": {
    "addr:full":"7 Hodgsons Court, Wickford Business Park, Hodgsons Way Wickford Essex SS11 8XR",
    "addr:housenumber":"7",
    "addr:postcode":"ss11 8xr",
    "addr:street":"Hodgsons Court Wickford Business Park Hodgsons Way",
    "iso:country":"GB",
    "sg:address":"7 Hodgsons Court, Wickford Business Park, Hodgsons Way",
    "sg:city":"Wickford",
    "sg:classifiers":[
        {
            "category":"Home & Garden",
            "subcategory":"Garden Supply",
            "type":"Retail Goods"
        }
    ],
    "sg:phone":"+44 1268 574444",
    "sg:postcode":"SS11 8XR",
    "sg:province":"Essex",
    "sg:tags":[
        "pool",
        "swimming"
    ],
    "wof:name":"Ryam Steels",
    "wof:placetype":"venue"
},
  "geometry": {"coordinates":[0.541185,51.603405],"type":"Point"}
}