{
  "type": "Feature",
  "properties": {
    "addr:full":"Borrans Road Ambleside Cumbria LA22 0EN",
    "addr:postcode":"la22 0en",
    "addr:street":"Borrans Road",
    "iso:country":"GB",
    "sg:address":"Borrans Road",
    "sg:city":"Ambleside",
    "sg:classifiers":[
        {
            "category":"Travel",
            "subcategory":"Hotels & Motels",
            "type":"Entertainment"
        }
    ],
    "sg:postcode":"LA22 0EN",
    "sg:province":"Cumbria",
    "wof:name":"Borrans Park Hotel",
    "wof:placetype":"venue"
},
  "geometry": {"coordinates":[-2.9675900936,54.424621582],"type":"Point"}
}