{
  "type": "Feature",
  "properties": {
    "iso:country":"GB",
    "sg:address":"Unit 6 Tanners Court, The Friars",
    "sg:city":"Newcastle Upon Tyne",
    "sg:classifiers":[
        {
            "category":"Banks & Credit Unions",
            "subcategory":"Financial Services",
            "type":"Services"
        }
    ],
    "sg:phone":"+44 191 232 0176",
    "sg:postcode":"NE1 5XE",
    "sg:province":"Tyne and Wear",
    "sg:tags":[
        "consultant"
    ],
    "wof:name":"Far East Commodities",
    "wof:placetype":"venue"
},
  "geometry": {"coordinates":[-1.61924,54.97105],"type":"Point"}
}