{
  "type": "Feature",
  "properties": {
    "addr:full":"10 Malvern Avenue, Stalmine Poulton Le Fylde Lancashire FY6 0QD",
    "addr:housenumber":"10",
    "addr:postcode":"fy6 0qd",
    "addr:street":"Malvern Avenue Stalmine Poulton Le Fylde",
    "iso:country":"GB",
    "sg:address":"10 Malvern Avenue, Stalmine",
    "sg:city":"Poulton Le Fylde",
    "sg:classifiers":[
        {
            "category":"Professional",
            "subcategory":"Printing & Photocopies",
            "type":"Services"
        }
    ],
    "sg:phone":"+44 1253 700038",
    "sg:postcode":"FY6 0QD",
    "sg:province":"Lancashire",
    "sg:tags":[
        "plate",
        "lithographic",
        "maker"
    ],
    "wof:name":"Gold Star Print Services",
    "wof:placetype":"venue"
},
  "geometry": {"coordinates":[-2.954849,53.899281],"type":"Point"}
}