{
  "type": "Feature",
  "properties": {
    "addr:full":"16 Princess Road, Standish Lower Ground Wigan Lancashire WN6 8LT",
    "addr:housenumber":"16",
    "addr:postcode":"wn6 8lt",
    "addr:street":"Princess Road",
    "iso:country":"GB",
    "sg:address":"16 Princess Road, Standish Lower Ground",
    "sg:city":"Wigan",
    "sg:classifiers":[
        {
            "category":"Freight",
            "type":"Transportation"
        }
    ],
    "sg:postcode":"WN6 8LT",
    "sg:province":"Lancashire",
    "sg:tags":[
        "haulage",
        "road"
    ],
    "wof:name":"Vincents Haulage Ltd.",
    "wof:placetype":"venue"
},
  "geometry": {"coordinates":[-2.674316,53.56311],"type":"Point"}
}