{
  "type": "Feature",
  "properties": {
    "iso:country":"GB",
    "sg:address":"8 Tregenna Hill",
    "sg:city":"St Ives",
    "sg:classifiers":[
        {
            "category":"Arts & Performance",
            "subcategory":"Art Gallery",
            "type":"Entertainment"
        }
    ],
    "sg:postcode":"TR26 1SE",
    "sg:province":"Cornwall",
    "wof:name":"8 Tregenna Hill Gallery",
    "wof:placetype":"venue"
},
  "geometry": {"coordinates":[-5.4806132317,50.2104873657],"type":"Point"}
}