{
  "type": "Feature",
  "properties": {
    "iso:country":"GB",
    "sg:address":"Greyfriars Ho, Gallowgate",
    "sg:city":"Aberdeen",
    "sg:classifiers":[
        {
            "category":"Government",
            "subcategory":"Office",
            "type":"Public Place"
        }
    ],
    "sg:phone":"+44 1224 618166",
    "sg:postcode":"AB10 1ZU",
    "sg:province":"Aberdeen City",
    "sg:tags":[
        "local"
    ],
    "wof:name":"Contributions Agency",
    "wof:placetype":"venue"
},
  "geometry": {"coordinates":[-2.0971798897,57.1507987976],"type":"Point"}
}