{
  "type": "Feature",
  "properties": {
    "addr:full":"17 Winchester Avenue Denny Falkirk FK6 6QE",
    "addr:housenumber":"17",
    "addr:postcode":"fk6 6qe",
    "addr:street":"Winchester Avenue Denny",
    "iso:country":"GB",
    "sg:address":"17 Winchester Avenue",
    "sg:city":"Denny",
    "sg:classifiers":[
        {
            "category":"Food & Beverages",
            "subcategory":"Supermarket",
            "type":"Retail Goods"
        }
    ],
    "sg:phone":"+44 1324 826363",
    "sg:postcode":"FK6 6QE",
    "sg:province":"Falkirk",
    "sg:tags":[
        "frozen"
    ],
    "wof:name":"Booker Foodservice Frozen",
    "wof:placetype":"venue"
},
  "geometry": {"coordinates":[-3.9054999352,56.0271911621],"type":"Point"}
}