{
  "type": "Feature",
  "properties": {
    "iso:country":"GB",
    "sg:address":"5 Highwalls Avenue",
    "sg:city":"Dinas Powys",
    "sg:classifiers":[
        {
            "category":"Building & Trades",
            "subcategory":"Construction",
            "type":"Services"
        }
    ],
    "sg:postcode":"CF64 4AP",
    "sg:province":"The Vale of Glamorgan",
    "sg:tags":[
        "builder"
    ],
    "wof:name":"Brain Brothers",
    "wof:placetype":"venue"
},
  "geometry": {"coordinates":[-3.221462965,51.4348907471],"type":"Point"}
}