{
  "type": "Feature",
  "properties": {
    "addr:full":"Northam Centre, Kent St Southampton Hampshire SO14 5SP",
    "addr:postcode":"so14 5sp",
    "addr:street":"Kent St",
    "iso:country":"GB",
    "sg:address":"Northam Centre, Kent St",
    "sg:city":"Southampton",
    "sg:classifiers":[
        {
            "category":"Community Center",
            "subcategory":"Youth",
            "type":"Public Place"
        }
    ],
    "sg:phone":"+44 23 8033 7888",
    "sg:postcode":"SO14 5SP",
    "sg:province":"Hampshire",
    "sg:tags":[
        "organisation",
        "centre"
    ],
    "wof:name":"Southampton Childrens Play Association",
    "wof:placetype":"venue"
},
  "geometry": {"coordinates":[-1.3880699873,50.9095611572],"type":"Point"}
}