{
  "type": "Feature",
  "properties": {
    "addr:full":"14-15 Marine Parade Southend-on-sea Essex SS1 2EJ",
    "addr:housenumber":"14-15",
    "addr:postcode":"ss1 2ej",
    "addr:street":"Marine Parade",
    "iso:country":"GB",
    "sg:address":"14-15 Marine Parade",
    "sg:city":"Southend-on-sea",
    "sg:classifiers":[
        {
            "category":"Bars & Pubs",
            "type":"Food & Drink"
        }
    ],
    "sg:phone":"+44 1702 468984",
    "sg:postcode":"SS1 2EJ",
    "sg:province":"Essex",
    "sg:tags":[
        "pubs",
        "inn"
    ],
    "wof:name":"The Papillion",
    "wof:placetype":"venue"
},
  "geometry": {"coordinates":[0.7184690237,51.5332260132],"type":"Point"}
}