{
  "type": "Feature",
  "properties": {
    "addr:full":"Zortech Avenue, Oldington Kidderminster Staffordshire DY11 7DY",
    "addr:postcode":"dy11 7dy",
    "addr:street":"Avenue Oldington",
    "iso:country":"GB",
    "sg:address":"Zortech Avenue, Oldington",
    "sg:city":"Kidderminster",
    "sg:classifiers":[
        {
            "category":"Community Center",
            "type":"Public Place"
        }
    ],
    "sg:phone":"+44 1562 829044",
    "sg:postcode":"DY11 7DY",
    "sg:province":"Staffordshire",
    "sg:tags":[
        "recreation",
        "leisure",
        "centre"
    ],
    "wof:name":"Gilt Edge Leisure Centre Ltd.",
    "wof:placetype":"venue"
},
  "geometry": {"coordinates":[-2.274538,52.360741],"type":"Point"}
}