{
  "type": "Feature",
  "properties": {
    "addr:full":"31 Weyside Road Guildford Surrey GU1 1HZ",
    "addr:housenumber":"31",
    "addr:postcode":"gu1 1hz",
    "addr:street":"Weyside Road",
    "iso:country":"GB",
    "sg:address":"31 Weyside Road",
    "sg:city":"Guildford",
    "sg:classifiers":[
        {
            "category":"Education",
            "subcategory":"School",
            "type":"Public Place"
        }
    ],
    "sg:phone":"+44 1483 572707",
    "sg:postcode":"GU1 1HZ",
    "sg:province":"Surrey",
    "sg:tags":[
        "private",
        "tuition"
    ],
    "wof:name":"Education Plus",
    "wof:placetype":"venue"
},
  "geometry": {"coordinates":[-0.580421,51.252483],"type":"Point"}
}