{
  "type": "Feature",
  "properties": {
    "addr:full":"Unit 10, Ludlow Hill Road, West Bridgford Nottingham Nottinghamshire NG2 6HF",
    "addr:housenumber":"unit 10",
    "addr:postcode":"ng2 6hf",
    "addr:street":"Ludlow Hill Road",
    "iso:country":"GB",
    "sg:address":"Unit 10, Ludlow Hill Road, West Bridgford",
    "sg:city":"Nottingham",
    "sg:classifiers":[
        {
            "category":"Sports & Exercise",
            "subcategory":"Tennis Court",
            "type":"Entertainment"
        }
    ],
    "sg:postcode":"NG2 6HF",
    "sg:province":"Nottinghamshire",
    "sg:tags":[
        "breakdown",
        "recovery"
    ],
    "wof:name":"K & C A Moore",
    "wof:placetype":"venue"
},
  "geometry": {"coordinates":[-1.1268049479,52.9212150574],"type":"Point"}
}