{
  "type": "Feature",
  "properties": {
    "iso:country":"GB",
    "sg:address":"P O Box 100",
    "sg:city":"Newcastle Upon Tyne",
    "sg:classifiers":[
        {
            "category":"Professional",
            "subcategory":"Employment Agencies",
            "type":"Services"
        }
    ],
    "sg:phone":"+44 191 261 5135",
    "sg:postcode":"NE99 1HE",
    "sg:province":"Tyne and Wear",
    "sg:tags":[
        "consultant"
    ],
    "wof:name":"Accountancy & Financial Appointments",
    "wof:placetype":"venue"
},
  "geometry": {"coordinates":[-1.6157699823,54.9677391052],"type":"Point"}
}