{
  "type": "Feature",
  "properties": {
    "iso:country":"GB",
    "sg:address":"Celtic Suite, 2 The Forum, Hanworth La",
    "sg:city":"Chertsey",
    "sg:classifiers":[
        {
            "category":"Professional",
            "subcategory":"Accounting & Tax Preparation",
            "type":"Services"
        }
    ],
    "sg:phone":"+44 1932 567374",
    "sg:postcode":"KT16 9JX",
    "sg:province":"Surrey",
    "sg:tags":[
        "consultant"
    ],
    "wof:name":"RM2 Ltd",
    "wof:placetype":"venue"
},
  "geometry": {"coordinates":[-0.508254,51.388199],"type":"Point"}
}