{
  "type": "Feature",
  "properties": {
    "iso:country":"GB",
    "sg:address":"228 Rye Lane, Peckham",
    "sg:city":"London",
    "sg:classifiers":[
        {
            "category":"Food & Beverages",
            "subcategory":"Meat & Fish",
            "type":"Retail Goods"
        }
    ],
    "sg:postcode":"SE15 4NL",
    "sg:province":"Greater London",
    "sg:tags":[
        "butcher"
    ],
    "wof:name":"W Head & Co.",
    "wof:placetype":"venue"
},
  "geometry": {"coordinates":[-0.0663,51.466324],"type":"Point"}
}