{
  "type": "Feature",
  "properties": {
    "iso:country":"GB",
    "sg:address":"7 Lincoln Road, Shortstown",
    "sg:city":"Bedford",
    "sg:classifiers":[
        {
            "category":"Manufacturing",
            "subcategory":"Signs",
            "type":"Manufacturing & Wholesale Goods"
        }
    ],
    "sg:postcode":"MK42 0UX",
    "sg:province":"Bedfordshire",
    "sg:tags":[
        "writer"
    ],
    "wof:name":"Dean Box Signwriters",
    "wof:placetype":"venue"
},
  "geometry": {"coordinates":[-0.437504,52.110325],"type":"Point"}
}