{
  "type": "Feature",
  "properties": {
    "iso:country":"GB",
    "sg:address":"9 Ledger Lane, Outwood",
    "sg:city":"Wakefield",
    "sg:classifiers":[
        {
            "category":"Retail",
            "subcategory":"Funeral Services",
            "type":"Services"
        }
    ],
    "sg:phone":"+44 1924 828238",
    "sg:postcode":"WF1 2PQ",
    "sg:province":"West Yorkshire",
    "sg:tags":[
        "director"
    ],
    "wof:name":"Harpins Funeral Services",
    "wof:placetype":"venue"
},
  "geometry": {"coordinates":[-1.5042970181,53.7090263367],"type":"Point"}
}