{
  "type": "Feature",
  "properties": {
    "iso:country":"GB",
    "sg:address":"Home Farm",
    "sg:city":"Swaffham",
    "sg:classifiers":[
        {
            "category":"Farming",
            "subcategory":"Farm",
            "type":"Manufacturing & Wholesale Goods"
        }
    ],
    "sg:phone":"+44 1366 328245",
    "sg:postcode":"PE37 8BE",
    "sg:province":"Norfolk",
    "sg:tags":[
        "mixed",
        "crop"
    ],
    "wof:name":"J Adcock",
    "wof:placetype":"venue"
},
  "geometry": {"coordinates":[0.689797,52.643845],"type":"Point"}
}