{
  "type": "Feature",
  "properties": {
    "addr:full":"12 Seymour Gro Manchester Cheshire M16 0LH",
    "addr:housenumber":"12",
    "addr:postcode":"m16 0lh",
    "addr:street":"Seymour Gro",
    "iso:country":"GB",
    "sg:address":"12 Seymour Gro",
    "sg:city":"Manchester",
    "sg:classifiers":[
        {
            "category":"Cafe",
            "type":"Food & Drink"
        }
    ],
    "sg:phone":"+44 161 876 4345",
    "sg:postcode":"M16 0LH",
    "sg:province":"Cheshire",
    "sg:tags":[
        "tea",
        "room"
    ],
    "wof:name":"Tracks Coffee Shop",
    "wof:placetype":"venue"
},
  "geometry": {"coordinates":[-2.273349,53.452888],"type":"Point"}
}