{
  "type": "Feature",
  "properties": {
    "addr:full":"56 Foregate Street Stafford Staffordshire ST16 2PR",
    "addr:housenumber":"56",
    "addr:postcode":"st16 2pr",
    "addr:street":"Foregate Street",
    "iso:country":"GB",
    "sg:address":"56 Foregate Street",
    "sg:city":"Stafford",
    "sg:classifiers":[
        {
            "category":"Restaurant",
            "type":"Food & Drink"
        }
    ],
    "sg:phone":"+44 1785 225772",
    "sg:postcode":"ST16 2PR",
    "sg:province":"Staffordshire",
    "sg:tags":[
        "indian"
    ],
    "wof:name":"Rose of Kashmir Balti Centre",
    "wof:placetype":"venue"
},
  "geometry": {"coordinates":[-2.1209468842,52.8116836548],"type":"Point"}
}