{
  "type": "Feature",
  "properties": {
    "addr:full":"41-42 High Street Exeter Devon EX4 3DJ",
    "addr:housenumber":"41-42",
    "addr:postcode":"ex4 3dj",
    "addr:street":"High Street",
    "iso:country":"GB",
    "sg:address":"41-42 High Street",
    "sg:city":"Exeter",
    "sg:classifiers":[
        {
            "category":"Shopping",
            "subcategory":"Clothing, Apparel, & Fashions",
            "type":"Retail Goods"
        }
    ],
    "sg:phone":"+44 1392 253949",
    "sg:postcode":"EX4 3DJ",
    "sg:province":"Devon",
    "sg:tags":[
        "shop",
        "lady",
        "fashionwear"
    ],
    "wof:name":"Laura Ashley Ltd",
    "wof:placetype":"venue"
},
  "geometry": {"coordinates":[-3.530924,50.723492],"type":"Point"}
}