{
  "type": "Feature",
  "properties": {
    "addr:full":"Brook Farm, Backwell Bristol Somerset BS48 3AA",
    "addr:postcode":"bs48 3aa",
    "addr:street":"Brook",
    "iso:country":"GB",
    "sg:address":"Brook Farm, Backwell",
    "sg:city":"Bristol",
    "sg:classifiers":[
        {
            "category":"Farming",
            "subcategory":"Livestock Farm",
            "type":"Manufacturing & Wholesale Goods"
        }
    ],
    "sg:phone":"+44 1275 462124",
    "sg:postcode":"BS48 3AA",
    "sg:province":"Somerset",
    "sg:tags":[
        "others"
    ],
    "wof:name":"E J Wyatt & Sons",
    "wof:placetype":"venue"
},
  "geometry": {"coordinates":[-2.7411789894,51.4130897522],"type":"Point"}
}