{
  "type": "Feature",
  "properties": {
    "iso:country":"GB",
    "sg:address":"5 Countess Lilias Road",
    "sg:city":"Cirencester",
    "sg:classifiers":[
        {
            "category":"Building & Trades",
            "subcategory":"Construction",
            "type":"Services"
        }
    ],
    "sg:phone":"+44 1285 656559",
    "sg:postcode":"GL7 1UD",
    "sg:province":"Gloucestershire",
    "sg:tags":[
        "glazier",
        "decorator",
        "painter"
    ],
    "wof:name":"James R Holden",
    "wof:placetype":"venue"
},
  "geometry": {"coordinates":[-1.971544,51.705017],"type":"Point"}
}