{
  "type": "Feature",
  "properties": {
    "addr:full":"46 Church Road Northolt Greater London UB5 5AB",
    "addr:housenumber":"46",
    "addr:postcode":"ub5 5ab",
    "addr:street":"Church Road",
    "iso:country":"GB",
    "sg:address":"46 Church Road",
    "sg:city":"Northolt",
    "sg:classifiers":[
        {
            "category":"Fast Food",
            "type":"Food & Drink"
        }
    ],
    "sg:phone":"+44 20 8841 3432",
    "sg:postcode":"UB5 5AB",
    "sg:province":"Greater London",
    "sg:tags":[
        "away",
        "take"
    ],
    "wof:name":"Target Fish Bar",
    "wof:placetype":"venue"
},
  "geometry": {"coordinates":[-0.373018,51.544861],"type":"Point"}
}