{
  "type": "Feature",
  "properties": {
    "iso:country":"GB",
    "sg:address":"Victoria House, 38-40 Dunraven Place",
    "sg:city":"Bridgend",
    "sg:classifiers":[
        {
            "category":"Real Estate",
            "subcategory":"Architect",
            "type":"Services"
        }
    ],
    "sg:phone":"+44 1656 654246",
    "sg:postcode":"CF31 1JB",
    "sg:province":"Bridgend",
    "wof:name":"William B Harries Baker",
    "wof:placetype":"venue"
},
  "geometry": {"coordinates":[-3.579106,51.50605],"type":"Point"}
}