{
  "type": "Feature",
  "properties": {
    "iso:country":"GB",
    "sg:address":"Bembridge New Road, Prestwood",
    "sg:city":"Great Missenden",
    "sg:classifiers":[
        {
            "category":"Building & Trades",
            "subcategory":"Landscaping Services",
            "type":"Services"
        }
    ],
    "sg:phone":"+44 1494 864168",
    "sg:postcode":"HP16 0PX",
    "sg:province":"Buckinghamshire",
    "sg:tags":[
        "landscape",
        "contractor"
    ],
    "wof:name":"Dove Landscapes",
    "wof:placetype":"venue"
},
  "geometry": {"coordinates":[-0.730009973,51.6993293762],"type":"Point"}
}