{
  "type": "Feature",
  "properties": {
    "addr:full":"27 Garbett Road, Winnall Winchester Hampshire SO23 0NY",
    "addr:housenumber":"27",
    "addr:postcode":"so23 0ny",
    "addr:street":"Garbett Road Winnall",
    "iso:country":"GB",
    "sg:address":"27 Garbett Road, Winnall",
    "sg:city":"Winchester",
    "sg:classifiers":[
        {
            "category":"Retail",
            "subcategory":"Laundry & Dry Cleaning",
            "type":"Services"
        }
    ],
    "sg:phone":"+44 1962 840658",
    "sg:postcode":"SO23 0NY",
    "sg:province":"Hampshire",
    "sg:tags":[
        "launderette"
    ],
    "wof:name":"Winnall Launderette",
    "wof:placetype":"venue"
},
  "geometry": {"coordinates":[-1.299941,51.064777],"type":"Point"}
}