{
  "type": "Feature",
  "properties": {
    "addr:full":"Sefton, Salisbury Street Hull East Riding of Yorkshire HU5 3EU",
    "addr:postcode":"hu5 3eu",
    "addr:street":"Salisbury Street",
    "iso:country":"GB",
    "sg:address":"Sefton, Salisbury Street",
    "sg:city":"Hull",
    "sg:classifiers":[
        {
            "category":"Farming",
            "subcategory":"Nursery",
            "type":"Manufacturing & Wholesale Goods"
        }
    ],
    "sg:phone":"+44 1482 448764",
    "sg:postcode":"HU5 3EU",
    "sg:province":"East Riding of Yorkshire",
    "sg:tags":[
        "creche"
    ],
    "wof:name":"Rainbow Nursery",
    "wof:placetype":"venue"
},
  "geometry": {"coordinates":[-0.366029,53.760025],"type":"Point"}
}