{
  "type": "Feature",
  "properties": {
    "addr:full":"Brookfields, Westridge Newbury Berkshire RG20 9RX",
    "addr:postcode":"rg20 9rx",
    "iso:country":"GB",
    "sg:address":"Brookfields, Westridge",
    "sg:city":"Newbury",
    "sg:classifiers":[
        {
            "category":"Health Services",
            "subcategory":"Health Practitioner",
            "type":"Services"
        }
    ],
    "sg:phone":"+44 1635 253973",
    "sg:postcode":"RG20 9RX",
    "sg:province":"Berkshire",
    "sg:tags":[
        "physiotherapist"
    ],
    "wof:name":"Andrew & Victoria Davis Ltd.",
    "wof:placetype":"venue"
},
  "geometry": {"coordinates":[-1.3770799637,51.3397789001],"type":"Point"}
}