{
  "type": "Feature",
  "properties": {
    "iso:country":"GB",
    "sg:address":"Leigh Street",
    "sg:city":"Chorley",
    "sg:classifiers":[
        {
            "category":"Social Services",
            "type":"Services"
        },
        {
            "category":"Government",
            "subcategory":"Office",
            "type":"Public Place"
        }
    ],
    "sg:phone":"+44 1257 260493",
    "sg:postcode":"PR7 3DJ",
    "sg:province":"Lancashire",
    "sg:tags":[
        "probation",
        "central"
    ],
    "wof:name":"The Probation Service",
    "wof:placetype":"venue"
},
  "geometry": {"coordinates":[-2.630134,53.648605],"type":"Point"}
}