{
  "type": "Feature",
  "properties": {
    "iso:country":"GB",
    "sg:address":"180 Bexley Road, Eltham",
    "sg:city":"London",
    "sg:classifiers":[
        {
            "category":"Personal",
            "subcategory":"Beauty Salon",
            "type":"Services"
        }
    ],
    "sg:postcode":"SE9 2PH",
    "sg:province":"Greater London",
    "wof:name":"Alexsam's Beauty Salon",
    "wof:placetype":"venue"
},
  "geometry": {"coordinates":[0.081899,51.45071],"type":"Point"}
}