{
  "type": "Feature",
  "properties": {
    "iso:country":"GB",
    "sg:address":"1 Albert Drive",
    "sg:city":"Gateshead",
    "sg:classifiers":[
        {
            "category":"Shopping",
            "subcategory":"Florist",
            "type":"Retail Goods"
        }
    ],
    "sg:postcode":"NE9 6EH",
    "sg:province":"Tyne and Wear",
    "wof:name":"Interior Plant Design",
    "wof:placetype":"venue"
},
  "geometry": {"coordinates":[-1.600304,54.934555],"type":"Point"}
}