{
  "type": "Feature",
  "properties": {
    "iso:country":"GB",
    "sg:address":"Warrington Market Hall, Bank St",
    "sg:city":"Warrington",
    "sg:classifiers":[
        {
            "category":"Shopping",
            "subcategory":"Luggage & Leather Goods",
            "type":"Retail Goods"
        }
    ],
    "sg:phone":"+44 1925 633409",
    "sg:postcode":"WA1 2EN",
    "sg:province":"Cheshire",
    "sg:tags":[
        "shop",
        "leathergoods"
    ],
    "wof:name":"Helens & Sybils",
    "wof:placetype":"venue"
},
  "geometry": {"coordinates":[-2.59178,53.38802],"type":"Point"}
}