{
  "type": "Feature",
  "properties": {
    "addr:full":"Barmouth, Rawcliffe Road, Airmyn Goole East Riding of Yorkshire DN14 8JN",
    "addr:postcode":"dn14 8jn",
    "addr:street":"Rawcliffe Road",
    "iso:country":"GB",
    "sg:address":"Barmouth, Rawcliffe Road, Airmyn",
    "sg:city":"Goole",
    "sg:classifiers":[
        {
            "category":"Professional",
            "subcategory":"Engineering",
            "type":"Services"
        }
    ],
    "sg:postcode":"DN14 8JN",
    "sg:province":"East Riding of Yorkshire",
    "sg:tags":[
        "contractor",
        "electrical",
        "engineer"
    ],
    "wof:name":"R & E Electrical Contractors",
    "wof:placetype":"venue"
},
  "geometry": {"coordinates":[-0.9030759931,53.7183609009],"type":"Point"}
}