{
  "type": "Feature",
  "properties": {
    "iso:country":"GB",
    "sg:address":"Drumoig Golf Club & Hotel, Drumoig, Leuchars",
    "sg:city":"St Andrews",
    "sg:classifiers":[
        {
            "category":"Travel",
            "subcategory":"Hotels & Motels",
            "type":"Entertainment"
        },
        {
            "category":"Sports & Exercise",
            "subcategory":"Golf",
            "type":"Entertainment"
        }
    ],
    "sg:phone":"+44 1382 541800",
    "sg:postcode":"KY16 0BE",
    "sg:province":"Fife",
    "sg:tags":[
        "club",
        "course"
    ],
    "wof:name":"Drumoig Ltd.",
    "wof:placetype":"venue"
},
  "geometry": {"coordinates":[-2.90958,56.414398],"type":"Point"}
}