{
  "type": "Feature",
  "properties": {
    "addr:full":"45 Hereward Cross Peterborough Cambridgeshire PE1 1TQ",
    "addr:housenumber":"45",
    "addr:postcode":"pe1 1tq",
    "addr:street":"Hereward Cross",
    "iso:country":"GB",
    "sg:address":"45 Hereward Cross",
    "sg:city":"Peterborough",
    "sg:classifiers":[
        {
            "category":"Shopping",
            "subcategory":"Pharmacy",
            "type":"Retail Goods"
        }
    ],
    "sg:phone":"+44 1733 343509",
    "sg:postcode":"PE1 1TQ",
    "sg:province":"Cambridgeshire",
    "sg:tags":[
        "pharmacist",
        "chemist"
    ],
    "wof:name":"Edwards Chemist",
    "wof:placetype":"venue"
},
  "geometry": {"coordinates":[-0.241794,52.574455],"type":"Point"}
}