{
  "type": "Feature",
  "properties": {
    "iso:country":"GB",
    "sg:address":"11 The Hams, Ide",
    "sg:city":"Exeter",
    "sg:classifiers":[
        {
            "category":"Professional",
            "subcategory":"Detective & Security Services",
            "type":"Services"
        }
    ],
    "sg:postcode":"EX2 9RU",
    "sg:province":"Devon",
    "sg:tags":[
        "alarm",
        "burglar",
        "system"
    ],
    "wof:name":"Devon Alarm Systems Ltd",
    "wof:placetype":"venue"
},
  "geometry": {"coordinates":[-3.560179,50.703583],"type":"Point"}
}