{
  "type": "Feature",
  "properties": {
    "addr:full":"Unit 13, Industrial Estate, National Exhibition Centre Birmingham West Midlands B40 1PJ",
    "addr:housenumber":"unit 13",
    "addr:postcode":"b40 1pj",
    "addr:street":"Industrial Estate",
    "iso:country":"GB",
    "sg:address":"Unit 13, Industrial Estate, National Exhibition Centre",
    "sg:city":"Birmingham",
    "sg:classifiers":[
        {
            "category":"Professional",
            "type":"Services"
        },
        {
            "category":"Sports & Exercise",
            "subcategory":"Playing Field",
            "type":"Entertainment"
        }
    ],
    "sg:phone":"+44 121 780 4511",
    "sg:postcode":"B40 1PJ",
    "sg:province":"West Midlands",
    "sg:tags":[
        "organiser",
        "exhibition",
        "fair",
        "trade"
    ],
    "wof:name":"Exoplan International Ltd",
    "wof:placetype":"venue"
},
  "geometry": {"coordinates":[-1.7249100208,52.4532814026],"type":"Point"}
}