{
  "type": "Feature",
  "properties": {
    "addr:full":"Crombie Centre, Crombie Rd Aberdeen Aberdeen City AB11 9QQ",
    "addr:postcode":"ab11 9qq",
    "addr:street":"Crombie Rd",
    "iso:country":"GB",
    "sg:address":"Crombie Centre, Crombie Rd",
    "sg:city":"Aberdeen",
    "sg:classifiers":[
        {
            "category":"Professional",
            "subcategory":"Management & Consulting",
            "type":"Services"
        }
    ],
    "sg:phone":"+44 1224 295000",
    "sg:postcode":"AB11 9QQ",
    "sg:province":"Aberdeen City",
    "sg:tags":[
        "fire",
        "consultant",
        "protection"
    ],
    "wof:name":"Wood Group Fire Protection Ltd",
    "wof:placetype":"venue"
},
  "geometry": {"coordinates":[-2.0857200623,57.1375312805],"type":"Point"}
}