{
  "type": "Feature",
  "properties": {
    "addr:full":"Manor House Farm, North Cliff York East Riding of Yorkshire YO43 4XE",
    "addr:postcode":"yo43 4xe",
    "addr:street":"Manor;North Cliff",
    "iso:country":"GB",
    "sg:address":"Manor House Farm, North Cliff",
    "sg:city":"York",
    "sg:classifiers":[
        {
            "category":"Farming",
            "subcategory":"Farm",
            "type":"Manufacturing & Wholesale Goods"
        }
    ],
    "sg:phone":"+44 1430 827661",
    "sg:postcode":"YO43 4XE",
    "sg:province":"East Riding of Yorkshire",
    "sg:tags":[
        "mixed",
        "crop"
    ],
    "wof:name":"R J Rook",
    "wof:placetype":"venue"
},
  "geometry": {"coordinates":[-0.674904,53.821304],"type":"Point"}
}