{
  "type": "Feature",
  "properties": {
    "iso:country":"GB",
    "sg:address":"78 Bury Old Rd",
    "sg:city":"Manchester",
    "sg:classifiers":[
        {
            "category":"Retail",
            "subcategory":"Repair Shop",
            "type":"Services"
        }
    ],
    "sg:phone":"+44 161 798 5288",
    "sg:postcode":"M45 6TQ",
    "sg:province":"Lancashire",
    "sg:tags":[
        "radio",
        "television",
        "video"
    ],
    "wof:name":"Telly Shop The",
    "wof:placetype":"venue"
},
  "geometry": {"coordinates":[-2.284058,53.540222],"type":"Point"}
}