{
  "type": "Feature",
  "properties": {
    "addr:full":"Castleton, Jubilee Road, Finchampstead Wokingham Berkshire RG40 3RU",
    "addr:postcode":"rg40 3ru",
    "addr:street":"Jubilee Road",
    "iso:country":"GB",
    "sg:address":"Castleton, Jubilee Road, Finchampstead",
    "sg:city":"Wokingham",
    "sg:classifiers":[
        {
            "category":"Real Estate",
            "subcategory":"Real Estate Services",
            "type":"Services"
        },
        {
            "category":"Banks & Credit Unions",
            "subcategory":"Financial Services",
            "type":"Services"
        }
    ],
    "sg:phone":"+44 118 932 8085",
    "sg:postcode":"RG40 3RU",
    "sg:province":"Berkshire",
    "sg:tags":[
        "consultant",
        "management"
    ],
    "wof:name":"Castleton Investments Ltd.",
    "wof:placetype":"venue"
},
  "geometry": {"coordinates":[-0.8345940113,51.4108009338],"type":"Point"}
}