{
  "type": "Feature",
  "properties": {
    "addr:full":"9 Harrison Rd Wakefield West Yorkshire WF4 1NE",
    "addr:housenumber":"9",
    "addr:postcode":"wf4 1ne",
    "addr:street":"Harrison Rd",
    "iso:country":"GB",
    "sg:address":"9 Harrison Rd",
    "sg:city":"Wakefield",
    "sg:classifiers":[
        {
            "category":"Retail",
            "subcategory":"Repair Shop",
            "type":"Services"
        }
    ],
    "sg:phone":"+44 1924 862800",
    "sg:postcode":"WF4 1NE",
    "sg:province":"West Yorkshire",
    "sg:tags":[
        "maintenance"
    ],
    "wof:name":"J & L R Services",
    "wof:placetype":"venue"
},
  "geometry": {"coordinates":[-1.433292985,53.6596488953],"type":"Point"}
}