{
  "type": "Feature",
  "properties": {
    "addr:full":"178 Corporation Rd Newport Newport NP19 0AW",
    "addr:housenumber":"178",
    "addr:postcode":"np19 0aw",
    "addr:street":"Corporation Rd",
    "iso:country":"GB",
    "sg:address":"178 Corporation Rd",
    "sg:city":"Newport",
    "sg:classifiers":[
        {
            "category":"Building & Trades",
            "subcategory":"Landscaping Services",
            "type":"Services"
        }
    ],
    "sg:postcode":"NP19 0AW",
    "sg:province":"Newport",
    "sg:tags":[
        "pond",
        "aquarium"
    ],
    "wof:name":"Ahmed,Javid,",
    "wof:placetype":"venue"
},
  "geometry": {"coordinates":[-2.9820730686,51.5863456726],"type":"Point"}
}