{
  "type": "Feature",
  "properties": {
    "iso:country":"GB",
    "sg:address":"Common Lane",
    "sg:city":"Knottingley",
    "sg:classifiers":[
        {
            "category":"Manufacturing",
            "subcategory":"Metals",
            "type":"Manufacturing & Wholesale Goods"
        },
        {
            "category":"Home & Garden",
            "subcategory":"Household Appliances",
            "type":"Retail Goods"
        },
        {
            "category":"Building & Trades",
            "subcategory":"Construction",
            "type":"Services"
        }
    ],
    "sg:phone":"+44 1977 672322",
    "sg:postcode":"WF11 8BN",
    "sg:province":"North Yorkshire",
    "sg:tags":[
        "steel",
        "electrical",
        "welder",
        "domestic",
        "fabricator"
    ],
    "sg:website":"http://www.gandb.co.uk",
    "wof:name":"Gillian & Baines",
    "wof:placetype":"venue"
},
  "geometry": {"coordinates":[-1.2303550243,53.7062835693],"type":"Point"}
}