{
  "type": "Feature",
  "properties": {
    "iso:country":"GB",
    "sg:address":"Unit 5b, Enterprise Road, Golf Road Industrial Estate",
    "sg:city":"Mablethorpe",
    "sg:classifiers":[
        {
            "category":"Shopping",
            "subcategory":"Stationery & Office Supplies",
            "type":"Retail Goods"
        }
    ],
    "sg:phone":"+44 1507 478757",
    "sg:postcode":"LN12 1NB",
    "sg:province":"Lincolnshire",
    "sg:tags":[
        "commercial"
    ],
    "wof:name":"Quantum Technologies Ltd.",
    "wof:placetype":"venue"
},
  "geometry": {"coordinates":[0.251095,53.34745],"type":"Point"}
}