{
  "type": "Feature",
  "properties": {
    "iso:country":"GB",
    "sg:address":"Visual Ho, York St",
    "sg:city":"Wigan",
    "sg:classifiers":[
        {
            "category":"Professional",
            "subcategory":"Detective & Security Services",
            "type":"Services"
        }
    ],
    "sg:postcode":"WN3 4BY",
    "sg:province":"Lancashire",
    "sg:tags":[
        "video",
        "cctv"
    ],
    "wof:name":"M G Visual C C T V",
    "wof:placetype":"venue"
},
  "geometry": {"coordinates":[-2.64171,53.54493],"type":"Point"}
}