{
  "type": "Feature",
  "properties": {
    "addr:full":"Bridgnorth Road, Madeley Telford Shropshire TF7 4JB",
    "addr:postcode":"tf7 4jb",
    "addr:street":"Bridgnorth Road",
    "iso:country":"GB",
    "sg:address":"Bridgnorth Road, Madeley",
    "sg:city":"Telford",
    "sg:classifiers":[
        {
            "category":"Utilities",
            "subcategory":"Water",
            "type":"Services"
        },
        {
            "category":"Military Area",
            "subcategory":"Air Force Base",
            "type":"Public Place"
        }
    ],
    "sg:phone":"+44 1952 582770",
    "sg:postcode":"TF7 4JB",
    "sg:province":"Shropshire",
    "sg:tags":[
        "treatment"
    ],
    "wof:name":"Graham F Price",
    "wof:placetype":"venue"
},
  "geometry": {"coordinates":[-2.4410591125,52.6418037415],"type":"Point"}
}