{
  "type": "Feature",
  "properties": {
    "iso:country":"GB",
    "sg:address":"Runwood House, 107 London Road",
    "sg:city":"Benfleet",
    "sg:classifiers":[
        {
            "category":"Insurance",
            "subcategory":"Insurance Agent",
            "type":"Services"
        },
        {
            "category":"Banks & Credit Unions",
            "subcategory":"Financial Services",
            "type":"Services"
        }
    ],
    "sg:phone":"+44 1702 557571",
    "sg:postcode":"SS7 2QL",
    "sg:province":"Essex",
    "sg:tags":[
        "adviser",
        "broker"
    ],
    "wof:name":"Professional Financial Solutions",
    "wof:placetype":"venue"
},
  "geometry": {"coordinates":[0.60384,51.55508],"type":"Point"}
}