{
  "type": "Feature",
  "properties": {
    "addr:full":"Greenwich Church Street London Greater London SE10 9BJ",
    "addr:postcode":"se10 9bj",
    "addr:street":"Church Street",
    "iso:country":"GB",
    "sg:address":"Greenwich Church Street",
    "sg:city":"London",
    "sg:classifiers":[
        {
            "category":"Place Of Worship",
            "type":"Public Place"
        }
    ],
    "sg:phone":"+44 20 8853 0687",
    "sg:postcode":"SE10 9BJ",
    "sg:province":"Greater London",
    "wof:name":"St.Alfege Church",
    "wof:placetype":"venue"
},
  "geometry": {"coordinates":[0.002435,51.484467],"type":"Point"}
}