{
  "type": "Feature",
  "properties": {
    "iso:country":"GB",
    "sg:address":"23b Dundas Street",
    "sg:city":"Edinburgh",
    "sg:classifiers":[
        {
            "category":"Professional",
            "subcategory":"Lawyer & Legal Services",
            "type":"Services"
        }
    ],
    "sg:phone":"+44 131 556 7525",
    "sg:postcode":"EH3 6QQ",
    "sg:province":"City of Edinburgh",
    "sg:tags":[
        "solicitor"
    ],
    "wof:name":"Kenneth F Brown",
    "wof:placetype":"venue"
},
  "geometry": {"coordinates":[-3.1989440918,55.95703125],"type":"Point"}
}