{
  "type": "Feature",
  "properties": {
    "iso:country":"GB",
    "sg:address":"5b Perry Rd",
    "sg:city":"Witham",
    "sg:classifiers":[
        {
            "category":"Autos & Motor Vehicles",
            "subcategory":"Automobile Sales",
            "type":"Retail Goods"
        }
    ],
    "sg:postcode":"CM8 3YZ",
    "sg:province":"Essex",
    "sg:tags":[
        "car"
    ],
    "wof:name":"Pryke,S,",
    "wof:placetype":"venue"
},
  "geometry": {"coordinates":[0.6491670012,51.7972602844],"type":"Point"}
}