{
  "type": "Feature",
  "properties": {
    "addr:full":"2 Monmore Rd Wolverhampton West Midlands WV1 2TZ",
    "addr:housenumber":"2",
    "addr:postcode":"wv1 2tz",
    "addr:street":"Monmore Rd",
    "iso:country":"GB",
    "sg:address":"2 Monmore Rd",
    "sg:city":"Wolverhampton",
    "sg:classifiers":[
        {
            "category":"Utilities",
            "subcategory":"Refuse",
            "type":"Services"
        }
    ],
    "sg:phone":"+44 1902 401232",
    "sg:postcode":"WV1 2TZ",
    "sg:province":"West Midlands",
    "sg:tags":[
        "skip",
        "hire"
    ],
    "wof:name":"Irving Skip Hire",
    "wof:placetype":"venue"
},
  "geometry": {"coordinates":[-2.1005089283,52.5753974915],"type":"Point"}
}