{
  "type": "Feature",
  "properties": {
    "addr:full":"Thorpe House, 149 Harwich Rd, Little Clacton Clacton On Sea Essex CO16 9NJ",
    "addr:housenumber":"149",
    "addr:postcode":"co16 9nj",
    "addr:street":"Harwich Rd;Sea",
    "iso:country":"GB",
    "sg:address":"Thorpe House, 149 Harwich Rd, Little Clacton",
    "sg:city":"Clacton On Sea",
    "sg:classifiers":[
        {
            "category":"Health Services",
            "subcategory":"Nursing And Care Facility",
            "type":"Services"
        }
    ],
    "sg:phone":"+44 1255 860737",
    "sg:postcode":"CO16 9NJ",
    "sg:province":"Essex",
    "sg:tags":[
        "home"
    ],
    "wof:name":"Edensor Nursing Care Home",
    "wof:placetype":"venue"
},
  "geometry": {"coordinates":[1.1482319832,51.8400001526],"type":"Point"}
}