{
  "type": "Feature",
  "properties": {
    "addr:full":"9 West Princes Street Helensburgh Argyll and Bute G84 8TF",
    "addr:housenumber":"9",
    "addr:postcode":"g84 8tf",
    "addr:street":"West Princes Street",
    "iso:country":"GB",
    "sg:address":"9 West Princes Street",
    "sg:city":"Helensburgh",
    "sg:classifiers":[
        {
            "category":"Cinema",
            "subcategory":"Movie Rental",
            "type":"Entertainment"
        }
    ],
    "sg:phone":"+44 1436 675168",
    "sg:postcode":"G84 8TF",
    "sg:province":"Argyll and Bute",
    "sg:tags":[
        "video",
        "library"
    ],
    "wof:name":"Global Video (Uk) Ltd.",
    "wof:placetype":"venue"
},
  "geometry": {"coordinates":[-4.7339630127,56.0039710999],"type":"Point"}
}