{
  "type": "Feature",
  "properties": {
    "addr:full":"10-12 The Forbury Reading Berkshire RG1 3EJ",
    "addr:housenumber":"10-12",
    "addr:postcode":"rg1 3ej",
    "addr:street":"The Forbury",
    "iso:country":"GB",
    "sg:address":"10-12 The Forbury",
    "sg:city":"Reading",
    "sg:classifiers":[
        {
            "category":"Banks & Credit Unions",
            "subcategory":"Bank",
            "type":"Services"
        }
    ],
    "sg:phone":"+44 118 958 2532",
    "sg:postcode":"RG1 3EJ",
    "sg:province":"Berkshire",
    "sg:tags":[
        "broker",
        "mortgage"
    ],
    "wof:name":"Goss & Co (Life & Pensions) Brokers",
    "wof:placetype":"venue"
},
  "geometry": {"coordinates":[-0.9691929817,51.4561309814],"type":"Point"}
}