{
  "type": "Feature",
  "properties": {
    "addr:full":"5a Chesterton Place, Chester Road Newquay Cornwall TR7 2RU",
    "addr:housenumber":"5a",
    "addr:postcode":"tr7 2ru",
    "addr:street":"Chesterton Place Chester Road",
    "iso:country":"GB",
    "sg:address":"5a Chesterton Place, Chester Road",
    "sg:city":"Newquay",
    "sg:classifiers":[
        {
            "category":"Shopping",
            "subcategory":"Clothing, Apparel, & Fashions",
            "type":"Retail Goods"
        }
    ],
    "sg:phone":"+44 1637 873820",
    "sg:postcode":"TR7 2RU",
    "sg:province":"Cornwall",
    "sg:tags":[
        "shop"
    ],
    "wof:name":"L A Style",
    "wof:placetype":"venue"
},
  "geometry": {"coordinates":[-5.071859,50.412086],"type":"Point"}
}