{
  "type": "Feature",
  "properties": {
    "iso:country":"GB",
    "sg:address":"179 Pixmore Way",
    "sg:city":"Letchworth",
    "sg:classifiers":[
        {
            "category":"Place Of Worship",
            "type":"Public Place"
        }
    ],
    "sg:phone":"+44 1462 637373",
    "sg:postcode":"SG6 1QT",
    "sg:province":"Hertfordshire",
    "wof:name":"St. Paul's Church",
    "wof:placetype":"venue"
},
  "geometry": {"coordinates":[-0.21486,51.976334],"type":"Point"}
}