{
  "type": "Feature",
  "properties": {
    "addr:full":"Unit 6, Smiths Yard, Hardings Row Iver Berkshire SL0 0HH",
    "addr:housenumber":"unit 6",
    "addr:postcode":"sl0 0hh",
    "addr:street":"Smiths Yard Hardings Row",
    "iso:country":"GB",
    "sg:address":"Unit 6, Smiths Yard, Hardings Row",
    "sg:city":"Iver",
    "sg:classifiers":[
        {
            "category":"Retail",
            "subcategory":"Auto Repair",
            "type":"Services"
        }
    ],
    "sg:phone":"+44 1753 791098",
    "sg:postcode":"SL0 0HH",
    "sg:province":"Berkshire",
    "sg:tags":[
        "body",
        "car"
    ],
    "wof:name":"Dragonquest Motors",
    "wof:placetype":"venue"
},
  "geometry": {"coordinates":[-0.5206189752,51.5365447998],"type":"Point"}
}