{
  "type": "Feature",
  "properties": {
    "iso:country":"GB",
    "sg:address":"37 The Village",
    "sg:city":"York",
    "sg:classifiers":[
        {
            "category":"Banks & Credit Unions",
            "subcategory":"Bank",
            "type":"Services"
        }
    ],
    "sg:phone":"+44 1904 884000",
    "sg:postcode":"YO32 2HU",
    "sg:province":"North Yorkshire",
    "wof:name":"Hsbc Bank Plc",
    "wof:placetype":"venue"
},
  "geometry": {"coordinates":[-1.086626,54.019051],"type":"Point"}
}