{
  "type": "Feature",
  "properties": {
    "iso:country":"GB",
    "sg:address":"4 Stone St",
    "sg:city":"Faversham",
    "sg:classifiers":[
        {
            "category":"Real Estate",
            "subcategory":"Architect",
            "type":"Services"
        }
    ],
    "sg:phone":"+44 1795 534185",
    "sg:postcode":"ME13 8PT",
    "sg:province":"Kent",
    "sg:tags":[
        "architectural"
    ],
    "wof:name":"Bee Design Associates",
    "wof:placetype":"venue"
},
  "geometry": {"coordinates":[0.886347,51.31461],"type":"Point"}
}