{
  "type": "Feature",
  "properties": {
    "addr:full":"30 High Street Addlestone Surrey KT15 1TN",
    "addr:housenumber":"30",
    "addr:postcode":"kt15 1tn",
    "addr:street":"High Street",
    "iso:country":"GB",
    "sg:address":"30 High Street",
    "sg:city":"Addlestone",
    "sg:classifiers":[
        {
            "category":"Insurance",
            "subcategory":"Insurance Agent",
            "type":"Services"
        }
    ],
    "sg:phone":"+44 1932 857727",
    "sg:postcode":"KT15 1TN",
    "sg:province":"Surrey",
    "wof:name":"Grayside (Addlestone) Ltd.",
    "wof:placetype":"venue"
},
  "geometry": {"coordinates":[-0.49343,51.372028],"type":"Point"}
}