{
  "type": "Feature",
  "properties": {
    "addr:full":"9 Southchurch Road Southend-on-sea Essex SS1 2NE",
    "addr:housenumber":"9",
    "addr:postcode":"ss1 2ne",
    "addr:street":"Southchurch Road",
    "iso:country":"GB",
    "sg:address":"9 Southchurch Road",
    "sg:city":"Southend-on-sea",
    "sg:classifiers":[
        {
            "category":"Food & Beverages",
            "subcategory":"Specialty",
            "type":"Retail Goods"
        }
    ],
    "sg:phone":"+44 1702 615415",
    "sg:postcode":"SS1 2NE",
    "sg:province":"Essex",
    "sg:tags":[
        "product",
        "health"
    ],
    "wof:name":"Holland & Barrett",
    "wof:placetype":"venue"
},
  "geometry": {"coordinates":[0.7118859887,51.5402488708],"type":"Point"}
}