{
  "type": "Feature",
  "properties": {
    "iso:country":"GB",
    "sg:address":"Number 1 Cottage Newton Farm, Harbottle",
    "sg:city":"Morpeth",
    "sg:classifiers":[
        {
            "category":"Building & Trades",
            "subcategory":"Equipment Rental",
            "type":"Services"
        }
    ],
    "sg:postcode":"NE65 7DP",
    "sg:province":"Northumberland",
    "sg:tags":[
        "plant",
        "machinery"
    ],
    "wof:name":"W A Graham & Sons",
    "wof:placetype":"venue"
},
  "geometry": {"coordinates":[-2.06924,55.346619],"type":"Point"}
}