{
  "type": "Feature",
  "properties": {
    "iso:country":"GB",
    "sg:address":"318 Dover Rd",
    "sg:city":"Deal",
    "sg:classifiers":[
        {
            "category":"Place Of Worship",
            "type":"Public Place"
        }
    ],
    "sg:phone":"+44 1304 374399",
    "sg:postcode":"CT14 7NX",
    "sg:province":"Kent",
    "wof:name":"Sacred Heart Chapel",
    "wof:placetype":"venue"
},
  "geometry": {"coordinates":[1.40009,51.210098],"type":"Point"}
}