{
  "type": "Feature",
  "properties": {
    "addr:full":"Fular Way, Wickford Business Park Wickford Essex SS11 8YW",
    "addr:postcode":"ss11 8yw",
    "addr:street":"Fular Way;Park",
    "iso:country":"GB",
    "sg:address":"Fular Way, Wickford Business Park",
    "sg:city":"Wickford",
    "sg:classifiers":[
        {
            "category":"Freight",
            "type":"Transportation"
        }
    ],
    "sg:phone":"+44 1268 572871",
    "sg:postcode":"SS11 8YW",
    "sg:province":"Essex",
    "sg:tags":[
        "forwarders"
    ],
    "wof:name":"Wilgo Freight Services Ltd.",
    "wof:placetype":"venue"
},
  "geometry": {"coordinates":[0.5469989777,51.6023597717],"type":"Point"}
}