{
  "type": "Feature",
  "properties": {
    "addr:full":"Yew Tree Cottage, Woonton Hereford Herefordshire HR3 6QH",
    "addr:postcode":"hr3 6qh",
    "addr:street":"Yew;Woonton",
    "iso:country":"GB",
    "sg:address":"Yew Tree Cottage, Woonton",
    "sg:city":"Hereford",
    "sg:classifiers":[
        {
            "category":"Travel",
            "subcategory":"Travel Agent",
            "type":"Entertainment"
        }
    ],
    "sg:phone":"+44 1544 327149",
    "sg:postcode":"HR3 6QH",
    "sg:province":"Herefordshire",
    "wof:name":"Best Algarve Ltd.",
    "wof:placetype":"venue"
},
  "geometry": {"coordinates":[-2.949051,52.16396],"type":"Point"}
}