{
  "type": "Feature",
  "properties": {
    "addr:full":"School Road, Symington Biggar Dumfries and Galloway ML12 6LT",
    "addr:postcode":"ml12 6lt",
    "addr:street":"School Road",
    "iso:country":"GB",
    "sg:address":"School Road, Symington",
    "sg:city":"Biggar",
    "sg:classifiers":[
        {
            "category":"Education",
            "subcategory":"School",
            "type":"Public Place"
        },
        {
            "category":"Government",
            "subcategory":"Office",
            "type":"Public Place"
        }
    ],
    "sg:phone":"+44 1899 308279",
    "sg:postcode":"ML12 6LT",
    "sg:province":"Dumfries and Galloway",
    "sg:tags":[
        "local",
        "authority"
    ],
    "wof:name":"Tinto Primary School",
    "wof:placetype":"venue"
},
  "geometry": {"coordinates":[-3.5230190754,55.624420166],"type":"Point"}
}