{
  "type": "Feature",
  "properties": {
    "addr:full":"Harris Hotel, Scott Road, Tarbert Harris Eilean Siar HS3 3DL",
    "addr:postcode":"hs3 3dl",
    "addr:street":"Scott Road",
    "iso:country":"GB",
    "sg:address":"Harris Hotel, Scott Road, Tarbert",
    "sg:city":"Harris",
    "sg:classifiers":[
        {
            "category":"Travel",
            "subcategory":"Hotels & Motels",
            "type":"Entertainment"
        }
    ],
    "sg:postcode":"HS3 3DL",
    "sg:province":"Eilean Siar",
    "wof:name":"Atlantic Land & Property Ltd.",
    "wof:placetype":"venue"
},
  "geometry": {"coordinates":[-6.7984838486,57.8973464966],"type":"Point"}
}