{
  "type": "Feature",
  "properties": {
    "addr:full":"35 Coleshill Birmingham West Midlands B36 8DT",
    "addr:housenumber":"35",
    "addr:postcode":"b36 8dt",
    "addr:street":"Coleshill Birmingham",
    "iso:country":"GB",
    "sg:address":"35 Coleshill",
    "sg:city":"Birmingham",
    "sg:classifiers":[
        {
            "category":"Professional",
            "subcategory":"Computer Services",
            "type":"Services"
        }
    ],
    "sg:phone":"+44 121 789 8986",
    "sg:postcode":"B36 8DT",
    "sg:province":"West Midlands",
    "sg:tags":[
        "system",
        "software"
    ],
    "wof:name":"Sterling Knight Corporation Ltd.",
    "wof:placetype":"venue"
},
  "geometry": {"coordinates":[-1.8168940544,52.4944000244],"type":"Point"}
}