{
  "type": "Feature",
  "properties": {
    "addr:full":"22 Llandaff Road, Canton Cardiff Cardiff CF11 9NJ",
    "addr:housenumber":"22",
    "addr:postcode":"cf11 9nj",
    "addr:street":"Llandaff Road",
    "iso:country":"GB",
    "sg:address":"22 Llandaff Road, Canton",
    "sg:city":"Cardiff",
    "sg:classifiers":[
        {
            "category":"Building & Trades",
            "subcategory":"Construction",
            "type":"Services"
        }
    ],
    "sg:phone":"+44 29 2037 4094",
    "sg:postcode":"CF11 9NJ",
    "sg:province":"Cardiff",
    "sg:tags":[
        "dry",
        "plastering",
        "plasterers",
        "lining",
        "related",
        "screeders"
    ],
    "wof:name":"Toshack & Gibson Ltd",
    "wof:placetype":"venue"
},
  "geometry": {"coordinates":[-3.202042,51.482449],"type":"Point"}
}