{
  "type": "Feature",
  "properties": {
    "addr:full":"63a Brownfield Gardens Maidenhead Berkshire SL6 2RL",
    "addr:housenumber":"63a",
    "addr:postcode":"sl6 2rl",
    "addr:street":"Brownfield Gardens",
    "iso:country":"GB",
    "sg:address":"63a Brownfield Gardens",
    "sg:city":"Maidenhead",
    "sg:classifiers":[
        {
            "category":"Building & Trades",
            "subcategory":"Landscaping Services",
            "type":"Services"
        }
    ],
    "sg:phone":"+44 1628 634967",
    "sg:postcode":"SL6 2RL",
    "sg:province":"Berkshire",
    "sg:tags":[
        "gardening"
    ],
    "wof:name":"H Rockall & Sons",
    "wof:placetype":"venue"
},
  "geometry": {"coordinates":[-0.7304909825,51.5151367188],"type":"Point"}
}