{
  "type": "Feature",
  "properties": {
    "iso:country":"GB",
    "sg:address":"7 Summerfield Road, Palm Bay",
    "sg:city":"Margate",
    "sg:classifiers":[
        {
            "category":"Insurance",
            "subcategory":"Insurance Agent",
            "type":"Services"
        }
    ],
    "sg:phone":"+44 1843 226611",
    "sg:postcode":"CT9 3EZ",
    "sg:province":"Kent",
    "wof:name":"Abacus Insurance Services Ltd.",
    "wof:placetype":"venue"
},
  "geometry": {"coordinates":[1.424485,51.386276],"type":"Point"}
}