{
  "type": "Feature",
  "properties": {
    "addr:full":"6 Market Terrace, Albany Road Brentford Greater London TW8 0NQ",
    "addr:housenumber":"6",
    "addr:postcode":"tw8 0nq",
    "addr:street":"Market Terrace Albany Road",
    "iso:country":"GB",
    "sg:address":"6 Market Terrace, Albany Road",
    "sg:city":"Brentford",
    "sg:classifiers":[
        {
            "category":"Home & Garden",
            "subcategory":"Household Appliances",
            "type":"Retail Goods"
        }
    ],
    "sg:postcode":"TW8 0NQ",
    "sg:province":"Greater London",
    "sg:tags":[
        "domestic",
        "centre"
    ],
    "wof:name":"Market Refrigeration",
    "wof:placetype":"venue"
},
  "geometry": {"coordinates":[-0.306724,51.484135],"type":"Point"}
}