{
  "type": "Feature",
  "properties": {
    "iso:country":"GB",
    "sg:address":"19 Leicester Road, Blaby",
    "sg:city":"Leicester",
    "sg:classifiers":[
        {
            "category":"Professional",
            "subcategory":"Art Services",
            "type":"Services"
        }
    ],
    "sg:phone":"+44 116 247 7853",
    "sg:postcode":"LE8 4GR",
    "sg:province":"Leicestershire",
    "sg:tags":[
        "framing"
    ],
    "wof:name":"Smiths Picture Framing Gallery",
    "wof:placetype":"venue"
},
  "geometry": {"coordinates":[-1.163086,52.57655],"type":"Point"}
}