{
  "type": "Feature",
  "properties": {
    "iso:country":"GB",
    "sg:address":"Pembroke Avenue, Orton Waterville",
    "sg:city":"Peterborough",
    "sg:classifiers":[
        {
            "category":"Professional",
            "subcategory":"Art Services",
            "type":"Services"
        }
    ],
    "sg:phone":"+44 7973 123515",
    "sg:postcode":"PE2 5EY",
    "sg:province":"Cambridgeshire",
    "sg:tags":[
        "photographer"
    ],
    "wof:name":"Cesare Colangelo",
    "wof:placetype":"venue"
},
  "geometry": {"coordinates":[-0.2967920005,52.5516853333],"type":"Point"}
}