{
  "type": "Feature",
  "properties": {
    "iso:country":"GB",
    "sg:address":"11a Beardmore Street",
    "sg:city":"Clydebank",
    "sg:classifiers":[
        {
            "category":"Retail",
            "subcategory":"Auto Repair",
            "type":"Services"
        }
    ],
    "sg:phone":"+44 141 952 5204",
    "sg:postcode":"G81 4HA",
    "sg:province":"East Dunbartonshire",
    "sg:tags":[
        "engine",
        "car",
        "specialist"
    ],
    "wof:name":"W J & W Mearns",
    "wof:placetype":"venue"
},
  "geometry": {"coordinates":[-4.427347,55.908901],"type":"Point"}
}