{
  "type": "Feature",
  "properties": {
    "iso:country":"GB",
    "sg:address":"High Street, Warboys",
    "sg:city":"Huntingdon",
    "sg:classifiers":[
        {
            "category":"Education",
            "subcategory":"Preschool",
            "type":"Public Place"
        }
    ],
    "sg:phone":"+44 1487 823190",
    "sg:postcode":"PE28 2TA",
    "sg:province":"Bedfordshire",
    "sg:tags":[
        "pre",
        "school",
        "playgroups",
        "pre-school"
    ],
    "wof:name":"Warboys Underfives Playgroup",
    "wof:placetype":"venue"
},
  "geometry": {"coordinates":[-0.074367,52.404549],"type":"Point"}
}