{
  "type": "Feature",
  "properties": {
    "iso:country":"GB",
    "sg:address":"222 Purley Way",
    "sg:city":"Croydon",
    "sg:classifiers":[
        {
            "category":"Home & Garden",
            "subcategory":"Household Appliances",
            "type":"Retail Goods"
        }
    ],
    "sg:phone":"+44 845 600 7002",
    "sg:postcode":"CR0 4XJ",
    "sg:province":"Surrey",
    "sg:tags":[
        "electrical",
        "domestic"
    ],
    "wof:name":"Comet Group Plc",
    "wof:placetype":"venue"
},
  "geometry": {"coordinates":[-0.119881,51.376175],"type":"Point"}
}