{
  "type": "Feature",
  "properties": {
    "addr:full":"P O Box 5 12 Coningsey Rd Peterborough Cambridgeshire PE3 8XP",
    "addr:housenumber":"12",
    "addr:postcode":"pe3 8xp",
    "addr:street":"P O Box 5;Coningsey Rd",
    "iso:country":"GB",
    "sg:address":"P O Box 5 12 Coningsey Rd",
    "sg:city":"Peterborough",
    "sg:classifiers":[
        {
            "category":"Travel",
            "subcategory":"Travel Agent",
            "type":"Entertainment"
        }
    ],
    "sg:phone":"+44 870 605 0506",
    "sg:postcode":"PE3 8XP",
    "sg:province":"Cambridgeshire",
    "wof:name":"American Airline Holidays",
    "wof:placetype":"venue"
},
  "geometry": {"coordinates":[-0.250052,52.572987],"type":"Point"}
}