{
  "type": "Feature",
  "properties": {
    "addr:full":"42 Offerton Road, Hazel Grove Stockport Cheshire SK7 4NL",
    "addr:housenumber":"42",
    "addr:postcode":"sk7 4nl",
    "addr:street":"Offerton Road",
    "iso:country":"GB",
    "sg:address":"42 Offerton Road, Hazel Grove",
    "sg:city":"Stockport",
    "sg:classifiers":[
        {
            "category":"Manufacturing",
            "subcategory":"Glass & Minerals",
            "type":"Manufacturing & Wholesale Goods"
        }
    ],
    "sg:postcode":"SK7 4NL",
    "sg:province":"Cheshire",
    "sg:tags":[
        "stained",
        "designer"
    ],
    "wof:name":"Renaissance Stained Glass Ltd",
    "wof:placetype":"venue"
},
  "geometry": {"coordinates":[-2.1040039062,53.3821487427],"type":"Point"}
}