{
  "type": "Feature",
  "properties": {
    "iso:country":"GB",
    "sg:address":"10 High Street, Upton-upon-severn",
    "sg:city":"Worcester",
    "sg:classifiers":[
        {
            "category":"Shopping",
            "subcategory":"Gifts & Souvenirs",
            "type":"Retail Goods"
        }
    ],
    "sg:phone":"+44 1684 594110",
    "sg:postcode":"WR8 0HB",
    "sg:province":"Gloucestershire",
    "sg:tags":[
        "shop"
    ],
    "wof:name":"Anemone Studio",
    "wof:placetype":"venue"
},
  "geometry": {"coordinates":[-2.217692,52.063763],"type":"Point"}
}