{
  "type": "Feature",
  "properties": {
    "iso:country":"GB",
    "sg:address":"30 Back Madoc St",
    "sg:city":"Llandudno",
    "sg:classifiers":[
        {
            "category":"Real Estate",
            "subcategory":"Real Estate Operator",
            "type":"Services"
        }
    ],
    "sg:phone":"+44 1492 871999",
    "sg:postcode":"LL30 2TE",
    "sg:province":"Conwy",
    "sg:tags":[
        "letting",
        "agent"
    ],
    "wof:name":"Letting Centre (North Wales) The",
    "wof:placetype":"venue"
},
  "geometry": {"coordinates":[-3.8296780586,53.3228912354],"type":"Point"}
}