{
  "type": "Feature",
  "properties": {
    "addr:full":"5 Lancaster House, Horne Way, Putney London Greater London SW15 1JB",
    "addr:housenumber":"5",
    "addr:postcode":"sw15 1jb",
    "addr:street":"Lancaster House Horne Way",
    "iso:country":"GB",
    "sg:address":"5 Lancaster House, Horne Way, Putney",
    "sg:city":"London",
    "sg:classifiers":[
        {
            "category":"Professional",
            "subcategory":"Art Services",
            "type":"Services"
        }
    ],
    "sg:postcode":"SW15 1JB",
    "sg:province":"Greater London",
    "sg:tags":[
        "graphic",
        "designer"
    ],
    "wof:name":"Jane Forshaw Design Services",
    "wof:placetype":"venue"
},
  "geometry": {"coordinates":[-0.2156240046,51.4636535645],"type":"Point"}
}