{
  "type": "Feature",
  "properties": {
    "iso:country":"GB",
    "sg:address":"10 Penshurst Gdn{s}",
    "sg:city":"Edgware",
    "sg:classifiers":[
        {
            "category":"Shopping",
            "subcategory":"Comic Books",
            "type":"Retail Goods"
        }
    ],
    "sg:postcode":"HA8 9TP",
    "sg:province":"Greater London",
    "sg:tags":[
        "jeweller"
    ],
    "wof:name":"Gail Klevan Jewellery",
    "wof:placetype":"venue"
},
  "geometry": {"coordinates":[-0.273770988,51.6155776978],"type":"Point"}
}