{
  "type": "Feature",
  "properties": {
    "iso:country":"GB",
    "sg:address":"6 Nelson Street",
    "sg:city":"Kilmarnock",
    "sg:classifiers":[
        {
            "category":"Personal",
            "subcategory":"Beauty Salon",
            "type":"Services"
        }
    ],
    "sg:phone":"+44 1563 522121",
    "sg:postcode":"KA1 2AA",
    "sg:province":"East Ayrshire",
    "sg:tags":[
        "unisex",
        "hairdresser"
    ],
    "wof:name":"Handling Hair",
    "wof:placetype":"venue"
},
  "geometry": {"coordinates":[-4.500284,55.608807],"type":"Point"}
}