{
  "type": "Feature",
  "properties": {
    "addr:full":"Oldfield Farm, Baulking Faringdon Oxfordshire SN7 8NR",
    "addr:postcode":"sn7 8nr",
    "iso:country":"GB",
    "sg:address":"Oldfield Farm, Baulking",
    "sg:city":"Faringdon",
    "sg:classifiers":[
        {
            "category":"Farming",
            "subcategory":"Livestock Farm",
            "type":"Manufacturing & Wholesale Goods"
        }
    ],
    "sg:postcode":"SN7 8NR",
    "sg:province":"Oxfordshire",
    "sg:tags":[
        "others"
    ],
    "wof:name":"K B Berry",
    "wof:placetype":"venue"
},
  "geometry": {"coordinates":[-1.5866539478,51.6561698914],"type":"Point"}
}