{
  "type": "Feature",
  "properties": {
    "iso:country":"GB",
    "sg:address":"6 St. Swithins St",
    "sg:city":"Worcester",
    "sg:classifiers":[
        {
            "category":"Travel",
            "subcategory":"Travel Agent",
            "type":"Entertainment"
        }
    ],
    "sg:phone":"+44 1905 27533",
    "sg:postcode":"WR1 2PY",
    "sg:province":"Worcestershire",
    "wof:name":"Worldchoice Carlson",
    "wof:placetype":"venue"
},
  "geometry": {"coordinates":[-2.22044,52.192673],"type":"Point"}
}