{
  "type": "Feature",
  "properties": {
    "addr:full":"Somerton Road, Compton Dundon Somerton Somerset TA11 6NY",
    "addr:postcode":"ta11 6ny",
    "addr:street":"Somerton Road",
    "iso:country":"GB",
    "sg:address":"Somerton Road, Compton Dundon",
    "sg:city":"Somerton",
    "sg:classifiers":[
        {
            "category":"Shopping",
            "subcategory":"Pets & Pet Supplies",
            "type":"Retail Goods"
        }
    ],
    "sg:phone":"+44 1458 272463",
    "sg:postcode":"TA11 6NY",
    "sg:province":"Somerset",
    "wof:name":"Tweenways Animal & Bird Farm",
    "wof:placetype":"venue"
},
  "geometry": {"coordinates":[-2.675007,51.059238],"type":"Point"}
}