{
  "type": "Feature",
  "properties": {
    "addr:full":"Cannock Market Hall, Market Hall Street Cannock Staffordshire WS11 1EB",
    "addr:postcode":"ws11 1eb",
    "addr:street":"Hall Street",
    "iso:country":"GB",
    "sg:address":"Cannock Market Hall, Market Hall Street",
    "sg:city":"Cannock",
    "sg:classifiers":[
        {
            "category":"Food & Beverages",
            "subcategory":"Meat & Fish",
            "type":"Retail Goods"
        }
    ],
    "sg:phone":"+44 1543 579951",
    "sg:postcode":"WS11 1EB",
    "sg:province":"Staffordshire",
    "sg:tags":[
        "butcher"
    ],
    "wof:name":"Cannock Butchers",
    "wof:placetype":"venue"
},
  "geometry": {"coordinates":[-2.033145,52.690952],"type":"Point"}
}