{
  "type": "Feature",
  "properties": {
    "iso:country":"GB",
    "sg:address":"20 Old Bailey",
    "sg:city":"St Paul's",
    "sg:classifiers":[
        {
            "category":"Professional",
            "subcategory":"Computer Services",
            "type":"Services"
        }
    ],
    "sg:postcode":"EC4M 7AN",
    "sg:province":"Greater London",
    "sg:tags":[
        "system",
        "software"
    ],
    "wof:name":"Matrixone Ltd",
    "wof:placetype":"venue"
},
  "geometry": {"coordinates":[-0.094041,51.536476],"type":"Point"}
}