{
  "type": "Feature",
  "properties": {
    "iso:country":"GB",
    "sg:address":"91 Holmsauld Rd, Govan",
    "sg:city":"Glasgow",
    "sg:classifiers":[
        {
            "category":"Shopping",
            "subcategory":"Beauty & Cosmetics",
            "type":"Retail Goods"
        }
    ],
    "sg:phone":"+44 141 440 1440",
    "sg:postcode":"G51 4RY",
    "sg:province":"Glasgow City",
    "sg:tags":[
        "product"
    ],
    "wof:name":"McPeak,J,",
    "wof:placetype":"venue"
},
  "geometry": {"coordinates":[-4.33175,55.86647],"type":"Point"}
}