{
  "type": "Feature",
  "properties": {
    "iso:country":"GB",
    "sg:address":"28 South Street",
    "sg:city":"Louth",
    "sg:classifiers":[
        {
            "category":"Health Services",
            "subcategory":"Nursing And Care Facility",
            "type":"Services"
        },
        {
            "category":"Social Services",
            "subcategory":"Retirement Home",
            "type":"Services"
        }
    ],
    "sg:phone":"+44 1507 603862",
    "sg:postcode":"LN11 9JT",
    "sg:province":"Lincolnshire",
    "sg:tags":[
        "residential"
    ],
    "wof:name":"The Beeches Residential Home",
    "wof:placetype":"venue"
},
  "geometry": {"coordinates":[-0.008104,53.363461],"type":"Point"}
}