{
  "type": "Feature",
  "properties": {
    "iso:country":"GB",
    "sg:address":"135 Whitelands Rd",
    "sg:city":"High Wycombe",
    "sg:classifiers":[
        {
            "category":"Building & Trades",
            "subcategory":"Construction",
            "type":"Services"
        }
    ],
    "sg:phone":"+44 1494 529720",
    "sg:postcode":"HP12 3EN",
    "sg:province":"Buckinghamshire",
    "sg:tags":[
        "builder"
    ],
    "wof:name":"M & B Builders",
    "wof:placetype":"venue"
},
  "geometry": {"coordinates":[-0.777481,51.627369],"type":"Point"}
}