{
  "type": "Feature",
  "properties": {
    "addr:full":"Manor Road Ossett West Yorkshire WF5 0AU",
    "addr:postcode":"wf5 0au",
    "addr:street":"Manor Road",
    "iso:country":"GB",
    "sg:address":"Manor Road",
    "sg:city":"Ossett",
    "sg:classifiers":[
        {
            "category":"Bars & Pubs",
            "type":"Food & Drink"
        }
    ],
    "sg:postcode":"WF5 0AU",
    "sg:province":"West Yorkshire",
    "sg:tags":[
        "pubs",
        "inn"
    ],
    "wof:name":"Victoria Hotel",
    "wof:placetype":"venue"
},
  "geometry": {"coordinates":[-1.5557990074,53.6734237671],"type":"Point"}
}