{
  "type": "Feature",
  "properties": {
    "iso:country":"GB",
    "sg:address":"608 Wolseley Road",
    "sg:city":"Plymouth",
    "sg:classifiers":[
        {
            "category":"Fast Food",
            "type":"Food & Drink"
        }
    ],
    "sg:phone":"+44 1752 365424",
    "sg:postcode":"PL5 1TE",
    "sg:province":"Devon",
    "sg:tags":[
        "away",
        "take"
    ],
    "wof:name":"K F C",
    "wof:placetype":"venue"
},
  "geometry": {"coordinates":[-4.185363,50.401508],"type":"Point"}
}