{
  "type": "Feature",
  "properties": {
    "addr:full":"38 Princes Street, California Falkirk Falkirk FK1 2BX",
    "addr:housenumber":"38",
    "addr:postcode":"fk1 2bx",
    "addr:street":"Princes Street",
    "iso:country":"GB",
    "sg:address":"38 Princes Street, California",
    "sg:city":"Falkirk",
    "sg:classifiers":[
        {
            "category":"Home & Garden",
            "subcategory":"Hardware",
            "type":"Retail Goods"
        }
    ],
    "sg:phone":"+44 1324 715878",
    "sg:postcode":"FK1 2BX",
    "sg:province":"Falkirk",
    "sg:tags":[
        "lawnmowers",
        "machinery"
    ],
    "wof:name":"Lawnmower & Saw Services",
    "wof:placetype":"venue"
},
  "geometry": {"coordinates":[-3.748876,55.966148],"type":"Point"}
}