{
  "type": "Feature",
  "properties": {
    "addr:full":"Peter St Yeovil Somerset BA20 1PN",
    "addr:postcode":"ba20 1pn",
    "addr:street":"Peter St",
    "iso:country":"GB",
    "sg:address":"Peter St",
    "sg:city":"Yeovil",
    "sg:classifiers":[
        {
            "category":"Organizations",
            "subcategory":"Professional Association",
            "type":"Services"
        }
    ],
    "sg:phone":"+44 1935 475999",
    "sg:postcode":"BA20 1PN",
    "sg:province":"Somerset",
    "sg:tags":[
        "union",
        "trade"
    ],
    "wof:name":"AEEU",
    "wof:placetype":"venue"
},
  "geometry": {"coordinates":[-2.630709,50.94088],"type":"Point"}
}