{
  "type": "Feature",
  "properties": {
    "addr:full":"251 High St Cowdenbeath Fife KY4 9QF",
    "addr:housenumber":"251",
    "addr:postcode":"ky4 9qf",
    "addr:street":"High St",
    "iso:country":"GB",
    "sg:address":"251 High St",
    "sg:city":"Cowdenbeath",
    "sg:classifiers":[
        {
            "category":"Recreation",
            "subcategory":"Dog Park",
            "type":"Entertainment"
        }
    ],
    "sg:phone":"+44 1383 611811",
    "sg:postcode":"KY4 9QF",
    "sg:province":"Fife",
    "wof:name":"Scrubb-A-Dugg",
    "wof:placetype":"venue"
},
  "geometry": {"coordinates":[-3.343531,56.111301],"type":"Point"}
}