{
  "type": "Feature",
  "properties": {
    "addr:full":"79 Blandford Waye Hayes Greater London UB4 0PB",
    "addr:housenumber":"79;waye",
    "addr:postcode":"ub4 0pb",
    "addr:street":"Blandford",
    "iso:country":"GB",
    "sg:address":"79 Blandford Waye",
    "sg:city":"Hayes",
    "sg:classifiers":[
        {
            "category":"Building & Trades",
            "subcategory":"Construction",
            "type":"Services"
        }
    ],
    "sg:postcode":"UB4 0PB",
    "sg:province":"Greater London",
    "sg:tags":[
        "builder"
    ],
    "wof:name":"Prestige Building Services",
    "wof:placetype":"venue"
},
  "geometry": {"coordinates":[-0.394272,51.518646],"type":"Point"}
}