{
  "type": "Feature",
  "properties": {
    "addr:full":"Ball Lane, Kennington Ashford Kent TN25 4EB",
    "addr:postcode":"tn25 4eb",
    "addr:street":"Ball Lane",
    "iso:country":"GB",
    "sg:address":"Ball Lane, Kennington",
    "sg:city":"Ashford",
    "sg:classifiers":[
        {
            "category":"Arena",
            "subcategory":"Sports Club",
            "type":"Entertainment"
        }
    ],
    "sg:phone":"+44 1233 631315",
    "sg:postcode":"TN25 4EB",
    "sg:province":"Kent",
    "wof:name":"Ashford Hockey & Cricket Club",
    "wof:placetype":"venue"
},
  "geometry": {"coordinates":[0.8917999864,51.1706466675],"type":"Point"}
}