{
  "type": "Feature",
  "properties": {
    "addr:full":"137-139 St Marychurch Road Torquay Devon TQ1 3HW",
    "addr:housenumber":"137-139",
    "addr:postcode":"tq1 3hw",
    "addr:street":"St Marychurch Road",
    "iso:country":"GB",
    "sg:address":"137-139 St Marychurch Road",
    "sg:city":"Torquay",
    "sg:classifiers":[
        {
            "category":"Professional",
            "subcategory":"Business Services",
            "type":"Services"
        }
    ],
    "sg:phone":"+44 1803 322066",
    "sg:postcode":"TQ1 3HW",
    "sg:province":"Devon",
    "sg:tags":[
        "trade"
    ],
    "wof:name":"Federation of Small Businesses",
    "wof:placetype":"venue"
},
  "geometry": {"coordinates":[-3.526832,50.477482],"type":"Point"}
}