{
  "type": "Feature",
  "properties": {
    "addr:full":"19 Oriental Place Brighton East Sussex BN1 2LL",
    "addr:housenumber":"19",
    "addr:postcode":"bn1 2ll",
    "addr:street":"Oriental Place",
    "iso:country":"GB",
    "sg:address":"19 Oriental Place",
    "sg:city":"Brighton",
    "sg:classifiers":[
        {
            "category":"Travel",
            "subcategory":"Hotels & Motels",
            "type":"Entertainment"
        }
    ],
    "sg:postcode":"BN1 2LL",
    "sg:province":"East Sussex",
    "wof:name":"Fredellen Hotel",
    "wof:placetype":"venue"
},
  "geometry": {"coordinates":[-0.153413,50.823318],"type":"Point"}
}