{
  "type": "Feature",
  "properties": {
    "addr:full":"15a Swan Hill Shrewsbury Shropshire SY1 1NL",
    "addr:housenumber":"15a",
    "addr:postcode":"sy1 1nl",
    "addr:street":"Swan",
    "iso:country":"GB",
    "sg:address":"15a Swan Hill",
    "sg:city":"Shrewsbury",
    "sg:classifiers":[
        {
            "category":"Home & Garden",
            "subcategory":"Furniture",
            "type":"Retail Goods"
        }
    ],
    "sg:phone":"+44 1743 354385",
    "sg:postcode":"SY1 1NL",
    "sg:province":"Shropshire",
    "wof:name":"Material Creations",
    "wof:placetype":"venue"
},
  "geometry": {"coordinates":[-2.757114,52.705833],"type":"Point"}
}