{
  "type": "Feature",
  "properties": {
    "addr:full":"25 Lee Crescent Edinburgh City of Edinburgh EH15 1LW",
    "addr:housenumber":"25",
    "addr:postcode":"eh15 1lw",
    "addr:street":"Lee Crescent",
    "iso:country":"GB",
    "sg:address":"25 Lee Crescent",
    "sg:city":"Edinburgh",
    "sg:classifiers":[
        {
            "category":"Arena",
            "subcategory":"Sports Club",
            "type":"Entertainment"
        }
    ],
    "sg:phone":"+44 131 669 0316",
    "sg:postcode":"EH15 1LW",
    "sg:province":"City of Edinburgh",
    "wof:name":"Portobello Outdoor Bowling Club",
    "wof:placetype":"venue"
},
  "geometry": {"coordinates":[-3.1143040657,55.951374054],"type":"Point"}
}