{
  "type": "Feature",
  "properties": {
    "addr:full":"Peacock Ho, Northbridge Rd Berkhamsted Bedfordshire HP4 1EH",
    "addr:postcode":"hp4 1eh",
    "addr:street":"Northbridge Rd",
    "iso:country":"GB",
    "sg:address":"Peacock Ho, Northbridge Rd",
    "sg:city":"Berkhamsted",
    "sg:classifiers":[
        {
            "category":"Freight",
            "type":"Transportation"
        }
    ],
    "sg:postcode":"HP4 1EH",
    "sg:province":"Bedfordshire",
    "sg:tags":[
        "forwarders"
    ],
    "wof:name":"Jukes,James,",
    "wof:placetype":"venue"
},
  "geometry": {"coordinates":[-0.583824,51.770939],"type":"Point"}
}