{
  "type": "Feature",
  "properties": {
    "addr:full":"56 Middleton Grange Shop'g Cent Hartlepool Durham TS24 7RX",
    "addr:housenumber":"56",
    "addr:postcode":"hartlepool;ts24 7rx",
    "addr:street":"Middleton Grange",
    "iso:country":"GB",
    "sg:address":"56 Middleton Grange Shop'g Cent",
    "sg:city":"Hartlepool",
    "sg:classifiers":[
        {
            "category":"Cafe",
            "type":"Food & Drink"
        }
    ],
    "sg:phone":"+44 1429 267286",
    "sg:postcode":"TS24 7RX",
    "sg:province":"Durham",
    "sg:tags":[
        "tea",
        "room"
    ],
    "wof:name":"Kwicksnax 1",
    "wof:placetype":"venue"
},
  "geometry": {"coordinates":[-1.2149699926,54.6840591431],"type":"Point"}
}