{
  "type": "Feature",
  "properties": {
    "iso:country":"GB",
    "sg:address":"16 George St",
    "sg:city":"Harwich",
    "sg:classifiers":[
        {
            "category":"Shopping",
            "subcategory":"Party Supplies",
            "type":"Retail Goods"
        }
    ],
    "sg:phone":"+44 1255 508174",
    "sg:postcode":"CO12 3ND",
    "sg:province":"Essex",
    "sg:tags":[
        "novelty"
    ],
    "wof:name":"Phantasm Fx",
    "wof:placetype":"venue"
},
  "geometry": {"coordinates":[1.28774,51.944607],"type":"Point"}
}