{
  "type": "Feature",
  "properties": {
    "addr:full":"59 St Peters St Bedford Bedfordshire MK40 2PR",
    "addr:housenumber":"59",
    "addr:postcode":"mk40 2pr",
    "addr:street":"St Peters St",
    "iso:country":"GB",
    "sg:address":"59 St Peters St",
    "sg:city":"Bedford",
    "sg:classifiers":[
        {
            "category":"Real Estate",
            "subcategory":"Surveying",
            "type":"Services"
        }
    ],
    "sg:postcode":"MK40 2PR",
    "sg:province":"Bedfordshire",
    "sg:tags":[
        "surveyor",
        "quantity"
    ],
    "wof:name":"Garner Partnership",
    "wof:placetype":"venue"
},
  "geometry": {"coordinates":[-0.462986,52.139286],"type":"Point"}
}