{
  "type": "Feature",
  "properties": {
    "addr:full":"24 Market Place, Cromford Matlock Derbyshire DE4 3QE",
    "addr:housenumber":"24",
    "addr:postcode":"de4 3qe",
    "addr:street":"Market Place",
    "iso:country":"GB",
    "sg:address":"24 Market Place, Cromford",
    "sg:city":"Matlock",
    "sg:classifiers":[
        {
            "category":"Cinema",
            "subcategory":"Movie Rental",
            "type":"Entertainment"
        }
    ],
    "sg:postcode":"DE4 3QE",
    "sg:province":"Derbyshire",
    "sg:tags":[
        "video",
        "library"
    ],
    "wof:name":"Video Nites",
    "wof:placetype":"venue"
},
  "geometry": {"coordinates":[-1.5482740402,53.1356163025],"type":"Point"}
}