{
  "type": "Feature",
  "properties": {
    "addr:full":"Swift Point Rugby Warwickshire CV21 1QH",
    "addr:postcode":"cv21 1qh",
    "addr:street":"Swift Point",
    "iso:country":"GB",
    "sg:address":"Swift Point",
    "sg:city":"Rugby",
    "sg:classifiers":[
        {
            "category":"Home & Garden",
            "subcategory":"Home Furnishings",
            "type":"Retail Goods"
        },
        {
            "category":"Building & Trades",
            "subcategory":"Construction",
            "type":"Services"
        }
    ],
    "sg:phone":"+44 1788 558600",
    "sg:postcode":"CV21 1QH",
    "sg:province":"Warwickshire",
    "sg:tags":[
        "window",
        "door",
        "furniture"
    ],
    "wof:name":"Roto Frank Ltd",
    "wof:placetype":"venue"
},
  "geometry": {"coordinates":[-1.26984,52.398769],"type":"Point"}
}