{
  "type": "Feature",
  "properties": {
    "iso:country":"GB",
    "sg:address":"Woodlands Of Kilravock",
    "sg:city":"Nairn",
    "sg:classifiers":[
        {
            "category":"Farming",
            "subcategory":"Farm",
            "type":"Manufacturing & Wholesale Goods"
        }
    ],
    "sg:postcode":"IV12 5NY",
    "sg:province":"Highland",
    "sg:tags":[
        "mixed",
        "crop"
    ],
    "wof:name":"Donald R Clark",
    "wof:placetype":"venue"
},
  "geometry": {"coordinates":[-3.859407,57.549931],"type":"Point"}
}