{
  "type": "Feature",
  "properties": {
    "iso:country":"GB",
    "sg:address":"Capstone Farm County Park, Capstone Rd",
    "sg:city":"Gillingham",
    "sg:classifiers":[
        {
            "category":"Government",
            "subcategory":"Office",
            "type":"Public Place"
        }
    ],
    "sg:phone":"+44 1634 812196",
    "sg:postcode":"ME7 3JG",
    "sg:province":"Kent",
    "sg:tags":[
        "local"
    ],
    "wof:name":"Medway Council",
    "wof:placetype":"venue"
},
  "geometry": {"coordinates":[0.5710600019,51.3514289856],"type":"Point"}
}