{
  "type": "Feature",
  "properties": {
    "iso:country":"GB",
    "sg:address":"4 Paddockholm North",
    "sg:city":"Kilbirnie",
    "sg:classifiers":[
        {
            "category":"Professional",
            "subcategory":"Art Services",
            "type":"Services"
        }
    ],
    "sg:postcode":"KA25 7DP",
    "sg:province":"North Ayrshire",
    "sg:tags":[
        "graphic",
        "designer"
    ],
    "wof:name":"Ailsa Corporation Ltd",
    "wof:placetype":"venue"
},
  "geometry": {"coordinates":[-4.6794519424,55.7551307678],"type":"Point"}
}