{
  "type": "Feature",
  "properties": {
    "iso:country":"GB",
    "sg:address":"23 Mill Carr Road",
    "sg:city":"Burnley",
    "sg:classifiers":[
        {
            "category":"Military Area",
            "subcategory":"Air Force Base",
            "type":"Public Place"
        }
    ],
    "sg:phone":"+44 1274 674995",
    "sg:postcode":"BB12 7EZ",
    "sg:province":"Lancashire",
    "sg:tags":[
        "taxi",
        "hire",
        "private"
    ],
    "wof:name":"Executive Travel",
    "wof:placetype":"venue"
},
  "geometry": {"coordinates":[-2.311259985,53.79737854],"type":"Point"}
}