{
  "type": "Feature",
  "properties": {
    "addr:full":"12 Kingcup Road Stafford Staffordshire ST17 9JQ",
    "addr:housenumber":"12",
    "addr:postcode":"st17 9jq",
    "addr:street":"Kingcup Road",
    "iso:country":"GB",
    "sg:address":"12 Kingcup Road",
    "sg:city":"Stafford",
    "sg:classifiers":[
        {
            "category":"Organizations",
            "subcategory":"Membership Organization",
            "type":"Services"
        }
    ],
    "sg:postcode":"ST17 9JQ",
    "sg:province":"Staffordshire",
    "sg:tags":[
        "club"
    ],
    "wof:name":"Staffordshire Aviation Heritage Group",
    "wof:placetype":"venue"
},
  "geometry": {"coordinates":[-2.1170630455,52.7785148621],"type":"Point"}
}