{
  "type": "Feature",
  "properties": {
    "addr:full":"Ainsty House, Uppleby, Easingwold York North Yorkshire YO61 3BB",
    "addr:postcode":"yo61 3bb",
    "iso:country":"GB",
    "sg:address":"Ainsty House, Uppleby, Easingwold",
    "sg:city":"York",
    "sg:classifiers":[
        {
            "category":"Banks & Credit Unions",
            "subcategory":"Bureau De Change",
            "type":"Services"
        }
    ],
    "sg:phone":"+44 1347 823853",
    "sg:postcode":"YO61 3BB",
    "sg:province":"North Yorkshire",
    "sg:tags":[
        "town",
        "consultant",
        "planning"
    ],
    "wof:name":"Stuart Copeland Associates",
    "wof:placetype":"venue"
},
  "geometry": {"coordinates":[-1.19231,54.121414],"type":"Point"}
}