{
  "type": "Feature",
  "properties": {
    "iso:country":"GB",
    "sg:address":"Poplar Farm, Skeavingtons Lane",
    "sg:city":"Ilkeston",
    "sg:classifiers":[
        {
            "category":"Farming",
            "subcategory":"Farm",
            "type":"Manufacturing & Wholesale Goods"
        }
    ],
    "sg:phone":"+44 115 932 2438",
    "sg:postcode":"DE7 8SU",
    "sg:province":"Derbyshire",
    "sg:tags":[
        "agricultural"
    ],
    "wof:name":"Pykett G & R",
    "wof:placetype":"venue"
},
  "geometry": {"coordinates":[-1.310189,52.978611],"type":"Point"}
}