{
  "type": "Feature",
  "properties": {
    "iso:country":"GB",
    "sg:address":"Margaret Street",
    "sg:city":"Inverness",
    "sg:classifiers":[
        {
            "category":"Shopping",
            "subcategory":"Pets & Pet Supplies",
            "type":"Retail Goods"
        }
    ],
    "sg:phone":"+44 1463 233593",
    "sg:postcode":"IV1 1LS",
    "sg:province":"Highland",
    "wof:name":"The Pet Shop (Inverness) Ltd.",
    "wof:placetype":"venue"
},
  "geometry": {"coordinates":[-4.2247481346,57.4808273315],"type":"Point"}
}