{
  "type": "Feature",
  "properties": {
    "iso:country":"GB",
    "sg:address":"Deighton Close",
    "sg:city":"Louth",
    "sg:classifiers":[
        {
            "category":"Education",
            "subcategory":"Special Training",
            "type":"Public Place"
        },
        {
            "category":"Government",
            "subcategory":"Office",
            "type":"Public Place"
        }
    ],
    "sg:phone":"+44 1507 605287",
    "sg:postcode":"LN11 0RS",
    "sg:province":"Lincolnshire",
    "sg:tags":[
        "school",
        "local"
    ],
    "wof:name":"Deighton Close School",
    "wof:placetype":"venue"
},
  "geometry": {"coordinates":[-0.0209940001,53.3667373657],"type":"Point"}
}