{
  "type": "Feature",
  "properties": {
    "iso:country":"GB",
    "sg:address":"Elbourne House 31 High Street",
    "sg:city":"Brandon",
    "sg:classifiers":[
        {
            "category":"Professional",
            "subcategory":"Computer Services",
            "type":"Services"
        }
    ],
    "sg:phone":"+44 1842 814955",
    "sg:postcode":"IP27 0AQ",
    "sg:province":"Norfolk",
    "sg:tags":[
        "information"
    ],
    "wof:name":"Brandon Tourist Information Centre",
    "wof:placetype":"venue"
},
  "geometry": {"coordinates":[0.623364985,52.4484481812],"type":"Point"}
}