{
  "type": "Feature",
  "properties": {
    "addr:full":"106 London Road Brighton East Sussex BN1 4JG",
    "addr:housenumber":"106",
    "addr:postcode":"bn1 4jg",
    "addr:street":"London Road",
    "iso:country":"GB",
    "sg:address":"106 London Road",
    "sg:city":"Brighton",
    "sg:classifiers":[
        {
            "category":"Shopping",
            "subcategory":"Clothing, Apparel, & Fashions",
            "type":"Retail Goods"
        }
    ],
    "sg:postcode":"BN1 4JG",
    "sg:province":"East Sussex",
    "sg:tags":[
        "shop"
    ],
    "wof:name":"Out of the Blue",
    "wof:placetype":"venue"
},
  "geometry": {"coordinates":[-0.1363479942,50.8315048218],"type":"Point"}
}