{
  "type": "Feature",
  "properties": {
    "iso:country":"GB",
    "sg:address":"14 Harlow Moor Drive",
    "sg:city":"Harrogate",
    "sg:classifiers":[
        {
            "category":"Travel",
            "subcategory":"Hotels & Motels",
            "type":"Entertainment"
        }
    ],
    "sg:phone":"+44 1423 503059",
    "sg:postcode":"HG2 0JX",
    "sg:province":"North Yorkshire",
    "sg:tags":[
        "house",
        "guest"
    ],
    "wof:name":"Garden House Hotel",
    "wof:placetype":"venue"
},
  "geometry": {"coordinates":[-1.5525909662,53.9885864258],"type":"Point"}
}