{
  "type": "Feature",
  "properties": {
    "iso:country":"GB",
    "sg:address":"125 Meggeson Avenue",
    "sg:city":"Southampton",
    "sg:classifiers":[
        {
            "category":"Personal",
            "subcategory":"Beauty Salon",
            "type":"Services"
        }
    ],
    "sg:phone":"+44 23 8067 1536",
    "sg:postcode":"SO18 2FN",
    "sg:province":"Hampshire",
    "sg:tags":[
        "unisex",
        "hairdresser"
    ],
    "wof:name":"Sheclips",
    "wof:placetype":"venue"
},
  "geometry": {"coordinates":[-1.357413,50.929077],"type":"Point"}
}