{
  "type": "Feature",
  "properties": {
    "addr:full":"Lauriston House, Town Hall Square Grimsby Lincolnshire DN31 1JB",
    "addr:postcode":"dn31 1jb",
    "addr:street":"Hall Square",
    "iso:country":"GB",
    "sg:address":"Lauriston House, Town Hall Square",
    "sg:city":"Grimsby",
    "sg:classifiers":[
        {
            "category":"Professional",
            "subcategory":"Lawyer & Legal Services",
            "type":"Services"
        }
    ],
    "sg:phone":"+44 1472 240251",
    "sg:postcode":"DN31 1JB",
    "sg:province":"Lincolnshire",
    "sg:tags":[
        "solicitor"
    ],
    "wof:name":"Beetenson & Gibbon",
    "wof:placetype":"venue"
},
  "geometry": {"coordinates":[-0.082714,53.565125],"type":"Point"}
}