{
  "type": "Feature",
  "properties": {
    "addr:full":"12 Kibcaps Lee Chapel South Basildon Essex SS16 5SA",
    "addr:housenumber":"12",
    "addr:postcode":"ss16 5sa",
    "addr:street":"Kibcaps Lee;South Basildon",
    "iso:country":"GB",
    "sg:address":"12 Kibcaps Lee Chapel South",
    "sg:city":"Basildon",
    "sg:classifiers":[
        {
            "category":"Health Services",
            "subcategory":"Dentist",
            "type":"Services"
        }
    ],
    "sg:phone":"+44 1268 544838",
    "sg:postcode":"SS16 5SA",
    "sg:province":"Essex",
    "wof:name":"Hodgson Sutton & Goodchild",
    "wof:placetype":"venue"
},
  "geometry": {"coordinates":[0.445462,51.563381],"type":"Point"}
}