{
  "type": "Feature",
  "properties": {
    "addr:full":"66 Lemon Street Truro Cornwall TR1 2PN",
    "addr:housenumber":"66",
    "addr:postcode":"tr1 2pn",
    "addr:street":"Lemon Street",
    "iso:country":"GB",
    "sg:address":"66 Lemon Street",
    "sg:city":"Truro",
    "sg:classifiers":[
        {
            "category":"Travel",
            "subcategory":"Hotels & Motels",
            "type":"Entertainment"
        }
    ],
    "sg:postcode":"TR1 2PN",
    "sg:province":"Cornwall",
    "sg:tags":[
        "house",
        "guest"
    ],
    "wof:name":"Trelin (Cornwall) Limited",
    "wof:placetype":"venue"
},
  "geometry": {"coordinates":[-5.052498,50.261669],"type":"Point"}
}