{
  "type": "Feature",
  "properties": {
    "addr:full":"1 Hackworth Road, North West Industrial Estate Peterlee Durham SR8 2JQ",
    "addr:housenumber":"1",
    "addr:postcode":"sr8 2jq",
    "addr:street":"Hackworth Road North;Industrial Estate",
    "iso:country":"GB",
    "sg:address":"1 Hackworth Road, North West Industrial Estate",
    "sg:city":"Peterlee",
    "sg:classifiers":[
        {
            "category":"Professional",
            "subcategory":"Business Services",
            "type":"Services"
        }
    ],
    "sg:phone":"+44 191 587 0778",
    "sg:postcode":"SR8 2JQ",
    "sg:province":"Durham",
    "sg:tags":[
        "distribution"
    ],
    "wof:name":"Leggett Freightways (North East)",
    "wof:placetype":"venue"
},
  "geometry": {"coordinates":[-1.3658519983,54.773109436],"type":"Point"}
}