{
  "type": "Feature",
  "properties": {
    "addr:full":"Bakewell House, Lamyatt Shepton Mallet Somerset BA4 6NP",
    "addr:postcode":"ba4 6np",
    "addr:street":"Lamyatt",
    "iso:country":"GB",
    "sg:address":"Bakewell House, Lamyatt",
    "sg:city":"Shepton Mallet",
    "sg:classifiers":[
        {
            "category":"Retail",
            "subcategory":"Storage",
            "type":"Services"
        }
    ],
    "sg:postcode":"BA4 6NP",
    "sg:province":"Somerset",
    "sg:tags":[
        "household",
        "removal"
    ],
    "wof:name":"James Removals",
    "wof:placetype":"venue"
},
  "geometry": {"coordinates":[-2.546778,51.189732],"type":"Point"}
}