{
  "type": "Feature",
  "properties": {
    "addr:full":"Demesne Farm Cottage Carlisle Cumbria CA5 6AW",
    "addr:postcode":"ca5 6aw",
    "iso:country":"GB",
    "sg:address":"Demesne Farm Cottage",
    "sg:city":"Carlisle",
    "sg:classifiers":[
        {
            "category":"Home & Garden",
            "subcategory":"Building Materials",
            "type":"Retail Goods"
        },
        {
            "category":"Home & Garden",
            "subcategory":"Furniture",
            "type":"Retail Goods"
        }
    ],
    "sg:phone":"+44 1228 576312",
    "sg:postcode":"CA5 6AW",
    "sg:province":"Cumbria",
    "sg:tags":[
        "installers",
        "planner",
        "built-in",
        "fitted",
        "kitchen"
    ],
    "wof:name":"D Holliday",
    "wof:placetype":"venue"
},
  "geometry": {"coordinates":[-3.0485301018,54.922328949],"type":"Point"}
}