{
  "type": "Feature",
  "properties": {
    "addr:full":"35 Ashfield Way, Limbury Mead Luton Bedfordshire LU3 2UN",
    "addr:housenumber":"35",
    "addr:postcode":"lu3 2un",
    "addr:street":"Ashfield Way Limbury Mead",
    "iso:country":"GB",
    "sg:address":"35 Ashfield Way, Limbury Mead",
    "sg:city":"Luton",
    "sg:classifiers":[
        {
            "category":"Retail",
            "subcategory":"Driving School",
            "type":"Services"
        }
    ],
    "sg:postcode":"LU3 2UN",
    "sg:province":"Bedfordshire",
    "wof:name":"Tyrrell Driving Tuition",
    "wof:placetype":"venue"
},
  "geometry": {"coordinates":[-0.44208,51.91143],"type":"Point"}
}