{
  "type": "Feature",
  "properties": {
    "addr:full":"22 Baker Street Stirling Stirling FK8 1BJ",
    "addr:housenumber":"22",
    "addr:postcode":"fk8 1bj",
    "addr:street":"Baker Street",
    "iso:country":"GB",
    "sg:address":"22 Baker Street",
    "sg:city":"Stirling",
    "sg:classifiers":[
        {
            "category":"Shopping",
            "subcategory":"Pets & Pet Supplies",
            "type":"Retail Goods"
        }
    ],
    "sg:phone":"+44 1786 474688",
    "sg:postcode":"FK8 1BJ",
    "sg:province":"Stirling",
    "wof:name":"Archie's Pet Shop Ltd.",
    "wof:placetype":"venue"
},
  "geometry": {"coordinates":[-3.9388999939,56.1192054749],"type":"Point"}
}