{
  "type": "Feature",
  "properties": {
    "addr:full":"Chelsea Manor Street London Greater London SW3 5PL",
    "addr:postcode":"sw3 5pl",
    "addr:street":"Manor Street",
    "iso:country":"GB",
    "sg:address":"Chelsea Manor Street",
    "sg:city":"London",
    "sg:classifiers":[
        {
            "category":"Community Center",
            "type":"Public Place"
        },
        {
            "category":"Government",
            "subcategory":"Office",
            "type":"Public Place"
        }
    ],
    "sg:phone":"+44 20 7352 6985",
    "sg:postcode":"SW3 5PL",
    "sg:province":"Greater London",
    "sg:tags":[
        "recreation",
        "local",
        "leisure",
        "centre"
    ],
    "wof:name":"Chelsea Sports Centre",
    "wof:placetype":"venue"
},
  "geometry": {"coordinates":[-0.166669,51.48613],"type":"Point"}
}