{
  "type": "Feature",
  "properties": {
    "addr:full":"19 Nicholls St Coventry Warwickshire CV2 4GY",
    "addr:housenumber":"19",
    "addr:postcode":"cv2 4gy",
    "addr:street":"Nicholls St",
    "iso:country":"GB",
    "sg:address":"19 Nicholls St",
    "sg:city":"Coventry",
    "sg:classifiers":[
        {
            "category":"Food & Beverages",
            "subcategory":"Liquor & Beverages",
            "type":"Retail Goods"
        }
    ],
    "sg:phone":"+44 24 7622 9654",
    "sg:postcode":"CV2 4GY",
    "sg:province":"Warwickshire",
    "sg:tags":[
        "beer",
        "spirit",
        "wines"
    ],
    "wof:name":"Rogers Stores",
    "wof:placetype":"venue"
},
  "geometry": {"coordinates":[-1.491833,52.412395],"type":"Point"}
}