{
  "type": "Feature",
  "properties": {
    "addr:full":"4 Broomlands Street Paisley Renfrewshire PA1 2LR",
    "addr:housenumber":"4",
    "addr:postcode":"pa1 2lr",
    "addr:street":"Broomlands Street",
    "iso:country":"GB",
    "sg:address":"4 Broomlands Street",
    "sg:city":"Paisley",
    "sg:classifiers":[
        {
            "category":"Cafe",
            "type":"Food & Drink"
        }
    ],
    "sg:postcode":"PA1 2LR",
    "sg:province":"Renfrewshire",
    "sg:tags":[
        "tea",
        "room"
    ],
    "wof:name":"Buttercup",
    "wof:placetype":"venue"
},
  "geometry": {"coordinates":[-4.437848,55.844246],"type":"Point"}
}