{
  "type": "Feature",
  "properties": {
    "addr:full":"39 Derby Rd Hinckley Leicestershire LE10 1QD",
    "addr:housenumber":"39",
    "addr:postcode":"le10 1qd",
    "addr:street":"Derby Rd",
    "iso:country":"GB",
    "sg:address":"39 Derby Rd",
    "sg:city":"Hinckley",
    "sg:classifiers":[
        {
            "category":"Retail",
            "subcategory":"Auto Rental",
            "type":"Services"
        }
    ],
    "sg:phone":"+44 1455 633375",
    "sg:postcode":"LE10 1QD",
    "sg:province":"Leicestershire",
    "sg:tags":[
        "car"
    ],
    "wof:name":"Arriva Vauxhall Rental",
    "wof:placetype":"venue"
},
  "geometry": {"coordinates":[-1.368301034,52.5451126099],"type":"Point"}
}