{
  "type": "Feature",
  "properties": {
    "addr:full":"100 Hatton Garden Clerkenwell Greater London EC1N 8NX",
    "addr:housenumber":"100",
    "addr:postcode":"ec1n 8nx",
    "addr:street":"Hatton Garden",
    "iso:country":"GB",
    "sg:address":"100 Hatton Garden",
    "sg:city":"Clerkenwell",
    "sg:classifiers":[
        {
            "category":"Manufacturing",
            "subcategory":"Jewelry",
            "type":"Manufacturing & Wholesale Goods"
        }
    ],
    "sg:phone":"+44 20 7430 9090",
    "sg:postcode":"EC1N 8NX",
    "sg:province":"Greater London",
    "sg:tags":[
        "repair",
        "jewellery"
    ],
    "wof:name":"Accoutrements",
    "wof:placetype":"venue"
},
  "geometry": {"coordinates":[-0.108078,51.518517],"type":"Point"}
}