{
  "type": "Feature",
  "properties": {
    "iso:country":"GB",
    "sg:address":"18 Bath Road, Bitton",
    "sg:city":"Bristol",
    "sg:classifiers":[
        {
            "category":"Autos & Motor Vehicles",
            "subcategory":"Auto Supplies",
            "type":"Retail Goods"
        }
    ],
    "sg:phone":"+44 117 932 9329",
    "sg:postcode":"BS30 6HZ",
    "sg:province":"Gloucestershire",
    "sg:tags":[
        "rubber",
        "tyre"
    ],
    "wof:name":"Unity Tyre Co. Ltd.",
    "wof:placetype":"venue"
},
  "geometry": {"coordinates":[-2.4744460583,51.4296646118],"type":"Point"}
}