{
  "type": "Feature",
  "properties": {
    "addr:full":"Atlantic Square, 2 Station Road Witham Essex CM8 2TL",
    "addr:housenumber":"2",
    "addr:postcode":"cm8 2tl",
    "addr:street":"Station Road",
    "iso:country":"GB",
    "sg:address":"Atlantic Square, 2 Station Road",
    "sg:city":"Witham",
    "sg:classifiers":[
        {
            "category":"Wholesale",
            "subcategory":"Metals & Minerals",
            "type":"Manufacturing & Wholesale Goods"
        },
        {
            "category":"Arena",
            "subcategory":"Bull Ring",
            "type":"Entertainment"
        }
    ],
    "sg:phone":"+44 1376 502064",
    "sg:postcode":"CM8 2TL",
    "sg:province":"Essex",
    "sg:tags":[
        "mnfrs",
        "copper",
        "aluminium",
        "brass",
        "stockholder"
    ],
    "wof:name":"M G Non-Ferrous Products Ltd.",
    "wof:placetype":"venue"
},
  "geometry": {"coordinates":[0.6399909854,51.8007125854],"type":"Point"}
}