{
  "type": "Feature",
  "properties": {
    "iso:country":"GB",
    "sg:address":"2 Fulford Road",
    "sg:city":"Caterham",
    "sg:classifiers":[
        {
            "category":"Personal",
            "type":"Services"
        }
    ],
    "sg:phone":"+44 20 8661 0226",
    "sg:postcode":"CR3 5SQ",
    "sg:province":"Surrey",
    "sg:tags":[
        "wedding"
    ],
    "wof:name":"Topped & Tailed Ltd.",
    "wof:placetype":"venue"
},
  "geometry": {"coordinates":[-0.094002,51.294331],"type":"Point"}
}