{
  "type": "Feature",
  "properties": {
    "iso:country":"GB",
    "sg:address":"Circuit House, St Clement Street",
    "sg:city":"Truro",
    "sg:classifiers":[
        {
            "category":"Education",
            "subcategory":"Special Training",
            "type":"Public Place"
        }
    ],
    "sg:phone":"+44 1872 223366",
    "sg:postcode":"TR1 1DT",
    "sg:province":"Cornwall",
    "sg:tags":[
        "product",
        "centre"
    ],
    "wof:name":"Joblink Training",
    "wof:placetype":"venue"
},
  "geometry": {"coordinates":[-5.0497488976,50.2647743225],"type":"Point"}
}