{
  "type": "Feature",
  "properties": {
    "addr:full":"Church Farm Barn, Cranworth Thetford Norfolk IP25 7SH",
    "addr:postcode":"ip25 7sh",
    "addr:street":"Cranworth",
    "iso:country":"GB",
    "sg:address":"Church Farm Barn, Cranworth",
    "sg:city":"Thetford",
    "sg:classifiers":[
        {
            "category":"Professional",
            "subcategory":"Management & Consulting",
            "type":"Services"
        }
    ],
    "sg:phone":"+44 1362 821599",
    "sg:postcode":"IP25 7SH",
    "sg:province":"Norfolk",
    "sg:tags":[
        "consultant",
        "business"
    ],
    "wof:name":"Just A Thought Ltd.",
    "wof:placetype":"venue"
},
  "geometry": {"coordinates":[0.925341,52.604782],"type":"Point"}
}