{
  "type": "Feature",
  "properties": {
    "addr:full":"35 Broadbank Louth Lincolnshire LN11 0EN",
    "addr:housenumber":"35",
    "addr:postcode":"ln11 0en",
    "addr:street":"Broadbank Louth",
    "iso:country":"GB",
    "sg:address":"35 Broadbank",
    "sg:city":"Louth",
    "sg:classifiers":[
        {
            "category":"Building & Trades",
            "subcategory":"Construction",
            "type":"Services"
        }
    ],
    "sg:phone":"+44 1507 604559",
    "sg:postcode":"LN11 0EN",
    "sg:province":"Lincolnshire",
    "sg:tags":[
        "glazier",
        "decorator",
        "painter"
    ],
    "wof:name":"Christopher Moncaster",
    "wof:placetype":"venue"
},
  "geometry": {"coordinates":[-0.0069360002,53.3690414429],"type":"Point"}
}