{
  "type": "Feature",
  "properties": {
    "addr:full":"124 Whitechapel Road London Greater London E1 1JE",
    "addr:housenumber":"124",
    "addr:postcode":"e1 1je",
    "addr:street":"Whitechapel Road",
    "iso:country":"GB",
    "sg:address":"124 Whitechapel Road",
    "sg:city":"London",
    "sg:classifiers":[
        {
            "category":"Shopping",
            "subcategory":"Clothing, Apparel, & Fashions",
            "type":"Retail Goods"
        }
    ],
    "sg:phone":"+44 20 7377 6803",
    "sg:postcode":"E1 1JE",
    "sg:province":"Greater London",
    "sg:tags":[
        "clothing"
    ],
    "wof:name":"Adam Sinclair Ltd.",
    "wof:placetype":"venue"
},
  "geometry": {"coordinates":[-0.063634,51.518101],"type":"Point"}
}