{
  "type": "Feature",
  "properties": {
    "addr:full":"Horderns Road, Chapel En Le Frith High Peak Cheshire SK23 9TB",
    "addr:postcode":"sk23 9tb",
    "addr:street":"Horderns Road",
    "iso:country":"GB",
    "sg:address":"Horderns Road, Chapel En Le Frith",
    "sg:city":"High Peak",
    "sg:classifiers":[
        {
            "category":"Building & Trades",
            "subcategory":"Construction",
            "type":"Services"
        }
    ],
    "sg:phone":"+44 1298 812877",
    "sg:postcode":"SK23 9TB",
    "sg:province":"Cheshire",
    "sg:tags":[
        "builder"
    ],
    "wof:name":"T D K Construction",
    "wof:placetype":"venue"
},
  "geometry": {"coordinates":[-1.9190770388,53.3217353821],"type":"Point"}
}