{
  "type": "Feature",
  "properties": {
    "addr:full":"17 West Shepton Shepton Mallet Somerset BA4 5UJ",
    "addr:housenumber":"17",
    "addr:postcode":"ba4 5uj",
    "addr:street":"West",
    "iso:country":"GB",
    "sg:address":"17 West Shepton",
    "sg:city":"Shepton Mallet",
    "sg:classifiers":[
        {
            "category":"Building & Trades",
            "subcategory":"Landscaping Services",
            "type":"Services"
        }
    ],
    "sg:phone":"+44 1749 345020",
    "sg:postcode":"BA4 5UJ",
    "sg:province":"Somerset",
    "sg:tags":[
        "gardening"
    ],
    "wof:name":"C B H Landscaping Services",
    "wof:placetype":"venue"
},
  "geometry": {"coordinates":[-2.547888,51.188213],"type":"Point"}
}