{
  "type": "Feature",
  "properties": {
    "addr:full":"179 Castelnau, Barnes London Greater London SW13 9ER",
    "addr:housenumber":"179",
    "addr:postcode":"sw13 9er",
    "addr:street":"Castelnau Barnes",
    "iso:country":"GB",
    "sg:address":"179 Castelnau, Barnes",
    "sg:city":"London",
    "sg:classifiers":[
        {
            "category":"Building & Trades",
            "subcategory":"Plumbing",
            "type":"Services"
        }
    ],
    "sg:phone":"+44 20 8748 8523",
    "sg:postcode":"SW13 9ER",
    "sg:province":"Greater London",
    "sg:tags":[
        "heating"
    ],
    "wof:name":"B & K O'Dwyer",
    "wof:placetype":"venue"
},
  "geometry": {"coordinates":[-0.2337940037,51.4851531982],"type":"Point"}
}