{
  "type": "Feature",
  "properties": {
    "iso:country":"GB",
    "sg:address":"Bodelwyddan Service Station, Abergele Rd, Bodelwyddan",
    "sg:city":"Rhyl",
    "sg:classifiers":[
        {
            "category":"Shopping",
            "subcategory":"Pharmacy",
            "type":"Retail Goods"
        }
    ],
    "sg:phone":"+44 1745 583862",
    "sg:postcode":"LL18 5SS",
    "sg:province":"Conwy",
    "sg:tags":[
        "pharmacist",
        "chemist"
    ],
    "wof:name":"Halls Chemists",
    "wof:placetype":"venue"
},
  "geometry": {"coordinates":[-3.5047390461,53.2685852051],"type":"Point"}
}