{
  "type": "Feature",
  "properties": {
    "addr:full":"21 Bath Road, Bawdrip Bridgwater Somerset TA7 8PG",
    "addr:housenumber":"21",
    "addr:postcode":"ta7 8pg",
    "addr:street":"Bath Road",
    "iso:country":"GB",
    "sg:address":"21 Bath Road, Bawdrip",
    "sg:city":"Bridgwater",
    "sg:classifiers":[
        {
            "category":"Shopping",
            "subcategory":"Department Store",
            "type":"Retail Goods"
        }
    ],
    "sg:postcode":"TA7 8PG",
    "sg:province":"Somerset",
    "wof:name":"Ashcott Stores",
    "wof:placetype":"venue"
},
  "geometry": {"coordinates":[-2.967694,51.147217],"type":"Point"}
}