{
  "type": "Feature",
  "properties": {
    "addr:full":"2 Felthambrook Way Feltham Greater London TW13 7DU",
    "addr:housenumber":"2",
    "addr:postcode":"tw13 7du",
    "addr:street":"Felthambrook Way",
    "iso:country":"GB",
    "sg:address":"2 Felthambrook Way",
    "sg:city":"Feltham",
    "sg:classifiers":[
        {
            "category":"Professional",
            "subcategory":"Printing & Photocopies",
            "type":"Services"
        }
    ],
    "sg:phone":"+44 20 8751 4341",
    "sg:postcode":"TW13 7DU",
    "sg:province":"Greater London",
    "sg:tags":[
        "printer"
    ],
    "wof:name":"Chromocraft Ltd.",
    "wof:placetype":"venue"
},
  "geometry": {"coordinates":[-0.404624,51.438923],"type":"Point"}
}