{
  "type": "Feature",
  "properties": {
    "addr:full":"249 High Street, Cippenham Slough Berkshire SL1 1BN",
    "addr:housenumber":"249",
    "addr:postcode":"sl1 1bn",
    "addr:street":"High Street",
    "iso:country":"GB",
    "sg:address":"249 High Street, Cippenham",
    "sg:city":"Slough",
    "sg:classifiers":[
        {
            "category":"Organizations",
            "subcategory":"Membership Organization",
            "type":"Services"
        }
    ],
    "sg:postcode":"SL1 1BN",
    "sg:province":"Berkshire",
    "sg:tags":[
        "club"
    ],
    "wof:name":"J Isaacs Management Ltd.",
    "wof:placetype":"venue"
},
  "geometry": {"coordinates":[-0.5880929828,51.5078201294],"type":"Point"}
}