{
  "type": "Feature",
  "properties": {
    "iso:country":"GB",
    "sg:address":"54 Barrington Road",
    "sg:city":"Sutton",
    "sg:classifiers":[
        {
            "category":"Retail",
            "subcategory":"Laundry & Dry Cleaning",
            "type":"Services"
        }
    ],
    "sg:postcode":"SM3 9PR",
    "sg:province":"Surrey",
    "sg:tags":[
        "home",
        "ironing"
    ],
    "wof:name":"Barbara's Ironing Services",
    "wof:placetype":"venue"
},
  "geometry": {"coordinates":[-0.204539001,51.3796577454],"type":"Point"}
}