{
  "type": "Feature",
  "properties": {
    "addr:full":"24 Marygate York North Yorkshire YO30 7BH",
    "addr:housenumber":"24",
    "addr:postcode":"yo30 7bh",
    "addr:street":"Marygate York",
    "iso:country":"GB",
    "sg:address":"24 Marygate",
    "sg:city":"York",
    "sg:classifiers":[
        {
            "category":"Bars & Pubs",
            "type":"Food & Drink"
        },
        {
            "category":"Community Center",
            "subcategory":"Social",
            "type":"Public Place"
        }
    ],
    "sg:phone":"+44 1904 624499",
    "sg:postcode":"YO30 7BH",
    "sg:province":"North Yorkshire",
    "sg:tags":[
        "pubs",
        "house",
        "inn",
        "activity"
    ],
    "wof:name":"Minster Inn",
    "wof:placetype":"venue"
},
  "geometry": {"coordinates":[-1.0885100365,53.9630889893],"type":"Point"}
}