{
  "type": "Feature",
  "properties": {
    "iso:country":"GB",
    "sg:address":"Winchfield Lodge, Old Potbridge Rd, Winchfield",
    "sg:city":"Hook",
    "sg:classifiers":[
        {
            "category":"Organizations",
            "subcategory":"Community Association",
            "type":"Services"
        }
    ],
    "sg:phone":"+44 1252 844614",
    "sg:postcode":"RG27 8BT",
    "sg:province":"Berkshire",
    "sg:tags":[
        "relation",
        "public"
    ],
    "wof:name":"Publicity Direct",
    "wof:placetype":"venue"
},
  "geometry": {"coordinates":[-0.9097869992,51.2849197388],"type":"Point"}
}