{
  "type": "Feature",
  "properties": {
    "addr:full":"135 High St Gravesend Kent DA11 9EZ",
    "addr:housenumber":"135",
    "addr:postcode":"da11 9ez",
    "addr:street":"High St",
    "iso:country":"GB",
    "sg:address":"135 High St",
    "sg:city":"Gravesend",
    "sg:classifiers":[
        {
            "category":"Autos & Motor Vehicles",
            "subcategory":"Automobile Sales",
            "type":"Retail Goods"
        }
    ],
    "sg:postcode":"DA11 9EZ",
    "sg:province":"Kent",
    "sg:tags":[
        "car"
    ],
    "wof:name":"Lh Auto Service",
    "wof:placetype":"venue"
},
  "geometry": {"coordinates":[0.327261,51.445843],"type":"Point"}
}