{
  "type": "Feature",
  "properties": {
    "addr:full":", Dunkeswell Honiton Devon EX14 0RE",
    "addr:housenumber":"dunkeswell",
    "addr:postcode":"ex14 0re",
    "iso:country":"GB",
    "sg:address":", Dunkeswell",
    "sg:city":"Honiton",
    "sg:classifiers":[
        {
            "category":"Bars & Pubs",
            "type":"Food & Drink"
        }
    ],
    "sg:phone":"+44 1404 891683",
    "sg:postcode":"EX14 0RE",
    "sg:province":"Devon",
    "sg:tags":[
        "pubs",
        "inn"
    ],
    "wof:name":"Royal Oak Inn",
    "wof:placetype":"venue"
},
  "geometry": {"coordinates":[-3.1969060898,50.7973861694],"type":"Point"}
}