{
  "type": "Feature",
  "properties": {
    "iso:country":"GB",
    "sg:address":"The Maltings, Croxton",
    "sg:city":"Stafford",
    "sg:classifiers":[
        {
            "category":"Transit Center",
            "subcategory":"Passenger",
            "type":"Transportation"
        }
    ],
    "sg:postcode":"ST21 6PE",
    "sg:province":"Staffordshire",
    "sg:tags":[
        "boarding",
        "kennel",
        "catteries"
    ],
    "wof:name":"Croxton Cattery",
    "wof:placetype":"venue"
},
  "geometry": {"coordinates":[-2.317239,52.886417],"type":"Point"}
}