{
  "type": "Feature",
  "properties": {
    "iso:country":"GB",
    "sg:address":"31 Townsend St",
    "sg:city":"Glasgow",
    "sg:classifiers":[
        {
            "category":"Sports & Exercise",
            "subcategory":"Golf",
            "type":"Entertainment"
        }
    ],
    "sg:phone":"+44 141 332 3959",
    "sg:postcode":"G4 0LA",
    "sg:province":"Glasgow City",
    "sg:tags":[
        "equipment"
    ],
    "wof:name":"Regal Golf",
    "wof:placetype":"venue"
},
  "geometry": {"coordinates":[-4.250837,55.87141],"type":"Point"}
}