{
  "type": "Feature",
  "properties": {
    "addr:full":"24 Hockerill Court, London Road Bishops Stortford Essex CM23 5SB",
    "addr:housenumber":"24",
    "addr:postcode":"cm23 5sb",
    "addr:street":"Hockerill Court London Road",
    "iso:country":"GB",
    "sg:address":"24 Hockerill Court, London Road",
    "sg:city":"Bishops Stortford",
    "sg:classifiers":[
        {
            "category":"Professional",
            "subcategory":"Business Services",
            "type":"Services"
        }
    ],
    "sg:phone":"+44 1279 501711",
    "sg:postcode":"CM23 5SB",
    "sg:province":"Essex",
    "sg:tags":[
        "food",
        "import",
        "export",
        "agent"
    ],
    "wof:name":"Porter Foods Co. Ltd.",
    "wof:placetype":"venue"
},
  "geometry": {"coordinates":[0.1619559973,51.8723564148],"type":"Point"}
}