{
  "type": "Feature",
  "properties": {
    "addr:full":"18 The Arcade Bedford Bedfordshire MK40 1NS",
    "addr:housenumber":"18",
    "addr:postcode":"mk40 1ns",
    "addr:street":"The Arcade",
    "iso:country":"GB",
    "sg:address":"18 The Arcade",
    "sg:city":"Bedford",
    "sg:classifiers":[
        {
            "category":"Shopping",
            "subcategory":"Music",
            "type":"Retail Goods"
        }
    ],
    "sg:phone":"+44 1234 215336",
    "sg:postcode":"MK40 1NS",
    "sg:province":"Bedfordshire",
    "sg:tags":[
        "record",
        "tape",
        "cd"
    ],
    "wof:name":"Planet of Sound",
    "wof:placetype":"venue"
},
  "geometry": {"coordinates":[-0.47792,52.137737],"type":"Point"}
}