{
  "type": "Feature",
  "properties": {
    "addr:full":"Chesterfield Shopping Court, Stallings Lane, Kingswinford Brierley Hill Staffordshire DY6 7SH",
    "addr:postcode":"dy6 7sh",
    "addr:street":"Stallings Lane",
    "iso:country":"GB",
    "sg:address":"Chesterfield Shopping Court, Stallings Lane, Kingswinford",
    "sg:city":"Brierley Hill",
    "sg:classifiers":[
        {
            "category":"Autos & Motor Vehicles",
            "subcategory":"Fuel & Gas Station",
            "type":"Retail Goods"
        },
        {
            "category":"Food & Beverages",
            "subcategory":"Supermarket",
            "type":"Retail Goods"
        }
    ],
    "sg:phone":"+44 1384 401611",
    "sg:postcode":"DY6 7SH",
    "sg:province":"Staffordshire",
    "sg:tags":[
        "petrol",
        "filling"
    ],
    "wof:name":"Safeway Petrol Station",
    "wof:placetype":"venue"
},
  "geometry": {"coordinates":[-2.1651349068,52.5058441162],"type":"Point"}
}