{
  "type": "Feature",
  "properties": {
    "addr:full":"Churt Farnham Hampshire GU10 2PG",
    "addr:postcode":"gu10 2pg",
    "iso:country":"GB",
    "sg:address":"Churt",
    "sg:city":"Farnham",
    "sg:classifiers":[
        {
            "category":"Social Services",
            "subcategory":"Adult Care",
            "type":"Services"
        },
        {
            "category":"Government",
            "subcategory":"Office",
            "type":"Public Place"
        }
    ],
    "sg:phone":"+44 1428 714118",
    "sg:postcode":"GU10 2PG",
    "sg:province":"Hampshire",
    "sg:tags":[
        "housing",
        "local",
        "sheltered"
    ],
    "wof:name":"Parkhurst Fields",
    "wof:placetype":"venue"
},
  "geometry": {"coordinates":[-0.7761099935,51.1359710693],"type":"Point"}
}