{
  "type": "Feature",
  "properties": {
    "addr:full":"16 Manor Gro London Greater London SE15 1SX",
    "addr:housenumber":"16",
    "addr:postcode":"se15 1sx",
    "addr:street":"Manor Gro",
    "iso:country":"GB",
    "sg:address":"16 Manor Gro",
    "sg:city":"London",
    "sg:classifiers":[
        {
            "category":"Professional",
            "subcategory":"Printing & Photocopies",
            "type":"Services"
        }
    ],
    "sg:phone":"+44 20 7732 3339",
    "sg:postcode":"SE15 1SX",
    "sg:province":"Greater London",
    "sg:tags":[
        "printer"
    ],
    "wof:name":"Moorgate Graphics",
    "wof:placetype":"venue"
},
  "geometry": {"coordinates":[-0.05401,51.481632],"type":"Point"}
}