{
  "type": "Feature",
  "properties": {
    "addr:full":"1 St.john's Centre Perth Perth and Kinross PH1 5UX",
    "addr:housenumber":"1",
    "addr:postcode":"ph1 5ux",
    "addr:street":"St.John'S Centre",
    "iso:country":"GB",
    "sg:address":"1 St.john's Centre",
    "sg:city":"Perth",
    "sg:classifiers":[
        {
            "category":"Shopping",
            "subcategory":"Clothing, Apparel, & Fashions",
            "type":"Retail Goods"
        }
    ],
    "sg:phone":"+44 1738 630501",
    "sg:postcode":"PH1 5UX",
    "sg:province":"Perth and Kinross",
    "sg:tags":[
        "wear",
        "leisure"
    ],
    "wof:name":"Actionwear",
    "wof:placetype":"venue"
},
  "geometry": {"coordinates":[-3.4272310734,56.396194458],"type":"Point"}
}