{
  "type": "Feature",
  "properties": {
    "iso:country":"GB",
    "sg:address":"Hoe Place, Old Woking Road",
    "sg:city":"Woking",
    "sg:classifiers":[
        {
            "category":"Education",
            "subcategory":"School",
            "type":"Public Place"
        }
    ],
    "sg:phone":"+44 1483 760065",
    "sg:postcode":"GU22 8JE",
    "sg:province":"Surrey",
    "sg:tags":[
        "independent",
        "preparatory"
    ],
    "wof:name":"The Hoe Bridge Pre-Preparatory School",
    "wof:placetype":"venue"
},
  "geometry": {"coordinates":[-0.54029,51.305408],"type":"Point"}
}