{
  "type": "Feature",
  "properties": {
    "addr:full":"224 Warwick Rd Solihull West Midlands B92 7AE",
    "addr:housenumber":"224",
    "addr:postcode":"b92 7ae",
    "addr:street":"Warwick Rd",
    "iso:country":"GB",
    "sg:address":"224 Warwick Rd",
    "sg:city":"Solihull",
    "sg:classifiers":[
        {
            "category":"Shopping",
            "subcategory":"Hobbies, Toys, & Games",
            "type":"Retail Goods"
        }
    ],
    "sg:phone":"+44 121 706 1435",
    "sg:postcode":"B92 7AE",
    "sg:province":"West Midlands",
    "sg:tags":[
        "gunsmith"
    ],
    "wof:name":"City Air Weapons & Firearms",
    "wof:placetype":"venue"
},
  "geometry": {"coordinates":[-1.800573,52.433231],"type":"Point"}
}