{
  "type": "Feature",
  "properties": {
    "addr:full":"Pinfold Lane Bridlington East Riding of Yorkshire YO16 6XP",
    "addr:postcode":"yo16 6xp",
    "addr:street":"Pinfold Lane",
    "iso:country":"GB",
    "sg:address":"Pinfold Lane",
    "sg:city":"Bridlington",
    "sg:classifiers":[
        {
            "category":"Wholesale",
            "subcategory":"Construction Materials",
            "type":"Manufacturing & Wholesale Goods"
        },
        {
            "category":"Home & Garden",
            "subcategory":"Building Materials",
            "type":"Retail Goods"
        }
    ],
    "sg:phone":"+44 1262 674431",
    "sg:postcode":"YO16 6XP",
    "sg:province":"East Riding of Yorkshire",
    "sg:tags":[
        "ready",
        "mixed",
        "mortar",
        "concrete"
    ],
    "wof:name":"Hanson Premix plc",
    "wof:placetype":"venue"
},
  "geometry": {"coordinates":[-0.209971,54.115498],"type":"Point"}
}