{
  "type": "Feature",
  "properties": {
    "iso:country":"GB",
    "sg:address":"Michell Centre For Art And Craft, Weeford Road",
    "sg:city":"Sutton Coldfield",
    "sg:classifiers":[
        {
            "category":"Transit Center",
            "subcategory":"Freight",
            "type":"Transportation"
        }
    ],
    "sg:phone":"+44 121 323 3776",
    "sg:postcode":"B75 6NA",
    "sg:province":"Staffordshire",
    "sg:tags":[
        "shop",
        "craft",
        "centre"
    ],
    "wof:name":"Artifex Galleries Ltd.",
    "wof:placetype":"venue"
},
  "geometry": {"coordinates":[-1.80677,52.58429],"type":"Point"}
}