{
  "type": "Feature",
  "properties": {
    "addr:full":"10 Garnockside, Glengarnock Beith North Ayrshire KA14 3AB",
    "addr:housenumber":"10",
    "addr:postcode":"ka14 3ab",
    "addr:street":"Garnockside Glengarnock Beith",
    "iso:country":"GB",
    "sg:address":"10 Garnockside, Glengarnock",
    "sg:city":"Beith",
    "sg:classifiers":[
        {
            "category":"Arts & Performance",
            "subcategory":"Arts Center",
            "type":"Entertainment"
        }
    ],
    "sg:phone":"+44 1505 684225",
    "sg:postcode":"KA14 3AB",
    "sg:province":"North Ayrshire",
    "sg:tags":[
        "centre"
    ],
    "wof:name":"Garnock Valley Arts Resource Centre",
    "wof:placetype":"venue"
},
  "geometry": {"coordinates":[-4.673822,55.74102],"type":"Point"}
}