{
  "type": "Feature",
  "properties": {
    "addr:full":"49 Belsize Avenue, Springfield Milton Keynes Buckinghamshire MK6 3LN",
    "addr:housenumber":"49",
    "addr:postcode":"mk6 3ln",
    "addr:street":"Belsize Avenue Springfield",
    "iso:country":"GB",
    "sg:address":"49 Belsize Avenue, Springfield",
    "sg:city":"Milton Keynes",
    "sg:classifiers":[
        {
            "category":"Professional",
            "subcategory":"Art Services",
            "type":"Services"
        },
        {
            "category":"Building & Trades",
            "subcategory":"Construction",
            "type":"Services"
        }
    ],
    "sg:phone":"+44 1908 672783",
    "sg:postcode":"MK6 3LN",
    "sg:province":"Buckinghamshire",
    "sg:tags":[
        "carver",
        "joiner",
        "carpenter",
        "sculptor"
    ],
    "wof:name":"J B Thomas Contractors",
    "wof:placetype":"venue"
},
  "geometry": {"coordinates":[-0.7342270017,52.0378684998],"type":"Point"}
}