{
  "type": "Feature",
  "properties": {
    "addr:full":"Cedar Lodge, Harlow Road, Moreton Ongar Essex CM5 0LH",
    "addr:postcode":"cm5 0lh",
    "addr:street":"Harlow Road",
    "iso:country":"GB",
    "sg:address":"Cedar Lodge, Harlow Road, Moreton",
    "sg:city":"Ongar",
    "sg:classifiers":[
        {
            "category":"Retail",
            "subcategory":"Auto Repair",
            "type":"Services"
        }
    ],
    "sg:postcode":"CM5 0LH",
    "sg:province":"Essex",
    "sg:tags":[
        "modification",
        "garage"
    ],
    "wof:name":"Rod Foster Vehicle Repairs",
    "wof:placetype":"venue"
},
  "geometry": {"coordinates":[0.21946,51.740643],"type":"Point"}
}