{
  "type": "Feature",
  "properties": {
    "addr:full":"Ceh Dorset, Winfrith Technology Centre Dorchester Dorset DT2 8ZD",
    "addr:postcode":"dt2 8zd",
    "addr:street":"Dorset",
    "iso:country":"GB",
    "sg:address":"Ceh Dorset, Winfrith Technology Centre",
    "sg:city":"Dorchester",
    "sg:classifiers":[
        {
            "category":"Government",
            "subcategory":"Post Office",
            "type":"Public Place"
        }
    ],
    "sg:phone":"+44 1305 213500",
    "sg:postcode":"DT2 8ZD",
    "sg:province":"Dorset",
    "sg:tags":[
        "organisation",
        "soc",
        "research"
    ],
    "wof:name":"Centre for Ecology and Hydrdyology",
    "wof:placetype":"venue"
},
  "geometry": {"coordinates":[-2.34296,50.744141],"type":"Point"}
}