{
  "type": "Feature",
  "properties": {
    "iso:country":"GB",
    "sg:address":"1 New Court, Temple",
    "sg:city":"London",
    "sg:classifiers":[
        {
            "category":"Professional",
            "subcategory":"Lawyer & Legal Services",
            "type":"Services"
        }
    ],
    "sg:phone":"+44 20 7583 5123",
    "sg:postcode":"EC4Y 9BE",
    "sg:province":"Greater London",
    "sg:tags":[
        "barrister"
    ],
    "wof:name":"James Hasslacher",
    "wof:placetype":"venue"
},
  "geometry": {"coordinates":[-0.112035,51.512672],"type":"Point"}
}