{
  "type": "Feature",
  "properties": {
    "addr:full":"144 Havelock Rd Wimbledon Greater London SW19 8HB",
    "addr:housenumber":"144",
    "addr:postcode":"sw19 8hb",
    "addr:street":"Havelock Rd",
    "iso:country":"GB",
    "sg:address":"144 Havelock Rd",
    "sg:city":"Wimbledon",
    "sg:classifiers":[
        {
            "category":"Building & Trades",
            "subcategory":"Construction",
            "type":"Services"
        }
    ],
    "sg:phone":"+44 20 8542 8048",
    "sg:postcode":"SW19 8HB",
    "sg:province":"Greater London",
    "sg:tags":[
        "dry",
        "lining",
        "plasterers",
        "screeders"
    ],
    "wof:name":"T Sweeney",
    "wof:placetype":"venue"
},
  "geometry": {"coordinates":[-0.188027,51.427433],"type":"Point"}
}