{
  "type": "Feature",
  "properties": {
    "addr:full":"Concorde House, Grenville Place, Mill Hill London Greater London NW7 3SA",
    "addr:postcode":"nw7 3sa",
    "addr:street":"Grenville Place",
    "iso:country":"GB",
    "sg:address":"Concorde House, Grenville Place, Mill Hill",
    "sg:city":"London",
    "sg:classifiers":[
        {
            "category":"Wholesale",
            "subcategory":"Books, Periodicals, & Newspapers",
            "type":"Manufacturing & Wholesale Goods"
        }
    ],
    "sg:phone":"+44 20 8959 3668",
    "sg:postcode":"NW7 3SA",
    "sg:province":"Greater London",
    "sg:tags":[
        "publishing"
    ],
    "wof:name":"Angus Hudson Ltd.",
    "wof:placetype":"venue"
},
  "geometry": {"coordinates":[-0.258389,51.616306],"type":"Point"}
}