{
  "type": "Feature",
  "properties": {
    "iso:country":"GB",
    "sg:address":"Little Forgue, Forgue",
    "sg:city":"Huntly",
    "sg:classifiers":[
        {
            "category":"Recreation",
            "subcategory":"Dog Park",
            "type":"Entertainment"
        },
        {
            "category":"Retail",
            "subcategory":"Animal Services",
            "type":"Services"
        }
    ],
    "sg:phone":"+44 1466 730292",
    "sg:postcode":"AB54 6DU",
    "sg:province":"Aberdeenshire",
    "sg:tags":[
        "breeder"
    ],
    "wof:name":"Forguecroft Kennels",
    "wof:placetype":"venue"
},
  "geometry": {"coordinates":[-2.651031,57.493866],"type":"Point"}
}