{
  "type": "Feature",
  "properties": {
    "iso:country":"GB",
    "sg:address":"Unit 2",
    "sg:city":"Truro",
    "sg:classifiers":[
        {
            "category":"Retail",
            "subcategory":"Storage",
            "type":"Services"
        }
    ],
    "sg:postcode":"TR1 2SU",
    "sg:province":"Cornwall",
    "sg:tags":[
        "cold"
    ],
    "wof:name":"Dorset & Cornwall Cold Stores Ltd.",
    "wof:placetype":"venue"
},
  "geometry": {"coordinates":[-5.051049,50.259529],"type":"Point"}
}