{
  "type": "Feature",
  "properties": {
    "addr:full":"13 Dod St Poplar Greater London E14 7EP",
    "addr:housenumber":"13",
    "addr:postcode":"e14 7ep",
    "addr:street":"Dod St",
    "iso:country":"GB",
    "sg:address":"13 Dod St",
    "sg:city":"Poplar",
    "sg:classifiers":[
        {
            "category":"Organizations",
            "subcategory":"Non-profit Organization",
            "type":"Services"
        }
    ],
    "sg:phone":"+44 20 7510 1300",
    "sg:postcode":"E14 7EP",
    "sg:province":"Greater London",
    "sg:tags":[
        "organisation",
        "voluntary",
        "charity"
    ],
    "wof:name":"Benefits Agency",
    "wof:placetype":"venue"
},
  "geometry": {"coordinates":[-0.054564,51.520161],"type":"Point"}
}