{
  "type": "Feature",
  "properties": {
    "addr:full":"Drovers Inn, Bishop Thornton Harrogate North Yorkshire HG3 3JN",
    "addr:postcode":"hg3 3jn",
    "iso:country":"GB",
    "sg:address":"Drovers Inn, Bishop Thornton",
    "sg:city":"Harrogate",
    "sg:classifiers":[
        {
            "category":"Bars & Pubs",
            "type":"Food & Drink"
        }
    ],
    "sg:phone":"+44 1423 779042",
    "sg:postcode":"HG3 3JN",
    "sg:province":"North Yorkshire",
    "sg:tags":[
        "pubs",
        "inn"
    ],
    "wof:name":"Drovers Inn (Harrogate) Ltd.",
    "wof:placetype":"venue"
},
  "geometry": {"coordinates":[-1.6005049944,54.0648117065],"type":"Point"}
}