{
  "type": "Feature",
  "properties": {
    "addr:full":"50-52 Pinbush Rd Lowestoft Suffolk NR33 7NL",
    "addr:housenumber":"50-52",
    "addr:postcode":"nr33 7nl",
    "addr:street":"Pinbush Rd",
    "iso:country":"GB",
    "sg:address":"50-52 Pinbush Rd",
    "sg:city":"Lowestoft",
    "sg:classifiers":[
        {
            "category":"Manufacturing",
            "subcategory":"Chemicals & Compounds",
            "type":"Manufacturing & Wholesale Goods"
        }
    ],
    "sg:phone":"+44 1502 588520",
    "sg:postcode":"NR33 7NL",
    "sg:province":"Suffolk",
    "sg:tags":[
        "pesticide"
    ],
    "wof:name":"Chemcraft Ltd",
    "wof:placetype":"venue"
},
  "geometry": {"coordinates":[1.7148000002,52.4450492859],"type":"Point"}
}