{
  "type": "Feature",
  "properties": {
    "addr:full":"The Limes, High Street, Hartley Wintney Basingstoke Berkshire RG27 8PE",
    "addr:postcode":"rg27 8pe",
    "addr:street":"The;High Street",
    "iso:country":"GB",
    "sg:address":"The Limes, High Street, Hartley Wintney",
    "sg:city":"Basingstoke",
    "sg:classifiers":[
        {
            "category":"Education",
            "subcategory":"Library",
            "type":"Public Place"
        }
    ],
    "sg:phone":"+44 1252 842402",
    "sg:postcode":"RG27 8PE",
    "sg:province":"Berkshire",
    "sg:tags":[
        "reproduction",
        "furniture"
    ],
    "wof:name":"Traditional Furnishings",
    "wof:placetype":"venue"
},
  "geometry": {"coordinates":[-0.9007539749,51.3058280945],"type":"Point"}
}