{
  "type": "Feature",
  "properties": {
    "addr:full":"183 Ormskirk Road, Rainford St Helens Lancashire WA11 8HR",
    "addr:housenumber":"183",
    "addr:postcode":"wa11 8hr",
    "addr:street":"Ormskirk Road Rainford",
    "iso:country":"GB",
    "sg:address":"183 Ormskirk Road, Rainford",
    "sg:city":"St Helens",
    "sg:classifiers":[
        {
            "category":"Food & Beverages",
            "subcategory":"Meat & Fish",
            "type":"Retail Goods"
        }
    ],
    "sg:phone":"+44 1744 885544",
    "sg:postcode":"WA11 8HR",
    "sg:province":"Lancashire",
    "sg:tags":[
        "chip"
    ],
    "wof:name":"Riverside",
    "wof:placetype":"venue"
},
  "geometry": {"coordinates":[-2.795256,53.507416],"type":"Point"}
}