{
  "type": "Feature",
  "properties": {
    "addr:full":"Unit 4 Point 4, Second Way Bristol City of Bristol BS11 8DF",
    "addr:housenumber":"unit 4;4",
    "addr:postcode":"bs11 8df",
    "addr:street":"Point;Second Way",
    "iso:country":"GB",
    "sg:address":"Unit 4 Point 4, Second Way",
    "sg:city":"Bristol",
    "sg:classifiers":[
        {
            "category":"Shopping",
            "subcategory":"Stationery & Office Supplies",
            "type":"Retail Goods"
        }
    ],
    "sg:postcode":"BS11 8DF",
    "sg:province":"City of Bristol",
    "sg:tags":[
        "box",
        "carton"
    ],
    "wof:name":"Kestrel Cases Ltd.",
    "wof:placetype":"venue"
},
  "geometry": {"coordinates":[-2.6822690964,51.500289917],"type":"Point"}
}