{
  "type": "Feature",
  "properties": {
    "addr:full":"New Market Hall Gainsborough Lincolnshire DN21 1JS",
    "addr:postcode":"dn21 1js",
    "iso:country":"GB",
    "sg:address":"New Market Hall",
    "sg:city":"Gainsborough",
    "sg:classifiers":[
        {
            "category":"Food & Beverages",
            "subcategory":"Meat & Fish",
            "type":"Retail Goods"
        }
    ],
    "sg:phone":"+44 1427 612882",
    "sg:postcode":"DN21 1JS",
    "sg:province":"Lincolnshire",
    "sg:tags":[
        "butcher"
    ],
    "wof:name":"S R Jubb Butcher",
    "wof:placetype":"venue"
},
  "geometry": {"coordinates":[-0.7727680206,53.3956947327],"type":"Point"}
}