{
  "type": "Feature",
  "properties": {
    "addr:full":"80-82 Alma Road Peterborough Cambridgeshire PE1 3AW",
    "addr:housenumber":"80-82",
    "addr:postcode":"pe1 3aw",
    "addr:street":"Alma Road",
    "iso:country":"GB",
    "sg:address":"80-82 Alma Road",
    "sg:city":"Peterborough",
    "sg:classifiers":[
        {
            "category":"Banks & Credit Unions",
            "subcategory":"Financial Services",
            "type":"Services"
        }
    ],
    "sg:phone":"+44 1733 777228",
    "sg:postcode":"PE1 3AW",
    "sg:province":"Cambridgeshire",
    "sg:tags":[
        "adviser",
        "independent"
    ],
    "wof:name":"Mckenna Associates Insurance Services",
    "wof:placetype":"venue"
},
  "geometry": {"coordinates":[-0.2432689965,52.586769104],"type":"Point"}
}