{
  "type": "Feature",
  "properties": {
    "addr:full":"137 High Street Street Somerset BA16 0EX",
    "addr:housenumber":"137",
    "addr:postcode":"ba16 0ex",
    "addr:street":"High Street Street",
    "iso:country":"GB",
    "sg:address":"137 High Street",
    "sg:city":"Street",
    "sg:classifiers":[
        {
            "category":"Personal",
            "subcategory":"Beauty Salon",
            "type":"Services"
        }
    ],
    "sg:postcode":"BA16 0EX",
    "sg:province":"Somerset",
    "sg:tags":[
        "unisex",
        "hairdresser"
    ],
    "wof:name":"The Hair Strand",
    "wof:placetype":"venue"
},
  "geometry": {"coordinates":[-2.742525,51.125038],"type":"Point"}
}