{
  "type": "Feature",
  "properties": {
    "addr:full":"193 High Street Swanage Dorset BH19 2NF",
    "addr:housenumber":"193",
    "addr:postcode":"bh19 2nf",
    "addr:street":"High Street",
    "iso:country":"GB",
    "sg:address":"193 High Street",
    "sg:city":"Swanage",
    "sg:classifiers":[
        {
            "category":"Fast Food",
            "type":"Food & Drink"
        }
    ],
    "sg:phone":"+44 1929 422327",
    "sg:postcode":"BH19 2NF",
    "sg:province":"Dorset",
    "sg:tags":[
        "away",
        "meal",
        "outlet",
        "take"
    ],
    "wof:name":"Wok Chef",
    "wof:placetype":"venue"
},
  "geometry": {"coordinates":[-1.9652,50.607983],"type":"Point"}
}