{
  "type": "Feature",
  "properties": {
    "addr:full":"Suite 4, Channel View, 14 Warren Edge Rd Bournemouth Dorset BH6 4AX",
    "addr:housenumber":"suite 4;14",
    "addr:postcode":"bh6 4ax",
    "addr:street":"Channel View;Warren Edge Rd",
    "iso:country":"GB",
    "sg:address":"Suite 4, Channel View, 14 Warren Edge Rd",
    "sg:city":"Bournemouth",
    "sg:classifiers":[
        {
            "category":"Professional",
            "subcategory":"Management & Consulting",
            "type":"Services"
        }
    ],
    "sg:phone":"+44 1202 423416",
    "sg:postcode":"BH6 4AX",
    "sg:province":"Dorset",
    "sg:tags":[
        "consultant"
    ],
    "wof:name":"The Memorable Number Co.",
    "wof:placetype":"venue"
},
  "geometry": {"coordinates":[-1.7907500267,50.7208518982],"type":"Point"}
}