{
  "type": "Feature",
  "properties": {
    "iso:country":"GB",
    "sg:address":"High St",
    "sg:city":"Worksop",
    "sg:classifiers":[
        {
            "category":"Bars & Pubs",
            "type":"Food & Drink"
        }
    ],
    "sg:phone":"+44 1909 591159",
    "sg:postcode":"S81 8EQ",
    "sg:province":"Nottinghamshire",
    "sg:tags":[
        "pubs",
        "inn"
    ],
    "wof:name":"Esco Business Retail Ltd",
    "wof:placetype":"venue"
},
  "geometry": {"coordinates":[-1.061189,53.375454],"type":"Point"}
}