{
  "type": "Feature",
  "properties": {
    "addr:full":"71 North Road, Kirkburton Huddersfield South Yorkshire HD8 0RH",
    "addr:housenumber":"71",
    "addr:postcode":"hd8 0rh",
    "addr:street":"North Road",
    "iso:country":"GB",
    "sg:address":"71 North Road, Kirkburton",
    "sg:city":"Huddersfield",
    "sg:classifiers":[
        {
            "category":"Food & Beverages",
            "subcategory":"Liquor & Beverages",
            "type":"Retail Goods"
        }
    ],
    "sg:phone":"+44 1484 608898",
    "sg:postcode":"HD8 0RH",
    "sg:province":"South Yorkshire",
    "sg:tags":[
        "beer",
        "spirit",
        "wines"
    ],
    "wof:name":"Southern Wine Brands (U K) Ltd.",
    "wof:placetype":"venue"
},
  "geometry": {"coordinates":[-1.704763,53.612888],"type":"Point"}
}