{
  "type": "Feature",
  "properties": {
    "addr:full":"52-54 The Green Banbury Oxfordshire OX16 9AB",
    "addr:housenumber":"52-54",
    "addr:postcode":"ox16 9ab",
    "addr:street":"The Green",
    "iso:country":"GB",
    "sg:address":"52-54 The Green",
    "sg:city":"Banbury",
    "sg:classifiers":[
        {
            "category":"Professional",
            "subcategory":"Lawyer & Legal Services",
            "type":"Services"
        }
    ],
    "sg:phone":"+44 1295 267971",
    "sg:postcode":"OX16 9AB",
    "sg:province":"Oxfordshire",
    "sg:tags":[
        "solicitor"
    ],
    "wof:name":"Shoosmith",
    "wof:placetype":"venue"
},
  "geometry": {"coordinates":[-1.330821991,52.0544662476],"type":"Point"}
}