{
  "type": "Feature",
  "properties": {
    "addr:full":"48 Gowthorpe Selby East Riding of Yorkshire YO8 4ET",
    "addr:housenumber":"48",
    "addr:postcode":"yo8 4et",
    "addr:street":"Gowthorpe",
    "iso:country":"GB",
    "sg:address":"48 Gowthorpe",
    "sg:city":"Selby",
    "sg:classifiers":[
        {
            "category":"Community Center",
            "subcategory":"Social",
            "type":"Public Place"
        }
    ],
    "sg:phone":"+44 1757 701602",
    "sg:postcode":"YO8 4ET",
    "sg:province":"East Riding of Yorkshire",
    "sg:tags":[
        "frozen",
        "food",
        "freezer",
        "centre"
    ],
    "wof:name":"Jack Fulton",
    "wof:placetype":"venue"
},
  "geometry": {"coordinates":[-1.072054,53.783829],"type":"Point"}
}