{
  "type": "Feature",
  "properties": {
    "addr:full":"11 Neasham Avenue Middlesbrough North Yorkshire TS7 8LY",
    "addr:housenumber":"11",
    "addr:postcode":"ts7 8ly",
    "addr:street":"Neasham Avenue",
    "iso:country":"GB",
    "sg:address":"11 Neasham Avenue",
    "sg:city":"Middlesbrough",
    "sg:classifiers":[
        {
            "category":"Building & Trades",
            "subcategory":"Construction",
            "type":"Services"
        }
    ],
    "sg:phone":"+44 1642 318320",
    "sg:postcode":"TS7 8LY",
    "sg:province":"North Yorkshire",
    "sg:tags":[
        "builder"
    ],
    "wof:name":"Colin R Burton",
    "wof:placetype":"venue"
},
  "geometry": {"coordinates":[-1.2031359673,54.5266723633],"type":"Point"}
}