{
  "type": "Feature",
  "properties": {
    "addr:full":"18 Holme Avenue, New Waltham Grimsby Lincolnshire DN36 4QN",
    "addr:housenumber":"18",
    "addr:postcode":"dn36 4qn",
    "addr:street":"Holme Avenue",
    "iso:country":"GB",
    "sg:address":"18 Holme Avenue, New Waltham",
    "sg:city":"Grimsby",
    "sg:classifiers":[
        {
            "category":"Government",
            "subcategory":"Department Of Motor Vehicles",
            "type":"Public Place"
        }
    ],
    "sg:phone":"+44 1472 811511",
    "sg:postcode":"DN36 4QN",
    "sg:province":"Lincolnshire",
    "sg:tags":[
        "inspection"
    ],
    "wof:name":"Pound Gates Vms",
    "wof:placetype":"venue"
},
  "geometry": {"coordinates":[-0.062996,53.525848],"type":"Point"}
}