{
  "type": "Feature",
  "properties": {
    "addr:full":"Lockgate House, Brackmills Northampton Northamptonshire NN4 7YB",
    "addr:postcode":"nn4 7yb",
    "addr:street":"Lockgate;Brackmills",
    "iso:country":"GB",
    "sg:address":"Lockgate House, Brackmills",
    "sg:city":"Northampton",
    "sg:classifiers":[
        {
            "category":"Professional",
            "subcategory":"Detective & Security Services",
            "type":"Services"
        }
    ],
    "sg:phone":"+44 1604 630314",
    "sg:postcode":"NN4 7YB",
    "sg:province":"Northamptonshire",
    "wof:name":"A D T Security Systems",
    "wof:placetype":"venue"
},
  "geometry": {"coordinates":[-0.8626499772,52.2274703979],"type":"Point"}
}