{
  "type": "Feature",
  "properties": {
    "iso:country":"GB",
    "sg:address":"Bilsborrow Hall Farm, Bilsborrow Lane",
    "sg:city":"Preston",
    "sg:classifiers":[
        {
            "category":"Farming",
            "subcategory":"Dairy Farm",
            "type":"Manufacturing & Wholesale Goods"
        }
    ],
    "sg:phone":"+44 1995 640209",
    "sg:postcode":"PR3 0RP",
    "sg:province":"Lancashire",
    "wof:name":"D J Tomlinson",
    "wof:placetype":"venue"
},
  "geometry": {"coordinates":[-2.744869,53.854244],"type":"Point"}
}