{
  "type": "Feature",
  "properties": {
    "iso:country":"GB",
    "sg:address":"Ground Floor Office, 810 Bury Road",
    "sg:city":"Bolton",
    "sg:classifiers":[
        {
            "category":"Wholesale",
            "subcategory":"Apparel",
            "type":"Manufacturing & Wholesale Goods"
        }
    ],
    "sg:phone":"+44 1204 433311",
    "sg:postcode":"BL2 6PA",
    "sg:province":"Lancashire",
    "sg:tags":[
        "babywear",
        "childrens"
    ],
    "wof:name":"Topsys",
    "wof:placetype":"venue"
},
  "geometry": {"coordinates":[-2.38501,53.580681],"type":"Point"}
}