{
  "type": "Feature",
  "properties": {
    "iso:country":"GB",
    "sg:address":"427 Wellingborough Road",
    "sg:city":"Northampton",
    "sg:classifiers":[
        {
            "category":"Retail",
            "subcategory":"Veterinary Services",
            "type":"Services"
        }
    ],
    "sg:phone":"+44 1604 628685",
    "sg:postcode":"NN1 4EZ",
    "sg:province":"Northamptonshire",
    "sg:tags":[
        "surgeon",
        "activity"
    ],
    "wof:name":"Abington Park Veterinary Surgery",
    "wof:placetype":"venue"
},
  "geometry": {"coordinates":[-0.869352,52.247444],"type":"Point"}
}