{
  "type": "Feature",
  "properties": {
    "addr:full":"The Old Rectory, Weston Patrick Basingstoke Hampshire RG25 2NU",
    "addr:postcode":"hampshire rg25 2nu",
    "addr:street":"Weston Patrick",
    "iso:country":"GB",
    "sg:address":"The Old Rectory, Weston Patrick",
    "sg:city":"Basingstoke",
    "sg:classifiers":[
        {
            "category":"Professional",
            "subcategory":"Management & Consulting",
            "type":"Services"
        }
    ],
    "sg:phone":"+44 1256 862966",
    "sg:postcode":"RG25 2NU",
    "sg:province":"Hampshire",
    "sg:tags":[
        "consultant",
        "business"
    ],
    "wof:name":"Longueville Communications",
    "wof:placetype":"venue"
},
  "geometry": {"coordinates":[-1.013618,51.217674],"type":"Point"}
}