{
  "type": "Feature",
  "properties": {
    "addr:full":"29 Brendon Rd Watchet Somerset TA23 0AX",
    "addr:housenumber":"29",
    "addr:postcode":"ta23 0ax",
    "addr:street":"Brendon Rd",
    "iso:country":"GB",
    "sg:address":"29 Brendon Rd",
    "sg:city":"Watchet",
    "sg:classifiers":[
        {
            "category":"Building & Trades",
            "subcategory":"Construction",
            "type":"Services"
        }
    ],
    "sg:phone":"+44 1984 631357",
    "sg:postcode":"TA23 0AX",
    "sg:province":"Somerset",
    "sg:tags":[
        "builder"
    ],
    "wof:name":"E J & D Prole",
    "wof:placetype":"venue"
},
  "geometry": {"coordinates":[-3.334321,51.177891],"type":"Point"}
}