{
  "type": "Feature",
  "properties": {
    "addr:full":"10 Castle Street Clitheroe Lancashire BB7 2BX",
    "addr:housenumber":"10",
    "addr:postcode":"bb7 2bx",
    "addr:street":"Castle Street",
    "iso:country":"GB",
    "sg:address":"10 Castle Street",
    "sg:city":"Clitheroe",
    "sg:classifiers":[
        {
            "category":"Food & Beverages",
            "subcategory":"Candy",
            "type":"Retail Goods"
        }
    ],
    "sg:phone":"+44 1200 425026",
    "sg:postcode":"BB7 2BX",
    "sg:province":"Lancashire",
    "sg:tags":[
        "confectioner"
    ],
    "wof:name":"Hampsons (Bolton) Ltd.",
    "wof:placetype":"venue"
},
  "geometry": {"coordinates":[-2.3919210434,53.8716583252],"type":"Point"}
}