{
  "type": "Feature",
  "properties": {
    "addr:full":"8 Green Road, Bernard Braine House Benfleet Essex SS7 5JT",
    "addr:housenumber":"8",
    "addr:postcode":"ss7 5jt",
    "addr:street":"Green Road Bernard Braine House Benfleet",
    "iso:country":"GB",
    "sg:address":"8 Green Road, Bernard Braine House",
    "sg:city":"Benfleet",
    "sg:classifiers":[
        {
            "category":"Organizations",
            "subcategory":"Political Organization",
            "type":"Services"
        }
    ],
    "sg:phone":"+44 1268 792992",
    "sg:postcode":"SS7 5JT",
    "sg:province":"Essex",
    "sg:tags":[
        "party"
    ],
    "wof:name":"Castlepoint Conservative Association",
    "wof:placetype":"venue"
},
  "geometry": {"coordinates":[0.5622479916,51.5482749939],"type":"Point"}
}