{
  "type": "Feature",
  "properties": {
    "addr:full":"Unit 1 Metropolitan Dr Blackpool Lancashire FY3 9JD",
    "addr:housenumber":"unit 1",
    "addr:postcode":"fy3 9jd",
    "addr:street":"Metropolitan Dr",
    "iso:country":"GB",
    "sg:address":"Unit 1 Metropolitan Dr",
    "sg:city":"Blackpool",
    "sg:classifiers":[
        {
            "category":"Travel",
            "subcategory":"Travel Agent",
            "type":"Entertainment"
        }
    ],
    "sg:phone":"+44 1253 401407",
    "sg:postcode":"FY3 9JD",
    "sg:province":"Lancashire",
    "wof:name":"South Shore Travel",
    "wof:placetype":"venue"
},
  "geometry": {"coordinates":[-3.005353,53.803822],"type":"Point"}
}