{
  "type": "Feature",
  "properties": {
    "iso:country":"GB",
    "sg:address":"Stourton House, High Street, Stourton",
    "sg:city":"Warminster",
    "sg:classifiers":[
        {
            "category":"Park",
            "type":"Public Place"
        },
        {
            "category":"Landmark",
            "subcategory":"Tourist Attraction",
            "type":"Public Place"
        }
    ],
    "sg:phone":"+44 1747 840417",
    "sg:postcode":"BA12 6QF",
    "sg:province":"Somerset",
    "sg:tags":[
        "garden",
        "interest"
    ],
    "wof:name":"Stourton House Flower Garden",
    "wof:placetype":"venue"
},
  "geometry": {"coordinates":[-2.318929,51.105549],"type":"Point"}
}