{
  "type": "Feature",
  "properties": {
    "addr:full":"91 Wey Hill Haslemere Hampshire GU27 1HP",
    "addr:housenumber":"91",
    "addr:postcode":"gu27 1hp",
    "addr:street":"Wey Hill",
    "iso:country":"GB",
    "sg:address":"91 Wey Hill",
    "sg:city":"Haslemere",
    "sg:classifiers":[
        {
            "category":"Education",
            "subcategory":"University",
            "type":"Public Place"
        },
        {
            "category":"Government",
            "subcategory":"Office",
            "type":"Public Place"
        }
    ],
    "sg:phone":"+44 1428 661650",
    "sg:postcode":"GU27 1HP",
    "sg:province":"Hampshire",
    "sg:tags":[
        "local",
        "adult"
    ],
    "wof:name":"Haslemere Adult Education Centre",
    "wof:placetype":"venue"
},
  "geometry": {"coordinates":[-0.7237049937,51.0880737305],"type":"Point"}
}