{
  "type": "Feature",
  "properties": {
    "addr:full":"28 Brock St Bath Bath and North East Somerset BA1 2LN",
    "addr:housenumber":"28",
    "addr:postcode":"ba1 2ln",
    "addr:street":"Brock St",
    "iso:country":"GB",
    "sg:address":"28 Brock St",
    "sg:city":"Bath",
    "sg:classifiers":[
        {
            "category":"Professional",
            "subcategory":"Computer Services",
            "type":"Services"
        }
    ],
    "sg:phone":"+44 1225 428494",
    "sg:postcode":"BA1 2LN",
    "sg:province":"Bath and North East Somerset",
    "sg:tags":[
        "system",
        "software"
    ],
    "wof:name":"C D G M Entertainment Ltd",
    "wof:placetype":"venue"
},
  "geometry": {"coordinates":[-2.36541605,51.3863220215],"type":"Point"}
}