{
  "type": "Feature",
  "properties": {
    "addr:full":"6 Union Street Newport-on-tay Fife DD6 8BP",
    "addr:housenumber":"6",
    "addr:postcode":"dd6 8bp",
    "addr:street":"Union Street",
    "iso:country":"GB",
    "sg:address":"6 Union Street",
    "sg:city":"Newport-on-tay",
    "sg:classifiers":[
        {
            "category":"Building & Trades",
            "subcategory":"Plumbing",
            "type":"Services"
        }
    ],
    "sg:phone":"+44 1382 543357",
    "sg:postcode":"DD6 8BP",
    "sg:province":"Fife",
    "sg:tags":[
        "plumber",
        "heating"
    ],
    "wof:name":"David D Smith",
    "wof:placetype":"venue"
},
  "geometry": {"coordinates":[-2.939546,56.441189],"type":"Point"}
}