{
  "type": "Feature",
  "properties": {
    "addr:full":"36 High Street, St Neots Huntingdon Bedfordshire PE19 1JA",
    "addr:housenumber":"36",
    "addr:postcode":"pe19 1ja",
    "addr:street":"High Street",
    "iso:country":"GB",
    "sg:address":"36 High Street, St Neots",
    "sg:city":"Huntingdon",
    "sg:classifiers":[
        {
            "category":"Sports & Exercise",
            "subcategory":"Sports Center",
            "type":"Entertainment"
        }
    ],
    "sg:phone":"+44 1480 407577",
    "sg:postcode":"PE19 1JA",
    "sg:province":"Bedfordshire",
    "sg:tags":[
        "shop",
        "good"
    ],
    "wof:name":"Sporting Image",
    "wof:placetype":"venue"
},
  "geometry": {"coordinates":[-0.2676779926,52.2280654907],"type":"Point"}
}