{
  "type": "Feature",
  "properties": {
    "addr:full":"Unit 1160, Elliot Ct, Herald Ave, Coventry Business Pk Coventry West Midlands CV5 6UB",
    "addr:housenumber":"unit 1160",
    "addr:postcode":"cv5 6ub",
    "addr:street":"Elliot Ct Herald Ave;Business Pk Coventry West",
    "iso:country":"GB",
    "sg:address":"Unit 1160, Elliot Ct, Herald Ave, Coventry Business Pk",
    "sg:city":"Coventry",
    "sg:classifiers":[
        {
            "category":"Shopping",
            "subcategory":"Computers & Home Electronics",
            "type":"Retail Goods"
        }
    ],
    "sg:phone":"+44 24 7671 8140",
    "sg:postcode":"CV5 6UB",
    "sg:province":"West Midlands",
    "wof:name":"Network Appliance Ltd",
    "wof:placetype":"venue"
},
  "geometry": {"coordinates":[-1.55275,52.403198],"type":"Point"}
}