{
  "type": "Feature",
  "properties": {
    "addr:full":"29 Kings Park Road Bournemouth Dorset BH7 7AE",
    "addr:housenumber":"29",
    "addr:postcode":"bh7 7ae",
    "addr:street":"Kings Park Road",
    "iso:country":"GB",
    "sg:address":"29 Kings Park Road",
    "sg:city":"Bournemouth",
    "sg:classifiers":[
        {
            "category":"Social Services",
            "subcategory":"Retirement Home",
            "type":"Services"
        }
    ],
    "sg:phone":"+44 1202 395342",
    "sg:postcode":"BH7 7AE",
    "sg:province":"Dorset",
    "sg:tags":[
        "rest"
    ],
    "wof:name":"Park View Rest Home",
    "wof:placetype":"venue"
},
  "geometry": {"coordinates":[-1.841769,50.734783],"type":"Point"}
}