{
  "type": "Feature",
  "properties": {
    "addr:full":"Waterford Bridge, Kentmere Kendal Cumbria LA8 9JJ",
    "addr:postcode":"la8 9jj",
    "addr:street":"Bridge",
    "iso:country":"GB",
    "sg:address":"Waterford Bridge, Kentmere",
    "sg:city":"Kendal",
    "sg:classifiers":[
        {
            "category":"Bus Stop",
            "subcategory":"None",
            "type":"Transportation"
        },
        {
            "category":"Manufacturing",
            "subcategory":"Building Materials",
            "type":"Manufacturing & Wholesale Goods"
        }
    ],
    "sg:phone":"+44 1539 825200",
    "sg:postcode":"LA8 9JJ",
    "sg:province":"Cumbria",
    "sg:tags":[
        "filter",
        "manufacturer"
    ],
    "wof:name":"Hollingsworth & Vose Air Filtration Ltd.",
    "wof:placetype":"venue"
},
  "geometry": {"coordinates":[-2.843019,54.429806],"type":"Point"}
}