{
  "type": "Feature",
  "properties": {
    "iso:country":"GB",
    "sg:address":"8 West St",
    "sg:city":"West Malling",
    "sg:classifiers":[
        {
            "category":"Shopping",
            "subcategory":"Books",
            "type":"Retail Goods"
        }
    ],
    "sg:postcode":"ME19 6QX",
    "sg:province":"Kent",
    "sg:tags":[
        "second-hand"
    ],
    "wof:name":"Rees,Lynne,",
    "wof:placetype":"venue"
},
  "geometry": {"coordinates":[0.407768,51.294338],"type":"Point"}
}