{
  "type": "Feature",
  "properties": {
    "addr:full":"Century Ho, 100 Maxted Rd Hemel Hempstead Hertfordshire HP2 7GL",
    "addr:housenumber":"100",
    "addr:postcode":"hp2 7gl",
    "addr:street":"Maxted Rd",
    "iso:country":"GB",
    "sg:address":"Century Ho, 100 Maxted Rd",
    "sg:city":"Hemel Hempstead",
    "sg:classifiers":[
        {
            "category":"Professional",
            "subcategory":"Engineering",
            "type":"Services"
        }
    ],
    "sg:phone":"+44 1442 280390",
    "sg:postcode":"HP2 7GL",
    "sg:province":"Hertfordshire",
    "sg:tags":[
        "precision",
        "engineer"
    ],
    "wof:name":"Triax Manufacturing Ltd",
    "wof:placetype":"venue"
},
  "geometry": {"coordinates":[-0.438658,51.762024],"type":"Point"}
}