{
  "type": "Feature",
  "properties": {
    "addr:full":"77a St Johns Road Tunbridge Wells Kent TN4 9TT",
    "addr:housenumber":"77a",
    "addr:postcode":"tn4 9tt",
    "addr:street":"St Johns Road",
    "iso:country":"GB",
    "sg:address":"77a St Johns Road",
    "sg:city":"Tunbridge Wells",
    "sg:classifiers":[
        {
            "category":"Government",
            "subcategory":"Customs House",
            "type":"Public Place"
        }
    ],
    "sg:phone":"+44 1892 677737",
    "sg:postcode":"TN4 9TT",
    "sg:province":"Kent",
    "sg:tags":[
        "clearance"
    ],
    "wof:name":"Junk & Disorderley",
    "wof:placetype":"venue"
},
  "geometry": {"coordinates":[0.259995997,51.1416091919],"type":"Point"}
}