{
  "type": "Feature",
  "properties": {
    "iso:country":"GB",
    "sg:address":"7-8 High Street",
    "sg:city":"Stroud",
    "sg:classifiers":[
        {
            "category":"Shopping",
            "subcategory":"News",
            "type":"Retail Goods"
        }
    ],
    "sg:phone":"+44 1453 752497",
    "sg:postcode":"GL5 1AU",
    "sg:province":"Gloucestershire",
    "sg:tags":[
        "newsagent"
    ],
    "wof:name":"Forbuoys Ltd",
    "wof:placetype":"venue"
},
  "geometry": {"coordinates":[-2.217034,51.745667],"type":"Point"}
}