{
  "type": "Feature",
  "properties": {
    "iso:country":"GB",
    "sg:address":"Nailsea Delivery Office, Crown Glass Place, Nailsea",
    "sg:city":"Bristol",
    "sg:classifiers":[
        {
            "category":"Personal",
            "type":"Services"
        }
    ],
    "sg:phone":"+44 1275 810340",
    "sg:postcode":"BS48 1RA",
    "sg:province":"Somerset",
    "sg:tags":[
        "delivery"
    ],
    "wof:name":"Royal Mail",
    "wof:placetype":"venue"
},
  "geometry": {"coordinates":[-2.75852,51.432411],"type":"Point"}
}