{
  "type": "Feature",
  "properties": {
    "addr:full":"Honeywood Park Way, White Cliffs Business Park, Whitfield Dover Kent CT16 3PT",
    "addr:postcode":"ct16 3pt",
    "addr:street":"Park Way;Business Park;Dover",
    "iso:country":"GB",
    "sg:address":"Honeywood Park Way, White Cliffs Business Park, Whitfield",
    "sg:city":"Dover",
    "sg:classifiers":[
        {
            "category":"Wholesale",
            "subcategory":"Construction Materials",
            "type":"Manufacturing & Wholesale Goods"
        },
        {
            "category":"Manufacturing",
            "subcategory":"Building Materials",
            "type":"Manufacturing & Wholesale Goods"
        }
    ],
    "sg:phone":"+44 1304 827722",
    "sg:postcode":"CT16 3PT",
    "sg:province":"Kent",
    "sg:tags":[
        "merchant",
        "builder",
        "brick"
    ],
    "wof:name":"Coastal Brick & Building Supplies Ltd.",
    "wof:placetype":"venue"
},
  "geometry": {"coordinates":[1.30422,51.153759],"type":"Point"}
}