{
  "type": "Feature",
  "properties": {
    "addr:full":"14 Pulteney Bridge Bath Somerset BA2 4AY",
    "addr:housenumber":"14",
    "addr:postcode":"ba2 4ay",
    "addr:street":"Pulteney Bridge",
    "iso:country":"GB",
    "sg:address":"14 Pulteney Bridge",
    "sg:city":"Bath",
    "sg:classifiers":[
        {
            "category":"Government",
            "subcategory":"Post Office",
            "type":"Public Place"
        },
        {
            "category":"Shopping",
            "subcategory":"Florist",
            "type":"Retail Goods"
        }
    ],
    "sg:phone":"+44 1225 461938",
    "sg:postcode":"BA2 4AY",
    "sg:province":"Somerset",
    "sg:tags":[
        "copper",
        "brass"
    ],
    "wof:name":"Pulteney Bridge Flowers",
    "wof:placetype":"venue"
},
  "geometry": {"coordinates":[-2.3501338959,51.3797187805],"type":"Point"}
}