{
  "type": "Feature",
  "properties": {
    "addr:full":"15 Chester Close Loughborough Leicestershire LE11 3BD",
    "addr:housenumber":"15",
    "addr:postcode":"le11 3bd",
    "addr:street":"Chester Close",
    "iso:country":"GB",
    "sg:address":"15 Chester Close",
    "sg:city":"Loughborough",
    "sg:classifiers":[
        {
            "category":"Professional",
            "subcategory":"Engineering",
            "type":"Services"
        },
        {
            "category":"Building & Trades",
            "subcategory":"Electrical",
            "type":"Services"
        }
    ],
    "sg:phone":"+44 1509 236739",
    "sg:postcode":"LE11 3BD",
    "sg:province":"Leicestershire",
    "sg:tags":[
        "engineer",
        "electrician",
        "contractor"
    ],
    "wof:name":"Stephen Charles Day",
    "wof:placetype":"venue"
},
  "geometry": {"coordinates":[-1.2164629698,52.7698974609],"type":"Point"}
}