{
  "type": "Feature",
  "properties": {
    "addr:full":"2 Dene Place Woking Surrey GU21 3DX",
    "addr:housenumber":"2",
    "addr:postcode":"gu21 3dx",
    "addr:street":"Dene Place",
    "iso:country":"GB",
    "sg:address":"2 Dene Place",
    "sg:city":"Woking",
    "sg:classifiers":[
        {
            "category":"Professional",
            "subcategory":"Computer Services",
            "type":"Services"
        }
    ],
    "sg:postcode":"GU21 3DX",
    "sg:province":"Surrey",
    "sg:tags":[
        "system",
        "software"
    ],
    "wof:name":"Sweepmode Ltd",
    "wof:placetype":"venue"
},
  "geometry": {"coordinates":[-0.5806369781,51.3166275024],"type":"Point"}
}