{
  "type": "Feature",
  "properties": {
    "addr:full":"Suite 17, City Business Centre London Greater London SE16 7AA",
    "addr:postcode":"se16 7aa",
    "addr:street":"Suite 17 City",
    "iso:country":"GB",
    "sg:address":"Suite 17, City Business Centre",
    "sg:city":"London",
    "sg:classifiers":[
        {
            "category":"Professional",
            "subcategory":"Engineering",
            "type":"Services"
        }
    ],
    "sg:phone":"+44 20 8671 9074",
    "sg:postcode":"SE16 7AA",
    "sg:province":"Greater London",
    "sg:tags":[
        "design",
        "engineer"
    ],
    "wof:name":"Dynamation Ltd.",
    "wof:placetype":"venue"
},
  "geometry": {"coordinates":[-0.0542859994,51.4986724854],"type":"Point"}
}