{
  "type": "Feature",
  "properties": {
    "iso:country":"GB",
    "sg:address":"Walker Road",
    "sg:city":"Inverness",
    "sg:classifiers":[
        {
            "category":"Retail",
            "subcategory":"Auto Repair",
            "type":"Services"
        }
    ],
    "sg:phone":"+44 1463 713251",
    "sg:postcode":"IV1 1TD",
    "sg:province":"Highland",
    "sg:tags":[
        "modification",
        "car",
        "vehicle",
        "commercial",
        "garage"
    ],
    "wof:name":"K W Motors",
    "wof:placetype":"venue"
},
  "geometry": {"coordinates":[-4.226020813,57.4856567383],"type":"Point"}
}