{
  "type": "Feature",
  "properties": {
    "addr:full":"9 Newminster Road Cardiff Cardiff CF23 5AP",
    "addr:housenumber":"9",
    "addr:postcode":"cf23 5ap",
    "addr:street":"Newminster Road",
    "iso:country":"GB",
    "sg:address":"9 Newminster Road",
    "sg:city":"Cardiff",
    "sg:classifiers":[
        {
            "category":"Professional",
            "subcategory":"Accounting & Tax Preparation",
            "type":"Services"
        }
    ],
    "sg:postcode":"CF23 5AP",
    "sg:province":"Cardiff",
    "sg:tags":[
        "payroll"
    ],
    "wof:name":"Howell Management Ltd.",
    "wof:placetype":"venue"
},
  "geometry": {"coordinates":[-3.15214,51.493809],"type":"Point"}
}