{
  "type": "Feature",
  "properties": {
    "addr:full":"18 Saxon Road Southampton Hampshire SO15 1JJ",
    "addr:housenumber":"18",
    "addr:postcode":"so15 1jj",
    "addr:street":"Saxon Road",
    "iso:country":"GB",
    "sg:address":"18 Saxon Road",
    "sg:city":"Southampton",
    "sg:classifiers":[
        {
            "category":"Building & Trades",
            "subcategory":"Construction",
            "type":"Services"
        }
    ],
    "sg:phone":"+44 23 8063 1881",
    "sg:postcode":"SO15 1JJ",
    "sg:province":"Hampshire",
    "sg:tags":[
        "builder"
    ],
    "wof:name":"Robert Silcock",
    "wof:placetype":"venue"
},
  "geometry": {"coordinates":[-1.421505,50.907738],"type":"Point"}
}