{
  "type": "Feature",
  "properties": {
    "addr:full":"Bellcrest House, Battle Road St Leonards-on-sea East Sussex TN37 7EP",
    "addr:postcode":"leonards-on-sea;tn37 7ep",
    "addr:street":"Battle Road St",
    "iso:country":"GB",
    "sg:address":"Bellcrest House, Battle Road",
    "sg:city":"St Leonards-on-sea",
    "sg:classifiers":[
        {
            "category":"Professional",
            "subcategory":"Detective & Security Services",
            "type":"Services"
        }
    ],
    "sg:phone":"+44 1424 852343",
    "sg:postcode":"TN37 7EP",
    "sg:province":"East Sussex",
    "sg:tags":[
        "alarm",
        "burglar",
        "system"
    ],
    "wof:name":"Bellcrest Ltd.",
    "wof:placetype":"venue"
},
  "geometry": {"coordinates":[0.5416849852,50.8891334534],"type":"Point"}
}