{
  "type": "Feature",
  "properties": {
    "addr:full":"46-48 Kings Road Brighton East Sussex BN1 1NA",
    "addr:housenumber":"46-48",
    "addr:postcode":"bn1 1na",
    "addr:street":"Kings Road",
    "iso:country":"GB",
    "sg:address":"46-48 Kings Road",
    "sg:city":"Brighton",
    "sg:classifiers":[
        {
            "category":"Restaurant",
            "type":"Food & Drink"
        }
    ],
    "sg:phone":"+44 1273 323600",
    "sg:postcode":"BN1 1NA",
    "sg:province":"East Sussex",
    "sg:tags":[
        "american"
    ],
    "wof:name":"Buddies",
    "wof:placetype":"venue"
},
  "geometry": {"coordinates":[-0.1429239959,50.8203964233],"type":"Point"}
}