{
  "type": "Feature",
  "properties": {
    "iso:country":"GB",
    "sg:address":"Forge Side",
    "sg:city":"Blaina",
    "sg:classifiers":[
        {
            "category":"Health Services",
            "subcategory":"Nursing And Care Facility",
            "type":"Services"
        }
    ],
    "sg:phone":"+44 1495 290550",
    "sg:postcode":"NP3 3AN",
    "sg:province":"Blaenau Gwent",
    "sg:tags":[
        "home"
    ],
    "wof:name":"Cwmcelyn Nursing Home",
    "wof:placetype":"venue"
},
  "geometry": {"coordinates":[-3.15989995,51.7653999329],"type":"Point"}
}