{
  "type": "Feature",
  "properties": {
    "addr:full":"25 Gloucester Road, Acton London Greater London W3 8PD",
    "addr:housenumber":"25",
    "addr:postcode":"w3 8pd",
    "addr:street":"Gloucester Road",
    "iso:country":"GB",
    "sg:address":"25 Gloucester Road, Acton",
    "sg:city":"London",
    "sg:classifiers":[
        {
            "category":"Building & Trades",
            "subcategory":"Construction",
            "type":"Services"
        }
    ],
    "sg:phone":"+44 20 8993 6127",
    "sg:postcode":"W3 8PD",
    "sg:province":"Greater London",
    "sg:tags":[
        "builder",
        "contractor"
    ],
    "sg:website":"http://www.porchfern.co.uk",
    "wof:name":"Porchfern Ltd.",
    "wof:placetype":"venue"
},
  "geometry": {"coordinates":[-0.2652800083,51.5059700012],"type":"Point"}
}