{
  "type": "Feature",
  "properties": {
    "addr:full":"3 Church Fields Kidderminster Staffordshire DY10 2JL",
    "addr:housenumber":"3",
    "addr:postcode":"dy10 2jl",
    "addr:street":"Church Fields",
    "iso:country":"GB",
    "sg:address":"3 Church Fields",
    "sg:city":"Kidderminster",
    "sg:classifiers":[
        {
            "category":"Banks & Credit Unions",
            "subcategory":"Financial Services",
            "type":"Services"
        }
    ],
    "sg:phone":"+44 1299 401466",
    "sg:postcode":"DY10 2JL",
    "sg:province":"Staffordshire",
    "sg:tags":[
        "consultant"
    ],
    "wof:name":"Finance & Leasing Bureau",
    "wof:placetype":"venue"
},
  "geometry": {"coordinates":[-2.2494928837,52.3908004761],"type":"Point"}
}