{
  "type": "Feature",
  "properties": {
    "addr:full":"Hollins Green Farm, Hollins Green Lane, Newhall Nantwich Cheshire CW5 8AZ",
    "addr:postcode":"cw5 8az",
    "addr:street":"Hollins Green;Hollins Green Lane",
    "iso:country":"GB",
    "sg:address":"Hollins Green Farm, Hollins Green Lane, Newhall",
    "sg:city":"Nantwich",
    "sg:classifiers":[
        {
            "category":"Farming",
            "subcategory":"Livestock Farm",
            "type":"Manufacturing & Wholesale Goods"
        }
    ],
    "sg:postcode":"CW5 8AZ",
    "sg:province":"Cheshire",
    "sg:tags":[
        "others"
    ],
    "wof:name":"T W Johnson",
    "wof:placetype":"venue"
},
  "geometry": {"coordinates":[-2.5692019463,53.0062942505],"type":"Point"}
}