{
  "type": "Feature",
  "properties": {
    "addr:full":"Windmill Lane, Bursledon Southampton Hampshire SO31 8BG",
    "addr:postcode":"so31 8bg",
    "addr:street":"Windmill Lane",
    "iso:country":"GB",
    "sg:address":"Windmill Lane, Bursledon",
    "sg:city":"Southampton",
    "sg:classifiers":[
        {
            "category":"Landmark",
            "subcategory":"Tourist Attraction",
            "type":"Public Place"
        }
    ],
    "sg:phone":"+44 23 8040 4999",
    "sg:postcode":"SO31 8BG",
    "sg:province":"Hampshire",
    "sg:tags":[
        "interest"
    ],
    "wof:name":"Bursledon Windmill",
    "wof:placetype":"venue"
},
  "geometry": {"coordinates":[-1.315344,50.889721],"type":"Point"}
}