{
  "type": "Feature",
  "properties": {
    "iso:country":"GB",
    "sg:address":"72 Northbrook Street",
    "sg:city":"Newbury",
    "sg:classifiers":[
        {
            "category":"Shopping",
            "subcategory":"Thrift Store",
            "type":"Retail Goods"
        }
    ],
    "sg:phone":"+44 1635 40712",
    "sg:postcode":"RG14 1AE",
    "sg:province":"Berkshire",
    "sg:tags":[
        "shop",
        "charity"
    ],
    "wof:name":"Oxfam",
    "wof:placetype":"venue"
},
  "geometry": {"coordinates":[-1.324772954,51.4035148621],"type":"Point"}
}