{
  "type": "Feature",
  "properties": {
    "addr:full":"6 Old Court Place London Greater London W8 4PL",
    "addr:housenumber":"6",
    "addr:postcode":"w8 4pl",
    "addr:street":"Old Court Place",
    "iso:country":"GB",
    "sg:address":"6 Old Court Place",
    "sg:city":"London",
    "sg:classifiers":[
        {
            "category":"Restaurant",
            "type":"Food & Drink"
        }
    ],
    "sg:phone":"+44 20 7937 6462",
    "sg:postcode":"W8 4PL",
    "sg:province":"Greater London",
    "sg:tags":[
        "-",
        "english"
    ],
    "wof:name":"Maggie Jones's Restaurant",
    "wof:placetype":"venue"
},
  "geometry": {"coordinates":[-0.191177994,51.5027313232],"type":"Point"}
}