{
  "type": "Feature",
  "properties": {
    "iso:country":"GB",
    "sg:address":"21 Reeve Road",
    "sg:city":"Reigate",
    "sg:classifiers":[
        {
            "category":"Building & Trades",
            "subcategory":"Construction",
            "type":"Services"
        }
    ],
    "sg:phone":"+44 1737 222361",
    "sg:postcode":"RH2 7PQ",
    "sg:province":"Surrey",
    "sg:tags":[
        "contractor",
        "paving",
        "driveway"
    ],
    "wof:name":"W Gardner",
    "wof:placetype":"venue"
},
  "geometry": {"coordinates":[-0.194324,51.220837],"type":"Point"}
}