{
  "type": "Feature",
  "properties": {
    "addr:full":"4 Hillary Crescent Liverpool Lancashire L31 6BL",
    "addr:housenumber":"4",
    "addr:postcode":"l31 6bl",
    "addr:street":"Hillary Crescent",
    "iso:country":"GB",
    "sg:address":"4 Hillary Crescent",
    "sg:city":"Liverpool",
    "sg:classifiers":[
        {
            "category":"Professional",
            "subcategory":"Management & Consulting",
            "type":"Services"
        },
        {
            "category":"Communications",
            "type":"Services"
        }
    ],
    "sg:phone":"+44 1925 271000",
    "sg:postcode":"L31 6BL",
    "sg:province":"Lancashire",
    "sg:tags":[
        "consultant",
        "telecommunication"
    ],
    "wof:name":"A T Installations Ltd.",
    "wof:placetype":"venue"
},
  "geometry": {"coordinates":[-2.938033,53.51461],"type":"Point"}
}