{
  "type": "Feature",
  "properties": {
    "addr:full":"26 North Road, Lerwick Shetland Shetland Islands ZE1 0NQ",
    "addr:housenumber":"26",
    "addr:postcode":"ze1 0nq",
    "addr:street":"North Road",
    "iso:country":"GB",
    "sg:address":"26 North Road, Lerwick",
    "sg:city":"Shetland",
    "sg:classifiers":[
        {
            "category":"Shopping",
            "subcategory":"Stationery & Office Supplies",
            "type":"Retail Goods"
        }
    ],
    "sg:phone":"+44 1595 698800",
    "sg:postcode":"ZE1 0NQ",
    "sg:province":"Shetland Islands",
    "wof:name":"Mes Business Equipment Ltd.",
    "wof:placetype":"venue"
},
  "geometry": {"coordinates":[-1.1551660299,60.1574478149],"type":"Point"}
}