{
  "type": "Feature",
  "properties": {
    "iso:country":"GB",
    "sg:address":"Grounds Farm, Water Stratford",
    "sg:city":"Buckingham",
    "sg:classifiers":[
        {
            "category":"Farming",
            "subcategory":"Livestock Farm",
            "type":"Manufacturing & Wholesale Goods"
        }
    ],
    "sg:phone":"+44 1280 812327",
    "sg:postcode":"MK18 5DP",
    "sg:province":"Buckinghamshire",
    "sg:tags":[
        "others"
    ],
    "wof:name":"P L Hilsdon",
    "wof:placetype":"venue"
},
  "geometry": {"coordinates":[-1.0503690243,52.0060348511],"type":"Point"}
}