{
  "type": "Feature",
  "properties": {
    "iso:country":"GB",
    "sg:address":"The Old Vicarage, 234 Abbeydale Road South",
    "sg:city":"Sheffield",
    "sg:classifiers":[
        {
            "category":"Shopping",
            "subcategory":"Discount & Variety Stores",
            "type":"Retail Goods"
        }
    ],
    "sg:postcode":"S17 3LA",
    "sg:province":"Derbyshire",
    "sg:tags":[
        "cleaning",
        "supply"
    ],
    "wof:name":"Diamond Supplies Ltd",
    "wof:placetype":"venue"
},
  "geometry": {"coordinates":[-1.464544,53.38311],"type":"Point"}
}