{
  "type": "Feature",
  "properties": {
    "iso:country":"GB",
    "sg:address":"20 King St",
    "sg:city":"Great Yarmouth",
    "sg:classifiers":[
        {
            "category":"Home & Garden",
            "subcategory":"Household Appliances",
            "type":"Retail Goods"
        }
    ],
    "sg:phone":"+44 1493 332720",
    "sg:postcode":"NR30 2NZ",
    "sg:province":"Norfolk",
    "sg:tags":[
        "gas"
    ],
    "wof:name":"House of Heating",
    "wof:placetype":"venue"
},
  "geometry": {"coordinates":[1.7282340527,52.6062927246],"type":"Point"}
}