{
  "type": "Feature",
  "properties": {
    "addr:full":"Chestnut Rd Windermere Cumbria LA23 2AL",
    "addr:postcode":"la23 2al",
    "addr:street":"Chestnut Rd",
    "iso:country":"GB",
    "sg:address":"Chestnut Rd",
    "sg:city":"Windermere",
    "sg:classifiers":[
        {
            "category":"Taxi",
            "type":"Transportation"
        }
    ],
    "sg:phone":"+44 15394 45282",
    "sg:postcode":"LA23 2AL",
    "sg:province":"Cumbria",
    "sg:tags":[
        "mini",
        "cab"
    ],
    "wof:name":"Windermere Taxis",
    "wof:placetype":"venue"
},
  "geometry": {"coordinates":[-2.9059979916,54.3752479553],"type":"Point"}
}