{
  "type": "Feature",
  "properties": {
    "addr:full":"South Ribble Enterprise Park, Edward Street, Walton Le Dale Preston Lancashire PR5 4AQ",
    "addr:postcode":"pr5 4aq",
    "addr:street":"Edward Street",
    "iso:country":"GB",
    "sg:address":"South Ribble Enterprise Park, Edward Street, Walton Le Dale",
    "sg:city":"Preston",
    "sg:classifiers":[
        {
            "category":"Conference Center",
            "type":"Public Place"
        }
    ],
    "sg:phone":"+44 1772 200747",
    "sg:postcode":"PR5 4AQ",
    "sg:province":"Lancashire",
    "wof:name":"Locations Venue Search",
    "wof:placetype":"venue"
},
  "geometry": {"coordinates":[-2.672687,53.744968],"type":"Point"}
}