{
  "type": "Feature",
  "properties": {
    "addr:full":"The Street, Billingford Dereham Norfolk NR20 4RD",
    "addr:postcode":"nr20 4rd",
    "addr:street":"The Street",
    "iso:country":"GB",
    "sg:address":"The Street, Billingford",
    "sg:city":"Dereham",
    "sg:classifiers":[
        {
            "category":"Government",
            "subcategory":"Post Office",
            "type":"Public Place"
        }
    ],
    "sg:postcode":"NR20 4RD",
    "sg:province":"Norfolk",
    "wof:name":"Billingford Sub Post Office",
    "wof:placetype":"venue"
},
  "geometry": {"coordinates":[1.029785037,52.7467536926],"type":"Point"}
}