{
  "type": "Feature",
  "properties": {
    "addr:full":"1a Saltoun Road London Greater London SW2 1EN",
    "addr:housenumber":"1a",
    "addr:postcode":"sw2 1en",
    "addr:street":"Saltoun Road",
    "iso:country":"GB",
    "sg:address":"1a Saltoun Road",
    "sg:city":"London",
    "sg:classifiers":[
        {
            "category":"Manufacturing",
            "subcategory":"Wood Products",
            "type":"Manufacturing & Wholesale Goods"
        }
    ],
    "sg:postcode":"SW2 1EN",
    "sg:province":"Greater London",
    "sg:tags":[
        "maker",
        "cabinet"
    ],
    "wof:name":"Saltoun Road Woodworkers",
    "wof:placetype":"venue"
},
  "geometry": {"coordinates":[-0.11469,51.460445],"type":"Point"}
}