{
  "type": "Feature",
  "properties": {
    "iso:country":"GB",
    "sg:address":"9 Bosley Close",
    "sg:city":"Darwen",
    "sg:classifiers":[
        {
            "category":"Retail",
            "subcategory":"Repair Shop",
            "type":"Services"
        }
    ],
    "sg:postcode":"BB3 3LF",
    "sg:province":"Lancashire",
    "sg:tags":[
        "maintenance"
    ],
    "wof:name":"S T S Property Repairs",
    "wof:placetype":"venue"
},
  "geometry": {"coordinates":[-2.447736,53.690121],"type":"Point"}
}