{
  "type": "Feature",
  "properties": {
    "addr:full":"The Nook, Stelling Minnis Canterbury Kent CT4 6AQ",
    "addr:postcode":"ct4 6aq",
    "addr:street":"Stelling Minnis",
    "iso:country":"GB",
    "sg:address":"The Nook, Stelling Minnis",
    "sg:city":"Canterbury",
    "sg:classifiers":[
        {
            "category":"Professional",
            "subcategory":"Management & Consulting",
            "type":"Services"
        }
    ],
    "sg:phone":"+44 1227 709575",
    "sg:postcode":"CT4 6AQ",
    "sg:province":"Kent",
    "sg:tags":[
        "marketing",
        "consultant"
    ],
    "wof:name":"The Centre For Future Studies",
    "wof:placetype":"venue"
},
  "geometry": {"coordinates":[1.0686600208,51.1792640686],"type":"Point"}
}