{
  "type": "Feature",
  "properties": {
    "addr:full":"Stn Rd Tregaron Ceredigion SY25 6HU",
    "addr:postcode":"sy25 6hu",
    "addr:street":"Stn Rd",
    "iso:country":"GB",
    "sg:address":"Stn Rd",
    "sg:city":"Tregaron",
    "sg:classifiers":[
        {
            "category":"Travel",
            "subcategory":"Hotels & Motels",
            "type":"Entertainment"
        }
    ],
    "sg:postcode":"SY25 6HU",
    "sg:province":"Ceredigion",
    "wof:name":"Reidy,Cornelius",
    "wof:placetype":"venue"
},
  "geometry": {"coordinates":[-3.934749,52.220085],"type":"Point"}
}