{
  "type": "Feature",
  "properties": {
    "addr:full":"Unit 1, Darwen Street Preston Lancashire PR5 4DH",
    "addr:housenumber":"unit 1",
    "addr:postcode":"pr5 4dh",
    "addr:street":"Darwen Street",
    "iso:country":"GB",
    "sg:address":"Unit 1, Darwen Street",
    "sg:city":"Preston",
    "sg:classifiers":[
        {
            "category":"Sports & Exercise",
            "subcategory":"Race Track",
            "type":"Entertainment"
        }
    ],
    "sg:phone":"+44 1772 620532",
    "sg:postcode":"PR5 4DH",
    "sg:province":"Lancashire",
    "sg:tags":[
        "motor"
    ],
    "wof:name":"Pro-Tec Performance",
    "wof:placetype":"venue"
},
  "geometry": {"coordinates":[-2.644469,53.743164],"type":"Point"}
}