{
  "type": "Feature",
  "properties": {
    "addr:full":"112 Beechwood Road, Cumbernauld Glasgow Falkirk G67 2NP",
    "addr:housenumber":"112",
    "addr:postcode":"g67 2np",
    "addr:street":"Beechwood Road",
    "iso:country":"GB",
    "sg:address":"112 Beechwood Road, Cumbernauld",
    "sg:city":"Glasgow",
    "sg:classifiers":[
        {
            "category":"Building & Trades",
            "subcategory":"Construction",
            "type":"Services"
        }
    ],
    "sg:phone":"+44 1236 733395",
    "sg:postcode":"G67 2NP",
    "sg:province":"Falkirk",
    "sg:tags":[
        "decorator",
        "painter"
    ],
    "wof:name":"Andrew McEnroe",
    "wof:placetype":"venue"
},
  "geometry": {"coordinates":[-3.9904789925,55.9426956177],"type":"Point"}
}