{
  "type": "Feature",
  "properties": {
    "addr:full":"Unit 2, Crowhurst Hop Farm, Bullen Lane Tonbridge Kent TN12 5LP",
    "addr:housenumber":"unit 2 crowhurst hop farm",
    "addr:postcode":"tn12 5lp",
    "addr:street":"Bullen Lane",
    "iso:country":"GB",
    "sg:address":"Unit 2, Crowhurst Hop Farm, Bullen Lane",
    "sg:city":"Tonbridge",
    "sg:classifiers":[
        {
            "category":"Manufacturing",
            "subcategory":"Rubber & Plastics",
            "type":"Manufacturing & Wholesale Goods"
        }
    ],
    "sg:phone":"+44 1622 872657",
    "sg:postcode":"TN12 5LP",
    "sg:province":"Kent",
    "sg:tags":[
        "injection",
        "moulding"
    ],
    "wof:name":"Pirholite",
    "wof:placetype":"venue"
},
  "geometry": {"coordinates":[0.3789800107,51.2261810303],"type":"Point"}
}