{
  "type": "Feature",
  "properties": {
    "iso:country":"GB",
    "sg:address":"326 Margate Road",
    "sg:city":"Ramsgate",
    "sg:classifiers":[
        {
            "category":"Shopping",
            "subcategory":"Pharmacy",
            "type":"Retail Goods"
        }
    ],
    "sg:phone":"+44 1843 592286",
    "sg:postcode":"CT12 6SQ",
    "sg:province":"Kent",
    "sg:tags":[
        "pharmacist",
        "chemist"
    ],
    "wof:name":"Northwood Pharmacy",
    "wof:placetype":"venue"
},
  "geometry": {"coordinates":[1.401831,51.352638],"type":"Point"}
}