{
  "type": "Feature",
  "properties": {
    "addr:full":"London Road, Wollaston Wellingborough Bedfordshire NN29 7QS",
    "addr:postcode":"nn29 7qs",
    "addr:street":"London Road",
    "iso:country":"GB",
    "sg:address":"London Road, Wollaston",
    "sg:city":"Wellingborough",
    "sg:classifiers":[
        {
            "category":"Retail",
            "subcategory":"Auto Repair",
            "type":"Services"
        }
    ],
    "sg:postcode":"NN29 7QS",
    "sg:province":"Bedfordshire",
    "sg:tags":[
        "modification",
        "garage"
    ],
    "wof:name":"Thomas R & Revene A Pearsons",
    "wof:placetype":"venue"
},
  "geometry": {"coordinates":[-0.6770989895,52.2578735352],"type":"Point"}
}