{
  "type": "Feature",
  "properties": {
    "iso:country":"GB",
    "sg:address":"99 High Street",
    "sg:city":"Arbroath",
    "sg:classifiers":[
        {
            "category":"Home & Garden",
            "subcategory":"Furniture",
            "type":"Retail Goods"
        }
    ],
    "sg:phone":"+44 1307 465338",
    "sg:postcode":"DD11 1DT",
    "sg:province":"Angus",
    "wof:name":"D T Wilson & Sons Ltd.",
    "wof:placetype":"venue"
},
  "geometry": {"coordinates":[-2.5812649727,56.5587539673],"type":"Point"}
}