{
  "type": "Feature",
  "properties": {
    "iso:country":"GB",
    "sg:address":"37 Park Avenue North, Abington",
    "sg:city":"Northampton",
    "sg:classifiers":[
        {
            "category":"Professional",
            "subcategory":"Secretarial Services",
            "type":"Services"
        }
    ],
    "sg:postcode":"NN3 2HT",
    "sg:province":"Northamptonshire",
    "wof:name":"Accurate Typing & W P Services",
    "wof:placetype":"venue"
},
  "geometry": {"coordinates":[-0.870144,52.25238],"type":"Point"}
}