{
  "type": "Feature",
  "properties": {
    "iso:country":"GB",
    "sg:address":"Mitchell Industrial Estate, Southend, Thornton",
    "sg:city":"Kirkcaldy",
    "sg:classifiers":[
        {
            "category":"Building & Trades",
            "subcategory":"Plumbing",
            "type":"Services"
        }
    ],
    "sg:phone":"+44 1592 771264",
    "sg:postcode":"KY1 4DT",
    "sg:province":"Fife",
    "sg:tags":[
        "plumber",
        "heating"
    ],
    "wof:name":"John Taylor (Plumbers) Ltd.",
    "wof:placetype":"venue"
},
  "geometry": {"coordinates":[-3.144894,56.163685],"type":"Point"}
}