{
  "type": "Feature",
  "properties": {
    "iso:country":"GB",
    "sg:address":"Orleton",
    "sg:city":"Ludlow",
    "sg:classifiers":[
        {
            "category":"Bars & Pubs",
            "type":"Food & Drink"
        }
    ],
    "sg:phone":"+44 1584 831686",
    "sg:postcode":"SY8 4JB",
    "sg:province":"Herefordshire",
    "sg:tags":[
        "pubs",
        "inn"
    ],
    "wof:name":"Maidenhead Inn",
    "wof:placetype":"venue"
},
  "geometry": {"coordinates":[-2.754189,52.301071],"type":"Point"}
}