{
  "type": "Feature",
  "properties": {
    "iso:country":"GB",
    "sg:address":"Unit C4 Brymau One Estate, River Lane",
    "sg:city":"Chester",
    "sg:classifiers":[
        {
            "category":"Organizations",
            "subcategory":"Non-profit Organization",
            "type":"Services"
        }
    ],
    "sg:phone":"+44 1244 335059",
    "sg:postcode":"CH4 8RG",
    "sg:province":"Cheshire",
    "sg:tags":[
        "organisation",
        "voluntary",
        "charity"
    ],
    "wof:name":"Multiple Sclerosis Support Centre Ltd.",
    "wof:placetype":"venue"
},
  "geometry": {"coordinates":[-2.921871,53.181263],"type":"Point"}
}