{
  "type": "Feature",
  "properties": {
    "iso:country":"GB",
    "sg:address":"730 Anlaby Rd",
    "sg:city":"Hull",
    "sg:classifiers":[
        {
            "category":"Home & Garden",
            "subcategory":"Furniture",
            "type":"Retail Goods"
        }
    ],
    "sg:phone":"+44 1482 564456",
    "sg:postcode":"HU4 6BP",
    "sg:province":"East Riding of Yorkshire",
    "wof:name":"M T M",
    "wof:placetype":"venue"
},
  "geometry": {"coordinates":[-0.3926160038,53.745010376],"type":"Point"}
}