{
  "type": "Feature",
  "properties": {
    "addr:full":"Tithe Barn Road Wellingborough Northamptonshire NN8 1BN",
    "addr:housenumber":"tithe",
    "addr:postcode":"nn8 1bn",
    "addr:street":"Barn Road",
    "iso:country":"GB",
    "sg:address":"Tithe Barn Road",
    "sg:city":"Wellingborough",
    "sg:classifiers":[
        {
            "category":"Government",
            "subcategory":"Office",
            "type":"Public Place"
        }
    ],
    "sg:phone":"+44 1933 229777",
    "sg:postcode":"NN8 1BN",
    "sg:province":"Northamptonshire",
    "sg:tags":[
        "local"
    ],
    "wof:name":"Borough Council of Wellingborough",
    "wof:placetype":"venue"
},
  "geometry": {"coordinates":[-0.692695,52.300343],"type":"Point"}
}