{
  "type": "Feature",
  "properties": {
    "addr:full":"Bagshot Road Bracknell Berkshire RG12 9RB",
    "addr:postcode":"rg12 9rb",
    "addr:street":"Bagshot Road",
    "iso:country":"GB",
    "sg:address":"Bagshot Road",
    "sg:city":"Bracknell",
    "sg:classifiers":[
        {
            "category":"Restaurant",
            "type":"Food & Drink"
        }
    ],
    "sg:phone":"+44 1344 422444",
    "sg:postcode":"RG12 9RB",
    "sg:province":"Berkshire",
    "wof:name":"Horse & Groom",
    "wof:placetype":"venue"
},
  "geometry": {"coordinates":[-0.7510120273,51.4111595154],"type":"Point"}
}