{
  "type": "Feature",
  "properties": {
    "addr:full":"Brewers Yd, High St Sevenoaks Kent TN13 1LU",
    "addr:postcode":"tn13 1lu",
    "addr:street":"Yd High St",
    "iso:country":"GB",
    "sg:address":"Brewers Yd, High St",
    "sg:city":"Sevenoaks",
    "sg:classifiers":[
        {
            "category":"Retail",
            "subcategory":"Auto Repair",
            "type":"Services"
        }
    ],
    "sg:postcode":"TN13 1LU",
    "sg:province":"Kent",
    "sg:tags":[
        "modification",
        "garage"
    ],
    "wof:name":"Wiggins,Roger,",
    "wof:placetype":"venue"
},
  "geometry": {"coordinates":[0.1929389983,51.270198822],"type":"Point"}
}