{
  "type": "Feature",
  "properties": {
    "addr:full":"20 Woodside Close Colchester Essex CO4 3HD",
    "addr:housenumber":"20",
    "addr:postcode":"co4 3hd",
    "addr:street":"Woodside Close",
    "iso:country":"GB",
    "sg:address":"20 Woodside Close",
    "sg:city":"Colchester",
    "sg:classifiers":[
        {
            "category":"Home & Garden",
            "subcategory":"Household Appliances",
            "type":"Retail Goods"
        },
        {
            "category":"Building & Trades",
            "subcategory":"Electrical",
            "type":"Services"
        }
    ],
    "sg:postcode":"CO4 3HD",
    "sg:province":"Essex",
    "sg:tags":[
        "contractor",
        "refrigeration",
        "air conditioning"
    ],
    "wof:name":"Optimum Cooling Ltd.",
    "wof:placetype":"venue"
},
  "geometry": {"coordinates":[0.9347010255,51.8973922729],"type":"Point"}
}