{
  "type": "Feature",
  "properties": {
    "iso:country":"GB",
    "sg:address":"The Old Barn, Nagington Grange, Childs Ercall",
    "sg:city":"Market Drayton",
    "sg:classifiers":[
        {
            "category":"Shopping",
            "subcategory":"Antiques",
            "type":"Retail Goods"
        }
    ],
    "sg:phone":"+44 1952 840409",
    "sg:postcode":"TF9 2TW",
    "sg:province":"Shropshire",
    "wof:name":"Timothy John Gittins",
    "wof:placetype":"venue"
},
  "geometry": {"coordinates":[-2.48177,52.826061],"type":"Point"}
}