{
  "type": "Feature",
  "properties": {
    "iso:country":"GB",
    "sg:address":"Moat House Street",
    "sg:city":"Wigan",
    "sg:classifiers":[
        {
            "category":"Autos & Motor Vehicles",
            "subcategory":"Auto Supplies",
            "type":"Retail Goods"
        }
    ],
    "sg:phone":"+44 1942 322889",
    "sg:postcode":"WN2 2EH",
    "sg:province":"Lancashire",
    "sg:tags":[
        "tyre"
    ],
    "wof:name":"Williams Motors",
    "wof:placetype":"venue"
},
  "geometry": {"coordinates":[-2.599784,53.541996],"type":"Point"}
}