{
  "type": "Feature",
  "properties": {
    "addr:full":"35 St Catherines Dr Leeds West Yorkshire LS13 2LD",
    "addr:housenumber":"35",
    "addr:postcode":"ls13 2ld",
    "addr:street":"St Catherines Dr",
    "iso:country":"GB",
    "sg:address":"35 St Catherines Dr",
    "sg:city":"Leeds",
    "sg:classifiers":[
        {
            "category":"Personal",
            "type":"Services"
        }
    ],
    "sg:phone":"+44 113 257 2582",
    "sg:postcode":"LS13 2LD",
    "sg:province":"West Yorkshire",
    "sg:tags":[
        "wedding"
    ],
    "wof:name":"White Lady Wedding Car Hire",
    "wof:placetype":"venue"
},
  "geometry": {"coordinates":[-1.626173,53.819878],"type":"Point"}
}