{
  "type": "Feature",
  "properties": {
    "addr:full":"1a South Terrace, South Street Dorchester Dorset DT1 1DE",
    "addr:housenumber":"1a",
    "addr:postcode":"dt1 1de",
    "addr:street":"South Terrace South Street",
    "iso:country":"GB",
    "sg:address":"1a South Terrace, South Street",
    "sg:city":"Dorchester",
    "sg:classifiers":[
        {
            "category":"Communications",
            "type":"Services"
        },
        {
            "category":"Real Estate",
            "subcategory":"Architect",
            "type":"Services"
        }
    ],
    "sg:phone":"+44 1305 267120",
    "sg:postcode":"DT1 1DE",
    "sg:province":"Dorset",
    "sg:tags":[
        "telecommunication"
    ],
    "wof:name":"A & Q Partnership South West",
    "wof:placetype":"venue"
},
  "geometry": {"coordinates":[-2.441564,50.711906],"type":"Point"}
}