{
  "type": "Feature",
  "properties": {
    "iso:country":"GB",
    "sg:address":"Park Lodge, Derby Road, Hilton",
    "sg:city":"Derby",
    "sg:classifiers":[
        {
            "category":"Retail",
            "subcategory":"Auto Repair",
            "type":"Services"
        }
    ],
    "sg:phone":"+44 1283 733896",
    "sg:postcode":"DE65 5FP",
    "sg:province":"Derbyshire",
    "sg:tags":[
        "garage",
        "electrician",
        "related"
    ],
    "wof:name":"HARRISON AUTO ELECTRICAL SERVICES LTD",
    "wof:placetype":"venue"
},
  "geometry": {"coordinates":[-1.640199,52.872623],"type":"Point"}
}