{
  "type": "Feature",
  "properties": {
    "addr:full":"81 Candleriggs Glasgow Glasgow City G1 1LF",
    "addr:housenumber":"81",
    "addr:postcode":"g1 1lf",
    "addr:street":"Candleriggs",
    "iso:country":"GB",
    "sg:address":"81 Candleriggs",
    "sg:city":"Glasgow",
    "sg:classifiers":[
        {
            "category":"Personal",
            "subcategory":"Beauty Salon",
            "type":"Services"
        }
    ],
    "sg:postcode":"G1 1LF",
    "sg:province":"Glasgow City",
    "sg:tags":[
        "unisex",
        "hairdresser"
    ],
    "wof:name":"Wilson Youngs",
    "wof:placetype":"venue"
},
  "geometry": {"coordinates":[-4.245784,55.858685],"type":"Point"}
}