{
  "type": "Feature",
  "properties": {
    "addr:full":"Felling Bypass Gateshead Tyne and Wear NE10 0RF",
    "addr:postcode":"ne10 0rf",
    "addr:street":"Felling Bypass",
    "iso:country":"GB",
    "sg:address":"Felling Bypass",
    "sg:city":"Gateshead",
    "sg:classifiers":[
        {
            "category":"Autos & Motor Vehicles",
            "subcategory":"Fuel & Gas Station",
            "type":"Retail Goods"
        }
    ],
    "sg:phone":"+44 191 438 0369",
    "sg:postcode":"NE10 0RF",
    "sg:province":"Tyne and Wear",
    "sg:tags":[
        "hr",
        "petrol"
    ],
    "wof:name":"Jet Service Station",
    "wof:placetype":"venue"
},
  "geometry": {"coordinates":[-1.5684980154,54.9566726685],"type":"Point"}
}