{
  "type": "Feature",
  "properties": {
    "iso:country":"GB",
    "sg:address":"Burnaston, 86 Heddon Court Avenue, Cockfosters",
    "sg:city":"Barnet",
    "sg:classifiers":[
        {
            "category":"Health Services",
            "subcategory":"Doctor",
            "type":"Services"
        }
    ],
    "sg:phone":"+44 20 8449 4221",
    "sg:postcode":"EN4 9NG",
    "sg:province":"Hertfordshire",
    "sg:tags":[
        "practitioners"
    ],
    "wof:name":"J.M Gugenheim",
    "wof:placetype":"venue"
},
  "geometry": {"coordinates":[-0.15292,51.64608],"type":"Point"}
}