{
  "type": "Feature",
  "properties": {
    "addr:full":"59 Cove Road Gourock Inverclyde PA19 1RN",
    "addr:housenumber":"59",
    "addr:postcode":"pa19 1rn",
    "addr:street":"Cove Road",
    "iso:country":"GB",
    "sg:address":"59 Cove Road",
    "sg:city":"Gourock",
    "sg:classifiers":[
        {
            "category":"Travel",
            "subcategory":"Hotels & Motels",
            "type":"Entertainment"
        }
    ],
    "sg:phone":"+44 1475 634709",
    "sg:postcode":"PA19 1RN",
    "sg:province":"Inverclyde",
    "wof:name":"Albert Hotel",
    "wof:placetype":"venue"
},
  "geometry": {"coordinates":[-4.8087091446,55.9570999146],"type":"Point"}
}