{
  "type": "Feature",
  "properties": {
    "addr:full":"21 Station Road Kirknewton City of Edinburgh EH27 8BJ",
    "addr:housenumber":"21",
    "addr:postcode":"eh27 8bj",
    "addr:street":"Station Road",
    "iso:country":"GB",
    "sg:address":"21 Station Road",
    "sg:city":"Kirknewton",
    "sg:classifiers":[
        {
            "category":"Education",
            "subcategory":"School",
            "type":"Public Place"
        },
        {
            "category":"Government",
            "subcategory":"Office",
            "type":"Public Place"
        }
    ],
    "sg:phone":"+44 1506 881461",
    "sg:postcode":"EH27 8BJ",
    "sg:province":"City of Edinburgh",
    "sg:tags":[
        "local",
        "authority"
    ],
    "wof:name":"Kirknewton Primary School",
    "wof:placetype":"venue"
},
  "geometry": {"coordinates":[-3.429115057,55.8882484436],"type":"Point"}
}