{
  "type": "Feature",
  "properties": {
    "iso:country":"GB",
    "sg:address":"34 Arcot Park",
    "sg:city":"Sidmouth",
    "sg:classifiers":[
        {
            "category":"Military Area",
            "subcategory":"Air Force Base",
            "type":"Public Place"
        }
    ],
    "sg:postcode":"EX10 9HS",
    "sg:province":"Devon",
    "sg:tags":[
        "taxi",
        "hire",
        "private"
    ],
    "wof:name":"Select Cars",
    "wof:placetype":"venue"
},
  "geometry": {"coordinates":[-3.238477,50.692089],"type":"Point"}
}