{
  "type": "Feature",
  "properties": {
    "addr:full":"23 Napier Street, Hazel Gro Stockport Cheshire SK7 4EW",
    "addr:housenumber":"23",
    "addr:postcode":"sk7 4ew",
    "addr:street":"Napier Street",
    "iso:country":"GB",
    "sg:address":"23 Napier Street, Hazel Gro",
    "sg:city":"Stockport",
    "sg:classifiers":[
        {
            "category":"Organizations",
            "subcategory":"Membership Organization",
            "type":"Services"
        }
    ],
    "sg:postcode":"SK7 4EW",
    "sg:province":"Cheshire",
    "sg:tags":[
        "club"
    ],
    "wof:name":"The Hazel Grove & District Reform Club",
    "wof:placetype":"venue"
},
  "geometry": {"coordinates":[-2.122788,53.379787],"type":"Point"}
}