{
  "type": "Feature",
  "properties": {
    "iso:country":"GB",
    "sg:address":"Unit 4, Valley Business Centre",
    "sg:city":"High Wycombe",
    "sg:classifiers":[
        {
            "category":"Shopping",
            "subcategory":"Clothing, Apparel, & Fashions",
            "type":"Retail Goods"
        }
    ],
    "sg:phone":"+44 1494 444224",
    "sg:postcode":"HP13 6EQ",
    "sg:province":"Buckinghamshire",
    "sg:tags":[
        "sportswear"
    ],
    "wof:name":"Action Performance International Ltd.",
    "wof:placetype":"venue"
},
  "geometry": {"coordinates":[-0.739664,51.62878],"type":"Point"}
}