{
  "type": "Feature",
  "properties": {
    "addr:full":"441 Barlow Moor Road, Chorlton Manchester Cheshire M21 2AU",
    "addr:housenumber":"441",
    "addr:postcode":"m21 2au",
    "addr:street":"Barlow Moor Road",
    "iso:country":"GB",
    "sg:address":"441 Barlow Moor Road, Chorlton",
    "sg:city":"Manchester",
    "sg:classifiers":[
        {
            "category":"Real Estate",
            "subcategory":"Real Estate Agent",
            "type":"Services"
        }
    ],
    "sg:phone":"+44 161 860 4645",
    "sg:postcode":"M21 2AU",
    "sg:province":"Cheshire",
    "wof:name":"Acorn Group Holdings Ltd.",
    "wof:placetype":"venue"
},
  "geometry": {"coordinates":[-2.27179,53.43325],"type":"Point"}
}