{
  "type": "Feature",
  "properties": {
    "addr:full":"Goddards, London Rd, Sunningdale Ascot Berkshire SL5 0JN",
    "addr:postcode":"sl5 0jn",
    "addr:street":"London Rd",
    "iso:country":"GB",
    "sg:address":"Goddards, London Rd, Sunningdale",
    "sg:city":"Ascot",
    "sg:classifiers":[
        {
            "category":"Manufacturing",
            "subcategory":"Buildings",
            "type":"Manufacturing & Wholesale Goods"
        }
    ],
    "sg:postcode":"SL5 0JN",
    "sg:province":"Berkshire",
    "sg:tags":[
        "mobile",
        "home"
    ],
    "wof:name":"Chartridge Park Ltd",
    "wof:placetype":"venue"
},
  "geometry": {"coordinates":[-0.639009,51.403221],"type":"Point"}
}