{
  "type": "Feature",
  "properties": {
    "iso:country":"GB",
    "sg:address":"602 Central Way, North Feltham",
    "sg:city":"Feltham",
    "sg:classifiers":[
        {
            "category":"Freight",
            "type":"Transportation"
        }
    ],
    "sg:phone":"+44 870 725 2599",
    "sg:postcode":"TW14 0RX",
    "sg:province":"Greater London",
    "sg:tags":[
        "cargo",
        "handling",
        "forwarders"
    ],
    "wof:name":"Gazelle Cargo Ltd.",
    "wof:placetype":"venue"
},
  "geometry": {"coordinates":[-0.404789,51.462105],"type":"Point"}
}