{
  "type": "Feature",
  "properties": {
    "iso:country":"GB",
    "sg:address":"23 Hay Lane",
    "sg:city":"London",
    "sg:classifiers":[
        {
            "category":"Bars & Pubs",
            "type":"Food & Drink"
        }
    ],
    "sg:phone":"+44 20 8206 2528",
    "sg:postcode":"NW9 0NH",
    "sg:province":"Greater London",
    "sg:tags":[
        "pubs",
        "inn"
    ],
    "wof:name":"Hartnett Public House",
    "wof:placetype":"venue"
},
  "geometry": {"coordinates":[-0.2625289857,51.5883255005],"type":"Point"}
}