{
  "type": "Feature",
  "properties": {
    "iso:country":"GB",
    "sg:address":"24 St Georges Drive, Brinsworth",
    "sg:city":"Rotherham",
    "sg:classifiers":[
        {
            "category":"Professional",
            "subcategory":"Engineering",
            "type":"Services"
        }
    ],
    "sg:postcode":"S60 5NG",
    "sg:province":"South Yorkshire",
    "wof:name":"Casey Brothers Ltd.",
    "wof:placetype":"venue"
},
  "geometry": {"coordinates":[-1.3782609701,53.404460907],"type":"Point"}
}