{
  "type": "Feature",
  "properties": {
    "addr:full":"28 Trojan Centre, Finedon Road Industrial Estate Wellingborough Northamptonshire NN8 4ST",
    "addr:housenumber":"28",
    "addr:postcode":"nn8 4st",
    "addr:street":"Trojan Centre Finedon Road Industrial Estate",
    "iso:country":"GB",
    "sg:address":"28 Trojan Centre, Finedon Road Industrial Estate",
    "sg:city":"Wellingborough",
    "sg:classifiers":[
        {
            "category":"Autos & Motor Vehicles",
            "subcategory":"Fuel & Gas Station",
            "type":"Retail Goods"
        },
        {
            "category":"Wholesale",
            "subcategory":"Machinery & Supplies",
            "type":"Manufacturing & Wholesale Goods"
        }
    ],
    "sg:phone":"+44 1933 226200",
    "sg:postcode":"NN8 4ST",
    "sg:province":"Northamptonshire",
    "sg:tags":[
        "pump",
        "sale",
        "servicing"
    ],
    "wof:name":"C D R  Pumps Uk Ltd.",
    "wof:placetype":"venue"
},
  "geometry": {"coordinates":[-0.6962959766,52.3024215698],"type":"Point"}
}