{
  "type": "Feature",
  "properties": {
    "addr:full":"Tanner Cottage, Berrick Salome Wallingford Oxfordshire OX10 6JN",
    "addr:housenumber":"berrick salome",
    "addr:postcode":"wallingford;ox10 6jn",
    "iso:country":"GB",
    "sg:address":"Tanner Cottage, Berrick Salome",
    "sg:city":"Wallingford",
    "sg:classifiers":[
        {
            "category":"Real Estate",
            "subcategory":"Architect",
            "type":"Services"
        }
    ],
    "sg:postcode":"OX10 6JN",
    "sg:province":"Oxfordshire",
    "sg:tags":[
        "architectural"
    ],
    "wof:name":"Tanner Cottage Architectural Designs Consultancy",
    "wof:placetype":"venue"
},
  "geometry": {"coordinates":[-1.1034940481,51.6453475952],"type":"Point"}
}