{
  "type": "Feature",
  "properties": {
    "iso:country":"GB",
    "sg:address":"No 4 Birth, Chatham Docks",
    "sg:city":"Chatham",
    "sg:classifiers":[
        {
            "category":"Freight",
            "type":"Transportation"
        }
    ],
    "sg:phone":"+44 1634 827754",
    "sg:postcode":"ME4 4SP",
    "sg:province":"Kent",
    "sg:tags":[
        "cargo",
        "handling",
        "forwarders"
    ],
    "wof:name":"North Kent Shipping & Chartering Ltd.",
    "wof:placetype":"venue"
},
  "geometry": {"coordinates":[0.52244,51.381889],"type":"Point"}
}