{
  "type": "Feature",
  "properties": {
    "addr:full":"50 Hertford Street Coventry West Midlands CV1 1LB",
    "addr:housenumber":"50",
    "addr:postcode":"cv1 1lb",
    "addr:street":"Hertford Street",
    "iso:country":"GB",
    "sg:address":"50 Hertford Street",
    "sg:city":"Coventry",
    "sg:classifiers":[
        {
            "category":"Professional",
            "subcategory":"Lawyer & Legal Services",
            "type":"Services"
        }
    ],
    "sg:phone":"+44 24 7655 5521",
    "sg:postcode":"CV1 1LB",
    "sg:province":"West Midlands",
    "sg:tags":[
        "solicitor"
    ],
    "wof:name":"Tustain Jones & Co",
    "wof:placetype":"venue"
},
  "geometry": {"coordinates":[-1.5112890005,52.4068565369],"type":"Point"}
}