{
  "type": "Feature",
  "properties": {
    "addr:full":"51 High St London Greater London W3 6ND",
    "addr:housenumber":"51",
    "addr:postcode":"w3 6nd",
    "addr:street":"High St",
    "iso:country":"GB",
    "sg:address":"51 High St",
    "sg:city":"London",
    "sg:classifiers":[
        {
            "category":"Food & Beverages",
            "subcategory":"Meat & Fish",
            "type":"Retail Goods"
        }
    ],
    "sg:postcode":"W3 6ND",
    "sg:province":"Greater London",
    "sg:tags":[
        "chip"
    ],
    "wof:name":"Sangaih,Addrian,",
    "wof:placetype":"venue"
},
  "geometry": {"coordinates":[-0.2664099932,51.5065422058],"type":"Point"}
}