{
  "type": "Feature",
  "properties": {
    "addr:full":"43 Cowick Street Exeter Devon EX4 1AP",
    "addr:housenumber":"43",
    "addr:postcode":"ex4 1ap",
    "addr:street":"Cowick Street",
    "iso:country":"GB",
    "sg:address":"43 Cowick Street",
    "sg:city":"Exeter",
    "sg:classifiers":[
        {
            "category":"Shopping",
            "subcategory":"Thrift Store",
            "type":"Retail Goods"
        }
    ],
    "sg:phone":"+44 1392 270563",
    "sg:postcode":"EX4 1AP",
    "sg:province":"Devon",
    "sg:tags":[
        "shop",
        "charity"
    ],
    "wof:name":"Oxfam",
    "wof:placetype":"venue"
},
  "geometry": {"coordinates":[-3.54169,50.716103],"type":"Point"}
}