{
  "type": "Feature",
  "properties": {
    "iso:country":"GB",
    "sg:address":"Beckingham Business Park, Tolleshunt Major",
    "sg:city":"Maldon",
    "sg:classifiers":[
        {
            "category":"Military Area",
            "subcategory":"Army Base",
            "type":"Public Place"
        }
    ],
    "sg:phone":"+44 1621 862100",
    "sg:postcode":"CM9 8LZ",
    "sg:province":"Essex",
    "sg:tags":[
        "mnfr",
        "printed",
        "circuit"
    ],
    "wof:name":"Autoroute Circuits",
    "wof:placetype":"venue"
},
  "geometry": {"coordinates":[0.753765,51.769272],"type":"Point"}
}