{
  "type": "Feature",
  "properties": {
    "addr:full":"33 Apollo Way Bootle Merseyside L30 7PH",
    "addr:housenumber":"33",
    "addr:postcode":"l30 7ph",
    "addr:street":"Apollo Way",
    "iso:country":"GB",
    "sg:address":"33 Apollo Way",
    "sg:city":"Bootle",
    "sg:classifiers":[
        {
            "category":"Retail",
            "subcategory":"Driving School",
            "type":"Services"
        }
    ],
    "sg:phone":"+44 151 531 0109",
    "sg:postcode":"L30 7PH",
    "sg:province":"Merseyside",
    "wof:name":"Apollo Driving School",
    "wof:placetype":"venue"
},
  "geometry": {"coordinates":[-2.96519,53.491489],"type":"Point"}
}