{
  "type": "Feature",
  "properties": {
    "iso:country":"GB",
    "sg:address":"6 Quinton Parade",
    "sg:city":"Coventry",
    "sg:classifiers":[
        {
            "category":"Professional",
            "subcategory":"Engineering",
            "type":"Services"
        },
        {
            "category":"Professional",
            "subcategory":"Detective & Security Services",
            "type":"Services"
        }
    ],
    "sg:postcode":"CV3 5HW",
    "sg:province":"Warwickshire",
    "sg:tags":[
        "burglar",
        "alarm",
        "system",
        "contractor",
        "electrical",
        "engineer"
    ],
    "wof:name":"T V M Systems U K",
    "wof:placetype":"venue"
},
  "geometry": {"coordinates":[-1.506876,52.393379],"type":"Point"}
}