{
  "type": "Feature",
  "properties": {
    "addr:full":"7 Cobbetts Mead Haywards Heath East Sussex RH16 3TQ",
    "addr:housenumber":"7",
    "addr:postcode":"rh16 3tq",
    "addr:street":"Cobbetts Mead",
    "iso:country":"GB",
    "sg:address":"7 Cobbetts Mead",
    "sg:city":"Haywards Heath",
    "sg:classifiers":[
        {
            "category":"Professional",
            "subcategory":"Employment Agencies",
            "type":"Services"
        }
    ],
    "sg:postcode":"RH16 3TQ",
    "sg:province":"East Sussex",
    "sg:tags":[
        "consultant"
    ],
    "wof:name":"Page Partnership",
    "wof:placetype":"venue"
},
  "geometry": {"coordinates":[-0.0778409988,50.9949378967],"type":"Point"}
}