{
  "type": "Feature",
  "properties": {
    "iso:country":"GB",
    "sg:address":"Unit 27 Eastern Avenue Trading Estate, Eastern Avenue",
    "sg:city":"Gloucester",
    "sg:classifiers":[
        {
            "category":"Manufacturing",
            "subcategory":"Rubber & Plastics",
            "type":"Manufacturing & Wholesale Goods"
        }
    ],
    "sg:phone":"+44 1452 300102",
    "sg:postcode":"GL4 3SJ",
    "sg:province":"Gloucestershire",
    "sg:tags":[
        "product"
    ],
    "wof:name":"Easelok Ltd.",
    "wof:placetype":"venue"
},
  "geometry": {"coordinates":[-2.213558,51.86356],"type":"Point"}
}