{
  "type": "Feature",
  "properties": {
    "addr:full":"461 Bethnal Green Road London Greater London E2 9QH",
    "addr:housenumber":"461",
    "addr:postcode":"e2 9qh",
    "addr:street":"Bethnal Green Road",
    "iso:country":"GB",
    "sg:address":"461 Bethnal Green Road",
    "sg:city":"London",
    "sg:classifiers":[
        {
            "category":"Sports & Exercise",
            "subcategory":"Gym",
            "type":"Entertainment"
        }
    ],
    "sg:phone":"+44 20 7613 1631",
    "sg:postcode":"E2 9QH",
    "sg:province":"Greater London",
    "sg:tags":[
        "club",
        "fitness",
        "health",
        "centre"
    ],
    "wof:name":"Body Lines Health Club",
    "wof:placetype":"venue"
},
  "geometry": {"coordinates":[-0.057386,51.527405],"type":"Point"}
}