{
  "type": "Feature",
  "properties": {
    "addr:full":"3 The Parade, Stourbridge Road Kidderminster Staffordshire DY10 2UJ",
    "addr:housenumber":"3",
    "addr:postcode":"dy10 2uj",
    "addr:street":"The Parade Stourbridge Road",
    "iso:country":"GB",
    "sg:address":"3 The Parade, Stourbridge Road",
    "sg:city":"Kidderminster",
    "sg:classifiers":[
        {
            "category":"Food & Beverages",
            "subcategory":"Liquor & Beverages",
            "type":"Retail Goods"
        }
    ],
    "sg:phone":"+44 1562 755206",
    "sg:postcode":"DY10 2UJ",
    "sg:province":"Staffordshire",
    "sg:tags":[
        "beer",
        "spirit",
        "wines"
    ],
    "wof:name":"Broadwaters Store & Off License",
    "wof:placetype":"venue"
},
  "geometry": {"coordinates":[-2.2460749149,52.3928794861],"type":"Point"}
}