{
  "type": "Feature",
  "properties": {
    "addr:full":"3 Green Walk Leicester Leicestershire LE3 6SE",
    "addr:housenumber":"3",
    "addr:postcode":"le3 6se",
    "addr:street":"Green Walk",
    "iso:country":"GB",
    "sg:address":"3 Green Walk",
    "sg:city":"Leicester",
    "sg:classifiers":[
        {
            "category":"Home & Garden",
            "subcategory":"Hardware",
            "type":"Retail Goods"
        }
    ],
    "sg:phone":"+44 116 291 0077",
    "sg:postcode":"LE3 6SE",
    "sg:province":"Leicestershire",
    "wof:name":"S M Supplies",
    "wof:placetype":"venue"
},
  "geometry": {"coordinates":[-1.18731,52.632984],"type":"Point"}
}