{
  "type": "Feature",
  "properties": {
    "addr:full":"54 Grant Road Croydon Surrey CR0 6PG",
    "addr:housenumber":"54",
    "addr:postcode":"cr0 6pg",
    "addr:street":"Grant Road",
    "iso:country":"GB",
    "sg:address":"54 Grant Road",
    "sg:city":"Croydon",
    "sg:classifiers":[
        {
            "category":"Retail",
            "subcategory":"Photofinishing",
            "type":"Services"
        }
    ],
    "sg:phone":"+44 20 8655 3218",
    "sg:postcode":"CR0 6PG",
    "sg:province":"Surrey",
    "sg:tags":[
        "photographic",
        "processor"
    ],
    "wof:name":"John Baker Photography",
    "wof:placetype":"venue"
},
  "geometry": {"coordinates":[-0.0780479982,51.3805046082],"type":"Point"}
}