{
  "type": "Feature",
  "properties": {
    "iso:country":"GB",
    "sg:address":"37 Market Place",
    "sg:city":"Boston",
    "sg:classifiers":[
        {
            "category":"Shopping",
            "subcategory":"Clothing, Apparel, & Fashions",
            "type":"Retail Goods"
        }
    ],
    "sg:phone":"+44 1205 350369",
    "sg:postcode":"PE21 6NG",
    "sg:province":"Lincolnshire",
    "sg:tags":[
        "shop"
    ],
    "wof:name":"Michelle",
    "wof:placetype":"venue"
},
  "geometry": {"coordinates":[-0.0234639999,52.9772186279],"type":"Point"}
}