{
  "type": "Feature",
  "properties": {
    "iso:country":"GB",
    "sg:address":"Ipsley Street",
    "sg:city":"Redditch",
    "sg:classifiers":[
        {
            "category":"Professional",
            "subcategory":"Detective & Security Services",
            "type":"Services"
        }
    ],
    "sg:phone":"+44 1527 65344",
    "sg:postcode":"B98 7AR",
    "sg:province":"Warwickshire",
    "wof:name":"Masterguard Security Services Ltd.",
    "wof:placetype":"venue"
},
  "geometry": {"coordinates":[-1.9368089437,52.3047218323],"type":"Point"}
}