{
  "type": "Feature",
  "properties": {
    "iso:country":"GB",
    "sg:address":"Heath Hill Avenue",
    "sg:city":"Brighton",
    "sg:classifiers":[
        {
            "category":"Education",
            "subcategory":"School",
            "type":"Public Place"
        },
        {
            "category":"Government",
            "subcategory":"Office",
            "type":"Public Place"
        }
    ],
    "sg:phone":"+44 1273 681292",
    "sg:postcode":"BN2 4JP",
    "sg:province":"East Sussex",
    "sg:tags":[
        "local",
        "authority"
    ],
    "wof:name":"Bevendean Primary School",
    "wof:placetype":"venue"
},
  "geometry": {"coordinates":[-0.0946799964,50.843170166],"type":"Point"}
}