{
  "type": "Feature",
  "properties": {
    "addr:full":"Great Hucklow Buxton Derbyshire SK17 8RF",
    "addr:postcode":"sk17 8rf",
    "iso:country":"GB",
    "sg:address":"Great Hucklow",
    "sg:city":"Buxton",
    "sg:classifiers":[
        {
            "category":"Bars & Pubs",
            "type":"Food & Drink"
        }
    ],
    "sg:phone":"+44 1298 871246",
    "sg:postcode":"SK17 8RF",
    "sg:province":"Derbyshire",
    "sg:tags":[
        "pubs",
        "inn"
    ],
    "wof:name":"Queen Anne Inn",
    "wof:placetype":"venue"
},
  "geometry": {"coordinates":[-1.73598,53.298019],"type":"Point"}
}