{
  "type": "Feature",
  "properties": {
    "iso:country":"GB",
    "sg:address":"Howley Farm, Buckland Brewer",
    "sg:city":"Bideford",
    "sg:classifiers":[
        {
            "category":"Farming",
            "subcategory":"Livestock Farm",
            "type":"Manufacturing & Wholesale Goods"
        }
    ],
    "sg:phone":"+44 1237 451252",
    "sg:postcode":"EX39 5EN",
    "sg:province":"Devon",
    "sg:tags":[
        "others"
    ],
    "wof:name":"A A Dunn",
    "wof:placetype":"venue"
},
  "geometry": {"coordinates":[-4.251404,50.964294],"type":"Point"}
}