{
  "type": "Feature",
  "properties": {
    "addr:full":"Unit 3a, Wellington Road Alcester Warwickshire B50 4JH",
    "addr:housenumber":"unit 3a",
    "addr:postcode":"b50 4jh",
    "addr:street":"Wellington Road",
    "iso:country":"GB",
    "sg:address":"Unit 3a, Wellington Road",
    "sg:city":"Alcester",
    "sg:classifiers":[
        {
            "category":"Shopping",
            "subcategory":"Clothing, Apparel, & Fashions",
            "type":"Retail Goods"
        }
    ],
    "sg:phone":"+44 1789 490000",
    "sg:postcode":"B50 4JH",
    "sg:province":"Warwickshire",
    "sg:tags":[
        "clothing"
    ],
    "wof:name":"Simpson Rare Jeans Ltd.",
    "wof:placetype":"venue"
},
  "geometry": {"coordinates":[-1.8502229452,52.1731033325],"type":"Point"}
}