{
  "type": "Feature",
  "properties": {
    "addr:full":"Unit A389 Western Avenue, Thames Valley Trading Estate Gateshead Tyne and Wear NE11 0SZ",
    "addr:housenumber":"a389",
    "addr:postcode":"ne11 0sz",
    "addr:street":"Western Avenue Thames Valley Trading Estate",
    "iso:country":"GB",
    "sg:address":"Unit A389 Western Avenue, Thames Valley Trading Estate",
    "sg:city":"Gateshead",
    "sg:classifiers":[
        {
            "category":"Home & Garden",
            "subcategory":"Building Materials",
            "type":"Retail Goods"
        }
    ],
    "sg:phone":"+44 191 482 1261",
    "sg:postcode":"NE11 0SZ",
    "sg:province":"Tyne and Wear",
    "sg:tags":[
        "insulation",
        "installers"
    ],
    "wof:name":"Kitsons Insulation Products Ltd.",
    "wof:placetype":"venue"
},
  "geometry": {"coordinates":[-1.6203989983,54.9331130981],"type":"Point"}
}