{
  "type": "Feature",
  "properties": {
    "iso:country":"GB",
    "sg:address":"40 The Hop Exchange, Southwark Street",
    "sg:city":"London",
    "sg:classifiers":[
        {
            "category":"Shopping",
            "subcategory":"Pets & Pet Supplies",
            "type":"Retail Goods"
        },
        {
            "category":"Food & Beverages",
            "subcategory":"Supermarket",
            "type":"Retail Goods"
        }
    ],
    "sg:phone":"+44 20 7480 5779",
    "sg:postcode":"SE1 1TY",
    "sg:province":"Greater London",
    "sg:tags":[
        "frozen"
    ],
    "wof:name":"H J Lea & Sons Ltd.",
    "wof:placetype":"venue"
},
  "geometry": {"coordinates":[-0.0909600034,51.5047798157],"type":"Point"}
}