{
  "type": "Feature",
  "properties": {
    "addr:full":"Pallet Hill Farm Penrith Cumbria CA11 0BY",
    "addr:postcode":"ca11 0by",
    "addr:street":"Pallet Hill Farm Penrith",
    "iso:country":"GB",
    "sg:address":"Pallet Hill Farm",
    "sg:city":"Penrith",
    "sg:classifiers":[
        {
            "category":"Farming",
            "subcategory":"Livestock Farm",
            "type":"Manufacturing & Wholesale Goods"
        },
        {
            "category":"Farming",
            "subcategory":"Farm",
            "type":"Manufacturing & Wholesale Goods"
        }
    ],
    "sg:postcode":"CA11 0BY",
    "sg:province":"Cumbria",
    "sg:tags":[
        "mixed",
        "crop",
        "others"
    ],
    "wof:name":"K M & R M Preston",
    "wof:placetype":"venue"
},
  "geometry": {"coordinates":[-2.757469,54.664303],"type":"Point"}
}