{
  "type": "Feature",
  "properties": {
    "addr:full":"78 Wathen Road Leamington Spa Warwickshire CV32 5UZ",
    "addr:housenumber":"78",
    "addr:postcode":"cv32 5uz",
    "addr:street":"Wathen Road",
    "iso:country":"GB",
    "sg:address":"78 Wathen Road",
    "sg:city":"Leamington Spa",
    "sg:classifiers":[
        {
            "category":"Building & Trades",
            "subcategory":"Plumbing",
            "type":"Services"
        }
    ],
    "sg:phone":"+44 1926 312800",
    "sg:postcode":"CV32 5UZ",
    "sg:province":"Warwickshire",
    "sg:tags":[
        "central",
        "heating"
    ],
    "wof:name":"Key Heating",
    "wof:placetype":"venue"
},
  "geometry": {"coordinates":[-1.526114,52.29744],"type":"Point"}
}