{
  "type": "Feature",
  "properties": {
    "addr:full":"558 Felixstowe Road Ipswich Suffolk IP3 8SY",
    "addr:housenumber":"558",
    "addr:postcode":"ip3 8sy",
    "addr:street":"Felixstowe Road",
    "iso:country":"GB",
    "sg:address":"558 Felixstowe Road",
    "sg:city":"Ipswich",
    "sg:classifiers":[
        {
            "category":"Education",
            "subcategory":"Music School",
            "type":"Public Place"
        },
        {
            "category":"Manufacturing",
            "subcategory":"Petroleum Products",
            "type":"Manufacturing & Wholesale Goods"
        }
    ],
    "sg:phone":"+44 1473 272445",
    "sg:postcode":"IP3 8SY",
    "sg:province":"Suffolk",
    "sg:tags":[
        "conservatory",
        "glazing",
        "double"
    ],
    "wof:name":"Ideal Homes Centre",
    "wof:placetype":"venue"
},
  "geometry": {"coordinates":[1.205057025,52.0361213684],"type":"Point"}
}