{
  "type": "Feature",
  "properties": {
    "iso:country":"GB",
    "sg:address":"13-15 Pentrebane Street",
    "sg:city":"Caerphilly",
    "sg:classifiers":[
        {
            "category":"Fast Food",
            "type":"Food & Drink"
        }
    ],
    "sg:phone":"+44 29 2088 8166",
    "sg:postcode":"CF83 1FR",
    "sg:province":"Caerphilly",
    "sg:tags":[
        "away",
        "take"
    ],
    "wof:name":"Great Wall",
    "wof:placetype":"venue"
},
  "geometry": {"coordinates":[-3.221043,51.572994],"type":"Point"}
}