{
  "type": "Feature",
  "properties": {
    "addr:full":"Unit 23, The Forum Centre Dundee Dundee City DD1 1DQ",
    "addr:housenumber":"unit 23 the forum centre",
    "addr:postcode":"dd1 1dq",
    "iso:country":"GB",
    "sg:address":"Unit 23, The Forum Centre",
    "sg:city":"Dundee",
    "sg:classifiers":[
        {
            "category":"Building & Trades",
            "subcategory":"Locksmith",
            "type":"Services"
        }
    ],
    "sg:phone":"+44 1382 224897",
    "sg:postcode":"DD1 1DQ",
    "sg:province":"Dundee City",
    "sg:tags":[
        "cutting",
        "key"
    ],
    "wof:name":"The Key Centre",
    "wof:placetype":"venue"
},
  "geometry": {"coordinates":[-2.967609,56.461376],"type":"Point"}
}