{
  "type": "Feature",
  "properties": {
    "iso:country":"GB",
    "sg:address":"34 Broad Street",
    "sg:city":"Fraserburgh",
    "sg:classifiers":[
        {
            "category":"Banks & Credit Unions",
            "subcategory":"Bank",
            "type":"Services"
        }
    ],
    "sg:phone":"+44 1346 513393",
    "sg:postcode":"AB43 5AH",
    "sg:province":"Aberdeenshire",
    "wof:name":"Clydesdale Bank Plc",
    "wof:placetype":"venue"
},
  "geometry": {"coordinates":[-2.005238,57.692745],"type":"Point"}
}