{
  "type": "Feature",
  "properties": {
    "iso:country":"GB",
    "sg:address":"The Old Fire Stn, Kirkland Dr",
    "sg:city":"Leven",
    "sg:classifiers":[
        {
            "category":"Retail",
            "subcategory":"Auto Repair",
            "type":"Services"
        }
    ],
    "sg:postcode":"KY8 3HX",
    "sg:province":"Fife",
    "sg:tags":[
        "modification",
        "garage"
    ],
    "wof:name":"Durward Motor Engineers",
    "wof:placetype":"venue"
},
  "geometry": {"coordinates":[-2.998787,56.194401],"type":"Point"}
}