{
  "type": "Feature",
  "properties": {
    "addr:full":"9 Sulgrave Rd Leicester Leicestershire LE5 0LH",
    "addr:housenumber":"9",
    "addr:postcode":"le5 0lh",
    "addr:street":"Sulgrave Rd",
    "iso:country":"GB",
    "sg:address":"9 Sulgrave Rd",
    "sg:city":"Leicester",
    "sg:classifiers":[
        {
            "category":"Retail",
            "subcategory":"Photofinishing",
            "type":"Services"
        }
    ],
    "sg:phone":"+44 116 246 0458",
    "sg:postcode":"LE5 0LH",
    "sg:province":"Leicestershire",
    "sg:tags":[
        "photographic",
        "processor"
    ],
    "wof:name":"East Park Studios",
    "wof:placetype":"venue"
},
  "geometry": {"coordinates":[-1.1004920006,52.6424446106],"type":"Point"}
}