{
  "type": "Feature",
  "properties": {
    "addr:full":"2 Garland Rd Poole Dorset BH15 2LA",
    "addr:housenumber":"2",
    "addr:postcode":"bh15 2la",
    "addr:street":"Garland Rd",
    "iso:country":"GB",
    "sg:address":"2 Garland Rd",
    "sg:city":"Poole",
    "sg:classifiers":[
        {
            "category":"Autos & Motor Vehicles",
            "subcategory":"Auto Supplies",
            "type":"Retail Goods"
        }
    ],
    "sg:phone":"+44 1202 681711",
    "sg:postcode":"BH15 2LA",
    "sg:province":"Dorset",
    "sg:tags":[
        "windscreen"
    ],
    "wof:name":"Novus Windscreen Repairs",
    "wof:placetype":"venue"
},
  "geometry": {"coordinates":[-1.970715,50.723595],"type":"Point"}
}