{
  "type": "Feature",
  "properties": {
    "iso:country":"GB",
    "sg:address":"215 Godstone Road",
    "sg:city":"Whyteleafe",
    "sg:classifiers":[
        {
            "category":"Restaurant",
            "type":"Food & Drink"
        }
    ],
    "sg:phone":"+44 1883 622443",
    "sg:postcode":"CR3 0EL",
    "sg:province":"Surrey",
    "wof:name":"Casa Pepe Restaurant",
    "wof:placetype":"venue"
},
  "geometry": {"coordinates":[-0.079721,51.30904],"type":"Point"}
}