{
  "type": "Feature",
  "properties": {
    "iso:country":"GB",
    "sg:address":"Shaw House, 27 West Way",
    "sg:city":"Oxford",
    "sg:classifiers":[
        {
            "category":"Professional",
            "subcategory":"Business Services",
            "type":"Services"
        }
    ],
    "sg:phone":"+44 1865 242332",
    "sg:postcode":"OX2 0QH",
    "sg:province":"Oxfordshire",
    "sg:tags":[
        "answering"
    ],
    "wof:name":"Healthcall",
    "wof:placetype":"venue"
},
  "geometry": {"coordinates":[-1.294431,51.753067],"type":"Point"}
}