{
  "type": "Feature",
  "properties": {
    "addr:full":"Brynrhea Farm, Deri Bargoed Caerphilly CF81 9NT",
    "addr:postcode":"cf81 9nt",
    "iso:country":"GB",
    "sg:address":"Brynrhea Farm, Deri",
    "sg:city":"Bargoed",
    "sg:classifiers":[
        {
            "category":"Home & Garden",
            "subcategory":"Garden Supply",
            "type":"Retail Goods"
        },
        {
            "category":"Farming",
            "subcategory":"Livestock Farm",
            "type":"Manufacturing & Wholesale Goods"
        }
    ],
    "sg:phone":"+44 1443 820147",
    "sg:postcode":"CF81 9NT",
    "sg:province":"Caerphilly",
    "sg:tags":[
        "bulb",
        "grower",
        "others"
    ],
    "wof:name":"Ernest Hone",
    "wof:placetype":"venue"
},
  "geometry": {"coordinates":[-3.2618350983,51.7073059082],"type":"Point"}
}