{
  "type": "Feature",
  "properties": {
    "addr:full":"248 Smithdown Road Liverpool Merseyside L15 5AH",
    "addr:housenumber":"248",
    "addr:postcode":"l15 5ah",
    "addr:street":"Smithdown Road",
    "iso:country":"GB",
    "sg:address":"248 Smithdown Road",
    "sg:city":"Liverpool",
    "sg:classifiers":[
        {
            "category":"Food & Beverages",
            "subcategory":"Specialty",
            "type":"Retail Goods"
        }
    ],
    "sg:phone":"+44 151 734 2425",
    "sg:postcode":"L15 5AH",
    "sg:province":"Merseyside",
    "sg:tags":[
        "product",
        "health"
    ],
    "wof:name":"Natures Gate",
    "wof:placetype":"venue"
},
  "geometry": {"coordinates":[-2.925874,53.389774],"type":"Point"}
}