{
  "type": "Feature",
  "properties": {
    "addr:full":"25 Main Street, Lumphinnans Cowdenbeath Fife KY4 9HG",
    "addr:housenumber":"25",
    "addr:postcode":"ky4 9hg",
    "addr:street":"Main Street",
    "iso:country":"GB",
    "sg:address":"25 Main Street, Lumphinnans",
    "sg:city":"Cowdenbeath",
    "sg:classifiers":[
        {
            "category":"Education",
            "subcategory":"School",
            "type":"Public Place"
        },
        {
            "category":"Education",
            "subcategory":"University",
            "type":"Public Place"
        }
    ],
    "sg:phone":"+44 1383 510774",
    "sg:postcode":"KY4 9HG",
    "sg:province":"Fife",
    "sg:tags":[
        "adult",
        "location"
    ],
    "wof:name":"Workers Educational Association",
    "wof:placetype":"venue"
},
  "geometry": {"coordinates":[-3.337698,56.118382],"type":"Point"}
}