{
  "type": "Feature",
  "properties": {
    "iso:country":"GB",
    "sg:address":"29 Taptonville Rd",
    "sg:city":"Sheffield",
    "sg:classifiers":[
        {
            "category":"Health Services",
            "subcategory":"Doctor",
            "type":"Services"
        }
    ],
    "sg:phone":"+44 114 268 0664",
    "sg:postcode":"S10 5BQ",
    "sg:province":"South Yorkshire",
    "sg:tags":[
        "practitioners"
    ],
    "wof:name":"Thomas, S E",
    "wof:placetype":"venue"
},
  "geometry": {"coordinates":[-1.504503,53.378803],"type":"Point"}
}