{
  "type": "Feature",
  "properties": {
    "iso:country":"GB",
    "sg:address":"Odiham Road, Riseley",
    "sg:city":"Reading",
    "sg:classifiers":[
        {
            "category":"Wholesale",
            "subcategory":"Medical Equipment & Supplies",
            "type":"Manufacturing & Wholesale Goods"
        }
    ],
    "sg:postcode":"RG7 1SQ",
    "sg:province":"Berkshire",
    "sg:tags":[
        "dental"
    ],
    "wof:name":"The Riseway Group",
    "wof:placetype":"venue"
},
  "geometry": {"coordinates":[-0.96568,51.361984],"type":"Point"}
}