{
  "type": "Feature",
  "properties": {
    "addr:full":"Park Works, 16/18 Park Road Kingston-upon-thames Greater London KT2 6BG",
    "addr:housenumber":"16 / 18",
    "addr:postcode":"kt2 6bg",
    "addr:street":"Park;Park Road",
    "iso:country":"GB",
    "sg:address":"Park Works, 16/18 Park Road",
    "sg:city":"Kingston-upon-thames",
    "sg:classifiers":[
        {
            "category":"Building & Trades",
            "subcategory":"Construction",
            "type":"Services"
        }
    ],
    "sg:phone":"+44 20 8547 0700",
    "sg:postcode":"KT2 6BG",
    "sg:province":"Greater London",
    "sg:tags":[
        "builder"
    ],
    "wof:name":"Avalon Management Ltd.",
    "wof:placetype":"venue"
},
  "geometry": {"coordinates":[-0.291474,51.411026],"type":"Point"}
}