{
  "type": "Feature",
  "properties": {
    "addr:full":"321c Bedfont Lane Feltham Greater London TW14 9SB",
    "addr:housenumber":"321c",
    "addr:postcode":"tw14 9sb",
    "addr:street":"Bedfont Lane",
    "iso:country":"GB",
    "sg:address":"321c Bedfont Lane",
    "sg:city":"Feltham",
    "sg:classifiers":[
        {
            "category":"Retail",
            "subcategory":"Auto Repair",
            "type":"Services"
        }
    ],
    "sg:phone":"+44 20 8844 0766",
    "sg:postcode":"TW14 9SB",
    "sg:province":"Greater London",
    "sg:tags":[
        "body",
        "car",
        "related",
        "garage"
    ],
    "wof:name":"STANWELL TRANSPORT SERVICES LTD",
    "wof:placetype":"venue"
},
  "geometry": {"coordinates":[-0.4256249964,51.452796936],"type":"Point"}
}