{
  "type": "Feature",
  "properties": {
    "iso:country":"GB",
    "sg:address":"13 Fairfields, Upper Denby",
    "sg:city":"Huddersfield",
    "sg:classifiers":[
        {
            "category":"Building & Trades",
            "subcategory":"Plumbing",
            "type":"Services"
        }
    ],
    "sg:postcode":"HD8 8UB",
    "sg:province":"South Yorkshire",
    "sg:tags":[
        "heating"
    ],
    "wof:name":"Ashley Smith Combustion",
    "wof:placetype":"venue"
},
  "geometry": {"coordinates":[-1.6554210186,53.5632667542],"type":"Point"}
}