{
  "type": "Feature",
  "properties": {
    "addr:full":"233a Church Lane, Lowton Warrington Cheshire WA3 2RZ",
    "addr:housenumber":"233a",
    "addr:postcode":"wa3 2rz",
    "addr:street":"Church Lane",
    "iso:country":"GB",
    "sg:address":"233a Church Lane, Lowton",
    "sg:city":"Warrington",
    "sg:classifiers":[
        {
            "category":"Professional",
            "subcategory":"Detective & Security Services",
            "type":"Services"
        }
    ],
    "sg:postcode":"WA3 2RZ",
    "sg:province":"Cheshire",
    "sg:tags":[
        "alarm",
        "burglar",
        "system"
    ],
    "wof:name":"J Metcalffe",
    "wof:placetype":"venue"
},
  "geometry": {"coordinates":[-2.5806219578,53.4745826721],"type":"Point"}
}