{
  "type": "Feature",
  "properties": {
    "addr:full":"Festival Ho, Floral Mile Reading Berkshire RG10 9DH",
    "addr:postcode":"rg10 9dh",
    "addr:street":"Mile",
    "iso:country":"GB",
    "sg:address":"Festival Ho, Floral Mile",
    "sg:city":"Reading",
    "sg:classifiers":[
        {
            "category":"Shopping",
            "subcategory":"Pets & Pet Supplies",
            "type":"Retail Goods"
        }
    ],
    "sg:phone":"+44 118 940 4347",
    "sg:postcode":"RG10 9DH",
    "sg:province":"Berkshire",
    "wof:name":"Petstop",
    "wof:placetype":"venue"
},
  "geometry": {"coordinates":[-0.963009,51.453522],"type":"Point"}
}