{
  "type": "Feature",
  "properties": {
    "addr:full":"Old Lane Cobham Surrey KT11 1NG",
    "addr:postcode":"kt11 1ng",
    "addr:street":"Old Lane",
    "iso:country":"GB",
    "sg:address":"Old Lane",
    "sg:city":"Cobham",
    "sg:classifiers":[
        {
            "category":"Bars & Pubs",
            "type":"Food & Drink"
        }
    ],
    "sg:phone":"+44 1932 862364",
    "sg:postcode":"KT11 1NG",
    "sg:province":"Surrey",
    "sg:tags":[
        "pubs",
        "inn"
    ],
    "wof:name":"Andrews",
    "wof:placetype":"venue"
},
  "geometry": {"coordinates":[-0.4234839976,51.2954063416],"type":"Point"}
}