{
  "type": "Feature",
  "properties": {
    "addr:full":"2 Station Parade, Elmers End Road Beckenham Kent BR3 4DH",
    "addr:housenumber":"2",
    "addr:postcode":"br3 4dh",
    "addr:street":"Station Parade Elmers End Road",
    "iso:country":"GB",
    "sg:address":"2 Station Parade, Elmers End Road",
    "sg:city":"Beckenham",
    "sg:classifiers":[
        {
            "category":"Building & Trades",
            "subcategory":"Construction",
            "type":"Services"
        }
    ],
    "sg:phone":"+44 20 8289 9887",
    "sg:postcode":"BR3 4DH",
    "sg:province":"Kent",
    "sg:tags":[
        "glazier"
    ],
    "wof:name":"M Collister",
    "wof:placetype":"venue"
},
  "geometry": {"coordinates":[-0.0477989987,51.3984985352],"type":"Point"}
}