{
  "type": "Feature",
  "properties": {
    "addr:full":"Waen, Dolwen Abergele Conwy LL22 8NY",
    "addr:postcode":"ll22 8ny",
    "addr:street":"Waen Dolwen",
    "iso:country":"GB",
    "sg:address":"Waen, Dolwen",
    "sg:city":"Abergele",
    "sg:classifiers":[
        {
            "category":"Farming",
            "subcategory":"Farm",
            "type":"Manufacturing & Wholesale Goods"
        }
    ],
    "sg:phone":"+44 1492 680277",
    "sg:postcode":"LL22 8NY",
    "sg:province":"Conwy",
    "sg:tags":[
        "mixed",
        "crop"
    ],
    "wof:name":"D R & A M Griffiths",
    "wof:placetype":"venue"
},
  "geometry": {"coordinates":[-3.669594,53.255733],"type":"Point"}
}