{
  "type": "Feature",
  "properties": {
    "addr:full":"56 Zion Hill, Coleorton Coalville Leicestershire LE67 8JP",
    "addr:housenumber":"56",
    "addr:postcode":"le67 8jp",
    "addr:street":"Zion Hill",
    "iso:country":"GB",
    "sg:address":"56 Zion Hill, Coleorton",
    "sg:city":"Coalville",
    "sg:classifiers":[
        {
            "category":"Professional",
            "subcategory":"Management & Consulting",
            "type":"Services"
        }
    ],
    "sg:phone":"+44 1530 222066",
    "sg:postcode":"LE67 8JP",
    "sg:province":"Leicestershire",
    "sg:tags":[
        "consultant",
        "business"
    ],
    "wof:name":"Metamorphosys Consulting Ltd.",
    "wof:placetype":"venue"
},
  "geometry": {"coordinates":[-1.394842,52.757935],"type":"Point"}
}