{
  "type": "Feature",
  "properties": {
    "addr:full":"211 Blackburn Rd Chorley Lancashire PR6 8EP",
    "addr:housenumber":"211",
    "addr:postcode":"pr6 8ep",
    "addr:street":"Blackburn Rd",
    "iso:country":"GB",
    "sg:address":"211 Blackburn Rd",
    "sg:city":"Chorley",
    "sg:classifiers":[
        {
            "category":"Sports & Exercise",
            "subcategory":"Sports Center",
            "type":"Entertainment"
        }
    ],
    "sg:phone":"+44 1254 831592",
    "sg:postcode":"PR6 8EP",
    "sg:province":"Lancashire",
    "sg:tags":[
        "shop",
        "good"
    ],
    "wof:name":"Chillfactor",
    "wof:placetype":"venue"
},
  "geometry": {"coordinates":[-2.6071341038,53.6854667664],"type":"Point"}
}