{
  "type": "Feature",
  "properties": {
    "addr:full":"13 Blenheim Way, Horspath Oxford Buckinghamshire OX33 1SB",
    "addr:housenumber":"13",
    "addr:postcode":"ox33 1sb",
    "addr:street":"Blenheim Way",
    "iso:country":"GB",
    "sg:address":"13 Blenheim Way, Horspath",
    "sg:city":"Oxford",
    "sg:classifiers":[
        {
            "category":"Manufacturing",
            "subcategory":"Signs",
            "type":"Manufacturing & Wholesale Goods"
        }
    ],
    "sg:postcode":"OX33 1SB",
    "sg:province":"Buckinghamshire",
    "sg:tags":[
        "writer"
    ],
    "wof:name":"David & Andrew Cummings",
    "wof:placetype":"venue"
},
  "geometry": {"coordinates":[-1.1737350225,51.7421264648],"type":"Point"}
}