{
  "type": "Feature",
  "properties": {
    "addr:full":"Markfield Rd Leicester Leicestershire LE6 0FL",
    "addr:postcode":"le6 0fl",
    "addr:street":"Markfield Rd",
    "iso:country":"GB",
    "sg:address":"Markfield Rd",
    "sg:city":"Leicester",
    "sg:classifiers":[
        {
            "category":"Place Of Worship",
            "type":"Public Place"
        }
    ],
    "sg:phone":"+44 116 231 3090",
    "sg:postcode":"LE6 0FL",
    "sg:province":"Leicestershire",
    "wof:name":"Groby Parish C Of E Church",
    "wof:placetype":"venue"
},
  "geometry": {"coordinates":[-1.2437759638,52.6699562073],"type":"Point"}
}