{
  "type": "Feature",
  "properties": {
    "addr:full":"Irby Ho Spalding Cambridgeshire PE12 6RT",
    "addr:postcode":"pe12 6rt",
    "addr:street":"Irby;Spalding",
    "iso:country":"GB",
    "sg:address":"Irby Ho",
    "sg:city":"Spalding",
    "sg:classifiers":[
        {
            "category":"Home & Garden",
            "subcategory":"Garden Supply",
            "type":"Retail Goods"
        }
    ],
    "sg:postcode":"PE12 6RT",
    "sg:province":"Cambridgeshire",
    "sg:tags":[
        "ornament"
    ],
    "wof:name":"Ivatt,Andrew,",
    "wof:placetype":"venue"
},
  "geometry": {"coordinates":[-0.0309660006,52.7983398438],"type":"Point"}
}