{
  "type": "Feature",
  "properties": {
    "iso:country":"GB",
    "sg:address":"11 Wilmington Square",
    "sg:city":"Eastbourne",
    "sg:classifiers":[
        {
            "category":"Travel",
            "subcategory":"Hotels & Motels",
            "type":"Entertainment"
        }
    ],
    "sg:phone":"+44 1323 731463",
    "sg:postcode":"BN21 4EA",
    "sg:province":"East Sussex",
    "wof:name":"Ellesmere",
    "wof:placetype":"venue"
},
  "geometry": {"coordinates":[0.284473002,50.7615470886],"type":"Point"}
}