{
  "type": "Feature",
  "properties": {
    "addr:full":"Adelphi Mill, Grimshaw Lane Macclesfield Cheshire SK10 5JB",
    "addr:postcode":"sk10 5jb",
    "addr:street":"Grimshaw Lane",
    "iso:country":"GB",
    "sg:address":"Adelphi Mill, Grimshaw Lane",
    "sg:city":"Macclesfield",
    "sg:classifiers":[
        {
            "category":"Building & Trades",
            "subcategory":"Construction",
            "type":"Services"
        }
    ],
    "sg:phone":"+44 1625 573999",
    "sg:postcode":"SK10 5JB",
    "sg:province":"Cheshire",
    "sg:tags":[
        "contractor"
    ],
    "wof:name":"Terra Firma Construction Ltd.",
    "wof:placetype":"venue"
},
  "geometry": {"coordinates":[-2.1101601124,53.2934608459],"type":"Point"}
}