{
  "type": "Feature",
  "properties": {
    "iso:country":"GB",
    "sg:address":"33 Church St",
    "sg:city":"Falmouth",
    "sg:classifiers":[
        {
            "category":"Banks & Credit Unions",
            "subcategory":"Financial Services",
            "type":"Services"
        }
    ],
    "sg:phone":"+44 1326 315102",
    "sg:postcode":"TR11 3DX",
    "sg:province":"Cornwall",
    "sg:tags":[
        "adviser"
    ],
    "wof:name":"Hambro Countrywide Financial Services",
    "wof:placetype":"venue"
},
  "geometry": {"coordinates":[-5.06778,50.153572],"type":"Point"}
}