{
  "type": "Feature",
  "properties": {
    "iso:country":"GB",
    "sg:address":"34 Rowan Close",
    "sg:city":"London",
    "sg:classifiers":[
        {
            "category":"Building & Trades",
            "subcategory":"Construction",
            "type":"Services"
        }
    ],
    "sg:phone":"+44 20 8579 8310",
    "sg:postcode":"W5 4YH",
    "sg:province":"Greater London",
    "sg:tags":[
        "builder"
    ],
    "wof:name":"Martin Building Services",
    "wof:placetype":"venue"
},
  "geometry": {"coordinates":[-0.295908,51.50333],"type":"Point"}
}