{
  "type": "Feature",
  "properties": {
    "iso:country":"GB",
    "sg:address":"The Cottage, Swanley Lane, Swanley Bridge",
    "sg:city":"Nantwich",
    "sg:classifiers":[
        {
            "category":"Retail",
            "subcategory":"Auto Repair",
            "type":"Services"
        }
    ],
    "sg:phone":"+44 1270 524488",
    "sg:postcode":"CW5 8QB",
    "sg:province":"Cheshire",
    "sg:tags":[
        "engine",
        "car",
        "specialist"
    ],
    "wof:name":"Autoscope",
    "wof:placetype":"venue"
},
  "geometry": {"coordinates":[-2.57033,53.065208],"type":"Point"}
}