{
  "type": "Feature",
  "properties": {
    "iso:country":"GB",
    "sg:address":"131 Elmshurst Gardens",
    "sg:city":"Tonbridge",
    "sg:classifiers":[
        {
            "category":"Building & Trades",
            "subcategory":"Plumbing",
            "type":"Services"
        }
    ],
    "sg:phone":"+44 1732 366003",
    "sg:postcode":"TN10 3QZ",
    "sg:province":"Kent",
    "sg:tags":[
        "heating"
    ],
    "wof:name":"Peter Moon",
    "wof:placetype":"venue"
},
  "geometry": {"coordinates":[0.277805,51.221985],"type":"Point"}
}