{
  "type": "Feature",
  "properties": {
    "addr:full":"2 Carriers Road Cranbrook Kent TN17 3JU",
    "addr:housenumber":"2",
    "addr:postcode":"tn17 3ju",
    "addr:street":"Carriers Road",
    "iso:country":"GB",
    "sg:address":"2 Carriers Road",
    "sg:city":"Cranbrook",
    "sg:classifiers":[
        {
            "category":"Shopping",
            "subcategory":"Shoes",
            "type":"Retail Goods"
        }
    ],
    "sg:phone":"+44 1580 714418",
    "sg:postcode":"TN17 3JU",
    "sg:province":"Kent",
    "wof:name":"The Cobblers Shop",
    "wof:placetype":"venue"
},
  "geometry": {"coordinates":[0.534932,51.097698],"type":"Point"}
}