{
  "type": "Feature",
  "properties": {
    "addr:full":"Unit 4 Merchiston Industrial Estate, Smith Street Falkirk Falkirk FK2 7NB",
    "addr:housenumber":"unit 4",
    "addr:postcode":"fk2 7nb",
    "addr:street":"Industrial Estate Smith Street",
    "iso:country":"GB",
    "sg:address":"Unit 4 Merchiston Industrial Estate, Smith Street",
    "sg:city":"Falkirk",
    "sg:classifiers":[
        {
            "category":"Food & Beverages",
            "subcategory":"Bakery",
            "type":"Retail Goods"
        }
    ],
    "sg:postcode":"FK2 7NB",
    "sg:province":"Falkirk",
    "sg:tags":[
        "baker"
    ],
    "wof:name":"Wheatfield Bakery",
    "wof:placetype":"venue"
},
  "geometry": {"coordinates":[-3.78439,56.012539],"type":"Point"}
}