{
  "type": "Feature",
  "properties": {
    "addr:full":"Cloth Hall Court, Infirmary Street Leeds West Yorkshire LS1 2JB",
    "addr:postcode":"ls1 2jb",
    "addr:street":"Hall Court Infirmary Street",
    "iso:country":"GB",
    "sg:address":"Cloth Hall Court, Infirmary Street",
    "sg:city":"Leeds",
    "sg:classifiers":[
        {
            "category":"Professional",
            "subcategory":"Lawyer & Legal Services",
            "type":"Services"
        }
    ],
    "sg:postcode":"LS1 2JB",
    "sg:province":"West Yorkshire",
    "sg:tags":[
        "solicitor"
    ],
    "wof:name":"Eversheds Solicitors",
    "wof:placetype":"venue"
},
  "geometry": {"coordinates":[-1.548653,53.797508],"type":"Point"}
}