{
  "type": "Feature",
  "properties": {
    "addr:full":"13 Great Moor Street Bolton Lancashire BL1 1NZ",
    "addr:housenumber":"13",
    "addr:postcode":"bl1 1nz",
    "addr:street":"Great Moor Street",
    "iso:country":"GB",
    "sg:address":"13 Great Moor Street",
    "sg:city":"Bolton",
    "sg:classifiers":[
        {
            "category":"Health Services",
            "subcategory":"Optometrist",
            "type":"Services"
        }
    ],
    "sg:phone":"+44 1204 525664",
    "sg:postcode":"BL1 1NZ",
    "sg:province":"Lancashire",
    "sg:tags":[
        "optician"
    ],
    "wof:name":"Sleddon Opticians",
    "wof:placetype":"venue"
},
  "geometry": {"coordinates":[-2.4280459881,53.576423645],"type":"Point"}
}