{
  "type": "Feature",
  "properties": {
    "iso:country":"GB",
    "sg:address":"Blackmore Farm, Froxfield",
    "sg:city":"Petersfield",
    "sg:classifiers":[
        {
            "category":"Retail",
            "subcategory":"Auto Repair",
            "type":"Services"
        }
    ],
    "sg:postcode":"GU32 1ED",
    "sg:province":"Hampshire",
    "sg:tags":[
        "body",
        "car"
    ],
    "wof:name":"Spraystyle",
    "wof:placetype":"venue"
},
  "geometry": {"coordinates":[-0.9980139732,51.0243225098],"type":"Point"}
}