{
  "type": "Feature",
  "properties": {
    "iso:country":"GB",
    "sg:address":"Unit Lyndene Industrial Estate, Willenhall Street",
    "sg:city":"Wednesbury",
    "sg:classifiers":[
        {
            "category":"Retail",
            "subcategory":"Repair Shop",
            "type":"Services"
        }
    ],
    "sg:phone":"+44 121 531 0031",
    "sg:postcode":"WS10 8HW",
    "sg:province":"West Midlands",
    "sg:tags":[
        "furniture"
    ],
    "wof:name":"Furnishings of Elegance",
    "wof:placetype":"venue"
},
  "geometry": {"coordinates":[-2.019254,52.552731],"type":"Point"}
}