{
  "type": "Feature",
  "properties": {
    "addr:full":"20 Tonbridge Road Maidstone Kent ME16 8RS",
    "addr:housenumber":"20",
    "addr:postcode":"me16 8rs",
    "addr:street":"Tonbridge Road",
    "iso:country":"GB",
    "sg:address":"20 Tonbridge Road",
    "sg:city":"Maidstone",
    "sg:classifiers":[
        {
            "category":"Insurance",
            "subcategory":"Insurance Agent",
            "type":"Services"
        }
    ],
    "sg:phone":"+44 1622 758694",
    "sg:postcode":"ME16 8RS",
    "sg:province":"Kent",
    "wof:name":"Royal Liver Assurance Ltd.",
    "wof:placetype":"venue"
},
  "geometry": {"coordinates":[0.5139219761,51.2709655762],"type":"Point"}
}