{
  "type": "Feature",
  "properties": {
    "addr:full":"New Lane, Sutton Green Guildford Surrey GU4 7QF",
    "addr:postcode":"gu4 7qf",
    "addr:street":"New Lane;Green",
    "iso:country":"GB",
    "sg:address":"New Lane, Sutton Green",
    "sg:city":"Guildford",
    "sg:classifiers":[
        {
            "category":"Retail",
            "subcategory":"Auto Repair",
            "type":"Services"
        }
    ],
    "sg:phone":"+44 1483 729866",
    "sg:postcode":"GU4 7QF",
    "sg:province":"Surrey",
    "sg:tags":[
        "modification",
        "garage"
    ],
    "wof:name":"H M C",
    "wof:placetype":"venue"
},
  "geometry": {"coordinates":[-0.55904001,51.2815284729],"type":"Point"}
}