{
  "type": "Feature",
  "properties": {
    "addr:full":"Unit 6 Parkway Industrial Centre, Heneage Street Birmingham West Midlands B7 4LY",
    "addr:housenumber":"unit 6",
    "addr:postcode":"b7 4ly",
    "addr:street":"Parkway Industrial Centre Heneage Street",
    "iso:country":"GB",
    "sg:address":"Unit 6 Parkway Industrial Centre, Heneage Street",
    "sg:city":"Birmingham",
    "sg:classifiers":[
        {
            "category":"Home & Garden",
            "subcategory":"Hardware",
            "type":"Retail Goods"
        }
    ],
    "sg:phone":"+44 121 359 4000",
    "sg:postcode":"B7 4LY",
    "sg:province":"West Midlands",
    "sg:tags":[
        "device",
        "fixing",
        "fastener"
    ],
    "wof:name":"Industrial Fastener Supplies Ltd.",
    "wof:placetype":"venue"
},
  "geometry": {"coordinates":[-1.8856899738,52.4867401123],"type":"Point"}
}