{
  "type": "Feature",
  "properties": {
    "iso:country":"GB",
    "sg:address":"Goose Eye, Oakworth",
    "sg:city":"Keighley",
    "sg:classifiers":[
        {
            "category":"Bars & Pubs",
            "type":"Food & Drink"
        },
        {
            "category":"Community Center",
            "subcategory":"Social",
            "type":"Public Place"
        }
    ],
    "sg:phone":"+44 1535 681339",
    "sg:postcode":"BD22 0PD",
    "sg:province":"North Yorkshire",
    "sg:tags":[
        "pubs",
        "house",
        "inn",
        "activity"
    ],
    "wof:name":"The Turkey Inn",
    "wof:placetype":"venue"
},
  "geometry": {"coordinates":[-1.957792,53.86153],"type":"Point"}
}