{
  "type": "Feature",
  "properties": {
    "addr:full":"Stafford Rd Halifax West Yorkshire HX3 0PA",
    "addr:postcode":"hx3 0pa",
    "addr:street":"Stafford Rd",
    "iso:country":"GB",
    "sg:address":"Stafford Rd",
    "sg:city":"Halifax",
    "sg:classifiers":[
        {
            "category":"Place Of Worship",
            "type":"Public Place"
        }
    ],
    "sg:phone":"+44 1422 360565",
    "sg:postcode":"HX3 0PA",
    "sg:province":"West Yorkshire",
    "wof:name":"Church of Jesus Christ of Latter Day Saints",
    "wof:placetype":"venue"
},
  "geometry": {"coordinates":[-1.860188961,53.7074317932],"type":"Point"}
}