{
  "type": "Feature",
  "properties": {
    "iso:country":"GB",
    "sg:address":"1 Alexandra Road",
    "sg:city":"Grimsby",
    "sg:classifiers":[
        {
            "category":"Food & Beverages",
            "subcategory":"Meat & Fish",
            "type":"Retail Goods"
        }
    ],
    "sg:postcode":"DN31 1RD",
    "sg:province":"Lincolnshire",
    "sg:tags":[
        "seafood"
    ],
    "wof:name":"Leon's Family Fish Restaurant",
    "wof:placetype":"venue"
},
  "geometry": {"coordinates":[-0.087706,53.567272],"type":"Point"}
}