{
  "type": "Feature",
  "properties": {
    "iso:country":"GB",
    "sg:address":"New Road, Yeadon",
    "sg:city":"Leeds",
    "sg:classifiers":[
        {
            "category":"Education",
            "subcategory":"School",
            "type":"Public Place"
        }
    ],
    "sg:phone":"+44 113 250 3540",
    "sg:postcode":"LS19 7HW",
    "sg:province":"West Yorkshire",
    "sg:tags":[
        "local",
        "authority"
    ],
    "wof:name":"St Peter & St Paul R C Primary School",
    "wof:placetype":"venue"
},
  "geometry": {"coordinates":[-1.6996040344,53.8662452698],"type":"Point"}
}