{
  "type": "Feature",
  "properties": {
    "addr:full":"6 Poplar Road, Broadmeadow Industrial Estate Dumbarton Argyll and Bute G82 2RQ",
    "addr:housenumber":"6;estate",
    "addr:postcode":"g82 2rq",
    "addr:street":"Poplar Road;Industrial",
    "iso:country":"GB",
    "sg:address":"6 Poplar Road, Broadmeadow Industrial Estate",
    "sg:city":"Dumbarton",
    "sg:classifiers":[
        {
            "category":"Education",
            "subcategory":"Music School",
            "type":"Public Place"
        }
    ],
    "sg:phone":"+44 1389 761133",
    "sg:postcode":"G82 2RQ",
    "sg:province":"Argyll and Bute",
    "sg:tags":[
        "conservatory"
    ],
    "wof:name":"Lenwood Conservatories",
    "wof:placetype":"venue"
},
  "geometry": {"coordinates":[-4.570166,55.94323],"type":"Point"}
}