{
  "type": "Feature",
  "properties": {
    "addr:full":"160 High Street Maldon Essex CM9 5BX",
    "addr:housenumber":"160",
    "addr:postcode":"cm9 5bx",
    "addr:street":"High Street",
    "iso:country":"GB",
    "sg:address":"160 High Street",
    "sg:city":"Maldon",
    "sg:classifiers":[
        {
            "category":"Home & Garden",
            "subcategory":"Home Furnishings",
            "type":"Retail Goods"
        }
    ],
    "sg:phone":"+44 1621 850414",
    "sg:postcode":"CM9 5BX",
    "sg:province":"Essex",
    "sg:tags":[
        "blind",
        "curtain",
        "fitting"
    ],
    "wof:name":"Chadwick Interiors",
    "wof:placetype":"venue"
},
  "geometry": {"coordinates":[0.68429,51.729519],"type":"Point"}
}