{
  "type": "Feature",
  "properties": {
    "iso:country":"GB",
    "sg:address":"67 Station Road",
    "sg:city":"Hayes",
    "sg:classifiers":[
        {
            "category":"Home & Garden",
            "subcategory":"Home Furnishings",
            "type":"Retail Goods"
        }
    ],
    "sg:phone":"+44 20 8573 8327",
    "sg:postcode":"UB3 4BG",
    "sg:province":"Greater London",
    "sg:tags":[
        "blind",
        "manufacture",
        "fitting",
        "curtain"
    ],
    "wof:name":"Housebox",
    "wof:placetype":"venue"
},
  "geometry": {"coordinates":[-0.4190349877,51.5050735474],"type":"Point"}
}