{
  "type": "Feature",
  "properties": {
    "addr:full":"486 Anlaby Road Hull East Riding of Yorkshire HU3 6TA",
    "addr:housenumber":"486",
    "addr:postcode":"hu3 6ta",
    "addr:street":"Anlaby Road",
    "iso:country":"GB",
    "sg:address":"486 Anlaby Road",
    "sg:city":"Hull",
    "sg:classifiers":[
        {
            "category":"Retail",
            "subcategory":"Laundry & Dry Cleaning",
            "type":"Services"
        }
    ],
    "sg:phone":"+44 1482 509535",
    "sg:postcode":"HU3 6TA",
    "sg:province":"East Riding of Yorkshire",
    "sg:tags":[
        "alteration"
    ],
    "wof:name":"Speedikleen Dry Cleaners",
    "wof:placetype":"venue"
},
  "geometry": {"coordinates":[-0.382071,53.74387],"type":"Point"}
}