{
  "type": "Feature",
  "properties": {
    "iso:country":"GB",
    "sg:address":"Rosedale House, Rosedale Road",
    "sg:city":"Richmond",
    "sg:classifiers":[
        {
            "category":"Food & Beverages",
            "subcategory":"Supermarket",
            "type":"Retail Goods"
        }
    ],
    "sg:phone":"+44 20 8940 6996",
    "sg:postcode":"TW9 2SZ",
    "sg:province":"Greater London",
    "sg:tags":[
        "frozen"
    ],
    "wof:name":"Fin Ba Uk",
    "wof:placetype":"venue"
},
  "geometry": {"coordinates":[-0.300273,51.465714],"type":"Point"}
}