{
  "type": "Feature",
  "properties": {
    "addr:full":"Providence Place Ilkeston Derbyshire DE7 8AL",
    "addr:postcode":"de7 8al",
    "addr:street":"Providence Place",
    "iso:country":"GB",
    "sg:address":"Providence Place",
    "sg:city":"Ilkeston",
    "sg:classifiers":[
        {
            "category":"Building & Trades",
            "subcategory":"Construction",
            "type":"Services"
        }
    ],
    "sg:phone":"+44 115 932 5262",
    "sg:postcode":"DE7 8AL",
    "sg:province":"Derbyshire",
    "sg:tags":[
        "joinery"
    ],
    "wof:name":"Yeomans Joinery",
    "wof:placetype":"venue"
},
  "geometry": {"coordinates":[-1.309489,52.974548],"type":"Point"}
}