{
  "type": "Feature",
  "properties": {
    "iso:country":"GB",
    "sg:address":"Walmersley Rd",
    "sg:city":"Bury",
    "sg:classifiers":[
        {
            "category":"Food & Beverages",
            "subcategory":"Fruits & Vegetables",
            "type":"Retail Goods"
        }
    ],
    "sg:phone":"+44 161 764 5001",
    "sg:postcode":"BL9 6LL",
    "sg:province":"Lancashire",
    "sg:tags":[
        "greengrocer"
    ],
    "wof:name":"Hanburys Ltd",
    "wof:placetype":"venue"
},
  "geometry": {"coordinates":[-2.2935640812,53.6141433716],"type":"Point"}
}