{
  "type": "Feature",
  "properties": {
    "iso:country":"GB",
    "sg:address":"5 Maple Tree Walk, Littlethorpe",
    "sg:city":"Leicester",
    "sg:classifiers":[
        {
            "category":"Professional",
            "subcategory":"Engineering",
            "type":"Services"
        },
        {
            "category":"Building & Trades",
            "subcategory":"Electrical",
            "type":"Services"
        }
    ],
    "sg:phone":"+44 116 275 0616",
    "sg:postcode":"LE19 2JX",
    "sg:province":"Leicestershire",
    "sg:tags":[
        "engineer",
        "electrician",
        "contractor"
    ],
    "wof:name":"K O Electrics Ltd",
    "wof:placetype":"venue"
},
  "geometry": {"coordinates":[-1.200277,52.568775],"type":"Point"}
}