{
  "type": "Feature",
  "properties": {
    "addr:full":"The Barne Southminster Essex CM0 7BW",
    "addr:postcode":"cm0 7bw",
    "addr:street":"Southminster",
    "iso:country":"GB",
    "sg:address":"The Barne",
    "sg:city":"Southminster",
    "sg:classifiers":[
        {
            "category":"Autos & Motor Vehicles",
            "subcategory":"Motorcycle Sales",
            "type":"Retail Goods"
        }
    ],
    "sg:phone":"+44 1621 774433",
    "sg:postcode":"CM0 7BW",
    "sg:province":"Essex",
    "sg:tags":[
        "chauffeur",
        "driven",
        "car"
    ],
    "wof:name":"Court Langley Ltd.",
    "wof:placetype":"venue"
},
  "geometry": {"coordinates":[0.826579988,51.6580543518],"type":"Point"}
}