{
  "type": "Feature",
  "properties": {
    "addr:full":"Brigg Farm, Brigg Lane, Camblesforth Selby East Riding of Yorkshire YO8 8HJ",
    "addr:postcode":"yo8 8hj",
    "addr:street":"Brigg Lane",
    "iso:country":"GB",
    "sg:address":"Brigg Farm, Brigg Lane, Camblesforth",
    "sg:city":"Selby",
    "sg:classifiers":[
        {
            "category":"Autos & Motor Vehicles",
            "subcategory":"Auto Supplies",
            "type":"Retail Goods"
        }
    ],
    "sg:postcode":"YO8 8HJ",
    "sg:province":"East Riding of Yorkshire",
    "sg:tags":[
        "equipment",
        "diesel"
    ],
    "wof:name":"Anco Diesel Services",
    "wof:placetype":"venue"
},
  "geometry": {"coordinates":[-1.01364398,53.7271156311],"type":"Point"}
}