{
  "type": "Feature",
  "properties": {
    "addr:full":"Achnashelloch Farm Lochgilphead Argyll and Bute PA31 8RE",
    "addr:postcode":"pa31 8re",
    "iso:country":"GB",
    "sg:address":"Achnashelloch Farm",
    "sg:city":"Lochgilphead",
    "sg:classifiers":[
        {
            "category":"Farming",
            "subcategory":"Dairy Farm",
            "type":"Manufacturing & Wholesale Goods"
        }
    ],
    "sg:phone":"+44 1546 600191",
    "sg:postcode":"PA31 8RE",
    "sg:province":"Argyll and Bute",
    "wof:name":"D J Campbell",
    "wof:placetype":"venue"
},
  "geometry": {"coordinates":[-5.431824,56.036106],"type":"Point"}
}