{
  "type": "Feature",
  "properties": {
    "addr:full":"51 Bondgate Within Alnwick Northumberland NE66 1HZ",
    "addr:housenumber":"51",
    "addr:postcode":"ne66 1hz",
    "addr:street":"Bondgate Within",
    "iso:country":"GB",
    "sg:address":"51 Bondgate Within",
    "sg:city":"Alnwick",
    "sg:classifiers":[
        {
            "category":"Shopping",
            "subcategory":"Clothing, Apparel, & Fashions",
            "type":"Retail Goods"
        }
    ],
    "sg:phone":"+44 1665 602396",
    "sg:postcode":"NE66 1HZ",
    "sg:province":"Northumberland",
    "sg:tags":[
        "shop"
    ],
    "wof:name":"Gladrads",
    "wof:placetype":"venue"
},
  "geometry": {"coordinates":[-1.706216,55.413486],"type":"Point"}
}