{
  "type": "Feature",
  "properties": {
    "addr:full":"81 St Johns Square, St Johns Precinct Liverpool Merseyside L1 1LT",
    "addr:housenumber":"81",
    "addr:postcode":"l1 1lt",
    "addr:street":"St Johns Square St",
    "iso:country":"GB",
    "sg:address":"81 St Johns Square, St Johns Precinct",
    "sg:city":"Liverpool",
    "sg:classifiers":[
        {
            "category":"Shopping",
            "subcategory":"Optician",
            "type":"Retail Goods"
        }
    ],
    "sg:phone":"+44 151 708 7032",
    "sg:postcode":"L1 1LT",
    "sg:province":"Merseyside",
    "wof:name":"Dollond & Aitchison",
    "wof:placetype":"venue"
},
  "geometry": {"coordinates":[-2.98105,53.40683],"type":"Point"}
}