{
  "type": "Feature",
  "properties": {
    "iso:country":"GB",
    "sg:address":"103 Balmoral Road",
    "sg:city":"Galashiels",
    "sg:classifiers":[
        {
            "category":"Shopping",
            "subcategory":"Department Store",
            "type":"Retail Goods"
        }
    ],
    "sg:phone":"+44 1896 758255",
    "sg:postcode":"TD1 1JW",
    "sg:province":"Scottish Borders",
    "wof:name":"Balmoral Mini-Market",
    "wof:placetype":"venue"
},
  "geometry": {"coordinates":[-2.819241,55.614304],"type":"Point"}
}