{
  "type": "Feature",
  "properties": {
    "iso:country":"GB",
    "sg:address":"Unit 3 Broadway Drive, Norwich Road",
    "sg:city":"Halesworth",
    "sg:classifiers":[
        {
            "category":"Shopping",
            "type":"Retail Goods"
        }
    ],
    "sg:phone":"+44 1986 875181",
    "sg:postcode":"IP19 8QR",
    "sg:province":"Suffolk",
    "sg:tags":[
        "merchant"
    ],
    "wof:name":"Crop Care Ltd.",
    "wof:placetype":"venue"
},
  "geometry": {"coordinates":[1.509231,52.353466],"type":"Point"}
}