{
  "type": "Feature",
  "properties": {
    "iso:country":"GB",
    "sg:address":"Lyndale, Wellhouse Road",
    "sg:city":"Alton",
    "sg:classifiers":[
        {
            "category":"Professional",
            "subcategory":"Research",
            "type":"Services"
        }
    ],
    "sg:postcode":"GU34 4AG",
    "sg:province":"Hampshire",
    "sg:tags":[
        "actuary"
    ],
    "wof:name":"Rose Walkling Consulting Actuary",
    "wof:placetype":"venue"
},
  "geometry": {"coordinates":[-1.010119,51.144619],"type":"Point"}
}