{
  "type": "Feature",
  "properties": {
    "addr:full":"Larks Hill Pontefract North Yorkshire WF8 4RJ",
    "addr:postcode":"wf8 4rj",
    "addr:street":"Larks Hill Pontefract",
    "iso:country":"GB",
    "sg:address":"Larks Hill",
    "sg:city":"Pontefract",
    "sg:classifiers":[
        {
            "category":"Education",
            "subcategory":"School",
            "type":"Public Place"
        },
        {
            "category":"Government",
            "subcategory":"Office",
            "type":"Public Place"
        }
    ],
    "sg:phone":"+44 1977 722845",
    "sg:postcode":"WF8 4RJ",
    "sg:province":"North Yorkshire",
    "sg:tags":[
        "local",
        "authority"
    ],
    "wof:name":"Larks Hill Junior & Infants School",
    "wof:placetype":"venue"
},
  "geometry": {"coordinates":[-1.322559,53.684078],"type":"Point"}
}