{
  "type": "Feature",
  "properties": {
    "addr:full":"Channel Of Pittendreich Farm Kinross Clackmannanshire KY13 9HD",
    "addr:postcode":"ky13 9hd",
    "iso:country":"GB",
    "sg:address":"Channel Of Pittendreich Farm",
    "sg:city":"Kinross",
    "sg:classifiers":[
        {
            "category":"Farming",
            "subcategory":"Livestock Farm",
            "type":"Manufacturing & Wholesale Goods"
        }
    ],
    "sg:phone":"+44 1592 840236",
    "sg:postcode":"KY13 9HD",
    "sg:province":"Clackmannanshire",
    "sg:tags":[
        "others"
    ],
    "wof:name":"Sandy Braid",
    "wof:placetype":"venue"
},
  "geometry": {"coordinates":[-3.4255139828,56.2113265991],"type":"Point"}
}