{
  "type": "Feature",
  "properties": {
    "iso:country":"GB",
    "sg:address":"Mary Street, Balsall Heath",
    "sg:city":"Birmingham",
    "sg:classifiers":[
        {
            "category":"Education",
            "subcategory":"School",
            "type":"Public Place"
        },
        {
            "category":"Government",
            "subcategory":"Office",
            "type":"Public Place"
        }
    ],
    "sg:phone":"+44 121 440 1493",
    "sg:postcode":"B12 9ST",
    "sg:province":"West Midlands",
    "sg:tags":[
        "local",
        "authority"
    ],
    "wof:name":"Heath Mount Junior & Infant School",
    "wof:placetype":"venue"
},
  "geometry": {"coordinates":[-1.8907389641,52.4612312317],"type":"Point"}
}