{
  "type": "Feature",
  "properties": {
    "iso:country":"GB",
    "sg:address":"19 Spout Lane, Albion House, Washington Village",
    "sg:city":"Washington",
    "sg:classifiers":[
        {
            "category":"Real Estate",
            "subcategory":"Architect",
            "type":"Services"
        }
    ],
    "sg:phone":"+44 191 416 8171",
    "sg:postcode":"NE38 7HN",
    "sg:province":"Durham",
    "wof:name":"David Johnson Architects",
    "wof:placetype":"venue"
},
  "geometry": {"coordinates":[-1.518801,54.903767],"type":"Point"}
}