{
  "type": "Feature",
  "properties": {
    "addr:full":"77 High Street Barnstaple Devon EX31 1HX",
    "addr:housenumber":"77",
    "addr:postcode":"ex31 1hx",
    "addr:street":"High Street",
    "iso:country":"GB",
    "sg:address":"77 High Street",
    "sg:city":"Barnstaple",
    "sg:classifiers":[
        {
            "category":"Shopping",
            "subcategory":"Clothing, Apparel, & Fashions",
            "type":"Retail Goods"
        }
    ],
    "sg:phone":"+44 1271 322266",
    "sg:postcode":"EX31 1HX",
    "sg:province":"Devon",
    "sg:tags":[
        "shop"
    ],
    "wof:name":"Monsoon",
    "wof:placetype":"venue"
},
  "geometry": {"coordinates":[-4.0606880188,51.0805931091],"type":"Point"}
}