{
  "type": "Feature",
  "properties": {
    "addr:full":"Featherholme Farm, Stokesley Road, Helmsley York North Yorkshire YO62 5LZ",
    "addr:postcode":"yo62 5lz",
    "addr:street":"Stokesley Road",
    "iso:country":"GB",
    "sg:address":"Featherholme Farm, Stokesley Road, Helmsley",
    "sg:city":"York",
    "sg:classifiers":[
        {
            "category":"Farming",
            "subcategory":"Livestock Farm",
            "type":"Manufacturing & Wholesale Goods"
        },
        {
            "category":"Farming",
            "subcategory":"Farm",
            "type":"Manufacturing & Wholesale Goods"
        }
    ],
    "sg:phone":"+44 1439 798272",
    "sg:postcode":"YO62 5LZ",
    "sg:province":"North Yorkshire",
    "sg:tags":[
        "mixed",
        "crop",
        "others"
    ],
    "wof:name":"G W & G Walsh",
    "wof:placetype":"venue"
},
  "geometry": {"coordinates":[-1.0606889725,54.2458686829],"type":"Point"}
}