{
  "type": "Feature",
  "properties": {
    "iso:country":"GB",
    "sg:address":"P O Box 42",
    "sg:city":"Stockport",
    "sg:classifiers":[
        {
            "category":"Community Center",
            "subcategory":"Youth",
            "type":"Public Place"
        }
    ],
    "sg:phone":"+44 161 440 8888",
    "sg:postcode":"SK1 1ED",
    "sg:province":"Cheshire",
    "sg:tags":[
        "organisation",
        "centre"
    ],
    "wof:name":"Air Training Corps",
    "wof:placetype":"venue"
},
  "geometry": {"coordinates":[-2.1578900814,53.4099311829],"type":"Point"}
}