{
  "type": "Feature",
  "properties": {
    "addr:full":"21 Clerkenwell Green London Greater London EC1R 0DX",
    "addr:housenumber":"21",
    "addr:postcode":"ec1r 0dx",
    "addr:street":"Clerkenwell Green",
    "iso:country":"GB",
    "sg:address":"21 Clerkenwell Green",
    "sg:city":"London",
    "sg:classifiers":[
        {
            "category":"Shopping",
            "subcategory":"Clothing, Apparel, & Fashions",
            "type":"Retail Goods"
        }
    ],
    "sg:phone":"+44 20 8699 8833",
    "sg:postcode":"EC1R 0DX",
    "sg:province":"Greater London",
    "sg:tags":[
        "accessory"
    ],
    "wof:name":"Emily-Jo Gibbs",
    "wof:placetype":"venue"
},
  "geometry": {"coordinates":[-0.1062569991,51.5241012573],"type":"Point"}
}