{
  "type": "Feature",
  "properties": {
    "iso:country":"GB",
    "sg:address":"St Andrews Court, High Street",
    "sg:city":"Burntisland",
    "sg:classifiers":[
        {
            "category":"Organizations",
            "subcategory":"Community Association",
            "type":"Services"
        }
    ],
    "sg:phone":"+44 1592 872770",
    "sg:postcode":"KY3 9AL",
    "sg:province":"Fife",
    "sg:tags":[
        "co-operatives",
        "society",
        "housing",
        "trust"
    ],
    "wof:name":"Kirk Care Housing Association Ltd",
    "wof:placetype":"venue"
},
  "geometry": {"coordinates":[-3.230619,56.060032],"type":"Point"}
}