{
  "type": "Feature",
  "properties": {
    "iso:country":"GB",
    "sg:address":"Winterton House, Nixey Close",
    "sg:city":"Slough",
    "sg:classifiers":[
        {
            "category":"Shopping",
            "subcategory":"Stationery & Office Supplies",
            "type":"Retail Goods"
        }
    ],
    "sg:postcode":"SL1 1ND",
    "sg:province":"Berkshire",
    "sg:tags":[
        "item",
        "promotional"
    ],
    "wof:name":"Moving Messages Ltd",
    "wof:placetype":"venue"
},
  "geometry": {"coordinates":[-0.583059,51.506268],"type":"Point"}
}