{
  "type": "Feature",
  "properties": {
    "addr:full":"Unit 9 John Baird House, Evelina Road London Greater London SE20 8RS",
    "addr:housenumber":"unit 9",
    "addr:postcode":"se20 8rs",
    "addr:street":"John Baird House Evelina Road",
    "iso:country":"GB",
    "sg:address":"Unit 9 John Baird House, Evelina Road",
    "sg:city":"London",
    "sg:classifiers":[
        {
            "category":"Autos & Motor Vehicles",
            "subcategory":"Motorcycle Sales",
            "type":"Retail Goods"
        }
    ],
    "sg:postcode":"SE20 8RS",
    "sg:province":"Greater London",
    "sg:tags":[
        "chauffeur",
        "driven",
        "car"
    ],
    "wof:name":"Senator Chauffeur Services",
    "wof:placetype":"venue"
},
  "geometry": {"coordinates":[-0.0529399998,51.4136390686],"type":"Point"}
}