{
  "type": "Feature",
  "properties": {
    "addr:full":"8b Parkes Passage Stourport-on-severn Worcestershire DY13 9EA",
    "addr:housenumber":"8b",
    "addr:postcode":"dy13 9ea",
    "addr:street":"Parkes Passage Stourport-On-Severn",
    "iso:country":"GB",
    "sg:address":"8b Parkes Passage",
    "sg:city":"Stourport-on-severn",
    "sg:classifiers":[
        {
            "category":"Social Services",
            "subcategory":"Adult Care",
            "type":"Services"
        },
        {
            "category":"Government",
            "subcategory":"Office",
            "type":"Public Place"
        }
    ],
    "sg:phone":"+44 1299 877904",
    "sg:postcode":"DY13 9EA",
    "sg:province":"Worcestershire",
    "sg:tags":[
        "local",
        "day",
        "centre"
    ],
    "wof:name":"Wesley Place Day Centre",
    "wof:placetype":"venue"
},
  "geometry": {"coordinates":[-2.278142,52.33902],"type":"Point"}
}