{
  "type": "Feature",
  "properties": {
    "iso:country":"GB",
    "sg:address":"University Of Portsmouth Milton Site, Locksway Rd",
    "sg:city":"Southsea",
    "sg:classifiers":[
        {
            "category":"Shopping",
            "subcategory":"Books",
            "type":"Retail Goods"
        }
    ],
    "sg:phone":"+44 23 9284 4181",
    "sg:postcode":"PO4 8JF",
    "sg:province":"Hampshire",
    "sg:tags":[
        "bookseller"
    ],
    "wof:name":"Blackwells",
    "wof:placetype":"venue"
},
  "geometry": {"coordinates":[-1.05653,50.792801],"type":"Point"}
}