{
  "type": "Feature",
  "properties": {
    "iso:country":"GB",
    "sg:address":"Reedham Street",
    "sg:city":"London",
    "sg:classifiers":[
        {
            "category":"Education",
            "subcategory":"School",
            "type":"Public Place"
        }
    ],
    "sg:phone":"+44 20 7732 7107",
    "sg:postcode":"SE15 4PF",
    "sg:province":"Greater London",
    "sg:tags":[
        "local",
        "authority"
    ],
    "wof:name":"Bellend Primary School",
    "wof:placetype":"venue"
},
  "geometry": {"coordinates":[-0.071284,51.467171],"type":"Point"}
}