{
  "type": "Feature",
  "properties": {
    "iso:country":"GB",
    "sg:address":"2 Rothbury Gardens, Lobley Hill",
    "sg:city":"Gateshead",
    "sg:classifiers":[
        {
            "category":"Food & Beverages",
            "subcategory":"Meat & Fish",
            "type":"Retail Goods"
        }
    ],
    "sg:postcode":"NE11 0AT",
    "sg:province":"Tyne and Wear",
    "sg:tags":[
        "chip"
    ],
    "wof:name":"Domenico Di-Biasio",
    "wof:placetype":"venue"
},
  "geometry": {"coordinates":[-1.637521,54.939419],"type":"Point"}
}