{
  "type": "Feature",
  "properties": {
    "addr:full":"45 High Road, Chadwell Heath Romford Essex RM6 6QJ",
    "addr:housenumber":"45",
    "addr:postcode":"rm6 6qj",
    "addr:street":"High Road",
    "iso:country":"GB",
    "sg:address":"45 High Road, Chadwell Heath",
    "sg:city":"Romford",
    "sg:classifiers":[
        {
            "category":"Restaurant",
            "type":"Food & Drink"
        }
    ],
    "sg:phone":"+44 20 8597 3019",
    "sg:postcode":"RM6 6QJ",
    "sg:province":"Essex",
    "wof:name":"Starburger",
    "wof:placetype":"venue"
},
  "geometry": {"coordinates":[0.131990999,51.5712242126],"type":"Point"}
}