{
  "type": "Feature",
  "properties": {
    "addr:full":"8 Red Lion Street Chesham Buckinghamshire HP5 1HF",
    "addr:housenumber":"8",
    "addr:postcode":"hp5 1hf",
    "addr:street":"Red Lion Street",
    "iso:country":"GB",
    "sg:address":"8 Red Lion Street",
    "sg:city":"Chesham",
    "sg:classifiers":[
        {
            "category":"Shopping",
            "subcategory":"News",
            "type":"Retail Goods"
        }
    ],
    "sg:phone":"+44 1494 784802",
    "sg:postcode":"HP5 1HF",
    "sg:province":"Buckinghamshire",
    "sg:tags":[
        "newsagent"
    ],
    "wof:name":"Bulldog News",
    "wof:placetype":"venue"
},
  "geometry": {"coordinates":[-0.612973,51.703453],"type":"Point"}
}