{
  "type": "Feature",
  "properties": {
    "iso:country":"GB",
    "sg:address":"Queens Pk Ct, Ilbert St",
    "sg:city":"London",
    "sg:classifiers":[
        {
            "category":"Farming",
            "subcategory":"Nursery",
            "type":"Manufacturing & Wholesale Goods"
        }
    ],
    "sg:postcode":"W10 4QA",
    "sg:province":"Greater London",
    "sg:tags":[
        "creche"
    ],
    "wof:name":"Westminster City Council",
    "wof:placetype":"venue"
},
  "geometry": {"coordinates":[-0.21411,51.529072],"type":"Point"}
}