{
  "type": "Feature",
  "properties": {
    "addr:full":"73 Evington Rd, Leicester Leicester Leicestershire LE2 1QH",
    "addr:housenumber":"73",
    "addr:postcode":"le2 1qh",
    "addr:street":"Evington Rd",
    "iso:country":"GB",
    "sg:address":"73 Evington Rd, Leicester",
    "sg:city":"Leicester",
    "sg:classifiers":[
        {
            "category":"Manufacturing",
            "subcategory":"Textiles",
            "type":"Manufacturing & Wholesale Goods"
        }
    ],
    "sg:postcode":"LE2 1QH",
    "sg:province":"Leicestershire",
    "sg:tags":[
        "knitwear"
    ],
    "wof:name":"Allinc Ltd",
    "wof:placetype":"venue"
},
  "geometry": {"coordinates":[-1.11336,52.626442],"type":"Point"}
}