{
  "type": "Feature",
  "properties": {
    "iso:country":"GB",
    "sg:address":"46 Links View",
    "sg:city":"Cirencester",
    "sg:classifiers":[
        {
            "category":"Retail",
            "subcategory":"Driving School",
            "type":"Services"
        }
    ],
    "sg:phone":"+44 1285 658746",
    "sg:postcode":"GL7 2NF",
    "sg:province":"Gloucestershire",
    "wof:name":"Cirencester & County Driving School",
    "wof:placetype":"venue"
},
  "geometry": {"coordinates":[-1.975992,51.735554],"type":"Point"}
}