{
  "type": "Feature",
  "properties": {
    "iso:country":"GB",
    "sg:address":"Phoenix House, Forstal Road",
    "sg:city":"Aylesford",
    "sg:classifiers":[
        {
            "category":"Building & Trades",
            "subcategory":"Construction",
            "type":"Services"
        }
    ],
    "sg:phone":"+44 1233 740737",
    "sg:postcode":"ME20 7AN",
    "sg:province":"Kent",
    "sg:tags":[
        "joiner",
        "carpenter"
    ],
    "wof:name":"M W M Carpentry",
    "wof:placetype":"venue"
},
  "geometry": {"coordinates":[0.4824720025,51.3033943176],"type":"Point"}
}