{
  "type": "Feature",
  "properties": {
    "addr:full":"Kings Cottage, Eggington Leighton Buzzard Bedfordshire LU7 9PG",
    "addr:postcode":"lu7 9pg",
    "iso:country":"GB",
    "sg:address":"Kings Cottage, Eggington",
    "sg:city":"Leighton Buzzard",
    "sg:classifiers":[
        {
            "category":"Shopping",
            "subcategory":"Books",
            "type":"Retail Goods"
        }
    ],
    "sg:phone":"+44 1525 210647",
    "sg:postcode":"LU7 9PG",
    "sg:province":"Bedfordshire",
    "sg:tags":[
        "second-hand"
    ],
    "wof:name":"Robert Kirkman Ltd.",
    "wof:placetype":"venue"
},
  "geometry": {"coordinates":[-0.6101509929,51.9171333313],"type":"Point"}
}