{
  "type": "Feature",
  "properties": {
    "iso:country":"GB",
    "sg:address":"Fieldhouse Farm, Dunnings Lane",
    "sg:city":"Brentwood",
    "sg:classifiers":[
        {
            "category":"Home & Garden",
            "subcategory":"Household Appliances",
            "type":"Retail Goods"
        }
    ],
    "sg:phone":"+44 1277 811022",
    "sg:postcode":"CM13 3HE",
    "sg:province":"Essex",
    "sg:tags":[
        "refrigeration",
        "air conditioning"
    ],
    "wof:name":"Herts & Essex Air Conditioning",
    "wof:placetype":"venue"
},
  "geometry": {"coordinates":[0.31501,51.592457],"type":"Point"}
}