{
  "type": "Feature",
  "properties": {
    "addr:full":"38 Skinnergate Darlington Durham DL3 7NR",
    "addr:housenumber":"38",
    "addr:postcode":"dl3 7nr",
    "addr:street":"Skinnergate Darlington",
    "iso:country":"GB",
    "sg:address":"38 Skinnergate",
    "sg:city":"Darlington",
    "sg:classifiers":[
        {
            "category":"Sports & Exercise",
            "subcategory":"Athletic Track",
            "type":"Entertainment"
        }
    ],
    "sg:postcode":"DL3 7NR",
    "sg:province":"Durham",
    "sg:tags":[
        "bags",
        "accessory",
        "belt"
    ],
    "wof:name":"Jones,Brian C,",
    "wof:placetype":"venue"
},
  "geometry": {"coordinates":[-1.5575289726,54.5260620117],"type":"Point"}
}