{
  "type": "Feature",
  "properties": {
    "iso:country":"GB",
    "sg:address":"1 Brize Norton Rd",
    "sg:city":"Carterton",
    "sg:classifiers":[
        {
            "category":"Professional",
            "subcategory":"Business Services",
            "type":"Services"
        }
    ],
    "sg:phone":"+44 1993 844884",
    "sg:postcode":"OX18 3HN",
    "sg:province":"Gloucestershire",
    "sg:tags":[
        "bookmaker"
    ],
    "wof:name":"Abbey Racing Ltd",
    "wof:placetype":"venue"
},
  "geometry": {"coordinates":[-1.5942289829,51.7593917847],"type":"Point"}
}