{
  "type": "Feature",
  "properties": {
    "addr:full":"Blackhill Indust Est Stratford-upon-avon Warwickshire CV37 0PT",
    "addr:postcode":"cv37 0pt",
    "iso:country":"GB",
    "sg:address":"Blackhill Indust Est",
    "sg:city":"Stratford-upon-avon",
    "sg:classifiers":[
        {
            "category":"Retail",
            "subcategory":"Auto Repair",
            "type":"Services"
        }
    ],
    "sg:postcode":"CV37 0PT",
    "sg:province":"Warwickshire",
    "sg:tags":[
        "modification",
        "garage"
    ],
    "wof:name":"Bay-Jon Automotive Engineers",
    "wof:placetype":"venue"
},
  "geometry": {"coordinates":[-1.6613559723,52.2319602966],"type":"Point"}
}