{
  "type": "Feature",
  "properties": {
    "addr:full":"8 Forest Road Loughborough Leicestershire LE11 3NP",
    "addr:housenumber":"8",
    "addr:postcode":"le11 3np",
    "addr:street":"Forest Road",
    "iso:country":"GB",
    "sg:address":"8 Forest Road",
    "sg:city":"Loughborough",
    "sg:classifiers":[
        {
            "category":"Banks & Credit Unions",
            "subcategory":"Financial Services",
            "type":"Services"
        }
    ],
    "sg:phone":"+44 1509 211011",
    "sg:postcode":"LE11 3NP",
    "sg:province":"Leicestershire",
    "sg:tags":[
        "adviser",
        "independent"
    ],
    "wof:name":"Cambourne Financial Planning Ltd",
    "wof:placetype":"venue"
},
  "geometry": {"coordinates":[-1.2092590332,52.7672157288],"type":"Point"}
}