{
  "type": "Feature",
  "properties": {
    "addr:full":"16 Dawlish Road Dudley West Midlands DY1 4LU",
    "addr:housenumber":"16",
    "addr:postcode":"dy1 4lu",
    "addr:street":"Dawlish Road",
    "iso:country":"GB",
    "sg:address":"16 Dawlish Road",
    "sg:city":"Dudley",
    "sg:classifiers":[
        {
            "category":"Travel",
            "subcategory":"Hotels & Motels",
            "type":"Entertainment"
        }
    ],
    "sg:postcode":"DY1 4LU",
    "sg:province":"West Midlands",
    "sg:tags":[
        "house",
        "guest"
    ],
    "wof:name":"Merdeka",
    "wof:placetype":"venue"
},
  "geometry": {"coordinates":[-2.0898370743,52.5297660828],"type":"Point"}
}