{
  "type": "Feature",
  "properties": {
    "addr:full":"94 The Street, Rustington Littlehampton West Sussex BN16 3NJ",
    "addr:housenumber":"94",
    "addr:postcode":"bn16 3nj",
    "addr:street":"The Street",
    "iso:country":"GB",
    "sg:address":"94 The Street, Rustington",
    "sg:city":"Littlehampton",
    "sg:classifiers":[
        {
            "category":"Banks & Credit Unions",
            "subcategory":"Bureau De Change",
            "type":"Services"
        }
    ],
    "sg:phone":"+44 1903 859110",
    "sg:postcode":"BN16 3NJ",
    "sg:province":"West Sussex",
    "sg:tags":[
        "town",
        "consultant",
        "planning"
    ],
    "wof:name":"Anthony  Greenwood",
    "wof:placetype":"venue"
},
  "geometry": {"coordinates":[-0.508863,50.810692],"type":"Point"}
}