{
  "type": "Feature",
  "properties": {
    "addr:full":"Prestonfield, Milngavie Glasgow East Dunbartonshire G62 7PZ",
    "addr:postcode":"g62 7pz",
    "iso:country":"GB",
    "sg:address":"Prestonfield, Milngavie",
    "sg:city":"Glasgow",
    "sg:classifiers":[
        {
            "category":"Education",
            "subcategory":"School",
            "type":"Public Place"
        }
    ],
    "sg:phone":"+44 141 956 5720",
    "sg:postcode":"G62 7PZ",
    "sg:province":"East Dunbartonshire",
    "sg:tags":[
        "local",
        "authority"
    ],
    "wof:name":"Craigdhu Primary School",
    "wof:placetype":"venue"
},
  "geometry": {"coordinates":[-4.331704,55.938461],"type":"Point"}
}