{
  "type": "Feature",
  "properties": {
    "iso:country":"GB",
    "sg:address":"33 Lowndes St",
    "sg:city":"London",
    "sg:classifiers":[
        {
            "category":"Professional",
            "type":"Services"
        }
    ],
    "sg:postcode":"SW1X 9HX",
    "sg:province":"Greater London",
    "sg:tags":[
        "caterer"
    ],
    "wof:name":"Mosimann's Ltd",
    "wof:placetype":"venue"
},
  "geometry": {"coordinates":[-0.157227,51.498402],"type":"Point"}
}