{
  "type": "Feature",
  "properties": {
    "addr:full":"Parish Office, St Peters Rectory, Vicarage Rd Manchester Greater Manchester M27 0WA",
    "addr:postcode":"m27 0wa",
    "addr:street":"Vicarage Rd",
    "iso:country":"GB",
    "sg:address":"Parish Office, St Peters Rectory, Vicarage Rd",
    "sg:city":"Manchester",
    "sg:classifiers":[
        {
            "category":"Place Of Worship",
            "type":"Public Place"
        }
    ],
    "sg:phone":"+44 161 727 8175",
    "sg:postcode":"M27 0WA",
    "sg:province":"Greater Manchester",
    "wof:name":"St Peters Church",
    "wof:placetype":"venue"
},
  "geometry": {"coordinates":[-2.3425199986,53.512008667],"type":"Point"}
}