{
  "type": "Feature",
  "properties": {
    "addr:full":"16 Tone Square, Bettws Newport Newport NP20 7AY",
    "addr:housenumber":"16",
    "addr:postcode":"np20 7ay",
    "addr:street":"Tone Square",
    "iso:country":"GB",
    "sg:address":"16 Tone Square, Bettws",
    "sg:city":"Newport",
    "sg:classifiers":[
        {
            "category":"Personal",
            "subcategory":"Tanning Parlor",
            "type":"Services"
        },
        {
            "category":"Sports & Exercise",
            "subcategory":"Swimming Pool",
            "type":"Entertainment"
        }
    ],
    "sg:phone":"+44 1633 854499",
    "sg:postcode":"NP20 7AY",
    "sg:province":"Newport",
    "sg:tags":[
        "sunbeds",
        "hire",
        "sunbed"
    ],
    "wof:name":"SUNFAST LEISURE",
    "wof:placetype":"venue"
},
  "geometry": {"coordinates":[-3.0312769413,51.6119270325],"type":"Point"}
}