{
  "type": "Feature",
  "properties": {
    "addr:full":"15 St Mary Street Weymouth Dorset DT4 8PB",
    "addr:housenumber":"15",
    "addr:postcode":"dt4 8pb",
    "addr:street":"St Mary Street",
    "iso:country":"GB",
    "sg:address":"15 St Mary Street",
    "sg:city":"Weymouth",
    "sg:classifiers":[
        {
            "category":"Shopping",
            "subcategory":"Shoes",
            "type":"Retail Goods"
        }
    ],
    "sg:phone":"+44 1305 775724",
    "sg:postcode":"DT4 8PB",
    "sg:province":"Dorset",
    "sg:tags":[
        "shop"
    ],
    "wof:name":"Barratt",
    "wof:placetype":"venue"
},
  "geometry": {"coordinates":[-2.4537599087,50.6102333069],"type":"Point"}
}