{
  "type": "Feature",
  "properties": {
    "addr:full":"Arbrack Farm, Whithorn Newton Stewart Dumfries and Galloway DG8 8HY",
    "addr:postcode":"dg8 8hy",
    "addr:street":"Stewart",
    "iso:country":"GB",
    "sg:address":"Arbrack Farm, Whithorn",
    "sg:city":"Newton Stewart",
    "sg:classifiers":[
        {
            "category":"Farming",
            "subcategory":"Livestock Farm",
            "type":"Manufacturing & Wholesale Goods"
        }
    ],
    "sg:phone":"+44 1988 500370",
    "sg:postcode":"DG8 8HY",
    "sg:province":"Dumfries and Galloway",
    "sg:tags":[
        "others"
    ],
    "wof:name":"J B McMiken",
    "wof:placetype":"venue"
},
  "geometry": {"coordinates":[-4.415584,54.733227],"type":"Point"}
}