{
  "type": "Feature",
  "properties": {
    "iso:country":"GB",
    "sg:address":"Albert Road",
    "sg:city":"Gourock",
    "sg:classifiers":[
        {
            "category":"Government",
            "subcategory":"Office",
            "type":"Public Place"
        }
    ],
    "sg:phone":"+44 1475 631561",
    "sg:postcode":"PA19 1NQ",
    "sg:province":"Inverclyde",
    "sg:tags":[
        "local"
    ],
    "wof:name":"Gourock Bathing Pond",
    "wof:placetype":"venue"
},
  "geometry": {"coordinates":[-4.815699,55.95929],"type":"Point"}
}