{
  "type": "Feature",
  "properties": {
    "addr:full":"Streetly Road Birmingham West Midlands B23 5JP",
    "addr:postcode":"b23 5jp",
    "addr:street":"Streetly Road",
    "iso:country":"GB",
    "sg:address":"Streetly Road",
    "sg:city":"Birmingham",
    "sg:classifiers":[
        {
            "category":"Farming",
            "subcategory":"Nursery",
            "type":"Manufacturing & Wholesale Goods"
        },
        {
            "category":"Education",
            "subcategory":"School",
            "type":"Public Place"
        }
    ],
    "sg:phone":"+44 121 350 7689",
    "sg:postcode":"B23 5JP",
    "sg:province":"West Midlands",
    "sg:tags":[
        "local",
        "creche",
        "authority"
    ],
    "wof:name":"Short Heath School Nursery Unit",
    "wof:placetype":"venue"
},
  "geometry": {"coordinates":[-1.8575899601,52.5339622498],"type":"Point"}
}