{
  "type": "Feature",
  "properties": {
    "addr:full":"7 Wren Avenue Ipswich Suffolk IP2 0TJ",
    "addr:housenumber":"7",
    "addr:postcode":"ip2 0tj",
    "addr:street":"Wren Avenue",
    "iso:country":"GB",
    "sg:address":"7 Wren Avenue",
    "sg:city":"Ipswich",
    "sg:classifiers":[
        {
            "category":"Social Services",
            "type":"Services"
        },
        {
            "category":"Government",
            "subcategory":"Office",
            "type":"Public Place"
        }
    ],
    "sg:phone":"+44 1473 686804",
    "sg:postcode":"IP2 0TJ",
    "sg:province":"Suffolk",
    "sg:tags":[
        "need",
        "disability",
        "central",
        "special"
    ],
    "wof:name":"The Wren Centre",
    "wof:placetype":"venue"
},
  "geometry": {"coordinates":[1.1153680086,52.0481910706],"type":"Point"}
}