{
  "type": "Feature",
  "properties": {
    "addr:full":"1 Olympia Mews London Greater London W2 3SA",
    "addr:housenumber":"1",
    "addr:postcode":"w2 3sa",
    "addr:street":"Olympia Mews",
    "iso:country":"GB",
    "sg:address":"1 Olympia Mews",
    "sg:city":"London",
    "sg:classifiers":[
        {
            "category":"Professional",
            "subcategory":"Research",
            "type":"Services"
        }
    ],
    "sg:phone":"+44 20 7243 2228",
    "sg:postcode":"W2 3SA",
    "sg:province":"Greater London",
    "sg:tags":[
        "market"
    ],
    "wof:name":"Sadek Wynberg Millward Brown Ltd.",
    "wof:placetype":"venue"
},
  "geometry": {"coordinates":[-0.186859,51.511688],"type":"Point"}
}