{
  "type": "Feature",
  "properties": {
    "iso:country":"GB",
    "sg:address":"14 Market Pl",
    "sg:city":"Abingdon",
    "sg:classifiers":[
        {
            "category":"Shopping",
            "subcategory":"Clothing, Apparel, & Fashions",
            "type":"Retail Goods"
        }
    ],
    "sg:phone":"+44 1235 553958",
    "sg:postcode":"OX14 3HA",
    "sg:province":"Oxfordshire",
    "sg:tags":[
        "shop"
    ],
    "wof:name":"Hamells",
    "wof:placetype":"venue"
},
  "geometry": {"coordinates":[-1.282349,51.670166],"type":"Point"}
}