{
  "type": "Feature",
  "properties": {
    "addr:full":"29 Market St Kidderminster Staffordshire DY10 1AB",
    "addr:housenumber":"29",
    "addr:postcode":"dy10 1ab",
    "addr:street":"Market St",
    "iso:country":"GB",
    "sg:address":"29 Market St",
    "sg:city":"Kidderminster",
    "sg:classifiers":[
        {
            "category":"Shopping",
            "subcategory":"Clothing, Apparel, & Fashions",
            "type":"Retail Goods"
        }
    ],
    "sg:phone":"+44 1384 401633",
    "sg:postcode":"DY10 1AB",
    "sg:province":"Staffordshire",
    "sg:tags":[
        "shop"
    ],
    "wof:name":"Smartypants",
    "wof:placetype":"venue"
},
  "geometry": {"coordinates":[-2.2479970455,52.385433197],"type":"Point"}
}