{
  "type": "Feature",
  "properties": {
    "addr:full":"47 St Botolphs Street Colchester Essex CO2 7EB",
    "addr:housenumber":"47",
    "addr:postcode":"co2 7eb",
    "addr:street":"St Botolphs Street",
    "iso:country":"GB",
    "sg:address":"47 St Botolphs Street",
    "sg:city":"Colchester",
    "sg:classifiers":[
        {
            "category":"Shopping",
            "subcategory":"Discount & Variety Stores",
            "type":"Retail Goods"
        }
    ],
    "sg:phone":"+44 1206 561566",
    "sg:postcode":"CO2 7EB",
    "sg:province":"Essex",
    "sg:tags":[
        "centre"
    ],
    "wof:name":"Petes Treats",
    "wof:placetype":"venue"
},
  "geometry": {"coordinates":[0.903514,51.8853],"type":"Point"}
}