{
  "type": "Feature",
  "properties": {
    "iso:country":"GB",
    "sg:address":"Springfield Park, Springfield Road",
    "sg:city":"Grantham",
    "sg:classifiers":[
        {
            "category":"Professional",
            "subcategory":"Detective & Security Services",
            "type":"Services"
        }
    ],
    "sg:postcode":"NG31 7JB",
    "sg:province":"Lincolnshire",
    "wof:name":"Intruder Watch Security Service",
    "wof:placetype":"venue"
},
  "geometry": {"coordinates":[-0.641679,52.902866],"type":"Point"}
}