{
  "type": "Feature",
  "properties": {
    "addr:full":"Pine Lodge, Rousdon Lyme Regis Devon DT7 3RD",
    "addr:postcode":"dt7 3rd",
    "addr:street":"Rousdon",
    "iso:country":"GB",
    "sg:address":"Pine Lodge, Rousdon",
    "sg:city":"Lyme Regis",
    "sg:classifiers":[
        {
            "category":"Bus Charters",
            "type":"Transportation"
        }
    ],
    "sg:phone":"+44 1297 23000",
    "sg:postcode":"DT7 3RD",
    "sg:province":"Devon",
    "sg:tags":[
        "hire",
        "coach"
    ],
    "wof:name":"Sovereign Cars & Coaches",
    "wof:placetype":"venue"
},
  "geometry": {"coordinates":[-2.943626,50.727894],"type":"Point"}
}