{
  "type": "Feature",
  "properties": {
    "addr:full":"3 Corrour Road, Newton Mearns Glasgow East Ayrshire G77 6TR",
    "addr:housenumber":"3",
    "addr:postcode":"g77 6tr",
    "addr:street":"Corrour Road",
    "iso:country":"GB",
    "sg:address":"3 Corrour Road, Newton Mearns",
    "sg:city":"Glasgow",
    "sg:classifiers":[
        {
            "category":"Health Services",
            "subcategory":"Doctor",
            "type":"Services"
        }
    ],
    "sg:phone":"+44 141 420 3355",
    "sg:postcode":"G77 6TR",
    "sg:province":"East Ayrshire",
    "sg:tags":[
        "practitioners"
    ],
    "wof:name":"Crookfur Medical Practise",
    "wof:placetype":"venue"
},
  "geometry": {"coordinates":[-4.3374681473,55.7817573547],"type":"Point"}
}