{
  "type": "Feature",
  "properties": {
    "iso:country":"GB",
    "sg:address":"241 Pickhurst Rise",
    "sg:city":"West Wickham",
    "sg:classifiers":[
        {
            "category":"Organizations",
            "subcategory":"Non-profit Organization",
            "type":"Services"
        }
    ],
    "sg:postcode":"BR4 0AH",
    "sg:province":"Kent",
    "sg:tags":[
        "organisation",
        "voluntary",
        "charity"
    ],
    "wof:name":"Bromley Humanists",
    "wof:placetype":"venue"
},
  "geometry": {"coordinates":[0.000213,51.381184],"type":"Point"}
}