{
  "type": "Feature",
  "properties": {
    "addr:full":"19 Westwood Rd Scarborough North Yorkshire YO11 2JH",
    "addr:housenumber":"19",
    "addr:postcode":"yo11 2jh",
    "addr:street":"Westwood Rd",
    "iso:country":"GB",
    "sg:address":"19 Westwood Rd",
    "sg:city":"Scarborough",
    "sg:classifiers":[
        {
            "category":"Retail",
            "subcategory":"Auto Repair",
            "type":"Services"
        }
    ],
    "sg:phone":"+44 1723 365555",
    "sg:postcode":"YO11 2JH",
    "sg:province":"North Yorkshire",
    "sg:tags":[
        "modification",
        "garage"
    ],
    "wof:name":"Westwood Garage (Scarborough) Ltd",
    "wof:placetype":"venue"
},
  "geometry": {"coordinates":[-0.4081830084,54.2758255005],"type":"Point"}
}