{
  "type": "Feature",
  "properties": {
    "iso:country":"GB",
    "sg:address":"3 Bedford House, Ashford Road",
    "sg:city":"Cheltenham",
    "sg:classifiers":[
        {
            "category":"Building & Trades",
            "subcategory":"Construction",
            "type":"Services"
        }
    ],
    "sg:postcode":"GL50 2QZ",
    "sg:province":"Gloucestershire",
    "sg:tags":[
        "tiling",
        "contractor"
    ],
    "wof:name":"Anthony Corrie",
    "wof:placetype":"venue"
},
  "geometry": {"coordinates":[-2.078459,51.898048],"type":"Point"}
}