{
  "type": "Feature",
  "properties": {
    "addr:full":"488 Station Road, Dorridge Solihull Warwickshire B93 8HP",
    "addr:housenumber":"488",
    "addr:postcode":"b93 8hp",
    "addr:street":"Station Road",
    "iso:country":"GB",
    "sg:address":"488 Station Road, Dorridge",
    "sg:city":"Solihull",
    "sg:classifiers":[
        {
            "category":"Shopping",
            "subcategory":"Bicycles & Sporting Goods",
            "type":"Retail Goods"
        }
    ],
    "sg:phone":"+44 1564 779996",
    "sg:postcode":"B93 8HP",
    "sg:province":"Warwickshire",
    "sg:tags":[
        "shop",
        "cycle",
        "accessory"
    ],
    "wof:name":"Dorridge Cycles",
    "wof:placetype":"venue"
},
  "geometry": {"coordinates":[-1.7535769939,52.3730583191],"type":"Point"}
}