{
  "type": "Feature",
  "properties": {
    "iso:country":"GB",
    "sg:address":"2 Turney Street",
    "sg:city":"Halifax",
    "sg:classifiers":[
        {
            "category":"Building & Trades",
            "subcategory":"Construction",
            "type":"Services"
        }
    ],
    "sg:postcode":"HX3 5PP",
    "sg:province":"West Yorkshire",
    "sg:tags":[
        "worker",
        "metal"
    ],
    "wof:name":"Profab Fabrications",
    "wof:placetype":"venue"
},
  "geometry": {"coordinates":[-1.874426,53.735931],"type":"Point"}
}