{
  "type": "Feature",
  "properties": {
    "iso:country":"GB",
    "sg:address":"70a Palace Road",
    "sg:city":"London",
    "sg:classifiers":[
        {
            "category":"Manufacturing",
            "subcategory":"Metals",
            "type":"Manufacturing & Wholesale Goods"
        }
    ],
    "sg:postcode":"N8 8QP",
    "sg:province":"Greater London",
    "sg:tags":[
        "product",
        "fabricated"
    ],
    "wof:name":"Chris Fabrications",
    "wof:placetype":"venue"
},
  "geometry": {"coordinates":[-0.12759,51.583199],"type":"Point"}
}