{
  "type": "Feature",
  "properties": {
    "iso:country":"GB",
    "sg:address":"Unit A, 80 Blackheath Road, Greenwich",
    "sg:city":"London",
    "sg:classifiers":[
        {
            "category":"Communications",
            "subcategory":"Film & Video Production",
            "type":"Services"
        }
    ],
    "sg:phone":"+44 20 8692 8332",
    "sg:postcode":"SE10 8DA",
    "sg:province":"Greater London",
    "sg:tags":[
        "recording",
        "studio"
    ],
    "wof:name":"Sound Generation Ltd.",
    "wof:placetype":"venue"
},
  "geometry": {"coordinates":[-0.0180900004,51.4731483459],"type":"Point"}
}