{
  "type": "Feature",
  "properties": {
    "addr:full":"The Fosse, Fosse Way Leamington Spa Warwickshire CV31 1XN",
    "addr:postcode":"cv31 1xn",
    "addr:street":"Fosse Way",
    "iso:country":"GB",
    "sg:address":"The Fosse, Fosse Way",
    "sg:city":"Leamington Spa",
    "sg:classifiers":[
        {
            "category":"Shopping",
            "subcategory":"Books",
            "type":"Retail Goods"
        }
    ],
    "sg:postcode":"CV31 1XN",
    "sg:province":"Warwickshire",
    "wof:name":"C L Deith",
    "wof:placetype":"venue"
},
  "geometry": {"coordinates":[-1.49322,52.263611],"type":"Point"}
}