{
  "type": "Feature",
  "properties": {
    "iso:country":"GB",
    "sg:address":"Three Leys, Honeybourne Road, Bretforton",
    "sg:city":"Evesham",
    "sg:classifiers":[
        {
            "category":"Home & Garden",
            "subcategory":"Garden Supply",
            "type":"Retail Goods"
        }
    ],
    "sg:phone":"+44 1386 833504",
    "sg:postcode":"WR11 7PB",
    "sg:province":"Gloucestershire",
    "sg:tags":[
        "planting",
        "tree",
        "shrub"
    ],
    "wof:name":"Jasmine's Nurseries",
    "wof:placetype":"venue"
},
  "geometry": {"coordinates":[-1.8657310009,52.0940856934],"type":"Point"}
}