{
  "type": "Feature",
  "properties": {
    "iso:country":"GB",
    "sg:address":"49 Burnt Oak Bdwy",
    "sg:city":"Edgware",
    "sg:classifiers":[
        {
            "category":"Shopping",
            "subcategory":"Baby Store",
            "type":"Retail Goods"
        }
    ],
    "sg:postcode":"HA8 5JZ",
    "sg:province":"Greater London",
    "sg:tags":[
        "nursery",
        "accessory"
    ],
    "wof:name":"Smarteeland",
    "wof:placetype":"venue"
},
  "geometry": {"coordinates":[-0.267132,51.600224],"type":"Point"}
}