{
  "type": "Feature",
  "properties": {
    "addr:full":"167 London Road Sheffield South Yorkshire S2 4LH",
    "addr:housenumber":"167",
    "addr:postcode":"s2 4lh",
    "addr:street":"London Road",
    "iso:country":"GB",
    "sg:address":"167 London Road",
    "sg:city":"Sheffield",
    "sg:classifiers":[
        {
            "category":"Travel",
            "subcategory":"Travel Agent",
            "type":"Entertainment"
        }
    ],
    "sg:phone":"+44 114 255 3878",
    "sg:postcode":"S2 4LH",
    "sg:province":"South Yorkshire",
    "wof:name":"Asia Pacific Travel",
    "wof:placetype":"venue"
},
  "geometry": {"coordinates":[-1.4766429663,53.3692131042],"type":"Point"}
}