{
  "type": "Feature",
  "properties": {
    "addr:full":"Peek House, 20 Eastcheap London Greater London EC3M 1EN",
    "addr:housenumber":"20",
    "addr:postcode":"ec3m 1en",
    "addr:street":"Eastcheap",
    "iso:country":"GB",
    "sg:address":"Peek House, 20 Eastcheap",
    "sg:city":"London",
    "sg:classifiers":[
        {
            "category":"Freight",
            "type":"Transportation"
        }
    ],
    "sg:phone":"+44 20 7626 2983",
    "sg:postcode":"EC3M 1EN",
    "sg:province":"Greater London",
    "sg:tags":[
        "overseas",
        "shipping",
        "removal"
    ],
    "wof:name":"H Barrett & Co. (Freightett) Ltd.",
    "wof:placetype":"venue"
},
  "geometry": {"coordinates":[-0.0838129967,51.5105552673],"type":"Point"}
}