{
  "type": "Feature",
  "properties": {
    "addr:full":"95 Commonside, Pensnett Brierley Hill West Midlands DY5 4AJ",
    "addr:housenumber":"95",
    "addr:postcode":"dy5 4aj",
    "addr:street":"Commonside Pensnett Brierley Hill",
    "iso:country":"GB",
    "sg:address":"95 Commonside, Pensnett",
    "sg:city":"Brierley Hill",
    "sg:classifiers":[
        {
            "category":"Farming",
            "subcategory":"Fish & Marine Products",
            "type":"Manufacturing & Wholesale Goods"
        },
        {
            "category":"Food & Beverages",
            "subcategory":"Meat & Fish",
            "type":"Retail Goods"
        }
    ],
    "sg:phone":"+44 1384 77228",
    "sg:postcode":"DY5 4AJ",
    "sg:province":"West Midlands",
    "sg:tags":[
        "fishmonger",
        "butcher"
    ],
    "wof:name":"Tomlinsons",
    "wof:placetype":"venue"
},
  "geometry": {"coordinates":[-2.133877,52.49733],"type":"Point"}
}