{
  "type": "Feature",
  "properties": {
    "addr:full":"Heage Road Ripley Derbyshire DE5 3GG",
    "addr:postcode":"de5 3gg",
    "addr:street":"Heage Road",
    "iso:country":"GB",
    "sg:address":"Heage Road",
    "sg:city":"Ripley",
    "sg:classifiers":[
        {
            "category":"Government",
            "subcategory":"Post Office",
            "type":"Public Place"
        }
    ],
    "sg:postcode":"DE5 3GG",
    "sg:province":"Derbyshire",
    "wof:name":"Heage Road Post Office",
    "wof:placetype":"venue"
},
  "geometry": {"coordinates":[-1.4147859812,53.0520477295],"type":"Point"}
}