{
  "type": "Feature",
  "properties": {
    "iso:country":"GB",
    "sg:address":"5-7 West Street",
    "sg:city":"Mexborough",
    "sg:classifiers":[
        {
            "category":"Real Estate",
            "subcategory":"Real Estate Agent",
            "type":"Services"
        }
    ],
    "sg:phone":"+44 1709 513098",
    "sg:postcode":"S64 9HZ",
    "sg:province":"South Yorkshire",
    "wof:name":"Wilkinson Estate Agents",
    "wof:placetype":"venue"
},
  "geometry": {"coordinates":[-1.292187,53.493576],"type":"Point"}
}