{
  "type": "Feature",
  "properties": {
    "addr:full":"Ben Hall Clinic, Cheltenham General Hospital Cheltenham Gloucestershire GL53 7AN",
    "addr:postcode":"gl53 7an",
    "iso:country":"GB",
    "sg:address":"Ben Hall Clinic, Cheltenham General Hospital",
    "sg:city":"Cheltenham",
    "sg:classifiers":[
        {
            "category":"Health Services",
            "subcategory":"Clinic",
            "type":"Services"
        }
    ],
    "sg:phone":"+44 1242 274279",
    "sg:postcode":"GL53 7AN",
    "sg:province":"Gloucestershire",
    "sg:tags":[
        "nh"
    ],
    "wof:name":"Genito Urinary Medicine",
    "wof:placetype":"venue"
},
  "geometry": {"coordinates":[-2.0719,51.892078],"type":"Point"}
}