{
  "type": "Feature",
  "properties": {
    "iso:country":"GB",
    "sg:address":"226 Green Lane",
    "sg:city":"Stockport",
    "sg:classifiers":[
        {
            "category":"Shopping",
            "subcategory":"News",
            "type":"Retail Goods"
        }
    ],
    "sg:phone":"+44 161 432 6480",
    "sg:postcode":"SK4 2NA",
    "sg:province":"Cheshire",
    "sg:tags":[
        "newsagent"
    ],
    "wof:name":"P Bhagdev",
    "wof:placetype":"venue"
},
  "geometry": {"coordinates":[-2.178151,53.415867],"type":"Point"}
}