{
  "type": "Feature",
  "properties": {
    "addr:full":"Louisa Buildings, Front Street, Front Street Stanley Durham DH9 0TE",
    "addr:postcode":"dh9 0te",
    "addr:street":"Louisa Buildings Front Street Front Street",
    "iso:country":"GB",
    "sg:address":"Louisa Buildings, Front Street, Front Street",
    "sg:city":"Stanley",
    "sg:classifiers":[
        {
            "category":"Education",
            "subcategory":"University",
            "type":"Public Place"
        }
    ],
    "sg:phone":"+44 1207 282050",
    "sg:postcode":"DH9 0TE",
    "sg:province":"Durham",
    "sg:tags":[
        "higher"
    ],
    "wof:name":"Derwentside College",
    "wof:placetype":"venue"
},
  "geometry": {"coordinates":[-1.690338,54.872379],"type":"Point"}
}