{
  "type": "Feature",
  "properties": {
    "iso:country":"GB",
    "sg:address":"162 Regent Street",
    "sg:city":"London",
    "sg:classifiers":[
        {
            "category":"Professional",
            "subcategory":"Engineering",
            "type":"Services"
        }
    ],
    "sg:phone":"+44 20 7287 4338",
    "sg:postcode":"W1B 5TG",
    "sg:province":"Greater London",
    "sg:tags":[
        "consulting",
        "engineer"
    ],
    "wof:name":"Melliss & Partners",
    "wof:placetype":"venue"
},
  "geometry": {"coordinates":[-0.13938,51.511909],"type":"Point"}
}