{
  "type": "Feature",
  "properties": {
    "iso:country":"GB",
    "sg:address":"33 Allan Park",
    "sg:city":"Stirling",
    "sg:classifiers":[
        {
            "category":"Shopping",
            "subcategory":"Florist",
            "type":"Retail Goods"
        }
    ],
    "sg:postcode":"FK8 2LT",
    "sg:province":"Stirling",
    "wof:name":"It's Blooming Wonderful",
    "wof:placetype":"venue"
},
  "geometry": {"coordinates":[-3.938963,56.115841],"type":"Point"}
}