{
  "type": "Feature",
  "properties": {
    "addr:full":"Sandy Farm, The Sands Farnham Hampshire GU10 1PX",
    "addr:postcode":"gu10 1px",
    "addr:street":"The Sands",
    "iso:country":"GB",
    "sg:address":"Sandy Farm, The Sands",
    "sg:city":"Farnham",
    "sg:classifiers":[
        {
            "category":"Professional",
            "subcategory":"Computer Services",
            "type":"Services"
        }
    ],
    "sg:phone":"+44 1252 783893",
    "sg:postcode":"GU10 1PX",
    "sg:province":"Hampshire",
    "sg:tags":[
        "system",
        "software"
    ],
    "wof:name":"Innecto Projects Ltd.",
    "wof:placetype":"venue"
},
  "geometry": {"coordinates":[-0.7415789962,51.2118835449],"type":"Point"}
}