{
  "type": "Feature",
  "properties": {
    "iso:country":"GB",
    "sg:address":"1 Church Walk, Holmes Chapel",
    "sg:city":"Crewe",
    "sg:classifiers":[
        {
            "category":"Shopping",
            "subcategory":"Department Store",
            "type":"Retail Goods"
        }
    ],
    "sg:phone":"+44 1477 532434",
    "sg:postcode":"CW4 7AZ",
    "sg:province":"Cheshire",
    "wof:name":"Susan Sinclair",
    "wof:placetype":"venue"
},
  "geometry": {"coordinates":[-2.356254,53.199566],"type":"Point"}
}