{
  "type": "Feature",
  "properties": {
    "iso:country":"GB",
    "sg:address":"117 Ringwood Road",
    "sg:city":"Verwood",
    "sg:classifiers":[
        {
            "category":"Manufacturing",
            "subcategory":"Lumber",
            "type":"Manufacturing & Wholesale Goods"
        }
    ],
    "sg:postcode":"BH31 7AD",
    "sg:province":"Dorset",
    "sg:tags":[
        "importer",
        "merchants",
        "agent",
        "timber"
    ],
    "wof:name":"E J  Humby",
    "wof:placetype":"venue"
},
  "geometry": {"coordinates":[-1.8648719788,50.8789367676],"type":"Point"}
}