{
  "type": "Feature",
  "properties": {
    "addr:full":"3 Stramongate Kendal Cumbria LA9 4BH",
    "addr:housenumber":"3",
    "addr:postcode":"la9 4bh",
    "addr:street":"Stramongate Kendal",
    "iso:country":"GB",
    "sg:address":"3 Stramongate",
    "sg:city":"Kendal",
    "sg:classifiers":[
        {
            "category":"Restaurant",
            "type":"Food & Drink"
        }
    ],
    "sg:phone":"+44 1539 735005",
    "sg:postcode":"LA9 4BH",
    "sg:province":"Cumbria",
    "wof:name":"Sizzling Wok The",
    "wof:placetype":"venue"
},
  "geometry": {"coordinates":[-2.74492,54.328056],"type":"Point"}
}