{
  "type": "Feature",
  "properties": {
    "iso:country":"GB",
    "sg:address":"9 Hydean Way",
    "sg:city":"Stevenage",
    "sg:classifiers":[
        {
            "category":"Shopping",
            "subcategory":"Department Store",
            "type":"Retail Goods"
        }
    ],
    "sg:postcode":"SG2 9XH",
    "sg:province":"Hertfordshire",
    "wof:name":"Londis",
    "wof:placetype":"venue"
},
  "geometry": {"coordinates":[-0.183105,51.892338],"type":"Point"}
}