{
  "type": "Feature",
  "properties": {
    "iso:country":"GB",
    "sg:address":"40 Park Crescent, Frenchay",
    "sg:city":"Bristol",
    "sg:classifiers":[
        {
            "category":"Shopping",
            "subcategory":"Books",
            "type":"Retail Goods"
        }
    ],
    "sg:phone":"+44 117 957 4927",
    "sg:postcode":"BS16 1NZ",
    "sg:province":"City of Bristol",
    "sg:tags":[
        "bookseller"
    ],
    "wof:name":"Usborne Books At Home",
    "wof:placetype":"venue"
},
  "geometry": {"coordinates":[-2.5145330429,51.5010452271],"type":"Point"}
}