{
  "type": "Feature",
  "properties": {
    "addr:full":"40 Oakleigh Road Worthing West Sussex BN11 2QG",
    "addr:housenumber":"40",
    "addr:postcode":"bn11 2qg",
    "addr:street":"Oakleigh Road",
    "iso:country":"GB",
    "sg:address":"40 Oakleigh Road",
    "sg:city":"Worthing",
    "sg:classifiers":[
        {
            "category":"Autos & Motor Vehicles",
            "subcategory":"Motorcycle Sales",
            "type":"Retail Goods"
        }
    ],
    "sg:phone":"+44 1903 522073",
    "sg:postcode":"BN11 2QG",
    "sg:province":"West Sussex",
    "sg:tags":[
        "chauffeur",
        "driven",
        "car"
    ],
    "wof:name":"Premiere Limousines",
    "wof:placetype":"venue"
},
  "geometry": {"coordinates":[-0.3509759903,50.8218040466],"type":"Point"}
}