{
  "type": "Feature",
  "properties": {
    "addr:full":"5 Beaumont Clo Southampton Hampshire SO16 7NE",
    "addr:housenumber":"5",
    "addr:postcode":"so16 7ne",
    "addr:street":"Beaumont Clo",
    "iso:country":"GB",
    "sg:address":"5 Beaumont Clo",
    "sg:city":"Southampton",
    "sg:classifiers":[
        {
            "category":"Professional",
            "subcategory":"Lawyer & Legal Services",
            "type":"Services"
        }
    ],
    "sg:phone":"+44 23 8052 9100",
    "sg:postcode":"SO16 7NE",
    "sg:province":"Hampshire",
    "sg:tags":[
        "advice",
        "counselling"
    ],
    "wof:name":"Renaissance Counselling Services",
    "wof:placetype":"venue"
},
  "geometry": {"coordinates":[-1.411221981,50.937084198],"type":"Point"}
}