{
  "type": "Feature",
  "properties": {
    "addr:full":"Dairy Farm Buildings, Saighton Chester Cheshire CH3 6EG",
    "addr:postcode":"ch3 6eg",
    "addr:street":"Dairy",
    "iso:country":"GB",
    "sg:address":"Dairy Farm Buildings, Saighton",
    "sg:city":"Chester",
    "sg:classifiers":[
        {
            "category":"Utilities",
            "type":"Services"
        }
    ],
    "sg:postcode":"CH3 6EG",
    "sg:province":"Cheshire",
    "sg:tags":[
        "internet"
    ],
    "wof:name":"Construction Network Ltd",
    "wof:placetype":"venue"
},
  "geometry": {"coordinates":[-2.8341429234,53.1525268555],"type":"Point"}
}