{
  "type": "Feature",
  "properties": {
    "addr:full":"Meekings Road, Chiltern Industrial Estate Sudbury Essex CO10 2XG",
    "addr:postcode":"co10 2xg",
    "addr:street":"Meekings Road;Industrial Estate",
    "iso:country":"GB",
    "sg:address":"Meekings Road, Chiltern Industrial Estate",
    "sg:city":"Sudbury",
    "sg:classifiers":[
        {
            "category":"Retail",
            "subcategory":"Storage",
            "type":"Services"
        }
    ],
    "sg:phone":"+44 1787 880597",
    "sg:postcode":"CO10 2XG",
    "sg:province":"Essex",
    "sg:tags":[
        "household",
        "removal"
    ],
    "wof:name":"D Todd Removals",
    "wof:placetype":"venue"
},
  "geometry": {"coordinates":[0.73439,52.038605],"type":"Point"}
}