{
  "type": "Feature",
  "properties": {
    "addr:full":"Studio 31, Woodfield Ave Wolverhampton Staffordshire WV4 4AG",
    "addr:housenumber":"31",
    "addr:postcode":"wv4 4ag",
    "addr:street":"Woodfield Ave",
    "iso:country":"GB",
    "sg:address":"Studio 31, Woodfield Ave",
    "sg:city":"Wolverhampton",
    "sg:classifiers":[
        {
            "category":"Arts & Performance",
            "subcategory":"Music",
            "type":"Entertainment"
        }
    ],
    "sg:postcode":"WV4 4AG",
    "sg:province":"Staffordshire",
    "sg:tags":[
        "musician",
        "composer"
    ],
    "wof:name":"Clark,Daniel,",
    "wof:placetype":"venue"
},
  "geometry": {"coordinates":[-2.1479699612,52.5657196045],"type":"Point"}
}