{
  "type": "Feature",
  "properties": {
    "iso:country":"GB",
    "sg:address":"Combe Ho,33 Oakfield Rd, Clifton",
    "sg:city":"Bristol",
    "sg:classifiers":[
        {
            "category":"Professional",
            "subcategory":"Advertising",
            "type":"Services"
        }
    ],
    "sg:postcode":"BS8 2AT",
    "sg:province":"City of Bristol",
    "sg:tags":[
        "agency"
    ],
    "wof:name":"Jeanes Carter Associates",
    "wof:placetype":"venue"
},
  "geometry": {"coordinates":[-2.61232,51.460709],"type":"Point"}
}