{
  "type": "Feature",
  "properties": {
    "iso:country":"GB",
    "sg:address":"Holly Bank, Rowton Lane",
    "sg:city":"Chester",
    "sg:classifiers":[
        {
            "category":"Farming",
            "subcategory":"Livestock Farm",
            "type":"Manufacturing & Wholesale Goods"
        }
    ],
    "sg:postcode":"CH3 6AT",
    "sg:province":"Cheshire",
    "sg:tags":[
        "others"
    ],
    "wof:name":"Allen R Salmon",
    "wof:placetype":"venue"
},
  "geometry": {"coordinates":[-2.8304069042,53.1750793457],"type":"Point"}
}