{
  "type": "Feature",
  "properties": {
    "addr:full":"175 Muller Road, Horfield Bristol City of Bristol BS7 9RD",
    "addr:housenumber":"175",
    "addr:postcode":"bs7 9rd",
    "addr:street":"Muller Road",
    "iso:country":"GB",
    "sg:address":"175 Muller Road, Horfield",
    "sg:city":"Bristol",
    "sg:classifiers":[
        {
            "category":"Autos & Motor Vehicles",
            "subcategory":"Automobile Sales",
            "type":"Retail Goods"
        }
    ],
    "sg:phone":"+44 117 951 3333",
    "sg:postcode":"BS7 9RD",
    "sg:province":"City of Bristol",
    "sg:tags":[
        "car"
    ],
    "wof:name":"Brunel Ford",
    "wof:placetype":"venue"
},
  "geometry": {"coordinates":[-2.579146,51.482841],"type":"Point"}
}