{
  "type": "Feature",
  "properties": {
    "iso:country":"GB",
    "sg:address":"24 Watford Road",
    "sg:city":"King's Langley",
    "sg:classifiers":[
        {
            "category":"Manufacturing",
            "subcategory":"Metals",
            "type":"Manufacturing & Wholesale Goods"
        }
    ],
    "sg:phone":"+44 1923 263570",
    "sg:postcode":"WD4 8EA",
    "sg:province":"Hertfordshire",
    "sg:tags":[
        "steel",
        "stockholder"
    ],
    "wof:name":"Chari-Til Ltd",
    "wof:placetype":"venue"
},
  "geometry": {"coordinates":[-0.447907,51.709106],"type":"Point"}
}