{
  "type": "Feature",
  "properties": {
    "addr:full":"1 Oak Street Preston Lancashire PR1 3XD",
    "addr:housenumber":"1",
    "addr:postcode":"pr1 3xd",
    "addr:street":"Oak Street",
    "iso:country":"GB",
    "sg:address":"1 Oak Street",
    "sg:city":"Preston",
    "sg:classifiers":[
        {
            "category":"Parking",
            "type":"Transportation"
        }
    ],
    "sg:phone":"+44 1772 555763",
    "sg:postcode":"PR1 3XD",
    "sg:province":"Lancashire",
    "sg:tags":[
        "car",
        "valet"
    ],
    "wof:name":"Norwest Car Wash Ltd.",
    "wof:placetype":"venue"
},
  "geometry": {"coordinates":[-2.692659,53.757969],"type":"Point"}
}