{
  "type": "Feature",
  "properties": {
    "iso:country":"GB",
    "sg:address":"The Crown Hotel, High Street",
    "sg:city":"Southwold",
    "sg:classifiers":[
        {
            "category":"Food & Beverages",
            "subcategory":"Liquor & Beverages",
            "type":"Retail Goods"
        }
    ],
    "sg:phone":"+44 1502 727222",
    "sg:postcode":"IP18 6DP",
    "sg:province":"Suffolk",
    "sg:tags":[
        "beer",
        "spirit",
        "wines"
    ],
    "wof:name":"Adnams Wine Merchants",
    "wof:placetype":"venue"
},
  "geometry": {"coordinates":[1.6762,52.328163],"type":"Point"}
}