{
  "type": "Feature",
  "properties": {
    "addr:full":"11 Clos Y Gwyddfid, Radyr Gardens, Radyr Cardiff Caerphilly CF15 8EX",
    "addr:housenumber":"11",
    "addr:postcode":"cf15 8ex",
    "addr:street":"Clos Y Gwyddfid Radyr Gardens",
    "iso:country":"GB",
    "sg:address":"11 Clos Y Gwyddfid, Radyr Gardens, Radyr",
    "sg:city":"Cardiff",
    "sg:classifiers":[
        {
            "category":"Building & Trades",
            "subcategory":"Construction",
            "type":"Services"
        }
    ],
    "sg:postcode":"CF15 8EX",
    "sg:province":"Caerphilly",
    "sg:tags":[
        "roofing"
    ],
    "wof:name":"D J Mackay & Son",
    "wof:placetype":"venue"
},
  "geometry": {"coordinates":[-3.2595028877,51.5166969299],"type":"Point"}
}