{
  "type": "Feature",
  "properties": {
    "addr:full":"23 Park St Leamington Spa Warwickshire CV32 4QN",
    "addr:housenumber":"23",
    "addr:postcode":"cv32 4qn",
    "addr:street":"Park St",
    "iso:country":"GB",
    "sg:address":"23 Park St",
    "sg:city":"Leamington Spa",
    "sg:classifiers":[
        {
            "category":"Food & Beverages",
            "subcategory":"Liquor & Beverages",
            "type":"Retail Goods"
        }
    ],
    "sg:phone":"+44 1926 311872",
    "sg:postcode":"CV32 4QN",
    "sg:province":"Warwickshire",
    "sg:tags":[
        "beer",
        "spirit",
        "wines"
    ],
    "wof:name":"Park Street Newsagents",
    "wof:placetype":"venue"
},
  "geometry": {"coordinates":[-1.5333729982,52.29139328],"type":"Point"}
}