{
  "type": "Feature",
  "properties": {
    "addr:full":"10 Barmoor Terrace Ryton Tyne and Wear NE40 3BB",
    "addr:housenumber":"10",
    "addr:postcode":"ne40 3bb",
    "addr:street":"Barmoor Terrace",
    "iso:country":"GB",
    "sg:address":"10 Barmoor Terrace",
    "sg:city":"Ryton",
    "sg:classifiers":[
        {
            "category":"Education",
            "subcategory":"Dance Studio",
            "type":"Public Place"
        }
    ],
    "sg:phone":"+44 191 413 5400",
    "sg:postcode":"NE40 3BB",
    "sg:province":"Tyne and Wear",
    "sg:tags":[
        "school",
        "dancing"
    ],
    "wof:name":"Hazel Rayson Theatre Dance Studio",
    "wof:placetype":"venue"
},
  "geometry": {"coordinates":[-1.771004,54.972485],"type":"Point"}
}