{
  "type": "Feature",
  "properties": {
    "addr:full":"Fisher Athletic Football Club, Surrey Docks Stadium, Salter Road London Greater London SE16 5LH",
    "addr:postcode":"se16 5lh",
    "addr:street":"Surrey;Salter Road",
    "iso:country":"GB",
    "sg:address":"Fisher Athletic Football Club, Surrey Docks Stadium, Salter Road",
    "sg:city":"London",
    "sg:classifiers":[
        {
            "category":"Arena",
            "subcategory":"Sports Club",
            "type":"Entertainment"
        }
    ],
    "sg:phone":"+44 20 7231 5144",
    "sg:postcode":"SE16 5LH",
    "sg:province":"Greater London",
    "sg:tags":[
        "ground"
    ],
    "wof:name":"Fisher Athletic (London) Football Club Ltd.",
    "wof:placetype":"venue"
},
  "geometry": {"coordinates":[-0.0434000008,51.5049514771],"type":"Point"}
}