{
  "type": "Feature",
  "properties": {
    "iso:country":"GB",
    "sg:address":"320 Oldham Road",
    "sg:city":"Rochdale",
    "sg:classifiers":[
        {
            "category":"Home & Garden",
            "subcategory":"Home Furnishings",
            "type":"Retail Goods"
        },
        {
            "category":"Home & Garden",
            "subcategory":"Building Materials",
            "type":"Retail Goods"
        }
    ],
    "sg:postcode":"OL11 2AL",
    "sg:province":"Lancashire",
    "sg:tags":[
        "installers",
        "planner",
        "kitchen",
        "furnishers"
    ],
    "wof:name":"CONTRACT KITCHENS",
    "wof:placetype":"venue"
},
  "geometry": {"coordinates":[-2.145613,53.598255],"type":"Point"}
}