{
  "type": "Feature",
  "properties": {
    "addr:full":"Garmouth Road, Lhanbryde Elgin Moray IV30 3PD",
    "addr:postcode":"iv30 3pd",
    "addr:street":"Garmouth Road",
    "iso:country":"GB",
    "sg:address":"Garmouth Road, Lhanbryde",
    "sg:city":"Elgin",
    "sg:classifiers":[
        {
            "category":"Education",
            "subcategory":"School",
            "type":"Public Place"
        },
        {
            "category":"Government",
            "subcategory":"Office",
            "type":"Public Place"
        }
    ],
    "sg:postcode":"IV30 3PD",
    "sg:province":"Moray",
    "sg:tags":[
        "local",
        "authority"
    ],
    "wof:name":"Lhanbryde Primary School",
    "wof:placetype":"venue"
},
  "geometry": {"coordinates":[-3.317868948,57.6493682861],"type":"Point"}
}