{
  "type": "Feature",
  "properties": {
    "addr:full":"Unit 7, The Gateway Indstl Est, Parkgate Rotherham South Yorkshire S62 6JL",
    "addr:housenumber":"unit 7",
    "addr:postcode":"s62 6jl",
    "addr:street":"The Gateway Indstl Est Parkgate",
    "iso:country":"GB",
    "sg:address":"Unit 7, The Gateway Indstl Est, Parkgate",
    "sg:city":"Rotherham",
    "sg:classifiers":[
        {
            "category":"Retail",
            "subcategory":"Auto Repair",
            "type":"Services"
        }
    ],
    "sg:phone":"+44 1709 719000",
    "sg:postcode":"S62 6JL",
    "sg:province":"South Yorkshire",
    "sg:tags":[
        "body",
        "car"
    ],
    "wof:name":"Gateway Auto Refinishers Ltd",
    "wof:placetype":"venue"
},
  "geometry": {"coordinates":[-1.347464,53.446651],"type":"Point"}
}