{
  "type": "Feature",
  "properties": {
    "addr:full":"90a Chester Road, Sutton Weaver Runcorn Cheshire WA7 3DY",
    "addr:housenumber":"90a",
    "addr:postcode":"wa7 3dy",
    "addr:street":"Chester Road;Weaver",
    "iso:country":"GB",
    "sg:address":"90a Chester Road, Sutton Weaver",
    "sg:city":"Runcorn",
    "sg:classifiers":[
        {
            "category":"Professional",
            "subcategory":"Computer Services",
            "type":"Services"
        }
    ],
    "sg:phone":"+44 7771 601668",
    "sg:postcode":"WA7 3DY",
    "sg:province":"Cheshire",
    "sg:tags":[
        "system",
        "software"
    ],
    "wof:name":"Gairlan Ltd.",
    "wof:placetype":"venue"
},
  "geometry": {"coordinates":[-2.6762979031,53.3127708435],"type":"Point"}
}