{
  "type": "Feature",
  "properties": {
    "addr:full":"14a Mapledale Avenue Croydon Surrey CR0 5TB",
    "addr:housenumber":"14a",
    "addr:postcode":"cr0 5tb",
    "addr:street":"Mapledale Avenue",
    "iso:country":"GB",
    "sg:address":"14a Mapledale Avenue",
    "sg:city":"Croydon",
    "sg:classifiers":[
        {
            "category":"Professional",
            "subcategory":"Management & Consulting",
            "type":"Services"
        }
    ],
    "sg:postcode":"CR0 5TB",
    "sg:province":"Surrey",
    "sg:tags":[
        "consultant",
        "business"
    ],
    "wof:name":"Amity Consulting Enterprises Ltd",
    "wof:placetype":"venue"
},
  "geometry": {"coordinates":[-0.069426,51.372311],"type":"Point"}
}