{
  "type": "Feature",
  "properties": {
    "addr:full":"Start Hill Bishops Stortford Essex CM22 7DW",
    "addr:postcode":"cm22 7dw",
    "iso:country":"GB",
    "sg:address":"Start Hill",
    "sg:city":"Bishops Stortford",
    "sg:classifiers":[
        {
            "category":"Autos & Motor Vehicles",
            "subcategory":"Automobile Sales",
            "type":"Retail Goods"
        }
    ],
    "sg:phone":"+44 1279 712200",
    "sg:postcode":"CM22 7DW",
    "sg:province":"Essex",
    "sg:tags":[
        "car"
    ],
    "wof:name":"Spellbrook Ltd.",
    "wof:placetype":"venue"
},
  "geometry": {"coordinates":[0.1619500071,51.8723297119],"type":"Point"}
}