{
  "type": "Feature",
  "properties": {
    "iso:country":"GB",
    "sg:address":"Unit 27, Strawberry Lane Industrial Estat",
    "sg:city":"Willenhall",
    "sg:classifiers":[
        {
            "category":"Manufacturing",
            "subcategory":"Electronics",
            "type":"Manufacturing & Wholesale Goods"
        }
    ],
    "sg:postcode":"WV13 3RS",
    "sg:province":"West Midlands",
    "sg:tags":[
        "control",
        "component",
        "-",
        "electronic"
    ],
    "wof:name":"Kasdon Electronics Ltd.",
    "wof:placetype":"venue"
},
  "geometry": {"coordinates":[-2.083489,52.588806],"type":"Point"}
}