{
  "type": "Feature",
  "properties": {
    "addr:full":"76 Main Street Alexandria Argyll and Bute G83 0PB",
    "addr:housenumber":"76",
    "addr:postcode":"g83 0pb",
    "addr:street":"Main Street",
    "iso:country":"GB",
    "sg:address":"76 Main Street",
    "sg:city":"Alexandria",
    "sg:classifiers":[
        {
            "category":"Fast Food",
            "type":"Food & Drink"
        }
    ],
    "sg:postcode":"G83 0PB",
    "sg:province":"Argyll and Bute",
    "sg:tags":[
        "away",
        "take"
    ],
    "wof:name":"Spice of Life",
    "wof:placetype":"venue"
},
  "geometry": {"coordinates":[-4.5827970505,55.988243103],"type":"Point"}
}