{
  "type": "Feature",
  "properties": {
    "addr:full":"3 Quantock View, Clyce Road Highbridge Somerset TA9 3DJ",
    "addr:housenumber":"3",
    "addr:postcode":"ta9 3dj",
    "addr:street":"Quantock View Clyce Road",
    "iso:country":"GB",
    "sg:address":"3 Quantock View, Clyce Road",
    "sg:city":"Highbridge",
    "sg:classifiers":[
        {
            "category":"Building & Trades",
            "subcategory":"Plumbing",
            "type":"Services"
        }
    ],
    "sg:postcode":"TA9 3DJ",
    "sg:province":"Somerset",
    "sg:tags":[
        "heating"
    ],
    "wof:name":"Mayday 24 Hr",
    "wof:placetype":"venue"
},
  "geometry": {"coordinates":[-2.974914,51.222324],"type":"Point"}
}