{
  "type": "Feature",
  "properties": {
    "iso:country":"GB",
    "sg:address":"79 Fordmoss Walk",
    "sg:city":"Newcastle-upon-tyne",
    "sg:classifiers":[
        {
            "category":"Manufacturing",
            "subcategory":"Paper Products",
            "type":"Manufacturing & Wholesale Goods"
        }
    ],
    "sg:phone":"+44 191 286 5138",
    "sg:postcode":"NE5 2RQ",
    "sg:province":"Tyne and Wear",
    "sg:tags":[
        "cardboard"
    ],
    "wof:name":"Metro Decorators",
    "wof:placetype":"venue"
},
  "geometry": {"coordinates":[-1.6884089708,54.993560791],"type":"Point"}
}