{
  "type": "Feature",
  "properties": {
    "addr:full":"45 Paddock Drive, Springfield Chelmsford Essex CM1 6SS",
    "addr:housenumber":"45",
    "addr:postcode":"cm1 6ss",
    "addr:street":"Paddock Drive",
    "iso:country":"GB",
    "sg:address":"45 Paddock Drive, Springfield",
    "sg:city":"Chelmsford",
    "sg:classifiers":[
        {
            "category":"Building & Trades",
            "subcategory":"Construction",
            "type":"Services"
        }
    ],
    "sg:phone":"+44 1245 463203",
    "sg:postcode":"CM1 6SS",
    "sg:province":"Essex",
    "sg:tags":[
        "builder"
    ],
    "wof:name":"Handyman Property Services",
    "wof:placetype":"venue"
},
  "geometry": {"coordinates":[0.495972991,51.7584991455],"type":"Point"}
}