{
  "type": "Feature",
  "properties": {
    "iso:country":"GB",
    "sg:address":"28 Hathaway Green Lane",
    "sg:city":"Stratford-upon-avon",
    "sg:classifiers":[
        {
            "category":"Building & Trades",
            "subcategory":"Construction",
            "type":"Services"
        }
    ],
    "sg:phone":"+44 1789 297011",
    "sg:postcode":"CV37 9HX",
    "sg:province":"Warwickshire",
    "sg:tags":[
        "glazier",
        "decorator",
        "painter"
    ],
    "wof:name":"M A Edkins",
    "wof:placetype":"venue"
},
  "geometry": {"coordinates":[-1.7386399508,52.1949501038],"type":"Point"}
}