{
  "type": "Feature",
  "properties": {
    "addr:full":"Thomas St Bristol City of Bristol BS2 9LL",
    "addr:postcode":"bs2 9ll",
    "addr:street":"Thomas St",
    "iso:country":"GB",
    "sg:address":"Thomas St",
    "sg:city":"Bristol",
    "sg:classifiers":[
        {
            "category":"Place Of Worship",
            "type":"Public Place"
        }
    ],
    "sg:phone":"+44 117 955 1755",
    "sg:postcode":"BS2 9LL",
    "sg:province":"City of Bristol",
    "wof:name":"St Agnes C of E Church",
    "wof:placetype":"venue"
},
  "geometry": {"coordinates":[-2.578124,51.465179],"type":"Point"}
}