{
  "type": "Feature",
  "properties": {
    "iso:country":"GB",
    "sg:address":"Unit 23, 65 South Parade",
    "sg:city":"Sutton Coldfield",
    "sg:classifiers":[
        {
            "category":"Shopping",
            "subcategory":"Tobacco",
            "type":"Retail Goods"
        }
    ],
    "sg:phone":"+44 121 321 2150",
    "sg:postcode":"B72 1QX",
    "sg:province":"West Midlands",
    "sg:tags":[
        "tobacconist"
    ],
    "wof:name":"Cigs 'R' Us",
    "wof:placetype":"venue"
},
  "geometry": {"coordinates":[-1.823032,52.561859],"type":"Point"}
}