{
  "type": "Feature",
  "properties": {
    "iso:country":"GB",
    "sg:address":"47 Stanford Rd",
    "sg:city":"Brighton",
    "sg:classifiers":[
        {
            "category":"Building & Trades",
            "subcategory":"Plumbing",
            "type":"Services"
        }
    ],
    "sg:postcode":"BN1 5DH",
    "sg:province":"East Sussex",
    "sg:tags":[
        "heating"
    ],
    "wof:name":"Pavilion Plumbers",
    "wof:placetype":"venue"
},
  "geometry": {"coordinates":[-0.147202,50.83485],"type":"Point"}
}