{
  "type": "Feature",
  "properties": {
    "addr:full":"82 St Aldates Oxford Oxfordshire OX1 1RA",
    "addr:housenumber":"82",
    "addr:postcode":"ox1 1ra",
    "addr:street":"St Aldates",
    "iso:country":"GB",
    "sg:address":"82 St Aldates",
    "sg:city":"Oxford",
    "sg:classifiers":[
        {
            "category":"Restaurant",
            "type":"Food & Drink"
        }
    ],
    "sg:postcode":"OX1 1RA",
    "sg:province":"Oxfordshire",
    "sg:tags":[
        "french"
    ],
    "wof:name":"Elizabeth Restaurant",
    "wof:placetype":"venue"
},
  "geometry": {"coordinates":[-1.2566770315,51.7488174438],"type":"Point"}
}