{
  "type": "Feature",
  "properties": {
    "addr:full":"1 Wordsworth Road Abingdon Oxfordshire OX14 5NY",
    "addr:housenumber":"1",
    "addr:postcode":"ox14 5ny",
    "addr:street":"Wordsworth Road",
    "iso:country":"GB",
    "sg:address":"1 Wordsworth Road",
    "sg:city":"Abingdon",
    "sg:classifiers":[
        {
            "category":"Building & Trades",
            "subcategory":"Construction",
            "type":"Services"
        }
    ],
    "sg:postcode":"OX14 5NY",
    "sg:province":"Oxfordshire",
    "sg:tags":[
        "builder"
    ],
    "wof:name":"J & S Carroll",
    "wof:placetype":"venue"
},
  "geometry": {"coordinates":[-1.2987749577,51.6647758484],"type":"Point"}
}