{
  "type": "Feature",
  "properties": {
    "addr:full":"119 Ecclesall Road South Sheffield Derbyshire S11 9PJ",
    "addr:housenumber":"119",
    "addr:postcode":"s11 9pj",
    "addr:street":"Ecclesall Road South",
    "iso:country":"GB",
    "sg:address":"119 Ecclesall Road South",
    "sg:city":"Sheffield",
    "sg:classifiers":[
        {
            "category":"Banks & Credit Unions",
            "subcategory":"Bank",
            "type":"Services"
        }
    ],
    "sg:phone":"+44 114 275 6677",
    "sg:postcode":"S11 9PJ",
    "sg:province":"Derbyshire",
    "wof:name":"NatWest",
    "wof:placetype":"venue"
},
  "geometry": {"coordinates":[-1.512069,53.35598],"type":"Point"}
}