{
  "type": "Feature",
  "properties": {
    "iso:country":"GB",
    "sg:address":"2 Canada Road",
    "sg:city":"Deal",
    "sg:classifiers":[
        {
            "category":"Personal",
            "subcategory":"Tattoo Parlor",
            "type":"Services"
        }
    ],
    "sg:phone":"+44 1304 361831",
    "sg:postcode":"CT14 7DZ",
    "sg:province":"Kent",
    "sg:tags":[
        "tattooing",
        "piercing"
    ],
    "wof:name":"Painless Jeffs Tattoo Studio",
    "wof:placetype":"venue"
},
  "geometry": {"coordinates":[1.401685,51.212543],"type":"Point"}
}