{
  "type": "Feature",
  "properties": {
    "iso:country":"GB",
    "sg:address":"Allostock Grange, Middlewich Road Allostock",
    "sg:city":"Knutsford",
    "sg:classifiers":[
        {
            "category":"Education",
            "subcategory":"Music School",
            "type":"Public Place"
        }
    ],
    "sg:postcode":"WA16 9JX",
    "sg:province":"Cheshire",
    "wof:name":"Cheshire School of Music Ltd.",
    "wof:placetype":"venue"
},
  "geometry": {"coordinates":[-2.3833479881,53.2358093262],"type":"Point"}
}