{
  "type": "Feature",
  "properties": {
    "addr:full":"2 Park Road New Milton Hampshire BH25 5DR",
    "addr:housenumber":"2",
    "addr:postcode":"bh25 5dr",
    "addr:street":"Park Road",
    "iso:country":"GB",
    "sg:address":"2 Park Road",
    "sg:city":"New Milton",
    "sg:classifiers":[
        {
            "category":"Home & Garden",
            "subcategory":"Building Materials",
            "type":"Retail Goods"
        }
    ],
    "sg:postcode":"BH25 5DR",
    "sg:province":"Hampshire",
    "sg:tags":[
        "fencing"
    ],
    "wof:name":"C A Earwicker",
    "wof:placetype":"venue"
},
  "geometry": {"coordinates":[-1.6433609724,50.7641372681],"type":"Point"}
}