{
  "type": "Feature",
  "properties": {
    "iso:country":"GB",
    "sg:address":", Doublebois",
    "sg:city":"Liskeard",
    "sg:classifiers":[
        {
            "category":"Recreation",
            "subcategory":"Campground",
            "type":"Entertainment"
        }
    ],
    "sg:phone":"+44 1579 320183",
    "sg:postcode":"PL14 6LD",
    "sg:province":"Cornwall",
    "sg:tags":[
        "caravan",
        "park"
    ],
    "wof:name":"Pine Green Caravan Park",
    "wof:placetype":"venue"
},
  "geometry": {"coordinates":[-4.531299,50.457909],"type":"Point"}
}