{
  "type": "Feature",
  "properties": {
    "iso:country":"GB",
    "sg:address":"Unit 3, 19 The Grn, Nettleham",
    "sg:city":"Lincoln",
    "sg:classifiers":[
        {
            "category":"Personal",
            "subcategory":"Beauty Salon",
            "type":"Services"
        },
        {
            "category":"Personal",
            "subcategory":"Barber",
            "type":"Services"
        }
    ],
    "sg:phone":"+44 1522 595859",
    "sg:postcode":"LN2 2NR",
    "sg:province":"Lincolnshire",
    "sg:tags":[
        "unisex",
        "hairdresser"
    ],
    "wof:name":"Free Style Hair Designs",
    "wof:placetype":"venue"
},
  "geometry": {"coordinates":[-0.5045790076,53.2660713196],"type":"Point"}
}