{
  "type": "Feature",
  "properties": {
    "addr:full":"Palatine Street Manchester Greater Manchester M34 3LY",
    "addr:postcode":"m34 3ly",
    "addr:street":"Palatine Street",
    "iso:country":"GB",
    "sg:address":"Palatine Street",
    "sg:city":"Manchester",
    "sg:classifiers":[
        {
            "category":"Communications",
            "subcategory":"News Services",
            "type":"Services"
        }
    ],
    "sg:phone":"+44 161 320 9800",
    "sg:postcode":"M34 3LY",
    "sg:province":"Greater Manchester",
    "sg:tags":[
        "press"
    ],
    "wof:name":"J Higgins",
    "wof:placetype":"venue"
},
  "geometry": {"coordinates":[-2.1176640987,53.4618148804],"type":"Point"}
}