{
  "type": "Feature",
  "properties": {
    "iso:country":"GB",
    "sg:address":"Yew Tree Cottage, High Clere",
    "sg:city":"Newbury",
    "sg:classifiers":[
        {
            "category":"Building & Trades",
            "subcategory":"Construction",
            "type":"Services"
        }
    ],
    "sg:postcode":"RG20 9QZ",
    "sg:province":"Berkshire",
    "sg:tags":[
        "builder"
    ],
    "wof:name":"B.G. Sturt & Son",
    "wof:placetype":"venue"
},
  "geometry": {"coordinates":[-1.3754899502,51.3499412537],"type":"Point"}
}