{
  "type": "Feature",
  "properties": {
    "addr:full":"Warcock Farm, Warcock Lane Bacup Lancashire OL13 9ES",
    "addr:postcode":"ol13 9es",
    "addr:street":"Warcock Lane",
    "iso:country":"GB",
    "sg:address":"Warcock Farm, Warcock Lane",
    "sg:city":"Bacup",
    "sg:classifiers":[
        {
            "category":"Utilities",
            "subcategory":"Recycling",
            "type":"Services"
        }
    ],
    "sg:phone":"+44 1706 873308",
    "sg:postcode":"OL13 9ES",
    "sg:province":"Lancashire",
    "sg:tags":[
        "merchant",
        "waste"
    ],
    "wof:name":"J M Ashworth (Waste) Ltd.",
    "wof:placetype":"venue"
},
  "geometry": {"coordinates":[-2.186734,53.704906],"type":"Point"}
}