{
  "type": "Feature",
  "properties": {
    "addr:full":"Fairview House, Dunmore Falkirk Falkirk FK2 8RY",
    "addr:postcode":"fk2 8ry",
    "addr:street":"Dunmore",
    "iso:country":"GB",
    "sg:address":"Fairview House, Dunmore",
    "sg:city":"Falkirk",
    "sg:classifiers":[
        {
            "category":"Building & Trades",
            "subcategory":"Construction",
            "type":"Services"
        }
    ],
    "sg:phone":"+44 1324 831999",
    "sg:postcode":"FK2 8RY",
    "sg:province":"Falkirk",
    "sg:tags":[
        "builder"
    ],
    "wof:name":"Fairley Homes",
    "wof:placetype":"venue"
},
  "geometry": {"coordinates":[-3.7826740742,56.0841941833],"type":"Point"}
}