{
  "type": "Feature",
  "properties": {
    "addr:full":"Fellside Chp Plant Seascale Cumbria CA20 1PG",
    "addr:postcode":"ca20 1pg",
    "iso:country":"GB",
    "sg:address":"Fellside Chp Plant",
    "sg:city":"Seascale",
    "sg:classifiers":[
        {
            "category":"Utilities",
            "subcategory":"Electric",
            "type":"Services"
        }
    ],
    "sg:phone":"+44 19467 29028",
    "sg:postcode":"CA20 1PG",
    "sg:province":"Cumbria",
    "sg:tags":[
        "electricity"
    ],
    "wof:name":"John Brown Engineering Ltd",
    "wof:placetype":"venue"
},
  "geometry": {"coordinates":[-3.4846200943,54.394821167],"type":"Point"}
}