{
  "type": "Feature",
  "properties": {
    "addr:full":"65 Willenhall Road Wolverhampton West Midlands WV1 2HL",
    "addr:postcode":"wv1 2hl",
    "addr:street":"Willenhall Road",
    "iso:country":"GB",
    "sg:address":"65 Willenhall Road",
    "sg:city":"Wolverhampton",
    "sg:classifiers":[
        {
            "category":"Food & Beverages",
            "subcategory":"Liquor & Beverages",
            "type":"Retail Goods"
        }
    ],
    "sg:phone":"+44 1902 453114",
    "sg:postcode":"WV1 2HL",
    "sg:province":"West Midlands",
    "sg:tags":[
        "beer",
        "spirit",
        "wines"
    ],
    "wof:name":"Mayco Stores",
    "wof:placetype":"venue"
},
  "geometry": {"coordinates":[-2.104112,52.583485],"type":"Point"}
}