{
  "type": "Feature",
  "properties": {
    "iso:country":"GB",
    "sg:address":"30 Cornfield Road",
    "sg:city":"Eastbourne",
    "sg:classifiers":[
        {
            "category":"Retail",
            "subcategory":"Storage",
            "type":"Services"
        }
    ],
    "sg:phone":"+44 1323 417218",
    "sg:postcode":"BN21 4QH",
    "sg:province":"East Sussex",
    "sg:tags":[
        "household",
        "removal"
    ],
    "wof:name":"Gary Tonks",
    "wof:placetype":"venue"
},
  "geometry": {"coordinates":[0.284625,50.766869],"type":"Point"}
}