{
  "type": "Feature",
  "properties": {
    "iso:country":"GB",
    "sg:address":"The Orchard, Gatcombe",
    "sg:city":"Newport",
    "sg:classifiers":[
        {
            "category":"Building & Trades",
            "subcategory":"Construction",
            "type":"Services"
        }
    ],
    "sg:phone":"+44 1983 721246",
    "sg:postcode":"PO30 3EF",
    "sg:province":"Isle of Wight",
    "sg:tags":[
        "contractor",
        "pool",
        "swimming"
    ],
    "wof:name":"Corbett Floral Arts Ltd.",
    "wof:placetype":"venue"
},
  "geometry": {"coordinates":[-1.308636,50.664509],"type":"Point"}
}