{
  "type": "Feature",
  "properties": {
    "addr:full":"89 Mallory Road, Bishops Gachbrook Leamington Spa Warwickshire CV33 9QZ",
    "addr:housenumber":"89",
    "addr:postcode":"cv33 9qz",
    "addr:street":"Mallory Road;Gachbrook",
    "iso:country":"GB",
    "sg:address":"89 Mallory Road, Bishops Gachbrook",
    "sg:city":"Leamington Spa",
    "sg:classifiers":[
        {
            "category":"Building & Trades",
            "subcategory":"Construction",
            "type":"Services"
        }
    ],
    "sg:postcode":"CV33 9QZ",
    "sg:province":"Warwickshire",
    "sg:tags":[
        "builder"
    ],
    "wof:name":"Arthur G R Hales",
    "wof:placetype":"venue"
},
  "geometry": {"coordinates":[-1.5491360426,52.2484970093],"type":"Point"}
}