{
  "type": "Feature",
  "properties": {
    "addr:full":"68 Brunel Road Maidenhead Berkshire SL6 2RT",
    "addr:housenumber":"68",
    "addr:postcode":"sl6 2rt",
    "addr:street":"Brunel Road",
    "iso:country":"GB",
    "sg:address":"68 Brunel Road",
    "sg:city":"Maidenhead",
    "sg:classifiers":[
        {
            "category":"Retail",
            "subcategory":"Storage",
            "type":"Services"
        }
    ],
    "sg:phone":"+44 1628 635336",
    "sg:postcode":"SL6 2RT",
    "sg:province":"Berkshire",
    "sg:tags":[
        "household",
        "activity",
        "domestic",
        "removal"
    ],
    "wof:name":"Man With A Luton Van",
    "wof:placetype":"venue"
},
  "geometry": {"coordinates":[-0.7360630035,51.5153083801],"type":"Point"}
}