{
  "type": "Feature",
  "properties": {
    "iso:country":"GB",
    "sg:address":"46 New Street",
    "sg:city":"Birmingham",
    "sg:classifiers":[
        {
            "category":"Shopping",
            "subcategory":"Books",
            "type":"Retail Goods"
        }
    ],
    "sg:phone":"+44 121 643 2882",
    "sg:postcode":"B2 4LL",
    "sg:province":"West Midlands",
    "sg:tags":[
        "bookseller",
        "retailer"
    ],
    "wof:name":"Leicester Book Clearance",
    "wof:placetype":"venue"
},
  "geometry": {"coordinates":[-1.8993649483,52.4792556763],"type":"Point"}
}