{
  "type": "Feature",
  "properties": {
    "addr:full":"16 East Church Street Buckie Moray AB56 1AE",
    "addr:housenumber":"16",
    "addr:postcode":"ab56 1ae",
    "addr:street":"East Church Street",
    "iso:country":"GB",
    "sg:address":"16 East Church Street",
    "sg:city":"Buckie",
    "sg:classifiers":[
        {
            "category":"Professional",
            "subcategory":"Lawyer & Legal Services",
            "type":"Services"
        }
    ],
    "sg:phone":"+44 1542 831307",
    "sg:postcode":"AB56 1AE",
    "sg:province":"Moray",
    "sg:tags":[
        "solicitor"
    ],
    "wof:name":"Alexander George & Co",
    "wof:placetype":"venue"
},
  "geometry": {"coordinates":[-2.962102,57.676983],"type":"Point"}
}