{
  "type": "Feature",
  "properties": {
    "iso:country":"GB",
    "sg:address":"1 Old Market Avenue",
    "sg:city":"Chichester",
    "sg:classifiers":[
        {
            "category":"Manufacturing",
            "subcategory":"Tools & Machinery",
            "type":"Manufacturing & Wholesale Goods"
        },
        {
            "category":"Insurance",
            "subcategory":"Insurance Agent",
            "type":"Services"
        }
    ],
    "sg:phone":"+44 1243 784282",
    "sg:postcode":"PO19 1SP",
    "sg:province":"West Sussex",
    "sg:tags":[
        "society",
        "friendly"
    ],
    "wof:name":"Co-Operative Insurance Society Ltd.",
    "wof:placetype":"venue"
},
  "geometry": {"coordinates":[-0.779178,50.833946],"type":"Point"}
}