{
  "type": "Feature",
  "properties": {
    "addr:full":"Marlborough Rd Cardiff Cardiff CF23 5BU",
    "addr:postcode":"cf23 5bu",
    "addr:street":"Marlborough Rd",
    "iso:country":"GB",
    "sg:address":"Marlborough Rd",
    "sg:city":"Cardiff",
    "sg:classifiers":[
        {
            "category":"Arena",
            "subcategory":"Sports Club",
            "type":"Entertainment"
        }
    ],
    "sg:phone":"+44 29 2049 1865",
    "sg:postcode":"CF23 5BU",
    "sg:province":"Cardiff",
    "wof:name":"Penylan Bowling & Lawn Tennis Club",
    "wof:placetype":"venue"
},
  "geometry": {"coordinates":[-3.1642789841,51.4960632324],"type":"Point"}
}