{
  "type": "Feature",
  "properties": {
    "addr:full":"2 Avon View Cottage, Pembroke Road, Shirehampton Bristol City of Bristol BS11 9SF",
    "addr:housenumber":"2;view",
    "addr:postcode":"bs11 9sf",
    "addr:street":"Avon;Pembroke Road",
    "iso:country":"GB",
    "sg:address":"2 Avon View Cottage, Pembroke Road, Shirehampton",
    "sg:city":"Bristol",
    "sg:classifiers":[
        {
            "category":"Home & Garden",
            "subcategory":"Carpets & Floor Coverings",
            "type":"Retail Goods"
        }
    ],
    "sg:phone":"+44 117 982 3624",
    "sg:postcode":"BS11 9SF",
    "sg:province":"City of Bristol",
    "sg:tags":[
        "cleaner",
        "upholstery"
    ],
    "wof:name":"Chem-Dry Bristol",
    "wof:placetype":"venue"
},
  "geometry": {"coordinates":[-2.688614,51.483135],"type":"Point"}
}