{
  "type": "Feature",
  "properties": {
    "addr:full":"21 Kent Rd, Wollaston Stourbridge Staffordshire DY8 4TS",
    "addr:housenumber":"21",
    "addr:postcode":"dy8 4ts",
    "addr:street":"Kent Rd",
    "iso:country":"GB",
    "sg:address":"21 Kent Rd, Wollaston",
    "sg:city":"Stourbridge",
    "sg:classifiers":[
        {
            "category":"Manufacturing",
            "subcategory":"Petroleum Products",
            "type":"Manufacturing & Wholesale Goods"
        }
    ],
    "sg:phone":"+44 1384 393126",
    "sg:postcode":"DY8 4TS",
    "sg:province":"Staffordshire",
    "sg:tags":[
        "double",
        "glazing"
    ],
    "wof:name":"Total Windows & Building Services",
    "wof:placetype":"venue"
},
  "geometry": {"coordinates":[-2.167038,52.467209],"type":"Point"}
}