{
  "type": "Feature",
  "properties": {
    "addr:full":"219 Stratford Road, Shirley Solihull West Midlands B90 3AH",
    "addr:housenumber":"219",
    "addr:postcode":"b90 3ah",
    "addr:street":"Stratford Road",
    "iso:country":"GB",
    "sg:address":"219 Stratford Road, Shirley",
    "sg:city":"Solihull",
    "sg:classifiers":[
        {
            "category":"Professional",
            "subcategory":"Employment Agencies",
            "type":"Services"
        }
    ],
    "sg:phone":"+44 121 744 4411",
    "sg:postcode":"B90 3AH",
    "sg:province":"West Midlands",
    "sg:tags":[
        "consultant",
        "recruitment"
    ],
    "sg:website":"http://www.teg77.com",
    "wof:name":"Travail Employment Group Ltd",
    "wof:placetype":"venue"
},
  "geometry": {"coordinates":[-1.826534,52.411968],"type":"Point"}
}