{
  "type": "Feature",
  "properties": {
    "iso:country":"GB",
    "sg:address":"Community Flat, 23 Quentin St",
    "sg:city":"Glasgow",
    "sg:classifiers":[
        {
            "category":"Social Services",
            "subcategory":"Adult Care",
            "type":"Services"
        }
    ],
    "sg:phone":"+44 141 649 3927",
    "sg:postcode":"G41 3TY",
    "sg:province":"Glasgow City",
    "sg:tags":[
        "day",
        "centre"
    ],
    "wof:name":"Crossmyloof Residents Association",
    "wof:placetype":"venue"
},
  "geometry": {"coordinates":[-4.28377,55.832378],"type":"Point"}
}