{
  "type": "Feature",
  "properties": {
    "iso:country":"GB",
    "sg:address":"5-7 St Marys Lane, North Ockendon",
    "sg:city":"Upminster",
    "sg:classifiers":[
        {
            "category":"Wholesale",
            "subcategory":"Scrap",
            "type":"Manufacturing & Wholesale Goods"
        }
    ],
    "sg:phone":"+44 1708 640781",
    "sg:postcode":"RM14 3PA",
    "sg:province":"Essex",
    "sg:tags":[
        "breaker",
        "dismantlers"
    ],
    "wof:name":"Just V W",
    "wof:placetype":"venue"
},
  "geometry": {"coordinates":[0.2497,51.556221],"type":"Point"}
}