{
  "type": "Feature",
  "properties": {
    "iso:country":"GB",
    "sg:address":"30 Lansdowne Road",
    "sg:city":"Luton",
    "sg:classifiers":[
        {
            "category":"Social Services",
            "subcategory":"Retirement Home",
            "type":"Services"
        }
    ],
    "sg:phone":"+44 1582 726265",
    "sg:postcode":"LU3 1EE",
    "sg:province":"Bedfordshire",
    "sg:tags":[
        "residential",
        "care"
    ],
    "wof:name":"St.Annes",
    "wof:placetype":"venue"
},
  "geometry": {"coordinates":[-0.424749,51.888844],"type":"Point"}
}