{
  "type": "Feature",
  "properties": {
    "addr:full":"122 Vine St South Shields Tyne and Wear NE33 4RG",
    "addr:housenumber":"122",
    "addr:postcode":"ne33 4rg",
    "addr:street":"Vine St",
    "iso:country":"GB",
    "sg:address":"122 Vine St",
    "sg:city":"South Shields",
    "sg:classifiers":[
        {
            "category":"Professional",
            "type":"Services"
        }
    ],
    "sg:phone":"+44 191 455 2297",
    "sg:postcode":"NE33 4RG",
    "sg:province":"Tyne and Wear",
    "sg:tags":[
        "repair",
        "tech",
        "maintenance"
    ],
    "wof:name":"Durham Computer Services Ltd",
    "wof:placetype":"venue"
},
  "geometry": {"coordinates":[-1.4379349947,54.9764251709],"type":"Point"}
}