{
  "type": "Feature",
  "properties": {
    "addr:full":"3 Market Place Egremont Cumbria CA22 2AE",
    "addr:housenumber":"3",
    "addr:postcode":"ca22 2ae",
    "addr:street":"Market Place",
    "iso:country":"GB",
    "sg:address":"3 Market Place",
    "sg:city":"Egremont",
    "sg:classifiers":[
        {
            "category":"Taxi",
            "type":"Transportation"
        },
        {
            "category":"Military Area",
            "subcategory":"Air Force Base",
            "type":"Public Place"
        }
    ],
    "sg:phone":"+44 1946 820913",
    "sg:postcode":"CA22 2AE",
    "sg:province":"Cumbria",
    "sg:tags":[
        "mini",
        "hire",
        "private",
        "cab"
    ],
    "wof:name":"Egremont Cabs",
    "wof:placetype":"venue"
},
  "geometry": {"coordinates":[-3.529288,54.483418],"type":"Point"}
}