{
  "type": "Feature",
  "properties": {
    "addr:full":"12 Priory Rd Worcester Worcestershire WR2 4PE",
    "addr:housenumber":"12",
    "addr:postcode":"wr2 4pe",
    "addr:street":"Priory Rd",
    "iso:country":"GB",
    "sg:address":"12 Priory Rd",
    "sg:city":"Worcester",
    "sg:classifiers":[
        {
            "category":"Wholesale",
            "subcategory":"Sporting Goods",
            "type":"Manufacturing & Wholesale Goods"
        }
    ],
    "sg:phone":"+44 1905 425848",
    "sg:postcode":"WR2 4PE",
    "sg:province":"Worcestershire",
    "sg:tags":[
        "mnfr",
        "sport",
        "equipment"
    ],
    "wof:name":"Raven Products Sports Bags",
    "wof:placetype":"venue"
},
  "geometry": {"coordinates":[-2.239547,52.180775],"type":"Point"}
}