{
  "type": "Feature",
  "properties": {
    "addr:full":"129 Trowell Gro, Long Eaton Nottingham Derbyshire NG10 4BA",
    "addr:housenumber":"129",
    "addr:postcode":"ng10 4ba",
    "addr:street":"Trowell Gro",
    "iso:country":"GB",
    "sg:address":"129 Trowell Gro, Long Eaton",
    "sg:city":"Nottingham",
    "sg:classifiers":[
        {
            "category":"Shopping",
            "subcategory":"News",
            "type":"Retail Goods"
        }
    ],
    "sg:postcode":"NG10 4BA",
    "sg:province":"Derbyshire",
    "sg:tags":[
        "newsagent"
    ],
    "wof:name":"Pickering,R & C A,Newsagents",
    "wof:placetype":"venue"
},
  "geometry": {"coordinates":[-1.288846,52.905849],"type":"Point"}
}