{
  "type": "Feature",
  "properties": {
    "addr:full":"Ashton Street Trowbridge Wiltshire BA14 7EU",
    "addr:postcode":"ba14 7eu",
    "addr:street":"Ashton Street",
    "iso:country":"GB",
    "sg:address":"Ashton Street",
    "sg:city":"Trowbridge",
    "sg:classifiers":[
        {
            "category":"Social Services",
            "type":"Services"
        },
        {
            "category":"Government",
            "subcategory":"Office",
            "type":"Public Place"
        }
    ],
    "sg:phone":"+44 1225 753780",
    "sg:postcode":"BA14 7EU",
    "sg:province":"Wiltshire",
    "sg:tags":[
        "local"
    ],
    "wof:name":"Ashton Street Resource Centre",
    "wof:placetype":"venue"
},
  "geometry": {"coordinates":[-2.1968140602,51.3216400146],"type":"Point"}
}