{
  "type": "Feature",
  "properties": {
    "addr:full":"Suite 10 D Kirkgate Business Centre, Stennard Island Wakefield West Yorkshire WF1 5DL",
    "addr:housenumber":"business centre",
    "addr:postcode":"wf1 5dl",
    "addr:street":"Suite 10 D Kirkgate;Island",
    "iso:country":"GB",
    "sg:address":"Suite 10 D Kirkgate Business Centre, Stennard Island",
    "sg:city":"Wakefield",
    "sg:classifiers":[
        {
            "category":"Professional",
            "subcategory":"Management & Consulting",
            "type":"Services"
        }
    ],
    "sg:phone":"+44 1924 211196",
    "sg:postcode":"WF1 5DL",
    "sg:province":"West Yorkshire",
    "sg:tags":[
        "consultant",
        "business"
    ],
    "wof:name":"Forward Sales Agency The",
    "wof:placetype":"venue"
},
  "geometry": {"coordinates":[-1.4906640053,53.6772842407],"type":"Point"}
}