{
  "type": "Feature",
  "properties": {
    "addr:full":"150 Weston Road Stafford Staffordshire ST16 3RU",
    "addr:housenumber":"150",
    "addr:postcode":"st16 3ru",
    "addr:street":"Weston Road",
    "iso:country":"GB",
    "sg:address":"150 Weston Road",
    "sg:city":"Stafford",
    "sg:classifiers":[
        {
            "category":"Shopping",
            "subcategory":"Pets & Pet Supplies",
            "type":"Retail Goods"
        }
    ],
    "sg:phone":"+44 1785 246800",
    "sg:postcode":"ST16 3RU",
    "sg:province":"Staffordshire",
    "wof:name":"Burnden House Veterinary Centre",
    "wof:placetype":"venue"
},
  "geometry": {"coordinates":[-2.096682,52.808952],"type":"Point"}
}