{
  "type": "Feature",
  "properties": {
    "addr:full":"26 Cranham Drive Worcester Worcestershire WR4 9PA",
    "addr:housenumber":"26",
    "addr:postcode":"wr4 9pa",
    "addr:street":"Cranham Drive",
    "iso:country":"GB",
    "sg:address":"26 Cranham Drive",
    "sg:city":"Worcester",
    "sg:classifiers":[
        {
            "category":"Shopping",
            "subcategory":"News",
            "type":"Retail Goods"
        }
    ],
    "sg:phone":"+44 1905 754090",
    "sg:postcode":"WR4 9PA",
    "sg:province":"Worcestershire",
    "sg:tags":[
        "newsagent"
    ],
    "wof:name":"Martin the Newsagent",
    "wof:placetype":"venue"
},
  "geometry": {"coordinates":[-2.1870961189,52.2099227905],"type":"Point"}
}