{
  "type": "Feature",
  "properties": {
    "addr:full":"90 Belville Street Greenock Inverclyde PA15 4TA",
    "addr:housenumber":"90",
    "addr:postcode":"pa15 4ta",
    "addr:street":"Belville Street Greenock",
    "iso:country":"GB",
    "sg:address":"90 Belville Street",
    "sg:city":"Greenock",
    "sg:classifiers":[
        {
            "category":"Retail",
            "subcategory":"Laundry & Dry Cleaning",
            "type":"Services"
        }
    ],
    "sg:phone":"+44 1475 791511",
    "sg:postcode":"PA15 4TA",
    "sg:province":"Inverclyde",
    "sg:tags":[
        "launderette"
    ],
    "wof:name":"Belville Launderette",
    "wof:placetype":"venue"
},
  "geometry": {"coordinates":[-4.736374,55.942303],"type":"Point"}
}