{
  "type": "Feature",
  "properties": {
    "addr:full":"School Lane Chalfont St Giles Buckinghamshire HP8 4JJ",
    "addr:postcode":"hp8 4jj",
    "addr:street":"School Lane",
    "iso:country":"GB",
    "sg:address":"School Lane",
    "sg:city":"Chalfont St Giles",
    "sg:classifiers":[
        {
            "category":"Farming",
            "subcategory":"Nursery",
            "type":"Manufacturing & Wholesale Goods"
        },
        {
            "category":"Education",
            "subcategory":"School",
            "type":"Public Place"
        }
    ],
    "sg:phone":"+44 1494 872160",
    "sg:postcode":"HP8 4JJ",
    "sg:province":"Buckinghamshire",
    "sg:tags":[
        "creche",
        "local",
        "authority"
    ],
    "wof:name":"Chalfont St. Giles Nursery Class",
    "wof:placetype":"venue"
},
  "geometry": {"coordinates":[-0.572681,51.63203],"type":"Point"}
}