{
  "type": "Feature",
  "properties": {
    "addr:full":"2-8 Belper Road Derby Derbyshire DE1 3EN",
    "addr:housenumber":"2-8",
    "addr:postcode":"de1 3en",
    "addr:street":"Belper Road",
    "iso:country":"GB",
    "sg:address":"2-8 Belper Road",
    "sg:city":"Derby",
    "sg:classifiers":[
        {
            "category":"Social Services",
            "subcategory":"Retirement Home",
            "type":"Services"
        }
    ],
    "sg:phone":"+44 1332 344476",
    "sg:postcode":"DE1 3EN",
    "sg:province":"Derbyshire",
    "sg:tags":[
        "rest"
    ],
    "wof:name":"Oakleigh Rest Home Ltd.",
    "wof:placetype":"venue"
},
  "geometry": {"coordinates":[-1.482401967,52.9303207397],"type":"Point"}
}