{
  "type": "Feature",
  "properties": {
    "iso:country":"GB",
    "sg:address":"Chesney Wold, Bleak Hall Indstrial Estate, Bleak Hall",
    "sg:city":"Milton Keynes",
    "sg:classifiers":[
        {
            "category":"Manufacturing",
            "subcategory":"Building Materials",
            "type":"Manufacturing & Wholesale Goods"
        }
    ],
    "sg:phone":"+44 1908 670211",
    "sg:postcode":"MK6 1LW",
    "sg:province":"Buckinghamshire",
    "sg:tags":[
        "merchant",
        "builder"
    ],
    "wof:name":"Keyline Builders Merchants Ltd.",
    "wof:placetype":"venue"
},
  "geometry": {"coordinates":[-0.753512,52.020439],"type":"Point"}
}