{
  "type": "Feature",
  "properties": {
    "addr:full":"9 Connaught Road East Cowes Isle of Wight PO32 6DP",
    "addr:housenumber":"9",
    "addr:postcode":"po32 6dp",
    "addr:street":"Connaught Road",
    "iso:country":"GB",
    "sg:address":"9 Connaught Road",
    "sg:city":"East Cowes",
    "sg:classifiers":[
        {
            "category":"Place Of Worship",
            "type":"Public Place"
        }
    ],
    "sg:phone":"+44 1983 292726",
    "sg:postcode":"PO32 6DP",
    "sg:province":"Isle of Wight",
    "wof:name":"St. David S Catholic Church",
    "wof:placetype":"venue"
},
  "geometry": {"coordinates":[-1.2827459574,50.7540969849],"type":"Point"}
}