{
  "type": "Feature",
  "properties": {
    "addr:full":"Brands Lane, Lawshall Bury St Edmunds Suffolk IP29 4SF",
    "addr:postcode":"ip29 4sf",
    "addr:street":"Brands Lane",
    "iso:country":"GB",
    "sg:address":"Brands Lane, Lawshall",
    "sg:city":"Bury St Edmunds",
    "sg:classifiers":[
        {
            "category":"Transit Center",
            "subcategory":"Passenger",
            "type":"Transportation"
        },
        {
            "category":"Retail",
            "subcategory":"Pet Boarding",
            "type":"Services"
        }
    ],
    "sg:phone":"+44 1284 830333",
    "sg:postcode":"IP29 4SF",
    "sg:province":"Suffolk",
    "sg:tags":[
        "kennel",
        "catteries"
    ],
    "wof:name":"Gold Star Boarding Kennels",
    "wof:placetype":"venue"
},
  "geometry": {"coordinates":[0.715255,52.176598],"type":"Point"}
}