{
  "type": "Feature",
  "properties": {
    "addr:full":"3 Pentland View Court Currie City of Edinburgh EH14 5NP",
    "addr:housenumber":"3",
    "addr:postcode":"eh14 5np",
    "addr:street":"Pentland View Court",
    "iso:country":"GB",
    "sg:address":"3 Pentland View Court",
    "sg:city":"Currie",
    "sg:classifiers":[
        {
            "category":"Food & Beverages",
            "subcategory":"Liquor & Beverages",
            "type":"Retail Goods"
        }
    ],
    "sg:phone":"+44 131 449 6834",
    "sg:postcode":"EH14 5NP",
    "sg:province":"City of Edinburgh",
    "sg:tags":[
        "beer",
        "spirit",
        "wines"
    ],
    "wof:name":"The Wine Rack",
    "wof:placetype":"venue"
},
  "geometry": {"coordinates":[-3.3129930496,55.8963928223],"type":"Point"}
}