{
  "type": "Feature",
  "properties": {
    "addr:full":"33 Litchfield Street Walsall West Midlands WS1 1TJ",
    "addr:housenumber":"33",
    "addr:postcode":"ws1 1tj",
    "addr:street":"Litchfield Street",
    "iso:country":"GB",
    "sg:address":"33 Litchfield Street",
    "sg:city":"Walsall",
    "sg:classifiers":[
        {
            "category":"Real Estate",
            "subcategory":"Surveying",
            "type":"Services"
        }
    ],
    "sg:postcode":"WS1 1TJ",
    "sg:province":"West Midlands",
    "sg:tags":[
        "surveyor",
        "quantity"
    ],
    "wof:name":"John Punch Frics",
    "wof:placetype":"venue"
},
  "geometry": {"coordinates":[-1.976104,52.585289],"type":"Point"}
}