{
  "type": "Feature",
  "properties": {
    "iso:country":"GB",
    "sg:address":"492 London Rd",
    "sg:city":"Westcliff On Sea",
    "sg:classifiers":[
        {
            "category":"Professional",
            "subcategory":"Lawyer & Legal Services",
            "type":"Services"
        }
    ],
    "sg:phone":"+44 1702 392939",
    "sg:postcode":"SS0 9LD",
    "sg:province":"Essex",
    "sg:tags":[
        "solicitor"
    ],
    "wof:name":"David Webb",
    "wof:placetype":"venue"
},
  "geometry": {"coordinates":[0.689411,51.544445],"type":"Point"}
}