{
  "type": "Feature",
  "properties": {
    "addr:full":"24 Highfield Road Ilfracombe Devon EX34 9LZ",
    "addr:housenumber":"24",
    "addr:postcode":"ex34 9lz",
    "addr:street":"Highfield Road",
    "iso:country":"GB",
    "sg:address":"24 Highfield Road",
    "sg:city":"Ilfracombe",
    "sg:classifiers":[
        {
            "category":"Retail",
            "subcategory":"Veterinary Services",
            "type":"Services"
        }
    ],
    "sg:phone":"+44 1271 867711",
    "sg:postcode":"EX34 9LZ",
    "sg:province":"Devon",
    "sg:tags":[
        "surgeon",
        "activity"
    ],
    "wof:name":"Argyll Veterinary Clinic",
    "wof:placetype":"venue"
},
  "geometry": {"coordinates":[-4.116401,51.206924],"type":"Point"}
}