{
  "type": "Feature",
  "properties": {
    "iso:country":"GB",
    "sg:address":"251 Twyford Avenue",
    "sg:city":"Portsmouth",
    "sg:classifiers":[
        {
            "category":"Building & Trades",
            "subcategory":"Cleaning & Sanitation",
            "type":"Services"
        },
        {
            "category":"Social Services",
            "subcategory":"Adult Care",
            "type":"Services"
        }
    ],
    "sg:phone":"+44 23 9266 0523",
    "sg:postcode":"PO2 8NY",
    "sg:province":"Hampshire",
    "sg:tags":[
        "contracting",
        "commercial",
        "domestic"
    ],
    "wof:name":"Pyrimid Cleaning & Interior Landscaping Services",
    "wof:placetype":"venue"
},
  "geometry": {"coordinates":[-1.084669,50.820034],"type":"Point"}
}