{
  "type": "Feature",
  "properties": {
    "addr:full":"Unit 10, Sandy Road, Scone Perth Perth and Kinross PH2 6JU",
    "addr:housenumber":"unit 10",
    "addr:postcode":"ph2 6ju",
    "addr:street":"Sandy Road",
    "iso:country":"GB",
    "sg:address":"Unit 10, Sandy Road, Scone",
    "sg:city":"Perth",
    "sg:classifiers":[
        {
            "category":"Retail",
            "subcategory":"Auto Repair",
            "type":"Services"
        }
    ],
    "sg:postcode":"PH2 6JU",
    "sg:province":"Perth and Kinross",
    "sg:tags":[
        "body",
        "car"
    ],
    "wof:name":"Scone Spray Shop",
    "wof:placetype":"venue"
},
  "geometry": {"coordinates":[-3.406808,56.422775],"type":"Point"}
}