{
  "type": "Feature",
  "properties": {
    "iso:country":"GB",
    "sg:address":"5 Broadway Market, Fencepiece Road",
    "sg:city":"Ilford",
    "sg:classifiers":[
        {
            "category":"Social Services",
            "subcategory":"Adult Care",
            "type":"Services"
        }
    ],
    "sg:postcode":"IG6 2JT",
    "sg:province":"Essex",
    "sg:tags":[
        "domestic",
        "cleaning"
    ],
    "wof:name":"Molly Maid",
    "wof:placetype":"venue"
},
  "geometry": {"coordinates":[0.08479,51.594639],"type":"Point"}
}