{
  "type": "Feature",
  "properties": {
    "addr:full":"Long Spinney, Sand Lane Macclesfield Cheshire SK10 4TS",
    "addr:postcode":"sk10 4ts",
    "addr:street":"Long Spinney Sand Lane",
    "iso:country":"GB",
    "sg:address":"Long Spinney, Sand Lane",
    "sg:city":"Macclesfield",
    "sg:classifiers":[
        {
            "category":"Professional",
            "subcategory":"Management & Consulting",
            "type":"Services"
        }
    ],
    "sg:postcode":"SK10 4TS",
    "sg:province":"Cheshire",
    "sg:tags":[
        "consultant",
        "business"
    ],
    "wof:name":"Ogden Dodd Associates Ltd",
    "wof:placetype":"venue"
},
  "geometry": {"coordinates":[-2.2412600517,53.2844810486],"type":"Point"}
}