{
  "type": "Feature",
  "properties": {
    "iso:country":"GB",
    "sg:address":"Shedfield House, Shedfield House Dairy Yard, Sandy Lane",
    "sg:city":"Southampton",
    "sg:classifiers":[
        {
            "category":"Retail",
            "subcategory":"Repair Shop",
            "type":"Services"
        }
    ],
    "sg:phone":"+44 1329 835525",
    "sg:postcode":"SO32 2HQ",
    "sg:province":"Hampshire",
    "sg:tags":[
        "furniture"
    ],
    "wof:name":"Yesterdays Beds",
    "wof:placetype":"venue"
},
  "geometry": {"coordinates":[-1.21395,50.921261],"type":"Point"}
}