{
  "type": "Feature",
  "properties": {
    "addr:full":"27 Broad Street Newent Gloucestershire GL18 1AQ",
    "addr:housenumber":"27",
    "addr:postcode":"gl18 1aq",
    "addr:street":"Broad Street",
    "iso:country":"GB",
    "sg:address":"27 Broad Street",
    "sg:city":"Newent",
    "sg:classifiers":[
        {
            "category":"Shopping",
            "subcategory":"News",
            "type":"Retail Goods"
        }
    ],
    "sg:phone":"+44 1531 820288",
    "sg:postcode":"GL18 1AQ",
    "sg:province":"Gloucestershire",
    "sg:tags":[
        "newsagent"
    ],
    "wof:name":"Gregsons News",
    "wof:placetype":"venue"
},
  "geometry": {"coordinates":[-2.4058830738,51.9307632446],"type":"Point"}
}