{
  "type": "Feature",
  "properties": {
    "addr:full":"Brockdish Hall, Brockdish Diss Norfolk IP21 4JS",
    "addr:housenumber":"brockdish",
    "addr:postcode":"ip21 4js",
    "addr:street":"Brockdish",
    "iso:country":"GB",
    "sg:address":"Brockdish Hall, Brockdish",
    "sg:city":"Diss",
    "sg:classifiers":[
        {
            "category":"Banks & Credit Unions",
            "subcategory":"Investment Brokerage",
            "type":"Services"
        }
    ],
    "sg:postcode":"IP21 4JS",
    "sg:province":"Norfolk",
    "sg:tags":[
        "contractor"
    ],
    "wof:name":"M Bradbury",
    "wof:placetype":"venue"
},
  "geometry": {"coordinates":[1.2411,52.368824],"type":"Point"}
}