{
  "type": "Feature",
  "properties": {
    "addr:full":"Business Link Building, 45 Grosvenor Road St Albans Hertfordshire AL1 3AW",
    "addr:housenumber":"45",
    "addr:postcode":"al1 3aw",
    "addr:street":"Grosvenor Road",
    "iso:country":"GB",
    "sg:address":"Business Link Building, 45 Grosvenor Road",
    "sg:city":"St Albans",
    "sg:classifiers":[
        {
            "category":"Professional",
            "subcategory":"Lawyer & Legal Services",
            "type":"Services"
        }
    ],
    "sg:phone":"+44 1727 854215",
    "sg:postcode":"AL1 3AW",
    "sg:province":"Hertfordshire",
    "sg:tags":[
        "patent",
        "agent"
    ],
    "wof:name":"Sommerville & Rushton",
    "wof:placetype":"venue"
},
  "geometry": {"coordinates":[-0.337752,51.753189],"type":"Point"}
}