{
  "type": "Feature",
  "properties": {
    "addr:full":"Unit 71 Barwell Business Park, Leatherhead Road Chessington Surrey KT9 2NY",
    "addr:housenumber":"unit 71",
    "addr:postcode":"kt9 2ny",
    "addr:street":"Barwell Business Park Leatherhead Road",
    "iso:country":"GB",
    "sg:address":"Unit 71 Barwell Business Park, Leatherhead Road",
    "sg:city":"Chessington",
    "sg:classifiers":[
        {
            "category":"Professional",
            "subcategory":"Business Services",
            "type":"Services"
        }
    ],
    "sg:phone":"+44 20 8410 0100",
    "sg:postcode":"KT9 2NY",
    "sg:province":"Surrey",
    "sg:tags":[
        "distribution"
    ],
    "wof:name":"Trembath Ltd.",
    "wof:placetype":"venue"
},
  "geometry": {"coordinates":[-0.3123289943,51.3527832031],"type":"Point"}
}