{
  "type": "Feature",
  "properties": {
    "addr:full":"26 Pear Tree Av Aylesford Kent ME20 6EB",
    "addr:housenumber":"26",
    "addr:postcode":"me20 6eb",
    "addr:street":"Pear Tree Av Aylesford",
    "iso:country":"GB",
    "sg:address":"26 Pear Tree Av",
    "sg:city":"Aylesford",
    "sg:classifiers":[
        {
            "category":"Building & Trades",
            "subcategory":"Plumbing",
            "type":"Services"
        }
    ],
    "sg:phone":"+44 1732 840324",
    "sg:postcode":"ME20 6EB",
    "sg:province":"Kent",
    "sg:tags":[
        "heating"
    ],
    "wof:name":"C & M Plumbing",
    "wof:placetype":"venue"
},
  "geometry": {"coordinates":[0.4565379918,51.2949104309],"type":"Point"}
}