{
  "type": "Feature",
  "properties": {
    "iso:country":"GB",
    "sg:address":"London Rd",
    "sg:city":"Pulborough",
    "sg:classifiers":[
        {
            "category":"Education",
            "subcategory":"School",
            "type":"Public Place"
        }
    ],
    "sg:phone":"+44 1903 877933",
    "sg:postcode":"RH20 4AY",
    "sg:province":"West Sussex",
    "sg:tags":[
        "independent",
        "preparatory"
    ],
    "wof:name":"Windlesham House School",
    "wof:placetype":"venue"
},
  "geometry": {"coordinates":[-0.405073,50.906063],"type":"Point"}
}