{
  "type": "Feature",
  "properties": {
    "iso:country":"GB",
    "sg:address":"Fides House, 10 Chertsey Road",
    "sg:city":"Woking",
    "sg:classifiers":[
        {
            "category":"Real Estate",
            "subcategory":"Real Estate Agent",
            "type":"Services"
        }
    ],
    "sg:phone":"+44 1483 730060",
    "sg:postcode":"GU21 5AB",
    "sg:province":"Surrey",
    "wof:name":"Davey Richard Associates Commercial Property Agenc",
    "wof:placetype":"venue"
},
  "geometry": {"coordinates":[-0.55684,51.319355],"type":"Point"}
}