{
  "type": "Feature",
  "properties": {
    "addr:full":"57 Green Park Rd Bromsgrove Worcestershire B60 2RD",
    "addr:housenumber":"57",
    "addr:postcode":"b60 2rd",
    "addr:street":"Green Park Rd",
    "iso:country":"GB",
    "sg:address":"57 Green Park Rd",
    "sg:city":"Bromsgrove",
    "sg:classifiers":[
        {
            "category":"Shopping",
            "subcategory":"Pets & Pet Supplies",
            "type":"Retail Goods"
        }
    ],
    "sg:phone":"+44 1527 577409",
    "sg:postcode":"B60 2RD",
    "sg:province":"Worcestershire",
    "sg:tags":[
        "food"
    ],
    "wof:name":"Oscars Pet Foods",
    "wof:placetype":"venue"
},
  "geometry": {"coordinates":[-2.048238,52.332302],"type":"Point"}
}