{
  "type": "Feature",
  "properties": {
    "iso:country":"GB",
    "sg:address":"Dental Surgery, 18 Magdalene St",
    "sg:city":"Glastonbury",
    "sg:classifiers":[
        {
            "category":"Health Services",
            "subcategory":"Dentist",
            "type":"Services"
        }
    ],
    "sg:phone":"+44 1458 832215",
    "sg:postcode":"BA6 9EH",
    "sg:province":"Somerset",
    "wof:name":"Wilson G E",
    "wof:placetype":"venue"
},
  "geometry": {"coordinates":[-2.717009,51.147591],"type":"Point"}
}