{
  "type": "Feature",
  "properties": {
    "iso:country":"GB",
    "sg:address":"63 Dale Street, Milnrow",
    "sg:city":"Rochdale",
    "sg:classifiers":[
        {
            "category":"Professional",
            "subcategory":"Art Services",
            "type":"Services"
        }
    ],
    "sg:phone":"+44 1706 642446",
    "sg:postcode":"OL16 3NJ",
    "sg:province":"Lancashire",
    "sg:tags":[
        "photographer"
    ],
    "wof:name":"Alpha Photography",
    "wof:placetype":"venue"
},
  "geometry": {"coordinates":[-2.109794,53.610023],"type":"Point"}
}