{
  "type": "Feature",
  "properties": {
    "addr:full":"British Waterways Yard, Cavendish Bridge Derby Derbyshire DE72 2HL",
    "addr:postcode":"de72 2hl",
    "addr:street":"British;Cavendish Bridge",
    "iso:country":"GB",
    "sg:address":"British Waterways Yard, Cavendish Bridge",
    "sg:city":"Derby",
    "sg:classifiers":[
        {
            "category":"Retail",
            "subcategory":"Auto Repair",
            "type":"Services"
        }
    ],
    "sg:phone":"+44 1332 792086",
    "sg:postcode":"DE72 2HL",
    "sg:province":"Derbyshire",
    "sg:tags":[
        "modification",
        "garage"
    ],
    "wof:name":"Kirkman Motor Engineers",
    "wof:placetype":"venue"
},
  "geometry": {"coordinates":[-1.3382300138,52.8640289307],"type":"Point"}
}