{
  "type": "Feature",
  "properties": {
    "addr:full":"Perdiswell Park Golf Centre, Bilford Rd Worcester Worcestershire WR3 8DX",
    "addr:postcode":"wr3 8dx",
    "addr:street":"Bilford Rd",
    "iso:country":"GB",
    "sg:address":"Perdiswell Park Golf Centre, Bilford Rd",
    "sg:city":"Worcester",
    "sg:classifiers":[
        {
            "category":"Government",
            "subcategory":"Office",
            "type":"Public Place"
        }
    ],
    "sg:phone":"+44 1905 457189",
    "sg:postcode":"WR3 8DX",
    "sg:province":"Worcestershire",
    "sg:tags":[
        "local"
    ],
    "wof:name":"Worcester City Council",
    "wof:placetype":"venue"
},
  "geometry": {"coordinates":[-2.21165,52.212971],"type":"Point"}
}