{
  "type": "Feature",
  "properties": {
    "iso:country":"GB",
    "sg:address":"26 Aston Road",
    "sg:city":"Waterlooville",
    "sg:classifiers":[
        {
            "category":"Professional",
            "subcategory":"Engineering",
            "type":"Services"
        }
    ],
    "sg:phone":"+44 23 9225 4341",
    "sg:postcode":"PO7 7UZ",
    "sg:province":"Hampshire",
    "sg:tags":[
        "engineer"
    ],
    "wof:name":"Premier Farnell Uk Ltd.",
    "wof:placetype":"venue"
},
  "geometry": {"coordinates":[-1.036566,50.885334],"type":"Point"}
}