{
  "type": "Feature",
  "properties": {
    "addr:full":"The Old Smithy, Water Street, Morland Penrith Cumbria CA10 3AY",
    "addr:postcode":"ca10 3ay",
    "addr:street":"Water Street",
    "iso:country":"GB",
    "sg:address":"The Old Smithy, Water Street, Morland",
    "sg:city":"Penrith",
    "sg:classifiers":[
        {
            "category":"Retail",
            "subcategory":"Repair Shop",
            "type":"Services"
        },
        {
            "category":"Manufacturing",
            "subcategory":"Furniture",
            "type":"Manufacturing & Wholesale Goods"
        }
    ],
    "sg:phone":"+44 1931 714245",
    "sg:postcode":"CA10 3AY",
    "sg:province":"Cumbria",
    "sg:tags":[
        "restored"
    ],
    "wof:name":"Ian Briggs",
    "wof:placetype":"venue"
},
  "geometry": {"coordinates":[-2.6275138855,54.5962257385],"type":"Point"}
}