{
  "type": "Feature",
  "properties": {
    "iso:country":"GB",
    "sg:address":"31-32 Duke Street",
    "sg:city":"Chelmsford",
    "sg:classifiers":[
        {
            "category":"Real Estate",
            "subcategory":"Real Estate Agent",
            "type":"Services"
        }
    ],
    "sg:phone":"+44 1245 344644",
    "sg:postcode":"CM1 1HY",
    "sg:province":"Essex",
    "wof:name":"Weir & Hodgkinson",
    "wof:placetype":"venue"
},
  "geometry": {"coordinates":[0.467573,51.736572],"type":"Point"}
}