{
  "type": "Feature",
  "properties": {
    "iso:country":"GB",
    "sg:address":"3 Bridge Pde, Streatham High Rd",
    "sg:city":"London",
    "sg:classifiers":[
        {
            "category":"Fast Food",
            "type":"Food & Drink"
        }
    ],
    "sg:postcode":"SW16 6EW",
    "sg:province":"Greater London",
    "sg:tags":[
        "away",
        "take"
    ],
    "wof:name":"Kirby,Alexina,",
    "wof:placetype":"venue"
},
  "geometry": {"coordinates":[-0.130909,51.429359],"type":"Point"}
}