{
  "type": "Feature",
  "properties": {
    "addr:full":"8 Victoria Road, Earby Barnoldswick Lancashire BB18 6UR",
    "addr:housenumber":"8",
    "addr:postcode":"bb18 6ur",
    "addr:street":"Victoria Road",
    "iso:country":"GB",
    "sg:address":"8 Victoria Road, Earby",
    "sg:city":"Barnoldswick",
    "sg:classifiers":[
        {
            "category":"Fast Food",
            "type":"Food & Drink"
        }
    ],
    "sg:postcode":"BB18 6UR",
    "sg:province":"Lancashire",
    "sg:tags":[
        "away",
        "take"
    ],
    "wof:name":"Porky's",
    "wof:placetype":"venue"
},
  "geometry": {"coordinates":[-2.14327,53.91729],"type":"Point"}
}