{
  "type": "Feature",
  "properties": {
    "iso:country":"GB",
    "sg:address":"33 Admirals Way",
    "sg:city":"Thetford",
    "sg:classifiers":[
        {
            "category":"Shopping",
            "subcategory":"News",
            "type":"Retail Goods"
        },
        {
            "category":"Government",
            "subcategory":"Post Office",
            "type":"Public Place"
        }
    ],
    "sg:postcode":"IP24 2LB",
    "sg:province":"Norfolk",
    "sg:tags":[
        "newsagent"
    ],
    "wof:name":"Admirals Way Post Office",
    "wof:placetype":"venue"
},
  "geometry": {"coordinates":[0.762569,52.423031],"type":"Point"}
}