{
  "type": "Feature",
  "properties": {
    "addr:full":"Unit 3 Cwmtawe Business Park, Pontardawe Indust Est Swansea Neath Port Talbot SA8 4HR",
    "addr:housenumber":"unit 3",
    "addr:postcode":"sa8 4hr",
    "addr:street":"Cwmtawe Business Park;Indust",
    "iso:country":"GB",
    "sg:address":"Unit 3 Cwmtawe Business Park, Pontardawe Indust Est",
    "sg:city":"Swansea",
    "sg:classifiers":[
        {
            "category":"Home & Garden",
            "subcategory":"Household Appliances",
            "type":"Retail Goods"
        }
    ],
    "sg:phone":"+44 1792 869660",
    "sg:postcode":"SA8 4HR",
    "sg:province":"Neath Port Talbot",
    "sg:tags":[
        "refrigeration",
        "air conditioning"
    ],
    "wof:name":"D R A C S Ltd",
    "wof:placetype":"venue"
},
  "geometry": {"coordinates":[-3.846144,51.72113],"type":"Point"}
}