{
  "type": "Feature",
  "properties": {
    "iso:country":"GB",
    "sg:address":"37 Main Street, Ewerby",
    "sg:city":"Sleaford",
    "sg:classifiers":[
        {
            "category":"Social Services",
            "subcategory":"Retirement Home",
            "type":"Services"
        }
    ],
    "sg:postcode":"NG34 9PH",
    "sg:province":"Lincolnshire",
    "sg:tags":[
        "residential",
        "care"
    ],
    "wof:name":"Amberley Residential Care Home",
    "wof:placetype":"venue"
},
  "geometry": {"coordinates":[-0.3314940035,53.0099334717],"type":"Point"}
}