{
  "type": "Feature",
  "properties": {
    "iso:country":"GB",
    "sg:address":"Priestwood Road, Harvel, Meopham",
    "sg:city":"Gravesend",
    "sg:classifiers":[
        {
            "category":"Shopping",
            "subcategory":"Pets & Pet Supplies",
            "type":"Retail Goods"
        }
    ],
    "sg:phone":"+44 1474 813999",
    "sg:postcode":"DA13 0DA",
    "sg:province":"Kent",
    "sg:tags":[
        "feed",
        "animal"
    ],
    "wof:name":"Net - Tex Industries Ltd.",
    "wof:placetype":"venue"
},
  "geometry": {"coordinates":[0.359182,51.381908],"type":"Point"}
}