{
  "type": "Feature",
  "properties": {
    "iso:country":"GB",
    "sg:address":"72 Victoria Road, Pinxton",
    "sg:city":"Nottingham",
    "sg:classifiers":[
        {
            "category":"Professional",
            "subcategory":"Art Services",
            "type":"Services"
        }
    ],
    "sg:phone":"+44 1773 812424",
    "sg:postcode":"NG16 6NE",
    "sg:province":"Derbyshire",
    "sg:tags":[
        "photographer"
    ],
    "wof:name":"Foto-Genic",
    "wof:placetype":"venue"
},
  "geometry": {"coordinates":[-1.317419,53.092999],"type":"Point"}
}