{
  "type": "Feature",
  "properties": {
    "addr:full":"Plum Tree Cottage, Maidstone Road Tonbridge Kent TN12 9AG",
    "addr:postcode":"tn12 9ag",
    "addr:street":"Plum;Maidstone Road",
    "iso:country":"GB",
    "sg:address":"Plum Tree Cottage, Maidstone Road",
    "sg:city":"Tonbridge",
    "sg:classifiers":[
        {
            "category":"Shopping",
            "subcategory":"Party Supplies",
            "type":"Retail Goods"
        },
        {
            "category":"Arts & Performance",
            "subcategory":"Music",
            "type":"Entertainment"
        }
    ],
    "sg:postcode":"TN12 9AG",
    "sg:province":"Kent",
    "sg:tags":[
        "mobile",
        "marquees",
        "disco",
        "tent",
        "floor"
    ],
    "wof:name":"Tony Lloyd Disco's",
    "wof:placetype":"venue"
},
  "geometry": {"coordinates":[0.50528,51.18174],"type":"Point"}
}