{
  "type": "Feature",
  "properties": {
    "iso:country":"GB",
    "sg:address":"71 Moss Lane",
    "sg:city":"Liverpool",
    "sg:classifiers":[
        {
            "category":"Food & Beverages",
            "subcategory":"Bakery",
            "type":"Retail Goods"
        }
    ],
    "sg:phone":"+44 151 525 0033",
    "sg:postcode":"L9 8AE",
    "sg:province":"Merseyside",
    "sg:tags":[
        "pizza"
    ],
    "wof:name":"La Casa Nostra",
    "wof:placetype":"venue"
},
  "geometry": {"coordinates":[-2.9675879478,53.4625244141],"type":"Point"}
}