{
  "type": "Feature",
  "properties": {
    "addr:full":"Unit C, Watlington Arc, 6 High St Watlington Buckinghamshire OX9 5PS",
    "addr:housenumber":"unit c;6",
    "addr:postcode":"ox9 5ps",
    "addr:street":"Arc;High St",
    "iso:country":"GB",
    "sg:address":"Unit C, Watlington Arc, 6 High St",
    "sg:city":"Watlington",
    "sg:classifiers":[
        {
            "category":"Shopping",
            "subcategory":"Florist",
            "type":"Retail Goods"
        }
    ],
    "sg:phone":"+44 1491 613775",
    "sg:postcode":"OX9 5PS",
    "sg:province":"Buckinghamshire",
    "wof:name":"Cottage Flowers",
    "wof:placetype":"venue"
},
  "geometry": {"coordinates":[-1.00568,51.644081],"type":"Point"}
}