{
  "type": "Feature",
  "properties": {
    "addr:full":"16 Quarry Road Irvine North Ayrshire KA12 0TH",
    "addr:housenumber":"16",
    "addr:postcode":"ka12 0th",
    "addr:street":"Quarry Road",
    "iso:country":"GB",
    "sg:address":"16 Quarry Road",
    "sg:city":"Irvine",
    "sg:classifiers":[
        {
            "category":"Retail",
            "subcategory":"Funeral Services",
            "type":"Services"
        }
    ],
    "sg:phone":"+44 1294 279193",
    "sg:postcode":"KA12 0TH",
    "sg:province":"North Ayrshire",
    "wof:name":"Conway William & Sons",
    "wof:placetype":"venue"
},
  "geometry": {"coordinates":[-4.667212,55.618553],"type":"Point"}
}