{
  "type": "Feature",
  "properties": {
    "addr:full":"Manor Hall, Calverhall Whitchurch Cheshire SY13 4PA",
    "addr:postcode":"sy13 4pa",
    "addr:street":"Whitchurch Cheshire",
    "iso:country":"GB",
    "sg:address":"Manor Hall, Calverhall",
    "sg:city":"Whitchurch",
    "sg:classifiers":[
        {
            "category":"Farming",
            "subcategory":"Livestock Farm",
            "type":"Manufacturing & Wholesale Goods"
        }
    ],
    "sg:phone":"+44 1948 890238",
    "sg:postcode":"SY13 4PA",
    "sg:province":"Cheshire",
    "sg:tags":[
        "others"
    ],
    "wof:name":"Philip S Kay",
    "wof:placetype":"venue"
},
  "geometry": {"coordinates":[-2.593144,52.931702],"type":"Point"}
}