{
  "type": "Feature",
  "properties": {
    "iso:country":"GB",
    "sg:address":"178 Turkey Road",
    "sg:city":"Bexhill-on-sea",
    "sg:classifiers":[
        {
            "category":"Home & Garden",
            "subcategory":"Carpets & Floor Coverings",
            "type":"Retail Goods"
        }
    ],
    "sg:postcode":"TN39 5HR",
    "sg:province":"East Sussex",
    "sg:tags":[
        "carpets",
        "rug",
        "matting"
    ],
    "wof:name":"Phillips Cleaning",
    "wof:placetype":"venue"
},
  "geometry": {"coordinates":[0.455483,50.857357],"type":"Point"}
}