{
  "type": "Feature",
  "properties": {
    "addr:full":"11-12 The Rushes Loughborough Leicestershire LE11 5BE",
    "addr:housenumber":"11-12",
    "addr:postcode":"le11 5be",
    "addr:street":"The Rushes",
    "iso:country":"GB",
    "sg:address":"11-12 The Rushes",
    "sg:city":"Loughborough",
    "sg:classifiers":[
        {
            "category":"Building & Trades",
            "subcategory":"Plumbing",
            "type":"Services"
        }
    ],
    "sg:phone":"+44 1509 212332",
    "sg:postcode":"LE11 5BE",
    "sg:province":"Leicestershire",
    "sg:tags":[
        "heating"
    ],
    "wof:name":"Hopkins (Plumbers) Ltd.",
    "wof:placetype":"venue"
},
  "geometry": {"coordinates":[-1.209561944,52.7733612061],"type":"Point"}
}