{
  "type": "Feature",
  "properties": {
    "addr:full":"Brynmeini Farm Glogue Pembrokeshire SA36 0DZ",
    "addr:postcode":"sa36 0dz",
    "iso:country":"GB",
    "sg:address":"Brynmeini Farm",
    "sg:city":"Glogue",
    "sg:classifiers":[
        {
            "category":"Farming",
            "subcategory":"Livestock Farm",
            "type":"Manufacturing & Wholesale Goods"
        }
    ],
    "sg:phone":"+44 1239 831372",
    "sg:postcode":"SA36 0DZ",
    "sg:province":"Pembrokeshire",
    "sg:tags":[
        "others"
    ],
    "wof:name":"Prescelli Seeds",
    "wof:placetype":"venue"
},
  "geometry": {"coordinates":[-4.5976390839,51.9622650146],"type":"Point"}
}