{
  "type": "Feature",
  "properties": {
    "iso:country":"GB",
    "sg:address":"Unit 1, Avon Terrace",
    "sg:city":"Salisbury",
    "sg:classifiers":[
        {
            "category":"Home & Garden",
            "subcategory":"Hardware",
            "type":"Retail Goods"
        }
    ],
    "sg:phone":"+44 1722 416110",
    "sg:postcode":"SP2 7BX",
    "sg:province":"Wiltshire",
    "wof:name":"Middleton Property Maintenance",
    "wof:placetype":"venue"
},
  "geometry": {"coordinates":[-1.8041490316,51.0753517151],"type":"Point"}
}