{
  "type": "Feature",
  "properties": {
    "iso:country":"GB",
    "sg:address":"Unit 27, Hillgrove Business Park",
    "sg:city":"Waltham Abbey",
    "sg:classifiers":[
        {
            "category":"Manufacturing",
            "subcategory":"Building Materials",
            "type":"Manufacturing & Wholesale Goods"
        }
    ],
    "sg:phone":"+44 1992 899255",
    "sg:postcode":"EN9 2HB",
    "sg:province":"Essex",
    "sg:tags":[
        "mnfr",
        "maker",
        "cabinet"
    ],
    "wof:name":"Field & Douglas",
    "wof:placetype":"venue"
},
  "geometry": {"coordinates":[0.00149,51.68642],"type":"Point"}
}