{
  "type": "Feature",
  "properties": {
    "iso:country":"GB",
    "sg:address":"Immingham Dock, Immingham",
    "sg:city":"Immingham",
    "sg:classifiers":[
        {
            "category":"Freight",
            "type":"Transportation"
        }
    ],
    "sg:phone":"+44 1469 575246",
    "sg:postcode":"DN40 2LZ",
    "sg:province":"Lincolnshire",
    "sg:tags":[
        "overseas",
        "shipping",
        "removal"
    ],
    "wof:name":"Clarkson Shipping",
    "wof:placetype":"venue"
},
  "geometry": {"coordinates":[-0.2289270014,53.633731842],"type":"Point"}
}