{
  "type": "Feature",
  "properties": {
    "iso:country":"GB",
    "sg:address":"Unit 1, Ashmore Lake Way",
    "sg:city":"Willenhall",
    "sg:classifiers":[
        {
            "category":"Building & Trades",
            "subcategory":"Construction",
            "type":"Services"
        }
    ],
    "sg:phone":"+44 1902 636634",
    "sg:postcode":"WV12 4LF",
    "sg:province":"West Midlands",
    "sg:tags":[
        "welder",
        "mechanical"
    ],
    "wof:name":"Sure Weld Engineers",
    "wof:placetype":"venue"
},
  "geometry": {"coordinates":[-2.0479109287,52.5951957703],"type":"Point"}
}