{
  "type": "Feature",
  "properties": {
    "iso:country":"GB",
    "sg:address":"92 Poole Road, Westbourne",
    "sg:city":"Bournemouth",
    "sg:classifiers":[
        {
            "category":"Shopping",
            "subcategory":"Thrift Store",
            "type":"Retail Goods"
        }
    ],
    "sg:phone":"+44 1202 751934",
    "sg:postcode":"BH4 9EN",
    "sg:province":"Dorset",
    "sg:tags":[
        "shop",
        "charity"
    ],
    "wof:name":"Help the Aged",
    "wof:placetype":"venue"
},
  "geometry": {"coordinates":[-1.903523,50.723297],"type":"Point"}
}