{
  "type": "Feature",
  "properties": {
    "addr:full":"Unit 6a Roxby Road Industrial Estate, Roxby Road Scunthorpe Lincolnshire DN15 9SX",
    "addr:housenumber":"unit 6a",
    "addr:postcode":"dn15 9sx",
    "addr:street":"Roxby Road Industrial Estate Roxby Road",
    "iso:country":"GB",
    "sg:address":"Unit 6a Roxby Road Industrial Estate, Roxby Road",
    "sg:city":"Scunthorpe",
    "sg:classifiers":[
        {
            "category":"Health Services",
            "subcategory":"Clinic",
            "type":"Services"
        }
    ],
    "sg:phone":"+44 1724 735000",
    "sg:postcode":"DN15 9SX",
    "sg:province":"Lincolnshire",
    "sg:tags":[
        "aromatherapy"
    ],
    "wof:name":"Razzmatazz Cane Furniture",
    "wof:placetype":"venue"
},
  "geometry": {"coordinates":[-0.6128240228,53.6515007019],"type":"Point"}
}