{
  "type": "Feature",
  "properties": {
    "addr:full":"253 Mansfield Road, Skedy Sutton-in-ashfield Nottinghamshire NG17 3DU",
    "addr:housenumber":"253",
    "addr:postcode":"ng17 3du",
    "addr:street":"Mansfield Road Skedy Sutton-In-Ashfield",
    "iso:country":"GB",
    "sg:address":"253 Mansfield Road, Skedy",
    "sg:city":"Sutton-in-ashfield",
    "sg:classifiers":[
        {
            "category":"Personal",
            "type":"Services"
        }
    ],
    "sg:phone":"+44 1623 443481",
    "sg:postcode":"NG17 3DU",
    "sg:province":"Nottinghamshire",
    "sg:tags":[
        "tailor"
    ],
    "wof:name":"Morris Jepson Ladies & Gentlemen Tailors",
    "wof:placetype":"venue"
},
  "geometry": {"coordinates":[-1.2506530285,53.140411377],"type":"Point"}
}