{
  "type": "Feature",
  "properties": {
    "addr:full":"146 North Rd Darlington Durham DL1 2EJ",
    "addr:housenumber":"146",
    "addr:postcode":"dl1 2ej",
    "addr:street":"North Rd",
    "iso:country":"GB",
    "sg:address":"146 North Rd",
    "sg:city":"Darlington",
    "sg:classifiers":[
        {
            "category":"Health Services",
            "subcategory":"Dentist",
            "type":"Services"
        }
    ],
    "sg:phone":"+44 1325 480628",
    "sg:postcode":"DL1 2EJ",
    "sg:province":"Durham",
    "sg:tags":[
        "technician",
        "instrument",
        "dental"
    ],
    "wof:name":"P.H Oldfield",
    "wof:placetype":"venue"
},
  "geometry": {"coordinates":[-1.55157,54.538986],"type":"Point"}
}