{
  "type": "Feature",
  "properties": {
    "addr:full":"238 Rochdale Road, Willowfield Halifax West Yorkshire HX2 7NL",
    "addr:housenumber":"238",
    "addr:postcode":"hx2 7nl",
    "addr:street":"Rochdale Road",
    "iso:country":"GB",
    "sg:address":"238 Rochdale Road, Willowfield",
    "sg:city":"Halifax",
    "sg:classifiers":[
        {
            "category":"Building & Trades",
            "subcategory":"Construction",
            "type":"Services"
        }
    ],
    "sg:phone":"+44 1422 344292",
    "sg:postcode":"HX2 7NL",
    "sg:province":"West Yorkshire",
    "sg:tags":[
        "decorator",
        "painter"
    ],
    "wof:name":"Norman Blackburn",
    "wof:placetype":"venue"
},
  "geometry": {"coordinates":[-1.8965879679,53.7152748108],"type":"Point"}
}