{
  "type": "Feature",
  "properties": {
    "addr:full":"66 Whitesands Dumfries Dumfries and Galloway DG1 2RS",
    "addr:housenumber":"66",
    "addr:postcode":"dg1 2rs",
    "addr:street":"Whitesands",
    "iso:country":"GB",
    "sg:address":"66 Whitesands",
    "sg:city":"Dumfries",
    "sg:classifiers":[
        {
            "category":"Bars & Pubs",
            "type":"Food & Drink"
        },
        {
            "category":"Community Center",
            "subcategory":"Social",
            "type":"Public Place"
        }
    ],
    "sg:phone":"+44 1387 279754",
    "sg:postcode":"DG1 2RS",
    "sg:province":"Dumfries and Galloway",
    "sg:tags":[
        "pubs",
        "house",
        "inn",
        "activity"
    ],
    "wof:name":"Coach & Horses Inn",
    "wof:placetype":"venue"
},
  "geometry": {"coordinates":[-3.6124389172,55.0672607422],"type":"Point"}
}