{
  "type": "Feature",
  "properties": {
    "addr:full":"334 Chester Road, Hartford Northwich Cheshire CW8 2AQ",
    "addr:housenumber":"334",
    "addr:postcode":"cw8 2aq",
    "addr:street":"Chester Road",
    "iso:country":"GB",
    "sg:address":"334 Chester Road, Hartford",
    "sg:city":"Northwich",
    "sg:classifiers":[
        {
            "category":"Retail",
            "subcategory":"Auto Repair",
            "type":"Services"
        }
    ],
    "sg:phone":"+44 1606 883416",
    "sg:postcode":"CW8 2AQ",
    "sg:province":"Cheshire",
    "sg:tags":[
        "modification",
        "garage"
    ],
    "wof:name":"Heyeswood Mot Service Centre",
    "wof:placetype":"venue"
},
  "geometry": {"coordinates":[-2.55841,53.241161],"type":"Point"}
}