{
  "type": "Feature",
  "properties": {
    "iso:country":"GB",
    "sg:address":"4 St Andrew Street",
    "sg:city":"Hertford",
    "sg:classifiers":[
        {
            "category":"Personal",
            "subcategory":"Beauty Salon",
            "type":"Services"
        }
    ],
    "sg:phone":"+44 1992 504039",
    "sg:postcode":"SG14 1JA",
    "sg:province":"Hertfordshire",
    "sg:tags":[
        "unisex",
        "hairdresser"
    ],
    "wof:name":"Vogue",
    "wof:placetype":"venue"
},
  "geometry": {"coordinates":[-0.080934,51.796993],"type":"Point"}
}