{
  "type": "Feature",
  "properties": {
    "iso:country":"GB",
    "sg:address":"The Old Tannery Tanyard Lane",
    "sg:city":"Steyning",
    "sg:classifiers":[
        {
            "category":"Real Estate",
            "subcategory":"Architect",
            "type":"Services"
        }
    ],
    "sg:phone":"+44 1903 879873",
    "sg:postcode":"BN44 3RJ",
    "sg:province":"West Sussex",
    "wof:name":"Rathbone Miller",
    "wof:placetype":"venue"
},
  "geometry": {"coordinates":[-0.3177250028,50.8827972412],"type":"Point"}
}