{
  "type": "Feature",
  "properties": {
    "iso:country":"GB",
    "sg:address":"19 Clarendon Ct",
    "sg:city":"Warrington",
    "sg:classifiers":[
        {
            "category":"Utilities",
            "subcategory":"Telephone",
            "type":"Services"
        }
    ],
    "sg:phone":"+44 1925 575252",
    "sg:postcode":"WA2 8QP",
    "sg:province":"Cheshire",
    "sg:tags":[
        "telecommunication"
    ],
    "wof:name":"Lake Communication Installations",
    "wof:placetype":"venue"
},
  "geometry": {"coordinates":[-2.6070458889,53.4215736389],"type":"Point"}
}