{
  "type": "Feature",
  "properties": {
    "addr:full":"424 Richmond Road Kingston-upon-thames Greater London KT2 5PU",
    "addr:housenumber":"424",
    "addr:postcode":"kt2 5pu",
    "addr:street":"Richmond Road",
    "iso:country":"GB",
    "sg:address":"424 Richmond Road",
    "sg:city":"Kingston-upon-thames",
    "sg:classifiers":[
        {
            "category":"Retail",
            "subcategory":"Laundry & Dry Cleaning",
            "type":"Services"
        }
    ],
    "sg:phone":"+44 20 8546 3990",
    "sg:postcode":"KT2 5PU",
    "sg:province":"Greater London",
    "sg:tags":[
        "alteration"
    ],
    "wof:name":"Sketchley Retail Ltd.",
    "wof:placetype":"venue"
},
  "geometry": {"coordinates":[-0.3069339991,51.4299507141],"type":"Point"}
}