{
  "type": "Feature",
  "properties": {
    "addr:full":"Parsonage Lane South Molton Devon EX36 3AX",
    "addr:postcode":"ex36 3ax",
    "addr:street":"Parsonage Lane",
    "iso:country":"GB",
    "sg:address":"Parsonage Lane",
    "sg:city":"South Molton",
    "sg:classifiers":[
        {
            "category":"Military Area",
            "subcategory":"Air Force Base",
            "type":"Public Place"
        }
    ],
    "sg:postcode":"EX36 3AX",
    "sg:province":"Devon",
    "sg:tags":[
        "taxi",
        "hire",
        "private"
    ],
    "wof:name":"South Molton Taxis Services",
    "wof:placetype":"venue"
},
  "geometry": {"coordinates":[-3.8344941139,51.0190963745],"type":"Point"}
}