{
  "type": "Feature",
  "properties": {
    "addr:full":"38 Shotton Lane, Shotton Deeside Flintshire CH5 1QT",
    "addr:housenumber":"38",
    "addr:postcode":"ch5 1qt",
    "addr:street":"Shotton Lane",
    "iso:country":"GB",
    "sg:address":"38 Shotton Lane, Shotton",
    "sg:city":"Deeside",
    "sg:classifiers":[
        {
            "category":"Health Services",
            "subcategory":"Doctor",
            "type":"Services"
        }
    ],
    "sg:phone":"+44 1244 812094",
    "sg:postcode":"CH5 1QT",
    "sg:province":"Flintshire",
    "sg:tags":[
        "practitioners"
    ],
    "wof:name":"Jolly Pritchard Markey Cliff (Drs)",
    "wof:placetype":"venue"
},
  "geometry": {"coordinates":[-3.036716,53.209114],"type":"Point"}
}