{
  "type": "Feature",
  "properties": {
    "addr:full":"7 Jubilee Road Burgess Hill East Sussex RH15 9TH",
    "addr:housenumber":"7",
    "addr:postcode":"rh15 9th",
    "addr:street":"Jubilee Road",
    "iso:country":"GB",
    "sg:address":"7 Jubilee Road",
    "sg:city":"Burgess Hill",
    "sg:classifiers":[
        {
            "category":"Retail",
            "subcategory":"Storage",
            "type":"Services"
        }
    ],
    "sg:phone":"+44 1444 242300",
    "sg:postcode":"RH15 9TH",
    "sg:province":"East Sussex",
    "sg:tags":[
        "household",
        "removal"
    ],
    "wof:name":"Pickfords Removals",
    "wof:placetype":"venue"
},
  "geometry": {"coordinates":[-0.1484010071,50.9532470703],"type":"Point"}
}