{
  "type": "Feature",
  "properties": {
    "iso:country":"GB",
    "sg:address":"10 Baddow Road",
    "sg:city":"Chelmsford",
    "sg:classifiers":[
        {
            "category":"Shopping",
            "subcategory":"Department Store",
            "type":"Retail Goods"
        },
        {
            "category":"Shopping",
            "subcategory":"Musical Instruments",
            "type":"Retail Goods"
        }
    ],
    "sg:postcode":"CM2 0DG",
    "sg:province":"Essex",
    "wof:name":"Sound World",
    "wof:placetype":"venue"
},
  "geometry": {"coordinates":[0.4743070006,51.7306289673],"type":"Point"}
}