{
  "type": "Feature",
  "properties": {
    "addr:full":"10 Wombwell Road, Hoyland Barnsley South Yorkshire S74 9SQ",
    "addr:housenumber":"10",
    "addr:postcode":"s74 9sq",
    "addr:street":"Wombwell Road;Yorkshire",
    "iso:country":"GB",
    "sg:address":"10 Wombwell Road, Hoyland",
    "sg:city":"Barnsley",
    "sg:classifiers":[
        {
            "category":"Government",
            "subcategory":"Post Office",
            "type":"Public Place"
        }
    ],
    "sg:phone":"+44 1226 742223",
    "sg:postcode":"S74 9SQ",
    "sg:province":"South Yorkshire",
    "wof:name":"D & N General News",
    "wof:placetype":"venue"
},
  "geometry": {"coordinates":[-1.440878,53.508984],"type":"Point"}
}