{
  "type": "Feature",
  "properties": {
    "iso:country":"GB",
    "sg:address":"69 Brockman Road",
    "sg:city":"Folkestone",
    "sg:classifiers":[
        {
            "category":"Food & Beverages",
            "subcategory":"Liquor & Beverages",
            "type":"Retail Goods"
        }
    ],
    "sg:phone":"+44 1303 252363",
    "sg:postcode":"CT20 1DJ",
    "sg:province":"Kent",
    "sg:tags":[
        "beer",
        "spirit",
        "wines"
    ],
    "wof:name":"Unwins Wine Merchants",
    "wof:placetype":"venue"
},
  "geometry": {"coordinates":[1.172049,51.082241],"type":"Point"}
}