{
  "type": "Feature",
  "properties": {
    "iso:country":"GB",
    "sg:address":"Castle Chambers, Mill Bridge",
    "sg:city":"Skipton",
    "sg:classifiers":[
        {
            "category":"Manufacturing",
            "subcategory":"Lumber",
            "type":"Manufacturing & Wholesale Goods"
        }
    ],
    "sg:postcode":"BD23 1NJ",
    "sg:province":"Lancashire",
    "sg:tags":[
        "importer",
        "merchants",
        "agent",
        "timber"
    ],
    "wof:name":"Bowdin,Keith E,Timber,",
    "wof:placetype":"venue"
},
  "geometry": {"coordinates":[-2.0185139179,53.9602012634],"type":"Point"}
}