{
  "type": "Feature",
  "properties": {
    "addr:full":"78 Birmingham Road, Ansley Nuneaton Leicestershire CV10 9PS",
    "addr:housenumber":"78",
    "addr:postcode":"cv10 9ps",
    "addr:street":"Birmingham Road",
    "iso:country":"GB",
    "sg:address":"78 Birmingham Road, Ansley",
    "sg:city":"Nuneaton",
    "sg:classifiers":[
        {
            "category":"Home & Garden",
            "subcategory":"Household Appliances",
            "type":"Retail Goods"
        },
        {
            "category":"Retail",
            "subcategory":"Repair Shop",
            "type":"Services"
        }
    ],
    "sg:phone":"+44 24 7639 4899",
    "sg:postcode":"CV10 9PS",
    "sg:province":"Leicestershire",
    "sg:tags":[
        "electrical",
        "television",
        "video",
        "radio"
    ],
    "wof:name":"T V Ryan & Video Services",
    "wof:placetype":"venue"
},
  "geometry": {"coordinates":[-1.5625400543,52.5217285156],"type":"Point"}
}