{
  "type": "Feature",
  "properties": {
    "iso:country":"GB",
    "sg:address":"1 Newhall Road",
    "sg:city":"Swadlincote",
    "sg:classifiers":[
        {
            "category":"Autos & Motor Vehicles",
            "subcategory":"Automobile Sales",
            "type":"Retail Goods"
        }
    ],
    "sg:phone":"+44 1283 222437",
    "sg:postcode":"DE11 0BA",
    "sg:province":"Derbyshire",
    "sg:tags":[
        "car"
    ],
    "wof:name":"Eaton Car Co",
    "wof:placetype":"venue"
},
  "geometry": {"coordinates":[-1.5518170595,52.7784156799],"type":"Point"}
}