{
  "type": "Feature",
  "properties": {
    "iso:country":"GB",
    "sg:address":"P O Box 266",
    "sg:city":"Staines",
    "sg:classifiers":[
        {
            "category":"Professional",
            "type":"Services"
        }
    ],
    "sg:phone":"+44 1784 880022",
    "sg:postcode":"TW18 4GP",
    "sg:province":"Berkshire",
    "sg:tags":[
        "directory",
        "pub"
    ],
    "wof:name":"London Christian Business Directory",
    "wof:placetype":"venue"
},
  "geometry": {"coordinates":[-0.5089390278,51.4347114563],"type":"Point"}
}