{
  "type": "Feature",
  "properties": {
    "iso:country":"GB",
    "sg:address":"12 Millgate",
    "sg:city":"Thirsk",
    "sg:classifiers":[
        {
            "category":"Shopping",
            "subcategory":"Antiques",
            "type":"Retail Goods"
        }
    ],
    "sg:postcode":"YO7 1AA",
    "sg:province":"North Yorkshire",
    "wof:name":"Millgate Pine & Antiques",
    "wof:placetype":"venue"
},
  "geometry": {"coordinates":[-1.341839,54.233517],"type":"Point"}
}