{
  "type": "Feature",
  "properties": {
    "addr:full":"3rd Floor Office, 44 High St Bridgnorth Shropshire WV16 4DX",
    "addr:housenumber":"3rd floor office 44",
    "addr:postcode":"wv16 4dx",
    "addr:street":"High St",
    "iso:country":"GB",
    "sg:address":"3rd Floor Office, 44 High St",
    "sg:city":"Bridgnorth",
    "sg:classifiers":[
        {
            "category":"Personal",
            "type":"Services"
        }
    ],
    "sg:phone":"+44 1746 762502",
    "sg:postcode":"WV16 4DX",
    "sg:province":"Shropshire",
    "sg:tags":[
        "tailor"
    ],
    "wof:name":"Higgins,N J,",
    "wof:placetype":"venue"
},
  "geometry": {"coordinates":[-2.420124,52.53624],"type":"Point"}
}