{
  "type": "Feature",
  "properties": {
    "addr:full":"40 Derwent Road, Skelton Saltburn-by-the-sea North Yorkshire TS12 2NU",
    "addr:housenumber":"40",
    "addr:postcode":"ts12 2nu",
    "addr:street":"Derwent Road",
    "iso:country":"GB",
    "sg:address":"40 Derwent Road, Skelton",
    "sg:city":"Saltburn-by-the-sea",
    "sg:classifiers":[
        {
            "category":"Building & Trades",
            "subcategory":"Cleaning & Sanitation",
            "type":"Services"
        }
    ],
    "sg:postcode":"TS12 2NU",
    "sg:province":"North Yorkshire",
    "sg:tags":[
        "cleaner",
        "window"
    ],
    "wof:name":"P Morgan Window Service",
    "wof:placetype":"venue"
},
  "geometry": {"coordinates":[-0.9828370214,54.5635108948],"type":"Point"}
}