{
  "type": "Feature",
  "properties": {
    "iso:country":"GB",
    "sg:address":"3 Manygates Lane",
    "sg:city":"Wakefield",
    "sg:classifiers":[
        {
            "category":"Personal",
            "subcategory":"Beauty Salon",
            "type":"Services"
        }
    ],
    "sg:phone":"+44 1924 255208",
    "sg:postcode":"WF1 5NJ",
    "sg:province":"West Yorkshire",
    "sg:tags":[
        "unisex",
        "hairdresser"
    ],
    "wof:name":"Ric's",
    "wof:placetype":"venue"
},
  "geometry": {"coordinates":[-1.487248,53.667118],"type":"Point"}
}