{
  "type": "Feature",
  "properties": {
    "addr:full":"2 Wellcroft Centre Shipley West Yorkshire BD18 3QH",
    "addr:housenumber":"2",
    "addr:postcode":"bd18 3qh",
    "addr:street":"Wellcroft Centre",
    "iso:country":"GB",
    "sg:address":"2 Wellcroft Centre",
    "sg:city":"Shipley",
    "sg:classifiers":[
        {
            "category":"Travel",
            "subcategory":"Travel Agent",
            "type":"Entertainment"
        }
    ],
    "sg:phone":"+44 1274 531209",
    "sg:postcode":"BD18 3QH",
    "sg:province":"West Yorkshire",
    "wof:name":"Lunn Poly Ltd.",
    "wof:placetype":"venue"
},
  "geometry": {"coordinates":[-1.77925,53.833069],"type":"Point"}
}