{
  "type": "Feature",
  "properties": {
    "addr:full":"139 Hamlet Court Road Westcliff-on-sea Essex SS0 7EW",
    "addr:housenumber":"139",
    "addr:postcode":"ss0 7ew",
    "addr:street":"Hamlet Court Road",
    "iso:country":"GB",
    "sg:address":"139 Hamlet Court Road",
    "sg:city":"Westcliff-on-sea",
    "sg:classifiers":[
        {
            "category":"Shopping",
            "subcategory":"Thrift Store",
            "type":"Retail Goods"
        }
    ],
    "sg:phone":"+44 1702 430611",
    "sg:postcode":"SS0 7EW",
    "sg:province":"Essex",
    "sg:tags":[
        "shop",
        "charity"
    ],
    "wof:name":"Mind",
    "wof:placetype":"venue"
},
  "geometry": {"coordinates":[0.6946150064,51.5403823853],"type":"Point"}
}