{
  "type": "Feature",
  "properties": {
    "addr:full":"Home Grove Farm, Hope Mansell Ross-on-wye Gloucestershire HR9 5TW",
    "addr:postcode":"hr9 5tw",
    "iso:country":"GB",
    "sg:address":"Home Grove Farm, Hope Mansell",
    "sg:city":"Ross-on-wye",
    "sg:classifiers":[
        {
            "category":"Farming",
            "subcategory":"Livestock Farm",
            "type":"Manufacturing & Wholesale Goods"
        }
    ],
    "sg:phone":"+44 1594 542510",
    "sg:postcode":"HR9 5TW",
    "sg:province":"Gloucestershire",
    "sg:tags":[
        "others"
    ],
    "wof:name":"John G Blenkin",
    "wof:placetype":"venue"
},
  "geometry": {"coordinates":[-2.5449590683,51.8729515076],"type":"Point"}
}