{
  "type": "Feature",
  "properties": {
    "addr:full":"17 Gold Tops Newport Newport NP20 4PH",
    "addr:housenumber":"17",
    "addr:postcode":"np20 4ph",
    "addr:street":"Gold Tops",
    "iso:country":"GB",
    "sg:address":"17 Gold Tops",
    "sg:city":"Newport",
    "sg:classifiers":[
        {
            "category":"Real Estate",
            "subcategory":"Real Estate Agent",
            "type":"Services"
        }
    ],
    "sg:postcode":"NP20 4PH",
    "sg:province":"Newport",
    "wof:name":"Linnells Property Consultants",
    "wof:placetype":"venue"
},
  "geometry": {"coordinates":[-3.0052700043,51.5894355774],"type":"Point"}
}