{
  "type": "Feature",
  "properties": {
    "addr:full":"40 Kemerton Road London Greater London SE5 9AR",
    "addr:housenumber":"40",
    "addr:postcode":"se5 9ar",
    "addr:street":"Kemerton Road",
    "iso:country":"GB",
    "sg:address":"40 Kemerton Road",
    "sg:city":"London",
    "sg:classifiers":[
        {
            "category":"Bars & Pubs",
            "type":"Food & Drink"
        }
    ],
    "sg:phone":"+44 20 7733 9001",
    "sg:postcode":"SE5 9AR",
    "sg:province":"Greater London",
    "sg:tags":[
        "pubs",
        "inn"
    ],
    "wof:name":"Cambria Arms",
    "wof:placetype":"venue"
},
  "geometry": {"coordinates":[-0.098136,51.464455],"type":"Point"}
}