{
  "type": "Feature",
  "properties": {
    "iso:country":"GB",
    "sg:address":"5-11 Denmark Grove, Alexandra Park",
    "sg:city":"Nottingham",
    "sg:classifiers":[
        {
            "category":"Health Services",
            "subcategory":"Nursing And Care Facility",
            "type":"Services"
        }
    ],
    "sg:phone":"+44 115 960 6595",
    "sg:postcode":"NG3 4JG",
    "sg:province":"Nottinghamshire",
    "sg:tags":[
        "home"
    ],
    "wof:name":"Edenhurst",
    "wof:placetype":"venue"
},
  "geometry": {"coordinates":[-1.1394649744,52.9724159241],"type":"Point"}
}