{
  "type": "Feature",
  "properties": {
    "iso:country":"GB",
    "sg:address":"8 Burleigh Court, Burleigh St",
    "sg:city":"Barnsley",
    "sg:classifiers":[
        {
            "category":"Organizations",
            "subcategory":"Non-profit Organization",
            "type":"Services"
        }
    ],
    "sg:phone":"+44 1226 779964",
    "sg:postcode":"S70 1XY",
    "sg:province":"South Yorkshire",
    "sg:tags":[
        "organisation",
        "voluntary",
        "charity"
    ],
    "wof:name":"Barnsley Crime Prevention Partnership",
    "wof:placetype":"venue"
},
  "geometry": {"coordinates":[-1.477928,53.549885],"type":"Point"}
}