{
  "type": "Feature",
  "properties": {
    "iso:country":"GB",
    "sg:address":"40 Wellings",
    "sg:city":"Kendal",
    "sg:classifiers":[
        {
            "category":"Building & Trades",
            "subcategory":"Construction",
            "type":"Services"
        }
    ],
    "sg:phone":"+44 1539 723463",
    "sg:postcode":"LA9 5LN",
    "sg:province":"Cumbria",
    "sg:tags":[
        "roofing"
    ],
    "wof:name":"Home Property Services",
    "wof:placetype":"venue"
},
  "geometry": {"coordinates":[-2.752002,54.320969],"type":"Point"}
}