{
  "type": "Feature",
  "properties": {
    "iso:country":"GB",
    "sg:address":"10 Coton Lane",
    "sg:city":"Birmingham",
    "sg:classifiers":[
        {
            "category":"Home & Garden",
            "subcategory":"Household Appliances",
            "type":"Retail Goods"
        },
        {
            "category":"Building & Trades",
            "subcategory":"Cleaning & Sanitation",
            "type":"Services"
        },
        {
            "category":"Retail",
            "subcategory":"Event Space",
            "type":"Services"
        }
    ],
    "sg:phone":"+44 121 373 3717",
    "sg:postcode":"B23 6TP",
    "sg:province":"West Midlands",
    "sg:tags":[
        "cleaner",
        "product",
        "repairer",
        "domestic",
        "sales",
        "sale",
        "electrical",
        "vacuum"
    ],
    "wof:name":"Tower Vacum",
    "wof:placetype":"venue"
},
  "geometry": {"coordinates":[-1.842855,52.522648],"type":"Point"}
}