{
  "type": "Feature",
  "properties": {
    "addr:full":"1 Abington Square Northampton Northamptonshire NN1 4AE",
    "addr:housenumber":"1",
    "addr:postcode":"nn1 4ae",
    "addr:street":"Abington Square",
    "iso:country":"GB",
    "sg:address":"1 Abington Square",
    "sg:city":"Northampton",
    "sg:classifiers":[
        {
            "category":"Shopping",
            "subcategory":"Photographic Equipment",
            "type":"Retail Goods"
        }
    ],
    "sg:phone":"+44 1604 230490",
    "sg:postcode":"NN1 4AE",
    "sg:province":"Northamptonshire",
    "sg:tags":[
        "supply"
    ],
    "wof:name":"Jessop Photo Video Centre",
    "wof:placetype":"venue"
},
  "geometry": {"coordinates":[-0.88831,52.240044],"type":"Point"}
}