{
  "type": "Feature",
  "properties": {
    "addr:full":"139 Homerton High St Hackney Greater London E9 6AS",
    "addr:housenumber":"139",
    "addr:postcode":"e9 6as",
    "addr:street":"Homerton High St",
    "iso:country":"GB",
    "sg:address":"139 Homerton High St",
    "sg:city":"Hackney",
    "sg:classifiers":[
        {
            "category":"Health Services",
            "subcategory":"Doctor",
            "type":"Services"
        }
    ],
    "sg:phone":"+44 20 8985 3444",
    "sg:postcode":"E9 6AS",
    "sg:province":"Greater London",
    "sg:tags":[
        "practitioners"
    ],
    "wof:name":"Rao, D R",
    "wof:placetype":"venue"
},
  "geometry": {"coordinates":[-0.0413220003,51.5488395691],"type":"Point"}
}