{
  "type": "Feature",
  "properties": {
    "addr:full":"70 Forest Road, Kingswood Bristol City of Bristol BS15 8EQ",
    "addr:housenumber":"70",
    "addr:postcode":"bs15 8eq",
    "addr:street":"Forest Road",
    "iso:country":"GB",
    "sg:address":"70 Forest Road, Kingswood",
    "sg:city":"Bristol",
    "sg:classifiers":[
        {
            "category":"Communications",
            "type":"Services"
        }
    ],
    "sg:phone":"+44 117 967 5444",
    "sg:postcode":"BS15 8EQ",
    "sg:province":"City of Bristol",
    "sg:tags":[
        "tv",
        "video",
        "radio"
    ],
    "wof:name":"T C Mills of Bristol",
    "wof:placetype":"venue"
},
  "geometry": {"coordinates":[-2.512058,51.456978],"type":"Point"}
}