{
  "type": "Feature",
  "properties": {
    "addr:full":"Stocks La Warrington Cheshire WA5 3JS",
    "addr:postcode":"wa5 3js",
    "addr:street":"Stocks La Warrington Cheshire",
    "iso:country":"GB",
    "sg:address":"Stocks La",
    "sg:city":"Warrington",
    "sg:classifiers":[
        {
            "category":"Health Services",
            "subcategory":"Nursing And Care Facility",
            "type":"Services"
        }
    ],
    "sg:phone":"+44 1925 791167",
    "sg:postcode":"WA5 3JS",
    "sg:province":"Cheshire",
    "sg:tags":[
        "home"
    ],
    "wof:name":"Holly Court",
    "wof:placetype":"venue"
},
  "geometry": {"coordinates":[-2.66434,53.391426],"type":"Point"}
}