{
  "type": "Feature",
  "properties": {
    "iso:country":"GB",
    "sg:address":"85a Upper St Giles Street",
    "sg:city":"Norwich",
    "sg:classifiers":[
        {
            "category":"Government",
            "subcategory":"Post Office",
            "type":"Public Place"
        }
    ],
    "sg:phone":"+44 1603 622871",
    "sg:postcode":"NR2 1AB",
    "sg:province":"Norfolk",
    "wof:name":"St Giles Post Office",
    "wof:placetype":"venue"
},
  "geometry": {"coordinates":[1.286112,52.629475],"type":"Point"}
}