{
  "type": "Feature",
  "properties": {
    "iso:country":"GB",
    "sg:address":"31 Beaufort Street",
    "sg:city":"Ebbw Vale",
    "sg:classifiers":[
        {
            "category":"Shopping",
            "subcategory":"Clothing, Apparel, & Fashions",
            "type":"Retail Goods"
        }
    ],
    "sg:phone":"+44 1495 313486",
    "sg:postcode":"NP23 4AB",
    "sg:province":"Blaenau Gwent",
    "sg:tags":[
        "shop"
    ],
    "wof:name":"New Look",
    "wof:placetype":"venue"
},
  "geometry": {"coordinates":[-3.175202,51.798164],"type":"Point"}
}