{
  "type": "Feature",
  "properties": {
    "iso:country":"GB",
    "sg:address":"Unit E, 1 Bank Road, Crown Square",
    "sg:city":"Matlock",
    "sg:classifiers":[
        {
            "category":"Travel",
            "subcategory":"Travel Agent",
            "type":"Entertainment"
        }
    ],
    "sg:phone":"+44 1629 56226",
    "sg:postcode":"DE4 3AQ",
    "sg:province":"Derbyshire",
    "wof:name":"Lunn Poly Ltd.",
    "wof:placetype":"venue"
},
  "geometry": {"coordinates":[-1.5482740402,53.1356163025],"type":"Point"}
}