{
  "type": "Feature",
  "properties": {
    "addr:full":"Howeth Rd Bournemouth Dorset BH10 5EA",
    "addr:postcode":"bh10 5ea",
    "addr:street":"Howeth Rd",
    "iso:country":"GB",
    "sg:address":"Howeth Rd",
    "sg:city":"Bournemouth",
    "sg:classifiers":[
        {
            "category":"Place Of Worship",
            "type":"Public Place"
        }
    ],
    "sg:phone":"+44 1202 516341",
    "sg:postcode":"BH10 5EA",
    "sg:province":"Dorset",
    "wof:name":"Howeth Road Evangelical Church",
    "wof:placetype":"venue"
},
  "geometry": {"coordinates":[-1.89495,50.762241],"type":"Point"}
}