{
  "type": "Feature",
  "properties": {
    "addr:full":"8 Winton Square Basingstoke Hampshire RG21 1EW",
    "addr:housenumber":"8",
    "addr:postcode":"rg21 1ew",
    "addr:street":"Winton Square",
    "iso:country":"GB",
    "sg:address":"8 Winton Square",
    "sg:city":"Basingstoke",
    "sg:classifiers":[
        {
            "category":"Military Area",
            "subcategory":"Air Force Base",
            "type":"Public Place"
        }
    ],
    "sg:phone":"+44 1256 350000",
    "sg:postcode":"RG21 1EW",
    "sg:province":"Hampshire",
    "sg:tags":[
        "taxi",
        "hire",
        "private"
    ],
    "wof:name":"Cab Express",
    "wof:placetype":"venue"
},
  "geometry": {"coordinates":[-1.0898489952,51.2622642517],"type":"Point"}
}