{
  "type": "Feature",
  "properties": {
    "addr:full":"42 Dalry Road Edinburgh City of Edinburgh EH11 2BA",
    "addr:housenumber":"42",
    "addr:postcode":"eh11 2ba",
    "addr:street":"Dalry Road",
    "iso:country":"GB",
    "sg:address":"42 Dalry Road",
    "sg:city":"Edinburgh",
    "sg:classifiers":[
        {
            "category":"Travel",
            "subcategory":"Travel Agent",
            "type":"Entertainment"
        }
    ],
    "sg:phone":"+44 131 337 8495",
    "sg:postcode":"EH11 2BA",
    "sg:province":"City of Edinburgh",
    "wof:name":"Paterson Travel & Tours Ltd",
    "wof:placetype":"venue"
},
  "geometry": {"coordinates":[-3.2179450989,55.9450035095],"type":"Point"}
}