{
  "type": "Feature",
  "properties": {
    "addr:full":"26 Brelades Clo Dudley West Midlands DY1 2UZ",
    "addr:housenumber":"26",
    "addr:postcode":"dy1 2uz",
    "addr:street":"Brelades Clo",
    "iso:country":"GB",
    "sg:address":"26 Brelades Clo",
    "sg:city":"Dudley",
    "sg:classifiers":[
        {
            "category":"Professional",
            "subcategory":"Accounting & Tax Preparation",
            "type":"Services"
        }
    ],
    "sg:phone":"+44 1384 821060",
    "sg:postcode":"DY1 2UZ",
    "sg:province":"West Midlands",
    "sg:tags":[
        "accountant"
    ],
    "wof:name":"Houldershaw & Co",
    "wof:placetype":"venue"
},
  "geometry": {"coordinates":[-2.1134340763,52.5168075562],"type":"Point"}
}