{
  "type": "Feature",
  "properties": {
    "iso:country":"GB",
    "sg:address":"23 Suffolk Drive",
    "sg:city":"Worcester",
    "sg:classifiers":[
        {
            "category":"Education",
            "subcategory":"Dance Studio",
            "type":"Public Place"
        }
    ],
    "sg:phone":"+44 1905 458407",
    "sg:postcode":"WR3 8QT",
    "sg:province":"Worcestershire",
    "sg:tags":[
        "school",
        "dancing"
    ],
    "wof:name":"Steve & Debbie",
    "wof:placetype":"venue"
},
  "geometry": {"coordinates":[-2.200884,52.21521],"type":"Point"}
}