{
  "type": "Feature",
  "properties": {
    "addr:full":"Kingswood Ho, 12 Shute End Wokingham Berkshire RG40 1BJ",
    "addr:housenumber":"12",
    "addr:postcode":"rg40 1bj",
    "addr:street":"Shute End",
    "iso:country":"GB",
    "sg:address":"Kingswood Ho, 12 Shute End",
    "sg:city":"Wokingham",
    "sg:classifiers":[
        {
            "category":"Education",
            "subcategory":"Special Training",
            "type":"Public Place"
        }
    ],
    "sg:phone":"+44 118 989 4609",
    "sg:postcode":"RG40 1BJ",
    "sg:province":"Berkshire",
    "sg:tags":[
        "product",
        "centre"
    ],
    "wof:name":"W I I FM Training",
    "wof:placetype":"venue"
},
  "geometry": {"coordinates":[-0.834594,51.410801],"type":"Point"}
}