{
  "type": "Feature",
  "properties": {
    "iso:country":"GB",
    "sg:address":"Unit 2ca, South Hams Business Park",
    "sg:city":"Kingsbridge",
    "sg:classifiers":[
        {
            "category":"Professional",
            "subcategory":"Computer Services",
            "type":"Services"
        }
    ],
    "sg:postcode":"TQ7 3QR",
    "sg:province":"Devon",
    "sg:tags":[
        "consultant"
    ],
    "wof:name":"Locus Systems",
    "wof:placetype":"venue"
},
  "geometry": {"coordinates":[-3.805539,50.296852],"type":"Point"}
}