{
  "type": "Feature",
  "properties": {
    "addr:full":"156 Commercial Street Kirkcaldy Fife KY1 2NU",
    "addr:housenumber":"156",
    "addr:postcode":"ky1 2nu",
    "addr:street":"Commercial Street",
    "iso:country":"GB",
    "sg:address":"156 Commercial Street",
    "sg:city":"Kirkcaldy",
    "sg:classifiers":[
        {
            "category":"Organizations",
            "subcategory":"Non-profit Organization",
            "type":"Services"
        }
    ],
    "sg:phone":"+44 1592 646059",
    "sg:postcode":"KY1 2NU",
    "sg:province":"Fife",
    "sg:tags":[
        "organisation",
        "voluntary",
        "charity"
    ],
    "wof:name":"Mental Health Survivors Group",
    "wof:placetype":"venue"
},
  "geometry": {"coordinates":[-3.1428630352,56.1221656799],"type":"Point"}
}