{
  "type": "Feature",
  "properties": {
    "addr:full":"Postgate House, Castleton Whitby North Yorkshire YO21 2ET",
    "addr:postcode":"yo21 2et",
    "addr:street":"Postgate",
    "iso:country":"GB",
    "sg:address":"Postgate House, Castleton",
    "sg:city":"Whitby",
    "sg:classifiers":[
        {
            "category":"Professional",
            "subcategory":"Computer Services",
            "type":"Services"
        }
    ],
    "sg:postcode":"YO21 2ET",
    "sg:province":"North Yorkshire",
    "sg:tags":[
        "system",
        "software"
    ],
    "wof:name":"Francis & Thomson Ltd.",
    "wof:placetype":"venue"
},
  "geometry": {"coordinates":[-0.8939139843,54.4577445984],"type":"Point"}
}