{
  "type": "Feature",
  "properties": {
    "addr:full":"3 The Denes Hemel Hempstead Hertfordshire HP3 8AP",
    "addr:housenumber":"3",
    "addr:postcode":"hp3 8ap",
    "addr:street":"The;Hemel Hempstead",
    "iso:country":"GB",
    "sg:address":"3 The Denes",
    "sg:city":"Hemel Hempstead",
    "sg:classifiers":[
        {
            "category":"Cafe",
            "type":"Food & Drink"
        }
    ],
    "sg:phone":"+44 1442 260313",
    "sg:postcode":"HP3 8AP",
    "sg:province":"Hertfordshire",
    "sg:tags":[
        "tea",
        "snack",
        "bar",
        "room"
    ],
    "wof:name":"Santos Cafe",
    "wof:placetype":"venue"
},
  "geometry": {"coordinates":[-0.454179,51.73312],"type":"Point"}
}