{
  "type": "Feature",
  "properties": {
    "iso:country":"GB",
    "sg:address":"War Memorial Ground, Bulpit Lane, Hungerford",
    "sg:city":"Newbury",
    "sg:classifiers":[
        {
            "category":"Arena",
            "subcategory":"Sports Club",
            "type":"Entertainment"
        }
    ],
    "sg:phone":"+44 1488 682663",
    "sg:postcode":"RG14 6RQ",
    "sg:province":"Berkshire",
    "wof:name":"Hungerford Cricket Club",
    "wof:placetype":"venue"
},
  "geometry": {"coordinates":[-1.3258719444,51.405872345],"type":"Point"}
}