{
  "type": "Feature",
  "properties": {
    "iso:country":"GB",
    "sg:address":"217 Clethorpe Road",
    "sg:city":"Grimsby",
    "sg:classifiers":[
        {
            "category":"Shopping",
            "subcategory":"Stationery & Office Supplies",
            "type":"Retail Goods"
        }
    ],
    "sg:phone":"+44 1472 251566",
    "sg:postcode":"DN31 3BE",
    "sg:province":"Lincolnshire",
    "sg:tags":[
        "item",
        "promotional"
    ],
    "wof:name":"Malmark",
    "wof:placetype":"venue"
},
  "geometry": {"coordinates":[-0.0669990033,53.5744285583],"type":"Point"}
}