{
  "type": "Feature",
  "properties": {
    "addr:full":"115 New Union Street Coventry West Midlands CV1 2NT",
    "addr:housenumber":"115",
    "addr:postcode":"cv1 2nt",
    "addr:street":"New Union Street",
    "iso:country":"GB",
    "sg:address":"115 New Union Street",
    "sg:city":"Coventry",
    "sg:classifiers":[
        {
            "category":"Banks & Credit Unions",
            "subcategory":"Bank",
            "type":"Services"
        },
        {
            "category":"Banks & Credit Unions",
            "subcategory":"Financial Services",
            "type":"Services"
        },
        {
            "category":"Real Estate",
            "subcategory":"Real Estate Agent",
            "type":"Services"
        }
    ],
    "sg:phone":"+44 24 7655 1758",
    "sg:postcode":"CV1 2NT",
    "sg:province":"West Midlands",
    "sg:tags":[
        "consultant",
        "institution"
    ],
    "wof:name":"STUART PETTIFER FINANCIAL PLANNING",
    "wof:placetype":"venue"
},
  "geometry": {"coordinates":[-1.510344,52.404938],"type":"Point"}
}