{
  "type": "Feature",
  "properties": {
    "addr:full":"12a Harwood Road, East Hagbourne Didcot Oxfordshire OX11 9LX",
    "addr:housenumber":"12a",
    "addr:postcode":"ox11 9lx",
    "addr:street":"Harwood Road East",
    "iso:country":"GB",
    "sg:address":"12a Harwood Road, East Hagbourne",
    "sg:city":"Didcot",
    "sg:classifiers":[
        {
            "category":"Retail",
            "subcategory":"Driving School",
            "type":"Services"
        }
    ],
    "sg:phone":"+44 1235 812517",
    "sg:postcode":"OX11 9LX",
    "sg:province":"Oxfordshire",
    "wof:name":"Drivewell School Of Motoring",
    "wof:placetype":"venue"
},
  "geometry": {"coordinates":[-1.2432130575,51.5934562683],"type":"Point"}
}