{
  "type": "Feature",
  "properties": {
    "iso:country":"GB",
    "sg:address":"59 High Street",
    "sg:city":"Westerham",
    "sg:classifiers":[
        {
            "category":"Freight",
            "type":"Transportation"
        }
    ],
    "sg:postcode":"TN16 1RE",
    "sg:province":"Kent",
    "sg:tags":[
        "haulage",
        "road"
    ],
    "wof:name":"G Burgess & Son",
    "wof:placetype":"venue"
},
  "geometry": {"coordinates":[0.068208,51.265778],"type":"Point"}
}