{
  "type": "Feature",
  "properties": {
    "addr:full":"C/o Victor Kirby & Co., 82 Snakes Lane East Woodford Green Essex IG8 7QQ",
    "addr:housenumber":"/ o;82",
    "addr:postcode":"ig8 7qq",
    "addr:street":"C;Victor;Snakes Lane East",
    "iso:country":"GB",
    "sg:address":"C/o Victor Kirby & Co., 82 Snakes Lane East",
    "sg:city":"Woodford Green",
    "sg:classifiers":[
        {
            "category":"Professional",
            "subcategory":"Computer Services",
            "type":"Services"
        }
    ],
    "sg:postcode":"IG8 7QQ",
    "sg:province":"Essex",
    "sg:tags":[
        "system",
        "software"
    ],
    "wof:name":"K H Victory Ltd",
    "wof:placetype":"venue"
},
  "geometry": {"coordinates":[0.0357099995,51.6078605652],"type":"Point"}
}