{
  "type": "Feature",
  "properties": {
    "addr:full":"Brigend, Oxton Lauder Scottish Borders TD2 6PP",
    "addr:postcode":"td2 6pp",
    "iso:country":"GB",
    "sg:address":"Brigend, Oxton",
    "sg:city":"Lauder",
    "sg:classifiers":[
        {
            "category":"Banks & Credit Unions",
            "subcategory":"Investment Brokerage",
            "type":"Services"
        }
    ],
    "sg:postcode":"TD2 6PP",
    "sg:province":"Scottish Borders",
    "sg:tags":[
        "contractor"
    ],
    "wof:name":"Agri-Chop",
    "wof:placetype":"venue"
},
  "geometry": {"coordinates":[-2.7500789165,55.7201194763],"type":"Point"}
}