{
  "type": "Feature",
  "properties": {
    "iso:country":"GB",
    "sg:address":"45a Chingford Mount Road",
    "sg:city":"London",
    "sg:classifiers":[
        {
            "category":"Military Area",
            "subcategory":"Naval Base",
            "type":"Public Place"
        },
        {
            "category":"Retail",
            "subcategory":"Auto Repair",
            "type":"Services"
        }
    ],
    "sg:phone":"+44 20 8527 3556",
    "sg:postcode":"E4 8LU",
    "sg:province":"Greater London",
    "sg:tags":[
        "truck",
        "electrical",
        "van",
        "car",
        "centre"
    ],
    "wof:name":"B & H Auto Electrical Services",
    "wof:placetype":"venue"
},
  "geometry": {"coordinates":[-0.0180549994,51.6101760864],"type":"Point"}
}