{
  "type": "Feature",
  "properties": {
    "addr:full":"Unit 16 Shrivenham Hundred Busin, Ess Park Majors R, Watchfield Swindon Gloucestershire SN6 8TZ",
    "addr:housenumber":"unit 16",
    "addr:postcode":"sn6 8tz",
    "iso:country":"GB",
    "sg:address":"Unit 16 Shrivenham Hundred Busin, Ess Park Majors R, Watchfield",
    "sg:city":"Swindon",
    "sg:classifiers":[
        {
            "category":"Home & Garden",
            "subcategory":"Kitchen Supply",
            "type":"Retail Goods"
        }
    ],
    "sg:phone":"+44 1793 784788",
    "sg:postcode":"SN6 8TZ",
    "sg:province":"Gloucestershire",
    "sg:tags":[
        "equipment",
        "catering"
    ],
    "wof:name":"Spectrum Contracts Ltd.",
    "wof:placetype":"venue"
},
  "geometry": {"coordinates":[-1.6466089487,51.6137313843],"type":"Point"}
}