{
  "type": "Feature",
  "properties": {
    "addr:full":"14 Limewood Clo Cardiff Caerphilly CF3 0BU",
    "addr:housenumber":"14",
    "addr:postcode":"cf3 0bu",
    "addr:street":"Limewood Clo",
    "iso:country":"GB",
    "sg:address":"14 Limewood Clo",
    "sg:city":"Cardiff",
    "sg:classifiers":[
        {
            "category":"Home & Garden",
            "subcategory":"Carpets & Floor Coverings",
            "type":"Retail Goods"
        }
    ],
    "sg:phone":"+44 29 2079 7249",
    "sg:postcode":"CF3 0BU",
    "sg:province":"Caerphilly",
    "sg:tags":[
        "carpets",
        "rug",
        "matting"
    ],
    "wof:name":"Amber Carpets",
    "wof:placetype":"venue"
},
  "geometry": {"coordinates":[-3.106326,51.527271],"type":"Point"}
}