{
  "type": "Feature",
  "properties": {
    "iso:country":"GB",
    "sg:address":"Within Kwiksave, Brighton Road, Waterloo",
    "sg:city":"Liverpool",
    "sg:classifiers":[
        {
            "category":"Food & Beverages",
            "subcategory":"Meat & Fish",
            "type":"Retail Goods"
        }
    ],
    "sg:phone":"+44 151 920 1476",
    "sg:postcode":"L22 5NG",
    "sg:province":"Merseyside",
    "sg:tags":[
        "butcher"
    ],
    "wof:name":"Greggs Quality Meats",
    "wof:placetype":"venue"
},
  "geometry": {"coordinates":[-3.02833,53.475842],"type":"Point"}
}