{
  "type": "Feature",
  "properties": {
    "addr:full":"70 Green Lane Northwood Greater London HA6 2XS",
    "addr:housenumber":"70",
    "addr:postcode":"ha6 2xs",
    "addr:street":"Green Lane",
    "iso:country":"GB",
    "sg:address":"70 Green Lane",
    "sg:city":"Northwood",
    "sg:classifiers":[
        {
            "category":"Shopping",
            "subcategory":"News",
            "type":"Retail Goods"
        }
    ],
    "sg:phone":"+44 1923 826349",
    "sg:postcode":"HA6 2XS",
    "sg:province":"Greater London",
    "sg:tags":[
        "newsagent"
    ],
    "wof:name":"Andrews Newsagents",
    "wof:placetype":"venue"
},
  "geometry": {"coordinates":[-0.425659,51.611858],"type":"Point"}
}