{
  "type": "Feature",
  "properties": {
    "iso:country":"GB",
    "sg:address":"4 Bethel Terrace, Luddenden",
    "sg:city":"Halifax",
    "sg:classifiers":[
        {
            "category":"Building & Trades",
            "subcategory":"Construction",
            "type":"Services"
        }
    ],
    "sg:phone":"+44 1422 884159",
    "sg:postcode":"HX2 6RE",
    "sg:province":"West Yorkshire",
    "sg:tags":[
        "decorator",
        "painter"
    ],
    "wof:name":"Anderson Marriott & Co Ltd",
    "wof:placetype":"venue"
},
  "geometry": {"coordinates":[-1.962166,53.728706],"type":"Point"}
}