{
  "type": "Feature",
  "properties": {
    "addr:full":"1a Anson Clo, Pysons Rd Indstl Est Broadstairs Kent CT10 2YB",
    "addr:housenumber":"1a",
    "addr:postcode":"ct10 2yb",
    "addr:street":"Pysons Rd;Est",
    "iso:country":"GB",
    "sg:address":"1a Anson Clo, Pysons Rd Indstl Est",
    "sg:city":"Broadstairs",
    "sg:classifiers":[
        {
            "category":"Shopping",
            "subcategory":"Computers & Home Electronics",
            "type":"Retail Goods"
        }
    ],
    "sg:postcode":"CT10 2YB",
    "sg:province":"Kent",
    "wof:name":"Jodach",
    "wof:placetype":"venue"
},
  "geometry": {"coordinates":[1.4096000195,51.3564949036],"type":"Point"}
}