{
  "type": "Feature",
  "properties": {
    "iso:country":"GB",
    "sg:address":"51 High St, Watton",
    "sg:city":"Thetford",
    "sg:classifiers":[
        {
            "category":"Shopping",
            "subcategory":"Thrift Store",
            "type":"Retail Goods"
        }
    ],
    "sg:phone":"+44 1953 882512",
    "sg:postcode":"IP25 6AB",
    "sg:province":"Norfolk",
    "sg:tags":[
        "shop",
        "charity"
    ],
    "wof:name":"Break",
    "wof:placetype":"venue"
},
  "geometry": {"coordinates":[0.8229290247,52.5712165833],"type":"Point"}
}