{
  "type": "Feature",
  "properties": {
    "iso:country":"GB",
    "sg:address":"709 Old Kent Rd",
    "sg:city":"Peckham",
    "sg:classifiers":[
        {
            "category":"Organizations",
            "subcategory":"Religious Organization",
            "type":"Services"
        }
    ],
    "sg:phone":"+44 20 7277 6220",
    "sg:postcode":"SE15 1JL",
    "sg:province":"Greater London",
    "sg:tags":[
        "organisation"
    ],
    "wof:name":"Holy Fire Revival Ministry",
    "wof:placetype":"venue"
},
  "geometry": {"coordinates":[-0.0611420013,51.481628418],"type":"Point"}
}