{
  "type": "Feature",
  "properties": {
    "addr:full":"8th Floor, Trafrod House Manchester Cheshire M32 0RS",
    "addr:housenumber":"8th floor trafrod house",
    "addr:postcode":"m32 0rs",
    "iso:country":"GB",
    "sg:address":"8th Floor, Trafrod House",
    "sg:city":"Manchester",
    "sg:classifiers":[
        {
            "category":"Professional",
            "subcategory":"Business Services",
            "type":"Services"
        }
    ],
    "sg:phone":"+44 161 886 8400",
    "sg:postcode":"M32 0RS",
    "sg:province":"Cheshire",
    "sg:tags":[
        "trade"
    ],
    "wof:name":"B P I F",
    "wof:placetype":"venue"
},
  "geometry": {"coordinates":[-2.248809,53.479622],"type":"Point"}
}