{
  "type": "Feature",
  "properties": {
    "addr:full":"20 Barnes High St, Barnes London Greater London SW13 9LW",
    "addr:housenumber":"20",
    "addr:postcode":"sw13 9lw",
    "addr:street":"Barnes High St",
    "iso:country":"GB",
    "sg:address":"20 Barnes High St, Barnes",
    "sg:city":"London",
    "sg:classifiers":[
        {
            "category":"Deli",
            "type":"Food & Drink"
        }
    ],
    "sg:phone":"+44 20 8878 1520",
    "sg:postcode":"SW13 9LW",
    "sg:province":"Greater London",
    "sg:tags":[
        "delicatessen"
    ],
    "wof:name":"Arkwrights Ltd",
    "wof:placetype":"venue"
},
  "geometry": {"coordinates":[-0.249109,51.473583],"type":"Point"}
}