{
  "type": "Feature",
  "properties": {
    "iso:country":"GB",
    "sg:address":"11 Mount Pleasant, Hildenborough",
    "sg:city":"Tonbridge",
    "sg:classifiers":[
        {
            "category":"Personal",
            "type":"Services"
        }
    ],
    "sg:phone":"+44 1732 832915",
    "sg:postcode":"TN11 9JQ",
    "sg:province":"Kent",
    "sg:tags":[
        "wedding"
    ],
    "wof:name":"Print Press",
    "wof:placetype":"venue"
},
  "geometry": {"coordinates":[0.2631419897,51.1302223206],"type":"Point"}
}