{
  "type": "Feature",
  "properties": {
    "addr:full":"86a Thornton Lane Bradford West Yorkshire BD5 9DS",
    "addr:housenumber":"86a",
    "addr:postcode":"bd5 9ds",
    "addr:street":"Thornton Lane",
    "iso:country":"GB",
    "sg:address":"86a Thornton Lane",
    "sg:city":"Bradford",
    "sg:classifiers":[
        {
            "category":"Personal",
            "subcategory":"Beauty Salon",
            "type":"Services"
        }
    ],
    "sg:phone":"+44 1274 572539",
    "sg:postcode":"BD5 9DS",
    "sg:province":"West Yorkshire",
    "sg:tags":[
        "lady",
        "hairdresser"
    ],
    "wof:name":"Betty's",
    "wof:placetype":"venue"
},
  "geometry": {"coordinates":[-1.7670400143,53.774810791],"type":"Point"}
}