{
  "type": "Feature",
  "properties": {
    "iso:country":"GB",
    "sg:address":"Unit 1 & 6, 217-227 Two Mile Hill Road, Kingswood",
    "sg:city":"Bristol",
    "sg:classifiers":[
        {
            "category":"Wholesale",
            "subcategory":"Scrap",
            "type":"Manufacturing & Wholesale Goods"
        }
    ],
    "sg:phone":"+44 117 947 6624",
    "sg:postcode":"BS15 1AZ",
    "sg:province":"City of Bristol",
    "sg:tags":[
        "breaker",
        "dismantlers"
    ],
    "wof:name":"Kingswood Cavaliers",
    "wof:placetype":"venue"
},
  "geometry": {"coordinates":[-2.51903,51.462929],"type":"Point"}
}