{
  "type": "Feature",
  "properties": {
    "addr:full":"Star House, Horsemarket Barnard Castle Cumbria DL12 8LY",
    "addr:postcode":"dl12 8ly",
    "addr:street":"Horsemarket",
    "iso:country":"GB",
    "sg:address":"Star House, Horsemarket",
    "sg:city":"Barnard Castle",
    "sg:classifiers":[
        {
            "category":"Shopping",
            "subcategory":"Thrift Store",
            "type":"Retail Goods"
        }
    ],
    "sg:phone":"+44 1833 690411",
    "sg:postcode":"DL12 8LY",
    "sg:province":"Cumbria",
    "sg:tags":[
        "shop",
        "charity"
    ],
    "wof:name":"Butterwick Childrens Hospice Shop",
    "wof:placetype":"venue"
},
  "geometry": {"coordinates":[-1.9233590364,54.5434265137],"type":"Point"}
}