{
  "type": "Feature",
  "properties": {
    "addr:full":"4 Attlee Rd Blackwood Caerphilly NP2 1QE",
    "addr:housenumber":"4",
    "addr:postcode":"np2 1qe",
    "addr:street":"Attlee Rd",
    "iso:country":"GB",
    "sg:address":"4 Attlee Rd",
    "sg:city":"Blackwood",
    "sg:classifiers":[
        {
            "category":"Building & Trades",
            "subcategory":"Plumbing",
            "type":"Services"
        }
    ],
    "sg:phone":"+44 1495 228094",
    "sg:postcode":"NP2 1QE",
    "sg:province":"Caerphilly",
    "sg:tags":[
        "central",
        "heating"
    ],
    "wof:name":"Paul Paton",
    "wof:placetype":"venue"
},
  "geometry": {"coordinates":[-3.2007749081,51.6664772034],"type":"Point"}
}