{
  "type": "Feature",
  "properties": {
    "iso:country":"GB",
    "sg:address":"16 Gainsborough Road",
    "sg:city":"Crewe",
    "sg:classifiers":[
        {
            "category":"Recreation",
            "subcategory":"Fishing",
            "type":"Entertainment"
        }
    ],
    "sg:phone":"+44 1270 650744",
    "sg:postcode":"CW2 7PH",
    "sg:province":"Cheshire",
    "sg:tags":[
        "equipment",
        "angling"
    ],
    "sg:website":"http://www.neptuneproducts.co.uk",
    "wof:name":"Neptune Products",
    "wof:placetype":"venue"
},
  "geometry": {"coordinates":[-2.4478640556,53.092628479],"type":"Point"}
}