{
  "type": "Feature",
  "properties": {
    "addr:full":"Mill Farm Jacks Lane, Marchington Uttoxeter Derbyshire ST14 8LN",
    "addr:postcode":"st14 8ln",
    "addr:street":"Jacks Lane",
    "iso:country":"GB",
    "sg:address":"Mill Farm Jacks Lane, Marchington",
    "sg:city":"Uttoxeter",
    "sg:classifiers":[
        {
            "category":"Retail",
            "subcategory":"Veterinary Services",
            "type":"Services"
        }
    ],
    "sg:phone":"+44 1283 820443",
    "sg:postcode":"ST14 8LN",
    "sg:province":"Derbyshire",
    "sg:tags":[
        "surgeon"
    ],
    "wof:name":"Braybridge Ltd.",
    "wof:placetype":"venue"
},
  "geometry": {"coordinates":[-1.807716012,52.8694610596],"type":"Point"}
}