{
  "type": "Feature",
  "properties": {
    "addr:full":"Lower Clough Mill, Pendle Street, Barrowford Nelson Lancashire BB9 8PH",
    "addr:postcode":"bb9 8ph",
    "addr:street":"Lower Clough;Pendle Street",
    "iso:country":"GB",
    "sg:address":"Lower Clough Mill, Pendle Street, Barrowford",
    "sg:city":"Nelson",
    "sg:classifiers":[
        {
            "category":"Home & Garden",
            "subcategory":"Furniture",
            "type":"Retail Goods"
        }
    ],
    "sg:phone":"+44 1282 694777",
    "sg:postcode":"BB9 8PH",
    "sg:province":"Lancashire",
    "sg:tags":[
        "bed",
        "mattress"
    ],
    "wof:name":"Silentnight Export",
    "wof:placetype":"venue"
},
  "geometry": {"coordinates":[-2.222503,53.846054],"type":"Point"}
}