{
  "type": "Feature",
  "properties": {
    "addr:full":"3 Intake Ave York North Yorkshire YO30 6HB",
    "addr:housenumber":"3",
    "addr:postcode":"yo30 6hb",
    "addr:street":"Intake Ave",
    "iso:country":"GB",
    "sg:address":"3 Intake Ave",
    "sg:city":"York",
    "sg:classifiers":[
        {
            "category":"Shopping",
            "subcategory":"Pharmacy",
            "type":"Retail Goods"
        }
    ],
    "sg:postcode":"YO30 6HB",
    "sg:province":"North Yorkshire",
    "sg:tags":[
        "pharmacist",
        "store",
        "drug",
        "chemist"
    ],
    "wof:name":"Oyston,J R H,",
    "wof:placetype":"venue"
},
  "geometry": {"coordinates":[-1.0844540596,53.9742927551],"type":"Point"}
}