{
  "type": "Feature",
  "properties": {
    "addr:full":"Hastings Lane Sheringham Norfolk NR26 8DP",
    "addr:postcode":"nr26 8dp",
    "addr:street":"Hastings Lane",
    "iso:country":"GB",
    "sg:address":"Hastings Lane",
    "sg:city":"Sheringham",
    "sg:classifiers":[
        {
            "category":"Home & Garden",
            "subcategory":"Building Materials",
            "type":"Retail Goods"
        }
    ],
    "sg:phone":"+44 1263 822925",
    "sg:postcode":"NR26 8DP",
    "sg:province":"Norfolk",
    "sg:tags":[
        "ironwork",
        "product",
        "production",
        "design",
        "diy",
        "iron",
        "wrought"
    ],
    "wof:name":"METAL DESIGNS (SHERINGHAM)",
    "wof:placetype":"venue"
},
  "geometry": {"coordinates":[1.2128800154,52.9430084229],"type":"Point"}
}