{
  "type": "Feature",
  "properties": {
    "iso:country":"GB",
    "sg:address":"2 Meyrick Street",
    "sg:city":"Hereford",
    "sg:classifiers":[
        {
            "category":"Utilities",
            "subcategory":"Refuse",
            "type":"Services"
        }
    ],
    "sg:postcode":"HR4 0DY",
    "sg:province":"Herefordshire",
    "sg:tags":[
        "disposal",
        "waste",
        "retail"
    ],
    "wof:name":"G T Skip Hire",
    "wof:placetype":"venue"
},
  "geometry": {"coordinates":[-2.735016,52.0602],"type":"Point"}
}