{
  "type": "Feature",
  "properties": {
    "addr:full":"Swan Ho, Swan Meadow Rd Wigan Lancashire WN3 5BE",
    "addr:postcode":"wn3 5be",
    "addr:street":"Swan Meadow Rd",
    "iso:country":"GB",
    "sg:address":"Swan Ho, Swan Meadow Rd",
    "sg:city":"Wigan",
    "sg:classifiers":[
        {
            "category":"Shopping",
            "subcategory":"Mobile Phones",
            "type":"Retail Goods"
        }
    ],
    "sg:postcode":"WN3 5BE",
    "sg:province":"Lancashire",
    "wof:name":"Kwikfone",
    "wof:placetype":"venue"
},
  "geometry": {"coordinates":[-2.637792,53.539993],"type":"Point"}
}