{
  "type": "Feature",
  "properties": {
    "addr:full":"Lidgate Garage Newmarket Cambridgeshire CB8 9PW",
    "addr:postcode":"cb8 9pw",
    "addr:street":"Newmarket",
    "iso:country":"GB",
    "sg:address":"Lidgate Garage",
    "sg:city":"Newmarket",
    "sg:classifiers":[
        {
            "category":"Retail",
            "subcategory":"Auto Repair",
            "type":"Services"
        }
    ],
    "sg:postcode":"CB8 9PW",
    "sg:province":"Cambridgeshire",
    "sg:tags":[
        "modification",
        "garage"
    ],
    "wof:name":"Lidgate Garage",
    "wof:placetype":"venue"
},
  "geometry": {"coordinates":[0.518247,52.191364],"type":"Point"}
}