{
  "type": "Feature",
  "properties": {
    "addr:full":"The Garages Brighton East Sussex BN1 6EN",
    "addr:postcode":"bn1 6en",
    "iso:country":"GB",
    "sg:address":"The Garages",
    "sg:city":"Brighton",
    "sg:classifiers":[
        {
            "category":"Retail",
            "subcategory":"Auto Repair",
            "type":"Services"
        }
    ],
    "sg:postcode":"BN1 6EN",
    "sg:province":"East Sussex",
    "sg:tags":[
        "modification",
        "garage"
    ],
    "wof:name":"St Andrews Coachworks",
    "wof:placetype":"venue"
},
  "geometry": {"coordinates":[-0.1348199993,50.8408699036],"type":"Point"}
}