{
  "type": "Feature",
  "properties": {
    "iso:country":"GB",
    "sg:address":"127 Mostyn St",
    "sg:city":"Llandudno",
    "sg:classifiers":[
        {
            "category":"Sports & Exercise",
            "subcategory":"Gym",
            "type":"Entertainment"
        }
    ],
    "sg:postcode":"LL30 2PE",
    "sg:province":"Conwy",
    "sg:tags":[
        "fitness",
        "health",
        "centre"
    ],
    "wof:name":"Llandudno Sauna",
    "wof:placetype":"venue"
},
  "geometry": {"coordinates":[-3.832066,53.326054],"type":"Point"}
}