{
  "type": "Feature",
  "properties": {
    "iso:country":"GB",
    "sg:address":"Milton Hall, Milton Park, Milton",
    "sg:city":"Peterborough",
    "sg:classifiers":[
        {
            "category":"Professional",
            "type":"Services"
        }
    ],
    "sg:phone":"+44 1733 380781",
    "sg:postcode":"PE6 7AA",
    "sg:province":"Cambridgeshire",
    "sg:tags":[
        "auctioneer"
    ],
    "wof:name":"Christie's",
    "wof:placetype":"venue"
},
  "geometry": {"coordinates":[-0.320041,52.585285],"type":"Point"}
}