{
  "type": "Feature",
  "properties": {
    "addr:full":"21 Blockall Wednesbury West Midlands WS10 8EP",
    "addr:housenumber":"21",
    "addr:postcode":"ws10 8ep",
    "addr:street":"Blockall Wednesbury West",
    "iso:country":"GB",
    "sg:address":"21 Blockall",
    "sg:city":"Wednesbury",
    "sg:classifiers":[
        {
            "category":"Building & Trades",
            "subcategory":"Construction",
            "type":"Services"
        }
    ],
    "sg:postcode":"WS10 8EP",
    "sg:province":"West Midlands",
    "sg:tags":[
        "builder"
    ],
    "wof:name":"D Butler",
    "wof:placetype":"venue"
},
  "geometry": {"coordinates":[-2.036843,52.572205],"type":"Point"}
}