{
  "type": "Feature",
  "properties": {
    "addr:full":"The Old Mill, Mill Street Wantage Berkshire OX12 9AB",
    "addr:postcode":"ox12 9ab",
    "addr:street":"Mill Street",
    "iso:country":"GB",
    "sg:address":"The Old Mill, Mill Street",
    "sg:city":"Wantage",
    "sg:classifiers":[
        {
            "category":"Professional",
            "subcategory":"Research",
            "type":"Services"
        }
    ],
    "sg:phone":"+44 1235 772001",
    "sg:postcode":"OX12 9AB",
    "sg:province":"Berkshire",
    "sg:tags":[
        "market"
    ],
    "wof:name":"Hunt Marketing Research",
    "wof:placetype":"venue"
},
  "geometry": {"coordinates":[-1.423639,51.591747],"type":"Point"}
}