{
  "type": "Feature",
  "properties": {
    "addr:full":"Mill Stream, Benson Wallingford Oxfordshire OX10 6RL",
    "addr:postcode":"ox10 6rl",
    "addr:street":"Mill;Benson",
    "iso:country":"GB",
    "sg:address":"Mill Stream, Benson",
    "sg:city":"Wallingford",
    "sg:classifiers":[
        {
            "category":"Health Services",
            "subcategory":"Clinic",
            "type":"Services"
        }
    ],
    "sg:phone":"+44 1491 832000",
    "sg:postcode":"OX10 6RL",
    "sg:province":"Oxfordshire",
    "sg:tags":[
        "nh"
    ],
    "wof:name":"Mill Stream Surgery",
    "wof:placetype":"venue"
},
  "geometry": {"coordinates":[-1.107081,51.624657],"type":"Point"}
}