{
  "type": "Feature",
  "properties": {
    "addr:full":"Hatter Street Congleton Cheshire CW12 1QQ",
    "addr:postcode":"cw12 1qq",
    "addr:street":"Hatter Street",
    "iso:country":"GB",
    "sg:address":"Hatter Street",
    "sg:city":"Congleton",
    "sg:classifiers":[
        {
            "category":"Shopping",
            "subcategory":"Clothing, Apparel, & Fashions",
            "type":"Retail Goods"
        }
    ],
    "sg:phone":"+44 1260 278233",
    "sg:postcode":"CW12 1QQ",
    "sg:province":"Cheshire",
    "sg:tags":[
        "clothing",
        "accessory"
    ],
    "wof:name":"Top Shot Promotions",
    "wof:placetype":"venue"
},
  "geometry": {"coordinates":[-2.204079,53.164604],"type":"Point"}
}