{
  "type": "Feature",
  "properties": {
    "addr:full":"Langstone Technology Park, Langstone Road Havant Hampshire PO9 1SA",
    "addr:postcode":"po9 1sa",
    "addr:street":"Langstone Road",
    "iso:country":"GB",
    "sg:address":"Langstone Technology Park, Langstone Road",
    "sg:city":"Havant",
    "sg:classifiers":[
        {
            "category":"Education",
            "subcategory":"University",
            "type":"Public Place"
        }
    ],
    "sg:phone":"+44 23 9249 6000",
    "sg:postcode":"PO9 1SA",
    "sg:province":"Hampshire",
    "sg:tags":[
        "higher"
    ],
    "wof:name":"Havant International Ltd.",
    "wof:placetype":"venue"
},
  "geometry": {"coordinates":[-0.985544,50.854496],"type":"Point"}
}