{
  "type": "Feature",
  "properties": {
    "iso:country":"GB",
    "sg:address":"Queensway Industrial Estate",
    "sg:city":"Glenrothes",
    "sg:classifiers":[
        {
            "category":"Manufacturing",
            "subcategory":"Electronics",
            "type":"Manufacturing & Wholesale Goods"
        }
    ],
    "sg:phone":"+44 1592 762277",
    "sg:postcode":"KY7 5PY",
    "sg:province":"Fife",
    "sg:tags":[
        "mnfr",
        "component",
        "electronic"
    ],
    "wof:name":"Raytheon Systems Ltd.",
    "wof:placetype":"venue"
},
  "geometry": {"coordinates":[-3.173744,56.197208],"type":"Point"}
}