{
  "type": "Feature",
  "properties": {
    "iso:country":"GB",
    "sg:address":"Dorchester House, Station Parade",
    "sg:city":"Letchworth",
    "sg:classifiers":[
        {
            "category":"Banks & Credit Unions",
            "subcategory":"Bank",
            "type":"Services"
        }
    ],
    "sg:phone":"+44 1462 480666",
    "sg:postcode":"SG6 3AW",
    "sg:province":"Hertfordshire",
    "sg:tags":[
        "broker",
        "mortgage"
    ],
    "wof:name":"Capital Finance Associates",
    "wof:placetype":"venue"
},
  "geometry": {"coordinates":[-0.2244630009,51.980846405],"type":"Point"}
}