{
  "type": "Feature",
  "properties": {
    "iso:country":"GB",
    "sg:address":"64-68 Station Lane, Featherston",
    "sg:city":"Pontefract",
    "sg:classifiers":[
        {
            "category":"Recreation",
            "subcategory":"Fishing",
            "type":"Entertainment"
        }
    ],
    "sg:phone":"+44 1977 706921",
    "sg:postcode":"WF7 5BB",
    "sg:province":"West Yorkshire",
    "sg:tags":[
        "angling"
    ],
    "wof:name":"Paul Chambers",
    "wof:placetype":"venue"
},
  "geometry": {"coordinates":[-1.358549,53.677013],"type":"Point"}
}