{
  "type": "Feature",
  "properties": {
    "addr:full":"28 Churchill Road Gloucester Gloucestershire GL1 5DG",
    "addr:housenumber":"28",
    "addr:postcode":"gl1 5dg",
    "addr:street":"Churchill Road",
    "iso:country":"GB",
    "sg:address":"28 Churchill Road",
    "sg:city":"Gloucester",
    "sg:classifiers":[
        {
            "category":"Professional",
            "subcategory":"Engineering",
            "type":"Services"
        }
    ],
    "sg:postcode":"GL1 5DG",
    "sg:province":"Gloucestershire",
    "sg:tags":[
        "contractor",
        "electrical",
        "engineer"
    ],
    "wof:name":"B & D Electrical",
    "wof:placetype":"venue"
},
  "geometry": {"coordinates":[-2.2454888821,51.8524742126],"type":"Point"}
}