{
  "type": "Feature",
  "properties": {
    "addr:full":"22 Belgrave Gardens Southgate Greater London N14 4TT",
    "addr:housenumber":"22",
    "addr:postcode":"n14 4tt",
    "addr:street":"Belgrave Gardens",
    "iso:country":"GB",
    "sg:address":"22 Belgrave Gardens",
    "sg:city":"Southgate",
    "sg:classifiers":[
        {
            "category":"Building & Trades",
            "subcategory":"Construction",
            "type":"Services"
        }
    ],
    "sg:phone":"+44 20 8360 8267",
    "sg:postcode":"N14 4TT",
    "sg:province":"Greater London",
    "sg:tags":[
        "restoration",
        "refurbishment"
    ],
    "wof:name":"C V P Contracts",
    "wof:placetype":"venue"
},
  "geometry": {"coordinates":[-0.128421,51.648281],"type":"Point"}
}