{
  "type": "Feature",
  "properties": {
    "iso:country":"GB",
    "sg:address":"Banana House, Victoria Rd",
    "sg:city":"Chelmsford",
    "sg:classifiers":[
        {
            "category":"Building & Trades",
            "subcategory":"Construction",
            "type":"Services"
        }
    ],
    "sg:phone":"+44 1245 281231",
    "sg:postcode":"CM1 1PA",
    "sg:province":"Essex",
    "sg:tags":[
        "paint",
        "household",
        "spraying"
    ],
    "wof:name":"Morelli & Co Ltd",
    "wof:placetype":"venue"
},
  "geometry": {"coordinates":[0.4696159959,51.7362709045],"type":"Point"}
}