{
  "type": "Feature",
  "properties": {
    "addr:full":"Innovator House, Sunderland Enterprise Park Sunderland Tyne and Wear SR5 2TP",
    "addr:postcode":"sr5 2tp",
    "addr:street":"Park",
    "iso:country":"GB",
    "sg:address":"Innovator House, Sunderland Enterprise Park",
    "sg:city":"Sunderland",
    "sg:classifiers":[
        {
            "category":"Shopping",
            "subcategory":"Books",
            "type":"Retail Goods"
        }
    ],
    "sg:phone":"+44 191 516 6810",
    "sg:postcode":"SR5 2TP",
    "sg:province":"Tyne and Wear",
    "wof:name":"Inka Publishing Ltd.",
    "wof:placetype":"venue"
},
  "geometry": {"coordinates":[-1.41668,54.917919],"type":"Point"}
}