{
  "type": "Feature",
  "properties": {
    "iso:country":"GB",
    "sg:address":"3 Countess Street",
    "sg:city":"Saltcoats",
    "sg:classifiers":[
        {
            "category":"Personal",
            "subcategory":"Beauty Salon",
            "type":"Services"
        }
    ],
    "sg:phone":"+44 1294 604102",
    "sg:postcode":"KA21 5HP",
    "sg:province":"North Ayrshire",
    "sg:tags":[
        "unisex",
        "hairdresser"
    ],
    "wof:name":"The Clip Joint",
    "wof:placetype":"venue"
},
  "geometry": {"coordinates":[-4.785068,55.632908],"type":"Point"}
}