{
  "type": "Feature",
  "properties": {
    "addr:full":"Kings Court, Kingsway South, Team Valley Trading Estate Gateshead Tyne and Wear NE11 0SH",
    "addr:postcode":"ne11 0sh",
    "addr:street":"Kings Court;Trading",
    "iso:country":"GB",
    "sg:address":"Kings Court, Kingsway South, Team Valley Trading Estate",
    "sg:city":"Gateshead",
    "sg:classifiers":[
        {
            "category":"Personal",
            "type":"Services"
        },
        {
            "category":"Freight",
            "type":"Transportation"
        }
    ],
    "sg:phone":"+44 191 421 0000",
    "sg:postcode":"NE11 0SH",
    "sg:province":"Tyne and Wear",
    "sg:tags":[
        "haulage",
        "delivery",
        "transport",
        "road"
    ],
    "wof:name":"Business Post",
    "wof:placetype":"venue"
},
  "geometry": {"coordinates":[-1.6177150011,54.9306221008],"type":"Point"}
}