{
  "type": "Feature",
  "properties": {
    "addr:full":"Uplands Farm, Burtons Lane, Wellington Heath Ledbury Gloucestershire HR8 1NF",
    "addr:postcode":"hr8 1nf",
    "addr:street":"Burtons Lane",
    "iso:country":"GB",
    "sg:address":"Uplands Farm, Burtons Lane, Wellington Heath",
    "sg:city":"Ledbury",
    "sg:classifiers":[
        {
            "category":"Farming",
            "subcategory":"Dairy Farm",
            "type":"Manufacturing & Wholesale Goods"
        }
    ],
    "sg:phone":"+44 1531 632631",
    "sg:postcode":"HR8 1NF",
    "sg:province":"Gloucestershire",
    "wof:name":"P J Goodhew",
    "wof:placetype":"venue"
},
  "geometry": {"coordinates":[-2.42434,52.03894],"type":"Point"}
}