{
  "type": "Feature",
  "properties": {
    "iso:country":"GB",
    "sg:address":"78-80 City Road, Roath",
    "sg:city":"Cardiff",
    "sg:classifiers":[
        {
            "category":"Food & Beverages",
            "subcategory":"Liquor & Beverages",
            "type":"Retail Goods"
        }
    ],
    "sg:phone":"+44 29 2048 6432",
    "sg:postcode":"CF24 3DD",
    "sg:province":"Cardiff",
    "sg:tags":[
        "beer",
        "wine",
        "spirit",
        "wines"
    ],
    "wof:name":"Bottoms Up",
    "wof:placetype":"venue"
},
  "geometry": {"coordinates":[-3.16719,51.488083],"type":"Point"}
}