{
  "type": "Feature",
  "properties": {
    "iso:country":"GB",
    "sg:address":"1 The Nurseries, Moulton",
    "sg:city":"Northampton",
    "sg:classifiers":[
        {
            "category":"Building & Trades",
            "subcategory":"Construction",
            "type":"Services"
        }
    ],
    "sg:phone":"+44 1604 645156",
    "sg:postcode":"NN3 7SA",
    "sg:province":"Northamptonshire",
    "sg:tags":[
        "builder"
    ],
    "wof:name":"Sturgess Builders & Plastering Contractors",
    "wof:placetype":"venue"
},
  "geometry": {"coordinates":[-0.8524479866,52.2885894775],"type":"Point"}
}