{
  "type": "Feature",
  "properties": {
    "addr:full":"95 Moresdale Lane Leeds West Yorkshire LS14 6GG",
    "addr:housenumber":"95",
    "addr:postcode":"ls14 6gg",
    "addr:street":"Moresdale Lane",
    "iso:country":"GB",
    "sg:address":"95 Moresdale Lane",
    "sg:city":"Leeds",
    "sg:classifiers":[
        {
            "category":"Health Services",
            "subcategory":"Clinic",
            "type":"Services"
        }
    ],
    "sg:phone":"+44 113 295 1200",
    "sg:postcode":"LS14 6GG",
    "sg:province":"West Yorkshire",
    "sg:tags":[
        "nh"
    ],
    "sg:website":"http://www.gp-b86106.nhs.uk",
    "wof:name":"Foundry Lane Surgery",
    "wof:placetype":"venue"
},
  "geometry": {"coordinates":[-1.5465869904,53.7944946289],"type":"Point"}
}