{
  "type": "Feature",
  "properties": {
    "iso:country":"GB",
    "sg:address":"Central Warehouse Ripley Dr, Normanton Ind Est",
    "sg:city":"Normanton",
    "sg:classifiers":[
        {
            "category":"Food & Beverages",
            "subcategory":"Supermarket",
            "type":"Retail Goods"
        }
    ],
    "sg:postcode":"WF6 1QT",
    "sg:province":"West Yorkshire",
    "wof:name":"G T Smith Ltd",
    "wof:placetype":"venue"
},
  "geometry": {"coordinates":[-1.412878,53.698082],"type":"Point"}
}