{
  "type": "Feature",
  "properties": {
    "iso:country":"GB",
    "sg:address":"Two Mile Oak",
    "sg:city":"Newton Abbot",
    "sg:classifiers":[
        {
            "category":"Manufacturing",
            "subcategory":"Buildings",
            "type":"Manufacturing & Wholesale Goods"
        }
    ],
    "sg:phone":"+44 1803 813105",
    "sg:postcode":"TQ12 6DF",
    "sg:province":"Devon",
    "sg:tags":[
        "shed",
        "greenhouse"
    ],
    "wof:name":"Toby's Sheds Ltd.",
    "wof:placetype":"venue"
},
  "geometry": {"coordinates":[-3.62807,50.500641],"type":"Point"}
}