{
  "type": "Feature",
  "properties": {
    "addr:full":"Sorbon, 24-26 Aylesbury End Beaconsfield Buckinghamshire HP9 1LW",
    "addr:housenumber":"24-26",
    "addr:postcode":"hp9 1lw",
    "addr:street":"Sorbon;End",
    "iso:country":"GB",
    "sg:address":"Sorbon, 24-26 Aylesbury End",
    "sg:city":"Beaconsfield",
    "sg:classifiers":[
        {
            "category":"Professional",
            "subcategory":"Computer Services",
            "type":"Services"
        }
    ],
    "sg:phone":"+44 1494 687200",
    "sg:postcode":"HP9 1LW",
    "sg:province":"Buckinghamshire",
    "sg:tags":[
        "system",
        "software"
    ],
    "wof:name":"Sealedmedia Ltd.",
    "wof:placetype":"venue"
},
  "geometry": {"coordinates":[-0.6470230222,51.611869812],"type":"Point"}
}