{
  "type": "Feature",
  "properties": {
    "addr:full":"2 Newport Road, Eccleshall Stafford Staffordshire ST21 6BG",
    "addr:housenumber":"2",
    "addr:postcode":"st21 6bg",
    "addr:street":"Newport Road",
    "iso:country":"GB",
    "sg:address":"2 Newport Road, Eccleshall",
    "sg:city":"Stafford",
    "sg:classifiers":[
        {
            "category":"Building & Trades",
            "subcategory":"Cleaning & Sanitation",
            "type":"Services"
        }
    ],
    "sg:phone":"+44 1785 850931",
    "sg:postcode":"ST21 6BG",
    "sg:province":"Staffordshire",
    "sg:tags":[
        "commercial"
    ],
    "wof:name":"Impact C & T Ltd.",
    "wof:placetype":"venue"
},
  "geometry": {"coordinates":[-2.252856,52.858128],"type":"Point"}
}