{
  "type": "Feature",
  "properties": {
    "iso:country":"GB",
    "sg:address":"6 Riddings Court, Hartford",
    "sg:city":"Huntingdon",
    "sg:classifiers":[
        {
            "category":"Recreation",
            "subcategory":"Boat Charter",
            "type":"Entertainment"
        }
    ],
    "sg:phone":"+44 1606 783712",
    "sg:postcode":"PE28 2LZ",
    "sg:province":"Bedfordshire",
    "sg:tags":[
        "excursion"
    ],
    "wof:name":"Earley International",
    "wof:placetype":"venue"
},
  "geometry": {"coordinates":[-0.1616300046,52.336971283],"type":"Point"}
}