{
  "type": "Feature",
  "properties": {
    "addr:full":"4 Lansdowne Hill London Greater London SE27 0AR",
    "addr:housenumber":"4",
    "addr:postcode":"se27 0ar",
    "addr:street":"Lansdowne Hill",
    "iso:country":"GB",
    "sg:address":"4 Lansdowne Hill",
    "sg:city":"London",
    "sg:classifiers":[
        {
            "category":"Cafe",
            "type":"Food & Drink"
        }
    ],
    "sg:postcode":"SE27 0AR",
    "sg:province":"Greater London",
    "sg:tags":[
        "tea",
        "room"
    ],
    "wof:name":"The Landsdowne Cafe",
    "wof:placetype":"venue"
},
  "geometry": {"coordinates":[-0.104809,51.434364],"type":"Point"}
}