{
  "type": "Feature",
  "properties": {
    "iso:country":"GB",
    "sg:address":"124 Cheltenham Rd",
    "sg:city":"Bristol",
    "sg:classifiers":[
        {
            "category":"Shopping",
            "subcategory":"Bicycles & Sporting Goods",
            "type":"Retail Goods"
        }
    ],
    "sg:postcode":"BS6 5RW",
    "sg:province":"City of Bristol",
    "sg:tags":[
        "cycle",
        "accessory"
    ],
    "wof:name":"Curtiss,Tony,",
    "wof:placetype":"venue"
},
  "geometry": {"coordinates":[-2.5897610188,51.4646835327],"type":"Point"}
}