{
  "type": "Feature",
  "properties": {
    "iso:country":"GB",
    "sg:address":"52 John Street",
    "sg:city":"Aberdeen",
    "sg:classifiers":[
        {
            "category":"Food & Beverages",
            "subcategory":"Bakery",
            "type":"Retail Goods"
        }
    ],
    "sg:phone":"+44 1224 639607",
    "sg:postcode":"AB25 1LL",
    "sg:province":"Aberdeen City",
    "sg:tags":[
        "shop",
        "baker"
    ],
    "wof:name":"Aitken's Bakery",
    "wof:placetype":"venue"
},
  "geometry": {"coordinates":[-2.1032729149,57.1510887146],"type":"Point"}
}