{
  "type": "Feature",
  "properties": {
    "addr:full":"137 Shaw Street St Helens Merseyside WA10 1EN",
    "addr:housenumber":"137",
    "addr:postcode":"wa10 1en",
    "addr:street":"Shaw Street",
    "iso:country":"GB",
    "sg:address":"137 Shaw Street",
    "sg:city":"St Helens",
    "sg:classifiers":[
        {
            "category":"Organizations",
            "subcategory":"Membership Organization",
            "type":"Services"
        }
    ],
    "sg:phone":"+44 1744 23527",
    "sg:postcode":"WA10 1EN",
    "sg:province":"Merseyside",
    "sg:tags":[
        "club"
    ],
    "wof:name":"Shaw Street Social Club",
    "wof:placetype":"venue"
},
  "geometry": {"coordinates":[-2.729383,53.456249],"type":"Point"}
}