{
  "type": "Feature",
  "properties": {
    "iso:country":"GB",
    "sg:address":"Cotton Of Ovenstone Farm, Kirkbuddo",
    "sg:city":"Forfar",
    "sg:classifiers":[
        {
            "category":"Farming",
            "subcategory":"Farm",
            "type":"Manufacturing & Wholesale Goods"
        }
    ],
    "sg:phone":"+44 1307 820249",
    "sg:postcode":"DD8 2NQ",
    "sg:province":"Angus",
    "sg:tags":[
        "mixed",
        "crop"
    ],
    "wof:name":"Chas Smeaton & Sons",
    "wof:placetype":"venue"
},
  "geometry": {"coordinates":[-2.81403,56.580387],"type":"Point"}
}