{
  "type": "Feature",
  "properties": {
    "addr:full":"Unit 17 Torrington Av Coventry Warwickshire CV4 9HN",
    "addr:housenumber":"unit 17",
    "addr:postcode":"cv4 9hn",
    "addr:street":"Torrington Av",
    "iso:country":"GB",
    "sg:address":"Unit 17 Torrington Av",
    "sg:city":"Coventry",
    "sg:classifiers":[
        {
            "category":"Home & Garden",
            "subcategory":"Hardware",
            "type":"Retail Goods"
        }
    ],
    "sg:phone":"+44 24 7669 4744",
    "sg:postcode":"CV4 9HN",
    "sg:province":"Warwickshire",
    "sg:tags":[
        "equipment",
        "heating"
    ],
    "wof:name":"B S S Uk Ltd",
    "wof:placetype":"venue"
},
  "geometry": {"coordinates":[-1.5603569746,52.399066925],"type":"Point"}
}