{
  "type": "Feature",
  "properties": {
    "iso:country":"GB",
    "sg:address":"42 Main Road, Duston",
    "sg:city":"Northampton",
    "sg:classifiers":[
        {
            "category":"Health Services",
            "subcategory":"Optometrist",
            "type":"Services"
        },
        {
            "category":"Shopping",
            "subcategory":"Optician",
            "type":"Retail Goods"
        }
    ],
    "sg:phone":"+44 1604 758587",
    "sg:postcode":"NN5 6JF",
    "sg:province":"Northamptonshire",
    "sg:tags":[
        "ophthalmic"
    ],
    "wof:name":"Punch Opticians Ltd.",
    "wof:placetype":"venue"
},
  "geometry": {"coordinates":[-0.944407,52.243355],"type":"Point"}
}