{
  "type": "Feature",
  "properties": {
    "iso:country":"GB",
    "sg:address":"1 Britwell Cres",
    "sg:city":"Edinburgh",
    "sg:classifiers":[
        {
            "category":"Professional",
            "subcategory":"Engineering",
            "type":"Services"
        }
    ],
    "sg:phone":"+44 131 669 8426",
    "sg:postcode":"EH7 6PS",
    "sg:province":"City of Edinburgh",
    "sg:tags":[
        "contractor",
        "electrical",
        "engineer"
    ],
    "wof:name":"R J P Crawford",
    "wof:placetype":"venue"
},
  "geometry": {"coordinates":[-3.159261,55.956009],"type":"Point"}
}