{
  "type": "Feature",
  "properties": {
    "iso:country":"GB",
    "sg:address":"14 Appletree Close, Yaxley",
    "sg:city":"Peterborough",
    "sg:classifiers":[
        {
            "category":"Building & Trades",
            "subcategory":"Construction",
            "type":"Services"
        }
    ],
    "sg:phone":"+44 1733 243984",
    "sg:postcode":"PE7 3JY",
    "sg:province":"Cambridgeshire",
    "sg:tags":[
        "builder"
    ],
    "wof:name":"M & N Home Improvement Services",
    "wof:placetype":"venue"
},
  "geometry": {"coordinates":[-0.242503,52.518593],"type":"Point"}
}