{
  "type": "Feature",
  "properties": {
    "iso:country":"GB",
    "sg:address":"Falkirk Road",
    "sg:city":"Grangemouth",
    "sg:classifiers":[
        {
            "category":"Education",
            "subcategory":"Special Training",
            "type":"Public Place"
        }
    ],
    "sg:phone":"+44 1324 471894",
    "sg:postcode":"FK3 8XZ",
    "sg:province":"Falkirk",
    "sg:tags":[
        "product",
        "centre"
    ],
    "wof:name":"E C I T B",
    "wof:placetype":"venue"
},
  "geometry": {"coordinates":[-3.7461969852,56.0114135742],"type":"Point"}
}