{
  "type": "Feature",
  "properties": {
    "iso:country":"GB",
    "sg:address":"N8-n9 Unit, Europa Trading Estate, Fraser Road",
    "sg:city":"Erith",
    "sg:classifiers":[
        {
            "category":"Wholesale",
            "subcategory":"Medical Equipment & Supplies",
            "type":"Manufacturing & Wholesale Goods"
        },
        {
            "category":"Building & Trades",
            "subcategory":"Equipment Rental",
            "type":"Services"
        }
    ],
    "sg:phone":"+44 1322 430558",
    "sg:postcode":"DA8 1QL",
    "sg:province":"Kent",
    "sg:tags":[
        "supplier",
        "dental"
    ],
    "wof:name":"Dencare Ltd.",
    "wof:placetype":"venue"
},
  "geometry": {"coordinates":[0.180495,51.479221],"type":"Point"}
}