{
  "type": "Feature",
  "properties": {
    "addr:full":"Lower Rd, Fetcham Leatherhead Surrey KT22 9HD",
    "addr:postcode":"kt22 9hd",
    "addr:street":"Lower Rd",
    "iso:country":"GB",
    "sg:address":"Lower Rd, Fetcham",
    "sg:city":"Leatherhead",
    "sg:classifiers":[
        {
            "category":"Conference Center",
            "type":"Public Place"
        }
    ],
    "sg:phone":"+44 1372 371000",
    "sg:postcode":"KT22 9HD",
    "sg:province":"Surrey",
    "sg:tags":[
        "business",
        "centre"
    ],
    "wof:name":"Fetcham Park House",
    "wof:placetype":"venue"
},
  "geometry": {"coordinates":[-0.345964998,51.2841873169],"type":"Point"}
}