{
  "type": "Feature",
  "properties": {
    "addr:full":"Adelaide House, Chiswick High Rd Chiswick Greater London W4 5RJ",
    "addr:postcode":"w4 5rj",
    "addr:street":"Chiswick High Rd",
    "iso:country":"GB",
    "sg:address":"Adelaide House, Chiswick High Rd",
    "sg:city":"Chiswick",
    "sg:classifiers":[
        {
            "category":"Cinema",
            "subcategory":"Movie Theater",
            "type":"Entertainment"
        }
    ],
    "sg:phone":"+44 20 8987 5000",
    "sg:postcode":"W4 5RJ",
    "sg:province":"Greater London",
    "wof:name":"Virgin Cinemas",
    "wof:placetype":"venue"
},
  "geometry": {"coordinates":[-0.2661440074,51.492641449],"type":"Point"}
}