{
  "type": "Feature",
  "properties": {
    "iso:country":"GB",
    "sg:address":"Ashcroft, Thornton Dam Lane, Gilberdyke",
    "sg:city":"Brough",
    "sg:classifiers":[
        {
            "category":"Professional",
            "subcategory":"Engineering",
            "type":"Services"
        }
    ],
    "sg:postcode":"HU15 2UL",
    "sg:province":"East Riding of Yorkshire",
    "sg:tags":[
        "contractor",
        "electrical",
        "engineer"
    ],
    "wof:name":"Graham Pollard Electrical",
    "wof:placetype":"venue"
},
  "geometry": {"coordinates":[-0.739696,53.754517],"type":"Point"}
}