{
  "type": "Feature",
  "properties": {
    "iso:country":"GB",
    "sg:address":"The Rick, Hole House Lane",
    "sg:city":"Sturminster Newton",
    "sg:classifiers":[
        {
            "category":"Manufacturing",
            "subcategory":"Metals",
            "type":"Manufacturing & Wholesale Goods"
        }
    ],
    "sg:postcode":"DT10 2DJ",
    "sg:province":"Dorset",
    "sg:tags":[
        "steel",
        "fabricator",
        "erectors"
    ],
    "wof:name":"Mervyn Rose Engineering Ltd.",
    "wof:placetype":"venue"
},
  "geometry": {"coordinates":[-2.3128418922,50.9198112488],"type":"Point"}
}