{
  "type": "Feature",
  "properties": {
    "addr:full":"77a Woodfield Street, Morriston Swansea Swansea SA6 8BQ",
    "addr:housenumber":"77a",
    "addr:postcode":"sa6 8bq",
    "addr:street":"Woodfield Street",
    "iso:country":"GB",
    "sg:address":"77a Woodfield Street, Morriston",
    "sg:city":"Swansea",
    "sg:classifiers":[
        {
            "category":"Personal",
            "subcategory":"Beauty Salon",
            "type":"Services"
        }
    ],
    "sg:postcode":"SA6 8BQ",
    "sg:province":"Swansea",
    "sg:tags":[
        "unisex",
        "hairdresser"
    ],
    "wof:name":"Hairitage",
    "wof:placetype":"venue"
},
  "geometry": {"coordinates":[-3.9257500172,51.6628684998],"type":"Point"}
}