{
  "type": "Feature",
  "properties": {
    "iso:country":"GB",
    "sg:address":"20 Main St",
    "sg:city":"York",
    "sg:classifiers":[
        {
            "category":"Bars & Pubs",
            "type":"Food & Drink"
        }
    ],
    "sg:phone":"+44 1430 422939",
    "sg:postcode":"YO4 3UD",
    "sg:province":"East Riding of Yorkshire",
    "sg:tags":[
        "pubs",
        "inn"
    ],
    "wof:name":"Hotham Arms",
    "wof:placetype":"venue"
},
  "geometry": {"coordinates":[-0.6438199878,53.7977371216],"type":"Point"}
}