{
  "type": "Feature",
  "properties": {
    "iso:country":"GB",
    "sg:address":"Lodge Farm, Lavenham",
    "sg:city":"Sudbury",
    "sg:classifiers":[
        {
            "category":"Farming",
            "subcategory":"Livestock Farm",
            "type":"Manufacturing & Wholesale Goods"
        }
    ],
    "sg:phone":"+44 1284 828226",
    "sg:postcode":"CO10 9LR",
    "sg:province":"Essex",
    "sg:tags":[
        "others"
    ],
    "wof:name":"David Alston (Suffolk) Ltd.",
    "wof:placetype":"venue"
},
  "geometry": {"coordinates":[0.795288,52.107121],"type":"Point"}
}