{
  "type": "Feature",
  "properties": {
    "addr:full":"130 Cricklewood Broadway Cricklewood Greater London NW2 3EE",
    "addr:housenumber":"130",
    "addr:postcode":"nw2 3ee",
    "addr:street":"Cricklewood Broadway",
    "iso:country":"GB",
    "sg:address":"130 Cricklewood Broadway",
    "sg:city":"Cricklewood",
    "sg:classifiers":[
        {
            "category":"Shopping",
            "subcategory":"Department Store",
            "type":"Retail Goods"
        }
    ],
    "sg:phone":"+44 20 8452 9442",
    "sg:postcode":"NW2 3EE",
    "sg:province":"Greater London",
    "wof:name":"Tekeyan Minimarket",
    "wof:placetype":"venue"
},
  "geometry": {"coordinates":[-0.213675,51.555462],"type":"Point"}
}