{
  "type": "Feature",
  "properties": {
    "addr:full":"Fleming Way Crawley Surrey RH10 9DP",
    "addr:postcode":"rh10 9dp",
    "addr:street":"Fleming Way",
    "iso:country":"GB",
    "sg:address":"Fleming Way",
    "sg:city":"Crawley",
    "sg:classifiers":[
        {
            "category":"Home & Garden",
            "subcategory":"Hardware",
            "type":"Retail Goods"
        }
    ],
    "sg:phone":"+44 1293 523372",
    "sg:postcode":"RH10 9DP",
    "sg:province":"Surrey",
    "sg:tags":[
        "device",
        "fixing",
        "fastener"
    ],
    "wof:name":"I T W Construction Products",
    "wof:placetype":"venue"
},
  "geometry": {"coordinates":[-0.1706230044,51.1356964111],"type":"Point"}
}