{
  "type": "Feature",
  "properties": {
    "addr:full":"Sussex County Hospital, Eastern Road Brighton East Sussex BN2 5BE",
    "addr:postcode":"bn2 5be",
    "addr:street":"Eastern Road",
    "iso:country":"GB",
    "sg:address":"Sussex County Hospital, Eastern Road",
    "sg:city":"Brighton",
    "sg:classifiers":[
        {
            "category":"Shopping",
            "subcategory":"News",
            "type":"Retail Goods"
        }
    ],
    "sg:phone":"+44 1273 623828",
    "sg:postcode":"BN2 5BE",
    "sg:province":"East Sussex",
    "sg:tags":[
        "newsagent"
    ],
    "wof:name":"The Hospital Shop",
    "wof:placetype":"venue"
},
  "geometry": {"coordinates":[-0.0914440006,50.8122787476],"type":"Point"}
}