{
  "type": "Feature",
  "properties": {
    "addr:full":"Sutton Dene, Torbay Road Castle Cary Somerset BA7 7DW",
    "addr:postcode":"ba7 7dw",
    "addr:street":"Dene Torbay Road",
    "iso:country":"GB",
    "sg:address":"Sutton Dene, Torbay Road",
    "sg:city":"Castle Cary",
    "sg:classifiers":[
        {
            "category":"Retail",
            "subcategory":"Driving School",
            "type":"Services"
        }
    ],
    "sg:phone":"+44 1963 350536",
    "sg:postcode":"BA7 7DW",
    "sg:province":"Somerset",
    "wof:name":"Bruton School of Motoring",
    "wof:placetype":"venue"
},
  "geometry": {"coordinates":[-2.5180859566,51.0890693665],"type":"Point"}
}