{
  "type": "Feature",
  "properties": {
    "iso:country":"GB",
    "sg:address":"30 Westman Road",
    "sg:city":"Winchester",
    "sg:classifiers":[
        {
            "category":"Organizations",
            "subcategory":"Non-profit Organization",
            "type":"Services"
        }
    ],
    "sg:phone":"+44 1962 883536",
    "sg:postcode":"SO22 6DT",
    "sg:province":"Hampshire",
    "sg:tags":[
        "organisation",
        "animal",
        "welfare"
    ],
    "wof:name":"Cat Protection League",
    "wof:placetype":"venue"
},
  "geometry": {"coordinates":[-1.332065,51.076611],"type":"Point"}
}