{
  "type": "Feature",
  "properties": {
    "addr:full":"7 The Square, Portscatho Truro Cornwall TR2 5HW",
    "addr:housenumber":"7",
    "addr:postcode":"tr2 5hw",
    "addr:street":"The Square Portscatho",
    "iso:country":"GB",
    "sg:address":"7 The Square, Portscatho",
    "sg:city":"Truro",
    "sg:classifiers":[
        {
            "category":"Food & Beverages",
            "subcategory":"Meat & Fish",
            "type":"Retail Goods"
        }
    ],
    "sg:phone":"+44 1872 580246",
    "sg:postcode":"TR2 5HW",
    "sg:province":"Cornwall",
    "sg:tags":[
        "butcher"
    ],
    "wof:name":"A R Day Butchers",
    "wof:placetype":"venue"
},
  "geometry": {"coordinates":[-4.975716114,50.1791381836],"type":"Point"}
}