{
  "type": "Feature",
  "properties": {
    "addr:full":"6 Hawley Lane Industrial Estate, Hawley Lane Farnborough Hampshire GU14 8EH",
    "addr:housenumber":"6;estate",
    "addr:postcode":"gu14 8eh",
    "addr:street":"Hawley Lane Industrial;Hawley Lane",
    "iso:country":"GB",
    "sg:address":"6 Hawley Lane Industrial Estate, Hawley Lane",
    "sg:city":"Farnborough",
    "sg:classifiers":[
        {
            "category":"Shopping",
            "subcategory":"Computers & Home Electronics",
            "type":"Retail Goods"
        }
    ],
    "sg:phone":"+44 1252 540721",
    "sg:postcode":"GU14 8EH",
    "sg:province":"Hampshire",
    "sg:tags":[
        "equipment",
        "audio-visual"
    ],
    "wof:name":"Saville Audio Visual",
    "wof:placetype":"venue"
},
  "geometry": {"coordinates":[-0.7520689964,51.3087387085],"type":"Point"}
}