{
  "type": "Feature",
  "properties": {
    "iso:country":"GB",
    "sg:address":"79 Church Street, Burton Latimer",
    "sg:city":"Kettering",
    "sg:classifiers":[
        {
            "category":"Health Services",
            "subcategory":"Doctor",
            "type":"Services"
        }
    ],
    "sg:phone":"+44 1536 723413",
    "sg:postcode":"NN15 5LU",
    "sg:province":"Northamptonshire",
    "sg:tags":[
        "practitioners"
    ],
    "wof:name":"Pickering, J",
    "wof:placetype":"venue"
},
  "geometry": {"coordinates":[-0.6733919978,52.3664245605],"type":"Point"}
}