{
  "type": "Feature",
  "properties": {
    "addr:full":"66-68 Margaret Street London Greater London W1W 8SR",
    "addr:housenumber":"66-68",
    "addr:postcode":"w1w 8sr",
    "addr:street":"Margaret Street",
    "iso:country":"GB",
    "sg:address":"66-68 Margaret Street",
    "sg:city":"London",
    "sg:classifiers":[
        {
            "category":"Professional",
            "subcategory":"Accounting & Tax Preparation",
            "type":"Services"
        }
    ],
    "sg:postcode":"W1W 8SR",
    "sg:province":"Greater London",
    "sg:tags":[
        "accountant"
    ],
    "wof:name":"Shelley Simmons Pinnick & Co.",
    "wof:placetype":"venue"
},
  "geometry": {"coordinates":[-0.1400700063,51.5167312622],"type":"Point"}
}