{
  "type": "Feature",
  "properties": {
    "iso:country":"GB",
    "sg:address":"40 Elizabeth Way, Bishops Walford",
    "sg:city":"Southampton",
    "sg:classifiers":[
        {
            "category":"Communications",
            "subcategory":"Film & Video Production",
            "type":"Services"
        }
    ],
    "sg:postcode":"SO32 1SQ",
    "sg:province":"Hampshire",
    "sg:tags":[
        "recording",
        "studio"
    ],
    "wof:name":"A-Live Mobile Recording Services",
    "wof:placetype":"venue"
},
  "geometry": {"coordinates":[-1.223615,50.953892],"type":"Point"}
}