{
  "type": "Feature",
  "properties": {
    "addr:full":"Unit 25 Grovelands Park, Winnersh Wokingham Berkshire RG41 5LD",
    "addr:housenumber":"unit 25",
    "addr:postcode":"rg41 5ld",
    "addr:street":"Grovelands Park",
    "iso:country":"GB",
    "sg:address":"Unit 25 Grovelands Park, Winnersh",
    "sg:city":"Wokingham",
    "sg:classifiers":[
        {
            "category":"Building & Trades",
            "subcategory":"Construction",
            "type":"Services"
        }
    ],
    "sg:phone":"+44 118 978 2736",
    "sg:postcode":"RG41 5LD",
    "sg:province":"Berkshire",
    "sg:tags":[
        "roofing"
    ],
    "wof:name":"A A Williams Roofing Contractors",
    "wof:placetype":"venue"
},
  "geometry": {"coordinates":[-0.8681989908,51.4325790405],"type":"Point"}
}