{
  "type": "Feature",
  "properties": {
    "addr:full":"Unit 20, Llandow Industrial Estate Cowbridge The Vale of Glamorgan CF71 7PB",
    "addr:housenumber":"unit 20",
    "addr:postcode":"cf71 7pb",
    "addr:street":"Industrial Estate;Vale",
    "iso:country":"GB",
    "sg:address":"Unit 20, Llandow Industrial Estate",
    "sg:city":"Cowbridge",
    "sg:classifiers":[
        {
            "category":"Retail",
            "subcategory":"Driving School",
            "type":"Services"
        }
    ],
    "sg:phone":"+44 1446 775196",
    "sg:postcode":"CF71 7PB",
    "sg:province":"The Vale of Glamorgan",
    "sg:tags":[
        "instruction",
        "cycling",
        "motor"
    ],
    "wof:name":"M C Autec",
    "wof:placetype":"venue"
},
  "geometry": {"coordinates":[-3.4504249096,51.4623908997],"type":"Point"}
}