{
  "type": "Feature",
  "properties": {
    "iso:country":"GB",
    "sg:address":"21 Mere Street",
    "sg:city":"Diss",
    "sg:classifiers":[
        {
            "category":"Professional",
            "subcategory":"Engineering",
            "type":"Services"
        }
    ],
    "sg:phone":"+44 1379 642741",
    "sg:postcode":"IP22 4AD",
    "sg:province":"Norfolk",
    "sg:tags":[
        "contractor",
        "electrical",
        "engineer"
    ],
    "wof:name":"Taylor Electrical",
    "wof:placetype":"venue"
},
  "geometry": {"coordinates":[1.109177,52.375065],"type":"Point"}
}