{
  "type": "Feature",
  "properties": {
    "addr:full":"45 Warbreck Moor Liverpool Merseyside L9 4RW",
    "addr:housenumber":"45",
    "addr:postcode":"l9 4rw",
    "addr:street":"Warbreck Moor",
    "iso:country":"GB",
    "sg:address":"45 Warbreck Moor",
    "sg:city":"Liverpool",
    "sg:classifiers":[
        {
            "category":"Shopping",
            "subcategory":"Florist",
            "type":"Retail Goods"
        }
    ],
    "sg:phone":"+44 151 523 4650",
    "sg:postcode":"L9 4RW",
    "sg:province":"Merseyside",
    "wof:name":"Autumn Florist",
    "wof:placetype":"venue"
},
  "geometry": {"coordinates":[-2.957763,53.464966],"type":"Point"}
}