{
  "type": "Feature",
  "properties": {
    "addr:full":"72 Ongar Road Brentwood Essex CM15 9AX",
    "addr:housenumber":"72",
    "addr:postcode":"cm15 9ax",
    "addr:street":"Ongar Road",
    "iso:country":"GB",
    "sg:address":"72 Ongar Road",
    "sg:city":"Brentwood",
    "sg:classifiers":[
        {
            "category":"Professional",
            "subcategory":"Art Services",
            "type":"Services"
        }
    ],
    "sg:phone":"+44 1277 212895",
    "sg:postcode":"CM15 9AX",
    "sg:province":"Essex",
    "sg:tags":[
        "photographer"
    ],
    "wof:name":"Lindrum Photography",
    "wof:placetype":"venue"
},
  "geometry": {"coordinates":[0.303549,51.622883],"type":"Point"}
}