{
  "type": "Feature",
  "properties": {
    "addr:full":"Harefield Road Rickmansworth Hertfordshire WD3 1PD",
    "addr:postcode":"wd3 1pd",
    "addr:street":"Harefield Road",
    "iso:country":"GB",
    "sg:address":"Harefield Road",
    "sg:city":"Rickmansworth",
    "sg:classifiers":[
        {
            "category":"Retail",
            "subcategory":"Funeral Services",
            "type":"Services"
        },
        {
            "category":"Government",
            "subcategory":"Office",
            "type":"Public Place"
        }
    ],
    "sg:phone":"+44 1923 776611",
    "sg:postcode":"WD3 1PD",
    "sg:province":"Hertfordshire",
    "sg:tags":[
        "cemetery",
        "local",
        "crematorium"
    ],
    "wof:name":"Woodcock Hill Cemetry",
    "wof:placetype":"venue"
},
  "geometry": {"coordinates":[-0.471457988,51.6241607666],"type":"Point"}
}