{
  "type": "Feature",
  "properties": {
    "addr:full":"Shuttocks Wood, Norbury Bishops Castle Shropshire SY9 5EA",
    "addr:postcode":"sy9 5ea",
    "addr:street":"Wood",
    "iso:country":"GB",
    "sg:address":"Shuttocks Wood, Norbury",
    "sg:city":"Bishops Castle",
    "sg:classifiers":[
        {
            "category":"Building & Trades",
            "subcategory":"Landscaping Services",
            "type":"Services"
        }
    ],
    "sg:phone":"+44 1588 650433",
    "sg:postcode":"SY9 5EA",
    "sg:province":"Shropshire",
    "sg:tags":[
        "horticultural",
        "consultant"
    ],
    "wof:name":"Heritage Compost",
    "wof:placetype":"venue"
},
  "geometry": {"coordinates":[-2.996149,52.493301],"type":"Point"}
}