{
  "type": "Feature",
  "properties": {
    "addr:full":"93 Oak Street Norwich Norfolk NR3 3BP",
    "addr:housenumber":"93",
    "addr:postcode":"nr3 3bp",
    "addr:street":"Oak Street",
    "iso:country":"GB",
    "sg:address":"93 Oak Street",
    "sg:city":"Norwich",
    "sg:classifiers":[
        {
            "category":"Retail",
            "subcategory":"Funeral Services",
            "type":"Services"
        }
    ],
    "sg:phone":"+44 1603 764157",
    "sg:postcode":"NR3 3BP",
    "sg:province":"Norfolk",
    "sg:tags":[
        "director"
    ],
    "wof:name":"George Bush Funeral Home",
    "wof:placetype":"venue"
},
  "geometry": {"coordinates":[1.2888480425,52.6356582642],"type":"Point"}
}