{
  "type": "Feature",
  "properties": {
    "addr:full":"District Nurses, Huntly Health Centre Huntly Aberdeenshire AB54 8EX",
    "addr:postcode":"ab54 8ex",
    "addr:street":"Huntly",
    "iso:country":"GB",
    "sg:address":"District Nurses, Huntly Health Centre",
    "sg:city":"Huntly",
    "sg:classifiers":[
        {
            "category":"Health Services",
            "subcategory":"Clinic",
            "type":"Services"
        }
    ],
    "sg:postcode":"AB54 8EX",
    "sg:province":"Aberdeenshire",
    "sg:tags":[
        "nh"
    ],
    "wof:name":"Huntly Community Staff",
    "wof:placetype":"venue"
},
  "geometry": {"coordinates":[-2.7934091091,57.4425811768],"type":"Point"}
}