{
  "type": "Feature",
  "properties": {
    "addr:full":"Bushland Road Northampton Northamptonshire NN3 2NS",
    "addr:postcode":"nn3 2ns",
    "addr:street":"Bushland Road",
    "iso:country":"GB",
    "sg:address":"Bushland Road",
    "sg:city":"Northampton",
    "sg:classifiers":[
        {
            "category":"Education",
            "subcategory":"School",
            "type":"Public Place"
        },
        {
            "category":"Government",
            "subcategory":"Office",
            "type":"Public Place"
        }
    ],
    "sg:phone":"+44 1604 407098",
    "sg:postcode":"NN3 2NS",
    "sg:province":"Northamptonshire",
    "sg:tags":[
        "local",
        "authority"
    ],
    "wof:name":"Headlands Lower School & Nursery Unit",
    "wof:placetype":"venue"
},
  "geometry": {"coordinates":[-0.852974,52.259457],"type":"Point"}
}