{
  "type": "Feature",
  "properties": {
    "iso:country":"GB",
    "sg:address":"New Orchard Road, Thurcroft Industrial Estate, Thurcroft",
    "sg:city":"Rotherham",
    "sg:classifiers":[
        {
            "category":"Home & Garden",
            "subcategory":"Kitchen Supply",
            "type":"Retail Goods"
        }
    ],
    "sg:phone":"+44 1709 545147",
    "sg:postcode":"S66 9HY",
    "sg:province":"South Yorkshire",
    "sg:tags":[
        "equipment",
        "catering"
    ],
    "wof:name":"Southcroft Engineering Co. Ltd.",
    "wof:placetype":"venue"
},
  "geometry": {"coordinates":[-1.257554,53.394321],"type":"Point"}
}