{
  "type": "Feature",
  "properties": {
    "addr:full":"30 Upper Market Fakenham Norfolk NR21 9BX",
    "addr:housenumber":"30",
    "addr:postcode":"nr21 9bx",
    "addr:street":"Upper Market Fakenham",
    "iso:country":"GB",
    "sg:address":"30 Upper Market",
    "sg:city":"Fakenham",
    "sg:classifiers":[
        {
            "category":"Real Estate",
            "subcategory":"Surveying",
            "type":"Services"
        }
    ],
    "sg:postcode":"NR21 9BX",
    "sg:province":"Norfolk",
    "sg:tags":[
        "surveyor",
        "valuer"
    ],
    "wof:name":"PATRICK PLUMBTON",
    "wof:placetype":"venue"
},
  "geometry": {"coordinates":[0.8481029868,52.830329895],"type":"Point"}
}