{
  "type": "Feature",
  "properties": {
    "iso:country":"GB",
    "sg:address":"404 Heysham Road, Heysham",
    "sg:city":"Morecambe",
    "sg:classifiers":[
        {
            "category":"Retail",
            "subcategory":"Laundry & Dry Cleaning",
            "type":"Services"
        }
    ],
    "sg:postcode":"LA3 2BJ",
    "sg:province":"Lancashire",
    "sg:tags":[
        "launderette"
    ],
    "wof:name":"Launderama",
    "wof:placetype":"venue"
},
  "geometry": {"coordinates":[-2.892482,54.047508],"type":"Point"}
}