{
  "type": "Feature",
  "properties": {
    "addr:full":"15 Sherwood Road, Aston Fields Industrial Estate Bromsgrove Worcestershire B60 3DR",
    "addr:housenumber":"15",
    "addr:postcode":"b60 3dr",
    "addr:street":"Sherwood Road Aston Fields Industrial Estate",
    "iso:country":"GB",
    "sg:address":"15 Sherwood Road, Aston Fields Industrial Estate",
    "sg:city":"Bromsgrove",
    "sg:classifiers":[
        {
            "category":"Home & Garden",
            "subcategory":"Home Furnishings",
            "type":"Retail Goods"
        }
    ],
    "sg:phone":"+44 1527 575567",
    "sg:postcode":"B60 3DR",
    "sg:province":"Worcestershire",
    "sg:tags":[
        "mantelpiece",
        "fireplace"
    ],
    "wof:name":"Fairways Pine & Fire Places",
    "wof:placetype":"venue"
},
  "geometry": {"coordinates":[-2.060951,52.318184],"type":"Point"}
}