{
  "type": "Feature",
  "properties": {
    "iso:country":"GB",
    "sg:address":"74 High Street",
    "sg:city":"Braintree",
    "sg:classifiers":[
        {
            "category":"Shopping",
            "subcategory":"Thrift Store",
            "type":"Retail Goods"
        }
    ],
    "sg:phone":"+44 1376 343003",
    "sg:postcode":"CM7 1JP",
    "sg:province":"Essex",
    "sg:tags":[
        "shop",
        "charity"
    ],
    "wof:name":"Farley (Chelmsford) Hospice Shop",
    "wof:placetype":"venue"
},
  "geometry": {"coordinates":[0.550283,51.878136],"type":"Point"}
}