{
  "type": "Feature",
  "properties": {
    "addr:full":"Stephenson Rd, Churchfields Industrial Estate Salisbury Wiltshire SP2 7NP",
    "addr:housenumber":"estate",
    "addr:postcode":"sp2 7np",
    "addr:street":"Stephenson Rd Churchfields Industrial",
    "iso:country":"GB",
    "sg:address":"Stephenson Rd, Churchfields Industrial Estate",
    "sg:city":"Salisbury",
    "sg:classifiers":[
        {
            "category":"Manufacturing",
            "subcategory":"Building Materials",
            "type":"Manufacturing & Wholesale Goods"
        }
    ],
    "sg:phone":"+44 1722 328401",
    "sg:postcode":"SP2 7NP",
    "sg:province":"Wiltshire",
    "sg:tags":[
        "merchant",
        "builder"
    ],
    "wof:name":"Woodrows Of Salisbury",
    "wof:placetype":"venue"
},
  "geometry": {"coordinates":[-1.8117649555,51.069229126],"type":"Point"}
}