{
  "type": "Feature",
  "properties": {
    "iso:country":"GB",
    "sg:address":"Wrantage Mills, Wrantage",
    "sg:city":"Taunton",
    "sg:classifiers":[
        {
            "category":"Shopping",
            "subcategory":"Pets & Pet Supplies",
            "type":"Retail Goods"
        }
    ],
    "sg:phone":"+44 1823 480484",
    "sg:postcode":"TA3 6DG",
    "sg:province":"Devon",
    "sg:tags":[
        "food",
        "feed",
        "animal"
    ],
    "wof:name":"Wrantage Mills Ltd.",
    "wof:placetype":"venue"
},
  "geometry": {"coordinates":[-2.98811,50.997101],"type":"Point"}
}