{
  "type": "Feature",
  "properties": {
    "iso:country":"GB",
    "sg:address":"The Airfield, Dalby Road",
    "sg:city":"Melton Mowbray",
    "sg:classifiers":[
        {
            "category":"Home & Garden",
            "subcategory":"Hardware",
            "type":"Retail Goods"
        }
    ],
    "sg:phone":"+44 1664 480876",
    "sg:postcode":"LE13 0BL",
    "sg:province":"Leicestershire",
    "sg:tags":[
        "sealant",
        "glue",
        "adhesives"
    ],
    "wof:name":"Fosse Paper Packaging",
    "wof:placetype":"venue"
},
  "geometry": {"coordinates":[-0.889555,52.765869],"type":"Point"}
}