{
  "type": "Feature",
  "properties": {
    "addr:full":"Caparo House, 103 Baker Street London Greater London W1U 6FG",
    "addr:housenumber":"103",
    "addr:postcode":"w1u 6fg",
    "addr:street":"Baker Street",
    "iso:country":"GB",
    "sg:address":"Caparo House, 103 Baker Street",
    "sg:city":"London",
    "sg:classifiers":[
        {
            "category":"Banks & Credit Unions",
            "subcategory":"Investment Brokerage",
            "type":"Services"
        }
    ],
    "sg:phone":"+44 20 7486 1417",
    "sg:postcode":"W1U 6FG",
    "sg:province":"Greater London",
    "wof:name":"Caparo Group Ltd.",
    "wof:placetype":"venue"
},
  "geometry": {"coordinates":[-0.157086,51.520775],"type":"Point"}
}