{
  "type": "Feature",
  "properties": {
    "iso:country":"GB",
    "sg:address":"40 Preston Court, Lansdown Close",
    "sg:city":"Walton-on-thames",
    "sg:classifiers":[
        {
            "category":"Building & Trades",
            "subcategory":"Construction",
            "type":"Services"
        }
    ],
    "sg:postcode":"KT12 3NU",
    "sg:province":"Surrey",
    "sg:tags":[
        "builder"
    ],
    "wof:name":"The Little Builder",
    "wof:placetype":"venue"
},
  "geometry": {"coordinates":[-0.4053109884,51.3833770752],"type":"Point"}
}