{
  "type": "Feature",
  "properties": {
    "iso:country":"GB",
    "sg:address":"Wilson Marriage Centre, Barrack Street",
    "sg:city":"Colchester",
    "sg:classifiers":[
        {
            "category":"Government",
            "subcategory":"Office",
            "type":"Public Place"
        }
    ],
    "sg:phone":"+44 1206 798787",
    "sg:postcode":"CO1 2LR",
    "sg:province":"Essex",
    "sg:tags":[
        "local"
    ],
    "wof:name":"Seax Training",
    "wof:placetype":"venue"
},
  "geometry": {"coordinates":[0.91616,51.885078],"type":"Point"}
}