{
  "type": "Feature",
  "properties": {
    "iso:country":"GB",
    "sg:address":"93 Head Street",
    "sg:city":"Halstead",
    "sg:classifiers":[
        {
            "category":"Professional",
            "subcategory":"Printing & Photocopies",
            "type":"Services"
        }
    ],
    "sg:phone":"+44 1787 472582",
    "sg:postcode":"CO9 2AZ",
    "sg:province":"Essex",
    "sg:tags":[
        "printer"
    ],
    "wof:name":"Print Plus",
    "wof:placetype":"venue"
},
  "geometry": {"coordinates":[0.642093,51.947086],"type":"Point"}
}