{
  "type": "Feature",
  "properties": {
    "addr:full":"The Forge, Mundesley Road, Paston North Walsham Norfolk NR28 9TE",
    "addr:postcode":"nr28 9te",
    "addr:street":"Mundesley Road;Walsham",
    "iso:country":"GB",
    "sg:address":"The Forge, Mundesley Road, Paston",
    "sg:city":"North Walsham",
    "sg:classifiers":[
        {
            "category":"Manufacturing",
            "subcategory":"Metals",
            "type":"Manufacturing & Wholesale Goods"
        }
    ],
    "sg:postcode":"NR28 9TE",
    "sg:province":"Norfolk",
    "sg:tags":[
        "blacksmith",
        "forgemasters"
    ],
    "wof:name":"Brian Reynolds Blacksmith",
    "wof:placetype":"venue"
},
  "geometry": {"coordinates":[1.3847600222,52.8183135986],"type":"Point"}
}