{
  "type": "Feature",
  "properties": {
    "addr:full":"75 Home Farm Crescent, Whitnash Leamington Spa Warwickshire CV31 2QY",
    "addr:housenumber":"75",
    "addr:postcode":"cv31 2qy",
    "addr:street":"Home Farm Crescent",
    "iso:country":"GB",
    "sg:address":"75 Home Farm Crescent, Whitnash",
    "sg:city":"Leamington Spa",
    "sg:classifiers":[
        {
            "category":"Professional",
            "subcategory":"Computer Services",
            "type":"Services"
        }
    ],
    "sg:postcode":"CV31 2QY",
    "sg:province":"Warwickshire",
    "sg:tags":[
        "system",
        "software"
    ],
    "wof:name":"Clive Jenkinson",
    "wof:placetype":"venue"
},
  "geometry": {"coordinates":[-1.5210369825,52.2691383362],"type":"Point"}
}