{
  "type": "Feature",
  "properties": {
    "addr:full":"Court Lodge Farm, Forge La, East Farley Maidstone Kent ME15 0HQ",
    "addr:postcode":"me15 0hq",
    "addr:street":"Forge La East",
    "iso:country":"GB",
    "sg:address":"Court Lodge Farm, Forge La, East Farley",
    "sg:city":"Maidstone",
    "sg:classifiers":[
        {
            "category":"Building & Trades",
            "subcategory":"Construction",
            "type":"Services"
        }
    ],
    "sg:phone":"+44 1622 721539",
    "sg:postcode":"ME15 0HQ",
    "sg:province":"Kent",
    "sg:tags":[
        "excavation",
        "groundwork",
        "contractor"
    ],
    "wof:name":"G H Groundwork Ltd",
    "wof:placetype":"venue"
},
  "geometry": {"coordinates":[0.493809998,51.2505187988],"type":"Point"}
}