{
  "type": "Feature",
  "properties": {
    "addr:full":"39 Jarrow Road, Chadwell Heath Romford Essex RM6 5RH",
    "addr:housenumber":"39",
    "addr:postcode":"rm6 5rh",
    "addr:street":"Jarrow Road",
    "iso:country":"GB",
    "sg:address":"39 Jarrow Road, Chadwell Heath",
    "sg:city":"Romford",
    "sg:classifiers":[
        {
            "category":"Home & Garden",
            "subcategory":"Carpets & Floor Coverings",
            "type":"Retail Goods"
        }
    ],
    "sg:postcode":"RM6 5RH",
    "sg:province":"Essex",
    "sg:tags":[
        "carpets",
        "rug",
        "matting"
    ],
    "wof:name":"Francis Carpets",
    "wof:placetype":"venue"
},
  "geometry": {"coordinates":[0.125774,51.57428],"type":"Point"}
}