{
  "type": "Feature",
  "properties": {
    "iso:country":"GB",
    "sg:address":"Meirion Road",
    "sg:city":"Bangor",
    "sg:classifiers":[
        {
            "category":"Communications",
            "subcategory":"Film & Video Production",
            "type":"Services"
        }
    ],
    "sg:postcode":"LL57 2BY",
    "sg:province":"Gwynedd",
    "sg:tags":[
        "illustrator",
        "artist"
    ],
    "wof:name":"Edward Povey Studio",
    "wof:placetype":"venue"
},
  "geometry": {"coordinates":[-4.12951,53.231697],"type":"Point"}
}