{
  "type": "Feature",
  "properties": {
    "iso:country":"GB",
    "sg:address":"Kimberley House, Benns Lane",
    "sg:city":"King's Lynn",
    "sg:classifiers":[
        {
            "category":"Professional",
            "subcategory":"Art Services",
            "type":"Services"
        }
    ],
    "sg:phone":"+44 1553 829436",
    "sg:postcode":"PE34 4JY",
    "sg:province":"Lincolnshire",
    "sg:tags":[
        "model",
        "maker"
    ],
    "wof:name":"Chas Emerson",
    "wof:placetype":"venue"
},
  "geometry": {"coordinates":[0.30098,52.756889],"type":"Point"}
}