{
  "type": "Feature",
  "properties": {
    "addr:full":"15 Park Walk, Purley On Thames Reading Berkshire RG8 8BT",
    "addr:housenumber":"15",
    "addr:postcode":"rg8 8bt",
    "addr:street":"Park Walk",
    "iso:country":"GB",
    "sg:address":"15 Park Walk, Purley On Thames",
    "sg:city":"Reading",
    "sg:classifiers":[
        {
            "category":"Building & Trades",
            "subcategory":"Construction",
            "type":"Services"
        }
    ],
    "sg:phone":"+44 118 941 6875",
    "sg:postcode":"RG8 8BT",
    "sg:province":"Berkshire",
    "sg:tags":[
        "builder"
    ],
    "wof:name":"R W Rightway Builders & Developers",
    "wof:placetype":"venue"
},
  "geometry": {"coordinates":[-1.041784,51.480743],"type":"Point"}
}