{
  "type": "Feature",
  "properties": {
    "addr:full":"The Old British School House, East Street Chesham Buckinghamshire HP5 1DG",
    "addr:postcode":"hp5 1dg",
    "addr:street":"East Street",
    "iso:country":"GB",
    "sg:address":"The Old British School House, East Street",
    "sg:city":"Chesham",
    "sg:classifiers":[
        {
            "category":"Professional",
            "subcategory":"Art Services",
            "type":"Services"
        }
    ],
    "sg:phone":"+44 1494 775331",
    "sg:postcode":"HP5 1DG",
    "sg:province":"Buckinghamshire",
    "sg:tags":[
        "graphic",
        "designer"
    ],
    "wof:name":"Artset Graphics",
    "wof:placetype":"venue"
},
  "geometry": {"coordinates":[-0.612234,51.704533],"type":"Point"}
}