{
  "type": "Feature",
  "properties": {
    "addr:full":"Lomeshaye Bridge Mill Road Nelson Lancashire BB9 7BA",
    "addr:postcode":"bb9 7ba",
    "addr:street":"Bridge Mill Road",
    "iso:country":"GB",
    "sg:address":"Lomeshaye Bridge Mill Road",
    "sg:city":"Nelson",
    "sg:classifiers":[
        {
            "category":"Shopping",
            "subcategory":"Books",
            "type":"Retail Goods"
        }
    ],
    "sg:phone":"+44 1282 605767",
    "sg:postcode":"BB9 7BA",
    "sg:province":"Lancashire",
    "sg:tags":[
        "sample",
        "pattern"
    ],
    "wof:name":"The Newbridge Pattern Co. Ltd.",
    "wof:placetype":"venue"
},
  "geometry": {"coordinates":[-2.223529,53.834801],"type":"Point"}
}