{
  "type": "Feature",
  "properties": {
    "iso:country":"GB",
    "sg:address":"232 Paisley Road West",
    "sg:city":"Glasgow",
    "sg:classifiers":[
        {
            "category":"Building & Trades",
            "subcategory":"Landscaping Services",
            "type":"Services"
        }
    ],
    "sg:phone":"+44 141 427 9552",
    "sg:postcode":"G51 1NE",
    "sg:province":"Glasgow City",
    "sg:tags":[
        "pond",
        "aquarium"
    ],
    "wof:name":"Water World Aquatics",
    "wof:placetype":"venue"
},
  "geometry": {"coordinates":[-4.288424015,55.8525428772],"type":"Point"}
}