{
  "type": "Feature",
  "properties": {
    "addr:full":"30-32 Whitfield Street London Greater London W1T 2HR",
    "addr:housenumber":"30-32",
    "addr:postcode":"w1t 2hr",
    "addr:street":"Whitfield Street",
    "iso:country":"GB",
    "sg:address":"30-32 Whitfield Street",
    "sg:city":"London",
    "sg:classifiers":[
        {
            "category":"Professional",
            "subcategory":"Employment Agencies",
            "type":"Services"
        }
    ],
    "sg:phone":"+44 20 7304 4200",
    "sg:postcode":"W1T 2HR",
    "sg:province":"Greater London",
    "sg:tags":[
        "consultant"
    ],
    "wof:name":"Stafford Long & Partners Ltd.",
    "wof:placetype":"venue"
},
  "geometry": {"coordinates":[-0.1345990002,51.5198097229],"type":"Point"}
}