{
  "type": "Feature",
  "properties": {
    "iso:country":"GB",
    "sg:address":"Hathaway House, Church Road, Buxted",
    "sg:city":"Uckfield",
    "sg:classifiers":[
        {
            "category":"Home & Garden",
            "subcategory":"Home Furnishings",
            "type":"Retail Goods"
        }
    ],
    "sg:postcode":"TN22 4LT",
    "sg:province":"East Sussex",
    "sg:tags":[
        "blind",
        "curtain",
        "fitting"
    ],
    "wof:name":"Tamara O'Riordan Interiors",
    "wof:placetype":"venue"
},
  "geometry": {"coordinates":[0.1417350024,50.9915885925],"type":"Point"}
}