{
  "type": "Feature",
  "properties": {
    "iso:country":"GB",
    "sg:address":"127 South Farm Road",
    "sg:city":"Worthing",
    "sg:classifiers":[
        {
            "category":"Shopping",
            "subcategory":"Shoes",
            "type":"Retail Goods"
        }
    ],
    "sg:phone":"+44 1903 209440",
    "sg:postcode":"BN14 7AX",
    "sg:province":"West Sussex",
    "wof:name":"A & H Searle",
    "wof:placetype":"venue"
},
  "geometry": {"coordinates":[-0.37993,50.824608],"type":"Point"}
}