{
  "type": "Feature",
  "properties": {
    "iso:country":"GB",
    "sg:address":"Bleachfield Street",
    "sg:city":"Huntly",
    "sg:classifiers":[
        {
            "category":"Health Services",
            "subcategory":"Hospital",
            "type":"Services"
        }
    ],
    "sg:phone":"+44 1466 792114",
    "sg:postcode":"AB54 8EX",
    "sg:province":"Aberdeenshire",
    "wof:name":"Jubilee Hospital",
    "wof:placetype":"venue"
},
  "geometry": {"coordinates":[-2.788173914,57.4434890747],"type":"Point"}
}