{
  "type": "Feature",
  "properties": {
    "addr:full":"Colliery Road, Creswell Worksop Nottinghamshire S80 4BX",
    "addr:postcode":"s80 4bx",
    "addr:street":"Colliery Road",
    "iso:country":"GB",
    "sg:address":"Colliery Road, Creswell",
    "sg:city":"Worksop",
    "sg:classifiers":[
        {
            "category":"Shopping",
            "subcategory":"Pets & Pet Supplies",
            "type":"Retail Goods"
        }
    ],
    "sg:phone":"+44 1909 724576",
    "sg:postcode":"S80 4BX",
    "sg:province":"Nottinghamshire",
    "sg:tags":[
        "food"
    ],
    "wof:name":"2 Counties Pigeon & Pet Supplies",
    "wof:placetype":"venue"
},
  "geometry": {"coordinates":[-1.217444,53.26239],"type":"Point"}
}