{
  "type": "Feature",
  "properties": {
    "addr:full":"Unit 6 Blackhall Indust Est Inverurie Aberdeenshire AB51 4FS",
    "addr:housenumber":"unit 6",
    "addr:postcode":"ab51 4fs",
    "addr:street":"Indust",
    "iso:country":"GB",
    "sg:address":"Unit 6 Blackhall Indust Est",
    "sg:city":"Inverurie",
    "sg:classifiers":[
        {
            "category":"Food & Beverages",
            "subcategory":"Supermarket",
            "type":"Retail Goods"
        }
    ],
    "sg:phone":"+44 1467 625485",
    "sg:postcode":"AB51 4FS",
    "sg:province":"Aberdeenshire",
    "sg:tags":[
        "frozen"
    ],
    "wof:name":"Donut Co Of Scotland Ltd",
    "wof:placetype":"venue"
},
  "geometry": {"coordinates":[-2.391179,57.290501],"type":"Point"}
}