{
  "type": "Feature",
  "properties": {
    "iso:country":"GB",
    "sg:address":"94 Mercer Crescent, Helmshore",
    "sg:city":"Rossendale",
    "sg:classifiers":[
        {
            "category":"Education",
            "subcategory":"Music School",
            "type":"Public Place"
        },
        {
            "category":"Building & Trades",
            "subcategory":"Construction",
            "type":"Services"
        }
    ],
    "sg:postcode":"BB4 4DX",
    "sg:province":"Lancashire",
    "sg:tags":[
        "conservatory",
        "roofing"
    ],
    "wof:name":"B Anforth Stonemason",
    "wof:placetype":"venue"
},
  "geometry": {"coordinates":[-2.333483,53.695133],"type":"Point"}
}