{
  "type": "Feature",
  "properties": {
    "addr:full":"50 High Street Kirkcaldy Fife KY1 1NA",
    "addr:housenumber":"50",
    "addr:postcode":"ky1 1na",
    "addr:street":"High Street",
    "iso:country":"GB",
    "sg:address":"50 High Street",
    "sg:city":"Kirkcaldy",
    "sg:classifiers":[
        {
            "category":"Bars & Pubs",
            "type":"Food & Drink"
        }
    ],
    "sg:postcode":"KY1 1NA",
    "sg:province":"Fife",
    "sg:tags":[
        "pubs",
        "inn"
    ],
    "wof:name":"Mullin's Bar",
    "wof:placetype":"venue"
},
  "geometry": {"coordinates":[-3.159954,56.108219],"type":"Point"}
}