{
  "type": "Feature",
  "properties": {
    "addr:full":"Bath Road, Harehatch Reading Berkshire RG10 9SB",
    "addr:postcode":"rg10 9sb",
    "addr:street":"Bath Road Harehatch",
    "iso:country":"GB",
    "sg:address":"Bath Road, Harehatch",
    "sg:city":"Reading",
    "sg:classifiers":[
        {
            "category":"Building & Trades",
            "subcategory":"Landscaping Services",
            "type":"Services"
        }
    ],
    "sg:phone":"+44 118 940 4404",
    "sg:postcode":"RG10 9SB",
    "sg:province":"Berkshire",
    "sg:tags":[
        "contractor"
    ],
    "wof:name":"L A D D Ltd.",
    "wof:placetype":"venue"
},
  "geometry": {"coordinates":[-0.8917490244,51.4744148254],"type":"Point"}
}