{
  "type": "Feature",
  "properties": {
    "addr:full":"8 Bank House, Cherry Street Birmingham West Midlands B2 5AL",
    "addr:housenumber":"8",
    "addr:postcode":"b2 5al",
    "addr:street":"Bank House Cherry Street",
    "iso:country":"GB",
    "sg:address":"8 Bank House, Cherry Street",
    "sg:city":"Birmingham",
    "sg:classifiers":[
        {
            "category":"Real Estate",
            "subcategory":"Developer",
            "type":"Services"
        }
    ],
    "sg:phone":"+44 121 632 4000",
    "sg:postcode":"B2 5AL",
    "sg:province":"West Midlands",
    "sg:tags":[
        "property"
    ],
    "wof:name":"Amec Developments",
    "wof:placetype":"venue"
},
  "geometry": {"coordinates":[-1.8975,52.480282],"type":"Point"}
}