{
  "type": "Feature",
  "properties": {
    "addr:full":"65 Soames Crescent, Saxonfield Stoke-on-trent Staffordshire ST3 5UE",
    "addr:housenumber":"65",
    "addr:postcode":"staffordshire st3 5ue",
    "addr:street":"Soames Crescent",
    "iso:country":"GB",
    "sg:address":"65 Soames Crescent, Saxonfield",
    "sg:city":"Stoke-on-trent",
    "sg:classifiers":[
        {
            "category":"Home & Garden",
            "subcategory":"Furniture",
            "type":"Retail Goods"
        }
    ],
    "sg:postcode":"ST3 5UE",
    "sg:province":"Staffordshire",
    "wof:name":"Garry Hopley",
    "wof:placetype":"venue"
},
  "geometry": {"coordinates":[-2.13466,52.999996],"type":"Point"}
}