{
  "type": "Feature",
  "properties": {
    "addr:full":"14 New Street Woodbridge Suffolk IP12 1DX",
    "addr:housenumber":"14",
    "addr:postcode":"ip12 1dx",
    "addr:street":"New Street",
    "iso:country":"GB",
    "sg:address":"14 New Street",
    "sg:city":"Woodbridge",
    "sg:classifiers":[
        {
            "category":"Shopping",
            "subcategory":"Crafts & Fabrics",
            "type":"Retail Goods"
        }
    ],
    "sg:phone":"+44 1394 383467",
    "sg:postcode":"IP12 1DX",
    "sg:province":"Suffolk",
    "sg:tags":[
        "material",
        "art"
    ],
    "wof:name":"Frames by Robert",
    "wof:placetype":"venue"
},
  "geometry": {"coordinates":[1.3176460266,52.0944137573],"type":"Point"}
}