{
  "type": "Feature",
  "properties": {
    "iso:country":"GB",
    "sg:address":"Cuthbert's Close, Queensbury",
    "sg:city":"Bradford",
    "sg:classifiers":[
        {
            "category":"Organizations",
            "subcategory":"Non-profit Organization",
            "type":"Services"
        }
    ],
    "sg:phone":"+44 1274 884428",
    "sg:postcode":"BD13 2DF",
    "sg:province":"West Yorkshire",
    "sg:tags":[
        "charitable",
        "organisation",
        "voluntary",
        "charity"
    ],
    "wof:name":"HOSPITALER ORDER OF ST JOHN OF GOD",
    "wof:placetype":"venue"
},
  "geometry": {"coordinates":[-1.756705,53.753853],"type":"Point"}
}