{
  "type": "Feature",
  "properties": {
    "addr:full":"3 Murray Park St Andrews Fife KY16 9AW",
    "addr:housenumber":"3",
    "addr:postcode":"ky16 9aw",
    "addr:street":"Murray Park",
    "iso:country":"GB",
    "sg:address":"3 Murray Park",
    "sg:city":"St Andrews",
    "sg:classifiers":[
        {
            "category":"Travel",
            "subcategory":"Hotels & Motels",
            "type":"Entertainment"
        }
    ],
    "sg:phone":"+44 1334 472142",
    "sg:postcode":"KY16 9AW",
    "sg:province":"Fife",
    "sg:tags":[
        "house",
        "guest"
    ],
    "wof:name":"Craigmore Guest House",
    "wof:placetype":"venue"
},
  "geometry": {"coordinates":[-2.7981700897,56.34192276],"type":"Point"}
}