{
  "type": "Feature",
  "properties": {
    "iso:country":"GB",
    "sg:address":"22 Upper Wickham Lane",
    "sg:city":"Welling",
    "sg:classifiers":[
        {
            "category":"Shopping",
            "subcategory":"Department Store",
            "type":"Retail Goods"
        },
        {
            "category":"Shopping",
            "subcategory":"Beauty & Cosmetics",
            "type":"Retail Goods"
        }
    ],
    "sg:phone":"+44 20 8304 0903",
    "sg:postcode":"DA16 3HE",
    "sg:province":"Kent",
    "sg:tags":[
        "equipment",
        "hairdressing",
        "departmental",
        "supply"
    ],
    "wof:name":"Alans Homecare",
    "wof:placetype":"venue"
},
  "geometry": {"coordinates":[0.1079400033,51.4630661011],"type":"Point"}
}