{
  "type": "Feature",
  "properties": {
    "iso:country":"GB",
    "sg:address":"Priory Road",
    "sg:city":"Ulverston",
    "sg:classifiers":[
        {
            "category":"Food & Beverages",
            "subcategory":"Supermarket",
            "type":"Retail Goods"
        }
    ],
    "sg:phone":"+44 1229 582489",
    "sg:postcode":"LA12 9HR",
    "sg:province":"Cumbria",
    "wof:name":"Cumbrian Co-Operative Society",
    "wof:placetype":"venue"
},
  "geometry": {"coordinates":[-3.087269,54.185486],"type":"Point"}
}