{
  "type": "Feature",
  "properties": {
    "iso:country":"GB",
    "sg:address":"Abspann Cottage, Hamstead Road",
    "sg:city":"Yarmouth",
    "sg:classifiers":[
        {
            "category":"Building & Trades",
            "subcategory":"Cleaning & Sanitation",
            "type":"Services"
        }
    ],
    "sg:phone":"+44 1983 760870",
    "sg:postcode":"PO41 0YB",
    "sg:province":"Isle of Wight",
    "sg:tags":[
        "commercial",
        "sweep",
        "chimney"
    ],
    "wof:name":"Chiverton Joe & Son Chimney Clean Service",
    "wof:placetype":"venue"
},
  "geometry": {"coordinates":[-1.4966590405,50.7050094604],"type":"Point"}
}