{
  "type": "Feature",
  "properties": {
    "iso:country":"GB",
    "sg:address":"205 Commercial Road",
    "sg:city":"Portsmouth",
    "sg:classifiers":[
        {
            "category":"Health Services",
            "subcategory":"Optometrist",
            "type":"Services"
        }
    ],
    "sg:phone":"+44 23 9229 6959",
    "sg:postcode":"PO1 4BJ",
    "sg:province":"Hampshire",
    "sg:tags":[
        "optician"
    ],
    "wof:name":"Specsavers Opticians",
    "wof:placetype":"venue"
},
  "geometry": {"coordinates":[-1.088056,50.802303],"type":"Point"}
}