{
  "type": "Feature",
  "properties": {
    "addr:full":"Unit F, Marsden Building Malin Rd Sheffield South Yorkshire S6 5FG",
    "addr:postcode":"s6 5fg",
    "addr:street":"Malin Rd",
    "iso:country":"GB",
    "sg:address":"Unit F, Marsden Building Malin Rd",
    "sg:city":"Sheffield",
    "sg:classifiers":[
        {
            "category":"Retail",
            "subcategory":"Auto Repair",
            "type":"Services"
        }
    ],
    "sg:phone":"+44 114 233 9939",
    "sg:postcode":"S6 5FG",
    "sg:province":"South Yorkshire",
    "sg:tags":[
        "modification",
        "garage"
    ],
    "wof:name":"Graham Hill Motor Engineer",
    "wof:placetype":"venue"
},
  "geometry": {"coordinates":[-1.51429,53.39867],"type":"Point"}
}