{
  "type": "Feature",
  "properties": {
    "addr:full":"3 Holmethorpe Av Redhill Surrey RH1 2PA",
    "addr:housenumber":"3",
    "addr:postcode":"rh1 2pa",
    "addr:street":"Av Redhill",
    "iso:country":"GB",
    "sg:address":"3 Holmethorpe Av",
    "sg:city":"Redhill",
    "sg:classifiers":[
        {
            "category":"Shopping",
            "type":"Retail Goods"
        }
    ],
    "sg:phone":"+44 1256 693200",
    "sg:postcode":"RH1 2PA",
    "sg:province":"Surrey",
    "sg:tags":[
        "equipment",
        "clothing",
        "safety"
    ],
    "wof:name":"Dalloz Safety",
    "wof:placetype":"venue"
},
  "geometry": {"coordinates":[-0.159297,51.248772],"type":"Point"}
}