{
  "type": "Feature",
  "properties": {
    "iso:country":"GB",
    "sg:address":"6 Norwood Av",
    "sg:city":"Southport",
    "sg:classifiers":[
        {
            "category":"Home & Garden",
            "subcategory":"Household Appliances",
            "type":"Retail Goods"
        }
    ],
    "sg:phone":"+44 1704 231857",
    "sg:postcode":"PR9 7DT",
    "sg:province":"Lancashire",
    "sg:tags":[
        "domestic",
        "oven",
        "microwave"
    ],
    "wof:name":"David Christian Services",
    "wof:placetype":"venue"
},
  "geometry": {"coordinates":[-2.979096,53.651569],"type":"Point"}
}