{
  "type": "Feature",
  "properties": {
    "iso:country":"GB",
    "sg:address":"Unit 3, Agar Way",
    "sg:city":"Redruth",
    "sg:classifiers":[
        {
            "category":"Shopping",
            "subcategory":"Hobbies, Toys, & Games",
            "type":"Retail Goods"
        }
    ],
    "sg:postcode":"TR15 3SF",
    "sg:province":"Cornwall",
    "sg:tags":[
        "toy"
    ],
    "wof:name":"Horsecraft",
    "wof:placetype":"venue"
},
  "geometry": {"coordinates":[-5.263502,50.226715],"type":"Point"}
}