{
  "type": "Feature",
  "properties": {
    "addr:full":"137 West Pottergate Norwich Norfolk NR2 4BX",
    "addr:housenumber":"137",
    "addr:postcode":"nr2 4bx",
    "addr:street":"West Pottergate Norwich Norfolk",
    "iso:country":"GB",
    "sg:address":"137 West Pottergate",
    "sg:city":"Norwich",
    "sg:classifiers":[
        {
            "category":"Health Services",
            "subcategory":"Clinic",
            "type":"Services"
        }
    ],
    "sg:phone":"+44 1603 620263",
    "sg:postcode":"NR2 4BX",
    "sg:province":"Norfolk",
    "sg:tags":[
        "private"
    ],
    "wof:name":"Norwich Community Health Partnership",
    "wof:placetype":"venue"
},
  "geometry": {"coordinates":[1.280511,52.631104],"type":"Point"}
}