{
  "type": "Feature",
  "properties": {
    "addr:full":"25 Holland Cr Nottingham Derbyshire NG16 6AQ",
    "addr:housenumber":"25",
    "addr:postcode":"ng16 6aq",
    "addr:street":"Holland Cr",
    "iso:country":"GB",
    "sg:address":"25 Holland Cr",
    "sg:city":"Nottingham",
    "sg:classifiers":[
        {
            "category":"Home & Garden",
            "subcategory":"Garden Supply",
            "type":"Retail Goods"
        }
    ],
    "sg:phone":"+44 1773 863024",
    "sg:postcode":"NG16 6AQ",
    "sg:province":"Derbyshire",
    "sg:tags":[
        "pool",
        "swimming"
    ],
    "wof:name":"Amber Manufacturing",
    "wof:placetype":"venue"
},
  "geometry": {"coordinates":[-1.2925570011,53.0732536316],"type":"Point"}
}