{
  "type": "Feature",
  "properties": {
    "addr:full":"82 Colinton Mains Road Edinburgh City of Edinburgh EH13 9DN",
    "addr:housenumber":"82",
    "addr:postcode":"eh13 9dn",
    "addr:street":"Colinton Mains Road",
    "iso:country":"GB",
    "sg:address":"82 Colinton Mains Road",
    "sg:city":"Edinburgh",
    "sg:classifiers":[
        {
            "category":"Building & Trades",
            "subcategory":"Plumbing",
            "type":"Services"
        }
    ],
    "sg:postcode":"EH13 9DN",
    "sg:province":"City of Edinburgh",
    "sg:tags":[
        "heating"
    ],
    "wof:name":"Alan McBride",
    "wof:placetype":"venue"
},
  "geometry": {"coordinates":[-3.234542,55.909554],"type":"Point"}
}