{
  "type": "Feature",
  "properties": {
    "addr:full":"80a Queensway Billingham Durham TS23 2NR",
    "addr:housenumber":"80a",
    "addr:postcode":"ts23 2nr",
    "addr:street":"Queensway Billingham",
    "iso:country":"GB",
    "sg:address":"80a Queensway",
    "sg:city":"Billingham",
    "sg:classifiers":[
        {
            "category":"Personal",
            "subcategory":"Beauty Salon",
            "type":"Services"
        }
    ],
    "sg:phone":"+44 1642 534680",
    "sg:postcode":"TS23 2NR",
    "sg:province":"Durham",
    "sg:tags":[
        "unisex",
        "hairdresser"
    ],
    "wof:name":"Michael Gerard",
    "wof:placetype":"venue"
},
  "geometry": {"coordinates":[-1.293864,54.608028],"type":"Point"}
}