{
  "type": "Feature",
  "properties": {
    "addr:full":"117 Pen-y-lan Road Cardiff Cardiff CF23 5RB",
    "addr:housenumber":"117",
    "addr:postcode":"cf23 5rb",
    "addr:street":"Pen-Y-Lan Road",
    "iso:country":"GB",
    "sg:address":"117 Pen-y-lan Road",
    "sg:city":"Cardiff",
    "sg:classifiers":[
        {
            "category":"Health Services",
            "subcategory":"Podiatrist",
            "type":"Services"
        }
    ],
    "sg:phone":"+44 29 2049 3326",
    "sg:postcode":"CF23 5RB",
    "sg:province":"Cardiff",
    "sg:tags":[
        "podiatrists",
        "chiropodist"
    ],
    "wof:name":"S L Humble-Jackson",
    "wof:placetype":"venue"
},
  "geometry": {"coordinates":[-3.1615269184,51.4993400574],"type":"Point"}
}