{
  "type": "Feature",
  "properties": {
    "addr:full":"44 Abernant Road Aberdare Neath Port Talbot CF44 0PY",
    "addr:housenumber":"44",
    "addr:postcode":"cf44 0py",
    "addr:street":"Abernant Road",
    "iso:country":"GB",
    "sg:address":"44 Abernant Road",
    "sg:city":"Aberdare",
    "sg:classifiers":[
        {
            "category":"Social Services",
            "subcategory":"Retirement Home",
            "type":"Services"
        },
        {
            "category":"Government",
            "subcategory":"Office",
            "type":"Public Place"
        }
    ],
    "sg:phone":"+44 1685 877598",
    "sg:postcode":"CF44 0PY",
    "sg:province":"Neath Port Talbot",
    "sg:tags":[
        "residential",
        "local",
        "care"
    ],
    "wof:name":"Abernant Road Respite Care",
    "wof:placetype":"venue"
},
  "geometry": {"coordinates":[-3.438751936,51.7165908813],"type":"Point"}
}