{
  "type": "Feature",
  "properties": {
    "addr:full":"13 Chapel St Aberdeen Aberdeen City AB10 1SQ",
    "addr:housenumber":"13",
    "addr:postcode":"ab10 1sq",
    "addr:street":"Chapel St",
    "iso:country":"GB",
    "sg:address":"13 Chapel St",
    "sg:city":"Aberdeen",
    "sg:classifiers":[
        {
            "category":"Arts & Performance",
            "subcategory":"Art Gallery",
            "type":"Entertainment"
        }
    ],
    "sg:phone":"+44 1224 645537",
    "sg:postcode":"AB10 1SQ",
    "sg:province":"Aberdeen City",
    "wof:name":"Azure Graphics",
    "wof:placetype":"venue"
},
  "geometry": {"coordinates":[-2.110055,57.144066],"type":"Point"}
}