{
  "type": "Feature",
  "properties": {
    "addr:full":"173 Swinston Hill Rd Sheffield Derbyshire S31 7RY",
    "addr:housenumber":"173",
    "addr:postcode":"s31 7ry",
    "addr:street":"Swinston Hill Rd",
    "iso:country":"GB",
    "sg:address":"173 Swinston Hill Rd",
    "sg:city":"Sheffield",
    "sg:classifiers":[
        {
            "category":"Home & Garden",
            "subcategory":"Garden Supply",
            "type":"Retail Goods"
        }
    ],
    "sg:phone":"+44 1909 562485",
    "sg:postcode":"S31 7RY",
    "sg:province":"Derbyshire",
    "sg:tags":[
        "sand",
        "gravel"
    ],
    "wof:name":"Mortons",
    "wof:placetype":"venue"
},
  "geometry": {"coordinates":[-1.195755,53.362217],"type":"Point"}
}