{
  "type": "Feature",
  "properties": {
    "addr:full":"Wellswood House, 33 Cunningham Drive Lutterworth Leicestershire LE17 4YR",
    "addr:housenumber":"33",
    "addr:postcode":"le17 4yr",
    "addr:street":"Cunningham Drive",
    "iso:country":"GB",
    "sg:address":"Wellswood House, 33 Cunningham Drive",
    "sg:city":"Lutterworth",
    "sg:classifiers":[
        {
            "category":"Professional",
            "subcategory":"Management & Consulting",
            "type":"Services"
        },
        {
            "category":"Real Estate",
            "subcategory":"Architect",
            "type":"Services"
        }
    ],
    "sg:phone":"+44 1455 558006",
    "sg:postcode":"LE17 4YR",
    "sg:province":"Leicestershire",
    "sg:tags":[
        "consultant",
        "business"
    ],
    "wof:name":"Roger Bicknell Associates",
    "wof:placetype":"venue"
},
  "geometry": {"coordinates":[-1.217113018,52.4522285461],"type":"Point"}
}