{
  "type": "Feature",
  "properties": {
    "iso:country":"GB",
    "sg:address":"232 Aldborough Road South",
    "sg:city":"Ilford",
    "sg:classifiers":[
        {
            "category":"Personal",
            "type":"Services"
        }
    ],
    "sg:phone":"+44 20 8590 4422",
    "sg:postcode":"IG3 8HG",
    "sg:province":"Essex",
    "sg:tags":[
        "wedding"
    ],
    "wof:name":"Pearl Print",
    "wof:placetype":"venue"
},
  "geometry": {"coordinates":[0.100246,51.577236],"type":"Point"}
}