{
  "type": "Feature",
  "properties": {
    "iso:country":"GB",
    "sg:address":"4 Hughenden Yd",
    "sg:city":"Marlborough",
    "sg:classifiers":[
        {
            "category":"Shopping",
            "subcategory":"Musical Instruments",
            "type":"Retail Goods"
        }
    ],
    "sg:postcode":"SN8 1LT",
    "sg:province":"Berkshire",
    "sg:tags":[
        "music",
        "sheet"
    ],
    "wof:name":"Davis,P,",
    "wof:placetype":"venue"
},
  "geometry": {"coordinates":[-1.73318398,51.4195365906],"type":"Point"}
}