{
  "type": "Feature",
  "properties": {
    "iso:country":"GB",
    "sg:address":"50 Wood Street",
    "sg:city":"Lytham St Annes",
    "sg:classifiers":[
        {
            "category":"Shopping",
            "subcategory":"Thrift Store",
            "type":"Retail Goods"
        }
    ],
    "sg:postcode":"FY8 1QR",
    "sg:province":"Lancashire",
    "sg:tags":[
        "shop",
        "charity"
    ],
    "wof:name":"Grace",
    "wof:placetype":"venue"
},
  "geometry": {"coordinates":[-3.031185,53.750267],"type":"Point"}
}