{
  "type": "Feature",
  "properties": {
    "addr:full":"The Ground Floor,wharf Mill,huddersfield Rd Oldham Lancashire OL3 5NT",
    "addr:postcode":"ol3 5nt",
    "addr:street":"Wharf Mill Huddersfield Rd",
    "iso:country":"GB",
    "sg:address":"The Ground Floor,wharf Mill,huddersfield Rd",
    "sg:city":"Oldham",
    "sg:classifiers":[
        {
            "category":"Professional",
            "subcategory":"Engineering",
            "type":"Services"
        }
    ],
    "sg:phone":"+44 1457 873479",
    "sg:postcode":"OL3 5NT",
    "sg:province":"Lancashire",
    "wof:name":"Alt Tool Co",
    "wof:placetype":"venue"
},
  "geometry": {"coordinates":[-2.0035099983,53.5600891113],"type":"Point"}
}