{
  "type": "Feature",
  "properties": {
    "addr:full":"Unit 5 Simonsburn Road, Loreny Industrial Estate Kilmarnock East Ayrshire KA1 5LA",
    "addr:housenumber":"unit 5",
    "addr:postcode":"ka1 5la",
    "addr:street":"Simonsburn Road Loreny Industrial Estate Kilmarnock East",
    "iso:country":"GB",
    "sg:address":"Unit 5 Simonsburn Road, Loreny Industrial Estate",
    "sg:city":"Kilmarnock",
    "sg:classifiers":[
        {
            "category":"Building & Trades",
            "subcategory":"Construction",
            "type":"Services"
        }
    ],
    "sg:phone":"+44 1563 527398",
    "sg:postcode":"KA1 5LA",
    "sg:province":"East Ayrshire",
    "sg:tags":[
        "welder"
    ],
    "wof:name":"Thomson Lockhart (Engineering) Ltd.",
    "wof:placetype":"venue"
},
  "geometry": {"coordinates":[-4.5074839592,55.5844917297],"type":"Point"}
}