{
  "type": "Feature",
  "properties": {
    "iso:country":"GB",
    "sg:address":"Llantrisant Business Park",
    "sg:city":"Pontyclun",
    "sg:classifiers":[
        {
            "category":"Manufacturing",
            "subcategory":"Metals",
            "type":"Manufacturing & Wholesale Goods"
        }
    ],
    "sg:phone":"+44 1443 239397",
    "sg:postcode":"CF72 8YW",
    "sg:province":"Bridgend",
    "sg:tags":[
        "work",
        "sheet"
    ],
    "wof:name":"Star Sheet Metal Works Ltd.",
    "wof:placetype":"venue"
},
  "geometry": {"coordinates":[-3.382039,51.554356],"type":"Point"}
}