{
  "type": "Feature",
  "properties": {
    "iso:country":"GB",
    "sg:address":"24 Mostyn St",
    "sg:city":"Wallasey",
    "sg:classifiers":[
        {
            "category":"Building & Trades",
            "subcategory":"Plumbing",
            "type":"Services"
        }
    ],
    "sg:phone":"+44 151 630 4322",
    "sg:postcode":"L44 4EA",
    "sg:province":"Merseyside",
    "sg:tags":[
        "drain",
        "clearance",
        "sewer"
    ],
    "wof:name":"Rob Harman",
    "wof:placetype":"venue"
},
  "geometry": {"coordinates":[-3.043852,53.409744],"type":"Point"}
}