{
  "type": "Feature",
  "properties": {
    "iso:country":"GB",
    "sg:address":"Totters Farm, Totters Lane",
    "sg:city":"Hook",
    "sg:classifiers":[
        {
            "category":"Retail",
            "subcategory":"Auto Repair",
            "type":"Services"
        }
    ],
    "sg:postcode":"RG27 8HX",
    "sg:province":"Berkshire",
    "sg:tags":[
        "modification",
        "garage"
    ],
    "wof:name":"C P Autos",
    "wof:placetype":"venue"
},
  "geometry": {"coordinates":[-0.929626,51.283886],"type":"Point"}
}