{
  "type": "Feature",
  "properties": {
    "iso:country":"GB",
    "sg:address":"Oulton Pl, George St",
    "sg:city":"Chester",
    "sg:classifiers":[
        {
            "category":"Education",
            "subcategory":"School",
            "type":"Public Place"
        }
    ],
    "sg:phone":"+44 1244 377346",
    "sg:postcode":"CH1 3HX",
    "sg:province":"Cheshire",
    "sg:tags":[
        "local",
        "authority"
    ],
    "wof:name":"Cheshire Support Teaching Services West Cheshire Area",
    "wof:placetype":"venue"
},
  "geometry": {"coordinates":[-2.889994,53.194721],"type":"Point"}
}