{
  "type": "Feature",
  "properties": {
    "addr:full":"29 Farley Hill Luton Bedfordshire LU1 5EE",
    "addr:housenumber":"29",
    "addr:postcode":"lu1 5ee",
    "addr:street":"Farley Hill",
    "iso:country":"GB",
    "sg:address":"29 Farley Hill",
    "sg:city":"Luton",
    "sg:classifiers":[
        {
            "category":"Retail",
            "subcategory":"Auto Repair",
            "type":"Services"
        }
    ],
    "sg:phone":"+44 1582 722776",
    "sg:postcode":"LU1 5EE",
    "sg:province":"Bedfordshire",
    "sg:tags":[
        "modification",
        "garage",
        "related"
    ],
    "wof:name":"Garage Services",
    "wof:placetype":"venue"
},
  "geometry": {"coordinates":[-0.419798,51.87352],"type":"Point"}
}