{
  "type": "Feature",
  "properties": {
    "addr:full":"Commercial Street, Pontymister Newport Blaenau Gwent NP11 6EE",
    "addr:postcode":"np11 6ee",
    "addr:street":"Commercial Street",
    "iso:country":"GB",
    "sg:address":"Commercial Street, Pontymister",
    "sg:city":"Newport",
    "sg:classifiers":[
        {
            "category":"Organizations",
            "subcategory":"Community Association",
            "type":"Services"
        },
        {
            "category":"Organizations",
            "subcategory":"Membership Organization",
            "type":"Services"
        }
    ],
    "sg:phone":"+44 1633 612375",
    "sg:postcode":"NP11 6EE",
    "sg:province":"Blaenau Gwent",
    "sg:tags":[
        "club",
        "social"
    ],
    "wof:name":"Risca Working Mens Branch Club",
    "wof:placetype":"venue"
},
  "geometry": {"coordinates":[-3.099243,51.605789],"type":"Point"}
}