{
  "type": "Feature",
  "properties": {
    "addr:full":"Swan Court, Swan St, Old Isleworth Isleworth Greater London TW7 6RJ",
    "addr:postcode":"tw7 6rj",
    "addr:street":"Swan Court;St",
    "iso:country":"GB",
    "sg:address":"Swan Court, Swan St, Old Isleworth",
    "sg:city":"Isleworth",
    "sg:classifiers":[
        {
            "category":"Autos & Motor Vehicles",
            "subcategory":"Motorcycle Sales",
            "type":"Retail Goods"
        }
    ],
    "sg:phone":"+44 1784 436087",
    "sg:postcode":"TW7 6RJ",
    "sg:province":"Greater London",
    "sg:tags":[
        "chauffeur",
        "driven",
        "car"
    ],
    "wof:name":"Hudson Chauffeur Drive",
    "wof:placetype":"venue"
},
  "geometry": {"coordinates":[-0.32376,51.46896],"type":"Point"}
}