{
  "type": "Feature",
  "properties": {
    "iso:country":"GB",
    "sg:address":"10 Lowfield Way, Hazelmere",
    "sg:city":"High Wycombe",
    "sg:classifiers":[
        {
            "category":"Building & Trades",
            "subcategory":"Plumbing",
            "type":"Services"
        }
    ],
    "sg:phone":"+44 1494 815608",
    "sg:postcode":"HP15 7TT",
    "sg:province":"Buckinghamshire",
    "sg:tags":[
        "central",
        "heating"
    ],
    "wof:name":"C.N.S. Plumbing and Heating",
    "wof:placetype":"venue"
},
  "geometry": {"coordinates":[-0.7074310184,51.6471824646],"type":"Point"}
}