{
  "type": "Feature",
  "properties": {
    "addr:full":"100 Edgeworth Rd Bath Somerset BA2 2LU",
    "addr:housenumber":"100",
    "addr:postcode":"ba2 2lu",
    "addr:street":"Edgeworth Rd",
    "iso:country":"GB",
    "sg:address":"100 Edgeworth Rd",
    "sg:city":"Bath",
    "sg:classifiers":[
        {
            "category":"Building & Trades",
            "subcategory":"Construction",
            "type":"Services"
        }
    ],
    "sg:phone":"+44 1225 424445",
    "sg:postcode":"BA2 2LU",
    "sg:province":"Somerset",
    "sg:tags":[
        "builder"
    ],
    "wof:name":"Richardson K",
    "wof:placetype":"venue"
},
  "geometry": {"coordinates":[-2.385419,51.364334],"type":"Point"}
}