{
  "type": "Feature",
  "properties": {
    "addr:full":"3-5 Thane Villas London Greater London N7 7PH",
    "addr:housenumber":"3-5",
    "addr:postcode":"n7 7ph",
    "addr:street":"Thane Villas",
    "iso:country":"GB",
    "sg:address":"3-5 Thane Villas",
    "sg:city":"London",
    "sg:classifiers":[
        {
            "category":"Shopping",
            "subcategory":"Clothing, Apparel, & Fashions",
            "type":"Retail Goods"
        }
    ],
    "sg:phone":"+44 20 7607 0429",
    "sg:postcode":"N7 7PH",
    "sg:province":"Greater London",
    "sg:tags":[
        "clothing",
        "fabric"
    ],
    "wof:name":"Fosby of London Ltd.",
    "wof:placetype":"venue"
},
  "geometry": {"coordinates":[-0.1125390008,51.5597801208],"type":"Point"}
}