{
  "type": "Feature",
  "properties": {
    "iso:country":"GB",
    "sg:address":"5-6 Woodside Walk, Whinfield Indstl Est",
    "sg:city":"Rowlands Gill",
    "sg:classifiers":[
        {
            "category":"Building & Trades",
            "subcategory":"Construction",
            "type":"Services"
        }
    ],
    "sg:phone":"+44 1207 545549",
    "sg:postcode":"NE39 1EH",
    "sg:province":"Durham",
    "sg:tags":[
        "builder"
    ],
    "wof:name":"Leech Homes Ltd",
    "wof:placetype":"venue"
},
  "geometry": {"coordinates":[-1.7627,54.918678],"type":"Point"}
}