{
  "type": "Feature",
  "properties": {
    "iso:country":"GB",
    "sg:address":"150 Chester Road",
    "sg:city":"Sunderland",
    "sg:classifiers":[
        {
            "category":"Organizations",
            "subcategory":"Non-profit Organization",
            "type":"Services"
        }
    ],
    "sg:phone":"+44 191 514 5460",
    "sg:postcode":"SR4 7EY",
    "sg:province":"Tyne and Wear",
    "sg:tags":[
        "organisation",
        "voluntary",
        "charity"
    ],
    "wof:name":"Barnardo's",
    "wof:placetype":"venue"
},
  "geometry": {"coordinates":[-1.3992749453,54.9025268555],"type":"Point"}
}