{
  "type": "Feature",
  "properties": {
    "iso:country":"GB",
    "sg:address":"Sands Care Home, 390 Marine Road East",
    "sg:city":"Morecambe",
    "sg:classifiers":[
        {
            "category":"Health Services",
            "subcategory":"Nursing And Care Facility",
            "type":"Services"
        },
        {
            "category":"Social Services",
            "subcategory":"Retirement Home",
            "type":"Services"
        }
    ],
    "sg:phone":"+44 1524 400300",
    "sg:postcode":"LA4 5AU",
    "sg:province":"Lancashire",
    "sg:tags":[
        "rest"
    ],
    "wof:name":"The Sands Retirement & Nursing Home",
    "wof:placetype":"venue"
},
  "geometry": {"coordinates":[-2.854494,54.070129],"type":"Point"}
}