{
  "type": "Feature",
  "properties": {
    "iso:country":"GB",
    "sg:address":"7-9 Station Square",
    "sg:city":"Lowestoft",
    "sg:classifiers":[
        {
            "category":"Recreation",
            "subcategory":"Amusement Park",
            "type":"Entertainment"
        }
    ],
    "sg:phone":"+44 1502 574764",
    "sg:postcode":"NR32 1BA",
    "sg:province":"Suffolk",
    "sg:tags":[
        "arcade",
        "activity"
    ],
    "wof:name":"Bridge Amusements",
    "wof:placetype":"venue"
},
  "geometry": {"coordinates":[1.7495830059,52.4731559753],"type":"Point"}
}