{
  "type": "Feature",
  "properties": {
    "iso:country":"GB",
    "sg:address":"58 Oxford Street",
    "sg:city":"Oldham",
    "sg:classifiers":[
        {
            "category":"Shopping",
            "subcategory":"Department Store",
            "type":"Retail Goods"
        },
        {
            "category":"Food & Beverages",
            "subcategory":"Groceries & Convenience Stores",
            "type":"Retail Goods"
        }
    ],
    "sg:phone":"+44 161 628 5396",
    "sg:postcode":"OL9 7SL",
    "sg:province":"Lancashire",
    "wof:name":"G M Khan",
    "wof:placetype":"venue"
},
  "geometry": {"coordinates":[-2.134826,53.534512],"type":"Point"}
}