{
  "type": "Feature",
  "properties": {
    "iso:country":"GB",
    "sg:address":"6-18 Corbert Place",
    "sg:city":"London",
    "sg:classifiers":[
        {
            "category":"Personal",
            "subcategory":"Skin Care",
            "type":"Services"
        }
    ],
    "sg:postcode":"E1 6NH",
    "sg:province":"Greater London",
    "sg:tags":[
        "leather",
        "merchant"
    ],
    "wof:name":"Al-Farooq Sheepskin",
    "wof:placetype":"venue"
},
  "geometry": {"coordinates":[-0.074184,51.520882],"type":"Point"}
}