{
  "type": "Feature",
  "properties": {
    "addr:full":"63 Lake Terr Melton Mowbray Leicestershire LE13 0BZ",
    "addr:housenumber":"63",
    "addr:postcode":"le13 0bz",
    "addr:street":"Lake Terr",
    "iso:country":"GB",
    "sg:address":"63 Lake Terr",
    "sg:city":"Melton Mowbray",
    "sg:classifiers":[
        {
            "category":"Organizations",
            "subcategory":"Non-profit Organization",
            "type":"Services"
        }
    ],
    "sg:phone":"+44 1664 410755",
    "sg:postcode":"LE13 0BZ",
    "sg:province":"Leicestershire",
    "sg:tags":[
        "organisation",
        "voluntary",
        "charity"
    ],
    "wof:name":"Mencap",
    "wof:placetype":"venue"
},
  "geometry": {"coordinates":[-0.8982639909,52.7610054016],"type":"Point"}
}