{
  "type": "Feature",
  "properties": {
    "iso:country":"GB",
    "sg:address":"1 Fairfield Road",
    "sg:city":"Warminster",
    "sg:classifiers":[
        {
            "category":"Personal",
            "subcategory":"Skin Care",
            "type":"Services"
        }
    ],
    "sg:phone":"+44 1985 212496",
    "sg:postcode":"BA12 9DJ",
    "sg:province":"Somerset",
    "sg:tags":[
        "leather",
        "merchant"
    ],
    "wof:name":"Clark International Components",
    "wof:placetype":"venue"
},
  "geometry": {"coordinates":[-2.1757609844,51.2046813965],"type":"Point"}
}