{
  "type": "Feature",
  "properties": {
    "iso:country":"GB",
    "sg:address":"27 Lyndale Road, Eldwick",
    "sg:city":"Bingley",
    "sg:classifiers":[
        {
            "category":"Professional",
            "subcategory":"Engineering",
            "type":"Services"
        }
    ],
    "sg:postcode":"BD16 3HE",
    "sg:province":"West Yorkshire",
    "wof:name":"Predictive Maintenance Co. Ltd.",
    "wof:placetype":"venue"
},
  "geometry": {"coordinates":[-1.813524,53.858414],"type":"Point"}
}