{
  "type": "Feature",
  "properties": {
    "addr:full":"8 Stoneleigh Park Road, Ewell Epsom Surrey KT19 0QT",
    "addr:housenumber":"8",
    "addr:postcode":"kt19 0qt",
    "addr:street":"Stoneleigh Park Road",
    "iso:country":"GB",
    "sg:address":"8 Stoneleigh Park Road, Ewell",
    "sg:city":"Epsom",
    "sg:classifiers":[
        {
            "category":"Bus Charters",
            "type":"Transportation"
        }
    ],
    "sg:phone":"+44 20 8394 1134",
    "sg:postcode":"KT19 0QT",
    "sg:province":"Surrey",
    "sg:tags":[
        "mini",
        "hire",
        "leasing"
    ],
    "wof:name":"Apex Mini Buses",
    "wof:placetype":"venue"
},
  "geometry": {"coordinates":[-0.25213,51.360748],"type":"Point"}
}