{
  "type": "Feature",
  "properties": {
    "iso:country":"GB",
    "sg:address":"190 Bexhill Road",
    "sg:city":"St Leonards-on-sea",
    "sg:classifiers":[
        {
            "category":"Organizations",
            "subcategory":"Membership Organization",
            "type":"Services"
        }
    ],
    "sg:postcode":"TN38 8BL",
    "sg:province":"East Sussex",
    "sg:tags":[
        "club"
    ],
    "wof:name":"The Ranch",
    "wof:placetype":"venue"
},
  "geometry": {"coordinates":[0.5283560157,50.8518066406],"type":"Point"}
}