{
  "type": "Feature",
  "properties": {
    "addr:full":"Wesley Drive, Benton Square Industrial Estate Newcastle Upon Tyne Tyne and Wear NE12 9UP",
    "addr:postcode":"ne12 9up",
    "addr:street":"Wesley Drive;Industrial Estate",
    "iso:country":"GB",
    "sg:address":"Wesley Drive, Benton Square Industrial Estate",
    "sg:city":"Newcastle Upon Tyne",
    "sg:classifiers":[
        {
            "category":"Shopping",
            "subcategory":"Stationery & Office Supplies",
            "type":"Retail Goods"
        }
    ],
    "sg:phone":"+44 191 270 0200",
    "sg:postcode":"NE12 9UP",
    "sg:province":"Tyne and Wear",
    "wof:name":"Office Smart",
    "wof:placetype":"venue"
},
  "geometry": {"coordinates":[-1.5338900089,55.0247688293],"type":"Point"}
}