{
  "type": "Feature",
  "properties": {
    "iso:country":"GB",
    "sg:address":"Little Hasguard, Dale Road, Broad Haven",
    "sg:city":"Haverfordwest",
    "sg:classifiers":[
        {
            "category":"Farming",
            "subcategory":"Livestock Farm",
            "type":"Manufacturing & Wholesale Goods"
        }
    ],
    "sg:postcode":"SA62 3SN",
    "sg:province":"Pembrokeshire",
    "sg:tags":[
        "others"
    ],
    "wof:name":"W J Richards & Son",
    "wof:placetype":"venue"
},
  "geometry": {"coordinates":[-5.0981841087,51.7838287354],"type":"Point"}
}