{
  "type": "Feature",
  "properties": {
    "addr:full":"Hill Street Sheffield South Yorkshire S2 4SP",
    "addr:postcode":"s2 4sp",
    "addr:street":"Hill Street",
    "iso:country":"GB",
    "sg:address":"Hill Street",
    "sg:city":"Sheffield",
    "sg:classifiers":[
        {
            "category":"Wholesale",
            "subcategory":"Construction Materials",
            "type":"Manufacturing & Wholesale Goods"
        },
        {
            "category":"Professional",
            "subcategory":"Business Services",
            "type":"Services"
        }
    ],
    "sg:phone":"+44 114 273 1133",
    "sg:postcode":"S2 4SP",
    "sg:province":"South Yorkshire",
    "sg:tags":[
        "tile",
        "wholesaler",
        "supplier",
        "stockist"
    ],
    "wof:name":"The Yorkshire Tile Company Ltd",
    "wof:placetype":"venue"
},
  "geometry": {"coordinates":[-1.476984,53.370541],"type":"Point"}
}