{
  "type": "Feature",
  "properties": {
    "addr:full":"719 Abbeydale Rd Sheffield South Yorkshire S7 2BE",
    "addr:housenumber":"719",
    "addr:postcode":"s7 2be",
    "addr:street":"Abbeydale Rd",
    "iso:country":"GB",
    "sg:address":"719 Abbeydale Rd",
    "sg:city":"Sheffield",
    "sg:classifiers":[
        {
            "category":"Shopping",
            "subcategory":"News",
            "type":"Retail Goods"
        }
    ],
    "sg:phone":"+44 114 281 4686",
    "sg:postcode":"S7 2BE",
    "sg:province":"South Yorkshire",
    "sg:tags":[
        "newsagent"
    ],
    "wof:name":"GT News",
    "wof:placetype":"venue"
},
  "geometry": {"coordinates":[-1.485492,53.354866],"type":"Point"}
}