{
  "type": "Feature",
  "properties": {
    "iso:country":"GB",
    "sg:address":"3 Valley Drive, Withdean",
    "sg:city":"Brighton",
    "sg:classifiers":[
        {
            "category":"Personal",
            "subcategory":"Beauty Salon",
            "type":"Services"
        },
        {
            "category":"Professional",
            "subcategory":"Lawyer & Legal Services",
            "type":"Services"
        }
    ],
    "sg:phone":"+44 1273 554937",
    "sg:postcode":"BN1 5FA",
    "sg:province":"East Sussex",
    "sg:tags":[
        "unisex",
        "advice",
        "counselling",
        "hairdresser"
    ],
    "wof:name":"Grahams",
    "wof:placetype":"venue"
},
  "geometry": {"coordinates":[-0.160847,50.854156],"type":"Point"}
}