{
  "type": "Feature",
  "properties": {
    "addr:full":"32 Mill Lane Shoreham-by-sea West Sussex BN43 5AG",
    "addr:housenumber":"32",
    "addr:postcode":"bn43 5ag",
    "addr:street":"Mill Lane",
    "iso:country":"GB",
    "sg:address":"32 Mill Lane",
    "sg:city":"Shoreham-by-sea",
    "sg:classifiers":[
        {
            "category":"Health Services",
            "subcategory":"Health Practitioner",
            "type":"Services"
        }
    ],
    "sg:postcode":"BN43 5AG",
    "sg:province":"West Sussex",
    "sg:tags":[
        "osteopath"
    ],
    "wof:name":"Andrew P Bellamy",
    "wof:placetype":"venue"
},
  "geometry": {"coordinates":[-0.275547,50.837994],"type":"Point"}
}