{
  "type": "Feature",
  "properties": {
    "addr:full":"18 Church Road Stanmore Greater London HA7 4AW",
    "addr:housenumber":"18",
    "addr:postcode":"ha7 4aw",
    "addr:street":"Church Road",
    "iso:country":"GB",
    "sg:address":"18 Church Road",
    "sg:city":"Stanmore",
    "sg:classifiers":[
        {
            "category":"Professional",
            "type":"Services"
        }
    ],
    "sg:phone":"+44 1992 890600",
    "sg:postcode":"HA7 4AW",
    "sg:province":"Greater London",
    "sg:tags":[
        "interior",
        "furnishers",
        "designer"
    ],
    "wof:name":"Lester Bennett Design Associates",
    "wof:placetype":"venue"
},
  "geometry": {"coordinates":[-0.3118120134,51.6173553467],"type":"Point"}
}