{
  "type": "Feature",
  "properties": {
    "iso:country":"GB",
    "sg:address":"35 Jonathan Road",
    "sg:city":"Fareham",
    "sg:classifiers":[
        {
            "category":"Professional",
            "subcategory":"Management & Consulting",
            "type":"Services"
        }
    ],
    "sg:postcode":"PO15 5JS",
    "sg:province":"Hampshire",
    "sg:tags":[
        "consultant",
        "specialist"
    ],
    "wof:name":"Tricia for Nails",
    "wof:placetype":"venue"
},
  "geometry": {"coordinates":[-1.203581,50.854252],"type":"Point"}
}