{
  "type": "Feature",
  "properties": {
    "addr:full":"143 Woolwich Rd Greenwich Greater London SE10 0RJ",
    "addr:housenumber":"143",
    "addr:postcode":"se10 0rj",
    "addr:street":"Woolwich Rd",
    "iso:country":"GB",
    "sg:address":"143 Woolwich Rd",
    "sg:city":"Greenwich",
    "sg:classifiers":[
        {
            "category":"Retail",
            "subcategory":"Auto Repair",
            "type":"Services"
        }
    ],
    "sg:phone":"+44 20 8858 7181",
    "sg:postcode":"SE10 0RJ",
    "sg:province":"Greater London",
    "sg:tags":[
        "engine",
        "car",
        "specialist"
    ],
    "wof:name":"Engine UK Ltd",
    "wof:placetype":"venue"
},
  "geometry": {"coordinates":[0.0147479996,51.4862174988],"type":"Point"}
}