{
  "type": "Feature",
  "properties": {
    "addr:full":"22 Church Road, Stainforth Doncaster South Yorkshire DN7 5AA",
    "addr:housenumber":"22",
    "addr:postcode":"dn7 5aa",
    "addr:street":"Church Road",
    "iso:country":"GB",
    "sg:address":"22 Church Road, Stainforth",
    "sg:city":"Doncaster",
    "sg:classifiers":[
        {
            "category":"Shopping",
            "subcategory":"News",
            "type":"Retail Goods"
        }
    ],
    "sg:phone":"+44 1302 841568",
    "sg:postcode":"DN7 5AA",
    "sg:province":"South Yorkshire",
    "sg:tags":[
        "newsagent"
    ],
    "wof:name":"R & J Pratt",
    "wof:placetype":"venue"
},
  "geometry": {"coordinates":[-1.0299210548,53.594291687],"type":"Point"}
}