{
  "type": "Feature",
  "properties": {
    "addr:full":"18 Butcher Clo, Milton Cambridge Cambridgeshire CB4 6ED",
    "addr:housenumber":"18",
    "addr:postcode":"cb4 6ed",
    "addr:street":"Milton",
    "iso:country":"GB",
    "sg:address":"18 Butcher Clo, Milton",
    "sg:city":"Cambridge",
    "sg:classifiers":[
        {
            "category":"Building & Trades",
            "subcategory":"Construction",
            "type":"Services"
        },
        {
            "category":"Home & Garden",
            "subcategory":"Carpets & Floor Coverings",
            "type":"Retail Goods"
        }
    ],
    "sg:postcode":"CB4 6ED",
    "sg:province":"Cambridgeshire",
    "sg:tags":[
        "textile",
        "flooring",
        "floorcoverings"
    ],
    "wof:name":"Webb,Darren R,",
    "wof:placetype":"venue"
},
  "geometry": {"coordinates":[0.1553799957,52.245929718],"type":"Point"}
}