{
  "type": "Feature",
  "properties": {
    "iso:country":"GB",
    "sg:address":"47 Great Western Street",
    "sg:city":"Wednesbury",
    "sg:classifiers":[
        {
            "category":"Professional",
            "subcategory":"Engineering",
            "type":"Services"
        }
    ],
    "sg:phone":"+44 121 556 1636",
    "sg:postcode":"WS10 7LL",
    "sg:province":"West Midlands",
    "sg:tags":[
        "contractor",
        "electrical",
        "engineer"
    ],
    "wof:name":"D & A Accessories Ltd.",
    "wof:placetype":"venue"
},
  "geometry": {"coordinates":[-2.026753,52.549618],"type":"Point"}
}