{
  "type": "Feature",
  "properties": {
    "iso:country":"GB",
    "sg:address":"12-14 Ninian Park, Ninian Way, Willancote",
    "sg:city":"Tamworth",
    "sg:classifiers":[
        {
            "category":"Manufacturing",
            "subcategory":"Metals",
            "type":"Manufacturing & Wholesale Goods"
        },
        {
            "category":"Manufacturing",
            "subcategory":"Musical Instruments",
            "type":"Manufacturing & Wholesale Goods"
        }
    ],
    "sg:phone":"+44 1827 250000",
    "sg:postcode":"B77 5ES",
    "sg:province":"Staffordshire",
    "sg:tags":[
        "work",
        "sheet",
        "agent",
        "manufacturer"
    ],
    "wof:name":"Press & Shear Machinery Ltd",
    "wof:placetype":"venue"
},
  "geometry": {"coordinates":[-1.676449,52.60181],"type":"Point"}
}