{
  "type": "Feature",
  "properties": {
    "addr:full":"March Place, Gatehouse Way Aylesbury Buckinghamshire HP19 8UG",
    "addr:postcode":"hp19 8ug",
    "addr:street":"March Place Gatehouse Way",
    "iso:country":"GB",
    "sg:address":"March Place, Gatehouse Way",
    "sg:city":"Aylesbury",
    "sg:classifiers":[
        {
            "category":"Retail",
            "subcategory":"Auto Repair",
            "type":"Services"
        }
    ],
    "sg:phone":"+44 1296 415579",
    "sg:postcode":"HP19 8UG",
    "sg:province":"Buckinghamshire",
    "sg:tags":[
        "body",
        "car"
    ],
    "wof:name":"M R Baldwin",
    "wof:placetype":"venue"
},
  "geometry": {"coordinates":[-0.8272699714,51.8180770874],"type":"Point"}
}