{
  "type": "Feature",
  "properties": {
    "addr:full":"13 Dimmock Close Tonbridge Kent TN12 6HS",
    "addr:housenumber":"13",
    "addr:postcode":"tn12 6hs",
    "addr:street":"Dimmock Close",
    "iso:country":"GB",
    "sg:address":"13 Dimmock Close",
    "sg:city":"Tonbridge",
    "sg:classifiers":[
        {
            "category":"Retail",
            "subcategory":"Auto Repair",
            "type":"Services"
        }
    ],
    "sg:postcode":"TN12 6HS",
    "sg:province":"Kent",
    "sg:tags":[
        "modification",
        "garage"
    ],
    "wof:name":"R W Auto's Mobile Mechanic",
    "wof:placetype":"venue"
},
  "geometry": {"coordinates":[0.3966200054,51.1806106567],"type":"Point"}
}