{
  "type": "Feature",
  "properties": {
    "addr:full":"Town Farm, Petrockstow Okehampton Devon EX20 3HQ",
    "addr:postcode":"ex20 3hq",
    "iso:country":"GB",
    "sg:address":"Town Farm, Petrockstow",
    "sg:city":"Okehampton",
    "sg:classifiers":[
        {
            "category":"Shopping",
            "subcategory":"Department Store",
            "type":"Retail Goods"
        }
    ],
    "sg:postcode":"EX20 3HQ",
    "sg:province":"Devon",
    "wof:name":"Fald,Brian,",
    "wof:placetype":"venue"
},
  "geometry": {"coordinates":[-4.115314,50.865612],"type":"Point"}
}