{
  "type": "Feature",
  "properties": {
    "addr:full":"7 Walton Court Centre, Hannon Road Aylesbury Buckinghamshire HP21 7QG",
    "addr:housenumber":"7",
    "addr:postcode":"hp21 7qg",
    "addr:street":"Walton Court;Hannon Road",
    "iso:country":"GB",
    "sg:address":"7 Walton Court Centre, Hannon Road",
    "sg:city":"Aylesbury",
    "sg:classifiers":[
        {
            "category":"Shopping",
            "subcategory":"Pharmacy",
            "type":"Retail Goods"
        }
    ],
    "sg:phone":"+44 1296 429553",
    "sg:postcode":"HP21 7QG",
    "sg:province":"Buckinghamshire",
    "sg:tags":[
        "pharmacist",
        "chemist"
    ],
    "wof:name":"Moss Chemists",
    "wof:placetype":"venue"
},
  "geometry": {"coordinates":[-0.80585,51.811157],"type":"Point"}
}