{
  "type": "Feature",
  "properties": {
    "iso:country":"GB",
    "sg:address":"3 The Boulevard",
    "sg:city":"Lytham St Annes",
    "sg:classifiers":[
        {
            "category":"Education",
            "subcategory":"School",
            "type":"Public Place"
        }
    ],
    "sg:phone":"+44 1253 712380",
    "sg:postcode":"FY8 1EH",
    "sg:province":"Lancashire",
    "sg:tags":[
        "private",
        "tuition"
    ],
    "wof:name":"Wilmington Science & Maths Tuition",
    "wof:placetype":"venue"
},
  "geometry": {"coordinates":[-3.018894,53.744274],"type":"Point"}
}