{
  "type": "Feature",
  "properties": {
    "iso:country":"GB",
    "sg:address":"43 Causewayhead",
    "sg:city":"Penzance",
    "sg:classifiers":[
        {
            "category":"Shopping",
            "subcategory":"Books",
            "type":"Retail Goods"
        }
    ],
    "sg:postcode":"TR18 2SS",
    "sg:province":"Cornwall",
    "sg:tags":[
        "bookseller"
    ],
    "wof:name":"Johnstone,Patricia,",
    "wof:placetype":"venue"
},
  "geometry": {"coordinates":[-5.538819,50.12038],"type":"Point"}
}