{
  "type": "Feature",
  "properties": {
    "addr:full":"102 Stewart Street Crewe Cheshire CW2 8LX",
    "addr:housenumber":"102",
    "addr:postcode":"cw2 8lx",
    "addr:street":"Stewart Street",
    "iso:country":"GB",
    "sg:address":"102 Stewart Street",
    "sg:city":"Crewe",
    "sg:classifiers":[
        {
            "category":"Professional",
            "type":"Services"
        },
        {
            "category":"Fast Food",
            "type":"Food & Drink"
        }
    ],
    "sg:phone":"+44 1270 661400",
    "sg:postcode":"CW2 8LX",
    "sg:province":"Cheshire",
    "sg:tags":[
        "away",
        "take",
        "caterer"
    ],
    "wof:name":"Wistaston Caterers",
    "wof:placetype":"venue"
},
  "geometry": {"coordinates":[-2.457368,53.092991],"type":"Point"}
}