{
  "type": "Feature",
  "properties": {
    "iso:country":"GB",
    "sg:address":"26 North Street",
    "sg:city":"Derby",
    "sg:classifiers":[
        {
            "category":"Health Services",
            "subcategory":"Doctor",
            "type":"Services"
        }
    ],
    "sg:postcode":"DE1 3AZ",
    "sg:province":"Derbyshire",
    "sg:tags":[
        "practitioners"
    ],
    "wof:name":"Derwent Medical Centre",
    "wof:placetype":"venue"
},
  "geometry": {"coordinates":[-1.4795470238,52.9293861389],"type":"Point"}
}