{
  "type": "Feature",
  "properties": {
    "iso:country":"GB",
    "sg:address":"Westfield Road",
    "sg:city":"Retford",
    "sg:classifiers":[
        {
            "category":"Health Services",
            "subcategory":"Nursing And Care Facility",
            "type":"Services"
        }
    ],
    "sg:phone":"+44 1777 701636",
    "sg:postcode":"DN22 7BT",
    "sg:province":"Nottinghamshire",
    "sg:tags":[
        "home"
    ],
    "wof:name":"West Villa Nursing Home",
    "wof:placetype":"venue"
},
  "geometry": {"coordinates":[-0.9524809718,53.3190460205],"type":"Point"}
}