{
  "type": "Feature",
  "properties": {
    "addr:full":"16a Queens Road Coventry West Midlands CV1 3EG",
    "addr:housenumber":"16a",
    "addr:postcode":"cv1 3eg",
    "addr:street":"Queens Road",
    "iso:country":"GB",
    "sg:address":"16a Queens Road",
    "sg:city":"Coventry",
    "sg:classifiers":[
        {
            "category":"Professional",
            "subcategory":"Employment Agencies",
            "type":"Services"
        }
    ],
    "sg:phone":"+44 24 7655 9944",
    "sg:postcode":"CV1 3EG",
    "sg:province":"West Midlands",
    "sg:tags":[
        "consultant",
        "recruitment"
    ],
    "wof:name":"Acorn Accountancy Select",
    "wof:placetype":"venue"
},
  "geometry": {"coordinates":[-1.517719,52.404324],"type":"Point"}
}