{
  "type": "Feature",
  "properties": {
    "addr:full":"26 West Cliff Dawlish Devon EX7 9DN",
    "addr:housenumber":"26",
    "addr:postcode":"ex7 9dn",
    "addr:street":"West Cliff",
    "iso:country":"GB",
    "sg:address":"26 West Cliff",
    "sg:city":"Dawlish",
    "sg:classifiers":[
        {
            "category":"Social Services",
            "subcategory":"Retirement Home",
            "type":"Services"
        }
    ],
    "sg:phone":"+44 1626 862260",
    "sg:postcode":"EX7 9DN",
    "sg:province":"Devon",
    "sg:tags":[
        "residential",
        "care"
    ],
    "wof:name":"Sidborough House",
    "wof:placetype":"venue"
},
  "geometry": {"coordinates":[-3.4666590691,50.5795936584],"type":"Point"}
}