{
  "type": "Feature",
  "properties": {
    "iso:country":"GB",
    "sg:address":"4 Church Street, Bishops Lydeard",
    "sg:city":"Taunton",
    "sg:classifiers":[
        {
            "category":"Food & Beverages",
            "subcategory":"Groceries & Convenience Stores",
            "type":"Retail Goods"
        }
    ],
    "sg:phone":"+44 1823 432259",
    "sg:postcode":"TA4 3AT",
    "sg:province":"Devon",
    "wof:name":"Quantock Stores",
    "wof:placetype":"venue"
},
  "geometry": {"coordinates":[-3.255699,51.047707],"type":"Point"}
}