{
  "type": "Feature",
  "properties": {
    "addr:full":"Bedford House, 215 Balham High Road London Greater London SW17 7BQ",
    "addr:housenumber":"215",
    "addr:postcode":"sw17 7bq",
    "addr:street":"Balham High Road",
    "iso:country":"GB",
    "sg:address":"Bedford House, 215 Balham High Road",
    "sg:city":"London",
    "sg:classifiers":[
        {
            "category":"Organizations",
            "subcategory":"Non-profit Organization",
            "type":"Services"
        }
    ],
    "sg:phone":"+44 20 8333 6960",
    "sg:postcode":"SW17 7BQ",
    "sg:province":"Greater London",
    "sg:tags":[
        "organisation",
        "voluntary",
        "charity"
    ],
    "wof:name":"Hemihelp",
    "wof:placetype":"venue"
},
  "geometry": {"coordinates":[-0.1552429944,51.4409561157],"type":"Point"}
}