{
  "type": "Feature",
  "properties": {
    "addr:full":"624a Ripponden Road Oldham Lancashire OL4 2LN",
    "addr:housenumber":"624a",
    "addr:postcode":"ol4 2ln",
    "addr:street":"Ripponden Road",
    "iso:country":"GB",
    "sg:address":"624a Ripponden Road",
    "sg:city":"Oldham",
    "sg:classifiers":[
        {
            "category":"Food & Beverages",
            "subcategory":"Meat & Fish",
            "type":"Retail Goods"
        }
    ],
    "sg:postcode":"OL4 2LN",
    "sg:province":"Lancashire",
    "sg:tags":[
        "butcher"
    ],
    "wof:name":"Cavendish Butchers",
    "wof:placetype":"venue"
},
  "geometry": {"coordinates":[-2.072719,53.565189],"type":"Point"}
}