{
  "type": "Feature",
  "properties": {
    "iso:country":"GB",
    "sg:address":"18 Beechwood Road",
    "sg:city":"Rhyl",
    "sg:classifiers":[
        {
            "category":"Travel",
            "subcategory":"Hotels & Motels",
            "type":"Entertainment"
        },
        {
            "category":"Bars & Pubs",
            "subcategory":"Hookah Bar",
            "type":"Food & Drink"
        }
    ],
    "sg:phone":"+44 1745 353291",
    "sg:postcode":"LL18 3EU",
    "sg:province":"Conwy",
    "sg:tags":[
        "self",
        "holiday",
        "catering"
    ],
    "wof:name":"GLYRON HOUSE",
    "wof:placetype":"venue"
},
  "geometry": {"coordinates":[-3.481918,53.325336],"type":"Point"}
}