{
  "type": "Feature",
  "properties": {
    "iso:country":"GB",
    "sg:address":"26 Turton Road, Yarm",
    "sg:city":"Stockton-on-tees",
    "sg:classifiers":[
        {
            "category":"Shopping",
            "subcategory":"News",
            "type":"Retail Goods"
        }
    ],
    "sg:postcode":"TS15 9DL",
    "sg:province":"North Yorkshire",
    "sg:tags":[
        "newsagent"
    ],
    "wof:name":"Kandola News",
    "wof:placetype":"venue"
},
  "geometry": {"coordinates":[-1.3595030308,54.499080658],"type":"Point"}
}