{
  "type": "Feature",
  "properties": {
    "addr:full":"Finch Grn, Chiddingstone Hoath Edenbridge East Sussex TN8 7DJ",
    "addr:postcode":"tn8 7dj",
    "addr:street":"Finch Grn",
    "iso:country":"GB",
    "sg:address":"Finch Grn, Chiddingstone Hoath",
    "sg:city":"Edenbridge",
    "sg:classifiers":[
        {
            "category":"Real Estate",
            "subcategory":"Surveying",
            "type":"Services"
        }
    ],
    "sg:phone":"+44 1892 871299",
    "sg:postcode":"TN8 7DJ",
    "sg:province":"East Sussex",
    "sg:tags":[
        "surveyor",
        "valuer"
    ],
    "wof:name":"Thorp Consultancy Chartered Quantity Surveyors",
    "wof:placetype":"venue"
},
  "geometry": {"coordinates":[0.141365,51.188419],"type":"Point"}
}