{
  "type": "Feature",
  "properties": {
    "iso:country":"GB",
    "sg:address":"22 Doncaster Rd, Carlton-in-lindrick",
    "sg:city":"Worksop",
    "sg:classifiers":[
        {
            "category":"Building & Trades",
            "subcategory":"Construction",
            "type":"Services"
        }
    ],
    "sg:phone":"+44 1909 730796",
    "sg:postcode":"S81 9JU",
    "sg:province":"Nottinghamshire",
    "sg:tags":[
        "glazier",
        "decorator",
        "painter"
    ],
    "wof:name":"Bailey,Brian,",
    "wof:placetype":"venue"
},
  "geometry": {"coordinates":[-1.113504,53.358273],"type":"Point"}
}