{
  "type": "Feature",
  "properties": {
    "addr:full":"7 Morrison St Edinburgh City of Edinburgh EH3 8BH",
    "addr:housenumber":"7",
    "addr:postcode":"eh3 8bh",
    "addr:street":"Morrison St Edinburgh",
    "iso:country":"GB",
    "sg:address":"7 Morrison St",
    "sg:city":"Edinburgh",
    "sg:classifiers":[
        {
            "category":"Shopping",
            "subcategory":"Music",
            "type":"Retail Goods"
        }
    ],
    "sg:phone":"+44 131 229 9696",
    "sg:postcode":"EH3 8BH",
    "sg:province":"City of Edinburgh",
    "sg:tags":[
        "record",
        "tape",
        "cd"
    ],
    "wof:name":"Sweet Inspiration Discos",
    "wof:placetype":"venue"
},
  "geometry": {"coordinates":[-3.206799,55.94566],"type":"Point"}
}