{
  "type": "Feature",
  "properties": {
    "addr:full":"102 Greenhill Rise Corby Northamptonshire NN18 0LR",
    "addr:housenumber":"102",
    "addr:postcode":"nn18 0lr",
    "addr:street":"Greenhill Rise",
    "iso:country":"GB",
    "sg:address":"102 Greenhill Rise",
    "sg:city":"Corby",
    "sg:classifiers":[
        {
            "category":"Retail",
            "subcategory":"Repair Shop",
            "type":"Services"
        }
    ],
    "sg:phone":"+44 1536 201697",
    "sg:postcode":"NN18 0LR",
    "sg:province":"Northamptonshire",
    "sg:tags":[
        "radio",
        "television",
        "video"
    ],
    "wof:name":"Sound & Vision Services",
    "wof:placetype":"venue"
},
  "geometry": {"coordinates":[-0.7234190106,52.4822845459],"type":"Point"}
}