{
  "type": "Feature",
  "properties": {
    "addr:full":"Thistle Close, Hanley Swan Worcester Gloucestershire WR8 0EQ",
    "addr:postcode":"wr8 0eq",
    "addr:street":"Thistle Close",
    "iso:country":"GB",
    "sg:address":"Thistle Close, Hanley Swan",
    "sg:city":"Worcester",
    "sg:classifiers":[
        {
            "category":"Professional",
            "subcategory":"Art Services",
            "type":"Services"
        }
    ],
    "sg:postcode":"WR8 0EQ",
    "sg:province":"Gloucestershire",
    "sg:tags":[
        "photographer"
    ],
    "wof:name":"Dennis Stone Photography",
    "wof:placetype":"venue"
},
  "geometry": {"coordinates":[-2.2735788822,52.0839118958],"type":"Point"}
}