{
  "type": "Feature",
  "properties": {
    "addr:full":"336b Ladbroke Gro Ladbroke Grove Greater London W10 6HA",
    "addr:housenumber":"336b",
    "addr:postcode":"w10 6ha",
    "addr:street":"Ladbroke Gro Ladbroke Grove",
    "iso:country":"GB",
    "sg:address":"336b Ladbroke Gro",
    "sg:city":"Ladbroke Grove",
    "sg:classifiers":[
        {
            "category":"Professional",
            "subcategory":"Business Services",
            "type":"Services"
        }
    ],
    "sg:phone":"+44 20 8964 0666",
    "sg:postcode":"W10 6HA",
    "sg:province":"Greater London",
    "sg:tags":[
        "distribution"
    ],
    "wof:name":"W A Ingram Associates Ltd",
    "wof:placetype":"venue"
},
  "geometry": {"coordinates":[-0.213729,51.523769],"type":"Point"}
}