{
  "type": "Feature",
  "properties": {
    "addr:full":"5 The Ropewalk Neath Neath Port Talbot SA11 1EW",
    "addr:housenumber":"5",
    "addr:postcode":"sa11 1ew",
    "addr:street":"The Ropewalk",
    "iso:country":"GB",
    "sg:address":"5 The Ropewalk",
    "sg:city":"Neath",
    "sg:classifiers":[
        {
            "category":"Communications",
            "subcategory":"Newspaper",
            "type":"Services"
        },
        {
            "category":"Shopping",
            "subcategory":"Books",
            "type":"Retail Goods"
        }
    ],
    "sg:postcode":"SA11 1EW",
    "sg:province":"Neath Port Talbot",
    "sg:tags":[
        "magazine"
    ],
    "wof:name":"South West Wales Publications Ltd.",
    "wof:placetype":"venue"
},
  "geometry": {"coordinates":[-3.805093,51.660439],"type":"Point"}
}