{
  "type": "Feature",
  "properties": {
    "addr:full":"Preston Road Linlithgow Falkirk EH49 6EU",
    "addr:postcode":"eh49 6eu",
    "addr:street":"Preston Road",
    "iso:country":"GB",
    "sg:address":"Preston Road",
    "sg:city":"Linlithgow",
    "sg:classifiers":[
        {
            "category":"Professional",
            "subcategory":"Engineering",
            "type":"Services"
        },
        {
            "category":"Transit Center",
            "subcategory":"Freight",
            "type":"Transportation"
        },
        {
            "category":"Manufacturing",
            "subcategory":"Electronics",
            "type":"Manufacturing & Wholesale Goods"
        },
        {
            "category":"Communications",
            "subcategory":"Television Station",
            "type":"Services"
        }
    ],
    "sg:phone":"+44 131 476 8817",
    "sg:postcode":"EH49 6EU",
    "sg:province":"Falkirk",
    "sg:tags":[
        "mnfr",
        "radar",
        "component",
        "equipment",
        "video",
        "electronic",
        "engineer"
    ],
    "wof:name":"Racal Radar Defence Systems",
    "wof:placetype":"venue"
},
  "geometry": {"coordinates":[-3.610889,55.974541],"type":"Point"}
}