{
  "type": "Feature",
  "properties": {
    "iso:country":"GB",
    "sg:address":"Forest Rd",
    "sg:city":"Northwich",
    "sg:classifiers":[
        {
            "category":"Banks & Credit Unions",
            "subcategory":"Bank",
            "type":"Services"
        }
    ],
    "sg:phone":"+44 1606 889641",
    "sg:postcode":"CW8 2ED",
    "sg:province":"Cheshire",
    "sg:tags":[
        "broker",
        "mortgage"
    ],
    "wof:name":"A I B M",
    "wof:placetype":"venue"
},
  "geometry": {"coordinates":[-2.6053779125,53.2346115112],"type":"Point"}
}