{
  "type": "Feature",
  "properties": {
    "addr:full":"High Quality Lifestyle Wolverton, Court Dover Kent CT15 7DS",
    "addr:postcode":"ct15 7ds",
    "addr:street":"Wolverton Court",
    "iso:country":"GB",
    "sg:address":"High Quality Lifestyle Wolverton, Court",
    "sg:city":"Dover",
    "sg:classifiers":[
        {
            "category":"Health Services",
            "subcategory":"Health Practitioner",
            "type":"Services"
        }
    ],
    "sg:phone":"+44 1304 825544",
    "sg:postcode":"CT15 7DS",
    "sg:province":"Kent",
    "sg:tags":[
        "psychologist"
    ],
    "wof:name":"Wolverton Court",
    "wof:placetype":"venue"
},
  "geometry": {"coordinates":[1.21877,51.148659],"type":"Point"}
}