{
  "type": "Feature",
  "properties": {
    "iso:country":"GB",
    "sg:address":"C/o M R Shah & Co",
    "sg:city":"Harrow",
    "sg:classifiers":[
        {
            "category":"Professional",
            "subcategory":"Accounting & Tax Preparation",
            "type":"Services"
        }
    ],
    "sg:phone":"+44 20 8909 2266",
    "sg:postcode":"HA3 8RP",
    "sg:province":"Greater London",
    "sg:tags":[
        "accountant"
    ],
    "wof:name":"Residential Property Maintenance Ltd.",
    "wof:placetype":"venue"
},
  "geometry": {"coordinates":[-0.31268,51.59584],"type":"Point"}
}