{
  "type": "Feature",
  "properties": {
    "addr:full":"Unit 3 Old Magpie Works, Station App, Four Marks Alton Hampshire GU34 5HN",
    "addr:housenumber":"unit 3",
    "addr:postcode":"gu34 5hn",
    "addr:street":"Old",
    "iso:country":"GB",
    "sg:address":"Unit 3 Old Magpie Works, Station App, Four Marks",
    "sg:city":"Alton",
    "sg:classifiers":[
        {
            "category":"Brewery",
            "type":"Food & Drink"
        }
    ],
    "sg:phone":"+44 1420 561422",
    "sg:postcode":"GU34 5HN",
    "sg:province":"Hampshire",
    "sg:tags":[
        "brewer"
    ],
    "wof:name":"Triple F F F Brewing Co.",
    "wof:placetype":"venue"
},
  "geometry": {"coordinates":[-1.041864,51.112995],"type":"Point"}
}