{
  "type": "Feature",
  "properties": {
    "addr:full":"39-41 South Promenade Lytham St Annes Lancashire FY8 1LS",
    "addr:housenumber":"39-41",
    "addr:postcode":"fy8 1ls",
    "addr:street":"South Promenade;St",
    "iso:country":"GB",
    "sg:address":"39-41 South Promenade",
    "sg:city":"Lytham St Annes",
    "sg:classifiers":[
        {
            "category":"Social Services",
            "subcategory":"Retirement Home",
            "type":"Services"
        }
    ],
    "sg:phone":"+44 1253 721356",
    "sg:postcode":"FY8 1LS",
    "sg:province":"Lancashire",
    "sg:tags":[
        "rest"
    ],
    "wof:name":"The Grove Rest Home",
    "wof:placetype":"venue"
},
  "geometry": {"coordinates":[-3.0310590267,53.7474784851],"type":"Point"}
}