{
  "type": "Feature",
  "properties": {
    "iso:country":"GB",
    "sg:address":"2 Ashmount Cotts, Swing Gate Lane",
    "sg:city":"Berkhamsted",
    "sg:classifiers":[
        {
            "category":"Building & Trades",
            "subcategory":"Construction",
            "type":"Services"
        }
    ],
    "sg:phone":"+44 1442 876286",
    "sg:postcode":"HP4 2LL",
    "sg:province":"Bedfordshire",
    "sg:tags":[
        "contractor"
    ],
    "wof:name":"Q T Constructions Ltd",
    "wof:placetype":"venue"
},
  "geometry": {"coordinates":[-0.564559,51.760414],"type":"Point"}
}