{
  "type": "Feature",
  "properties": {
    "iso:country":"GB",
    "sg:address":"43 Leasowe Road",
    "sg:city":"Wallasey",
    "sg:classifiers":[
        {
            "category":"Shopping",
            "subcategory":"News",
            "type":"Retail Goods"
        }
    ],
    "sg:postcode":"CH45 8NY",
    "sg:province":"Merseyside",
    "sg:tags":[
        "newsagent"
    ],
    "wof:name":"B J News",
    "wof:placetype":"venue"
},
  "geometry": {"coordinates":[-3.067729,53.422741],"type":"Point"}
}