{
  "type": "Feature",
  "properties": {
    "addr:full":"Unit 15 London Greater London N1 7BS",
    "addr:housenumber":"unit 15",
    "addr:postcode":"n1 7bs",
    "iso:country":"GB",
    "sg:address":"Unit 15",
    "sg:city":"London",
    "sg:classifiers":[
        {
            "category":"Professional",
            "subcategory":"Art Services",
            "type":"Services"
        }
    ],
    "sg:phone":"+44 20 7354 3934",
    "sg:postcode":"N1 7BS",
    "sg:province":"Greater London",
    "sg:tags":[
        "photographer"
    ],
    "wof:name":"Chris King Photography Ltd.",
    "wof:placetype":"venue"
},
  "geometry": {"coordinates":[-0.0919540003,51.536655426],"type":"Point"}
}