{
  "type": "Feature",
  "properties": {
    "addr:full":"Cartford Hotel, Cartford Lane, Little Eccleston Preston Lancashire PR3 0YP",
    "addr:postcode":"pr3 0yp",
    "addr:street":"Cartford Lane",
    "iso:country":"GB",
    "sg:address":"Cartford Hotel, Cartford Lane, Little Eccleston",
    "sg:city":"Preston",
    "sg:classifiers":[
        {
            "category":"Brewery",
            "type":"Food & Drink"
        }
    ],
    "sg:phone":"+44 1995 671686",
    "sg:postcode":"PR3 0YP",
    "sg:province":"Lancashire",
    "sg:tags":[
        "brewer"
    ],
    "wof:name":"Hart Brewery",
    "wof:placetype":"venue"
},
  "geometry": {"coordinates":[-2.882179,53.858295],"type":"Point"}
}