{
  "type": "Feature",
  "properties": {
    "iso:country":"GB",
    "sg:address":"29 Somerset Clo",
    "sg:city":"Shepton Mallet",
    "sg:classifiers":[
        {
            "category":"Building & Trades",
            "subcategory":"Construction",
            "type":"Services"
        }
    ],
    "sg:phone":"+44 1749 345194",
    "sg:postcode":"BA4 5QL",
    "sg:province":"Somerset",
    "sg:tags":[
        "joiner",
        "carpenter"
    ],
    "wof:name":"J Tully",
    "wof:placetype":"venue"
},
  "geometry": {"coordinates":[-2.538437,51.186577],"type":"Point"}
}