{
  "type": "Feature",
  "properties": {
    "addr:full":"Edmund Street Rochdale Lancashire OL12 6QG",
    "addr:postcode":"ol12 6qg",
    "addr:street":"Edmund Street",
    "iso:country":"GB",
    "sg:address":"Edmund Street",
    "sg:city":"Rochdale",
    "sg:classifiers":[
        {
            "category":"Education",
            "subcategory":"School",
            "type":"Public Place"
        },
        {
            "category":"Government",
            "subcategory":"Office",
            "type":"Public Place"
        }
    ],
    "sg:phone":"+44 1706 648198",
    "sg:postcode":"OL12 6QG",
    "sg:province":"Lancashire",
    "sg:tags":[
        "local",
        "authority"
    ],
    "wof:name":"Spotland County Primary School",
    "wof:placetype":"venue"
},
  "geometry": {"coordinates":[-2.1726400852,53.6216011047],"type":"Point"}
}