{
  "type": "Feature",
  "properties": {
    "addr:full":"10 Abbey Road Enfield Greater London EN1 2QL",
    "addr:housenumber":"10",
    "addr:postcode":"en1 2ql",
    "addr:street":"Abbey Road",
    "iso:country":"GB",
    "sg:address":"10 Abbey Road",
    "sg:city":"Enfield",
    "sg:classifiers":[
        {
            "category":"Professional",
            "subcategory":"Management & Consulting",
            "type":"Services"
        }
    ],
    "sg:phone":"+44 7836 286593",
    "sg:postcode":"EN1 2QL",
    "sg:province":"Greater London",
    "sg:tags":[
        "consultant",
        "business"
    ],
    "wof:name":"The Project Partnership",
    "wof:placetype":"venue"
},
  "geometry": {"coordinates":[-0.0733560026,51.645690918],"type":"Point"}
}