{
  "type": "Feature",
  "properties": {
    "iso:country":"GB",
    "sg:address":"48 Mount Street",
    "sg:city":"London",
    "sg:classifiers":[
        {
            "category":"Professional",
            "subcategory":"Business Services",
            "type":"Services"
        }
    ],
    "sg:phone":"+44 20 7629 8367",
    "sg:postcode":"W1K 2SB",
    "sg:province":"Greater London",
    "sg:tags":[
        "broker",
        "commodity"
    ],
    "wof:name":"Rafsanjan Pistachio Producers Co-Op",
    "wof:placetype":"venue"
},
  "geometry": {"coordinates":[-0.153535,51.509331],"type":"Point"}
}