{
  "type": "Feature",
  "properties": {
    "addr:full":"12 High Street Ludlow Herefordshire SY8 1BS",
    "addr:housenumber":"12",
    "addr:postcode":"sy8 1bs",
    "addr:street":"High Street",
    "iso:country":"GB",
    "sg:address":"12 High Street",
    "sg:city":"Ludlow",
    "sg:classifiers":[
        {
            "category":"Fast Food",
            "type":"Food & Drink"
        }
    ],
    "sg:phone":"+44 1584 877686",
    "sg:postcode":"SY8 1BS",
    "sg:province":"Herefordshire",
    "sg:tags":[
        "away",
        "take"
    ],
    "wof:name":"Ludlow Kebab House",
    "wof:placetype":"venue"
},
  "geometry": {"coordinates":[-2.719520092,52.3674468994],"type":"Point"}
}