{
  "type": "Feature",
  "properties": {
    "addr:full":"1a Green Lane, Burnham Slough Berkshire SL1 8BZ",
    "addr:housenumber":"1a",
    "addr:postcode":"sl1 8bz",
    "addr:street":"Green Lane",
    "iso:country":"GB",
    "sg:address":"1a Green Lane, Burnham",
    "sg:city":"Slough",
    "sg:classifiers":[
        {
            "category":"Professional",
            "subcategory":"Engineering",
            "type":"Services"
        }
    ],
    "sg:postcode":"SL1 8BZ",
    "sg:province":"Berkshire",
    "sg:tags":[
        "contractor",
        "electrical",
        "engineer"
    ],
    "wof:name":"Burnham Electrical Contracting Ltd.",
    "wof:placetype":"venue"
},
  "geometry": {"coordinates":[-0.654073,51.5343132019],"type":"Point"}
}