{
  "type": "Feature",
  "properties": {
    "addr:full":"Ridgeway Rd Sheffield Derbyshire S12 2SS",
    "addr:postcode":"s12 2ss",
    "addr:street":"Ridgeway Rd",
    "iso:country":"GB",
    "sg:address":"Ridgeway Rd",
    "sg:city":"Sheffield",
    "sg:classifiers":[
        {
            "category":"Health Services",
            "subcategory":"Clinic",
            "type":"Services"
        }
    ],
    "sg:phone":"+44 114 239 7119",
    "sg:postcode":"S12 2SS",
    "sg:province":"Derbyshire",
    "sg:tags":[
        "nh"
    ],
    "wof:name":"Manor Top Medical Centre",
    "wof:placetype":"venue"
},
  "geometry": {"coordinates":[-1.426017046,53.3549003601],"type":"Point"}
}