{
  "type": "Feature",
  "properties": {
    "addr:full":"7a Station Road Biggleswade Bedfordshire SG18 8AL",
    "addr:housenumber":"7a",
    "addr:postcode":"sg18 8al",
    "addr:street":"Station Road",
    "iso:country":"GB",
    "sg:address":"7a Station Road",
    "sg:city":"Biggleswade",
    "sg:classifiers":[
        {
            "category":"Place Of Worship",
            "type":"Public Place"
        }
    ],
    "sg:phone":"+44 1767 312013",
    "sg:postcode":"SG18 8AL",
    "sg:province":"Bedfordshire",
    "wof:name":"St.Peters Catholic Church",
    "wof:placetype":"venue"
},
  "geometry": {"coordinates":[-0.2615709901,52.084236145],"type":"Point"}
}