{
  "type": "Feature",
  "properties": {
    "addr:full":"Upcott Farm, Brushford Dulverton Devon TA22 9RS",
    "addr:postcode":"ta22 9rs",
    "iso:country":"GB",
    "sg:address":"Upcott Farm, Brushford",
    "sg:city":"Dulverton",
    "sg:classifiers":[
        {
            "category":"Professional",
            "subcategory":"Management & Consulting",
            "type":"Services"
        },
        {
            "category":"Organizations",
            "subcategory":"Community Association",
            "type":"Services"
        }
    ],
    "sg:phone":"+44 1398 323997",
    "sg:postcode":"TA22 9RS",
    "sg:province":"Devon",
    "sg:tags":[
        "consultant",
        "relation",
        "public"
    ],
    "wof:name":"Hindsight Public Relations",
    "wof:placetype":"venue"
},
  "geometry": {"coordinates":[-3.5504629612,51.0399169922],"type":"Point"}
}