{
  "type": "Feature",
  "properties": {
    "addr:full":"28 Kingsley Park Terrace Northampton Northamptonshire NN2 7HG",
    "addr:housenumber":"28",
    "addr:postcode":"nn2 7hg",
    "addr:street":"Kingsley Park Terrace",
    "iso:country":"GB",
    "sg:address":"28 Kingsley Park Terrace",
    "sg:city":"Northampton",
    "sg:classifiers":[
        {
            "category":"Food & Beverages",
            "subcategory":"Groceries & Convenience Stores",
            "type":"Retail Goods"
        }
    ],
    "sg:phone":"+44 1604 791072",
    "sg:postcode":"NN2 7HG",
    "sg:province":"Northamptonshire",
    "wof:name":"Alldays",
    "wof:placetype":"venue"
},
  "geometry": {"coordinates":[-0.8780339956,52.2522315979],"type":"Point"}
}