{
  "type": "Feature",
  "properties": {
    "addr:full":"Enterprise Centre, Hanson Lane Halifax West Yorkshire HX1 5PG",
    "addr:postcode":"hx1 5pg",
    "addr:street":"Hanson Lane",
    "iso:country":"GB",
    "sg:address":"Enterprise Centre, Hanson Lane",
    "sg:city":"Halifax",
    "sg:classifiers":[
        {
            "category":"Government",
            "subcategory":"Office",
            "type":"Public Place"
        }
    ],
    "sg:phone":"+44 1422 362120",
    "sg:postcode":"HX1 5PG",
    "sg:province":"West Yorkshire",
    "sg:tags":[
        "education",
        "agency",
        "authority"
    ],
    "wof:name":"New Life Day Nursery",
    "wof:placetype":"venue"
},
  "geometry": {"coordinates":[-1.862224,53.721233],"type":"Point"}
}