{
  "type": "Feature",
  "properties": {
    "iso:country":"GB",
    "sg:address":"Unit 3, Leycroft Road, Barrington Industrial Estate",
    "sg:city":"Leicester",
    "sg:classifiers":[
        {
            "category":"Professional",
            "subcategory":"Printing & Photocopies",
            "type":"Services"
        }
    ],
    "sg:phone":"+44 116 233 4909",
    "sg:postcode":"LE4 1ET",
    "sg:province":"Leicestershire",
    "sg:tags":[
        "printer"
    ],
    "wof:name":"Quality Dot Proofing Studio",
    "wof:placetype":"venue"
},
  "geometry": {"coordinates":[-1.161419034,52.6721458435],"type":"Point"}
}