{
  "type": "Feature",
  "properties": {
    "iso:country":"GB",
    "sg:address":"16-18 High Street",
    "sg:city":"Brecon",
    "sg:classifiers":[
        {
            "category":"Shopping",
            "subcategory":"Clothing, Apparel, & Fashions",
            "type":"Retail Goods"
        }
    ],
    "sg:phone":"+44 1874 624278",
    "sg:postcode":"LD3 7AL",
    "sg:province":"Powys",
    "sg:tags":[
        "shop"
    ],
    "wof:name":"Richleys",
    "wof:placetype":"venue"
},
  "geometry": {"coordinates":[-3.391147,51.947811],"type":"Point"}
}