{
  "type": "Feature",
  "properties": {
    "iso:country":"GB",
    "sg:address":"Ratcliffe Lane",
    "sg:city":"London",
    "sg:classifiers":[
        {
            "category":"Retail",
            "subcategory":"Auto Repair",
            "type":"Services"
        }
    ],
    "sg:phone":"+44 20 7790 0822",
    "sg:postcode":"E14 7JE",
    "sg:province":"Greater London",
    "sg:tags":[
        "modification",
        "garage",
        "related"
    ],
    "wof:name":"Swift Motors",
    "wof:placetype":"venue"
},
  "geometry": {"coordinates":[-0.039119,51.51215],"type":"Point"}
}