{
  "type": "Feature",
  "properties": {
    "addr:full":"Suite 7 Coach House Cloisters, Hitchin Street Baldock Bedfordshire SG7 6AE",
    "addr:housenumber":"suite 7",
    "addr:postcode":"sg7 6ae",
    "addr:street":"Coach;Cloisters Hitchin Street",
    "iso:country":"GB",
    "sg:address":"Suite 7 Coach House Cloisters, Hitchin Street",
    "sg:city":"Baldock",
    "sg:classifiers":[
        {
            "category":"Insurance",
            "subcategory":"Insurance Agent",
            "type":"Services"
        }
    ],
    "sg:phone":"+44 1462 894999",
    "sg:postcode":"SG7 6AE",
    "sg:province":"Bedfordshire",
    "wof:name":"Thatched Owners Insurance Services Ltd.",
    "wof:placetype":"venue"
},
  "geometry": {"coordinates":[-0.187854,51.98877],"type":"Point"}
}