{
  "type": "Feature",
  "properties": {
    "addr:full":"Grays Farm Production Village Orpington Kent BR5 3BD",
    "addr:postcode":"br5 3bd",
    "addr:street":"Grays;Production Village",
    "iso:country":"GB",
    "sg:address":"Grays Farm Production Village",
    "sg:city":"Orpington",
    "sg:classifiers":[
        {
            "category":"Professional",
            "subcategory":"Art Services",
            "type":"Services"
        }
    ],
    "sg:phone":"+44 20 8300 8493",
    "sg:postcode":"BR5 3BD",
    "sg:province":"Kent",
    "sg:tags":[
        "photographer"
    ],
    "wof:name":"Bassano Studios",
    "wof:placetype":"venue"
},
  "geometry": {"coordinates":[0.111442,51.408066],"type":"Point"}
}