{
  "type": "Feature",
  "properties": {
    "iso:country":"GB",
    "sg:address":"54a Frogmore Street",
    "sg:city":"Abergavenny",
    "sg:classifiers":[
        {
            "category":"Shopping",
            "subcategory":"Mobile Phones",
            "type":"Retail Goods"
        }
    ],
    "sg:postcode":"NP7 5AR",
    "sg:province":"Herefordshire",
    "sg:tags":[
        "personal",
        "-",
        "number"
    ],
    "wof:name":"Interkal",
    "wof:placetype":"venue"
},
  "geometry": {"coordinates":[-3.020269,51.823841],"type":"Point"}
}