{
  "type": "Feature",
  "properties": {
    "addr:full":"Unit 1 Victory Close Wimborne Dorset BH21 6SX",
    "addr:housenumber":"unit 1",
    "addr:postcode":"bh21 6sx",
    "addr:street":"Victory Close",
    "iso:country":"GB",
    "sg:address":"Unit 1 Victory Close",
    "sg:city":"Wimborne",
    "sg:classifiers":[
        {
            "category":"Autos & Motor Vehicles",
            "subcategory":"Motorcycle Sales",
            "type":"Retail Goods"
        }
    ],
    "sg:postcode":"BH21 6SX",
    "sg:province":"Dorset",
    "wof:name":"Geds Motorcycle Services",
    "wof:placetype":"venue"
},
  "geometry": {"coordinates":[-1.8639390469,50.8433609009],"type":"Point"}
}