{
  "type": "Feature",
  "properties": {
    "addr:full":"Manor Walks Shopping Centre, Kiosk 3 Cramlington Northumberland NE23 6QW",
    "addr:housenumber":"3",
    "addr:postcode":"ne23 6qw",
    "addr:street":"Northumberland",
    "iso:country":"GB",
    "sg:address":"Manor Walks Shopping Centre, Kiosk 3",
    "sg:city":"Cramlington",
    "sg:classifiers":[
        {
            "category":"Shopping",
            "subcategory":"Florist",
            "type":"Retail Goods"
        }
    ],
    "sg:phone":"+44 1670 733449",
    "sg:postcode":"NE23 6QW",
    "sg:province":"Northumberland",
    "wof:name":"Acorn Flowers",
    "wof:placetype":"venue"
},
  "geometry": {"coordinates":[-1.564857,55.078117],"type":"Point"}
}