{
  "type": "Feature",
  "properties": {
    "addr:full":"179 Park Lane, Poynton Stockport Cheshire SK12 1RH",
    "addr:housenumber":"179",
    "addr:postcode":"sk12 1rh",
    "addr:street":"Park Lane",
    "iso:country":"GB",
    "sg:address":"179 Park Lane, Poynton",
    "sg:city":"Stockport",
    "sg:classifiers":[
        {
            "category":"Shopping",
            "subcategory":"Stationery & Office Supplies",
            "type":"Retail Goods"
        },
        {
            "category":"Professional",
            "subcategory":"Printing & Photocopies",
            "type":"Services"
        }
    ],
    "sg:phone":"+44 1625 858687",
    "sg:postcode":"SK12 1RH",
    "sg:province":"Cheshire",
    "sg:tags":[
        "equipment",
        "photocopier",
        "furniture"
    ],
    "wof:name":"Arrow Business Machines Ltd.",
    "wof:placetype":"venue"
},
  "geometry": {"coordinates":[-2.113576,53.348114],"type":"Point"}
}