{
  "type": "Feature",
  "properties": {
    "addr:full":"Unit 1 Quadeast, Warme Road Weston-super-mare Somerset BS23 3TR",
    "addr:housenumber":"unit 1",
    "addr:postcode":"bs23 3tr",
    "addr:street":"Quadeast Warme Road",
    "iso:country":"GB",
    "sg:address":"Unit 1 Quadeast, Warme Road",
    "sg:city":"Weston-super-mare",
    "sg:classifiers":[
        {
            "category":"Farming",
            "subcategory":"Farm",
            "type":"Manufacturing & Wholesale Goods"
        }
    ],
    "sg:phone":"+44 1934 420770",
    "sg:postcode":"BS23 3TR",
    "sg:province":"Somerset",
    "sg:tags":[
        "agricultural"
    ],
    "wof:name":"Liebherr-Great Britain Ltd.",
    "wof:placetype":"venue"
},
  "geometry": {"coordinates":[-2.9771840572,51.3461914062],"type":"Point"}
}