{
  "type": "Feature",
  "properties": {
    "addr:full":"38 Greenside Lane Lanark South Lanarkshire ML11 7PY",
    "addr:housenumber":"38",
    "addr:postcode":"ml11 7py",
    "addr:street":"Greenside Lane",
    "iso:country":"GB",
    "sg:address":"38 Greenside Lane",
    "sg:city":"Lanark",
    "sg:classifiers":[
        {
            "category":"Health Services",
            "subcategory":"Podiatrist",
            "type":"Services"
        }
    ],
    "sg:phone":"+44 1555 663203",
    "sg:postcode":"ML11 7PY",
    "sg:province":"South Lanarkshire",
    "sg:tags":[
        "podiatrists",
        "chiropodist"
    ],
    "wof:name":"K C Hutchison",
    "wof:placetype":"venue"
},
  "geometry": {"coordinates":[-3.7805991173,55.6756782532],"type":"Point"}
}