{
  "type": "Feature",
  "properties": {
    "addr:full":"36 Shores Green Dr Northwich Cheshire CW9 6EE",
    "addr:housenumber":"36",
    "addr:postcode":"cw9 6ee",
    "addr:street":"Shores Green Dr",
    "iso:country":"GB",
    "sg:address":"36 Shores Green Dr",
    "sg:city":"Northwich",
    "sg:classifiers":[
        {
            "category":"Building & Trades",
            "subcategory":"Construction",
            "type":"Services"
        }
    ],
    "sg:phone":"+44 1565 733475",
    "sg:postcode":"CW9 6EE",
    "sg:province":"Cheshire",
    "sg:tags":[
        "decorator",
        "painter"
    ],
    "wof:name":"C Holman",
    "wof:placetype":"venue"
},
  "geometry": {"coordinates":[-2.4702510834,53.2820587158],"type":"Point"}
}