{
  "type": "Feature",
  "properties": {
    "addr:full":"East Witton Leyburn North Yorkshire DL8 4SQ",
    "addr:postcode":"dl8 4sq",
    "addr:street":"East Witton",
    "iso:country":"GB",
    "sg:address":"East Witton",
    "sg:city":"Leyburn",
    "sg:classifiers":[
        {
            "category":"Bars & Pubs",
            "type":"Food & Drink"
        }
    ],
    "sg:postcode":"DL8 4SQ",
    "sg:province":"North Yorkshire",
    "sg:tags":[
        "pubs",
        "inn"
    ],
    "wof:name":"N  Harrington",
    "wof:placetype":"venue"
},
  "geometry": {"coordinates":[-1.803213954,54.2855987549],"type":"Point"}
}