{
  "type": "Feature",
  "properties": {
    "addr:full":"3 Whiting Road, Norwich Business Park Norwich Norfolk NR4 6EA",
    "addr:housenumber":"3",
    "addr:postcode":"nr4 6ea",
    "addr:street":"Whiting Road Norwich Business Park Norwich Norfolk",
    "iso:country":"GB",
    "sg:address":"3 Whiting Road, Norwich Business Park",
    "sg:city":"Norwich",
    "sg:classifiers":[
        {
            "category":"Banks & Credit Unions",
            "subcategory":"Financial Services",
            "type":"Services"
        }
    ],
    "sg:phone":"+44 1603 762614",
    "sg:postcode":"NR4 6EA",
    "sg:province":"Norfolk",
    "sg:tags":[
        "consultant"
    ],
    "wof:name":"Michael Keith Eddison",
    "wof:placetype":"venue"
},
  "geometry": {"coordinates":[1.2925050259,52.608215332],"type":"Point"}
}