{
  "type": "Feature",
  "properties": {
    "iso:country":"GB",
    "sg:address":"Charley Hill, Adbury Road, Burghclere",
    "sg:city":"Reading",
    "sg:classifiers":[
        {
            "category":"Building & Trades",
            "subcategory":"Construction",
            "type":"Services"
        }
    ],
    "sg:phone":"+44 1635 278604",
    "sg:postcode":"RG20 9HN",
    "sg:province":"Berkshire",
    "sg:tags":[
        "dry",
        "plastering",
        "plasterers",
        "lining",
        "related",
        "screeders"
    ],
    "wof:name":"Jaycee Plastering Contractors",
    "wof:placetype":"venue"
},
  "geometry": {"coordinates":[-1.3240389824,51.3482666016],"type":"Point"}
}