{
  "type": "Feature",
  "properties": {
    "iso:country":"GB",
    "sg:address":"Blackwater Centre, 12-14 London Road, Blackwater",
    "sg:city":"Camberley",
    "sg:classifiers":[
        {
            "category":"Government",
            "subcategory":"City Hall",
            "type":"Public Place"
        },
        {
            "category":"Retail",
            "subcategory":"Event Space",
            "type":"Services"
        }
    ],
    "sg:phone":"+44 1276 33050",
    "sg:postcode":"GU17 9AA",
    "sg:province":"Hampshire",
    "sg:tags":[
        "function",
        "hire",
        "room"
    ],
    "wof:name":"Blackwater & Hawley Town Council",
    "wof:placetype":"venue"
},
  "geometry": {"coordinates":[-0.786969,51.329739],"type":"Point"}
}