{
  "type": "Feature",
  "properties": {
    "addr:full":"5 Market St Mall, Clay Cross Chesterfield Derbyshire S45 9JE",
    "addr:housenumber":"5",
    "addr:postcode":"s45 9je",
    "addr:street":"Market St Mall",
    "iso:country":"GB",
    "sg:address":"5 Market St Mall, Clay Cross",
    "sg:city":"Chesterfield",
    "sg:classifiers":[
        {
            "category":"Travel",
            "subcategory":"Travel Agent",
            "type":"Entertainment"
        }
    ],
    "sg:phone":"+44 1246 860085",
    "sg:postcode":"S45 9JE",
    "sg:province":"Derbyshire",
    "wof:name":"Global Travel",
    "wof:placetype":"venue"
},
  "geometry": {"coordinates":[-1.4135899544,53.166721344],"type":"Point"}
}