{
  "type": "Feature",
  "properties": {
    "iso:country":"GB",
    "sg:address":"260-268 Archway Road, Highgate",
    "sg:city":"London",
    "sg:classifiers":[
        {
            "category":"Shopping Center",
            "type":"Public Place"
        }
    ],
    "sg:phone":"+44 20 8342 9300",
    "sg:postcode":"N6 5AX",
    "sg:province":"Greater London",
    "sg:tags":[
        "clutch",
        "brake",
        "centre"
    ],
    "wof:name":"Mr Clutch",
    "wof:placetype":"venue"
},
  "geometry": {"coordinates":[-0.142363,51.575108],"type":"Point"}
}