{
  "type": "Feature",
  "properties": {
    "iso:country":"GB",
    "sg:address":"6 Old Oak Ave",
    "sg:city":"Coulsdon",
    "sg:classifiers":[
        {
            "category":"Building & Trades",
            "subcategory":"Landscaping Services",
            "type":"Services"
        }
    ],
    "sg:phone":"+44 1737 551975",
    "sg:postcode":"CR5 3PG",
    "sg:province":"Surrey",
    "sg:tags":[
        "landscape",
        "contractor"
    ],
    "wof:name":"Bignell,Gary,",
    "wof:placetype":"venue"
},
  "geometry": {"coordinates":[-0.174175,51.306168],"type":"Point"}
}