{
  "type": "Feature",
  "properties": {
    "addr:full":"63-65 Greenhill Rise Corby Northamptonshire NN18 0LR",
    "addr:housenumber":"63-65",
    "addr:postcode":"nn18 0lr",
    "addr:street":"Greenhill Rise",
    "iso:country":"GB",
    "sg:address":"63-65 Greenhill Rise",
    "sg:city":"Corby",
    "sg:classifiers":[
        {
            "category":"Shopping",
            "subcategory":"News",
            "type":"Retail Goods"
        }
    ],
    "sg:phone":"+44 1536 203913",
    "sg:postcode":"NN18 0LR",
    "sg:province":"Northamptonshire",
    "sg:tags":[
        "newsagent"
    ],
    "wof:name":"Green's News & Post Office",
    "wof:placetype":"venue"
},
  "geometry": {"coordinates":[-0.722819984,52.4825897217],"type":"Point"}
}