{
  "type": "Feature",
  "properties": {
    "addr:full":"270 Westgate Rd Newcastle Upon Tyne Tyne and Wear NE4 6AR",
    "addr:housenumber":"270",
    "addr:postcode":"ne4 6ar",
    "addr:street":"Westgate Rd",
    "iso:country":"GB",
    "sg:address":"270 Westgate Rd",
    "sg:city":"Newcastle Upon Tyne",
    "sg:classifiers":[
        {
            "category":"Shopping",
            "subcategory":"Mobile Phones",
            "type":"Retail Goods"
        }
    ],
    "sg:phone":"+44 191 261 4394",
    "sg:postcode":"NE4 6AR",
    "sg:province":"Tyne and Wear",
    "wof:name":"Happy Talk",
    "wof:placetype":"venue"
},
  "geometry": {"coordinates":[-1.628345,54.97179],"type":"Point"}
}