{
  "type": "Feature",
  "properties": {
    "addr:full":"79 Estcourt Road Salisbury Wiltshire SP1 3AX",
    "addr:housenumber":"79",
    "addr:postcode":"sp1 3ax",
    "addr:street":"Estcourt Road",
    "iso:country":"GB",
    "sg:address":"79 Estcourt Road",
    "sg:city":"Salisbury",
    "sg:classifiers":[
        {
            "category":"Personal",
            "subcategory":"Beauty Salon",
            "type":"Services"
        }
    ],
    "sg:postcode":"SP1 3AX",
    "sg:province":"Wiltshire",
    "sg:tags":[
        "unisex",
        "hairdresser"
    ],
    "wof:name":"Anonymous",
    "wof:placetype":"venue"
},
  "geometry": {"coordinates":[-1.7871539593,51.0741157532],"type":"Point"}
}