{
  "type": "Feature",
  "properties": {
    "iso:country":"GB",
    "sg:address":"1-3 Kenyon Road, Brierfield",
    "sg:city":"Nelson",
    "sg:classifiers":[
        {
            "category":"Home & Garden",
            "subcategory":"Household Appliances",
            "type":"Retail Goods"
        },
        {
            "category":"Utilities",
            "subcategory":"Natural Gas",
            "type":"Services"
        }
    ],
    "sg:phone":"+44 1282 611000",
    "sg:postcode":"BB9 5SP",
    "sg:province":"Lancashire",
    "sg:tags":[
        "sale"
    ],
    "wof:name":"Independent Gas Co",
    "wof:placetype":"venue"
},
  "geometry": {"coordinates":[-2.231505,53.832924],"type":"Point"}
}