{
  "type": "Feature",
  "properties": {
    "iso:country":"GB",
    "sg:address":"Queen Elizabeth Drive",
    "sg:city":"Paignton",
    "sg:classifiers":[
        {
            "category":"Community Center",
            "type":"Public Place"
        }
    ],
    "sg:phone":"+44 1803 558023",
    "sg:postcode":"TQ3 3YS",
    "sg:province":"Devon",
    "sg:tags":[
        "centre"
    ],
    "wof:name":"Great Parks Community Centre",
    "wof:placetype":"venue"
},
  "geometry": {"coordinates":[-3.5919399261,50.4371376038],"type":"Point"}
}