{
  "type": "Feature",
  "properties": {
    "addr:full":"5 Marshall Way, Luncarty Perth Perth and Kinross PH1 3UX",
    "addr:housenumber":"5",
    "addr:postcode":"ph1 3ux",
    "addr:street":"Marshall Way",
    "iso:country":"GB",
    "sg:address":"5 Marshall Way, Luncarty",
    "sg:city":"Perth",
    "sg:classifiers":[
        {
            "category":"Home & Garden",
            "subcategory":"Household Appliances",
            "type":"Retail Goods"
        }
    ],
    "sg:phone":"+44 1738 828036",
    "sg:postcode":"PH1 3UX",
    "sg:province":"Perth and Kinross",
    "sg:tags":[
        "repairs",
        "electrical",
        "domestic",
        "servicing"
    ],
    "wof:name":"William G L Ramsay",
    "wof:placetype":"venue"
},
  "geometry": {"coordinates":[-3.466582,56.448299],"type":"Point"}
}