{
  "type": "Feature",
  "properties": {
    "iso:country":"GB",
    "sg:address":"161 Hatfield Road",
    "sg:city":"St Albans",
    "sg:classifiers":[
        {
            "category":"Shopping",
            "subcategory":"Thrift Store",
            "type":"Retail Goods"
        }
    ],
    "sg:phone":"+44 1727 854251",
    "sg:postcode":"AL1 4LB",
    "sg:province":"Hertfordshire",
    "sg:tags":[
        "shop",
        "charity"
    ],
    "sg:website":"http://www.oxfam.org.uk",
    "wof:name":"Oxfam",
    "wof:placetype":"venue"
},
  "geometry": {"coordinates":[-0.315505,51.752567],"type":"Point"}
}