{
  "type": "Feature",
  "properties": {
    "iso:country":"GB",
    "sg:address":"Green Lane Fish Bar, 18 Green Lane",
    "sg:city":"Redruth",
    "sg:classifiers":[
        {
            "category":"Fast Food",
            "type":"Food & Drink"
        }
    ],
    "sg:phone":"+44 1209 216456",
    "sg:postcode":"TR15 1JT",
    "sg:province":"Cornwall",
    "sg:tags":[
        "away",
        "take"
    ],
    "wof:name":"Mr Chips Fish & Chip Shop",
    "wof:placetype":"venue"
},
  "geometry": {"coordinates":[-5.211314,50.244926],"type":"Point"}
}