{
  "type": "Feature",
  "properties": {
    "iso:country":"GB",
    "sg:address":"6 Defoe Parade",
    "sg:city":"Grays",
    "sg:classifiers":[
        {
            "category":"Professional",
            "subcategory":"Business Services",
            "type":"Services"
        }
    ],
    "sg:phone":"+44 1375 855241",
    "sg:postcode":"RM16 4QR",
    "sg:province":"Essex",
    "sg:tags":[
        "bookmaker"
    ],
    "wof:name":"R S Pridmore",
    "wof:placetype":"venue"
},
  "geometry": {"coordinates":[0.3710179925,51.4884605408],"type":"Point"}
}