{
  "type": "Feature",
  "properties": {
    "addr:full":"11-13 Erskine Square, Hillington Industrial Estate Glasgow Glasgow City G52 4BJ",
    "addr:housenumber":"11-13",
    "addr:postcode":"g52 4bj",
    "addr:street":"Erskine Square;Industrial Estate",
    "iso:country":"GB",
    "sg:address":"11-13 Erskine Square, Hillington Industrial Estate",
    "sg:city":"Glasgow",
    "sg:classifiers":[
        {
            "category":"Professional",
            "subcategory":"Engineering",
            "type":"Services"
        }
    ],
    "sg:phone":"+44 141 883 3622",
    "sg:postcode":"G52 4BJ",
    "sg:province":"Glasgow City",
    "sg:tags":[
        "contractor",
        "electrical",
        "engineer"
    ],
    "wof:name":"Alan S Dickson (Electrical Contractors) Ltd.",
    "wof:placetype":"venue"
},
  "geometry": {"coordinates":[-4.366032,55.856014],"type":"Point"}
}