{
  "type": "Feature",
  "properties": {
    "addr:full":"First Floor, 2 Bartholomew Street Newbury Berkshire RG14 5LL",
    "addr:postcode":"rg14 5ll",
    "addr:street":"Bartholomew Street",
    "iso:country":"GB",
    "sg:address":"First Floor, 2 Bartholomew Street",
    "sg:city":"Newbury",
    "sg:classifiers":[
        {
            "category":"Professional",
            "subcategory":"Computer Services",
            "type":"Services"
        }
    ],
    "sg:postcode":"RG14 5LL",
    "sg:province":"Berkshire",
    "sg:tags":[
        "system",
        "software"
    ],
    "wof:name":"Timothy Cable",
    "wof:placetype":"venue"
},
  "geometry": {"coordinates":[-1.3244459629,51.4010505676],"type":"Point"}
}