{
  "type": "Feature",
  "properties": {
    "addr:full":"9 Pynate Road Batley West Yorkshire WF17 8EP",
    "addr:housenumber":"9",
    "addr:postcode":"wf17 8ep",
    "addr:street":"Pynate Road",
    "iso:country":"GB",
    "sg:address":"9 Pynate Road",
    "sg:city":"Batley",
    "sg:classifiers":[
        {
            "category":"Bus Charters",
            "type":"Transportation"
        }
    ],
    "sg:phone":"+44 1924 422571",
    "sg:postcode":"WF17 8EP",
    "sg:province":"West Yorkshire",
    "sg:tags":[
        "hire",
        "coach"
    ],
    "wof:name":"D & T Coaches",
    "wof:placetype":"venue"
},
  "geometry": {"coordinates":[-1.6494710445,53.7185287476],"type":"Point"}
}