{
  "type": "Feature",
  "properties": {
    "iso:country":"GB",
    "sg:address":"Units 11-11a Euro Business Park, New Road",
    "sg:city":"Newhaven",
    "sg:classifiers":[
        {
            "category":"Wholesale",
            "subcategory":"Medical Equipment & Supplies",
            "type":"Manufacturing & Wholesale Goods"
        },
        {
            "category":"Manufacturing",
            "subcategory":"Tools & Machinery",
            "type":"Manufacturing & Wholesale Goods"
        }
    ],
    "sg:phone":"+44 1273 516661",
    "sg:postcode":"BN9 0DQ",
    "sg:province":"East Sussex",
    "sg:tags":[
        "manufacture",
        "hospital"
    ],
    "sg:website":"http://www.goldsworth.co.uk",
    "wof:name":"Goldsworth Medical Ltd.",
    "wof:placetype":"venue"
},
  "geometry": {"coordinates":[0.046175,50.795036],"type":"Point"}
}