{
  "type": "Feature",
  "properties": {
    "addr:full":"53 Shooters Hill London Greater London SE18 3RL",
    "addr:housenumber":"53",
    "addr:postcode":"se18 3rl",
    "addr:street":"Shooters Hill",
    "iso:country":"GB",
    "sg:address":"53 Shooters Hill",
    "sg:city":"London",
    "sg:classifiers":[
        {
            "category":"Shopping",
            "subcategory":"Department Store",
            "type":"Retail Goods"
        }
    ],
    "sg:phone":"+44 20 8856 0171",
    "sg:postcode":"SE18 3RL",
    "sg:province":"Greater London",
    "wof:name":"Oasis",
    "wof:placetype":"venue"
},
  "geometry": {"coordinates":[0.060633,51.470375061],"type":"Point"}
}