{
  "type": "Feature",
  "properties": {
    "addr:full":"50 Bergen Way, North Lynn Ind Est King's Lynn Norfolk PE30 2JG",
    "addr:housenumber":"50",
    "addr:postcode":"pe30 2jg",
    "addr:street":"Bergen Way North",
    "iso:country":"GB",
    "sg:address":"50 Bergen Way, North Lynn Ind Est",
    "sg:city":"King's Lynn",
    "sg:classifiers":[
        {
            "category":"Professional",
            "type":"Services"
        }
    ],
    "sg:phone":"+44 1553 776790",
    "sg:postcode":"PE30 2JG",
    "sg:province":"Norfolk",
    "sg:tags":[
        "shopfitters"
    ],
    "wof:name":"Anglia Labelling Systems",
    "wof:placetype":"venue"
},
  "geometry": {"coordinates":[0.4149149954,52.7711029053],"type":"Point"}
}