{
  "type": "Feature",
  "properties": {
    "iso:country":"GB",
    "sg:address":"244 Nuneaton Street",
    "sg:city":"Glasgow",
    "sg:classifiers":[
        {
            "category":"Social Services",
            "type":"Services"
        }
    ],
    "sg:phone":"+44 141 550 4177",
    "sg:postcode":"G40 3DX",
    "sg:province":"Glasgow City",
    "sg:tags":[
        "need",
        "disability",
        "special"
    ],
    "wof:name":"Adaptocare Ltd.",
    "wof:placetype":"venue"
},
  "geometry": {"coordinates":[-4.216652,55.844444],"type":"Point"}
}