{
  "type": "Feature",
  "properties": {
    "iso:country":"GB",
    "sg:address":"Bank Farm, Tiverton",
    "sg:city":"Tarporley",
    "sg:classifiers":[
        {
            "category":"Farming",
            "subcategory":"Livestock Farm",
            "type":"Manufacturing & Wholesale Goods"
        }
    ],
    "sg:postcode":"CW6 9NA",
    "sg:province":"Cheshire",
    "sg:tags":[
        "others"
    ],
    "wof:name":"P S & B M Crossley",
    "wof:placetype":"venue"
},
  "geometry": {"coordinates":[-2.667804,53.137566],"type":"Point"}
}