{
  "type": "Feature",
  "properties": {
    "iso:country":"GB",
    "sg:address":"Market Hall, The Mall",
    "sg:city":"Bury",
    "sg:classifiers":[
        {
            "category":"Sports & Exercise",
            "subcategory":"Athletic Track",
            "type":"Entertainment"
        }
    ],
    "sg:phone":"+44 161 761 6479",
    "sg:postcode":"BL9 0BD",
    "sg:province":"Lancashire",
    "sg:tags":[
        "bags",
        "accessory",
        "belt"
    ],
    "wof:name":"Casson & Co Handbags",
    "wof:placetype":"venue"
},
  "geometry": {"coordinates":[-2.293651,53.592548],"type":"Point"}
}