{
  "type": "Feature",
  "properties": {
    "addr:full":"Canford House, 11 Roumelia Lane Poole Dorset BH5 1EU",
    "addr:housenumber":"canford;11",
    "addr:postcode":"bh5 1eu",
    "addr:street":"Roumelia Lane",
    "iso:country":"GB",
    "sg:address":"Canford House, 11 Roumelia Lane",
    "sg:city":"Poole",
    "sg:classifiers":[
        {
            "category":"Building & Trades",
            "subcategory":"Construction",
            "type":"Services"
        }
    ],
    "sg:phone":"+44 1202 729111",
    "sg:postcode":"BH5 1EU",
    "sg:province":"Dorset",
    "sg:tags":[
        "restoration",
        "refurbishment"
    ],
    "wof:name":"Canford Construction Ltd.",
    "wof:placetype":"venue"
},
  "geometry": {"coordinates":[-1.8419200182,50.7252311707],"type":"Point"}
}