{
  "type": "Feature",
  "properties": {
    "iso:country":"GB",
    "sg:address":"138 Central Road, Partington",
    "sg:city":"Manchester",
    "sg:classifiers":[
        {
            "category":"Military Area",
            "subcategory":"Air Force Base",
            "type":"Public Place"
        }
    ],
    "sg:postcode":"M31 4EQ",
    "sg:province":"Cheshire",
    "sg:tags":[
        "taxi",
        "hire",
        "private"
    ],
    "wof:name":"C & A Radio Cars",
    "wof:placetype":"venue"
},
  "geometry": {"coordinates":[-2.4258790016,53.4200782776],"type":"Point"}
}