{
  "type": "Feature",
  "properties": {
    "addr:full":"20-22 Catmose Street Oakham Leicestershire LE15 6HW",
    "addr:housenumber":"20-22",
    "addr:postcode":"le15 6hw",
    "addr:street":"Catmose Street",
    "iso:country":"GB",
    "sg:address":"20-22 Catmose Street",
    "sg:city":"Oakham",
    "sg:classifiers":[
        {
            "category":"Shopping",
            "subcategory":"Clothing, Apparel, & Fashions",
            "type":"Retail Goods"
        },
        {
            "category":"Shopping",
            "subcategory":"Bicycles & Sporting Goods",
            "type":"Retail Goods"
        }
    ],
    "sg:phone":"+44 1572 722675",
    "sg:postcode":"LE15 6HW",
    "sg:province":"Leicestershire",
    "sg:tags":[
        "sport",
        "clothing",
        "fabric",
        "sale"
    ],
    "wof:name":"Rutland Sports",
    "wof:placetype":"venue"
},
  "geometry": {"coordinates":[-0.7185140252,52.6657218933],"type":"Point"}
}