{
  "type": "Feature",
  "properties": {
    "addr:full":"46-48 Wood St Kingston-upon-thames Greater London KT1 1UG",
    "addr:housenumber":"46-48",
    "addr:postcode":"kt1 1ug",
    "addr:street":"Wood St",
    "iso:country":"GB",
    "sg:address":"46-48 Wood St",
    "sg:city":"Kingston-upon-thames",
    "sg:classifiers":[
        {
            "category":"Professional",
            "subcategory":"Printing & Photocopies",
            "type":"Services"
        }
    ],
    "sg:postcode":"KT1 1UG",
    "sg:province":"Greater London",
    "sg:tags":[
        "printer"
    ],
    "wof:name":"Aim Ventures Ltd",
    "wof:placetype":"venue"
},
  "geometry": {"coordinates":[-0.302019,51.412411],"type":"Point"}
}