{
  "type": "Feature",
  "properties": {
    "iso:country":"GB",
    "sg:address":"63 North Seventh Street, Central Milton Keynes",
    "sg:city":"Buckingham",
    "sg:classifiers":[
        {
            "category":"Organizations",
            "subcategory":"Non-profit Organization",
            "type":"Services"
        }
    ],
    "sg:phone":"+44 1908 605655",
    "sg:postcode":"MK9 2DP",
    "sg:province":"Buckinghamshire",
    "sg:tags":[
        "organisation",
        "voluntary",
        "charity"
    ],
    "wof:name":"The David Baxter Centre",
    "wof:placetype":"venue"
},
  "geometry": {"coordinates":[-0.7641,52.04287],"type":"Point"}
}