{
  "type": "Feature",
  "properties": {
    "addr:full":"21 Stacey Street London Greater London WC2H 8DG",
    "addr:housenumber":"21",
    "addr:postcode":"wc2h 8dg",
    "addr:street":"Stacey Street",
    "iso:country":"GB",
    "sg:address":"21 Stacey Street",
    "sg:city":"London",
    "sg:classifiers":[
        {
            "category":"Organizations",
            "subcategory":"Membership Organization",
            "type":"Services"
        }
    ],
    "sg:phone":"+44 20 7379 3187",
    "sg:postcode":"WC2H 8DG",
    "sg:province":"Greater London",
    "sg:tags":[
        "club"
    ],
    "wof:name":"Covent Garden Open Spaces Association",
    "wof:placetype":"venue"
},
  "geometry": {"coordinates":[-0.126944,51.51532],"type":"Point"}
}