{
  "type": "Feature",
  "properties": {
    "addr:full":"84 Stoke Lane, Westbury-on-trym Bristol City of Bristol BS9 3SP",
    "addr:housenumber":"84",
    "addr:postcode":"bs9 3sp",
    "addr:street":"Stoke Lane",
    "iso:country":"GB",
    "sg:address":"84 Stoke Lane, Westbury-on-trym",
    "sg:city":"Bristol",
    "sg:classifiers":[
        {
            "category":"Bars & Pubs",
            "type":"Food & Drink"
        }
    ],
    "sg:phone":"+44 117 962 3715",
    "sg:postcode":"BS9 3SP",
    "sg:province":"City of Bristol",
    "sg:tags":[
        "pubs",
        "inn"
    ],
    "wof:name":"The Prince of Wales",
    "wof:placetype":"venue"
},
  "geometry": {"coordinates":[-2.621319,51.490829],"type":"Point"}
}