{
  "type": "Feature",
  "properties": {
    "addr:full":"Dunrobin, King's Road Longniddry East Lothian EH32 0NN",
    "addr:postcode":"eh32 0nn",
    "addr:street":"King'S Road",
    "iso:country":"GB",
    "sg:address":"Dunrobin, King's Road",
    "sg:city":"Longniddry",
    "sg:classifiers":[
        {
            "category":"Building & Trades",
            "subcategory":"Landscaping Services",
            "type":"Services"
        }
    ],
    "sg:phone":"+44 1875 852829",
    "sg:postcode":"EH32 0NN",
    "sg:province":"East Lothian",
    "sg:tags":[
        "gardening"
    ],
    "wof:name":"Hard Graft Garden Services",
    "wof:placetype":"venue"
},
  "geometry": {"coordinates":[-2.8956229687,55.9738540649],"type":"Point"}
}