{
  "type": "Feature",
  "properties": {
    "iso:country":"GB",
    "sg:address":"Eastlea Brook Lane",
    "sg:city":"Alderley Edge",
    "sg:classifiers":[
        {
            "category":"Shopping",
            "subcategory":"Tobacco",
            "type":"Retail Goods"
        },
        {
            "category":"Professional",
            "subcategory":"Management & Consulting",
            "type":"Services"
        }
    ],
    "sg:phone":"+44 1625 583558",
    "sg:postcode":"SK9 7QQ",
    "sg:province":"Cheshire",
    "sg:tags":[
        "distributor",
        "consultant",
        "importer",
        "agent",
        "business"
    ],
    "wof:name":"The McLane Group Ltd.",
    "wof:placetype":"venue"
},
  "geometry": {"coordinates":[-2.236334,53.302807],"type":"Point"}
}