{
  "type": "Feature",
  "properties": {
    "addr:full":"886 Dunstable Road Luton Bedfordshire LU4 0HJ",
    "addr:housenumber":"886",
    "addr:postcode":"lu4 0hj",
    "addr:street":"Dunstable Road",
    "iso:country":"GB",
    "sg:address":"886 Dunstable Road",
    "sg:city":"Luton",
    "sg:classifiers":[
        {
            "category":"Shopping",
            "subcategory":"Clothing, Apparel, & Fashions",
            "type":"Retail Goods"
        }
    ],
    "sg:phone":"+44 1582 507069",
    "sg:postcode":"LU4 0HJ",
    "sg:province":"Bedfordshire",
    "sg:tags":[
        "shop"
    ],
    "wof:name":"Elenis Fashion",
    "wof:placetype":"venue"
},
  "geometry": {"coordinates":[-0.4825829864,51.8920478821],"type":"Point"}
}