{
  "type": "Feature",
  "properties": {
    "iso:country":"GB",
    "sg:address":"327 Mile End Road",
    "sg:city":"London",
    "sg:classifiers":[
        {
            "category":"Utilities",
            "subcategory":"Telephone",
            "type":"Services"
        },
        {
            "category":"Government",
            "subcategory":"Post Office",
            "type":"Public Place"
        }
    ],
    "sg:phone":"+44 20 8983 3162",
    "sg:postcode":"E1 4NS",
    "sg:province":"Greater London",
    "sg:tags":[
        "network",
        "organisation",
        "telecommunication",
        "soc",
        "research"
    ],
    "wof:name":"INTERSCIENCE COMMUNICATIONS LTD.",
    "wof:placetype":"venue"
},
  "geometry": {"coordinates":[-0.040628,51.52293],"type":"Point"}
}