{
  "type": "Feature",
  "properties": {
    "addr:full":"Malmesbury Health Centre, 46 High St Malmesbury Wiltshire SN16 9AT",
    "addr:housenumber":"46",
    "addr:postcode":"sn16 9at",
    "addr:street":"High St",
    "iso:country":"GB",
    "sg:address":"Malmesbury Health Centre, 46 High St",
    "sg:city":"Malmesbury",
    "sg:classifiers":[
        {
            "category":"Health Services",
            "subcategory":"Dentist",
            "type":"Services"
        }
    ],
    "sg:phone":"+44 1666 822595",
    "sg:postcode":"SN16 9AT",
    "sg:province":"Wiltshire",
    "wof:name":"B Wilkinson",
    "wof:placetype":"venue"
},
  "geometry": {"coordinates":[-2.097419,51.582245],"type":"Point"}
}