{
  "type": "Feature",
  "properties": {
    "addr:full":"23 George Street Luton Bedfordshire LU1 2AF",
    "addr:housenumber":"23",
    "addr:postcode":"lu1 2af",
    "addr:street":"George Street",
    "iso:country":"GB",
    "sg:address":"23 George Street",
    "sg:city":"Luton",
    "sg:classifiers":[
        {
            "category":"Professional",
            "subcategory":"Employment Agencies",
            "type":"Services"
        }
    ],
    "sg:phone":"+44 1582 400930",
    "sg:postcode":"LU1 2AF",
    "sg:province":"Bedfordshire",
    "sg:tags":[
        "consultant"
    ],
    "wof:name":"Adecco Alfred Marks",
    "wof:placetype":"venue"
},
  "geometry": {"coordinates":[-0.414831996,51.8782272339],"type":"Point"}
}