{
  "type": "Feature",
  "properties": {
    "addr:full":"Marklands, Lower Durston Taunton Devon TA3 5AH",
    "addr:postcode":"ta3 5ah",
    "addr:street":"Lower Durston",
    "iso:country":"GB",
    "sg:address":"Marklands, Lower Durston",
    "sg:city":"Taunton",
    "sg:classifiers":[
        {
            "category":"Building & Trades",
            "subcategory":"Construction",
            "type":"Services"
        }
    ],
    "sg:phone":"+44 1823 412727",
    "sg:postcode":"TA3 5AH",
    "sg:province":"Devon",
    "sg:tags":[
        "builder"
    ],
    "wof:name":"S A England & Sons",
    "wof:placetype":"venue"
},
  "geometry": {"coordinates":[-3.013044,51.04755],"type":"Point"}
}