{
  "type": "Feature",
  "properties": {
    "addr:full":"10 Chapel Wood, Llanedeyrn Cardiff Cardiff CF23 9EE",
    "addr:housenumber":"10",
    "addr:postcode":"cf23 9ee",
    "addr:street":"Chapel Wood Llanedeyrn",
    "iso:country":"GB",
    "sg:address":"10 Chapel Wood, Llanedeyrn",
    "sg:city":"Cardiff",
    "sg:classifiers":[
        {
            "category":"Building & Trades",
            "subcategory":"Landscaping Services",
            "type":"Services"
        }
    ],
    "sg:postcode":"CF23 9EE",
    "sg:province":"Cardiff",
    "sg:tags":[
        "forestry",
        "tree"
    ],
    "wof:name":"Alpine Tree & Garden Services",
    "wof:placetype":"venue"
},
  "geometry": {"coordinates":[-3.157409,51.50436],"type":"Point"}
}