{
  "type": "Feature",
  "properties": {
    "addr:full":"210 High Street Cheltenham Gloucestershire GL50 3HF",
    "addr:housenumber":"210",
    "addr:postcode":"gl50 3hf",
    "addr:street":"High Street",
    "iso:country":"GB",
    "sg:address":"210 High Street",
    "sg:city":"Cheltenham",
    "sg:classifiers":[
        {
            "category":"Food & Beverages",
            "subcategory":"Bakery",
            "type":"Retail Goods"
        }
    ],
    "sg:phone":"+44 1242 233086",
    "sg:postcode":"GL50 3HF",
    "sg:province":"Gloucestershire",
    "sg:tags":[
        "shop",
        "baker"
    ],
    "wof:name":"LAWRANCE'S BAKERY",
    "wof:placetype":"venue"
},
  "geometry": {"coordinates":[-2.075764,51.901497],"type":"Point"}
}