{
  "type": "Feature",
  "properties": {
    "addr:full":"62-66 Parsonage Street Dursley Gloucestershire GL11 4AA",
    "addr:housenumber":"62-66",
    "addr:postcode":"gl11 4aa",
    "addr:street":"Parsonage Street",
    "iso:country":"GB",
    "sg:address":"62-66 Parsonage Street",
    "sg:city":"Dursley",
    "sg:classifiers":[
        {
            "category":"Shopping",
            "subcategory":"News",
            "type":"Retail Goods"
        }
    ],
    "sg:phone":"+44 1453 544000",
    "sg:postcode":"GL11 4AA",
    "sg:province":"Gloucestershire",
    "sg:tags":[
        "newsagent"
    ],
    "wof:name":"Baileys News Ltd.",
    "wof:placetype":"venue"
},
  "geometry": {"coordinates":[-2.3566989899,51.6819114685],"type":"Point"}
}