{
  "type": "Feature",
  "properties": {
    "iso:country":"GB",
    "sg:address":"Stepaside Heritage Project, Stepaside",
    "sg:city":"Narberth",
    "sg:classifiers":[
        {
            "category":"Home & Garden",
            "subcategory":"Kitchen Supply",
            "type":"Retail Goods"
        }
    ],
    "sg:phone":"+44 1834 811104",
    "sg:postcode":"SA67 8LL",
    "sg:province":"Carmarthenshire",
    "sg:tags":[
        "glassware",
        "china"
    ],
    "wof:name":"Glyncoch Designs",
    "wof:placetype":"venue"
},
  "geometry": {"coordinates":[-4.691234,51.747456],"type":"Point"}
}