{
  "type": "Feature",
  "properties": {
    "iso:country":"GB",
    "sg:address":"Central Methodist Church, Hargreaves St",
    "sg:city":"Burnley",
    "sg:classifiers":[
        {
            "category":"Professional",
            "subcategory":"Testing Lab",
            "type":"Services"
        }
    ],
    "sg:phone":"+44 1282 450880",
    "sg:postcode":"BB11 4BN",
    "sg:province":"Lancashire",
    "sg:tags":[
        "pregnancy"
    ],
    "wof:name":"Life Pregnancy Care Service",
    "wof:placetype":"venue"
},
  "geometry": {"coordinates":[-2.2438089848,53.7880096436],"type":"Point"}
}