{
  "type": "Feature",
  "properties": {
    "iso:country":"GB",
    "sg:address":"241 Stanstead Road",
    "sg:city":"London",
    "sg:classifiers":[
        {
            "category":"Organizations",
            "subcategory":"Membership Organization",
            "type":"Services"
        }
    ],
    "sg:phone":"+44 20 8690 1410",
    "sg:postcode":"SE23 1HU",
    "sg:province":"Greater London",
    "sg:tags":[
        "club"
    ],
    "wof:name":"Lewisham National Reserve Club Ltd.",
    "wof:placetype":"venue"
},
  "geometry": {"coordinates":[-0.039637,51.442142],"type":"Point"}
}