{
  "type": "Feature",
  "properties": {
    "iso:country":"GB",
    "sg:address":"3 Jinians Terr",
    "sg:city":"Kilwinning",
    "sg:classifiers":[
        {
            "category":"Building & Trades",
            "subcategory":"Construction",
            "type":"Services"
        }
    ],
    "sg:phone":"+44 1294 559011",
    "sg:postcode":"KA13 7PN",
    "sg:province":"East Ayrshire",
    "sg:tags":[
        "joiner",
        "carpenter"
    ],
    "wof:name":"R.S. Joinery",
    "wof:placetype":"venue"
},
  "geometry": {"coordinates":[-4.68878,55.647259],"type":"Point"}
}