{
  "type": "Feature",
  "properties": {
    "addr:full":"48 Vicarage Rd, Winslow Buckingham Buckinghamshire MK18 3BH",
    "addr:housenumber":"48",
    "addr:postcode":"mk18 3bh",
    "addr:street":"Vicarage Rd",
    "iso:country":"GB",
    "sg:address":"48 Vicarage Rd, Winslow",
    "sg:city":"Buckingham",
    "sg:classifiers":[
        {
            "category":"Home & Garden",
            "subcategory":"Building Materials",
            "type":"Retail Goods"
        }
    ],
    "sg:phone":"+44 1296 712362",
    "sg:postcode":"MK18 3BH",
    "sg:province":"Buckinghamshire",
    "sg:tags":[
        "ironwork",
        "wrought"
    ],
    "wof:name":"Brookside Wrought Ironwork & Metalwork",
    "wof:placetype":"venue"
},
  "geometry": {"coordinates":[-0.88544,51.942657],"type":"Point"}
}