{
  "type": "Feature",
  "properties": {
    "addr:full":"5 Church Lane Chesterfield Derbyshire S42 5SD",
    "addr:housenumber":"5",
    "addr:postcode":"s42 5sd",
    "addr:street":"Church Lane",
    "iso:country":"GB",
    "sg:address":"5 Church Lane",
    "sg:city":"Chesterfield",
    "sg:classifiers":[
        {
            "category":"Building & Trades",
            "subcategory":"Construction",
            "type":"Services"
        }
    ],
    "sg:phone":"+44 1246 852500",
    "sg:postcode":"S42 5SD",
    "sg:province":"Derbyshire",
    "sg:tags":[
        "flooring"
    ],
    "wof:name":"Carlin Quality Surfaces",
    "wof:placetype":"venue"
},
  "geometry": {"coordinates":[-1.393806,53.174774],"type":"Point"}
}