{
  "type": "Feature",
  "properties": {
    "addr:full":"14 Woodland Rd Darlington Durham DL3 7PL",
    "addr:housenumber":"14",
    "addr:postcode":"dl3 7pl",
    "addr:street":"Woodland Rd",
    "iso:country":"GB",
    "sg:address":"14 Woodland Rd",
    "sg:city":"Darlington",
    "sg:classifiers":[
        {
            "category":"Professional",
            "type":"Services"
        }
    ],
    "sg:postcode":"DL3 7PL",
    "sg:province":"Durham",
    "sg:tags":[
        "reflexologists"
    ],
    "wof:name":"Marshall,Judith,",
    "wof:placetype":"venue"
},
  "geometry": {"coordinates":[-1.560945034,54.5277748108],"type":"Point"}
}