{
  "type": "Feature",
  "properties": {
    "iso:country":"GB",
    "sg:address":"Shayes Farm, Noneley, Wem",
    "sg:city":"Shrewsbury",
    "sg:classifiers":[
        {
            "category":"Building & Trades",
            "subcategory":"Construction",
            "type":"Services"
        }
    ],
    "sg:postcode":"SY4 5SL",
    "sg:province":"Shropshire",
    "sg:tags":[
        "builder"
    ],
    "wof:name":"M Salt Building Contractor",
    "wof:placetype":"venue"
},
  "geometry": {"coordinates":[-2.7740700245,52.8466911316],"type":"Point"}
}