{
  "type": "Feature",
  "properties": {
    "addr:full":"North Treveneague, Goldsithney Penzance Cornwall TR20 9BY",
    "addr:postcode":"tr20 9by",
    "addr:street":"North;Goldsithney",
    "iso:country":"GB",
    "sg:address":"North Treveneague, Goldsithney",
    "sg:city":"Penzance",
    "sg:classifiers":[
        {
            "category":"Banks & Credit Unions",
            "subcategory":"Investment Brokerage",
            "type":"Services"
        }
    ],
    "sg:postcode":"TR20 9BY",
    "sg:province":"Cornwall",
    "sg:tags":[
        "contractor"
    ],
    "wof:name":"J C Keskeys",
    "wof:placetype":"venue"
},
  "geometry": {"coordinates":[-5.4367542267,50.1250991821],"type":"Point"}
}