{
  "type": "Feature",
  "properties": {
    "iso:country":"GB",
    "sg:address":"152 Amington Road",
    "sg:city":"Birmingham",
    "sg:classifiers":[
        {
            "category":"Autos & Motor Vehicles",
            "subcategory":"Fuel & Gas Station",
            "type":"Retail Goods"
        }
    ],
    "sg:phone":"+44 121 706 5673",
    "sg:postcode":"B25 8EL",
    "sg:province":"West Midlands",
    "sg:tags":[
        "petrol",
        "filling"
    ],
    "wof:name":"Stockfield Service Station",
    "wof:placetype":"venue"
},
  "geometry": {"coordinates":[-1.823162,52.457668],"type":"Point"}
}