{
  "type": "Feature",
  "properties": {
    "iso:country":"GB",
    "sg:address":"433 Eglinton Street",
    "sg:city":"Glasgow",
    "sg:classifiers":[
        {
            "category":"Home & Garden",
            "subcategory":"Hardware",
            "type":"Retail Goods"
        },
        {
            "category":"Shopping",
            "subcategory":"Discount & Variety Stores",
            "type":"Retail Goods"
        }
    ],
    "sg:phone":"+44 141 429 2837",
    "sg:postcode":"G5 9RU",
    "sg:province":"Glasgow City",
    "sg:tags":[
        "equipment",
        "material",
        "cleaning",
        "supply"
    ],
    "wof:name":"John Black & Sons",
    "wof:placetype":"venue"
},
  "geometry": {"coordinates":[-4.261799,55.845058],"type":"Point"}
}