{
  "type": "Feature",
  "properties": {
    "iso:country":"GB",
    "sg:address":"High Street",
    "sg:city":"Runcorn",
    "sg:classifiers":[
        {
            "category":"Organizations",
            "subcategory":"Membership Organization",
            "type":"Services"
        }
    ],
    "sg:phone":"+44 1928 572140",
    "sg:postcode":"WA7 1AH",
    "sg:province":"Cheshire",
    "sg:tags":[
        "club"
    ],
    "wof:name":"la Scala Bingo & Social Club",
    "wof:placetype":"venue"
},
  "geometry": {"coordinates":[-2.730224,53.342087],"type":"Point"}
}