{
  "type": "Feature",
  "properties": {
    "addr:full":"3 Great Bramingham Farm, Bramingham Lane Luton Bedfordshire LU3 3NW",
    "addr:housenumber":"3",
    "addr:postcode":"lu3 3nw",
    "addr:street":"Great Bramingham;Bramingham Lane",
    "iso:country":"GB",
    "sg:address":"3 Great Bramingham Farm, Bramingham Lane",
    "sg:city":"Luton",
    "sg:classifiers":[
        {
            "category":"Building & Trades",
            "subcategory":"Construction",
            "type":"Services"
        }
    ],
    "sg:postcode":"LU3 3NW",
    "sg:province":"Bedfordshire",
    "sg:tags":[
        "glazier",
        "decorator",
        "painter"
    ],
    "wof:name":"A K L Decorators",
    "wof:placetype":"venue"
},
  "geometry": {"coordinates":[-0.4295400083,51.9332504272],"type":"Point"}
}