{
  "type": "Feature",
  "properties": {
    "addr:full":"Unit 4 8 Marsh Green Road Exeter Devon EX2 8NY",
    "addr:housenumber":"unit;8",
    "addr:postcode":"ex2 8ny",
    "addr:street":"Marsh Green Road",
    "iso:country":"GB",
    "sg:address":"Unit 4 8 Marsh Green Road",
    "sg:city":"Exeter",
    "sg:classifiers":[
        {
            "category":"Parking",
            "type":"Transportation"
        }
    ],
    "sg:phone":"+44 1392 490890",
    "sg:postcode":"EX2 8NY",
    "sg:province":"Devon",
    "sg:tags":[
        "car",
        "valet"
    ],
    "wof:name":"R M Cars",
    "wof:placetype":"venue"
},
  "geometry": {"coordinates":[-3.5273060799,50.7084388733],"type":"Point"}
}