{
  "type": "Feature",
  "properties": {
    "iso:country":"GB",
    "sg:address":"The Arrow Mill",
    "sg:city":"Alcester",
    "sg:classifiers":[
        {
            "category":"Travel",
            "subcategory":"Hotels & Motels",
            "type":"Entertainment"
        }
    ],
    "sg:phone":"+44 1789 762419",
    "sg:postcode":"B49 5NL",
    "sg:province":"Warwickshire",
    "wof:name":"The Arrow Mill Hotel Ltd.",
    "wof:placetype":"venue"
},
  "geometry": {"coordinates":[-1.8839210272,52.2071914673],"type":"Point"}
}