{
  "type": "Feature",
  "properties": {
    "addr:full":"11a Portland Street, Cosby Leicester Leicestershire LE9 1TF",
    "addr:housenumber":"11a",
    "addr:postcode":"le9 1tf",
    "addr:street":"Portland Street",
    "iso:country":"GB",
    "sg:address":"11a Portland Street, Cosby",
    "sg:city":"Leicester",
    "sg:classifiers":[
        {
            "category":"Military Area",
            "subcategory":"Air Force Base",
            "type":"Public Place"
        }
    ],
    "sg:postcode":"LE9 1TF",
    "sg:province":"Leicestershire",
    "sg:tags":[
        "taxi",
        "hire",
        "private"
    ],
    "wof:name":"Kenneys Taxi Service",
    "wof:placetype":"venue"
},
  "geometry": {"coordinates":[-1.195049,52.554588],"type":"Point"}
}