{
  "type": "Feature",
  "properties": {
    "iso:country":"GB",
    "sg:address":"18 Burford Rd",
    "sg:city":"Stratford",
    "sg:classifiers":[
        {
            "category":"Food & Beverages",
            "subcategory":"Supermarket",
            "type":"Retail Goods"
        }
    ],
    "sg:phone":"+44 20 8519 8140",
    "sg:postcode":"E15 2SP",
    "sg:province":"Greater London",
    "sg:tags":[
        "frozen"
    ],
    "wof:name":"Best Food Manufacturers",
    "wof:placetype":"venue"
},
  "geometry": {"coordinates":[-0.001391,51.537849],"type":"Point"}
}