{
  "type": "Feature",
  "properties": {
    "addr:full":"162 Newtown Road Bedworth Warwickshire CV12 8QN",
    "addr:housenumber":"162",
    "addr:postcode":"cv12 8qn",
    "addr:street":"Newtown Road",
    "iso:country":"GB",
    "sg:address":"162 Newtown Road",
    "sg:city":"Bedworth",
    "sg:classifiers":[
        {
            "category":"Professional",
            "subcategory":"Engineering",
            "type":"Services"
        }
    ],
    "sg:postcode":"CV12 8QN",
    "sg:province":"Warwickshire",
    "sg:tags":[
        "electronic",
        "engineer"
    ],
    "wof:name":"D M W Electronic Services",
    "wof:placetype":"venue"
},
  "geometry": {"coordinates":[-1.484381,52.479244],"type":"Point"}
}