{
  "type": "Feature",
  "properties": {
    "iso:country":"GB",
    "sg:address":"Bodmin Rd",
    "sg:city":"Coventry",
    "sg:classifiers":[
        {
            "category":"Retail",
            "subcategory":"Auto Repair",
            "type":"Services"
        }
    ],
    "sg:phone":"+44 24 7660 2633",
    "sg:postcode":"CV2 5DY",
    "sg:province":"Warwickshire",
    "sg:tags":[
        "body",
        "car"
    ],
    "wof:name":"Eastern Garage",
    "wof:placetype":"venue"
},
  "geometry": {"coordinates":[-1.447924,52.41893],"type":"Point"}
}