{
  "type": "Feature",
  "properties": {
    "iso:country":"GB",
    "sg:address":"Mayfield, Giantswood Lane, Hulme Walfield",
    "sg:city":"Congleton",
    "sg:classifiers":[
        {
            "category":"Building & Trades",
            "subcategory":"Landscaping Services",
            "type":"Services"
        }
    ],
    "sg:phone":"+44 1260 270611",
    "sg:postcode":"CW12 2HH",
    "sg:province":"Cheshire",
    "sg:tags":[
        "designer",
        "architect",
        "landscape"
    ],
    "wof:name":"Redesmere Garden Design",
    "wof:placetype":"venue"
},
  "geometry": {"coordinates":[-2.228024,53.183426],"type":"Point"}
}