{
  "type": "Feature",
  "properties": {
    "iso:country":"GB",
    "sg:address":"Unit 7a-b Wirral Business Park, Arrowbrook Road, Upton",
    "sg:city":"Wirral",
    "sg:classifiers":[
        {
            "category":"Home & Garden",
            "subcategory":"Furniture",
            "type":"Retail Goods"
        }
    ],
    "sg:phone":"+44 151 678 9673",
    "sg:postcode":"CH49 1QZ",
    "sg:province":"Merseyside",
    "wof:name":"Pinewood Warehouse Supplies (Wholesale) Ltd.",
    "wof:placetype":"venue"
},
  "geometry": {"coordinates":[-3.1027090549,53.3750915527],"type":"Point"}
}