{
  "type": "Feature",
  "properties": {
    "addr:full":"67 Church Road Manchester Greater Manchester M22 4WD",
    "addr:housenumber":"67",
    "addr:postcode":"m22 4wd",
    "addr:street":"Church Road",
    "iso:country":"GB",
    "sg:address":"67 Church Road",
    "sg:city":"Manchester",
    "sg:classifiers":[
        {
            "category":"Food & Beverages",
            "subcategory":"Groceries & Convenience Stores",
            "type":"Retail Goods"
        }
    ],
    "sg:phone":"+44 161 945 7071",
    "sg:postcode":"M22 4WD",
    "sg:province":"Greater Manchester",
    "wof:name":"NORTHERNDENS MINI MARKET",
    "wof:placetype":"venue"
},
  "geometry": {"coordinates":[-2.257206,53.397099],"type":"Point"}
}