{
  "type": "Feature",
  "properties": {
    "addr:full":"77 Princedale Road London Greater London W11 4NS",
    "addr:housenumber":"77",
    "addr:postcode":"w11 4ns",
    "addr:street":"Princedale Road",
    "iso:country":"GB",
    "sg:address":"77 Princedale Road",
    "sg:city":"London",
    "sg:classifiers":[
        {
            "category":"Organizations",
            "subcategory":"Non-profit Organization",
            "type":"Services"
        }
    ],
    "sg:phone":"+44 20 7727 5021",
    "sg:postcode":"W11 4NS",
    "sg:province":"Greater London",
    "sg:tags":[
        "organisation",
        "voluntary",
        "charity"
    ],
    "wof:name":"Full of Life",
    "wof:placetype":"venue"
},
  "geometry": {"coordinates":[-0.2111400068,51.5092506409],"type":"Point"}
}