{
  "type": "Feature",
  "properties": {
    "addr:full":"24-26 Coppergate York North Yorkshire YO1 9NR",
    "addr:housenumber":"24-26",
    "addr:postcode":"yo1 9nr",
    "addr:street":"Coppergate York",
    "iso:country":"GB",
    "sg:address":"24-26 Coppergate",
    "sg:city":"York",
    "sg:classifiers":[
        {
            "category":"Restaurant",
            "type":"Food & Drink"
        }
    ],
    "sg:phone":"+44 1904 644330",
    "sg:postcode":"YO1 9NR",
    "sg:province":"North Yorkshire",
    "wof:name":"Russells Of Coppergate",
    "wof:placetype":"venue"
},
  "geometry": {"coordinates":[-1.080714,53.957844],"type":"Point"}
}