{
  "type": "Feature",
  "properties": {
    "iso:country":"GB",
    "sg:address":"8 Belsay, Ox Close",
    "sg:city":"Washington",
    "sg:classifiers":[
        {
            "category":"Retail",
            "subcategory":"Driving School",
            "type":"Services"
        }
    ],
    "sg:phone":"+44 191 415 4307",
    "sg:postcode":"NE38 0NE",
    "sg:province":"Durham",
    "wof:name":"Steve Roberts",
    "wof:placetype":"venue"
},
  "geometry": {"coordinates":[-1.550646,54.89793],"type":"Point"}
}