{
  "type": "Feature",
  "properties": {
    "addr:full":"3 Lancaster Gardens London Greater London W13 9JY",
    "addr:housenumber":"3",
    "addr:postcode":"w13 9jy",
    "addr:street":"Lancaster Gardens",
    "iso:country":"GB",
    "sg:address":"3 Lancaster Gardens",
    "sg:city":"London",
    "sg:classifiers":[
        {
            "category":"Social Services",
            "subcategory":"Job Training",
            "type":"Services"
        }
    ],
    "sg:phone":"+44 20 8579 8474",
    "sg:postcode":"W13 9JY",
    "sg:province":"Greater London",
    "sg:tags":[
        "translator",
        "interpreter"
    ],
    "wof:name":"Paul Vincent",
    "wof:placetype":"venue"
},
  "geometry": {"coordinates":[-0.3163850009,51.5068817139],"type":"Point"}
}