{
  "type": "Feature",
  "properties": {
    "addr:full":"Station Road, Kirton Lindsey Gainsborough Lincolnshire DN21 4BD",
    "addr:postcode":"dn21 4bd",
    "addr:street":"Station Road",
    "iso:country":"GB",
    "sg:address":"Station Road, Kirton Lindsey",
    "sg:city":"Gainsborough",
    "sg:classifiers":[
        {
            "category":"Autos & Motor Vehicles",
            "subcategory":"Automobile Sales",
            "type":"Retail Goods"
        }
    ],
    "sg:phone":"+44 1652 648429",
    "sg:postcode":"DN21 4BD",
    "sg:province":"Lincolnshire",
    "sg:tags":[
        "car"
    ],
    "wof:name":"G G Steel",
    "wof:placetype":"venue"
},
  "geometry": {"coordinates":[-0.5874530077,53.4758453369],"type":"Point"}
}