{
  "type": "Feature",
  "properties": {
    "addr:full":"Wessington Avenue, London Road Calne Wiltshire SN11 0AW",
    "addr:postcode":"sn11 0aw",
    "addr:street":"Wessington Avenue London Road",
    "iso:country":"GB",
    "sg:address":"Wessington Avenue, London Road",
    "sg:city":"Calne",
    "sg:classifiers":[
        {
            "category":"Personal",
            "type":"Services"
        }
    ],
    "sg:postcode":"SN11 0AW",
    "sg:province":"Wiltshire",
    "sg:tags":[
        "delivery"
    ],
    "wof:name":"Robert Hasell (Haulage) Ltd.",
    "wof:placetype":"venue"
},
  "geometry": {"coordinates":[-1.997964,51.430286],"type":"Point"}
}