{
  "type": "Feature",
  "properties": {
    "iso:country":"GB",
    "sg:address":"Hurdon Road, Scarne Industrial Estate",
    "sg:city":"Launceston",
    "sg:classifiers":[
        {
            "category":"Manufacturing",
            "subcategory":"Paper Products",
            "type":"Manufacturing & Wholesale Goods"
        }
    ],
    "sg:phone":"+44 1566 772303",
    "sg:postcode":"PL15 9HN",
    "sg:province":"Cornwall",
    "sg:tags":[
        "cardboard"
    ],
    "wof:name":"David S Smith Corrugated",
    "wof:placetype":"venue"
},
  "geometry": {"coordinates":[-4.3559532166,50.6298713684],"type":"Point"}
}