{
  "type": "Feature",
  "properties": {
    "iso:country":"GB",
    "sg:address":"Unit 2b St Benedicts Court",
    "sg:city":"Huntingdon",
    "sg:classifiers":[
        {
            "category":"Shopping",
            "subcategory":"Clothing, Apparel, & Fashions",
            "type":"Retail Goods"
        }
    ],
    "sg:phone":"+44 1480 436300",
    "sg:postcode":"PE29 3PN",
    "sg:province":"Cambridgeshire",
    "sg:tags":[
        "shop"
    ],
    "wof:name":"Tatlas Clothing Ltd.",
    "wof:placetype":"venue"
},
  "geometry": {"coordinates":[-0.183809,52.329941],"type":"Point"}
}