{
  "type": "Feature",
  "properties": {
    "iso:country":"GB",
    "sg:address":"Sheffield Rd",
    "sg:city":"Rotherham",
    "sg:classifiers":[
        {
            "category":"Building & Trades",
            "subcategory":"Construction",
            "type":"Services"
        }
    ],
    "sg:phone":"+44 1709 835500",
    "sg:postcode":"S60 1BN",
    "sg:province":"South Yorkshire",
    "sg:tags":[
        "roofing"
    ],
    "wof:name":"Kesteven Roofing Centre",
    "wof:placetype":"venue"
},
  "geometry": {"coordinates":[-1.361209,53.425446],"type":"Point"}
}