{
  "type": "Feature",
  "properties": {
    "addr:full":"21 Willingham Road Market Rasen Lincolnshire LN8 3DP",
    "addr:housenumber":"21",
    "addr:postcode":"ln8 3dp",
    "addr:street":"Willingham Road",
    "iso:country":"GB",
    "sg:address":"21 Willingham Road",
    "sg:city":"Market Rasen",
    "sg:classifiers":[
        {
            "category":"Food & Beverages",
            "subcategory":"Meat & Fish",
            "type":"Retail Goods"
        }
    ],
    "sg:phone":"+44 1673 842437",
    "sg:postcode":"LN8 3DP",
    "sg:province":"Lincolnshire",
    "sg:tags":[
        "chip"
    ],
    "wof:name":"S  Beck",
    "wof:placetype":"venue"
},
  "geometry": {"coordinates":[-0.3324289918,53.3865242004],"type":"Point"}
}