{
  "type": "Feature",
  "properties": {
    "addr:full":"43 Handel Street Sneinton, Nottingham Nottingham Nottinghamshire NG3 1JE",
    "addr:housenumber":"43",
    "addr:postcode":"ng3 1je",
    "addr:street":"Handel Street",
    "iso:country":"GB",
    "sg:address":"43 Handel Street Sneinton, Nottingham",
    "sg:city":"Nottingham",
    "sg:classifiers":[
        {
            "category":"Professional",
            "subcategory":"Business Services",
            "type":"Services"
        }
    ],
    "sg:postcode":"NG3 1JE",
    "sg:province":"Nottinghamshire",
    "sg:tags":[
        "import",
        "export",
        "agent"
    ],
    "wof:name":"Here 2 There Ltd",
    "wof:placetype":"venue"
},
  "geometry": {"coordinates":[-1.1352889538,52.9554595947],"type":"Point"}
}