{
  "type": "Feature",
  "properties": {
    "addr:full":"Old Folkestone Road, Aycliffe Dover Kent CT17 9HB",
    "addr:postcode":"ct17 9hb",
    "addr:street":"Old Folkestone Road;Dover",
    "iso:country":"GB",
    "sg:address":"Old Folkestone Road, Aycliffe",
    "sg:city":"Dover",
    "sg:classifiers":[
        {
            "category":"Bars & Pubs",
            "type":"Food & Drink"
        }
    ],
    "sg:phone":"+44 1304 204756",
    "sg:postcode":"CT17 9HB",
    "sg:province":"Kent",
    "sg:tags":[
        "pubs",
        "inn"
    ],
    "wof:name":"The King Lear",
    "wof:placetype":"venue"
},
  "geometry": {"coordinates":[1.2904,51.112156],"type":"Point"}
}