{
  "type": "Feature",
  "properties": {
    "iso:country":"GB",
    "sg:address":"Purrett Road",
    "sg:city":"London",
    "sg:classifiers":[
        {
            "category":"Education",
            "subcategory":"School",
            "type":"Public Place"
        },
        {
            "category":"Government",
            "subcategory":"Office",
            "type":"Public Place"
        }
    ],
    "sg:phone":"+44 20 8854 2691",
    "sg:postcode":"SE18 1JR",
    "sg:province":"Greater London",
    "sg:tags":[
        "local",
        "authority"
    ],
    "wof:name":"Gallions Mount Primary School",
    "wof:placetype":"venue"
},
  "geometry": {"coordinates":[0.0984459966,51.4856452942],"type":"Point"}
}