{
  "type": "Feature",
  "properties": {
    "addr:full":"Llangurig Rd Llanidloes Powys SY18 6ES",
    "addr:postcode":"sy18 6es",
    "addr:street":"Llangurig Rd",
    "iso:country":"GB",
    "sg:address":"Llangurig Rd",
    "sg:city":"Llanidloes",
    "sg:classifiers":[
        {
            "category":"Food & Beverages",
            "subcategory":"Supermarket",
            "type":"Retail Goods"
        }
    ],
    "sg:phone":"+44 1686 413570",
    "sg:postcode":"SY18 6ES",
    "sg:province":"Powys",
    "wof:name":"Kwik Save Foodstores",
    "wof:placetype":"venue"
},
  "geometry": {"coordinates":[-3.5401659012,52.4459152222],"type":"Point"}
}