{
  "type": "Feature",
  "properties": {
    "iso:country":"GB",
    "sg:address":"Piccotts End Lane",
    "sg:city":"Hemel Hempstead",
    "sg:classifiers":[
        {
            "category":"Retail",
            "subcategory":"Event Space",
            "type":"Services"
        }
    ],
    "sg:phone":"+44 1442 230033",
    "sg:postcode":"HP2 6JH",
    "sg:province":"Hertfordshire",
    "sg:tags":[
        "exhibition",
        "organiser"
    ],
    "wof:name":"International Trade Shows Link Ltd.",
    "wof:placetype":"venue"
},
  "geometry": {"coordinates":[-0.47031,51.769882],"type":"Point"}
}