{
  "type": "Feature",
  "properties": {
    "addr:full":"Spencer Road Bradford West Yorkshire BD7 2LD",
    "addr:postcode":"bd7 2ld",
    "addr:street":"Spencer Road",
    "iso:country":"GB",
    "sg:address":"Spencer Road",
    "sg:city":"Bradford",
    "sg:classifiers":[
        {
            "category":"Autos & Motor Vehicles",
            "subcategory":"Fuel & Gas Station",
            "type":"Retail Goods"
        }
    ],
    "sg:phone":"+44 1274 521737",
    "sg:postcode":"BD7 2LD",
    "sg:province":"West Yorkshire",
    "sg:tags":[
        "petrol",
        "filling"
    ],
    "wof:name":"Save Service Station",
    "wof:placetype":"venue"
},
  "geometry": {"coordinates":[-1.779384017,53.7882881165],"type":"Point"}
}