{
  "type": "Feature",
  "properties": {
    "iso:country":"GB",
    "sg:address":"15 Chapelwell Street",
    "sg:city":"Saltcoats",
    "sg:classifiers":[
        {
            "category":"Cafe",
            "type":"Food & Drink"
        }
    ],
    "sg:phone":"+44 1294 602437",
    "sg:postcode":"KA21 5EB",
    "sg:province":"North Ayrshire",
    "sg:tags":[
        "tea",
        "room"
    ],
    "wof:name":"Delgrecos",
    "wof:placetype":"venue"
},
  "geometry": {"coordinates":[-4.7883090973,55.6337242126],"type":"Point"}
}