{
  "type": "Feature",
  "properties": {
    "addr:full":"Po Box 357 New Malden Surrey KT3 6WN",
    "addr:housenumber":"po;357",
    "addr:postcode":"kt3 6wn",
    "addr:street":"Box",
    "iso:country":"GB",
    "sg:address":"Po Box 357",
    "sg:city":"New Malden",
    "sg:classifiers":[
        {
            "category":"Professional",
            "subcategory":"Computer Services",
            "type":"Services"
        }
    ],
    "sg:phone":"+44 870 199 5108",
    "sg:postcode":"KT3 6WN",
    "sg:province":"Surrey",
    "sg:tags":[
        "system",
        "software"
    ],
    "wof:name":"Portland Communications Ltd.",
    "wof:placetype":"venue"
},
  "geometry": {"coordinates":[-0.256194,51.401772],"type":"Point"}
}