{
  "type": "Feature",
  "properties": {
    "addr:full":"14 The Vale, Shepherds Bush London Greater London W3 7SB",
    "addr:housenumber":"14",
    "addr:postcode":"w3 7sb",
    "addr:street":"The Vale",
    "iso:country":"GB",
    "sg:address":"14 The Vale, Shepherds Bush",
    "sg:city":"London",
    "sg:classifiers":[
        {
            "category":"Building & Trades",
            "subcategory":"Equipment Rental",
            "type":"Services"
        }
    ],
    "sg:phone":"+44 20 8743 6300",
    "sg:postcode":"W3 7SB",
    "sg:province":"Greater London",
    "sg:tags":[
        "hire",
        "centre"
    ],
    "wof:name":"H S S Hire Shops",
    "wof:placetype":"venue"
},
  "geometry": {"coordinates":[-0.246266,51.50687],"type":"Point"}
}