{
  "type": "Feature",
  "properties": {
    "addr:full":"3 Cavendish Rd, Ellesmere Park, Eccles Manchester Greater Manchester M30 9JZ",
    "addr:housenumber":"3",
    "addr:postcode":"m30 9jz",
    "addr:street":"Cavendish Rd Ellesmere Park",
    "iso:country":"GB",
    "sg:address":"3 Cavendish Rd, Ellesmere Park, Eccles",
    "sg:city":"Manchester",
    "sg:classifiers":[
        {
            "category":"Building & Trades",
            "subcategory":"Construction",
            "type":"Services"
        }
    ],
    "sg:phone":"+44 161 788 8194",
    "sg:postcode":"M30 9JZ",
    "sg:province":"Greater Manchester",
    "sg:tags":[
        "decorator",
        "painter"
    ],
    "wof:name":"Tom Redshaw & Son",
    "wof:placetype":"venue"
},
  "geometry": {"coordinates":[-2.347116,53.489555],"type":"Point"}
}