{
  "type": "Feature",
  "properties": {
    "iso:country":"GB",
    "sg:address":"Watson House Care Home, 50 Station Road",
    "sg:city":"Blackpool",
    "sg:classifiers":[
        {
            "category":"Social Services",
            "subcategory":"Retirement Home",
            "type":"Services"
        }
    ],
    "sg:phone":"+44 1253 341550",
    "sg:postcode":"FY4 1EU",
    "sg:province":"Lancashire",
    "sg:tags":[
        "rest"
    ],
    "wof:name":"Watson House",
    "wof:placetype":"venue"
},
  "geometry": {"coordinates":[-3.0523989201,53.7959785461],"type":"Point"}
}