{
  "type": "Feature",
  "properties": {
    "addr:full":"Station Rd, Belton Great Yarmouth Norfolk NR31 9NB",
    "addr:postcode":"nr31 9nb",
    "addr:street":"Station Rd;Great Yarmouth",
    "iso:country":"GB",
    "sg:address":"Station Rd, Belton",
    "sg:city":"Great Yarmouth",
    "sg:classifiers":[
        {
            "category":"Travel",
            "subcategory":"Hotels & Motels",
            "type":"Entertainment"
        },
        {
            "category":"Recreation",
            "subcategory":"Campground",
            "type":"Entertainment"
        }
    ],
    "sg:phone":"+44 1493 781234",
    "sg:postcode":"NR31 9NB",
    "sg:province":"Norfolk",
    "sg:tags":[
        "holiday",
        "self",
        "camp",
        "catering",
        "centre"
    ],
    "wof:name":"Blue Sky Caravan Park",
    "wof:placetype":"venue"
},
  "geometry": {"coordinates":[1.7277749777,52.5393562317],"type":"Point"}
}