{
  "type": "Feature",
  "properties": {
    "iso:country":"GB",
    "sg:address":"218 Town Lane, Bebington",
    "sg:city":"Wirral",
    "sg:classifiers":[
        {
            "category":"Banks & Credit Unions",
            "subcategory":"Bank",
            "type":"Services"
        }
    ],
    "sg:phone":"+44 845 740 4404",
    "sg:postcode":"CH63 8LG",
    "sg:province":"Merseyside",
    "sg:tags":[
        "financial",
        "institution"
    ],
    "sg:website":"http://www.hsbc.co.uk",
    "wof:name":"Hsbc Bank Plc",
    "wof:placetype":"venue"
},
  "geometry": {"coordinates":[-3.023916,53.356033],"type":"Point"}
}