{
  "type": "Feature",
  "properties": {
    "iso:country":"GB",
    "sg:address":"Gas Showroom, Albert Walk",
    "sg:city":"Spalding",
    "sg:classifiers":[
        {
            "category":"Building & Trades",
            "subcategory":"Plumbing",
            "type":"Services"
        }
    ],
    "sg:phone":"+44 1406 422368",
    "sg:postcode":"PE12 7DP",
    "sg:province":"Cambridgeshire",
    "sg:tags":[
        "central",
        "heating"
    ],
    "wof:name":"E G & L B Martin Ltd.",
    "wof:placetype":"venue"
},
  "geometry": {"coordinates":[0.01554,52.802601],"type":"Point"}
}