{
  "type": "Feature",
  "properties": {
    "addr:full":"Grange La Stourbridge West Midlands DY9 7HJ",
    "addr:postcode":"dy9 7hj",
    "addr:street":"Grange La Stourbridge West",
    "iso:country":"GB",
    "sg:address":"Grange La",
    "sg:city":"Stourbridge",
    "sg:classifiers":[
        {
            "category":"Bars & Pubs",
            "type":"Food & Drink"
        }
    ],
    "sg:phone":"+44 1384 422061",
    "sg:postcode":"DY9 7HJ",
    "sg:province":"West Midlands",
    "sg:tags":[
        "pubs",
        "inn"
    ],
    "wof:name":"Noahs Ark The",
    "wof:placetype":"venue"
},
  "geometry": {"coordinates":[-2.1256101131,52.4528617859],"type":"Point"}
}