{
  "type": "Feature",
  "properties": {
    "iso:country":"GB",
    "sg:address":"34 Clarkston Road",
    "sg:city":"Glasgow",
    "sg:classifiers":[
        {
            "category":"Bars & Pubs",
            "type":"Food & Drink"
        },
        {
            "category":"Community Center",
            "subcategory":"Social",
            "type":"Public Place"
        }
    ],
    "sg:phone":"+44 141 633 3585",
    "sg:postcode":"G44 3QH",
    "sg:province":"East Renfrewshire",
    "sg:tags":[
        "pubs",
        "house",
        "inn",
        "activity"
    ],
    "wof:name":"Beechings Public House",
    "wof:placetype":"venue"
},
  "geometry": {"coordinates":[-4.262792,55.816952],"type":"Point"}
}