{
  "type": "Feature",
  "properties": {
    "addr:full":"105 Streatham Hill London Greater London SW2 4UG",
    "addr:housenumber":"105",
    "addr:postcode":"sw2 4ug",
    "addr:street":"Streatham Hill",
    "iso:country":"GB",
    "sg:address":"105 Streatham Hill",
    "sg:city":"London",
    "sg:classifiers":[
        {
            "category":"Professional",
            "subcategory":"Employment Agencies",
            "type":"Services"
        }
    ],
    "sg:phone":"+44 20 8671 2711",
    "sg:postcode":"SW2 4UG",
    "sg:province":"Greater London",
    "sg:tags":[
        "consultant"
    ],
    "wof:name":"Blue Arrow Ltd.",
    "wof:placetype":"venue"
},
  "geometry": {"coordinates":[-0.126362,51.438591],"type":"Point"}
}