{
  "type": "Feature",
  "properties": {
    "iso:country":"GB",
    "sg:address":"Thimbler Road",
    "sg:city":"Coventry",
    "sg:classifiers":[
        {
            "category":"Social Services",
            "subcategory":"Adult Care",
            "type":"Services"
        }
    ],
    "sg:phone":"+44 24 8071 1482",
    "sg:postcode":"CV4 8HG",
    "sg:province":"Warwickshire",
    "sg:tags":[
        "housing",
        "sheltered"
    ],
    "wof:name":"George Rowley House",
    "wof:placetype":"venue"
},
  "geometry": {"coordinates":[-1.5595289469,52.3928184509],"type":"Point"}
}