{
  "type": "Feature",
  "properties": {
    "iso:country":"GB",
    "sg:address":"37 Alma Rd",
    "sg:city":"Carshalton",
    "sg:classifiers":[
        {
            "category":"Building & Trades",
            "subcategory":"Construction",
            "type":"Services"
        }
    ],
    "sg:phone":"+44 20 8643 4305",
    "sg:postcode":"SM5 2PQ",
    "sg:province":"Surrey",
    "sg:tags":[
        "builder"
    ],
    "wof:name":"Carshalton Construction Co",
    "wof:placetype":"venue"
},
  "geometry": {"coordinates":[-0.172036,51.364643],"type":"Point"}
}