{
  "type": "Feature",
  "properties": {
    "addr:full":"87 Lygate Road Burnley Lancashire BB10 2DU",
    "addr:housenumber":"87",
    "addr:postcode":"bb10 2du",
    "addr:street":"Lygate Road",
    "iso:country":"GB",
    "sg:address":"87 Lygate Road",
    "sg:city":"Burnley",
    "sg:classifiers":[
        {
            "category":"Manufacturing",
            "subcategory":"Building Materials",
            "type":"Manufacturing & Wholesale Goods"
        }
    ],
    "sg:phone":"+44 1282 422122",
    "sg:postcode":"BB10 2DU",
    "sg:province":"Lancashire",
    "sg:tags":[
        "gate",
        "mnfrs"
    ],
    "wof:name":"Pendle Forge",
    "wof:placetype":"venue"
},
  "geometry": {"coordinates":[-2.2076001167,53.809463501],"type":"Point"}
}