{
  "type": "Feature",
  "properties": {
    "iso:country":"GB",
    "sg:address":"Toft Lodge Farm",
    "sg:city":"Bourne",
    "sg:classifiers":[
        {
            "category":"Farming",
            "subcategory":"Livestock Farm",
            "type":"Manufacturing & Wholesale Goods"
        }
    ],
    "sg:phone":"+44 1778 422196",
    "sg:postcode":"PE10 0JY",
    "sg:province":"Lincolnshire",
    "sg:tags":[
        "others"
    ],
    "wof:name":"W Baldock & Son",
    "wof:placetype":"venue"
},
  "geometry": {"coordinates":[-0.415574,52.742119],"type":"Point"}
}