{
  "type": "Feature",
  "properties": {
    "iso:country":"GB",
    "sg:address":"409 Birchfield Rd, Webheath",
    "sg:city":"Redditch",
    "sg:classifiers":[
        {
            "category":"Building & Trades",
            "subcategory":"Construction",
            "type":"Services"
        }
    ],
    "sg:phone":"+44 1527 403341",
    "sg:postcode":"B97 4NF",
    "sg:province":"Warwickshire",
    "sg:tags":[
        "builder"
    ],
    "wof:name":"R.P Melley",
    "wof:placetype":"venue"
},
  "geometry": {"coordinates":[-1.968983,52.30027],"type":"Point"}
}