{
  "type": "Feature",
  "properties": {
    "addr:full":"Central Office, Paycocke Road Basildon Essex SS14 3HP",
    "addr:postcode":"ss14 3hp",
    "addr:street":"Paycocke Road",
    "iso:country":"GB",
    "sg:address":"Central Office, Paycocke Road",
    "sg:city":"Basildon",
    "sg:classifiers":[
        {
            "category":"Building & Trades",
            "subcategory":"Electrical",
            "type":"Services"
        }
    ],
    "sg:postcode":"SS14 3HP",
    "sg:province":"Essex",
    "sg:tags":[
        "lighting"
    ],
    "wof:name":"Leyton Lighting",
    "wof:placetype":"venue"
},
  "geometry": {"coordinates":[0.4708400071,51.5854911804],"type":"Point"}
}