{
  "type": "Feature",
  "properties": {
    "addr:full":"101 Battersea Park Rd, Battersea South Lambeth Greater London SW8 4DS",
    "addr:housenumber":"101",
    "addr:postcode":"sw8 4ds",
    "addr:street":"Battersea Park Rd",
    "iso:country":"GB",
    "sg:address":"101 Battersea Park Rd, Battersea",
    "sg:city":"South Lambeth",
    "sg:classifiers":[
        {
            "category":"Bars & Pubs",
            "type":"Food & Drink"
        }
    ],
    "sg:phone":"+44 20 7627 2911",
    "sg:postcode":"SW8 4DS",
    "sg:province":"Greater London",
    "sg:tags":[
        "pubs",
        "house",
        "inn",
        "public",
        "activity"
    ],
    "wof:name":"Duchess Of York",
    "wof:placetype":"venue"
},
  "geometry": {"coordinates":[-0.1424760073,51.4792327881],"type":"Point"}
}