{
  "type": "Feature",
  "properties": {
    "iso:country":"GB",
    "sg:address":"14 Regent Road",
    "sg:city":"Blackpool",
    "sg:classifiers":[
        {
            "category":"Travel",
            "subcategory":"Hotels & Motels",
            "type":"Entertainment"
        }
    ],
    "sg:postcode":"FY1 4LY",
    "sg:province":"Lancashire",
    "wof:name":"Victoria House",
    "wof:placetype":"venue"
},
  "geometry": {"coordinates":[-3.0460729599,53.8173980713],"type":"Point"}
}