{
  "type": "Feature",
  "properties": {
    "addr:full":"Ciceley Mill Farm, Rostherne Knutsford Cheshire WA16 6RB",
    "addr:housenumber":"rostherne",
    "addr:postcode":"wa16 6rb",
    "iso:country":"GB",
    "sg:address":"Ciceley Mill Farm, Rostherne",
    "sg:city":"Knutsford",
    "sg:classifiers":[
        {
            "category":"Farming",
            "subcategory":"Livestock Farm",
            "type":"Manufacturing & Wholesale Goods"
        }
    ],
    "sg:postcode":"WA16 6RB",
    "sg:province":"Cheshire",
    "sg:tags":[
        "others"
    ],
    "wof:name":"J Gate",
    "wof:placetype":"venue"
},
  "geometry": {"coordinates":[-2.371164,53.351814],"type":"Point"}
}