{
  "type": "Feature",
  "properties": {
    "addr:full":"First Floor Rowan Ho, Westwood Way, Westwood Business Park Coventry Warwickshire CV4 8LE",
    "addr:postcode":"cv4 8le",
    "addr:street":"Westwood Way;Business Park",
    "iso:country":"GB",
    "sg:address":"First Floor Rowan Ho, Westwood Way, Westwood Business Park",
    "sg:city":"Coventry",
    "sg:classifiers":[
        {
            "category":"Banks & Credit Unions",
            "subcategory":"Bank",
            "type":"Services"
        }
    ],
    "sg:phone":"+44 24 7669 4944",
    "sg:postcode":"CV4 8LE",
    "sg:province":"Warwickshire",
    "wof:name":"NatWest",
    "wof:placetype":"venue"
},
  "geometry": {"coordinates":[-1.577493,52.387718],"type":"Point"}
}