{
  "type": "Feature",
  "properties": {
    "iso:country":"GB",
    "sg:address":"Suite 312 India Mill Busns Cntr",
    "sg:city":"Darwen",
    "sg:classifiers":[
        {
            "category":"Professional",
            "subcategory":"Computer Services",
            "type":"Services"
        }
    ],
    "sg:phone":"+44 1254 708340",
    "sg:postcode":"BB3 1AE",
    "sg:province":"Lancashire",
    "sg:tags":[
        "system",
        "software"
    ],
    "wof:name":"ACCESS2.Co.Uk",
    "wof:placetype":"venue"
},
  "geometry": {"coordinates":[-2.4671690464,53.6941986084],"type":"Point"}
}