{
  "type": "Feature",
  "properties": {
    "addr:full":"Mile Rd Bedford Bedfordshire MK42 9TW",
    "addr:postcode":"mk42 9tw",
    "addr:street":"Mile Rd",
    "iso:country":"GB",
    "sg:address":"Mile Rd",
    "sg:city":"Bedford",
    "sg:classifiers":[
        {
            "category":"Government",
            "subcategory":"Post Office",
            "type":"Public Place"
        }
    ],
    "sg:phone":"+44 1234 271557",
    "sg:postcode":"MK42 9TW",
    "sg:province":"Bedfordshire",
    "sg:tags":[
        "messenger",
        "courier"
    ],
    "wof:name":"Initial City Link",
    "wof:placetype":"venue"
},
  "geometry": {"coordinates":[-0.4663490057,52.1194610596],"type":"Point"}
}