{
  "type": "Feature",
  "properties": {
    "addr:full":"301 New Kings Road London Greater London SW6 4RE",
    "addr:housenumber":"301",
    "addr:postcode":"sw6 4re",
    "addr:street":"New Kings Road",
    "iso:country":"GB",
    "sg:address":"301 New Kings Road",
    "sg:city":"London",
    "sg:classifiers":[
        {
            "category":"Home & Garden",
            "subcategory":"Furniture",
            "type":"Retail Goods"
        }
    ],
    "sg:phone":"+44 20 7731 4315",
    "sg:postcode":"SW6 4RE",
    "sg:province":"Greater London",
    "wof:name":"Frontever Ltd.",
    "wof:placetype":"venue"
},
  "geometry": {"coordinates":[-0.203282,51.472107],"type":"Point"}
}