{
  "type": "Feature",
  "properties": {
    "addr:full":"17 Oglander Road London Greater London SE15 4EQ",
    "addr:housenumber":"17",
    "addr:postcode":"se15 4eq",
    "addr:street":"Oglander Road",
    "iso:country":"GB",
    "sg:address":"17 Oglander Road",
    "sg:city":"London",
    "sg:classifiers":[
        {
            "category":"Bars & Pubs",
            "type":"Food & Drink"
        }
    ],
    "sg:postcode":"SE15 4EQ",
    "sg:province":"Greater London",
    "sg:tags":[
        "pubs",
        "inn"
    ],
    "wof:name":"The Oglander",
    "wof:placetype":"venue"
},
  "geometry": {"coordinates":[-0.073302,51.465229],"type":"Point"}
}