{
  "type": "Feature",
  "properties": {
    "iso:country":"GB",
    "sg:address":"39 Weston Road",
    "sg:city":"Stoke On Trent",
    "sg:classifiers":[
        {
            "category":"Fast Food",
            "type":"Food & Drink"
        }
    ],
    "sg:phone":"+44 1782 596116",
    "sg:postcode":"ST3 6AB",
    "sg:province":"Staffordshire",
    "sg:tags":[
        "away",
        "take"
    ],
    "wof:name":"Flames Kebab Ho",
    "wof:placetype":"venue"
},
  "geometry": {"coordinates":[-2.1031610966,52.9784927368],"type":"Point"}
}