{
  "type": "Feature",
  "properties": {
    "iso:country":"GB",
    "sg:address":"20 High Street",
    "sg:city":"Dover",
    "sg:classifiers":[
        {
            "category":"Health Services",
            "subcategory":"Optometrist",
            "type":"Services"
        },
        {
            "category":"Shopping",
            "subcategory":"Optician",
            "type":"Retail Goods"
        }
    ],
    "sg:phone":"+44 1304 206665",
    "sg:postcode":"CT16 1DR",
    "sg:province":"Kent",
    "sg:tags":[
        "ophthalmic"
    ],
    "wof:name":"N J Bailey Opticians",
    "wof:placetype":"venue"
},
  "geometry": {"coordinates":[1.308199,51.128483],"type":"Point"}
}