{
  "type": "Feature",
  "properties": {
    "iso:country":"GB",
    "sg:address":"6 Trafford Walk, Hillheads Estate, Westerhope",
    "sg:city":"Newcastle Upon Tyne",
    "sg:classifiers":[
        {
            "category":"Building & Trades",
            "subcategory":"Construction",
            "type":"Services"
        }
    ],
    "sg:phone":"+44 191 267 3467",
    "sg:postcode":"NE5 5NT",
    "sg:province":"Tyne and Wear",
    "sg:tags":[
        "decorator",
        "painter"
    ],
    "wof:name":"Ian Burnell",
    "wof:placetype":"venue"
},
  "geometry": {"coordinates":[-1.703142,54.998497],"type":"Point"}
}