{
  "type": "Feature",
  "properties": {
    "addr:full":"Cellphone Ho, North Circular Rd Willesden Greater London NW10 7SH",
    "addr:postcode":"nw10 7sh",
    "addr:street":"North Circular Rd",
    "iso:country":"GB",
    "sg:address":"Cellphone Ho, North Circular Rd",
    "sg:city":"Willesden",
    "sg:classifiers":[
        {
            "category":"Utilities",
            "subcategory":"Telephone",
            "type":"Services"
        }
    ],
    "sg:phone":"+44 20 8961 7000",
    "sg:postcode":"NW10 7SH",
    "sg:province":"Greater London",
    "sg:tags":[
        "telecommunication"
    ],
    "wof:name":"Zoo Direct",
    "wof:placetype":"venue"
},
  "geometry": {"coordinates":[-0.28125,51.5387992859],"type":"Point"}
}