{
  "type": "Feature",
  "properties": {
    "iso:country":"GB",
    "sg:address":"2 Marchhall Road",
    "sg:city":"Edinburgh",
    "sg:classifiers":[
        {
            "category":"Health Services",
            "subcategory":"Nursing And Care Facility",
            "type":"Services"
        }
    ],
    "sg:postcode":"EH16 5HR",
    "sg:province":"City of Edinburgh",
    "sg:tags":[
        "home"
    ],
    "wof:name":"Queen's Park Nursing Home Ltd.",
    "wof:placetype":"venue"
},
  "geometry": {"coordinates":[-3.167588,55.936935],"type":"Point"}
}