{
  "type": "Feature",
  "properties": {
    "addr:full":"Uckfield Road, Ringmer Lewes East Sussex BN8 5RP",
    "addr:postcode":"bn8 5rp",
    "addr:street":"Uckfield Road",
    "iso:country":"GB",
    "sg:address":"Uckfield Road, Ringmer",
    "sg:city":"Lewes",
    "sg:classifiers":[
        {
            "category":"Retail",
            "subcategory":"Auto Repair",
            "type":"Services"
        }
    ],
    "sg:phone":"+44 1273 812121",
    "sg:postcode":"BN8 5RP",
    "sg:province":"East Sussex",
    "sg:tags":[
        "modification",
        "garage"
    ],
    "wof:name":"Winstons",
    "wof:placetype":"venue"
},
  "geometry": {"coordinates":[0.0452199988,50.9020004272],"type":"Point"}
}