{
  "type": "Feature",
  "properties": {
    "addr:full":"24 Bury New Road, Prestwich Manchester Greater Manchester M25 0LD",
    "addr:housenumber":"24",
    "addr:postcode":"m25 0ld",
    "addr:street":"Bury New Road",
    "iso:country":"GB",
    "sg:address":"24 Bury New Road, Prestwich",
    "sg:city":"Manchester",
    "sg:classifiers":[
        {
            "category":"Food & Beverages",
            "subcategory":"Bakery",
            "type":"Retail Goods"
        }
    ],
    "sg:phone":"+44 161 773 7997",
    "sg:postcode":"M25 0LD",
    "sg:province":"Greater Manchester",
    "sg:tags":[
        "baker"
    ],
    "wof:name":"Crusty Corner",
    "wof:placetype":"venue"
},
  "geometry": {"coordinates":[-2.271495,53.518108],"type":"Point"}
}