{
  "type": "Feature",
  "properties": {
    "iso:country":"GB",
    "sg:address":"Sough Hall Avenue, Thorpe Hesley",
    "sg:city":"Rotherham",
    "sg:classifiers":[
        {
            "category":"Health Services",
            "subcategory":"Doctor",
            "type":"Services"
        }
    ],
    "sg:phone":"+44 114 245 6192",
    "sg:postcode":"S61 2QP",
    "sg:province":"South Yorkshire",
    "sg:tags":[
        "practitioners"
    ],
    "wof:name":"Thorpe Hesley Health Clinic",
    "wof:placetype":"venue"
},
  "geometry": {"coordinates":[-1.435834,53.460442],"type":"Point"}
}