{
  "type": "Feature",
  "properties": {
    "iso:country":"GB",
    "sg:address":"High View House",
    "sg:city":"London",
    "sg:classifiers":[
        {
            "category":"Building & Trades",
            "subcategory":"Construction",
            "type":"Services"
        }
    ],
    "sg:phone":"+44 20 7267 4366",
    "sg:postcode":"NW5 1TN",
    "sg:province":"Greater London",
    "sg:tags":[
        "contractor"
    ],
    "wof:name":"Murphy Homes Ltd.",
    "wof:placetype":"venue"
},
  "geometry": {"coordinates":[-0.087914,51.50737],"type":"Point"}
}