{
  "type": "Feature",
  "properties": {
    "iso:country":"GB",
    "sg:address":"25 Hyde Gardens",
    "sg:city":"Eastbourne",
    "sg:classifiers":[
        {
            "category":"Education",
            "subcategory":"Special Training",
            "type":"Public Place"
        }
    ],
    "sg:phone":"+44 1323 744020",
    "sg:postcode":"BN21 4PX",
    "sg:province":"East Sussex",
    "sg:tags":[
        "school",
        "language"
    ],
    "wof:name":"Jurgen Matthes Student Organisation",
    "wof:placetype":"venue"
},
  "geometry": {"coordinates":[0.282628,50.767502],"type":"Point"}
}