{
  "type": "Feature",
  "properties": {
    "addr:full":"368 Aigburth Road Liverpool Merseyside L17 6AE",
    "addr:housenumber":"368",
    "addr:postcode":"l17 6ae",
    "addr:street":"Aigburth Road",
    "iso:country":"GB",
    "sg:address":"368 Aigburth Road",
    "sg:city":"Liverpool",
    "sg:classifiers":[
        {
            "category":"Food & Beverages",
            "subcategory":"Bakery",
            "type":"Retail Goods"
        }
    ],
    "sg:phone":"+44 151 281 8118",
    "sg:postcode":"L17 6AE",
    "sg:province":"Merseyside",
    "sg:tags":[
        "baker"
    ],
    "wof:name":"Cottage Loaf",
    "wof:placetype":"venue"
},
  "geometry": {"coordinates":[-2.9258539677,53.36743927],"type":"Point"}
}