{
  "type": "Feature",
  "properties": {
    "addr:full":"30 School Crescent, Godshill Ventnor Isle of Wight PO38 3JL",
    "addr:housenumber":"30",
    "addr:postcode":"po38 3jl",
    "addr:street":"School Crescent",
    "iso:country":"GB",
    "sg:address":"30 School Crescent, Godshill",
    "sg:city":"Ventnor",
    "sg:classifiers":[
        {
            "category":"Professional",
            "subcategory":"Accounting & Tax Preparation",
            "type":"Services"
        }
    ],
    "sg:phone":"+44 1983 840566",
    "sg:postcode":"PO38 3JL",
    "sg:province":"Isle of Wight",
    "sg:tags":[
        "accountant"
    ],
    "wof:name":"Allen Book Keeping",
    "wof:placetype":"venue"
},
  "geometry": {"coordinates":[-1.25571,50.636166],"type":"Point"}
}