{
  "type": "Feature",
  "properties": {
    "iso:country":"GB",
    "sg:address":"Coronation Mills, Cottam Avenue",
    "sg:city":"Bradford",
    "sg:classifiers":[
        {
            "category":"Shopping",
            "subcategory":"Crafts & Fabrics",
            "type":"Retail Goods"
        }
    ],
    "sg:phone":"+44 1274 576611",
    "sg:postcode":"BD7 2BT",
    "sg:province":"West Yorkshire",
    "sg:tags":[
        "material",
        "art"
    ],
    "wof:name":"Gorji Alliance Ltd.",
    "wof:placetype":"venue"
},
  "geometry": {"coordinates":[-1.77663,53.790649],"type":"Point"}
}