{
  "type": "Feature",
  "properties": {
    "addr:full":"42 Bickford Road Birmingham West Midlands B6 7EE",
    "addr:housenumber":"42",
    "addr:postcode":"b6 7ee",
    "addr:street":"Bickford Road",
    "iso:country":"GB",
    "sg:address":"42 Bickford Road",
    "sg:city":"Birmingham",
    "sg:classifiers":[
        {
            "category":"Utilities",
            "subcategory":"Electric",
            "type":"Services"
        }
    ],
    "sg:postcode":"B6 7EE",
    "sg:province":"West Midlands",
    "sg:tags":[
        "electrical",
        "contractor"
    ],
    "wof:name":"The Appliance Testing Co",
    "wof:placetype":"venue"
},
  "geometry": {"coordinates":[-1.8757770061,52.5109024048],"type":"Point"}
}