{
  "type": "Feature",
  "properties": {
    "iso:country":"GB",
    "sg:address":"Unit A, Whitehill Rd, Whitehill Ind Est",
    "sg:city":"Glenrothes",
    "sg:classifiers":[
        {
            "category":"Building & Trades",
            "subcategory":"Landscaping Services",
            "type":"Services"
        }
    ],
    "sg:phone":"+44 1592 772202",
    "sg:postcode":"KY6 2RP",
    "sg:province":"Fife",
    "sg:tags":[
        "horticultural"
    ],
    "wof:name":"Inpots Euro Ltd",
    "wof:placetype":"venue"
},
  "geometry": {"coordinates":[-3.204794,56.183681],"type":"Point"}
}