{
  "type": "Feature",
  "properties": {
    "iso:country":"GB",
    "sg:address":"Westgate End",
    "sg:city":"Wakefield",
    "sg:classifiers":[
        {
            "category":"Professional",
            "subcategory":"Computer Services",
            "type":"Services"
        }
    ],
    "sg:phone":"+44 1924 332373",
    "sg:postcode":"WF2 9RL",
    "sg:province":"West Yorkshire",
    "sg:tags":[
        "system",
        "software"
    ],
    "wof:name":"Microtech Services Ltd.",
    "wof:placetype":"venue"
},
  "geometry": {"coordinates":[-1.509234,53.680214],"type":"Point"}
}