{
  "type": "Feature",
  "properties": {
    "iso:country":"GB",
    "sg:address":"Unit 8, Paxton Court",
    "sg:city":"Newark",
    "sg:classifiers":[
        {
            "category":"Shopping",
            "subcategory":"Pets & Pet Supplies",
            "type":"Retail Goods"
        }
    ],
    "sg:phone":"+44 1636 679628",
    "sg:postcode":"NG24 1DH",
    "sg:province":"Nottinghamshire",
    "wof:name":"Animal Magic",
    "wof:placetype":"venue"
},
  "geometry": {"coordinates":[-0.809827,53.078018],"type":"Point"}
}