{
  "type": "Feature",
  "properties": {
    "addr:full":"84 Harlesden Gardens, Harlesden London Greater London NW10 4HA",
    "addr:housenumber":"84",
    "addr:postcode":"nw10 4ha",
    "addr:street":"Harlesden Gardens Harlesden",
    "iso:country":"GB",
    "sg:address":"84 Harlesden Gardens, Harlesden",
    "sg:city":"London",
    "sg:classifiers":[
        {
            "category":"Organizations",
            "subcategory":"Membership Organization",
            "type":"Services"
        }
    ],
    "sg:postcode":"NW10 4HA",
    "sg:province":"Greater London",
    "sg:tags":[
        "club"
    ],
    "wof:name":"Gold Arrow Management Ltd",
    "wof:placetype":"venue"
},
  "geometry": {"coordinates":[-0.2459799945,51.5396232605],"type":"Point"}
}