{
  "type": "Feature",
  "properties": {
    "addr:full":"4 Poplar Terrace, Chapel-en-le-frith High Peak Cheshire SK23 0JR",
    "addr:housenumber":"4",
    "addr:postcode":"sk23 0jr",
    "addr:street":"Poplar Terrace",
    "iso:country":"GB",
    "sg:address":"4 Poplar Terrace, Chapel-en-le-frith",
    "sg:city":"High Peak",
    "sg:classifiers":[
        {
            "category":"Taxi",
            "type":"Transportation"
        },
        {
            "category":"Military Area",
            "subcategory":"Air Force Base",
            "type":"Public Place"
        }
    ],
    "sg:phone":"+44 1298 814863",
    "sg:postcode":"SK23 0JR",
    "sg:province":"Cheshire",
    "sg:tags":[
        "mini",
        "hire",
        "private",
        "cab"
    ],
    "wof:name":"Ian's Private Hire",
    "wof:placetype":"venue"
},
  "geometry": {"coordinates":[-1.912164,53.327034],"type":"Point"}
}