{
  "type": "Feature",
  "properties": {
    "iso:country":"GB",
    "sg:address":"Glovers Brow",
    "sg:city":"Liverpool",
    "sg:classifiers":[
        {
            "category":"Bars & Pubs",
            "type":"Food & Drink"
        },
        {
            "category":"Community Center",
            "subcategory":"Social",
            "type":"Public Place"
        }
    ],
    "sg:phone":"+44 151 546 1046",
    "sg:postcode":"L32 2AD",
    "sg:province":"Merseyside",
    "sg:tags":[
        "pubs",
        "house",
        "inn",
        "activity"
    ],
    "wof:name":"The Railway",
    "wof:placetype":"venue"
},
  "geometry": {"coordinates":[-2.901749,53.487141],"type":"Point"}
}