{
  "type": "Feature",
  "properties": {
    "addr:full":"The Old Skill Centre, Doncaster Rd Wakefield West Yorkshire WF1 5EA",
    "addr:postcode":"wf1 5ea",
    "addr:street":"Doncaster Rd",
    "iso:country":"GB",
    "sg:address":"The Old Skill Centre, Doncaster Rd",
    "sg:city":"Wakefield",
    "sg:classifiers":[
        {
            "category":"Retail",
            "subcategory":"Auto Repair",
            "type":"Services"
        }
    ],
    "sg:phone":"+44 1924 369263",
    "sg:postcode":"WF1 5EA",
    "sg:province":"West Yorkshire",
    "sg:tags":[
        "modification",
        "garage"
    ],
    "wof:name":"Millenium Car Sales",
    "wof:placetype":"venue"
},
  "geometry": {"coordinates":[-1.4879100323,53.6748008728],"type":"Point"}
}