{
  "type": "Feature",
  "properties": {
    "iso:country":"GB",
    "sg:address":"30 Newton Crescent",
    "sg:city":"Arbroath",
    "sg:classifiers":[
        {
            "category":"Recreation",
            "type":"Entertainment"
        }
    ],
    "sg:phone":"+44 1241 878149",
    "sg:postcode":"DD11 3JZ",
    "sg:province":"Angus",
    "sg:tags":[
        "outdoor",
        "pursuit"
    ],
    "wof:name":"Melee Paintball Wargames",
    "wof:placetype":"venue"
},
  "geometry": {"coordinates":[-2.615601,56.570747],"type":"Point"}
}