{
  "type": "Feature",
  "properties": {
    "iso:country":"GB",
    "sg:address":"14 Malpas Dr",
    "sg:city":"Pinner",
    "sg:classifiers":[
        {
            "category":"Professional",
            "subcategory":"Management & Consulting",
            "type":"Services"
        }
    ],
    "sg:phone":"+44 20 8429 4740",
    "sg:postcode":"HA5 1DG",
    "sg:province":"Greater London",
    "sg:tags":[
        "consultant",
        "energy",
        "conservation"
    ],
    "wof:name":"Kelly Paul",
    "wof:placetype":"venue"
},
  "geometry": {"coordinates":[-0.3882040083,51.5871200562],"type":"Point"}
}