{
  "type": "Feature",
  "properties": {
    "iso:country":"GB",
    "sg:address":"17 Fleet Street",
    "sg:city":"London",
    "sg:classifiers":[
        {
            "category":"Organizations",
            "subcategory":"Membership Organization",
            "type":"Services"
        }
    ],
    "sg:phone":"+44 20 7583 7733",
    "sg:postcode":"EC4Y 1AA",
    "sg:province":"Greater London",
    "sg:tags":[
        "club"
    ],
    "wof:name":"Commonwealth Press Union",
    "wof:placetype":"venue"
},
  "geometry": {"coordinates":[-0.110863,51.513805],"type":"Point"}
}