{
  "type": "Feature",
  "properties": {
    "iso:country":"GB",
    "sg:address":"23 Litcham Road, Mileham",
    "sg:city":"King's Lynn",
    "sg:classifiers":[
        {
            "category":"Real Estate",
            "subcategory":"Architect",
            "type":"Services"
        }
    ],
    "sg:phone":"+44 1328 701779",
    "sg:postcode":"PE32 2PS",
    "sg:province":"Norfolk",
    "sg:tags":[
        "architectural"
    ],
    "wof:name":"J W M Design",
    "wof:placetype":"venue"
},
  "geometry": {"coordinates":[0.83159,52.736622],"type":"Point"}
}