{
  "type": "Feature",
  "properties": {
    "addr:full":"1-2 Tilley Road, Crowther Washington Durham NE38 0AE",
    "addr:housenumber":"1-2",
    "addr:postcode":"ne38 0ae",
    "addr:street":"Tilley Road",
    "iso:country":"GB",
    "sg:address":"1-2 Tilley Road, Crowther",
    "sg:city":"Washington",
    "sg:classifiers":[
        {
            "category":"Professional",
            "subcategory":"Engineering",
            "type":"Services"
        }
    ],
    "sg:phone":"+44 191 416 1689",
    "sg:postcode":"NE38 0AE",
    "sg:province":"Durham",
    "sg:tags":[
        "electronic",
        "engineer"
    ],
    "sg:website":"http://www.ronan.com",
    "wof:name":"Ronan Engineering Ltd",
    "wof:placetype":"venue"
},
  "geometry": {"coordinates":[-1.5536819696,54.8991851807],"type":"Point"}
}