{
  "type": "Feature",
  "properties": {
    "addr:full":"The Galleries, Washington Centre Washington Durham NE38 7SD",
    "addr:postcode":"ne38 7sd",
    "addr:street":"Washington Centre",
    "iso:country":"GB",
    "sg:address":"The Galleries, Washington Centre",
    "sg:city":"Washington",
    "sg:classifiers":[
        {
            "category":"Shopping",
            "subcategory":"Clothing, Apparel, & Fashions",
            "type":"Retail Goods"
        }
    ],
    "sg:phone":"+44 191 416 7048",
    "sg:postcode":"NE38 7SD",
    "sg:province":"Durham",
    "sg:tags":[
        "shop"
    ],
    "wof:name":"Geordie Jeans Ltd.",
    "wof:placetype":"venue"
},
  "geometry": {"coordinates":[-1.531789,54.898144],"type":"Point"}
}