{
  "type": "Feature",
  "properties": {
    "addr:full":"14 Warner Drive, Springwood Industrial Estate Braintree Essex CM7 2YW",
    "addr:housenumber":"14",
    "addr:postcode":"cm7 2yw",
    "addr:street":"Warner Drive;Industrial Estate",
    "iso:country":"GB",
    "sg:address":"14 Warner Drive, Springwood Industrial Estate",
    "sg:city":"Braintree",
    "sg:classifiers":[
        {
            "category":"Professional",
            "subcategory":"Printing & Photocopies",
            "type":"Services"
        }
    ],
    "sg:phone":"+44 1376 552766",
    "sg:postcode":"CM7 2YW",
    "sg:province":"Essex",
    "sg:tags":[
        "printer"
    ],
    "wof:name":"Arrow Press Ltd",
    "wof:placetype":"venue"
},
  "geometry": {"coordinates":[0.5340870023,51.8837585449],"type":"Point"}
}