{
  "type": "Feature",
  "properties": {
    "addr:full":"Lincombe Salcombe Devon TQ8 8NQ",
    "addr:postcode":"tq8 8nq",
    "iso:country":"GB",
    "sg:address":"Lincombe",
    "sg:city":"Salcombe",
    "sg:classifiers":[
        {
            "category":"Home & Garden",
            "subcategory":"Garden Supply",
            "type":"Retail Goods"
        },
        {
            "category":"Farming",
            "subcategory":"Farm",
            "type":"Manufacturing & Wholesale Goods"
        }
    ],
    "sg:postcode":"TQ8 8NQ",
    "sg:province":"Devon",
    "sg:tags":[
        "mixed",
        "bulb",
        "crop",
        "grower"
    ],
    "wof:name":"Richard F B Gatehouse",
    "wof:placetype":"venue"
},
  "geometry": {"coordinates":[-3.7747991085,50.237865448],"type":"Point"}
}