{
  "type": "Feature",
  "properties": {
    "addr:full":"Pamona Garage, Kings Acre Rd Hereford Herefordshire HR4 0SN",
    "addr:postcode":"hr4 0sn",
    "addr:street":"Acre Rd",
    "iso:country":"GB",
    "sg:address":"Pamona Garage, Kings Acre Rd",
    "sg:city":"Hereford",
    "sg:classifiers":[
        {
            "category":"Retail",
            "subcategory":"Auto Repair",
            "type":"Services"
        }
    ],
    "sg:phone":"+44 1432 270200",
    "sg:postcode":"HR4 0SN",
    "sg:province":"Herefordshire",
    "sg:tags":[
        "modification",
        "garage"
    ],
    "wof:name":"Potter,Neil,",
    "wof:placetype":"venue"
},
  "geometry": {"coordinates":[-2.7317609787,52.0592041016],"type":"Point"}
}