{
  "type": "Feature",
  "properties": {
    "iso:country":"GB",
    "sg:address":"2 Hillview Road, Hucclecote",
    "sg:city":"Gloucester",
    "sg:classifiers":[
        {
            "category":"Personal",
            "subcategory":"Beauty Salon",
            "type":"Services"
        }
    ],
    "sg:phone":"+44 1452 616674",
    "sg:postcode":"GL3 3LD",
    "sg:province":"Gloucestershire",
    "sg:tags":[
        "unisex",
        "hairdresser"
    ],
    "wof:name":"Headline Hair",
    "wof:placetype":"venue"
},
  "geometry": {"coordinates":[-2.1913609505,51.8568458557],"type":"Point"}
}