{
  "type": "Feature",
  "properties": {
    "iso:country":"GB",
    "sg:address":"6 Gatley Road",
    "sg:city":"Cheadle",
    "sg:classifiers":[
        {
            "category":"Professional",
            "subcategory":"Management & Consulting",
            "type":"Services"
        }
    ],
    "sg:phone":"+44 161 491 2114",
    "sg:postcode":"SK8 1PY",
    "sg:province":"Cheshire",
    "sg:tags":[
        "consultant",
        "specialist"
    ],
    "wof:name":"Distinctive Nails",
    "wof:placetype":"venue"
},
  "geometry": {"coordinates":[-2.221163,53.392746],"type":"Point"}
}