{
  "type": "Feature",
  "properties": {
    "addr:full":"Unit D6 Laser Quay, Culpeper Clo Rochester Kent ME2 4HU",
    "addr:postcode":"me2 4hu",
    "addr:street":"Quay",
    "iso:country":"GB",
    "sg:address":"Unit D6 Laser Quay, Culpeper Clo",
    "sg:city":"Rochester",
    "sg:classifiers":[
        {
            "category":"Professional",
            "subcategory":"Printing & Photocopies",
            "type":"Services"
        }
    ],
    "sg:postcode":"ME2 4HU",
    "sg:province":"Kent",
    "sg:tags":[
        "printer"
    ],
    "wof:name":"Soho Printers Co Ltd",
    "wof:placetype":"venue"
},
  "geometry": {"coordinates":[0.4887830019,51.3963699341],"type":"Point"}
}