{
  "type": "Feature",
  "properties": {
    "iso:country":"GB",
    "sg:address":"South Cottage, Station Road, Skirlaugh",
    "sg:city":"Hull",
    "sg:classifiers":[
        {
            "category":"Freight",
            "type":"Transportation"
        }
    ],
    "sg:postcode":"HU11 5AF",
    "sg:province":"East Riding of Yorkshire",
    "sg:tags":[
        "haulage",
        "road"
    ],
    "wof:name":"Stephen Hewick (Haulage)",
    "wof:placetype":"venue"
},
  "geometry": {"coordinates":[-0.265626,53.841583],"type":"Point"}
}