{
  "type": "Feature",
  "properties": {
    "iso:country":"GB",
    "sg:address":"Syke House Farm, Syke House Lane, Dungworth",
    "sg:city":"Sheffield",
    "sg:classifiers":[
        {
            "category":"Farming",
            "subcategory":"Livestock Farm",
            "type":"Manufacturing & Wholesale Goods"
        }
    ],
    "sg:postcode":"S6 6HG",
    "sg:province":"South Yorkshire",
    "sg:tags":[
        "others"
    ],
    "wof:name":"D Gray & Sons",
    "wof:placetype":"venue"
},
  "geometry": {"coordinates":[-1.574312,53.405918],"type":"Point"}
}