{
  "type": "Feature",
  "properties": {
    "addr:full":"9-15 Port Glasgow Road Greenock Inverclyde PA15 2UD",
    "addr:housenumber":"9-15",
    "addr:postcode":"pa15 2ud",
    "addr:street":"Port Glasgow Road",
    "iso:country":"GB",
    "sg:address":"9-15 Port Glasgow Road",
    "sg:city":"Greenock",
    "sg:classifiers":[
        {
            "category":"Autos & Motor Vehicles",
            "subcategory":"Automobile Sales",
            "type":"Retail Goods"
        }
    ],
    "sg:phone":"+44 1475 742511",
    "sg:postcode":"PA15 2UD",
    "sg:province":"Inverclyde",
    "sg:tags":[
        "car"
    ],
    "wof:name":"Arnold Clark Automobiles",
    "wof:placetype":"venue"
},
  "geometry": {"coordinates":[-4.719583,55.940517],"type":"Point"}
}