{
  "type": "Feature",
  "properties": {
    "addr:full":"39 East Walk Basildon Essex SS14 1HA",
    "addr:housenumber":"39",
    "addr:postcode":"ss14 1ha",
    "addr:street":"East Walk",
    "iso:country":"GB",
    "sg:address":"39 East Walk",
    "sg:city":"Basildon",
    "sg:classifiers":[
        {
            "category":"Health Services",
            "subcategory":"Optometrist",
            "type":"Services"
        }
    ],
    "sg:phone":"+44 1268 531420",
    "sg:postcode":"SS14 1HA",
    "sg:province":"Essex",
    "sg:tags":[
        "optician"
    ],
    "wof:name":"Weston Opticians Ltd.",
    "wof:placetype":"venue"
},
  "geometry": {"coordinates":[0.4705899954,51.5713233948],"type":"Point"}
}