{
  "type": "Feature",
  "properties": {
    "addr:full":"12-14 Uppingham Road, Billesdon Leicester Leicestershire LE5 0QD",
    "addr:housenumber":"12-14",
    "addr:postcode":"le5 0qd",
    "addr:street":"Uppingham Road",
    "iso:country":"GB",
    "sg:address":"12-14 Uppingham Road, Billesdon",
    "sg:city":"Leicester",
    "sg:classifiers":[
        {
            "category":"Personal",
            "subcategory":"Beauty Salon",
            "type":"Services"
        }
    ],
    "sg:postcode":"LE5 0QD",
    "sg:province":"Leicestershire",
    "sg:tags":[
        "lady",
        "hairdresser"
    ],
    "wof:name":"Billesdon Hairdressers",
    "wof:placetype":"venue"
},
  "geometry": {"coordinates":[-1.1008690596,52.6420631409],"type":"Point"}
}