{
  "type": "Feature",
  "properties": {
    "addr:full":"28 Malpas Road Newport Newport NP20 5PA",
    "addr:housenumber":"28",
    "addr:postcode":"np20 5pa",
    "addr:street":"Malpas Road",
    "iso:country":"GB",
    "sg:address":"28 Malpas Road",
    "sg:city":"Newport",
    "sg:classifiers":[
        {
            "category":"Real Estate",
            "subcategory":"Real Estate Agent",
            "type":"Services"
        }
    ],
    "sg:phone":"+44 1633 859500",
    "sg:postcode":"NP20 5PA",
    "sg:province":"Newport",
    "wof:name":"Grove Estates",
    "wof:placetype":"venue"
},
  "geometry": {"coordinates":[-2.9994959831,51.5979156494],"type":"Point"}
}