{
  "type": "Feature",
  "properties": {
    "addr:full":"Crendon Way, Long Crendon Aylesbury Buckinghamshire HP18 9BD",
    "addr:postcode":"hp18 9bd",
    "addr:street":"Crendon Way",
    "iso:country":"GB",
    "sg:address":"Crendon Way, Long Crendon",
    "sg:city":"Aylesbury",
    "sg:classifiers":[
        {
            "category":"Home & Garden",
            "subcategory":"Kitchen Supply",
            "type":"Retail Goods"
        }
    ],
    "sg:phone":"+44 1844 208722",
    "sg:postcode":"HP18 9BD",
    "sg:province":"Buckinghamshire",
    "sg:tags":[
        "catering"
    ],
    "wof:name":"Mclaren Foods plc",
    "wof:placetype":"venue"
},
  "geometry": {"coordinates":[-0.9953759909,51.7735023499],"type":"Point"}
}