{
  "type": "Feature",
  "properties": {
    "addr:full":"133 Richmond Road Kingston-upon-thames Greater London KT2 5BZ",
    "addr:housenumber":"133",
    "addr:postcode":"kt2 5bz",
    "addr:street":"Richmond Road",
    "iso:country":"GB",
    "sg:address":"133 Richmond Road",
    "sg:city":"Kingston-upon-thames",
    "sg:classifiers":[
        {
            "category":"Fast Food",
            "type":"Food & Drink"
        }
    ],
    "sg:phone":"+44 20 8549 6789",
    "sg:postcode":"KT2 5BZ",
    "sg:province":"Greater London",
    "sg:tags":[
        "away",
        "take"
    ],
    "wof:name":"Silver River",
    "wof:placetype":"venue"
},
  "geometry": {"coordinates":[-0.3018240035,51.4186630249],"type":"Point"}
}