{
  "type": "Feature",
  "properties": {
    "iso:country":"GB",
    "sg:address":"4 Garden Lane, Boothstown, Worsley",
    "sg:city":"Manchester",
    "sg:classifiers":[
        {
            "category":"Professional",
            "subcategory":"Engineering",
            "type":"Services"
        },
        {
            "category":"Communications",
            "subcategory":"Film & Video Production",
            "type":"Services"
        }
    ],
    "sg:phone":"+44 161 790 8144",
    "sg:postcode":"M28 1JX",
    "sg:province":"Greater Manchester",
    "sg:tags":[
        "container",
        "engineer"
    ],
    "wof:name":"Aspull Engineering Co Ltd",
    "wof:placetype":"venue"
},
  "geometry": {"coordinates":[-2.4209740162,53.5029335022],"type":"Point"}
}