{
  "type": "Feature",
  "properties": {
    "iso:country":"GB",
    "sg:address":"Unit 13",
    "sg:city":"Luton",
    "sg:classifiers":[
        {
            "category":"Retail",
            "subcategory":"Auto Repair",
            "type":"Services"
        }
    ],
    "sg:phone":"+44 1582 723129",
    "sg:postcode":"LU1 3XJ",
    "sg:province":"Bedfordshire",
    "sg:tags":[
        "body",
        "car"
    ],
    "wof:name":"Ludlow Group Services Ltd.",
    "wof:placetype":"venue"
},
  "geometry": {"coordinates":[-0.4156149924,51.8813362122],"type":"Point"}
}