{
  "type": "Feature",
  "properties": {
    "iso:country":"GB",
    "sg:address":"3 Broughton Street",
    "sg:city":"Manchester",
    "sg:classifiers":[
        {
            "category":"Shopping",
            "subcategory":"Comic Books",
            "type":"Retail Goods"
        }
    ],
    "sg:phone":"+44 161 832 1708",
    "sg:postcode":"M8 8RF",
    "sg:province":"Greater Manchester",
    "sg:tags":[
        "jeweller"
    ],
    "wof:name":"Darengate Ltd.",
    "wof:placetype":"venue"
},
  "geometry": {"coordinates":[-2.236615,53.495014],"type":"Point"}
}