{
  "type": "Feature",
  "properties": {
    "addr:full":"Unit 2, Bone Lane Newbury Berkshire RG14 5SH",
    "addr:housenumber":"unit 2",
    "addr:postcode":"rg14 5sh",
    "addr:street":"Bone Lane",
    "iso:country":"GB",
    "sg:address":"Unit 2, Bone Lane",
    "sg:city":"Newbury",
    "sg:classifiers":[
        {
            "category":"Retail",
            "subcategory":"Auto Repair",
            "type":"Services"
        }
    ],
    "sg:phone":"+44 1635 551661",
    "sg:postcode":"RG14 5SH",
    "sg:province":"Berkshire",
    "sg:tags":[
        "modification",
        "garage"
    ],
    "wof:name":"Sharps Auto Services",
    "wof:placetype":"venue"
},
  "geometry": {"coordinates":[-1.3098189831,51.4016494751],"type":"Point"}
}