{
  "type": "Feature",
  "properties": {
    "addr:full":"46 Stand Park Avenue Bootle Merseyside L30 3SA",
    "addr:housenumber":"46",
    "addr:postcode":"l30 3sa",
    "addr:street":"Stand Park Avenue",
    "iso:country":"GB",
    "sg:address":"46 Stand Park Avenue",
    "sg:city":"Bootle",
    "sg:classifiers":[
        {
            "category":"Building & Trades",
            "subcategory":"Construction",
            "type":"Services"
        }
    ],
    "sg:phone":"+44 151 523 4722",
    "sg:postcode":"L30 3SA",
    "sg:province":"Merseyside",
    "sg:tags":[
        "joinery",
        "joiner",
        "carpenter",
        "carpentry"
    ],
    "wof:name":"A T Brennan",
    "wof:placetype":"venue"
},
  "geometry": {"coordinates":[-2.9716360569,53.4825592041],"type":"Point"}
}