{
  "type": "Feature",
  "properties": {
    "iso:country":"GB",
    "sg:address":"30 South Park Road, Gatley",
    "sg:city":"Cheadle",
    "sg:classifiers":[
        {
            "category":"Military Area",
            "subcategory":"Air Force Base",
            "type":"Public Place"
        }
    ],
    "sg:phone":"+44 161 428 8212",
    "sg:postcode":"SK8 4AN",
    "sg:province":"Cheshire",
    "sg:tags":[
        "water",
        "treatment"
    ],
    "wof:name":"Bailey & Partners Ltd.",
    "wof:placetype":"venue"
},
  "geometry": {"coordinates":[-2.228943,53.395443],"type":"Point"}
}