{
  "type": "Feature",
  "properties": {
    "iso:country":"GB",
    "sg:address":"Room 305 Premier House, Gayton Road",
    "sg:city":"Harrow",
    "sg:classifiers":[
        {
            "category":"Banks & Credit Unions",
            "subcategory":"Financial Services",
            "type":"Services"
        }
    ],
    "sg:phone":"+44 20 8423 3033",
    "sg:postcode":"HA1 2XU",
    "sg:province":"Greater London",
    "sg:tags":[
        "consultant"
    ],
    "wof:name":"Rita Jones",
    "wof:placetype":"venue"
},
  "geometry": {"coordinates":[-0.3258349895,51.5806770325],"type":"Point"}
}