{
  "type": "Feature",
  "properties": {
    "addr:full":"Carrick Works, 11 Standalane Kilmarnock East Ayrshire KA3 5BQ",
    "addr:housenumber":"11",
    "addr:postcode":"ka3 5bq",
    "addr:street":"Standalane Kilmarnock East",
    "iso:country":"GB",
    "sg:address":"Carrick Works, 11 Standalane",
    "sg:city":"Kilmarnock",
    "sg:classifiers":[
        {
            "category":"Professional",
            "subcategory":"Engineering",
            "type":"Services"
        }
    ],
    "sg:phone":"+44 1560 482207",
    "sg:postcode":"KA3 5BQ",
    "sg:province":"East Ayrshire",
    "sg:tags":[
        "precision",
        "engineer"
    ],
    "wof:name":"Filtronic Comtek",
    "wof:placetype":"venue"
},
  "geometry": {"coordinates":[-4.5025987625,55.6843910217],"type":"Point"}
}