{
  "type": "Feature",
  "properties": {
    "addr:full":"80 Hamilton Road Bellshill North Lanarkshire ML4 1AG",
    "addr:housenumber":"80",
    "addr:postcode":"ml4 1ag",
    "addr:street":"Hamilton Road",
    "iso:country":"GB",
    "sg:address":"80 Hamilton Road",
    "sg:city":"Bellshill",
    "sg:classifiers":[
        {
            "category":"Personal",
            "subcategory":"Beauty Salon",
            "type":"Services"
        }
    ],
    "sg:phone":"+44 1698 745339",
    "sg:postcode":"ML4 1AG",
    "sg:province":"North Lanarkshire",
    "sg:tags":[
        "unisex",
        "hairdresser"
    ],
    "wof:name":"Margarets Hair Fashion",
    "wof:placetype":"venue"
},
  "geometry": {"coordinates":[-4.025869,55.818039],"type":"Point"}
}