{
  "type": "Feature",
  "properties": {
    "addr:full":"6 Lwr Charles St Camberley Berkshire GU15 3LJ",
    "addr:housenumber":"6",
    "addr:postcode":"gu15 3lj",
    "addr:street":"Lwr Charles St",
    "iso:country":"GB",
    "sg:address":"6 Lwr Charles St",
    "sg:city":"Camberley",
    "sg:classifiers":[
        {
            "category":"Shopping",
            "subcategory":"News",
            "type":"Retail Goods"
        }
    ],
    "sg:postcode":"GU15 3LJ",
    "sg:province":"Berkshire",
    "sg:tags":[
        "newsagent"
    ],
    "wof:name":"Charles,Michael,",
    "wof:placetype":"venue"
},
  "geometry": {"coordinates":[-0.750217,51.337887],"type":"Point"}
}