{
  "type": "Feature",
  "properties": {
    "iso:country":"GB",
    "sg:address":"West Camp Raf Station, St Athan",
    "sg:city":"Barry",
    "sg:classifiers":[
        {
            "category":"Professional",
            "subcategory":"Engineering",
            "type":"Services"
        }
    ],
    "sg:phone":"+44 1446 751437",
    "sg:postcode":"CF62 9WA",
    "sg:province":"The Vale of Glamorgan",
    "sg:tags":[
        "contractor",
        "electrical",
        "engineer"
    ],
    "wof:name":"Thomas Patterson (Cardiff) Ltd.",
    "wof:placetype":"venue"
},
  "geometry": {"coordinates":[-3.28187,51.417702],"type":"Point"}
}