{
  "type": "Feature",
  "properties": {
    "iso:country":"GB",
    "sg:address":"2a Worksop Road, Woodsetts",
    "sg:city":"Worksop",
    "sg:classifiers":[
        {
            "category":"Food & Beverages",
            "subcategory":"Meat & Fish",
            "type":"Retail Goods"
        }
    ],
    "sg:postcode":"S81 8RN",
    "sg:province":"Nottinghamshire",
    "sg:tags":[
        "chip"
    ],
    "wof:name":"Woodsetts Fish Bar",
    "wof:placetype":"venue"
},
  "geometry": {"coordinates":[-1.1718859673,53.347820282],"type":"Point"}
}