{
  "type": "Feature",
  "properties": {
    "addr:full":"4 St. Botolphs St Colchester Essex CO2 7DX",
    "addr:housenumber":"4",
    "addr:postcode":"co2 7dx",
    "addr:street":"St. Botolphs St",
    "iso:country":"GB",
    "sg:address":"4 St. Botolphs St",
    "sg:city":"Colchester",
    "sg:classifiers":[
        {
            "category":"Bars & Pubs",
            "subcategory":"Wine Bar",
            "type":"Food & Drink"
        }
    ],
    "sg:phone":"+44 1206 766644",
    "sg:postcode":"CO2 7DX",
    "sg:province":"Essex",
    "wof:name":"Spoofers Cafe Bar",
    "wof:placetype":"venue"
},
  "geometry": {"coordinates":[0.9035140276,51.8852996826],"type":"Point"}
}