{
  "type": "Feature",
  "properties": {
    "addr:full":"27 Station Rd King's Lynn Norfolk PE31 7QL",
    "addr:housenumber":"27",
    "addr:postcode":"pe31 7ql",
    "addr:street":"Station Rd",
    "iso:country":"GB",
    "sg:address":"27 Station Rd",
    "sg:city":"King's Lynn",
    "sg:classifiers":[
        {
            "category":"Building & Trades",
            "subcategory":"Construction",
            "type":"Services"
        }
    ],
    "sg:phone":"+44 1485 541684",
    "sg:postcode":"PE31 7QL",
    "sg:province":"Norfolk",
    "sg:tags":[
        "decorator",
        "painter"
    ],
    "wof:name":"G J Johnson",
    "wof:placetype":"venue"
},
  "geometry": {"coordinates":[0.4991300106,52.8741416931],"type":"Point"}
}