{
  "type": "Feature",
  "properties": {
    "iso:country":"GB",
    "sg:address":"130 The Hoo",
    "sg:city":"Harlow",
    "sg:classifiers":[
        {
            "category":"Organizations",
            "subcategory":"Non-profit Organization",
            "type":"Services"
        }
    ],
    "sg:postcode":"CM17 0HS",
    "sg:province":"Essex",
    "sg:tags":[
        "organisation",
        "voluntary",
        "charity"
    ],
    "wof:name":"Harlow Pensioners Action Association",
    "wof:placetype":"venue"
},
  "geometry": {"coordinates":[0.1356869936,51.7900428772],"type":"Point"}
}