{
  "type": "Feature",
  "properties": {
    "iso:country":"GB",
    "sg:address":"209 Milngavie Road, Bearsden",
    "sg:city":"Glasgow",
    "sg:classifiers":[
        {
            "category":"Home & Garden",
            "subcategory":"Furniture",
            "type":"Retail Goods"
        }
    ],
    "sg:phone":"+44 141 942 7355",
    "sg:postcode":"G61 3DU",
    "sg:province":"East Dunbartonshire",
    "wof:name":"Bob Glen Contract Services",
    "wof:placetype":"venue"
},
  "geometry": {"coordinates":[-4.3167710304,55.9245910645],"type":"Point"}
}