{
  "type": "Feature",
  "properties": {
    "addr:full":"Kenyon Road, Lomeshaye Industrial Estate Nelson Lancashire BB9 5SP",
    "addr:postcode":"bb9 5sp",
    "addr:street":"Kenyon Road Lomeshaye Industrial Estate",
    "iso:country":"GB",
    "sg:address":"Kenyon Road, Lomeshaye Industrial Estate",
    "sg:city":"Nelson",
    "sg:classifiers":[
        {
            "category":"Building & Trades",
            "subcategory":"Construction",
            "type":"Services"
        }
    ],
    "sg:phone":"+44 1282 442300",
    "sg:postcode":"BB9 5SP",
    "sg:province":"Lancashire",
    "sg:tags":[
        "contractor"
    ],
    "wof:name":"Barnfield Construction Ltd",
    "wof:placetype":"venue"
},
  "geometry": {"coordinates":[-2.231464,53.833027],"type":"Point"}
}