{
  "type": "Feature",
  "properties": {
    "addr:full":"26 Commercial Road Swindon Wiltshire SN1 5NS",
    "addr:housenumber":"26",
    "addr:postcode":"sn1 5ns",
    "addr:street":"Commercial Road",
    "iso:country":"GB",
    "sg:address":"26 Commercial Road",
    "sg:city":"Swindon",
    "sg:classifiers":[
        {
            "category":"Real Estate",
            "subcategory":"Real Estate Agent",
            "type":"Services"
        }
    ],
    "sg:phone":"+44 1793 430588",
    "sg:postcode":"SN1 5NS",
    "sg:province":"Wiltshire",
    "wof:name":"Charles Harding Estate Agents",
    "wof:placetype":"venue"
},
  "geometry": {"coordinates":[-1.784854,51.558781],"type":"Point"}
}