{
  "type": "Feature",
  "properties": {
    "addr:full":"5 Kirkton Road, Kilmaurs Kilmarnock East Ayrshire KA3 2NW",
    "addr:housenumber":"5",
    "addr:postcode":"ka3 2nw",
    "addr:street":"Kirkton Road",
    "iso:country":"GB",
    "sg:address":"5 Kirkton Road, Kilmaurs",
    "sg:city":"Kilmarnock",
    "sg:classifiers":[
        {
            "category":"Professional",
            "subcategory":"Management & Consulting",
            "type":"Services"
        }
    ],
    "sg:phone":"+44 1563 573177",
    "sg:postcode":"KA3 2NW",
    "sg:province":"East Ayrshire",
    "sg:tags":[
        "consultant",
        "business"
    ],
    "wof:name":"Frank Murray",
    "wof:placetype":"venue"
},
  "geometry": {"coordinates":[-4.498489,55.628765],"type":"Point"}
}