{
  "type": "Feature",
  "properties": {
    "iso:country":"GB",
    "sg:address":"Acorn House, 365 Midsumer Blvd",
    "sg:city":"Milton Keynes",
    "sg:classifiers":[
        {
            "category":"Professional",
            "subcategory":"Lawyer & Legal Services",
            "type":"Services"
        }
    ],
    "sg:phone":"+44 1908 200676",
    "sg:postcode":"MK9 3HP",
    "sg:province":"Buckinghamshire",
    "sg:tags":[
        "advice",
        "counselling"
    ],
    "wof:name":"Milton Keynes Women & Work Group",
    "wof:placetype":"venue"
},
  "geometry": {"coordinates":[-0.756819,52.041851],"type":"Point"}
}