{
  "type": "Feature",
  "properties": {
    "iso:country":"GB",
    "sg:address":"Aldermoor Way",
    "sg:city":"Bristol",
    "sg:classifiers":[
        {
            "category":"Home & Garden",
            "subcategory":"Furniture",
            "type":"Retail Goods"
        }
    ],
    "sg:postcode":"BS30 7DA",
    "sg:province":"Gloucestershire",
    "wof:name":"Aldermoor Fitted Kitchens & Bedroom Cent",
    "wof:placetype":"venue"
},
  "geometry": {"coordinates":[-2.498159,51.446594],"type":"Point"}
}