{
  "type": "Feature",
  "properties": {
    "addr:full":"13 Webber Heath, Old Farm Park Milton Keynes Buckinghamshire MK7 8QL",
    "addr:housenumber":"13",
    "addr:postcode":"mk7 8ql",
    "addr:street":"Webber Heath;Park",
    "iso:country":"GB",
    "sg:address":"13 Webber Heath, Old Farm Park",
    "sg:city":"Milton Keynes",
    "sg:classifiers":[
        {
            "category":"Shopping",
            "subcategory":"Bicycles & Sporting Goods",
            "type":"Retail Goods"
        }
    ],
    "sg:phone":"+44 1908 644383",
    "sg:postcode":"MK7 8QL",
    "sg:province":"Buckinghamshire",
    "sg:tags":[
        "cycle",
        "accessory"
    ],
    "wof:name":"Gep International",
    "wof:placetype":"venue"
},
  "geometry": {"coordinates":[-0.679491,52.013294],"type":"Point"}
}