{
  "type": "Feature",
  "properties": {
    "addr:full":"85 London Road North Lowestoft Suffolk NR32 1LS",
    "addr:housenumber":"85",
    "addr:postcode":"nr32 1ls",
    "addr:street":"London Road North",
    "iso:country":"GB",
    "sg:address":"85 London Road North",
    "sg:city":"Lowestoft",
    "sg:classifiers":[
        {
            "category":"Restaurant",
            "type":"Food & Drink"
        }
    ],
    "sg:phone":"+44 1502 587878",
    "sg:postcode":"NR32 1LS",
    "sg:province":"Suffolk",
    "wof:name":"Wimpy International Ltd.",
    "wof:placetype":"venue"
},
  "geometry": {"coordinates":[1.752361,52.476246],"type":"Point"}
}