{
  "type": "Feature",
  "properties": {
    "iso:country":"GB",
    "sg:address":"78 Sterte Road",
    "sg:city":"Poole",
    "sg:classifiers":[
        {
            "category":"Retail",
            "subcategory":"Auto Repair",
            "type":"Services"
        }
    ],
    "sg:phone":"+44 1202 673169",
    "sg:postcode":"BH15 2AH",
    "sg:province":"Dorset",
    "sg:tags":[
        "modification",
        "garage",
        "related"
    ],
    "wof:name":"Sterte Garage Ltd",
    "wof:placetype":"venue"
},
  "geometry": {"coordinates":[-1.985484,50.72522],"type":"Point"}
}