{
  "type": "Feature",
  "properties": {
    "addr:full":"103 Congleton Road, Butt Ln Stoke-on-trent Cheshire ST7 1LY",
    "addr:housenumber":"103",
    "addr:postcode":"st7 1ly",
    "addr:street":"Congleton Road Butt Ln",
    "iso:country":"GB",
    "sg:address":"103 Congleton Road, Butt Ln",
    "sg:city":"Stoke-on-trent",
    "sg:classifiers":[
        {
            "category":"Shopping",
            "subcategory":"Clothing, Apparel, & Fashions",
            "type":"Retail Goods"
        }
    ],
    "sg:phone":"+44 1782 782393",
    "sg:postcode":"ST7 1LY",
    "sg:province":"Cheshire",
    "sg:tags":[
        "shop"
    ],
    "wof:name":"Rebecca's",
    "wof:placetype":"venue"
},
  "geometry": {"coordinates":[-2.2577090263,53.0898284912],"type":"Point"}
}