{
  "type": "Feature",
  "properties": {
    "addr:full":"Monastery La St Helens Cheshire WA9 5SG",
    "addr:postcode":"wa9 5sg",
    "addr:street":"La St",
    "iso:country":"GB",
    "sg:address":"Monastery La",
    "sg:city":"St Helens",
    "sg:classifiers":[
        {
            "category":"Retail",
            "subcategory":"Auto Repair",
            "type":"Services"
        }
    ],
    "sg:postcode":"WA9 5SG",
    "sg:province":"Cheshire",
    "sg:tags":[
        "modification",
        "garage"
    ],
    "wof:name":"Pott,Geoffrey William,",
    "wof:placetype":"venue"
},
  "geometry": {"coordinates":[-2.7457,53.43483],"type":"Point"}
}