{
  "type": "Feature",
  "properties": {
    "iso:country":"GB",
    "sg:address":"8a Bridge Street",
    "sg:city":"Musselburgh",
    "sg:classifiers":[
        {
            "category":"Health Services",
            "subcategory":"Clinic",
            "type":"Services"
        }
    ],
    "sg:phone":"+44 131 665 6821",
    "sg:postcode":"EH21 6AG",
    "sg:province":"City of Edinburgh",
    "sg:tags":[
        "nh"
    ],
    "wof:name":"Eskbridge Medical Centre",
    "wof:placetype":"venue"
},
  "geometry": {"coordinates":[-3.055742979,55.9427452087],"type":"Point"}
}