{
  "type": "Feature",
  "properties": {
    "iso:country":"GB",
    "sg:address":"Keighley Rd",
    "sg:city":"Halifax",
    "sg:classifiers":[
        {
            "category":"Education",
            "subcategory":"School",
            "type":"Public Place"
        }
    ],
    "sg:phone":"+44 1422 352292",
    "sg:postcode":"HX2 8AR",
    "sg:province":"West Yorkshire",
    "sg:tags":[
        "local",
        "authority"
    ],
    "wof:name":"Moorside Infant School",
    "wof:placetype":"venue"
},
  "geometry": {"coordinates":[-1.8956739902,53.7642631531],"type":"Point"}
}