{
  "type": "Feature",
  "properties": {
    "addr:full":"44 Westexe South Tiverton Devon EX16 5DH",
    "addr:housenumber":"44",
    "addr:postcode":"ex16 5dh",
    "addr:street":"Westexe South",
    "iso:country":"GB",
    "sg:address":"44 Westexe South",
    "sg:city":"Tiverton",
    "sg:classifiers":[
        {
            "category":"Organizations",
            "subcategory":"Non-profit Organization",
            "type":"Services"
        }
    ],
    "sg:phone":"+44 1884 255606",
    "sg:postcode":"EX16 5DH",
    "sg:province":"Devon",
    "sg:tags":[
        "organisation",
        "voluntary",
        "charity"
    ],
    "wof:name":"Church Housing Action Team",
    "wof:placetype":"venue"
},
  "geometry": {"coordinates":[-3.4961190224,50.9043502808],"type":"Point"}
}