{
  "type": "Feature",
  "properties": {
    "addr:full":"1 Hobart Place London Greater London SW1W 0HU",
    "addr:housenumber":"1",
    "addr:postcode":"sw1w 0hu",
    "addr:street":"Hobart Place",
    "iso:country":"GB",
    "sg:address":"1 Hobart Place",
    "sg:city":"London",
    "sg:classifiers":[
        {
            "category":"Banks & Credit Unions",
            "subcategory":"Bank",
            "type":"Services"
        }
    ],
    "sg:phone":"+44 20 7245 1234",
    "sg:postcode":"SW1W 0HU",
    "sg:province":"Greater London",
    "wof:name":"Duncan Lawrie Ltd.",
    "wof:placetype":"venue"
},
  "geometry": {"coordinates":[-0.148545,51.497818],"type":"Point"}
}