{
  "type": "Feature",
  "properties": {
    "addr:full":"Commercial House, 1 Foundry Terrace Cleckheaton West Yorkshire BD19 3JZ",
    "addr:housenumber":"1",
    "addr:postcode":"bd19 3jz",
    "addr:street":"Foundry Terrace",
    "iso:country":"GB",
    "sg:address":"Commercial House, 1 Foundry Terrace",
    "sg:city":"Cleckheaton",
    "sg:classifiers":[
        {
            "category":"Building & Trades",
            "subcategory":"Construction",
            "type":"Services"
        }
    ],
    "sg:phone":"+44 1274 872622",
    "sg:postcode":"BD19 3JZ",
    "sg:province":"West Yorkshire",
    "sg:tags":[
        "builder"
    ],
    "wof:name":"Torpoint Ltd.",
    "wof:placetype":"venue"
},
  "geometry": {"coordinates":[-1.7111990452,53.725730896],"type":"Point"}
}