{
  "type": "Feature",
  "properties": {
    "iso:country":"GB",
    "sg:address":"Kandalaska, Clifton Road, Netherseal",
    "sg:city":"Swadlincote",
    "sg:classifiers":[
        {
            "category":"Building & Trades",
            "subcategory":"Construction",
            "type":"Services"
        }
    ],
    "sg:phone":"+44 1827 373641",
    "sg:postcode":"DE12 8BT",
    "sg:province":"Derbyshire",
    "sg:tags":[
        "excavation",
        "groundwork",
        "contractor"
    ],
    "wof:name":"Roman Paving",
    "wof:placetype":"venue"
},
  "geometry": {"coordinates":[-1.576359,52.71484],"type":"Point"}
}