{
  "type": "Feature",
  "properties": {
    "addr:full":"32 Duke Street, Burton Latimer Kettering Northamptonshire NN15 5SG",
    "addr:housenumber":"32",
    "addr:postcode":"nn15 5sg",
    "addr:street":"Duke Street",
    "iso:country":"GB",
    "sg:address":"32 Duke Street, Burton Latimer",
    "sg:city":"Kettering",
    "sg:classifiers":[
        {
            "category":"Manufacturing",
            "subcategory":"Petroleum Products",
            "type":"Manufacturing & Wholesale Goods"
        }
    ],
    "sg:phone":"+44 1536 420808",
    "sg:postcode":"NN15 5SG",
    "sg:province":"Northamptonshire",
    "sg:tags":[
        "double",
        "glazing"
    ],
    "wof:name":"Belgrave Windows",
    "wof:placetype":"venue"
},
  "geometry": {"coordinates":[-0.680313,52.363018],"type":"Point"}
}