{
  "type": "Feature",
  "properties": {
    "iso:country":"GB",
    "sg:address":"121 Whalley Road, Ramsbottom",
    "sg:city":"Bury",
    "sg:classifiers":[
        {
            "category":"Government",
            "subcategory":"Post Office",
            "type":"Public Place"
        }
    ],
    "sg:postcode":"BL0 0DG",
    "sg:province":"Lancashire",
    "wof:name":"Shuttleworth Sub Post Office",
    "wof:placetype":"venue"
},
  "geometry": {"coordinates":[-2.3037009239,53.6582527161],"type":"Point"}
}