{
  "type": "Feature",
  "properties": {
    "addr:full":"Ferry Rd Cardiff Cardiff CF11 0JL",
    "addr:postcode":"cf11 0jl",
    "addr:street":"Ferry Rd",
    "iso:country":"GB",
    "sg:address":"Ferry Rd",
    "sg:city":"Cardiff",
    "sg:classifiers":[
        {
            "category":"Arena",
            "subcategory":"Sports Club",
            "type":"Entertainment"
        }
    ],
    "sg:phone":"+44 29 2022 6575",
    "sg:postcode":"CF11 0JL",
    "sg:province":"Cardiff",
    "wof:name":"Penarth Motor Boat & Sailing Club",
    "wof:placetype":"venue"
},
  "geometry": {"coordinates":[-3.185419,51.454987],"type":"Point"}
}