{
  "type": "Feature",
  "properties": {
    "iso:country":"GB",
    "sg:address":"The Chough, Penbeagle Way",
    "sg:city":"St Ives",
    "sg:classifiers":[
        {
            "category":"Building & Trades",
            "subcategory":"Construction",
            "type":"Services"
        }
    ],
    "sg:postcode":"TR26 2JQ",
    "sg:province":"Cornwall",
    "sg:tags":[
        "restoration",
        "refurbishment"
    ],
    "wof:name":"F A W",
    "wof:placetype":"venue"
},
  "geometry": {"coordinates":[-5.4910302162,50.207359314],"type":"Point"}
}