{
  "type": "Feature",
  "properties": {
    "iso:country":"GB",
    "sg:address":"6 Thirlmere Grove",
    "sg:city":"Bolton",
    "sg:classifiers":[
        {
            "category":"Building & Trades",
            "subcategory":"Construction",
            "type":"Services"
        }
    ],
    "sg:phone":"+44 1204 794095",
    "sg:postcode":"BL4 0QB",
    "sg:province":"Lancashire",
    "sg:tags":[
        "roofing"
    ],
    "wof:name":"Ken Smith",
    "wof:placetype":"venue"
},
  "geometry": {"coordinates":[-2.43187,53.545864],"type":"Point"}
}