{
  "type": "Feature",
  "properties": {
    "iso:country":"GB",
    "sg:address":"Rowan Place",
    "sg:city":"Newton Aycliffe",
    "sg:classifiers":[
        {
            "category":"Education",
            "subcategory":"School",
            "type":"Public Place"
        },
        {
            "category":"Government",
            "subcategory":"Office",
            "type":"Public Place"
        }
    ],
    "sg:phone":"+44 1325 300325",
    "sg:postcode":"DL5 7BB",
    "sg:province":"Durham",
    "sg:tags":[
        "local",
        "authority"
    ],
    "wof:name":"Elmfield Primary School",
    "wof:placetype":"venue"
},
  "geometry": {"coordinates":[-1.587814,54.615486],"type":"Point"}
}