{
  "type": "Feature",
  "properties": {
    "addr:full":"25 Broomfield Rd Reading Berkshire RG30 6AJ",
    "addr:housenumber":"25",
    "addr:postcode":"rg30 6aj",
    "addr:street":"Broomfield Rd",
    "iso:country":"GB",
    "sg:address":"25 Broomfield Rd",
    "sg:city":"Reading",
    "sg:classifiers":[
        {
            "category":"Arts & Performance",
            "subcategory":"Music",
            "type":"Entertainment"
        }
    ],
    "sg:phone":"+44 118 945 3311",
    "sg:postcode":"RG30 6AJ",
    "sg:province":"Berkshire",
    "sg:tags":[
        "musician",
        "composer"
    ],
    "wof:name":"Oxford Orchestra da Camera",
    "wof:placetype":"venue"
},
  "geometry": {"coordinates":[-1.0224250555,51.4610443115],"type":"Point"}
}