{
  "type": "Feature",
  "properties": {
    "addr:full":"272 Shipbourne Road Tonbridge Kent TN10 3EX",
    "addr:housenumber":"272",
    "addr:postcode":"tn10 3ex",
    "addr:street":"Shipbourne Road",
    "iso:country":"GB",
    "sg:address":"272 Shipbourne Road",
    "sg:city":"Tonbridge",
    "sg:classifiers":[
        {
            "category":"Real Estate",
            "subcategory":"Architect",
            "type":"Services"
        }
    ],
    "sg:postcode":"TN10 3EX",
    "sg:province":"Kent",
    "wof:name":"Linwood Surveying Ltd.",
    "wof:placetype":"venue"
},
  "geometry": {"coordinates":[0.280578,51.214539],"type":"Point"}
}