{
  "type": "Feature",
  "properties": {
    "addr:full":"Unit 7 Vale Enterprise Centre Ha, Yes Road, Sully Penarth The Vale of Glamorgan CF64 5SY",
    "addr:housenumber":"unit 7",
    "addr:postcode":"cf64 5sy",
    "addr:street":"Vale Enterprise Centre Ha Yes Road;Vale",
    "iso:country":"GB",
    "sg:address":"Unit 7 Vale Enterprise Centre Ha, Yes Road, Sully",
    "sg:city":"Penarth",
    "sg:classifiers":[
        {
            "category":"Building & Trades",
            "subcategory":"Construction",
            "type":"Services"
        }
    ],
    "sg:phone":"+44 1446 734647",
    "sg:postcode":"CF64 5SY",
    "sg:province":"The Vale of Glamorgan",
    "sg:tags":[
        "builder"
    ],
    "wof:name":"Nigel Phillips",
    "wof:placetype":"venue"
},
  "geometry": {"coordinates":[-3.214549,51.405689],"type":"Point"}
}