{
  "type": "Feature",
  "properties": {
    "addr:full":"121 Salisbury Road Worcester Park Surrey KT4 7BU",
    "addr:housenumber":"121",
    "addr:postcode":"kt4 7bu",
    "addr:street":"Salisbury Road",
    "iso:country":"GB",
    "sg:address":"121 Salisbury Road",
    "sg:city":"Worcester Park",
    "sg:classifiers":[
        {
            "category":"Building & Trades",
            "subcategory":"Construction",
            "type":"Services"
        }
    ],
    "sg:phone":"+44 20 8335 3218",
    "sg:postcode":"KT4 7BU",
    "sg:province":"Surrey",
    "sg:tags":[
        "contractor",
        "paving",
        "driveway"
    ],
    "wof:name":"Bissell Builders",
    "wof:placetype":"venue"
},
  "geometry": {"coordinates":[-0.253772,51.375507],"type":"Point"}
}