{
  "type": "Feature",
  "properties": {
    "addr:full":"21 Henbury Rise Wimborne Dorset BH21 3TE",
    "addr:housenumber":"21",
    "addr:postcode":"bh21 3te",
    "addr:street":"Henbury Rise",
    "iso:country":"GB",
    "sg:address":"21 Henbury Rise",
    "sg:city":"Wimborne",
    "sg:classifiers":[
        {
            "category":"Professional",
            "subcategory":"Engineering",
            "type":"Services"
        }
    ],
    "sg:phone":"+44 1202 697567",
    "sg:postcode":"BH21 3TE",
    "sg:province":"Dorset",
    "sg:tags":[
        "contractor",
        "electrical",
        "engineer"
    ],
    "wof:name":"Poole Electrical Services",
    "wof:placetype":"venue"
},
  "geometry": {"coordinates":[-2.0196650028,50.7705574036],"type":"Point"}
}