{
  "type": "Feature",
  "properties": {
    "iso:country":"GB",
    "sg:address":"6 The Mall",
    "sg:city":"Faversham",
    "sg:classifiers":[
        {
            "category":"Building & Trades",
            "subcategory":"Construction",
            "type":"Services"
        }
    ],
    "sg:phone":"+44 1795 536983",
    "sg:postcode":"ME13 8JL",
    "sg:province":"Kent",
    "sg:tags":[
        "restoration",
        "refurbishment"
    ],
    "wof:name":"A D A S Construction Ltd",
    "wof:placetype":"venue"
},
  "geometry": {"coordinates":[0.8885769844,51.3107681274],"type":"Point"}
}