{
  "type": "Feature",
  "properties": {
    "addr:full":"Seymour Rd Bolton Lancashire BL1 8PU",
    "addr:postcode":"bl1 8pu",
    "addr:street":"Seymour Rd",
    "iso:country":"GB",
    "sg:address":"Seymour Rd",
    "sg:city":"Bolton",
    "sg:classifiers":[
        {
            "category":"Place Of Worship",
            "type":"Public Place"
        }
    ],
    "sg:phone":"+44 1204 306056",
    "sg:postcode":"BL1 8PU",
    "sg:province":"Lancashire",
    "wof:name":"Astley Bridge Methodist Church",
    "wof:placetype":"venue"
},
  "geometry": {"coordinates":[-2.4253330231,53.5985794067],"type":"Point"}
}