{
  "type": "Feature",
  "properties": {
    "addr:full":"80 Goosemoor La Birmingham West Midlands B23 5PN",
    "addr:housenumber":"80",
    "addr:postcode":"b23 5pn",
    "addr:street":"Goosemoor La Birmingham",
    "iso:country":"GB",
    "sg:address":"80 Goosemoor La",
    "sg:city":"Birmingham",
    "sg:classifiers":[
        {
            "category":"Parking",
            "type":"Transportation"
        }
    ],
    "sg:phone":"+44 121 350 6616",
    "sg:postcode":"B23 5PN",
    "sg:province":"West Midlands",
    "sg:tags":[
        "car",
        "valet"
    ],
    "wof:name":"Tandys Mobile Car Valeting Service",
    "wof:placetype":"venue"
},
  "geometry": {"coordinates":[-1.8408850431,52.5350074768],"type":"Point"}
}