{
  "type": "Feature",
  "properties": {
    "addr:full":"Flacks Flower Fields, East End Green Hertford Hertfordshire SG14 2PD",
    "addr:postcode":"sg14 2pd",
    "addr:street":"East;Green",
    "iso:country":"GB",
    "sg:address":"Flacks Flower Fields, East End Green",
    "sg:city":"Hertford",
    "sg:classifiers":[
        {
            "category":"Home & Garden",
            "subcategory":"Garden Supply",
            "type":"Retail Goods"
        }
    ],
    "sg:phone":"+44 1992 589932",
    "sg:postcode":"SG14 2PD",
    "sg:province":"Hertfordshire",
    "sg:tags":[
        "flower",
        "shrub"
    ],
    "wof:name":"Flacks",
    "wof:placetype":"venue"
},
  "geometry": {"coordinates":[-0.12183,51.780338],"type":"Point"}
}