{
  "type": "Feature",
  "properties": {
    "addr:full":"25 Wardour Street London Greater London W1D 6PP",
    "addr:housenumber":"25",
    "addr:postcode":"w1d 6pp",
    "addr:street":"Wardour Street",
    "iso:country":"GB",
    "sg:address":"25 Wardour Street",
    "sg:city":"London",
    "sg:classifiers":[
        {
            "category":"Home & Garden",
            "subcategory":"Household Appliances",
            "type":"Retail Goods"
        }
    ],
    "sg:phone":"+44 20 7437 7541",
    "sg:postcode":"W1D 6PP",
    "sg:province":"Greater London",
    "sg:tags":[
        "electrical",
        "domestic"
    ],
    "wof:name":"Lee Fook Electric Co",
    "wof:placetype":"venue"
},
  "geometry": {"coordinates":[-0.1321379989,51.5111160278],"type":"Point"}
}