{
  "type": "Feature",
  "properties": {
    "addr:full":"Castle Iron Works, Overens Street Oldham Lancashire OL4 1LA",
    "addr:postcode":"ol4 1la",
    "addr:street":"Overens Street",
    "iso:country":"GB",
    "sg:address":"Castle Iron Works, Overens Street",
    "sg:city":"Oldham",
    "sg:classifiers":[
        {
            "category":"Professional",
            "subcategory":"Engineering",
            "type":"Services"
        }
    ],
    "sg:phone":"+44 161 627 5822",
    "sg:postcode":"OL4 1LA",
    "sg:province":"Lancashire",
    "sg:tags":[
        "engineer"
    ],
    "wof:name":"Oldham Engineering Ltd.",
    "wof:placetype":"venue"
},
  "geometry": {"coordinates":[-2.0924301147,53.5431785583],"type":"Point"}
}