{
  "type": "Feature",
  "properties": {
    "addr:full":"Davy Avenue, Knowl Hill Milton Keynes Buckinghamshire MK5 8HJ",
    "addr:postcode":"mk5 8hj",
    "addr:street":"Davy Avenue",
    "iso:country":"GB",
    "sg:address":"Davy Avenue, Knowl Hill",
    "sg:city":"Milton Keynes",
    "sg:classifiers":[
        {
            "category":"Shopping",
            "subcategory":"Computers & Home Electronics",
            "type":"Retail Goods"
        }
    ],
    "sg:phone":"+44 1908 666777",
    "sg:postcode":"MK5 8HJ",
    "sg:province":"Buckinghamshire",
    "sg:tags":[
        "electrical"
    ],
    "wof:name":"Routeco Plc",
    "wof:placetype":"venue"
},
  "geometry": {"coordinates":[-0.766839,52.022137],"type":"Point"}
}