{
  "type": "Feature",
  "properties": {
    "iso:country":"GB",
    "sg:address":"3 Guston Gdns, Kirton",
    "sg:city":"Ipswich",
    "sg:classifiers":[
        {
            "category":"Building & Trades",
            "subcategory":"Construction",
            "type":"Services"
        }
    ],
    "sg:postcode":"IP10 0PN",
    "sg:province":"Suffolk",
    "sg:tags":[
        "demolition",
        "contractor"
    ],
    "wof:name":"Krailing,Anthony,",
    "wof:placetype":"venue"
},
  "geometry": {"coordinates":[1.321135,52.003639],"type":"Point"}
}