{
  "type": "Feature",
  "properties": {
    "iso:country":"GB",
    "sg:address":"46 Stapleton Road",
    "sg:city":"Bristol",
    "sg:classifiers":[
        {
            "category":"Sports & Exercise",
            "subcategory":"Sports Center",
            "type":"Entertainment"
        }
    ],
    "sg:phone":"+44 117 949 9966",
    "sg:postcode":"BS5 0RA",
    "sg:province":"City of Bristol",
    "sg:tags":[
        "shop",
        "good"
    ],
    "wof:name":"Venom Sports",
    "wof:placetype":"venue"
},
  "geometry": {"coordinates":[-2.5750079155,51.4601173401],"type":"Point"}
}