{
  "type": "Feature",
  "properties": {
    "iso:country":"GB",
    "sg:address":"Trading Place Unit 7, 222 Breck Rd",
    "sg:city":"Liverpool",
    "sg:classifiers":[
        {
            "category":"Shopping",
            "subcategory":"Department Store",
            "type":"Retail Goods"
        }
    ],
    "sg:postcode":"L5 6PX",
    "sg:province":"Merseyside",
    "wof:name":"Farrell,Christian,",
    "wof:placetype":"venue"
},
  "geometry": {"coordinates":[-2.9577000141,53.4233589172],"type":"Point"}
}