{
  "type": "Feature",
  "properties": {
    "iso:country":"GB",
    "sg:address":"Sirhowy Bridge",
    "sg:city":"Tredegar",
    "sg:classifiers":[
        {
            "category":"Government",
            "subcategory":"Department Of Motor Vehicles",
            "type":"Public Place"
        }
    ],
    "sg:phone":"+44 1495 725311",
    "sg:postcode":"NP2 4XL",
    "sg:province":"Blaenau Gwent",
    "sg:tags":[
        "inspection"
    ],
    "wof:name":"Express Vehicle Rentals",
    "wof:placetype":"venue"
},
  "geometry": {"coordinates":[-3.23717,51.783661],"type":"Point"}
}