{
  "type": "Feature",
  "properties": {
    "addr:full":"6 Sussex Street Rhyl Conwy LL18 1SG",
    "addr:housenumber":"6",
    "addr:postcode":"ll18 1sg",
    "addr:street":"Sussex Street",
    "iso:country":"GB",
    "sg:address":"6 Sussex Street",
    "sg:city":"Rhyl",
    "sg:classifiers":[
        {
            "category":"Shopping",
            "subcategory":"Clothing, Apparel, & Fashions",
            "type":"Retail Goods"
        }
    ],
    "sg:phone":"+44 1745 334112",
    "sg:postcode":"LL18 1SG",
    "sg:province":"Conwy",
    "sg:tags":[
        "shop"
    ],
    "wof:name":"Rock Bottom",
    "wof:placetype":"venue"
},
  "geometry": {"coordinates":[-3.491744,53.32111],"type":"Point"}
}