{
  "type": "Feature",
  "properties": {
    "iso:country":"GB",
    "sg:address":"77 York Rd",
    "sg:city":"Paignton",
    "sg:classifiers":[
        {
            "category":"Mining & Drilling",
            "type":"Manufacturing & Wholesale Goods"
        }
    ],
    "sg:phone":"+44 1803 663333",
    "sg:postcode":"TQ4 5NR",
    "sg:province":"Devon",
    "sg:tags":[
        "contractor"
    ],
    "wof:name":"M.D.C Nationwide",
    "wof:placetype":"venue"
},
  "geometry": {"coordinates":[-3.571833,50.427322],"type":"Point"}
}