{
  "type": "Feature",
  "properties": {
    "iso:country":"GB",
    "sg:address":"13 Cloth Hall Street",
    "sg:city":"Dewsbury",
    "sg:classifiers":[
        {
            "category":"Sports & Exercise",
            "subcategory":"Sports Center",
            "type":"Entertainment"
        }
    ],
    "sg:phone":"+44 1924 466090",
    "sg:postcode":"WF13 1QE",
    "sg:province":"West Yorkshire",
    "sg:tags":[
        "shop",
        "good"
    ],
    "wof:name":"Discount Sports",
    "wof:placetype":"venue"
},
  "geometry": {"coordinates":[-1.6286050081,53.6935081482],"type":"Point"}
}