{
  "type": "Feature",
  "properties": {
    "addr:full":"First Floor, Orchard House Ashford Kent TN23 1PL",
    "addr:housenumber":"orchard house",
    "addr:postcode":"tn23 1pl",
    "iso:country":"GB",
    "sg:address":"First Floor, Orchard House",
    "sg:city":"Ashford",
    "sg:classifiers":[
        {
            "category":"Real Estate",
            "subcategory":"Surveying",
            "type":"Services"
        }
    ],
    "sg:phone":"+44 1233 625574",
    "sg:postcode":"TN23 1PL",
    "sg:province":"Kent",
    "sg:tags":[
        "surveyor",
        "land"
    ],
    "wof:name":"Ordnance Survey",
    "wof:placetype":"venue"
},
  "geometry": {"coordinates":[0.8760370016,51.1466331482],"type":"Point"}
}