{
  "type": "Feature",
  "properties": {
    "iso:country":"GB",
    "sg:address":"Oxgang Road",
    "sg:city":"Grangemouth",
    "sg:classifiers":[
        {
            "category":"Education",
            "subcategory":"Special Training",
            "type":"Public Place"
        }
    ],
    "sg:phone":"+44 1324 473030",
    "sg:postcode":"FK3 9ER",
    "sg:province":"Falkirk",
    "sg:tags":[
        "martial art",
        "instruction"
    ],
    "wof:name":"Sen-No-Kai Martial Arts",
    "wof:placetype":"venue"
},
  "geometry": {"coordinates":[-3.708969,56.016243],"type":"Point"}
}