{
  "type": "Feature",
  "properties": {
    "iso:country":"GB",
    "sg:address":"Nash",
    "sg:city":"Newport",
    "sg:classifiers":[
        {
            "category":"Building & Trades",
            "subcategory":"Construction",
            "type":"Services"
        }
    ],
    "sg:postcode":"NP18 2BW",
    "sg:province":"Monmouthshire",
    "sg:tags":[
        "fork",
        "lift",
        "truck"
    ],
    "wof:name":"The Parts Centre Ltd.",
    "wof:placetype":"venue"
},
  "geometry": {"coordinates":[-2.9468729496,51.54895401],"type":"Point"}
}