{
  "type": "Feature",
  "properties": {
    "iso:country":"GB",
    "sg:address":"23 Northfields, Lode",
    "sg:city":"Cambridge",
    "sg:classifiers":[
        {
            "category":"Building & Trades",
            "subcategory":"Construction",
            "type":"Services"
        }
    ],
    "sg:phone":"+44 1223 812016",
    "sg:postcode":"CB5 9EU",
    "sg:province":"Cambridgeshire",
    "sg:tags":[
        "decorator",
        "painter"
    ],
    "wof:name":"Golding & Heffer Painting & Decorating",
    "wof:placetype":"venue"
},
  "geometry": {"coordinates":[0.2438299954,52.2602615356],"type":"Point"}
}