{
  "type": "Feature",
  "properties": {
    "iso:country":"GB",
    "sg:address":"Townsend House, Westheath Avenue",
    "sg:city":"Bodmin",
    "sg:classifiers":[
        {
            "category":"Building & Trades",
            "subcategory":"Construction",
            "type":"Services"
        }
    ],
    "sg:phone":"+44 1208 76303",
    "sg:postcode":"PL31 1QH",
    "sg:province":"Cornwall",
    "sg:tags":[
        "builder"
    ],
    "wof:name":"B A J Builders (S W)",
    "wof:placetype":"venue"
},
  "geometry": {"coordinates":[-4.741744,50.465752],"type":"Point"}
}