{
  "type": "Feature",
  "properties": {
    "addr:full":"76 Abington Avenue Northampton Northamptonshire NN1 4PA",
    "addr:housenumber":"76",
    "addr:postcode":"nn1 4pa",
    "addr:street":"Abington Avenue",
    "iso:country":"GB",
    "sg:address":"76 Abington Avenue",
    "sg:city":"Northampton",
    "sg:classifiers":[
        {
            "category":"Health Services",
            "subcategory":"Chiropractor",
            "type":"Services"
        }
    ],
    "sg:postcode":"NN1 4PA",
    "sg:province":"Northamptonshire",
    "wof:name":"Z Iqbal",
    "wof:placetype":"venue"
},
  "geometry": {"coordinates":[-0.879057,52.24715],"type":"Point"}
}