{
  "type": "Feature",
  "properties": {
    "addr:full":"Kilbirnie Road Lochwinnoch Renfrewshire PA12 4DT",
    "addr:postcode":"pa12 4dt",
    "addr:street":"Kilbirnie Road",
    "iso:country":"GB",
    "sg:address":"Kilbirnie Road",
    "sg:city":"Lochwinnoch",
    "sg:classifiers":[
        {
            "category":"Home & Garden",
            "subcategory":"Garden Supply",
            "type":"Retail Goods"
        }
    ],
    "sg:postcode":"PA12 4DT",
    "sg:province":"Renfrewshire",
    "sg:tags":[
        "nursery",
        "centre"
    ],
    "wof:name":"The Kerse Nursery",
    "wof:placetype":"venue"
},
  "geometry": {"coordinates":[-4.625364,55.797005],"type":"Point"}
}