{
  "type": "Feature",
  "properties": {
    "addr:full":"1307 London Road Leigh-on-sea Essex SS9 2AD",
    "addr:housenumber":"1307",
    "addr:postcode":"ss9 2ad",
    "addr:street":"London Road",
    "iso:country":"GB",
    "sg:address":"1307 London Road",
    "sg:city":"Leigh-on-sea",
    "sg:classifiers":[
        {
            "category":"Retail",
            "subcategory":"Auto Repair",
            "type":"Services"
        }
    ],
    "sg:phone":"+44 1702 714368",
    "sg:postcode":"SS9 2AD",
    "sg:province":"Essex",
    "sg:tags":[
        "modification",
        "garage"
    ],
    "wof:name":"London Road Motors",
    "wof:placetype":"venue"
},
  "geometry": {"coordinates":[0.6513910294,51.5485916138],"type":"Point"}
}