{
  "type": "Feature",
  "properties": {
    "iso:country":"GB",
    "sg:address":"163 Rusper Rd",
    "sg:city":"Crawley",
    "sg:classifiers":[
        {
            "category":"Professional",
            "subcategory":"Business Services",
            "type":"Services"
        }
    ],
    "sg:phone":"+44 1293 440647",
    "sg:postcode":"RH11 0HR",
    "sg:province":"West Sussex",
    "sg:tags":[
        "import",
        "export",
        "agent"
    ],
    "wof:name":"Linejet Associates Ltd",
    "wof:placetype":"venue"
},
  "geometry": {"coordinates":[-0.217381,51.118011],"type":"Point"}
}