{
  "type": "Feature",
  "properties": {
    "iso:country":"GB",
    "sg:address":"The Bungalow, Main Street",
    "sg:city":"Bicester",
    "sg:classifiers":[
        {
            "category":"Home & Garden",
            "subcategory":"Carpets & Floor Coverings",
            "type":"Retail Goods"
        }
    ],
    "sg:phone":"+44 1869 278409",
    "sg:postcode":"OX27 9BB",
    "sg:province":"Buckinghamshire",
    "sg:tags":[
        "textile",
        "floorcoverings"
    ],
    "wof:name":"C R Tipping Ltd.",
    "wof:placetype":"venue"
},
  "geometry": {"coordinates":[-1.064,51.922649],"type":"Point"}
}