{
  "type": "Feature",
  "properties": {
    "addr:full":"Crofton Back Lane, Burtonwood Warrington Cheshire WA5 4AG",
    "addr:postcode":"wa5 4ag",
    "addr:street":"Back Lane",
    "iso:country":"GB",
    "sg:address":"Crofton Back Lane, Burtonwood",
    "sg:city":"Warrington",
    "sg:classifiers":[
        {
            "category":"Professional",
            "subcategory":"Detective & Security Services",
            "type":"Services"
        }
    ],
    "sg:postcode":"WA5 4AG",
    "sg:province":"Cheshire",
    "wof:name":"Q Investigations Ltd.",
    "wof:placetype":"venue"
},
  "geometry": {"coordinates":[-2.6593739986,53.4310760498],"type":"Point"}
}