{
  "type": "Feature",
  "properties": {
    "addr:full":"Telford Studios Unit 14 Telford Ct, 9 South Ave Clydebank East Dunbartonshire G81 2NR",
    "addr:housenumber":"unit 14;9",
    "addr:postcode":"g81 2nr",
    "addr:street":"Telford Ct;South Ave",
    "iso:country":"GB",
    "sg:address":"Telford Studios Unit 14 Telford Ct, 9 South Ave",
    "sg:city":"Clydebank",
    "sg:classifiers":[
        {
            "category":"Professional",
            "subcategory":"Art Services",
            "type":"Services"
        }
    ],
    "sg:postcode":"G81 2NR",
    "sg:province":"East Dunbartonshire",
    "sg:tags":[
        "photographer"
    ],
    "wof:name":"Marshall,Ian,Photography",
    "wof:placetype":"venue"
},
  "geometry": {"coordinates":[-4.4036488533,55.9108581543],"type":"Point"}
}