{
  "type": "Feature",
  "properties": {
    "addr:full":"44 Crosby Road North, Waterloo Liverpool Merseyside L22 4QQ",
    "addr:housenumber":"44",
    "addr:postcode":"l22 4qq",
    "addr:street":"Crosby Road North",
    "iso:country":"GB",
    "sg:address":"44 Crosby Road North, Waterloo",
    "sg:city":"Liverpool",
    "sg:classifiers":[
        {
            "category":"Home & Garden",
            "subcategory":"Home Furnishings",
            "type":"Retail Goods"
        }
    ],
    "sg:postcode":"L22 4QQ",
    "sg:province":"Merseyside",
    "sg:tags":[
        "mantelpiece",
        "fireplace"
    ],
    "wof:name":"Crystal Fires Ltd.",
    "wof:placetype":"venue"
},
  "geometry": {"coordinates":[-3.023399,53.480194],"type":"Point"}
}