{
  "type": "Feature",
  "properties": {
    "iso:country":"GB",
    "sg:address":"95 St. Georges Rd",
    "sg:city":"Bolton",
    "sg:classifiers":[
        {
            "category":"Shopping",
            "subcategory":"Stationery & Office Supplies",
            "type":"Retail Goods"
        }
    ],
    "sg:phone":"+44 1204 392020",
    "sg:postcode":"BL1 2BY",
    "sg:province":"Lancashire",
    "wof:name":"B S Paper Products",
    "wof:placetype":"venue"
},
  "geometry": {"coordinates":[-2.433099,53.581444],"type":"Point"}
}