{
  "type": "Feature",
  "properties": {
    "iso:country":"GB",
    "sg:address":"Block Lane, Chadderton",
    "sg:city":"Oldham",
    "sg:classifiers":[
        {
            "category":"Health Services",
            "subcategory":"Doctor",
            "type":"Services"
        }
    ],
    "sg:postcode":"OL9 7SG",
    "sg:province":"Lancashire",
    "sg:tags":[
        "practitioners"
    ],
    "wof:name":"The Doctors Surgery",
    "wof:placetype":"venue"
},
  "geometry": {"coordinates":[-2.13791,53.53648],"type":"Point"}
}