{
  "type": "Feature",
  "properties": {
    "iso:country":"GB",
    "sg:address":"1084 Melton Road, Syston",
    "sg:city":"Leicester",
    "sg:classifiers":[
        {
            "category":"Professional",
            "subcategory":"Engineering",
            "type":"Services"
        }
    ],
    "sg:phone":"+44 116 260 0719",
    "sg:postcode":"LE7 2HA",
    "sg:province":"Leicestershire",
    "wof:name":"Wanlip Engineering",
    "wof:placetype":"venue"
},
  "geometry": {"coordinates":[-1.0791150331,52.6950836182],"type":"Point"}
}