{
  "type": "Feature",
  "properties": {
    "addr:full":"Market Cross Sturminster Newton Dorset DT10 1AN",
    "addr:postcode":"dt10 1an",
    "iso:country":"GB",
    "sg:address":"Market Cross",
    "sg:city":"Sturminster Newton",
    "sg:classifiers":[
        {
            "category":"Real Estate",
            "subcategory":"Real Estate Agent",
            "type":"Services"
        }
    ],
    "sg:phone":"+44 1258 473900",
    "sg:postcode":"DT10 1AN",
    "sg:province":"Dorset",
    "wof:name":"Roy Barrett",
    "wof:placetype":"venue"
},
  "geometry": {"coordinates":[-2.3053379059,50.9256019592],"type":"Point"}
}