{
  "type": "Feature",
  "properties": {
    "iso:country":"GB",
    "sg:address":"Centre Ho, Ashburton Rd East, Trafford Pk",
    "sg:city":"Manchester",
    "sg:classifiers":[
        {
            "category":"Autos & Motor Vehicles",
            "subcategory":"Automobile Sales",
            "type":"Retail Goods"
        }
    ],
    "sg:phone":"+44 161 872 7788",
    "sg:postcode":"M17 1QG",
    "sg:province":"Cheshire",
    "sg:tags":[
        "car"
    ],
    "wof:name":"Parkside Ltd",
    "wof:placetype":"venue"
},
  "geometry": {"coordinates":[-2.3435750008,53.4738616943],"type":"Point"}
}