{
  "type": "Feature",
  "properties": {
    "addr:full":"15 Tettenhall Road Wolverhampton Staffordshire WV3 9NB",
    "addr:housenumber":"15",
    "addr:postcode":"wv3 9nb",
    "addr:street":"Tettenhall Road",
    "iso:country":"GB",
    "sg:address":"15 Tettenhall Road",
    "sg:city":"Wolverhampton",
    "sg:classifiers":[
        {
            "category":"Health Services",
            "subcategory":"Dentist",
            "type":"Services"
        }
    ],
    "sg:phone":"+44 1902 420331",
    "sg:postcode":"WV3 9NB",
    "sg:province":"Staffordshire",
    "wof:name":"Ian M Boyle",
    "wof:placetype":"venue"
},
  "geometry": {"coordinates":[-2.1482429504,52.5889701843],"type":"Point"}
}