{
  "type": "Feature",
  "properties": {
    "iso:country":"GB",
    "sg:address":"Spring Lane",
    "sg:city":"Bury St Edmunds",
    "sg:classifiers":[
        {
            "category":"Building & Trades",
            "subcategory":"Construction",
            "type":"Services"
        }
    ],
    "sg:phone":"+44 1284 754882",
    "sg:postcode":"IP33 3AP",
    "sg:province":"Suffolk",
    "sg:tags":[
        "builder"
    ],
    "wof:name":"E E Mortimer & Sons (Bury St.Edmunds) Ltd.",
    "wof:placetype":"venue"
},
  "geometry": {"coordinates":[0.7063800097,52.2511405945],"type":"Point"}
}