{
  "type": "Feature",
  "properties": {
    "addr:full":"31 Burnham Road Glasgow Glasgow City G14 0XA",
    "addr:housenumber":"31",
    "addr:postcode":"g14 0xa",
    "addr:street":"Burnham Road",
    "iso:country":"GB",
    "sg:address":"31 Burnham Road",
    "sg:city":"Glasgow",
    "sg:classifiers":[
        {
            "category":"Shopping",
            "subcategory":"Department Store",
            "type":"Retail Goods"
        },
        {
            "category":"Retail",
            "subcategory":"Auto Repair",
            "type":"Services"
        }
    ],
    "sg:phone":"+44 141 950 1747",
    "sg:postcode":"G14 0XA",
    "sg:province":"Glasgow City",
    "sg:tags":[
        "modification",
        "garage"
    ],
    "wof:name":"Kingsway Autos",
    "wof:placetype":"venue"
},
  "geometry": {"coordinates":[-4.364445,55.88203],"type":"Point"}
}