{
  "type": "Feature",
  "properties": {
    "iso:country":"GB",
    "sg:address":"Glanville Rd",
    "sg:city":"Oxford",
    "sg:classifiers":[
        {
            "category":"Building & Trades",
            "subcategory":"Construction",
            "type":"Services"
        }
    ],
    "sg:phone":"+44 1865 747447",
    "sg:postcode":"OX4 2DD",
    "sg:province":"Oxfordshire",
    "sg:tags":[
        "decorator",
        "painter"
    ],
    "wof:name":"Phipps & Wynn (Oxford) Ltd",
    "wof:placetype":"venue"
},
  "geometry": {"coordinates":[-1.222499,51.742275],"type":"Point"}
}