{
  "type": "Feature",
  "properties": {
    "addr:full":"Roebuck House, The Square, Tollesbury Maldon Essex CM9 8QJ",
    "addr:postcode":"cm9 8qj",
    "addr:street":"The Square Tollesbury",
    "iso:country":"GB",
    "sg:address":"Roebuck House, The Square, Tollesbury",
    "sg:city":"Maldon",
    "sg:classifiers":[
        {
            "category":"Health Services",
            "subcategory":"Nursing And Care Facility",
            "type":"Services"
        }
    ],
    "sg:phone":"+44 1621 869384",
    "sg:postcode":"CM9 8QJ",
    "sg:province":"Essex",
    "sg:tags":[
        "agency"
    ],
    "wof:name":"A S A P",
    "wof:placetype":"venue"
},
  "geometry": {"coordinates":[0.73819,51.773605],"type":"Point"}
}