{
  "type": "Feature",
  "properties": {
    "addr:full":"26 Almleys Lane, Earl Shilton Leicester Leicestershire LE9 7JA",
    "addr:housenumber":"26",
    "addr:postcode":"le9 7ja",
    "addr:street":"Almleys Lane",
    "iso:country":"GB",
    "sg:address":"26 Almleys Lane, Earl Shilton",
    "sg:city":"Leicester",
    "sg:classifiers":[
        {
            "category":"Home & Garden",
            "subcategory":"Furniture",
            "type":"Retail Goods"
        }
    ],
    "sg:postcode":"LE9 7JA",
    "sg:province":"Leicestershire",
    "wof:name":"Janet Brant",
    "wof:placetype":"venue"
},
  "geometry": {"coordinates":[-1.3144949675,52.5757751465],"type":"Point"}
}