{
  "type": "Feature",
  "properties": {
    "iso:country":"GB",
    "sg:address":"83 Neilston Road",
    "sg:city":"Paisley",
    "sg:classifiers":[
        {
            "category":"Personal",
            "subcategory":"Beauty Salon",
            "type":"Services"
        }
    ],
    "sg:phone":"+44 141 887 7698",
    "sg:postcode":"PA2 6EJ",
    "sg:province":"East Renfrewshire",
    "sg:tags":[
        "unisex",
        "hairdresser"
    ],
    "wof:name":"Scissor Talk",
    "wof:placetype":"venue"
},
  "geometry": {"coordinates":[-4.422897,55.833851],"type":"Point"}
}