{
  "type": "Feature",
  "properties": {
    "iso:country":"GB",
    "sg:address":"17 Hartley Rd",
    "sg:city":"Luton",
    "sg:classifiers":[
        {
            "category":"Professional",
            "subcategory":"Engineering",
            "type":"Services"
        },
        {
            "category":"Autos & Motor Vehicles",
            "subcategory":"Auto Supplies",
            "type":"Retail Goods"
        },
        {
            "category":"Retail",
            "subcategory":"Auto Repair",
            "type":"Services"
        }
    ],
    "sg:postcode":"LU2 0HX",
    "sg:province":"Bedfordshire",
    "sg:tags":[
        "electric",
        "contractor",
        "garage",
        "electrical",
        "modification",
        "engineer"
    ],
    "wof:name":"Cripps,Donald,",
    "wof:placetype":"venue"
},
  "geometry": {"coordinates":[-0.408848,51.883114],"type":"Point"}
}