{
  "type": "Feature",
  "properties": {
    "addr:full":"35 Whitehawk Rd Brighton East Sussex BN2 5FB",
    "addr:housenumber":"35",
    "addr:postcode":"bn2 5fb",
    "addr:street":"Whitehawk Rd",
    "iso:country":"GB",
    "sg:address":"35 Whitehawk Rd",
    "sg:city":"Brighton",
    "sg:classifiers":[
        {
            "category":"Professional",
            "type":"Services"
        },
        {
            "category":"Fast Food",
            "type":"Food & Drink"
        }
    ],
    "sg:postcode":"BN2 5FB",
    "sg:province":"East Sussex",
    "sg:tags":[
        "away",
        "take",
        "caterer"
    ],
    "wof:name":"Wright,Heather,",
    "wof:placetype":"venue"
},
  "geometry": {"coordinates":[-0.1061479971,50.8187828064],"type":"Point"}
}