{
  "type": "Feature",
  "properties": {
    "addr:full":"Main Road, Ravenshead Nottingham Nottinghamshire NG15 9GP",
    "addr:postcode":"ng15 9gp",
    "addr:street":"Main Road",
    "iso:country":"GB",
    "sg:address":"Main Road, Ravenshead",
    "sg:city":"Nottingham",
    "sg:classifiers":[
        {
            "category":"Shopping",
            "subcategory":"News",
            "type":"Retail Goods"
        }
    ],
    "sg:postcode":"NG15 9GP",
    "sg:province":"Nottinghamshire",
    "sg:tags":[
        "newsagent"
    ],
    "wof:name":"Main Road Post Office Stores",
    "wof:placetype":"venue"
},
  "geometry": {"coordinates":[-1.156003952,53.0925941467],"type":"Point"}
}