{
  "type": "Feature",
  "properties": {
    "addr:full":"10 Bluebellwood Close Sutton Coldfield Warwickshire B76 2UB",
    "addr:housenumber":"10",
    "addr:postcode":"b76 2ub",
    "addr:street":"Bluebellwood Close",
    "iso:country":"GB",
    "sg:address":"10 Bluebellwood Close",
    "sg:city":"Sutton Coldfield",
    "sg:classifiers":[
        {
            "category":"Shopping",
            "subcategory":"Party Supplies",
            "type":"Retail Goods"
        },
        {
            "category":"Arts & Performance",
            "subcategory":"Music",
            "type":"Entertainment"
        }
    ],
    "sg:phone":"+44 121 351 3562",
    "sg:postcode":"B76 2UB",
    "sg:province":"Warwickshire",
    "sg:tags":[
        "mobile",
        "operator",
        "disco"
    ],
    "wof:name":"Millennium Discos",
    "wof:placetype":"venue"
},
  "geometry": {"coordinates":[-1.793609,52.554817],"type":"Point"}
}