{
  "type": "Feature",
  "properties": {
    "iso:country":"GB",
    "sg:address":"17 High St",
    "sg:city":"Olney",
    "sg:classifiers":[
        {
            "category":"Professional",
            "type":"Services"
        }
    ],
    "sg:postcode":"MK46 4EB",
    "sg:province":"Buckinghamshire",
    "sg:tags":[
        "interior",
        "furnishers",
        "designer"
    ],
    "wof:name":"Ward,Richard,",
    "wof:placetype":"venue"
},
  "geometry": {"coordinates":[-0.7023339868,52.1518936157],"type":"Point"}
}