{
  "type": "Feature",
  "properties": {
    "addr:full":"Fletcher Way, Weston Road Norwich Norfolk NR3 3ST",
    "addr:postcode":"nr3 3st",
    "addr:street":"Fletcher Way Weston Road Norwich Norfolk",
    "iso:country":"GB",
    "sg:address":"Fletcher Way, Weston Road",
    "sg:city":"Norwich",
    "sg:classifiers":[
        {
            "category":"Home & Garden",
            "subcategory":"Furniture",
            "type":"Retail Goods"
        }
    ],
    "sg:phone":"+44 1603 486579",
    "sg:postcode":"NR3 3ST",
    "sg:province":"Norfolk",
    "sg:tags":[
        "outlet"
    ],
    "wof:name":"YOUNG BROS (NORWICH) LTD",
    "wof:placetype":"venue"
},
  "geometry": {"coordinates":[1.28284,52.654076],"type":"Point"}
}