{
  "type": "Feature",
  "properties": {
    "addr:full":"Haymore Mill, Broadshard Crewkerne Dorset TA18 7ND",
    "addr:postcode":"ta18 7nd",
    "addr:street":"Broadshard",
    "iso:country":"GB",
    "sg:address":"Haymore Mill, Broadshard",
    "sg:city":"Crewkerne",
    "sg:classifiers":[
        {
            "category":"Shopping",
            "subcategory":"Pets & Pet Supplies",
            "type":"Retail Goods"
        }
    ],
    "sg:postcode":"TA18 7ND",
    "sg:province":"Dorset",
    "sg:tags":[
        "food"
    ],
    "wof:name":"Agrilink Storage",
    "wof:placetype":"venue"
},
  "geometry": {"coordinates":[-2.7960140705,50.8843269348],"type":"Point"}
}