{
  "type": "Feature",
  "properties": {
    "iso:country":"GB",
    "sg:address":"Unit 2, Market Trading Estate, Christopher Rd",
    "sg:city":"Southall",
    "sg:classifiers":[
        {
            "category":"Freight",
            "type":"Transportation"
        }
    ],
    "sg:phone":"+44 20 8573 5773",
    "sg:postcode":"UB2 5YG",
    "sg:province":"Greater London",
    "sg:tags":[
        "forwarders"
    ],
    "wof:name":"Alpi Air",
    "wof:placetype":"venue"
},
  "geometry": {"coordinates":[-0.40582,51.497459],"type":"Point"}
}