{
  "type": "Feature",
  "properties": {
    "iso:country":"GB",
    "sg:address":"69 High Street, Wouldham",
    "sg:city":"Rochester",
    "sg:classifiers":[
        {
            "category":"Professional",
            "type":"Services"
        },
        {
            "category":"Food & Beverages",
            "subcategory":"Specialty",
            "type":"Retail Goods"
        }
    ],
    "sg:phone":"+44 1634 684637",
    "sg:postcode":"ME1 3XE",
    "sg:province":"Kent",
    "sg:tags":[
        "entertainer",
        "retailer",
        "health"
    ],
    "wof:name":"MARK GRAY",
    "wof:placetype":"venue"
},
  "geometry": {"coordinates":[0.457953006,51.3485336304],"type":"Point"}
}