{
  "type": "Feature",
  "properties": {
    "iso:country":"GB",
    "sg:address":"The Wheatsheaf Bldg, Speirs Wharf, Port Dundas",
    "sg:city":"Glasgow",
    "sg:classifiers":[
        {
            "category":"Professional",
            "subcategory":"Advertising",
            "type":"Services"
        }
    ],
    "sg:phone":"+44 141 332 1234",
    "sg:postcode":"G4 9TB",
    "sg:province":"Glasgow City",
    "sg:tags":[
        "agency"
    ],
    "wof:name":"Morgan Partnership Ltd (The)",
    "wof:placetype":"venue"
},
  "geometry": {"coordinates":[-4.25747,55.87236],"type":"Point"}
}