{
  "type": "Feature",
  "properties": {
    "addr:full":"44 Clapham Common, South Side London Greater London SW4 9BU",
    "addr:housenumber":"44",
    "addr:postcode":"sw4 9bu",
    "addr:street":"Clapham Common South Side",
    "iso:country":"GB",
    "sg:address":"44 Clapham Common, South Side",
    "sg:city":"London",
    "sg:classifiers":[
        {
            "category":"Building & Trades",
            "subcategory":"Cleaning & Sanitation",
            "type":"Services"
        }
    ],
    "sg:phone":"+44 20 7622 3387",
    "sg:postcode":"SW4 9BU",
    "sg:province":"Greater London",
    "sg:tags":[
        "hygiene",
        "cleansing"
    ],
    "wof:name":"Cannon Hygiene Ltd.",
    "wof:placetype":"venue"
},
  "geometry": {"coordinates":[-0.1414629966,51.4592170715],"type":"Point"}
}