{
  "type": "Feature",
  "properties": {
    "iso:country":"GB",
    "sg:address":"Unit 27 Tweedale Court, Tweedale Industrial Estate, Madeley",
    "sg:city":"Telford",
    "sg:classifiers":[
        {
            "category":"Personal",
            "subcategory":"Nail Salon",
            "type":"Services"
        }
    ],
    "sg:phone":"+44 1952 588881",
    "sg:postcode":"TF7 4JZ",
    "sg:province":"Shropshire",
    "sg:tags":[
        "technician"
    ],
    "wof:name":"B N Produsts",
    "wof:placetype":"venue"
},
  "geometry": {"coordinates":[-2.4437310696,52.6435394287],"type":"Point"}
}