{
  "type": "Feature",
  "properties": {
    "iso:country":"GB",
    "sg:address":"26 Nelson Road",
    "sg:city":"Blackpool",
    "sg:classifiers":[
        {
            "category":"Travel",
            "subcategory":"Hotels & Motels",
            "type":"Entertainment"
        }
    ],
    "sg:postcode":"FY1 6AS",
    "sg:province":"Lancashire",
    "sg:tags":[
        "house",
        "guest"
    ],
    "wof:name":"Del-Mar Guest House",
    "wof:placetype":"venue"
},
  "geometry": {"coordinates":[-3.05299,53.804283],"type":"Point"}
}