{
  "type": "Feature",
  "properties": {
    "iso:country":"GB",
    "sg:address":"21 Chestnut Close, Stowupland",
    "sg:city":"Stowmarket",
    "sg:classifiers":[
        {
            "category":"Professional",
            "subcategory":"Art Services",
            "type":"Services"
        },
        {
            "category":"Building & Trades",
            "subcategory":"Construction",
            "type":"Services"
        }
    ],
    "sg:phone":"+44 1449 675928",
    "sg:postcode":"IP14 4DN",
    "sg:province":"Suffolk",
    "sg:tags":[
        "ceiling",
        "decorator",
        "painter",
        "contractor"
    ],
    "wof:name":"Howard G Sutton",
    "wof:placetype":"venue"
},
  "geometry": {"coordinates":[1.019545,52.19838],"type":"Point"}
}