{
  "type": "Feature",
  "properties": {
    "iso:country":"GB",
    "sg:address":"The Media Playground, 19 Lind Street",
    "sg:city":"Manchester",
    "sg:classifiers":[
        {
            "category":"Shopping",
            "subcategory":"Computers & Home Electronics",
            "type":"Retail Goods"
        }
    ],
    "sg:phone":"+44 161 273 7228",
    "sg:postcode":"M40 7ES",
    "sg:province":"Greater Manchester",
    "sg:tags":[
        "consumables"
    ],
    "wof:name":"A1 Card & Stationery Services",
    "wof:placetype":"venue"
},
  "geometry": {"coordinates":[-2.2124500275,53.4848213196],"type":"Point"}
}