{
  "type": "Feature",
  "properties": {
    "iso:country":"GB",
    "sg:address":"28 Forest Road, Pontarddulais",
    "sg:city":"Swansea",
    "sg:classifiers":[
        {
            "category":"Building & Trades",
            "subcategory":"Construction",
            "type":"Services"
        }
    ],
    "sg:postcode":"SA4 0TN",
    "sg:province":"Carmarthenshire",
    "sg:tags":[
        "builder"
    ],
    "wof:name":"D & G Builders",
    "wof:placetype":"venue"
},
  "geometry": {"coordinates":[-4.046628952,51.7161941528],"type":"Point"}
}