{
  "type": "Feature",
  "properties": {
    "iso:country":"GB",
    "sg:address":"40 Gaol Lane",
    "sg:city":"Sudbury",
    "sg:classifiers":[
        {
            "category":"Education",
            "subcategory":"College",
            "type":"Public Place"
        }
    ],
    "sg:phone":"+44 1787 881500",
    "sg:postcode":"CO10 1JL",
    "sg:province":"Essex",
    "sg:tags":[
        "school"
    ],
    "wof:name":"Greens Clothing Co.",
    "wof:placetype":"venue"
},
  "geometry": {"coordinates":[0.730378,52.039505],"type":"Point"}
}