{
  "type": "Feature",
  "properties": {
    "addr:full":"Pykards Hall Bury St Edmunds Suffolk IP29 4AY",
    "addr:postcode":"ip29 4ay",
    "iso:country":"GB",
    "sg:address":"Pykards Hall",
    "sg:city":"Bury St Edmunds",
    "sg:classifiers":[
        {
            "category":"Professional",
            "subcategory":"Printing & Photocopies",
            "type":"Services"
        }
    ],
    "sg:postcode":"IP29 4AY",
    "sg:province":"Suffolk",
    "sg:tags":[
        "printer"
    ],
    "wof:name":"Cat Print",
    "wof:placetype":"venue"
},
  "geometry": {"coordinates":[0.63752,52.167881],"type":"Point"}
}