{
  "type": "Feature",
  "properties": {
    "iso:country":"GB",
    "sg:address":"81-83 Bank Street, Rawtenstall",
    "sg:city":"Rossendale",
    "sg:classifiers":[
        {
            "category":"Shopping",
            "subcategory":"Clothing, Apparel, & Fashions",
            "type":"Retail Goods"
        },
        {
            "category":"Education",
            "subcategory":"University",
            "type":"Public Place"
        }
    ],
    "sg:phone":"+44 1706 213539",
    "sg:postcode":"BB4 7QN",
    "sg:province":"Lancashire",
    "sg:tags":[
        "shop",
        "school",
        "outfitter"
    ],
    "wof:name":"Amin Fashion Stores",
    "wof:placetype":"venue"
},
  "geometry": {"coordinates":[-2.284603,53.703617],"type":"Point"}
}