{
  "type": "Feature",
  "properties": {
    "iso:country":"GB",
    "sg:address":"Alexandra Road",
    "sg:city":"Penzance",
    "sg:classifiers":[
        {
            "category":"Travel",
            "subcategory":"Hotels & Motels",
            "type":"Entertainment"
        }
    ],
    "sg:postcode":"TR18 4LZ",
    "sg:province":"Cornwall",
    "wof:name":"Penmorvah Hotel",
    "wof:placetype":"venue"
},
  "geometry": {"coordinates":[-5.541574,50.114639],"type":"Point"}
}