{
  "type": "Feature",
  "properties": {
    "addr:full":"Gerrard Street Aberdeen Aberdeen City AB1 1HP",
    "addr:postcode":"ab1 1hp",
    "addr:street":"Gerrard Street",
    "iso:country":"GB",
    "sg:address":"Gerrard Street",
    "sg:city":"Aberdeen",
    "sg:classifiers":[
        {
            "category":"Arena",
            "subcategory":"Sports Club",
            "type":"Entertainment"
        }
    ],
    "sg:phone":"+44 1224 635408",
    "sg:postcode":"AB1 1HP",
    "sg:province":"Aberdeen City",
    "wof:name":"Dee Swimming Club & Humane Society",
    "wof:placetype":"venue"
},
  "geometry": {"coordinates":[-2.1014990807,57.1531639099],"type":"Point"}
}