{
  "type": "Feature",
  "properties": {
    "iso:country":"GB",
    "sg:address":"228a Romford Road, Forest Gate",
    "sg:city":"London",
    "sg:classifiers":[
        {
            "category":"Organizations",
            "subcategory":"Non-profit Organization",
            "type":"Services"
        }
    ],
    "sg:phone":"+44 20 8503 1511",
    "sg:postcode":"E7 9HZ",
    "sg:province":"Greater London",
    "sg:tags":[
        "organisation",
        "voluntary",
        "charity"
    ],
    "wof:name":"Age Concern Newham Trading Co. Ltd.",
    "wof:placetype":"venue"
},
  "geometry": {"coordinates":[0.0210870001,51.5457344055],"type":"Point"}
}