{
  "type": "Feature",
  "properties": {
    "iso:country":"GB",
    "sg:address":"Moorside Farm, Brookhouse",
    "sg:city":"Lancaster",
    "sg:classifiers":[
        {
            "category":"Farming",
            "subcategory":"Livestock Farm",
            "type":"Manufacturing & Wholesale Goods"
        }
    ],
    "sg:phone":"+44 1524 770721",
    "sg:postcode":"LA2 9PN",
    "sg:province":"Lancashire",
    "sg:tags":[
        "others"
    ],
    "wof:name":"A J Kevill",
    "wof:placetype":"venue"
},
  "geometry": {"coordinates":[-2.703013,54.074707],"type":"Point"}
}