{
  "type": "Feature",
  "properties": {
    "addr:full":"12 Rose Terr Perth Perth and Kinross PH1 5HA",
    "addr:housenumber":"12",
    "addr:postcode":"ph1 5ha",
    "addr:street":"Rose Terr",
    "iso:country":"GB",
    "sg:address":"12 Rose Terr",
    "sg:city":"Perth",
    "sg:classifiers":[
        {
            "category":"Shopping",
            "subcategory":"Clothing, Apparel, & Fashions",
            "type":"Retail Goods"
        }
    ],
    "sg:phone":"+44 1738 444226",
    "sg:postcode":"PH1 5HA",
    "sg:province":"Perth and Kinross",
    "sg:tags":[
        "shop",
        "dress",
        "fancy"
    ],
    "wof:name":"Fancy Dress Workshop & Costume Hire",
    "wof:placetype":"venue"
},
  "geometry": {"coordinates":[-3.4326879978,56.4005584717],"type":"Point"}
}