{
  "type": "Feature",
  "properties": {
    "iso:country":"GB",
    "sg:address":"17 Clarence Ct, The Broadway",
    "sg:city":"Mill Hill",
    "sg:classifiers":[
        {
            "category":"Building & Trades",
            "subcategory":"Plumbing",
            "type":"Services"
        }
    ],
    "sg:phone":"+44 20 8959 1944",
    "sg:postcode":"NW7 4RP",
    "sg:province":"Greater London",
    "sg:tags":[
        "central",
        "heating"
    ],
    "wof:name":"Addison",
    "wof:placetype":"venue"
},
  "geometry": {"coordinates":[-0.2485900074,51.6142616272],"type":"Point"}
}