{
  "type": "Feature",
  "properties": {
    "iso:country":"GB",
    "sg:address":"The Health Centre, Church St",
    "sg:city":"Houghton Le Spring",
    "sg:classifiers":[
        {
            "category":"Health Services",
            "subcategory":"Doctor",
            "type":"Services"
        }
    ],
    "sg:phone":"+44 191 584 2106",
    "sg:postcode":"DH4 4DN",
    "sg:province":"Durham",
    "sg:tags":[
        "practitioners"
    ],
    "wof:name":"Locke Dr S I",
    "wof:placetype":"venue"
},
  "geometry": {"coordinates":[-1.48806,54.867691],"type":"Point"}
}