{
  "type": "Feature",
  "properties": {
    "addr:full":"219 Hawthorn Road Birmingham West Midlands B44 8PL",
    "addr:housenumber":"219",
    "addr:postcode":"b44 8pl",
    "addr:street":"Hawthorn Road",
    "iso:country":"GB",
    "sg:address":"219 Hawthorn Road",
    "sg:city":"Birmingham",
    "sg:classifiers":[
        {
            "category":"Food & Beverages",
            "subcategory":"Liquor & Beverages",
            "type":"Retail Goods"
        }
    ],
    "sg:phone":"+44 121 373 2286",
    "sg:postcode":"B44 8PL",
    "sg:province":"West Midlands",
    "sg:tags":[
        "beer",
        "wine",
        "spirit",
        "wines"
    ],
    "wof:name":"Drinks Cabin",
    "wof:placetype":"venue"
},
  "geometry": {"coordinates":[-1.88403,52.540932],"type":"Point"}
}