{
  "type": "Feature",
  "properties": {
    "addr:full":"35 Kenneth Road, Arnold Nottingham Nottinghamshire NG5 8HY",
    "addr:housenumber":"35",
    "addr:postcode":"ng5 8hy",
    "addr:street":"Kenneth Road",
    "iso:country":"GB",
    "sg:address":"35 Kenneth Road, Arnold",
    "sg:city":"Nottingham",
    "sg:classifiers":[
        {
            "category":"Professional",
            "subcategory":"Engineering",
            "type":"Services"
        }
    ],
    "sg:postcode":"NG5 8HY",
    "sg:province":"Nottinghamshire",
    "sg:tags":[
        "contractor",
        "electrical",
        "engineer"
    ],
    "wof:name":"D & M Electrical Services",
    "wof:placetype":"venue"
},
  "geometry": {"coordinates":[-1.1269010305,53.0135955811],"type":"Point"}
}