{
  "type": "Feature",
  "properties": {
    "iso:country":"GB",
    "sg:address":"Lamberts Lane",
    "sg:city":"Midhurst",
    "sg:classifiers":[
        {
            "category":"Social Services",
            "subcategory":"Retirement Home",
            "type":"Services"
        }
    ],
    "sg:postcode":"GU29 9DZ",
    "sg:province":"West Sussex",
    "sg:tags":[
        "residential",
        "care"
    ],
    "wof:name":"Rother House",
    "wof:placetype":"venue"
},
  "geometry": {"coordinates":[-0.73969,50.98904],"type":"Point"}
}