{
  "type": "Feature",
  "properties": {
    "addr:full":"Worcester Road Tenbury Wells Herefordshire WR15 8AR",
    "addr:postcode":"wr15 8ar",
    "addr:street":"Worcester Road",
    "iso:country":"GB",
    "sg:address":"Worcester Road",
    "sg:city":"Tenbury Wells",
    "sg:classifiers":[
        {
            "category":"Autos & Motor Vehicles",
            "subcategory":"Fuel & Gas Station",
            "type":"Retail Goods"
        }
    ],
    "sg:phone":"+44 1584 810756",
    "sg:postcode":"WR15 8AR",
    "sg:province":"Herefordshire",
    "sg:tags":[
        "hr",
        "petrol"
    ],
    "wof:name":"B J & E Maybury & Co. Ltd.",
    "wof:placetype":"venue"
},
  "geometry": {"coordinates":[-2.594179,52.312584],"type":"Point"}
}