{
  "type": "Feature",
  "properties": {
    "iso:country":"GB",
    "sg:address":"21 High St",
    "sg:city":"Slough",
    "sg:classifiers":[
        {
            "category":"Social Services",
            "subcategory":"Retirement Home",
            "type":"Services"
        }
    ],
    "sg:phone":"+44 1753 550600",
    "sg:postcode":"SL1 1DY",
    "sg:province":"Berkshire",
    "sg:tags":[
        "care"
    ],
    "wof:name":"Goldsborough Homecare & Nursing Services",
    "wof:placetype":"venue"
},
  "geometry": {"coordinates":[-0.6583729982,51.5323982239],"type":"Point"}
}