{
  "type": "Feature",
  "properties": {
    "iso:country":"GB",
    "sg:address":"Whistley Grn, Hurst",
    "sg:city":"Reading",
    "sg:classifiers":[
        {
            "category":"Autos & Motor Vehicles",
            "subcategory":"Auto Supplies",
            "type":"Retail Goods"
        }
    ],
    "sg:postcode":"RG10 0EA",
    "sg:province":"Berkshire",
    "sg:tags":[
        "tyre"
    ],
    "wof:name":"Hurst Tyre Co",
    "wof:placetype":"venue"
},
  "geometry": {"coordinates":[-0.8528860211,51.4585494995],"type":"Point"}
}