{
  "type": "Feature",
  "properties": {
    "iso:country":"GB",
    "sg:address":"1 St Johns Square",
    "sg:city":"Abergavenny",
    "sg:classifiers":[
        {
            "category":"Government",
            "subcategory":"Post Office",
            "type":"Public Place"
        }
    ],
    "sg:phone":"+44 1873 852833",
    "sg:postcode":"NP7 5EB",
    "sg:province":"Herefordshire",
    "wof:name":"Post Office Counters Ltd.",
    "wof:placetype":"venue"
},
  "geometry": {"coordinates":[-3.018911,51.821693],"type":"Point"}
}