{
  "type": "Feature",
  "properties": {
    "iso:country":"GB",
    "sg:address":"Coed Isa, Downing Road, Whitford",
    "sg:city":"Holywell",
    "sg:classifiers":[
        {
            "category":"Farming",
            "subcategory":"Livestock Farm",
            "type":"Manufacturing & Wholesale Goods"
        },
        {
            "category":"Farming",
            "subcategory":"Farm",
            "type":"Manufacturing & Wholesale Goods"
        }
    ],
    "sg:postcode":"CH8 9EG",
    "sg:province":"Denbighshire",
    "sg:tags":[
        "mixed",
        "crop",
        "others"
    ],
    "wof:name":"Thomas Axon",
    "wof:placetype":"venue"
},
  "geometry": {"coordinates":[-3.251179,53.302059],"type":"Point"}
}