{
  "type": "Feature",
  "properties": {
    "addr:full":"457 West Green Road London Greater London N15 3PW",
    "addr:housenumber":"457",
    "addr:postcode":"n15 3pw",
    "addr:street":"West Green Road",
    "iso:country":"GB",
    "sg:address":"457 West Green Road",
    "sg:city":"London",
    "sg:classifiers":[
        {
            "category":"Freight",
            "type":"Transportation"
        },
        {
            "category":"Real Estate",
            "subcategory":"Real Estate Agent",
            "type":"Services"
        }
    ],
    "sg:phone":"+44 20 8365 8888",
    "sg:postcode":"N15 3PW",
    "sg:province":"Greater London",
    "sg:tags":[
        "ship",
        "overseas",
        "shipping",
        "removal"
    ],
    "wof:name":"Euromed Maritime Ltd",
    "wof:placetype":"venue"
},
  "geometry": {"coordinates":[-0.098698,51.587303],"type":"Point"}
}