{
  "type": "Feature",
  "properties": {
    "addr:full":"Heugh Road, Portpatrick Stranraer Dumfries and Galloway DG9 8TD",
    "addr:postcode":"dg9 8td",
    "addr:street":"Heugh Road",
    "iso:country":"GB",
    "sg:address":"Heugh Road, Portpatrick",
    "sg:city":"Stranraer",
    "sg:classifiers":[
        {
            "category":"Travel",
            "subcategory":"Hotels & Motels",
            "type":"Entertainment"
        }
    ],
    "sg:phone":"+44 1776 810316",
    "sg:postcode":"DG9 8TD",
    "sg:province":"Dumfries and Galloway",
    "sg:tags":[
        "house",
        "guest"
    ],
    "wof:name":"Crest House",
    "wof:placetype":"venue"
},
  "geometry": {"coordinates":[-5.0164442062,54.9056358337],"type":"Point"}
}