{
  "type": "Feature",
  "properties": {
    "addr:full":"Manson Road Perth Perth and Kinross PH2 8BP",
    "addr:postcode":"ph2 8bp",
    "addr:street":"Manson Road",
    "iso:country":"GB",
    "sg:address":"Manson Road",
    "sg:city":"Perth",
    "sg:classifiers":[
        {
            "category":"Autos & Motor Vehicles",
            "subcategory":"Automobile Sales",
            "type":"Retail Goods"
        }
    ],
    "sg:phone":"+44 1738 630606",
    "sg:postcode":"PH2 8BP",
    "sg:province":"Perth and Kinross",
    "sg:tags":[
        "car"
    ],
    "wof:name":"Westcars Tayside Ltd.",
    "wof:placetype":"venue"
},
  "geometry": {"coordinates":[-3.433073,56.385258],"type":"Point"}
}