{
  "type": "Feature",
  "properties": {
    "addr:full":"46 Bridge Road, Sutton Bridge Spalding Cambridgeshire PE12 9UA",
    "addr:housenumber":"46",
    "addr:postcode":"pe12 9ua",
    "addr:street":"Bridge Road",
    "iso:country":"GB",
    "sg:address":"46 Bridge Road, Sutton Bridge",
    "sg:city":"Spalding",
    "sg:classifiers":[
        {
            "category":"Bars & Pubs",
            "type":"Food & Drink"
        },
        {
            "category":"Community Center",
            "subcategory":"Social",
            "type":"Public Place"
        }
    ],
    "sg:phone":"+44 1406 351032",
    "sg:postcode":"PE12 9UA",
    "sg:province":"Cambridgeshire",
    "sg:tags":[
        "pubs",
        "house",
        "inn",
        "activity"
    ],
    "wof:name":"New Inn",
    "wof:placetype":"venue"
},
  "geometry": {"coordinates":[0.13888,52.779762],"type":"Point"}
}