{
  "type": "Feature",
  "properties": {
    "iso:country":"GB",
    "sg:address":"7-17 North Road",
    "sg:city":"Middlesbrough",
    "sg:classifiers":[
        {
            "category":"Autos & Motor Vehicles",
            "subcategory":"Auto Supplies",
            "type":"Retail Goods"
        }
    ],
    "sg:phone":"+44 1642 244048",
    "sg:postcode":"TS2 1BZ",
    "sg:province":"Durham",
    "sg:tags":[
        "component"
    ],
    "wof:name":"Eec (Fl) Realisations Ltd.",
    "wof:placetype":"venue"
},
  "geometry": {"coordinates":[-1.2412589788,54.579788208],"type":"Point"}
}