{
  "type": "Feature",
  "properties": {
    "addr:full":"47 Federation Rd London Greater London SE2 0JT",
    "addr:housenumber":"47",
    "addr:postcode":"se2 0jt",
    "addr:street":"Federation Rd",
    "iso:country":"GB",
    "sg:address":"47 Federation Rd",
    "sg:city":"London",
    "sg:classifiers":[
        {
            "category":"Retail",
            "subcategory":"Auto Repair",
            "type":"Services"
        }
    ],
    "sg:postcode":"SE2 0JT",
    "sg:province":"Greater London",
    "sg:tags":[
        "engine",
        "car",
        "specialist"
    ],
    "wof:name":"Carhill,M T,",
    "wof:placetype":"venue"
},
  "geometry": {"coordinates":[0.1162720025,51.4870414734],"type":"Point"}
}