{
  "type": "Feature",
  "properties": {
    "addr:full":"The Lees, Adderley Market Drayton Shropshire TF9 3SU",
    "addr:postcode":"tf9 3su",
    "iso:country":"GB",
    "sg:address":"The Lees, Adderley",
    "sg:city":"Market Drayton",
    "sg:classifiers":[
        {
            "category":"Farming",
            "subcategory":"Dairy Farm",
            "type":"Manufacturing & Wholesale Goods"
        },
        {
            "category":"Farming",
            "subcategory":"Livestock Farm",
            "type":"Manufacturing & Wholesale Goods"
        }
    ],
    "sg:phone":"+44 1630 653815",
    "sg:postcode":"TF9 3SU",
    "sg:province":"Shropshire",
    "sg:tags":[
        "others",
        "farmer"
    ],
    "wof:name":"Lees Dairy Farmers",
    "wof:placetype":"venue"
},
  "geometry": {"coordinates":[-2.486172,52.904091],"type":"Point"}
}