{
  "type": "Feature",
  "properties": {
    "addr:full":"88 The Bdwy London Greater London NW7 3TB",
    "addr:housenumber":"88",
    "addr:postcode":"nw7 3tb",
    "addr:street":"The Bdwy",
    "iso:country":"GB",
    "sg:address":"88 The Bdwy",
    "sg:city":"London",
    "sg:classifiers":[
        {
            "category":"Home & Garden",
            "subcategory":"Furniture",
            "type":"Retail Goods"
        }
    ],
    "sg:postcode":"NW7 3TB",
    "sg:province":"Greater London",
    "wof:name":"Kitty Sansome Ltd.",
    "wof:placetype":"venue"
},
  "geometry": {"coordinates":[-0.2448240072,51.6158409119],"type":"Point"}
}