{
  "type": "Feature",
  "properties": {
    "iso:country":"GB",
    "sg:address":"Woldview Farm, North Dalton",
    "sg:city":"Driffield",
    "sg:classifiers":[
        {
            "category":"Farming",
            "subcategory":"Livestock Farm",
            "type":"Manufacturing & Wholesale Goods"
        }
    ],
    "sg:postcode":"YO25 9XD",
    "sg:province":"East Riding of Yorkshire",
    "sg:tags":[
        "others"
    ],
    "wof:name":"T Foxton & Sons",
    "wof:placetype":"venue"
},
  "geometry": {"coordinates":[-0.575117,53.957779],"type":"Point"}
}