{
  "type": "Feature",
  "properties": {
    "iso:country":"GB",
    "sg:address":"6 Millington Road",
    "sg:city":"Hayes",
    "sg:classifiers":[
        {
            "category":"Food & Beverages",
            "subcategory":"Supermarket",
            "type":"Retail Goods"
        },
        {
            "category":"Military Area",
            "subcategory":"Air Force Base",
            "type":"Public Place"
        }
    ],
    "sg:phone":"+44 20 8848 8744",
    "sg:postcode":"UB3 4AY",
    "sg:province":"Greater London",
    "sg:tags":[
        "ftse"
    ],
    "wof:name":"Safeway Stores Ltd.",
    "wof:placetype":"venue"
},
  "geometry": {"coordinates":[-0.4283440113,51.5026245117],"type":"Point"}
}