{
  "type": "Feature",
  "properties": {
    "addr:full":"20 Holden Clough Drive Ashton-under-lyne Greater Manchester OL7 9TH",
    "addr:housenumber":"20",
    "addr:postcode":"ashton-under-lyne;ol7 9th",
    "addr:street":"Holden Clough Drive",
    "iso:country":"GB",
    "sg:address":"20 Holden Clough Drive",
    "sg:city":"Ashton-under-lyne",
    "sg:classifiers":[
        {
            "category":"Building & Trades",
            "subcategory":"Landscaping Services",
            "type":"Services"
        }
    ],
    "sg:phone":"+44 161 330 0161",
    "sg:postcode":"OL7 9TH",
    "sg:province":"Greater Manchester",
    "sg:tags":[
        "landscape",
        "contractor"
    ],
    "wof:name":"Shippon Landscapes",
    "wof:placetype":"venue"
},
  "geometry": {"coordinates":[-2.098088026,53.5076942444],"type":"Point"}
}