{
  "type": "Feature",
  "properties": {
    "iso:country":"GB",
    "sg:address":"1 Bollihope Gro",
    "sg:city":"Bishop Auckland",
    "sg:classifiers":[
        {
            "category":"Personal",
            "type":"Services"
        }
    ],
    "sg:postcode":"DL14 0SA",
    "sg:province":"Durham",
    "sg:tags":[
        "wedding"
    ],
    "wof:name":"Andrew's Wedding Photography",
    "wof:placetype":"venue"
},
  "geometry": {"coordinates":[-1.699753,54.64814],"type":"Point"}
}