{
  "type": "Feature",
  "properties": {
    "addr:full":"Purfleet Industrial Park, 19 Juliet Way South Ockendon Essex RM15 4YD",
    "addr:housenumber":"19",
    "addr:postcode":"rm15 4yd",
    "addr:street":"Juliet Way",
    "iso:country":"GB",
    "sg:address":"Purfleet Industrial Park, 19 Juliet Way",
    "sg:city":"South Ockendon",
    "sg:classifiers":[
        {
            "category":"Freight",
            "type":"Transportation"
        }
    ],
    "sg:phone":"+44 1708 866444",
    "sg:postcode":"RM15 4YD",
    "sg:province":"Essex",
    "sg:tags":[
        "haulage",
        "road"
    ],
    "wof:name":"Cyril Knowles Ltd.",
    "wof:placetype":"venue"
},
  "geometry": {"coordinates":[0.2836500108,51.5024757385],"type":"Point"}
}