{
  "type": "Feature",
  "properties": {
    "addr:full":"Coutance Way, Burley In Wharfedale Ilkley North Yorkshire LS29 7HQ",
    "addr:postcode":"ls29 7hq",
    "addr:street":"Coutance Way",
    "iso:country":"GB",
    "sg:address":"Coutance Way, Burley In Wharfedale",
    "sg:city":"Ilkley",
    "sg:classifiers":[
        {
            "category":"Restaurant",
            "type":"Food & Drink"
        }
    ],
    "sg:phone":"+44 1943 864392",
    "sg:postcode":"LS29 7HQ",
    "sg:province":"North Yorkshire",
    "wof:name":"Little Chef",
    "wof:placetype":"venue"
},
  "geometry": {"coordinates":[-1.750624,53.913952],"type":"Point"}
}