{
  "type": "Feature",
  "properties": {
    "iso:country":"GB",
    "sg:address":"9 Greenfern Place",
    "sg:city":"Aberdeen",
    "sg:classifiers":[
        {
            "category":"Food & Beverages",
            "subcategory":"Specialty",
            "type":"Retail Goods"
        }
    ],
    "sg:phone":"+44 1224 662844",
    "sg:postcode":"AB16 6JR",
    "sg:province":"Aberdeen City",
    "sg:tags":[
        "product",
        "health"
    ],
    "wof:name":"WEIGH & SAVE",
    "wof:placetype":"venue"
},
  "geometry": {"coordinates":[-2.167722,57.154293],"type":"Point"}
}