{
  "type": "Feature",
  "properties": {
    "addr:full":"Rear Of 24 Hanford Way Loughborough Leicestershire LE11 1LS",
    "addr:housenumber":"rear of 24",
    "addr:postcode":"le11 1ls",
    "addr:street":"Hanford Way",
    "iso:country":"GB",
    "sg:address":"Rear Of 24 Hanford Way",
    "sg:city":"Loughborough",
    "sg:classifiers":[
        {
            "category":"Retail",
            "subcategory":"Auto Repair",
            "type":"Services"
        }
    ],
    "sg:phone":"+44 1509 236096",
    "sg:postcode":"LE11 1LS",
    "sg:province":"Leicestershire",
    "sg:tags":[
        "modification",
        "garage"
    ],
    "wof:name":"Jays Motors",
    "wof:placetype":"venue"
},
  "geometry": {"coordinates":[-1.2234740257,52.7685241699],"type":"Point"}
}