{
  "type": "Feature",
  "properties": {
    "addr:full":"Pettaugh Road, Stonham Aspal Stowmarket Suffolk IP14 6AT",
    "addr:postcode":"ip14 6at",
    "addr:street":"Pettaugh Road",
    "iso:country":"GB",
    "sg:address":"Pettaugh Road, Stonham Aspal",
    "sg:city":"Stowmarket",
    "sg:classifiers":[
        {
            "category":"Shopping",
            "subcategory":"Hobbies, Toys, & Games",
            "type":"Retail Goods"
        },
        {
            "category":"Transit Center",
            "subcategory":"Freight",
            "type":"Transportation"
        }
    ],
    "sg:phone":"+44 1449 711755",
    "sg:postcode":"IP14 6AT",
    "sg:province":"Suffolk",
    "sg:tags":[
        "collectors'",
        "item",
        "collector"
    ],
    "wof:name":"PAUL ANTILL",
    "wof:placetype":"venue"
},
  "geometry": {"coordinates":[1.1699750423,52.1915435791],"type":"Point"}
}