{
  "type": "Feature",
  "properties": {
    "addr:full":"Four Oaks Farm, Hundred Acre La, Streat Hassocks East Sussex BN6 8SH",
    "addr:housenumber":"hundred",
    "addr:postcode":"bn6 8sh",
    "addr:street":"Acre La Streat",
    "iso:country":"GB",
    "sg:address":"Four Oaks Farm, Hundred Acre La, Streat",
    "sg:city":"Hassocks",
    "sg:classifiers":[
        {
            "category":"Manufacturing",
            "subcategory":"Rubber & Plastics",
            "type":"Manufacturing & Wholesale Goods"
        },
        {
            "category":"Professional",
            "subcategory":"Engineering",
            "type":"Services"
        }
    ],
    "sg:postcode":"BN6 8SH",
    "sg:province":"East Sussex",
    "sg:tags":[
        "product",
        "engineer",
        "mechanical"
    ],
    "wof:name":"Wilson,John Ernest,",
    "wof:placetype":"venue"
},
  "geometry": {"coordinates":[-0.140269,50.923996],"type":"Point"}
}