{
  "type": "Feature",
  "properties": {
    "iso:country":"GB",
    "sg:address":"132-135 Lewes Road",
    "sg:city":"Brighton",
    "sg:classifiers":[
        {
            "category":"Retail",
            "subcategory":"Funeral Services",
            "type":"Services"
        }
    ],
    "sg:postcode":"BN2 3LG",
    "sg:province":"East Sussex",
    "wof:name":"Grosvenor Funeral Consultants",
    "wof:placetype":"venue"
},
  "geometry": {"coordinates":[-0.1251820028,50.8361053467],"type":"Point"}
}