{
  "type": "Feature",
  "properties": {
    "iso:country":"GB",
    "sg:address":"7 Lockwood Avenue",
    "sg:city":"Poulton-le-fylde",
    "sg:classifiers":[
        {
            "category":"Professional",
            "subcategory":"Engineering",
            "type":"Services"
        },
        {
            "category":"Building & Trades",
            "subcategory":"Construction",
            "type":"Services"
        }
    ],
    "sg:phone":"+44 1253 882777",
    "sg:postcode":"FY6 7AB",
    "sg:province":"Lancashire",
    "sg:tags":[
        "installers",
        "gas",
        "engineer"
    ],
    "wof:name":"A W Mortimer",
    "wof:placetype":"venue"
},
  "geometry": {"coordinates":[-2.992103,53.849312],"type":"Point"}
}