{
  "type": "Feature",
  "properties": {
    "iso:country":"GB",
    "sg:address":"17 Elm Tree Close",
    "sg:city":"Stalybridge",
    "sg:classifiers":[
        {
            "category":"Building & Trades",
            "subcategory":"Construction",
            "type":"Services"
        }
    ],
    "sg:phone":"+44 161 338 5538",
    "sg:postcode":"SK15 2HF",
    "sg:province":"Greater Manchester",
    "sg:tags":[
        "roofing"
    ],
    "wof:name":"Russell Smith",
    "wof:placetype":"venue"
},
  "geometry": {"coordinates":[-2.054629,53.477425],"type":"Point"}
}