{
  "type": "Feature",
  "properties": {
    "addr:full":"43a Settles Street London Greater London E1 1JN",
    "addr:housenumber":"43a",
    "addr:postcode":"e1 1jn",
    "addr:street":"Settles Street",
    "iso:country":"GB",
    "sg:address":"43a Settles Street",
    "sg:city":"London",
    "sg:classifiers":[
        {
            "category":"Building & Trades",
            "subcategory":"Construction",
            "type":"Services"
        }
    ],
    "sg:phone":"+44 20 7247 0008",
    "sg:postcode":"E1 1JN",
    "sg:province":"Greater London",
    "sg:tags":[
        "contractor"
    ],
    "wof:name":"Design & Construction Group",
    "wof:placetype":"venue"
},
  "geometry": {"coordinates":[-0.064646,51.516277],"type":"Point"}
}