{
  "type": "Feature",
  "properties": {
    "iso:country":"GB",
    "sg:address":"46 Meadenvale",
    "sg:city":"Peterborough",
    "sg:classifiers":[
        {
            "category":"Home & Garden",
            "subcategory":"Carpets & Floor Coverings",
            "type":"Retail Goods"
        }
    ],
    "sg:phone":"+44 1733 358374",
    "sg:postcode":"PE1 5PX",
    "sg:province":"Cambridgeshire",
    "sg:tags":[
        "carpets",
        "rug",
        "matting"
    ],
    "wof:name":"Carpet & Vinyl Specialist",
    "wof:placetype":"venue"
},
  "geometry": {"coordinates":[-0.206924,52.587765],"type":"Point"}
}