{
  "type": "Feature",
  "properties": {
    "iso:country":"GB",
    "sg:address":"Old Colliery Yard, Graddfa Rd, Llanbradach Ind Est, Llanbradach",
    "sg:city":"Caerphilly",
    "sg:classifiers":[
        {
            "category":"Wholesale",
            "subcategory":"Scrap",
            "type":"Manufacturing & Wholesale Goods"
        }
    ],
    "sg:phone":"+44 29 2086 0407",
    "sg:postcode":"CF83 3QS",
    "sg:province":"Caerphilly",
    "sg:tags":[
        "car",
        "breaker",
        "dismantlers"
    ],
    "wof:name":"G M H Salvage",
    "wof:placetype":"venue"
},
  "geometry": {"coordinates":[-3.227449,51.611214],"type":"Point"}
}