{
  "type": "Feature",
  "properties": {
    "addr:full":"15 Cedar Lawn Romsey Hampshire SO51 7US",
    "addr:housenumber":"15",
    "addr:postcode":"so51 7us",
    "addr:street":"Cedar Lawn",
    "iso:country":"GB",
    "sg:address":"15 Cedar Lawn",
    "sg:city":"Romsey",
    "sg:classifiers":[
        {
            "category":"Banks & Credit Unions",
            "subcategory":"Financial Services",
            "type":"Services"
        }
    ],
    "sg:postcode":"SO51 7US",
    "sg:province":"Hampshire",
    "sg:tags":[
        "adviser"
    ],
    "wof:name":"Cedar Financial Services",
    "wof:placetype":"venue"
},
  "geometry": {"coordinates":[-1.472225,50.998394],"type":"Point"}
}