{
  "type": "Feature",
  "properties": {
    "addr:full":"Orchard House, Trewedna Lane, Perranwell Station Truro Cornwall TR3 7PG",
    "addr:postcode":"tr3 7pg",
    "addr:street":"Trewedna Lane Perranwell Station",
    "iso:country":"GB",
    "sg:address":"Orchard House, Trewedna Lane, Perranwell Station",
    "sg:city":"Truro",
    "sg:classifiers":[
        {
            "category":"Health Services",
            "subcategory":"Health Practitioner",
            "type":"Services"
        }
    ],
    "sg:phone":"+44 1872 864710",
    "sg:postcode":"TR3 7PG",
    "sg:province":"Cornwall",
    "sg:tags":[
        "physiotherapist"
    ],
    "wof:name":"Perranwell Physiotherapy",
    "wof:placetype":"venue"
},
  "geometry": {"coordinates":[-5.126119,50.20742],"type":"Point"}
}