{
  "type": "Feature",
  "properties": {
    "addr:full":"South Lodge Farm, Station Rd Scarborough North Yorkshire YO13 9AP",
    "addr:postcode":"yo13 9ap",
    "addr:street":"Station Rd",
    "iso:country":"GB",
    "sg:address":"South Lodge Farm, Station Rd",
    "sg:city":"Scarborough",
    "sg:classifiers":[
        {
            "category":"Social Services",
            "subcategory":"Retirement Home",
            "type":"Services"
        }
    ],
    "sg:phone":"+44 1723 859189",
    "sg:postcode":"YO13 9AP",
    "sg:province":"North Yorkshire",
    "sg:tags":[
        "care"
    ],
    "wof:name":"Eldercare",
    "wof:placetype":"venue"
},
  "geometry": {"coordinates":[-0.5905799866,54.2261581421],"type":"Point"}
}