{
  "type": "Feature",
  "properties": {
    "addr:full":"Unit 3 Watermill Indstl Est, Aspenden Rd Buntingford Hertfordshire SG9 9JB",
    "addr:housenumber":"unit 3",
    "addr:postcode":"sg9 9jb",
    "addr:street":"Watermill Indstl Est Aspenden Rd",
    "iso:country":"GB",
    "sg:address":"Unit 3 Watermill Indstl Est, Aspenden Rd",
    "sg:city":"Buntingford",
    "sg:classifiers":[
        {
            "category":"Manufacturing",
            "subcategory":"Petroleum Products",
            "type":"Manufacturing & Wholesale Goods"
        }
    ],
    "sg:phone":"+44 1763 273668",
    "sg:postcode":"SG9 9JB",
    "sg:province":"Hertfordshire",
    "sg:tags":[
        "double",
        "glazing"
    ],
    "wof:name":"Cheshunt Glasswork",
    "wof:placetype":"venue"
},
  "geometry": {"coordinates":[-0.0186349992,51.9463005066],"type":"Point"}
}