{
  "type": "Feature",
  "properties": {
    "addr:full":"North Road Middlesbrough Durham TS2 1BZ",
    "addr:postcode":"ts2 1bz",
    "addr:street":"North Road",
    "iso:country":"GB",
    "sg:address":"North Road",
    "sg:city":"Middlesbrough",
    "sg:classifiers":[
        {
            "category":"Food & Beverages",
            "subcategory":"Meat & Fish",
            "type":"Retail Goods"
        }
    ],
    "sg:phone":"+44 1642 242637",
    "sg:postcode":"TS2 1BZ",
    "sg:province":"Durham",
    "sg:tags":[
        "merchant"
    ],
    "wof:name":"Junella Fish Merchants & Catering Services Ltd.",
    "wof:placetype":"venue"
},
  "geometry": {"coordinates":[-1.2414940596,54.5796661377],"type":"Point"}
}