{
  "type": "Feature",
  "properties": {
    "iso:country":"GB",
    "sg:address":"49a Market Place",
    "sg:city":"Beverley",
    "sg:classifiers":[
        {
            "category":"Professional",
            "subcategory":"Accounting & Tax Preparation",
            "type":"Services"
        }
    ],
    "sg:phone":"+44 1482 870055",
    "sg:postcode":"HU17 8AA",
    "sg:province":"East Riding of Yorkshire",
    "sg:tags":[
        "accountant"
    ],
    "wof:name":"Edwin Jones & Co",
    "wof:placetype":"venue"
},
  "geometry": {"coordinates":[-0.432449013,53.8428115845],"type":"Point"}
}