{
  "type": "Feature",
  "properties": {
    "iso:country":"GB",
    "sg:address":"The Garage, Howe Lane, Goxhill",
    "sg:city":"Barrow-upon-humber",
    "sg:classifiers":[
        {
            "category":"Retail",
            "subcategory":"Auto Repair",
            "type":"Services"
        }
    ],
    "sg:phone":"+44 1469 530238",
    "sg:postcode":"DN19 7HS",
    "sg:province":"Lincolnshire",
    "sg:tags":[
        "modification",
        "garage",
        "related"
    ],
    "wof:name":"Mellers Coaches Ltd",
    "wof:placetype":"venue"
},
  "geometry": {"coordinates":[-0.381838,53.675011],"type":"Point"}
}