{
  "type": "Feature",
  "properties": {
    "addr:full":"Wensley House, Park Lane, Madeley Telford Shropshire TF7 5HN",
    "addr:postcode":"tf7 5hn",
    "addr:street":"Park Lane",
    "iso:country":"GB",
    "sg:address":"Wensley House, Park Lane, Madeley",
    "sg:city":"Telford",
    "sg:classifiers":[
        {
            "category":"Home & Garden",
            "subcategory":"Household Appliances",
            "type":"Retail Goods"
        }
    ],
    "sg:phone":"+44 1952 401005",
    "sg:postcode":"TF7 5HN",
    "sg:province":"Shropshire",
    "sg:tags":[
        "domestic",
        "oven",
        "microwave"
    ],
    "wof:name":"Shropshire Microwave Services",
    "wof:placetype":"venue"
},
  "geometry": {"coordinates":[-2.4723520279,52.6390838623],"type":"Point"}
}