{
  "type": "Feature",
  "properties": {
    "iso:country":"GB",
    "sg:address":"1 Cavendish Rd, Eccleshill",
    "sg:city":"Bradford",
    "sg:classifiers":[
        {
            "category":"Professional",
            "subcategory":"Engineering",
            "type":"Services"
        }
    ],
    "sg:phone":"+44 1274 639363",
    "sg:postcode":"BD2 2DS",
    "sg:province":"West Yorkshire",
    "sg:tags":[
        "gas",
        "engineer"
    ],
    "wof:name":"Gas Safety Services",
    "wof:placetype":"venue"
},
  "geometry": {"coordinates":[-1.7212840319,53.8212013245],"type":"Point"}
}