{
  "type": "Feature",
  "properties": {
    "addr:full":"5 Market Street Wisbech Cambridgeshire PE13 1EX",
    "addr:housenumber":"5",
    "addr:postcode":"pe13 1ex",
    "addr:street":"Market Street",
    "iso:country":"GB",
    "sg:address":"5 Market Street",
    "sg:city":"Wisbech",
    "sg:classifiers":[
        {
            "category":"Shopping",
            "subcategory":"Bicycles & Sporting Goods",
            "type":"Retail Goods"
        }
    ],
    "sg:phone":"+44 1945 589509",
    "sg:postcode":"PE13 1EX",
    "sg:province":"Cambridgeshire",
    "sg:tags":[
        "cycle",
        "accessory"
    ],
    "wof:name":"The Bike Shop",
    "wof:placetype":"venue"
},
  "geometry": {"coordinates":[0.16066,52.6646],"type":"Point"}
}