{
  "type": "Feature",
  "properties": {
    "iso:country":"GB",
    "sg:address":"Pinfold Lane",
    "sg:city":"Bridlington",
    "sg:classifiers":[
        {
            "category":"Autos & Motor Vehicles",
            "subcategory":"Automobile Sales",
            "type":"Retail Goods"
        },
        {
            "category":"Retail",
            "subcategory":"Auto Repair",
            "type":"Services"
        }
    ],
    "sg:phone":"+44 1262 674044",
    "sg:postcode":"YO16 7AF",
    "sg:province":"East Riding of Yorkshire",
    "sg:tags":[
        "auction",
        "car",
        "related",
        "garage"
    ],
    "wof:name":"BRUNSWICK GARAGE LTD",
    "wof:placetype":"venue"
},
  "geometry": {"coordinates":[-0.204074,54.100014],"type":"Point"}
}