{
  "type": "Feature",
  "properties": {
    "addr:full":"Langley Mill, Langley Road Salford Greater Manchester M6 6JP",
    "addr:postcode":"m6 6jp",
    "addr:street":"Langley Road",
    "iso:country":"GB",
    "sg:address":"Langley Mill, Langley Road",
    "sg:city":"Salford",
    "sg:classifiers":[
        {
            "category":"Home & Garden",
            "subcategory":"Home Furnishings",
            "type":"Retail Goods"
        },
        {
            "category":"Manufacturing",
            "subcategory":"Textiles",
            "type":"Manufacturing & Wholesale Goods"
        }
    ],
    "sg:postcode":"M6 6JP",
    "sg:province":"Greater Manchester",
    "sg:tags":[
        "made-up",
        "beds",
        "bedding",
        "printer",
        "blanket"
    ],
    "wof:name":"Wills Fabrics Ltd.",
    "wof:placetype":"venue"
},
  "geometry": {"coordinates":[-2.282739,53.496216],"type":"Point"}
}