{
  "type": "Feature",
  "properties": {
    "addr:full":"16-17 Montpellier Arcade, Montpellier Cheltenham Gloucestershire GL50 1SU",
    "addr:housenumber":"16-17",
    "addr:postcode":"gl50 1su",
    "addr:street":"Montpellier Arcade",
    "iso:country":"GB",
    "sg:address":"16-17 Montpellier Arcade, Montpellier",
    "sg:city":"Cheltenham",
    "sg:classifiers":[
        {
            "category":"Communications",
            "type":"Services"
        }
    ],
    "sg:phone":"+44 1242 226400",
    "sg:postcode":"GL50 1SU",
    "sg:province":"Gloucestershire",
    "sg:tags":[
        "telecommunication"
    ],
    "wof:name":"Fax The Facts",
    "wof:placetype":"venue"
},
  "geometry": {"coordinates":[-2.0784919262,51.8936157227],"type":"Point"}
}