{
  "type": "Feature",
  "properties": {
    "iso:country":"GB",
    "sg:address":"Rosevanion Farm",
    "sg:city":"St Columb",
    "sg:classifiers":[
        {
            "category":"Building & Trades",
            "subcategory":"Construction",
            "type":"Services"
        }
    ],
    "sg:postcode":"TR9 6DJ",
    "sg:province":"Cornwall",
    "sg:tags":[
        "builder"
    ],
    "wof:name":"R Bennett Builders",
    "wof:placetype":"venue"
},
  "geometry": {"coordinates":[-4.936884,50.43256],"type":"Point"}
}