{
  "type": "Feature",
  "properties": {
    "addr:full":"12 Oakley Terr Leeds West Yorkshire LS11 5HT",
    "addr:housenumber":"12",
    "addr:postcode":"ls11 5ht",
    "addr:street":"Oakley Terr",
    "iso:country":"GB",
    "sg:address":"12 Oakley Terr",
    "sg:city":"Leeds",
    "sg:classifiers":[
        {
            "category":"Health Services",
            "subcategory":"Doctor",
            "type":"Services"
        }
    ],
    "sg:phone":"+44 113 272 0900",
    "sg:postcode":"LS11 5HT",
    "sg:province":"West Yorkshire",
    "sg:tags":[
        "practitioners"
    ],
    "wof:name":"Manning, S I",
    "wof:placetype":"venue"
},
  "geometry": {"coordinates":[-1.5457789898,53.774269104],"type":"Point"}
}