{
  "type": "Feature",
  "properties": {
    "iso:country":"GB",
    "sg:address":"37 High Street",
    "sg:city":"Bridgnorth",
    "sg:classifiers":[
        {
            "category":"Building & Trades",
            "subcategory":"Cleaning & Sanitation",
            "type":"Services"
        }
    ],
    "sg:phone":"+44 1746 761214",
    "sg:postcode":"WV16 4DB",
    "sg:province":"Shropshire",
    "sg:tags":[
        "commercial"
    ],
    "wof:name":"Provac Cleaning Services",
    "wof:placetype":"venue"
},
  "geometry": {"coordinates":[-2.420172,52.535809],"type":"Point"}
}