{
  "type": "Feature",
  "properties": {
    "addr:full":"Unit 22-23 Chanters Industrial Estate, Atherton Manchester Greater Manchester M46 9BP",
    "addr:housenumber":"unit 22-23",
    "addr:postcode":"m46 9bp",
    "addr:street":"Chanters Industrial Estate",
    "iso:country":"GB",
    "sg:address":"Unit 22-23 Chanters Industrial Estate, Atherton",
    "sg:city":"Manchester",
    "sg:classifiers":[
        {
            "category":"Bus Charters",
            "type":"Transportation"
        }
    ],
    "sg:phone":"+44 1942 888893",
    "sg:postcode":"M46 9BP",
    "sg:province":"Greater Manchester",
    "sg:tags":[
        "coach"
    ],
    "wof:name":"Green Triangle Buses Ltd.",
    "wof:placetype":"venue"
},
  "geometry": {"coordinates":[-2.489241,53.523132],"type":"Point"}
}