{
  "type": "Feature",
  "properties": {
    "addr:full":"413 Manchester Road Rochdale Lancashire OL11 3PG",
    "addr:housenumber":"413",
    "addr:postcode":"ol11 3pg",
    "addr:street":"Manchester Road",
    "iso:country":"GB",
    "sg:address":"413 Manchester Road",
    "sg:city":"Rochdale",
    "sg:classifiers":[
        {
            "category":"Retail",
            "subcategory":"Driving School",
            "type":"Services"
        }
    ],
    "sg:phone":"+44 1706 825307",
    "sg:postcode":"OL11 3PG",
    "sg:province":"Lancashire",
    "wof:name":"Phoenix Driving Academy",
    "wof:placetype":"venue"
},
  "geometry": {"coordinates":[-2.1759669781,53.6028709412],"type":"Point"}
}