{
  "type": "Feature",
  "properties": {
    "addr:full":"62-70 Dew Street Haverfordwest Pembrokeshire SA61 1NR",
    "addr:housenumber":"62-70",
    "addr:postcode":"sa61 1nr",
    "addr:street":"Dew Street",
    "iso:country":"GB",
    "sg:address":"62-70 Dew Street",
    "sg:city":"Haverfordwest",
    "sg:classifiers":[
        {
            "category":"Shopping",
            "subcategory":"Baby Store",
            "type":"Retail Goods"
        }
    ],
    "sg:phone":"+44 1437 767222",
    "sg:postcode":"SA61 1NR",
    "sg:province":"Pembrokeshire",
    "sg:tags":[
        "babywear",
        "childrens"
    ],
    "wof:name":"Toffee Apple",
    "wof:placetype":"venue"
},
  "geometry": {"coordinates":[-4.973459,51.798733],"type":"Point"}
}