{
  "type": "Feature",
  "properties": {
    "iso:country":"GB",
    "sg:address":"4 Butler Crescent, Exhall",
    "sg:city":"Coventry",
    "sg:phone":"+44 24 7649 0441",
    "sg:postcode":"CV7 9DA",
    "sg:province":"Warwickshire",
    "wof:name":"Allan's Machines Painting Services",
    "wof:placetype":"venue"
},
  "geometry": {"coordinates":[-1.483224,52.471844],"type":"Point"}
}