{
  "type": "Feature",
  "properties": {
    "addr:full":"15 Beresford Terrace Ayr South Ayrshire KA7 2EU",
    "addr:housenumber":"15",
    "addr:postcode":"ka7 2eu",
    "addr:street":"Beresford Terrace",
    "iso:country":"GB",
    "sg:address":"15 Beresford Terrace",
    "sg:city":"Ayr",
    "sg:classifiers":[
        {
            "category":"Shopping",
            "subcategory":"Thrift Store",
            "type":"Retail Goods"
        }
    ],
    "sg:phone":"+44 1292 880640",
    "sg:postcode":"KA7 2EU",
    "sg:province":"South Ayrshire",
    "sg:tags":[
        "shop",
        "charity"
    ],
    "wof:name":"The Royal British Legion Scotland",
    "wof:placetype":"venue"
},
  "geometry": {"coordinates":[-4.628946,55.450642],"type":"Point"}
}