{
  "type": "Feature",
  "properties": {
    "iso:country":"GB",
    "sg:address":"11 A & B East Street",
    "sg:city":"Shoreham-by-sea",
    "sg:classifiers":[
        {
            "category":"Shopping",
            "subcategory":"Computers & Home Electronics",
            "type":"Retail Goods"
        },
        {
            "category":"Communications",
            "type":"Services"
        }
    ],
    "sg:phone":"+44 1273 461579",
    "sg:postcode":"BN43 5ZE",
    "sg:province":"West Sussex",
    "sg:tags":[
        "tv",
        "video",
        "television",
        "aerial",
        "radio"
    ],
    "wof:name":"A & S Satellites Ltd.",
    "wof:placetype":"venue"
},
  "geometry": {"coordinates":[-0.27418,50.832199],"type":"Point"}
}