{
  "type": "Feature",
  "properties": {
    "iso:country":"GB",
    "sg:address":"Farmhouse Court, Kingsbury Road, Marston",
    "sg:city":"Sutton Coldfield",
    "sg:classifiers":[
        {
            "category":"Sports & Exercise",
            "subcategory":"Stables",
            "type":"Entertainment"
        }
    ],
    "sg:postcode":"B76 0DW",
    "sg:province":"Warwickshire",
    "sg:tags":[
        "education",
        "equestrian"
    ],
    "wof:name":"Farmhouse Stables",
    "wof:placetype":"venue"
},
  "geometry": {"coordinates":[-1.717793,52.541264],"type":"Point"}
}