{
  "type": "Feature",
  "properties": {
    "addr:full":"43 Front Street Chester-le-street Durham DH3 3BH",
    "addr:housenumber":"43",
    "addr:postcode":"dh3 3bh",
    "addr:street":"Front Street",
    "iso:country":"GB",
    "sg:address":"43 Front Street",
    "sg:city":"Chester-le-street",
    "sg:classifiers":[
        {
            "category":"Food & Beverages",
            "subcategory":"Fruits & Vegetables",
            "type":"Retail Goods"
        }
    ],
    "sg:phone":"+44 191 388 2518",
    "sg:postcode":"DH3 3BH",
    "sg:province":"Durham",
    "sg:tags":[
        "greengrocer"
    ],
    "wof:name":"Youngs",
    "wof:placetype":"venue"
},
  "geometry": {"coordinates":[-1.574194,54.857307],"type":"Point"}
}