{
  "type": "Feature",
  "properties": {
    "iso:country":"GB",
    "sg:address":"Unit 3 Friars Oak, Boyneswood Road",
    "sg:city":"Alton",
    "sg:classifiers":[
        {
            "category":"Manufacturing",
            "subcategory":"Wood Products",
            "type":"Manufacturing & Wholesale Goods"
        }
    ],
    "sg:postcode":"GU34 5EA",
    "sg:province":"Hampshire",
    "sg:tags":[
        "maker",
        "cabinet"
    ],
    "wof:name":"Dalbergia Bespoke Cabinet Maker",
    "wof:placetype":"venue"
},
  "geometry": {"coordinates":[-1.041568,51.119335],"type":"Point"}
}