{
  "type": "Feature",
  "properties": {
    "addr:full":"Murton Swansea Swansea SA3 3AS",
    "addr:postcode":"sa3 3as",
    "iso:country":"GB",
    "sg:address":"Murton",
    "sg:city":"Swansea",
    "sg:classifiers":[
        {
            "category":"Health Services",
            "subcategory":"Clinic",
            "type":"Services"
        }
    ],
    "sg:phone":"+44 1792 232229",
    "sg:postcode":"SA3 3AS",
    "sg:province":"Swansea",
    "sg:tags":[
        "nh"
    ],
    "wof:name":"Bishopston Surgery",
    "wof:placetype":"venue"
},
  "geometry": {"coordinates":[-4.03275,51.579151],"type":"Point"}
}