{
  "type": "Feature",
  "properties": {
    "iso:country":"GB",
    "sg:address":"Unit 19, Upminster Trading Park, Warley Street",
    "sg:city":"Upminster",
    "sg:classifiers":[
        {
            "category":"Shopping",
            "subcategory":"Stationery & Office Supplies",
            "type":"Retail Goods"
        },
        {
            "category":"Manufacturing",
            "subcategory":"Paper Products",
            "type":"Manufacturing & Wholesale Goods"
        },
        {
            "category":"Professional",
            "subcategory":"Computer Services",
            "type":"Services"
        }
    ],
    "sg:phone":"+44 1708 223344",
    "sg:postcode":"RM14 3PJ",
    "sg:province":"Essex",
    "sg:tags":[
        "mnfr",
        "system",
        "software"
    ],
    "wof:name":"Continuous Design Ltd.",
    "wof:placetype":"venue"
},
  "geometry": {"coordinates":[0.30017,51.566814],"type":"Point"}
}