{
  "type": "Feature",
  "properties": {
    "iso:country":"GB",
    "sg:address":"133 Waterloo Road",
    "sg:city":"Middlesbrough",
    "sg:classifiers":[
        {
            "category":"Shopping",
            "subcategory":"Comic Books",
            "type":"Retail Goods"
        }
    ],
    "sg:phone":"+44 1642 251625",
    "sg:postcode":"TS1 3JB",
    "sg:province":"North Yorkshire",
    "sg:tags":[
        "jeweller"
    ],
    "wof:name":"Boro Jewellers",
    "wof:placetype":"venue"
},
  "geometry": {"coordinates":[-1.23066,54.568409],"type":"Point"}
}