{
  "type": "Feature",
  "properties": {
    "addr:full":"33 Kirkcross Cres, Royston Barnsley South Yorkshire S71 4PJ",
    "addr:housenumber":"33",
    "addr:postcode":"s71 4pj",
    "addr:street":"Kirkcross Cres;Yorkshire",
    "iso:country":"GB",
    "sg:address":"33 Kirkcross Cres, Royston",
    "sg:city":"Barnsley",
    "sg:classifiers":[
        {
            "category":"Building & Trades",
            "subcategory":"Construction",
            "type":"Services"
        }
    ],
    "sg:postcode":"S71 4PJ",
    "sg:province":"South Yorkshire",
    "sg:tags":[
        "contractor",
        "paving",
        "driveway"
    ],
    "wof:name":"Moxon,Gregory,",
    "wof:placetype":"venue"
},
  "geometry": {"coordinates":[-1.453829,53.591824],"type":"Point"}
}