{
  "type": "Feature",
  "properties": {
    "addr:full":"83 County Road Liverpool Merseyside L4 3QD",
    "addr:housenumber":"83",
    "addr:postcode":"l4 3qd",
    "addr:street":"County Road",
    "iso:country":"GB",
    "sg:address":"83 County Road",
    "sg:city":"Liverpool",
    "sg:classifiers":[
        {
            "category":"Shopping",
            "subcategory":"News",
            "type":"Retail Goods"
        }
    ],
    "sg:postcode":"L4 3QD",
    "sg:province":"Merseyside",
    "sg:tags":[
        "newsagent"
    ],
    "wof:name":"Abdul Mohammed Newsagents",
    "wof:placetype":"venue"
},
  "geometry": {"coordinates":[-2.970885,53.441154],"type":"Point"}
}