{
  "type": "Feature",
  "properties": {
    "iso:country":"GB",
    "sg:address":"202 High Street, Ponders End",
    "sg:city":"Enfield",
    "sg:classifiers":[
        {
            "category":"Insurance",
            "subcategory":"Insurance Agent",
            "type":"Services"
        }
    ],
    "sg:phone":"+44 20 8805 1121",
    "sg:postcode":"EN3 4EZ",
    "sg:province":"Greater London",
    "wof:name":"Clover Insurance",
    "wof:placetype":"venue"
},
  "geometry": {"coordinates":[-0.0465020016,51.6499290466],"type":"Point"}
}