{
  "type": "Feature",
  "properties": {
    "addr:full":"The Fryern Surgery, Oakmount Rd Eastleigh Hampshire SO53 2LH",
    "addr:postcode":"so53 2lh",
    "addr:street":"Oakmount Rd",
    "iso:country":"GB",
    "sg:address":"The Fryern Surgery, Oakmount Rd",
    "sg:city":"Eastleigh",
    "sg:classifiers":[
        {
            "category":"Health Services",
            "subcategory":"Doctor",
            "type":"Services"
        }
    ],
    "sg:phone":"+44 23 8027 3252",
    "sg:postcode":"SO53 2LH",
    "sg:province":"Hampshire",
    "sg:tags":[
        "practitioners"
    ],
    "wof:name":"Foote, G A",
    "wof:placetype":"venue"
},
  "geometry": {"coordinates":[-1.3726940155,50.9862136841],"type":"Point"}
}