{
  "type": "Feature",
  "properties": {
    "addr:full":"15 Primrose Gardens, Codsall Wolverhampton Shropshire WV8 1PA",
    "addr:housenumber":"15",
    "addr:postcode":"wv8 1pa",
    "addr:street":"Primrose Gardens",
    "iso:country":"GB",
    "sg:address":"15 Primrose Gardens, Codsall",
    "sg:city":"Wolverhampton",
    "sg:classifiers":[
        {
            "category":"Building & Trades",
            "subcategory":"Cleaning & Sanitation",
            "type":"Services"
        }
    ],
    "sg:phone":"+44 1902 844418",
    "sg:postcode":"WV8 1PA",
    "sg:province":"Shropshire",
    "sg:tags":[
        "contracting",
        "commercial"
    ],
    "wof:name":"Helping Hands",
    "wof:placetype":"venue"
},
  "geometry": {"coordinates":[-2.1901841164,52.6262817383],"type":"Point"}
}