{
  "type": "Feature",
  "properties": {
    "iso:country":"GB",
    "sg:address":"Cnwl-yr-hyglyn, Llangranog",
    "sg:city":"Llandysul",
    "sg:classifiers":[
        {
            "category":"Farming",
            "subcategory":"Dairy Farm",
            "type":"Manufacturing & Wholesale Goods"
        }
    ],
    "sg:phone":"+44 1239 654200",
    "sg:postcode":"SA44 6RR",
    "sg:province":"Carmarthenshire",
    "wof:name":"E M & D I O Evans",
    "wof:placetype":"venue"
},
  "geometry": {"coordinates":[-4.462604,52.157333],"type":"Point"}
}