{
  "type": "Feature",
  "properties": {
    "addr:full":"5 Home Park Parade Kingston-upon-thames Greater London KT1 4BY",
    "addr:housenumber":"5",
    "addr:postcode":"kt1 4by",
    "addr:street":"Home Park Parade",
    "iso:country":"GB",
    "sg:address":"5 Home Park Parade",
    "sg:city":"Kingston-upon-thames",
    "sg:classifiers":[
        {
            "category":"Retail",
            "subcategory":"Laundry & Dry Cleaning",
            "type":"Services"
        },
        {
            "category":"Retail",
            "subcategory":"Repair Shop",
            "type":"Services"
        }
    ],
    "sg:phone":"+44 20 8977 4234",
    "sg:postcode":"KT1 4BY",
    "sg:province":"Greater London",
    "sg:tags":[
        "clothing",
        "alteration"
    ],
    "wof:name":"Anne Green Tailoring",
    "wof:placetype":"venue"
},
  "geometry": {"coordinates":[-0.308193,51.399673],"type":"Point"}
}