{
  "type": "Feature",
  "properties": {
    "iso:country":"GB",
    "sg:address":"25 Alicia Drive",
    "sg:city":"Rochdale",
    "sg:classifiers":[
        {
            "category":"Travel",
            "subcategory":"Hostel",
            "type":"Entertainment"
        },
        {
            "category":"Organizations",
            "subcategory":"Non-profit Organization",
            "type":"Services"
        }
    ],
    "sg:phone":"+44 1706 45827",
    "sg:postcode":"OL12 6JW",
    "sg:province":"Lancashire",
    "sg:tags":[
        "organisation",
        "voluntary",
        "charity"
    ],
    "wof:name":"The Salvation Army",
    "wof:placetype":"venue"
},
  "geometry": {"coordinates":[-2.1647839546,53.6265182495],"type":"Point"}
}