{
  "type": "Feature",
  "properties": {
    "addr:full":"181 Allaway Avenue Portsmouth Hampshire PO6 4HG",
    "addr:housenumber":"181",
    "addr:postcode":"po6 4hg",
    "addr:street":"Allaway Avenue",
    "iso:country":"GB",
    "sg:address":"181 Allaway Avenue",
    "sg:city":"Portsmouth",
    "sg:classifiers":[
        {
            "category":"Organizations",
            "subcategory":"Non-profit Organization",
            "type":"Services"
        }
    ],
    "sg:phone":"+44 23 9221 5525",
    "sg:postcode":"PO6 4HG",
    "sg:province":"Hampshire",
    "sg:tags":[
        "organisation",
        "voluntary",
        "charity"
    ],
    "wof:name":"Age Concern England (National Council of",
    "wof:placetype":"venue"
},
  "geometry": {"coordinates":[-1.093867,50.849693],"type":"Point"}
}