{
  "type": "Feature",
  "properties": {
    "iso:country":"GB",
    "sg:address":"26 Great Queen Street",
    "sg:city":"London",
    "sg:classifiers":[
        {
            "category":"Professional",
            "subcategory":"Business Services",
            "type":"Services"
        },
        {
            "category":"Communications",
            "type":"Services"
        }
    ],
    "sg:phone":"+44 20 7930 0777",
    "sg:postcode":"WC2B 5BL",
    "sg:province":"Greater London",
    "sg:tags":[
        "telecommunication"
    ],
    "wof:name":"Chancery Communications Ltd.",
    "wof:placetype":"venue"
},
  "geometry": {"coordinates":[-0.12133,51.515514],"type":"Point"}
}