{
  "type": "Feature",
  "properties": {
    "addr:full":"Hillbury Road Aldershot Dorset SP6 3BH",
    "addr:postcode":"sp6 3bh",
    "addr:street":"Hillbury Road",
    "iso:country":"GB",
    "sg:address":"Hillbury Road",
    "sg:city":"Aldershot",
    "sg:classifiers":[
        {
            "category":"Building & Trades",
            "subcategory":"Equipment Rental",
            "type":"Services"
        }
    ],
    "sg:phone":"+44 1425 654856",
    "sg:postcode":"SP6 3BH",
    "sg:province":"Dorset",
    "sg:tags":[
        "plant",
        "machinery"
    ],
    "wof:name":"Groundwise Ltd.",
    "wof:placetype":"venue"
},
  "geometry": {"coordinates":[-1.8209400177,50.9123001099],"type":"Point"}
}