{
  "type": "Feature",
  "properties": {
    "addr:full":"295 Darwen Road, Bromley Cross Bolton Lancashire BL7 9BT",
    "addr:housenumber":"295",
    "addr:postcode":"bl7 9bt",
    "addr:street":"Darwen Road",
    "iso:country":"GB",
    "sg:address":"295 Darwen Road, Bromley Cross",
    "sg:city":"Bolton",
    "sg:classifiers":[
        {
            "category":"Freight",
            "type":"Transportation"
        }
    ],
    "sg:phone":"+44 1895 820888",
    "sg:postcode":"BL7 9BT",
    "sg:province":"Lancashire",
    "sg:tags":[
        "haulage",
        "road"
    ],
    "wof:name":"Chiltern Transport (Northern) Ltd.",
    "wof:placetype":"venue"
},
  "geometry": {"coordinates":[-2.421657,53.616161],"type":"Point"}
}