{
  "type": "Feature",
  "properties": {
    "iso:country":"GB",
    "sg:address":"2 Church Lane",
    "sg:city":"Stafford",
    "sg:classifiers":[
        {
            "category":"Restaurant",
            "type":"Food & Drink"
        }
    ],
    "sg:phone":"+44 1785 254775",
    "sg:postcode":"ST16 2AW",
    "sg:province":"Staffordshire",
    "wof:name":"Soup Kitchen",
    "wof:placetype":"venue"
},
  "geometry": {"coordinates":[-2.118178,52.805862],"type":"Point"}
}