{
  "type": "Feature",
  "properties": {
    "iso:country":"GB",
    "sg:address":"Lintonville Terrace",
    "sg:city":"Ashington",
    "sg:classifiers":[
        {
            "category":"Wholesale",
            "subcategory":"Home Furnishings",
            "type":"Manufacturing & Wholesale Goods"
        }
    ],
    "sg:phone":"+44 1670 520006",
    "sg:postcode":"NE63 9UN",
    "sg:province":"Northumberland",
    "sg:tags":[
        "merchant",
        "decorators'"
    ],
    "wof:name":"The Paint Shop",
    "wof:placetype":"venue"
},
  "geometry": {"coordinates":[-1.5693839788,55.1836204529],"type":"Point"}
}