{
  "type": "Feature",
  "properties": {
    "addr:full":"Meadow House, Cooks Lane, Calmore Southampton Hampshire SO40 2RU",
    "addr:postcode":"so40 2ru",
    "addr:street":"Cooks Lane",
    "iso:country":"GB",
    "sg:address":"Meadow House, Cooks Lane, Calmore",
    "sg:city":"Southampton",
    "sg:classifiers":[
        {
            "category":"Building & Trades",
            "subcategory":"Construction",
            "type":"Services"
        }
    ],
    "sg:phone":"+44 23 8081 4466",
    "sg:postcode":"SO40 2RU",
    "sg:province":"Hampshire",
    "sg:tags":[
        "excavation",
        "groundwork",
        "contractor"
    ],
    "wof:name":"Lydfield Construction Ltd.",
    "wof:placetype":"venue"
},
  "geometry": {"coordinates":[-1.5116590261,50.9340553284],"type":"Point"}
}