{
  "type": "Feature",
  "properties": {
    "addr:full":"43 Bull Street Holt Norfolk NR25 6HP",
    "addr:housenumber":"43",
    "addr:postcode":"nr25 6hp",
    "addr:street":"Bull Street",
    "iso:country":"GB",
    "sg:address":"43 Bull Street",
    "sg:city":"Holt",
    "sg:classifiers":[
        {
            "category":"Professional",
            "subcategory":"Accounting & Tax Preparation",
            "type":"Services"
        }
    ],
    "sg:phone":"+44 1263 712017",
    "sg:postcode":"NR25 6HP",
    "sg:province":"Norfolk",
    "sg:tags":[
        "accountant",
        "activity"
    ],
    "wof:name":"Larking Gowen",
    "wof:placetype":"venue"
},
  "geometry": {"coordinates":[1.090299964,52.9065322876],"type":"Point"}
}