{
  "type": "Feature",
  "properties": {
    "iso:country":"GB",
    "sg:address":"8 Cranleigh Av",
    "sg:city":"Portsmouth",
    "sg:classifiers":[
        {
            "category":"Health Services",
            "subcategory":"Health Practitioner",
            "type":"Services"
        }
    ],
    "sg:phone":"+44 23 9229 4037",
    "sg:postcode":"PO1 5LU",
    "sg:province":"Hampshire",
    "sg:tags":[
        "hypnotherapists"
    ],
    "wof:name":"Baldacchino Paul",
    "wof:placetype":"venue"
},
  "geometry": {"coordinates":[-1.072371006,50.8040924072],"type":"Point"}
}