{
  "type": "Feature",
  "properties": {
    "iso:country":"GB",
    "sg:address":"18 Pittville Close, Thornbury",
    "sg:city":"Bristol",
    "sg:classifiers":[
        {
            "category":"Shopping",
            "subcategory":"Crafts & Fabrics",
            "type":"Retail Goods"
        }
    ],
    "sg:postcode":"BS35 1SE",
    "sg:province":"Gloucestershire",
    "sg:tags":[
        "material",
        "art"
    ],
    "wof:name":"Silkraft",
    "wof:placetype":"venue"
},
  "geometry": {"coordinates":[-2.518666,51.618191],"type":"Point"}
}