{
  "type": "Feature",
  "properties": {
    "iso:country":"GB",
    "sg:address":"Ashby Road",
    "sg:city":"Watford",
    "sg:classifiers":[
        {
            "category":"Arena",
            "subcategory":"Sports Club",
            "type":"Entertainment"
        }
    ],
    "sg:phone":"+44 1923 244054",
    "sg:postcode":"WD24 5GU",
    "sg:province":"Hertfordshire",
    "wof:name":"North Watford Bowls Club",
    "wof:placetype":"venue"
},
  "geometry": {"coordinates":[-0.405174,51.67421],"type":"Point"}
}