{
  "type": "Feature",
  "properties": {
    "addr:full":"Victoria Buildings Business Centre, Violet St Paisley Renfrewshire PA1 1PA",
    "addr:postcode":"pa1 1pa",
    "addr:street":"Violet St",
    "iso:country":"GB",
    "sg:address":"Victoria Buildings Business Centre, Violet St",
    "sg:city":"Paisley",
    "sg:classifiers":[
        {
            "category":"Health Services",
            "subcategory":"Health Practitioner",
            "type":"Services"
        }
    ],
    "sg:phone":"+44 141 561 2007",
    "sg:postcode":"PA1 1PA",
    "sg:province":"Renfrewshire",
    "sg:tags":[
        "acupuncture"
    ],
    "wof:name":"Anne Penman",
    "wof:placetype":"venue"
},
  "geometry": {"coordinates":[-4.40904,55.843868],"type":"Point"}
}