{
  "type": "Feature",
  "properties": {
    "addr:full":"Beech House, 5 Bridgenorth Avenue, Urmston Manchester Cheshire M41 9PA",
    "addr:housenumber":"5",
    "addr:postcode":"m41 9pa",
    "addr:street":"Bridgenorth Avenue",
    "iso:country":"GB",
    "sg:address":"Beech House, 5 Bridgenorth Avenue, Urmston",
    "sg:city":"Manchester",
    "sg:classifiers":[
        {
            "category":"Building & Trades",
            "subcategory":"Cleaning & Sanitation",
            "type":"Services"
        }
    ],
    "sg:phone":"+44 161 748 0973",
    "sg:postcode":"M41 9PA",
    "sg:province":"Cheshire",
    "sg:tags":[
        "dry",
        "control",
        "damp",
        "rot"
    ],
    "wof:name":"B P A Protim",
    "wof:placetype":"venue"
},
  "geometry": {"coordinates":[-2.338235,53.448711],"type":"Point"}
}