{
  "type": "Feature",
  "properties": {
    "addr:full":"Charter Ct, Third Av Southampton Hampshire SO15 0AP",
    "addr:postcode":"so15 0ap",
    "addr:street":"Charter Ct Third Av",
    "iso:country":"GB",
    "sg:address":"Charter Ct, Third Av",
    "sg:city":"Southampton",
    "sg:classifiers":[
        {
            "category":"Professional",
            "subcategory":"Business Services",
            "type":"Services"
        }
    ],
    "sg:phone":"+44 23 8070 2264",
    "sg:postcode":"SO15 0AP",
    "sg:province":"Hampshire",
    "sg:tags":[
        "import",
        "export",
        "agent"
    ],
    "wof:name":"Advisory & Trading Services Ltd",
    "wof:placetype":"venue"
},
  "geometry": {"coordinates":[-1.4554610252,50.9162559509],"type":"Point"}
}