{
  "type": "Feature",
  "properties": {
    "addr:full":"13-15 Lampits Hill, Corringham Stanford-le-hope Essex SS17 9AA",
    "addr:housenumber":"13-15",
    "addr:postcode":"ss17 9aa",
    "addr:street":"Lampits Hill",
    "iso:country":"GB",
    "sg:address":"13-15 Lampits Hill, Corringham",
    "sg:city":"Stanford-le-hope",
    "sg:classifiers":[
        {
            "category":"Shopping",
            "type":"Retail Goods"
        }
    ],
    "sg:postcode":"SS17 9AA",
    "sg:province":"Essex",
    "sg:tags":[
        "part",
        "accessory"
    ],
    "wof:name":"Choice Tyres Ltd.",
    "wof:placetype":"venue"
},
  "geometry": {"coordinates":[0.460496,51.525734],"type":"Point"}
}