{
  "type": "Feature",
  "properties": {
    "iso:country":"GB",
    "sg:address":"8 Bentley Industrial Centre, Bentley",
    "sg:city":"Farnham",
    "sg:classifiers":[
        {
            "category":"Building & Trades",
            "subcategory":"Plumbing",
            "type":"Services"
        },
        {
            "category":"Home & Garden",
            "subcategory":"Building Materials",
            "type":"Retail Goods"
        }
    ],
    "sg:phone":"+44 1420 23717",
    "sg:postcode":"GU10 5NJ",
    "sg:province":"Hampshire",
    "sg:tags":[
        "ventilator",
        "plumber",
        "system",
        "ventilation"
    ],
    "wof:name":"G H Sansom Installations Ltd.",
    "wof:placetype":"venue"
},
  "geometry": {"coordinates":[-0.8753089905,51.1901931763],"type":"Point"}
}