{
  "type": "Feature",
  "properties": {
    "iso:country":"GB",
    "sg:address":"88 Main Rd, Sundridge",
    "sg:city":"Sevenoaks",
    "sg:classifiers":[
        {
            "category":"Communications",
            "type":"Services"
        }
    ],
    "sg:phone":"+44 1959 568300",
    "sg:postcode":"TN14 6ER",
    "sg:province":"Kent",
    "sg:tags":[
        "telecommunication"
    ],
    "wof:name":"Unitel Communications Ltd",
    "wof:placetype":"venue"
},
  "geometry": {"coordinates":[0.1317590028,51.2789764404],"type":"Point"}
}