{
  "type": "Feature",
  "properties": {
    "iso:country":"GB",
    "sg:address":"55 Leven Road, Lundin Links",
    "sg:city":"Leven",
    "sg:classifiers":[
        {
            "category":"Travel",
            "subcategory":"Hotels & Motels",
            "type":"Entertainment"
        }
    ],
    "sg:phone":"+44 1333 320368",
    "sg:postcode":"KY8 6AJ",
    "sg:province":"Fife",
    "wof:name":"Tollerton Hotels Ltd.",
    "wof:placetype":"venue"
},
  "geometry": {"coordinates":[-2.96192,56.212284],"type":"Point"}
}