{
  "type": "Feature",
  "properties": {
    "addr:full":"Bridge House, 181 Queen Victoria Street London Greater London EC4V 4DD",
    "addr:housenumber":"181",
    "addr:postcode":"ec4v 4dd",
    "addr:street":"Queen Victoria Street",
    "iso:country":"GB",
    "sg:address":"Bridge House, 181 Queen Victoria Street",
    "sg:city":"London",
    "sg:classifiers":[
        {
            "category":"Professional",
            "type":"Services"
        }
    ],
    "sg:postcode":"EC4V 4DD",
    "sg:province":"Greater London",
    "sg:tags":[
        "repair",
        "tech",
        "maintenance"
    ],
    "wof:name":"Midrange Support Limited",
    "wof:placetype":"venue"
},
  "geometry": {"coordinates":[-0.1037999988,51.5117530823],"type":"Point"}
}