{
  "type": "Feature",
  "properties": {
    "addr:full":"Unit 8, Old Station Close Coalville Leicestershire LE67 3FH",
    "addr:housenumber":"unit 8",
    "addr:postcode":"le67 3fh",
    "addr:street":"Old Station Close",
    "iso:country":"GB",
    "sg:address":"Unit 8, Old Station Close",
    "sg:city":"Coalville",
    "sg:classifiers":[
        {
            "category":"Building & Trades",
            "subcategory":"Construction",
            "type":"Services"
        }
    ],
    "sg:phone":"+44 1530 812253",
    "sg:postcode":"LE67 3FH",
    "sg:province":"Leicestershire",
    "sg:tags":[
        "concrete"
    ],
    "wof:name":"Ivor Parnham Building Services Ltd.",
    "wof:placetype":"venue"
},
  "geometry": {"coordinates":[-1.3701210022,52.7255630493],"type":"Point"}
}