{
  "type": "Feature",
  "properties": {
    "iso:country":"GB",
    "sg:address":"49 Gordon Street",
    "sg:city":"Huntly",
    "sg:classifiers":[
        {
            "category":"Food & Beverages",
            "subcategory":"Bakery",
            "type":"Retail Goods"
        }
    ],
    "sg:postcode":"AB54 5EQ",
    "sg:province":"Aberdeenshire",
    "sg:tags":[
        "baker"
    ],
    "wof:name":"J & I Smith",
    "wof:placetype":"venue"
},
  "geometry": {"coordinates":[-2.7881400585,57.4461555481],"type":"Point"}
}