{
  "type": "Feature",
  "properties": {
    "iso:country":"GB",
    "sg:address":"Excalibur House, 630 Liverpool Road, Erlam",
    "sg:city":"Manchester",
    "sg:classifiers":[
        {
            "category":"Home & Garden",
            "subcategory":"Hardware",
            "type":"Retail Goods"
        }
    ],
    "sg:phone":"+44 161 775 0051",
    "sg:postcode":"M44 5AD",
    "sg:province":"Greater Manchester",
    "sg:tags":[
        "generator"
    ],
    "wof:name":"Goodwin Machinery Ltd.",
    "wof:placetype":"venue"
},
  "geometry": {"coordinates":[-2.432211,53.433842],"type":"Point"}
}