{
  "type": "Feature",
  "properties": {
    "addr:full":"Peak Buildings, Terrace Road Buxton Derbyshire SK17 6DY",
    "addr:postcode":"sk17 6dy",
    "addr:street":"Terrace Road",
    "iso:country":"GB",
    "sg:address":"Peak Buildings, Terrace Road",
    "sg:city":"Buxton",
    "sg:classifiers":[
        {
            "category":"Government",
            "subcategory":"Court House",
            "type":"Public Place"
        }
    ],
    "sg:phone":"+44 1298 23951",
    "sg:postcode":"SK17 6DY",
    "sg:province":"Derbyshire",
    "wof:name":"High Peak Magistrates Court",
    "wof:placetype":"venue"
},
  "geometry": {"coordinates":[-1.9130489826,53.2603874207],"type":"Point"}
}