{
  "type": "Feature",
  "properties": {
    "addr:full":"Grove Lane, Handsworth Birmingham West Midlands B21 9HB",
    "addr:postcode":"b21 9hb",
    "addr:street":"Grove Lane",
    "iso:country":"GB",
    "sg:address":"Grove Lane, Handsworth",
    "sg:city":"Birmingham",
    "sg:classifiers":[
        {
            "category":"Education",
            "subcategory":"School",
            "type":"Public Place"
        },
        {
            "category":"Government",
            "subcategory":"Office",
            "type":"Public Place"
        }
    ],
    "sg:phone":"+44 121 464 4669",
    "sg:postcode":"B21 9HB",
    "sg:province":"West Midlands",
    "sg:tags":[
        "local",
        "authority"
    ],
    "wof:name":"Grove Primary School",
    "wof:placetype":"venue"
},
  "geometry": {"coordinates":[-1.9316339493,52.5074501038],"type":"Point"}
}