{
  "type": "Feature",
  "properties": {
    "iso:country":"GB",
    "sg:address":"A3-a4 Unit, Cumberland Buss Ctr, Northumberland Road",
    "sg:city":"Southsea",
    "sg:classifiers":[
        {
            "category":"Professional",
            "subcategory":"Computer Services",
            "type":"Services"
        }
    ],
    "sg:phone":"+44 23 9287 7111",
    "sg:postcode":"PO5 1DS",
    "sg:province":"Hampshire",
    "sg:tags":[
        "system",
        "software"
    ],
    "wof:name":"Printware Ltd.",
    "wof:placetype":"venue"
},
  "geometry": {"coordinates":[-1.088164,50.784664],"type":"Point"}
}