{
  "type": "Feature",
  "properties": {
    "addr:full":"138 Hermon Hill, South Woodford London Greater London E18 1QH",
    "addr:housenumber":"138",
    "addr:postcode":"e18 1qh",
    "addr:street":"Hermon Hill",
    "iso:country":"GB",
    "sg:address":"138 Hermon Hill, South Woodford",
    "sg:city":"London",
    "sg:classifiers":[
        {
            "category":"Communications",
            "subcategory":"Film & Video Production",
            "type":"Services"
        }
    ],
    "sg:postcode":"E18 1QH",
    "sg:province":"Greater London",
    "sg:tags":[
        "tv"
    ],
    "wof:name":"Granditer,A,",
    "wof:placetype":"venue"
},
  "geometry": {"coordinates":[0.027863,51.587788],"type":"Point"}
}