{
  "type": "Feature",
  "properties": {
    "addr:full":"22 Brompton High Street Sittingbourne Kent ME7 5AQ",
    "addr:housenumber":"22",
    "addr:postcode":"me7 5aq",
    "addr:street":"Brompton High Street",
    "iso:country":"GB",
    "sg:address":"22 Brompton High Street",
    "sg:city":"Sittingbourne",
    "sg:classifiers":[
        {
            "category":"Shopping",
            "subcategory":"News",
            "type":"Retail Goods"
        }
    ],
    "sg:phone":"+44 1634 842440",
    "sg:postcode":"ME7 5AQ",
    "sg:province":"Kent",
    "sg:tags":[
        "newsagent"
    ],
    "wof:name":"Brompton Newsagents Ltd.",
    "wof:placetype":"venue"
},
  "geometry": {"coordinates":[0.543,51.389011],"type":"Point"}
}