{
  "type": "Feature",
  "properties": {
    "iso:country":"GB",
    "sg:address":"Avenue House, East End Road",
    "sg:city":"London",
    "sg:classifiers":[
        {
            "category":"Organizations",
            "subcategory":"Non-profit Organization",
            "type":"Services"
        }
    ],
    "sg:phone":"+44 20 8346 9789",
    "sg:postcode":"N3 3QE",
    "sg:province":"Greater London",
    "sg:tags":[
        "organisation",
        "voluntary",
        "charity"
    ],
    "wof:name":"Community Focus",
    "wof:placetype":"venue"
},
  "geometry": {"coordinates":[-0.19557,51.596809],"type":"Point"}
}