{
  "type": "Feature",
  "properties": {
    "iso:country":"GB",
    "sg:address":"17 Elmer Road, Middleton On Sea",
    "sg:city":"Bognor Regis",
    "sg:classifiers":[
        {
            "category":"Professional",
            "subcategory":"Engineering",
            "type":"Services"
        }
    ],
    "sg:phone":"+44 1243 582402",
    "sg:postcode":"PO22 6DZ",
    "sg:province":"West Sussex",
    "sg:tags":[
        "contractor",
        "electrical",
        "engineer"
    ],
    "wof:name":"Wickham & Pierce",
    "wof:placetype":"venue"
},
  "geometry": {"coordinates":[-0.618263,50.795055],"type":"Point"}
}