{
  "type": "Feature",
  "properties": {
    "addr:full":"Main Street, Swannington Coalville Leicestershire LE67 8QJ",
    "addr:postcode":"le67 8qj",
    "addr:street":"Main Street",
    "iso:country":"GB",
    "sg:address":"Main Street, Swannington",
    "sg:city":"Coalville",
    "sg:classifiers":[
        {
            "category":"Education",
            "subcategory":"School",
            "type":"Public Place"
        }
    ],
    "sg:phone":"+44 1530 832655",
    "sg:postcode":"LE67 8QJ",
    "sg:province":"Leicestershire",
    "sg:tags":[
        "local",
        "authority"
    ],
    "wof:name":"Swannington Church of England School",
    "wof:placetype":"venue"
},
  "geometry": {"coordinates":[-1.3869550228,52.7409973145],"type":"Point"}
}