{
  "type": "Feature",
  "properties": {
    "iso:country":"GB",
    "sg:address":"45 Queens Parade",
    "sg:city":"Cleethorpes",
    "sg:classifiers":[
        {
            "category":"Travel",
            "subcategory":"Hotels & Motels",
            "type":"Entertainment"
        }
    ],
    "sg:phone":"+44 1472 692184",
    "sg:postcode":"DN35 0DQ",
    "sg:province":"Lincolnshire",
    "wof:name":"The Kristina Hotel",
    "wof:placetype":"venue"
},
  "geometry": {"coordinates":[-0.023804,53.553417],"type":"Point"}
}