{
  "type": "Feature",
  "properties": {
    "addr:full":"45 Queens Parade Cleethorpes Lincolnshire DN35 0DQ",
    "addr:housenumber":"45",
    "addr:postcode":"dn35 0dq",
    "addr:street":"Queens Parade",
    "iso:country":"GB",
    "sg:address":"45 Queens Parade",
    "sg:city":"Cleethorpes",
    "sg:classifiers":[
        {
            "category":"Travel",
            "subcategory":"Hotels & Motels",
            "type":"Entertainment"
        }
    ],
    "sg:phone":"+44 1472 692184",
    "sg:postcode":"DN35 0DQ",
    "sg:province":"Lincolnshire",
    "wof:name":"The Kristina Hotel",
    "wof:placetype":"venue"
},
  "geometry": {"coordinates":[-0.023804,53.553417],"type":"Point"}
}