{
  "type": "Feature",
  "properties": {
    "addr:full":"52 North Hill Plymouth Devon PL4 8EU",
    "addr:housenumber":"52",
    "addr:postcode":"pl4 8eu",
    "addr:street":"North Hill",
    "iso:country":"GB",
    "sg:address":"52 North Hill",
    "sg:city":"Plymouth",
    "sg:classifiers":[
        {
            "category":"Real Estate",
            "subcategory":"Real Estate Agent",
            "type":"Services"
        }
    ],
    "sg:phone":"+44 1752 202121",
    "sg:postcode":"PL4 8EU",
    "sg:province":"Devon",
    "wof:name":"Bettison & Co.",
    "wof:placetype":"venue"
},
  "geometry": {"coordinates":[-4.13582,50.377117],"type":"Point"}
}