{
  "type": "Feature",
  "properties": {
    "iso:country":"GB",
    "sg:address":"132 Upper Chobham Road",
    "sg:city":"Camberley",
    "sg:classifiers":[
        {
            "category":"Real Estate",
            "subcategory":"Real Estate Operator",
            "type":"Services"
        }
    ],
    "sg:phone":"+44 1276 27119",
    "sg:postcode":"GU15 1EJ",
    "sg:province":"Berkshire",
    "sg:tags":[
        "letting",
        "agent"
    ],
    "wof:name":"Ravenswood Pilgrims Ltd.",
    "wof:placetype":"venue"
},
  "geometry": {"coordinates":[-0.715273,51.327545],"type":"Point"}
}