{
  "type": "Feature",
  "properties": {
    "iso:country":"GB",
    "sg:address":"High Street, Bangor On Dee",
    "sg:city":"Wrexham",
    "sg:classifiers":[
        {
            "category":"Professional",
            "subcategory":"Printing & Photocopies",
            "type":"Services"
        }
    ],
    "sg:phone":"+44 1978 780445",
    "sg:postcode":"LL13 0AU",
    "sg:province":"Wrexham",
    "sg:tags":[
        "printer"
    ],
    "wof:name":"Action Litho Printers",
    "wof:placetype":"venue"
},
  "geometry": {"coordinates":[-2.934964,52.970905],"type":"Point"}
}