{
  "type": "Feature",
  "properties": {
    "addr:full":"Hillingdon Indepen Living Centre, Royal Lane, Hillingdon Uxbridge Buckinghamshire UB8 3QX",
    "addr:postcode":"ub8 3qx",
    "addr:street":"Royal Lane",
    "iso:country":"GB",
    "sg:address":"Hillingdon Indepen Living Centre, Royal Lane, Hillingdon",
    "sg:city":"Uxbridge",
    "sg:classifiers":[
        {
            "category":"Organizations",
            "subcategory":"Non-profit Organization",
            "type":"Services"
        }
    ],
    "sg:phone":"+44 20 8848 8319",
    "sg:postcode":"UB8 3QX",
    "sg:province":"Buckinghamshire",
    "sg:tags":[
        "organisation",
        "voluntary",
        "charity"
    ],
    "wof:name":"Disablement Association",
    "wof:placetype":"venue"
},
  "geometry": {"coordinates":[-0.4652499855,51.5242004395],"type":"Point"}
}