{
  "type": "Feature",
  "properties": {
    "iso:country":"GB",
    "sg:address":"Unit G, Pasture Lane",
    "sg:city":"Leicester",
    "sg:classifiers":[
        {
            "category":"Professional",
            "subcategory":"Accounting & Tax Preparation",
            "type":"Services"
        },
        {
            "category":"Professional",
            "type":"Services"
        }
    ],
    "sg:phone":"+44 116 253 2434",
    "sg:postcode":"LE1 4EY",
    "sg:province":"Leicestershire",
    "sg:tags":[
        "pattern",
        "industrial",
        "maker"
    ],
    "wof:name":"D K Patterns",
    "wof:placetype":"venue"
},
  "geometry": {"coordinates":[-1.1403650045,52.6378860474],"type":"Point"}
}