{
  "type": "Feature",
  "properties": {
    "addr:full":"Newlands Hall, Frosterley Bishop Auckland Durham DL13 2SH",
    "addr:postcode":"dl13 2sh",
    "addr:street":"Bishop Auckland",
    "iso:country":"GB",
    "sg:address":"Newlands Hall, Frosterley",
    "sg:city":"Bishop Auckland",
    "sg:classifiers":[
        {
            "category":"Farming",
            "subcategory":"Livestock Farm",
            "type":"Manufacturing & Wholesale Goods"
        }
    ],
    "sg:phone":"+44 1388 527258",
    "sg:postcode":"DL13 2SH",
    "sg:province":"Durham",
    "sg:tags":[
        "others"
    ],
    "wof:name":"T.H Pickering",
    "wof:placetype":"venue"
},
  "geometry": {"coordinates":[-1.9549839497,54.7272644043],"type":"Point"}
}