{
  "type": "Feature",
  "properties": {
    "addr:full":"Unit 15, Telford Court, Clydebank Business Park Clydebank East Dunbartonshire G81 2NR",
    "addr:housenumber":"unit 15",
    "addr:postcode":"g81 2nr",
    "addr:street":"Telford Court Clydebank Business Park Clydebank",
    "iso:country":"GB",
    "sg:address":"Unit 15, Telford Court, Clydebank Business Park",
    "sg:city":"Clydebank",
    "sg:classifiers":[
        {
            "category":"Shopping",
            "subcategory":"Stationery & Office Supplies",
            "type":"Retail Goods"
        }
    ],
    "sg:postcode":"G81 2NR",
    "sg:province":"East Dunbartonshire",
    "wof:name":"Donation Envelopes Ltd.",
    "wof:placetype":"venue"
},
  "geometry": {"coordinates":[-4.4036488533,55.9108581543],"type":"Point"}
}