{
  "type": "Feature",
  "properties": {
    "addr:full":"Unit 21, Empire Ctre, Interior Way Watford Hertfordshire WD24 4YY",
    "addr:housenumber":"unit 21",
    "addr:postcode":"wd24 4yy",
    "addr:street":"Empire;Interior Way",
    "iso:country":"GB",
    "sg:address":"Unit 21, Empire Ctre, Interior Way",
    "sg:city":"Watford",
    "sg:classifiers":[
        {
            "category":"Shopping",
            "subcategory":"Stationery & Office Supplies",
            "type":"Retail Goods"
        }
    ],
    "sg:phone":"+44 1923 817699",
    "sg:postcode":"WD24 4YY",
    "sg:province":"Hertfordshire",
    "sg:tags":[
        "printers'"
    ],
    "wof:name":"Empire Graphics Ltd",
    "wof:placetype":"venue"
},
  "geometry": {"coordinates":[-0.3916,51.668308],"type":"Point"}
}