{
  "type": "Feature",
  "properties": {
    "addr:full":"4 Evansfield Road Cardiff Cardiff CF14 2FA",
    "addr:housenumber":"4",
    "addr:postcode":"cf14 2fa",
    "addr:street":"Evansfield Road",
    "iso:country":"GB",
    "sg:address":"4 Evansfield Road",
    "sg:city":"Cardiff",
    "sg:classifiers":[
        {
            "category":"Retail",
            "subcategory":"Veterinary Services",
            "type":"Services"
        }
    ],
    "sg:phone":"+44 29 2057 6600",
    "sg:postcode":"CF14 2FA",
    "sg:province":"Cardiff",
    "sg:tags":[
        "surgeon",
        "activity"
    ],
    "wof:name":"Cumines Veterinary Surgery",
    "wof:placetype":"venue"
},
  "geometry": {"coordinates":[-3.228174,51.507496],"type":"Point"}
}