{
  "type": "Feature",
  "properties": {
    "addr:full":"Langdon Road Swansea Neath Port Talbot SA1 8QY",
    "addr:postcode":"sa1 8qy",
    "addr:street":"Langdon Road",
    "iso:country":"GB",
    "sg:address":"Langdon Road",
    "sg:city":"Swansea",
    "sg:classifiers":[
        {
            "category":"Retail",
            "subcategory":"Auto Repair",
            "type":"Services"
        }
    ],
    "sg:phone":"+44 1792 456327",
    "sg:postcode":"SA1 8QY",
    "sg:province":"Neath Port Talbot",
    "sg:tags":[
        "body",
        "car"
    ],
    "wof:name":"The Exclusive Body Centre",
    "wof:placetype":"venue"
},
  "geometry": {"coordinates":[-3.91921,51.620167],"type":"Point"}
}