{
  "type": "Feature",
  "properties": {
    "iso:country":"GB",
    "sg:address":"Shadon Way, Portobello Industrial Est, Birtley",
    "sg:city":"Chester-le-street",
    "sg:classifiers":[
        {
            "category":"Food & Beverages",
            "subcategory":"Bakery",
            "type":"Retail Goods"
        }
    ],
    "sg:postcode":"DH3 2RG",
    "sg:province":"Durham",
    "sg:tags":[
        "confectionery"
    ],
    "wof:name":"Jackson,William,& Son Ltd",
    "wof:placetype":"venue"
},
  "geometry": {"coordinates":[-1.561794,54.893559],"type":"Point"}
}