{
  "type": "Feature",
  "properties": {
    "addr:full":"South Street Atherstone Leicestershire CV9 1DR",
    "addr:postcode":"cv9 1dr",
    "addr:street":"South Street",
    "iso:country":"GB",
    "sg:address":"South Street",
    "sg:city":"Atherstone",
    "sg:classifiers":[
        {
            "category":"Autos & Motor Vehicles",
            "subcategory":"Auto Supplies",
            "type":"Retail Goods"
        }
    ],
    "sg:phone":"+44 1827 712701",
    "sg:postcode":"CV9 1DR",
    "sg:province":"Leicestershire",
    "sg:tags":[
        "tyre"
    ],
    "wof:name":"Hi-Q Tyre Services",
    "wof:placetype":"venue"
},
  "geometry": {"coordinates":[-1.5460239649,52.5760612488],"type":"Point"}
}