{
  "type": "Feature",
  "properties": {
    "iso:country":"GB",
    "sg:address":"6 Wilson Street",
    "sg:city":"Peterhead",
    "sg:classifiers":[
        {
            "category":"Retail",
            "subcategory":"Auto Repair",
            "type":"Services"
        }
    ],
    "sg:phone":"+44 1779 477009",
    "sg:postcode":"AB42 6UD",
    "sg:province":"Aberdeenshire",
    "sg:tags":[
        "body",
        "car"
    ],
    "wof:name":"Neil Daniel Autobody",
    "wof:placetype":"venue"
},
  "geometry": {"coordinates":[-1.778233,57.510395],"type":"Point"}
}