{
  "type": "Feature",
  "properties": {
    "addr:full":"44 Gordon Road Gosport Hampshire PO12 3QF",
    "addr:housenumber":"44",
    "addr:postcode":"po12 3qf",
    "addr:street":"Gordon Road",
    "iso:country":"GB",
    "sg:address":"44 Gordon Road",
    "sg:city":"Gosport",
    "sg:classifiers":[
        {
            "category":"Professional",
            "type":"Services"
        }
    ],
    "sg:postcode":"PO12 3QF",
    "sg:province":"Hampshire",
    "sg:tags":[
        "entertainer"
    ],
    "wof:name":"Paramount Entertainments",
    "wof:placetype":"venue"
},
  "geometry": {"coordinates":[-1.144028,50.794056],"type":"Point"}
}