{
  "type": "Feature",
  "properties": {
    "iso:country":"GB",
    "sg:address":"29 Frinton Road, Holland-on-sea",
    "sg:city":"Clacton-on-sea",
    "sg:classifiers":[
        {
            "category":"Shopping",
            "subcategory":"Used Merchandise",
            "type":"Retail Goods"
        }
    ],
    "sg:phone":"+44 1255 815625",
    "sg:postcode":"CO15 5UH",
    "sg:province":"Essex",
    "sg:tags":[
        "shop",
        "second-hand"
    ],
    "wof:name":"Caters Secondhand",
    "wof:placetype":"venue"
},
  "geometry": {"coordinates":[1.18201,51.803055],"type":"Point"}
}