{
  "type": "Feature",
  "properties": {
    "iso:country":"GB",
    "sg:address":"5 Ullswater Rd, Fulwood",
    "sg:city":"Preston",
    "sg:classifiers":[
        {
            "category":"Building & Trades",
            "subcategory":"Plumbing",
            "type":"Services"
        }
    ],
    "sg:postcode":"PR2 8AT",
    "sg:province":"Lancashire",
    "sg:tags":[
        "heating"
    ],
    "wof:name":"Breakell,Paul,",
    "wof:placetype":"venue"
},
  "geometry": {"coordinates":[-2.6815319061,53.7794342041],"type":"Point"}
}