{
  "type": "Feature",
  "properties": {
    "addr:full":"Langdale Road Barnsley South Yorkshire S71 1AQ",
    "addr:postcode":"s71 1aq",
    "addr:street":"Langdale Road;Yorkshire",
    "iso:country":"GB",
    "sg:address":"Langdale Road",
    "sg:city":"Barnsley",
    "sg:classifiers":[
        {
            "category":"Education",
            "subcategory":"Special Training",
            "type":"Public Place"
        }
    ],
    "sg:postcode":"S71 1AQ",
    "sg:province":"South Yorkshire",
    "sg:tags":[
        "product",
        "centre"
    ],
    "wof:name":"Barnsley T U C Training Ltd.",
    "wof:placetype":"venue"
},
  "geometry": {"coordinates":[-1.472383976,53.5505485535],"type":"Point"}
}