{
  "type": "Feature",
  "properties": {
    "addr:full":"42a Throwley Way Sutton Surrey SM1 4AF",
    "addr:housenumber":"42a",
    "addr:postcode":"sm1 4af",
    "addr:street":"Throwley Way",
    "iso:country":"GB",
    "sg:address":"42a Throwley Way",
    "sg:city":"Sutton",
    "sg:classifiers":[
        {
            "category":"Autos & Motor Vehicles",
            "subcategory":"Fuel & Gas Station",
            "type":"Retail Goods"
        }
    ],
    "sg:postcode":"SM1 4AF",
    "sg:province":"Surrey",
    "sg:tags":[
        "hr",
        "petrol"
    ],
    "wof:name":"SNAX 24 LTD",
    "wof:placetype":"venue"
},
  "geometry": {"coordinates":[-0.1921640038,51.3651313782],"type":"Point"}
}