{
  "type": "Feature",
  "properties": {
    "addr:full":"8 Monument Grn Weybridge Surrey KT13 8QS",
    "addr:housenumber":"8",
    "addr:postcode":"kt13 8qs",
    "addr:street":"Monument Grn Weybridge",
    "iso:country":"GB",
    "sg:address":"8 Monument Grn",
    "sg:city":"Weybridge",
    "sg:classifiers":[
        {
            "category":"Health Services",
            "subcategory":"Podiatrist",
            "type":"Services"
        }
    ],
    "sg:postcode":"KT13 8QS",
    "sg:province":"Surrey",
    "sg:tags":[
        "podiatrists",
        "chiropodist"
    ],
    "wof:name":"Weybridge Chiropody Surgery",
    "wof:placetype":"venue"
},
  "geometry": {"coordinates":[-0.4537180066,51.3736991882],"type":"Point"}
}