{
  "type": "Feature",
  "properties": {
    "iso:country":"GB",
    "sg:address":"Burnley Road, Brierfield",
    "sg:city":"Nelson",
    "sg:classifiers":[
        {
            "category":"Shopping",
            "subcategory":"Clothing, Apparel, & Fashions",
            "type":"Retail Goods"
        }
    ],
    "sg:phone":"+44 1282 602074",
    "sg:postcode":"BB9 5HR",
    "sg:province":"Lancashire",
    "sg:tags":[
        "clothing",
        "fabric"
    ],
    "wof:name":"Powerhouse Designer Fashion",
    "wof:placetype":"venue"
},
  "geometry": {"coordinates":[-2.2342839241,53.8236045837],"type":"Point"}
}