{
  "type": "Feature",
  "properties": {
    "iso:country":"GB",
    "sg:address":"51 Aveley Lane",
    "sg:city":"Farnham",
    "sg:classifiers":[
        {
            "category":"Professional",
            "subcategory":"Management & Consulting",
            "type":"Services"
        },
        {
            "category":"Building & Trades",
            "subcategory":"Construction",
            "type":"Services"
        }
    ],
    "sg:postcode":"GU9 8PS",
    "sg:province":"Surrey",
    "sg:tags":[
        "consultant",
        "builder",
        "specialist"
    ],
    "wof:name":"Colour Charisma & Beauty",
    "wof:placetype":"venue"
},
  "geometry": {"coordinates":[-0.8007289767,51.1993217468],"type":"Point"}
}