{
  "type": "Feature",
  "properties": {
    "addr:full":"19-21 Woodside Rd Bournemouth Dorset BH5 2BA",
    "addr:housenumber":"19-21",
    "addr:postcode":"bh5 2ba",
    "addr:street":"Woodside Rd",
    "iso:country":"GB",
    "sg:address":"19-21 Woodside Rd",
    "sg:city":"Bournemouth",
    "sg:classifiers":[
        {
            "category":"Professional",
            "subcategory":"Art Services",
            "type":"Services"
        }
    ],
    "sg:phone":"+44 1202 420858",
    "sg:postcode":"BH5 2BA",
    "sg:province":"Dorset",
    "sg:tags":[
        "graphic",
        "designer"
    ],
    "wof:name":"Concept Design Group",
    "wof:placetype":"venue"
},
  "geometry": {"coordinates":[-1.8200279474,50.7262077332],"type":"Point"}
}