{
  "type": "Feature",
  "properties": {
    "addr:full":"Lunb Lane Mills Bradford West Yorkshire BD8 7RP",
    "addr:postcode":"bd8 7rp",
    "addr:street":"Lunb Lane",
    "iso:country":"GB",
    "sg:address":"Lunb Lane Mills",
    "sg:city":"Bradford",
    "sg:classifiers":[
        {
            "category":"Manufacturing",
            "subcategory":"Textiles",
            "type":"Manufacturing & Wholesale Goods"
        }
    ],
    "sg:phone":"+44 1274 725761",
    "sg:postcode":"BD8 7RP",
    "sg:province":"West Yorkshire",
    "sg:tags":[
        "knitwear"
    ],
    "wof:name":"Victoria Warping Co. Ltd.",
    "wof:placetype":"venue"
},
  "geometry": {"coordinates":[-1.761416,53.798008],"type":"Point"}
}