{
  "type": "Feature",
  "properties": {
    "iso:country":"GB",
    "sg:address":"96 Oldham Road, Middleton",
    "sg:city":"Manchester",
    "sg:classifiers":[
        {
            "category":"Retail",
            "subcategory":"Driving School",
            "type":"Services"
        }
    ],
    "sg:phone":"+44 161 653 1591",
    "sg:postcode":"M24 1AX",
    "sg:province":"Greater Manchester",
    "wof:name":"Georgies School of Motoring",
    "wof:placetype":"venue"
},
  "geometry": {"coordinates":[-2.1933341026,53.5487213135],"type":"Point"}
}