{
  "type": "Feature",
  "properties": {
    "iso:country":"GB",
    "sg:address":"Boodles House, 35 Lord Street",
    "sg:city":"Liverpool",
    "sg:classifiers":[
        {
            "category":"Shopping",
            "subcategory":"Comic Books",
            "type":"Retail Goods"
        }
    ],
    "sg:phone":"+44 151 227 2525",
    "sg:postcode":"L2 9SQ",
    "sg:province":"Merseyside",
    "sg:tags":[
        "jeweller"
    ],
    "wof:name":"Boodle & Dunthorne Ltd.",
    "wof:placetype":"venue"
},
  "geometry": {"coordinates":[-2.9884879589,53.4053840637],"type":"Point"}
}