{
  "type": "Feature",
  "properties": {
    "addr:full":", Wimborne St Giles Wimborne Dorset BH21 5NF",
    "addr:postcode":"bh21 5nf",
    "addr:street":"Wimborne",
    "iso:country":"GB",
    "sg:address":", Wimborne St Giles",
    "sg:city":"Wimborne",
    "sg:classifiers":[
        {
            "category":"Bars & Pubs",
            "type":"Food & Drink"
        }
    ],
    "sg:phone":"+44 1725 517284",
    "sg:postcode":"BH21 5NF",
    "sg:province":"Dorset",
    "sg:tags":[
        "pubs",
        "inn"
    ],
    "wof:name":"The Bull Inn",
    "wof:placetype":"venue"
},
  "geometry": {"coordinates":[-1.922606945,50.918094635],"type":"Point"}
}