{
  "type": "Feature",
  "properties": {
    "addr:full":"92 Kirk Edge Road Sheffield South Yorkshire S35 0AE",
    "addr:housenumber":"92",
    "addr:postcode":"s35 0ae",
    "addr:street":"Kirk Edge Road",
    "iso:country":"GB",
    "sg:address":"92 Kirk Edge Road",
    "sg:city":"Sheffield",
    "sg:classifiers":[
        {
            "category":"Building & Trades",
            "subcategory":"Construction",
            "type":"Services"
        }
    ],
    "sg:phone":"+44 114 286 3230",
    "sg:postcode":"S35 0AE",
    "sg:province":"South Yorkshire",
    "sg:tags":[
        "builder"
    ],
    "wof:name":"David Dixon",
    "wof:placetype":"venue"
},
  "geometry": {"coordinates":[-1.543965,53.423817],"type":"Point"}
}