{
  "type": "Feature",
  "properties": {
    "iso:country":"GB",
    "sg:address":"28a North Rd",
    "sg:city":"Brighton",
    "sg:classifiers":[
        {
            "category":"Professional",
            "subcategory":"Printing & Photocopies",
            "type":"Services"
        }
    ],
    "sg:phone":"+44 1273 626333",
    "sg:postcode":"BN1 1YB",
    "sg:province":"East Sussex",
    "sg:tags":[
        "t-shirt"
    ],
    "wof:name":"Jump The Gun",
    "wof:placetype":"venue"
},
  "geometry": {"coordinates":[-0.139619,50.825653],"type":"Point"}
}