{
  "type": "Feature",
  "properties": {
    "addr:full":"37 Broad St Ross On Wye Gloucestershire HR9 7DY",
    "addr:housenumber":"37",
    "addr:postcode":"hr9 7dy",
    "addr:street":"Broad St",
    "iso:country":"GB",
    "sg:address":"37 Broad St",
    "sg:city":"Ross On Wye",
    "sg:classifiers":[
        {
            "category":"Home & Garden",
            "subcategory":"Kitchen Supply",
            "type":"Retail Goods"
        }
    ],
    "sg:phone":"+44 1989 562546",
    "sg:postcode":"HR9 7DY",
    "sg:province":"Gloucestershire",
    "sg:tags":[
        "glassware",
        "china"
    ],
    "wof:name":"Wye Gallery",
    "wof:placetype":"venue"
},
  "geometry": {"coordinates":[-2.582173,51.9156],"type":"Point"}
}