{
  "type": "Feature",
  "properties": {
    "addr:full":"158 Standard Ave Coventry Warwickshire CV4 9BS",
    "addr:housenumber":"158",
    "addr:postcode":"cv4 9bs",
    "addr:street":"Standard Ave",
    "iso:country":"GB",
    "sg:address":"158 Standard Ave",
    "sg:city":"Coventry",
    "sg:classifiers":[
        {
            "category":"Communications",
            "type":"Services"
        }
    ],
    "sg:postcode":"CV4 9BS",
    "sg:province":"Warwickshire",
    "sg:tags":[
        "telecommunication"
    ],
    "wof:name":"Phonetel Communications",
    "wof:placetype":"venue"
},
  "geometry": {"coordinates":[-1.570274,52.401161],"type":"Point"}
}