{
  "type": "Feature",
  "properties": {
    "addr:full":"Castle Maluuood, Minstead Southampton Hampshire SO43 7PE",
    "addr:postcode":"so43 7pe",
    "iso:country":"GB",
    "sg:address":"Castle Maluuood, Minstead",
    "sg:city":"Southampton",
    "sg:classifiers":[
        {
            "category":"Home & Garden",
            "subcategory":"Household Appliances",
            "type":"Retail Goods"
        }
    ],
    "sg:phone":"+44 23 8081 7490",
    "sg:postcode":"SO43 7PE",
    "sg:province":"Hampshire",
    "sg:tags":[
        "equipment",
        "refrigeration",
        "air conditioning"
    ],
    "wof:name":"Thermal Transfer (Southern) Ltd.",
    "wof:placetype":"venue"
},
  "geometry": {"coordinates":[-1.609734,50.902676],"type":"Point"}
}