{
  "type": "Feature",
  "properties": {
    "addr:full":"35 Kings Way Harrow Greater London HA1 1XT",
    "addr:housenumber":"35",
    "addr:postcode":"ha1 1xt",
    "addr:street":"Kings Way",
    "iso:country":"GB",
    "sg:address":"35 Kings Way",
    "sg:city":"Harrow",
    "sg:classifiers":[
        {
            "category":"Retail",
            "subcategory":"Driving School",
            "type":"Services"
        }
    ],
    "sg:phone":"+44 20 8861 0421",
    "sg:postcode":"HA1 1XT",
    "sg:province":"Greater London",
    "wof:name":"Drive School of Motoring",
    "wof:placetype":"venue"
},
  "geometry": {"coordinates":[-0.3377130032,51.5910186768],"type":"Point"}
}