{
  "type": "Feature",
  "properties": {
    "addr:full":"Unit 5 Swan Corner Centre, Chase Road Burntwood Staffordshire WS7 0DW",
    "addr:housenumber":"unit 5",
    "addr:postcode":"ws7 0dw",
    "addr:street":"Chase Road",
    "iso:country":"GB",
    "sg:address":"Unit 5 Swan Corner Centre, Chase Road",
    "sg:city":"Burntwood",
    "sg:classifiers":[
        {
            "category":"Food & Beverages",
            "subcategory":"Liquor & Beverages",
            "type":"Retail Goods"
        }
    ],
    "sg:phone":"+44 1543 685422",
    "sg:postcode":"WS7 0DW",
    "sg:province":"Staffordshire",
    "sg:tags":[
        "beer",
        "spirit",
        "wines"
    ],
    "wof:name":"Thresher",
    "wof:placetype":"venue"
},
  "geometry": {"coordinates":[-1.920019,52.67976],"type":"Point"}
}