{
  "type": "Feature",
  "properties": {
    "addr:full":"29 Whytescauseway Kirkcaldy Fife KY1 1XF",
    "addr:housenumber":"29",
    "addr:postcode":"ky1 1xf",
    "addr:street":"Whytescauseway",
    "iso:country":"GB",
    "sg:address":"29 Whytescauseway",
    "sg:city":"Kirkcaldy",
    "sg:classifiers":[
        {
            "category":"Real Estate",
            "subcategory":"Real Estate Agent",
            "type":"Services"
        }
    ],
    "sg:postcode":"KY1 1XF",
    "sg:province":"Fife",
    "wof:name":"Kirkcaldy Properties",
    "wof:placetype":"venue"
},
  "geometry": {"coordinates":[-3.161386,56.109192],"type":"Point"}
}