{
  "type": "Feature",
  "properties": {
    "addr:full":"10 Tower Hill Ormskirk Lancashire L39 2EF",
    "addr:housenumber":"10",
    "addr:postcode":"l39 2ef",
    "addr:street":"Tower Hill",
    "iso:country":"GB",
    "sg:address":"10 Tower Hill",
    "sg:city":"Ormskirk",
    "sg:classifiers":[
        {
            "category":"Building & Trades",
            "subcategory":"Plumbing",
            "type":"Services"
        }
    ],
    "sg:phone":"+44 1695 573007",
    "sg:postcode":"L39 2EF",
    "sg:province":"Lancashire",
    "sg:tags":[
        "central",
        "heating"
    ],
    "wof:name":"Sprint Heating & Plumbing Services",
    "wof:placetype":"venue"
},
  "geometry": {"coordinates":[-2.873276,53.570026],"type":"Point"}
}