{
  "type": "Feature",
  "properties": {
    "iso:country":"GB",
    "sg:address":"10 Tower Gardens",
    "sg:city":"Holywell",
    "sg:classifiers":[
        {
            "category":"Real Estate",
            "subcategory":"Real Estate Agent",
            "type":"Services"
        }
    ],
    "sg:phone":"+44 1352 711456",
    "sg:postcode":"CH8 7TG",
    "sg:province":"Denbighshire",
    "wof:name":"Preston's Estate Agents",
    "wof:placetype":"venue"
},
  "geometry": {"coordinates":[-3.22104,53.273621],"type":"Point"}
}