{
  "type": "Feature",
  "properties": {
    "addr:full":"Unit 5, Park Venture Centre, Park Street Cannock Staffordshire WS11 3BT",
    "addr:housenumber":"unit 5",
    "addr:postcode":"ws11 3bt",
    "addr:street":"Park Venture Centre Park Street",
    "iso:country":"GB",
    "sg:address":"Unit 5, Park Venture Centre, Park Street",
    "sg:city":"Cannock",
    "sg:classifiers":[
        {
            "category":"Shopping",
            "subcategory":"Clothing, Apparel, & Fashions",
            "type":"Retail Goods"
        }
    ],
    "sg:phone":"+44 1543 571990",
    "sg:postcode":"WS11 3BT",
    "sg:province":"Staffordshire",
    "sg:tags":[
        "t-shirt"
    ],
    "wof:name":"Supa Print",
    "wof:placetype":"venue"
},
  "geometry": {"coordinates":[-2.033145,52.690952],"type":"Point"}
}