{
  "type": "Feature",
  "properties": {
    "iso:country":"GB",
    "sg:address":"Kimberley House, 11 Woodhouse Square",
    "sg:city":"Leeds",
    "sg:classifiers":[
        {
            "category":"Banks & Credit Unions",
            "subcategory":"Financial Services",
            "type":"Services"
        }
    ],
    "sg:phone":"+44 113 244 4582",
    "sg:postcode":"LS3 1AD",
    "sg:province":"West Yorkshire",
    "sg:tags":[
        "consultant"
    ],
    "wof:name":"General Motor Acceptance Corp",
    "wof:placetype":"venue"
},
  "geometry": {"coordinates":[-1.556907,53.801334],"type":"Point"}
}