{
  "type": "Feature",
  "properties": {
    "addr:full":"The Elms, Cranfield Park Road Wickford Essex SS12 9EP",
    "addr:postcode":"ss12 9ep",
    "addr:street":"Park Road",
    "iso:country":"GB",
    "sg:address":"The Elms, Cranfield Park Road",
    "sg:city":"Wickford",
    "sg:classifiers":[
        {
            "category":"Retail",
            "subcategory":"Auto Repair",
            "type":"Services"
        }
    ],
    "sg:postcode":"SS12 9EP",
    "sg:province":"Essex",
    "sg:tags":[
        "modification",
        "garage"
    ],
    "wof:name":"Pitchers Vehicle Repairs",
    "wof:placetype":"venue"
},
  "geometry": {"coordinates":[0.5186,51.600033],"type":"Point"}
}