{
  "type": "Feature",
  "properties": {
    "addr:full":"Unit 5, Montrose Way Liverpool Merseyside L13 1EW",
    "addr:housenumber":"unit 5",
    "addr:postcode":"l13 1ew",
    "addr:street":"Montrose Way",
    "iso:country":"GB",
    "sg:address":"Unit 5, Montrose Way",
    "sg:city":"Liverpool",
    "sg:classifiers":[
        {
            "category":"Home & Garden",
            "subcategory":"Hardware",
            "type":"Retail Goods"
        }
    ],
    "sg:phone":"+44 151 254 2044",
    "sg:postcode":"L13 1EW",
    "sg:province":"Merseyside",
    "sg:tags":[
        "retailer",
        "diy"
    ],
    "wof:name":"B & Q DIY & Garden Supercentres",
    "wof:placetype":"venue"
},
  "geometry": {"coordinates":[-2.9233388901,53.410068512],"type":"Point"}
}