{
  "type": "Feature",
  "properties": {
    "addr:full":"158 Central Road Worcester Park Surrey KT4 8HH",
    "addr:housenumber":"158",
    "addr:postcode":"kt4 8hh",
    "addr:street":"Central Road",
    "iso:country":"GB",
    "sg:address":"158 Central Road",
    "sg:city":"Worcester Park",
    "sg:classifiers":[
        {
            "category":"Shopping",
            "subcategory":"Pharmacy",
            "type":"Retail Goods"
        }
    ],
    "sg:phone":"+44 20 8337 2612",
    "sg:postcode":"KT4 8HH",
    "sg:province":"Surrey",
    "sg:tags":[
        "pharmacist",
        "chemist"
    ],
    "wof:name":"Boots the Chemist",
    "wof:placetype":"venue"
},
  "geometry": {"coordinates":[-0.2433239967,51.3795471191],"type":"Point"}
}