{
  "type": "Feature",
  "properties": {
    "addr:full":"32 Spring Bank Road Chesterfield Derbyshire S40 1NL",
    "addr:housenumber":"32",
    "addr:postcode":"s40 1nl",
    "addr:street":"Spring Bank Road",
    "iso:country":"GB",
    "sg:address":"32 Spring Bank Road",
    "sg:city":"Chesterfield",
    "sg:classifiers":[
        {
            "category":"Travel",
            "subcategory":"Hotels & Motels",
            "type":"Entertainment"
        }
    ],
    "sg:postcode":"S40 1NL",
    "sg:province":"Derbyshire",
    "wof:name":"Tullamore Hotel",
    "wof:placetype":"venue"
},
  "geometry": {"coordinates":[-1.437869,53.237514],"type":"Point"}
}