{
  "type": "Feature",
  "properties": {
    "addr:full":"Unit 7, Tindle Centre, St. Marychurch Rd Newton Abbot Devon TQ12 4UQ",
    "addr:housenumber":"unit 7",
    "addr:postcode":"tq12 4uq",
    "addr:street":"Tindle Centre St. Marychurch Rd",
    "iso:country":"GB",
    "sg:address":"Unit 7, Tindle Centre, St. Marychurch Rd",
    "sg:city":"Newton Abbot",
    "sg:classifiers":[
        {
            "category":"Home & Garden",
            "subcategory":"Hardware",
            "type":"Retail Goods"
        }
    ],
    "sg:phone":"+44 1626 353720",
    "sg:postcode":"TQ12 4UQ",
    "sg:province":"Devon",
    "sg:tags":[
        "heat",
        "mech",
        "exchanger"
    ],
    "wof:name":"Fridgestock Ltd",
    "wof:placetype":"venue"
},
  "geometry": {"coordinates":[-3.5911879539,50.524181366],"type":"Point"}
}