{
  "type": "Feature",
  "properties": {
    "addr:full":"Rockdale Rd Sevenoaks Kent TN13 1JT",
    "addr:postcode":"tn13 1jt",
    "addr:street":"Rockdale Rd",
    "iso:country":"GB",
    "sg:address":"Rockdale Rd",
    "sg:city":"Sevenoaks",
    "sg:classifiers":[
        {
            "category":"Social Services",
            "subcategory":"Retirement Home",
            "type":"Services"
        }
    ],
    "sg:phone":"+44 1732 454763",
    "sg:postcode":"TN13 1JT",
    "sg:province":"Kent",
    "sg:tags":[
        "residential",
        "care"
    ],
    "wof:name":"Rockdale House",
    "wof:placetype":"venue"
},
  "geometry": {"coordinates":[0.1927849948,51.2693252563],"type":"Point"}
}