{
  "type": "Feature",
  "properties": {
    "iso:country":"GB",
    "sg:address":"Chart Road",
    "sg:city":"Ashford",
    "sg:classifiers":[
        {
            "category":"Retail",
            "subcategory":"Auto Repair",
            "type":"Services"
        }
    ],
    "sg:postcode":"TN23 3HZ",
    "sg:province":"Kent",
    "sg:tags":[
        "modification",
        "garage"
    ],
    "wof:name":"Ashford Motor Co.",
    "wof:placetype":"venue"
},
  "geometry": {"coordinates":[0.863107,51.152798],"type":"Point"}
}