{
  "type": "Feature",
  "properties": {
    "iso:country":"GB",
    "sg:address":"17 Ince Road",
    "sg:city":"Canterbury",
    "sg:classifiers":[
        {
            "category":"Building & Trades",
            "subcategory":"Plumbing",
            "type":"Services"
        }
    ],
    "sg:phone":"+44 1227 712695",
    "sg:postcode":"CT2 0NU",
    "sg:province":"Kent",
    "sg:tags":[
        "heating"
    ],
    "wof:name":"Plumbqwik",
    "wof:placetype":"venue"
},
  "geometry": {"coordinates":[1.1251749992,51.3070068359],"type":"Point"}
}