{
  "type": "Feature",
  "properties": {
    "addr:full":"15 The Parade, Uttoxeter Road, Mickleover Derby Derbyshire DE3 0GB",
    "addr:housenumber":"15",
    "addr:postcode":"de3 0gb",
    "addr:street":"The Parade Uttoxeter Road",
    "iso:country":"GB",
    "sg:address":"15 The Parade, Uttoxeter Road, Mickleover",
    "sg:city":"Derby",
    "sg:classifiers":[
        {
            "category":"Food & Beverages",
            "subcategory":"Meat & Fish",
            "type":"Retail Goods"
        },
        {
            "category":"Food & Beverages",
            "subcategory":"Groceries & Convenience Stores",
            "type":"Retail Goods"
        }
    ],
    "sg:phone":"+44 1332 511451",
    "sg:postcode":"DE3 0GB",
    "sg:province":"Derbyshire",
    "sg:tags":[
        "shop",
        "chip"
    ],
    "wof:name":"Steves Fish Bar",
    "wof:placetype":"venue"
},
  "geometry": {"coordinates":[-1.5461349487,52.9039077759],"type":"Point"}
}