{
  "type": "Feature",
  "properties": {
    "addr:full":"23 Gorsride Grantham Lincolnshire NG31 9BS",
    "addr:housenumber":"23",
    "addr:postcode":"ng31 9bs",
    "addr:street":"Gorsride Grantham",
    "iso:country":"GB",
    "sg:address":"23 Gorsride",
    "sg:city":"Grantham",
    "sg:classifiers":[
        {
            "category":"Building & Trades",
            "subcategory":"Plumbing",
            "type":"Services"
        }
    ],
    "sg:postcode":"NG31 9BS",
    "sg:province":"Lincolnshire",
    "sg:tags":[
        "heating"
    ],
    "wof:name":"Brian K Ford",
    "wof:placetype":"venue"
},
  "geometry": {"coordinates":[-0.58347,52.930553],"type":"Point"}
}