{
  "type": "Feature",
  "properties": {
    "iso:country":"GB",
    "sg:address":"152 Westborough Road",
    "sg:city":"Westcliff-on-sea",
    "sg:classifiers":[
        {
            "category":"Freight",
            "type":"Transportation"
        }
    ],
    "sg:phone":"+44 870 240 8287",
    "sg:postcode":"SS0 9JF",
    "sg:province":"Essex",
    "sg:tags":[
        "forwarders"
    ],
    "wof:name":"Brindlex Shipping Ltd.",
    "wof:placetype":"venue"
},
  "geometry": {"coordinates":[0.691472,51.546436],"type":"Point"}
}