{
  "type": "Feature",
  "properties": {
    "iso:country":"GB",
    "sg:address":"178 Woodhouse Road",
    "sg:city":"Manchester",
    "sg:classifiers":[
        {
            "category":"Building & Trades",
            "subcategory":"Plumbing",
            "type":"Services"
        }
    ],
    "sg:phone":"+44 161 748 3446",
    "sg:postcode":"M41 8NU",
    "sg:province":"Cheshire",
    "sg:tags":[
        "heating"
    ],
    "wof:name":"B Walker & Sons",
    "wof:placetype":"venue"
},
  "geometry": {"coordinates":[-2.385024,53.458744],"type":"Point"}
}