{
  "type": "Feature",
  "properties": {
    "addr:full":"3 South Av Hassocks East Sussex BN6 9QB",
    "addr:housenumber":"3",
    "addr:postcode":"bn6 9qb",
    "addr:street":"South Av Hassocks",
    "iso:country":"GB",
    "sg:address":"3 South Av",
    "sg:city":"Hassocks",
    "sg:classifiers":[
        {
            "category":"Professional",
            "subcategory":"Lawyer & Legal Services",
            "type":"Services"
        }
    ],
    "sg:phone":"+44 1273 832618",
    "sg:postcode":"BN6 9QB",
    "sg:province":"East Sussex",
    "sg:tags":[
        "solicitor"
    ],
    "wof:name":"A J Oakley",
    "wof:placetype":"venue"
},
  "geometry": {"coordinates":[-0.1743710041,50.931350708],"type":"Point"}
}