{
  "type": "Feature",
  "properties": {
    "addr:full":"Station Road, Stainforth Doncaster South Yorkshire DN7 5HS",
    "addr:postcode":"dn7 5hs",
    "addr:street":"Station Road",
    "iso:country":"GB",
    "sg:address":"Station Road, Stainforth",
    "sg:city":"Doncaster",
    "sg:classifiers":[
        {
            "category":"Arena",
            "subcategory":"Sports Club",
            "type":"Entertainment"
        }
    ],
    "sg:phone":"+44 1302 351204",
    "sg:postcode":"DN7 5HS",
    "sg:province":"South Yorkshire",
    "sg:tags":[
        "ground"
    ],
    "wof:name":"Meadow Court Stadium",
    "wof:placetype":"venue"
},
  "geometry": {"coordinates":[-1.028071,53.590454],"type":"Point"}
}