{
  "type": "Feature",
  "properties": {
    "addr:full":"Moat St Wigston Leicestershire LE18 2GD",
    "addr:postcode":"le18 2gd",
    "addr:street":"Moat St",
    "iso:country":"GB",
    "sg:address":"Moat St",
    "sg:city":"Wigston",
    "sg:classifiers":[
        {
            "category":"Shopping",
            "subcategory":"Clothing, Apparel, & Fashions",
            "type":"Retail Goods"
        }
    ],
    "sg:postcode":"LE18 2GD",
    "sg:province":"Leicestershire",
    "sg:tags":[
        "clothing"
    ],
    "wof:name":"Phasetape Ltd",
    "wof:placetype":"venue"
},
  "geometry": {"coordinates":[-1.1079570055,52.5821266174],"type":"Point"}
}