{
  "type": "Feature",
  "properties": {
    "iso:country":"GB",
    "sg:address":"31 Locksgreen Cres, Moredon",
    "sg:city":"Swindon",
    "sg:classifiers":[
        {
            "category":"Building & Trades",
            "subcategory":"Construction",
            "type":"Services"
        }
    ],
    "sg:postcode":"SN25 3HR",
    "sg:province":"Wiltshire",
    "sg:tags":[
        "contractor",
        "paving",
        "driveway"
    ],
    "wof:name":"Roberts,Tj,",
    "wof:placetype":"venue"
},
  "geometry": {"coordinates":[-1.8125629425,51.5866355896],"type":"Point"}
}