{
  "type": "Feature",
  "properties": {
    "addr:full":"Chesworth Ho, Pound Green Uckfield East Sussex TN22 4JW",
    "addr:postcode":"tn22 4jw",
    "addr:street":"Green",
    "iso:country":"GB",
    "sg:address":"Chesworth Ho, Pound Green",
    "sg:city":"Uckfield",
    "sg:classifiers":[
        {
            "category":"Health Services",
            "subcategory":"Health Practitioner",
            "type":"Services"
        }
    ],
    "sg:phone":"+44 1825 733766",
    "sg:postcode":"TN22 4JW",
    "sg:province":"East Sussex",
    "sg:tags":[
        "osteopath"
    ],
    "wof:name":"Diane Hales",
    "wof:placetype":"venue"
},
  "geometry": {"coordinates":[0.09665,50.971813],"type":"Point"}
}