{
  "type": "Feature",
  "properties": {
    "addr:full":"75 Cardiff Road, Northend Portsmouth Hampshire PO2 8BJ",
    "addr:housenumber":"75",
    "addr:postcode":"hampshire po2 8bj",
    "addr:street":"Cardiff Road",
    "iso:country":"GB",
    "sg:address":"75 Cardiff Road, Northend",
    "sg:city":"Portsmouth",
    "sg:classifiers":[
        {
            "category":"Building & Trades",
            "subcategory":"Construction",
            "type":"Services"
        }
    ],
    "sg:postcode":"PO2 8BJ",
    "sg:province":"Hampshire",
    "sg:tags":[
        "contractor",
        "paving",
        "driveway"
    ],
    "wof:name":"Quality Drives",
    "wof:placetype":"venue"
},
  "geometry": {"coordinates":[-1.0820169449,50.8183555603],"type":"Point"}
}