{
  "type": "Feature",
  "properties": {
    "addr:full":"4 Tavistock Place London Greater London WC1H 9RA",
    "addr:housenumber":"4",
    "addr:postcode":"wc1h 9ra",
    "addr:street":"Tavistock Place",
    "iso:country":"GB",
    "sg:address":"4 Tavistock Place",
    "sg:city":"London",
    "sg:classifiers":[
        {
            "category":"Professional",
            "subcategory":"Management & Consulting",
            "type":"Services"
        }
    ],
    "sg:postcode":"WC1H 9RA",
    "sg:province":"Greater London",
    "sg:tags":[
        "consultant"
    ],
    "wof:name":"Hunter Associates",
    "wof:placetype":"venue"
},
  "geometry": {"coordinates":[-0.1274860054,51.5247192383],"type":"Point"}
}