{
  "type": "Feature",
  "properties": {
    "addr:full":"484 Kings Road London Greater London SW10 0LF",
    "addr:housenumber":"484",
    "addr:postcode":"sw10 0lf",
    "addr:street":"Kings Road",
    "iso:country":"GB",
    "sg:address":"484 Kings Road",
    "sg:city":"London",
    "sg:classifiers":[
        {
            "category":"Professional",
            "subcategory":"Management & Consulting",
            "type":"Services"
        }
    ],
    "sg:phone":"+44 20 7221 6650",
    "sg:postcode":"SW10 0LF",
    "sg:province":"Greater London",
    "sg:tags":[
        "music"
    ],
    "wof:name":"Universe Tribal Gathering",
    "wof:placetype":"venue"
},
  "geometry": {"coordinates":[-0.1799730062,51.4822235107],"type":"Point"}
}