{
  "type": "Feature",
  "properties": {
    "addr:full":"777 Fulham Road London Greater London SW6 5HA",
    "addr:housenumber":"777",
    "addr:postcode":"sw6 5ha",
    "addr:street":"Fulham Road",
    "iso:country":"GB",
    "sg:address":"777 Fulham Road",
    "sg:city":"London",
    "sg:classifiers":[
        {
            "category":"Shopping",
            "subcategory":"Stationery & Office Supplies",
            "type":"Retail Goods"
        }
    ],
    "sg:phone":"+44 20 7736 7225",
    "sg:postcode":"SW6 5HA",
    "sg:province":"Greater London",
    "wof:name":"Perry Art & Stationers",
    "wof:placetype":"venue"
},
  "geometry": {"coordinates":[-0.2038760036,51.476474762],"type":"Point"}
}