{
  "type": "Feature",
  "properties": {
    "iso:country":"GB",
    "sg:address":"Unit 4, Tan La",
    "sg:city":"Exeter",
    "sg:classifiers":[
        {
            "category":"Autos & Motor Vehicles",
            "subcategory":"Auto Supplies",
            "type":"Retail Goods"
        }
    ],
    "sg:postcode":"EX2 8EG",
    "sg:province":"Devon",
    "sg:tags":[
        "windscreen"
    ],
    "wof:name":"Fields,F P,",
    "wof:placetype":"venue"
},
  "geometry": {"coordinates":[-3.5317099094,50.7129936218],"type":"Point"}
}