{
  "type": "Feature",
  "properties": {
    "addr:full":"30 Beaconsfield Road, Ealing London Greater London W5 5JE",
    "addr:housenumber":"30",
    "addr:postcode":"w5 5je",
    "addr:street":"Beaconsfield Road",
    "iso:country":"GB",
    "sg:address":"30 Beaconsfield Road, Ealing",
    "sg:city":"London",
    "sg:classifiers":[
        {
            "category":"Professional",
            "subcategory":"Lawyer & Legal Services",
            "type":"Services"
        }
    ],
    "sg:phone":"+44 20 8840 3849",
    "sg:postcode":"W5 5JE",
    "sg:province":"Greater London",
    "sg:tags":[
        "advice",
        "counselling"
    ],
    "wof:name":"Haven Centre for Counselling & Psychotherapy",
    "wof:placetype":"venue"
},
  "geometry": {"coordinates":[-0.3077079952,51.505153656],"type":"Point"}
}