{
  "type": "Feature",
  "properties": {
    "iso:country":"GB",
    "sg:address":"18-19 St. Dominic St",
    "sg:city":"Truro",
    "sg:classifiers":[
        {
            "category":"Retail",
            "subcategory":"Auto Repair",
            "type":"Services"
        }
    ],
    "sg:phone":"+44 1872 279952",
    "sg:postcode":"TR1 3JL",
    "sg:province":"Cornwall",
    "sg:tags":[
        "modification",
        "garage"
    ],
    "wof:name":"St. Dominic Street Motors",
    "wof:placetype":"venue"
},
  "geometry": {"coordinates":[-5.0576272011,50.2631988525],"type":"Point"}
}