{
  "type": "Feature",
  "properties": {
    "iso:country":"GB",
    "sg:address":"Kirkby Gardens",
    "sg:city":"Nottingham",
    "sg:classifiers":[
        {
            "category":"Education",
            "subcategory":"School",
            "type":"Public Place"
        }
    ],
    "sg:postcode":"NG2 2HZ",
    "sg:province":"Nottinghamshire",
    "sg:tags":[
        "local",
        "authority"
    ],
    "wof:name":"Nottingham City Council",
    "wof:placetype":"venue"
},
  "geometry": {"coordinates":[-1.14353,52.941925],"type":"Point"}
}