{
  "type": "Feature",
  "properties": {
    "addr:full":"Cressex Workshop, Unit 5 Halifax Rd High Wycombe Buckinghamshire HP12 3ST",
    "addr:housenumber":"unit 5",
    "addr:postcode":"hp12 3st",
    "addr:street":"Halifax Rd",
    "iso:country":"GB",
    "sg:address":"Cressex Workshop, Unit 5 Halifax Rd",
    "sg:city":"High Wycombe",
    "sg:classifiers":[
        {
            "category":"Education",
            "subcategory":"Special Training",
            "type":"Public Place"
        }
    ],
    "sg:phone":"+44 1494 459159",
    "sg:postcode":"HP12 3ST",
    "sg:province":"Buckinghamshire",
    "sg:tags":[
        "product",
        "centre"
    ],
    "wof:name":"Amersham & Wycombe College",
    "wof:placetype":"venue"
},
  "geometry": {"coordinates":[-0.7798699737,51.6222496033],"type":"Point"}
}