{
  "type": "Feature",
  "properties": {
    "addr:full":"Elder Park Primary School, St Kenneth Drive Glasgow Glasgow City G51 4QD",
    "addr:postcode":"g51 4qd",
    "addr:street":"Elder;St Kenneth Drive",
    "iso:country":"GB",
    "sg:address":"Elder Park Primary School, St Kenneth Drive",
    "sg:city":"Glasgow",
    "sg:classifiers":[
        {
            "category":"Government",
            "subcategory":"Office",
            "type":"Public Place"
        }
    ],
    "sg:phone":"+44 141 445 3654",
    "sg:postcode":"G51 4QD",
    "sg:province":"Glasgow City",
    "sg:tags":[
        "education",
        "agency",
        "authority"
    ],
    "wof:name":"Network Support",
    "wof:placetype":"venue"
},
  "geometry": {"coordinates":[-4.3301401138,55.8616409302],"type":"Point"}
}