{
  "type": "Feature",
  "properties": {
    "iso:country":"GB",
    "sg:address":"13 Laurence Industrial Estate, Eastwoodbury Lane",
    "sg:city":"Southend-on-sea",
    "sg:classifiers":[
        {
            "category":"Manufacturing",
            "subcategory":"Petroleum Products",
            "type":"Manufacturing & Wholesale Goods"
        }
    ],
    "sg:phone":"+44 1702 512444",
    "sg:postcode":"SS2 6RH",
    "sg:province":"Essex",
    "sg:tags":[
        "double",
        "glazing"
    ],
    "wof:name":"A B L Double Glazing & Joinery",
    "wof:placetype":"venue"
},
  "geometry": {"coordinates":[0.68176,51.567719],"type":"Point"}
}