{
  "type": "Feature",
  "properties": {
    "addr:full":"88 Mid Street Fraserburgh Aberdeenshire AB43 9JN",
    "addr:housenumber":"88",
    "addr:postcode":"ab43 9jn",
    "addr:street":"Mid Street",
    "iso:country":"GB",
    "sg:address":"88 Mid Street",
    "sg:city":"Fraserburgh",
    "sg:classifiers":[
        {
            "category":"Autos & Motor Vehicles",
            "subcategory":"Automobile Sales",
            "type":"Retail Goods"
        }
    ],
    "sg:phone":"+44 1346 518020",
    "sg:postcode":"AB43 9JN",
    "sg:province":"Aberdeenshire",
    "sg:tags":[
        "car"
    ],
    "wof:name":"JOHN WILLOX (FRASERBURGH) LTD",
    "wof:placetype":"venue"
},
  "geometry": {"coordinates":[-2.012223959,57.6923179626],"type":"Point"}
}