{
  "type": "Feature",
  "properties": {
    "iso:country":"GB",
    "sg:address":"170 High Street",
    "sg:city":"Lewes",
    "sg:classifiers":[
        {
            "category":"Shopping",
            "subcategory":"Luggage & Leather Goods",
            "type":"Retail Goods"
        }
    ],
    "sg:phone":"+44 1273 477018",
    "sg:postcode":"BN7 1XG",
    "sg:province":"East Sussex",
    "sg:tags":[
        "shop",
        "leathergoods"
    ],
    "wof:name":"The Dirca Shop",
    "wof:placetype":"venue"
},
  "geometry": {"coordinates":[0.0084650004,50.8726043701],"type":"Point"}
}