{
  "type": "Feature",
  "properties": {
    "addr:full":"8-10 Southgate Halifax West Yorkshire HX1 1DL",
    "addr:housenumber":"8-10",
    "addr:postcode":"hx1 1dl",
    "addr:street":"Southgate Halifax West",
    "iso:country":"GB",
    "sg:address":"8-10 Southgate",
    "sg:city":"Halifax",
    "sg:classifiers":[
        {
            "category":"Food & Beverages",
            "subcategory":"Bakery",
            "type":"Retail Goods"
        }
    ],
    "sg:phone":"+44 1422 344921",
    "sg:postcode":"HX1 1DL",
    "sg:province":"West Yorkshire",
    "sg:tags":[
        "baker"
    ],
    "wof:name":"Thurstons",
    "wof:placetype":"venue"
},
  "geometry": {"coordinates":[-1.8603589535,53.7225418091],"type":"Point"}
}