{
  "type": "Feature",
  "properties": {
    "iso:country":"GB",
    "sg:address":"Unit B, Batford Mill Ind Est, Lower Luton Rd",
    "sg:city":"Harpenden",
    "sg:classifiers":[
        {
            "category":"Professional",
            "subcategory":"Printing & Photocopies",
            "type":"Services"
        }
    ],
    "sg:phone":"+44 1582 766540",
    "sg:postcode":"AL5 5BZ",
    "sg:province":"Hertfordshire",
    "sg:tags":[
        "photocopier"
    ],
    "wof:name":"Toshiba Corporate Sales",
    "wof:placetype":"venue"
},
  "geometry": {"coordinates":[-0.3391,51.824028],"type":"Point"}
}