{
  "type": "Feature",
  "properties": {
    "iso:country":"GB",
    "sg:address":"94 Upminster Road South",
    "sg:city":"Rainham",
    "sg:classifiers":[
        {
            "category":"Real Estate",
            "subcategory":"Real Estate Agent",
            "type":"Services"
        }
    ],
    "sg:phone":"+44 1708 555574",
    "sg:postcode":"RM13 9BH",
    "sg:province":"Essex",
    "wof:name":"Edlen Property Services",
    "wof:placetype":"venue"
},
  "geometry": {"coordinates":[0.195328,51.519104],"type":"Point"}
}