{
  "type": "Feature",
  "properties": {
    "addr:full":"Exchange Street, St Annes Square, St Annes Square Manchester Greater Manchester M2 7HA",
    "addr:postcode":"m2 7ha",
    "addr:street":"Exchange Street St Annes Square St Annes Square",
    "iso:country":"GB",
    "sg:address":"Exchange Street, St Annes Square, St Annes Square",
    "sg:city":"Manchester",
    "sg:classifiers":[
        {
            "category":"Shopping",
            "subcategory":"Gifts & Souvenirs",
            "type":"Retail Goods"
        }
    ],
    "sg:phone":"+44 161 832 4361",
    "sg:postcode":"M2 7HA",
    "sg:province":"Greater Manchester",
    "sg:tags":[
        "shop"
    ],
    "wof:name":"The Disney Store Ltd",
    "wof:placetype":"venue"
},
  "geometry": {"coordinates":[-2.245184,53.482895],"type":"Point"}
}