{
  "type": "Feature",
  "properties": {
    "iso:country":"GB",
    "sg:address":"251 Birdsfoot Lane",
    "sg:city":"Luton",
    "sg:classifiers":[
        {
            "category":"Personal",
            "subcategory":"Beauty Salon",
            "type":"Services"
        }
    ],
    "sg:phone":"+44 1582 503753",
    "sg:postcode":"LU3 2HX",
    "sg:province":"Bedfordshire",
    "wof:name":"Altering Images",
    "wof:placetype":"venue"
},
  "geometry": {"coordinates":[-0.4343189895,51.909072876],"type":"Point"}
}