{
  "type": "Feature",
  "properties": {
    "addr:full":"21 Third Close West Molesey Greater London KT8 1PW",
    "addr:housenumber":"21",
    "addr:postcode":"kt8 1pw",
    "addr:street":"Third Close",
    "iso:country":"GB",
    "sg:address":"21 Third Close",
    "sg:city":"West Molesey",
    "sg:classifiers":[
        {
            "category":"Professional",
            "subcategory":"Accounting & Tax Preparation",
            "type":"Services"
        }
    ],
    "sg:phone":"+44 20 8979 6422",
    "sg:postcode":"KT8 1PW",
    "sg:province":"Greater London",
    "sg:tags":[
        "accountant",
        "activity"
    ],
    "wof:name":"Colin Bass",
    "wof:placetype":"venue"
},
  "geometry": {"coordinates":[-0.362474,51.402592],"type":"Point"}
}