{
  "type": "Feature",
  "properties": {
    "addr:full":"Raigmore Hospital, Birnie Chld Development Centre Inverness Highland IV2 3UJ",
    "addr:postcode":"iv2 3uj",
    "iso:country":"GB",
    "sg:address":"Raigmore Hospital, Birnie Chld Development Centre",
    "sg:city":"Inverness",
    "sg:classifiers":[
        {
            "category":"Organizations",
            "subcategory":"Non-profit Organization",
            "type":"Services"
        }
    ],
    "sg:phone":"+44 1463 711189",
    "sg:postcode":"IV2 3UJ",
    "sg:province":"Highland",
    "sg:tags":[
        "organisation",
        "voluntary",
        "charity"
    ],
    "wof:name":"Children in the Highland Information Point",
    "wof:placetype":"venue"
},
  "geometry": {"coordinates":[-4.195579,57.480446],"type":"Point"}
}