{
  "type": "Feature",
  "properties": {
    "addr:full":"53 Surbiton Road Kingston-upon-thames Greater London KT1 2HG",
    "addr:housenumber":"53",
    "addr:postcode":"kt1 2hg",
    "addr:street":"Surbiton Road",
    "iso:country":"GB",
    "sg:address":"53 Surbiton Road",
    "sg:city":"Kingston-upon-thames",
    "sg:classifiers":[
        {
            "category":"Shopping",
            "subcategory":"Pharmacy",
            "type":"Retail Goods"
        }
    ],
    "sg:phone":"+44 20 8546 0372",
    "sg:postcode":"KT1 2HG",
    "sg:province":"Greater London",
    "sg:tags":[
        "pharmacist",
        "dispensing",
        "chemist"
    ],
    "wof:name":"Eagercare Ltd.",
    "wof:placetype":"venue"
},
  "geometry": {"coordinates":[-0.30392,51.401455],"type":"Point"}
}