{
  "type": "Feature",
  "properties": {
    "addr:full":"165 Forton Road Gosport Hampshire PO12 3HB",
    "addr:housenumber":"165",
    "addr:postcode":"po12 3hb",
    "addr:street":"Forton Road",
    "iso:country":"GB",
    "sg:address":"165 Forton Road",
    "sg:city":"Gosport",
    "sg:classifiers":[
        {
            "category":"Personal",
            "subcategory":"Barber",
            "type":"Services"
        }
    ],
    "sg:phone":"+44 23 9250 3178",
    "sg:postcode":"PO12 3HB",
    "sg:province":"Hampshire",
    "sg:tags":[
        "men's",
        "hairdresser"
    ],
    "wof:name":"No 1 Barber Shop",
    "wof:placetype":"venue"
},
  "geometry": {"coordinates":[-1.1415499449,50.8007125854],"type":"Point"}
}