{
  "type": "Feature",
  "properties": {
    "addr:full":"Eastland, Maryculter Aberdeen Aberdeen City AB12 5FS",
    "addr:postcode":"ab12 5fs",
    "iso:country":"GB",
    "sg:address":"Eastland, Maryculter",
    "sg:city":"Aberdeen",
    "sg:classifiers":[
        {
            "category":"Building & Trades",
            "subcategory":"Landscaping Services",
            "type":"Services"
        }
    ],
    "sg:postcode":"AB12 5FS",
    "sg:province":"Aberdeen City",
    "sg:tags":[
        "landscape",
        "contractor"
    ],
    "wof:name":"Eastland Foresters",
    "wof:placetype":"venue"
},
  "geometry": {"coordinates":[-2.238559,57.085957],"type":"Point"}
}