{
  "type": "Feature",
  "properties": {
    "iso:country":"GB",
    "sg:address":"155 High Street",
    "sg:city":"Potters Bar",
    "sg:classifiers":[
        {
            "category":"Building & Trades",
            "subcategory":"Construction",
            "type":"Services"
        }
    ],
    "sg:phone":"+44 1707 656636",
    "sg:postcode":"EN6 5BB",
    "sg:province":"Greater London",
    "sg:tags":[
        "builder"
    ],
    "wof:name":"P French & Co. Ltd.",
    "wof:placetype":"venue"
},
  "geometry": {"coordinates":[-0.1749829948,51.697303772],"type":"Point"}
}