{
  "type": "Feature",
  "properties": {
    "iso:country":"GB",
    "sg:address":"884 Alum Rock Road, Ward End",
    "sg:city":"Birmingham",
    "sg:classifiers":[
        {
            "category":"Recreation",
            "subcategory":"Fishing",
            "type":"Entertainment"
        }
    ],
    "sg:phone":"+44 121 327 4193",
    "sg:postcode":"B8 2TY",
    "sg:province":"West Midlands",
    "sg:tags":[
        "angling"
    ],
    "wof:name":"J Chaplains",
    "wof:placetype":"venue"
},
  "geometry": {"coordinates":[-1.8264509439,52.4902763367],"type":"Point"}
}