{
  "type": "Feature",
  "properties": {
    "addr:full":"51 Connaught Avenue Frinton-on-sea Essex CO13 9PP",
    "addr:housenumber":"51",
    "addr:postcode":"co13 9pp",
    "addr:street":"Connaught Avenue",
    "iso:country":"GB",
    "sg:address":"51 Connaught Avenue",
    "sg:city":"Frinton-on-sea",
    "sg:classifiers":[
        {
            "category":"Food & Beverages",
            "subcategory":"Bakery",
            "type":"Retail Goods"
        }
    ],
    "sg:phone":"+44 1255 674591",
    "sg:postcode":"CO13 9PP",
    "sg:province":"Essex",
    "sg:tags":[
        "shop",
        "baker"
    ],
    "wof:name":"The Cake Kitchen",
    "wof:placetype":"venue"
},
  "geometry": {"coordinates":[1.2453409433,51.8313751221],"type":"Point"}
}