{
  "type": "Feature",
  "properties": {
    "addr:full":"8 Flushards Estate Lymington Hampshire SO41 3RX",
    "addr:housenumber":"8",
    "addr:postcode":"so41 3rx",
    "addr:street":"Flushards Estate",
    "iso:country":"GB",
    "sg:address":"8 Flushards Estate",
    "sg:city":"Lymington",
    "sg:classifiers":[
        {
            "category":"Retail",
            "subcategory":"Storage",
            "type":"Services"
        }
    ],
    "sg:phone":"+44 1590 676385",
    "sg:postcode":"SO41 3RX",
    "sg:province":"Hampshire",
    "sg:tags":[
        "household",
        "removal"
    ],
    "wof:name":"Man & Van",
    "wof:placetype":"venue"
},
  "geometry": {"coordinates":[-1.5352489948,50.7560195923],"type":"Point"}
}