{
  "type": "Feature",
  "properties": {
    "iso:country":"GB",
    "sg:address":"4 Moorfoot Road",
    "sg:city":"Worthing",
    "sg:classifiers":[
        {
            "category":"Retail",
            "subcategory":"Driving School",
            "type":"Services"
        }
    ],
    "sg:phone":"+44 1903 265737",
    "sg:postcode":"BN13 2EY",
    "sg:province":"West Sussex",
    "wof:name":"Nigel J Green",
    "wof:placetype":"venue"
},
  "geometry": {"coordinates":[-0.400811,50.838337],"type":"Point"}
}