{
  "type": "Feature",
  "properties": {
    "addr:full":"149 Central Road Worcester Park Surrey KT4 8DT",
    "addr:housenumber":"149",
    "addr:postcode":"kt4 8dt",
    "addr:street":"Central Road",
    "iso:country":"GB",
    "sg:address":"149 Central Road",
    "sg:city":"Worcester Park",
    "sg:classifiers":[
        {
            "category":"Manufacturing",
            "subcategory":"Metals",
            "type":"Manufacturing & Wholesale Goods"
        }
    ],
    "sg:postcode":"KT4 8DT",
    "sg:province":"Surrey",
    "sg:tags":[
        "merchant"
    ],
    "wof:name":"Lynch Trading Ltd",
    "wof:placetype":"venue"
},
  "geometry": {"coordinates":[-0.243299,51.379192],"type":"Point"}
}