{
  "type": "Feature",
  "properties": {
    "addr:full":"214 Main Rd, Hawkwell Hockley Essex SS5 4EG",
    "addr:housenumber":"214",
    "addr:postcode":"ss5 4eg",
    "addr:street":"Main Rd;Hockley",
    "iso:country":"GB",
    "sg:address":"214 Main Rd, Hawkwell",
    "sg:city":"Hockley",
    "sg:classifiers":[
        {
            "category":"Farming",
            "subcategory":"Fish & Marine Products",
            "type":"Manufacturing & Wholesale Goods"
        }
    ],
    "sg:postcode":"SS5 4EG",
    "sg:province":"Essex",
    "sg:tags":[
        "fishmonger"
    ],
    "wof:name":"Harris,T A J,",
    "wof:placetype":"venue"
},
  "geometry": {"coordinates":[0.665123,51.597527],"type":"Point"}
}