{
  "type": "Feature",
  "properties": {
    "iso:country":"GB",
    "sg:address":"10 Queen Street, Bottesford",
    "sg:city":"Nottingham",
    "sg:classifiers":[
        {
            "category":"Home & Garden",
            "subcategory":"Home Furnishings",
            "type":"Retail Goods"
        }
    ],
    "sg:postcode":"NG13 0AH",
    "sg:province":"Leicestershire",
    "sg:tags":[
        "blind",
        "curtain",
        "fitting"
    ],
    "wof:name":"Fabric Flair",
    "wof:placetype":"venue"
},
  "geometry": {"coordinates":[-0.802894,52.941757],"type":"Point"}
}