{
  "type": "Feature",
  "properties": {
    "addr:full":"20 Strawberry Close Tunbridge Wells East Sussex TN2 5PD",
    "addr:housenumber":"20",
    "addr:postcode":"tn2 5pd",
    "addr:street":"Strawberry Close",
    "iso:country":"GB",
    "sg:address":"20 Strawberry Close",
    "sg:city":"Tunbridge Wells",
    "sg:classifiers":[
        {
            "category":"Social Services",
            "type":"Services"
        }
    ],
    "sg:phone":"+44 1892 511396",
    "sg:postcode":"TN2 5PD",
    "sg:province":"East Sussex",
    "sg:tags":[
        "helplines"
    ],
    "wof:name":"Action Support for the Special Needs Child",
    "wof:placetype":"venue"
},
  "geometry": {"coordinates":[0.2456759959,51.1153068542],"type":"Point"}
}