{
  "type": "Feature",
  "properties": {
    "iso:country":"GB",
    "sg:address":"156 Waterside Road, Carmunnock",
    "sg:city":"Glasgow",
    "sg:classifiers":[
        {
            "category":"Home & Garden",
            "subcategory":"Building Materials",
            "type":"Retail Goods"
        },
        {
            "category":"Manufacturing",
            "subcategory":"Building Materials",
            "type":"Manufacturing & Wholesale Goods"
        }
    ],
    "sg:phone":"+44 141 644 1955",
    "sg:postcode":"G76 9AJ",
    "sg:province":"East Renfrewshire",
    "sg:tags":[
        "staircase",
        "system",
        "stair",
        "manufacturer"
    ],
    "wof:name":"Strathclyde Spirals",
    "wof:placetype":"venue"
},
  "geometry": {"coordinates":[-4.235488,55.787052],"type":"Point"}
}