{
  "type": "Feature",
  "properties": {
    "iso:country":"GB",
    "sg:address":"1 Camp Hill Road",
    "sg:city":"Nuneaton",
    "sg:classifiers":[
        {
            "category":"Shopping",
            "subcategory":"Used Merchandise",
            "type":"Retail Goods"
        }
    ],
    "sg:postcode":"CV10 0JP",
    "sg:province":"Leicestershire",
    "sg:tags":[
        "shop",
        "second-hand"
    ],
    "wof:name":"The Pharaoh's Tomb",
    "wof:placetype":"venue"
},
  "geometry": {"coordinates":[-1.517860055,52.537071228],"type":"Point"}
}