{
  "type": "Feature",
  "properties": {
    "iso:country":"GB",
    "sg:address":"156 Barkham Road",
    "sg:city":"Wokingham",
    "sg:classifiers":[
        {
            "category":"Recreation",
            "subcategory":"Dog Park",
            "type":"Entertainment"
        }
    ],
    "sg:postcode":"RG41 2RP",
    "sg:province":"Berkshire",
    "wof:name":"Mans Best Friend",
    "wof:placetype":"venue"
},
  "geometry": {"coordinates":[-0.854254,51.40556],"type":"Point"}
}