{
  "type": "Feature",
  "properties": {
    "iso:country":"GB",
    "sg:address":"Unit 3, Kirkland Avenue",
    "sg:city":"Mansfield",
    "sg:classifiers":[
        {
            "category":"Food & Beverages",
            "subcategory":"Meat & Fish",
            "type":"Retail Goods"
        }
    ],
    "sg:phone":"+44 1623 422971",
    "sg:postcode":"NG18 5QP",
    "sg:province":"Nottinghamshire",
    "sg:tags":[
        "butcher"
    ],
    "wof:name":"John L White Ltd.",
    "wof:placetype":"venue"
},
  "geometry": {"coordinates":[-1.214449,53.140549],"type":"Point"}
}