{
  "type": "Feature",
  "properties": {
    "iso:country":"GB",
    "sg:address":"124 St Vincent Street",
    "sg:city":"Glasgow",
    "sg:classifiers":[
        {
            "category":"Insurance",
            "subcategory":"Insurance Agent",
            "type":"Services"
        }
    ],
    "sg:postcode":"G2 5SR",
    "sg:province":"Glasgow City",
    "wof:name":"Commercial Union General Insurance",
    "wof:placetype":"venue"
},
  "geometry": {"coordinates":[-4.2572321892,55.8616905212],"type":"Point"}
}