{
  "type": "Feature",
  "properties": {
    "addr:full":"Damems Mill House, Damems Lane Keighley North Yorkshire BD22 7AR",
    "addr:postcode":"north;bd22 7ar",
    "addr:street":"Damems Lane",
    "iso:country":"GB",
    "sg:address":"Damems Mill House, Damems Lane",
    "sg:city":"Keighley",
    "sg:classifiers":[
        {
            "category":"Manufacturing",
            "subcategory":"Rubber & Plastics",
            "type":"Manufacturing & Wholesale Goods"
        }
    ],
    "sg:phone":"+44 1535 669881",
    "sg:postcode":"BD22 7AR",
    "sg:province":"North Yorkshire",
    "sg:tags":[
        "product"
    ],
    "wof:name":"Marjon Plastics Engineers",
    "wof:placetype":"venue"
},
  "geometry": {"coordinates":[-1.9240490198,53.8454360962],"type":"Point"}
}