{
  "type": "Feature",
  "properties": {
    "addr:full":"351 Clay Hill Road Basildon Essex SS16 4HA",
    "addr:housenumber":"351",
    "addr:postcode":"ss16 4ha",
    "addr:street":"Clay Hill Road",
    "iso:country":"GB",
    "sg:address":"351 Clay Hill Road",
    "sg:city":"Basildon",
    "sg:classifiers":[
        {
            "category":"Retail",
            "subcategory":"Veterinary Services",
            "type":"Services"
        }
    ],
    "sg:phone":"+44 1268 284281",
    "sg:postcode":"SS16 4HA",
    "sg:province":"Essex",
    "sg:tags":[
        "surgeon"
    ],
    "wof:name":"Clayhill Veterinary Centre",
    "wof:placetype":"venue"
},
  "geometry": {"coordinates":[0.479557991,51.565864563],"type":"Point"}
}