{
  "type": "Feature",
  "properties": {
    "addr:full":"Manor Farm, Hardington Mandeville Yeovil Dorset BA22 9PQ",
    "addr:postcode":"ba22 9pq",
    "addr:street":"Manor",
    "iso:country":"GB",
    "sg:address":"Manor Farm, Hardington Mandeville",
    "sg:city":"Yeovil",
    "sg:classifiers":[
        {
            "category":"Farming",
            "subcategory":"Farm",
            "type":"Manufacturing & Wholesale Goods"
        }
    ],
    "sg:phone":"+44 1935 862141",
    "sg:postcode":"BA22 9PQ",
    "sg:province":"Dorset",
    "sg:tags":[
        "mixed",
        "crop"
    ],
    "wof:name":"W E Turner & Son",
    "wof:placetype":"venue"
},
  "geometry": {"coordinates":[-2.698615,50.905167],"type":"Point"}
}