{
  "type": "Feature",
  "properties": {
    "iso:country":"GB",
    "sg:address":"58 Queen Alexandra Road",
    "sg:city":"Salisbury",
    "sg:classifiers":[
        {
            "category":"Building & Trades",
            "subcategory":"Cleaning & Sanitation",
            "type":"Services"
        }
    ],
    "sg:postcode":"SP2 9LA",
    "sg:province":"Wiltshire",
    "sg:tags":[
        "commercial"
    ],
    "wof:name":"Contract Cleaning Specialist",
    "wof:placetype":"venue"
},
  "geometry": {"coordinates":[-1.822196,51.079952],"type":"Point"}
}