{
  "type": "Feature",
  "properties": {
    "addr:full":"Beaufort House, Tenth Floor London Greater London EC3A 7EE",
    "addr:postcode":"ec3a 7ee",
    "iso:country":"GB",
    "sg:address":"Beaufort House, Tenth Floor",
    "sg:city":"London",
    "sg:classifiers":[
        {
            "category":"Travel",
            "subcategory":"Travel Agent",
            "type":"Entertainment"
        }
    ],
    "sg:postcode":"EC3A 7EE",
    "sg:province":"Greater London",
    "wof:name":"Foreign Window Limited",
    "wof:placetype":"venue"
},
  "geometry": {"coordinates":[-0.0788000003,51.5153503418],"type":"Point"}
}