{
  "type": "Feature",
  "properties": {
    "addr:full":"Gallows Hill Lane Abbots Langley Hertfordshire WD5 0DD",
    "addr:postcode":"wd5 0dd",
    "addr:street":"Gallows Hill Lane",
    "iso:country":"GB",
    "sg:address":"Gallows Hill Lane",
    "sg:city":"Abbots Langley",
    "sg:classifiers":[
        {
            "category":"Organizations",
            "subcategory":"Membership Organization",
            "type":"Services"
        }
    ],
    "sg:phone":"+44 1923 260462",
    "sg:postcode":"WD5 0DD",
    "sg:province":"Hertfordshire",
    "sg:tags":[
        "club"
    ],
    "wof:name":"Abbots Langley Parish Council",
    "wof:placetype":"venue"
},
  "geometry": {"coordinates":[-0.4211240113,51.7031745911],"type":"Point"}
}