{
  "type": "Feature",
  "properties": {
    "addr:full":"86 Redhill Road Nottingham Nottinghamshire NG5 8HB",
    "addr:housenumber":"86",
    "addr:postcode":"ng5 8hb",
    "addr:street":"Redhill Road",
    "iso:country":"GB",
    "sg:address":"86 Redhill Road",
    "sg:city":"Nottingham",
    "sg:classifiers":[
        {
            "category":"Building & Trades",
            "subcategory":"Construction",
            "type":"Services"
        }
    ],
    "sg:postcode":"NG5 8HB",
    "sg:province":"Nottinghamshire",
    "sg:tags":[
        "builder"
    ],
    "wof:name":"M & M Goodson",
    "wof:placetype":"venue"
},
  "geometry": {"coordinates":[-1.1304379702,53.0104675293],"type":"Point"}
}