{
  "type": "Feature",
  "properties": {
    "addr:full":"5 Mallard Close, Earls Barton Northampton Northamptonshire NN6 0LS",
    "addr:housenumber":"5;barton",
    "addr:postcode":"nn6 0ls",
    "addr:street":"Mallard Close Earls",
    "iso:country":"GB",
    "sg:address":"5 Mallard Close, Earls Barton",
    "sg:city":"Northampton",
    "sg:classifiers":[
        {
            "category":"Professional",
            "subcategory":"Printing & Photocopies",
            "type":"Services"
        }
    ],
    "sg:postcode":"NN6 0LS",
    "sg:province":"Northamptonshire",
    "sg:tags":[
        "computer",
        "tag",
        "label"
    ],
    "wof:name":"Steepleprint Ltd.",
    "wof:placetype":"venue"
},
  "geometry": {"coordinates":[-0.7471889853,52.2711181641],"type":"Point"}
}