{
  "type": "Feature",
  "properties": {
    "addr:full":"The Stables, Knowles, Coly Road Colyton Devon EX24 6PU",
    "addr:postcode":"ex24 6pu",
    "addr:street":"Coly Road",
    "iso:country":"GB",
    "sg:address":"The Stables, Knowles, Coly Road",
    "sg:city":"Colyton",
    "sg:classifiers":[
        {
            "category":"Building & Trades",
            "subcategory":"Equipment Rental",
            "type":"Services"
        }
    ],
    "sg:phone":"+44 1297 553729",
    "sg:postcode":"EX24 6PU",
    "sg:province":"Devon",
    "sg:tags":[
        "plant",
        "machinery"
    ],
    "wof:name":"Maclean (South West) Ltd.",
    "wof:placetype":"venue"
},
  "geometry": {"coordinates":[-3.0702440739,50.7403373718],"type":"Point"}
}