{
  "type": "Feature",
  "properties": {
    "addr:full":"Pottery Rd, Off Coach Rd Whitehaven Cumbria CA28 9BZ",
    "addr:postcode":"ca28 9bz",
    "addr:street":"Pottery Rd Off Coach Rd",
    "iso:country":"GB",
    "sg:address":"Pottery Rd, Off Coach Rd",
    "sg:city":"Whitehaven",
    "sg:classifiers":[
        {
            "category":"Autos & Motor Vehicles",
            "subcategory":"Auto Supplies",
            "type":"Retail Goods"
        }
    ],
    "sg:phone":"+44 1946 694794",
    "sg:postcode":"CA28 9BZ",
    "sg:province":"Cumbria",
    "sg:tags":[
        "tyre"
    ],
    "wof:name":"Camskill Performance",
    "wof:placetype":"venue"
},
  "geometry": {"coordinates":[-3.5883889198,54.5406532288],"type":"Point"}
}