{
  "type": "Feature",
  "properties": {
    "addr:full":"181 Oatlands Drive Weybridge Surrey KT13 9DJ",
    "addr:housenumber":"181",
    "addr:postcode":"kt13 9dj",
    "addr:street":"Oatlands Drive",
    "iso:country":"GB",
    "sg:address":"181 Oatlands Drive",
    "sg:city":"Weybridge",
    "sg:classifiers":[
        {
            "category":"Autos & Motor Vehicles",
            "subcategory":"Fuel & Gas Station",
            "type":"Retail Goods"
        }
    ],
    "sg:phone":"+44 1932 839920",
    "sg:postcode":"KT13 9DJ",
    "sg:province":"Surrey",
    "sg:tags":[
        "petrol",
        "filling"
    ],
    "wof:name":"Total Convenience Stores",
    "wof:placetype":"venue"
},
  "geometry": {"coordinates":[-0.4507730007,51.3713684082],"type":"Point"}
}