{
  "type": "Feature",
  "properties": {
    "addr:full":"Europa House, Bower Hill Industrial Estate Epping Essex CM16 7BN",
    "addr:postcode":"cm16 7bn",
    "addr:street":"Bower Hill Industrial Estate",
    "iso:country":"GB",
    "sg:address":"Europa House, Bower Hill Industrial Estate",
    "sg:city":"Epping",
    "sg:classifiers":[
        {
            "category":"Home & Garden",
            "subcategory":"Home Furnishings",
            "type":"Retail Goods"
        },
        {
            "category":"Professional",
            "subcategory":"Business Services",
            "type":"Services"
        },
        {
            "category":"Building & Trades",
            "subcategory":"Landfill",
            "type":"Services"
        }
    ],
    "sg:phone":"+44 1992 560161",
    "sg:postcode":"CM16 7BN",
    "sg:province":"Essex",
    "sg:tags":[
        "shop",
        "blind",
        "cleaning",
        "awning",
        "canopy",
        "blinds"
    ],
    "wof:name":"Duncan Whitehouse Ltd.",
    "wof:placetype":"venue"
},
  "geometry": {"coordinates":[0.1151899993,51.6929512024],"type":"Point"}
}