{
  "type": "Feature",
  "properties": {
    "addr:full":"The Garage, Ditton Priors Bridgnorth Shropshire WV16 6SQ",
    "addr:postcode":"wv16 6sq",
    "iso:country":"GB",
    "sg:address":"The Garage, Ditton Priors",
    "sg:city":"Bridgnorth",
    "sg:classifiers":[
        {
            "category":"Retail",
            "subcategory":"Auto Repair",
            "type":"Services"
        }
    ],
    "sg:phone":"+44 1746 712238",
    "sg:postcode":"WV16 6SQ",
    "sg:province":"Shropshire",
    "sg:tags":[
        "modification",
        "garage"
    ],
    "wof:name":"Parker Motors",
    "wof:placetype":"venue"
},
  "geometry": {"coordinates":[-2.5784900188,52.4997062683],"type":"Point"}
}