{
  "type": "Feature",
  "properties": {
    "iso:country":"GB",
    "sg:address":"43 Melrose Gardens, Arborfield Cross",
    "sg:city":"Reading",
    "sg:classifiers":[
        {
            "category":"Banks & Credit Unions",
            "subcategory":"Financial Services",
            "type":"Services"
        }
    ],
    "sg:postcode":"RG2 9PY",
    "sg:province":"Berkshire",
    "sg:tags":[
        "agent",
        "tied"
    ],
    "wof:name":"R Martin & Co",
    "wof:placetype":"venue"
},
  "geometry": {"coordinates":[-0.9075260162,51.3948860168],"type":"Point"}
}