{
  "type": "Feature",
  "properties": {
    "iso:country":"GB",
    "sg:address":"26 Holme Chase",
    "sg:city":"Weybridge",
    "sg:classifiers":[
        {
            "category":"Personal",
            "type":"Services"
        },
        {
            "category":"Professional",
            "subcategory":"Art Services",
            "type":"Services"
        }
    ],
    "sg:postcode":"KT13 0BZ",
    "sg:province":"Surrey",
    "sg:tags":[
        "photographer",
        "wedding"
    ],
    "wof:name":"Aetel Productions",
    "wof:placetype":"venue"
},
  "geometry": {"coordinates":[-0.447859,51.362762],"type":"Point"}
}