{
  "type": "Feature",
  "properties": {
    "addr:full":"51 Old Elvet Durham Durham DH1 3JF",
    "addr:housenumber":"51",
    "addr:postcode":"dh1 3jf",
    "addr:street":"Old Elvet",
    "iso:country":"GB",
    "sg:address":"51 Old Elvet",
    "sg:city":"Durham",
    "sg:classifiers":[
        {
            "category":"Professional",
            "subcategory":"Lawyer & Legal Services",
            "type":"Services"
        }
    ],
    "sg:phone":"+44 191 374 3444",
    "sg:postcode":"DH1 3JF",
    "sg:province":"Durham",
    "sg:tags":[
        "advice",
        "counselling"
    ],
    "wof:name":"Nightline",
    "wof:placetype":"venue"
},
  "geometry": {"coordinates":[-1.570269,54.775455],"type":"Point"}
}