{
  "type": "Feature",
  "properties": {
    "addr:full":"29 George Street Paisley Renfrewshire PA1 2JY",
    "addr:housenumber":"29",
    "addr:postcode":"pa1 2jy",
    "addr:street":"George Street",
    "iso:country":"GB",
    "sg:address":"29 George Street",
    "sg:city":"Paisley",
    "sg:classifiers":[
        {
            "category":"Fast Food",
            "type":"Food & Drink"
        }
    ],
    "sg:phone":"+44 141 561 7087",
    "sg:postcode":"PA1 2JY",
    "sg:province":"Renfrewshire",
    "sg:tags":[
        "away",
        "take"
    ],
    "wof:name":"Tasty Bites",
    "wof:placetype":"venue"
},
  "geometry": {"coordinates":[-4.43004179,55.8423233032],"type":"Point"}
}