{
  "type": "Feature",
  "properties": {
    "addr:full":"Resington House 82 Great Eastren Street London Greater London EC2A 3JF",
    "addr:housenumber":"82",
    "addr:postcode":"ec2a 3jf",
    "addr:street":"Great Eastren Street",
    "iso:country":"GB",
    "sg:address":"Resington House 82 Great Eastren Street",
    "sg:city":"London",
    "sg:classifiers":[
        {
            "category":"Professional",
            "subcategory":"Lawyer & Legal Services",
            "type":"Services"
        }
    ],
    "sg:phone":"+44 20 8877 3844",
    "sg:postcode":"EC2A 3JF",
    "sg:province":"Greater London",
    "sg:tags":[
        "solicitor"
    ],
    "wof:name":"Figueiredo & Co",
    "wof:placetype":"venue"
},
  "geometry": {"coordinates":[-0.0831149966,51.52602005],"type":"Point"}
}