{
  "type": "Feature",
  "properties": {
    "iso:country":"GB",
    "sg:address":"Freeport",
    "sg:city":"Prestwick",
    "sg:classifiers":[
        {
            "category":"Professional",
            "subcategory":"Management & Consulting",
            "type":"Services"
        }
    ],
    "sg:phone":"+44 1292 678920",
    "sg:postcode":"KA9 2TR",
    "sg:province":"South Ayrshire",
    "sg:tags":[
        "marketing",
        "consultant"
    ],
    "wof:name":"Ayrshire Marketing Executive",
    "wof:placetype":"venue"
},
  "geometry": {"coordinates":[-4.599251,55.516792],"type":"Point"}
}