{
  "type": "Feature",
  "properties": {
    "iso:country":"GB",
    "sg:address":"43 Alder Close, Mansfield Woodhouse",
    "sg:city":"Mansfield",
    "sg:classifiers":[
        {
            "category":"Building & Trades",
            "subcategory":"Construction",
            "type":"Services"
        }
    ],
    "sg:phone":"+44 1623 424137",
    "sg:postcode":"NG19 0NQ",
    "sg:province":"Derbyshire",
    "sg:tags":[
        "decorator",
        "painter"
    ],
    "wof:name":"Alan Musson",
    "wof:placetype":"venue"
},
  "geometry": {"coordinates":[-1.1784720421,53.156162262],"type":"Point"}
}