{
  "type": "Feature",
  "properties": {
    "addr:full":"4 Mill Road, Mayland Chelmsford Essex CM3 6EQ",
    "addr:housenumber":"4",
    "addr:postcode":"cm3 6eq",
    "addr:street":"Mill Road",
    "iso:country":"GB",
    "sg:address":"4 Mill Road, Mayland",
    "sg:city":"Chelmsford",
    "sg:classifiers":[
        {
            "category":"Building & Trades",
            "subcategory":"Landscaping Services",
            "type":"Services"
        },
        {
            "category":"Retail",
            "subcategory":"Storage",
            "type":"Services"
        }
    ],
    "sg:phone":"+44 1621 740460",
    "sg:postcode":"CM3 6EQ",
    "sg:province":"Essex",
    "sg:tags":[
        "consultant",
        "safe",
        "horticultural",
        "vault"
    ],
    "wof:name":"R K Terry Security",
    "wof:placetype":"venue"
},
  "geometry": {"coordinates":[0.774359,51.681877],"type":"Point"}
}