{
  "type": "Feature",
  "properties": {
    "addr:full":"The Sidings, Holdsworth Road, Holmfield Halifax West Yorkshire HX3 6SN",
    "addr:postcode":"hx3 6sn",
    "addr:street":"The;Holdsworth Road",
    "iso:country":"GB",
    "sg:address":"The Sidings, Holdsworth Road, Holmfield",
    "sg:city":"Halifax",
    "sg:classifiers":[
        {
            "category":"Freight",
            "type":"Transportation"
        }
    ],
    "sg:postcode":"HX3 6SN",
    "sg:province":"West Yorkshire",
    "sg:tags":[
        "haulage",
        "road"
    ],
    "wof:name":"W Greenwood & Sons",
    "wof:placetype":"venue"
},
  "geometry": {"coordinates":[-1.8737959862,53.7530136108],"type":"Point"}
}