{
  "type": "Feature",
  "properties": {
    "iso:country":"GB",
    "sg:address":"Aulby Farm, Laithes",
    "sg:city":"Penrith",
    "sg:classifiers":[
        {
            "category":"Farming",
            "subcategory":"Farm",
            "type":"Manufacturing & Wholesale Goods"
        }
    ],
    "sg:phone":"+44 17684 84260",
    "sg:postcode":"CA11 0AN",
    "sg:province":"Cumbria",
    "sg:tags":[
        "mixed",
        "crop"
    ],
    "wof:name":"H B Mattocks & Sons",
    "wof:placetype":"venue"
},
  "geometry": {"coordinates":[-2.8308200836,54.6890602112],"type":"Point"}
}