{
  "type": "Feature",
  "properties": {
    "addr:full":"Unit 1a Westgate, 1 Avia Park Feltham Greater London TW14 8RS",
    "addr:housenumber":"unit 1a;1",
    "addr:postcode":"tw14 8rs",
    "addr:street":"Westgate;Avia Park",
    "iso:country":"GB",
    "sg:address":"Unit 1a Westgate, 1 Avia Park",
    "sg:city":"Feltham",
    "sg:classifiers":[
        {
            "category":"Freight",
            "type":"Transportation"
        }
    ],
    "sg:phone":"+44 1784 251252",
    "sg:postcode":"TW14 8RS",
    "sg:province":"Greater London",
    "sg:tags":[
        "overseas",
        "shipping",
        "removal"
    ],
    "wof:name":"Tooth Transport Ltd.",
    "wof:placetype":"venue"
},
  "geometry": {"coordinates":[-0.4530600011,51.4463806152],"type":"Point"}
}