{
  "type": "Feature",
  "properties": {
    "addr:full":"7 Cherry Wood, Oldland Common Bristol Gloucestershire BS30 6PQ",
    "addr:housenumber":"7",
    "addr:postcode":"bs30 6pq",
    "addr:street":"Cherry Wood",
    "iso:country":"GB",
    "sg:address":"7 Cherry Wood, Oldland Common",
    "sg:city":"Bristol",
    "sg:classifiers":[
        {
            "category":"Professional",
            "subcategory":"Accounting & Tax Preparation",
            "type":"Services"
        }
    ],
    "sg:postcode":"BS30 6PQ",
    "sg:province":"Gloucestershire",
    "sg:tags":[
        "accountant"
    ],
    "wof:name":"N D Lintern",
    "wof:placetype":"venue"
},
  "geometry": {"coordinates":[-2.476514101,51.4370613098],"type":"Point"}
}