{
  "type": "Feature",
  "properties": {
    "iso:country":"GB",
    "sg:address":"32 Dudden Hill Lane, Willesden",
    "sg:city":"London",
    "sg:classifiers":[
        {
            "category":"Freight",
            "type":"Transportation"
        }
    ],
    "sg:phone":"+44 20 8459 6586",
    "sg:postcode":"NW10 2ER",
    "sg:province":"Greater London",
    "sg:tags":[
        "haulage",
        "road"
    ],
    "wof:name":"McGovern Brothers (Haulage) Ltd.",
    "wof:placetype":"venue"
},
  "geometry": {"coordinates":[-0.239792,51.549854],"type":"Point"}
}