{
  "type": "Feature",
  "properties": {
    "addr:full":"61 High Street Bembridge Isle of Wight PO35 5SF",
    "addr:housenumber":"61",
    "addr:postcode":"po35 5sf",
    "addr:street":"High Street",
    "iso:country":"GB",
    "sg:address":"61 High Street",
    "sg:city":"Bembridge",
    "sg:classifiers":[
        {
            "category":"Bars & Pubs",
            "type":"Food & Drink"
        }
    ],
    "sg:phone":"+44 1983 872616",
    "sg:postcode":"PO35 5SF",
    "sg:province":"Isle of Wight",
    "sg:tags":[
        "pubs",
        "house",
        "inn",
        "public",
        "activity"
    ],
    "wof:name":"Ye Olde Village Inn",
    "wof:placetype":"venue"
},
  "geometry": {"coordinates":[-1.0893189907,50.6901931763],"type":"Point"}
}