{
  "type": "Feature",
  "properties": {
    "addr:full":"7 Summerfield Rd, West Park Wolverhampton West Midlands WV1 4PR",
    "addr:housenumber":"7",
    "addr:postcode":"wv1 4pr",
    "addr:street":"Summerfield Rd",
    "iso:country":"GB",
    "sg:address":"7 Summerfield Rd, West Park",
    "sg:city":"Wolverhampton",
    "sg:classifiers":[
        {
            "category":"Shopping",
            "subcategory":"Pharmacy",
            "type":"Retail Goods"
        }
    ],
    "sg:phone":"+44 1902 772091",
    "sg:postcode":"WV1 4PR",
    "sg:province":"West Midlands",
    "sg:tags":[
        "medicine",
        "therapy"
    ],
    "wof:name":"Beechwood House Medical Centre",
    "wof:placetype":"venue"
},
  "geometry": {"coordinates":[-2.139373064,52.5866584778],"type":"Point"}
}