{
  "type": "Feature",
  "properties": {
    "iso:country":"GB",
    "sg:address":"Manor Way, Bank St",
    "sg:city":"Chepstow",
    "sg:classifiers":[
        {
            "category":"Professional",
            "subcategory":"Employment Agencies",
            "type":"Services"
        }
    ],
    "sg:phone":"+44 1291 622609",
    "sg:postcode":"NP6 5HZ",
    "sg:province":"Gloucestershire",
    "sg:tags":[
        "career",
        "guidance"
    ],
    "wof:name":"Gwent Careers",
    "wof:placetype":"venue"
},
  "geometry": {"coordinates":[-2.67609,51.641411],"type":"Point"}
}