{
  "type": "Feature",
  "properties": {
    "iso:country":"GB",
    "sg:address":"39 Whitcombe Road",
    "sg:city":"Newport",
    "sg:classifiers":[
        {
            "category":"Organizations",
            "subcategory":"Non-profit Organization",
            "type":"Services"
        }
    ],
    "sg:phone":"+44 1983 523354",
    "sg:postcode":"PO30 1YS",
    "sg:province":"Isle of Wight",
    "sg:tags":[
        "charitable",
        "organisation",
        "voluntary",
        "charity"
    ],
    "wof:name":"Carisbrooke Priory Trust",
    "wof:placetype":"venue"
},
  "geometry": {"coordinates":[-1.308224,50.685871],"type":"Point"}
}