{
  "type": "Feature",
  "properties": {
    "iso:country":"GB",
    "sg:address":"Head House, 1-3 Dogs Head Street",
    "sg:city":"Ipswich",
    "sg:classifiers":[
        {
            "category":"Professional",
            "subcategory":"Lawyer & Legal Services",
            "type":"Services"
        }
    ],
    "sg:phone":"+44 1473 231200",
    "sg:postcode":"IP4 1AE",
    "sg:province":"Suffolk",
    "sg:tags":[
        "solicitor"
    ],
    "wof:name":"David Barnes",
    "wof:placetype":"venue"
},
  "geometry": {"coordinates":[1.154327035,52.0559806824],"type":"Point"}
}