{
  "type": "Feature",
  "properties": {
    "addr:full":"104 Dartmouth Park Hill Archway Greater London N19 5HU",
    "addr:housenumber":"104",
    "addr:postcode":"n19 5hu",
    "addr:street":"Dartmouth Park;Archway",
    "iso:country":"GB",
    "sg:address":"104 Dartmouth Park Hill",
    "sg:city":"Archway",
    "sg:classifiers":[
        {
            "category":"Health Services",
            "subcategory":"Health Practitioner",
            "type":"Services"
        }
    ],
    "sg:phone":"+44 20 7281 0707",
    "sg:postcode":"N19 5HU",
    "sg:province":"Greater London",
    "sg:tags":[
        "psychotherapist"
    ],
    "wof:name":"Gabriel Programme The",
    "wof:placetype":"venue"
},
  "geometry": {"coordinates":[-0.140555,51.563793],"type":"Point"}
}