{
  "type": "Feature",
  "properties": {
    "addr:full":"43 Copnor Rd Portsmouth Hampshire PO3 5AB",
    "addr:housenumber":"43",
    "addr:postcode":"hampshire po3 5ab",
    "addr:street":"Copnor Rd",
    "iso:country":"GB",
    "sg:address":"43 Copnor Rd",
    "sg:city":"Portsmouth",
    "sg:classifiers":[
        {
            "category":"Building & Trades",
            "subcategory":"Construction",
            "type":"Services"
        }
    ],
    "sg:phone":"+44 23 9264 3434",
    "sg:postcode":"PO3 5AB",
    "sg:province":"Hampshire",
    "sg:tags":[
        "builder"
    ],
    "wof:name":"A & K Specialist Building Services",
    "wof:placetype":"venue"
},
  "geometry": {"coordinates":[-1.06416,50.810276],"type":"Point"}
}