{
  "type": "Feature",
  "properties": {
    "addr:full":"7 Windermere Avenue Morecambe Lancashire LA4 5TT",
    "addr:housenumber":"7",
    "addr:postcode":"la4 5tt",
    "addr:street":"Windermere Avenue",
    "iso:country":"GB",
    "sg:address":"7 Windermere Avenue",
    "sg:city":"Morecambe",
    "sg:classifiers":[
        {
            "category":"Food & Beverages",
            "subcategory":"Meat & Fish",
            "type":"Retail Goods"
        },
        {
            "category":"Food & Beverages",
            "subcategory":"Groceries & Convenience Stores",
            "type":"Retail Goods"
        }
    ],
    "sg:postcode":"LA4 5TT",
    "sg:province":"Lancashire",
    "sg:tags":[
        "shop",
        "chip"
    ],
    "wof:name":"TROUT BECK FISHERIES",
    "wof:placetype":"venue"
},
  "geometry": {"coordinates":[-2.84313,54.064903],"type":"Point"}
}