{
  "type": "Feature",
  "properties": {
    "iso:country":"GB",
    "sg:address":"22 Skardu Road",
    "sg:city":"London",
    "sg:classifiers":[
        {
            "category":"Banks & Credit Unions",
            "subcategory":"Financial Services",
            "type":"Services"
        }
    ],
    "sg:phone":"+44 20 8450 0988",
    "sg:postcode":"NW2 3ER",
    "sg:province":"Greater London",
    "sg:tags":[
        "consultant"
    ],
    "sg:website":"http://www.porterbrown.co.uk",
    "wof:name":"Porter Brown & Co Financial Services Ltd",
    "wof:placetype":"venue"
},
  "geometry": {"coordinates":[-0.210199,51.554619],"type":"Point"}
}