{
  "type": "Feature",
  "properties": {
    "iso:country":"GB",
    "sg:address":"Dartmouth Road",
    "sg:city":"London",
    "sg:classifiers":[
        {
            "category":"Education",
            "subcategory":"School",
            "type":"Public Place"
        }
    ],
    "sg:phone":"+44 20 8699 6731",
    "sg:postcode":"SE26 4RD",
    "sg:province":"Greater London",
    "sg:tags":[
        "local",
        "authority"
    ],
    "wof:name":"Sydenham School",
    "wof:placetype":"venue"
},
  "geometry": {"coordinates":[-0.056454,51.435181],"type":"Point"}
}