{
  "type": "Feature",
  "properties": {
    "addr:full":"40 Palace St Canterbury Kent CT1 2DZ",
    "addr:housenumber":"40",
    "addr:postcode":"ct1 2dz",
    "addr:street":"Palace St",
    "iso:country":"GB",
    "sg:address":"40 Palace St",
    "sg:city":"Canterbury",
    "sg:classifiers":[
        {
            "category":"Food & Beverages",
            "subcategory":"Bakery",
            "type":"Retail Goods"
        }
    ],
    "sg:postcode":"CT1 2DZ",
    "sg:province":"Kent",
    "sg:tags":[
        "baker"
    ],
    "wof:name":"Mogridge,Tony,",
    "wof:placetype":"venue"
},
  "geometry": {"coordinates":[1.0812269449,51.2808609009],"type":"Point"}
}