{
  "type": "Feature",
  "properties": {
    "addr:full":"34 Market Place Melton Mowbray Leicestershire LE13 1XD",
    "addr:housenumber":"34",
    "addr:postcode":"le13 1xd",
    "addr:street":"Market Place",
    "iso:country":"GB",
    "sg:address":"34 Market Place",
    "sg:city":"Melton Mowbray",
    "sg:classifiers":[
        {
            "category":"Shopping",
            "subcategory":"Department Store",
            "type":"Retail Goods"
        },
        {
            "category":"Shopping",
            "subcategory":"Music",
            "type":"Retail Goods"
        }
    ],
    "sg:phone":"+44 1664 565025",
    "sg:postcode":"LE13 1XD",
    "sg:province":"Leicestershire",
    "sg:tags":[
        "dvd",
        "record",
        "tape",
        "vinyl",
        "cd"
    ],
    "wof:name":"Pendulum Records",
    "wof:placetype":"venue"
},
  "geometry": {"coordinates":[-0.8858510256,52.764591217],"type":"Point"}
}