{
  "type": "Feature",
  "properties": {
    "addr:full":"Carlinghurst Road Blackburn Lancashire BB2 1TN",
    "addr:postcode":"bb2 1tn",
    "addr:street":"Carlinghurst Road",
    "iso:country":"GB",
    "sg:address":"Carlinghurst Road",
    "sg:city":"Blackburn",
    "sg:classifiers":[
        {
            "category":"Wholesale",
            "subcategory":"Machinery & Supplies",
            "type":"Manufacturing & Wholesale Goods"
        }
    ],
    "sg:phone":"+44 1254 679944",
    "sg:postcode":"BB2 1TN",
    "sg:province":"Lancashire",
    "sg:tags":[
        "industrial",
        "commercial"
    ],
    "wof:name":"Phoenix Dryers & Engineering (Blackburn) Ltd.",
    "wof:placetype":"venue"
},
  "geometry": {"coordinates":[-2.491784,53.746105],"type":"Point"}
}