{
  "type": "Feature",
  "properties": {
    "addr:full":"Wedge Cottage, Shawfield Park Bromley Kent BR1 2NQ",
    "addr:postcode":"br1 2nq",
    "addr:street":"Shawfield Park",
    "iso:country":"GB",
    "sg:address":"Wedge Cottage, Shawfield Park",
    "sg:city":"Bromley",
    "sg:classifiers":[
        {
            "category":"Organizations",
            "subcategory":"Non-profit Organization",
            "type":"Services"
        }
    ],
    "sg:phone":"+44 20 8460 3266",
    "sg:postcode":"BR1 2NQ",
    "sg:province":"Kent",
    "sg:tags":[
        "organisation",
        "voluntary",
        "charity"
    ],
    "wof:name":"Cancer Research Campaign",
    "wof:placetype":"venue"
},
  "geometry": {"coordinates":[0.014928,51.4057006836],"type":"Point"}
}