{
  "type": "Feature",
  "properties": {
    "addr:full":"340 Seaside Eastbourne East Sussex BN22 7RJ",
    "addr:housenumber":"340",
    "addr:postcode":"bn22 7rj",
    "addr:street":"Seaside",
    "iso:country":"GB",
    "sg:address":"340 Seaside",
    "sg:city":"Eastbourne",
    "sg:classifiers":[
        {
            "category":"Building & Trades",
            "subcategory":"Construction",
            "type":"Services"
        }
    ],
    "sg:phone":"+44 1323 639455",
    "sg:postcode":"BN22 7RJ",
    "sg:province":"East Sussex",
    "sg:tags":[
        "heating",
        "contractor"
    ],
    "wof:name":"Roselands Heating Ltd.",
    "wof:placetype":"venue"
},
  "geometry": {"coordinates":[0.300931,50.780727],"type":"Point"}
}