{
  "type": "Feature",
  "properties": {
    "iso:country":"GB",
    "sg:address":"340 Seaside",
    "sg:city":"Eastbourne",
    "sg:classifiers":[
        {
            "category":"Building & Trades",
            "subcategory":"Construction",
            "type":"Services"
        }
    ],
    "sg:phone":"+44 1323 639455",
    "sg:postcode":"BN22 7RJ",
    "sg:province":"East Sussex",
    "sg:tags":[
        "heating",
        "contractor"
    ],
    "wof:name":"Roselands Heating Ltd.",
    "wof:placetype":"venue"
},
  "geometry": {"coordinates":[0.300931,50.780727],"type":"Point"}
}