{
  "type": "Feature",
  "properties": {
    "addr:full":"Harbour Office, The Harbour Saundersfoot Pembrokeshire SA69 9HE",
    "addr:postcode":"sa69 9he",
    "addr:street":"The",
    "iso:country":"GB",
    "sg:address":"Harbour Office, The Harbour",
    "sg:city":"Saundersfoot",
    "sg:classifiers":[
        {
            "category":"Harbor",
            "type":"Transportation"
        }
    ],
    "sg:phone":"+44 1834 812094",
    "sg:postcode":"SA69 9HE",
    "sg:province":"Pembrokeshire",
    "sg:tags":[
        "dock",
        "ports",
        "harbour"
    ],
    "wof:name":"Saundersfoot Harbour Commissioners",
    "wof:placetype":"venue"
},
  "geometry": {"coordinates":[-4.6995558739,51.7102050781],"type":"Point"}
}