{
  "type": "Feature",
  "properties": {
    "iso:country":"GB",
    "sg:address":"Wellington, Swaffham Road",
    "sg:city":"Dereham",
    "sg:classifiers":[
        {
            "category":"Education",
            "subcategory":"Special Training",
            "type":"Public Place"
        }
    ],
    "sg:postcode":"NR19 2AZ",
    "sg:province":"Norfolk",
    "sg:tags":[
        "product",
        "centre"
    ],
    "wof:name":"Thilmcraft",
    "wof:placetype":"venue"
},
  "geometry": {"coordinates":[0.9416400194,52.6823692322],"type":"Point"}
}