{
  "type": "Feature",
  "properties": {
    "addr:full":"8 Abbey Wood Road, Kings Hill West Malling Kent ME19 6YT",
    "addr:housenumber":"8",
    "addr:postcode":"me19 6yt",
    "addr:street":"Abbey Wood Road",
    "iso:country":"GB",
    "sg:address":"8 Abbey Wood Road, Kings Hill",
    "sg:city":"West Malling",
    "sg:classifiers":[
        {
            "category":"Professional",
            "subcategory":"Testing Lab",
            "type":"Services"
        }
    ],
    "sg:phone":"+44 1732 220001",
    "sg:postcode":"ME19 6YT",
    "sg:province":"Kent",
    "sg:tags":[
        "inspection",
        "calibration"
    ],
    "wof:name":"Kent Scientific Services",
    "wof:placetype":"venue"
},
  "geometry": {"coordinates":[0.41294,51.293709],"type":"Point"}
}