{
  "type": "Feature",
  "properties": {
    "iso:country":"GB",
    "sg:address":"Itchen Down Farm, Itchen Down, Itchen Abbas",
    "sg:city":"Winchester",
    "sg:classifiers":[
        {
            "category":"Farming",
            "subcategory":"Livestock Farm",
            "type":"Manufacturing & Wholesale Goods"
        }
    ],
    "sg:phone":"+44 1962 779388",
    "sg:postcode":"SO21 1BS",
    "sg:province":"Hampshire",
    "sg:tags":[
        "others"
    ],
    "wof:name":"Richard R Burge",
    "wof:placetype":"venue"
},
  "geometry": {"coordinates":[-1.237859,51.092876],"type":"Point"}
}