{
  "type": "Feature",
  "properties": {
    "addr:full":"64 Albion Road, New Mills High Peak Cheshire SK22 3EY",
    "addr:housenumber":"64",
    "addr:postcode":"sk22 3ey",
    "addr:street":"Albion Road",
    "iso:country":"GB",
    "sg:address":"64 Albion Road, New Mills",
    "sg:city":"High Peak",
    "sg:classifiers":[
        {
            "category":"Food & Beverages",
            "subcategory":"Meat & Fish",
            "type":"Retail Goods"
        }
    ],
    "sg:phone":"+44 1663 743054",
    "sg:postcode":"SK22 3EY",
    "sg:province":"Cheshire",
    "sg:tags":[
        "chip"
    ],
    "wof:name":"The New Lucky Tree",
    "wof:placetype":"venue"
},
  "geometry": {"coordinates":[-2.0018689632,53.3627090454],"type":"Point"}
}