{
  "type": "Feature",
  "properties": {
    "addr:full":"Little Wings, Cranmore Lane, West Horsley Leatherhead Surrey KT24 6BW",
    "addr:postcode":"kt24 6bw",
    "addr:street":"Cranmore Lane",
    "iso:country":"GB",
    "sg:address":"Little Wings, Cranmore Lane, West Horsley",
    "sg:city":"Leatherhead",
    "sg:classifiers":[
        {
            "category":"Transit Center",
            "subcategory":"Passenger",
            "type":"Transportation"
        },
        {
            "category":"Retail",
            "subcategory":"Pet Boarding",
            "type":"Services"
        }
    ],
    "sg:phone":"+44 1483 284263",
    "sg:postcode":"KT24 6BW",
    "sg:province":"Surrey",
    "sg:tags":[
        "kennel",
        "catteries"
    ],
    "wof:name":"Cranmore Cattery",
    "wof:placetype":"venue"
},
  "geometry": {"coordinates":[-0.4530999959,51.2605857849],"type":"Point"}
}