{
  "type": "Feature",
  "properties": {
    "addr:full":"8 Wingates Lane, West Houghton Bolton Lancashire BL5 3LP",
    "addr:housenumber":"8",
    "addr:postcode":"bl5 3lp",
    "addr:street":"Wingates Lane West",
    "iso:country":"GB",
    "sg:address":"8 Wingates Lane, West Houghton",
    "sg:city":"Bolton",
    "sg:classifiers":[
        {
            "category":"Retail",
            "subcategory":"Auto Repair",
            "type":"Services"
        }
    ],
    "sg:phone":"+44 1942 816312",
    "sg:postcode":"BL5 3LP",
    "sg:province":"Lancashire",
    "sg:tags":[
        "modification",
        "garage",
        "related"
    ],
    "wof:name":"Mobile Motor Engineer",
    "wof:placetype":"venue"
},
  "geometry": {"coordinates":[-2.525534,53.563305],"type":"Point"}
}