{
  "type": "Feature",
  "properties": {
    "addr:full":"76 Ben Jonson Rd Whitechapel Greater London E1 3NN",
    "addr:housenumber":"76",
    "addr:postcode":"e1 3nn",
    "addr:street":"Ben Jonson Rd",
    "iso:country":"GB",
    "sg:address":"76 Ben Jonson Rd",
    "sg:city":"Whitechapel",
    "sg:classifiers":[
        {
            "category":"Insurance",
            "subcategory":"Insurance Agent",
            "type":"Services"
        }
    ],
    "sg:phone":"+44 20 7702 8814",
    "sg:postcode":"E1 3NN",
    "sg:province":"Greater London",
    "wof:name":"Insure",
    "wof:placetype":"venue"
},
  "geometry": {"coordinates":[-0.0404889993,51.5179290771],"type":"Point"}
}