{
  "type": "Feature",
  "properties": {
    "iso:country":"GB",
    "sg:address":"21 St. Albans Pl",
    "sg:city":"London",
    "sg:classifiers":[
        {
            "category":"Home & Garden",
            "subcategory":"Home Furnishings",
            "type":"Retail Goods"
        }
    ],
    "sg:phone":"+44 20 7359 0224",
    "sg:postcode":"N1 0NX",
    "sg:province":"Greater London",
    "sg:tags":[
        "homefurnishings"
    ],
    "wof:name":"Steve Armitage Furniture Ltd",
    "wof:placetype":"venue"
},
  "geometry": {"coordinates":[-0.104219,51.53685],"type":"Point"}
}