{
  "type": "Feature",
  "properties": {
    "iso:country":"GB",
    "sg:address":"Barker La",
    "sg:city":"Chesterfield",
    "sg:classifiers":[
        {
            "category":"Professional",
            "subcategory":"Computer Services",
            "type":"Services"
        }
    ],
    "sg:phone":"+44 1246 220322",
    "sg:postcode":"S40 1DY",
    "sg:province":"Derbyshire",
    "sg:tags":[
        "system",
        "software"
    ],
    "wof:name":"I T Information Technology Business Of The Post Office",
    "wof:placetype":"venue"
},
  "geometry": {"coordinates":[-1.450986,53.23624],"type":"Point"}
}