{
  "type": "Feature",
  "properties": {
    "addr:full":"Softech House, London Road, Albourne Hassocks East Sussex BN6 9BN",
    "addr:postcode":"bn6 9bn",
    "addr:street":"London Road",
    "iso:country":"GB",
    "sg:address":"Softech House, London Road, Albourne",
    "sg:city":"Hassocks",
    "sg:classifiers":[
        {
            "category":"Travel",
            "subcategory":"Travel Agent",
            "type":"Entertainment"
        }
    ],
    "sg:phone":"+44 1273 835888",
    "sg:postcode":"BN6 9BN",
    "sg:province":"East Sussex",
    "wof:name":"The Cruise Line Ltd.",
    "wof:placetype":"venue"
},
  "geometry": {"coordinates":[-0.1942310035,50.9172554016],"type":"Point"}
}