{
  "type": "Feature",
  "properties": {
    "iso:country":"GB",
    "sg:address":"The Farm Shop, School Lane, Three Legged Cross",
    "sg:city":"Wimborne",
    "sg:classifiers":[
        {
            "category":"Professional",
            "subcategory":"Engineering",
            "type":"Services"
        }
    ],
    "sg:postcode":"BH21 6RU",
    "sg:province":"Dorset",
    "sg:tags":[
        "civil",
        "engineer"
    ],
    "wof:name":"Moors Contractors Ltd.",
    "wof:placetype":"venue"
},
  "geometry": {"coordinates":[-1.884271,50.850346],"type":"Point"}
}