{
  "type": "Feature",
  "properties": {
    "addr:full":"79 Whetley Lane Bradford West Yorkshire BD8 9DZ",
    "addr:housenumber":"79",
    "addr:postcode":"bd8 9dz",
    "addr:street":"Whetley Lane",
    "iso:country":"GB",
    "sg:address":"79 Whetley Lane",
    "sg:city":"Bradford",
    "sg:classifiers":[
        {
            "category":"Personal",
            "subcategory":"Barber",
            "type":"Services"
        }
    ],
    "sg:phone":"+44 1274 547855",
    "sg:postcode":"BD8 9DZ",
    "sg:province":"West Yorkshire",
    "sg:tags":[
        "men's",
        "hairdresser"
    ],
    "wof:name":"Sabir",
    "wof:placetype":"venue"
},
  "geometry": {"coordinates":[-1.78046,53.802177],"type":"Point"}
}