{
  "type": "Feature",
  "properties": {
    "addr:full":"10 Market Pl Camelford Cornwall PL32 9PB",
    "addr:housenumber":"10",
    "addr:postcode":"pl32 9pb",
    "addr:street":"Market Pl",
    "iso:country":"GB",
    "sg:address":"10 Market Pl",
    "sg:city":"Camelford",
    "sg:classifiers":[
        {
            "category":"Food & Beverages",
            "subcategory":"Bakery",
            "type":"Retail Goods"
        }
    ],
    "sg:postcode":"PL32 9PB",
    "sg:province":"Cornwall",
    "sg:tags":[
        "baker"
    ],
    "wof:name":"Headons Bakery",
    "wof:placetype":"venue"
},
  "geometry": {"coordinates":[-4.6788687706,50.6231651306],"type":"Point"}
}