{
  "type": "Feature",
  "properties": {
    "iso:country":"GB",
    "sg:address":"Harben House  Harben Parade, Finchley Road",
    "sg:city":"London",
    "sg:classifiers":[
        {
            "category":"Shopping",
            "subcategory":"Clothing, Apparel, & Fashions",
            "type":"Retail Goods"
        }
    ],
    "sg:postcode":"E11 2PU",
    "sg:province":"Greater London",
    "sg:tags":[
        "clothing",
        "fabric"
    ],
    "wof:name":"Krystal Clothing Ltd",
    "wof:placetype":"venue"
},
  "geometry": {"coordinates":[0.02592,51.57473],"type":"Point"}
}