{
  "type": "Feature",
  "properties": {
    "addr:full":"93 Knightsbridge London Greater London SW1X 7RB",
    "addr:housenumber":"93",
    "addr:postcode":"sw1x 7rb",
    "addr:street":"Knightsbridge",
    "iso:country":"GB",
    "sg:address":"93 Knightsbridge",
    "sg:city":"London",
    "sg:classifiers":[
        {
            "category":"Organizations",
            "subcategory":"Membership Organization",
            "type":"Services"
        }
    ],
    "sg:phone":"+44 20 7235 9595",
    "sg:postcode":"SW1X 7RB",
    "sg:province":"Greater London",
    "sg:tags":[
        "club"
    ],
    "wof:name":"Zealcastle Ltd.",
    "wof:placetype":"venue"
},
  "geometry": {"coordinates":[-0.158224,51.502151],"type":"Point"}
}