{
  "type": "Feature",
  "properties": {
    "addr:full":"1 Rosewood Av Hornchurch Essex RM12 5BU",
    "addr:housenumber":"1",
    "addr:postcode":"rm12 5bu",
    "addr:street":"Rosewood Av Hornchurch",
    "iso:country":"GB",
    "sg:address":"1 Rosewood Av",
    "sg:city":"Hornchurch",
    "sg:classifiers":[
        {
            "category":"Health Services",
            "subcategory":"Doctor",
            "type":"Services"
        }
    ],
    "sg:phone":"+44 1708 451295",
    "sg:postcode":"RM12 5BU",
    "sg:province":"Essex",
    "sg:tags":[
        "practitioners"
    ],
    "wof:name":"Gupta, A",
    "wof:placetype":"venue"
},
  "geometry": {"coordinates":[0.199475,51.547848],"type":"Point"}
}