{
  "type": "Feature",
  "properties": {
    "addr:full":"7 The Cresent Bromsgrove Worcestershire B60 2DQ",
    "addr:housenumber":"7",
    "addr:postcode":"b60 2dq",
    "addr:street":"The Cresent",
    "iso:country":"GB",
    "sg:address":"7 The Cresent",
    "sg:city":"Bromsgrove",
    "sg:classifiers":[
        {
            "category":"Professional",
            "subcategory":"Art Services",
            "type":"Services"
        }
    ],
    "sg:postcode":"B60 2DQ",
    "sg:province":"Worcestershire",
    "sg:tags":[
        "framing"
    ],
    "wof:name":"Surrounds Picture Framing",
    "wof:placetype":"venue"
},
  "geometry": {"coordinates":[-2.0599548817,52.3316955566],"type":"Point"}
}