{
  "type": "Feature",
  "properties": {
    "addr:full":"Whiteladies Road Bristol City of Bristol BS8 2RL",
    "addr:postcode":"bs8 2rl",
    "addr:street":"Whiteladies Road",
    "iso:country":"GB",
    "sg:address":"Whiteladies Road",
    "sg:city":"Bristol",
    "sg:classifiers":[
        {
            "category":"Shopping",
            "subcategory":"News",
            "type":"Retail Goods"
        }
    ],
    "sg:phone":"+44 117 973 8447",
    "sg:postcode":"BS8 2RL",
    "sg:province":"City of Bristol",
    "sg:tags":[
        "newsagent"
    ],
    "wof:name":"News Shop",
    "wof:placetype":"venue"
},
  "geometry": {"coordinates":[-2.6149339676,51.4701805115],"type":"Point"}
}