{
  "type": "Feature",
  "properties": {
    "addr:full":"King Street Bakery Colne Lancashire BB8 9HU",
    "addr:postcode":"bb8 9hu",
    "addr:street":"Colne",
    "iso:country":"GB",
    "sg:address":"King Street Bakery",
    "sg:city":"Colne",
    "sg:classifiers":[
        {
            "category":"Communications",
            "subcategory":"Film & Video Production",
            "type":"Services"
        },
        {
            "category":"Manufacturing",
            "subcategory":"Petroleum Products",
            "type":"Manufacturing & Wholesale Goods"
        }
    ],
    "sg:phone":"+44 1282 864198",
    "sg:postcode":"BB8 9HU",
    "sg:province":"Lancashire",
    "sg:tags":[
        "manufacture",
        "biscuit"
    ],
    "wof:name":"Kippax Biscuits Ltd",
    "wof:placetype":"venue"
},
  "geometry": {"coordinates":[-2.1662690639,53.8580093384],"type":"Point"}
}