{
  "type": "Feature",
  "properties": {
    "addr:full":"4 Harewood Road, Colliers Wood London Greater London SW19 2HD",
    "addr:housenumber":"4",
    "addr:postcode":"sw19 2hd",
    "addr:street":"Harewood Road Colliers",
    "iso:country":"GB",
    "sg:address":"4 Harewood Road, Colliers Wood",
    "sg:city":"London",
    "sg:classifiers":[
        {
            "category":"Professional",
            "subcategory":"Art Services",
            "type":"Services"
        }
    ],
    "sg:postcode":"SW19 2HD",
    "sg:province":"Greater London",
    "sg:tags":[
        "photographer"
    ],
    "wof:name":"Roger H R Dixon",
    "wof:placetype":"venue"
},
  "geometry": {"coordinates":[-0.170346,51.41964],"type":"Point"}
}