{
  "type": "Feature",
  "properties": {
    "iso:country":"GB",
    "sg:address":"The Sidings",
    "sg:city":"Leicester",
    "sg:classifiers":[
        {
            "category":"Transit Center",
            "subcategory":"Passenger",
            "type":"Transportation"
        }
    ],
    "sg:postcode":"LE4 2QG",
    "sg:province":"Leicestershire",
    "sg:tags":[
        "boarding",
        "kennel",
        "catteries"
    ],
    "wof:name":"Marion Sargent",
    "wof:placetype":"venue"
},
  "geometry": {"coordinates":[-1.161584,52.674435],"type":"Point"}
}