{
  "type": "Feature",
  "properties": {
    "iso:country":"GB",
    "sg:address":"22 Eaton Rd",
    "sg:city":"Liverpool",
    "sg:classifiers":[
        {
            "category":"Place Of Worship",
            "type":"Public Place"
        }
    ],
    "sg:phone":"+44 151 427 1474",
    "sg:postcode":"L19 0PW",
    "sg:province":"Merseyside",
    "wof:name":"St Mary's Grassendale C Of E Church",
    "wof:placetype":"venue"
},
  "geometry": {"coordinates":[-2.9153289795,53.3555793762],"type":"Point"}
}