{
  "type": "Feature",
  "properties": {
    "addr:full":"Melbourne Place Forfar Angus DD8 1JJ",
    "addr:postcode":"dd8 1jj",
    "addr:street":"Melbourne Place",
    "iso:country":"GB",
    "sg:address":"Melbourne Place",
    "sg:city":"Forfar",
    "sg:classifiers":[
        {
            "category":"Arena",
            "subcategory":"Sports Club",
            "type":"Entertainment"
        }
    ],
    "sg:phone":"+44 1307 463700",
    "sg:postcode":"DD8 1JJ",
    "sg:province":"Angus",
    "wof:name":"Forfar Bowling Club",
    "wof:placetype":"venue"
},
  "geometry": {"coordinates":[-2.8843340874,56.641960144],"type":"Point"}
}