{
  "type": "Feature",
  "properties": {
    "addr:full":"170 Hale End Road Woodford Green Essex IG8 9LZ",
    "addr:housenumber":"170",
    "addr:postcode":"ig8 9lz",
    "addr:street":"Hale End Road",
    "iso:country":"GB",
    "sg:address":"170 Hale End Road",
    "sg:city":"Woodford Green",
    "sg:classifiers":[
        {
            "category":"Government",
            "subcategory":"Police Station",
            "type":"Public Place"
        },
        {
            "category":"Professional",
            "subcategory":"Credit Reporting & Collection",
            "type":"Services"
        }
    ],
    "sg:phone":"+44 20 8523 4110",
    "sg:postcode":"IG8 9LZ",
    "sg:province":"Essex",
    "sg:tags":[
        "bailiff",
        "certificated"
    ],
    "wof:name":"Cuthbert & Kingsley",
    "wof:placetype":"venue"
},
  "geometry": {"coordinates":[-0.00092,51.6007499695],"type":"Point"}
}