{
  "type": "Feature",
  "properties": {
    "addr:full":"190 High Rd Loughton Essex IG10 1DN",
    "addr:housenumber":"190",
    "addr:postcode":"ig10 1dn",
    "addr:street":"High Rd",
    "iso:country":"GB",
    "sg:address":"190 High Rd",
    "sg:city":"Loughton",
    "sg:classifiers":[
        {
            "category":"Personal",
            "subcategory":"Beauty Salon",
            "type":"Services"
        }
    ],
    "sg:phone":"+44 20 8502 0303",
    "sg:postcode":"IG10 1DN",
    "sg:province":"Essex",
    "sg:tags":[
        "unisex",
        "hairdresser"
    ],
    "wof:name":"Steven Russell",
    "wof:placetype":"venue"
},
  "geometry": {"coordinates":[0.053861,51.646465],"type":"Point"}
}