{
  "type": "Feature",
  "properties": {
    "iso:country":"GB",
    "sg:address":"4 Broomfield",
    "sg:city":"Sunbury-on-thames",
    "sg:classifiers":[
        {
            "category":"Building & Trades",
            "subcategory":"Construction",
            "type":"Services"
        }
    ],
    "sg:phone":"+44 1932 771200",
    "sg:postcode":"TW16 6SW",
    "sg:province":"Surrey",
    "sg:tags":[
        "builder"
    ],
    "wof:name":"A B A Interiors Ltd.",
    "wof:placetype":"venue"
},
  "geometry": {"coordinates":[-0.41392,51.418198],"type":"Point"}
}