{
  "type": "Feature",
  "properties": {
    "iso:country":"GB",
    "sg:address":"Unit B, Dukes Drive",
    "sg:city":"Carlisle",
    "sg:classifiers":[
        {
            "category":"Home & Garden",
            "subcategory":"Building Materials",
            "type":"Retail Goods"
        }
    ],
    "sg:postcode":"CA6 4SH",
    "sg:province":"Cumbria",
    "sg:tags":[
        "fencing"
    ],
    "wof:name":"Contract Fencing Ltd.",
    "wof:placetype":"venue"
},
  "geometry": {"coordinates":[-2.823059082,54.9315795898],"type":"Point"}
}