{
  "type": "Feature",
  "properties": {
    "iso:country":"GB",
    "sg:address":"Plashett Park Farm, Ringmer",
    "sg:city":"Lewes",
    "sg:classifiers":[
        {
            "category":"Farming",
            "subcategory":"Farm",
            "type":"Manufacturing & Wholesale Goods"
        }
    ],
    "sg:phone":"+44 1273 812389",
    "sg:postcode":"BN8 5SJ",
    "sg:province":"East Sussex",
    "sg:tags":[
        "mixed",
        "crop"
    ],
    "wof:name":"A Peters & Son",
    "wof:placetype":"venue"
},
  "geometry": {"coordinates":[0.059079,50.894077],"type":"Point"}
}