{
  "type": "Feature",
  "properties": {
    "iso:country":"GB",
    "sg:address":"Sdc Ho, 31 Waddon Rd",
    "sg:city":"Croydon",
    "sg:classifiers":[
        {
            "category":"Retail",
            "subcategory":"Auto Rental",
            "type":"Services"
        }
    ],
    "sg:postcode":"CR0 4LH",
    "sg:province":"Surrey",
    "sg:tags":[
        "car"
    ],
    "wof:name":"Self Drive (Croydon) Ltd",
    "wof:placetype":"venue"
},
  "geometry": {"coordinates":[-0.1090300009,51.3718185425],"type":"Point"}
}