{
  "type": "Feature",
  "properties": {
    "addr:full":"Mornington Avenue London Greater London W14 8UJ",
    "addr:postcode":"w14 8uj",
    "addr:street":"Mornington Avenue",
    "iso:country":"GB",
    "sg:address":"Mornington Avenue",
    "sg:city":"London",
    "sg:classifiers":[
        {
            "category":"Health Services",
            "subcategory":"Clinic",
            "type":"Services"
        }
    ],
    "sg:postcode":"W14 8UJ",
    "sg:province":"Greater London",
    "sg:tags":[
        "nh"
    ],
    "wof:name":"Falkland House Health Clinic",
    "wof:placetype":"venue"
},
  "geometry": {"coordinates":[-0.206196,51.492188],"type":"Point"}
}