{
  "type": "Feature",
  "properties": {
    "iso:country":"GB",
    "sg:address":"11 King Edward Avenue",
    "sg:city":"Blackpool",
    "sg:classifiers":[
        {
            "category":"Travel",
            "subcategory":"Hotels & Motels",
            "type":"Entertainment"
        }
    ],
    "sg:postcode":"FY2 9TD",
    "sg:province":"Lancashire",
    "wof:name":"Pembroke Private Hotel",
    "wof:placetype":"venue"
},
  "geometry": {"coordinates":[-3.053092,53.835194],"type":"Point"}
}