{
  "type": "Feature",
  "properties": {
    "addr:full":"28 West St Marlow Berkshire SL7 2NB",
    "addr:housenumber":"28",
    "addr:postcode":"sl7 2nb",
    "addr:street":"West St",
    "iso:country":"GB",
    "sg:address":"28 West St",
    "sg:city":"Marlow",
    "sg:classifiers":[
        {
            "category":"Professional",
            "subcategory":"Art Services",
            "type":"Services"
        }
    ],
    "sg:phone":"+44 1628 477707",
    "sg:postcode":"SL7 2NB",
    "sg:province":"Berkshire",
    "sg:tags":[
        "decorating",
        "painting"
    ],
    "wof:name":"Paint Magic Marlow",
    "wof:placetype":"venue"
},
  "geometry": {"coordinates":[-0.7779530287,51.5713996887],"type":"Point"}
}