{
  "type": "Feature",
  "properties": {
    "addr:full":"25 Harley Street London Greater London W1G 9BR",
    "addr:housenumber":"25",
    "addr:postcode":"w1g 9br",
    "addr:street":"Harley Street",
    "iso:country":"GB",
    "sg:address":"25 Harley Street",
    "sg:city":"London",
    "sg:classifiers":[
        {
            "category":"Professional",
            "subcategory":"Lawyer & Legal Services",
            "type":"Services"
        }
    ],
    "sg:phone":"+44 20 7299 1400",
    "sg:postcode":"W1G 9BR",
    "sg:province":"Greater London",
    "sg:tags":[
        "practitioner",
        "insolvency"
    ],
    "wof:name":"Gerald Edelman Financial Solutions Ltd.",
    "wof:placetype":"venue"
},
  "geometry": {"coordinates":[-0.14658,51.517712],"type":"Point"}
}