{
  "type": "Feature",
  "properties": {
    "addr:full":"Dunrose Clo Coventry Warwickshire CV2 5PG",
    "addr:postcode":"cv2 5pg",
    "iso:country":"GB",
    "sg:address":"Dunrose Clo",
    "sg:city":"Coventry",
    "sg:classifiers":[
        {
            "category":"Social Services",
            "subcategory":"Adult Care",
            "type":"Services"
        }
    ],
    "sg:phone":"+44 24 7645 8069",
    "sg:postcode":"CV2 5PG",
    "sg:province":"Warwickshire",
    "sg:tags":[
        "housing",
        "sheltered"
    ],
    "wof:name":"William Sheridan House Sheltered Housing",
    "wof:placetype":"venue"
},
  "geometry": {"coordinates":[-1.4518209696,52.4072341919],"type":"Point"}
}