{
  "type": "Feature",
  "properties": {
    "iso:country":"GB",
    "sg:address":"Unit 33/34, Churchill Way, Fleckney",
    "sg:city":"Leicester",
    "sg:classifiers":[
        {
            "category":"Shopping",
            "subcategory":"Crafts & Fabrics",
            "type":"Retail Goods"
        }
    ],
    "sg:phone":"+44 116 240 2909",
    "sg:postcode":"LE8 8UD",
    "sg:province":"Leicestershire",
    "sg:tags":[
        "knitwear",
        "yarn"
    ],
    "wof:name":"B H M Knitwear Ltd.",
    "wof:placetype":"venue"
},
  "geometry": {"coordinates":[-1.0394099951,52.5311393738],"type":"Point"}
}