{
  "type": "Feature",
  "properties": {
    "iso:country":"GB",
    "sg:address":"8th Floor, 40 Lime Street",
    "sg:city":"London",
    "sg:classifiers":[
        {
            "category":"Manufacturing",
            "subcategory":"Tools & Machinery",
            "type":"Manufacturing & Wholesale Goods"
        }
    ],
    "sg:phone":"+44 20 7929 1355",
    "sg:postcode":"EC3M 5BS",
    "sg:province":"Greater London",
    "sg:tags":[
        "society",
        "friendly"
    ],
    "wof:name":"E A L C Ltd.",
    "wof:placetype":"venue"
},
  "geometry": {"coordinates":[-0.0821790025,51.5125274658],"type":"Point"}
}