{
  "type": "Feature",
  "properties": {
    "addr:full":"Acorn House, 33 Churchfield Road London Greater London W3 6AY",
    "addr:housenumber":"33",
    "addr:postcode":"w3 6ay",
    "addr:street":"Churchfield Road",
    "iso:country":"GB",
    "sg:address":"Acorn House, 33 Churchfield Road",
    "sg:city":"London",
    "sg:classifiers":[
        {
            "category":"Real Estate",
            "subcategory":"Developer",
            "type":"Services"
        }
    ],
    "sg:postcode":"W3 6AY",
    "sg:province":"Greater London",
    "sg:tags":[
        "property"
    ],
    "wof:name":"S. Budner Limited",
    "wof:placetype":"venue"
},
  "geometry": {"coordinates":[-0.265115,51.508671],"type":"Point"}
}