{
  "type": "Feature",
  "properties": {
    "addr:full":"22 Rowley Avenue Sidcup Kent DA15 9LB",
    "addr:housenumber":"22",
    "addr:postcode":"da15 9lb",
    "addr:street":"Rowley Avenue",
    "iso:country":"GB",
    "sg:address":"22 Rowley Avenue",
    "sg:city":"Sidcup",
    "sg:classifiers":[
        {
            "category":"Home & Garden",
            "subcategory":"Carpets & Floor Coverings",
            "type":"Retail Goods"
        }
    ],
    "sg:postcode":"DA15 9LB",
    "sg:province":"Kent",
    "sg:tags":[
        "carpets",
        "rug",
        "matting"
    ],
    "wof:name":"Complete Flooring",
    "wof:placetype":"venue"
},
  "geometry": {"coordinates":[0.1101600006,51.44323349],"type":"Point"}
}