{
  "type": "Feature",
  "properties": {
    "addr:full":"Suite 6 Regent Chambers, 1-3 Regent Street Barnsley South Yorkshire S70 2EG",
    "addr:housenumber":"suite 6;1-3",
    "addr:postcode":"s70 2eg",
    "addr:street":"Regent;Regent Street;Yorkshire",
    "iso:country":"GB",
    "sg:address":"Suite 6 Regent Chambers, 1-3 Regent Street",
    "sg:city":"Barnsley",
    "sg:classifiers":[
        {
            "category":"Communications",
            "subcategory":"Newspaper",
            "type":"Services"
        }
    ],
    "sg:phone":"+44 1226 242727",
    "sg:postcode":"S70 2EG",
    "sg:province":"South Yorkshire",
    "sg:tags":[
        "magazine"
    ],
    "wof:name":"Barnsley Star",
    "wof:placetype":"venue"
},
  "geometry": {"coordinates":[-1.484738,53.553192],"type":"Point"}
}