{
  "type": "Feature",
  "properties": {
    "addr:full":"Greenvale Mill, Summit Littleborough Lancashire OL15 9QP",
    "addr:postcode":"ol15 9qp",
    "addr:street":"Greenvale Mill",
    "iso:country":"GB",
    "sg:address":"Greenvale Mill, Summit",
    "sg:city":"Littleborough",
    "sg:classifiers":[
        {
            "category":"Manufacturing",
            "subcategory":"Textiles",
            "type":"Manufacturing & Wholesale Goods"
        }
    ],
    "sg:phone":"+44 1706 371137",
    "sg:postcode":"OL15 9QP",
    "sg:province":"Lancashire",
    "sg:tags":[
        "made-up"
    ],
    "wof:name":"Fothergill-Crenette Ltd.",
    "wof:placetype":"venue"
},
  "geometry": {"coordinates":[-2.0837950706,53.6626396179],"type":"Point"}
}