{
  "type": "Feature",
  "properties": {
    "addr:full":"Corner Farm Huntingdon Cambridgeshire PE18 0XZ",
    "addr:postcode":"pe18 0xz",
    "iso:country":"GB",
    "sg:address":"Corner Farm",
    "sg:city":"Huntingdon",
    "sg:classifiers":[
        {
            "category":"Farming",
            "subcategory":"Livestock Farm",
            "type":"Manufacturing & Wholesale Goods"
        }
    ],
    "sg:phone":"+44 1480 890477",
    "sg:postcode":"PE18 0XZ",
    "sg:province":"Cambridgeshire",
    "sg:tags":[
        "others"
    ],
    "wof:name":"R B Coulson",
    "wof:placetype":"venue"
},
  "geometry": {"coordinates":[-0.1893,52.33514],"type":"Point"}
}