{
  "type": "Feature",
  "properties": {
    "addr:full":"The Woodlands Farm, Elton Ludlow Herefordshire SY8 2HH",
    "addr:postcode":"sy8 2hh",
    "addr:street":"Elton",
    "iso:country":"GB",
    "sg:address":"The Woodlands Farm, Elton",
    "sg:city":"Ludlow",
    "sg:classifiers":[
        {
            "category":"Farming",
            "subcategory":"Livestock Farm",
            "type":"Manufacturing & Wholesale Goods"
        }
    ],
    "sg:postcode":"SY8 2HH",
    "sg:province":"Herefordshire",
    "sg:tags":[
        "others"
    ],
    "wof:name":"R H Stinton",
    "wof:placetype":"venue"
},
  "geometry": {"coordinates":[-2.798919,52.333851],"type":"Point"}
}