{
  "type": "Feature",
  "properties": {
    "addr:full":"P O Box 40 Carlisle Cumbria CA1 2LA",
    "addr:housenumber":"box 40",
    "addr:postcode":"ca1 2la",
    "addr:street":"P O",
    "iso:country":"GB",
    "sg:address":"P O Box 40",
    "sg:city":"Carlisle",
    "sg:classifiers":[
        {
            "category":"Organizations",
            "subcategory":"Non-profit Organization",
            "type":"Services"
        }
    ],
    "sg:phone":"+44 1228 591995",
    "sg:postcode":"CA1 2LA",
    "sg:province":"Cumbria",
    "sg:tags":[
        "organisation",
        "voluntary",
        "charity"
    ],
    "wof:name":"Carlisle Aid For Women",
    "wof:placetype":"venue"
},
  "geometry": {"coordinates":[-2.907959,54.89003],"type":"Point"}
}