{
  "type": "Feature",
  "properties": {
    "addr:full":"North Darkland Farm Elgin Moray IV30 8LB",
    "addr:postcode":"iv30 8lb",
    "addr:street":"North;Elgin",
    "iso:country":"GB",
    "sg:address":"North Darkland Farm",
    "sg:city":"Elgin",
    "sg:classifiers":[
        {
            "category":"Shopping",
            "subcategory":"Hobbies, Toys, & Games",
            "type":"Retail Goods"
        },
        {
            "category":"Farming",
            "subcategory":"Livestock Farm",
            "type":"Manufacturing & Wholesale Goods"
        }
    ],
    "sg:phone":"+44 1343 842216",
    "sg:postcode":"IV30 8LB",
    "sg:province":"Moray",
    "sg:tags":[
        "others",
        "gunsmith"
    ],
    "wof:name":"Trap & Field Supplies",
    "wof:placetype":"venue"
},
  "geometry": {"coordinates":[-3.215574,57.637299],"type":"Point"}
}