{
  "type": "Feature",
  "properties": {
    "iso:country":"GB",
    "sg:address":"Oakridge Lynch",
    "sg:city":"Stroud",
    "sg:classifiers":[
        {
            "category":"Shopping",
            "subcategory":"Bicycles & Sporting Goods",
            "type":"Retail Goods"
        }
    ],
    "sg:phone":"+44 1285 760762",
    "sg:postcode":"GL6 7PA",
    "sg:province":"Gloucestershire",
    "sg:tags":[
        "equipment",
        "leisure"
    ],
    "wof:name":"Silver Crest Submarines",
    "wof:placetype":"venue"
},
  "geometry": {"coordinates":[-2.1172099113,51.729839325],"type":"Point"}
}