{
  "type": "Feature",
  "properties": {
    "iso:country":"GB",
    "sg:address":"The Power House, Heath Park Industrial Estate",
    "sg:city":"Honiton",
    "sg:classifiers":[
        {
            "category":"Professional",
            "subcategory":"Engineering",
            "type":"Services"
        }
    ],
    "sg:postcode":"EX14 1YD",
    "sg:province":"Devon",
    "sg:tags":[
        "engineer",
        "mechanical"
    ],
    "wof:name":"Richard G Williams",
    "wof:placetype":"venue"
},
  "geometry": {"coordinates":[-3.196906,50.797386],"type":"Point"}
}