{
  "type": "Feature",
  "properties": {
    "addr:full":"Reedham House Manchester Greater Manchester M3 2PJ",
    "addr:postcode":"m3 2pj",
    "addr:street":"Manchester",
    "iso:country":"GB",
    "sg:address":"Reedham House",
    "sg:city":"Manchester",
    "sg:classifiers":[
        {
            "category":"Professional",
            "subcategory":"Accounting & Tax Preparation",
            "type":"Services"
        }
    ],
    "sg:phone":"+44 161 834 2574",
    "sg:postcode":"M3 2PJ",
    "sg:province":"Greater Manchester",
    "sg:tags":[
        "accountant"
    ],
    "wof:name":"Freedman Frankl & Taylor",
    "wof:placetype":"venue"
},
  "geometry": {"coordinates":[-2.2488090992,53.4796218872],"type":"Point"}
}