{
  "type": "Feature",
  "properties": {
    "addr:full":"Throstle Nest Mill, Leeds Road Nelson Lancashire BB9 9XG",
    "addr:postcode":"bb9 9xg",
    "addr:street":"Leeds Road",
    "iso:country":"GB",
    "sg:address":"Throstle Nest Mill, Leeds Road",
    "sg:city":"Nelson",
    "sg:classifiers":[
        {
            "category":"Home & Garden",
            "subcategory":"Home Furnishings",
            "type":"Retail Goods"
        }
    ],
    "sg:phone":"+44 1282 698091",
    "sg:postcode":"BB9 9XG",
    "sg:province":"Lancashire",
    "sg:tags":[
        "homefurnishings"
    ],
    "wof:name":"J W FABRICS",
    "wof:placetype":"venue"
},
  "geometry": {"coordinates":[-2.213340044,53.8359680176],"type":"Point"}
}