{
  "type": "Feature",
  "properties": {
    "addr:full":"Charles House, Denbigh Road Laindon Basildon Essex SS15 6PZ",
    "addr:postcode":"ss15 6pz",
    "addr:street":"Denbigh Road",
    "iso:country":"GB",
    "sg:address":"Charles House, Denbigh Road Laindon",
    "sg:city":"Basildon",
    "sg:classifiers":[
        {
            "category":"Retail",
            "subcategory":"Storage",
            "type":"Services"
        }
    ],
    "sg:phone":"+44 1268 414979",
    "sg:postcode":"SS15 6PZ",
    "sg:province":"Essex",
    "sg:tags":[
        "household",
        "removal"
    ],
    "wof:name":"Jeakins Removals",
    "wof:placetype":"venue"
},
  "geometry": {"coordinates":[0.4103490114,51.5749893188],"type":"Point"}
}