{
  "type": "Feature",
  "properties": {
    "addr:full":"Tannachie Stonehaven Aberdeenshire AB39 3UY",
    "addr:postcode":"ab39 3uy",
    "iso:country":"GB",
    "sg:address":"Tannachie",
    "sg:city":"Stonehaven",
    "sg:classifiers":[
        {
            "category":"Farming",
            "subcategory":"Livestock Farm",
            "type":"Manufacturing & Wholesale Goods"
        }
    ],
    "sg:phone":"+44 1569 740248",
    "sg:postcode":"AB39 3UY",
    "sg:province":"Aberdeenshire",
    "sg:tags":[
        "others"
    ],
    "wof:name":"A Johnstone & Partners",
    "wof:placetype":"venue"
},
  "geometry": {"coordinates":[-2.2199690342,56.9946784973],"type":"Point"}
}