{
  "type": "Feature",
  "properties": {
    "iso:country":"GB",
    "sg:address":"139 Upper College Ride",
    "sg:city":"Camberley",
    "sg:classifiers":[
        {
            "category":"Building & Trades",
            "subcategory":"Plumbing",
            "type":"Services"
        }
    ],
    "sg:postcode":"GU15 4EY",
    "sg:province":"Berkshire",
    "sg:tags":[
        "heating"
    ],
    "wof:name":"White,Leslie,",
    "wof:placetype":"venue"
},
  "geometry": {"coordinates":[-0.731593,51.347511],"type":"Point"}
}