{
  "type": "Feature",
  "properties": {
    "addr:full":"816 Christchurch Rd, Boscombe Bournemouth Dorset BH7 6DF",
    "addr:housenumber":"816",
    "addr:postcode":"bh7 6df",
    "addr:street":"Christchurch Rd",
    "iso:country":"GB",
    "sg:address":"816 Christchurch Rd, Boscombe",
    "sg:city":"Bournemouth",
    "sg:classifiers":[
        {
            "category":"Government",
            "subcategory":"Customs House",
            "type":"Public Place"
        }
    ],
    "sg:phone":"+44 1202 430548",
    "sg:postcode":"BH7 6DF",
    "sg:province":"Dorset",
    "sg:tags":[
        "clearance"
    ],
    "wof:name":"Bits & Pieces",
    "wof:placetype":"venue"
},
  "geometry": {"coordinates":[-1.8296509981,50.7293243408],"type":"Point"}
}