{
  "type": "Feature",
  "properties": {
    "addr:full":"22 Townhill Road Dunfermline Fife KY12 0QX",
    "addr:housenumber":"22",
    "addr:postcode":"ky12 0qx",
    "addr:street":"Townhill Road",
    "iso:country":"GB",
    "sg:address":"22 Townhill Road",
    "sg:city":"Dunfermline",
    "sg:classifiers":[
        {
            "category":"Organizations",
            "subcategory":"Non-profit Organization",
            "type":"Services"
        }
    ],
    "sg:phone":"+44 1383 722222",
    "sg:postcode":"KY12 0QX",
    "sg:province":"Fife",
    "sg:tags":[
        "organisation",
        "voluntary",
        "charity"
    ],
    "wof:name":"The Samaritans",
    "wof:placetype":"venue"
},
  "geometry": {"coordinates":[-3.4517080784,56.075012207],"type":"Point"}
}