{
  "type": "Feature",
  "properties": {
    "addr:full":"Washington Court, 38 Washington Street Birmingham West Midlands B1 1LB",
    "addr:housenumber":"38",
    "addr:postcode":"b1 1lb",
    "addr:street":"Washington Court;Washington Street",
    "iso:country":"GB",
    "sg:address":"Washington Court, 38 Washington Street",
    "sg:city":"Birmingham",
    "sg:classifiers":[
        {
            "category":"Travel",
            "subcategory":"Hostel",
            "type":"Entertainment"
        }
    ],
    "sg:phone":"+44 121 643 6182",
    "sg:postcode":"B1 1LB",
    "sg:province":"West Midlands",
    "wof:name":"Birmingham City Mission",
    "wof:placetype":"venue"
},
  "geometry": {"coordinates":[-1.906435,52.474667],"type":"Point"}
}