{
  "type": "Feature",
  "properties": {
    "addr:full":"57 Beardmore Way Clydebank East Dunbartonshire G81 4HT",
    "addr:housenumber":"57",
    "addr:postcode":"g81 4ht",
    "addr:street":"Beardmore Way",
    "iso:country":"GB",
    "sg:address":"57 Beardmore Way",
    "sg:city":"Clydebank",
    "sg:classifiers":[
        {
            "category":"Shopping",
            "subcategory":"Stationery & Office Supplies",
            "type":"Retail Goods"
        }
    ],
    "sg:phone":"+44 141 952 1856",
    "sg:postcode":"G81 4HT",
    "sg:province":"East Dunbartonshire",
    "sg:tags":[
        "box",
        "carton"
    ],
    "wof:name":"Wace Corporate Packaging Clydebank",
    "wof:placetype":"venue"
},
  "geometry": {"coordinates":[-4.434398,55.9076],"type":"Point"}
}