{
  "type": "Feature",
  "properties": {
    "iso:country":"GB",
    "sg:address":"17 Pecks Hill",
    "sg:city":"Mansfield",
    "sg:classifiers":[
        {
            "category":"Shopping",
            "subcategory":"Pets & Pet Supplies",
            "type":"Retail Goods"
        }
    ],
    "sg:phone":"+44 1623 650233",
    "sg:postcode":"NG18 2NS",
    "sg:province":"Nottinghamshire",
    "sg:tags":[
        "food"
    ],
    "wof:name":"Kennelgate",
    "wof:placetype":"venue"
},
  "geometry": {"coordinates":[-1.178705,53.144173],"type":"Point"}
}