{
  "type": "Feature",
  "properties": {
    "addr:full":"901 Herries Rd Sheffield South Yorkshire S6 1QH",
    "addr:housenumber":"901",
    "addr:postcode":"s6 1qh",
    "addr:street":"Herries Rd",
    "iso:country":"GB",
    "sg:address":"901 Herries Rd",
    "sg:city":"Sheffield",
    "sg:classifiers":[
        {
            "category":"Autos & Motor Vehicles",
            "subcategory":"Auto Supplies",
            "type":"Retail Goods"
        }
    ],
    "sg:phone":"+44 114 234 5772",
    "sg:postcode":"S6 1QH",
    "sg:province":"South Yorkshire",
    "sg:tags":[
        "guard",
        "grille"
    ],
    "wof:name":"ASD RP Profiles",
    "wof:placetype":"venue"
},
  "geometry": {"coordinates":[-1.496639,53.41328],"type":"Point"}
}