{
  "type": "Feature",
  "properties": {
    "addr:full":"75 Rushey Grn London Greater London SE6 4AF",
    "addr:housenumber":"75",
    "addr:postcode":"se6 4af",
    "addr:street":"Rushey Grn",
    "iso:country":"GB",
    "sg:address":"75 Rushey Grn",
    "sg:city":"London",
    "sg:classifiers":[
        {
            "category":"Manufacturing",
            "subcategory":"Tools & Machinery",
            "type":"Manufacturing & Wholesale Goods"
        }
    ],
    "sg:phone":"+44 20 8461 2606",
    "sg:postcode":"SE6 4AF",
    "sg:province":"Greater London",
    "sg:tags":[
        "power"
    ],
    "wof:name":"Black & Decker Factory Outlet",
    "wof:placetype":"venue"
},
  "geometry": {"coordinates":[-0.017953,51.447727],"type":"Point"}
}