{
  "type": "Feature",
  "properties": {
    "addr:full":"631-633 Fulham Rd Fulham Greater London SW6 5UQ",
    "addr:housenumber":"631-633",
    "addr:postcode":"sw6 5uq",
    "addr:street":"Fulham Rd",
    "iso:country":"GB",
    "sg:address":"631-633 Fulham Rd",
    "sg:city":"Fulham",
    "sg:classifiers":[
        {
            "category":"Utilities",
            "type":"Services"
        }
    ],
    "sg:phone":"+44 20 7460 4322",
    "sg:postcode":"SW6 5UQ",
    "sg:province":"Greater London",
    "sg:tags":[
        "internet"
    ],
    "wof:name":"Bibliotech Ltd",
    "wof:placetype":"venue"
},
  "geometry": {"coordinates":[-0.1987639964,51.4796218872],"type":"Point"}
}