{
  "type": "Feature",
  "properties": {
    "iso:country":"GB",
    "sg:address":"88 Barncroft Way",
    "sg:city":"Havant",
    "sg:classifiers":[
        {
            "category":"Food & Beverages",
            "subcategory":"Groceries & Convenience Stores",
            "type":"Retail Goods"
        }
    ],
    "sg:phone":"+44 23 9248 1501",
    "sg:postcode":"PO9 3AH",
    "sg:province":"Hampshire",
    "wof:name":"M & S Stores",
    "wof:placetype":"venue"
},
  "geometry": {"coordinates":[-0.994241,50.861473],"type":"Point"}
}