{
  "type": "Feature",
  "properties": {
    "iso:country":"GB",
    "sg:address":"Liverpool Avenue",
    "sg:city":"Southport",
    "sg:classifiers":[
        {
            "category":"Education",
            "subcategory":"Library",
            "type":"Public Place"
        }
    ],
    "sg:phone":"+44 1704 577345",
    "sg:postcode":"PR8 3NE",
    "sg:province":"Lancashire",
    "sg:tags":[
        "book"
    ],
    "wof:name":"Ainsdale Library",
    "wof:placetype":"venue"
},
  "geometry": {"coordinates":[-3.016279,53.617256],"type":"Point"}
}