{
  "type": "Feature",
  "properties": {
    "iso:country":"GB",
    "sg:address":"Unit 5 16a Pony Road, Horspatgh Trading Estate",
    "sg:city":"Oxford",
    "sg:classifiers":[
        {
            "category":"Building & Trades",
            "subcategory":"Construction",
            "type":"Services"
        }
    ],
    "sg:phone":"+44 1865 774488",
    "sg:postcode":"OX4 2RD",
    "sg:province":"Oxfordshire",
    "sg:tags":[
        "builder"
    ],
    "wof:name":"Serwyn Homes Ltd.",
    "wof:placetype":"venue"
},
  "geometry": {"coordinates":[-1.194609,51.737728],"type":"Point"}
}