{
  "type": "Feature",
  "properties": {
    "addr:full":"Unit 14a Attley Way, North Nelson Ind Est Cramlington Northumberland NE23 1WA",
    "addr:housenumber":"unit 14a",
    "addr:postcode":"ne23 1wa",
    "addr:street":"Attley Way North;Ind Est;Northumberland",
    "iso:country":"GB",
    "sg:address":"Unit 14a Attley Way, North Nelson Ind Est",
    "sg:city":"Cramlington",
    "sg:classifiers":[
        {
            "category":"Professional",
            "subcategory":"Engineering",
            "type":"Services"
        }
    ],
    "sg:phone":"+44 1670 734375",
    "sg:postcode":"NE23 1WA",
    "sg:province":"Northumberland",
    "sg:tags":[
        "engineer",
        "mechanical"
    ],
    "wof:name":"Hood Engineering Services Ltd",
    "wof:placetype":"venue"
},
  "geometry": {"coordinates":[-1.6080789566,55.1029891968],"type":"Point"}
}