{
  "type": "Feature",
  "properties": {
    "addr:full":"85 Sheen Road Richmond Greater London TW9 1YJ",
    "addr:housenumber":"85",
    "addr:postcode":"tw9 1yj",
    "addr:street":"Sheen Road",
    "iso:country":"GB",
    "sg:address":"85 Sheen Road",
    "sg:city":"Richmond",
    "sg:classifiers":[
        {
            "category":"Professional",
            "subcategory":"Advertising",
            "type":"Services"
        },
        {
            "category":"Airline",
            "type":"Transportation"
        }
    ],
    "sg:phone":"+44 20 8948 5322",
    "sg:postcode":"TW9 1YJ",
    "sg:province":"Greater London",
    "sg:tags":[
        "agency"
    ],
    "wof:name":"Lansdowne Creative Marketing Ltd.",
    "wof:placetype":"venue"
},
  "geometry": {"coordinates":[-0.2952339947,51.4620323181],"type":"Point"}
}