{
  "type": "Feature",
  "properties": {
    "addr:full":"2 Adams Close, Kempston Bedford Bedfordshire MK42 7JE",
    "addr:housenumber":"2",
    "addr:postcode":"mk42 7je",
    "addr:street":"Adams Close",
    "iso:country":"GB",
    "sg:address":"2 Adams Close, Kempston",
    "sg:city":"Bedford",
    "sg:classifiers":[
        {
            "category":"Ice Cream",
            "type":"Food & Drink"
        }
    ],
    "sg:postcode":"MK42 7JE",
    "sg:province":"Bedfordshire",
    "sg:tags":[
        "mnfr"
    ],
    "wof:name":"Franco Ices",
    "wof:placetype":"venue"
},
  "geometry": {"coordinates":[-0.49505,52.106747],"type":"Point"}
}