{
  "type": "Feature",
  "properties": {
    "addr:full":"Starworks, Darnall Rd Sheffield South Yorkshire S9 5AF",
    "addr:postcode":"s9 5af",
    "addr:street":"Darnall Rd",
    "iso:country":"GB",
    "sg:address":"Starworks, Darnall Rd",
    "sg:city":"Sheffield",
    "sg:classifiers":[
        {
            "category":"Organizations",
            "subcategory":"Non-profit Organization",
            "type":"Services"
        }
    ],
    "sg:phone":"+44 114 242 4066",
    "sg:postcode":"S9 5AF",
    "sg:province":"South Yorkshire",
    "sg:tags":[
        "organisation",
        "voluntary",
        "charity"
    ],
    "wof:name":"Sooper Troopers",
    "wof:placetype":"venue"
},
  "geometry": {"coordinates":[-1.410154,53.387859],"type":"Point"}
}