{
  "type": "Feature",
  "properties": {
    "addr:full":"135 Outram Street Sutton-in-ashfield Nottinghamshire NG17 4FU",
    "addr:housenumber":"135",
    "addr:postcode":"ng17 4fu",
    "addr:street":"Outram Street",
    "iso:country":"GB",
    "sg:address":"135 Outram Street",
    "sg:city":"Sutton-in-ashfield",
    "sg:classifiers":[
        {
            "category":"Shopping",
            "subcategory":"Discount & Variety Stores",
            "type":"Retail Goods"
        }
    ],
    "sg:phone":"+44 1623 557812",
    "sg:postcode":"NG17 4FU",
    "sg:province":"Nottinghamshire",
    "sg:tags":[
        "shop",
        "model"
    ],
    "wof:name":"Models & Hobby Centre",
    "wof:placetype":"venue"
},
  "geometry": {"coordinates":[-1.255042,53.12978],"type":"Point"}
}