{
  "type": "Feature",
  "properties": {
    "addr:full":"4-8 Thorn Road, Hedon Hull East Riding of Yorkshire HU12 8HP",
    "addr:housenumber":"4-8",
    "addr:postcode":"hu12 8hp",
    "addr:street":"Thorn Road",
    "iso:country":"GB",
    "sg:address":"4-8 Thorn Road, Hedon",
    "sg:city":"Hull",
    "sg:classifiers":[
        {
            "category":"Autos & Motor Vehicles",
            "subcategory":"Automobile Sales",
            "type":"Retail Goods"
        }
    ],
    "sg:phone":"+44 1482 891593",
    "sg:postcode":"HU12 8HP",
    "sg:province":"East Riding of Yorkshire",
    "sg:tags":[
        "car"
    ],
    "wof:name":"Nicholsons Hedon",
    "wof:placetype":"venue"
},
  "geometry": {"coordinates":[-0.1960130036,53.7389907837],"type":"Point"}
}