{
  "type": "Feature",
  "properties": {
    "iso:country":"GB",
    "sg:address":"2 Crantock Street",
    "sg:city":"Newquay",
    "sg:classifiers":[
        {
            "category":"Shopping",
            "subcategory":"Bicycles & Sporting Goods",
            "type":"Retail Goods"
        },
        {
            "category":"Sports & Exercise",
            "subcategory":"Sports Center",
            "type":"Entertainment"
        }
    ],
    "sg:phone":"+44 1637 874101",
    "sg:postcode":"TR7 1JA",
    "sg:province":"Cornwall",
    "sg:tags":[
        "shop",
        "sale"
    ],
    "wof:name":"Newquay Sports Shop",
    "wof:placetype":"venue"
},
  "geometry": {"coordinates":[-5.087837,50.413185],"type":"Point"}
}