{
  "type": "Feature",
  "properties": {
    "iso:country":"GB",
    "sg:address":"Rear Of 10-14 Bromley Road",
    "sg:city":"Beckenham",
    "sg:classifiers":[
        {
            "category":"Retail",
            "subcategory":"Auto Repair",
            "type":"Services"
        }
    ],
    "sg:phone":"+44 20 8650 8986",
    "sg:postcode":"BR3 5JE",
    "sg:province":"Kent",
    "sg:tags":[
        "car",
        "servicing",
        "radiator"
    ],
    "wof:name":"South London Radiator Co",
    "wof:placetype":"venue"
},
  "geometry": {"coordinates":[-0.027835,51.407162],"type":"Point"}
}