{
  "type": "Feature",
  "properties": {
    "addr:full":"65 London Road Gloucester Gloucestershire GL1 3HF",
    "addr:housenumber":"65",
    "addr:postcode":"gl1 3hf",
    "addr:street":"London Road",
    "iso:country":"GB",
    "sg:address":"65 London Road",
    "sg:city":"Gloucester",
    "sg:classifiers":[
        {
            "category":"Professional",
            "subcategory":"Business Services",
            "type":"Services"
        }
    ],
    "sg:phone":"+44 1452 532424",
    "sg:postcode":"GL1 3HF",
    "sg:province":"Gloucestershire",
    "sg:tags":[
        "answering"
    ],
    "wof:name":"Message Link",
    "wof:placetype":"venue"
},
  "geometry": {"coordinates":[-2.235393,51.868271],"type":"Point"}
}