{
  "type": "Feature",
  "properties": {
    "iso:country":"GB",
    "sg:address":"Unit 10, Drewitt Ind Est",
    "sg:city":"Bournemouth",
    "sg:classifiers":[
        {
            "category":"Home & Garden",
            "subcategory":"Household Appliances",
            "type":"Retail Goods"
        }
    ],
    "sg:phone":"+44 1202 576511",
    "sg:postcode":"BH11 8LL",
    "sg:province":"Dorset",
    "sg:tags":[
        "refrigeration",
        "air conditioning"
    ],
    "wof:name":"Air-o-ducts Group of Companies",
    "wof:placetype":"venue"
},
  "geometry": {"coordinates":[-1.9279,50.756908],"type":"Point"}
}