{
  "type": "Feature",
  "properties": {
    "iso:country":"GB",
    "sg:address":"The Works, Middlewood Road, High Lane",
    "sg:city":"Stockport",
    "sg:classifiers":[
        {
            "category":"Retail",
            "subcategory":"Auto Repair",
            "type":"Services"
        }
    ],
    "sg:postcode":"SK6 8AU",
    "sg:province":"Cheshire",
    "sg:tags":[
        "modification",
        "garage"
    ],
    "wof:name":"D J Nelson",
    "wof:placetype":"venue"
},
  "geometry": {"coordinates":[-2.068597,53.364067],"type":"Point"}
}