{
  "type": "Feature",
  "properties": {
    "addr:full":"4 Station Buildings, Blackwood Road Blackwood Caerphilly NP12 2BS",
    "addr:housenumber":"4",
    "addr:postcode":"np12 2bs",
    "addr:street":"Station Buildings Blackwood Road",
    "iso:country":"GB",
    "sg:address":"4 Station Buildings, Blackwood Road",
    "sg:city":"Blackwood",
    "sg:classifiers":[
        {
            "category":"Fast Food",
            "type":"Food & Drink"
        }
    ],
    "sg:phone":"+44 1495 224306",
    "sg:postcode":"NP12 2BS",
    "sg:province":"Caerphilly",
    "sg:tags":[
        "away",
        "take"
    ],
    "wof:name":"Wong's",
    "wof:placetype":"venue"
},
  "geometry": {"coordinates":[-3.1956140995,51.6672744751],"type":"Point"}
}