{
  "type": "Feature",
  "properties": {
    "iso:country":"GB",
    "sg:address":"67 The Strand, Longton",
    "sg:city":"Stoke-on-trent",
    "sg:classifiers":[
        {
            "category":"Shopping",
            "subcategory":"Music",
            "type":"Retail Goods"
        }
    ],
    "sg:phone":"+44 1782 312178",
    "sg:postcode":"ST3 2NS",
    "sg:province":"Staffordshire",
    "sg:tags":[
        "record",
        "tape",
        "cd"
    ],
    "wof:name":"Bevan's Sound Centre",
    "wof:placetype":"venue"
},
  "geometry": {"coordinates":[-2.136797905,52.9875335693],"type":"Point"}
}