{
  "type": "Feature",
  "properties": {
    "addr:full":"336 Green Lane Walsall West Midlands WS2 8HH",
    "addr:housenumber":"336",
    "addr:postcode":"ws2 8hh",
    "addr:street":"Green Lane",
    "iso:country":"GB",
    "sg:address":"336 Green Lane",
    "sg:city":"Walsall",
    "sg:classifiers":[
        {
            "category":"Bars & Pubs",
            "type":"Food & Drink"
        }
    ],
    "sg:phone":"+44 1922 645758",
    "sg:postcode":"WS2 8HH",
    "sg:province":"West Midlands",
    "sg:tags":[
        "pubs",
        "inn"
    ],
    "wof:name":"The Oak Inn",
    "wof:placetype":"venue"
},
  "geometry": {"coordinates":[-1.985834,52.587006],"type":"Point"}
}