{
  "type": "Feature",
  "properties": {
    "iso:country":"GB",
    "sg:address":"High St, Nutley",
    "sg:city":"Uckfield",
    "sg:classifiers":[
        {
            "category":"Autos & Motor Vehicles",
            "subcategory":"Automobile Sales",
            "type":"Retail Goods"
        }
    ],
    "sg:postcode":"TN22 3NN",
    "sg:province":"East Sussex",
    "sg:tags":[
        "car"
    ],
    "wof:name":"Kirk,Lyn,",
    "wof:placetype":"venue"
},
  "geometry": {"coordinates":[0.0551650003,51.0344047546],"type":"Point"}
}