{
  "type": "Feature",
  "properties": {
    "iso:country":"GB",
    "sg:address":"77 Carholme Road",
    "sg:city":"Lincoln",
    "sg:classifiers":[
        {
            "category":"Health Services",
            "subcategory":"Nursing And Care Facility",
            "type":"Services"
        }
    ],
    "sg:phone":"+44 1522 534032",
    "sg:postcode":"LN1 1RT",
    "sg:province":"Lincolnshire",
    "sg:tags":[
        "home"
    ],
    "wof:name":"St. Dominics",
    "wof:placetype":"venue"
},
  "geometry": {"coordinates":[-0.5523710251,53.2320213318],"type":"Point"}
}