{
  "type": "Feature",
  "properties": {
    "addr:full":"9 Argyle St Northampton Northamptonshire NN5 5LJ",
    "addr:housenumber":"9",
    "addr:postcode":"nn5 5lj",
    "addr:street":"Argyle St",
    "iso:country":"GB",
    "sg:address":"9 Argyle St",
    "sg:city":"Northampton",
    "sg:classifiers":[
        {
            "category":"Shopping",
            "subcategory":"Department Store",
            "type":"Retail Goods"
        }
    ],
    "sg:phone":"+44 1604 754079",
    "sg:postcode":"NN5 5LJ",
    "sg:province":"Northamptonshire",
    "wof:name":"Milu's",
    "wof:placetype":"venue"
},
  "geometry": {"coordinates":[-0.916777,52.241467],"type":"Point"}
}