{
  "type": "Feature",
  "properties": {
    "iso:country":"GB",
    "sg:address":"166 Solly Street",
    "sg:city":"Sheffield",
    "sg:classifiers":[
        {
            "category":"Manufacturing",
            "subcategory":"Tools & Machinery",
            "type":"Manufacturing & Wholesale Goods"
        }
    ],
    "sg:phone":"+44 114 272 3149",
    "sg:postcode":"S1 4BB",
    "sg:province":"South Yorkshire",
    "wof:name":"F E W Tools Ltd.",
    "wof:placetype":"venue"
},
  "geometry": {"coordinates":[-1.4781559706,53.3845062256],"type":"Point"}
}