{
  "type": "Feature",
  "properties": {
    "addr:full":"1 School Cotts, Raydon Ipswich Suffolk IP7 5LL",
    "addr:housenumber":"1;cotts",
    "addr:postcode":"ip7 5ll",
    "addr:street":"School",
    "iso:country":"GB",
    "sg:address":"1 School Cotts, Raydon",
    "sg:city":"Ipswich",
    "sg:classifiers":[
        {
            "category":"Building & Trades",
            "subcategory":"Pest Control",
            "type":"Services"
        }
    ],
    "sg:postcode":"IP7 5LL",
    "sg:province":"Suffolk",
    "sg:tags":[
        "vermin"
    ],
    "wof:name":"Laurie & Partners",
    "wof:placetype":"venue"
},
  "geometry": {"coordinates":[0.963235,52.043434],"type":"Point"}
}