{
  "type": "Feature",
  "properties": {
    "addr:full":"17g Vyse St Birmingham West Midlands B18 6LE",
    "addr:housenumber":"17g",
    "addr:postcode":"b18 6le",
    "addr:street":"Vyse St",
    "iso:country":"GB",
    "sg:address":"17g Vyse St",
    "sg:city":"Birmingham",
    "sg:classifiers":[
        {
            "category":"Professional",
            "subcategory":"Art Services",
            "type":"Services"
        }
    ],
    "sg:postcode":"B18 6LE",
    "sg:province":"West Midlands",
    "sg:tags":[
        "model",
        "maker"
    ],
    "wof:name":"Birbeck,Robert W,",
    "wof:placetype":"venue"
},
  "geometry": {"coordinates":[-1.912865,52.488777],"type":"Point"}
}