{
  "type": "Feature",
  "properties": {
    "iso:country":"GB",
    "sg:address":"Unit 8 Ironside Way, Hingham",
    "sg:city":"Norwich",
    "sg:classifiers":[
        {
            "category":"Manufacturing",
            "subcategory":"Metals",
            "type":"Manufacturing & Wholesale Goods"
        }
    ],
    "sg:postcode":"NR9 4LF",
    "sg:province":"Norfolk",
    "sg:tags":[
        "work",
        "sheet"
    ],
    "wof:name":"Dave Tyler Engineering",
    "wof:placetype":"venue"
},
  "geometry": {"coordinates":[0.9980400205,52.5805702209],"type":"Point"}
}