{
  "type": "Feature",
  "properties": {
    "iso:country":"GB",
    "sg:address":"79 Broadmead, Killay",
    "sg:city":"Swansea",
    "sg:classifiers":[
        {
            "category":"Professional",
            "subcategory":"Art Services",
            "type":"Services"
        }
    ],
    "sg:postcode":"SA2 7EJ",
    "sg:province":"Swansea",
    "sg:tags":[
        "photographer"
    ],
    "wof:name":"John Fry",
    "wof:placetype":"venue"
},
  "geometry": {"coordinates":[-4.02983,51.620064],"type":"Point"}
}