{
  "type": "Feature",
  "properties": {
    "iso:country":"GB",
    "sg:address":"30 Wellington Street",
    "sg:city":"Luton",
    "sg:classifiers":[
        {
            "category":"Retail",
            "subcategory":"Laundry & Dry Cleaning",
            "type":"Services"
        }
    ],
    "sg:phone":"+44 1582 454018",
    "sg:postcode":"LU1 2QH",
    "sg:province":"Bedfordshire",
    "sg:tags":[
        "alteration"
    ],
    "wof:name":"Five Star Dry Cleaners",
    "wof:placetype":"venue"
},
  "geometry": {"coordinates":[-0.418503,51.878841],"type":"Point"}
}