{
  "type": "Feature",
  "properties": {
    "iso:country":"GB",
    "sg:address":"53 Wimpole St",
    "sg:city":"West End",
    "sg:classifiers":[
        {
            "category":"Health Services",
            "subcategory":"Dentist",
            "type":"Services"
        }
    ],
    "sg:phone":"+44 20 7935 6809",
    "sg:postcode":"W1M 7DF",
    "sg:province":"Hampshire",
    "wof:name":"Lord Colwyn",
    "wof:placetype":"venue"
},
  "geometry": {"coordinates":[-0.149021,51.519501],"type":"Point"}
}