{
  "type": "Feature",
  "properties": {
    "iso:country":"GB",
    "sg:address":"11 The Crescent",
    "sg:city":"Taunton",
    "sg:classifiers":[
        {
            "category":"Farming",
            "subcategory":"Fish & Marine Products",
            "type":"Manufacturing & Wholesale Goods"
        }
    ],
    "sg:postcode":"TA1 4DS",
    "sg:province":"Somerset",
    "sg:tags":[
        "fisherman"
    ],
    "wof:name":"Spurtham Fishery Ltd.",
    "wof:placetype":"venue"
},
  "geometry": {"coordinates":[-3.1056609154,51.013053894],"type":"Point"}
}