{
  "type": "Feature",
  "properties": {
    "addr:full":"10 Fairfax Road Kidlington Buckinghamshire OX5 2PF",
    "addr:housenumber":"10",
    "addr:postcode":"ox5 2pf",
    "addr:street":"Fairfax Road",
    "iso:country":"GB",
    "sg:address":"10 Fairfax Road",
    "sg:city":"Kidlington",
    "sg:classifiers":[
        {
            "category":"Government",
            "subcategory":"Post Office",
            "type":"Public Place"
        }
    ],
    "sg:postcode":"OX5 2PF",
    "sg:province":"Buckinghamshire",
    "sg:tags":[
        "messenger",
        "courier"
    ],
    "wof:name":"John R Clarke",
    "wof:placetype":"venue"
},
  "geometry": {"coordinates":[-1.2786730528,51.8119125366],"type":"Point"}
}