{
  "type": "Feature",
  "properties": {
    "addr:full":"524-528 Burton Road, Littleover Derby Derbyshire DE23 6FN",
    "addr:housenumber":"524-528",
    "addr:postcode":"de23 6fn",
    "addr:street":"Burton Road",
    "iso:country":"GB",
    "sg:address":"524-528 Burton Road, Littleover",
    "sg:city":"Derby",
    "sg:classifiers":[
        {
            "category":"Fast Food",
            "type":"Food & Drink"
        },
        {
            "category":"Restaurant",
            "type":"Food & Drink"
        }
    ],
    "sg:phone":"+44 1332 299552",
    "sg:postcode":"DE23 6FN",
    "sg:province":"Derbyshire",
    "sg:tags":[
        "away",
        "-",
        "take",
        "chinese"
    ],
    "wof:name":"Zing Vaa Restaurant",
    "wof:placetype":"venue"
},
  "geometry": {"coordinates":[-1.5026949644,52.9073181152],"type":"Point"}
}