{
  "type": "Feature",
  "properties": {
    "addr:full":"4 Queens Parade Walsall Staffordshire WS3 2EX",
    "addr:housenumber":"4",
    "addr:postcode":"ws3 2ex",
    "addr:street":"Queens Parade",
    "iso:country":"GB",
    "sg:address":"4 Queens Parade",
    "sg:city":"Walsall",
    "sg:classifiers":[
        {
            "category":"Health Services",
            "subcategory":"Optometrist",
            "type":"Services"
        }
    ],
    "sg:phone":"+44 1922 409000",
    "sg:postcode":"WS3 2EX",
    "sg:province":"Staffordshire",
    "sg:tags":[
        "optician"
    ],
    "wof:name":"Kelcher & Pearson (Opticians) Ltd.",
    "wof:placetype":"venue"
},
  "geometry": {"coordinates":[-1.956685,52.570534],"type":"Point"}
}