{
  "type": "Feature",
  "properties": {
    "addr:full":"Gun Court 70 Wapping Lane London Greater London E1 9RL",
    "addr:housenumber":"70",
    "addr:postcode":"e1 9rl",
    "addr:street":"Wapping Lane",
    "iso:country":"GB",
    "sg:address":"Gun Court 70 Wapping Lane",
    "sg:city":"London",
    "sg:classifiers":[
        {
            "category":"Organizations",
            "subcategory":"Membership Organization",
            "type":"Services"
        }
    ],
    "sg:postcode":"E1 9RL",
    "sg:province":"Greater London",
    "sg:tags":[
        "club"
    ],
    "wof:name":"Creek House Residents' Association Ltd.",
    "wof:placetype":"venue"
},
  "geometry": {"coordinates":[-0.05756,51.504692],"type":"Point"}
}