{
  "type": "Feature",
  "properties": {
    "addr:full":"Unit 3 Norparc, Colomendy Industrial Estate Denbigh Conwy LL16 5TA",
    "addr:housenumber":"unit 3",
    "addr:postcode":"ll16 5ta",
    "addr:street":"Industrial Estate",
    "iso:country":"GB",
    "sg:address":"Unit 3 Norparc, Colomendy Industrial Estate",
    "sg:city":"Denbigh",
    "sg:classifiers":[
        {
            "category":"Professional",
            "subcategory":"Advertising",
            "type":"Services"
        },
        {
            "category":"Manufacturing",
            "subcategory":"Signs",
            "type":"Manufacturing & Wholesale Goods"
        }
    ],
    "sg:phone":"+44 1745 817294",
    "sg:postcode":"LL16 5TA",
    "sg:province":"Conwy",
    "sg:tags":[
        "commercial",
        "maker",
        "signwriters"
    ],
    "wof:name":"P R Signs & Graphics",
    "wof:placetype":"venue"
},
  "geometry": {"coordinates":[-3.4211490154,53.1834106445],"type":"Point"}
}