{
  "type": "Feature",
  "properties": {
    "addr:full":"31 Station Road, Penshaw Houghton-le-spring Durham DH4 7PF",
    "addr:housenumber":"31",
    "addr:postcode":"dh4 7pf",
    "addr:street":"Station Road",
    "iso:country":"GB",
    "sg:address":"31 Station Road, Penshaw",
    "sg:city":"Houghton-le-spring",
    "sg:classifiers":[
        {
            "category":"Government",
            "subcategory":"Post Office",
            "type":"Public Place"
        }
    ],
    "sg:postcode":"DH4 7PF",
    "sg:province":"Durham",
    "wof:name":"New Penshaw Post Office",
    "wof:placetype":"venue"
},
  "geometry": {"coordinates":[-1.501495,54.87125],"type":"Point"}
}