{
  "type": "Feature",
  "properties": {
    "addr:full":"Banbeath Industrial Estate Leven Fife KY8 5HD",
    "addr:housenumber":"estate",
    "addr:postcode":"ky8 5hd",
    "addr:street":"Leven",
    "iso:country":"GB",
    "sg:address":"Banbeath Industrial Estate",
    "sg:city":"Leven",
    "sg:classifiers":[
        {
            "category":"Shopping",
            "subcategory":"Computers & Home Electronics",
            "type":"Retail Goods"
        }
    ],
    "sg:postcode":"KY8 5HD",
    "sg:province":"Fife",
    "wof:name":"Scotfoil Services",
    "wof:placetype":"venue"
},
  "geometry": {"coordinates":[-3.050124,56.203762],"type":"Point"}
}