{
  "type": "Feature",
  "properties": {
    "addr:full":"Bath Road Chippenham Gloucestershire SN14 0AB",
    "addr:postcode":"sn14 0ab",
    "addr:street":"Bath Road",
    "iso:country":"GB",
    "sg:address":"Bath Road",
    "sg:city":"Chippenham",
    "sg:classifiers":[
        {
            "category":"Professional",
            "subcategory":"Engineering",
            "type":"Services"
        }
    ],
    "sg:phone":"+44 1249 653705",
    "sg:postcode":"SN14 0AB",
    "sg:province":"Gloucestershire",
    "sg:tags":[
        "civil",
        "engineer"
    ],
    "wof:name":"Prangle & Carey Ltd.",
    "wof:placetype":"venue"
},
  "geometry": {"coordinates":[-2.1423339844,51.448677063],"type":"Point"}
}