{
  "type": "Feature",
  "properties": {
    "addr:full":"5 Sandfield Road Rochdale Lancashire OL16 5LE",
    "addr:housenumber":"5",
    "addr:postcode":"ol16 5le",
    "addr:street":"Sandfield Road",
    "iso:country":"GB",
    "sg:address":"5 Sandfield Road",
    "sg:city":"Rochdale",
    "sg:classifiers":[
        {
            "category":"Professional",
            "subcategory":"Engineering",
            "type":"Services"
        }
    ],
    "sg:phone":"+44 1706 341070",
    "sg:postcode":"OL16 5LE",
    "sg:province":"Lancashire",
    "sg:tags":[
        "contractor",
        "electrical",
        "engineer"
    ],
    "wof:name":"G Buckley",
    "wof:placetype":"venue"
},
  "geometry": {"coordinates":[-2.1423020363,53.6070518494],"type":"Point"}
}