{
  "type": "Feature",
  "properties": {
    "addr:full":"Little North Fen Farm, Rampton Road, Cottenham Cambridge Cambridgeshire CB4 8PZ",
    "addr:postcode":"cb4 8pz",
    "addr:street":"Fen;Rampton Road",
    "iso:country":"GB",
    "sg:address":"Little North Fen Farm, Rampton Road, Cottenham",
    "sg:city":"Cambridge",
    "sg:classifiers":[
        {
            "category":"Home & Garden",
            "subcategory":"Garden Supply",
            "type":"Retail Goods"
        },
        {
            "category":"Farming",
            "subcategory":"Livestock Farm",
            "type":"Manufacturing & Wholesale Goods"
        }
    ],
    "sg:postcode":"CB4 8PZ",
    "sg:province":"Cambridgeshire",
    "sg:tags":[
        "bulb",
        "grower",
        "others"
    ],
    "wof:name":"J B T Benton & Son",
    "wof:placetype":"venue"
},
  "geometry": {"coordinates":[0.126215,52.286472],"type":"Point"}
}