{
  "type": "Feature",
  "properties": {
    "iso:country":"GB",
    "sg:address":"359a Edgware Road",
    "sg:city":"London",
    "sg:classifiers":[
        {
            "category":"Professional",
            "subcategory":"Detective & Security Services",
            "type":"Services"
        }
    ],
    "sg:phone":"+44 20 7402 1359",
    "sg:postcode":"W2 1BS",
    "sg:province":"Greater London",
    "sg:tags":[
        "agency"
    ],
    "wof:name":"Michael P Horsburgh",
    "wof:placetype":"venue"
},
  "geometry": {"coordinates":[-0.1734990031,51.5222129822],"type":"Point"}
}