{
  "type": "Feature",
  "properties": {
    "iso:country":"GB",
    "sg:address":"Lockinge",
    "sg:city":"Wantage",
    "sg:classifiers":[
        {
            "category":"Place Of Worship",
            "type":"Public Place"
        }
    ],
    "sg:phone":"+44 1235 833235",
    "sg:postcode":"OX12 0LG",
    "sg:province":"Berkshire",
    "wof:name":"All Saints C of E Church",
    "wof:placetype":"venue"
},
  "geometry": {"coordinates":[-1.437279,51.611851],"type":"Point"}
}