{
  "type": "Feature",
  "properties": {
    "addr:full":"6 Marion Road Southsea Hampshire PO4 0QX",
    "addr:housenumber":"6",
    "addr:postcode":"po4 0qx",
    "addr:street":"Marion Road",
    "iso:country":"GB",
    "sg:address":"6 Marion Road",
    "sg:city":"Southsea",
    "sg:classifiers":[
        {
            "category":"Social Services",
            "subcategory":"Retirement Home",
            "type":"Services"
        }
    ],
    "sg:postcode":"PO4 0QX",
    "sg:province":"Hampshire",
    "sg:tags":[
        "rest"
    ],
    "wof:name":"Bronte Rest Home",
    "wof:placetype":"venue"
},
  "geometry": {"coordinates":[-1.073987,50.782505],"type":"Point"}
}