{
  "type": "Feature",
  "properties": {
    "iso:country":"GB",
    "sg:address":"73 Maygrove Rd",
    "sg:city":"Kilburn",
    "sg:classifiers":[
        {
            "category":"Shopping",
            "type":"Retail Goods"
        }
    ],
    "sg:phone":"+44 20 7328 1551",
    "sg:postcode":"NW6 2EG",
    "sg:province":"Greater London",
    "sg:tags":[
        "scientific",
        "apparatus"
    ],
    "wof:name":"Scientific Laboratory Supplies Ltd",
    "wof:placetype":"venue"
},
  "geometry": {"coordinates":[-0.196808,51.548054],"type":"Point"}
}