{
  "type": "Feature",
  "properties": {
    "addr:full":"Middle Road, Coedpoeth Wrexham Wrexham LL11 3TN",
    "addr:postcode":"ll11 3tn",
    "addr:street":"Middle Road",
    "iso:country":"GB",
    "sg:address":"Middle Road, Coedpoeth",
    "sg:city":"Wrexham",
    "sg:classifiers":[
        {
            "category":"Home & Garden",
            "subcategory":"Carpets & Floor Coverings",
            "type":"Retail Goods"
        }
    ],
    "sg:phone":"+44 1978 751771",
    "sg:postcode":"LL11 3TN",
    "sg:province":"Wrexham",
    "sg:tags":[
        "cleaner",
        "upholstery"
    ],
    "wof:name":"Tony Sinnett",
    "wof:placetype":"venue"
},
  "geometry": {"coordinates":[-3.0703039169,53.0532646179],"type":"Point"}
}