{
  "type": "Feature",
  "properties": {
    "addr:full":"165 High Street, Chasetown Burntwood Staffordshire WS7 8XL",
    "addr:housenumber":"165",
    "addr:postcode":"ws7 8xl",
    "addr:street":"High Street",
    "iso:country":"GB",
    "sg:address":"165 High Street, Chasetown",
    "sg:city":"Burntwood",
    "sg:classifiers":[
        {
            "category":"Building & Trades",
            "subcategory":"Construction",
            "type":"Services"
        }
    ],
    "sg:phone":"+44 1543 686234",
    "sg:postcode":"WS7 8XL",
    "sg:province":"Staffordshire",
    "sg:tags":[
        "builder"
    ],
    "wof:name":"Building & Reclamation Supplies by Maddox",
    "wof:placetype":"venue"
},
  "geometry": {"coordinates":[-1.9342509508,52.6763114929],"type":"Point"}
}