{
  "type": "Feature",
  "properties": {
    "iso:country":"GB",
    "sg:address":"15 Manor Road, Grendon",
    "sg:city":"Northampton",
    "sg:classifiers":[
        {
            "category":"Professional",
            "subcategory":"Engineering",
            "type":"Services"
        },
        {
            "category":"Professional",
            "subcategory":"Detective & Security Services",
            "type":"Services"
        }
    ],
    "sg:phone":"+44 1933 664224",
    "sg:postcode":"NN7 1JF",
    "sg:province":"Buckinghamshire",
    "sg:tags":[
        "civil",
        "engineer"
    ],
    "sg:website":"http://www.grendon.co.uk",
    "wof:name":"Grendon Design Agency Ltd",
    "wof:placetype":"venue"
},
  "geometry": {"coordinates":[-0.715909,52.233208],"type":"Point"}
}