{
  "type": "Feature",
  "properties": {
    "iso:country":"GB",
    "sg:address":"55 Eastfield Road, Fauldhouse",
    "sg:city":"Bathgate",
    "sg:classifiers":[
        {
            "category":"Shopping",
            "subcategory":"Party Supplies",
            "type":"Retail Goods"
        }
    ],
    "sg:postcode":"EH47 9LE",
    "sg:province":"North Lanarkshire",
    "sg:tags":[
        "plan",
        "agent"
    ],
    "wof:name":"Ann Summers",
    "wof:placetype":"venue"
},
  "geometry": {"coordinates":[-3.7001619339,55.8319244385],"type":"Point"}
}