{
  "type": "Feature",
  "properties": {
    "addr:full":"101 Roe Lane Southport Lancashire PR9 7PD",
    "addr:housenumber":"101",
    "addr:postcode":"pr9 7pd",
    "addr:street":"Roe Lane",
    "iso:country":"GB",
    "sg:address":"101 Roe Lane",
    "sg:city":"Southport",
    "sg:classifiers":[
        {
            "category":"Health Services",
            "subcategory":"Nursing And Care Facility",
            "type":"Services"
        },
        {
            "category":"Social Services",
            "subcategory":"Retirement Home",
            "type":"Services"
        }
    ],
    "sg:phone":"+44 1704 227030",
    "sg:postcode":"PR9 7PD",
    "sg:province":"Lancashire",
    "sg:tags":[
        "residential"
    ],
    "wof:name":"Peacehaven House Ltd",
    "wof:placetype":"venue"
},
  "geometry": {"coordinates":[-2.9717540741,53.6535835266],"type":"Point"}
}