{
  "type": "Feature",
  "properties": {
    "addr:full":"Cottage 4 Newhall Campus, Longmoor Lane Liverpool Merseyside L10 1LD",
    "addr:housenumber":"4",
    "addr:postcode":"l10 1ld",
    "addr:street":"Newhall Campus Longmoor Lane",
    "iso:country":"GB",
    "sg:address":"Cottage 4 Newhall Campus, Longmoor Lane",
    "sg:city":"Liverpool",
    "sg:classifiers":[
        {
            "category":"Organizations",
            "subcategory":"Non-profit Organization",
            "type":"Services"
        }
    ],
    "sg:phone":"+44 151 521 7569",
    "sg:postcode":"L10 1LD",
    "sg:province":"Merseyside",
    "sg:tags":[
        "organisation",
        "voluntary",
        "charity"
    ],
    "wof:name":"Fazakerley Special Needs Projects",
    "wof:placetype":"venue"
},
  "geometry": {"coordinates":[-2.978481,53.409775],"type":"Point"}
}