{
  "type": "Feature",
  "properties": {
    "addr:full":"80 Wimpole Street London Greater London W1G 9RE",
    "addr:housenumber":"80",
    "addr:postcode":"w1g 9re",
    "addr:street":"Wimpole Street",
    "iso:country":"GB",
    "sg:address":"80 Wimpole Street",
    "sg:city":"London",
    "sg:classifiers":[
        {
            "category":"Professional",
            "subcategory":"Management & Consulting",
            "type":"Services"
        }
    ],
    "sg:phone":"+44 20 7487 5776",
    "sg:postcode":"W1G 9RE",
    "sg:province":"Greater London",
    "sg:tags":[
        "consultant",
        "business"
    ],
    "wof:name":"Personnel Decisions International U K Ltd.",
    "wof:placetype":"venue"
},
  "geometry": {"coordinates":[-0.147897,51.517113],"type":"Point"}
}