{
  "type": "Feature",
  "properties": {
    "iso:country":"GB",
    "sg:address":"Mount Pleasant M O T Centre, Ninfield Road",
    "sg:city":"Bexhill-on-sea",
    "sg:classifiers":[
        {
            "category":"Professional",
            "subcategory":"Testing Lab",
            "type":"Services"
        }
    ],
    "sg:phone":"+44 1424 893344",
    "sg:postcode":"TN39 5JG",
    "sg:province":"East Sussex",
    "sg:tags":[
        "mot"
    ],
    "wof:name":"Mount Pleasant M O T Centre",
    "wof:placetype":"venue"
},
  "geometry": {"coordinates":[0.44969,50.86684],"type":"Point"}
}