{
  "type": "Feature",
  "properties": {
    "addr:full":"10 The Parade, Bournemouth Road, Chandlers Ford Southampton Hampshire SO53 3DB",
    "addr:housenumber":"10",
    "addr:postcode":"so53 3db",
    "addr:street":"The Parade Bournemouth Road",
    "iso:country":"GB",
    "sg:address":"10 The Parade, Bournemouth Road, Chandlers Ford",
    "sg:city":"Southampton",
    "sg:classifiers":[
        {
            "category":"Health Services",
            "subcategory":"Optometrist",
            "type":"Services"
        }
    ],
    "sg:phone":"+44 23 8025 2428",
    "sg:postcode":"SO53 3DB",
    "sg:province":"Hampshire",
    "sg:tags":[
        "optician"
    ],
    "wof:name":"Rawling & Sons (Opticians) Ltd.",
    "wof:placetype":"venue"
},
  "geometry": {"coordinates":[-1.38402,50.98204],"type":"Point"}
}