{
  "type": "Feature",
  "properties": {
    "addr:full":"High St Newpits, Sligo Peterhead Aberdeenshire AB42 5EE",
    "addr:postcode":"ab42 5ee",
    "addr:street":"High St Newpits",
    "iso:country":"GB",
    "sg:address":"High St Newpits, Sligo",
    "sg:city":"Peterhead",
    "sg:classifiers":[
        {
            "category":"Government",
            "subcategory":"Office",
            "type":"Public Place"
        }
    ],
    "sg:phone":"+44 1771 653465",
    "sg:postcode":"AB42 5EE",
    "sg:province":"Aberdeenshire",
    "sg:tags":[
        "education",
        "agency",
        "authority"
    ],
    "wof:name":"St.Johns Education Centre",
    "wof:placetype":"venue"
},
  "geometry": {"coordinates":[-2.00671,57.525169],"type":"Point"}
}