{
  "type": "Feature",
  "properties": {
    "iso:country":"GB",
    "sg:address":"463 Lichfield Rd",
    "sg:city":"Sutton Coldfield",
    "sg:classifiers":[
        {
            "category":"Health Services",
            "subcategory":"Nursing And Care Facility",
            "type":"Services"
        }
    ],
    "sg:phone":"+44 121 308 2585",
    "sg:postcode":"B74 4DJ",
    "sg:province":"Staffordshire",
    "sg:tags":[
        "home"
    ],
    "wof:name":"Vahron House Residential Home",
    "wof:placetype":"venue"
},
  "geometry": {"coordinates":[-1.837552,52.595108],"type":"Point"}
}