{
  "type": "Feature",
  "properties": {
    "iso:country":"GB",
    "sg:address":"74 Church Road, Alphington",
    "sg:city":"Exeter",
    "sg:classifiers":[
        {
            "category":"Bars & Pubs",
            "type":"Food & Drink"
        }
    ],
    "sg:phone":"+44 1392 272584",
    "sg:postcode":"EX2 8TA",
    "sg:province":"Devon",
    "sg:tags":[
        "pubs",
        "inn"
    ],
    "wof:name":"The New Inn",
    "wof:placetype":"venue"
},
  "geometry": {"coordinates":[-3.5337560177,50.6998329163],"type":"Point"}
}