{
  "type": "Feature",
  "properties": {
    "iso:country":"GB",
    "sg:address":"262a Chillingham Road",
    "sg:city":"Newcastle-upon-tyne",
    "sg:classifiers":[
        {
            "category":"Professional",
            "subcategory":"Lawyer & Legal Services",
            "type":"Services"
        }
    ],
    "sg:phone":"+44 191 276 5300",
    "sg:postcode":"NE6 5LQ",
    "sg:province":"Tyne and Wear",
    "sg:tags":[
        "solicitor"
    ],
    "wof:name":"Richard Haswell & Co",
    "wof:placetype":"venue"
},
  "geometry": {"coordinates":[-1.577036,54.987427],"type":"Point"}
}