{
  "type": "Feature",
  "properties": {
    "iso:country":"GB",
    "sg:address":"The Forum Centre, Northgate Street",
    "sg:city":"Chester",
    "sg:classifiers":[
        {
            "category":"Food & Beverages",
            "subcategory":"Candy",
            "type":"Retail Goods"
        }
    ],
    "sg:phone":"+44 1244 313017",
    "sg:postcode":"CH1 2HQ",
    "sg:province":"Cheshire",
    "sg:tags":[
        "merchant",
        "produce"
    ],
    "wof:name":"Julian Graves Ltd.",
    "wof:placetype":"venue"
},
  "geometry": {"coordinates":[-2.894369,53.188129],"type":"Point"}
}