{
  "type": "Feature",
  "properties": {
    "addr:full":"Wireless Hill, South Luffenham Oakham Leicestershire LE15 8NF",
    "addr:postcode":"le15 8nf",
    "addr:street":"Wireless",
    "iso:country":"GB",
    "sg:address":"Wireless Hill, South Luffenham",
    "sg:city":"Oakham",
    "sg:classifiers":[
        {
            "category":"Professional",
            "subcategory":"Business Services",
            "type":"Services"
        }
    ],
    "sg:phone":"+44 1780 720133",
    "sg:postcode":"LE15 8NF",
    "sg:province":"Leicestershire",
    "sg:tags":[
        "distribution"
    ],
    "wof:name":"C S Ellis (Group) Ltd.",
    "wof:placetype":"venue"
},
  "geometry": {"coordinates":[-0.609858,52.605846],"type":"Point"}
}