{
  "type": "Feature",
  "properties": {
    "addr:full":"87 Gloucester Place London Greater London W1U 6JF",
    "addr:housenumber":"87",
    "addr:postcode":"w1u 6jf",
    "addr:street":"Gloucester Place",
    "iso:country":"GB",
    "sg:address":"87 Gloucester Place",
    "sg:city":"London",
    "sg:classifiers":[
        {
            "category":"Travel",
            "subcategory":"Hotels & Motels",
            "type":"Entertainment"
        }
    ],
    "sg:phone":"+44 20 7935 2211",
    "sg:postcode":"W1U 6JF",
    "sg:province":"Greater London",
    "wof:name":"Gladbrook Ltd.",
    "wof:placetype":"venue"
},
  "geometry": {"coordinates":[-0.1590089947,51.5190010071],"type":"Point"}
}