{
  "type": "Feature",
  "properties": {
    "addr:full":"61 Market Place Thirsk North Yorkshire YO7 1EY",
    "addr:housenumber":"61",
    "addr:postcode":"yo7 1ey",
    "addr:street":"Market Place",
    "iso:country":"GB",
    "sg:address":"61 Market Place",
    "sg:city":"Thirsk",
    "sg:classifiers":[
        {
            "category":"Home & Garden",
            "subcategory":"Hardware",
            "type":"Retail Goods"
        }
    ],
    "sg:postcode":"YO7 1EY",
    "sg:province":"North Yorkshire",
    "wof:name":"Woolens & Harwoods",
    "wof:placetype":"venue"
},
  "geometry": {"coordinates":[-1.3427540064,54.232624054],"type":"Point"}
}