{
  "type": "Feature",
  "properties": {
    "iso:country":"GB",
    "sg:address":"Caroline St",
    "sg:city":"Stoke On Trent",
    "sg:classifiers":[
        {
            "category":"Shopping",
            "subcategory":"Crafts & Fabrics",
            "type":"Retail Goods"
        }
    ],
    "sg:phone":"+44 1782 594054",
    "sg:postcode":"ST3 1DB",
    "sg:province":"Staffordshire",
    "sg:tags":[
        "ceramic"
    ],
    "wof:name":"C H Rathbone & Son",
    "wof:placetype":"venue"
},
  "geometry": {"coordinates":[-2.1321260929,52.9906082153],"type":"Point"}
}