{
  "type": "Feature",
  "properties": {
    "addr:full":"Ton Farm Raglan Monmouthshire NP5 2JA",
    "addr:postcode":"np5 2ja",
    "addr:street":"Ton",
    "iso:country":"GB",
    "sg:address":"Ton Farm",
    "sg:city":"Raglan",
    "sg:classifiers":[
        {
            "category":"Farming",
            "subcategory":"Livestock Farm",
            "type":"Manufacturing & Wholesale Goods"
        }
    ],
    "sg:phone":"+44 1291 690496",
    "sg:postcode":"NP5 2JA",
    "sg:province":"Monmouthshire",
    "sg:tags":[
        "others"
    ],
    "wof:name":"B A Parry",
    "wof:placetype":"venue"
},
  "geometry": {"coordinates":[-2.90837,51.664867],"type":"Point"}
}