{
  "type": "Feature",
  "properties": {
    "iso:country":"GB",
    "sg:address":"19 Washway Road, Sale",
    "sg:city":"Manchester",
    "sg:classifiers":[
        {
            "category":"Professional",
            "subcategory":"Employment Agencies",
            "type":"Services"
        }
    ],
    "sg:phone":"+44 161 283 8383",
    "sg:postcode":"M33 7AD",
    "sg:province":"Cheshire",
    "sg:tags":[
        "consultant"
    ],
    "wof:name":"N E S Recruitment",
    "wof:placetype":"venue"
},
  "geometry": {"coordinates":[-2.3260600567,53.4246864319],"type":"Point"}
}