{
  "type": "Feature",
  "properties": {
    "iso:country":"GB",
    "sg:address":"Cornerpiece, Bagwell Lane, Winchfield",
    "sg:city":"Hook",
    "sg:classifiers":[
        {
            "category":"Building & Trades",
            "subcategory":"Construction",
            "type":"Services"
        }
    ],
    "sg:phone":"+44 1256 702480",
    "sg:postcode":"RG27 8DB",
    "sg:province":"Berkshire",
    "sg:tags":[
        "builder"
    ],
    "wof:name":"Blay Builders",
    "wof:placetype":"venue"
},
  "geometry": {"coordinates":[-0.9657189846,51.2813606262],"type":"Point"}
}