{
  "type": "Feature",
  "properties": {
    "iso:country":"GB",
    "sg:address":"Eyre Medical Practice, 31 Eyre Cres",
    "sg:city":"Edinburgh",
    "sg:classifiers":[
        {
            "category":"Health Services",
            "subcategory":"Doctor",
            "type":"Services"
        }
    ],
    "sg:phone":"+44 131 556 8842",
    "sg:postcode":"EH3 5EU",
    "sg:province":"City of Edinburgh",
    "sg:tags":[
        "practitioners"
    ],
    "wof:name":"Foster, K",
    "wof:placetype":"venue"
},
  "geometry": {"coordinates":[-3.19894,55.96172],"type":"Point"}
}