{
  "type": "Feature",
  "properties": {
    "addr:full":"7 Gorton Road, Reddish Stockport Cheshire SK5 6AZ",
    "addr:housenumber":"7",
    "addr:postcode":"sk5 6az",
    "addr:street":"Gorton Road",
    "iso:country":"GB",
    "sg:address":"7 Gorton Road, Reddish",
    "sg:city":"Stockport",
    "sg:classifiers":[
        {
            "category":"Travel",
            "subcategory":"Travel Agent",
            "type":"Entertainment"
        }
    ],
    "sg:phone":"+44 161 432 5700",
    "sg:postcode":"SK5 6AZ",
    "sg:province":"Cheshire",
    "wof:name":"Edward Mellor Holiday Shop",
    "wof:placetype":"venue"
},
  "geometry": {"coordinates":[-2.1599929333,53.4377098083],"type":"Point"}
}