{
  "type": "Feature",
  "properties": {
    "addr:full":"15 Union Street Newton Abbot Devon TQ12 2JX",
    "addr:housenumber":"15",
    "addr:postcode":"tq12 2jx",
    "addr:street":"Union Street",
    "iso:country":"GB",
    "sg:address":"15 Union Street",
    "sg:city":"Newton Abbot",
    "sg:classifiers":[
        {
            "category":"Banks & Credit Unions",
            "subcategory":"Financial Services",
            "type":"Services"
        }
    ],
    "sg:phone":"+44 1626 206073",
    "sg:postcode":"TQ12 2JX",
    "sg:province":"Devon",
    "sg:tags":[
        "adviser"
    ],
    "wof:name":"Castellan Asset Management Ltd.",
    "wof:placetype":"venue"
},
  "geometry": {"coordinates":[-3.609032,50.529755],"type":"Point"}
}