{
  "type": "Feature",
  "properties": {
    "iso:country":"GB",
    "sg:address":"Arch Unit 1139 Bath Factory Estate, 41 Norwood Road",
    "sg:city":"London",
    "sg:classifiers":[
        {
            "category":"Professional",
            "subcategory":"Printing & Photocopies",
            "type":"Services"
        }
    ],
    "sg:postcode":"SE24 9AJ",
    "sg:province":"Greater London",
    "sg:tags":[
        "computer",
        "tag",
        "label"
    ],
    "wof:name":"Fast Stik Labels",
    "wof:placetype":"venue"
},
  "geometry": {"coordinates":[-0.10094,51.451569],"type":"Point"}
}