{
  "type": "Feature",
  "properties": {
    "iso:country":"GB",
    "sg:address":"Paxton Street, Hanley",
    "sg:city":"Stoke-on-trent",
    "sg:classifiers":[
        {
            "category":"Wholesale",
            "subcategory":"Home Furnishings",
            "type":"Manufacturing & Wholesale Goods"
        }
    ],
    "sg:phone":"+44 1782 262848",
    "sg:postcode":"ST1 3SD",
    "sg:province":"Staffordshire",
    "sg:tags":[
        "wsale",
        "rug",
        "carpet"
    ],
    "wof:name":"A & K Wholesale Ltd.",
    "wof:placetype":"venue"
},
  "geometry": {"coordinates":[-2.1721789837,53.019153595],"type":"Point"}
}