{
  "type": "Feature",
  "properties": {
    "addr:full":"17a Boggs Holdings, Pencaitland Tranent East Lothian EH34 5BD",
    "addr:housenumber":"17a",
    "addr:postcode":"eh34 5bd",
    "addr:street":"Boggs Holdings",
    "iso:country":"GB",
    "sg:address":"17a Boggs Holdings, Pencaitland",
    "sg:city":"Tranent",
    "sg:classifiers":[
        {
            "category":"Transit Center",
            "subcategory":"Passenger",
            "type":"Transportation"
        }
    ],
    "sg:postcode":"EH34 5BD",
    "sg:province":"East Lothian",
    "sg:tags":[
        "boarding",
        "kennel",
        "catteries"
    ],
    "wof:name":"Paw Prints Cattery",
    "wof:placetype":"venue"
},
  "geometry": {"coordinates":[-2.8961689472,55.9100837708],"type":"Point"}
}