{
  "type": "Feature",
  "properties": {
    "addr:full":"25 Welling High Street Welling Kent DA16 1TR",
    "addr:housenumber":"25",
    "addr:postcode":"da16 1tr",
    "addr:street":"Welling High Street",
    "iso:country":"GB",
    "sg:address":"25 Welling High Street",
    "sg:city":"Welling",
    "sg:classifiers":[
        {
            "category":"Shopping",
            "subcategory":"News",
            "type":"Retail Goods"
        }
    ],
    "sg:phone":"+44 20 8303 0577",
    "sg:postcode":"DA16 1TR",
    "sg:province":"Kent",
    "sg:tags":[
        "newsagent"
    ],
    "wof:name":"Priya",
    "wof:placetype":"venue"
},
  "geometry": {"coordinates":[0.112089999,51.4620018005],"type":"Point"}
}