{
  "type": "Feature",
  "properties": {
    "addr:full":"Albany House, Whitecoats Lane Chesterfield Derbyshire S40 3HJ",
    "addr:postcode":"s40 3hj",
    "addr:street":"Whitecoats Lane",
    "iso:country":"GB",
    "sg:address":"Albany House, Whitecoats Lane",
    "sg:city":"Chesterfield",
    "sg:classifiers":[
        {
            "category":"Professional",
            "subcategory":"Detective & Security Services",
            "type":"Services"
        }
    ],
    "sg:phone":"+44 1246 276299",
    "sg:postcode":"S40 3HJ",
    "sg:province":"Derbyshire",
    "sg:tags":[
        "agency"
    ],
    "wof:name":"Albany Investigations Chesterfield",
    "wof:placetype":"venue"
},
  "geometry": {"coordinates":[-1.440418005,53.2230072021],"type":"Point"}
}