{
  "type": "Feature",
  "properties": {
    "addr:full":"Pensarn Trading Estate Abergele Conwy LL22 7PR",
    "addr:postcode":"ll22 7pr",
    "iso:country":"GB",
    "sg:address":"Pensarn Trading Estate",
    "sg:city":"Abergele",
    "sg:classifiers":[
        {
            "category":"Home & Garden",
            "subcategory":"Furniture",
            "type":"Retail Goods"
        }
    ],
    "sg:phone":"+44 1745 824720",
    "sg:postcode":"LL22 7PR",
    "sg:province":"Conwy",
    "wof:name":"Colour & Home Improvement Centres Ltd.",
    "wof:placetype":"venue"
},
  "geometry": {"coordinates":[-3.5811440945,53.2843551636],"type":"Point"}
}