{
  "type": "Feature",
  "properties": {
    "iso:country":"GB",
    "sg:address":"67-72 Titchfield Street",
    "sg:city":"Kilmarnock",
    "sg:classifiers":[
        {
            "category":"Professional",
            "subcategory":"Business Services",
            "type":"Services"
        }
    ],
    "sg:phone":"+44 1563 534463",
    "sg:postcode":"KA1 1QS",
    "sg:province":"East Ayrshire",
    "sg:tags":[
        "operator",
        "market"
    ],
    "wof:name":"Kilmarnock Indoor Market",
    "wof:placetype":"venue"
},
  "geometry": {"coordinates":[-4.497461,55.605335],"type":"Point"}
}