{
  "type": "Feature",
  "properties": {
    "iso:country":"GB",
    "sg:address":"118 Crag Road",
    "sg:city":"Shipley",
    "sg:classifiers":[
        {
            "category":"Personal",
            "subcategory":"Beauty Salon",
            "type":"Services"
        }
    ],
    "sg:postcode":"BD18 2ER",
    "sg:province":"West Yorkshire",
    "sg:tags":[
        "unisex",
        "hairdresser"
    ],
    "wof:name":"Curl Up & Di",
    "wof:placetype":"venue"
},
  "geometry": {"coordinates":[-1.772326,53.828266],"type":"Point"}
}