{
  "type": "Feature",
  "properties": {
    "iso:country":"GB",
    "sg:address":"23 Ribblesdale Avenue",
    "sg:city":"Corby",
    "sg:classifiers":[
        {
            "category":"Professional",
            "subcategory":"Detective & Security Services",
            "type":"Services"
        }
    ],
    "sg:phone":"+44 1536 403555",
    "sg:postcode":"NN17 1TH",
    "sg:province":"Northamptonshire",
    "wof:name":"Ages Security",
    "wof:placetype":"venue"
},
  "geometry": {"coordinates":[-0.701308,52.492283],"type":"Point"}
}