{
  "type": "Feature",
  "properties": {
    "iso:country":"GB",
    "sg:address":"The Grove",
    "sg:city":"Christchurch",
    "sg:classifiers":[
        {
            "category":"Retail",
            "subcategory":"Auto Repair",
            "type":"Services"
        }
    ],
    "sg:phone":"+44 1202 485137",
    "sg:postcode":"BH23 2EZ",
    "sg:province":"Dorset",
    "sg:tags":[
        "modification",
        "garage"
    ],
    "wof:name":"Grove Garage Mobile Services",
    "wof:placetype":"venue"
},
  "geometry": {"coordinates":[-1.7979040146,50.751285553],"type":"Point"}
}