{
  "type": "Feature",
  "properties": {
    "addr:full":"1 Redbridge Lane East Ilford Essex IG4 5ET",
    "addr:housenumber":"1",
    "addr:postcode":"ig4 5et",
    "addr:street":"Redbridge Lane East",
    "iso:country":"GB",
    "sg:address":"1 Redbridge Lane East",
    "sg:city":"Ilford",
    "sg:classifiers":[
        {
            "category":"Shopping",
            "subcategory":"Gifts & Souvenirs",
            "type":"Retail Goods"
        }
    ],
    "sg:postcode":"IG4 5ET",
    "sg:province":"Essex",
    "sg:tags":[
        "shop"
    ],
    "wof:name":"Marilyn Marks",
    "wof:placetype":"venue"
},
  "geometry": {"coordinates":[0.057724,51.58157],"type":"Point"}
}