{
  "type": "Feature",
  "properties": {
    "iso:country":"GB",
    "sg:address":"Clacton Undercover Market, Rosemary Road",
    "sg:city":"Clacton-on-sea",
    "sg:classifiers":[
        {
            "category":"Farming",
            "subcategory":"Fish & Marine Products",
            "type":"Manufacturing & Wholesale Goods"
        }
    ],
    "sg:postcode":"CO15 1NY",
    "sg:province":"Essex",
    "sg:tags":[
        "fishmonger"
    ],
    "wof:name":"Ken Marks",
    "wof:placetype":"venue"
},
  "geometry": {"coordinates":[1.1532700062,51.8018264771],"type":"Point"}
}