{
  "type": "Feature",
  "properties": {
    "addr:full":"86 West Street Newbury Berkshire RG14 1BD",
    "addr:housenumber":"86",
    "addr:postcode":"rg14 1bd",
    "addr:street":"West Street",
    "iso:country":"GB",
    "sg:address":"86 West Street",
    "sg:city":"Newbury",
    "sg:classifiers":[
        {
            "category":"Building & Trades",
            "subcategory":"Construction",
            "type":"Services"
        }
    ],
    "sg:phone":"+44 1488 683000",
    "sg:postcode":"RG14 1BD",
    "sg:province":"Berkshire",
    "sg:tags":[
        "builder"
    ],
    "wof:name":"Robert James Boulton",
    "wof:placetype":"venue"
},
  "geometry": {"coordinates":[-1.3270670176,51.4032516479],"type":"Point"}
}