{
  "type": "Feature",
  "properties": {
    "addr:full":"7 Gorton Rd, Reddish Stockport Cheshire SK5 6AZ",
    "addr:housenumber":"7",
    "addr:postcode":"sk5 6az",
    "addr:street":"Gorton Rd",
    "iso:country":"GB",
    "sg:address":"7 Gorton Rd, Reddish",
    "sg:city":"Stockport",
    "sg:classifiers":[
        {
            "category":"Travel",
            "subcategory":"Travel Agent",
            "type":"Entertainment"
        }
    ],
    "sg:phone":"+44 161 443 1536",
    "sg:postcode":"SK5 6AZ",
    "sg:province":"Cheshire",
    "wof:name":"Ski & Adventure Travel",
    "wof:placetype":"venue"
},
  "geometry": {"coordinates":[-2.1599929333,53.4377098083],"type":"Point"}
}