{
  "type": "Feature",
  "properties": {
    "addr:full":"C/o Fairfield Graphics, 34 Station Rd Liphook Hampshire GU30 7DS",
    "addr:housenumber":"34",
    "addr:postcode":"gu30 7ds",
    "addr:street":"C;Graphics;Station Rd",
    "iso:country":"GB",
    "sg:address":"C/o Fairfield Graphics, 34 Station Rd",
    "sg:city":"Liphook",
    "sg:classifiers":[
        {
            "category":"Professional",
            "subcategory":"Printing & Photocopies",
            "type":"Services"
        }
    ],
    "sg:postcode":"GU30 7DS",
    "sg:province":"Hampshire",
    "sg:tags":[
        "printer"
    ],
    "wof:name":"Prontaprint Ltd",
    "wof:placetype":"venue"
},
  "geometry": {"coordinates":[-0.7991999984,51.0776405334],"type":"Point"}
}