{
  "type": "Feature",
  "properties": {
    "iso:country":"GB",
    "sg:address":"4 Ching Court",
    "sg:city":"London",
    "sg:classifiers":[
        {
            "category":"Arts & Performance",
            "subcategory":"Theater",
            "type":"Entertainment"
        }
    ],
    "sg:phone":"+44 20 7240 2420",
    "sg:postcode":"WC2H 9EY",
    "sg:province":"Greater London",
    "sg:tags":[
        "theatre"
    ],
    "wof:name":"Andrew Fell Ltd.",
    "wof:placetype":"venue"
},
  "geometry": {"coordinates":[-0.12695,51.51355],"type":"Point"}
}