{
  "type": "Feature",
  "properties": {
    "iso:country":"GB",
    "sg:address":"9-10 The Arches, Golders Green Crescent",
    "sg:city":"London",
    "sg:classifiers":[
        {
            "category":"Retail",
            "subcategory":"Auto Repair",
            "type":"Services"
        }
    ],
    "sg:postcode":"NW11 8LE",
    "sg:province":"Greater London",
    "sg:tags":[
        "modification",
        "garage"
    ],
    "wof:name":"Zig Zag",
    "wof:placetype":"venue"
},
  "geometry": {"coordinates":[-0.19675,51.57283],"type":"Point"}
}