{
  "type": "Feature",
  "properties": {
    "addr:full":"1c Royal Parade Richmond Greater London TW9 3QD",
    "addr:housenumber":"1c",
    "addr:postcode":"tw9 3qd",
    "addr:street":"Royal Parade",
    "iso:country":"GB",
    "sg:address":"1c Royal Parade",
    "sg:city":"Richmond",
    "sg:classifiers":[
        {
            "category":"Professional",
            "subcategory":"Art Services",
            "type":"Services"
        }
    ],
    "sg:postcode":"TW9 3QD",
    "sg:province":"Greater London",
    "sg:tags":[
        "graphic",
        "designer"
    ],
    "wof:name":"United Design Consultants Ltd.",
    "wof:placetype":"venue"
},
  "geometry": {"coordinates":[-0.286393,51.477898],"type":"Point"}
}