{
  "type": "Feature",
  "properties": {
    "iso:country":"GB",
    "sg:address":"37 Canon Street",
    "sg:city":"Aberdare",
    "sg:classifiers":[
        {
            "category":"Shopping",
            "subcategory":"Jewelry",
            "type":"Retail Goods"
        },
        {
            "category":"Shopping",
            "subcategory":"Comic Books",
            "type":"Retail Goods"
        }
    ],
    "sg:phone":"+44 1685 873853",
    "sg:postcode":"CF44 7AP",
    "sg:province":"Neath Port Talbot",
    "sg:tags":[
        "jeweller",
        "sale",
        "jewellery"
    ],
    "wof:name":"Windsor Jewellers",
    "wof:placetype":"venue"
},
  "geometry": {"coordinates":[-3.4474029541,51.7133026123],"type":"Point"}
}