{
  "type": "Feature",
  "properties": {
    "iso:country":"GB",
    "sg:address":"45 North Street",
    "sg:city":"Keighley",
    "sg:classifiers":[
        {
            "category":"Shopping",
            "subcategory":"Clothing, Apparel, & Fashions",
            "type":"Retail Goods"
        }
    ],
    "sg:phone":"+44 1535 210221",
    "sg:postcode":"BD21 3SL",
    "sg:province":"West Yorkshire",
    "sg:tags":[
        "shop"
    ],
    "wof:name":"Asset Branded Clothing",
    "wof:placetype":"venue"
},
  "geometry": {"coordinates":[-1.9098969698,53.8665542603],"type":"Point"}
}