{
  "type": "Feature",
  "properties": {
    "iso:country":"GB",
    "sg:address":"Media House, 99 High Street",
    "sg:city":"Orpington",
    "sg:classifiers":[
        {
            "category":"Professional",
            "subcategory":"Management & Consulting",
            "type":"Services"
        }
    ],
    "sg:phone":"+44 1689 891710",
    "sg:postcode":"BR6 0LG",
    "sg:province":"Kent",
    "sg:tags":[
        "consultant",
        "business"
    ],
    "wof:name":"Robin J Coles",
    "wof:placetype":"venue"
},
  "geometry": {"coordinates":[0.102586,51.379257],"type":"Point"}
}