{
  "type": "Feature",
  "properties": {
    "iso:country":"GB",
    "sg:address":"Corporation Street",
    "sg:city":"Preston",
    "sg:classifiers":[
        {
            "category":"Shopping",
            "subcategory":"Mobile Phones",
            "type":"Retail Goods"
        }
    ],
    "sg:phone":"+44 1772 888041",
    "sg:postcode":"PR1 2UQ",
    "sg:province":"Lancashire",
    "sg:tags":[
        "supplier"
    ],
    "wof:name":"Racom Sales Ltd",
    "wof:placetype":"venue"
},
  "geometry": {"coordinates":[-2.706819,53.761421],"type":"Point"}
}