{
  "type": "Feature",
  "properties": {
    "iso:country":"GB",
    "sg:address":"26 Eridge Rd",
    "sg:city":"Tunbridge Wells",
    "sg:classifiers":[
        {
            "category":"Bars & Pubs",
            "subcategory":"Nightclub",
            "type":"Food & Drink"
        }
    ],
    "sg:phone":"+44 1892 528216",
    "sg:postcode":"TN4 8HJ",
    "sg:province":"Kent",
    "sg:tags":[
        "karaoke"
    ],
    "wof:name":"Karaoke Klub",
    "wof:placetype":"venue"
},
  "geometry": {"coordinates":[0.25067,51.12402],"type":"Point"}
}