{
  "type": "Feature",
  "properties": {
    "addr:full":"Enterprise Ho, 113 George La London Greater London E18 1AB",
    "addr:housenumber":"113",
    "addr:postcode":"e18 1ab",
    "addr:street":"George La",
    "iso:country":"GB",
    "sg:address":"Enterprise Ho, 113 George La",
    "sg:city":"London",
    "sg:classifiers":[
        {
            "category":"Shopping",
            "subcategory":"Beauty & Cosmetics",
            "type":"Retail Goods"
        }
    ],
    "sg:postcode":"E18 1AB",
    "sg:province":"Greater London",
    "sg:tags":[
        "equipment",
        "supply",
        "hairdressing"
    ],
    "wof:name":"Whyte,Tony,",
    "wof:placetype":"venue"
},
  "geometry": {"coordinates":[0.03061,51.589931],"type":"Point"}
}