{
  "type": "Feature",
  "properties": {
    "addr:full":"Miller Ct, Millbay Rd Plymouth Devon PL1 3LQ",
    "addr:postcode":"pl1 3lq",
    "addr:street":"Miller Ct Millbay Rd",
    "iso:country":"GB",
    "sg:address":"Miller Ct, Millbay Rd",
    "sg:city":"Plymouth",
    "sg:classifiers":[
        {
            "category":"Home & Garden",
            "subcategory":"Hardware",
            "type":"Retail Goods"
        }
    ],
    "sg:phone":"+44 1752 222588",
    "sg:postcode":"PL1 3LQ",
    "sg:province":"Devon",
    "sg:tags":[
        "equipment",
        "welding"
    ],
    "wof:name":"Independent Welding Supplies Ltd",
    "wof:placetype":"venue"
},
  "geometry": {"coordinates":[-4.157124,50.367977],"type":"Point"}
}