{
  "type": "Feature",
  "properties": {
    "addr:full":"48 Apsley Road, South Norwood London Greater London SE25 4XT",
    "addr:housenumber":"48",
    "addr:postcode":"se25 4xt",
    "addr:street":"Apsley Road",
    "iso:country":"GB",
    "sg:address":"48 Apsley Road, South Norwood",
    "sg:city":"London",
    "sg:classifiers":[
        {
            "category":"Retail",
            "subcategory":"Driving School",
            "type":"Services"
        }
    ],
    "sg:postcode":"SE25 4XT",
    "sg:province":"Greater London",
    "wof:name":"Daniels Driving School",
    "wof:placetype":"venue"
},
  "geometry": {"coordinates":[-0.0659679994,51.3964271545],"type":"Point"}
}