{
  "type": "Feature",
  "properties": {
    "addr:full":"51 Broad Street, Old Portsmouth Portsmouth Hampshire PO1 2JD",
    "addr:housenumber":"51",
    "addr:postcode":"hampshire po1 2jd",
    "addr:street":"Broad Street",
    "iso:country":"GB",
    "sg:address":"51 Broad Street, Old Portsmouth",
    "sg:city":"Portsmouth",
    "sg:classifiers":[
        {
            "category":"Travel",
            "subcategory":"Hotels & Motels",
            "type":"Entertainment"
        }
    ],
    "sg:phone":"+44 23 9282 3748",
    "sg:postcode":"PO1 2JD",
    "sg:province":"Hampshire",
    "sg:tags":[
        "house",
        "guest"
    ],
    "wof:name":"Fortitude Cottage",
    "wof:placetype":"venue"
},
  "geometry": {"coordinates":[-1.1078510284,50.7907371521],"type":"Point"}
}