{
  "type": "Feature",
  "properties": {
    "addr:full":"32b Swan Salmon Yard, Castlegate Newark Nottinghamshire NG24 1BG",
    "addr:housenumber":"32b",
    "addr:postcode":"ng24 1bg",
    "addr:street":"Swan Salmon Yard Castlegate",
    "iso:country":"GB",
    "sg:address":"32b Swan Salmon Yard, Castlegate",
    "sg:city":"Newark",
    "sg:classifiers":[
        {
            "category":"Manufacturing",
            "subcategory":"Textiles",
            "type":"Manufacturing & Wholesale Goods"
        }
    ],
    "sg:postcode":"NG24 1BG",
    "sg:province":"Nottinghamshire",
    "sg:tags":[
        "made-up"
    ],
    "wof:name":"Clark & English",
    "wof:placetype":"venue"
},
  "geometry": {"coordinates":[-0.809347,53.073895],"type":"Point"}
}