{
  "type": "Feature",
  "properties": {
    "iso:country":"GB",
    "sg:address":"272 Ringinglow Road",
    "sg:city":"Sheffield",
    "sg:classifiers":[
        {
            "category":"Banks & Credit Unions",
            "subcategory":"Financial Services",
            "type":"Services"
        }
    ],
    "sg:phone":"+44 114 229 5959",
    "sg:postcode":"S11 7PX",
    "sg:province":"Derbyshire",
    "sg:tags":[
        "adviser"
    ],
    "wof:name":"Ethical Investments Ltd.",
    "wof:placetype":"venue"
},
  "geometry": {"coordinates":[-1.523144,53.356503],"type":"Point"}
}