{
  "type": "Feature",
  "properties": {
    "iso:country":"GB",
    "sg:address":"Four Brindleyplace",
    "sg:city":"Birmingham",
    "sg:classifiers":[
        {
            "category":"Professional",
            "subcategory":"Business Services",
            "type":"Services"
        }
    ],
    "sg:postcode":"B1 2HZ",
    "sg:province":"West Midlands",
    "sg:tags":[
        "holding"
    ],
    "wof:name":"M C I Great Britain Ltd",
    "wof:placetype":"venue"
},
  "geometry": {"coordinates":[-1.908604,52.478596],"type":"Point"}
}