{
  "type": "Feature",
  "properties": {
    "addr:full":"1 Chase Side London Greater London N14 5BP",
    "addr:housenumber":"1",
    "addr:postcode":"n14 5bp",
    "addr:street":"Chase",
    "iso:country":"GB",
    "sg:address":"1 Chase Side",
    "sg:city":"London",
    "sg:classifiers":[
        {
            "category":"Shopping",
            "subcategory":"Florist",
            "type":"Retail Goods"
        }
    ],
    "sg:phone":"+44 20 8886 1710",
    "sg:postcode":"N14 5BP",
    "sg:province":"Greater London",
    "wof:name":"Iris Florist",
    "wof:placetype":"venue"
},
  "geometry": {"coordinates":[-0.127989,51.632629],"type":"Point"}
}