{
  "type": "Feature",
  "properties": {
    "iso:country":"GB",
    "sg:address":"Watling St",
    "sg:city":"Rugby",
    "sg:classifiers":[
        {
            "category":"Retail",
            "subcategory":"Auto Repair",
            "type":"Services"
        }
    ],
    "sg:phone":"+44 1788 860223",
    "sg:postcode":"CV23 0AP",
    "sg:province":"Northamptonshire",
    "sg:tags":[
        "modification",
        "garage"
    ],
    "wof:name":"Watling Street Garage",
    "wof:placetype":"venue"
},
  "geometry": {"coordinates":[-1.19517,52.388023],"type":"Point"}
}