{
  "type": "Feature",
  "properties": {
    "addr:full":"Rockley House, Rockley Street Dewsbury West Yorkshire WF13 1NS",
    "addr:postcode":"wf13 1ns",
    "addr:street":"Rockley Street",
    "iso:country":"GB",
    "sg:address":"Rockley House, Rockley Street",
    "sg:city":"Dewsbury",
    "sg:classifiers":[
        {
            "category":"Education",
            "subcategory":"School",
            "type":"Public Place"
        },
        {
            "category":"Government",
            "subcategory":"Office",
            "type":"Public Place"
        }
    ],
    "sg:phone":"+44 1924 325285",
    "sg:postcode":"WF13 1NS",
    "sg:province":"West Yorkshire",
    "sg:tags":[
        "local",
        "authority"
    ],
    "wof:name":"J I Eastborough & Nursery",
    "wof:placetype":"venue"
},
  "geometry": {"coordinates":[-1.625232,53.693314],"type":"Point"}
}