{
  "type": "Feature",
  "properties": {
    "iso:country":"GB",
    "sg:address":"Frontier House, 63 Guildford Road",
    "sg:city":"Lightwater",
    "sg:classifiers":[
        {
            "category":"Professional",
            "subcategory":"Computer Services",
            "type":"Services"
        }
    ],
    "sg:phone":"+44 1276 451551",
    "sg:postcode":"GU18 5SA",
    "sg:province":"Surrey",
    "sg:tags":[
        "system",
        "software"
    ],
    "wof:name":"Frontier Software Plc",
    "wof:placetype":"venue"
},
  "geometry": {"coordinates":[-0.664759,51.351109],"type":"Point"}
}