{
  "type": "Feature",
  "properties": {
    "addr:full":"41 Keighley Rd Colne Lancashire BB8 0LS",
    "addr:housenumber":"41",
    "addr:postcode":"bb8 0ls",
    "addr:street":"Keighley Rd",
    "iso:country":"GB",
    "sg:address":"41 Keighley Rd",
    "sg:city":"Colne",
    "sg:classifiers":[
        {
            "category":"Home & Garden",
            "subcategory":"Hardware",
            "type":"Retail Goods"
        }
    ],
    "sg:postcode":"BB8 0LS",
    "sg:province":"Lancashire",
    "sg:tags":[
        "retailer",
        "diy"
    ],
    "wof:name":"Colne Diy Store",
    "wof:placetype":"venue"
},
  "geometry": {"coordinates":[-2.1604239941,53.8576850891],"type":"Point"}
}