{
  "type": "Feature",
  "properties": {
    "addr:full":"55 Clifton Road Shefford Bedfordshire SG17 5AE",
    "addr:housenumber":"55",
    "addr:postcode":"sg17 5ae",
    "addr:street":"Clifton Road",
    "iso:country":"GB",
    "sg:address":"55 Clifton Road",
    "sg:city":"Shefford",
    "sg:classifiers":[
        {
            "category":"Manufacturing",
            "subcategory":"Signs",
            "type":"Manufacturing & Wholesale Goods"
        }
    ],
    "sg:phone":"+44 1462 811397",
    "sg:postcode":"SG17 5AE",
    "sg:province":"Bedfordshire",
    "sg:tags":[
        "nameplate"
    ],
    "wof:name":"Everitt Signs",
    "wof:placetype":"venue"
},
  "geometry": {"coordinates":[-0.3281590044,52.0371742249],"type":"Point"}
}