{
  "type": "Feature",
  "properties": {
    "iso:country":"GB",
    "sg:address":"8 Melbourne Gro",
    "sg:city":"London",
    "sg:classifiers":[
        {
            "category":"Shopping",
            "subcategory":"Antiques",
            "type":"Retail Goods"
        }
    ],
    "sg:phone":"+44 20 8299 6565",
    "sg:postcode":"SE22 8QZ",
    "sg:province":"Greater London",
    "wof:name":"Melbourne Antiques",
    "wof:placetype":"venue"
},
  "geometry": {"coordinates":[-0.079966,51.461018],"type":"Point"}
}