{
  "type": "Feature",
  "properties": {
    "addr:full":"8 The Bridge Taunton Somerset TA1 1UG",
    "addr:housenumber":"8",
    "addr:postcode":"ta1 1ug",
    "addr:street":"The Bridge",
    "iso:country":"GB",
    "sg:address":"8 The Bridge",
    "sg:city":"Taunton",
    "sg:classifiers":[
        {
            "category":"Retail",
            "subcategory":"Repair Shop",
            "type":"Services"
        }
    ],
    "sg:postcode":"TA1 1UG",
    "sg:province":"Somerset",
    "sg:tags":[
        "clocks",
        "watch"
    ],
    "wof:name":"Showerings",
    "wof:placetype":"venue"
},
  "geometry": {"coordinates":[-3.1037769318,51.0174446106],"type":"Point"}
}