{
  "type": "Feature",
  "properties": {
    "addr:full":"66a Woodfield Ave Lincoln Lincolnshire LN6 0LP",
    "addr:housenumber":"66a",
    "addr:postcode":"ln6 0lp",
    "addr:street":"Woodfield Ave",
    "iso:country":"GB",
    "sg:address":"66a Woodfield Ave",
    "sg:city":"Lincoln",
    "sg:classifiers":[
        {
            "category":"Fast Food",
            "type":"Food & Drink"
        }
    ],
    "sg:postcode":"LN6 0LP",
    "sg:province":"Lincolnshire",
    "sg:tags":[
        "away",
        "take"
    ],
    "wof:name":"Hart,John,",
    "wof:placetype":"venue"
},
  "geometry": {"coordinates":[-0.600946,53.221081],"type":"Point"}
}