{
  "type": "Feature",
  "properties": {
    "addr:full":"Hollyrood House, 46 Green Lane Burnham-on-crouch Essex CM0 8PU",
    "addr:housenumber":"46",
    "addr:postcode":"cm0 8pu",
    "addr:street":"Green Lane",
    "iso:country":"GB",
    "sg:address":"Hollyrood House, 46 Green Lane",
    "sg:city":"Burnham-on-crouch",
    "sg:classifiers":[
        {
            "category":"Building & Trades",
            "subcategory":"Construction",
            "type":"Services"
        }
    ],
    "sg:postcode":"CM0 8PU",
    "sg:province":"Essex",
    "sg:tags":[
        "roofing"
    ],
    "wof:name":"A & M Walters Roofing",
    "wof:placetype":"venue"
},
  "geometry": {"coordinates":[0.7972149849,51.64320755],"type":"Point"}
}