{
  "type": "Feature",
  "properties": {
    "iso:country":"GB",
    "sg:address":"1376 Leeds Road",
    "sg:city":"Bradford",
    "sg:classifiers":[
        {
            "category":"Communications",
            "type":"Services"
        }
    ],
    "sg:postcode":"BD3 8NE",
    "sg:province":"West Yorkshire",
    "sg:tags":[
        "telecommunication"
    ],
    "wof:name":"Network Mobile Phones",
    "wof:placetype":"venue"
},
  "geometry": {"coordinates":[-1.711966,53.797085],"type":"Point"}
}