{
  "type": "Feature",
  "properties": {
    "iso:country":"GB",
    "sg:address":"3 Long Street",
    "sg:city":"Tetbury",
    "sg:classifiers":[
        {
            "category":"Cafe",
            "type":"Food & Drink"
        }
    ],
    "sg:phone":"+44 1666 503337",
    "sg:postcode":"GL8 8AA",
    "sg:province":"Gloucestershire",
    "sg:tags":[
        "tea",
        "snack",
        "bar",
        "room"
    ],
    "wof:name":"The Welcome Chair",
    "wof:placetype":"venue"
},
  "geometry": {"coordinates":[-2.159761,51.637272],"type":"Point"}
}