{
  "type": "Feature",
  "properties": {
    "addr:full":"The Yard, Lanchards Lane Blandford Forum Dorset DT11 0TF",
    "addr:postcode":"dt11 0tf",
    "addr:street":"Lanchards Lane",
    "iso:country":"GB",
    "sg:address":"The Yard, Lanchards Lane",
    "sg:city":"Blandford Forum",
    "sg:classifiers":[
        {
            "category":"Professional",
            "subcategory":"Engineering",
            "type":"Services"
        }
    ],
    "sg:postcode":"DT11 0TF",
    "sg:province":"Dorset",
    "sg:tags":[
        "contractor",
        "electrical",
        "engineer"
    ],
    "wof:name":"J R Hall Electrical",
    "wof:placetype":"venue"
},
  "geometry": {"coordinates":[-2.254482,50.898216],"type":"Point"}
}