{
  "type": "Feature",
  "properties": {
    "addr:full":"696 Whitworth Road Rochdale Lancashire OL12 0TG",
    "addr:housenumber":"696",
    "addr:postcode":"ol12 0tg",
    "addr:street":"Whitworth Road",
    "iso:country":"GB",
    "sg:address":"696 Whitworth Road",
    "sg:city":"Rochdale",
    "sg:classifiers":[
        {
            "category":"Government",
            "subcategory":"Post Office",
            "type":"Public Place"
        }
    ],
    "sg:postcode":"OL12 0TG",
    "sg:province":"Lancashire",
    "sg:tags":[
        "messenger",
        "courier"
    ],
    "wof:name":"Albion Express Parcels",
    "wof:placetype":"venue"
},
  "geometry": {"coordinates":[-2.173115015,53.6392745972],"type":"Point"}
}