{
  "type": "Feature",
  "properties": {
    "iso:country":"GB",
    "sg:address":"90 Merthyrmawr Road",
    "sg:city":"Bridgend",
    "sg:classifiers":[
        {
            "category":"Organizations",
            "subcategory":"Non-profit Organization",
            "type":"Services"
        }
    ],
    "sg:postcode":"CF31 3NS",
    "sg:province":"Bridgend",
    "sg:tags":[
        "fundraising",
        "charity"
    ],
    "wof:name":"Intercontinental Films",
    "wof:placetype":"venue"
},
  "geometry": {"coordinates":[-3.5827329159,51.498966217],"type":"Point"}
}