{
  "type": "Feature",
  "properties": {
    "addr:full":"64-66 Brighton Road Surbiton Surrey KT6 5PP",
    "addr:housenumber":"64-66",
    "addr:postcode":"kt6 5pp",
    "addr:street":"Brighton Road",
    "iso:country":"GB",
    "sg:address":"64-66 Brighton Road",
    "sg:city":"Surbiton",
    "sg:classifiers":[
        {
            "category":"Manufacturing",
            "subcategory":"Building Materials",
            "type":"Manufacturing & Wholesale Goods"
        }
    ],
    "sg:phone":"+44 20 8399 4144",
    "sg:postcode":"KT6 5PP",
    "sg:province":"Surrey",
    "sg:tags":[
        "merchant",
        "builder"
    ],
    "wof:name":"Jewson Ltd.",
    "wof:placetype":"venue"
},
  "geometry": {"coordinates":[-0.311215,51.392277],"type":"Point"}
}