{
  "type": "Feature",
  "properties": {
    "addr:full":"152 Beaulieu Gardens, Blackwater Camberley Hampshire GU17 0LE",
    "addr:housenumber":"152",
    "addr:postcode":"gu17 0le",
    "addr:street":"Beaulieu Gardens Blackwater",
    "iso:country":"GB",
    "sg:address":"152 Beaulieu Gardens, Blackwater",
    "sg:city":"Camberley",
    "sg:classifiers":[
        {
            "category":"Retail",
            "subcategory":"Auto Repair",
            "type":"Services"
        }
    ],
    "sg:postcode":"GU17 0LE",
    "sg:province":"Hampshire",
    "sg:tags":[
        "engine",
        "car",
        "specialist"
    ],
    "wof:name":"Allcars Anytime",
    "wof:placetype":"venue"
},
  "geometry": {"coordinates":[-0.7943099737,51.3359527588],"type":"Point"}
}