{
  "type": "Feature",
  "properties": {
    "iso:country":"GB",
    "sg:address":"Hook Road, North Warnborough",
    "sg:city":"Hook",
    "sg:classifiers":[
        {
            "category":"Bars & Pubs",
            "type":"Food & Drink"
        }
    ],
    "sg:phone":"+44 1256 702085",
    "sg:postcode":"RG29 1ET",
    "sg:province":"Hampshire",
    "sg:tags":[
        "pubs",
        "inn"
    ],
    "wof:name":"The Jolly Miller Free House",
    "wof:placetype":"venue"
},
  "geometry": {"coordinates":[-0.9586390257,51.2688751221],"type":"Point"}
}