{
  "type": "Feature",
  "properties": {
    "addr:full":"14-14a Hempsted Lane Gloucester Gloucestershire GL2 5JA",
    "addr:housenumber":"14-14a",
    "addr:postcode":"gl2 5ja",
    "addr:street":"Hempsted Lane",
    "iso:country":"GB",
    "sg:address":"14-14a Hempsted Lane",
    "sg:city":"Gloucester",
    "sg:classifiers":[
        {
            "category":"Wholesale",
            "subcategory":"Machinery & Supplies",
            "type":"Manufacturing & Wholesale Goods"
        }
    ],
    "sg:phone":"+44 1452 303006",
    "sg:postcode":"GL2 5JA",
    "sg:province":"Gloucestershire",
    "sg:tags":[
        "pump"
    ],
    "wof:name":"Pump Supplies Ltd.",
    "wof:placetype":"venue"
},
  "geometry": {"coordinates":[-2.2593541145,51.8596954346],"type":"Point"}
}