{
  "type": "Feature",
  "properties": {
    "addr:full":"Maypole Cottage, Jubilee Road, Chelsfield Orpington Kent BR6 7QZ",
    "addr:postcode":"chelsfield;br6 7qz",
    "addr:street":"Jubilee Road",
    "iso:country":"GB",
    "sg:address":"Maypole Cottage, Jubilee Road, Chelsfield",
    "sg:city":"Orpington",
    "sg:classifiers":[
        {
            "category":"Professional",
            "subcategory":"Employment Agencies",
            "type":"Services"
        }
    ],
    "sg:phone":"+44 1959 534482",
    "sg:postcode":"BR6 7QZ",
    "sg:province":"Kent",
    "sg:tags":[
        "consultant"
    ],
    "wof:name":"Grange Selection Ltd.",
    "wof:placetype":"venue"
},
  "geometry": {"coordinates":[0.1348879933,51.3552703857],"type":"Point"}
}