{
  "type": "Feature",
  "properties": {
    "addr:full":"Pirnhow Street, Ditchingham Bungay Norfolk NR35 2RU",
    "addr:postcode":"nr35 2ru",
    "addr:street":"Pirnhow Street",
    "iso:country":"GB",
    "sg:address":"Pirnhow Street, Ditchingham",
    "sg:city":"Bungay",
    "sg:classifiers":[
        {
            "category":"Home & Garden",
            "subcategory":"Kitchen Supply",
            "type":"Retail Goods"
        }
    ],
    "sg:phone":"+44 1986 892860",
    "sg:postcode":"NR35 2RU",
    "sg:province":"Norfolk",
    "sg:tags":[
        "equipment",
        "brewer"
    ],
    "wof:name":"Crisp Malting Group Ltd.",
    "wof:placetype":"venue"
},
  "geometry": {"coordinates":[1.4394019842,52.4675140381],"type":"Point"}
}