{
  "type": "Feature",
  "properties": {
    "iso:country":"GB",
    "sg:address":"St Edmunds Road Business Park, St Edmunds Road",
    "sg:city":"Southwold",
    "sg:classifiers":[
        {
            "category":"Shopping",
            "subcategory":"Antiques",
            "type":"Retail Goods"
        }
    ],
    "sg:phone":"+44 1502 722211",
    "sg:postcode":"IP18 6BZ",
    "sg:province":"Suffolk",
    "wof:name":"Puritan Values",
    "wof:placetype":"venue"
},
  "geometry": {"coordinates":[1.6773649454,52.3313484192],"type":"Point"}
}