{
  "type": "Feature",
  "properties": {
    "addr:full":"9 Brunswick Street Leicester Leicestershire LE1 2LP",
    "addr:housenumber":"9",
    "addr:postcode":"le1 2lp",
    "addr:street":"Brunswick Street",
    "iso:country":"GB",
    "sg:address":"9 Brunswick Street",
    "sg:city":"Leicester",
    "sg:classifiers":[
        {
            "category":"Professional",
            "subcategory":"Business Services",
            "type":"Services"
        },
        {
            "category":"Manufacturing",
            "subcategory":"Paper Products",
            "type":"Manufacturing & Wholesale Goods"
        }
    ],
    "sg:phone":"+44 116 251 1674",
    "sg:postcode":"LE1 2LP",
    "sg:province":"Leicestershire",
    "sg:tags":[
        "distribution",
        "clothing",
        "fabric",
        "manufacturer"
    ],
    "wof:name":"Slyde Ltd",
    "wof:placetype":"venue"
},
  "geometry": {"coordinates":[-1.121562,52.638451],"type":"Point"}
}