{
  "type": "Feature",
  "properties": {
    "addr:full":"75 Tavistock St Bedford Bedfordshire MK40 2RR",
    "addr:housenumber":"75",
    "addr:postcode":"mk40 2rr",
    "addr:street":"Tavistock St",
    "iso:country":"GB",
    "sg:address":"75 Tavistock St",
    "sg:city":"Bedford",
    "sg:classifiers":[
        {
            "category":"Shopping",
            "subcategory":"Mobile Phones",
            "type":"Retail Goods"
        }
    ],
    "sg:phone":"+44 1234 272233",
    "sg:postcode":"MK40 2RR",
    "sg:province":"Bedfordshire",
    "wof:name":"Telecom South",
    "wof:placetype":"venue"
},
  "geometry": {"coordinates":[-0.4712559879,52.1410331726],"type":"Point"}
}