{
  "type": "Feature",
  "properties": {
    "addr:full":"4 Ernan Road South Ockendon Essex RM15 5EW",
    "addr:housenumber":"4",
    "addr:postcode":"rm15 5ew",
    "addr:street":"Ernan Road",
    "iso:country":"GB",
    "sg:address":"4 Ernan Road",
    "sg:city":"South Ockendon",
    "sg:classifiers":[
        {
            "category":"Bus Charters",
            "type":"Transportation"
        }
    ],
    "sg:postcode":"RM15 5EW",
    "sg:province":"Essex",
    "sg:tags":[
        "hire",
        "coach"
    ],
    "wof:name":"Hunters Mini Bus",
    "wof:placetype":"venue"
},
  "geometry": {"coordinates":[0.280582,51.511368],"type":"Point"}
}