{
  "type": "Feature",
  "properties": {
    "iso:country":"GB",
    "sg:address":"5 Claybury, Broadway, Clayhall",
    "sg:city":"Ilford",
    "sg:classifiers":[
        {
            "category":"Professional",
            "type":"Services"
        },
        {
            "category":"Fast Food",
            "type":"Food & Drink"
        }
    ],
    "sg:phone":"+44 20 8550 5908",
    "sg:postcode":"IG5 0JP",
    "sg:province":"Essex",
    "sg:tags":[
        "away",
        "take",
        "caterer"
    ],
    "wof:name":"First Choice Catering",
    "wof:placetype":"venue"
},
  "geometry": {"coordinates":[0.0496799983,51.5901756287],"type":"Point"}
}