{
  "type": "Feature",
  "properties": {
    "iso:country":"GB",
    "sg:address":"Argyll Road",
    "sg:city":"Llandudno",
    "sg:classifiers":[
        {
            "category":"Retail",
            "subcategory":"Auto Repair",
            "type":"Services"
        }
    ],
    "sg:phone":"+44 1492 860060",
    "sg:postcode":"LL30 1DF",
    "sg:province":"Conwy",
    "sg:tags":[
        "modification",
        "garage",
        "related"
    ],
    "wof:name":"Mochdre Garage Ltd",
    "wof:placetype":"venue"
},
  "geometry": {"coordinates":[-3.824489,53.320515],"type":"Point"}
}