{
  "type": "Feature",
  "properties": {
    "addr:full":"Underwood Building, Osmani School London Greater London E1 5AB",
    "addr:postcode":"e1 5ab",
    "iso:country":"GB",
    "sg:address":"Underwood Building, Osmani School",
    "sg:city":"London",
    "sg:classifiers":[
        {
            "category":"Community Center",
            "subcategory":"Youth",
            "type":"Public Place"
        }
    ],
    "sg:postcode":"E1 5AB",
    "sg:province":"Greater London",
    "sg:tags":[
        "organisation",
        "centre"
    ],
    "wof:name":"Osmani Junior Youth Club",
    "wof:placetype":"venue"
},
  "geometry": {"coordinates":[-0.0656939968,51.5212402344],"type":"Point"}
}