{
  "type": "Feature",
  "properties": {
    "addr:full":"20 Kingsbury Road, Erdington Birmingham West Midlands B24 8QQ",
    "addr:housenumber":"20",
    "addr:postcode":"b24 8qq",
    "addr:street":"Kingsbury Road",
    "iso:country":"GB",
    "sg:address":"20 Kingsbury Road, Erdington",
    "sg:city":"Birmingham",
    "sg:classifiers":[
        {
            "category":"Retail",
            "subcategory":"Driving School",
            "type":"Services"
        }
    ],
    "sg:phone":"+44 121 350 4841",
    "sg:postcode":"B24 8QQ",
    "sg:province":"West Midlands",
    "wof:name":"Marys Driving School",
    "wof:placetype":"venue"
},
  "geometry": {"coordinates":[-1.850556016,52.5130958557],"type":"Point"}
}