{
  "type": "Feature",
  "properties": {
    "addr:full":"Unit 21 Pinfold Workshops, Pinfold Lane Indust Est Buckley Denbighshire CH7 3PL",
    "addr:housenumber":"unit 21",
    "addr:postcode":"ch7 3pl",
    "addr:street":"Workshops Pinfold Lane",
    "iso:country":"GB",
    "sg:address":"Unit 21 Pinfold Workshops, Pinfold Lane Indust Est",
    "sg:city":"Buckley",
    "sg:classifiers":[
        {
            "category":"Travel",
            "subcategory":"Travel Agent",
            "type":"Entertainment"
        }
    ],
    "sg:phone":"+44 1244 550196",
    "sg:postcode":"CH7 3PL",
    "sg:province":"Denbighshire",
    "wof:name":"Traveltec Direct",
    "wof:placetype":"venue"
},
  "geometry": {"coordinates":[-3.083634,53.179405],"type":"Point"}
}