{
  "type": "Feature",
  "properties": {
    "addr:full":"305a Nantwich Road Crewe Cheshire CW2 6PE",
    "addr:housenumber":"305a",
    "addr:postcode":"cw2 6pe",
    "addr:street":"Nantwich Road",
    "iso:country":"GB",
    "sg:address":"305a Nantwich Road",
    "sg:city":"Crewe",
    "sg:classifiers":[
        {
            "category":"Professional",
            "subcategory":"Engineering",
            "type":"Services"
        }
    ],
    "sg:phone":"+44 1270 560701",
    "sg:postcode":"CW2 6PE",
    "sg:province":"Cheshire",
    "sg:tags":[
        "contractor",
        "electrical",
        "engineer"
    ],
    "wof:name":"Norman G White",
    "wof:placetype":"venue"
},
  "geometry": {"coordinates":[-2.4524428844,53.0854454041],"type":"Point"}
}