{
  "type": "Feature",
  "properties": {
    "addr:full":"Forthill Surgery, Winklebury Centre Basingstoke Hampshire RG23 8BU",
    "addr:postcode":"rg23 8bu",
    "addr:street":"Winklebury Centre",
    "iso:country":"GB",
    "sg:address":"Forthill Surgery, Winklebury Centre",
    "sg:city":"Basingstoke",
    "sg:classifiers":[
        {
            "category":"Health Services",
            "subcategory":"Doctor",
            "type":"Services"
        }
    ],
    "sg:phone":"+44 1256 359440",
    "sg:postcode":"RG23 8BU",
    "sg:province":"Hampshire",
    "sg:tags":[
        "practitioners"
    ],
    "wof:name":"Thein, M",
    "wof:placetype":"venue"
},
  "geometry": {"coordinates":[-1.1245529652,51.2685012817],"type":"Point"}
}