{
  "type": "Feature",
  "properties": {
    "addr:full":"276a High Street Waltham Cross Essex EN8 7EA",
    "addr:housenumber":"276a",
    "addr:postcode":"en8 7ea",
    "addr:street":"High Street",
    "iso:country":"GB",
    "sg:address":"276a High Street",
    "sg:city":"Waltham Cross",
    "sg:classifiers":[
        {
            "category":"Taxi",
            "type":"Transportation"
        }
    ],
    "sg:phone":"+44 1992 620380",
    "sg:postcode":"EN8 7EA",
    "sg:province":"Essex",
    "sg:tags":[
        "mini",
        "cab"
    ],
    "wof:name":"C M S Car Services",
    "wof:placetype":"venue"
},
  "geometry": {"coordinates":[-0.033909,51.691471],"type":"Point"}
}