{
  "type": "Feature",
  "properties": {
    "iso:country":"GB",
    "sg:address":"Cardiff Rd",
    "sg:city":"Cardiff",
    "sg:classifiers":[
        {
            "category":"Organizations",
            "subcategory":"Membership Organization",
            "type":"Services"
        }
    ],
    "sg:phone":"+44 29 2081 0220",
    "sg:postcode":"CF4 7QG",
    "sg:province":"Cardiff",
    "sg:tags":[
        "club"
    ],
    "wof:name":"Taffs Well Ex-Service & Social Club",
    "wof:placetype":"venue"
},
  "geometry": {"coordinates":[-3.2623391151,51.5395736694],"type":"Point"}
}