{
  "type": "Feature",
  "properties": {
    "addr:full":"Alltgoch Farm, Cwrtnewydd Llanybydder Carmarthenshire SA40 9YL",
    "addr:postcode":"sa40 9yl",
    "iso:country":"GB",
    "sg:address":"Alltgoch Farm, Cwrtnewydd",
    "sg:city":"Llanybydder",
    "sg:classifiers":[
        {
            "category":"Farming",
            "subcategory":"Livestock Farm",
            "type":"Manufacturing & Wholesale Goods"
        }
    ],
    "sg:postcode":"SA40 9YL",
    "sg:province":"Carmarthenshire",
    "sg:tags":[
        "others"
    ],
    "wof:name":"Huw Evans",
    "wof:placetype":"venue"
},
  "geometry": {"coordinates":[-4.1583609581,52.0739364624],"type":"Point"}
}