{
  "type": "Feature",
  "properties": {
    "addr:full":"18 Friar St Worcester Worcestershire WR1 2LZ",
    "addr:housenumber":"18",
    "addr:postcode":"wr1 2lz",
    "addr:street":"Friar St",
    "iso:country":"GB",
    "sg:address":"18 Friar St",
    "sg:city":"Worcester",
    "sg:classifiers":[
        {
            "category":"Government",
            "subcategory":"Post Office",
            "type":"Public Place"
        }
    ],
    "sg:phone":"+44 1905 770312",
    "sg:postcode":"WR1 2LZ",
    "sg:province":"Worcestershire",
    "sg:tags":[
        "window",
        "display",
        "dressing"
    ],
    "wof:name":"I C P Marketing Ltd",
    "wof:placetype":"venue"
},
  "geometry": {"coordinates":[-2.2191939354,52.1905136108],"type":"Point"}
}