{
  "type": "Feature",
  "properties": {
    "addr:full":"207 Nottingham Road, Eastwood Nottingham Derbyshire NG16 3GS",
    "addr:housenumber":"207",
    "addr:postcode":"ng16 3gs",
    "addr:street":"Nottingham Road",
    "iso:country":"GB",
    "sg:address":"207 Nottingham Road, Eastwood",
    "sg:city":"Nottingham",
    "sg:classifiers":[
        {
            "category":"Personal",
            "subcategory":"Beauty Salon",
            "type":"Services"
        }
    ],
    "sg:phone":"+44 1773 761913",
    "sg:postcode":"NG16 3GS",
    "sg:province":"Derbyshire",
    "sg:tags":[
        "unisex",
        "hairdresser"
    ],
    "wof:name":"Stylistics",
    "wof:placetype":"venue"
},
  "geometry": {"coordinates":[-1.293854,53.014465],"type":"Point"}
}