{
  "type": "Feature",
  "properties": {
    "addr:full":"Fordor House, 115 North Road, Kew Richmond Greater London TW9 4HJ",
    "addr:housenumber":"115",
    "addr:postcode":"tw9 4hj",
    "addr:street":"North Road",
    "iso:country":"GB",
    "sg:address":"Fordor House, 115 North Road, Kew",
    "sg:city":"Richmond",
    "sg:classifiers":[
        {
            "category":"Taxi",
            "type":"Transportation"
        }
    ],
    "sg:phone":"+44 20 8995 9999",
    "sg:postcode":"TW9 4HJ",
    "sg:province":"Greater London",
    "sg:tags":[
        "mini",
        "cab"
    ],
    "wof:name":"Lichfield 24 Hour Executive Cars",
    "wof:placetype":"venue"
},
  "geometry": {"coordinates":[-0.2851060033,51.4766311646],"type":"Point"}
}