{
  "type": "Feature",
  "properties": {
    "iso:country":"GB",
    "sg:address":"1 Bowling Green Rd",
    "sg:city":"Cirencester",
    "sg:classifiers":[
        {
            "category":"Social Services",
            "subcategory":"Child Care",
            "type":"Services"
        }
    ],
    "sg:phone":"+44 1285 641041",
    "sg:postcode":"GL7 2EZ",
    "sg:province":"Gloucestershire",
    "sg:tags":[
        "agency",
        "nanny"
    ],
    "wof:name":"Poppins Nannies & Baby Sitting",
    "wof:placetype":"venue"
},
  "geometry": {"coordinates":[-1.97116,51.724262],"type":"Point"}
}