{
  "type": "Feature",
  "properties": {
    "iso:country":"GB",
    "sg:address":"Star Meadow, Zeal Monachorum",
    "sg:city":"Crediton",
    "sg:classifiers":[
        {
            "category":"Personal",
            "type":"Services"
        }
    ],
    "sg:phone":"+44 1363 82504",
    "sg:postcode":"EX17 6DF",
    "sg:province":"Devon",
    "sg:tags":[
        "wedding"
    ],
    "wof:name":"Country Bridal Collection",
    "wof:placetype":"venue"
},
  "geometry": {"coordinates":[-3.8192429543,50.8216362],"type":"Point"}
}