{
  "type": "Feature",
  "properties": {
    "addr:full":"10 Moorlands Road Ferndown Dorset BH22 0JW",
    "addr:housenumber":"10",
    "addr:postcode":"bh22 0jw",
    "addr:street":"Moorlands Road",
    "iso:country":"GB",
    "sg:address":"10 Moorlands Road",
    "sg:city":"Ferndown",
    "sg:classifiers":[
        {
            "category":"Communications",
            "type":"Services"
        }
    ],
    "sg:phone":"+44 1202 894421",
    "sg:postcode":"BH22 0JW",
    "sg:province":"Dorset",
    "sg:tags":[
        "tv",
        "video",
        "radio"
    ],
    "wof:name":"Gordon Hall",
    "wof:placetype":"venue"
},
  "geometry": {"coordinates":[-1.8879400492,50.8253822327],"type":"Point"}
}