{
  "type": "Feature",
  "properties": {
    "addr:full":"5-6 Friar Street Reading Berkshire RG1 1BB",
    "addr:housenumber":"5-6",
    "addr:postcode":"rg1 1bb",
    "addr:street":"Friar Street",
    "iso:country":"GB",
    "sg:address":"5-6 Friar Street",
    "sg:city":"Reading",
    "sg:classifiers":[
        {
            "category":"Bars & Pubs",
            "type":"Food & Drink"
        }
    ],
    "sg:phone":"+44 118 959 0614",
    "sg:postcode":"RG1 1BB",
    "sg:province":"Berkshire",
    "sg:tags":[
        "pubs",
        "inn"
    ],
    "wof:name":"The Old Society",
    "wof:placetype":"venue"
},
  "geometry": {"coordinates":[-0.970434,51.45668],"type":"Point"}
}