{
  "type": "Feature",
  "properties": {
    "iso:country":"GB",
    "sg:address":"St Vincents Works, Silverthorne La",
    "sg:city":"Bristol",
    "sg:classifiers":[
        {
            "category":"Manufacturing",
            "subcategory":"Wood Products",
            "type":"Manufacturing & Wholesale Goods"
        }
    ],
    "sg:phone":"+44 117 977 6087",
    "sg:postcode":"BS2 0QD",
    "sg:province":"City of Bristol",
    "sg:tags":[
        "packaging",
        "crate",
        "pallets"
    ],
    "wof:name":"Blagden Packaging Ltd",
    "wof:placetype":"venue"
},
  "geometry": {"coordinates":[-2.56886,51.45155],"type":"Point"}
}