{
  "type": "Feature",
  "properties": {
    "iso:country":"GB",
    "sg:address":"28 Albion Street",
    "sg:city":"Saxmundham",
    "sg:classifiers":[
        {
            "category":"Organizations",
            "subcategory":"Membership Organization",
            "type":"Services"
        }
    ],
    "sg:phone":"+44 1728 602927",
    "sg:postcode":"IP17 1BL",
    "sg:province":"Suffolk",
    "sg:tags":[
        "club"
    ],
    "wof:name":"Saxmundham Ex-Servicemens Social Club",
    "wof:placetype":"venue"
},
  "geometry": {"coordinates":[1.48782,52.214531],"type":"Point"}
}