{
  "type": "Feature",
  "properties": {
    "addr:full":"8 Lebanon Avenue, Hanworth Feltham Greater London TW13 6RS",
    "addr:housenumber":"8",
    "addr:postcode":"tw13 6rs",
    "addr:street":"Lebanon Avenue",
    "iso:country":"GB",
    "sg:address":"8 Lebanon Avenue, Hanworth",
    "sg:city":"Feltham",
    "sg:classifiers":[
        {
            "category":"Health Services",
            "subcategory":"Health Practitioner",
            "type":"Services"
        }
    ],
    "sg:phone":"+44 20 8898 1146",
    "sg:postcode":"TW13 6RS",
    "sg:province":"Greater London",
    "sg:tags":[
        "physiotherapist",
        "osteopath"
    ],
    "wof:name":"Reginald Patrick Pearce",
    "wof:placetype":"venue"
},
  "geometry": {"coordinates":[-0.39397,51.429848],"type":"Point"}
}