{
  "type": "Feature",
  "properties": {
    "iso:country":"GB",
    "sg:address":"Riding Court, Riding Court Road, Datchet",
    "sg:city":"Slough",
    "sg:classifiers":[
        {
            "category":"Organizations",
            "subcategory":"Community Association",
            "type":"Services"
        }
    ],
    "sg:phone":"+44 1753 595828",
    "sg:postcode":"SL3 9LE",
    "sg:province":"Berkshire",
    "sg:tags":[
        "relation",
        "public"
    ],
    "wof:name":"Bourne River Marketing Communications Plc",
    "wof:placetype":"venue"
},
  "geometry": {"coordinates":[-0.5657600164,51.4871635437],"type":"Point"}
}