{
  "type": "Feature",
  "properties": {
    "iso:country":"GB",
    "sg:address":"2 Tennyson Road",
    "sg:city":"Blackpool",
    "sg:classifiers":[
        {
            "category":"Building & Trades",
            "subcategory":"Construction",
            "type":"Services"
        }
    ],
    "sg:postcode":"FY3 7ET",
    "sg:province":"Lancashire",
    "sg:tags":[
        "roofing"
    ],
    "wof:name":"R & N Davidson & Son",
    "wof:placetype":"venue"
},
  "geometry": {"coordinates":[-3.02596,53.829369],"type":"Point"}
}