{
  "type": "Feature",
  "properties": {
    "addr:full":"Towyn Rd Abergele Conwy LL22 7PY",
    "addr:postcode":"ll22 7py",
    "addr:street":"Towyn Rd",
    "iso:country":"GB",
    "sg:address":"Towyn Rd",
    "sg:city":"Abergele",
    "sg:classifiers":[
        {
            "category":"Farming",
            "subcategory":"Fish & Marine Products",
            "type":"Manufacturing & Wholesale Goods"
        }
    ],
    "sg:postcode":"LL22 7PY",
    "sg:province":"Conwy",
    "sg:tags":[
        "fishmonger"
    ],
    "wof:name":"Warren,S,",
    "wof:placetype":"venue"
},
  "geometry": {"coordinates":[-3.5719339848,53.2962608337],"type":"Point"}
}