{
  "type": "Feature",
  "properties": {
    "addr:full":"Northgate House, St Peters Street Colchester Essex CO1 1HT",
    "addr:postcode":"co1 1ht",
    "addr:street":"Northgate;St Peters Street",
    "iso:country":"GB",
    "sg:address":"Northgate House, St Peters Street",
    "sg:city":"Colchester",
    "sg:classifiers":[
        {
            "category":"Communications",
            "subcategory":"Film & Video Production",
            "type":"Services"
        },
        {
            "category":"Communications",
            "type":"Services"
        }
    ],
    "sg:phone":"+44 1206 764466",
    "sg:postcode":"CO1 1HT",
    "sg:province":"Essex",
    "sg:tags":[
        "tv",
        "broadcasting",
        "radio"
    ],
    "wof:name":"Mellow 1557 Ltd.",
    "wof:placetype":"venue"
},
  "geometry": {"coordinates":[0.8969359994,51.8926124573],"type":"Point"}
}