{
  "type": "Feature",
  "properties": {
    "addr:full":"118-120 The Hornet Chichester West Sussex PO19 4JR",
    "addr:housenumber":"118-120",
    "addr:postcode":"po19 4jr",
    "addr:street":"The Hornet",
    "iso:country":"GB",
    "sg:address":"118-120 The Hornet",
    "sg:city":"Chichester",
    "sg:classifiers":[
        {
            "category":"Shopping",
            "subcategory":"Stationery & Office Supplies",
            "type":"Retail Goods"
        }
    ],
    "sg:phone":"+44 1243 782564",
    "sg:postcode":"PO19 4JR",
    "sg:province":"West Sussex",
    "sg:tags":[
        "drawing"
    ],
    "wof:name":"Reflex Drawing Office Supplies",
    "wof:placetype":"venue"
},
  "geometry": {"coordinates":[-0.7679079771,50.8362197876],"type":"Point"}
}