{
  "type": "Feature",
  "properties": {
    "addr:full":"14 Trafalgar Road Great Yarmouth Norfolk NR30 2LD",
    "addr:housenumber":"14",
    "addr:postcode":"nr30 2ld",
    "addr:street":"Trafalgar Road",
    "iso:country":"GB",
    "sg:address":"14 Trafalgar Road",
    "sg:city":"Great Yarmouth",
    "sg:classifiers":[
        {
            "category":"Travel",
            "subcategory":"Hotels & Motels",
            "type":"Entertainment"
        }
    ],
    "sg:postcode":"NR30 2LD",
    "sg:province":"Norfolk",
    "sg:tags":[
        "house",
        "guest"
    ],
    "wof:name":"Kilbrannan Guest House",
    "wof:placetype":"venue"
},
  "geometry": {"coordinates":[1.7343399525,52.6053924561],"type":"Point"}
}