{
  "type": "Feature",
  "properties": {
    "iso:country":"GB",
    "sg:address":"191 Angel Place",
    "sg:city":"London",
    "sg:classifiers":[
        {
            "category":"Professional",
            "subcategory":"Accounting & Tax Preparation",
            "type":"Services"
        }
    ],
    "sg:phone":"+44 20 8807 8794",
    "sg:postcode":"N18 2UD",
    "sg:province":"Greater London",
    "sg:tags":[
        "accountant"
    ],
    "wof:name":"Wilson Stevens",
    "wof:placetype":"venue"
},
  "geometry": {"coordinates":[-0.064644,51.615086],"type":"Point"}
}