{
  "type": "Feature",
  "properties": {
    "addr:full":"Moorland Rd, Burslem Stoke On Trent Staffordshire ST6 1JP",
    "addr:postcode":"st6 1jp",
    "addr:street":"Moorland Rd",
    "iso:country":"GB",
    "sg:address":"Moorland Rd, Burslem",
    "sg:city":"Stoke On Trent",
    "sg:classifiers":[
        {
            "category":"Bars & Pubs",
            "type":"Food & Drink"
        }
    ],
    "sg:phone":"+44 1782 837702",
    "sg:postcode":"ST6 1JP",
    "sg:province":"Staffordshire",
    "sg:tags":[
        "pubs",
        "inn"
    ],
    "wof:name":"Moorland Road Service Station",
    "wof:placetype":"venue"
},
  "geometry": {"coordinates":[-2.1941690445,53.0462684631],"type":"Point"}
}