{
  "type": "Feature",
  "properties": {
    "addr:full":"Wellesley Road Ilford Essex IG1 4LQ",
    "addr:postcode":"ig1 4lq",
    "addr:street":"Wellesley Road",
    "iso:country":"GB",
    "sg:address":"Wellesley Road",
    "sg:city":"Ilford",
    "sg:classifiers":[
        {
            "category":"Education",
            "subcategory":"School",
            "type":"Public Place"
        },
        {
            "category":"Government",
            "subcategory":"Office",
            "type":"Public Place"
        }
    ],
    "sg:phone":"+44 20 8478 5560",
    "sg:postcode":"IG1 4LQ",
    "sg:province":"Essex",
    "sg:tags":[
        "local",
        "authority"
    ],
    "wof:name":"Christchurch Primary School",
    "wof:placetype":"venue"
},
  "geometry": {"coordinates":[0.080724,51.567211],"type":"Point"}
}