{
  "type": "Feature",
  "properties": {
    "addr:full":"Abbey Park Road Leicester Leicestershire LE4 5AH",
    "addr:postcode":"le4 5ah",
    "addr:street":"Park Road",
    "iso:country":"GB",
    "sg:address":"Abbey Park Road",
    "sg:city":"Leicester",
    "sg:classifiers":[
        {
            "category":"Parking",
            "type":"Transportation"
        }
    ],
    "sg:phone":"+44 116 251 0506",
    "sg:postcode":"LE4 5AH",
    "sg:province":"Leicestershire",
    "sg:tags":[
        "car",
        "valet"
    ],
    "wof:name":"Allbrite Valeting",
    "wof:placetype":"venue"
},
  "geometry": {"coordinates":[-1.1383190155,52.6500816345],"type":"Point"}
}