{
  "type": "Feature",
  "properties": {
    "addr:full":"Sidmouth Road Lyme Regis Devon DT7 3EQ",
    "addr:postcode":"dt7 3eq",
    "addr:street":"Sidmouth Road",
    "iso:country":"GB",
    "sg:address":"Sidmouth Road",
    "sg:city":"Lyme Regis",
    "sg:classifiers":[
        {
            "category":"Professional",
            "subcategory":"Detective & Security Services",
            "type":"Services"
        }
    ],
    "sg:postcode":"DT7 3EQ",
    "sg:province":"Devon",
    "sg:tags":[
        "locksmith"
    ],
    "wof:name":"Dorset Locksmith",
    "wof:placetype":"venue"
},
  "geometry": {"coordinates":[-2.9481089115,50.7258033752],"type":"Point"}
}