{
  "type": "Feature",
  "properties": {
    "addr:full":"Dirleton House, Cainscross Road Stroud Gloucestershire GL5 4ES",
    "addr:postcode":"gl5 4es",
    "addr:street":"Cainscross Road",
    "iso:country":"GB",
    "sg:address":"Dirleton House, Cainscross Road",
    "sg:city":"Stroud",
    "sg:classifiers":[
        {
            "category":"Retail",
            "subcategory":"Funeral Services",
            "type":"Services"
        }
    ],
    "sg:phone":"+44 1453 763592",
    "sg:postcode":"GL5 4ES",
    "sg:province":"Gloucestershire",
    "sg:tags":[
        "director"
    ],
    "wof:name":"Philip Ford & Son (Funeral Directors) Ltd.",
    "wof:placetype":"venue"
},
  "geometry": {"coordinates":[-2.233729,51.744991],"type":"Point"}
}