{
  "type": "Feature",
  "properties": {
    "iso:country":"GB",
    "sg:address":"81 Liverpool Road, Penwortham",
    "sg:city":"Preston",
    "sg:classifiers":[
        {
            "category":"Shopping",
            "subcategory":"Gifts & Souvenirs",
            "type":"Retail Goods"
        }
    ],
    "sg:phone":"+44 1772 750720",
    "sg:postcode":"PR1 0QB",
    "sg:province":"Lancashire",
    "sg:tags":[
        "shop"
    ],
    "wof:name":"Niceties",
    "wof:placetype":"venue"
},
  "geometry": {"coordinates":[-2.7337090969,53.7491416931],"type":"Point"}
}