{
  "type": "Feature",
  "properties": {
    "addr:full":"19 Passingham Walk Waterlooville Hampshire PO8 8JH",
    "addr:housenumber":"19",
    "addr:postcode":"po8 8jh",
    "addr:street":"Passingham Walk",
    "iso:country":"GB",
    "sg:address":"19 Passingham Walk",
    "sg:city":"Waterlooville",
    "sg:classifiers":[
        {
            "category":"Manufacturing",
            "subcategory":"Petroleum Products",
            "type":"Manufacturing & Wholesale Goods"
        }
    ],
    "sg:postcode":"PO8 8JH",
    "sg:province":"Hampshire",
    "sg:tags":[
        "double",
        "glazing"
    ],
    "wof:name":"D G R Double Glazing Repairs",
    "wof:placetype":"venue"
},
  "geometry": {"coordinates":[-1.019544,50.902596],"type":"Point"}
}