{
  "type": "Feature",
  "properties": {
    "iso:country":"GB",
    "sg:address":"Unit 17c Double Row",
    "sg:city":"Whitley Bay",
    "sg:classifiers":[
        {
            "category":"Retail",
            "subcategory":"Auto Repair",
            "type":"Services"
        }
    ],
    "sg:phone":"+44 191 237 4226",
    "sg:postcode":"NE25 0PP",
    "sg:province":"Northumberland",
    "sg:tags":[
        "modification",
        "garage"
    ],
    "wof:name":"R & B Motors",
    "wof:placetype":"venue"
},
  "geometry": {"coordinates":[-1.5315799713,55.0798301697],"type":"Point"}
}