{
  "type": "Feature",
  "properties": {
    "iso:country":"GB",
    "sg:address":"Cryers Hill Rd, Cryers Hill",
    "sg:city":"High Wycombe",
    "sg:classifiers":[
        {
            "category":"Home & Garden",
            "subcategory":"Garden Supply",
            "type":"Retail Goods"
        }
    ],
    "sg:phone":"+44 1494 718766",
    "sg:postcode":"HP15 6LJ",
    "sg:province":"Buckinghamshire",
    "sg:tags":[
        "aggregate",
        "sand",
        "gravel"
    ],
    "wof:name":"The Clive Winslow Group",
    "wof:placetype":"venue"
},
  "geometry": {"coordinates":[-0.749964,51.65971],"type":"Point"}
}