{
  "type": "Feature",
  "properties": {
    "iso:country":"GB",
    "sg:address":"4 Mervyn Place",
    "sg:city":"Bilston",
    "sg:classifiers":[
        {
            "category":"Food & Beverages",
            "subcategory":"Meat & Fish",
            "type":"Retail Goods"
        }
    ],
    "sg:phone":"+44 1902 353953",
    "sg:postcode":"WV14 8DD",
    "sg:province":"West Midlands",
    "sg:tags":[
        "chip"
    ],
    "wof:name":"Mr Phu's Singh for Your Supper",
    "wof:placetype":"venue"
},
  "geometry": {"coordinates":[-2.059777,52.554016],"type":"Point"}
}