{
  "type": "Feature",
  "properties": {
    "addr:full":"17 Lyon Road London Greater London SW19 2SE",
    "addr:housenumber":"17",
    "addr:postcode":"sw19 2se",
    "addr:street":"Lyon Road",
    "iso:country":"GB",
    "sg:address":"17 Lyon Road",
    "sg:city":"London",
    "sg:classifiers":[
        {
            "category":"Professional",
            "subcategory":"Printing & Photocopies",
            "type":"Services"
        }
    ],
    "sg:phone":"+44 20 8543 8082",
    "sg:postcode":"SW19 2SE",
    "sg:province":"Greater London",
    "sg:tags":[
        "printer"
    ],
    "wof:name":"B G Press Ltd.",
    "wof:placetype":"venue"
},
  "geometry": {"coordinates":[-0.1858299971,51.4122619629],"type":"Point"}
}