{
  "type": "Feature",
  "properties": {
    "iso:country":"GB",
    "sg:address":"Strathray, Ukintore",
    "sg:city":"Inverurie",
    "sg:classifiers":[
        {
            "category":"Farming",
            "subcategory":"Dairy Farm",
            "type":"Manufacturing & Wholesale Goods"
        }
    ],
    "sg:phone":"+44 1224 790218",
    "sg:postcode":"AB51 0XE",
    "sg:province":"Aberdeenshire",
    "wof:name":"Strathray Farms Ltd.",
    "wof:placetype":"venue"
},
  "geometry": {"coordinates":[-2.346634,57.234192],"type":"Point"}
}