{
  "type": "Feature",
  "properties": {
    "addr:full":"Unit 3-4, Maer Lane Industrial Estate, Llewellyn Roberts Way Market Drayton Shropshire TF9 1QS",
    "addr:housenumber":"unit 3-4",
    "addr:postcode":"tf9 1qs",
    "addr:street":"Maer Lane Industrial Estate Llewellyn Roberts Way",
    "iso:country":"GB",
    "sg:address":"Unit 3-4, Maer Lane Industrial Estate, Llewellyn Roberts Way",
    "sg:city":"Market Drayton",
    "sg:classifiers":[
        {
            "category":"Home & Garden",
            "subcategory":"Home Furnishings",
            "type":"Retail Goods"
        },
        {
            "category":"Professional",
            "subcategory":"Printing & Photocopies",
            "type":"Services"
        }
    ],
    "sg:phone":"+44 1630 655800",
    "sg:postcode":"TF9 1QS",
    "sg:province":"Shropshire",
    "sg:tags":[
        "tubing",
        "fitting",
        "printer"
    ],
    "wof:name":"Depicton Ltd",
    "wof:placetype":"venue"
},
  "geometry": {"coordinates":[-2.484899044,52.9090881348],"type":"Point"}
}