{
  "type": "Feature",
  "properties": {
    "addr:full":"Greenwich House, Olde English Road Matlock Derbyshire DE4 3SA",
    "addr:postcode":"de4 3sa",
    "addr:street":"Olde English Road",
    "iso:country":"GB",
    "sg:address":"Greenwich House, Olde English Road",
    "sg:city":"Matlock",
    "sg:classifiers":[
        {
            "category":"Social Services",
            "subcategory":"Retirement Home",
            "type":"Services"
        }
    ],
    "sg:phone":"+44 1283 568034",
    "sg:postcode":"DE4 3SA",
    "sg:province":"Derbyshire",
    "sg:tags":[
        "residential",
        "care"
    ],
    "wof:name":"Hemmingway House Ltd.",
    "wof:placetype":"venue"
},
  "geometry": {"coordinates":[-1.5482740402,53.1356163025],"type":"Point"}
}