{
  "type": "Feature",
  "properties": {
    "addr:full":"The Gardens Arbroath Angus DD11 3RH",
    "addr:postcode":"dd11 3rh",
    "addr:street":"Gardens",
    "iso:country":"GB",
    "sg:address":"The Gardens",
    "sg:city":"Arbroath",
    "sg:classifiers":[
        {
            "category":"Real Estate",
            "subcategory":"Developer",
            "type":"Services"
        }
    ],
    "sg:phone":"+44 1241 875788",
    "sg:postcode":"DD11 3RH",
    "sg:province":"Angus",
    "sg:tags":[
        "property"
    ],
    "wof:name":"Woodville Developments (Arbroath) Ltd",
    "wof:placetype":"venue"
},
  "geometry": {"coordinates":[-2.633660078,56.5805892944],"type":"Point"}
}