{
  "type": "Feature",
  "properties": {
    "addr:full":"Fairfield House, Evenwood Gate Bishop Auckland Durham DL14 9NH",
    "addr:postcode":"dl14 9nh",
    "addr:street":"Evenwood Gate",
    "iso:country":"GB",
    "sg:address":"Fairfield House, Evenwood Gate",
    "sg:city":"Bishop Auckland",
    "sg:classifiers":[
        {
            "category":"Shopping",
            "subcategory":"Pharmacy",
            "type":"Retail Goods"
        }
    ],
    "sg:phone":"+44 1388 833321",
    "sg:postcode":"DL14 9NH",
    "sg:province":"Durham",
    "sg:tags":[
        "pharmacist",
        "chemist"
    ],
    "wof:name":"Premier Care",
    "wof:placetype":"venue"
},
  "geometry": {"coordinates":[-1.7596939802,54.6178894043],"type":"Point"}
}