{
  "type": "Feature",
  "properties": {
    "addr:full":"Station Road, East Preston Littlehampton West Sussex BN16 3AA",
    "addr:postcode":"bn16 3aa",
    "addr:street":"Station Road",
    "iso:country":"GB",
    "sg:address":"Station Road, East Preston",
    "sg:city":"Littlehampton",
    "sg:classifiers":[
        {
            "category":"Building & Trades",
            "subcategory":"Plumbing",
            "type":"Services"
        }
    ],
    "sg:phone":"+44 1903 785373",
    "sg:postcode":"BN16 3AA",
    "sg:province":"West Sussex",
    "sg:tags":[
        "drain",
        "clearance",
        "sewer"
    ],
    "wof:name":"Arun Works Services",
    "wof:placetype":"venue"
},
  "geometry": {"coordinates":[-0.502744019,50.8132705688],"type":"Point"}
}