{
  "type": "Feature",
  "properties": {
    "addr:full":"Church Rd, Hanwell Hanwell Greater London W7 3BP",
    "addr:postcode":"w7 3bp",
    "addr:street":"Church Rd",
    "iso:country":"GB",
    "sg:address":"Church Rd, Hanwell",
    "sg:city":"Hanwell",
    "sg:classifiers":[
        {
            "category":"Place Of Worship",
            "type":"Public Place"
        }
    ],
    "sg:phone":"+44 20 8840 0364",
    "sg:postcode":"W7 3BP",
    "sg:province":"Greater London",
    "wof:name":"St. Mary's C of E Church",
    "wof:placetype":"venue"
},
  "geometry": {"coordinates":[-0.3354740143,51.5087814331],"type":"Point"}
}