{
  "type": "Feature",
  "properties": {
    "addr:full":"53a Perry's Lane, Wroughton Swindon Wiltshire SN4 9AZ",
    "addr:housenumber":"53a",
    "addr:postcode":"sn4 9az",
    "addr:street":"Perry'S Lane",
    "iso:country":"GB",
    "sg:address":"53a Perry's Lane, Wroughton",
    "sg:city":"Swindon",
    "sg:classifiers":[
        {
            "category":"Professional",
            "subcategory":"Detective & Security Services",
            "type":"Services"
        }
    ],
    "sg:postcode":"SN4 9AZ",
    "sg:province":"Wiltshire",
    "sg:tags":[
        "alarm",
        "burglar",
        "system"
    ],
    "wof:name":"R & D Security Services",
    "wof:placetype":"venue"
},
  "geometry": {"coordinates":[-1.765938,51.557201],"type":"Point"}
}