{
  "type": "Feature",
  "properties": {
    "iso:country":"GB",
    "sg:address":"Comeytrowe Manor, 19a Comeytrowe Lane Est",
    "sg:city":"Taunton",
    "sg:classifiers":[
        {
            "category":"Shopping",
            "type":"Retail Goods"
        }
    ],
    "sg:phone":"+44 1823 324100",
    "sg:postcode":"TA4 1EF",
    "sg:province":"Devon",
    "sg:tags":[
        "part",
        "accessory"
    ],
    "wof:name":"D & T Used Auto Spares",
    "wof:placetype":"venue"
},
  "geometry": {"coordinates":[-3.135,51.003021],"type":"Point"}
}