{
  "type": "Feature",
  "properties": {
    "iso:country":"GB",
    "sg:address":"Sixth Floor, Linen Hall, 162- Regent Street",
    "sg:city":"London",
    "sg:classifiers":[
        {
            "category":"Professional",
            "subcategory":"Employment Agencies",
            "type":"Services"
        }
    ],
    "sg:phone":"+44 20 7734 0051",
    "sg:postcode":"W1B 5TG",
    "sg:province":"Greater London",
    "sg:tags":[
        "consultant"
    ],
    "wof:name":"Regent Staff Centre",
    "wof:placetype":"venue"
},
  "geometry": {"coordinates":[-0.13996,51.512291],"type":"Point"}
}