{
  "type": "Feature",
  "properties": {
    "addr:full":"66 Lock Street, Abercynon Mountain Ash Rhondda, Cynon, Taff CF45 4UH",
    "addr:housenumber":"66",
    "addr:postcode":"cf45 4uh",
    "addr:street":"Lock Street;Ash;Cynon Taff",
    "iso:country":"GB",
    "sg:address":"66 Lock Street, Abercynon",
    "sg:city":"Mountain Ash",
    "sg:classifiers":[
        {
            "category":"Manufacturing",
            "subcategory":"Metals",
            "type":"Manufacturing & Wholesale Goods"
        },
        {
            "category":"Manufacturing",
            "subcategory":"Furniture",
            "type":"Manufacturing & Wholesale Goods"
        }
    ],
    "sg:phone":"+44 1443 741820",
    "sg:postcode":"CF45 4UH",
    "sg:province":"Rhondda, Cynon, Taff",
    "sg:tags":[
        "polishing",
        "heat",
        "-",
        "treatment",
        "french"
    ],
    "wof:name":"Abercynon French Polisher",
    "wof:placetype":"venue"
},
  "geometry": {"coordinates":[-3.3203499317,51.6498527527],"type":"Point"}
}