{
  "type": "Feature",
  "properties": {
    "addr:full":"8 Meadowside, Grindleton Clitheroe Lancashire BB7 4RR",
    "addr:housenumber":"8;grindleton",
    "addr:postcode":"bb7 4rr",
    "iso:country":"GB",
    "sg:address":"8 Meadowside, Grindleton",
    "sg:city":"Clitheroe",
    "sg:classifiers":[
        {
            "category":"Building & Trades",
            "subcategory":"Landscaping Services",
            "type":"Services"
        }
    ],
    "sg:postcode":"BB7 4RR",
    "sg:province":"Lancashire",
    "sg:tags":[
        "forestry",
        "tree"
    ],
    "wof:name":"Karl T Simpson",
    "wof:placetype":"venue"
},
  "geometry": {"coordinates":[-2.3310890198,53.9127082825],"type":"Point"}
}