{
  "type": "Feature",
  "properties": {
    "iso:country":"GB",
    "sg:address":"Clarence Drive",
    "sg:city":"Filey",
    "sg:classifiers":[
        {
            "category":"Manufacturing",
            "subcategory":"Wood Products",
            "type":"Manufacturing & Wholesale Goods"
        }
    ],
    "sg:phone":"+44 1723 512500",
    "sg:postcode":"YO14 0AA",
    "sg:province":"North Yorkshire",
    "sg:tags":[
        "packaging",
        "crate",
        "pallets"
    ],
    "wof:name":"Zephyr Plastic Products Ltd.",
    "wof:placetype":"venue"
},
  "geometry": {"coordinates":[-0.294869,54.209339],"type":"Point"}
}