{
  "type": "Feature",
  "properties": {
    "addr:full":"1 Melford Tamworth Staffordshire B79 7UX",
    "addr:housenumber":"1",
    "addr:postcode":"b79 7ux",
    "addr:street":"Melford",
    "iso:country":"GB",
    "sg:address":"1 Melford",
    "sg:city":"Tamworth",
    "sg:classifiers":[
        {
            "category":"Professional",
            "subcategory":"Management & Consulting",
            "type":"Services"
        }
    ],
    "sg:postcode":"B79 7UX",
    "sg:province":"Staffordshire",
    "sg:tags":[
        "consultant",
        "business"
    ],
    "wof:name":"Ian Lynch & Co.",
    "wof:placetype":"venue"
},
  "geometry": {"coordinates":[-1.719542,52.64175],"type":"Point"}
}