{
  "type": "Feature",
  "properties": {
    "addr:full":"17-19 Falcon Street Workington Cumbria CA14 2XD",
    "addr:housenumber":"17-19",
    "addr:postcode":"ca14 2xd",
    "addr:street":"Falcon Street",
    "iso:country":"GB",
    "sg:address":"17-19 Falcon Street",
    "sg:city":"Workington",
    "sg:classifiers":[
        {
            "category":"Education",
            "subcategory":"Special Training",
            "type":"Public Place"
        }
    ],
    "sg:phone":"+44 1900 63777",
    "sg:postcode":"CA14 2XD",
    "sg:province":"Cumbria",
    "sg:tags":[
        "product",
        "centre"
    ],
    "wof:name":"City Centre Training",
    "wof:placetype":"venue"
},
  "geometry": {"coordinates":[-3.557349,54.645287],"type":"Point"}
}