{
  "type": "Feature",
  "properties": {
    "addr:full":"25 Bold Street Southport Lancashire PR9 0DB",
    "addr:housenumber":"25",
    "addr:postcode":"pr9 0db",
    "addr:street":"Bold Street",
    "iso:country":"GB",
    "sg:address":"25 Bold Street",
    "sg:city":"Southport",
    "sg:classifiers":[
        {
            "category":"Shopping",
            "subcategory":"Discount & Variety Stores",
            "type":"Retail Goods"
        }
    ],
    "sg:postcode":"PR9 0DB",
    "sg:province":"Lancashire",
    "sg:tags":[
        "shop",
        "model"
    ],
    "wof:name":"The Hobby Shop",
    "wof:placetype":"venue"
},
  "geometry": {"coordinates":[-3.0036,53.651009],"type":"Point"}
}