{
  "type": "Feature",
  "properties": {
    "iso:country":"GB",
    "sg:address":"810 Whitchurch Lane, Whitchurch",
    "sg:city":"Bristol",
    "sg:classifiers":[
        {
            "category":"Manufacturing",
            "subcategory":"Petroleum Products",
            "type":"Manufacturing & Wholesale Goods"
        },
        {
            "category":"Building & Trades",
            "subcategory":"Construction",
            "type":"Services"
        }
    ],
    "sg:phone":"+44 1275 837066",
    "sg:postcode":"BS14 0JP",
    "sg:province":"City of Bristol",
    "sg:tags":[
        "double",
        "glazier",
        "glazing"
    ],
    "wof:name":"Aaron Glass",
    "wof:placetype":"venue"
},
  "geometry": {"coordinates":[-2.566464,51.406837],"type":"Point"}
}