{
  "type": "Feature",
  "properties": {
    "iso:country":"GB",
    "sg:address":"Unit 15 Reaymer Close, Bloxwich",
    "sg:city":"Walsall",
    "sg:classifiers":[
        {
            "category":"Manufacturing",
            "subcategory":"Signs",
            "type":"Manufacturing & Wholesale Goods"
        }
    ],
    "sg:postcode":"WS2 7QZ",
    "sg:province":"West Midlands",
    "sg:tags":[
        "writer"
    ],
    "wof:name":"Q C Signs & Graphics Ltd",
    "wof:placetype":"venue"
},
  "geometry": {"coordinates":[-2.007615,52.606033],"type":"Point"}
}