{
  "type": "Feature",
  "properties": {
    "addr:full":"5 Hilda Place Kettering Northamptonshire NN16 0PX",
    "addr:housenumber":"5",
    "addr:postcode":"nn16 0px",
    "addr:street":"Hilda Place",
    "iso:country":"GB",
    "sg:address":"5 Hilda Place",
    "sg:city":"Kettering",
    "sg:classifiers":[
        {
            "category":"Retail",
            "subcategory":"Repair Shop",
            "type":"Services"
        }
    ],
    "sg:postcode":"NN16 0PX",
    "sg:province":"Northamptonshire",
    "sg:tags":[
        "radio",
        "television",
        "video"
    ],
    "wof:name":"Viditron",
    "wof:placetype":"venue"
},
  "geometry": {"coordinates":[-0.7033860087,52.4075927734],"type":"Point"}
}