{
  "type": "Feature",
  "properties": {
    "addr:full":"First Floor, 32-38 Osnaburgh Street Camden Greater London NW1 3ND",
    "addr:housenumber":"32-38",
    "addr:postcode":"nw1 3nd",
    "addr:street":"Osnaburgh Street",
    "iso:country":"GB",
    "sg:address":"First Floor, 32-38 Osnaburgh Street",
    "sg:city":"Camden",
    "sg:classifiers":[
        {
            "category":"Professional",
            "subcategory":"Lawyer & Legal Services",
            "type":"Services"
        }
    ],
    "sg:phone":"+44 20 7388 6776",
    "sg:postcode":"NW1 3ND",
    "sg:province":"Greater London",
    "wof:name":"Immunity Legal Centre",
    "wof:placetype":"venue"
},
  "geometry": {"coordinates":[-0.142942,51.524864],"type":"Point"}
}