{
  "type": "Feature",
  "properties": {
    "addr:full":"Redhill Street London Greater London NW1 4BD",
    "addr:postcode":"nw1 4bd",
    "addr:street":"Redhill Street",
    "iso:country":"GB",
    "sg:address":"Redhill Street",
    "sg:city":"London",
    "sg:classifiers":[
        {
            "category":"Education",
            "subcategory":"School",
            "type":"Public Place"
        }
    ],
    "sg:phone":"+44 20 7387 7881",
    "sg:postcode":"NW1 4BD",
    "sg:province":"Greater London",
    "sg:tags":[
        "local",
        "authority"
    ],
    "wof:name":"Christ Church C E School",
    "wof:placetype":"venue"
},
  "geometry": {"coordinates":[-0.1437070072,51.5304641724],"type":"Point"}
}