{
  "type": "Feature",
  "properties": {
    "iso:country":"GB",
    "sg:address":"104 Dawlish Road",
    "sg:city":"Birmingham",
    "sg:classifiers":[
        {
            "category":"Social Services",
            "subcategory":"Adult Care",
            "type":"Services"
        }
    ],
    "sg:phone":"+44 121 415 4321",
    "sg:postcode":"B29 7AA",
    "sg:province":"West Midlands",
    "sg:tags":[
        "housing",
        "sheltered"
    ],
    "wof:name":"Sense Midlands Centre",
    "wof:placetype":"venue"
},
  "geometry": {"coordinates":[-1.93006,52.441734],"type":"Point"}
}