{
  "type": "Feature",
  "properties": {
    "addr:full":"122-123 Royal Parade Eastbourne East Sussex BN22 7JY",
    "addr:housenumber":"122-123",
    "addr:postcode":"bn22 7jy",
    "addr:street":"Royal Parade",
    "iso:country":"GB",
    "sg:address":"122-123 Royal Parade",
    "sg:city":"Eastbourne",
    "sg:classifiers":[
        {
            "category":"Travel",
            "subcategory":"Hotels & Motels",
            "type":"Entertainment"
        }
    ],
    "sg:postcode":"BN22 7JY",
    "sg:province":"East Sussex",
    "sg:tags":[
        "house",
        "guest"
    ],
    "wof:name":"Marwood Guest Ho",
    "wof:placetype":"venue"
},
  "geometry": {"coordinates":[0.30488801,50.7777328491],"type":"Point"}
}