{
  "type": "Feature",
  "properties": {
    "addr:full":"4 Gospel Farm Road Birmingham West Midlands B27 7JN",
    "addr:housenumber":"4",
    "addr:postcode":"b27 7jn",
    "addr:street":"Gospel Farm Road",
    "iso:country":"GB",
    "sg:address":"4 Gospel Farm Road",
    "sg:city":"Birmingham",
    "sg:classifiers":[
        {
            "category":"Shopping",
            "subcategory":"News",
            "type":"Retail Goods"
        }
    ],
    "sg:phone":"+44 121 777 3700",
    "sg:postcode":"B27 7JN",
    "sg:province":"West Midlands",
    "sg:tags":[
        "newsagent"
    ],
    "wof:name":"Jays News",
    "wof:placetype":"venue"
},
  "geometry": {"coordinates":[-1.825613,52.429661],"type":"Point"}
}