{
  "type": "Feature",
  "properties": {
    "addr:full":"26 Hobson Way, Holbury Southampton Hampshire SO45 2GE",
    "addr:housenumber":"26",
    "addr:postcode":"so45 2ge",
    "addr:street":"Hobson Way",
    "iso:country":"GB",
    "sg:address":"26 Hobson Way, Holbury",
    "sg:city":"Southampton",
    "sg:classifiers":[
        {
            "category":"Building & Trades",
            "subcategory":"Construction",
            "type":"Services"
        }
    ],
    "sg:phone":"+44 23 8089 2780",
    "sg:postcode":"SO45 2GE",
    "sg:province":"Hampshire",
    "sg:tags":[
        "decorator",
        "painter"
    ],
    "wof:name":"Henry House",
    "wof:placetype":"venue"
},
  "geometry": {"coordinates":[-1.382103,50.82653],"type":"Point"}
}