{
  "type": "Feature",
  "properties": {
    "iso:country":"GB",
    "sg:address":"St Georges Rd",
    "sg:city":"Lytham St Annes",
    "sg:classifiers":[
        {
            "category":"Autos & Motor Vehicles",
            "subcategory":"Automobile Sales",
            "type":"Retail Goods"
        }
    ],
    "sg:phone":"+44 1253 722241",
    "sg:postcode":"FY8 2AH",
    "sg:province":"Lancashire",
    "sg:tags":[
        "car"
    ],
    "wof:name":"Dean Smith",
    "wof:placetype":"venue"
},
  "geometry": {"coordinates":[-3.031129,53.752853],"type":"Point"}
}