{
  "type": "Feature",
  "properties": {
    "iso:country":"GB",
    "sg:address":"Varrier Jones Drive, Papworth Everard",
    "sg:city":"Cambridge",
    "sg:classifiers":[
        {
            "category":"Education",
            "subcategory":"School",
            "type":"Public Place"
        }
    ],
    "sg:phone":"+44 1480 830267",
    "sg:postcode":"CB3 8XQ",
    "sg:province":"Cambridgeshire",
    "sg:tags":[
        "local",
        "authority"
    ],
    "wof:name":"Pendragon Community Primary School",
    "wof:placetype":"venue"
},
  "geometry": {"coordinates":[-0.117424,52.24868],"type":"Point"}
}