{
  "type": "Feature",
  "properties": {
    "addr:full":"Oxford Road, Stone Aylesbury Buckinghamshire HP17 8NP",
    "addr:postcode":"hp17 8np",
    "addr:street":"Oxford Road Stone",
    "iso:country":"GB",
    "sg:address":"Oxford Road, Stone",
    "sg:city":"Aylesbury",
    "sg:classifiers":[
        {
            "category":"Sports & Exercise",
            "subcategory":"Stables",
            "type":"Entertainment"
        },
        {
            "category":"Arena",
            "subcategory":"Sports Club",
            "type":"Entertainment"
        }
    ],
    "sg:phone":"+44 1296 748641",
    "sg:postcode":"HP17 8NP",
    "sg:province":"Buckinghamshire",
    "sg:tags":[
        "education",
        "equestrian"
    ],
    "wof:name":"Hartwell Riding Stables Ltd",
    "wof:placetype":"venue"
},
  "geometry": {"coordinates":[-0.8532890081,51.8036994934],"type":"Point"}
}