{
  "type": "Feature",
  "properties": {
    "addr:full":"88 Worksop Road, Swallownest Sheffield South Yorkshire S26 4WB",
    "addr:housenumber":"88",
    "addr:postcode":"s26 4wb",
    "addr:street":"Worksop Road",
    "iso:country":"GB",
    "sg:address":"88 Worksop Road, Swallownest",
    "sg:city":"Sheffield",
    "sg:classifiers":[
        {
            "category":"Retail",
            "subcategory":"Funeral Services",
            "type":"Services"
        }
    ],
    "sg:phone":"+44 114 287 5852",
    "sg:postcode":"S26 4WB",
    "sg:province":"South Yorkshire",
    "wof:name":"Co-Operative Funeral Services",
    "wof:placetype":"venue"
},
  "geometry": {"coordinates":[-1.3155200481,53.3632621765],"type":"Point"}
}