{
  "type": "Feature",
  "properties": {
    "addr:full":"3 Dalgety Avenue Edinburgh City of Edinburgh EH7 5UF",
    "addr:housenumber":"3",
    "addr:postcode":"eh7 5uf",
    "addr:street":"Dalgety Avenue Edinburgh",
    "iso:country":"GB",
    "sg:address":"3 Dalgety Avenue",
    "sg:city":"Edinburgh",
    "sg:classifiers":[
        {
            "category":"Professional",
            "subcategory":"Business Services",
            "type":"Services"
        }
    ],
    "sg:phone":"+44 131 620 7037",
    "sg:postcode":"EH7 5UF",
    "sg:province":"City of Edinburgh",
    "sg:tags":[
        "import",
        "export",
        "agent"
    ],
    "wof:name":"Floral Decor",
    "wof:placetype":"venue"
},
  "geometry": {"coordinates":[-3.173795,55.957458],"type":"Point"}
}