{
  "type": "Feature",
  "properties": {
    "addr:full":"98 Streatham High Road London Greater London SW16 1BS",
    "addr:housenumber":"98",
    "addr:postcode":"sw16 1bs",
    "addr:street":"Streatham High Road",
    "iso:country":"GB",
    "sg:address":"98 Streatham High Road",
    "sg:city":"London",
    "sg:classifiers":[
        {
            "category":"Shopping",
            "subcategory":"Party Supplies",
            "type":"Retail Goods"
        }
    ],
    "sg:phone":"+44 20 8769 7140",
    "sg:postcode":"SW16 1BS",
    "sg:province":"Greater London",
    "sg:tags":[
        "novelty"
    ],
    "wof:name":"Nirco Ltd.",
    "wof:placetype":"venue"
},
  "geometry": {"coordinates":[-0.128361,51.434856],"type":"Point"}
}