{
  "type": "Feature",
  "properties": {
    "addr:full":"26 London End Beaconsfield Buckinghamshire HP9 2JH",
    "addr:housenumber":"26",
    "addr:postcode":"hp9 2jh",
    "addr:street":"London End",
    "iso:country":"GB",
    "sg:address":"26 London End",
    "sg:city":"Beaconsfield",
    "sg:classifiers":[
        {
            "category":"Home & Garden",
            "subcategory":"Garden Supply",
            "type":"Retail Goods"
        }
    ],
    "sg:phone":"+44 1494 678151",
    "sg:postcode":"HP9 2JH",
    "sg:province":"Buckinghamshire",
    "sg:tags":[
        "flower",
        "shrub"
    ],
    "wof:name":"The Conservatory Ltd",
    "wof:placetype":"venue"
},
  "geometry": {"coordinates":[-0.635631,51.601795],"type":"Point"}
}