{
  "type": "Feature",
  "properties": {
    "iso:country":"GB",
    "sg:address":"33 Meadowside Dr, Whitchurch",
    "sg:city":"Bristol",
    "sg:classifiers":[
        {
            "category":"Building & Trades",
            "subcategory":"Cleaning & Sanitation",
            "type":"Services"
        }
    ],
    "sg:postcode":"BS14 0NR",
    "sg:province":"City of Bristol",
    "sg:tags":[
        "commercial"
    ],
    "wof:name":"Owen,T,",
    "wof:placetype":"venue"
},
  "geometry": {"coordinates":[-2.5759,51.40464],"type":"Point"}
}