{
  "type": "Feature",
  "properties": {
    "addr:full":"Room 17 Charing Cross Norwich Norfolk NR2 4AX",
    "addr:housenumber":"17",
    "addr:postcode":"nr2 4ax",
    "addr:street":"Charing Cross Norwich Norfolk",
    "iso:country":"GB",
    "sg:address":"Room 17 Charing Cross",
    "sg:city":"Norwich",
    "sg:classifiers":[
        {
            "category":"Professional",
            "subcategory":"Testing Lab",
            "type":"Services"
        }
    ],
    "sg:phone":"+44 1603 660298",
    "sg:postcode":"NR2 4AX",
    "sg:province":"Norfolk",
    "sg:tags":[
        "pregnancy"
    ],
    "wof:name":"Life Pregnancy Care Service",
    "wof:placetype":"venue"
},
  "geometry": {"coordinates":[1.2925070524,52.6307754517],"type":"Point"}
}