{
  "type": "Feature",
  "properties": {
    "addr:full":"20 Middle Watch Cambridge Cambridgeshire CB4 5RN",
    "addr:housenumber":"20",
    "addr:postcode":"cb4 5rn",
    "addr:street":"Middle Watch",
    "iso:country":"GB",
    "sg:address":"20 Middle Watch",
    "sg:city":"Cambridge",
    "sg:classifiers":[
        {
            "category":"Retail",
            "subcategory":"Auto Repair",
            "type":"Services"
        }
    ],
    "sg:phone":"+44 1954 230264",
    "sg:postcode":"CB4 5RN",
    "sg:province":"Cambridgeshire",
    "sg:tags":[
        "modification",
        "garage"
    ],
    "wof:name":"Clutch Point",
    "wof:placetype":"venue"
},
  "geometry": {"coordinates":[-0.003166,52.297688],"type":"Point"}
}