{
  "type": "Feature",
  "properties": {
    "addr:full":"10a-12a Broughton Street Edinburgh City of Edinburgh EH1 3RH",
    "addr:housenumber":"10a-12a",
    "addr:postcode":"eh1 3rh",
    "addr:street":"Broughton Street",
    "iso:country":"GB",
    "sg:address":"10a-12a Broughton Street",
    "sg:city":"Edinburgh",
    "sg:classifiers":[
        {
            "category":"Bars & Pubs",
            "type":"Food & Drink"
        },
        {
            "category":"Community Center",
            "subcategory":"Social",
            "type":"Public Place"
        }
    ],
    "sg:phone":"+44 131 557 0097",
    "sg:postcode":"EH1 3RH",
    "sg:province":"City of Edinburgh",
    "sg:tags":[
        "pubs",
        "house",
        "inn",
        "activity"
    ],
    "wof:name":"The Basement",
    "wof:placetype":"venue"
},
  "geometry": {"coordinates":[-3.18832,55.956955],"type":"Point"}
}