{
  "type": "Feature",
  "properties": {
    "iso:country":"GB",
    "sg:address":"Morley Cottage, Cooksbridge",
    "sg:city":"Lewes",
    "sg:classifiers":[
        {
            "category":"Farming",
            "subcategory":"Livestock Farm",
            "type":"Manufacturing & Wholesale Goods"
        }
    ],
    "sg:phone":"+44 1273 401883",
    "sg:postcode":"BN8 4ST",
    "sg:province":"East Sussex",
    "sg:tags":[
        "others"
    ],
    "wof:name":"K G Freeman & Son",
    "wof:placetype":"venue"
},
  "geometry": {"coordinates":[-0.008204,50.904427],"type":"Point"}
}