{
  "type": "Feature",
  "properties": {
    "addr:full":"39 Roscoe Street Scarborough North Yorkshire YO12 7BX",
    "addr:housenumber":"39",
    "addr:postcode":"yo12 7bx",
    "addr:street":"Roscoe Street",
    "iso:country":"GB",
    "sg:address":"39 Roscoe Street",
    "sg:city":"Scarborough",
    "sg:classifiers":[
        {
            "category":"Manufacturing",
            "subcategory":"Metals",
            "type":"Manufacturing & Wholesale Goods"
        }
    ],
    "sg:phone":"+44 1723 376870",
    "sg:postcode":"YO12 7BX",
    "sg:province":"North Yorkshire",
    "sg:tags":[
        "product",
        "fabricated"
    ],
    "wof:name":"Cherry Fabrications",
    "wof:placetype":"venue"
},
  "geometry": {"coordinates":[-0.411706,54.279804],"type":"Point"}
}