{
  "type": "Feature",
  "properties": {
    "addr:full":"71 High Street Heathfield East Sussex TN21 8HU",
    "addr:housenumber":"71",
    "addr:postcode":"tn21 8hu",
    "addr:street":"High Street",
    "iso:country":"GB",
    "sg:address":"71 High Street",
    "sg:city":"Heathfield",
    "sg:classifiers":[
        {
            "category":"Real Estate",
            "subcategory":"Real Estate Agent",
            "type":"Services"
        }
    ],
    "sg:postcode":"TN21 8HU",
    "sg:province":"East Sussex",
    "wof:name":"Beacroft Young & Puplett",
    "wof:placetype":"venue"
},
  "geometry": {"coordinates":[0.2484460026,50.9705085754],"type":"Point"}
}