{
  "type": "Feature",
  "properties": {
    "addr:full":"7 Oakes Rd Huddersfield West Yorkshire HD3 3EW",
    "addr:housenumber":"7",
    "addr:postcode":"hd3 3ew",
    "addr:street":"Oakes Rd",
    "iso:country":"GB",
    "sg:address":"7 Oakes Rd",
    "sg:city":"Huddersfield",
    "sg:classifiers":[
        {
            "category":"Farming",
            "subcategory":"Fish & Marine Products",
            "type":"Manufacturing & Wholesale Goods"
        }
    ],
    "sg:postcode":"HD3 3EW",
    "sg:province":"West Yorkshire",
    "sg:tags":[
        "fishmonger"
    ],
    "wof:name":"Hizzard,Brian,",
    "wof:placetype":"venue"
},
  "geometry": {"coordinates":[-1.823954,53.654205],"type":"Point"}
}