{
  "type": "Feature",
  "properties": {
    "iso:country":"GB",
    "sg:address":"Esh",
    "sg:city":"Durham",
    "sg:classifiers":[
        {
            "category":"Organizations",
            "subcategory":"Religious Organization",
            "type":"Services"
        }
    ],
    "sg:phone":"+44 191 373 1217",
    "sg:postcode":"DH7 9QY",
    "sg:province":"Durham",
    "sg:tags":[
        "organisation",
        "place",
        "worship"
    ],
    "wof:name":"St Michaels Convent Of Mercy",
    "wof:placetype":"venue"
},
  "geometry": {"coordinates":[-1.7062799931,54.7879219055],"type":"Point"}
}