{
  "type": "Feature",
  "properties": {
    "addr:full":"Castle Hill Bodmin Cornwall PL31 2DU",
    "addr:postcode":"pl31 2du",
    "addr:street":"Hill",
    "iso:country":"GB",
    "sg:address":"Castle Hill",
    "sg:city":"Bodmin",
    "sg:classifiers":[
        {
            "category":"Social Services",
            "subcategory":"Retirement Home",
            "type":"Services"
        }
    ],
    "sg:phone":"+44 1208 72310",
    "sg:postcode":"PL31 2DU",
    "sg:province":"Cornwall",
    "sg:tags":[
        "residential",
        "care"
    ],
    "wof:name":"White House The",
    "wof:placetype":"venue"
},
  "geometry": {"coordinates":[-4.716369,50.471046],"type":"Point"}
}