{
  "type": "Feature",
  "properties": {
    "addr:full":"121 Uxbridge Road London Greater London W12 8NL",
    "addr:housenumber":"121",
    "addr:postcode":"w12 8nl",
    "addr:street":"Uxbridge Road",
    "iso:country":"GB",
    "sg:address":"121 Uxbridge Road",
    "sg:city":"London",
    "sg:classifiers":[
        {
            "category":"Restaurant",
            "type":"Food & Drink"
        }
    ],
    "sg:phone":"+44 20 8740 7551",
    "sg:postcode":"W12 8NL",
    "sg:province":"Greater London",
    "sg:tags":[
        "indian",
        "-"
    ],
    "wof:name":"Nepalese Tandoori Restaurant",
    "wof:placetype":"venue"
},
  "geometry": {"coordinates":[-0.233583,51.506325],"type":"Point"}
}