{
  "type": "Feature",
  "properties": {
    "addr:full":"25a Newport Road Caldicot Monmouthshire NP26 4BG",
    "addr:housenumber":"25a",
    "addr:postcode":"np26 4bg",
    "addr:street":"Newport Road",
    "iso:country":"GB",
    "sg:address":"25a Newport Road",
    "sg:city":"Caldicot",
    "sg:classifiers":[
        {
            "category":"Personal",
            "subcategory":"Beauty Salon",
            "type":"Services"
        },
        {
            "category":"Personal",
            "subcategory":"Barber",
            "type":"Services"
        }
    ],
    "sg:phone":"+44 1291 421116",
    "sg:postcode":"NP26 4BG",
    "sg:province":"Monmouthshire",
    "sg:tags":[
        "unisex",
        "hairdresser"
    ],
    "wof:name":"Geoff's Hairstyling",
    "wof:placetype":"venue"
},
  "geometry": {"coordinates":[-2.753809,51.590069],"type":"Point"}
}