{
  "type": "Feature",
  "properties": {
    "addr:full":"17 Orchard Drive, Cowley Uxbridge Buckinghamshire UB8 3AE",
    "addr:housenumber":"17",
    "addr:postcode":"ub8 3ae",
    "addr:street":"Orchard Drive",
    "iso:country":"GB",
    "sg:address":"17 Orchard Drive, Cowley",
    "sg:city":"Uxbridge",
    "sg:classifiers":[
        {
            "category":"Building & Trades",
            "subcategory":"Plumbing",
            "type":"Services"
        }
    ],
    "sg:phone":"+44 1895 237838",
    "sg:postcode":"UB8 3AE",
    "sg:province":"Buckinghamshire",
    "sg:tags":[
        "central",
        "heating"
    ],
    "wof:name":"A V B Plumbing",
    "wof:placetype":"venue"
},
  "geometry": {"coordinates":[-0.4771589935,51.5291595459],"type":"Point"}
}