{
  "type": "Feature",
  "properties": {
    "iso:country":"GB",
    "sg:address":", Llangadfan",
    "sg:city":"Welshpool",
    "sg:classifiers":[
        {
            "category":"Bars & Pubs",
            "type":"Food & Drink"
        }
    ],
    "sg:phone":"+44 1938 820202",
    "sg:postcode":"SY21 0PL",
    "sg:province":"Shropshire",
    "sg:tags":[
        "pubs",
        "inn"
    ],
    "wof:name":"Cann Office Hotel",
    "wof:placetype":"venue"
},
  "geometry": {"coordinates":[-3.4635119438,52.6859054565],"type":"Point"}
}