{
  "type": "Feature",
  "properties": {
    "iso:country":"GB",
    "sg:address":"Talsarn Farm, Cwmdu",
    "sg:city":"Crickhowell",
    "sg:classifiers":[
        {
            "category":"Government",
            "subcategory":"Customs House",
            "type":"Public Place"
        }
    ],
    "sg:phone":"+44 1874 730615",
    "sg:postcode":"NP8 1RS",
    "sg:province":"Monmouthshire",
    "sg:tags":[
        "clearance"
    ],
    "wof:name":"S Games",
    "wof:placetype":"venue"
},
  "geometry": {"coordinates":[-3.138122,51.861626],"type":"Point"}
}