{
  "type": "Feature",
  "properties": {
    "addr:full":"57 Albert Rd Southport Lancashire PR9 9LN",
    "addr:housenumber":"57",
    "addr:postcode":"pr9 9ln",
    "addr:street":"Albert Rd",
    "iso:country":"GB",
    "sg:address":"57 Albert Rd",
    "sg:city":"Southport",
    "sg:classifiers":[
        {
            "category":"Health Services",
            "subcategory":"Nursing And Care Facility",
            "type":"Services"
        }
    ],
    "sg:phone":"+44 1704 546438",
    "sg:postcode":"PR9 9LN",
    "sg:province":"Lancashire",
    "sg:tags":[
        "home"
    ],
    "wof:name":"Albert Road Nursing Home",
    "wof:placetype":"venue"
},
  "geometry": {"coordinates":[-2.991279,53.656418],"type":"Point"}
}