{
  "type": "Feature",
  "properties": {
    "addr:full":"Victoria Rd Runcorn Cheshire WA7 5BN",
    "addr:postcode":"wa7 5bn",
    "addr:street":"Victoria Rd",
    "iso:country":"GB",
    "sg:address":"Victoria Rd",
    "sg:city":"Runcorn",
    "sg:classifiers":[
        {
            "category":"Education",
            "subcategory":"School",
            "type":"Public Place"
        }
    ],
    "sg:phone":"+44 1928 574644",
    "sg:postcode":"WA7 5BN",
    "sg:province":"Cheshire",
    "sg:tags":[
        "local",
        "authority"
    ],
    "wof:name":"Victoria Road County Primary School",
    "wof:placetype":"venue"
},
  "geometry": {"coordinates":[-2.728853941,53.3380813599],"type":"Point"}
}