{
  "type": "Feature",
  "properties": {
    "addr:full":"Unit 7 Douglas House, 32-34 Simpson Road, Fenny Stratford Milton Keynes Buckinghamshire MK1 1BA",
    "addr:housenumber":"unit 7;32-34",
    "addr:postcode":"mk1 1ba",
    "addr:street":"Douglas;Simpson Road",
    "iso:country":"GB",
    "sg:address":"Unit 7 Douglas House, 32-34 Simpson Road, Fenny Stratford",
    "sg:city":"Milton Keynes",
    "sg:classifiers":[
        {
            "category":"Building & Trades",
            "subcategory":"Cleaning & Sanitation",
            "type":"Services"
        }
    ],
    "sg:phone":"+44 1908 368899",
    "sg:postcode":"MK1 1BA",
    "sg:province":"Buckinghamshire",
    "sg:tags":[
        "commercial"
    ],
    "wof:name":"Mitie Group",
    "wof:placetype":"venue"
},
  "geometry": {"coordinates":[-0.7155990005,52.000629425],"type":"Point"}
}