{
  "type": "Feature",
  "properties": {
    "iso:country":"GB",
    "sg:address":"1020 Chester Rd, Erdington",
    "sg:city":"Birmingham",
    "sg:classifiers":[
        {
            "category":"Manufacturing",
            "subcategory":"Wood Products",
            "type":"Manufacturing & Wholesale Goods"
        }
    ],
    "sg:postcode":"B24 0LL",
    "sg:province":"West Midlands",
    "sg:tags":[
        "sawmill",
        "shaving"
    ],
    "wof:name":"Lynch,Mark,",
    "wof:placetype":"venue"
},
  "geometry": {"coordinates":[-1.809642,52.524471],"type":"Point"}
}