{
  "type": "Feature",
  "properties": {
    "addr:full":"13 Manse Street Tain Highland IV19 1HE",
    "addr:housenumber":"13",
    "addr:postcode":"iv19 1he",
    "addr:street":"Manse Street",
    "iso:country":"GB",
    "sg:address":"13 Manse Street",
    "sg:city":"Tain",
    "sg:classifiers":[
        {
            "category":"Professional",
            "subcategory":"Management & Consulting",
            "type":"Services"
        }
    ],
    "sg:postcode":"IV19 1HE",
    "sg:province":"Highland",
    "sg:tags":[
        "consultant",
        "geophysical",
        "geological"
    ],
    "wof:name":"Parker Associates",
    "wof:placetype":"venue"
},
  "geometry": {"coordinates":[-4.058339119,57.8124847412],"type":"Point"}
}