{
  "type": "Feature",
  "properties": {
    "iso:country":"GB",
    "sg:address":"Stable Court Ferrars Road",
    "sg:city":"Huntingdon",
    "sg:classifiers":[
        {
            "category":"Banks & Credit Unions",
            "subcategory":"Bureau De Change",
            "type":"Services"
        }
    ],
    "sg:postcode":"PE29 3DH",
    "sg:province":"Cambridgeshire",
    "sg:tags":[
        "town",
        "consultant",
        "planning"
    ],
    "wof:name":"Andrew S Campbell Associates",
    "wof:placetype":"venue"
},
  "geometry": {"coordinates":[-0.187509,52.332531],"type":"Point"}
}