{
  "type": "Feature",
  "properties": {
    "addr:full":"Oakmills, Lower Mill Street Tillicoultry Clackmannanshire FK13 6BP",
    "addr:postcode":"fk13 6bp",
    "addr:street":"Lower Mill Street",
    "iso:country":"GB",
    "sg:address":"Oakmills, Lower Mill Street",
    "sg:city":"Tillicoultry",
    "sg:classifiers":[
        {
            "category":"Freight",
            "type":"Transportation"
        }
    ],
    "sg:phone":"+44 1259 750459",
    "sg:postcode":"FK13 6BP",
    "sg:province":"Clackmannanshire",
    "sg:tags":[
        "haulage",
        "road"
    ],
    "wof:name":"J B P Transport Ltd.",
    "wof:placetype":"venue"
},
  "geometry": {"coordinates":[-3.742110014,56.1532669067],"type":"Point"}
}