{
  "type": "Feature",
  "properties": {
    "addr:full":"2 Upper Street South, New Ash Green Longfield Kent DA3 8JJ",
    "addr:housenumber":"2",
    "addr:postcode":"da3 8jj",
    "addr:street":"Upper Street South",
    "iso:country":"GB",
    "sg:address":"2 Upper Street South, New Ash Green",
    "sg:city":"Longfield",
    "sg:classifiers":[
        {
            "category":"Real Estate",
            "subcategory":"Real Estate Agent",
            "type":"Services"
        }
    ],
    "sg:postcode":"DA3 8JJ",
    "sg:province":"Kent",
    "wof:name":"Hornglade Projects Ltd.",
    "wof:placetype":"venue"
},
  "geometry": {"coordinates":[0.302167,51.365288],"type":"Point"}
}