{
  "type": "Feature",
  "properties": {
    "addr:full":"Alkerton Road, Eastington Stonehouse Gloucestershire GL10 3RT",
    "addr:postcode":"gl10 3rt",
    "addr:street":"Alkerton Road",
    "iso:country":"GB",
    "sg:address":"Alkerton Road, Eastington",
    "sg:city":"Stonehouse",
    "sg:classifiers":[
        {
            "category":"Bars & Pubs",
            "type":"Food & Drink"
        }
    ],
    "sg:phone":"+44 1453 822892",
    "sg:postcode":"GL10 3RT",
    "sg:province":"Gloucestershire",
    "sg:tags":[
        "pubs",
        "inn"
    ],
    "wof:name":"Victoria Inn",
    "wof:placetype":"venue"
},
  "geometry": {"coordinates":[-2.325842,51.746082],"type":"Point"}
}