{
  "type": "Feature",
  "properties": {
    "addr:full":"Wormiston Farm, Crail Anstruther Fife KY10 3XH",
    "addr:postcode":"ky10 3xh",
    "addr:street":"Crail",
    "iso:country":"GB",
    "sg:address":"Wormiston Farm, Crail",
    "sg:city":"Anstruther",
    "sg:classifiers":[
        {
            "category":"Farming",
            "subcategory":"Livestock Farm",
            "type":"Manufacturing & Wholesale Goods"
        }
    ],
    "sg:postcode":"KY10 3XH",
    "sg:province":"Fife",
    "sg:tags":[
        "others"
    ],
    "wof:name":"C & A Edie",
    "wof:placetype":"venue"
},
  "geometry": {"coordinates":[-2.7009840012,56.2228851318],"type":"Point"}
}