{
  "type": "Feature",
  "properties": {
    "addr:full":"The Pippin Calne Wiltshire SN11 8JG",
    "addr:postcode":"sn11 8jg",
    "iso:country":"GB",
    "sg:address":"The Pippin",
    "sg:city":"Calne",
    "sg:classifiers":[
        {
            "category":"Food & Beverages",
            "subcategory":"Supermarket",
            "type":"Retail Goods"
        }
    ],
    "sg:phone":"+44 1249 815927",
    "sg:postcode":"SN11 8JG",
    "sg:province":"Wiltshire",
    "wof:name":"Sainsbury's Supermarkets Ltd.",
    "wof:placetype":"venue"
},
  "geometry": {"coordinates":[-2.0025839806,51.4402961731],"type":"Point"}
}