{
  "type": "Feature",
  "properties": {
    "iso:country":"GB",
    "sg:address":"Springfield, 23 Church Road",
    "sg:city":"Bridgwater",
    "sg:classifiers":[
        {
            "category":"Building & Trades",
            "subcategory":"Construction",
            "type":"Services"
        }
    ],
    "sg:phone":"+44 1278 683476",
    "sg:postcode":"TA7 8PY",
    "sg:province":"Somerset",
    "sg:tags":[
        "builder"
    ],
    "wof:name":"M R Hawkins",
    "wof:placetype":"venue"
},
  "geometry": {"coordinates":[-2.94317,51.1511],"type":"Point"}
}