{
  "type": "Feature",
  "properties": {
    "iso:country":"GB",
    "sg:address":"Ian Bell & Co Delta 606, Weldon Road Delta Office Park",
    "sg:city":"Swindon",
    "sg:classifiers":[
        {
            "category":"Professional",
            "subcategory":"Computer Services",
            "type":"Services"
        }
    ],
    "sg:postcode":"SN5 7XF",
    "sg:province":"Wiltshire",
    "sg:tags":[
        "system",
        "software"
    ],
    "wof:name":"Sentinel Ltd",
    "wof:placetype":"venue"
},
  "geometry": {"coordinates":[-1.8161699772,51.5567588806],"type":"Point"}
}