{
  "type": "Feature",
  "properties": {
    "addr:full":"18 Richfield Av Reading Berkshire RG1 8EQ",
    "addr:housenumber":"18",
    "addr:postcode":"rg1 8eq",
    "addr:street":"Richfield Av",
    "iso:country":"GB",
    "sg:address":"18 Richfield Av",
    "sg:city":"Reading",
    "sg:classifiers":[
        {
            "category":"Bars & Pubs",
            "subcategory":"Nightclub",
            "type":"Food & Drink"
        }
    ],
    "sg:phone":"+44 118 939 1888",
    "sg:postcode":"RG1 8EQ",
    "sg:province":"Berkshire",
    "sg:tags":[
        "club",
        "night"
    ],
    "wof:name":"Churchill Night Club",
    "wof:placetype":"venue"
},
  "geometry": {"coordinates":[-0.9830170274,51.4642028809],"type":"Point"}
}