{
  "type": "Feature",
  "properties": {
    "addr:full":"79 Cheshire Street Market Drayton Shropshire TF9 1PN",
    "addr:housenumber":"79",
    "addr:postcode":"tf9 1pn",
    "addr:street":"Cheshire Street",
    "iso:country":"GB",
    "sg:address":"79 Cheshire Street",
    "sg:city":"Market Drayton",
    "sg:classifiers":[
        {
            "category":"Travel",
            "subcategory":"Hotels & Motels",
            "type":"Entertainment"
        }
    ],
    "sg:phone":"+44 1630 652083",
    "sg:postcode":"TF9 1PN",
    "sg:province":"Shropshire",
    "wof:name":"Railway Hotel",
    "wof:placetype":"venue"
},
  "geometry": {"coordinates":[-2.4862709045,52.9057579041],"type":"Point"}
}