{
  "type": "Feature",
  "properties": {
    "addr:full":"2a Elphinstone Road Hastings East Sussex TN34 2EE",
    "addr:housenumber":"2a",
    "addr:postcode":"tn34 2ee",
    "addr:street":"Elphinstone Road",
    "iso:country":"GB",
    "sg:address":"2a Elphinstone Road",
    "sg:city":"Hastings",
    "sg:classifiers":[
        {
            "category":"Shopping",
            "subcategory":"Used Merchandise",
            "type":"Retail Goods"
        }
    ],
    "sg:phone":"+44 1424 430480",
    "sg:postcode":"TN34 2EE",
    "sg:province":"East Sussex",
    "sg:tags":[
        "shop",
        "second-hand"
    ],
    "wof:name":"M & M Secondhand",
    "wof:placetype":"venue"
},
  "geometry": {"coordinates":[0.583388,50.862705],"type":"Point"}
}