{
  "type": "Feature",
  "properties": {
    "iso:country":"GB",
    "sg:address":"225 Park Lane",
    "sg:city":"Macclesfield",
    "sg:classifiers":[
        {
            "category":"Professional",
            "subcategory":"Art Services",
            "type":"Services"
        }
    ],
    "sg:postcode":"SK11 8AA",
    "sg:province":"Cheshire",
    "sg:tags":[
        "photographer"
    ],
    "wof:name":"Mike Pritchard Photography",
    "wof:placetype":"venue"
},
  "geometry": {"coordinates":[-2.131113,53.253399],"type":"Point"}
}