{
  "type": "Feature",
  "properties": {
    "addr:full":"191 Copnor Road Portsmouth Hampshire PO3 5BY",
    "addr:housenumber":"191",
    "addr:postcode":"hampshire po3 5by",
    "addr:street":"Copnor Road",
    "iso:country":"GB",
    "sg:address":"191 Copnor Road",
    "sg:city":"Portsmouth",
    "sg:classifiers":[
        {
            "category":"Food & Beverages",
            "subcategory":"Supermarket",
            "type":"Retail Goods"
        }
    ],
    "sg:phone":"+44 23 9266 9794",
    "sg:postcode":"PO3 5BY",
    "sg:province":"Hampshire",
    "wof:name":"Co-Op Foodstore",
    "wof:placetype":"venue"
},
  "geometry": {"coordinates":[-1.064696,50.816254],"type":"Point"}
}