{
  "type": "Feature",
  "properties": {
    "iso:country":"GB",
    "sg:address":"51-55 Gresham St",
    "sg:city":"Moorgate",
    "sg:classifiers":[
        {
            "category":"Professional",
            "subcategory":"Computer Services",
            "type":"Services"
        }
    ],
    "sg:phone":"+44 20 7325 6565",
    "sg:postcode":"EC2V 7EH",
    "sg:province":"Greater London",
    "sg:tags":[
        "system",
        "software"
    ],
    "wof:name":"Market Vision",
    "wof:placetype":"venue"
},
  "geometry": {"coordinates":[-0.094619,51.515709],"type":"Point"}
}