{
  "type": "Feature",
  "properties": {
    "addr:full":"19 Elmwood Close Retford Nottinghamshire DN22 6SL",
    "addr:housenumber":"19",
    "addr:postcode":"dn22 6sl",
    "addr:street":"Elmwood Close",
    "iso:country":"GB",
    "sg:address":"19 Elmwood Close",
    "sg:city":"Retford",
    "sg:classifiers":[
        {
            "category":"Professional",
            "subcategory":"Engineering",
            "type":"Services"
        }
    ],
    "sg:phone":"+44 1777 703784",
    "sg:postcode":"DN22 6SL",
    "sg:province":"Nottinghamshire",
    "sg:tags":[
        "civil",
        "engineer"
    ],
    "wof:name":"Listers Geotechnical Consultants",
    "wof:placetype":"venue"
},
  "geometry": {"coordinates":[-0.9347,53.330074],"type":"Point"}
}