{
  "type": "Feature",
  "properties": {
    "addr:full":"1 Leeholme Rd Billingham Durham TS23 3TA",
    "addr:housenumber":"1",
    "addr:postcode":"ts23 3ta",
    "addr:street":"Leeholme Rd",
    "iso:country":"GB",
    "sg:address":"1 Leeholme Rd",
    "sg:city":"Billingham",
    "sg:classifiers":[
        {
            "category":"Autos & Motor Vehicles",
            "subcategory":"Automobile Sales",
            "type":"Retail Goods"
        }
    ],
    "sg:phone":"+44 1642 650066",
    "sg:postcode":"TS23 3TA",
    "sg:province":"Durham",
    "sg:tags":[
        "car"
    ],
    "wof:name":"Stephen Moran",
    "wof:placetype":"venue"
},
  "geometry": {"coordinates":[-1.2805589437,54.6064910889],"type":"Point"}
}