{
  "type": "Feature",
  "properties": {
    "addr:full":"Springfield, Hardington Yeovil Dorset BA22 9NP",
    "addr:postcode":"ba22 9np",
    "addr:street":"Dorset",
    "iso:country":"GB",
    "sg:address":"Springfield, Hardington",
    "sg:city":"Yeovil",
    "sg:classifiers":[
        {
            "category":"Shopping",
            "subcategory":"Department Store",
            "type":"Retail Goods"
        }
    ],
    "sg:postcode":"BA22 9NP",
    "sg:province":"Dorset",
    "wof:name":"Hardington Moore Post Office",
    "wof:placetype":"venue"
},
  "geometry": {"coordinates":[-2.721443,50.917786],"type":"Point"}
}