{
  "type": "Feature",
  "properties": {
    "addr:full":"113 South Lambeth Road London Greater London SW8 1UZ",
    "addr:housenumber":"113",
    "addr:postcode":"sw8 1uz",
    "addr:street":"South Lambeth Road",
    "iso:country":"GB",
    "sg:address":"113 South Lambeth Road",
    "sg:city":"London",
    "sg:classifiers":[
        {
            "category":"Restaurant",
            "type":"Food & Drink"
        }
    ],
    "sg:phone":"+44 20 7793 1051",
    "sg:postcode":"SW8 1UZ",
    "sg:province":"Greater London",
    "wof:name":"Estrela Bar",
    "wof:placetype":"venue"
},
  "geometry": {"coordinates":[-0.123432003,51.4792404175],"type":"Point"}
}