{
  "type": "Feature",
  "properties": {
    "iso:country":"GB",
    "sg:address":"194-196 High Street",
    "sg:city":"Slough",
    "sg:classifiers":[
        {
            "category":"Health Services",
            "subcategory":"Optometrist",
            "type":"Services"
        }
    ],
    "sg:phone":"+44 1753 502700",
    "sg:postcode":"SL1 1JS",
    "sg:province":"Berkshire",
    "sg:tags":[
        "optician"
    ],
    "wof:name":"Specsavers",
    "wof:placetype":"venue"
},
  "geometry": {"coordinates":[-0.588939,51.507778],"type":"Point"}
}