{
  "type": "Feature",
  "properties": {
    "addr:full":"1 Merton High Street London Greater London SW19 1DD",
    "addr:housenumber":"1",
    "addr:postcode":"sw19 1dd",
    "addr:street":"Merton High Street",
    "iso:country":"GB",
    "sg:address":"1 Merton High Street",
    "sg:city":"London",
    "sg:classifiers":[
        {
            "category":"Professional",
            "subcategory":"Printing & Photocopies",
            "type":"Services"
        }
    ],
    "sg:phone":"+44 20 8543 2622",
    "sg:postcode":"SW19 1DD",
    "sg:province":"Greater London",
    "sg:tags":[
        "engraving"
    ],
    "wof:name":"Scribe Engravers",
    "wof:placetype":"venue"
},
  "geometry": {"coordinates":[-0.186269,51.415981],"type":"Point"}
}