{
  "type": "Feature",
  "properties": {
    "iso:country":"GB",
    "sg:address":"Ferndown Middle School",
    "sg:city":"Ferndown",
    "sg:classifiers":[
        {
            "category":"Education",
            "subcategory":"School",
            "type":"Public Place"
        }
    ],
    "sg:postcode":"BH22 9ET",
    "sg:province":"Dorset",
    "sg:tags":[
        "catering"
    ],
    "wof:name":"Pace Services for Dorset Schools",
    "wof:placetype":"venue"
},
  "geometry": {"coordinates":[-1.889389,50.80183],"type":"Point"}
}