{
  "type": "Feature",
  "properties": {
    "addr:full":"Railway Arch 91 London Greater London SE16 3RA",
    "addr:housenumber":"91",
    "addr:postcode":"se16 3ra",
    "addr:street":"Railway Arch",
    "iso:country":"GB",
    "sg:address":"Railway Arch 91",
    "sg:city":"London",
    "sg:classifiers":[
        {
            "category":"Building & Trades",
            "subcategory":"Cleaning & Sanitation",
            "type":"Services"
        }
    ],
    "sg:phone":"+44 20 7064 1515",
    "sg:postcode":"SE16 3RA",
    "sg:province":"Greater London",
    "sg:tags":[
        "commercial"
    ],
    "wof:name":"The Cleaning Co-Operative",
    "wof:placetype":"venue"
},
  "geometry": {"coordinates":[-0.0634199977,51.4951095581],"type":"Point"}
}