{
  "type": "Feature",
  "properties": {
    "iso:country":"GB",
    "sg:address":"The Poplars",
    "sg:city":"Nottingham",
    "sg:classifiers":[
        {
            "category":"Home & Garden",
            "subcategory":"Furniture",
            "type":"Retail Goods"
        }
    ],
    "sg:phone":"+44 115 943 0378",
    "sg:postcode":"NG9 2PD",
    "sg:province":"Nottinghamshire",
    "wof:name":"Beeston Suite Co Ltd",
    "wof:placetype":"venue"
},
  "geometry": {"coordinates":[-1.218009,52.92942],"type":"Point"}
}