{
  "type": "Feature",
  "properties": {
    "addr:full":"75 Morris Road Southampton Hampshire SO15 2BQ",
    "addr:housenumber":"75",
    "addr:postcode":"so15 2bq",
    "addr:street":"Morris Road",
    "iso:country":"GB",
    "sg:address":"75 Morris Road",
    "sg:city":"Southampton",
    "sg:classifiers":[
        {
            "category":"Travel",
            "subcategory":"Hotels & Motels",
            "type":"Entertainment"
        }
    ],
    "sg:postcode":"SO15 2BQ",
    "sg:province":"Hampshire",
    "sg:tags":[
        "house",
        "guest"
    ],
    "wof:name":"Acorn Lodge",
    "wof:placetype":"venue"
},
  "geometry": {"coordinates":[-1.4118540287,50.9101257324],"type":"Point"}
}