{
  "type": "Feature",
  "properties": {
    "addr:full":"115 Station Rd Stockport Cheshire SK6 6PA",
    "addr:housenumber":"115",
    "addr:postcode":"sk6 6pa",
    "addr:street":"Station Rd",
    "iso:country":"GB",
    "sg:address":"115 Station Rd",
    "sg:city":"Stockport",
    "sg:classifiers":[
        {
            "category":"Travel",
            "subcategory":"Hotels & Motels",
            "type":"Entertainment"
        }
    ],
    "sg:phone":"+44 161 427 7751",
    "sg:postcode":"SK6 6PA",
    "sg:province":"Cheshire",
    "sg:tags":[
        "house",
        "guest"
    ],
    "wof:name":"Park View Guest House",
    "wof:placetype":"venue"
},
  "geometry": {"coordinates":[-2.060005,53.398304],"type":"Point"}
}