{
  "type": "Feature",
  "properties": {
    "iso:country":"GB",
    "sg:address":"Melton Road",
    "sg:city":"Doncaster",
    "sg:classifiers":[
        {
            "category":"Home & Garden",
            "subcategory":"Garden Supply",
            "type":"Retail Goods"
        }
    ],
    "sg:postcode":"DN5 7TQ",
    "sg:province":"South Yorkshire",
    "sg:tags":[
        "nursery",
        "centre"
    ],
    "wof:name":"Rouletta Nurseries",
    "wof:placetype":"venue"
},
  "geometry": {"coordinates":[-1.167818,53.519596],"type":"Point"}
}