{
  "type": "Feature",
  "properties": {
    "iso:country":"GB",
    "sg:address":"Ross Mills Est, Rodley La",
    "sg:city":"Leeds",
    "sg:classifiers":[
        {
            "category":"Utilities",
            "subcategory":"Refuse",
            "type":"Services"
        }
    ],
    "sg:phone":"+44 113 236 0372",
    "sg:postcode":"LS13 1BJ",
    "sg:province":"West Yorkshire",
    "sg:tags":[
        "skip",
        "hire"
    ],
    "wof:name":"Quick Skips",
    "wof:placetype":"venue"
},
  "geometry": {"coordinates":[-1.661319,53.823101],"type":"Point"}
}