{
  "type": "Feature",
  "properties": {
    "addr:full":"West View, Holcombe Lane, Ottery St Mary Exeter Devon EX1 1PH",
    "addr:postcode":"ex1 1ph",
    "addr:street":"Holcombe Lane;St",
    "iso:country":"GB",
    "sg:address":"West View, Holcombe Lane, Ottery St Mary",
    "sg:city":"Exeter",
    "sg:classifiers":[
        {
            "category":"Farming",
            "subcategory":"Livestock Farm",
            "type":"Manufacturing & Wholesale Goods"
        }
    ],
    "sg:phone":"+44 1404 812525",
    "sg:postcode":"EX1 1PH",
    "sg:province":"Devon",
    "sg:tags":[
        "others"
    ],
    "wof:name":"C E Lawrence",
    "wof:placetype":"venue"
},
  "geometry": {"coordinates":[-3.5316441059,50.7199058533],"type":"Point"}
}