{
  "type": "Feature",
  "properties": {
    "addr:full":"68 Waverley Gardens Barking Essex IG11 0BH",
    "addr:housenumber":"68",
    "addr:postcode":"ig11 0bh",
    "addr:street":"Waverley Gardens",
    "iso:country":"GB",
    "sg:address":"68 Waverley Gardens",
    "sg:city":"Barking",
    "sg:classifiers":[
        {
            "category":"Building & Trades",
            "subcategory":"Construction",
            "type":"Services"
        }
    ],
    "sg:phone":"+44 20 8591 4165",
    "sg:postcode":"IG11 0BH",
    "sg:province":"Essex",
    "sg:tags":[
        "glazier"
    ],
    "wof:name":"Amazing Glazing",
    "wof:placetype":"venue"
},
  "geometry": {"coordinates":[0.089946,51.528416],"type":"Point"}
}