{
  "type": "Feature",
  "properties": {
    "addr:full":"13 Old Brompton Road London Greater London SW7 3HZ",
    "addr:housenumber":"13",
    "addr:postcode":"sw7 3hz",
    "addr:street":"Old Brompton Road",
    "iso:country":"GB",
    "sg:address":"13 Old Brompton Road",
    "sg:city":"London",
    "sg:classifiers":[
        {
            "category":"Professional",
            "type":"Services"
        }
    ],
    "sg:postcode":"SW7 3HZ",
    "sg:province":"Greater London",
    "sg:tags":[
        "interior",
        "furnishers",
        "designer"
    ],
    "wof:name":"B13 Design",
    "wof:placetype":"venue"
},
  "geometry": {"coordinates":[-0.175181,51.493435],"type":"Point"}
}