{
  "type": "Feature",
  "properties": {
    "iso:country":"GB",
    "sg:address":"Blaenffynonau, Llangynin, St Clears",
    "sg:city":"Carmarthen",
    "sg:classifiers":[
        {
            "category":"Farming",
            "subcategory":"Dairy Farm",
            "type":"Manufacturing & Wholesale Goods"
        }
    ],
    "sg:postcode":"SA33 4JY",
    "sg:province":"Carmarthenshire",
    "wof:name":"J M & L Morris",
    "wof:placetype":"venue"
},
  "geometry": {"coordinates":[-4.53863,51.845402],"type":"Point"}
}