{
  "type": "Feature",
  "properties": {
    "addr:full":"World Trade Centre, Europe Ho, East Smithfield London Greater London E1 9AA",
    "addr:postcode":"e1 9aa",
    "addr:street":"East",
    "iso:country":"GB",
    "sg:address":"World Trade Centre, Europe Ho, East Smithfield",
    "sg:city":"London",
    "sg:classifiers":[
        {
            "category":"Professional",
            "subcategory":"Business Services",
            "type":"Services"
        }
    ],
    "sg:phone":"+44 20 7488 3232",
    "sg:postcode":"E1 9AA",
    "sg:province":"Greater London",
    "sg:tags":[
        "holding"
    ],
    "wof:name":"Refco U K Holdings Ltd",
    "wof:placetype":"venue"
},
  "geometry": {"coordinates":[-0.05736,51.517979],"type":"Point"}
}