{
  "type": "Feature",
  "properties": {
    "iso:country":"GB",
    "sg:address":"23 Ferndale Ave",
    "sg:city":"Chertsey",
    "sg:classifiers":[
        {
            "category":"Professional",
            "subcategory":"Computer Services",
            "type":"Services"
        }
    ],
    "sg:postcode":"KT16 9RB",
    "sg:province":"Surrey",
    "sg:tags":[
        "system",
        "software"
    ],
    "wof:name":"Pafec Ltd",
    "wof:placetype":"venue"
},
  "geometry": {"coordinates":[-0.518614,51.376667],"type":"Point"}
}