{
  "type": "Feature",
  "properties": {
    "addr:full":"St Marys Works, St Marys Plain Norwich Norfolk NR3 3AF",
    "addr:postcode":"nr3 3af",
    "addr:street":"St Marys Plain Norwich Norfolk",
    "iso:country":"GB",
    "sg:address":"St Marys Works, St Marys Plain",
    "sg:city":"Norwich",
    "sg:classifiers":[
        {
            "category":"Personal",
            "subcategory":"Beauty Salon",
            "type":"Services"
        }
    ],
    "sg:phone":"+44 1603 664050",
    "sg:postcode":"NR3 3AF",
    "sg:province":"Norfolk",
    "sg:tags":[
        "unisex",
        "hairdresser"
    ],
    "wof:name":"Snips Hair Studio",
    "wof:placetype":"venue"
},
  "geometry": {"coordinates":[1.290784,52.63401],"type":"Point"}
}