{
  "type": "Feature",
  "properties": {
    "iso:country":"GB",
    "sg:address":"8 Riley Rd, Off Henson Way, Telford Way Indstl Est",
    "sg:city":"Kettering",
    "sg:classifiers":[
        {
            "category":"Autos & Motor Vehicles",
            "subcategory":"Auto Supplies",
            "type":"Retail Goods"
        }
    ],
    "sg:phone":"+44 1536 85584",
    "sg:postcode":"NN16 8NN",
    "sg:province":"Northamptonshire",
    "sg:tags":[
        "component"
    ],
    "wof:name":"Fastline Factors Ltd",
    "wof:placetype":"venue"
},
  "geometry": {"coordinates":[-0.744986,52.410164],"type":"Point"}
}