{
  "type": "Feature",
  "properties": {
    "addr:full":"St Josephs Old School, Bolton Road, Anderton Chorley Lancashire PR6 9LX",
    "addr:postcode":"pr6 9lx",
    "addr:street":"Old;Bolton Road",
    "iso:country":"GB",
    "sg:address":"St Josephs Old School, Bolton Road, Anderton",
    "sg:city":"Chorley",
    "sg:classifiers":[
        {
            "category":"Farming",
            "subcategory":"Nursery",
            "type":"Manufacturing & Wholesale Goods"
        }
    ],
    "sg:phone":"+44 1257 474211",
    "sg:postcode":"PR6 9LX",
    "sg:province":"Lancashire",
    "sg:tags":[
        "creche"
    ],
    "wof:name":"Anderton Day Nursery",
    "wof:placetype":"venue"
},
  "geometry": {"coordinates":[-2.592979,53.614574],"type":"Point"}
}