{
  "type": "Feature",
  "properties": {
    "addr:full":"Kent Street Southampton Hampshire SO14 5SP",
    "addr:postcode":"so14 5sp",
    "addr:street":"Kent Street",
    "iso:country":"GB",
    "sg:address":"Kent Street",
    "sg:city":"Southampton",
    "sg:classifiers":[
        {
            "category":"Organizations",
            "subcategory":"Non-profit Organization",
            "type":"Services"
        }
    ],
    "sg:phone":"+44 23 8022 0923",
    "sg:postcode":"SO14 5SP",
    "sg:province":"Hampshire",
    "sg:tags":[
        "charitable",
        "organisation",
        "voluntary",
        "charity"
    ],
    "wof:name":"Cabins Playbus",
    "wof:placetype":"venue"
},
  "geometry": {"coordinates":[-1.387485981,50.910610199],"type":"Point"}
}