{
  "type": "Feature",
  "properties": {
    "addr:full":"438 Watnall Road, Hucknall Nottingham Nottinghamshire NG15 6FQ",
    "addr:housenumber":"438",
    "addr:postcode":"ng15 6fq",
    "addr:street":"Watnall Road",
    "iso:country":"GB",
    "sg:address":"438 Watnall Road, Hucknall",
    "sg:city":"Nottingham",
    "sg:classifiers":[
        {
            "category":"Bars & Pubs",
            "type":"Food & Drink"
        }
    ],
    "sg:postcode":"NG15 6FQ",
    "sg:province":"Nottinghamshire",
    "sg:tags":[
        "pubs",
        "inn"
    ],
    "wof:name":"Will Scarlet Inn",
    "wof:placetype":"venue"
},
  "geometry": {"coordinates":[-1.2248270512,53.0212745667],"type":"Point"}
}