{
  "type": "Feature",
  "properties": {
    "addr:full":"28 Upper High Street Thame Buckinghamshire OX9 3EX",
    "addr:housenumber":"28",
    "addr:postcode":"ox9 3ex",
    "addr:street":"Upper High Street",
    "iso:country":"GB",
    "sg:address":"28 Upper High Street",
    "sg:city":"Thame",
    "sg:classifiers":[
        {
            "category":"Food & Beverages",
            "subcategory":"Bakery",
            "type":"Retail Goods"
        }
    ],
    "sg:postcode":"OX9 3EX",
    "sg:province":"Buckinghamshire",
    "sg:tags":[
        "baker"
    ],
    "wof:name":"The Cottage Bakery",
    "wof:placetype":"venue"
},
  "geometry": {"coordinates":[-0.97524,51.745979],"type":"Point"}
}