{
  "type": "Feature",
  "properties": {
    "iso:country":"GB",
    "sg:address":"Galtres House, 3 Lysander Close, Clifton Moorgate",
    "sg:city":"York",
    "sg:classifiers":[
        {
            "category":"Health Services",
            "subcategory":"Health Practitioner",
            "type":"Services"
        }
    ],
    "sg:phone":"+44 1904 693197",
    "sg:postcode":"YO30 4GE",
    "sg:province":"North Yorkshire",
    "sg:tags":[
        "osteopath"
    ],
    "wof:name":"Peter J Morton",
    "wof:placetype":"venue"
},
  "geometry": {"coordinates":[-1.0953830481,53.9875946045],"type":"Point"}
}