{
  "type": "Feature",
  "properties": {
    "addr:full":"283 Fullwell Avenue, Barkingside Ilford Essex IG5 0RG",
    "addr:housenumber":"283",
    "addr:postcode":"ig5 0rg",
    "addr:street":"Fullwell Avenue",
    "iso:country":"GB",
    "sg:address":"283 Fullwell Avenue, Barkingside",
    "sg:city":"Ilford",
    "sg:classifiers":[
        {
            "category":"Retail",
            "subcategory":"Repair Shop",
            "type":"Services"
        }
    ],
    "sg:phone":"+44 20 8551 8926",
    "sg:postcode":"IG5 0RG",
    "sg:province":"Essex",
    "sg:tags":[
        "radio",
        "television",
        "video"
    ],
    "wof:name":"Colin's Tv's",
    "wof:placetype":"venue"
},
  "geometry": {"coordinates":[0.066813,51.597134],"type":"Point"}
}