{
  "type": "Feature",
  "properties": {
    "addr:full":"Abbeydore Hereford Herefordshire HR2 0AA",
    "addr:postcode":"hr2 0aa",
    "addr:street":"Abbeydore",
    "iso:country":"GB",
    "sg:address":"Abbeydore",
    "sg:city":"Hereford",
    "sg:classifiers":[
        {
            "category":"Retail",
            "subcategory":"Repair Shop",
            "type":"Services"
        }
    ],
    "sg:phone":"+44 1981 240311",
    "sg:postcode":"HR2 0AA",
    "sg:province":"Herefordshire",
    "sg:tags":[
        "furniture"
    ],
    "wof:name":"Ernest H Howes",
    "wof:placetype":"venue"
},
  "geometry": {"coordinates":[-2.89538,51.969719],"type":"Point"}
}