{
  "type": "Feature",
  "properties": {
    "addr:full":"37 Lombard Street Newark Nottinghamshire NG24 1XG",
    "addr:housenumber":"37",
    "addr:postcode":"ng24 1xg",
    "addr:street":"Lombard Street",
    "iso:country":"GB",
    "sg:address":"37 Lombard Street",
    "sg:city":"Newark",
    "sg:classifiers":[
        {
            "category":"Retail",
            "subcategory":"Auto Rental",
            "type":"Services"
        }
    ],
    "sg:phone":"+44 1636 610090",
    "sg:postcode":"NG24 1XG",
    "sg:province":"Nottinghamshire",
    "sg:tags":[
        "car"
    ],
    "wof:name":"Eurodrive Car Rental Ltd.",
    "wof:placetype":"venue"
},
  "geometry": {"coordinates":[-0.8131269813,53.0753288269],"type":"Point"}
}