{
  "type": "Feature",
  "properties": {
    "iso:country":"GB",
    "sg:address":"16 Westbay",
    "sg:city":"Bridport",
    "sg:classifiers":[
        {
            "category":"Recreation",
            "subcategory":"Water Park",
            "type":"Entertainment"
        }
    ],
    "sg:postcode":"DT6 4EU",
    "sg:province":"Dorset",
    "sg:tags":[
        "theme"
    ],
    "wof:name":"Harbou Amusments",
    "wof:placetype":"venue"
},
  "geometry": {"coordinates":[-2.757159,50.722988],"type":"Point"}
}