{
  "type": "Feature",
  "properties": {
    "addr:full":"75 High Street Bristol City of Bristol BS16 5HE",
    "addr:housenumber":"75",
    "addr:postcode":"bs16 5he",
    "addr:street":"High Street",
    "iso:country":"GB",
    "sg:address":"75 High Street",
    "sg:city":"Bristol",
    "sg:classifiers":[
        {
            "category":"Fast Food",
            "type":"Food & Drink"
        }
    ],
    "sg:phone":"+44 117 956 8771",
    "sg:postcode":"BS16 5HE",
    "sg:province":"City of Bristol",
    "sg:tags":[
        "away",
        "take"
    ],
    "wof:name":"Staple Hill Fishbar",
    "wof:placetype":"venue"
},
  "geometry": {"coordinates":[-2.510157,51.481392],"type":"Point"}
}