{
  "type": "Feature",
  "properties": {
    "iso:country":"GB",
    "sg:address":"Ratcliffe On Soar Power Station",
    "sg:city":"Nottingham",
    "sg:classifiers":[
        {
            "category":"Utilities",
            "subcategory":"Electric",
            "type":"Services"
        }
    ],
    "sg:phone":"+44 115 936 5000",
    "sg:postcode":"NG11 0EE",
    "sg:province":"Nottinghamshire",
    "sg:tags":[
        "electricity"
    ],
    "wof:name":"Powergen PLC",
    "wof:placetype":"venue"
},
  "geometry": {"coordinates":[-1.264027,52.855232],"type":"Point"}
}