{
  "type": "Feature",
  "properties": {
    "iso:country":"GB",
    "sg:address":"14 Western Road, Plaistow",
    "sg:city":"London",
    "sg:classifiers":[
        {
            "category":"Building & Trades",
            "subcategory":"Construction",
            "type":"Services"
        }
    ],
    "sg:phone":"+44 20 8514 0545",
    "sg:postcode":"E13 9JF",
    "sg:province":"Greater London",
    "sg:tags":[
        "bricklaying",
        "contractor"
    ],
    "wof:name":"Triamond Brickworks Ltd.",
    "wof:placetype":"venue"
},
  "geometry": {"coordinates":[0.031304,51.533051],"type":"Point"}
}