{
  "type": "Feature",
  "properties": {
    "addr:full":"10a Fernhurst Road, Fulham London Greater London SW6 7JW",
    "addr:housenumber":"10a",
    "addr:postcode":"sw6 7jw",
    "addr:street":"Fernhurst Road",
    "iso:country":"GB",
    "sg:address":"10a Fernhurst Road, Fulham",
    "sg:city":"London",
    "sg:classifiers":[
        {
            "category":"Professional",
            "subcategory":"Management & Consulting",
            "type":"Services"
        }
    ],
    "sg:postcode":"SW6 7JW",
    "sg:province":"Greater London",
    "sg:tags":[
        "consultant",
        "business"
    ],
    "wof:name":"Camps Bay Consulting Ltd",
    "wof:placetype":"venue"
},
  "geometry": {"coordinates":[-0.2087330073,51.4783744812],"type":"Point"}
}