{
  "type": "Feature",
  "properties": {
    "addr:full":"118 Mill Lane, Chadwell Heath Romford Essex RM6 6RS",
    "addr:housenumber":"118",
    "addr:postcode":"rm6 6rs",
    "addr:street":"Mill Lane",
    "iso:country":"GB",
    "sg:address":"118 Mill Lane, Chadwell Heath",
    "sg:city":"Romford",
    "sg:classifiers":[
        {
            "category":"Food & Beverages",
            "subcategory":"Liquor & Beverages",
            "type":"Retail Goods"
        }
    ],
    "sg:phone":"+44 20 8590 2696",
    "sg:postcode":"RM6 6RS",
    "sg:province":"Essex",
    "sg:tags":[
        "beer",
        "spirit",
        "wines"
    ],
    "wof:name":"Mill Stores",
    "wof:placetype":"venue"
},
  "geometry": {"coordinates":[0.1398340017,51.5752868652],"type":"Point"}
}