{
  "type": "Feature",
  "properties": {
    "iso:country":"GB",
    "sg:address":"P O Box 12815, Northway House, 1379 High Road",
    "sg:city":"London",
    "sg:classifiers":[
        {
            "category":"Professional",
            "subcategory":"Accounting & Tax Preparation",
            "type":"Services"
        }
    ],
    "sg:phone":"+44 7899 848791",
    "sg:postcode":"N20 9WB",
    "sg:province":"Greater London",
    "sg:tags":[
        "accountant"
    ],
    "wof:name":"Accounting Services Bureau Ltd.",
    "wof:placetype":"venue"
},
  "geometry": {"coordinates":[-0.176119,51.633675],"type":"Point"}
}