{
  "type": "Feature",
  "properties": {
    "iso:country":"GB",
    "sg:address":"39 Winchester Street",
    "sg:city":"Salisbury",
    "sg:classifiers":[
        {
            "category":"Professional",
            "type":"Services"
        }
    ],
    "sg:postcode":"SP1 1HG",
    "sg:province":"Wiltshire",
    "sg:tags":[
        "caterer"
    ],
    "wof:name":"Angie Cooper",
    "wof:placetype":"venue"
},
  "geometry": {"coordinates":[-1.792336,51.069729],"type":"Point"}
}