{
  "type": "Feature",
  "properties": {
    "iso:country":"GB",
    "sg:address":"27a Morgan Arcade, St Marys Street",
    "sg:city":"Cardiff",
    "sg:classifiers":[
        {
            "category":"Home & Garden",
            "subcategory":"Furniture",
            "type":"Retail Goods"
        }
    ],
    "sg:postcode":"CF1 4LD",
    "sg:province":"Cardiff",
    "wof:name":"Johnathon David",
    "wof:placetype":"venue"
},
  "geometry": {"coordinates":[-3.18067,51.481258],"type":"Point"}
}