{
  "type": "Feature",
  "properties": {
    "addr:full":"372 Attercliffe Common Sheffield South Yorkshire S9 2BT",
    "addr:housenumber":"372",
    "addr:postcode":"s9 2bt",
    "addr:street":"Attercliffe Common",
    "iso:country":"GB",
    "sg:address":"372 Attercliffe Common",
    "sg:city":"Sheffield",
    "sg:classifiers":[
        {
            "category":"Retail",
            "subcategory":"Auto Repair",
            "type":"Services"
        }
    ],
    "sg:phone":"+44 114 244 1446",
    "sg:postcode":"S9 2BT",
    "sg:province":"South Yorkshire",
    "sg:tags":[
        "modification",
        "garage"
    ],
    "wof:name":"Acliffe Garage",
    "wof:placetype":"venue"
},
  "geometry": {"coordinates":[-1.4201740026,53.4025726318],"type":"Point"}
}