{
  "type": "Feature",
  "properties": {
    "addr:full":"Castle Park Indstl Est Flint Flintshire CH6 5XA",
    "addr:postcode":"ch6 5xa",
    "addr:street":"Castle Park Indstl Est",
    "iso:country":"GB",
    "sg:address":"Castle Park Indstl Est",
    "sg:city":"Flint",
    "sg:classifiers":[
        {
            "category":"Manufacturing",
            "subcategory":"Petroleum Products",
            "type":"Manufacturing & Wholesale Goods"
        }
    ],
    "sg:postcode":"CH6 5XA",
    "sg:province":"Flintshire",
    "sg:tags":[
        "double",
        "glazing"
    ],
    "wof:name":"Allerton Glass",
    "wof:placetype":"venue"
},
  "geometry": {"coordinates":[-3.1318690777,53.251411438],"type":"Point"}
}