{
  "type": "Feature",
  "properties": {
    "addr:full":"29 Wellington Street Leeds West Yorkshire LS1 1QQ",
    "addr:housenumber":"29",
    "addr:postcode":"ls1 1qq",
    "addr:street":"Wellington Street",
    "iso:country":"GB",
    "sg:address":"29 Wellington Street",
    "sg:city":"Leeds",
    "sg:classifiers":[
        {
            "category":"Professional",
            "subcategory":"Business Services",
            "type":"Services"
        }
    ],
    "sg:phone":"+44 113 244 7103",
    "sg:postcode":"LS1 1QQ",
    "sg:province":"West Yorkshire",
    "sg:tags":[
        "trade"
    ],
    "wof:name":"Direct Marketing Association (U K) Ltd. (",
    "wof:placetype":"venue"
},
  "geometry": {"coordinates":[-1.5480639935,53.7961502075],"type":"Point"}
}