{
  "type": "Feature",
  "properties": {
    "iso:country":"GB",
    "sg:address":"20 Cairnie Street",
    "sg:city":"Arbroath",
    "sg:classifiers":[
        {
            "category":"Fast Food",
            "type":"Food & Drink"
        },
        {
            "category":"Food & Beverages",
            "subcategory":"Groceries & Convenience Stores",
            "type":"Retail Goods"
        }
    ],
    "sg:phone":"+44 1241 873203",
    "sg:postcode":"DD11 3BJ",
    "sg:province":"Angus",
    "sg:tags":[
        "shop",
        "fish",
        "take",
        "chip",
        "away"
    ],
    "wof:name":"CARINIE CHIP SHOP",
    "wof:placetype":"venue"
},
  "geometry": {"coordinates":[-2.593274,56.563328],"type":"Point"}
}