{
  "type": "Feature",
  "properties": {
    "addr:full":"Gainsbourough House Sawbridgeworth Essex CM21 9EG",
    "addr:postcode":"cm21 9eg",
    "iso:country":"GB",
    "sg:address":"Gainsbourough House",
    "sg:city":"Sawbridgeworth",
    "sg:classifiers":[
        {
            "category":"Professional",
            "subcategory":"Accounting & Tax Preparation",
            "type":"Services"
        }
    ],
    "sg:phone":"+44 1279 725050",
    "sg:postcode":"CM21 9EG",
    "sg:province":"Essex",
    "sg:tags":[
        "accountant"
    ],
    "wof:name":"A L Shelley",
    "wof:placetype":"venue"
},
  "geometry": {"coordinates":[0.147223,51.812527],"type":"Point"}
}