{
  "type": "Feature",
  "properties": {
    "addr:full":"Bear Passage, High Street Welshpool Shropshire SY21 7JP",
    "addr:postcode":"sy21 7jp",
    "addr:street":"Bear Passage High Street",
    "iso:country":"GB",
    "sg:address":"Bear Passage, High Street",
    "sg:city":"Welshpool",
    "sg:classifiers":[
        {
            "category":"Personal",
            "type":"Services"
        }
    ],
    "sg:phone":"+44 1938 556185",
    "sg:postcode":"SY21 7JP",
    "sg:province":"Shropshire",
    "sg:tags":[
        "wedding"
    ],
    "wof:name":"B Mills",
    "wof:placetype":"venue"
},
  "geometry": {"coordinates":[-3.145203,52.66119],"type":"Point"}
}