{
  "type": "Feature",
  "properties": {
    "addr:full":"144 King St Plymouth Devon PL1 5JE",
    "addr:housenumber":"144",
    "addr:postcode":"pl1 5je",
    "addr:street":"King St",
    "iso:country":"GB",
    "sg:address":"144 King St",
    "sg:city":"Plymouth",
    "sg:classifiers":[
        {
            "category":"Professional",
            "subcategory":"Art Services",
            "type":"Services"
        }
    ],
    "sg:phone":"+44 1752 301914",
    "sg:postcode":"PL1 5JE",
    "sg:province":"Devon",
    "sg:tags":[
        "photographer"
    ],
    "wof:name":"Piper Photography",
    "wof:placetype":"venue"
},
  "geometry": {"coordinates":[-4.148991,50.371834],"type":"Point"}
}