{
  "type": "Feature",
  "properties": {
    "addr:full":"49 High Street New Malden Surrey KT3 4BY",
    "addr:housenumber":"49",
    "addr:postcode":"kt3 4by",
    "addr:street":"High Street",
    "iso:country":"GB",
    "sg:address":"49 High Street",
    "sg:city":"New Malden",
    "sg:classifiers":[
        {
            "category":"Place Of Worship",
            "type":"Public Place"
        }
    ],
    "sg:phone":"+44 20 8942 1288",
    "sg:postcode":"KT3 4BY",
    "sg:province":"Surrey",
    "wof:name":"New Malden Methodist Church",
    "wof:placetype":"venue"
},
  "geometry": {"coordinates":[-0.2695870101,51.4103660583],"type":"Point"}
}