{
  "type": "Feature",
  "properties": {
    "addr:full":"Saltburn Bank Saltburn-by-the-sea North Yorkshire TS12 1HH",
    "addr:postcode":"ts12 1hh",
    "iso:country":"GB",
    "sg:address":"Saltburn Bank",
    "sg:city":"Saltburn-by-the-sea",
    "sg:classifiers":[
        {
            "category":"Travel",
            "subcategory":"Hotels & Motels",
            "type":"Entertainment"
        }
    ],
    "sg:phone":"+44 1287 622544",
    "sg:postcode":"TS12 1HH",
    "sg:province":"North Yorkshire",
    "wof:name":"The Spa Hotel",
    "wof:placetype":"venue"
},
  "geometry": {"coordinates":[-0.9677600265,54.5833206177],"type":"Point"}
}