{
  "type": "Feature",
  "properties": {
    "addr:full":"The Old Boatyard Stalybridge Greater Manchester SK15 1LT",
    "addr:postcode":"sk15 1lt",
    "iso:country":"GB",
    "sg:address":"The Old Boatyard",
    "sg:city":"Stalybridge",
    "sg:classifiers":[
        {
            "category":"Building & Trades",
            "subcategory":"Construction",
            "type":"Services"
        }
    ],
    "sg:postcode":"SK15 1LT",
    "sg:province":"Greater Manchester",
    "sg:tags":[
        "builder"
    ],
    "wof:name":"Springwell Building & Roofing Contractor",
    "wof:placetype":"venue"
},
  "geometry": {"coordinates":[-2.0575690269,53.483543396],"type":"Point"}
}