{
  "type": "Feature",
  "properties": {
    "addr:full":"1 Portnall Road London Greater London W9 3BA",
    "addr:housenumber":"1",
    "addr:postcode":"w9 3ba",
    "addr:street":"Portnall Road",
    "iso:country":"GB",
    "sg:address":"1 Portnall Road",
    "sg:city":"London",
    "sg:classifiers":[
        {
            "category":"Food & Beverages",
            "subcategory":"Supermarket",
            "type":"Retail Goods"
        }
    ],
    "sg:phone":"+44 20 8969 9123",
    "sg:postcode":"W9 3BA",
    "sg:province":"Greater London",
    "wof:name":"All Nation Tropcal",
    "wof:placetype":"venue"
},
  "geometry": {"coordinates":[-0.203768,51.525642395],"type":"Point"}
}