{
  "type": "Feature",
  "properties": {
    "iso:country":"GB",
    "sg:address":"77 Elsmere Road, Benwell",
    "sg:city":"Newcastle-upon-tyne",
    "sg:classifiers":[
        {
            "category":"Professional",
            "subcategory":"Computer Services",
            "type":"Services"
        }
    ],
    "sg:phone":"+44 191 273 1838",
    "sg:postcode":"NE4 8BE",
    "sg:province":"Tyne and Wear",
    "sg:tags":[
        "information"
    ],
    "wof:name":"The Rights Project",
    "wof:placetype":"venue"
},
  "geometry": {"coordinates":[-1.65574,54.970268],"type":"Point"}
}