{
  "type": "Feature",
  "properties": {
    "iso:country":"GB",
    "sg:address":"74 Oakdale Road",
    "sg:city":"Poole",
    "sg:classifiers":[
        {
            "category":"Food & Beverages",
            "subcategory":"Groceries & Convenience Stores",
            "type":"Retail Goods"
        }
    ],
    "sg:phone":"+44 1202 675429",
    "sg:postcode":"BH15 3LG",
    "sg:province":"Dorset",
    "wof:name":"Alldays",
    "wof:placetype":"venue"
},
  "geometry": {"coordinates":[-1.970243,50.737934],"type":"Point"}
}