{
  "type": "Feature",
  "properties": {
    "addr:full":"35 Caldmore Green Walsall West Midlands WS1 3RW",
    "addr:housenumber":"35",
    "addr:postcode":"ws1 3rw",
    "addr:street":"Caldmore Green",
    "iso:country":"GB",
    "sg:address":"35 Caldmore Green",
    "sg:city":"Walsall",
    "sg:classifiers":[
        {
            "category":"Food & Beverages",
            "subcategory":"Meat & Fish",
            "type":"Retail Goods"
        }
    ],
    "sg:phone":"+44 1922 612895",
    "sg:postcode":"WS1 3RW",
    "sg:province":"West Midlands",
    "sg:tags":[
        "butcher"
    ],
    "wof:name":"D Ward",
    "wof:placetype":"venue"
},
  "geometry": {"coordinates":[-1.9826829433,52.5766868591],"type":"Point"}
}