{
  "type": "Feature",
  "properties": {
    "iso:country":"GB",
    "sg:address":"316 Beacon View Road",
    "sg:city":"West Bromwich",
    "sg:classifiers":[
        {
            "category":"Government",
            "subcategory":"Post Office",
            "type":"Public Place"
        }
    ],
    "sg:phone":"+44 121 588 2970",
    "sg:postcode":"B71 3NX",
    "sg:province":"West Midlands",
    "wof:name":"Charlemont Farm Post Office",
    "wof:placetype":"venue"
},
  "geometry": {"coordinates":[-1.975354,52.545792],"type":"Point"}
}