{
  "type": "Feature",
  "properties": {
    "iso:country":"GB",
    "sg:address":"International Departure Lounge, North Terminal, London Gatwick Airport",
    "sg:city":"Gatwick",
    "sg:classifiers":[
        {
            "category":"Shopping",
            "subcategory":"Stationery & Office Supplies",
            "type":"Retail Goods"
        }
    ],
    "sg:phone":"+44 1293 579330",
    "sg:postcode":"RH6 0NP",
    "sg:province":"Surrey",
    "wof:name":"The Pen Shop",
    "wof:placetype":"venue"
},
  "geometry": {"coordinates":[-0.1723539978,51.1617736816],"type":"Point"}
}