{
  "type": "Feature",
  "properties": {
    "addr:full":"1 Ollgar Close Shepherd's Bush Greater London W12 0NF",
    "addr:housenumber":"1",
    "addr:postcode":"w12 0nf",
    "addr:street":"Ollgar Close",
    "iso:country":"GB",
    "sg:address":"1 Ollgar Close",
    "sg:city":"Shepherd's Bush",
    "sg:classifiers":[
        {
            "category":"Organizations",
            "subcategory":"Non-profit Organization",
            "type":"Services"
        }
    ],
    "sg:phone":"+44 20 8749 7211",
    "sg:postcode":"W12 0NF",
    "sg:province":"Greater London",
    "sg:tags":[
        "organisation",
        "voluntary",
        "charity"
    ],
    "wof:name":"NCH Action for Children",
    "wof:placetype":"venue"
},
  "geometry": {"coordinates":[-0.242554,51.507317],"type":"Point"}
}