{
  "type": "Feature",
  "properties": {
    "addr:full":"1 Paradise Lane, Warley Halifax West Yorkshire HX2 7RQ",
    "addr:housenumber":"1",
    "addr:postcode":"hx2 7rq",
    "addr:street":"Paradise Lane",
    "iso:country":"GB",
    "sg:address":"1 Paradise Lane, Warley",
    "sg:city":"Halifax",
    "sg:classifiers":[
        {
            "category":"Home & Garden",
            "subcategory":"Home Furnishings",
            "type":"Retail Goods"
        }
    ],
    "sg:postcode":"HX2 7RQ",
    "sg:province":"West Yorkshire",
    "sg:tags":[
        "blind",
        "curtain",
        "fitting"
    ],
    "wof:name":"Ruth Powell",
    "wof:placetype":"venue"
},
  "geometry": {"coordinates":[-1.9217649698,53.7236061096],"type":"Point"}
}