{
  "type": "Feature",
  "properties": {
    "addr:full":"89 Canada Road Cardiff Cardiff CF14 3BX",
    "addr:housenumber":"89",
    "addr:postcode":"cf14 3bx",
    "addr:street":"Canada Road",
    "iso:country":"GB",
    "sg:address":"89 Canada Road",
    "sg:city":"Cardiff",
    "sg:classifiers":[
        {
            "category":"Professional",
            "subcategory":"Art Services",
            "type":"Services"
        }
    ],
    "sg:phone":"+44 29 2069 2433",
    "sg:postcode":"CF14 3BX",
    "sg:province":"Cardiff",
    "sg:tags":[
        "graphic",
        "designer"
    ],
    "wof:name":"Brinkworth Design",
    "wof:placetype":"venue"
},
  "geometry": {"coordinates":[-3.1934349537,51.4988250732],"type":"Point"}
}