{
  "type": "Feature",
  "properties": {
    "addr:full":"46 The Crosspath Radlett Hertfordshire WD7 8HW",
    "addr:housenumber":"46",
    "addr:postcode":"wd7 8hw",
    "addr:street":"The Crosspath Radlett",
    "iso:country":"GB",
    "sg:address":"46 The Crosspath",
    "sg:city":"Radlett",
    "sg:classifiers":[
        {
            "category":"Travel",
            "subcategory":"Hotels & Motels",
            "type":"Entertainment"
        }
    ],
    "sg:phone":"+44 1923 469142",
    "sg:postcode":"WD7 8HW",
    "sg:province":"Hertfordshire",
    "sg:tags":[
        "house",
        "guest"
    ],
    "wof:name":"Cotswold Guest House",
    "wof:placetype":"venue"
},
  "geometry": {"coordinates":[-0.320507,51.684353],"type":"Point"}
}