{
  "type": "Feature",
  "properties": {
    "addr:full":"Britannia Wks Gainsborough Lincolnshire DN21 2EX",
    "addr:postcode":"dn21 2ex",
    "iso:country":"GB",
    "sg:address":"Britannia Wks",
    "sg:city":"Gainsborough",
    "sg:classifiers":[
        {
            "category":"Professional",
            "subcategory":"Engineering",
            "type":"Services"
        }
    ],
    "sg:phone":"+44 1427 616927",
    "sg:postcode":"DN21 2EX",
    "sg:province":"Lincolnshire",
    "wof:name":"Environmental Engineering Group Ltd",
    "wof:placetype":"venue"
},
  "geometry": {"coordinates":[-0.78836,53.405788],"type":"Point"}
}