{
  "type": "Feature",
  "properties": {
    "iso:country":"GB",
    "sg:address":"Molland Cross Farm",
    "sg:city":"South Molton",
    "sg:classifiers":[
        {
            "category":"Farming",
            "subcategory":"Livestock Farm",
            "type":"Manufacturing & Wholesale Goods"
        }
    ],
    "sg:phone":"+44 1598 710243",
    "sg:postcode":"EX36 3EU",
    "sg:province":"Devon",
    "sg:tags":[
        "others"
    ],
    "wof:name":"B J Tapp",
    "wof:placetype":"venue"
},
  "geometry": {"coordinates":[-3.8318240643,51.0176467896],"type":"Point"}
}