{
  "type": "Feature",
  "properties": {
    "iso:country":"GB",
    "sg:address":"St Christopher Road",
    "sg:city":"Colchester",
    "sg:classifiers":[
        {
            "category":"Bars & Pubs",
            "type":"Food & Drink"
        },
        {
            "category":"Community Center",
            "subcategory":"Social",
            "type":"Public Place"
        }
    ],
    "sg:phone":"+44 1206 843402",
    "sg:postcode":"CO4 0NE",
    "sg:province":"Essex",
    "sg:tags":[
        "pubs",
        "house",
        "inn",
        "activity"
    ],
    "wof:name":"The Friar",
    "wof:placetype":"venue"
},
  "geometry": {"coordinates":[0.93462,51.903515],"type":"Point"}
}