{
  "type": "Feature",
  "properties": {
    "addr:full":"Great North Rd Newcastle Upon Tyne Tyne and Wear NE3 2DT",
    "addr:postcode":"ne3 2dt",
    "addr:street":"Great North Rd",
    "iso:country":"GB",
    "sg:address":"Great North Rd",
    "sg:city":"Newcastle Upon Tyne",
    "sg:classifiers":[
        {
            "category":"Autos & Motor Vehicles",
            "subcategory":"Fuel & Gas Station",
            "type":"Retail Goods"
        }
    ],
    "sg:phone":"+44 191 213 3770",
    "sg:postcode":"NE3 2DT",
    "sg:province":"Tyne and Wear",
    "sg:tags":[
        "hr",
        "petrol"
    ],
    "wof:name":"Shell Gosforth",
    "wof:placetype":"venue"
},
  "geometry": {"coordinates":[-1.6211899519,55.0217781067],"type":"Point"}
}