{
  "type": "Feature",
  "properties": {
    "addr:full":"The Smithy, Hampden Bottom, Little Hampden Great Missenden Buckinghamshire HP16 9PR",
    "addr:postcode":"hp16 9pr",
    "iso:country":"GB",
    "sg:address":"The Smithy, Hampden Bottom, Little Hampden",
    "sg:city":"Great Missenden",
    "sg:classifiers":[
        {
            "category":"Home & Garden",
            "subcategory":"Building Materials",
            "type":"Retail Goods"
        }
    ],
    "sg:phone":"+44 1494 488106",
    "sg:postcode":"HP16 9PR",
    "sg:province":"Buckinghamshire",
    "sg:tags":[
        "ironwork",
        "wrought"
    ],
    "wof:name":"Forge Planters",
    "wof:placetype":"venue"
},
  "geometry": {"coordinates":[-0.709043026,51.7040672302],"type":"Point"}
}