{
  "type": "Feature",
  "properties": {
    "addr:full":"11 Barchester Road Harrow Greater London HA3 5HH",
    "addr:housenumber":"11",
    "addr:postcode":"ha3 5hh",
    "addr:street":"Barchester Road",
    "iso:country":"GB",
    "sg:address":"11 Barchester Road",
    "sg:city":"Harrow",
    "sg:classifiers":[
        {
            "category":"Manufacturing",
            "subcategory":"Toys & Sporting Goods",
            "type":"Manufacturing & Wholesale Goods"
        },
        {
            "category":"Shopping",
            "subcategory":"Clothing, Apparel, & Fashions",
            "type":"Retail Goods"
        }
    ],
    "sg:phone":"+44 20 8863 4014",
    "sg:postcode":"HA3 5HH",
    "sg:province":"Greater London",
    "sg:tags":[
        "sportswear",
        "manufacturer"
    ],
    "wof:name":"Abbtex Sportswear Specialist In Football Kits",
    "wof:placetype":"venue"
},
  "geometry": {"coordinates":[-0.3421060145,51.6011505127],"type":"Point"}
}