{
  "type": "Feature",
  "properties": {
    "iso:country":"GB",
    "sg:address":"234 Holmley Lane, Coal Aston",
    "sg:city":"Dronfield",
    "sg:classifiers":[
        {
            "category":"Bars & Pubs",
            "type":"Food & Drink"
        }
    ],
    "sg:phone":"+44 1246 412846",
    "sg:postcode":"S18 3DB",
    "sg:province":"Derbyshire",
    "sg:tags":[
        "pubs",
        "inn"
    ],
    "wof:name":"Yew Tree Inn",
    "wof:placetype":"venue"
},
  "geometry": {"coordinates":[-1.462921,53.310974],"type":"Point"}
}