{
  "type": "Feature",
  "properties": {
    "addr:full":"26 Wellington Road South Stockport Cheshire SK4 1AA",
    "addr:housenumber":"26",
    "addr:postcode":"sk4 1aa",
    "addr:street":"Wellington Road South",
    "iso:country":"GB",
    "sg:address":"26 Wellington Road South",
    "sg:city":"Stockport",
    "sg:classifiers":[
        {
            "category":"Retail",
            "subcategory":"Driving School",
            "type":"Services"
        }
    ],
    "sg:phone":"+44 161 480 5284",
    "sg:postcode":"SK4 1AA",
    "sg:province":"Cheshire",
    "wof:name":"B S M",
    "wof:placetype":"venue"
},
  "geometry": {"coordinates":[-2.161371,53.408176],"type":"Point"}
}