{
  "type": "Feature",
  "properties": {
    "addr:full":"Annie Pit Lane, Clay Flatts Trading Estate Workington Cumbria CA14 2DB",
    "addr:postcode":"ca14 2db",
    "addr:street":"Annie Pit Lane;Trading Estate",
    "iso:country":"GB",
    "sg:address":"Annie Pit Lane, Clay Flatts Trading Estate",
    "sg:city":"Workington",
    "sg:classifiers":[
        {
            "category":"Utilities",
            "subcategory":"Natural Gas",
            "type":"Services"
        }
    ],
    "sg:postcode":"CA14 2DB",
    "sg:province":"Cumbria",
    "sg:tags":[
        "supplier"
    ],
    "wof:name":"Boc Gases",
    "wof:placetype":"venue"
},
  "geometry": {"coordinates":[-3.550002,54.638981],"type":"Point"}
}