{
  "type": "Feature",
  "properties": {
    "addr:full":"17 Princess Street Shrewsbury Shropshire SY1 1LP",
    "addr:housenumber":"17",
    "addr:postcode":"sy1 1lp",
    "addr:street":"Princess Street",
    "iso:country":"GB",
    "sg:address":"17 Princess Street",
    "sg:city":"Shrewsbury",
    "sg:classifiers":[
        {
            "category":"Shopping",
            "subcategory":"Clothing, Apparel, & Fashions",
            "type":"Retail Goods"
        }
    ],
    "sg:phone":"+44 1743 351731",
    "sg:postcode":"SY1 1LP",
    "sg:province":"Shropshire",
    "sg:tags":[
        "shop"
    ],
    "wof:name":"Expressions",
    "wof:placetype":"venue"
},
  "geometry": {"coordinates":[-2.7529990673,52.7067718506],"type":"Point"}
}