{
  "type": "Feature",
  "properties": {
    "iso:country":"GB",
    "sg:address":"84 High Street",
    "sg:city":"Braintree",
    "sg:classifiers":[
        {
            "category":"Shopping",
            "subcategory":"Gifts & Souvenirs",
            "type":"Retail Goods"
        }
    ],
    "sg:phone":"+44 1376 331950",
    "sg:postcode":"CM7 1JP",
    "sg:province":"Essex",
    "sg:tags":[
        "poster",
        "card"
    ],
    "wof:name":"For All Occasions",
    "wof:placetype":"venue"
},
  "geometry": {"coordinates":[0.550043,51.878044],"type":"Point"}
}