{
  "type": "Feature",
  "properties": {
    "addr:full":"5 Chiltern Close Ware Hertfordshire SG12 0RN",
    "addr:housenumber":"5",
    "addr:postcode":"sg12 0rn",
    "addr:street":"Chiltern Close",
    "iso:country":"GB",
    "sg:address":"5 Chiltern Close",
    "sg:city":"Ware",
    "sg:classifiers":[
        {
            "category":"Autos & Motor Vehicles",
            "subcategory":"Motorcycle Sales",
            "type":"Retail Goods"
        }
    ],
    "sg:phone":"+44 1992 303060",
    "sg:postcode":"SG12 0RN",
    "sg:province":"Hertfordshire",
    "sg:tags":[
        "chauffeur",
        "driven",
        "car"
    ],
    "wof:name":"First Choice Limousines",
    "wof:placetype":"venue"
},
  "geometry": {"coordinates":[-0.032166,51.821346],"type":"Point"}
}