{
  "type": "Feature",
  "properties": {
    "iso:country":"GB",
    "sg:address":"8 Second Avenue, Bluebridge Industrial Estate",
    "sg:city":"Halstead",
    "sg:classifiers":[
        {
            "category":"Shopping",
            "subcategory":"Discount & Variety Stores",
            "type":"Retail Goods"
        },
        {
            "category":"Wholesale",
            "subcategory":"Home Furnishings",
            "type":"Manufacturing & Wholesale Goods"
        }
    ],
    "sg:phone":"+44 1787 477149",
    "sg:postcode":"CO9 2SU",
    "sg:province":"Essex",
    "sg:tags":[
        "cleaning",
        "tube",
        "fitting",
        "supply"
    ],
    "wof:name":"I R Donald",
    "wof:placetype":"venue"
},
  "geometry": {"coordinates":[0.655902,51.939659],"type":"Point"}
}