{
  "type": "Feature",
  "properties": {
    "addr:full":"7 Wigan New Market Wigan Lancashire WN1 1PW",
    "addr:housenumber":"7",
    "addr:postcode":"wn1 1pw",
    "iso:country":"GB",
    "sg:address":"7 Wigan New Market",
    "sg:city":"Wigan",
    "sg:classifiers":[
        {
            "category":"Deli",
            "type":"Food & Drink"
        }
    ],
    "sg:postcode":"WN1 1PW",
    "sg:province":"Lancashire",
    "sg:tags":[
        "delicatessen"
    ],
    "wof:name":"Clunans",
    "wof:placetype":"venue"
},
  "geometry": {"coordinates":[-2.6355071068,53.5475692749],"type":"Point"}
}