{
  "type": "Feature",
  "properties": {
    "iso:country":"GB",
    "sg:address":"26 High Street",
    "sg:city":"Street",
    "sg:classifiers":[
        {
            "category":"Professional",
            "subcategory":"Accounting & Tax Preparation",
            "type":"Services"
        }
    ],
    "sg:phone":"+44 1458 442027",
    "sg:postcode":"BA16 0EB",
    "sg:province":"Somerset",
    "sg:tags":[
        "accountant"
    ],
    "wof:name":"Raymond Wright & Co",
    "wof:placetype":"venue"
},
  "geometry": {"coordinates":[-2.737503,51.128803],"type":"Point"}
}