{
  "type": "Feature",
  "properties": {
    "addr:full":"Colliery Lane, Hetton Le Hole Houghton-le-spring Durham DH5 0BD",
    "addr:postcode":"dh5 0bd",
    "addr:street":"Colliery Lane;Le Hole",
    "iso:country":"GB",
    "sg:address":"Colliery Lane, Hetton Le Hole",
    "sg:city":"Houghton-le-spring",
    "sg:classifiers":[
        {
            "category":"Building & Trades",
            "subcategory":"Landscaping Services",
            "type":"Services"
        }
    ],
    "sg:phone":"+44 191 526 3619",
    "sg:postcode":"DH5 0BD",
    "sg:province":"Durham",
    "sg:tags":[
        "landscape",
        "contractor"
    ],
    "wof:name":"John Hellens (Contracts) Ltd.",
    "wof:placetype":"venue"
},
  "geometry": {"coordinates":[-1.4473839998,54.815448761],"type":"Point"}
}