{
  "type": "Feature",
  "properties": {
    "addr:full":"28 Main Street, Etwall Derby Derbyshire DE65 6LP",
    "addr:housenumber":"28",
    "addr:postcode":"de65 6lp",
    "addr:street":"Main Street",
    "iso:country":"GB",
    "sg:address":"28 Main Street, Etwall",
    "sg:city":"Derby",
    "sg:classifiers":[
        {
            "category":"Bars & Pubs",
            "type":"Food & Drink"
        }
    ],
    "sg:postcode":"DE65 6LP",
    "sg:province":"Derbyshire",
    "sg:tags":[
        "pubs",
        "inn"
    ],
    "wof:name":"Spread Eagle",
    "wof:placetype":"venue"
},
  "geometry": {"coordinates":[-1.60165,52.883961],"type":"Point"}
}