{
  "type": "Feature",
  "properties": {
    "iso:country":"GB",
    "sg:address":"2 Lonsdale Road",
    "sg:city":"Sheffield",
    "sg:classifiers":[
        {
            "category":"Building & Trades",
            "subcategory":"Construction",
            "type":"Services"
        }
    ],
    "sg:phone":"+44 114 231 4721",
    "sg:postcode":"S6 2PS",
    "sg:province":"South Yorkshire",
    "sg:tags":[
        "builder"
    ],
    "wof:name":"H M Builders",
    "wof:placetype":"venue"
},
  "geometry": {"coordinates":[-1.500918,53.397564],"type":"Point"}
}