{
  "type": "Feature",
  "properties": {
    "addr:full":"Dunston Enterprise Park, West View Terrace Gateshead Tyne and Wear NE11 9DW",
    "addr:postcode":"ne11 9dw",
    "addr:street":"West View Terrace",
    "iso:country":"GB",
    "sg:address":"Dunston Enterprise Park, West View Terrace",
    "sg:city":"Gateshead",
    "sg:classifiers":[
        {
            "category":"Home & Garden",
            "subcategory":"Home Furnishings",
            "type":"Retail Goods"
        }
    ],
    "sg:phone":"+44 191 460 3553",
    "sg:postcode":"NE11 9DW",
    "sg:province":"Tyne and Wear",
    "sg:tags":[
        "blind",
        "curtain",
        "fitting"
    ],
    "wof:name":"The Vertical Blind Company",
    "wof:placetype":"venue"
},
  "geometry": {"coordinates":[-1.6511900425,54.9584007263],"type":"Point"}
}