{
  "type": "Feature",
  "properties": {
    "addr:full":"Blunts La Peterborough Cambridgeshire PE7 1AH",
    "addr:postcode":"pe7 1ah",
    "addr:street":"La Peterborough",
    "iso:country":"GB",
    "sg:address":"Blunts La",
    "sg:city":"Peterborough",
    "sg:classifiers":[
        {
            "category":"Insurance",
            "subcategory":"Insurance Agent",
            "type":"Services"
        }
    ],
    "sg:phone":"+44 1733 203274",
    "sg:postcode":"PE7 1AH",
    "sg:province":"Cambridgeshire",
    "wof:name":"N F U Mutual",
    "wof:placetype":"venue"
},
  "geometry": {"coordinates":[-0.1246839985,52.5571670532],"type":"Point"}
}