{
  "type": "Feature",
  "properties": {
    "addr:full":"Cherry Tree Lane, Fulmer Slough Berkshire SL3 6JE",
    "addr:postcode":"sl3 6je",
    "addr:street":"Cherry Tree Lane",
    "iso:country":"GB",
    "sg:address":"Cherry Tree Lane, Fulmer",
    "sg:city":"Slough",
    "sg:classifiers":[
        {
            "category":"Home & Garden",
            "subcategory":"Garden Supply",
            "type":"Retail Goods"
        },
        {
            "category":"Shopping",
            "subcategory":"Computers & Home Electronics",
            "type":"Retail Goods"
        }
    ],
    "sg:phone":"+44 1753 662604",
    "sg:postcode":"SL3 6JE",
    "sg:province":"Berkshire",
    "sg:tags":[
        "household",
        "nursery",
        "store",
        "centre"
    ],
    "wof:name":"Fulmer Plant Park",
    "wof:placetype":"venue"
},
  "geometry": {"coordinates":[-0.5600559711,51.5614547729],"type":"Point"}
}