{
  "type": "Feature",
  "properties": {
    "addr:full":"Thorpe La Leeds West Yorkshire LS10 4EP",
    "addr:postcode":"ls10 4ep",
    "addr:street":"West",
    "iso:country":"GB",
    "sg:address":"Thorpe La",
    "sg:city":"Leeds",
    "sg:classifiers":[
        {
            "category":"Wholesale",
            "subcategory":"Scrap",
            "type":"Manufacturing & Wholesale Goods"
        }
    ],
    "sg:postcode":"LS10 4EP",
    "sg:province":"West Yorkshire",
    "sg:tags":[
        "breaker",
        "dismantlers"
    ],
    "wof:name":"Ferguson,Patrick,",
    "wof:placetype":"venue"
},
  "geometry": {"coordinates":[-1.548099041,53.7386665344],"type":"Point"}
}