{
  "type": "Feature",
  "properties": {
    "iso:country":"GB",
    "sg:address":"20 Upper Wimpole Street",
    "sg:city":"London",
    "sg:classifiers":[
        {
            "category":"Shopping",
            "subcategory":"Catalog Store",
            "type":"Retail Goods"
        }
    ],
    "sg:phone":"+44 20 7289 1149",
    "sg:postcode":"W1G 6NB",
    "sg:province":"Greater London",
    "sg:tags":[
        "mail",
        "order"
    ],
    "wof:name":"Joanna's",
    "wof:placetype":"venue"
},
  "geometry": {"coordinates":[-0.149648,51.520828],"type":"Point"}
}