{
  "type": "Feature",
  "properties": {
    "addr:full":"18 Thorncroft Egham Surrey TW20 0SB",
    "addr:housenumber":"18",
    "addr:postcode":"tw20 0sb",
    "addr:street":"Thorncroft Egham",
    "iso:country":"GB",
    "sg:address":"18 Thorncroft",
    "sg:city":"Egham",
    "sg:classifiers":[
        {
            "category":"Building & Trades",
            "subcategory":"Plumbing",
            "type":"Services"
        }
    ],
    "sg:phone":"+44 1784 438370",
    "sg:postcode":"TW20 0SB",
    "sg:province":"Surrey",
    "sg:tags":[
        "heating"
    ],
    "wof:name":"E J Rowe & Son",
    "wof:placetype":"venue"
},
  "geometry": {"coordinates":[-0.574847,51.423981],"type":"Point"}
}