{
  "type": "Feature",
  "properties": {
    "iso:country":"GB",
    "sg:address":"14 The Old School, Station Rd",
    "sg:city":"Narberth",
    "sg:classifiers":[
        {
            "category":"Professional",
            "subcategory":"Management & Consulting",
            "type":"Services"
        }
    ],
    "sg:postcode":"SA67 7DU",
    "sg:province":"Carmarthenshire",
    "sg:tags":[
        "consultant",
        "business"
    ],
    "wof:name":"New Paradigm Consultants Ltd",
    "wof:placetype":"venue"
},
  "geometry": {"coordinates":[-4.744227,51.80117],"type":"Point"}
}