{
  "type": "Feature",
  "properties": {
    "addr:full":"51 Midland Road Scunthorpe Lincolnshire DN16 1DQ",
    "addr:housenumber":"51",
    "addr:postcode":"dn16 1dq",
    "addr:street":"Midland Road",
    "iso:country":"GB",
    "sg:address":"51 Midland Road",
    "sg:city":"Scunthorpe",
    "sg:classifiers":[
        {
            "category":"Retail",
            "subcategory":"Auto Repair",
            "type":"Services"
        }
    ],
    "sg:phone":"+44 1724 282060",
    "sg:postcode":"DN16 1DQ",
    "sg:province":"Lincolnshire",
    "sg:tags":[
        "modification",
        "garage"
    ],
    "wof:name":"Automech",
    "wof:placetype":"venue"
},
  "geometry": {"coordinates":[-0.6312509775,53.5822143555],"type":"Point"}
}