{
  "type": "Feature",
  "properties": {
    "iso:country":"GB",
    "sg:address":"76 The Broadway",
    "sg:city":"Birmingham",
    "sg:classifiers":[
        {
            "category":"Freight",
            "type":"Transportation"
        }
    ],
    "sg:postcode":"B20 3DY",
    "sg:province":"West Midlands",
    "sg:tags":[
        "haulage",
        "road"
    ],
    "wof:name":"P A W",
    "wof:placetype":"venue"
},
  "geometry": {"coordinates":[-1.892313,52.511288],"type":"Point"}
}