{
  "type": "Feature",
  "properties": {
    "iso:country":"GB",
    "sg:address":"High Street West, Portgordon",
    "sg:city":"Buckie",
    "sg:classifiers":[
        {
            "category":"Bars & Pubs",
            "type":"Food & Drink"
        }
    ],
    "sg:postcode":"AB56 5QS",
    "sg:province":"Moray",
    "sg:tags":[
        "pubs",
        "inn"
    ],
    "wof:name":"The Richmond Arms Hotel",
    "wof:placetype":"venue"
},
  "geometry": {"coordinates":[-2.958509,57.669739],"type":"Point"}
}