{
  "type": "Feature",
  "properties": {
    "addr:full":"31 Louth Road Grimsby Lincolnshire DN33 2ER",
    "addr:housenumber":"31",
    "addr:postcode":"dn33 2er",
    "addr:street":"Louth Road",
    "iso:country":"GB",
    "sg:address":"31 Louth Road",
    "sg:city":"Grimsby",
    "sg:classifiers":[
        {
            "category":"Shopping",
            "subcategory":"News",
            "type":"Retail Goods"
        }
    ],
    "sg:phone":"+44 1472 879314",
    "sg:postcode":"DN33 2ER",
    "sg:province":"Lincolnshire",
    "sg:tags":[
        "newsagent"
    ],
    "wof:name":"United News Shops Ltd.",
    "wof:placetype":"venue"
},
  "geometry": {"coordinates":[-0.091216,53.537605],"type":"Point"}
}