{
  "type": "Feature",
  "properties": {
    "addr:full":"63 Ambleside Rd, Bedworth Nuneaton Warwickshire CV12 8RR",
    "addr:housenumber":"63",
    "addr:postcode":"cv12 8rr",
    "addr:street":"Ambleside Rd",
    "iso:country":"GB",
    "sg:address":"63 Ambleside Rd, Bedworth",
    "sg:city":"Nuneaton",
    "sg:classifiers":[
        {
            "category":"Professional",
            "subcategory":"Art Services",
            "type":"Services"
        }
    ],
    "sg:postcode":"CV12 8RR",
    "sg:province":"Warwickshire",
    "sg:tags":[
        "photographer"
    ],
    "wof:name":"John,Colleen,",
    "wof:placetype":"venue"
},
  "geometry": {"coordinates":[-1.480049,52.475277],"type":"Point"}
}