{
  "type": "Feature",
  "properties": {
    "addr:full":"56 Knight Street, Pinchbeck Spalding Lincolnshire PE11 3RB",
    "addr:housenumber":"56",
    "addr:postcode":"pe11 3rb",
    "addr:street":"Knight Street",
    "iso:country":"GB",
    "sg:address":"56 Knight Street, Pinchbeck",
    "sg:city":"Spalding",
    "sg:classifiers":[
        {
            "category":"Shopping",
            "subcategory":"Florist",
            "type":"Retail Goods"
        }
    ],
    "sg:postcode":"PE11 3RB",
    "sg:province":"Lincolnshire",
    "wof:name":"Village Flowers",
    "wof:placetype":"venue"
},
  "geometry": {"coordinates":[-0.161305,52.816399],"type":"Point"}
}