{
  "type": "Feature",
  "properties": {
    "addr:full":"112-114-116 Water Street, Radcliffe Manchester Greater Manchester M26 4BE",
    "addr:housenumber":"112-114-116",
    "addr:postcode":"m26 4be",
    "addr:street":"Water Street",
    "iso:country":"GB",
    "sg:address":"112-114-116 Water Street, Radcliffe",
    "sg:city":"Manchester",
    "sg:classifiers":[
        {
            "category":"Shopping",
            "subcategory":"Clothing, Apparel, & Fashions",
            "type":"Retail Goods"
        }
    ],
    "sg:phone":"+44 161 725 9085",
    "sg:postcode":"M26 4BE",
    "sg:province":"Greater Manchester",
    "sg:tags":[
        "shop"
    ],
    "wof:name":"White Lines For Men Women & Children",
    "wof:placetype":"venue"
},
  "geometry": {"coordinates":[-2.33525,53.562981],"type":"Point"}
}