{
  "type": "Feature",
  "properties": {
    "iso:country":"GB",
    "sg:address":"Kirk Rd",
    "sg:city":"Beith",
    "sg:classifiers":[
        {
            "category":"Place Of Worship",
            "type":"Public Place"
        }
    ],
    "sg:phone":"+44 1505 502686",
    "sg:postcode":"KA15 1EX",
    "sg:province":"North Ayrshire",
    "wof:name":"Beith High Parish Church",
    "wof:placetype":"venue"
},
  "geometry": {"coordinates":[-4.637898,55.748066],"type":"Point"}
}