{
  "type": "Feature",
  "properties": {
    "iso:country":"GB",
    "sg:address":"93 Lemsford Road",
    "sg:city":"Hatfield",
    "sg:classifiers":[
        {
            "category":"Professional",
            "subcategory":"Detective & Security Services",
            "type":"Services"
        }
    ],
    "sg:phone":"+44 1707 272268",
    "sg:postcode":"AL10 0DZ",
    "sg:province":"Hertfordshire",
    "sg:tags":[
        "locksmith"
    ],
    "wof:name":"David Wilson Locksmith",
    "wof:placetype":"venue"
},
  "geometry": {"coordinates":[-0.23365,51.767422],"type":"Point"}
}