{
  "type": "Feature",
  "properties": {
    "addr:full":"132 Main Street Prestwick South Ayrshire KA9 1PB",
    "addr:housenumber":"132",
    "addr:postcode":"ka9 1pb",
    "addr:street":"Main Street",
    "iso:country":"GB",
    "sg:address":"132 Main Street",
    "sg:city":"Prestwick",
    "sg:classifiers":[
        {
            "category":"Travel",
            "subcategory":"Hotels & Motels",
            "type":"Entertainment"
        }
    ],
    "sg:postcode":"KA9 1PB",
    "sg:province":"South Ayrshire",
    "wof:name":"Butlers House Hotel",
    "wof:placetype":"venue"
},
  "geometry": {"coordinates":[-4.6123800278,55.497428894],"type":"Point"}
}