{
  "type": "Feature",
  "properties": {
    "iso:country":"GB",
    "sg:address":"Criterion Way",
    "sg:city":"Pembroke Dock",
    "sg:classifiers":[
        {
            "category":"Retail",
            "subcategory":"Auto Repair",
            "type":"Services"
        }
    ],
    "sg:phone":"+44 1646 621499",
    "sg:postcode":"SA72 6TA",
    "sg:province":"Pembrokeshire",
    "sg:tags":[
        "modification",
        "garage"
    ],
    "wof:name":"Criterion Motor Repairs",
    "wof:placetype":"venue"
},
  "geometry": {"coordinates":[-4.9408888817,51.6968536377],"type":"Point"}
}