{
  "type": "Feature",
  "properties": {
    "addr:full":"24 Middle Mead Rochford Essex SS4 1RL",
    "addr:housenumber":"24",
    "addr:postcode":"ss4 1rl",
    "addr:street":"Middle Mead",
    "iso:country":"GB",
    "sg:address":"24 Middle Mead",
    "sg:city":"Rochford",
    "sg:classifiers":[
        {
            "category":"Building & Trades",
            "subcategory":"Construction",
            "type":"Services"
        }
    ],
    "sg:postcode":"SS4 1RL",
    "sg:province":"Essex",
    "sg:tags":[
        "tiling",
        "contractor"
    ],
    "wof:name":"T H Davies",
    "wof:placetype":"venue"
},
  "geometry": {"coordinates":[0.708176,51.585026],"type":"Point"}
}