{
  "type": "Feature",
  "properties": {
    "addr:full":"Botley Road, Shedfield Southampton Hampshire SO32 2JG",
    "addr:postcode":"so32 2jg",
    "addr:street":"Botley Road",
    "iso:country":"GB",
    "sg:address":"Botley Road, Shedfield",
    "sg:city":"Southampton",
    "sg:classifiers":[
        {
            "category":"Bars & Pubs",
            "type":"Food & Drink"
        }
    ],
    "sg:postcode":"SO32 2JG",
    "sg:province":"Hampshire",
    "sg:tags":[
        "pubs",
        "inn"
    ],
    "wof:name":"The Wheatsheaf Inn",
    "wof:placetype":"venue"
},
  "geometry": {"coordinates":[-1.209134,50.915001],"type":"Point"}
}