{
  "type": "Feature",
  "properties": {
    "addr:full":"Marlborough House, Headley Road, Grayshott Hindhead Hampshire GU26 6LG",
    "addr:postcode":"gu26 6lg",
    "addr:street":"Headley Road",
    "iso:country":"GB",
    "sg:address":"Marlborough House, Headley Road, Grayshott",
    "sg:city":"Hindhead",
    "sg:classifiers":[
        {
            "category":"Professional",
            "subcategory":"Business Services",
            "type":"Services"
        }
    ],
    "sg:phone":"+44 1428 602627",
    "sg:postcode":"GU26 6LG",
    "sg:province":"Hampshire",
    "sg:tags":[
        "trade"
    ],
    "wof:name":"Association of Police & Public Security Suppliers",
    "wof:placetype":"venue"
},
  "geometry": {"coordinates":[-0.7837190032,51.1160583496],"type":"Point"}
}