{
  "type": "Feature",
  "properties": {
    "addr:full":"80 Virginia Road Whitstable Kent CT5 3HZ",
    "addr:housenumber":"80",
    "addr:postcode":"ct5 3hz",
    "addr:street":"Virginia Road",
    "iso:country":"GB",
    "sg:address":"80 Virginia Road",
    "sg:city":"Whitstable",
    "sg:classifiers":[
        {
            "category":"Building & Trades",
            "subcategory":"Construction",
            "type":"Services"
        }
    ],
    "sg:phone":"+44 1227 272729",
    "sg:postcode":"CT5 3HZ",
    "sg:province":"Kent",
    "sg:tags":[
        "joinery",
        "joiner",
        "carpenter",
        "carpentry"
    ],
    "wof:name":"Clark & Hockey",
    "wof:placetype":"venue"
},
  "geometry": {"coordinates":[1.050755024,51.3520812988],"type":"Point"}
}