{
  "type": "Feature",
  "properties": {
    "addr:full":"213 Milton Road Weston-super-mare Somerset BS22 8EG",
    "addr:housenumber":"213",
    "addr:postcode":"bs22 8eg",
    "addr:street":"Milton Road",
    "iso:country":"GB",
    "sg:address":"213 Milton Road",
    "sg:city":"Weston-super-mare",
    "sg:classifiers":[
        {
            "category":"Home & Garden",
            "subcategory":"Furniture",
            "type":"Retail Goods"
        }
    ],
    "sg:postcode":"BS22 8EG",
    "sg:province":"Somerset",
    "wof:name":"Linton Handcrafts",
    "wof:placetype":"venue"
},
  "geometry": {"coordinates":[-2.9444429874,51.3540916443],"type":"Point"}
}