{
  "type": "Feature",
  "properties": {
    "addr:full":"South Stour Avenue Ashford Kent TN23 7RS",
    "addr:postcode":"tn23 7rs",
    "addr:street":"South Stour Avenue",
    "iso:country":"GB",
    "sg:address":"South Stour Avenue",
    "sg:city":"Ashford",
    "sg:classifiers":[
        {
            "category":"Retail",
            "subcategory":"Laundry & Dry Cleaning",
            "type":"Services"
        }
    ],
    "sg:phone":"+44 1233 646168",
    "sg:postcode":"TN23 7RS",
    "sg:province":"Kent",
    "sg:tags":[
        "cleaner",
        "alteration"
    ],
    "wof:name":"Kennington Laundry (Ashford) Ltd",
    "wof:placetype":"venue"
},
  "geometry": {"coordinates":[0.8741750121,51.1409645081],"type":"Point"}
}