{
  "type": "Feature",
  "properties": {
    "iso:country":"GB",
    "sg:address":"85 Sinclair Road",
    "sg:city":"London",
    "sg:classifiers":[
        {
            "category":"Organizations",
            "subcategory":"Membership Organization",
            "type":"Services"
        }
    ],
    "sg:postcode":"W14 0NR",
    "sg:province":"Greater London",
    "sg:tags":[
        "club"
    ],
    "wof:name":"85 Sinclair Road Management Company Limi",
    "wof:placetype":"venue"
},
  "geometry": {"coordinates":[-0.214322,51.50013],"type":"Point"}
}