{
  "type": "Feature",
  "properties": {
    "addr:full":"3 Neal's Yard London Greater London WC2H 9DP",
    "addr:housenumber":"3",
    "addr:postcode":"wc2h 9dp",
    "addr:street":"Neal'S Yard",
    "iso:country":"GB",
    "sg:address":"3 Neal's Yard",
    "sg:city":"London",
    "sg:classifiers":[
        {
            "category":"Health Services",
            "subcategory":"Health Practitioner",
            "type":"Services"
        }
    ],
    "sg:phone":"+44 20 7379 1312",
    "sg:postcode":"WC2H 9DP",
    "sg:province":"Greater London",
    "sg:tags":[
        "acupuncture"
    ],
    "wof:name":"East West Herb Shop",
    "wof:placetype":"venue"
},
  "geometry": {"coordinates":[-0.12615,51.51445],"type":"Point"}
}