{
  "type": "Feature",
  "properties": {
    "iso:country":"GB",
    "sg:address":"118 Yoden Road",
    "sg:city":"Peterlee",
    "sg:classifiers":[
        {
            "category":"Food & Beverages",
            "subcategory":"Meat & Fish",
            "type":"Retail Goods"
        }
    ],
    "sg:postcode":"SR8 5DY",
    "sg:province":"Durham",
    "sg:tags":[
        "chip"
    ],
    "wof:name":"Monte Carlo Fish Bar",
    "wof:placetype":"venue"
},
  "geometry": {"coordinates":[-1.337007,54.767654],"type":"Point"}
}