{
  "type": "Feature",
  "properties": {
    "iso:country":"GB",
    "sg:address":"Bromsgrove Road, Hunnington",
    "sg:city":"Halesowen",
    "sg:classifiers":[
        {
            "category":"Farming",
            "subcategory":"Farm",
            "type":"Manufacturing & Wholesale Goods"
        }
    ],
    "sg:phone":"+44 1562 711034",
    "sg:postcode":"B62 0JU",
    "sg:province":"West Midlands",
    "sg:tags":[
        "mixed",
        "crop"
    ],
    "wof:name":"Hollies Farm",
    "wof:placetype":"venue"
},
  "geometry": {"coordinates":[-2.0524089336,52.4281044006],"type":"Point"}
}