{
  "type": "Feature",
  "properties": {
    "iso:country":"GB",
    "sg:address":"Greys Building, 53 Grey Street",
    "sg:city":"Newcastle-upon-tyne",
    "sg:classifiers":[
        {
            "category":"Manufacturing",
            "subcategory":"Tools & Machinery",
            "type":"Manufacturing & Wholesale Goods"
        },
        {
            "category":"Insurance",
            "subcategory":"Insurance Agent",
            "type":"Services"
        },
        {
            "category":"Banks & Credit Unions",
            "subcategory":"Financial Services",
            "type":"Services"
        }
    ],
    "sg:phone":"+44 191 232 2673",
    "sg:postcode":"NE1 6QH",
    "sg:province":"Tyne and Wear",
    "sg:tags":[
        "society",
        "claim",
        "friendly",
        "assessor"
    ],
    "wof:name":"Gab Robins Uk",
    "wof:placetype":"venue"
},
  "geometry": {"coordinates":[-1.612369,54.977917],"type":"Point"}
}