{
  "type": "Feature",
  "properties": {
    "addr:full":"1 Morrison Link Edinburgh City of Edinburgh EH3 8DN",
    "addr:housenumber":"1",
    "addr:postcode":"eh3 8dn",
    "addr:street":"Morrison Link",
    "iso:country":"GB",
    "sg:address":"1 Morrison Link",
    "sg:city":"Edinburgh",
    "sg:classifiers":[
        {
            "category":"Travel",
            "subcategory":"Hotels & Motels",
            "type":"Entertainment"
        }
    ],
    "sg:phone":"+44 870 238 3319",
    "sg:postcode":"EH3 8DN",
    "sg:province":"City of Edinburgh",
    "wof:name":"Edinburgh City Travel Inn",
    "wof:placetype":"venue"
},
  "geometry": {"coordinates":[-3.214073,55.945705],"type":"Point"}
}