{
  "type": "Feature",
  "properties": {
    "addr:full":"20 Chapel Croft, Ardleigh Colchester Essex CO7 7TQ",
    "addr:housenumber":"20",
    "addr:postcode":"co7 7tq",
    "addr:street":"Chapel Croft Ardleigh Colchester",
    "iso:country":"GB",
    "sg:address":"20 Chapel Croft, Ardleigh",
    "sg:city":"Colchester",
    "sg:classifiers":[
        {
            "category":"Professional",
            "subcategory":"Management & Consulting",
            "type":"Services"
        },
        {
            "category":"Organizations",
            "subcategory":"Community Association",
            "type":"Services"
        }
    ],
    "sg:phone":"+44 1206 230831",
    "sg:postcode":"CO7 7TQ",
    "sg:province":"Essex",
    "sg:tags":[
        "consultant",
        "relation",
        "public",
        "business"
    ],
    "wof:name":"A B R Publicity",
    "wof:placetype":"venue"
},
  "geometry": {"coordinates":[0.9866480231,51.9252586365],"type":"Point"}
}