{
  "type": "Feature",
  "properties": {
    "iso:country":"GB",
    "sg:address":"59 York Road",
    "sg:city":"Northampton",
    "sg:classifiers":[
        {
            "category":"Real Estate",
            "subcategory":"Architect",
            "type":"Services"
        }
    ],
    "sg:phone":"+44 1604 635343",
    "sg:postcode":"NN1 5QL",
    "sg:province":"Northamptonshire",
    "wof:name":"Michael Ellard Design Associates Ltd.",
    "wof:placetype":"venue"
},
  "geometry": {"coordinates":[-0.88765,52.237957],"type":"Point"}
}