{
  "type": "Feature",
  "properties": {
    "addr:full":"18c The Broadway Woking Surrey GU21 5AP",
    "addr:housenumber":"18c",
    "addr:postcode":"gu21 5ap",
    "addr:street":"The Broadway",
    "iso:country":"GB",
    "sg:address":"18c The Broadway",
    "sg:city":"Woking",
    "sg:classifiers":[
        {
            "category":"Military Area",
            "subcategory":"Air Force Base",
            "type":"Public Place"
        }
    ],
    "sg:phone":"+44 1483 773000",
    "sg:postcode":"GU21 5AP",
    "sg:province":"Surrey",
    "sg:tags":[
        "taxi",
        "hire",
        "private"
    ],
    "wof:name":"Woking Cars",
    "wof:placetype":"venue"
},
  "geometry": {"coordinates":[-0.555454,51.319576],"type":"Point"}
}