{
  "type": "Feature",
  "properties": {
    "iso:country":"GB",
    "sg:address":"44 Gorselands Road, West End Park",
    "sg:city":"Southampton",
    "sg:classifiers":[
        {
            "category":"Retail",
            "subcategory":"Repair Shop",
            "type":"Services"
        }
    ],
    "sg:phone":"+44 23 8039 9380",
    "sg:postcode":"SO18 5QF",
    "sg:province":"Hampshire",
    "sg:tags":[
        "radio",
        "television",
        "video"
    ],
    "wof:name":"Alpha Electronics",
    "wof:placetype":"venue"
},
  "geometry": {"coordinates":[-1.350504,50.924183],"type":"Point"}
}