{
  "type": "Feature",
  "properties": {
    "addr:full":"Gavell Rd Twechar, Kilsyth Glasgow East Dunbartonshire G65 9LP",
    "addr:postcode":"g65 9lp",
    "addr:street":"Gavell Rd",
    "iso:country":"GB",
    "sg:address":"Gavell Rd Twechar, Kilsyth",
    "sg:city":"Glasgow",
    "sg:classifiers":[
        {
            "category":"Freight",
            "type":"Transportation"
        }
    ],
    "sg:phone":"+44 1236 821394",
    "sg:postcode":"G65 9LP",
    "sg:province":"East Dunbartonshire",
    "sg:tags":[
        "haulage",
        "road"
    ],
    "wof:name":"Withers R & C",
    "wof:placetype":"venue"
},
  "geometry": {"coordinates":[-4.081139,55.972454],"type":"Point"}
}