{
  "type": "Feature",
  "properties": {
    "iso:country":"GB",
    "sg:address":"69 High Street, Gravenhurst",
    "sg:city":"Bedford",
    "sg:classifiers":[
        {
            "category":"Bars & Pubs",
            "type":"Food & Drink"
        }
    ],
    "sg:phone":"+44 1462 711682",
    "sg:postcode":"MK45 4HZ",
    "sg:province":"Bedfordshire",
    "sg:tags":[
        "pubs",
        "inn"
    ],
    "wof:name":"The Green Dragon",
    "wof:placetype":"venue"
},
  "geometry": {"coordinates":[-0.417372,52.029846],"type":"Point"}
}