{
  "type": "Feature",
  "properties": {
    "iso:country":"GB",
    "sg:address":"Quebec Road",
    "sg:city":"St Leonards-on-sea",
    "sg:classifiers":[
        {
            "category":"Education",
            "subcategory":"School",
            "type":"Public Place"
        }
    ],
    "sg:phone":"+44 1424 851783",
    "sg:postcode":"TN38 9HH",
    "sg:province":"East Sussex",
    "sg:tags":[
        "local",
        "authority"
    ],
    "wof:name":"Hollington Infants School",
    "wof:placetype":"venue"
},
  "geometry": {"coordinates":[0.547388,50.877766],"type":"Point"}
}