{
  "type": "Feature",
  "properties": {
    "iso:country":"GB",
    "sg:address":"76 Evelyn Road",
    "sg:city":"Dunstable",
    "sg:classifiers":[
        {
            "category":"Retail",
            "subcategory":"Repair Shop",
            "type":"Services"
        },
        {
            "category":"Building & Trades",
            "subcategory":"Construction",
            "type":"Services"
        }
    ],
    "sg:phone":"+44 1582 663896",
    "sg:postcode":"LU5 4NQ",
    "sg:province":"Bedfordshire",
    "sg:tags":[
        "builder",
        "maintenance"
    ],
    "wof:name":"Shorter & Noblet",
    "wof:placetype":"venue"
},
  "geometry": {"coordinates":[-0.492334,51.89349],"type":"Point"}
}