{
  "type": "Feature",
  "properties": {
    "iso:country":"GB",
    "sg:address":"Bury Rd, Ramsey",
    "sg:city":"Huntingdon",
    "sg:classifiers":[
        {
            "category":"Autos & Motor Vehicles",
            "subcategory":"Auto Supplies",
            "type":"Retail Goods"
        }
    ],
    "sg:phone":"+44 1487 812428",
    "sg:postcode":"PE26 1NE",
    "sg:province":"Cambridgeshire",
    "sg:tags":[
        "exhaust",
        "absorber",
        "shock"
    ],
    "wof:name":"Burtons Tyre & Exhaust Centre",
    "wof:placetype":"venue"
},
  "geometry": {"coordinates":[-0.106907,52.448158],"type":"Point"}
}