{
  "type": "Feature",
  "properties": {
    "addr:full":"138 Shakespeare St Coventry Warwickshire CV2 4NG",
    "addr:housenumber":"138",
    "addr:postcode":"cv2 4ng",
    "addr:street":"Shakespeare St",
    "iso:country":"GB",
    "sg:address":"138 Shakespeare St",
    "sg:city":"Coventry",
    "sg:classifiers":[
        {
            "category":"Shopping",
            "subcategory":"Pharmacy",
            "type":"Retail Goods"
        }
    ],
    "sg:phone":"+44 24 7644 0127",
    "sg:postcode":"CV2 4NG",
    "sg:province":"Warwickshire",
    "sg:tags":[
        "medicine",
        "therapy"
    ],
    "wof:name":"Alison Humphey",
    "wof:placetype":"venue"
},
  "geometry": {"coordinates":[-1.4780629873,52.4153060913],"type":"Point"}
}