{
  "type": "Feature",
  "properties": {
    "addr:full":"5 Rowan House, Blind Lane, Bourne End High Wycombe Buckinghamshire HP10 9LE",
    "addr:housenumber":"5",
    "addr:postcode":"hp10 9le",
    "addr:street":"Blind Lane Bourne End",
    "iso:country":"GB",
    "sg:address":"5 Rowan House, Blind Lane, Bourne End",
    "sg:city":"High Wycombe",
    "sg:classifiers":[
        {
            "category":"Building & Trades",
            "subcategory":"Construction",
            "type":"Services"
        }
    ],
    "sg:postcode":"HP10 9LE",
    "sg:province":"Buckinghamshire",
    "sg:tags":[
        "decorator",
        "painter"
    ],
    "wof:name":"P C Wallington",
    "wof:placetype":"venue"
},
  "geometry": {"coordinates":[-0.7027,51.59193],"type":"Point"}
}