{
  "type": "Feature",
  "properties": {
    "addr:full":"Longcroft Trading Ctr, Glasgow Road, Longcroft Bonnybridge Falkirk FK4 1QQ",
    "addr:postcode":"fk4 1qq",
    "addr:street":"Glasgow Road",
    "iso:country":"GB",
    "sg:address":"Longcroft Trading Ctr, Glasgow Road, Longcroft",
    "sg:city":"Bonnybridge",
    "sg:classifiers":[
        {
            "category":"Autos & Motor Vehicles",
            "subcategory":"Auto Supplies",
            "type":"Retail Goods"
        }
    ],
    "sg:phone":"+44 1324 841888",
    "sg:postcode":"FK4 1QQ",
    "sg:province":"Falkirk",
    "sg:tags":[
        "car",
        "audio"
    ],
    "wof:name":"Car Hi-Fi Servicing",
    "wof:placetype":"venue"
},
  "geometry": {"coordinates":[-3.881618,56.002949],"type":"Point"}
}