{
  "type": "Feature",
  "properties": {
    "iso:country":"GB",
    "sg:address":"Apex Project, 128 London Road, Southborough",
    "sg:city":"Tunbridge Wells",
    "sg:classifiers":[
        {
            "category":"Organizations",
            "subcategory":"Non-profit Organization",
            "type":"Services"
        }
    ],
    "sg:phone":"+44 1892 510650",
    "sg:postcode":"TN4 0PL",
    "sg:province":"Kent",
    "sg:tags":[
        "organisation",
        "voluntary",
        "charity"
    ],
    "wof:name":"Barnardo's",
    "wof:placetype":"venue"
},
  "geometry": {"coordinates":[0.26009,51.154549],"type":"Point"}
}