{
  "type": "Feature",
  "properties": {
    "addr:full":"Overcliffe House, 55 New Road Gravesend Kent DA11 0AD",
    "addr:housenumber":"55",
    "addr:postcode":"da11 0ad",
    "addr:street":"New Road",
    "iso:country":"GB",
    "sg:address":"Overcliffe House, 55 New Road",
    "sg:city":"Gravesend",
    "sg:classifiers":[
        {
            "category":"Education",
            "subcategory":"Special Training",
            "type":"Public Place"
        }
    ],
    "sg:phone":"+44 1474 561155",
    "sg:postcode":"DA11 0AD",
    "sg:province":"Kent",
    "sg:tags":[
        "product",
        "centre"
    ],
    "wof:name":"Learn I T",
    "wof:placetype":"venue"
},
  "geometry": {"coordinates":[0.364992,51.442551],"type":"Point"}
}