{
  "type": "Feature",
  "properties": {
    "addr:full":"2 Ash Units, Down End, Lords Meadow Industrial Estate Crediton Devon EX17 1HN",
    "addr:housenumber":"2;units",
    "addr:postcode":"ex17 1hn",
    "addr:street":"Ash;End Lords Meadow Industrial Estate",
    "iso:country":"GB",
    "sg:address":"2 Ash Units, Down End, Lords Meadow Industrial Estate",
    "sg:city":"Crediton",
    "sg:classifiers":[
        {
            "category":"Home & Garden",
            "subcategory":"Home Furnishings",
            "type":"Retail Goods"
        }
    ],
    "sg:postcode":"EX17 1HN",
    "sg:province":"Devon",
    "sg:tags":[
        "furnishers",
        "planner",
        "kitchen"
    ],
    "wof:name":"Crediton Woodcraft",
    "wof:placetype":"venue"
},
  "geometry": {"coordinates":[-3.644358,50.790417],"type":"Point"}
}