{
  "type": "Feature",
  "properties": {
    "iso:country":"GB",
    "sg:address":"Lyncastle Way, Barley Castle La, Appleton Thorn",
    "sg:city":"Warrington",
    "sg:classifiers":[
        {
            "category":"Autos & Motor Vehicles",
            "subcategory":"Automobile Sales",
            "type":"Retail Goods"
        },
        {
            "category":"Shopping",
            "type":"Retail Goods"
        }
    ],
    "sg:postcode":"WA4 4ST",
    "sg:province":"Cheshire",
    "sg:tags":[
        "auction",
        "car",
        "part",
        "accessory"
    ],
    "wof:name":"Warrington Motor Auction Ltd",
    "wof:placetype":"venue"
},
  "geometry": {"coordinates":[-2.53169,53.351395],"type":"Point"}
}