{
  "type": "Feature",
  "properties": {
    "iso:country":"GB",
    "sg:address":"Corolone, The Old Wood, Skellingthorpe",
    "sg:city":"Lincoln",
    "sg:classifiers":[
        {
            "category":"Freight",
            "type":"Transportation"
        }
    ],
    "sg:phone":"+44 1522 500990",
    "sg:postcode":"LN6 5UA",
    "sg:province":"Lincolnshire",
    "sg:tags":[
        "haulage",
        "road"
    ],
    "wof:name":"S G Haulage",
    "wof:placetype":"venue"
},
  "geometry": {"coordinates":[-0.616529,53.236427],"type":"Point"}
}