{
  "type": "Feature",
  "properties": {
    "iso:country":"GB",
    "sg:address":"5 Princeston Court, 55 Felsham Road",
    "sg:city":"London",
    "sg:classifiers":[
        {
            "category":"Organizations",
            "subcategory":"Non-profit Organization",
            "type":"Services"
        }
    ],
    "sg:phone":"+44 20 8789 5555",
    "sg:postcode":"SW15 1AZ",
    "sg:province":"Greater London",
    "sg:tags":[
        "organisation",
        "voluntary",
        "charity"
    ],
    "wof:name":"World Humanity Action Trust",
    "wof:placetype":"venue"
},
  "geometry": {"coordinates":[-0.2165700048,51.4650802612],"type":"Point"}
}