{
  "type": "Feature",
  "properties": {
    "iso:country":"GB",
    "sg:address":"London Road, Binfield",
    "sg:city":"Bracknell",
    "sg:classifiers":[
        {
            "category":"Government",
            "subcategory":"Post Office",
            "type":"Public Place"
        }
    ],
    "sg:phone":"+44 1344 300222",
    "sg:postcode":"RG42 4AA",
    "sg:province":"Berkshire",
    "wof:name":"Popeswood Post Office",
    "wof:placetype":"venue"
},
  "geometry": {"coordinates":[-0.7825639844,51.4204444885],"type":"Point"}
}