{
  "type": "Feature",
  "properties": {
    "addr:full":"Llwyn Fedw Gardens Cardiff Cardiff CF14 4NW",
    "addr:postcode":"cf14 4nw",
    "addr:street":"Llwyn Fedw Gardens",
    "iso:country":"GB",
    "sg:address":"Llwyn Fedw Gardens",
    "sg:city":"Cardiff",
    "sg:classifiers":[
        {
            "category":"Community Center",
            "type":"Public Place"
        }
    ],
    "sg:phone":"+44 29 2052 0306",
    "sg:postcode":"CF14 4NW",
    "sg:province":"Cardiff",
    "sg:tags":[
        "recreation",
        "leisure",
        "centre"
    ],
    "wof:name":"Llwynfedw Gardens Pavilion",
    "wof:placetype":"venue"
},
  "geometry": {"coordinates":[-3.1980938911,51.51379776],"type":"Point"}
}