{
  "type": "Feature",
  "properties": {
    "iso:country":"GB",
    "sg:address":"23 Southfield Road",
    "sg:city":"Glasgow",
    "sg:classifiers":[
        {
            "category":"Personal",
            "type":"Services"
        }
    ],
    "sg:phone":"+44 1236 730770",
    "sg:postcode":"G68 9DQ",
    "sg:province":"East Dunbartonshire",
    "sg:tags":[
        "wedding"
    ],
    "sg:website":"http://www.dvdwed.com",
    "wof:name":"Grahams Video Productions",
    "wof:placetype":"venue"
},
  "geometry": {"coordinates":[-4.0114917755,55.9468955994],"type":"Point"}
}