{
  "type": "Feature",
  "properties": {
    "addr:full":"76 Stanhope Road Greenford Greater London UB6 9EA",
    "addr:housenumber":"76",
    "addr:postcode":"ub6 9ea",
    "addr:street":"Stanhope Road",
    "iso:country":"GB",
    "sg:address":"76 Stanhope Road",
    "sg:city":"Greenford",
    "sg:classifiers":[
        {
            "category":"Building & Trades",
            "subcategory":"Construction",
            "type":"Services"
        }
    ],
    "sg:phone":"+44 20 8575 2890",
    "sg:postcode":"UB6 9EA",
    "sg:province":"Greater London",
    "sg:tags":[
        "builder"
    ],
    "wof:name":"John Morgan",
    "wof:placetype":"venue"
},
  "geometry": {"coordinates":[-0.3536359966,51.5261230469],"type":"Point"}
}