{
  "type": "Feature",
  "properties": {
    "addr:full":"43 High Street Swanage Dorset BH19 2LT",
    "addr:housenumber":"43",
    "addr:postcode":"bh19 2lt",
    "addr:street":"High Street",
    "iso:country":"GB",
    "sg:address":"43 High Street",
    "sg:city":"Swanage",
    "sg:classifiers":[
        {
            "category":"Food & Beverages",
            "subcategory":"Bakery",
            "type":"Retail Goods"
        }
    ],
    "sg:phone":"+44 1929 422360",
    "sg:postcode":"BH19 2LT",
    "sg:province":"Dorset",
    "sg:tags":[
        "shop",
        "baker"
    ],
    "wof:name":"Huon Pine Bakery",
    "wof:placetype":"venue"
},
  "geometry": {"coordinates":[-1.9573379755,50.608127594],"type":"Point"}
}