{
  "type": "Feature",
  "properties": {
    "addr:full":"31 Sturmi Way, Village Farm Industrial Estate, Pyle Bridgend Bridgend CF33 6NU",
    "addr:housenumber":"31;estate",
    "addr:postcode":"cf33 6nu",
    "addr:street":"Sturmi Way Village;Pyle",
    "iso:country":"GB",
    "sg:address":"31 Sturmi Way, Village Farm Industrial Estate, Pyle",
    "sg:city":"Bridgend",
    "sg:classifiers":[
        {
            "category":"Shopping",
            "subcategory":"Computers & Home Electronics",
            "type":"Retail Goods"
        }
    ],
    "sg:phone":"+44 1656 744511",
    "sg:postcode":"CF33 6NU",
    "sg:province":"Bridgend",
    "wof:name":"Jogmaster Ltd.",
    "wof:placetype":"venue"
},
  "geometry": {"coordinates":[-3.686455,51.525845],"type":"Point"}
}