{
  "type": "Feature",
  "properties": {
    "iso:country":"GB",
    "sg:address":"Wilson Road, Huyton",
    "sg:city":"Liverpool",
    "sg:classifiers":[
        {
            "category":"Military Area",
            "subcategory":"Air Force Base",
            "type":"Public Place"
        }
    ],
    "sg:phone":"+44 151 449 0100",
    "sg:postcode":"L36 6AY",
    "sg:province":"Merseyside",
    "sg:tags":[
        "taxi",
        "hire",
        "private"
    ],
    "wof:name":"Brs",
    "wof:placetype":"venue"
},
  "geometry": {"coordinates":[-2.8258390427,53.4069862366],"type":"Point"}
}