{
  "type": "Feature",
  "properties": {
    "iso:country":"GB",
    "sg:address":"Burcott Mill, Wookey Road",
    "sg:city":"Wells",
    "sg:classifiers":[
        {
            "category":"Manufacturing",
            "subcategory":"Metals",
            "type":"Manufacturing & Wholesale Goods"
        }
    ],
    "sg:postcode":"BA5 1NJ",
    "sg:province":"Somerset",
    "sg:tags":[
        "blacksmith",
        "forgemasters"
    ],
    "wof:name":"Phill Raynor",
    "wof:placetype":"venue"
},
  "geometry": {"coordinates":[-2.6827690601,51.207775116],"type":"Point"}
}