{
  "type": "Feature",
  "properties": {
    "addr:full":"23 Acacia Way Sidcup Kent DA15 8WW",
    "addr:housenumber":"23",
    "addr:postcode":"da15 8ww",
    "addr:street":"Acacia Way",
    "iso:country":"GB",
    "sg:address":"23 Acacia Way",
    "sg:city":"Sidcup",
    "sg:classifiers":[
        {
            "category":"Building & Trades",
            "subcategory":"Construction",
            "type":"Services"
        }
    ],
    "sg:postcode":"DA15 8WW",
    "sg:province":"Kent",
    "sg:tags":[
        "glazier"
    ],
    "wof:name":"F W SMITH & SONS",
    "wof:placetype":"venue"
},
  "geometry": {"coordinates":[0.099733,51.442051],"type":"Point"}
}