{
  "type": "Feature",
  "properties": {
    "iso:country":"GB",
    "sg:address":"Gidlow Cemetery, Wigan Road, Standish",
    "sg:city":"Wigan",
    "sg:classifiers":[
        {
            "category":"Building & Trades",
            "subcategory":"Construction",
            "type":"Services"
        }
    ],
    "sg:phone":"+44 1257 472466",
    "sg:postcode":"WN6 0AD",
    "sg:province":"Lancashire",
    "sg:tags":[
        "monumental",
        "mason"
    ],
    "wof:name":"Gidlow Memorials",
    "wof:placetype":"venue"
},
  "geometry": {"coordinates":[-2.663401,53.586021],"type":"Point"}
}