{
  "type": "Feature",
  "properties": {
    "iso:country":"GB",
    "sg:address":"The Great Wakering Health Centre, High St",
    "sg:city":"Southend On Sea",
    "sg:classifiers":[
        {
            "category":"Health Services",
            "subcategory":"Doctor",
            "type":"Services"
        }
    ],
    "sg:phone":"+44 1702 218678",
    "sg:postcode":"SS3 0HX",
    "sg:province":"Essex",
    "sg:tags":[
        "practitioners"
    ],
    "wof:name":"Osborne, C E",
    "wof:placetype":"venue"
},
  "geometry": {"coordinates":[0.79427,51.553791],"type":"Point"}
}