{
  "type": "Feature",
  "properties": {
    "iso:country":"GB",
    "sg:address":"15 High St, Brimington",
    "sg:city":"Chesterfield",
    "sg:classifiers":[
        {
            "category":"Building & Trades",
            "subcategory":"Construction",
            "type":"Services"
        }
    ],
    "sg:postcode":"S43 1DE",
    "sg:province":"Derbyshire",
    "sg:tags":[
        "equipment"
    ],
    "wof:name":"P M Cranes U K",
    "wof:placetype":"venue"
},
  "geometry": {"coordinates":[-1.394329,53.258038],"type":"Point"}
}