{
  "type": "Feature",
  "properties": {
    "iso:country":"GB",
    "sg:address":"Unit 34 Bradley Hall Trading Estate, Bradley Lane, Standish",
    "sg:city":"Wigan",
    "sg:classifiers":[
        {
            "category":"Retail",
            "subcategory":"Auto Repair",
            "type":"Services"
        }
    ],
    "sg:postcode":"WN6 0XQ",
    "sg:province":"Lancashire",
    "sg:tags":[
        "modification",
        "garage"
    ],
    "wof:name":"Motor Mec",
    "wof:placetype":"venue"
},
  "geometry": {"coordinates":[-2.663401,53.586021],"type":"Point"}
}