{
  "type": "Feature",
  "properties": {
    "addr:full":"South Yorkshire Industrial Estate, Whalley Road Barnsley South Yorkshire S75 1HT",
    "addr:housenumber":"estate",
    "addr:postcode":"s75 1ht",
    "addr:street":"South Yorkshire Industrial;Whalley Road;Yorkshire",
    "iso:country":"GB",
    "sg:address":"South Yorkshire Industrial Estate, Whalley Road",
    "sg:city":"Barnsley",
    "sg:classifiers":[
        {
            "category":"Building & Trades",
            "subcategory":"Construction",
            "type":"Services"
        }
    ],
    "sg:phone":"+44 1226 206356",
    "sg:postcode":"S75 1HT",
    "sg:province":"South Yorkshire",
    "sg:tags":[
        "platform",
        "work",
        "scaffolding"
    ],
    "wof:name":"Formscaff (U K) Ltd.",
    "wof:placetype":"venue"
},
  "geometry": {"coordinates":[-1.5199899673,53.5713195801],"type":"Point"}
}