{
  "type": "Feature",
  "properties": {
    "addr:full":"Unit 9, Belmont Industrial Estate Durham Durham DH1 1TN",
    "addr:housenumber":"unit 9",
    "addr:postcode":"dh1 1tn",
    "addr:street":"Belmont Industrial Estate",
    "iso:country":"GB",
    "sg:address":"Unit 9, Belmont Industrial Estate",
    "sg:city":"Durham",
    "sg:classifiers":[
        {
            "category":"Organizations",
            "subcategory":"Professional Association",
            "type":"Services"
        }
    ],
    "sg:phone":"+44 191 386 2232",
    "sg:postcode":"DH1 1TN",
    "sg:province":"Durham",
    "sg:tags":[
        "tech",
        "system",
        "automation"
    ],
    "wof:name":"W H Promation Ltd.",
    "wof:placetype":"venue"
},
  "geometry": {"coordinates":[-1.5309189558,54.7857513428],"type":"Point"}
}