{
  "type": "Feature",
  "properties": {
    "addr:full":"14 Paddock Gardens Upper Norwood Greater London SE19 3SB",
    "addr:housenumber":"14",
    "addr:postcode":"se19 3sb",
    "addr:street":"Paddock Gardens",
    "iso:country":"GB",
    "sg:address":"14 Paddock Gardens",
    "sg:city":"Upper Norwood",
    "sg:classifiers":[
        {
            "category":"Professional",
            "subcategory":"Art Services",
            "type":"Services"
        }
    ],
    "sg:phone":"+44 20 8761 7837",
    "sg:postcode":"SE19 3SB",
    "sg:province":"Greater London",
    "sg:tags":[
        "graphic",
        "designer"
    ],
    "wof:name":"Raphael Design",
    "wof:placetype":"venue"
},
  "geometry": {"coordinates":[-0.082043,51.41943],"type":"Point"}
}