{
  "type": "Feature",
  "properties": {
    "addr:full":"27 Falcon Ave Edinburgh City of Edinburgh EH10 4AL",
    "addr:housenumber":"27",
    "addr:postcode":"eh10 4al",
    "addr:street":"Falcon Ave",
    "iso:country":"GB",
    "sg:address":"27 Falcon Ave",
    "sg:city":"Edinburgh",
    "sg:classifiers":[
        {
            "category":"Building & Trades",
            "subcategory":"Construction",
            "type":"Services"
        }
    ],
    "sg:postcode":"EH10 4AL",
    "sg:province":"City of Edinburgh",
    "sg:tags":[
        "joiner",
        "carpenter"
    ],
    "wof:name":"Alba Joinery",
    "wof:placetype":"venue"
},
  "geometry": {"coordinates":[-3.208626,55.930298],"type":"Point"}
}