{
  "type": "Feature",
  "properties": {
    "iso:country":"GB",
    "sg:address":"Shiv Lodge Medical Centre, 357-359 Dickenson Road",
    "sg:city":"Manchester",
    "sg:classifiers":[
        {
            "category":"Health Services",
            "subcategory":"Doctor",
            "type":"Services"
        }
    ],
    "sg:phone":"+44 161 224 6522",
    "sg:postcode":"M13 0WQ",
    "sg:province":"Greater Manchester",
    "sg:tags":[
        "practitioners"
    ],
    "wof:name":"P GULATI",
    "wof:placetype":"venue"
},
  "geometry": {"coordinates":[-2.20106,53.456089],"type":"Point"}
}