{
  "type": "Feature",
  "properties": {
    "addr:full":"278 Harrison Rd Leicester Leicestershire LE4 6QL",
    "addr:housenumber":"278",
    "addr:postcode":"le4 6ql",
    "addr:street":"Harrison Rd",
    "iso:country":"GB",
    "sg:address":"278 Harrison Rd",
    "sg:city":"Leicester",
    "sg:classifiers":[
        {
            "category":"Coffee & Tea",
            "type":"Food & Drink"
        }
    ],
    "sg:phone":"+44 116 266 4020",
    "sg:postcode":"LE4 6QL",
    "sg:province":"Leicestershire",
    "wof:name":"Trio Tea Co",
    "wof:placetype":"venue"
},
  "geometry": {"coordinates":[-1.114471,52.654881],"type":"Point"}
}