{
  "type": "Feature",
  "properties": {
    "addr:full":"339 Denby Dale Road, Durkar Wakefield West Yorkshire WF4 3BB",
    "addr:housenumber":"339",
    "addr:postcode":"wf4 3bb",
    "addr:street":"Denby Dale Road;West",
    "iso:country":"GB",
    "sg:address":"339 Denby Dale Road, Durkar",
    "sg:city":"Wakefield",
    "sg:classifiers":[
        {
            "category":"Autos & Motor Vehicles",
            "subcategory":"Automobile Sales",
            "type":"Retail Goods"
        }
    ],
    "sg:phone":"+44 1924 290390",
    "sg:postcode":"WF4 3BB",
    "sg:province":"West Yorkshire",
    "sg:tags":[
        "car"
    ],
    "wof:name":"Harratt Nissan",
    "wof:placetype":"venue"
},
  "geometry": {"coordinates":[-1.51805,53.653519],"type":"Point"}
}