{
  "type": "Feature",
  "properties": {
    "addr:full":"17 Middle Lane, Grenoside Sheffield South Yorkshire S35 8PS",
    "addr:housenumber":"17",
    "addr:postcode":"s35 8ps",
    "addr:street":"Middle Lane",
    "iso:country":"GB",
    "sg:address":"17 Middle Lane, Grenoside",
    "sg:city":"Sheffield",
    "sg:classifiers":[
        {
            "category":"Professional",
            "type":"Services"
        }
    ],
    "sg:phone":"+44 114 240 0098",
    "sg:postcode":"S35 8PS",
    "sg:province":"South Yorkshire",
    "sg:tags":[
        "entertainer"
    ],
    "wof:name":"Barn Dance Band",
    "wof:placetype":"venue"
},
  "geometry": {"coordinates":[-1.506429,53.442188],"type":"Point"}
}