{
  "type": "Feature",
  "properties": {
    "iso:country":"GB",
    "sg:address":"Hill Street",
    "sg:city":"Wrexham",
    "sg:classifiers":[
        {
            "category":"Retail",
            "subcategory":"Auto Repair",
            "type":"Services"
        },
        {
            "category":"Sports & Exercise",
            "subcategory":"Tennis Court",
            "type":"Entertainment"
        }
    ],
    "sg:phone":"+44 1978 840064",
    "sg:postcode":"LL14 1LN",
    "sg:province":"Wrexham",
    "sg:tags":[
        "breakdown",
        "garage",
        "modification",
        "recovery"
    ],
    "wof:name":"P & G Motors",
    "wof:placetype":"venue"
},
  "geometry": {"coordinates":[-3.0502340794,53.0096282959],"type":"Point"}
}