{
  "type": "Feature",
  "properties": {
    "addr:full":"Old House, Little Maplestead Road Halstead Essex CO9 3AR",
    "addr:postcode":"co9 3ar",
    "addr:street":"Little Maplestead Road",
    "iso:country":"GB",
    "sg:address":"Old House, Little Maplestead Road",
    "sg:city":"Halstead",
    "sg:classifiers":[
        {
            "category":"Coffee & Tea",
            "type":"Food & Drink"
        }
    ],
    "sg:phone":"+44 1787 463161",
    "sg:postcode":"CO9 3AR",
    "sg:province":"Essex",
    "wof:name":"Coffilta Coffee Services",
    "wof:placetype":"venue"
},
  "geometry": {"coordinates":[0.635825,51.943996],"type":"Point"}
}