{
  "type": "Feature",
  "properties": {
    "addr:full":"Broad St Hereford Herefordshire HR4 9BG",
    "addr:postcode":"hr4 9bg",
    "addr:street":"Broad St",
    "iso:country":"GB",
    "sg:address":"Broad St",
    "sg:city":"Hereford",
    "sg:classifiers":[
        {
            "category":"Travel",
            "subcategory":"Hotels & Motels",
            "type":"Entertainment"
        }
    ],
    "sg:phone":"+44 1432 272506",
    "sg:postcode":"HR4 9BG",
    "sg:province":"Herefordshire",
    "wof:name":"Compass Entertainments Ltd",
    "wof:placetype":"venue"
},
  "geometry": {"coordinates":[-2.717599,52.05629],"type":"Point"}
}