{
  "type": "Feature",
  "properties": {
    "iso:country":"GB",
    "sg:address":"6 Castletown",
    "sg:city":"Portland",
    "sg:classifiers":[
        {
            "category":"Professional",
            "subcategory":"Engineering",
            "type":"Services"
        }
    ],
    "sg:phone":"+44 1305 826384",
    "sg:postcode":"DT5 1BD",
    "sg:province":"Dorset",
    "sg:tags":[
        "electronic",
        "engineer"
    ],
    "wof:name":"Albion Robotics Ltd.",
    "wof:placetype":"venue"
},
  "geometry": {"coordinates":[-2.441747,50.568024],"type":"Point"}
}