{
  "type": "Feature",
  "properties": {
    "addr:full":"4 Ewellhurst Road Ilford Essex IG5 0PE",
    "addr:housenumber":"4",
    "addr:postcode":"ig5 0pe",
    "addr:street":"Ewellhurst Road",
    "iso:country":"GB",
    "sg:address":"4 Ewellhurst Road",
    "sg:city":"Ilford",
    "sg:classifiers":[
        {
            "category":"Building & Trades",
            "subcategory":"Construction",
            "type":"Services"
        }
    ],
    "sg:phone":"+44 20 8551 5627",
    "sg:postcode":"IG5 0PE",
    "sg:province":"Essex",
    "sg:tags":[
        "builder"
    ],
    "wof:name":"K J V Contractors",
    "wof:placetype":"venue"
},
  "geometry": {"coordinates":[0.053262,51.592701],"type":"Point"}
}