{
  "type": "Feature",
  "properties": {
    "addr:full":"2 Northolme Road London Greater London N5 2UZ",
    "addr:housenumber":"2",
    "addr:postcode":"n5 2uz",
    "addr:street":"Northolme Road",
    "iso:country":"GB",
    "sg:address":"2 Northolme Road",
    "sg:city":"London",
    "sg:classifiers":[
        {
            "category":"Professional",
            "subcategory":"Management & Consulting",
            "type":"Services"
        }
    ],
    "sg:phone":"+44 20 7690 5812",
    "sg:postcode":"N5 2UZ",
    "sg:province":"Greater London",
    "sg:tags":[
        "consultant",
        "business"
    ],
    "wof:name":"Adrian Dicks Consulting Ltd.",
    "wof:placetype":"venue"
},
  "geometry": {"coordinates":[-0.0976380035,51.5570602417],"type":"Point"}
}