{
  "type": "Feature",
  "properties": {
    "iso:country":"GB",
    "sg:address":"3 Matthews Villas, Old House Lane Roydon",
    "sg:city":"Harlow",
    "sg:classifiers":[
        {
            "category":"Building & Trades",
            "subcategory":"Construction",
            "type":"Services"
        }
    ],
    "sg:postcode":"CM19 5DN",
    "sg:province":"Essex",
    "sg:tags":[
        "builder"
    ],
    "wof:name":"P.B. Plumbing Ltd",
    "wof:placetype":"venue"
},
  "geometry": {"coordinates":[0.038872,51.769241],"type":"Point"}
}