{
  "type": "Feature",
  "properties": {
    "iso:country":"GB",
    "sg:address":"28/30 Landsdown Road",
    "sg:city":"Bude",
    "sg:classifiers":[
        {
            "category":"Shopping",
            "subcategory":"Antiques",
            "type":"Retail Goods"
        }
    ],
    "sg:postcode":"EX23 8BN",
    "sg:province":"Cornwall",
    "wof:name":"The Bric A Brac Shop",
    "wof:placetype":"venue"
},
  "geometry": {"coordinates":[-4.543665,50.829849],"type":"Point"}
}