{
  "type": "Feature",
  "properties": {
    "iso:country":"GB",
    "sg:address":"Jet Garage, 122 Queens Drive",
    "sg:city":"Bedford",
    "sg:classifiers":[
        {
            "category":"Autos & Motor Vehicles",
            "subcategory":"Fuel & Gas Station",
            "type":"Retail Goods"
        }
    ],
    "sg:phone":"+44 1234 349802",
    "sg:postcode":"MK41 9JF",
    "sg:province":"Bedfordshire",
    "sg:tags":[
        "petrol",
        "filling"
    ],
    "wof:name":"Putnoe Service Station",
    "wof:placetype":"venue"
},
  "geometry": {"coordinates":[-0.43868,52.148479],"type":"Point"}
}