{
  "type": "Feature",
  "properties": {
    "iso:country":"GB",
    "sg:address":"40 Stockton",
    "sg:city":"Warminster",
    "sg:classifiers":[
        {
            "category":"Shopping",
            "subcategory":"Gifts & Souvenirs",
            "type":"Retail Goods"
        }
    ],
    "sg:phone":"+44 1985 850408",
    "sg:postcode":"BA12 0SQ",
    "sg:province":"Somerset",
    "sg:tags":[
        "giftware"
    ],
    "wof:name":"Daphne Pain",
    "wof:placetype":"venue"
},
  "geometry": {"coordinates":[-2.0373570919,51.1495819092],"type":"Point"}
}