{
  "type": "Feature",
  "properties": {
    "addr:full":"Lowhill Farm, Portsmouth Rd, Fishers Pond Eastleigh Hampshire SO50 7HF",
    "addr:postcode":"so50 7hf",
    "addr:street":"Portsmouth Rd;Pond",
    "iso:country":"GB",
    "sg:address":"Lowhill Farm, Portsmouth Rd, Fishers Pond",
    "sg:city":"Eastleigh",
    "sg:classifiers":[
        {
            "category":"Government",
            "subcategory":"Department Of Motor Vehicles",
            "type":"Public Place"
        }
    ],
    "sg:phone":"+44 1962 777863",
    "sg:postcode":"SO50 7HF",
    "sg:province":"Hampshire",
    "sg:tags":[
        "drawn",
        "horse",
        "hire"
    ],
    "wof:name":"Grayswood Carriages",
    "wof:placetype":"venue"
},
  "geometry": {"coordinates":[-1.3058160543,50.984413147],"type":"Point"}
}