{
  "type": "Feature",
  "properties": {
    "iso:country":"GB",
    "sg:address":"Po Box 5352",
    "sg:city":"Clacton-on-sea",
    "sg:classifiers":[
        {
            "category":"Building & Trades",
            "subcategory":"Construction",
            "type":"Services"
        }
    ],
    "sg:postcode":"CO16 9NR",
    "sg:province":"Essex",
    "sg:tags":[
        "contractor",
        "pool",
        "swimming"
    ],
    "wof:name":"Eatonfield Ltd.",
    "wof:placetype":"venue"
},
  "geometry": {"coordinates":[1.1326099634,51.8339996338],"type":"Point"}
}