{
  "type": "Feature",
  "properties": {
    "iso:country":"GB",
    "sg:address":"Brookside Park, Hawley Lane",
    "sg:city":"Farnborough",
    "sg:classifiers":[
        {
            "category":"Manufacturing",
            "subcategory":"Buildings",
            "type":"Manufacturing & Wholesale Goods"
        },
        {
            "category":"Train Station",
            "subcategory":"Rail",
            "type":"Transportation"
        }
    ],
    "sg:phone":"+44 1252 543996",
    "sg:postcode":"GU14 9AZ",
    "sg:province":"Hampshire",
    "sg:tags":[
        "mobile",
        "caravan",
        "home"
    ],
    "wof:name":"Farnborough Caravan Sites Ltd",
    "wof:placetype":"venue"
},
  "geometry": {"coordinates":[-0.755569,51.293724],"type":"Point"}
}