{
  "type": "Feature",
  "properties": {
    "addr:full":"St Brides High School, Platthorn Drive, East Kilbride Glasgow South Lanarkshire G74 1NL",
    "addr:postcode":"g74 1nl",
    "addr:street":"St;Platthorn Drive",
    "iso:country":"GB",
    "sg:address":"St Brides High School, Platthorn Drive, East Kilbride",
    "sg:city":"Glasgow",
    "sg:classifiers":[
        {
            "category":"Professional",
            "subcategory":"Employment Agencies",
            "type":"Services"
        },
        {
            "category":"Government",
            "subcategory":"Office",
            "type":"Public Place"
        }
    ],
    "sg:phone":"+44 1355 225478",
    "sg:postcode":"G74 1NL",
    "sg:province":"South Lanarkshire",
    "sg:tags":[
        "career",
        "guidance",
        "local"
    ],
    "wof:name":"East Kilbride Careers Centre",
    "wof:placetype":"venue"
},
  "geometry": {"coordinates":[-4.185876,55.767391],"type":"Point"}
}