{
  "type": "Feature",
  "properties": {
    "addr:full":"178 Broad Street Birmingham West Midlands B15 1DX",
    "addr:housenumber":"178",
    "addr:postcode":"b15 1dx",
    "addr:street":"Broad Street",
    "iso:country":"GB",
    "sg:address":"178 Broad Street",
    "sg:city":"Birmingham",
    "sg:classifiers":[
        {
            "category":"Restaurant",
            "type":"Food & Drink"
        }
    ],
    "sg:postcode":"B15 1DX",
    "sg:province":"West Midlands",
    "sg:tags":[
        "oriental"
    ],
    "wof:name":"Mai Thai",
    "wof:placetype":"venue"
},
  "geometry": {"coordinates":[-1.915975,52.474228],"type":"Point"}
}