{
  "type": "Feature",
  "properties": {
    "addr:full":"The Old Stocks High Mickley Stocksfield Northumberland NE43 7LU",
    "addr:postcode":"ne43 7lu",
    "addr:street":"Mickley",
    "iso:country":"GB",
    "sg:address":"The Old Stocks High Mickley",
    "sg:city":"Stocksfield",
    "sg:classifiers":[
        {
            "category":"Health Services",
            "subcategory":"Clinic",
            "type":"Services"
        }
    ],
    "sg:phone":"+44 1661 842085",
    "sg:postcode":"NE43 7LU",
    "sg:province":"Northumberland",
    "sg:tags":[
        "aromatherapy"
    ],
    "wof:name":"Massage Matters",
    "wof:placetype":"venue"
},
  "geometry": {"coordinates":[-1.9158940315,54.946685791],"type":"Point"}
}