{
  "type": "Feature",
  "properties": {
    "addr:full":"38 Park Ridings, Hornsey London Greater London N8 0LD",
    "addr:housenumber":"38",
    "addr:postcode":"n8 0ld",
    "addr:street":"Park Ridings",
    "iso:country":"GB",
    "sg:address":"38 Park Ridings, Hornsey",
    "sg:city":"London",
    "sg:classifiers":[
        {
            "category":"Home & Garden",
            "subcategory":"Carpets & Floor Coverings",
            "type":"Retail Goods"
        }
    ],
    "sg:postcode":"N8 0LD",
    "sg:province":"Greater London",
    "sg:tags":[
        "cleaner",
        "upholstery"
    ],
    "wof:name":"North London's Carpet & Upholstery Cleaning Specialists",
    "wof:placetype":"venue"
},
  "geometry": {"coordinates":[-0.1094349995,51.5926780701],"type":"Point"}
}