{
  "type": "Feature",
  "properties": {
    "iso:country":"GB",
    "sg:address":"Leicester Road, Groby",
    "sg:city":"Leicester",
    "sg:classifiers":[
        {
            "category":"Education",
            "subcategory":"Library",
            "type":"Public Place"
        }
    ],
    "sg:phone":"+44 116 287 6949",
    "sg:postcode":"LE6 0DQ",
    "sg:province":"Leicestershire",
    "sg:tags":[
        "book"
    ],
    "wof:name":"Groby Library",
    "wof:placetype":"venue"
},
  "geometry": {"coordinates":[-1.2055850029,52.6606521606],"type":"Point"}
}