{
  "type": "Feature",
  "properties": {
    "addr:full":"Burgen House, South View Jarrow Tyne and Wear NE32 5JP",
    "addr:postcode":"ne32 5jp",
    "addr:street":"South View",
    "iso:country":"GB",
    "sg:address":"Burgen House, South View",
    "sg:city":"Jarrow",
    "sg:classifiers":[
        {
            "category":"Professional",
            "subcategory":"Lawyer & Legal Services",
            "type":"Services"
        }
    ],
    "sg:postcode":"NE32 5JP",
    "sg:province":"Tyne and Wear",
    "wof:name":"Heywood & Black",
    "wof:placetype":"venue"
},
  "geometry": {"coordinates":[-1.496679,54.977016],"type":"Point"}
}