{
  "type": "Feature",
  "properties": {
    "addr:full":"12 Marine Pl Seaton Devon EX12 2QL",
    "addr:housenumber":"12",
    "addr:postcode":"ex12 2ql",
    "addr:street":"Marine Pl",
    "iso:country":"GB",
    "sg:address":"12 Marine Pl",
    "sg:city":"Seaton",
    "sg:classifiers":[
        {
            "category":"Food & Beverages",
            "subcategory":"Meat & Fish",
            "type":"Retail Goods"
        }
    ],
    "sg:phone":"+44 1297 23912",
    "sg:postcode":"EX12 2QL",
    "sg:province":"Devon",
    "sg:tags":[
        "butcher"
    ],
    "wof:name":"K Clarke Butchers",
    "wof:placetype":"venue"
},
  "geometry": {"coordinates":[-3.0709590912,50.7044296265],"type":"Point"}
}