{
  "type": "Feature",
  "properties": {
    "iso:country":"GB",
    "sg:address":"91 Houndiscombe Road",
    "sg:city":"Plymouth",
    "sg:classifiers":[
        {
            "category":"Professional",
            "subcategory":"Accounting & Tax Preparation",
            "type":"Services"
        }
    ],
    "sg:phone":"+44 1752 260606",
    "sg:postcode":"PL4 6HB",
    "sg:province":"Devon",
    "sg:tags":[
        "payroll"
    ],
    "wof:name":"Mark N Smith",
    "wof:placetype":"venue"
},
  "geometry": {"coordinates":[-4.134704,50.38028],"type":"Point"}
}