{
  "type": "Feature",
  "properties": {
    "addr:full":"312 Padcaster Road York North Yorkshire YO24 1GS",
    "addr:housenumber":"312",
    "addr:postcode":"yo24 1gs",
    "addr:street":"Padcaster Road",
    "iso:country":"GB",
    "sg:address":"312 Padcaster Road",
    "sg:city":"York",
    "sg:classifiers":[
        {
            "category":"Professional",
            "subcategory":"Management & Consulting",
            "type":"Services"
        }
    ],
    "sg:phone":"+44 1904 702205",
    "sg:postcode":"YO24 1GS",
    "sg:province":"North Yorkshire",
    "sg:tags":[
        "marketing",
        "consultant"
    ],
    "wof:name":"England's North Country",
    "wof:placetype":"venue"
},
  "geometry": {"coordinates":[-1.10476,53.94302],"type":"Point"}
}