{
  "type": "Feature",
  "properties": {
    "iso:country":"GB",
    "sg:address":"32 High Street",
    "sg:city":"Anstruther",
    "sg:classifiers":[
        {
            "category":"Personal",
            "subcategory":"Beauty Salon",
            "type":"Services"
        }
    ],
    "sg:postcode":"KY10 2LA",
    "sg:province":"Fife",
    "sg:tags":[
        "unisex",
        "hairdresser"
    ],
    "wof:name":"Jaba",
    "wof:placetype":"venue"
},
  "geometry": {"coordinates":[-2.701419,56.223541],"type":"Point"}
}