{
  "type": "Feature",
  "properties": {
    "addr:full":"15 Vale Street Denbigh Conwy LL16 3AD",
    "addr:housenumber":"15",
    "addr:postcode":"ll16 3ad",
    "addr:street":"Vale Street",
    "iso:country":"GB",
    "sg:address":"15 Vale Street",
    "sg:city":"Denbigh",
    "sg:classifiers":[
        {
            "category":"Travel",
            "subcategory":"Travel Agent",
            "type":"Entertainment"
        }
    ],
    "sg:postcode":"LL16 3AD",
    "sg:province":"Conwy",
    "wof:name":"Ariel Travel",
    "wof:placetype":"venue"
},
  "geometry": {"coordinates":[-3.4140191078,53.1858787537],"type":"Point"}
}