{
  "type": "Feature",
  "properties": {
    "addr:full":"Unit 18, 12 Horn Lane London Greater London SE10 0RT",
    "addr:housenumber":"unit;12",
    "addr:postcode":"se10 0rt",
    "addr:street":"Horn Lane",
    "iso:country":"GB",
    "sg:address":"Unit 18, 12 Horn Lane",
    "sg:city":"London",
    "sg:classifiers":[
        {
            "category":"Social Services",
            "subcategory":"Adult Care",
            "type":"Services"
        }
    ],
    "sg:phone":"+44 20 8293 6422",
    "sg:postcode":"SE10 0RT",
    "sg:province":"Greater London",
    "sg:tags":[
        "lubrication"
    ],
    "wof:name":"Meterlube Systems Ltd.",
    "wof:placetype":"venue"
},
  "geometry": {"coordinates":[0.0184199996,51.488910675],"type":"Point"}
}