{
  "type": "Feature",
  "properties": {
    "addr:full":"35 Highfield Road Felixstowe Suffolk IP11 7BZ",
    "addr:housenumber":"35",
    "addr:postcode":"ip11 7bz",
    "addr:street":"Highfield Road",
    "iso:country":"GB",
    "sg:address":"35 Highfield Road",
    "sg:city":"Felixstowe",
    "sg:classifiers":[
        {
            "category":"Personal",
            "type":"Services"
        },
        {
            "category":"Professional",
            "subcategory":"Art Services",
            "type":"Services"
        }
    ],
    "sg:phone":"+44 1394 279084",
    "sg:postcode":"IP11 7BZ",
    "sg:province":"Suffolk",
    "sg:tags":[
        "interior",
        "designer",
        "wedding"
    ],
    "wof:name":"Ramsey-Wherrett Design",
    "wof:placetype":"venue"
},
  "geometry": {"coordinates":[1.350722,51.962971],"type":"Point"}
}