{
  "type": "Feature",
  "properties": {
    "addr:full":"22 Mountain Ash Road Dorchester Dorset DT1 2PB",
    "addr:housenumber":"22",
    "addr:postcode":"dt1 2pb",
    "addr:street":"Mountain Ash Road",
    "iso:country":"GB",
    "sg:address":"22 Mountain Ash Road",
    "sg:city":"Dorchester",
    "sg:classifiers":[
        {
            "category":"Building & Trades",
            "subcategory":"Plumbing",
            "type":"Services"
        }
    ],
    "sg:phone":"+44 1305 260897",
    "sg:postcode":"DT1 2PB",
    "sg:province":"Dorset",
    "sg:tags":[
        "central",
        "heating"
    ],
    "wof:name":"Will Gardiner Gas Services",
    "wof:placetype":"venue"
},
  "geometry": {"coordinates":[-2.44808,50.714661],"type":"Point"}
}