{
  "type": "Feature",
  "properties": {
    "addr:full":"Unit 2a Heather Rd Skegness Lincolnshire PE25 3SR",
    "addr:housenumber":"unit 2a",
    "addr:postcode":"pe25 3sr",
    "addr:street":"Heather Rd",
    "iso:country":"GB",
    "sg:address":"Unit 2a Heather Rd",
    "sg:city":"Skegness",
    "sg:classifiers":[
        {
            "category":"Home & Garden",
            "subcategory":"Building Materials",
            "type":"Retail Goods"
        }
    ],
    "sg:phone":"+44 1754 760606",
    "sg:postcode":"PE25 3SR",
    "sg:province":"Lincolnshire",
    "sg:tags":[
        "window",
        "frame"
    ],
    "wof:name":"Estate 2000",
    "wof:placetype":"venue"
},
  "geometry": {"coordinates":[0.32601,53.140652],"type":"Point"}
}