{
  "type": "Feature",
  "properties": {
    "iso:country":"GB",
    "sg:address":"Unit 3 Tower Enterprise Park, Great George Street",
    "sg:city":"Wigan",
    "sg:classifiers":[
        {
            "category":"Building & Trades",
            "subcategory":"Construction",
            "type":"Services"
        }
    ],
    "sg:postcode":"WN3 4DP",
    "sg:province":"Lancashire",
    "sg:tags":[
        "valve"
    ],
    "wof:name":"Whittle Valve Repairs Ltd.",
    "wof:placetype":"venue"
},
  "geometry": {"coordinates":[-2.63784,53.544861],"type":"Point"}
}