{
  "type": "Feature",
  "properties": {
    "iso:country":"GB",
    "sg:address":"177 Chester Road",
    "sg:city":"Sunderland",
    "sg:classifiers":[
        {
            "category":"Shopping",
            "subcategory":"Baby Store",
            "type":"Retail Goods"
        }
    ],
    "sg:postcode":"SR4 7JA",
    "sg:province":"Tyne and Wear",
    "sg:tags":[
        "babywear",
        "childrens"
    ],
    "wof:name":"Windmill Childrens Wear",
    "wof:placetype":"venue"
},
  "geometry": {"coordinates":[-1.404802,54.901459],"type":"Point"}
}