{
  "type": "Feature",
  "properties": {
    "iso:country":"GB",
    "sg:address":"Canada Drive",
    "sg:city":"Redhill",
    "sg:classifiers":[
        {
            "category":"Health Services",
            "subcategory":"Hospital",
            "type":"Services"
        }
    ],
    "sg:phone":"+44 1737 277277",
    "sg:postcode":"RH1 5BY",
    "sg:province":"Surrey",
    "wof:name":"Bupa Redwood Hospital",
    "wof:placetype":"venue"
},
  "geometry": {"coordinates":[-0.16144,51.217415],"type":"Point"}
}