{
  "type": "Feature",
  "properties": {
    "addr:full":"Mole End, Hermitage Road Thatcham Berkshire RG18 9JN",
    "addr:postcode":"rg18 9jn",
    "addr:street":"Hermitage Road",
    "iso:country":"GB",
    "sg:address":"Mole End, Hermitage Road",
    "sg:city":"Thatcham",
    "sg:classifiers":[
        {
            "category":"Shopping",
            "subcategory":"Gifts & Souvenirs",
            "type":"Retail Goods"
        }
    ],
    "sg:postcode":"RG18 9JN",
    "sg:province":"Berkshire",
    "sg:tags":[
        "window",
        "leaded"
    ],
    "wof:name":"C J L Designs",
    "wof:placetype":"venue"
},
  "geometry": {"coordinates":[-1.271127,51.454067],"type":"Point"}
}