{
  "type": "Feature",
  "properties": {
    "addr:full":"Constable Croft, New Road, Hixon Stafford Staffordshire ST18 0PE",
    "addr:postcode":"st18 0pe",
    "addr:street":"Constable Croft New Road",
    "iso:country":"GB",
    "sg:address":"Constable Croft, New Road, Hixon",
    "sg:city":"Stafford",
    "sg:classifiers":[
        {
            "category":"Utilities",
            "subcategory":"Fuel Oil & Lpg",
            "type":"Services"
        }
    ],
    "sg:postcode":"ST18 0PE",
    "sg:province":"Staffordshire",
    "sg:tags":[
        "peat",
        "firewood",
        "logs"
    ],
    "wof:name":"Charles Raby Timber",
    "wof:placetype":"venue"
},
  "geometry": {"coordinates":[-1.999984026,52.8308486938],"type":"Point"}
}