{
  "type": "Feature",
  "properties": {
    "iso:country":"GB",
    "sg:address":"90 High Street, Selsey",
    "sg:city":"Chichester",
    "sg:classifiers":[
        {
            "category":"Health Services",
            "subcategory":"Optometrist",
            "type":"Services"
        },
        {
            "category":"Shopping",
            "subcategory":"Optician",
            "type":"Retail Goods"
        }
    ],
    "sg:phone":"+44 1243 605222",
    "sg:postcode":"PO20 0QG",
    "sg:province":"West Sussex",
    "sg:tags":[
        "ophthalmic"
    ],
    "wof:name":"Selsey Opticians",
    "wof:placetype":"venue"
},
  "geometry": {"coordinates":[-0.7910810113,50.7337875366],"type":"Point"}
}