{
  "type": "Feature",
  "properties": {
    "addr:full":"Whinney Hill Farm Choppington Northumberland NE62 5RE",
    "addr:housenumber":"choppington",
    "addr:postcode":"ne62 5re",
    "addr:street":"Whinney Hill;Northumberland",
    "iso:country":"GB",
    "sg:address":"Whinney Hill Farm",
    "sg:city":"Choppington",
    "sg:classifiers":[
        {
            "category":"Farming",
            "subcategory":"Livestock Farm",
            "type":"Manufacturing & Wholesale Goods"
        }
    ],
    "sg:phone":"+44 1670 826311",
    "sg:postcode":"NE62 5RE",
    "sg:province":"Northumberland",
    "sg:tags":[
        "others"
    ],
    "wof:name":"R Holmes & Son",
    "wof:placetype":"venue"
},
  "geometry": {"coordinates":[-1.600085,55.146175],"type":"Point"}
}