{
  "type": "Feature",
  "properties": {
    "addr:full":"Towergate House, St Edwards Court, London Road Romford Essex RM7 9QD",
    "addr:postcode":"rm7 9qd",
    "addr:street":"St Edwards Court London Road",
    "iso:country":"GB",
    "sg:address":"Towergate House, St Edwards Court, London Road",
    "sg:city":"Romford",
    "sg:classifiers":[
        {
            "category":"Insurance",
            "subcategory":"Insurance Agent",
            "type":"Services"
        }
    ],
    "sg:phone":"+44 1708 777710",
    "sg:postcode":"RM7 9QD",
    "sg:province":"Essex",
    "wof:name":"Towergate Strovers Ltd.",
    "wof:placetype":"venue"
},
  "geometry": {"coordinates":[0.175498,51.575237],"type":"Point"}
}