{
  "type": "Feature",
  "properties": {
    "addr:full":"49a St Peters Road Reading Berkshire RG6 1NT",
    "addr:housenumber":"49a",
    "addr:postcode":"rg6 1nt",
    "addr:street":"St Peters Road",
    "iso:country":"GB",
    "sg:address":"49a St Peters Road",
    "sg:city":"Reading",
    "sg:classifiers":[
        {
            "category":"Professional",
            "subcategory":"Art Services",
            "type":"Services"
        },
        {
            "category":"Building & Trades",
            "subcategory":"Construction",
            "type":"Services"
        }
    ],
    "sg:phone":"+44 118 935 1895",
    "sg:postcode":"RG6 1NT",
    "sg:province":"Berkshire",
    "sg:tags":[
        "decorator",
        "painter"
    ],
    "wof:name":"L S M DECORATORS LTD",
    "wof:placetype":"venue"
},
  "geometry": {"coordinates":[-0.9342070222,51.4470748901],"type":"Point"}
}