{
  "type": "Feature",
  "properties": {
    "addr:full":"Unit A Bridal Road Bootle Merseyside L30 4UG",
    "addr:housenumber":"unit a",
    "addr:postcode":"l30 4ug",
    "addr:street":"Bridal Road",
    "iso:country":"GB",
    "sg:address":"Unit A Bridal Road",
    "sg:city":"Bootle",
    "sg:classifiers":[
        {
            "category":"Building & Trades",
            "subcategory":"Construction",
            "type":"Services"
        },
        {
            "category":"Manufacturing",
            "subcategory":"Lumber",
            "type":"Manufacturing & Wholesale Goods"
        }
    ],
    "sg:phone":"+44 151 530 1800",
    "sg:postcode":"L30 4UG",
    "sg:province":"Merseyside",
    "sg:tags":[
        "agent",
        "merchants",
        "importer",
        "preservation",
        "timber"
    ],
    "sg:website":"http://www.haydock.co.uk",
    "wof:name":"Roger Haydock & Co. Ltd.",
    "wof:placetype":"venue"
},
  "geometry": {"coordinates":[-2.965569973,53.4716300964],"type":"Point"}
}