{
  "type": "Feature",
  "properties": {
    "addr:full":"168 Newbridge Road Bath Bath and North East Somerset BA1 3LE",
    "addr:housenumber":"168",
    "addr:postcode":"ba1 3le",
    "addr:street":"Newbridge Road",
    "iso:country":"GB",
    "sg:address":"168 Newbridge Road",
    "sg:city":"Bath",
    "sg:classifiers":[
        {
            "category":"Social Services",
            "subcategory":"Retirement Home",
            "type":"Services"
        }
    ],
    "sg:postcode":"BA1 3LE",
    "sg:province":"Bath and North East Somerset",
    "sg:tags":[
        "residential",
        "care"
    ],
    "wof:name":"Brynmawr Residential Home",
    "wof:placetype":"venue"
},
  "geometry": {"coordinates":[-2.3983869553,51.3867607117],"type":"Point"}
}