{
  "type": "Feature",
  "properties": {
    "addr:full":"St Pauls Church Hall, Regent Street Ryde Isle of Wight PO33 2RR",
    "addr:postcode":"isle;po33 2rr",
    "addr:street":"Regent Street",
    "iso:country":"GB",
    "sg:address":"St Pauls Church Hall, Regent Street",
    "sg:city":"Ryde",
    "sg:classifiers":[
        {
            "category":"Farming",
            "subcategory":"Nursery",
            "type":"Manufacturing & Wholesale Goods"
        }
    ],
    "sg:postcode":"PO33 2RR",
    "sg:province":"Isle of Wight",
    "sg:tags":[
        "creche"
    ],
    "wof:name":"Shanklin Pre-School Nursery",
    "wof:placetype":"venue"
},
  "geometry": {"coordinates":[-1.1686660051,50.7275657654],"type":"Point"}
}