{
  "type": "Feature",
  "properties": {
    "iso:country":"GB",
    "sg:address":"Cassrock, Belmangate",
    "sg:city":"Guisborough",
    "sg:classifiers":[
        {
            "category":"Real Estate",
            "subcategory":"Architect",
            "type":"Services"
        }
    ],
    "sg:phone":"+44 1287 631639",
    "sg:postcode":"TS14 7BD",
    "sg:province":"North Yorkshire",
    "sg:tags":[
        "architectural"
    ],
    "wof:name":"Brian Rigby Building Services",
    "wof:placetype":"venue"
},
  "geometry": {"coordinates":[-1.049718976,54.5340690613],"type":"Point"}
}