{
  "type": "Feature",
  "properties": {
    "iso:country":"GB",
    "sg:address":"51 Fieldside, Thorne",
    "sg:city":"Doncaster",
    "sg:classifiers":[
        {
            "category":"Professional",
            "subcategory":"Art Services",
            "type":"Services"
        }
    ],
    "sg:postcode":"DN8 4AD",
    "sg:province":"East Riding of Yorkshire",
    "sg:tags":[
        "framing"
    ],
    "wof:name":"In the Frame",
    "wof:placetype":"venue"
},
  "geometry": {"coordinates":[-0.973894,53.616131],"type":"Point"}
}