{
  "type": "Feature",
  "properties": {
    "addr:full":"Sea View, Golant Fowey Cornwall PL23 1LL",
    "addr:postcode":"pl23 1ll",
    "iso:country":"GB",
    "sg:address":"Sea View, Golant",
    "sg:city":"Fowey",
    "sg:classifiers":[
        {
            "category":"Autos & Motor Vehicles",
            "subcategory":"Boat Sales",
            "type":"Retail Goods"
        }
    ],
    "sg:phone":"+44 1726 832424",
    "sg:postcode":"PL23 1LL",
    "sg:province":"Cornwall",
    "sg:tags":[
        "repair",
        "builder"
    ],
    "wof:name":"A J Fuge",
    "wof:placetype":"venue"
},
  "geometry": {"coordinates":[-4.6396479607,50.3362731934],"type":"Point"}
}