{
  "type": "Feature",
  "properties": {
    "addr:full":"164 Robertown Lane, Robert Town Liversedge West Yorkshire WF15 7LT",
    "addr:housenumber":"164",
    "addr:postcode":"wf15 7lt",
    "addr:street":"Robertown Lane Robert Town Liversedge West",
    "iso:country":"GB",
    "sg:address":"164 Robertown Lane, Robert Town",
    "sg:city":"Liversedge",
    "sg:classifiers":[
        {
            "category":"Personal",
            "subcategory":"Beauty Salon",
            "type":"Services"
        },
        {
            "category":"Personal",
            "subcategory":"Barber",
            "type":"Services"
        }
    ],
    "sg:phone":"+44 1924 401628",
    "sg:postcode":"WF15 7LT",
    "sg:province":"West Yorkshire",
    "sg:tags":[
        "unisex",
        "hairdresser"
    ],
    "wof:name":"J Askwith-Holland",
    "wof:placetype":"venue"
},
  "geometry": {"coordinates":[-1.7044899464,53.6998138428],"type":"Point"}
}