{
  "type": "Feature",
  "properties": {
    "addr:full":"10 Brighton Square Brighton East Sussex BN1 1HD",
    "addr:housenumber":"10",
    "addr:postcode":"bn1 1hd",
    "addr:street":"Brighton Square",
    "iso:country":"GB",
    "sg:address":"10 Brighton Square",
    "sg:city":"Brighton",
    "sg:classifiers":[
        {
            "category":"Shopping",
            "subcategory":"Gifts & Souvenirs",
            "type":"Retail Goods"
        }
    ],
    "sg:phone":"+44 1273 323200",
    "sg:postcode":"BN1 1HD",
    "sg:province":"East Sussex",
    "sg:tags":[
        "shop"
    ],
    "wof:name":"Earthly Artefacts Ltd.",
    "wof:placetype":"venue"
},
  "geometry": {"coordinates":[-0.1406890005,50.8221931458],"type":"Point"}
}