{
  "type": "Feature",
  "properties": {
    "addr:full":"21 London Road Bexhill-on-sea East Sussex TN39 3JR",
    "addr:housenumber":"21",
    "addr:postcode":"tn39 3jr",
    "addr:street":"London Road",
    "iso:country":"GB",
    "sg:address":"21 London Road",
    "sg:city":"Bexhill-on-sea",
    "sg:classifiers":[
        {
            "category":"Military Area",
            "subcategory":"Air Force Base",
            "type":"Public Place"
        }
    ],
    "sg:phone":"+44 1424 730910",
    "sg:postcode":"TN39 3JR",
    "sg:province":"East Sussex",
    "sg:tags":[
        "taxi",
        "hire",
        "private"
    ],
    "wof:name":"Fareways Taxis",
    "wof:placetype":"venue"
},
  "geometry": {"coordinates":[0.46975,50.84166],"type":"Point"}
}