{
  "type": "Feature",
  "properties": {
    "iso:country":"GB",
    "sg:address":"Good Shepherd Church Hall, Forbeck Road, Ford Estate",
    "sg:city":"Sunderland",
    "sg:classifiers":[
        {
            "category":"Building & Trades",
            "subcategory":"Construction",
            "type":"Services"
        }
    ],
    "sg:postcode":"SR4 0DQ",
    "sg:province":"Tyne and Wear",
    "sg:tags":[
        "dry",
        "lining",
        "plasterers",
        "screeders"
    ],
    "wof:name":"Commercial Plasterers",
    "wof:placetype":"venue"
},
  "geometry": {"coordinates":[-1.43177,54.905731],"type":"Point"}
}