{
  "type": "Feature",
  "properties": {
    "addr:full":"Norwich Union House, Lichfield Street Walsall West Midlands WS1 1TU",
    "addr:postcode":"ws1 1tu",
    "addr:street":"Lichfield Street",
    "iso:country":"GB",
    "sg:address":"Norwich Union House, Lichfield Street",
    "sg:city":"Walsall",
    "sg:classifiers":[
        {
            "category":"Insurance",
            "subcategory":"Insurance Agent",
            "type":"Services"
        }
    ],
    "sg:phone":"+44 1922 633163",
    "sg:postcode":"WS1 1TU",
    "sg:province":"West Midlands",
    "sg:tags":[
        "broker"
    ],
    "wof:name":"Cox Lee & Co. Ltd.",
    "wof:placetype":"venue"
},
  "geometry": {"coordinates":[-1.975272,52.588787],"type":"Point"}
}