{
  "type": "Feature",
  "properties": {
    "iso:country":"GB",
    "sg:address":"43 Church St",
    "sg:city":"Littlehampton",
    "sg:classifiers":[
        {
            "category":"Travel",
            "subcategory":"Hotels & Motels",
            "type":"Entertainment"
        }
    ],
    "sg:phone":"+44 1903 723174",
    "sg:postcode":"BN17 5PU",
    "sg:province":"West Sussex",
    "sg:tags":[
        "house",
        "guest"
    ],
    "wof:name":"Bracken Lodge Guest House",
    "wof:placetype":"venue"
},
  "geometry": {"coordinates":[-0.5352240205,50.8091545105],"type":"Point"}
}