{
  "type": "Feature",
  "properties": {
    "addr:full":"Chardley 70 Primrose Way Lydney Gloucestershire GL15 5SQ",
    "addr:housenumber":"70",
    "addr:postcode":"gl15 5sq",
    "addr:street":"Chardley;Primrose Way",
    "iso:country":"GB",
    "sg:address":"Chardley 70 Primrose Way",
    "sg:city":"Lydney",
    "sg:classifiers":[
        {
            "category":"Building & Trades",
            "subcategory":"Construction",
            "type":"Services"
        }
    ],
    "sg:phone":"+44 1594 842819",
    "sg:postcode":"GL15 5SQ",
    "sg:province":"Gloucestershire",
    "sg:tags":[
        "builder"
    ],
    "wof:name":"A.A Saunders",
    "wof:placetype":"venue"
},
  "geometry": {"coordinates":[-2.5358190536,51.7244911194],"type":"Point"}
}