{
  "type": "Feature",
  "properties": {
    "addr:full":"Research House, Caton Road Lancaster Lancashire LA1 3PE",
    "addr:postcode":"la1 3pe",
    "addr:street":"Caton Road",
    "iso:country":"GB",
    "sg:address":"Research House, Caton Road",
    "sg:city":"Lancaster",
    "sg:classifiers":[
        {
            "category":"Communications",
            "type":"Services"
        }
    ],
    "sg:phone":"+44 1524 382000",
    "sg:postcode":"LA1 3PE",
    "sg:province":"Lancashire",
    "sg:tags":[
        "telecommunication"
    ],
    "wof:name":"Teleconomy Ltd.",
    "wof:placetype":"venue"
},
  "geometry": {"coordinates":[-2.788207,54.06205],"type":"Point"}
}