{
  "type": "Feature",
  "properties": {
    "iso:country":"GB",
    "sg:address":"16 Cockburn Street",
    "sg:city":"Falkirk",
    "sg:classifiers":[
        {
            "category":"Personal",
            "subcategory":"Beauty Salon",
            "type":"Services"
        }
    ],
    "sg:postcode":"FK1 5BE",
    "sg:province":"Falkirk",
    "sg:tags":[
        "unisex",
        "hairdresser"
    ],
    "wof:name":"Andy's Barber Shop",
    "wof:placetype":"venue"
},
  "geometry": {"coordinates":[-3.787909,55.99894],"type":"Point"}
}