{
  "type": "Feature",
  "properties": {
    "addr:full":"8 Hunter Street Kirkcaldy Fife KY1 1ED",
    "addr:housenumber":"8",
    "addr:postcode":"ky1 1ed",
    "addr:street":"Hunter Street",
    "iso:country":"GB",
    "sg:address":"8 Hunter Street",
    "sg:city":"Kirkcaldy",
    "sg:classifiers":[
        {
            "category":"Building & Trades",
            "subcategory":"Cleaning & Sanitation",
            "type":"Services"
        }
    ],
    "sg:phone":"+44 1592 267835",
    "sg:postcode":"KY1 1ED",
    "sg:province":"Fife",
    "sg:tags":[
        "dry",
        "control",
        "damp",
        "rot"
    ],
    "wof:name":"Richardson & Starling (Northern) Ltd.",
    "wof:placetype":"venue"
},
  "geometry": {"coordinates":[-3.1614620686,56.1105995178],"type":"Point"}
}