{
  "type": "Feature",
  "properties": {
    "addr:full":"Rear Of St Andrews Church, 145 High Road London Greater London NW10 2QS",
    "addr:housenumber":"rear of;145",
    "addr:postcode":"nw10 2qs",
    "addr:street":"St Andrews;High Road",
    "iso:country":"GB",
    "sg:address":"Rear Of St Andrews Church, 145 High Road",
    "sg:city":"London",
    "sg:classifiers":[
        {
            "category":"Organizations",
            "subcategory":"Non-profit Organization",
            "type":"Services"
        }
    ],
    "sg:postcode":"NW10 2QS",
    "sg:province":"Greater London",
    "sg:tags":[
        "organisation",
        "voluntary",
        "charity"
    ],
    "wof:name":"Brent Welcare",
    "wof:placetype":"venue"
},
  "geometry": {"coordinates":[-0.2322160006,51.5470657349],"type":"Point"}
}