{
  "type": "Feature",
  "properties": {
    "addr:full":"Claylands Road, Bishops Waltham Southampton Hampshire SO32 1BH",
    "addr:postcode":"so32 1bh",
    "addr:street":"Claylands Road",
    "iso:country":"GB",
    "sg:address":"Claylands Road, Bishops Waltham",
    "sg:city":"Southampton",
    "sg:classifiers":[
        {
            "category":"Professional",
            "subcategory":"Printing & Photocopies",
            "type":"Services"
        }
    ],
    "sg:postcode":"SO32 1BH",
    "sg:province":"Hampshire",
    "sg:tags":[
        "printer"
    ],
    "wof:name":"Solent Design Studios",
    "wof:placetype":"venue"
},
  "geometry": {"coordinates":[-1.2214750051,50.9577522278],"type":"Point"}
}