{
  "type": "Feature",
  "properties": {
    "addr:full":"28 Countess Gdns, Littledown Bournemouth Dorset BH7 7RR",
    "addr:housenumber":"28",
    "addr:postcode":"bh7 7rr",
    "addr:street":"Countess Gdns Littledown",
    "iso:country":"GB",
    "sg:address":"28 Countess Gdns, Littledown",
    "sg:city":"Bournemouth",
    "sg:classifiers":[
        {
            "category":"Professional",
            "subcategory":"Management & Consulting",
            "type":"Services"
        }
    ],
    "sg:phone":"+44 1202 392037",
    "sg:postcode":"BH7 7RR",
    "sg:province":"Dorset",
    "sg:tags":[
        "consultant",
        "business"
    ],
    "wof:name":"1ST Instinct Leisure",
    "wof:placetype":"venue"
},
  "geometry": {"coordinates":[-1.8332740068,50.7425422668],"type":"Point"}
}