{
  "type": "Feature",
  "properties": {
    "addr:full":"Unit 4 Block 8, Chapelhall Industrial Estate, Chapelhall Airdrie North Lanarkshire ML6 8QH",
    "addr:housenumber":"unit 4 block",
    "addr:postcode":"ml6 8qh",
    "addr:street":"Chapelhall Industrial Estate",
    "iso:country":"GB",
    "sg:address":"Unit 4 Block 8, Chapelhall Industrial Estate, Chapelhall",
    "sg:city":"Airdrie",
    "sg:classifiers":[
        {
            "category":"Home & Garden",
            "subcategory":"Carpets & Floor Coverings",
            "type":"Retail Goods"
        }
    ],
    "sg:phone":"+44 1236 770300",
    "sg:postcode":"ML6 8QH",
    "sg:province":"North Lanarkshire",
    "sg:tags":[
        "cleaner",
        "upholstery"
    ],
    "wof:name":"Caledonia Carpet Upholstery",
    "wof:placetype":"venue"
},
  "geometry": {"coordinates":[-3.9504139423,55.8420333862],"type":"Point"}
}