{
  "type": "Feature",
  "properties": {
    "addr:full":"31 Fieldside Scunthorpe Lincolnshire DN17 4HL",
    "addr:housenumber":"31",
    "addr:postcode":"dn17 4hl",
    "addr:street":"Fieldside",
    "iso:country":"GB",
    "sg:address":"31 Fieldside",
    "sg:city":"Scunthorpe",
    "sg:classifiers":[
        {
            "category":"Home & Garden",
            "subcategory":"Kitchen Supply",
            "type":"Retail Goods"
        }
    ],
    "sg:phone":"+44 1724 711660",
    "sg:postcode":"DN17 4HL",
    "sg:province":"Lincolnshire",
    "sg:tags":[
        "ware"
    ],
    "wof:name":"Paul Chapman",
    "wof:placetype":"venue"
},
  "geometry": {"coordinates":[-0.831747,53.607868],"type":"Point"}
}