{
  "type": "Feature",
  "properties": {
    "addr:full":"3 Coleshill Rd, Water Orton Birmingham Warwickshire B46 1SH",
    "addr:housenumber":"3",
    "addr:postcode":"b46 1sh",
    "addr:street":"Coleshill Rd",
    "iso:country":"GB",
    "sg:address":"3 Coleshill Rd, Water Orton",
    "sg:city":"Birmingham",
    "sg:classifiers":[
        {
            "category":"Food & Beverages",
            "subcategory":"Fruits & Vegetables",
            "type":"Retail Goods"
        }
    ],
    "sg:postcode":"B46 1SH",
    "sg:province":"Warwickshire",
    "sg:tags":[
        "greengrocer"
    ],
    "wof:name":"Clements, Michael,",
    "wof:placetype":"venue"
},
  "geometry": {"coordinates":[-1.740618,52.516888],"type":"Point"}
}