{
  "type": "Feature",
  "properties": {
    "iso:country":"GB",
    "sg:address":"Aysgarth Rd",
    "sg:city":"Waterlooville",
    "sg:classifiers":[
        {
            "category":"Autos & Motor Vehicles",
            "subcategory":"Auto Supplies",
            "type":"Retail Goods"
        },
        {
            "category":"Retail",
            "subcategory":"Auto Repair",
            "type":"Services"
        }
    ],
    "sg:phone":"+44 23 9224 0777",
    "sg:postcode":"PO7 7UG",
    "sg:province":"Hampshire",
    "sg:tags":[
        "modification",
        "garage",
        "component"
    ],
    "wof:name":"Express Factors Ltd",
    "wof:placetype":"venue"
},
  "geometry": {"coordinates":[-1.032859,50.883461],"type":"Point"}
}