{
  "type": "Feature",
  "properties": {
    "iso:country":"GB",
    "sg:address":"62 Eldon Road",
    "sg:city":"Caterham",
    "sg:classifiers":[
        {
            "category":"Communications",
            "type":"Services"
        }
    ],
    "sg:postcode":"CR3 5JR",
    "sg:province":"Surrey",
    "sg:tags":[
        "audio-visual"
    ],
    "wof:name":"Merlin Movies",
    "wof:placetype":"venue"
},
  "geometry": {"coordinates":[-0.0980509967,51.2935371399],"type":"Point"}
}