{
  "type": "Feature",
  "properties": {
    "addr:full":"Catherine Street London Greater London WC2B 5LA",
    "addr:postcode":"wc2b 5la",
    "addr:street":"Catherine Street",
    "iso:country":"GB",
    "sg:address":"Catherine Street",
    "sg:city":"London",
    "sg:classifiers":[
        {
            "category":"Arts & Performance",
            "subcategory":"Theater",
            "type":"Entertainment"
        }
    ],
    "sg:postcode":"WC2B 5LA",
    "sg:province":"Greater London",
    "sg:tags":[
        "hall",
        "theatre",
        "concert"
    ],
    "wof:name":"The Duchess Theatre",
    "wof:placetype":"venue"
},
  "geometry": {"coordinates":[-0.1203889996,51.5126037598],"type":"Point"}
}