{
  "type": "Feature",
  "properties": {
    "addr:full":"Barrett House, Sopers Rd Potters Bar Greater London EN6 4RY",
    "addr:postcode":"en6 4ry",
    "addr:street":"Sopers Rd",
    "iso:country":"GB",
    "sg:address":"Barrett House, Sopers Rd",
    "sg:city":"Potters Bar",
    "sg:classifiers":[
        {
            "category":"Building & Trades",
            "subcategory":"Construction",
            "type":"Services"
        }
    ],
    "sg:phone":"+44 1707 876464",
    "sg:postcode":"EN6 4RY",
    "sg:province":"Greater London",
    "sg:tags":[
        "builder"
    ],
    "wof:name":"Ben Barrett & Son Ltd",
    "wof:placetype":"venue"
},
  "geometry": {"coordinates":[-0.1086340025,51.7072639465],"type":"Point"}
}