{
  "type": "Feature",
  "properties": {
    "addr:full":"100 Lewin Street Middlewich Cheshire CW10 9AS",
    "addr:housenumber":"100",
    "addr:postcode":"cw10 9as",
    "addr:street":"Lewin Street",
    "iso:country":"GB",
    "sg:address":"100 Lewin Street",
    "sg:city":"Middlewich",
    "sg:classifiers":[
        {
            "category":"Organizations",
            "subcategory":"Membership Organization",
            "type":"Services"
        }
    ],
    "sg:phone":"+44 1606 833286",
    "sg:postcode":"CW10 9AS",
    "sg:province":"Cheshire",
    "sg:tags":[
        "club",
        "social"
    ],
    "wof:name":"The Royal British Legion",
    "wof:placetype":"venue"
},
  "geometry": {"coordinates":[-2.4413809776,53.1885528564],"type":"Point"}
}