{
  "type": "Feature",
  "properties": {
    "addr:full":"London Road, Hook Common Hook Berkshire RG27 9JJ",
    "addr:postcode":"rg27 9jj",
    "addr:street":"London Road",
    "iso:country":"GB",
    "sg:address":"London Road, Hook Common",
    "sg:city":"Hook",
    "sg:classifiers":[
        {
            "category":"Bars & Pubs",
            "type":"Food & Drink"
        }
    ],
    "sg:phone":"+44 1256 762690",
    "sg:postcode":"RG27 9JJ",
    "sg:province":"Berkshire",
    "sg:tags":[
        "pubs",
        "inn"
    ],
    "wof:name":"The Dorchester Arms",
    "wof:placetype":"venue"
},
  "geometry": {"coordinates":[-0.967529,51.280586],"type":"Point"}
}