{
  "type": "Feature",
  "properties": {
    "addr:full":"Chinnor Rd, Gledlow Princes Risborough Buckinghamshire HP27 9PH",
    "addr:postcode":"hp27 9ph",
    "addr:street":"Chinnor Rd Gledlow",
    "iso:country":"GB",
    "sg:address":"Chinnor Rd, Gledlow",
    "sg:city":"Princes Risborough",
    "sg:classifiers":[
        {
            "category":"Building & Trades",
            "subcategory":"Landscaping Services",
            "type":"Services"
        }
    ],
    "sg:phone":"+44 1844 292764",
    "sg:postcode":"HP27 9PH",
    "sg:province":"Buckinghamshire",
    "sg:tags":[
        "landscape",
        "contractor"
    ],
    "wof:name":"Risborough Turf",
    "wof:placetype":"venue"
},
  "geometry": {"coordinates":[-0.8745340109,51.7208137512],"type":"Point"}
}