{
  "type": "Feature",
  "properties": {
    "iso:country":"GB",
    "sg:address":"Andante, Stone St",
    "sg:city":"Ipswich",
    "sg:classifiers":[
        {
            "category":"Shopping",
            "type":"Retail Goods"
        }
    ],
    "sg:phone":"+44 1449 760352",
    "sg:postcode":"IP6 9SZ",
    "sg:province":"Suffolk",
    "sg:tags":[
        "bag"
    ],
    "wof:name":"Pakams",
    "wof:placetype":"venue"
},
  "geometry": {"coordinates":[1.14233,52.170059],"type":"Point"}
}