{
  "type": "Feature",
  "properties": {
    "addr:full":"15 Summit Close London Greater London N14 7NR",
    "addr:housenumber":"15",
    "addr:postcode":"n14 7nr",
    "addr:street":"Summit Close",
    "iso:country":"GB",
    "sg:address":"15 Summit Close",
    "sg:city":"London",
    "sg:classifiers":[
        {
            "category":"Shopping",
            "subcategory":"Party Supplies",
            "type":"Retail Goods"
        }
    ],
    "sg:postcode":"N14 7NR",
    "sg:province":"Greater London",
    "sg:tags":[
        "inflatables",
        "bouncy",
        "castle"
    ],
    "wof:name":"Party Castles",
    "wof:placetype":"venue"
},
  "geometry": {"coordinates":[-0.13964,51.627769],"type":"Point"}
}