{
  "type": "Feature",
  "properties": {
    "iso:country":"GB",
    "sg:address":"130 Engaine Drive, Shenley Church End",
    "sg:city":"Milton Keynes",
    "sg:classifiers":[
        {
            "category":"Professional",
            "subcategory":"Management & Consulting",
            "type":"Services"
        }
    ],
    "sg:phone":"+44 1908 506996",
    "sg:postcode":"MK5 6DH",
    "sg:province":"Buckinghamshire",
    "sg:tags":[
        "consultant",
        "business"
    ],
    "wof:name":"Development At Work",
    "wof:placetype":"venue"
},
  "geometry": {"coordinates":[-0.7952359915,52.0238647461],"type":"Point"}
}