{
  "type": "Feature",
  "properties": {
    "iso:country":"GB",
    "sg:address":"110 Coast Road, West Mersea",
    "sg:city":"Colchester",
    "sg:classifiers":[
        {
            "category":"Recreation",
            "subcategory":"Marina",
            "type":"Entertainment"
        }
    ],
    "sg:postcode":"CO5 8PE",
    "sg:province":"Essex",
    "sg:tags":[
        "mooring",
        "boat"
    ],
    "wof:name":"West Mersea Marine Ltd.",
    "wof:placetype":"venue"
},
  "geometry": {"coordinates":[0.8991280198,51.7784385681],"type":"Point"}
}