{
  "type": "Feature",
  "properties": {
    "iso:country":"GB",
    "sg:address":"12 Balmoral Close, Lordswood",
    "sg:city":"Southampton",
    "sg:classifiers":[
        {
            "category":"Home & Garden",
            "subcategory":"Carpets & Floor Coverings",
            "type":"Retail Goods"
        }
    ],
    "sg:postcode":"SO16 8ER",
    "sg:province":"Hampshire",
    "sg:tags":[
        "carpets",
        "rug",
        "matting"
    ],
    "wof:name":"A J Dixon",
    "wof:placetype":"venue"
},
  "geometry": {"coordinates":[-1.428333,50.945522],"type":"Point"}
}