{
  "type": "Feature",
  "properties": {
    "iso:country":"GB",
    "sg:address":"Unit 124, Camelot Studios, 222 Kensal Rd",
    "sg:city":"London",
    "sg:classifiers":[
        {
            "category":"Communications",
            "type":"Services"
        }
    ],
    "sg:postcode":"W10 5BN",
    "sg:province":"Greater London",
    "sg:tags":[
        "audio-visual"
    ],
    "wof:name":"Essential Pictures Ltd",
    "wof:placetype":"venue"
},
  "geometry": {"coordinates":[-0.2067400068,51.5256500244],"type":"Point"}
}