{
  "type": "Feature",
  "properties": {
    "iso:country":"GB",
    "sg:address":"132 Ayr Road, Newton Mearns",
    "sg:city":"Glasgow",
    "sg:classifiers":[
        {
            "category":"Personal",
            "subcategory":"Beauty Salon",
            "type":"Services"
        }
    ],
    "sg:postcode":"G77 6EG",
    "sg:province":"East Ayrshire",
    "sg:tags":[
        "unisex",
        "hairdresser"
    ],
    "wof:name":"David Sands",
    "wof:placetype":"venue"
},
  "geometry": {"coordinates":[-4.321972,55.778706],"type":"Point"}
}