{
  "type": "Feature",
  "properties": {
    "addr:full":"17 Birchgrave Close Coventry Warwickshire CV6 7NQ",
    "addr:housenumber":"17",
    "addr:postcode":"cv6 7nq",
    "addr:street":"Birchgrave Close",
    "iso:country":"GB",
    "sg:address":"17 Birchgrave Close",
    "sg:city":"Coventry",
    "sg:classifiers":[
        {
            "category":"Retail",
            "subcategory":"Driving School",
            "type":"Services"
        }
    ],
    "sg:phone":"+44 24 7663 8800",
    "sg:postcode":"CV6 7NQ",
    "sg:province":"Warwickshire",
    "wof:name":"S M G School of Motoring",
    "wof:placetype":"venue"
},
  "geometry": {"coordinates":[-1.4811290503,52.4281082153],"type":"Point"}
}