{
  "type": "Feature",
  "properties": {
    "addr:full":"St Asaph Avenue Rhyl Conwy LL18 5HA",
    "addr:postcode":"ll18 5ha",
    "addr:street":"St Asaph Avenue",
    "iso:country":"GB",
    "sg:address":"St Asaph Avenue",
    "sg:city":"Rhyl",
    "sg:classifiers":[
        {
            "category":"Professional",
            "subcategory":"Printing & Photocopies",
            "type":"Services"
        }
    ],
    "sg:phone":"+44 7714 458733",
    "sg:postcode":"LL18 5HA",
    "sg:province":"Conwy",
    "sg:tags":[
        "process",
        "screen",
        "printer"
    ],
    "wof:name":"Transprint",
    "wof:placetype":"venue"
},
  "geometry": {"coordinates":[-3.5197780132,53.3105583191],"type":"Point"}
}