{
  "type": "Feature",
  "properties": {
    "iso:country":"GB",
    "sg:address":"12 Gravel Road, Upper Hale",
    "sg:city":"Farnham",
    "sg:classifiers":[
        {
            "category":"Professional",
            "subcategory":"Engineering",
            "type":"Services"
        }
    ],
    "sg:postcode":"GU9 0JB",
    "sg:province":"Surrey",
    "sg:tags":[
        "contractor",
        "electrical",
        "engineer"
    ],
    "wof:name":"Roger Mantle",
    "wof:placetype":"venue"
},
  "geometry": {"coordinates":[-0.802654,51.234463],"type":"Point"}
}