{
  "type": "Feature",
  "properties": {
    "addr:full":"12 Crescent Road Rochdale Lancashire OL11 3LF",
    "addr:housenumber":"12",
    "addr:postcode":"ol11 3lf",
    "addr:street":"Crescent Road",
    "iso:country":"GB",
    "sg:address":"12 Crescent Road",
    "sg:city":"Rochdale",
    "sg:classifiers":[
        {
            "category":"Professional",
            "subcategory":"Detective & Security Services",
            "type":"Services"
        }
    ],
    "sg:phone":"+44 1706 715932",
    "sg:postcode":"OL11 3LF",
    "sg:province":"Lancashire",
    "sg:tags":[
        "alarm",
        "burglar",
        "system"
    ],
    "wof:name":"Onguard Security Systems",
    "wof:placetype":"venue"
},
  "geometry": {"coordinates":[-2.184394,53.601944],"type":"Point"}
}