{
  "type": "Feature",
  "properties": {
    "iso:country":"GB",
    "sg:address":"Caton Road",
    "sg:city":"Lancaster",
    "sg:classifiers":[
        {
            "category":"Manufacturing",
            "subcategory":"Textiles",
            "type":"Manufacturing & Wholesale Goods"
        }
    ],
    "sg:phone":"+44 1524 389308",
    "sg:postcode":"LA1 3PA",
    "sg:province":"Lancashire",
    "sg:tags":[
        "printer"
    ],
    "wof:name":"Courtaulds Textiles (Holdings) Ltd.",
    "wof:placetype":"venue"
},
  "geometry": {"coordinates":[-2.788207,54.06205],"type":"Point"}
}