{
  "type": "Feature",
  "properties": {
    "addr:full":"92 Mid Street, South Nutfield Redhill Surrey RH1 4JH",
    "addr:housenumber":"92",
    "addr:postcode":"rh1 4jh",
    "addr:street":"Mid Street",
    "iso:country":"GB",
    "sg:address":"92 Mid Street, South Nutfield",
    "sg:city":"Redhill",
    "sg:classifiers":[
        {
            "category":"Professional",
            "type":"Services"
        },
        {
            "category":"Health Services",
            "subcategory":"Nursing And Care Facility",
            "type":"Services"
        },
        {
            "category":"Professional",
            "subcategory":"Employment Agencies",
            "type":"Services"
        }
    ],
    "sg:phone":"+44 1737 822726",
    "sg:postcode":"RH1 4JH",
    "sg:province":"Surrey",
    "sg:tags":[
        "entertainer",
        "home",
        "entertainment"
    ],
    "wof:name":"Gambit Music Promotions",
    "wof:placetype":"venue"
},
  "geometry": {"coordinates":[-0.1301189959,51.2330207825],"type":"Point"}
}