{
  "type": "Feature",
  "properties": {
    "addr:full":"10 Church Rd Teddington Greater London TW11 8PB",
    "addr:housenumber":"10",
    "addr:postcode":"tw11 8pb",
    "addr:street":"Church Rd",
    "iso:country":"GB",
    "sg:address":"10 Church Rd",
    "sg:city":"Teddington",
    "sg:classifiers":[
        {
            "category":"Food & Beverages",
            "subcategory":"Candy",
            "type":"Retail Goods"
        }
    ],
    "sg:phone":"+44 20 8943 4839",
    "sg:postcode":"TW11 8PB",
    "sg:province":"Greater London",
    "sg:tags":[
        "confectioner"
    ],
    "wof:name":"Gourmet Gourmand",
    "wof:placetype":"venue"
},
  "geometry": {"coordinates":[-0.3364639878,51.4266242981],"type":"Point"}
}