{
  "type": "Feature",
  "properties": {
    "addr:full":"23 Station Rd Upminster Essex RM14 2SJ",
    "addr:housenumber":"23",
    "addr:postcode":"rm14 2sj",
    "addr:street":"Station Rd",
    "iso:country":"GB",
    "sg:address":"23 Station Rd",
    "sg:city":"Upminster",
    "sg:classifiers":[
        {
            "category":"Education",
            "subcategory":"College",
            "type":"Public Place"
        }
    ],
    "sg:phone":"+44 1708 223421",
    "sg:postcode":"RM14 2SJ",
    "sg:province":"Essex",
    "sg:tags":[
        "school"
    ],
    "wof:name":"Ladyplus Ltd",
    "wof:placetype":"venue"
},
  "geometry": {"coordinates":[0.2493840009,51.5571479797],"type":"Point"}
}