{
  "type": "Feature",
  "properties": {
    "addr:full":"24 Crowborough Hill Crowborough East Sussex TN6 2JE",
    "addr:housenumber":"24",
    "addr:postcode":"tn6 2je",
    "addr:street":"Crowborough Hill",
    "iso:country":"GB",
    "sg:address":"24 Crowborough Hill",
    "sg:city":"Crowborough",
    "sg:classifiers":[
        {
            "category":"Restaurant",
            "type":"Food & Drink"
        }
    ],
    "sg:phone":"+44 1892 661881",
    "sg:postcode":"TN6 2JE",
    "sg:province":"East Sussex",
    "sg:tags":[
        "indian"
    ],
    "wof:name":"Bengal Spice",
    "wof:placetype":"venue"
},
  "geometry": {"coordinates":[0.163595,51.058384],"type":"Point"}
}