{
  "type": "Feature",
  "properties": {
    "addr:full":"67 Lower Clapton Road London Greater London E5 0NP",
    "addr:housenumber":"67",
    "addr:postcode":"e5 0np",
    "addr:street":"Lower Clapton Road",
    "iso:country":"GB",
    "sg:address":"67 Lower Clapton Road",
    "sg:city":"London",
    "sg:classifiers":[
        {
            "category":"Fast Food",
            "type":"Food & Drink"
        }
    ],
    "sg:phone":"+44 20 8985 7971",
    "sg:postcode":"E5 0NP",
    "sg:province":"Greater London",
    "sg:tags":[
        "away",
        "take"
    ],
    "wof:name":"The Golden States",
    "wof:placetype":"venue"
},
  "geometry": {"coordinates":[-0.0519200005,51.551410675],"type":"Point"}
}