{
  "type": "Feature",
  "properties": {
    "addr:full":"The Drill Hall, Hydes Close Winchester Hampshire SO23 7DJ",
    "addr:postcode":"so23 7dj",
    "addr:street":"Hydes Close",
    "iso:country":"GB",
    "sg:address":"The Drill Hall, Hydes Close",
    "sg:city":"Winchester",
    "sg:classifiers":[
        {
            "category":"Communications",
            "subcategory":"Film & Video Production",
            "type":"Services"
        }
    ],
    "sg:phone":"+44 1489 877600",
    "sg:postcode":"SO23 7DJ",
    "sg:province":"Hampshire",
    "sg:tags":[
        "microfilming"
    ],
    "wof:name":"Knightswade Ltd",
    "wof:placetype":"venue"
},
  "geometry": {"coordinates":[-1.3168090582,51.0630683899],"type":"Point"}
}