{
  "type": "Feature",
  "properties": {
    "iso:country":"GB",
    "sg:address":"Marine House, High Street",
    "sg:city":"Lincoln",
    "sg:classifiers":[
        {
            "category":"Professional",
            "subcategory":"Business Services",
            "type":"Services"
        }
    ],
    "sg:phone":"+44 1608 664550",
    "sg:postcode":"LN5 9RF",
    "sg:province":"Lincolnshire",
    "sg:tags":[
        "import",
        "export",
        "agent"
    ],
    "wof:name":"Mampro Ltd.",
    "wof:placetype":"venue"
},
  "geometry": {"coordinates":[-0.638639,53.130157],"type":"Point"}
}