{
  "type": "Feature",
  "properties": {
    "iso:country":"GB",
    "sg:address":"22 Summerfield Rd",
    "sg:city":"Luton",
    "sg:classifiers":[
        {
            "category":"Professional",
            "subcategory":"Management & Consulting",
            "type":"Services"
        }
    ],
    "sg:phone":"+44 1582 414467",
    "sg:postcode":"LU1 1UJ",
    "sg:province":"Bedfordshire",
    "sg:tags":[
        "consultant",
        "business"
    ],
    "wof:name":"Michael Weedon Associates",
    "wof:placetype":"venue"
},
  "geometry": {"coordinates":[-0.4491539896,51.8826446533],"type":"Point"}
}