{
  "type": "Feature",
  "properties": {
    "iso:country":"GB",
    "sg:address":"2 Home Farm Cotts, Kipling",
    "sg:city":"Richmond",
    "sg:classifiers":[
        {
            "category":"Building & Trades",
            "subcategory":"Construction",
            "type":"Services"
        }
    ],
    "sg:phone":"+44 1748 812907",
    "sg:postcode":"DL10 6AS",
    "sg:province":"North Yorkshire",
    "sg:tags":[
        "roofing"
    ],
    "wof:name":"Flat Roof Co.",
    "wof:placetype":"venue"
},
  "geometry": {"coordinates":[-1.565762043,54.3682403564],"type":"Point"}
}