{
  "type": "Feature",
  "properties": {
    "iso:country":"GB",
    "sg:address":"64 Broad Street",
    "sg:city":"Teddington",
    "sg:classifiers":[
        {
            "category":"Shopping",
            "subcategory":"Crafts & Fabrics",
            "type":"Retail Goods"
        }
    ],
    "sg:postcode":"TW11 8QY",
    "sg:province":"Greater London",
    "sg:tags":[
        "material",
        "art"
    ],
    "wof:name":"Art & Graphics",
    "wof:placetype":"venue"
},
  "geometry": {"coordinates":[-0.336492002,51.4258956909],"type":"Point"}
}