{
  "type": "Feature",
  "properties": {
    "iso:country":"GB",
    "sg:address":"Arundel House, Wrenbury Road",
    "sg:city":"Nantwich",
    "sg:classifiers":[
        {
            "category":"Retail",
            "subcategory":"Event Space",
            "type":"Services"
        }
    ],
    "sg:phone":"+44 1270 216000",
    "sg:postcode":"CW5 8HA",
    "sg:province":"Cheshire",
    "sg:tags":[
        "exhibition",
        "organiser"
    ],
    "wof:name":"European Exhibition Co. Ltd.",
    "wof:placetype":"venue"
},
  "geometry": {"coordinates":[-2.6036388874,53.024055481],"type":"Point"}
}