{
  "type": "Feature",
  "properties": {
    "addr:full":"547 Green Lanes London Greater London N8 0RL",
    "addr:housenumber":"547",
    "addr:postcode":"n8 0rl",
    "addr:street":"Green Lanes",
    "iso:country":"GB",
    "sg:address":"547 Green Lanes",
    "sg:city":"London",
    "sg:classifiers":[
        {
            "category":"Food & Beverages",
            "subcategory":"Meat & Fish",
            "type":"Retail Goods"
        }
    ],
    "sg:phone":"+44 20 8341 2620",
    "sg:postcode":"N8 0RL",
    "sg:province":"Greater London",
    "sg:tags":[
        "butcher"
    ],
    "wof:name":"Thomas Butchers",
    "wof:placetype":"venue"
},
  "geometry": {"coordinates":[-0.0999620035,51.5825157166],"type":"Point"}
}