{
  "type": "Feature",
  "properties": {
    "addr:full":"9-11 Ashley Hill Bristol City of Bristol BS6 5HZ",
    "addr:housenumber":"9-11",
    "addr:postcode":"bs6 5hz",
    "addr:street":"Ashley Hill",
    "iso:country":"GB",
    "sg:address":"9-11 Ashley Hill",
    "sg:city":"Bristol",
    "sg:classifiers":[
        {
            "category":"Shopping",
            "subcategory":"Department Store",
            "type":"Retail Goods"
        }
    ],
    "sg:phone":"+44 117 955 2394",
    "sg:postcode":"BS6 5HZ",
    "sg:province":"City of Bristol",
    "wof:name":"A & M Stores",
    "wof:placetype":"venue"
},
  "geometry": {"coordinates":[-2.579886,51.468884],"type":"Point"}
}