{
  "type": "Feature",
  "properties": {
    "addr:full":"44 Dickens Road Ipswich Suffolk IP2 0JW",
    "addr:housenumber":"44",
    "addr:postcode":"ip2 0jw",
    "addr:street":"Dickens Road",
    "iso:country":"GB",
    "sg:address":"44 Dickens Road",
    "sg:city":"Ipswich",
    "sg:classifiers":[
        {
            "category":"Food & Beverages",
            "subcategory":"Meat & Fish",
            "type":"Retail Goods"
        },
        {
            "category":"Food & Beverages",
            "subcategory":"Groceries & Convenience Stores",
            "type":"Retail Goods"
        }
    ],
    "sg:phone":"+44 1473 254757",
    "sg:postcode":"IP2 0JW",
    "sg:province":"Suffolk",
    "sg:tags":[
        "shop",
        "chip"
    ],
    "wof:name":"N W FISH & CHIPS",
    "wof:placetype":"venue"
},
  "geometry": {"coordinates":[1.127479,52.057026],"type":"Point"}
}