{
  "type": "Feature",
  "properties": {
    "iso:country":"GB",
    "sg:address":"Woodfield Road",
    "sg:city":"Shrewsbury",
    "sg:classifiers":[
        {
            "category":"Education",
            "subcategory":"School",
            "type":"Public Place"
        }
    ],
    "sg:phone":"+44 1743 357133",
    "sg:postcode":"SY3 8LU",
    "sg:province":"Shropshire",
    "sg:tags":[
        "local",
        "authority"
    ],
    "wof:name":"St. Georges Junior School",
    "wof:placetype":"venue"
},
  "geometry": {"coordinates":[-2.768489,52.709084],"type":"Point"}
}