{
  "type": "Feature",
  "properties": {
    "addr:full":"Melbourne House, 24-26 Whitworth Rd South Norwood Greater London SE25 6XG",
    "addr:housenumber":"24-26",
    "addr:postcode":"se25 6xg",
    "addr:street":"Whitworth Rd",
    "iso:country":"GB",
    "sg:address":"Melbourne House, 24-26 Whitworth Rd",
    "sg:city":"South Norwood",
    "sg:classifiers":[
        {
            "category":"Health Services",
            "subcategory":"Nursing And Care Facility",
            "type":"Services"
        }
    ],
    "sg:phone":"+44 20 8771 5911",
    "sg:postcode":"SE25 6XG",
    "sg:province":"Greater London",
    "sg:tags":[
        "home"
    ],
    "wof:name":"Shaftesbury Society Housing Association",
    "wof:placetype":"venue"
},
  "geometry": {"coordinates":[-0.081187,51.399487],"type":"Point"}
}