{
  "type": "Feature",
  "properties": {
    "addr:full":"51 Bridge Street Ledbury Gloucestershire HR8 2AH",
    "addr:housenumber":"51",
    "addr:postcode":"hr8 2ah",
    "addr:street":"Bridge Street",
    "iso:country":"GB",
    "sg:address":"51 Bridge Street",
    "sg:city":"Ledbury",
    "sg:classifiers":[
        {
            "category":"Taxi",
            "type":"Transportation"
        },
        {
            "category":"Military Area",
            "subcategory":"Air Force Base",
            "type":"Public Place"
        }
    ],
    "sg:phone":"+44 1531 632852",
    "sg:postcode":"HR8 2AH",
    "sg:province":"Gloucestershire",
    "sg:tags":[
        "hire",
        "private"
    ],
    "wof:name":"E N Meredith",
    "wof:placetype":"venue"
},
  "geometry": {"coordinates":[-2.4295580387,52.0365638733],"type":"Point"}
}