{
  "type": "Feature",
  "properties": {
    "addr:full":"1 Summerhill Avenue, Southborough Tunbridge Wells Kent TN4 0QX",
    "addr:housenumber":"1",
    "addr:postcode":"tn4 0qx",
    "addr:street":"Summerhill Avenue",
    "iso:country":"GB",
    "sg:address":"1 Summerhill Avenue, Southborough",
    "sg:city":"Tunbridge Wells",
    "sg:classifiers":[
        {
            "category":"Professional",
            "subcategory":"Lawyer & Legal Services",
            "type":"Services"
        }
    ],
    "sg:phone":"+44 1892 528504",
    "sg:postcode":"TN4 0QX",
    "sg:province":"Kent",
    "sg:tags":[
        "solicitor"
    ],
    "wof:name":"Jonathan C Brunker",
    "wof:placetype":"venue"
},
  "geometry": {"coordinates":[0.2549189925,51.1580314636],"type":"Point"}
}