{
  "type": "Feature",
  "properties": {
    "iso:country":"GB",
    "sg:address":"74 Albert Street, Lockwood",
    "sg:city":"Huddersfield",
    "sg:classifiers":[
        {
            "category":"Professional",
            "subcategory":"Engineering",
            "type":"Services"
        }
    ],
    "sg:phone":"+44 1484 425645",
    "sg:postcode":"HD1 3QL",
    "sg:province":"West Yorkshire",
    "sg:tags":[
        "precision",
        "engineer"
    ],
    "wof:name":"Kingsmith Engineering",
    "wof:placetype":"venue"
},
  "geometry": {"coordinates":[-1.7909549475,53.6356010437],"type":"Point"}
}