{
  "type": "Feature",
  "properties": {
    "addr:full":"6 Crighton Place Edinburgh City of Edinburgh EH7 4NZ",
    "addr:housenumber":"6",
    "addr:postcode":"eh7 4nz",
    "addr:street":"Crighton Place Edinburgh",
    "iso:country":"GB",
    "sg:address":"6 Crighton Place",
    "sg:city":"Edinburgh",
    "sg:classifiers":[
        {
            "category":"Shopping",
            "subcategory":"Bicycles & Sporting Goods",
            "type":"Retail Goods"
        },
        {
            "category":"Sports & Exercise",
            "subcategory":"Sports Center",
            "type":"Entertainment"
        }
    ],
    "sg:phone":"+44 131 554 5040",
    "sg:postcode":"EH7 4NZ",
    "sg:province":"City of Edinburgh",
    "sg:tags":[
        "shop",
        "sale"
    ],
    "wof:name":"Elite Sports",
    "wof:placetype":"venue"
},
  "geometry": {"coordinates":[-3.189179,55.958988],"type":"Point"}
}