{
  "type": "Feature",
  "properties": {
    "addr:full":"Church Road, Undy Magor Caldicot Monmouthshire NP26 3EN",
    "addr:postcode":"np26 3en",
    "addr:street":"Church Road",
    "iso:country":"GB",
    "sg:address":"Church Road, Undy Magor",
    "sg:city":"Caldicot",
    "sg:classifiers":[
        {
            "category":"Building & Trades",
            "subcategory":"Construction",
            "type":"Services"
        }
    ],
    "sg:postcode":"NP26 3EN",
    "sg:province":"Monmouthshire",
    "sg:tags":[
        "joinery"
    ],
    "wof:name":"Tony Baker Joinery",
    "wof:placetype":"venue"
},
  "geometry": {"coordinates":[-2.8106598854,51.5783691406],"type":"Point"}
}