{
  "type": "Feature",
  "properties": {
    "iso:country":"GB",
    "sg:address":"67 Crompton Road",
    "sg:city":"Macclesfield",
    "sg:classifiers":[
        {
            "category":"Food & Beverages",
            "subcategory":"Meat & Fish",
            "type":"Retail Goods"
        }
    ],
    "sg:phone":"+44 1625 425851",
    "sg:postcode":"SK11 8EB",
    "sg:province":"Cheshire",
    "sg:tags":[
        "butcher"
    ],
    "wof:name":"L & J M Wain",
    "wof:placetype":"venue"
},
  "geometry": {"coordinates":[-2.135206,53.257881],"type":"Point"}
}