{
  "type": "Feature",
  "properties": {
    "addr:full":"92e New Greenham Park, Greenham Thatcham Berkshire RG19 6HN",
    "addr:housenumber":"92e",
    "addr:postcode":"rg19 6hn",
    "addr:street":"New Greenham Park",
    "iso:country":"GB",
    "sg:address":"92e New Greenham Park, Greenham",
    "sg:city":"Thatcham",
    "sg:classifiers":[
        {
            "category":"Utilities",
            "subcategory":"Mobile Phone",
            "type":"Services"
        },
        {
            "category":"Professional",
            "subcategory":"Business Services",
            "type":"Services"
        }
    ],
    "sg:phone":"+44 1635 573200",
    "sg:postcode":"RG19 6HN",
    "sg:province":"Berkshire",
    "sg:tags":[
        "answering",
        "telephone"
    ],
    "wof:name":"P H D IN COMMUNICATIONS LTD",
    "wof:placetype":"venue"
},
  "geometry": {"coordinates":[-1.2819900513,51.3749694824],"type":"Point"}
}