{
  "type": "Feature",
  "properties": {
    "iso:country":"GB",
    "sg:address":"Westgate Business Park",
    "sg:city":"Pickering",
    "sg:classifiers":[
        {
            "category":"Professional",
            "subcategory":"Engineering",
            "type":"Services"
        }
    ],
    "sg:phone":"+44 1751 476740",
    "sg:postcode":"YO18 8LX",
    "sg:province":"North Yorkshire",
    "sg:tags":[
        "electronic",
        "engineer"
    ],
    "wof:name":"Meadowview Electronics",
    "wof:placetype":"venue"
},
  "geometry": {"coordinates":[-0.7948899865,54.2483558655],"type":"Point"}
}