{
  "type": "Feature",
  "properties": {
    "iso:country":"GB",
    "sg:address":"Perseverance Works, 38 Kingsland Road",
    "sg:city":"London",
    "sg:classifiers":[
        {
            "category":"Retail",
            "subcategory":"Portrait Studio",
            "type":"Services"
        },
        {
            "category":"Professional",
            "subcategory":"Art Services",
            "type":"Services"
        }
    ],
    "sg:phone":"+44 20 7256 0384",
    "sg:postcode":"E2 8DA",
    "sg:province":"Greater London",
    "sg:tags":[
        "photographer",
        "commercial"
    ],
    "wof:name":"CHRIS KNAGGS & ASSOCIATES",
    "wof:placetype":"venue"
},
  "geometry": {"coordinates":[-0.0779229999,51.5278701782],"type":"Point"}
}