{
  "type": "Feature",
  "properties": {
    "addr:full":"859 London Road Westcliff-on-sea Essex SS0 9SZ",
    "addr:housenumber":"859",
    "addr:postcode":"ss0 9sz",
    "addr:street":"London Road",
    "iso:country":"GB",
    "sg:address":"859 London Road",
    "sg:city":"Westcliff-on-sea",
    "sg:classifiers":[
        {
            "category":"Sports & Exercise",
            "subcategory":"Sports Center",
            "type":"Entertainment"
        }
    ],
    "sg:phone":"+44 1702 471718",
    "sg:postcode":"SS0 9SZ",
    "sg:province":"Essex",
    "sg:tags":[
        "shop",
        "good"
    ],
    "wof:name":"Archery 2000",
    "wof:placetype":"venue"
},
  "geometry": {"coordinates":[0.6744289994,51.5459098816],"type":"Point"}
}