{
  "type": "Feature",
  "properties": {
    "addr:full":"3 Perimeter Shop, New Market Hall Rotherham South Yorkshire S65 1JQ",
    "addr:housenumber":"3",
    "addr:postcode":"s65 1jq",
    "addr:street":"Rotherham South",
    "iso:country":"GB",
    "sg:address":"3 Perimeter Shop, New Market Hall",
    "sg:city":"Rotherham",
    "sg:classifiers":[
        {
            "category":"Food & Beverages",
            "subcategory":"Meat & Fish",
            "type":"Retail Goods"
        }
    ],
    "sg:postcode":"S65 1JQ",
    "sg:province":"South Yorkshire",
    "sg:tags":[
        "butcher"
    ],
    "wof:name":"J T Hill & Son",
    "wof:placetype":"venue"
},
  "geometry": {"coordinates":[-1.35458,53.43214],"type":"Point"}
}