{
  "type": "Feature",
  "properties": {
    "iso:country":"GB",
    "sg:address":"Marine Parade",
    "sg:city":"Seaford",
    "sg:classifiers":[
        {
            "category":"Social Services",
            "subcategory":"Adult Care",
            "type":"Services"
        }
    ],
    "sg:phone":"+44 1323 490700",
    "sg:postcode":"BN25 2PN",
    "sg:province":"East Sussex",
    "sg:tags":[
        "housing",
        "sheltered"
    ],
    "wof:name":"Merryfield Court",
    "wof:placetype":"venue"
},
  "geometry": {"coordinates":[0.0829719976,50.7822647095],"type":"Point"}
}