{
  "type": "Feature",
  "properties": {
    "addr:full":"85 Stonnall Road, Aldridge Walsall Staffordshire WS9 8JZ",
    "addr:housenumber":"85",
    "addr:postcode":"ws9 8jz",
    "addr:street":"Stonnall Road",
    "iso:country":"GB",
    "sg:address":"85 Stonnall Road, Aldridge",
    "sg:city":"Walsall",
    "sg:classifiers":[
        {
            "category":"Government",
            "subcategory":"Police Station",
            "type":"Public Place"
        },
        {
            "category":"Travel",
            "subcategory":"Hostel",
            "type":"Entertainment"
        },
        {
            "category":"Government",
            "subcategory":"Office",
            "type":"Public Place"
        }
    ],
    "sg:phone":"+44 1922 459574",
    "sg:postcode":"WS9 8JZ",
    "sg:province":"Staffordshire",
    "sg:tags":[
        "support",
        "central"
    ],
    "wof:name":"Stonnall Road Probation Hostel",
    "wof:placetype":"venue"
},
  "geometry": {"coordinates":[-1.9072669744,52.6137504578],"type":"Point"}
}