{
  "type": "Feature",
  "properties": {
    "addr:full":"133 Station Road Ellon Aberdeenshire AB41 9AZ",
    "addr:housenumber":"133",
    "addr:postcode":"ab41 9az",
    "addr:street":"Station Road",
    "iso:country":"GB",
    "sg:address":"133 Station Road",
    "sg:city":"Ellon",
    "sg:classifiers":[
        {
            "category":"Building & Trades",
            "subcategory":"Plumbing",
            "type":"Services"
        }
    ],
    "sg:phone":"+44 1358 720979",
    "sg:postcode":"AB41 9AZ",
    "sg:province":"Aberdeenshire",
    "sg:tags":[
        "heating"
    ],
    "wof:name":"William J Clubb",
    "wof:placetype":"venue"
},
  "geometry": {"coordinates":[-2.08774,57.366302],"type":"Point"}
}