{
  "type": "Feature",
  "properties": {
    "addr:full":"Romford Street Burnley Lancashire BB12 8AF",
    "addr:postcode":"bb12 8af",
    "addr:street":"Romford Street",
    "iso:country":"GB",
    "sg:address":"Romford Street",
    "sg:city":"Burnley",
    "sg:classifiers":[
        {
            "category":"Education",
            "subcategory":"Library",
            "type":"Public Place"
        },
        {
            "category":"Sports & Exercise",
            "subcategory":"Bowling",
            "type":"Entertainment"
        }
    ],
    "sg:phone":"+44 1282 414188",
    "sg:postcode":"BB12 8AF",
    "sg:province":"Lancashire",
    "wof:name":"The Ighten Mount Bowling Club Ltd.",
    "wof:placetype":"venue"
},
  "geometry": {"coordinates":[-2.2703990936,53.7943649292],"type":"Point"}
}