{
  "type": "Feature",
  "properties": {
    "iso:country":"GB",
    "sg:address":"Elms Farm, Storden Lane, Thringstone",
    "sg:city":"Leicester",
    "sg:classifiers":[
        {
            "category":"Farming",
            "subcategory":"Livestock Farm",
            "type":"Manufacturing & Wholesale Goods"
        }
    ],
    "sg:postcode":"LE67 8US",
    "sg:province":"Leicestershire",
    "sg:tags":[
        "others"
    ],
    "wof:name":"B & A J Elson & Son",
    "wof:placetype":"venue"
},
  "geometry": {"coordinates":[-1.3728640079,52.7602958679],"type":"Point"}
}