{
  "type": "Feature",
  "properties": {
    "iso:country":"GB",
    "sg:address":"Amberley Farm, Bishopstone La",
    "sg:city":"Haywards Heath",
    "sg:classifiers":[
        {
            "category":"Farming",
            "subcategory":"Livestock Farm",
            "type":"Manufacturing & Wholesale Goods"
        }
    ],
    "sg:phone":"+44 1444 454491",
    "sg:postcode":"RH17 5AR",
    "sg:province":"East Sussex",
    "sg:tags":[
        "others"
    ],
    "wof:name":"A G Brown",
    "wof:placetype":"venue"
},
  "geometry": {"coordinates":[-0.17015,50.981998],"type":"Point"}
}