{
  "type": "Feature",
  "properties": {
    "addr:full":"22 Halley Street Bacup Lancashire OL13 8QF",
    "addr:housenumber":"22",
    "addr:postcode":"ol13 8qf",
    "addr:street":"Halley Street",
    "iso:country":"GB",
    "sg:address":"22 Halley Street",
    "sg:city":"Bacup",
    "sg:classifiers":[
        {
            "category":"Building & Trades",
            "subcategory":"Plumbing",
            "type":"Services"
        }
    ],
    "sg:postcode":"OL13 8QF",
    "sg:province":"Lancashire",
    "sg:tags":[
        "heating"
    ],
    "wof:name":"Wilson's Heating Services",
    "wof:placetype":"venue"
},
  "geometry": {"coordinates":[-2.197732,53.723537],"type":"Point"}
}