{
  "type": "Feature",
  "properties": {
    "iso:country":"GB",
    "sg:address":"142 Chesterfield Road North",
    "sg:city":"Mansfield",
    "sg:classifiers":[
        {
            "category":"Banks & Credit Unions",
            "subcategory":"Financial Services",
            "type":"Services"
        }
    ],
    "sg:phone":"+44 1623 633008",
    "sg:postcode":"NG19 7JD",
    "sg:province":"Derbyshire",
    "sg:tags":[
        "cashing",
        "cheque"
    ],
    "wof:name":"Sovereign Pawnbrokers",
    "wof:placetype":"venue"
},
  "geometry": {"coordinates":[-1.223176,53.159805],"type":"Point"}
}