{
  "type": "Feature",
  "properties": {
    "addr:full":"55 Cromwell Road, Forest Gate London Greater London E7 8PA",
    "addr:housenumber":"55",
    "addr:postcode":"e7 8pa",
    "addr:street":"Cromwell Road",
    "iso:country":"GB",
    "sg:address":"55 Cromwell Road, Forest Gate",
    "sg:city":"London",
    "sg:classifiers":[
        {
            "category":"Building & Trades",
            "subcategory":"Plumbing",
            "type":"Services"
        }
    ],
    "sg:phone":"+44 20 8475 0125",
    "sg:postcode":"E7 8PA",
    "sg:province":"Greater London",
    "sg:tags":[
        "central",
        "heating"
    ],
    "wof:name":"Heatarama",
    "wof:placetype":"venue"
},
  "geometry": {"coordinates":[0.034749,51.540321],"type":"Point"}
}