{
  "type": "Feature",
  "properties": {
    "addr:full":"2 Watnall Road Nottingham Nottinghamshire NG15 7LE",
    "addr:housenumber":"2",
    "addr:postcode":"ng15 7le",
    "addr:street":"Watnall Road",
    "iso:country":"GB",
    "sg:address":"2 Watnall Road",
    "sg:city":"Nottingham",
    "sg:classifiers":[
        {
            "category":"Farming",
            "subcategory":"Fish & Marine Products",
            "type":"Manufacturing & Wholesale Goods"
        },
        {
            "category":"Food & Beverages",
            "subcategory":"Liquor & Beverages",
            "type":"Retail Goods"
        }
    ],
    "sg:phone":"+44 115 963 2950",
    "sg:postcode":"NG15 7LE",
    "sg:province":"Nottinghamshire",
    "sg:tags":[
        "fishmonger",
        "beer",
        "spirit",
        "wines"
    ],
    "wof:name":"Hedley Wright & Co.",
    "wof:placetype":"venue"
},
  "geometry": {"coordinates":[-1.2027180195,53.0378913879],"type":"Point"}
}