{
  "type": "Feature",
  "properties": {
    "iso:country":"GB",
    "sg:address":"High Street, Ramsbury",
    "sg:city":"Marlborough",
    "sg:classifiers":[
        {
            "category":"Education",
            "subcategory":"Library",
            "type":"Public Place"
        }
    ],
    "sg:phone":"+44 1672 520364",
    "sg:postcode":"SN8 2QP",
    "sg:province":"Berkshire",
    "sg:tags":[
        "book"
    ],
    "wof:name":"Ramsbury Library",
    "wof:placetype":"venue"
},
  "geometry": {"coordinates":[-1.6109950542,51.4419822693],"type":"Point"}
}