{
  "type": "Feature",
  "properties": {
    "addr:full":"80 South Street Dorking Surrey RH4 2HE",
    "addr:housenumber":"80",
    "addr:postcode":"rh4 2he",
    "addr:street":"South Street",
    "iso:country":"GB",
    "sg:address":"80 South Street",
    "sg:city":"Dorking",
    "sg:classifiers":[
        {
            "category":"Communications",
            "subcategory":"Newspaper",
            "type":"Services"
        }
    ],
    "sg:phone":"+44 1306 886661",
    "sg:postcode":"RH4 2HE",
    "sg:province":"Surrey",
    "sg:tags":[
        "magazine"
    ],
    "wof:name":"Dorking Advertiser",
    "wof:placetype":"venue"
},
  "geometry": {"coordinates":[-0.3271529973,51.223274231],"type":"Point"}
}