{
  "type": "Feature",
  "properties": {
    "iso:country":"GB",
    "sg:address":"44 Stanhope Road, Wigston Magna",
    "sg:city":"Wigston",
    "sg:classifiers":[
        {
            "category":"Building & Trades",
            "subcategory":"Construction",
            "type":"Services"
        }
    ],
    "sg:postcode":"LE18 3SJ",
    "sg:province":"Leicestershire",
    "sg:tags":[
        "builder"
    ],
    "wof:name":"Wright Bros",
    "wof:placetype":"venue"
},
  "geometry": {"coordinates":[-1.099032,52.578259],"type":"Point"}
}