{
  "type": "Feature",
  "properties": {
    "addr:full":"21 Glebe Farm Road Birmingham West Midlands B33 9LY",
    "addr:housenumber":"21",
    "addr:postcode":"b33 9ly",
    "addr:street":"Glebe Farm Road",
    "iso:country":"GB",
    "sg:address":"21 Glebe Farm Road",
    "sg:city":"Birmingham",
    "sg:classifiers":[
        {
            "category":"Health Services",
            "subcategory":"Dentist",
            "type":"Services"
        }
    ],
    "sg:postcode":"B33 9LY",
    "sg:province":"West Midlands",
    "wof:name":"Glebe Farm Dental Practice",
    "wof:placetype":"venue"
},
  "geometry": {"coordinates":[-1.793342948,52.4877700806],"type":"Point"}
}