{
  "type": "Feature",
  "properties": {
    "iso:country":"GB",
    "sg:address":"Norden Farm, Harwood Road, Rishton",
    "sg:city":"Blackburn",
    "sg:classifiers":[
        {
            "category":"Farming",
            "subcategory":"Dairy Farm",
            "type":"Manufacturing & Wholesale Goods"
        }
    ],
    "sg:phone":"+44 1254 888704",
    "sg:postcode":"BB1 4AL",
    "sg:province":"Lancashire",
    "sg:tags":[
        "farmer"
    ],
    "wof:name":"J A England",
    "wof:placetype":"venue"
},
  "geometry": {"coordinates":[-2.417644,53.768017],"type":"Point"}
}