{
  "type": "Feature",
  "properties": {
    "iso:country":"GB",
    "sg:address":"Morebath Road Garage, Shillingford",
    "sg:city":"Tiverton",
    "sg:classifiers":[
        {
            "category":"Retail",
            "subcategory":"Auto Repair",
            "type":"Services"
        }
    ],
    "sg:postcode":"EX16 9AU",
    "sg:province":"Devon",
    "sg:tags":[
        "modification",
        "garage"
    ],
    "wof:name":"Lawrence Cann",
    "wof:placetype":"venue"
},
  "geometry": {"coordinates":[-3.490803957,51.0139465332],"type":"Point"}
}