{
  "type": "Feature",
  "properties": {
    "iso:country":"GB",
    "sg:address":"22 Main Street, Renton",
    "sg:city":"Dumbarton",
    "sg:classifiers":[
        {
            "category":"Professional",
            "subcategory":"Accounting & Tax Preparation",
            "type":"Services"
        }
    ],
    "sg:phone":"+44 1389 710858",
    "sg:postcode":"G82 4LY",
    "sg:province":"Argyll and Bute",
    "sg:tags":[
        "accountant",
        "activity"
    ],
    "wof:name":"McLellan & Co",
    "wof:placetype":"venue"
},
  "geometry": {"coordinates":[-4.583825,55.969208],"type":"Point"}
}