{
  "type": "Feature",
  "properties": {
    "addr:full":"The Park Business Centre, Kilburn Park Road London Greater London NW6 5LF",
    "addr:postcode":"nw6 5lf",
    "addr:street":"Kilburn Park Road",
    "iso:country":"GB",
    "sg:address":"The Park Business Centre, Kilburn Park Road",
    "sg:city":"London",
    "sg:classifiers":[
        {
            "category":"Retail",
            "subcategory":"Driving School",
            "type":"Services"
        }
    ],
    "sg:phone":"+44 20 7372 4222",
    "sg:postcode":"NW6 5LF",
    "sg:province":"Greater London",
    "wof:name":"London & Suburbs School of Motoring",
    "wof:placetype":"venue"
},
  "geometry": {"coordinates":[-0.19567,51.52911],"type":"Point"}
}