{
  "type": "Feature",
  "properties": {
    "addr:full":"11 Weston Rd, Southend-on-sea Essex SS1 1AS",
    "addr:housenumber":"11",
    "addr:postcode":"ss1 1as",
    "addr:street":"Weston Rd",
    "iso:country":"GB",
    "sg:address":"11 Weston Rd,",
    "sg:city":"Southend-on-sea",
    "sg:classifiers":[
        {
            "category":"Fast Food",
            "type":"Food & Drink"
        }
    ],
    "sg:postcode":"SS1 1AS",
    "sg:province":"Essex",
    "sg:tags":[
        "away",
        "take"
    ],
    "wof:name":"Goodbest Ltd",
    "wof:placetype":"venue"
},
  "geometry": {"coordinates":[0.712821,51.536259],"type":"Point"}
}