{
  "type": "Feature",
  "properties": {
    "addr:full":"8 Chartwell Road, Churchill Industrial Estate Lancing West Sussex BN15 8TY",
    "addr:housenumber":"8",
    "addr:postcode":"bn15 8ty",
    "addr:street":"Chartwell Road;Estate",
    "iso:country":"GB",
    "sg:address":"8 Chartwell Road, Churchill Industrial Estate",
    "sg:city":"Lancing",
    "sg:classifiers":[
        {
            "category":"Wholesale",
            "subcategory":"Construction Materials",
            "type":"Manufacturing & Wholesale Goods"
        }
    ],
    "sg:phone":"+44 1903 762272",
    "sg:postcode":"BN15 8TY",
    "sg:province":"West Sussex",
    "sg:tags":[
        "distributor",
        "spring"
    ],
    "wof:name":"Sperry Springs (Sussex) Ltd.",
    "wof:placetype":"venue"
},
  "geometry": {"coordinates":[-0.318039,50.8218994141],"type":"Point"}
}