{
  "type": "Feature",
  "properties": {
    "addr:full":"Alby Craft Centre, Cromer Rd, Erpingham Norwich Norfolk NR11 7QE",
    "addr:postcode":"nr11 7qe",
    "addr:street":"Cromer Rd;Norwich",
    "iso:country":"GB",
    "sg:address":"Alby Craft Centre, Cromer Rd, Erpingham",
    "sg:city":"Norwich",
    "sg:classifiers":[
        {
            "category":"Home & Garden",
            "subcategory":"Home Furnishings",
            "type":"Retail Goods"
        }
    ],
    "sg:phone":"+44 1263 768060",
    "sg:postcode":"NR11 7QE",
    "sg:province":"Norfolk",
    "sg:tags":[
        "homefurnishings"
    ],
    "wof:name":"Charles Matts",
    "wof:placetype":"venue"
},
  "geometry": {"coordinates":[1.2510900497,52.840259552],"type":"Point"}
}