{
  "type": "Feature",
  "properties": {
    "addr:full":"188 Beaumont Rd Birmingham West Midlands B30 1NY",
    "addr:housenumber":"188",
    "addr:postcode":"b30 1ny",
    "addr:street":"Beaumont Rd",
    "iso:country":"GB",
    "sg:address":"188 Beaumont Rd",
    "sg:city":"Birmingham",
    "sg:classifiers":[
        {
            "category":"Retail",
            "subcategory":"Driving School",
            "type":"Services"
        }
    ],
    "sg:phone":"+44 121 451 1221",
    "sg:postcode":"B30 1NY",
    "sg:province":"West Midlands",
    "wof:name":"Noviss School of Motoring",
    "wof:placetype":"venue"
},
  "geometry": {"coordinates":[-1.9355540276,52.4232444763],"type":"Point"}
}