{
  "type": "Feature",
  "properties": {
    "iso:country":"GB",
    "sg:address":"Bath Street",
    "sg:city":"Nelson",
    "sg:classifiers":[
        {
            "category":"Retail",
            "subcategory":"Auto Repair",
            "type":"Services"
        }
    ],
    "sg:phone":"+44 1282 698240",
    "sg:postcode":"BB9 0NN",
    "sg:province":"Lancashire",
    "sg:tags":[
        "body",
        "garage",
        "modification",
        "car"
    ],
    "wof:name":"Robert J Reeve Auto Bodies",
    "wof:placetype":"venue"
},
  "geometry": {"coordinates":[-2.199569,53.835644],"type":"Point"}
}