{
  "type": "Feature",
  "properties": {
    "addr:full":"40 Carr Lane Wigan Lancashire WN3 5ND",
    "addr:housenumber":"40",
    "addr:postcode":"wn3 5nd",
    "addr:street":"Carr Lane",
    "iso:country":"GB",
    "sg:address":"40 Carr Lane",
    "sg:city":"Wigan",
    "sg:classifiers":[
        {
            "category":"Fast Food",
            "type":"Food & Drink"
        }
    ],
    "sg:phone":"+44 1942 244471",
    "sg:postcode":"WN3 5ND",
    "sg:province":"Lancashire",
    "sg:tags":[
        "away",
        "take"
    ],
    "wof:name":"A Little Chippy",
    "wof:placetype":"venue"
},
  "geometry": {"coordinates":[-2.642399,53.52396],"type":"Point"}
}