{
  "type": "Feature",
  "properties": {
    "addr:full":"20 Manchester Square London Greater London SW1P 3JF",
    "addr:housenumber":"20",
    "addr:postcode":"sw1p 3jf",
    "addr:street":"Manchester Square",
    "iso:country":"GB",
    "sg:address":"20 Manchester Square",
    "sg:city":"London",
    "sg:classifiers":[
        {
            "category":"Military Area",
            "subcategory":"Air Force Base",
            "type":"Public Place"
        }
    ],
    "sg:phone":"+44 20 7834 4444",
    "sg:postcode":"SW1P 3JF",
    "sg:province":"Greater London",
    "sg:tags":[
        "ftse"
    ],
    "wof:name":"Imperial Chemical Industries Plc",
    "wof:placetype":"venue"
},
  "geometry": {"coordinates":[-0.1533000022,51.5169563293],"type":"Point"}
}