{
  "type": "Feature",
  "properties": {
    "iso:country":"GB",
    "sg:address":"51 Mountview Court, Green Lanes",
    "sg:city":"London",
    "sg:classifiers":[
        {
            "category":"Banks & Credit Unions",
            "subcategory":"Financial Services",
            "type":"Services"
        }
    ],
    "sg:postcode":"N8 0SH",
    "sg:province":"Greater London",
    "sg:tags":[
        "consultant"
    ],
    "wof:name":"Big Deals Investment Ltd",
    "wof:placetype":"venue"
},
  "geometry": {"coordinates":[-0.09986,51.58646],"type":"Point"}
}