{
  "type": "Feature",
  "properties": {
    "iso:country":"GB",
    "sg:address":"611a Lea Bridge Road, Leyton",
    "sg:city":"London",
    "sg:classifiers":[
        {
            "category":"Fast Food",
            "type":"Food & Drink"
        }
    ],
    "sg:phone":"+44 20 8520 5666",
    "sg:postcode":"E10 6AJ",
    "sg:province":"Greater London",
    "sg:tags":[
        "away",
        "meal",
        "outlet",
        "take"
    ],
    "sg:website":"http://www.favorite.co.uk",
    "wof:name":"Favorite Fried Chicken Ltd",
    "wof:placetype":"venue"
},
  "geometry": {"coordinates":[-0.011399,51.576561],"type":"Point"}
}