{
  "type": "Feature",
  "properties": {
    "addr:full":"12a Boultons La Redditch Warwickshire B97 5NY",
    "addr:housenumber":"12a",
    "addr:postcode":"b97 5ny",
    "addr:street":"Boultons La",
    "iso:country":"GB",
    "sg:address":"12a Boultons La",
    "sg:city":"Redditch",
    "sg:classifiers":[
        {
            "category":"Building & Trades",
            "subcategory":"Construction",
            "type":"Services"
        }
    ],
    "sg:phone":"+44 1527 542708",
    "sg:postcode":"B97 5NY",
    "sg:province":"Warwickshire",
    "sg:tags":[
        "builder"
    ],
    "wof:name":"H Boot",
    "wof:placetype":"venue"
},
  "geometry": {"coordinates":[-1.948029,52.280209],"type":"Point"}
}