{
  "type": "Feature",
  "properties": {
    "iso:country":"GB",
    "sg:address":"Boasts Industrial Estate, College Lane",
    "sg:city":"Beccles",
    "sg:classifiers":[
        {
            "category":"Wholesale",
            "subcategory":"Construction Materials",
            "type":"Manufacturing & Wholesale Goods"
        }
    ],
    "sg:postcode":"NR34 7TF",
    "sg:province":"Norfolk",
    "sg:tags":[
        "merchant",
        "glass"
    ],
    "wof:name":"Ellough Glass",
    "wof:placetype":"venue"
},
  "geometry": {"coordinates":[1.596135,52.43935],"type":"Point"}
}