{
  "type": "Feature",
  "properties": {
    "addr:full":"2-4 Woods Lane, Ashton-in-makerfieldwoods Wigan Lancashire WN4 8TF",
    "addr:housenumber":"2-4",
    "addr:postcode":"wn4 8tf",
    "addr:street":"Woods Lane",
    "iso:country":"GB",
    "sg:address":"2-4 Woods Lane, Ashton-in-makerfieldwoods",
    "sg:city":"Wigan",
    "sg:classifiers":[
        {
            "category":"Freight",
            "type":"Transportation"
        }
    ],
    "sg:phone":"+44 1942 727368",
    "sg:postcode":"WN4 8TF",
    "sg:province":"Lancashire",
    "sg:tags":[
        "haulage",
        "road"
    ],
    "wof:name":"A B Little & Co. (Stubshaw Cross) Ltd.",
    "wof:placetype":"venue"
},
  "geometry": {"coordinates":[-2.62659,53.494591],"type":"Point"}
}