{
  "type": "Feature",
  "properties": {
    "addr:full":"35 Briar Bank, Lesmahagow Lanark South Lanarkshire ML11 0AT",
    "addr:housenumber":"35",
    "addr:postcode":"ml11 0at",
    "addr:street":"Briar Bank",
    "iso:country":"GB",
    "sg:address":"35 Briar Bank, Lesmahagow",
    "sg:city":"Lanark",
    "sg:classifiers":[
        {
            "category":"Taxi",
            "type":"Transportation"
        },
        {
            "category":"Military Area",
            "subcategory":"Air Force Base",
            "type":"Public Place"
        }
    ],
    "sg:phone":"+44 1555 894848",
    "sg:postcode":"ML11 0AT",
    "sg:province":"South Lanarkshire",
    "sg:tags":[
        "mini",
        "hire",
        "private",
        "cab"
    ],
    "wof:name":"Country Cabs",
    "wof:placetype":"venue"
},
  "geometry": {"coordinates":[-3.8779549599,55.6284828186],"type":"Point"}
}