{
  "type": "Feature",
  "properties": {
    "addr:full":"The Haven, Hampton Bishop Hereford Herefordshire HR1 4JR",
    "addr:postcode":"hr1 4jr",
    "iso:country":"GB",
    "sg:address":"The Haven, Hampton Bishop",
    "sg:city":"Hereford",
    "sg:classifiers":[
        {
            "category":"Building & Trades",
            "subcategory":"Construction",
            "type":"Services"
        }
    ],
    "sg:postcode":"HR1 4JR",
    "sg:province":"Herefordshire",
    "sg:tags":[
        "flooring"
    ],
    "wof:name":"Arthur Jones",
    "wof:placetype":"venue"
},
  "geometry": {"coordinates":[-2.6439790726,52.0380897522],"type":"Point"}
}