{
  "type": "Feature",
  "properties": {
    "addr:full":"Springfield Ho, 88 Clare Rd Great Missenden Buckinghamshire HP16 0NU",
    "addr:housenumber":"88",
    "addr:postcode":"hp16 0nu",
    "addr:street":"Clare Rd",
    "iso:country":"GB",
    "sg:address":"Springfield Ho, 88 Clare Rd",
    "sg:city":"Great Missenden",
    "sg:classifiers":[
        {
            "category":"Professional",
            "subcategory":"Accounting & Tax Preparation",
            "type":"Services"
        }
    ],
    "sg:phone":"+44 1494 891086",
    "sg:postcode":"HP16 0NU",
    "sg:province":"Buckinghamshire",
    "sg:tags":[
        "accountant"
    ],
    "wof:name":"Counting House The",
    "wof:placetype":"venue"
},
  "geometry": {"coordinates":[-0.709043,51.704067],"type":"Point"}
}