{
  "type": "Feature",
  "properties": {
    "addr:full":"Airdrie Road, Caldercruix Airdrie North Lanarkshire ML6 8PA",
    "addr:postcode":"ml6 8pa",
    "addr:street":"Airdrie Road",
    "iso:country":"GB",
    "sg:address":"Airdrie Road, Caldercruix",
    "sg:city":"Airdrie",
    "sg:classifiers":[
        {
            "category":"Farming",
            "subcategory":"Dairy Farm",
            "type":"Manufacturing & Wholesale Goods"
        }
    ],
    "sg:phone":"+44 1236 842294",
    "sg:postcode":"ML6 8PA",
    "sg:province":"North Lanarkshire",
    "wof:name":"D & J Black",
    "wof:placetype":"venue"
},
  "geometry": {"coordinates":[-3.8920440674,55.8861465454],"type":"Point"}
}