{
  "type": "Feature",
  "properties": {
    "iso:country":"GB",
    "sg:address":"Heath Farm, Boundary Lane, Hundred End",
    "sg:city":"Preston",
    "sg:classifiers":[
        {
            "category":"Food & Beverages",
            "subcategory":"Farmers Market",
            "type":"Retail Goods"
        }
    ],
    "sg:postcode":"PR4 6XE",
    "sg:province":"Lancashire",
    "sg:tags":[
        "gardener"
    ],
    "wof:name":"M J Bond",
    "wof:placetype":"venue"
},
  "geometry": {"coordinates":[-2.881259,53.691132],"type":"Point"}
}