{
  "type": "Feature",
  "properties": {
    "iso:country":"GB",
    "sg:address":"North Farm, Sheepdrove Hill",
    "sg:city":"Newbury",
    "sg:classifiers":[
        {
            "category":"Farming",
            "subcategory":"Livestock Farm",
            "type":"Manufacturing & Wholesale Goods"
        }
    ],
    "sg:phone":"+44 1488 71376",
    "sg:postcode":"RG17 8YL",
    "sg:province":"Berkshire",
    "sg:tags":[
        "others"
    ],
    "wof:name":"J Radbourne",
    "wof:placetype":"venue"
},
  "geometry": {"coordinates":[-1.52548,51.510899],"type":"Point"}
}