{
  "type": "Feature",
  "properties": {
    "iso:country":"GB",
    "sg:address":"43 High Street",
    "sg:city":"Selkirk",
    "sg:classifiers":[
        {
            "category":"Sports & Exercise",
            "subcategory":"Sports Center",
            "type":"Entertainment"
        }
    ],
    "sg:postcode":"TD7 4BZ",
    "sg:province":"Scottish Borders",
    "sg:tags":[
        "shop",
        "good"
    ],
    "wof:name":"Thomas Dickson & Sons",
    "wof:placetype":"venue"
},
  "geometry": {"coordinates":[-2.840375,55.548233],"type":"Point"}
}