{
  "type": "Feature",
  "properties": {
    "iso:country":"GB",
    "sg:address":"104 Tarbock Road, Huyton",
    "sg:city":"Liverpool",
    "sg:classifiers":[
        {
            "category":"Health Services",
            "subcategory":"Doctor",
            "type":"Services"
        }
    ],
    "sg:phone":"+44 151 489 1444",
    "sg:postcode":"L36 5TH",
    "sg:province":"Merseyside",
    "sg:tags":[
        "practitioners"
    ],
    "wof:name":"S Singh",
    "wof:placetype":"venue"
},
  "geometry": {"coordinates":[-2.8421580791,53.4053001404],"type":"Point"}
}