{
  "type": "Feature",
  "properties": {
    "addr:full":"Appointments Only, Mergate Farm, Mergate La Norwich Norfolk NR14 8EW",
    "addr:postcode":"nr14 8ew",
    "addr:street":"Mergate;Mergate La Norwich",
    "iso:country":"GB",
    "sg:address":"Appointments Only, Mergate Farm, Mergate La",
    "sg:city":"Norwich",
    "sg:classifiers":[
        {
            "category":"Personal",
            "type":"Services"
        }
    ],
    "sg:phone":"+44 1508 570217",
    "sg:postcode":"NR14 8EW",
    "sg:province":"Norfolk",
    "sg:tags":[
        "wedding"
    ],
    "wof:name":"Dress Circle",
    "wof:placetype":"venue"
},
  "geometry": {"coordinates":[1.2948999405,52.6224937439],"type":"Point"}
}