{
  "type": "Feature",
  "properties": {
    "iso:country":"GB",
    "sg:address":"163 Manor Road",
    "sg:city":"Chigwell",
    "sg:classifiers":[
        {
            "category":"Shopping",
            "subcategory":"Gifts & Souvenirs",
            "type":"Retail Goods"
        },
        {
            "category":"Wholesale",
            "subcategory":"Toys & Hobbies",
            "type":"Manufacturing & Wholesale Goods"
        }
    ],
    "sg:postcode":"IG7 5QA",
    "sg:province":"Essex",
    "sg:tags":[
        "shop",
        "balloon",
        "novelty"
    ],
    "wof:name":"BALLOON CELLAR",
    "wof:placetype":"venue"
},
  "geometry": {"coordinates":[0.090359,51.612869],"type":"Point"}
}