{
  "type": "Feature",
  "properties": {
    "iso:country":"GB",
    "sg:address":"45 Station Road, Nassington",
    "sg:city":"Peterborough",
    "sg:classifiers":[
        {
            "category":"Building & Trades",
            "subcategory":"Construction",
            "type":"Services"
        }
    ],
    "sg:postcode":"PE8 6QB",
    "sg:province":"Cambridgeshire",
    "sg:tags":[
        "joiner",
        "carpenter"
    ],
    "wof:name":"R E Newton",
    "wof:placetype":"venue"
},
  "geometry": {"coordinates":[-0.42625,52.555431],"type":"Point"}
}