{
  "type": "Feature",
  "properties": {
    "iso:country":"GB",
    "sg:address":"Victoria Garage, Victoria Road",
    "sg:city":"Oswestry",
    "sg:classifiers":[
        {
            "category":"Autos & Motor Vehicles",
            "subcategory":"Automobile Sales",
            "type":"Retail Goods"
        }
    ],
    "sg:phone":"+44 1691 652413",
    "sg:postcode":"SY11 2HR",
    "sg:province":"Shropshire",
    "sg:tags":[
        "car"
    ],
    "wof:name":"A Beauclerk & Son",
    "wof:placetype":"venue"
},
  "geometry": {"coordinates":[-3.048089,52.863602],"type":"Point"}
}