{
  "type": "Feature",
  "properties": {
    "addr:full":"6-7 The Maltings, Mill Street Oakham Leicestershire LE15 6EA",
    "addr:housenumber":"6-7",
    "addr:postcode":"le15 6ea",
    "addr:street":"The Maltings Mill Street",
    "iso:country":"GB",
    "sg:address":"6-7 The Maltings, Mill Street",
    "sg:city":"Oakham",
    "sg:classifiers":[
        {
            "category":"Home & Garden",
            "subcategory":"Carpets & Floor Coverings",
            "type":"Retail Goods"
        },
        {
            "category":"Wholesale",
            "subcategory":"Furniture",
            "type":"Manufacturing & Wholesale Goods"
        },
        {
            "category":"Home & Garden",
            "subcategory":"Furniture",
            "type":"Retail Goods"
        }
    ],
    "sg:phone":"+44 1572 724441",
    "sg:postcode":"LE15 6EA",
    "sg:province":"Leicestershire",
    "sg:tags":[
        "carpets",
        "rug",
        "matting",
        "outlet"
    ],
    "wof:name":"Oakham Oriental Rugs",
    "wof:placetype":"venue"
},
  "geometry": {"coordinates":[-0.730749,52.669979],"type":"Point"}
}