{
  "type": "Feature",
  "properties": {
    "iso:country":"GB",
    "sg:address":"15 Blaen Y Coed, Castle View",
    "sg:city":"Cardiff",
    "sg:classifiers":[
        {
            "category":"Autos & Motor Vehicles",
            "subcategory":"Motorcycle Sales",
            "type":"Retail Goods"
        }
    ],
    "sg:postcode":"CF15 8RL",
    "sg:province":"Caerphilly",
    "sg:tags":[
        "chauffeur",
        "driven",
        "car"
    ],
    "wof:name":"J R C Chauffeur Hire",
    "wof:placetype":"venue"
},
  "geometry": {"coordinates":[-3.264969,51.520123],"type":"Point"}
}