{
  "type": "Feature",
  "properties": {
    "iso:country":"GB",
    "sg:address":"4-5 Queen Street",
    "sg:city":"Portsmouth",
    "sg:classifiers":[
        {
            "category":"Shopping",
            "subcategory":"Clothing, Apparel, & Fashions",
            "type":"Retail Goods"
        }
    ],
    "sg:phone":"+44 23 9273 6529",
    "sg:postcode":"PO1 3HL",
    "sg:province":"Hampshire",
    "sg:tags":[
        "staff",
        "wear",
        "uniform"
    ],
    "wof:name":"Louis Bernard",
    "wof:placetype":"venue"
},
  "geometry": {"coordinates":[-1.098121,50.799698],"type":"Point"}
}