{
  "type": "Feature",
  "properties": {
    "addr:full":"Bunfoot Camp Site Haltwhistle Northumberland NE49 0JP",
    "addr:postcode":"ne49 0jp",
    "addr:street":"Northumberland",
    "iso:country":"GB",
    "sg:address":"Bunfoot Camp Site",
    "sg:city":"Haltwhistle",
    "sg:classifiers":[
        {
            "category":"Recreation",
            "subcategory":"Campground",
            "type":"Entertainment"
        }
    ],
    "sg:phone":"+44 1434 320106",
    "sg:postcode":"NE49 0JP",
    "sg:province":"Northumberland",
    "sg:tags":[
        "site",
        "camping"
    ],
    "wof:name":"The Camping & Caravanning Club Ltd.",
    "wof:placetype":"venue"
},
  "geometry": {"coordinates":[-2.4644970894,54.9685935974],"type":"Point"}
}