{
  "type": "Feature",
  "properties": {
    "addr:full":"Fall Bank Indust Est Barnsley South Yorkshire S75 3LS",
    "addr:postcode":"s75 3ls",
    "addr:street":"Indust;Yorkshire",
    "iso:country":"GB",
    "sg:address":"Fall Bank Indust Est",
    "sg:city":"Barnsley",
    "sg:classifiers":[
        {
            "category":"Professional",
            "subcategory":"Computer Services",
            "type":"Services"
        }
    ],
    "sg:phone":"+44 1226 295880",
    "sg:postcode":"S75 3LS",
    "sg:province":"South Yorkshire",
    "sg:tags":[
        "system",
        "software"
    ],
    "wof:name":"Connectis",
    "wof:placetype":"venue"
},
  "geometry": {"coordinates":[-1.5348500013,53.5450668335],"type":"Point"}
}