{
  "type": "Feature",
  "properties": {
    "iso:country":"GB",
    "sg:address":"6 Cross Street",
    "sg:city":"Seaton",
    "sg:classifiers":[
        {
            "category":"Military Area",
            "subcategory":"Air Force Base",
            "type":"Public Place"
        }
    ],
    "sg:phone":"+44 1297 20038",
    "sg:postcode":"EX12 2LH",
    "sg:province":"Devon",
    "sg:tags":[
        "taxi",
        "hire",
        "private"
    ],
    "wof:name":"Clapps Taxis",
    "wof:placetype":"venue"
},
  "geometry": {"coordinates":[-3.0719089508,50.7055397034],"type":"Point"}
}