{
  "type": "Feature",
  "properties": {
    "addr:full":"The Community Mental Health Centre, 79 Buckingham Rd Brighton East Sussex BN1 3RJ",
    "addr:housenumber":"79",
    "addr:postcode":"bn1 3rj",
    "addr:street":"Buckingham Rd",
    "iso:country":"GB",
    "sg:address":"The Community Mental Health Centre, 79 Buckingham Rd",
    "sg:city":"Brighton",
    "sg:classifiers":[
        {
            "category":"Professional",
            "subcategory":"Lawyer & Legal Services",
            "type":"Services"
        }
    ],
    "sg:phone":"+44 1273 720110",
    "sg:postcode":"BN1 3RJ",
    "sg:province":"East Sussex",
    "sg:tags":[
        "advice",
        "counselling"
    ],
    "wof:name":"Survivor's Network",
    "wof:placetype":"venue"
},
  "geometry": {"coordinates":[-0.1440600008,50.8281517029],"type":"Point"}
}