{
  "type": "Feature",
  "properties": {
    "addr:full":"16 The Turnstones Watford Hertfordshire WD25 9SB",
    "addr:housenumber":"16",
    "addr:postcode":"wd25 9sb",
    "addr:street":"The Turnstones",
    "iso:country":"GB",
    "sg:address":"16 The Turnstones",
    "sg:city":"Watford",
    "sg:classifiers":[
        {
            "category":"Personal",
            "type":"Services"
        }
    ],
    "sg:postcode":"WD25 9SB",
    "sg:province":"Hertfordshire",
    "sg:tags":[
        "wedding"
    ],
    "wof:name":"White,Michael,",
    "wof:placetype":"venue"
},
  "geometry": {"coordinates":[-0.37859,51.680931],"type":"Point"}
}