{
  "type": "Feature",
  "properties": {
    "addr:full":"159 Leeward Circle, East Kilbride Glasgow South Lanarkshire G75 8PD",
    "addr:housenumber":"159",
    "addr:postcode":"g75 8pd",
    "addr:street":"Leeward Circle East",
    "iso:country":"GB",
    "sg:address":"159 Leeward Circle, East Kilbride",
    "sg:city":"Glasgow",
    "sg:classifiers":[
        {
            "category":"Personal",
            "subcategory":"Beauty Salon",
            "type":"Services"
        }
    ],
    "sg:phone":"+44 1355 238337",
    "sg:postcode":"G75 8PD",
    "sg:province":"South Lanarkshire",
    "sg:tags":[
        "unisex",
        "hairdresser"
    ],
    "wof:name":"Cleopatras Hair Studio",
    "wof:placetype":"venue"
},
  "geometry": {"coordinates":[-4.211951,55.760674],"type":"Point"}
}