{
  "type": "Feature",
  "properties": {
    "addr:full":"Estate Offices, Ludborough Grimsby Lincolnshire DN36 5SG",
    "addr:postcode":"dn36 5sg",
    "iso:country":"GB",
    "sg:address":"Estate Offices, Ludborough",
    "sg:city":"Grimsby",
    "sg:classifiers":[
        {
            "category":"Farming",
            "subcategory":"Livestock Farm",
            "type":"Manufacturing & Wholesale Goods"
        }
    ],
    "sg:phone":"+44 1472 840381",
    "sg:postcode":"DN36 5SG",
    "sg:province":"Lincolnshire",
    "sg:tags":[
        "others"
    ],
    "wof:name":"R Caudwell (Produce) Ltd.",
    "wof:placetype":"venue"
},
  "geometry": {"coordinates":[-0.0521779992,53.4403266907],"type":"Point"}
}