{
  "type": "Feature",
  "properties": {
    "addr:full":"30 Chesswick Crescent, Keadby Scunthorpe Lincolnshire DN17 3DQ",
    "addr:housenumber":"30",
    "addr:postcode":"dn17 3dq",
    "addr:street":"Chesswick Crescent",
    "iso:country":"GB",
    "sg:address":"30 Chesswick Crescent, Keadby",
    "sg:city":"Scunthorpe",
    "sg:classifiers":[
        {
            "category":"Bus Charters",
            "type":"Transportation"
        }
    ],
    "sg:phone":"+44 1724 782339",
    "sg:postcode":"DN17 3DQ",
    "sg:province":"Lincolnshire",
    "sg:tags":[
        "coach"
    ],
    "wof:name":"John Cranrdge",
    "wof:placetype":"venue"
},
  "geometry": {"coordinates":[-0.743616,53.587875],"type":"Point"}
}