{
  "type": "Feature",
  "properties": {
    "addr:full":"9 Paradise Sq Sheffield South Yorkshire S1 2DE",
    "addr:housenumber":"9",
    "addr:postcode":"s1 2de",
    "addr:street":"Paradise Sq",
    "iso:country":"GB",
    "sg:address":"9 Paradise Sq",
    "sg:city":"Sheffield",
    "sg:classifiers":[
        {
            "category":"Professional",
            "type":"Services"
        }
    ],
    "sg:phone":"+44 114 272 8728",
    "sg:postcode":"S1 2DE",
    "sg:province":"South Yorkshire",
    "sg:tags":[
        "auctioneer"
    ],
    "wof:name":"Phillips Incorporating Henry Spencer & Sons",
    "wof:placetype":"venue"
},
  "geometry": {"coordinates":[-1.470372,53.383884],"type":"Point"}
}