{
  "type": "Feature",
  "properties": {
    "addr:full":"Travers Yard, Silver Street South Petherton Somerset TA13 5BY",
    "addr:postcode":"ta13 5by",
    "addr:street":"Travers;Silver Street",
    "iso:country":"GB",
    "sg:address":"Travers Yard, Silver Street",
    "sg:city":"South Petherton",
    "sg:classifiers":[
        {
            "category":"Government",
            "subcategory":"Department Of Motor Vehicles",
            "type":"Public Place"
        },
        {
            "category":"Retail",
            "subcategory":"Auto Repair",
            "type":"Services"
        }
    ],
    "sg:phone":"+44 1460 241472",
    "sg:postcode":"TA13 5BY",
    "sg:province":"Somerset",
    "sg:tags":[
        "garage",
        "inspection",
        "related"
    ],
    "wof:name":"Western Engineering Services",
    "wof:placetype":"venue"
},
  "geometry": {"coordinates":[-2.805539,50.949532],"type":"Point"}
}