{
  "type": "Feature",
  "properties": {
    "iso:country":"GB",
    "sg:address":"Valentine Row",
    "sg:city":"Callington",
    "sg:classifiers":[
        {
            "category":"Retail",
            "subcategory":"Storage",
            "type":"Services"
        }
    ],
    "sg:phone":"+44 1579 383210",
    "sg:postcode":"PL17 7DH",
    "sg:province":"Cornwall",
    "sg:tags":[
        "household",
        "removal"
    ],
    "wof:name":"Callington Carriers",
    "wof:placetype":"venue"
},
  "geometry": {"coordinates":[-4.3104901314,50.5004081726],"type":"Point"}
}