{
  "type": "Feature",
  "properties": {
    "addr:full":"120 Union Road, Oswaldtwistle Accrington Lancashire BB5 3DR",
    "addr:housenumber":"120",
    "addr:postcode":"bb5 3dr",
    "addr:street":"Union Road;Accrington",
    "iso:country":"GB",
    "sg:address":"120 Union Road, Oswaldtwistle",
    "sg:city":"Accrington",
    "sg:classifiers":[
        {
            "category":"Autos & Motor Vehicles",
            "subcategory":"Auto Supplies",
            "type":"Retail Goods"
        },
        {
            "category":"Shopping",
            "type":"Retail Goods"
        }
    ],
    "sg:phone":"+44 1254 872692",
    "sg:postcode":"BB5 3DR",
    "sg:province":"Lancashire",
    "sg:tags":[
        "car",
        "part",
        "accessory"
    ],
    "wof:name":"Car Care",
    "wof:placetype":"venue"
},
  "geometry": {"coordinates":[-2.3932828903,53.7463722229],"type":"Point"}
}