{
  "type": "Feature",
  "properties": {
    "addr:full":"York Road, Deganwy Llandudno Junction Conwy LL31 9PX",
    "addr:postcode":"ll31 9px",
    "addr:street":"York Road",
    "iso:country":"GB",
    "sg:address":"York Road, Deganwy",
    "sg:city":"Llandudno Junction",
    "sg:classifiers":[
        {
            "category":"Building & Trades",
            "subcategory":"Construction",
            "type":"Services"
        }
    ],
    "sg:phone":"+44 1492 583217",
    "sg:postcode":"LL31 9PX",
    "sg:province":"Conwy",
    "sg:tags":[
        "decorator",
        "painter"
    ],
    "wof:name":"North Wales Coating Co",
    "wof:placetype":"venue"
},
  "geometry": {"coordinates":[-3.835829,53.296982],"type":"Point"}
}