{
  "type": "Feature",
  "properties": {
    "addr:full":"Underhill Farm, Winderton Banbury Oxfordshire OX15 5JF",
    "addr:postcode":"ox15 5jf",
    "addr:street":"Winderton",
    "iso:country":"GB",
    "sg:address":"Underhill Farm, Winderton",
    "sg:city":"Banbury",
    "sg:classifiers":[
        {
            "category":"Farming",
            "subcategory":"Farm",
            "type":"Manufacturing & Wholesale Goods"
        }
    ],
    "sg:phone":"+44 1608 685553",
    "sg:postcode":"OX15 5JF",
    "sg:province":"Oxfordshire",
    "sg:tags":[
        "mixed",
        "crop"
    ],
    "wof:name":"John W Walton",
    "wof:placetype":"venue"
},
  "geometry": {"coordinates":[-1.5244580507,52.0628662109],"type":"Point"}
}