{
  "type": "Feature",
  "properties": {
    "addr:full":"Unit 3a Roman Way, Glebe Farm Industrial Estate Rugby Warwickshire CV21 1DB",
    "addr:housenumber":"unit 3a;industrial estate",
    "addr:postcode":"cv21 1db",
    "addr:street":"Roman Way",
    "iso:country":"GB",
    "sg:address":"Unit 3a Roman Way, Glebe Farm Industrial Estate",
    "sg:city":"Rugby",
    "sg:classifiers":[
        {
            "category":"Professional",
            "subcategory":"Engineering",
            "type":"Services"
        }
    ],
    "sg:phone":"+44 1788 560522",
    "sg:postcode":"CV21 1DB",
    "sg:province":"Warwickshire",
    "sg:tags":[
        "precision",
        "engineer"
    ],
    "wof:name":"Technoset Ltd.",
    "wof:placetype":"venue"
},
  "geometry": {"coordinates":[-1.2639290094,52.3898735046],"type":"Point"}
}