{
  "type": "Feature",
  "properties": {
    "addr:full":"531 London Road Westcliff-on-sea Essex SS0 9LJ",
    "addr:housenumber":"531",
    "addr:postcode":"ss0 9lj",
    "addr:street":"London Road",
    "iso:country":"GB",
    "sg:address":"531 London Road",
    "sg:city":"Westcliff-on-sea",
    "sg:classifiers":[
        {
            "category":"Home & Garden",
            "subcategory":"Building Materials",
            "type":"Retail Goods"
        },
        {
            "category":"Home & Garden",
            "subcategory":"Furniture",
            "type":"Retail Goods"
        }
    ],
    "sg:phone":"+44 1702 333608",
    "sg:postcode":"SS0 9LJ",
    "sg:province":"Essex",
    "sg:tags":[
        "shutter",
        "door"
    ],
    "wof:name":"Classic Doors",
    "wof:placetype":"venue"
},
  "geometry": {"coordinates":[0.6892780066,51.5447502136],"type":"Point"}
}