{
  "type": "Feature",
  "properties": {
    "iso:country":"GB",
    "sg:address":"Mickle Hill Farm, Keyston",
    "sg:city":"Huntingdon",
    "sg:classifiers":[
        {
            "category":"Farming",
            "subcategory":"Livestock Farm",
            "type":"Manufacturing & Wholesale Goods"
        }
    ],
    "sg:phone":"+44 1832 710229",
    "sg:postcode":"PE28 0RQ",
    "sg:province":"Bedfordshire",
    "sg:tags":[
        "others"
    ],
    "wof:name":"P Mangan & Son",
    "wof:placetype":"venue"
},
  "geometry": {"coordinates":[-0.467355,52.365837],"type":"Point"}
}