{
  "type": "Feature",
  "properties": {
    "iso:country":"GB",
    "sg:address":"367 Charminster Road",
    "sg:city":"Bournemouth",
    "sg:classifiers":[
        {
            "category":"Shopping",
            "subcategory":"News",
            "type":"Retail Goods"
        }
    ],
    "sg:phone":"+44 1202 513096",
    "sg:postcode":"BH8 9QS",
    "sg:province":"Dorset",
    "sg:tags":[
        "newsagent"
    ],
    "wof:name":"Fiveways Newsagents",
    "wof:placetype":"venue"
},
  "geometry": {"coordinates":[-1.8617290258,50.7420005798],"type":"Point"}
}