{
  "type": "Feature",
  "properties": {
    "addr:full":"Salterhebble Hill Halifax West Yorkshire HX3 0QT",
    "addr:postcode":"hx3 0qt",
    "addr:street":"Salterhebble Hill",
    "iso:country":"GB",
    "sg:address":"Salterhebble Hill",
    "sg:city":"Halifax",
    "sg:classifiers":[
        {
            "category":"Travel",
            "subcategory":"Hotels & Motels",
            "type":"Entertainment"
        }
    ],
    "sg:phone":"+44 1422 347700",
    "sg:postcode":"HX3 0QT",
    "sg:province":"West Yorkshire",
    "wof:name":"Quays Premier Lodge",
    "wof:placetype":"venue"
},
  "geometry": {"coordinates":[-1.8532739878,53.7050666809],"type":"Point"}
}