{
  "type": "Feature",
  "properties": {
    "addr:full":"89 South Road Southall Greater London UB1 1SQ",
    "addr:housenumber":"89",
    "addr:postcode":"ub1 1sq",
    "addr:street":"South Road",
    "iso:country":"GB",
    "sg:address":"89 South Road",
    "sg:city":"Southall",
    "sg:classifiers":[
        {
            "category":"Health Services",
            "subcategory":"Dentist",
            "type":"Services"
        }
    ],
    "sg:postcode":"UB1 1SQ",
    "sg:province":"Greater London",
    "wof:name":"The Dental Referral Clinic",
    "wof:placetype":"venue"
},
  "geometry": {"coordinates":[-0.37794,51.507439],"type":"Point"}
}