{
  "type": "Feature",
  "properties": {
    "iso:country":"GB",
    "sg:address":"9 Westlands",
    "sg:city":"Worthing",
    "sg:classifiers":[
        {
            "category":"Retail",
            "subcategory":"Driving School",
            "type":"Services"
        }
    ],
    "sg:phone":"+44 1903 243913",
    "sg:postcode":"BN12 5JQ",
    "sg:province":"West Sussex",
    "wof:name":"Adept Driving Tuition",
    "wof:placetype":"venue"
},
  "geometry": {"coordinates":[-0.453795,50.811394],"type":"Point"}
}