{
  "type": "Feature",
  "properties": {
    "iso:country":"GB",
    "sg:address":"Sovereign House, Station Rd, Sulgrave",
    "sg:city":"Washington",
    "sg:classifiers":[
        {
            "category":"Utilities",
            "subcategory":"Telephone",
            "type":"Services"
        }
    ],
    "sg:phone":"+44 191 415 3828",
    "sg:postcode":"NE37 3AS",
    "sg:province":"Tyne and Wear",
    "sg:tags":[
        "telecommunication"
    ],
    "wof:name":"C D S TELECOM",
    "wof:placetype":"venue"
},
  "geometry": {"coordinates":[-1.510054,54.913185],"type":"Point"}
}