{
  "type": "Feature",
  "properties": {
    "addr:full":"4 Station Mews, Glovers Brow Liverpool Merseyside L32 2BR",
    "addr:housenumber":"4",
    "addr:postcode":"l32 2br",
    "addr:street":"Station Mews Glovers Brow",
    "iso:country":"GB",
    "sg:address":"4 Station Mews, Glovers Brow",
    "sg:city":"Liverpool",
    "sg:classifiers":[
        {
            "category":"Fast Food",
            "type":"Food & Drink"
        },
        {
            "category":"Food & Beverages",
            "subcategory":"Groceries & Convenience Stores",
            "type":"Retail Goods"
        }
    ],
    "sg:phone":"+44 151 548 4055",
    "sg:postcode":"L32 2BR",
    "sg:province":"Merseyside",
    "sg:tags":[
        "shop",
        "fish",
        "take",
        "chip",
        "away"
    ],
    "wof:name":"Ken's Takeaway",
    "wof:placetype":"venue"
},
  "geometry": {"coordinates":[-2.901534,53.487495],"type":"Point"}
}