{
  "type": "Feature",
  "properties": {
    "addr:full":"128 Whalley Rd Blackburn Lancashire BB6 8DD",
    "addr:housenumber":"128",
    "addr:postcode":"bb6 8dd",
    "addr:street":"Whalley Rd",
    "iso:country":"GB",
    "sg:address":"128 Whalley Rd",
    "sg:city":"Blackburn",
    "sg:classifiers":[
        {
            "category":"Government",
            "subcategory":"Police Station",
            "type":"Public Place"
        }
    ],
    "sg:phone":"+44 1254 248936",
    "sg:postcode":"BB6 8DD",
    "sg:province":"Lancashire",
    "sg:tags":[
        "support",
        "force"
    ],
    "wof:name":"Billington & Langho Police Sub Station",
    "wof:placetype":"venue"
},
  "geometry": {"coordinates":[-2.467169,53.792122],"type":"Point"}
}