{
  "type": "Feature",
  "properties": {
    "addr:full":"65 Byron St Hove East Sussex BN3 5BB",
    "addr:housenumber":"65",
    "addr:postcode":"bn3 5bb",
    "addr:street":"Byron St",
    "iso:country":"GB",
    "sg:address":"65 Byron St",
    "sg:city":"Hove",
    "sg:classifiers":[
        {
            "category":"Home & Garden",
            "subcategory":"Household Appliances",
            "type":"Retail Goods"
        }
    ],
    "sg:postcode":"BN3 5BB",
    "sg:province":"East Sussex",
    "sg:tags":[
        "electrical"
    ],
    "wof:name":"Millett,A, Domestic Electrics",
    "wof:placetype":"venue"
},
  "geometry": {"coordinates":[-0.1803500056,50.8347702026],"type":"Point"}
}