{
  "type": "Feature",
  "properties": {
    "iso:country":"GB",
    "sg:address":"80 Carr House Road",
    "sg:city":"Halifax",
    "sg:classifiers":[
        {
            "category":"Place Of Worship",
            "type":"Public Place"
        }
    ],
    "sg:postcode":"HX3 7RJ",
    "sg:province":"West Yorkshire",
    "wof:name":"Parish of St.Michael Shelf With St.Aidan Buttershaw",
    "wof:placetype":"venue"
},
  "geometry": {"coordinates":[-1.801659,53.757648],"type":"Point"}
}