{
  "type": "Feature",
  "properties": {
    "iso:country":"GB",
    "sg:address":"Gregorys Cottage, Ashcombe",
    "sg:city":"Dawlish",
    "sg:classifiers":[
        {
            "category":"Building & Trades",
            "subcategory":"Landscaping Services",
            "type":"Services"
        }
    ],
    "sg:postcode":"EX7 0QD",
    "sg:province":"Devon",
    "sg:tags":[
        "landscape",
        "contractor"
    ],
    "wof:name":"Rural Stonework",
    "wof:placetype":"venue"
},
  "geometry": {"coordinates":[-3.533079,50.605824],"type":"Point"}
}