{
  "type": "Feature",
  "properties": {
    "addr:full":"29 Newhailes Avenue Musselburgh City of Edinburgh EH21 6DW",
    "addr:housenumber":"29",
    "addr:postcode":"eh21 6dw",
    "addr:street":"Newhailes Avenue",
    "iso:country":"GB",
    "sg:address":"29 Newhailes Avenue",
    "sg:city":"Musselburgh",
    "sg:classifiers":[
        {
            "category":"Professional",
            "type":"Services"
        }
    ],
    "sg:phone":"+44 131 653 3635",
    "sg:postcode":"EH21 6DW",
    "sg:province":"City of Edinburgh",
    "sg:tags":[
        "reflexologists"
    ],
    "wof:name":"Julie A Hamilton BSc GSSR",
    "wof:placetype":"venue"
},
  "geometry": {"coordinates":[-3.068699,55.943993],"type":"Point"}
}