{
  "type": "Feature",
  "properties": {
    "addr:full":"91 Partridge Way Cirencester Gloucestershire GL7 1BH",
    "addr:housenumber":"91",
    "addr:postcode":"gl7 1bh",
    "addr:street":"Partridge Way",
    "iso:country":"GB",
    "sg:address":"91 Partridge Way",
    "sg:city":"Cirencester",
    "sg:classifiers":[
        {
            "category":"Manufacturing",
            "subcategory":"Petroleum Products",
            "type":"Manufacturing & Wholesale Goods"
        },
        {
            "category":"Building & Trades",
            "subcategory":"Construction",
            "type":"Services"
        }
    ],
    "sg:phone":"+44 1285 653974",
    "sg:postcode":"GL7 1BH",
    "sg:province":"Gloucestershire",
    "sg:tags":[
        "double",
        "glazing",
        "installers"
    ],
    "wof:name":"CIRENCESTER WINDOWS",
    "wof:placetype":"venue"
},
  "geometry": {"coordinates":[-1.9504560232,51.7165641785],"type":"Point"}
}