{
  "type": "Feature",
  "properties": {
    "iso:country":"GB",
    "sg:address":"Albion Wharf, Albion Street",
    "sg:city":"Manchester",
    "sg:classifiers":[
        {
            "category":"Professional",
            "subcategory":"Employment Agencies",
            "type":"Services"
        }
    ],
    "sg:phone":"+44 161 236 0001",
    "sg:postcode":"M1 5LN",
    "sg:province":"Greater Manchester",
    "sg:tags":[
        "consultant"
    ],
    "wof:name":"Soma International Recruitment",
    "wof:placetype":"venue"
},
  "geometry": {"coordinates":[-2.248071909,53.4744110107],"type":"Point"}
}