{
  "type": "Feature",
  "properties": {
    "addr:full":"38 High Street, Foxton Cambridge Cambridgeshire CB2 6RP",
    "addr:housenumber":"38",
    "addr:postcode":"cb2 6rp",
    "addr:street":"High Street",
    "iso:country":"GB",
    "sg:address":"38 High Street, Foxton",
    "sg:city":"Cambridge",
    "sg:classifiers":[
        {
            "category":"Government",
            "subcategory":"Post Office",
            "type":"Public Place"
        }
    ],
    "sg:postcode":"CB2 6RP",
    "sg:province":"Cambridgeshire",
    "wof:name":"Foxton Post Office",
    "wof:placetype":"venue"
},
  "geometry": {"coordinates":[0.05935,52.115143],"type":"Point"}
}