{
  "type": "Feature",
  "properties": {
    "iso:country":"GB",
    "sg:address":"14 Hartshill Rd",
    "sg:city":"Stoke-on-trent",
    "sg:classifiers":[
        {
            "category":"Home & Garden",
            "subcategory":"Kitchen Supply",
            "type":"Retail Goods"
        }
    ],
    "sg:postcode":"ST4 7QU",
    "sg:province":"Staffordshire",
    "sg:tags":[
        "glassware",
        "china"
    ],
    "wof:name":"Chadwick,Peter,",
    "wof:placetype":"venue"
},
  "geometry": {"coordinates":[-2.186975,53.005295],"type":"Point"}
}