{
  "type": "Feature",
  "properties": {
    "iso:country":"GB",
    "sg:address":"39 North Rd",
    "sg:city":"St Helens",
    "sg:classifiers":[
        {
            "category":"Bars & Pubs",
            "type":"Food & Drink"
        }
    ],
    "sg:postcode":"WA10 2TW",
    "sg:province":"Merseyside",
    "sg:tags":[
        "pubs",
        "inn"
    ],
    "wof:name":"Turner,William,",
    "wof:placetype":"venue"
},
  "geometry": {"coordinates":[-2.739538,53.456776],"type":"Point"}
}