{
  "type": "Feature",
  "properties": {
    "iso:country":"GB",
    "sg:address":"Hyde Woods, Hyde",
    "sg:city":"Wareham",
    "sg:classifiers":[
        {
            "category":"Professional",
            "subcategory":"Computer Services",
            "type":"Services"
        }
    ],
    "sg:phone":"+44 70 1070 0427",
    "sg:postcode":"BH20 7NT",
    "sg:province":"Dorset",
    "sg:tags":[
        "consultant"
    ],
    "wof:name":"Good Business Practices Ltd.",
    "wof:placetype":"venue"
},
  "geometry": {"coordinates":[-2.181664,50.716805],"type":"Point"}
}