{
  "type": "Feature",
  "properties": {
    "iso:country":"GB",
    "sg:address":"46 Long Lane",
    "sg:city":"Halesowen",
    "sg:classifiers":[
        {
            "category":"Shopping",
            "subcategory":"Clothing, Apparel, & Fashions",
            "type":"Retail Goods"
        }
    ],
    "sg:phone":"+44 121 559 4095",
    "sg:postcode":"B62 9LS",
    "sg:province":"West Midlands",
    "sg:tags":[
        "lingerie"
    ],
    "wof:name":"R S Hosiery Wholesales",
    "wof:placetype":"venue"
},
  "geometry": {"coordinates":[-2.034669,52.471638],"type":"Point"}
}