{
  "type": "Feature",
  "properties": {
    "iso:country":"GB",
    "sg:address":"9 King St",
    "sg:city":"Wallasey",
    "sg:classifiers":[
        {
            "category":"Health Services",
            "subcategory":"Doctor",
            "type":"Services"
        }
    ],
    "sg:phone":"+44 151 639 6999",
    "sg:postcode":"L44 8AT",
    "sg:province":"Merseyside",
    "sg:tags":[
        "practitioners"
    ],
    "wof:name":"Egremont Medical Centre",
    "wof:placetype":"venue"
},
  "geometry": {"coordinates":[-3.026738,53.418316],"type":"Point"}
}