{
  "type": "Feature",
  "properties": {
    "addr:full":"43-44 North Bar St Banbury Oxfordshire OX16 0TH",
    "addr:housenumber":"43-44",
    "addr:postcode":"ox16 0th",
    "addr:street":"North Bar St",
    "iso:country":"GB",
    "sg:address":"43-44 North Bar St",
    "sg:city":"Banbury",
    "sg:classifiers":[
        {
            "category":"Professional",
            "subcategory":"Computer Services",
            "type":"Services"
        }
    ],
    "sg:phone":"+44 1295 258335",
    "sg:postcode":"OX16 0TH",
    "sg:province":"Oxfordshire",
    "sg:tags":[
        "system",
        "software"
    ],
    "wof:name":"Digital Workshop",
    "wof:placetype":"venue"
},
  "geometry": {"coordinates":[-1.3393479586,52.0628585815],"type":"Point"}
}