{
  "type": "Feature",
  "properties": {
    "addr:full":"Tudor House Farm, Church Lane, Kirk Langley Ashbourne Derbyshire DE6 4NG",
    "addr:postcode":"de6 4ng",
    "addr:street":"Church Lane",
    "iso:country":"GB",
    "sg:address":"Tudor House Farm, Church Lane, Kirk Langley",
    "sg:city":"Ashbourne",
    "sg:classifiers":[
        {
            "category":"Farming",
            "subcategory":"Livestock Farm",
            "type":"Manufacturing & Wholesale Goods"
        },
        {
            "category":"Military Area",
            "subcategory":"Air Force Base",
            "type":"Public Place"
        }
    ],
    "sg:phone":"+44 1332 824216",
    "sg:postcode":"DE6 4NG",
    "sg:province":"Derbyshire",
    "sg:tags":[
        "ornamental",
        "production",
        "metalwork",
        "others"
    ],
    "wof:name":"G & M Spencer",
    "wof:placetype":"venue"
},
  "geometry": {"coordinates":[-1.5725280046,52.9467277527],"type":"Point"}
}