{
  "type": "Feature",
  "properties": {
    "addr:full":"14 Keswick Gardens, Woodley Reading Berkshire RG5 3QB",
    "addr:housenumber":"14",
    "addr:postcode":"rg5 3qb",
    "addr:street":"Keswick Gardens",
    "iso:country":"GB",
    "sg:address":"14 Keswick Gardens, Woodley",
    "sg:city":"Reading",
    "sg:classifiers":[
        {
            "category":"Building & Trades",
            "subcategory":"Construction",
            "type":"Services"
        }
    ],
    "sg:postcode":"RG5 3QB",
    "sg:province":"Berkshire",
    "sg:tags":[
        "decorator",
        "painter"
    ],
    "wof:name":"Denis Catlow",
    "wof:placetype":"venue"
},
  "geometry": {"coordinates":[-0.9018309712,51.4423065186],"type":"Point"}
}