{
  "type": "Feature",
  "properties": {
    "iso:country":"GB",
    "sg:address":"Gybe Ho, Weeley Rd",
    "sg:city":"Clacton On Sea",
    "sg:classifiers":[
        {
            "category":"Building & Trades",
            "subcategory":"Construction",
            "type":"Services"
        }
    ],
    "sg:phone":"+44 1255 860421",
    "sg:postcode":"CO16 9EN",
    "sg:province":"Essex",
    "sg:tags":[
        "joiner",
        "carpenter"
    ],
    "wof:name":"R J Jarrold",
    "wof:placetype":"venue"
},
  "geometry": {"coordinates":[1.1372900009,51.8354682922],"type":"Point"}
}