{
  "type": "Feature",
  "properties": {
    "iso:country":"GB",
    "sg:address":"Whitecairns",
    "sg:city":"Turriff",
    "sg:classifiers":[
        {
            "category":"Farming",
            "subcategory":"Farm",
            "type":"Manufacturing & Wholesale Goods"
        }
    ],
    "sg:phone":"+44 1771 653315",
    "sg:postcode":"AB53 6UU",
    "sg:province":"Aberdeenshire",
    "sg:tags":[
        "mixed",
        "crop"
    ],
    "wof:name":"W Laird & Co.",
    "wof:placetype":"venue"
},
  "geometry": {"coordinates":[-2.1974990368,57.5151901245],"type":"Point"}
}