{
  "type": "Feature",
  "properties": {
    "addr:full":"Penterry Farm, St Arvans Chepstow Gloucestershire NP16 6HG",
    "addr:postcode":"np16 6hg",
    "iso:country":"GB",
    "sg:address":"Penterry Farm, St Arvans",
    "sg:city":"Chepstow",
    "sg:classifiers":[
        {
            "category":"Farming",
            "subcategory":"Livestock Farm",
            "type":"Manufacturing & Wholesale Goods"
        }
    ],
    "sg:phone":"+44 1291 689301",
    "sg:postcode":"NP16 6HG",
    "sg:province":"Gloucestershire",
    "sg:tags":[
        "others"
    ],
    "wof:name":"H D & L M Spencer",
    "wof:placetype":"venue"
},
  "geometry": {"coordinates":[-2.69093,51.67968],"type":"Point"}
}