{
  "type": "Feature",
  "properties": {
    "iso:country":"GB",
    "sg:address":"Unit B Crown Square",
    "sg:city":"Matlock",
    "sg:classifiers":[
        {
            "category":"Shopping",
            "subcategory":"Shoes",
            "type":"Retail Goods"
        }
    ],
    "sg:phone":"+44 1629 55616",
    "sg:postcode":"DE4 3AT",
    "sg:province":"Derbyshire",
    "sg:tags":[
        "shop",
        "retailer",
        "footwear"
    ],
    "wof:name":"Broughton Shoe Warehouse",
    "wof:placetype":"venue"
},
  "geometry": {"coordinates":[-1.5482740402,53.1356163025],"type":"Point"}
}