{
  "type": "Feature",
  "properties": {
    "iso:country":"GB",
    "sg:address":"Gloucester Enterprise Workshops, Chequers Road",
    "sg:city":"Gloucester",
    "sg:classifiers":[
        {
            "category":"Professional",
            "subcategory":"Business Services",
            "type":"Services"
        }
    ],
    "sg:phone":"+44 1452 525282",
    "sg:postcode":"GL4 6PN",
    "sg:province":"Gloucestershire",
    "sg:tags":[
        "assessment",
        "quality"
    ],
    "wof:name":"Chris Gay",
    "wof:placetype":"venue"
},
  "geometry": {"coordinates":[-2.22616,51.852619],"type":"Point"}
}