{
  "type": "Feature",
  "properties": {
    "addr:full":"1 St Georges Yd Farnham Surrey GU9 7LW",
    "addr:housenumber":"1",
    "addr:postcode":"gu9 7lw",
    "addr:street":"St;Yd Farnham",
    "iso:country":"GB",
    "sg:address":"1 St Georges Yd",
    "sg:city":"Farnham",
    "sg:classifiers":[
        {
            "category":"Travel",
            "subcategory":"Travel Agent",
            "type":"Entertainment"
        }
    ],
    "sg:phone":"+44 1932 860360",
    "sg:postcode":"GU9 7LW",
    "sg:province":"Surrey",
    "wof:name":"Travel Professionals Ltd (The)",
    "wof:placetype":"venue"
},
  "geometry": {"coordinates":[-0.800837,51.214321],"type":"Point"}
}