{
  "type": "Feature",
  "properties": {
    "addr:full":"42 Avenue Victoria Scarborough North Yorkshire YO11 2QT",
    "addr:housenumber":"42",
    "addr:postcode":"yo11 2qt",
    "addr:street":"Avenue Victoria",
    "iso:country":"GB",
    "sg:address":"42 Avenue Victoria",
    "sg:city":"Scarborough",
    "sg:classifiers":[
        {
            "category":"Professional",
            "subcategory":"Management & Consulting",
            "type":"Services"
        }
    ],
    "sg:phone":"+44 1723 371739",
    "sg:postcode":"YO11 2QT",
    "sg:province":"North Yorkshire",
    "sg:tags":[
        "fire",
        "consultant",
        "protection"
    ],
    "wof:name":"East Coast Fire Services Ltd.",
    "wof:placetype":"venue"
},
  "geometry": {"coordinates":[-0.400684,54.270924],"type":"Point"}
}