{
  "type": "Feature",
  "properties": {
    "iso:country":"GB",
    "sg:address":"Gorse Cottage, Furze Hill",
    "sg:city":"Fordingbridge",
    "sg:classifiers":[
        {
            "category":"Shopping",
            "subcategory":"Florist",
            "type":"Retail Goods"
        }
    ],
    "sg:postcode":"SP6 2PU",
    "sg:province":"Dorset",
    "wof:name":"Dial-A-Teddy Ltd",
    "wof:placetype":"venue"
},
  "geometry": {"coordinates":[-1.760964,50.898651],"type":"Point"}
}