{
  "type": "Feature",
  "properties": {
    "iso:country":"GB",
    "sg:address":"16 Westwood Road",
    "sg:city":"Newbury",
    "sg:classifiers":[
        {
            "category":"Professional",
            "subcategory":"Engineering",
            "type":"Services"
        },
        {
            "category":"Shopping",
            "subcategory":"Computers & Home Electronics",
            "type":"Retail Goods"
        }
    ],
    "sg:phone":"+44 1635 820778",
    "sg:postcode":"RG14 7TN",
    "sg:province":"Berkshire",
    "sg:tags":[
        "television",
        "aerial",
        "contractor",
        "electrical",
        "radio",
        "engineer"
    ],
    "wof:name":"Ronald A Hookway",
    "wof:placetype":"venue"
},
  "geometry": {"coordinates":[-1.311213,51.389923],"type":"Point"}
}