{
  "type": "Feature",
  "properties": {
    "addr:full":"14 Market Pl Devizes Wiltshire SN10 4AH",
    "addr:housenumber":"14",
    "addr:postcode":"sn10 4ah",
    "addr:street":"Market Pl",
    "iso:country":"GB",
    "sg:address":"14 Market Pl",
    "sg:city":"Devizes",
    "sg:classifiers":[
        {
            "category":"Communications",
            "subcategory":"Newspaper",
            "type":"Services"
        }
    ],
    "sg:phone":"+44 1380 723501",
    "sg:postcode":"SN10 4AH",
    "sg:province":"Wiltshire",
    "sg:tags":[
        "magazine"
    ],
    "wof:name":"Evening Advertiser",
    "wof:placetype":"venue"
},
  "geometry": {"coordinates":[-1.9797489643,51.2875099182],"type":"Point"}
}