{
  "type": "Feature",
  "properties": {
    "addr:full":"11-13 Taff Street Pontypridd Caerphilly CF37 4UA",
    "addr:housenumber":"11-13",
    "addr:postcode":"cf37 4ua",
    "addr:street":"Taff Street",
    "iso:country":"GB",
    "sg:address":"11-13 Taff Street",
    "sg:city":"Pontypridd",
    "sg:classifiers":[
        {
            "category":"Home & Garden",
            "subcategory":"Furniture",
            "type":"Retail Goods"
        }
    ],
    "sg:phone":"+44 1443 480854",
    "sg:postcode":"CF37 4UA",
    "sg:province":"Caerphilly",
    "wof:name":"Harveys Furnishing Group Ltd.",
    "wof:placetype":"venue"
},
  "geometry": {"coordinates":[-3.3405919075,51.6033401489],"type":"Point"}
}