{
  "type": "Feature",
  "properties": {
    "iso:country":"GB",
    "sg:address":"East Nether Crimond, Keith Hall",
    "sg:city":"Inverurie",
    "sg:classifiers":[
        {
            "category":"Farming",
            "subcategory":"Farm",
            "type":"Manufacturing & Wholesale Goods"
        }
    ],
    "sg:phone":"+44 1651 882242",
    "sg:postcode":"AB51 0LQ",
    "sg:province":"Aberdeenshire",
    "sg:tags":[
        "mixed",
        "crop"
    ],
    "wof:name":"D Jamieson & Son",
    "wof:placetype":"venue"
},
  "geometry": {"coordinates":[-2.389794,57.291119],"type":"Point"}
}