{
  "type": "Feature",
  "properties": {
    "addr:full":"140b Melton Rd Leicester Leicestershire LE4 5EE",
    "addr:housenumber":"140b",
    "addr:postcode":"le4 5ee",
    "addr:street":"Melton Rd",
    "iso:country":"GB",
    "sg:address":"140b Melton Rd",
    "sg:city":"Leicester",
    "sg:classifiers":[
        {
            "category":"Shopping",
            "subcategory":"Pharmacy",
            "type":"Retail Goods"
        }
    ],
    "sg:phone":"+44 116 266 6485",
    "sg:postcode":"LE4 5EE",
    "sg:province":"Leicestershire",
    "sg:tags":[
        "medicine",
        "therapy"
    ],
    "wof:name":"Co-co's",
    "wof:placetype":"venue"
},
  "geometry": {"coordinates":[-1.119899,52.65313],"type":"Point"}
}