{
  "type": "Feature",
  "properties": {
    "iso:country":"GB",
    "sg:address":"Ginger Hall, Rattlerow, Mileham",
    "sg:city":"King's Lynn",
    "sg:classifiers":[
        {
            "category":"Utilities",
            "subcategory":"Refuse",
            "type":"Services"
        }
    ],
    "sg:phone":"+44 1328 701723",
    "sg:postcode":"PE32 2PY",
    "sg:province":"Norfolk",
    "sg:tags":[
        "skip",
        "hire"
    ],
    "wof:name":"Robo Mini Skip Hire",
    "wof:placetype":"venue"
},
  "geometry": {"coordinates":[0.82416,52.735611],"type":"Point"}
}