{
  "type": "Feature",
  "properties": {
    "iso:country":"GB",
    "sg:address":"1 Queens Parade",
    "sg:city":"Bristol",
    "sg:classifiers":[
        {
            "category":"Professional",
            "type":"Services"
        }
    ],
    "sg:postcode":"BS1 5XJ",
    "sg:province":"City of Bristol",
    "sg:tags":[
        "entertainer"
    ],
    "wof:name":"Bijou Cirque Productions Ltd.",
    "wof:placetype":"venue"
},
  "geometry": {"coordinates":[-2.6040980816,51.4523925781],"type":"Point"}
}