{
  "type": "Feature",
  "properties": {
    "addr:full":"63 Greencroft Gardens Kilburn Greater London NW6 3LJ",
    "addr:housenumber":"63",
    "addr:postcode":"nw6 3lj",
    "addr:street":"Greencroft Gardens",
    "iso:country":"GB",
    "sg:address":"63 Greencroft Gardens",
    "sg:city":"Kilburn",
    "sg:classifiers":[
        {
            "category":"Retail",
            "subcategory":"Auto Rental",
            "type":"Services"
        }
    ],
    "sg:phone":"+44 20 7625 7166",
    "sg:postcode":"NW6 3LJ",
    "sg:province":"Greater London",
    "sg:tags":[
        "car"
    ],
    "wof:name":"Car Rental Direct",
    "wof:placetype":"venue"
},
  "geometry": {"coordinates":[-0.1840299964,51.5432777405],"type":"Point"}
}