{
  "type": "Feature",
  "properties": {
    "addr:full":"2 Greville Rd, Ore Hastings East Sussex TN35 5AQ",
    "addr:housenumber":"2",
    "addr:postcode":"tn35 5aq",
    "addr:street":"Greville Rd;Hastings",
    "iso:country":"GB",
    "sg:address":"2 Greville Rd, Ore",
    "sg:city":"Hastings",
    "sg:classifiers":[
        {
            "category":"Personal",
            "type":"Services"
        }
    ],
    "sg:phone":"+44 1424 443738",
    "sg:postcode":"TN35 5AQ",
    "sg:province":"East Sussex",
    "sg:tags":[
        "delivery"
    ],
    "wof:name":"T.J Keppler Freight",
    "wof:placetype":"venue"
},
  "geometry": {"coordinates":[0.6038140059,50.8729095459],"type":"Point"}
}