{
  "type": "Feature",
  "properties": {
    "addr:full":"85 Commercial Square Leicester Leicestershire LE2 7SR",
    "addr:housenumber":"85",
    "addr:postcode":"le2 7sr",
    "addr:street":"Commercial Square",
    "iso:country":"GB",
    "sg:address":"85 Commercial Square",
    "sg:city":"Leicester",
    "sg:classifiers":[
        {
            "category":"Wholesale",
            "subcategory":"Toys & Hobbies",
            "type":"Manufacturing & Wholesale Goods"
        }
    ],
    "sg:phone":"+44 116 254 3645",
    "sg:postcode":"LE2 7SR",
    "sg:province":"Leicestershire",
    "sg:tags":[
        "game"
    ],
    "wof:name":"Peterkin (U K) Ltd.",
    "wof:placetype":"venue"
},
  "geometry": {"coordinates":[-1.132992,52.616688],"type":"Point"}
}