{
  "type": "Feature",
  "properties": {
    "addr:full":"12 Hyde Road, Sanderstead Croydon Surrey CR2 9NP",
    "addr:housenumber":"12",
    "addr:postcode":"cr2 9np",
    "addr:street":"Hyde Road",
    "iso:country":"GB",
    "sg:address":"12 Hyde Road, Sanderstead",
    "sg:city":"Croydon",
    "sg:classifiers":[
        {
            "category":"Building & Trades",
            "subcategory":"Construction",
            "type":"Services"
        }
    ],
    "sg:phone":"+44 20 8657 6197",
    "sg:postcode":"CR2 9NP",
    "sg:province":"Surrey",
    "sg:tags":[
        "glazier",
        "decorator",
        "painter"
    ],
    "wof:name":"Marshall Decorators",
    "wof:placetype":"venue"
},
  "geometry": {"coordinates":[-0.0867919996,51.3318595886],"type":"Point"}
}