{
  "type": "Feature",
  "properties": {
    "addr:full":"21 Fairbourne Close, Callands Warrington Cheshire WA5 9RR",
    "addr:housenumber":"21",
    "addr:postcode":"wa5 9rr",
    "addr:street":"Fairbourne Close",
    "iso:country":"GB",
    "sg:address":"21 Fairbourne Close, Callands",
    "sg:city":"Warrington",
    "sg:classifiers":[
        {
            "category":"Building & Trades",
            "subcategory":"Construction",
            "type":"Services"
        }
    ],
    "sg:postcode":"WA5 9RR",
    "sg:province":"Cheshire",
    "sg:tags":[
        "bricklaying"
    ],
    "wof:name":"Mike Jones Building Services",
    "wof:placetype":"venue"
},
  "geometry": {"coordinates":[-2.616795063,53.414981842],"type":"Point"}
}