{
  "type": "Feature",
  "properties": {
    "addr:full":"96 Scott Road Bishops Stortford Essex CM23 3QJ",
    "addr:housenumber":"96",
    "addr:postcode":"cm23 3qj",
    "addr:street":"Scott Road",
    "iso:country":"GB",
    "sg:address":"96 Scott Road",
    "sg:city":"Bishops Stortford",
    "sg:classifiers":[
        {
            "category":"Home & Garden",
            "subcategory":"Building Materials",
            "type":"Retail Goods"
        },
        {
            "category":"Building & Trades",
            "subcategory":"Construction",
            "type":"Services"
        }
    ],
    "sg:phone":"+44 1279 653808",
    "sg:postcode":"CM23 3QJ",
    "sg:province":"Essex",
    "sg:tags":[
        "fencing",
        "contractor"
    ],
    "wof:name":"H Davidson Fencing Contractor",
    "wof:placetype":"venue"
},
  "geometry": {"coordinates":[0.150368005,51.8652992249],"type":"Point"}
}