{
  "type": "Feature",
  "properties": {
    "addr:full":"Elvet Waterside Durham Durham DH1 3BW",
    "addr:postcode":"dh1 3bw",
    "addr:street":"Waterside",
    "iso:country":"GB",
    "sg:address":"Elvet Waterside",
    "sg:city":"Durham",
    "sg:classifiers":[
        {
            "category":"Travel",
            "subcategory":"Hotels & Motels",
            "type":"Entertainment"
        }
    ],
    "sg:phone":"+44 191 384 6660",
    "sg:postcode":"DH1 3BW",
    "sg:province":"Durham",
    "sg:tags":[
        "house",
        "guest"
    ],
    "wof:name":"Waterside Guest House",
    "wof:placetype":"venue"
},
  "geometry": {"coordinates":[-1.5692700148,54.7764854431],"type":"Point"}
}