{
  "type": "Feature",
  "properties": {
    "iso:country":"GB",
    "sg:address":"41 Sherbourn Street",
    "sg:city":"Manchester",
    "sg:classifiers":[
        {
            "category":"Professional",
            "subcategory":"Printing & Photocopies",
            "type":"Services"
        }
    ],
    "sg:phone":"+44 161 832 3198",
    "sg:postcode":"M8 8NE",
    "sg:province":"Greater Manchester",
    "sg:tags":[
        "plate",
        "lithographic",
        "maker"
    ],
    "wof:name":"F I Printing Co. Ltd.",
    "wof:placetype":"venue"
},
  "geometry": {"coordinates":[-2.245683,53.49416],"type":"Point"}
}