{
  "type": "Feature",
  "properties": {
    "iso:country":"GB",
    "sg:address":"5 Cole Green Lane",
    "sg:city":"Welwyn Garden City",
    "sg:classifiers":[
        {
            "category":"Retail",
            "subcategory":"Funeral Services",
            "type":"Services"
        }
    ],
    "sg:phone":"+44 1707 391808",
    "sg:postcode":"AL7 3PP",
    "sg:province":"Hertfordshire",
    "sg:tags":[
        "director"
    ],
    "wof:name":"J J Burgess & Sons",
    "wof:placetype":"venue"
},
  "geometry": {"coordinates":[-0.1969889998,51.7905540466],"type":"Point"}
}