{
  "type": "Feature",
  "properties": {
    "iso:country":"GB",
    "sg:address":"Manvers Road, Swallownest",
    "sg:city":"Sheffield",
    "sg:classifiers":[
        {
            "category":"Home & Garden",
            "subcategory":"Home Furnishings",
            "type":"Retail Goods"
        },
        {
            "category":"Building & Trades",
            "subcategory":"Landfill",
            "type":"Services"
        }
    ],
    "sg:phone":"+44 114 287 2748",
    "sg:postcode":"S26 4UB",
    "sg:province":"South Yorkshire",
    "sg:tags":[
        "blind",
        "awning",
        "canopy",
        "blinds"
    ],
    "wof:name":"Swan Sun Blinds",
    "wof:placetype":"venue"
},
  "geometry": {"coordinates":[-1.325109,53.362091],"type":"Point"}
}