{
  "type": "Feature",
  "properties": {
    "addr:full":"7-9 Chester Road West, Shotton Deeside Flintshire CH5 1QA",
    "addr:housenumber":"7-9",
    "addr:postcode":"ch5 1qa",
    "addr:street":"Chester Road West",
    "iso:country":"GB",
    "sg:address":"7-9 Chester Road West, Shotton",
    "sg:city":"Deeside",
    "sg:classifiers":[
        {
            "category":"Shopping",
            "subcategory":"Pharmacy",
            "type":"Retail Goods"
        }
    ],
    "sg:phone":"+44 1244 830452",
    "sg:postcode":"CH5 1QA",
    "sg:province":"Flintshire",
    "sg:tags":[
        "pharmacist",
        "chemist"
    ],
    "wof:name":"Boots the Chemists",
    "wof:placetype":"venue"
},
  "geometry": {"coordinates":[-3.03904,53.21191],"type":"Point"}
}