{
  "type": "Feature",
  "properties": {
    "addr:full":"Lawnside, Bridewell Gardens, Undy Caldicot Monmouthshire NP26 3JZ",
    "addr:postcode":"np26 3jz",
    "addr:street":"Bridewell Gardens",
    "iso:country":"GB",
    "sg:address":"Lawnside, Bridewell Gardens, Undy",
    "sg:city":"Caldicot",
    "sg:classifiers":[
        {
            "category":"Real Estate",
            "subcategory":"Architect",
            "type":"Services"
        }
    ],
    "sg:phone":"+44 1633 880891",
    "sg:postcode":"NP26 3JZ",
    "sg:province":"Monmouthshire",
    "wof:name":"Corners Chartered Surveyors",
    "wof:placetype":"venue"
},
  "geometry": {"coordinates":[-2.748045,51.585957],"type":"Point"}
}