{
  "type": "Feature",
  "properties": {
    "iso:country":"GB",
    "sg:address":"50 Main Street, Spittal",
    "sg:city":"Berwick-upon-tweed",
    "sg:classifiers":[
        {
            "category":"Building & Trades",
            "subcategory":"Construction",
            "type":"Services"
        }
    ],
    "sg:postcode":"TD15 1QY",
    "sg:province":"Northumberland",
    "sg:tags":[
        "decorator",
        "painter"
    ],
    "wof:name":"Keith Morgan",
    "wof:placetype":"venue"
},
  "geometry": {"coordinates":[-2.007024,55.771435],"type":"Point"}
}