{
  "type": "Feature",
  "properties": {
    "addr:full":"50 Berkeley Street London Greater London W1J 8HA",
    "addr:housenumber":"50",
    "addr:postcode":"w1j 8ha",
    "addr:street":"Berkeley Street",
    "iso:country":"GB",
    "sg:address":"50 Berkeley Street",
    "sg:city":"London",
    "sg:classifiers":[
        {
            "category":"Banks & Credit Unions",
            "subcategory":"Bank",
            "type":"Services"
        }
    ],
    "sg:phone":"+44 20 7588 2721",
    "sg:postcode":"W1J 8HA",
    "sg:province":"Greater London",
    "wof:name":"Lazard Fund Managers Ltd.",
    "wof:placetype":"venue"
},
  "geometry": {"coordinates":[-0.1441890001,51.5088615417],"type":"Point"}
}