{
  "type": "Feature",
  "properties": {
    "iso:country":"GB",
    "sg:address":"89 Summerway, Whipton",
    "sg:city":"Exeter",
    "sg:classifiers":[
        {
            "category":"Building & Trades",
            "subcategory":"Construction",
            "type":"Services"
        }
    ],
    "sg:phone":"+44 1392 466985",
    "sg:postcode":"EX4 8DJ",
    "sg:province":"Devon",
    "sg:tags":[
        "platform",
        "builder",
        "work",
        "scaffolding"
    ],
    "wof:name":"R Chapman Scaffolding Contractor",
    "wof:placetype":"venue"
},
  "geometry": {"coordinates":[-3.485450983,50.7358055115],"type":"Point"}
}