{
  "type": "Feature",
  "properties": {
    "iso:country":"GB",
    "sg:address":"Leone Works, John Street, New Basford",
    "sg:city":"Nottingham",
    "sg:classifiers":[
        {
            "category":"Manufacturing",
            "subcategory":"Metals",
            "type":"Manufacturing & Wholesale Goods"
        }
    ],
    "sg:phone":"+44 115 942 0006",
    "sg:postcode":"NG7 7HL",
    "sg:province":"Nottinghamshire",
    "sg:tags":[
        "merchant"
    ],
    "wof:name":"Knobs Ltd.",
    "wof:placetype":"venue"
},
  "geometry": {"coordinates":[-1.162504,52.974766],"type":"Point"}
}