{
  "type": "Feature",
  "properties": {
    "iso:country":"GB",
    "sg:address":"331 North Deeside Road, Cults",
    "sg:city":"Aberdeen",
    "sg:classifiers":[
        {
            "category":"Shopping",
            "subcategory":"Clothing, Apparel, & Fashions",
            "type":"Retail Goods"
        }
    ],
    "sg:phone":"+44 1224 868377",
    "sg:postcode":"AB15 9SN",
    "sg:province":"Aberdeen City",
    "sg:tags":[
        "shop"
    ],
    "wof:name":"Rodier",
    "wof:placetype":"venue"
},
  "geometry": {"coordinates":[-2.190186,57.113781],"type":"Point"}
}