{
  "type": "Feature",
  "properties": {
    "addr:full":"Barton Dene, Heald House Road Preston Lancashire PR25 5DD",
    "addr:postcode":"pr25 5dd",
    "addr:street":"Dene;House Road",
    "iso:country":"GB",
    "sg:address":"Barton Dene, Heald House Road",
    "sg:city":"Preston",
    "sg:classifiers":[
        {
            "category":"Transit Center",
            "subcategory":"Passenger",
            "type":"Transportation"
        }
    ],
    "sg:phone":"+44 1772 457322",
    "sg:postcode":"PR25 5DD",
    "sg:province":"Lancashire",
    "sg:tags":[
        "boarding",
        "kennel",
        "catteries"
    ],
    "wof:name":"Barton Dene Boarding Kennels",
    "wof:placetype":"venue"
},
  "geometry": {"coordinates":[-2.6766400337,53.6880493164],"type":"Point"}
}