{
  "type": "Feature",
  "properties": {
    "addr:full":"Beeswing Dumfries Dumfries and Galloway DG2 8ED",
    "addr:postcode":"dg2 8ed",
    "iso:country":"GB",
    "sg:address":"Beeswing",
    "sg:city":"Dumfries",
    "sg:classifiers":[
        {
            "category":"Professional",
            "subcategory":"Art Services",
            "type":"Services"
        }
    ],
    "sg:phone":"+44 1387 760643",
    "sg:postcode":"DG2 8ED",
    "sg:province":"Dumfries and Galloway",
    "sg:tags":[
        "glass",
        "engraver"
    ],
    "wof:name":"Galloway Glass",
    "wof:placetype":"venue"
},
  "geometry": {"coordinates":[-3.7063500881,54.999458313],"type":"Point"}
}