{
  "type": "Feature",
  "properties": {
    "addr:full":"88 Newton Rd Torquay Devon TQ2 7AB",
    "addr:housenumber":"88",
    "addr:postcode":"tq2 7ab",
    "addr:street":"Newton Rd",
    "iso:country":"GB",
    "sg:address":"88 Newton Rd",
    "sg:city":"Torquay",
    "sg:classifiers":[
        {
            "category":"Health Services",
            "subcategory":"Health Practitioner",
            "type":"Services"
        }
    ],
    "sg:phone":"+44 1803 616240",
    "sg:postcode":"TQ2 7AB",
    "sg:province":"Devon",
    "sg:tags":[
        "hypnotherapists"
    ],
    "wof:name":"H Campbell",
    "wof:placetype":"venue"
},
  "geometry": {"coordinates":[-3.551024,50.48312],"type":"Point"}
}