{
  "type": "Feature",
  "properties": {
    "addr:full":"28 Dunsbury Clo Sutton Surrey SM2 6TP",
    "addr:housenumber":"28",
    "addr:postcode":"sm2 6tp",
    "addr:street":"Dunsbury Clo Sutton",
    "iso:country":"GB",
    "sg:address":"28 Dunsbury Clo",
    "sg:city":"Sutton",
    "sg:classifiers":[
        {
            "category":"Building & Trades",
            "subcategory":"Plumbing",
            "type":"Services"
        }
    ],
    "sg:phone":"+44 20 8643 7341",
    "sg:postcode":"SM2 6TP",
    "sg:province":"Surrey",
    "sg:tags":[
        "drain",
        "clearance",
        "sewer"
    ],
    "wof:name":"Drains We Clean",
    "wof:placetype":"venue"
},
  "geometry": {"coordinates":[-0.194806993,51.3489151001],"type":"Point"}
}