{
  "type": "Feature",
  "properties": {
    "addr:full":"17/23 Elmshott Lane, Cippenham Slough Berkshire SL1 5QS",
    "addr:housenumber":"17 / 23",
    "addr:postcode":"sl1 5qs",
    "addr:street":"Elmshott Lane",
    "iso:country":"GB",
    "sg:address":"17/23 Elmshott Lane, Cippenham",
    "sg:city":"Slough",
    "sg:classifiers":[
        {
            "category":"Home & Garden",
            "subcategory":"Building Materials",
            "type":"Retail Goods"
        }
    ],
    "sg:phone":"+44 1628 666668",
    "sg:postcode":"SL1 5QS",
    "sg:province":"Berkshire",
    "sg:tags":[
        "furnishers",
        "bathroom",
        "planner"
    ],
    "wof:name":"Corniche Bathrooms Ltd.",
    "wof:placetype":"venue"
},
  "geometry": {"coordinates":[-0.6449970007,51.5185966492],"type":"Point"}
}