{
  "type": "Feature",
  "properties": {
    "iso:country":"GB",
    "sg:address":"Aylesham Industrial Estate",
    "sg:city":"Canterbury",
    "sg:classifiers":[
        {
            "category":"Manufacturing",
            "subcategory":"Wood Products",
            "type":"Manufacturing & Wholesale Goods"
        }
    ],
    "sg:phone":"+44 1304 840581",
    "sg:postcode":"CT3 3EF",
    "sg:province":"Kent",
    "sg:tags":[
        "packaging",
        "crate",
        "pallets"
    ],
    "wof:name":"M Y Plastics",
    "wof:placetype":"venue"
},
  "geometry": {"coordinates":[1.20096,51.226166],"type":"Point"}
}