{
  "type": "Feature",
  "properties": {
    "addr:full":"Chalvey Park Slough Berkshire SL1 2HX",
    "addr:postcode":"sl1 2hx",
    "addr:street":"Park",
    "iso:country":"GB",
    "sg:address":"Chalvey Park",
    "sg:city":"Slough",
    "sg:classifiers":[
        {
            "category":"Social Services",
            "type":"Services"
        }
    ],
    "sg:phone":"+44 1753 521448",
    "sg:postcode":"SL1 2HX",
    "sg:province":"Berkshire",
    "wof:name":"Slough Family Centre",
    "wof:placetype":"venue"
},
  "geometry": {"coordinates":[-0.5974040031,51.5075683594],"type":"Point"}
}