{
  "type": "Feature",
  "properties": {
    "addr:full":"Greshop Industrial Estate Forres Moray IV36 2SN",
    "addr:postcode":"iv36 2sn",
    "addr:street":"Estate Forres",
    "iso:country":"GB",
    "sg:address":"Greshop Industrial Estate",
    "sg:city":"Forres",
    "sg:classifiers":[
        {
            "category":"Retail",
            "subcategory":"Auto Repair",
            "type":"Services"
        }
    ],
    "sg:postcode":"IV36 2SN",
    "sg:province":"Moray",
    "sg:tags":[
        "modification",
        "garage"
    ],
    "wof:name":"Findhorn Motors Ltd.",
    "wof:placetype":"venue"
},
  "geometry": {"coordinates":[-3.636991024,57.6073303223],"type":"Point"}
}