{
  "type": "Feature",
  "properties": {
    "iso:country":"GB",
    "sg:address":"Pen-yr-allt, Tan-y-fron Road",
    "sg:city":"Abergele",
    "sg:classifiers":[
        {
            "category":"Farming",
            "subcategory":"Livestock Farm",
            "type":"Manufacturing & Wholesale Goods"
        }
    ],
    "sg:phone":"+44 1745 832052",
    "sg:postcode":"LL22 9BB",
    "sg:province":"Conwy",
    "sg:tags":[
        "others"
    ],
    "wof:name":"G O  Parry",
    "wof:placetype":"venue"
},
  "geometry": {"coordinates":[-3.566114,53.274963],"type":"Point"}
}