{
  "type": "Feature",
  "properties": {
    "addr:full":"37a Aire Street Goole East Riding of Yorkshire DN14 5QW",
    "addr:housenumber":"37a",
    "addr:postcode":"dn14 5qw",
    "addr:street":"Aire Street",
    "iso:country":"GB",
    "sg:address":"37a Aire Street",
    "sg:city":"Goole",
    "sg:classifiers":[
        {
            "category":"Health Services",
            "subcategory":"Podiatrist",
            "type":"Services"
        }
    ],
    "sg:phone":"+44 1405 763519",
    "sg:postcode":"DN14 5QW",
    "sg:province":"East Riding of Yorkshire",
    "sg:tags":[
        "podiatrists",
        "chiropodist"
    ],
    "wof:name":"J GAVIN ANDERSON",
    "wof:placetype":"venue"
},
  "geometry": {"coordinates":[-0.87016,53.701942],"type":"Point"}
}