{
  "type": "Feature",
  "properties": {
    "iso:country":"GB",
    "sg:address":"23 South View Road, Milborne Port",
    "sg:city":"Sherborne",
    "sg:classifiers":[
        {
            "category":"Building & Trades",
            "subcategory":"Plumbing",
            "type":"Services"
        }
    ],
    "sg:phone":"+44 1963 250467",
    "sg:postcode":"DT9 5BS",
    "sg:province":"Dorset",
    "sg:tags":[
        "plumber",
        "heating"
    ],
    "wof:name":"Raymond John Woodley",
    "wof:placetype":"venue"
},
  "geometry": {"coordinates":[-2.4678039551,50.9692726135],"type":"Point"}
}