{
  "type": "Feature",
  "properties": {
    "addr:full":"40-42 Newbiggin Richmond North Yorkshire DL10 4DT",
    "addr:housenumber":"40-42",
    "addr:postcode":"dl10 4dt",
    "addr:street":"Newbiggin Richmond",
    "iso:country":"GB",
    "sg:address":"40-42 Newbiggin",
    "sg:city":"Richmond",
    "sg:classifiers":[
        {
            "category":"Retail",
            "subcategory":"Funeral Services",
            "type":"Services"
        }
    ],
    "sg:phone":"+44 1748 822326",
    "sg:postcode":"DL10 4DT",
    "sg:province":"North Yorkshire",
    "wof:name":"H Harrison & Son",
    "wof:placetype":"venue"
},
  "geometry": {"coordinates":[-1.74258,54.403885],"type":"Point"}
}