{
  "type": "Feature",
  "properties": {
    "addr:full":"Unit 14 Oak Street Industrial Pa, Rk Oak Street Cradley Heath West Midlands B64 5JY",
    "addr:housenumber":"unit 14",
    "addr:postcode":"b64 5jy",
    "addr:street":"Oak Street;Oak Street",
    "iso:country":"GB",
    "sg:address":"Unit 14 Oak Street Industrial Pa, Rk Oak Street",
    "sg:city":"Cradley Heath",
    "sg:classifiers":[
        {
            "category":"Health Services",
            "subcategory":"Dentist",
            "type":"Services"
        }
    ],
    "sg:phone":"+44 1384 564661",
    "sg:postcode":"B64 5JY",
    "sg:province":"West Midlands",
    "sg:tags":[
        "technician",
        "dental"
    ],
    "wof:name":"Gannow Dental Laboratory Ltd.",
    "wof:placetype":"venue"
},
  "geometry": {"coordinates":[-2.0754919052,52.4763526917],"type":"Point"}
}