{
  "type": "Feature",
  "properties": {
    "addr:full":"5 Quantock Close, Arnold Nottingham Nottinghamshire NG5 9QA",
    "addr:housenumber":"5",
    "addr:postcode":"ng5 9qa",
    "addr:street":"Quantock Close",
    "iso:country":"GB",
    "sg:address":"5 Quantock Close, Arnold",
    "sg:city":"Nottingham",
    "sg:classifiers":[
        {
            "category":"Manufacturing",
            "subcategory":"Signs",
            "type":"Manufacturing & Wholesale Goods"
        }
    ],
    "sg:phone":"+44 115 955 0672",
    "sg:postcode":"NG5 9QA",
    "sg:province":"Nottinghamshire",
    "sg:tags":[
        "commercial",
        "maker"
    ],
    "wof:name":"Nottingham Signs & Electrical Services",
    "wof:placetype":"venue"
},
  "geometry": {"coordinates":[-1.1576700211,53.0141563416],"type":"Point"}
}