{
  "type": "Feature",
  "properties": {
    "iso:country":"GB",
    "sg:address":"495 Bellhouse Road",
    "sg:city":"Sheffield",
    "sg:classifiers":[
        {
            "category":"Government",
            "subcategory":"Post Office",
            "type":"Public Place"
        }
    ],
    "sg:phone":"+44 114 245 6707",
    "sg:postcode":"S5 0EP",
    "sg:province":"South Yorkshire",
    "wof:name":"Lower Shiregreen Post Office",
    "wof:placetype":"venue"
},
  "geometry": {"coordinates":[-1.440356,53.431629],"type":"Point"}
}