{
  "type": "Feature",
  "properties": {
    "iso:country":"GB",
    "sg:address":"1 Brecon Close",
    "sg:city":"Swindon",
    "sg:classifiers":[
        {
            "category":"Retail",
            "subcategory":"Driving School",
            "type":"Services"
        }
    ],
    "sg:postcode":"SN3 1JT",
    "sg:province":"Wiltshire",
    "wof:name":"Grants Learner Driving School",
    "wof:placetype":"venue"
},
  "geometry": {"coordinates":[-1.764365,51.545589],"type":"Point"}
}