{
  "type": "Feature",
  "properties": {
    "addr:full":"11 Hillsborough Road Sheffield South Yorkshire S6 4JL",
    "addr:housenumber":"11",
    "addr:postcode":"s6 4jl",
    "addr:street":"Hillsborough Road",
    "iso:country":"GB",
    "sg:address":"11 Hillsborough Road",
    "sg:city":"Sheffield",
    "sg:classifiers":[
        {
            "category":"Shopping",
            "subcategory":"Pets & Pet Supplies",
            "type":"Retail Goods"
        }
    ],
    "sg:phone":"+44 114 233 9233",
    "sg:postcode":"S6 4JL",
    "sg:province":"South Yorkshire",
    "sg:tags":[
        "shop"
    ],
    "wof:name":"FISHERS PET STORE",
    "wof:placetype":"venue"
},
  "geometry": {"coordinates":[-1.5022929907,53.4028358459],"type":"Point"}
}