{
  "type": "Feature",
  "properties": {
    "addr:full":"Laurel Ho, Station Approach Alresford Hampshire SO24 9JH",
    "addr:postcode":"so24 9jh",
    "addr:street":"Station Approach",
    "iso:country":"GB",
    "sg:address":"Laurel Ho, Station Approach",
    "sg:city":"Alresford",
    "sg:classifiers":[
        {
            "category":"Shopping",
            "subcategory":"Books",
            "type":"Retail Goods"
        }
    ],
    "sg:phone":"+44 1962 735633",
    "sg:postcode":"SO24 9JH",
    "sg:province":"Hampshire",
    "wof:name":"Hunt & Thorpe",
    "wof:placetype":"venue"
},
  "geometry": {"coordinates":[-1.1617239714,51.090511322],"type":"Point"}
}