{
  "type": "Feature",
  "properties": {
    "addr:full":"14 York Road Wetherby North Yorkshire LS22 6SL",
    "addr:housenumber":"14",
    "addr:postcode":"ls22 6sl",
    "addr:street":"York Road",
    "iso:country":"GB",
    "sg:address":"14 York Road",
    "sg:city":"Wetherby",
    "sg:classifiers":[
        {
            "category":"Wholesale",
            "subcategory":"Machinery & Supplies",
            "type":"Manufacturing & Wholesale Goods"
        }
    ],
    "sg:phone":"+44 1937 583740",
    "sg:postcode":"LS22 6SL",
    "sg:province":"North Yorkshire",
    "sg:tags":[
        "industrial",
        "commercial"
    ],
    "wof:name":"Greenwood Machinery Ltd.",
    "wof:placetype":"venue"
},
  "geometry": {"coordinates":[-1.3824429512,53.9318351746],"type":"Point"}
}