{
  "type": "Feature",
  "properties": {
    "addr:full":"115 Upsall Gro, Fairfield Stockton-on-tees Durham TS19 7QW",
    "addr:housenumber":"115",
    "addr:postcode":"ts19 7qw",
    "addr:street":"Upsall Gro",
    "iso:country":"GB",
    "sg:address":"115 Upsall Gro, Fairfield",
    "sg:city":"Stockton-on-tees",
    "sg:classifiers":[
        {
            "category":"Professional",
            "subcategory":"Art Services",
            "type":"Services"
        }
    ],
    "sg:phone":"+44 1642 570170",
    "sg:postcode":"TS19 7QW",
    "sg:province":"Durham",
    "sg:tags":[
        "photographer"
    ],
    "wof:name":"Photoflair Studio",
    "wof:placetype":"venue"
},
  "geometry": {"coordinates":[-1.330024,54.578495],"type":"Point"}
}