{
  "type": "Feature",
  "properties": {
    "iso:country":"GB",
    "sg:address":"Trinity House, Heather Park Drive",
    "sg:city":"Wembley",
    "sg:classifiers":[
        {
            "category":"Real Estate",
            "subcategory":"Surveying",
            "type":"Services"
        }
    ],
    "sg:postcode":"HA0 1SX",
    "sg:province":"Greater London",
    "sg:tags":[
        "surveyor",
        "quantity"
    ],
    "wof:name":"Consul Chartered Surveyors",
    "wof:placetype":"venue"
},
  "geometry": {"coordinates":[-0.282949,51.543411],"type":"Point"}
}