{
  "type": "Feature",
  "properties": {
    "addr:full":"The Hall, Hickling Norwich Norfolk NR12 0AZ",
    "addr:postcode":"nr12 0az",
    "addr:street":"Hickling Norwich",
    "iso:country":"GB",
    "sg:address":"The Hall, Hickling",
    "sg:city":"Norwich",
    "sg:classifiers":[
        {
            "category":"Farming",
            "subcategory":"Farm",
            "type":"Manufacturing & Wholesale Goods"
        }
    ],
    "sg:phone":"+44 1692 598493",
    "sg:postcode":"NR12 0AZ",
    "sg:province":"Norfolk",
    "sg:tags":[
        "mixed",
        "crop"
    ],
    "wof:name":"R Ellis & Son",
    "wof:placetype":"venue"
},
  "geometry": {"coordinates":[1.5759079456,52.7600097656],"type":"Point"}
}