{
  "type": "Feature",
  "properties": {
    "iso:country":"GB",
    "sg:address":"Mount Misery Farm, Troutsdale",
    "sg:city":"Scarborough",
    "sg:classifiers":[
        {
            "category":"Farming",
            "subcategory":"Farm",
            "type":"Manufacturing & Wholesale Goods"
        }
    ],
    "sg:phone":"+44 1723 882277",
    "sg:postcode":"YO13 0BS",
    "sg:province":"North Yorkshire",
    "sg:tags":[
        "mixed",
        "crop"
    ],
    "wof:name":"Raymond Lawson",
    "wof:placetype":"venue"
},
  "geometry": {"coordinates":[-0.5842270255,54.2904701233],"type":"Point"}
}