{
  "type": "Feature",
  "properties": {
    "iso:country":"GB",
    "sg:address":"Trefere Bella, Penparc",
    "sg:city":"Cardigan",
    "sg:classifiers":[
        {
            "category":"Sports & Exercise",
            "subcategory":"Swimming Pool",
            "type":"Entertainment"
        }
    ],
    "sg:phone":"+44 1239 810301",
    "sg:postcode":"SA43 1RN",
    "sg:province":"Ceredigion",
    "sg:tags":[
        "bee"
    ],
    "wof:name":"Life of the Hive",
    "wof:placetype":"venue"
},
  "geometry": {"coordinates":[-4.655044,52.086868],"type":"Point"}
}