{
  "type": "Feature",
  "properties": {
    "iso:country":"GB",
    "sg:address":"194 High Street West",
    "sg:city":"Sunderland",
    "sg:classifiers":[
        {
            "category":"Home & Garden",
            "subcategory":"Home Furnishings",
            "type":"Retail Goods"
        }
    ],
    "sg:phone":"+44 191 567 6860",
    "sg:postcode":"SR1 1UG",
    "sg:province":"Tyne and Wear",
    "sg:tags":[
        "homefurnishings"
    ],
    "wof:name":"Barrass Beautiful Bedrooms",
    "wof:placetype":"venue"
},
  "geometry": {"coordinates":[-1.37802,54.907768],"type":"Point"}
}