{
  "type": "Feature",
  "properties": {
    "iso:country":"GB",
    "sg:address":"Standish Street",
    "sg:city":"St Helens",
    "sg:classifiers":[
        {
            "category":"Retail",
            "subcategory":"Auto Repair",
            "type":"Services"
        }
    ],
    "sg:phone":"+44 1744 23243",
    "sg:postcode":"WA10 1HY",
    "sg:province":"Merseyside",
    "sg:tags":[
        "modification",
        "garage"
    ],
    "wof:name":"Reynolds Yard Garage",
    "wof:placetype":"venue"
},
  "geometry": {"coordinates":[-2.7354490757,53.4582061768],"type":"Point"}
}