{
  "type": "Feature",
  "properties": {
    "iso:country":"GB",
    "sg:address":"Station Road, North Kilworth",
    "sg:city":"Lutterworth",
    "sg:classifiers":[
        {
            "category":"Autos & Motor Vehicles",
            "subcategory":"Automobile Sales",
            "type":"Retail Goods"
        }
    ],
    "sg:postcode":"LE17 6ES",
    "sg:province":"Leicestershire",
    "sg:tags":[
        "car"
    ],
    "wof:name":"Key West Service Station",
    "wof:placetype":"venue"
},
  "geometry": {"coordinates":[-1.0741820335,52.4468269348],"type":"Point"}
}