{
  "type": "Feature",
  "properties": {
    "addr:full":"631 Mansfield Rd, Sherwood Nottingham Nottinghamshire NG5 2FX",
    "addr:housenumber":"631",
    "addr:postcode":"ng5 2fx",
    "addr:street":"Mansfield Rd",
    "iso:country":"GB",
    "sg:address":"631 Mansfield Rd, Sherwood",
    "sg:city":"Nottingham",
    "sg:classifiers":[
        {
            "category":"Retail",
            "subcategory":"Repair Shop",
            "type":"Services"
        }
    ],
    "sg:phone":"+44 115 985 7142",
    "sg:postcode":"NG5 2FX",
    "sg:province":"Nottinghamshire",
    "sg:tags":[
        "upholsterer"
    ],
    "wof:name":"S.A Ball & Son",
    "wof:placetype":"venue"
},
  "geometry": {"coordinates":[-1.144853,52.983452],"type":"Point"}
}