{
  "type": "Feature",
  "properties": {
    "addr:full":"132 Town Row Liverpool Merseyside L12 8SN",
    "addr:housenumber":"132",
    "addr:postcode":"l12 8sn",
    "addr:street":"Town",
    "iso:country":"GB",
    "sg:address":"132 Town Row",
    "sg:city":"Liverpool",
    "sg:classifiers":[
        {
            "category":"Government",
            "subcategory":"Post Office",
            "type":"Public Place"
        }
    ],
    "sg:phone":"+44 151 228 3505",
    "sg:postcode":"L12 8SN",
    "sg:province":"Merseyside",
    "wof:name":"Town Row Sub Post Office",
    "wof:placetype":"venue"
},
  "geometry": {"coordinates":[-2.903218,53.429092],"type":"Point"}
}