{
  "type": "Feature",
  "properties": {
    "iso:country":"GB",
    "sg:address":"3 Queen Isabel's Avenue, Cheylesmore",
    "sg:city":"Coventry",
    "sg:classifiers":[
        {
            "category":"Food & Beverages",
            "subcategory":"Meat & Fish",
            "type":"Retail Goods"
        }
    ],
    "sg:phone":"+44 24 7650 2451",
    "sg:postcode":"CV3 5GE",
    "sg:province":"Warwickshire",
    "sg:tags":[
        "butcher"
    ],
    "wof:name":"Peter Tuckeys",
    "wof:placetype":"venue"
},
  "geometry": {"coordinates":[-1.479907,52.407078],"type":"Point"}
}