{
  "type": "Feature",
  "properties": {
    "addr:full":"79 Tottenham La Hornsey Greater London N8 9BE",
    "addr:housenumber":"79",
    "addr:postcode":"n8 9be",
    "addr:street":"Tottenham La Hornsey",
    "iso:country":"GB",
    "sg:address":"79 Tottenham La",
    "sg:city":"Hornsey",
    "sg:classifiers":[
        {
            "category":"Shopping",
            "subcategory":"Party Supplies",
            "type":"Retail Goods"
        }
    ],
    "sg:phone":"+44 20 8341 6060",
    "sg:postcode":"N8 9BE",
    "sg:province":"Greater London",
    "sg:tags":[
        "equipment",
        "disco"
    ],
    "wof:name":"Sound By Design Mobile Disco & Hire Centre",
    "wof:placetype":"venue"
},
  "geometry": {"coordinates":[-0.1162090003,51.5837898254],"type":"Point"}
}