{
  "type": "Feature",
  "properties": {
    "iso:country":"GB",
    "sg:address":"47-49 Carlton Road",
    "sg:city":"Worksop",
    "sg:classifiers":[
        {
            "category":"Building & Trades",
            "subcategory":"Construction",
            "type":"Services"
        }
    ],
    "sg:phone":"+44 1909 472353",
    "sg:postcode":"S80 1PD",
    "sg:province":"Nottinghamshire",
    "sg:tags":[
        "monumental",
        "mason"
    ],
    "wof:name":"Glenhaven Funeral Service Ltd.",
    "wof:placetype":"venue"
},
  "geometry": {"coordinates":[-1.1220829487,53.3096618652],"type":"Point"}
}