{
  "type": "Feature",
  "properties": {
    "addr:full":"218 Norton Lane, Earlswood Solihull Warwickshire B94 5LT",
    "addr:housenumber":"218",
    "addr:postcode":"b94 5lt",
    "addr:street":"Norton Lane",
    "iso:country":"GB",
    "sg:address":"218 Norton Lane, Earlswood",
    "sg:city":"Solihull",
    "sg:classifiers":[
        {
            "category":"Home & Garden",
            "subcategory":"Home Furnishings",
            "type":"Retail Goods"
        }
    ],
    "sg:phone":"+44 1564 702463",
    "sg:postcode":"B94 5LT",
    "sg:province":"Warwickshire",
    "sg:tags":[
        "blind",
        "manufacture",
        "fitting",
        "curtain"
    ],
    "wof:name":"Mary Jane Soft Furnishings",
    "wof:placetype":"venue"
},
  "geometry": {"coordinates":[-1.8522410393,52.3754386902],"type":"Point"}
}