{
  "type": "Feature",
  "properties": {
    "addr:full":"9 Clifford Street, Fish Quay North Shields Tyne and Wear NE30 1JQ",
    "addr:housenumber":"9",
    "addr:postcode":"ne30 1jq",
    "addr:street":"Clifford Street Fish Quay",
    "iso:country":"GB",
    "sg:address":"9 Clifford Street, Fish Quay",
    "sg:city":"North Shields",
    "sg:classifiers":[
        {
            "category":"Food & Beverages",
            "subcategory":"Meat & Fish",
            "type":"Retail Goods"
        }
    ],
    "sg:postcode":"NE30 1JQ",
    "sg:province":"Tyne and Wear",
    "sg:tags":[
        "merchant"
    ],
    "wof:name":"Harry Foskett",
    "wof:placetype":"venue"
},
  "geometry": {"coordinates":[-1.433256,55.010693],"type":"Point"}
}