{
  "type": "Feature",
  "properties": {
    "addr:full":"Malpas Rd Newport East Riding of Yorkshire NP9 6ZD",
    "addr:postcode":"np9 6zd",
    "addr:street":"Malpas Rd",
    "iso:country":"GB",
    "sg:address":"Malpas Rd",
    "sg:city":"Newport",
    "sg:classifiers":[
        {
            "category":"Government",
            "subcategory":"Office",
            "type":"Public Place"
        }
    ],
    "sg:phone":"+44 1633 858366",
    "sg:postcode":"NP9 6ZD",
    "sg:province":"East Riding of Yorkshire",
    "sg:tags":[
        "armed",
        "reserve"
    ],
    "wof:name":"Malpas TAC",
    "wof:placetype":"venue"
},
  "geometry": {"coordinates":[-3.0058789253,51.6022987366],"type":"Point"}
}