{
  "type": "Feature",
  "properties": {
    "addr:full":"157 Bethnal Green Road London Greater London E2 7DG",
    "addr:housenumber":"157",
    "addr:postcode":"e2 7dg",
    "addr:street":"Bethnal Green Road",
    "iso:country":"GB",
    "sg:address":"157 Bethnal Green Road",
    "sg:city":"London",
    "sg:classifiers":[
        {
            "category":"Professional",
            "subcategory":"Detective & Security Services",
            "type":"Services"
        }
    ],
    "sg:phone":"+44 20 7739 7588",
    "sg:postcode":"E2 7DG",
    "sg:province":"Greater London",
    "sg:tags":[
        "activity",
        "locksmith"
    ],
    "wof:name":"Midas Security Co",
    "wof:placetype":"venue"
},
  "geometry": {"coordinates":[-0.07057,51.525528],"type":"Point"}
}