{
  "type": "Feature",
  "properties": {
    "addr:full":"170 Pegasus Rd Oxford Oxfordshire OX4 5JQ",
    "addr:housenumber":"170",
    "addr:postcode":"ox4 5jq",
    "addr:street":"Pegasus Rd",
    "iso:country":"GB",
    "sg:address":"170 Pegasus Rd",
    "sg:city":"Oxford",
    "sg:classifiers":[
        {
            "category":"Food & Beverages",
            "subcategory":"Fruits & Vegetables",
            "type":"Retail Goods"
        }
    ],
    "sg:phone":"+44 1865 770503",
    "sg:postcode":"OX4 5JQ",
    "sg:province":"Oxfordshire",
    "sg:tags":[
        "greengrocer"
    ],
    "wof:name":"Link Food Ltd",
    "wof:placetype":"venue"
},
  "geometry": {"coordinates":[-1.1951309443,51.720287323],"type":"Point"}
}