{
  "type": "Feature",
  "properties": {
    "addr:full":"Abingdon Chambers Blackpool Lancashire FY1 1DG",
    "addr:postcode":"fy1 1dg",
    "iso:country":"GB",
    "sg:address":"Abingdon Chambers",
    "sg:city":"Blackpool",
    "sg:classifiers":[
        {
            "category":"Professional",
            "subcategory":"Accounting & Tax Preparation",
            "type":"Services"
        }
    ],
    "sg:phone":"+44 1253 626066",
    "sg:postcode":"FY1 1DG",
    "sg:province":"Lancashire",
    "sg:tags":[
        "accountant"
    ],
    "wof:name":"William Harling & Co",
    "wof:placetype":"venue"
},
  "geometry": {"coordinates":[-3.0537090302,53.8207397461],"type":"Point"}
}