{
  "type": "Feature",
  "properties": {
    "iso:country":"GB",
    "sg:address":"The Vineyards, Great Baddow",
    "sg:city":"Chelmsford",
    "sg:classifiers":[
        {
            "category":"Personal",
            "type":"Services"
        }
    ],
    "sg:phone":"+44 1245 478811",
    "sg:postcode":"CM99 1AA",
    "sg:province":"Essex",
    "sg:tags":[
        "delivery"
    ],
    "wof:name":"Royal Mail",
    "wof:placetype":"venue"
},
  "geometry": {"coordinates":[0.5007600188,51.7173995972],"type":"Point"}
}