{
  "type": "Feature",
  "properties": {
    "iso:country":"GB",
    "sg:address":"67 Carlisle Street",
    "sg:city":"Leicester",
    "sg:classifiers":[
        {
            "category":"Building & Trades",
            "subcategory":"Construction",
            "type":"Services"
        }
    ],
    "sg:phone":"+44 116 255 8285",
    "sg:postcode":"LE3 6AH",
    "sg:province":"Leicestershire",
    "sg:tags":[
        "builder"
    ],
    "wof:name":"Curson Building Contractors",
    "wof:placetype":"venue"
},
  "geometry": {"coordinates":[-1.157868,52.635078],"type":"Point"}
}