{
  "type": "Feature",
  "properties": {
    "addr:full":"Victoria House, 96 Newmarket Road Norwich Norfolk NR2 2LB",
    "addr:housenumber":"96",
    "addr:postcode":"nr2 2lb",
    "addr:street":"Newmarket Road Norwich Norfolk",
    "iso:country":"GB",
    "sg:address":"Victoria House, 96 Newmarket Road",
    "sg:city":"Norwich",
    "sg:classifiers":[
        {
            "category":"Personal",
            "subcategory":"Beauty Salon",
            "type":"Services"
        }
    ],
    "sg:phone":"+44 1603 504869",
    "sg:postcode":"NR2 2LB",
    "sg:province":"Norfolk",
    "wof:name":"Orchid Room for Beauty & Aromatherapy (The)",
    "wof:placetype":"venue"
},
  "geometry": {"coordinates":[1.2769449949,52.6173973083],"type":"Point"}
}