{
  "type": "Feature",
  "properties": {
    "addr:full":"24 Hill Rise Greenford Greater London UB6 8NZ",
    "addr:housenumber":"24",
    "addr:postcode":"ub6 8nz",
    "addr:street":"Hill Rise",
    "iso:country":"GB",
    "sg:address":"24 Hill Rise",
    "sg:city":"Greenford",
    "sg:classifiers":[
        {
            "category":"Communications",
            "type":"Services"
        }
    ],
    "sg:postcode":"UB6 8NZ",
    "sg:province":"Greater London",
    "sg:tags":[
        "telecommunication"
    ],
    "wof:name":"Glowlogic Ltd",
    "wof:placetype":"venue"
},
  "geometry": {"coordinates":[-0.3482249975,51.5423126221],"type":"Point"}
}