{
  "type": "Feature",
  "properties": {
    "iso:country":"GB",
    "sg:address":"Unit 2, Woodland Court, Soothouse Spring",
    "sg:city":"St Albans",
    "sg:classifiers":[
        {
            "category":"Professional",
            "subcategory":"Computer Services",
            "type":"Services"
        }
    ],
    "sg:phone":"+44 1727 855563",
    "sg:postcode":"AL3 6NR",
    "sg:province":"Hertfordshire",
    "sg:tags":[
        "system",
        "software"
    ],
    "wof:name":"Masterbill Micro Systems Ltd.",
    "wof:placetype":"venue"
},
  "geometry": {"coordinates":[-0.325369,51.770367],"type":"Point"}
}