{
  "type": "Feature",
  "properties": {
    "addr:full":"Dental Surgery, 16 Kiln Lane, Dentons Grn St Helens Merseyside WA10 6AD",
    "addr:housenumber":"16",
    "addr:postcode":"wa10 6ad",
    "addr:street":"Kiln Lane Dentons Grn",
    "iso:country":"GB",
    "sg:address":"Dental Surgery, 16 Kiln Lane, Dentons Grn",
    "sg:city":"St Helens",
    "sg:classifiers":[
        {
            "category":"Health Services",
            "subcategory":"Dentist",
            "type":"Services"
        }
    ],
    "sg:phone":"+44 1744 25776",
    "sg:postcode":"WA10 6AD",
    "sg:province":"Merseyside",
    "wof:name":"Kiln Lane Dental Surgery",
    "wof:placetype":"venue"
},
  "geometry": {"coordinates":[-2.7598,53.46209],"type":"Point"}
}