{
  "type": "Feature",
  "properties": {
    "iso:country":"GB",
    "sg:address":"De Courcy's Arcade, 5-21 Cresswell Lane",
    "sg:city":"Glasgow",
    "sg:classifiers":[
        {
            "category":"Shopping",
            "type":"Retail Goods"
        }
    ],
    "sg:phone":"+44 141 338 6010",
    "sg:postcode":"G12 8AA",
    "sg:province":"Glasgow City",
    "sg:tags":[
        "shop",
        "new age"
    ],
    "wof:name":"Opal Moon",
    "wof:placetype":"venue"
},
  "geometry": {"coordinates":[-4.2920279503,55.8756484985],"type":"Point"}
}