{
  "type": "Feature",
  "properties": {
    "addr:full":"Curzon Street Calne Wiltshire SN11 0DB",
    "addr:postcode":"sn11 0db",
    "addr:street":"Curzon Street",
    "iso:country":"GB",
    "sg:address":"Curzon Street",
    "sg:city":"Calne",
    "sg:classifiers":[
        {
            "category":"Bars & Pubs",
            "type":"Food & Drink"
        }
    ],
    "sg:phone":"+44 1249 814040",
    "sg:postcode":"SN11 0DB",
    "sg:province":"Wiltshire",
    "sg:tags":[
        "pubs",
        "inn"
    ],
    "wof:name":"The Wheatsheaf Inn",
    "wof:placetype":"venue"
},
  "geometry": {"coordinates":[-2.015166,51.440014],"type":"Point"}
}