{
  "type": "Feature",
  "properties": {
    "addr:full":"Unit 26, Coach Ho, Brunswick Square Bristol City of Bristol BS2 8QN",
    "addr:housenumber":"unit 26",
    "addr:postcode":"bs2 8qn",
    "addr:street":"Coach Ho Brunswick Square",
    "iso:country":"GB",
    "sg:address":"Unit 26, Coach Ho, Brunswick Square",
    "sg:city":"Bristol",
    "sg:classifiers":[
        {
            "category":"Professional",
            "subcategory":"Computer Services",
            "type":"Services"
        }
    ],
    "sg:postcode":"BS2 8QN",
    "sg:province":"City of Bristol",
    "sg:tags":[
        "consultant"
    ],
    "wof:name":"Mdc Training Ltd",
    "wof:placetype":"venue"
},
  "geometry": {"coordinates":[-2.588024,51.460434],"type":"Point"}
}