{
  "type": "Feature",
  "properties": {
    "addr:full":"62 Pitfields Road Oldbury West Midlands B68 0RQ",
    "addr:housenumber":"62",
    "addr:postcode":"b68 0rq",
    "addr:street":"Pitfields Road",
    "iso:country":"GB",
    "sg:address":"62 Pitfields Road",
    "sg:city":"Oldbury",
    "sg:classifiers":[
        {
            "category":"Building & Trades",
            "subcategory":"Construction",
            "type":"Services"
        }
    ],
    "sg:postcode":"B68 0RQ",
    "sg:province":"West Midlands",
    "sg:tags":[
        "builder"
    ],
    "wof:name":"C J Building & Roofing Services",
    "wof:placetype":"venue"
},
  "geometry": {"coordinates":[-2.0113420486,52.4687767029],"type":"Point"}
}