{
  "type": "Feature",
  "properties": {
    "addr:full":"207 Prescot Road Liverpool Merseyside L7 0LG",
    "addr:housenumber":"207",
    "addr:postcode":"l7 0lg",
    "addr:street":"Prescot Road",
    "iso:country":"GB",
    "sg:address":"207 Prescot Road",
    "sg:city":"Liverpool",
    "sg:classifiers":[
        {
            "category":"Building & Trades",
            "subcategory":"Construction",
            "type":"Services"
        }
    ],
    "sg:phone":"+44 151 228 5328",
    "sg:postcode":"L7 0LG",
    "sg:province":"Merseyside",
    "sg:tags":[
        "glass",
        "replacement"
    ],
    "wof:name":"W G Roberts & Son Glass & Glazing",
    "wof:placetype":"venue"
},
  "geometry": {"coordinates":[-2.9350891113,53.4140815735],"type":"Point"}
}