{
  "type": "Feature",
  "properties": {
    "iso:country":"GB",
    "sg:address":"The Leys, Loughborough Road, Hathern",
    "sg:city":"Loughborough",
    "sg:classifiers":[
        {
            "category":"Education",
            "subcategory":"Music School",
            "type":"Public Place"
        }
    ],
    "sg:phone":"+44 1509 646950",
    "sg:postcode":"LE12 5JB",
    "sg:province":"Leicestershire",
    "sg:tags":[
        "conservatory"
    ],
    "wof:name":"Peter Martin Windows & Conservatories",
    "wof:placetype":"venue"
},
  "geometry": {"coordinates":[-1.25617,52.792515],"type":"Point"}
}