{
  "type": "Feature",
  "properties": {
    "iso:country":"GB",
    "sg:address":"5-6 Church Street",
    "sg:city":"Seaham",
    "sg:classifiers":[
        {
            "category":"Personal",
            "subcategory":"Beauty Salon",
            "type":"Services"
        }
    ],
    "sg:phone":"+44 191 581 9858",
    "sg:postcode":"SR7 7HE",
    "sg:province":"Durham",
    "sg:tags":[
        "unisex",
        "hairdresser"
    ],
    "wof:name":"Kinkz Hairdressers",
    "wof:placetype":"venue"
},
  "geometry": {"coordinates":[-1.332054,54.836983],"type":"Point"}
}