{
  "type": "Feature",
  "properties": {
    "addr:full":"Chell Street, Hanley Stoke-on-trent Staffordshire ST1 6BA",
    "addr:postcode":"staffordshire st1 6ba",
    "addr:street":"Chell Street",
    "iso:country":"GB",
    "sg:address":"Chell Street, Hanley",
    "sg:city":"Stoke-on-trent",
    "sg:classifiers":[
        {
            "category":"Manufacturing",
            "subcategory":"Pottery",
            "type":"Manufacturing & Wholesale Goods"
        }
    ],
    "sg:phone":"+44 1782 266746",
    "sg:postcode":"ST1 6BA",
    "sg:province":"Staffordshire",
    "wof:name":"Superange Ltd.",
    "wof:placetype":"venue"
},
  "geometry": {"coordinates":[-2.1697590351,53.0369338989],"type":"Point"}
}