{
  "type": "Feature",
  "properties": {
    "addr:full":"7 Northbrooke Ashford Kent TN24 8DZ",
    "addr:housenumber":"7",
    "addr:postcode":"tn24 8dz",
    "addr:street":"Northbrooke",
    "iso:country":"GB",
    "sg:address":"7 Northbrooke",
    "sg:city":"Ashford",
    "sg:classifiers":[
        {
            "category":"Wholesale",
            "subcategory":"Scrap",
            "type":"Manufacturing & Wholesale Goods"
        }
    ],
    "sg:phone":"+44 1233 623572",
    "sg:postcode":"TN24 8DZ",
    "sg:province":"Kent",
    "sg:tags":[
        "waste",
        "metal"
    ],
    "wof:name":"G D Stevens",
    "wof:placetype":"venue"
},
  "geometry": {"coordinates":[0.876586,51.154751],"type":"Point"}
}