{
  "type": "Feature",
  "properties": {
    "addr:full":"Betws Parc Workshops, Park Street Ammanford Carmarthenshire SA18 2ET",
    "addr:housenumber":"betws",
    "addr:postcode":"sa18 2et",
    "addr:street":"Parc Workshops Park Street",
    "iso:country":"GB",
    "sg:address":"Betws Parc Workshops, Park Street",
    "sg:city":"Ammanford",
    "sg:classifiers":[
        {
            "category":"Manufacturing",
            "subcategory":"Petroleum Products",
            "type":"Manufacturing & Wholesale Goods"
        }
    ],
    "sg:phone":"+44 1269 592333",
    "sg:postcode":"SA18 2ET",
    "sg:province":"Carmarthenshire",
    "sg:tags":[
        "double",
        "glazing"
    ],
    "wof:name":"Profab 2000",
    "wof:placetype":"venue"
},
  "geometry": {"coordinates":[-3.985546,51.780876],"type":"Point"}
}