{
  "type": "Feature",
  "properties": {
    "addr:full":"262 Great North Road, Woodlands Doncaster North Yorkshire DN6 7HP",
    "addr:housenumber":"262",
    "addr:postcode":"dn6 7hp",
    "addr:street":"Great North Road",
    "iso:country":"GB",
    "sg:address":"262 Great North Road, Woodlands",
    "sg:city":"Doncaster",
    "sg:classifiers":[
        {
            "category":"Food & Beverages",
            "subcategory":"Bakery",
            "type":"Retail Goods"
        }
    ],
    "sg:phone":"+44 1302 723512",
    "sg:postcode":"DN6 7HP",
    "sg:province":"North Yorkshire",
    "sg:tags":[
        "shop",
        "baker"
    ],
    "wof:name":"COOPLANDS (DONCASTER) LTD",
    "wof:placetype":"venue"
},
  "geometry": {"coordinates":[-1.1875040531,53.5609359741],"type":"Point"}
}