{
  "type": "Feature",
  "properties": {
    "iso:country":"GB",
    "sg:address":"37 Compton Court, Compton Road",
    "sg:city":"Coventry",
    "sg:classifiers":[
        {
            "category":"Retail",
            "subcategory":"Event Space",
            "type":"Services"
        }
    ],
    "sg:phone":"+44 24 7658 1481",
    "sg:postcode":"CV6 6GZ",
    "sg:province":"Warwickshire",
    "sg:tags":[
        "product",
        "disposable",
        "dom"
    ],
    "wof:name":"Premium Health Care",
    "wof:placetype":"venue"
},
  "geometry": {"coordinates":[-1.50243,52.443432],"type":"Point"}
}