{
  "type": "Feature",
  "properties": {
    "iso:country":"GB",
    "sg:address":"Sunflower Cottage, Deaks Lane, Ansty",
    "sg:city":"Haywards Heath",
    "sg:classifiers":[
        {
            "category":"Building & Trades",
            "subcategory":"Construction",
            "type":"Services"
        }
    ],
    "sg:phone":"+44 1444 452650",
    "sg:postcode":"RH17 5AS",
    "sg:province":"East Sussex",
    "sg:tags":[
        "ceiling",
        "contractor"
    ],
    "wof:name":"Joseph Mallett",
    "wof:placetype":"venue"
},
  "geometry": {"coordinates":[-0.161602,50.994526],"type":"Point"}
}