{
  "type": "Feature",
  "properties": {
    "iso:country":"GB",
    "sg:address":"60 Beauchamp Place",
    "sg:city":"London",
    "sg:classifiers":[
        {
            "category":"Shopping",
            "subcategory":"Comic Books",
            "type":"Retail Goods"
        }
    ],
    "sg:phone":"+44 20 7589 8474",
    "sg:postcode":"SW3 1NZ",
    "sg:province":"Greater London",
    "sg:tags":[
        "jeweller"
    ],
    "wof:name":"Dower & Hall",
    "wof:placetype":"venue"
},
  "geometry": {"coordinates":[-0.166156,51.498032],"type":"Point"}
}