{
  "type": "Feature",
  "properties": {
    "addr:full":"135c Sheen Lane, East Sheen Mortlake Greater London SW14 8AE",
    "addr:housenumber":"135c",
    "addr:postcode":"sw14 8ae",
    "addr:street":"Sheen Lane",
    "iso:country":"GB",
    "sg:address":"135c Sheen Lane, East Sheen",
    "sg:city":"Mortlake",
    "sg:classifiers":[
        {
            "category":"Professional",
            "subcategory":"Art Services",
            "type":"Services"
        }
    ],
    "sg:phone":"+44 20 8878 4835",
    "sg:postcode":"SW14 8AE",
    "sg:province":"Greater London",
    "sg:tags":[
        "consultant",
        "design"
    ],
    "wof:name":"Heurtey Kenward Ltd",
    "wof:placetype":"venue"
},
  "geometry": {"coordinates":[-0.2662169933,51.4646339417],"type":"Point"}
}