{
  "type": "Feature",
  "properties": {
    "addr:full":"Unit F Morgan Street Works, Llanbradach Caerphilly Caerphilly CF8 1BQ",
    "addr:postcode":"cf8 1bq",
    "addr:street":"Morgan Street",
    "iso:country":"GB",
    "sg:address":"Unit F Morgan Street Works, Llanbradach",
    "sg:city":"Caerphilly",
    "sg:classifiers":[
        {
            "category":"Manufacturing",
            "subcategory":"Metals",
            "type":"Manufacturing & Wholesale Goods"
        }
    ],
    "sg:phone":"+44 29 2086 6661",
    "sg:postcode":"CF8 1BQ",
    "sg:province":"Caerphilly",
    "sg:tags":[
        "steel",
        "fabricator",
        "erectors"
    ],
    "wof:name":"A & R Design & Manufacturers Ltd",
    "wof:placetype":"venue"
},
  "geometry": {"coordinates":[-3.227449894,51.6112098694],"type":"Point"}
}