{
  "type": "Feature",
  "properties": {
    "addr:full":"The British Waterways Depot Brentford Greater London TW8 0AB",
    "addr:postcode":"tw8 0ab",
    "addr:street":"Brentford",
    "iso:country":"GB",
    "sg:address":"The British Waterways Depot",
    "sg:city":"Brentford",
    "sg:classifiers":[
        {
            "category":"Building & Trades",
            "subcategory":"Construction",
            "type":"Services"
        }
    ],
    "sg:postcode":"TW8 0AB",
    "sg:province":"Greater London",
    "sg:tags":[
        "demolition",
        "contractor"
    ],
    "wof:name":"Gregory Demolition Ltd.",
    "wof:placetype":"venue"
},
  "geometry": {"coordinates":[-0.306724,51.484135],"type":"Point"}
}