{
  "type": "Feature",
  "properties": {
    "addr:full":"45 Hill Top Knottingley North Yorkshire WF11 9AQ",
    "addr:housenumber":"45",
    "addr:postcode":"wf11 9aq",
    "addr:street":"Hill Top Knottingley",
    "iso:country":"GB",
    "sg:address":"45 Hill Top",
    "sg:city":"Knottingley",
    "sg:classifiers":[
        {
            "category":"Health Services",
            "subcategory":"Dentist",
            "type":"Services"
        }
    ],
    "sg:postcode":"WF11 9AQ",
    "sg:province":"North Yorkshire",
    "wof:name":"G M & R S Eades",
    "wof:placetype":"venue"
},
  "geometry": {"coordinates":[-1.2457849979,53.7098388672],"type":"Point"}
}