{
  "type": "Feature",
  "properties": {
    "addr:full":"215 Lower Blandford Rd Broadstone Dorset BH18 8DN",
    "addr:housenumber":"215",
    "addr:postcode":"bh18 8dn",
    "addr:street":"Lower Blandford Rd",
    "iso:country":"GB",
    "sg:address":"215 Lower Blandford Rd",
    "sg:city":"Broadstone",
    "sg:classifiers":[
        {
            "category":"Fast Food",
            "type":"Food & Drink"
        }
    ],
    "sg:phone":"+44 1202 690862",
    "sg:postcode":"BH18 8DN",
    "sg:province":"Dorset",
    "sg:tags":[
        "away",
        "meal",
        "outlet",
        "take"
    ],
    "wof:name":"Maxs Takeaway",
    "wof:placetype":"venue"
},
  "geometry": {"coordinates":[-1.9955430031,50.7609138489],"type":"Point"}
}