{
  "type": "Feature",
  "properties": {
    "addr:full":"133 Brettell Lane, Amblecote Stourbridge Staffordshire DY8 4BA",
    "addr:housenumber":"133",
    "addr:postcode":"dy8 4ba",
    "addr:street":"Brettell Lane",
    "iso:country":"GB",
    "sg:address":"133 Brettell Lane, Amblecote",
    "sg:city":"Stourbridge",
    "sg:classifiers":[
        {
            "category":"Home & Garden",
            "subcategory":"Furniture",
            "type":"Retail Goods"
        }
    ],
    "sg:phone":"+44 1384 375933",
    "sg:postcode":"DY8 4BA",
    "sg:province":"Staffordshire",
    "sg:tags":[
        "outlet"
    ],
    "wof:name":"Amblecote Furnishers",
    "wof:placetype":"venue"
},
  "geometry": {"coordinates":[-2.153366,52.471066],"type":"Point"}
}