{
  "type": "Feature",
  "properties": {
    "iso:country":"GB",
    "sg:address":"P O Box 180",
    "sg:city":"Bournemouth",
    "sg:classifiers":[
        {
            "category":"Health Services",
            "subcategory":"Health Practitioner",
            "type":"Services"
        }
    ],
    "sg:phone":"+44 1202 318099",
    "sg:postcode":"BH3 7YR",
    "sg:province":"Dorset",
    "sg:tags":[
        "hypnotherapists"
    ],
    "wof:name":"H C B Hypnotherapists",
    "wof:placetype":"venue"
},
  "geometry": {"coordinates":[-1.88191,50.736401],"type":"Point"}
}