{
  "type": "Feature",
  "properties": {
    "addr:full":"Out Newton Road Withernsea East Riding of Yorkshire HU19 2RD",
    "addr:postcode":"hu19 2rd",
    "addr:street":"Out Newton Road",
    "iso:country":"GB",
    "sg:address":"Out Newton Road",
    "sg:city":"Withernsea",
    "sg:classifiers":[
        {
            "category":"Retail",
            "subcategory":"Auto Repair",
            "type":"Services"
        }
    ],
    "sg:postcode":"HU19 2RD",
    "sg:province":"East Riding of Yorkshire",
    "sg:tags":[
        "modification",
        "garage"
    ],
    "wof:name":"Holmpton Garage",
    "wof:placetype":"venue"
},
  "geometry": {"coordinates":[0.0330349989,53.7302818298],"type":"Point"}
}