{
  "type": "Feature",
  "properties": {
    "addr:full":"Victoria Square Gateshead Tyne and Wear NE10 9LX",
    "addr:postcode":"ne10 9lx",
    "addr:street":"Square",
    "iso:country":"GB",
    "sg:address":"Victoria Square",
    "sg:city":"Gateshead",
    "sg:classifiers":[
        {
            "category":"Organizations",
            "subcategory":"Membership Organization",
            "type":"Services"
        }
    ],
    "sg:phone":"+44 191 469 2336",
    "sg:postcode":"NE10 9LX",
    "sg:province":"Tyne and Wear",
    "sg:tags":[
        "club"
    ],
    "wof:name":"Imperia Bingo & Social Club",
    "wof:placetype":"venue"
},
  "geometry": {"coordinates":[-1.5736340284,54.9469108582],"type":"Point"}
}