{
  "type": "Feature",
  "properties": {
    "iso:country":"GB",
    "sg:address":"Unit 5 Deeside Shopping Centre, Connah's Quay",
    "sg:city":"Deeside",
    "sg:classifiers":[
        {
            "category":"Shopping",
            "subcategory":"Pets & Pet Supplies",
            "type":"Retail Goods"
        }
    ],
    "sg:phone":"+44 1244 810724",
    "sg:postcode":"CH5 4NX",
    "sg:province":"Flintshire",
    "sg:tags":[
        "food"
    ],
    "wof:name":"Pet Save",
    "wof:placetype":"venue"
},
  "geometry": {"coordinates":[-3.05036,53.215961],"type":"Point"}
}