{
  "type": "Feature",
  "properties": {
    "addr:full":"15-17 Moss Street Paisley Renfrewshire PA1 1BQ",
    "addr:housenumber":"15-17",
    "addr:postcode":"pa1 1bq",
    "addr:street":"Moss Street",
    "iso:country":"GB",
    "sg:address":"15-17 Moss Street",
    "sg:city":"Paisley",
    "sg:classifiers":[
        {
            "category":"Food & Beverages",
            "subcategory":"Liquor & Beverages",
            "type":"Retail Goods"
        }
    ],
    "sg:phone":"+44 141 848 9490",
    "sg:postcode":"PA1 1BQ",
    "sg:province":"Renfrewshire",
    "sg:tags":[
        "beer",
        "spirit",
        "wines"
    ],
    "wof:name":"Victoria Wines",
    "wof:placetype":"venue"
},
  "geometry": {"coordinates":[-4.425075,55.846275],"type":"Point"}
}