{
  "type": "Feature",
  "properties": {
    "addr:full":"17 Orchard Close, Blackwater Camberley Hampshire GU17 9EX",
    "addr:housenumber":"17",
    "addr:postcode":"gu17 9ex",
    "addr:street":"Orchard Close",
    "iso:country":"GB",
    "sg:address":"17 Orchard Close, Blackwater",
    "sg:city":"Camberley",
    "sg:classifiers":[
        {
            "category":"Building & Trades",
            "subcategory":"Construction",
            "type":"Services"
        }
    ],
    "sg:postcode":"GU17 9EX",
    "sg:province":"Hampshire",
    "sg:tags":[
        "builder"
    ],
    "wof:name":"D King Builder",
    "wof:placetype":"venue"
},
  "geometry": {"coordinates":[-0.7684320211,51.3171195984],"type":"Point"}
}