{
  "type": "Feature",
  "properties": {
    "addr:full":"Care Of Fenwicks Department Store, Royal Victoria Place Tunbridge Wells Kent TN1 2SR",
    "addr:postcode":"tn1 2sr",
    "addr:street":"Victoria Place",
    "iso:country":"GB",
    "sg:address":"Care Of Fenwicks Department Store, Royal Victoria Place",
    "sg:city":"Tunbridge Wells",
    "sg:classifiers":[
        {
            "category":"Shopping",
            "subcategory":"Shoes",
            "type":"Retail Goods"
        }
    ],
    "sg:phone":"+44 1892 547147",
    "sg:postcode":"TN1 2SR",
    "sg:province":"Kent",
    "sg:tags":[
        "shop"
    ],
    "wof:name":"The Shoe Studio Group Ltd.",
    "wof:placetype":"venue"
},
  "geometry": {"coordinates":[0.26355,51.133373],"type":"Point"}
}