{
  "type": "Feature",
  "properties": {
    "addr:full":"46 Lowther Ave Chester-le-street Durham DH2 3BN",
    "addr:housenumber":"46",
    "addr:postcode":"dh2 3bn",
    "addr:street":"Lowther Ave",
    "iso:country":"GB",
    "sg:address":"46 Lowther Ave",
    "sg:city":"Chester-le-street",
    "sg:classifiers":[
        {
            "category":"Retail",
            "subcategory":"Auto Repair",
            "type":"Services"
        }
    ],
    "sg:postcode":"DH2 3BN",
    "sg:province":"Durham",
    "sg:tags":[
        "modification",
        "garage"
    ],
    "wof:name":"Cruddas,Richard,",
    "wof:placetype":"venue"
},
  "geometry": {"coordinates":[-1.588389,54.849285],"type":"Point"}
}