{
  "type": "Feature",
  "properties": {
    "addr:full":"110c Bradford St, Digbeth Birmingham West Midlands B12 0NS",
    "addr:housenumber":"110c",
    "addr:postcode":"b12 0ns",
    "addr:street":"Bradford St",
    "iso:country":"GB",
    "sg:address":"110c Bradford St, Digbeth",
    "sg:city":"Birmingham",
    "sg:classifiers":[
        {
            "category":"Wholesale",
            "subcategory":"Metals & Minerals",
            "type":"Manufacturing & Wholesale Goods"
        }
    ],
    "sg:phone":"+44 121 248 8404",
    "sg:postcode":"B12 0NS",
    "sg:province":"West Midlands",
    "sg:tags":[
        "equipment",
        "finishing"
    ],
    "wof:name":"M & M Metal Polishing",
    "wof:placetype":"venue"
},
  "geometry": {"coordinates":[-1.881779,52.47163],"type":"Point"}
}