{
  "type": "Feature",
  "properties": {
    "addr:full":"467 Moorside Road, Urmston Manchester Cheshire M41 8TW",
    "addr:housenumber":"467",
    "addr:postcode":"m41 8tw",
    "addr:street":"Moorside Road",
    "iso:country":"GB",
    "sg:address":"467 Moorside Road, Urmston",
    "sg:city":"Manchester",
    "sg:classifiers":[
        {
            "category":"Home & Garden",
            "subcategory":"Carpets & Floor Coverings",
            "type":"Retail Goods"
        }
    ],
    "sg:phone":"+44 161 748 3082",
    "sg:postcode":"M41 8TW",
    "sg:province":"Cheshire",
    "sg:tags":[
        "carpets",
        "rug",
        "matting"
    ],
    "wof:name":"Ian Dewar Interiors",
    "wof:placetype":"venue"
},
  "geometry": {"coordinates":[-2.391476,53.452469],"type":"Point"}
}