{
  "type": "Feature",
  "properties": {
    "addr:full":"Pendle Ho, Mkt Sq Burnley Lancashire BB11 1AX",
    "addr:postcode":"bb11 1ax",
    "addr:street":"Mkt Sq",
    "iso:country":"GB",
    "sg:address":"Pendle Ho, Mkt Sq",
    "sg:city":"Burnley",
    "sg:classifiers":[
        {
            "category":"Shopping",
            "subcategory":"Department Store",
            "type":"Retail Goods"
        }
    ],
    "sg:postcode":"BB11 1AX",
    "sg:province":"Lancashire",
    "wof:name":"Co-Operative Group (C W S) Ltd",
    "wof:placetype":"venue"
},
  "geometry": {"coordinates":[-2.2438089848,53.7880096436],"type":"Point"}
}