{
  "type": "Feature",
  "properties": {
    "addr:full":"Mascalls Way Chelmsford Essex CM2 7NS",
    "addr:postcode":"cm2 7ns",
    "addr:street":"Mascalls Way",
    "iso:country":"GB",
    "sg:address":"Mascalls Way",
    "sg:city":"Chelmsford",
    "sg:classifiers":[
        {
            "category":"Government",
            "subcategory":"Office",
            "type":"Public Place"
        }
    ],
    "sg:postcode":"CM2 7NS",
    "sg:province":"Essex",
    "sg:tags":[
        "local",
        "agency",
        "education",
        "authority"
    ],
    "wof:name":"Essex County Council",
    "wof:placetype":"venue"
},
  "geometry": {"coordinates":[0.4936000109,51.7245635986],"type":"Point"}
}