{
  "type": "Feature",
  "properties": {
    "addr:full":"5 Glan Nant Clo Caerphilly Caerphilly CF83 1EE",
    "addr:housenumber":"5",
    "addr:postcode":"cf83 1ee",
    "addr:street":"Glan Nant Clo",
    "iso:country":"GB",
    "sg:address":"5 Glan Nant Clo",
    "sg:city":"Caerphilly",
    "sg:classifiers":[
        {
            "category":"Place Of Worship",
            "type":"Public Place"
        }
    ],
    "sg:phone":"+44 29 2086 6622",
    "sg:postcode":"CF83 1EE",
    "sg:province":"Caerphilly",
    "wof:name":"Caerphilly Evangelical Independent Church",
    "wof:placetype":"venue"
},
  "geometry": {"coordinates":[-3.225532,51.569904],"type":"Point"}
}