{
  "type": "Feature",
  "properties": {
    "iso:country":"GB",
    "sg:address":"36 Rugby Road, Wollaston",
    "sg:city":"Stourbridge",
    "sg:classifiers":[
        {
            "category":"Building & Trades",
            "subcategory":"Plumbing",
            "type":"Services"
        }
    ],
    "sg:postcode":"DY8 4RJ",
    "sg:province":"Staffordshire",
    "sg:tags":[
        "central",
        "heating"
    ],
    "wof:name":"T H B Heating & Plumbing",
    "wof:placetype":"venue"
},
  "geometry": {"coordinates":[-2.163496,52.465199],"type":"Point"}
}