{
  "type": "Feature",
  "properties": {
    "addr:full":"Elstree Road, Elstree Borehamwood Hertfordshire WD6 3EA",
    "addr:postcode":"wd6 3ea",
    "addr:street":"Elstree Road",
    "iso:country":"GB",
    "sg:address":"Elstree Road, Elstree",
    "sg:city":"Borehamwood",
    "sg:classifiers":[
        {
            "category":"Building & Trades",
            "subcategory":"Construction",
            "type":"Services"
        }
    ],
    "sg:phone":"+44 20 8953 4144",
    "sg:postcode":"WD6 3EA",
    "sg:province":"Hertfordshire",
    "sg:tags":[
        "builder"
    ],
    "wof:name":"McNicholas Construction Services Ltd.",
    "wof:placetype":"venue"
},
  "geometry": {"coordinates":[-0.3223179877,51.6424980164],"type":"Point"}
}