{
  "type": "Feature",
  "properties": {
    "iso:country":"GB",
    "sg:address":"14 Granville Road",
    "sg:city":"Harrogate",
    "sg:classifiers":[
        {
            "category":"Real Estate",
            "subcategory":"Real Estate Agent",
            "type":"Services"
        }
    ],
    "sg:postcode":"HG1 1BY",
    "sg:province":"North Yorkshire",
    "wof:name":"Town & Countryside Letting",
    "wof:placetype":"venue"
},
  "geometry": {"coordinates":[-1.5406719446,53.9954299927],"type":"Point"}
}