{
  "type": "Feature",
  "properties": {
    "addr:full":"14 Granville Road Harrogate North Yorkshire HG1 1BY",
    "addr:housenumber":"14",
    "addr:postcode":"hg1 1by",
    "addr:street":"Granville Road",
    "iso:country":"GB",
    "sg:address":"14 Granville Road",
    "sg:city":"Harrogate",
    "sg:classifiers":[
        {
            "category":"Real Estate",
            "subcategory":"Real Estate Agent",
            "type":"Services"
        }
    ],
    "sg:postcode":"HG1 1BY",
    "sg:province":"North Yorkshire",
    "wof:name":"Town & Countryside Letting",
    "wof:placetype":"venue"
},
  "geometry": {"coordinates":[-1.5406719446,53.9954299927],"type":"Point"}
}