{
  "type": "Feature",
  "properties": {
    "iso:country":"GB",
    "sg:address":"1 Newton Terrace, Bucksburn",
    "sg:city":"Aberdeen",
    "sg:classifiers":[
        {
            "category":"Building & Trades",
            "subcategory":"Construction",
            "type":"Services"
        }
    ],
    "sg:phone":"+44 1224 712218",
    "sg:postcode":"AB21 9LP",
    "sg:province":"Aberdeen City",
    "sg:tags":[
        "dry",
        "lining",
        "plasterers",
        "screeders"
    ],
    "wof:name":"John L Davie & Son",
    "wof:placetype":"venue"
},
  "geometry": {"coordinates":[-2.167274,57.177113],"type":"Point"}
}