{
  "type": "Feature",
  "properties": {
    "iso:country":"GB",
    "sg:address":"3-4 Wellington Lane",
    "sg:city":"Stamford",
    "sg:classifiers":[
        {
            "category":"Professional",
            "subcategory":"Art Services",
            "type":"Services"
        }
    ],
    "sg:phone":"+44 1780 757673",
    "sg:postcode":"PE9 1QB",
    "sg:province":"Cambridgeshire",
    "sg:tags":[
        "photographer"
    ],
    "wof:name":"Don Lambert Photography",
    "wof:placetype":"venue"
},
  "geometry": {"coordinates":[-0.479674,52.652325],"type":"Point"}
}