{
  "type": "Feature",
  "properties": {
    "iso:country":"GB",
    "sg:address":"Arley Grange, Burnham Rd, Latchingdon",
    "sg:city":"Chelmsford",
    "sg:classifiers":[
        {
            "category":"Recreation",
            "subcategory":"Sailing Club",
            "type":"Entertainment"
        }
    ],
    "sg:phone":"+44 1621 741820",
    "sg:postcode":"CM3 6EY",
    "sg:province":"Essex",
    "wof:name":"East Coast Sale Trust",
    "wof:placetype":"venue"
},
  "geometry": {"coordinates":[0.726811,51.671715],"type":"Point"}
}