{
  "type": "Feature",
  "properties": {
    "iso:country":"GB",
    "sg:address":"31 Etheldene Avenue, Muswell Hill",
    "sg:city":"London",
    "sg:classifiers":[
        {
            "category":"Professional",
            "subcategory":"Advertising",
            "type":"Services"
        }
    ],
    "sg:postcode":"N10 3QG",
    "sg:province":"Greater London",
    "sg:tags":[
        "agency"
    ],
    "wof:name":"Stage Display Ltd",
    "wof:placetype":"venue"
},
  "geometry": {"coordinates":[-0.135936,51.586872],"type":"Point"}
}