{
  "type": "Feature",
  "properties": {
    "addr:full":"31 Etheldene Avenue, Muswell Hill London Greater London N10 3QG",
    "addr:housenumber":"31",
    "addr:postcode":"n10 3qg",
    "addr:street":"Etheldene Avenue",
    "iso:country":"GB",
    "sg:address":"31 Etheldene Avenue, Muswell Hill",
    "sg:city":"London",
    "sg:classifiers":[
        {
            "category":"Professional",
            "subcategory":"Advertising",
            "type":"Services"
        }
    ],
    "sg:postcode":"N10 3QG",
    "sg:province":"Greater London",
    "sg:tags":[
        "agency"
    ],
    "wof:name":"Stage Display Ltd",
    "wof:placetype":"venue"
},
  "geometry": {"coordinates":[-0.135936,51.586872],"type":"Point"}
}