{
  "type": "Feature",
  "properties": {
    "addr:full":"124 Stricklandgate Kendal Cumbria LA9 4QG",
    "addr:housenumber":"124",
    "addr:postcode":"la9 4qg",
    "addr:street":"Stricklandgate",
    "iso:country":"GB",
    "sg:address":"124 Stricklandgate",
    "sg:city":"Kendal",
    "sg:classifiers":[
        {
            "category":"Fast Food",
            "type":"Food & Drink"
        }
    ],
    "sg:phone":"+44 1539 724843",
    "sg:postcode":"LA9 4QG",
    "sg:province":"Cumbria",
    "sg:tags":[
        "away",
        "take"
    ],
    "wof:name":"Deja-Vous in Kendal",
    "wof:placetype":"venue"
},
  "geometry": {"coordinates":[-2.747506,54.330433],"type":"Point"}
}