{
  "type": "Feature",
  "properties": {
    "addr:full":"Worcester Road Droitwich Worcestershire WR9 8AJ",
    "addr:postcode":"wr9 8aj",
    "addr:street":"Worcester Road",
    "iso:country":"GB",
    "sg:address":"Worcester Road",
    "sg:city":"Droitwich",
    "sg:classifiers":[
        {
            "category":"Bars & Pubs",
            "type":"Food & Drink"
        }
    ],
    "sg:phone":"+44 1905 778845",
    "sg:postcode":"WR9 8AJ",
    "sg:province":"Worcestershire",
    "sg:tags":[
        "pubs",
        "inn"
    ],
    "wof:name":"Trotter Hall",
    "wof:placetype":"venue"
},
  "geometry": {"coordinates":[-2.1460740566,52.2678184509],"type":"Point"}
}