{
  "type": "Feature",
  "properties": {
    "iso:country":"GB",
    "sg:address":"Brynyreos, Rhydyfelin",
    "sg:city":"Aberystwyth",
    "sg:classifiers":[
        {
            "category":"Social Services",
            "subcategory":"Job Training",
            "type":"Services"
        }
    ],
    "sg:postcode":"SY23 4LU",
    "sg:province":"Ceredigion",
    "sg:tags":[
        "translator",
        "interpreter"
    ],
    "wof:name":"Oriel Associates",
    "wof:placetype":"venue"
},
  "geometry": {"coordinates":[-4.069353,52.392597],"type":"Point"}
}