{
  "type": "Feature",
  "properties": {
    "iso:country":"GB",
    "sg:address":"Pottery Rd",
    "sg:city":"Newton Abbot",
    "sg:classifiers":[
        {
            "category":"Home & Garden",
            "subcategory":"Furniture",
            "type":"Retail Goods"
        }
    ],
    "sg:phone":"+44 1626 204604",
    "sg:postcode":"TQ12 3BN",
    "sg:province":"Devon",
    "wof:name":"Suiteworld",
    "wof:placetype":"venue"
},
  "geometry": {"coordinates":[-3.598739,50.541519],"type":"Point"}
}