{
  "type": "Feature",
  "properties": {
    "addr:full":"Station Approach Sheringham Norfolk NR26 8RA",
    "addr:postcode":"nr26 8ra",
    "addr:street":"Station Approach",
    "iso:country":"GB",
    "sg:address":"Station Approach",
    "sg:city":"Sheringham",
    "sg:classifiers":[
        {
            "category":"Banks & Credit Unions",
            "subcategory":"Investment Brokerage",
            "type":"Services"
        },
        {
            "category":"Train Station",
            "subcategory":"Rail",
            "type":"Transportation"
        }
    ],
    "sg:phone":"+44 1263 860808",
    "sg:postcode":"NR26 8RA",
    "sg:province":"Norfolk",
    "sg:tags":[
        "operator",
        "railway"
    ],
    "wof:name":"North Norfolk Railway plc",
    "wof:placetype":"venue"
},
  "geometry": {"coordinates":[1.2109849453,52.9405517578],"type":"Point"}
}