{
  "type": "Feature",
  "properties": {
    "addr:full":"6-10 The Shambles Malton North Yorkshire YO17 7LZ",
    "addr:housenumber":"6-10",
    "addr:postcode":"yo17 7lz",
    "addr:street":"The Shambles",
    "iso:country":"GB",
    "sg:address":"6-10 The Shambles",
    "sg:city":"Malton",
    "sg:classifiers":[
        {
            "category":"Personal",
            "subcategory":"Shoe Repair & Shine",
            "type":"Services"
        },
        {
            "category":"Shopping",
            "subcategory":"Shoes",
            "type":"Retail Goods"
        }
    ],
    "sg:phone":"+44 1653 697599",
    "sg:postcode":"YO17 7LZ",
    "sg:province":"North Yorkshire",
    "wof:name":"Country Cobbler",
    "wof:placetype":"venue"
},
  "geometry": {"coordinates":[-0.7998759747,54.1357345581],"type":"Point"}
}