{
  "type": "Feature",
  "properties": {
    "iso:country":"GB",
    "sg:address":"10 Mills Walk",
    "sg:city":"Sandy",
    "sg:classifiers":[
        {
            "category":"Communications",
            "subcategory":"Film & Video Production",
            "type":"Services"
        }
    ],
    "sg:phone":"+44 1767 681369",
    "sg:postcode":"SG19 1LR",
    "sg:province":"Bedfordshire",
    "sg:tags":[
        "pr",
        "telemarketing"
    ],
    "wof:name":"Sarah Sales & Marketing",
    "wof:placetype":"venue"
},
  "geometry": {"coordinates":[-0.291671,52.131695],"type":"Point"}
}