{
  "type": "Feature",
  "properties": {
    "addr:full":"Swallow House, Swallow Street Manchester Greater Manchester M12 4GH",
    "addr:postcode":"m12 4gh",
    "addr:street":"Swallow Street",
    "iso:country":"GB",
    "sg:address":"Swallow House, Swallow Street",
    "sg:city":"Manchester",
    "sg:classifiers":[
        {
            "category":"Shopping",
            "subcategory":"Clothing, Apparel, & Fashions",
            "type":"Retail Goods"
        }
    ],
    "sg:postcode":"M12 4GH",
    "sg:province":"Greater Manchester",
    "sg:tags":[
        "lingerie"
    ],
    "wof:name":"Swallow Hosiery",
    "wof:placetype":"venue"
},
  "geometry": {"coordinates":[-2.194049,53.449696],"type":"Point"}
}