{
  "type": "Feature",
  "properties": {
    "iso:country":"GB",
    "sg:address":"Moulton Rd",
    "sg:city":"Northampton",
    "sg:classifiers":[
        {
            "category":"Arena",
            "subcategory":"Stadium",
            "type":"Entertainment"
        },
        {
            "category":"Arena",
            "subcategory":"Sports Club",
            "type":"Entertainment"
        }
    ],
    "sg:phone":"+44 1604 494790",
    "sg:postcode":"NN6 9SH",
    "sg:province":"Northamptonshire",
    "sg:tags":[
        "ground"
    ],
    "wof:name":"Northfields Cricket Ground",
    "wof:placetype":"venue"
},
  "geometry": {"coordinates":[-0.844276011,52.3161506653],"type":"Point"}
}