{
  "type": "Feature",
  "properties": {
    "addr:full":"North Road Industrial Estate Berwick-upon-tweed Northumberland TD15 1UN",
    "addr:postcode":"td15 1un",
    "addr:street":"North Road Industrial Estate;Northumberland",
    "iso:country":"GB",
    "sg:address":"North Road Industrial Estate",
    "sg:city":"Berwick-upon-tweed",
    "sg:classifiers":[
        {
            "category":"Personal",
            "type":"Services"
        }
    ],
    "sg:phone":"+44 1289 330472",
    "sg:postcode":"TD15 1UN",
    "sg:province":"Northumberland",
    "sg:tags":[
        "delivery"
    ],
    "wof:name":"Shunters Borders",
    "wof:placetype":"venue"
},
  "geometry": {"coordinates":[-2.011494,55.781616],"type":"Point"}
}