{
  "type": "Feature",
  "properties": {
    "addr:full":"6 Union Street Leven Fife KY8 4NJ",
    "addr:housenumber":"6",
    "addr:postcode":"ky8 4nj",
    "addr:street":"Union Street",
    "iso:country":"GB",
    "sg:address":"6 Union Street",
    "sg:city":"Leven",
    "sg:classifiers":[
        {
            "category":"Wholesale",
            "subcategory":"Machinery & Supplies",
            "type":"Manufacturing & Wholesale Goods"
        }
    ],
    "sg:phone":"+44 1333 427727",
    "sg:postcode":"KY8 4NJ",
    "sg:province":"Fife",
    "sg:tags":[
        "industrial",
        "commercial"
    ],
    "wof:name":"Key Industrial Equipment Ltd.",
    "wof:placetype":"venue"
},
  "geometry": {"coordinates":[-2.9988610744,56.193939209],"type":"Point"}
}