{
  "type": "Feature",
  "properties": {
    "addr:full":"Main Street, Wray Lancaster Lancashire LA2 8QD",
    "addr:postcode":"la2 8qd",
    "addr:street":"Main Street",
    "iso:country":"GB",
    "sg:address":"Main Street, Wray",
    "sg:city":"Lancaster",
    "sg:classifiers":[
        {
            "category":"Government",
            "subcategory":"Post Office",
            "type":"Public Place"
        }
    ],
    "sg:phone":"+44 15242 21253",
    "sg:postcode":"LA2 8QD",
    "sg:province":"Lancashire",
    "wof:name":"P O Wray",
    "wof:placetype":"venue"
},
  "geometry": {"coordinates":[-2.608847,54.10355],"type":"Point"}
}