{
  "type": "Feature",
  "properties": {
    "iso:country":"GB",
    "sg:address":"9a Church Lane",
    "sg:city":"Barnstaple",
    "sg:classifiers":[
        {
            "category":"Personal",
            "type":"Services"
        },
        {
            "category":"Professional",
            "subcategory":"Lawyer & Legal Services",
            "type":"Services"
        }
    ],
    "sg:phone":"+44 1271 379719",
    "sg:postcode":"EX31 1BH",
    "sg:province":"Devon",
    "sg:tags":[
        "advice",
        "counselling"
    ],
    "wof:name":"Cruse Bereavement Care",
    "wof:placetype":"venue"
},
  "geometry": {"coordinates":[-4.059279,51.079464],"type":"Point"}
}