{
  "type": "Feature",
  "properties": {
    "addr:full":"Woodrolfe Road Maldon Essex CM9 8SJ",
    "addr:postcode":"cm9 8sj",
    "addr:street":"Woodrolfe Road",
    "iso:country":"GB",
    "sg:address":"Woodrolfe Road",
    "sg:city":"Maldon",
    "sg:classifiers":[
        {
            "category":"Manufacturing",
            "subcategory":"Signs",
            "type":"Manufacturing & Wholesale Goods"
        }
    ],
    "sg:phone":"+44 1621 860579",
    "sg:postcode":"CM9 8SJ",
    "sg:province":"Essex",
    "sg:tags":[
        "nameplate"
    ],
    "wof:name":"Alacrity Signs",
    "wof:placetype":"venue"
},
  "geometry": {"coordinates":[0.8452600241,51.7600517273],"type":"Point"}
}