{
  "type": "Feature",
  "properties": {
    "iso:country":"GB",
    "sg:address":"51-53 Guildford St",
    "sg:city":"Chertsey",
    "sg:classifiers":[
        {
            "category":"Professional",
            "subcategory":"Secretarial Services",
            "type":"Services"
        }
    ],
    "sg:phone":"+44 1932 570306",
    "sg:postcode":"KT16 9BA",
    "sg:province":"Surrey",
    "wof:name":"CV's By Post",
    "wof:placetype":"venue"
},
  "geometry": {"coordinates":[-0.5072960258,51.3888549805],"type":"Point"}
}