{
  "type": "Feature",
  "properties": {
    "iso:country":"GB",
    "sg:address":"22a Station Lane",
    "sg:city":"Hornchurch",
    "sg:classifiers":[
        {
            "category":"Professional",
            "subcategory":"Detective & Security Services",
            "type":"Services"
        }
    ],
    "sg:phone":"+44 1708 453465",
    "sg:postcode":"RM12 6NJ",
    "sg:province":"Essex",
    "wof:name":"R & D Security Manufacturing Ltd.",
    "wof:placetype":"venue"
},
  "geometry": {"coordinates":[0.220776,51.561188],"type":"Point"}
}