{
  "type": "Feature",
  "properties": {
    "addr:full":"102 Church Street Highbridge Somerset TA9 3HR",
    "addr:housenumber":"102",
    "addr:postcode":"ta9 3hr",
    "addr:street":"Church Street",
    "iso:country":"GB",
    "sg:address":"102 Church Street",
    "sg:city":"Highbridge",
    "sg:classifiers":[
        {
            "category":"Restaurant",
            "type":"Food & Drink"
        }
    ],
    "sg:phone":"+44 1278 782560",
    "sg:postcode":"TA9 3HR",
    "sg:province":"Somerset",
    "sg:tags":[
        "indian",
        "-"
    ],
    "wof:name":"Highbridge Tandoori",
    "wof:placetype":"venue"
},
  "geometry": {"coordinates":[-2.975578,51.221317],"type":"Point"}
}