{
  "type": "Feature",
  "properties": {
    "iso:country":"GB",
    "sg:address":"66 Drake Road",
    "sg:city":"Chessington",
    "sg:classifiers":[
        {
            "category":"Health Services",
            "subcategory":"Clinic",
            "type":"Services"
        }
    ],
    "sg:phone":"+44 20 8391 9179",
    "sg:postcode":"KT9 1LW",
    "sg:province":"Surrey",
    "sg:tags":[
        "injury",
        "sport"
    ],
    "wof:name":"Park View Book Keeping & Office Services",
    "wof:placetype":"venue"
},
  "geometry": {"coordinates":[-0.285547,51.36525],"type":"Point"}
}