{
  "type": "Feature",
  "properties": {
    "iso:country":"GB",
    "sg:address":"London Trading Estate",
    "sg:city":"Farnham",
    "sg:classifiers":[
        {
            "category":"Building & Trades",
            "subcategory":"Locksmith",
            "type":"Services"
        }
    ],
    "sg:phone":"+44 1252 741100",
    "sg:postcode":"GU9 9PL",
    "sg:province":"Surrey",
    "wof:name":"Arden Farnham Locks Ltd.",
    "wof:placetype":"venue"
},
  "geometry": {"coordinates":[-0.8008369803,51.2143211365],"type":"Point"}
}