{
  "type": "Feature",
  "properties": {
    "iso:country":"GB",
    "sg:address":"Unit A3 The Merlin Centre, Acrewood Way",
    "sg:city":"St Albans",
    "sg:classifiers":[
        {
            "category":"Professional",
            "subcategory":"Business Services",
            "type":"Services"
        }
    ],
    "sg:phone":"+44 1727 833391",
    "sg:postcode":"AL4 0JY",
    "sg:province":"Hertfordshire",
    "sg:tags":[
        "code",
        "bar"
    ],
    "wof:name":"Martec Technology Ltd.",
    "wof:placetype":"venue"
},
  "geometry": {"coordinates":[-0.27866,51.750759],"type":"Point"}
}