{
  "type": "Feature",
  "properties": {
    "iso:country":"GB",
    "sg:address":"Lea Hall Farm, Admaston",
    "sg:city":"Rugeley",
    "sg:classifiers":[
        {
            "category":"Farming",
            "subcategory":"Farm",
            "type":"Manufacturing & Wholesale Goods"
        }
    ],
    "sg:phone":"+44 1889 500219",
    "sg:postcode":"WS15 3NN",
    "sg:province":"Staffordshire",
    "sg:tags":[
        "mixed",
        "crop"
    ],
    "wof:name":"C Geoffrey Parkinson",
    "wof:placetype":"venue"
},
  "geometry": {"coordinates":[-1.926924,52.80611],"type":"Point"}
}