{
  "type": "Feature",
  "properties": {
    "iso:country":"GB",
    "sg:address":"Woodside House, 37 The Green",
    "sg:city":"London",
    "sg:classifiers":[
        {
            "category":"Professional",
            "subcategory":"Lawyer & Legal Services",
            "type":"Services"
        }
    ],
    "sg:phone":"+44 20 8886 5734",
    "sg:postcode":"N21 1HT",
    "sg:province":"Greater London",
    "sg:tags":[
        "conveyancing",
        "solicitor"
    ],
    "wof:name":"Barker Gooch & Swailes",
    "wof:placetype":"venue"
},
  "geometry": {"coordinates":[-0.103796,51.633686],"type":"Point"}
}