{
  "type": "Feature",
  "properties": {
    "addr:full":"110 The Crossway, Portchester Fareham Hampshire PO16 8NH",
    "addr:housenumber":"110",
    "addr:postcode":"po16 8nh",
    "addr:street":"The Crossway",
    "iso:country":"GB",
    "sg:address":"110 The Crossway, Portchester",
    "sg:city":"Fareham",
    "sg:classifiers":[
        {
            "category":"Retail",
            "subcategory":"Animal Services",
            "type":"Services"
        },
        {
            "category":"Personal",
            "subcategory":"Adult",
            "type":"Services"
        }
    ],
    "sg:phone":"+44 23 9237 9282",
    "sg:postcode":"PO16 8NH",
    "sg:province":"Hampshire",
    "sg:tags":[
        "farrier",
        "equestrian"
    ],
    "wof:name":"Ivor R Cordall",
    "wof:placetype":"venue"
},
  "geometry": {"coordinates":[-1.1335,50.848373],"type":"Point"}
}