{
  "type": "Feature",
  "properties": {
    "iso:country":"GB",
    "sg:address":"The Oaklands, Edstaston, Wem",
    "sg:city":"Shrewsbury",
    "sg:classifiers":[
        {
            "category":"Manufacturing",
            "subcategory":"Wood Products",
            "type":"Manufacturing & Wholesale Goods"
        }
    ],
    "sg:phone":"+44 1939 236766",
    "sg:postcode":"SY4 5RF",
    "sg:province":"Shropshire",
    "sg:tags":[
        "packaging",
        "crate",
        "pallets"
    ],
    "wof:name":"Oaklands Farm Eggs Ltd.",
    "wof:placetype":"venue"
},
  "geometry": {"coordinates":[-2.71943,52.884731],"type":"Point"}
}