{
  "type": "Feature",
  "properties": {
    "addr:full":"12 High Street, Caistor Lincoln Lincolnshire LN7 6TX",
    "addr:housenumber":"12",
    "addr:postcode":"ln7 6tx",
    "addr:street":"High Street",
    "iso:country":"GB",
    "sg:address":"12 High Street, Caistor",
    "sg:city":"Lincoln",
    "sg:classifiers":[
        {
            "category":"Shopping",
            "subcategory":"Antiques",
            "type":"Retail Goods"
        }
    ],
    "sg:phone":"+44 1472 851975",
    "sg:postcode":"LN7 6TX",
    "sg:province":"Lincolnshire",
    "wof:name":"Caistor Antiques",
    "wof:placetype":"venue"
},
  "geometry": {"coordinates":[-0.3150019944,53.4975700378],"type":"Point"}
}