{
  "type": "Feature",
  "properties": {
    "iso:country":"GB",
    "sg:address":"41 Golding Place",
    "sg:city":"Norwich",
    "sg:classifiers":[
        {
            "category":"Bars & Pubs",
            "type":"Food & Drink"
        }
    ],
    "sg:phone":"+44 1603 622126",
    "sg:postcode":"NR2 4BD",
    "sg:province":"Norfolk",
    "sg:tags":[
        "pubs",
        "inn"
    ],
    "wof:name":"Britannia",
    "wof:placetype":"venue"
},
  "geometry": {"coordinates":[1.283655,52.631474],"type":"Point"}
}