{
  "type": "Feature",
  "properties": {
    "addr:full":"1 The Concourse, Grahame Park Estate London Greater London NW9 5XB",
    "addr:housenumber":"1",
    "addr:postcode":"nw9 5xb",
    "addr:street":"The Concourse Grahame Park Estate",
    "iso:country":"GB",
    "sg:address":"1 The Concourse, Grahame Park Estate",
    "sg:city":"London",
    "sg:classifiers":[
        {
            "category":"Fast Food",
            "type":"Food & Drink"
        }
    ],
    "sg:phone":"+44 20 8205 9141",
    "sg:postcode":"NW9 5XB",
    "sg:province":"Greater London",
    "sg:tags":[
        "away",
        "take"
    ],
    "wof:name":"New Ocean Bar",
    "wof:placetype":"venue"
},
  "geometry": {"coordinates":[-0.2443200052,51.6021995544],"type":"Point"}
}