{
  "type": "Feature",
  "properties": {
    "addr:full":"4th Floor, 1 Union Court Liverpool Merseyside L2 4SJ",
    "addr:housenumber":"4th floor 1",
    "addr:postcode":"l2 4sj",
    "addr:street":"Union Court",
    "iso:country":"GB",
    "sg:address":"4th Floor, 1 Union Court",
    "sg:city":"Liverpool",
    "sg:classifiers":[
        {
            "category":"Professional",
            "subcategory":"Engineering",
            "type":"Services"
        }
    ],
    "sg:phone":"+44 151 231 1230",
    "sg:postcode":"L2 4SJ",
    "sg:province":"Merseyside",
    "sg:tags":[
        "consulting",
        "engineer"
    ],
    "wof:name":"T D Bingham Partnership",
    "wof:placetype":"venue"
},
  "geometry": {"coordinates":[-2.9900550842,53.4064674377],"type":"Point"}
}