{
  "type": "Feature",
  "properties": {
    "addr:full":"5 Station Road Dollar Clackmannanshire FK14 7EJ",
    "addr:housenumber":"5",
    "addr:postcode":"fk14 7ej",
    "addr:street":"Station Road",
    "iso:country":"GB",
    "sg:address":"5 Station Road",
    "sg:city":"Dollar",
    "sg:classifiers":[
        {
            "category":"Government",
            "subcategory":"Post Office",
            "type":"Public Place"
        }
    ],
    "sg:phone":"+44 1259 742670",
    "sg:postcode":"FK14 7EJ",
    "sg:province":"Clackmannanshire",
    "wof:name":"Dollar Sub Post Office",
    "wof:placetype":"venue"
},
  "geometry": {"coordinates":[-3.672949,56.162586],"type":"Point"}
}