{
  "type": "Feature",
  "properties": {
    "addr:full":"Market Place, Olston Ferry Doncaster Lincolnshire DN9 1RB",
    "addr:postcode":"dn9 1rb",
    "addr:street":"Market Place Olston Ferry",
    "iso:country":"GB",
    "sg:address":"Market Place, Olston Ferry",
    "sg:city":"Doncaster",
    "sg:classifiers":[
        {
            "category":"Building & Trades",
            "subcategory":"Construction",
            "type":"Services"
        }
    ],
    "sg:postcode":"DN9 1RB",
    "sg:province":"Lincolnshire",
    "sg:tags":[
        "equipment"
    ],
    "wof:name":"B McKeown (Haulage)",
    "wof:placetype":"venue"
},
  "geometry": {"coordinates":[-0.8196790218,53.5254631042],"type":"Point"}
}