{
  "type": "Feature",
  "properties": {
    "addr:full":"Raytel House Rayleigh Essex SS6 7XH",
    "addr:postcode":"ss6 7xh",
    "iso:country":"GB",
    "sg:address":"Raytel House",
    "sg:city":"Rayleigh",
    "sg:classifiers":[
        {
            "category":"Professional",
            "subcategory":"Art Services",
            "type":"Services"
        }
    ],
    "sg:phone":"+44 1268 775656",
    "sg:postcode":"SS6 7XH",
    "sg:province":"Essex",
    "sg:tags":[
        "graphic",
        "designer"
    ],
    "wof:name":"Adform Ltd.",
    "wof:placetype":"venue"
},
  "geometry": {"coordinates":[0.604678,51.586445],"type":"Point"}
}