{
  "type": "Feature",
  "properties": {
    "addr:full":"Mere Farm, Green Rd, Haughley Stowmarket Suffolk IP14 3RA",
    "addr:postcode":"ip14 3ra",
    "addr:street":"Mere;Green Rd",
    "iso:country":"GB",
    "sg:address":"Mere Farm, Green Rd, Haughley",
    "sg:city":"Stowmarket",
    "sg:classifiers":[
        {
            "category":"Wholesale",
            "subcategory":"Machinery & Supplies",
            "type":"Manufacturing & Wholesale Goods"
        }
    ],
    "sg:phone":"+44 1449 673371",
    "sg:postcode":"IP14 3RA",
    "sg:province":"Suffolk",
    "sg:tags":[
        "pump"
    ],
    "wof:name":"Acfil Pumps",
    "wof:placetype":"venue"
},
  "geometry": {"coordinates":[0.971325,52.219727],"type":"Point"}
}