{
  "type": "Feature",
  "properties": {
    "addr:full":"117 Alumhurst Road Bournemouth Dorset BH4 8HS",
    "addr:housenumber":"117",
    "addr:postcode":"bh4 8hs",
    "addr:street":"Alumhurst Road",
    "iso:country":"GB",
    "sg:address":"117 Alumhurst Road",
    "sg:city":"Bournemouth",
    "sg:classifiers":[
        {
            "category":"Travel",
            "subcategory":"Hotels & Motels",
            "type":"Entertainment"
        }
    ],
    "sg:postcode":"BH4 8HS",
    "sg:province":"Dorset",
    "wof:name":"West Dene Private Hotel",
    "wof:placetype":"venue"
},
  "geometry": {"coordinates":[-1.898603,50.710976],"type":"Point"}
}