{
  "type": "Feature",
  "properties": {
    "iso:country":"GB",
    "sg:address":"Warren House Farm, Barracks Lane, Brownhills",
    "sg:city":"Walsall",
    "sg:classifiers":[
        {
            "category":"Retail",
            "subcategory":"Veterinary Services",
            "type":"Services"
        }
    ],
    "sg:phone":"+44 1543 373033",
    "sg:postcode":"WS8 6LS",
    "sg:province":"Staffordshire",
    "sg:tags":[
        "surgeon",
        "activity"
    ],
    "wof:name":"J R Newcombe",
    "wof:placetype":"venue"
},
  "geometry": {"coordinates":[-1.932484,52.646725],"type":"Point"}
}