{
  "type": "Feature",
  "properties": {
    "addr:full":"16 Atherton Rd Wigan Lancashire WN2 3EU",
    "addr:housenumber":"16",
    "addr:postcode":"wn2 3eu",
    "addr:street":"Atherton Rd",
    "iso:country":"GB",
    "sg:address":"16 Atherton Rd",
    "sg:city":"Wigan",
    "sg:classifiers":[
        {
            "category":"Professional",
            "subcategory":"Detective & Security Services",
            "type":"Services"
        }
    ],
    "sg:phone":"+44 1942 700000",
    "sg:postcode":"WN2 3EU",
    "sg:province":"Lancashire",
    "wof:name":"Property Watch Security Services",
    "wof:placetype":"venue"
},
  "geometry": {"coordinates":[-2.58028,53.532948],"type":"Point"}
}