{
  "type": "Feature",
  "properties": {
    "addr:full":"17 Marmion Road Hove East Sussex BN3 5FS",
    "addr:housenumber":"17",
    "addr:postcode":"bn3 5fs",
    "addr:street":"Marmion Road",
    "iso:country":"GB",
    "sg:address":"17 Marmion Road",
    "sg:city":"Hove",
    "sg:classifiers":[
        {
            "category":"Organizations",
            "subcategory":"Non-profit Organization",
            "type":"Services"
        }
    ],
    "sg:phone":"+44 1273 731724",
    "sg:postcode":"BN3 5FS",
    "sg:province":"East Sussex",
    "sg:tags":[
        "organisation",
        "voluntary",
        "charity"
    ],
    "wof:name":"Y M C A",
    "wof:placetype":"venue"
},
  "geometry": {"coordinates":[-0.1879729927,50.8344345093],"type":"Point"}
}