{
  "type": "Feature",
  "properties": {
    "addr:full":"158 Main Street, Cambuslang Glasgow South Lanarkshire G72 7EL",
    "addr:housenumber":"158",
    "addr:postcode":"g72 7el",
    "addr:street":"Main Street",
    "iso:country":"GB",
    "sg:address":"158 Main Street, Cambuslang",
    "sg:city":"Glasgow",
    "sg:classifiers":[
        {
            "category":"Food & Beverages",
            "subcategory":"Meat & Fish",
            "type":"Retail Goods"
        }
    ],
    "sg:phone":"+44 141 641 4066",
    "sg:postcode":"G72 7EL",
    "sg:province":"South Lanarkshire",
    "sg:tags":[
        "butcher"
    ],
    "wof:name":"S W McIntyre",
    "wof:placetype":"venue"
},
  "geometry": {"coordinates":[-4.168062,55.818974],"type":"Point"}
}