{
  "type": "Feature",
  "properties": {
    "iso:country":"GB",
    "sg:address":"2 Church Avenue",
    "sg:city":"Huddersfield",
    "sg:classifiers":[
        {
            "category":"Shopping",
            "subcategory":"Department Store",
            "type":"Retail Goods"
        }
    ],
    "sg:phone":"+44 1484 513492",
    "sg:postcode":"HD4 5DF",
    "sg:province":"West Yorkshire",
    "wof:name":"B Singh",
    "wof:placetype":"venue"
},
  "geometry": {"coordinates":[-1.8035509586,53.6364631653],"type":"Point"}
}