{
  "type": "Feature",
  "properties": {
    "iso:country":"GB",
    "sg:address":"Mansfield Rd",
    "sg:city":"Nottingham",
    "sg:classifiers":[
        {
            "category":"Bars & Pubs",
            "type":"Food & Drink"
        }
    ],
    "sg:phone":"+44 115 926 8864",
    "sg:postcode":"NG5 3GG",
    "sg:province":"Nottinghamshire",
    "sg:tags":[
        "pubs",
        "inn"
    ],
    "wof:name":"Vale Hotel",
    "wof:placetype":"venue"
},
  "geometry": {"coordinates":[-1.139457,52.993134],"type":"Point"}
}