{
  "type": "Feature",
  "properties": {
    "addr:full":"17-19 Heddon Street London Greater London W1B 4AZ",
    "addr:housenumber":"17-19",
    "addr:postcode":"w1b 4az",
    "addr:street":"Heddon Street",
    "iso:country":"GB",
    "sg:address":"17-19 Heddon Street",
    "sg:city":"London",
    "sg:classifiers":[
        {
            "category":"Professional",
            "type":"Services"
        }
    ],
    "sg:postcode":"W1B 4AZ",
    "sg:province":"Greater London",
    "sg:tags":[
        "repair",
        "tech",
        "maintenance"
    ],
    "wof:name":"Direct Approach",
    "wof:placetype":"venue"
},
  "geometry": {"coordinates":[-0.1394920051,51.5108566284],"type":"Point"}
}