{
  "type": "Feature",
  "properties": {
    "iso:country":"GB",
    "sg:address":"5 Bessemer Rd",
    "sg:city":"Norwich",
    "sg:classifiers":[
        {
            "category":"Professional",
            "subcategory":"Art Services",
            "type":"Services"
        }
    ],
    "sg:phone":"+44 1603 620703",
    "sg:postcode":"NR4 6DQ",
    "sg:province":"Norfolk",
    "sg:tags":[
        "graphic",
        "designer"
    ],
    "wof:name":"DSN Graphics",
    "wof:placetype":"venue"
},
  "geometry": {"coordinates":[1.289644,52.606228],"type":"Point"}
}