{
  "type": "Feature",
  "properties": {
    "addr:full":"8 Holway Road Taunton Somerset TA1 2EY",
    "addr:housenumber":"8",
    "addr:postcode":"ta1 2ey",
    "addr:street":"Holway Road",
    "iso:country":"GB",
    "sg:address":"8 Holway Road",
    "sg:city":"Taunton",
    "sg:classifiers":[
        {
            "category":"Building & Trades",
            "subcategory":"Plumbing",
            "type":"Services"
        }
    ],
    "sg:phone":"+44 1823 286666",
    "sg:postcode":"TA1 2EY",
    "sg:province":"Somerset",
    "sg:tags":[
        "central",
        "heating"
    ],
    "wof:name":"J L Plumbing Heating & Electrical Services",
    "wof:placetype":"venue"
},
  "geometry": {"coordinates":[-3.0894389153,51.0116195679],"type":"Point"}
}