{
  "type": "Feature",
  "properties": {
    "addr:full":"162 Victoria Road West Thornton-cleveleys Lancashire FY5 3NE",
    "addr:housenumber":"162",
    "addr:postcode":"fy5 3ne",
    "addr:street":"Victoria Road West Thornton-Cleveleys",
    "iso:country":"GB",
    "sg:address":"162 Victoria Road West",
    "sg:city":"Thornton-cleveleys",
    "sg:classifiers":[
        {
            "category":"Shopping",
            "subcategory":"Pharmacy",
            "type":"Retail Goods"
        }
    ],
    "sg:postcode":"FY5 3NE",
    "sg:province":"Lancashire",
    "sg:tags":[
        "pharmacist",
        "store",
        "drug",
        "chemist"
    ],
    "wof:name":"J H Tait",
    "wof:placetype":"venue"
},
  "geometry": {"coordinates":[-3.0374979973,53.8763847351],"type":"Point"}
}