{
  "type": "Feature",
  "properties": {
    "addr:full":"Unit 3 Stephens Yard, Simpson Road, Fenny Sratford Milton Keynes Buckinghamshire MK1 1BA",
    "addr:housenumber":"unit 3",
    "addr:postcode":"mk1 1ba",
    "addr:street":"Stephens Yard Simpson Road Fenny Sratford",
    "iso:country":"GB",
    "sg:address":"Unit 3 Stephens Yard, Simpson Road, Fenny Sratford",
    "sg:city":"Milton Keynes",
    "sg:classifiers":[
        {
            "category":"Home & Garden",
            "subcategory":"Hardware",
            "type":"Retail Goods"
        },
        {
            "category":"Home & Garden",
            "subcategory":"Building Materials",
            "type":"Retail Goods"
        }
    ],
    "sg:phone":"+44 1908 366985",
    "sg:postcode":"MK1 1BA",
    "sg:province":"Buckinghamshire",
    "sg:tags":[
        "paint",
        "coating",
        "sprayer"
    ],
    "wof:name":"R S Coatings",
    "wof:placetype":"venue"
},
  "geometry": {"coordinates":[-0.7277489901,52.0058555603],"type":"Point"}
}