{
  "type": "Feature",
  "properties": {
    "addr:full":"The Telephone Exchange, Crockham Hill Edenbridge East Sussex TN8 6TE",
    "addr:postcode":"tn8 6te",
    "iso:country":"GB",
    "sg:address":"The Telephone Exchange, Crockham Hill",
    "sg:city":"Edenbridge",
    "sg:classifiers":[
        {
            "category":"Banks & Credit Unions",
            "subcategory":"Bureau De Change",
            "type":"Services"
        }
    ],
    "sg:phone":"+44 1732 865800",
    "sg:postcode":"TN8 6TE",
    "sg:province":"East Sussex",
    "sg:tags":[
        "hamper",
        "gift",
        "pack"
    ],
    "wof:name":"Your Choice Hampers",
    "wof:placetype":"venue"
},
  "geometry": {"coordinates":[0.064747,51.197388],"type":"Point"}
}