{
  "type": "Feature",
  "properties": {
    "addr:full":"10a Little Underbank Stockport Cheshire SK1 1LF",
    "addr:housenumber":"10a",
    "addr:postcode":"sk1 1lf",
    "addr:street":"Little Underbank",
    "iso:country":"GB",
    "sg:address":"10a Little Underbank",
    "sg:city":"Stockport",
    "sg:classifiers":[
        {
            "category":"Personal",
            "type":"Services"
        }
    ],
    "sg:phone":"+44 161 477 5827",
    "sg:postcode":"SK1 1LF",
    "sg:province":"Cheshire",
    "sg:tags":[
        "wedding"
    ],
    "wof:name":"Wedding World (Stockport) Ltd.",
    "wof:placetype":"venue"
},
  "geometry": {"coordinates":[-2.157357,53.410992],"type":"Point"}
}