{
  "type": "Feature",
  "properties": {
    "iso:country":"GB",
    "sg:address":"2b Weston Av",
    "sg:city":"Ayr",
    "sg:classifiers":[
        {
            "category":"Government",
            "subcategory":"Post Office",
            "type":"Public Place"
        }
    ],
    "sg:phone":"+44 1292 520269",
    "sg:postcode":"KA6 5EG",
    "sg:province":"East Ayrshire",
    "wof:name":"R & S Stores & Post Office",
    "wof:placetype":"venue"
},
  "geometry": {"coordinates":[-4.556139,55.483372],"type":"Point"}
}