{
  "type": "Feature",
  "properties": {
    "addr:full":"55 Ambush St Northampton Northamptonshire NN5 5DU",
    "addr:housenumber":"55",
    "addr:postcode":"nn5 5du",
    "addr:street":"Ambush St",
    "iso:country":"GB",
    "sg:address":"55 Ambush St",
    "sg:city":"Northampton",
    "sg:classifiers":[
        {
            "category":"Shopping",
            "subcategory":"Computers & Home Electronics",
            "type":"Retail Goods"
        }
    ],
    "sg:phone":"+44 1604 587793",
    "sg:postcode":"NN5 5DU",
    "sg:province":"Northamptonshire",
    "sg:tags":[
        "sound",
        "equipment",
        "system"
    ],
    "wof:name":"Soundhaus",
    "wof:placetype":"venue"
},
  "geometry": {"coordinates":[-0.910515,52.237877],"type":"Point"}
}