{
  "type": "Feature",
  "properties": {
    "addr:full":"Unit 24 Eldon Way Hockley Essex SS5 4AD",
    "addr:housenumber":"unit 24",
    "addr:postcode":"ss5 4ad",
    "addr:street":"Eldon Way Hockley",
    "iso:country":"GB",
    "sg:address":"Unit 24 Eldon Way",
    "sg:city":"Hockley",
    "sg:classifiers":[
        {
            "category":"Communications",
            "type":"Services"
        }
    ],
    "sg:postcode":"SS5 4AD",
    "sg:province":"Essex",
    "sg:tags":[
        "system",
        "music",
        "public",
        "address"
    ],
    "wof:name":"Revelation Systems",
    "wof:placetype":"venue"
},
  "geometry": {"coordinates":[0.656665,51.602371],"type":"Point"}
}