{
  "type": "Feature",
  "properties": {
    "addr:full":"243-247 Westborough Road Westcliff-on-sea Essex SS0 9PR",
    "addr:housenumber":"243-247",
    "addr:postcode":"ss0 9pr",
    "addr:street":"Westborough Road",
    "iso:country":"GB",
    "sg:address":"243-247 Westborough Road",
    "sg:city":"Westcliff-on-sea",
    "sg:classifiers":[
        {
            "category":"Retail",
            "subcategory":"Auto Repair",
            "type":"Services"
        }
    ],
    "sg:phone":"+44 1702 290433",
    "sg:postcode":"SS0 9PR",
    "sg:province":"Essex",
    "sg:tags":[
        "modification",
        "garage"
    ],
    "wof:name":"M J Steptoe Motor Engineers",
    "wof:placetype":"venue"
},
  "geometry": {"coordinates":[0.6880729795,51.5469665527],"type":"Point"}
}