{
  "type": "Feature",
  "properties": {
    "iso:country":"GB",
    "sg:address":"5 Cranstock Close",
    "sg:city":"Billingham",
    "sg:classifiers":[
        {
            "category":"Health Services",
            "subcategory":"Clinic",
            "type":"Services"
        }
    ],
    "sg:phone":"+44 1642 361220",
    "sg:postcode":"TS22 5RS",
    "sg:province":"Durham",
    "sg:tags":[
        "aromatherapy"
    ],
    "wof:name":"Holopathic Therapy",
    "wof:placetype":"venue"
},
  "geometry": {"coordinates":[-1.307469,54.62851],"type":"Point"}
}