{
  "type": "Feature",
  "properties": {
    "addr:full":"Lower Edmonton Post Office, 1-7 South Mall London Greater London N9 0TX",
    "addr:housenumber":"1-7",
    "addr:postcode":"n9 0tx",
    "addr:street":"South Mall",
    "iso:country":"GB",
    "sg:address":"Lower Edmonton Post Office, 1-7 South Mall",
    "sg:city":"London",
    "sg:classifiers":[
        {
            "category":"Government",
            "subcategory":"Post Office",
            "type":"Public Place"
        }
    ],
    "sg:phone":"+44 20 8807 3380",
    "sg:postcode":"N9 0TX",
    "sg:province":"Greater London",
    "wof:name":"Post Office Counters Ltd.",
    "wof:placetype":"venue"
},
  "geometry": {"coordinates":[-0.05905,51.623032],"type":"Point"}
}