{
  "type": "Feature",
  "properties": {
    "addr:full":"Unit 21 London Greater London E2 8HD",
    "addr:housenumber":"unit 21",
    "addr:postcode":"e2 8hd",
    "iso:country":"GB",
    "sg:address":"Unit 21",
    "sg:city":"London",
    "sg:classifiers":[
        {
            "category":"Professional",
            "subcategory":"Printing & Photocopies",
            "type":"Services"
        }
    ],
    "sg:phone":"+44 20 7739 8155",
    "sg:postcode":"E2 8HD",
    "sg:province":"Greater London",
    "sg:tags":[
        "printer"
    ],
    "wof:name":"Horseshoe Litho",
    "wof:placetype":"venue"
},
  "geometry": {"coordinates":[-0.0688640028,51.5306739807],"type":"Point"}
}