{
  "type": "Feature",
  "properties": {
    "addr:full":"807 Commercial Rd London Greater London E14 7HG",
    "addr:housenumber":"807",
    "addr:postcode":"e14 7hg",
    "addr:street":"Commercial Rd",
    "iso:country":"GB",
    "sg:address":"807 Commercial Rd",
    "sg:city":"London",
    "sg:classifiers":[
        {
            "category":"Cafe",
            "type":"Food & Drink"
        }
    ],
    "sg:postcode":"E14 7HG",
    "sg:province":"Greater London",
    "sg:tags":[
        "tea",
        "room"
    ],
    "wof:name":"Eastern Cafe",
    "wof:placetype":"venue"
},
  "geometry": {"coordinates":[-0.028606,51.512127],"type":"Point"}
}