{
  "type": "Feature",
  "properties": {
    "addr:full":"1390 Coventry Road Birmingham West Midlands B25 8AE",
    "addr:housenumber":"1390",
    "addr:postcode":"b25 8ae",
    "addr:street":"Coventry Road",
    "iso:country":"GB",
    "sg:address":"1390 Coventry Road",
    "sg:city":"Birmingham",
    "sg:classifiers":[
        {
            "category":"Building & Trades",
            "subcategory":"Construction",
            "type":"Services"
        }
    ],
    "sg:phone":"+44 121 440 2429",
    "sg:postcode":"B25 8AE",
    "sg:province":"West Midlands",
    "sg:tags":[
        "management"
    ],
    "wof:name":"Allen Construction Managerment",
    "wof:placetype":"venue"
},
  "geometry": {"coordinates":[-1.8185210228,52.4623718262],"type":"Point"}
}