{
  "type": "Feature",
  "properties": {
    "iso:country":"GB",
    "sg:address":"Watnall Road Aerodrome",
    "sg:city":"Nottingham",
    "sg:classifiers":[
        {
            "category":"Home & Garden",
            "subcategory":"Household Appliances",
            "type":"Retail Goods"
        }
    ],
    "sg:phone":"+44 115 964 1073",
    "sg:postcode":"NG15 6EQ",
    "sg:province":"Nottinghamshire",
    "sg:tags":[
        "refrigeration",
        "air conditioning"
    ],
    "wof:name":"C C Refrigeration",
    "wof:placetype":"venue"
},
  "geometry": {"coordinates":[-1.2099089622,53.0318756104],"type":"Point"}
}