{
  "type": "Feature",
  "properties": {
    "addr:full":"Unit B, 1a Conduit Road London Greater London SE18 7AJ",
    "addr:housenumber":"1a",
    "addr:postcode":"se18 7aj",
    "addr:street":"Conduit Road",
    "iso:country":"GB",
    "sg:address":"Unit B, 1a Conduit Road",
    "sg:city":"London",
    "sg:classifiers":[
        {
            "category":"Building & Trades",
            "subcategory":"Cleaning & Sanitation",
            "type":"Services"
        }
    ],
    "sg:phone":"+44 20 8316 1509",
    "sg:postcode":"SE18 7AJ",
    "sg:province":"Greater London",
    "sg:tags":[
        "dry",
        "control",
        "damp",
        "rot"
    ],
    "wof:name":"Allied Remedial Treatments Ltd.",
    "wof:placetype":"venue"
},
  "geometry": {"coordinates":[0.0699200034,51.4869499207],"type":"Point"}
}