{
  "type": "Feature",
  "properties": {
    "addr:full":"131 Brent Street, Hendon London Greater London NW4 4BY",
    "addr:housenumber":"131",
    "addr:postcode":"nw4 4by",
    "addr:street":"Brent Street",
    "iso:country":"GB",
    "sg:address":"131 Brent Street, Hendon",
    "sg:city":"London",
    "sg:classifiers":[
        {
            "category":"Government",
            "subcategory":"Post Office",
            "type":"Public Place"
        }
    ],
    "sg:phone":"+44 845 722 3344",
    "sg:postcode":"NW4 4BY",
    "sg:province":"Greater London",
    "wof:name":"Post Office Ltd.",
    "wof:placetype":"venue"
},
  "geometry": {"coordinates":[-0.2212789953,51.5880699158],"type":"Point"}
}