{
  "type": "Feature",
  "properties": {
    "addr:full":"Horton Park Farm, Horton Lane Epsom Surrey KT19 8PT",
    "addr:postcode":"kt19 8pt",
    "addr:street":"Horton Lane",
    "iso:country":"GB",
    "sg:address":"Horton Park Farm, Horton Lane",
    "sg:city":"Epsom",
    "sg:classifiers":[
        {
            "category":"Home & Garden",
            "subcategory":"Building Materials",
            "type":"Retail Goods"
        }
    ],
    "sg:phone":"+44 1372 720273",
    "sg:postcode":"KT19 8PT",
    "sg:province":"Surrey",
    "sg:tags":[
        "ironwork",
        "diy",
        "wrought"
    ],
    "wof:name":"Black Barn Forge",
    "wof:placetype":"venue"
},
  "geometry": {"coordinates":[-0.271106,51.333008],"type":"Point"}
}