{
  "type": "Feature",
  "properties": {
    "addr:full":"17 Broomfield Close, Ainsworth Bolton Lancashire BL2 5QY",
    "addr:housenumber":"17",
    "addr:postcode":"bl2 5qy",
    "addr:street":"Broomfield Close",
    "iso:country":"GB",
    "sg:address":"17 Broomfield Close, Ainsworth",
    "sg:city":"Bolton",
    "sg:classifiers":[
        {
            "category":"Building & Trades",
            "subcategory":"Construction",
            "type":"Services"
        }
    ],
    "sg:phone":"+44 1204 386221",
    "sg:postcode":"BL2 5QY",
    "sg:province":"Lancashire",
    "sg:tags":[
        "roofing"
    ],
    "wof:name":"Ainsworth Roofing",
    "wof:placetype":"venue"
},
  "geometry": {"coordinates":[-2.359592,53.586201],"type":"Point"}
}