{
  "type": "Feature",
  "properties": {
    "iso:country":"GB",
    "sg:address":"Effingham Rd, Copthorne",
    "sg:city":"Crawley",
    "sg:classifiers":[
        {
            "category":"Social Services",
            "type":"Services"
        }
    ],
    "sg:phone":"+44 1342 712309",
    "sg:postcode":"RH10 3HZ",
    "sg:province":"Surrey",
    "wof:name":"Beechfield Secure Unit",
    "wof:placetype":"venue"
},
  "geometry": {"coordinates":[-0.0990289971,51.148311615],"type":"Point"}
}