{
  "type": "Feature",
  "properties": {
    "addr:full":"Fullers Road Farnham Hampshire GU10 4DF",
    "addr:postcode":"gu10 4df",
    "addr:street":"Fullers Road",
    "iso:country":"GB",
    "sg:address":"Fullers Road",
    "sg:city":"Farnham",
    "sg:classifiers":[
        {
            "category":"Home & Garden",
            "subcategory":"Home Furnishings",
            "type":"Retail Goods"
        }
    ],
    "sg:phone":"+44 1252 795411",
    "sg:postcode":"GU10 4DF",
    "sg:province":"Hampshire",
    "sg:tags":[
        "furnishers",
        "planner",
        "bedroom"
    ],
    "wof:name":"D J C Fitted Bedrooms",
    "wof:placetype":"venue"
},
  "geometry": {"coordinates":[-0.8347820044,51.1854782104],"type":"Point"}
}