{
  "type": "Feature",
  "properties": {
    "iso:country":"GB",
    "sg:address":"Shaw's Trailer Park",
    "sg:city":"Harrogate",
    "sg:classifiers":[
        {
            "category":"Manufacturing",
            "subcategory":"Buildings",
            "type":"Manufacturing & Wholesale Goods"
        }
    ],
    "sg:phone":"+44 1423 884432",
    "sg:postcode":"HG2 7NE",
    "sg:province":"North Yorkshire",
    "sg:tags":[
        "mobile",
        "home"
    ],
    "wof:name":"Nobles Seaton Carew",
    "wof:placetype":"venue"
},
  "geometry": {"coordinates":[-1.50701,53.996712],"type":"Point"}
}