{
  "type": "Feature",
  "properties": {
    "addr:full":"1249 Melton Road, Syston Leicester Leicestershire LE7 2JT",
    "addr:housenumber":"1249",
    "addr:postcode":"le7 2jt",
    "addr:street":"Melton Road",
    "iso:country":"GB",
    "sg:address":"1249 Melton Road, Syston",
    "sg:city":"Leicester",
    "sg:classifiers":[
        {
            "category":"Cinema",
            "subcategory":"Movie Rental",
            "type":"Entertainment"
        }
    ],
    "sg:phone":"+44 116 260 8638",
    "sg:postcode":"LE7 2JT",
    "sg:province":"Leicestershire",
    "sg:tags":[
        "video",
        "library"
    ],
    "wof:name":"Syston Car & Video Film Hire",
    "wof:placetype":"venue"
},
  "geometry": {"coordinates":[-1.074117,52.697971],"type":"Point"}
}