{
  "type": "Feature",
  "properties": {
    "iso:country":"GB",
    "sg:address":"35 Bushey Rd",
    "sg:city":"Sutton",
    "sg:classifiers":[
        {
            "category":"Insurance",
            "subcategory":"Insurance Agent",
            "type":"Services"
        }
    ],
    "sg:phone":"+44 20 8641 6508",
    "sg:postcode":"SM1 1QR",
    "sg:province":"Surrey",
    "wof:name":"M Durban",
    "wof:placetype":"venue"
},
  "geometry": {"coordinates":[-0.1971579939,51.3698997498],"type":"Point"}
}