{
  "type": "Feature",
  "properties": {
    "addr:full":"40 Bowflatts, Great Clifton Workington Cumbria CA14 1TD",
    "addr:housenumber":"40",
    "addr:postcode":"ca14 1td",
    "addr:street":"Bowflatts",
    "iso:country":"GB",
    "sg:address":"40 Bowflatts, Great Clifton",
    "sg:city":"Workington",
    "sg:classifiers":[
        {
            "category":"Taxi",
            "type":"Transportation"
        },
        {
            "category":"Military Area",
            "subcategory":"Air Force Base",
            "type":"Public Place"
        }
    ],
    "sg:phone":"+44 1900 65968",
    "sg:postcode":"CA14 1TD",
    "sg:province":"Cumbria",
    "sg:tags":[
        "hire",
        "private"
    ],
    "wof:name":"B Cabs",
    "wof:placetype":"venue"
},
  "geometry": {"coordinates":[-3.5500020981,54.6389808655],"type":"Point"}
}