{
  "type": "Feature",
  "properties": {
    "iso:country":"GB",
    "sg:address":"56 Market Place, Market Wheaton",
    "sg:city":"York",
    "sg:classifiers":[
        {
            "category":"Professional",
            "subcategory":"Printing & Photocopies",
            "type":"Services"
        }
    ],
    "sg:phone":"+44 1430 873996",
    "sg:postcode":"YO43 3AW",
    "sg:province":"East Riding of Yorkshire",
    "sg:tags":[
        "printer"
    ],
    "wof:name":"Wyngarth Graphics",
    "wof:placetype":"venue"
},
  "geometry": {"coordinates":[-0.667857,53.865005],"type":"Point"}
}