{
  "type": "Feature",
  "properties": {
    "iso:country":"GB",
    "sg:address":"Trevalyn Farm, Darland, Rossett",
    "sg:city":"Wrexham",
    "sg:classifiers":[
        {
            "category":"Farming",
            "subcategory":"Farm",
            "type":"Manufacturing & Wholesale Goods"
        }
    ],
    "sg:phone":"+44 1244 570248",
    "sg:postcode":"LL12 0BD",
    "sg:province":"Wrexham",
    "sg:tags":[
        "mixed",
        "crop"
    ],
    "wof:name":"Bellis Bros",
    "wof:placetype":"venue"
},
  "geometry": {"coordinates":[-2.943889,53.109631],"type":"Point"}
}