{
  "type": "Feature",
  "properties": {
    "addr:full":"Gaddum House, 6 Great Jackson Street Manchester Cheshire M15 4AS",
    "addr:housenumber":"6",
    "addr:postcode":"m15 4as",
    "addr:street":"Great Jackson Street",
    "iso:country":"GB",
    "sg:address":"Gaddum House, 6 Great Jackson Street",
    "sg:city":"Manchester",
    "sg:classifiers":[
        {
            "category":"Professional",
            "subcategory":"Art Services",
            "type":"Services"
        }
    ],
    "sg:phone":"+44 161 834 7080",
    "sg:postcode":"M15 4AS",
    "sg:province":"Cheshire",
    "sg:tags":[
        "photographer"
    ],
    "wof:name":"Nick Brown Photography",
    "wof:placetype":"venue"
},
  "geometry": {"coordinates":[-2.253896,53.472244],"type":"Point"}
}