{
  "type": "Feature",
  "properties": {
    "addr:full":"Townsend House, Clement Street Birmingham West Midlands B1 2RT",
    "addr:postcode":"b1 2rt",
    "addr:street":"Clement Street",
    "iso:country":"GB",
    "sg:address":"Townsend House, Clement Street",
    "sg:city":"Birmingham",
    "sg:classifiers":[
        {
            "category":"Professional",
            "subcategory":"Engineering",
            "type":"Services"
        }
    ],
    "sg:phone":"+44 121 236 2877",
    "sg:postcode":"B1 2RT",
    "sg:province":"West Midlands",
    "wof:name":"L B E Contract Tooling Ltd.",
    "wof:placetype":"venue"
},
  "geometry": {"coordinates":[-1.913383,52.481918],"type":"Point"}
}