{
  "type": "Feature",
  "properties": {
    "iso:country":"GB",
    "sg:address":"22 St Mary's Walk",
    "sg:city":"Mirfield",
    "sg:classifiers":[
        {
            "category":"Building & Trades",
            "subcategory":"Construction",
            "type":"Services"
        }
    ],
    "sg:phone":"+44 1924 494718",
    "sg:postcode":"WF14 0QB",
    "sg:province":"West Yorkshire",
    "sg:tags":[
        "tiling",
        "contractor"
    ],
    "wof:name":"Boyes-hunter C G",
    "wof:placetype":"venue"
},
  "geometry": {"coordinates":[-1.699416995,53.6707954407],"type":"Point"}
}