{
  "type": "Feature",
  "properties": {
    "addr:full":"High St, Westend Southampton Hampshire SO30 3JJ",
    "addr:postcode":"so30 3jj",
    "addr:street":"High St",
    "iso:country":"GB",
    "sg:address":"High St, Westend",
    "sg:city":"Southampton",
    "sg:classifiers":[
        {
            "category":"Organizations",
            "subcategory":"Membership Organization",
            "type":"Services"
        }
    ],
    "sg:postcode":"SO30 3JJ",
    "sg:province":"Hampshire",
    "sg:tags":[
        "club"
    ],
    "wof:name":"Gee (Merton) Management Co Ltd",
    "wof:placetype":"venue"
},
  "geometry": {"coordinates":[-1.3436310291,50.9288597107],"type":"Point"}
}