{
  "type": "Feature",
  "properties": {
    "iso:country":"GB",
    "sg:address":"East Midland Intntl Airport, Castle Donington",
    "sg:city":"Derby",
    "sg:classifiers":[
        {
            "category":"Professional",
            "subcategory":"Art Services",
            "type":"Services"
        }
    ],
    "sg:phone":"+44 1332 814850",
    "sg:postcode":"DE74 2SA",
    "sg:province":"Leicestershire",
    "sg:tags":[
        "graphic",
        "designer"
    ],
    "wof:name":"Aviation Graphics Ltd.",
    "wof:placetype":"venue"
},
  "geometry": {"coordinates":[-1.3373839855,52.8448791504],"type":"Point"}
}