{
  "type": "Feature",
  "properties": {
    "addr:full":"6 Pat-yat, Kemble Cirencester Gloucestershire GL7 6AY",
    "addr:housenumber":"6",
    "addr:postcode":"gl7 6ay",
    "addr:street":"Pat-Yat Kemble",
    "iso:country":"GB",
    "sg:address":"6 Pat-yat, Kemble",
    "sg:city":"Cirencester",
    "sg:classifiers":[
        {
            "category":"Retail",
            "subcategory":"Auto Repair",
            "type":"Services"
        }
    ],
    "sg:phone":"+44 1285 771221",
    "sg:postcode":"GL7 6AY",
    "sg:province":"Gloucestershire",
    "sg:tags":[
        "modification",
        "garage"
    ],
    "wof:name":"Oaksey Garage",
    "wof:placetype":"venue"
},
  "geometry": {"coordinates":[-2.018334,51.675209],"type":"Point"}
}