{
  "type": "Feature",
  "properties": {
    "iso:country":"GB",
    "sg:address":"Eaves Lane, Chadderton",
    "sg:city":"Oldham",
    "sg:classifiers":[
        {
            "category":"Shopping",
            "subcategory":"Pharmacy",
            "type":"Retail Goods"
        }
    ],
    "sg:phone":"+44 161 620 5005",
    "sg:postcode":"OL9 8RT",
    "sg:province":"Lancashire",
    "sg:tags":[
        "dispensing",
        "store",
        "pharmacist",
        "chemist",
        "drug"
    ],
    "wof:name":"Goldstone & Watson Ltd.",
    "wof:placetype":"venue"
},
  "geometry": {"coordinates":[-2.151644,53.53373],"type":"Point"}
}