{
  "type": "Feature",
  "properties": {
    "addr:full":"1 Bridge Street Hereford Herefordshire HR4 9DF",
    "addr:housenumber":"1",
    "addr:postcode":"hr4 9df",
    "addr:street":"Bridge Street",
    "iso:country":"GB",
    "sg:address":"1 Bridge Street",
    "sg:city":"Hereford",
    "sg:classifiers":[
        {
            "category":"Real Estate",
            "subcategory":"Real Estate Agent",
            "type":"Services"
        }
    ],
    "sg:phone":"+44 1432 266775",
    "sg:postcode":"HR4 9DF",
    "sg:province":"Herefordshire",
    "sg:website":"http://www.andrew-morris.co.uk",
    "wof:name":"Andrew Morris & Co",
    "wof:placetype":"venue"
},
  "geometry": {"coordinates":[-2.718724,52.054165],"type":"Point"}
}