{
  "type": "Feature",
  "properties": {
    "addr:full":"Sunnyside Walton-on-thames Surrey KT12 2ET",
    "addr:postcode":"kt12 2et",
    "addr:street":"Walton-On-Thames",
    "iso:country":"GB",
    "sg:address":"Sunnyside",
    "sg:city":"Walton-on-thames",
    "sg:classifiers":[
        {
            "category":"Home & Garden",
            "subcategory":"Building Materials",
            "type":"Retail Goods"
        },
        {
            "category":"Military Area",
            "subcategory":"Air Force Base",
            "type":"Public Place"
        }
    ],
    "sg:phone":"+44 1932 220980",
    "sg:postcode":"KT12 2ET",
    "sg:province":"Surrey",
    "sg:tags":[
        "ornamental",
        "ironwork",
        "production",
        "diy",
        "metalwork",
        "wrought"
    ],
    "wof:name":"R M Brown",
    "wof:placetype":"venue"
},
  "geometry": {"coordinates":[-0.4031989872,51.3973693848],"type":"Point"}
}