{
  "type": "Feature",
  "properties": {
    "iso:country":"GB",
    "sg:address":"Bute Lodge, Wharf St",
    "sg:city":"Warwick",
    "sg:classifiers":[
        {
            "category":"Retail",
            "subcategory":"Storage",
            "type":"Services"
        }
    ],
    "sg:phone":"+44 1926 499919",
    "sg:postcode":"CV34 5LB",
    "sg:province":"Warwickshire",
    "sg:tags":[
        "household",
        "removal"
    ],
    "wof:name":"Andrews Removals (1883) Ltd",
    "wof:placetype":"venue"
},
  "geometry": {"coordinates":[-1.5910340548,52.28175354],"type":"Point"}
}