{
  "type": "Feature",
  "properties": {
    "addr:full":"10 Seamoor Road Bournemouth Dorset BH4 9AN",
    "addr:housenumber":"10",
    "addr:postcode":"bh4 9an",
    "addr:street":"Seamoor Road",
    "iso:country":"GB",
    "sg:address":"10 Seamoor Road",
    "sg:city":"Bournemouth",
    "sg:classifiers":[
        {
            "category":"Personal",
            "type":"Services"
        }
    ],
    "sg:phone":"+44 1202 763113",
    "sg:postcode":"BH4 9AN",
    "sg:province":"Dorset",
    "sg:tags":[
        "delivery"
    ],
    "wof:name":"Royal Mail",
    "wof:placetype":"venue"
},
  "geometry": {"coordinates":[-1.9023510218,50.7219467163],"type":"Point"}
}