{
  "type": "Feature",
  "properties": {
    "addr:full":"Praze, Black Rock Camborne Cornwall TR14 9NR",
    "addr:postcode":"tr14 9nr",
    "iso:country":"GB",
    "sg:address":"Praze, Black Rock",
    "sg:city":"Camborne",
    "sg:classifiers":[
        {
            "category":"Retail",
            "subcategory":"Auto Repair",
            "type":"Services"
        }
    ],
    "sg:phone":"+44 1209 831799",
    "sg:postcode":"TR14 9NR",
    "sg:province":"Cornwall",
    "sg:tags":[
        "bodybuilder",
        "repairer"
    ],
    "wof:name":"Kerrier Coach Works",
    "wof:placetype":"venue"
},
  "geometry": {"coordinates":[-5.2777891159,50.1680793762],"type":"Point"}
}