{
  "type": "Feature",
  "properties": {
    "iso:country":"GB",
    "sg:address":"55 Graham Gardens",
    "sg:city":"Luton",
    "sg:classifiers":[
        {
            "category":"Building & Trades",
            "subcategory":"Construction",
            "type":"Services"
        }
    ],
    "sg:phone":"+44 1582 755644",
    "sg:postcode":"LU3 1NF",
    "sg:province":"Bedfordshire",
    "sg:tags":[
        "decorator",
        "painter"
    ],
    "wof:name":"Adrian Wise",
    "wof:placetype":"venue"
},
  "geometry": {"coordinates":[-0.426011,51.899719],"type":"Point"}
}