{
  "type": "Feature",
  "properties": {
    "addr:full":"Lightwood Grn, Overton Wrexham Wrexham LL13 0HY",
    "addr:postcode":"ll13 0hy",
    "addr:street":"Lightwood Grn",
    "iso:country":"GB",
    "sg:address":"Lightwood Grn, Overton",
    "sg:city":"Wrexham",
    "sg:classifiers":[
        {
            "category":"Freight",
            "type":"Transportation"
        }
    ],
    "sg:phone":"+44 1978 710478",
    "sg:postcode":"LL13 0HY",
    "sg:province":"Wrexham",
    "sg:tags":[
        "haulage",
        "transport",
        "road"
    ],
    "wof:name":"Reeves Bros",
    "wof:placetype":"venue"
},
  "geometry": {"coordinates":[-2.934289,52.968571],"type":"Point"}
}