{
  "type": "Feature",
  "properties": {
    "iso:country":"GB",
    "sg:address":"81 Melton Road, West Bridgford",
    "sg:city":"Nottingham",
    "sg:classifiers":[
        {
            "category":"Professional",
            "subcategory":"Accounting & Tax Preparation",
            "type":"Services"
        }
    ],
    "sg:postcode":"NG2 6EN",
    "sg:province":"Nottinghamshire",
    "sg:tags":[
        "accountant"
    ],
    "wof:name":"Longley & Co",
    "wof:placetype":"venue"
},
  "geometry": {"coordinates":[-1.129656,52.927429],"type":"Point"}
}