{
  "type": "Feature",
  "properties": {
    "addr:full":"Chilford Hall, Balsham Road Cambridge Cambridgeshire CB1 6LE",
    "addr:postcode":"cb1 6le",
    "addr:street":"Balsham Road",
    "iso:country":"GB",
    "sg:address":"Chilford Hall, Balsham Road",
    "sg:city":"Cambridge",
    "sg:classifiers":[
        {
            "category":"Professional",
            "subcategory":"Printing & Photocopies",
            "type":"Services"
        }
    ],
    "sg:phone":"+44 1223 893544",
    "sg:postcode":"CB1 6LE",
    "sg:province":"Cambridgeshire",
    "sg:tags":[
        "printer"
    ],
    "wof:name":"Curwen Chilford Prints Ltd.",
    "wof:placetype":"venue"
},
  "geometry": {"coordinates":[0.315337,52.132877],"type":"Point"}
}