{
  "type": "Feature",
  "properties": {
    "addr:full":"76 Neale Rd Sevenoaks Kent TN15 6DQ",
    "addr:housenumber":"76",
    "addr:postcode":"tn15 6dq",
    "addr:street":"Neale Rd",
    "iso:country":"GB",
    "sg:address":"76 Neale Rd",
    "sg:city":"Sevenoaks",
    "sg:classifiers":[
        {
            "category":"Professional",
            "subcategory":"Detective & Security Services",
            "type":"Services"
        }
    ],
    "sg:phone":"+44 7956 409058",
    "sg:postcode":"TN15 6DQ",
    "sg:province":"Kent",
    "sg:tags":[
        "locksmith"
    ],
    "wof:name":"Aden Security Locksmiths",
    "wof:placetype":"venue"
},
  "geometry": {"coordinates":[0.2570610046,51.355342865],"type":"Point"}
}