{
  "type": "Feature",
  "properties": {
    "addr:full":"2nd Floor South West Suite, 59 Lansdowne Place Hove East Sussex BN3 1FL",
    "addr:housenumber":"2nd floor south;59",
    "addr:postcode":"bn3 1fl",
    "addr:street":"West Suite;Lansdowne Place Hove",
    "iso:country":"GB",
    "sg:address":"2nd Floor South West Suite, 59 Lansdowne Place",
    "sg:city":"Hove",
    "sg:classifiers":[
        {
            "category":"Professional",
            "subcategory":"Advertising",
            "type":"Services"
        }
    ],
    "sg:phone":"+44 1273 738399",
    "sg:postcode":"BN3 1FL",
    "sg:province":"East Sussex",
    "sg:tags":[
        "mail",
        "direct"
    ],
    "wof:name":"Bridge Direct Marketing",
    "wof:placetype":"venue"
},
  "geometry": {"coordinates":[-0.182449,50.838943],"type":"Point"}
}