{
  "type": "Feature",
  "properties": {
    "iso:country":"GB",
    "sg:address":"23 Nash Lane",
    "sg:city":"Margate",
    "sg:classifiers":[
        {
            "category":"Professional",
            "subcategory":"Art Services",
            "type":"Services"
        }
    ],
    "sg:phone":"+44 1843 224963",
    "sg:postcode":"CT9 4EX",
    "sg:province":"Kent",
    "sg:tags":[
        "photographer"
    ],
    "wof:name":"Martin Welch",
    "wof:placetype":"venue"
},
  "geometry": {"coordinates":[1.385446,51.373909],"type":"Point"}
}