{
  "type": "Feature",
  "properties": {
    "addr:full":"56 Bilton Road, Perivale Greenford Greater London UB6 7DH",
    "addr:housenumber":"56",
    "addr:postcode":"ub6 7dh",
    "addr:street":"Bilton Road",
    "iso:country":"GB",
    "sg:address":"56 Bilton Road, Perivale",
    "sg:city":"Greenford",
    "sg:classifiers":[
        {
            "category":"Travel",
            "subcategory":"Travel Agent",
            "type":"Entertainment"
        }
    ],
    "sg:phone":"+44 20 8998 9095",
    "sg:postcode":"UB6 7DH",
    "sg:province":"Greater London",
    "wof:name":"Robert Barrett Travel",
    "wof:placetype":"venue"
},
  "geometry": {"coordinates":[-0.3099209964,51.5395088196],"type":"Point"}
}