{
  "type": "Feature",
  "properties": {
    "addr:full":"33 Kelthorpe Close, Ketton Stamford Cambridgeshire PE9 3RS",
    "addr:housenumber":"33",
    "addr:postcode":"pe9 3rs",
    "addr:street":"Kelthorpe Close",
    "iso:country":"GB",
    "sg:address":"33 Kelthorpe Close, Ketton",
    "sg:city":"Stamford",
    "sg:classifiers":[
        {
            "category":"Retail",
            "subcategory":"Driving School",
            "type":"Services"
        }
    ],
    "sg:postcode":"PE9 3RS",
    "sg:province":"Cambridgeshire",
    "wof:name":"Pennys School of Motoring",
    "wof:placetype":"venue"
},
  "geometry": {"coordinates":[-0.54733,52.62299],"type":"Point"}
}