{
  "type": "Feature",
  "properties": {
    "addr:full":"81 Clifton St Lytham St Annes Lancashire FY8 5ER",
    "addr:housenumber":"81",
    "addr:postcode":"fy8 5er",
    "addr:street":"Clifton St;St",
    "iso:country":"GB",
    "sg:address":"81 Clifton St",
    "sg:city":"Lytham St Annes",
    "sg:classifiers":[
        {
            "category":"Restaurant",
            "type":"Food & Drink"
        }
    ],
    "sg:phone":"+44 1253 796473",
    "sg:postcode":"FY8 5ER",
    "sg:province":"Lancashire",
    "wof:name":"Una Vez",
    "wof:placetype":"venue"
},
  "geometry": {"coordinates":[-2.9616689682,53.7372894287],"type":"Point"}
}