{
  "type": "Feature",
  "properties": {
    "addr:full":"3 Lichfield Terrace, Sheen Rd Richmond Greater London TW9 1AS",
    "addr:housenumber":"3",
    "addr:postcode":"tw9 1as",
    "addr:street":"Lichfield Terrace Sheen Rd",
    "iso:country":"GB",
    "sg:address":"3 Lichfield Terrace, Sheen Rd",
    "sg:city":"Richmond",
    "sg:classifiers":[
        {
            "category":"Real Estate",
            "subcategory":"Real Estate Agent",
            "type":"Services"
        }
    ],
    "sg:phone":"+44 20 8940 6789",
    "sg:postcode":"TW9 1AS",
    "sg:province":"Greater London",
    "wof:name":"Town Choice",
    "wof:placetype":"venue"
},
  "geometry": {"coordinates":[-0.300182,51.461067],"type":"Point"}
}