{
  "type": "Feature",
  "properties": {
    "iso:country":"GB",
    "sg:address":"Shadycombe Road",
    "sg:city":"Salcombe",
    "sg:classifiers":[
        {
            "category":"Health Services",
            "subcategory":"Doctor",
            "type":"Services"
        },
        {
            "category":"Health Services",
            "subcategory":"Clinic",
            "type":"Services"
        }
    ],
    "sg:phone":"+44 1548 842284",
    "sg:postcode":"TQ8 8DJ",
    "sg:province":"Devon",
    "sg:tags":[
        "nh",
        "practitioners"
    ],
    "wof:name":"Redfern Health Centre",
    "wof:placetype":"venue"
},
  "geometry": {"coordinates":[-3.771569,50.239624],"type":"Point"}
}