{
  "type": "Feature",
  "properties": {
    "addr:full":"46 Manor Road, London Colney St Albans Hertfordshire AL2 1PW",
    "addr:housenumber":"46",
    "addr:postcode":"al2 1pw",
    "addr:street":"Manor Road",
    "iso:country":"GB",
    "sg:address":"46 Manor Road, London Colney",
    "sg:city":"St Albans",
    "sg:classifiers":[
        {
            "category":"Building & Trades",
            "subcategory":"Construction",
            "type":"Services"
        }
    ],
    "sg:phone":"+44 1727 824237",
    "sg:postcode":"AL2 1PW",
    "sg:province":"Hertfordshire",
    "sg:tags":[
        "flooring"
    ],
    "wof:name":"G J Hinson Flooring Co",
    "wof:placetype":"venue"
},
  "geometry": {"coordinates":[-0.3035019934,51.7234802246],"type":"Point"}
}