{
  "type": "Feature",
  "properties": {
    "addr:full":"Kingfisher Drive Glasgow Glasgow City G13 4QA",
    "addr:postcode":"g13 4qa",
    "addr:street":"Kingfisher Drive",
    "iso:country":"GB",
    "sg:address":"Kingfisher Drive",
    "sg:city":"Glasgow",
    "sg:classifiers":[
        {
            "category":"Real Estate",
            "subcategory":"Developer",
            "type":"Services"
        },
        {
            "category":"Building & Trades",
            "subcategory":"Construction",
            "type":"Services"
        }
    ],
    "sg:phone":"+44 141 959 7653",
    "sg:postcode":"G13 4QA",
    "sg:province":"Glasgow City",
    "sg:tags":[
        "residential",
        "builder",
        "property"
    ],
    "wof:name":"BEAZER HOMES GLASGOW LTD",
    "wof:placetype":"venue"
},
  "geometry": {"coordinates":[-4.3707890511,55.8956108093],"type":"Point"}
}