{
  "type": "Feature",
  "properties": {
    "addr:full":"16 The Forge Shopping Cen, Gallowgate Glasgow Glasgow City G31 4EB",
    "addr:housenumber":"16",
    "addr:postcode":"g31 4eb",
    "addr:street":"The Forge;Gallowgate",
    "iso:country":"GB",
    "sg:address":"16 The Forge Shopping Cen, Gallowgate",
    "sg:city":"Glasgow",
    "sg:classifiers":[
        {
            "category":"Shopping",
            "subcategory":"Shoes",
            "type":"Retail Goods"
        }
    ],
    "sg:phone":"+44 141 556 2744",
    "sg:postcode":"G31 4EB",
    "sg:province":"Glasgow City",
    "sg:tags":[
        "shop"
    ],
    "wof:name":"Stead & Simpson Ltd.",
    "wof:placetype":"venue"
},
  "geometry": {"coordinates":[-4.19981,55.853481],"type":"Point"}
}