{
  "type": "Feature",
  "properties": {
    "iso:country":"GB",
    "sg:address":"47 Livingstone Rd",
    "sg:city":"Blackpool",
    "sg:classifiers":[
        {
            "category":"Building & Trades",
            "subcategory":"Construction",
            "type":"Services"
        }
    ],
    "sg:phone":"+44 1253 623232",
    "sg:postcode":"FY1 4BU",
    "sg:province":"Lancashire",
    "sg:tags":[
        "flooring"
    ],
    "wof:name":"Haldon Thompsons Ltd",
    "wof:placetype":"venue"
},
  "geometry": {"coordinates":[-3.0475599766,53.8118515015],"type":"Point"}
}