{
  "type": "Feature",
  "properties": {
    "addr:full":"Glan Yr Afon, Well St Merthyr Tydfil Caerphilly CF48 2LL",
    "addr:postcode":"cf48 2ll",
    "addr:street":"Yr Afon Well St",
    "iso:country":"GB",
    "sg:address":"Glan Yr Afon, Well St",
    "sg:city":"Merthyr Tydfil",
    "sg:classifiers":[
        {
            "category":"Retail",
            "subcategory":"Funeral Services",
            "type":"Services"
        }
    ],
    "sg:phone":"+44 1685 384538",
    "sg:postcode":"CF48 2LL",
    "sg:province":"Caerphilly",
    "sg:tags":[
        "director"
    ],
    "wof:name":"Raymond Iles & Sons",
    "wof:placetype":"venue"
},
  "geometry": {"coordinates":[-3.3996698856,51.7608299255],"type":"Point"}
}