{
  "type": "Feature",
  "properties": {
    "iso:country":"GB",
    "sg:address":"23-25 St Georges Street Off Regent St",
    "sg:city":"Northampton",
    "sg:classifiers":[
        {
            "category":"Community Center",
            "subcategory":"Youth",
            "type":"Public Place"
        }
    ],
    "sg:phone":"+44 1604 639636",
    "sg:postcode":"NN1 2TN",
    "sg:province":"Northamptonshire",
    "sg:tags":[
        "organisation",
        "centre"
    ],
    "wof:name":"Shiekh Community Centre And Youth Club",
    "wof:placetype":"venue"
},
  "geometry": {"coordinates":[-0.8993409872,52.2432136536],"type":"Point"}
}