{
  "type": "Feature",
  "properties": {
    "addr:full":"Unit 12 Radcliffe Moor Road, Bradley Fold Trading Estate Bolton Lancashire BL2 6RT",
    "addr:housenumber":"unit 12",
    "addr:postcode":"bl2 6rt",
    "addr:street":"Radcliffe Moor Road;Trading",
    "iso:country":"GB",
    "sg:address":"Unit 12 Radcliffe Moor Road, Bradley Fold Trading Estate",
    "sg:city":"Bolton",
    "sg:classifiers":[
        {
            "category":"Home & Garden",
            "subcategory":"Home Furnishings",
            "type":"Retail Goods"
        }
    ],
    "sg:phone":"+44 1204 366000",
    "sg:postcode":"BL2 6RT",
    "sg:province":"Lancashire",
    "sg:tags":[
        "furnishers",
        "planner",
        "kitchen"
    ],
    "wof:name":"Apple Kitchens",
    "wof:placetype":"venue"
},
  "geometry": {"coordinates":[-2.366329,53.573914],"type":"Point"}
}