{
  "type": "Feature",
  "properties": {
    "iso:country":"GB",
    "sg:address":"130 Marion Crescent",
    "sg:city":"Maidstone",
    "sg:classifiers":[
        {
            "category":"Building & Trades",
            "subcategory":"Construction",
            "type":"Services"
        }
    ],
    "sg:phone":"+44 1622 676152",
    "sg:postcode":"ME15 7EY",
    "sg:province":"Kent",
    "sg:tags":[
        "roofing",
        "contracting"
    ],
    "wof:name":"Miller Roofing",
    "wof:placetype":"venue"
},
  "geometry": {"coordinates":[0.536083,51.255405],"type":"Point"}
}