{
  "type": "Feature",
  "properties": {
    "iso:country":"GB",
    "sg:address":"3 Ransomes Dock, 35-37 Parkgate Road",
    "sg:city":"London",
    "sg:classifiers":[
        {
            "category":"Professional",
            "subcategory":"Secretarial Services",
            "type":"Services"
        }
    ],
    "sg:postcode":"SW11 4NP",
    "sg:province":"Greater London",
    "wof:name":"South Bank Office Services",
    "wof:placetype":"venue"
},
  "geometry": {"coordinates":[-0.16759,51.479031],"type":"Point"}
}