{
  "type": "Feature",
  "properties": {
    "iso:country":"GB",
    "sg:address":"241 Allerton Road, Allerton",
    "sg:city":"Bradford",
    "sg:classifiers":[
        {
            "category":"Food & Beverages",
            "subcategory":"Meat & Fish",
            "type":"Retail Goods"
        },
        {
            "category":"Food & Beverages",
            "subcategory":"Groceries & Convenience Stores",
            "type":"Retail Goods"
        }
    ],
    "sg:phone":"+44 1274 484876",
    "sg:postcode":"BD15 7QU",
    "sg:province":"West Yorkshire",
    "sg:tags":[
        "shop",
        "chip"
    ],
    "wof:name":"Allerton Fisheries",
    "wof:placetype":"venue"
},
  "geometry": {"coordinates":[-1.8182200193,53.8032913208],"type":"Point"}
}