{
  "type": "Feature",
  "properties": {
    "iso:country":"GB",
    "sg:address":"4 Addison Close, Petts Wood",
    "sg:city":"Orpington",
    "sg:classifiers":[
        {
            "category":"Building & Trades",
            "subcategory":"Plumbing",
            "type":"Services"
        }
    ],
    "sg:phone":"+44 1689 878578",
    "sg:postcode":"BR5 1DS",
    "sg:province":"Kent",
    "sg:tags":[
        "central",
        "heating"
    ],
    "wof:name":"Colin Andrew Evans",
    "wof:placetype":"venue"
},
  "geometry": {"coordinates":[0.074733,51.384491],"type":"Point"}
}