{
  "type": "Feature",
  "properties": {
    "addr:full":"122 Allport Rd, Bromborough Wirral Cheshire L62 6AQ",
    "addr:housenumber":"122",
    "addr:postcode":"l62 6aq",
    "addr:street":"Allport Rd",
    "iso:country":"GB",
    "sg:address":"122 Allport Rd, Bromborough",
    "sg:city":"Wirral",
    "sg:classifiers":[
        {
            "category":"Food & Beverages",
            "subcategory":"Candy",
            "type":"Retail Goods"
        }
    ],
    "sg:phone":"+44 151 334 6656",
    "sg:postcode":"L62 6AQ",
    "sg:province":"Cheshire",
    "sg:tags":[
        "confectioner"
    ],
    "wof:name":"Lucas-smith",
    "wof:placetype":"venue"
},
  "geometry": {"coordinates":[-2.97803,53.334751],"type":"Point"}
}