{
  "type": "Feature",
  "properties": {
    "addr:full":"2 Station Road, Barnack Stamford Cambridgeshire PE9 3DW",
    "addr:housenumber":"2",
    "addr:postcode":"pe9 3dw",
    "addr:street":"Station Road",
    "iso:country":"GB",
    "sg:address":"2 Station Road, Barnack",
    "sg:city":"Stamford",
    "sg:classifiers":[
        {
            "category":"Shopping",
            "subcategory":"Stationery & Office Supplies",
            "type":"Retail Goods"
        }
    ],
    "sg:phone":"+44 1780 740300",
    "sg:postcode":"PE9 3DW",
    "sg:province":"Cambridgeshire",
    "sg:tags":[
        "item",
        "promotional"
    ],
    "wof:name":"Libra Promotions International",
    "wof:placetype":"venue"
},
  "geometry": {"coordinates":[-0.4055280089,52.6344490051],"type":"Point"}
}