{
  "type": "Feature",
  "properties": {
    "addr:full":"349-351 Aldermans Green Road Coventry Warwickshire CV2 1PB",
    "addr:housenumber":"349-351",
    "addr:postcode":"cv2 1pb",
    "addr:street":"Aldermans Green Road",
    "iso:country":"GB",
    "sg:address":"349-351 Aldermans Green Road",
    "sg:city":"Coventry",
    "sg:classifiers":[
        {
            "category":"Shopping",
            "subcategory":"News",
            "type":"Retail Goods"
        }
    ],
    "sg:phone":"+44 24 7636 6872",
    "sg:postcode":"CV2 1PB",
    "sg:province":"Warwickshire",
    "sg:tags":[
        "newsagent"
    ],
    "wof:name":"Aldermans Green Post Office",
    "wof:placetype":"venue"
},
  "geometry": {"coordinates":[-1.470202,52.450596],"type":"Point"}
}