{
  "type": "Feature",
  "properties": {
    "addr:full":"820 Stratford Road, Sparkhill Birmingham West Midlands B11 4BS",
    "addr:housenumber":"820",
    "addr:postcode":"b11 4bs",
    "addr:street":"Stratford Road",
    "iso:country":"GB",
    "sg:address":"820 Stratford Road, Sparkhill",
    "sg:city":"Birmingham",
    "sg:classifiers":[
        {
            "category":"Shopping",
            "subcategory":"Clothing, Apparel, & Fashions",
            "type":"Retail Goods"
        }
    ],
    "sg:postcode":"B11 4BS",
    "sg:province":"West Midlands",
    "sg:tags":[
        "ladieswear"
    ],
    "wof:name":"Modern Girl",
    "wof:placetype":"venue"
},
  "geometry": {"coordinates":[-1.8592079878,52.4453010559],"type":"Point"}
}