{
  "type": "Feature",
  "properties": {
    "iso:country":"GB",
    "sg:address":"Woodside Farm, Thorpe In The Glebe, Wysall",
    "sg:city":"Nottingham",
    "sg:classifiers":[
        {
            "category":"Farming",
            "subcategory":"Livestock Farm",
            "type":"Manufacturing & Wholesale Goods"
        }
    ],
    "sg:postcode":"NG12 5QX",
    "sg:province":"Nottinghamshire",
    "sg:tags":[
        "others"
    ],
    "wof:name":"G W Atkinson & Son",
    "wof:placetype":"venue"
},
  "geometry": {"coordinates":[-1.103759,52.839497],"type":"Point"}
}