{
  "type": "Feature",
  "properties": {
    "addr:full":"14 Hollythorpe Crescent Sheffield Derbyshire S8 9NA",
    "addr:housenumber":"14",
    "addr:postcode":"s8 9na",
    "addr:street":"Hollythorpe Crescent",
    "iso:country":"GB",
    "sg:address":"14 Hollythorpe Crescent",
    "sg:city":"Sheffield",
    "sg:classifiers":[
        {
            "category":"Professional",
            "subcategory":"Detective & Security Services",
            "type":"Services"
        }
    ],
    "sg:phone":"+44 114 258 2722",
    "sg:postcode":"S8 9NA",
    "sg:province":"Derbyshire",
    "wof:name":"A D V Investigations",
    "wof:placetype":"venue"
},
  "geometry": {"coordinates":[-1.468213,53.351044],"type":"Point"}
}