{
  "type": "Feature",
  "properties": {
    "addr:full":"39 Albion Street Exmouth Devon EX8 1JJ",
    "addr:housenumber":"39",
    "addr:postcode":"ex8 1jj",
    "addr:street":"Albion Street",
    "iso:country":"GB",
    "sg:address":"39 Albion Street",
    "sg:city":"Exmouth",
    "sg:classifiers":[
        {
            "category":"Food & Beverages",
            "subcategory":"Meat & Fish",
            "type":"Retail Goods"
        }
    ],
    "sg:phone":"+44 1395 279319",
    "sg:postcode":"EX8 1JJ",
    "sg:province":"Devon",
    "sg:tags":[
        "chip"
    ],
    "wof:name":"The Golden Fryer Take Away",
    "wof:placetype":"venue"
},
  "geometry": {"coordinates":[-3.4097709656,50.6204185486],"type":"Point"}
}