{
  "type": "Feature",
  "properties": {
    "addr:full":"The Old Bank, 55 High Street Amersham Buckinghamshire HP7 0DR",
    "addr:housenumber":"55",
    "addr:postcode":"hp7 0dr",
    "addr:street":"High Street",
    "iso:country":"GB",
    "sg:address":"The Old Bank, 55 High Street",
    "sg:city":"Amersham",
    "sg:classifiers":[
        {
            "category":"Manufacturing",
            "subcategory":"Apparel",
            "type":"Manufacturing & Wholesale Goods"
        }
    ],
    "sg:phone":"+44 1494 722854",
    "sg:postcode":"HP7 0DR",
    "sg:province":"Buckinghamshire",
    "sg:tags":[
        "garment",
        "designer"
    ],
    "wof:name":"Chattertons",
    "wof:placetype":"venue"
},
  "geometry": {"coordinates":[-0.6168799996,51.6666183472],"type":"Point"}
}