{
  "type": "Feature",
  "properties": {
    "iso:country":"GB",
    "sg:address":"6 East Street, Bedminster",
    "sg:city":"Bristol",
    "sg:classifiers":[
        {
            "category":"Shopping",
            "subcategory":"Clothing, Apparel, & Fashions",
            "type":"Retail Goods"
        }
    ],
    "sg:phone":"+44 117 966 9366",
    "sg:postcode":"BS3 4JZ",
    "sg:province":"City of Bristol",
    "sg:tags":[
        "shop"
    ],
    "wof:name":"Revelation Shops",
    "wof:placetype":"venue"
},
  "geometry": {"coordinates":[-2.59501791,51.4431686401],"type":"Point"}
}