{
  "type": "Feature",
  "properties": {
    "iso:country":"GB",
    "sg:address":"Magnum House",
    "sg:city":"Leigh",
    "sg:classifiers":[
        {
            "category":"Personal",
            "type":"Services"
        }
    ],
    "sg:phone":"+44 1942 260080",
    "sg:postcode":"WN7 1BY",
    "sg:province":"Lancashire",
    "sg:tags":[
        "party",
        "organiser"
    ],
    "wof:name":"The Incredible Event Co. Ltd.",
    "wof:placetype":"venue"
},
  "geometry": {"coordinates":[-2.518994,53.496971],"type":"Point"}
}