{
  "type": "Feature",
  "properties": {
    "iso:country":"GB",
    "sg:address":"38 Hilltop Crescent, Edlington",
    "sg:city":"Doncaster",
    "sg:classifiers":[
        {
            "category":"Building & Trades",
            "subcategory":"Construction",
            "type":"Services"
        }
    ],
    "sg:postcode":"DN12 1HE",
    "sg:province":"South Yorkshire",
    "sg:tags":[
        "contractor",
        "paving",
        "driveway"
    ],
    "wof:name":"Hilltop Surfacing Contractors",
    "wof:placetype":"venue"
},
  "geometry": {"coordinates":[-1.192688,53.475845],"type":"Point"}
}