{
  "type": "Feature",
  "properties": {
    "addr:full":"Foresters Leisure Park, Osmaston Park Road, Sinfin Lane Derby Derbyshire DE23 8AG",
    "addr:postcode":"de23 8ag",
    "addr:street":"Park Osmaston Park Road Sinfin Lane",
    "iso:country":"GB",
    "sg:address":"Foresters Leisure Park, Osmaston Park Road, Sinfin Lane",
    "sg:city":"Derby",
    "sg:classifiers":[
        {
            "category":"Sports & Exercise",
            "subcategory":"Bowling",
            "type":"Entertainment"
        }
    ],
    "sg:phone":"+44 1332 270057",
    "sg:postcode":"DE23 8AG",
    "sg:province":"Derbyshire",
    "wof:name":"Derby Megabowl",
    "wof:placetype":"venue"
},
  "geometry": {"coordinates":[-1.4750000238,52.8964118958],"type":"Point"}
}