{
  "type": "Feature",
  "properties": {
    "iso:country":"GB",
    "sg:address":"Capitol Centre London Way, Walton-le-dale",
    "sg:city":"Preston",
    "sg:classifiers":[
        {
            "category":"Home & Garden",
            "subcategory":"Household Appliances",
            "type":"Retail Goods"
        }
    ],
    "sg:phone":"+44 1772 563251",
    "sg:postcode":"PR5 4AW",
    "sg:province":"Lancashire",
    "sg:tags":[
        "electrical",
        "domestic"
    ],
    "wof:name":"Currys",
    "wof:placetype":"venue"
},
  "geometry": {"coordinates":[-2.6775200367,53.748878479],"type":"Point"}
}