{
  "type": "Feature",
  "properties": {
    "addr:full":"Pant Coch, Ceinws Machynlleth Ceredigion SY20 9HE",
    "addr:postcode":"sy20 9he",
    "addr:street":"Pant;Ceinws",
    "iso:country":"GB",
    "sg:address":"Pant Coch, Ceinws",
    "sg:city":"Machynlleth",
    "sg:classifiers":[
        {
            "category":"Retail",
            "subcategory":"Auto Repair",
            "type":"Services"
        }
    ],
    "sg:phone":"+44 1654 761293",
    "sg:postcode":"SY20 9HE",
    "sg:province":"Ceredigion",
    "sg:tags":[
        "modification",
        "garage"
    ],
    "wof:name":"C J H Engineering",
    "wof:placetype":"venue"
},
  "geometry": {"coordinates":[-3.8341751099,52.636806488],"type":"Point"}
}