{
  "type": "Feature",
  "properties": {
    "addr:full":"59 Pages Hill, Muswell Hill London Greater London N10 1EH",
    "addr:housenumber":"59",
    "addr:postcode":"n10 1eh",
    "addr:street":"Pages Hill",
    "iso:country":"GB",
    "sg:address":"59 Pages Hill, Muswell Hill",
    "sg:city":"London",
    "sg:classifiers":[
        {
            "category":"Fast Food",
            "type":"Food & Drink"
        }
    ],
    "sg:postcode":"N10 1EH",
    "sg:province":"Greater London",
    "sg:tags":[
        "away",
        "take"
    ],
    "wof:name":"Cafe Libano Ltd",
    "wof:placetype":"venue"
},
  "geometry": {"coordinates":[-0.146512,51.597672],"type":"Point"}
}