{
  "type": "Feature",
  "properties": {
    "addr:full":"17 Eccles Rd High Peak Cheshire SK23 9RP",
    "addr:housenumber":"17",
    "addr:postcode":"sk23 9rp",
    "addr:street":"Eccles Rd",
    "iso:country":"GB",
    "sg:address":"17 Eccles Rd",
    "sg:city":"High Peak",
    "sg:classifiers":[
        {
            "category":"Social Services",
            "subcategory":"Retirement Home",
            "type":"Services"
        }
    ],
    "sg:phone":"+44 1298 814700",
    "sg:postcode":"SK23 9RP",
    "sg:province":"Cheshire",
    "sg:tags":[
        "care"
    ],
    "wof:name":"Moncrieff Homecare Services",
    "wof:placetype":"venue"
},
  "geometry": {"coordinates":[-1.926144,53.324295],"type":"Point"}
}