{
  "type": "Feature",
  "properties": {
    "addr:full":"10 Theatre Street Preston Lancashire PR1 8BQ",
    "addr:housenumber":"10",
    "addr:postcode":"pr1 8bq",
    "addr:street":"Theatre Street",
    "iso:country":"GB",
    "sg:address":"10 Theatre Street",
    "sg:city":"Preston",
    "sg:classifiers":[
        {
            "category":"Banks & Credit Unions",
            "subcategory":"Financial Services",
            "type":"Services"
        }
    ],
    "sg:phone":"+44 1772 909902",
    "sg:postcode":"PR1 8BQ",
    "sg:province":"Lancashire",
    "sg:tags":[
        "adviser",
        "independent"
    ],
    "wof:name":"Ashley Law",
    "wof:placetype":"venue"
},
  "geometry": {"coordinates":[-2.7045390606,53.7571563721],"type":"Point"}
}