{
  "type": "Feature",
  "properties": {
    "iso:country":"GB",
    "sg:address":"Light House, Unit 33b, High Street",
    "sg:city":"Staines",
    "sg:classifiers":[
        {
            "category":"Professional",
            "subcategory":"Management & Consulting",
            "type":"Services"
        }
    ],
    "sg:phone":"+44 1491 413923",
    "sg:postcode":"TW19 5DA",
    "sg:province":"Berkshire",
    "sg:tags":[
        "consultant",
        "safety"
    ],
    "wof:name":"National Training First & Inspection Ltd.",
    "wof:placetype":"venue"
},
  "geometry": {"coordinates":[-0.554474,51.456879],"type":"Point"}
}