{
  "type": "Feature",
  "properties": {
    "iso:country":"GB",
    "sg:address":"Huntercombe Lane South, Taplow",
    "sg:city":"Maidenhead",
    "sg:classifiers":[
        {
            "category":"Shopping",
            "subcategory":"Pharmacy",
            "type":"Retail Goods"
        }
    ],
    "sg:phone":"+44 1628 604377",
    "sg:postcode":"SL6 0PH",
    "sg:province":"Berkshire",
    "sg:tags":[
        "pharmaceutical"
    ],
    "wof:name":"American Home Products Holdings (U K) Ltd.",
    "wof:placetype":"venue"
},
  "geometry": {"coordinates":[-0.658949,51.519936],"type":"Point"}
}