{
  "type": "Feature",
  "properties": {
    "addr:full":"26 Pembroke Road Bootle Merseyside L20 7BB",
    "addr:housenumber":"26",
    "addr:postcode":"l20 7bb",
    "addr:street":"Pembroke Road",
    "iso:country":"GB",
    "sg:address":"26 Pembroke Road",
    "sg:city":"Bootle",
    "sg:classifiers":[
        {
            "category":"Retail",
            "subcategory":"Auto Repair",
            "type":"Services"
        }
    ],
    "sg:phone":"+44 151 933 0066",
    "sg:postcode":"L20 7BB",
    "sg:province":"Merseyside",
    "sg:tags":[
        "modification",
        "garage"
    ],
    "wof:name":"L A J Heldt",
    "wof:placetype":"venue"
},
  "geometry": {"coordinates":[-2.9920349121,53.4455223083],"type":"Point"}
}