{
  "type": "Feature",
  "properties": {
    "addr:full":"93 Allport Rd, Bromborough Wirral Cheshire CH62 6AB",
    "addr:housenumber":"93",
    "addr:postcode":"ch62 6ab",
    "addr:street":"Allport Rd",
    "iso:country":"GB",
    "sg:address":"93 Allport Rd, Bromborough",
    "sg:city":"Wirral",
    "sg:classifiers":[
        {
            "category":"Professional",
            "subcategory":"Computer Services",
            "type":"Services"
        }
    ],
    "sg:postcode":"CH62 6AB",
    "sg:province":"Cheshire",
    "sg:tags":[
        "system",
        "software"
    ],
    "wof:name":"Watson,Dave,",
    "wof:placetype":"venue"
},
  "geometry": {"coordinates":[-2.980054,53.322769],"type":"Point"}
}