{
  "type": "Feature",
  "properties": {
    "addr:full":"Denmede, Eddington Road Seaview Isle of Wight PO34 5EE",
    "addr:postcode":"po34 5ee",
    "addr:street":"Eddington Road",
    "iso:country":"GB",
    "sg:address":"Denmede, Eddington Road",
    "sg:city":"Seaview",
    "sg:classifiers":[
        {
            "category":"Military Area",
            "subcategory":"Air Force Base",
            "type":"Public Place"
        }
    ],
    "sg:postcode":"PO34 5EE",
    "sg:province":"Isle of Wight",
    "sg:tags":[
        "taxi",
        "hire",
        "private"
    ],
    "wof:name":"Bill's Taxis",
    "wof:placetype":"venue"
},
  "geometry": {"coordinates":[-1.110274,50.719559],"type":"Point"}
}