{
  "type": "Feature",
  "properties": {
    "addr:full":"57 Bath Lane Leicester Leicestershire LE3 5BF",
    "addr:housenumber":"57",
    "addr:postcode":"le3 5bf",
    "addr:street":"Bath Lane",
    "iso:country":"GB",
    "sg:address":"57 Bath Lane",
    "sg:city":"Leicester",
    "sg:classifiers":[
        {
            "category":"Shopping",
            "subcategory":"Clothing, Apparel, & Fashions",
            "type":"Retail Goods"
        }
    ],
    "sg:phone":"+44 116 251 3397",
    "sg:postcode":"LE3 5BF",
    "sg:province":"Leicestershire",
    "sg:tags":[
        "clothing",
        "fabric"
    ],
    "wof:name":"Y E S Clothing Co. Ltd.",
    "wof:placetype":"venue"
},
  "geometry": {"coordinates":[-1.1431139708,52.6354293823],"type":"Point"}
}