{
  "type": "Feature",
  "properties": {
    "addr:full":"Unit 32, Blackmore Park, Hanley Swan Worcester Gloucestershire WR8 0EF",
    "addr:housenumber":"unit 32",
    "addr:postcode":"wr8 0ef",
    "addr:street":"Blackmore Park",
    "iso:country":"GB",
    "sg:address":"Unit 32, Blackmore Park, Hanley Swan",
    "sg:city":"Worcester",
    "sg:classifiers":[
        {
            "category":"Manufacturing",
            "subcategory":"Glass & Minerals",
            "type":"Manufacturing & Wholesale Goods"
        }
    ],
    "sg:postcode":"WR8 0EF",
    "sg:province":"Gloucestershire",
    "sg:tags":[
        "fibre",
        "moulding"
    ],
    "wof:name":"Hanley Glass Fiber Mouldings Ltd.",
    "wof:placetype":"venue"
},
  "geometry": {"coordinates":[-2.2735788822,52.0839118958],"type":"Point"}
}