{
  "type": "Feature",
  "properties": {
    "iso:country":"GB",
    "sg:address":"47/49 Crowmere Road",
    "sg:city":"Shrewsbury",
    "sg:classifiers":[
        {
            "category":"Shopping",
            "subcategory":"Department Store",
            "type":"Retail Goods"
        }
    ],
    "sg:phone":"+44 1743 356842",
    "sg:postcode":"SY2 5HT",
    "sg:province":"Shropshire",
    "wof:name":"A G & E Cook",
    "wof:placetype":"venue"
},
  "geometry": {"coordinates":[-2.735574,52.709629],"type":"Point"}
}