{
  "type": "Feature",
  "properties": {
    "iso:country":"GB",
    "sg:address":"52 Osborne Street",
    "sg:city":"Glasgow",
    "sg:classifiers":[
        {
            "category":"Wholesale",
            "subcategory":"Music Publishers",
            "type":"Manufacturing & Wholesale Goods"
        }
    ],
    "sg:phone":"+44 141 552 0375",
    "sg:postcode":"G1 5QH",
    "sg:province":"Glasgow City",
    "sg:tags":[
        "record"
    ],
    "wof:name":"Randan Ltd.",
    "wof:placetype":"venue"
},
  "geometry": {"coordinates":[-4.2468791008,55.85597229],"type":"Point"}
}