{
  "type": "Feature",
  "properties": {
    "addr:full":"17 Gartocher Terr Glasgow Glasgow City G32 0HE",
    "addr:housenumber":"17",
    "addr:postcode":"g32 0he",
    "addr:street":"Gartocher Terr",
    "iso:country":"GB",
    "sg:address":"17 Gartocher Terr",
    "sg:city":"Glasgow",
    "sg:classifiers":[
        {
            "category":"Wholesale",
            "subcategory":"Scrap",
            "type":"Manufacturing & Wholesale Goods"
        }
    ],
    "sg:phone":"+44 141 402 6828",
    "sg:postcode":"G32 0HE",
    "sg:province":"Glasgow City",
    "sg:tags":[
        "breaker",
        "dismantlers"
    ],
    "wof:name":"Dead End Autos",
    "wof:placetype":"venue"
},
  "geometry": {"coordinates":[-4.1526908875,55.8539772034],"type":"Point"}
}