{
  "type": "Feature",
  "properties": {
    "iso:country":"GB",
    "sg:address":"28 Worthing Rd",
    "sg:city":"Horsham",
    "sg:classifiers":[
        {
            "category":"Health Services",
            "subcategory":"Dentist",
            "type":"Services"
        }
    ],
    "sg:phone":"+44 1403 252646",
    "sg:postcode":"RH12 1SL",
    "sg:province":"West Sussex",
    "wof:name":"G L Bell",
    "wof:placetype":"venue"
},
  "geometry": {"coordinates":[-0.334176,51.061916],"type":"Point"}
}