{
  "type": "Feature",
  "properties": {
    "iso:country":"GB",
    "sg:address":"Unit 17a Honeybourne Airfield Indust Est, Weston Road, Honeybourne",
    "sg:city":"Evesham",
    "sg:classifiers":[
        {
            "category":"Autos & Motor Vehicles",
            "subcategory":"Automobile Sales",
            "type":"Retail Goods"
        }
    ],
    "sg:phone":"+44 1386 834234",
    "sg:postcode":"WR11 5QF",
    "sg:province":"Gloucestershire",
    "sg:tags":[
        "car",
        "specialist",
        "sales",
        "classic"
    ],
    "wof:name":"W Allman",
    "wof:placetype":"venue"
},
  "geometry": {"coordinates":[-1.83043,52.093491],"type":"Point"}
}