{
  "type": "Feature",
  "properties": {
    "iso:country":"GB",
    "sg:address":"9 Swift House, Sandbrook Rd",
    "sg:city":"Stoke Newington",
    "sg:classifiers":[
        {
            "category":"Professional",
            "type":"Services"
        }
    ],
    "sg:phone":"+44 20 7241 1511",
    "sg:postcode":"N16 0SJ",
    "sg:province":"Greater London",
    "sg:tags":[
        "entertainer"
    ],
    "wof:name":"Nu-age Arts",
    "wof:placetype":"venue"
},
  "geometry": {"coordinates":[-0.08093,51.559368],"type":"Point"}
}