{
  "type": "Feature",
  "properties": {
    "iso:country":"GB",
    "sg:address":"5 Eastcroft Rd",
    "sg:city":"Gosport",
    "sg:classifiers":[
        {
            "category":"Building & Trades",
            "subcategory":"Construction",
            "type":"Services"
        }
    ],
    "sg:phone":"+44 23 9258 4683",
    "sg:postcode":"PO12 3LG",
    "sg:province":"Hampshire",
    "sg:tags":[
        "decorator",
        "painter"
    ],
    "wof:name":"D W Bartlett",
    "wof:placetype":"venue"
},
  "geometry": {"coordinates":[-1.150203,50.799294],"type":"Point"}
}