{
  "type": "Feature",
  "properties": {
    "addr:full":"37-41 York Rd Ilford Essex IG1 3AD",
    "addr:housenumber":"37-41",
    "addr:postcode":"ig1 3ad",
    "addr:street":"York Rd",
    "iso:country":"GB",
    "sg:address":"37-41 York Rd",
    "sg:city":"Ilford",
    "sg:classifiers":[
        {
            "category":"Retail",
            "subcategory":"Repair Shop",
            "type":"Services"
        }
    ],
    "sg:phone":"+44 20 8553 5533",
    "sg:postcode":"IG1 3AD",
    "sg:province":"Essex",
    "sg:tags":[
        "maintenance"
    ],
    "wof:name":"Tokeley Ltd",
    "wof:placetype":"venue"
},
  "geometry": {"coordinates":[0.0676899999,51.5592575073],"type":"Point"}
}