{
  "type": "Feature",
  "properties": {
    "iso:country":"GB",
    "sg:address":"Buckingham House, Mineral Lane",
    "sg:city":"Chesham",
    "sg:classifiers":[
        {
            "category":"Manufacturing",
            "subcategory":"Rubber & Plastics",
            "type":"Manufacturing & Wholesale Goods"
        }
    ],
    "sg:phone":"+44 1494 774798",
    "sg:postcode":"HP5 1NL",
    "sg:province":"Buckinghamshire",
    "sg:tags":[
        "mould"
    ],
    "wof:name":"J A Dutch Toolmakers Ltd.",
    "wof:placetype":"venue"
},
  "geometry": {"coordinates":[-0.6105319858,51.7007904053],"type":"Point"}
}