{
  "type": "Feature",
  "properties": {
    "iso:country":"GB",
    "sg:address":"Flatts Farm, Rabbit Lane, Talbot Bridge",
    "sg:city":"Clitheroe",
    "sg:classifiers":[
        {
            "category":"Retail",
            "subcategory":"Repair Shop",
            "type":"Services"
        },
        {
            "category":"Wholesale",
            "subcategory":"Machinery & Supplies",
            "type":"Manufacturing & Wholesale Goods"
        }
    ],
    "sg:phone":"+44 1254 826295",
    "sg:postcode":"BB7 3NB",
    "sg:province":"Lancashire",
    "sg:tags":[
        "agricultural",
        "sale"
    ],
    "wof:name":"F G Rowland Ltd",
    "wof:placetype":"venue"
},
  "geometry": {"coordinates":[-2.391749,53.87278],"type":"Point"}
}