{
  "type": "Feature",
  "properties": {
    "addr:full":"3a Woodlawn Street Whitstable Kent CT5 1HG",
    "addr:housenumber":"3a",
    "addr:postcode":"ct5 1hg",
    "addr:street":"Woodlawn Street",
    "iso:country":"GB",
    "sg:address":"3a Woodlawn Street",
    "sg:city":"Whitstable",
    "sg:classifiers":[
        {
            "category":"Bars & Pubs",
            "subcategory":"Nightclub",
            "type":"Food & Drink"
        }
    ],
    "sg:postcode":"CT5 1HG",
    "sg:province":"Kent",
    "sg:tags":[
        "karaoke"
    ],
    "wof:name":"SMART KARAOKE",
    "wof:placetype":"venue"
},
  "geometry": {"coordinates":[1.0259959698,51.3620643616],"type":"Point"}
}