{
  "type": "Feature",
  "properties": {
    "addr:full":"Manor House, High Street Dronfield Derbyshire S18 1PY",
    "addr:postcode":"s18 1py",
    "addr:street":"Manor;High Street",
    "iso:country":"GB",
    "sg:address":"Manor House, High Street",
    "sg:city":"Dronfield",
    "sg:classifiers":[
        {
            "category":"Education",
            "subcategory":"Library",
            "type":"Public Place"
        }
    ],
    "sg:phone":"+44 1246 414001",
    "sg:postcode":"S18 1PY",
    "sg:province":"Derbyshire",
    "sg:tags":[
        "book"
    ],
    "wof:name":"Dronfield Library",
    "wof:placetype":"venue"
},
  "geometry": {"coordinates":[-1.4740550518,53.3022499084],"type":"Point"}
}