{
  "type": "Feature",
  "properties": {
    "addr:full":"Earle Road Medical Centre, 131 Earle Rd Liverpool Merseyside L7 6HD",
    "addr:housenumber":"131",
    "addr:postcode":"l7 6hd",
    "addr:street":"Earle;Earle Rd",
    "iso:country":"GB",
    "sg:address":"Earle Road Medical Centre, 131 Earle Rd",
    "sg:city":"Liverpool",
    "sg:classifiers":[
        {
            "category":"Health Services",
            "subcategory":"Doctor",
            "type":"Services"
        }
    ],
    "sg:phone":"+44 151 733 7172",
    "sg:postcode":"L7 6HD",
    "sg:province":"Merseyside",
    "sg:tags":[
        "practitioners"
    ],
    "wof:name":"Blakeborough, J L",
    "wof:placetype":"venue"
},
  "geometry": {"coordinates":[-2.94254,53.398701],"type":"Point"}
}