{
  "type": "Feature",
  "properties": {
    "addr:full":"60 Craigiehall Street Glasgow Glasgow City G51 1EU",
    "addr:housenumber":"60",
    "addr:postcode":"g51 1eu",
    "addr:street":"Craigiehall Street",
    "iso:country":"GB",
    "sg:address":"60 Craigiehall Street",
    "sg:city":"Glasgow",
    "sg:classifiers":[
        {
            "category":"Place Of Worship",
            "type":"Public Place"
        }
    ],
    "sg:phone":"+44 141 427 1878",
    "sg:postcode":"G51 1EU",
    "sg:province":"Glasgow City",
    "wof:name":"Harper Memorial Baptist Church",
    "wof:placetype":"venue"
},
  "geometry": {"coordinates":[-4.2855038643,55.8544502258],"type":"Point"}
}