{
  "type": "Feature",
  "properties": {
    "addr:full":"6 New Dock Road Llanelli Carmarthenshire SA15 2EL",
    "addr:housenumber":"6",
    "addr:postcode":"sa15 2el",
    "addr:street":"New Dock Road",
    "iso:country":"GB",
    "sg:address":"6 New Dock Road",
    "sg:city":"Llanelli",
    "sg:classifiers":[
        {
            "category":"Home & Garden",
            "subcategory":"Hardware",
            "type":"Retail Goods"
        }
    ],
    "sg:phone":"+44 1554 774005",
    "sg:postcode":"SA15 2EL",
    "sg:province":"Carmarthenshire",
    "sg:tags":[
        "merchant",
        "ironmonger"
    ],
    "wof:name":"J Romero",
    "wof:placetype":"venue"
},
  "geometry": {"coordinates":[-4.1589832306,51.6727104187],"type":"Point"}
}