{
  "type": "Feature",
  "properties": {
    "iso:country":"GB",
    "sg:address":"Beehive Works, Louth Road, Wragby",
    "sg:city":"Market Rasen",
    "sg:classifiers":[
        {
            "category":"Sports & Exercise",
            "subcategory":"Swimming Pool",
            "type":"Entertainment"
        }
    ],
    "sg:postcode":"LN8 5LA",
    "sg:province":"Lincolnshire",
    "sg:tags":[
        "bee"
    ],
    "wof:name":"E H Thorne (Beehives) Ltd.",
    "wof:placetype":"venue"
},
  "geometry": {"coordinates":[-0.301939,53.287292],"type":"Point"}
}