{
  "type": "Feature",
  "properties": {
    "addr:full":"300 Thornton Road, Thornton Bradford West Yorkshire BD13 3AB",
    "addr:housenumber":"300",
    "addr:postcode":"bd13 3ab",
    "addr:street":"Thornton Road",
    "iso:country":"GB",
    "sg:address":"300 Thornton Road, Thornton",
    "sg:city":"Bradford",
    "sg:classifiers":[
        {
            "category":"Place Of Worship",
            "type":"Public Place"
        }
    ],
    "sg:phone":"+44 1274 833200",
    "sg:postcode":"BD13 3AB",
    "sg:province":"West Yorkshire",
    "wof:name":"St. James Church",
    "wof:placetype":"venue"
},
  "geometry": {"coordinates":[-1.841386,53.790802],"type":"Point"}
}