{
  "type": "Feature",
  "properties": {
    "addr:full":"Manchester Road, Higher Ince Wigan Lancashire WN2 2DJ",
    "addr:postcode":"wn2 2dj",
    "addr:street":"Manchester Road",
    "iso:country":"GB",
    "sg:address":"Manchester Road, Higher Ince",
    "sg:city":"Wigan",
    "sg:classifiers":[
        {
            "category":"Health Services",
            "subcategory":"Clinic",
            "type":"Services"
        }
    ],
    "sg:phone":"+44 1942 493094",
    "sg:postcode":"WN2 2DJ",
    "sg:province":"Lancashire",
    "sg:tags":[
        "private"
    ],
    "wof:name":"Wigan & Leigh Health Services NHS Trust",
    "wof:placetype":"venue"
},
  "geometry": {"coordinates":[-2.608454,53.544785],"type":"Point"}
}