{
  "type": "Feature",
  "properties": {
    "iso:country":"GB",
    "sg:address":"45-49 Bank Hey Street",
    "sg:city":"Blackpool",
    "sg:classifiers":[
        {
            "category":"Shopping",
            "subcategory":"Tobacco",
            "type":"Retail Goods"
        }
    ],
    "sg:phone":"+44 1253 752453",
    "sg:postcode":"FY1 4RY",
    "sg:province":"Lancashire",
    "sg:tags":[
        "tobacconist"
    ],
    "wof:name":"Smokers Choice",
    "wof:placetype":"venue"
},
  "geometry": {"coordinates":[-3.054512,53.816063],"type":"Point"}
}