{
  "type": "Feature",
  "properties": {
    "iso:country":"GB",
    "sg:address":"Old School, Forest Road, Hartwell",
    "sg:city":"Northampton",
    "sg:classifiers":[
        {
            "category":"Retail",
            "subcategory":"Auto Repair",
            "type":"Services"
        }
    ],
    "sg:phone":"+44 800 026 2086",
    "sg:postcode":"NN7 2HE",
    "sg:province":"Buckinghamshire",
    "sg:tags":[
        "modification",
        "garage"
    ],
    "wof:name":"Hartwell Vehicle Repair Centre",
    "wof:placetype":"venue"
},
  "geometry": {"coordinates":[-0.85409,52.145782],"type":"Point"}
}