{
  "type": "Feature",
  "properties": {
    "iso:country":"GB",
    "sg:address":"51a George Street",
    "sg:city":"Richmond",
    "sg:classifiers":[
        {
            "category":"Real Estate",
            "subcategory":"Architect",
            "type":"Services"
        }
    ],
    "sg:phone":"+44 20 8740 1070",
    "sg:postcode":"TW9 1HJ",
    "sg:province":"Greater London",
    "sg:tags":[
        "architectural"
    ],
    "wof:name":"TUGMAN",
    "wof:placetype":"venue"
},
  "geometry": {"coordinates":[-0.304248,51.461002],"type":"Point"}
}