{
  "type": "Feature",
  "properties": {
    "addr:full":"2 Victoria Road Plymouth Devon PL5 1RQ",
    "addr:housenumber":"2",
    "addr:postcode":"pl5 1rq",
    "addr:street":"Victoria Road",
    "iso:country":"GB",
    "sg:address":"2 Victoria Road",
    "sg:city":"Plymouth",
    "sg:classifiers":[
        {
            "category":"Shopping",
            "subcategory":"Clothing, Apparel, & Fashions",
            "type":"Retail Goods"
        },
        {
            "category":"Manufacturing",
            "subcategory":"Paper Products",
            "type":"Manufacturing & Wholesale Goods"
        }
    ],
    "sg:phone":"+44 1752 365765",
    "sg:postcode":"PL5 1RQ",
    "sg:province":"Devon",
    "sg:tags":[
        "shop"
    ],
    "wof:name":"Be-Wise Ltd.",
    "wof:placetype":"venue"
},
  "geometry": {"coordinates":[-4.1818790436,50.4089012146],"type":"Point"}
}