{
  "type": "Feature",
  "properties": {
    "addr:full":"15 Burnt Oak Bdwy Edgware Greater London HA8 5LD",
    "addr:housenumber":"15",
    "addr:postcode":"ha8 5ld",
    "addr:street":"Burnt Oak Bdwy",
    "iso:country":"GB",
    "sg:address":"15 Burnt Oak Bdwy",
    "sg:city":"Edgware",
    "sg:classifiers":[
        {
            "category":"Personal",
            "subcategory":"Beauty Salon",
            "type":"Services"
        },
        {
            "category":"Personal",
            "subcategory":"Barber",
            "type":"Services"
        }
    ],
    "sg:phone":"+44 20 8205 8578",
    "sg:postcode":"HA8 5LD",
    "sg:province":"Greater London",
    "sg:tags":[
        "unisex",
        "hairdresser"
    ],
    "wof:name":"New Image",
    "wof:placetype":"venue"
},
  "geometry": {"coordinates":[-0.2652820051,51.598487854],"type":"Point"}
}