{
  "type": "Feature",
  "properties": {
    "addr:full":"82 Larch Hill Crescent Bradford West Yorkshire BD6 1DS",
    "addr:housenumber":"82",
    "addr:postcode":"bd6 1ds",
    "addr:street":"Larch Hill Crescent",
    "iso:country":"GB",
    "sg:address":"82 Larch Hill Crescent",
    "sg:city":"Bradford",
    "sg:classifiers":[
        {
            "category":"Personal",
            "subcategory":"Beauty Salon",
            "type":"Services"
        }
    ],
    "sg:phone":"+44 1274 691474",
    "sg:postcode":"BD6 1DS",
    "sg:province":"West Yorkshire",
    "sg:tags":[
        "unisex",
        "hairdresser"
    ],
    "wof:name":"L A Hair",
    "wof:placetype":"venue"
},
  "geometry": {"coordinates":[-1.765633,53.762508],"type":"Point"}
}