{
  "type": "Feature",
  "properties": {
    "addr:full":"Gabriels Wharf, Water La Exeter Devon EX2 8BZ",
    "addr:postcode":"ex2 8bz",
    "addr:street":"Gabriels;Water La Exeter",
    "iso:country":"GB",
    "sg:address":"Gabriels Wharf, Water La",
    "sg:city":"Exeter",
    "sg:classifiers":[
        {
            "category":"Manufacturing",
            "subcategory":"Building Materials",
            "type":"Manufacturing & Wholesale Goods"
        }
    ],
    "sg:phone":"+44 1392 207201",
    "sg:postcode":"EX2 8BZ",
    "sg:province":"Devon",
    "sg:tags":[
        "tarmac",
        "asphalt"
    ],
    "wof:name":"Colcon Ltd",
    "wof:placetype":"venue"
},
  "geometry": {"coordinates":[-3.5267140865,50.7117424011],"type":"Point"}
}