{
  "type": "Feature",
  "properties": {
    "addr:full":"Oxford House, Oxford Rd Llandudno Conwy LL30 1DH",
    "addr:postcode":"ll30 1dh",
    "addr:street":"Oxford Rd",
    "iso:country":"GB",
    "sg:address":"Oxford House, Oxford Rd",
    "sg:city":"Llandudno",
    "sg:classifiers":[
        {
            "category":"Professional",
            "subcategory":"Business Services",
            "type":"Services"
        }
    ],
    "sg:phone":"+44 1492 874424",
    "sg:postcode":"LL30 1DH",
    "sg:province":"Conwy",
    "sg:tags":[
        "tile",
        "stockist"
    ],
    "wof:name":"Tile Trend",
    "wof:placetype":"venue"
},
  "geometry": {"coordinates":[-3.826284,53.320679],"type":"Point"}
}