{
  "type": "Feature",
  "properties": {
    "iso:country":"GB",
    "sg:address":"25 Vanston Place",
    "sg:city":"London",
    "sg:classifiers":[
        {
            "category":"Organizations",
            "subcategory":"Membership Organization",
            "type":"Services"
        }
    ],
    "sg:postcode":"SW6 1AZ",
    "sg:province":"Greater London",
    "sg:tags":[
        "club"
    ],
    "wof:name":"Club Bon Viveur Ltd.",
    "wof:placetype":"venue"
},
  "geometry": {"coordinates":[-0.197892,51.480953],"type":"Point"}
}