{
  "type": "Feature",
  "properties": {
    "iso:country":"GB",
    "sg:address":"Freeman Rd",
    "sg:city":"Lincoln",
    "sg:classifiers":[
        {
            "category":"Military Area",
            "subcategory":"Air Force Base",
            "type":"Public Place"
        }
    ],
    "sg:postcode":"LN6 8JX",
    "sg:province":"Lincolnshire",
    "sg:tags":[
        "taxi",
        "hire",
        "private"
    ],
    "wof:name":"Aston,Harold,",
    "wof:placetype":"venue"
},
  "geometry": {"coordinates":[-0.5973560214,53.1939048767],"type":"Point"}
}