{
  "type": "Feature",
  "properties": {
    "iso:country":"GB",
    "sg:address":"Colliton Park",
    "sg:city":"Dorchester",
    "sg:classifiers":[
        {
            "category":"Government",
            "subcategory":"Fire Station",
            "type":"Public Place"
        }
    ],
    "sg:phone":"+44 1305 251133",
    "sg:postcode":"DT1 1FB",
    "sg:province":"Dorset",
    "wof:name":"Dorset Fire Authority",
    "wof:placetype":"venue"
},
  "geometry": {"coordinates":[-2.441564,50.711906],"type":"Point"}
}