{
  "type": "Feature",
  "properties": {
    "iso:country":"GB",
    "sg:address":"Milestones",
    "sg:city":"Shaftesbury",
    "sg:classifiers":[
        {
            "category":"Education",
            "subcategory":"Library",
            "type":"Public Place"
        }
    ],
    "sg:phone":"+44 1747 811360",
    "sg:postcode":"SP7 0NL",
    "sg:province":"Dorset",
    "sg:tags":[
        "reproduction",
        "furniture"
    ],
    "wof:name":"R A Smith",
    "wof:placetype":"venue"
},
  "geometry": {"coordinates":[-2.1899290085,50.9792404175],"type":"Point"}
}