{
  "type": "Feature",
  "properties": {
    "iso:country":"GB",
    "sg:address":"9 The Triangle, Brackla",
    "sg:city":"Bridgend",
    "sg:classifiers":[
        {
            "category":"Shopping",
            "subcategory":"Pharmacy",
            "type":"Retail Goods"
        }
    ],
    "sg:postcode":"CF31 2LL",
    "sg:province":"Bridgend",
    "sg:tags":[
        "pharmacist",
        "chemist"
    ],
    "wof:name":"Brackla Pharmacy",
    "wof:placetype":"venue"
},
  "geometry": {"coordinates":[-3.5517749786,51.5041236877],"type":"Point"}
}