{
  "type": "Feature",
  "properties": {
    "iso:country":"GB",
    "sg:address":"44 Bickford Road, Aston",
    "sg:city":"Birmingham",
    "sg:classifiers":[
        {
            "category":"Manufacturing",
            "subcategory":"Rubber & Plastics",
            "type":"Manufacturing & Wholesale Goods"
        }
    ],
    "sg:phone":"+44 121 327 5736",
    "sg:postcode":"B6 7EE",
    "sg:province":"West Midlands",
    "sg:tags":[
        "injection",
        "moulding"
    ],
    "wof:name":"Pobs Precision",
    "wof:placetype":"venue"
},
  "geometry": {"coordinates":[-1.8756560087,52.5108985901],"type":"Point"}
}