{
  "type": "Feature",
  "properties": {
    "iso:country":"GB",
    "sg:address":"63-65 London Road South",
    "sg:city":"Lowestoft",
    "sg:classifiers":[
        {
            "category":"Community Center",
            "type":"Public Place"
        }
    ],
    "sg:phone":"+44 1502 585252",
    "sg:postcode":"NR33 0AS",
    "sg:province":"Suffolk",
    "sg:tags":[
        "centre",
        "entertainment"
    ],
    "wof:name":"Kenny Cantor Productions Ltd.",
    "wof:placetype":"venue"
},
  "geometry": {"coordinates":[1.74747,52.470913],"type":"Point"}
}