{
  "type": "Feature",
  "properties": {
    "iso:country":"GB",
    "sg:address":"Beddgelert Road",
    "sg:city":"Caernarfon",
    "sg:classifiers":[
        {
            "category":"Museum",
            "subcategory":"Art Museum",
            "type":"Entertainment"
        }
    ],
    "sg:phone":"+44 1286 675625",
    "sg:postcode":"LL55 2LN",
    "sg:province":"Gwynedd",
    "sg:tags":[
        "gallery"
    ],
    "wof:name":"Segontium Roman Fort Museum",
    "wof:placetype":"venue"
},
  "geometry": {"coordinates":[-4.271809,53.142593],"type":"Point"}
}