{
  "type": "Feature",
  "properties": {
    "addr:full":"Weydale Hotel, 14 Weydale Avenue Scarborough North Yorkshire YO12 6BA",
    "addr:housenumber":"14",
    "addr:postcode":"yo12 6ba",
    "addr:street":"Weydale Avenue",
    "iso:country":"GB",
    "sg:address":"Weydale Hotel, 14 Weydale Avenue",
    "sg:city":"Scarborough",
    "sg:classifiers":[
        {
            "category":"Travel",
            "subcategory":"Hotels & Motels",
            "type":"Entertainment"
        }
    ],
    "sg:phone":"+44 1723 373393",
    "sg:postcode":"YO12 6BA",
    "sg:province":"North Yorkshire",
    "wof:name":"Weydale Hotel",
    "wof:placetype":"venue"
},
  "geometry": {"coordinates":[-0.42753,54.280506],"type":"Point"}
}