{
  "type": "Feature",
  "properties": {
    "iso:country":"GB",
    "sg:address":"124 Main Street, Bulwell",
    "sg:city":"Nottingham",
    "sg:classifiers":[
        {
            "category":"Farming",
            "subcategory":"Livestock Farm",
            "type":"Manufacturing & Wholesale Goods"
        }
    ],
    "sg:phone":"+44 115 927 8062",
    "sg:postcode":"NG6 8ET",
    "sg:province":"Nottinghamshire",
    "sg:tags":[
        "breeder"
    ],
    "wof:name":"W French & Sons Florists",
    "wof:placetype":"venue"
},
  "geometry": {"coordinates":[-1.1952610016,53.0033187866],"type":"Point"}
}