{
  "type": "Feature",
  "properties": {
    "addr:full":"16 Warwick Avenue New Milton Hampshire BH25 6AH",
    "addr:housenumber":"16",
    "addr:postcode":"bh25 6ah",
    "addr:street":"Warwick Avenue",
    "iso:country":"GB",
    "sg:address":"16 Warwick Avenue",
    "sg:city":"New Milton",
    "sg:classifiers":[
        {
            "category":"Building & Trades",
            "subcategory":"Construction",
            "type":"Services"
        }
    ],
    "sg:postcode":"BH25 6AH",
    "sg:province":"Hampshire",
    "sg:tags":[
        "builder"
    ],
    "wof:name":"Allied Hants & Dorset Builders",
    "wof:placetype":"venue"
},
  "geometry": {"coordinates":[-1.647585,50.755585],"type":"Point"}
}