{
  "type": "Feature",
  "properties": {
    "addr:full":"15 Bentinck Mews London Greater London W1U 2AL",
    "addr:housenumber":"15",
    "addr:postcode":"w1u 2al",
    "addr:street":"Bentinck Mews",
    "iso:country":"GB",
    "sg:address":"15 Bentinck Mews",
    "sg:city":"London",
    "sg:classifiers":[
        {
            "category":"Manufacturing",
            "subcategory":"Apparel",
            "type":"Manufacturing & Wholesale Goods"
        }
    ],
    "sg:phone":"+44 20 7486 6691",
    "sg:postcode":"W1U 2AL",
    "sg:province":"Greater London",
    "sg:tags":[
        "garment",
        "designer"
    ],
    "wof:name":"Zilkha Ronit",
    "wof:placetype":"venue"
},
  "geometry": {"coordinates":[-0.1506610066,51.5174865723],"type":"Point"}
}