{
  "type": "Feature",
  "properties": {
    "addr:full":"Unit 5 Gerston Indust Est, Greyfriars La Pulborough West Sussex RH20 4HE",
    "addr:housenumber":"unit 5",
    "addr:postcode":"rh20 4he",
    "addr:street":"Indust;Greyfriars",
    "iso:country":"GB",
    "sg:address":"Unit 5 Gerston Indust Est, Greyfriars La",
    "sg:city":"Pulborough",
    "sg:classifiers":[
        {
            "category":"Retail",
            "subcategory":"Auto Repair",
            "type":"Services"
        }
    ],
    "sg:phone":"+44 1903 741333",
    "sg:postcode":"RH20 4HE",
    "sg:province":"West Sussex",
    "sg:tags":[
        "body",
        "car"
    ],
    "wof:name":"Carline",
    "wof:placetype":"venue"
},
  "geometry": {"coordinates":[-0.5118790269,50.9570770264],"type":"Point"}
}