{
  "type": "Feature",
  "properties": {
    "iso:country":"GB",
    "sg:address":"1 Saint Pauls Road, Clifton",
    "sg:city":"Bristol",
    "sg:classifiers":[
        {
            "category":"Professional",
            "subcategory":"Management & Consulting",
            "type":"Services"
        }
    ],
    "sg:postcode":"BS8 1LZ",
    "sg:province":"City of Bristol",
    "sg:tags":[
        "consultant",
        "business"
    ],
    "wof:name":"Woolf Consultancy Services Ltd",
    "wof:placetype":"venue"
},
  "geometry": {"coordinates":[-2.6091589928,51.4595069885],"type":"Point"}
}