{
  "type": "Feature",
  "properties": {
    "iso:country":"GB",
    "sg:address":"Old Mill La Indstl Est",
    "sg:city":"Mansfield",
    "sg:classifiers":[
        {
            "category":"Retail",
            "subcategory":"Auto Repair",
            "type":"Services"
        }
    ],
    "sg:postcode":"NG19 9GB",
    "sg:province":"Derbyshire",
    "sg:tags":[
        "modification",
        "garage"
    ],
    "wof:name":"Wood,Geoff,",
    "wof:placetype":"venue"
},
  "geometry": {"coordinates":[-1.188625,53.158104],"type":"Point"}
}