{
  "type": "Feature",
  "properties": {
    "addr:full":"P O Box 1196 Cheddar Somerset BS27 3ES",
    "addr:housenumber":"p o;1196",
    "addr:postcode":"bs27 3es",
    "addr:street":"Cheddar",
    "iso:country":"GB",
    "sg:address":"P O Box 1196",
    "sg:city":"Cheddar",
    "sg:classifiers":[
        {
            "category":"Professional",
            "subcategory":"Business Services",
            "type":"Services"
        }
    ],
    "sg:phone":"+44 1934 741102",
    "sg:postcode":"BS27 3ES",
    "sg:province":"Somerset",
    "sg:tags":[
        "trade"
    ],
    "wof:name":"Customer Network Services Ltd.",
    "wof:placetype":"venue"
},
  "geometry": {"coordinates":[-2.7736589909,51.2720298767],"type":"Point"}
}