{
  "type": "Feature",
  "properties": {
    "addr:full":"Generation Centre, Dane St Rochdale Lancashire OL12 6XB",
    "addr:postcode":"ol12 6xb",
    "addr:street":"Dane St",
    "iso:country":"GB",
    "sg:address":"Generation Centre, Dane St",
    "sg:city":"Rochdale",
    "sg:classifiers":[
        {
            "category":"Banks & Credit Unions",
            "subcategory":"Bank",
            "type":"Services"
        }
    ],
    "sg:phone":"+44 1706 710891",
    "sg:postcode":"OL12 6XB",
    "sg:province":"Lancashire",
    "sg:tags":[
        "broker",
        "mortgage"
    ],
    "wof:name":"Advance Personal Finance",
    "wof:placetype":"venue"
},
  "geometry": {"coordinates":[-2.1627659798,53.6190071106],"type":"Point"}
}