{
  "type": "Feature",
  "properties": {
    "addr:full":"47 Polwarth Drive Newcastle-upon-tyne Tyne and Wear NE3 5NJ",
    "addr:housenumber":"47",
    "addr:postcode":"ne3 5nj",
    "addr:street":"Polwarth Drive",
    "iso:country":"GB",
    "sg:address":"47 Polwarth Drive",
    "sg:city":"Newcastle-upon-tyne",
    "sg:classifiers":[
        {
            "category":"Organizations",
            "subcategory":"Non-profit Organization",
            "type":"Services"
        }
    ],
    "sg:postcode":"NE3 5NJ",
    "sg:province":"Tyne and Wear",
    "sg:tags":[
        "organisation",
        "voluntary",
        "charity"
    ],
    "wof:name":"Adventure Holidays",
    "wof:placetype":"venue"
},
  "geometry": {"coordinates":[-1.626629,55.026077],"type":"Point"}
}