{
  "type": "Feature",
  "properties": {
    "iso:country":"GB",
    "sg:address":"1 Dee Court Arcade, Dee Lane, West Kirby",
    "sg:city":"Wirral",
    "sg:classifiers":[
        {
            "category":"Shopping",
            "subcategory":"Clothing, Apparel, & Fashions",
            "type":"Retail Goods"
        }
    ],
    "sg:postcode":"CH48 0QH",
    "sg:province":"Merseyside",
    "sg:tags":[
        "shop"
    ],
    "wof:name":"Fashion Care",
    "wof:placetype":"venue"
},
  "geometry": {"coordinates":[-3.184314,53.372936],"type":"Point"}
}