{
  "type": "Feature",
  "properties": {
    "iso:country":"GB",
    "sg:address":"Oak Lodge, Stoneacre Dr, Sutton La",
    "sg:city":"Chorley",
    "sg:classifiers":[
        {
            "category":"Building & Trades",
            "subcategory":"Construction",
            "type":"Services"
        }
    ],
    "sg:phone":"+44 1257 482409",
    "sg:postcode":"PR6 9SP",
    "sg:province":"Lancashire",
    "sg:tags":[
        "supplier",
        "installers",
        "cladding"
    ],
    "wof:name":"G & S Design And Build",
    "wof:placetype":"venue"
},
  "geometry": {"coordinates":[-2.60005,53.622162],"type":"Point"}
}