{
  "type": "Feature",
  "properties": {
    "addr:full":"4 High Town, Hay-on-wye Hereford Herefordshire HR3 5AE",
    "addr:housenumber":"4",
    "addr:postcode":"hr3 5ae",
    "addr:street":"High Town Hay-On-Wye",
    "iso:country":"GB",
    "sg:address":"4 High Town, Hay-on-wye",
    "sg:city":"Hereford",
    "sg:classifiers":[
        {
            "category":"Professional",
            "subcategory":"Art Services",
            "type":"Services"
        }
    ],
    "sg:phone":"+44 1497 821744",
    "sg:postcode":"HR3 5AE",
    "sg:province":"Herefordshire",
    "sg:tags":[
        "photographer"
    ],
    "wof:name":"Studio Mcmahon",
    "wof:placetype":"venue"
},
  "geometry": {"coordinates":[-3.125142,52.074577],"type":"Point"}
}