{
  "type": "Feature",
  "properties": {
    "iso:country":"GB",
    "sg:address":"Cavendish Rd",
    "sg:city":"Wimbledon",
    "sg:classifiers":[
        {
            "category":"Community Center",
            "type":"Public Place"
        }
    ],
    "sg:phone":"+44 20 8542 1458",
    "sg:postcode":"SW19 2EZ",
    "sg:province":"Greater London",
    "sg:tags":[
        "nursery",
        "centre"
    ],
    "wof:name":"Colliers Wood Recreation Ground",
    "wof:placetype":"venue"
},
  "geometry": {"coordinates":[-0.176839,51.418903],"type":"Point"}
}