{
  "type": "Feature",
  "properties": {
    "iso:country":"GB",
    "sg:address":"Ballinluig",
    "sg:city":"Pitlochry",
    "sg:classifiers":[
        {
            "category":"Autos & Motor Vehicles",
            "subcategory":"Fuel & Gas Station",
            "type":"Retail Goods"
        }
    ],
    "sg:phone":"+44 1796 482212",
    "sg:postcode":"PH9 0LG",
    "sg:province":"Perth and Kinross",
    "sg:tags":[
        "petrol",
        "filling"
    ],
    "wof:name":"Ballinluig Services",
    "wof:placetype":"venue"
},
  "geometry": {"coordinates":[-3.6697070599,56.6565742493],"type":"Point"}
}