{
  "type": "Feature",
  "properties": {
    "iso:country":"GB",
    "sg:address":"195 Wandsworth Bridge Road, Fulham",
    "sg:city":"London",
    "sg:classifiers":[
        {
            "category":"Communications",
            "type":"Services"
        }
    ],
    "sg:postcode":"SW6 2TT",
    "sg:province":"Greater London",
    "sg:tags":[
        "telecommunication"
    ],
    "wof:name":"Zootie Ventures Ltd",
    "wof:placetype":"venue"
},
  "geometry": {"coordinates":[-0.19099,51.470757],"type":"Point"}
}