{
  "type": "Feature",
  "properties": {
    "iso:country":"GB",
    "sg:address":"Comberford Rd",
    "sg:city":"Tamworth",
    "sg:classifiers":[
        {
            "category":"Place Of Worship",
            "type":"Public Place"
        }
    ],
    "sg:phone":"+44 1827 60789",
    "sg:postcode":"B79 9AA",
    "sg:province":"Staffordshire",
    "wof:name":"The Coton Centre",
    "wof:placetype":"venue"
},
  "geometry": {"coordinates":[-1.692707,52.657372],"type":"Point"}
}