{
  "type": "Feature",
  "properties": {
    "iso:country":"GB",
    "sg:address":"3 Race Hill",
    "sg:city":"Launceston",
    "sg:classifiers":[
        {
            "category":"Manufacturing",
            "subcategory":"Tools & Machinery",
            "type":"Manufacturing & Wholesale Goods"
        },
        {
            "category":"Insurance",
            "subcategory":"Insurance Agent",
            "type":"Services"
        }
    ],
    "sg:phone":"+44 1566 772282",
    "sg:postcode":"PL15 9BA",
    "sg:province":"Cornwall",
    "sg:tags":[
        "society",
        "friendly"
    ],
    "wof:name":"Cornwall & Devon Insurance Services",
    "wof:placetype":"venue"
},
  "geometry": {"coordinates":[-4.3579788208,50.6352996826],"type":"Point"}
}