{
  "type": "Feature",
  "properties": {
    "addr:full":"35 Beauchamp Ave Birmingham West Midlands B20 1DR",
    "addr:housenumber":"35",
    "addr:postcode":"b20 1dr",
    "addr:street":"Beauchamp Ave",
    "iso:country":"GB",
    "sg:address":"35 Beauchamp Ave",
    "sg:city":"Birmingham",
    "sg:classifiers":[
        {
            "category":"Building & Trades",
            "subcategory":"Construction",
            "type":"Services"
        }
    ],
    "sg:postcode":"B20 1DR",
    "sg:province":"West Midlands",
    "sg:tags":[
        "builder"
    ],
    "wof:name":"Kumar,Paramjit,",
    "wof:placetype":"venue"
},
  "geometry": {"coordinates":[-1.930729,52.526924],"type":"Point"}
}