{
  "type": "Feature",
  "properties": {
    "iso:country":"GB",
    "sg:address":"211 Kings Hall Road",
    "sg:city":"Beckenham",
    "sg:classifiers":[
        {
            "category":"Professional",
            "subcategory":"Art Services",
            "type":"Services"
        }
    ],
    "sg:postcode":"BR3 1LL",
    "sg:province":"Kent",
    "sg:tags":[
        "graphic",
        "designer"
    ],
    "wof:name":"Robert Claxton",
    "wof:placetype":"venue"
},
  "geometry": {"coordinates":[-0.0369209982,51.4157142639],"type":"Point"}
}