{
  "type": "Feature",
  "properties": {
    "addr:full":"Unit C, 301b The Arcadian, Hurst Street Birmingham West Midlands B5 4TD",
    "addr:housenumber":"unit c 301b",
    "addr:postcode":"b5 4td",
    "addr:street":"The Arcadian Hurst Street",
    "iso:country":"GB",
    "sg:address":"Unit C, 301b The Arcadian, Hurst Street",
    "sg:city":"Birmingham",
    "sg:classifiers":[
        {
            "category":"Community Center",
            "type":"Public Place"
        }
    ],
    "sg:phone":"+44 121 693 3600",
    "sg:postcode":"B5 4TD",
    "sg:province":"West Midlands",
    "sg:tags":[
        "centre",
        "entertainment"
    ],
    "wof:name":"Comic Enterprises Ltd.",
    "wof:placetype":"venue"
},
  "geometry": {"coordinates":[-1.89674,52.473999],"type":"Point"}
}