{
  "type": "Feature",
  "properties": {
    "addr:full":"48 Greetham Street, Cottesmore Oakham Leicestershire LE15 7DB",
    "addr:housenumber":"48",
    "addr:postcode":"le15 7db",
    "addr:street":"Greetham Street",
    "iso:country":"GB",
    "sg:address":"48 Greetham Street, Cottesmore",
    "sg:city":"Oakham",
    "sg:classifiers":[
        {
            "category":"Building & Trades",
            "subcategory":"Construction",
            "type":"Services"
        }
    ],
    "sg:phone":"+44 1572 813584",
    "sg:postcode":"LE15 7DB",
    "sg:province":"Leicestershire",
    "sg:tags":[
        "builder"
    ],
    "wof:name":"C A Pilgrim",
    "wof:placetype":"venue"
},
  "geometry": {"coordinates":[-0.6566680074,52.7138938904],"type":"Point"}
}