{
  "type": "Feature",
  "properties": {
    "iso:country":"GB",
    "sg:address":"69 Lostock Gardens",
    "sg:city":"Blackpool",
    "sg:classifiers":[
        {
            "category":"Retail",
            "subcategory":"Driving School",
            "type":"Services"
        }
    ],
    "sg:phone":"+44 1253 310141",
    "sg:postcode":"FY4 3PP",
    "sg:province":"Lancashire",
    "wof:name":"Studio School of Motoring",
    "wof:placetype":"venue"
},
  "geometry": {"coordinates":[-3.031704,53.786201],"type":"Point"}
}