{
  "type": "Feature",
  "properties": {
    "addr:full":"Crown Centre, Crown Square Matlock Derbyshire DE4 3AT",
    "addr:postcode":"de4 3at",
    "addr:street":"Crown Square",
    "iso:country":"GB",
    "sg:address":"Crown Centre, Crown Square",
    "sg:city":"Matlock",
    "sg:classifiers":[
        {
            "category":"Real Estate",
            "subcategory":"Surveying",
            "type":"Services"
        }
    ],
    "sg:phone":"+44 1629 55383",
    "sg:postcode":"DE4 3AT",
    "sg:province":"Derbyshire",
    "sg:tags":[
        "surveyor",
        "valuer"
    ],
    "wof:name":"Colleys Professional Services",
    "wof:placetype":"venue"
},
  "geometry": {"coordinates":[-1.5482740402,53.1356163025],"type":"Point"}
}