{
  "type": "Feature",
  "properties": {
    "iso:country":"GB",
    "sg:address":"49 Aldenham Rd, Bushey",
    "sg:city":"Watford",
    "sg:classifiers":[
        {
            "category":"Communications",
            "subcategory":"Film & Video Production",
            "type":"Services"
        }
    ],
    "sg:phone":"+44 1923 232181",
    "sg:postcode":"WD2 2NB",
    "sg:province":"Hertfordshire",
    "sg:tags":[
        "illustrator",
        "artist"
    ],
    "wof:name":"Paige Associates",
    "wof:placetype":"venue"
},
  "geometry": {"coordinates":[-0.36307,51.644341],"type":"Point"}
}