{
  "type": "Feature",
  "properties": {
    "addr:full":"26-28 West Row Stockton-on-tees Durham TS18 1BN",
    "addr:housenumber":"26-28",
    "addr:postcode":"ts18 1bn",
    "addr:street":"West Row",
    "iso:country":"GB",
    "sg:address":"26-28 West Row",
    "sg:city":"Stockton-on-tees",
    "sg:classifiers":[
        {
            "category":"Wholesale",
            "subcategory":"Construction Materials",
            "type":"Manufacturing & Wholesale Goods"
        }
    ],
    "sg:phone":"+44 1642 676480",
    "sg:postcode":"TS18 1BN",
    "sg:province":"Durham",
    "sg:tags":[
        "merchant",
        "glass"
    ],
    "wof:name":"H Dobson (Glass Merchants) Ltd.",
    "wof:placetype":"venue"
},
  "geometry": {"coordinates":[-1.3147549629,54.5627098083],"type":"Point"}
}