{
  "type": "Feature",
  "properties": {
    "iso:country":"GB",
    "sg:address":"1 Arden Rd",
    "sg:city":"Finchley Central",
    "sg:classifiers":[
        {
            "category":"Health Services",
            "subcategory":"Dentist",
            "type":"Services"
        }
    ],
    "sg:phone":"+44 20 8349 2209",
    "sg:postcode":"N3 3AB",
    "sg:province":"Greater London",
    "wof:name":"Henry Arnold BDS",
    "wof:placetype":"venue"
},
  "geometry": {"coordinates":[-0.199606,51.593708],"type":"Point"}
}