{
  "type": "Feature",
  "properties": {
    "addr:full":"44 Springbank Road Cheltenham Gloucestershire GL51 0NH",
    "addr:housenumber":"44",
    "addr:postcode":"gl51 0nh",
    "addr:street":"Springbank Road",
    "iso:country":"GB",
    "sg:address":"44 Springbank Road",
    "sg:city":"Cheltenham",
    "sg:classifiers":[
        {
            "category":"Professional",
            "subcategory":"Engineering",
            "type":"Services"
        },
        {
            "category":"Building & Trades",
            "subcategory":"Electrical",
            "type":"Services"
        }
    ],
    "sg:phone":"+44 1242 237251",
    "sg:postcode":"GL51 0NH",
    "sg:province":"Gloucestershire",
    "sg:tags":[
        "engineer",
        "electrician",
        "contractor"
    ],
    "wof:name":"D A Tombs Electrical Contractors",
    "wof:placetype":"venue"
},
  "geometry": {"coordinates":[-2.1231689453,51.9092750549],"type":"Point"}
}