{
  "type": "Feature",
  "properties": {
    "addr:full":"245 High Street Aldershot Hampshire GU12 4NG",
    "addr:housenumber":"245",
    "addr:postcode":"gu12 4ng",
    "addr:street":"High Street",
    "iso:country":"GB",
    "sg:address":"245 High Street",
    "sg:city":"Aldershot",
    "sg:classifiers":[
        {
            "category":"Manufacturing",
            "subcategory":"Wood Products",
            "type":"Manufacturing & Wholesale Goods"
        },
        {
            "category":"Home & Garden",
            "subcategory":"Home Furnishings",
            "type":"Retail Goods"
        }
    ],
    "sg:phone":"+44 1252 319588",
    "sg:postcode":"GU12 4NG",
    "sg:province":"Hampshire",
    "sg:tags":[
        "furnishers",
        "planner",
        "maker",
        "kitchen",
        "cabinet"
    ],
    "wof:name":"C R D Interiors",
    "wof:placetype":"venue"
},
  "geometry": {"coordinates":[-0.7555779815,51.2468528748],"type":"Point"}
}