{
  "type": "Feature",
  "properties": {
    "addr:full":"10 West St Bicester Oxfordshire OX6 8EW",
    "addr:housenumber":"10",
    "addr:postcode":"ox6 8ew",
    "addr:street":"West St",
    "iso:country":"GB",
    "sg:address":"10 West St",
    "sg:city":"Bicester",
    "sg:classifiers":[
        {
            "category":"Building & Trades",
            "subcategory":"Plumbing",
            "type":"Services"
        }
    ],
    "sg:phone":"+44 1869 321087",
    "sg:postcode":"OX6 8EW",
    "sg:province":"Oxfordshire",
    "sg:tags":[
        "heating"
    ],
    "wof:name":"Aardvark",
    "wof:placetype":"venue"
},
  "geometry": {"coordinates":[-1.1625809669,51.9043273926],"type":"Point"}
}