{
  "type": "Feature",
  "properties": {
    "iso:country":"GB",
    "sg:address":"Tweenroade, Church Street, Tempsford",
    "sg:city":"Sandy",
    "sg:classifiers":[
        {
            "category":"Farming",
            "subcategory":"Livestock Farm",
            "type":"Manufacturing & Wholesale Goods"
        }
    ],
    "sg:postcode":"SG19 2AN",
    "sg:province":"Bedfordshire",
    "sg:tags":[
        "others"
    ],
    "wof:name":"P G Russell",
    "wof:placetype":"venue"
},
  "geometry": {"coordinates":[-0.296319,52.170605],"type":"Point"}
}