{
  "type": "Feature",
  "properties": {
    "iso:country":"GB",
    "sg:address":"Central Buildings",
    "sg:city":"Ambleside",
    "sg:classifiers":[
        {
            "category":"Shopping",
            "subcategory":"Clothing, Apparel, & Fashions",
            "type":"Retail Goods"
        }
    ],
    "sg:phone":"+44 15394 32235",
    "sg:postcode":"LA22 9BS",
    "sg:province":"Cumbria",
    "sg:tags":[
        "workwear",
        "protective"
    ],
    "wof:name":"Anorak",
    "wof:placetype":"venue"
},
  "geometry": {"coordinates":[-2.963089,54.432606],"type":"Point"}
}