{
  "type": "Feature",
  "properties": {
    "addr:full":"Kings Estate, 1 The Broadway, Elm Park Hornchurch Essex RM12 4RS",
    "addr:housenumber":"1",
    "addr:postcode":"rm12 4rs",
    "addr:street":"The Broadway Elm",
    "iso:country":"GB",
    "sg:address":"Kings Estate, 1 The Broadway, Elm Park",
    "sg:city":"Hornchurch",
    "sg:classifiers":[
        {
            "category":"Home & Garden",
            "subcategory":"Hardware",
            "type":"Retail Goods"
        }
    ],
    "sg:phone":"+44 1708 450697",
    "sg:postcode":"RM12 4RS",
    "sg:province":"Essex",
    "sg:tags":[
        "sealant",
        "glue",
        "adhesives"
    ],
    "wof:name":"Besthaven Ltd.",
    "wof:placetype":"venue"
},
  "geometry": {"coordinates":[0.19817,51.55056],"type":"Point"}
}