{
  "type": "Feature",
  "properties": {
    "addr:full":"The Lodge, Stainforthmoor Rd Doncaster South Yorkshire DN7 6EZ",
    "addr:postcode":"dn7 6ez",
    "addr:street":"Stainforthmoor Rd",
    "iso:country":"GB",
    "sg:address":"The Lodge, Stainforthmoor Rd",
    "sg:city":"Doncaster",
    "sg:classifiers":[
        {
            "category":"Bus Charters",
            "type":"Transportation"
        }
    ],
    "sg:postcode":"DN7 6EZ",
    "sg:province":"South Yorkshire",
    "sg:tags":[
        "coach"
    ],
    "wof:name":"Parkin,B A,",
    "wof:placetype":"venue"
},
  "geometry": {"coordinates":[-0.943690002,53.5680618286],"type":"Point"}
}