{
  "type": "Feature",
  "properties": {
    "addr:full":"River Bank Surgery, Kilmun Dunoon Argyll and Bute PA23 8RR",
    "addr:postcode":"pa23 8rr",
    "addr:street":"River;Kilmun",
    "iso:country":"GB",
    "sg:address":"River Bank Surgery, Kilmun",
    "sg:city":"Dunoon",
    "sg:classifiers":[
        {
            "category":"Health Services",
            "subcategory":"Doctor",
            "type":"Services"
        }
    ],
    "sg:phone":"+44 1369 840279",
    "sg:postcode":"PA23 8RR",
    "sg:province":"Argyll and Bute",
    "sg:tags":[
        "practitioners"
    ],
    "wof:name":"W J Wilkie",
    "wof:placetype":"venue"
},
  "geometry": {"coordinates":[-4.9216980934,55.9523658752],"type":"Point"}
}