{
  "type": "Feature",
  "properties": {
    "addr:full":"11 Back Row Selkirk Scottish Borders TD7 4LP",
    "addr:housenumber":"11",
    "addr:postcode":"td7 4lp",
    "addr:street":"Back Row",
    "iso:country":"GB",
    "sg:address":"11 Back Row",
    "sg:city":"Selkirk",
    "sg:classifiers":[
        {
            "category":"Building & Trades",
            "subcategory":"Construction",
            "type":"Services"
        }
    ],
    "sg:phone":"+44 1750 20205",
    "sg:postcode":"TD7 4LP",
    "sg:province":"Scottish Borders",
    "sg:tags":[
        "dry",
        "lining",
        "plasterers",
        "screeders"
    ],
    "wof:name":"W.B Robertson",
    "wof:placetype":"venue"
},
  "geometry": {"coordinates":[-2.8271210194,55.5333824158],"type":"Point"}
}