{
  "type": "Feature",
  "properties": {
    "iso:country":"GB",
    "sg:address":"16 Pensnett Road, Holly Hall",
    "sg:city":"Dudley",
    "sg:classifiers":[
        {
            "category":"Bars & Pubs",
            "type":"Food & Drink"
        }
    ],
    "sg:phone":"+44 1384 77410",
    "sg:postcode":"DY1 2EY",
    "sg:province":"West Midlands",
    "sg:tags":[
        "pubs",
        "inn"
    ],
    "wof:name":"King William",
    "wof:placetype":"venue"
},
  "geometry": {"coordinates":[-2.111582,52.500706],"type":"Point"}
}