{
  "type": "Feature",
  "properties": {
    "iso:country":"GB",
    "sg:address":"3 Openshaw Way",
    "sg:city":"Letchworth",
    "sg:classifiers":[
        {
            "category":"Building & Trades",
            "subcategory":"Construction",
            "type":"Services"
        }
    ],
    "sg:phone":"+44 1462 684939",
    "sg:postcode":"SG6 3ER",
    "sg:province":"Hertfordshire",
    "sg:tags":[
        "builder"
    ],
    "wof:name":"Howes & Boughton Ltd.",
    "wof:placetype":"venue"
},
  "geometry": {"coordinates":[-0.224879,51.978939],"type":"Point"}
}