{
  "type": "Feature",
  "properties": {
    "addr:full":"Bridgend Road Grantham Lincolnshire NG31 6EU",
    "addr:postcode":"ng31 6eu",
    "addr:street":"Bridgend Road",
    "iso:country":"GB",
    "sg:address":"Bridgend Road",
    "sg:city":"Grantham",
    "sg:classifiers":[
        {
            "category":"Autos & Motor Vehicles",
            "subcategory":"Fuel & Gas Station",
            "type":"Retail Goods"
        }
    ],
    "sg:postcode":"NG31 6EU",
    "sg:province":"Lincolnshire",
    "sg:tags":[
        "petrol",
        "filling"
    ],
    "wof:name":"Gainsborough Corner Service Station",
    "wof:placetype":"venue"
},
  "geometry": {"coordinates":[-0.642859,52.913197],"type":"Point"}
}