{
  "type": "Feature",
  "properties": {
    "iso:country":"GB",
    "sg:address":"503 Hucknall Road, Sherwood",
    "sg:city":"Nottingham",
    "sg:classifiers":[
        {
            "category":"Shopping",
            "subcategory":"News",
            "type":"Retail Goods"
        }
    ],
    "sg:phone":"+44 115 952 0820",
    "sg:postcode":"NG5 1FW",
    "sg:province":"Nottinghamshire",
    "sg:tags":[
        "newsagent"
    ],
    "wof:name":"Parmjit S T R Thiara",
    "wof:placetype":"venue"
},
  "geometry": {"coordinates":[-1.159627,52.986572],"type":"Point"}
}