{
  "type": "Feature",
  "properties": {
    "addr:full":"Unit 1 Pontcynon Indust Est Mountain Ash Rhondda, Cynon, Taff CF45 4EP",
    "addr:housenumber":"unit 1",
    "addr:postcode":"cf45 4ep",
    "addr:street":"Indust Est;Cynon Taff",
    "iso:country":"GB",
    "sg:address":"Unit 1 Pontcynon Indust Est",
    "sg:city":"Mountain Ash",
    "sg:classifiers":[
        {
            "category":"Building & Trades",
            "subcategory":"Electrical",
            "type":"Services"
        }
    ],
    "sg:phone":"+44 1443 740500",
    "sg:postcode":"CF45 4EP",
    "sg:province":"Rhondda, Cynon, Taff",
    "sg:tags":[
        "consultant",
        "lighting"
    ],
    "wof:name":"B E I Lighting",
    "wof:placetype":"venue"
},
  "geometry": {"coordinates":[-3.336188,51.655415],"type":"Point"}
}