{
  "type": "Feature",
  "properties": {
    "iso:country":"GB",
    "sg:address":"90 County Road, Walton",
    "sg:city":"Liverpool",
    "sg:classifiers":[
        {
            "category":"Shopping",
            "subcategory":"Thrift Store",
            "type":"Retail Goods"
        }
    ],
    "sg:phone":"+44 151 284 2700",
    "sg:postcode":"L4 3QN",
    "sg:province":"Merseyside",
    "sg:tags":[
        "shop",
        "charity"
    ],
    "wof:name":"Schools of Good Shepherd",
    "wof:placetype":"venue"
},
  "geometry": {"coordinates":[-2.970652,53.440865],"type":"Point"}
}