{
  "type": "Feature",
  "properties": {
    "iso:country":"GB",
    "sg:address":"Church Flats Farm, Grangewood",
    "sg:city":"Swadlincote",
    "sg:classifiers":[
        {
            "category":"Farming",
            "subcategory":"Dairy Farm",
            "type":"Manufacturing & Wholesale Goods"
        }
    ],
    "sg:phone":"+44 1827 373281",
    "sg:postcode":"DE12 8DZ",
    "sg:province":"Derbyshire",
    "wof:name":"A H Blackwell",
    "wof:placetype":"venue"
},
  "geometry": {"coordinates":[-1.5866910219,52.7265777588],"type":"Point"}
}