{
  "type": "Feature",
  "properties": {
    "addr:full":"Shaw St Worksop Nottinghamshire S80 1SJ",
    "addr:postcode":"s80 1sj",
    "addr:street":"Shaw St",
    "iso:country":"GB",
    "sg:address":"Shaw St",
    "sg:city":"Worksop",
    "sg:classifiers":[
        {
            "category":"Community Center",
            "subcategory":"Youth",
            "type":"Public Place"
        }
    ],
    "sg:phone":"+44 1909 474034",
    "sg:postcode":"S80 1SJ",
    "sg:province":"Nottinghamshire",
    "sg:tags":[
        "organisation",
        "centre"
    ],
    "wof:name":"Worksop Teen Club",
    "wof:placetype":"venue"
},
  "geometry": {"coordinates":[-1.1242790222,53.3086395264],"type":"Point"}
}