{
  "type": "Feature",
  "properties": {
    "addr:full":"Lyon Way, Hatfield Way St Albans Hertfordshire AL4 0QU",
    "addr:postcode":"al4 0qu",
    "addr:street":"Lyon Way Hatfield Way",
    "iso:country":"GB",
    "sg:address":"Lyon Way, Hatfield Way",
    "sg:city":"St Albans",
    "sg:classifiers":[
        {
            "category":"Autos & Motor Vehicles",
            "subcategory":"Automobile Sales",
            "type":"Retail Goods"
        }
    ],
    "sg:phone":"+44 1707 277911",
    "sg:postcode":"AL4 0QU",
    "sg:province":"Hertfordshire",
    "sg:tags":[
        "car"
    ],
    "wof:name":"H R Owen",
    "wof:placetype":"venue"
},
  "geometry": {"coordinates":[-0.2753590047,51.7522735596],"type":"Point"}
}