{
  "type": "Feature",
  "properties": {
    "addr:full":"2 Acicia Court, Blenheim Close, Brantham Manningtree Essex CO11 1TR",
    "addr:housenumber":"2",
    "addr:postcode":"co11 1tr",
    "addr:street":"Acicia Court Blenheim Close",
    "iso:country":"GB",
    "sg:address":"2 Acicia Court, Blenheim Close, Brantham",
    "sg:city":"Manningtree",
    "sg:classifiers":[
        {
            "category":"Personal",
            "subcategory":"Beauty Salon",
            "type":"Services"
        }
    ],
    "sg:postcode":"CO11 1TR",
    "sg:province":"Essex",
    "sg:tags":[
        "unisex",
        "hairdresser"
    ],
    "wof:name":"Changes",
    "wof:placetype":"venue"
},
  "geometry": {"coordinates":[1.06304,51.945381],"type":"Point"}
}