{
  "type": "Feature",
  "properties": {
    "addr:full":"1 Gorselands, Blackbushe Indstl, Yateley Camberley Hampshire GU17 7ET",
    "addr:housenumber":"1",
    "addr:postcode":"gu17 7et",
    "addr:street":"Gorselands Blackbushe Indstl",
    "iso:country":"GB",
    "sg:address":"1 Gorselands, Blackbushe Indstl, Yateley",
    "sg:city":"Camberley",
    "sg:classifiers":[
        {
            "category":"Manufacturing",
            "subcategory":"Metals",
            "type":"Manufacturing & Wholesale Goods"
        }
    ],
    "sg:postcode":"GU17 7ET",
    "sg:province":"Hampshire",
    "sg:tags":[
        "work",
        "sheet"
    ],
    "wof:name":"Eden,Phillip T,",
    "wof:placetype":"venue"
},
  "geometry": {"coordinates":[-0.8116599917,51.3216018677],"type":"Point"}
}