{
  "type": "Feature",
  "properties": {
    "addr:full":"Bryan Road Huddersfield West Yorkshire HD2 2AJ",
    "addr:postcode":"hd2 2aj",
    "addr:street":"Bryan Road",
    "iso:country":"GB",
    "sg:address":"Bryan Road",
    "sg:city":"Huddersfield",
    "sg:classifiers":[
        {
            "category":"Social Services",
            "subcategory":"Retirement Home",
            "type":"Services"
        }
    ],
    "sg:postcode":"HD2 2AJ",
    "sg:province":"West Yorkshire",
    "sg:tags":[
        "rest"
    ],
    "wof:name":"THORNLEIGH LODGE",
    "wof:placetype":"venue"
},
  "geometry": {"coordinates":[-1.8060239553,53.659198761],"type":"Point"}
}