{
  "type": "Feature",
  "properties": {
    "addr:full":"244 Stanley St Grimsby Lincolnshire DN32 8BS",
    "addr:housenumber":"244",
    "addr:postcode":"dn32 8bs",
    "addr:street":"Stanley St",
    "iso:country":"GB",
    "sg:address":"244 Stanley St",
    "sg:city":"Grimsby",
    "sg:classifiers":[
        {
            "category":"Shopping",
            "subcategory":"Pets & Pet Supplies",
            "type":"Retail Goods"
        }
    ],
    "sg:phone":"+44 1472 240561",
    "sg:postcode":"DN32 8BS",
    "sg:province":"Lincolnshire",
    "wof:name":"Sunshine Corner",
    "wof:placetype":"venue"
},
  "geometry": {"coordinates":[-0.065053001,53.5665817261],"type":"Point"}
}