{
  "type": "Feature",
  "properties": {
    "addr:full":"59 Princes Court, Croxteth Road Liverpool Merseyside L8 3UJ",
    "addr:housenumber":"59",
    "addr:postcode":"l8 3uj",
    "addr:street":"Princes Court Croxteth Road",
    "iso:country":"GB",
    "sg:address":"59 Princes Court, Croxteth Road",
    "sg:city":"Liverpool",
    "sg:classifiers":[
        {
            "category":"Home & Garden",
            "subcategory":"Furniture",
            "type":"Retail Goods"
        }
    ],
    "sg:postcode":"L8 3UJ",
    "sg:province":"Merseyside",
    "wof:name":"Kardus Enterprises Ltd",
    "wof:placetype":"venue"
},
  "geometry": {"coordinates":[-2.9536099434,53.3900489807],"type":"Point"}
}