{
  "type": "Feature",
  "properties": {
    "iso:country":"GB",
    "sg:address":"60 Upperthorpe Road",
    "sg:city":"Sheffield",
    "sg:classifiers":[
        {
            "category":"Community Center",
            "subcategory":"Social",
            "type":"Public Place"
        }
    ],
    "sg:phone":"+44 114 281 2897",
    "sg:postcode":"S6 3EB",
    "sg:province":"South Yorkshire",
    "sg:tags":[
        "frozen",
        "food",
        "freezer",
        "centre"
    ],
    "wof:name":"Upperthorpe Freezer Centre",
    "wof:placetype":"venue"
},
  "geometry": {"coordinates":[-1.486729,53.39011],"type":"Point"}
}