{
  "type": "Feature",
  "properties": {
    "iso:country":"GB",
    "sg:address":"377 Regents Park Road",
    "sg:city":"London",
    "sg:classifiers":[
        {
            "category":"Fast Food",
            "type":"Food & Drink"
        }
    ],
    "sg:phone":"+44 20 8343 0923",
    "sg:postcode":"N3 1DE",
    "sg:province":"Greater London",
    "sg:tags":[
        "away",
        "meal",
        "outlet",
        "take"
    ],
    "wof:name":"Touch of Delicacy",
    "wof:placetype":"venue"
},
  "geometry": {"coordinates":[-0.194257,51.601055],"type":"Point"}
}