{
  "type": "Feature",
  "properties": {
    "iso:country":"GB",
    "sg:address":"34 Church Street",
    "sg:city":"Peterborough",
    "sg:classifiers":[
        {
            "category":"Fast Food",
            "type":"Food & Drink"
        }
    ],
    "sg:phone":"+44 1778 345370",
    "sg:postcode":"PE6 8HD",
    "sg:province":"Cambridgeshire",
    "sg:tags":[
        "away",
        "take"
    ],
    "wof:name":"Riceland Chinese Takeaway",
    "wof:placetype":"venue"
},
  "geometry": {"coordinates":[-0.2916980088,52.671043396],"type":"Point"}
}