{
  "type": "Feature",
  "properties": {
    "addr:full":"24 New La Ormskirk Lancashire L40 8JA",
    "addr:housenumber":"24",
    "addr:postcode":"l40 8ja",
    "addr:street":"New La Ormskirk",
    "iso:country":"GB",
    "sg:address":"24 New La",
    "sg:city":"Ormskirk",
    "sg:classifiers":[
        {
            "category":"Professional",
            "subcategory":"Business Services",
            "type":"Services"
        }
    ],
    "sg:phone":"+44 1704 896558",
    "sg:postcode":"L40 8JA",
    "sg:province":"Lancashire",
    "sg:tags":[
        "distribution"
    ],
    "wof:name":"Salvesen Food Logistics",
    "wof:placetype":"venue"
},
  "geometry": {"coordinates":[-2.864620924,53.6048126221],"type":"Point"}
}