{
  "type": "Feature",
  "properties": {
    "iso:country":"GB",
    "sg:address":"149 Lower Cheltenham Place",
    "sg:city":"Bristol",
    "sg:classifiers":[
        {
            "category":"Building & Trades",
            "subcategory":"Construction",
            "type":"Services"
        }
    ],
    "sg:phone":"+44 117 935 1717",
    "sg:postcode":"BS6 5LB",
    "sg:province":"City of Bristol",
    "sg:tags":[
        "roofing"
    ],
    "wof:name":"Zenor Ltd.",
    "wof:placetype":"venue"
},
  "geometry": {"coordinates":[-2.580471,51.468498],"type":"Point"}
}