{
  "type": "Feature",
  "properties": {
    "addr:full":"Suite 20 Queensgate Bus Centre, Fraser St Inverness Highland IV1 1DW",
    "addr:postcode":"iv1 1dw",
    "addr:street":"Suite 20 Queensgate Bus;Fraser St",
    "iso:country":"GB",
    "sg:address":"Suite 20 Queensgate Bus Centre, Fraser St",
    "sg:city":"Inverness",
    "sg:classifiers":[
        {
            "category":"Professional",
            "subcategory":"Detective & Security Services",
            "type":"Services"
        }
    ],
    "sg:postcode":"IV1 1DW",
    "sg:province":"Highland",
    "sg:tags":[
        "agency"
    ],
    "wof:name":"Dorman,Mark,& Associates",
    "wof:placetype":"venue"
},
  "geometry": {"coordinates":[-4.225563,57.47953],"type":"Point"}
}