{
  "type": "Feature",
  "properties": {
    "addr:full":"Great Guildford Street London Greater London SE1 0ES",
    "addr:postcode":"se1 0es",
    "addr:street":"Great Guildford Street",
    "iso:country":"GB",
    "sg:address":"Great Guildford Street",
    "sg:city":"London",
    "sg:classifiers":[
        {
            "category":"Professional",
            "subcategory":"Art Services",
            "type":"Services"
        }
    ],
    "sg:phone":"+44 20 7261 0360",
    "sg:postcode":"SE1 0ES",
    "sg:province":"Greater London",
    "sg:tags":[
        "photographer"
    ],
    "wof:name":"Duthy Hall Studios",
    "wof:placetype":"venue"
},
  "geometry": {"coordinates":[-0.09679,51.503368],"type":"Point"}
}