{
  "type": "Feature",
  "properties": {
    "addr:full":"Police Headquarters, Aykley Heads Durham Durham DH1 5TT",
    "addr:postcode":"dh1 5tt",
    "addr:street":"Aykley",
    "iso:country":"GB",
    "sg:address":"Police Headquarters, Aykley Heads",
    "sg:city":"Durham",
    "sg:classifiers":[
        {
            "category":"Government",
            "subcategory":"Police Station",
            "type":"Public Place"
        }
    ],
    "sg:phone":"+44 191 386 4929",
    "sg:postcode":"DH1 5TT",
    "sg:province":"Durham",
    "sg:tags":[
        "support"
    ],
    "wof:name":"Durham Constabulary",
    "wof:placetype":"venue"
},
  "geometry": {"coordinates":[-1.59205,54.790318],"type":"Point"}
}