{
  "type": "Feature",
  "properties": {
    "addr:full":"Ace House, Redry Street Newport Newport NP19 7AN",
    "addr:postcode":"np19 7an",
    "addr:street":"Redry Street",
    "iso:country":"GB",
    "sg:address":"Ace House, Redry Street",
    "sg:city":"Newport",
    "sg:classifiers":[
        {
            "category":"Wholesale",
            "subcategory":"Vending Machines",
            "type":"Manufacturing & Wholesale Goods"
        }
    ],
    "sg:postcode":"NP19 7AN",
    "sg:province":"Newport",
    "wof:name":"Valley Catering Vending Supplies",
    "wof:placetype":"venue"
},
  "geometry": {"coordinates":[-2.9904959202,51.5929527283],"type":"Point"}
}