{
  "type": "Feature",
  "properties": {
    "addr:full":"31 Parkwood Road, Boscombe Bournemouth Dorset BH5 2BS",
    "addr:housenumber":"31",
    "addr:postcode":"bh5 2bs",
    "addr:street":"Parkwood Road",
    "iso:country":"GB",
    "sg:address":"31 Parkwood Road, Boscombe",
    "sg:city":"Bournemouth",
    "sg:classifiers":[
        {
            "category":"Building & Trades",
            "subcategory":"Construction",
            "type":"Services"
        }
    ],
    "sg:phone":"+44 1202 417347",
    "sg:postcode":"BH5 2BS",
    "sg:province":"Dorset",
    "sg:tags":[
        "dry",
        "lining",
        "plasterers",
        "screeders"
    ],
    "wof:name":"S C L Plastering",
    "wof:placetype":"venue"
},
  "geometry": {"coordinates":[-1.8258759975,50.7262496948],"type":"Point"}
}