{
  "type": "Feature",
  "properties": {
    "iso:country":"GB",
    "sg:address":"The Lodge House, 22 Neilston Road",
    "sg:city":"Paisley",
    "sg:classifiers":[
        {
            "category":"Farming",
            "subcategory":"Nursery",
            "type":"Manufacturing & Wholesale Goods"
        },
        {
            "category":"Education",
            "subcategory":"Preschool",
            "type":"Public Place"
        }
    ],
    "sg:phone":"+44 141 848 9292",
    "sg:postcode":"PA2 6LN",
    "sg:province":"East Renfrewshire",
    "sg:tags":[
        "school",
        "creche"
    ],
    "wof:name":"Nursery Times Ltd.",
    "wof:placetype":"venue"
},
  "geometry": {"coordinates":[-4.424666,55.837666],"type":"Point"}
}