{
  "type": "Feature",
  "properties": {
    "addr:full":"2 Juniper Way Colchester Essex CO4 3NW",
    "addr:housenumber":"2",
    "addr:postcode":"co4 3nw",
    "addr:street":"Juniper Way",
    "iso:country":"GB",
    "sg:address":"2 Juniper Way",
    "sg:city":"Colchester",
    "sg:classifiers":[
        {
            "category":"Professional",
            "type":"Services"
        }
    ],
    "sg:postcode":"CO4 3NW",
    "sg:province":"Essex",
    "sg:tags":[
        "directory",
        "pub"
    ],
    "wof:name":"Blackman,R T,",
    "wof:placetype":"venue"
},
  "geometry": {"coordinates":[0.932315,51.893791],"type":"Point"}
}