{
  "type": "Feature",
  "properties": {
    "addr:full":"16 Bury Road Hatfield Hertfordshire AL10 8BJ",
    "addr:housenumber":"16",
    "addr:postcode":"al10 8bj",
    "addr:street":"Bury Road",
    "iso:country":"GB",
    "sg:address":"16 Bury Road",
    "sg:city":"Hatfield",
    "sg:classifiers":[
        {
            "category":"Autos & Motor Vehicles",
            "subcategory":"Boat Sales",
            "type":"Retail Goods"
        },
        {
            "category":"Retail",
            "subcategory":"Auto Repair",
            "type":"Services"
        }
    ],
    "sg:phone":"+44 1707 264310",
    "sg:postcode":"AL10 8BJ",
    "sg:province":"Hertfordshire",
    "sg:tags":[
        "engine",
        "car",
        "rebuilders",
        "specialist"
    ],
    "wof:name":"Power Units (Hatfield)",
    "wof:placetype":"venue"
},
  "geometry": {"coordinates":[-0.217449,51.76268],"type":"Point"}
}