{
  "type": "Feature",
  "properties": {
    "addr:full":"5 Ramshill Road Scarborough North Yorkshire YO11 2LN",
    "addr:housenumber":"5",
    "addr:postcode":"yo11 2ln",
    "addr:street":"Ramshill Road",
    "iso:country":"GB",
    "sg:address":"5 Ramshill Road",
    "sg:city":"Scarborough",
    "sg:classifiers":[
        {
            "category":"Shopping",
            "subcategory":"Pharmacy",
            "type":"Retail Goods"
        }
    ],
    "sg:phone":"+44 1723 362796",
    "sg:postcode":"YO11 2LN",
    "sg:province":"North Yorkshire",
    "sg:tags":[
        "pharmacist",
        "chemist"
    ],
    "wof:name":"Edward A Clarke",
    "wof:placetype":"venue"
},
  "geometry": {"coordinates":[-0.4027160108,54.2741928101],"type":"Point"}
}