{
  "type": "Feature",
  "properties": {
    "iso:country":"GB",
    "sg:address":"102 Widnes Rd",
    "sg:city":"Widnes",
    "sg:classifiers":[
        {
            "category":"Retail",
            "subcategory":"Auto Repair",
            "type":"Services"
        }
    ],
    "sg:phone":"+44 151 422 0788",
    "sg:postcode":"WA8 6AX",
    "sg:province":"Cheshire",
    "sg:tags":[
        "modification",
        "garage"
    ],
    "wof:name":"Autofix",
    "wof:placetype":"venue"
},
  "geometry": {"coordinates":[-2.7294409275,53.3660163879],"type":"Point"}
}