{
  "type": "Feature",
  "properties": {
    "addr:full":"19-21 Lake St, Lower Gornal Dudley Staffordshire DY3 2AU",
    "addr:housenumber":"19-21",
    "addr:postcode":"dy3 2au",
    "addr:street":"Lake St",
    "iso:country":"GB",
    "sg:address":"19-21 Lake St, Lower Gornal",
    "sg:city":"Dudley",
    "sg:classifiers":[
        {
            "category":"Government",
            "subcategory":"Office",
            "type":"Public Place"
        }
    ],
    "sg:phone":"+44 1902 679797",
    "sg:postcode":"DY3 2AU",
    "sg:province":"Staffordshire",
    "sg:tags":[
        "central"
    ],
    "wof:name":"Vehicle Inspectorate Enforcement Agency",
    "wof:placetype":"venue"
},
  "geometry": {"coordinates":[-2.12228,52.520638],"type":"Point"}
}