{
  "type": "Feature",
  "properties": {
    "addr:full":"Unit 4, Market Industrial Estate Bristol Somerset BS49 4RF",
    "addr:housenumber":"unit 4",
    "addr:postcode":"bs49 4rf",
    "addr:street":"Market Industrial Estate",
    "iso:country":"GB",
    "sg:address":"Unit 4, Market Industrial Estate",
    "sg:city":"Bristol",
    "sg:classifiers":[
        {
            "category":"Communications",
            "type":"Services"
        }
    ],
    "sg:phone":"+44 1934 830301",
    "sg:postcode":"BS49 4RF",
    "sg:province":"Somerset",
    "sg:tags":[
        "audio-visual"
    ],
    "wof:name":"Pip Recording",
    "wof:placetype":"venue"
},
  "geometry": {"coordinates":[-2.82561,51.39233],"type":"Point"}
}