{
  "type": "Feature",
  "properties": {
    "addr:full":"160-164 Front St, Arnold Nottingham Nottinghamshire NG5 7EG",
    "addr:housenumber":"160-164",
    "addr:postcode":"ng5 7eg",
    "addr:street":"Front St",
    "iso:country":"GB",
    "sg:address":"160-164 Front St, Arnold",
    "sg:city":"Nottingham",
    "sg:classifiers":[
        {
            "category":"Shopping",
            "subcategory":"Clothing, Apparel, & Fashions",
            "type":"Retail Goods"
        }
    ],
    "sg:phone":"+44 115 926 9743",
    "sg:postcode":"NG5 7EG",
    "sg:province":"Nottinghamshire",
    "sg:tags":[
        "shop"
    ],
    "wof:name":"Thrifty",
    "wof:placetype":"venue"
},
  "geometry": {"coordinates":[-1.1267499924,53.0058441162],"type":"Point"}
}