{
  "type": "Feature",
  "properties": {
    "addr:full":"144 Forton Rd Gosport Hampshire PO12 3HG",
    "addr:housenumber":"144",
    "addr:postcode":"po12 3hg",
    "addr:street":"Forton Rd",
    "iso:country":"GB",
    "sg:address":"144 Forton Rd",
    "sg:city":"Gosport",
    "sg:classifiers":[
        {
            "category":"Shopping",
            "subcategory":"Thrift Store",
            "type":"Retail Goods"
        }
    ],
    "sg:phone":"+44 23 9252 7542",
    "sg:postcode":"PO12 3HG",
    "sg:province":"Hampshire",
    "sg:tags":[
        "shop",
        "charity"
    ],
    "wof:name":"The Rowans Hospice",
    "wof:placetype":"venue"
},
  "geometry": {"coordinates":[-1.1406320333,50.8004112244],"type":"Point"}
}