{
  "type": "Feature",
  "properties": {
    "addr:full":"2 Bon Accord Crescent Aberdeen Aberdeen City AB11 6DH",
    "addr:housenumber":"2",
    "addr:postcode":"ab11 6dh",
    "addr:street":"Bon Accord Crescent",
    "iso:country":"GB",
    "sg:address":"2 Bon Accord Crescent",
    "sg:city":"Aberdeen",
    "sg:classifiers":[
        {
            "category":"Professional",
            "subcategory":"Business Services",
            "type":"Services"
        }
    ],
    "sg:postcode":"AB11 6DH",
    "sg:province":"Aberdeen City",
    "sg:tags":[
        "accomodation"
    ],
    "wof:name":"Nestaglen Ltd",
    "wof:placetype":"venue"
},
  "geometry": {"coordinates":[-2.106257,57.14167],"type":"Point"}
}