{
  "type": "Feature",
  "properties": {
    "iso:country":"GB",
    "sg:address":"47 Mill Lane",
    "sg:city":"Gosport",
    "sg:classifiers":[
        {
            "category":"Professional",
            "subcategory":"Engineering",
            "type":"Services"
        },
        {
            "category":"Building & Trades",
            "subcategory":"Electrical",
            "type":"Services"
        }
    ],
    "sg:phone":"+44 23 9252 2735",
    "sg:postcode":"PO12 4QG",
    "sg:province":"Hampshire",
    "sg:tags":[
        "engineer",
        "electrician",
        "contractor"
    ],
    "wof:name":"Vale Contracting Ltd.",
    "wof:placetype":"venue"
},
  "geometry": {"coordinates":[-1.138323,50.803162],"type":"Point"}
}