{
  "type": "Feature",
  "properties": {
    "addr:full":"Warehouse, Richmond Rd, Dukes Pk Indust Est Chelmsford Essex CM2 6UA",
    "addr:postcode":"cm2 6ua",
    "addr:street":"Rd;Pk Indust Est",
    "iso:country":"GB",
    "sg:address":"Warehouse, Richmond Rd, Dukes Pk Indust Est",
    "sg:city":"Chelmsford",
    "sg:classifiers":[
        {
            "category":"Shopping",
            "subcategory":"Pharmacy",
            "type":"Retail Goods"
        }
    ],
    "sg:phone":"+44 1245 461460",
    "sg:postcode":"CM2 6UA",
    "sg:province":"Essex",
    "sg:tags":[
        "pharmacist",
        "chemist"
    ],
    "wof:name":"Boots the Chemists Ltd",
    "wof:placetype":"venue"
},
  "geometry": {"coordinates":[0.477891,51.731918],"type":"Point"}
}