{
  "type": "Feature",
  "properties": {
    "addr:full":"69 Mansel Street Swansea Neath Port Talbot SA1 5TN",
    "addr:housenumber":"69",
    "addr:postcode":"sa1 5tn",
    "addr:street":"Mansel Street",
    "iso:country":"GB",
    "sg:address":"69 Mansel Street",
    "sg:city":"Swansea",
    "sg:classifiers":[
        {
            "category":"Banks & Credit Unions",
            "subcategory":"Financial Services",
            "type":"Services"
        }
    ],
    "sg:phone":"+44 1792 411118",
    "sg:postcode":"SA1 5TN",
    "sg:province":"Neath Port Talbot",
    "sg:tags":[
        "adviser",
        "consultant"
    ],
    "sg:website":"http://www.johndyer.net",
    "wof:name":"John Dyer Life & Pensions Ltd",
    "wof:placetype":"venue"
},
  "geometry": {"coordinates":[-3.950658083,51.6207771301],"type":"Point"}
}