{
  "type": "Feature",
  "properties": {
    "addr:full":"5a Priory Row Coventry West Midlands CV1 5EX",
    "addr:housenumber":"5a",
    "addr:postcode":"cv1 5ex",
    "addr:street":"Priory Row",
    "iso:country":"GB",
    "sg:address":"5a Priory Row",
    "sg:city":"Coventry",
    "sg:classifiers":[
        {
            "category":"Place Of Worship",
            "type":"Public Place"
        }
    ],
    "sg:phone":"+44 24 7622 0418",
    "sg:postcode":"CV1 5EX",
    "sg:province":"West Midlands",
    "wof:name":"Holy Trinity C Of E Church",
    "wof:placetype":"venue"
},
  "geometry": {"coordinates":[-1.5079109669,52.4085769653],"type":"Point"}
}