{
  "type": "Feature",
  "properties": {
    "addr:full":"38 Alders Green Road, Hindley Grn Wigan Lancashire WN2 4LA",
    "addr:housenumber":"38",
    "addr:postcode":"wn2 4la",
    "addr:street":"Alders Green Road",
    "iso:country":"GB",
    "sg:address":"38 Alders Green Road, Hindley Grn",
    "sg:city":"Wigan",
    "sg:classifiers":[
        {
            "category":"Personal",
            "type":"Services"
        }
    ],
    "sg:phone":"+44 1942 523340",
    "sg:postcode":"WN2 4LA",
    "sg:province":"Lancashire",
    "sg:tags":[
        "dressmaker"
    ],
    "wof:name":"Sheila Fogg Sewing Services",
    "wof:placetype":"venue"
},
  "geometry": {"coordinates":[-2.557033,53.534641],"type":"Point"}
}