{
  "type": "Feature",
  "properties": {
    "iso:country":"GB",
    "sg:address":"Brooklyn Farm, North Hill, Horndon On The Hill",
    "sg:city":"Stanford-le-hope",
    "sg:classifiers":[
        {
            "category":"Building & Trades",
            "subcategory":"Construction",
            "type":"Services"
        }
    ],
    "sg:postcode":"SS17 8QA",
    "sg:province":"Essex",
    "sg:tags":[
        "platform",
        "work",
        "scaffolding"
    ],
    "wof:name":"Tube Tech Scaffolding Ltd",
    "wof:placetype":"venue"
},
  "geometry": {"coordinates":[0.40201,51.526279],"type":"Point"}
}