{
  "type": "Feature",
  "properties": {
    "addr:full":"Chelmsford & Essex Centre, New London Road Chelmsford Essex CM2 0QH",
    "addr:postcode":"cm2 0qh",
    "addr:street":"New London Road",
    "iso:country":"GB",
    "sg:address":"Chelmsford & Essex Centre, New London Road",
    "sg:city":"Chelmsford",
    "sg:classifiers":[
        {
            "category":"Social Services",
            "type":"Services"
        },
        {
            "category":"Social Services",
            "subcategory":"Adult Care",
            "type":"Services"
        }
    ],
    "sg:phone":"+44 1245 318640",
    "sg:postcode":"CM2 0QH",
    "sg:province":"Essex",
    "sg:tags":[
        "need",
        "disability",
        "day",
        "special",
        "centre"
    ],
    "wof:name":"Mid Essex Community & Mental Health Nhs",
    "wof:placetype":"venue"
},
  "geometry": {"coordinates":[0.47086,51.730949],"type":"Point"}
}