{
  "type": "Feature",
  "properties": {
    "iso:country":"GB",
    "sg:address":"102 Cowley Rd",
    "sg:city":"Oxford",
    "sg:classifiers":[
        {
            "category":"Shopping",
            "subcategory":"Jewelry",
            "type":"Retail Goods"
        }
    ],
    "sg:phone":"+44 1865 790867",
    "sg:postcode":"OX4 1JE",
    "sg:province":"Oxfordshire",
    "sg:tags":[
        "gold",
        "silversmith"
    ],
    "wof:name":"Campion,S,",
    "wof:placetype":"venue"
},
  "geometry": {"coordinates":[-1.2393120527,51.7483787537],"type":"Point"}
}