{
  "type": "Feature",
  "properties": {
    "addr:full":"2 Crosscoates Road Grimsby Lincolnshire DN34 4QG",
    "addr:housenumber":"2",
    "addr:postcode":"dn34 4qg",
    "addr:street":"Crosscoates Road",
    "iso:country":"GB",
    "sg:address":"2 Crosscoates Road",
    "sg:city":"Grimsby",
    "sg:classifiers":[
        {
            "category":"Government",
            "subcategory":"Post Office",
            "type":"Public Place"
        }
    ],
    "sg:phone":"+44 1472 356642",
    "sg:postcode":"DN34 4QG",
    "sg:province":"Lincolnshire",
    "wof:name":"Yarborough Road P O",
    "wof:placetype":"venue"
},
  "geometry": {"coordinates":[-0.1097410023,53.5626144409],"type":"Point"}
}