{
  "type": "Feature",
  "properties": {
    "iso:country":"GB",
    "sg:address":"30 Francis Street",
    "sg:city":"Stornoway",
    "sg:classifiers":[
        {
            "category":"Organizations",
            "subcategory":"Non-profit Organization",
            "type":"Services"
        }
    ],
    "sg:phone":"+44 1851 702632",
    "sg:postcode":"HS1 2ND",
    "sg:province":"Eilean Siar",
    "sg:tags":[
        "organisation",
        "voluntary",
        "charity"
    ],
    "wof:name":"Voluntary Action Lewis",
    "wof:placetype":"venue"
},
  "geometry": {"coordinates":[-6.3847489357,58.2090339661],"type":"Point"}
}