{
  "type": "Feature",
  "properties": {
    "addr:full":"Thornbridge, Hawkers Lane Plymouth Devon PL3 4QA",
    "addr:postcode":"pl3 4qa",
    "addr:street":"Hawkers Lane",
    "iso:country":"GB",
    "sg:address":"Thornbridge, Hawkers Lane",
    "sg:city":"Plymouth",
    "sg:classifiers":[
        {
            "category":"Social Services",
            "subcategory":"Child Care",
            "type":"Services"
        },
        {
            "category":"Government",
            "subcategory":"Office",
            "type":"Public Place"
        }
    ],
    "sg:phone":"+44 1752 225618",
    "sg:postcode":"PL3 4QA",
    "sg:province":"Devon",
    "sg:tags":[
        "home",
        "local",
        "children's"
    ],
    "wof:name":"Thornbridge Childrens Home",
    "wof:placetype":"venue"
},
  "geometry": {"coordinates":[-4.136660099,50.3877983093],"type":"Point"}
}