{
  "type": "Feature",
  "properties": {
    "iso:country":"GB",
    "sg:address":"9 High View, Meir Heath",
    "sg:city":"Stoke On Trent",
    "sg:classifiers":[
        {
            "category":"Arts & Performance",
            "subcategory":"Music",
            "type":"Entertainment"
        }
    ],
    "sg:phone":"+44 1782 397507",
    "sg:postcode":"ST3 7JS",
    "sg:province":"Staffordshire",
    "sg:tags":[
        "mobile",
        "disco"
    ],
    "wof:name":"Blockbuster Disco",
    "wof:placetype":"venue"
},
  "geometry": {"coordinates":[-2.104735,52.957844],"type":"Point"}
}