{
  "type": "Feature",
  "properties": {
    "addr:full":"Community Centre, Worcester Clo, Istead Rise Gravesend Kent DA13 9LB",
    "addr:postcode":"da13 9lb",
    "addr:street":"Istead Rise",
    "iso:country":"GB",
    "sg:address":"Community Centre, Worcester Clo, Istead Rise",
    "sg:city":"Gravesend",
    "sg:classifiers":[
        {
            "category":"Government",
            "subcategory":"City Hall",
            "type":"Public Place"
        }
    ],
    "sg:postcode":"DA13 9LB",
    "sg:province":"Kent",
    "wof:name":"Istead Rise Community Association Ltd",
    "wof:placetype":"venue"
},
  "geometry": {"coordinates":[0.35252,51.40654],"type":"Point"}
}