{
  "type": "Feature",
  "properties": {
    "addr:full":"7 Tor Church Road Torquay Devon TQ2 5UR",
    "addr:housenumber":"7",
    "addr:postcode":"tq2 5ur",
    "addr:street":"Tor Church Road",
    "iso:country":"GB",
    "sg:address":"7 Tor Church Road",
    "sg:city":"Torquay",
    "sg:classifiers":[
        {
            "category":"Travel",
            "subcategory":"Hotels & Motels",
            "type":"Entertainment"
        }
    ],
    "sg:postcode":"TQ2 5UR",
    "sg:province":"Devon",
    "wof:name":"The Ascot House Hotel",
    "wof:placetype":"venue"
},
  "geometry": {"coordinates":[-3.5365719795,50.4680786133],"type":"Point"}
}