{
  "type": "Feature",
  "properties": {
    "iso:country":"GB",
    "sg:address":"8 King St",
    "sg:city":"Brixham",
    "sg:classifiers":[
        {
            "category":"Bars & Pubs",
            "type":"Food & Drink"
        }
    ],
    "sg:phone":"+44 1803 851600",
    "sg:postcode":"TQ5 9TW",
    "sg:province":"Devon",
    "sg:tags":[
        "pubs",
        "inn"
    ],
    "wof:name":"Hole In The Wall The",
    "wof:placetype":"venue"
},
  "geometry": {"coordinates":[-3.512603,50.395618],"type":"Point"}
}