{
  "type": "Feature",
  "properties": {
    "addr:full":"67 Teme Street Tenbury Wells Herefordshire WR15 8AE",
    "addr:housenumber":"67",
    "addr:postcode":"wr15 8ae",
    "addr:street":"Teme Street",
    "iso:country":"GB",
    "sg:address":"67 Teme Street",
    "sg:city":"Tenbury Wells",
    "sg:classifiers":[
        {
            "category":"Personal",
            "subcategory":"Beauty Salon",
            "type":"Services"
        }
    ],
    "sg:postcode":"WR15 8AE",
    "sg:province":"Herefordshire",
    "sg:tags":[
        "unisex",
        "hairdresser"
    ],
    "wof:name":"Soap Opera",
    "wof:placetype":"venue"
},
  "geometry": {"coordinates":[-2.594708,52.313217],"type":"Point"}
}