{
  "type": "Feature",
  "properties": {
    "iso:country":"GB",
    "sg:address":"4 Butts Court",
    "sg:city":"Leeds",
    "sg:classifiers":[
        {
            "category":"Real Estate",
            "subcategory":"Architect",
            "type":"Services"
        }
    ],
    "sg:phone":"+44 113 242 8282",
    "sg:postcode":"LS1 5JS",
    "sg:province":"West Yorkshire",
    "wof:name":"Frank Turner",
    "wof:placetype":"venue"
},
  "geometry": {"coordinates":[-1.5458010435,53.7994117737],"type":"Point"}
}