{
  "type": "Feature",
  "properties": {
    "addr:full":"6 Merstow Grn Evesham Gloucestershire WR11 4BD",
    "addr:housenumber":"6",
    "addr:postcode":"wr11 4bd",
    "addr:street":"Merstow Grn",
    "iso:country":"GB",
    "sg:address":"6 Merstow Grn",
    "sg:city":"Evesham",
    "sg:classifiers":[
        {
            "category":"Professional",
            "subcategory":"Advertising",
            "type":"Services"
        },
        {
            "category":"Professional",
            "subcategory":"Art Services",
            "type":"Services"
        }
    ],
    "sg:postcode":"WR11 4BD",
    "sg:province":"Gloucestershire",
    "sg:tags":[
        "graphic",
        "agency",
        "designer"
    ],
    "wof:name":"Bryon,Michael J,",
    "wof:placetype":"venue"
},
  "geometry": {"coordinates":[-1.950298,52.091885],"type":"Point"}
}