{
  "type": "Feature",
  "properties": {
    "iso:country":"GB",
    "sg:address":"Balfour House, 399 Street Lane",
    "sg:city":"Leeds",
    "sg:classifiers":[
        {
            "category":"Organizations",
            "subcategory":"Non-profit Organization",
            "type":"Services"
        }
    ],
    "sg:phone":"+44 113 269 3136",
    "sg:postcode":"LS17 6HQ",
    "sg:province":"North Yorkshire",
    "sg:tags":[
        "organisation",
        "voluntary",
        "charity"
    ],
    "wof:name":"J.I.A.",
    "wof:placetype":"venue"
},
  "geometry": {"coordinates":[-1.528202,53.843712],"type":"Point"}
}