{
  "type": "Feature",
  "properties": {
    "iso:country":"GB",
    "sg:address":"South Hill, Whixley",
    "sg:city":"York",
    "sg:classifiers":[
        {
            "category":"Travel",
            "subcategory":"Travel Agent",
            "type":"Entertainment"
        },
        {
            "category":"Recreation",
            "subcategory":"Gun Range",
            "type":"Entertainment"
        }
    ],
    "sg:phone":"+44 1423 330533",
    "sg:postcode":"YO26 8AT",
    "sg:province":"North Yorkshire",
    "sg:tags":[
        "operator",
        "tour"
    ],
    "wof:name":"Art Study Tours Ltd",
    "wof:placetype":"venue"
},
  "geometry": {"coordinates":[-1.327428,54.016209],"type":"Point"}
}