{
  "type": "Feature",
  "properties": {
    "iso:country":"GB",
    "sg:address":"49 Witherford Way",
    "sg:city":"Birmingham",
    "sg:classifiers":[
        {
            "category":"Government",
            "subcategory":"Post Office",
            "type":"Public Place"
        }
    ],
    "sg:phone":"+44 121 472 0056",
    "sg:postcode":"B29 4AY",
    "sg:province":"West Midlands",
    "wof:name":"Weoley Hill Post Office",
    "wof:placetype":"venue"
},
  "geometry": {"coordinates":[-1.951328,52.43269],"type":"Point"}
}