{
  "type": "Feature",
  "properties": {
    "addr:full":"89 Quicks Road London Greater London SW19 1EX",
    "addr:housenumber":"89",
    "addr:postcode":"sw19 1ex",
    "addr:street":"Quicks Road",
    "iso:country":"GB",
    "sg:address":"89 Quicks Road",
    "sg:city":"London",
    "sg:classifiers":[
        {
            "category":"Farming",
            "subcategory":"Nursery",
            "type":"Manufacturing & Wholesale Goods"
        }
    ],
    "sg:phone":"+44 20 8545 0699",
    "sg:postcode":"SW19 1EX",
    "sg:province":"Greater London",
    "sg:tags":[
        "creche"
    ],
    "wof:name":"The Eveline Day Nursery Schools Ltd.",
    "wof:placetype":"venue"
},
  "geometry": {"coordinates":[-0.191773,51.418797],"type":"Point"}
}