{
  "type": "Feature",
  "properties": {
    "addr:full":"88 Main Road Northampton Buckinghamshire NN7 2AD",
    "addr:housenumber":"88",
    "addr:postcode":"nn7 2ad",
    "addr:street":"Main Road",
    "iso:country":"GB",
    "sg:address":"88 Main Road",
    "sg:city":"Northampton",
    "sg:classifiers":[
        {
            "category":"Food & Beverages",
            "subcategory":"Fruits & Vegetables",
            "type":"Retail Goods"
        },
        {
            "category":"Education",
            "subcategory":"School",
            "type":"Public Place"
        }
    ],
    "sg:postcode":"NN7 2AD",
    "sg:province":"Buckinghamshire",
    "sg:tags":[
        "greengrocer",
        "local",
        "authority"
    ],
    "wof:name":"Hackleton Stores",
    "wof:placetype":"venue"
},
  "geometry": {"coordinates":[-0.8196730018,52.1871261597],"type":"Point"}
}