{
  "type": "Feature",
  "properties": {
    "iso:country":"GB",
    "sg:address":"Ashgrove, Blackburn",
    "sg:city":"Bathgate",
    "sg:classifiers":[
        {
            "category":"Education",
            "subcategory":"University",
            "type":"Public Place"
        },
        {
            "category":"Government",
            "subcategory":"Office",
            "type":"Public Place"
        }
    ],
    "sg:phone":"+44 1506 653014",
    "sg:postcode":"EH47 7LJ",
    "sg:province":"North Lanarkshire",
    "sg:tags":[
        "local",
        "adult"
    ],
    "wof:name":"Blackburn Community Centre",
    "wof:placetype":"venue"
},
  "geometry": {"coordinates":[-3.624277,55.875298],"type":"Point"}
}