{
  "type": "Feature",
  "properties": {
    "addr:full":"99 Regent Street London Greater London W1R 7HB",
    "addr:housenumber":"99",
    "addr:postcode":"w1r 7hb",
    "addr:street":"Regent Street",
    "iso:country":"GB",
    "sg:address":"99 Regent Street",
    "sg:city":"London",
    "sg:classifiers":[
        {
            "category":"Personal",
            "type":"Services"
        },
        {
            "category":"Manufacturing",
            "subcategory":"Textiles",
            "type":"Manufacturing & Wholesale Goods"
        }
    ],
    "sg:phone":"+44 20 7734 0833",
    "sg:postcode":"W1R 7HB",
    "sg:province":"Greater London",
    "sg:tags":[
        "merchant",
        "tailor",
        "agent"
    ],
    "wof:name":"Tudorcraft Ltd.",
    "wof:placetype":"venue"
},
  "geometry": {"coordinates":[-0.137622,51.509968],"type":"Point"}
}