{
  "type": "Feature",
  "properties": {
    "addr:full":"173 The Broadway, Thorpe Bay Southend-on-sea Essex SS1 3EX",
    "addr:housenumber":"173",
    "addr:postcode":"ss1 3ex",
    "addr:street":"The Broadway",
    "iso:country":"GB",
    "sg:address":"173 The Broadway, Thorpe Bay",
    "sg:city":"Southend-on-sea",
    "sg:classifiers":[
        {
            "category":"Food & Beverages",
            "subcategory":"Bakery",
            "type":"Retail Goods"
        }
    ],
    "sg:phone":"+44 1702 588400",
    "sg:postcode":"SS1 3EX",
    "sg:province":"Essex",
    "sg:tags":[
        "baker"
    ],
    "wof:name":"The Breadwinner",
    "wof:placetype":"venue"
},
  "geometry": {"coordinates":[0.7609770298,51.5363006592],"type":"Point"}
}