{
  "type": "Feature",
  "properties": {
    "addr:full":"42 Cannon Lane Pinner Greater London HA5 1HW",
    "addr:housenumber":"42",
    "addr:postcode":"ha5 1hw",
    "addr:street":"Cannon Lane",
    "iso:country":"GB",
    "sg:address":"42 Cannon Lane",
    "sg:city":"Pinner",
    "sg:classifiers":[
        {
            "category":"Building & Trades",
            "subcategory":"Plumbing",
            "type":"Services"
        }
    ],
    "sg:phone":"+44 20 8357 7000",
    "sg:postcode":"HA5 1HW",
    "sg:province":"Greater London",
    "sg:tags":[
        "repair",
        "heating",
        "servicing",
        "boiler"
    ],
    "wof:name":"Goff & Crawford Ltd",
    "wof:placetype":"venue"
},
  "geometry": {"coordinates":[-0.38175,51.586624],"type":"Point"}
}