{
  "type": "Feature",
  "properties": {
    "addr:full":"Unit 4 Tamar Square Daventry Northamptonshire NN11 4RB",
    "addr:housenumber":"unit 4",
    "addr:postcode":"nn11 4rb",
    "addr:street":"Tamar Square",
    "iso:country":"GB",
    "sg:address":"Unit 4 Tamar Square",
    "sg:city":"Daventry",
    "sg:classifiers":[
        {
            "category":"Retail",
            "subcategory":"Laundry & Dry Cleaning",
            "type":"Services"
        }
    ],
    "sg:phone":"+44 1327 877267",
    "sg:postcode":"NN11 4RB",
    "sg:province":"Northamptonshire",
    "sg:tags":[
        "launderette"
    ],
    "wof:name":"D & D Launderette",
    "wof:placetype":"venue"
},
  "geometry": {"coordinates":[-1.179164052,52.2541542053],"type":"Point"}
}