{
  "type": "Feature",
  "properties": {
    "addr:full":"2a & 2b Kingsley Avenue, Altwood Wakefield West Yorkshire WF1 2LA",
    "addr:housenumber":"2a & 2b",
    "addr:postcode":"wf1 2la",
    "addr:street":"Kingsley Avenue Altwood",
    "iso:country":"GB",
    "sg:address":"2a & 2b Kingsley Avenue, Altwood",
    "sg:city":"Wakefield",
    "sg:classifiers":[
        {
            "category":"Social Services",
            "subcategory":"Job Training",
            "type":"Services"
        },
        {
            "category":"Personal",
            "subcategory":"Nail Salon",
            "type":"Services"
        }
    ],
    "sg:phone":"+44 1924 871770",
    "sg:postcode":"WF1 2LA",
    "sg:province":"West Yorkshire",
    "sg:tags":[
        "solarium",
        "tanning",
        "related",
        "activity"
    ],
    "wof:name":"Tanfastique",
    "wof:placetype":"venue"
},
  "geometry": {"coordinates":[-1.5059330463,53.71352005],"type":"Point"}
}