{
  "type": "Feature",
  "properties": {
    "addr:full":"Fulham Place, Bishops Avenue London Greater London SW6 6EA",
    "addr:postcode":"sw6 6ea",
    "addr:street":"Fulham Place Bishops Avenue",
    "iso:country":"GB",
    "sg:address":"Fulham Place, Bishops Avenue",
    "sg:city":"London",
    "sg:classifiers":[
        {
            "category":"Wholesale",
            "subcategory":"Music Publishers",
            "type":"Manufacturing & Wholesale Goods"
        }
    ],
    "sg:phone":"+44 20 7800 4400",
    "sg:postcode":"SW6 6EA",
    "sg:province":"Greater London",
    "sg:tags":[
        "record"
    ],
    "wof:name":"Go Beat Ltd.",
    "wof:placetype":"venue"
},
  "geometry": {"coordinates":[-0.218751,51.482582],"type":"Point"}
}