{
  "type": "Feature",
  "properties": {
    "addr:full":"107-109 Stoke Newington High Street London Greater London N16 0PH",
    "addr:housenumber":"107-109",
    "addr:postcode":"n16 0ph",
    "addr:street":"Stoke Newington High Street",
    "iso:country":"GB",
    "sg:address":"107-109 Stoke Newington High Street",
    "sg:city":"London",
    "sg:classifiers":[
        {
            "category":"Shopping",
            "subcategory":"Shoes",
            "type":"Retail Goods"
        }
    ],
    "sg:phone":"+44 20 7254 7131",
    "sg:postcode":"N16 0PH",
    "sg:province":"Greater London",
    "sg:tags":[
        "shop",
        "retailer",
        "footwear"
    ],
    "wof:name":"Shoefayre Ltd",
    "wof:placetype":"venue"
},
  "geometry": {"coordinates":[-0.074253,51.560051],"type":"Point"}
}