{
  "type": "Feature",
  "properties": {
    "iso:country":"GB",
    "sg:address":"The Beneficial Centre, Eastern Road",
    "sg:city":"Portsmouth",
    "sg:classifiers":[
        {
            "category":"Education",
            "subcategory":"Special Training",
            "type":"Public Place"
        }
    ],
    "sg:phone":"+44 23 9261 0170",
    "sg:postcode":"PO3 6EP",
    "sg:province":"Hampshire",
    "sg:tags":[
        "product",
        "centre"
    ],
    "wof:name":"Beneficial Foundation The",
    "wof:placetype":"venue"
},
  "geometry": {"coordinates":[-1.05259,50.80233],"type":"Point"}
}