{
  "type": "Feature",
  "properties": {
    "iso:country":"GB",
    "sg:address":"1803 London Rd",
    "sg:city":"Leigh-on-sea",
    "sg:classifiers":[
        {
            "category":"Building & Trades",
            "subcategory":"Construction",
            "type":"Services"
        }
    ],
    "sg:postcode":"SS9 2ST",
    "sg:province":"Essex",
    "sg:tags":[
        "builder"
    ],
    "wof:name":"K.M.H Construction Ltd",
    "wof:placetype":"venue"
},
  "geometry": {"coordinates":[0.628912,51.548756],"type":"Point"}
}