{
  "type": "Feature",
  "properties": {
    "addr:full":"21 Station App Virginia Water Surrey GU25 4DW",
    "addr:housenumber":"21;app",
    "addr:postcode":"gu25 4dw",
    "addr:street":"Station",
    "iso:country":"GB",
    "sg:address":"21 Station App",
    "sg:city":"Virginia Water",
    "sg:classifiers":[
        {
            "category":"Professional",
            "type":"Services"
        }
    ],
    "sg:postcode":"GU25 4DW",
    "sg:province":"Surrey",
    "sg:tags":[
        "auctioneer"
    ],
    "wof:name":"Wentworth Auction Galleries",
    "wof:placetype":"venue"
},
  "geometry": {"coordinates":[-0.5676599741,51.4033737183],"type":"Point"}
}