{
  "type": "Feature",
  "properties": {
    "iso:country":"GB",
    "sg:address":"23 City Road",
    "sg:city":"Chester",
    "sg:classifiers":[
        {
            "category":"Shopping",
            "subcategory":"Bicycles & Sporting Goods",
            "type":"Retail Goods"
        },
        {
            "category":"Arts & Performance",
            "subcategory":"Theater",
            "type":"Entertainment"
        }
    ],
    "sg:phone":"+44 1244 320271",
    "sg:postcode":"CH1 3AE",
    "sg:province":"Cheshire",
    "sg:tags":[
        "dance",
        "dancewear",
        "ballet",
        "balletwear"
    ],
    "wof:name":"Artistes Theatre Shop",
    "wof:placetype":"venue"
},
  "geometry": {"coordinates":[-2.882001,53.193146],"type":"Point"}
}