{
  "type": "Feature",
  "properties": {
    "iso:country":"GB",
    "sg:address":"Drayton Mill, Drayton Near Belbroughton",
    "sg:city":"Worcester",
    "sg:classifiers":[
        {
            "category":"Shopping",
            "subcategory":"Musical Instruments",
            "type":"Retail Goods"
        },
        {
            "category":"Transit Center",
            "subcategory":"Freight",
            "type":"Transportation"
        },
        {
            "category":"Education",
            "subcategory":"Library",
            "type":"Public Place"
        }
    ],
    "sg:phone":"+44 1562 731113",
    "sg:postcode":"DY9 0BT",
    "sg:province":"West Midlands",
    "sg:tags":[
        "sheet",
        "retailer",
        "accessory",
        "music",
        "reproduction",
        "piano",
        "furniture"
    ],
    "wof:name":"BROUGHTON PIANOS LTD",
    "wof:placetype":"venue"
},
  "geometry": {"coordinates":[-2.13878,52.382408],"type":"Point"}
}