{
  "type": "Feature",
  "properties": {
    "iso:country":"GB",
    "sg:address":"Unit 2 Zetland Buildings, Longbeck Estate, Marske-by-the-sea",
    "sg:city":"Redcar",
    "sg:classifiers":[
        {
            "category":"Building & Trades",
            "subcategory":"Construction",
            "type":"Services"
        },
        {
            "category":"Manufacturing",
            "subcategory":"Building Materials",
            "type":"Manufacturing & Wholesale Goods"
        }
    ],
    "sg:phone":"+44 1642 479166",
    "sg:postcode":"TS11 6HB",
    "sg:province":"North Yorkshire",
    "sg:tags":[
        "merchant",
        "builder"
    ],
    "wof:name":"H & W Building & D I Y Supplies",
    "wof:placetype":"venue"
},
  "geometry": {"coordinates":[-1.019694,54.592369],"type":"Point"}
}