{
  "type": "Feature",
  "properties": {
    "iso:country":"GB",
    "sg:address":"93 Burnham La",
    "sg:city":"Slough",
    "sg:classifiers":[
        {
            "category":"Building & Trades",
            "subcategory":"Construction",
            "type":"Services"
        }
    ],
    "sg:phone":"+44 1628 604729",
    "sg:postcode":"SL1 6JY",
    "sg:province":"Berkshire",
    "sg:tags":[
        "builder"
    ],
    "wof:name":"R D Cottington",
    "wof:placetype":"venue"
},
  "geometry": {"coordinates":[-0.6477829814,51.5262107849],"type":"Point"}
}