{
  "type": "Feature",
  "properties": {
    "addr:full":"Capitol Shopping Centre, Queen Street Cardiff Cardiff CF10 2HQ",
    "addr:postcode":"cf10 2hq",
    "addr:street":"Queen Street",
    "iso:country":"GB",
    "sg:address":"Capitol Shopping Centre, Queen Street",
    "sg:city":"Cardiff",
    "sg:classifiers":[
        {
            "category":"Shopping",
            "subcategory":"Clothing, Apparel, & Fashions",
            "type":"Retail Goods"
        }
    ],
    "sg:postcode":"CF10 2HQ",
    "sg:province":"Cardiff",
    "sg:tags":[
        "shop"
    ],
    "wof:name":"Hudson & Hudson Ltd.",
    "wof:placetype":"venue"
},
  "geometry": {"coordinates":[-3.180669,51.481258],"type":"Point"}
}