{
  "type": "Feature",
  "properties": {
    "iso:country":"GB",
    "sg:address":"130-134 High Street",
    "sg:city":"Solihull",
    "sg:classifiers":[
        {
            "category":"Professional",
            "subcategory":"Management & Consulting",
            "type":"Services"
        }
    ],
    "sg:phone":"+44 121 704 4334",
    "sg:postcode":"B91 3SX",
    "sg:province":"West Midlands",
    "sg:tags":[
        "consultant",
        "business"
    ],
    "wof:name":"Sterling Management Consultants Ltd.",
    "wof:placetype":"venue"
},
  "geometry": {"coordinates":[-1.7773740292,52.4124221802],"type":"Point"}
}