{
  "type": "Feature",
  "properties": {
    "iso:country":"GB",
    "sg:address":"Vicarage, Comp La",
    "sg:city":"Sevenoaks",
    "sg:classifiers":[
        {
            "category":"Place Of Worship",
            "type":"Public Place"
        }
    ],
    "sg:phone":"+44 1732 885482",
    "sg:postcode":"TN15 8NR",
    "sg:province":"Kent",
    "wof:name":"St Mary The Virgin C Of E Church",
    "wof:placetype":"venue"
},
  "geometry": {"coordinates":[0.32731,51.287689],"type":"Point"}
}