{
  "type": "Feature",
  "properties": {
    "iso:country":"GB",
    "sg:address":"Unit 1, Redkiln Close",
    "sg:city":"Horsham",
    "sg:classifiers":[
        {
            "category":"Banks & Credit Unions",
            "subcategory":"Investment Brokerage",
            "type":"Services"
        },
        {
            "category":"Building & Trades",
            "subcategory":"Construction",
            "type":"Services"
        }
    ],
    "sg:phone":"+44 1403 218877",
    "sg:postcode":"RH13 5QL",
    "sg:province":"West Sussex",
    "sg:tags":[
        "supplier",
        "installers",
        "cladding",
        "contractor"
    ],
    "wof:name":"Way P V C - U Supplies",
    "wof:placetype":"venue"
},
  "geometry": {"coordinates":[-0.30816,51.070572],"type":"Point"}
}