{
  "type": "Feature",
  "properties": {
    "iso:country":"GB",
    "sg:address":"2 Drumlanrig Sq",
    "sg:city":"Hawick",
    "sg:classifiers":[
        {
            "category":"Fast Food",
            "type":"Food & Drink"
        }
    ],
    "sg:phone":"+44 1450 370600",
    "sg:postcode":"TD9 0AS",
    "sg:province":"Cumbria",
    "sg:tags":[
        "away",
        "take"
    ],
    "wof:name":"Ming Palace The",
    "wof:placetype":"venue"
},
  "geometry": {"coordinates":[-2.790125,55.420429],"type":"Point"}
}