{
  "type": "Feature",
  "properties": {
    "addr:full":"Selly Oak Road Birmingham West Midlands B30 1HW",
    "addr:postcode":"b30 1hw",
    "addr:street":"Selly Oak Road",
    "iso:country":"GB",
    "sg:address":"Selly Oak Road",
    "sg:city":"Birmingham",
    "sg:classifiers":[
        {
            "category":"Education",
            "subcategory":"School",
            "type":"Public Place"
        }
    ],
    "sg:phone":"+44 121 458 1305",
    "sg:postcode":"B30 1HW",
    "sg:province":"West Midlands",
    "sg:tags":[
        "college"
    ],
    "wof:name":"Kings Norton Girls School",
    "wof:placetype":"venue"
},
  "geometry": {"coordinates":[-1.9397809505,52.4263572693],"type":"Point"}
}