{
  "type": "Feature",
  "properties": {
    "addr:full":"102 Hough Lane Preston Lancashire PR25 2YB",
    "addr:housenumber":"102",
    "addr:postcode":"pr25 2yb",
    "addr:street":"Hough Lane",
    "iso:country":"GB",
    "sg:address":"102 Hough Lane",
    "sg:city":"Preston",
    "sg:classifiers":[
        {
            "category":"Shopping",
            "subcategory":"Gifts & Souvenirs",
            "type":"Retail Goods"
        }
    ],
    "sg:phone":"+44 1772 455510",
    "sg:postcode":"PR25 2YB",
    "sg:province":"Lancashire",
    "sg:tags":[
        "shop"
    ],
    "wof:name":"Fairport",
    "wof:placetype":"venue"
},
  "geometry": {"coordinates":[-2.6913399696,53.695930481],"type":"Point"}
}