{
  "type": "Feature",
  "properties": {
    "iso:country":"GB",
    "sg:address":"26 Main Street, Cossington",
    "sg:city":"Leicester",
    "sg:classifiers":[
        {
            "category":"Building & Trades",
            "subcategory":"Plumbing",
            "type":"Services"
        }
    ],
    "sg:postcode":"LE7 4UU",
    "sg:province":"Leicestershire",
    "sg:tags":[
        "heating"
    ],
    "wof:name":"Cooper Stevie Plumbing & Heating Contractor",
    "wof:placetype":"venue"
},
  "geometry": {"coordinates":[-1.105366,52.719376],"type":"Point"}
}