{
  "type": "Feature",
  "properties": {
    "addr:full":"43 Grant Rd, Farlington Portsmouth Hampshire PO6 1DU",
    "addr:housenumber":"43",
    "addr:postcode":"hampshire po6 1du",
    "addr:street":"Grant Rd",
    "iso:country":"GB",
    "sg:address":"43 Grant Rd, Farlington",
    "sg:city":"Portsmouth",
    "sg:classifiers":[
        {
            "category":"Shopping",
            "subcategory":"Bicycles & Sporting Goods",
            "type":"Retail Goods"
        }
    ],
    "sg:postcode":"PO6 1DU",
    "sg:province":"Hampshire",
    "sg:tags":[
        "cycle",
        "accessory"
    ],
    "wof:name":"Allintex Ltd",
    "wof:placetype":"venue"
},
  "geometry": {"coordinates":[-1.034082,50.849491],"type":"Point"}
}