{
  "type": "Feature",
  "properties": {
    "iso:country":"GB",
    "sg:address":"Pen Y Maes, Brookhouse",
    "sg:city":"Denbigh",
    "sg:classifiers":[
        {
            "category":"Farming",
            "subcategory":"Livestock Farm",
            "type":"Manufacturing & Wholesale Goods"
        },
        {
            "category":"Farming",
            "subcategory":"Farm",
            "type":"Manufacturing & Wholesale Goods"
        }
    ],
    "sg:phone":"+44 1745 812197",
    "sg:postcode":"LL16 4RD",
    "sg:province":"Conwy",
    "sg:tags":[
        "mixed",
        "crop",
        "others"
    ],
    "wof:name":"Edward H Ames",
    "wof:placetype":"venue"
},
  "geometry": {"coordinates":[-3.396914959,53.1805877686],"type":"Point"}
}