{
  "type": "Feature",
  "properties": {
    "addr:full":"98 Jardine Crescent Coventry Warwickshire CV4 9PP",
    "addr:housenumber":"98",
    "addr:postcode":"cv4 9pp",
    "addr:street":"Jardine Crescent",
    "iso:country":"GB",
    "sg:address":"98 Jardine Crescent",
    "sg:city":"Coventry",
    "sg:classifiers":[
        {
            "category":"Shopping",
            "subcategory":"Bicycles & Sporting Goods",
            "type":"Retail Goods"
        }
    ],
    "sg:phone":"+44 24 7646 0880",
    "sg:postcode":"CV4 9PP",
    "sg:province":"Warwickshire",
    "sg:tags":[
        "shop",
        "cycle",
        "accessory"
    ],
    "wof:name":"Jardine Cycles",
    "wof:placetype":"venue"
},
  "geometry": {"coordinates":[-1.5787030458,52.4066123962],"type":"Point"}
}