{
  "type": "Feature",
  "properties": {
    "iso:country":"GB",
    "sg:address":"13 Elder St",
    "sg:city":"Glasgow",
    "sg:classifiers":[
        {
            "category":"Farming",
            "subcategory":"Dairy Farm",
            "type":"Manufacturing & Wholesale Goods"
        }
    ],
    "sg:postcode":"G51 3DY",
    "sg:province":"Glasgow City",
    "wof:name":"Fairfield Dairy",
    "wof:placetype":"venue"
},
  "geometry": {"coordinates":[-4.318735,55.86433],"type":"Point"}
}