{
  "type": "Feature",
  "properties": {
    "addr:full":"62 Downs Park Herne Bay Kent CT6 6BZ",
    "addr:housenumber":"62",
    "addr:postcode":"ct6 6bz",
    "addr:street":"Downs Park Herne",
    "iso:country":"GB",
    "sg:address":"62 Downs Park",
    "sg:city":"Herne Bay",
    "sg:classifiers":[
        {
            "category":"Retail",
            "subcategory":"Storage",
            "type":"Services"
        }
    ],
    "sg:phone":"+44 1227 372542",
    "sg:postcode":"CT6 6BZ",
    "sg:province":"Kent",
    "sg:tags":[
        "household",
        "removal"
    ],
    "wof:name":"Burchett Removals",
    "wof:placetype":"venue"
},
  "geometry": {"coordinates":[1.1370099783,51.3677711487],"type":"Point"}
}