{
  "type": "Feature",
  "properties": {
    "addr:full":"41 Fife Rd Kingston Upon Thames Greater London KT1 1SF",
    "addr:housenumber":"41",
    "addr:postcode":"kt1 1sf",
    "addr:street":"Fife Rd",
    "iso:country":"GB",
    "sg:address":"41 Fife Rd",
    "sg:city":"Kingston Upon Thames",
    "sg:classifiers":[
        {
            "category":"Personal",
            "type":"Services"
        },
        {
            "category":"Professional",
            "subcategory":"Lawyer & Legal Services",
            "type":"Services"
        }
    ],
    "sg:phone":"+44 20 8549 3318",
    "sg:postcode":"KT1 1SF",
    "sg:province":"Greater London",
    "sg:tags":[
        "advice",
        "counselling"
    ],
    "wof:name":"Relate",
    "wof:placetype":"venue"
},
  "geometry": {"coordinates":[-0.301826,51.412052],"type":"Point"}
}