{
  "type": "Feature",
  "properties": {
    "iso:country":"GB",
    "sg:address":"301 Aston Lane",
    "sg:city":"Birmingham",
    "sg:classifiers":[
        {
            "category":"Manufacturing",
            "subcategory":"Wood Products",
            "type":"Manufacturing & Wholesale Goods"
        }
    ],
    "sg:phone":"+44 121 356 1779",
    "sg:postcode":"B6 6QR",
    "sg:province":"West Midlands",
    "sg:tags":[
        "packaging",
        "crate",
        "pallets"
    ],
    "wof:name":"Pallet Recycling",
    "wof:placetype":"venue"
},
  "geometry": {"coordinates":[-1.887368,52.512482],"type":"Point"}
}