{
  "type": "Feature",
  "properties": {
    "iso:country":"GB",
    "sg:address":"Inatween, Great Ormside",
    "sg:city":"Appleby-in-westmorland",
    "sg:classifiers":[
        {
            "category":"Freight",
            "type":"Transportation"
        }
    ],
    "sg:postcode":"CA16 6EJ",
    "sg:province":"Cumbria",
    "sg:tags":[
        "haulage",
        "road"
    ],
    "wof:name":"R & J Bainbridge",
    "wof:placetype":"venue"
},
  "geometry": {"coordinates":[-2.48743,54.577309],"type":"Point"}
}