{
  "type": "Feature",
  "properties": {
    "addr:full":"6 Coventry Road, Narborough Leicester Leicestershire LE19 2GR",
    "addr:housenumber":"6",
    "addr:postcode":"le19 2gr",
    "addr:street":"Coventry Road",
    "iso:country":"GB",
    "sg:address":"6 Coventry Road, Narborough",
    "sg:city":"Leicester",
    "sg:classifiers":[
        {
            "category":"Travel",
            "subcategory":"Hotels & Motels",
            "type":"Entertainment"
        },
        {
            "category":"Community Center",
            "subcategory":"Social",
            "type":"Public Place"
        }
    ],
    "sg:phone":"+44 116 284 8212",
    "sg:postcode":"LE19 2GR",
    "sg:province":"Leicestershire",
    "sg:tags":[
        "house",
        "activity"
    ],
    "wof:name":"The Narborough Arms Hotel",
    "wof:placetype":"venue"
},
  "geometry": {"coordinates":[-1.204968,52.571751],"type":"Point"}
}