{
  "type": "Feature",
  "properties": {
    "iso:country":"GB",
    "sg:address":"Mains Of Pittendreich",
    "sg:city":"Turriff",
    "sg:classifiers":[
        {
            "category":"Farming",
            "subcategory":"Farm",
            "type":"Manufacturing & Wholesale Goods"
        }
    ],
    "sg:phone":"+44 1466 780288",
    "sg:postcode":"AB53 4LE",
    "sg:province":"Aberdeenshire",
    "sg:tags":[
        "mixed",
        "crop"
    ],
    "wof:name":"Stephen A Duncan",
    "wof:placetype":"venue"
},
  "geometry": {"coordinates":[-2.455229,57.539902],"type":"Point"}
}