{
  "type": "Feature",
  "properties": {
    "addr:full":"1 Hamilton Street Girvan South Ayrshire KA26 9EY",
    "addr:housenumber":"1",
    "addr:postcode":"ka26 9ey",
    "addr:street":"Hamilton Street",
    "iso:country":"GB",
    "sg:address":"1 Hamilton Street",
    "sg:city":"Girvan",
    "sg:classifiers":[
        {
            "category":"Professional",
            "subcategory":"Lawyer & Legal Services",
            "type":"Services"
        }
    ],
    "sg:phone":"+44 1465 715434",
    "sg:postcode":"KA26 9EY",
    "sg:province":"South Ayrshire",
    "sg:tags":[
        "solicitor"
    ],
    "wof:name":"Alistair Lambert",
    "wof:placetype":"venue"
},
  "geometry": {"coordinates":[-4.855392,55.243378],"type":"Point"}
}