{
  "type": "Feature",
  "properties": {
    "addr:full":"43-45 High St Mexborough South Yorkshire S64 9AB",
    "addr:housenumber":"43-45",
    "addr:postcode":"s64 9ab",
    "addr:street":"High St",
    "iso:country":"GB",
    "sg:address":"43-45 High St",
    "sg:city":"Mexborough",
    "sg:classifiers":[
        {
            "category":"Shopping",
            "subcategory":"Gifts & Souvenirs",
            "type":"Retail Goods"
        }
    ],
    "sg:phone":"+44 1709 582275",
    "sg:postcode":"S64 9AB",
    "sg:province":"South Yorkshire",
    "sg:tags":[
        "poster",
        "card"
    ],
    "wof:name":"Supercigs",
    "wof:placetype":"venue"
},
  "geometry": {"coordinates":[-1.2902859449,53.4934501648],"type":"Point"}
}