{
  "type": "Feature",
  "properties": {
    "addr:full":"Kemp House Wokingham Berkshire RG41 5JH",
    "addr:postcode":"rg41 5jh",
    "iso:country":"GB",
    "sg:address":"Kemp House",
    "sg:city":"Wokingham",
    "sg:classifiers":[
        {
            "category":"Education",
            "subcategory":"Special Training",
            "type":"Public Place"
        }
    ],
    "sg:phone":"+44 118 977 5036",
    "sg:postcode":"RG41 5JH",
    "sg:province":"Berkshire",
    "sg:tags":[
        "product",
        "centre"
    ],
    "wof:name":"Healthscope (U K) Ltd.",
    "wof:placetype":"venue"
},
  "geometry": {"coordinates":[-0.881599009,51.4333381653],"type":"Point"}
}