{
  "type": "Feature",
  "properties": {
    "iso:country":"GB",
    "sg:address":"44 Darwen Street",
    "sg:city":"Blackburn",
    "sg:classifiers":[
        {
            "category":"Insurance",
            "subcategory":"Insurance Agent",
            "type":"Services"
        }
    ],
    "sg:phone":"+44 1254 680243",
    "sg:postcode":"BB2 2BH",
    "sg:province":"Lancashire",
    "wof:name":"DEANSGATE INSURANCE SERVICES LTD",
    "wof:placetype":"venue"
},
  "geometry": {"coordinates":[-2.4826860428,53.7463340759],"type":"Point"}
}