{
  "type": "Feature",
  "properties": {
    "addr:full":"108 Carlton Road Lowestoft Suffolk NR33 0NB",
    "addr:housenumber":"108",
    "addr:postcode":"nr33 0nb",
    "addr:street":"Carlton Road",
    "iso:country":"GB",
    "sg:address":"108 Carlton Road",
    "sg:city":"Lowestoft",
    "sg:classifiers":[
        {
            "category":"Bars & Pubs",
            "type":"Food & Drink"
        }
    ],
    "sg:phone":"+44 1502 573727",
    "sg:postcode":"NR33 0NB",
    "sg:province":"Suffolk",
    "sg:tags":[
        "pubs",
        "inn"
    ],
    "wof:name":"The Morning Star",
    "wof:placetype":"venue"
},
  "geometry": {"coordinates":[1.7369589806,52.4646110535],"type":"Point"}
}