{
  "type": "Feature",
  "properties": {
    "addr:full":"123 Baker St Enfield Greater London EN1 3HA",
    "addr:housenumber":"123",
    "addr:postcode":"en1 3ha",
    "addr:street":"Baker St",
    "iso:country":"GB",
    "sg:address":"123 Baker St",
    "sg:city":"Enfield",
    "sg:classifiers":[
        {
            "category":"Building & Trades",
            "subcategory":"Construction",
            "type":"Services"
        }
    ],
    "sg:phone":"+44 20 8364 6611",
    "sg:postcode":"EN1 3HA",
    "sg:province":"Greater London",
    "sg:tags":[
        "builder"
    ],
    "wof:name":"Romark Construction Ltd",
    "wof:placetype":"venue"
},
  "geometry": {"coordinates":[-0.0798240006,51.6581802368],"type":"Point"}
}