{
  "type": "Feature",
  "properties": {
    "iso:country":"GB",
    "sg:address":"19 St Annes Lane, Godmanchester",
    "sg:city":"Huntingdon",
    "sg:classifiers":[
        {
            "category":"Health Services",
            "subcategory":"Doctor",
            "type":"Services"
        }
    ],
    "sg:postcode":"PE29 2JE",
    "sg:province":"Cambridgeshire",
    "sg:tags":[
        "practitioners"
    ],
    "wof:name":"R K Gupta",
    "wof:placetype":"venue"
},
  "geometry": {"coordinates":[-0.171025,52.3186],"type":"Point"}
}