{
  "type": "Feature",
  "properties": {
    "iso:country":"GB",
    "sg:address":"13 Kelburn St",
    "sg:city":"Millport",
    "sg:classifiers":[
        {
            "category":"Cafe",
            "type":"Food & Drink"
        }
    ],
    "sg:postcode":"KA28 0DT",
    "sg:province":"North Ayrshire",
    "sg:tags":[
        "tea",
        "room"
    ],
    "wof:name":"Diamond,Margaret,",
    "wof:placetype":"venue"
},
  "geometry": {"coordinates":[-4.9187269211,55.7548713684],"type":"Point"}
}