{
  "type": "Feature",
  "properties": {
    "addr:full":"15-16 Front Street, Framwellgate Moor Durham Durham DH1 5EJ",
    "addr:housenumber":"15-16",
    "addr:postcode":"dh1 5ej",
    "addr:street":"Front Street",
    "iso:country":"GB",
    "sg:address":"15-16 Front Street, Framwellgate Moor",
    "sg:city":"Durham",
    "sg:classifiers":[
        {
            "category":"Personal",
            "subcategory":"Beauty Salon",
            "type":"Services"
        },
        {
            "category":"Personal",
            "subcategory":"Barber",
            "type":"Services"
        }
    ],
    "sg:phone":"+44 191 386 5544",
    "sg:postcode":"DH1 5EJ",
    "sg:province":"Durham",
    "sg:tags":[
        "unisex",
        "hairdresser"
    ],
    "wof:name":"Brown's Hair Salons",
    "wof:placetype":"venue"
},
  "geometry": {"coordinates":[-1.590473,54.7948],"type":"Point"}
}