{
  "type": "Feature",
  "properties": {
    "addr:full":"Unit B, Belgrave Business Centre Leicester Leicestershire LE4 5HD",
    "addr:housenumber":"b",
    "addr:postcode":"le4 5hd",
    "addr:street":"Belgrave Business Centre",
    "iso:country":"GB",
    "sg:address":"Unit B, Belgrave Business Centre",
    "sg:city":"Leicester",
    "sg:classifiers":[
        {
            "category":"Wholesale",
            "subcategory":"Home Furnishings",
            "type":"Manufacturing & Wholesale Goods"
        }
    ],
    "sg:phone":"+44 116 266 4667",
    "sg:postcode":"LE4 5HD",
    "sg:province":"Leicestershire",
    "sg:tags":[
        "wsale",
        "rug",
        "carpet"
    ],
    "wof:name":"Carpet Choice",
    "wof:placetype":"venue"
},
  "geometry": {"coordinates":[-1.122364,52.655064],"type":"Point"}
}