{
  "type": "Feature",
  "properties": {
    "iso:country":"GB",
    "sg:address":"The Lodge, 69 Beaufort Street",
    "sg:city":"London",
    "sg:classifiers":[
        {
            "category":"Government",
            "subcategory":"Office",
            "type":"Public Place"
        }
    ],
    "sg:postcode":"SW3 5AH",
    "sg:province":"Greater London",
    "sg:tags":[
        "chamber",
        "commerce"
    ],
    "wof:name":"Kensington & Chelsea Chamber of Trade An",
    "wof:placetype":"venue"
},
  "geometry": {"coordinates":[-0.17592,51.483822],"type":"Point"}
}