{
  "type": "Feature",
  "properties": {
    "addr:full":"Grange Road Otley West Yorkshire LS19 7AD",
    "addr:postcode":"ls19 7ad",
    "addr:street":"Grange Road",
    "iso:country":"GB",
    "sg:address":"Grange Road",
    "sg:city":"Otley",
    "sg:classifiers":[
        {
            "category":"Retail",
            "subcategory":"Auto Repair",
            "type":"Services"
        }
    ],
    "sg:phone":"+44 113 250 7730",
    "sg:postcode":"LS19 7AD",
    "sg:province":"West Yorkshire",
    "sg:tags":[
        "modification",
        "garage"
    ],
    "wof:name":"Dennis Metcalfe",
    "wof:placetype":"venue"
},
  "geometry": {"coordinates":[-1.67734,53.86343],"type":"Point"}
}