{
  "type": "Feature",
  "properties": {
    "addr:full":"163 Palmerston Road, Woodston Peterborough Cambridgeshire PE2 9DE",
    "addr:housenumber":"163",
    "addr:postcode":"pe2 9de",
    "addr:street":"Palmerston Road",
    "iso:country":"GB",
    "sg:address":"163 Palmerston Road, Woodston",
    "sg:city":"Peterborough",
    "sg:classifiers":[
        {
            "category":"Professional",
            "subcategory":"Engineering",
            "type":"Services"
        },
        {
            "category":"Building & Trades",
            "subcategory":"Electrical",
            "type":"Services"
        }
    ],
    "sg:phone":"+44 1733 553721",
    "sg:postcode":"PE2 9DE",
    "sg:province":"Cambridgeshire",
    "sg:tags":[
        "engineer",
        "electrician",
        "contractor"
    ],
    "wof:name":"David R Sterry",
    "wof:placetype":"venue"
},
  "geometry": {"coordinates":[-0.2500370145,52.5602111816],"type":"Point"}
}