{
  "type": "Feature",
  "properties": {
    "addr:full":"9 Church Mews Reading Berkshire RG5 4RJ",
    "addr:housenumber":"9",
    "addr:postcode":"rg5 4rj",
    "addr:street":"Church Mews",
    "iso:country":"GB",
    "sg:address":"9 Church Mews",
    "sg:city":"Reading",
    "sg:classifiers":[
        {
            "category":"Building & Trades",
            "subcategory":"Construction",
            "type":"Services"
        }
    ],
    "sg:phone":"+44 118 969 9239",
    "sg:postcode":"RG5 4RJ",
    "sg:province":"Berkshire",
    "sg:tags":[
        "joiner",
        "carpenter"
    ],
    "wof:name":"D B Acoustics",
    "wof:placetype":"venue"
},
  "geometry": {"coordinates":[-0.8944330215,51.4567947388],"type":"Point"}
}