{
  "type": "Feature",
  "properties": {
    "addr:full":"18 Grange Gardens Pinner Greater London HA5 5QE",
    "addr:housenumber":"18",
    "addr:postcode":"ha5 5qe",
    "addr:street":"Grange Gardens",
    "iso:country":"GB",
    "sg:address":"18 Grange Gardens",
    "sg:city":"Pinner",
    "sg:classifiers":[
        {
            "category":"Real Estate",
            "subcategory":"Surveying",
            "type":"Services"
        }
    ],
    "sg:postcode":"HA5 5QE",
    "sg:province":"Greater London",
    "sg:tags":[
        "surveyor",
        "valuer"
    ],
    "wof:name":"Brampton & Associates",
    "wof:placetype":"venue"
},
  "geometry": {"coordinates":[-0.379203,51.59322],"type":"Point"}
}