{
  "type": "Feature",
  "properties": {
    "addr:full":"7 Windsor Road Worcester Park Surrey KT4 8ES",
    "addr:housenumber":"7",
    "addr:postcode":"kt4 8es",
    "addr:street":"Windsor Road",
    "iso:country":"GB",
    "sg:address":"7 Windsor Road",
    "sg:city":"Worcester Park",
    "sg:classifiers":[
        {
            "category":"Shopping",
            "subcategory":"Gifts & Souvenirs",
            "type":"Retail Goods"
        }
    ],
    "sg:phone":"+44 20 8330 4965",
    "sg:postcode":"KT4 8ES",
    "sg:province":"Surrey",
    "sg:tags":[
        "poster",
        "card"
    ],
    "wof:name":"Carol's Cards",
    "wof:placetype":"venue"
},
  "geometry": {"coordinates":[-0.2414360046,51.3776855469],"type":"Point"}
}