{
  "type": "Feature",
  "properties": {
    "addr:full":"Units 4, 5 & 6, 8 Dashwood Ave High Wycombe Buckinghamshire HP12 3DN",
    "addr:housenumber":"units 4 5 &;8",
    "addr:postcode":"hp12 3dn",
    "addr:street":"Dashwood Ave",
    "iso:country":"GB",
    "sg:address":"Units 4, 5 & 6, 8 Dashwood Ave",
    "sg:city":"High Wycombe",
    "sg:classifiers":[
        {
            "category":"Manufacturing",
            "subcategory":"Tools & Machinery",
            "type":"Manufacturing & Wholesale Goods"
        }
    ],
    "sg:postcode":"HP12 3DN",
    "sg:province":"Buckinghamshire",
    "sg:tags":[
        "design",
        "maker"
    ],
    "wof:name":"Wilkie,Anthony,",
    "wof:placetype":"venue"
},
  "geometry": {"coordinates":[-0.767927,51.633366],"type":"Point"}
}