{
  "type": "Feature",
  "properties": {
    "addr:full":"19 Bridgegate Business Park Aylesbury Buckinghamshire HP19 8XN",
    "addr:housenumber":"19",
    "addr:postcode":"hp19 8xn",
    "addr:street":"Bridgegate Business Park",
    "iso:country":"GB",
    "sg:address":"19 Bridgegate Business Park",
    "sg:city":"Aylesbury",
    "sg:classifiers":[
        {
            "category":"Food & Beverages",
            "subcategory":"Fruits & Vegetables",
            "type":"Retail Goods"
        }
    ],
    "sg:phone":"+44 1296 482379",
    "sg:postcode":"HP19 8XN",
    "sg:province":"Buckinghamshire",
    "sg:tags":[
        "greengrocer"
    ],
    "wof:name":"Derek Pigott",
    "wof:placetype":"venue"
},
  "geometry": {"coordinates":[-0.83133,51.819901],"type":"Point"}
}