{
  "type": "Feature",
  "properties": {
    "iso:country":"GB",
    "sg:address":"7-8 Holmbeck Rd",
    "sg:city":"Saltburn By The Sea",
    "sg:classifiers":[
        {
            "category":"Shopping",
            "subcategory":"Used Merchandise",
            "type":"Retail Goods"
        }
    ],
    "sg:phone":"+44 1287 653000",
    "sg:postcode":"TS12 2AL",
    "sg:province":"North Yorkshire",
    "sg:tags":[
        "shop",
        "second-hand"
    ],
    "wof:name":"Secondhand Shop The",
    "wof:placetype":"venue"
},
  "geometry": {"coordinates":[-0.963569,54.558304],"type":"Point"}
}