{
  "type": "Feature",
  "properties": {
    "iso:country":"GB",
    "sg:address":"3 Regent Street, Stotfold",
    "sg:city":"Hitchin",
    "sg:classifiers":[
        {
            "category":"Building & Trades",
            "subcategory":"Construction",
            "type":"Services"
        }
    ],
    "sg:postcode":"SG5 4ED",
    "sg:province":"Bedfordshire",
    "sg:tags":[
        "builder"
    ],
    "wof:name":"Regency Driveways",
    "wof:placetype":"venue"
},
  "geometry": {"coordinates":[-0.232007,52.016403],"type":"Point"}
}