{
  "type": "Feature",
  "properties": {
    "iso:country":"GB",
    "sg:address":"23 Atwood Road",
    "sg:city":"Hammersmith",
    "sg:classifiers":[
        {
            "category":"Professional",
            "subcategory":"Employment Agencies",
            "type":"Services"
        }
    ],
    "sg:phone":"+44 20 8741 7663",
    "sg:postcode":"W6 0HX",
    "sg:province":"Greater London",
    "sg:tags":[
        "consultant",
        "recruitment"
    ],
    "wof:name":"C M C Recruitment",
    "wof:placetype":"venue"
},
  "geometry": {"coordinates":[-0.233038,51.495811],"type":"Point"}
}