{
  "type": "Feature",
  "properties": {
    "iso:country":"GB",
    "sg:address":"137 Main Street, Addingham",
    "sg:city":"Ilkley",
    "sg:classifiers":[
        {
            "category":"Fast Food",
            "type":"Food & Drink"
        },
        {
            "category":"Food & Beverages",
            "subcategory":"Meat & Fish",
            "type":"Retail Goods"
        }
    ],
    "sg:phone":"+44 1943 830864",
    "sg:postcode":"LS29 0LZ",
    "sg:province":"North Yorkshire",
    "sg:tags":[
        "shop",
        "chip"
    ],
    "wof:name":"Addingham Fisheries",
    "wof:placetype":"venue"
},
  "geometry": {"coordinates":[-1.882573,53.943939],"type":"Point"}
}