{
  "type": "Feature",
  "properties": {
    "iso:country":"GB",
    "sg:address":"Whitehill Farm",
    "sg:city":"Perth",
    "sg:classifiers":[
        {
            "category":"Farming",
            "subcategory":"Farm",
            "type":"Manufacturing & Wholesale Goods"
        }
    ],
    "sg:phone":"+44 1738 583275",
    "sg:postcode":"PH1 4PX",
    "sg:province":"Perth and Kinross",
    "sg:tags":[
        "mixed",
        "crop"
    ],
    "wof:name":"W Ewan",
    "wof:placetype":"venue"
},
  "geometry": {"coordinates":[-3.488414,56.507095],"type":"Point"}
}