{
  "type": "Feature",
  "properties": {
    "addr:full":"Unit 3 Estcourt House, Escourt Road Great Yarmouth Norfolk NR30 4JQ",
    "addr:housenumber":"unit 3 estcourt house",
    "addr:postcode":"nr30 4jq",
    "addr:street":"Escourt Road",
    "iso:country":"GB",
    "sg:address":"Unit 3 Estcourt House, Escourt Road",
    "sg:city":"Great Yarmouth",
    "sg:classifiers":[
        {
            "category":"Home & Garden",
            "subcategory":"Building Materials",
            "type":"Retail Goods"
        }
    ],
    "sg:postcode":"NR30 4JQ",
    "sg:province":"Norfolk",
    "sg:tags":[
        "ironwork",
        "diy",
        "wrought"
    ],
    "wof:name":"Michael John Tuffrey",
    "wof:placetype":"venue"
},
  "geometry": {"coordinates":[1.728725,52.616436],"type":"Point"}
}