{
  "type": "Feature",
  "properties": {
    "addr:full":"3 Heol Gam Cardiff Cardiff CF4 8QA",
    "addr:housenumber":"3",
    "addr:postcode":"cf4 8qa",
    "addr:street":"Heol Gam",
    "iso:country":"GB",
    "sg:address":"3 Heol Gam",
    "sg:city":"Cardiff",
    "sg:classifiers":[
        {
            "category":"Farming",
            "subcategory":"Livestock Farm",
            "type":"Manufacturing & Wholesale Goods"
        }
    ],
    "sg:phone":"+44 29 2089 0174",
    "sg:postcode":"CF4 8QA",
    "sg:province":"Cardiff",
    "sg:tags":[
        "stud"
    ],
    "wof:name":"B Williams",
    "wof:placetype":"venue"
},
  "geometry": {"coordinates":[-3.301921,51.531105],"type":"Point"}
}