{
  "type": "Feature",
  "properties": {
    "addr:full":"72 Morfa Road Swansea Neath Port Talbot SA1 2EW",
    "addr:housenumber":"72",
    "addr:postcode":"sa1 2ew",
    "addr:street":"Morfa Road",
    "iso:country":"GB",
    "sg:address":"72 Morfa Road",
    "sg:city":"Swansea",
    "sg:classifiers":[
        {
            "category":"Building & Trades",
            "subcategory":"Construction",
            "type":"Services"
        }
    ],
    "sg:postcode":"SA1 2EW",
    "sg:province":"Neath Port Talbot",
    "sg:tags":[
        "platform",
        "work",
        "scaffolding"
    ],
    "wof:name":"David Swan",
    "wof:placetype":"venue"
},
  "geometry": {"coordinates":[-3.936809063,51.6327400208],"type":"Point"}
}