{
  "type": "Feature",
  "properties": {
    "iso:country":"GB",
    "sg:address":"8 Lavender Clo, Merryoak",
    "sg:city":"Southampton",
    "sg:classifiers":[
        {
            "category":"Building & Trades",
            "subcategory":"Construction",
            "type":"Services"
        }
    ],
    "sg:postcode":"SO19 7SA",
    "sg:province":"Hampshire",
    "sg:tags":[
        "builder"
    ],
    "wof:name":"M P S Mobile Welding",
    "wof:placetype":"venue"
},
  "geometry": {"coordinates":[-1.36603,50.907028],"type":"Point"}
}