{
  "type": "Feature",
  "properties": {
    "addr:full":"48 Chartley Avenue Stanmore Greater London HA7 3QZ",
    "addr:housenumber":"48",
    "addr:postcode":"ha7 3qz",
    "addr:street":"Chartley Avenue",
    "iso:country":"GB",
    "sg:address":"48 Chartley Avenue",
    "sg:city":"Stanmore",
    "sg:classifiers":[
        {
            "category":"Professional",
            "subcategory":"Business Services",
            "type":"Services"
        }
    ],
    "sg:phone":"+44 20 8420 7288",
    "sg:postcode":"HA7 3QZ",
    "sg:province":"Greater London",
    "sg:tags":[
        "distributor",
        "film"
    ],
    "wof:name":"United International Trade Ltd.",
    "wof:placetype":"venue"
},
  "geometry": {"coordinates":[-0.326977998,51.6111831665],"type":"Point"}
}