{
  "type": "Feature",
  "properties": {
    "iso:country":"GB",
    "sg:address":"7c Church Street",
    "sg:city":"Dronfield",
    "sg:classifiers":[
        {
            "category":"Home & Garden",
            "subcategory":"Kitchen Supply",
            "type":"Retail Goods"
        }
    ],
    "sg:postcode":"S18 1QB",
    "sg:province":"Derbyshire",
    "sg:tags":[
        "equipment",
        "catering"
    ],
    "wof:name":"Humphrey Newcombe Marketing Co.",
    "wof:placetype":"venue"
},
  "geometry": {"coordinates":[-1.471138,53.301113],"type":"Point"}
}