{
  "type": "Feature",
  "properties": {
    "iso:country":"GB",
    "sg:address":"Unit 5 Victoria Works, Victoria Street, Rainhill",
    "sg:city":"Prescot",
    "sg:classifiers":[
        {
            "category":"Retail",
            "subcategory":"Auto Repair",
            "type":"Services"
        }
    ],
    "sg:phone":"+44 151 426 0314",
    "sg:postcode":"L35 0LB",
    "sg:province":"Cheshire",
    "sg:tags":[
        "body",
        "car"
    ],
    "wof:name":"S B Motors",
    "wof:placetype":"venue"
},
  "geometry": {"coordinates":[-2.7647199631,53.4163818359],"type":"Point"}
}