{
  "type": "Feature",
  "properties": {
    "addr:full":"Ty Newydd, Abersoch Pwllheli Gwynedd LL53 7LE",
    "addr:postcode":"ll53 7le",
    "iso:country":"GB",
    "sg:address":"Ty Newydd, Abersoch",
    "sg:city":"Pwllheli",
    "sg:classifiers":[
        {
            "category":"Farming",
            "subcategory":"Dairy Farm",
            "type":"Manufacturing & Wholesale Goods"
        }
    ],
    "sg:phone":"+44 1758 712752",
    "sg:postcode":"LL53 7LE",
    "sg:province":"Gwynedd",
    "sg:tags":[
        "farmer"
    ],
    "wof:name":"R B & J & C J & J B Jones",
    "wof:placetype":"venue"
},
  "geometry": {"coordinates":[-4.5051288605,52.8274040222],"type":"Point"}
}