{
  "type": "Feature",
  "properties": {
    "addr:full":"39 Fauldburn Edinburgh City of Edinburgh EH12 8YQ",
    "addr:housenumber":"39",
    "addr:postcode":"eh12 8yq",
    "addr:street":"Fauldburn Edinburgh",
    "iso:country":"GB",
    "sg:address":"39 Fauldburn",
    "sg:city":"Edinburgh",
    "sg:classifiers":[
        {
            "category":"Shopping",
            "subcategory":"Books",
            "type":"Retail Goods"
        }
    ],
    "sg:phone":"+44 131 339 8750",
    "sg:postcode":"EH12 8YQ",
    "sg:province":"City of Edinburgh",
    "wof:name":"Thompson's Streetwyse",
    "wof:placetype":"venue"
},
  "geometry": {"coordinates":[-3.3037850857,55.951839447],"type":"Point"}
}