{
  "type": "Feature",
  "properties": {
    "addr:full":"2 Cranbrook Road Ilford Essex IG1 4DJ",
    "addr:housenumber":"2",
    "addr:postcode":"ig1 4dj",
    "addr:street":"Cranbrook Road",
    "iso:country":"GB",
    "sg:address":"2 Cranbrook Road",
    "sg:city":"Ilford",
    "sg:classifiers":[
        {
            "category":"Restaurant",
            "type":"Food & Drink"
        },
        {
            "category":"Food & Beverages",
            "subcategory":"Bakery",
            "type":"Retail Goods"
        }
    ],
    "sg:phone":"+44 20 8478 2486",
    "sg:postcode":"IG1 4DJ",
    "sg:province":"Essex",
    "sg:tags":[
        "-",
        "pizza"
    ],
    "wof:name":"CITY CENTRE RESTAURANTS (UK) LTD",
    "wof:placetype":"venue"
},
  "geometry": {"coordinates":[0.070129998,51.558681488],"type":"Point"}
}