{
  "type": "Feature",
  "properties": {
    "addr:full":"Quinta Oswestry Shropshire SY10 7LR",
    "addr:postcode":"sy10 7lr",
    "addr:street":"Quinta",
    "iso:country":"GB",
    "sg:address":"Quinta",
    "sg:city":"Oswestry",
    "sg:classifiers":[
        {
            "category":"Community Center",
            "type":"Public Place"
        }
    ],
    "sg:phone":"+44 1691 773696",
    "sg:postcode":"SY10 7LR",
    "sg:province":"Shropshire",
    "sg:tags":[
        "conference",
        "room",
        "centre"
    ],
    "wof:name":"Quinta Christian Centre",
    "wof:placetype":"venue"
},
  "geometry": {"coordinates":[-3.07733,52.916641],"type":"Point"}
}