{
  "type": "Feature",
  "properties": {
    "addr:full":"129 Stratford Rd Plaistow Greater London E13 0JN",
    "addr:housenumber":"129",
    "addr:postcode":"e13 0jn",
    "addr:street":"Stratford Rd",
    "iso:country":"GB",
    "sg:address":"129 Stratford Rd",
    "sg:city":"Plaistow",
    "sg:classifiers":[
        {
            "category":"Building & Trades",
            "subcategory":"Landscaping Services",
            "type":"Services"
        }
    ],
    "sg:phone":"+44 20 8471 2450",
    "sg:postcode":"E13 0JN",
    "sg:province":"Greater London",
    "sg:tags":[
        "pond",
        "aquarium"
    ],
    "wof:name":"Frost Bros East London Koi",
    "wof:placetype":"venue"
},
  "geometry": {"coordinates":[0.017296,51.533806],"type":"Point"}
}