{
  "type": "Feature",
  "properties": {
    "addr:full":"83 Thorpe Rd Peterborough Cambridgeshire PE3 6JQ",
    "addr:housenumber":"83",
    "addr:postcode":"pe3 6jq",
    "addr:street":"Thorpe Rd",
    "iso:country":"GB",
    "sg:address":"83 Thorpe Rd",
    "sg:city":"Peterborough",
    "sg:classifiers":[
        {
            "category":"Travel",
            "subcategory":"Hotels & Motels",
            "type":"Entertainment"
        }
    ],
    "sg:phone":"+44 1733 348759",
    "sg:postcode":"PE3 6JQ",
    "sg:province":"Cambridgeshire",
    "wof:name":"Thorpe Lodge Hotel",
    "wof:placetype":"venue"
},
  "geometry": {"coordinates":[-0.258037,52.5728],"type":"Point"}
}