{
  "type": "Feature",
  "properties": {
    "addr:full":"41 Sipson Way, Heathrow South Kensington Greater London SW7 4QT",
    "addr:housenumber":"41",
    "addr:postcode":"sw7 4qt",
    "addr:street":"Sipson Way",
    "iso:country":"GB",
    "sg:address":"41 Sipson Way, Heathrow",
    "sg:city":"South Kensington",
    "sg:classifiers":[
        {
            "category":"Travel",
            "subcategory":"Travel Agent",
            "type":"Entertainment"
        }
    ],
    "sg:phone":"+44 20 7584 6565",
    "sg:postcode":"SW7 4QT",
    "sg:province":"Greater London",
    "wof:name":"GFS Tours International",
    "wof:placetype":"venue"
},
  "geometry": {"coordinates":[-0.18391,51.498032],"type":"Point"}
}