{
  "type": "Feature",
  "properties": {
    "iso:country":"GB",
    "sg:address":"St Marys Road",
    "sg:city":"Evesham",
    "sg:classifiers":[
        {
            "category":"Social Services",
            "subcategory":"Retirement Home",
            "type":"Services"
        }
    ],
    "sg:phone":"+44 1386 765472",
    "sg:postcode":"WR11 4EH",
    "sg:province":"Gloucestershire",
    "sg:tags":[
        "rest"
    ],
    "wof:name":"Homesmith House",
    "wof:placetype":"venue"
},
  "geometry": {"coordinates":[-1.944719,52.097412],"type":"Point"}
}