{
  "type": "Feature",
  "properties": {
    "iso:country":"GB",
    "sg:address":"C/o Douglas Shanks Levy Gee, 66 Wigmore Street",
    "sg:city":"London",
    "sg:classifiers":[
        {
            "category":"Professional",
            "subcategory":"Management & Consulting",
            "type":"Services"
        }
    ],
    "sg:postcode":"W1U 2HQ",
    "sg:province":"Greater London",
    "sg:tags":[
        "consultant",
        "business"
    ],
    "wof:name":"Metrostack Ltd",
    "wof:placetype":"venue"
},
  "geometry": {"coordinates":[-0.14999,51.516499],"type":"Point"}
}