{
  "type": "Feature",
  "properties": {
    "addr:full":"Q E 11 Conference Centre, Broad Sanctuary, Westminster London Greater London SW1P 3EE",
    "addr:housenumber":"11",
    "addr:postcode":"sw1p 3ee",
    "addr:street":"Conference Centre Broad Sanctuary",
    "iso:country":"GB",
    "sg:address":"Q E 11 Conference Centre, Broad Sanctuary, Westminster",
    "sg:city":"London",
    "sg:classifiers":[
        {
            "category":"Professional",
            "subcategory":"Computer Services",
            "type":"Services"
        }
    ],
    "sg:phone":"+44 20 7798 4700",
    "sg:postcode":"SW1P 3EE",
    "sg:province":"Greater London",
    "sg:tags":[
        "system",
        "software"
    ],
    "wof:name":"Maestro Business Systems Ltd.",
    "wof:placetype":"venue"
},
  "geometry": {"coordinates":[-0.127994,51.500065],"type":"Point"}
}