{
  "type": "Feature",
  "properties": {
    "addr:full":"4 Westerfield Court, Westerfield Road Ipswich Suffolk IP4 2UP",
    "addr:housenumber":"4",
    "addr:postcode":"ip4 2up",
    "addr:street":"Westerfield Court Westerfield Road",
    "iso:country":"GB",
    "sg:address":"4 Westerfield Court, Westerfield Road",
    "sg:city":"Ipswich",
    "sg:classifiers":[
        {
            "category":"Professional",
            "subcategory":"Engineering",
            "type":"Services"
        },
        {
            "category":"Real Estate",
            "subcategory":"Architect",
            "type":"Services"
        }
    ],
    "sg:phone":"+44 1842 890686",
    "sg:postcode":"IP4 2UP",
    "sg:province":"Suffolk",
    "sg:tags":[
        "engineer"
    ],
    "wof:name":"LEIGHWELL ENGINEERING",
    "wof:placetype":"venue"
},
  "geometry": {"coordinates":[1.160236,52.062576],"type":"Point"}
}