{
  "type": "Feature",
  "properties": {
    "iso:country":"GB",
    "sg:address":"2 Farrand House, London Road",
    "sg:city":"Stanford-le-hope",
    "sg:classifiers":[
        {
            "category":"Professional",
            "subcategory":"Accounting & Tax Preparation",
            "type":"Services"
        }
    ],
    "sg:postcode":"SS17 0LB",
    "sg:province":"Essex",
    "sg:tags":[
        "accountant"
    ],
    "wof:name":"Lane Farrand & Co.",
    "wof:placetype":"venue"
},
  "geometry": {"coordinates":[0.4147500098,51.5136451721],"type":"Point"}
}