{
  "type": "Feature",
  "properties": {
    "addr:full":"61 The Hall London Greater London SE3 9BG",
    "addr:housenumber":"61",
    "addr:postcode":"se3 9bg",
    "addr:street":"The Hall",
    "iso:country":"GB",
    "sg:address":"61 The Hall",
    "sg:city":"London",
    "sg:classifiers":[
        {
            "category":"Sports & Exercise",
            "subcategory":"Bowling",
            "type":"Entertainment"
        }
    ],
    "sg:phone":"+44 20 8852 4156",
    "sg:postcode":"SE3 9BG",
    "sg:province":"Greater London",
    "sg:tags":[
        "photography"
    ],
    "wof:name":"Filmfinders Ltd.",
    "wof:placetype":"venue"
},
  "geometry": {"coordinates":[0.0159600005,51.4636306763],"type":"Point"}
}