{
  "type": "Feature",
  "properties": {
    "iso:country":"GB",
    "sg:address":"Glansevern Hall",
    "sg:city":"Welshpool",
    "sg:classifiers":[
        {
            "category":"Landmark",
            "subcategory":"Tourist Attraction",
            "type":"Public Place"
        }
    ],
    "sg:phone":"+44 1686 640200",
    "sg:postcode":"SY21 8AH",
    "sg:province":"Shropshire",
    "sg:tags":[
        "interest"
    ],
    "wof:name":"Glansevern Hall Gardens",
    "wof:placetype":"venue"
},
  "geometry": {"coordinates":[-3.15361,52.634331],"type":"Point"}
}