{
  "type": "Feature",
  "properties": {
    "iso:country":"GB",
    "sg:address":"33 Ridley Rd",
    "sg:city":"Willesden",
    "sg:classifiers":[
        {
            "category":"Building & Trades",
            "subcategory":"Construction",
            "type":"Services"
        }
    ],
    "sg:phone":"+44 20 8961 4536",
    "sg:postcode":"NW10 5UB",
    "sg:province":"Greater London",
    "sg:tags":[
        "joiner",
        "carpenter"
    ],
    "wof:name":"R T Lane",
    "wof:placetype":"venue"
},
  "geometry": {"coordinates":[-0.236607,51.536461],"type":"Point"}
}