{
  "type": "Feature",
  "properties": {
    "addr:full":"38 Morton Avenue Bideford Devon EX39 3AY",
    "addr:housenumber":"38",
    "addr:postcode":"ex39 3ay",
    "addr:street":"Morton Avenue",
    "iso:country":"GB",
    "sg:address":"38 Morton Avenue",
    "sg:city":"Bideford",
    "sg:classifiers":[
        {
            "category":"Manufacturing",
            "subcategory":"Petroleum Products",
            "type":"Manufacturing & Wholesale Goods"
        }
    ],
    "sg:postcode":"EX39 3AY",
    "sg:province":"Devon",
    "sg:tags":[
        "double",
        "glazing"
    ],
    "wof:name":"K B Windows & Fascias",
    "wof:placetype":"venue"
},
  "geometry": {"coordinates":[-4.2121591568,51.0160713196],"type":"Point"}
}