{
  "type": "Feature",
  "properties": {
    "addr:full":"Cockaynes Lane, Alresford Colchester Essex CO7 8DA",
    "addr:postcode":"co7 8da",
    "addr:street":"Cockaynes Lane",
    "iso:country":"GB",
    "sg:address":"Cockaynes Lane, Alresford",
    "sg:city":"Colchester",
    "sg:classifiers":[
        {
            "category":"Professional",
            "subcategory":"Engineering",
            "type":"Services"
        }
    ],
    "sg:phone":"+44 1206 825625",
    "sg:postcode":"CO7 8DA",
    "sg:province":"Essex",
    "sg:tags":[
        "precision",
        "engineer"
    ],
    "wof:name":"Wyvern Engineering",
    "wof:placetype":"venue"
},
  "geometry": {"coordinates":[1.007203,51.853226],"type":"Point"}
}