{
  "type": "Feature",
  "properties": {
    "addr:full":"25 Belvedere Road Barrow-in-furness Cumbria LA13 0HS",
    "addr:housenumber":"25",
    "addr:postcode":"la13 0hs",
    "addr:street":"Belvedere Road",
    "iso:country":"GB",
    "sg:address":"25 Belvedere Road",
    "sg:city":"Barrow-in-furness",
    "sg:classifiers":[
        {
            "category":"Home & Garden",
            "subcategory":"Garden Supply",
            "type":"Retail Goods"
        }
    ],
    "sg:postcode":"LA13 0HS",
    "sg:province":"Cumbria",
    "sg:tags":[
        "equipment",
        "playground"
    ],
    "wof:name":"Play Safe",
    "wof:placetype":"venue"
},
  "geometry": {"coordinates":[-3.1913359165,54.117389679],"type":"Point"}
}