{
  "type": "Feature",
  "properties": {
    "addr:full":"Hatherleigh Place, Merthyr Link Road Abergavenny Herefordshire NP7 7RL",
    "addr:postcode":"np7 7rl",
    "addr:street":"Hatherleigh Place Merthyr Link Road",
    "iso:country":"GB",
    "sg:address":"Hatherleigh Place, Merthyr Link Road",
    "sg:city":"Abergavenny",
    "sg:classifiers":[
        {
            "category":"Shopping",
            "subcategory":"Clothing, Apparel, & Fashions",
            "type":"Retail Goods"
        }
    ],
    "sg:phone":"+44 1873 855923",
    "sg:postcode":"NP7 7RL",
    "sg:province":"Herefordshire",
    "sg:tags":[
        "shop",
        "hat"
    ],
    "wof:name":"Aristohats",
    "wof:placetype":"venue"
},
  "geometry": {"coordinates":[-3.0304288864,51.8230018616],"type":"Point"}
}