{
  "type": "Feature",
  "properties": {
    "addr:full":"131 Old St Ashton Under Lyne Greater Manchester OL6 7SA",
    "addr:housenumber":"131",
    "addr:postcode":"ol6 7sa",
    "addr:street":"Old St;Under Lyne",
    "iso:country":"GB",
    "sg:address":"131 Old St",
    "sg:city":"Ashton Under Lyne",
    "sg:classifiers":[
        {
            "category":"Professional",
            "subcategory":"Lawyer & Legal Services",
            "type":"Services"
        }
    ],
    "sg:phone":"+44 161 285 3355",
    "sg:postcode":"OL6 7SA",
    "sg:province":"Greater Manchester",
    "sg:tags":[
        "advice",
        "counselling"
    ],
    "wof:name":"Family Mediators Association",
    "wof:placetype":"venue"
},
  "geometry": {"coordinates":[-2.096507,53.487427],"type":"Point"}
}