{
  "type": "Feature",
  "properties": {
    "iso:country":"GB",
    "sg:address":"263 Station Road",
    "sg:city":"Harrow",
    "sg:classifiers":[
        {
            "category":"Food & Beverages",
            "subcategory":"Liquor & Beverages",
            "type":"Retail Goods"
        }
    ],
    "sg:postcode":"HA1 2TB",
    "sg:province":"Greater London",
    "sg:tags":[
        "beer",
        "spirit",
        "wines"
    ],
    "wof:name":"Harrow Off Licence",
    "wof:placetype":"venue"
},
  "geometry": {"coordinates":[-0.332481,51.582516],"type":"Point"}
}