{
  "type": "Feature",
  "properties": {
    "addr:full":"14-15 High Street Shrewsbury Shropshire SY1 1SP",
    "addr:housenumber":"14-15",
    "addr:postcode":"sy1 1sp",
    "addr:street":"High Street",
    "iso:country":"GB",
    "sg:address":"14-15 High Street",
    "sg:city":"Shrewsbury",
    "sg:classifiers":[
        {
            "category":"Shopping",
            "subcategory":"Clothing, Apparel, & Fashions",
            "type":"Retail Goods"
        }
    ],
    "sg:postcode":"SY1 1SP",
    "sg:province":"Shropshire",
    "sg:tags":[
        "ladieswear"
    ],
    "wof:name":"McClures",
    "wof:placetype":"venue"
},
  "geometry": {"coordinates":[-2.7532279491,52.7075767517],"type":"Point"}
}