{
  "type": "Feature",
  "properties": {
    "iso:country":"GB",
    "sg:address":"25 Brindley Avenue",
    "sg:city":"Winsford",
    "sg:classifiers":[
        {
            "category":"Building & Trades",
            "subcategory":"Construction",
            "type":"Services"
        }
    ],
    "sg:phone":"+44 1606 558004",
    "sg:postcode":"CW7 2EG",
    "sg:province":"Cheshire",
    "sg:tags":[
        "decorator",
        "painter"
    ],
    "wof:name":"H & H Painters & Decorators",
    "wof:placetype":"venue"
},
  "geometry": {"coordinates":[-2.538992,53.193436],"type":"Point"}
}