{
  "type": "Feature",
  "properties": {
    "iso:country":"GB",
    "sg:address":"Hullbridge Road",
    "sg:city":"Rayleigh",
    "sg:classifiers":[
        {
            "category":"Home & Garden",
            "subcategory":"Garden Supply",
            "type":"Retail Goods"
        }
    ],
    "sg:postcode":"SS6 9QS",
    "sg:province":"Essex",
    "sg:tags":[
        "nursery",
        "centre"
    ],
    "wof:name":"Fairways Garden Centre",
    "wof:placetype":"venue"
},
  "geometry": {"coordinates":[0.6111209989,51.6025428772],"type":"Point"}
}