{
  "type": "Feature",
  "properties": {
    "addr:full":"Mallards, The Mere, Great Glen Leicester Leicestershire LE8 9FS",
    "addr:postcode":"le8 9fs",
    "addr:street":"Great Glen",
    "iso:country":"GB",
    "sg:address":"Mallards, The Mere, Great Glen",
    "sg:city":"Leicester",
    "sg:classifiers":[
        {
            "category":"Real Estate",
            "subcategory":"Architect",
            "type":"Services"
        }
    ],
    "sg:phone":"+44 116 259 3840",
    "sg:postcode":"LE8 9FS",
    "sg:province":"Leicestershire",
    "wof:name":"Gap Design",
    "wof:placetype":"venue"
},
  "geometry": {"coordinates":[-1.03391397,52.5713424683],"type":"Point"}
}