{
  "type": "Feature",
  "properties": {
    "iso:country":"GB",
    "sg:address":"55 Fishwives Causeway",
    "sg:city":"Edinburgh",
    "sg:classifiers":[
        {
            "category":"Building & Trades",
            "subcategory":"Construction",
            "type":"Services"
        }
    ],
    "sg:phone":"+44 131 657 2261",
    "sg:postcode":"EH7 6GG",
    "sg:province":"City of Edinburgh",
    "sg:tags":[
        "builder"
    ],
    "wof:name":"Teague Homes (Scotland) Ltd.",
    "wof:placetype":"venue"
},
  "geometry": {"coordinates":[-3.126239,55.95483],"type":"Point"}
}