{
  "type": "Feature",
  "properties": {
    "iso:country":"GB",
    "sg:address":"Causeway, Bardney",
    "sg:city":"Lincoln",
    "sg:classifiers":[
        {
            "category":"Building & Trades",
            "subcategory":"Construction",
            "type":"Services"
        }
    ],
    "sg:phone":"+44 1526 397697",
    "sg:postcode":"LN3 5UL",
    "sg:province":"Lincolnshire",
    "sg:tags":[
        "welder"
    ],
    "wof:name":"Ricweld",
    "wof:placetype":"venue"
},
  "geometry": {"coordinates":[-0.323684,53.211296],"type":"Point"}
}