{
  "type": "Feature",
  "properties": {
    "addr:full":"Brock Hill Farm, Brock Hill, Runwell Wickford Essex SS11 7NY",
    "addr:postcode":"ss11 7ny",
    "addr:street":"Brock Hill",
    "iso:country":"GB",
    "sg:address":"Brock Hill Farm, Brock Hill, Runwell",
    "sg:city":"Wickford",
    "sg:classifiers":[
        {
            "category":"Farming",
            "subcategory":"Livestock Farm",
            "type":"Manufacturing & Wholesale Goods"
        }
    ],
    "sg:postcode":"SS11 7NY",
    "sg:province":"Essex",
    "sg:tags":[
        "others"
    ],
    "wof:name":"F Pearce & Sons",
    "wof:placetype":"venue"
},
  "geometry": {"coordinates":[0.5117269754,51.6374435425],"type":"Point"}
}