{
  "type": "Feature",
  "properties": {
    "addr:full":"90 Kilburn High Street, Kilburn London Greater London NW6 7XS",
    "addr:housenumber":"90",
    "addr:postcode":"nw6 7xs",
    "addr:street":"Kilburn High Street",
    "iso:country":"GB",
    "sg:address":"90 Kilburn High Street, Kilburn",
    "sg:city":"London",
    "sg:classifiers":[
        {
            "category":"Food & Beverages",
            "subcategory":"Supermarket",
            "type":"Retail Goods"
        }
    ],
    "sg:phone":"+44 20 7328 3536",
    "sg:postcode":"NW6 7XS",
    "sg:province":"Greater London",
    "wof:name":"J Sainsbury",
    "wof:placetype":"venue"
},
  "geometry": {"coordinates":[-0.2082899958,51.5432510376],"type":"Point"}
}