{
  "type": "Feature",
  "properties": {
    "iso:country":"GB",
    "sg:address":"39 New Street, Darfield",
    "sg:city":"Barnsley",
    "sg:classifiers":[
        {
            "category":"Autos & Motor Vehicles",
            "subcategory":"Automobile Sales",
            "type":"Retail Goods"
        }
    ],
    "sg:phone":"+44 1226 753063",
    "sg:postcode":"S73 9LL",
    "sg:province":"South Yorkshire",
    "sg:tags":[
        "commercial"
    ],
    "wof:name":"R Smith",
    "wof:placetype":"venue"
},
  "geometry": {"coordinates":[-1.376122,53.533051],"type":"Point"}
}