{
  "type": "Feature",
  "properties": {
    "addr:full":"462 Bury Old Road, Prestwich Manchester Greater Manchester M25 1NL",
    "addr:housenumber":"462",
    "addr:postcode":"m25 1nl",
    "addr:street":"Bury Old Road",
    "iso:country":"GB",
    "sg:address":"462 Bury Old Road, Prestwich",
    "sg:city":"Manchester",
    "sg:classifiers":[
        {
            "category":"Shopping",
            "subcategory":"Clothing, Apparel, & Fashions",
            "type":"Retail Goods"
        }
    ],
    "sg:phone":"+44 845 765 4321",
    "sg:postcode":"M25 1NL",
    "sg:province":"Greater Manchester",
    "sg:tags":[
        "lady",
        "fashionwear",
        "ladieswear"
    ],
    "wof:name":"C Curtis",
    "wof:placetype":"venue"
},
  "geometry": {"coordinates":[-2.2755379677,53.5375671387],"type":"Point"}
}