{
  "type": "Feature",
  "properties": {
    "addr:full":"Egremont, Payhembury Honiton Devon EX14 3JA",
    "addr:postcode":"ex14 3ja",
    "iso:country":"GB",
    "sg:address":"Egremont, Payhembury",
    "sg:city":"Honiton",
    "sg:classifiers":[
        {
            "category":"Wholesale",
            "subcategory":"Machinery & Supplies",
            "type":"Manufacturing & Wholesale Goods"
        }
    ],
    "sg:postcode":"EX14 3JA",
    "sg:province":"Devon",
    "wof:name":"Carthorse Machinery",
    "wof:placetype":"venue"
},
  "geometry": {"coordinates":[-3.2940330505,50.8069190979],"type":"Point"}
}