{
  "type": "Feature",
  "properties": {
    "iso:country":"GB",
    "sg:address":"90 High Street, Gosforth",
    "sg:city":"Newcastle-upon-tyne",
    "sg:classifiers":[
        {
            "category":"Wholesale",
            "subcategory":"Medical Equipment & Supplies",
            "type":"Manufacturing & Wholesale Goods"
        },
        {
            "category":"Professional",
            "subcategory":"Computer Services",
            "type":"Services"
        },
        {
            "category":"Health Services",
            "subcategory":"Dentist",
            "type":"Services"
        }
    ],
    "sg:phone":"+44 191 285 9192",
    "sg:postcode":"NE3 1HB",
    "sg:province":"Tyne and Wear",
    "sg:tags":[
        "development",
        "dental",
        "software"
    ],
    "wof:name":"SYSTEMS FOR DENTISTS LTD",
    "wof:placetype":"venue"
},
  "geometry": {"coordinates":[-1.6200020313,55.0042266846],"type":"Point"}
}