{
  "type": "Feature",
  "properties": {
    "iso:country":"GB",
    "sg:address":"Unit 138 Swan Centre, Coventry Rd",
    "sg:city":"Birmingham",
    "sg:classifiers":[
        {
            "category":"Fast Food",
            "type":"Food & Drink"
        }
    ],
    "sg:phone":"+44 121 604 6223",
    "sg:postcode":"B26 1BS",
    "sg:province":"West Midlands",
    "sg:tags":[
        "away",
        "take"
    ],
    "wof:name":"Quick Snacks",
    "wof:placetype":"venue"
},
  "geometry": {"coordinates":[-1.798157,52.457718],"type":"Point"}
}