{
  "type": "Feature",
  "properties": {
    "iso:country":"GB",
    "sg:address":"4 Westover Road",
    "sg:city":"Bournemouth",
    "sg:classifiers":[
        {
            "category":"Arts & Performance",
            "subcategory":"Art Gallery",
            "type":"Entertainment"
        }
    ],
    "sg:phone":"+44 1202 297682",
    "sg:postcode":"BH1 2BY",
    "sg:province":"Dorset",
    "wof:name":"Westover Gallery",
    "wof:placetype":"venue"
},
  "geometry": {"coordinates":[-1.876066,50.719349],"type":"Point"}
}