{
  "type": "Feature",
  "properties": {
    "addr:full":"20 Browns Lane, Knowle Solihull Warwickshire B93 8BA",
    "addr:housenumber":"20",
    "addr:postcode":"b93 8ba",
    "addr:street":"Browns Lane",
    "iso:country":"GB",
    "sg:address":"20 Browns Lane, Knowle",
    "sg:city":"Solihull",
    "sg:classifiers":[
        {
            "category":"Real Estate",
            "subcategory":"Architect",
            "type":"Services"
        }
    ],
    "sg:phone":"+44 1564 772263",
    "sg:postcode":"B93 8BA",
    "sg:province":"Warwickshire",
    "sg:tags":[
        "architectural"
    ],
    "wof:name":"Phyllis Degens",
    "wof:placetype":"venue"
},
  "geometry": {"coordinates":[-1.761435,52.385693],"type":"Point"}
}