{
  "type": "Feature",
  "properties": {
    "addr:full":"107 Old Forest Way Birmingham West Midlands B34 7AR",
    "addr:housenumber":"107",
    "addr:postcode":"7ar",
    "addr:street":"Old Forest Way",
    "iso:country":"GB",
    "sg:address":"107 Old Forest Way",
    "sg:city":"Birmingham",
    "sg:classifiers":[
        {
            "category":"Professional",
            "subcategory":"Engineering",
            "type":"Services"
        }
    ],
    "sg:postcode":"B34 7AR",
    "sg:province":"West Midlands",
    "sg:tags":[
        "contractor",
        "electrical",
        "engineer"
    ],
    "wof:name":"First Quote Electrical & Building",
    "wof:placetype":"venue"
},
  "geometry": {"coordinates":[-1.781340003,52.4937477112],"type":"Point"}
}