{
  "type": "Feature",
  "properties": {
    "addr:full":"Kirkhill Ho, 30 Ellon Rd Aberdeen Aberdeen City AB23 8BX",
    "addr:housenumber":"30",
    "addr:postcode":"ab23 8bx",
    "addr:street":"Ellon Rd",
    "iso:country":"GB",
    "sg:address":"Kirkhill Ho, 30 Ellon Rd",
    "sg:city":"Aberdeen",
    "sg:classifiers":[
        {
            "category":"Health Services",
            "subcategory":"Dentist",
            "type":"Services"
        }
    ],
    "sg:phone":"+44 1224 820775",
    "sg:postcode":"AB23 8BX",
    "sg:province":"Aberdeen City",
    "wof:name":"K Kumar",
    "wof:placetype":"venue"
},
  "geometry": {"coordinates":[-2.0730888844,57.225818634],"type":"Point"}
}