{
  "type": "Feature",
  "properties": {
    "iso:country":"GB",
    "sg:address":"37 Edgware Road",
    "sg:city":"London",
    "sg:classifiers":[
        {
            "category":"Shopping",
            "subcategory":"Books",
            "type":"Retail Goods"
        }
    ],
    "sg:phone":"+44 20 7706 1717",
    "sg:postcode":"W2 2JE",
    "sg:province":"Greater London",
    "sg:tags":[
        "bookseller"
    ],
    "wof:name":"Arabic Store",
    "wof:placetype":"venue"
},
  "geometry": {"coordinates":[-0.1627209932,51.5146903992],"type":"Point"}
}