{
  "type": "Feature",
  "properties": {
    "iso:country":"GB",
    "sg:address":"26 Charnwood Street",
    "sg:city":"Derby",
    "sg:classifiers":[
        {
            "category":"Organizations",
            "subcategory":"Community Association",
            "type":"Services"
        },
        {
            "category":"Organizations",
            "subcategory":"Membership Organization",
            "type":"Services"
        }
    ],
    "sg:phone":"+44 1332 364627",
    "sg:postcode":"DE1 2GU",
    "sg:province":"Derbyshire",
    "sg:tags":[
        "club",
        "social"
    ],
    "wof:name":"Derby Labour Party Social Club",
    "wof:placetype":"venue"
},
  "geometry": {"coordinates":[-1.4761420488,52.9154853821],"type":"Point"}
}