{
  "type": "Feature",
  "properties": {
    "addr:full":"2 Cedric Road Westgate-on-sea Kent CT8 8NZ",
    "addr:housenumber":"2",
    "addr:postcode":"ct8 8nz",
    "addr:street":"Cedric Road Westgate-On-Sea",
    "iso:country":"GB",
    "sg:address":"2 Cedric Road",
    "sg:city":"Westgate-on-sea",
    "sg:classifiers":[
        {
            "category":"Retail",
            "subcategory":"Driving School",
            "type":"Services"
        }
    ],
    "sg:phone":"+44 1843 832505",
    "sg:postcode":"CT8 8NZ",
    "sg:province":"Kent",
    "wof:name":"One Way School of Motoring",
    "wof:placetype":"venue"
},
  "geometry": {"coordinates":[1.333759,51.38205],"type":"Point"}
}