{
  "type": "Feature",
  "properties": {
    "addr:full":"3 Orchard Close, Penkridge Stafford Shropshire ST19 5BJ",
    "addr:housenumber":"3",
    "addr:postcode":"st19 5bj",
    "addr:street":"Orchard Close",
    "iso:country":"GB",
    "sg:address":"3 Orchard Close, Penkridge",
    "sg:city":"Stafford",
    "sg:classifiers":[
        {
            "category":"Taxi",
            "type":"Transportation"
        }
    ],
    "sg:phone":"+44 1785 716671",
    "sg:postcode":"ST19 5BJ",
    "sg:province":"Shropshire",
    "sg:tags":[
        "mini",
        "cab"
    ],
    "wof:name":"1 A.B.A",
    "wof:placetype":"venue"
},
  "geometry": {"coordinates":[-2.107304,52.727757],"type":"Point"}
}