{
  "type": "Feature",
  "properties": {
    "addr:full":"8 Market Pde, Portland Rd London Greater London SE25 4PP",
    "addr:housenumber":"8",
    "addr:postcode":"se25 4pp",
    "addr:street":"Market Pde Portland Rd",
    "iso:country":"GB",
    "sg:address":"8 Market Pde, Portland Rd",
    "sg:city":"London",
    "sg:classifiers":[
        {
            "category":"Shopping",
            "subcategory":"Computers & Home Electronics",
            "type":"Retail Goods"
        }
    ],
    "sg:phone":"+44 20 8656 3724",
    "sg:postcode":"SE25 4PP",
    "sg:province":"Greater London",
    "sg:tags":[
        "electrical"
    ],
    "wof:name":"Beamelect Ltd",
    "wof:placetype":"venue"
},
  "geometry": {"coordinates":[-0.0676980019,51.3951721191],"type":"Point"}
}