{
  "type": "Feature",
  "properties": {
    "addr:full":"Old House, North Farm Wimborne Dorset BH21 5JE",
    "addr:housenumber":"wimborne",
    "addr:postcode":"bh21 5je",
    "addr:street":"North;Dorset",
    "iso:country":"GB",
    "sg:address":"Old House, North Farm",
    "sg:city":"Wimborne",
    "sg:classifiers":[
        {
            "category":"Farming",
            "subcategory":"Farm",
            "type":"Manufacturing & Wholesale Goods"
        }
    ],
    "sg:phone":"+44 1725 552253",
    "sg:postcode":"BH21 5JE",
    "sg:province":"Dorset",
    "sg:tags":[
        "mixed",
        "crop"
    ],
    "wof:name":"Anthony Molins",
    "wof:placetype":"venue"
},
  "geometry": {"coordinates":[-2.03077,50.915852],"type":"Point"}
}