{
  "type": "Feature",
  "properties": {
    "addr:full":"Berryyards, Lynedoch Street Greenock Inverclyde PA15 4BG",
    "addr:postcode":"pa15 4bg",
    "addr:street":"Lynedoch Street Greenock",
    "iso:country":"GB",
    "sg:address":"Berryyards, Lynedoch Street",
    "sg:city":"Greenock",
    "sg:classifiers":[
        {
            "category":"Retail",
            "subcategory":"Auto Repair",
            "type":"Services"
        }
    ],
    "sg:phone":"+44 1475 781538",
    "sg:postcode":"PA15 4BG",
    "sg:province":"Inverclyde",
    "sg:tags":[
        "body",
        "car",
        "repairer"
    ],
    "wof:name":"Westburn Autos",
    "wof:placetype":"venue"
},
  "geometry": {"coordinates":[-4.76085,55.939529],"type":"Point"}
}