{
  "type": "Feature",
  "properties": {
    "iso:country":"GB",
    "sg:address":"Berrends Farm, Cooks Lane, Redmarley",
    "sg:city":"Gloucester",
    "sg:classifiers":[
        {
            "category":"Farming",
            "subcategory":"Livestock Farm",
            "type":"Manufacturing & Wholesale Goods"
        }
    ],
    "sg:phone":"+44 1531 650325",
    "sg:postcode":"GL19 3LE",
    "sg:province":"Gloucestershire",
    "sg:tags":[
        "others"
    ],
    "wof:name":"E & A Wadley",
    "wof:placetype":"venue"
},
  "geometry": {"coordinates":[-2.361724,51.981339],"type":"Point"}
}