{
  "type": "Feature",
  "properties": {
    "iso:country":"GB",
    "sg:address":"22-24 Collingham Place",
    "sg:city":"London",
    "sg:classifiers":[
        {
            "category":"Travel",
            "subcategory":"Hotels & Motels",
            "type":"Entertainment"
        }
    ],
    "sg:phone":"+44 20 7373 0666",
    "sg:postcode":"SW5 0PZ",
    "sg:province":"Greater London",
    "wof:name":"Westbury Hotel",
    "wof:placetype":"venue"
},
  "geometry": {"coordinates":[-0.189625,51.493664],"type":"Point"}
}