{
  "type": "Feature",
  "properties": {
    "iso:country":"GB",
    "sg:address":"9 Lendal",
    "sg:city":"York",
    "sg:classifiers":[
        {
            "category":"Travel",
            "subcategory":"Hotels & Motels",
            "type":"Entertainment"
        }
    ],
    "sg:phone":"+44 1904 638733",
    "sg:postcode":"YO1 8AQ",
    "sg:province":"North Yorkshire",
    "wof:name":"The Judges Lodging Hotel",
    "wof:placetype":"venue"
},
  "geometry": {"coordinates":[-1.08561,53.960621],"type":"Point"}
}