{
  "type": "Feature",
  "properties": {
    "iso:country":"GB",
    "sg:address":"14 Martin Court, Southbridge Way",
    "sg:city":"Southall",
    "sg:classifiers":[
        {
            "category":"Education",
            "subcategory":"School",
            "type":"Public Place"
        },
        {
            "category":"Education",
            "subcategory":"University",
            "type":"Public Place"
        }
    ],
    "sg:phone":"+44 20 8574 8387",
    "sg:postcode":"UB2 4QW",
    "sg:province":"Greater London",
    "sg:tags":[
        "private",
        "tuition"
    ],
    "wof:name":"Margaret Hegarty",
    "wof:placetype":"venue"
},
  "geometry": {"coordinates":[-0.37978,51.505291],"type":"Point"}
}