{
  "type": "Feature",
  "properties": {
    "addr:full":"Wentworth House, 87 Bradford Street Braintree Essex CM7 9AU",
    "addr:housenumber":"87",
    "addr:postcode":"cm7 9au",
    "addr:street":"Bradford Street",
    "iso:country":"GB",
    "sg:address":"Wentworth House, 87 Bradford Street",
    "sg:city":"Braintree",
    "sg:classifiers":[
        {
            "category":"Shopping",
            "type":"Retail Goods"
        },
        {
            "category":"Manufacturing",
            "subcategory":"Glass & Minerals",
            "type":"Manufacturing & Wholesale Goods"
        }
    ],
    "sg:phone":"+44 1376 552975",
    "sg:postcode":"CM7 9AU",
    "sg:province":"Essex",
    "sg:tags":[
        "mnfrs",
        "fibre",
        "scientific",
        "apparatus",
        "med"
    ],
    "wof:name":"Thies Clima U K",
    "wof:placetype":"venue"
},
  "geometry": {"coordinates":[0.5563,51.887505],"type":"Point"}
}