{
  "type": "Feature",
  "properties": {
    "iso:country":"GB",
    "sg:address":"Linear Park Residential Home, Bradley Road",
    "sg:city":"Newton-le-willows",
    "sg:classifiers":[
        {
            "category":"Health Services",
            "subcategory":"Nursing And Care Facility",
            "type":"Services"
        }
    ],
    "sg:postcode":"WA12 8RA",
    "sg:province":"Cheshire",
    "sg:tags":[
        "home"
    ],
    "wof:name":"Housing With Care Ltd.",
    "wof:placetype":"venue"
},
  "geometry": {"coordinates":[-2.6299650669,53.4412498474],"type":"Point"}
}