{
  "type": "Feature",
  "properties": {
    "iso:country":"GB",
    "sg:address":"Unit 6 Enterprise Centre, Bumpers Way, Bumpers Industrial Estate",
    "sg:city":"Chippenham",
    "sg:classifiers":[
        {
            "category":"Shopping",
            "type":"Retail Goods"
        }
    ],
    "sg:phone":"+44 1249 462655",
    "sg:postcode":"SN14 6QA",
    "sg:province":"Gloucestershire",
    "sg:tags":[
        "med",
        "scientific",
        "apparatus"
    ],
    "wof:name":"Brunel Microscopes Ltd.",
    "wof:placetype":"venue"
},
  "geometry": {"coordinates":[-2.14758,51.464401],"type":"Point"}
}