{
  "type": "Feature",
  "properties": {
    "addr:full":"C/o Carnon Downs Garden Centre, Quenchwell Road Truro Cornwall TR3 6LN",
    "addr:postcode":"tr3 6ln",
    "addr:street":"C;Quenchwell Road",
    "iso:country":"GB",
    "sg:address":"C/o Carnon Downs Garden Centre, Quenchwell Road",
    "sg:city":"Truro",
    "sg:classifiers":[
        {
            "category":"Cafe",
            "type":"Food & Drink"
        }
    ],
    "sg:postcode":"TR3 6LN",
    "sg:province":"Cornwall",
    "sg:tags":[
        "tea",
        "room"
    ],
    "wof:name":"Cherry Garden Tea Room",
    "wof:placetype":"venue"
},
  "geometry": {"coordinates":[-5.08938,50.228642],"type":"Point"}
}