{
  "type": "Feature",
  "properties": {
    "addr:full":"66 Old Christchurch Road Bournemouth Dorset BH1 1LL",
    "addr:housenumber":"66",
    "addr:postcode":"bh1 1ll",
    "addr:street":"Old Christchurch Road",
    "iso:country":"GB",
    "sg:address":"66 Old Christchurch Road",
    "sg:city":"Bournemouth",
    "sg:classifiers":[
        {
            "category":"Shopping",
            "subcategory":"Clothing, Apparel, & Fashions",
            "type":"Retail Goods"
        }
    ],
    "sg:phone":"+44 1202 555537",
    "sg:postcode":"BH1 1LL",
    "sg:province":"Dorset",
    "sg:tags":[
        "shop"
    ],
    "wof:name":"Edinburgh Woollen Mill",
    "wof:placetype":"venue"
},
  "geometry": {"coordinates":[-1.876183033,50.72133255],"type":"Point"}
}