{
  "type": "Feature",
  "properties": {
    "addr:full":"5 Courtrai, Lansdown Castle Dr Cheltenham Gloucestershire GL51 7AF",
    "addr:housenumber":"5",
    "addr:postcode":"gl51 7af",
    "addr:street":"Courtrai Lansdown Castle Dr",
    "iso:country":"GB",
    "sg:address":"5 Courtrai, Lansdown Castle Dr",
    "sg:city":"Cheltenham",
    "sg:classifiers":[
        {
            "category":"Professional",
            "subcategory":"Accounting & Tax Preparation",
            "type":"Services"
        }
    ],
    "sg:phone":"+44 1242 233487",
    "sg:postcode":"GL51 7AF",
    "sg:province":"Gloucestershire",
    "sg:tags":[
        "accountant"
    ],
    "wof:name":"Carey,Robin F,",
    "wof:placetype":"venue"
},
  "geometry": {"coordinates":[-2.103478,51.895432],"type":"Point"}
}