{
  "type": "Feature",
  "properties": {
    "iso:country":"GB",
    "sg:address":"271 Main Rd",
    "sg:city":"Emsworth",
    "sg:classifiers":[
        {
            "category":"Place Of Worship",
            "type":"Public Place"
        }
    ],
    "sg:phone":"+44 1243 372436",
    "sg:postcode":"PO10 8JE",
    "sg:province":"Hampshire",
    "wof:name":"St John The Evangelist C Of E Church",
    "wof:placetype":"venue"
},
  "geometry": {"coordinates":[-0.909713,50.845261],"type":"Point"}
}