{
  "type": "Feature",
  "properties": {
    "addr:full":"1 Hallstile Bank Hexham Northumberland NE46 3PG",
    "addr:housenumber":"1",
    "addr:postcode":"ne46 3pg",
    "addr:street":"Hallstile Bank",
    "iso:country":"GB",
    "sg:address":"1 Hallstile Bank",
    "sg:city":"Hexham",
    "sg:classifiers":[
        {
            "category":"Organizations",
            "subcategory":"Community Association",
            "type":"Services"
        },
        {
            "category":"Organizations",
            "subcategory":"Membership Organization",
            "type":"Services"
        }
    ],
    "sg:phone":"+44 1434 603719",
    "sg:postcode":"NE46 3PG",
    "sg:province":"Northumberland",
    "sg:tags":[
        "club",
        "social"
    ],
    "wof:name":"Hexham & District Ex Service Club",
    "wof:placetype":"venue"
},
  "geometry": {"coordinates":[-2.100939,54.971851],"type":"Point"}
}