{
  "type": "Feature",
  "properties": {
    "iso:country":"GB",
    "sg:address":"Brunel Road",
    "sg:city":"St Leonards-on-sea",
    "sg:classifiers":[
        {
            "category":"Professional",
            "subcategory":"Engineering",
            "type":"Services"
        }
    ],
    "sg:phone":"+44 1424 850860",
    "sg:postcode":"TN38 9RT",
    "sg:province":"East Sussex",
    "sg:tags":[
        "precision",
        "engineer"
    ],
    "wof:name":"G T  Precision Ltd.",
    "wof:placetype":"venue"
},
  "geometry": {"coordinates":[0.531467,50.877029],"type":"Point"}
}