{
  "type": "Feature",
  "properties": {
    "iso:country":"GB",
    "sg:address":"14 Barkham Road",
    "sg:city":"Wokingham",
    "sg:classifiers":[
        {
            "category":"Building & Trades",
            "subcategory":"Construction",
            "type":"Services"
        }
    ],
    "sg:postcode":"RG41 2XP",
    "sg:province":"Berkshire",
    "sg:tags":[
        "dry",
        "lining",
        "plasterers",
        "screeders"
    ],
    "wof:name":"P D Plastering",
    "wof:placetype":"venue"
},
  "geometry": {"coordinates":[-0.842948,51.410301],"type":"Point"}
}