{
  "type": "Feature",
  "properties": {
    "iso:country":"GB",
    "sg:address":"639d Bloxwich Road",
    "sg:city":"Walsall",
    "sg:classifiers":[
        {
            "category":"Shopping",
            "subcategory":"Antiques",
            "type":"Retail Goods"
        }
    ],
    "sg:postcode":"WS3 2BQ",
    "sg:province":"Staffordshire",
    "wof:name":"Cobwebs Antiques",
    "wof:placetype":"venue"
},
  "geometry": {"coordinates":[-1.995692,52.608631],"type":"Point"}
}