{
  "type": "Feature",
  "properties": {
    "addr:full":"34 Francis Street Lincoln Lincolnshire LN5 8QG",
    "addr:housenumber":"34",
    "addr:postcode":"ln5 8qg",
    "addr:street":"Francis Street",
    "iso:country":"GB",
    "sg:address":"34 Francis Street",
    "sg:city":"Lincoln",
    "sg:classifiers":[
        {
            "category":"Arts & Performance",
            "subcategory":"Music",
            "type":"Entertainment"
        }
    ],
    "sg:postcode":"LN5 8QG",
    "sg:province":"Lincolnshire",
    "sg:tags":[
        "mobile",
        "disco"
    ],
    "wof:name":"Cchristopher Rowe",
    "wof:placetype":"venue"
},
  "geometry": {"coordinates":[-0.5496960282,53.2050933838],"type":"Point"}
}