{
  "type": "Feature",
  "properties": {
    "iso:country":"GB",
    "sg:address":"45 Austin Road",
    "sg:city":"Luton",
    "sg:classifiers":[
        {
            "category":"Professional",
            "type":"Services"
        }
    ],
    "sg:phone":"+44 1582 502910",
    "sg:postcode":"LU3 1TY",
    "sg:province":"Bedfordshire",
    "sg:tags":[
        "caterer"
    ],
    "wof:name":"Adept Catering",
    "wof:placetype":"venue"
},
  "geometry": {"coordinates":[-0.432373,51.902187],"type":"Point"}
}