{
  "type": "Feature",
  "properties": {
    "addr:full":"56 Buccleuch Street Dumfries Dumfries and Galloway DG1 2AA",
    "addr:housenumber":"56",
    "addr:postcode":"dg1 2aa",
    "addr:street":"Buccleuch Street",
    "iso:country":"GB",
    "sg:address":"56 Buccleuch Street",
    "sg:city":"Dumfries",
    "sg:classifiers":[
        {
            "category":"Shopping",
            "subcategory":"Gifts & Souvenirs",
            "type":"Retail Goods"
        }
    ],
    "sg:phone":"+44 1387 264050",
    "sg:postcode":"DG1 2AA",
    "sg:province":"Dumfries and Galloway",
    "sg:tags":[
        "shop"
    ],
    "wof:name":"Greyfriars Crafts",
    "wof:placetype":"venue"
},
  "geometry": {"coordinates":[-3.6139240265,55.0701179504],"type":"Point"}
}