{
  "type": "Feature",
  "properties": {
    "addr:full":"2 Horsham Road Littlehampton West Sussex BN17 6BU",
    "addr:postcode":"bn17 6bu",
    "addr:street":"Horsham Road",
    "iso:country":"GB",
    "sg:address":"2 Horsham Road",
    "sg:city":"Littlehampton",
    "sg:classifiers":[
        {
            "category":"Travel",
            "subcategory":"Hotels & Motels",
            "type":"Entertainment"
        }
    ],
    "sg:postcode":"BN17 6BU",
    "sg:province":"West Sussex",
    "sg:tags":[
        "house",
        "guest"
    ],
    "wof:name":"Tudor Lodge Guest House",
    "wof:placetype":"venue"
},
  "geometry": {"coordinates":[-0.530801,50.812386],"type":"Point"}
}