{
  "type": "Feature",
  "properties": {
    "addr:full":"Elmgrove Industrial Estate, Elmgrove London Greater London SW19 4HE",
    "addr:housenumber":"estate",
    "addr:postcode":"sw19 4he",
    "addr:street":"Elmgrove Industrial",
    "iso:country":"GB",
    "sg:address":"Elmgrove Industrial Estate, Elmgrove",
    "sg:city":"London",
    "sg:classifiers":[
        {
            "category":"Retail",
            "subcategory":"Auto Repair",
            "type":"Services"
        }
    ],
    "sg:postcode":"SW19 4HE",
    "sg:province":"Greater London",
    "sg:tags":[
        "modification",
        "garage"
    ],
    "wof:name":"Cox & Buckles Workshop Ltd.",
    "wof:placetype":"venue"
},
  "geometry": {"coordinates":[-0.21514,51.4168701172],"type":"Point"}
}