{
  "type": "Feature",
  "properties": {
    "addr:full":"5 West Shore Road Edinburgh City of Edinburgh EH5 1QB",
    "addr:housenumber":"5",
    "addr:postcode":"eh5 1qb",
    "addr:street":"West Shore Road",
    "iso:country":"GB",
    "sg:address":"5 West Shore Road",
    "sg:city":"Edinburgh",
    "sg:classifiers":[
        {
            "category":"Manufacturing",
            "subcategory":"Rubber & Plastics",
            "type":"Manufacturing & Wholesale Goods"
        }
    ],
    "sg:phone":"+44 131 552 8181",
    "sg:postcode":"EH5 1QB",
    "sg:province":"City of Edinburgh",
    "sg:tags":[
        "supplier",
        "stockist"
    ],
    "wof:name":"Capper",
    "wof:placetype":"venue"
},
  "geometry": {"coordinates":[-3.233382,55.983006],"type":"Point"}
}