{
  "type": "Feature",
  "properties": {
    "addr:full":"21 Gloucester Place London Greater London W1U 8HR",
    "addr:housenumber":"21",
    "addr:postcode":"w1u 8hr",
    "addr:street":"Gloucester Place",
    "iso:country":"GB",
    "sg:address":"21 Gloucester Place",
    "sg:city":"London",
    "sg:classifiers":[
        {
            "category":"Real Estate",
            "subcategory":"Surveying",
            "type":"Services"
        }
    ],
    "sg:phone":"+44 20 7486 4734",
    "sg:postcode":"W1U 8HR",
    "sg:province":"Greater London",
    "sg:tags":[
        "surveyor",
        "valuer"
    ],
    "wof:name":"Springett Gould & Keel",
    "wof:placetype":"venue"
},
  "geometry": {"coordinates":[-0.1577119976,51.5171737671],"type":"Point"}
}