{
  "type": "Feature",
  "properties": {
    "iso:country":"GB",
    "sg:address":"19 Wren Close, Bishops Hull",
    "sg:city":"Taunton",
    "sg:classifiers":[
        {
            "category":"Building & Trades",
            "subcategory":"Cleaning & Sanitation",
            "type":"Services"
        }
    ],
    "sg:phone":"+44 1823 275952",
    "sg:postcode":"TA1 5EZ",
    "sg:province":"Somerset",
    "sg:tags":[
        "cleaner",
        "window"
    ],
    "wof:name":"J A Hudson",
    "wof:placetype":"venue"
},
  "geometry": {"coordinates":[-3.127285,51.016159],"type":"Point"}
}