{
  "type": "Feature",
  "properties": {
    "addr:full":"The Surgery, Chapel La Colchester Essex CO7 7AG",
    "addr:postcode":"co7 7ag",
    "iso:country":"GB",
    "sg:address":"The Surgery, Chapel La",
    "sg:city":"Colchester",
    "sg:classifiers":[
        {
            "category":"Health Services",
            "subcategory":"Doctor",
            "type":"Services"
        }
    ],
    "sg:phone":"+44 1206 823940",
    "sg:postcode":"CO7 7AG",
    "sg:province":"Essex",
    "sg:tags":[
        "practitioners"
    ],
    "wof:name":"Rodrigues, E A",
    "wof:placetype":"venue"
},
  "geometry": {"coordinates":[0.9963899851,51.8812294006],"type":"Point"}
}