{
  "type": "Feature",
  "properties": {
    "addr:full":"694 Goffs Lane, Goffs Oak Waltham Cross Greater London EN7 5ET",
    "addr:housenumber":"694",
    "addr:postcode":"en7 5et",
    "addr:street":"Goffs Lane;Cross",
    "iso:country":"GB",
    "sg:address":"694 Goffs Lane, Goffs Oak",
    "sg:city":"Waltham Cross",
    "sg:classifiers":[
        {
            "category":"Shopping",
            "subcategory":"Pharmacy",
            "type":"Retail Goods"
        }
    ],
    "sg:phone":"+44 1707 875083",
    "sg:postcode":"EN7 5ET",
    "sg:province":"Greater London",
    "sg:tags":[
        "pharmacist",
        "chemist"
    ],
    "wof:name":"J V Doshi Pharmacy",
    "wof:placetype":"venue"
},
  "geometry": {"coordinates":[-0.0868860036,51.7102203369],"type":"Point"}
}