{
  "type": "Feature",
  "properties": {
    "addr:full":"1 Norwood Beverley East Riding of Yorkshire HU17 9ET",
    "addr:housenumber":"1",
    "addr:postcode":"hu17 9et",
    "addr:street":"Norwood Beverley",
    "iso:country":"GB",
    "sg:address":"1 Norwood",
    "sg:city":"Beverley",
    "sg:classifiers":[
        {
            "category":"Insurance",
            "subcategory":"Insurance Agent",
            "type":"Services"
        }
    ],
    "sg:postcode":"HU17 9ET",
    "sg:province":"East Riding of Yorkshire",
    "wof:name":"Swinton",
    "wof:placetype":"venue"
},
  "geometry": {"coordinates":[-0.431524,53.84515],"type":"Point"}
}