{
  "type": "Feature",
  "properties": {
    "iso:country":"GB",
    "sg:address":"The View Station Lane, Pelton",
    "sg:city":"Chester-le-street",
    "sg:classifiers":[
        {
            "category":"Real Estate",
            "subcategory":"Real Estate Services",
            "type":"Services"
        },
        {
            "category":"Building & Trades",
            "subcategory":"Equipment Rental",
            "type":"Services"
        }
    ],
    "sg:phone":"+44 191 387 4000",
    "sg:postcode":"DH2 2RE",
    "sg:province":"Durham",
    "sg:tags":[
        "hire",
        "leasing",
        "plant",
        "machinery"
    ],
    "wof:name":"Chester-le-Street Plant Hire",
    "wof:placetype":"venue"
},
  "geometry": {"coordinates":[-1.578884,54.854855],"type":"Point"}
}