{
  "type": "Feature",
  "properties": {
    "iso:country":"GB",
    "sg:address":"Ashlyn, Wrington Road, Congresbury",
    "sg:city":"Bristol",
    "sg:classifiers":[
        {
            "category":"Building & Trades",
            "subcategory":"Construction",
            "type":"Services"
        }
    ],
    "sg:postcode":"BS49 5AN",
    "sg:province":"Somerset",
    "sg:tags":[
        "joiner",
        "carpenter"
    ],
    "wof:name":"Tony Burford",
    "wof:placetype":"venue"
},
  "geometry": {"coordinates":[-2.806914,51.366467],"type":"Point"}
}