{
  "type": "Feature",
  "properties": {
    "addr:full":"40a Piccadilly Bradford West Yorkshire BD1 3NN",
    "addr:housenumber":"40a",
    "addr:postcode":"bd1 3nn",
    "addr:street":"Piccadilly Bradford West",
    "iso:country":"GB",
    "sg:address":"40a Piccadilly",
    "sg:city":"Bradford",
    "sg:classifiers":[
        {
            "category":"Professional",
            "subcategory":"Lawyer & Legal Services",
            "type":"Services"
        }
    ],
    "sg:phone":"+44 1274 720225",
    "sg:postcode":"BD1 3NN",
    "sg:province":"West Yorkshire",
    "sg:tags":[
        "advice",
        "counselling"
    ],
    "wof:name":"Bradford Association For The Elderly",
    "wof:placetype":"venue"
},
  "geometry": {"coordinates":[-1.7546550035,53.796661377],"type":"Point"}
}