{
  "type": "Feature",
  "properties": {
    "addr:full":"Craven House, 40-44 Uxbridge Road London Greater London W5 2BS",
    "addr:housenumber":"40-44",
    "addr:postcode":"w5 2bs",
    "addr:street":"Uxbridge Road",
    "iso:country":"GB",
    "sg:address":"Craven House, 40-44 Uxbridge Road",
    "sg:city":"London",
    "sg:classifiers":[
        {
            "category":"Real Estate",
            "subcategory":"Surveying",
            "type":"Services"
        }
    ],
    "sg:phone":"+44 20 8579 1370",
    "sg:postcode":"W5 2BS",
    "sg:province":"Greater London",
    "sg:tags":[
        "surveyor",
        "land"
    ],
    "wof:name":"Countrywide Surveyors",
    "wof:placetype":"venue"
},
  "geometry": {"coordinates":[-0.293193996,51.5117988586],"type":"Point"}
}