{
  "type": "Feature",
  "properties": {
    "addr:full":"44 London Road Enfield Greater London EN2 6EF",
    "addr:housenumber":"44",
    "addr:postcode":"en2 6ef",
    "addr:street":"London Road",
    "iso:country":"GB",
    "sg:address":"44 London Road",
    "sg:city":"Enfield",
    "sg:classifiers":[
        {
            "category":"Home & Garden",
            "subcategory":"Furniture",
            "type":"Retail Goods"
        }
    ],
    "sg:phone":"+44 20 8363 0359",
    "sg:postcode":"EN2 6EF",
    "sg:province":"Greater London",
    "wof:name":"Furncrafts Ltd.",
    "wof:placetype":"venue"
},
  "geometry": {"coordinates":[-0.0800969973,51.6505966187],"type":"Point"}
}