{
  "type": "Feature",
  "properties": {
    "addr:full":"1a Boldero Rd Bury St Edmunds Suffolk IP32 7BS",
    "addr:housenumber":"1a",
    "addr:postcode":"ip32 7bs",
    "addr:street":"Boldero Rd",
    "iso:country":"GB",
    "sg:address":"1a Boldero Rd",
    "sg:city":"Bury St Edmunds",
    "sg:classifiers":[
        {
            "category":"Shopping",
            "type":"Retail Goods"
        }
    ],
    "sg:phone":"+44 1284 755535",
    "sg:postcode":"IP32 7BS",
    "sg:province":"Suffolk",
    "sg:tags":[
        "part",
        "accessory"
    ],
    "wof:name":"Anglia Motor Parts",
    "wof:placetype":"venue"
},
  "geometry": {"coordinates":[0.7480660081,52.240436554],"type":"Point"}
}