{
  "type": "Feature",
  "properties": {
    "iso:country":"GB",
    "sg:address":"Sawdon",
    "sg:city":"Scarborough",
    "sg:classifiers":[
        {
            "category":"Home & Garden",
            "subcategory":"Building Materials",
            "type":"Retail Goods"
        }
    ],
    "sg:postcode":"YO13 9DU",
    "sg:province":"North Yorkshire",
    "sg:tags":[
        "plaster",
        "ware"
    ],
    "wof:name":"Brook,David,",
    "wof:placetype":"venue"
},
  "geometry": {"coordinates":[-0.5584179759,54.2525367737],"type":"Point"}
}