{
  "type": "Feature",
  "properties": {
    "iso:country":"GB",
    "sg:address":"Woolrich House, Colts Home Road, Old Wolverton",
    "sg:city":"Milton Keynes",
    "sg:classifiers":[
        {
            "category":"Freight",
            "type":"Transportation"
        }
    ],
    "sg:phone":"+44 1908 220252",
    "sg:postcode":"MK12 5QD",
    "sg:province":"Buckinghamshire",
    "sg:tags":[
        "haulage",
        "road"
    ],
    "wof:name":"J D Woolrich & Son Ltd.",
    "wof:placetype":"venue"
},
  "geometry": {"coordinates":[-0.814784,52.068474],"type":"Point"}
}