{
  "type": "Feature",
  "properties": {
    "iso:country":"GB",
    "sg:address":"5 The Close",
    "sg:city":"Salisbury",
    "sg:classifiers":[
        {
            "category":"Education",
            "subcategory":"Music School",
            "type":"Public Place"
        }
    ],
    "sg:phone":"+44 1722 331436",
    "sg:postcode":"SP1 2EF",
    "sg:province":"Wiltshire",
    "sg:tags":[
        "teacher"
    ],
    "wof:name":"Rowan  Wright",
    "wof:placetype":"venue"
},
  "geometry": {"coordinates":[-1.7918490171,51.0653533936],"type":"Point"}
}