{
  "type": "Feature",
  "properties": {
    "addr:full":"Fox Covert Barn, Thorpe Waterville Kettering Northamptonshire NN14 3ED",
    "addr:postcode":"nn14 3ed",
    "addr:street":"Fox Covert",
    "iso:country":"GB",
    "sg:address":"Fox Covert Barn, Thorpe Waterville",
    "sg:city":"Kettering",
    "sg:classifiers":[
        {
            "category":"Building & Trades",
            "subcategory":"Construction",
            "type":"Services"
        }
    ],
    "sg:phone":"+44 1832 720214",
    "sg:postcode":"NN14 3ED",
    "sg:province":"Northamptonshire",
    "sg:tags":[
        "builder"
    ],
    "wof:name":"Welland Properties (Peterborough) Ltd.",
    "wof:placetype":"venue"
},
  "geometry": {"coordinates":[-0.4939810038,52.4224052429],"type":"Point"}
}