{
  "type": "Feature",
  "properties": {
    "iso:country":"GB",
    "sg:address":"9 Windmill Drive",
    "sg:city":"Bexhill-on-sea",
    "sg:classifiers":[
        {
            "category":"Personal",
            "subcategory":"Beauty Salon",
            "type":"Services"
        },
        {
            "category":"Personal",
            "subcategory":"Barber",
            "type":"Services"
        }
    ],
    "sg:phone":"+44 1424 215348",
    "sg:postcode":"TN39 4DG",
    "sg:province":"East Sussex",
    "sg:tags":[
        "unisex",
        "hairdresser"
    ],
    "wof:name":"Images Hair Salon",
    "wof:placetype":"venue"
},
  "geometry": {"coordinates":[0.462873,50.852497],"type":"Point"}
}