{
  "type": "Feature",
  "properties": {
    "addr:full":"Unit 1 Aylesbury Buckinghamshire HP19 8UG",
    "addr:housenumber":"unit 1",
    "addr:postcode":"hp19 8ug",
    "iso:country":"GB",
    "sg:address":"Unit 1",
    "sg:city":"Aylesbury",
    "sg:classifiers":[
        {
            "category":"Farming",
            "subcategory":"Farm",
            "type":"Manufacturing & Wholesale Goods"
        }
    ],
    "sg:postcode":"HP19 8UG",
    "sg:province":"Buckinghamshire",
    "sg:tags":[
        "agricultural"
    ],
    "wof:name":"First Engineering Products",
    "wof:placetype":"venue"
},
  "geometry": {"coordinates":[-0.8443890214,51.8231887817],"type":"Point"}
}