{
  "type": "Feature",
  "properties": {
    "iso:country":"GB",
    "sg:address":"Chestnut House, North Street",
    "sg:city":"Rugby",
    "sg:classifiers":[
        {
            "category":"Fast Food",
            "type":"Food & Drink"
        }
    ],
    "sg:phone":"+44 1788 543130",
    "sg:postcode":"CV21 2AG",
    "sg:province":"Warwickshire",
    "sg:tags":[
        "away",
        "take"
    ],
    "wof:name":"Upper Crust Two",
    "wof:placetype":"venue"
},
  "geometry": {"coordinates":[-1.2626589537,52.3740959167],"type":"Point"}
}