{
  "type": "Feature",
  "properties": {
    "addr:full":"Ashwellthorpe Norwich Norfolk NR16 1EX",
    "addr:postcode":"nr16 1ex",
    "addr:street":"Norwich",
    "iso:country":"GB",
    "sg:address":"Ashwellthorpe",
    "sg:city":"Norwich",
    "sg:classifiers":[
        {
            "category":"Organizations",
            "subcategory":"Non-profit Organization",
            "type":"Services"
        }
    ],
    "sg:phone":"+44 1508 489449",
    "sg:postcode":"NR16 1EX",
    "sg:province":"Norfolk",
    "sg:tags":[
        "charitable",
        "organisation",
        "voluntary",
        "charity"
    ],
    "wof:name":"Disabled Drivers Association",
    "wof:placetype":"venue"
},
  "geometry": {"coordinates":[1.1789610386,52.5414924622],"type":"Point"}
}