{
  "type": "Feature",
  "properties": {
    "addr:full":"The Old School, Gundry Lane Bridport Dorset DT6 3RL",
    "addr:postcode":"dt6 3rl",
    "addr:street":"Gundry Lane",
    "iso:country":"GB",
    "sg:address":"The Old School, Gundry Lane",
    "sg:city":"Bridport",
    "sg:classifiers":[
        {
            "category":"Shopping",
            "subcategory":"Clothing, Apparel, & Fashions",
            "type":"Retail Goods"
        },
        {
            "category":"Shopping",
            "subcategory":"Baby Store",
            "type":"Retail Goods"
        },
        {
            "category":"Professional",
            "subcategory":"Business Services",
            "type":"Services"
        }
    ],
    "sg:phone":"+44 1308 422552",
    "sg:postcode":"DT6 3RL",
    "sg:province":"Dorset",
    "sg:tags":[
        "agent",
        "accessory",
        "nursery",
        "export",
        "babywear",
        "child",
        "import"
    ],
    "wof:name":"Babygear",
    "wof:placetype":"venue"
},
  "geometry": {"coordinates":[-2.7580189705,50.7335662842],"type":"Point"}
}