{
  "type": "Feature",
  "properties": {
    "iso:country":"GB",
    "sg:address":"Powney Cottage, Powney Street, Milden",
    "sg:city":"Ipswich",
    "sg:classifiers":[
        {
            "category":"Professional",
            "type":"Services"
        }
    ],
    "sg:postcode":"IP7 7AL",
    "sg:province":"Suffolk",
    "sg:tags":[
        "entertainer"
    ],
    "wof:name":"Rosie Perkins Puppets",
    "wof:placetype":"venue"
},
  "geometry": {"coordinates":[0.848232,52.077614],"type":"Point"}
}