{
  "type": "Feature",
  "properties": {
    "addr:full":"17 Market Street Gainsborough Lincolnshire DN21 2BL",
    "addr:housenumber":"17",
    "addr:postcode":"dn21 2bl",
    "addr:street":"Market Street",
    "iso:country":"GB",
    "sg:address":"17 Market Street",
    "sg:city":"Gainsborough",
    "sg:classifiers":[
        {
            "category":"Shopping",
            "subcategory":"Music",
            "type":"Retail Goods"
        }
    ],
    "sg:postcode":"DN21 2BL",
    "sg:province":"Lincolnshire",
    "sg:tags":[
        "record",
        "tape",
        "cd"
    ],
    "wof:name":"Musique",
    "wof:placetype":"venue"
},
  "geometry": {"coordinates":[-0.7749109864,53.3998908997],"type":"Point"}
}