{
  "type": "Feature",
  "properties": {
    "iso:country":"GB",
    "sg:address":"Station Rd",
    "sg:city":"Chester",
    "sg:classifiers":[
        {
            "category":"Building & Trades",
            "subcategory":"Landscaping Services",
            "type":"Services"
        }
    ],
    "sg:phone":"+44 1244 311550",
    "sg:postcode":"CH1 3DW",
    "sg:province":"Cheshire",
    "sg:tags":[
        "designer",
        "architect",
        "landscape"
    ],
    "wof:name":"Chris Blandford Associates",
    "wof:placetype":"venue"
},
  "geometry": {"coordinates":[-2.8808040619,53.1965904236],"type":"Point"}
}