{
  "type": "Feature",
  "properties": {
    "iso:country":"GB",
    "sg:address":"4 The Hilders",
    "sg:city":"Ashtead",
    "sg:classifiers":[
        {
            "category":"Travel",
            "subcategory":"Travel Agent",
            "type":"Entertainment"
        }
    ],
    "sg:postcode":"KT21 1LS",
    "sg:province":"Surrey",
    "wof:name":"Spear Travels",
    "wof:placetype":"venue"
},
  "geometry": {"coordinates":[-0.285771,51.315388],"type":"Point"}
}