{
  "type": "Feature",
  "properties": {
    "addr:full":"11 Glencraig Street, Drongan Ayr East Ayrshire KA6 7AS",
    "addr:housenumber":"11",
    "addr:postcode":"ka6 7as",
    "addr:street":"Glencraig Street Drongan;East",
    "iso:country":"GB",
    "sg:address":"11 Glencraig Street, Drongan",
    "sg:city":"Ayr",
    "sg:classifiers":[
        {
            "category":"Professional",
            "type":"Services"
        }
    ],
    "sg:phone":"+44 1292 591661",
    "sg:postcode":"KA6 7AS",
    "sg:province":"East Ayrshire",
    "sg:tags":[
        "caterer"
    ],
    "wof:name":"Eighty 9",
    "wof:placetype":"venue"
},
  "geometry": {"coordinates":[-4.459923,55.435638],"type":"Point"}
}