{
  "type": "Feature",
  "properties": {
    "addr:full":"26 The Moat, Charing Ashford Kent TN27 0JH",
    "addr:housenumber":"26",
    "addr:postcode":"tn27 0jh",
    "addr:street":"The Moat",
    "iso:country":"GB",
    "sg:address":"26 The Moat, Charing",
    "sg:city":"Ashford",
    "sg:classifiers":[
        {
            "category":"Building & Trades",
            "subcategory":"Construction",
            "type":"Services"
        }
    ],
    "sg:phone":"+44 1233 712368",
    "sg:postcode":"TN27 0JH",
    "sg:province":"Kent",
    "sg:tags":[
        "builder"
    ],
    "wof:name":"Peter Humphries Carpentry & Building Ltd.",
    "wof:placetype":"venue"
},
  "geometry": {"coordinates":[0.790926,51.211514],"type":"Point"}
}