{
  "type": "Feature",
  "properties": {
    "iso:country":"GB",
    "sg:address":"12 Portland Street",
    "sg:city":"Southampton",
    "sg:classifiers":[
        {
            "category":"Building & Trades",
            "subcategory":"Landscaping Services",
            "type":"Services"
        }
    ],
    "sg:postcode":"SO14 7EB",
    "sg:province":"Hampshire",
    "sg:tags":[
        "consultant"
    ],
    "wof:name":"Rosedale Developments Ltd",
    "wof:placetype":"venue"
},
  "geometry": {"coordinates":[-1.405966,50.904594],"type":"Point"}
}