{
  "type": "Feature",
  "properties": {
    "iso:country":"GB",
    "sg:address":"123 High Street",
    "sg:city":"Newport",
    "sg:classifiers":[
        {
            "category":"Personal",
            "type":"Services"
        },
        {
            "category":"Shopping",
            "subcategory":"Bridal",
            "type":"Retail Goods"
        }
    ],
    "sg:phone":"+44 1952 814631",
    "sg:postcode":"TF10 7BB",
    "sg:province":"Shropshire",
    "sg:tags":[
        "shop",
        "gown",
        "wedding"
    ],
    "wof:name":"Renaissance",
    "wof:placetype":"venue"
},
  "geometry": {"coordinates":[-2.3806180954,52.7701759338],"type":"Point"}
}