{
  "type": "Feature",
  "properties": {
    "addr:full":"6 Long Lane London Greater London EC1A 9HF",
    "addr:housenumber":"6",
    "addr:postcode":"ec1a 9hf",
    "addr:street":"Long Lane",
    "iso:country":"GB",
    "sg:address":"6 Long Lane",
    "sg:city":"London",
    "sg:classifiers":[
        {
            "category":"Real Estate",
            "subcategory":"Surveying",
            "type":"Services"
        }
    ],
    "sg:postcode":"EC1A 9HF",
    "sg:province":"Greater London",
    "sg:tags":[
        "surveyor",
        "valuer"
    ],
    "wof:name":"Anstey Horne & Co.",
    "wof:placetype":"venue"
},
  "geometry": {"coordinates":[-0.098595,51.519882],"type":"Point"}
}