{
  "type": "Feature",
  "properties": {
    "addr:full":"5 Cleeve House, Calvert Avenue London Greater London E2 7JJ",
    "addr:housenumber":"5;house",
    "addr:postcode":"e2 7jj",
    "addr:street":"Cleeve;Calvert Avenue",
    "iso:country":"GB",
    "sg:address":"5 Cleeve House, Calvert Avenue",
    "sg:city":"London",
    "sg:classifiers":[
        {
            "category":"Building & Trades",
            "subcategory":"Construction",
            "type":"Services"
        }
    ],
    "sg:postcode":"E2 7JJ",
    "sg:province":"Greater London",
    "sg:tags":[
        "builder"
    ],
    "wof:name":"P Eustace & Son Ltd.",
    "wof:placetype":"venue"
},
  "geometry": {"coordinates":[-0.0771349967,51.5262985229],"type":"Point"}
}