{
  "type": "Feature",
  "properties": {
    "iso:country":"GB",
    "sg:address":"Crown Road",
    "sg:city":"Norwich",
    "sg:classifiers":[
        {
            "category":"Food & Beverages",
            "subcategory":"Supermarket",
            "type":"Retail Goods"
        }
    ],
    "sg:phone":"+44 1603 279324",
    "sg:postcode":"NR10 5EN",
    "sg:province":"Norfolk",
    "wof:name":"Powell Country Stores",
    "wof:placetype":"venue"
},
  "geometry": {"coordinates":[1.300994,52.753071],"type":"Point"}
}