{
  "type": "Feature",
  "properties": {
    "addr:full":"D S House, 306 High Street Croydon Surrey CR0 1NG",
    "addr:housenumber":"s;306",
    "addr:postcode":"cr0 1ng",
    "addr:street":"D;High Street",
    "iso:country":"GB",
    "sg:address":"D S House, 306 High Street",
    "sg:city":"Croydon",
    "sg:classifiers":[
        {
            "category":"Retail",
            "subcategory":"Laundry & Dry Cleaning",
            "type":"Services"
        }
    ],
    "sg:phone":"+44 20 8669 1460",
    "sg:postcode":"CR0 1NG",
    "sg:province":"Surrey",
    "sg:tags":[
        "alteration"
    ],
    "wof:name":"Hackbridge Cleaners Ltd.",
    "wof:placetype":"venue"
},
  "geometry": {"coordinates":[-0.0993859991,51.368106842],"type":"Point"}
}