{
  "type": "Feature",
  "properties": {
    "addr:full":"Quorn Road Rushden Bedfordshire NN10 9UU",
    "addr:postcode":"nn10 9uu",
    "addr:street":"Quorn Road",
    "iso:country":"GB",
    "sg:address":"Quorn Road",
    "sg:city":"Rushden",
    "sg:classifiers":[
        {
            "category":"Autos & Motor Vehicles",
            "subcategory":"Automobile Sales",
            "type":"Retail Goods"
        }
    ],
    "sg:postcode":"NN10 9UU",
    "sg:province":"Bedfordshire",
    "sg:tags":[
        "car"
    ],
    "wof:name":"Roger Denton Motors",
    "wof:placetype":"venue"
},
  "geometry": {"coordinates":[-0.607656,52.29483],"type":"Point"}
}