{
  "type": "Feature",
  "properties": {
    "addr:full":"Broad La Goole East Riding of Yorkshire DN14 9AS",
    "addr:postcode":"dn14 9as",
    "iso:country":"GB",
    "sg:address":"Broad La",
    "sg:city":"Goole",
    "sg:classifiers":[
        {
            "category":"Bars & Pubs",
            "type":"Food & Drink"
        }
    ],
    "sg:phone":"+44 1405 785273",
    "sg:postcode":"DN14 9AS",
    "sg:province":"East Riding of Yorkshire",
    "sg:tags":[
        "pubs",
        "inn"
    ],
    "wof:name":"Three Horse Shoes",
    "wof:placetype":"venue"
},
  "geometry": {"coordinates":[-1.0363440514,53.648021698],"type":"Point"}
}