{
  "type": "Feature",
  "properties": {
    "iso:country":"GB",
    "sg:address":"20a Church Street",
    "sg:city":"Helston",
    "sg:classifiers":[
        {
            "category":"Home & Garden",
            "subcategory":"Household Appliances",
            "type":"Retail Goods"
        }
    ],
    "sg:postcode":"TR13 8TG",
    "sg:province":"Cornwall",
    "sg:tags":[
        "electrical",
        "domestic"
    ],
    "wof:name":"Gwerthjy Tredanek",
    "wof:placetype":"venue"
},
  "geometry": {"coordinates":[-5.274845,50.101757],"type":"Point"}
}