{
  "type": "Feature",
  "properties": {
    "iso:country":"GB",
    "sg:address":"7 Harvest Road, Maidenbower",
    "sg:city":"Crawley",
    "sg:classifiers":[
        {
            "category":"Shopping",
            "subcategory":"Pharmacy",
            "type":"Retail Goods"
        }
    ],
    "sg:phone":"+44 1293 888411",
    "sg:postcode":"RH10 7RA",
    "sg:province":"Surrey",
    "sg:tags":[
        "pharmacist",
        "chemist"
    ],
    "wof:name":"Moss Chemists",
    "wof:placetype":"venue"
},
  "geometry": {"coordinates":[-0.151735,51.10717],"type":"Point"}
}