{
  "type": "Feature",
  "properties": {
    "addr:full":"87 Charnock Dale Rd Sheffield Derbyshire S12 3HR",
    "addr:housenumber":"87",
    "addr:postcode":"s12 3hr",
    "addr:street":"Charnock Dale Rd",
    "iso:country":"GB",
    "sg:address":"87 Charnock Dale Rd",
    "sg:city":"Sheffield",
    "sg:classifiers":[
        {
            "category":"Health Services",
            "subcategory":"Health Practitioner",
            "type":"Services"
        }
    ],
    "sg:phone":"+44 114 264 4455",
    "sg:postcode":"S12 3HR",
    "sg:province":"Derbyshire",
    "sg:tags":[
        "homoeopathic"
    ],
    "wof:name":"Grants Pharmacy",
    "wof:placetype":"venue"
},
  "geometry": {"coordinates":[-1.4198850393,53.3395996094],"type":"Point"}
}