{
  "type": "Feature",
  "properties": {
    "iso:country":"GB",
    "sg:address":"Thistleton House, Fleetwood Road, Thistleton",
    "sg:city":"Preston",
    "sg:classifiers":[
        {
            "category":"Professional",
            "subcategory":"Management & Consulting",
            "type":"Services"
        },
        {
            "category":"Communications",
            "subcategory":"Television Station",
            "type":"Services"
        }
    ],
    "sg:phone":"+44 1995 671571",
    "sg:postcode":"PR4 3YA",
    "sg:province":"Lancashire",
    "sg:tags":[
        "consultant",
        "telephone",
        "business",
        "equipment"
    ],
    "wof:name":"Advance Consultants Services Ltd.",
    "wof:placetype":"venue"
},
  "geometry": {"coordinates":[-2.894915,53.814056],"type":"Point"}
}