{
  "type": "Feature",
  "properties": {
    "iso:country":"GB",
    "sg:address":"Alverton Grn",
    "sg:city":"Middlesbrough",
    "sg:classifiers":[
        {
            "category":"Real Estate",
            "subcategory":"Real Estate Agent",
            "type":"Services"
        }
    ],
    "sg:phone":"+44 1642 247063",
    "sg:postcode":"TS3 9QP",
    "sg:province":"North Yorkshire",
    "wof:name":"Alverton Green Sheltered Housing",
    "wof:placetype":"venue"
},
  "geometry": {"coordinates":[-1.182328,54.562023],"type":"Point"}
}