{
  "type": "Feature",
  "properties": {
    "addr:full":"12a Sandwell Mansions, West End Lane London Greater London NW6 1XL",
    "addr:housenumber":"12a",
    "addr:postcode":"nw6 1xl",
    "addr:street":"West End Lane",
    "iso:country":"GB",
    "sg:address":"12a Sandwell Mansions, West End Lane",
    "sg:city":"London",
    "sg:classifiers":[
        {
            "category":"Professional",
            "subcategory":"Accounting & Tax Preparation",
            "type":"Services"
        }
    ],
    "sg:phone":"+44 20 7431 4336",
    "sg:postcode":"NW6 1XL",
    "sg:province":"Greater London",
    "sg:tags":[
        "accountant"
    ],
    "wof:name":"Ionian Accounting Ltd.",
    "wof:placetype":"venue"
},
  "geometry": {"coordinates":[-0.19173,51.549259],"type":"Point"}
}