{
  "type": "Feature",
  "properties": {
    "addr:full":"72 Thoday Street Cambridge Cambridgeshire CB1 3AX",
    "addr:housenumber":"72",
    "addr:postcode":"cb1 3ax",
    "addr:street":"Thoday Street",
    "iso:country":"GB",
    "sg:address":"72 Thoday Street",
    "sg:city":"Cambridge",
    "sg:classifiers":[
        {
            "category":"Bars & Pubs",
            "type":"Food & Drink"
        }
    ],
    "sg:phone":"+44 1223 247236",
    "sg:postcode":"CB1 3AX",
    "sg:province":"Cambridgeshire",
    "sg:tags":[
        "pubs",
        "inn"
    ],
    "wof:name":"The Empress",
    "wof:placetype":"venue"
},
  "geometry": {"coordinates":[0.1474560052,52.1993026733],"type":"Point"}
}