{
  "type": "Feature",
  "properties": {
    "addr:full":"11 Waltham Road, Scartho Grimsby Lincolnshire DN33 2LY",
    "addr:housenumber":"11",
    "addr:postcode":"dn33 2ly",
    "addr:street":"Waltham Road",
    "iso:country":"GB",
    "sg:address":"11 Waltham Road, Scartho",
    "sg:city":"Grimsby",
    "sg:classifiers":[
        {
            "category":"Shopping",
            "subcategory":"Clothing, Apparel, & Fashions",
            "type":"Retail Goods"
        }
    ],
    "sg:phone":"+44 1472 877235",
    "sg:postcode":"DN33 2LY",
    "sg:province":"Lincolnshire",
    "sg:tags":[
        "shop"
    ],
    "wof:name":"Christine Ann Ladies Fashions",
    "wof:placetype":"venue"
},
  "geometry": {"coordinates":[-0.09298,53.537411],"type":"Point"}
}