{
  "type": "Feature",
  "properties": {
    "addr:full":"The Vicarage, Richard Avenue, Brightlingsea Colchester Essex CO7 0LP",
    "addr:postcode":"co7 0lp",
    "addr:street":"Richard Avenue",
    "iso:country":"GB",
    "sg:address":"The Vicarage, Richard Avenue, Brightlingsea",
    "sg:city":"Colchester",
    "sg:classifiers":[
        {
            "category":"Organizations",
            "subcategory":"Religious Organization",
            "type":"Services"
        }
    ],
    "sg:phone":"+44 1206 302378",
    "sg:postcode":"CO7 0LP",
    "sg:province":"Essex",
    "sg:tags":[
        "organisation",
        "place",
        "worship"
    ],
    "wof:name":"St James Church Office",
    "wof:placetype":"venue"
},
  "geometry": {"coordinates":[1.02805,51.812683],"type":"Point"}
}