{
  "type": "Feature",
  "properties": {
    "iso:country":"GB",
    "sg:address":"Rudd Lane, Upper Timsbury",
    "sg:city":"Romsey",
    "sg:classifiers":[
        {
            "category":"Farming",
            "subcategory":"Livestock Farm",
            "type":"Manufacturing & Wholesale Goods"
        }
    ],
    "sg:postcode":"SO51 0NU",
    "sg:province":"Hampshire",
    "sg:tags":[
        "others"
    ],
    "wof:name":"P G & U Pratt",
    "wof:placetype":"venue"
},
  "geometry": {"coordinates":[-1.505119,51.032299],"type":"Point"}
}