{
  "type": "Feature",
  "properties": {
    "iso:country":"GB",
    "sg:address":"Beech Rise, 13 Hart Hill La",
    "sg:city":"Luton",
    "sg:classifiers":[
        {
            "category":"Professional",
            "subcategory":"Management & Consulting",
            "type":"Services"
        }
    ],
    "sg:postcode":"LU2 0AZ",
    "sg:province":"Bedfordshire",
    "sg:tags":[
        "consultant",
        "business"
    ],
    "wof:name":"McKay,Hugh,",
    "wof:placetype":"venue"
},
  "geometry": {"coordinates":[-0.4032900035,51.8813514709],"type":"Point"}
}