{
  "type": "Feature",
  "properties": {
    "iso:country":"GB",
    "sg:address":"6 Turnpike Lane, Hornsey",
    "sg:city":"London",
    "sg:classifiers":[
        {
            "category":"Professional",
            "subcategory":"Accounting & Tax Preparation",
            "type":"Services"
        }
    ],
    "sg:phone":"+44 20 8889 8802",
    "sg:postcode":"N8 0PT",
    "sg:province":"Greater London",
    "sg:tags":[
        "accountant"
    ],
    "wof:name":"Ajay Associates",
    "wof:placetype":"venue"
},
  "geometry": {"coordinates":[-0.1039690003,51.5901489258],"type":"Point"}
}