{
  "type": "Feature",
  "properties": {
    "addr:full":"Brook House, South St Brentwood Essex CM14 4BJ",
    "addr:postcode":"cm14 4bj",
    "addr:street":"South St",
    "iso:country":"GB",
    "sg:address":"Brook House, South St",
    "sg:city":"Brentwood",
    "sg:classifiers":[
        {
            "category":"Professional",
            "subcategory":"Employment Agencies",
            "type":"Services"
        }
    ],
    "sg:phone":"+44 1277 261611",
    "sg:postcode":"CM14 4BJ",
    "sg:province":"Essex",
    "sg:tags":[
        "consultant"
    ],
    "wof:name":"Personnel & Technical Plus",
    "wof:placetype":"venue"
},
  "geometry": {"coordinates":[0.3017149866,51.6190071106],"type":"Point"}
}