{
  "type": "Feature",
  "properties": {
    "addr:full":"80 A Central Drive Blackpool Lancashire FY1 5QD",
    "addr:housenumber":"80 a",
    "addr:postcode":"fy1 5qd",
    "addr:street":"Central Drive",
    "iso:country":"GB",
    "sg:address":"80 A Central Drive",
    "sg:city":"Blackpool",
    "sg:classifiers":[
        {
            "category":"Shopping",
            "subcategory":"Clothing, Apparel, & Fashions",
            "type":"Retail Goods"
        }
    ],
    "sg:postcode":"FY1 5QD",
    "sg:province":"Lancashire",
    "sg:tags":[
        "ladieswear"
    ],
    "wof:name":"Soda",
    "wof:placetype":"venue"
},
  "geometry": {"coordinates":[-3.050784111,53.8129081726],"type":"Point"}
}