{
  "type": "Feature",
  "properties": {
    "iso:country":"GB",
    "sg:address":"16 West Row",
    "sg:city":"Barrow-in-furness",
    "sg:classifiers":[
        {
            "category":"Retail",
            "subcategory":"Driving School",
            "type":"Services"
        }
    ],
    "sg:phone":"+44 1229 830314",
    "sg:postcode":"LA13 0HW",
    "sg:province":"Cumbria",
    "wof:name":"Apex Driving Instruction",
    "wof:placetype":"venue"
},
  "geometry": {"coordinates":[-3.1909189224,54.112701416],"type":"Point"}
}