{
  "type": "Feature",
  "properties": {
    "addr:full":"2 Ivel Ctourt Letchworth Hertfordshire SG6 2NH",
    "addr:housenumber":"2",
    "addr:postcode":"sg6 2nh",
    "addr:street":"Ivel Ctourt Letchworth",
    "iso:country":"GB",
    "sg:address":"2 Ivel Ctourt",
    "sg:city":"Letchworth",
    "sg:classifiers":[
        {
            "category":"Shopping",
            "subcategory":"News",
            "type":"Retail Goods"
        }
    ],
    "sg:phone":"+44 1462 685011",
    "sg:postcode":"SG6 2NH",
    "sg:province":"Hertfordshire",
    "sg:tags":[
        "newsagent"
    ],
    "wof:name":"Forbuoys Ltd.",
    "wof:placetype":"venue"
},
  "geometry": {"coordinates":[-0.222243,51.972549],"type":"Point"}
}