{
  "type": "Feature",
  "properties": {
    "addr:full":"Rissington Road, Bourton On The Water Cheltenham Gloucestershire GL51 6LW",
    "addr:postcode":"gl51 6lw",
    "addr:street":"Rissington Road",
    "iso:country":"GB",
    "sg:address":"Rissington Road, Bourton On The Water",
    "sg:city":"Cheltenham",
    "sg:classifiers":[
        {
            "category":"Arena",
            "subcategory":"Sports Club",
            "type":"Entertainment"
        }
    ],
    "sg:phone":"+44 1451 821977",
    "sg:postcode":"GL51 6LW",
    "sg:province":"Gloucestershire",
    "wof:name":"Bourton Rovers Football & Social Club",
    "wof:placetype":"venue"
},
  "geometry": {"coordinates":[-2.110864,51.894314],"type":"Point"}
}