{
  "type": "Feature",
  "properties": {
    "addr:full":"9 The Square Woodford Green Essex IG8 0UJ",
    "addr:housenumber":"9",
    "addr:postcode":"ig8 0uj",
    "addr:street":"The Square",
    "iso:country":"GB",
    "sg:address":"9 The Square",
    "sg:city":"Woodford Green",
    "sg:classifiers":[
        {
            "category":"Shopping",
            "type":"Retail Goods"
        }
    ],
    "sg:phone":"+44 20 8559 7436",
    "sg:postcode":"IG8 0UJ",
    "sg:province":"Essex",
    "sg:tags":[
        "part",
        "accessory"
    ],
    "wof:name":"H S A Motorsport PLC",
    "wof:placetype":"venue"
},
  "geometry": {"coordinates":[0.02114,51.610481],"type":"Point"}
}