{
  "type": "Feature",
  "properties": {
    "iso:country":"GB",
    "sg:address":"97 Holliers Crescent, Middle Barton",
    "sg:city":"Chipping Norton",
    "sg:classifiers":[
        {
            "category":"Retail",
            "subcategory":"Laundry & Dry Cleaning",
            "type":"Services"
        }
    ],
    "sg:phone":"+44 1869 347414",
    "sg:postcode":"OX7 7HW",
    "sg:province":"Gloucestershire",
    "sg:tags":[
        "home",
        "ironing"
    ],
    "wof:name":"Creases Ironing Services",
    "wof:placetype":"venue"
},
  "geometry": {"coordinates":[-1.3621979952,51.9299736023],"type":"Point"}
}