{
  "type": "Feature",
  "properties": {
    "addr:full":"Gnaton Estate Office, Yealmpton Plymouth Devon PL8 2HU",
    "addr:postcode":"pl8 2hu",
    "addr:street":"Yealmpton",
    "iso:country":"GB",
    "sg:address":"Gnaton Estate Office, Yealmpton",
    "sg:city":"Plymouth",
    "sg:classifiers":[
        {
            "category":"Farming",
            "subcategory":"Farm",
            "type":"Manufacturing & Wholesale Goods"
        }
    ],
    "sg:phone":"+44 1752 881254",
    "sg:postcode":"PL8 2HU",
    "sg:province":"Devon",
    "sg:tags":[
        "mixed",
        "crop"
    ],
    "wof:name":"The Hon George Lopes",
    "wof:placetype":"venue"
},
  "geometry": {"coordinates":[-3.9982709885,50.3471794128],"type":"Point"}
}