{
  "type": "Feature",
  "properties": {
    "iso:country":"GB",
    "sg:address":"Lower Farm, Dodds Lane, Gwersyllt",
    "sg:city":"Wrexham",
    "sg:classifiers":[
        {
            "category":"Building & Trades",
            "subcategory":"Construction",
            "type":"Services"
        }
    ],
    "sg:phone":"+44 1978 755642",
    "sg:postcode":"LL11 4NS",
    "sg:province":"Wrexham",
    "sg:tags":[
        "builder"
    ],
    "wof:name":"Gareth Reece Developments",
    "wof:placetype":"venue"
},
  "geometry": {"coordinates":[-3.019284,53.072384],"type":"Point"}
}