{
  "type": "Feature",
  "properties": {
    "addr:full":"46 Dudley Close, Winklebury Basingstoke Hampshire RG23 8BP",
    "addr:housenumber":"46",
    "addr:postcode":"rg23 8bp",
    "addr:street":"Dudley Close",
    "iso:country":"GB",
    "sg:address":"46 Dudley Close, Winklebury",
    "sg:city":"Basingstoke",
    "sg:classifiers":[
        {
            "category":"Health Services",
            "subcategory":"Dentist",
            "type":"Services"
        }
    ],
    "sg:postcode":"RG23 8BP",
    "sg:province":"Hampshire",
    "sg:tags":[
        "technician",
        "dental"
    ],
    "wof:name":"Darren Redstall",
    "wof:placetype":"venue"
},
  "geometry": {"coordinates":[-1.1286280155,51.2671470642],"type":"Point"}
}