{
  "type": "Feature",
  "properties": {
    "addr:full":"Ruthvenfield Place, Inveralmond Ind Est Perth Perth and Kinross PH1 3XU",
    "addr:postcode":"ph1 3xu",
    "addr:street":"Place Inveralmond",
    "iso:country":"GB",
    "sg:address":"Ruthvenfield Place, Inveralmond Ind Est",
    "sg:city":"Perth",
    "sg:classifiers":[
        {
            "category":"Wholesale",
            "subcategory":"Machinery & Supplies",
            "type":"Manufacturing & Wholesale Goods"
        }
    ],
    "sg:phone":"+44 1738 441689",
    "sg:postcode":"PH1 3XU",
    "sg:province":"Perth and Kinross",
    "sg:tags":[
        "equipment",
        "railway"
    ],
    "wof:name":"Hewden Rail Services",
    "wof:placetype":"venue"
},
  "geometry": {"coordinates":[-3.4800190926,56.4187240601],"type":"Point"}
}