{
  "type": "Feature",
  "properties": {
    "addr:full":"62 Mount Pleasant Avenue Exmouth Devon EX8 4QR",
    "addr:housenumber":"62",
    "addr:postcode":"ex8 4qr",
    "addr:street":"Mount Pleasant Avenue",
    "iso:country":"GB",
    "sg:address":"62 Mount Pleasant Avenue",
    "sg:city":"Exmouth",
    "sg:classifiers":[
        {
            "category":"Retail",
            "subcategory":"Driving School",
            "type":"Services"
        }
    ],
    "sg:phone":"+44 1395 270329",
    "sg:postcode":"EX8 4QR",
    "sg:province":"Devon",
    "wof:name":"Crossroads Driving Academy",
    "wof:placetype":"venue"
},
  "geometry": {"coordinates":[-3.4039750099,50.6390609741],"type":"Point"}
}