{
  "type": "Feature",
  "properties": {
    "iso:country":"GB",
    "sg:address":"Uplands Stud, Scotland Farm, Hawkley",
    "sg:city":"Liss",
    "sg:classifiers":[
        {
            "category":"Farming",
            "subcategory":"Livestock Farm",
            "type":"Manufacturing & Wholesale Goods"
        }
    ],
    "sg:postcode":"GU33 6NH",
    "sg:province":"Hampshire",
    "sg:tags":[
        "stud"
    ],
    "wof:name":"D J Haak",
    "wof:placetype":"venue"
},
  "geometry": {"coordinates":[-0.937635,51.057117],"type":"Point"}
}