{
  "type": "Feature",
  "properties": {
    "addr:full":"Mawren, Blackmoor Road Ormskirk Lancashire L40 2QE",
    "addr:postcode":"l40 2qe",
    "addr:street":"Blackmoor Road",
    "iso:country":"GB",
    "sg:address":"Mawren, Blackmoor Road",
    "sg:city":"Ormskirk",
    "sg:classifiers":[
        {
            "category":"Freight",
            "type":"Transportation"
        }
    ],
    "sg:phone":"+44 1704 822229",
    "sg:postcode":"L40 2QE",
    "sg:province":"Lancashire",
    "sg:tags":[
        "haulage",
        "road"
    ],
    "wof:name":"N R Marsden",
    "wof:placetype":"venue"
},
  "geometry": {"coordinates":[-2.7759768963,53.628036499],"type":"Point"}
}