{
  "type": "Feature",
  "properties": {
    "iso:country":"GB",
    "sg:address":"Unit 4 Limekiln La",
    "sg:city":"Stoke On Trent",
    "sg:classifiers":[
        {
            "category":"Military Area",
            "subcategory":"Air Force Base",
            "type":"Public Place"
        }
    ],
    "sg:phone":"+44 1782 774422",
    "sg:postcode":"ST7 3AG",
    "sg:province":"Cheshire",
    "sg:tags":[
        "taxi",
        "hire",
        "private"
    ],
    "wof:name":"Fare Deal Private Hire",
    "wof:placetype":"venue"
},
  "geometry": {"coordinates":[-2.252884,53.091614],"type":"Point"}
}