{
  "type": "Feature",
  "properties": {
    "iso:country":"GB",
    "sg:address":"17 Burford Av",
    "sg:city":"Salisbury",
    "sg:classifiers":[
        {
            "category":"Real Estate",
            "subcategory":"Architect",
            "type":"Services"
        }
    ],
    "sg:phone":"+44 1722 333093",
    "sg:postcode":"SP2 8AG",
    "sg:province":"Wiltshire",
    "wof:name":"Gerard Kelly",
    "wof:placetype":"venue"
},
  "geometry": {"coordinates":[-1.791573,51.057686],"type":"Point"}
}