{
  "type": "Feature",
  "properties": {
    "addr:full":"Meadow View, 1 Salem Clo Northampton Northamptonshire NN6 7YW",
    "addr:housenumber":"1",
    "addr:postcode":"nn6 7yw",
    "addr:street":"Meadow View",
    "iso:country":"GB",
    "sg:address":"Meadow View, 1 Salem Clo",
    "sg:city":"Northampton",
    "sg:classifiers":[
        {
            "category":"Professional",
            "subcategory":"Employment Agencies",
            "type":"Services"
        }
    ],
    "sg:phone":"+44 1327 844767",
    "sg:postcode":"NN6 7YW",
    "sg:province":"Northamptonshire",
    "sg:tags":[
        "consultant"
    ],
    "wof:name":"YMH Services Ltd",
    "wof:placetype":"venue"
},
  "geometry": {"coordinates":[-1.0873600245,52.3015289307],"type":"Point"}
}