{
  "type": "Feature",
  "properties": {
    "addr:full":"17 Hill Rise Potters Bar Greater London EN6 2RX",
    "addr:housenumber":"17",
    "addr:postcode":"en6 2rx",
    "addr:street":"Hill Rise",
    "iso:country":"GB",
    "sg:address":"17 Hill Rise",
    "sg:city":"Potters Bar",
    "sg:classifiers":[
        {
            "category":"Building & Trades",
            "subcategory":"Landscaping Services",
            "type":"Services"
        }
    ],
    "sg:phone":"+44 1707 645877",
    "sg:postcode":"EN6 2RX",
    "sg:province":"Greater London",
    "sg:tags":[
        "landscape",
        "contractor"
    ],
    "wof:name":"Wilby Landscapes",
    "wof:placetype":"venue"
},
  "geometry": {"coordinates":[-0.1764,51.687977],"type":"Point"}
}