{
  "type": "Feature",
  "properties": {
    "addr:full":"The Green Room, 1 Burston Road London Greater London SW15 6AR",
    "addr:housenumber":"1",
    "addr:postcode":"sw15 6ar",
    "addr:street":"Burston Road",
    "iso:country":"GB",
    "sg:address":"The Green Room, 1 Burston Road",
    "sg:city":"London",
    "sg:classifiers":[
        {
            "category":"Professional",
            "subcategory":"Management & Consulting",
            "type":"Services"
        }
    ],
    "sg:postcode":"SW15 6AR",
    "sg:province":"Greater London",
    "sg:tags":[
        "marketing",
        "consultant"
    ],
    "wof:name":"Sportsworld Television Ltd.",
    "wof:placetype":"venue"
},
  "geometry": {"coordinates":[-0.21905,51.460217],"type":"Point"}
}