{
  "type": "Feature",
  "properties": {
    "addr:full":"69 Heol Don, Whitchurch Cardiff Cardiff CF14 2AT",
    "addr:housenumber":"69",
    "addr:postcode":"cf14 2at",
    "addr:street":"Heol Don Whitchurch",
    "iso:country":"GB",
    "sg:address":"69 Heol Don, Whitchurch",
    "sg:city":"Cardiff",
    "sg:classifiers":[
        {
            "category":"Communications",
            "type":"Services"
        }
    ],
    "sg:postcode":"CF14 2AT",
    "sg:province":"Cardiff",
    "sg:tags":[
        "audio-visual"
    ],
    "wof:name":"South Wales Mobile Cine Services",
    "wof:placetype":"venue"
},
  "geometry": {"coordinates":[-3.2291638851,51.514087677],"type":"Point"}
}