{
  "type": "Feature",
  "properties": {
    "addr:full":"Thorntree Farm, Shay Lane, Walton Wakefield West Yorkshire WF2 6PR",
    "addr:postcode":"wf2 6pr",
    "addr:street":"Shay Lane;West",
    "iso:country":"GB",
    "sg:address":"Thorntree Farm, Shay Lane, Walton",
    "sg:city":"Wakefield",
    "sg:classifiers":[
        {
            "category":"Farming",
            "subcategory":"Dairy Farm",
            "type":"Manufacturing & Wholesale Goods"
        }
    ],
    "sg:postcode":"WF2 6PR",
    "sg:province":"West Yorkshire",
    "wof:name":"John A Gemmell",
    "wof:placetype":"venue"
},
  "geometry": {"coordinates":[-1.463949,53.64893],"type":"Point"}
}