{
  "type": "Feature",
  "properties": {
    "addr:full":"261 Goldhawk Rd Shepherd's Bush Greater London W12 8EU",
    "addr:housenumber":"261",
    "addr:postcode":"w12 8eu",
    "addr:street":"Goldhawk Rd",
    "iso:country":"GB",
    "sg:address":"261 Goldhawk Rd",
    "sg:city":"Shepherd's Bush",
    "sg:classifiers":[
        {
            "category":"Organizations",
            "subcategory":"Non-profit Organization",
            "type":"Services"
        }
    ],
    "sg:phone":"+44 20 8846 9777",
    "sg:postcode":"W12 8EU",
    "sg:province":"Greater London",
    "sg:tags":[
        "organisation",
        "animal",
        "welfare"
    ],
    "wof:name":"Lord Dowding Fund for Humane Research",
    "wof:placetype":"venue"
},
  "geometry": {"coordinates":[-0.2397570014,51.4994773865],"type":"Point"}
}