{
  "type": "Feature",
  "properties": {
    "addr:full":"Sennen Penzance Cornwall TR19 7AD",
    "addr:postcode":"tr19 7ad",
    "iso:country":"GB",
    "sg:address":"Sennen",
    "sg:city":"Penzance",
    "sg:classifiers":[
        {
            "category":"Travel",
            "subcategory":"Hotels & Motels",
            "type":"Entertainment"
        }
    ],
    "sg:phone":"+44 1736 871280",
    "sg:postcode":"TR19 7AD",
    "sg:province":"Cornwall",
    "wof:name":"The Old Manor Hotel",
    "wof:placetype":"venue"
},
  "geometry": {"coordinates":[-5.6952400208,50.0711402893],"type":"Point"}
}