{
  "type": "Feature",
  "properties": {
    "addr:full":"Unit 1 Ferry Works, Summer Road Thames Ditton Surrey KT7 0QQ",
    "addr:housenumber":"unit 1;works",
    "addr:postcode":"kt7 0qq",
    "addr:street":"Ferry;Summer Road",
    "iso:country":"GB",
    "sg:address":"Unit 1 Ferry Works, Summer Road",
    "sg:city":"Thames Ditton",
    "sg:classifiers":[
        {
            "category":"Manufacturing",
            "subcategory":"Tools & Machinery",
            "type":"Manufacturing & Wholesale Goods"
        },
        {
            "category":"Building & Trades",
            "subcategory":"Landscaping Services",
            "type":"Services"
        }
    ],
    "sg:phone":"+44 20 8398 4277",
    "sg:postcode":"KT7 0QQ",
    "sg:province":"Surrey",
    "sg:tags":[
        "horticultural",
        "consultant"
    ],
    "wof:name":"Ncmt Ltd",
    "wof:placetype":"venue"
},
  "geometry": {"coordinates":[-0.3333089948,51.3873443604],"type":"Point"}
}