{
  "type": "Feature",
  "properties": {
    "iso:country":"GB",
    "sg:address":"Cilcennin",
    "sg:city":"Lampeter",
    "sg:classifiers":[
        {
            "category":"Community Center",
            "type":"Public Place"
        }
    ],
    "sg:postcode":"SA48 8RJ",
    "sg:province":"Carmarthenshire",
    "sg:tags":[
        "nursery",
        "centre"
    ],
    "wof:name":"Glynwern Heather Nursery",
    "wof:placetype":"venue"
},
  "geometry": {"coordinates":[-4.16666,52.219395],"type":"Point"}
}