{
  "type": "Feature",
  "properties": {
    "addr:full":"Wood Farm, Golden Corner Norwich Norfolk NR9 4NU",
    "addr:postcode":"nr9 4nu",
    "addr:street":"Norwich Norfolk",
    "iso:country":"GB",
    "sg:address":"Wood Farm, Golden Corner",
    "sg:city":"Norwich",
    "sg:classifiers":[
        {
            "category":"Retail",
            "subcategory":"Auto Repair",
            "type":"Services"
        }
    ],
    "sg:postcode":"NR9 4NU",
    "sg:province":"Norfolk",
    "sg:tags":[
        "modification",
        "garage"
    ],
    "wof:name":"Caston Garage",
    "wof:placetype":"venue"
},
  "geometry": {"coordinates":[0.92644,52.557018],"type":"Point"}
}