{
  "type": "Feature",
  "properties": {
    "addr:full":"Newholm Hall Farm, Newholm Whitby North Yorkshire YO21 3QR",
    "addr:postcode":"yo21 3qr",
    "addr:street":"Newholm",
    "iso:country":"GB",
    "sg:address":"Newholm Hall Farm, Newholm",
    "sg:city":"Whitby",
    "sg:classifiers":[
        {
            "category":"Banks & Credit Unions",
            "subcategory":"Investment Brokerage",
            "type":"Services"
        }
    ],
    "sg:phone":"+44 1947 603335",
    "sg:postcode":"YO21 3QR",
    "sg:province":"North Yorkshire",
    "sg:tags":[
        "contractor"
    ],
    "wof:name":"David Hill",
    "wof:placetype":"venue"
},
  "geometry": {"coordinates":[-0.6597689986,54.4832267761],"type":"Point"}
}