{
  "type": "Feature",
  "properties": {
    "addr:full":"7 Poplar Drive, Lenzie Glasgow East Dunbartonshire G66 4DN",
    "addr:housenumber":"7",
    "addr:postcode":"g66 4dn",
    "addr:street":"Poplar Drive",
    "iso:country":"GB",
    "sg:address":"7 Poplar Drive, Lenzie",
    "sg:city":"Glasgow",
    "sg:classifiers":[
        {
            "category":"Professional",
            "subcategory":"Engineering",
            "type":"Services"
        }
    ],
    "sg:phone":"+44 1242 224874",
    "sg:postcode":"G66 4DN",
    "sg:province":"East Dunbartonshire",
    "sg:tags":[
        "electrical",
        "engineer"
    ],
    "wof:name":"Intronic Technology Ltd.",
    "wof:placetype":"venue"
},
  "geometry": {"coordinates":[-4.171099,55.923969],"type":"Point"}
}