{
  "type": "Feature",
  "properties": {
    "iso:country":"GB",
    "sg:address":"138 Blake Street, Little Aston",
    "sg:city":"Sutton Coldfield",
    "sg:classifiers":[
        {
            "category":"Retail",
            "subcategory":"Auto Repair",
            "type":"Services"
        }
    ],
    "sg:phone":"+44 121 580 9500",
    "sg:postcode":"B74 4EU",
    "sg:province":"Staffordshire",
    "sg:tags":[
        "modification",
        "garage"
    ],
    "wof:name":"Blake Street Autos Ltd.",
    "wof:placetype":"venue"
},
  "geometry": {"coordinates":[-1.849267,52.60466],"type":"Point"}
}