{
  "type": "Feature",
  "properties": {
    "addr:full":"1a Water Lane Ilford Essex IG3 9HE",
    "addr:housenumber":"1a",
    "addr:postcode":"ig3 9he",
    "addr:street":"Water Lane",
    "iso:country":"GB",
    "sg:address":"1a Water Lane",
    "sg:city":"Ilford",
    "sg:classifiers":[
        {
            "category":"Building & Trades",
            "subcategory":"Construction",
            "type":"Services"
        }
    ],
    "sg:phone":"+44 20 8252 3300",
    "sg:postcode":"IG3 9HE",
    "sg:province":"Essex",
    "sg:tags":[
        "builder"
    ],
    "wof:name":"GOC Property Management & Construction Ltd",
    "wof:placetype":"venue"
},
  "geometry": {"coordinates":[0.099393,51.560036],"type":"Point"}
}