{
  "type": "Feature",
  "properties": {
    "addr:full":"77 Regent Street Leamington Spa Warwickshire CV32 5DX",
    "addr:housenumber":"77",
    "addr:postcode":"cv32 5dx",
    "addr:street":"Regent Street",
    "iso:country":"GB",
    "sg:address":"77 Regent Street",
    "sg:city":"Leamington Spa",
    "sg:classifiers":[
        {
            "category":"Retail",
            "subcategory":"Photofinishing",
            "type":"Services"
        }
    ],
    "sg:phone":"+44 1926 831540",
    "sg:postcode":"CV32 5DX",
    "sg:province":"Warwickshire",
    "sg:tags":[
        "photographic",
        "processor"
    ],
    "wof:name":"Fast Fotos",
    "wof:placetype":"venue"
},
  "geometry": {"coordinates":[-1.535801053,52.2904701233],"type":"Point"}
}