{
  "type": "Feature",
  "properties": {
    "addr:full":"Unit 4, Thongsbridge Mills, Miry Lane Huddersfield South Yorkshire HD9 7RY",
    "addr:housenumber":"unit 4",
    "addr:postcode":"hd9 7ry",
    "addr:street":"Thongsbridge Mills Miry Lane",
    "iso:country":"GB",
    "sg:address":"Unit 4, Thongsbridge Mills, Miry Lane",
    "sg:city":"Huddersfield",
    "sg:classifiers":[
        {
            "category":"Professional",
            "subcategory":"Management & Consulting",
            "type":"Services"
        }
    ],
    "sg:phone":"+44 1484 686900",
    "sg:postcode":"HD9 7RY",
    "sg:province":"South Yorkshire",
    "sg:tags":[
        "fire",
        "consultant",
        "protection"
    ],
    "wof:name":"Holm Valley Fire Protection Engineers",
    "wof:placetype":"venue"
},
  "geometry": {"coordinates":[-1.7787499428,53.5845184326],"type":"Point"}
}