{
  "type": "Feature",
  "properties": {
    "addr:full":"The Green, Biddestone Chippenham Gloucestershire SN14 7DG",
    "addr:postcode":"sn14 7dg",
    "addr:street":"Green",
    "iso:country":"GB",
    "sg:address":"The Green, Biddestone",
    "sg:city":"Chippenham",
    "sg:classifiers":[
        {
            "category":"Bars & Pubs",
            "type":"Food & Drink"
        }
    ],
    "sg:phone":"+44 1249 713305",
    "sg:postcode":"SN14 7DG",
    "sg:province":"Gloucestershire",
    "sg:tags":[
        "pubs",
        "inn"
    ],
    "wof:name":"The White Horse",
    "wof:placetype":"venue"
},
  "geometry": {"coordinates":[-2.199524,51.460533],"type":"Point"}
}