{
  "type": "Feature",
  "properties": {
    "addr:full":"31 Mount Avenue, Bletchley Milton Keynes Buckinghamshire MK1 1LS",
    "addr:housenumber":"31",
    "addr:postcode":"mk1 1ls",
    "addr:street":"Mount Avenue",
    "iso:country":"GB",
    "sg:address":"31 Mount Avenue, Bletchley",
    "sg:city":"Milton Keynes",
    "sg:classifiers":[
        {
            "category":"Freight",
            "type":"Transportation"
        }
    ],
    "sg:phone":"+44 1908 366444",
    "sg:postcode":"MK1 1LS",
    "sg:province":"Buckinghamshire",
    "sg:tags":[
        "forwarders"
    ],
    "wof:name":"P.B.I International Freight Services",
    "wof:placetype":"venue"
},
  "geometry": {"coordinates":[-0.7277489901,52.0058555603],"type":"Point"}
}