{
  "type": "Feature",
  "properties": {
    "addr:full":"23 Waterloo Road Wolverhampton West Midlands WV1 4TJ",
    "addr:housenumber":"23",
    "addr:postcode":"wv1 4tj",
    "addr:street":"Waterloo Road",
    "iso:country":"GB",
    "sg:address":"23 Waterloo Road",
    "sg:city":"Wolverhampton",
    "sg:classifiers":[
        {
            "category":"Professional",
            "subcategory":"Lawyer & Legal Services",
            "type":"Services"
        }
    ],
    "sg:postcode":"WV1 4TJ",
    "sg:province":"West Midlands",
    "sg:tags":[
        "solicitor"
    ],
    "wof:name":"Dallow & Dallow",
    "wof:placetype":"venue"
},
  "geometry": {"coordinates":[-2.132708,52.586964],"type":"Point"}
}