{
  "type": "Feature",
  "properties": {
    "iso:country":"GB",
    "sg:address":"1-2 Harbour Yard, Chelsea Harbour",
    "sg:city":"London",
    "sg:classifiers":[
        {
            "category":"Professional",
            "subcategory":"Art Services",
            "type":"Services"
        }
    ],
    "sg:phone":"+44 20 7351 1550",
    "sg:postcode":"SW10 0XD",
    "sg:province":"Greater London",
    "sg:tags":[
        "graphic",
        "designer"
    ],
    "wof:name":"Gyrographic Communications Ltd.",
    "wof:placetype":"venue"
},
  "geometry": {"coordinates":[-0.1817490011,51.4744186401],"type":"Point"}
}