{
  "type": "Feature",
  "properties": {
    "iso:country":"GB",
    "sg:address":"Stafford Road, Huntington",
    "sg:city":"Cannock",
    "sg:classifiers":[
        {
            "category":"Home & Garden",
            "subcategory":"Building Materials",
            "type":"Retail Goods"
        }
    ],
    "sg:phone":"+44 1543 570911",
    "sg:postcode":"WS12 4NQ",
    "sg:province":"Staffordshire",
    "sg:tags":[
        "ironwork",
        "diy",
        "wrought"
    ],
    "wof:name":"Bentleys Fabrications",
    "wof:placetype":"venue"
},
  "geometry": {"coordinates":[-2.040043,52.708275],"type":"Point"}
}