{
  "type": "Feature",
  "properties": {
    "addr:full":"105 Ash Road Sutton Surrey SM3 9LA",
    "addr:housenumber":"105",
    "addr:postcode":"sm3 9la",
    "addr:street":"Ash Road",
    "iso:country":"GB",
    "sg:address":"105 Ash Road",
    "sg:city":"Sutton",
    "sg:classifiers":[
        {
            "category":"Home & Garden",
            "subcategory":"Hardware",
            "type":"Retail Goods"
        }
    ],
    "sg:phone":"+44 20 8288 1185",
    "sg:postcode":"SM3 9LA",
    "sg:province":"Surrey",
    "sg:tags":[
        "heat",
        "mech",
        "exchanger"
    ],
    "wof:name":"A C A Distribution Ltd.",
    "wof:placetype":"venue"
},
  "geometry": {"coordinates":[-0.2132889926,51.3841209412],"type":"Point"}
}