{
  "type": "Feature",
  "properties": {
    "iso:country":"GB",
    "sg:address":"8 Queen Street",
    "sg:city":"Southwold",
    "sg:classifiers":[
        {
            "category":"Real Estate",
            "subcategory":"Real Estate Agent",
            "type":"Services"
        }
    ],
    "sg:phone":"+44 1502 722253",
    "sg:postcode":"IP18 6EQ",
    "sg:province":"Suffolk",
    "wof:name":"Flick & Son",
    "wof:placetype":"venue"
},
  "geometry": {"coordinates":[1.677792,52.323151],"type":"Point"}
}