{
  "type": "Feature",
  "properties": {
    "addr:full":"3 Corporation Road Chelmsford Essex CM1 2AR",
    "addr:housenumber":"3",
    "addr:postcode":"cm1 2ar",
    "addr:street":"Corporation Road",
    "iso:country":"GB",
    "sg:address":"3 Corporation Road",
    "sg:city":"Chelmsford",
    "sg:classifiers":[
        {
            "category":"Food & Beverages",
            "subcategory":"Liquor & Beverages",
            "type":"Retail Goods"
        }
    ],
    "sg:postcode":"CM1 2AR",
    "sg:province":"Essex",
    "sg:tags":[
        "beer",
        "spirit",
        "wines"
    ],
    "wof:name":"The Beacon",
    "wof:placetype":"venue"
},
  "geometry": {"coordinates":[0.4629290104,51.744228363],"type":"Point"}
}