{
  "type": "Feature",
  "properties": {
    "addr:full":"11 Freckleton Close, Great Sankey Warrington Cheshire WA5 2TH",
    "addr:housenumber":"11",
    "addr:postcode":"wa5 2th",
    "addr:street":"Freckleton Close",
    "iso:country":"GB",
    "sg:address":"11 Freckleton Close, Great Sankey",
    "sg:city":"Warrington",
    "sg:classifiers":[
        {
            "category":"Retail",
            "subcategory":"Driving School",
            "type":"Services"
        }
    ],
    "sg:postcode":"WA5 2TH",
    "sg:province":"Cheshire",
    "wof:name":"G B Driver Training",
    "wof:placetype":"venue"
},
  "geometry": {"coordinates":[-2.6390419006,53.3854026794],"type":"Point"}
}