{
  "type": "Feature",
  "properties": {
    "addr:full":"Llwyn Yr Ynn, Llandeilo Road, Gorslas Llanelli Carmarthenshire SA14 7LU",
    "addr:postcode":"sa14 7lu",
    "addr:street":"Llwyn;Ynn Llandeilo Road",
    "iso:country":"GB",
    "sg:address":"Llwyn Yr Ynn, Llandeilo Road, Gorslas",
    "sg:city":"Llanelli",
    "sg:classifiers":[
        {
            "category":"Building & Trades",
            "subcategory":"Landscaping Services",
            "type":"Services"
        }
    ],
    "sg:phone":"+44 1269 845296",
    "sg:postcode":"SA14 7LU",
    "sg:province":"Carmarthenshire",
    "sg:tags":[
        "landscape",
        "contractor"
    ],
    "wof:name":"Spencer Environmental Care Associates Ltd.",
    "wof:placetype":"venue"
},
  "geometry": {"coordinates":[-4.075134,51.804161],"type":"Point"}
}