{
  "type": "Feature",
  "properties": {
    "iso:country":"GB",
    "sg:address":"37 Waltham Ave",
    "sg:city":"Guildford",
    "sg:classifiers":[
        {
            "category":"Autos & Motor Vehicles",
            "subcategory":"Automobile Sales",
            "type":"Retail Goods"
        },
        {
            "category":"Retail",
            "subcategory":"Auto Repair",
            "type":"Services"
        }
    ],
    "sg:postcode":"GU2 9QF",
    "sg:province":"Surrey",
    "sg:tags":[
        "modification",
        "garage",
        "car"
    ],
    "wof:name":"Harms,Robert,",
    "wof:placetype":"venue"
},
  "geometry": {"coordinates":[-0.584633,51.258274],"type":"Point"}
}