{
  "type": "Feature",
  "properties": {
    "addr:full":"16-18 Trafalgar Way Cambridge Cambridgeshire CB3 8SQ",
    "addr:housenumber":"16-18",
    "addr:postcode":"cb3 8sq",
    "addr:street":"Trafalgar Way",
    "iso:country":"GB",
    "sg:address":"16-18 Trafalgar Way",
    "sg:city":"Cambridge",
    "sg:classifiers":[
        {
            "category":"Wholesale",
            "subcategory":"Sporting Goods",
            "type":"Manufacturing & Wholesale Goods"
        }
    ],
    "sg:phone":"+44 1954 786600",
    "sg:postcode":"CB3 8SQ",
    "sg:province":"Cambridgeshire",
    "sg:tags":[
        "mnfr",
        "sport",
        "equipment"
    ],
    "wof:name":"Tf Uk Estate Ltd.",
    "wof:placetype":"venue"
},
  "geometry": {"coordinates":[0.0200449992,52.2569313049],"type":"Point"}
}