{
  "type": "Feature",
  "properties": {
    "addr:full":"158 Norburn Park, Witton Gilbert Durham Durham DH7 6SQ",
    "addr:housenumber":"158",
    "addr:postcode":"dh7 6sq",
    "addr:street":"Norburn Park",
    "iso:country":"GB",
    "sg:address":"158 Norburn Park, Witton Gilbert",
    "sg:city":"Durham",
    "sg:classifiers":[
        {
            "category":"Bakery",
            "type":"Food & Drink"
        }
    ],
    "sg:phone":"+44 191 371 0204",
    "sg:postcode":"DH7 6SQ",
    "sg:province":"Durham",
    "sg:tags":[
        "cake",
        "maker"
    ],
    "wof:name":"Cake Magic",
    "wof:placetype":"venue"
},
  "geometry": {"coordinates":[-1.6382550001,54.8093338013],"type":"Point"}
}