{
  "type": "Feature",
  "properties": {
    "addr:full":"All Hallows On The Wall, 83 London Wall London Greater London EC2M 5ND",
    "addr:housenumber":"83",
    "addr:postcode":"ec2m 5nd",
    "addr:street":"London Wall",
    "iso:country":"GB",
    "sg:address":"All Hallows On The Wall, 83 London Wall",
    "sg:city":"London",
    "sg:classifiers":[
        {
            "category":"Organizations",
            "subcategory":"Non-profit Organization",
            "type":"Services"
        }
    ],
    "sg:phone":"+44 20 7496 1689",
    "sg:postcode":"EC2M 5ND",
    "sg:province":"Greater London",
    "sg:tags":[
        "organisation",
        "voluntary",
        "charity"
    ],
    "wof:name":"Christian Aid",
    "wof:placetype":"venue"
},
  "geometry": {"coordinates":[-0.0839900002,51.5165405273],"type":"Point"}
}