{
  "type": "Feature",
  "properties": {
    "iso:country":"GB",
    "sg:address":"Garden Court, Lockington Hall",
    "sg:city":"Derby",
    "sg:classifiers":[
        {
            "category":"Professional",
            "subcategory":"Printing & Photocopies",
            "type":"Services"
        }
    ],
    "sg:phone":"+44 1509 670067",
    "sg:postcode":"DE74 2SJ",
    "sg:province":"Leicestershire",
    "sg:tags":[
        "duplicating",
        "copying"
    ],
    "wof:name":"Copystatic Ltd.",
    "wof:placetype":"venue"
},
  "geometry": {"coordinates":[-1.3340489864,52.8414764404],"type":"Point"}
}