{
  "type": "Feature",
  "properties": {
    "addr:full":"Mudgley Road, Rooksbridge Axbridge Somerset BS26 2TL",
    "addr:postcode":"bs26 2tl",
    "addr:street":"Mudgley Road Rooksbridge",
    "iso:country":"GB",
    "sg:address":"Mudgley Road, Rooksbridge",
    "sg:city":"Axbridge",
    "sg:classifiers":[
        {
            "category":"Transit Center",
            "subcategory":"Passenger",
            "type":"Transportation"
        }
    ],
    "sg:phone":"+44 1934 750332",
    "sg:postcode":"BS26 2TL",
    "sg:province":"Somerset",
    "sg:tags":[
        "boarding",
        "kennel",
        "catteries"
    ],
    "wof:name":"Suda Boarding Kennels",
    "wof:placetype":"venue"
},
  "geometry": {"coordinates":[-2.8184089661,51.2883911133],"type":"Point"}
}