{
  "type": "Feature",
  "properties": {
    "iso:country":"GB",
    "sg:address":"3 High View, High St",
    "sg:city":"Bordon",
    "sg:classifiers":[
        {
            "category":"Professional",
            "subcategory":"Engineering",
            "type":"Services"
        }
    ],
    "sg:postcode":"GU35 0AX",
    "sg:province":"Hampshire",
    "sg:tags":[
        "consulting",
        "engineer"
    ],
    "wof:name":"Defence Systems Designers Ltd",
    "wof:placetype":"venue"
},
  "geometry": {"coordinates":[-0.865114,51.108856],"type":"Point"}
}