{
  "type": "Feature",
  "properties": {
    "iso:country":"GB",
    "sg:address":"23 Holmfield Terrace, Long Buckby",
    "sg:city":"Northampton",
    "sg:classifiers":[
        {
            "category":"Building & Trades",
            "subcategory":"Construction",
            "type":"Services"
        }
    ],
    "sg:postcode":"NN6 7QN",
    "sg:province":"Northamptonshire",
    "sg:tags":[
        "builder"
    ],
    "wof:name":"Partridge & Hobbs",
    "wof:placetype":"venue"
},
  "geometry": {"coordinates":[-1.087799,52.301739],"type":"Point"}
}