{
  "type": "Feature",
  "properties": {
    "iso:country":"GB",
    "sg:address":"9 Bon Accord Square",
    "sg:city":"Aberdeen",
    "sg:classifiers":[
        {
            "category":"Insurance",
            "subcategory":"Insurance Agent",
            "type":"Services"
        }
    ],
    "sg:phone":"+44 1224 596000",
    "sg:postcode":"AB11 6DJ",
    "sg:province":"Aberdeen City",
    "sg:tags":[
        "broker"
    ],
    "wof:name":"Executive Insurance Brokers",
    "wof:placetype":"venue"
},
  "geometry": {"coordinates":[-2.1062569618,57.1416702271],"type":"Point"}
}