{
  "type": "Feature",
  "properties": {
    "addr:full":"West Mill House Bradford West Yorkshire BD13 4DN",
    "addr:postcode":"bd13 4dn",
    "addr:street":"West Mill House Bradford West",
    "iso:country":"GB",
    "sg:address":"West Mill House",
    "sg:city":"Bradford",
    "sg:classifiers":[
        {
            "category":"Utilities",
            "subcategory":"Refuse",
            "type":"Services"
        }
    ],
    "sg:phone":"+44 1274 834498",
    "sg:postcode":"BD13 4DN",
    "sg:province":"West Yorkshire",
    "sg:tags":[
        "skip",
        "hire"
    ],
    "wof:name":"Speights Skip Hire Ltd.",
    "wof:placetype":"venue"
},
  "geometry": {"coordinates":[-1.896679,53.800529],"type":"Point"}
}