{
  "type": "Feature",
  "properties": {
    "iso:country":"GB",
    "sg:address":"12 Aldborough St",
    "sg:city":"Blyth",
    "sg:classifiers":[
        {
            "category":"Sports & Exercise",
            "subcategory":"Gym",
            "type":"Entertainment"
        }
    ],
    "sg:phone":"+44 1670 364503",
    "sg:postcode":"NE24 2EU",
    "sg:province":"Northumberland",
    "sg:tags":[
        "fitness",
        "health",
        "centre"
    ],
    "wof:name":"Fitness Station The",
    "wof:placetype":"venue"
},
  "geometry": {"coordinates":[-1.508723,55.125126],"type":"Point"}
}