{
  "type": "Feature",
  "properties": {
    "iso:country":"GB",
    "sg:address":"71 High Street",
    "sg:city":"Bembridge",
    "sg:classifiers":[
        {
            "category":"Arts & Performance",
            "subcategory":"Art Gallery",
            "type":"Entertainment"
        }
    ],
    "sg:phone":"+44 1983 875115",
    "sg:postcode":"PO35 5SF",
    "sg:province":"Isle of Wight",
    "wof:name":"Bembridge Gallery",
    "wof:placetype":"venue"
},
  "geometry": {"coordinates":[-1.0901730061,50.6890945435],"type":"Point"}
}