{
  "type": "Feature",
  "properties": {
    "addr:full":"North Building, Nainholm Accademy, Nainholm Rd Ayr South Ayrshire KA8 0QQ",
    "addr:postcode":"ka8 0qq",
    "addr:street":"Nainholm Rd",
    "iso:country":"GB",
    "sg:address":"North Building, Nainholm Accademy, Nainholm Rd",
    "sg:city":"Ayr",
    "sg:classifiers":[
        {
            "category":"Organizations",
            "subcategory":"Non-profit Organization",
            "type":"Services"
        }
    ],
    "sg:phone":"+44 1292 281625",
    "sg:postcode":"KA8 0QQ",
    "sg:province":"South Ayrshire",
    "sg:tags":[
        "organisation",
        "voluntary",
        "charity"
    ],
    "wof:name":"Ayrshire Volunteer Exchange",
    "wof:placetype":"venue"
},
  "geometry": {"coordinates":[-4.6012802124,55.4670791626],"type":"Point"}
}