{
  "type": "Feature",
  "properties": {
    "iso:country":"GB",
    "sg:address":"28 Dalesway, Tranmere Pk",
    "sg:city":"Leeds",
    "sg:classifiers":[
        {
            "category":"Building & Trades",
            "subcategory":"Landscaping Services",
            "type":"Services"
        }
    ],
    "sg:phone":"+44 1274 610155",
    "sg:postcode":"LS20 8JN",
    "sg:province":"West Yorkshire",
    "sg:tags":[
        "landscape",
        "contractor"
    ],
    "wof:name":"Treescape",
    "wof:placetype":"venue"
},
  "geometry": {"coordinates":[-1.72963,53.872108],"type":"Point"}
}