{
  "type": "Feature",
  "properties": {
    "addr:full":"9 The Parade, Hengrove Lane Bristol City of Bristol BS14 9DB",
    "addr:housenumber":"9",
    "addr:postcode":"bs14 9db",
    "addr:street":"The Parade Hengrove Lane",
    "iso:country":"GB",
    "sg:address":"9 The Parade, Hengrove Lane",
    "sg:city":"Bristol",
    "sg:classifiers":[
        {
            "category":"Communications",
            "type":"Services"
        }
    ],
    "sg:phone":"+44 117 977 5287",
    "sg:postcode":"BS14 9DB",
    "sg:province":"City of Bristol",
    "sg:tags":[
        "tv",
        "radio",
        "video",
        "audio-visual"
    ],
    "wof:name":"Select T V Ltd.",
    "wof:placetype":"venue"
},
  "geometry": {"coordinates":[-2.569829,51.424229],"type":"Point"}
}