{
  "type": "Feature",
  "properties": {
    "addr:full":"32a Havelock Street Aylesbury Buckinghamshire HP20 2NX",
    "addr:housenumber":"32a",
    "addr:postcode":"hp20 2nx",
    "addr:street":"Havelock Street",
    "iso:country":"GB",
    "sg:address":"32a Havelock Street",
    "sg:city":"Aylesbury",
    "sg:classifiers":[
        {
            "category":"Manufacturing",
            "subcategory":"Jewelry",
            "type":"Manufacturing & Wholesale Goods"
        },
        {
            "category":"Building & Trades",
            "subcategory":"Construction",
            "type":"Services"
        }
    ],
    "sg:phone":"+44 1296 426919",
    "sg:postcode":"HP20 2NX",
    "sg:province":"Buckinghamshire",
    "sg:tags":[
        "joinery",
        "jewellery",
        "repair"
    ],
    "wof:name":"Micklee Trading",
    "wof:placetype":"venue"
},
  "geometry": {"coordinates":[-0.811874,51.820419],"type":"Point"}
}