{
  "type": "Feature",
  "properties": {
    "addr:full":"Unit 5 Arbroath Business Centre, 31 Dens Rd Arbroath Angus DD11 1RS",
    "addr:housenumber":"unit 5;31",
    "addr:postcode":"dd11 1rs",
    "addr:street":"Arbroath Business;Dens Rd",
    "iso:country":"GB",
    "sg:address":"Unit 5 Arbroath Business Centre, 31 Dens Rd",
    "sg:city":"Arbroath",
    "sg:classifiers":[
        {
            "category":"Shopping",
            "subcategory":"Computers & Home Electronics",
            "type":"Retail Goods"
        }
    ],
    "sg:phone":"+44 1241 879788",
    "sg:postcode":"DD11 1RS",
    "sg:province":"Angus",
    "sg:tags":[
        "aerial",
        "television",
        "radio"
    ],
    "wof:name":"Tay Tech",
    "wof:placetype":"venue"
},
  "geometry": {"coordinates":[-2.58713,56.56311],"type":"Point"}
}