{
  "type": "Feature",
  "properties": {
    "addr:full":"1a Gaol Street Oakham Leicestershire LE15 6AQ",
    "addr:housenumber":"1a",
    "addr:postcode":"le15 6aq",
    "addr:street":"Gaol Street",
    "iso:country":"GB",
    "sg:address":"1a Gaol Street",
    "sg:city":"Oakham",
    "sg:classifiers":[
        {
            "category":"Organizations",
            "subcategory":"Non-profit Organization",
            "type":"Services"
        }
    ],
    "sg:postcode":"LE15 6AQ",
    "sg:province":"Leicestershire",
    "sg:tags":[
        "charitable",
        "organisation",
        "voluntary",
        "charity"
    ],
    "wof:name":"BRITISH RED CROSS SOCIETY",
    "wof:placetype":"venue"
},
  "geometry": {"coordinates":[-0.7300590277,52.6698493958],"type":"Point"}
}