{
  "type": "Feature",
  "properties": {
    "addr:full":"11 Mossvale Crescent Glasgow Glasgow City G33 5NZ",
    "addr:housenumber":"11",
    "addr:postcode":"g33 5nz",
    "addr:street":"Mossvale Crescent",
    "iso:country":"GB",
    "sg:address":"11 Mossvale Crescent",
    "sg:city":"Glasgow",
    "sg:classifiers":[
        {
            "category":"Food & Beverages",
            "subcategory":"Bakery",
            "type":"Retail Goods"
        }
    ],
    "sg:postcode":"G33 5NZ",
    "sg:province":"Glasgow City",
    "sg:tags":[
        "baker"
    ],
    "wof:name":"Craigend Home Bakery",
    "wof:placetype":"venue"
},
  "geometry": {"coordinates":[-4.1603088379,55.8771781921],"type":"Point"}
}