{
  "type": "Feature",
  "properties": {
    "iso:country":"GB",
    "sg:address":"2 Quay Street",
    "sg:city":"Lymington",
    "sg:classifiers":[
        {
            "category":"Personal",
            "subcategory":"Beauty Salon",
            "type":"Services"
        }
    ],
    "sg:phone":"+44 1590 677165",
    "sg:postcode":"SO41 3AS",
    "sg:province":"Hampshire",
    "sg:tags":[
        "unisex",
        "hairdresser"
    ],
    "wof:name":"The Hairnet",
    "wof:placetype":"venue"
},
  "geometry": {"coordinates":[-1.5362110138,50.7584190369],"type":"Point"}
}