{
  "type": "Feature",
  "properties": {
    "iso:country":"GB",
    "sg:address":"The Chase, Walpole St Peter",
    "sg:city":"Wisbech",
    "sg:classifiers":[
        {
            "category":"Education",
            "subcategory":"School",
            "type":"Public Place"
        }
    ],
    "sg:phone":"+44 1945 780121",
    "sg:postcode":"PE14 7NG",
    "sg:province":"Cambridgeshire",
    "sg:tags":[
        "local",
        "authority"
    ],
    "wof:name":"NORFOLK COUNTY COUNCIL",
    "wof:placetype":"venue"
},
  "geometry": {"coordinates":[0.2207909971,52.7332038879],"type":"Point"}
}