{
  "type": "Feature",
  "properties": {
    "addr:full":"13 Bellegrove Road Welling Kent DA16 3PA",
    "addr:housenumber":"13",
    "addr:postcode":"da16 3pa",
    "addr:street":"Bellegrove Road",
    "iso:country":"GB",
    "sg:address":"13 Bellegrove Road",
    "sg:city":"Welling",
    "sg:classifiers":[
        {
            "category":"Travel",
            "subcategory":"Travel Agent",
            "type":"Entertainment"
        }
    ],
    "sg:phone":"+44 20 8303 4688",
    "sg:postcode":"DA16 3PA",
    "sg:province":"Kent",
    "sg:tags":[
        "agency",
        "activity"
    ],
    "wof:name":"LUNN POLY LTD",
    "wof:placetype":"venue"
},
  "geometry": {"coordinates":[0.1070720032,51.4624252319],"type":"Point"}
}