{
  "type": "Feature",
  "properties": {
    "iso:country":"GB",
    "sg:address":"Commercial Street",
    "sg:city":"Lerwick",
    "sg:classifiers":[
        {
            "category":"Personal",
            "subcategory":"Beauty Salon",
            "type":"Services"
        }
    ],
    "sg:postcode":"ZE1 0DL",
    "sg:province":"Shetland Islands",
    "sg:tags":[
        "unisex",
        "hairdresser"
    ],
    "wof:name":"Unistyles",
    "wof:placetype":"venue"
},
  "geometry": {"coordinates":[-1.143876,60.155582],"type":"Point"}
}