{
  "type": "Feature",
  "properties": {
    "addr:full":"Margaret St Walsall West Midlands WS2 8HJ",
    "addr:postcode":"ws2 8hj",
    "addr:street":"Margaret St",
    "iso:country":"GB",
    "sg:address":"Margaret St",
    "sg:city":"Walsall",
    "sg:classifiers":[
        {
            "category":"Utilities",
            "subcategory":"Refuse",
            "type":"Services"
        }
    ],
    "sg:phone":"+44 1922 612411",
    "sg:postcode":"WS2 8HJ",
    "sg:province":"West Midlands",
    "sg:tags":[
        "skip",
        "hire"
    ],
    "wof:name":"Salts-Steptoe Ltd",
    "wof:placetype":"venue"
},
  "geometry": {"coordinates":[-1.987755,52.587708],"type":"Point"}
}