{
  "type": "Feature",
  "properties": {
    "addr:full":"12 Grey St Nottingham Derbyshire NG16 2EF",
    "addr:housenumber":"12",
    "addr:postcode":"ng16 2ef",
    "addr:street":"Grey St",
    "iso:country":"GB",
    "sg:address":"12 Grey St",
    "sg:city":"Nottingham",
    "sg:classifiers":[
        {
            "category":"Manufacturing",
            "subcategory":"Petroleum Products",
            "type":"Manufacturing & Wholesale Goods"
        }
    ],
    "sg:phone":"+44 1773 769788",
    "sg:postcode":"NG16 2EF",
    "sg:province":"Derbyshire",
    "sg:tags":[
        "double",
        "glazing"
    ],
    "wof:name":"Newthorpe Home Improvement Services",
    "wof:placetype":"venue"
},
  "geometry": {"coordinates":[-1.293054,53.010406],"type":"Point"}
}