{
  "type": "Feature",
  "properties": {
    "addr:full":"18 Carey Rd, Bulwell Nottingham Nottinghamshire NG6 8AT",
    "addr:housenumber":"18",
    "addr:postcode":"ng6 8at",
    "addr:street":"Carey Rd",
    "iso:country":"GB",
    "sg:address":"18 Carey Rd, Bulwell",
    "sg:city":"Nottingham",
    "sg:classifiers":[
        {
            "category":"Personal",
            "subcategory":"Beauty Salon",
            "type":"Services"
        }
    ],
    "sg:postcode":"NG6 8AT",
    "sg:province":"Nottinghamshire",
    "sg:tags":[
        "unisex",
        "hairdresser"
    ],
    "wof:name":"Monk,F,",
    "wof:placetype":"venue"
},
  "geometry": {"coordinates":[-1.1921210289,53.0051116943],"type":"Point"}
}