{
  "type": "Feature",
  "properties": {
    "addr:full":"17 Bingswood Avenue, Whaley Bridge High Peak Cheshire SK23 7LX",
    "addr:housenumber":"17",
    "addr:postcode":"sk23 7lx",
    "addr:street":"Bingswood Avenue;Peak",
    "iso:country":"GB",
    "sg:address":"17 Bingswood Avenue, Whaley Bridge",
    "sg:city":"High Peak",
    "sg:classifiers":[
        {
            "category":"Building & Trades",
            "subcategory":"Landscaping Services",
            "type":"Services"
        }
    ],
    "sg:phone":"+44 1663 734747",
    "sg:postcode":"SK23 7LX",
    "sg:province":"Cheshire",
    "sg:tags":[
        "gardening"
    ],
    "wof:name":"Prestige Garden Services",
    "wof:placetype":"venue"
},
  "geometry": {"coordinates":[-1.982652,53.331528],"type":"Point"}
}