{
  "type": "Feature",
  "properties": {
    "iso:country":"GB",
    "sg:address":"Redwald Ho, Greenway, Stiffkey",
    "sg:city":"Wells-next-the-sea",
    "sg:classifiers":[
        {
            "category":"Building & Trades",
            "subcategory":"Construction",
            "type":"Services"
        }
    ],
    "sg:postcode":"NR23 1QF",
    "sg:province":"Norfolk",
    "sg:tags":[
        "contractor"
    ],
    "wof:name":"Hodges,M F,",
    "wof:placetype":"venue"
},
  "geometry": {"coordinates":[0.85581,52.952644],"type":"Point"}
}