{
  "type": "Feature",
  "properties": {
    "iso:country":"GB",
    "sg:address":"Brook Cottage, Calveley",
    "sg:city":"Tarporley",
    "sg:classifiers":[
        {
            "category":"Home & Garden",
            "subcategory":"Building Materials",
            "type":"Retail Goods"
        }
    ],
    "sg:phone":"+44 1829 260335",
    "sg:postcode":"CW6 9JS",
    "sg:province":"Cheshire",
    "sg:tags":[
        "ironwork",
        "wrought"
    ],
    "wof:name":"K Stockton",
    "wof:placetype":"venue"
},
  "geometry": {"coordinates":[-2.611007,53.125912],"type":"Point"}
}