{
  "type": "Feature",
  "properties": {
    "addr:full":"2 Penleys Grove St York North Yorkshire YO31 7PN",
    "addr:housenumber":"2",
    "addr:postcode":"yo31 7pn",
    "addr:street":"Penleys Grove St York",
    "iso:country":"GB",
    "sg:address":"2 Penleys Grove St",
    "sg:city":"York",
    "sg:classifiers":[
        {
            "category":"Social Services",
            "subcategory":"Retirement Home",
            "type":"Services"
        }
    ],
    "sg:phone":"+44 1904 659777",
    "sg:postcode":"YO31 7PN",
    "sg:province":"North Yorkshire",
    "sg:tags":[
        "care"
    ],
    "wof:name":"Primrose Care Ltd",
    "wof:placetype":"venue"
},
  "geometry": {"coordinates":[-1.075509,53.964909],"type":"Point"}
}