{
  "type": "Feature",
  "properties": {
    "addr:full":"Carr Lane, Walney Barrow-in-furness Cumbria LA14 3YH",
    "addr:postcode":"la14 3yh",
    "addr:street":"Carr Lane",
    "iso:country":"GB",
    "sg:address":"Carr Lane, Walney",
    "sg:city":"Barrow-in-furness",
    "sg:classifiers":[
        {
            "category":"Recreation",
            "subcategory":"Campground",
            "type":"Entertainment"
        }
    ],
    "sg:phone":"+44 1229 473505",
    "sg:postcode":"LA14 3YH",
    "sg:province":"Cumbria",
    "sg:tags":[
        "site",
        "camping"
    ],
    "wof:name":"Saltmarsh Caravan Park",
    "wof:placetype":"venue"
},
  "geometry": {"coordinates":[-3.2540569305,54.0983352661],"type":"Point"}
}