{
  "type": "Feature",
  "properties": {
    "addr:full":"The Central Promenade Mablethorpe Lincolnshire LN12 1LU",
    "addr:postcode":"ln12 1lu",
    "addr:street":"Promenade Mablethorpe",
    "iso:country":"GB",
    "sg:address":"The Central Promenade",
    "sg:city":"Mablethorpe",
    "sg:classifiers":[
        {
            "category":"Cafe",
            "type":"Food & Drink"
        }
    ],
    "sg:postcode":"LN12 1LU",
    "sg:province":"Lincolnshire",
    "sg:tags":[
        "tea",
        "room"
    ],
    "wof:name":"The Look Out Cafe",
    "wof:placetype":"venue"
},
  "geometry": {"coordinates":[0.258197,53.340668],"type":"Point"}
}