{
  "type": "Feature",
  "properties": {
    "iso:country":"GB",
    "sg:address":"104 Inskip Crescent",
    "sg:city":"Stevenage",
    "sg:classifiers":[
        {
            "category":"Real Estate",
            "subcategory":"Developer",
            "type":"Services"
        },
        {
            "category":"Organizations",
            "subcategory":"Community Association",
            "type":"Services"
        }
    ],
    "sg:phone":"+44 1438 354792",
    "sg:postcode":"SG1 1JZ",
    "sg:province":"Hertfordshire",
    "sg:tags":[
        "society",
        "housing",
        "property"
    ],
    "wof:name":"The Guinness Trust",
    "wof:placetype":"venue"
},
  "geometry": {"coordinates":[-0.195677,51.905087],"type":"Point"}
}