{
  "type": "Feature",
  "properties": {
    "addr:full":"50 High Street West Wickham Kent BR4 0PA",
    "addr:housenumber":"50",
    "addr:postcode":"br4 0pa",
    "addr:street":"High Street",
    "iso:country":"GB",
    "sg:address":"50 High Street",
    "sg:city":"West Wickham",
    "sg:classifiers":[
        {
            "category":"Retail",
            "subcategory":"Repair Shop",
            "type":"Services"
        }
    ],
    "sg:postcode":"BR4 0PA",
    "sg:province":"Kent",
    "sg:tags":[
        "radio",
        "television",
        "video"
    ],
    "wof:name":"Croft Radio Ltd.",
    "wof:placetype":"venue"
},
  "geometry": {"coordinates":[-0.0171269998,51.3761863708],"type":"Point"}
}