{
  "type": "Feature",
  "properties": {
    "addr:full":"Forge Cottage, Kirkby Underwood Road Sleaford Lincolnshire NG34 0HN",
    "addr:postcode":"ng34 0hn",
    "addr:street":"Underwood Road",
    "iso:country":"GB",
    "sg:address":"Forge Cottage, Kirkby Underwood Road",
    "sg:city":"Sleaford",
    "sg:classifiers":[
        {
            "category":"Professional",
            "subcategory":"Engineering",
            "type":"Services"
        }
    ],
    "sg:phone":"+44 1778 440615",
    "sg:postcode":"NG34 0HN",
    "sg:province":"Lincolnshire",
    "wof:name":"Stanton's of Aslackby",
    "wof:placetype":"venue"
},
  "geometry": {"coordinates":[-0.389124,52.859734],"type":"Point"}
}