{
  "type": "Feature",
  "properties": {
    "iso:country":"GB",
    "sg:address":"186 High Street",
    "sg:city":"Uckfield",
    "sg:classifiers":[
        {
            "category":"Organizations",
            "subcategory":"Membership Organization",
            "type":"Services"
        }
    ],
    "sg:phone":"+44 1825 765278",
    "sg:postcode":"TN22 1AU",
    "sg:province":"East Sussex",
    "sg:tags":[
        "club"
    ],
    "wof:name":"Cinque Ports Club",
    "wof:placetype":"venue"
},
  "geometry": {"coordinates":[0.097017,50.97263],"type":"Point"}
}