{
  "type": "Feature",
  "properties": {
    "iso:country":"GB",
    "sg:address":"33a North Street",
    "sg:city":"Newcastle",
    "sg:classifiers":[
        {
            "category":"Building & Trades",
            "subcategory":"Plumbing",
            "type":"Services"
        }
    ],
    "sg:phone":"+44 1782 662938",
    "sg:postcode":"ST5 1AZ",
    "sg:province":"Staffordshire",
    "sg:tags":[
        "merchant",
        "plumbers'"
    ],
    "wof:name":"Newcastle Plumbing & Heating Supplies",
    "wof:placetype":"venue"
},
  "geometry": {"coordinates":[-2.221073,53.012146],"type":"Point"}
}