{
  "type": "Feature",
  "properties": {
    "iso:country":"GB",
    "sg:address":"38 Elm Road",
    "sg:city":"Leigh-on-sea",
    "sg:classifiers":[
        {
            "category":"Home & Garden",
            "subcategory":"Furniture",
            "type":"Retail Goods"
        }
    ],
    "sg:phone":"+44 1702 712958",
    "sg:postcode":"SS9 1SN",
    "sg:province":"Essex",
    "wof:name":"Prust",
    "wof:placetype":"venue"
},
  "geometry": {"coordinates":[0.6544920206,51.5420913696],"type":"Point"}
}