{
  "type": "Feature",
  "properties": {
    "iso:country":"GB",
    "sg:address":"7 Cross St",
    "sg:city":"Preston",
    "sg:classifiers":[
        {
            "category":"Personal",
            "subcategory":"Beauty Salon",
            "type":"Services"
        }
    ],
    "sg:phone":"+44 1772 258913",
    "sg:postcode":"PR1 3LT",
    "sg:province":"Lancashire",
    "sg:tags":[
        "unisex",
        "hairdresser"
    ],
    "wof:name":"Suki's",
    "wof:placetype":"venue"
},
  "geometry": {"coordinates":[-2.6991779804,53.7564582825],"type":"Point"}
}