{
  "type": "Feature",
  "properties": {
    "addr:full":"Dumyat Farm, Blairlogie Stirling Clackmannanshire FK9 5QF",
    "addr:postcode":"fk9 5qf",
    "addr:street":"Blairlogie",
    "iso:country":"GB",
    "sg:address":"Dumyat Farm, Blairlogie",
    "sg:city":"Stirling",
    "sg:classifiers":[
        {
            "category":"Farming",
            "subcategory":"Farm",
            "type":"Manufacturing & Wholesale Goods"
        }
    ],
    "sg:postcode":"FK9 5QF",
    "sg:province":"Clackmannanshire",
    "sg:tags":[
        "mixed",
        "crop"
    ],
    "wof:name":"Burns,D,",
    "wof:placetype":"venue"
},
  "geometry": {"coordinates":[-3.886337,56.149055],"type":"Point"}
}