{
  "type": "Feature",
  "properties": {
    "iso:country":"GB",
    "sg:address":"12 High Street",
    "sg:city":"Teddington",
    "sg:classifiers":[
        {
            "category":"Shopping",
            "subcategory":"News",
            "type":"Retail Goods"
        }
    ],
    "sg:phone":"+44 20 8977 1576",
    "sg:postcode":"TW11 8EW",
    "sg:province":"Greater London",
    "sg:tags":[
        "newsagent"
    ],
    "wof:name":"Dowsetts",
    "wof:placetype":"venue"
},
  "geometry": {"coordinates":[-0.332865,51.426998],"type":"Point"}
}