{
  "type": "Feature",
  "properties": {
    "iso:country":"GB",
    "sg:address":"21a Harris Rd",
    "sg:city":"Sheerness",
    "sg:classifiers":[
        {
            "category":"Recreation",
            "subcategory":"Water Park",
            "type":"Entertainment"
        }
    ],
    "sg:phone":"+44 1795 663531",
    "sg:postcode":"ME12 1UF",
    "sg:province":"Kent",
    "sg:tags":[
        "sport"
    ],
    "wof:name":"Tripple S Water Sports Surf Ski Scuba",
    "wof:placetype":"venue"
},
  "geometry": {"coordinates":[0.7631599903,51.4375305176],"type":"Point"}
}