{
  "type": "Feature",
  "properties": {
    "iso:country":"GB",
    "sg:address":"14 Kathryn Avenue, Huntington",
    "sg:city":"York",
    "sg:classifiers":[
        {
            "category":"Autos & Motor Vehicles",
            "subcategory":"Automobile Sales",
            "type":"Retail Goods"
        }
    ],
    "sg:phone":"+44 1904 639639",
    "sg:postcode":"YO32 9JS",
    "sg:province":"North Yorkshire",
    "sg:tags":[
        "car"
    ],
    "wof:name":"Peppermint Cars",
    "wof:placetype":"venue"
},
  "geometry": {"coordinates":[-1.0488740206,53.9851875305],"type":"Point"}
}