{
  "type": "Feature",
  "properties": {
    "iso:country":"GB",
    "sg:address":"Cowpen Rd",
    "sg:city":"Blyth",
    "sg:classifiers":[
        {
            "category":"Place Of Worship",
            "type":"Public Place"
        }
    ],
    "sg:phone":"+44 1670 363458",
    "sg:postcode":"NE24 5JN",
    "sg:province":"Northumberland",
    "wof:name":"St Cuthberts R C Presbythery",
    "wof:placetype":"venue"
},
  "geometry": {"coordinates":[-1.535319,55.130764],"type":"Point"}
}