{
  "type": "Feature",
  "properties": {
    "addr:full":"68 Northfield Road, Harborne Birmingham West Midlands B17 0SU",
    "addr:housenumber":"68",
    "addr:postcode":"b17 0su",
    "addr:street":"Northfield Road",
    "iso:country":"GB",
    "sg:address":"68 Northfield Road, Harborne",
    "sg:city":"Birmingham",
    "sg:classifiers":[
        {
            "category":"Health Services",
            "subcategory":"Dentist",
            "type":"Services"
        }
    ],
    "sg:phone":"+44 121 427 2349",
    "sg:postcode":"B17 0SU",
    "sg:province":"West Midlands",
    "wof:name":"JOHN R RICHARDSON",
    "wof:placetype":"venue"
},
  "geometry": {"coordinates":[-1.965970993,52.4535522461],"type":"Point"}
}