{
  "type": "Feature",
  "properties": {
    "addr:full":"67 Station Road, Castle Donnington Derby Leicestershire DE74 2NL",
    "addr:housenumber":"67",
    "addr:postcode":"de74 2nl",
    "addr:street":"Station Road",
    "iso:country":"GB",
    "sg:address":"67 Station Road, Castle Donnington",
    "sg:city":"Derby",
    "sg:classifiers":[
        {
            "category":"Autos & Motor Vehicles",
            "subcategory":"Automobile Sales",
            "type":"Retail Goods"
        }
    ],
    "sg:postcode":"DE74 2NL",
    "sg:province":"Leicestershire",
    "sg:tags":[
        "car"
    ],
    "wof:name":"S B Financial Services",
    "wof:placetype":"venue"
},
  "geometry": {"coordinates":[-1.2743899822,52.8401603699],"type":"Point"}
}