{
  "type": "Feature",
  "properties": {
    "iso:country":"GB",
    "sg:address":"437 Green Lanes",
    "sg:city":"London",
    "sg:classifiers":[
        {
            "category":"Personal",
            "subcategory":"Beauty Salon",
            "type":"Services"
        }
    ],
    "sg:postcode":"N4 1HA",
    "sg:province":"Greater London",
    "sg:tags":[
        "unisex",
        "hairdresser"
    ],
    "wof:name":"Hair City One",
    "wof:placetype":"venue"
},
  "geometry": {"coordinates":[-0.0993300006,51.5790596008],"type":"Point"}
}