{
  "type": "Feature",
  "properties": {
    "iso:country":"GB",
    "sg:address":"6 The Wynd, Cumbernauld",
    "sg:city":"Glasgow",
    "sg:classifiers":[
        {
            "category":"Real Estate",
            "subcategory":"Surveying",
            "type":"Services"
        }
    ],
    "sg:phone":"+44 1236 727706",
    "sg:postcode":"G67 2SU",
    "sg:province":"Falkirk",
    "sg:tags":[
        "surveyor",
        "quantity"
    ],
    "wof:name":"The Rennie Partnership",
    "wof:placetype":"venue"
},
  "geometry": {"coordinates":[-3.974861,55.962692],"type":"Point"}
}