{
  "type": "Feature",
  "properties": {
    "addr:full":"15 Hay Hill London Greater London W1J 8NS",
    "addr:housenumber":"15",
    "addr:postcode":"w1j 8ns",
    "addr:street":"Hay Hill",
    "iso:country":"GB",
    "sg:address":"15 Hay Hill",
    "sg:city":"London",
    "sg:classifiers":[
        {
            "category":"Real Estate",
            "subcategory":"Real Estate Agent",
            "type":"Services"
        }
    ],
    "sg:phone":"+44 20 7493 1904",
    "sg:postcode":"W1J 8NS",
    "sg:province":"Greater London",
    "wof:name":"Archie Sherman Administration Ltd.",
    "wof:placetype":"venue"
},
  "geometry": {"coordinates":[-0.1433449984,51.5090942383],"type":"Point"}
}