{
  "type": "Feature",
  "properties": {
    "iso:country":"GB",
    "sg:address":"Beech Drive, Killearn",
    "sg:city":"Glasgow",
    "sg:classifiers":[
        {
            "category":"Farming",
            "subcategory":"Nursery",
            "type":"Manufacturing & Wholesale Goods"
        }
    ],
    "sg:postcode":"G63 9SD",
    "sg:province":"Argyll and Bute",
    "sg:tags":[
        "creche"
    ],
    "wof:name":"Beech Drive Nursery & Kindergarten",
    "wof:placetype":"venue"
},
  "geometry": {"coordinates":[-4.376809,56.04538],"type":"Point"}
}