{
  "type": "Feature",
  "properties": {
    "iso:country":"GB",
    "sg:address":"Unit N Newington Industrial Estate, London Road, Newington",
    "sg:city":"Sittingbourne",
    "sg:classifiers":[
        {
            "category":"Building & Trades",
            "subcategory":"Construction",
            "type":"Services"
        },
        {
            "category":"Manufacturing",
            "subcategory":"Building Materials",
            "type":"Manufacturing & Wholesale Goods"
        }
    ],
    "sg:phone":"+44 1795 843967",
    "sg:postcode":"ME9 7NU",
    "sg:province":"Kent",
    "sg:tags":[
        "merchant",
        "roofing",
        "builder"
    ],
    "wof:name":"Roofing Centre Group Ltd.",
    "wof:placetype":"venue"
},
  "geometry": {"coordinates":[0.6662920117,51.3522071838],"type":"Point"}
}