{
  "type": "Feature",
  "properties": {
    "iso:country":"GB",
    "sg:address":"103 Holmefield Rd",
    "sg:city":"Liverpool",
    "sg:classifiers":[
        {
            "category":"Government",
            "subcategory":"Post Office",
            "type":"Public Place"
        }
    ],
    "sg:phone":"+44 151 724 4366",
    "sg:postcode":"L19 3PF",
    "sg:province":"Merseyside",
    "wof:name":"Eyre,William,",
    "wof:placetype":"venue"
},
  "geometry": {"coordinates":[-2.9126260281,53.3684501648],"type":"Point"}
}