{
  "type": "Feature",
  "properties": {
    "iso:country":"GB",
    "sg:address":"Exeter F A E, Earl Richrds Road North",
    "sg:city":"Exeter",
    "sg:classifiers":[
        {
            "category":"Shopping",
            "subcategory":"Books",
            "type":"Retail Goods"
        }
    ],
    "sg:phone":"+44 1392 475110",
    "sg:postcode":"EX2 6AS",
    "sg:province":"Devon",
    "wof:name":"Intellect Ltd.",
    "wof:placetype":"venue"
},
  "geometry": {"coordinates":[-3.513358,50.710014],"type":"Point"}
}