{
  "type": "Feature",
  "properties": {
    "iso:country":"GB",
    "sg:address":"P O Box 316",
    "sg:city":"Tadworth",
    "sg:classifiers":[
        {
            "category":"Manufacturing",
            "subcategory":"Metals",
            "type":"Manufacturing & Wholesale Goods"
        }
    ],
    "sg:postcode":"KT20 6WB",
    "sg:province":"Surrey",
    "sg:tags":[
        "fab",
        "foundry"
    ],
    "wof:name":"Peter Kefford",
    "wof:placetype":"venue"
},
  "geometry": {"coordinates":[-0.215319,51.287048],"type":"Point"}
}