{
  "type": "Feature",
  "properties": {
    "iso:country":"GB",
    "sg:address":"208 Shirley Rd",
    "sg:city":"Southampton",
    "sg:classifiers":[
        {
            "category":"Professional",
            "subcategory":"Computer Services",
            "type":"Services"
        }
    ],
    "sg:phone":"+44 23 8021 1991",
    "sg:postcode":"SO15 3FL",
    "sg:province":"Hampshire",
    "sg:tags":[
        "system",
        "software"
    ],
    "wof:name":"Data Base Computers (Southampton) Ltd",
    "wof:placetype":"venue"
},
  "geometry": {"coordinates":[-1.4237710238,50.9145774841],"type":"Point"}
}