{
  "type": "Feature",
  "properties": {
    "addr:full":"3 Park End Hampstead Greater London NW3 2SE",
    "addr:housenumber":"3",
    "addr:postcode":"nw3 2se",
    "addr:street":"Park End",
    "iso:country":"GB",
    "sg:address":"3 Park End",
    "sg:city":"Hampstead",
    "sg:classifiers":[
        {
            "category":"Health Services",
            "subcategory":"Doctor",
            "type":"Services"
        }
    ],
    "sg:phone":"+44 20 7435 7282",
    "sg:postcode":"NW3 2SE",
    "sg:province":"Greater London",
    "sg:tags":[
        "practitioners"
    ],
    "wof:name":"Shaw, E H",
    "wof:placetype":"venue"
},
  "geometry": {"coordinates":[-0.16556,51.555981],"type":"Point"}
}