{
  "type": "Feature",
  "properties": {
    "iso:country":"GB",
    "sg:address":"13 High Street",
    "sg:city":"Inverurie",
    "sg:classifiers":[
        {
            "category":"Shopping",
            "subcategory":"Stationery & Office Supplies",
            "type":"Retail Goods"
        }
    ],
    "sg:phone":"+44 845 722 3344",
    "sg:postcode":"AB51 5NB",
    "sg:province":"Aberdeenshire",
    "wof:name":"E & H A Cruickshank",
    "wof:placetype":"venue"
},
  "geometry": {"coordinates":[-2.4454760551,57.2346191406],"type":"Point"}
}