{
  "type": "Feature",
  "properties": {
    "addr:full":"37 West Market Building, London Central Markets London Greater London EC1A 9PS",
    "addr:housenumber":"37",
    "addr:postcode":"ec1a 9ps",
    "addr:street":"West",
    "iso:country":"GB",
    "sg:address":"37 West Market Building, London Central Markets",
    "sg:city":"London",
    "sg:classifiers":[
        {
            "category":"Wholesale",
            "subcategory":"Meat",
            "type":"Manufacturing & Wholesale Goods"
        }
    ],
    "sg:phone":"+44 20 7236 5509",
    "sg:postcode":"EC1A 9PS",
    "sg:province":"Greater London",
    "sg:tags":[
        "-"
    ],
    "wof:name":"Central Meat (Smithfield) Ltd.",
    "wof:placetype":"venue"
},
  "geometry": {"coordinates":[-0.1019399986,51.5190505981],"type":"Point"}
}