{
  "type": "Feature",
  "properties": {
    "iso:country":"GB",
    "sg:address":"Unit 5 Mangochi House, 107-115 Gwendolen Road",
    "sg:city":"Leicester",
    "sg:classifiers":[
        {
            "category":"Professional",
            "subcategory":"Printing & Photocopies",
            "type":"Services"
        }
    ],
    "sg:phone":"+44 116 273 1552",
    "sg:postcode":"LE5 5FL",
    "sg:province":"Leicestershire",
    "sg:tags":[
        "printer"
    ],
    "wof:name":"Print A Print",
    "wof:placetype":"venue"
},
  "geometry": {"coordinates":[-1.100952,52.630581],"type":"Point"}
}