{
  "type": "Feature",
  "properties": {
    "iso:country":"GB",
    "sg:address":"Lower Westwater Farm, Westwater",
    "sg:city":"Axminster",
    "sg:classifiers":[
        {
            "category":"Farming",
            "subcategory":"Dairy Farm",
            "type":"Manufacturing & Wholesale Goods"
        }
    ],
    "sg:phone":"+44 1297 33740",
    "sg:postcode":"EX13 7JD",
    "sg:province":"Devon",
    "sg:tags":[
        "farmer"
    ],
    "wof:name":"R H & M J HURFORD",
    "wof:placetype":"venue"
},
  "geometry": {"coordinates":[-3.026292,50.793629],"type":"Point"}
}