{
  "type": "Feature",
  "properties": {
    "iso:country":"GB",
    "sg:address":"33-35 Black Bull Road",
    "sg:city":"Folkestone",
    "sg:classifiers":[
        {
            "category":"Travel",
            "subcategory":"Hotels & Motels",
            "type":"Entertainment"
        }
    ],
    "sg:phone":"+44 1303 226662",
    "sg:postcode":"CT19 5QP",
    "sg:province":"Kent",
    "wof:name":"The Imperial",
    "wof:placetype":"venue"
},
  "geometry": {"coordinates":[1.17799,51.085949],"type":"Point"}
}