{
  "type": "Feature",
  "properties": {
    "iso:country":"GB",
    "sg:address":"143 Mullway",
    "sg:city":"Letchworth",
    "sg:classifiers":[
        {
            "category":"Building & Trades",
            "subcategory":"Pest Control",
            "type":"Services"
        }
    ],
    "sg:phone":"+44 1462 672032",
    "sg:postcode":"SG6 4BG",
    "sg:province":"Hertfordshire",
    "sg:tags":[
        "vermin"
    ],
    "wof:name":"Bugs 'n' Things Independent Pest Control",
    "wof:placetype":"venue"
},
  "geometry": {"coordinates":[-0.248981,51.980324],"type":"Point"}
}