{
  "type": "Feature",
  "properties": {
    "iso:country":"GB",
    "sg:address":"Foundry Lane, Loosley Row",
    "sg:city":"Princes Risborough",
    "sg:classifiers":[
        {
            "category":"Home & Garden",
            "subcategory":"Building Materials",
            "type":"Retail Goods"
        }
    ],
    "sg:phone":"+44 1844 345546",
    "sg:postcode":"HP27 0NY",
    "sg:province":"Buckinghamshire",
    "sg:tags":[
        "ironwork",
        "product",
        "production",
        "design",
        "diy",
        "iron",
        "wrought"
    ],
    "wof:name":"Gommes Forge Ltd.",
    "wof:placetype":"venue"
},
  "geometry": {"coordinates":[-0.832952,51.721622],"type":"Point"}
}