{
  "type": "Feature",
  "properties": {
    "iso:country":"GB",
    "sg:address":"10 De La Beche St",
    "sg:city":"Swansea",
    "sg:classifiers":[
        {
            "category":"Professional",
            "subcategory":"Detective & Security Services",
            "type":"Services"
        }
    ],
    "sg:phone":"+44 1792 458999",
    "sg:postcode":"SA1 3EZ",
    "sg:province":"Neath Port Talbot",
    "wof:name":"Active Security Services Ltd",
    "wof:placetype":"venue"
},
  "geometry": {"coordinates":[-3.9469189644,51.6216316223],"type":"Point"}
}