{
  "type": "Feature",
  "properties": {
    "addr:full":"Roscoe Street Scarborough North Yorkshire YO12 7BY",
    "addr:postcode":"yo12 7by",
    "addr:street":"Roscoe Street",
    "iso:country":"GB",
    "sg:address":"Roscoe Street",
    "sg:city":"Scarborough",
    "sg:classifiers":[
        {
            "category":"Building & Trades",
            "subcategory":"Construction",
            "type":"Services"
        }
    ],
    "sg:phone":"+44 1723 367361",
    "sg:postcode":"YO12 7BY",
    "sg:province":"North Yorkshire",
    "sg:tags":[
        "builder"
    ],
    "wof:name":"A W Sinclair & Sons Ltd.",
    "wof:placetype":"venue"
},
  "geometry": {"coordinates":[-0.410792,54.279358],"type":"Point"}
}