{
  "type": "Feature",
  "properties": {
    "addr:full":"Willow House, Willow Place London Greater London SW1P 1JD",
    "addr:postcode":"sw1p 1jd",
    "addr:street":"Willow Place",
    "iso:country":"GB",
    "sg:address":"Willow House, Willow Place",
    "sg:city":"London",
    "sg:classifiers":[
        {
            "category":"Real Estate",
            "subcategory":"Surveying",
            "type":"Services"
        }
    ],
    "sg:postcode":"SW1P 1JD",
    "sg:province":"Greater London",
    "sg:tags":[
        "surveyor",
        "quantity"
    ],
    "wof:name":"Ernest Pasterfield & Partners",
    "wof:placetype":"venue"
},
  "geometry": {"coordinates":[-0.13848,51.493301],"type":"Point"}
}