{
  "type": "Feature",
  "properties": {
    "iso:country":"GB",
    "sg:address":"36 Erskine Street, Nechells",
    "sg:city":"Birmingham",
    "sg:classifiers":[
        {
            "category":"Manufacturing",
            "subcategory":"Wood Products",
            "type":"Manufacturing & Wholesale Goods"
        }
    ],
    "sg:phone":"+44 121 359 8101",
    "sg:postcode":"B7 4LL",
    "sg:province":"West Midlands",
    "sg:tags":[
        "packaging",
        "crate",
        "pallets"
    ],
    "wof:name":"J Nicklin & Sons Ltd.",
    "wof:placetype":"venue"
},
  "geometry": {"coordinates":[-1.8740860224,52.4854125977],"type":"Point"}
}