{
  "type": "Feature",
  "properties": {
    "addr:full":"122 Paynes La Coventry West Midlands CV1 5LJ",
    "addr:housenumber":"122",
    "addr:postcode":"cv1 5lj",
    "addr:street":"Paynes La Coventry West",
    "iso:country":"GB",
    "sg:address":"122 Paynes La",
    "sg:city":"Coventry",
    "sg:classifiers":[
        {
            "category":"Professional",
            "subcategory":"Art Services",
            "type":"Services"
        }
    ],
    "sg:phone":"+44 24 7645 0067",
    "sg:postcode":"CV1 5LJ",
    "sg:province":"West Midlands",
    "sg:tags":[
        "photographer"
    ],
    "wof:name":"Colin Finch",
    "wof:placetype":"venue"
},
  "geometry": {"coordinates":[-1.492917,52.410667],"type":"Point"}
}