{
  "type": "Feature",
  "properties": {
    "addr:full":"264 Gorgie Road Edinburgh City of Edinburgh EH11 2PP",
    "addr:housenumber":"264",
    "addr:postcode":"eh11 2pp",
    "addr:street":"Gorgie Road",
    "iso:country":"GB",
    "sg:address":"264 Gorgie Road",
    "sg:city":"Edinburgh",
    "sg:classifiers":[
        {
            "category":"Food & Beverages",
            "subcategory":"Meat & Fish",
            "type":"Retail Goods"
        }
    ],
    "sg:phone":"+44 131 337 1858",
    "sg:postcode":"EH11 2PP",
    "sg:province":"City of Edinburgh",
    "sg:tags":[
        "butcher"
    ],
    "wof:name":"James Robertson",
    "wof:placetype":"venue"
},
  "geometry": {"coordinates":[-3.2356569767,55.9373474121],"type":"Point"}
}