{
  "type": "Feature",
  "properties": {
    "iso:country":"GB",
    "sg:address":"3 Church Lane, Coalpit Heath",
    "sg:city":"Bristol",
    "sg:classifiers":[
        {
            "category":"Health Services",
            "subcategory":"Doctor",
            "type":"Services"
        },
        {
            "category":"Health Services",
            "subcategory":"Clinic",
            "type":"Services"
        }
    ],
    "sg:phone":"+44 1454 772150",
    "sg:postcode":"BS36 2SR",
    "sg:province":"Gloucestershire",
    "sg:tags":[
        "nh",
        "practitioners"
    ],
    "wof:name":"Coalpit Heath Surgery",
    "wof:placetype":"venue"
},
  "geometry": {"coordinates":[-2.4790608883,51.5350379944],"type":"Point"}
}