{
  "type": "Feature",
  "properties": {
    "addr:full":"42 Gorst Road London Greater London NW10 6LD",
    "addr:housenumber":"42",
    "addr:postcode":"nw10 6ld",
    "addr:street":"Gorst Road",
    "iso:country":"GB",
    "sg:address":"42 Gorst Road",
    "sg:city":"London",
    "sg:classifiers":[
        {
            "category":"Shopping",
            "subcategory":"Catalog Store",
            "type":"Retail Goods"
        }
    ],
    "sg:phone":"+44 20 8961 8334",
    "sg:postcode":"NW10 6LD",
    "sg:province":"Greater London",
    "sg:tags":[
        "mail",
        "order"
    ],
    "wof:name":"Monami",
    "wof:placetype":"venue"
},
  "geometry": {"coordinates":[-0.265069,51.526722],"type":"Point"}
}