{
  "type": "Feature",
  "properties": {
    "iso:country":"GB",
    "sg:address":"Cransden, North Street",
    "sg:city":"Midhurst",
    "sg:classifiers":[
        {
            "category":"Retail",
            "subcategory":"Laundry & Dry Cleaning",
            "type":"Services"
        }
    ],
    "sg:phone":"+44 1730 812887",
    "sg:postcode":"GU29 9DJ",
    "sg:province":"West Sussex",
    "sg:tags":[
        "alteration"
    ],
    "wof:name":"Liphook Valet Service (Dry Cleaners) Ltd.",
    "wof:placetype":"venue"
},
  "geometry": {"coordinates":[-0.74058,50.984913],"type":"Point"}
}