{
  "type": "Feature",
  "properties": {
    "addr:full":"Farnley Road, Menston Ilkley North Yorkshire LS29 6JW",
    "addr:postcode":"ls29 6jw",
    "addr:street":"Farnley Road",
    "iso:country":"GB",
    "sg:address":"Farnley Road, Menston",
    "sg:city":"Ilkley",
    "sg:classifiers":[
        {
            "category":"Organizations",
            "subcategory":"Membership Organization",
            "type":"Services"
        }
    ],
    "sg:phone":"+44 1943 878114",
    "sg:postcode":"LS29 6JW",
    "sg:province":"North Yorkshire",
    "sg:tags":[
        "club"
    ],
    "wof:name":"The Menstone Club Ltd.",
    "wof:placetype":"venue"
},
  "geometry": {"coordinates":[-1.7352739573,53.8953208923],"type":"Point"}
}