{
  "type": "Feature",
  "properties": {
    "addr:full":"Lewis Street, Miles Platting Manchester Greater Manchester M40 7NP",
    "addr:postcode":"m40 7np",
    "addr:street":"Lewis Street",
    "iso:country":"GB",
    "sg:address":"Lewis Street, Miles Platting",
    "sg:city":"Manchester",
    "sg:classifiers":[
        {
            "category":"Social Services",
            "subcategory":"Adult Care",
            "type":"Services"
        },
        {
            "category":"Social Services",
            "subcategory":"Retirement Home",
            "type":"Services"
        }
    ],
    "sg:phone":"+44 161 205 8027",
    "sg:postcode":"M40 7NP",
    "sg:province":"Greater Manchester",
    "sg:tags":[
        "housing",
        "sheltered",
        "accommodation"
    ],
    "wof:name":"Reginald Latham CT",
    "wof:placetype":"venue"
},
  "geometry": {"coordinates":[-2.215734,53.491413],"type":"Point"}
}