{
  "type": "Feature",
  "properties": {
    "addr:full":"High Street Dunbar East Lothian EH42 1ER",
    "addr:postcode":"eh42 1er",
    "addr:street":"High Street",
    "iso:country":"GB",
    "sg:address":"High Street",
    "sg:city":"Dunbar",
    "sg:classifiers":[
        {
            "category":"Museum",
            "subcategory":"Art Museum",
            "type":"Entertainment"
        },
        {
            "category":"Government",
            "subcategory":"Office",
            "type":"Public Place"
        }
    ],
    "sg:phone":"+44 1368 863734",
    "sg:postcode":"EH42 1ER",
    "sg:province":"East Lothian",
    "sg:tags":[
        "local",
        "gallery"
    ],
    "wof:name":"Dunbar Townhouse Museum",
    "wof:placetype":"venue"
},
  "geometry": {"coordinates":[-2.516014,56.002258],"type":"Point"}
}