{
  "type": "Feature",
  "properties": {
    "addr:full":"2 Market Street Oakham Leicestershire LE15 6DY",
    "addr:housenumber":"2",
    "addr:postcode":"le15 6dy",
    "addr:street":"Market Street",
    "iso:country":"GB",
    "sg:address":"2 Market Street",
    "sg:city":"Oakham",
    "sg:classifiers":[
        {
            "category":"Health Services",
            "subcategory":"Dentist",
            "type":"Services"
        }
    ],
    "sg:phone":"+44 1572 755002",
    "sg:postcode":"LE15 6DY",
    "sg:province":"Leicestershire",
    "wof:name":"Dennis Nadany",
    "wof:placetype":"venue"
},
  "geometry": {"coordinates":[-0.7278699875,52.6700439453],"type":"Point"}
}