{
  "type": "Feature",
  "properties": {
    "addr:full":"426 Main St Wishaw North Lanarkshire ML2 7PL",
    "addr:housenumber":"426",
    "addr:postcode":"ml2 7pl",
    "addr:street":"Main St",
    "iso:country":"GB",
    "sg:address":"426 Main St",
    "sg:city":"Wishaw",
    "sg:classifiers":[
        {
            "category":"Farming",
            "subcategory":"Nursery",
            "type":"Manufacturing & Wholesale Goods"
        }
    ],
    "sg:phone":"+44 1698 357322",
    "sg:postcode":"ML2 7PL",
    "sg:province":"North Lanarkshire",
    "sg:tags":[
        "creche"
    ],
    "wof:name":"Little Kiddies Corner",
    "wof:placetype":"venue"
},
  "geometry": {"coordinates":[-3.927611,55.777218],"type":"Point"}
}