{
  "type": "Feature",
  "properties": {
    "addr:full":"Unit 5 Ashford House, Beaufort Court, Sir Thomas Longley Road Rochester Kent ME2 4FA",
    "addr:housenumber":"unit 5 ashford house",
    "addr:postcode":"me2 4fa",
    "addr:street":"Beaufort Court Sir Thomas Longley Road Rochester",
    "iso:country":"GB",
    "sg:address":"Unit 5 Ashford House, Beaufort Court, Sir Thomas Longley Road",
    "sg:city":"Rochester",
    "sg:classifiers":[
        {
            "category":"Health Services",
            "subcategory":"Nursing And Care Facility",
            "type":"Services"
        },
        {
            "category":"Social Services",
            "subcategory":"Retirement Home",
            "type":"Services"
        }
    ],
    "sg:phone":"+44 1634 291073",
    "sg:postcode":"ME2 4FA",
    "sg:province":"Kent",
    "sg:tags":[
        "residential"
    ],
    "wof:name":"Kent Care Homes Association",
    "wof:placetype":"venue"
},
  "geometry": {"coordinates":[0.516595,51.394852],"type":"Point"}
}