{
  "type": "Feature",
  "properties": {
    "addr:full":"113 Clifton Street Cardiff Cardiff CF24 1LW",
    "addr:housenumber":"113",
    "addr:postcode":"cf24 1lw",
    "addr:street":"Clifton Street",
    "iso:country":"GB",
    "sg:address":"113 Clifton Street",
    "sg:city":"Cardiff",
    "sg:classifiers":[
        {
            "category":"Shopping",
            "subcategory":"Pets & Pet Supplies",
            "type":"Retail Goods"
        }
    ],
    "sg:postcode":"CF24 1LW",
    "sg:province":"Cardiff",
    "wof:name":"K Smith",
    "wof:placetype":"venue"
},
  "geometry": {"coordinates":[-3.157490015,51.4849281311],"type":"Point"}
}