{
  "type": "Feature",
  "properties": {
    "addr:full":"Kelvin Hall Argyle St Glasgow Glasgow City G3 8AW",
    "addr:postcode":"g3 8aw",
    "addr:street":"Argyle St",
    "iso:country":"GB",
    "sg:address":"Kelvin Hall Argyle St",
    "sg:city":"Glasgow",
    "sg:classifiers":[
        {
            "category":"Sports & Exercise",
            "subcategory":"Sports Center",
            "type":"Entertainment"
        }
    ],
    "sg:postcode":"G3 8AW",
    "sg:province":"Glasgow City",
    "sg:tags":[
        "shop",
        "good"
    ],
    "wof:name":"Pringle,Ian,",
    "wof:placetype":"venue"
},
  "geometry": {"coordinates":[-4.29415,55.868542],"type":"Point"}
}