{
  "type": "Feature",
  "properties": {
    "addr:full":"7 Highcroft Close, Yardley Gobion Towcester Buckinghamshire NN12 7TH",
    "addr:housenumber":"7",
    "addr:postcode":"nn12 7th",
    "addr:street":"Highcroft Close",
    "iso:country":"GB",
    "sg:address":"7 Highcroft Close, Yardley Gobion",
    "sg:city":"Towcester",
    "sg:classifiers":[
        {
            "category":"Building & Trades",
            "subcategory":"Construction",
            "type":"Services"
        }
    ],
    "sg:postcode":"NN12 7TH",
    "sg:province":"Buckinghamshire",
    "sg:tags":[
        "flooring"
    ],
    "wof:name":"Floor Coverings International",
    "wof:placetype":"venue"
},
  "geometry": {"coordinates":[-0.891409,52.096142],"type":"Point"}
}