{
  "type": "Feature",
  "properties": {
    "iso:country":"GB",
    "sg:address":"Rose Acres, Barrow Lane, Hale",
    "sg:city":"Altrincham",
    "sg:classifiers":[
        {
            "category":"Banks & Credit Unions",
            "subcategory":"Investment Brokerage",
            "type":"Services"
        }
    ],
    "sg:postcode":"WA15 0DN",
    "sg:province":"Cheshire",
    "wof:name":"Sheralee Holdings Ltd.",
    "wof:placetype":"venue"
},
  "geometry": {"coordinates":[-2.32311,53.365372],"type":"Point"}
}