{
  "type": "Feature",
  "properties": {
    "addr:full":"Davidson House, Forbury Square Reading Berkshire RG1 3GA",
    "addr:postcode":"rg1 3ga",
    "addr:street":"Forbury Square",
    "iso:country":"GB",
    "sg:address":"Davidson House, Forbury Square",
    "sg:city":"Reading",
    "sg:classifiers":[
        {
            "category":"Banks & Credit Unions",
            "subcategory":"Financial Services",
            "type":"Services"
        }
    ],
    "sg:phone":"+44 118 906 8500",
    "sg:postcode":"RG1 3GA",
    "sg:province":"Berkshire",
    "sg:tags":[
        "consultant"
    ],
    "wof:name":"Assetco Ltd.",
    "wof:placetype":"venue"
},
  "geometry": {"coordinates":[-0.9657199979,51.4574546814],"type":"Point"}
}