{
  "type": "Feature",
  "properties": {
    "iso:country":"GB",
    "sg:address":"455 Yardley Wood Road",
    "sg:city":"Birmingham",
    "sg:classifiers":[
        {
            "category":"Social Services",
            "subcategory":"Child Care",
            "type":"Services"
        },
        {
            "category":"Community Center",
            "subcategory":"Youth",
            "type":"Public Place"
        }
    ],
    "sg:postcode":"B13 0TA",
    "sg:province":"West Midlands",
    "sg:tags":[
        "home",
        "children's",
        "organisation",
        "centre"
    ],
    "wof:name":"870 HOUSE",
    "wof:placetype":"venue"
},
  "geometry": {"coordinates":[-1.869479,52.434582],"type":"Point"}
}