{
  "type": "Feature",
  "properties": {
    "addr:full":"Birchlings, Cilcain Road, Pantymwyn Mold Denbighshire CH7 5EH",
    "addr:postcode":"ch7 5eh",
    "addr:street":"Cilcain Road Pantymwyn",
    "iso:country":"GB",
    "sg:address":"Birchlings, Cilcain Road, Pantymwyn",
    "sg:city":"Mold",
    "sg:classifiers":[
        {
            "category":"Professional",
            "subcategory":"Art Services",
            "type":"Services"
        }
    ],
    "sg:postcode":"CH7 5EH",
    "sg:province":"Denbighshire",
    "sg:tags":[
        "framing"
    ],
    "wof:name":"Thomas & Thomas",
    "wof:placetype":"venue"
},
  "geometry": {"coordinates":[-3.2312290668,53.1776733398],"type":"Point"}
}