{
  "type": "Feature",
  "properties": {
    "addr:full":"22 Rubislaw Terrace Aberdeen Aberdeen City AB10 1XE",
    "addr:housenumber":"22",
    "addr:postcode":"ab10 1xe",
    "addr:street":"Rubislaw Terrace",
    "iso:country":"GB",
    "sg:address":"22 Rubislaw Terrace",
    "sg:city":"Aberdeen",
    "sg:classifiers":[
        {
            "category":"Professional",
            "type":"Services"
        }
    ],
    "sg:phone":"+44 1224 647979",
    "sg:postcode":"AB10 1XE",
    "sg:province":"Aberdeen City",
    "sg:tags":[
        "interior",
        "furnishers",
        "designer"
    ],
    "wof:name":"Design Forum Scotland",
    "wof:placetype":"venue"
},
  "geometry": {"coordinates":[-2.1183218956,57.1434860229],"type":"Point"}
}