{
  "type": "Feature",
  "properties": {
    "iso:country":"GB",
    "sg:address":"17 Magdalen Road",
    "sg:city":"Exeter",
    "sg:classifiers":[
        {
            "category":"Fast Food",
            "type":"Food & Drink"
        }
    ],
    "sg:phone":"+44 1392 499249",
    "sg:postcode":"EX2 4TA",
    "sg:province":"Devon",
    "sg:tags":[
        "away",
        "take"
    ],
    "wof:name":"Visage House",
    "wof:placetype":"venue"
},
  "geometry": {"coordinates":[-3.5220370293,50.7210426331],"type":"Point"}
}