{
  "type": "Feature",
  "properties": {
    "iso:country":"GB",
    "sg:address":"Sutton Farm, Boyton",
    "sg:city":"Launceston",
    "sg:classifiers":[
        {
            "category":"Farming",
            "subcategory":"Livestock Farm",
            "type":"Manufacturing & Wholesale Goods"
        }
    ],
    "sg:phone":"+44 1409 271269",
    "sg:postcode":"PL15 9RN",
    "sg:province":"Cornwall",
    "sg:tags":[
        "others"
    ],
    "wof:name":"L T A T Colwill & Son",
    "wof:placetype":"venue"
},
  "geometry": {"coordinates":[-4.383843,50.701855],"type":"Point"}
}