{
  "type": "Feature",
  "properties": {
    "addr:full":"87 Wilton Street, Denton Manchester Greater Manchester M34 3WH",
    "addr:housenumber":"87",
    "addr:postcode":"m34 3wh",
    "addr:street":"Wilton Street",
    "iso:country":"GB",
    "sg:address":"87 Wilton Street, Denton",
    "sg:city":"Manchester",
    "sg:classifiers":[
        {
            "category":"Building & Trades",
            "subcategory":"Construction",
            "type":"Services"
        }
    ],
    "sg:postcode":"M34 3WH",
    "sg:province":"Greater Manchester",
    "sg:tags":[
        "welder",
        "mechanical"
    ],
    "wof:name":"Davenport Welding Co.",
    "wof:placetype":"venue"
},
  "geometry": {"coordinates":[-2.251474,53.474522],"type":"Point"}
}