{
  "type": "Feature",
  "properties": {
    "addr:full":"20 Waterside Way Bath Somerset BA3 3YG",
    "addr:housenumber":"20",
    "addr:postcode":"ba3 3yg",
    "addr:street":"Waterside Way",
    "iso:country":"GB",
    "sg:address":"20 Waterside Way",
    "sg:city":"Bath",
    "sg:classifiers":[
        {
            "category":"Taxi",
            "type":"Transportation"
        },
        {
            "category":"Military Area",
            "subcategory":"Air Force Base",
            "type":"Public Place"
        }
    ],
    "sg:phone":"+44 1761 431611",
    "sg:postcode":"BA3 3YG",
    "sg:province":"Somerset",
    "sg:tags":[
        "hire",
        "private"
    ],
    "wof:name":"Ivory Taxis",
    "wof:placetype":"venue"
},
  "geometry": {"coordinates":[-2.46456,51.28442],"type":"Point"}
}