{
  "type": "Feature",
  "properties": {
    "addr:full":"Haybanks Farm, Drybeck Appleby-in-westmorland Cumbria CA16 6TF",
    "addr:postcode":"ca16 6tf",
    "addr:street":"Drybeck",
    "iso:country":"GB",
    "sg:address":"Haybanks Farm, Drybeck",
    "sg:city":"Appleby-in-westmorland",
    "sg:classifiers":[
        {
            "category":"Farming",
            "subcategory":"Livestock Farm",
            "type":"Manufacturing & Wholesale Goods"
        },
        {
            "category":"Farming",
            "subcategory":"Farm",
            "type":"Manufacturing & Wholesale Goods"
        }
    ],
    "sg:phone":"+44 17683 51112",
    "sg:postcode":"CA16 6TF",
    "sg:province":"Cumbria",
    "sg:tags":[
        "mixed",
        "crop",
        "others"
    ],
    "wof:name":"W T & J C Sowerby",
    "wof:placetype":"venue"
},
  "geometry": {"coordinates":[-2.4874300957,54.5773086548],"type":"Point"}
}