{
  "type": "Feature",
  "properties": {
    "addr:full":"4 Forest Road, Huncote Leicester Leicestershire LE9 3BG",
    "addr:housenumber":"4",
    "addr:postcode":"le9 3bg",
    "addr:street":"Forest Road",
    "iso:country":"GB",
    "sg:address":"4 Forest Road, Huncote",
    "sg:city":"Leicester",
    "sg:classifiers":[
        {
            "category":"Building & Trades",
            "subcategory":"Cleaning & Sanitation",
            "type":"Services"
        }
    ],
    "sg:phone":"+44 116 286 4544",
    "sg:postcode":"LE9 3BG",
    "sg:province":"Leicestershire",
    "sg:tags":[
        "commercial"
    ],
    "wof:name":"Hamiltons Cleaning Service",
    "wof:placetype":"venue"
},
  "geometry": {"coordinates":[-1.2383929491,52.5725440979],"type":"Point"}
}