{
  "type": "Feature",
  "properties": {
    "addr:full":"4 Antrim Road Bristol City of Bristol BS9 4BS",
    "addr:housenumber":"4",
    "addr:postcode":"bs9 4bs",
    "addr:street":"Antrim Road",
    "iso:country":"GB",
    "sg:address":"4 Antrim Road",
    "sg:city":"Bristol",
    "sg:classifiers":[
        {
            "category":"Professional",
            "subcategory":"Printing & Photocopies",
            "type":"Services"
        }
    ],
    "sg:phone":"+44 117 962 0191",
    "sg:postcode":"BS9 4BS",
    "sg:province":"City of Bristol",
    "sg:tags":[
        "emblem",
        "wholesale",
        "badge"
    ],
    "wof:name":"Ken Pearce Badges",
    "wof:placetype":"venue"
},
  "geometry": {"coordinates":[-2.609912,51.487286],"type":"Point"}
}