{
  "type": "Feature",
  "properties": {
    "iso:country":"GB",
    "sg:address":"Unit 2 Compton Mills, Shaftesbury Road, Compton Chamberlayne",
    "sg:city":"Salisbury",
    "sg:classifiers":[
        {
            "category":"Autos & Motor Vehicles",
            "subcategory":"Auto Supplies",
            "type":"Retail Goods"
        }
    ],
    "sg:phone":"+44 1722 714701",
    "sg:postcode":"SP3 5DW",
    "sg:province":"Wiltshire",
    "sg:tags":[
        "towbars"
    ],
    "wof:name":"Wiltshire Towbar Company",
    "wof:placetype":"venue"
},
  "geometry": {"coordinates":[-1.9600299597,51.0656318665],"type":"Point"}
}