{
  "type": "Feature",
  "properties": {
    "addr:full":", Amroth Narberth Carmarthenshire SA67 8NG",
    "addr:postcode":"sa67 8ng",
    "iso:country":"GB",
    "sg:address":", Amroth",
    "sg:city":"Narberth",
    "sg:classifiers":[
        {
            "category":"Bars & Pubs",
            "type":"Food & Drink"
        }
    ],
    "sg:phone":"+44 1834 812480",
    "sg:postcode":"SA67 8NG",
    "sg:province":"Carmarthenshire",
    "sg:tags":[
        "pubs",
        "inn"
    ],
    "wof:name":"Amroth Arms",
    "wof:placetype":"venue"
},
  "geometry": {"coordinates":[-4.6634068489,51.7564125061],"type":"Point"}
}