{
  "type": "Feature",
  "properties": {
    "iso:country":"GB",
    "sg:address":"Carters Farm, Dalwood",
    "sg:city":"Axminster",
    "sg:classifiers":[
        {
            "category":"Farming",
            "subcategory":"Livestock Farm",
            "type":"Manufacturing & Wholesale Goods"
        }
    ],
    "sg:postcode":"EX13 7ED",
    "sg:province":"Devon",
    "sg:tags":[
        "others"
    ],
    "wof:name":"Philip Bull",
    "wof:placetype":"venue"
},
  "geometry": {"coordinates":[-3.068769,50.798565],"type":"Point"}
}