{
  "type": "Feature",
  "properties": {
    "addr:full":"Next To The Century Tavern, Forty Av Wembley Greater London HA9 8QQ",
    "addr:postcode":"ha9 8qq",
    "addr:street":"Forty Av Wembley",
    "iso:country":"GB",
    "sg:address":"Next To The Century Tavern, Forty Av",
    "sg:city":"Wembley",
    "sg:classifiers":[
        {
            "category":"Home & Garden",
            "subcategory":"Garden Supply",
            "type":"Retail Goods"
        }
    ],
    "sg:phone":"+44 20 8385 1644",
    "sg:postcode":"HA9 8QQ",
    "sg:province":"Greater London",
    "sg:tags":[
        "nursery",
        "centre"
    ],
    "wof:name":"Apricot Flowers & Gardens",
    "wof:placetype":"venue"
},
  "geometry": {"coordinates":[-0.284804,51.565544],"type":"Point"}
}