{
  "type": "Feature",
  "properties": {
    "iso:country":"GB",
    "sg:address":"14 Maryland Drive",
    "sg:city":"Glasgow",
    "sg:classifiers":[
        {
            "category":"Recreation",
            "subcategory":"Dog Park",
            "type":"Entertainment"
        },
        {
            "category":"Retail",
            "subcategory":"Animal Services",
            "type":"Services"
        }
    ],
    "sg:phone":"+44 141 882 5552",
    "sg:postcode":"G52 1SW",
    "sg:province":"Glasgow City",
    "sg:tags":[
        "grooming",
        "clipping"
    ],
    "wof:name":"Wash 'N' Wag",
    "wof:placetype":"venue"
},
  "geometry": {"coordinates":[-4.332726,55.847004],"type":"Point"}
}