{
  "type": "Feature",
  "properties": {
    "addr:full":"Coombe Nurseries, The Race Plain, Netherhampton Salisbury Wiltshire SP2 8PN",
    "addr:postcode":"sp2 8pn",
    "addr:street":"The;Plain",
    "iso:country":"GB",
    "sg:address":"Coombe Nurseries, The Race Plain, Netherhampton",
    "sg:city":"Salisbury",
    "sg:classifiers":[
        {
            "category":"Recreation",
            "subcategory":"Campground",
            "type":"Entertainment"
        }
    ],
    "sg:phone":"+44 1722 328451",
    "sg:postcode":"SP2 8PN",
    "sg:province":"Wiltshire",
    "sg:tags":[
        "site",
        "camping"
    ],
    "wof:name":"Coombe Touring Caravan Park",
    "wof:placetype":"venue"
},
  "geometry": {"coordinates":[-1.8490840197,51.0673484802],"type":"Point"}
}