{
  "type": "Feature",
  "properties": {
    "addr:full":"Luton Road, Kinsbourne Grn Harpenden Hertfordshire AL5 3NG",
    "addr:postcode":"al5 3ng",
    "addr:street":"Luton Road Kinsbourne Grn Harpenden",
    "iso:country":"GB",
    "sg:address":"Luton Road, Kinsbourne Grn",
    "sg:city":"Harpenden",
    "sg:classifiers":[
        {
            "category":"Restaurant",
            "type":"Food & Drink"
        }
    ],
    "sg:phone":"+44 1582 713891",
    "sg:postcode":"AL5 3NG",
    "sg:province":"Hertfordshire",
    "wof:name":"The Harrow Beefeater",
    "wof:placetype":"venue"
},
  "geometry": {"coordinates":[-0.382909,51.831791],"type":"Point"}
}