{
  "type": "Feature",
  "properties": {
    "addr:full":"7 Chelverton Road Putney Greater London SW15 1RN",
    "addr:housenumber":"7",
    "addr:postcode":"sw15 1rn",
    "addr:street":"Chelverton Road",
    "iso:country":"GB",
    "sg:address":"7 Chelverton Road",
    "sg:city":"Putney",
    "sg:classifiers":[
        {
            "category":"Real Estate",
            "subcategory":"Developer",
            "type":"Services"
        }
    ],
    "sg:postcode":"SW15 1RN",
    "sg:province":"Greater London",
    "sg:tags":[
        "property"
    ],
    "wof:name":"Warmark Ltd",
    "wof:placetype":"venue"
},
  "geometry": {"coordinates":[-0.2168370038,51.462223053],"type":"Point"}
}