{
  "type": "Feature",
  "properties": {
    "addr:full":"275 Oxford Street London Greater London W1C 2DL",
    "addr:housenumber":"275",
    "addr:postcode":"w1c 2dl",
    "addr:street":"Oxford Street",
    "iso:country":"GB",
    "sg:address":"275 Oxford Street",
    "sg:city":"London",
    "sg:classifiers":[
        {
            "category":"Organizations",
            "subcategory":"Non-profit Organization",
            "type":"Services"
        }
    ],
    "sg:phone":"+44 20 7629 5424",
    "sg:postcode":"W1C 2DL",
    "sg:province":"Greater London",
    "sg:tags":[
        "organisation",
        "voluntary",
        "charity"
    ],
    "wof:name":"The Salvation Army",
    "wof:placetype":"venue"
},
  "geometry": {"coordinates":[-0.143199,51.515129],"type":"Point"}
}