{
  "type": "Feature",
  "properties": {
    "addr:full":"Burnt Tree Tipton West Midlands DY4 7UB",
    "addr:postcode":"dy4 7ub",
    "addr:street":"Burnt Tree Tipton",
    "iso:country":"GB",
    "sg:address":"Burnt Tree",
    "sg:city":"Tipton",
    "sg:classifiers":[
        {
            "category":"Autos & Motor Vehicles",
            "subcategory":"Auto Supplies",
            "type":"Retail Goods"
        }
    ],
    "sg:phone":"+44 121 557 7878",
    "sg:postcode":"DY4 7UB",
    "sg:province":"West Midlands",
    "sg:tags":[
        "tyre"
    ],
    "wof:name":"Tyre Sales (Birmingham) Ltd.",
    "wof:placetype":"venue"
},
  "geometry": {"coordinates":[-2.0622739792,52.5146865845],"type":"Point"}
}