{
  "type": "Feature",
  "properties": {
    "iso:country":"GB",
    "sg:address":"Unit 11, 1-45 Durham Street",
    "sg:city":"London",
    "sg:classifiers":[
        {
            "category":"Shopping",
            "subcategory":"Stationery & Office Supplies",
            "type":"Retail Goods"
        }
    ],
    "sg:phone":"+44 20 7582 0505",
    "sg:postcode":"SE11 5JH",
    "sg:province":"Greater London",
    "sg:tags":[
        "printers'"
    ],
    "wof:name":"Madeart Ltd.",
    "wof:placetype":"venue"
},
  "geometry": {"coordinates":[-0.118334,51.484871],"type":"Point"}
}