{
  "type": "Feature",
  "properties": {
    "addr:full":"47 Lower Bridge St Chester Cheshire CH1 1RS",
    "addr:housenumber":"47",
    "addr:postcode":"ch1 1rs",
    "addr:street":"Lower Bridge St",
    "iso:country":"GB",
    "sg:address":"47 Lower Bridge St",
    "sg:city":"Chester",
    "sg:classifiers":[
        {
            "category":"Personal",
            "subcategory":"Nail Salon",
            "type":"Services"
        }
    ],
    "sg:phone":"+44 1244 401442",
    "sg:postcode":"CH1 1RS",
    "sg:province":"Cheshire",
    "sg:tags":[
        "solarium",
        "tanning"
    ],
    "wof:name":"The Tanning Shop",
    "wof:placetype":"venue"
},
  "geometry": {"coordinates":[-2.8902029991,53.187625885],"type":"Point"}
}