{
  "type": "Feature",
  "properties": {
    "iso:country":"GB",
    "sg:address":"58-60 Holyrood Street",
    "sg:city":"Chard",
    "sg:classifiers":[
        {
            "category":"Organizations",
            "subcategory":"Non-profit Organization",
            "type":"Services"
        }
    ],
    "sg:phone":"+44 1460 64709",
    "sg:postcode":"TA20 2AL",
    "sg:province":"Devon",
    "sg:tags":[
        "organisation",
        "voluntary",
        "charity"
    ],
    "wof:name":"British Red Cross",
    "wof:placetype":"venue"
},
  "geometry": {"coordinates":[-2.9651548862,50.8708381653],"type":"Point"}
}