{
  "type": "Feature",
  "properties": {
    "addr:full":"Webster House, Dynevor Street Merthyr Tydfil Caerphilly CF48 1BA",
    "addr:postcode":"cf48 1ba",
    "addr:street":"Dynevor Street",
    "iso:country":"GB",
    "sg:address":"Webster House, Dynevor Street",
    "sg:city":"Merthyr Tydfil",
    "sg:classifiers":[
        {
            "category":"Organizations",
            "subcategory":"Membership Organization",
            "type":"Services"
        }
    ],
    "sg:phone":"+44 1685 722079",
    "sg:postcode":"CF48 1BA",
    "sg:province":"Caerphilly",
    "sg:tags":[
        "club"
    ],
    "wof:name":"The Royal Air Forces Association",
    "wof:placetype":"venue"
},
  "geometry": {"coordinates":[-3.384689,51.74828],"type":"Point"}
}