{
  "type": "Feature",
  "properties": {
    "iso:country":"GB",
    "sg:address":"Lewis Taylor End, Grenville Park",
    "sg:city":"Cheltenham",
    "sg:classifiers":[
        {
            "category":"Organizations",
            "subcategory":"Community Association",
            "type":"Services"
        },
        {
            "category":"Arena",
            "subcategory":"Sports Club",
            "type":"Entertainment"
        }
    ],
    "sg:phone":"+44 1452 864157",
    "sg:postcode":"GL3 4UD",
    "sg:province":"Gloucestershire",
    "sg:tags":[
        "social"
    ],
    "sg:website":"http://www.benthamcc.com",
    "wof:name":"Bentham Country Club Ltd.",
    "wof:placetype":"venue"
},
  "geometry": {"coordinates":[-2.1313300133,51.8424186707],"type":"Point"}
}