{
  "type": "Feature",
  "properties": {
    "addr:full":"Units 26 & 27, Vinehall Farm Indstl Est Robertsbridge East Sussex TN32 5JW",
    "addr:housenumber":"units 26 & 27 vinehall",
    "addr:postcode":"tn32 5jw",
    "addr:street":"Indstl",
    "iso:country":"GB",
    "sg:address":"Units 26 & 27, Vinehall Farm Indstl Est",
    "sg:city":"Robertsbridge",
    "sg:classifiers":[
        {
            "category":"Building & Trades",
            "subcategory":"Construction",
            "type":"Services"
        }
    ],
    "sg:phone":"+44 1424 870000",
    "sg:postcode":"TN32 5JW",
    "sg:province":"East Sussex",
    "sg:tags":[
        "ceiling",
        "contractor"
    ],
    "wof:name":"Omega Environmental Ltd",
    "wof:placetype":"venue"
},
  "geometry": {"coordinates":[0.50122,50.954971],"type":"Point"}
}