{
  "type": "Feature",
  "properties": {
    "addr:full":"Mullacott Cross Ilfracombe Devon EX34 8NY",
    "addr:postcode":"ex34 8ny",
    "addr:street":"Mullacott Cross",
    "iso:country":"GB",
    "sg:address":"Mullacott Cross",
    "sg:city":"Ilfracombe",
    "sg:classifiers":[
        {
            "category":"Bars & Pubs",
            "type":"Food & Drink"
        }
    ],
    "sg:phone":"+44 1271 865500",
    "sg:postcode":"EX34 8NY",
    "sg:province":"Devon",
    "sg:tags":[
        "pubs",
        "inn"
    ],
    "wof:name":"Mullacott Inn",
    "wof:placetype":"venue"
},
  "geometry": {"coordinates":[-4.1261987686,51.1788864136],"type":"Point"}
}