{
  "type": "Feature",
  "properties": {
    "iso:country":"GB",
    "sg:address":"Lonsdale Centre, Blake Street",
    "sg:city":"Bridgwater",
    "sg:classifiers":[
        {
            "category":"Government",
            "subcategory":"Police Station",
            "type":"Public Place"
        }
    ],
    "sg:phone":"+44 1278 431071",
    "sg:postcode":"TA6 3NB",
    "sg:province":"Somerset",
    "sg:tags":[
        "support"
    ],
    "wof:name":"The Home Office",
    "wof:placetype":"venue"
},
  "geometry": {"coordinates":[-3.013824,51.127556],"type":"Point"}
}