{
  "type": "Feature",
  "properties": {
    "iso:country":"GB",
    "sg:address":"Sigford Road, Matford Park",
    "sg:city":"Exeter",
    "sg:classifiers":[
        {
            "category":"Autos & Motor Vehicles",
            "subcategory":"Automobile Sales",
            "type":"Retail Goods"
        }
    ],
    "sg:phone":"+44 1392 201040",
    "sg:postcode":"EX2 8NL",
    "sg:province":"Devon",
    "sg:tags":[
        "car"
    ],
    "wof:name":"Kastner Ltd.",
    "wof:placetype":"venue"
},
  "geometry": {"coordinates":[-3.517749,50.696545],"type":"Point"}
}