{
  "type": "Feature",
  "properties": {
    "iso:country":"GB",
    "sg:address":"Millennium Business Park, Concorde Way",
    "sg:city":"Mansfield",
    "sg:classifiers":[
        {
            "category":"Manufacturing",
            "subcategory":"Metals",
            "type":"Manufacturing & Wholesale Goods"
        },
        {
            "category":"Wholesale",
            "subcategory":"Metals & Minerals",
            "type":"Manufacturing & Wholesale Goods"
        }
    ],
    "sg:phone":"+44 1623 624955",
    "sg:postcode":"NG19 7JZ",
    "sg:province":"Derbyshire",
    "sg:tags":[
        "steel",
        "fabricator",
        "erectors",
        "sheet"
    ],
    "wof:name":"LILLIMAN ENGINEERING LTD",
    "wof:placetype":"venue"
},
  "geometry": {"coordinates":[-1.220017,53.158588],"type":"Point"}
}