{
  "type": "Feature",
  "properties": {
    "addr:full":"Box, 4117 Abbs Cross Gardens Hornchurch Essex RM12 4ER",
    "addr:housenumber":"4117",
    "addr:postcode":"rm12 4er",
    "addr:street":"Abbs Cross Gardens",
    "iso:country":"GB",
    "sg:address":"Box, 4117 Abbs Cross Gardens",
    "sg:city":"Hornchurch",
    "sg:classifiers":[
        {
            "category":"Building & Trades",
            "subcategory":"Cleaning & Sanitation",
            "type":"Services"
        }
    ],
    "sg:phone":"+44 1708 471233",
    "sg:postcode":"RM12 4ER",
    "sg:province":"Essex",
    "sg:tags":[
        "cleaner",
        "window"
    ],
    "wof:name":"Clearview",
    "wof:placetype":"venue"
},
  "geometry": {"coordinates":[0.2006299943,51.5586700439],"type":"Point"}
}