{
  "type": "Feature",
  "properties": {
    "addr:full":"5 Saxon Way, Chelmsley Wood Birmingham West Midlands B37 5AY",
    "addr:housenumber":"5",
    "addr:postcode":"b37 5ay",
    "addr:street":"Saxon Way",
    "iso:country":"GB",
    "sg:address":"5 Saxon Way, Chelmsley Wood",
    "sg:city":"Birmingham",
    "sg:classifiers":[
        {
            "category":"Shopping",
            "subcategory":"Crafts & Fabrics",
            "type":"Retail Goods"
        }
    ],
    "sg:phone":"+44 121 770 2905",
    "sg:postcode":"B37 5AY",
    "sg:province":"West Midlands",
    "sg:tags":[
        "material",
        "art"
    ],
    "wof:name":"Habberley Meadows W Ltd.",
    "wof:placetype":"venue"
},
  "geometry": {"coordinates":[-1.7552390099,52.483379364],"type":"Point"}
}