{
  "type": "Feature",
  "properties": {
    "addr:full":"The Old Brickyard, North End Swindon Gloucestershire SN6 6QR",
    "addr:postcode":"sn6 6qr",
    "iso:country":"GB",
    "sg:address":"The Old Brickyard, North End",
    "sg:city":"Swindon",
    "sg:classifiers":[
        {
            "category":"Building & Trades",
            "subcategory":"Landscaping Services",
            "type":"Services"
        }
    ],
    "sg:phone":"+44 1285 860015",
    "sg:postcode":"SN6 6QR",
    "sg:province":"Gloucestershire",
    "sg:tags":[
        "horticultural"
    ],
    "wof:name":"Agralan Ltd.",
    "wof:placetype":"venue"
},
  "geometry": {"coordinates":[-1.929411,51.643608],"type":"Point"}
}