{
  "type": "Feature",
  "properties": {
    "addr:full":"23a-23b North Street Emsworth Hampshire PO10 7BY",
    "addr:housenumber":"23a-23b",
    "addr:postcode":"po10 7by",
    "addr:street":"North Street",
    "iso:country":"GB",
    "sg:address":"23a-23b North Street",
    "sg:city":"Emsworth",
    "sg:classifiers":[
        {
            "category":"Shopping",
            "subcategory":"Crafts & Fabrics",
            "type":"Retail Goods"
        }
    ],
    "sg:postcode":"PO10 7BY",
    "sg:province":"Hampshire",
    "sg:tags":[
        "material",
        "art"
    ],
    "wof:name":"The White Knight",
    "wof:placetype":"venue"
},
  "geometry": {"coordinates":[-0.937002,50.848873],"type":"Point"}
}