{
  "type": "Feature",
  "properties": {
    "iso:country":"GB",
    "sg:address":"75 Hart Road",
    "sg:city":"Benfleet",
    "sg:classifiers":[
        {
            "category":"Personal",
            "subcategory":"Beauty Salon",
            "type":"Services"
        }
    ],
    "sg:phone":"+44 1268 565097",
    "sg:postcode":"SS7 3PB",
    "sg:province":"Essex",
    "sg:tags":[
        "unisex",
        "hairdresser"
    ],
    "wof:name":"Hairwaves",
    "wof:placetype":"venue"
},
  "geometry": {"coordinates":[0.581199,51.568932],"type":"Point"}
}