{
  "type": "Feature",
  "properties": {
    "addr:full":"The Abbey School Church Street Tewkesbury Gloucestershire GL20 5PD",
    "addr:postcode":"gl20 5pd",
    "addr:street":"Church Street",
    "iso:country":"GB",
    "sg:address":"The Abbey School Church Street",
    "sg:city":"Tewkesbury",
    "sg:classifiers":[
        {
            "category":"Education",
            "subcategory":"School",
            "type":"Public Place"
        }
    ],
    "sg:phone":"+44 1684 294460",
    "sg:postcode":"GL20 5PD",
    "sg:province":"Gloucestershire",
    "sg:tags":[
        "independent",
        "preparatory"
    ],
    "wof:name":"The Abbey School Tewkesbury",
    "wof:placetype":"venue"
},
  "geometry": {"coordinates":[-2.1494629383,51.9929580688],"type":"Point"}
}