{
  "type": "Feature",
  "properties": {
    "iso:country":"GB",
    "sg:address":"51 Browhill Terrace",
    "sg:city":"Leeds",
    "sg:classifiers":[
        {
            "category":"Building & Trades",
            "subcategory":"Cleaning & Sanitation",
            "type":"Services"
        }
    ],
    "sg:phone":"+44 113 248 4601",
    "sg:postcode":"LS9 6DU",
    "sg:province":"West Yorkshire",
    "sg:tags":[
        "commercial"
    ],
    "wof:name":"C & C Clean",
    "wof:placetype":"venue"
},
  "geometry": {"coordinates":[-1.510039,53.806614],"type":"Point"}
}