{
  "type": "Feature",
  "properties": {
    "addr:full":"Suite 10, St Marys House, 1-7 St Marys Road Market Harborough Leicestershire LE16 7DS",
    "addr:housenumber":"1-7",
    "addr:postcode":"le16 7ds",
    "addr:street":"Suite 10 St;St Marys Road",
    "iso:country":"GB",
    "sg:address":"Suite 10, St Marys House, 1-7 St Marys Road",
    "sg:city":"Market Harborough",
    "sg:classifiers":[
        {
            "category":"Professional",
            "subcategory":"Printing & Photocopies",
            "type":"Services"
        }
    ],
    "sg:phone":"+44 1858 440935",
    "sg:postcode":"LE16 7DS",
    "sg:province":"Leicestershire",
    "sg:tags":[
        "image",
        "processing",
        "system"
    ],
    "wof:name":"Open Image",
    "wof:placetype":"venue"
},
  "geometry": {"coordinates":[-0.9196990132,52.4779281616],"type":"Point"}
}