{
  "type": "Feature",
  "properties": {
    "iso:country":"GB",
    "sg:address":"4 The Green, Clanfield",
    "sg:city":"Bampton",
    "sg:classifiers":[
        {
            "category":"Professional",
            "type":"Services"
        }
    ],
    "sg:phone":"+44 1367 810340",
    "sg:postcode":"OX18 2SR",
    "sg:province":"Gloucestershire",
    "sg:tags":[
        "caterer"
    ],
    "wof:name":"Lindsey Allan",
    "wof:placetype":"venue"
},
  "geometry": {"coordinates":[-1.546758,51.727924],"type":"Point"}
}