{
  "type": "Feature",
  "properties": {
    "addr:full":"Gateway House, Kings Road Fleet Hampshire GU51 3AB",
    "addr:postcode":"gu51 3ab",
    "addr:street":"Kings Road",
    "iso:country":"GB",
    "sg:address":"Gateway House, Kings Road",
    "sg:city":"Fleet",
    "sg:classifiers":[
        {
            "category":"Insurance",
            "subcategory":"Insurance Agent",
            "type":"Services"
        }
    ],
    "sg:phone":"+44 1252 620106",
    "sg:postcode":"GU51 3AB",
    "sg:province":"Hampshire",
    "sg:tags":[
        "broker"
    ],
    "wof:name":"Griffiths Good & Co. Ltd.",
    "wof:placetype":"venue"
},
  "geometry": {"coordinates":[-0.83694,51.284763],"type":"Point"}
}