{
  "type": "Feature",
  "properties": {
    "iso:country":"GB",
    "sg:address":"10a St Johns Square",
    "sg:city":"Glastonbury",
    "sg:classifiers":[
        {
            "category":"Professional",
            "subcategory":"Printing & Photocopies",
            "type":"Services"
        }
    ],
    "sg:postcode":"BA6 9DP",
    "sg:province":"Somerset",
    "sg:tags":[
        "top",
        "publishing",
        "desk"
    ],
    "wof:name":"Shades & Characters Ltd.",
    "wof:placetype":"venue"
},
  "geometry": {"coordinates":[-2.718579,51.148121],"type":"Point"}
}