{
  "type": "Feature",
  "properties": {
    "addr:full":"72 High Street Ruislip Greater London HA4 7AU",
    "addr:housenumber":"72",
    "addr:postcode":"ha4 7au",
    "addr:street":"High Street",
    "iso:country":"GB",
    "sg:address":"72 High Street",
    "sg:city":"Ruislip",
    "sg:classifiers":[
        {
            "category":"Home & Garden",
            "subcategory":"Home Furnishings",
            "type":"Retail Goods"
        }
    ],
    "sg:phone":"+44 1895 630360",
    "sg:postcode":"HA4 7AU",
    "sg:province":"Greater London",
    "sg:tags":[
        "furnishers",
        "planner",
        "kitchen"
    ],
    "wof:name":"County Kitchens Ltd.",
    "wof:placetype":"venue"
},
  "geometry": {"coordinates":[-0.425542,51.574795],"type":"Point"}
}