{
  "type": "Feature",
  "properties": {
    "addr:full":"156 Lincoln Road, North Hykeham Lincoln Lincolnshire LN6 8PE",
    "addr:housenumber":"156",
    "addr:postcode":"ln6 8pe",
    "addr:street":"Lincoln Road North",
    "iso:country":"GB",
    "sg:address":"156 Lincoln Road, North Hykeham",
    "sg:city":"Lincoln",
    "sg:classifiers":[
        {
            "category":"Manufacturing",
            "subcategory":"Wood Products",
            "type":"Manufacturing & Wholesale Goods"
        }
    ],
    "sg:phone":"+44 1522 500454",
    "sg:postcode":"LN6 8PE",
    "sg:province":"Lincolnshire",
    "sg:tags":[
        "maker",
        "cabinet"
    ],
    "wof:name":"Linden Home Improvements",
    "wof:placetype":"venue"
},
  "geometry": {"coordinates":[-0.5829110146,53.1856002808],"type":"Point"}
}