{
  "type": "Feature",
  "properties": {
    "iso:country":"GB",
    "sg:address":"36 Carron Rd",
    "sg:city":"Falkirk",
    "sg:classifiers":[
        {
            "category":"Home & Garden",
            "subcategory":"Household Appliances",
            "type":"Retail Goods"
        }
    ],
    "sg:postcode":"FK2 7RR",
    "sg:province":"Falkirk",
    "sg:tags":[
        "electrical"
    ],
    "wof:name":"Black,Melville,",
    "wof:placetype":"venue"
},
  "geometry": {"coordinates":[-3.790026,56.014435],"type":"Point"}
}