{
  "type": "Feature",
  "properties": {
    "addr:full":"21 Waterpark Rd Birkenhead Merseyside L42 8PJ",
    "addr:housenumber":"21",
    "addr:postcode":"l42 8pj",
    "addr:street":"Waterpark Rd",
    "iso:country":"GB",
    "sg:address":"21 Waterpark Rd",
    "sg:city":"Birkenhead",
    "sg:classifiers":[
        {
            "category":"Home & Garden",
            "subcategory":"Carpets & Floor Coverings",
            "type":"Retail Goods"
        }
    ],
    "sg:phone":"+44 151 608 5914",
    "sg:postcode":"L42 8PJ",
    "sg:province":"Merseyside",
    "sg:tags":[
        "wall",
        "tie",
        "replacement"
    ],
    "wof:name":"Harrison Property Maintenance",
    "wof:placetype":"venue"
},
  "geometry": {"coordinates":[-3.043083,53.371883],"type":"Point"}
}