{
  "type": "Feature",
  "properties": {
    "iso:country":"GB",
    "sg:address":"4 Bank Buildings, Mitcham Lane",
    "sg:city":"London",
    "sg:classifiers":[
        {
            "category":"Retail",
            "subcategory":"Laundry & Dry Cleaning",
            "type":"Services"
        }
    ],
    "sg:phone":"+44 20 8769 2506",
    "sg:postcode":"SW16 6NG",
    "sg:province":"Greater London",
    "sg:tags":[
        "launderette"
    ],
    "wof:name":"Starlight Dry Cleaners",
    "wof:placetype":"venue"
},
  "geometry": {"coordinates":[-0.14199,51.423561],"type":"Point"}
}