{
  "type": "Feature",
  "properties": {
    "addr:full":"18 Cheriton Pl Folkestone Kent CT20 2AZ",
    "addr:housenumber":"18",
    "addr:postcode":"ct20 2az",
    "addr:street":"Cheriton Pl",
    "iso:country":"GB",
    "sg:address":"18 Cheriton Pl",
    "sg:city":"Folkestone",
    "sg:classifiers":[
        {
            "category":"Home & Garden",
            "subcategory":"Furniture",
            "type":"Retail Goods"
        }
    ],
    "sg:postcode":"CT20 2AZ",
    "sg:province":"Kent",
    "wof:name":"The Linen House",
    "wof:placetype":"venue"
},
  "geometry": {"coordinates":[1.1763750315,51.0786895752],"type":"Point"}
}