{
  "type": "Feature",
  "properties": {
    "addr:full":"Devonshire Rd Blackpool Lancashire FY2 0RE",
    "addr:postcode":"fy2 0re",
    "addr:street":"Devonshire Rd",
    "iso:country":"GB",
    "sg:address":"Devonshire Rd",
    "sg:city":"Blackpool",
    "sg:classifiers":[
        {
            "category":"Manufacturing",
            "subcategory":"Rubber & Plastics",
            "type":"Manufacturing & Wholesale Goods"
        },
        {
            "category":"Shopping",
            "subcategory":"Discount & Variety Stores",
            "type":"Retail Goods"
        }
    ],
    "sg:postcode":"FY2 0RE",
    "sg:province":"Lancashire",
    "sg:tags":[
        "product",
        "foam",
        "cleaning",
        "supply"
    ],
    "wof:name":"Gardener,R E,",
    "wof:placetype":"venue"
},
  "geometry": {"coordinates":[-3.0402328968,53.8593330383],"type":"Point"}
}