{
  "type": "Feature",
  "properties": {
    "addr:full":"Black Bourton Rd Carterton Gloucestershire OX18 3HQ",
    "addr:postcode":"ox18 3hq",
    "addr:street":"Black Bourton Rd",
    "iso:country":"GB",
    "sg:address":"Black Bourton Rd",
    "sg:city":"Carterton",
    "sg:classifiers":[
        {
            "category":"Food & Beverages",
            "subcategory":"Supermarket",
            "type":"Retail Goods"
        }
    ],
    "sg:phone":"+44 1993 847700",
    "sg:postcode":"OX18 3HQ",
    "sg:province":"Gloucestershire",
    "wof:name":"Oxford Swindon & Gloucester Co-Operative",
    "wof:placetype":"venue"
},
  "geometry": {"coordinates":[-1.5939589739,51.7583961487],"type":"Point"}
}