{
  "type": "Feature",
  "properties": {
    "iso:country":"GB",
    "sg:address":"62 Maldon Road",
    "sg:city":"Colchester",
    "sg:classifiers":[
        {
            "category":"Travel",
            "subcategory":"Hotels & Motels",
            "type":"Entertainment"
        }
    ],
    "sg:postcode":"CO3 3AG",
    "sg:province":"Essex",
    "wof:name":"Jacqueline A Charman",
    "wof:placetype":"venue"
},
  "geometry": {"coordinates":[0.892032,51.885803],"type":"Point"}
}