{
  "type": "Feature",
  "properties": {
    "addr:full":"West Way, Walworth Industrial Estate Andover Hampshire SP10 5JG",
    "addr:housenumber":"estate",
    "addr:postcode":"sp10 5jg",
    "addr:street":"West Way;Industrial",
    "iso:country":"GB",
    "sg:address":"West Way, Walworth Industrial Estate",
    "sg:city":"Andover",
    "sg:classifiers":[
        {
            "category":"Professional",
            "subcategory":"Accounting & Tax Preparation",
            "type":"Services"
        }
    ],
    "sg:phone":"+44 1264 723615",
    "sg:postcode":"SP10 5JG",
    "sg:province":"Hampshire",
    "sg:tags":[
        "accountant"
    ],
    "wof:name":"Allen & Co.",
    "wof:placetype":"venue"
},
  "geometry": {"coordinates":[-1.461004,51.215961],"type":"Point"}
}