{
  "type": "Feature",
  "properties": {
    "iso:country":"GB",
    "sg:address":"37 Hilderthorpe Road",
    "sg:city":"Bridlington",
    "sg:classifiers":[
        {
            "category":"Shopping",
            "subcategory":"Bicycles & Sporting Goods",
            "type":"Retail Goods"
        }
    ],
    "sg:postcode":"YO15 3AZ",
    "sg:province":"East Riding of Yorkshire",
    "sg:tags":[
        "cycle",
        "accessory"
    ],
    "wof:name":"Shire Cycles",
    "wof:placetype":"venue"
},
  "geometry": {"coordinates":[-0.194583,54.082718],"type":"Point"}
}