{
  "type": "Feature",
  "properties": {
    "iso:country":"GB",
    "sg:address":"6 Hillside Rd, Corfe Mullen",
    "sg:city":"Wimborne",
    "sg:classifiers":[
        {
            "category":"Building & Trades",
            "subcategory":"Cleaning & Sanitation",
            "type":"Services"
        }
    ],
    "sg:phone":"+44 1202 640000",
    "sg:postcode":"BH21 3SA",
    "sg:province":"Dorset",
    "sg:tags":[
        "cleaner",
        "window"
    ],
    "wof:name":"Clarity Window Cleaning",
    "wof:placetype":"venue"
},
  "geometry": {"coordinates":[-2.0269680023,50.7613792419],"type":"Point"}
}