{
  "type": "Feature",
  "properties": {
    "addr:full":"41-43 Kings Road Ashford Kent TN27 9QP",
    "addr:housenumber":"41-43",
    "addr:postcode":"tn27 9qp",
    "addr:street":"Kings Road",
    "iso:country":"GB",
    "sg:address":"41-43 Kings Road",
    "sg:city":"Ashford",
    "sg:classifiers":[
        {
            "category":"Food & Beverages",
            "subcategory":"Fruits & Vegetables",
            "type":"Retail Goods"
        }
    ],
    "sg:phone":"+44 1622 890336",
    "sg:postcode":"TN27 9QP",
    "sg:province":"Kent",
    "sg:tags":[
        "greengrocer"
    ],
    "wof:name":"P Austen",
    "wof:placetype":"venue"
},
  "geometry": {"coordinates":[0.6234679818,51.1702232361],"type":"Point"}
}