{
  "type": "Feature",
  "properties": {
    "iso:country":"GB",
    "sg:address":"6 Cleveland Place East",
    "sg:city":"Bath",
    "sg:classifiers":[
        {
            "category":"Autos & Motor Vehicles",
            "subcategory":"Auto Supplies",
            "type":"Retail Goods"
        }
    ],
    "sg:phone":"+44 1225 421339",
    "sg:postcode":"BA1 5DJ",
    "sg:province":"Bath and North East Somerset",
    "sg:tags":[
        "part",
        "motorcycle",
        "accessory"
    ],
    "wof:name":"H R S Motorcycles & Accessories",
    "wof:placetype":"venue"
},
  "geometry": {"coordinates":[-2.364607,51.391373],"type":"Point"}
}