{
  "type": "Feature",
  "properties": {
    "addr:full":"613 Southchurch Road Southend On Sea Essex SS1 2PN",
    "addr:housenumber":"613",
    "addr:postcode":"ss1 2pn",
    "addr:street":"Southchurch Road",
    "iso:country":"GB",
    "sg:address":"613 Southchurch Road",
    "sg:city":"Southend On Sea",
    "sg:classifiers":[
        {
            "category":"Shopping",
            "subcategory":"Catalog Store",
            "type":"Retail Goods"
        }
    ],
    "sg:phone":"+44 1702 468483",
    "sg:postcode":"SS1 2PN",
    "sg:province":"Essex",
    "sg:tags":[
        "mail",
        "order"
    ],
    "wof:name":"Kingdom Krafts",
    "wof:placetype":"venue"
},
  "geometry": {"coordinates":[0.7321529984,51.5407714844],"type":"Point"}
}