{
  "type": "Feature",
  "properties": {
    "addr:full":"354 Wylds Lane Worcester Worcestershire WR5 1EF",
    "addr:housenumber":"354",
    "addr:postcode":"wr5 1ef",
    "addr:street":"Wylds Lane",
    "iso:country":"GB",
    "sg:address":"354 Wylds Lane",
    "sg:city":"Worcester",
    "sg:classifiers":[
        {
            "category":"Shopping",
            "subcategory":"Crafts & Fabrics",
            "type":"Retail Goods"
        }
    ],
    "sg:postcode":"WR5 1EF",
    "sg:province":"Worcestershire",
    "sg:tags":[
        "machine",
        "sewing",
        "knitting"
    ],
    "wof:name":"Charles Wright Sewing Machine Engineer",
    "wof:placetype":"venue"
},
  "geometry": {"coordinates":[-2.2050879002,52.1864242554],"type":"Point"}
}