{
  "type": "Feature",
  "properties": {
    "addr:full":"Care Of Midland Bank, 38 High Street Exeter Devon EX4 3LP",
    "addr:housenumber":"38",
    "addr:postcode":"ex4 3lp",
    "addr:street":"High Street",
    "iso:country":"GB",
    "sg:address":"Care Of Midland Bank, 38 High Street",
    "sg:city":"Exeter",
    "sg:classifiers":[
        {
            "category":"Travel",
            "subcategory":"Travel Agent",
            "type":"Entertainment"
        }
    ],
    "sg:phone":"+44 1392 425712",
    "sg:postcode":"EX4 3LP",
    "sg:province":"Devon",
    "wof:name":"Bureaux De Change",
    "wof:placetype":"venue"
},
  "geometry": {"coordinates":[-3.5306301117,50.7237281799],"type":"Point"}
}