{
  "type": "Feature",
  "properties": {
    "addr:full":"56 High Street, Barkingside Ilford Essex IG6 2DQ",
    "addr:housenumber":"56",
    "addr:postcode":"ig6 2dq",
    "addr:street":"High Street",
    "iso:country":"GB",
    "sg:address":"56 High Street, Barkingside",
    "sg:city":"Ilford",
    "sg:classifiers":[
        {
            "category":"Shopping",
            "subcategory":"Clothing, Apparel, & Fashions",
            "type":"Retail Goods"
        }
    ],
    "sg:phone":"+44 20 8550 6434",
    "sg:postcode":"IG6 2DQ",
    "sg:province":"Essex",
    "sg:tags":[
        "shop",
        "lady",
        "fashionwear"
    ],
    "wof:name":"Panache Ladieswear Ltd.",
    "wof:placetype":"venue"
},
  "geometry": {"coordinates":[0.081973,51.589828],"type":"Point"}
}