{
  "type": "Feature",
  "properties": {
    "addr:full":"18 Woodgate, Rothley Leicester Leicestershire LE7 7LJ",
    "addr:housenumber":"18;rothley",
    "addr:postcode":"le7 7lj",
    "addr:street":"Woodgate",
    "iso:country":"GB",
    "sg:address":"18 Woodgate, Rothley",
    "sg:city":"Leicester",
    "sg:classifiers":[
        {
            "category":"Cinema",
            "subcategory":"Movie Rental",
            "type":"Entertainment"
        }
    ],
    "sg:postcode":"LE7 7LJ",
    "sg:province":"Leicestershire",
    "sg:tags":[
        "video",
        "library"
    ],
    "wof:name":"Rothley Video Centre",
    "wof:placetype":"venue"
},
  "geometry": {"coordinates":[-1.1835589409,52.6738357544],"type":"Point"}
}