{
  "type": "Feature",
  "properties": {
    "addr:full":"329 Greenford Road Greenford Greater London UB6 8RE",
    "addr:housenumber":"329",
    "addr:postcode":"ub6 8re",
    "addr:street":"Greenford Road",
    "iso:country":"GB",
    "sg:address":"329 Greenford Road",
    "sg:city":"Greenford",
    "sg:classifiers":[
        {
            "category":"Fast Food",
            "type":"Food & Drink"
        }
    ],
    "sg:phone":"+44 20 8575 0860",
    "sg:postcode":"UB6 8RE",
    "sg:province":"Greater London",
    "sg:tags":[
        "away",
        "take"
    ],
    "wof:name":"Kebab Center",
    "wof:placetype":"venue"
},
  "geometry": {"coordinates":[-0.349755,51.531761],"type":"Point"}
}