{
  "type": "Feature",
  "properties": {
    "iso:country":"GB",
    "sg:address":"Silwood Road",
    "sg:city":"Ascot",
    "sg:classifiers":[
        {
            "category":"Government",
            "subcategory":"Post Office",
            "type":"Public Place"
        }
    ],
    "sg:postcode":"SL5 0QF",
    "sg:province":"Berkshire",
    "sg:tags":[
        "messenger",
        "courier"
    ],
    "wof:name":"P C Couriers",
    "wof:placetype":"venue"
},
  "geometry": {"coordinates":[-0.639064,51.405472],"type":"Point"}
}