{
  "type": "Feature",
  "properties": {
    "addr:full":"61 Orchard Street Weston-super-mare Somerset BS23 1RJ",
    "addr:housenumber":"61",
    "addr:postcode":"bs23 1rj",
    "addr:street":"Orchard Street",
    "iso:country":"GB",
    "sg:address":"61 Orchard Street",
    "sg:city":"Weston-super-mare",
    "sg:classifiers":[
        {
            "category":"Personal",
            "subcategory":"Beauty Salon",
            "type":"Services"
        }
    ],
    "sg:postcode":"BS23 1RJ",
    "sg:province":"Somerset",
    "sg:tags":[
        "unisex",
        "hairdresser"
    ],
    "wof:name":"Orchard Hair Co",
    "wof:placetype":"venue"
},
  "geometry": {"coordinates":[-2.975983,51.349518],"type":"Point"}
}