{
  "type": "Feature",
  "properties": {
    "iso:country":"GB",
    "sg:address":"6 Rock Street",
    "sg:city":"Brighton",
    "sg:classifiers":[
        {
            "category":"Building & Trades",
            "subcategory":"Landscaping Services",
            "type":"Services"
        }
    ],
    "sg:phone":"+44 1273 674077",
    "sg:postcode":"BN2 1NF",
    "sg:province":"East Sussex",
    "sg:tags":[
        "pond",
        "aquarium"
    ],
    "wof:name":"The Fish Tank",
    "wof:placetype":"venue"
},
  "geometry": {"coordinates":[-0.1124799997,50.8165664673],"type":"Point"}
}