{
  "type": "Feature",
  "properties": {
    "iso:country":"GB",
    "sg:address":"1 Raynham Street",
    "sg:city":"Norwich",
    "sg:classifiers":[
        {
            "category":"Retail",
            "subcategory":"Auto Repair",
            "type":"Services"
        }
    ],
    "sg:phone":"+44 1603 766545",
    "sg:postcode":"NR2 4LL",
    "sg:province":"Norfolk",
    "sg:tags":[
        "modification",
        "garage"
    ],
    "wof:name":"A & R Autos",
    "wof:placetype":"venue"
},
  "geometry": {"coordinates":[1.27987,52.639462],"type":"Point"}
}