{
  "type": "Feature",
  "properties": {
    "addr:full":"Archway Resource Centre, 1b Waterlow Rd Archway Greater London N19 5NJ",
    "addr:housenumber":"1b",
    "addr:postcode":"n19 5nj",
    "addr:street":"Waterlow Rd",
    "iso:country":"GB",
    "sg:address":"Archway Resource Centre, 1b Waterlow Rd",
    "sg:city":"Archway",
    "sg:classifiers":[
        {
            "category":"Organizations",
            "subcategory":"Non-profit Organization",
            "type":"Services"
        }
    ],
    "sg:phone":"+44 20 7263 9759",
    "sg:postcode":"N19 5NJ",
    "sg:province":"Greater London",
    "sg:tags":[
        "organisation",
        "voluntary",
        "charity"
    ],
    "wof:name":"Centres for Change",
    "wof:placetype":"venue"
},
  "geometry": {"coordinates":[-0.1375499964,51.5685501099],"type":"Point"}
}