{
  "type": "Feature",
  "properties": {
    "addr:full":"Unit 30 Power Station Road Rugeley Staffordshire WS15 2HS",
    "addr:housenumber":"unit 30",
    "addr:postcode":"ws15 2hs",
    "addr:street":"Power Station Road",
    "iso:country":"GB",
    "sg:address":"Unit 30 Power Station Road",
    "sg:city":"Rugeley",
    "sg:classifiers":[
        {
            "category":"Manufacturing",
            "subcategory":"Electronics",
            "type":"Manufacturing & Wholesale Goods"
        }
    ],
    "sg:phone":"+44 1889 578220",
    "sg:postcode":"WS15 2HS",
    "sg:province":"Staffordshire",
    "sg:tags":[
        "printed",
        "circuit"
    ],
    "wof:name":"Circuits Seventy Seven Ltd.",
    "wof:placetype":"venue"
},
  "geometry": {"coordinates":[-1.932009,52.765644],"type":"Point"}
}