{
  "type": "Feature",
  "properties": {
    "iso:country":"GB",
    "sg:address":"Health Centre, Stafford Road",
    "sg:city":"Caterham",
    "sg:classifiers":[
        {
            "category":"Health Services",
            "subcategory":"Dentist",
            "type":"Services"
        }
    ],
    "sg:phone":"+44 1883 343444",
    "sg:postcode":"CR3 6JG",
    "sg:province":"Surrey",
    "wof:name":"Community Dental Services",
    "wof:placetype":"venue"
},
  "geometry": {"coordinates":[-0.076936,51.281578],"type":"Point"}
}