{
  "type": "Feature",
  "properties": {
    "iso:country":"GB",
    "sg:address":"52a Grand Parade Green Lanes",
    "sg:city":"Finsbury Park",
    "sg:classifiers":[
        {
            "category":"Fast Food",
            "type":"Food & Drink"
        }
    ],
    "sg:postcode":"N4 1AG",
    "sg:province":"Greater London",
    "sg:tags":[
        "away",
        "take"
    ],
    "wof:name":"Sofra Ltd",
    "wof:placetype":"venue"
},
  "geometry": {"coordinates":[-0.0989,51.578861],"type":"Point"}
}