{
  "type": "Feature",
  "properties": {
    "addr:full":"94 Union Street Plymouth Devon PL1 3EZ",
    "addr:housenumber":"94",
    "addr:postcode":"pl1 3ez",
    "addr:street":"Union Street",
    "iso:country":"GB",
    "sg:address":"94 Union Street",
    "sg:city":"Plymouth",
    "sg:classifiers":[
        {
            "category":"Health Services",
            "subcategory":"Medical Lab",
            "type":"Services"
        },
        {
            "category":"Shopping",
            "subcategory":"Pharmacy",
            "type":"Retail Goods"
        }
    ],
    "sg:phone":"+44 1752 263860",
    "sg:postcode":"PL1 3EZ",
    "sg:province":"Devon",
    "sg:tags":[
        "medicine",
        "alternative",
        "therapy",
        "treatment"
    ],
    "wof:name":"The Gentlemans Club",
    "wof:placetype":"venue"
},
  "geometry": {"coordinates":[-4.1535511017,50.369846344],"type":"Point"}
}