{
  "type": "Feature",
  "properties": {
    "addr:full":"45 Ferryfield Edinburgh City of Edinburgh EH5 2PS",
    "addr:housenumber":"45",
    "addr:postcode":"eh5 2ps",
    "addr:street":"Ferryfield Edinburgh",
    "iso:country":"GB",
    "sg:address":"45 Ferryfield",
    "sg:city":"Edinburgh",
    "sg:classifiers":[
        {
            "category":"Communications",
            "subcategory":"Newspaper",
            "type":"Services"
        }
    ],
    "sg:phone":"+44 131 551 4757",
    "sg:postcode":"EH5 2PS",
    "sg:province":"City of Edinburgh",
    "sg:tags":[
        "magazine"
    ],
    "wof:name":"The Scottish Property Executive",
    "wof:placetype":"venue"
},
  "geometry": {"coordinates":[-3.2205491066,55.9710121155],"type":"Point"}
}