{
  "type": "Feature",
  "properties": {
    "iso:country":"GB",
    "sg:address":"Poppy Holborn Studios",
    "sg:city":"London",
    "sg:classifiers":[
        {
            "category":"Communications",
            "subcategory":"Film & Video Production",
            "type":"Services"
        },
        {
            "category":"Communications",
            "type":"Services"
        }
    ],
    "sg:phone":"+44 20 7684 0011",
    "sg:postcode":"N1 7ED",
    "sg:province":"Greater London",
    "sg:tags":[
        "tv",
        "studio",
        "audio-visual"
    ],
    "wof:name":"Hammer & Tongs Ltd.",
    "wof:placetype":"venue"
},
  "geometry": {"coordinates":[-0.0913100019,51.5343399048],"type":"Point"}
}