{
  "type": "Feature",
  "properties": {
    "iso:country":"GB",
    "sg:address":"15-23 Merridale Road, Chapel Ash",
    "sg:city":"Wolverhampton",
    "sg:classifiers":[
        {
            "category":"Home & Garden",
            "subcategory":"Furniture",
            "type":"Retail Goods"
        }
    ],
    "sg:phone":"+44 1902 420699",
    "sg:postcode":"WV3 9RX",
    "sg:province":"Staffordshire",
    "wof:name":"Merridale Furnishers",
    "wof:placetype":"venue"
},
  "geometry": {"coordinates":[-2.1424291134,52.5849838257],"type":"Point"}
}