{
  "type": "Feature",
  "properties": {
    "iso:country":"GB",
    "sg:address":"Waterside, Dornafield Rd",
    "sg:city":"Newton Abbot",
    "sg:classifiers":[
        {
            "category":"Shopping",
            "subcategory":"Clothing, Apparel, & Fashions",
            "type":"Retail Goods"
        }
    ],
    "sg:phone":"+44 1803 812958",
    "sg:postcode":"TQ12 5SG",
    "sg:province":"Devon",
    "sg:tags":[
        "clothing"
    ],
    "wof:name":"J P A Dewhirst",
    "wof:placetype":"venue"
},
  "geometry": {"coordinates":[-3.6397778988,50.4902191162],"type":"Point"}
}