{
  "type": "Feature",
  "properties": {
    "addr:full":"6 Clarence Place Whitby North Yorkshire YO21 3AS",
    "addr:housenumber":"6",
    "addr:postcode":"yo21 3as",
    "addr:street":"Clarence Place",
    "iso:country":"GB",
    "sg:address":"6 Clarence Place",
    "sg:city":"Whitby",
    "sg:classifiers":[
        {
            "category":"Retail",
            "subcategory":"Auto Repair",
            "type":"Services"
        }
    ],
    "sg:phone":"+44 1723 500451",
    "sg:postcode":"YO21 3AS",
    "sg:province":"North Yorkshire",
    "sg:tags":[
        "modification",
        "garage"
    ],
    "wof:name":"Andrew Taylor",
    "wof:placetype":"venue"
},
  "geometry": {"coordinates":[-0.6190620065,54.4880523682],"type":"Point"}
}