{
  "type": "Feature",
  "properties": {
    "iso:country":"GB",
    "sg:address":"Wellbrook Medical Centre, Welland Road",
    "sg:city":"Derby",
    "sg:classifiers":[
        {
            "category":"Health Services",
            "subcategory":"Doctor",
            "type":"Services"
        }
    ],
    "sg:phone":"+44 1283 732257",
    "sg:postcode":"DE65 5GZ",
    "sg:province":"Derbyshire",
    "sg:tags":[
        "practitioners"
    ],
    "wof:name":"Williams N.R Newton R.J & Bryant G.M.C Drs",
    "wof:placetype":"venue"
},
  "geometry": {"coordinates":[-1.63065,52.868622],"type":"Point"}
}