{
  "type": "Feature",
  "properties": {
    "iso:country":"GB",
    "sg:address":"Unit 1 & 2 Priory Indust Est",
    "sg:city":"Tetbury",
    "sg:classifiers":[
        {
            "category":"Professional",
            "subcategory":"Testing Lab",
            "type":"Services"
        }
    ],
    "sg:phone":"+44 1666 502316",
    "sg:postcode":"GL8 8HZ",
    "sg:province":"Gloucestershire",
    "sg:tags":[
        "mot"
    ],
    "wof:name":"Tetbury Mot Centre",
    "wof:placetype":"venue"
},
  "geometry": {"coordinates":[-2.1571099758,51.6415214539],"type":"Point"}
}