{
  "type": "Feature",
  "properties": {
    "addr:full":"1 Romill Close, West End Southampton Hampshire SO18 3NE",
    "addr:housenumber":"1",
    "addr:postcode":"so18 3ne",
    "addr:street":"Romill Close",
    "iso:country":"GB",
    "sg:address":"1 Romill Close, West End",
    "sg:city":"Southampton",
    "sg:classifiers":[
        {
            "category":"Building & Trades",
            "subcategory":"Construction",
            "type":"Services"
        }
    ],
    "sg:phone":"+44 23 8047 2776",
    "sg:postcode":"SO18 3NE",
    "sg:province":"Hampshire",
    "sg:tags":[
        "builder"
    ],
    "wof:name":"Mill Developments",
    "wof:placetype":"venue"
},
  "geometry": {"coordinates":[-1.3521800041,50.935508728],"type":"Point"}
}