{
  "type": "Feature",
  "properties": {
    "addr:full":"29 Catherine St Frome Somerset BA11 1DB",
    "addr:housenumber":"29",
    "addr:postcode":"ba11 1db",
    "addr:street":"Catherine St",
    "iso:country":"GB",
    "sg:address":"29 Catherine St",
    "sg:city":"Frome",
    "sg:classifiers":[
        {
            "category":"Shopping",
            "subcategory":"Discount & Variety Stores",
            "type":"Retail Goods"
        }
    ],
    "sg:phone":"+44 1373 452522",
    "sg:postcode":"BA11 1DB",
    "sg:province":"Somerset",
    "sg:tags":[
        "shop",
        "model"
    ],
    "wof:name":"Mendip Models",
    "wof:placetype":"venue"
},
  "geometry": {"coordinates":[-2.3265550137,51.2309036255],"type":"Point"}
}