{
  "type": "Feature",
  "properties": {
    "iso:country":"GB",
    "sg:address":"52 Ibstock Rd",
    "sg:city":"Coalville",
    "sg:classifiers":[
        {
            "category":"Professional",
            "subcategory":"Art Services",
            "type":"Services"
        }
    ],
    "sg:phone":"+44 1530 832320",
    "sg:postcode":"LE67 2AL",
    "sg:province":"Leicestershire",
    "sg:tags":[
        "photographer"
    ],
    "wof:name":"Bloomfield Photography",
    "wof:placetype":"venue"
},
  "geometry": {"coordinates":[-1.3984470367,52.7180366516],"type":"Point"}
}