{
  "type": "Feature",
  "properties": {
    "addr:full":"2 Vancouver Avenue, Radcliffe On Trent Nottingham Nottinghamshire NG12 2ES",
    "addr:housenumber":"2",
    "addr:postcode":"ng12 2es",
    "addr:street":"Vancouver Avenue",
    "iso:country":"GB",
    "sg:address":"2 Vancouver Avenue, Radcliffe On Trent",
    "sg:city":"Nottingham",
    "sg:classifiers":[
        {
            "category":"Building & Trades",
            "subcategory":"Plumbing",
            "type":"Services"
        }
    ],
    "sg:postcode":"NG12 2ES",
    "sg:province":"Nottinghamshire",
    "sg:tags":[
        "heating"
    ],
    "wof:name":"Maurice F Fisher & Son",
    "wof:placetype":"venue"
},
  "geometry": {"coordinates":[-1.0443079472,52.9447555542],"type":"Point"}
}