{
  "type": "Feature",
  "properties": {
    "addr:full":"Mary Catherine House, Third Avenue, Millbrook Southampton Hampshire SO15 0JX",
    "addr:postcode":"so15 0jx",
    "addr:street":"Mary;Third Avenue",
    "iso:country":"GB",
    "sg:address":"Mary Catherine House, Third Avenue, Millbrook",
    "sg:city":"Southampton",
    "sg:classifiers":[
        {
            "category":"Professional",
            "subcategory":"Business Services",
            "type":"Services"
        }
    ],
    "sg:postcode":"SO15 0JX",
    "sg:province":"Hampshire",
    "sg:tags":[
        "tile",
        "stockist"
    ],
    "wof:name":"On the Tiles",
    "wof:placetype":"venue"
},
  "geometry": {"coordinates":[-1.4554610252,50.9162559509],"type":"Point"}
}