{
  "type": "Feature",
  "properties": {
    "iso:country":"GB",
    "sg:address":"64 Bryant Road",
    "sg:city":"Rochester",
    "sg:classifiers":[
        {
            "category":"Food & Beverages",
            "subcategory":"Liquor & Beverages",
            "type":"Retail Goods"
        }
    ],
    "sg:phone":"+44 1634 718658",
    "sg:postcode":"ME2 3ES",
    "sg:province":"Kent",
    "sg:tags":[
        "beer",
        "wine",
        "spirit",
        "wines"
    ],
    "wof:name":"Ace Wine Stores",
    "wof:placetype":"venue"
},
  "geometry": {"coordinates":[0.489688,51.398464],"type":"Point"}
}