{
  "type": "Feature",
  "properties": {
    "iso:country":"GB",
    "sg:address":"Unit 3 Kings Meadow, Ferry Hinksey Rd",
    "sg:city":"Oxford",
    "sg:classifiers":[
        {
            "category":"Professional",
            "subcategory":"Printing & Photocopies",
            "type":"Services"
        }
    ],
    "sg:phone":"+44 1865 248382",
    "sg:postcode":"OX2 0DP",
    "sg:province":"Oxfordshire",
    "sg:tags":[
        "printer"
    ],
    "wof:name":"Hunts Printing Ltd",
    "wof:placetype":"venue"
},
  "geometry": {"coordinates":[-1.276211,51.751202],"type":"Point"}
}