{
  "type": "Feature",
  "properties": {
    "addr:full":"24 Westwood Rd Newbury Berkshire RG14 7TP",
    "addr:housenumber":"24",
    "addr:postcode":"rg14 7tp",
    "addr:street":"Westwood Rd",
    "iso:country":"GB",
    "sg:address":"24 Westwood Rd",
    "sg:city":"Newbury",
    "sg:classifiers":[
        {
            "category":"Professional",
            "subcategory":"Art Services",
            "type":"Services"
        }
    ],
    "sg:phone":"+44 1635 528163",
    "sg:postcode":"RG14 7TP",
    "sg:province":"Berkshire",
    "sg:tags":[
        "consultant",
        "design"
    ],
    "wof:name":"Bob Morley Designs Ltd",
    "wof:placetype":"venue"
},
  "geometry": {"coordinates":[-1.3102600574,51.3908691406],"type":"Point"}
}