{
  "type": "Feature",
  "properties": {
    "addr:full":"3 Millpond End, North Woodchester Stroud Gloucestershire GL5 5PB",
    "addr:housenumber":"3",
    "addr:postcode":"gl5 5pb",
    "addr:street":"Millpond End North",
    "iso:country":"GB",
    "sg:address":"3 Millpond End, North Woodchester",
    "sg:city":"Stroud",
    "sg:classifiers":[
        {
            "category":"Professional",
            "subcategory":"Business Services",
            "type":"Services"
        }
    ],
    "sg:phone":"+44 1453 872141",
    "sg:postcode":"GL5 5PB",
    "sg:province":"Gloucestershire",
    "sg:tags":[
        "transfer",
        "agent",
        "broking"
    ],
    "wof:name":"Lakey & Co",
    "wof:placetype":"venue"
},
  "geometry": {"coordinates":[-2.2282230854,51.723449707],"type":"Point"}
}