{
  "type": "Feature",
  "properties": {
    "addr:full":"Jasmine Ho, 7 West Terr Richmond North Yorkshire DL10 4EQ",
    "addr:housenumber":"7",
    "addr:postcode":"dl10 4eq",
    "addr:street":"West Terr",
    "iso:country":"GB",
    "sg:address":"Jasmine Ho, 7 West Terr",
    "sg:city":"Richmond",
    "sg:classifiers":[
        {
            "category":"Professional",
            "subcategory":"Advertising",
            "type":"Services"
        }
    ],
    "sg:phone":"+44 1748 825712",
    "sg:postcode":"DL10 4EQ",
    "sg:province":"North Yorkshire",
    "sg:tags":[
        "agency"
    ],
    "wof:name":"Kennedy Advertising & Design",
    "wof:placetype":"venue"
},
  "geometry": {"coordinates":[-1.738664031,54.4043388367],"type":"Point"}
}