{
  "type": "Feature",
  "properties": {
    "iso:country":"GB",
    "sg:address":"23 St Georges Street",
    "sg:city":"Stamford",
    "sg:classifiers":[
        {
            "category":"Farming",
            "subcategory":"Farm",
            "type":"Manufacturing & Wholesale Goods"
        }
    ],
    "sg:postcode":"PE9 2BJ",
    "sg:province":"Cambridgeshire",
    "sg:tags":[
        "mixed",
        "crop"
    ],
    "wof:name":"C G Musson & Sons Ltd.",
    "wof:placetype":"venue"
},
  "geometry": {"coordinates":[-0.4760940075,52.6526184082],"type":"Point"}
}