{
  "type": "Feature",
  "properties": {
    "iso:country":"GB",
    "sg:address":"Unit 12 Baildon Mills, Northgate",
    "sg:city":"Shipley",
    "sg:classifiers":[
        {
            "category":"Building & Trades",
            "subcategory":"Construction",
            "type":"Services"
        }
    ],
    "sg:phone":"+44 1274 587290",
    "sg:postcode":"BD17 6JY",
    "sg:province":"West Yorkshire",
    "sg:tags":[
        "joiner",
        "carpenter"
    ],
    "wof:name":"Carter & Spencer",
    "wof:placetype":"venue"
},
  "geometry": {"coordinates":[-1.766849,53.848671],"type":"Point"}
}