{
  "type": "Feature",
  "properties": {
    "iso:country":"GB",
    "sg:address":"29 South Street",
    "sg:city":"Chichester",
    "sg:classifiers":[
        {
            "category":"Health Services",
            "subcategory":"Optometrist",
            "type":"Services"
        }
    ],
    "sg:phone":"+44 1243 782953",
    "sg:postcode":"PO19 1EL",
    "sg:province":"West Sussex",
    "sg:tags":[
        "optician"
    ],
    "wof:name":"Hortsmanns (Opticians)",
    "wof:placetype":"venue"
},
  "geometry": {"coordinates":[-0.779883,50.8344],"type":"Point"}
}