{
  "type": "Feature",
  "properties": {
    "iso:country":"GB",
    "sg:address":"Cloves Wood, Main Road, Morley",
    "sg:city":"Ilkeston",
    "sg:classifiers":[
        {
            "category":"Retail",
            "subcategory":"Portrait Studio",
            "type":"Services"
        },
        {
            "category":"Professional",
            "subcategory":"Art Services",
            "type":"Services"
        }
    ],
    "sg:phone":"+44 1332 880496",
    "sg:postcode":"DE7 6DG",
    "sg:province":"Derbyshire",
    "sg:tags":[
        "photographer",
        "commercial"
    ],
    "wof:name":"Stephen Granger",
    "wof:placetype":"venue"
},
  "geometry": {"coordinates":[-1.415454,52.964596],"type":"Point"}
}