{
  "type": "Feature",
  "properties": {
    "iso:country":"GB",
    "sg:address":"4 Hornbeam Clo",
    "sg:city":"Wellingborough",
    "sg:classifiers":[
        {
            "category":"Professional",
            "subcategory":"Computer Services",
            "type":"Services"
        }
    ],
    "sg:phone":"+44 1933 315515",
    "sg:postcode":"NN29 7HZ",
    "sg:province":"Bedfordshire",
    "sg:tags":[
        "system",
        "software"
    ],
    "wof:name":"M.M.D Software Ltd",
    "wof:placetype":"venue"
},
  "geometry": {"coordinates":[-0.623899,52.253246],"type":"Point"}
}