{
  "type": "Feature",
  "properties": {
    "addr:full":"Oakhurst Rd Oswestry Shropshire SY11 1BH",
    "addr:postcode":"sy11 1bh",
    "addr:street":"Oakhurst Rd",
    "iso:country":"GB",
    "sg:address":"Oakhurst Rd",
    "sg:city":"Oswestry",
    "sg:classifiers":[
        {
            "category":"Bars & Pubs",
            "type":"Food & Drink"
        }
    ],
    "sg:phone":"+44 1691 652529",
    "sg:postcode":"SY11 1BH",
    "sg:province":"Shropshire",
    "sg:tags":[
        "pubs",
        "inn"
    ],
    "wof:name":"Ye Olde White Lion Inn",
    "wof:placetype":"venue"
},
  "geometry": {"coordinates":[-3.062594,52.866619],"type":"Point"}
}