{
  "type": "Feature",
  "properties": {
    "addr:full":"24 Ladywell Walk Birmingham West Midlands B5 4ST",
    "addr:housenumber":"24;b5",
    "addr:postcode":"4st",
    "addr:street":"Ladywell Walk",
    "iso:country":"GB",
    "sg:address":"24 Ladywell Walk",
    "sg:city":"Birmingham",
    "sg:classifiers":[
        {
            "category":"Restaurant",
            "type":"Food & Drink"
        }
    ],
    "sg:phone":"+44 121 666 7031",
    "sg:postcode":"B5 4ST",
    "sg:province":"West Midlands",
    "sg:tags":[
        "oriental"
    ],
    "wof:name":"China Court (Birmingham) Ltd.",
    "wof:placetype":"venue"
},
  "geometry": {"coordinates":[-1.8963409662,52.4754371643],"type":"Point"}
}