{
  "type": "Feature",
  "properties": {
    "iso:country":"GB",
    "sg:address":"Owens Ho, 281-283 Goswell Rd",
    "sg:city":"Clerkenwell",
    "sg:classifiers":[
        {
            "category":"Manufacturing",
            "subcategory":"Textiles",
            "type":"Manufacturing & Wholesale Goods"
        }
    ],
    "sg:phone":"+44 20 7837 7838",
    "sg:postcode":"EC1V 7NT",
    "sg:province":"Greater London",
    "sg:tags":[
        "designer"
    ],
    "wof:name":"Clarissa Hulse",
    "wof:placetype":"venue"
},
  "geometry": {"coordinates":[-0.10377,51.5303],"type":"Point"}
}