{
  "type": "Feature",
  "properties": {
    "iso:country":"GB",
    "sg:address":"13 Orchard Gardens",
    "sg:city":"Littlehampton",
    "sg:classifiers":[
        {
            "category":"Professional",
            "subcategory":"Detective & Security Services",
            "type":"Services"
        }
    ],
    "sg:phone":"+44 1903 787132",
    "sg:postcode":"BN16 3HN",
    "sg:province":"West Sussex",
    "sg:tags":[
        "alarm",
        "burglar",
        "system"
    ],
    "wof:name":"Thistle Alarms",
    "wof:placetype":"venue"
},
  "geometry": {"coordinates":[-0.501761,50.814785],"type":"Point"}
}