{
  "type": "Feature",
  "properties": {
    "addr:full":"71 Pinhoe Road Exeter Devon EX4 7HS",
    "addr:housenumber":"71",
    "addr:postcode":"ex4 7hs",
    "addr:street":"Pinhoe Road",
    "iso:country":"GB",
    "sg:address":"71 Pinhoe Road",
    "sg:city":"Exeter",
    "sg:classifiers":[
        {
            "category":"Professional",
            "subcategory":"Art Services",
            "type":"Services"
        }
    ],
    "sg:postcode":"EX4 7HS",
    "sg:province":"Devon",
    "sg:tags":[
        "photographer"
    ],
    "wof:name":"Peter Sandilands",
    "wof:placetype":"venue"
},
  "geometry": {"coordinates":[-3.510537,50.730412],"type":"Point"}
}