{
  "type": "Feature",
  "properties": {
    "iso:country":"GB",
    "sg:address":"26 Cotteswold Road",
    "sg:city":"Tewkesbury",
    "sg:classifiers":[
        {
            "category":"Real Estate",
            "subcategory":"Real Estate Services",
            "type":"Services"
        },
        {
            "category":"Building & Trades",
            "subcategory":"Equipment Rental",
            "type":"Services"
        }
    ],
    "sg:phone":"+44 1684 850779",
    "sg:postcode":"GL20 5DL",
    "sg:province":"Gloucestershire",
    "sg:tags":[
        "hire",
        "leasing",
        "plant",
        "machinery"
    ],
    "wof:name":"K J Plant Hire",
    "wof:placetype":"venue"
},
  "geometry": {"coordinates":[-2.151196,51.996658],"type":"Point"}
}