{
  "type": "Feature",
  "properties": {
    "iso:country":"GB",
    "sg:address":"Victory Lodge, Sarson Lane, Weyhill",
    "sg:city":"Andover",
    "sg:classifiers":[
        {
            "category":"Sports & Exercise",
            "subcategory":"Race Track",
            "type":"Entertainment"
        }
    ],
    "sg:phone":"+44 1264 771321",
    "sg:postcode":"SP11 8DY",
    "sg:province":"Hampshire",
    "sg:tags":[
        "motor"
    ],
    "wof:name":"Mervyn Anstie Ltd.",
    "wof:placetype":"venue"
},
  "geometry": {"coordinates":[-1.56149,51.207932],"type":"Point"}
}