{
  "type": "Feature",
  "properties": {
    "iso:country":"GB",
    "sg:address":"Unit 3 Ackhurst Road",
    "sg:city":"Chorley",
    "sg:classifiers":[
        {
            "category":"Professional",
            "type":"Services"
        }
    ],
    "sg:postcode":"PR7 1ND",
    "sg:province":"Lancashire",
    "sg:tags":[
        "repair",
        "tech",
        "maintenance"
    ],
    "wof:name":"A R K Computers",
    "wof:placetype":"venue"
},
  "geometry": {"coordinates":[-2.65396,53.655384],"type":"Point"}
}