{
  "type": "Feature",
  "properties": {
    "addr:full":"12 Pilgrimage St Southwark Greater London SE1 4LL",
    "addr:housenumber":"12",
    "addr:postcode":"se1 4ll",
    "addr:street":"Pilgrimage St",
    "iso:country":"GB",
    "sg:address":"12 Pilgrimage St",
    "sg:city":"Southwark",
    "sg:classifiers":[
        {
            "category":"Professional",
            "subcategory":"Printing & Photocopies",
            "type":"Services"
        }
    ],
    "sg:phone":"+44 20 7378 6045",
    "sg:postcode":"SE1 4LL",
    "sg:province":"Greater London",
    "sg:tags":[
        "duplicating",
        "copying"
    ],
    "wof:name":"Wildcat Repographics",
    "wof:placetype":"venue"
},
  "geometry": {"coordinates":[-0.0889699981,51.5005111694],"type":"Point"}
}