{
  "type": "Feature",
  "properties": {
    "addr:full":"Wycombe Rd Wembley Greater London HA0 1RH",
    "addr:postcode":"ha0 1rh",
    "addr:street":"Wycombe Rd",
    "iso:country":"GB",
    "sg:address":"Wycombe Rd",
    "sg:city":"Wembley",
    "sg:classifiers":[
        {
            "category":"Building & Trades",
            "subcategory":"Construction",
            "type":"Services"
        }
    ],
    "sg:phone":"+44 20 8903 7271",
    "sg:postcode":"HA0 1RH",
    "sg:province":"Greater London",
    "sg:tags":[
        "worker",
        "metal"
    ],
    "wof:name":"Phoenix Finishers Ltd",
    "wof:placetype":"venue"
},
  "geometry": {"coordinates":[-0.280149,51.541077],"type":"Point"}
}