{
  "type": "Feature",
  "properties": {
    "iso:country":"GB",
    "sg:address":"22 Longlands",
    "sg:city":"Worthing",
    "sg:classifiers":[
        {
            "category":"Health Services",
            "subcategory":"Doctor",
            "type":"Services"
        }
    ],
    "sg:phone":"+44 1903 236086",
    "sg:postcode":"BN14 9NN",
    "sg:province":"West Sussex",
    "sg:tags":[
        "practitioners"
    ],
    "wof:name":"Kenneth C Rooke",
    "wof:placetype":"venue"
},
  "geometry": {"coordinates":[-0.3713580072,50.8398399353],"type":"Point"}
}