{
  "type": "Feature",
  "properties": {
    "iso:country":"GB",
    "sg:address":"3 East Back Street",
    "sg:city":"Elgin",
    "sg:classifiers":[
        {
            "category":"Building & Trades",
            "subcategory":"Plumbing",
            "type":"Services"
        }
    ],
    "sg:phone":"+44 1343 542033",
    "sg:postcode":"IV30 4EQ",
    "sg:province":"Moray",
    "sg:tags":[
        "plumber",
        "heating"
    ],
    "wof:name":"Simpson Plumbers",
    "wof:placetype":"venue"
},
  "geometry": {"coordinates":[-3.317844,57.654774],"type":"Point"}
}