{
  "type": "Feature",
  "properties": {
    "addr:full":"56 Station Road Taunton Somerset TA1 1NS",
    "addr:housenumber":"56",
    "addr:postcode":"ta1 1ns",
    "addr:street":"Station Road",
    "iso:country":"GB",
    "sg:address":"56 Station Road",
    "sg:city":"Taunton",
    "sg:classifiers":[
        {
            "category":"Retail",
            "subcategory":"Repair Shop",
            "type":"Services"
        }
    ],
    "sg:phone":"+44 1823 271928",
    "sg:postcode":"TA1 1NS",
    "sg:province":"Somerset",
    "sg:tags":[
        "upholstering",
        "upholsterer"
    ],
    "wof:name":"Regency Upholstery",
    "wof:placetype":"venue"
},
  "geometry": {"coordinates":[-3.104158,51.020416],"type":"Point"}
}