{
  "type": "Feature",
  "properties": {
    "addr:full":"Unit 25, Castlefields Ind Est Bridgwater Somerset TA6 4DH",
    "addr:housenumber":"unit 25",
    "addr:postcode":"ta6 4dh",
    "addr:street":"Castlefields Ind Est",
    "iso:country":"GB",
    "sg:address":"Unit 25, Castlefields Ind Est",
    "sg:city":"Bridgwater",
    "sg:classifiers":[
        {
            "category":"Home & Garden",
            "subcategory":"Hardware",
            "type":"Retail Goods"
        }
    ],
    "sg:phone":"+44 1278 426530",
    "sg:postcode":"TA6 4DH",
    "sg:province":"Somerset",
    "sg:tags":[
        "retailer",
        "diy"
    ],
    "wof:name":"Great Mills D.I.Y Superstore",
    "wof:placetype":"venue"
},
  "geometry": {"coordinates":[-3.013824,51.127556],"type":"Point"}
}