{
  "type": "Feature",
  "properties": {
    "addr:full":"61 Ecclesbourne Gardens Palmers Green Greater London N13 5JD",
    "addr:housenumber":"61",
    "addr:postcode":"n13 5jd",
    "addr:street":"Ecclesbourne Gardens",
    "iso:country":"GB",
    "sg:address":"61 Ecclesbourne Gardens",
    "sg:city":"Palmers Green",
    "sg:classifiers":[
        {
            "category":"Retail",
            "subcategory":"Repair Shop",
            "type":"Services"
        }
    ],
    "sg:phone":"+44 20 8882 9745",
    "sg:postcode":"N13 5JD",
    "sg:province":"Greater London",
    "sg:tags":[
        "maintenance"
    ],
    "wof:name":"C Minott",
    "wof:placetype":"venue"
},
  "geometry": {"coordinates":[-0.1057019979,51.6143569946],"type":"Point"}
}