{
  "type": "Feature",
  "properties": {
    "iso:country":"GB",
    "sg:address":"1 Hansler Road, East Dulwich",
    "sg:city":"London",
    "sg:classifiers":[
        {
            "category":"Building & Trades",
            "subcategory":"Construction",
            "type":"Services"
        }
    ],
    "sg:phone":"+44 20 8693 5144",
    "sg:postcode":"SE22 9DJ",
    "sg:province":"Greater London",
    "sg:tags":[
        "builder"
    ],
    "wof:name":"Hotson Ltd.",
    "wof:placetype":"venue"
},
  "geometry": {"coordinates":[-0.0756,51.45652],"type":"Point"}
}