{
  "type": "Feature",
  "properties": {
    "addr:full":"28 Peel Street, Marsden Huddersfield West Yorkshire HD7 6BW",
    "addr:housenumber":"28",
    "addr:postcode":"hd7 6bw",
    "addr:street":"Peel Street;West",
    "iso:country":"GB",
    "sg:address":"28 Peel Street, Marsden",
    "sg:city":"Huddersfield",
    "sg:classifiers":[
        {
            "category":"Personal",
            "subcategory":"Beauty Salon",
            "type":"Services"
        }
    ],
    "sg:phone":"+44 1484 841015",
    "sg:postcode":"HD7 6BW",
    "sg:province":"West Yorkshire",
    "sg:tags":[
        "unisex",
        "hairdresser"
    ],
    "wof:name":"The Cutting Room",
    "wof:placetype":"venue"
},
  "geometry": {"coordinates":[-1.9263679981,53.6003761292],"type":"Point"}
}