{
  "type": "Feature",
  "properties": {
    "iso:country":"GB",
    "sg:address":"12 Prospect Road",
    "sg:city":"Sevenoaks",
    "sg:classifiers":[
        {
            "category":"Communications",
            "subcategory":"Film & Video Production",
            "type":"Services"
        }
    ],
    "sg:postcode":"TN13 3UA",
    "sg:province":"Kent",
    "sg:tags":[
        "illustrator",
        "artist"
    ],
    "wof:name":"Anne Oliver",
    "wof:placetype":"venue"
},
  "geometry": {"coordinates":[0.1953639984,51.2819252014],"type":"Point"}
}