{
  "type": "Feature",
  "properties": {
    "iso:country":"GB",
    "sg:address":"36 High Rd",
    "sg:city":"Romford",
    "sg:classifiers":[
        {
            "category":"Banks & Credit Unions",
            "subcategory":"Bank",
            "type":"Services"
        }
    ],
    "sg:phone":"+44 18122138",
    "sg:postcode":"RM6 6PR",
    "sg:province":"Essex",
    "wof:name":"Woolwich plc",
    "wof:placetype":"venue"
},
  "geometry": {"coordinates":[0.1309799999,51.570766449],"type":"Point"}
}