{
  "type": "Feature",
  "properties": {
    "addr:full":"Bowhill Swimming Pool, 141 Station Rd Lochgelly Fife KY5 9EL",
    "addr:housenumber":"141",
    "addr:postcode":"ky5 9el",
    "addr:street":"Station Rd",
    "iso:country":"GB",
    "sg:address":"Bowhill Swimming Pool, 141 Station Rd",
    "sg:city":"Lochgelly",
    "sg:classifiers":[
        {
            "category":"Government",
            "subcategory":"Office",
            "type":"Public Place"
        }
    ],
    "sg:phone":"+44 1592 414860",
    "sg:postcode":"KY5 9EL",
    "sg:province":"Fife",
    "sg:tags":[
        "local"
    ],
    "wof:name":"Fife Council",
    "wof:placetype":"venue"
},
  "geometry": {"coordinates":[-3.3100790977,56.129776001],"type":"Point"}
}