{
  "type": "Feature",
  "properties": {
    "addr:full":"66 High St Plaistow Greater London E13 0AJ",
    "addr:housenumber":"66",
    "addr:postcode":"e13 0aj",
    "addr:street":"High St",
    "iso:country":"GB",
    "sg:address":"66 High St",
    "sg:city":"Plaistow",
    "sg:classifiers":[
        {
            "category":"Shopping",
            "subcategory":"Department Store",
            "type":"Retail Goods"
        }
    ],
    "sg:phone":"+44 20 8470 5012",
    "sg:postcode":"E13 0AJ",
    "sg:province":"Greater London",
    "wof:name":"Peacocks Stores",
    "wof:placetype":"venue"
},
  "geometry": {"coordinates":[0.022483,51.529942],"type":"Point"}
}