{
  "type": "Feature",
  "properties": {
    "iso:country":"GB",
    "sg:address":"8 Bath St",
    "sg:city":"Nottingham",
    "sg:classifiers":[
        {
            "category":"Cinema",
            "subcategory":"Movie Rental",
            "type":"Entertainment"
        }
    ],
    "sg:phone":"+44 115 911 0414",
    "sg:postcode":"NG1 1DF",
    "sg:province":"Nottinghamshire",
    "sg:tags":[
        "video",
        "library"
    ],
    "wof:name":"Titans Videos",
    "wof:placetype":"venue"
},
  "geometry": {"coordinates":[-1.1367950439,52.9541740417],"type":"Point"}
}