{
  "type": "Feature",
  "properties": {
    "iso:country":"GB",
    "sg:address":"Unit 4, Metro Centre, Ronsons Way",
    "sg:city":"St Albans",
    "sg:classifiers":[
        {
            "category":"Home & Garden",
            "subcategory":"Home Furnishings",
            "type":"Retail Goods"
        },
        {
            "category":"Retail",
            "subcategory":"Storage",
            "type":"Services"
        },
        {
            "category":"Wholesale",
            "subcategory":"Furniture",
            "type":"Manufacturing & Wholesale Goods"
        }
    ],
    "sg:phone":"+44 1727 861092",
    "sg:postcode":"AL4 9QT",
    "sg:province":"Hertfordshire",
    "sg:tags":[
        "shop",
        "shelving",
        "system",
        "fitting",
        "diy",
        "racking"
    ],
    "wof:name":"Smith Daldry & Co. Ltd.",
    "wof:placetype":"venue"
},
  "geometry": {"coordinates":[-0.32113,51.768471],"type":"Point"}
}