{
  "type": "Feature",
  "properties": {
    "iso:country":"GB",
    "sg:address":"222 Grimsby Road",
    "sg:city":"Grimsby",
    "sg:classifiers":[
        {
            "category":"Retail",
            "subcategory":"Repair Shop",
            "type":"Services"
        }
    ],
    "sg:phone":"+44 1472 603349",
    "sg:postcode":"DN32 7EY",
    "sg:province":"Lincolnshire",
    "sg:tags":[
        "upholsterer"
    ],
    "wof:name":"Traditional Styles Upholsterers",
    "wof:placetype":"venue"
},
  "geometry": {"coordinates":[-0.1369590014,53.5496482849],"type":"Point"}
}