{
  "type": "Feature",
  "properties": {
    "iso:country":"GB",
    "sg:address":"149 Elm Road",
    "sg:city":"New Malden",
    "sg:classifiers":[
        {
            "category":"Banks & Credit Unions",
            "subcategory":"Bureau De Change",
            "type":"Services"
        }
    ],
    "sg:phone":"+44 20 8336 2161",
    "sg:postcode":"KT3 3HX",
    "sg:province":"Surrey",
    "sg:tags":[
        "town",
        "consultant",
        "planning"
    ],
    "wof:name":"Planappeal",
    "wof:placetype":"venue"
},
  "geometry": {"coordinates":[-0.2652040124,51.4064331055],"type":"Point"}
}