{
  "type": "Feature",
  "properties": {
    "addr:full":"21a Cross Arthurlie Street, Barrhead Glasgow East Ayrshire G78 1QY",
    "addr:housenumber":"21a",
    "addr:postcode":"g78 1qy",
    "addr:street":"Cross Arthurlie Street",
    "iso:country":"GB",
    "sg:address":"21a Cross Arthurlie Street, Barrhead",
    "sg:city":"Glasgow",
    "sg:classifiers":[
        {
            "category":"Professional",
            "subcategory":"Business Services",
            "type":"Services"
        }
    ],
    "sg:postcode":"G78 1QY",
    "sg:province":"East Ayrshire",
    "sg:tags":[
        "bookmaker"
    ],
    "wof:name":"Sean Graham Bookmakers",
    "wof:placetype":"venue"
},
  "geometry": {"coordinates":[-4.398108,55.799191],"type":"Point"}
}