{
  "type": "Feature",
  "properties": {
    "addr:full":"Broad St Business Complex, Broad Street Glasgow Glasgow City G40 2QW",
    "addr:housenumber":"complex",
    "addr:postcode":"g40 2qw",
    "addr:street":"Broad St;Broad Street",
    "iso:country":"GB",
    "sg:address":"Broad St Business Complex, Broad Street",
    "sg:city":"Glasgow",
    "sg:classifiers":[
        {
            "category":"Manufacturing",
            "subcategory":"Metals",
            "type":"Manufacturing & Wholesale Goods"
        }
    ],
    "sg:phone":"+44 141 554 5506",
    "sg:postcode":"G40 2QW",
    "sg:province":"Glasgow City",
    "sg:tags":[
        "work",
        "sheet"
    ],
    "wof:name":"Shawfield Glazing & Sheet Metal Workers",
    "wof:placetype":"venue"
},
  "geometry": {"coordinates":[-4.217529,55.85202],"type":"Point"}
}