{
  "type": "Feature",
  "properties": {
    "addr:full":"Corner Ho High St, Hartley Wintney, Hook Basingstoke Berkshire RG27 8NY",
    "addr:postcode":"rg27 8ny",
    "addr:street":"High St",
    "iso:country":"GB",
    "sg:address":"Corner Ho High St, Hartley Wintney, Hook",
    "sg:city":"Basingstoke",
    "sg:classifiers":[
        {
            "category":"Shopping",
            "subcategory":"Antiques",
            "type":"Retail Goods"
        }
    ],
    "sg:postcode":"RG27 8NY",
    "sg:province":"Berkshire",
    "wof:name":"Gratwick,Adam,",
    "wof:placetype":"venue"
},
  "geometry": {"coordinates":[-0.900754,51.305828],"type":"Point"}
}