{
  "type": "Feature",
  "properties": {
    "iso:country":"GB",
    "sg:address":"Beech House, 6 Manor Road, Horsforth",
    "sg:city":"Leeds",
    "sg:classifiers":[
        {
            "category":"Professional",
            "subcategory":"Lawyer & Legal Services",
            "type":"Services"
        }
    ],
    "sg:phone":"+44 113 281 8500",
    "sg:postcode":"LS18 4DX",
    "sg:province":"West Yorkshire",
    "sg:tags":[
        "solicitor"
    ],
    "wof:name":"Morley Mitchell",
    "wof:placetype":"venue"
},
  "geometry": {"coordinates":[-1.648647,53.834225],"type":"Point"}
}