{
  "type": "Feature",
  "properties": {
    "addr:full":"Broaddway Shopping Centre London Greater London W6 9YD",
    "addr:postcode":"w6 9yd",
    "iso:country":"GB",
    "sg:address":"Broaddway Shopping Centre",
    "sg:city":"London",
    "sg:classifiers":[
        {
            "category":"Food & Beverages",
            "subcategory":"Supermarket",
            "type":"Retail Goods"
        }
    ],
    "sg:phone":"+44 20 8741 4345",
    "sg:postcode":"W6 9YD",
    "sg:province":"Greater London",
    "wof:name":"Tesco Stores Ltd.",
    "wof:placetype":"venue"
},
  "geometry": {"coordinates":[-0.22367,51.493172],"type":"Point"}
}