{
  "type": "Feature",
  "properties": {
    "addr:full":"Unit 7-9 Furthergate Industrial Estate, Harwood Street Blackburn Lancashire BB1 3BD",
    "addr:housenumber":"unit 7-9;estate",
    "addr:postcode":"bb1 3bd",
    "addr:street":"Furthergate Industrial;Harwood Street",
    "iso:country":"GB",
    "sg:address":"Unit 7-9 Furthergate Industrial Estate, Harwood Street",
    "sg:city":"Blackburn",
    "sg:classifiers":[
        {
            "category":"Manufacturing",
            "subcategory":"Petroleum Products",
            "type":"Manufacturing & Wholesale Goods"
        }
    ],
    "sg:phone":"+44 1254 56513",
    "sg:postcode":"BB1 3BD",
    "sg:province":"Lancashire",
    "sg:tags":[
        "double",
        "glazing"
    ],
    "wof:name":"Hi-Tech Replacement Windows Ltd.",
    "wof:placetype":"venue"
},
  "geometry": {"coordinates":[-2.4608340263,53.7506561279],"type":"Point"}
}