{
  "type": "Feature",
  "properties": {
    "addr:full":"97a Felpham Way Bognor Regis West Sussex PO22 8QB",
    "addr:housenumber":"97a",
    "addr:postcode":"po22 8qb",
    "addr:street":"Felpham Way",
    "iso:country":"GB",
    "sg:address":"97a Felpham Way",
    "sg:city":"Bognor Regis",
    "sg:classifiers":[
        {
            "category":"Professional",
            "subcategory":"Engineering",
            "type":"Services"
        }
    ],
    "sg:phone":"+44 1243 585034",
    "sg:postcode":"PO22 8QB",
    "sg:province":"West Sussex",
    "wof:name":"Arun Automatics",
    "wof:placetype":"venue"
},
  "geometry": {"coordinates":[-0.6422349811,50.793598175],"type":"Point"}
}