{
  "type": "Feature",
  "properties": {
    "iso:country":"GB",
    "sg:address":"119 Cambuslang Rd",
    "sg:city":"Glasgow",
    "sg:classifiers":[
        {
            "category":"Building & Trades",
            "subcategory":"Construction",
            "type":"Services"
        }
    ],
    "sg:phone":"+44 7885 652010",
    "sg:postcode":"G44 5SL",
    "sg:province":"East Renfrewshire",
    "sg:tags":[
        "contractor",
        "paving",
        "driveway"
    ],
    "wof:name":"S & D Paviors",
    "wof:placetype":"venue"
},
  "geometry": {"coordinates":[-4.24968,55.818111],"type":"Point"}
}