{
  "type": "Feature",
  "properties": {
    "iso:country":"GB",
    "sg:address":"40 Ferndale Road",
    "sg:city":"New Milton",
    "sg:classifiers":[
        {
            "category":"Personal",
            "subcategory":"Beauty Salon",
            "type":"Services"
        }
    ],
    "sg:phone":"+44 1425 618846",
    "sg:postcode":"BH25 5EY",
    "sg:province":"Hampshire",
    "sg:tags":[
        "unisex",
        "hairdresser"
    ],
    "wof:name":"Lord & Lady",
    "wof:placetype":"venue"
},
  "geometry": {"coordinates":[-1.649607,50.763744],"type":"Point"}
}