{
  "type": "Feature",
  "properties": {
    "addr:full":"West Beach Kiosk, West Pier Newhaven East Sussex BN9 9DN",
    "addr:postcode":"bn9 9dn",
    "addr:street":"West Pier",
    "iso:country":"GB",
    "sg:address":"West Beach Kiosk, West Pier",
    "sg:city":"Newhaven",
    "sg:classifiers":[
        {
            "category":"Cafe",
            "type":"Food & Drink"
        }
    ],
    "sg:phone":"+44 1273 513514",
    "sg:postcode":"BN9 9DN",
    "sg:province":"East Sussex",
    "sg:tags":[
        "tea",
        "room"
    ],
    "wof:name":"West Beach Cafe",
    "wof:placetype":"venue"
},
  "geometry": {"coordinates":[0.046175,50.795036],"type":"Point"}
}