{
  "type": "Feature",
  "properties": {
    "addr:full":"25 Shadygrove Rd, Raffles Carlisle Cumbria CA2 7LD",
    "addr:housenumber":"25",
    "addr:postcode":"ca2 7ld",
    "addr:street":"Shadygrove Rd",
    "iso:country":"GB",
    "sg:address":"25 Shadygrove Rd, Raffles",
    "sg:city":"Carlisle",
    "sg:classifiers":[
        {
            "category":"Shopping",
            "subcategory":"Thrift Store",
            "type":"Retail Goods"
        }
    ],
    "sg:phone":"+44 1228 590503",
    "sg:postcode":"CA2 7LD",
    "sg:province":"Cumbria",
    "sg:tags":[
        "shop",
        "charity"
    ],
    "wof:name":"Age Concern",
    "wof:placetype":"venue"
},
  "geometry": {"coordinates":[-2.9672451019,54.8905105591],"type":"Point"}
}