{
  "type": "Feature",
  "properties": {
    "iso:country":"GB",
    "sg:address":"17 Medway Clo",
    "sg:city":"Taunton",
    "sg:classifiers":[
        {
            "category":"Education",
            "subcategory":"Music School",
            "type":"Public Place"
        }
    ],
    "sg:phone":"+44 1823 289559",
    "sg:postcode":"TA1 2NS",
    "sg:province":"Somerset",
    "sg:tags":[
        "information",
        "support",
        "dyslexia"
    ],
    "wof:name":"Next Generation",
    "wof:placetype":"venue"
},
  "geometry": {"coordinates":[-3.071667,51.016132],"type":"Point"}
}