{
  "type": "Feature",
  "properties": {
    "iso:country":"GB",
    "sg:address":"49 Cranford St",
    "sg:city":"Smethwick",
    "sg:classifiers":[
        {
            "category":"Bars & Pubs",
            "type":"Food & Drink"
        }
    ],
    "sg:postcode":"B66 2RT",
    "sg:province":"West Midlands",
    "sg:tags":[
        "pubs",
        "inn"
    ],
    "wof:name":"Dewdrop Ltd",
    "wof:placetype":"venue"
},
  "geometry": {"coordinates":[-1.952873,52.49419],"type":"Point"}
}