{
  "type": "Feature",
  "properties": {
    "addr:full":"49 Cranford St Smethwick West Midlands B66 2RT",
    "addr:housenumber":"49",
    "addr:postcode":"b66 2rt",
    "addr:street":"Cranford St",
    "iso:country":"GB",
    "sg:address":"49 Cranford St",
    "sg:city":"Smethwick",
    "sg:classifiers":[
        {
            "category":"Bars & Pubs",
            "type":"Food & Drink"
        }
    ],
    "sg:postcode":"B66 2RT",
    "sg:province":"West Midlands",
    "sg:tags":[
        "pubs",
        "inn"
    ],
    "wof:name":"Dewdrop Ltd",
    "wof:placetype":"venue"
},
  "geometry": {"coordinates":[-1.952873,52.49419],"type":"Point"}
}