{
  "type": "Feature",
  "properties": {
    "addr:full":"Mixenden Adventure Playground, Slippy La Halifax West Yorkshire HX2 8UD",
    "addr:postcode":"hx2 8ud",
    "addr:street":"La;West",
    "iso:country":"GB",
    "sg:address":"Mixenden Adventure Playground, Slippy La",
    "sg:city":"Halifax",
    "sg:classifiers":[
        {
            "category":"Government",
            "subcategory":"Office",
            "type":"Public Place"
        }
    ],
    "sg:phone":"+44 1422 246530",
    "sg:postcode":"HX2 8UD",
    "sg:province":"West Yorkshire",
    "sg:tags":[
        "local"
    ],
    "wof:name":"Calderdale Metropolitan Education Department",
    "wof:placetype":"venue"
},
  "geometry": {"coordinates":[-1.907306,53.752159],"type":"Point"}
}