{
  "type": "Feature",
  "properties": {
    "addr:full":"26 Barton Dale Penrith Cumbria CA10 1BU",
    "addr:housenumber":"26",
    "addr:postcode":"ca10 1bu",
    "addr:street":"Barton Dale",
    "iso:country":"GB",
    "sg:address":"26 Barton Dale",
    "sg:city":"Penrith",
    "sg:classifiers":[
        {
            "category":"Freight",
            "type":"Transportation"
        }
    ],
    "sg:phone":"+44 1768 897070",
    "sg:postcode":"CA10 1BU",
    "sg:province":"Cumbria",
    "sg:tags":[
        "haulage",
        "road"
    ],
    "wof:name":"D E & J Holmes",
    "wof:placetype":"venue"
},
  "geometry": {"coordinates":[-2.7417840958,54.6686820984],"type":"Point"}
}