{
  "type": "Feature",
  "properties": {
    "iso:country":"GB",
    "sg:address":"21 Canon Street",
    "sg:city":"Aberdare",
    "sg:classifiers":[
        {
            "category":"Home & Garden",
            "subcategory":"Carpets & Floor Coverings",
            "type":"Retail Goods"
        }
    ],
    "sg:phone":"+44 1685 883886",
    "sg:postcode":"CF44 7AP",
    "sg:province":"Neath Port Talbot",
    "sg:tags":[
        "carpets",
        "rug",
        "matting"
    ],
    "wof:name":"Home Select Carpets Ltd.",
    "wof:placetype":"venue"
},
  "geometry": {"coordinates":[-3.444478035,51.7132911682],"type":"Point"}
}