{
  "type": "Feature",
  "properties": {
    "addr:full":"20 Marlborough Road Oxford Oxfordshire OX1 4LP",
    "addr:housenumber":"20",
    "addr:postcode":"ox1 4lp",
    "addr:street":"Marlborough Road",
    "iso:country":"GB",
    "sg:address":"20 Marlborough Road",
    "sg:city":"Oxford",
    "sg:classifiers":[
        {
            "category":"Health Services",
            "subcategory":"Clinic",
            "type":"Services"
        }
    ],
    "sg:postcode":"OX1 4LP",
    "sg:province":"Oxfordshire",
    "sg:tags":[
        "aromatherapy"
    ],
    "wof:name":"Margaret Bjarnason",
    "wof:placetype":"venue"
},
  "geometry": {"coordinates":[-1.25964,51.74651],"type":"Point"}
}