{
  "type": "Feature",
  "properties": {
    "addr:full":"11 Dalnair St Glasgow Glasgow City G3 8SD",
    "addr:housenumber":"11",
    "addr:postcode":"g3 8sd",
    "addr:street":"Dalnair St",
    "iso:country":"GB",
    "sg:address":"11 Dalnair St",
    "sg:city":"Glasgow",
    "sg:classifiers":[
        {
            "category":"Health Services",
            "subcategory":"Health Practitioner",
            "type":"Services"
        }
    ],
    "sg:phone":"+44 141 339 0557",
    "sg:postcode":"G3 8SD",
    "sg:province":"Glasgow City",
    "sg:tags":[
        "therapist",
        "speech"
    ],
    "wof:name":"Grace Lockhart B.Sc M.R.C.S.L.T",
    "wof:placetype":"venue"
},
  "geometry": {"coordinates":[-4.293701,55.867195],"type":"Point"}
}