{
  "type": "Feature",
  "properties": {
    "addr:full":"Garden House Studio, Eartham Chichester West Sussex PO18 0LS",
    "addr:postcode":"po18 0ls",
    "iso:country":"GB",
    "sg:address":"Garden House Studio, Eartham",
    "sg:city":"Chichester",
    "sg:classifiers":[
        {
            "category":"Real Estate",
            "subcategory":"Architect",
            "type":"Services"
        }
    ],
    "sg:phone":"+44 1243 814673",
    "sg:postcode":"PO18 0LS",
    "sg:province":"West Sussex",
    "wof:name":"Duncan O'Kelly Architecture",
    "wof:placetype":"venue"
},
  "geometry": {"coordinates":[-0.666877985,50.8765563965],"type":"Point"}
}