{
  "type": "Feature",
  "properties": {
    "iso:country":"GB",
    "sg:address":"Linden Ho, Broad St",
    "sg:city":"Somerton",
    "sg:classifiers":[
        {
            "category":"Organizations",
            "subcategory":"Non-profit Organization",
            "type":"Services"
        }
    ],
    "sg:phone":"+44 1458 274443",
    "sg:postcode":"TA11 7ND",
    "sg:province":"Somerset",
    "sg:tags":[
        "organisation",
        "voluntary",
        "charity"
    ],
    "wof:name":"Prospects Care Services Ltd",
    "wof:placetype":"venue"
},
  "geometry": {"coordinates":[-2.734899,51.054165],"type":"Point"}
}