{
  "type": "Feature",
  "properties": {
    "iso:country":"GB",
    "sg:address":"8 Rowantree Place",
    "sg:city":"Larkhall",
    "sg:classifiers":[
        {
            "category":"Building & Trades",
            "subcategory":"Plumbing",
            "type":"Services"
        }
    ],
    "sg:phone":"+44 1698 883809",
    "sg:postcode":"ML9 2TH",
    "sg:province":"South Lanarkshire",
    "sg:tags":[
        "plumber",
        "heating"
    ],
    "wof:name":"Rowantree Plumbing & Heating",
    "wof:placetype":"venue"
},
  "geometry": {"coordinates":[-3.9515960217,55.7346382141],"type":"Point"}
}