{
  "type": "Feature",
  "properties": {
    "addr:full":"19 High Street, Minster On Sea Sheerness Kent ME12 3QD",
    "addr:housenumber":"19",
    "addr:postcode":"me12 3qd",
    "addr:street":"High Street",
    "iso:country":"GB",
    "sg:address":"19 High Street, Minster On Sea",
    "sg:city":"Sheerness",
    "sg:classifiers":[
        {
            "category":"Fast Food",
            "type":"Food & Drink"
        }
    ],
    "sg:phone":"+44 1795 870647",
    "sg:postcode":"ME12 3QD",
    "sg:province":"Kent",
    "sg:tags":[
        "away",
        "meal",
        "outlet",
        "take"
    ],
    "wof:name":"Kwong Ming Take Away",
    "wof:placetype":"venue"
},
  "geometry": {"coordinates":[0.812564,51.421562],"type":"Point"}
}