{
  "type": "Feature",
  "properties": {
    "addr:full":"3 Nepean Street London Greater London SW15 5DW",
    "addr:housenumber":"3",
    "addr:postcode":"sw15 5dw",
    "addr:street":"Nepean Street",
    "iso:country":"GB",
    "sg:address":"3 Nepean Street",
    "sg:city":"London",
    "sg:classifiers":[
        {
            "category":"Health Services",
            "subcategory":"Doctor",
            "type":"Services"
        }
    ],
    "sg:phone":"+44 20 8780 0792",
    "sg:postcode":"SW15 5DW",
    "sg:province":"Greater London",
    "sg:tags":[
        "practitioners"
    ],
    "wof:name":"Andrew Cull",
    "wof:placetype":"venue"
},
  "geometry": {"coordinates":[-0.2397360057,51.4515457153],"type":"Point"}
}