{
  "type": "Feature",
  "properties": {
    "addr:full":"6 St Oswalds Clo Malpas Cheshire SY14 8QT",
    "addr:housenumber":"6",
    "addr:postcode":"sy14 8qt",
    "addr:street":"St;Cheshire",
    "iso:country":"GB",
    "sg:address":"6 St Oswalds Clo",
    "sg:city":"Malpas",
    "sg:classifiers":[
        {
            "category":"Professional",
            "type":"Services"
        }
    ],
    "sg:phone":"+44 1948 860327",
    "sg:postcode":"SY14 8QT",
    "sg:province":"Cheshire",
    "sg:tags":[
        "repair",
        "tech",
        "maintenance"
    ],
    "wof:name":"B P G A Computer Repairs",
    "wof:placetype":"venue"
},
  "geometry": {"coordinates":[-2.76265,53.021889],"type":"Point"}
}