{
  "type": "Feature",
  "properties": {
    "addr:full":"Newcomen Road Middlesbrough North Yorkshire TS6 6PS",
    "addr:postcode":"ts6 6ps",
    "addr:street":"Newcomen Road",
    "iso:country":"GB",
    "sg:address":"Newcomen Road",
    "sg:city":"Middlesbrough",
    "sg:classifiers":[
        {
            "category":"Building & Trades",
            "subcategory":"Construction",
            "type":"Services"
        }
    ],
    "sg:phone":"+44 1642 440666",
    "sg:postcode":"TS6 6PS",
    "sg:province":"North Yorkshire",
    "sg:tags":[
        "joinery"
    ],
    "wof:name":"Woodtech (Joinery) Ltd.",
    "wof:placetype":"venue"
},
  "geometry": {"coordinates":[-1.182809,54.572796],"type":"Point"}
}