{
  "type": "Feature",
  "properties": {
    "addr:full":"4a Monument Road Ayr South Ayrshire KA7 2RJ",
    "addr:housenumber":"4a",
    "addr:postcode":"ka7 2rj",
    "addr:street":"Monument Road",
    "iso:country":"GB",
    "sg:address":"4a Monument Road",
    "sg:city":"Ayr",
    "sg:classifiers":[
        {
            "category":"Building & Trades",
            "subcategory":"Construction",
            "type":"Services"
        }
    ],
    "sg:postcode":"KA7 2RJ",
    "sg:province":"South Ayrshire",
    "sg:tags":[
        "joiner",
        "carpenter"
    ],
    "wof:name":"James D Thomson & Son",
    "wof:placetype":"venue"
},
  "geometry": {"coordinates":[-4.629394,55.45042],"type":"Point"}
}