{
  "type": "Feature",
  "properties": {
    "addr:full":"58 Market St Bolton Lancashire BL3 1HN",
    "addr:housenumber":"58",
    "addr:postcode":"bl3 1hn",
    "addr:street":"Market St",
    "iso:country":"GB",
    "sg:address":"58 Market St",
    "sg:city":"Bolton",
    "sg:classifiers":[
        {
            "category":"Professional",
            "subcategory":"Lawyer & Legal Services",
            "type":"Services"
        }
    ],
    "sg:phone":"+44 1204 709959",
    "sg:postcode":"BL3 1HN",
    "sg:province":"Lancashire",
    "sg:tags":[
        "solicitor"
    ],
    "wof:name":"The Wells Law Partnership",
    "wof:placetype":"venue"
},
  "geometry": {"coordinates":[-2.369675,53.561665],"type":"Point"}
}