{
  "type": "Feature",
  "properties": {
    "iso:country":"GB",
    "sg:address":"59 North Street, Off Eastcott Hill, Old Town",
    "sg:city":"Swindon",
    "sg:classifiers":[
        {
            "category":"Shopping",
            "subcategory":"Clothing, Apparel, & Fashions",
            "type":"Retail Goods"
        }
    ],
    "sg:phone":"+44 1793 695223",
    "sg:postcode":"SN1 3JY",
    "sg:province":"Wiltshire",
    "sg:tags":[
        "dresswear"
    ],
    "wof:name":"Wear It Well",
    "wof:placetype":"venue"
},
  "geometry": {"coordinates":[-1.779859,51.555222],"type":"Point"}
}