{
  "type": "Feature",
  "properties": {
    "iso:country":"GB",
    "sg:address":"Tong Lane, Tong Village, Off Westgate Hill",
    "sg:city":"Bradford",
    "sg:classifiers":[
        {
            "category":"Government",
            "subcategory":"Post Office",
            "type":"Public Place"
        }
    ],
    "sg:phone":"+44 113 285 3506",
    "sg:postcode":"BD4 0RY",
    "sg:province":"West Yorkshire",
    "wof:name":"Tong Garden Centre Plc",
    "wof:placetype":"venue"
},
  "geometry": {"coordinates":[-1.662504,53.772507],"type":"Point"}
}