{
  "type": "Feature",
  "properties": {
    "addr:full":"138 Victoria Rd Stoke On Trent Staffordshire ST4 2JX",
    "addr:housenumber":"138",
    "addr:postcode":"st4 2jx",
    "addr:street":"Victoria Rd",
    "iso:country":"GB",
    "sg:address":"138 Victoria Rd",
    "sg:city":"Stoke On Trent",
    "sg:classifiers":[
        {
            "category":"Home & Garden",
            "subcategory":"Home Furnishings",
            "type":"Retail Goods"
        }
    ],
    "sg:phone":"+44 1782 746886",
    "sg:postcode":"ST4 2JX",
    "sg:province":"Staffordshire",
    "sg:tags":[
        "blind",
        "curtain",
        "fitting"
    ],
    "wof:name":"Hunters Loose Covers",
    "wof:placetype":"venue"
},
  "geometry": {"coordinates":[-2.162168,53.002293],"type":"Point"}
}