{
  "type": "Feature",
  "properties": {
    "addr:full":"Hanbury Road Pontypool Monmouthshire NP4 6JL",
    "addr:postcode":"np4 6jl",
    "addr:street":"Hanbury Road",
    "iso:country":"GB",
    "sg:address":"Hanbury Road",
    "sg:city":"Pontypool",
    "sg:classifiers":[
        {
            "category":"Education",
            "subcategory":"Library",
            "type":"Public Place"
        },
        {
            "category":"Government",
            "subcategory":"Office",
            "type":"Public Place"
        }
    ],
    "sg:phone":"+44 1495 762820",
    "sg:postcode":"NP4 6JL",
    "sg:province":"Monmouthshire",
    "sg:tags":[
        "book",
        "local"
    ],
    "wof:name":"Pontypool Library",
    "wof:placetype":"venue"
},
  "geometry": {"coordinates":[-3.060379,51.709625],"type":"Point"}
}