{
  "type": "Feature",
  "properties": {
    "addr:full":"26 Earl St Coventry West Midlands CV1 5RU",
    "addr:housenumber":"26",
    "addr:postcode":"cv1 5ru",
    "addr:street":"Earl St",
    "iso:country":"GB",
    "sg:address":"26 Earl St",
    "sg:city":"Coventry",
    "sg:classifiers":[
        {
            "category":"Shopping",
            "subcategory":"Books",
            "type":"Retail Goods"
        }
    ],
    "sg:phone":"+44 24 7622 9092",
    "sg:postcode":"CV1 5RU",
    "sg:province":"West Midlands",
    "sg:tags":[
        "bookseller"
    ],
    "wof:name":"Dillons The Bookstore",
    "wof:placetype":"venue"
},
  "geometry": {"coordinates":[-1.5062279701,52.4068489075],"type":"Point"}
}