{
  "type": "Feature",
  "properties": {
    "addr:full":"16 Beechey Road Bournemouth Dorset BH8 8LL",
    "addr:housenumber":"16",
    "addr:postcode":"bh8 8ll",
    "addr:street":"Beechey Road",
    "iso:country":"GB",
    "sg:address":"16 Beechey Road",
    "sg:city":"Bournemouth",
    "sg:classifiers":[
        {
            "category":"Social Services",
            "subcategory":"Retirement Home",
            "type":"Services"
        }
    ],
    "sg:postcode":"BH8 8LL",
    "sg:province":"Dorset",
    "sg:tags":[
        "rest"
    ],
    "wof:name":"Manse Rest Home",
    "wof:placetype":"venue"
},
  "geometry": {"coordinates":[-1.865212,50.731693],"type":"Point"}
}