{
  "type": "Feature",
  "properties": {
    "addr:full":"21 Station Road, Surfleet Spalding Lincolnshire PE11 4DA",
    "addr:housenumber":"21",
    "addr:postcode":"pe11 4da",
    "addr:street":"Station Road",
    "iso:country":"GB",
    "sg:address":"21 Station Road, Surfleet",
    "sg:city":"Spalding",
    "sg:classifiers":[
        {
            "category":"Professional",
            "subcategory":"Engineering",
            "type":"Services"
        }
    ],
    "sg:postcode":"PE11 4DA",
    "sg:province":"Lincolnshire",
    "sg:tags":[
        "contractor",
        "electrical",
        "engineer"
    ],
    "wof:name":"John Malcom Mayfield",
    "wof:placetype":"venue"
},
  "geometry": {"coordinates":[-0.140424,52.838295],"type":"Point"}
}