{
  "type": "Feature",
  "properties": {
    "iso:country":"GB",
    "sg:address":"3 Doughty Mews",
    "sg:city":"London",
    "sg:classifiers":[
        {
            "category":"Organizations",
            "subcategory":"Membership Organization",
            "type":"Services"
        }
    ],
    "sg:postcode":"WC1N 2PG",
    "sg:province":"Greater London",
    "sg:tags":[
        "club"
    ],
    "wof:name":"The Egypt Exploration Society",
    "wof:placetype":"venue"
},
  "geometry": {"coordinates":[-0.116892,51.523201],"type":"Point"}
}