{
  "type": "Feature",
  "properties": {
    "addr:full":"9 Barnsley Street Wigan Lancashire WN6 7HA",
    "addr:housenumber":"9",
    "addr:postcode":"wn6 7ha",
    "addr:street":"Barnsley Street",
    "iso:country":"GB",
    "sg:address":"9 Barnsley Street",
    "sg:city":"Wigan",
    "sg:classifiers":[
        {
            "category":"Retail",
            "subcategory":"Driving School",
            "type":"Services"
        }
    ],
    "sg:postcode":"WN6 7HA",
    "sg:province":"Lancashire",
    "wof:name":"Paul's Driving Force",
    "wof:placetype":"venue"
},
  "geometry": {"coordinates":[-2.6410050392,53.552230835],"type":"Point"}
}