{
  "type": "Feature",
  "properties": {
    "addr:full":"110 Buxton Road High Peak Cheshire SK23 7PF",
    "addr:housenumber":"110",
    "addr:postcode":"sk23 7pf",
    "addr:street":"Buxton Road",
    "iso:country":"GB",
    "sg:address":"110 Buxton Road",
    "sg:city":"High Peak",
    "sg:classifiers":[
        {
            "category":"Restaurant",
            "type":"Food & Drink"
        }
    ],
    "sg:phone":"+44 1663 732002",
    "sg:postcode":"SK23 7PF",
    "sg:province":"Cheshire",
    "wof:name":"Edwardo's Bistro",
    "wof:placetype":"venue"
},
  "geometry": {"coordinates":[-1.988606,53.347801],"type":"Point"}
}