{
  "type": "Feature",
  "properties": {
    "addr:full":"Richmond Street South, Swan Village West Bromwich West Midlands B70 0DG",
    "addr:postcode":"b70 0dg",
    "addr:street":"Richmond Street South",
    "iso:country":"GB",
    "sg:address":"Richmond Street South, Swan Village",
    "sg:city":"West Bromwich",
    "sg:classifiers":[
        {
            "category":"Retail",
            "subcategory":"Funeral Services",
            "type":"Services"
        }
    ],
    "sg:phone":"+44 121 520 1815",
    "sg:postcode":"B70 0DG",
    "sg:province":"West Midlands",
    "wof:name":"Midland Funeral Supplies Ltd.",
    "wof:placetype":"venue"
},
  "geometry": {"coordinates":[-2.022062,52.531647],"type":"Point"}
}