{
  "type": "Feature",
  "properties": {
    "addr:full":"662 Huddersfield Road, Wyke Bradford West Yorkshire BD12 8JR",
    "addr:housenumber":"662",
    "addr:postcode":"bd12 8jr",
    "addr:street":"Huddersfield Road",
    "iso:country":"GB",
    "sg:address":"662 Huddersfield Road, Wyke",
    "sg:city":"Bradford",
    "sg:classifiers":[
        {
            "category":"Professional",
            "subcategory":"Engineering",
            "type":"Services"
        }
    ],
    "sg:phone":"+44 1274 694089",
    "sg:postcode":"BD12 8JR",
    "sg:province":"West Yorkshire",
    "sg:tags":[
        "civil",
        "engineer"
    ],
    "wof:name":"C C M Construction Ltd.",
    "wof:placetype":"venue"
},
  "geometry": {"coordinates":[-1.772521,53.738468],"type":"Point"}
}