{
  "type": "Feature",
  "properties": {
    "iso:country":"GB",
    "sg:address":"Donnington House, Riverside Road, Pride Park",
    "sg:city":"Derby",
    "sg:classifiers":[
        {
            "category":"Professional",
            "subcategory":"Printing & Photocopies",
            "type":"Services"
        }
    ],
    "sg:phone":"+44 1332 524400",
    "sg:postcode":"DE24 8HX",
    "sg:province":"Derbyshire",
    "sg:tags":[
        "wooden",
        "seal"
    ],
    "wof:name":"Dichtomatik Ltd.",
    "wof:placetype":"venue"
},
  "geometry": {"coordinates":[-1.45644,52.916569],"type":"Point"}
}