{
  "type": "Feature",
  "properties": {
    "addr:full":"Dominion House Harding Way, Somersham Rd Huntingdon Cambridgeshire PE17 4WR",
    "addr:postcode":"pe17 4wr",
    "addr:street":"Harding Way Somersham Rd",
    "iso:country":"GB",
    "sg:address":"Dominion House Harding Way, Somersham Rd",
    "sg:city":"Huntingdon",
    "sg:classifiers":[
        {
            "category":"Building & Trades",
            "subcategory":"Equipment Rental",
            "type":"Services"
        }
    ],
    "sg:phone":"+44 1480 467776",
    "sg:postcode":"PE17 4WR",
    "sg:province":"Cambridgeshire",
    "sg:tags":[
        "plant",
        "machinery"
    ],
    "wof:name":"Dom-Hire",
    "wof:placetype":"venue"
},
  "geometry": {"coordinates":[-0.1893,52.33514],"type":"Point"}
}