{
  "type": "Feature",
  "properties": {
    "iso:country":"GB",
    "sg:address":"Marlborough Court, West Bridgford",
    "sg:city":"Nottingham",
    "sg:classifiers":[
        {
            "category":"Health Services",
            "subcategory":"Nursing And Care Facility",
            "type":"Services"
        },
        {
            "category":"Social Services",
            "subcategory":"Adult Care",
            "type":"Services"
        }
    ],
    "sg:phone":"+44 115 945 5529",
    "sg:postcode":"NG2 6BY",
    "sg:province":"Nottinghamshire",
    "sg:tags":[
        "home",
        "housing",
        "sheltered"
    ],
    "wof:name":"Longhurst Housing Association Ltd.",
    "wof:placetype":"venue"
},
  "geometry": {"coordinates":[-1.1312710047,52.9294548035],"type":"Point"}
}