{
  "type": "Feature",
  "properties": {
    "iso:country":"GB",
    "sg:address":"Po Box 53",
    "sg:city":"Burnley",
    "sg:classifiers":[
        {
            "category":"Retail",
            "subcategory":"Storage",
            "type":"Services"
        }
    ],
    "sg:phone":"+44 1282 424324",
    "sg:postcode":"BB12 8AY",
    "sg:province":"Lancashire",
    "sg:tags":[
        "household",
        "removal"
    ],
    "wof:name":"A Spence Removals",
    "wof:placetype":"venue"
},
  "geometry": {"coordinates":[-2.3033690453,53.7970199585],"type":"Point"}
}