{
  "type": "Feature",
  "properties": {
    "addr:full":"Broadlands Blean Canterbury Kent CT2 9JJ",
    "addr:postcode":"ct2 9jj",
    "addr:street":"Blean",
    "iso:country":"GB",
    "sg:address":"Broadlands Blean",
    "sg:city":"Canterbury",
    "sg:classifiers":[
        {
            "category":"Building & Trades",
            "subcategory":"Construction",
            "type":"Services"
        }
    ],
    "sg:phone":"+44 1227 471206",
    "sg:postcode":"CT2 9JJ",
    "sg:province":"Kent",
    "sg:tags":[
        "builder"
    ],
    "wof:name":"S T Abbott Ltd.",
    "wof:placetype":"venue"
},
  "geometry": {"coordinates":[1.0420769453,51.3078918457],"type":"Point"}
}