{
  "type": "Feature",
  "properties": {
    "iso:country":"GB",
    "sg:address":"Park House Farm, North Street, Flixton",
    "sg:city":"Scarborough",
    "sg:classifiers":[
        {
            "category":"Farming",
            "subcategory":"Dairy Farm",
            "type":"Manufacturing & Wholesale Goods"
        }
    ],
    "sg:phone":"+44 1723 891071",
    "sg:postcode":"YO11 3UA",
    "sg:province":"North Yorkshire",
    "wof:name":"Brian & Joyce Lunn",
    "wof:placetype":"venue"
},
  "geometry": {"coordinates":[-0.406984,54.201904],"type":"Point"}
}