{
  "type": "Feature",
  "properties": {
    "addr:full":"22 Wickham Road, Lower Earley Reading Berkshire RG6 3TE",
    "addr:housenumber":"22",
    "addr:postcode":"rg6 3te",
    "addr:street":"Wickham Road",
    "iso:country":"GB",
    "sg:address":"22 Wickham Road, Lower Earley",
    "sg:city":"Reading",
    "sg:classifiers":[
        {
            "category":"Building & Trades",
            "subcategory":"Construction",
            "type":"Services"
        }
    ],
    "sg:phone":"+44 118 926 5380",
    "sg:postcode":"RG6 3TE",
    "sg:province":"Berkshire",
    "sg:tags":[
        "joiner",
        "carpenter"
    ],
    "wof:name":"Skillcraft",
    "wof:placetype":"venue"
},
  "geometry": {"coordinates":[-0.904874,51.427559],"type":"Point"}
}