{
  "type": "Feature",
  "properties": {
    "addr:full":"1 Salisbury Road, St Annes Bristol City of Bristol BS4 4EL",
    "addr:housenumber":"1",
    "addr:postcode":"bs4 4el",
    "addr:street":"Salisbury Road St",
    "iso:country":"GB",
    "sg:address":"1 Salisbury Road, St Annes",
    "sg:city":"Bristol",
    "sg:classifiers":[
        {
            "category":"Personal",
            "subcategory":"Beauty Salon",
            "type":"Services"
        }
    ],
    "sg:phone":"+44 117 977 0576",
    "sg:postcode":"BS4 4EL",
    "sg:province":"City of Bristol",
    "sg:tags":[
        "unisex",
        "hairdresser"
    ],
    "wof:name":"Unique",
    "wof:placetype":"venue"
},
  "geometry": {"coordinates":[-2.549724102,51.4474143982],"type":"Point"}
}