{
  "type": "Feature",
  "properties": {
    "iso:country":"GB",
    "sg:address":"2 East Road, Bedfont",
    "sg:city":"Feltham",
    "sg:classifiers":[
        {
            "category":"Home & Garden",
            "subcategory":"Home Furnishings",
            "type":"Retail Goods"
        }
    ],
    "sg:phone":"+44 20 8890 5000",
    "sg:postcode":"TW14 8DQ",
    "sg:province":"Greater London",
    "sg:tags":[
        "awning",
        "canopy",
        "blinds"
    ],
    "wof:name":"Sam Blinds (Uk)",
    "wof:placetype":"venue"
},
  "geometry": {"coordinates":[-0.434026,51.452869],"type":"Point"}
}