{
  "type": "Feature",
  "properties": {
    "iso:country":"GB",
    "sg:address":"8, The Hexagon",
    "sg:city":"Andover",
    "sg:classifiers":[
        {
            "category":"Building & Trades",
            "subcategory":"Construction",
            "type":"Services"
        }
    ],
    "sg:phone":"+44 20 7328 8745",
    "sg:postcode":"SP10 3PR",
    "sg:province":"Hampshire",
    "sg:tags":[
        "builder"
    ],
    "wof:name":"Orchard Construction",
    "wof:placetype":"venue"
},
  "geometry": {"coordinates":[-1.476779,51.206493],"type":"Point"}
}