{
  "type": "Feature",
  "properties": {
    "iso:country":"GB",
    "sg:address":"Admin Wing Lowestoft Hospital, Tennyson Road",
    "sg:city":"Lowestoft",
    "sg:classifiers":[
        {
            "category":"Organizations",
            "subcategory":"Non-profit Organization",
            "type":"Services"
        }
    ],
    "sg:postcode":"NR32 1PT",
    "sg:province":"Suffolk",
    "sg:tags":[
        "organisation",
        "voluntary",
        "charity"
    ],
    "wof:name":"Crossroads Care Attendant Scheme",
    "wof:placetype":"venue"
},
  "geometry": {"coordinates":[1.75332,52.479191],"type":"Point"}
}