{
  "type": "Feature",
  "properties": {
    "addr:full":"17 Wydncliffe View, St Arvans Chepstow Gloucestershire NP16 6ET",
    "addr:housenumber":"17",
    "addr:postcode":"np16 6et",
    "addr:street":"Wydncliffe View St",
    "iso:country":"GB",
    "sg:address":"17 Wydncliffe View, St Arvans",
    "sg:city":"Chepstow",
    "sg:classifiers":[
        {
            "category":"Professional",
            "subcategory":"Business Services",
            "type":"Services"
        },
        {
            "category":"Recreation",
            "subcategory":"Playground",
            "type":"Entertainment"
        }
    ],
    "sg:phone":"+44 1291 624584",
    "sg:postcode":"NP16 6ET",
    "sg:province":"Gloucestershire",
    "sg:tags":[
        "hospitality",
        "corporate"
    ],
    "wof:name":"Wye Valley Leisure",
    "wof:placetype":"venue"
},
  "geometry": {"coordinates":[-2.699972,51.664532],"type":"Point"}
}