{
  "type": "Feature",
  "properties": {
    "addr:full":"C/o R C Jani & Co, Office 6a 1st Floor Wembley Greater London HA9 0HB",
    "addr:housenumber":"6a 1st floor",
    "addr:postcode":"ha9 0hb",
    "addr:street":"C;O;Wembley",
    "iso:country":"GB",
    "sg:address":"C/o R C Jani & Co, Office 6a 1st Floor",
    "sg:city":"Wembley",
    "sg:classifiers":[
        {
            "category":"Communications",
            "type":"Services"
        }
    ],
    "sg:postcode":"HA9 0HB",
    "sg:province":"Greater London",
    "sg:tags":[
        "broadcasting"
    ],
    "wof:name":"Asianet Ltd.",
    "wof:placetype":"venue"
},
  "geometry": {"coordinates":[-0.272879988,51.5560112],"type":"Point"}
}