{
  "type": "Feature",
  "properties": {
    "addr:full":"1a Bushey Rd Hayes Greater London UB3 4AS",
    "addr:housenumber":"1a",
    "addr:postcode":"ub3 4as",
    "addr:street":"Bushey Rd",
    "iso:country":"GB",
    "sg:address":"1a Bushey Rd",
    "sg:city":"Hayes",
    "sg:classifiers":[
        {
            "category":"Health Services",
            "subcategory":"Doctor",
            "type":"Services"
        }
    ],
    "sg:phone":"+44 20 8848 9358",
    "sg:postcode":"UB3 4AS",
    "sg:province":"Greater London",
    "sg:tags":[
        "practitioners"
    ],
    "wof:name":"Depani, J",
    "wof:placetype":"venue"
},
  "geometry": {"coordinates":[-0.4282310009,51.4972801208],"type":"Point"}
}