{
  "type": "Feature",
  "properties": {
    "iso:country":"GB",
    "sg:address":"74 Huddersfield Rd",
    "sg:city":"Huddersfield",
    "sg:classifiers":[
        {
            "category":"Personal",
            "subcategory":"Beauty Salon",
            "type":"Services"
        }
    ],
    "sg:phone":"+44 1484 681394",
    "sg:postcode":"HD7 1AZ",
    "sg:province":"West Yorkshire",
    "wof:name":"Club 21",
    "wof:placetype":"venue"
},
  "geometry": {"coordinates":[-1.692882,53.597496],"type":"Point"}
}