{
  "type": "Feature",
  "properties": {
    "iso:country":"GB",
    "sg:address":"3 New Burlington Street",
    "sg:city":"London",
    "sg:classifiers":[
        {
            "category":"Restaurant",
            "type":"Food & Drink"
        }
    ],
    "sg:phone":"+44 20 7287 1991",
    "sg:postcode":"W1S 2JG",
    "sg:province":"Greater London",
    "sg:tags":[
        "american"
    ],
    "wof:name":"Zazoom",
    "wof:placetype":"venue"
},
  "geometry": {"coordinates":[-0.140028,51.512142],"type":"Point"}
}