{
  "type": "Feature",
  "properties": {
    "iso:country":"GB",
    "sg:address":"4 Hitchen La",
    "sg:city":"Shepton Mallet",
    "sg:classifiers":[
        {
            "category":"Professional",
            "subcategory":"Engineering",
            "type":"Services"
        }
    ],
    "sg:phone":"+44 1749 344330",
    "sg:postcode":"BA4 5TZ",
    "sg:province":"Somerset",
    "sg:tags":[
        "gas",
        "engineer"
    ],
    "wof:name":"Parry D G",
    "wof:placetype":"venue"
},
  "geometry": {"coordinates":[-2.5529139042,51.1877365112],"type":"Point"}
}