{
  "type": "Feature",
  "properties": {
    "iso:country":"GB",
    "sg:address":"Fulwell Rd",
    "sg:city":"Sunderland",
    "sg:classifiers":[
        {
            "category":"Bars & Pubs",
            "type":"Food & Drink"
        }
    ],
    "sg:phone":"+44 191 548 3809",
    "sg:postcode":"SR6 9AD",
    "sg:province":"Tyne and Wear",
    "sg:tags":[
        "pubs",
        "inn"
    ],
    "wof:name":"Blue Bell",
    "wof:placetype":"venue"
},
  "geometry": {"coordinates":[-1.381406,54.929134],"type":"Point"}
}