{
  "type": "Feature",
  "properties": {
    "addr:full":"99a Southwell Road West Mansfield Nottinghamshire NG18 4EX",
    "addr:housenumber":"99a",
    "addr:postcode":"ng18 4ex",
    "addr:street":"Southwell Road West",
    "iso:country":"GB",
    "sg:address":"99a Southwell Road West",
    "sg:city":"Mansfield",
    "sg:classifiers":[
        {
            "category":"Personal",
            "subcategory":"Beauty Salon",
            "type":"Services"
        }
    ],
    "sg:phone":"+44 1623 622853",
    "sg:postcode":"NG18 4EX",
    "sg:province":"Nottinghamshire",
    "sg:tags":[
        "unisex",
        "hairdresser"
    ],
    "wof:name":"Classic Cuts",
    "wof:placetype":"venue"
},
  "geometry": {"coordinates":[-1.1751639843,53.1372718811],"type":"Point"}
}