{
  "type": "Feature",
  "properties": {
    "addr:full":"Penlands Farm, Church Road, Herstmonceux Hailsham East Sussex BN27 1RJ",
    "addr:postcode":"bn27 1rj",
    "addr:street":"Church Road",
    "iso:country":"GB",
    "sg:address":"Penlands Farm, Church Road, Herstmonceux",
    "sg:city":"Hailsham",
    "sg:classifiers":[
        {
            "category":"Farming",
            "subcategory":"Farm",
            "type":"Manufacturing & Wholesale Goods"
        }
    ],
    "sg:phone":"+44 1323 832210",
    "sg:postcode":"BN27 1RJ",
    "sg:province":"East Sussex",
    "sg:tags":[
        "egg",
        "producer"
    ],
    "wof:name":"The Friendly Farmer",
    "wof:placetype":"venue"
},
  "geometry": {"coordinates":[0.2565200031,50.8653831482],"type":"Point"}
}