{
  "type": "Feature",
  "properties": {
    "addr:full":"Armstrong Washington Tyne and Wear NE37 1QW",
    "addr:postcode":"tyne and;ne37 1qw",
    "iso:country":"GB",
    "sg:address":"Armstrong",
    "sg:city":"Washington",
    "sg:classifiers":[
        {
            "category":"Home & Garden",
            "subcategory":"Home Furnishings",
            "type":"Retail Goods"
        }
    ],
    "sg:phone":"+44 191 419 1439",
    "sg:postcode":"NE37 1QW",
    "sg:province":"Tyne and Wear",
    "sg:tags":[
        "furnishers",
        "planner",
        "kitchen"
    ],
    "wof:name":"Moben Kitchens",
    "wof:placetype":"venue"
},
  "geometry": {"coordinates":[-1.54562,54.90963],"type":"Point"}
}