{
  "type": "Feature",
  "properties": {
    "addr:full":"119 Sea Rd, East Preston Littlehampton West Sussex BN16 1NX",
    "addr:housenumber":"119",
    "addr:postcode":"bn16 1nx",
    "addr:street":"Sea Rd",
    "iso:country":"GB",
    "sg:address":"119 Sea Rd, East Preston",
    "sg:city":"Littlehampton",
    "sg:classifiers":[
        {
            "category":"Transit Center",
            "subcategory":"Passenger",
            "type":"Transportation"
        }
    ],
    "sg:postcode":"BN16 1NX",
    "sg:province":"West Sussex",
    "sg:tags":[
        "airport"
    ],
    "wof:name":"Eurosurance Ltd",
    "wof:placetype":"venue"
},
  "geometry": {"coordinates":[-0.4813089967,50.8050460815],"type":"Point"}
}