{
  "type": "Feature",
  "properties": {
    "addr:full":"39 Station Road Hayes Greater London UB3 4BE",
    "addr:housenumber":"39",
    "addr:postcode":"ub3 4be",
    "addr:street":"Station Road",
    "iso:country":"GB",
    "sg:address":"39 Station Road",
    "sg:city":"Hayes",
    "sg:classifiers":[
        {
            "category":"Professional",
            "subcategory":"Employment Agencies",
            "type":"Services"
        }
    ],
    "sg:phone":"+44 20 8573 6272",
    "sg:postcode":"UB3 4BE",
    "sg:province":"Greater London",
    "sg:tags":[
        "consultant"
    ],
    "wof:name":"Reed Employment",
    "wof:placetype":"venue"
},
  "geometry": {"coordinates":[-0.4188970029,51.5060081482],"type":"Point"}
}