{
  "type": "Feature",
  "properties": {
    "addr:full":"64 Fore St Hertford Hertfordshire SG14 1BY",
    "addr:housenumber":"64",
    "addr:postcode":"sg14 1by",
    "addr:street":"Fore St",
    "iso:country":"GB",
    "sg:address":"64 Fore St",
    "sg:city":"Hertford",
    "sg:classifiers":[
        {
            "category":"Manufacturing",
            "subcategory":"Glass & Minerals",
            "type":"Manufacturing & Wholesale Goods"
        }
    ],
    "sg:phone":"+44 1992 558881",
    "sg:postcode":"SG14 1BY",
    "sg:province":"Hertfordshire",
    "sg:tags":[
        "stained",
        "designer"
    ],
    "wof:name":"Stained Glass",
    "wof:placetype":"venue"
},
  "geometry": {"coordinates":[-0.076094,51.796513],"type":"Point"}
}