{
  "type": "Feature",
  "properties": {
    "addr:full":"Colne Health Centre, Market St Colne Lancashire BB8 0LJ",
    "addr:postcode":"bb8 0lj",
    "addr:street":"Centre Market St",
    "iso:country":"GB",
    "sg:address":"Colne Health Centre, Market St",
    "sg:city":"Colne",
    "sg:classifiers":[
        {
            "category":"Health Services",
            "subcategory":"Doctor",
            "type":"Services"
        }
    ],
    "sg:phone":"+44 1282 863509",
    "sg:postcode":"BB8 0LJ",
    "sg:province":"Lancashire",
    "sg:tags":[
        "practitioners"
    ],
    "wof:name":"Sinha, B K",
    "wof:placetype":"venue"
},
  "geometry": {"coordinates":[-2.1703650951,53.8568572998],"type":"Point"}
}