{
  "type": "Feature",
  "properties": {
    "iso:country":"GB",
    "sg:address":"14 Arlington Square",
    "sg:city":"London",
    "sg:classifiers":[
        {
            "category":"Social Services",
            "subcategory":"Retirement Home",
            "type":"Services"
        }
    ],
    "sg:phone":"+44 20 7359 2617",
    "sg:postcode":"N1 7DR",
    "sg:province":"Greater London",
    "sg:tags":[
        "residential",
        "care"
    ],
    "wof:name":"The Arlington Project",
    "wof:placetype":"venue"
},
  "geometry": {"coordinates":[-0.0916690007,51.5353851318],"type":"Point"}
}