{
  "type": "Feature",
  "properties": {
    "iso:country":"GB",
    "sg:address":"166 Lincoln Road",
    "sg:city":"Enfield",
    "sg:classifiers":[
        {
            "category":"Wholesale",
            "subcategory":"Scrap",
            "type":"Manufacturing & Wholesale Goods"
        }
    ],
    "sg:postcode":"EN1 1LN",
    "sg:province":"Greater London",
    "sg:tags":[
        "breaker",
        "dismantlers"
    ],
    "wof:name":"R Clark",
    "wof:placetype":"venue"
},
  "geometry": {"coordinates":[-0.0639579967,51.646320343],"type":"Point"}
}