{
  "type": "Feature",
  "properties": {
    "addr:full":"5 Market Street Brighouse West Yorkshire HD6 1AP",
    "addr:housenumber":"5",
    "addr:postcode":"hd6 1ap",
    "addr:street":"Market Street",
    "iso:country":"GB",
    "sg:address":"5 Market Street",
    "sg:city":"Brighouse",
    "sg:classifiers":[
        {
            "category":"Food & Beverages",
            "subcategory":"Meat & Fish",
            "type":"Retail Goods"
        }
    ],
    "sg:phone":"+44 1484 400686",
    "sg:postcode":"HD6 1AP",
    "sg:province":"West Yorkshire",
    "sg:tags":[
        "butcher"
    ],
    "wof:name":"S Chadwick Quality Butcher",
    "wof:placetype":"venue"
},
  "geometry": {"coordinates":[-1.781064,53.70166],"type":"Point"}
}