{
  "type": "Feature",
  "properties": {
    "iso:country":"GB",
    "sg:address":"36 Stone Lane",
    "sg:city":"Yeovil",
    "sg:classifiers":[
        {
            "category":"Building & Trades",
            "subcategory":"Plumbing",
            "type":"Services"
        }
    ],
    "sg:phone":"+44 1935 471829",
    "sg:postcode":"BA21 4NW",
    "sg:province":"Somerset",
    "sg:tags":[
        "central",
        "installation",
        "system",
        "servicing",
        "heating"
    ],
    "wof:name":"Goodier Heating",
    "wof:placetype":"venue"
},
  "geometry": {"coordinates":[-2.633674,50.958527],"type":"Point"}
}