{
  "type": "Feature",
  "properties": {
    "addr:full":"The Warren, Bramshill Road, Eversley Basingstoke Berkshire RG27 0PR",
    "addr:postcode":"rg27 0pr",
    "addr:street":"Bramshill Road",
    "iso:country":"GB",
    "sg:address":"The Warren, Bramshill Road, Eversley",
    "sg:city":"Basingstoke",
    "sg:classifiers":[
        {
            "category":"Professional",
            "subcategory":"Business Services",
            "type":"Services"
        }
    ],
    "sg:phone":"+44 118 932 4418",
    "sg:postcode":"RG27 0PR",
    "sg:province":"Berkshire",
    "sg:tags":[
        "trade"
    ],
    "wof:name":"BRITISH PHOTOVOLTAIC ASSOCIATION",
    "wof:placetype":"venue"
},
  "geometry": {"coordinates":[-0.923434,51.34528],"type":"Point"}
}