{
  "type": "Feature",
  "properties": {
    "iso:country":"GB",
    "sg:address":"Unit 2 Station Road, Latchford",
    "sg:city":"Warrington",
    "sg:classifiers":[
        {
            "category":"Community Center",
            "subcategory":"Social",
            "type":"Public Place"
        }
    ],
    "sg:phone":"+44 1925 650412",
    "sg:postcode":"WA4 1LB",
    "sg:province":"Cheshire",
    "sg:tags":[
        "furnishers",
        "contract"
    ],
    "wof:name":"M D Hotel Interiors Ltd.",
    "wof:placetype":"venue"
},
  "geometry": {"coordinates":[-2.561479,53.378941],"type":"Point"}
}