{
  "type": "Feature",
  "properties": {
    "iso:country":"GB",
    "sg:address":"10 Grenville Rd",
    "sg:city":"Buckingham",
    "sg:classifiers":[
        {
            "category":"Building & Trades",
            "subcategory":"Construction",
            "type":"Services"
        }
    ],
    "sg:phone":"+44 1280 817313",
    "sg:postcode":"MK18 1LR",
    "sg:province":"Buckinghamshire",
    "sg:tags":[
        "flooring"
    ],
    "wof:name":"Millennium Interiors",
    "wof:placetype":"venue"
},
  "geometry": {"coordinates":[-0.9931160212,52.0029258728],"type":"Point"}
}