{
  "type": "Feature",
  "properties": {
    "addr:full":"Queens House, Queen Street Barnstaple Devon EX32 8TB",
    "addr:postcode":"ex32 8tb",
    "addr:street":"Queen Street",
    "iso:country":"GB",
    "sg:address":"Queens House, Queen Street",
    "sg:city":"Barnstaple",
    "sg:classifiers":[
        {
            "category":"Professional",
            "subcategory":"Lawyer & Legal Services",
            "type":"Services"
        }
    ],
    "sg:phone":"+44 1271 374132",
    "sg:postcode":"EX32 8TB",
    "sg:province":"Devon",
    "sg:tags":[
        "solicitor"
    ],
    "wof:name":"Toller Beattie",
    "wof:placetype":"venue"
},
  "geometry": {"coordinates":[-4.056374073,51.0792312622],"type":"Point"}
}