{
  "type": "Feature",
  "properties": {
    "addr:full":"18 Standpark Road Liverpool Merseyside L16 9JL",
    "addr:housenumber":"18",
    "addr:postcode":"l16 9jl",
    "addr:street":"Standpark Road",
    "iso:country":"GB",
    "sg:address":"18 Standpark Road",
    "sg:city":"Liverpool",
    "sg:classifiers":[
        {
            "category":"Professional",
            "subcategory":"Detective & Security Services",
            "type":"Services"
        }
    ],
    "sg:phone":"+44 151 722 5044",
    "sg:postcode":"L16 9JL",
    "sg:province":"Merseyside",
    "sg:tags":[
        "agency"
    ],
    "wof:name":"John P Clarke",
    "wof:placetype":"venue"
},
  "geometry": {"coordinates":[-2.8878641129,53.3926773071],"type":"Point"}
}