{
  "type": "Feature",
  "properties": {
    "addr:full":"25 Everington Road London Greater London N10 1HT",
    "addr:housenumber":"25",
    "addr:postcode":"n10 1ht",
    "addr:street":"Everington Road",
    "iso:country":"GB",
    "sg:address":"25 Everington Road",
    "sg:city":"London",
    "sg:classifiers":[
        {
            "category":"Home & Garden",
            "subcategory":"Carpets & Floor Coverings",
            "type":"Retail Goods"
        }
    ],
    "sg:postcode":"N10 1HT",
    "sg:province":"Greater London",
    "sg:tags":[
        "cleaner",
        "upholstery"
    ],
    "wof:name":"Greenall Mel Carpet & Upholstery Cleaning",
    "wof:placetype":"venue"
},
  "geometry": {"coordinates":[-0.154331,51.597565],"type":"Point"}
}