{
  "type": "Feature",
  "properties": {
    "iso:country":"GB",
    "sg:address":"Rosemorran, West Hill",
    "sg:city":"Ottery St Mary",
    "sg:classifiers":[
        {
            "category":"Professional",
            "subcategory":"Accounting & Tax Preparation",
            "type":"Services"
        }
    ],
    "sg:phone":"+44 1404 814968",
    "sg:postcode":"EX11 1UX",
    "sg:province":"Devon",
    "sg:tags":[
        "accountant",
        "bookkeeping",
        "primarily",
        "activity"
    ],
    "wof:name":"J P Office Skills",
    "wof:placetype":"venue"
},
  "geometry": {"coordinates":[-3.283026,50.751137],"type":"Point"}
}