{
  "type": "Feature",
  "properties": {
    "addr:full":"53 George Street Ayr South Ayrshire KA8 0BN",
    "addr:housenumber":"53",
    "addr:postcode":"ka8 0bn",
    "addr:street":"George Street",
    "iso:country":"GB",
    "sg:address":"53 George Street",
    "sg:city":"Ayr",
    "sg:classifiers":[
        {
            "category":"Military Area",
            "subcategory":"Air Force Base",
            "type":"Public Place"
        }
    ],
    "sg:postcode":"KA8 0BN",
    "sg:province":"South Ayrshire",
    "sg:tags":[
        "taxi",
        "hire",
        "private"
    ],
    "wof:name":"Gribbens Taxis",
    "wof:placetype":"venue"
},
  "geometry": {"coordinates":[-4.626272,55.465588],"type":"Point"}
}