{
  "type": "Feature",
  "properties": {
    "addr:full":"23 Red Admiral Drive, Abbeymead Gloucester Gloucestershire GL4 5EA",
    "addr:housenumber":"23",
    "addr:postcode":"gl4 5ea",
    "addr:street":"Red Admiral Drive",
    "iso:country":"GB",
    "sg:address":"23 Red Admiral Drive, Abbeymead",
    "sg:city":"Gloucester",
    "sg:classifiers":[
        {
            "category":"Retail",
            "subcategory":"Repair Shop",
            "type":"Services"
        }
    ],
    "sg:postcode":"GL4 5EA",
    "sg:province":"Gloucestershire",
    "sg:tags":[
        "radio",
        "television",
        "video"
    ],
    "wof:name":"The Video Repair House",
    "wof:placetype":"venue"
},
  "geometry": {"coordinates":[-2.1975309849,51.8423347473],"type":"Point"}
}