{
  "type": "Feature",
  "properties": {
    "addr:full":"Drewery Drive Gillingham Kent ME8 0NX",
    "addr:postcode":"me8 0nx",
    "addr:street":"Drewery Drive",
    "iso:country":"GB",
    "sg:address":"Drewery Drive",
    "sg:city":"Gillingham",
    "sg:classifiers":[
        {
            "category":"Place Of Worship",
            "type":"Public Place"
        }
    ],
    "sg:phone":"+44 1634 231451",
    "sg:postcode":"ME8 0NX",
    "sg:province":"Kent",
    "wof:name":"St.Matthews Hall & Community Centre",
    "wof:placetype":"venue"
},
  "geometry": {"coordinates":[0.584385,51.349186],"type":"Point"}
}