{
  "type": "Feature",
  "properties": {
    "addr:full":"Store F, General Market Hall, Mardol Head Shrewsbury Shropshire SY1 1HJ",
    "addr:postcode":"sy1 1hj",
    "addr:street":"Mardol Head",
    "iso:country":"GB",
    "sg:address":"Store F, General Market Hall, Mardol Head",
    "sg:city":"Shrewsbury",
    "sg:classifiers":[
        {
            "category":"Farming",
            "subcategory":"Farm",
            "type":"Manufacturing & Wholesale Goods"
        }
    ],
    "sg:phone":"+44 1743 232410",
    "sg:postcode":"SY1 1HJ",
    "sg:province":"Shropshire",
    "sg:tags":[
        "egg",
        "producer"
    ],
    "wof:name":"G.R & M.J Corbett",
    "wof:placetype":"venue"
},
  "geometry": {"coordinates":[-2.751283884,52.7065658569],"type":"Point"}
}