{
  "type": "Feature",
  "properties": {
    "iso:country":"GB",
    "sg:address":"Potters Bar Nursery, The Ridgeway",
    "sg:city":"Potters Bar",
    "sg:classifiers":[
        {
            "category":"Home & Garden",
            "subcategory":"Garden Supply",
            "type":"Retail Goods"
        },
        {
            "category":"Manufacturing",
            "subcategory":"Building Materials",
            "type":"Manufacturing & Wholesale Goods"
        }
    ],
    "sg:phone":"+44 1707 658444",
    "sg:postcode":"EN6 5QS",
    "sg:province":"Greater London",
    "sg:tags":[
        "merchant",
        "builder",
        "nursery",
        "centre"
    ],
    "wof:name":"Naybur Bros Ltd.",
    "wof:placetype":"venue"
},
  "geometry": {"coordinates":[-0.178424,51.693012],"type":"Point"}
}