{
  "type": "Feature",
  "properties": {
    "iso:country":"GB",
    "sg:address":"Craft House, 206 Legrams Lane, Lidget Green",
    "sg:city":"Bradford",
    "sg:classifiers":[
        {
            "category":"Manufacturing",
            "subcategory":"Signs",
            "type":"Manufacturing & Wholesale Goods"
        }
    ],
    "sg:phone":"+44 1274 571307",
    "sg:postcode":"BD7 2EB",
    "sg:province":"West Yorkshire",
    "sg:tags":[
        "writer"
    ],
    "wof:name":"SIGNS OF CRAFT",
    "wof:placetype":"venue"
},
  "geometry": {"coordinates":[-1.785029,53.789902],"type":"Point"}
}