{
  "type": "Feature",
  "properties": {
    "addr:full":"254 High Street, Batheaston Bath Bath and North East Somerset BA1 7RA",
    "addr:housenumber":"254",
    "addr:postcode":"ba1 7ra",
    "addr:street":"High Street",
    "iso:country":"GB",
    "sg:address":"254 High Street, Batheaston",
    "sg:city":"Bath",
    "sg:classifiers":[
        {
            "category":"Professional",
            "subcategory":"Computer Services",
            "type":"Services"
        }
    ],
    "sg:postcode":"BA1 7RA",
    "sg:province":"Bath and North East Somerset",
    "sg:tags":[
        "system",
        "software"
    ],
    "wof:name":"Time's Knot Ltd",
    "wof:placetype":"venue"
},
  "geometry": {"coordinates":[-2.3219211102,51.4051132202],"type":"Point"}
}