{
  "type": "Feature",
  "properties": {
    "addr:full":"Spinney Lane, Boney Hay Burntwood Staffordshire WS7 8HA",
    "addr:postcode":"ws7 8ha",
    "addr:street":"Spinney Lane",
    "iso:country":"GB",
    "sg:address":"Spinney Lane, Boney Hay",
    "sg:city":"Burntwood",
    "sg:classifiers":[
        {
            "category":"Sports & Exercise",
            "subcategory":"Tennis Court",
            "type":"Entertainment"
        }
    ],
    "sg:postcode":"WS7 8HA",
    "sg:province":"Staffordshire",
    "sg:tags":[
        "squash"
    ],
    "wof:name":"Spinney Squash Club",
    "wof:placetype":"venue"
},
  "geometry": {"coordinates":[-1.9250689745,52.6886787415],"type":"Point"}
}