{
  "type": "Feature",
  "properties": {
    "addr:full":"York House, Valley Court Bradford West Yorkshire BD1 4SP",
    "addr:postcode":"bd1 4sp",
    "addr:street":"Valley Court",
    "iso:country":"GB",
    "sg:address":"York House, Valley Court",
    "sg:city":"Bradford",
    "sg:classifiers":[
        {
            "category":"Professional",
            "subcategory":"Management & Consulting",
            "type":"Services"
        }
    ],
    "sg:postcode":"BD1 4SP",
    "sg:province":"West Yorkshire",
    "sg:tags":[
        "consultant",
        "business"
    ],
    "wof:name":"305 Management Services",
    "wof:placetype":"venue"
},
  "geometry": {"coordinates":[-1.752054,53.799664],"type":"Point"}
}