{
  "type": "Feature",
  "properties": {
    "addr:full":"16 Heeswyk Road Canvey Island Essex SS8 8ET",
    "addr:housenumber":"16",
    "addr:postcode":"ss8 8et",
    "addr:street":"Heeswyk Road",
    "iso:country":"GB",
    "sg:address":"16 Heeswyk Road",
    "sg:city":"Canvey Island",
    "sg:classifiers":[
        {
            "category":"Home & Garden",
            "subcategory":"Carpets & Floor Coverings",
            "type":"Retail Goods"
        }
    ],
    "sg:postcode":"SS8 8ET",
    "sg:province":"Essex",
    "sg:tags":[
        "cleaner",
        "upholstery"
    ],
    "wof:name":"Alliance Carpet & Upholstery Cleaning Services",
    "wof:placetype":"venue"
},
  "geometry": {"coordinates":[0.60242,51.527809],"type":"Point"}
}