{
  "type": "Feature",
  "properties": {
    "iso:country":"GB",
    "sg:address":"Lodge Farm, Cowslip Lane, Mickleham",
    "sg:city":"Dorking",
    "sg:classifiers":[
        {
            "category":"Building & Trades",
            "subcategory":"Construction",
            "type":"Services"
        }
    ],
    "sg:phone":"+44 1372 375358",
    "sg:postcode":"RH5 6ET",
    "sg:province":"Surrey",
    "sg:tags":[
        "roofing",
        "contracting"
    ],
    "wof:name":"James Kinloch",
    "wof:placetype":"venue"
},
  "geometry": {"coordinates":[-0.323827,51.268349],"type":"Point"}
}