{
  "type": "Feature",
  "properties": {
    "addr:full":"79 High Street Marlow Berkshire SL7 1AB",
    "addr:housenumber":"79",
    "addr:postcode":"sl7 1ab",
    "addr:street":"High Street",
    "iso:country":"GB",
    "sg:address":"79 High Street",
    "sg:city":"Marlow",
    "sg:classifiers":[
        {
            "category":"Home & Garden",
            "subcategory":"Kitchen Supply",
            "type":"Retail Goods"
        }
    ],
    "sg:phone":"+44 1628 472838",
    "sg:postcode":"SL7 1AB",
    "sg:province":"Berkshire",
    "sg:tags":[
        "glassware",
        "china"
    ],
    "wof:name":"Henry Jones (China & Glass) Ltd.",
    "wof:placetype":"venue"
},
  "geometry": {"coordinates":[-0.7745479941,51.5698165894],"type":"Point"}
}