{
  "type": "Feature",
  "properties": {
    "iso:country":"GB",
    "sg:address":"88 High Street, Walkern",
    "sg:city":"Stevenage",
    "sg:classifiers":[
        {
            "category":"Home & Garden",
            "subcategory":"Building Materials",
            "type":"Retail Goods"
        }
    ],
    "sg:phone":"+44 1438 355489",
    "sg:postcode":"SG2 7PG",
    "sg:province":"Hertfordshire",
    "sg:tags":[
        "fencing"
    ],
    "wof:name":"P J Fencing & Landscapes",
    "wof:placetype":"venue"
},
  "geometry": {"coordinates":[-0.127273,51.920074],"type":"Point"}
}