{
  "type": "Feature",
  "properties": {
    "addr:full":"68 Myddleton La Warrington Cheshire WA2 8NJ",
    "addr:housenumber":"68",
    "addr:postcode":"wa2 8nj",
    "addr:street":"Myddleton La Warrington Cheshire",
    "iso:country":"GB",
    "sg:address":"68 Myddleton La",
    "sg:city":"Warrington",
    "sg:classifiers":[
        {
            "category":"Building & Trades",
            "subcategory":"Construction",
            "type":"Services"
        }
    ],
    "sg:phone":"+44 1925 639640",
    "sg:postcode":"WA2 8NJ",
    "sg:province":"Cheshire",
    "sg:tags":[
        "glazier"
    ],
    "wof:name":"Llewellyn Joinery Services",
    "wof:placetype":"venue"
},
  "geometry": {"coordinates":[-2.591357,53.431629],"type":"Point"}
}