{
  "type": "Feature",
  "properties": {
    "addr:full":"28 Cambridge Rd, Granby Ind Est Weymouth Dorset DT4 9TJ",
    "addr:housenumber":"28",
    "addr:postcode":"dt4 9tj",
    "addr:street":"Cambridge Rd",
    "iso:country":"GB",
    "sg:address":"28 Cambridge Rd, Granby Ind Est",
    "sg:city":"Weymouth",
    "sg:classifiers":[
        {
            "category":"Building & Trades",
            "subcategory":"Construction",
            "type":"Services"
        }
    ],
    "sg:postcode":"DT4 9TJ",
    "sg:province":"Dorset",
    "sg:tags":[
        "builder"
    ],
    "wof:name":"Taylor,W, & Co Ltd",
    "wof:placetype":"venue"
},
  "geometry": {"coordinates":[-2.491839,50.615498],"type":"Point"}
}