{
  "type": "Feature",
  "properties": {
    "addr:full":"271 Green Lane, Seven Kings Ilford Essex IG3 9TN",
    "addr:housenumber":"271",
    "addr:postcode":"ig3 9tn",
    "addr:street":"Green Lane",
    "iso:country":"GB",
    "sg:address":"271 Green Lane, Seven Kings",
    "sg:city":"Ilford",
    "sg:classifiers":[
        {
            "category":"Bars & Pubs",
            "type":"Food & Drink"
        }
    ],
    "sg:phone":"+44 20 8599 4181",
    "sg:postcode":"IG3 9TN",
    "sg:province":"Essex",
    "sg:tags":[
        "pubs",
        "inn"
    ],
    "wof:name":"The Ashgrove",
    "wof:placetype":"venue"
},
  "geometry": {"coordinates":[0.095499,51.560413],"type":"Point"}
}