{
  "type": "Feature",
  "properties": {
    "addr:full":"265 Deane Church La Bolton Lancashire BL3 4ES",
    "addr:housenumber":"265",
    "addr:postcode":"bl3 4es",
    "addr:street":"Deane Church La Bolton",
    "iso:country":"GB",
    "sg:address":"265 Deane Church La",
    "sg:city":"Bolton",
    "sg:classifiers":[
        {
            "category":"Food & Beverages",
            "subcategory":"Bakery",
            "type":"Retail Goods"
        }
    ],
    "sg:postcode":"BL3 4ES",
    "sg:province":"Lancashire",
    "sg:tags":[
        "baker"
    ],
    "wof:name":"Moxon,C T,",
    "wof:placetype":"venue"
},
  "geometry": {"coordinates":[-2.4599831104,53.5661010742],"type":"Point"}
}