{
  "type": "Feature",
  "properties": {
    "addr:full":"47 Southgate Street Winchester Hampshire SO23 9EH",
    "addr:housenumber":"47",
    "addr:postcode":"so23 9eh",
    "addr:street":"Southgate Street",
    "iso:country":"GB",
    "sg:address":"47 Southgate Street",
    "sg:city":"Winchester",
    "sg:classifiers":[
        {
            "category":"Real Estate",
            "subcategory":"Architect",
            "type":"Services"
        }
    ],
    "sg:phone":"+44 1962 841032",
    "sg:postcode":"SO23 9EH",
    "sg:province":"Hampshire",
    "wof:name":"Temple Knott Lewis",
    "wof:placetype":"venue"
},
  "geometry": {"coordinates":[-1.317996,51.060684],"type":"Point"}
}