{
  "type": "Feature",
  "properties": {
    "iso:country":"GB",
    "sg:address":"16 Stafford Street",
    "sg:city":"Bristol",
    "sg:classifiers":[
        {
            "category":"Retail",
            "subcategory":"Auto Repair",
            "type":"Services"
        }
    ],
    "sg:postcode":"BS3 4DA",
    "sg:province":"City of Bristol",
    "sg:tags":[
        "modification",
        "garage"
    ],
    "wof:name":"Stratford Street Garage",
    "wof:placetype":"venue"
},
  "geometry": {"coordinates":[-2.5962190628,51.4407920837],"type":"Point"}
}