{
  "type": "Feature",
  "properties": {
    "addr:full":"11 West Square Scarborough North Yorkshire YO11 1TW",
    "addr:housenumber":"11",
    "addr:postcode":"yo11 1tw",
    "addr:street":"West Square",
    "iso:country":"GB",
    "sg:address":"11 West Square",
    "sg:city":"Scarborough",
    "sg:classifiers":[
        {
            "category":"Travel",
            "subcategory":"Hotels & Motels",
            "type":"Entertainment"
        }
    ],
    "sg:phone":"+44 1723 364963",
    "sg:postcode":"YO11 1TW",
    "sg:province":"North Yorkshire",
    "sg:tags":[
        "house",
        "guest"
    ],
    "wof:name":"Ascot Guest House",
    "wof:placetype":"venue"
},
  "geometry": {"coordinates":[-0.406783,54.280396],"type":"Point"}
}