{
  "type": "Feature",
  "properties": {
    "addr:full":"20 Market Place Barton-upon-humber Lincolnshire DN18 5DA",
    "addr:housenumber":"20",
    "addr:postcode":"dn18 5da",
    "addr:street":"Market Place",
    "iso:country":"GB",
    "sg:address":"20 Market Place",
    "sg:city":"Barton-upon-humber",
    "sg:classifiers":[
        {
            "category":"Fast Food",
            "type":"Food & Drink"
        }
    ],
    "sg:phone":"+44 1652 636100",
    "sg:postcode":"DN18 5DA",
    "sg:province":"Lincolnshire",
    "sg:tags":[
        "away",
        "meal",
        "outlet",
        "take"
    ],
    "wof:name":"Mama Mia",
    "wof:placetype":"venue"
},
  "geometry": {"coordinates":[-0.4392240047,53.6827507019],"type":"Point"}
}