{
  "type": "Feature",
  "properties": {
    "addr:full":"1 Grove Terrace Stockton-on-tees Durham TS20 2HN",
    "addr:housenumber":"1",
    "addr:postcode":"ts20 2hn",
    "addr:street":"Grove Terrace",
    "iso:country":"GB",
    "sg:address":"1 Grove Terrace",
    "sg:city":"Stockton-on-tees",
    "sg:classifiers":[
        {
            "category":"Building & Trades",
            "subcategory":"Construction",
            "type":"Services"
        }
    ],
    "sg:phone":"+44 1642 534546",
    "sg:postcode":"TS20 2HN",
    "sg:province":"Durham",
    "sg:tags":[
        "decorator",
        "painter"
    ],
    "wof:name":"Peter Green Decor",
    "wof:placetype":"venue"
},
  "geometry": {"coordinates":[-1.31092,54.57954],"type":"Point"}
}