{
  "type": "Feature",
  "properties": {
    "addr:full":"Woodside Lodge Beith North Ayrshire KA15 2HZ",
    "addr:postcode":"ka15 2hz",
    "addr:street":"Beith",
    "iso:country":"GB",
    "sg:address":"Woodside Lodge",
    "sg:city":"Beith",
    "sg:classifiers":[
        {
            "category":"Shopping",
            "subcategory":"Catalog Store",
            "type":"Retail Goods"
        }
    ],
    "sg:postcode":"KA15 2HZ",
    "sg:province":"North Ayrshire",
    "sg:tags":[
        "mail",
        "order"
    ],
    "wof:name":"Court,Christopher,",
    "wof:placetype":"venue"
},
  "geometry": {"coordinates":[-4.633949,55.754448],"type":"Point"}
}