{
  "type": "Feature",
  "properties": {
    "iso:country":"GB",
    "sg:address":"Greenhills, Kilbride",
    "sg:city":"Glasgow",
    "sg:classifiers":[
        {
            "category":"Food & Beverages",
            "subcategory":"Supermarket",
            "type":"Retail Goods"
        }
    ],
    "sg:phone":"+44 1355 266446",
    "sg:postcode":"G75 8TU",
    "sg:province":"South Lanarkshire",
    "wof:name":"Shoppers Paradise (U K) Ltd",
    "wof:placetype":"venue"
},
  "geometry": {"coordinates":[-4.205849,55.745129],"type":"Point"}
}