{
  "type": "Feature",
  "properties": {
    "addr:full":"47 Bethel Road Sevenoaks Kent TN13 3UE",
    "addr:housenumber":"47",
    "addr:postcode":"tn13 3ue",
    "addr:street":"Bethel Road",
    "iso:country":"GB",
    "sg:address":"47 Bethel Road",
    "sg:city":"Sevenoaks",
    "sg:classifiers":[
        {
            "category":"Bars & Pubs",
            "type":"Food & Drink"
        }
    ],
    "sg:postcode":"TN13 3UE",
    "sg:province":"Kent",
    "sg:tags":[
        "pubs",
        "inn"
    ],
    "wof:name":"Camden Arms",
    "wof:placetype":"venue"
},
  "geometry": {"coordinates":[0.1969629973,51.2817726135],"type":"Point"}
}