{
  "type": "Feature",
  "properties": {
    "iso:country":"GB",
    "sg:address":"The Tye, Alfriston",
    "sg:city":"Polegate",
    "sg:classifiers":[
        {
            "category":"Landmark",
            "subcategory":"Tourist Attraction",
            "type":"Public Place"
        }
    ],
    "sg:phone":"+44 1323 870001",
    "sg:postcode":"BN26 5TL",
    "sg:province":"East Sussex",
    "sg:tags":[
        "interest"
    ],
    "wof:name":"National Trust (The)",
    "wof:placetype":"venue"
},
  "geometry": {"coordinates":[0.15672,50.808384],"type":"Point"}
}