{
  "type": "Feature",
  "properties": {
    "addr:full":"14 Park St, Rhosddu Wrexham Wrexham LL11 2NN",
    "addr:housenumber":"14",
    "addr:postcode":"ll11 2nn",
    "addr:street":"Park St",
    "iso:country":"GB",
    "sg:address":"14 Park St, Rhosddu",
    "sg:city":"Wrexham",
    "sg:classifiers":[
        {
            "category":"Building & Trades",
            "subcategory":"Construction",
            "type":"Services"
        }
    ],
    "sg:postcode":"LL11 2NN",
    "sg:province":"Wrexham",
    "sg:tags":[
        "roofing"
    ],
    "wof:name":"Jones,Martin,",
    "wof:placetype":"venue"
},
  "geometry": {"coordinates":[-2.9969389439,53.0544090271],"type":"Point"}
}