{
  "type": "Feature",
  "properties": {
    "addr:full":"Unit 5 Windmill Farm Business Centre, Bartley St Bristol City of Bristol BS3 4DB",
    "addr:housenumber":"unit 5",
    "addr:postcode":"bs3 4db",
    "addr:street":"Windmill Farm;Bartley St",
    "iso:country":"GB",
    "sg:address":"Unit 5 Windmill Farm Business Centre, Bartley St",
    "sg:city":"Bristol",
    "sg:classifiers":[
        {
            "category":"Retail",
            "subcategory":"Auto Repair",
            "type":"Services"
        }
    ],
    "sg:phone":"+44 117 953 7611",
    "sg:postcode":"BS3 4DB",
    "sg:province":"City of Bristol",
    "sg:tags":[
        "modification",
        "garage"
    ],
    "wof:name":"Riverside Autos",
    "wof:placetype":"venue"
},
  "geometry": {"coordinates":[-2.5946519375,51.4422912598],"type":"Point"}
}