{
  "type": "Feature",
  "properties": {
    "addr:full":"86-88 Wingrove Road, Fenham Newcastle-upon-tyne Tyne and Wear NE4 9BR",
    "addr:housenumber":"86-88",
    "addr:postcode":"ne4 9br",
    "addr:street":"Wingrove Road",
    "iso:country":"GB",
    "sg:address":"86-88 Wingrove Road, Fenham",
    "sg:city":"Newcastle-upon-tyne",
    "sg:classifiers":[
        {
            "category":"Organizations",
            "subcategory":"Community Association",
            "type":"Services"
        }
    ],
    "sg:phone":"+44 191 273 1191",
    "sg:postcode":"NE4 9BR",
    "sg:province":"Tyne and Wear",
    "sg:tags":[
        "society",
        "housing"
    ],
    "wof:name":"Abbeyfield Newcastle upon Tune Society L",
    "wof:placetype":"venue"
},
  "geometry": {"coordinates":[-1.6473020315,54.9776382446],"type":"Point"}
}