{
  "type": "Feature",
  "properties": {
    "addr:full":"27-28 Victoria Street Burton On Trent Derbyshire DE14 2LP",
    "addr:housenumber":"27-28",
    "addr:postcode":"de14 2lp",
    "addr:street":"Victoria Street",
    "iso:country":"GB",
    "sg:address":"27-28 Victoria Street",
    "sg:city":"Burton On Trent",
    "sg:classifiers":[
        {
            "category":"Bars & Pubs",
            "type":"Food & Drink"
        }
    ],
    "sg:phone":"+44 1283 568118",
    "sg:postcode":"DE14 2LP",
    "sg:province":"Derbyshire",
    "sg:tags":[
        "pubs",
        "inn"
    ],
    "wof:name":"A Leese",
    "wof:placetype":"venue"
},
  "geometry": {"coordinates":[-1.6413949728,52.8108558655],"type":"Point"}
}