{
  "type": "Feature",
  "properties": {
    "iso:country":"GB",
    "sg:address":"Pitreavie Business Park, Queensferry Road",
    "sg:city":"Dunfermline",
    "sg:classifiers":[
        {
            "category":"Communications",
            "subcategory":"Newspaper",
            "type":"Services"
        }
    ],
    "sg:phone":"+44 1383 728201",
    "sg:postcode":"KY11 8QS",
    "sg:province":"Fife",
    "sg:tags":[
        "magazine"
    ],
    "wof:name":"Dunfermline Press & West of Fife Advertiser",
    "wof:placetype":"venue"
},
  "geometry": {"coordinates":[-3.4426500797,56.055721283],"type":"Point"}
}