{
  "type": "Feature",
  "properties": {
    "addr:full":"1 Sandridge Road St Albans Hertfordshire AL1 4AB",
    "addr:housenumber":"1",
    "addr:postcode":"al1 4ab",
    "addr:street":"Sandridge Road",
    "iso:country":"GB",
    "sg:address":"1 Sandridge Road",
    "sg:city":"St Albans",
    "sg:classifiers":[
        {
            "category":"Social Services",
            "subcategory":"Retirement Home",
            "type":"Services"
        }
    ],
    "sg:postcode":"AL1 4AB",
    "sg:province":"Hertfordshire",
    "sg:tags":[
        "residential",
        "care"
    ],
    "wof:name":"Sandridge House",
    "wof:placetype":"venue"
},
  "geometry": {"coordinates":[-0.331815,51.758854],"type":"Point"}
}