{
  "type": "Feature",
  "properties": {
    "iso:country":"GB",
    "sg:address":"Flat 4 55 Enys Rd",
    "sg:city":"Eastbourne",
    "sg:classifiers":[
        {
            "category":"Professional",
            "subcategory":"Printing & Photocopies",
            "type":"Services"
        }
    ],
    "sg:phone":"+44 1323 646984",
    "sg:postcode":"BN21 2DN",
    "sg:province":"East Sussex",
    "sg:tags":[
        "printer"
    ],
    "wof:name":"Printing Services",
    "wof:placetype":"venue"
},
  "geometry": {"coordinates":[0.28535,50.766911],"type":"Point"}
}