{
  "type": "Feature",
  "properties": {
    "iso:country":"GB",
    "sg:address":"Glyndebourne Farm",
    "sg:city":"Lewes",
    "sg:classifiers":[
        {
            "category":"Farming",
            "subcategory":"Livestock Farm",
            "type":"Manufacturing & Wholesale Goods"
        }
    ],
    "sg:phone":"+44 1273 812391",
    "sg:postcode":"BN8 6SH",
    "sg:province":"East Sussex",
    "sg:tags":[
        "others"
    ],
    "wof:name":"R D Brickell",
    "wof:placetype":"venue"
},
  "geometry": {"coordinates":[0.0663499981,50.8738899231],"type":"Point"}
}