{
  "type": "Feature",
  "properties": {
    "addr:full":"London Representative Office, 6th Floor Cornhill London Greater London EC3V 3ND",
    "addr:housenumber":"6th floor",
    "addr:postcode":"ec3v 3nd",
    "addr:street":"Cornhill",
    "iso:country":"GB",
    "sg:address":"London Representative Office, 6th Floor Cornhill",
    "sg:city":"London",
    "sg:classifiers":[
        {
            "category":"Banks & Credit Unions",
            "subcategory":"Bank",
            "type":"Services"
        }
    ],
    "sg:phone":"+44 20 7220 7871",
    "sg:postcode":"EC3V 3ND",
    "sg:province":"Greater London",
    "wof:name":"China Construction Bank",
    "wof:placetype":"venue"
},
  "geometry": {"coordinates":[-0.0868199989,51.513168335],"type":"Point"}
}