{
  "type": "Feature",
  "properties": {
    "addr:full":"1 Crockers Place, The Street, Cobham Gravesend Kent DA12 3BZ",
    "addr:housenumber":"1",
    "addr:postcode":"da12 3bz",
    "addr:street":"Crockers Place The Street",
    "iso:country":"GB",
    "sg:address":"1 Crockers Place, The Street, Cobham",
    "sg:city":"Gravesend",
    "sg:classifiers":[
        {
            "category":"Health Services",
            "subcategory":"Clinic",
            "type":"Services"
        }
    ],
    "sg:phone":"+44 1474 814462",
    "sg:postcode":"DA12 3BZ",
    "sg:province":"Kent",
    "sg:tags":[
        "aromatherapy"
    ],
    "wof:name":"Hargreaves Jacqueline",
    "wof:placetype":"venue"
},
  "geometry": {"coordinates":[0.3992320001,51.3903617859],"type":"Point"}
}