{
  "type": "Feature",
  "properties": {
    "iso:country":"GB",
    "sg:address":"4 Far Rye",
    "sg:city":"Nottingham",
    "sg:classifiers":[
        {
            "category":"Professional",
            "subcategory":"Engineering",
            "type":"Services"
        },
        {
            "category":"Building & Trades",
            "subcategory":"Electrical",
            "type":"Services"
        }
    ],
    "sg:phone":"+44 115 928 3951",
    "sg:postcode":"NG8 1GJ",
    "sg:province":"Nottinghamshire",
    "sg:tags":[
        "engineer",
        "electrician",
        "contractor"
    ],
    "wof:name":"Jackson Electrical Engineering",
    "wof:placetype":"venue"
},
  "geometry": {"coordinates":[-1.2161860466,52.9599075317],"type":"Point"}
}