{
  "type": "Feature",
  "properties": {
    "addr:full":"The Auction Mart, Appleby Road Kendal Cumbria LA9 6ES",
    "addr:postcode":"la9 6es",
    "addr:street":"Appleby Road",
    "iso:country":"GB",
    "sg:address":"The Auction Mart, Appleby Road",
    "sg:city":"Kendal",
    "sg:classifiers":[
        {
            "category":"Professional",
            "type":"Services"
        },
        {
            "category":"Shopping",
            "subcategory":"Computers & Home Electronics",
            "type":"Retail Goods"
        },
        {
            "category":"Insurance",
            "subcategory":"Insurance Agent",
            "type":"Services"
        }
    ],
    "sg:phone":"+44 1539 720603",
    "sg:postcode":"LA9 6ES",
    "sg:province":"Cumbria",
    "sg:tags":[
        "radio",
        "television",
        "aerial",
        "broker",
        "auctioneer"
    ],
    "wof:name":"The Kendal & District Auction Mart Plc",
    "wof:placetype":"venue"
},
  "geometry": {"coordinates":[-2.7480840683,54.3240013123],"type":"Point"}
}