{
  "type": "Feature",
  "properties": {
    "addr:full":"Norwest House, Redwood Lane, Medstead Alton Hampshire GU34 5PE",
    "addr:postcode":"gu34 5pe",
    "addr:street":"Redwood Lane",
    "iso:country":"GB",
    "sg:address":"Norwest House, Redwood Lane, Medstead",
    "sg:city":"Alton",
    "sg:classifiers":[
        {
            "category":"Wholesale",
            "subcategory":"Meat",
            "type":"Manufacturing & Wholesale Goods"
        },
        {
            "category":"Food & Beverages",
            "subcategory":"Meat & Fish",
            "type":"Retail Goods"
        }
    ],
    "sg:phone":"+44 1420 562345",
    "sg:postcode":"GU34 5PE",
    "sg:province":"Hampshire",
    "sg:tags":[
        "-",
        "butcher"
    ],
    "wof:name":"North West Meat Supply Co  Ltd",
    "wof:placetype":"venue"
},
  "geometry": {"coordinates":[-1.0534410477,51.1337203979],"type":"Point"}
}