{
  "type": "Feature",
  "properties": {
    "iso:country":"GB",
    "sg:address":"7 Eastbury Road",
    "sg:city":"London",
    "sg:classifiers":[
        {
            "category":"Real Estate",
            "subcategory":"Real Estate Agent",
            "type":"Services"
        }
    ],
    "sg:phone":"+44 20 7511 8899",
    "sg:postcode":"E6 6LP",
    "sg:province":"Greater London",
    "wof:name":"McDonald Insulation & Maintenance Ltd.",
    "wof:placetype":"venue"
},
  "geometry": {"coordinates":[0.064661,51.518753],"type":"Point"}
}