{
  "type": "Feature",
  "properties": {
    "addr:full":"23a Lodge Lane Grays Essex RM17 5RY",
    "addr:housenumber":"23a",
    "addr:postcode":"rm17 5ry",
    "addr:street":"Lodge Lane",
    "iso:country":"GB",
    "sg:address":"23a Lodge Lane",
    "sg:city":"Grays",
    "sg:classifiers":[
        {
            "category":"Banks & Credit Unions",
            "subcategory":"Financial Services",
            "type":"Services"
        }
    ],
    "sg:phone":"+44 1375 399777",
    "sg:postcode":"RM17 5RY",
    "sg:province":"Essex",
    "sg:tags":[
        "adviser"
    ],
    "wof:name":"Langdon Financial Services Ltd.",
    "wof:placetype":"venue"
},
  "geometry": {"coordinates":[0.340422,51.488922],"type":"Point"}
}