{
  "type": "Feature",
  "properties": {
    "addr:full":"236 Rochdale Rd Oldham Lancashire OL2 6UE",
    "addr:housenumber":"236",
    "addr:postcode":"ol2 6ue",
    "addr:street":"Rochdale Rd",
    "iso:country":"GB",
    "sg:address":"236 Rochdale Rd",
    "sg:city":"Oldham",
    "sg:classifiers":[
        {
            "category":"Professional",
            "subcategory":"Lawyer & Legal Services",
            "type":"Services"
        }
    ],
    "sg:phone":"+44 161 624 3563",
    "sg:postcode":"OL2 6UE",
    "sg:province":"Lancashire",
    "sg:tags":[
        "advice",
        "counselling"
    ],
    "wof:name":"Wellspring Pregnancy Crisis Centre",
    "wof:placetype":"venue"
},
  "geometry": {"coordinates":[-2.124739,53.568901],"type":"Point"}
}