{
  "type": "Feature",
  "properties": {
    "iso:country":"GB",
    "sg:address":"Auchinleck, Logan",
    "sg:city":"Cumnock",
    "sg:classifiers":[
        {
            "category":"Farming",
            "subcategory":"Dairy Farm",
            "type":"Manufacturing & Wholesale Goods"
        }
    ],
    "sg:phone":"+44 1290 420415",
    "sg:postcode":"KA18 3HX",
    "sg:province":"East Ayrshire",
    "wof:name":"William Raphael & Sons",
    "wof:placetype":"venue"
},
  "geometry": {"coordinates":[-4.233433,55.458473],"type":"Point"}
}