{
  "type": "Feature",
  "properties": {
    "addr:full":"2 Eleanors Cross Precinct, 29 High Street North Dunstable Bedfordshire LU6 1HX",
    "addr:housenumber":"2;29",
    "addr:postcode":"lu6 1hx",
    "addr:street":"Eleanors Cross Precinct;High Street North",
    "iso:country":"GB",
    "sg:address":"2 Eleanors Cross Precinct, 29 High Street North",
    "sg:city":"Dunstable",
    "sg:classifiers":[
        {
            "category":"Banks & Credit Unions",
            "subcategory":"Financial Services",
            "type":"Services"
        }
    ],
    "sg:phone":"+44 1582 662274",
    "sg:postcode":"LU6 1HX",
    "sg:province":"Bedfordshire",
    "sg:tags":[
        "consultant"
    ],
    "wof:name":"Provident Personal Credit",
    "wof:placetype":"venue"
},
  "geometry": {"coordinates":[-0.520663023,51.8858032227],"type":"Point"}
}