{
  "type": "Feature",
  "properties": {
    "addr:full":"235 Oakbrook Road Sheffield Derbyshire S11 7EB",
    "addr:housenumber":"235",
    "addr:postcode":"s11 7eb",
    "addr:street":"Oakbrook Road",
    "iso:country":"GB",
    "sg:address":"235 Oakbrook Road",
    "sg:city":"Sheffield",
    "sg:classifiers":[
        {
            "category":"Shopping",
            "subcategory":"Clothing, Apparel, & Fashions",
            "type":"Retail Goods"
        }
    ],
    "sg:phone":"+44 114 230 1111",
    "sg:postcode":"S11 7EB",
    "sg:province":"Derbyshire",
    "sg:tags":[
        "dresswear"
    ],
    "wof:name":"Rich Rags Dress Agency",
    "wof:placetype":"venue"
},
  "geometry": {"coordinates":[-1.5247370005,53.3682365417],"type":"Point"}
}