{
  "type": "Feature",
  "properties": {
    "addr:full":"616 Coventry Road, Small Heath Birmingham West Midlands B10 0UT",
    "addr:housenumber":"616",
    "addr:postcode":"b10 0ut",
    "addr:street":"Coventry Road",
    "iso:country":"GB",
    "sg:address":"616 Coventry Road, Small Heath",
    "sg:city":"Birmingham",
    "sg:classifiers":[
        {
            "category":"Food & Beverages",
            "subcategory":"Candy",
            "type":"Retail Goods"
        }
    ],
    "sg:phone":"+44 121 771 3031",
    "sg:postcode":"B10 0UT",
    "sg:province":"West Midlands",
    "sg:tags":[
        "confectioner"
    ],
    "wof:name":"Riaz's Sweets",
    "wof:placetype":"venue"
},
  "geometry": {"coordinates":[-1.852322,52.467701],"type":"Point"}
}