{
  "type": "Feature",
  "properties": {
    "addr:full":"Unit 11 Philadelphia Complex, Philadelphia Houghton-le-spring Durham DH4 4UQ",
    "addr:housenumber":"unit 11;complex;houghton-le-spring",
    "addr:postcode":"dh4 4uq",
    "iso:country":"GB",
    "sg:address":"Unit 11 Philadelphia Complex, Philadelphia",
    "sg:city":"Houghton-le-spring",
    "sg:classifiers":[
        {
            "category":"Retail",
            "subcategory":"Auto Repair",
            "type":"Services"
        }
    ],
    "sg:postcode":"DH4 4UQ",
    "sg:province":"Durham",
    "sg:tags":[
        "body",
        "car"
    ],
    "wof:name":"Philadelphia Coachworks",
    "wof:placetype":"venue"
},
  "geometry": {"coordinates":[-1.47656,54.86652],"type":"Point"}
}