{
  "type": "Feature",
  "properties": {
    "iso:country":"GB",
    "sg:address":"39-41 Nottingham Road",
    "sg:city":"Loughborough",
    "sg:classifiers":[
        {
            "category":"Shopping",
            "subcategory":"Stationery & Office Supplies",
            "type":"Retail Goods"
        },
        {
            "category":"Retail",
            "subcategory":"Repair Shop",
            "type":"Services"
        }
    ],
    "sg:phone":"+44 1509 262490",
    "sg:postcode":"LE11 1ER",
    "sg:province":"Leicestershire",
    "sg:tags":[
        "machine",
        "clock",
        "watch",
        "sale",
        "recording",
        "time"
    ],
    "wof:name":"Martyns Watch & Clock Repairs",
    "wof:placetype":"venue"
},
  "geometry": {"coordinates":[-1.200315,52.774929],"type":"Point"}
}