{
  "type": "Feature",
  "properties": {
    "addr:full":"Vicarage Farm Road Hounslow Greater London TW5 0AG",
    "addr:postcode":"tw5 0ag",
    "addr:street":"Farm Road",
    "iso:country":"GB",
    "sg:address":"Vicarage Farm Road",
    "sg:city":"Hounslow",
    "sg:classifiers":[
        {
            "category":"Education",
            "subcategory":"School",
            "type":"Public Place"
        }
    ],
    "sg:phone":"+44 20 8570 1079",
    "sg:postcode":"TW5 0AG",
    "sg:province":"Greater London",
    "sg:tags":[
        "local",
        "authority"
    ],
    "wof:name":"Springwell Junior School",
    "wof:placetype":"venue"
},
  "geometry": {"coordinates":[-0.3807339966,51.4845314026],"type":"Point"}
}