{
  "type": "Feature",
  "properties": {
    "addr:full":"61a Tuel Lane Sowerby Bridge West Yorkshire HX6 2EL",
    "addr:housenumber":"61a",
    "addr:postcode":"hx6 2el",
    "addr:street":"Tuel Lane",
    "iso:country":"GB",
    "sg:address":"61a Tuel Lane",
    "sg:city":"Sowerby Bridge",
    "sg:classifiers":[
        {
            "category":"Retail",
            "subcategory":"Repair Shop",
            "type":"Services"
        }
    ],
    "sg:postcode":"HX6 2EL",
    "sg:province":"West Yorkshire",
    "sg:tags":[
        "radio",
        "television",
        "video"
    ],
    "wof:name":"C V T V",
    "wof:placetype":"venue"
},
  "geometry": {"coordinates":[-1.9138120413,53.7123527527],"type":"Point"}
}