{
  "type": "Feature",
  "properties": {
    "addr:full":"138 Highgate Kendal Cumbria LA9 4HW",
    "addr:housenumber":"138",
    "addr:postcode":"la9 4hw",
    "addr:street":"Highgate",
    "iso:country":"GB",
    "sg:address":"138 Highgate",
    "sg:city":"Kendal",
    "sg:classifiers":[
        {
            "category":"Home & Garden",
            "subcategory":"Home Furnishings",
            "type":"Retail Goods"
        }
    ],
    "sg:phone":"+44 1539 731699",
    "sg:postcode":"LA9 4HW",
    "sg:province":"Cumbria",
    "sg:tags":[
        "furnishers",
        "planner",
        "kitchen"
    ],
    "wof:name":"Kirkland Kitchens",
    "wof:placetype":"venue"
},
  "geometry": {"coordinates":[-2.7474610806,54.3238792419],"type":"Point"}
}