{
  "type": "Feature",
  "properties": {
    "addr:full":"54 Peckham Rd Camberwell Greater London SE5 8PX",
    "addr:housenumber":"54",
    "addr:postcode":"se5 8px",
    "addr:street":"Peckham Rd",
    "iso:country":"GB",
    "sg:address":"54 Peckham Rd",
    "sg:city":"Camberwell",
    "sg:classifiers":[
        {
            "category":"Professional",
            "subcategory":"Lawyer & Legal Services",
            "type":"Services"
        }
    ],
    "sg:phone":"+44 20 7252 6900",
    "sg:postcode":"SE5 8PX",
    "sg:province":"Greater London",
    "sg:tags":[
        "advice",
        "counselling"
    ],
    "wof:name":"Equinox",
    "wof:placetype":"venue"
},
  "geometry": {"coordinates":[-0.0797329992,51.4738082886],"type":"Point"}
}