{
  "type": "Feature",
  "properties": {
    "addr:full":"Duke Street Sutton Coldfield West Midlands B72 1RJ",
    "addr:postcode":"b72 1rj",
    "addr:street":"Duke Street",
    "iso:country":"GB",
    "sg:address":"Duke Street",
    "sg:city":"Sutton Coldfield",
    "sg:classifiers":[
        {
            "category":"Place Of Worship",
            "type":"Public Place"
        }
    ],
    "sg:phone":"+44 121 355 7319",
    "sg:postcode":"B72 1RJ",
    "sg:province":"West Midlands",
    "wof:name":"Duke Street Chapel",
    "wof:placetype":"venue"
},
  "geometry": {"coordinates":[-1.8247690201,52.5586242676],"type":"Point"}
}