{
  "type": "Feature",
  "properties": {
    "addr:full":"Unit 6b, Prince Edward Drive Immingham Lincolnshire DN40 1QU",
    "addr:housenumber":"unit 6b",
    "addr:postcode":"dn40 1qu",
    "addr:street":"Prince Edward Drive",
    "iso:country":"GB",
    "sg:address":"Unit 6b, Prince Edward Drive",
    "sg:city":"Immingham",
    "sg:classifiers":[
        {
            "category":"Building & Trades",
            "subcategory":"Construction",
            "type":"Services"
        }
    ],
    "sg:phone":"+44 1469 574545",
    "sg:postcode":"DN40 1QU",
    "sg:province":"Lincolnshire",
    "sg:tags":[
        "builder"
    ],
    "wof:name":"Roxton Building Services",
    "wof:placetype":"venue"
},
  "geometry": {"coordinates":[-0.1867280006,53.6165962219],"type":"Point"}
}