{
  "type": "Feature",
  "properties": {
    "addr:full":"Thurston House Peterborough Cambridgeshire PE1 2SN",
    "addr:postcode":"pe1 2sn",
    "iso:country":"GB",
    "sg:address":"Thurston House",
    "sg:city":"Peterborough",
    "sg:classifiers":[
        {
            "category":"Professional",
            "subcategory":"Business Services",
            "type":"Services"
        }
    ],
    "sg:phone":"+44 1733 564167",
    "sg:postcode":"PE1 2SN",
    "sg:province":"Cambridgeshire",
    "sg:tags":[
        "trade"
    ],
    "wof:name":"The Business Club",
    "wof:placetype":"venue"
},
  "geometry": {"coordinates":[-0.2436199933,52.5793495178],"type":"Point"}
}