{
  "type": "Feature",
  "properties": {
    "iso:country":"GB",
    "sg:address":"1 Front Street",
    "sg:city":"Bamburgh",
    "sg:classifiers":[
        {
            "category":"Travel",
            "subcategory":"Hotels & Motels",
            "type":"Entertainment"
        }
    ],
    "sg:phone":"+44 1668 214431",
    "sg:postcode":"NE69 7BP",
    "sg:province":"Northumberland",
    "sg:website":"http://www.victoria.net",
    "wof:name":"Victoria Hotel",
    "wof:placetype":"venue"
},
  "geometry": {"coordinates":[-1.7138589621,55.6079368591],"type":"Point"}
}