{
  "type": "Feature",
  "properties": {
    "addr:full":"15-29 East Clyde Street Helensburgh Argyll and Bute G84 7NY",
    "addr:housenumber":"15-29",
    "addr:postcode":"g84 7ny",
    "addr:street":"East Clyde Street",
    "iso:country":"GB",
    "sg:address":"15-29 East Clyde Street",
    "sg:city":"Helensburgh",
    "sg:classifiers":[
        {
            "category":"Autos & Motor Vehicles",
            "subcategory":"Automobile Sales",
            "type":"Retail Goods"
        }
    ],
    "sg:phone":"+44 1436 678081",
    "sg:postcode":"G84 7NY",
    "sg:province":"Argyll and Bute",
    "sg:tags":[
        "car"
    ],
    "wof:name":"Arnold Clark Automobiles Ltd",
    "wof:placetype":"venue"
},
  "geometry": {"coordinates":[-4.735098,56.003307],"type":"Point"}
}