{
  "type": "Feature",
  "properties": {
    "addr:full":"Britania House, 29 Station Road Kettering Northamptonshire NN15 7HJ",
    "addr:housenumber":"29",
    "addr:postcode":"nn15 7hj",
    "addr:street":"Station Road",
    "iso:country":"GB",
    "sg:address":"Britania House, 29 Station Road",
    "sg:city":"Kettering",
    "sg:classifiers":[
        {
            "category":"Conference Center",
            "type":"Public Place"
        },
        {
            "category":"Professional",
            "subcategory":"Computer Services",
            "type":"Services"
        }
    ],
    "sg:phone":"+44 1536 515855",
    "sg:postcode":"NN15 7HJ",
    "sg:province":"Northamptonshire",
    "sg:tags":[
        "software",
        "system",
        "business",
        "centre"
    ],
    "wof:name":"Principle Management Ltd.",
    "wof:placetype":"venue"
},
  "geometry": {"coordinates":[-0.731234,52.393627],"type":"Point"}
}