{
  "type": "Feature",
  "properties": {
    "addr:full":"2 High Street, Navenby Lincoln Lincolnshire LN5 0EN",
    "addr:housenumber":"2",
    "addr:postcode":"ln5 0en",
    "addr:street":"High Street",
    "iso:country":"GB",
    "sg:address":"2 High Street, Navenby",
    "sg:city":"Lincoln",
    "sg:classifiers":[
        {
            "category":"Utilities",
            "subcategory":"Electric",
            "type":"Services"
        },
        {
            "category":"Home & Garden",
            "subcategory":"Hardware",
            "type":"Retail Goods"
        }
    ],
    "sg:phone":"+44 1522 810050",
    "sg:postcode":"LN5 0EN",
    "sg:province":"Lincolnshire",
    "sg:tags":[
        "equipment",
        "heating",
        "sale"
    ],
    "wof:name":"The Woodstove",
    "wof:placetype":"venue"
},
  "geometry": {"coordinates":[-0.6335229874,53.0732536316],"type":"Point"}
}