{
  "type": "Feature",
  "properties": {
    "iso:country":"GB",
    "sg:address":"73 Whatriggs Road",
    "sg:city":"Kilmarnock",
    "sg:classifiers":[
        {
            "category":"Food & Beverages",
            "subcategory":"Groceries & Convenience Stores",
            "type":"Retail Goods"
        }
    ],
    "sg:phone":"+44 1563 521526",
    "sg:postcode":"KA1 3RB",
    "sg:province":"East Ayrshire",
    "wof:name":"Morning Noon & Night Ltd",
    "wof:placetype":"venue"
},
  "geometry": {"coordinates":[-4.488205,55.592045],"type":"Point"}
}