{
  "type": "Feature",
  "properties": {
    "addr:full":"33 Waterloo Road Northwich Cheshire CW8 1EL",
    "addr:housenumber":"33",
    "addr:postcode":"cw8 1el",
    "addr:street":"Waterloo Road",
    "iso:country":"GB",
    "sg:address":"33 Waterloo Road",
    "sg:city":"Northwich",
    "sg:classifiers":[
        {
            "category":"Building & Trades",
            "subcategory":"Construction",
            "type":"Services"
        }
    ],
    "sg:phone":"+44 1606 333159",
    "sg:postcode":"CW8 1EL",
    "sg:province":"Cheshire",
    "sg:tags":[
        "decorator",
        "painter"
    ],
    "wof:name":"Tony's Painting & Decorating",
    "wof:placetype":"venue"
},
  "geometry": {"coordinates":[-2.51985,53.256931],"type":"Point"}
}