{
  "type": "Feature",
  "properties": {
    "iso:country":"GB",
    "sg:address":"West Works, Cecil Road",
    "sg:city":"Gloucester",
    "sg:classifiers":[
        {
            "category":"Home & Garden",
            "subcategory":"Household Appliances",
            "type":"Retail Goods"
        }
    ],
    "sg:postcode":"GL1 5HQ",
    "sg:province":"Gloucestershire",
    "sg:tags":[
        "electrical"
    ],
    "wof:name":"Hooper Knight & Co.",
    "wof:placetype":"venue"
},
  "geometry": {"coordinates":[-2.249624,51.863811],"type":"Point"}
}