{
  "type": "Feature",
  "properties": {
    "addr:full":"1a Osborne Place, Palmersville Newcastle-upon-tyne Tyne and Wear NE12 9EY",
    "addr:housenumber":"1a",
    "addr:postcode":"ne12 9ey",
    "addr:street":"Osborne Place",
    "iso:country":"GB",
    "sg:address":"1a Osborne Place, Palmersville",
    "sg:city":"Newcastle-upon-tyne",
    "sg:classifiers":[
        {
            "category":"Government",
            "subcategory":"Post Office",
            "type":"Public Place"
        }
    ],
    "sg:phone":"+44 191 268 2642",
    "sg:postcode":"NE12 9EY",
    "sg:province":"Tyne and Wear",
    "wof:name":"Palmersville Post Office",
    "wof:placetype":"venue"
},
  "geometry": {"coordinates":[-1.604152,54.982471],"type":"Point"}
}