{
  "type": "Feature",
  "properties": {
    "addr:full":"Lidgate Crescent, Langthwaite Grange Industrial Estate, South Kirkby Wakefield West Yorkshire WF9 3NR",
    "addr:postcode":"wf9 3nr",
    "addr:street":"Lidgate Crescent Langthwaite Grange Industrial Estate;West",
    "iso:country":"GB",
    "sg:address":"Lidgate Crescent, Langthwaite Grange Industrial Estate, South Kirkby",
    "sg:city":"Wakefield",
    "sg:classifiers":[
        {
            "category":"Utilities",
            "subcategory":"Recycling",
            "type":"Services"
        }
    ],
    "sg:phone":"+44 1977 608020",
    "sg:postcode":"WF9 3NR",
    "sg:province":"West Yorkshire",
    "sg:tags":[
        "waste",
        "processing"
    ],
    "wof:name":"ReUse Collections Ltd. t/a Berryman",
    "wof:placetype":"venue"
},
  "geometry": {"coordinates":[-1.30729,53.592834],"type":"Point"}
}