{
  "type": "Feature",
  "properties": {
    "iso:country":"GB",
    "sg:address":"Bedfont Road",
    "sg:city":"Feltham",
    "sg:classifiers":[
        {
            "category":"Utilities",
            "subcategory":"Refuse",
            "type":"Services"
        }
    ],
    "sg:phone":"+44 1784 251155",
    "sg:postcode":"TW14 8EB",
    "sg:province":"Greater London",
    "sg:tags":[
        "disposal",
        "waste"
    ],
    "wof:name":"T D Haulage Ltd.",
    "wof:placetype":"venue"
},
  "geometry": {"coordinates":[-0.444751,51.448307],"type":"Point"}
}