{
  "type": "Feature",
  "properties": {
    "addr:full":"131 Millgate Selby East Riding of Yorkshire YO8 3LL",
    "addr:housenumber":"131",
    "addr:postcode":"yo8 3ll",
    "addr:street":"Millgate",
    "iso:country":"GB",
    "sg:address":"131 Millgate",
    "sg:city":"Selby",
    "sg:classifiers":[
        {
            "category":"Brewery",
            "type":"Food & Drink"
        }
    ],
    "sg:phone":"+44 1757 702826",
    "sg:postcode":"YO8 3LL",
    "sg:province":"East Riding of Yorkshire",
    "sg:tags":[
        "brewer"
    ],
    "wof:name":"Selby (Middlebrough) Brewery Ltd.",
    "wof:placetype":"venue"
},
  "geometry": {"coordinates":[-1.0710990429,53.787563324],"type":"Point"}
}