{
  "type": "Feature",
  "properties": {
    "iso:country":"GB",
    "sg:address":"Hillend Industrial Park",
    "sg:city":"Dunfermline",
    "sg:classifiers":[
        {
            "category":"Professional",
            "subcategory":"Engineering",
            "type":"Services"
        }
    ],
    "sg:phone":"+44 1383 822131",
    "sg:postcode":"KY11 9JE",
    "sg:province":"Fife",
    "sg:tags":[
        "electronic",
        "engineer"
    ],
    "wof:name":"Elenie Marconi Systems",
    "wof:placetype":"venue"
},
  "geometry": {"coordinates":[-3.371114,56.04221],"type":"Point"}
}