{
  "type": "Feature",
  "properties": {
    "iso:country":"GB",
    "sg:address":"64 Norman Road",
    "sg:city":"St Leonards-on-sea",
    "sg:classifiers":[
        {
            "category":"Professional",
            "subcategory":"Computer Services",
            "type":"Services"
        }
    ],
    "sg:phone":"+44 1424 425111",
    "sg:postcode":"TN38 0EJ",
    "sg:province":"East Sussex",
    "sg:tags":[
        "system",
        "software"
    ],
    "wof:name":"Peer Systems Ltd.",
    "wof:placetype":"venue"
},
  "geometry": {"coordinates":[0.558193,50.851776],"type":"Point"}
}