{
  "type": "Feature",
  "properties": {
    "addr:full":"3b Whittle Avenue, Segensworth West Fareham Hampshire PO15 5SH",
    "addr:housenumber":"3b",
    "addr:postcode":"po15 5sh",
    "addr:street":"Whittle Avenue",
    "iso:country":"GB",
    "sg:address":"3b Whittle Avenue, Segensworth West",
    "sg:city":"Fareham",
    "sg:classifiers":[
        {
            "category":"Home & Garden",
            "subcategory":"Building Materials",
            "type":"Retail Goods"
        },
        {
            "category":"Building & Trades",
            "subcategory":"Construction",
            "type":"Services"
        }
    ],
    "sg:phone":"+44 1489 582588",
    "sg:postcode":"PO15 5SH",
    "sg:province":"Hampshire",
    "sg:tags":[
        "insulation",
        "installers"
    ],
    "wof:name":"Economic Insulations Ltd.",
    "wof:placetype":"venue"
},
  "geometry": {"coordinates":[-1.2595130205,50.8704376221],"type":"Point"}
}