{
  "type": "Feature",
  "properties": {
    "iso:country":"GB",
    "sg:address":"94 Mudeford",
    "sg:city":"Christchurch",
    "sg:classifiers":[
        {
            "category":"Shopping",
            "subcategory":"Pharmacy",
            "type":"Retail Goods"
        }
    ],
    "sg:phone":"+44 1425 272798",
    "sg:postcode":"BH23 4AS",
    "sg:province":"Dorset",
    "sg:tags":[
        "pharmacist",
        "dispensing",
        "chemist"
    ],
    "wof:name":"Mudeford Pharmacy",
    "wof:placetype":"venue"
},
  "geometry": {"coordinates":[-1.7426450253,50.7282829285],"type":"Point"}
}