{
  "type": "Feature",
  "properties": {
    "iso:country":"GB",
    "sg:address":"Thorny Marsh Farm",
    "sg:city":"Castle Cary",
    "sg:classifiers":[
        {
            "category":"Farming",
            "subcategory":"Livestock Farm",
            "type":"Manufacturing & Wholesale Goods"
        }
    ],
    "sg:phone":"+44 1963 240203",
    "sg:postcode":"BA7 7NT",
    "sg:province":"Somerset",
    "sg:tags":[
        "others"
    ],
    "wof:name":"D H & C Bennett",
    "wof:placetype":"venue"
},
  "geometry": {"coordinates":[-2.518086,51.089069],"type":"Point"}
}