{
  "type": "Feature",
  "properties": {
    "iso:country":"GB",
    "sg:address":"58 The Broadway, Cheam",
    "sg:city":"Sutton",
    "sg:classifiers":[
        {
            "category":"Personal",
            "subcategory":"Beauty Salon",
            "type":"Services"
        }
    ],
    "sg:postcode":"SM3 8BD",
    "sg:province":"Surrey",
    "sg:tags":[
        "unisex",
        "hairdresser"
    ],
    "wof:name":"The Hair Co",
    "wof:placetype":"venue"
},
  "geometry": {"coordinates":[-0.216589,51.359222],"type":"Point"}
}