{
  "type": "Feature",
  "properties": {
    "iso:country":"GB",
    "sg:address":"14 Hawthorn Road, Shaw",
    "sg:city":"Newbury",
    "sg:classifiers":[
        {
            "category":"Retail",
            "subcategory":"Repair Shop",
            "type":"Services"
        }
    ],
    "sg:phone":"+44 1635 523132",
    "sg:postcode":"RG14 1LB",
    "sg:province":"Berkshire",
    "sg:tags":[
        "maintenance"
    ],
    "wof:name":"Collins & Co",
    "wof:placetype":"venue"
},
  "geometry": {"coordinates":[-1.321462,51.407001],"type":"Point"}
}