{
  "type": "Feature",
  "properties": {
    "iso:country":"GB",
    "sg:address":"70-72 Fortis Green Road, Muswell Hill",
    "sg:city":"London",
    "sg:classifiers":[
        {
            "category":"Shopping",
            "subcategory":"Books",
            "type":"Retail Goods"
        }
    ],
    "sg:phone":"+44 20 8444 7588",
    "sg:postcode":"N10 3HN",
    "sg:province":"Greater London",
    "sg:tags":[
        "bookseller",
        "retailer"
    ],
    "wof:name":"Muswell Hill Bookshop Ltd.",
    "wof:placetype":"venue"
},
  "geometry": {"coordinates":[-0.146223,51.590179],"type":"Point"}
}