{
  "type": "Feature",
  "properties": {
    "addr:full":"55-57 Church Street Guisborough North Yorkshire TS14 6HG",
    "addr:housenumber":"55-57",
    "addr:postcode":"ts14 6hg",
    "addr:street":"Church Street",
    "iso:country":"GB",
    "sg:address":"55-57 Church Street",
    "sg:city":"Guisborough",
    "sg:classifiers":[
        {
            "category":"Sports & Exercise",
            "subcategory":"Sports Center",
            "type":"Entertainment"
        }
    ],
    "sg:phone":"+44 1287 631001",
    "sg:postcode":"TS14 6HG",
    "sg:province":"North Yorkshire",
    "sg:tags":[
        "shop",
        "good"
    ],
    "wof:name":"Adrenalin",
    "wof:placetype":"venue"
},
  "geometry": {"coordinates":[-1.0497430563,54.5365791321],"type":"Point"}
}