{
  "type": "Feature",
  "properties": {
    "addr:full":"53 Roff Avenue Bedford Bedfordshire MK41 7TJ",
    "addr:housenumber":"53",
    "addr:postcode":"mk41 7tj",
    "addr:street":"Roff Avenue",
    "iso:country":"GB",
    "sg:address":"53 Roff Avenue",
    "sg:city":"Bedford",
    "sg:classifiers":[
        {
            "category":"Shopping",
            "subcategory":"Bicycles & Sporting Goods",
            "type":"Retail Goods"
        }
    ],
    "sg:phone":"+44 1234 353136",
    "sg:postcode":"MK41 7TJ",
    "sg:province":"Bedfordshire",
    "sg:tags":[
        "equipment",
        "camping"
    ],
    "wof:name":"Millar-Tree",
    "wof:placetype":"venue"
},
  "geometry": {"coordinates":[-0.472518,52.143162],"type":"Point"}
}