{
  "type": "Feature",
  "properties": {
    "iso:country":"GB",
    "sg:address":"15 Cromwell Road",
    "sg:city":"Croydon",
    "sg:classifiers":[
        {
            "category":"Home & Garden",
            "subcategory":"Carpets & Floor Coverings",
            "type":"Retail Goods"
        }
    ],
    "sg:phone":"+44 20 8689 3146",
    "sg:postcode":"CR0 2JZ",
    "sg:province":"Surrey",
    "sg:tags":[
        "cleaner",
        "upholstery"
    ],
    "wof:name":"Gooch Fabric Care",
    "wof:placetype":"venue"
},
  "geometry": {"coordinates":[-0.096799,51.384811],"type":"Point"}
}