{
  "type": "Feature",
  "properties": {
    "addr:full":"Ebbor Farm, Wookey Hole Wells Somerset BA5 1AY",
    "addr:postcode":"ba5 1ay",
    "addr:street":"Wookey",
    "iso:country":"GB",
    "sg:address":"Ebbor Farm, Wookey Hole",
    "sg:city":"Wells",
    "sg:classifiers":[
        {
            "category":"Farming",
            "subcategory":"Livestock Farm",
            "type":"Manufacturing & Wholesale Goods"
        }
    ],
    "sg:postcode":"BA5 1AY",
    "sg:province":"Somerset",
    "sg:tags":[
        "others"
    ],
    "wof:name":"W J E M & S J Masters",
    "wof:placetype":"venue"
},
  "geometry": {"coordinates":[-2.670349,51.223667],"type":"Point"}
}