{
  "type": "Feature",
  "properties": {
    "addr:full":"251 Heywood Road, Prestwich Manchester Greater Manchester M25 2QP",
    "addr:housenumber":"251",
    "addr:postcode":"m25 2qp",
    "addr:street":"Heywood Road",
    "iso:country":"GB",
    "sg:address":"251 Heywood Road, Prestwich",
    "sg:city":"Manchester",
    "sg:classifiers":[
        {
            "category":"Food & Beverages",
            "subcategory":"Groceries & Convenience Stores",
            "type":"Retail Goods"
        }
    ],
    "sg:postcode":"M25 2QP",
    "sg:province":"Greater Manchester",
    "wof:name":"One Stop Savers",
    "wof:placetype":"venue"
},
  "geometry": {"coordinates":[-2.2716810703,53.5397911072],"type":"Point"}
}