{
  "type": "Feature",
  "properties": {
    "iso:country":"GB",
    "sg:address":"1 Eddison Place, Dryburgh Indslt Estate",
    "sg:city":"Dundee",
    "sg:classifiers":[
        {
            "category":"Autos & Motor Vehicles",
            "subcategory":"Automobile Sales",
            "type":"Retail Goods"
        }
    ],
    "sg:phone":"+44 1382 812210",
    "sg:postcode":"DD2 3QU",
    "sg:province":"Dundee City",
    "wof:name":"Tayside Commercial Vehicle Builders Ltd.",
    "wof:placetype":"venue"
},
  "geometry": {"coordinates":[-3.0162351131,56.4848175049],"type":"Point"}
}