{
  "type": "Feature",
  "properties": {
    "addr:full":"6 Forest Court, Dorridge Solihull Warwickshire B93 8HN",
    "addr:housenumber":"6",
    "addr:postcode":"b93 8hn",
    "addr:street":"Forest Court",
    "iso:country":"GB",
    "sg:address":"6 Forest Court, Dorridge",
    "sg:city":"Solihull",
    "sg:classifiers":[
        {
            "category":"Shopping",
            "subcategory":"Tobacco",
            "type":"Retail Goods"
        },
        {
            "category":"Shopping",
            "subcategory":"Pets & Pet Supplies",
            "type":"Retail Goods"
        }
    ],
    "sg:phone":"+44 1564 775408",
    "sg:postcode":"B93 8HN",
    "sg:province":"Warwickshire",
    "sg:tags":[
        "tobacconist"
    ],
    "wof:name":"Dixons Pet & Garden Supplies",
    "wof:placetype":"venue"
},
  "geometry": {"coordinates":[-1.7521740198,52.3741493225],"type":"Point"}
}