{
  "type": "Feature",
  "properties": {
    "addr:full":"5 Hesketh Avenue Manchester Greater Manchester M20 2QN",
    "addr:housenumber":"5",
    "addr:postcode":"m20 2qn",
    "addr:street":"Hesketh Avenue",
    "iso:country":"GB",
    "sg:address":"5 Hesketh Avenue",
    "sg:city":"Manchester",
    "sg:classifiers":[
        {
            "category":"Professional",
            "subcategory":"Computer Services",
            "type":"Services"
        }
    ],
    "sg:phone":"+44 161 448 7800",
    "sg:postcode":"M20 2QN",
    "sg:province":"Greater Manchester",
    "sg:tags":[
        "development",
        "web",
        "system",
        "site",
        "design",
        "software"
    ],
    "wof:name":"Inspired It Ltd",
    "wof:placetype":"venue"
},
  "geometry": {"coordinates":[-2.2368350029,53.418838501],"type":"Point"}
}