{
  "type": "Feature",
  "properties": {
    "iso:country":"GB",
    "sg:address":"Foxglove Road",
    "sg:city":"Dudley",
    "sg:classifiers":[
        {
            "category":"Education",
            "subcategory":"School",
            "type":"Public Place"
        },
        {
            "category":"Government",
            "subcategory":"Office",
            "type":"Public Place"
        }
    ],
    "sg:phone":"+44 1384 818515",
    "sg:postcode":"DY1 3NQ",
    "sg:province":"West Midlands",
    "sg:tags":[
        "local",
        "authority"
    ],
    "wof:name":"Wren's Nest Primary School",
    "wof:placetype":"venue"
},
  "geometry": {"coordinates":[-2.099984,52.525696],"type":"Point"}
}