{
  "type": "Feature",
  "properties": {
    "addr:full":"51a St Marys Road Liverpool Merseyside L19 2NJ",
    "addr:housenumber":"51a",
    "addr:postcode":"l19 2nj",
    "addr:street":"St Marys Road",
    "iso:country":"GB",
    "sg:address":"51a St Marys Road",
    "sg:city":"Liverpool",
    "sg:classifiers":[
        {
            "category":"Autos & Motor Vehicles",
            "subcategory":"Automobile Sales",
            "type":"Retail Goods"
        }
    ],
    "sg:postcode":"L19 2NJ",
    "sg:province":"Merseyside",
    "sg:tags":[
        "car"
    ],
    "wof:name":"Bootle Brake & Clutch",
    "wof:placetype":"venue"
},
  "geometry": {"coordinates":[-2.8996319771,53.3542633057],"type":"Point"}
}