{
  "type": "Feature",
  "properties": {
    "addr:full":"Resource Centre, Riby Square Grimsby Lincolnshire DN31 3HA",
    "addr:postcode":"dn31 3ha",
    "addr:street":"Riby Square",
    "iso:country":"GB",
    "sg:address":"Resource Centre, Riby Square",
    "sg:city":"Grimsby",
    "sg:classifiers":[
        {
            "category":"Education",
            "subcategory":"University",
            "type":"Public Place"
        },
        {
            "category":"Government",
            "subcategory":"Office",
            "type":"Public Place"
        }
    ],
    "sg:phone":"+44 1472 324643",
    "sg:postcode":"DN31 3HA",
    "sg:province":"Lincolnshire",
    "sg:tags":[
        "local",
        "adult"
    ],
    "wof:name":"Educational Guidance Service",
    "wof:placetype":"venue"
},
  "geometry": {"coordinates":[-0.0717400014,53.5761985779],"type":"Point"}
}