{
  "type": "Feature",
  "properties": {
    "iso:country":"GB",
    "sg:address":"Bryn Eglwys",
    "sg:city":"Pentraeth",
    "sg:classifiers":[
        {
            "category":"Museum",
            "subcategory":"Art Museum",
            "type":"Entertainment"
        }
    ],
    "sg:postcode":"LL75 8UL",
    "sg:province":"Isle of Anglesey",
    "sg:tags":[
        "gallery"
    ],
    "wof:name":"Stone Science",
    "wof:placetype":"venue"
},
  "geometry": {"coordinates":[-4.2166237831,53.2825965881],"type":"Point"}
}