{
  "type": "Feature",
  "properties": {
    "addr:full":"65 Southway, South West Denton Newcastle-upon-tyne Northumberland NE15 7RB",
    "addr:housenumber":"65",
    "addr:postcode":"ne15 7rb",
    "addr:street":"Southway South",
    "iso:country":"GB",
    "sg:address":"65 Southway, South West Denton",
    "sg:city":"Newcastle-upon-tyne",
    "sg:classifiers":[
        {
            "category":"Shopping",
            "subcategory":"Department Store",
            "type":"Retail Goods"
        },
        {
            "category":"Food & Beverages",
            "subcategory":"Groceries & Convenience Stores",
            "type":"Retail Goods"
        }
    ],
    "sg:phone":"+44 191 267 5448",
    "sg:postcode":"NE15 7RB",
    "sg:province":"Northumberland",
    "wof:name":"Southway Supermarket",
    "wof:placetype":"venue"
},
  "geometry": {"coordinates":[-1.6123689413,54.9779167175],"type":"Point"}
}