{
  "type": "Feature",
  "properties": {
    "iso:country":"GB",
    "sg:address":"16 Truleigh Close",
    "sg:city":"Brighton",
    "sg:classifiers":[
        {
            "category":"Communications",
            "type":"Services"
        }
    ],
    "sg:phone":"+44 1273 390662",
    "sg:postcode":"BN2 6TS",
    "sg:province":"East Sussex",
    "sg:tags":[
        "tv",
        "video",
        "radio"
    ],
    "wof:name":"Rk Electrical Supplies",
    "wof:placetype":"venue"
},
  "geometry": {"coordinates":[-0.0600639991,50.8326416016],"type":"Point"}
}