{
  "type": "Feature",
  "properties": {
    "addr:full":"69 Home Street Edinburgh City of Edinburgh EH3 9JP",
    "addr:housenumber":"69",
    "addr:postcode":"eh3 9jp",
    "addr:street":"Home Street",
    "iso:country":"GB",
    "sg:address":"69 Home Street",
    "sg:city":"Edinburgh",
    "sg:classifiers":[
        {
            "category":"Bars & Pubs",
            "type":"Food & Drink"
        },
        {
            "category":"Bars & Pubs",
            "subcategory":"Wine Bar",
            "type":"Food & Drink"
        }
    ],
    "sg:phone":"+44 131 229 9516",
    "sg:postcode":"EH3 9JP",
    "sg:province":"City of Edinburgh",
    "sg:tags":[
        "pubs",
        "inn"
    ],
    "wof:name":"Thistle Inns Ltd",
    "wof:placetype":"venue"
},
  "geometry": {"coordinates":[-3.2033369541,55.9421424866],"type":"Point"}
}