{
  "type": "Feature",
  "properties": {
    "iso:country":"GB",
    "sg:address":"C P D C, Foster Rd",
    "sg:city":"Cambridge",
    "sg:classifiers":[
        {
            "category":"Government",
            "subcategory":"Office",
            "type":"Public Place"
        }
    ],
    "sg:phone":"+44 1223 566756",
    "sg:postcode":"CB2 2NL",
    "sg:province":"Cambridgeshire",
    "sg:tags":[
        "education",
        "agency",
        "authority"
    ],
    "wof:name":"Education Welfare",
    "wof:placetype":"venue"
},
  "geometry": {"coordinates":[0.127753,52.191158],"type":"Point"}
}