{
  "type": "Feature",
  "properties": {
    "addr:full":"Vikings, Clifford Manor Rd Guildford Surrey GU4 8AG",
    "addr:postcode":"gu4 8ag",
    "addr:street":"Manor Rd",
    "iso:country":"GB",
    "sg:address":"Vikings, Clifford Manor Rd",
    "sg:city":"Guildford",
    "sg:classifiers":[
        {
            "category":"Education",
            "subcategory":"Special Training",
            "type":"Public Place"
        }
    ],
    "sg:phone":"+44 1483 450178",
    "sg:postcode":"GU4 8AG",
    "sg:province":"Surrey",
    "sg:tags":[
        "school",
        "language"
    ],
    "wof:name":"German Naturally",
    "wof:placetype":"venue"
},
  "geometry": {"coordinates":[-0.566365,51.224266],"type":"Point"}
}