{
  "type": "Feature",
  "properties": {
    "addr:full":"Tiptree Medical Centre, Church Rd Colchester Essex CO5 0HB",
    "addr:postcode":"co5 0hb",
    "addr:street":"Church Rd",
    "iso:country":"GB",
    "sg:address":"Tiptree Medical Centre, Church Rd",
    "sg:city":"Colchester",
    "sg:classifiers":[
        {
            "category":"Health Services",
            "subcategory":"Doctor",
            "type":"Services"
        }
    ],
    "sg:phone":"+44 1621 816475",
    "sg:postcode":"CO5 0HB",
    "sg:province":"Essex",
    "sg:tags":[
        "practitioners"
    ],
    "wof:name":"Fowler, P J",
    "wof:placetype":"venue"
},
  "geometry": {"coordinates":[0.7511299849,51.8102302551],"type":"Point"}
}