{
  "type": "Feature",
  "properties": {
    "addr:full":"114 High Street Deal Kent CT14 6BB",
    "addr:housenumber":"114",
    "addr:postcode":"ct14 6bb",
    "addr:street":"High Street Deal",
    "iso:country":"GB",
    "sg:address":"114 High Street",
    "sg:city":"Deal",
    "sg:classifiers":[
        {
            "category":"Fast Food",
            "type":"Food & Drink"
        }
    ],
    "sg:phone":"+44 1304 367707",
    "sg:postcode":"CT14 6BB",
    "sg:province":"Kent",
    "sg:tags":[
        "away",
        "take"
    ],
    "wof:name":"P Nopa",
    "wof:placetype":"venue"
},
  "geometry": {"coordinates":[1.4028149843,51.225894928],"type":"Point"}
}