{
  "type": "Feature",
  "properties": {
    "addr:full":"127 New Union Street Coventry West Midlands CV1 2NT",
    "addr:housenumber":"127",
    "addr:postcode":"cv1 2nt",
    "addr:street":"New Union Street",
    "iso:country":"GB",
    "sg:address":"127 New Union Street",
    "sg:city":"Coventry",
    "sg:classifiers":[
        {
            "category":"Education",
            "subcategory":"Special Training",
            "type":"Public Place"
        }
    ],
    "sg:phone":"+44 24 7622 8884",
    "sg:postcode":"CV1 2NT",
    "sg:province":"West Midlands",
    "sg:tags":[
        "product",
        "centre"
    ],
    "wof:name":"A C T Recruitment & Training",
    "wof:placetype":"venue"
},
  "geometry": {"coordinates":[-1.510512,52.405045],"type":"Point"}
}