{
  "type": "Feature",
  "properties": {
    "iso:country":"GB",
    "sg:address":"36a Friars Stile Road",
    "sg:city":"Richmond",
    "sg:classifiers":[
        {
            "category":"Health Services",
            "subcategory":"Clinic",
            "type":"Services"
        }
    ],
    "sg:phone":"+44 20 8332 2262",
    "sg:postcode":"TW10 6NQ",
    "sg:province":"Greater London",
    "sg:tags":[
        "aromatherapy"
    ],
    "wof:name":"Aroma Secrets",
    "wof:placetype":"venue"
},
  "geometry": {"coordinates":[-0.2971549928,51.4550323486],"type":"Point"}
}