{
  "type": "Feature",
  "properties": {
    "addr:full":"3 Prospect Terrace, Lumphanan Banchory Aberdeen City AB31 4SH",
    "addr:housenumber":"3",
    "addr:postcode":"ab31 4sh",
    "addr:street":"Prospect Terrace",
    "iso:country":"GB",
    "sg:address":"3 Prospect Terrace, Lumphanan",
    "sg:city":"Banchory",
    "sg:classifiers":[
        {
            "category":"Professional",
            "subcategory":"Credit Reporting & Collection",
            "type":"Services"
        }
    ],
    "sg:postcode":"AB31 4SH",
    "sg:province":"Aberdeen City",
    "sg:tags":[
        "collecting",
        "agency"
    ],
    "wof:name":"Connect Financial Services",
    "wof:placetype":"venue"
},
  "geometry": {"coordinates":[-2.689881,57.129574],"type":"Point"}
}