{
  "type": "Feature",
  "properties": {
    "addr:full":"117-121 Bramford La Ipswich Suffolk IP1 4DH",
    "addr:postcode":"117-121;ipswich;ip1 4dh",
    "iso:country":"GB",
    "sg:address":"117-121 Bramford La",
    "sg:city":"Ipswich",
    "sg:classifiers":[
        {
            "category":"Professional",
            "subcategory":"Art Services",
            "type":"Services"
        }
    ],
    "sg:phone":"+44 1473 257595",
    "sg:postcode":"IP1 4DH",
    "sg:province":"Suffolk",
    "sg:tags":[
        "photographer"
    ],
    "wof:name":"Photo-Craft",
    "wof:placetype":"venue"
},
  "geometry": {"coordinates":[1.1345560551,52.0658226013],"type":"Point"}
}