{
  "type": "Feature",
  "properties": {
    "addr:full":"Warwick Way London Greater London SW1V 4JE",
    "addr:postcode":"sw1v 4je",
    "addr:street":"Warwick Way",
    "iso:country":"GB",
    "sg:address":"Warwick Way",
    "sg:city":"London",
    "sg:classifiers":[
        {
            "category":"Parking",
            "type":"Transportation"
        }
    ],
    "sg:phone":"+44 20 7828 4520",
    "sg:postcode":"SW1V 4JE",
    "sg:province":"Greater London",
    "sg:tags":[
        "car",
        "park"
    ],
    "wof:name":"Warwick Way Car Parking",
    "wof:placetype":"venue"
},
  "geometry": {"coordinates":[-0.1445720047,51.4908599854],"type":"Point"}
}