{
  "type": "Feature",
  "properties": {
    "iso:country":"GB",
    "sg:address":"16 Hazelwood Drive",
    "sg:city":"Plymouth",
    "sg:classifiers":[
        {
            "category":"Building & Trades",
            "subcategory":"Construction",
            "type":"Services"
        }
    ],
    "sg:postcode":"PL6 7HL",
    "sg:province":"Devon",
    "sg:tags":[
        "builder"
    ],
    "wof:name":"Newlook Property Services",
    "wof:placetype":"venue"
},
  "geometry": {"coordinates":[-4.104631,50.43494],"type":"Point"}
}