{
  "type": "Feature",
  "properties": {
    "iso:country":"GB",
    "sg:address":"40 Harley St",
    "sg:city":"West End",
    "sg:classifiers":[
        {
            "category":"Health Services",
            "subcategory":"Doctor",
            "type":"Services"
        }
    ],
    "sg:phone":"+44 20 7580 3478",
    "sg:postcode":"W1N 1AB",
    "sg:province":"Hampshire",
    "sg:tags":[
        "practitioners"
    ],
    "wof:name":"Page, E D",
    "wof:placetype":"venue"
},
  "geometry": {"coordinates":[-0.146466,51.518383],"type":"Point"}
}