{
  "type": "Feature",
  "properties": {
    "addr:full":"15 Clarendon Drive Stafford Staffordshire ST17 9UF",
    "addr:housenumber":"15",
    "addr:postcode":"st17 9uf",
    "addr:street":"Clarendon Drive",
    "iso:country":"GB",
    "sg:address":"15 Clarendon Drive",
    "sg:city":"Stafford",
    "sg:classifiers":[
        {
            "category":"Professional",
            "subcategory":"Management & Consulting",
            "type":"Services"
        }
    ],
    "sg:postcode":"ST17 9UF",
    "sg:province":"Staffordshire",
    "sg:tags":[
        "consultant",
        "business"
    ],
    "wof:name":"Up-Data",
    "wof:placetype":"venue"
},
  "geometry": {"coordinates":[-2.14105,52.794449],"type":"Point"}
}