{
  "type": "Feature",
  "properties": {
    "iso:country":"GB",
    "sg:address":"34 Castle Street, Rothesay",
    "sg:city":"Rothesay",
    "sg:classifiers":[
        {
            "category":"Professional",
            "subcategory":"Lawyer & Legal Services",
            "type":"Services"
        }
    ],
    "sg:phone":"+44 1700 503157",
    "sg:postcode":"PA20 9HD",
    "sg:province":"Argyll and Bute",
    "sg:tags":[
        "solicitor"
    ],
    "wof:name":"Macbeth & Maclagan",
    "wof:placetype":"venue"
},
  "geometry": {"coordinates":[-5.051801,55.83609],"type":"Point"}
}