{
  "type": "Feature",
  "properties": {
    "addr:full":"4 Dalrymple Loan Musselburgh City of Edinburgh EH21 7DH",
    "addr:housenumber":"4",
    "addr:postcode":"eh21 7dh",
    "addr:street":"Dalrymple Loan",
    "iso:country":"GB",
    "sg:address":"4 Dalrymple Loan",
    "sg:city":"Musselburgh",
    "sg:classifiers":[
        {
            "category":"Government",
            "subcategory":"Police Station",
            "type":"Public Place"
        }
    ],
    "sg:postcode":"EH21 7DH",
    "sg:province":"City of Edinburgh",
    "sg:tags":[
        "support"
    ],
    "wof:name":"Graham Associates",
    "wof:placetype":"venue"
},
  "geometry": {"coordinates":[-3.0532860756,55.941986084],"type":"Point"}
}