{
  "type": "Feature",
  "properties": {
    "iso:country":"GB",
    "sg:address":"Cemetery Office, Torver Crescent",
    "sg:city":"Sunderland",
    "sg:classifiers":[
        {
            "category":"Retail",
            "subcategory":"Funeral Services",
            "type":"Services"
        },
        {
            "category":"Government",
            "subcategory":"Office",
            "type":"Public Place"
        }
    ],
    "sg:phone":"+44 191 553 5345",
    "sg:postcode":"SR6 8LG",
    "sg:province":"Tyne and Wear",
    "sg:tags":[
        "cemetery",
        "local",
        "crematorium"
    ],
    "wof:name":"Mere Knolls Cemetery",
    "wof:placetype":"venue"
},
  "geometry": {"coordinates":[-1.3839199543,54.935508728],"type":"Point"}
}