{
  "type": "Feature",
  "properties": {
    "addr:full":"53 Shirley Street Hove East Sussex BN3 3WH",
    "addr:housenumber":"53",
    "addr:postcode":"bn3 3wh",
    "addr:street":"Shirley Street",
    "iso:country":"GB",
    "sg:address":"53 Shirley Street",
    "sg:city":"Hove",
    "sg:classifiers":[
        {
            "category":"Fast Food",
            "type":"Food & Drink"
        }
    ],
    "sg:phone":"+44 1273 736110",
    "sg:postcode":"BN3 3WH",
    "sg:province":"East Sussex",
    "sg:tags":[
        "away",
        "take"
    ],
    "wof:name":"Jade Well",
    "wof:placetype":"venue"
},
  "geometry": {"coordinates":[-0.1746409982,50.8332138062],"type":"Point"}
}