{
  "type": "Feature",
  "properties": {
    "iso:country":"GB",
    "sg:address":"Amberley House, Quakers Hill, Mundesley Road",
    "sg:city":"North Walsham",
    "sg:classifiers":[
        {
            "category":"Professional",
            "subcategory":"Management & Consulting",
            "type":"Services"
        }
    ],
    "sg:phone":"+44 1692 404468",
    "sg:postcode":"NR28 0RE",
    "sg:province":"Norfolk",
    "sg:tags":[
        "consultant",
        "business"
    ],
    "wof:name":"Cougar Management Services Ltd.",
    "wof:placetype":"venue"
},
  "geometry": {"coordinates":[1.3847600222,52.8183135986],"type":"Point"}
}