{
  "type": "Feature",
  "properties": {
    "addr:full":"Pollington Grange, Bridge Lane Goole East Riding of Yorkshire DN14 0DY",
    "addr:housenumber":"pollington",
    "addr:postcode":"dn14 0dy",
    "addr:street":"Grange Bridge Lane",
    "iso:country":"GB",
    "sg:address":"Pollington Grange, Bridge Lane",
    "sg:city":"Goole",
    "sg:classifiers":[
        {
            "category":"Freight",
            "type":"Transportation"
        },
        {
            "category":"Farming",
            "subcategory":"Farm",
            "type":"Manufacturing & Wholesale Goods"
        }
    ],
    "sg:postcode":"DN14 0DY",
    "sg:province":"East Riding of Yorkshire",
    "sg:tags":[
        "producer",
        "haulage",
        "crop",
        "mixed",
        "egg",
        "road"
    ],
    "wof:name":"C G Bayston & Son",
    "wof:placetype":"venue"
},
  "geometry": {"coordinates":[-1.081795,53.676044],"type":"Point"}
}