{
  "type": "Feature",
  "properties": {
    "addr:full":"Unit 30 Clayton Square Shopping Cntr Liverpool Merseyside L1 1QR",
    "addr:housenumber":"unit 30",
    "addr:postcode":"l1 1qr",
    "addr:street":"Clayton Square",
    "iso:country":"GB",
    "sg:address":"Unit 30 Clayton Square Shopping Cntr",
    "sg:city":"Liverpool",
    "sg:classifiers":[
        {
            "category":"Shopping",
            "subcategory":"Gifts & Souvenirs",
            "type":"Retail Goods"
        }
    ],
    "sg:phone":"+44 151 709 3006",
    "sg:postcode":"L1 1QR",
    "sg:province":"Merseyside",
    "sg:tags":[
        "shop"
    ],
    "wof:name":"Wax Lyrical",
    "wof:placetype":"venue"
},
  "geometry": {"coordinates":[-2.981159,53.405674],"type":"Point"}
}