{
  "type": "Feature",
  "properties": {
    "addr:full":"Unit 6g Thorn Bsns Park, Rotherwas Hereford Herefordshire HR2 6JT",
    "addr:housenumber":"6g",
    "addr:postcode":"hr2 6jt",
    "addr:street":"Thorn Bsns Park Rotherwas",
    "iso:country":"GB",
    "sg:address":"Unit 6g Thorn Bsns Park, Rotherwas",
    "sg:city":"Hereford",
    "sg:classifiers":[
        {
            "category":"Wholesale",
            "subcategory":"Machinery & Supplies",
            "type":"Manufacturing & Wholesale Goods"
        }
    ],
    "sg:phone":"+44 1432 340240",
    "sg:postcode":"HR2 6JT",
    "sg:province":"Herefordshire",
    "sg:tags":[
        "plant"
    ],
    "wof:name":"Western Machinery Services Ltd.",
    "wof:placetype":"venue"
},
  "geometry": {"coordinates":[-2.6783390045,52.0369262695],"type":"Point"}
}