{
  "type": "Feature",
  "properties": {
    "addr:full":"15 Dunstew Bicester Oxfordshire OX6 7JR",
    "addr:housenumber":"15",
    "addr:postcode":"ox6 7jr",
    "addr:street":"Dunstew Bicester",
    "iso:country":"GB",
    "sg:address":"15 Dunstew",
    "sg:city":"Bicester",
    "sg:classifiers":[
        {
            "category":"Retail",
            "subcategory":"Funeral Services",
            "type":"Services"
        }
    ],
    "sg:phone":"+44 1993 812500",
    "sg:postcode":"OX6 7JR",
    "sg:province":"Oxfordshire",
    "wof:name":"Hancock D L",
    "wof:placetype":"venue"
},
  "geometry": {"coordinates":[-1.15354,51.898022],"type":"Point"}
}