{
  "type": "Feature",
  "properties": {
    "addr:full":"29 Runton Road Cromer Norfolk NR27 9AS",
    "addr:housenumber":"29",
    "addr:postcode":"nr27 9as",
    "addr:street":"Runton Road",
    "iso:country":"GB",
    "sg:address":"29 Runton Road",
    "sg:city":"Cromer",
    "sg:classifiers":[
        {
            "category":"Travel",
            "subcategory":"Hotels & Motels",
            "type":"Entertainment"
        }
    ],
    "sg:phone":"+44 1263 512543",
    "sg:postcode":"NR27 9AS",
    "sg:province":"Norfolk",
    "wof:name":"Cliftonville Hotel",
    "wof:placetype":"venue"
},
  "geometry": {"coordinates":[1.293223,52.93298],"type":"Point"}
}