{
  "type": "Feature",
  "properties": {
    "iso:country":"GB",
    "sg:address":"376-380 High Road Leyton, Leyton",
    "sg:city":"London",
    "sg:classifiers":[
        {
            "category":"Professional",
            "type":"Services"
        }
    ],
    "sg:phone":"+44 20 8556 5405",
    "sg:postcode":"E10 6QE",
    "sg:province":"Greater London",
    "sg:tags":[
        "caterer"
    ],
    "wof:name":"Andy Catering Equipment Ltd.",
    "wof:placetype":"venue"
},
  "geometry": {"coordinates":[-0.010411,51.562443],"type":"Point"}
}