{
  "type": "Feature",
  "properties": {
    "iso:country":"GB",
    "sg:address":"4-8 Leverson Street, Streatham",
    "sg:city":"London",
    "sg:classifiers":[
        {
            "category":"Retail",
            "subcategory":"Auto Repair",
            "type":"Services"
        }
    ],
    "sg:phone":"+44 20 8677 0707",
    "sg:postcode":"SW16 6DD",
    "sg:province":"Greater London",
    "sg:tags":[
        "modification",
        "garage"
    ],
    "wof:name":"Unique Motors",
    "wof:placetype":"venue"
},
  "geometry": {"coordinates":[-0.139361,51.421158],"type":"Point"}
}