{
  "type": "Feature",
  "properties": {
    "addr:full":"37 Station Road Sutton Surrey SM2 6DF",
    "addr:housenumber":"37",
    "addr:postcode":"sm2 6df",
    "addr:street":"Station Road",
    "iso:country":"GB",
    "sg:address":"37 Station Road",
    "sg:city":"Sutton",
    "sg:classifiers":[
        {
            "category":"Government",
            "subcategory":"Fire Station",
            "type":"Public Place"
        },
        {
            "category":"Home & Garden",
            "subcategory":"Hardware",
            "type":"Retail Goods"
        }
    ],
    "sg:postcode":"SM2 6DF",
    "sg:province":"Surrey",
    "sg:tags":[
        "w'sale",
        "lighting",
        "retailer"
    ],
    "wof:name":"P D Q Lighting Ltd.",
    "wof:placetype":"venue"
},
  "geometry": {"coordinates":[-0.2001360059,51.343875885],"type":"Point"}
}