{
  "type": "Feature",
  "properties": {
    "iso:country":"GB",
    "sg:address":"Wykeham, Church Lane, Oving",
    "sg:city":"Chichester",
    "sg:classifiers":[
        {
            "category":"Professional",
            "subcategory":"Accounting & Tax Preparation",
            "type":"Services"
        }
    ],
    "sg:phone":"+44 1243 528937",
    "sg:postcode":"PO20 2DG",
    "sg:province":"West Sussex",
    "sg:tags":[
        "accountant",
        "activity"
    ],
    "wof:name":"John N Sheppard",
    "wof:placetype":"venue"
},
  "geometry": {"coordinates":[-0.722296,50.836811],"type":"Point"}
}