{
  "type": "Feature",
  "properties": {
    "iso:country":"GB",
    "sg:address":"Bromford Lane, Ward End",
    "sg:city":"Birmingham",
    "sg:classifiers":[
        {
            "category":"Wholesale",
            "subcategory":"Scrap",
            "type":"Manufacturing & Wholesale Goods"
        }
    ],
    "sg:phone":"+44 121 328 2978",
    "sg:postcode":"B8 2SG",
    "sg:province":"West Midlands",
    "sg:tags":[
        "breaker",
        "dismantlers"
    ],
    "wof:name":"Bromford Spares Centre",
    "wof:placetype":"venue"
},
  "geometry": {"coordinates":[-1.8303610086,52.5032234192],"type":"Point"}
}