{
  "type": "Feature",
  "properties": {
    "iso:country":"GB",
    "sg:address":"Gulliford House, Kenton",
    "sg:city":"Exeter",
    "sg:classifiers":[
        {
            "category":"Manufacturing",
            "subcategory":"Tools & Machinery",
            "type":"Manufacturing & Wholesale Goods"
        },
        {
            "category":"Banks & Credit Unions",
            "subcategory":"Financial Services",
            "type":"Services"
        }
    ],
    "sg:phone":"+44 1392 272729",
    "sg:postcode":"EX6 8HH",
    "sg:province":"Devon",
    "sg:tags":[
        "society",
        "independent",
        "friendly",
        "adviser"
    ],
    "wof:name":"MERCHANT FINANCIAL SERVICES",
    "wof:placetype":"venue"
},
  "geometry": {"coordinates":[-3.472966,50.63995],"type":"Point"}
}