{
  "type": "Feature",
  "properties": {
    "iso:country":"GB",
    "sg:address":"11 Heath Rd",
    "sg:city":"Haywards Heath",
    "sg:classifiers":[
        {
            "category":"Professional",
            "subcategory":"Management & Consulting",
            "type":"Services"
        }
    ],
    "sg:phone":"+44 1444 458896",
    "sg:postcode":"RH16 3AX",
    "sg:province":"East Sussex",
    "sg:tags":[
        "marketing",
        "consultant"
    ],
    "wof:name":"Aubergene Communications Ltd",
    "wof:placetype":"venue"
},
  "geometry": {"coordinates":[-0.1014539972,51.0006866455],"type":"Point"}
}