{
  "type": "Feature",
  "properties": {
    "addr:full":"Efail Shingrig, Trelewis Treharris Caerphilly CF46 6DP",
    "addr:postcode":"cf46 6dp",
    "addr:street":"Treharris",
    "iso:country":"GB",
    "sg:address":"Efail Shingrig, Trelewis",
    "sg:city":"Treharris",
    "sg:classifiers":[
        {
            "category":"Manufacturing",
            "subcategory":"Metals",
            "type":"Manufacturing & Wholesale Goods"
        },
        {
            "category":"Utilities",
            "subcategory":"Natural Gas",
            "type":"Services"
        }
    ],
    "sg:phone":"+44 1443 411080",
    "sg:postcode":"CF46 6DP",
    "sg:province":"Caerphilly",
    "sg:tags":[
        "blacksmith",
        "forgemasters"
    ],
    "wof:name":"A Griffiths & Son",
    "wof:placetype":"venue"
},
  "geometry": {"coordinates":[-3.298256,51.67009],"type":"Point"}
}