{
  "type": "Feature",
  "properties": {
    "iso:country":"GB",
    "sg:address":"49-53 Fargate",
    "sg:city":"Sheffield",
    "sg:classifiers":[
        {
            "category":"Professional",
            "subcategory":"Employment Agencies",
            "type":"Services"
        }
    ],
    "sg:phone":"+44 114 276 8844",
    "sg:postcode":"S1 2HD",
    "sg:province":"South Yorkshire",
    "sg:tags":[
        "consultant"
    ],
    "wof:name":"Hays Recruitment",
    "wof:placetype":"venue"
},
  "geometry": {"coordinates":[-1.468626,53.382088],"type":"Point"}
}