{
  "type": "Feature",
  "properties": {
    "iso:country":"GB",
    "sg:address":"12 East Street",
    "sg:city":"Stamford",
    "sg:classifiers":[
        {
            "category":"Travel",
            "subcategory":"Hotels & Motels",
            "type":"Entertainment"
        }
    ],
    "sg:phone":"+44 1780 757515",
    "sg:postcode":"PE9 1QD",
    "sg:province":"Cambridgeshire",
    "sg:tags":[
        "house",
        "guest"
    ],
    "wof:name":"Dolphin Guest House",
    "wof:placetype":"venue"
},
  "geometry": {"coordinates":[-0.476412,52.65435],"type":"Point"}
}