{
  "type": "Feature",
  "properties": {
    "addr:full":"145 Homerton High Street London Greater London E9 6AS",
    "addr:housenumber":"145",
    "addr:postcode":"e9 6as",
    "addr:street":"Homerton High Street",
    "iso:country":"GB",
    "sg:address":"145 Homerton High Street",
    "sg:city":"London",
    "sg:classifiers":[
        {
            "category":"Retail",
            "subcategory":"Laundry & Dry Cleaning",
            "type":"Services"
        }
    ],
    "sg:phone":"+44 20 8985 7877",
    "sg:postcode":"E9 6AS",
    "sg:province":"Greater London",
    "sg:tags":[
        "alteration"
    ],
    "wof:name":"Star",
    "wof:placetype":"venue"
},
  "geometry": {"coordinates":[-0.0409240015,51.5488586426],"type":"Point"}
}