{
  "type": "Feature",
  "properties": {
    "iso:country":"GB",
    "sg:address":"139 Stamperland Gardens, Clarkston",
    "sg:city":"Glasgow",
    "sg:classifiers":[
        {
            "category":"Shopping",
            "subcategory":"Clothing, Apparel, & Fashions",
            "type":"Retail Goods"
        }
    ],
    "sg:phone":"+44 141 638 5559",
    "sg:postcode":"G76 8LJ",
    "sg:province":"East Renfrewshire",
    "sg:tags":[
        "dresswear"
    ],
    "wof:name":"Twice As Nice",
    "wof:placetype":"venue"
},
  "geometry": {"coordinates":[-4.272716,55.794765],"type":"Point"}
}