{
  "type": "Feature",
  "properties": {
    "addr:full":"Hallyburton, Coupar Angus Blairgowrie Angus PH13 9JR",
    "addr:postcode":"ph13 9jr",
    "iso:country":"GB",
    "sg:address":"Hallyburton, Coupar Angus",
    "sg:city":"Blairgowrie",
    "sg:classifiers":[
        {
            "category":"Farming",
            "subcategory":"Farm",
            "type":"Manufacturing & Wholesale Goods"
        }
    ],
    "sg:phone":"+44 1828 627232",
    "sg:postcode":"PH13 9JR",
    "sg:province":"Angus",
    "sg:tags":[
        "mixed",
        "crop"
    ],
    "wof:name":"Hallyburton Farming Partnership",
    "wof:placetype":"venue"
},
  "geometry": {"coordinates":[-3.2664289474,56.5461349487],"type":"Point"}
}