{
  "type": "Feature",
  "properties": {
    "iso:country":"GB",
    "sg:address":"6 Crown St",
    "sg:city":"Brentwood",
    "sg:classifiers":[
        {
            "category":"Organizations",
            "subcategory":"Non-profit Organization",
            "type":"Services"
        }
    ],
    "sg:phone":"+44 1277 263325",
    "sg:postcode":"CM14 4BA",
    "sg:province":"Essex",
    "sg:tags":[
        "organisation",
        "voluntary",
        "charity"
    ],
    "wof:name":"Home-start",
    "wof:placetype":"venue"
},
  "geometry": {"coordinates":[0.3007650077,51.619468689],"type":"Point"}
}