{
  "type": "Feature",
  "properties": {
    "iso:country":"GB",
    "sg:address":"59 Littabourne",
    "sg:city":"Barnstaple",
    "sg:classifiers":[
        {
            "category":"Retail",
            "subcategory":"Driving School",
            "type":"Services"
        }
    ],
    "sg:phone":"+44 1271 376114",
    "sg:postcode":"EX31 1PU",
    "sg:province":"Devon",
    "wof:name":"Clearway Driving School",
    "wof:placetype":"venue"
},
  "geometry": {"coordinates":[-4.05963,51.088863],"type":"Point"}
}