{
  "type": "Feature",
  "properties": {
    "iso:country":"GB",
    "sg:address":"Saxon Way East, Oakley Hay Industrial Estate",
    "sg:city":"Corby",
    "sg:classifiers":[
        {
            "category":"Wholesale",
            "subcategory":"Sporting Goods",
            "type":"Manufacturing & Wholesale Goods"
        }
    ],
    "sg:phone":"+44 1536 743337",
    "sg:postcode":"NN18 9EY",
    "sg:province":"Northamptonshire",
    "sg:tags":[
        "mnfr",
        "sport",
        "equipment"
    ],
    "wof:name":"Kookaburra Reader Ltd.",
    "wof:placetype":"venue"
},
  "geometry": {"coordinates":[-0.731504,52.463943],"type":"Point"}
}