{
  "type": "Feature",
  "properties": {
    "addr:full":"40 Park Road, Southville Bristol City of Bristol BS3 1PU",
    "addr:housenumber":"40",
    "addr:postcode":"bs3 1pu",
    "addr:street":"Park Road",
    "iso:country":"GB",
    "sg:address":"40 Park Road, Southville",
    "sg:city":"Bristol",
    "sg:classifiers":[
        {
            "category":"Shopping",
            "subcategory":"Musical Instruments",
            "type":"Retail Goods"
        }
    ],
    "sg:phone":"+44 117 953 2122",
    "sg:postcode":"BS3 1PU",
    "sg:province":"City of Bristol",
    "wof:name":"Claire Edwards",
    "wof:placetype":"venue"
},
  "geometry": {"coordinates":[-2.6064779758,51.4454727173],"type":"Point"}
}