{
  "type": "Feature",
  "properties": {
    "iso:country":"GB",
    "sg:address":"25-27 Kirkdale Road",
    "sg:city":"London",
    "sg:classifiers":[
        {
            "category":"Bars & Pubs",
            "subcategory":"Nightclub",
            "type":"Food & Drink"
        },
        {
            "category":"Bars & Pubs",
            "subcategory":"Wine Bar",
            "type":"Food & Drink"
        }
    ],
    "sg:phone":"+44 20 8539 6975",
    "sg:postcode":"E11 1HP",
    "sg:province":"Greater London",
    "sg:tags":[
        "activity"
    ],
    "wof:name":"Kirkdale Wine Bar",
    "wof:placetype":"venue"
},
  "geometry": {"coordinates":[0.0118549997,51.5692596436],"type":"Point"}
}