{
  "type": "Feature",
  "properties": {
    "addr:full":"95 Guisborough Rd Middlesbrough North Yorkshire TS7 0JS",
    "addr:housenumber":"95",
    "addr:postcode":"ts7 0js",
    "addr:street":"Guisborough Rd",
    "iso:country":"GB",
    "sg:address":"95 Guisborough Rd",
    "sg:city":"Middlesbrough",
    "sg:classifiers":[
        {
            "category":"Real Estate",
            "subcategory":"Real Estate Agent",
            "type":"Services"
        }
    ],
    "sg:phone":"+44 1642 300700",
    "sg:postcode":"TS7 0JS",
    "sg:province":"North Yorkshire",
    "wof:name":"Sanderson Taylor Partnership",
    "wof:placetype":"venue"
},
  "geometry": {"coordinates":[-1.168456,54.528641],"type":"Point"}
}