{
  "type": "Feature",
  "properties": {
    "addr:full":"20 Black Friars La London Greater London EC4V 6HD",
    "addr:housenumber":"20",
    "addr:postcode":"ec4v 6hd",
    "addr:street":"Black Friars La",
    "iso:country":"GB",
    "sg:address":"20 Black Friars La",
    "sg:city":"London",
    "sg:classifiers":[
        {
            "category":"Airline",
            "type":"Transportation"
        }
    ],
    "sg:postcode":"EC4V 6HD",
    "sg:province":"Greater London",
    "sg:tags":[
        "airport"
    ],
    "wof:name":"London Southend Airport Co Ltd",
    "wof:placetype":"venue"
},
  "geometry": {"coordinates":[-0.102971,51.513035],"type":"Point"}
}