{
  "type": "Feature",
  "properties": {
    "iso:country":"GB",
    "sg:address":"10 Abingdon St",
    "sg:city":"Burnham-on-sea",
    "sg:classifiers":[
        {
            "category":"Restaurant",
            "type":"Food & Drink"
        }
    ],
    "sg:postcode":"TA8 1PH",
    "sg:province":"Somerset",
    "wof:name":"Abingdon Omelette Bar & Grill",
    "wof:placetype":"venue"
},
  "geometry": {"coordinates":[-2.9972600937,51.2343597412],"type":"Point"}
}