{
  "type": "Feature",
  "properties": {
    "addr:full":"1 Moorgate London Greater London EC2R 6JH",
    "addr:housenumber":"1",
    "addr:postcode":"ec2r 6jh",
    "addr:street":"Moorgate",
    "iso:country":"GB",
    "sg:address":"1 Moorgate",
    "sg:city":"London",
    "sg:classifiers":[
        {
            "category":"Banks & Credit Unions",
            "subcategory":"Bank",
            "type":"Services"
        }
    ],
    "sg:phone":"+44 20 7726 4131",
    "sg:postcode":"EC2R 6JH",
    "sg:province":"Greater London",
    "wof:name":"Banco Di Napoli Spa",
    "wof:placetype":"venue"
},
  "geometry": {"coordinates":[-0.089469,51.515339],"type":"Point"}
}