{
  "type": "Feature",
  "properties": {
    "iso:country":"GB",
    "sg:address":"707 High Road, Finchley",
    "sg:city":"London",
    "sg:classifiers":[
        {
            "category":"Education",
            "subcategory":"Special Training",
            "type":"Public Place"
        }
    ],
    "sg:phone":"+44 20 8446 6481",
    "sg:postcode":"N12 0BT",
    "sg:province":"Greater London",
    "sg:tags":[
        "product",
        "centre"
    ],
    "wof:name":"Skilladvance Ltd.",
    "wof:placetype":"venue"
},
  "geometry": {"coordinates":[-0.175916,51.612289],"type":"Point"}
}