{
  "type": "Feature",
  "properties": {
    "iso:country":"GB",
    "sg:address":"26 Park Road West, Wolliston",
    "sg:city":"Stourbridge",
    "sg:classifiers":[
        {
            "category":"Building & Trades",
            "subcategory":"Construction",
            "type":"Services"
        }
    ],
    "sg:phone":"+44 1384 825982",
    "sg:postcode":"DY8 3NQ",
    "sg:province":"Staffordshire",
    "sg:tags":[
        "roofing",
        "contracting"
    ],
    "wof:name":"Andrew's Roofing Services",
    "wof:placetype":"venue"
},
  "geometry": {"coordinates":[-2.164164,52.456741],"type":"Point"}
}