{
  "type": "Feature",
  "properties": {
    "iso:country":"GB",
    "sg:address":"1 Cornish Close",
    "sg:city":"Manchester",
    "sg:classifiers":[
        {
            "category":"Organizations",
            "subcategory":"Non-profit Organization",
            "type":"Services"
        }
    ],
    "sg:phone":"+44 161 436 3848",
    "sg:postcode":"M22 0GJ",
    "sg:province":"Greater Manchester",
    "sg:tags":[
        "charitable",
        "organisation",
        "voluntary",
        "charity"
    ],
    "wof:name":"United Response",
    "wof:placetype":"venue"
},
  "geometry": {"coordinates":[-2.258495,53.369442],"type":"Point"}
}