{
  "type": "Feature",
  "properties": {
    "iso:country":"GB",
    "sg:address":"Concord House, Park Lane",
    "sg:city":"Leeds",
    "sg:classifiers":[
        {
            "category":"Organizations",
            "subcategory":"Professional Association",
            "type":"Services"
        }
    ],
    "sg:phone":"+44 113 244 1881",
    "sg:postcode":"LS3 1EJ",
    "sg:province":"West Yorkshire",
    "sg:tags":[
        "union",
        "trade"
    ],
    "wof:name":"Union of Shop Distributive & Allied Workers",
    "wof:placetype":"venue"
},
  "geometry": {"coordinates":[-1.559671998,53.8004074097],"type":"Point"}
}