{
  "type": "Feature",
  "properties": {
    "addr:full":"Perrott Farm, Llandegveth Newport Monmouthshire NP18 1HX",
    "addr:postcode":"np18 1hx",
    "addr:street":"Llandegveth",
    "iso:country":"GB",
    "sg:address":"Perrott Farm, Llandegveth",
    "sg:city":"Newport",
    "sg:classifiers":[
        {
            "category":"Farming",
            "subcategory":"Dairy Farm",
            "type":"Manufacturing & Wholesale Goods"
        }
    ],
    "sg:phone":"+44 1633 450237",
    "sg:postcode":"NP18 1HX",
    "sg:province":"Monmouthshire",
    "wof:name":"W E Dowds Ltd.",
    "wof:placetype":"venue"
},
  "geometry": {"coordinates":[-2.96044,51.656139],"type":"Point"}
}