{
  "type": "Feature",
  "properties": {
    "addr:full":"6 Norham Road North Shields Tyne and Wear NE29 7AJ",
    "addr:housenumber":"6",
    "addr:postcode":"ne29 7aj",
    "addr:street":"Norham Road",
    "iso:country":"GB",
    "sg:address":"6 Norham Road",
    "sg:city":"North Shields",
    "sg:classifiers":[
        {
            "category":"Food & Beverages",
            "subcategory":"Liquor & Beverages",
            "type":"Retail Goods"
        },
        {
            "category":"Shopping",
            "subcategory":"News",
            "type":"Retail Goods"
        }
    ],
    "sg:phone":"+44 191 258 5242",
    "sg:postcode":"NE29 7AJ",
    "sg:province":"Tyne and Wear",
    "sg:tags":[
        "beer",
        "wine",
        "newsagent",
        "spirit"
    ],
    "wof:name":"L & P R Davis",
    "wof:placetype":"venue"
},
  "geometry": {"coordinates":[-1.4759119749,55.0030212402],"type":"Point"}
}