{
  "type": "Feature",
  "properties": {
    "iso:country":"GB",
    "sg:address":"The Market, Choumert Road",
    "sg:city":"London",
    "sg:classifiers":[
        {
            "category":"Personal",
            "subcategory":"Beauty Salon",
            "type":"Services"
        }
    ],
    "sg:phone":"+44 20 7277 5335",
    "sg:postcode":"SE15 4SG",
    "sg:province":"Greater London",
    "wof:name":"Afro Beauty Salon",
    "wof:placetype":"venue"
},
  "geometry": {"coordinates":[-0.0678400025,51.4679718018],"type":"Point"}
}