{
  "type": "Feature",
  "properties": {
    "addr:full":"Units 1 & 2 Chandlery Building, Hamble Point Marina, School Lane Southampton Hampshire SO31 4NB",
    "addr:housenumber":"units 1 & 2",
    "addr:postcode":"so31 4nb",
    "addr:street":"Hamble Point;School Lane",
    "iso:country":"GB",
    "sg:address":"Units 1 & 2 Chandlery Building, Hamble Point Marina, School Lane",
    "sg:city":"Southampton",
    "sg:classifiers":[
        {
            "category":"Retail",
            "subcategory":"Event Space",
            "type":"Services"
        }
    ],
    "sg:postcode":"SO31 4NB",
    "sg:province":"Hampshire",
    "sg:tags":[
        "sale",
        "boat"
    ],
    "wof:name":"Transworld Yachts Ltd.",
    "wof:placetype":"venue"
},
  "geometry": {"coordinates":[-1.31041,50.849331],"type":"Point"}
}