{
  "type": "Feature",
  "properties": {
    "addr:full":"Westfield 16 Booth Lane South Northampton Northamptonshire NN3 3EP",
    "addr:housenumber":"16",
    "addr:postcode":"nn3 3ep",
    "addr:street":"Westfield;Booth Lane",
    "iso:country":"GB",
    "sg:address":"Westfield 16 Booth Lane South",
    "sg:city":"Northampton",
    "sg:classifiers":[
        {
            "category":"Professional",
            "subcategory":"Management & Consulting",
            "type":"Services"
        }
    ],
    "sg:phone":"+44 1604 402277",
    "sg:postcode":"NN3 3EP",
    "sg:province":"Northamptonshire",
    "sg:tags":[
        "environmental",
        "consultant"
    ],
    "wof:name":"A.f Fleming",
    "wof:placetype":"venue"
},
  "geometry": {"coordinates":[-0.846849978,52.2560806274],"type":"Point"}
}