{
  "type": "Feature",
  "properties": {
    "iso:country":"GB",
    "sg:address":"57 Ringwood Drive",
    "sg:city":"Cramlington",
    "sg:classifiers":[
        {
            "category":"Professional",
            "subcategory":"Engineering",
            "type":"Services"
        },
        {
            "category":"Building & Trades",
            "subcategory":"Construction",
            "type":"Services"
        }
    ],
    "sg:postcode":"NE23 1ND",
    "sg:province":"Northumberland",
    "sg:tags":[
        "civil",
        "contractor",
        "paving",
        "engineer"
    ],
    "wof:name":"C M G",
    "wof:placetype":"venue"
},
  "geometry": {"coordinates":[-1.578169,55.089443],"type":"Point"}
}