{
  "type": "Feature",
  "properties": {
    "iso:country":"GB",
    "sg:address":"Foxlands Farm, Croft Road, Cosby",
    "sg:city":"Leicester",
    "sg:classifiers":[
        {
            "category":"Professional",
            "subcategory":"Engineering",
            "type":"Services"
        },
        {
            "category":"Shopping",
            "type":"Retail Goods"
        }
    ],
    "sg:phone":"+44 116 286 2666",
    "sg:postcode":"LE9 1SG",
    "sg:province":"Leicestershire",
    "sg:tags":[
        "merchant"
    ],
    "wof:name":"Dalgety Arable Ltd.",
    "wof:placetype":"venue"
},
  "geometry": {"coordinates":[-1.194663,52.551392],"type":"Point"}
}