{
  "type": "Feature",
  "properties": {
    "iso:country":"GB",
    "sg:address":"7 Tyldesley Rd",
    "sg:city":"Manchester",
    "sg:classifiers":[
        {
            "category":"Shopping",
            "subcategory":"News",
            "type":"Retail Goods"
        }
    ],
    "sg:phone":"+44 1942 883614",
    "sg:postcode":"M46 9DA",
    "sg:province":"Greater Manchester",
    "sg:tags":[
        "newsagent"
    ],
    "wof:name":"Perry's Newsagents",
    "wof:placetype":"venue"
},
  "geometry": {"coordinates":[-2.489858,53.523418],"type":"Point"}
}