{
  "type": "Feature",
  "properties": {
    "iso:country":"GB",
    "sg:address":"Unit 90 Alloa Business Centre, The Whins",
    "sg:city":"Alloa",
    "sg:classifiers":[
        {
            "category":"Banks & Credit Unions",
            "subcategory":"Financial Services",
            "type":"Services"
        }
    ],
    "sg:phone":"+44 1259 720077",
    "sg:postcode":"FK10 3SA",
    "sg:province":"Clackmannanshire",
    "sg:tags":[
        "consultant",
        "finance"
    ],
    "wof:name":"Greenwood Personal Credit",
    "wof:placetype":"venue"
},
  "geometry": {"coordinates":[-3.7951939106,56.1163215637],"type":"Point"}
}