{
  "type": "Feature",
  "properties": {
    "addr:full":"Madford Retail Park, Foregate Street Stafford Staffordshire ST16 2PA",
    "addr:postcode":"st16 2pa",
    "addr:street":"Park Foregate Street",
    "iso:country":"GB",
    "sg:address":"Madford Retail Park, Foregate Street",
    "sg:city":"Stafford",
    "sg:classifiers":[
        {
            "category":"Organizations",
            "subcategory":"Non-profit Organization",
            "type":"Services"
        }
    ],
    "sg:phone":"+44 1785 276800",
    "sg:postcode":"ST16 2PA",
    "sg:province":"Staffordshire",
    "sg:tags":[
        "organisation",
        "voluntary",
        "charity"
    ],
    "wof:name":"Stafford Area Service Office",
    "wof:placetype":"venue"
},
  "geometry": {"coordinates":[-2.1217679977,52.8039588928],"type":"Point"}
}