{
  "type": "Feature",
  "properties": {
    "addr:full":"The Danesmead Business Centre, 33 Fulford Cross York North Yorkshire YO10 4PB",
    "addr:housenumber":"33",
    "addr:postcode":"yo10 4pb",
    "addr:street":"Fulford Cross York",
    "iso:country":"GB",
    "sg:address":"The Danesmead Business Centre, 33 Fulford Cross",
    "sg:city":"York",
    "sg:classifiers":[
        {
            "category":"Military Area",
            "subcategory":"Air Force Base",
            "type":"Public Place"
        }
    ],
    "sg:postcode":"YO10 4PB",
    "sg:province":"North Yorkshire",
    "sg:tags":[
        "energy",
        "conservation"
    ],
    "wof:name":"Leading Lines Worldwide",
    "wof:placetype":"venue"
},
  "geometry": {"coordinates":[-1.070884,53.933109],"type":"Point"}
}