{
  "type": "Feature",
  "properties": {
    "iso:country":"GB",
    "sg:address":"24 Tombland",
    "sg:city":"Norwich",
    "sg:classifiers":[
        {
            "category":"Bars & Pubs",
            "type":"Food & Drink"
        },
        {
            "category":"Bars & Pubs",
            "subcategory":"Nightclub",
            "type":"Food & Drink"
        }
    ],
    "sg:phone":"+44 1603 285366",
    "sg:postcode":"NR3 1RF",
    "sg:province":"Norfolk",
    "sg:tags":[
        "club",
        "pubs",
        "inn",
        "night"
    ],
    "wof:name":"Kurzner Enterprises Ltd.",
    "wof:placetype":"venue"
},
  "geometry": {"coordinates":[1.2993340492,52.6308708191],"type":"Point"}
}