{
  "type": "Feature",
  "properties": {
    "iso:country":"GB",
    "sg:address":"Church House, 94 Felpham Road",
    "sg:city":"Bognor Regis",
    "sg:classifiers":[
        {
            "category":"Banks & Credit Unions",
            "subcategory":"Financial Services",
            "type":"Services"
        }
    ],
    "sg:phone":"+44 1243 826166",
    "sg:postcode":"PO22 7PG",
    "sg:province":"West Sussex",
    "sg:tags":[
        "consultant"
    ],
    "wof:name":"K & M Associates",
    "wof:placetype":"venue"
},
  "geometry": {"coordinates":[-0.653852,50.790527],"type":"Point"}
}