{
  "type": "Feature",
  "properties": {
    "iso:country":"GB",
    "sg:address":"4 Hodders Close",
    "sg:city":"Frome",
    "sg:classifiers":[
        {
            "category":"Retail",
            "subcategory":"Auto Repair",
            "type":"Services"
        }
    ],
    "sg:phone":"+44 1373 451097",
    "sg:postcode":"BA11 3AG",
    "sg:province":"Somerset",
    "sg:tags":[
        "body",
        "car"
    ],
    "wof:name":"A.M Doel",
    "wof:placetype":"venue"
},
  "geometry": {"coordinates":[-2.3247148991,51.2346153259],"type":"Point"}
}