{
  "type": "Feature",
  "properties": {
    "addr:full":"21/27 Ock St Abingdon Oxfordshire OX14 5AG",
    "addr:housenumber":"21 / 27",
    "addr:postcode":"ox14 5ag",
    "addr:street":"Ock St",
    "iso:country":"GB",
    "sg:address":"21/27 Ock St",
    "sg:city":"Abingdon",
    "sg:classifiers":[
        {
            "category":"Home & Garden",
            "subcategory":"Garden Supply",
            "type":"Retail Goods"
        }
    ],
    "sg:phone":"+44 1235 524197",
    "sg:postcode":"OX14 5AG",
    "sg:province":"Oxfordshire",
    "sg:tags":[
        "flower",
        "shrub"
    ],
    "wof:name":"Coxeters Ltd",
    "wof:placetype":"venue"
},
  "geometry": {"coordinates":[-1.2852089405,51.6700515747],"type":"Point"}
}