{
  "type": "Feature",
  "properties": {
    "addr:full":"Hicks Common Road, Winterbourne Bristol Gloucestershire BS36 1EJ",
    "addr:postcode":"bs36 1ej",
    "addr:street":"Hicks Common Road",
    "iso:country":"GB",
    "sg:address":"Hicks Common Road, Winterbourne",
    "sg:city":"Bristol",
    "sg:classifiers":[
        {
            "category":"Professional",
            "subcategory":"Engineering",
            "type":"Services"
        }
    ],
    "sg:postcode":"BS36 1EJ",
    "sg:province":"Gloucestershire",
    "wof:name":"Reynolds Engineering (Winterbourne) Ltd.",
    "wof:placetype":"venue"
},
  "geometry": {"coordinates":[-2.508889,51.523251],"type":"Point"}
}