{
  "type": "Feature",
  "properties": {
    "addr:full":"132 Front Street, Arnold Nottingham Nottinghamshire NG5 7EG",
    "addr:housenumber":"132",
    "addr:postcode":"ng5 7eg",
    "addr:street":"Front Street",
    "iso:country":"GB",
    "sg:address":"132 Front Street, Arnold",
    "sg:city":"Nottingham",
    "sg:classifiers":[
        {
            "category":"Personal",
            "subcategory":"Nail Salon",
            "type":"Services"
        }
    ],
    "sg:phone":"+44 115 966 6106",
    "sg:postcode":"NG5 7EG",
    "sg:province":"Nottinghamshire",
    "sg:tags":[
        "solarium",
        "tanning"
    ],
    "wof:name":"Easy Tan",
    "wof:placetype":"venue"
},
  "geometry": {"coordinates":[-1.1268709898,53.0051727295],"type":"Point"}
}