{
  "type": "Feature",
  "properties": {
    "iso:country":"GB",
    "sg:address":"Carrs Lane Church Centre Carrs, Carrs Lane,",
    "sg:city":"Birmingham",
    "sg:classifiers":[
        {
            "category":"Fast Food",
            "type":"Food & Drink"
        }
    ],
    "sg:postcode":"B4 7SX",
    "sg:province":"West Midlands",
    "sg:tags":[
        "away",
        "take"
    ],
    "wof:name":"Dale Pantry Ltd",
    "wof:placetype":"venue"
},
  "geometry": {"coordinates":[-1.8938339949,52.4795951843],"type":"Point"}
}