{
  "type": "Feature",
  "properties": {
    "iso:country":"GB",
    "sg:address":"3a Beachfield Ave",
    "sg:city":"Newquay",
    "sg:classifiers":[
        {
            "category":"Shopping",
            "subcategory":"Bicycles & Sporting Goods",
            "type":"Retail Goods"
        }
    ],
    "sg:postcode":"TR7 1DP",
    "sg:province":"Cornwall",
    "sg:tags":[
        "cycle",
        "accessory"
    ],
    "wof:name":"Cycle Xtreme",
    "wof:placetype":"venue"
},
  "geometry": {"coordinates":[-5.084276,50.413944],"type":"Point"}
}