{
  "type": "Feature",
  "properties": {
    "addr:full":"Icen Lane, Shipton Gorge Bridport Dorset DT6 4PP",
    "addr:postcode":"dt6 4pp",
    "addr:street":"Icen Lane",
    "iso:country":"GB",
    "sg:address":"Icen Lane, Shipton Gorge",
    "sg:city":"Bridport",
    "sg:classifiers":[
        {
            "category":"Farming",
            "subcategory":"Livestock Farm",
            "type":"Manufacturing & Wholesale Goods"
        }
    ],
    "sg:phone":"+44 1308 897517",
    "sg:postcode":"DT6 4PP",
    "sg:province":"Dorset",
    "sg:tags":[
        "others"
    ],
    "wof:name":"W N Chick & Sons",
    "wof:placetype":"venue"
},
  "geometry": {"coordinates":[-2.716204,50.72208],"type":"Point"}
}