{
  "type": "Feature",
  "properties": {
    "addr:full":"89 Egerton Rd Blackpool Lancashire FY1 2NN",
    "addr:housenumber":"89",
    "addr:postcode":"fy1 2nn",
    "addr:street":"Egerton Rd",
    "iso:country":"GB",
    "sg:address":"89 Egerton Rd",
    "sg:city":"Blackpool",
    "sg:classifiers":[
        {
            "category":"Travel",
            "subcategory":"Hotels & Motels",
            "type":"Entertainment"
        }
    ],
    "sg:phone":"+44 1253 626364",
    "sg:postcode":"FY1 2NN",
    "sg:province":"Lancashire",
    "sg:tags":[
        "self",
        "catering"
    ],
    "wof:name":"R E Lee",
    "wof:placetype":"venue"
},
  "geometry": {"coordinates":[-3.051527977,53.8260040283],"type":"Point"}
}