{
  "type": "Feature",
  "properties": {
    "iso:country":"GB",
    "sg:address":"Purves Hall, Greenlaw",
    "sg:city":"Duns",
    "sg:classifiers":[
        {
            "category":"Professional",
            "subcategory":"Employment Agencies",
            "type":"Services"
        }
    ],
    "sg:phone":"+44 1890 840444",
    "sg:postcode":"TD10 6UJ",
    "sg:province":"Scottish Borders",
    "sg:tags":[
        "agricultural",
        "advice"
    ],
    "wof:name":"Simon Richard Agriculture",
    "wof:placetype":"venue"
},
  "geometry": {"coordinates":[-2.462528944,55.7065162659],"type":"Point"}
}