{
  "type": "Feature",
  "properties": {
    "addr:full":"1 Woodside Atherstone Leicestershire CV9 2BX",
    "addr:housenumber":"1",
    "addr:postcode":"cv9 2bx",
    "addr:street":"Woodside",
    "iso:country":"GB",
    "sg:address":"1 Woodside",
    "sg:city":"Atherstone",
    "sg:classifiers":[
        {
            "category":"Farming",
            "subcategory":"Livestock Farm",
            "type":"Manufacturing & Wholesale Goods"
        }
    ],
    "sg:phone":"+44 1945 700202",
    "sg:postcode":"CV9 2BX",
    "sg:province":"Leicestershire",
    "sg:tags":[
        "others"
    ],
    "wof:name":"P Scrimshaw",
    "wof:placetype":"venue"
},
  "geometry": {"coordinates":[-1.5951600075,52.5809745789],"type":"Point"}
}