{
  "type": "Feature",
  "properties": {
    "iso:country":"GB",
    "sg:address":"66 Highgate Road",
    "sg:city":"Walsall",
    "sg:classifiers":[
        {
            "category":"Health Services",
            "subcategory":"Nursing And Care Facility",
            "type":"Services"
        },
        {
            "category":"Social Services",
            "subcategory":"Retirement Home",
            "type":"Services"
        }
    ],
    "sg:phone":"+44 1922 646168",
    "sg:postcode":"WS1 3JE",
    "sg:province":"West Midlands",
    "sg:tags":[
        "rest"
    ],
    "wof:name":"Crossways Home for the Elderly",
    "wof:placetype":"venue"
},
  "geometry": {"coordinates":[-1.973904,52.5741],"type":"Point"}
}