{
  "type": "Feature",
  "properties": {
    "addr:full":"14 & 15 Craven St London Greater London WC2N 5AD",
    "addr:housenumber":"14 & 15",
    "addr:postcode":"wc2n 5ad",
    "addr:street":"Craven St",
    "iso:country":"GB",
    "sg:address":"14 & 15 Craven St",
    "sg:city":"London",
    "sg:classifiers":[
        {
            "category":"Organizations",
            "subcategory":"Membership Organization",
            "type":"Services"
        }
    ],
    "sg:postcode":"WC2N 5AD",
    "sg:province":"Greater London",
    "sg:tags":[
        "club"
    ],
    "wof:name":"49, Grosvenor Square Management Ltd",
    "wof:placetype":"venue"
},
  "geometry": {"coordinates":[-0.125524,51.507675],"type":"Point"}
}