{
  "type": "Feature",
  "properties": {
    "addr:full":"69 King St, Nantyglo Ebbw Vale Blaenau Gwent NP23 4JN",
    "addr:housenumber":"69",
    "addr:postcode":"np23 4jn",
    "addr:street":"King St",
    "iso:country":"GB",
    "sg:address":"69 King St, Nantyglo",
    "sg:city":"Ebbw Vale",
    "sg:classifiers":[
        {
            "category":"Government",
            "subcategory":"Post Office",
            "type":"Public Place"
        }
    ],
    "sg:postcode":"NP23 4JN",
    "sg:province":"Blaenau Gwent",
    "wof:name":"White,Ian,",
    "wof:placetype":"venue"
},
  "geometry": {"coordinates":[-3.175786,51.80035],"type":"Point"}
}