{
  "type": "Feature",
  "properties": {
    "iso:country":"GB",
    "sg:address":"Unit 9, Carrington Centre, The Green, Eccleston",
    "sg:city":"Chorley",
    "sg:classifiers":[
        {
            "category":"Personal",
            "subcategory":"Beauty Salon",
            "type":"Services"
        }
    ],
    "sg:phone":"+44 1257 451900",
    "sg:postcode":"PR7 5UP",
    "sg:province":"Lancashire",
    "wof:name":"Carringtons Beauty & Skincare Clinic",
    "wof:placetype":"venue"
},
  "geometry": {"coordinates":[-2.731795,53.650291],"type":"Point"}
}