{
  "type": "Feature",
  "properties": {
    "addr:full":"51 Main Aitchison Street Airdrie North Lanarkshire ML6 0BZ",
    "addr:housenumber":"51",
    "addr:postcode":"ml6 0bz",
    "addr:street":"Main Aitchison Street",
    "iso:country":"GB",
    "sg:address":"51 Main Aitchison Street",
    "sg:city":"Airdrie",
    "sg:classifiers":[
        {
            "category":"Bars & Pubs",
            "type":"Food & Drink"
        }
    ],
    "sg:phone":"+44 1236 763000",
    "sg:postcode":"ML6 0BZ",
    "sg:province":"North Lanarkshire",
    "sg:tags":[
        "pubs",
        "inn"
    ],
    "wof:name":"Wilson Arms",
    "wof:placetype":"venue"
},
  "geometry": {"coordinates":[-3.9891901016,55.8665618896],"type":"Point"}
}