{
  "type": "Feature",
  "properties": {
    "addr:full":"Convent Garden Business Centre, 22-24 Southampton Street London Greater London WC2E 7JB",
    "addr:housenumber":"22-24",
    "addr:postcode":"wc2e 7jb",
    "addr:street":"Southampton Street",
    "iso:country":"GB",
    "sg:address":"Convent Garden Business Centre, 22-24 Southampton Street",
    "sg:city":"London",
    "sg:classifiers":[
        {
            "category":"Banks & Credit Unions",
            "subcategory":"Bank",
            "type":"Services"
        }
    ],
    "sg:phone":"+44 20 7626 1500",
    "sg:postcode":"WC2E 7JB",
    "sg:province":"Greater London",
    "wof:name":"Lloyds Tsb Bank Plc",
    "wof:placetype":"venue"
},
  "geometry": {"coordinates":[-0.15639,51.550468],"type":"Point"}
}