{
  "type": "Feature",
  "properties": {
    "iso:country":"GB",
    "sg:address":"37-41 Dean Street",
    "sg:city":"Blackpool",
    "sg:classifiers":[
        {
            "category":"Health Services",
            "subcategory":"Nursing And Care Facility",
            "type":"Services"
        }
    ],
    "sg:phone":"+44 1253 349617",
    "sg:postcode":"FY4 1BP",
    "sg:province":"Lancashire",
    "sg:tags":[
        "home"
    ],
    "wof:name":"Elmsdene Nursing Home",
    "wof:placetype":"venue"
},
  "geometry": {"coordinates":[-3.051852,53.796673],"type":"Point"}
}