{
  "type": "Feature",
  "properties": {
    "addr:full":"8 Finkle Court, Finkle Street Doncaster East Riding of Yorkshire DN8 5TW",
    "addr:housenumber":"8",
    "addr:postcode":"dn8 5tw",
    "addr:street":"Finkle Court Finkle Street",
    "iso:country":"GB",
    "sg:address":"8 Finkle Court, Finkle Street",
    "sg:city":"Doncaster",
    "sg:classifiers":[
        {
            "category":"Fast Food",
            "type":"Food & Drink"
        }
    ],
    "sg:phone":"+44 1405 740680",
    "sg:postcode":"DN8 5TW",
    "sg:province":"East Riding of Yorkshire",
    "sg:tags":[
        "away",
        "take"
    ],
    "wof:name":"Fernando's Pizzeria",
    "wof:placetype":"venue"
},
  "geometry": {"coordinates":[-0.9628440142,53.6110534668],"type":"Point"}
}