{
  "type": "Feature",
  "properties": {
    "addr:full":"Union Street Chorley Lancashire PR7 1AA",
    "addr:postcode":"pr7 1aa",
    "addr:street":"Union Street",
    "iso:country":"GB",
    "sg:address":"Union Street",
    "sg:city":"Chorley",
    "sg:classifiers":[
        {
            "category":"Bus Charters",
            "type":"Transportation"
        }
    ],
    "sg:phone":"+44 1257 267728",
    "sg:postcode":"PR7 1AA",
    "sg:province":"Lancashire",
    "sg:tags":[
        "coach"
    ],
    "wof:name":"Stagecoach Ribble",
    "wof:placetype":"venue"
},
  "geometry": {"coordinates":[-2.6287889481,53.654750824],"type":"Point"}
}