{
  "type": "Feature",
  "properties": {
    "addr:full":"35 Mickleton Avenue Birmingham West Midlands B33 0TX",
    "addr:housenumber":"35",
    "addr:postcode":"b33 0tx",
    "addr:street":"Mickleton Avenue",
    "iso:country":"GB",
    "sg:address":"35 Mickleton Avenue",
    "sg:city":"Birmingham",
    "sg:classifiers":[
        {
            "category":"Shopping",
            "subcategory":"News",
            "type":"Retail Goods"
        }
    ],
    "sg:phone":"+44 121 743 6769",
    "sg:postcode":"B33 0TX",
    "sg:province":"West Midlands",
    "sg:tags":[
        "newsagent"
    ],
    "wof:name":"Headline News",
    "wof:placetype":"venue"
},
  "geometry": {"coordinates":[-1.7779029608,52.4703979492],"type":"Point"}
}