{
  "type": "Feature",
  "properties": {
    "iso:country":"GB",
    "sg:address":"Halbeath Rd",
    "sg:city":"Dunfermline",
    "sg:classifiers":[
        {
            "category":"Retail",
            "subcategory":"Auto Repair",
            "type":"Services"
        }
    ],
    "sg:phone":"+44 1383 626696",
    "sg:postcode":"KY12 7RD",
    "sg:province":"Fife",
    "sg:tags":[
        "modification",
        "garage"
    ],
    "wof:name":"Rapid Fit",
    "wof:placetype":"venue"
},
  "geometry": {"coordinates":[-3.429954052,56.0776100159],"type":"Point"}
}