{
  "type": "Feature",
  "properties": {
    "addr:full":"Davis Street, Hurst Reading Berkshire RG10 0TH",
    "addr:postcode":"rg10 0th",
    "addr:street":"Davis Street",
    "iso:country":"GB",
    "sg:address":"Davis Street, Hurst",
    "sg:city":"Reading",
    "sg:classifiers":[
        {
            "category":"Bars & Pubs",
            "type":"Food & Drink"
        }
    ],
    "sg:phone":"+44 118 934 1881",
    "sg:postcode":"RG10 0TH",
    "sg:province":"Berkshire",
    "sg:tags":[
        "pubs",
        "inn"
    ],
    "wof:name":"The Jolly Farmer Inn",
    "wof:placetype":"venue"
},
  "geometry": {"coordinates":[-0.8713610172,51.4385795593],"type":"Point"}
}