{
  "type": "Feature",
  "properties": {
    "addr:full":"Lake Indstl Way Sandown Isle of Wight PO36 9PL",
    "addr:postcode":"po36 9pl",
    "addr:street":"Indstl Way",
    "iso:country":"GB",
    "sg:address":"Lake Indstl Way",
    "sg:city":"Sandown",
    "sg:classifiers":[
        {
            "category":"Travel",
            "subcategory":"Hotels & Motels",
            "type":"Entertainment"
        }
    ],
    "sg:postcode":"PO36 9PL",
    "sg:province":"Isle of Wight",
    "sg:tags":[
        "house",
        "guest"
    ],
    "wof:name":"Cottage Holidays",
    "wof:placetype":"venue"
},
  "geometry": {"coordinates":[-1.182782,50.645401],"type":"Point"}
}