{
  "type": "Feature",
  "properties": {
    "addr:full":"6 Elliot Avenue Peterborough Cambridgeshire PE3 9TG",
    "addr:housenumber":"6",
    "addr:postcode":"pe3 9tg",
    "addr:street":"Elliot Avenue",
    "iso:country":"GB",
    "sg:address":"6 Elliot Avenue",
    "sg:city":"Peterborough",
    "sg:classifiers":[
        {
            "category":"Building & Trades",
            "subcategory":"Plumbing",
            "type":"Services"
        }
    ],
    "sg:phone":"+44 1733 264037",
    "sg:postcode":"PE3 9TG",
    "sg:province":"Cambridgeshire",
    "sg:tags":[
        "heating"
    ],
    "wof:name":"M Fletcher Plumbing & Heating",
    "wof:placetype":"venue"
},
  "geometry": {"coordinates":[-0.291512996,52.5757484436],"type":"Point"}
}