{
  "type": "Feature",
  "properties": {
    "addr:full":"Langstone Road, Langstone Havant Hampshire PO9 1RD",
    "addr:postcode":"po9 1rd",
    "addr:street":"Langstone Road",
    "iso:country":"GB",
    "sg:address":"Langstone Road, Langstone",
    "sg:city":"Havant",
    "sg:classifiers":[
        {
            "category":"Bars & Pubs",
            "type":"Food & Drink"
        }
    ],
    "sg:phone":"+44 23 9247 1719",
    "sg:postcode":"PO9 1RD",
    "sg:province":"Hampshire",
    "sg:tags":[
        "pubs",
        "inn"
    ],
    "wof:name":"The Ship Inn",
    "wof:placetype":"venue"
},
  "geometry": {"coordinates":[-0.985544,50.854496],"type":"Point"}
}