{
  "type": "Feature",
  "properties": {
    "addr:full":"New Portreath Road Redruth Cornwall TR16 4HH",
    "addr:postcode":"tr16 4hh",
    "addr:street":"Portreath Road",
    "iso:country":"GB",
    "sg:address":"New Portreath Road",
    "sg:city":"Redruth",
    "sg:classifiers":[
        {
            "category":"Transit Center",
            "subcategory":"Passenger",
            "type":"Transportation"
        }
    ],
    "sg:phone":"+44 1209 217880",
    "sg:postcode":"TR16 4HH",
    "sg:province":"Cornwall",
    "sg:tags":[
        "boarding",
        "kennel",
        "catteries"
    ],
    "wof:name":"Sun Valley Cattery",
    "wof:placetype":"venue"
},
  "geometry": {"coordinates":[-5.290253,50.25972],"type":"Point"}
}