{
  "type": "Feature",
  "properties": {
    "addr:full":"66 Pinfold Lane, Methley Leeds West Yorkshire LS26 9AB",
    "addr:housenumber":"66",
    "addr:postcode":"ls26 9ab",
    "addr:street":"Pinfold Lane",
    "iso:country":"GB",
    "sg:address":"66 Pinfold Lane, Methley",
    "sg:city":"Leeds",
    "sg:classifiers":[
        {
            "category":"Building & Trades",
            "subcategory":"Construction",
            "type":"Services"
        }
    ],
    "sg:phone":"+44 1977 515300",
    "sg:postcode":"LS26 9AB",
    "sg:province":"West Yorkshire",
    "sg:tags":[
        "glazier"
    ],
    "wof:name":"Gordon Brown",
    "wof:placetype":"venue"
},
  "geometry": {"coordinates":[-1.3935970068,53.7343673706],"type":"Point"}
}