{
  "type": "Feature",
  "properties": {
    "addr:full":"1 High Street Dartford Kent DA1 1DU",
    "addr:housenumber":"1",
    "addr:postcode":"da1 1du",
    "addr:street":"High Street",
    "iso:country":"GB",
    "sg:address":"1 High Street",
    "sg:city":"Dartford",
    "sg:classifiers":[
        {
            "category":"Travel",
            "subcategory":"Hotels & Motels",
            "type":"Entertainment"
        }
    ],
    "sg:phone":"+44 1322 224415",
    "sg:postcode":"DA1 1DU",
    "sg:province":"Kent",
    "wof:name":"The Royal Victoria & Bull Hotel",
    "wof:placetype":"venue"
},
  "geometry": {"coordinates":[0.216973,51.444321],"type":"Point"}
}