{
  "type": "Feature",
  "properties": {
    "iso:country":"GB",
    "sg:address":"115 Hartsfield Road",
    "sg:city":"Luton",
    "sg:classifiers":[
        {
            "category":"Arts & Performance",
            "subcategory":"Music",
            "type":"Entertainment"
        }
    ],
    "sg:phone":"+44 1582 615261",
    "sg:postcode":"LU2 9DY",
    "sg:province":"Bedfordshire",
    "sg:tags":[
        "mobile",
        "disco"
    ],
    "wof:name":"Sunset Disco",
    "wof:placetype":"venue"
},
  "geometry": {"coordinates":[-0.389692,51.888195],"type":"Point"}
}