{
  "type": "Feature",
  "properties": {
    "iso:country":"GB",
    "sg:address":"Trafford Park",
    "sg:city":"Manchester",
    "sg:classifiers":[
        {
            "category":"Food & Beverages",
            "subcategory":"Farmers Market",
            "type":"Retail Goods"
        }
    ],
    "sg:phone":"+44 161 872 5959",
    "sg:postcode":"M17 1PA",
    "sg:province":"Cheshire",
    "sg:tags":[
        "oil",
        "-",
        "edible"
    ],
    "wof:name":"Cerestar U K Ltd.",
    "wof:placetype":"venue"
},
  "geometry": {"coordinates":[-2.32875,53.476841],"type":"Point"}
}