{
  "type": "Feature",
  "properties": {
    "iso:country":"GB",
    "sg:address":"Virginia Galleries, Virginia St",
    "sg:city":"Glasgow",
    "sg:classifiers":[
        {
            "category":"Arts & Performance",
            "subcategory":"Art Gallery",
            "type":"Entertainment"
        }
    ],
    "sg:phone":"+44 141 553 0553",
    "sg:postcode":"G1 1TU",
    "sg:province":"Glasgow City",
    "wof:name":"Archies Art Lodge",
    "wof:placetype":"venue"
},
  "geometry": {"coordinates":[-4.2425107956,55.8578071594],"type":"Point"}
}