{
  "type": "Feature",
  "properties": {
    "addr:full":"C/o Park Circus Management, James Sellars Ho,  144 West George St Glasgow Glasgow City G2 2HG",
    "addr:housenumber":"144",
    "addr:postcode":"g2 2hg",
    "addr:street":"C / O Park Circus;West George St",
    "iso:country":"GB",
    "sg:address":"C/o Park Circus Management, James Sellars Ho,  144 West George St",
    "sg:city":"Glasgow",
    "sg:classifiers":[
        {
            "category":"Real Estate",
            "subcategory":"Developer",
            "type":"Services"
        }
    ],
    "sg:postcode":"G2 2HG",
    "sg:province":"Glasgow City",
    "sg:tags":[
        "property"
    ],
    "wof:name":"Reversionary Gains I Ltd",
    "wof:placetype":"venue"
},
  "geometry": {"coordinates":[-4.2572898865,55.8627090454],"type":"Point"}
}