{
  "type": "Feature",
  "properties": {
    "addr:full":"Maycroft Works, Stone Cross Road Mayfield East Sussex TN20 6EJ",
    "addr:postcode":"tn20 6ej",
    "addr:street":"Stone Cross Road",
    "iso:country":"GB",
    "sg:address":"Maycroft Works, Stone Cross Road",
    "sg:city":"Mayfield",
    "sg:classifiers":[
        {
            "category":"Retail",
            "subcategory":"Auto Repair",
            "type":"Services"
        }
    ],
    "sg:postcode":"TN20 6EJ",
    "sg:province":"East Sussex",
    "sg:tags":[
        "modification",
        "garage"
    ],
    "wof:name":"A & R Hurst",
    "wof:placetype":"venue"
},
  "geometry": {"coordinates":[0.258735,51.020004],"type":"Point"}
}