{
  "type": "Feature",
  "properties": {
    "iso:country":"GB",
    "sg:address":"Maes Clwyd, Park Road",
    "sg:city":"Ruthin",
    "sg:classifiers":[
        {
            "category":"Personal",
            "subcategory":"Beauty Salon",
            "type":"Services"
        },
        {
            "category":"Personal",
            "subcategory":"Barber",
            "type":"Services"
        }
    ],
    "sg:phone":"+44 1824 705830",
    "sg:postcode":"LL15 1NB",
    "sg:province":"Denbighshire",
    "sg:tags":[
        "unisex",
        "hairdresser"
    ],
    "wof:name":"New Image",
    "wof:placetype":"venue"
},
  "geometry": {"coordinates":[-3.31597,53.113392],"type":"Point"}
}