{
  "type": "Feature",
  "properties": {
    "addr:full":"89 Chiltern Road St Albans Hertfordshire AL4 9TA",
    "addr:housenumber":"89",
    "addr:postcode":"al4 9ta",
    "addr:street":"Chiltern Road",
    "iso:country":"GB",
    "sg:address":"89 Chiltern Road",
    "sg:city":"St Albans",
    "sg:classifiers":[
        {
            "category":"Government",
            "subcategory":"Office",
            "type":"Public Place"
        },
        {
            "category":"Social Services",
            "subcategory":"Adult Care",
            "type":"Services"
        },
        {
            "category":"Social Services",
            "subcategory":"Retirement Home",
            "type":"Services"
        }
    ],
    "sg:phone":"+44 1727 867867",
    "sg:postcode":"AL4 9TA",
    "sg:province":"Hertfordshire",
    "sg:tags":[
        "housing",
        "local",
        "accommodation",
        "sheltered"
    ],
    "wof:name":"Caroline Sharpe House",
    "wof:placetype":"venue"
},
  "geometry": {"coordinates":[-0.304896,51.771145],"type":"Point"}
}