{
  "type": "Feature",
  "properties": {
    "iso:country":"GB",
    "sg:address":"Exhibition Square",
    "sg:city":"York",
    "sg:classifiers":[
        {
            "category":"Arts & Performance",
            "subcategory":"Art Gallery",
            "type":"Entertainment"
        }
    ],
    "sg:phone":"+44 1904 551861",
    "sg:postcode":"YO1 2EW",
    "sg:province":"North Yorkshire",
    "wof:name":"Art Gallery",
    "wof:placetype":"venue"
},
  "geometry": {"coordinates":[-1.085511,53.962364],"type":"Point"}
}