{
  "type": "Feature",
  "properties": {
    "iso:country":"GB",
    "sg:address":"132b Filton Road, Horfield",
    "sg:city":"Bristol",
    "sg:classifiers":[
        {
            "category":"Manufacturing",
            "subcategory":"Building Materials",
            "type":"Manufacturing & Wholesale Goods"
        }
    ],
    "sg:phone":"+44 117 914 0652",
    "sg:postcode":"BS7 0PF",
    "sg:province":"City of Bristol",
    "sg:tags":[
        "stonemason"
    ],
    "wof:name":"Robbins Masonry",
    "wof:placetype":"venue"
},
  "geometry": {"coordinates":[-2.5787549019,51.4995803833],"type":"Point"}
}