{
  "type": "Feature",
  "properties": {
    "iso:country":"GB",
    "sg:address":"71 Redvales Road",
    "sg:city":"Bury",
    "sg:classifiers":[
        {
            "category":"Retail",
            "subcategory":"Auto Repair",
            "type":"Services"
        }
    ],
    "sg:postcode":"BL9 9PS",
    "sg:province":"Lancashire",
    "sg:tags":[
        "modification",
        "garage"
    ],
    "wof:name":"Total Car Care",
    "wof:placetype":"venue"
},
  "geometry": {"coordinates":[-2.302185,53.579388],"type":"Point"}
}