{"geometry":{"type":"Point","coordinates":[-0.732197,51.391922]},"type":"Feature","id":102560375,"bbox":[-0.732197,51.391922,-0.732197,51.391922],"properties":{"sg:province":"Berkshire","sg:tags":["messenger","courier"],"geom:longitude":-0.732197,"wof:breaches":[],"sg:href":"http://api.simplegeo.com/1.0/features/SG_5rBAdygtUsb8AyxjpoC6wF_51.391922_-0.732197@1300740015.json","sg:owner":"simplegeo","sg:postcode":"RG12 0XQ","geom:latitude":51.391922,"sg:classifiers":[{"category":"Government","type":"Public Place","subcategory":"Post Office"}],"sg:address":"Unit 5, Forest Park Business Centre","sg:phone":"+44 1344 489099","wof:hierarchy":[{"locality_id":101750375,"venue_id":102560375,"country_id":85633159,"neighbourhood_id":85860901,"region_id":85684497}],"geom:area":0.000000,"sg:city":"Bracknell","wof:lastmodified":1438093236,"iso:country":"GB","wof:geomhash":"d5614b169b5b7c454d3b4000b253852a","wof:name":"Scarlet Couriers","wof:belongsto":[101750375,85633159,85860901,85684497],"src:geom":"simplegeo","wof:placetype":"venue","wof:supersedes":[],"wof:id":102560375,"wof:superseded_by":[],"wof:concordances":{"sg:id":"SG_5rBAdygtUsb8AyxjpoC6wF_51.391922_-0.732197@1300740015"},"wof:parent_id":85860901}}