{
  "type": "Feature",
  "properties": {
    "addr:full":"Unit 5, Forest Park Business Centre Bracknell Berkshire RG12 0XQ",
    "addr:housenumber":"unit 5",
    "addr:postcode":"rg12 0xq",
    "addr:street":"Forest Park",
    "iso:country":"GB",
    "sg:address":"Unit 5, Forest Park Business Centre",
    "sg:city":"Bracknell",
    "sg:classifiers":[
        {
            "category":"Government",
            "subcategory":"Post Office",
            "type":"Public Place"
        }
    ],
    "sg:href":"http://api.simplegeo.com/1.0/features/SG_5rBAdygtUsb8AyxjpoC6wF_51.391922_-0.732197@1300740015.json",
    "sg:phone":"+44 1344 489099",
    "sg:postcode":"RG12 0XQ",
    "sg:province":"Berkshire",
    "sg:tags":[
        "messenger",
        "courier"
    ],
    "wof:name":"Scarlet Couriers",
    "wof:placetype":"venue"
},
  "geometry": {"coordinates":[-0.732197,51.391922],"type":"Point"}
}