{
  "type": "Feature",
  "properties": {
    "iso:country":"GB",
    "sg:address":"33 Longridge Avenue, Saltdean",
    "sg:city":"Brighton",
    "sg:classifiers":[
        {
            "category":"Retail",
            "subcategory":"Auto Repair",
            "type":"Services"
        }
    ],
    "sg:postcode":"BN2 8LG",
    "sg:province":"East Sussex",
    "sg:tags":[
        "body",
        "car"
    ],
    "wof:name":"Vincent Body Repairs",
    "wof:placetype":"venue"
},
  "geometry": {"coordinates":[-0.037655,50.800816],"type":"Point"}
}