{
  "type": "Feature",
  "properties": {
    "addr:full":"71 Deptford High St Deptford Greater London SE8 4AA",
    "addr:housenumber":"71",
    "addr:postcode":"se8 4aa",
    "addr:street":"Deptford High St",
    "iso:country":"GB",
    "sg:address":"71 Deptford High St",
    "sg:city":"Deptford",
    "sg:classifiers":[
        {
            "category":"Home & Garden",
            "subcategory":"Carpets & Floor Coverings",
            "type":"Retail Goods"
        }
    ],
    "sg:phone":"+44 20 8691 2816",
    "sg:postcode":"SE8 4AA",
    "sg:province":"Greater London",
    "sg:tags":[
        "carpets",
        "rug",
        "matting"
    ],
    "wof:name":"The Carpet Market",
    "wof:placetype":"venue"
},
  "geometry": {"coordinates":[-0.026096,51.477009],"type":"Point"}
}