{
  "type": "Feature",
  "properties": {
    "iso:country":"GB",
    "sg:address":"Creed Court Sheltered Housing, 1 Outram Road",
    "sg:city":"Croydon",
    "sg:classifiers":[
        {
            "category":"Government",
            "subcategory":"Office",
            "type":"Public Place"
        }
    ],
    "sg:phone":"+44 20 8656 4918",
    "sg:postcode":"CR0 6XG",
    "sg:province":"Surrey",
    "sg:tags":[
        "local"
    ],
    "wof:name":"Creed Court Sheltered Housing",
    "wof:placetype":"venue"
},
  "geometry": {"coordinates":[-0.07657,51.376678],"type":"Point"}
}