{
  "type": "Feature",
  "properties": {
    "iso:country":"GB",
    "sg:address":"419 Bearwood Rd",
    "sg:city":"Smethwick",
    "sg:classifiers":[
        {
            "category":"Shopping",
            "subcategory":"Clothing, Apparel, & Fashions",
            "type":"Retail Goods"
        }
    ],
    "sg:postcode":"B66 4DF",
    "sg:province":"West Midlands",
    "sg:tags":[
        "menswear"
    ],
    "wof:name":"Bottrell,S A,",
    "wof:placetype":"venue"
},
  "geometry": {"coordinates":[-1.969718,52.478516],"type":"Point"}
}