{
  "type": "Feature",
  "properties": {
    "addr:full":"180 Cambridge Road Southport Lancashire PR9 7LW",
    "addr:housenumber":"180",
    "addr:postcode":"pr9 7lw",
    "addr:street":"Cambridge Road",
    "iso:country":"GB",
    "sg:address":"180 Cambridge Road",
    "sg:city":"Southport",
    "sg:classifiers":[
        {
            "category":"Health Services",
            "subcategory":"Doctor",
            "type":"Services"
        }
    ],
    "sg:phone":"+44 1704 506055",
    "sg:postcode":"PR9 7LW",
    "sg:province":"Lancashire",
    "sg:tags":[
        "practitioners"
    ],
    "wof:name":"The Corner Surgery",
    "wof:placetype":"venue"
},
  "geometry": {"coordinates":[-2.9659070969,53.660823822],"type":"Point"}
}