{
  "type": "Feature",
  "properties": {
    "addr:full":"64 Delamere Road Hayes Greater London UB4 0NN",
    "addr:housenumber":"64",
    "addr:postcode":"ub4 0nn",
    "addr:street":"Delamere Road",
    "iso:country":"GB",
    "sg:address":"64 Delamere Road",
    "sg:city":"Hayes",
    "sg:classifiers":[
        {
            "category":"Manufacturing",
            "subcategory":"Building Materials",
            "type":"Manufacturing & Wholesale Goods"
        }
    ],
    "sg:phone":"+44 20 8573 0357",
    "sg:postcode":"UB4 0NN",
    "sg:province":"Greater London",
    "sg:tags":[
        "merchant",
        "builder"
    ],
    "wof:name":"C & C Building Merchants",
    "wof:placetype":"venue"
},
  "geometry": {"coordinates":[-0.392228,51.513824],"type":"Point"}
}