{
  "type": "Feature",
  "properties": {
    "iso:country":"GB",
    "sg:address":"205 Holdernerss Road",
    "sg:city":"Hull",
    "sg:classifiers":[
        {
            "category":"Military Area",
            "subcategory":"Air Force Base",
            "type":"Public Place"
        }
    ],
    "sg:phone":"+44 1482 444555",
    "sg:postcode":"HU8 8TA",
    "sg:province":"East Riding of Yorkshire",
    "sg:tags":[
        "taxi",
        "hire",
        "private"
    ],
    "wof:name":"Express Cars",
    "wof:placetype":"venue"
},
  "geometry": {"coordinates":[-0.314586,53.753315],"type":"Point"}
}