{
  "type": "Feature",
  "properties": {
    "iso:country":"GB",
    "sg:address":"Landau House, Bontoft Avenue",
    "sg:city":"Hull",
    "sg:classifiers":[
        {
            "category":"Home & Garden",
            "subcategory":"Home Furnishings",
            "type":"Retail Goods"
        }
    ],
    "sg:phone":"+44 1482 443666",
    "sg:postcode":"HU5 4HF",
    "sg:province":"East Riding of Yorkshire",
    "sg:tags":[
        "furnishers",
        "planner",
        "kitchen"
    ],
    "wof:name":"G A E Ltd.",
    "wof:placetype":"venue"
},
  "geometry": {"coordinates":[-0.38658,53.757195],"type":"Point"}
}