{
  "type": "Feature",
  "properties": {
    "addr:full":"9 Matlock Street Leicester Leicestershire LE2 0GS",
    "addr:housenumber":"9",
    "addr:postcode":"le2 0gs",
    "addr:street":"Matlock Street",
    "iso:country":"GB",
    "sg:address":"9 Matlock Street",
    "sg:city":"Leicester",
    "sg:classifiers":[
        {
            "category":"Shopping",
            "subcategory":"Clothing, Apparel, & Fashions",
            "type":"Retail Goods"
        },
        {
            "category":"Wholesale",
            "subcategory":"Apparel",
            "type":"Manufacturing & Wholesale Goods"
        }
    ],
    "sg:phone":"+44 116 253 2524",
    "sg:postcode":"LE2 0GS",
    "sg:province":"Leicestershire",
    "sg:tags":[
        "supplier",
        "clothing"
    ],
    "wof:name":"Fancy Cloth",
    "wof:placetype":"venue"
},
  "geometry": {"coordinates":[-1.1129720211,52.6360359192],"type":"Point"}
}