{
  "type": "Feature",
  "properties": {
    "addr:full":"48 Lower Richmond Road London Greater London SW15 1JP",
    "addr:housenumber":"48",
    "addr:postcode":"sw15 1jp",
    "addr:street":"Lower Richmond Road",
    "iso:country":"GB",
    "sg:address":"48 Lower Richmond Road",
    "sg:city":"London",
    "sg:classifiers":[
        {
            "category":"Food & Beverages",
            "subcategory":"Liquor & Beverages",
            "type":"Retail Goods"
        }
    ],
    "sg:phone":"+44 20 8788 4651",
    "sg:postcode":"SW15 1JP",
    "sg:province":"Greater London",
    "sg:tags":[
        "beer",
        "spirit",
        "wines"
    ],
    "wof:name":"Thresher",
    "wof:placetype":"venue"
},
  "geometry": {"coordinates":[-0.2188999951,51.4672813416],"type":"Point"}
}