{
  "type": "Feature",
  "properties": {
    "addr:full":"574 Bearwood Rd, Smethwick Warley Smethwick West Midlands B66 4BW",
    "addr:housenumber":"574",
    "addr:postcode":"b66 4bw",
    "addr:street":"Bearwood Rd",
    "iso:country":"GB",
    "sg:address":"574 Bearwood Rd, Smethwick Warley",
    "sg:city":"Smethwick",
    "sg:classifiers":[
        {
            "category":"Communications",
            "subcategory":"Film & Video Production",
            "type":"Services"
        }
    ],
    "sg:phone":"+44 121 429 9663",
    "sg:postcode":"B66 4BW",
    "sg:province":"West Midlands",
    "sg:tags":[
        "tv"
    ],
    "wof:name":"Granada Home Technology",
    "wof:placetype":"venue"
},
  "geometry": {"coordinates":[-1.9690849781,52.4737205505],"type":"Point"}
}