{
  "type": "Feature",
  "properties": {
    "addr:full":"4 Queen Street, Rhosllanerchrugog Wrexham Wrexham LL14 1PY",
    "addr:housenumber":"4",
    "addr:postcode":"ll14 1py",
    "addr:street":"Queen Street",
    "iso:country":"GB",
    "sg:address":"4 Queen Street, Rhosllanerchrugog",
    "sg:city":"Wrexham",
    "sg:classifiers":[
        {
            "category":"Health Services",
            "subcategory":"Nursing And Care Facility",
            "type":"Services"
        },
        {
            "category":"Social Services",
            "subcategory":"Retirement Home",
            "type":"Services"
        }
    ],
    "sg:phone":"+44 1978 846686",
    "sg:postcode":"LL14 1PY",
    "sg:province":"Wrexham",
    "sg:tags":[
        "residential"
    ],
    "wof:name":"Aran Care Ltd.",
    "wof:placetype":"venue"
},
  "geometry": {"coordinates":[-3.055141,53.009037],"type":"Point"}
}