{
  "type": "Feature",
  "properties": {
    "addr:full":"Frome Road Bradford-on-avon Wiltshire BA15 1LE",
    "addr:postcode":"ba15 1le",
    "addr:street":"Frome Road",
    "iso:country":"GB",
    "sg:address":"Frome Road",
    "sg:city":"Bradford-on-avon",
    "sg:classifiers":[
        {
            "category":"Education",
            "subcategory":"School",
            "type":"Public Place"
        },
        {
            "category":"Government",
            "subcategory":"Office",
            "type":"Public Place"
        }
    ],
    "sg:phone":"+44 1225 862162",
    "sg:postcode":"BA15 1LE",
    "sg:province":"Wiltshire",
    "sg:tags":[
        "local",
        "authority"
    ],
    "wof:name":"Fitzmaurice Primary School",
    "wof:placetype":"venue"
},
  "geometry": {"coordinates":[-2.2515599728,51.3437042236],"type":"Point"}
}