{
  "type": "Feature",
  "properties": {
    "iso:country":"GB",
    "sg:address":"80 Roman Road",
    "sg:city":"Middlesbrough",
    "sg:classifiers":[
        {
            "category":"Social Services",
            "subcategory":"Retirement Home",
            "type":"Services"
        }
    ],
    "sg:postcode":"TS5 5QE",
    "sg:province":"North Yorkshire",
    "sg:tags":[
        "rest"
    ],
    "wof:name":"Hollygarth",
    "wof:placetype":"venue"
},
  "geometry": {"coordinates":[-1.244121,54.552898],"type":"Point"}
}