{
  "type": "Feature",
  "properties": {
    "iso:country":"GB",
    "sg:address":"62 Knights Hill",
    "sg:city":"London",
    "sg:classifiers":[
        {
            "category":"Fast Food",
            "type":"Food & Drink"
        }
    ],
    "sg:phone":"+44 20 8761 4318",
    "sg:postcode":"SE27 0JD",
    "sg:province":"Greater London",
    "sg:tags":[
        "away",
        "take"
    ],
    "wof:name":"Tandoori Express",
    "wof:placetype":"venue"
},
  "geometry": {"coordinates":[-0.104437,51.431232],"type":"Point"}
}