{
  "type": "Feature",
  "properties": {
    "addr:full":"Church Road, Gosforth Newcastle-upon-tyne Tyne and Wear NE3 1TX",
    "addr:postcode":"ne3 1tx",
    "addr:street":"Church Road",
    "iso:country":"GB",
    "sg:address":"Church Road, Gosforth",
    "sg:city":"Newcastle-upon-tyne",
    "sg:classifiers":[
        {
            "category":"Health Services",
            "subcategory":"Clinic",
            "type":"Services"
        }
    ],
    "sg:phone":"+44 191 210 6636",
    "sg:postcode":"NE3 1TX",
    "sg:province":"Tyne and Wear",
    "sg:tags":[
        "nh"
    ],
    "wof:name":"Newcastle Primary Care Trust",
    "wof:placetype":"venue"
},
  "geometry": {"coordinates":[-1.612,55.00769],"type":"Point"}
}