{
  "type": "Feature",
  "properties": {
    "iso:country":"GB",
    "sg:address":"6 Vanburgh Way, Chandlers Ford",
    "sg:city":"Eastleigh",
    "sg:classifiers":[
        {
            "category":"Professional",
            "subcategory":"Management & Consulting",
            "type":"Services"
        }
    ],
    "sg:postcode":"SO53 1SE",
    "sg:province":"Hampshire",
    "sg:tags":[
        "consultant",
        "business"
    ],
    "wof:name":"Kgb Consultants Ltd",
    "wof:placetype":"venue"
},
  "geometry": {"coordinates":[-1.394062,50.998009],"type":"Point"}
}