{
  "type": "Feature",
  "properties": {
    "iso:country":"GB",
    "sg:address":"40 The Bridges",
    "sg:city":"Sunderland",
    "sg:classifiers":[
        {
            "category":"Shopping",
            "subcategory":"Clothing, Apparel, & Fashions",
            "type":"Retail Goods"
        }
    ],
    "sg:phone":"+44 191 567 4178",
    "sg:postcode":"SR1 3LE",
    "sg:province":"Tyne and Wear",
    "sg:tags":[
        "shop"
    ],
    "wof:name":"C & A",
    "wof:placetype":"venue"
},
  "geometry": {"coordinates":[-1.442955,54.91927],"type":"Point"}
}