{
  "type": "Feature",
  "properties": {
    "addr:full":"17 Hampden Rd Hitchin Hertfordshire SG4 0LD",
    "addr:housenumber":"17",
    "addr:postcode":"sg4 0ld",
    "addr:street":"Hampden Rd",
    "iso:country":"GB",
    "sg:address":"17 Hampden Rd",
    "sg:city":"Hitchin",
    "sg:classifiers":[
        {
            "category":"Building & Trades",
            "subcategory":"Plumbing",
            "type":"Services"
        }
    ],
    "sg:postcode":"SG4 0LD",
    "sg:province":"Hertfordshire",
    "sg:tags":[
        "central",
        "heating"
    ],
    "wof:name":"Lammiman,Mervyn,",
    "wof:placetype":"venue"
},
  "geometry": {"coordinates":[-0.2546199858,51.9564971924],"type":"Point"}
}