{
  "type": "Feature",
  "properties": {
    "iso:country":"GB",
    "sg:address":"Capland, Hatch Beauchamp",
    "sg:city":"Taunton",
    "sg:classifiers":[
        {
            "category":"Building & Trades",
            "subcategory":"Construction",
            "type":"Services"
        }
    ],
    "sg:phone":"+44 1823 480248",
    "sg:postcode":"TA3 6TW",
    "sg:province":"Devon",
    "sg:tags":[
        "builder"
    ],
    "wof:name":"G Woodland & Sons Ltd.",
    "wof:placetype":"venue"
},
  "geometry": {"coordinates":[-2.9897420406,50.9645195007],"type":"Point"}
}