{
  "type": "Feature",
  "properties": {
    "addr:full":"Godstone Road Oxted Surrey RH8 9NQ",
    "addr:postcode":"rh8 9nq",
    "addr:street":"Godstone Road",
    "iso:country":"GB",
    "sg:address":"Godstone Road",
    "sg:city":"Oxted",
    "sg:classifiers":[
        {
            "category":"Sports & Exercise",
            "subcategory":"Golf",
            "type":"Entertainment"
        }
    ],
    "sg:phone":"+44 1883 712274",
    "sg:postcode":"RH8 9NQ",
    "sg:province":"Surrey",
    "sg:tags":[
        "club",
        "course"
    ],
    "wof:name":"Tandridge Golf Club",
    "wof:placetype":"venue"
},
  "geometry": {"coordinates":[-0.0178490002,51.2520484924],"type":"Point"}
}