{
  "type": "Feature",
  "properties": {
    "addr:full":"The Tee Squares, 9 Padarn Close Cardiff Cardiff CF23 6ER",
    "addr:housenumber":"9",
    "addr:postcode":"cf23 6er",
    "addr:street":"Tee Squares;Padarn Close",
    "iso:country":"GB",
    "sg:address":"The Tee Squares, 9 Padarn Close",
    "sg:city":"Cardiff",
    "sg:classifiers":[
        {
            "category":"Professional",
            "subcategory":"Engineering",
            "type":"Services"
        }
    ],
    "sg:phone":"+44 29 2075 5405",
    "sg:postcode":"CF23 6ER",
    "sg:province":"Cardiff",
    "sg:tags":[
        "design",
        "engineer"
    ],
    "wof:name":"Dr W.A Morris M.Sc",
    "wof:placetype":"venue"
},
  "geometry": {"coordinates":[-3.17208,51.516739],"type":"Point"}
}