{
  "type": "Feature",
  "properties": {
    "addr:full":"48 Manor Place Edinburgh City of Edinburgh EH3 7EH",
    "addr:housenumber":"48",
    "addr:postcode":"eh3 7eh",
    "addr:street":"Manor Place Edinburgh",
    "iso:country":"GB",
    "sg:address":"48 Manor Place",
    "sg:city":"Edinburgh",
    "sg:classifiers":[
        {
            "category":"Communications",
            "type":"Services"
        }
    ],
    "sg:phone":"+44 131 240 2900",
    "sg:postcode":"EH3 7EH",
    "sg:province":"City of Edinburgh",
    "sg:tags":[
        "data",
        "network"
    ],
    "wof:name":"3 Com (U K) Ltd.",
    "wof:placetype":"venue"
},
  "geometry": {"coordinates":[-3.217103,55.949684],"type":"Point"}
}