{
  "type": "Feature",
  "properties": {
    "addr:full":"Broomfallen Road, Scotby Carlisle Cumbria CA4 8DG",
    "addr:postcode":"ca4 8dg",
    "addr:street":"Broomfallen Road",
    "iso:country":"GB",
    "sg:address":"Broomfallen Road, Scotby",
    "sg:city":"Carlisle",
    "sg:classifiers":[
        {
            "category":"Transit Center",
            "subcategory":"Passenger",
            "type":"Transportation"
        },
        {
            "category":"Retail",
            "subcategory":"Pet Boarding",
            "type":"Services"
        }
    ],
    "sg:phone":"+44 1228 513397",
    "sg:postcode":"CA4 8DG",
    "sg:province":"Cumbria",
    "sg:tags":[
        "kennel",
        "catteries"
    ],
    "wof:name":"Broomeden Kennels",
    "wof:placetype":"venue"
},
  "geometry": {"coordinates":[-2.8720030785,54.8859939575],"type":"Point"}
}