{
  "type": "Feature",
  "properties": {
    "addr:full":"8 Buxton Road North Walsham Norfolk NR28 0ED",
    "addr:housenumber":"8",
    "addr:postcode":"nr28 0ed",
    "addr:street":"Buxton Road",
    "iso:country":"GB",
    "sg:address":"8 Buxton Road",
    "sg:city":"North Walsham",
    "sg:classifiers":[
        {
            "category":"Building & Trades",
            "subcategory":"Construction",
            "type":"Services"
        }
    ],
    "sg:phone":"+44 1692 406388",
    "sg:postcode":"NR28 0ED",
    "sg:province":"Norfolk",
    "sg:tags":[
        "decorator",
        "painter"
    ],
    "wof:name":"J Allen",
    "wof:placetype":"venue"
},
  "geometry": {"coordinates":[1.3754429817,52.8171386719],"type":"Point"}
}