{
  "type": "Feature",
  "properties": {
    "iso:country":"GB",
    "sg:address":"20-22high St",
    "sg:city":"Thornton Heath",
    "sg:classifiers":[
        {
            "category":"Shopping",
            "subcategory":"Department Store",
            "type":"Retail Goods"
        }
    ],
    "sg:phone":"+44 20 8684 0111",
    "sg:postcode":"CR7 8LE",
    "sg:province":"Surrey",
    "wof:name":"Fresyls",
    "wof:placetype":"venue"
},
  "geometry": {"coordinates":[-0.098405,51.401165],"type":"Point"}
}