{
  "type": "Feature",
  "properties": {
    "iso:country":"GB",
    "sg:address":"Birch Stables, Birch La",
    "sg:city":"Worcester",
    "sg:classifiers":[
        {
            "category":"Building & Trades",
            "subcategory":"Construction",
            "type":"Services"
        }
    ],
    "sg:phone":"+44 1905 20261",
    "sg:postcode":"WR8 9DN",
    "sg:province":"Gloucestershire",
    "sg:tags":[
        "roofing"
    ],
    "wof:name":"M R Roper",
    "wof:placetype":"venue"
},
  "geometry": {"coordinates":[-2.19832,52.10508],"type":"Point"}
}