{
  "type": "Feature",
  "properties": {
    "addr:full":"11a Sharoe Mount Avenue, Fulwood Preston Lancashire PR2 9HQ",
    "addr:housenumber":"11a",
    "addr:postcode":"pr2 9hq",
    "addr:street":"Sharoe Mount Avenue",
    "iso:country":"GB",
    "sg:address":"11a Sharoe Mount Avenue, Fulwood",
    "sg:city":"Preston",
    "sg:classifiers":[
        {
            "category":"Professional",
            "subcategory":"Engineering",
            "type":"Services"
        },
        {
            "category":"Building & Trades",
            "subcategory":"Electrical",
            "type":"Services"
        }
    ],
    "sg:postcode":"PR2 9HQ",
    "sg:province":"Lancashire",
    "sg:tags":[
        "engineer",
        "electrician",
        "contractor"
    ],
    "wof:name":"Gordon H Smith",
    "wof:placetype":"venue"
},
  "geometry": {"coordinates":[-2.700225,53.793121],"type":"Point"}
}