{
  "type": "Feature",
  "properties": {
    "addr:full":"1-3 Manor Place Bognor Regis West Sussex PO21 1TB",
    "addr:housenumber":"1-3",
    "addr:postcode":"po21 1tb",
    "addr:street":"Manor Place",
    "iso:country":"GB",
    "sg:address":"1-3 Manor Place",
    "sg:city":"Bognor Regis",
    "sg:classifiers":[
        {
            "category":"Restaurant",
            "type":"Food & Drink"
        }
    ],
    "sg:postcode":"PO21 1TB",
    "sg:province":"West Sussex",
    "wof:name":"Bon Appetit",
    "wof:placetype":"venue"
},
  "geometry": {"coordinates":[-0.6770570278,50.781578064],"type":"Point"}
}