{
  "type": "Feature",
  "properties": {
    "addr:full":"94 Central Street London Greater London EC1V 8AJ",
    "addr:housenumber":"94",
    "addr:postcode":"ec1v 8aj",
    "addr:street":"Central Street",
    "iso:country":"GB",
    "sg:address":"94 Central Street",
    "sg:city":"London",
    "sg:classifiers":[
        {
            "category":"Professional",
            "type":"Services"
        }
    ],
    "sg:phone":"+44 20 7250 1860",
    "sg:postcode":"EC1V 8AJ",
    "sg:province":"Greater London",
    "sg:tags":[
        "repair",
        "tech",
        "maintenance"
    ],
    "wof:name":"Computer Terminal Services Ltd.",
    "wof:placetype":"venue"
},
  "geometry": {"coordinates":[-0.0966250002,51.5273933411],"type":"Point"}
}