{
  "type": "Feature",
  "properties": {
    "iso:country":"GB",
    "sg:address":"70 Sullington Gardens",
    "sg:city":"Worthing",
    "sg:classifiers":[
        {
            "category":"Health Services",
            "subcategory":"Podiatrist",
            "type":"Services"
        }
    ],
    "sg:postcode":"BN14 0HS",
    "sg:province":"West Sussex",
    "sg:tags":[
        "podiatrists",
        "chiropodist"
    ],
    "wof:name":"Alsmeer Chiropody Service",
    "wof:placetype":"venue"
},
  "geometry": {"coordinates":[-0.398304,50.856586],"type":"Point"}
}