{
  "type": "Feature",
  "properties": {
    "addr:full":"White Hart Street, East Harling Norwich Norfolk NR16 2NE",
    "addr:postcode":"nr16 2ne",
    "addr:street":"Hart Street East;Norwich",
    "iso:country":"GB",
    "sg:address":"White Hart Street, East Harling",
    "sg:city":"Norwich",
    "sg:classifiers":[
        {
            "category":"Food & Beverages",
            "subcategory":"Liquor & Beverages",
            "type":"Retail Goods"
        },
        {
            "category":"Wholesale",
            "subcategory":"Wine & Distilled Alcoholic Beverages",
            "type":"Manufacturing & Wholesale Goods"
        }
    ],
    "sg:phone":"+44 1953 718605",
    "sg:postcode":"NR16 2NE",
    "sg:province":"Norfolk",
    "sg:tags":[
        "beer",
        "importers",
        "spirit",
        "wines"
    ],
    "wof:name":"William Mason Fine Wines Ltd",
    "wof:placetype":"venue"
},
  "geometry": {"coordinates":[0.9361420274,52.4406433105],"type":"Point"}
}