{
  "type": "Feature",
  "properties": {
    "addr:full":"58 Wickham Hill Hassocks East Sussex BN6 9NP",
    "addr:housenumber":"58",
    "addr:postcode":"bn6 9np",
    "addr:street":"Wickham Hill",
    "iso:country":"GB",
    "sg:address":"58 Wickham Hill",
    "sg:city":"Hassocks",
    "sg:classifiers":[
        {
            "category":"Building & Trades",
            "subcategory":"Equipment Rental",
            "type":"Services"
        }
    ],
    "sg:postcode":"BN6 9NP",
    "sg:province":"East Sussex",
    "sg:tags":[
        "hire",
        "catering"
    ],
    "wof:name":"Carolines",
    "wof:placetype":"venue"
},
  "geometry": {"coordinates":[-0.16143,50.926529],"type":"Point"}
}