{
  "type": "Feature",
  "properties": {
    "iso:country":"GB",
    "sg:address":"Care Of Education Gateway, 199 Nithsdale Road",
    "sg:city":"Glasgow",
    "sg:classifiers":[
        {
            "category":"Education",
            "subcategory":"Special Training",
            "type":"Public Place"
        }
    ],
    "sg:phone":"+44 141 422 2303",
    "sg:postcode":"G41 5EX",
    "sg:province":"Glasgow City",
    "sg:tags":[
        "product",
        "centre"
    ],
    "wof:name":"Work Experience Unit",
    "wof:placetype":"venue"
},
  "geometry": {"coordinates":[-4.285610199,55.8414802551],"type":"Point"}
}