{
  "type": "Feature",
  "properties": {
    "addr:full":"New Look House, Shawclough Road Rochdale Lancashire OL12 6HQ",
    "addr:postcode":"ol12 6hq",
    "addr:street":"Shawclough Road",
    "iso:country":"GB",
    "sg:address":"New Look House, Shawclough Road",
    "sg:city":"Rochdale",
    "sg:classifiers":[
        {
            "category":"Manufacturing",
            "subcategory":"Petroleum Products",
            "type":"Manufacturing & Wholesale Goods"
        }
    ],
    "sg:phone":"+44 1706 358879",
    "sg:postcode":"OL12 6HQ",
    "sg:province":"Lancashire",
    "sg:tags":[
        "double",
        "glazing"
    ],
    "wof:name":"New Look Replacement Windows Ltd.",
    "wof:placetype":"venue"
},
  "geometry": {"coordinates":[-2.1732320786,53.6310501099],"type":"Point"}
}