{
  "type": "Feature",
  "properties": {
    "addr:full":"233 Tamworth Rd Sutton Coldfield Staffordshire B75 6DX",
    "addr:housenumber":"233",
    "addr:postcode":"b75 6dx",
    "addr:street":"Tamworth Rd",
    "iso:country":"GB",
    "sg:address":"233 Tamworth Rd",
    "sg:city":"Sutton Coldfield",
    "sg:classifiers":[
        {
            "category":"Shopping",
            "subcategory":"Pharmacy",
            "type":"Retail Goods"
        }
    ],
    "sg:phone":"+44 121 323 4300",
    "sg:postcode":"B75 6DX",
    "sg:province":"Staffordshire",
    "sg:tags":[
        "pharmacist",
        "chemist"
    ],
    "wof:name":"Lloyds Chemist",
    "wof:placetype":"venue"
},
  "geometry": {"coordinates":[-1.804659,52.57851],"type":"Point"}
}