{
  "type": "Feature",
  "properties": {
    "iso:country":"GB",
    "sg:address":"109 Brixton Hill",
    "sg:city":"London",
    "sg:classifiers":[
        {
            "category":"Food & Beverages",
            "subcategory":"Meat & Fish",
            "type":"Retail Goods"
        }
    ],
    "sg:phone":"+44 20 8674 7754",
    "sg:postcode":"SW2 1AA",
    "sg:province":"Greater London",
    "sg:tags":[
        "chip"
    ],
    "wof:name":"Alberts Place",
    "wof:placetype":"venue"
},
  "geometry": {"coordinates":[-0.119597,51.454594],"type":"Point"}
}