{
  "type": "Feature",
  "properties": {
    "addr:full":"30 Purbeck Stantonbury Centre, Stantonbury Milton Keynes Buckinghamshire MK14 6BL",
    "addr:housenumber":"30;stantonbury",
    "addr:postcode":"mk14 6bl",
    "addr:street":"Purbeck",
    "iso:country":"GB",
    "sg:address":"30 Purbeck Stantonbury Centre, Stantonbury",
    "sg:city":"Milton Keynes",
    "sg:classifiers":[
        {
            "category":"Shopping",
            "subcategory":"Thrift Store",
            "type":"Retail Goods"
        }
    ],
    "sg:phone":"+44 1908 226415",
    "sg:postcode":"MK14 6BL",
    "sg:province":"Buckinghamshire",
    "sg:tags":[
        "shop",
        "charity"
    ],
    "wof:name":"Age Concern Mk Mind",
    "wof:placetype":"venue"
},
  "geometry": {"coordinates":[-0.7654790282,52.0645332336],"type":"Point"}
}