{
  "type": "Feature",
  "properties": {
    "addr:full":"6 Park Lane, Tilehurst Reading Berkshire RG31 5DL",
    "addr:housenumber":"6",
    "addr:postcode":"rg31 5dl",
    "addr:street":"Park Lane",
    "iso:country":"GB",
    "sg:address":"6 Park Lane, Tilehurst",
    "sg:city":"Reading",
    "sg:classifiers":[
        {
            "category":"Restaurant",
            "type":"Food & Drink"
        }
    ],
    "sg:phone":"+44 118 967 2710",
    "sg:postcode":"RG31 5DL",
    "sg:province":"Berkshire",
    "sg:tags":[
        "indian"
    ],
    "wof:name":"Bengal Cottage",
    "wof:placetype":"venue"
},
  "geometry": {"coordinates":[-1.044451952,51.4566116333],"type":"Point"}
}