{
  "type": "Feature",
  "properties": {
    "addr:full":"38 Taunton Rd Oldham Lancashire OL9 0BE",
    "addr:housenumber":"38",
    "addr:postcode":"ol9 0be",
    "addr:street":"Taunton Rd",
    "iso:country":"GB",
    "sg:address":"38 Taunton Rd",
    "sg:city":"Oldham",
    "sg:classifiers":[
        {
            "category":"Place Of Worship",
            "type":"Public Place"
        }
    ],
    "sg:phone":"+44 161 652 8527",
    "sg:postcode":"OL9 0BE",
    "sg:province":"Lancashire",
    "wof:name":"Chadderton Congregational Church",
    "wof:placetype":"venue"
},
  "geometry": {"coordinates":[-2.146682,53.553864],"type":"Point"}
}