{
  "type": "Feature",
  "properties": {
    "addr:full":"Park Farm, Little Somborne Stockbridge Hampshire SO20 6QT",
    "addr:housenumber":"somborne",
    "addr:postcode":"so20 6qt",
    "addr:street":"Park",
    "iso:country":"GB",
    "sg:address":"Park Farm, Little Somborne",
    "sg:city":"Stockbridge",
    "sg:classifiers":[
        {
            "category":"Farming",
            "subcategory":"Livestock Farm",
            "type":"Manufacturing & Wholesale Goods"
        }
    ],
    "sg:phone":"+44 1794 388330",
    "sg:postcode":"SO20 6QT",
    "sg:province":"Hampshire",
    "sg:tags":[
        "others"
    ],
    "wof:name":"Windover Farms Ltd.",
    "wof:placetype":"venue"
},
  "geometry": {"coordinates":[-1.4941020012,51.1142807007],"type":"Point"}
}