{
  "type": "Feature",
  "properties": {
    "addr:full":"Becket Ho, 1 Lambeth Palace Rd London Greater London SE1 7EU",
    "addr:housenumber":"1",
    "addr:postcode":"se1 7eu",
    "addr:street":"Lambeth Palace Rd",
    "iso:country":"GB",
    "sg:address":"Becket Ho, 1 Lambeth Palace Rd",
    "sg:city":"London",
    "sg:classifiers":[
        {
            "category":"Autos & Motor Vehicles",
            "subcategory":"Boat Sales",
            "type":"Retail Goods"
        }
    ],
    "sg:postcode":"SE1 7EU",
    "sg:province":"Greater London",
    "sg:tags":[
        "rustproofing"
    ],
    "wof:name":"Pava (Products) U K Ltd",
    "wof:placetype":"venue"
},
  "geometry": {"coordinates":[-0.1162099987,51.4999008179],"type":"Point"}
}