{
  "type": "Feature",
  "properties": {
    "iso:country":"GB",
    "sg:address":"Stirling Way, Northfields Indstl Est, Market Deeping",
    "sg:city":"Peterborough",
    "sg:classifiers":[
        {
            "category":"Freight",
            "type":"Transportation"
        }
    ],
    "sg:phone":"+44 1778 343211",
    "sg:postcode":"PE6 8LB",
    "sg:province":"Cambridgeshire",
    "sg:tags":[
        "forwarders"
    ],
    "wof:name":"Hereward Freight Group Ltd",
    "wof:placetype":"venue"
},
  "geometry": {"coordinates":[-0.314479,52.688316],"type":"Point"}
}