{
  "type": "Feature",
  "properties": {
    "addr:full":"Station Road Porthmadog Gwynedd LL49 9HT",
    "addr:postcode":"ll49 9ht",
    "addr:street":"Station Road",
    "iso:country":"GB",
    "sg:address":"Station Road",
    "sg:city":"Porthmadog",
    "sg:classifiers":[
        {
            "category":"Bars & Pubs",
            "type":"Food & Drink"
        }
    ],
    "sg:postcode":"LL49 9HT",
    "sg:province":"Gwynedd",
    "sg:tags":[
        "pubs",
        "inn"
    ],
    "wof:name":"The Queens Hotel",
    "wof:placetype":"venue"
},
  "geometry": {"coordinates":[-4.1329889297,52.9277381897],"type":"Point"}
}