{
  "type": "Feature",
  "properties": {
    "addr:full":"1 Wardrobe Place London Greater London EC4V 5AG",
    "addr:housenumber":"1",
    "addr:postcode":"ec4v 5ag",
    "addr:street":"Wardrobe Place",
    "iso:country":"GB",
    "sg:address":"1 Wardrobe Place",
    "sg:city":"London",
    "sg:classifiers":[
        {
            "category":"Professional",
            "subcategory":"Management & Consulting",
            "type":"Services"
        }
    ],
    "sg:phone":"+44 20 7489 9066",
    "sg:postcode":"EC4V 5AG",
    "sg:province":"Greater London",
    "sg:tags":[
        "consultant",
        "business"
    ],
    "wof:name":"Keith Boyfield Associates",
    "wof:placetype":"venue"
},
  "geometry": {"coordinates":[-0.100864,51.513004],"type":"Point"}
}