{
  "type": "Feature",
  "properties": {
    "addr:full":"Gordon Road, Curdridge Southampton Hampshire SO32 2BE",
    "addr:postcode":"so32 2be",
    "addr:street":"Gordon Road",
    "iso:country":"GB",
    "sg:address":"Gordon Road, Curdridge",
    "sg:city":"Southampton",
    "sg:classifiers":[
        {
            "category":"Government",
            "subcategory":"Post Office",
            "type":"Public Place"
        }
    ],
    "sg:phone":"+44 1489 782004",
    "sg:postcode":"SO32 2BE",
    "sg:province":"Hampshire",
    "wof:name":"Upper Curdridge Rural Post Office",
    "wof:placetype":"venue"
},
  "geometry": {"coordinates":[-1.2321380377,50.9245643616],"type":"Point"}
}