{
  "type": "Feature",
  "properties": {
    "addr:full":"53 Grosvenor St London Greater London W1K 3HU",
    "addr:housenumber":"53",
    "addr:postcode":"w1k 3hu",
    "addr:street":"Grosvenor St",
    "iso:country":"GB",
    "sg:address":"53 Grosvenor St",
    "sg:city":"London",
    "sg:classifiers":[
        {
            "category":"Professional",
            "subcategory":"Business Services",
            "type":"Services"
        }
    ],
    "sg:postcode":"W1K 3HU",
    "sg:province":"Greater London",
    "sg:tags":[
        "hospitality",
        "corporate"
    ],
    "wof:name":"Barrow Gordon Associates Ltd",
    "wof:placetype":"venue"
},
  "geometry": {"coordinates":[-0.1483,51.511391],"type":"Point"}
}