{
  "type": "Feature",
  "properties": {
    "addr:full":"Psp, 27 Old Gloucester St Bloomsbury Greater London WC1N 3AF",
    "addr:housenumber":"27",
    "addr:postcode":"wc1n 3af",
    "addr:street":"Old Gloucester St",
    "iso:country":"GB",
    "sg:address":"Psp, 27 Old Gloucester St",
    "sg:city":"Bloomsbury",
    "sg:classifiers":[
        {
            "category":"Personal",
            "subcategory":"Psychics & Astrologers",
            "type":"Services"
        }
    ],
    "sg:phone":"+44 20 8870 0230",
    "sg:postcode":"WC1N 3AF",
    "sg:province":"Greater London",
    "sg:tags":[
        "clairvoyant",
        "palmist"
    ],
    "wof:name":"Psychic Services",
    "wof:placetype":"venue"
},
  "geometry": {"coordinates":[-0.12215,51.520821],"type":"Point"}
}