{
  "type": "Feature",
  "properties": {
    "iso:country":"GB",
    "sg:address":"Ayot St Lawrence",
    "sg:city":"Welwyn",
    "sg:classifiers":[
        {
            "category":"Travel",
            "subcategory":"Hotels & Motels",
            "type":"Entertainment"
        }
    ],
    "sg:phone":"+44 1438 820250",
    "sg:postcode":"AL6 9BT",
    "sg:province":"Hertfordshire",
    "wof:name":"Brocket Arms The",
    "wof:placetype":"venue"
},
  "geometry": {"coordinates":[-0.228549,51.81126],"type":"Point"}
}