{
  "type": "Feature",
  "properties": {
    "addr:full":"Farleigh Court Rd Warlingham Kent CR6 9PX",
    "addr:postcode":"cr6 9px",
    "addr:street":"Farleigh Court Rd",
    "iso:country":"GB",
    "sg:address":"Farleigh Court Rd",
    "sg:city":"Warlingham",
    "sg:classifiers":[
        {
            "category":"Sports & Exercise",
            "subcategory":"Stables",
            "type":"Entertainment"
        }
    ],
    "sg:postcode":"CR6 9PX",
    "sg:province":"Kent",
    "sg:tags":[
        "education",
        "equestrian"
    ],
    "wof:name":"Baird,Deborah,",
    "wof:placetype":"venue"
},
  "geometry": {"coordinates":[-0.020224,51.321629],"type":"Point"}
}