{
  "type": "Feature",
  "properties": {
    "addr:full":"The Green, Bearsted Maidstone Kent ME14 4EJ",
    "addr:postcode":"me14 4ej",
    "addr:street":"Green",
    "iso:country":"GB",
    "sg:address":"The Green, Bearsted",
    "sg:city":"Maidstone",
    "sg:classifiers":[
        {
            "category":"Bars & Pubs",
            "type":"Food & Drink"
        }
    ],
    "sg:phone":"+44 1622 736458",
    "sg:postcode":"ME14 4EJ",
    "sg:province":"Kent",
    "sg:tags":[
        "pubs",
        "inn"
    ],
    "wof:name":"Royal Oak",
    "wof:placetype":"venue"
},
  "geometry": {"coordinates":[0.5740839839,51.2672576904],"type":"Point"}
}