{
  "type": "Feature",
  "properties": {
    "iso:country":"GB",
    "sg:address":"432 Ashley Road, Parkstone",
    "sg:city":"Poole",
    "sg:classifiers":[
        {
            "category":"Personal",
            "subcategory":"Beauty Salon",
            "type":"Services"
        }
    ],
    "sg:phone":"+44 1202 742766",
    "sg:postcode":"BH14 0AA",
    "sg:province":"Dorset",
    "sg:tags":[
        "unisex",
        "hairdresser"
    ],
    "wof:name":"Cutting Crew Hair & Beauty",
    "wof:placetype":"venue"
},
  "geometry": {"coordinates":[-1.941523,50.729095],"type":"Point"}
}