{
  "type": "Feature",
  "properties": {
    "addr:full":"Unit 27b, Parkrose Industrial Estate Smethwick West Midlands B66 2DZ",
    "addr:housenumber":"unit 27b",
    "addr:postcode":"b66 2dz",
    "addr:street":"Industrial Estate Smethwick",
    "iso:country":"GB",
    "sg:address":"Unit 27b, Parkrose Industrial Estate",
    "sg:city":"Smethwick",
    "sg:classifiers":[
        {
            "category":"Manufacturing",
            "subcategory":"Building Materials",
            "type":"Manufacturing & Wholesale Goods"
        }
    ],
    "sg:phone":"+44 121 555 6397",
    "sg:postcode":"B66 2DZ",
    "sg:province":"West Midlands",
    "sg:tags":[
        "tube",
        "manipulator",
        "bender"
    ],
    "wof:name":"Cook Tube Forming Ltd.",
    "wof:placetype":"venue"
},
  "geometry": {"coordinates":[-1.9494080544,52.4885826111],"type":"Point"}
}