{
  "type": "Feature",
  "properties": {
    "addr:full":"44 Kirkgate Bradford West Yorkshire BD1 1QT",
    "addr:housenumber":"44",
    "addr:postcode":"bd1 1qt",
    "addr:street":"Kirkgate Bradford West",
    "iso:country":"GB",
    "sg:address":"44 Kirkgate",
    "sg:city":"Bradford",
    "sg:classifiers":[
        {
            "category":"Communications",
            "subcategory":"Film & Video Production",
            "type":"Services"
        }
    ],
    "sg:phone":"+44 1274 726912",
    "sg:postcode":"BD1 1QT",
    "sg:province":"West Yorkshire",
    "sg:tags":[
        "tv"
    ],
    "wof:name":"Radio Rentals",
    "wof:placetype":"venue"
},
  "geometry": {"coordinates":[-1.7557309866,53.7942390442],"type":"Point"}
}