{
  "type": "Feature",
  "properties": {
    "iso:country":"GB",
    "sg:address":"Bowness-on-windermerhamilton",
    "sg:city":"Windermere",
    "sg:classifiers":[
        {
            "category":"Travel",
            "subcategory":"Hotels & Motels",
            "type":"Entertainment"
        }
    ],
    "sg:phone":"+44 15394 46226",
    "sg:postcode":"LA23 3HH",
    "sg:province":"Cumbria",
    "wof:name":"Burnhow Hotel",
    "wof:placetype":"venue"
},
  "geometry": {"coordinates":[-2.9224359989,54.3628692627],"type":"Point"}
}