{
  "type": "Feature",
  "properties": {
    "iso:country":"GB",
    "sg:address":"10-14 Cambridge Street",
    "sg:city":"Aylesbury",
    "sg:classifiers":[
        {
            "category":"Banks & Credit Unions",
            "subcategory":"Financial Services",
            "type":"Services"
        }
    ],
    "sg:phone":"+44 1296 431671",
    "sg:postcode":"HP20 1RS",
    "sg:province":"Buckinghamshire",
    "sg:tags":[
        "consultant"
    ],
    "wof:name":"Avco Trust Ltd.",
    "wof:placetype":"venue"
},
  "geometry": {"coordinates":[-0.8125100136,51.8172302246],"type":"Point"}
}