{
  "type": "Feature",
  "properties": {
    "addr:full":"Grn Keeper, Hobson Newcastle-upon-tyne Durham NE16 6BZ",
    "addr:postcode":"ne16 6bz",
    "addr:street":"Grn Keeper",
    "iso:country":"GB",
    "sg:address":"Grn Keeper, Hobson",
    "sg:city":"Newcastle-upon-tyne",
    "sg:classifiers":[
        {
            "category":"Sports & Exercise",
            "subcategory":"Golf",
            "type":"Entertainment"
        }
    ],
    "sg:phone":"+44 1207 270790",
    "sg:postcode":"NE16 6BZ",
    "sg:province":"Durham",
    "sg:tags":[
        "club",
        "course"
    ],
    "wof:name":"Derwentside District Council",
    "wof:placetype":"venue"
},
  "geometry": {"coordinates":[-1.73033,54.89595],"type":"Point"}
}