{
  "type": "Feature",
  "properties": {
    "addr:full":"159 Acre Lane London Greater London SW2 5UA",
    "addr:housenumber":"159",
    "addr:postcode":"sw2 5ua",
    "addr:street":"Acre Lane",
    "iso:country":"GB",
    "sg:address":"159 Acre Lane",
    "sg:city":"London",
    "sg:classifiers":[
        {
            "category":"Wholesale",
            "subcategory":"Books, Periodicals, & Newspapers",
            "type":"Manufacturing & Wholesale Goods"
        }
    ],
    "sg:phone":"+44 20 7274 9381",
    "sg:postcode":"SW2 5UA",
    "sg:province":"Greater London",
    "sg:tags":[
        "publishing"
    ],
    "wof:name":"Houni Ltd.",
    "wof:placetype":"venue"
},
  "geometry": {"coordinates":[-0.1289509982,51.459651947],"type":"Point"}
}