{
  "type": "Feature",
  "properties": {
    "addr:full":"Mahn Ho, Spexhall Halesworth Suffolk IP19 0RJ",
    "addr:postcode":"ip19 0rj",
    "iso:country":"GB",
    "sg:address":"Mahn Ho, Spexhall",
    "sg:city":"Halesworth",
    "sg:classifiers":[
        {
            "category":"Building & Trades",
            "subcategory":"Construction",
            "type":"Services"
        }
    ],
    "sg:phone":"+44 1986 872499",
    "sg:postcode":"IP19 0RJ",
    "sg:province":"Suffolk",
    "sg:tags":[
        "conservation",
        "craft",
        "thatching"
    ],
    "wof:name":"Thatchering",
    "wof:placetype":"venue"
},
  "geometry": {"coordinates":[1.492938,52.367741],"type":"Point"}
}