{
  "type": "Feature",
  "properties": {
    "iso:country":"GB",
    "sg:address":"181 Charles Street",
    "sg:city":"Leicester",
    "sg:classifiers":[
        {
            "category":"Professional",
            "subcategory":"Printing & Photocopies",
            "type":"Services"
        }
    ],
    "sg:phone":"+44 116 247 1479",
    "sg:postcode":"LE1 1LA",
    "sg:province":"Leicestershire",
    "sg:tags":[
        "printer"
    ],
    "wof:name":"Alphagraphics",
    "wof:placetype":"venue"
},
  "geometry": {"coordinates":[-1.1279089451,52.6333808899],"type":"Point"}
}