{
  "type": "Feature",
  "properties": {
    "addr:full":"9 The Shrubberies, George Lane London Greater London E18 1BD",
    "addr:housenumber":"9",
    "addr:postcode":"e18 1bd",
    "addr:street":"The Shrubberies George Lane",
    "iso:country":"GB",
    "sg:address":"9 The Shrubberies, George Lane",
    "sg:city":"London",
    "sg:classifiers":[
        {
            "category":"Professional",
            "subcategory":"Computer Services",
            "type":"Services"
        }
    ],
    "sg:postcode":"E18 1BD",
    "sg:province":"Greater London",
    "sg:tags":[
        "system",
        "software"
    ],
    "wof:name":"Robsoft Limited",
    "wof:placetype":"venue"
},
  "geometry": {"coordinates":[0.0249199998,51.5943107605],"type":"Point"}
}