{
  "type": "Feature",
  "properties": {
    "addr:full":"Airedale Trading Park, Skipton Rd, Cross Hills Keighley North Yorkshire BD20 7DS",
    "addr:postcode":"bd20 7ds",
    "addr:street":"Skipton Rd",
    "iso:country":"GB",
    "sg:address":"Airedale Trading Park, Skipton Rd, Cross Hills",
    "sg:city":"Keighley",
    "sg:classifiers":[
        {
            "category":"Autos & Motor Vehicles",
            "subcategory":"Automobile Sales",
            "type":"Retail Goods"
        }
    ],
    "sg:phone":"+44 1535 637878",
    "sg:postcode":"BD20 7DS",
    "sg:province":"North Yorkshire",
    "wof:name":"County Cab Co",
    "wof:placetype":"venue"
},
  "geometry": {"coordinates":[-1.9863669872,53.9033203125],"type":"Point"}
}