{
  "type": "Feature",
  "properties": {
    "iso:country":"GB",
    "sg:address":"49 Rowanfield Road",
    "sg:city":"Cheltenham",
    "sg:classifiers":[
        {
            "category":"Shopping",
            "subcategory":"Baby Store",
            "type":"Retail Goods"
        }
    ],
    "sg:postcode":"GL51 8AF",
    "sg:province":"Gloucestershire",
    "sg:tags":[
        "babywear",
        "childrens"
    ],
    "wof:name":"Hangers",
    "wof:placetype":"venue"
},
  "geometry": {"coordinates":[-2.1006989479,51.9009819031],"type":"Point"}
}