{
  "type": "Feature",
  "properties": {
    "addr:full":"Crowley Works, Swalwell Newcastle-upon-tyne Durham NE16 3AF",
    "addr:postcode":"ne16 3af",
    "iso:country":"GB",
    "sg:address":"Crowley Works, Swalwell",
    "sg:city":"Newcastle-upon-tyne",
    "sg:classifiers":[
        {
            "category":"Manufacturing",
            "subcategory":"Building Materials",
            "type":"Manufacturing & Wholesale Goods"
        }
    ],
    "sg:phone":"+44 191 488 1722",
    "sg:postcode":"NE16 3AF",
    "sg:province":"Durham",
    "sg:tags":[
        "concrete",
        "product"
    ],
    "wof:name":"Bespoke Concrete Products Ltd.",
    "wof:placetype":"venue"
},
  "geometry": {"coordinates":[-1.6776950359,54.9539833069],"type":"Point"}
}