{
  "type": "Feature",
  "properties": {
    "addr:full":"Miresfield, Malham Skipton Lancashire BD23 4DA",
    "addr:postcode":"bd23 4da",
    "addr:street":"Malham",
    "iso:country":"GB",
    "sg:address":"Miresfield, Malham",
    "sg:city":"Skipton",
    "sg:classifiers":[
        {
            "category":"Travel",
            "subcategory":"Hotels & Motels",
            "type":"Entertainment"
        }
    ],
    "sg:postcode":"BD23 4DA",
    "sg:province":"Lancashire",
    "sg:tags":[
        "house",
        "guest"
    ],
    "wof:name":"Miresfield Farm Guest House",
    "wof:placetype":"venue"
},
  "geometry": {"coordinates":[-2.1537189484,54.0630645752],"type":"Point"}
}