{
  "type": "Feature",
  "properties": {
    "iso:country":"GB",
    "sg:address":"The Clock, Cransford, Houselow Road",
    "sg:city":"Saxmundham",
    "sg:classifiers":[
        {
            "category":"Real Estate",
            "subcategory":"Developer",
            "type":"Services"
        }
    ],
    "sg:phone":"+44 1728 663512",
    "sg:postcode":"IP17 2EA",
    "sg:province":"Suffolk",
    "sg:tags":[
        "property"
    ],
    "wof:name":"Timepiece Developments Ltd",
    "wof:placetype":"venue"
},
  "geometry": {"coordinates":[1.4895329475,52.2167129517],"type":"Point"}
}