{
  "type": "Feature",
  "properties": {
    "addr:full":"23 Queen Street Deal Kent CT14 6ET",
    "addr:housenumber":"23",
    "addr:postcode":"ct14 6et",
    "addr:street":"Queen Street Deal",
    "iso:country":"GB",
    "sg:address":"23 Queen Street",
    "sg:city":"Deal",
    "sg:classifiers":[
        {
            "category":"Home & Garden",
            "subcategory":"Home Furnishings",
            "type":"Retail Goods"
        },
        {
            "category":"Home & Garden",
            "subcategory":"Furniture",
            "type":"Retail Goods"
        }
    ],
    "sg:phone":"+44 1304 381012",
    "sg:postcode":"CT14 6ET",
    "sg:province":"Kent",
    "sg:tags":[
        "furnishers",
        "planner",
        "kitchen"
    ],
    "wof:name":"Bhj Bush",
    "wof:placetype":"venue"
},
  "geometry": {"coordinates":[1.4018690586,51.2231750488],"type":"Point"}
}