{
  "type": "Feature",
  "properties": {
    "addr:full":"21 Lesnewth, Biscovey Par Cornwall PL24 2DE",
    "addr:housenumber":"21",
    "addr:postcode":"pl24 2de",
    "addr:street":"Lesnewth Biscovey Par",
    "iso:country":"GB",
    "sg:address":"21 Lesnewth, Biscovey",
    "sg:city":"Par",
    "sg:classifiers":[
        {
            "category":"Military Area",
            "subcategory":"Air Force Base",
            "type":"Public Place"
        }
    ],
    "sg:postcode":"PL24 2DE",
    "sg:province":"Cornwall",
    "sg:tags":[
        "taxi",
        "hire",
        "private"
    ],
    "wof:name":"Coombe,Samuel,",
    "wof:placetype":"venue"
},
  "geometry": {"coordinates":[-4.720822,50.347965],"type":"Point"}
}