{
  "type": "Feature",
  "properties": {
    "addr:full":"146 Pottery Road Oldbury West Midlands B68 9HD",
    "addr:housenumber":"146",
    "addr:postcode":"b68 9hd",
    "addr:street":"Pottery Road",
    "iso:country":"GB",
    "sg:address":"146 Pottery Road",
    "sg:city":"Oldbury",
    "sg:classifiers":[
        {
            "category":"Personal",
            "type":"Services"
        },
        {
            "category":"Government",
            "subcategory":"Customs House",
            "type":"Public Place"
        }
    ],
    "sg:postcode":"B68 9HD",
    "sg:province":"West Midlands",
    "sg:tags":[
        "clearance"
    ],
    "wof:name":"Warley House Clearances",
    "wof:placetype":"venue"
},
  "geometry": {"coordinates":[-1.990021944,52.4735221863],"type":"Point"}
}