{
  "type": "Feature",
  "properties": {
    "iso:country":"GB",
    "sg:address":"11 Woodsome Avenue",
    "sg:city":"Mirfield",
    "sg:classifiers":[
        {
            "category":"Professional",
            "subcategory":"Accounting & Tax Preparation",
            "type":"Services"
        }
    ],
    "sg:postcode":"WF14 9QX",
    "sg:province":"West Yorkshire",
    "sg:tags":[
        "accountant"
    ],
    "wof:name":"Brian Lomas & Co",
    "wof:placetype":"venue"
},
  "geometry": {"coordinates":[-1.711371,53.68383],"type":"Point"}
}