{
  "type": "Feature",
  "properties": {
    "iso:country":"GB",
    "sg:address":"54 The Dingle, Haslington",
    "sg:city":"Crewe",
    "sg:classifiers":[
        {
            "category":"Building & Trades",
            "subcategory":"Construction",
            "type":"Services"
        }
    ],
    "sg:phone":"+44 1270 583988",
    "sg:postcode":"CW1 5SD",
    "sg:province":"Cheshire",
    "sg:tags":[
        "builder"
    ],
    "wof:name":"Alan Bates",
    "wof:placetype":"venue"
},
  "geometry": {"coordinates":[-2.395043,53.105495],"type":"Point"}
}