{
  "type": "Feature",
  "properties": {
    "addr:full":"43 Norwich Avenue West Bournemouth Dorset BH2 6AJ",
    "addr:housenumber":"43",
    "addr:postcode":"bh2 6aj",
    "addr:street":"Norwich Avenue West",
    "iso:country":"GB",
    "sg:address":"43 Norwich Avenue West",
    "sg:city":"Bournemouth",
    "sg:classifiers":[
        {
            "category":"Autos & Motor Vehicles",
            "subcategory":"Automobile Sales",
            "type":"Retail Goods"
        }
    ],
    "sg:phone":"+44 1202 555767",
    "sg:postcode":"BH2 6AJ",
    "sg:province":"Dorset",
    "sg:tags":[
        "commercial"
    ],
    "wof:name":"Richard Dean",
    "wof:placetype":"venue"
},
  "geometry": {"coordinates":[-1.890339,50.721401],"type":"Point"}
}