{
  "type": "Feature",
  "properties": {
    "addr:full":"Rear Of Kings Garage, Market Street, Shipdham Thetford Norfolk IP25 7LZ",
    "addr:housenumber":"rear of",
    "addr:postcode":"ip25 7lz",
    "addr:street":"Market Street",
    "iso:country":"GB",
    "sg:address":"Rear Of Kings Garage, Market Street, Shipdham",
    "sg:city":"Thetford",
    "sg:classifiers":[
        {
            "category":"Autos & Motor Vehicles",
            "subcategory":"Motorcycle Sales",
            "type":"Retail Goods"
        }
    ],
    "sg:phone":"+44 1362 821263",
    "sg:postcode":"IP25 7LZ",
    "sg:province":"Norfolk",
    "sg:tags":[
        "scooter",
        "cycle"
    ],
    "wof:name":"J C Walker Motorcycle Engineering",
    "wof:placetype":"venue"
},
  "geometry": {"coordinates":[0.8974660039,52.629940033],"type":"Point"}
}