{
  "type": "Feature",
  "properties": {
    "addr:full":"Glengallan Road Oban Argyll and Bute PA34 4HH",
    "addr:postcode":"pa34 4hh",
    "addr:street":"Glengallan Road",
    "iso:country":"GB",
    "sg:address":"Glengallan Road",
    "sg:city":"Oban",
    "sg:classifiers":[
        {
            "category":"Health Services",
            "subcategory":"Hospital",
            "type":"Services"
        }
    ],
    "sg:phone":"+44 1631 567500",
    "sg:postcode":"PA34 4HH",
    "sg:province":"Argyll and Bute",
    "wof:name":"Lorn & Islands District General Hospital",
    "wof:placetype":"venue"
},
  "geometry": {"coordinates":[-5.469119072,56.4079818726],"type":"Point"}
}