{
  "type": "Feature",
  "properties": {
    "addr:full":"6 The Rows Harlow Essex CM20 1BZ",
    "addr:housenumber":"6",
    "addr:postcode":"cm20 1bz",
    "addr:street":"The Rows",
    "iso:country":"GB",
    "sg:address":"6 The Rows",
    "sg:city":"Harlow",
    "sg:classifiers":[
        {
            "category":"Manufacturing",
            "subcategory":"Petroleum Products",
            "type":"Manufacturing & Wholesale Goods"
        }
    ],
    "sg:phone":"+44 1279 444211",
    "sg:postcode":"CM20 1BZ",
    "sg:province":"Essex",
    "sg:tags":[
        "double",
        "glazing"
    ],
    "wof:name":"Zenith Windows",
    "wof:placetype":"venue"
},
  "geometry": {"coordinates":[0.09343,51.771095],"type":"Point"}
}