{
  "type": "Feature",
  "properties": {
    "addr:full":"Technical Centre, Tring Road Halton Aylesbury Buckinghamshire HP22 5PJ",
    "addr:postcode":"hp22 5pj",
    "addr:street":"Tring Road",
    "iso:country":"GB",
    "sg:address":"Technical Centre, Tring Road Halton",
    "sg:city":"Aylesbury",
    "sg:classifiers":[
        {
            "category":"Museum",
            "subcategory":"Art Museum",
            "type":"Entertainment"
        }
    ],
    "sg:phone":"+44 1296 696012",
    "sg:postcode":"HP22 5PJ",
    "sg:province":"Buckinghamshire",
    "sg:tags":[
        "gallery"
    ],
    "wof:name":"Buckinghamshire County Museum & Roald Dahl Gallery",
    "wof:placetype":"venue"
},
  "geometry": {"coordinates":[-0.734823,51.782345],"type":"Point"}
}