{
  "type": "Feature",
  "properties": {
    "iso:country":"GB",
    "sg:address":"12 Richmond St",
    "sg:city":"Bristol",
    "sg:classifiers":[
        {
            "category":"Building & Trades",
            "subcategory":"Construction",
            "type":"Services"
        }
    ],
    "sg:phone":"+44 117 966 2609",
    "sg:postcode":"BS3 4TQ",
    "sg:province":"City of Bristol",
    "sg:tags":[
        "builder"
    ],
    "wof:name":"Euro Builders",
    "wof:placetype":"venue"
},
  "geometry": {"coordinates":[-2.581568,51.444126],"type":"Point"}
}