{
  "type": "Feature",
  "properties": {
    "iso:country":"GB",
    "sg:address":"43 Armingford Crescent, Melbourn",
    "sg:city":"Royston",
    "sg:classifiers":[
        {
            "category":"Sports & Exercise",
            "subcategory":"Sports Center",
            "type":"Entertainment"
        }
    ],
    "sg:phone":"+44 1763 260770",
    "sg:postcode":"SG8 6NG",
    "sg:province":"Bedfordshire",
    "sg:tags":[
        "shop",
        "good"
    ],
    "wof:name":"Roc Sport",
    "wof:placetype":"venue"
},
  "geometry": {"coordinates":[0.0277280007,52.0868225098],"type":"Point"}
}