{
  "type": "Feature",
  "properties": {
    "addr:full":"Reeds Farm, Reeds Lane Rainford St Helens Lancashire WA11 7JN",
    "addr:postcode":"wa11 7jn",
    "addr:street":"Reeds Lane",
    "iso:country":"GB",
    "sg:address":"Reeds Farm, Reeds Lane Rainford",
    "sg:city":"St Helens",
    "sg:classifiers":[
        {
            "category":"Farming",
            "subcategory":"Livestock Farm",
            "type":"Manufacturing & Wholesale Goods"
        }
    ],
    "sg:phone":"+44 1744 882081",
    "sg:postcode":"WA11 7JN",
    "sg:province":"Lancashire",
    "sg:tags":[
        "others"
    ],
    "wof:name":"J B Rose",
    "wof:placetype":"venue"
},
  "geometry": {"coordinates":[-2.7935700417,53.4894485474],"type":"Point"}
}