{
  "type": "Feature",
  "properties": {
    "iso:country":"GB",
    "sg:address":"3 North Brook Farm, Titore Lane",
    "sg:city":"Worthing",
    "sg:classifiers":[
        {
            "category":"Recreation",
            "subcategory":"Water Park",
            "type":"Entertainment"
        }
    ],
    "sg:postcode":"BN12 6NZ",
    "sg:province":"West Sussex",
    "sg:tags":[
        "sport"
    ],
    "wof:name":"Sailboard Repair Centre",
    "wof:placetype":"venue"
},
  "geometry": {"coordinates":[-0.4350799918,50.8280715942],"type":"Point"}
}