{
  "type": "Feature",
  "properties": {
    "addr:full":"5 Eastgate St Gloucester Gloucestershire GL1 1NS",
    "addr:housenumber":"5",
    "addr:postcode":"gl1 1ns",
    "addr:street":"Eastgate St",
    "iso:country":"GB",
    "sg:address":"5 Eastgate St",
    "sg:city":"Gloucester",
    "sg:classifiers":[
        {
            "category":"Banks & Credit Unions",
            "subcategory":"Financial Services",
            "type":"Services"
        }
    ],
    "sg:phone":"+44 1452 410035",
    "sg:postcode":"GL1 1NS",
    "sg:province":"Gloucestershire",
    "sg:tags":[
        "building",
        "society"
    ],
    "wof:name":"Alliance & Leicester plc",
    "wof:placetype":"venue"
},
  "geometry": {"coordinates":[-2.2439219952,51.8642196655],"type":"Point"}
}