{
  "type": "Feature",
  "properties": {
    "addr:full":"Unit 5-6, The Woodland Centre, Whitesmith Lewes East Sussex BN8 6JB",
    "addr:housenumber":"unit 5-6",
    "addr:postcode":"bn8 6jb",
    "addr:street":"Woodland Centre",
    "iso:country":"GB",
    "sg:address":"Unit 5-6, The Woodland Centre, Whitesmith",
    "sg:city":"Lewes",
    "sg:classifiers":[
        {
            "category":"Manufacturing",
            "subcategory":"Lumber",
            "type":"Manufacturing & Wholesale Goods"
        }
    ],
    "sg:phone":"+44 1825 872025",
    "sg:postcode":"BN8 6JB",
    "sg:province":"East Sussex",
    "sg:tags":[
        "importer",
        "merchants",
        "agent",
        "timber"
    ],
    "wof:name":"E C Forest Products Ltd.",
    "wof:placetype":"venue"
},
  "geometry": {"coordinates":[0.171365,50.903675],"type":"Point"}
}