{
  "type": "Feature",
  "properties": {
    "iso:country":"GB",
    "sg:address":"325 Green Street, Upton Park",
    "sg:city":"London",
    "sg:classifiers":[
        {
            "category":"Shopping",
            "subcategory":"Pharmacy",
            "type":"Retail Goods"
        }
    ],
    "sg:phone":"+44 20 8503 5061",
    "sg:postcode":"E13 9AR",
    "sg:province":"Greater London",
    "sg:tags":[
        "store",
        "drug",
        "outlet"
    ],
    "wof:name":"Superdrug Stores plc",
    "wof:placetype":"venue"
},
  "geometry": {"coordinates":[0.035079,51.536648],"type":"Point"}
}