{
  "type": "Feature",
  "properties": {
    "addr:full":"Bourtonfields Farm, Southam Road Banbury Northamptonshire OX17 1AS",
    "addr:postcode":"ox17 1as",
    "addr:street":"Southam Road",
    "iso:country":"GB",
    "sg:address":"Bourtonfields Farm, Southam Road",
    "sg:city":"Banbury",
    "sg:classifiers":[
        {
            "category":"Travel",
            "subcategory":"Hotels & Motels",
            "type":"Entertainment"
        },
        {
            "category":"Farming",
            "subcategory":"Livestock Farm",
            "type":"Manufacturing & Wholesale Goods"
        }
    ],
    "sg:phone":"+44 1295 750254",
    "sg:postcode":"OX17 1AS",
    "sg:province":"Northamptonshire",
    "sg:tags":[
        "house",
        "guest",
        "others"
    ],
    "wof:name":"Cecil A & Ann Hall",
    "wof:placetype":"venue"
},
  "geometry": {"coordinates":[-1.35036,52.11198],"type":"Point"}
}