{
  "type": "Feature",
  "properties": {
    "addr:full":"8 Fore Street, Lower Darwen Darwen Lancashire BB3 0QD",
    "addr:housenumber":"8",
    "addr:postcode":"bb3 0qd",
    "addr:street":"Fore Street",
    "iso:country":"GB",
    "sg:address":"8 Fore Street, Lower Darwen",
    "sg:city":"Darwen",
    "sg:classifiers":[
        {
            "category":"Fast Food",
            "type":"Food & Drink"
        }
    ],
    "sg:phone":"+44 1254 676112",
    "sg:postcode":"BB3 0QD",
    "sg:province":"Lancashire",
    "sg:tags":[
        "away",
        "meal",
        "outlet",
        "take"
    ],
    "wof:name":"Crispy Cob",
    "wof:placetype":"venue"
},
  "geometry": {"coordinates":[-2.474495,53.721493],"type":"Point"}
}