{
  "type": "Feature",
  "properties": {
    "addr:full":"211 Aldborough Road South Ilford Essex IG3 8HY",
    "addr:housenumber":"211",
    "addr:postcode":"ig3 8hy",
    "addr:street":"Aldborough Road South",
    "iso:country":"GB",
    "sg:address":"211 Aldborough Road South",
    "sg:city":"Ilford",
    "sg:classifiers":[
        {
            "category":"Place Of Worship",
            "type":"Public Place"
        }
    ],
    "sg:phone":"+44 20 8590 3288",
    "sg:postcode":"IG3 8HY",
    "sg:province":"Essex",
    "wof:name":"Seven Kings United Free Church",
    "wof:placetype":"venue"
},
  "geometry": {"coordinates":[0.095178,51.569923],"type":"Point"}
}