{
  "type": "Feature",
  "properties": {
    "iso:country":"GB",
    "sg:address":"300 Bole Hill Rd",
    "sg:city":"Sheffield",
    "sg:classifiers":[
        {
            "category":"Professional",
            "subcategory":"Computer Services",
            "type":"Services"
        }
    ],
    "sg:phone":"+44 114 251 7772",
    "sg:postcode":"S6 5DF",
    "sg:province":"South Yorkshire",
    "sg:tags":[
        "consultant"
    ],
    "wof:name":"Information Management Solutions",
    "wof:placetype":"venue"
},
  "geometry": {"coordinates":[-1.512539,53.390816],"type":"Point"}
}