{
  "type": "Feature",
  "properties": {
    "iso:country":"GB",
    "sg:address":"9 Jarvis St",
    "sg:city":"Leicester",
    "sg:classifiers":[
        {
            "category":"Autos & Motor Vehicles",
            "subcategory":"Motorcycle Sales",
            "type":"Retail Goods"
        }
    ],
    "sg:postcode":"LE3 5BN",
    "sg:province":"Leicestershire",
    "sg:tags":[
        "component"
    ],
    "wof:name":"Burdett,Nigel,",
    "wof:placetype":"venue"
},
  "geometry": {"coordinates":[-1.1437020302,52.6376304626],"type":"Point"}
}