{
  "type": "Feature",
  "properties": {
    "addr:full":"53 Crown Street Brentwood Essex CM14 4BD",
    "addr:housenumber":"53",
    "addr:postcode":"cm14 4bd",
    "addr:street":"Crown Street",
    "iso:country":"GB",
    "sg:address":"53 Crown Street",
    "sg:city":"Brentwood",
    "sg:classifiers":[
        {
            "category":"Real Estate",
            "subcategory":"Surveying",
            "type":"Services"
        }
    ],
    "sg:phone":"+44 1708 738877",
    "sg:postcode":"CM14 4BD",
    "sg:province":"Essex",
    "sg:tags":[
        "surveyor",
        "marine"
    ],
    "wof:name":"Vathek (Marine) Ltd.",
    "wof:placetype":"venue"
},
  "geometry": {"coordinates":[0.3010999858,51.6183128357],"type":"Point"}
}