{
  "type": "Feature",
  "properties": {
    "iso:country":"GB",
    "sg:address":"Spencer St",
    "sg:city":"Leamington Spa",
    "sg:classifiers":[
        {
            "category":"Organizations",
            "subcategory":"Membership Organization",
            "type":"Services"
        }
    ],
    "sg:phone":"+44 1926 426348",
    "sg:postcode":"CV31 3NF",
    "sg:province":"Warwickshire",
    "sg:tags":[
        "club"
    ],
    "wof:name":"Gala Clubs",
    "wof:placetype":"venue"
},
  "geometry": {"coordinates":[-1.533339,52.28577],"type":"Point"}
}