{
  "type": "Feature",
  "properties": {
    "iso:country":"GB",
    "sg:address":"144 Fernhill Rd",
    "sg:city":"Oxford",
    "sg:classifiers":[
        {
            "category":"Professional",
            "subcategory":"Engineering",
            "type":"Services"
        }
    ],
    "sg:phone":"+44 1865 777116",
    "sg:postcode":"OX4 2JR",
    "sg:province":"Oxfordshire",
    "sg:tags":[
        "gas",
        "engineer"
    ],
    "wof:name":"Hazell & Edwards Plumbers Extraordinare",
    "wof:placetype":"venue"
},
  "geometry": {"coordinates":[-1.201688,51.733532],"type":"Point"}
}