{
  "type": "Feature",
  "properties": {
    "addr:full":"Room 910 Lloyds 1986 Building, 1 Lime Street London Greater London EC3M 7DQ",
    "addr:housenumber":"910;1986;1",
    "addr:postcode":"ec3m 7dq",
    "addr:street":"Lloyds;Lime Street",
    "iso:country":"GB",
    "sg:address":"Room 910 Lloyds 1986 Building, 1 Lime Street",
    "sg:city":"London",
    "sg:classifiers":[
        {
            "category":"Manufacturing",
            "subcategory":"Tools & Machinery",
            "type":"Manufacturing & Wholesale Goods"
        },
        {
            "category":"Professional",
            "subcategory":"Lawyer & Legal Services",
            "type":"Services"
        }
    ],
    "sg:phone":"+44 20 7929 5474",
    "sg:postcode":"EC3M 7DQ",
    "sg:province":"Greater London",
    "sg:tags":[
        "society",
        "friendly",
        "solicitor"
    ],
    "wof:name":"M C Kershaw & Co.",
    "wof:placetype":"venue"
},
  "geometry": {"coordinates":[-0.0827400014,51.5122909546],"type":"Point"}
}