{
  "type": "Feature",
  "properties": {
    "iso:country":"GB",
    "sg:address":"Minerva House, 16 Greek Street",
    "sg:city":"Leeds",
    "sg:classifiers":[
        {
            "category":"Restaurant",
            "type":"Food & Drink"
        }
    ],
    "sg:phone":"+44 113 243 0905",
    "sg:postcode":"LS1 5RU",
    "sg:province":"West Yorkshire",
    "wof:name":"Bibis Restaurants Ltd.",
    "wof:placetype":"venue"
},
  "geometry": {"coordinates":[-1.5488890409,53.7982711792],"type":"Point"}
}