{
  "type": "Feature",
  "properties": {
    "addr:full":"200 North Walls Stafford Staffordshire ST16 3AD",
    "addr:housenumber":"200",
    "addr:postcode":"st16 3ad",
    "addr:street":"North Walls",
    "iso:country":"GB",
    "sg:address":"200 North Walls",
    "sg:city":"Stafford",
    "sg:classifiers":[
        {
            "category":"Building & Trades",
            "subcategory":"Plumbing",
            "type":"Services"
        }
    ],
    "sg:phone":"+44 1785 213800",
    "sg:postcode":"ST16 3AD",
    "sg:province":"Staffordshire",
    "sg:tags":[
        "merchant",
        "plumbers'"
    ],
    "wof:name":"Plumbits",
    "wof:placetype":"venue"
},
  "geometry": {"coordinates":[-2.117833,52.808815],"type":"Point"}
}