{
  "type": "Feature",
  "properties": {
    "iso:country":"GB",
    "sg:address":"106-110 Exeter Road",
    "sg:city":"Cullompton",
    "sg:classifiers":[
        {
            "category":"Shopping",
            "subcategory":"Department Store",
            "type":"Retail Goods"
        }
    ],
    "sg:phone":"+44 1884 32451",
    "sg:postcode":"EX15 1DZ",
    "sg:province":"Devon",
    "wof:name":"The Cherry Tree",
    "wof:placetype":"venue"
},
  "geometry": {"coordinates":[-3.394225,50.850903],"type":"Point"}
}