{
  "type": "Feature",
  "properties": {
    "addr:full":"Whitby Road Bristol City of Bristol BS4 3QF",
    "addr:postcode":"bs4 3qf",
    "addr:street":"Whitby Road",
    "iso:country":"GB",
    "sg:address":"Whitby Road",
    "sg:city":"Bristol",
    "sg:classifiers":[
        {
            "category":"Food & Beverages",
            "subcategory":"Bakery",
            "type":"Retail Goods"
        }
    ],
    "sg:phone":"+44 117 972 8119",
    "sg:postcode":"BS4 3QF",
    "sg:province":"City of Bristol",
    "sg:tags":[
        "pizza"
    ],
    "wof:name":"Pizza Hut",
    "wof:placetype":"venue"
},
  "geometry": {"coordinates":[-2.5580639839,51.4435195923],"type":"Point"}
}