{
  "type": "Feature",
  "properties": {
    "iso:country":"GB",
    "sg:address":"192 Binley Road",
    "sg:city":"Coventry",
    "sg:classifiers":[
        {
            "category":"Shopping",
            "subcategory":"Musical Instruments",
            "type":"Retail Goods"
        }
    ],
    "sg:phone":"+44 24 7644 8933",
    "sg:postcode":"CV3 1HG",
    "sg:province":"Warwickshire",
    "sg:tags":[
        "retailer",
        "sheet",
        "music"
    ],
    "wof:name":"Accordians Of Coventry",
    "wof:placetype":"venue"
},
  "geometry": {"coordinates":[-1.470936,52.407028],"type":"Point"}
}