{
  "type": "Feature",
  "properties": {
    "iso:country":"GB",
    "sg:address":"156 Stoke Newington Road",
    "sg:city":"London",
    "sg:classifiers":[
        {
            "category":"Professional",
            "subcategory":"Detective & Security Services",
            "type":"Services"
        }
    ],
    "sg:phone":"+44 20 7249 3276",
    "sg:postcode":"N16 7XA",
    "sg:province":"Greater London",
    "sg:tags":[
        "car"
    ],
    "wof:name":"Automotive Components Ltd.",
    "wof:placetype":"venue"
},
  "geometry": {"coordinates":[-0.073602,51.561211],"type":"Point"}
}