{
  "type": "Feature",
  "properties": {
    "addr:full":"Unit A Meadow Street Barnsley South Yorkshire S71 1DR",
    "addr:housenumber":"unit a",
    "addr:postcode":"s71 1dr",
    "addr:street":"Meadow Street;Yorkshire",
    "iso:country":"GB",
    "sg:address":"Unit A Meadow Street",
    "sg:city":"Barnsley",
    "sg:classifiers":[
        {
            "category":"Manufacturing",
            "subcategory":"Textiles",
            "type":"Manufacturing & Wholesale Goods"
        }
    ],
    "sg:phone":"+44 1226 281155",
    "sg:postcode":"S71 1DR",
    "sg:province":"South Yorkshire",
    "sg:tags":[
        "made-up"
    ],
    "wof:name":"Beds for Everyone (Sheffield) Ltd.",
    "wof:placetype":"venue"
},
  "geometry": {"coordinates":[-1.474009,53.557838],"type":"Point"}
}