{
  "type": "Feature",
  "properties": {
    "addr:full":"7-8 Yates Ave, Aston-on-trent Derby Derbyshire DE72 2BG",
    "addr:housenumber":"7-8",
    "addr:postcode":"de72 2bg",
    "addr:street":"Yates Ave",
    "iso:country":"GB",
    "sg:address":"7-8 Yates Ave, Aston-on-trent",
    "sg:city":"Derby",
    "sg:classifiers":[
        {
            "category":"Social Services",
            "subcategory":"Retirement Home",
            "type":"Services"
        }
    ],
    "sg:postcode":"DE72 2BG",
    "sg:province":"Derbyshire",
    "sg:tags":[
        "residential",
        "care"
    ],
    "wof:name":"Aston Hall",
    "wof:placetype":"venue"
},
  "geometry": {"coordinates":[-1.391724,52.857914],"type":"Point"}
}