{
  "type": "Feature",
  "properties": {
    "addr:full":"8 Summertown Road Glasgow Glasgow City G51 2LY",
    "addr:housenumber":"8",
    "addr:postcode":"g51 2ly",
    "addr:street":"Summertown Road",
    "iso:country":"GB",
    "sg:address":"8 Summertown Road",
    "sg:city":"Glasgow",
    "sg:classifiers":[
        {
            "category":"Fast Food",
            "type":"Food & Drink"
        }
    ],
    "sg:phone":"+44 141 445 6588",
    "sg:postcode":"G51 2LY",
    "sg:province":"Glasgow City",
    "sg:tags":[
        "away",
        "take"
    ],
    "wof:name":"Summertown Ltd.",
    "wof:placetype":"venue"
},
  "geometry": {"coordinates":[-4.3013682365,55.8567276001],"type":"Point"}
}