{
  "type": "Feature",
  "properties": {
    "addr:full":"5 Constitution Hill Ipswich Suffolk IP1 3RG",
    "addr:housenumber":"5",
    "addr:postcode":"ip1 3rg",
    "addr:street":"Constitution Hill",
    "iso:country":"GB",
    "sg:address":"5 Constitution Hill",
    "sg:city":"Ipswich",
    "sg:classifiers":[
        {
            "category":"Health Services",
            "subcategory":"Nursing And Care Facility",
            "type":"Services"
        }
    ],
    "sg:phone":"+44 1473 254709",
    "sg:postcode":"IP1 3RG",
    "sg:province":"Suffolk",
    "sg:tags":[
        "home"
    ],
    "wof:name":"St. Edmunds Nursing Home",
    "wof:placetype":"venue"
},
  "geometry": {"coordinates":[1.1513750553,52.0683670044],"type":"Point"}
}