{
  "type": "Feature",
  "properties": {
    "iso:country":"GB",
    "sg:address":"1st Floor, 2 Osbourne Dr",
    "sg:city":"Lightwater",
    "sg:classifiers":[
        {
            "category":"Professional",
            "subcategory":"Management & Consulting",
            "type":"Services"
        }
    ],
    "sg:postcode":"GU18 5QU",
    "sg:province":"Surrey",
    "sg:tags":[
        "marketing",
        "consultant"
    ],
    "wof:name":"Todd Harvell Services",
    "wof:placetype":"venue"
},
  "geometry": {"coordinates":[-0.674854,51.346375],"type":"Point"}
}