{
  "type": "Feature",
  "properties": {
    "addr:full":"69 Birch St Swindon Wiltshire SN1 5EZ",
    "addr:housenumber":"69",
    "addr:postcode":"sn1 5ez",
    "addr:street":"Birch St",
    "iso:country":"GB",
    "sg:address":"69 Birch St",
    "sg:city":"Swindon",
    "sg:classifiers":[
        {
            "category":"Professional",
            "subcategory":"Engineering",
            "type":"Services"
        }
    ],
    "sg:phone":"+44 1793 522421",
    "sg:postcode":"SN1 5EZ",
    "sg:province":"Wiltshire",
    "sg:tags":[
        "contractor",
        "electrical",
        "engineer"
    ],
    "wof:name":"Paul B Fluck",
    "wof:placetype":"venue"
},
  "geometry": {"coordinates":[-1.797497,51.558109],"type":"Point"}
}