{
  "type": "Feature",
  "properties": {
    "addr:full":"52 Collier Row Lane Romford Essex RM5 3BB",
    "addr:housenumber":"52",
    "addr:postcode":"rm5 3bb",
    "addr:street":"Collier Row Lane",
    "iso:country":"GB",
    "sg:address":"52 Collier Row Lane",
    "sg:city":"Romford",
    "sg:classifiers":[
        {
            "category":"Shopping",
            "subcategory":"Pharmacy",
            "type":"Retail Goods"
        }
    ],
    "sg:postcode":"RM5 3BB",
    "sg:province":"Essex",
    "sg:tags":[
        "pharmacist",
        "chemist"
    ],
    "wof:name":"A S Bowen & Son Ltd.",
    "wof:placetype":"venue"
},
  "geometry": {"coordinates":[0.168071,51.589771],"type":"Point"}
}