{
  "type": "Feature",
  "properties": {
    "iso:country":"GB",
    "sg:address":"8 Benview Road, Clarkston",
    "sg:city":"Glasgow",
    "sg:classifiers":[
        {
            "category":"Shopping",
            "subcategory":"Computers & Home Electronics",
            "type":"Retail Goods"
        }
    ],
    "sg:postcode":"G76 7PP",
    "sg:province":"East Renfrewshire",
    "sg:tags":[
        "equipment",
        "video",
        "cctv"
    ],
    "wof:name":"1ST Active Security Ltd.",
    "wof:placetype":"venue"
},
  "geometry": {"coordinates":[-4.2756938934,55.7833061218],"type":"Point"}
}