{
  "type": "Feature",
  "properties": {
    "addr:full":"48 Minor Avenue, Lyme Grn, Sutton Macclesfield Cheshire SK11 0LQ",
    "addr:housenumber":"48",
    "addr:postcode":"sk11 0lq",
    "addr:street":"Minor Avenue Lyme Grn",
    "iso:country":"GB",
    "sg:address":"48 Minor Avenue, Lyme Grn, Sutton",
    "sg:city":"Macclesfield",
    "sg:classifiers":[
        {
            "category":"Retail",
            "subcategory":"Driving School",
            "type":"Services"
        }
    ],
    "sg:phone":"+44 1260 252603",
    "sg:postcode":"SK11 0LQ",
    "sg:province":"Cheshire",
    "wof:name":"David Foy Driving School",
    "wof:placetype":"venue"
},
  "geometry": {"coordinates":[-2.1258859634,53.2369194031],"type":"Point"}
}