{
  "type": "Feature",
  "properties": {
    "iso:country":"GB",
    "sg:address":"Grampian Way, Bransholme",
    "sg:city":"Hull",
    "sg:classifiers":[
        {
            "category":"Shopping",
            "subcategory":"News",
            "type":"Retail Goods"
        }
    ],
    "sg:phone":"+44 1482 826504",
    "sg:postcode":"HU7 5BJ",
    "sg:province":"East Riding of Yorkshire",
    "sg:tags":[
        "newsagent"
    ],
    "wof:name":"United News Shops Ltd.",
    "wof:placetype":"venue"
},
  "geometry": {"coordinates":[-0.32805,53.805653],"type":"Point"}
}