{
  "type": "Feature",
  "properties": {
    "iso:country":"GB",
    "sg:address":"Danesmead Close",
    "sg:city":"York",
    "sg:classifiers":[
        {
            "category":"Real Estate",
            "subcategory":"Real Estate Operator",
            "type":"Services"
        },
        {
            "category":"Social Services",
            "subcategory":"Retirement Home",
            "type":"Services"
        }
    ],
    "sg:phone":"+44 1904 610961",
    "sg:postcode":"YO10 4QX",
    "sg:province":"North Yorkshire",
    "sg:tags":[
        "letting",
        "rest",
        "agent"
    ],
    "wof:name":"Home York House",
    "wof:placetype":"venue"
},
  "geometry": {"coordinates":[-1.0769139528,53.9420967102],"type":"Point"}
}