{
  "type": "Feature",
  "properties": {
    "addr:full":"Phoebe Cottage, Phoebe Lane Halifax West Yorkshire HX3 9EY",
    "addr:postcode":"hx3 9ey",
    "addr:street":"Phoebe Lane",
    "iso:country":"GB",
    "sg:address":"Phoebe Cottage, Phoebe Lane",
    "sg:city":"Halifax",
    "sg:classifiers":[
        {
            "category":"Home & Garden",
            "subcategory":"Furniture",
            "type":"Retail Goods"
        }
    ],
    "sg:postcode":"HX3 9EY",
    "sg:province":"West Yorkshire",
    "wof:name":"The Polish Shop",
    "wof:placetype":"venue"
},
  "geometry": {"coordinates":[-1.8535089493,53.7098350525],"type":"Point"}
}