{
  "type": "Feature",
  "properties": {
    "addr:full":"67 Warren Way Brighton East Sussex BN2 6PH",
    "addr:housenumber":"67",
    "addr:postcode":"bn2 6ph",
    "addr:street":"Warren Way",
    "iso:country":"GB",
    "sg:address":"67 Warren Way",
    "sg:city":"Brighton",
    "sg:classifiers":[
        {
            "category":"Education",
            "subcategory":"Special Training",
            "type":"Public Place"
        }
    ],
    "sg:phone":"+44 1273 300938",
    "sg:postcode":"BN2 6PH",
    "sg:province":"East Sussex",
    "sg:tags":[
        "school",
        "language"
    ],
    "wof:name":"Manor Courses Ltd.",
    "wof:placetype":"venue"
},
  "geometry": {"coordinates":[-0.0728370026,50.8378181458],"type":"Point"}
}