{
  "type": "Feature",
  "properties": {
    "addr:full":"3 The Shambles Sevenoaks Kent TN13 1LJ",
    "addr:housenumber":"3",
    "addr:postcode":"tn13 1lj",
    "addr:street":"The Shambles",
    "iso:country":"GB",
    "sg:address":"3 The Shambles",
    "sg:city":"Sevenoaks",
    "sg:classifiers":[
        {
            "category":"Arts & Performance",
            "subcategory":"Art Gallery",
            "type":"Entertainment"
        }
    ],
    "sg:phone":"+44 1732 450960",
    "sg:postcode":"TN13 1LJ",
    "sg:province":"Kent",
    "wof:name":"Art Works",
    "wof:placetype":"venue"
},
  "geometry": {"coordinates":[0.1921579987,51.2706832886],"type":"Point"}
}