{
  "type": "Feature",
  "properties": {
    "iso:country":"GB",
    "sg:address":"75 Neath Road, Briton Ferry",
    "sg:city":"Neath",
    "sg:classifiers":[
        {
            "category":"Food & Beverages",
            "subcategory":"Liquor & Beverages",
            "type":"Retail Goods"
        }
    ],
    "sg:phone":"+44 1639 813271",
    "sg:postcode":"SA11 2DQ",
    "sg:province":"Neath Port Talbot",
    "sg:tags":[
        "beer",
        "spirit",
        "wines"
    ],
    "wof:name":"Victoria Wine",
    "wof:placetype":"venue"
},
  "geometry": {"coordinates":[-3.818717,51.631672],"type":"Point"}
}