{
  "type": "Feature",
  "properties": {
    "addr:full":"Bramblewood, 8 Rockfield Close Oxted Surrey RH8 0DN",
    "addr:housenumber":"8",
    "addr:postcode":"rh8 0dn",
    "addr:street":"Bramblewood;Rockfield Close",
    "iso:country":"GB",
    "sg:address":"Bramblewood, 8 Rockfield Close",
    "sg:city":"Oxted",
    "sg:classifiers":[
        {
            "category":"Professional",
            "subcategory":"Management & Consulting",
            "type":"Services"
        }
    ],
    "sg:postcode":"RH8 0DN",
    "sg:province":"Surrey",
    "sg:tags":[
        "consultant",
        "business"
    ],
    "wof:name":"J & Jb Consultants Ltd",
    "wof:placetype":"venue"
},
  "geometry": {"coordinates":[-0.0046799998,51.2548942566],"type":"Point"}
}