{
  "type": "Feature",
  "properties": {
    "addr:full":"204 Gossops Drive Crawley West Sussex RH11 8LJ",
    "addr:housenumber":"204",
    "addr:postcode":"rh11 8lj",
    "addr:street":"Gossops Drive",
    "iso:country":"GB",
    "sg:address":"204 Gossops Drive",
    "sg:city":"Crawley",
    "sg:classifiers":[
        {
            "category":"Health Services",
            "subcategory":"Dentist",
            "type":"Services"
        }
    ],
    "sg:phone":"+44 1293 512158",
    "sg:postcode":"RH11 8LJ",
    "sg:province":"West Sussex",
    "wof:name":"W O Clinton",
    "wof:placetype":"venue"
},
  "geometry": {"coordinates":[-0.2174129933,51.1094589233],"type":"Point"}
}