{
  "type": "Feature",
  "properties": {
    "addr:full":"Unit 7 & 30, Coppull Enterprise Centre Chorley Lancashire PR7 5BW",
    "addr:housenumber":"unit 7 & 30 coppull enterprise centre",
    "addr:postcode":"pr7 5bw",
    "iso:country":"GB",
    "sg:address":"Unit 7 & 30, Coppull Enterprise Centre",
    "sg:city":"Chorley",
    "sg:classifiers":[
        {
            "category":"Wholesale",
            "subcategory":"Vending Machines",
            "type":"Manufacturing & Wholesale Goods"
        }
    ],
    "sg:phone":"+44 1257 471110",
    "sg:postcode":"PR7 5BW",
    "sg:province":"Lancashire",
    "sg:tags":[
        "sale"
    ],
    "wof:name":"Kwikdrinx",
    "wof:placetype":"venue"
},
  "geometry": {"coordinates":[-2.6486349106,53.6384353638],"type":"Point"}
}