{
  "type": "Feature",
  "properties": {
    "addr:full":"8 Burnett Road, Streetl Sutton Coldfield Staffordshire B74 3EJ",
    "addr:housenumber":"8",
    "addr:postcode":"b74 3ej",
    "addr:street":"Burnett Road Streetl",
    "iso:country":"GB",
    "sg:address":"8 Burnett Road, Streetl",
    "sg:city":"Sutton Coldfield",
    "sg:classifiers":[
        {
            "category":"Home & Garden",
            "subcategory":"Home Furnishings",
            "type":"Retail Goods"
        }
    ],
    "sg:phone":"+44 121 353 6653",
    "sg:postcode":"B74 3EJ",
    "sg:province":"Staffordshire",
    "sg:tags":[
        "furnishers",
        "planner",
        "kitchen"
    ],
    "wof:name":"New Concept Design Ltd.",
    "wof:placetype":"venue"
},
  "geometry": {"coordinates":[-1.8728580475,52.5863800049],"type":"Point"}
}