{
  "type": "Feature",
  "properties": {
    "addr:full":"786 Green Lane Dagenham Essex RM8 1YT",
    "addr:housenumber":"786",
    "addr:postcode":"rm8 1yt",
    "addr:street":"Green Lane",
    "iso:country":"GB",
    "sg:address":"786 Green Lane",
    "sg:city":"Dagenham",
    "sg:classifiers":[
        {
            "category":"Shopping",
            "subcategory":"News",
            "type":"Retail Goods"
        }
    ],
    "sg:phone":"+44 20 8590 2335",
    "sg:postcode":"RM8 1YT",
    "sg:province":"Essex",
    "sg:tags":[
        "newsagent"
    ],
    "wof:name":"Newsplus",
    "wof:placetype":"venue"
},
  "geometry": {"coordinates":[0.123106,51.562027],"type":"Point"}
}