{
  "type": "Feature",
  "properties": {
    "addr:full":"Tatton Park, Ashley Road Knutsford Cheshire WA16 6QJ",
    "addr:postcode":"wa16 6qj",
    "addr:street":"Ashley Road",
    "iso:country":"GB",
    "sg:address":"Tatton Park, Ashley Road",
    "sg:city":"Knutsford",
    "sg:classifiers":[
        {
            "category":"Sports & Exercise",
            "subcategory":"Stables",
            "type":"Entertainment"
        }
    ],
    "sg:postcode":"WA16 6QJ",
    "sg:province":"Cheshire",
    "sg:tags":[
        "education",
        "equestrian"
    ],
    "wof:name":"Tattondale Stables",
    "wof:placetype":"venue"
},
  "geometry": {"coordinates":[-2.37624,53.304203],"type":"Point"}
}