{
  "type": "Feature",
  "properties": {
    "addr:full":"30 Westfield, Old Town Hebden Bridge West Yorkshire HX7 8SH",
    "addr:housenumber":"30",
    "addr:postcode":"hx7 8sh",
    "addr:street":"Westfield;West",
    "iso:country":"GB",
    "sg:address":"30 Westfield, Old Town",
    "sg:city":"Hebden Bridge",
    "sg:classifiers":[
        {
            "category":"Arts & Performance",
            "subcategory":"Music",
            "type":"Entertainment"
        }
    ],
    "sg:postcode":"HX7 8SH",
    "sg:province":"West Yorkshire",
    "sg:tags":[
        "mobile",
        "disco"
    ],
    "wof:name":"Philip Dennis",
    "wof:placetype":"venue"
},
  "geometry": {"coordinates":[-2.0144910812,53.7412261963],"type":"Point"}
}