{
  "type": "Feature",
  "properties": {
    "addr:full":"Lynn Lane, Shenstone Lichfield Staffordshire WS14 0ED",
    "addr:postcode":"ws14 0ed",
    "addr:street":"Lynn Lane",
    "iso:country":"GB",
    "sg:address":"Lynn Lane, Shenstone",
    "sg:city":"Lichfield",
    "sg:classifiers":[
        {
            "category":"Cafe",
            "type":"Food & Drink"
        }
    ],
    "sg:postcode":"WS14 0ED",
    "sg:province":"Staffordshire",
    "sg:tags":[
        "tea",
        "room"
    ],
    "wof:name":"The Canteen",
    "wof:placetype":"venue"
},
  "geometry": {"coordinates":[-1.8923330307,52.6399116516],"type":"Point"}
}