{
  "type": "Feature",
  "properties": {
    "iso:country":"GB",
    "sg:address":"Unit A11, Telford Road",
    "sg:city":"Bicester",
    "sg:classifiers":[
        {
            "category":"Wholesale",
            "subcategory":"Books, Periodicals, & Newspapers",
            "type":"Manufacturing & Wholesale Goods"
        }
    ],
    "sg:postcode":"OX26 4LQ",
    "sg:province":"Oxfordshire",
    "sg:tags":[
        "publishing"
    ],
    "wof:name":"Winslow Press Ltd.",
    "wof:placetype":"venue"
},
  "geometry": {"coordinates":[-1.1315490007,51.9028968811],"type":"Point"}
}