{
  "type": "Feature",
  "properties": {
    "iso:country":"GB",
    "sg:address":"38 High Street",
    "sg:city":"Chatham",
    "sg:classifiers":[
        {
            "category":"Organizations",
            "subcategory":"Non-profit Organization",
            "type":"Services"
        }
    ],
    "sg:postcode":"ME4 4EA",
    "sg:province":"Kent",
    "sg:tags":[
        "organisation",
        "voluntary",
        "charity"
    ],
    "wof:name":"Aiden Turner Trust",
    "wof:placetype":"venue"
},
  "geometry": {"coordinates":[0.518989,51.383259],"type":"Point"}
}