{
  "type": "Feature",
  "properties": {
    "addr:full":"St Roques, Blackscroft Dundee Dundee City DD4 6AS",
    "addr:postcode":"dd4 6as",
    "addr:street":"St;Dundee",
    "iso:country":"GB",
    "sg:address":"St Roques, Blackscroft",
    "sg:city":"Dundee",
    "sg:classifiers":[
        {
            "category":"Bars & Pubs",
            "subcategory":"Nightclub",
            "type":"Food & Drink"
        }
    ],
    "sg:phone":"+44 1382 458322",
    "sg:postcode":"DD4 6AS",
    "sg:province":"Dundee City",
    "sg:tags":[
        "club",
        "night"
    ],
    "wof:name":"Biblio Tek",
    "wof:placetype":"venue"
},
  "geometry": {"coordinates":[-2.9583749771,56.4658355713],"type":"Point"}
}