{
  "type": "Feature",
  "properties": {
    "addr:full":"Moor Lane, Witton Birmingham West Midlands B6 7HH",
    "addr:postcode":"b6 7hh",
    "addr:street":"Moor Lane",
    "iso:country":"GB",
    "sg:address":"Moor Lane, Witton",
    "sg:city":"Birmingham",
    "sg:classifiers":[
        {
            "category":"Retail",
            "subcategory":"Auto Repair",
            "type":"Services"
        }
    ],
    "sg:postcode":"B6 7HH",
    "sg:province":"West Midlands",
    "sg:tags":[
        "modification",
        "garage"
    ],
    "wof:name":"John Alan Motor Services",
    "wof:placetype":"venue"
},
  "geometry": {"coordinates":[-1.8841730356,52.5300674438],"type":"Point"}
}