{
  "type": "Feature",
  "properties": {
    "addr:full":"2 Bryn Offa Wrexham Wrexham LL11 3RG",
    "addr:housenumber":"2",
    "addr:postcode":"ll11 3rg",
    "addr:street":"Bryn Offa",
    "iso:country":"GB",
    "sg:address":"2 Bryn Offa",
    "sg:city":"Wrexham",
    "sg:classifiers":[
        {
            "category":"Professional",
            "subcategory":"Engineering",
            "type":"Services"
        }
    ],
    "sg:phone":"+44 1978 751486",
    "sg:postcode":"LL11 3RG",
    "sg:province":"Wrexham",
    "sg:tags":[
        "contractor",
        "electrical",
        "engineer"
    ],
    "wof:name":"Adwy Electrics",
    "wof:placetype":"venue"
},
  "geometry": {"coordinates":[-3.092499,53.057991],"type":"Point"}
}