{
  "type": "Feature",
  "properties": {
    "addr:full":"Bridleway Lodge Neath Neath Port Talbot SA10 7BQ",
    "addr:postcode":"sa10 7bq",
    "iso:country":"GB",
    "sg:address":"Bridleway Lodge",
    "sg:city":"Neath",
    "sg:classifiers":[
        {
            "category":"Building & Trades",
            "subcategory":"Construction",
            "type":"Services"
        }
    ],
    "sg:phone":"+44 1792 813045",
    "sg:postcode":"SA10 7BQ",
    "sg:province":"Neath Port Talbot",
    "sg:tags":[
        "decorator",
        "painter"
    ],
    "wof:name":"Dennis Davies",
    "wof:placetype":"venue"
},
  "geometry": {"coordinates":[-3.8277549744,51.6670799255],"type":"Point"}
}