{
  "type": "Feature",
  "properties": {
    "addr:full":"76 Long Lane Halesowen West Midlands B62 9DJ",
    "addr:housenumber":"76",
    "addr:postcode":"b62 9dj",
    "addr:street":"Long Lane",
    "iso:country":"GB",
    "sg:address":"76 Long Lane",
    "sg:city":"Halesowen",
    "sg:classifiers":[
        {
            "category":"Building & Trades",
            "subcategory":"Plumbing",
            "type":"Services"
        }
    ],
    "sg:postcode":"B62 9DJ",
    "sg:province":"West Midlands",
    "sg:tags":[
        "clearance",
        "drain",
        "heating",
        "sewer"
    ],
    "wof:name":"Abba Drainage",
    "wof:placetype":"venue"
},
  "geometry": {"coordinates":[-2.032886982,52.4704437256],"type":"Point"}
}