{
  "type": "Feature",
  "properties": {
    "iso:country":"GB",
    "sg:address":"33 High Street",
    "sg:city":"Southwold",
    "sg:classifiers":[
        {
            "category":"Insurance",
            "subcategory":"Insurance Agent",
            "type":"Services"
        }
    ],
    "sg:phone":"+44 1502 722727",
    "sg:postcode":"IP18 6AB",
    "sg:province":"Suffolk",
    "sg:tags":[
        "broker"
    ],
    "wof:name":"D V Jackson & Co. Ltd.",
    "wof:placetype":"venue"
},
  "geometry": {"coordinates":[1.676551,52.327576],"type":"Point"}
}