{
  "type": "Feature",
  "properties": {
    "addr:full":"Middle Farm, Oulton Norwich Norfolk NR11 6NZ",
    "addr:postcode":"nr11 6nz",
    "addr:street":"Middle;Norwich",
    "iso:country":"GB",
    "sg:address":"Middle Farm, Oulton",
    "sg:city":"Norwich",
    "sg:classifiers":[
        {
            "category":"Home & Garden",
            "subcategory":"Garden Supply",
            "type":"Retail Goods"
        },
        {
            "category":"Farming",
            "subcategory":"Farm",
            "type":"Manufacturing & Wholesale Goods"
        }
    ],
    "sg:phone":"+44 1263 732200",
    "sg:postcode":"NR11 6NZ",
    "sg:province":"Norfolk",
    "sg:tags":[
        "mixed",
        "bulb",
        "crop",
        "grower"
    ],
    "wof:name":"F E Smith",
    "wof:placetype":"venue"
},
  "geometry": {"coordinates":[1.1705130339,52.8134307861],"type":"Point"}
}