{
  "type": "Feature",
  "properties": {
    "addr:full":"Unit 2 Gateway Place, Parkgate Rotherham South Yorkshire S62 6LL",
    "addr:housenumber":"unit 2",
    "addr:postcode":"s62 6ll",
    "addr:street":"Gateway Place Parkgate",
    "iso:country":"GB",
    "sg:address":"Unit 2 Gateway Place, Parkgate",
    "sg:city":"Rotherham",
    "sg:classifiers":[
        {
            "category":"Wholesale",
            "subcategory":"Machinery & Supplies",
            "type":"Manufacturing & Wholesale Goods"
        }
    ],
    "sg:postcode":"S62 6LL",
    "sg:province":"South Yorkshire",
    "sg:tags":[
        "hydraulic"
    ],
    "wof:name":"Power Fluid Systems (Uk) Ltd.",
    "wof:placetype":"venue"
},
  "geometry": {"coordinates":[-1.349815,53.444897],"type":"Point"}
}