{
  "type": "Feature",
  "properties": {
    "addr:full":"Briardon Ring Road, Bramley Leeds West Yorkshire LS13 4DU",
    "addr:postcode":"ls13 4du",
    "addr:street":"Briardon Ring Road",
    "iso:country":"GB",
    "sg:address":"Briardon Ring Road, Bramley",
    "sg:city":"Leeds",
    "sg:classifiers":[
        {
            "category":"Bus Charters",
            "type":"Transportation"
        }
    ],
    "sg:phone":"+44 113 257 6002",
    "sg:postcode":"LS13 4DU",
    "sg:province":"West Yorkshire",
    "sg:tags":[
        "hire",
        "coach"
    ],
    "wof:name":"Briardon Coaches",
    "wof:placetype":"venue"
},
  "geometry": {"coordinates":[-1.634169,53.806179],"type":"Point"}
}