{
  "type": "Feature",
  "properties": {
    "addr:full":"Crown Nursery, High Street, Ufford Woodbridge Suffolk IP13 6EL",
    "addr:postcode":"ip13 6el",
    "addr:street":"High Street",
    "iso:country":"GB",
    "sg:address":"Crown Nursery, High Street, Ufford",
    "sg:city":"Woodbridge",
    "sg:classifiers":[
        {
            "category":"Home & Garden",
            "subcategory":"Garden Supply",
            "type":"Retail Goods"
        }
    ],
    "sg:phone":"+44 1394 460755",
    "sg:postcode":"IP13 6EL",
    "sg:province":"Suffolk",
    "sg:tags":[
        "nursery",
        "centre"
    ],
    "wof:name":"Crown Nursery Ltd.",
    "wof:placetype":"venue"
},
  "geometry": {"coordinates":[1.3468699455,52.1246299744],"type":"Point"}
}