{
  "type": "Feature",
  "properties": {
    "addr:full":"41 Kilbowie Rd Clydebank East Dunbartonshire G81 1BL",
    "addr:housenumber":"41",
    "addr:postcode":"g81 1bl",
    "addr:street":"Kilbowie Rd",
    "iso:country":"GB",
    "sg:address":"41 Kilbowie Rd",
    "sg:city":"Clydebank",
    "sg:classifiers":[
        {
            "category":"Shopping",
            "subcategory":"Baby Store",
            "type":"Retail Goods"
        }
    ],
    "sg:phone":"+44 141 562 0041",
    "sg:postcode":"G81 1BL",
    "sg:province":"East Dunbartonshire",
    "sg:tags":[
        "babywear",
        "childrens"
    ],
    "wof:name":"Primary Childrens Clothing",
    "wof:placetype":"venue"
},
  "geometry": {"coordinates":[-4.4057679176,55.9014892578],"type":"Point"}
}