{
  "type": "Feature",
  "properties": {
    "addr:full":"Woodfoot Cottage, Millheugh Larkhall South Lanarkshire ML9 1QU",
    "addr:postcode":"ml9 1qu",
    "addr:street":"Millheugh",
    "iso:country":"GB",
    "sg:address":"Woodfoot Cottage, Millheugh",
    "sg:city":"Larkhall",
    "sg:classifiers":[
        {
            "category":"Personal",
            "subcategory":"Adult",
            "type":"Services"
        }
    ],
    "sg:phone":"+44 1698 881608",
    "sg:postcode":"ML9 1QU",
    "sg:province":"South Lanarkshire",
    "sg:tags":[
        "equestrian"
    ],
    "wof:name":"Woodfoot Riding Centre",
    "wof:placetype":"venue"
},
  "geometry": {"coordinates":[-3.973058939,55.7384796143],"type":"Point"}
}