{
  "type": "Feature",
  "properties": {
    "iso:country":"GB",
    "sg:address":"51 Nottingham Road, Eastwood",
    "sg:city":"Nottingham",
    "sg:classifiers":[
        {
            "category":"Shopping",
            "subcategory":"News",
            "type":"Retail Goods"
        }
    ],
    "sg:phone":"+44 1773 712633",
    "sg:postcode":"NG16 3AN",
    "sg:province":"Derbyshire",
    "sg:tags":[
        "newsagent"
    ],
    "wof:name":"Jacksons the Cleaners",
    "wof:placetype":"venue"
},
  "geometry": {"coordinates":[-1.305844,53.018082],"type":"Point"}
}