{
  "type": "Feature",
  "properties": {
    "addr:full":"Merlin House, 12 Simmons Way Atherstone Leicestershire CV9 3AX",
    "addr:housenumber":"12",
    "addr:postcode":"cv9 3ax",
    "addr:street":"Simmons Way",
    "iso:country":"GB",
    "sg:address":"Merlin House, 12 Simmons Way",
    "sg:city":"Atherstone",
    "sg:classifiers":[
        {
            "category":"Manufacturing",
            "subcategory":"Signs",
            "type":"Manufacturing & Wholesale Goods"
        }
    ],
    "sg:phone":"+44 1827 720001",
    "sg:postcode":"CV9 3AX",
    "sg:province":"Leicestershire",
    "sg:tags":[
        "writer"
    ],
    "wof:name":"Sign Up-Today",
    "wof:placetype":"venue"
},
  "geometry": {"coordinates":[-1.544476,52.584675],"type":"Point"}
}