{
  "type": "Feature",
  "properties": {
    "iso:country":"GB",
    "sg:address":"Blake End Road, Great Saling",
    "sg:city":"Braintree",
    "sg:classifiers":[
        {
            "category":"Home & Garden",
            "subcategory":"Garden Supply",
            "type":"Retail Goods"
        },
        {
            "category":"Farming",
            "subcategory":"Livestock Farm",
            "type":"Manufacturing & Wholesale Goods"
        }
    ],
    "sg:phone":"+44 1376 326592",
    "sg:postcode":"CM7 5DS",
    "sg:province":"Essex",
    "sg:tags":[
        "bulb",
        "grower",
        "others"
    ],
    "wof:name":"W P Bucknell & Son",
    "wof:placetype":"venue"
},
  "geometry": {"coordinates":[0.47155,51.902981],"type":"Point"}
}