{
  "type": "Feature",
  "properties": {
    "iso:country":"GB",
    "sg:address":"48 Darbys Lane, Oakdale",
    "sg:city":"Poole",
    "sg:classifiers":[
        {
            "category":"Building & Trades",
            "subcategory":"Construction",
            "type":"Services"
        }
    ],
    "sg:postcode":"BH15 3ET",
    "sg:province":"Dorset",
    "sg:tags":[
        "contractor"
    ],
    "wof:name":"Richway Construction Ltd",
    "wof:placetype":"venue"
},
  "geometry": {"coordinates":[-1.976551,50.734081],"type":"Point"}
}