{
  "type": "Feature",
  "properties": {
    "addr:full":"144 Stratford Road, Shirley Solihull West Midlands B90 3BB",
    "addr:housenumber":"144",
    "addr:postcode":"b90 3bb",
    "addr:street":"Stratford Road",
    "iso:country":"GB",
    "sg:address":"144 Stratford Road, Shirley",
    "sg:city":"Solihull",
    "sg:classifiers":[
        {
            "category":"Shopping",
            "subcategory":"News",
            "type":"Retail Goods"
        },
        {
            "category":"Home & Garden",
            "subcategory":"Carpets & Floor Coverings",
            "type":"Retail Goods"
        }
    ],
    "sg:phone":"+44 121 744 1102",
    "sg:postcode":"B90 3BB",
    "sg:province":"West Midlands",
    "sg:tags":[
        "carpets",
        "retailer",
        "newsagent",
        "matting",
        "rug"
    ],
    "wof:name":"Shirley Carpet Centre",
    "wof:placetype":"venue"
},
  "geometry": {"coordinates":[-1.82851,52.41404],"type":"Point"}
}