{
  "type": "Feature",
  "properties": {
    "addr:full":"53 Church Walk Worksop Nottinghamshire S80 2EJ",
    "addr:housenumber":"53",
    "addr:postcode":"s80 2ej",
    "addr:street":"Church Walk",
    "iso:country":"GB",
    "sg:address":"53 Church Walk",
    "sg:city":"Worksop",
    "sg:classifiers":[
        {
            "category":"Manufacturing",
            "subcategory":"Building Materials",
            "type":"Manufacturing & Wholesale Goods"
        }
    ],
    "sg:phone":"+44 1909 487362",
    "sg:postcode":"S80 2EJ",
    "sg:province":"Nottinghamshire",
    "sg:tags":[
        "distributor",
        "concrete",
        "mnfrs"
    ],
    "wof:name":"Trio Concrete Products",
    "wof:placetype":"venue"
},
  "geometry": {"coordinates":[-1.12083,53.306541],"type":"Point"}
}