{
  "type": "Feature",
  "properties": {
    "iso:country":"GB",
    "sg:address":"196 Bell La",
    "sg:city":"Bury",
    "sg:classifiers":[
        {
            "category":"Building & Trades",
            "subcategory":"Construction",
            "type":"Services"
        }
    ],
    "sg:phone":"+44 161 705 2845",
    "sg:postcode":"BL9 6HS",
    "sg:province":"Lancashire",
    "sg:tags":[
        "builder"
    ],
    "wof:name":"Patton N",
    "wof:placetype":"venue"
},
  "geometry": {"coordinates":[-2.277553,53.597637],"type":"Point"}
}