{
  "type": "Feature",
  "properties": {
    "addr:full":"19 Raymill Road East Maidenhead Berkshire SL6 8SW",
    "addr:housenumber":"19",
    "addr:postcode":"sl6 8sw",
    "addr:street":"Raymill Road East",
    "iso:country":"GB",
    "sg:address":"19 Raymill Road East",
    "sg:city":"Maidenhead",
    "sg:classifiers":[
        {
            "category":"Home & Garden",
            "subcategory":"Building Materials",
            "type":"Retail Goods"
        }
    ],
    "sg:phone":"+44 1628 632468",
    "sg:postcode":"SL6 8SW",
    "sg:province":"Berkshire",
    "sg:tags":[
        "ventilator",
        "ventilation",
        "system"
    ],
    "wof:name":"Solvetotal Co. Ltd.",
    "wof:placetype":"venue"
},
  "geometry": {"coordinates":[-0.7130759954,51.5307807922],"type":"Point"}
}