{
  "type": "Feature",
  "properties": {
    "iso:country":"GB",
    "sg:address":"Beadlow",
    "sg:city":"Shefford",
    "sg:classifiers":[
        {
            "category":"Shopping",
            "subcategory":"Florist",
            "type":"Retail Goods"
        }
    ],
    "sg:phone":"+44 1525 861824",
    "sg:postcode":"SG17 5PL",
    "sg:province":"Bedfordshire",
    "wof:name":"Growswell",
    "wof:placetype":"venue"
},
  "geometry": {"coordinates":[-0.39228,52.03463],"type":"Point"}
}