{
  "type": "Feature",
  "properties": {
    "iso:country":"GB",
    "sg:address":"60 Friargate",
    "sg:city":"Preston",
    "sg:classifiers":[
        {
            "category":"Shopping",
            "subcategory":"Comic Books",
            "type":"Retail Goods"
        }
    ],
    "sg:postcode":"PR1 2AT",
    "sg:province":"Lancashire",
    "sg:tags":[
        "jeweller"
    ],
    "wof:name":"Jewelery by Judith",
    "wof:placetype":"venue"
},
  "geometry": {"coordinates":[-2.704696,53.760986],"type":"Point"}
}