{
  "type": "Feature",
  "properties": {
    "addr:full":"329-331 Chartwell North, Victoria Plaza Shopping Centre Southend-on-sea Essex SS2 5SR",
    "addr:housenumber":"329-331",
    "addr:postcode":"ss2 5sr",
    "addr:street":"Chartwell North Victoria;Shopping Centre",
    "iso:country":"GB",
    "sg:address":"329-331 Chartwell North, Victoria Plaza Shopping Centre",
    "sg:city":"Southend-on-sea",
    "sg:classifiers":[
        {
            "category":"Shopping",
            "subcategory":"Gifts & Souvenirs",
            "type":"Retail Goods"
        }
    ],
    "sg:phone":"+44 1702 460077",
    "sg:postcode":"SS2 5SR",
    "sg:province":"Essex",
    "sg:tags":[
        "shop"
    ],
    "wof:name":"Emantee Ltd.",
    "wof:placetype":"venue"
},
  "geometry": {"coordinates":[0.7124,51.541],"type":"Point"}
}