{
  "type": "Feature",
  "properties": {
    "addr:full":"1 Princess Crescent, Trinant Crumlin Newport Blaenau Gwent NP11 3JG",
    "addr:housenumber":"1",
    "addr:postcode":"np11 3jg",
    "addr:street":"Princess Crescent Trinant",
    "iso:country":"GB",
    "sg:address":"1 Princess Crescent, Trinant Crumlin",
    "sg:city":"Newport",
    "sg:classifiers":[
        {
            "category":"Taxi",
            "type":"Transportation"
        }
    ],
    "sg:phone":"+44 1495 217691",
    "sg:postcode":"NP11 3JG",
    "sg:province":"Blaenau Gwent",
    "sg:tags":[
        "mini",
        "cab"
    ],
    "wof:name":"Pentwyn Private Hire",
    "wof:placetype":"venue"
},
  "geometry": {"coordinates":[-3.1519370079,51.6981010437],"type":"Point"}
}