{
  "type": "Feature",
  "properties": {
    "iso:country":"GB",
    "sg:address":"282 Church Road, St George",
    "sg:city":"Bristol",
    "sg:classifiers":[
        {
            "category":"Professional",
            "subcategory":"Employment Agencies",
            "type":"Services"
        }
    ],
    "sg:phone":"+44 117 954 1030",
    "sg:postcode":"BS5 8AH",
    "sg:province":"City of Bristol",
    "sg:tags":[
        "consultant"
    ],
    "wof:name":"Driver Services",
    "wof:placetype":"venue"
},
  "geometry": {"coordinates":[-2.546814,51.459724],"type":"Point"}
}