{
  "type": "Feature",
  "properties": {
    "iso:country":"GB",
    "sg:address":"8 Bell Lane",
    "sg:city":"London",
    "sg:classifiers":[
        {
            "category":"Shopping",
            "subcategory":"News",
            "type":"Retail Goods"
        }
    ],
    "sg:phone":"+44 20 8202 7227",
    "sg:postcode":"NW4 2AD",
    "sg:province":"Greater London",
    "sg:tags":[
        "newsagent"
    ],
    "wof:name":"Bennetts",
    "wof:placetype":"venue"
},
  "geometry": {"coordinates":[-0.219773,51.586029],"type":"Point"}
}