{
  "type": "Feature",
  "properties": {
    "addr:full":"Priory Lane Putney Greater London SW15 5JR",
    "addr:postcode":"sw15 5jr",
    "addr:street":"Priory Lane",
    "iso:country":"GB",
    "sg:address":"Priory Lane",
    "sg:city":"Putney",
    "sg:classifiers":[
        {
            "category":"Personal",
            "subcategory":"Adult",
            "type":"Services"
        }
    ],
    "sg:phone":"+44 20 8876 7089",
    "sg:postcode":"SW15 5JR",
    "sg:province":"Greater London",
    "sg:tags":[
        "equestrian"
    ],
    "wof:name":"Roehampton Gate Equestrian Centre",
    "wof:placetype":"venue"
},
  "geometry": {"coordinates":[-0.25385,51.456596],"type":"Point"}
}