{
  "type": "Feature",
  "properties": {
    "iso:country":"GB",
    "sg:address":"Cardinal Avenue",
    "sg:city":"Borehamwood",
    "sg:classifiers":[
        {
            "category":"Health Services",
            "subcategory":"Nursing And Care Facility",
            "type":"Services"
        }
    ],
    "sg:phone":"+44 20 8207 0599",
    "sg:postcode":"WD6 1TB",
    "sg:province":"Hertfordshire",
    "sg:tags":[
        "home"
    ],
    "wof:name":"Borehamwood Nursing Home The",
    "wof:placetype":"venue"
},
  "geometry": {"coordinates":[-0.2715989947,51.6544113159],"type":"Point"}
}