{
  "type": "Feature",
  "properties": {
    "iso:country":"GB",
    "sg:address":"30 & 32 Martock Business Pk, Gt Western Rd",
    "sg:city":"Martock",
    "sg:classifiers":[
        {
            "category":"Home & Garden",
            "subcategory":"Furniture",
            "type":"Retail Goods"
        }
    ],
    "sg:phone":"+44 1935 826641",
    "sg:postcode":"TA12 6HB",
    "sg:province":"Somerset",
    "wof:name":"Corbiere Furniture Direct (Yeovil) Ltd",
    "wof:placetype":"venue"
},
  "geometry": {"coordinates":[-2.76869,50.978611],"type":"Point"}
}