{
  "type": "Feature",
  "properties": {
    "addr:full":"Rear Of Cadwgan Rd, Old Colwyn Colwyn Bay Conwy LL29 9PY",
    "addr:postcode":"ll29 9py",
    "addr:street":"Cadwgan Rd",
    "iso:country":"GB",
    "sg:address":"Rear Of Cadwgan Rd, Old Colwyn",
    "sg:city":"Colwyn Bay",
    "sg:classifiers":[
        {
            "category":"Real Estate",
            "subcategory":"Real Estate Agent",
            "type":"Services"
        }
    ],
    "sg:phone":"+44 1492 512088",
    "sg:postcode":"LL29 9PY",
    "sg:province":"Conwy",
    "wof:name":"Coastal Property Services",
    "wof:placetype":"venue"
},
  "geometry": {"coordinates":[-3.6971390247,53.2889900208],"type":"Point"}
}