{
  "type": "Feature",
  "properties": {
    "iso:country":"GB",
    "sg:address":"69 King Street",
    "sg:city":"Lancaster",
    "sg:classifiers":[
        {
            "category":"Sports & Exercise",
            "subcategory":"Sports Center",
            "type":"Entertainment"
        }
    ],
    "sg:postcode":"LA1 1RE",
    "sg:province":"Lancashire",
    "sg:tags":[
        "shop",
        "good"
    ],
    "wof:name":"Blue Tubes (Lancaster) Ltd.",
    "wof:placetype":"venue"
},
  "geometry": {"coordinates":[-2.8017559052,54.0470657349],"type":"Point"}
}