{
  "type": "Feature",
  "properties": {
    "iso:country":"GB",
    "sg:address":"Active Ho, Keppel Ho",
    "sg:city":"Manchester",
    "sg:classifiers":[
        {
            "category":"Professional",
            "subcategory":"Management & Consulting",
            "type":"Services"
        }
    ],
    "sg:postcode":"M21 0BP",
    "sg:province":"Cheshire",
    "sg:tags":[
        "marketing",
        "consultant"
    ],
    "wof:name":"Active Channels Ltd",
    "wof:placetype":"venue"
},
  "geometry": {"coordinates":[-2.27779,53.445179],"type":"Point"}
}