{
  "type": "Feature",
  "properties": {
    "addr:full":"71 Reading Rd, Woodley Reading Berkshire RG5 3AE",
    "addr:housenumber":"71",
    "addr:postcode":"rg5 3ae",
    "addr:street":"Reading Rd",
    "iso:country":"GB",
    "sg:address":"71 Reading Rd, Woodley",
    "sg:city":"Reading",
    "sg:classifiers":[
        {
            "category":"Insurance",
            "subcategory":"Insurance Agent",
            "type":"Services"
        }
    ],
    "sg:postcode":"RG5 3AE",
    "sg:province":"Berkshire",
    "sg:tags":[
        "broker"
    ],
    "wof:name":"Consulting Insurance Brokers",
    "wof:placetype":"venue"
},
  "geometry": {"coordinates":[-0.9108989835,51.4570884705],"type":"Point"}
}