{
  "type": "Feature",
  "properties": {
    "addr:full":"2 Mabledon Avenue Ashford Kent TN24 8BJ",
    "addr:housenumber":"2",
    "addr:postcode":"tn24 8bj",
    "addr:street":"Mabledon Avenue",
    "iso:country":"GB",
    "sg:address":"2 Mabledon Avenue",
    "sg:city":"Ashford",
    "sg:classifiers":[
        {
            "category":"Professional",
            "subcategory":"Engineering",
            "type":"Services"
        }
    ],
    "sg:phone":"+44 1233 634142",
    "sg:postcode":"TN24 8BJ",
    "sg:province":"Kent",
    "sg:tags":[
        "contractor",
        "electrical",
        "engineer"
    ],
    "wof:name":"Larkin Installations Ltd.",
    "wof:placetype":"venue"
},
  "geometry": {"coordinates":[0.8860729933,51.1459197998],"type":"Point"}
}