{
  "type": "Feature",
  "properties": {
    "addr:full":"3 St Peters Street Bedford Bedfordshire MK40 2PN",
    "addr:housenumber":"3",
    "addr:postcode":"mk40 2pn",
    "addr:street":"St Peters Street",
    "iso:country":"GB",
    "sg:address":"3 St Peters Street",
    "sg:city":"Bedford",
    "sg:classifiers":[
        {
            "category":"Government",
            "subcategory":"Police Station",
            "type":"Public Place"
        },
        {
            "category":"Government",
            "subcategory":"Office",
            "type":"Public Place"
        }
    ],
    "sg:phone":"+44 1234 213541",
    "sg:postcode":"MK40 2PN",
    "sg:province":"Bedfordshire",
    "sg:tags":[
        "support",
        "local"
    ],
    "wof:name":"The Probation Office",
    "wof:placetype":"venue"
},
  "geometry": {"coordinates":[-0.466046989,52.1386528015],"type":"Point"}
}