{
  "type": "Feature",
  "properties": {
    "iso:country":"GB",
    "sg:address":"6 Ruislip Road",
    "sg:city":"Greenford",
    "sg:classifiers":[
        {
            "category":"Professional",
            "subcategory":"Art Services",
            "type":"Services"
        }
    ],
    "sg:postcode":"UB6 9QN",
    "sg:province":"Greater London",
    "sg:tags":[
        "framing"
    ],
    "wof:name":"Greenford Framing",
    "wof:placetype":"venue"
},
  "geometry": {"coordinates":[-0.3567770123,51.5286216736],"type":"Point"}
}