{
  "type": "Feature",
  "properties": {
    "iso:country":"GB",
    "sg:address":"Cheam Resource Centre, 671 London Road, North Cheam",
    "sg:city":"Sutton",
    "sg:classifiers":[
        {
            "category":"Government",
            "subcategory":"Office",
            "type":"Public Place"
        }
    ],
    "sg:phone":"+44 20 8335 3825",
    "sg:postcode":"SM3 9DL",
    "sg:province":"Surrey",
    "sg:tags":[
        "local"
    ],
    "wof:name":"London Borough of Sutton",
    "wof:placetype":"venue"
},
  "geometry": {"coordinates":[-0.22228,51.37645],"type":"Point"}
}