{
  "type": "Feature",
  "properties": {
    "addr:full":"Brandheath Lane, Astwood Bank Redditch Warwickshire B96 6NQ",
    "addr:postcode":"b96 6nq",
    "addr:street":"Brandheath Lane",
    "iso:country":"GB",
    "sg:address":"Brandheath Lane, Astwood Bank",
    "sg:city":"Redditch",
    "sg:classifiers":[
        {
            "category":"Building & Trades",
            "subcategory":"Landscaping Services",
            "type":"Services"
        }
    ],
    "sg:phone":"+44 1527 892975",
    "sg:postcode":"B96 6NQ",
    "sg:province":"Warwickshire",
    "sg:tags":[
        "pond",
        "aquarium"
    ],
    "wof:name":"Fanday Aquatic Imports Ltd.",
    "wof:placetype":"venue"
},
  "geometry": {"coordinates":[-1.9280309677,52.2377281189],"type":"Point"}
}