{
  "type": "Feature",
  "properties": {
    "addr:full":"The Maltings, Milton Street Lincoln Lincolnshire LN5 8PU",
    "addr:postcode":"ln5 8pu",
    "addr:street":"The Maltings Milton Street",
    "iso:country":"GB",
    "sg:address":"The Maltings, Milton Street",
    "sg:city":"Lincoln",
    "sg:classifiers":[
        {
            "category":"Home & Garden",
            "subcategory":"Building Materials",
            "type":"Retail Goods"
        }
    ],
    "sg:phone":"+44 1522 512088",
    "sg:postcode":"LN5 8PU",
    "sg:province":"Lincolnshire",
    "sg:tags":[
        "plaster",
        "ware",
        "plasterware"
    ],
    "wof:name":"Finecast Products",
    "wof:placetype":"venue"
},
  "geometry": {"coordinates":[-0.542038,53.226086],"type":"Point"}
}