{
  "type": "Feature",
  "properties": {
    "iso:country":"GB",
    "sg:address":"12 Skinner Street",
    "sg:city":"Worcester",
    "sg:classifiers":[
        {
            "category":"Building & Trades",
            "subcategory":"Construction",
            "type":"Services"
        }
    ],
    "sg:postcode":"WR2 4JD",
    "sg:province":"Worcestershire",
    "sg:tags":[
        "dry",
        "lining",
        "plasterers",
        "screeders"
    ],
    "wof:name":"Colin J Gormley",
    "wof:placetype":"venue"
},
  "geometry": {"coordinates":[-2.240001,52.184666],"type":"Point"}
}