{
  "type": "Feature",
  "properties": {
    "iso:country":"GB",
    "sg:address":"Scotchells Brook Lane",
    "sg:city":"Sandown",
    "sg:classifiers":[
        {
            "category":"Education",
            "subcategory":"Special Training",
            "type":"Public Place"
        }
    ],
    "sg:phone":"+44 1983 402402",
    "sg:postcode":"PO36 0JP",
    "sg:province":"Isle of Wight",
    "sg:tags":[
        "school",
        "flying"
    ],
    "wof:name":"Specialist Flying School",
    "wof:placetype":"venue"
},
  "geometry": {"coordinates":[-1.1501640081,50.6560134888],"type":"Point"}
}