{
  "type": "Feature",
  "properties": {
    "iso:country":"GB",
    "sg:address":"2a Main Street, Keyworth",
    "sg:city":"Nottingham",
    "sg:classifiers":[
        {
            "category":"Shopping",
            "subcategory":"Gifts & Souvenirs",
            "type":"Retail Goods"
        }
    ],
    "sg:postcode":"NG12 5AD",
    "sg:province":"Nottinghamshire",
    "sg:tags":[
        "shop"
    ],
    "wof:name":"Bumble Bee",
    "wof:placetype":"venue"
},
  "geometry": {"coordinates":[-1.0896430016,52.870967865],"type":"Point"}
}