{
  "type": "Feature",
  "properties": {
    "addr:full":"43 Lee High Road, Lewisham London Greater London SE13 5NS",
    "addr:housenumber":"43",
    "addr:postcode":"se13 5ns",
    "addr:street":"Lee High Road",
    "iso:country":"GB",
    "sg:address":"43 Lee High Road, Lewisham",
    "sg:city":"London",
    "sg:classifiers":[
        {
            "category":"Recreation",
            "subcategory":"Amusement Park",
            "type":"Entertainment"
        }
    ],
    "sg:phone":"+44 20 8473 4730",
    "sg:postcode":"SE13 5NS",
    "sg:province":"Greater London",
    "sg:tags":[
        "arcade"
    ],
    "wof:name":"Cash Pot",
    "wof:placetype":"venue"
},
  "geometry": {"coordinates":[-0.005569,51.460751],"type":"Point"}
}