{
  "type": "Feature",
  "properties": {
    "iso:country":"GB",
    "sg:address":"43 Badger Clo",
    "sg:city":"Maidenhead",
    "sg:classifiers":[
        {
            "category":"Arts & Performance",
            "subcategory":"Music",
            "type":"Entertainment"
        }
    ],
    "sg:phone":"+44 1628 773149",
    "sg:postcode":"SL6 2TE",
    "sg:province":"Berkshire",
    "sg:tags":[
        "mobile",
        "disco"
    ],
    "wof:name":"Gerry Broad-Love Bytes",
    "wof:placetype":"venue"
},
  "geometry": {"coordinates":[-0.7338809967,51.51014328],"type":"Point"}
}