{
  "type": "Feature",
  "properties": {
    "addr:full":"10 Nettleton Hill, Golcar Huddersfield West Yorkshire HD7 4NZ",
    "addr:housenumber":"10",
    "addr:postcode":"hd7 4nz",
    "addr:street":"Nettleton Hill;West",
    "iso:country":"GB",
    "sg:address":"10 Nettleton Hill, Golcar",
    "sg:city":"Huddersfield",
    "sg:classifiers":[
        {
            "category":"Professional",
            "type":"Services"
        }
    ],
    "sg:phone":"+44 1484 651735",
    "sg:postcode":"HD7 4NZ",
    "sg:province":"West Yorkshire",
    "sg:tags":[
        "repair",
        "tech",
        "maintenance"
    ],
    "wof:name":"Harold Smith",
    "wof:placetype":"venue"
},
  "geometry": {"coordinates":[-1.8399139643,53.6400985718],"type":"Point"}
}