{
  "type": "Feature",
  "properties": {
    "addr:full":"31a Castle Street Cirencester Gloucestershire GL7 1QD",
    "addr:housenumber":"31a",
    "addr:postcode":"gl7 1qd",
    "addr:street":"Castle Street",
    "iso:country":"GB",
    "sg:address":"31a Castle Street",
    "sg:city":"Cirencester",
    "sg:classifiers":[
        {
            "category":"Professional",
            "subcategory":"Accounting & Tax Preparation",
            "type":"Services"
        }
    ],
    "sg:postcode":"GL7 1QD",
    "sg:province":"Gloucestershire",
    "sg:tags":[
        "accountant"
    ],
    "wof:name":"H J Shave",
    "wof:placetype":"venue"
},
  "geometry": {"coordinates":[-1.970226,51.716175],"type":"Point"}
}