{
  "type": "Feature",
  "properties": {
    "addr:full":"18 Unit, Lower Chase Road, Swanmore Southampton Hampshire SO32 2PB",
    "addr:housenumber":"18 unit",
    "addr:postcode":"so32 2pb",
    "addr:street":"Lower Chase Road",
    "iso:country":"GB",
    "sg:address":"18 Unit, Lower Chase Road, Swanmore",
    "sg:city":"Southampton",
    "sg:classifiers":[
        {
            "category":"Retail",
            "subcategory":"Auto Repair",
            "type":"Services"
        }
    ],
    "sg:phone":"+44 1489 891391",
    "sg:postcode":"SO32 2PB",
    "sg:province":"Hampshire",
    "sg:tags":[
        "modification",
        "garage"
    ],
    "wof:name":"P Snook & Sons",
    "wof:placetype":"venue"
},
  "geometry": {"coordinates":[-1.1784089804,50.9406738281],"type":"Point"}
}