{
  "type": "Feature",
  "properties": {
    "iso:country":"GB",
    "sg:address":"Coombe Road, Neasden",
    "sg:city":"London",
    "sg:classifiers":[
        {
            "category":"Autos & Motor Vehicles",
            "subcategory":"Auto Supplies",
            "type":"Retail Goods"
        }
    ],
    "sg:postcode":"NW10 0EB",
    "sg:province":"Greater London",
    "sg:tags":[
        "component"
    ],
    "wof:name":"Ghai Distributors Ltd.",
    "wof:placetype":"venue"
},
  "geometry": {"coordinates":[-0.259799,51.564117],"type":"Point"}
}