{
  "type": "Feature",
  "properties": {
    "addr:full":"Summerley, Apperknowle Dronfield Derbyshire S18 4BA",
    "addr:postcode":"s18 4ba",
    "iso:country":"GB",
    "sg:address":"Summerley, Apperknowle",
    "sg:city":"Dronfield",
    "sg:classifiers":[
        {
            "category":"Train Station",
            "subcategory":"Rail",
            "type":"Transportation"
        }
    ],
    "sg:phone":"+44 1246 416516",
    "sg:postcode":"S18 4BA",
    "sg:province":"Derbyshire",
    "sg:tags":[
        "railway"
    ],
    "wof:name":"R E S",
    "wof:placetype":"venue"
},
  "geometry": {"coordinates":[-1.4291139841,53.3007202148],"type":"Point"}
}