{
  "type": "Feature",
  "properties": {
    "iso:country":"GB",
    "sg:address":"6 Warren Way",
    "sg:city":"Brighton",
    "sg:classifiers":[
        {
            "category":"Fast Food",
            "type":"Food & Drink"
        }
    ],
    "sg:phone":"+44 1273 303061",
    "sg:postcode":"BN2 6PJ",
    "sg:province":"East Sussex",
    "sg:tags":[
        "away",
        "take"
    ],
    "wof:name":"Woodingdean Fish Bar",
    "wof:placetype":"venue"
},
  "geometry": {"coordinates":[-0.0747999996,50.8368759155],"type":"Point"}
}