{
  "type": "Feature",
  "properties": {
    "addr:full":"19 Ravensworth Road, Dunston Gateshead Tyne and Wear NE11 9AB",
    "addr:housenumber":"19",
    "addr:postcode":"ne11 9ab",
    "addr:street":"Ravensworth Road",
    "iso:country":"GB",
    "sg:address":"19 Ravensworth Road, Dunston",
    "sg:city":"Gateshead",
    "sg:classifiers":[
        {
            "category":"Organizations",
            "subcategory":"Community Association",
            "type":"Services"
        },
        {
            "category":"Government",
            "subcategory":"Office",
            "type":"Public Place"
        }
    ],
    "sg:phone":"+44 191 420 0300",
    "sg:postcode":"NE11 9AB",
    "sg:province":"Tyne and Wear",
    "sg:tags":[
        "member",
        "parliament",
        "central"
    ],
    "wof:name":"David Clelland",
    "wof:placetype":"venue"
},
  "geometry": {"coordinates":[-1.6409080029,54.9514274597],"type":"Point"}
}