{
  "type": "Feature",
  "properties": {
    "iso:country":"GB",
    "sg:address":"176b Tollington Park",
    "sg:city":"London",
    "sg:classifiers":[
        {
            "category":"Shopping",
            "subcategory":"Clothing, Apparel, & Fashions",
            "type":"Retail Goods"
        }
    ],
    "sg:postcode":"N4 3AJ",
    "sg:province":"Greater London",
    "sg:tags":[
        "shop"
    ],
    "wof:name":"Lyndia Shaw",
    "wof:placetype":"venue"
},
  "geometry": {"coordinates":[-0.110746,51.568413],"type":"Point"}
}