{
  "type": "Feature",
  "properties": {
    "iso:country":"GB",
    "sg:address":"18 Harrier Way, Morley",
    "sg:city":"Leeds",
    "sg:classifiers":[
        {
            "category":"Autos & Motor Vehicles",
            "subcategory":"Auto Supplies",
            "type":"Retail Goods"
        }
    ],
    "sg:phone":"+44 113 252 2106",
    "sg:postcode":"LS27 8TG",
    "sg:province":"West Yorkshire",
    "sg:tags":[
        "car",
        "component"
    ],
    "wof:name":"E.P.S Systems",
    "wof:placetype":"venue"
},
  "geometry": {"coordinates":[-1.5829219818,53.745513916],"type":"Point"}
}