{
  "type": "Feature",
  "properties": {
    "iso:country":"GB",
    "sg:address":"The Wharf",
    "sg:city":"Elland",
    "sg:classifiers":[
        {
            "category":"Retail",
            "subcategory":"Repair Shop",
            "type":"Services"
        }
    ],
    "sg:postcode":"HX5 9HH",
    "sg:province":"West Yorkshire",
    "sg:tags":[
        "radio",
        "television",
        "video"
    ],
    "wof:name":"Sound & Vision",
    "wof:placetype":"venue"
},
  "geometry": {"coordinates":[-1.835879,53.686256],"type":"Point"}
}