{
  "type": "Feature",
  "properties": {
    "iso:country":"GB",
    "sg:address":"Lazarus Court",
    "sg:city":"Leicester",
    "sg:classifiers":[
        {
            "category":"Professional",
            "subcategory":"Engineering",
            "type":"Services"
        }
    ],
    "sg:phone":"+44 116 237 4222",
    "sg:postcode":"LE7 7NR",
    "sg:province":"Leicestershire",
    "sg:tags":[
        "contractor",
        "electrical",
        "engineer"
    ],
    "wof:name":"Nick Moore Electrical Services Ltd.",
    "wof:placetype":"venue"
},
  "geometry": {"coordinates":[-1.140329957,52.7073516846],"type":"Point"}
}