{
  "type": "Feature",
  "properties": {
    "iso:country":"GB",
    "sg:address":"Enterprise House, 113 George Lane",
    "sg:city":"South Woodford",
    "sg:classifiers":[
        {
            "category":"Professional",
            "subcategory":"Engineering",
            "type":"Services"
        }
    ],
    "sg:phone":"+44 20 8252 5983",
    "sg:postcode":"E18 1AB",
    "sg:province":"Greater London",
    "sg:tags":[
        "contractor",
        "electrical",
        "engineer"
    ],
    "wof:name":"Paul J Toner",
    "wof:placetype":"venue"
},
  "geometry": {"coordinates":[0.026783,51.592583],"type":"Point"}
}