{
  "type": "Feature",
  "properties": {
    "addr:full":"188 Brampton Rd Bexleyheath Kent DA7 4SY",
    "addr:housenumber":"188",
    "addr:postcode":"da7 4sy",
    "addr:street":"Brampton Rd",
    "iso:country":"GB",
    "sg:address":"188 Brampton Rd",
    "sg:city":"Bexleyheath",
    "sg:classifiers":[
        {
            "category":"Professional",
            "subcategory":"Business Services",
            "type":"Services"
        }
    ],
    "sg:phone":"+44 20 8301 6156",
    "sg:postcode":"DA7 4SY",
    "sg:province":"Kent",
    "sg:tags":[
        "registrar"
    ],
    "wof:name":"KS Companies",
    "wof:placetype":"venue"
},
  "geometry": {"coordinates":[0.12953,51.472092],"type":"Point"}
}