{
  "type": "Feature",
  "properties": {
    "iso:country":"GB",
    "sg:address":"37 Sadler Road, Brownhills",
    "sg:city":"Walsall",
    "sg:classifiers":[
        {
            "category":"Retail",
            "subcategory":"Driving School",
            "type":"Services"
        }
    ],
    "sg:phone":"+44 1543 378075",
    "sg:postcode":"WS8 6BJ",
    "sg:province":"Staffordshire",
    "wof:name":"D C G School of Motoring",
    "wof:placetype":"venue"
},
  "geometry": {"coordinates":[-1.920391,52.649292],"type":"Point"}
}