{
  "type": "Feature",
  "properties": {
    "addr:full":"22 Clydesdale Enfield Greater London EN3 4RJ",
    "addr:housenumber":"22",
    "addr:postcode":"en3 4rj",
    "addr:street":"Clydesdale",
    "iso:country":"GB",
    "sg:address":"22 Clydesdale",
    "sg:city":"Enfield",
    "sg:classifiers":[
        {
            "category":"Building & Trades",
            "subcategory":"Construction",
            "type":"Services"
        }
    ],
    "sg:phone":"+44 20 8805 2351",
    "sg:postcode":"EN3 4RJ",
    "sg:province":"Greater London",
    "sg:tags":[
        "demolition",
        "contractor"
    ],
    "wof:name":"Langton Bros",
    "wof:placetype":"venue"
},
  "geometry": {"coordinates":[-0.0423169993,51.6469917297],"type":"Point"}
}