{
  "type": "Feature",
  "properties": {
    "addr:full":"Pump Street, Orford Woodbridge Suffolk IP12 2LZ",
    "addr:postcode":"ip12 2lz",
    "addr:street":"Pump Street",
    "iso:country":"GB",
    "sg:address":"Pump Street, Orford",
    "sg:city":"Woodbridge",
    "sg:classifiers":[
        {
            "category":"Government",
            "subcategory":"Post Office",
            "type":"Public Place"
        },
        {
            "category":"Food & Beverages",
            "subcategory":"Groceries & Convenience Stores",
            "type":"Retail Goods"
        }
    ],
    "sg:phone":"+44 1394 450201",
    "sg:postcode":"IP12 2LZ",
    "sg:province":"Suffolk",
    "wof:name":"Orford Supply Stores",
    "wof:placetype":"venue"
},
  "geometry": {"coordinates":[1.5332560539,52.0945892334],"type":"Point"}
}