{
  "type": "Feature",
  "properties": {
    "addr:full":"90 Glebe Way West Wickham Kent BR4 0SA",
    "addr:housenumber":"90",
    "addr:postcode":"br4 0sa",
    "addr:street":"Glebe Way",
    "iso:country":"GB",
    "sg:address":"90 Glebe Way",
    "sg:city":"West Wickham",
    "sg:classifiers":[
        {
            "category":"Arts & Performance",
            "subcategory":"Music",
            "type":"Entertainment"
        }
    ],
    "sg:phone":"+44 20 8776 0663",
    "sg:postcode":"BR4 0SA",
    "sg:province":"Kent",
    "sg:tags":[
        "mobile",
        "disco"
    ],
    "wof:name":"The Party People",
    "wof:placetype":"venue"
},
  "geometry": {"coordinates":[-0.009176,51.3743591309],"type":"Point"}
}