{
  "type": "Feature",
  "properties": {
    "iso:country":"GB",
    "sg:address":"Burlington House, 10-11 Ribblesdale Place",
    "sg:city":"Preston",
    "sg:classifiers":[
        {
            "category":"Professional",
            "subcategory":"Computer Services",
            "type":"Services"
        }
    ],
    "sg:phone":"+44 1772 204096",
    "sg:postcode":"PR1 3NA",
    "sg:province":"Lancashire",
    "sg:tags":[
        "information"
    ],
    "wof:name":"Preston Care & Repair Ltd.",
    "wof:placetype":"venue"
},
  "geometry": {"coordinates":[-2.7002770901,53.7543678284],"type":"Point"}
}