{
  "type": "Feature",
  "properties": {
    "iso:country":"GB",
    "sg:address":"30 Histon Road, Cottenham",
    "sg:city":"Cambridge",
    "sg:classifiers":[
        {
            "category":"Wholesale",
            "subcategory":"Machinery & Supplies",
            "type":"Manufacturing & Wholesale Goods"
        },
        {
            "category":"Building & Trades",
            "subcategory":"Construction",
            "type":"Services"
        }
    ],
    "sg:phone":"+44 1954 250221",
    "sg:postcode":"CB4 8UD",
    "sg:province":"Cambridgeshire",
    "sg:tags":[
        "builder",
        "pump"
    ],
    "wof:name":"G W Lack & Sons Ltd.",
    "wof:placetype":"venue"
},
  "geometry": {"coordinates":[0.121285,52.280746],"type":"Point"}
}