{
  "type": "Feature",
  "properties": {
    "addr:full":"294 Highfield Rd Blackpool Lancashire FY4 3JU",
    "addr:housenumber":"294",
    "addr:postcode":"fy4 3ju",
    "addr:street":"Highfield Rd",
    "iso:country":"GB",
    "sg:address":"294 Highfield Rd",
    "sg:city":"Blackpool",
    "sg:classifiers":[
        {
            "category":"Food & Beverages",
            "subcategory":"Supermarket",
            "type":"Retail Goods"
        }
    ],
    "sg:postcode":"FY4 3JU",
    "sg:province":"Lancashire",
    "wof:name":"A R Choudhuri",
    "wof:placetype":"venue"
},
  "geometry": {"coordinates":[-3.032688,53.788136],"type":"Point"}
}