{
  "type": "Feature",
  "properties": {
    "iso:country":"GB",
    "sg:address":"108 St Leonards Road, East Sheen",
    "sg:city":"Richmond",
    "sg:classifiers":[
        {
            "category":"Building & Trades",
            "subcategory":"Construction",
            "type":"Services"
        }
    ],
    "sg:phone":"+44 20 8876 2495",
    "sg:postcode":"TW10 7NJ",
    "sg:province":"Greater London",
    "sg:tags":[
        "roofing"
    ],
    "wof:name":"Sheen Roofing",
    "wof:placetype":"venue"
},
  "geometry": {"coordinates":[-0.3174,51.436562],"type":"Point"}
}