{
  "type": "Feature",
  "properties": {
    "iso:country":"GB",
    "sg:address":"9 Hedge Hill Rd, East Challow",
    "sg:city":"Wantage",
    "sg:classifiers":[
        {
            "category":"Professional",
            "type":"Services"
        }
    ],
    "sg:phone":"+44 1235 772615",
    "sg:postcode":"OX12 9SD",
    "sg:province":"Berkshire",
    "sg:tags":[
        "interior",
        "furnishers",
        "designer"
    ],
    "wof:name":"S.O.D.C.",
    "wof:placetype":"venue"
},
  "geometry": {"coordinates":[-1.4533330202,51.5901374817],"type":"Point"}
}