{
  "type": "Feature",
  "properties": {
    "iso:country":"GB",
    "sg:address":"34b Christchurch Road",
    "sg:city":"Ringwood",
    "sg:classifiers":[
        {
            "category":"Fast Food",
            "type":"Food & Drink"
        }
    ],
    "sg:phone":"+44 1425 472555",
    "sg:postcode":"BH24 1DN",
    "sg:province":"Dorset",
    "sg:tags":[
        "away",
        "take"
    ],
    "wof:name":"Toni's Pizza Chef",
    "wof:placetype":"venue"
},
  "geometry": {"coordinates":[-1.7893350124,50.845085144],"type":"Point"}
}