{
  "type": "Feature",
  "properties": {
    "addr:full":"Red Marley, Gurney Slade Bath Somerset BA3 4TG",
    "addr:postcode":"ba3 4tg",
    "addr:street":"Slade",
    "iso:country":"GB",
    "sg:address":"Red Marley, Gurney Slade",
    "sg:city":"Bath",
    "sg:classifiers":[
        {
            "category":"Autos & Motor Vehicles",
            "subcategory":"Automobile Sales",
            "type":"Retail Goods"
        }
    ],
    "sg:postcode":"BA3 4TG",
    "sg:province":"Somerset",
    "sg:tags":[
        "car"
    ],
    "wof:name":"Bitton Cars Ltd",
    "wof:placetype":"venue"
},
  "geometry": {"coordinates":[-2.538593,51.241013],"type":"Point"}
}