{
  "type": "Feature",
  "properties": {
    "addr:full":"62 Portland Rd Weymouth Dorset DT4 9AB",
    "addr:housenumber":"62",
    "addr:postcode":"dt4 9ab",
    "addr:street":"Portland Rd",
    "iso:country":"GB",
    "sg:address":"62 Portland Rd",
    "sg:city":"Weymouth",
    "sg:classifiers":[
        {
            "category":"Home & Garden",
            "subcategory":"Household Appliances",
            "type":"Retail Goods"
        }
    ],
    "sg:postcode":"DT4 9AB",
    "sg:province":"Dorset",
    "sg:tags":[
        "domestic",
        "centre"
    ],
    "wof:name":"Pankhurst,Mark,",
    "wof:placetype":"venue"
},
  "geometry": {"coordinates":[-2.4756000042,50.5942573547],"type":"Point"}
}