{
  "type": "Feature",
  "properties": {
    "iso:country":"GB",
    "sg:address":"103 Tilehouse Way, Denham",
    "sg:city":"Uxbridge",
    "sg:classifiers":[
        {
            "category":"Retail",
            "subcategory":"Repair Shop",
            "type":"Services"
        }
    ],
    "sg:postcode":"UB9 5JA",
    "sg:province":"Buckinghamshire",
    "sg:tags":[
        "upholsterer"
    ],
    "wof:name":"Uticolor",
    "wof:placetype":"venue"
},
  "geometry": {"coordinates":[-0.503547,51.57999],"type":"Point"}
}