{
  "type": "Feature",
  "properties": {
    "addr:full":"122 Prestbury Road Cheltenham Gloucestershire GL52 2DP",
    "addr:housenumber":"122",
    "addr:postcode":"gl52 2dp",
    "addr:street":"Prestbury Road",
    "iso:country":"GB",
    "sg:address":"122 Prestbury Road",
    "sg:city":"Cheltenham",
    "sg:classifiers":[
        {
            "category":"Manufacturing",
            "subcategory":"Tools & Machinery",
            "type":"Manufacturing & Wholesale Goods"
        }
    ],
    "sg:phone":"+44 1242 526376",
    "sg:postcode":"GL52 2DP",
    "sg:province":"Gloucestershire",
    "sg:tags":[
        "society",
        "friendly"
    ],
    "wof:name":"Trident Insurance Consultants",
    "wof:placetype":"venue"
},
  "geometry": {"coordinates":[-2.0605170727,51.9082374573],"type":"Point"}
}