{
  "type": "Feature",
  "properties": {
    "iso:country":"GB",
    "sg:address":"Rugby Camp, Norway Road",
    "sg:city":"Portsmouth",
    "sg:classifiers":[
        {
            "category":"Arena",
            "subcategory":"Sports Club",
            "type":"Entertainment"
        }
    ],
    "sg:phone":"+44 23 9266 0610",
    "sg:postcode":"PO3 5HR",
    "sg:province":"Hampshire",
    "wof:name":"Portsmouth Rugby Football Club",
    "wof:placetype":"venue"
},
  "geometry": {"coordinates":[-1.05575,50.822632],"type":"Point"}
}