{
  "type": "Feature",
  "properties": {
    "addr:full":"2 Stonebridge St, East Park Rd Leicester Leicestershire LE5 3PA",
    "addr:housenumber":"2",
    "addr:postcode":"le5 3pa",
    "addr:street":"Stonebridge St East Park Rd",
    "iso:country":"GB",
    "sg:address":"2 Stonebridge St, East Park Rd",
    "sg:city":"Leicester",
    "sg:classifiers":[
        {
            "category":"Shopping",
            "subcategory":"Used Merchandise",
            "type":"Retail Goods"
        }
    ],
    "sg:phone":"+44 116 276 6107",
    "sg:postcode":"LE5 3PA",
    "sg:province":"Leicestershire",
    "sg:tags":[
        "shop",
        "second-hand"
    ],
    "wof:name":"A Start Mart",
    "wof:placetype":"venue"
},
  "geometry": {"coordinates":[-1.0999499559,52.6385536194],"type":"Point"}
}