{
  "type": "Feature",
  "properties": {
    "addr:full":"28 Streatham High Road London Greater London SW16 1DB",
    "addr:housenumber":"28",
    "addr:postcode":"sw16 1db",
    "addr:street":"Streatham High Road",
    "iso:country":"GB",
    "sg:address":"28 Streatham High Road",
    "sg:city":"London",
    "sg:classifiers":[
        {
            "category":"Insurance",
            "subcategory":"Insurance Agent",
            "type":"Services"
        }
    ],
    "sg:phone":"+44 20 8769 7718",
    "sg:postcode":"SW16 1DB",
    "sg:province":"Greater London",
    "wof:name":"T W Mallett (Insurance Services) Ltd.",
    "wof:placetype":"venue"
},
  "geometry": {"coordinates":[-0.127681,51.437359],"type":"Point"}
}