{
  "type": "Feature",
  "properties": {
    "addr:full":"1 Parklands, Bramhope Leeds West Yorkshire LS16 9AH",
    "addr:housenumber":"1",
    "addr:postcode":"ls16 9ah",
    "addr:street":"Parklands",
    "iso:country":"GB",
    "sg:address":"1 Parklands, Bramhope",
    "sg:city":"Leeds",
    "sg:classifiers":[
        {
            "category":"Taxi",
            "type":"Transportation"
        }
    ],
    "sg:phone":"+44 113 284 3853",
    "sg:postcode":"LS16 9AH",
    "sg:province":"West Yorkshire",
    "sg:tags":[
        "mini",
        "cab"
    ],
    "wof:name":"Bramhope Central Private Hire",
    "wof:placetype":"venue"
},
  "geometry": {"coordinates":[-1.620522,53.88361],"type":"Point"}
}