{
  "type": "Feature",
  "properties": {
    "addr:full":"16 Whiteness Green, Kingsgate Broadstairs Kent CT10 3JS",
    "addr:housenumber":"16",
    "addr:postcode":"ct10 3js",
    "addr:street":"Whiteness Green Kingsgate",
    "iso:country":"GB",
    "sg:address":"16 Whiteness Green, Kingsgate",
    "sg:city":"Broadstairs",
    "sg:classifiers":[
        {
            "category":"Shopping",
            "subcategory":"Clothing, Apparel, & Fashions",
            "type":"Retail Goods"
        }
    ],
    "sg:postcode":"CT10 3JS",
    "sg:province":"Kent",
    "sg:tags":[
        "clothing"
    ],
    "wof:name":"D R Hunt",
    "wof:placetype":"venue"
},
  "geometry": {"coordinates":[1.4325489998,51.3810195923],"type":"Point"}
}