{
  "type": "Feature",
  "properties": {
    "addr:full":"31 Waddon Rd Croydon Surrey CR0 4LH",
    "addr:housenumber":"31",
    "addr:postcode":"cr0 4lh",
    "addr:street":"Waddon Rd",
    "iso:country":"GB",
    "sg:address":"31 Waddon Rd",
    "sg:city":"Croydon",
    "sg:classifiers":[
        {
            "category":"Professional",
            "subcategory":"Computer Services",
            "type":"Services"
        }
    ],
    "sg:phone":"+44 20 8667 9998",
    "sg:postcode":"CR0 4LH",
    "sg:province":"Surrey",
    "sg:tags":[
        "system",
        "software"
    ],
    "wof:name":"UFO Computer Supplies",
    "wof:placetype":"venue"
},
  "geometry": {"coordinates":[-0.1095630005,51.3716773987],"type":"Point"}
}