{
  "type": "Feature",
  "properties": {
    "addr:full":"Wreake Ho Farm, Ratcliffe On The Wreake Leicester Leicestershire LE7 4SH",
    "addr:housenumber":"ratcliffe;the wreake",
    "addr:postcode":"le7 4sh",
    "iso:country":"GB",
    "sg:address":"Wreake Ho Farm, Ratcliffe On The Wreake",
    "sg:city":"Leicester",
    "sg:classifiers":[
        {
            "category":"Farming",
            "subcategory":"Farm",
            "type":"Manufacturing & Wholesale Goods"
        }
    ],
    "sg:postcode":"LE7 4SH",
    "sg:province":"Leicestershire",
    "sg:tags":[
        "mixed",
        "crop"
    ],
    "wof:name":"Sherwood Farms",
    "wof:placetype":"venue"
},
  "geometry": {"coordinates":[-1.033582,52.72982],"type":"Point"}
}