{
  "type": "Feature",
  "properties": {
    "addr:full":"Leigh Road Chulmleigh Devon EX18 7JN",
    "addr:postcode":"ex18 7jn",
    "addr:street":"Leigh Road",
    "iso:country":"GB",
    "sg:address":"Leigh Road",
    "sg:city":"Chulmleigh",
    "sg:classifiers":[
        {
            "category":"Sports & Exercise",
            "subcategory":"Stables",
            "type":"Entertainment"
        },
        {
            "category":"Personal",
            "subcategory":"Adult",
            "type":"Services"
        }
    ],
    "sg:phone":"+44 1769 580366",
    "sg:postcode":"EX18 7JN",
    "sg:province":"Devon",
    "sg:tags":[
        "schools",
        "riding",
        "livery",
        "equestrian",
        "centre"
    ],
    "wof:name":"Boldtry Riding Stables",
    "wof:placetype":"venue"
},
  "geometry": {"coordinates":[-3.8731880188,50.9139175415],"type":"Point"}
}