{
  "type": "Feature",
  "properties": {
    "addr:full":"50 St Marks Road Chester Cheshire CH4 8DQ",
    "addr:housenumber":"50",
    "addr:postcode":"ch4 8dq",
    "addr:street":"St Marks Road",
    "iso:country":"GB",
    "sg:address":"50 St Marks Road",
    "sg:city":"Chester",
    "sg:classifiers":[
        {
            "category":"Retail",
            "subcategory":"Auto Repair",
            "type":"Services"
        }
    ],
    "sg:phone":"+44 1244 681679",
    "sg:postcode":"CH4 8DQ",
    "sg:province":"Cheshire",
    "sg:tags":[
        "modification",
        "garage",
        "related"
    ],
    "wof:name":"Saltney Service Station",
    "wof:placetype":"venue"
},
  "geometry": {"coordinates":[-2.9158079624,53.1791419983],"type":"Point"}
}