{
  "type": "Feature",
  "properties": {
    "addr:full":"21 Newton Road, Mumbles Swansea Swansea SA3 4AS",
    "addr:housenumber":"21",
    "addr:postcode":"sa3 4as",
    "addr:street":"Newton Road",
    "iso:country":"GB",
    "sg:address":"21 Newton Road, Mumbles",
    "sg:city":"Swansea",
    "sg:classifiers":[
        {
            "category":"Travel",
            "subcategory":"Travel Agent",
            "type":"Entertainment"
        }
    ],
    "sg:phone":"+44 1792 366206",
    "sg:postcode":"SA3 4AS",
    "sg:province":"Swansea",
    "wof:name":"Going Places Leisure Travel Ltd.",
    "wof:placetype":"venue"
},
  "geometry": {"coordinates":[-3.999755,51.575481],"type":"Point"}
}