{
  "type": "Feature",
  "properties": {
    "addr:full":"296 Sangley Rd Catford Greater London SE6 2JT",
    "addr:housenumber":"296",
    "addr:postcode":"se6 2jt",
    "addr:street":"Sangley Rd",
    "iso:country":"GB",
    "sg:address":"296 Sangley Rd",
    "sg:city":"Catford",
    "sg:classifiers":[
        {
            "category":"Shopping",
            "subcategory":"News",
            "type":"Retail Goods"
        }
    ],
    "sg:phone":"+44 20 8244 3918",
    "sg:postcode":"SE6 2JT",
    "sg:province":"Greater London",
    "sg:tags":[
        "newsagent"
    ],
    "wof:name":"Turners",
    "wof:placetype":"venue"
},
  "geometry": {"coordinates":[-0.0117009999,51.4423751831],"type":"Point"}
}