{
  "type": "Feature",
  "properties": {
    "iso:country":"GB",
    "sg:address":"Elms Farm, Dadlington La",
    "sg:city":"Leicester",
    "sg:classifiers":[
        {
            "category":"Building & Trades",
            "subcategory":"Cleaning & Sanitation",
            "type":"Services"
        }
    ],
    "sg:phone":"+44 1455 841297",
    "sg:postcode":"LE9 8JL",
    "sg:province":"Leicestershire",
    "sg:tags":[
        "blast"
    ],
    "wof:name":"Richard Andrews",
    "wof:placetype":"venue"
},
  "geometry": {"coordinates":[-1.3613239527,52.5835037231],"type":"Point"}
}