{
  "type": "Feature",
  "properties": {
    "iso:country":"GB",
    "sg:address":"Biggin Lane, Chadwell St Mary",
    "sg:city":"Grays",
    "sg:classifiers":[
        {
            "category":"Sports & Exercise",
            "subcategory":"Stables",
            "type":"Entertainment"
        }
    ],
    "sg:phone":"+44 1375 858038",
    "sg:postcode":"RM16 4LT",
    "sg:province":"Essex",
    "sg:tags":[
        "education",
        "equestrian"
    ],
    "wof:name":"Tally-Ho Riding School",
    "wof:placetype":"venue"
},
  "geometry": {"coordinates":[0.371218,51.47506],"type":"Point"}
}