{
  "type": "Feature",
  "properties": {
    "iso:country":"GB",
    "sg:address":"St Georges Pier",
    "sg:city":"Menai Bridge",
    "sg:classifiers":[
        {
            "category":"Recreation",
            "subcategory":"Marina",
            "type":"Entertainment"
        },
        {
            "category":"Government",
            "subcategory":"Office",
            "type":"Public Place"
        }
    ],
    "sg:phone":"+44 1248 712312",
    "sg:postcode":"LL59 5EY",
    "sg:province":"Isle of Anglesey",
    "sg:tags":[
        "local",
        "mooring",
        "boat"
    ],
    "wof:name":"Piermasters Office",
    "wof:placetype":"venue"
},
  "geometry": {"coordinates":[-4.161559,53.227612],"type":"Point"}
}