{
  "type": "Feature",
  "properties": {
    "iso:country":"GB",
    "sg:address":"The Grange, Manor Road",
    "sg:city":"Doncaster",
    "sg:classifiers":[
        {
            "category":"Organizations",
            "subcategory":"Membership Organization",
            "type":"Services"
        }
    ],
    "sg:postcode":"DN7 6SB",
    "sg:province":"South Yorkshire",
    "sg:tags":[
        "club"
    ],
    "wof:name":"Ryburn Management Services Ltd.",
    "wof:placetype":"venue"
},
  "geometry": {"coordinates":[-1.0072380304,53.5794143677],"type":"Point"}
}