{
  "type": "Feature",
  "properties": {
    "addr:full":"51 Maddiston Rd, Brightons Falkirk Falkirk FK2 0JP",
    "addr:housenumber":"51",
    "addr:postcode":"fk2 0jp",
    "addr:street":"Maddiston Rd",
    "iso:country":"GB",
    "sg:address":"51 Maddiston Rd, Brightons",
    "sg:city":"Falkirk",
    "sg:classifiers":[
        {
            "category":"Farming",
            "subcategory":"Livestock Farm",
            "type":"Manufacturing & Wholesale Goods"
        }
    ],
    "sg:postcode":"FK2 0JP",
    "sg:province":"Falkirk",
    "sg:tags":[
        "breeder"
    ],
    "wof:name":"Brodie,Alison,",
    "wof:placetype":"venue"
},
  "geometry": {"coordinates":[-3.720429,55.981373],"type":"Point"}
}