{
  "type": "Feature",
  "properties": {
    "iso:country":"GB",
    "sg:address":"131 Bell Green Road",
    "sg:city":"Coventry",
    "sg:classifiers":[
        {
            "category":"Home & Garden",
            "subcategory":"Building Materials",
            "type":"Retail Goods"
        },
        {
            "category":"Building & Trades",
            "subcategory":"Construction",
            "type":"Services"
        }
    ],
    "sg:phone":"+44 24 7666 1639",
    "sg:postcode":"CV6 7GW",
    "sg:province":"Warwickshire",
    "sg:tags":[
        "fencing",
        "contractor"
    ],
    "wof:name":"R B Landscapes",
    "wof:placetype":"venue"
},
  "geometry": {"coordinates":[-1.483148,52.431656],"type":"Point"}
}