{
  "type": "Feature",
  "properties": {
    "iso:country":"GB",
    "sg:address":"Westwood Rd",
    "sg:city":"Broadstairs",
    "sg:classifiers":[
        {
            "category":"Utilities",
            "subcategory":"Refuse",
            "type":"Services"
        }
    ],
    "sg:postcode":"CT10 2NZ",
    "sg:province":"Kent",
    "sg:tags":[
        "disposal",
        "waste"
    ],
    "wof:name":"Eco-Clear Ltd",
    "wof:placetype":"venue"
},
  "geometry": {"coordinates":[1.398035,51.360626],"type":"Point"}
}