{
  "type": "Feature",
  "properties": {
    "iso:country":"GB",
    "sg:address":"Fieldhouse, Windmill Road, Bramham",
    "sg:city":"Wetherby",
    "sg:classifiers":[
        {
            "category":"Manufacturing",
            "subcategory":"Lumber",
            "type":"Manufacturing & Wholesale Goods"
        }
    ],
    "sg:phone":"+44 1937 843392",
    "sg:postcode":"LS23 6QP",
    "sg:province":"West Yorkshire",
    "sg:tags":[
        "importer",
        "merchants",
        "agent",
        "timber"
    ],
    "wof:name":"Rhodes (Timber Contractors) Ltd.",
    "wof:placetype":"venue"
},
  "geometry": {"coordinates":[-1.355319,53.880943],"type":"Point"}
}