{
  "type": "Feature",
  "properties": {
    "addr:full":"8 Meadow Close, Trench Telford Shropshire TF2 6PA",
    "addr:housenumber":"8",
    "addr:postcode":"tf2 6pa",
    "addr:street":"Meadow Close",
    "iso:country":"GB",
    "sg:address":"8 Meadow Close, Trench",
    "sg:city":"Telford",
    "sg:classifiers":[
        {
            "category":"Building & Trades",
            "subcategory":"Construction",
            "type":"Services"
        }
    ],
    "sg:phone":"+44 1952 608180",
    "sg:postcode":"TF2 6PA",
    "sg:province":"Shropshire",
    "sg:tags":[
        "joiner",
        "carpenter"
    ],
    "wof:name":"David Charles Lewis",
    "wof:placetype":"venue"
},
  "geometry": {"coordinates":[-2.4645149708,52.7107620239],"type":"Point"}
}