{
  "type": "Feature",
  "properties": {
    "addr:full":"77 Deacon Road London Greater London NW2 5NN",
    "addr:housenumber":"77",
    "addr:postcode":"nw2 5nn",
    "addr:street":"Deacon Road",
    "iso:country":"GB",
    "sg:address":"77 Deacon Road",
    "sg:city":"London",
    "sg:classifiers":[
        {
            "category":"Building & Trades",
            "subcategory":"Cleaning & Sanitation",
            "type":"Services"
        },
        {
            "category":"Food & Beverages",
            "subcategory":"Liquor & Beverages",
            "type":"Retail Goods"
        },
        {
            "category":"Building & Trades",
            "subcategory":"Construction",
            "type":"Services"
        }
    ],
    "sg:phone":"+44 20 8459 5764",
    "sg:postcode":"NW2 5NN",
    "sg:province":"Greater London",
    "sg:tags":[
        "flooring",
        "wines",
        "sweep",
        "beer",
        "spirit",
        "chimney"
    ],
    "wof:name":"A B V",
    "wof:placetype":"venue"
},
  "geometry": {"coordinates":[-0.237574,51.550503],"type":"Point"}
}