{
  "type": "Feature",
  "properties": {
    "iso:country":"GB",
    "sg:address":"500 Sheffield Road, Whittington Moor",
    "sg:city":"Chesterfield",
    "sg:classifiers":[
        {
            "category":"Organizations",
            "subcategory":"Membership Organization",
            "type":"Services"
        }
    ],
    "sg:phone":"+44 1246 452246",
    "sg:postcode":"S41 8LP",
    "sg:province":"Derbyshire",
    "sg:tags":[
        "club"
    ],
    "wof:name":"Chesters Club",
    "wof:placetype":"venue"
},
  "geometry": {"coordinates":[-1.428086,53.257538],"type":"Point"}
}