{
  "type": "Feature",
  "properties": {
    "iso:country":"GB",
    "sg:address":"Oak Lodge, Nightingales Lane",
    "sg:city":"Chalfont St Giles",
    "sg:classifiers":[
        {
            "category":"Retail",
            "subcategory":"Auto Rental",
            "type":"Services"
        },
        {
            "category":"Autos & Motor Vehicles",
            "subcategory":"Motorcycle Sales",
            "type":"Retail Goods"
        }
    ],
    "sg:postcode":"HP8 4SF",
    "sg:province":"Buckinghamshire",
    "sg:tags":[
        "chauffeur",
        "car",
        "driven"
    ],
    "wof:name":"Robinsons Executive Car Hire",
    "wof:placetype":"venue"
},
  "geometry": {"coordinates":[-0.555641,51.641876],"type":"Point"}
}