{
  "type": "Feature",
  "properties": {
    "iso:country":"GB",
    "sg:address":"50 Taverner Clo",
    "sg:city":"Basingstoke",
    "sg:classifiers":[
        {
            "category":"Retail",
            "subcategory":"Auto Repair",
            "type":"Services"
        }
    ],
    "sg:phone":"+44 7836 555733",
    "sg:postcode":"RG21 4JF",
    "sg:province":"Hampshire",
    "sg:tags":[
        "electrician"
    ],
    "wof:name":"Autolec",
    "wof:placetype":"venue"
},
  "geometry": {"coordinates":[-1.0761940479,51.2745704651],"type":"Point"}
}