{
  "type": "Feature",
  "properties": {
    "addr:full":"Red Roofs, Crowhurst Road Lingfield Surrey RH7 6DG",
    "addr:postcode":"rh7 6dg",
    "addr:street":"Crowhurst Road",
    "iso:country":"GB",
    "sg:address":"Red Roofs, Crowhurst Road",
    "sg:city":"Lingfield",
    "sg:classifiers":[
        {
            "category":"Professional",
            "subcategory":"Business Services",
            "type":"Services"
        }
    ],
    "sg:phone":"+44 1342 832559",
    "sg:postcode":"RH7 6DG",
    "sg:province":"Surrey",
    "sg:tags":[
        "bookmaker"
    ],
    "wof:name":"T G R Services",
    "wof:placetype":"venue"
},
  "geometry": {"coordinates":[-0.0196860004,51.1748199463],"type":"Point"}
}