{
  "type": "Feature",
  "properties": {
    "iso:country":"GB",
    "sg:address":"16 Langlands Ave, Kelvinsouth Business Pk",
    "sg:city":"Glasgow",
    "sg:classifiers":[
        {
            "category":"Manufacturing",
            "subcategory":"Buildings",
            "type":"Manufacturing & Wholesale Goods"
        }
    ],
    "sg:phone":"+44 1355 234482",
    "sg:postcode":"G75 0YG",
    "sg:province":"South Lanarkshire",
    "sg:tags":[
        "system",
        "air conditioning"
    ],
    "wof:name":"Mitchell Turnkey Ltd",
    "wof:placetype":"venue"
},
  "geometry": {"coordinates":[-4.172489,55.739254],"type":"Point"}
}