{
  "type": "Feature",
  "properties": {
    "addr:full":"Unit 6 Swansey Mill, Mill Lane, Whitle-le-woods Chorley Lancashire PR6 7LX",
    "addr:housenumber":"unit 6",
    "addr:postcode":"pr6 7lx",
    "addr:street":"Swansey Mill Mill Lane",
    "iso:country":"GB",
    "sg:address":"Unit 6 Swansey Mill, Mill Lane, Whitle-le-woods",
    "sg:city":"Chorley",
    "sg:classifiers":[
        {
            "category":"Building & Trades",
            "subcategory":"Construction",
            "type":"Services"
        }
    ],
    "sg:phone":"+44 1257 263976",
    "sg:postcode":"PR6 7LX",
    "sg:province":"Lancashire",
    "sg:tags":[
        "builder"
    ],
    "wof:name":"M J Fellows Building Contractors",
    "wof:placetype":"venue"
},
  "geometry": {"coordinates":[-2.6359500885,53.693271637],"type":"Point"}
}