{
  "type": "Feature",
  "properties": {
    "addr:full":"Rear Of 48-50, Humber Street Cleethorpes Lincolnshire DN35 8NN",
    "addr:housenumber":"rear of 48-50",
    "addr:postcode":"dn35 8nn",
    "addr:street":"Humber Street",
    "iso:country":"GB",
    "sg:address":"Rear Of 48-50, Humber Street",
    "sg:city":"Cleethorpes",
    "sg:classifiers":[
        {
            "category":"Home & Garden",
            "subcategory":"Building Materials",
            "type":"Retail Goods"
        },
        {
            "category":"Building & Trades",
            "subcategory":"Construction",
            "type":"Services"
        }
    ],
    "sg:phone":"+44 1472 694739",
    "sg:postcode":"DN35 8NN",
    "sg:province":"Lincolnshire",
    "sg:tags":[
        "insulation",
        "installers"
    ],
    "wof:name":"W & K Insulation Ltd",
    "wof:placetype":"venue"
},
  "geometry": {"coordinates":[-0.0393589996,53.5594902039],"type":"Point"}
}