{
  "type": "Feature",
  "properties": {
    "addr:full":"37 Clifton Road Rugby Warwickshire CV21 3PY",
    "addr:housenumber":"37",
    "addr:postcode":"cv21 3py",
    "addr:street":"Clifton Road",
    "iso:country":"GB",
    "sg:address":"37 Clifton Road",
    "sg:city":"Rugby",
    "sg:classifiers":[
        {
            "category":"Fast Food",
            "type":"Food & Drink"
        }
    ],
    "sg:phone":"+44 1788 546883",
    "sg:postcode":"CV21 3PY",
    "sg:province":"Warwickshire",
    "sg:tags":[
        "away",
        "take"
    ],
    "wof:name":"Kfc",
    "wof:placetype":"venue"
},
  "geometry": {"coordinates":[-1.256069,52.371944],"type":"Point"}
}