{
  "type": "Feature",
  "properties": {
    "addr:full":"Hockley House Farm, Marton Rugby Northamptonshire CV23 9RN",
    "addr:postcode":"cv23 9rn",
    "iso:country":"GB",
    "sg:address":"Hockley House Farm, Marton",
    "sg:city":"Rugby",
    "sg:classifiers":[
        {
            "category":"Farming",
            "subcategory":"Farm",
            "type":"Manufacturing & Wholesale Goods"
        }
    ],
    "sg:phone":"+44 1926 632260",
    "sg:postcode":"CV23 9RN",
    "sg:province":"Northamptonshire",
    "sg:tags":[
        "mixed",
        "crop"
    ],
    "wof:name":"Robson G & J C",
    "wof:placetype":"venue"
},
  "geometry": {"coordinates":[-1.402275,52.315662],"type":"Point"}
}