{
  "type": "Feature",
  "properties": {
    "addr:full":"210 Church Road London Greater London E10 7JQ",
    "addr:housenumber":"210",
    "addr:postcode":"e10 7jq",
    "addr:street":"Church Road",
    "iso:country":"GB",
    "sg:address":"210 Church Road",
    "sg:city":"London",
    "sg:classifiers":[
        {
            "category":"Autos & Motor Vehicles",
            "subcategory":"Automobile Sales",
            "type":"Retail Goods"
        }
    ],
    "sg:postcode":"E10 7JQ",
    "sg:province":"Greater London",
    "sg:tags":[
        "car"
    ],
    "wof:name":"Zenith Car Centre",
    "wof:placetype":"venue"
},
  "geometry": {"coordinates":[-0.0217569992,51.5668029785],"type":"Point"}
}