{
  "type": "Feature",
  "properties": {
    "addr:full":"19 Meadow Road, Beeston Nottingham Nottinghamshire NG9 1JP",
    "addr:housenumber":"19",
    "addr:postcode":"ng9 1jp",
    "addr:street":"Meadow Road",
    "iso:country":"GB",
    "sg:address":"19 Meadow Road, Beeston",
    "sg:city":"Nottingham",
    "sg:classifiers":[
        {
            "category":"Travel",
            "subcategory":"Hotels & Motels",
            "type":"Entertainment"
        }
    ],
    "sg:phone":"+44 115 922 7509",
    "sg:postcode":"NG9 1JP",
    "sg:province":"Nottinghamshire",
    "wof:name":"P Bowers & M Brierley",
    "wof:placetype":"venue"
},
  "geometry": {"coordinates":[-1.204453,52.919411],"type":"Point"}
}