{
  "type": "Feature",
  "properties": {
    "iso:country":"GB",
    "sg:address":"3 Guns Lane",
    "sg:city":"West Bromwich",
    "sg:classifiers":[
        {
            "category":"Professional",
            "subcategory":"Engineering",
            "type":"Services"
        }
    ],
    "sg:phone":"+44 121 525 5922",
    "sg:postcode":"B70 9HS",
    "sg:province":"West Midlands",
    "wof:name":"Midland Trading & Manufacturing",
    "wof:placetype":"venue"
},
  "geometry": {"coordinates":[-2.0034120083,52.5236206055],"type":"Point"}
}