{
  "type": "Feature",
  "properties": {
    "iso:country":"GB",
    "sg:address":"37 Portsmouth Road",
    "sg:city":"Liphook",
    "sg:classifiers":[
        {
            "category":"Education",
            "subcategory":"Music School",
            "type":"Public Place"
        }
    ],
    "sg:postcode":"GU30 7DJ",
    "sg:province":"Hampshire",
    "sg:tags":[
        "teacher"
    ],
    "wof:name":"Geoffrey Lea",
    "wof:placetype":"venue"
},
  "geometry": {"coordinates":[-0.8031389713,51.0733718872],"type":"Point"}
}