{
  "type": "Feature",
  "properties": {
    "addr:full":"69 High Street, Cheadle Stoke-on-trent Staffordshire ST10 1AN",
    "addr:housenumber":"69",
    "addr:postcode":"st10 1an",
    "addr:street":"High Street Cheadle",
    "iso:country":"GB",
    "sg:address":"69 High Street, Cheadle",
    "sg:city":"Stoke-on-trent",
    "sg:classifiers":[
        {
            "category":"Travel",
            "subcategory":"Hotels & Motels",
            "type":"Entertainment"
        }
    ],
    "sg:phone":"+44 1538 753116",
    "sg:postcode":"ST10 1AN",
    "sg:province":"Staffordshire",
    "wof:name":"Royal Oak Hotel",
    "wof:placetype":"venue"
},
  "geometry": {"coordinates":[-1.990906,52.986328],"type":"Point"}
}