{
  "type": "Feature",
  "properties": {
    "iso:country":"GB",
    "sg:address":"C1 Worth Corner, Turners Hill Rd, Pound Hill",
    "sg:city":"Crawley",
    "sg:classifiers":[
        {
            "category":"Building & Trades",
            "subcategory":"Landscaping Services",
            "type":"Services"
        }
    ],
    "sg:postcode":"RH10 7SL",
    "sg:province":"Surrey",
    "sg:tags":[
        "horticultural",
        "consultant"
    ],
    "wof:name":"Ballpoint Office Supplies",
    "wof:placetype":"venue"
},
  "geometry": {"coordinates":[-0.1482840031,51.1207504272],"type":"Point"}
}