{
  "type": "Feature",
  "properties": {
    "iso:country":"GB",
    "sg:address":"28-30 High Street, Boosbeck",
    "sg:city":"Saltburn-by-the-sea",
    "sg:classifiers":[
        {
            "category":"Shopping",
            "subcategory":"Department Store",
            "type":"Retail Goods"
        }
    ],
    "sg:phone":"+44 1287 653246",
    "sg:postcode":"TS12 3AA",
    "sg:province":"North Yorkshire",
    "wof:name":"Naylor's General Store Off Licence",
    "wof:placetype":"venue"
},
  "geometry": {"coordinates":[-0.98237,54.543655],"type":"Point"}
}