{
  "type": "Feature",
  "properties": {
    "addr:full":"114 High Street Chesham Buckinghamshire HP5 1EB",
    "addr:housenumber":"114",
    "addr:postcode":"hp5 1eb",
    "addr:street":"High Street",
    "iso:country":"GB",
    "sg:address":"114 High Street",
    "sg:city":"Chesham",
    "sg:classifiers":[
        {
            "category":"Food & Beverages",
            "subcategory":"Bakery",
            "type":"Retail Goods"
        }
    ],
    "sg:phone":"+44 1494 792564",
    "sg:postcode":"HP5 1EB",
    "sg:province":"Buckinghamshire",
    "sg:tags":[
        "baker"
    ],
    "wof:name":"Channelle",
    "wof:placetype":"venue"
},
  "geometry": {"coordinates":[-0.6126679778,51.7064094543],"type":"Point"}
}