{
  "type": "Feature",
  "properties": {
    "iso:country":"GB",
    "sg:address":"23-25 Regent Street",
    "sg:city":"Swindon",
    "sg:classifiers":[
        {
            "category":"Education",
            "subcategory":"Preschool",
            "type":"Public Place"
        }
    ],
    "sg:phone":"+44 1793 484183",
    "sg:postcode":"SN1 1JL",
    "sg:province":"Wiltshire",
    "sg:tags":[
        "pre-school",
        "playgroups"
    ],
    "wof:name":"Woolworths Play Centre",
    "wof:placetype":"venue"
},
  "geometry": {"coordinates":[-1.783353,51.560337],"type":"Point"}
}