{
  "type": "Feature",
  "properties": {
    "iso:country":"GB",
    "sg:address":"13 North Silver Street",
    "sg:city":"Aberdeen",
    "sg:classifiers":[
        {
            "category":"Bars & Pubs",
            "type":"Food & Drink"
        }
    ],
    "sg:phone":"+44 1224 624258",
    "sg:postcode":"AB10 1RJ",
    "sg:province":"Aberdeen City",
    "sg:tags":[
        "pubs",
        "inn"
    ],
    "wof:name":"The Globe (Aberdeen) Ltd.",
    "wof:placetype":"venue"
},
  "geometry": {"coordinates":[-2.10604,57.146675],"type":"Point"}
}