{
  "type": "Feature",
  "properties": {
    "iso:country":"GB",
    "sg:address":"100 Upper Richmond Road",
    "sg:city":"London",
    "sg:classifiers":[
        {
            "category":"Restaurant",
            "type":"Food & Drink"
        }
    ],
    "sg:phone":"+44 20 8789 3161",
    "sg:postcode":"SW15 2SP",
    "sg:province":"Greater London",
    "sg:tags":[
        "chinese"
    ],
    "wof:name":"Bayee House",
    "wof:placetype":"venue"
},
  "geometry": {"coordinates":[-0.210729003,51.4595108032],"type":"Point"}
}