{
  "type": "Feature",
  "properties": {
    "addr:full":"1 Trinity Pla, Midland Drive Sutton Coldfield West Midlands B72 1TX",
    "addr:housenumber":"1",
    "addr:postcode":"b72 1tx",
    "addr:street":"Trinity Pla Midland Drive",
    "iso:country":"GB",
    "sg:address":"1 Trinity Pla, Midland Drive",
    "sg:city":"Sutton Coldfield",
    "sg:classifiers":[
        {
            "category":"Real Estate",
            "subcategory":"Surveying",
            "type":"Services"
        }
    ],
    "sg:phone":"+44 121 355 5533",
    "sg:postcode":"B72 1TX",
    "sg:province":"West Midlands",
    "sg:tags":[
        "surveyor",
        "quantity"
    ],
    "wof:name":"James R Knowles Ltd.",
    "wof:placetype":"venue"
},
  "geometry": {"coordinates":[-1.8210999966,52.5655097961],"type":"Point"}
}