{
  "type": "Feature",
  "properties": {
    "addr:full":"10 South Drive Banstead Surrey SM7 3BH",
    "addr:housenumber":"10",
    "addr:postcode":"sm7 3bh",
    "addr:street":"South Drive",
    "iso:country":"GB",
    "sg:address":"10 South Drive",
    "sg:city":"Banstead",
    "sg:classifiers":[
        {
            "category":"Professional",
            "subcategory":"Engineering",
            "type":"Services"
        },
        {
            "category":"Building & Trades",
            "subcategory":"Electrical",
            "type":"Services"
        }
    ],
    "sg:phone":"+44 20 8642 4918",
    "sg:postcode":"SM7 3BH",
    "sg:province":"Surrey",
    "sg:tags":[
        "engineer",
        "electrician",
        "contractor"
    ],
    "wof:name":"A Adams",
    "wof:placetype":"venue"
},
  "geometry": {"coordinates":[-0.177882,51.33205],"type":"Point"}
}