{
  "type": "Feature",
  "properties": {
    "addr:full":"Care Of Beatties, 700 Warwick Road Solihull West Midlands B91 3UU",
    "addr:housenumber":"700",
    "addr:postcode":"b91 3uu",
    "addr:street":"Warwick Road",
    "iso:country":"GB",
    "sg:address":"Care Of Beatties, 700 Warwick Road",
    "sg:city":"Solihull",
    "sg:classifiers":[
        {
            "category":"Shopping",
            "subcategory":"Clothing, Apparel, & Fashions",
            "type":"Retail Goods"
        }
    ],
    "sg:phone":"+44 121 704 9410",
    "sg:postcode":"B91 3UU",
    "sg:province":"West Midlands",
    "sg:tags":[
        "shop"
    ],
    "wof:name":"Jaegar Ladieswear",
    "wof:placetype":"venue"
},
  "geometry": {"coordinates":[-1.777849,52.415066],"type":"Point"}
}