{
  "type": "Feature",
  "properties": {
    "addr:full":"Chainey Rd, Kings Cross Islington Greater London N1 9AN",
    "addr:postcode":"n1 9an",
    "addr:street":"Chainey Rd",
    "iso:country":"GB",
    "sg:address":"Chainey Rd, Kings Cross",
    "sg:city":"Islington",
    "sg:classifiers":[
        {
            "category":"Travel",
            "subcategory":"Hotels & Motels",
            "type":"Entertainment"
        }
    ],
    "sg:phone":"+44 20 7837 5454",
    "sg:postcode":"N1 9AN",
    "sg:province":"Greater London",
    "wof:name":"The Great Northern Hotel",
    "wof:placetype":"venue"
},
  "geometry": {"coordinates":[-0.106149,51.532795],"type":"Point"}
}