{
  "type": "Feature",
  "properties": {
    "addr:full":"1 Spa Rd Witham Essex CM8 1NE",
    "addr:housenumber":"1",
    "addr:postcode":"cm8 1ne",
    "addr:street":"Spa Rd",
    "iso:country":"GB",
    "sg:address":"1 Spa Rd",
    "sg:city":"Witham",
    "sg:classifiers":[
        {
            "category":"Government",
            "subcategory":"Post Office",
            "type":"Public Place"
        }
    ],
    "sg:phone":"+44 1376 511753",
    "sg:postcode":"CM8 1NE",
    "sg:province":"Essex",
    "wof:name":"Powers Hall End Post Office",
    "wof:placetype":"venue"
},
  "geometry": {"coordinates":[0.6257110238,51.8051300049],"type":"Point"}
}