{
  "type": "Feature",
  "properties": {
    "addr:full":"7 Lyndhurst Road Burnley Lancashire BB10 4EG",
    "addr:housenumber":"7",
    "addr:postcode":"bb10 4eg",
    "addr:street":"Lyndhurst Road",
    "iso:country":"GB",
    "sg:address":"7 Lyndhurst Road",
    "sg:city":"Burnley",
    "sg:classifiers":[
        {
            "category":"Personal",
            "subcategory":"Beauty Salon",
            "type":"Services"
        },
        {
            "category":"Personal",
            "subcategory":"Barber",
            "type":"Services"
        }
    ],
    "sg:phone":"+44 1282 423308",
    "sg:postcode":"BB10 4EG",
    "sg:province":"Lancashire",
    "sg:tags":[
        "unisex",
        "hairdresser"
    ],
    "wof:name":"Truly Fair",
    "wof:placetype":"venue"
},
  "geometry": {"coordinates":[-2.230645,53.786385],"type":"Point"}
}