{
  "type": "Feature",
  "properties": {
    "addr:full":"New Folly Doctors Surgery, Bell Mead, High St Ingatestone Essex CM4 0FA",
    "addr:postcode":"cm4 0fa",
    "addr:street":"Bell Mead High St",
    "iso:country":"GB",
    "sg:address":"New Folly Doctors Surgery, Bell Mead, High St",
    "sg:city":"Ingatestone",
    "sg:classifiers":[
        {
            "category":"Health Services",
            "subcategory":"Doctor",
            "type":"Services"
        }
    ],
    "sg:phone":"+44 1277 352224",
    "sg:postcode":"CM4 0FA",
    "sg:province":"Essex",
    "sg:tags":[
        "practitioners"
    ],
    "wof:name":"Copsey, M D",
    "wof:placetype":"venue"
},
  "geometry": {"coordinates":[0.383585006,51.669921875],"type":"Point"}
}