{
  "type": "Feature",
  "properties": {
    "iso:country":"GB",
    "sg:address":"85 High St, Little Lever",
    "sg:city":"Bolton",
    "sg:classifiers":[
        {
            "category":"Shopping",
            "subcategory":"Department Store",
            "type":"Retail Goods"
        }
    ],
    "sg:postcode":"BL3 1NA",
    "sg:province":"Lancashire",
    "wof:name":"Moran,Peter,",
    "wof:placetype":"venue"
},
  "geometry": {"coordinates":[-2.365966,53.561378],"type":"Point"}
}