{
  "type": "Feature",
  "properties": {
    "addr:full":"39-41 Carnie Drive Aberdeen Aberdeen City AB2 5AN",
    "addr:housenumber":"39-41",
    "addr:postcode":"ab2 5an",
    "addr:street":"Carnie Drive",
    "iso:country":"GB",
    "sg:address":"39-41 Carnie Drive",
    "sg:city":"Aberdeen",
    "sg:classifiers":[
        {
            "category":"Social Services",
            "type":"Services"
        }
    ],
    "sg:phone":"+44 1224 492711",
    "sg:postcode":"AB2 5AN",
    "sg:province":"Aberdeen City",
    "wof:name":"Community Placement Team",
    "wof:placetype":"venue"
},
  "geometry": {"coordinates":[-2.123461,57.159908],"type":"Point"}
}