{
  "type": "Feature",
  "properties": {
    "addr:full":"5th Floor, Produce Exchange Buildings, 8 Victoria St Liverpool Merseyside L2 6QG",
    "addr:housenumber":"5th floor;8",
    "addr:postcode":"l2 6qg",
    "addr:street":"Victoria St",
    "iso:country":"GB",
    "sg:address":"5th Floor, Produce Exchange Buildings, 8 Victoria St",
    "sg:city":"Liverpool",
    "sg:classifiers":[
        {
            "category":"Organizations",
            "subcategory":"Political Organization",
            "type":"Services"
        }
    ],
    "sg:phone":"+44 151 236 1332",
    "sg:postcode":"L2 6QG",
    "sg:province":"Merseyside",
    "sg:tags":[
        "party"
    ],
    "wof:name":"Richard Corbett M E P",
    "wof:placetype":"venue"
},
  "geometry": {"coordinates":[-2.988049984,53.4066009521],"type":"Point"}
}