{
  "type": "Feature",
  "properties": {
    "addr:full":"699 Rainham Road Sth Dagenham Essex RM10 8UX",
    "addr:housenumber":"699",
    "addr:postcode":"rm10 8ux",
    "addr:street":"Rainham Road Sth Dagenham",
    "iso:country":"GB",
    "sg:address":"699 Rainham Road Sth",
    "sg:city":"Dagenham",
    "sg:classifiers":[
        {
            "category":"Autos & Motor Vehicles",
            "subcategory":"Fuel & Gas Station",
            "type":"Retail Goods"
        }
    ],
    "sg:postcode":"RM10 8UX",
    "sg:province":"Essex",
    "sg:tags":[
        "hr",
        "petrol"
    ],
    "wof:name":"Coronet Self Service Station",
    "wof:placetype":"venue"
},
  "geometry": {"coordinates":[0.1652140021,51.5409812927],"type":"Point"}
}