{
  "type": "Feature",
  "properties": {
    "iso:country":"GB",
    "sg:address":"19 Settle Street, Little Lever",
    "sg:city":"Bolton",
    "sg:classifiers":[
        {
            "category":"Retail",
            "subcategory":"Driving School",
            "type":"Services"
        }
    ],
    "sg:phone":"+44 1204 576285",
    "sg:postcode":"BL3 1LF",
    "sg:province":"Lancashire",
    "wof:name":"N Tyldesley",
    "wof:placetype":"venue"
},
  "geometry": {"coordinates":[-2.3627939224,53.5612220764],"type":"Point"}
}