{
  "type": "Feature",
  "properties": {
    "addr:full":"Manor House Farm, Spon Lane, Grendon Atherstone Leicestershire CV9 2EX",
    "addr:postcode":"cv9 2ex",
    "addr:street":"Manor;Spon Lane",
    "iso:country":"GB",
    "sg:address":"Manor House Farm, Spon Lane, Grendon",
    "sg:city":"Atherstone",
    "sg:classifiers":[
        {
            "category":"Retail",
            "subcategory":"Event Space",
            "type":"Services"
        }
    ],
    "sg:phone":"+44 1827 898459",
    "sg:postcode":"CV9 2EX",
    "sg:province":"Leicestershire",
    "sg:tags":[
        "exhibition",
        "organiser"
    ],
    "wof:name":"Kristal Design Ltd.",
    "wof:placetype":"venue"
},
  "geometry": {"coordinates":[-1.599473,52.585907],"type":"Point"}
}