{
  "type": "Feature",
  "properties": {
    "addr:full":"26 Old Milton Road New Milton Hampshire BH25 6DX",
    "addr:housenumber":"26",
    "addr:postcode":"bh25 6dx",
    "addr:street":"Old Milton Road",
    "iso:country":"GB",
    "sg:address":"26 Old Milton Road",
    "sg:city":"New Milton",
    "sg:classifiers":[
        {
            "category":"Personal",
            "subcategory":"Barber",
            "type":"Services"
        }
    ],
    "sg:phone":"+44 1425 614329",
    "sg:postcode":"BH25 6DX",
    "sg:province":"Hampshire",
    "sg:tags":[
        "men's",
        "hairdresser"
    ],
    "wof:name":"Martin Harvey Hairdressing",
    "wof:placetype":"venue"
},
  "geometry": {"coordinates":[-1.658969,50.751839],"type":"Point"}
}