{
  "type": "Feature",
  "properties": {
    "iso:country":"GB",
    "sg:address":"Unit 7, Herald Business Park, Golden Acres Lane",
    "sg:city":"Coventry",
    "sg:classifiers":[
        {
            "category":"Building & Trades",
            "subcategory":"Pest Control",
            "type":"Services"
        }
    ],
    "sg:phone":"+44 24 7665 9933",
    "sg:postcode":"CV3 2SY",
    "sg:province":"Warwickshire",
    "sg:tags":[
        "franchise"
    ],
    "wof:name":"Sign-a-rama",
    "wof:placetype":"venue"
},
  "geometry": {"coordinates":[-1.443786,52.393253],"type":"Point"}
}