{
  "type": "Feature",
  "properties": {
    "addr:full":"Northumberland Street Morecambe Lancashire LA4 4AU",
    "addr:postcode":"la4 4au",
    "addr:street":"Northumberland Street",
    "iso:country":"GB",
    "sg:address":"Northumberland Street",
    "sg:city":"Morecambe",
    "sg:classifiers":[
        {
            "category":"Bars & Pubs",
            "type":"Food & Drink"
        }
    ],
    "sg:phone":"+44 1524 831720",
    "sg:postcode":"LA4 4AU",
    "sg:province":"Lancashire",
    "sg:tags":[
        "pubs",
        "inn"
    ],
    "wof:name":"The Bath Hotel",
    "wof:placetype":"venue"
},
  "geometry": {"coordinates":[-2.870199,54.072189],"type":"Point"}
}