{
  "type": "Feature",
  "properties": {
    "iso:country":"GB",
    "sg:address":"51 Chirton Green",
    "sg:city":"North Shields",
    "sg:classifiers":[
        {
            "category":"Health Services",
            "subcategory":"Dentist",
            "type":"Services"
        }
    ],
    "sg:phone":"+44 191 257 3885",
    "sg:postcode":"NE29 0JR",
    "sg:province":"Tyne and Wear",
    "wof:name":"G.R Almond BDS",
    "wof:placetype":"venue"
},
  "geometry": {"coordinates":[-1.460491,55.008217],"type":"Point"}
}