{
  "type": "Feature",
  "properties": {
    "addr:full":"16 Piccadilly Stoke On Trent Staffordshire ST1 1DH",
    "addr:housenumber":"16",
    "addr:postcode":"st1 1dh",
    "addr:street":"Piccadilly Stoke On",
    "iso:country":"GB",
    "sg:address":"16 Piccadilly",
    "sg:city":"Stoke On Trent",
    "sg:classifiers":[
        {
            "category":"Shopping",
            "subcategory":"Clothing, Apparel, & Fashions",
            "type":"Retail Goods"
        }
    ],
    "sg:phone":"+44 1782 269027",
    "sg:postcode":"ST1 1DH",
    "sg:province":"Staffordshire",
    "sg:tags":[
        "menswear"
    ],
    "wof:name":"D N A Menswear",
    "wof:placetype":"venue"
},
  "geometry": {"coordinates":[-2.176623106,53.025428772],"type":"Point"}
}