{
  "type": "Feature",
  "properties": {
    "addr:full":"Market Service Station, Old Vicarage Preston Lancashire PR1 2QN",
    "addr:postcode":"pr1 2qn",
    "addr:street":"Old",
    "iso:country":"GB",
    "sg:address":"Market Service Station, Old Vicarage",
    "sg:city":"Preston",
    "sg:classifiers":[
        {
            "category":"Retail",
            "subcategory":"Auto Rental",
            "type":"Services"
        }
    ],
    "sg:phone":"+44 1772 253844",
    "sg:postcode":"PR1 2QN",
    "sg:province":"Lancashire",
    "sg:tags":[
        "car"
    ],
    "wof:name":"National Car Rental",
    "wof:placetype":"venue"
},
  "geometry": {"coordinates":[-2.7057290077,53.7579612732],"type":"Point"}
}