{
  "type": "Feature",
  "properties": {
    "addr:full":"Leymoor Road, Golcar Huddersfield West Yorkshire HD7 4QQ",
    "addr:postcode":"hd7 4qq",
    "addr:street":"Leymoor Road;West",
    "iso:country":"GB",
    "sg:address":"Leymoor Road, Golcar",
    "sg:city":"Huddersfield",
    "sg:classifiers":[
        {
            "category":"Health Services",
            "subcategory":"Doctor",
            "type":"Services"
        }
    ],
    "sg:phone":"+44 1484 654504",
    "sg:postcode":"HD7 4QQ",
    "sg:province":"West Yorkshire",
    "sg:tags":[
        "practitioners"
    ],
    "wof:name":"Faulkner Wallwork Benett & Dempsey Drs",
    "wof:placetype":"venue"
},
  "geometry": {"coordinates":[-1.8399139643,53.6400985718],"type":"Point"}
}