{
  "type": "Feature",
  "properties": {
    "addr:full":"84 Anlaby Road Hull East Riding of Yorkshire HU3 2JA",
    "addr:housenumber":"84",
    "addr:postcode":"hu3 2ja",
    "addr:street":"Anlaby Road",
    "iso:country":"GB",
    "sg:address":"84 Anlaby Road",
    "sg:city":"Hull",
    "sg:classifiers":[
        {
            "category":"Restaurant",
            "type":"Food & Drink"
        }
    ],
    "sg:phone":"+44 1482 327104",
    "sg:postcode":"HU3 2JA",
    "sg:province":"East Riding of Yorkshire",
    "wof:name":"Mustafa's",
    "wof:placetype":"venue"
},
  "geometry": {"coordinates":[-0.3498570025,53.7431335449],"type":"Point"}
}