{
  "type": "Feature",
  "properties": {
    "iso:country":"GB",
    "sg:address":"West Lane Trading Estate",
    "sg:city":"Sittingbourne",
    "sg:classifiers":[
        {
            "category":"Manufacturing",
            "subcategory":"Buildings",
            "type":"Manufacturing & Wholesale Goods"
        }
    ],
    "sg:phone":"+44 1795 421183",
    "sg:postcode":"ME10 3TT",
    "sg:province":"Kent",
    "sg:tags":[
        "system",
        "air conditioning"
    ],
    "wof:name":"Greypillar Systems Ltd.",
    "wof:placetype":"venue"
},
  "geometry": {"coordinates":[0.7442650199,51.3393516541],"type":"Point"}
}