{
  "type": "Feature",
  "properties": {
    "addr:full":"The Croft, Stafford St Willenhall West Midlands WV13 1TG",
    "addr:postcode":"wv13 1tg",
    "addr:street":"Stafford St",
    "iso:country":"GB",
    "sg:address":"The Croft, Stafford St",
    "sg:city":"Willenhall",
    "sg:classifiers":[
        {
            "category":"Sports & Exercise",
            "subcategory":"Skate Park",
            "type":"Entertainment"
        }
    ],
    "sg:postcode":"WV13 1TG",
    "sg:province":"West Midlands",
    "sg:tags":[
        "equipment",
        "grinding"
    ],
    "wof:name":"Bridge Precision Grinding",
    "wof:placetype":"venue"
},
  "geometry": {"coordinates":[-2.056507,52.585735],"type":"Point"}
}