{
  "type": "Feature",
  "properties": {
    "addr:full":"Warwick House, 35 Spring Road, Hall Grn Birmingham West Midlands B11 3EA",
    "addr:housenumber":"35",
    "addr:postcode":"b11 3ea",
    "addr:street":"Spring Road Hall Grn",
    "iso:country":"GB",
    "sg:address":"Warwick House, 35 Spring Road, Hall Grn",
    "sg:city":"Birmingham",
    "sg:classifiers":[
        {
            "category":"Professional",
            "subcategory":"Business Services",
            "type":"Services"
        }
    ],
    "sg:phone":"+44 121 778 2233",
    "sg:postcode":"B11 3EA",
    "sg:province":"West Midlands",
    "sg:tags":[
        "retail",
        "premise"
    ],
    "wof:name":"Bridge House (Bewdley) Ltd.",
    "wof:placetype":"venue"
},
  "geometry": {"coordinates":[-1.8445099592,52.4462013245],"type":"Point"}
}