{
  "type": "Feature",
  "properties": {
    "iso:country":"GB",
    "sg:address":"560 High Rd",
    "sg:city":"London",
    "sg:classifiers":[
        {
            "category":"Professional",
            "subcategory":"Detective & Security Services",
            "type":"Services"
        }
    ],
    "sg:phone":"+44 20 8539 9000",
    "sg:postcode":"E11 3DH",
    "sg:province":"Greater London",
    "sg:tags":[
        "locksmith"
    ],
    "wof:name":"Stone Security Locksmiths Ltd",
    "wof:placetype":"venue"
},
  "geometry": {"coordinates":[-0.06868,51.59549],"type":"Point"}
}