{
  "type": "Feature",
  "properties": {
    "iso:country":"GB",
    "sg:address":"Remmington House, 34a Market Street, Mottram",
    "sg:city":"Hyde",
    "sg:classifiers":[
        {
            "category":"Shopping",
            "subcategory":"Gifts & Souvenirs",
            "type":"Retail Goods"
        }
    ],
    "sg:phone":"+44 1457 763773",
    "sg:postcode":"SK14 6JG",
    "sg:province":"Cheshire",
    "sg:tags":[
        "greeting",
        "card"
    ],
    "wof:name":"The Card Creation Co",
    "wof:placetype":"venue"
},
  "geometry": {"coordinates":[-2.0074689388,53.4399795532],"type":"Point"}
}