{
  "type": "Feature",
  "properties": {
    "addr:full":"85a Fleet Road London Greater London NW3 2QY",
    "addr:housenumber":"85a",
    "addr:postcode":"nw3 2qy",
    "addr:street":"Fleet Road",
    "iso:country":"GB",
    "sg:address":"85a Fleet Road",
    "sg:city":"London",
    "sg:classifiers":[
        {
            "category":"Cafe",
            "type":"Food & Drink"
        }
    ],
    "sg:phone":"+44 20 7431 3011",
    "sg:postcode":"NW3 2QY",
    "sg:province":"Greater London",
    "sg:tags":[
        "tea",
        "room"
    ],
    "wof:name":"Villa Maria",
    "wof:placetype":"venue"
},
  "geometry": {"coordinates":[-0.164003998,51.5537223816],"type":"Point"}
}