{
  "type": "Feature",
  "properties": {
    "iso:country":"GB",
    "sg:address":"212 Bordesley Grn",
    "sg:city":"Birmingham",
    "sg:classifiers":[
        {
            "category":"Food & Beverages",
            "subcategory":"Meat & Fish",
            "type":"Retail Goods"
        }
    ],
    "sg:phone":"+44 121 772 0125",
    "sg:postcode":"B9 4SU",
    "sg:province":"West Midlands",
    "sg:tags":[
        "butcher"
    ],
    "wof:name":"Wadhams",
    "wof:placetype":"venue"
},
  "geometry": {"coordinates":[-1.8536119461,52.4773139954],"type":"Point"}
}