{
  "type": "Feature",
  "properties": {
    "iso:country":"GB",
    "sg:address":"15 Broadoaks Rd",
    "sg:city":"Sale",
    "sg:classifiers":[
        {
            "category":"Professional",
            "subcategory":"Engineering",
            "type":"Services"
        }
    ],
    "sg:phone":"+44 161 969 5915",
    "sg:postcode":"M33 7SR",
    "sg:province":"Cheshire",
    "sg:tags":[
        "contractor",
        "electrical",
        "engineer"
    ],
    "wof:name":"Spectrum NICEIC Approved Contractors",
    "wof:placetype":"venue"
},
  "geometry": {"coordinates":[-2.3269369602,53.4228363037],"type":"Point"}
}