{
  "type": "Feature",
  "properties": {
    "iso:country":"GB",
    "sg:address":"9 Aynam Road",
    "sg:city":"Kendal",
    "sg:classifiers":[
        {
            "category":"Home & Garden",
            "subcategory":"Garden Supply",
            "type":"Retail Goods"
        },
        {
            "category":"Home & Garden",
            "subcategory":"Hardware",
            "type":"Retail Goods"
        }
    ],
    "sg:phone":"+44 1539 724466",
    "sg:postcode":"LA9 7DE",
    "sg:province":"Cumbria",
    "sg:tags":[
        "lawnmowers",
        "sales",
        "machinery"
    ],
    "wof:name":"Lakeland Lawnmowers",
    "wof:placetype":"venue"
},
  "geometry": {"coordinates":[-2.743608,54.324814],"type":"Point"}
}