{
  "type": "Feature",
  "properties": {
    "addr:full":"63 Ash Street, Ash Aldershot Hampshire GU12 6LG",
    "addr:housenumber":"63",
    "addr:postcode":"gu12 6lg",
    "addr:street":"Ash Street",
    "iso:country":"GB",
    "sg:address":"63 Ash Street, Ash",
    "sg:city":"Aldershot",
    "sg:classifiers":[
        {
            "category":"Building & Trades",
            "subcategory":"Plumbing",
            "type":"Services"
        }
    ],
    "sg:postcode":"GU12 6LG",
    "sg:province":"Hampshire",
    "sg:tags":[
        "central",
        "heating"
    ],
    "wof:name":"Alan D Belcher",
    "wof:placetype":"venue"
},
  "geometry": {"coordinates":[-0.725073,51.245964],"type":"Point"}
}