{
  "type": "Feature",
  "properties": {
    "addr:full":"80a Rolfe St Smethwick West Midlands B66 2AR",
    "addr:housenumber":"80a",
    "addr:postcode":"b66 2ar",
    "addr:street":"Rolfe St",
    "iso:country":"GB",
    "sg:address":"80a Rolfe St",
    "sg:city":"Smethwick",
    "sg:classifiers":[
        {
            "category":"Professional",
            "subcategory":"Detective & Security Services",
            "type":"Services"
        }
    ],
    "sg:postcode":"B66 2AR",
    "sg:province":"West Midlands",
    "sg:tags":[
        "car"
    ],
    "wof:name":"Swor,N,",
    "wof:placetype":"venue"
},
  "geometry": {"coordinates":[-1.964959,52.497173],"type":"Point"}
}