{
  "type": "Feature",
  "properties": {
    "addr:full":"33 Hamps Valley Road, Waterhouses Stoke-on-trent Staffordshire ST10 3LJ",
    "addr:housenumber":"33",
    "addr:postcode":"st10 3lj",
    "addr:street":"Hamps Valley Road",
    "iso:country":"GB",
    "sg:address":"33 Hamps Valley Road, Waterhouses",
    "sg:city":"Stoke-on-trent",
    "sg:classifiers":[
        {
            "category":"Autos & Motor Vehicles",
            "subcategory":"Auto Supplies",
            "type":"Retail Goods"
        },
        {
            "category":"Retail",
            "subcategory":"Auto Repair",
            "type":"Services"
        }
    ],
    "sg:phone":"+44 1538 308180",
    "sg:postcode":"ST10 3LJ",
    "sg:province":"Staffordshire",
    "sg:tags":[
        "car",
        "specialist",
        "tyre",
        "customizing"
    ],
    "wof:name":"M T S Mobile Tyre Specialists",
    "wof:placetype":"venue"
},
  "geometry": {"coordinates":[-1.884864,53.052647],"type":"Point"}
}