{
  "type": "Feature",
  "properties": {
    "addr:full":"Neville Street, Longridge Preston Lancashire PR3 3FD",
    "addr:postcode":"pr3 3fd",
    "addr:street":"Neville Street",
    "iso:country":"GB",
    "sg:address":"Neville Street, Longridge",
    "sg:city":"Preston",
    "sg:classifiers":[
        {
            "category":"Autos & Motor Vehicles",
            "subcategory":"Automobile Sales",
            "type":"Retail Goods"
        }
    ],
    "sg:phone":"+44 1772 784419",
    "sg:postcode":"PR3 3FD",
    "sg:province":"Lancashire",
    "sg:tags":[
        "car"
    ],
    "wof:name":"John Greenwood",
    "wof:placetype":"venue"
},
  "geometry": {"coordinates":[-2.6068489552,53.8303756714],"type":"Point"}
}