{
  "type": "Feature",
  "properties": {
    "addr:full":"24 Green Lanes London Greater London N13 6HT",
    "addr:housenumber":"24",
    "addr:postcode":"n13 6ht",
    "addr:street":"Green Lanes",
    "iso:country":"GB",
    "sg:address":"24 Green Lanes",
    "sg:city":"London",
    "sg:classifiers":[
        {
            "category":"Farming",
            "subcategory":"Fish & Marine Products",
            "type":"Manufacturing & Wholesale Goods"
        },
        {
            "category":"Food & Beverages",
            "subcategory":"Meat & Fish",
            "type":"Retail Goods"
        }
    ],
    "sg:phone":"+44 20 8888 2819",
    "sg:postcode":"N13 6HT",
    "sg:province":"Greater London",
    "sg:tags":[
        "fishmonger",
        "related"
    ],
    "wof:name":"Green Lanes Fisheries",
    "wof:placetype":"venue"
},
  "geometry": {"coordinates":[-0.109507,51.610504],"type":"Point"}
}