{
  "type": "Feature",
  "properties": {
    "iso:country":"GB",
    "sg:address":"Ivy Cottage, Pump Lane, Churton Chester",
    "sg:city":"Chester",
    "sg:classifiers":[
        {
            "category":"Health Services",
            "subcategory":"Health Practitioner",
            "type":"Services"
        }
    ],
    "sg:phone":"+44 1829 271607",
    "sg:postcode":"CH3 6LR",
    "sg:province":"Cheshire",
    "sg:tags":[
        "therapist",
        "speech"
    ],
    "wof:name":"Cathy Elliott Counsellor & Psychotherapist",
    "wof:placetype":"venue"
},
  "geometry": {"coordinates":[-2.871154,53.103188],"type":"Point"}
}