{
  "type": "Feature",
  "properties": {
    "iso:country":"GB",
    "sg:address":"Clint Bank, Burnt Yates",
    "sg:city":"Harrogate",
    "sg:classifiers":[
        {
            "category":"Professional",
            "subcategory":"Engineering",
            "type":"Services"
        }
    ],
    "sg:postcode":"HG3 3DW",
    "sg:province":"North Yorkshire",
    "wof:name":"P & P Craven",
    "wof:placetype":"venue"
},
  "geometry": {"coordinates":[-1.617709,54.046055],"type":"Point"}
}