{
  "type": "Feature",
  "properties": {
    "iso:country":"GB",
    "sg:address":"Resiblock House, Archers Fields Close, Burnt Mills Industrial Estate",
    "sg:city":"Basildon",
    "sg:classifiers":[
        {
            "category":"Building & Trades",
            "subcategory":"Construction",
            "type":"Services"
        }
    ],
    "sg:phone":"+44 1268 273344",
    "sg:postcode":"SS13 1DW",
    "sg:province":"Essex",
    "sg:tags":[
        "contractor",
        "paving",
        "driveway"
    ],
    "wof:name":"Resiblock Ltd.",
    "wof:placetype":"venue"
},
  "geometry": {"coordinates":[0.502577,51.585571],"type":"Point"}
}