{
  "type": "Feature",
  "properties": {
    "addr:full":"Stanley Cabinet Works, St James Street Accrington Lancashire BB5 1NU",
    "addr:postcode":"bb5 1nu",
    "addr:street":"St James Street",
    "iso:country":"GB",
    "sg:address":"Stanley Cabinet Works, St James Street",
    "sg:city":"Accrington",
    "sg:classifiers":[
        {
            "category":"Shopping",
            "subcategory":"Computers & Home Electronics",
            "type":"Retail Goods"
        },
        {
            "category":"Home & Garden",
            "subcategory":"Furniture",
            "type":"Retail Goods"
        }
    ],
    "sg:phone":"+44 1254 234743",
    "sg:postcode":"BB5 1NU",
    "sg:province":"Lancashire",
    "wof:name":"M A Platt Ltd",
    "wof:placetype":"venue"
},
  "geometry": {"coordinates":[-2.3706440926,53.7553291321],"type":"Point"}
}