{
  "type": "Feature",
  "properties": {
    "addr:full":"120 Muirhead Avenue East Liverpool Merseyside L11 1EL",
    "addr:housenumber":"120",
    "addr:postcode":"l11 1el",
    "addr:street":"Muirhead Avenue East",
    "iso:country":"GB",
    "sg:address":"120 Muirhead Avenue East",
    "sg:city":"Liverpool",
    "sg:classifiers":[
        {
            "category":"Shopping",
            "subcategory":"News",
            "type":"Retail Goods"
        }
    ],
    "sg:phone":"+44 151 256 6116",
    "sg:postcode":"L11 1EL",
    "sg:province":"Merseyside",
    "sg:tags":[
        "newsagent"
    ],
    "wof:name":"Muirhead Newsagents",
    "wof:placetype":"venue"
},
  "geometry": {"coordinates":[-2.9133210182,53.4383926392],"type":"Point"}
}