{
  "type": "Feature",
  "properties": {
    "iso:country":"GB",
    "sg:address":"Westgate",
    "sg:city":"Haltwhistle",
    "sg:classifiers":[
        {
            "category":"Food & Beverages",
            "subcategory":"Liquor & Beverages",
            "type":"Retail Goods"
        }
    ],
    "sg:phone":"+44 1434 321403",
    "sg:postcode":"NE49 9AF",
    "sg:province":"Northumberland",
    "sg:tags":[
        "beer",
        "spirit",
        "wines"
    ],
    "wof:name":"Westgate Wine & Video Store",
    "wof:placetype":"venue"
},
  "geometry": {"coordinates":[-2.462877,54.969292],"type":"Point"}
}