{
  "type": "Feature",
  "properties": {
    "addr:full":"Unit 7 St Giles Centre Elgin Moray IV30 1EA",
    "addr:housenumber":"unit 7",
    "addr:postcode":"iv30 1ea",
    "addr:street":"St Giles Centre Elgin",
    "iso:country":"GB",
    "sg:address":"Unit 7 St Giles Centre",
    "sg:city":"Elgin",
    "sg:classifiers":[
        {
            "category":"Wholesale",
            "subcategory":"Non-durable Goods",
            "type":"Manufacturing & Wholesale Goods"
        }
    ],
    "sg:postcode":"IV30 1EA",
    "sg:province":"Moray",
    "sg:tags":[
        "carry",
        "cash"
    ],
    "wof:name":"Brooks,Jonathan,Ltd",
    "wof:placetype":"venue"
},
  "geometry": {"coordinates":[-3.314384,57.649673],"type":"Point"}
}