{
  "type": "Feature",
  "properties": {
    "iso:country":"GB",
    "sg:address":"The Coach Ho, Severn Stoke Bank, Severn Stoke",
    "sg:city":"Worcester",
    "sg:classifiers":[
        {
            "category":"Freight",
            "type":"Transportation"
        }
    ],
    "sg:phone":"+44 1905 371282",
    "sg:postcode":"WR8 9JG",
    "sg:province":"Gloucestershire",
    "sg:tags":[
        "forwarders"
    ],
    "wof:name":"Amco Services (International) Ltd",
    "wof:placetype":"venue"
},
  "geometry": {"coordinates":[-2.210084,52.095421],"type":"Point"}
}