{
  "type": "Feature",
  "properties": {
    "addr:full":"Shawe House Nursing Home, Pennybridge Lane Manchester Cheshire M41 5DX",
    "addr:postcode":"m41 5dx",
    "addr:street":"Pennybridge Lane",
    "iso:country":"GB",
    "sg:address":"Shawe House Nursing Home, Pennybridge Lane",
    "sg:city":"Manchester",
    "sg:classifiers":[
        {
            "category":"Health Services",
            "subcategory":"Nursing And Care Facility",
            "type":"Services"
        }
    ],
    "sg:postcode":"M41 5DX",
    "sg:province":"Cheshire",
    "sg:tags":[
        "home"
    ],
    "wof:name":"Shawe House Nursing Home Ltd.",
    "wof:placetype":"venue"
},
  "geometry": {"coordinates":[-2.3737299442,53.4467391968],"type":"Point"}
}