{
  "type": "Feature",
  "properties": {
    "iso:country":"GB",
    "sg:address":"Thrapston Road, Ellington",
    "sg:city":"Huntingdon",
    "sg:classifiers":[
        {
            "category":"Farming",
            "subcategory":"Farm",
            "type":"Manufacturing & Wholesale Goods"
        }
    ],
    "sg:postcode":"PE28 0AE",
    "sg:province":"Bedfordshire",
    "sg:tags":[
        "mixed",
        "crop"
    ],
    "wof:name":"D S S Horsford",
    "wof:placetype":"venue"
},
  "geometry": {"coordinates":[-0.2992799878,52.3336296082],"type":"Point"}
}