{
  "type": "Feature",
  "properties": {
    "addr:full":"3 Brunel Drive, Northern Road Industrial Estate Newark Nottinghamshire NG24 2DE",
    "addr:housenumber":"3",
    "addr:postcode":"ng24 2de",
    "addr:street":"Brunel Drive Northern Road Industrial",
    "iso:country":"GB",
    "sg:address":"3 Brunel Drive, Northern Road Industrial Estate",
    "sg:city":"Newark",
    "sg:classifiers":[
        {
            "category":"Manufacturing",
            "subcategory":"Building Materials",
            "type":"Manufacturing & Wholesale Goods"
        }
    ],
    "sg:phone":"+44 1636 703388",
    "sg:postcode":"NG24 2DE",
    "sg:province":"Nottinghamshire",
    "sg:tags":[
        "merchant",
        "builder"
    ],
    "wof:name":"Travis Perkins Trading Co. Ltd.",
    "wof:placetype":"venue"
},
  "geometry": {"coordinates":[-0.7866259813,53.08826828],"type":"Point"}
}