{
  "type": "Feature",
  "properties": {
    "addr:full":"Webb Ellis Road Rugby Warwickshire CV22 7AU",
    "addr:postcode":"cv22 7au",
    "addr:street":"Ellis Road",
    "iso:country":"GB",
    "sg:address":"Webb Ellis Road",
    "sg:city":"Rugby",
    "sg:classifiers":[
        {
            "category":"Sports & Exercise",
            "subcategory":"Gym",
            "type":"Entertainment"
        }
    ],
    "sg:phone":"+44 1788 540523",
    "sg:postcode":"CV22 7AU",
    "sg:province":"Warwickshire",
    "sg:tags":[
        "fitness",
        "health",
        "centre"
    ],
    "wof:name":"Nobody's Perfect the Club",
    "wof:placetype":"venue"
},
  "geometry": {"coordinates":[-1.27454,52.369381],"type":"Point"}
}