{
  "type": "Feature",
  "properties": {
    "iso:country":"GB",
    "sg:address":"Unit 5, Pear Mill Industrial Estate, Stockport Road West",
    "sg:city":"Stockport",
    "sg:classifiers":[
        {
            "category":"Shopping",
            "subcategory":"Stationery & Office Supplies",
            "type":"Retail Goods"
        },
        {
            "category":"Shopping",
            "subcategory":"Crafts & Fabrics",
            "type":"Retail Goods"
        }
    ],
    "sg:phone":"+44 161 430 3222",
    "sg:postcode":"SK6 2BP",
    "sg:province":"Cheshire",
    "sg:tags":[
        "services",
        "supplies",
        "ceramic",
        "manufacturer"
    ],
    "wof:name":"YEW TREE STUDIOS",
    "wof:placetype":"venue"
},
  "geometry": {"coordinates":[-2.13388,53.413818],"type":"Point"}
}