{
  "type": "Feature",
  "properties": {
    "addr:full":"3 Cae Glas, Trefnant Denbigh Conwy LL16 5UB",
    "addr:housenumber":"3",
    "addr:postcode":"ll16 5ub",
    "addr:street":"Cae Glas",
    "iso:country":"GB",
    "sg:address":"3 Cae Glas, Trefnant",
    "sg:city":"Denbigh",
    "sg:classifiers":[
        {
            "category":"Retail",
            "subcategory":"Funeral Services",
            "type":"Services"
        }
    ],
    "sg:phone":"+44 1745 730369",
    "sg:postcode":"LL16 5UB",
    "sg:province":"Conwy",
    "sg:tags":[
        "director",
        "cemetery",
        "crematorium"
    ],
    "wof:name":"R MORRIS & SON FUNERAL DIRECTORS",
    "wof:placetype":"venue"
},
  "geometry": {"coordinates":[-3.4296739101,53.229019165],"type":"Point"}
}