{
  "type": "Feature",
  "properties": {
    "addr:full":"22 Palace Street Canterbury Kent CT1 2DZ",
    "addr:housenumber":"22",
    "addr:postcode":"ct1 2dz",
    "addr:street":"Palace Street",
    "iso:country":"GB",
    "sg:address":"22 Palace Street",
    "sg:city":"Canterbury",
    "sg:classifiers":[
        {
            "category":"Social Services",
            "type":"Services"
        }
    ],
    "sg:phone":"+44 1227 478990",
    "sg:postcode":"CT1 2DZ",
    "sg:province":"Kent",
    "sg:tags":[
        "educational"
    ],
    "wof:name":"Corridors of Time (Historical Presentations) Ltd.",
    "wof:placetype":"venue"
},
  "geometry": {"coordinates":[1.081518054,51.2813072205],"type":"Point"}
}