{
  "type": "Feature",
  "properties": {
    "addr:full":"Burma Rd Berkeley Gloucestershire GL13 9UQ",
    "addr:postcode":"gl13 9uq",
    "addr:street":"Burma Rd",
    "iso:country":"GB",
    "sg:address":"Burma Rd",
    "sg:city":"Berkeley",
    "sg:classifiers":[
        {
            "category":"Professional",
            "subcategory":"Business Services",
            "type":"Services"
        }
    ],
    "sg:phone":"+44 1453 811222",
    "sg:postcode":"GL13 9UQ",
    "sg:province":"Gloucestershire",
    "sg:tags":[
        "distribution"
    ],
    "wof:name":"BOC Interbrand",
    "wof:placetype":"venue"
},
  "geometry": {"coordinates":[-2.459569,51.693188],"type":"Point"}
}