{
  "type": "Feature",
  "properties": {
    "addr:full":"28 Market Street Carnforth Cumbria LA5 9JX",
    "addr:housenumber":"28",
    "addr:postcode":"la5 9jx",
    "addr:street":"Market Street",
    "iso:country":"GB",
    "sg:address":"28 Market Street",
    "sg:city":"Carnforth",
    "sg:classifiers":[
        {
            "category":"Fast Food",
            "type":"Food & Drink"
        }
    ],
    "sg:phone":"+44 1524 732725",
    "sg:postcode":"LA5 9JX",
    "sg:province":"Cumbria",
    "sg:tags":[
        "away",
        "take"
    ],
    "wof:name":"Bake-Wells",
    "wof:placetype":"venue"
},
  "geometry": {"coordinates":[-2.7689421177,54.1291885376],"type":"Point"}
}