{
  "type": "Feature",
  "properties": {
    "addr:full":"The Old Chapel, High Street, Burbage Marlborough Berkshire SN8 3AA",
    "addr:postcode":"sn8 3aa",
    "addr:street":"High Street",
    "iso:country":"GB",
    "sg:address":"The Old Chapel, High Street, Burbage",
    "sg:city":"Marlborough",
    "sg:classifiers":[
        {
            "category":"Conference Center",
            "type":"Public Place"
        }
    ],
    "sg:phone":"+44 1672 810509",
    "sg:postcode":"SN8 3AA",
    "sg:province":"Berkshire",
    "wof:name":"Kinwardstone Conferencing",
    "wof:placetype":"venue"
},
  "geometry": {"coordinates":[-1.670117,51.346455],"type":"Point"}
}