{
  "type": "Feature",
  "properties": {
    "addr:full":"6 Broadmead Bristol City of Bristol BS1 3HH",
    "addr:housenumber":"6",
    "addr:postcode":"bs1 3hh",
    "addr:street":"Broadmead",
    "iso:country":"GB",
    "sg:address":"6 Broadmead",
    "sg:city":"Bristol",
    "sg:classifiers":[
        {
            "category":"Communications",
            "type":"Services"
        }
    ],
    "sg:phone":"+44 117 922 6333",
    "sg:postcode":"BS1 3HH",
    "sg:province":"City of Bristol",
    "sg:tags":[
        "telecommunication"
    ],
    "wof:name":"The Pocket Phone Shop",
    "wof:placetype":"venue"
},
  "geometry": {"coordinates":[-2.58711,51.458279],"type":"Point"}
}