{
  "type": "Feature",
  "properties": {
    "addr:full":"357 Shoreham Street Sheffield South Yorkshire S2 4FA",
    "addr:housenumber":"357",
    "addr:postcode":"s2 4fa",
    "addr:street":"Shoreham Street",
    "iso:country":"GB",
    "sg:address":"357 Shoreham Street",
    "sg:city":"Sheffield",
    "sg:classifiers":[
        {
            "category":"Education",
            "subcategory":"Special Training",
            "type":"Public Place"
        }
    ],
    "sg:postcode":"S2 4FA",
    "sg:province":"South Yorkshire",
    "sg:tags":[
        "product",
        "centre"
    ],
    "wof:name":"Bvk Ltd.",
    "wof:placetype":"venue"
},
  "geometry": {"coordinates":[-1.4685909748,53.3699760437],"type":"Point"}
}