{
  "type": "Feature",
  "properties": {
    "addr:full":"Unit 4 Tythe Barn Workshops, Pound Lane Bradford-on-avon Wiltshire BA15 1LF",
    "addr:housenumber":"unit 4",
    "addr:postcode":"ba15 1lf",
    "addr:street":"Tythe;Pound Lane",
    "iso:country":"GB",
    "sg:address":"Unit 4 Tythe Barn Workshops, Pound Lane",
    "sg:city":"Bradford-on-avon",
    "sg:classifiers":[
        {
            "category":"Transit Center",
            "subcategory":"Freight",
            "type":"Transportation"
        }
    ],
    "sg:phone":"+44 1225 868250",
    "sg:postcode":"BA15 1LF",
    "sg:province":"Wiltshire",
    "sg:tags":[
        "shop",
        "craft",
        "centre"
    ],
    "wof:name":"Sky Blue Ltd.",
    "wof:placetype":"venue"
},
  "geometry": {"coordinates":[-2.2517769337,51.3483581543],"type":"Point"}
}