{
  "type": "Feature",
  "properties": {
    "addr:full":"The Health Centre Huddersfield West Yorkshire HD7 6DF",
    "addr:postcode":"hd7 6df",
    "addr:street":"West",
    "iso:country":"GB",
    "sg:address":"The Health Centre",
    "sg:city":"Huddersfield",
    "sg:classifiers":[
        {
            "category":"Health Services",
            "subcategory":"Doctor",
            "type":"Services"
        }
    ],
    "sg:phone":"+44 1484 844332",
    "sg:postcode":"HD7 6DF",
    "sg:province":"West Yorkshire",
    "sg:tags":[
        "practitioners"
    ],
    "wof:name":"Benson, H A",
    "wof:placetype":"venue"
},
  "geometry": {"coordinates":[-1.92828,53.602081],"type":"Point"}
}