{
  "type": "Feature",
  "properties": {
    "iso:country":"GB",
    "sg:address":"57 Queensfields West",
    "sg:city":"Bognor Regis",
    "sg:classifiers":[
        {
            "category":"Retail",
            "subcategory":"Auto Repair",
            "type":"Services"
        }
    ],
    "sg:phone":"+44 1243 827023",
    "sg:postcode":"PO21 5SH",
    "sg:province":"West Sussex",
    "sg:tags":[
        "modification",
        "garage"
    ],
    "wof:name":"Peterlee Motors",
    "wof:placetype":"venue"
},
  "geometry": {"coordinates":[-0.704099,50.788715],"type":"Point"}
}