{
  "type": "Feature",
  "properties": {
    "iso:country":"GB",
    "sg:address":"Lane End Road, Sands",
    "sg:city":"High Wycombe",
    "sg:classifiers":[
        {
            "category":"Farming",
            "subcategory":"Nursery",
            "type":"Manufacturing & Wholesale Goods"
        }
    ],
    "sg:phone":"+44 1494 534377",
    "sg:postcode":"HP12 4HG",
    "sg:province":"Buckinghamshire",
    "sg:tags":[
        "creche"
    ],
    "wof:name":"Little Oaks Nursery School",
    "wof:placetype":"venue"
},
  "geometry": {"coordinates":[-0.785725,51.631752],"type":"Point"}
}