{
  "type": "Feature",
  "properties": {
    "addr:full":"Yapton Lane, Walberton Arundel West Sussex BN18 0LS",
    "addr:postcode":"bn18 0ls",
    "addr:street":"Yapton Lane",
    "iso:country":"GB",
    "sg:address":"Yapton Lane, Walberton",
    "sg:city":"Arundel",
    "sg:classifiers":[
        {
            "category":"Sports & Exercise",
            "subcategory":"Gym",
            "type":"Entertainment"
        }
    ],
    "sg:phone":"+44 1243 554693",
    "sg:postcode":"BN18 0LS",
    "sg:province":"West Sussex",
    "sg:tags":[
        "fitness",
        "health",
        "centre"
    ],
    "wof:name":"Livingwell Health Club Hair & Beauty Salon",
    "wof:placetype":"venue"
},
  "geometry": {"coordinates":[-0.617679,50.852905],"type":"Point"}
}