{
  "type": "Feature",
  "properties": {
    "addr:full":"28 Elizabeth Road Wokingham Berkshire RG40 1UB",
    "addr:housenumber":"28",
    "addr:postcode":"rg40 1ub",
    "addr:street":"Elizabeth Road",
    "iso:country":"GB",
    "sg:address":"28 Elizabeth Road",
    "sg:city":"Wokingham",
    "sg:classifiers":[
        {
            "category":"Retail",
            "subcategory":"Repair Shop",
            "type":"Services"
        }
    ],
    "sg:phone":"+44 118 979 4598",
    "sg:postcode":"RG40 1UB",
    "sg:province":"Berkshire",
    "sg:tags":[
        "maintenance"
    ],
    "wof:name":"R G Services",
    "wof:placetype":"venue"
},
  "geometry": {"coordinates":[-0.8250859976,51.4132537842],"type":"Point"}
}