{
  "type": "Feature",
  "properties": {
    "addr:full":"32 Headingley Lane Leeds West Yorkshire LS6 2EB",
    "addr:housenumber":"32",
    "addr:postcode":"ls6 2eb",
    "addr:street":"Headingley Lane",
    "iso:country":"GB",
    "sg:address":"32 Headingley Lane",
    "sg:city":"Leeds",
    "sg:classifiers":[
        {
            "category":"Real Estate",
            "subcategory":"Architect",
            "type":"Services"
        }
    ],
    "sg:phone":"+44 113 274 2511",
    "sg:postcode":"LS6 2EB",
    "sg:province":"West Yorkshire",
    "wof:name":"Cook Robertshaw & Lancaster Ltd.",
    "wof:placetype":"venue"
},
  "geometry": {"coordinates":[-1.5643290281,53.8160133362],"type":"Point"}
}