{
  "type": "Feature",
  "properties": {
    "iso:country":"GB",
    "sg:address":"32-40 Cromwell Street",
    "sg:city":"Coventry",
    "sg:classifiers":[
        {
            "category":"Military Area",
            "subcategory":"Air Force Base",
            "type":"Public Place"
        }
    ],
    "sg:phone":"+44 24 7666 6333",
    "sg:postcode":"CV6 5EZ",
    "sg:province":"Warwickshire",
    "sg:tags":[
        "taxi",
        "hire",
        "private"
    ],
    "wof:name":"Coventry Taxis & Coaches",
    "wof:placetype":"venue"
},
  "geometry": {"coordinates":[-1.493652,52.420704],"type":"Point"}
}