{
  "type": "Feature",
  "properties": {
    "iso:country":"GB",
    "sg:address":"St John Ambulance Hall, Reigate Road",
    "sg:city":"Dorking",
    "sg:classifiers":[
        {
            "category":"Education",
            "subcategory":"Preschool",
            "type":"Public Place"
        }
    ],
    "sg:postcode":"RH4 1SG",
    "sg:province":"Surrey",
    "sg:tags":[
        "pre-school",
        "playgroups"
    ],
    "wof:name":"Deepdene Playgroup",
    "wof:placetype":"venue"
},
  "geometry": {"coordinates":[-0.328814,51.233341],"type":"Point"}
}