{
  "type": "Feature",
  "properties": {
    "addr:full":"Mongleath Road Falmouth Cornwall TR11 4PN",
    "addr:postcode":"tr11 4pn",
    "addr:street":"Mongleath Road",
    "iso:country":"GB",
    "sg:address":"Mongleath Road",
    "sg:city":"Falmouth",
    "sg:classifiers":[
        {
            "category":"Bars & Pubs",
            "type":"Food & Drink"
        }
    ],
    "sg:postcode":"TR11 4PN",
    "sg:province":"Cornwall",
    "sg:tags":[
        "pubs",
        "inn"
    ],
    "wof:name":"The Clipper Way",
    "wof:placetype":"venue"
},
  "geometry": {"coordinates":[-5.0911521912,50.1498641968],"type":"Point"}
}