{
  "type": "Feature",
  "properties": {
    "iso:country":"GB",
    "sg:address":"Farfield Street",
    "sg:city":"Cleckheaton",
    "sg:classifiers":[
        {
            "category":"Wholesale",
            "subcategory":"Office Equipment",
            "type":"Manufacturing & Wholesale Goods"
        },
        {
            "category":"Building & Trades",
            "subcategory":"Landscaping Services",
            "type":"Services"
        }
    ],
    "sg:postcode":"BD19 3TX",
    "sg:province":"West Yorkshire",
    "sg:tags":[
        "horticultural",
        "consultant",
        "register",
        "cash",
        "accessory"
    ],
    "wof:name":"Vanguard Paper Roll Factory",
    "wof:placetype":"venue"
},
  "geometry": {"coordinates":[-1.717357,53.730755],"type":"Point"}
}