{
  "type": "Feature",
  "properties": {
    "iso:country":"GB",
    "sg:address":"Goldline Ho, Vickers Indust Est, Mellishaw La",
    "sg:city":"Morecambe",
    "sg:classifiers":[
        {
            "category":"Building & Trades",
            "subcategory":"Construction",
            "type":"Services"
        }
    ],
    "sg:phone":"+44 1524 37857",
    "sg:postcode":"LA3 3EN",
    "sg:province":"Lancashire",
    "sg:tags":[
        "builder"
    ],
    "wof:name":"Baldwins",
    "wof:placetype":"venue"
},
  "geometry": {"coordinates":[-2.850855,54.056004],"type":"Point"}
}