{
  "type": "Feature",
  "properties": {
    "iso:country":"GB",
    "sg:address":"159 Leeds Old Road",
    "sg:city":"Heckmondwike",
    "sg:classifiers":[
        {
            "category":"Retail",
            "subcategory":"Auto Repair",
            "type":"Services"
        }
    ],
    "sg:phone":"+44 1924 472233",
    "sg:postcode":"WF16 9BB",
    "sg:province":"West Yorkshire",
    "sg:tags":[
        "modification",
        "garage",
        "related"
    ],
    "wof:name":"Whitehall Service Station",
    "wof:placetype":"venue"
},
  "geometry": {"coordinates":[-1.66870296,53.7202110291],"type":"Point"}
}