{
  "type": "Feature",
  "properties": {
    "iso:country":"GB",
    "sg:address":"Britannia Foundry, Lomax Street",
    "sg:city":"Rochdale",
    "sg:classifiers":[
        {
            "category":"Manufacturing",
            "subcategory":"Rubber & Plastics",
            "type":"Manufacturing & Wholesale Goods"
        },
        {
            "category":"Professional",
            "subcategory":"Engineering",
            "type":"Services"
        }
    ],
    "sg:phone":"+44 1706 868070",
    "sg:postcode":"OL12 0DN",
    "sg:province":"Lancashire",
    "sg:tags":[
        "product",
        "engineer"
    ],
    "wof:name":"CARBON LITE LTD",
    "wof:placetype":"venue"
},
  "geometry": {"coordinates":[-2.1627659798,53.6190071106],"type":"Point"}
}