{
  "type": "Feature",
  "properties": {
    "iso:country":"GB",
    "sg:address":"126 Port Tennant Road, Port Tennant",
    "sg:city":"Swansea",
    "sg:classifiers":[
        {
            "category":"Food & Beverages",
            "subcategory":"Groceries & Convenience Stores",
            "type":"Retail Goods"
        }
    ],
    "sg:phone":"+44 1792 456656",
    "sg:postcode":"SA1 8JG",
    "sg:province":"Neath Port Talbot",
    "wof:name":"Spar Shop",
    "wof:placetype":"venue"
},
  "geometry": {"coordinates":[-3.9229619503,51.6222419739],"type":"Point"}
}