{
  "type": "Feature",
  "properties": {
    "addr:full":"1 Queens Rd Farnborough Hampshire GU14 6DJ",
    "addr:housenumber":"1",
    "addr:postcode":"gu14 6dj",
    "addr:street":"Queens Rd",
    "iso:country":"GB",
    "sg:address":"1 Queens Rd",
    "sg:city":"Farnborough",
    "sg:classifiers":[
        {
            "category":"Building & Trades",
            "subcategory":"Plumbing",
            "type":"Services"
        }
    ],
    "sg:phone":"+44 1252 400800",
    "sg:postcode":"GU14 6DJ",
    "sg:province":"Hampshire",
    "sg:tags":[
        "central",
        "heating"
    ],
    "wof:name":"Gas Network (uk) Ltd",
    "wof:placetype":"venue"
},
  "geometry": {"coordinates":[-0.7495470047,51.2764587402],"type":"Point"}
}