{
  "type": "Feature",
  "properties": {
    "addr:full":"Harris Young & Bettie, Arcadia Ho, 37 Worchester St Kidderminster Staffordshire DY10 1EW",
    "addr:housenumber":"37",
    "addr:postcode":"dy10 1ew",
    "addr:street":"Worchester St",
    "iso:country":"GB",
    "sg:address":"Harris Young & Bettie, Arcadia Ho, 37 Worchester St",
    "sg:city":"Kidderminster",
    "sg:classifiers":[
        {
            "category":"Banks & Credit Unions",
            "subcategory":"Investment Brokerage",
            "type":"Services"
        }
    ],
    "sg:postcode":"DY10 1EW",
    "sg:province":"Staffordshire",
    "wof:name":"Foregate Investment Advisers Ltd",
    "wof:placetype":"venue"
},
  "geometry": {"coordinates":[-2.2466371059,52.3866081238],"type":"Point"}
}