{
  "type": "Feature",
  "properties": {
    "addr:full":"179 Frogmore Lane, Lovedean Waterlooville Hampshire PO8 9RD",
    "addr:housenumber":"179",
    "addr:postcode":"po8 9rd",
    "addr:street":"Frogmore Lane",
    "iso:country":"GB",
    "sg:address":"179 Frogmore Lane, Lovedean",
    "sg:city":"Waterlooville",
    "sg:classifiers":[
        {
            "category":"Professional",
            "subcategory":"Engineering",
            "type":"Services"
        }
    ],
    "sg:phone":"+44 23 9259 9163",
    "sg:postcode":"PO8 9RD",
    "sg:province":"Hampshire",
    "sg:tags":[
        "civil",
        "engineer"
    ],
    "wof:name":"Benstan Civil Engineers Ltd",
    "wof:placetype":"venue"
},
  "geometry": {"coordinates":[-1.016154,50.91568],"type":"Point"}
}