{
  "type": "Feature",
  "properties": {
    "addr:full":"Common Farm, Back Lane York East Riding of Yorkshire YO42 4EW",
    "addr:postcode":"yo42 4ew",
    "addr:street":"Back Lane",
    "iso:country":"GB",
    "sg:address":"Common Farm, Back Lane",
    "sg:city":"York",
    "sg:classifiers":[
        {
            "category":"Building & Trades",
            "subcategory":"Construction",
            "type":"Services"
        }
    ],
    "sg:phone":"+44 1759 303327",
    "sg:postcode":"YO42 4EW",
    "sg:province":"East Riding of Yorkshire",
    "sg:tags":[
        "builder"
    ],
    "wof:name":"P Gardham",
    "wof:placetype":"venue"
},
  "geometry": {"coordinates":[-0.8514509797,53.9077186584],"type":"Point"}
}