{
  "type": "Feature",
  "properties": {
    "addr:full":"Sycamore Close Bourne Lincolnshire PE10 9RS",
    "addr:postcode":"pe10 9rs",
    "addr:street":"Sycamore Close",
    "iso:country":"GB",
    "sg:address":"Sycamore Close",
    "sg:city":"Bourne",
    "sg:classifiers":[
        {
            "category":"Professional",
            "type":"Services"
        }
    ],
    "sg:phone":"+44 1778 394865",
    "sg:postcode":"PE10 9RS",
    "sg:province":"Lincolnshire",
    "sg:tags":[
        "repair",
        "tech",
        "maintenance"
    ],
    "wof:name":"Diamond Information Technology",
    "wof:placetype":"venue"
},
  "geometry": {"coordinates":[-0.3931739926,52.7692337036],"type":"Point"}
}