{
  "type": "Feature",
  "properties": {
    "addr:full":"21 Iliffe Yard, Crampton Street London Greater London SE17 3QA",
    "addr:housenumber":"21",
    "addr:postcode":"se17 3qa",
    "addr:street":"Iliffe Yard Crampton Street",
    "iso:country":"GB",
    "sg:address":"21 Iliffe Yard, Crampton Street",
    "sg:city":"London",
    "sg:classifiers":[
        {
            "category":"Manufacturing",
            "subcategory":"Pottery",
            "type":"Manufacturing & Wholesale Goods"
        }
    ],
    "sg:postcode":"SE17 3QA",
    "sg:province":"Greater London",
    "wof:name":"Caroline Whyman",
    "wof:placetype":"venue"
},
  "geometry": {"coordinates":[-0.0996560007,51.4898147583],"type":"Point"}
}