{
  "type": "Feature",
  "properties": {
    "addr:full":"136 High Street, Quarry Bank Brierley Hill West Midlands DY5 2AF",
    "addr:housenumber":"136",
    "addr:postcode":"dy5 2af",
    "addr:street":"High Street;Brierley Hill",
    "iso:country":"GB",
    "sg:address":"136 High Street, Quarry Bank",
    "sg:city":"Brierley Hill",
    "sg:classifiers":[
        {
            "category":"Food & Beverages",
            "subcategory":"Meat & Fish",
            "type":"Retail Goods"
        }
    ],
    "sg:phone":"+44 1384 635168",
    "sg:postcode":"DY5 2AF",
    "sg:province":"West Midlands",
    "sg:tags":[
        "chip"
    ],
    "wof:name":"Our Plaice Too",
    "wof:placetype":"venue"
},
  "geometry": {"coordinates":[-2.100698,52.471523],"type":"Point"}
}