{
  "type": "Feature",
  "properties": {
    "addr:full":"The Old Co-op Llanelly Hill Abergavenny Herefordshire NP7 0PG",
    "addr:postcode":"np7 0pg",
    "addr:street":"Hill",
    "iso:country":"GB",
    "sg:address":"The Old Co-op Llanelly Hill",
    "sg:city":"Abergavenny",
    "sg:classifiers":[
        {
            "category":"Home & Garden",
            "subcategory":"Hardware",
            "type":"Retail Goods"
        }
    ],
    "sg:phone":"+44 1873 832383",
    "sg:postcode":"NP7 0PG",
    "sg:province":"Herefordshire",
    "sg:tags":[
        "part",
        "accessory"
    ],
    "wof:name":"Big Hill Motor Cycles",
    "wof:placetype":"venue"
},
  "geometry": {"coordinates":[-3.1392080784,51.8060874939],"type":"Point"}
}