{
  "type": "Feature",
  "properties": {
    "addr:full":"8 Links Way, Flackwell Heath High Wycombe Buckinghamshire HP10 9LZ",
    "addr:housenumber":"8",
    "addr:postcode":"hp10 9lz",
    "addr:street":"Links Way",
    "iso:country":"GB",
    "sg:address":"8 Links Way, Flackwell Heath",
    "sg:city":"High Wycombe",
    "sg:classifiers":[
        {
            "category":"Travel",
            "subcategory":"Travel Agent",
            "type":"Entertainment"
        }
    ],
    "sg:phone":"+44 1628 850169",
    "sg:postcode":"HP10 9LZ",
    "sg:province":"Buckinghamshire",
    "sg:tags":[
        "hotel",
        "agency",
        "booking"
    ],
    "wof:name":"Location-Link",
    "wof:placetype":"venue"
},
  "geometry": {"coordinates":[-0.702858,51.599434],"type":"Point"}
}