{
  "type": "Feature",
  "properties": {
    "addr:full":"89-91 Queen Street Morpeth Northumberland NE65 0DA",
    "addr:housenumber":"89-91",
    "addr:postcode":"ne65 0da",
    "addr:street":"Queen Street",
    "iso:country":"GB",
    "sg:address":"89-91 Queen Street",
    "sg:city":"Morpeth",
    "sg:classifiers":[
        {
            "category":"Home & Garden",
            "subcategory":"Hardware",
            "type":"Retail Goods"
        }
    ],
    "sg:phone":"+44 1665 710800",
    "sg:postcode":"NE65 0DA",
    "sg:province":"Northumberland",
    "sg:tags":[
        "retailer",
        "diy"
    ],
    "wof:name":"E T Lawrence",
    "wof:placetype":"venue"
},
  "geometry": {"coordinates":[-1.5831389427,55.3342285156],"type":"Point"}
}