{
  "type": "Feature",
  "properties": {
    "addr:full":"5 Byron Square Aberdeen Aberdeen City AB16 7LL",
    "addr:housenumber":"5",
    "addr:postcode":"ab16 7ll",
    "addr:street":"Byron Square",
    "iso:country":"GB",
    "sg:address":"5 Byron Square",
    "sg:city":"Aberdeen",
    "sg:classifiers":[
        {
            "category":"Shopping",
            "subcategory":"News",
            "type":"Retail Goods"
        }
    ],
    "sg:phone":"+44 1224 663099",
    "sg:postcode":"AB16 7LL",
    "sg:province":"Aberdeen City",
    "sg:tags":[
        "newsagent"
    ],
    "wof:name":"R S McColl",
    "wof:placetype":"venue"
},
  "geometry": {"coordinates":[-2.162164,57.165272],"type":"Point"}
}