{
  "type": "Feature",
  "properties": {
    "addr:full":"Manor Farm, Stanford Lane, Cotes Loughborough Leicestershire LE12 5TW",
    "addr:postcode":"le12 5tw",
    "addr:street":"Manor;Stanford Lane",
    "iso:country":"GB",
    "sg:address":"Manor Farm, Stanford Lane, Cotes",
    "sg:city":"Loughborough",
    "sg:classifiers":[
        {
            "category":"Farming",
            "subcategory":"Livestock Farm",
            "type":"Manufacturing & Wholesale Goods"
        }
    ],
    "sg:postcode":"LE12 5TW",
    "sg:province":"Leicestershire",
    "sg:tags":[
        "others"
    ],
    "wof:name":"Prestwold Farms",
    "wof:placetype":"venue"
},
  "geometry": {"coordinates":[-1.1783189774,52.7820014954],"type":"Point"}
}