{
  "type": "Feature",
  "properties": {
    "addr:full":"39 Main Road Bradford West Yorkshire BD13 4AF",
    "addr:housenumber":"39",
    "addr:postcode":"bd13 4af",
    "addr:street":"Main Road",
    "iso:country":"GB",
    "sg:address":"39 Main Road",
    "sg:city":"Bradford",
    "sg:classifiers":[
        {
            "category":"Shopping",
            "subcategory":"Clothing, Apparel, & Fashions",
            "type":"Retail Goods"
        }
    ],
    "sg:phone":"+44 1274 832925",
    "sg:postcode":"BD13 4AF",
    "sg:province":"West Yorkshire",
    "sg:tags":[
        "haberdasher"
    ],
    "wof:name":"Jowetts",
    "wof:placetype":"venue"
},
  "geometry": {"coordinates":[-1.8969980478,53.8012275696],"type":"Point"}
}