{
  "type": "Feature",
  "properties": {
    "addr:full":"High Barbuchany Christian Centre Newton Stewart Dumfries and Galloway DG8 6QF",
    "addr:postcode":"dg8 6qf",
    "addr:street":"Newton Stewart",
    "iso:country":"GB",
    "sg:address":"High Barbuchany Christian Centre",
    "sg:city":"Newton Stewart",
    "sg:classifiers":[
        {
            "category":"Organizations",
            "subcategory":"Religious Organization",
            "type":"Services"
        }
    ],
    "sg:phone":"+44 1671 403632",
    "sg:postcode":"DG8 6QF",
    "sg:province":"Dumfries and Galloway",
    "sg:tags":[
        "organisation"
    ],
    "wof:name":"The Safe Mission",
    "wof:placetype":"venue"
},
  "geometry": {"coordinates":[-4.482984066,54.9547843933],"type":"Point"}
}