{
  "type": "Feature",
  "properties": {
    "iso:country":"GB",
    "sg:address":"56b Roseville Road",
    "sg:city":"Leeds",
    "sg:classifiers":[
        {
            "category":"Shopping",
            "subcategory":"Crafts & Fabrics",
            "type":"Retail Goods"
        }
    ],
    "sg:postcode":"LS8 5DJ",
    "sg:province":"West Yorkshire",
    "sg:tags":[
        "knitwear",
        "yarn"
    ],
    "wof:name":"Dihman Fashions",
    "wof:placetype":"venue"
},
  "geometry": {"coordinates":[-1.5283410549,53.8078346252],"type":"Point"}
}