{
  "type": "Feature",
  "properties": {
    "addr:full":"The Smithy, Chelmorton Buxton Derbyshire SK17 9SL",
    "addr:postcode":"sk17 9sl",
    "iso:country":"GB",
    "sg:address":"The Smithy, Chelmorton",
    "sg:city":"Buxton",
    "sg:classifiers":[
        {
            "category":"Retail",
            "subcategory":"Repair Shop",
            "type":"Services"
        }
    ],
    "sg:postcode":"SK17 9SL",
    "sg:province":"Derbyshire",
    "sg:tags":[
        "plant",
        "machinery"
    ],
    "wof:name":"Geoffrey Standidge",
    "wof:placetype":"venue"
},
  "geometry": {"coordinates":[-1.831879,53.227661],"type":"Point"}
}