{
  "type": "Feature",
  "properties": {
    "iso:country":"GB",
    "sg:address":"Hadlow",
    "sg:city":"Tonbridge",
    "sg:classifiers":[
        {
            "category":"Education",
            "subcategory":"School",
            "type":"Public Place"
        }
    ],
    "sg:phone":"+44 1732 850349",
    "sg:postcode":"TN11 0EH",
    "sg:province":"Kent",
    "sg:tags":[
        "local",
        "authority"
    ],
    "wof:name":"Hadlow County Primary School",
    "wof:placetype":"venue"
},
  "geometry": {"coordinates":[0.33772,51.22435],"type":"Point"}
}