{
  "type": "Feature",
  "properties": {
    "addr:full":"St Kilda Bank, Bourtreehill Irvine East Ayrshire KA11 1LA",
    "addr:postcode":"ka11 1la",
    "addr:street":"Bourtreehill;East",
    "iso:country":"GB",
    "sg:address":"St Kilda Bank, Bourtreehill",
    "sg:city":"Irvine",
    "sg:classifiers":[
        {
            "category":"Education",
            "subcategory":"School",
            "type":"Public Place"
        }
    ],
    "sg:phone":"+44 1294 214170",
    "sg:postcode":"KA11 1LA",
    "sg:province":"East Ayrshire",
    "sg:tags":[
        "local",
        "authority"
    ],
    "wof:name":"Broomlands Primary School",
    "wof:placetype":"venue"
},
  "geometry": {"coordinates":[-4.633285,55.613232],"type":"Point"}
}