{
  "type": "Feature",
  "properties": {
    "addr:full":"68 Wildern Lane, West Hunsbury Northampton Northamptonshire NN4 0SN",
    "addr:housenumber":"68",
    "addr:postcode":"nn4 0sn",
    "addr:street":"Wildern Lane West Hunsbury",
    "iso:country":"GB",
    "sg:address":"68 Wildern Lane, West Hunsbury",
    "sg:city":"Northampton",
    "sg:classifiers":[
        {
            "category":"Professional",
            "subcategory":"Business Services",
            "type":"Services"
        }
    ],
    "sg:phone":"+44 1604 768440",
    "sg:postcode":"NN4 0SN",
    "sg:province":"Northamptonshire",
    "sg:tags":[
        "food",
        "import",
        "export",
        "agent"
    ],
    "wof:name":"Mistral Wholesale",
    "wof:placetype":"venue"
},
  "geometry": {"coordinates":[-0.897562027,52.2012138367],"type":"Point"}
}