{
  "type": "Feature",
  "properties": {
    "addr:full":"Unit 1, 60 Westcliffe Rd, Ruskington Sleaford Lincolnshire NG34 9AY",
    "addr:housenumber":"unit;60",
    "addr:postcode":"ng34 9ay",
    "addr:street":"Westcliffe Rd",
    "iso:country":"GB",
    "sg:address":"Unit 1, 60 Westcliffe Rd, Ruskington",
    "sg:city":"Sleaford",
    "sg:classifiers":[
        {
            "category":"Retail",
            "subcategory":"Auto Repair",
            "type":"Services"
        }
    ],
    "sg:phone":"+44 1526 834576",
    "sg:postcode":"NG34 9AY",
    "sg:province":"Lincolnshire",
    "sg:tags":[
        "modification",
        "garage"
    ],
    "wof:name":"A & P Garage Services & Vehicle Air Conditioning",
    "wof:placetype":"venue"
},
  "geometry": {"coordinates":[-0.399652,53.046898],"type":"Point"}
}