{
  "type": "Feature",
  "properties": {
    "addr:full":"Units F4-f5 Westfield Industrial Estate, Second Avenue, Midsomer Norton Bath Somerset BA3 4BH",
    "addr:postcode":"ba3 4bh",
    "addr:street":"Industrial Estate Second Avenue",
    "iso:country":"GB",
    "sg:address":"Units F4-f5 Westfield Industrial Estate, Second Avenue, Midsomer Norton",
    "sg:city":"Bath",
    "sg:classifiers":[
        {
            "category":"Home & Garden",
            "subcategory":"Household Appliances",
            "type":"Retail Goods"
        }
    ],
    "sg:phone":"+44 1761 417018",
    "sg:postcode":"BA3 4BH",
    "sg:province":"Somerset",
    "sg:tags":[
        "electrical"
    ],
    "wof:name":"Mike Haley",
    "wof:placetype":"venue"
},
  "geometry": {"coordinates":[-2.466989994,51.2775802612],"type":"Point"}
}