{
  "type": "Feature",
  "properties": {
    "addr:full":"39 Webb Lane, Offerton Stockport Cheshire SK1 4EL",
    "addr:housenumber":"39",
    "addr:postcode":"sk1 4el",
    "addr:street":"Webb Lane",
    "iso:country":"GB",
    "sg:address":"39 Webb Lane, Offerton",
    "sg:city":"Stockport",
    "sg:classifiers":[
        {
            "category":"Retail",
            "subcategory":"Driving School",
            "type":"Services"
        }
    ],
    "sg:phone":"+44 161 477 1827",
    "sg:postcode":"SK1 4EL",
    "sg:province":"Cheshire",
    "wof:name":"J D S Driving Tuition",
    "wof:placetype":"venue"
},
  "geometry": {"coordinates":[-2.14459,53.405361],"type":"Point"}
}