{
  "type": "Feature",
  "properties": {
    "addr:full":"Hollands Farm, Hawley Dartford Kent DA1 1PX",
    "addr:postcode":"da1 1px",
    "addr:street":"Hollands Farm Hawley",
    "iso:country":"GB",
    "sg:address":"Hollands Farm, Hawley",
    "sg:city":"Dartford",
    "sg:classifiers":[
        {
            "category":"Wholesale",
            "subcategory":"Fruits & Vegetables",
            "type":"Manufacturing & Wholesale Goods"
        }
    ],
    "sg:phone":"+44 1322 223627",
    "sg:postcode":"DA1 1PX",
    "sg:province":"Kent",
    "wof:name":"J J Barker Southfleet",
    "wof:placetype":"venue"
},
  "geometry": {"coordinates":[0.2205549926,51.4446334839],"type":"Point"}
}