{
  "type": "Feature",
  "properties": {
    "iso:country":"GB",
    "sg:address":"5 Alma Lane",
    "sg:city":"Heckmondwike",
    "sg:classifiers":[
        {
            "category":"Personal",
            "subcategory":"Beauty Salon",
            "type":"Services"
        },
        {
            "category":"Personal",
            "subcategory":"Barber",
            "type":"Services"
        }
    ],
    "sg:phone":"+44 1924 405091",
    "sg:postcode":"WF16 9AB",
    "sg:province":"West Yorkshire",
    "sg:tags":[
        "unisex",
        "hairdresser"
    ],
    "wof:name":"Hair Fashions",
    "wof:placetype":"venue"
},
  "geometry": {"coordinates":[-1.673992,53.71748],"type":"Point"}
}