{
  "type": "Feature",
  "properties": {
    "addr:full":"520 Durham Road, Low Fell Gateshead Tyne and Wear NE9 6HU",
    "addr:housenumber":"520",
    "addr:postcode":"ne9 6hu",
    "addr:street":"Durham Road",
    "iso:country":"GB",
    "sg:address":"520 Durham Road, Low Fell",
    "sg:city":"Gateshead",
    "sg:classifiers":[
        {
            "category":"Home & Garden",
            "subcategory":"Building Materials",
            "type":"Retail Goods"
        }
    ],
    "sg:phone":"+44 191 487 6266",
    "sg:postcode":"NE9 6HU",
    "sg:province":"Tyne and Wear",
    "sg:tags":[
        "brick"
    ],
    "wof:name":"The Chimney Stack",
    "wof:placetype":"venue"
},
  "geometry": {"coordinates":[-1.5998859406,54.9362792969],"type":"Point"}
}