{
  "type": "Feature",
  "properties": {
    "addr:full":"51 Albert Road Blackpool Lancashire FY1 4TA",
    "addr:housenumber":"51",
    "addr:postcode":"fy1 4ta",
    "addr:street":"Albert Road",
    "iso:country":"GB",
    "sg:address":"51 Albert Road",
    "sg:city":"Blackpool",
    "sg:classifiers":[
        {
            "category":"Travel",
            "subcategory":"Hotels & Motels",
            "type":"Entertainment"
        }
    ],
    "sg:phone":"+44 1253 626467",
    "sg:postcode":"FY1 4TA",
    "sg:province":"Lancashire",
    "wof:name":"The Courtland Hotel",
    "wof:placetype":"venue"
},
  "geometry": {"coordinates":[-3.051459,53.815197],"type":"Point"}
}