{
  "type": "Feature",
  "properties": {
    "addr:full":"Unit 3 Halstead Business Centre, Factory Lane West Halstead Essex CO9 1EX",
    "addr:housenumber":"unit 3",
    "addr:postcode":"co9 1ex",
    "addr:street":"Halstead Business Centre Factory Lane West",
    "iso:country":"GB",
    "sg:address":"Unit 3 Halstead Business Centre, Factory Lane West",
    "sg:city":"Halstead",
    "sg:classifiers":[
        {
            "category":"Retail",
            "subcategory":"Auto Repair",
            "type":"Services"
        }
    ],
    "sg:phone":"+44 1787 477474",
    "sg:postcode":"CO9 1EX",
    "sg:province":"Essex",
    "sg:tags":[
        "electrician"
    ],
    "wof:name":"Halstead Auto Electrical",
    "wof:placetype":"venue"
},
  "geometry": {"coordinates":[0.6358249784,51.9439964294],"type":"Point"}
}