{
  "type": "Feature",
  "properties": {
    "iso:country":"GB",
    "sg:address":"3 Carbis Clo",
    "sg:city":"Barnsley",
    "sg:classifiers":[
        {
            "category":"Professional",
            "subcategory":"Detective & Security Services",
            "type":"Services"
        }
    ],
    "sg:phone":"+44 1226 201022",
    "sg:postcode":"S71 2QN",
    "sg:province":"South Yorkshire",
    "sg:tags":[
        "alarm",
        "burglar",
        "system"
    ],
    "wof:name":"Bretton Security",
    "wof:placetype":"venue"
},
  "geometry": {"coordinates":[-1.458367,53.559086],"type":"Point"}
}