{
  "type": "Feature",
  "properties": {
    "addr:full":"2 Osborne Street Grimsby Lincolnshire DN31 1EY",
    "addr:housenumber":"2",
    "addr:postcode":"dn31 1ey",
    "addr:street":"Osborne Street",
    "iso:country":"GB",
    "sg:address":"2 Osborne Street",
    "sg:city":"Grimsby",
    "sg:classifiers":[
        {
            "category":"Restaurant",
            "type":"Food & Drink"
        }
    ],
    "sg:phone":"+44 1472 361146",
    "sg:postcode":"DN31 1EY",
    "sg:province":"Lincolnshire",
    "sg:tags":[
        "french"
    ],
    "wof:name":"Bon Appetit Bistro",
    "wof:placetype":"venue"
},
  "geometry": {"coordinates":[-0.085417,53.564713],"type":"Point"}
}