{
  "type": "Feature",
  "properties": {
    "addr:full":"39 Lincoln Way Colchester Essex CO1 2RJ",
    "addr:housenumber":"39",
    "addr:postcode":"co1 2rj",
    "addr:street":"Lincoln Way",
    "iso:country":"GB",
    "sg:address":"39 Lincoln Way",
    "sg:city":"Colchester",
    "sg:classifiers":[
        {
            "category":"Building & Trades",
            "subcategory":"Plumbing",
            "type":"Services"
        }
    ],
    "sg:phone":"+44 1206 866543",
    "sg:postcode":"CO1 2RJ",
    "sg:province":"Essex",
    "sg:tags":[
        "heating"
    ],
    "wof:name":"Michael Duffett",
    "wof:placetype":"venue"
},
  "geometry": {"coordinates":[0.9097189903,51.8933830261],"type":"Point"}
}