{
  "type": "Feature",
  "properties": {
    "addr:full":"27 Thingwall Rd Wirral Merseyside CH61 3UE",
    "addr:housenumber":"27",
    "addr:postcode":"ch61 3ue",
    "addr:street":"Thingwall Rd",
    "iso:country":"GB",
    "sg:address":"27 Thingwall Rd",
    "sg:city":"Wirral",
    "sg:classifiers":[
        {
            "category":"Food & Beverages",
            "subcategory":"Bakery",
            "type":"Retail Goods"
        }
    ],
    "sg:postcode":"CH61 3UE",
    "sg:province":"Merseyside",
    "sg:tags":[
        "baker"
    ],
    "wof:name":"J W Matthews",
    "wof:placetype":"venue"
},
  "geometry": {"coordinates":[-3.097233,53.354961],"type":"Point"}
}