{
  "type": "Feature",
  "properties": {
    "addr:full":"3a Tannery Lane, Penketh Warrington Cheshire WA5 2UD",
    "addr:housenumber":"3a",
    "addr:postcode":"wa5 2ud",
    "addr:street":"Tannery Lane",
    "iso:country":"GB",
    "sg:address":"3a Tannery Lane, Penketh",
    "sg:city":"Warrington",
    "sg:classifiers":[
        {
            "category":"Professional",
            "subcategory":"Engineering",
            "type":"Services"
        }
    ],
    "sg:phone":"+44 1925 728090",
    "sg:postcode":"WA5 2UD",
    "sg:province":"Cheshire",
    "sg:tags":[
        "contractor",
        "electrical",
        "engineer"
    ],
    "wof:name":"Surety Electrics",
    "wof:placetype":"venue"
},
  "geometry": {"coordinates":[-2.6720221043,53.379776001],"type":"Point"}
}