{
  "type": "Feature",
  "properties": {
    "iso:country":"GB",
    "sg:address":"50 Chadwick Close",
    "sg:city":"Coventry",
    "sg:classifiers":[
        {
            "category":"Professional",
            "subcategory":"Printing & Photocopies",
            "type":"Services"
        }
    ],
    "sg:postcode":"CV5 7HQ",
    "sg:province":"West Midlands",
    "sg:tags":[
        "top",
        "publishing",
        "desk"
    ],
    "wof:name":"I C P S",
    "wof:placetype":"venue"
},
  "geometry": {"coordinates":[-1.560743,52.408707],"type":"Point"}
}