{
  "type": "Feature",
  "properties": {
    "addr:full":"Unit 30, Midland Oak Trading Estate, Marlissa Drive Coventry Warwickshire CV6 6HQ",
    "addr:housenumber":"unit 30",
    "addr:postcode":"cv6 6hq",
    "addr:street":"Trading;Marlissa Drive",
    "iso:country":"GB",
    "sg:address":"Unit 30, Midland Oak Trading Estate, Marlissa Drive",
    "sg:city":"Coventry",
    "sg:classifiers":[
        {
            "category":"Autos & Motor Vehicles",
            "subcategory":"Auto Supplies",
            "type":"Retail Goods"
        }
    ],
    "sg:phone":"+44 24 7666 7211",
    "sg:postcode":"CV6 6HQ",
    "sg:province":"Warwickshire",
    "sg:tags":[
        "gearbox"
    ],
    "wof:name":"Coventry Gearbox Services",
    "wof:placetype":"venue"
},
  "geometry": {"coordinates":[-1.4993900061,52.4430885315],"type":"Point"}
}