{
  "type": "Feature",
  "properties": {
    "addr:full":"788 Newport Road, Rumney Cardiff Caerphilly CF3 4FG",
    "addr:housenumber":"788",
    "addr:postcode":"cf3 4fg",
    "addr:street":"Newport Road",
    "iso:country":"GB",
    "sg:address":"788 Newport Road, Rumney",
    "sg:city":"Cardiff",
    "sg:classifiers":[
        {
            "category":"Retail",
            "subcategory":"Auto Repair",
            "type":"Services"
        }
    ],
    "sg:phone":"+44 29 2079 7847",
    "sg:postcode":"CF3 4FG",
    "sg:province":"Caerphilly",
    "sg:tags":[
        "modification",
        "garage",
        "related"
    ],
    "wof:name":"Rumney Hill Garage",
    "wof:placetype":"venue"
},
  "geometry": {"coordinates":[-3.132668972,51.5084114075],"type":"Point"}
}