{
  "type": "Feature",
  "properties": {
    "iso:country":"GB",
    "sg:address":"5b Bedford Sq",
    "sg:city":"Loughborough",
    "sg:classifiers":[
        {
            "category":"Personal",
            "subcategory":"Barber",
            "type":"Services"
        }
    ],
    "sg:phone":"+44 1509 264971",
    "sg:postcode":"LE11 2TP",
    "sg:province":"Leicestershire",
    "sg:tags":[
        "men's",
        "hairdresser"
    ],
    "wof:name":"Hair-Port",
    "wof:placetype":"venue"
},
  "geometry": {"coordinates":[-1.207513,52.768364],"type":"Point"}
}