{
  "type": "Feature",
  "properties": {
    "addr:full":"Fairfield Farm, Barkers La Wrexham Wrexham LL13 9TP",
    "addr:postcode":"ll13 9tp",
    "iso:country":"GB",
    "sg:address":"Fairfield Farm, Barkers La",
    "sg:city":"Wrexham",
    "sg:classifiers":[
        {
            "category":"Freight",
            "type":"Transportation"
        }
    ],
    "sg:phone":"+44 1978 365460",
    "sg:postcode":"LL13 9TP",
    "sg:province":"Wrexham",
    "sg:tags":[
        "haulage",
        "road"
    ],
    "wof:name":"D & J Moore",
    "wof:placetype":"venue"
},
  "geometry": {"coordinates":[-2.91579,53.039108],"type":"Point"}
}