{
  "type": "Feature",
  "properties": {
    "addr:full":"Killiow Farm, Tregony Truro Cornwall TR2 5UD",
    "addr:postcode":"tr2 5ud",
    "addr:street":"Tregony",
    "iso:country":"GB",
    "sg:address":"Killiow Farm, Tregony",
    "sg:city":"Truro",
    "sg:classifiers":[
        {
            "category":"Farming",
            "subcategory":"Livestock Farm",
            "type":"Manufacturing & Wholesale Goods"
        }
    ],
    "sg:postcode":"TR2 5UD",
    "sg:province":"Cornwall",
    "sg:tags":[
        "others"
    ],
    "wof:name":"Denning,David J, Peter J, & Elizabeth H,",
    "wof:placetype":"venue"
},
  "geometry": {"coordinates":[-4.9126501083,50.2677154541],"type":"Point"}
}