{
  "type": "Feature",
  "properties": {
    "addr:full":"8 Olive St Chester-le-street Durham DH2 3SQ",
    "addr:housenumber":"8",
    "addr:postcode":"dh2 3sq",
    "addr:street":"Olive St",
    "iso:country":"GB",
    "sg:address":"8 Olive St",
    "sg:city":"Chester-le-street",
    "sg:classifiers":[
        {
            "category":"Home & Garden",
            "subcategory":"Furniture",
            "type":"Retail Goods"
        }
    ],
    "sg:postcode":"DH2 3SQ",
    "sg:province":"Durham",
    "wof:name":"Bell,David,",
    "wof:placetype":"venue"
},
  "geometry": {"coordinates":[-1.6087659597,54.8454093933],"type":"Point"}
}