{
  "type": "Feature",
  "properties": {
    "addr:full":"37 Cedar Avenue, Coseley Bilston West Midlands WV14 9TX",
    "addr:housenumber":"37",
    "addr:postcode":"wv14 9tx",
    "addr:street":"Cedar Avenue",
    "iso:country":"GB",
    "sg:address":"37 Cedar Avenue, Coseley",
    "sg:city":"Bilston",
    "sg:classifiers":[
        {
            "category":"Professional",
            "subcategory":"Detective & Security Services",
            "type":"Services"
        }
    ],
    "sg:phone":"+44 1902 677334",
    "sg:postcode":"WV14 9TX",
    "sg:province":"West Midlands",
    "wof:name":"G J B Electrical & Security",
    "wof:placetype":"venue"
},
  "geometry": {"coordinates":[-2.0970799923,52.5375976562],"type":"Point"}
}