{
  "type": "Feature",
  "properties": {
    "iso:country":"GB",
    "sg:address":"Hackworth House, Byerley Road",
    "sg:city":"Durham",
    "sg:classifiers":[
        {
            "category":"Social Services",
            "subcategory":"Job Training",
            "type":"Services"
        }
    ],
    "sg:phone":"+44 1388 774790",
    "sg:postcode":"DL4 1PU",
    "sg:province":"Durham",
    "sg:tags":[
        "draughtsman",
        "drawing"
    ],
    "wof:name":"C S E S Ltd.",
    "wof:placetype":"venue"
},
  "geometry": {"coordinates":[-1.64826,54.625801],"type":"Point"}
}