{
  "type": "Feature",
  "properties": {
    "iso:country":"GB",
    "sg:address":"Saba House, 192 Knollys Rd",
    "sg:city":"Streatham",
    "sg:classifiers":[
        {
            "category":"Organizations",
            "subcategory":"Community Association",
            "type":"Services"
        }
    ],
    "sg:phone":"+44 20 8696 7003",
    "sg:postcode":"SW16 2JS",
    "sg:province":"Greater London",
    "sg:tags":[
        "relation",
        "public"
    ],
    "wof:name":"Saba Communications",
    "wof:placetype":"venue"
},
  "geometry": {"coordinates":[-0.1080819964,51.4354705811],"type":"Point"}
}