{
  "type": "Feature",
  "properties": {
    "iso:country":"GB",
    "sg:address":"189 London Road",
    "sg:city":"Burgess Hill",
    "sg:classifiers":[
        {
            "category":"Bars & Pubs",
            "type":"Food & Drink"
        }
    ],
    "sg:phone":"+44 1444 246401",
    "sg:postcode":"RH15 8LH",
    "sg:province":"East Sussex",
    "sg:tags":[
        "pubs",
        "house",
        "inn",
        "public",
        "activity"
    ],
    "wof:name":"Unique Pubs Ltd.",
    "wof:placetype":"venue"
},
  "geometry": {"coordinates":[-0.139049,50.957039],"type":"Point"}
}