{
  "type": "Feature",
  "properties": {
    "addr:full":"Derwent Street Belper Derbyshire DE56 1UQ",
    "addr:postcode":"de56 1uq",
    "addr:street":"Derwent Street",
    "iso:country":"GB",
    "sg:address":"Derwent Street",
    "sg:city":"Belper",
    "sg:classifiers":[
        {
            "category":"Autos & Motor Vehicles",
            "subcategory":"Auto Supplies",
            "type":"Retail Goods"
        }
    ],
    "sg:phone":"+44 1773 820938",
    "sg:postcode":"DE56 1UQ",
    "sg:province":"Derbyshire",
    "sg:tags":[
        "tyre"
    ],
    "wof:name":"Belper Tyres Ltd.",
    "wof:placetype":"venue"
},
  "geometry": {"coordinates":[-1.4864180088,53.0232505798],"type":"Point"}
}