{
  "type": "Feature",
  "properties": {
    "addr:full":"Love Lane Denbigh Conwy LL16 3LU",
    "addr:postcode":"ll16 3lu",
    "addr:street":"Love Lane",
    "iso:country":"GB",
    "sg:address":"Love Lane",
    "sg:city":"Denbigh",
    "sg:classifiers":[
        {
            "category":"Retail",
            "subcategory":"Auto Repair",
            "type":"Services"
        }
    ],
    "sg:phone":"+44 1745 815550",
    "sg:postcode":"LL16 3LU",
    "sg:province":"Conwy",
    "sg:tags":[
        "modification",
        "garage",
        "related"
    ],
    "wof:name":"Love Lane Garage",
    "wof:placetype":"venue"
},
  "geometry": {"coordinates":[-3.422306,53.181671],"type":"Point"}
}