{
  "type": "Feature",
  "properties": {
    "addr:full":"27 Dean Road Leicester Leicestershire LE4 6GP",
    "addr:housenumber":"27",
    "addr:postcode":"le4 6gp",
    "addr:street":"Dean Road",
    "iso:country":"GB",
    "sg:address":"27 Dean Road",
    "sg:city":"Leicester",
    "sg:classifiers":[
        {
            "category":"Professional",
            "subcategory":"Accounting & Tax Preparation",
            "type":"Services"
        }
    ],
    "sg:phone":"+44 116 268 1701",
    "sg:postcode":"LE4 6GP",
    "sg:province":"Leicestershire",
    "sg:tags":[
        "accountant",
        "bookkeeping",
        "primarily",
        "activity"
    ],
    "wof:name":"Arvind Dattani",
    "wof:placetype":"venue"
},
  "geometry": {"coordinates":[-1.1094540358,52.6496582031],"type":"Point"}
}