{
  "type": "Feature",
  "properties": {
    "iso:country":"GB",
    "sg:address":"Rectory Road",
    "sg:city":"Farnborough",
    "sg:classifiers":[
        {
            "category":"Education",
            "subcategory":"School",
            "type":"Public Place"
        }
    ],
    "sg:phone":"+44 1252 544606",
    "sg:postcode":"GU14 8AJ",
    "sg:province":"Hampshire",
    "sg:tags":[
        "local",
        "authority"
    ],
    "wof:name":"North Farnborough County Infant School",
    "wof:placetype":"venue"
},
  "geometry": {"coordinates":[-0.743639,51.300571],"type":"Point"}
}