{
  "type": "Feature",
  "properties": {
    "addr:full":"Blackhurst Lane Tunbridge Wells East Sussex TN2 4PY",
    "addr:postcode":"tn2 4py",
    "addr:street":"Blackhurst Lane;Wells",
    "iso:country":"GB",
    "sg:address":"Blackhurst Lane",
    "sg:city":"Tunbridge Wells",
    "sg:classifiers":[
        {
            "category":"Education",
            "subcategory":"School",
            "type":"Public Place"
        }
    ],
    "sg:phone":"+44 1892 534377",
    "sg:postcode":"TN2 4PY",
    "sg:province":"East Sussex",
    "sg:tags":[
        "college"
    ],
    "wof:name":"Sandown Court Community College",
    "wof:placetype":"venue"
},
  "geometry": {"coordinates":[0.295883,51.144966],"type":"Point"}
}