{
  "type": "Feature",
  "properties": {
    "iso:country":"GB",
    "sg:address":"15a Rossall Road",
    "sg:city":"Thornton-cleveleys",
    "sg:classifiers":[
        {
            "category":"Personal",
            "subcategory":"Beauty Salon",
            "type":"Services"
        }
    ],
    "sg:phone":"+44 1253 855707",
    "sg:postcode":"FY5 1AP",
    "sg:province":"Lancashire",
    "sg:tags":[
        "ladies",
        "lady",
        "hairdresser"
    ],
    "wof:name":"Strands Hair & Beauty",
    "wof:placetype":"venue"
},
  "geometry": {"coordinates":[-3.039985,53.878014],"type":"Point"}
}