{
  "type": "Feature",
  "properties": {
    "addr:full":"115 South East Road, Sholing Southampton Hampshire SO19 8JR",
    "addr:housenumber":"115",
    "addr:postcode":"so19 8jr",
    "addr:street":"South East Road",
    "iso:country":"GB",
    "sg:address":"115 South East Road, Sholing",
    "sg:city":"Southampton",
    "sg:classifiers":[
        {
            "category":"Professional",
            "subcategory":"Accounting & Tax Preparation",
            "type":"Services"
        }
    ],
    "sg:phone":"+44 23 8049 9300",
    "sg:postcode":"SO19 8JR",
    "sg:province":"Hampshire",
    "sg:tags":[
        "accountant"
    ],
    "wof:name":"G C A Taverns",
    "wof:placetype":"venue"
},
  "geometry": {"coordinates":[-1.356490016,50.9023551941],"type":"Point"}
}