{
  "type": "Feature",
  "properties": {
    "iso:country":"GB",
    "sg:address":"62 Sheridan Street",
    "sg:city":"Leicester",
    "sg:classifiers":[
        {
            "category":"Building & Trades",
            "subcategory":"Construction",
            "type":"Services"
        }
    ],
    "sg:phone":"+44 7850 109318",
    "sg:postcode":"LE2 7NG",
    "sg:province":"Leicestershire",
    "sg:tags":[
        "joiner",
        "carpenter"
    ],
    "wof:name":"A & J Joinery",
    "wof:placetype":"venue"
},
  "geometry": {"coordinates":[-1.132836,52.612289],"type":"Point"}
}