{
  "type": "Feature",
  "properties": {
    "iso:country":"GB",
    "sg:address":"Church Grn",
    "sg:city":"Wareham",
    "sg:classifiers":[
        {
            "category":"Travel",
            "subcategory":"Hotels & Motels",
            "type":"Entertainment"
        }
    ],
    "sg:phone":"+44 1929 551666",
    "sg:postcode":"BH20 4ND",
    "sg:province":"Dorset",
    "wof:name":"The Priory Hotel",
    "wof:placetype":"venue"
},
  "geometry": {"coordinates":[-2.108345,50.684284],"type":"Point"}
}