{
  "type": "Feature",
  "properties": {
    "addr:full":"5-9 Orchard Street Neath Neath Port Talbot SA11 1DS",
    "addr:housenumber":"5-9",
    "addr:postcode":"sa11 1ds",
    "addr:street":"Orchard Street",
    "iso:country":"GB",
    "sg:address":"5-9 Orchard Street",
    "sg:city":"Neath",
    "sg:classifiers":[
        {
            "category":"Shopping",
            "subcategory":"Department Store",
            "type":"Retail Goods"
        }
    ],
    "sg:phone":"+44 1639 643736",
    "sg:postcode":"SA11 1DS",
    "sg:province":"Neath Port Talbot",
    "wof:name":"Woolworths Plc",
    "wof:placetype":"venue"
},
  "geometry": {"coordinates":[-3.803561,51.66283],"type":"Point"}
}