{
  "type": "Feature",
  "properties": {
    "addr:full":"17 Islay Crescent Paisley East Renfrewshire PA2 8HD",
    "addr:housenumber":"17",
    "addr:postcode":"pa2 8hd",
    "addr:street":"Islay Crescent",
    "iso:country":"GB",
    "sg:address":"17 Islay Crescent",
    "sg:city":"Paisley",
    "sg:classifiers":[
        {
            "category":"Communications",
            "type":"Services"
        }
    ],
    "sg:phone":"+44 1505 816876",
    "sg:postcode":"PA2 8HD",
    "sg:province":"East Renfrewshire",
    "sg:tags":[
        "audio-visual"
    ],
    "wof:name":"Caledonia Vision",
    "wof:placetype":"venue"
},
  "geometry": {"coordinates":[-4.4286518097,55.8194999695],"type":"Point"}
}