{
  "type": "Feature",
  "properties": {
    "iso:country":"GB",
    "sg:address":"22 Poplar Avenue, New Mills",
    "sg:city":"High Peak",
    "sg:classifiers":[
        {
            "category":"Building & Trades",
            "subcategory":"Construction",
            "type":"Services"
        }
    ],
    "sg:postcode":"SK22 4HR",
    "sg:province":"Cheshire",
    "sg:tags":[
        "builder"
    ],
    "wof:name":"Green A R Groundwork & Building Contractors",
    "wof:placetype":"venue"
},
  "geometry": {"coordinates":[-1.988243,53.373058],"type":"Point"}
}