{
  "type": "Feature",
  "properties": {
    "iso:country":"GB",
    "sg:address":"182a Telegraph Road, Heswall",
    "sg:city":"Wirral",
    "sg:classifiers":[
        {
            "category":"Shopping",
            "subcategory":"Florist",
            "type":"Retail Goods"
        }
    ],
    "sg:phone":"+44 151 342 6563",
    "sg:postcode":"CH60 0AJ",
    "sg:province":"Merseyside",
    "wof:name":"Wirral Flowers Ltd",
    "wof:placetype":"venue"
},
  "geometry": {"coordinates":[-3.096517086,53.3275604248],"type":"Point"}
}