{
  "type": "Feature",
  "properties": {
    "addr:full":"7-9 Humphrey Street Swansea Neath Port Talbot SA1 6BG",
    "addr:housenumber":"7-9",
    "addr:postcode":"sa1 6bg",
    "addr:street":"Humphrey Street",
    "iso:country":"GB",
    "sg:address":"7-9 Humphrey Street",
    "sg:city":"Swansea",
    "sg:classifiers":[
        {
            "category":"Home & Garden",
            "subcategory":"Carpets & Floor Coverings",
            "type":"Retail Goods"
        }
    ],
    "sg:postcode":"SA1 6BG",
    "sg:province":"Neath Port Talbot",
    "sg:tags":[
        "carpets",
        "rug",
        "matting"
    ],
    "wof:name":"Carpet Selection Centre",
    "wof:placetype":"venue"
},
  "geometry": {"coordinates":[-3.954726,51.620529],"type":"Point"}
}