{
  "type": "Feature",
  "properties": {
    "addr:full":"144 London Road Brighton East Sussex BN1 4PH",
    "addr:housenumber":"144",
    "addr:postcode":"bn1 4ph",
    "addr:street":"London Road",
    "iso:country":"GB",
    "sg:address":"144 London Road",
    "sg:city":"Brighton",
    "sg:classifiers":[
        {
            "category":"Organizations",
            "subcategory":"Non-profit Organization",
            "type":"Services"
        }
    ],
    "sg:postcode":"BN1 4PH",
    "sg:province":"East Sussex",
    "sg:tags":[
        "organisation",
        "voluntary",
        "charity"
    ],
    "wof:name":"Mental Health Project for Homeless Project",
    "wof:placetype":"venue"
},
  "geometry": {"coordinates":[-0.1357389987,50.8296203613],"type":"Point"}
}