{
  "type": "Feature",
  "properties": {
    "iso:country":"GB",
    "sg:address":"Second Avenue, Pensnett Trading Estate",
    "sg:city":"Brierley Hill",
    "sg:classifiers":[
        {
            "category":"Bus Charters",
            "type":"Transportation"
        }
    ],
    "sg:phone":"+44 1384 277926",
    "sg:postcode":"DY6 7NA",
    "sg:province":"Staffordshire",
    "sg:tags":[
        "coach"
    ],
    "wof:name":"Travel Merry Hill",
    "wof:placetype":"venue"
},
  "geometry": {"coordinates":[-2.151539,52.505814],"type":"Point"}
}