{
  "type": "Feature",
  "properties": {
    "addr:full":"Kettering Road, Burton Latimer Kettering Northamptonshire NN15 5LP",
    "addr:postcode":"nn15 5lp",
    "addr:street":"Kettering Road",
    "iso:country":"GB",
    "sg:address":"Kettering Road, Burton Latimer",
    "sg:city":"Kettering",
    "sg:classifiers":[
        {
            "category":"Retail",
            "subcategory":"Auto Repair",
            "type":"Services"
        }
    ],
    "sg:postcode":"NN15 5LP",
    "sg:province":"Northamptonshire",
    "sg:tags":[
        "modification",
        "garage"
    ],
    "wof:name":"Drage Autos",
    "wof:placetype":"venue"
},
  "geometry": {"coordinates":[-0.6899039745,52.3654556274],"type":"Point"}
}