{
  "type": "Feature",
  "properties": {
    "iso:country":"GB",
    "sg:address":"183 Ashley Rd",
    "sg:city":"Altrincham",
    "sg:classifiers":[
        {
            "category":"Banks & Credit Unions",
            "subcategory":"Financial Services",
            "type":"Services"
        }
    ],
    "sg:phone":"+44 161 929 7004",
    "sg:postcode":"WA15 9SD",
    "sg:province":"Cheshire",
    "sg:tags":[
        "adviser"
    ],
    "wof:name":"Earthwork Financial Planning",
    "wof:placetype":"venue"
},
  "geometry": {"coordinates":[-2.345899,53.377247],"type":"Point"}
}