{
  "type": "Feature",
  "properties": {
    "addr:full":"Carrington Road, Moulton Seas End Spalding Cambridgeshire PE12 6LS",
    "addr:postcode":"pe12 6ls",
    "addr:street":"Carrington Road;Spalding",
    "iso:country":"GB",
    "sg:address":"Carrington Road, Moulton Seas End",
    "sg:city":"Spalding",
    "sg:classifiers":[
        {
            "category":"Home & Garden",
            "subcategory":"Garden Supply",
            "type":"Retail Goods"
        },
        {
            "category":"Farming",
            "subcategory":"Livestock Farm",
            "type":"Manufacturing & Wholesale Goods"
        }
    ],
    "sg:postcode":"PE12 6LS",
    "sg:province":"Cambridgeshire",
    "sg:tags":[
        "bulb",
        "grower",
        "others"
    ],
    "wof:name":"Michael J Congreve",
    "wof:placetype":"venue"
},
  "geometry": {"coordinates":[-0.058479,52.836933],"type":"Point"}
}