{
  "type": "Feature",
  "properties": {
    "addr:full":"17 The Bramley Business Centre, Bramley Guildford Surrey GU5 0AZ",
    "addr:housenumber":"17;bramley business centre",
    "addr:postcode":"gu5 0az",
    "addr:street":"The;Bramley",
    "iso:country":"GB",
    "sg:address":"17 The Bramley Business Centre, Bramley",
    "sg:city":"Guildford",
    "sg:classifiers":[
        {
            "category":"Professional",
            "type":"Services"
        }
    ],
    "sg:phone":"+44 1483 892440",
    "sg:postcode":"GU5 0AZ",
    "sg:province":"Surrey",
    "sg:tags":[
        "repair",
        "tech",
        "maintenance"
    ],
    "wof:name":"Steve & Nancy Hales",
    "wof:placetype":"venue"
},
  "geometry": {"coordinates":[-0.558077,51.194248],"type":"Point"}
}