{
  "type": "Feature",
  "properties": {
    "addr:full":"Lea Cottage, Tissington Ashbourne Derbyshire DE6 1RD",
    "addr:postcode":"de6 1rd",
    "iso:country":"GB",
    "sg:address":"Lea Cottage, Tissington",
    "sg:city":"Ashbourne",
    "sg:classifiers":[
        {
            "category":"Banks & Credit Unions",
            "subcategory":"Investment Brokerage",
            "type":"Services"
        }
    ],
    "sg:phone":"+44 1335 390222",
    "sg:postcode":"DE6 1RD",
    "sg:province":"Derbyshire",
    "sg:tags":[
        "contractor"
    ],
    "wof:name":"I B Naylor & Sons",
    "wof:placetype":"venue"
},
  "geometry": {"coordinates":[-1.7325639725,53.0182800293],"type":"Point"}
}