{
  "type": "Feature",
  "properties": {
    "iso:country":"GB",
    "sg:address":"2 High Street, Winslow",
    "sg:city":"Buckingham",
    "sg:classifiers":[
        {
            "category":"Deli",
            "type":"Food & Drink"
        }
    ],
    "sg:phone":"+44 1296 712159",
    "sg:postcode":"MK18 3HF",
    "sg:province":"Buckinghamshire",
    "sg:tags":[
        "delicatessen"
    ],
    "wof:name":"Winslow Delicatessen",
    "wof:placetype":"venue"
},
  "geometry": {"coordinates":[-0.8766980171,51.8986778259],"type":"Point"}
}