{
  "type": "Feature",
  "properties": {
    "addr:full":"Auto House, Commercial Road, Pontllanfraith Blackwood Caerphilly NP12 2JG",
    "addr:postcode":"np12 2jg",
    "addr:street":"Commercial Road",
    "iso:country":"GB",
    "sg:address":"Auto House, Commercial Road, Pontllanfraith",
    "sg:city":"Blackwood",
    "sg:classifiers":[
        {
            "category":"Retail",
            "subcategory":"Auto Repair",
            "type":"Services"
        }
    ],
    "sg:phone":"+44 1495 224074",
    "sg:postcode":"NP12 2JG",
    "sg:province":"Caerphilly",
    "sg:tags":[
        "body",
        "car"
    ],
    "wof:name":"Autobond (Blackwood) Ltd.",
    "wof:placetype":"venue"
},
  "geometry": {"coordinates":[-3.187312,51.655807],"type":"Point"}
}