{
  "type": "Feature",
  "properties": {
    "iso:country":"GB",
    "sg:address":"100 High Street",
    "sg:city":"Crediton",
    "sg:classifiers":[
        {
            "category":"Shopping",
            "subcategory":"Pharmacy",
            "type":"Retail Goods"
        }
    ],
    "sg:postcode":"EX17 3LF",
    "sg:province":"Devon",
    "sg:tags":[
        "medicine",
        "therapy"
    ],
    "wof:name":"Philip Deem",
    "wof:placetype":"venue"
},
  "geometry": {"coordinates":[-3.661757,50.791],"type":"Point"}
}