{
  "type": "Feature",
  "properties": {
    "iso:country":"GB",
    "sg:address":"9 Beckenham Road",
    "sg:city":"West Wickham",
    "sg:classifiers":[
        {
            "category":"Food & Beverages",
            "subcategory":"Specialty",
            "type":"Retail Goods"
        }
    ],
    "sg:phone":"+44 20 8777 8721",
    "sg:postcode":"BR4 0QR",
    "sg:province":"Kent",
    "sg:tags":[
        "product",
        "health"
    ],
    "wof:name":"J & B Health Foods",
    "wof:placetype":"venue"
},
  "geometry": {"coordinates":[-0.0152869998,51.3800735474],"type":"Point"}
}