{
  "type": "Feature",
  "properties": {
    "addr:full":"117-119 Masons Hill Bromley Kent BR2 9HT",
    "addr:housenumber":"117-119",
    "addr:postcode":"br2 9ht",
    "addr:street":"Masons Hill",
    "iso:country":"GB",
    "sg:address":"117-119 Masons Hill",
    "sg:city":"Bromley",
    "sg:classifiers":[
        {
            "category":"Manufacturing",
            "subcategory":"Building Materials",
            "type":"Manufacturing & Wholesale Goods"
        }
    ],
    "sg:phone":"+44 20 8464 2126",
    "sg:postcode":"BR2 9HT",
    "sg:province":"Kent",
    "sg:tags":[
        "merchant",
        "builder"
    ],
    "wof:name":"B G C Supplies",
    "wof:placetype":"venue"
},
  "geometry": {"coordinates":[0.023147,51.397102],"type":"Point"}
}