{
  "type": "Feature",
  "properties": {
    "iso:country":"GB",
    "sg:address":"188 Ladypool Road",
    "sg:city":"Birmingham",
    "sg:classifiers":[
        {
            "category":"Banks & Credit Unions",
            "subcategory":"Financial Services",
            "type":"Services"
        }
    ],
    "sg:phone":"+44 121 772 0105",
    "sg:postcode":"B12 8JS",
    "sg:province":"West Midlands",
    "sg:tags":[
        "consultant"
    ],
    "wof:name":"Crystal International",
    "wof:placetype":"venue"
},
  "geometry": {"coordinates":[-1.876346,52.457207],"type":"Point"}
}