{
  "type": "Feature",
  "properties": {
    "iso:country":"GB",
    "sg:address":"Buxton Mill, Buxton",
    "sg:city":"Norwich",
    "sg:classifiers":[
        {
            "category":"Bars & Pubs",
            "type":"Food & Drink"
        }
    ],
    "sg:postcode":"NR10 5JF",
    "sg:province":"Norfolk",
    "sg:tags":[
        "pubs",
        "inn"
    ],
    "wof:name":"Buxton Mill Tavern",
    "wof:placetype":"venue"
},
  "geometry": {"coordinates":[1.3076980114,52.755531311],"type":"Point"}
}