{
  "type": "Feature",
  "properties": {
    "addr:full":"7 Noel Road London Greater London N1 8HQ",
    "addr:housenumber":"7",
    "addr:postcode":"n1 8hq",
    "addr:street":"Noel Road",
    "iso:country":"GB",
    "sg:address":"7 Noel Road",
    "sg:city":"London",
    "sg:classifiers":[
        {
            "category":"Building & Trades",
            "subcategory":"Construction",
            "type":"Services"
        }
    ],
    "sg:phone":"+44 20 7226 0252",
    "sg:postcode":"N1 8HQ",
    "sg:province":"Greater London",
    "sg:tags":[
        "builder"
    ],
    "wof:name":"Frank Carling",
    "wof:placetype":"venue"
},
  "geometry": {"coordinates":[-0.102365002,51.5337295532],"type":"Point"}
}