{
  "type": "Feature",
  "properties": {
    "iso:country":"GB",
    "sg:address":"107 Planks Lane, Wombourne",
    "sg:city":"Wolverhampton",
    "sg:classifiers":[
        {
            "category":"Professional",
            "subcategory":"Accounting & Tax Preparation",
            "type":"Services"
        }
    ],
    "sg:postcode":"WV5 8EB",
    "sg:province":"Shropshire",
    "sg:tags":[
        "accountant"
    ],
    "wof:name":"M D R Henley & Co",
    "wof:placetype":"venue"
},
  "geometry": {"coordinates":[-2.199703,52.531952],"type":"Point"}
}