{
  "type": "Feature",
  "properties": {
    "addr:full":"343 Prince Regents Lane London Greater London E16 3JL",
    "addr:housenumber":"343",
    "addr:postcode":"e16 3jl",
    "addr:street":"Prince Regents Lane",
    "iso:country":"GB",
    "sg:address":"343 Prince Regents Lane",
    "sg:city":"London",
    "sg:classifiers":[
        {
            "category":"Health Services",
            "subcategory":"Doctor",
            "type":"Services"
        }
    ],
    "sg:phone":"+44 20 7511 2980",
    "sg:postcode":"E16 3JL",
    "sg:province":"Greater London",
    "sg:tags":[
        "practitioners"
    ],
    "wof:name":"Tun Lwin",
    "wof:placetype":"venue"
},
  "geometry": {"coordinates":[0.03184,51.51466],"type":"Point"}
}