{
  "type": "Feature",
  "properties": {
    "addr:full":"98 Long Row, Horsforth Leeds West Yorkshire LS18 5AT",
    "addr:housenumber":"98",
    "addr:postcode":"ls18 5at",
    "addr:street":"Long Row",
    "iso:country":"GB",
    "sg:address":"98 Long Row, Horsforth",
    "sg:city":"Leeds",
    "sg:classifiers":[
        {
            "category":"Building & Trades",
            "subcategory":"Construction",
            "type":"Services"
        }
    ],
    "sg:phone":"+44 113 258 3881",
    "sg:postcode":"LS18 5AT",
    "sg:province":"West Yorkshire",
    "sg:tags":[
        "builder"
    ],
    "wof:name":"John M Sykes & Sons",
    "wof:placetype":"venue"
},
  "geometry": {"coordinates":[-1.6335560083,53.8446617126],"type":"Point"}
}