{
  "type": "Feature",
  "properties": {
    "addr:full":"25 Ridgeway Clo Heathfield East Sussex TN21 8NS",
    "addr:housenumber":"25;clo",
    "addr:postcode":"tn21 8ns",
    "addr:street":"Ridgeway",
    "iso:country":"GB",
    "sg:address":"25 Ridgeway Clo",
    "sg:city":"Heathfield",
    "sg:classifiers":[
        {
            "category":"Military Area",
            "subcategory":"Air Force Base",
            "type":"Public Place"
        }
    ],
    "sg:postcode":"TN21 8NS",
    "sg:province":"East Sussex",
    "sg:tags":[
        "taxi",
        "hire",
        "private"
    ],
    "wof:name":"Cronk,Alan,",
    "wof:placetype":"venue"
},
  "geometry": {"coordinates":[0.258124,50.974522],"type":"Point"}
}