{
  "type": "Feature",
  "properties": {
    "addr:full":"1073 Wimborne Road Bournemouth Dorset BH9 2BY",
    "addr:housenumber":"1073",
    "addr:postcode":"bh9 2by",
    "addr:street":"Wimborne Road",
    "iso:country":"GB",
    "sg:address":"1073 Wimborne Road",
    "sg:city":"Bournemouth",
    "sg:classifiers":[
        {
            "category":"Building & Trades",
            "subcategory":"Plumbing",
            "type":"Services"
        }
    ],
    "sg:phone":"+44 1202 530004",
    "sg:postcode":"BH9 2BY",
    "sg:province":"Dorset",
    "sg:tags":[
        "merchant",
        "plumbers'"
    ],
    "wof:name":"G & B Plumbing Supplies",
    "wof:placetype":"venue"
},
  "geometry": {"coordinates":[-1.8722920418,50.7579307556],"type":"Point"}
}