{
  "type": "Feature",
  "properties": {
    "iso:country":"GB",
    "sg:address":"Crown House, 18 Queens Rd",
    "sg:city":"Walton On Thames",
    "sg:classifiers":[
        {
            "category":"Organizations",
            "subcategory":"Non-profit Organization",
            "type":"Services"
        },
        {
            "category":"Organizations",
            "subcategory":"Professional Association",
            "type":"Services"
        }
    ],
    "sg:phone":"+44 1932 231330",
    "sg:postcode":"KT12 5LR",
    "sg:province":"Surrey",
    "sg:tags":[
        "organisation",
        "dyslexia",
        "advice",
        "charity",
        "support",
        "voluntary"
    ],
    "wof:name":"KT Learning Centre",
    "wof:placetype":"venue"
},
  "geometry": {"coordinates":[-0.4035559893,51.3665466309],"type":"Point"}
}