{
  "type": "Feature",
  "properties": {
    "addr:full":"13 South Molton Street London Greater London W1K 5QW",
    "addr:housenumber":"13",
    "addr:postcode":"w1k 5qw",
    "addr:street":"South Molton Street",
    "iso:country":"GB",
    "sg:address":"13 South Molton Street",
    "sg:city":"London",
    "sg:classifiers":[
        {
            "category":"Shopping",
            "subcategory":"Clothing, Apparel, & Fashions",
            "type":"Retail Goods"
        }
    ],
    "sg:phone":"+44 20 7499 7178",
    "sg:postcode":"W1K 5QW",
    "sg:province":"Greater London",
    "sg:tags":[
        "clothing",
        "ladieswear"
    ],
    "wof:name":"Antonio D'Errico (U K) Ltd.",
    "wof:placetype":"venue"
},
  "geometry": {"coordinates":[-0.14789,51.513538],"type":"Point"}
}