{
  "type": "Feature",
  "properties": {
    "addr:full":"15 Pulborough Road London Greater London SW18 5UN",
    "addr:housenumber":"15",
    "addr:postcode":"sw18 5un",
    "addr:street":"Pulborough Road",
    "iso:country":"GB",
    "sg:address":"15 Pulborough Road",
    "sg:city":"London",
    "sg:classifiers":[
        {
            "category":"Shopping",
            "subcategory":"Antiques",
            "type":"Retail Goods"
        }
    ],
    "sg:phone":"+44 20 8874 0762",
    "sg:postcode":"SW18 5UN",
    "sg:province":"Greater London",
    "wof:name":"Compton Street Ltd.",
    "wof:placetype":"venue"
},
  "geometry": {"coordinates":[-0.2064390033,51.4496765137],"type":"Point"}
}