{
  "type": "Feature",
  "properties": {
    "iso:country":"GB",
    "sg:address":"10 Court Road",
    "sg:city":"Bridgend",
    "sg:classifiers":[
        {
            "category":"Professional",
            "subcategory":"Management & Consulting",
            "type":"Services"
        }
    ],
    "sg:phone":"+44 1656 663090",
    "sg:postcode":"CF31 1BN",
    "sg:province":"Bridgend",
    "sg:tags":[
        "consultant",
        "business"
    ],
    "wof:name":"C D I",
    "wof:placetype":"venue"
},
  "geometry": {"coordinates":[-3.5759510994,51.5066070557],"type":"Point"}
}