{
  "type": "Feature",
  "properties": {
    "addr:full":"3 Parkside Road Paignton Devon TQ4 6AE",
    "addr:housenumber":"3",
    "addr:postcode":"tq4 6ae",
    "addr:street":"Parkside Road",
    "iso:country":"GB",
    "sg:address":"3 Parkside Road",
    "sg:city":"Paignton",
    "sg:classifiers":[
        {
            "category":"Food & Beverages",
            "subcategory":"Meat & Fish",
            "type":"Retail Goods"
        }
    ],
    "sg:phone":"+44 1803 559729",
    "sg:postcode":"TQ4 6AE",
    "sg:province":"Devon",
    "sg:tags":[
        "butcher"
    ],
    "wof:name":"Parkside Butchers",
    "wof:placetype":"venue"
},
  "geometry": {"coordinates":[-3.564385891,50.435459137],"type":"Point"}
}