{
  "type": "Feature",
  "properties": {
    "iso:country":"GB",
    "sg:address":"Vintage Corner, Old Cambridge R, Puckeridge",
    "sg:city":"Ware",
    "sg:classifiers":[
        {
            "category":"Travel",
            "subcategory":"Hotels & Motels",
            "type":"Entertainment"
        }
    ],
    "sg:phone":"+44 1920 822722",
    "sg:postcode":"SG11 1SA",
    "sg:province":"Hertfordshire",
    "wof:name":"St.Ouen Hotels Ltd.",
    "wof:placetype":"venue"
},
  "geometry": {"coordinates":[0.014141,51.890293],"type":"Point"}
}