{
  "type": "Feature",
  "properties": {
    "addr:full":"Galon Uchaf Road Merthyr Tydfil Merthyr Tydfil CF47 9TP",
    "addr:postcode":"cf47 9tp",
    "addr:street":"Uchaf Road",
    "iso:country":"GB",
    "sg:address":"Galon Uchaf Road",
    "sg:city":"Merthyr Tydfil",
    "sg:classifiers":[
        {
            "category":"Food & Beverages",
            "subcategory":"Groceries & Convenience Stores",
            "type":"Retail Goods"
        },
        {
            "category":"Shopping",
            "subcategory":"Used Merchandise",
            "type":"Retail Goods"
        }
    ],
    "sg:phone":"+44 1685 723011",
    "sg:postcode":"CF47 9TP",
    "sg:province":"Merthyr Tydfil",
    "sg:tags":[
        "shop",
        "second-hand"
    ],
    "wof:name":"The Trading Post",
    "wof:placetype":"venue"
},
  "geometry": {"coordinates":[-3.3706789017,51.7659378052],"type":"Point"}
}