{
  "type": "Feature",
  "properties": {
    "iso:country":"GB",
    "sg:address":"4c Palmston Business Centre, Palmerston",
    "sg:city":"Barry",
    "sg:classifiers":[
        {
            "category":"Government",
            "subcategory":"Fire Station",
            "type":"Public Place"
        }
    ],
    "sg:phone":"+44 1446 700123",
    "sg:postcode":"CF63 2XA",
    "sg:province":"The Vale of Glamorgan",
    "sg:tags":[
        "w'sale",
        "lighting"
    ],
    "wof:name":"Day-Light Distributors Ltd.",
    "wof:placetype":"venue"
},
  "geometry": {"coordinates":[-3.2434699535,51.4140815735],"type":"Point"}
}