{
  "type": "Feature",
  "properties": {
    "addr:full":"7 Ingram Street Glasgow Glasgow City G1 1HA",
    "addr:housenumber":"7",
    "addr:postcode":"g1 1ha",
    "addr:street":"Ingram Street",
    "iso:country":"GB",
    "sg:address":"7 Ingram Street",
    "sg:city":"Glasgow",
    "sg:classifiers":[
        {
            "category":"Professional",
            "subcategory":"Detective & Security Services",
            "type":"Services"
        }
    ],
    "sg:phone":"+44 141 552 7523",
    "sg:postcode":"G1 1HA",
    "sg:province":"Glasgow City",
    "sg:tags":[
        "agency"
    ],
    "wof:name":"CITY INVESTIGATIONS",
    "wof:placetype":"venue"
},
  "geometry": {"coordinates":[-4.241615,55.858986],"type":"Point"}
}