{
  "type": "Feature",
  "properties": {
    "addr:full":"Wham Lane, Whitestake, New Longton Preston Lancashire PR4 4JS",
    "addr:postcode":"pr4 4js",
    "addr:street":"Wham Lane",
    "iso:country":"GB",
    "sg:address":"Wham Lane, Whitestake, New Longton",
    "sg:city":"Preston",
    "sg:classifiers":[
        {
            "category":"Restaurant",
            "type":"Food & Drink"
        }
    ],
    "sg:phone":"+44 1772 613210",
    "sg:postcode":"PR4 4JS",
    "sg:province":"Lancashire",
    "wof:name":"The Farmers Arms",
    "wof:placetype":"venue"
},
  "geometry": {"coordinates":[-2.7632169724,53.7076072693],"type":"Point"}
}