{
  "type": "Feature",
  "properties": {
    "iso:country":"GB",
    "sg:address":"The Green, Bagnall",
    "sg:city":"Stoke-on-trent",
    "sg:classifiers":[
        {
            "category":"Government",
            "subcategory":"Post Office",
            "type":"Public Place"
        }
    ],
    "sg:postcode":"ST9 9JR",
    "sg:province":"Staffordshire",
    "wof:name":"Bagnall Sub Post Office",
    "wof:placetype":"venue"
},
  "geometry": {"coordinates":[-2.135719,53.060829],"type":"Point"}
}