{
  "type": "Feature",
  "properties": {
    "addr:full":"Crazy Corner, 2 Coombe Rd Sheffield South Yorkshire S10 1FF",
    "addr:housenumber":"2",
    "addr:postcode":"s10 1ff",
    "addr:street":"Coombe Rd",
    "iso:country":"GB",
    "sg:address":"Crazy Corner, 2 Coombe Rd",
    "sg:city":"Sheffield",
    "sg:classifiers":[
        {
            "category":"Professional",
            "type":"Services"
        }
    ],
    "sg:phone":"+44 114 268 4824",
    "sg:postcode":"S10 1FF",
    "sg:province":"South Yorkshire",
    "sg:tags":[
        "entertainer"
    ],
    "wof:name":"Manic Manipulation",
    "wof:placetype":"venue"
},
  "geometry": {"coordinates":[-1.464544,53.38311],"type":"Point"}
}