{
  "type": "Feature",
  "properties": {
    "addr:full":"41 Englands Lane London Greater London NW3 4YD",
    "addr:housenumber":"41",
    "addr:postcode":"nw3 4yd",
    "addr:street":"Englands Lane",
    "iso:country":"GB",
    "sg:address":"41 Englands Lane",
    "sg:city":"London",
    "sg:classifiers":[
        {
            "category":"Shopping",
            "subcategory":"Florist",
            "type":"Retail Goods"
        }
    ],
    "sg:phone":"+44 20 7722 3929",
    "sg:postcode":"NW3 4YD",
    "sg:province":"Greater London",
    "wof:name":"Aurora Flower Shop",
    "wof:placetype":"venue"
},
  "geometry": {"coordinates":[-0.16209,51.545753],"type":"Point"}
}