{
  "type": "Feature",
  "properties": {
    "addr:full":"Gleave Wood, Farm Road, Weaverham Northwich Cheshire CW8 3NT",
    "addr:postcode":"cw8 3nt",
    "addr:street":"Farm Road",
    "iso:country":"GB",
    "sg:address":"Gleave Wood, Farm Road, Weaverham",
    "sg:city":"Northwich",
    "sg:classifiers":[
        {
            "category":"Social Services",
            "subcategory":"Retirement Home",
            "type":"Services"
        }
    ],
    "sg:phone":"+44 1606 853395",
    "sg:postcode":"CW8 3NT",
    "sg:province":"Cheshire",
    "sg:tags":[
        "residential",
        "care"
    ],
    "wof:name":"C L S Care Services",
    "wof:placetype":"venue"
},
  "geometry": {"coordinates":[-2.574792,53.260963],"type":"Point"}
}