{
  "type": "Feature",
  "properties": {
    "addr:full":"39 Chobham Road Woking Surrey GU21 6JD",
    "addr:housenumber":"39",
    "addr:postcode":"gu21 6jd",
    "addr:street":"Chobham Road",
    "iso:country":"GB",
    "sg:address":"39 Chobham Road",
    "sg:city":"Woking",
    "sg:classifiers":[
        {
            "category":"Communications",
            "subcategory":"Film & Video Production",
            "type":"Services"
        }
    ],
    "sg:phone":"+44 1473 721701",
    "sg:postcode":"GU21 6JD",
    "sg:province":"Surrey",
    "sg:tags":[
        "hot",
        "stamping",
        "foil"
    ],
    "wof:name":"W Vinter (1956) Ltd.",
    "wof:placetype":"venue"
},
  "geometry": {"coordinates":[-0.557771,51.321129],"type":"Point"}
}