{
  "type": "Feature",
  "properties": {
    "addr:full":"Unit 2 Lansdowne Workshops, Lansdowne Mews London Greater London SE7 8AZ",
    "addr:housenumber":"unit 2;workshops",
    "addr:postcode":"se7 8az",
    "addr:street":"Lansdowne Mews",
    "iso:country":"GB",
    "sg:address":"Unit 2 Lansdowne Workshops, Lansdowne Mews",
    "sg:city":"London",
    "sg:classifiers":[
        {
            "category":"Bakery",
            "type":"Food & Drink"
        }
    ],
    "sg:phone":"+44 20 8293 3913",
    "sg:postcode":"SE7 8AZ",
    "sg:province":"Greater London",
    "sg:tags":[
        "cake",
        "maker"
    ],
    "wof:name":"Village Cakecraft",
    "wof:placetype":"venue"
},
  "geometry": {"coordinates":[0.038895,51.485004],"type":"Point"}
}