{
  "type": "Feature",
  "properties": {
    "addr:full":"29 Orchard Way York North Yorkshire YO24 2NY",
    "addr:housenumber":"29",
    "addr:postcode":"yo24 2ny",
    "addr:street":"Orchard Way",
    "iso:country":"GB",
    "sg:address":"29 Orchard Way",
    "sg:city":"York",
    "sg:classifiers":[
        {
            "category":"Banks & Credit Unions",
            "subcategory":"Bank",
            "type":"Services"
        }
    ],
    "sg:phone":"+44 1904 706300",
    "sg:postcode":"YO24 2NY",
    "sg:province":"North Yorkshire",
    "sg:tags":[
        "stocktaking",
        "inventory"
    ],
    "wof:name":"Hebbies Wholesale",
    "wof:placetype":"venue"
},
  "geometry": {"coordinates":[-1.115184,53.943943],"type":"Point"}
}