{
  "type": "Feature",
  "properties": {
    "addr:full":"10 Birmingham Road Sutton Coldfield West Midlands B72 1QG",
    "addr:housenumber":"10",
    "addr:postcode":"b72 1qg",
    "addr:street":"Birmingham Road",
    "iso:country":"GB",
    "sg:address":"10 Birmingham Road",
    "sg:city":"Sutton Coldfield",
    "sg:classifiers":[
        {
            "category":"Personal",
            "type":"Services"
        }
    ],
    "sg:phone":"+44 121 354 6292",
    "sg:postcode":"B72 1QG",
    "sg:province":"West Midlands",
    "sg:tags":[
        "wedding"
    ],
    "wof:name":"Red Rose Designs",
    "wof:placetype":"venue"
},
  "geometry": {"coordinates":[-1.826575,52.559196],"type":"Point"}
}