{
  "type": "Feature",
  "properties": {
    "iso:country":"GB",
    "sg:address":"5 Marlowe Rd, Barnby Dun",
    "sg:city":"Doncaster",
    "sg:classifiers":[
        {
            "category":"Food & Beverages",
            "subcategory":"Meat & Fish",
            "type":"Retail Goods"
        }
    ],
    "sg:phone":"+44 1302 881886",
    "sg:postcode":"DN3 1AU",
    "sg:province":"South Yorkshire",
    "sg:tags":[
        "chip"
    ],
    "wof:name":"Peter's Crispy Cod",
    "wof:placetype":"venue"
},
  "geometry": {"coordinates":[-1.069039,53.578609],"type":"Point"}
}