{
  "type": "Feature",
  "properties": {
    "addr:full":"5 Market Square, Tremadog Porthmadog Gwynedd LL49 9RB",
    "addr:housenumber":"5",
    "addr:postcode":"ll49 9rb",
    "addr:street":"Market Square Tremadog Porthmadog",
    "iso:country":"GB",
    "sg:address":"5 Market Square, Tremadog",
    "sg:city":"Porthmadog",
    "sg:classifiers":[
        {
            "category":"Bars & Pubs",
            "type":"Food & Drink"
        }
    ],
    "sg:phone":"+44 1766 512421",
    "sg:postcode":"LL49 9RB",
    "sg:province":"Gwynedd",
    "sg:tags":[
        "pubs",
        "inn"
    ],
    "wof:name":"Golden Fleece Inn",
    "wof:placetype":"venue"
},
  "geometry": {"coordinates":[-4.14146,52.939472],"type":"Point"}
}