{
  "type": "Feature",
  "properties": {
    "iso:country":"GB",
    "sg:address":"4 Victoria Mount",
    "sg:city":"Prenton",
    "sg:classifiers":[
        {
            "category":"Building & Trades",
            "subcategory":"Construction",
            "type":"Services"
        }
    ],
    "sg:phone":"+44 151 652 1741",
    "sg:postcode":"CH43 5TH",
    "sg:province":"Merseyside",
    "sg:tags":[
        "builder"
    ],
    "wof:name":"N Blakemore",
    "wof:placetype":"venue"
},
  "geometry": {"coordinates":[-3.0421,53.381451],"type":"Point"}
}