{
  "type": "Feature",
  "properties": {
    "iso:country":"GB",
    "sg:address":"53 Marple Road",
    "sg:city":"Stockport",
    "sg:classifiers":[
        {
            "category":"Building & Trades",
            "subcategory":"Construction",
            "type":"Services"
        }
    ],
    "sg:phone":"+44 161 483 4086",
    "sg:postcode":"SK2 5EL",
    "sg:province":"Cheshire",
    "sg:tags":[
        "dry",
        "lining",
        "plasterers",
        "screeders"
    ],
    "wof:name":"H A Melville (Plasterers) Ltd.",
    "wof:placetype":"venue"
},
  "geometry": {"coordinates":[-2.12603,53.399883],"type":"Point"}
}