{
  "type": "Feature",
  "properties": {
    "addr:full":"Murmur Yr Afon Dyffryn Ardudwy Gwynedd LL44 2BE",
    "addr:postcode":"ll44 2be",
    "addr:street":"Yr Afon;Ardudwy",
    "iso:country":"GB",
    "sg:address":"Murmur Yr Afon",
    "sg:city":"Dyffryn Ardudwy",
    "sg:classifiers":[
        {
            "category":"Recreation",
            "subcategory":"Campground",
            "type":"Entertainment"
        }
    ],
    "sg:phone":"+44 1341 247827",
    "sg:postcode":"LL44 2BE",
    "sg:province":"Gwynedd",
    "sg:tags":[
        "caravan",
        "park"
    ],
    "wof:name":"Nicholas Edward & Meirwen Mills",
    "wof:placetype":"venue"
},
  "geometry": {"coordinates":[-4.0967340469,52.7872810364],"type":"Point"}
}