{
  "type": "Feature",
  "properties": {
    "addr:full":"40 Rosebery Avenue London Greater London EC1R 4RX",
    "addr:housenumber":"40",
    "addr:postcode":"ec1r 4rx",
    "addr:street":"Rosebery Avenue",
    "iso:country":"GB",
    "sg:address":"40 Rosebery Avenue",
    "sg:city":"London",
    "sg:classifiers":[
        {
            "category":"Professional",
            "subcategory":"Employment Agencies",
            "type":"Services"
        }
    ],
    "sg:phone":"+44 20 7833 0770",
    "sg:postcode":"EC1R 4RX",
    "sg:province":"Greater London",
    "sg:tags":[
        "consultant"
    ],
    "wof:name":"C R Charity Recruitment",
    "wof:placetype":"venue"
},
  "geometry": {"coordinates":[-0.110891,51.524433],"type":"Point"}
}