{
  "type": "Feature",
  "properties": {
    "addr:full":"126 Rydal Cres Greenford Greater London UB6 8EQ",
    "addr:housenumber":"126",
    "addr:postcode":"ub6 8eq",
    "addr:street":"Rydal Cres",
    "iso:country":"GB",
    "sg:address":"126 Rydal Cres",
    "sg:city":"Greenford",
    "sg:classifiers":[
        {
            "category":"Building & Trades",
            "subcategory":"Construction",
            "type":"Services"
        }
    ],
    "sg:phone":"+44 20 8991 5937",
    "sg:postcode":"UB6 8EQ",
    "sg:province":"Greater London",
    "sg:tags":[
        "joiner",
        "carpenter"
    ],
    "wof:name":"J Flynn",
    "wof:placetype":"venue"
},
  "geometry": {"coordinates":[-0.312365,51.533295],"type":"Point"}
}