{
  "type": "Feature",
  "properties": {
    "addr:full":"The Royal Victoria Hospital, Radnor Park Avenue Folkestone Kent CT19 5BN",
    "addr:postcode":"ct19 5bn",
    "addr:street":"Park Avenue",
    "iso:country":"GB",
    "sg:address":"The Royal Victoria Hospital, Radnor Park Avenue",
    "sg:city":"Folkestone",
    "sg:classifiers":[
        {
            "category":"Professional",
            "subcategory":"Lawyer & Legal Services",
            "type":"Services"
        }
    ],
    "sg:phone":"+44 1303 854435",
    "sg:postcode":"CT19 5BN",
    "sg:province":"Kent",
    "sg:tags":[
        "advice",
        "counselling"
    ],
    "wof:name":"The Stroke Association",
    "wof:placetype":"venue"
},
  "geometry": {"coordinates":[1.17097,51.083359],"type":"Point"}
}