{
  "type": "Feature",
  "properties": {
    "addr:full":"38 Mildmay Road Burnham-on-crouch Essex CM0 8ED",
    "addr:housenumber":"38",
    "addr:postcode":"cm0 8ed",
    "addr:street":"Mildmay Road",
    "iso:country":"GB",
    "sg:address":"38 Mildmay Road",
    "sg:city":"Burnham-on-crouch",
    "sg:classifiers":[
        {
            "category":"Building & Trades",
            "subcategory":"Construction",
            "type":"Services"
        }
    ],
    "sg:phone":"+44 1621 783638",
    "sg:postcode":"CM0 8ED",
    "sg:province":"Essex",
    "sg:tags":[
        "builder"
    ],
    "wof:name":"Wheeler Builders",
    "wof:placetype":"venue"
},
  "geometry": {"coordinates":[0.819497,51.630966],"type":"Point"}
}