{
  "type": "Feature",
  "properties": {
    "addr:full":"2-3 Market Street Loughborough Leicestershire LE11 3EP",
    "addr:housenumber":"2-3",
    "addr:postcode":"le11 3ep",
    "addr:street":"Market Street",
    "iso:country":"GB",
    "sg:address":"2-3 Market Street",
    "sg:city":"Loughborough",
    "sg:classifiers":[
        {
            "category":"Shopping",
            "subcategory":"Clothing, Apparel, & Fashions",
            "type":"Retail Goods"
        },
        {
            "category":"Shopping",
            "subcategory":"Baby Store",
            "type":"Retail Goods"
        }
    ],
    "sg:phone":"+44 1509 218716",
    "sg:postcode":"LE11 3EP",
    "sg:province":"Leicestershire",
    "sg:tags":[
        "child",
        "childrens",
        "babywear"
    ],
    "wof:name":"Adams Childrenswear Ltd.",
    "wof:placetype":"venue"
},
  "geometry": {"coordinates":[-1.207356,52.771046],"type":"Point"}
}