{
  "type": "Feature",
  "properties": {
    "addr:full":"Unit 5 White St Newcastle Upon Tyne Tyne and Wear NE6 3PJ",
    "addr:housenumber":"unit 5",
    "addr:postcode":"ne6 3pj",
    "addr:street":"White St",
    "iso:country":"GB",
    "sg:address":"Unit 5 White St",
    "sg:city":"Newcastle Upon Tyne",
    "sg:classifiers":[
        {
            "category":"Home & Garden",
            "subcategory":"Furniture",
            "type":"Retail Goods"
        }
    ],
    "sg:phone":"+44 191 262 6488",
    "sg:postcode":"NE6 3PJ",
    "sg:province":"Tyne and Wear",
    "wof:name":"Ashgrove Upholstery",
    "wof:placetype":"venue"
},
  "geometry": {"coordinates":[-1.5387350321,54.9739685059],"type":"Point"}
}