{
  "type": "Feature",
  "properties": {
    "iso:country":"GB",
    "sg:address":"415 Pensby Road",
    "sg:city":"Wirral",
    "sg:classifiers":[
        {
            "category":"Food & Beverages",
            "subcategory":"Supermarket",
            "type":"Retail Goods"
        }
    ],
    "sg:phone":"+44 151 648 2110",
    "sg:postcode":"CH61 9PF",
    "sg:province":"Merseyside",
    "wof:name":"Co-Operative",
    "wof:placetype":"venue"
},
  "geometry": {"coordinates":[-3.095529,53.34959],"type":"Point"}
}