{
  "type": "Feature",
  "properties": {
    "addr:full":"415 Pensby Road Wirral Merseyside CH61 9PF",
    "addr:housenumber":"415",
    "addr:postcode":"ch61 9pf",
    "addr:street":"Pensby Road",
    "iso:country":"GB",
    "sg:address":"415 Pensby Road",
    "sg:city":"Wirral",
    "sg:classifiers":[
        {
            "category":"Food & Beverages",
            "subcategory":"Supermarket",
            "type":"Retail Goods"
        }
    ],
    "sg:phone":"+44 151 648 2110",
    "sg:postcode":"CH61 9PF",
    "sg:province":"Merseyside",
    "wof:name":"Co-Operative",
    "wof:placetype":"venue"
},
  "geometry": {"coordinates":[-3.095529,53.34959],"type":"Point"}
}