{
  "type": "Feature",
  "properties": {
    "iso:country":"GB",
    "sg:address":"116 Renacres Lane",
    "sg:city":"Ormskirk",
    "sg:classifiers":[
        {
            "category":"Food & Beverages",
            "subcategory":"Groceries & Convenience Stores",
            "type":"Retail Goods"
        }
    ],
    "sg:postcode":"L39 8SF",
    "sg:province":"Lancashire",
    "sg:tags":[
        "merchant",
        "potato"
    ],
    "wof:name":"A & Kj Georgeson",
    "wof:placetype":"venue"
},
  "geometry": {"coordinates":[-2.961436,53.604523],"type":"Point"}
}