{
  "type": "Feature",
  "properties": {
    "addr:full":"304 Highfield Rd North Chorley Lancashire PR7 1PH",
    "addr:housenumber":"304",
    "addr:postcode":"pr7 1ph",
    "addr:street":"Highfield Rd",
    "iso:country":"GB",
    "sg:address":"304 Highfield Rd North",
    "sg:city":"Chorley",
    "sg:classifiers":[
        {
            "category":"Building & Trades",
            "subcategory":"Landscaping Services",
            "type":"Services"
        }
    ],
    "sg:postcode":"PR7 1PH",
    "sg:province":"Lancashire",
    "sg:tags":[
        "forestry",
        "tree"
    ],
    "wof:name":"Logwood Treecare",
    "wof:placetype":"venue"
},
  "geometry": {"coordinates":[-2.6330990791,53.6636886597],"type":"Point"}
}