{
  "type": "Feature",
  "properties": {
    "addr:full":"26 Windsor Drive, Lower Bredbury Stockport Cheshire SK6 2EH",
    "addr:housenumber":"26",
    "addr:postcode":"sk6 2eh",
    "addr:street":"Windsor Drive Lower Bredbury",
    "iso:country":"GB",
    "sg:address":"26 Windsor Drive, Lower Bredbury",
    "sg:city":"Stockport",
    "sg:classifiers":[
        {
            "category":"Building & Trades",
            "subcategory":"Construction",
            "type":"Services"
        }
    ],
    "sg:phone":"+44 161 430 6852",
    "sg:postcode":"SK6 2EH",
    "sg:province":"Cheshire",
    "sg:tags":[
        "ceiling",
        "suspended",
        "contractor"
    ],
    "wof:name":"Conroy Building Services",
    "wof:placetype":"venue"
},
  "geometry": {"coordinates":[-2.129671,53.418911],"type":"Point"}
}