{
  "type": "Feature",
  "properties": {
    "addr:full":"9 Eccleshall Road, Loggerheads Market Drayton Shropshire TF9 4NX",
    "addr:housenumber":"9",
    "addr:postcode":"tf9 4nx",
    "addr:street":"Eccleshall Road;Market",
    "iso:country":"GB",
    "sg:address":"9 Eccleshall Road, Loggerheads",
    "sg:city":"Market Drayton",
    "sg:classifiers":[
        {
            "category":"Government",
            "subcategory":"Post Office",
            "type":"Public Place"
        }
    ],
    "sg:phone":"+44 1630 672234",
    "sg:postcode":"TF9 4NX",
    "sg:province":"Shropshire",
    "wof:name":"Loggerheads Sub Post Office",
    "wof:placetype":"venue"
},
  "geometry": {"coordinates":[-2.389551,52.919422],"type":"Point"}
}