{
  "type": "Feature",
  "properties": {
    "iso:country":"GB",
    "sg:address":"Riverside, Bourton-on-the-waterbarn",
    "sg:city":"Cheltenham",
    "sg:classifiers":[
        {
            "category":"Home & Garden",
            "subcategory":"Furniture",
            "type":"Retail Goods"
        }
    ],
    "sg:phone":"+44 1451 822000",
    "sg:postcode":"GL54 2DP",
    "sg:province":"Gloucestershire",
    "wof:name":"Cotswold Country Shop",
    "wof:placetype":"venue"
},
  "geometry": {"coordinates":[-1.760916,51.88678],"type":"Point"}
}