{
  "type": "Feature",
  "properties": {
    "addr:full":"Roper Street Penrith Cumbria CA11 8HS",
    "addr:postcode":"ca11 8hs",
    "addr:street":"Roper Street",
    "iso:country":"GB",
    "sg:address":"Roper Street",
    "sg:city":"Penrith",
    "sg:classifiers":[
        {
            "category":"Military Area",
            "subcategory":"Army Base",
            "type":"Public Place"
        }
    ],
    "sg:phone":"+44 1768 862070",
    "sg:postcode":"CA11 8HS",
    "sg:province":"Cumbria",
    "sg:tags":[
        "joinery",
        "centre"
    ],
    "wof:name":"Bayshields Ltd.",
    "wof:placetype":"venue"
},
  "geometry": {"coordinates":[-2.7478458881,54.6615943909],"type":"Point"}
}