{
  "type": "Feature",
  "properties": {
    "iso:country":"GB",
    "sg:address":"57 Holmewood Gardens",
    "sg:city":"London",
    "sg:classifiers":[
        {
            "category":"Education",
            "subcategory":"Special Training",
            "type":"Public Place"
        }
    ],
    "sg:postcode":"SW2 3NB",
    "sg:province":"Greater London",
    "sg:tags":[
        "product",
        "centre"
    ],
    "wof:name":"Reel Women",
    "wof:placetype":"venue"
},
  "geometry": {"coordinates":[-0.1207540035,51.4462814331],"type":"Point"}
}