{
  "type": "Feature",
  "properties": {
    "addr:full":"Cottage Retreat, Gonvena Wadebridge Cornwall PL27 6DP",
    "addr:postcode":"pl27 6dp",
    "addr:street":"Gonvena",
    "iso:country":"GB",
    "sg:address":"Cottage Retreat, Gonvena",
    "sg:city":"Wadebridge",
    "sg:classifiers":[
        {
            "category":"Utilities",
            "subcategory":"Natural Gas",
            "type":"Services"
        }
    ],
    "sg:phone":"+44 1208 812272",
    "sg:postcode":"PL27 6DP",
    "sg:province":"Cornwall",
    "sg:tags":[
        "control",
        "energy",
        "management",
        "system"
    ],
    "wof:name":"Cottage Heating",
    "wof:placetype":"venue"
},
  "geometry": {"coordinates":[-4.87123,50.56913],"type":"Point"}
}