{
  "type": "Feature",
  "properties": {
    "addr:full":"Sherwood House, Woollards Road, Ash Vale Aldershot Hampshire GU12 5DS",
    "addr:postcode":"gu12 5ds",
    "addr:street":"Woollards Road Ash",
    "iso:country":"GB",
    "sg:address":"Sherwood House, Woollards Road, Ash Vale",
    "sg:city":"Aldershot",
    "sg:classifiers":[
        {
            "category":"Utilities",
            "type":"Services"
        }
    ],
    "sg:phone":"+44 1252 336644",
    "sg:postcode":"GU12 5DS",
    "sg:province":"Hampshire",
    "sg:tags":[
        "internet"
    ],
    "wof:name":"Web Genie Internet Ltd.",
    "wof:placetype":"venue"
},
  "geometry": {"coordinates":[-0.718184,51.257851],"type":"Point"}
}