{
  "type": "Feature",
  "properties": {
    "iso:country":"GB",
    "sg:address":"15 Victoria Street",
    "sg:city":"Kirkwall",
    "sg:classifiers":[
        {
            "category":"Real Estate",
            "subcategory":"Real Estate Operator",
            "type":"Services"
        }
    ],
    "sg:phone":"+44 1856 876310",
    "sg:postcode":"KW15 1DN",
    "sg:province":"Orkney Islands",
    "sg:tags":[
        "letting",
        "agent"
    ],
    "wof:name":"Orkney Islands Property Developments Ltd.",
    "wof:placetype":"venue"
},
  "geometry": {"coordinates":[-2.961468,58.980877],"type":"Point"}
}