{
  "type": "Feature",
  "properties": {
    "addr:full":"Unit 25a, Bolney Grange, Stairbridge Lane, Bolney Haywards Heath East Sussex RH17 5PA",
    "addr:housenumber":"unit 25a bolney",
    "addr:postcode":"rh17 5pa",
    "addr:street":"Grange Stairbridge Lane",
    "iso:country":"GB",
    "sg:address":"Unit 25a, Bolney Grange, Stairbridge Lane, Bolney",
    "sg:city":"Haywards Heath",
    "sg:classifiers":[
        {
            "category":"Wholesale",
            "subcategory":"Scrap",
            "type":"Manufacturing & Wholesale Goods"
        }
    ],
    "sg:phone":"+44 1444 410134",
    "sg:postcode":"RH17 5PA",
    "sg:province":"East Sussex",
    "sg:tags":[
        "car",
        "breaker",
        "dismantlers"
    ],
    "wof:name":"Direct Salvage Cars",
    "wof:placetype":"venue"
},
  "geometry": {"coordinates":[-0.204452,50.990582],"type":"Point"}
}