{
  "type": "Feature",
  "properties": {
    "iso:country":"GB",
    "sg:address":"Sefton Park, Bells Hill, Stoke Poges",
    "sg:city":"Slough",
    "sg:classifiers":[
        {
            "category":"Building & Trades",
            "subcategory":"Construction",
            "type":"Services"
        }
    ],
    "sg:phone":"+44 1753 664448",
    "sg:postcode":"SL2 4JS",
    "sg:province":"Berkshire",
    "sg:tags":[
        "fork",
        "lift",
        "truck"
    ],
    "wof:name":"Jungheinrich (G B) Ltd",
    "wof:placetype":"venue"
},
  "geometry": {"coordinates":[-0.584677,51.547764],"type":"Point"}
}