{
  "type": "Feature",
  "properties": {
    "addr:full":"Reynolds House Courtyard, Erasmus Street London Greater London SW1P 4HP",
    "addr:postcode":"sw1p 4hp",
    "addr:street":"Erasmus Street",
    "iso:country":"GB",
    "sg:address":"Reynolds House Courtyard, Erasmus Street",
    "sg:city":"London",
    "sg:classifiers":[
        {
            "category":"Health Services",
            "subcategory":"Nursing And Care Facility",
            "type":"Services"
        },
        {
            "category":"Real Estate",
            "subcategory":"Real Estate Agent",
            "type":"Services"
        }
    ],
    "sg:phone":"+44 20 7976 5788",
    "sg:postcode":"SW1P 4HP",
    "sg:province":"Greater London",
    "sg:tags":[
        "home"
    ],
    "wof:name":"Millbank Estate Managements Organisation",
    "wof:placetype":"venue"
},
  "geometry": {"coordinates":[-0.12944,51.492531],"type":"Point"}
}