{
  "type": "Feature",
  "properties": {
    "addr:full":"177 Mauldeth Rd Manchester Greater Manchester M14 6SG",
    "addr:housenumber":"177",
    "addr:postcode":"m14 6sg",
    "addr:street":"Mauldeth Rd",
    "iso:country":"GB",
    "sg:address":"177 Mauldeth Rd",
    "sg:city":"Manchester",
    "sg:classifiers":[
        {
            "category":"Health Services",
            "subcategory":"Doctor",
            "type":"Services"
        }
    ],
    "sg:phone":"+44 161 224 2873",
    "sg:postcode":"M14 6SG",
    "sg:province":"Greater Manchester",
    "sg:tags":[
        "practitioners"
    ],
    "wof:name":"Goodman Dr S L",
    "wof:placetype":"venue"
},
  "geometry": {"coordinates":[-2.210329,53.433578],"type":"Point"}
}