{
  "type": "Feature",
  "properties": {
    "addr:full":"110a Brighton Road Coulsdon Surrey CR5 3EF",
    "addr:housenumber":"110a",
    "addr:postcode":"cr5 3ef",
    "addr:street":"Brighton Road",
    "iso:country":"GB",
    "sg:address":"110a Brighton Road",
    "sg:city":"Coulsdon",
    "sg:classifiers":[
        {
            "category":"Personal",
            "subcategory":"Tattoo Parlor",
            "type":"Services"
        }
    ],
    "sg:phone":"+44 20 8668 9266",
    "sg:postcode":"CR5 3EF",
    "sg:province":"Surrey",
    "sg:tags":[
        "tattooing",
        "piercing"
    ],
    "wof:name":"Mr Alan Lewbon",
    "wof:placetype":"venue"
},
  "geometry": {"coordinates":[-0.1391790062,51.3189086914],"type":"Point"}
}