{
  "type": "Feature",
  "properties": {
    "addr:full":"23 Heol-y-deri Cardiff Cardiff CF4 6YF",
    "addr:housenumber":"23",
    "addr:postcode":"cf4 6yf",
    "addr:street":"Heol-Y-Deri Cardiff",
    "iso:country":"GB",
    "sg:address":"23 Heol-y-deri",
    "sg:city":"Cardiff",
    "sg:classifiers":[
        {
            "category":"Travel",
            "subcategory":"Travel Agent",
            "type":"Entertainment"
        }
    ],
    "sg:phone":"+44 29 2069 1667",
    "sg:postcode":"CF4 6YF",
    "sg:province":"Cardiff",
    "wof:name":"Gill's Cruise Centre",
    "wof:placetype":"venue"
},
  "geometry": {"coordinates":[-3.212889,51.522934],"type":"Point"}
}