{
  "type": "Feature",
  "properties": {
    "addr:full":"258a Lee High Rd Lewisham Greater London SE13 5PL",
    "addr:housenumber":"258a",
    "addr:postcode":"se13 5pl",
    "addr:street":"Lee High Rd",
    "iso:country":"GB",
    "sg:address":"258a Lee High Rd",
    "sg:city":"Lewisham",
    "sg:classifiers":[
        {
            "category":"Taxi",
            "type":"Transportation"
        }
    ],
    "sg:phone":"+44 20 8318 1919",
    "sg:postcode":"SE13 5PL",
    "sg:province":"Greater London",
    "sg:tags":[
        "mini",
        "cab"
    ],
    "wof:name":"Penny's Cars",
    "wof:placetype":"venue"
},
  "geometry": {"coordinates":[0.002564,51.458496],"type":"Point"}
}