{
  "type": "Feature",
  "properties": {
    "iso:country":"GB",
    "sg:address":"Chengate House, 61 Pepper Rd",
    "sg:city":"Leeds",
    "sg:classifiers":[
        {
            "category":"Freight",
            "type":"Transportation"
        }
    ],
    "sg:phone":"+44 113 272 3252",
    "sg:postcode":"LS10 2RU",
    "sg:province":"West Yorkshire",
    "sg:tags":[
        "haulage",
        "road"
    ],
    "wof:name":"N.H Haulage",
    "wof:placetype":"venue"
},
  "geometry": {"coordinates":[-1.521919,53.773834],"type":"Point"}
}