{
  "type": "Feature",
  "properties": {
    "iso:country":"GB",
    "sg:address":"Unit 10 Imperial Business Centre, 41 Gatwick Rd",
    "sg:city":"Crawley",
    "sg:classifiers":[
        {
            "category":"Building & Trades",
            "subcategory":"Construction",
            "type":"Services"
        }
    ],
    "sg:phone":"+44 1293 436292",
    "sg:postcode":"RH10 2RD",
    "sg:province":"Surrey",
    "sg:tags":[
        "contractor"
    ],
    "wof:name":"R L Construction",
    "wof:placetype":"venue"
},
  "geometry": {"coordinates":[-0.184753,51.118458],"type":"Point"}
}