{
  "type": "Feature",
  "properties": {
    "iso:country":"GB",
    "sg:address":"Elmfield Rd, Morley",
    "sg:city":"Leeds",
    "sg:classifiers":[
        {
            "category":"Autos & Motor Vehicles",
            "subcategory":"Auto Supplies",
            "type":"Retail Goods"
        }
    ],
    "sg:postcode":"LS27 0EL",
    "sg:province":"West Yorkshire",
    "sg:tags":[
        "towing",
        "eqpt",
        "trailer"
    ],
    "wof:name":"M6 Trailer Rentals",
    "wof:placetype":"venue"
},
  "geometry": {"coordinates":[-1.5946780443,53.7376441956],"type":"Point"}
}