{
  "type": "Feature",
  "properties": {
    "addr:full":"James Street Seahouses Northumberland NE68 7YF",
    "addr:postcode":"ne68 7yf",
    "addr:street":"James Street",
    "iso:country":"GB",
    "sg:address":"James Street",
    "sg:city":"Seahouses",
    "sg:classifiers":[
        {
            "category":"Education",
            "subcategory":"School",
            "type":"Public Place"
        }
    ],
    "sg:phone":"+44 1665 720473",
    "sg:postcode":"NE68 7YF",
    "sg:province":"Northumberland",
    "sg:tags":[
        "local",
        "authority"
    ],
    "wof:name":"Seahouses County Middle School",
    "wof:placetype":"venue"
},
  "geometry": {"coordinates":[-1.6541240215,55.5811729431],"type":"Point"}
}