{
  "type": "Feature",
  "properties": {
    "iso:country":"GB",
    "sg:address":"54 Tontine Street",
    "sg:city":"Folkestone",
    "sg:classifiers":[
        {
            "category":"Restaurant",
            "type":"Food & Drink"
        }
    ],
    "sg:phone":"+44 1303 254052",
    "sg:postcode":"CT20 1JP",
    "sg:province":"Kent",
    "sg:tags":[
        "indian",
        "-"
    ],
    "wof:name":"Curry Garden",
    "wof:placetype":"venue"
},
  "geometry": {"coordinates":[1.1832209826,51.0814590454],"type":"Point"}
}