{
  "type": "Feature",
  "properties": {
    "iso:country":"GB",
    "sg:address":"Bryn Golau",
    "sg:city":"Pwllheli",
    "sg:classifiers":[
        {
            "category":"Wholesale",
            "subcategory":"Fruits & Vegetables",
            "type":"Manufacturing & Wholesale Goods"
        }
    ],
    "sg:postcode":"LL53 7RL",
    "sg:province":"Gwynedd",
    "wof:name":"I G Roberts & Son",
    "wof:placetype":"venue"
},
  "geometry": {"coordinates":[-4.414314,52.889847],"type":"Point"}
}