{
  "type": "Feature",
  "properties": {
    "addr:full":"157 Whitletts Road Ayr South Ayrshire KA8 0JQ",
    "addr:housenumber":"157",
    "addr:postcode":"ka8 0jq",
    "addr:street":"Whitletts Road",
    "iso:country":"GB",
    "sg:address":"157 Whitletts Road",
    "sg:city":"Ayr",
    "sg:classifiers":[
        {
            "category":"Fast Food",
            "type":"Food & Drink"
        },
        {
            "category":"Restaurant",
            "type":"Food & Drink"
        }
    ],
    "sg:postcode":"KA8 0JQ",
    "sg:province":"South Ayrshire",
    "sg:tags":[
        "away",
        "indian",
        "take"
    ],
    "wof:name":"Kismet Tandoori",
    "wof:placetype":"venue"
},
  "geometry": {"coordinates":[-4.6076011658,55.469581604],"type":"Point"}
}