{
  "type": "Feature",
  "properties": {
    "addr:full":"18 Toll Wynd, Avon Gro Hamilton South Lanarkshire ML3 7QF",
    "addr:housenumber":"18",
    "addr:postcode":"ml3 7qf",
    "addr:street":"Toll Wynd",
    "iso:country":"GB",
    "sg:address":"18 Toll Wynd, Avon Gro",
    "sg:city":"Hamilton",
    "sg:classifiers":[
        {
            "category":"Building & Trades",
            "subcategory":"Landscaping Services",
            "type":"Services"
        }
    ],
    "sg:phone":"+44 1698 824411",
    "sg:postcode":"ML3 7QF",
    "sg:province":"South Lanarkshire",
    "sg:tags":[
        "landscape",
        "contractor"
    ],
    "wof:name":"Gary Aitchison",
    "wof:placetype":"venue"
},
  "geometry": {"coordinates":[-4.0517239571,55.754486084],"type":"Point"}
}