{
  "type": "Feature",
  "properties": {
    "addr:full":"Battersea Leisure Centre Latchmere Rd Battersea Greater London SW11 2DY",
    "addr:postcode":"sw11 2dy",
    "addr:street":"Latchmere Rd",
    "iso:country":"GB",
    "sg:address":"Battersea Leisure Centre Latchmere Rd",
    "sg:city":"Battersea",
    "sg:classifiers":[
        {
            "category":"Professional",
            "type":"Services"
        }
    ],
    "sg:phone":"+44 20 7223 4114",
    "sg:postcode":"SW11 2DY",
    "sg:province":"Greater London",
    "sg:tags":[
        "caterer"
    ],
    "wof:name":"Penacom Catering",
    "wof:placetype":"venue"
},
  "geometry": {"coordinates":[-0.162839,51.467464],"type":"Point"}
}