{
  "type": "Feature",
  "properties": {
    "iso:country":"GB",
    "sg:address":"29 Cheriton High Street",
    "sg:city":"Folkestone",
    "sg:classifiers":[
        {
            "category":"Fast Food",
            "type":"Food & Drink"
        }
    ],
    "sg:phone":"+44 1303 273429",
    "sg:postcode":"CT19 4EY",
    "sg:province":"Kent",
    "sg:tags":[
        "away",
        "take"
    ],
    "wof:name":"Aspendos Kebab House",
    "wof:placetype":"venue"
},
  "geometry": {"coordinates":[1.144844,51.087673],"type":"Point"}
}