{
  "type": "Feature",
  "properties": {
    "addr:full":"23 Stalin Road Colchester Essex CO2 8RX",
    "addr:housenumber":"23",
    "addr:postcode":"co2 8rx",
    "addr:street":"Stalin Road Colchester",
    "iso:country":"GB",
    "sg:address":"23 Stalin Road",
    "sg:city":"Colchester",
    "sg:classifiers":[
        {
            "category":"Retail",
            "subcategory":"Repair Shop",
            "type":"Services"
        }
    ],
    "sg:phone":"+44 1206 515047",
    "sg:postcode":"CO2 8RX",
    "sg:province":"Essex",
    "sg:tags":[
        "maintenance"
    ],
    "wof:name":"Allsorts",
    "wof:placetype":"venue"
},
  "geometry": {"coordinates":[0.9101279974,51.8753547668],"type":"Point"}
}