{
  "type": "Feature",
  "properties": {
    "addr:full":"160 Bank Street Alexandria Argyll and Bute G83 0UP",
    "addr:housenumber":"160",
    "addr:postcode":"g83 0up",
    "addr:street":"Bank Street",
    "iso:country":"GB",
    "sg:address":"160 Bank Street",
    "sg:city":"Alexandria",
    "sg:classifiers":[
        {
            "category":"Professional",
            "subcategory":"Employment Agencies",
            "type":"Services"
        }
    ],
    "sg:phone":"+44 1389 823420",
    "sg:postcode":"G83 0UP",
    "sg:province":"Argyll and Bute",
    "sg:tags":[
        "consultant"
    ],
    "wof:name":"Jobcentres",
    "wof:placetype":"venue"
},
  "geometry": {"coordinates":[-4.576091,55.985687],"type":"Point"}
}