{
  "type": "Feature",
  "properties": {
    "iso:country":"GB",
    "sg:address":"184-186 Stamford Street Central",
    "sg:city":"Ashton Under Lyne",
    "sg:classifiers":[
        {
            "category":"Home & Garden",
            "subcategory":"Furniture",
            "type":"Retail Goods"
        }
    ],
    "sg:phone":"+44 161 343 1151",
    "sg:postcode":"OL6 7LR",
    "sg:province":"Greater Manchester",
    "wof:name":"Oakland Furnishing Co",
    "wof:placetype":"venue"
},
  "geometry": {"coordinates":[-2.093569994,53.4874038696],"type":"Point"}
}