{
  "type": "Feature",
  "properties": {
    "addr:full":"16 Node Hill Studley Warwickshire B80 7RR",
    "addr:housenumber":"16",
    "addr:postcode":"b80 7rr",
    "addr:street":"Node Hill",
    "iso:country":"GB",
    "sg:address":"16 Node Hill",
    "sg:city":"Studley",
    "sg:classifiers":[
        {
            "category":"Education",
            "subcategory":"Preschool",
            "type":"Public Place"
        }
    ],
    "sg:phone":"+44 1527 854287",
    "sg:postcode":"B80 7RR",
    "sg:province":"Warwickshire",
    "sg:tags":[
        "pre-school",
        "playgroups"
    ],
    "wof:name":"Tumble Tots",
    "wof:placetype":"venue"
},
  "geometry": {"coordinates":[-1.904133,52.267941],"type":"Point"}
}