{
  "type": "Feature",
  "properties": {
    "addr:full":"White Cottage, Pickhill Thirsk North Yorkshire YO7 4JG",
    "addr:postcode":"yo7 4jg",
    "iso:country":"GB",
    "sg:address":"White Cottage, Pickhill",
    "sg:city":"Thirsk",
    "sg:classifiers":[
        {
            "category":"Farming",
            "subcategory":"Poultry Farm",
            "type":"Manufacturing & Wholesale Goods"
        }
    ],
    "sg:phone":"+44 1845 567461",
    "sg:postcode":"YO7 4JG",
    "sg:province":"North Yorkshire",
    "wof:name":"Cockfield Chicken Co.",
    "wof:placetype":"venue"
},
  "geometry": {"coordinates":[-1.4705959558,54.2475166321],"type":"Point"}
}