{
  "type": "Feature",
  "properties": {
    "addr:full":"Windmill Lane, Warley Smethwick West Midlands B66 3EN",
    "addr:postcode":"b66 3en",
    "addr:street":"Windmill Lane",
    "iso:country":"GB",
    "sg:address":"Windmill Lane, Warley",
    "sg:city":"Smethwick",
    "sg:classifiers":[
        {
            "category":"Personal",
            "subcategory":"Beauty Salon",
            "type":"Services"
        }
    ],
    "sg:phone":"+44 121 555 7455",
    "sg:postcode":"B66 3EN",
    "sg:province":"West Midlands",
    "sg:tags":[
        "lady",
        "hairdresser"
    ],
    "wof:name":"Solutions",
    "wof:placetype":"venue"
},
  "geometry": {"coordinates":[-1.971184,52.495926],"type":"Point"}
}