{
  "type": "Feature",
  "properties": {
    "iso:country":"GB",
    "sg:address":"The Retreat, High Street",
    "sg:city":"Bedford",
    "sg:classifiers":[
        {
            "category":"Building & Trades",
            "subcategory":"Construction",
            "type":"Services"
        }
    ],
    "sg:postcode":"MK43 7NU",
    "sg:province":"Bedfordshire",
    "sg:tags":[
        "builder"
    ],
    "wof:name":"D & S Lovell",
    "wof:placetype":"venue"
},
  "geometry": {"coordinates":[-0.6104789972,52.2012481689],"type":"Point"}
}