{
  "type": "Feature",
  "properties": {
    "addr:full":"Unit 3 Friday House, 46 Friday Street Leicester Leicestershire LE1 3BW",
    "addr:housenumber":"unit 3 friday house 46",
    "addr:postcode":"le1 3bw",
    "addr:street":"Street",
    "iso:country":"GB",
    "sg:address":"Unit 3 Friday House, 46 Friday Street",
    "sg:city":"Leicester",
    "sg:classifiers":[
        {
            "category":"Manufacturing",
            "subcategory":"Textiles",
            "type":"Manufacturing & Wholesale Goods"
        }
    ],
    "sg:phone":"+44 116 222 8838",
    "sg:postcode":"LE1 3BW",
    "sg:province":"Leicestershire",
    "sg:tags":[
        "merchant",
        "agent"
    ],
    "wof:name":"M H D Enterprises (U K) Ltd.",
    "wof:placetype":"venue"
},
  "geometry": {"coordinates":[-1.1361370087,52.6423835754],"type":"Point"}
}