{
  "type": "Feature",
  "properties": {
    "addr:full":"Unit 18, Lynx Crescent Weston-super-mare Somerset BS24 9DJ",
    "addr:housenumber":"unit 18",
    "addr:postcode":"bs24 9dj",
    "addr:street":"Lynx Crescent",
    "iso:country":"GB",
    "sg:address":"Unit 18, Lynx Crescent",
    "sg:city":"Weston-super-mare",
    "sg:classifiers":[
        {
            "category":"Professional",
            "subcategory":"Engineering",
            "type":"Services"
        }
    ],
    "sg:phone":"+44 1934 628476",
    "sg:postcode":"BS24 9DJ",
    "sg:province":"Somerset",
    "sg:tags":[
        "precision",
        "engineer"
    ],
    "wof:name":"D & G Engineering",
    "wof:placetype":"venue"
},
  "geometry": {"coordinates":[-2.9524540901,51.325050354],"type":"Point"}
}