{
  "type": "Feature",
  "properties": {
    "iso:country":"GB",
    "sg:address":"29 Brewer St",
    "sg:city":"West End",
    "sg:classifiers":[
        {
            "category":"Shopping",
            "subcategory":"Clothing, Apparel, & Fashions",
            "type":"Retail Goods"
        }
    ],
    "sg:phone":"+44 20 7437 2285",
    "sg:postcode":"W1R 3FE",
    "sg:province":"Hampshire",
    "sg:tags":[
        "shop"
    ],
    "wof:name":"El Paso",
    "wof:placetype":"venue"
},
  "geometry": {"coordinates":[-0.134548,51.511898],"type":"Point"}
}