{
  "type": "Feature",
  "properties": {
    "addr:full":"26 Clarendon Rise London Greater London SE13 5EY",
    "addr:housenumber":"26",
    "addr:postcode":"se13 5ey",
    "addr:street":"Clarendon Rise",
    "iso:country":"GB",
    "sg:address":"26 Clarendon Rise",
    "sg:city":"London",
    "sg:classifiers":[
        {
            "category":"Health Services",
            "subcategory":"Health Practitioner",
            "type":"Services"
        }
    ],
    "sg:postcode":"SE13 5EY",
    "sg:province":"Greater London",
    "sg:tags":[
        "homoeopathic"
    ],
    "wof:name":"Lesley King",
    "wof:placetype":"venue"
},
  "geometry": {"coordinates":[-0.0077940002,51.4594306946],"type":"Point"}
}