{
  "type": "Feature",
  "properties": {
    "addr:full":"3 Plumstead Road London Greater London SE18 7BZ",
    "addr:housenumber":"3",
    "addr:postcode":"se18 7bz",
    "addr:street":"Plumstead Road",
    "iso:country":"GB",
    "sg:address":"3 Plumstead Road",
    "sg:city":"London",
    "sg:classifiers":[
        {
            "category":"Communications",
            "type":"Services"
        }
    ],
    "sg:phone":"+44 20 8854 7871",
    "sg:postcode":"SE18 7BZ",
    "sg:province":"Greater London",
    "sg:tags":[
        "tv",
        "video",
        "radio"
    ],
    "wof:name":"Revelward Ltd.",
    "wof:placetype":"venue"
},
  "geometry": {"coordinates":[0.0705379993,51.4912071228],"type":"Point"}
}