{
  "type": "Feature",
  "properties": {
    "addr:full":"Suite 4214, Belasis Business Centre, Coxwold Way Billingham Durham TS23 4EA",
    "addr:housenumber":"suite 4214",
    "addr:postcode":"ts23 4ea",
    "addr:street":"Belasis Business;Coxwold Way",
    "iso:country":"GB",
    "sg:address":"Suite 4214, Belasis Business Centre, Coxwold Way",
    "sg:city":"Billingham",
    "sg:classifiers":[
        {
            "category":"Professional",
            "subcategory":"Management & Consulting",
            "type":"Services"
        },
        {
            "category":"Real Estate",
            "subcategory":"Surveying",
            "type":"Services"
        }
    ],
    "sg:postcode":"TS23 4EA",
    "sg:province":"Durham",
    "sg:tags":[
        "project",
        "surveyor",
        "quantity"
    ],
    "wof:name":"Project Management & Procurement Service",
    "wof:placetype":"venue"
},
  "geometry": {"coordinates":[-1.2936450243,54.6068572998],"type":"Point"}
}