{
  "type": "Feature",
  "properties": {
    "addr:full":"29 - 33 Church Road, Gosforth Newcastle-upon-tyne Tyne and Wear NE3 1UE",
    "addr:housenumber":"33",
    "addr:postcode":"ne3 1ue",
    "addr:street":"Church Road",
    "iso:country":"GB",
    "sg:address":"29 - 33 Church Road, Gosforth",
    "sg:city":"Newcastle-upon-tyne",
    "sg:classifiers":[
        {
            "category":"Social Services",
            "subcategory":"Retirement Home",
            "type":"Services"
        }
    ],
    "sg:postcode":"NE3 1UE",
    "sg:province":"Tyne and Wear",
    "sg:tags":[
        "rest"
    ],
    "wof:name":"Heywood Rest Home",
    "wof:placetype":"venue"
},
  "geometry": {"coordinates":[-1.616648,55.00758],"type":"Point"}
}