{
  "type": "Feature",
  "properties": {
    "addr:full":"12 York Gate London Greater London NW1 4QS",
    "addr:housenumber":"12",
    "addr:postcode":"nw1 4qs",
    "addr:street":"York Gate",
    "iso:country":"GB",
    "sg:address":"12 York Gate",
    "sg:city":"London",
    "sg:classifiers":[
        {
            "category":"Banks & Credit Unions",
            "subcategory":"Financial Services",
            "type":"Services"
        }
    ],
    "sg:postcode":"NW1 4QS",
    "sg:province":"Greater London",
    "sg:tags":[
        "consultant"
    ],
    "wof:name":"Nightingale Property Investments Ltd",
    "wof:placetype":"venue"
},
  "geometry": {"coordinates":[-0.152819,51.52335],"type":"Point"}
}