{
  "type": "Feature",
  "properties": {
    "addr:full":"The Pary Williams Bldng Aberystwyth Ceredigion SY23 3AJ",
    "addr:postcode":"sy23 3aj",
    "iso:country":"GB",
    "sg:address":"The Pary Williams Bldng",
    "sg:city":"Aberystwyth",
    "sg:classifiers":[
        {
            "category":"Communications",
            "type":"Services"
        }
    ],
    "sg:phone":"+44 1970 833965",
    "sg:postcode":"SY23 3AJ",
    "sg:province":"Ceredigion",
    "sg:tags":[
        "broadcasting"
    ],
    "wof:name":"B B C Aberystwyth",
    "wof:placetype":"venue"
},
  "geometry": {"coordinates":[-4.077869,52.41605],"type":"Point"}
}