{
  "type": "Feature",
  "properties": {
    "addr:full":"7 Callander Road Ayr South Ayrshire KA8 9AF",
    "addr:housenumber":"7",
    "addr:postcode":"ka8 9af",
    "addr:street":"Callander Road",
    "iso:country":"GB",
    "sg:address":"7 Callander Road",
    "sg:city":"Ayr",
    "sg:classifiers":[
        {
            "category":"Home & Garden",
            "subcategory":"Home Furnishings",
            "type":"Retail Goods"
        }
    ],
    "sg:postcode":"KA8 9AF",
    "sg:province":"South Ayrshire",
    "sg:tags":[
        "merchant",
        "diy",
        "decorators'"
    ],
    "wof:name":"James Davie Decor Ltd.",
    "wof:placetype":"venue"
},
  "geometry": {"coordinates":[-4.6062688828,55.4777183533],"type":"Point"}
}