{
  "type": "Feature",
  "properties": {
    "addr:full":"31 Princess Rd Sheffield Derbyshire S18 2LX",
    "addr:housenumber":"31",
    "addr:postcode":"s18 2lx",
    "addr:street":"Princess Rd",
    "iso:country":"GB",
    "sg:address":"31 Princess Rd",
    "sg:city":"Sheffield",
    "sg:classifiers":[
        {
            "category":"Recreation",
            "subcategory":"Gun Range",
            "type":"Entertainment"
        }
    ],
    "sg:phone":"+44 1246 292010",
    "sg:postcode":"S18 2LX",
    "sg:province":"Derbyshire",
    "sg:tags":[
        "operator",
        "tour"
    ],
    "wof:name":"Altours Travel",
    "wof:placetype":"venue"
},
  "geometry": {"coordinates":[-1.447724,53.390953],"type":"Point"}
}