{
  "type": "Feature",
  "properties": {
    "iso:country":"GB",
    "sg:address":"Bashfords Lane",
    "sg:city":"Worthing",
    "sg:classifiers":[
        {
            "category":"Manufacturing",
            "subcategory":"Signs",
            "type":"Manufacturing & Wholesale Goods"
        }
    ],
    "sg:phone":"+44 1903 230830",
    "sg:postcode":"BN14 8AF",
    "sg:province":"West Sussex",
    "sg:tags":[
        "writer"
    ],
    "wof:name":"A J Marchant Signwriter of Worthing",
    "wof:placetype":"venue"
},
  "geometry": {"coordinates":[-0.372468,50.820869],"type":"Point"}
}