{
  "type": "Feature",
  "properties": {
    "addr:full":"Unit T4, Greenheath Business Centre Bethnal Green Greater London E2 6JB",
    "addr:postcode":"e2 6jb",
    "iso:country":"GB",
    "sg:address":"Unit T4, Greenheath Business Centre",
    "sg:city":"Bethnal Green",
    "sg:classifiers":[
        {
            "category":"Building & Trades",
            "subcategory":"Construction",
            "type":"Services"
        }
    ],
    "sg:phone":"+44 20 7790 9757",
    "sg:postcode":"E2 6JB",
    "sg:province":"Greater London",
    "sg:tags":[
        "flooring"
    ],
    "wof:name":"Flooring Systems",
    "wof:placetype":"venue"
},
  "geometry": {"coordinates":[-0.057312,51.524925],"type":"Point"}
}