{
  "type": "Feature",
  "properties": {
    "iso:country":"GB",
    "sg:address":"32 Kingly Street",
    "sg:city":"London",
    "sg:classifiers":[
        {
            "category":"Fast Food",
            "type":"Food & Drink"
        }
    ],
    "sg:postcode":"W1B 5QG",
    "sg:province":"Greater London",
    "sg:tags":[
        "away",
        "take"
    ],
    "wof:name":"Peter's Restaurant",
    "wof:placetype":"venue"
},
  "geometry": {"coordinates":[-0.140201,51.513447],"type":"Point"}
}