{
  "type": "Feature",
  "properties": {
    "iso:country":"GB",
    "sg:address":"16b Witherington Road",
    "sg:city":"London",
    "sg:classifiers":[
        {
            "category":"Organizations",
            "subcategory":"Professional Association",
            "type":"Services"
        }
    ],
    "sg:phone":"+44 20 7700 5777",
    "sg:postcode":"N5 1PP",
    "sg:province":"Greater London",
    "sg:tags":[
        "artist",
        "make-up"
    ],
    "wof:name":"Warpaint Agency",
    "wof:placetype":"venue"
},
  "geometry": {"coordinates":[-0.107248,51.550739],"type":"Point"}
}