{
  "type": "Feature",
  "properties": {
    "iso:country":"GB",
    "sg:address":"The Family Court Welfare Service, Meridians Cross, Ocean Way",
    "sg:city":"Southampton",
    "sg:classifiers":[
        {
            "category":"Government",
            "subcategory":"Office",
            "type":"Public Place"
        }
    ],
    "sg:phone":"+44 23 8063 0996",
    "sg:postcode":"SO14 3TJ",
    "sg:province":"Hampshire",
    "sg:tags":[
        "local"
    ],
    "wof:name":"Hampshire Probation Service",
    "wof:placetype":"venue"
},
  "geometry": {"coordinates":[-1.39505,50.89566],"type":"Point"}
}