{
  "type": "Feature",
  "properties": {
    "addr:full":"Chapel Pond Hill Bury St Edmunds Suffolk IP32 7HT",
    "addr:postcode":"ip32 7ht",
    "addr:street":"Pond Hill",
    "iso:country":"GB",
    "sg:address":"Chapel Pond Hill",
    "sg:city":"Bury St Edmunds",
    "sg:classifiers":[
        {
            "category":"Manufacturing",
            "subcategory":"Metals",
            "type":"Manufacturing & Wholesale Goods"
        }
    ],
    "sg:phone":"+44 1284 754389",
    "sg:postcode":"IP32 7HT",
    "sg:province":"Suffolk",
    "sg:tags":[
        "steel",
        "stockholder"
    ],
    "wof:name":"A J N Steel Stock Ltd",
    "wof:placetype":"venue"
},
  "geometry": {"coordinates":[0.7303500175,52.2562522888],"type":"Point"}
}