{
  "type": "Feature",
  "properties": {
    "iso:country":"GB",
    "sg:address":"16 Cross Way",
    "sg:city":"Christchurch",
    "sg:classifiers":[
        {
            "category":"Building & Trades",
            "subcategory":"Construction",
            "type":"Services"
        }
    ],
    "sg:phone":"+44 1202 477585",
    "sg:postcode":"BH23 2PJ",
    "sg:province":"Dorset",
    "sg:tags":[
        "window",
        "replacement"
    ],
    "wof:name":"T T S",
    "wof:placetype":"venue"
},
  "geometry": {"coordinates":[-1.804142,50.747402],"type":"Point"}
}