{
  "type": "Feature",
  "properties": {
    "addr:full":"Church La, Horsforth Leeds West Yorkshire LS18 5LA",
    "addr:postcode":"ls18 5la",
    "addr:street":"La Horsforth Leeds West",
    "iso:country":"GB",
    "sg:address":"Church La, Horsforth",
    "sg:city":"Leeds",
    "sg:classifiers":[
        {
            "category":"Social Services",
            "type":"Services"
        }
    ],
    "sg:postcode":"LS18 5LA",
    "sg:province":"West Yorkshire",
    "wof:name":"Horsforth Training Centre",
    "wof:placetype":"venue"
},
  "geometry": {"coordinates":[-1.6407090425,53.8403587341],"type":"Point"}
}