{
  "type": "Feature",
  "properties": {
    "addr:full":"1 Well Road Moffat Dumfries and Galloway DG10 9AR",
    "addr:housenumber":"1",
    "addr:postcode":"dg10 9ar",
    "addr:street":"Well Road",
    "iso:country":"GB",
    "sg:address":"1 Well Road",
    "sg:city":"Moffat",
    "sg:classifiers":[
        {
            "category":"Professional",
            "subcategory":"Engineering",
            "type":"Services"
        }
    ],
    "sg:phone":"+44 1683 220280",
    "sg:postcode":"DG10 9AR",
    "sg:province":"Dumfries and Galloway",
    "sg:tags":[
        "contractor",
        "electrical",
        "engineer"
    ],
    "wof:name":"R Matchett & Son",
    "wof:placetype":"venue"
},
  "geometry": {"coordinates":[-3.4438490868,55.3328399658],"type":"Point"}
}