{
  "type": "Feature",
  "properties": {
    "addr:full":"3 Caradoc Clo Coventry Warwickshire CV2 1QT",
    "addr:housenumber":"3",
    "addr:postcode":"cv2 1qt",
    "addr:street":"Caradoc Clo",
    "iso:country":"GB",
    "sg:address":"3 Caradoc Clo",
    "sg:city":"Coventry",
    "sg:classifiers":[
        {
            "category":"Food & Beverages",
            "subcategory":"Supermarket",
            "type":"Retail Goods"
        }
    ],
    "sg:postcode":"CV2 1QT",
    "sg:province":"Warwickshire",
    "wof:name":"Manor Supermarket (The)",
    "wof:placetype":"venue"
},
  "geometry": {"coordinates":[-1.457102,52.428192],"type":"Point"}
}