{
  "type": "Feature",
  "properties": {
    "addr:full":"28 Ashley Road, Hildenborough Tonbridge Kent TN11 9ED",
    "addr:housenumber":"28",
    "addr:postcode":"tn11 9ed",
    "addr:street":"Ashley Road",
    "iso:country":"GB",
    "sg:address":"28 Ashley Road, Hildenborough",
    "sg:city":"Tonbridge",
    "sg:classifiers":[
        {
            "category":"Professional",
            "subcategory":"Engineering",
            "type":"Services"
        }
    ],
    "sg:postcode":"TN11 9ED",
    "sg:province":"Kent",
    "sg:tags":[
        "contractor",
        "electrical",
        "engineer"
    ],
    "wof:name":"Brian William Child",
    "wof:placetype":"venue"
},
  "geometry": {"coordinates":[0.249513,51.209145],"type":"Point"}
}