{
  "type": "Feature",
  "properties": {
    "iso:country":"GB",
    "sg:address":"Boreen Cottage, Westhorpe Lane, Byfield",
    "sg:city":"Daventry",
    "sg:classifiers":[
        {
            "category":"Building & Trades",
            "subcategory":"Construction",
            "type":"Services"
        }
    ],
    "sg:phone":"+44 1327 260183",
    "sg:postcode":"NN11 6XB",
    "sg:province":"Northamptonshire",
    "sg:tags":[
        "builder"
    ],
    "wof:name":"Woodford & Upfield",
    "wof:placetype":"venue"
},
  "geometry": {"coordinates":[-1.2455370426,52.1749839783],"type":"Point"}
}