{
  "type": "Feature",
  "properties": {
    "iso:country":"GB",
    "sg:address":"Forest Road",
    "sg:city":"Tunbridge Wells",
    "sg:classifiers":[
        {
            "category":"Community Center",
            "type":"Public Place"
        }
    ],
    "sg:postcode":"TN2 5AL",
    "sg:province":"East Sussex",
    "sg:tags":[
        "nursery",
        "centre"
    ],
    "wof:name":"Plantbase",
    "wof:placetype":"venue"
},
  "geometry": {"coordinates":[0.2810670137,51.1265792847],"type":"Point"}
}