{
  "type": "Feature",
  "properties": {
    "addr:full":"Cara Congalton Gardens North Berwick East Lothian EH39 5JP",
    "addr:postcode":"eh39 5jp",
    "addr:street":"Berwick",
    "iso:country":"GB",
    "sg:address":"Cara Congalton Gardens",
    "sg:city":"North Berwick",
    "sg:classifiers":[
        {
            "category":"Wholesale",
            "subcategory":"Fruits & Vegetables",
            "type":"Manufacturing & Wholesale Goods"
        }
    ],
    "sg:phone":"+44 1620 892512",
    "sg:postcode":"EH39 5JP",
    "sg:province":"East Lothian",
    "wof:name":"Robert Sinclair & Son",
    "wof:placetype":"venue"
},
  "geometry": {"coordinates":[-2.7170538902,56.058555603],"type":"Point"}
}