{
  "type": "Feature",
  "properties": {
    "addr:full":"Pensarn Road Carmarthen Carmarthenshire SA31 2DD",
    "addr:postcode":"sa31 2dd",
    "addr:street":"Pensarn Road",
    "iso:country":"GB",
    "sg:address":"Pensarn Road",
    "sg:city":"Carmarthen",
    "sg:classifiers":[
        {
            "category":"Autos & Motor Vehicles",
            "subcategory":"Automobile Sales",
            "type":"Retail Goods"
        }
    ],
    "sg:phone":"+44 1267 234847",
    "sg:postcode":"SA31 2DD",
    "sg:province":"Carmarthenshire",
    "sg:tags":[
        "car"
    ],
    "wof:name":"Arthur Bassett",
    "wof:placetype":"venue"
},
  "geometry": {"coordinates":[-4.30468,51.852463],"type":"Point"}
}