{
  "type": "Feature",
  "properties": {
    "addr:full":"4th Floor City Gate House, 399 - 425 Eastern Avenue Ilford Essex IG2 6LR",
    "addr:housenumber":"4th floor;399 425",
    "addr:postcode":"ig2 6lr",
    "addr:street":"City Gate;Eastern Avenue",
    "iso:country":"GB",
    "sg:address":"4th Floor City Gate House, 399 - 425 Eastern Avenue",
    "sg:city":"Ilford",
    "sg:classifiers":[
        {
            "category":"Banks & Credit Unions",
            "subcategory":"Financial Services",
            "type":"Services"
        }
    ],
    "sg:phone":"+44 870 161 3333",
    "sg:postcode":"IG2 6LR",
    "sg:province":"Essex",
    "sg:tags":[
        "consultant"
    ],
    "wof:name":"Sun Life Assurance Co. of Canada",
    "wof:placetype":"venue"
},
  "geometry": {"coordinates":[0.069214,51.576195],"type":"Point"}
}