{
  "type": "Feature",
  "properties": {
    "iso:country":"GB",
    "sg:address":"77 Stanley Rd",
    "sg:city":"Morecambe",
    "sg:classifiers":[
        {
            "category":"Retail",
            "subcategory":"Auto Repair",
            "type":"Services"
        }
    ],
    "sg:phone":"+44 1524 420817",
    "sg:postcode":"LA3 1UT",
    "sg:province":"Lancashire",
    "sg:tags":[
        "modification",
        "garage"
    ],
    "wof:name":"S T Motors",
    "wof:placetype":"venue"
},
  "geometry": {"coordinates":[-2.883165,54.061455],"type":"Point"}
}