{
  "type": "Feature",
  "properties": {
    "addr:full":"11a Briarfield Road, Farnworth Bolton Lancashire BL4 0HD",
    "addr:housenumber":"11a",
    "addr:postcode":"bl4 0hd",
    "addr:street":"Briarfield Road",
    "iso:country":"GB",
    "sg:address":"11a Briarfield Road, Farnworth",
    "sg:city":"Bolton",
    "sg:classifiers":[
        {
            "category":"Building & Trades",
            "subcategory":"Cleaning & Sanitation",
            "type":"Services"
        }
    ],
    "sg:phone":"+44 1204 795719",
    "sg:postcode":"BL4 0HD",
    "sg:province":"Lancashire",
    "sg:tags":[
        "dry",
        "control",
        "damp",
        "rot"
    ],
    "wof:name":"Briarfields Remedials",
    "wof:placetype":"venue"
},
  "geometry": {"coordinates":[-2.421545,53.549961],"type":"Point"}
}