{
  "type": "Feature",
  "properties": {
    "addr:full":"Willow Lodge, Horseshoe Road Spalding Lincolnshire PE11 3JA",
    "addr:postcode":"pe11 3ja",
    "addr:street":"Horseshoe Road",
    "iso:country":"GB",
    "sg:address":"Willow Lodge, Horseshoe Road",
    "sg:city":"Spalding",
    "sg:classifiers":[
        {
            "category":"Real Estate",
            "subcategory":"Architect",
            "type":"Services"
        }
    ],
    "sg:phone":"+44 1775 767968",
    "sg:postcode":"PE11 3JA",
    "sg:province":"Lincolnshire",
    "sg:tags":[
        "architectural"
    ],
    "wof:name":"East Midland Design Associates",
    "wof:placetype":"venue"
},
  "geometry": {"coordinates":[-0.1808339953,52.7610168457],"type":"Point"}
}