{
  "type": "Feature",
  "properties": {
    "addr:full":"7 Headley Rd Reading Berkshire RG5 4JB",
    "addr:housenumber":"7",
    "addr:postcode":"rg5 4jb",
    "addr:street":"Headley Rd",
    "iso:country":"GB",
    "sg:address":"7 Headley Rd",
    "sg:city":"Reading",
    "sg:classifiers":[
        {
            "category":"Health Services",
            "subcategory":"Clinic",
            "type":"Services"
        }
    ],
    "sg:phone":"+44 118 969 0797",
    "sg:postcode":"RG5 4JB",
    "sg:province":"Berkshire",
    "sg:tags":[
        "nh"
    ],
    "wof:name":"Woodley Park Surgery",
    "wof:placetype":"venue"
},
  "geometry": {"coordinates":[-0.8886100054,51.4560928345],"type":"Point"}
}