{
  "type": "Feature",
  "properties": {
    "addr:full":"38 High Street, Eccleshall Stafford Staffordshire ST21 6BZ",
    "addr:housenumber":"38",
    "addr:postcode":"st21 6bz",
    "addr:street":"High Street",
    "iso:country":"GB",
    "sg:address":"38 High Street, Eccleshall",
    "sg:city":"Stafford",
    "sg:classifiers":[
        {
            "category":"Health Services",
            "subcategory":"Clinic",
            "type":"Services"
        }
    ],
    "sg:postcode":"ST21 6BZ",
    "sg:province":"Staffordshire",
    "sg:tags":[
        "injury",
        "sport"
    ],
    "wof:name":"Physiotherapy & Sports Injury Clinic (The)",
    "wof:placetype":"venue"
},
  "geometry": {"coordinates":[-2.25436,52.859642],"type":"Point"}
}