{
  "type": "Feature",
  "properties": {
    "iso:country":"GB",
    "sg:address":"93 High Street, Horsell",
    "sg:city":"Woking",
    "sg:classifiers":[
        {
            "category":"Real Estate",
            "subcategory":"Real Estate Agent",
            "type":"Services"
        }
    ],
    "sg:phone":"+44 1483 751000",
    "sg:postcode":"GU21 4SY",
    "sg:province":"Surrey",
    "wof:name":"Tony Lynch & Co. Ltd.",
    "wof:placetype":"venue"
},
  "geometry": {"coordinates":[-0.574871,51.324192],"type":"Point"}
}