{
  "type": "Feature",
  "properties": {
    "iso:country":"GB",
    "sg:address":"29 St Dunstans Road",
    "sg:city":"Feltham",
    "sg:classifiers":[
        {
            "category":"Retail",
            "subcategory":"Auto Repair",
            "type":"Services"
        }
    ],
    "sg:phone":"+44 20 8890 3191",
    "sg:postcode":"TW13 4JY",
    "sg:province":"Greater London",
    "sg:tags":[
        "modification",
        "garage"
    ],
    "wof:name":"Gold Star Garage",
    "wof:placetype":"venue"
},
  "geometry": {"coordinates":[-0.420357,51.439468],"type":"Point"}
}