{
  "type": "Feature",
  "properties": {
    "addr:full":"Liphook Way, 20/20 Business Park, Allington Maidstone Kent ME16 0LQ",
    "addr:housenumber":"20 / 20",
    "addr:postcode":"me16 0lq",
    "addr:street":"Liphook Way;Business Park",
    "iso:country":"GB",
    "sg:address":"Liphook Way, 20/20 Business Park, Allington",
    "sg:city":"Maidstone",
    "sg:classifiers":[
        {
            "category":"Professional",
            "subcategory":"Printing & Photocopies",
            "type":"Services"
        }
    ],
    "sg:phone":"+44 1622 764504",
    "sg:postcode":"ME16 0LQ",
    "sg:province":"Kent",
    "sg:tags":[
        "computer",
        "tag",
        "label"
    ],
    "wof:name":"Francis Green Ltd.",
    "wof:placetype":"venue"
},
  "geometry": {"coordinates":[0.492387,51.286961],"type":"Point"}
}