{
  "type": "Feature",
  "properties": {
    "iso:country":"GB",
    "sg:address":"Tempo House, 15-21 Falcon Rd",
    "sg:city":"Battersea",
    "sg:classifiers":[
        {
            "category":"Building & Trades",
            "subcategory":"Cleaning & Sanitation",
            "type":"Services"
        }
    ],
    "sg:phone":"+44 20 7223 1212",
    "sg:postcode":"SW11 2PJ",
    "sg:province":"Greater London",
    "sg:tags":[
        "cleaner",
        "window"
    ],
    "wof:name":"Seagrave Cleaning",
    "wof:placetype":"venue"
},
  "geometry": {"coordinates":[-0.171075,51.469105],"type":"Point"}
}