{
  "type": "Feature",
  "properties": {
    "addr:full":"16-17 Clerkenwell Clo Clerkenwell Greater London EC1R 0AA",
    "addr:housenumber":"16-17",
    "addr:postcode":"ec1r 0aa",
    "addr:street":"Clerkenwell Clo",
    "iso:country":"GB",
    "sg:address":"16-17 Clerkenwell Clo",
    "sg:city":"Clerkenwell",
    "sg:classifiers":[
        {
            "category":"Professional",
            "subcategory":"Computer Services",
            "type":"Services"
        }
    ],
    "sg:phone":"+44 20 7505 1700",
    "sg:postcode":"EC1R 0AA",
    "sg:province":"Greater London",
    "sg:tags":[
        "system",
        "software"
    ],
    "wof:name":"Marketing Systems Ltd",
    "wof:placetype":"venue"
},
  "geometry": {"coordinates":[-0.1051440015,51.5228042603],"type":"Point"}
}