{
  "type": "Feature",
  "properties": {
    "addr:full":"Grosvenor Gardens House, 35-37 Grosvenor Gardens Westminster Greater London SW1W 0BS",
    "addr:housenumber":"35-37",
    "addr:postcode":"sw1w 0bs",
    "addr:street":"Grosvenor;Grosvenor Gardens",
    "iso:country":"GB",
    "sg:address":"Grosvenor Gardens House, 35-37 Grosvenor Gardens",
    "sg:city":"Westminster",
    "sg:classifiers":[
        {
            "category":"Banks & Credit Unions",
            "subcategory":"Investment Brokerage",
            "type":"Services"
        }
    ],
    "sg:phone":"+44 20 7821 5640",
    "sg:postcode":"SW1W 0BS",
    "sg:province":"Greater London",
    "wof:name":"Hunt-tyzack Ltd",
    "wof:placetype":"venue"
},
  "geometry": {"coordinates":[-0.14535,51.496948],"type":"Point"}
}