{
  "type": "Feature",
  "properties": {
    "addr:full":"Brook Street Wakefield West Yorkshire WF1 1QW",
    "addr:postcode":"wf1 1qw",
    "addr:street":"Brook Street",
    "iso:country":"GB",
    "sg:address":"Brook Street",
    "sg:city":"Wakefield",
    "sg:classifiers":[
        {
            "category":"Travel",
            "subcategory":"Hotels & Motels",
            "type":"Entertainment"
        }
    ],
    "sg:phone":"+44 1924 376804",
    "sg:postcode":"WF1 1QW",
    "sg:province":"West Yorkshire",
    "wof:name":"Fleece Hotel",
    "wof:placetype":"venue"
},
  "geometry": {"coordinates":[-1.4966789484,53.6836585999],"type":"Point"}
}