{
  "type": "Feature",
  "properties": {
    "iso:country":"GB",
    "sg:address":"Golden Rigg, Golden Gro",
    "sg:city":"Whitby",
    "sg:classifiers":[
        {
            "category":"Building & Trades",
            "subcategory":"Construction",
            "type":"Services"
        }
    ],
    "sg:postcode":"YO22 5HH",
    "sg:province":"North Yorkshire",
    "sg:tags":[
        "builder"
    ],
    "wof:name":"T Parkes",
    "wof:placetype":"venue"
},
  "geometry": {"coordinates":[-0.736759,54.431931],"type":"Point"}
}