{
  "type": "Feature",
  "properties": {
    "addr:full":"Richmond Walk, Devonport Plymouth Devon PL1 4LL",
    "addr:postcode":"pl1 4ll",
    "addr:street":"Richmond Walk",
    "iso:country":"GB",
    "sg:address":"Richmond Walk, Devonport",
    "sg:city":"Plymouth",
    "sg:classifiers":[
        {
            "category":"Wholesale",
            "subcategory":"Vending Machines",
            "type":"Manufacturing & Wholesale Goods"
        }
    ],
    "sg:phone":"+44 1752 562223",
    "sg:postcode":"PL1 4LL",
    "sg:province":"Devon",
    "sg:tags":[
        "sale"
    ],
    "wof:name":"V H Graddon & Sons (Catervend) Ltd.",
    "wof:placetype":"venue"
},
  "geometry": {"coordinates":[-4.1691088676,50.364818573],"type":"Point"}
}