{
  "type": "Feature",
  "properties": {
    "iso:country":"GB",
    "sg:address":"30 Mill Street, Bedford",
    "sg:city":"Bedford",
    "sg:classifiers":[
        {
            "category":"Professional",
            "subcategory":"Accounting & Tax Preparation",
            "type":"Services"
        }
    ],
    "sg:postcode":"MK40 3HD",
    "sg:province":"Bedfordshire",
    "sg:tags":[
        "accountant"
    ],
    "wof:name":"Novakovic & Co Ltd",
    "wof:placetype":"venue"
},
  "geometry": {"coordinates":[-0.464562,52.13707],"type":"Point"}
}