{
  "type": "Feature",
  "properties": {
    "addr:full":"24 Axholme Road Doncaster South Yorkshire DN2 4AW",
    "addr:housenumber":"24",
    "addr:postcode":"dn2 4aw",
    "addr:street":"Axholme Road",
    "iso:country":"GB",
    "sg:address":"24 Axholme Road",
    "sg:city":"Doncaster",
    "sg:classifiers":[
        {
            "category":"Building & Trades",
            "subcategory":"Construction",
            "type":"Services"
        }
    ],
    "sg:postcode":"DN2 4AW",
    "sg:province":"South Yorkshire",
    "sg:tags":[
        "guttering"
    ],
    "wof:name":"A1 Rafter Roofing",
    "wof:placetype":"venue"
},
  "geometry": {"coordinates":[-1.1184420586,53.5306510925],"type":"Point"}
}