{
  "type": "Feature",
  "properties": {
    "iso:country":"GB",
    "sg:address":"100 Park Road, Timperley",
    "sg:city":"Altrincham",
    "sg:classifiers":[
        {
            "category":"Government",
            "subcategory":"Post Office",
            "type":"Public Place"
        }
    ],
    "sg:phone":"+44 161 973 5072",
    "sg:postcode":"WA15 6TE",
    "sg:province":"Cheshire",
    "wof:name":"Timperley Station Post Office",
    "wof:placetype":"venue"
},
  "geometry": {"coordinates":[-2.336955,53.403427],"type":"Point"}
}