{
  "type": "Feature",
  "properties": {
    "addr:full":"Wantage Road Wallingford Oxfordshire OX10 0LL",
    "addr:postcode":"ox10 0ll",
    "addr:street":"Wantage Road",
    "iso:country":"GB",
    "sg:address":"Wantage Road",
    "sg:city":"Wallingford",
    "sg:classifiers":[
        {
            "category":"Social Services",
            "subcategory":"Retirement Home",
            "type":"Services"
        }
    ],
    "sg:phone":"+44 1491 836332",
    "sg:postcode":"OX10 0LL",
    "sg:province":"Oxfordshire",
    "sg:tags":[
        "residential",
        "care"
    ],
    "wof:name":"Blue Mountains",
    "wof:placetype":"venue"
},
  "geometry": {"coordinates":[-1.144576,51.610497],"type":"Point"}
}