{
  "type": "Feature",
  "properties": {
    "iso:country":"GB",
    "sg:address":"104 Shaftesbury Avenue",
    "sg:city":"London",
    "sg:classifiers":[
        {
            "category":"Banks & Credit Unions",
            "subcategory":"Bureau De Change",
            "type":"Services"
        }
    ],
    "sg:phone":"+44 20 7437 6590",
    "sg:postcode":"W1D 5EG",
    "sg:province":"Greater London",
    "wof:name":"Mohammed Manjouna",
    "wof:placetype":"venue"
},
  "geometry": {"coordinates":[-0.131005,51.512222],"type":"Point"}
}