{
  "type": "Feature",
  "properties": {
    "addr:full":"15 Wharncliffe, Dodworth Barnsley South Yorkshire S75 3QA",
    "addr:housenumber":"15",
    "addr:postcode":"s75 3qa",
    "addr:street":"Yorkshire",
    "iso:country":"GB",
    "sg:address":"15 Wharncliffe, Dodworth",
    "sg:city":"Barnsley",
    "sg:classifiers":[
        {
            "category":"Social Services",
            "subcategory":"Adult Care",
            "type":"Services"
        }
    ],
    "sg:postcode":"S75 3QA",
    "sg:province":"South Yorkshire",
    "sg:tags":[
        "housing",
        "sheltered"
    ],
    "wof:name":"Wharncliffe",
    "wof:placetype":"venue"
},
  "geometry": {"coordinates":[-1.510509,53.53194],"type":"Point"}
}