{
  "type": "Feature",
  "properties": {
    "iso:country":"GB",
    "sg:address":"Rear Of Spout Lane, Concord",
    "sg:city":"Washington",
    "sg:classifiers":[
        {
            "category":"Shopping",
            "subcategory":"Pets & Pet Supplies",
            "type":"Retail Goods"
        }
    ],
    "sg:phone":"+44 191 419 1600",
    "sg:postcode":"NE37 2AH",
    "sg:province":"Tyne and Wear",
    "sg:tags":[
        "food"
    ],
    "wof:name":"Washington Pet & Garden",
    "wof:placetype":"venue"
},
  "geometry": {"coordinates":[-1.5211,54.911289],"type":"Point"}
}