{
  "type": "Feature",
  "properties": {
    "iso:country":"GB",
    "sg:address":"Gleaston Castle, Gleaston",
    "sg:city":"Ulverston",
    "sg:classifiers":[
        {
            "category":"Farming",
            "subcategory":"Farm",
            "type":"Manufacturing & Wholesale Goods"
        }
    ],
    "sg:phone":"+44 1229 869200",
    "sg:postcode":"LA12 0QH",
    "sg:province":"Cumbria",
    "sg:tags":[
        "mixed",
        "crop"
    ],
    "wof:name":"W S & E M Webster",
    "wof:placetype":"venue"
},
  "geometry": {"coordinates":[-3.1392400265,54.1278991699],"type":"Point"}
}