{
  "type": "Feature",
  "properties": {
    "addr:full":"31 Bicknell Street Blackburn Lancashire BB1 7EY",
    "addr:housenumber":"31",
    "addr:postcode":"bb1 7ey",
    "addr:street":"Bicknell Street",
    "iso:country":"GB",
    "sg:address":"31 Bicknell Street",
    "sg:city":"Blackburn",
    "sg:classifiers":[
        {
            "category":"Education",
            "subcategory":"School",
            "type":"Public Place"
        }
    ],
    "sg:phone":"+44 1254 54021",
    "sg:postcode":"BB1 7EY",
    "sg:province":"Lancashire",
    "sg:tags":[
        "independent",
        "preparatory"
    ],
    "wof:name":"T I Girls High School",
    "wof:placetype":"venue"
},
  "geometry": {"coordinates":[-2.4853720665,53.7533416748],"type":"Point"}
}