{
  "type": "Feature",
  "properties": {
    "iso:country":"GB",
    "sg:address":"Unit 56/57",
    "sg:city":"Newcastle-upon-tyne",
    "sg:classifiers":[
        {
            "category":"Shopping",
            "subcategory":"Comic Books",
            "type":"Retail Goods"
        }
    ],
    "sg:phone":"+44 191 261 7312",
    "sg:postcode":"NE1 5QQ",
    "sg:province":"Tyne and Wear",
    "sg:tags":[
        "jeweller"
    ],
    "wof:name":"King Robert",
    "wof:placetype":"venue"
},
  "geometry": {"coordinates":[-1.61493,54.972912],"type":"Point"}
}