{
  "type": "Feature",
  "properties": {
    "addr:full":"7 Stapleford Welwyn Garden City Hertfordshire AL7 2PD",
    "addr:housenumber":"7",
    "addr:postcode":"al7 2pd",
    "addr:street":"Stapleford Welwyn",
    "iso:country":"GB",
    "sg:address":"7 Stapleford",
    "sg:city":"Welwyn Garden City",
    "sg:classifiers":[
        {
            "category":"Education",
            "subcategory":"Special Training",
            "type":"Public Place"
        }
    ],
    "sg:phone":"+44 1707 372037",
    "sg:postcode":"AL7 2PD",
    "sg:province":"Hertfordshire",
    "sg:tags":[
        "product",
        "centre"
    ],
    "wof:name":"Powertrain Ltd",
    "wof:placetype":"venue"
},
  "geometry": {"coordinates":[-0.166646,51.79911],"type":"Point"}
}