{
  "type": "Feature",
  "properties": {
    "iso:country":"GB",
    "sg:address":"Millthorpe Business Centre",
    "sg:city":"Wakefield",
    "sg:classifiers":[
        {
            "category":"Shopping",
            "subcategory":"Stationery & Office Supplies",
            "type":"Retail Goods"
        }
    ],
    "sg:phone":"+44 1924 380740",
    "sg:postcode":"WF2 7XA",
    "sg:province":"West Yorkshire",
    "sg:tags":[
        "printers'"
    ],
    "wof:name":"Title Plastics",
    "wof:placetype":"venue"
},
  "geometry": {"coordinates":[-1.489134,53.664379],"type":"Point"}
}