{
  "type": "Feature",
  "properties": {
    "addr:full":"Unit 34, Vinehall Farm, Vinehall Rd, Mountfield Robertsbridge East Sussex TN32 5JW",
    "addr:housenumber":"unit 34 vinehall farm",
    "addr:postcode":"tn32 5jw",
    "addr:street":"Vinehall Rd",
    "iso:country":"GB",
    "sg:address":"Unit 34, Vinehall Farm, Vinehall Rd, Mountfield",
    "sg:city":"Robertsbridge",
    "sg:classifiers":[
        {
            "category":"Home & Garden",
            "subcategory":"Kitchen Supply",
            "type":"Retail Goods"
        }
    ],
    "sg:phone":"+44 1424 870022",
    "sg:postcode":"TN32 5JW",
    "sg:province":"East Sussex",
    "sg:tags":[
        "ware"
    ],
    "wof:name":"Gallery Kitchens",
    "wof:placetype":"venue"
},
  "geometry": {"coordinates":[0.47447,50.985649],"type":"Point"}
}