{
  "type": "Feature",
  "properties": {
    "addr:full":"18 The Esplanade Weymouth Dorset DT4 8DT",
    "addr:housenumber":"18",
    "addr:postcode":"dt4 8dt",
    "addr:street":"The Esplanade",
    "iso:country":"GB",
    "sg:address":"18 The Esplanade",
    "sg:city":"Weymouth",
    "sg:classifiers":[
        {
            "category":"Place Of Worship",
            "type":"Public Place"
        }
    ],
    "sg:phone":"+44 1305 787778",
    "sg:postcode":"DT4 8DT",
    "sg:province":"Dorset",
    "wof:name":"Weymouth baptist Church Office",
    "wof:placetype":"venue"
},
  "geometry": {"coordinates":[-2.4517149925,50.6086425781],"type":"Point"}
}