{
  "type": "Feature",
  "properties": {
    "addr:full":"Unit 9, Lockwood Way London Greater London E17 5RB",
    "addr:housenumber":"unit 9",
    "addr:postcode":"e17 5rb",
    "addr:street":"Lockwood Way",
    "iso:country":"GB",
    "sg:address":"Unit 9, Lockwood Way",
    "sg:city":"London",
    "sg:classifiers":[
        {
            "category":"Manufacturing",
            "subcategory":"Wood Products",
            "type":"Manufacturing & Wholesale Goods"
        }
    ],
    "sg:phone":"+44 20 8531 3130",
    "sg:postcode":"E17 5RB",
    "sg:province":"Greater London",
    "sg:tags":[
        "packaging",
        "crate",
        "pallets"
    ],
    "wof:name":"Global Packaging 1989 Ltd.",
    "wof:placetype":"venue"
},
  "geometry": {"coordinates":[-0.041989,51.595581],"type":"Point"}
}