{
  "type": "Feature",
  "properties": {
    "addr:full":"36 High Street Narberth Carmarthenshire SA67 7AS",
    "addr:housenumber":"36",
    "addr:postcode":"sa67 7as",
    "addr:street":"High Street",
    "iso:country":"GB",
    "sg:address":"36 High Street",
    "sg:city":"Narberth",
    "sg:classifiers":[
        {
            "category":"Food & Beverages",
            "subcategory":"Groceries & Convenience Stores",
            "type":"Retail Goods"
        }
    ],
    "sg:phone":"+44 1834 860273",
    "sg:postcode":"SA67 7AS",
    "sg:province":"Carmarthenshire",
    "wof:name":"Spar Stores",
    "wof:placetype":"venue"
},
  "geometry": {"coordinates":[-4.7441101074,51.7987785339],"type":"Point"}
}