{
  "type": "Feature",
  "properties": {
    "addr:full":"58 Charter Ho, Lord Montgomery Way Portsmouth Hampshire PO1 2SB",
    "addr:housenumber":"58",
    "addr:postcode":"hampshire po1 2sb",
    "addr:street":"Charter Ho;Montgomery Way",
    "iso:country":"GB",
    "sg:address":"58 Charter Ho, Lord Montgomery Way",
    "sg:city":"Portsmouth",
    "sg:classifiers":[
        {
            "category":"Community Center",
            "subcategory":"Youth",
            "type":"Public Place"
        }
    ],
    "sg:phone":"+44 23 9286 4006",
    "sg:postcode":"PO1 2SB",
    "sg:province":"Hampshire",
    "sg:tags":[
        "organisation",
        "centre"
    ],
    "wof:name":"Scout Association The",
    "wof:placetype":"venue"
},
  "geometry": {"coordinates":[-1.095306,50.794834],"type":"Point"}
}