{
  "type": "Feature",
  "properties": {
    "iso:country":"GB",
    "sg:address":"Summer Hill Rd, Ladywood",
    "sg:city":"Birmingham",
    "sg:classifiers":[
        {
            "category":"Shopping",
            "subcategory":"Stationery & Office Supplies",
            "type":"Retail Goods"
        }
    ],
    "sg:phone":"+44 121 236 6636",
    "sg:postcode":"B1 3RH",
    "sg:province":"West Midlands",
    "sg:tags":[
        "equipment"
    ],
    "wof:name":"Office World",
    "wof:placetype":"venue"
},
  "geometry": {"coordinates":[-1.918032,52.484135],"type":"Point"}
}