{
  "type": "Feature",
  "properties": {
    "addr:full":"38 Queens Road Buckhurst Hill Essex IG9 5BY",
    "addr:housenumber":"38",
    "addr:postcode":"ig9 5by",
    "addr:street":"Queens Road",
    "iso:country":"GB",
    "sg:address":"38 Queens Road",
    "sg:city":"Buckhurst Hill",
    "sg:classifiers":[
        {
            "category":"Shopping",
            "subcategory":"Clothing, Apparel, & Fashions",
            "type":"Retail Goods"
        }
    ],
    "sg:phone":"+44 20 8505 9155",
    "sg:postcode":"IG9 5BY",
    "sg:province":"Essex",
    "sg:tags":[
        "shop"
    ],
    "wof:name":"Anita At Creme Ltd.",
    "wof:placetype":"venue"
},
  "geometry": {"coordinates":[0.044306,51.625137],"type":"Point"}
}