{
  "type": "Feature",
  "properties": {
    "addr:full":"9 Nestles Avenue Hayes Greater London UB3 4SA",
    "addr:housenumber":"9",
    "addr:postcode":"ub3 4sa",
    "addr:street":"Nestles Avenue",
    "iso:country":"GB",
    "sg:address":"9 Nestles Avenue",
    "sg:city":"Hayes",
    "sg:classifiers":[
        {
            "category":"Professional",
            "subcategory":"Printing & Photocopies",
            "type":"Services"
        }
    ],
    "sg:phone":"+44 20 8581 5151",
    "sg:postcode":"UB3 4SA",
    "sg:province":"Greater London",
    "sg:tags":[
        "printer"
    ],
    "wof:name":"Victoria Realty Ltd.",
    "wof:placetype":"venue"
},
  "geometry": {"coordinates":[-0.4221200049,51.5018615723],"type":"Point"}
}