{
  "type": "Feature",
  "properties": {
    "addr:full":"109 Mickleburgh Hill Herne Bay Kent CT6 6JZ",
    "addr:housenumber":"109",
    "addr:postcode":"ct6 6jz",
    "addr:street":"Mickleburgh Hill Herne",
    "iso:country":"GB",
    "sg:address":"109 Mickleburgh Hill",
    "sg:city":"Herne Bay",
    "sg:classifiers":[
        {
            "category":"Home & Garden",
            "subcategory":"Carpets & Floor Coverings",
            "type":"Retail Goods"
        }
    ],
    "sg:phone":"+44 1227 360076",
    "sg:postcode":"CT6 6JZ",
    "sg:province":"Kent",
    "sg:tags":[
        "cleaner",
        "upholstery"
    ],
    "wof:name":"Les Howard & Son-Carpet Care",
    "wof:placetype":"venue"
},
  "geometry": {"coordinates":[1.143842,51.365108],"type":"Point"}
}