{
  "type": "Feature",
  "properties": {
    "addr:full":"45 Camberwell New Road London Greater London SE5 0RZ",
    "addr:housenumber":"45",
    "addr:postcode":"se5 0rz",
    "addr:street":"Camberwell New Road",
    "iso:country":"GB",
    "sg:address":"45 Camberwell New Road",
    "sg:city":"London",
    "sg:classifiers":[
        {
            "category":"Personal",
            "subcategory":"Beauty Salon",
            "type":"Services"
        }
    ],
    "sg:phone":"+44 20 7582 8092",
    "sg:postcode":"SE5 0RZ",
    "sg:province":"Greater London",
    "sg:tags":[
        "unisex",
        "hairdresser"
    ],
    "wof:name":"Hair Talk",
    "wof:placetype":"venue"
},
  "geometry": {"coordinates":[-0.094166,51.483322],"type":"Point"}
}