{
  "type": "Feature",
  "properties": {
    "iso:country":"GB",
    "sg:address":"3 The Mews Home Farm, Brickendon Bury, Brickendon",
    "sg:city":"Hertford",
    "sg:classifiers":[
        {
            "category":"Professional",
            "subcategory":"Art Services",
            "type":"Services"
        }
    ],
    "sg:phone":"+44 1992 504390",
    "sg:postcode":"SG13 8NP",
    "sg:province":"Hertfordshire",
    "sg:tags":[
        "consultant",
        "design"
    ],
    "wof:name":"Destech (U K) Ltd.",
    "wof:placetype":"venue"
},
  "geometry": {"coordinates":[-0.084236,51.755196],"type":"Point"}
}