{
  "type": "Feature",
  "properties": {
    "addr:full":"129 New Union St Coventry West Midlands CV1 2NT",
    "addr:housenumber":"129",
    "addr:postcode":"cv1 2nt",
    "addr:street":"New Union St",
    "iso:country":"GB",
    "sg:address":"129 New Union St",
    "sg:city":"Coventry",
    "sg:classifiers":[
        {
            "category":"Real Estate",
            "subcategory":"Architect",
            "type":"Services"
        }
    ],
    "sg:postcode":"CV1 2NT",
    "sg:province":"West Midlands",
    "wof:name":"Hatwood,Keith,",
    "wof:placetype":"venue"
},
  "geometry": {"coordinates":[-1.510534,52.405067],"type":"Point"}
}