{
  "type": "Feature",
  "properties": {
    "addr:full":"261 Kilburn High Rd London Greater London NW6 7JR",
    "addr:housenumber":"261",
    "addr:postcode":"nw6 7jr",
    "addr:street":"Kilburn High Rd",
    "iso:country":"GB",
    "sg:address":"261 Kilburn High Rd",
    "sg:city":"London",
    "sg:classifiers":[
        {
            "category":"Shopping",
            "subcategory":"Crafts & Fabrics",
            "type":"Retail Goods"
        }
    ],
    "sg:postcode":"NW6 7JR",
    "sg:province":"Greater London",
    "sg:tags":[
        "material",
        "art"
    ],
    "wof:name":"Patel,Jayendra R,",
    "wof:placetype":"venue"
},
  "geometry": {"coordinates":[-0.199723,51.543159],"type":"Point"}
}