{
  "type": "Feature",
  "properties": {
    "addr:full":"22 Gale Rd, Litherland Liverpool Merseyside L21 7QR",
    "addr:housenumber":"22",
    "addr:postcode":"l21 7qr",
    "addr:street":"Gale Rd",
    "iso:country":"GB",
    "sg:address":"22 Gale Rd, Litherland",
    "sg:city":"Liverpool",
    "sg:classifiers":[
        {
            "category":"Organizations",
            "subcategory":"Non-profit Organization",
            "type":"Services"
        }
    ],
    "sg:phone":"+44 151 920 2686",
    "sg:postcode":"L21 7QR",
    "sg:province":"Merseyside",
    "sg:tags":[
        "organisation",
        "voluntary",
        "charity"
    ],
    "wof:name":"The Pride of Sefton",
    "wof:placetype":"venue"
},
  "geometry": {"coordinates":[-2.994548,53.474964],"type":"Point"}
}