{
  "type": "Feature",
  "properties": {
    "addr:full":"17 Sundridge Avenue Bromley Kent BR1 2PU",
    "addr:housenumber":"17",
    "addr:postcode":"br1 2pu",
    "addr:street":"Sundridge Avenue",
    "iso:country":"GB",
    "sg:address":"17 Sundridge Avenue",
    "sg:city":"Bromley",
    "sg:classifiers":[
        {
            "category":"Professional",
            "type":"Services"
        }
    ],
    "sg:phone":"+44 20 8290 1599",
    "sg:postcode":"BR1 2PU",
    "sg:province":"Kent",
    "sg:tags":[
        "repair",
        "tech",
        "maintenance"
    ],
    "wof:name":"Key Systems",
    "wof:placetype":"venue"
},
  "geometry": {"coordinates":[0.0343910009,51.4091873169],"type":"Point"}
}