{
  "type": "Feature",
  "properties": {
    "iso:country":"GB",
    "sg:address":"Sheepscar St South",
    "sg:city":"Leeds",
    "sg:classifiers":[
        {
            "category":"Bars & Pubs",
            "type":"Food & Drink"
        }
    ],
    "sg:phone":"+44 113 243 2378",
    "sg:postcode":"LS7 1AD",
    "sg:province":"West Yorkshire",
    "sg:tags":[
        "pubs",
        "inn"
    ],
    "wof:name":"The Pointers Inn Fact",
    "wof:placetype":"venue"
},
  "geometry": {"coordinates":[-1.534638,53.807739],"type":"Point"}
}