{
  "type": "Feature",
  "properties": {
    "addr:full":"12 High Street, Flitwick Bedford Bedfordshire MK45 1DS",
    "addr:housenumber":"12",
    "addr:postcode":"mk45 1ds",
    "addr:street":"High Street",
    "iso:country":"GB",
    "sg:address":"12 High Street, Flitwick",
    "sg:city":"Bedford",
    "sg:classifiers":[
        {
            "category":"Professional",
            "subcategory":"Detective & Security Services",
            "type":"Services"
        }
    ],
    "sg:postcode":"MK45 1DS",
    "sg:province":"Bedfordshire",
    "wof:name":"Curzon Security Ltd.",
    "wof:placetype":"venue"
},
  "geometry": {"coordinates":[-0.4951600134,52.0046691895],"type":"Point"}
}