{
  "type": "Feature",
  "properties": {
    "iso:country":"GB",
    "sg:address":"Broadway Rd, Childswickham",
    "sg:city":"Broadway",
    "sg:classifiers":[
        {
            "category":"Retail",
            "subcategory":"Auto Repair",
            "type":"Services"
        }
    ],
    "sg:phone":"+44 1386 852311",
    "sg:postcode":"WR12 7HD",
    "sg:province":"Gloucestershire",
    "sg:tags":[
        "modification",
        "garage"
    ],
    "wof:name":"Alan Aston",
    "wof:placetype":"venue"
},
  "geometry": {"coordinates":[-1.884749,52.045235],"type":"Point"}
}