{
  "type": "Feature",
  "properties": {
    "addr:full":"38 George Street Stranraer Dumfries and Galloway DG9 7RL",
    "addr:housenumber":"38",
    "addr:postcode":"dg9 7rl",
    "addr:street":"George Street",
    "iso:country":"GB",
    "sg:address":"38 George Street",
    "sg:city":"Stranraer",
    "sg:classifiers":[
        {
            "category":"Shopping",
            "subcategory":"Pharmacy",
            "type":"Retail Goods"
        }
    ],
    "sg:postcode":"DG9 7RL",
    "sg:province":"Dumfries and Galloway",
    "sg:tags":[
        "pharmacist",
        "chemist"
    ],
    "wof:name":"Richard Ker & Son",
    "wof:placetype":"venue"
},
  "geometry": {"coordinates":[-5.027601,54.904839],"type":"Point"}
}