{
  "type": "Feature",
  "properties": {
    "addr:full":"13 Queen Charlotte Street Edinburgh City of Edinburgh EH6 6BA",
    "addr:housenumber":"13",
    "addr:postcode":"eh6 6ba",
    "addr:street":"Queen Charlotte Street",
    "iso:country":"GB",
    "sg:address":"13 Queen Charlotte Street",
    "sg:city":"Edinburgh",
    "sg:classifiers":[
        {
            "category":"Personal",
            "subcategory":"Beauty Salon",
            "type":"Services"
        }
    ],
    "sg:phone":"+44 131 554 6641",
    "sg:postcode":"EH6 6BA",
    "sg:province":"City of Edinburgh",
    "sg:tags":[
        "ladies",
        "lady",
        "hairdresser"
    ],
    "wof:name":"Charlotte",
    "wof:placetype":"venue"
},
  "geometry": {"coordinates":[-3.1691870689,55.9741973877],"type":"Point"}
}