{
  "type": "Feature",
  "properties": {
    "addr:full":"Unit 2/3 Cambridge Cambridgeshire CB1 3EW",
    "addr:housenumber":"unit 2 / 3",
    "addr:postcode":"cb1 3ew",
    "iso:country":"GB",
    "sg:address":"Unit 2/3",
    "sg:city":"Cambridge",
    "sg:classifiers":[
        {
            "category":"Manufacturing",
            "subcategory":"Signs",
            "type":"Manufacturing & Wholesale Goods"
        }
    ],
    "sg:phone":"+44 1223 212151",
    "sg:postcode":"CB1 3EW",
    "sg:province":"Cambridgeshire",
    "sg:tags":[
        "supplier",
        "nameplate"
    ],
    "wof:name":"ALGAR SIGNCRAFT SERVICES (CAMBRIDGE) LTD",
    "wof:placetype":"venue"
},
  "geometry": {"coordinates":[0.14865,52.207561],"type":"Point"}
}