{
  "type": "Feature",
  "properties": {
    "iso:country":"GB",
    "sg:address":"43 Brentwood Place",
    "sg:city":"Brentwood",
    "sg:classifiers":[
        {
            "category":"Manufacturing",
            "subcategory":"Signs",
            "type":"Manufacturing & Wholesale Goods"
        }
    ],
    "sg:phone":"+44 1277 229954",
    "sg:postcode":"CM15 9DW",
    "sg:province":"Essex",
    "sg:tags":[
        "writer"
    ],
    "wof:name":"Auton & Harms Ltd.",
    "wof:placetype":"venue"
},
  "geometry": {"coordinates":[0.304668,51.624172],"type":"Point"}
}