{
  "type": "Feature",
  "properties": {
    "addr:full":"1176 Warwick Road, Acocks Green Birmingham West Midlands B27 6BS",
    "addr:housenumber":"1176",
    "addr:postcode":"b27 6bs",
    "addr:street":"Warwick Road",
    "iso:country":"GB",
    "sg:address":"1176 Warwick Road, Acocks Green",
    "sg:city":"Birmingham",
    "sg:classifiers":[
        {
            "category":"Home & Garden",
            "subcategory":"Furniture",
            "type":"Retail Goods"
        }
    ],
    "sg:phone":"+44 121 603 3344",
    "sg:postcode":"B27 6BS",
    "sg:province":"West Midlands",
    "wof:name":"T & Lewis David O'Sullivan",
    "wof:placetype":"venue"
},
  "geometry": {"coordinates":[-1.817369,52.445793],"type":"Point"}
}