{
  "type": "Feature",
  "properties": {
    "addr:full":"66 Rutland Road Stamford Cambridgeshire PE9 1UW",
    "addr:housenumber":"66",
    "addr:postcode":"pe9 1uw",
    "addr:street":"Rutland Road",
    "iso:country":"GB",
    "sg:address":"66 Rutland Road",
    "sg:city":"Stamford",
    "sg:classifiers":[
        {
            "category":"Building & Trades",
            "subcategory":"Construction",
            "type":"Services"
        }
    ],
    "sg:phone":"+44 1780 753940",
    "sg:postcode":"PE9 1UW",
    "sg:province":"Cambridgeshire",
    "sg:tags":[
        "roofing"
    ],
    "wof:name":"John Middleton Roofing",
    "wof:placetype":"venue"
},
  "geometry": {"coordinates":[-0.4683330059,52.6636199951],"type":"Point"}
}