{
  "type": "Feature",
  "properties": {
    "addr:full":"19 Ashton Clough Road Liversedge West Yorkshire WF15 6JX",
    "addr:housenumber":"19",
    "addr:postcode":"wf15 6jx",
    "addr:street":"Ashton Clough Road",
    "iso:country":"GB",
    "sg:address":"19 Ashton Clough Road",
    "sg:city":"Liversedge",
    "sg:classifiers":[
        {
            "category":"Retail",
            "subcategory":"Storage",
            "type":"Services"
        }
    ],
    "sg:postcode":"WF15 6JX",
    "sg:province":"West Yorkshire",
    "sg:tags":[
        "household",
        "removal"
    ],
    "wof:name":"Hiab Wagon Hire",
    "wof:placetype":"venue"
},
  "geometry": {"coordinates":[-1.6928880215,53.7093696594],"type":"Point"}
}