{
  "type": "Feature",
  "properties": {
    "addr:full":"23 The Broadway London Greater London N8 8DU",
    "addr:housenumber":"23",
    "addr:postcode":"n8 8du",
    "addr:street":"The Broadway",
    "iso:country":"GB",
    "sg:address":"23 The Broadway",
    "sg:city":"London",
    "sg:classifiers":[
        {
            "category":"Food & Beverages",
            "subcategory":"Supermarket",
            "type":"Retail Goods"
        }
    ],
    "sg:phone":"+44 20 8340 9636",
    "sg:postcode":"N8 8DU",
    "sg:province":"Greater London",
    "wof:name":"Budgens Stores Ltd.",
    "wof:placetype":"venue"
},
  "geometry": {"coordinates":[-0.1240409985,51.5790710449],"type":"Point"}
}