{
  "type": "Feature",
  "properties": {
    "addr:full":"23 Llanberis Close, Tonteg Pontypridd Rhondda, Cynon, Taff CF38 1HR",
    "addr:housenumber":"23",
    "addr:postcode":"tonteg;cf38 1hr",
    "addr:street":"Llanberis Close",
    "iso:country":"GB",
    "sg:address":"23 Llanberis Close, Tonteg",
    "sg:city":"Pontypridd",
    "sg:classifiers":[
        {
            "category":"Home & Garden",
            "subcategory":"Household Appliances",
            "type":"Retail Goods"
        }
    ],
    "sg:phone":"+44 1443 203423",
    "sg:postcode":"CF38 1HR",
    "sg:province":"Rhondda, Cynon, Taff",
    "sg:tags":[
        "refrigeration",
        "air conditioning"
    ],
    "wof:name":"Page & Fisher Refrigeration",
    "wof:placetype":"venue"
},
  "geometry": {"coordinates":[-3.323281,51.572025],"type":"Point"}
}