{
  "type": "Feature",
  "properties": {
    "addr:full":"46 Field Place, Naish Estate New Milton Hampshire BH25 7RD",
    "addr:housenumber":"46",
    "addr:postcode":"bh25 7rd",
    "addr:street":"Field Place Naish Estate",
    "iso:country":"GB",
    "sg:address":"46 Field Place, Naish Estate",
    "sg:city":"New Milton",
    "sg:classifiers":[
        {
            "category":"Building & Trades",
            "subcategory":"Construction",
            "type":"Services"
        }
    ],
    "sg:phone":"+44 1425 619499",
    "sg:postcode":"BH25 7RD",
    "sg:province":"Hampshire",
    "sg:tags":[
        "decorator",
        "painter"
    ],
    "wof:name":"R J Smith",
    "wof:placetype":"venue"
},
  "geometry": {"coordinates":[-1.671652,50.757618],"type":"Point"}
}