{
  "type": "Feature",
  "properties": {
    "addr:full":"Express House, Southgate Wakefield West Yorkshire WF1 1TE",
    "addr:postcode":"wf1 1te",
    "addr:street":"Southgate Wakefield West",
    "iso:country":"GB",
    "sg:address":"Express House, Southgate",
    "sg:city":"Wakefield",
    "sg:classifiers":[
        {
            "category":"Travel",
            "subcategory":"Travel Agent",
            "type":"Entertainment"
        }
    ],
    "sg:phone":"+44 1924 433015",
    "sg:postcode":"WF1 1TE",
    "sg:province":"West Yorkshire",
    "sg:tags":[
        "agency",
        "activity"
    ],
    "wof:name":"Out & About",
    "wof:placetype":"venue"
},
  "geometry": {"coordinates":[-1.4966160059,53.6810951233],"type":"Point"}
}