{
  "type": "Feature",
  "properties": {
    "iso:country":"GB",
    "sg:address":"Langdon Park Rd",
    "sg:city":"Highgate",
    "sg:classifiers":[
        {
            "category":"Place Of Worship",
            "type":"Public Place"
        }
    ],
    "sg:phone":"+44 20 8340 3567",
    "sg:postcode":"N6 5BH",
    "sg:province":"Greater London",
    "wof:name":"St Augustine's C Of E Church",
    "wof:placetype":"venue"
},
  "geometry": {"coordinates":[-0.1399050057,51.5742683411],"type":"Point"}
}