{
  "type": "Feature",
  "properties": {
    "iso:country":"GB",
    "sg:address":"112 The Bdwy",
    "sg:city":"Southall",
    "sg:classifiers":[
        {
            "category":"Restaurant",
            "type":"Food & Drink"
        }
    ],
    "sg:phone":"+44 20 8571 2100",
    "sg:postcode":"UB1 1QF",
    "sg:province":"Greater London",
    "wof:name":"Rita's Samosa Centre",
    "wof:placetype":"venue"
},
  "geometry": {"coordinates":[-0.3785090148,51.511051178],"type":"Point"}
}