{
  "type": "Feature",
  "properties": {
    "addr:full":"22 Redshaw Road Leeds West Yorkshire LS12 1HH",
    "addr:housenumber":"22",
    "addr:postcode":"ls12 1hh",
    "addr:street":"Redshaw Road",
    "iso:country":"GB",
    "sg:address":"22 Redshaw Road",
    "sg:city":"Leeds",
    "sg:classifiers":[
        {
            "category":"Organizations",
            "subcategory":"Community Association",
            "type":"Services"
        },
        {
            "category":"Organizations",
            "subcategory":"Membership Organization",
            "type":"Services"
        }
    ],
    "sg:phone":"+44 113 263 0255",
    "sg:postcode":"LS12 1HH",
    "sg:province":"West Yorkshire",
    "sg:tags":[
        "club",
        "social"
    ],
    "wof:name":"West Leeds Sports & Social Club",
    "wof:placetype":"venue"
},
  "geometry": {"coordinates":[-1.580229,53.791012],"type":"Point"}
}