{
  "type": "Feature",
  "properties": {
    "addr:full":"38 High Street Newmarket Cambridgeshire CB8 8LB",
    "addr:housenumber":"38",
    "addr:postcode":"cb8 8lb",
    "addr:street":"High Street",
    "iso:country":"GB",
    "sg:address":"38 High Street",
    "sg:city":"Newmarket",
    "sg:classifiers":[
        {
            "category":"Professional",
            "subcategory":"Accounting & Tax Preparation",
            "type":"Services"
        }
    ],
    "sg:phone":"+44 1638 668531",
    "sg:postcode":"CB8 8LB",
    "sg:province":"Cambridgeshire",
    "sg:tags":[
        "accountant"
    ],
    "wof:name":"N T A Tax & Management",
    "wof:placetype":"venue"
},
  "geometry": {"coordinates":[0.407622993,52.244934082],"type":"Point"}
}