{
  "type": "Feature",
  "properties": {
    "addr:full":"Back Byron Road Morecambe Lancashire LA3 1UJ",
    "addr:postcode":"la3 1uj",
    "addr:street":"Back Byron Road",
    "iso:country":"GB",
    "sg:address":"Back Byron Road",
    "sg:city":"Morecambe",
    "sg:classifiers":[
        {
            "category":"Home & Garden",
            "subcategory":"Home Furnishings",
            "type":"Retail Goods"
        }
    ],
    "sg:postcode":"LA3 1UJ",
    "sg:province":"Lancashire",
    "sg:tags":[
        "furnishers",
        "planner",
        "kitchen"
    ],
    "wof:name":"Classic Kitchens",
    "wof:placetype":"venue"
},
  "geometry": {"coordinates":[-2.883034,54.063068],"type":"Point"}
}