{
  "type": "Feature",
  "properties": {
    "iso:country":"GB",
    "sg:address":"Syringa Somnes Avenue",
    "sg:city":"Canvey Island",
    "sg:classifiers":[
        {
            "category":"Utilities",
            "subcategory":"Refuse",
            "type":"Services"
        }
    ],
    "sg:phone":"+44 1268 511777",
    "sg:postcode":"SS8 9QB",
    "sg:province":"Essex",
    "sg:tags":[
        "skip",
        "hire"
    ],
    "wof:name":"K B R Skips",
    "wof:placetype":"venue"
},
  "geometry": {"coordinates":[0.59112,51.520374],"type":"Point"}
}