{
  "type": "Feature",
  "properties": {
    "addr:full":"170 Balham High Road London Greater London SW12 9BW",
    "addr:housenumber":"170",
    "addr:postcode":"sw12 9bw",
    "addr:street":"Balham High Road",
    "iso:country":"GB",
    "sg:address":"170 Balham High Road",
    "sg:city":"London",
    "sg:classifiers":[
        {
            "category":"Shopping",
            "subcategory":"Optician",
            "type":"Retail Goods"
        }
    ],
    "sg:phone":"+44 20 8673 1546",
    "sg:postcode":"SW12 9BW",
    "sg:province":"Greater London",
    "wof:name":"Dollond & Aitchison Ltd.",
    "wof:placetype":"venue"
},
  "geometry": {"coordinates":[-0.1522610039,51.4443511963],"type":"Point"}
}