{
  "type": "Feature",
  "properties": {
    "iso:country":"GB",
    "sg:address":"560 Westhorne Avenue",
    "sg:city":"London",
    "sg:classifiers":[
        {
            "category":"Shopping",
            "subcategory":"Pharmacy",
            "type":"Retail Goods"
        }
    ],
    "sg:phone":"+44 20 8850 1944",
    "sg:postcode":"SE9 6DR",
    "sg:province":"Greater London",
    "sg:tags":[
        "pharmacist",
        "dispensing",
        "chemist"
    ],
    "wof:name":"Anand Pharmacy Ltd.",
    "wof:placetype":"venue"
},
  "geometry": {"coordinates":[0.039708,51.455601],"type":"Point"}
}