{
  "type": "Feature",
  "properties": {
    "iso:country":"GB",
    "sg:address":"14/16 Station Road West",
    "sg:city":"Oxted",
    "sg:classifiers":[
        {
            "category":"Professional",
            "subcategory":"Business Services",
            "type":"Services"
        }
    ],
    "sg:postcode":"RH8 9EP",
    "sg:province":"Surrey",
    "sg:tags":[
        "accomodation"
    ],
    "wof:name":"Eberhart Ltd",
    "wof:placetype":"venue"
},
  "geometry": {"coordinates":[-0.006581,51.256809],"type":"Point"}
}