{
  "type": "Feature",
  "properties": {
    "addr:full":"North West Dock, Wellington Dock Liverpool Merseyside L3 0AR",
    "addr:postcode":"l3 0ar",
    "addr:street":"North West Dock Wellington Dock",
    "iso:country":"GB",
    "sg:address":"North West Dock, Wellington Dock",
    "sg:city":"Liverpool",
    "sg:classifiers":[
        {
            "category":"Home & Garden",
            "subcategory":"Garden Supply",
            "type":"Retail Goods"
        },
        {
            "category":"Home & Garden",
            "subcategory":"Building Materials",
            "type":"Retail Goods"
        }
    ],
    "sg:phone":"+44 151 207 1104",
    "sg:postcode":"L3 0AR",
    "sg:province":"Merseyside",
    "sg:tags":[
        "shale",
        "supplier",
        "sand",
        "including",
        "aggregate",
        "gravel"
    ],
    "wof:name":"Mersey Sand Suppliers",
    "wof:placetype":"venue"
},
  "geometry": {"coordinates":[-2.9991540909,53.4262619019],"type":"Point"}
}