{
  "type": "Feature",
  "properties": {
    "iso:country":"GB",
    "sg:address":"519 Stanhope Road",
    "sg:city":"South Shields",
    "sg:classifiers":[
        {
            "category":"Communications",
            "subcategory":"Film & Video Production",
            "type":"Services"
        }
    ],
    "sg:phone":"+44 191 455 9747",
    "sg:postcode":"NE33 4QA",
    "sg:province":"Tyne and Wear",
    "sg:tags":[
        "tv"
    ],
    "wof:name":"Telesave (South Shields) Ltd.",
    "wof:placetype":"venue"
},
  "geometry": {"coordinates":[-1.4395619631,54.9748344421],"type":"Point"}
}