{
  "type": "Feature",
  "properties": {
    "iso:country":"GB",
    "sg:address":"4 Woodlea Crescent, Crosshouse",
    "sg:city":"Kilmarnock",
    "sg:classifiers":[
        {
            "category":"Bus Charters",
            "type":"Transportation"
        }
    ],
    "sg:phone":"+44 1563 524248",
    "sg:postcode":"KA2 0EW",
    "sg:province":"East Ayrshire",
    "sg:tags":[
        "coach"
    ],
    "wof:name":"Robert Sweetin",
    "wof:placetype":"venue"
},
  "geometry": {"coordinates":[-4.5461378098,55.6146659851],"type":"Point"}
}