{
  "type": "Feature",
  "properties": {
    "iso:country":"GB",
    "sg:address":"4 Webbers Way",
    "sg:city":"Totnes",
    "sg:classifiers":[
        {
            "category":"Shopping",
            "subcategory":"Discount & Variety Stores",
            "type":"Retail Goods"
        }
    ],
    "sg:postcode":"TQ9 6JY",
    "sg:province":"Devon",
    "sg:tags":[
        "cleaning",
        "supply"
    ],
    "wof:name":"C M S Services Ltd.",
    "wof:placetype":"venue"
},
  "geometry": {"coordinates":[-3.688093,50.434147],"type":"Point"}
}