{
  "type": "Feature",
  "properties": {
    "addr:full":"19 Westbury Road London Greater London N12 7NY",
    "addr:housenumber":"19",
    "addr:postcode":"n12 7ny",
    "addr:street":"Westbury Road",
    "iso:country":"GB",
    "sg:address":"19 Westbury Road",
    "sg:city":"London",
    "sg:classifiers":[
        {
            "category":"Shopping",
            "subcategory":"Department Store",
            "type":"Retail Goods"
        }
    ],
    "sg:phone":"+44 20 8343 7809",
    "sg:postcode":"N12 7NY",
    "sg:province":"Greater London",
    "wof:name":"Startling Automata Ltd.",
    "wof:placetype":"venue"
},
  "geometry": {"coordinates":[-0.188277,51.615273],"type":"Point"}
}