{
  "type": "Feature",
  "properties": {
    "iso:country":"GB",
    "sg:address":"7 Hythe Cl, Martello Bay",
    "sg:city":"Clacton-on-sea",
    "sg:classifiers":[
        {
            "category":"Building & Trades",
            "subcategory":"Construction",
            "type":"Services"
        }
    ],
    "sg:postcode":"CO15 1XQ",
    "sg:province":"Essex",
    "sg:tags":[
        "glazier"
    ],
    "wof:name":"Quantlog Ltd",
    "wof:placetype":"venue"
},
  "geometry": {"coordinates":[1.1386430264,51.7825546265],"type":"Point"}
}