{
  "type": "Feature",
  "properties": {
    "addr:full":"Lakeland View, Greengill Penrith Cumbria CA11 8SE",
    "addr:postcode":"ca11 8se",
    "addr:street":"Lakeland;Greengill",
    "iso:country":"GB",
    "sg:address":"Lakeland View, Greengill",
    "sg:city":"Penrith",
    "sg:classifiers":[
        {
            "category":"Recreation",
            "subcategory":"Campground",
            "type":"Entertainment"
        }
    ],
    "sg:phone":"+44 1768 863055",
    "sg:postcode":"CA11 8SE",
    "sg:province":"Cumbria",
    "sg:tags":[
        "caravan",
        "park"
    ],
    "wof:name":"Lakeland View Caravan Site",
    "wof:placetype":"venue"
},
  "geometry": {"coordinates":[-2.7620890141,54.6817932129],"type":"Point"}
}