{
  "type": "Feature",
  "properties": {
    "iso:country":"GB",
    "sg:address":"44 Lillington Road",
    "sg:city":"Leamington Spa",
    "sg:classifiers":[
        {
            "category":"Professional",
            "subcategory":"Management & Consulting",
            "type":"Services"
        }
    ],
    "sg:phone":"+44 1926 334466",
    "sg:postcode":"CV32 5YZ",
    "sg:province":"Warwickshire",
    "sg:tags":[
        "sport"
    ],
    "wof:name":"Sports Administration Services Ltd.",
    "wof:placetype":"venue"
},
  "geometry": {"coordinates":[-1.5307370424,52.2988357544],"type":"Point"}
}