{
  "type": "Feature",
  "properties": {
    "addr:full":"Mulberry House, Little Comberton Pershore Worcestershire WR10 3EP",
    "addr:postcode":"wr10 3ep",
    "iso:country":"GB",
    "sg:address":"Mulberry House, Little Comberton",
    "sg:city":"Pershore",
    "sg:classifiers":[
        {
            "category":"Banks & Credit Unions",
            "subcategory":"Financial Services",
            "type":"Services"
        }
    ],
    "sg:postcode":"WR10 3EP",
    "sg:province":"Worcestershire",
    "sg:tags":[
        "consultant"
    ],
    "wof:name":"Kottler Investments & Developments Ltd.",
    "wof:placetype":"venue"
},
  "geometry": {"coordinates":[-2.0793390274,52.1137657166],"type":"Point"}
}