{
  "type": "Feature",
  "properties": {
    "iso:country":"GB",
    "sg:address":"52 Coburg St",
    "sg:city":"Edinburgh",
    "sg:classifiers":[
        {
            "category":"Food & Beverages",
            "subcategory":"Meat & Fish",
            "type":"Retail Goods"
        }
    ],
    "sg:postcode":"EH6 6HJ",
    "sg:province":"City of Edinburgh",
    "sg:tags":[
        "seafood"
    ],
    "wof:name":"Faber,Francis,",
    "wof:placetype":"venue"
},
  "geometry": {"coordinates":[-3.175749,55.976028],"type":"Point"}
}