{
  "type": "Feature",
  "properties": {
    "iso:country":"GB",
    "sg:address":"Unit 18 Edgwick Pk Indstl Est, Canal Rd",
    "sg:city":"Coventry",
    "sg:classifiers":[
        {
            "category":"Building & Trades",
            "subcategory":"Construction",
            "type":"Services"
        }
    ],
    "sg:postcode":"CV6 5FQ",
    "sg:province":"Warwickshire",
    "sg:tags":[
        "equipment"
    ],
    "wof:name":"Jones,Brian,",
    "wof:placetype":"venue"
},
  "geometry": {"coordinates":[-1.491354,52.428017],"type":"Point"}
}