{
  "type": "Feature",
  "properties": {
    "iso:country":"GB",
    "sg:address":"45a High Street",
    "sg:city":"Walton-on-thames",
    "sg:classifiers":[
        {
            "category":"Real Estate",
            "subcategory":"Real Estate Agent",
            "type":"Services"
        }
    ],
    "sg:phone":"+44 1932 220022",
    "sg:postcode":"KT12 1DH",
    "sg:province":"Surrey",
    "wof:name":"Jacksons Lettings Agents Ltd.",
    "wof:placetype":"venue"
},
  "geometry": {"coordinates":[-0.418033,51.38488],"type":"Point"}
}