{
  "type": "Feature",
  "properties": {
    "iso:country":"GB",
    "sg:address":"34-36 Camwal Rd",
    "sg:city":"Harrogate",
    "sg:classifiers":[
        {
            "category":"Manufacturing",
            "subcategory":"Metals",
            "type":"Manufacturing & Wholesale Goods"
        }
    ],
    "sg:phone":"+44 1423 888898",
    "sg:postcode":"HG1 4PT",
    "sg:province":"North Yorkshire",
    "sg:tags":[
        "steel",
        "fabricator",
        "erectors"
    ],
    "wof:name":"Stoneage Interiors Ltd",
    "wof:placetype":"venue"
},
  "geometry": {"coordinates":[-1.500419,53.999447],"type":"Point"}
}