{
  "type": "Feature",
  "properties": {
    "iso:country":"GB",
    "sg:address":"St Stephens Grn",
    "sg:city":"Canterbury",
    "sg:classifiers":[
        {
            "category":"Bars & Pubs",
            "type":"Food & Drink"
        }
    ],
    "sg:phone":"+44 1227 463974",
    "sg:postcode":"CT2 7JU",
    "sg:province":"Kent",
    "sg:tags":[
        "pubs",
        "inn"
    ],
    "wof:name":"Ye Olde Beverlie",
    "wof:placetype":"venue"
},
  "geometry": {"coordinates":[1.0780500174,51.290271759],"type":"Point"}
}