{
  "type": "Feature",
  "properties": {
    "iso:country":"GB",
    "sg:address":"374 Bethnal Green Road",
    "sg:city":"London",
    "sg:classifiers":[
        {
            "category":"Food & Beverages",
            "subcategory":"Meat & Fish",
            "type":"Retail Goods"
        }
    ],
    "sg:phone":"+44 20 7739 8185",
    "sg:postcode":"E2 0AH",
    "sg:province":"Greater London",
    "sg:tags":[
        "butcher"
    ],
    "wof:name":"The Butchers Shop",
    "wof:placetype":"venue"
},
  "geometry": {"coordinates":[-0.0618939996,51.5267295837],"type":"Point"}
}