{
  "type": "Feature",
  "properties": {
    "iso:country":"GB",
    "sg:address":"35 Erskine View",
    "sg:city":"Clydebank",
    "sg:classifiers":[
        {
            "category":"Building & Trades",
            "subcategory":"Plumbing",
            "type":"Services"
        }
    ],
    "sg:phone":"+44 1389 873942",
    "sg:postcode":"G81 6EE",
    "sg:province":"East Dunbartonshire",
    "sg:tags":[
        "heating"
    ],
    "wof:name":"Angus McLeod Plumbing",
    "wof:placetype":"venue"
},
  "geometry": {"coordinates":[-4.403649,55.910858],"type":"Point"}
}