{
  "type": "Feature",
  "properties": {
    "addr:full":"35 Erskine View Clydebank East Dunbartonshire G81 6EE",
    "addr:housenumber":"35",
    "addr:postcode":"g81 6ee",
    "addr:street":"Erskine View Clydebank",
    "iso:country":"GB",
    "sg:address":"35 Erskine View",
    "sg:city":"Clydebank",
    "sg:classifiers":[
        {
            "category":"Building & Trades",
            "subcategory":"Plumbing",
            "type":"Services"
        }
    ],
    "sg:phone":"+44 1389 873942",
    "sg:postcode":"G81 6EE",
    "sg:province":"East Dunbartonshire",
    "sg:tags":[
        "heating"
    ],
    "wof:name":"Angus McLeod Plumbing",
    "wof:placetype":"venue"
},
  "geometry": {"coordinates":[-4.403649,55.910858],"type":"Point"}
}