{
  "type": "Feature",
  "properties": {
    "iso:country":"GB",
    "sg:address":"30 Caldy Road, West Kirby",
    "sg:city":"Wirral",
    "sg:classifiers":[
        {
            "category":"Real Estate",
            "subcategory":"Architect",
            "type":"Services"
        }
    ],
    "sg:postcode":"CH48 2HQ",
    "sg:province":"Merseyside",
    "wof:name":"Tony Haire",
    "wof:placetype":"venue"
},
  "geometry": {"coordinates":[-3.1734039783,53.3632583618],"type":"Point"}
}