{
  "type": "Feature",
  "properties": {
    "addr:full":"30 Caldy Road, West Kirby Wirral Merseyside CH48 2HQ",
    "addr:housenumber":"30",
    "addr:postcode":"ch48 2hq",
    "addr:street":"Caldy Road",
    "iso:country":"GB",
    "sg:address":"30 Caldy Road, West Kirby",
    "sg:city":"Wirral",
    "sg:classifiers":[
        {
            "category":"Real Estate",
            "subcategory":"Architect",
            "type":"Services"
        }
    ],
    "sg:postcode":"CH48 2HQ",
    "sg:province":"Merseyside",
    "wof:name":"Tony Haire",
    "wof:placetype":"venue"
},
  "geometry": {"coordinates":[-3.1734039783,53.3632583618],"type":"Point"}
}