{
  "type": "Feature",
  "properties": {
    "addr:full":"117 Bath Road Worcester Worcestershire WR5 3AF",
    "addr:housenumber":"117",
    "addr:postcode":"wr5 3af",
    "addr:street":"Bath Road",
    "iso:country":"GB",
    "sg:address":"117 Bath Road",
    "sg:city":"Worcester",
    "sg:classifiers":[
        {
            "category":"Shopping",
            "subcategory":"Pharmacy",
            "type":"Retail Goods"
        }
    ],
    "sg:phone":"+44 1905 354651",
    "sg:postcode":"WR5 3AF",
    "sg:province":"Worcestershire",
    "sg:tags":[
        "pharmacist",
        "chemist"
    ],
    "wof:name":"A W Sandles Chemists",
    "wof:placetype":"venue"
},
  "geometry": {"coordinates":[-2.217712,52.182423],"type":"Point"}
}