{
  "type": "Feature",
  "properties": {
    "addr:full":"503 Gander Green La Sutton Surrey SM3 9RA",
    "addr:housenumber":"503",
    "addr:postcode":"sm3 9ra",
    "addr:street":"Gander Green La Sutton",
    "iso:country":"GB",
    "sg:address":"503 Gander Green La",
    "sg:city":"Sutton",
    "sg:classifiers":[
        {
            "category":"Shopping",
            "subcategory":"Mobile Phones",
            "type":"Retail Goods"
        }
    ],
    "sg:postcode":"SM3 9RA",
    "sg:province":"Surrey",
    "wof:name":"Capital Communications",
    "wof:placetype":"venue"
},
  "geometry": {"coordinates":[-0.2159000039,51.376865387],"type":"Point"}
}