{
  "type": "Feature",
  "properties": {
    "addr:full":"63-65 Lewis Road Brighton East Sussex BN2 3HZ",
    "addr:housenumber":"63-65",
    "addr:postcode":"bn2 3hz",
    "addr:street":"Lewis Road",
    "iso:country":"GB",
    "sg:address":"63-65 Lewis Road",
    "sg:city":"Brighton",
    "sg:classifiers":[
        {
            "category":"Food & Beverages",
            "subcategory":"Bakery",
            "type":"Retail Goods"
        }
    ],
    "sg:phone":"+44 1273 600927",
    "sg:postcode":"BN2 3HZ",
    "sg:province":"East Sussex",
    "sg:tags":[
        "confectionery"
    ],
    "wof:name":"Chunky Bakery",
    "wof:placetype":"venue"
},
  "geometry": {"coordinates":[-0.1263220012,50.8350791931],"type":"Point"}
}