{
  "type": "Feature",
  "properties": {
    "iso:country":"GB",
    "sg:address":"46 Usmere Rd, Broadwaters",
    "sg:city":"Kidderminster",
    "sg:classifiers":[
        {
            "category":"Organizations",
            "subcategory":"Non-profit Organization",
            "type":"Services"
        }
    ],
    "sg:phone":"+44 1562 824307",
    "sg:postcode":"DY12 2XZ",
    "sg:province":"Shropshire",
    "sg:tags":[
        "alarm",
        "system"
    ],
    "wof:name":"1st Call Fire & Security",
    "wof:placetype":"venue"
},
  "geometry": {"coordinates":[-2.23422,52.39941],"type":"Point"}
}