{
  "type": "Feature",
  "properties": {
    "addr:full":"Stoney Bank Mill, Stoney Bank Lane, New Mill Holmfirth South Yorkshire HD9 7LZ",
    "addr:postcode":"hd9 7lz",
    "addr:street":"Stoney Bank Mill Stoney Bank Lane",
    "iso:country":"GB",
    "sg:address":"Stoney Bank Mill, Stoney Bank Lane, New Mill",
    "sg:city":"Holmfirth",
    "sg:classifiers":[
        {
            "category":"Building & Trades",
            "subcategory":"Construction",
            "type":"Services"
        }
    ],
    "sg:phone":"+44 1484 687951",
    "sg:postcode":"HD9 7LZ",
    "sg:province":"South Yorkshire",
    "sg:tags":[
        "joiner",
        "carpenter"
    ],
    "wof:name":"Home From Holme",
    "wof:placetype":"venue"
},
  "geometry": {"coordinates":[-1.7559429407,53.5761222839],"type":"Point"}
}