{
  "type": "Feature",
  "properties": {
    "addr:full":"47 New Greenmarket Newcastle-upon-tyne Tyne and Wear NE1 7YB",
    "addr:housenumber":"47",
    "addr:postcode":"ne1 7yb",
    "addr:street":"New Greenmarket",
    "iso:country":"GB",
    "sg:address":"47 New Greenmarket",
    "sg:city":"Newcastle-upon-tyne",
    "sg:classifiers":[
        {
            "category":"Shopping",
            "type":"Retail Goods"
        }
    ],
    "sg:postcode":"NE1 7YB",
    "sg:province":"Tyne and Wear",
    "sg:tags":[
        "shop",
        "new age"
    ],
    "wof:name":"Dances With Unicorns",
    "wof:placetype":"venue"
},
  "geometry": {"coordinates":[-1.6123689413,54.9779167175],"type":"Point"}
}