{
  "type": "Feature",
  "properties": {
    "addr:full":"Shambles, Vicarage Road Thetford Norfolk IP24 1PE",
    "addr:postcode":"ip24 1pe",
    "addr:street":"Vicarage Road",
    "iso:country":"GB",
    "sg:address":"Shambles, Vicarage Road",
    "sg:city":"Thetford",
    "sg:classifiers":[
        {
            "category":"Fast Food",
            "type":"Food & Drink"
        }
    ],
    "sg:postcode":"IP24 1PE",
    "sg:province":"Norfolk",
    "sg:tags":[
        "away",
        "take"
    ],
    "wof:name":"The Lunch Break",
    "wof:placetype":"venue"
},
  "geometry": {"coordinates":[0.872421,52.497158],"type":"Point"}
}