{
  "type": "Feature",
  "properties": {
    "addr:full":"College House, College Close Sandown Isle of Wight PO36 8EB",
    "addr:postcode":"po36 8eb",
    "addr:street":"College Close",
    "iso:country":"GB",
    "sg:address":"College House, College Close",
    "sg:city":"Sandown",
    "sg:classifiers":[
        {
            "category":"Retail",
            "subcategory":"Repair Shop",
            "type":"Services"
        }
    ],
    "sg:phone":"+44 1983 402114",
    "sg:postcode":"PO36 8EB",
    "sg:province":"Isle of Wight",
    "sg:tags":[
        "radio",
        "television",
        "video"
    ],
    "wof:name":"Culver Electrical",
    "wof:placetype":"venue"
},
  "geometry": {"coordinates":[-1.151094,50.661041],"type":"Point"}
}