{
  "type": "Feature",
  "properties": {
    "iso:country":"GB",
    "sg:address":"23 Mustow Street",
    "sg:city":"Bury St Edmunds",
    "sg:classifiers":[
        {
            "category":"Retail",
            "subcategory":"Funeral Services",
            "type":"Services"
        }
    ],
    "sg:phone":"+44 1284 754349",
    "sg:postcode":"IP33 1XL",
    "sg:province":"Suffolk",
    "sg:tags":[
        "director"
    ],
    "wof:name":"F Clutterham & Son",
    "wof:placetype":"venue"
},
  "geometry": {"coordinates":[0.718061,52.245888],"type":"Point"}
}