{
  "type": "Feature",
  "properties": {
    "iso:country":"GB",
    "sg:address":"Southview, Lower Park Rd",
    "sg:city":"Wickford",
    "sg:classifiers":[
        {
            "category":"Manufacturing",
            "subcategory":"Building Materials",
            "type":"Manufacturing & Wholesale Goods"
        }
    ],
    "sg:phone":"+44 1268 735963",
    "sg:postcode":"SS12 9EJ",
    "sg:province":"Essex",
    "sg:tags":[
        "tarmac",
        "asphalt"
    ],
    "wof:name":"South Essex Tarmac",
    "wof:placetype":"venue"
},
  "geometry": {"coordinates":[0.518481,51.59985],"type":"Point"}
}