{
  "type": "Feature",
  "properties": {
    "iso:country":"GB",
    "sg:address":"11 Bank Street",
    "sg:city":"Wrexham",
    "sg:classifiers":[
        {
            "category":"Shopping",
            "subcategory":"Clothing, Apparel, & Fashions",
            "type":"Retail Goods"
        }
    ],
    "sg:phone":"+44 1978 353355",
    "sg:postcode":"LL11 1AH",
    "sg:province":"Wrexham",
    "sg:tags":[
        "shop"
    ],
    "wof:name":"The Dressing Room",
    "wof:placetype":"venue"
},
  "geometry": {"coordinates":[-3.043864,53.059376],"type":"Point"}
}