{
  "type": "Feature",
  "properties": {
    "iso:country":"GB",
    "sg:address":"Westgate House, Royland Road",
    "sg:city":"Loughborough",
    "sg:classifiers":[
        {
            "category":"Professional",
            "subcategory":"Accounting & Tax Preparation",
            "type":"Services"
        }
    ],
    "sg:phone":"+44 1509 212890",
    "sg:postcode":"LE11 2EH",
    "sg:province":"Leicestershire",
    "sg:tags":[
        "accountant"
    ],
    "wof:name":"Turner & Smith",
    "wof:placetype":"venue"
},
  "geometry": {"coordinates":[-1.208014,52.767727],"type":"Point"}
}