{
  "type": "Feature",
  "properties": {
    "addr:full":"59-61 Faulkner Street Manchester Greater Manchester M1 4FF",
    "addr:housenumber":"59-61",
    "addr:postcode":"m1 4ff",
    "addr:street":"Faulkner Street",
    "iso:country":"GB",
    "sg:address":"59-61 Faulkner Street",
    "sg:city":"Manchester",
    "sg:classifiers":[
        {
            "category":"Professional",
            "subcategory":"Management & Consulting",
            "type":"Services"
        }
    ],
    "sg:phone":"+44 161 236 8018",
    "sg:postcode":"M1 4FF",
    "sg:province":"Greater Manchester",
    "sg:tags":[
        "consultant",
        "business"
    ],
    "wof:name":"United (B I C) Ltd.",
    "wof:placetype":"venue"
},
  "geometry": {"coordinates":[-2.240115881,53.4780082703],"type":"Point"}
}