{
  "type": "Feature",
  "properties": {
    "iso:country":"GB",
    "sg:address":"Hickleton Hall, Hickleton",
    "sg:city":"Doncaster",
    "sg:classifiers":[
        {
            "category":"Health Services",
            "subcategory":"Nursing And Care Facility",
            "type":"Services"
        }
    ],
    "sg:phone":"+44 1709 892070",
    "sg:postcode":"DN5 7BB",
    "sg:province":"South Yorkshire",
    "sg:tags":[
        "home"
    ],
    "wof:name":"Sue Ryder Home",
    "wof:placetype":"venue"
},
  "geometry": {"coordinates":[-1.276529,53.542244],"type":"Point"}
}