{
  "type": "Feature",
  "properties": {
    "iso:country":"GB",
    "sg:address":"6 The Green, Wrenthorpe",
    "sg:city":"Wakefield",
    "sg:classifiers":[
        {
            "category":"Shopping",
            "subcategory":"Party Supplies",
            "type":"Retail Goods"
        }
    ],
    "sg:postcode":"WF2 0JP",
    "sg:province":"West Yorkshire",
    "sg:tags":[
        "inflatables",
        "bouncy",
        "castle"
    ],
    "wof:name":"Linden Leisure",
    "wof:placetype":"venue"
},
  "geometry": {"coordinates":[-1.524307,53.704536],"type":"Point"}
}