{
  "type": "Feature",
  "properties": {
    "iso:country":"GB",
    "sg:address":"Unit 6, Burntwood Town Shopping Centre, Cannock Road",
    "sg:city":"Burntwood",
    "sg:classifiers":[
        {
            "category":"Education",
            "subcategory":"College",
            "type":"Public Place"
        }
    ],
    "sg:phone":"+44 1543 677068",
    "sg:postcode":"WS7 8JR",
    "sg:province":"Staffordshire",
    "sg:tags":[
        "school"
    ],
    "wof:name":"Uniforms Plus",
    "wof:placetype":"venue"
},
  "geometry": {"coordinates":[-1.9347840548,52.6818199158],"type":"Point"}
}