{
  "type": "Feature",
  "properties": {
    "iso:country":"GB",
    "sg:address":"26 Birchitt Road",
    "sg:city":"Sheffield",
    "sg:classifiers":[
        {
            "category":"Professional",
            "subcategory":"Lawyer & Legal Services",
            "type":"Services"
        }
    ],
    "sg:postcode":"S17 4QP",
    "sg:province":"Derbyshire",
    "wof:name":"Professional Will Writing Services",
    "wof:placetype":"venue"
},
  "geometry": {"coordinates":[-1.500745,53.317451],"type":"Point"}
}