{
  "type": "Feature",
  "properties": {
    "addr:full":"The Bungalow, Moss Hill Stoke-on-trent Staffordshire ST9 9NW",
    "addr:postcode":"st9 9nw",
    "addr:street":"Moss Hill",
    "iso:country":"GB",
    "sg:address":"The Bungalow, Moss Hill",
    "sg:city":"Stoke-on-trent",
    "sg:classifiers":[
        {
            "category":"Building & Trades",
            "subcategory":"Plumbing",
            "type":"Services"
        }
    ],
    "sg:phone":"+44 1782 502841",
    "sg:postcode":"ST9 9NW",
    "sg:province":"Staffordshire",
    "sg:tags":[
        "heating"
    ],
    "wof:name":"P & J Riley",
    "wof:placetype":"venue"
},
  "geometry": {"coordinates":[-2.12654,53.06741],"type":"Point"}
}