{
  "type": "Feature",
  "properties": {
    "addr:full":"68 High Street Walton-on-thames Surrey KT12 1DT",
    "addr:housenumber":"68",
    "addr:postcode":"kt12 1dt",
    "addr:street":"High Street",
    "iso:country":"GB",
    "sg:address":"68 High Street",
    "sg:city":"Walton-on-thames",
    "sg:classifiers":[
        {
            "category":"Professional",
            "subcategory":"Lawyer & Legal Services",
            "type":"Services"
        }
    ],
    "sg:phone":"+44 1932 223787",
    "sg:postcode":"KT12 1DT",
    "sg:province":"Surrey",
    "sg:tags":[
        "solicitor"
    ],
    "wof:name":"Howell-Jones & Partners",
    "wof:placetype":"venue"
},
  "geometry": {"coordinates":[-0.416984,51.383667],"type":"Point"}
}