{
  "type": "Feature",
  "properties": {
    "addr:full":"Sywell Airport Business Park, Wellingborough Rd Northampton Northamptonshire NN6 0BT",
    "addr:housenumber":"sywell",
    "addr:postcode":"nn6 0bt",
    "addr:street":"Airport Business Park Wellingborough Rd",
    "iso:country":"GB",
    "sg:address":"Sywell Airport Business Park, Wellingborough Rd",
    "sg:city":"Northampton",
    "sg:classifiers":[
        {
            "category":"Building & Trades",
            "subcategory":"Cleaning & Sanitation",
            "type":"Services"
        }
    ],
    "sg:phone":"+44 1604 671092",
    "sg:postcode":"NN6 0BT",
    "sg:province":"Northamptonshire",
    "sg:tags":[
        "blast"
    ],
    "wof:name":"P C S Shotblasting & Scaffolding",
    "wof:placetype":"venue"
},
  "geometry": {"coordinates":[-0.7884,52.301392],"type":"Point"}
}