{
  "type": "Feature",
  "properties": {
    "addr:full":"304 Charminster Road Bournemouth Dorset BH8 9RT",
    "addr:housenumber":"304",
    "addr:postcode":"bh8 9rt",
    "addr:street":"Charminster Road",
    "iso:country":"GB",
    "sg:address":"304 Charminster Road",
    "sg:city":"Bournemouth",
    "sg:classifiers":[
        {
            "category":"Shopping",
            "subcategory":"Used Merchandise",
            "type":"Retail Goods"
        }
    ],
    "sg:postcode":"BH8 9RT",
    "sg:province":"Dorset",
    "sg:tags":[
        "shop",
        "second-hand"
    ],
    "wof:name":"Smashing Designs",
    "wof:placetype":"venue"
},
  "geometry": {"coordinates":[-1.863000989,50.7408180237],"type":"Point"}
}