{
  "type": "Feature",
  "properties": {
    "addr:full":"32 Bethnal Green Road Whitechapel Greater London E1 6HZ",
    "addr:housenumber":"32",
    "addr:postcode":"e1 6hz",
    "addr:street":"Bethnal Green Road",
    "iso:country":"GB",
    "sg:address":"32 Bethnal Green Road",
    "sg:city":"Whitechapel",
    "sg:classifiers":[
        {
            "category":"Shopping",
            "subcategory":"Stationery & Office Supplies",
            "type":"Retail Goods"
        }
    ],
    "sg:phone":"+44 20 7749 8400",
    "sg:postcode":"E1 6HZ",
    "sg:province":"Greater London",
    "sg:tags":[
        "equipment"
    ],
    "wof:name":"Dudley Office Automation",
    "wof:placetype":"venue"
},
  "geometry": {"coordinates":[-0.0730699971,51.524181366],"type":"Point"}
}