{
  "type": "Feature",
  "properties": {
    "iso:country":"GB",
    "sg:address":"4 Well Ct, Bank St",
    "sg:city":"Sevenoaks",
    "sg:classifiers":[
        {
            "category":"Shopping",
            "subcategory":"Clothing, Apparel, & Fashions",
            "type":"Retail Goods"
        }
    ],
    "sg:phone":"+44 1732 459454",
    "sg:postcode":"TN13 1UN",
    "sg:province":"Kent",
    "sg:tags":[
        "menswear"
    ],
    "wof:name":"Gerrards",
    "wof:placetype":"venue"
},
  "geometry": {"coordinates":[0.192939,51.270199],"type":"Point"}
}