{
  "type": "Feature",
  "properties": {
    "addr:full":"Oakmead, Broad St Haywards Heath East Sussex RH17 5DX",
    "addr:postcode":"rh17 5dx",
    "addr:street":"Broad St",
    "iso:country":"GB",
    "sg:address":"Oakmead, Broad St",
    "sg:city":"Haywards Heath",
    "sg:classifiers":[
        {
            "category":"Real Estate",
            "subcategory":"Real Estate Agent",
            "type":"Services"
        }
    ],
    "sg:phone":"+44 1444 452560",
    "sg:postcode":"RH17 5DX",
    "sg:province":"East Sussex",
    "wof:name":"Business Property Sales",
    "wof:placetype":"venue"
},
  "geometry": {"coordinates":[-0.130429998,51.0045318604],"type":"Point"}
}