{
  "type": "Feature",
  "properties": {
    "iso:country":"GB",
    "sg:address":"12 Chiltern Road",
    "sg:city":"Maidenhead",
    "sg:classifiers":[
        {
            "category":"Professional",
            "subcategory":"Computer Services",
            "type":"Services"
        }
    ],
    "sg:phone":"+44 1628 676669",
    "sg:postcode":"SL6 1XA",
    "sg:province":"Berkshire",
    "sg:tags":[
        "system",
        "software"
    ],
    "wof:name":"Monterey Systems Ltd.",
    "wof:placetype":"venue"
},
  "geometry": {"coordinates":[-0.708231,51.517494],"type":"Point"}
}