{
  "type": "Feature",
  "properties": {
    "addr:full":"15 Carter Avenue, Rainford St Helens Lancashire WA11 8EL",
    "addr:housenumber":"15",
    "addr:postcode":"wa11 8el",
    "addr:street":"Carter Avenue Rainford",
    "iso:country":"GB",
    "sg:address":"15 Carter Avenue, Rainford",
    "sg:city":"St Helens",
    "sg:classifiers":[
        {
            "category":"Home & Garden",
            "subcategory":"Carpets & Floor Coverings",
            "type":"Retail Goods"
        }
    ],
    "sg:postcode":"WA11 8EL",
    "sg:province":"Lancashire",
    "sg:tags":[
        "cleaner",
        "upholstery"
    ],
    "wof:name":"Carpet Cleaning Services",
    "wof:placetype":"venue"
},
  "geometry": {"coordinates":[-2.7797598839,53.4969215393],"type":"Point"}
}