{
  "type": "Feature",
  "properties": {
    "iso:country":"GB",
    "sg:address":"2 Dawesgreen Cotts, Tapners Road",
    "sg:city":"Reigate",
    "sg:classifiers":[
        {
            "category":"Professional",
            "subcategory":"Secretarial Services",
            "type":"Services"
        }
    ],
    "sg:postcode":"RH2 8NN",
    "sg:province":"Surrey",
    "wof:name":"Lyndsay Smith",
    "wof:placetype":"venue"
},
  "geometry": {"coordinates":[-0.2047789991,51.2357444763],"type":"Point"}
}