{
  "type": "Feature",
  "properties": {
    "iso:country":"GB",
    "sg:address":"11 Boynton",
    "sg:city":"Bridlington",
    "sg:classifiers":[
        {
            "category":"Social Services",
            "subcategory":"Retirement Home",
            "type":"Services"
        }
    ],
    "sg:phone":"+44 1262 603488",
    "sg:postcode":"YO16 4XJ",
    "sg:province":"East Riding of Yorkshire",
    "sg:tags":[
        "residential",
        "care"
    ],
    "wof:name":"Barn Cottage Residential Home",
    "wof:placetype":"venue"
},
  "geometry": {"coordinates":[-0.231399,54.076515],"type":"Point"}
}