{
  "type": "Feature",
  "properties": {
    "iso:country":"GB",
    "sg:address":"55 School Road, Downham",
    "sg:city":"Billericay",
    "sg:classifiers":[
        {
            "category":"Professional",
            "subcategory":"Engineering",
            "type":"Services"
        }
    ],
    "sg:phone":"+44 1268 710720",
    "sg:postcode":"CM11 1QP",
    "sg:province":"Essex",
    "sg:tags":[
        "contractor",
        "electrical",
        "engineer"
    ],
    "wof:name":"Downham Electrical Services Ltd.",
    "wof:placetype":"venue"
},
  "geometry": {"coordinates":[0.492026,51.637447],"type":"Point"}
}