{
  "type": "Feature",
  "properties": {
    "iso:country":"GB",
    "sg:address":"St Florence, Manorbier",
    "sg:city":"Tenby",
    "sg:classifiers":[
        {
            "category":"Building & Trades",
            "subcategory":"Landscaping Services",
            "type":"Services"
        }
    ],
    "sg:phone":"+44 1834 871500",
    "sg:postcode":"SA70 8LP",
    "sg:province":"Pembrokeshire",
    "sg:tags":[
        "forestry",
        "tree"
    ],
    "wof:name":"County Trees",
    "wof:placetype":"venue"
},
  "geometry": {"coordinates":[-4.712056,51.6768],"type":"Point"}
}