{
  "type": "Feature",
  "properties": {
    "iso:country":"GB",
    "sg:address":"Unit A8(6)pennington Court, Moss Industrial Estate",
    "sg:city":"Leigh",
    "sg:classifiers":[
        {
            "category":"Building & Trades",
            "subcategory":"Construction",
            "type":"Services"
        }
    ],
    "sg:phone":"+44 1942 609494",
    "sg:postcode":"WN7 3PT",
    "sg:province":"Lancashire",
    "sg:tags":[
        "builder"
    ],
    "wof:name":"Willow Woodfinishing",
    "wof:placetype":"venue"
},
  "geometry": {"coordinates":[-2.5466039181,53.4800109863],"type":"Point"}
}