{
  "type": "Feature",
  "properties": {
    "iso:country":"GB",
    "sg:address":"17 The Avenue",
    "sg:city":"Sandy",
    "sg:classifiers":[
        {
            "category":"Building & Trades",
            "subcategory":"Construction",
            "type":"Services"
        }
    ],
    "sg:phone":"+44 1767 692209",
    "sg:postcode":"SG19 1ER",
    "sg:province":"Bedfordshire",
    "sg:tags":[
        "builder"
    ],
    "wof:name":"Wynnstay Construction (Uk) Ltd",
    "wof:placetype":"venue"
},
  "geometry": {"coordinates":[-0.293442,52.127071],"type":"Point"}
}