{
  "type": "Feature",
  "properties": {
    "addr:full":"176 Coates Road, Coates, Whittlesey Peterborough Cambridgeshire PE7 2BE",
    "addr:housenumber":"176",
    "addr:postcode":"pe7 2be",
    "addr:street":"Coates Road",
    "iso:country":"GB",
    "sg:address":"176 Coates Road, Coates, Whittlesey",
    "sg:city":"Peterborough",
    "sg:classifiers":[
        {
            "category":"Professional",
            "subcategory":"Management & Consulting",
            "type":"Services"
        }
    ],
    "sg:phone":"+44 1733 208208",
    "sg:postcode":"PE7 2BE",
    "sg:province":"Cambridgeshire",
    "sg:tags":[
        "consultant",
        "business"
    ],
    "wof:name":"David Turnbull Consulting",
    "wof:placetype":"venue"
},
  "geometry": {"coordinates":[-0.080562003,52.5594520569],"type":"Point"}
}