{
  "type": "Feature",
  "properties": {
    "addr:full":"87 Ambleside Avenue, Telscombe Cliff Peacehaven East Sussex BN10 7LN",
    "addr:housenumber":"87",
    "addr:postcode":"bn10 7ln",
    "addr:street":"Ambleside Avenue;Cliff Peacehaven",
    "iso:country":"GB",
    "sg:address":"87 Ambleside Avenue, Telscombe Cliff",
    "sg:city":"Peacehaven",
    "sg:classifiers":[
        {
            "category":"Building & Trades",
            "subcategory":"Plumbing",
            "type":"Services"
        }
    ],
    "sg:phone":"+44 1273 583022",
    "sg:postcode":"BN10 7LN",
    "sg:province":"East Sussex",
    "sg:tags":[
        "heating"
    ],
    "wof:name":"L Edwards",
    "wof:placetype":"venue"
},
  "geometry": {"coordinates":[-0.0074499999,50.7986984253],"type":"Point"}
}