{
  "type": "Feature",
  "properties": {
    "iso:country":"GB",
    "sg:address":"Unit 4, Talewater Works, Talaton",
    "sg:city":"Exeter",
    "sg:classifiers":[
        {
            "category":"Wholesale",
            "subcategory":"Construction Materials",
            "type":"Manufacturing & Wholesale Goods"
        }
    ],
    "sg:postcode":"EX5 2RT",
    "sg:province":"Devon",
    "sg:tags":[
        "sawdust",
        "sawmills",
        "shaving"
    ],
    "wof:name":"Woodstock Timber Co.",
    "wof:placetype":"venue"
},
  "geometry": {"coordinates":[-3.323099,50.788094],"type":"Point"}
}