{
  "type": "Feature",
  "properties": {
    "addr:full":"21 Bolton Rd, Farnworth Bolton Lancashire BL4 7JN",
    "addr:housenumber":"21",
    "addr:postcode":"bl4 7jn",
    "addr:street":"Bolton Rd",
    "iso:country":"GB",
    "sg:address":"21 Bolton Rd, Farnworth",
    "sg:city":"Bolton",
    "sg:classifiers":[
        {
            "category":"Professional",
            "subcategory":"Engineering",
            "type":"Services"
        }
    ],
    "sg:postcode":"BL4 7JN",
    "sg:province":"Lancashire",
    "wof:name":"Sutton Bowles Consultants Ltd",
    "wof:placetype":"venue"
},
  "geometry": {"coordinates":[-2.399798,53.554607],"type":"Point"}
}