{
  "type": "Feature",
  "properties": {
    "addr:full":"Park Ave Aberystwyth Ceredigion SY23 1PG",
    "addr:postcode":"sy23 1pg",
    "addr:street":"Park Ave",
    "iso:country":"GB",
    "sg:address":"Park Ave",
    "sg:city":"Aberystwyth",
    "sg:classifiers":[
        {
            "category":"Bus Charters",
            "type":"Transportation"
        }
    ],
    "sg:postcode":"SY23 1PG",
    "sg:province":"Ceredigion",
    "sg:tags":[
        "coach"
    ],
    "wof:name":"Cosville Wales",
    "wof:placetype":"venue"
},
  "geometry": {"coordinates":[-4.0824561119,52.4131393433],"type":"Point"}
}