{
  "type": "Feature",
  "properties": {
    "addr:full":"121a Bury Old Road, Whitefield Manchester Lancashire M45 7AY",
    "addr:housenumber":"121a",
    "addr:postcode":"m45 7ay",
    "addr:street":"Bury Old Road",
    "iso:country":"GB",
    "sg:address":"121a Bury Old Road, Whitefield",
    "sg:city":"Manchester",
    "sg:classifiers":[
        {
            "category":"Professional",
            "subcategory":"Art Services",
            "type":"Services"
        }
    ],
    "sg:phone":"+44 161 792 3303",
    "sg:postcode":"M45 7AY",
    "sg:province":"Lancashire",
    "sg:tags":[
        "picture",
        "restoration",
        "cleaning"
    ],
    "wof:name":"Memories in the Making",
    "wof:placetype":"venue"
},
  "geometry": {"coordinates":[-2.2882900238,53.5423202515],"type":"Point"}
}