{
  "type": "Feature",
  "properties": {
    "addr:full":"161-167 High St, Acton Acton Greater London W3 6LP",
    "addr:housenumber":"161-167",
    "addr:postcode":"w3 6lp",
    "addr:street":"High St",
    "iso:country":"GB",
    "sg:address":"161-167 High St, Acton",
    "sg:city":"Acton",
    "sg:classifiers":[
        {
            "category":"Professional",
            "subcategory":"Business Services",
            "type":"Services"
        }
    ],
    "sg:phone":"+44 20 8965 0100",
    "sg:postcode":"W3 6LP",
    "sg:province":"Greater London",
    "sg:tags":[
        "import",
        "export",
        "agent"
    ],
    "wof:name":"Fomak (UK) Ltd",
    "wof:placetype":"venue"
},
  "geometry": {"coordinates":[-0.2710089982,51.507068634],"type":"Point"}
}