{
  "type": "Feature",
  "properties": {
    "addr:full":"Unit 3 Cambrian Yard, Cambrian Pl Swansea Carmarthenshire SA4 1RG",
    "addr:housenumber":"unit 3",
    "addr:postcode":"sa4 1rg",
    "addr:street":"Cambrian Yard Cambrian Pl",
    "iso:country":"GB",
    "sg:address":"Unit 3 Cambrian Yard, Cambrian Pl",
    "sg:city":"Swansea",
    "sg:classifiers":[
        {
            "category":"Building & Trades",
            "subcategory":"Construction",
            "type":"Services"
        }
    ],
    "sg:phone":"+44 1792 881273",
    "sg:postcode":"SA4 1RG",
    "sg:province":"Carmarthenshire",
    "sg:tags":[
        "roofing"
    ],
    "wof:name":"Abar Roofing",
    "wof:placetype":"venue"
},
  "geometry": {"coordinates":[-4.068570137,51.6847915649],"type":"Point"}
}