{
  "type": "Feature",
  "properties": {
    "iso:country":"GB",
    "sg:address":"Lyric House, 6b St Andrews Street",
    "sg:city":"Hertford",
    "sg:classifiers":[
        {
            "category":"Professional",
            "subcategory":"Printing & Photocopies",
            "type":"Services"
        }
    ],
    "sg:phone":"+44 1992 587871",
    "sg:postcode":"SG14 1JA",
    "sg:province":"Hertfordshire",
    "sg:tags":[
        "plate",
        "lithographic",
        "maker"
    ],
    "wof:name":"The Printed Page",
    "wof:placetype":"venue"
},
  "geometry": {"coordinates":[-0.081016,51.797012],"type":"Point"}
}