{
  "type": "Feature",
  "properties": {
    "addr:full":"Royal Welsh Showground Builth Wells Powys LD2 3SY",
    "addr:postcode":"ld2 3sy",
    "addr:street":"Builth Wells",
    "iso:country":"GB",
    "sg:address":"Royal Welsh Showground",
    "sg:city":"Builth Wells",
    "sg:classifiers":[
        {
            "category":"Shopping",
            "subcategory":"Department Store",
            "type":"Retail Goods"
        }
    ],
    "sg:postcode":"LD2 3SY",
    "sg:province":"Powys",
    "wof:name":"Welsh Food Promotions Ltd",
    "wof:placetype":"venue"
},
  "geometry": {"coordinates":[-3.4030599594,52.148273468],"type":"Point"}
}