{
  "type": "Feature",
  "properties": {
    "addr:full":"Flat 1 Highfield Ct, Hyde Rd Hyde Cheshire SK14 6NG",
    "addr:housenumber":"1",
    "addr:postcode":"sk14 6ng",
    "addr:street":"Highfield Ct Hyde Rd",
    "iso:country":"GB",
    "sg:address":"Flat 1 Highfield Ct, Hyde Rd",
    "sg:city":"Hyde",
    "sg:classifiers":[
        {
            "category":"Education",
            "subcategory":"Dance Studio",
            "type":"Public Place"
        }
    ],
    "sg:phone":"+44 1457 766870",
    "sg:postcode":"SK14 6NG",
    "sg:province":"Cheshire",
    "sg:tags":[
        "school",
        "dancing"
    ],
    "wof:name":"Norton School Of Dancing",
    "wof:placetype":"venue"
},
  "geometry": {"coordinates":[-2.0808839798,53.4543113708],"type":"Point"}
}