{
  "type": "Feature",
  "properties": {
    "iso:country":"GB",
    "sg:address":"Five Ashes Farm, Macclesfield Forest",
    "sg:city":"Macclesfield",
    "sg:classifiers":[
        {
            "category":"Farming",
            "subcategory":"Livestock Farm",
            "type":"Manufacturing & Wholesale Goods"
        }
    ],
    "sg:phone":"+44 1625 426501",
    "sg:postcode":"SK11 0ND",
    "sg:province":"Cheshire",
    "sg:tags":[
        "others"
    ],
    "wof:name":"J & J Burrows",
    "wof:placetype":"venue"
},
  "geometry": {"coordinates":[-2.037759,53.244656],"type":"Point"}
}