{
  "type": "Feature",
  "properties": {
    "addr:full":"34b Albert Rd Widnes Cheshire WA8 6JE",
    "addr:housenumber":"34b",
    "addr:postcode":"wa8 6je",
    "addr:street":"Albert Rd",
    "iso:country":"GB",
    "sg:address":"34b Albert Rd",
    "sg:city":"Widnes",
    "sg:classifiers":[
        {
            "category":"Communications",
            "subcategory":"Film & Video Production",
            "type":"Services"
        }
    ],
    "sg:phone":"+44 151 424 2768",
    "sg:postcode":"WA8 6JE",
    "sg:province":"Cheshire",
    "sg:tags":[
        "tv"
    ],
    "wof:name":"Granada Home Technology",
    "wof:placetype":"venue"
},
  "geometry": {"coordinates":[-2.7255280018,53.3689231873],"type":"Point"}
}