{
  "type": "Feature",
  "properties": {
    "iso:country":"GB",
    "sg:address":"27 Manchester Road, Tytherington",
    "sg:city":"Macclesfield",
    "sg:classifiers":[
        {
            "category":"Travel",
            "subcategory":"Hotels & Motels",
            "type":"Entertainment"
        }
    ],
    "sg:postcode":"SK10 2JJ",
    "sg:province":"Cheshire",
    "sg:tags":[
        "house",
        "guest"
    ],
    "wof:name":"Moorhayes House Hotel",
    "wof:placetype":"venue"
},
  "geometry": {"coordinates":[-2.127635,53.272163],"type":"Point"}
}