{
  "type": "Feature",
  "properties": {
    "addr:full":"1 Cheam Road Sutton Surrey SM1 1SN",
    "addr:housenumber":"1",
    "addr:postcode":"sm1 1sn",
    "addr:street":"Cheam Road",
    "iso:country":"GB",
    "sg:address":"1 Cheam Road",
    "sg:city":"Sutton",
    "sg:classifiers":[
        {
            "category":"Government",
            "subcategory":"City Hall",
            "type":"Public Place"
        }
    ],
    "sg:postcode":"SM1 1SN",
    "sg:province":"Surrey",
    "wof:name":"Christy's",
    "wof:placetype":"venue"
},
  "geometry": {"coordinates":[-0.192487,51.361053],"type":"Point"}
}