{
  "type": "Feature",
  "properties": {
    "addr:full":"The Courtyard, Cowl La Cheltenham Gloucestershire GL54 5RA",
    "addr:postcode":"gl54 5ra",
    "addr:street":"La",
    "iso:country":"GB",
    "sg:address":"The Courtyard, Cowl La",
    "sg:city":"Cheltenham",
    "sg:classifiers":[
        {
            "category":"Building & Trades",
            "subcategory":"Construction",
            "type":"Services"
        }
    ],
    "sg:phone":"+44 1242 602453",
    "sg:postcode":"GL54 5RA",
    "sg:province":"Gloucestershire",
    "sg:tags":[
        "builder"
    ],
    "wof:name":"N J Smith",
    "wof:placetype":"venue"
},
  "geometry": {"coordinates":[-1.96593,51.95425],"type":"Point"}
}