{
  "type": "Feature",
  "properties": {
    "iso:country":"GB",
    "sg:address":"St Marys Church, Hillingden Avenue",
    "sg:city":"Liverpool",
    "sg:classifiers":[
        {
            "category":"Farming",
            "subcategory":"Nursery",
            "type":"Manufacturing & Wholesale Goods"
        }
    ],
    "sg:postcode":"L26 9TZ",
    "sg:province":"Merseyside",
    "sg:tags":[
        "creche"
    ],
    "wof:name":"St.Marys Nursery",
    "wof:placetype":"venue"
},
  "geometry": {"coordinates":[-2.8279,53.360458],"type":"Point"}
}