{
  "type": "Feature",
  "properties": {
    "iso:country":"GB",
    "sg:address":"Meadowfield Place",
    "sg:city":"Plymouth",
    "sg:classifiers":[
        {
            "category":"Farming",
            "subcategory":"Nursery",
            "type":"Manufacturing & Wholesale Goods"
        },
        {
            "category":"Education",
            "subcategory":"Preschool",
            "type":"Public Place"
        }
    ],
    "sg:phone":"+44 1752 343127",
    "sg:postcode":"PL7 1XQ",
    "sg:province":"Devon",
    "sg:tags":[
        "school",
        "creche"
    ],
    "wof:name":"Plymton Montessori Nursery",
    "wof:placetype":"venue"
},
  "geometry": {"coordinates":[-4.030825,50.380089],"type":"Point"}
}