{
  "type": "Feature",
  "properties": {
    "addr:full":"2 Greenbridge Lane, Greenfield Oldham Lancashire OL3 7JR",
    "addr:housenumber":"2",
    "addr:postcode":"ol3 7jr",
    "addr:street":"Greenbridge Lane",
    "iso:country":"GB",
    "sg:address":"2 Greenbridge Lane, Greenfield",
    "sg:city":"Oldham",
    "sg:classifiers":[
        {
            "category":"Government",
            "subcategory":"Post Office",
            "type":"Public Place"
        }
    ],
    "sg:postcode":"OL3 7JR",
    "sg:province":"Lancashire",
    "sg:tags":[
        "print",
        "typesetter"
    ],
    "wof:name":"Nonpareil Typesetting",
    "wof:placetype":"venue"
},
  "geometry": {"coordinates":[-2.0094470978,53.5366706848],"type":"Point"}
}