{
  "type": "Feature",
  "properties": {
    "iso:country":"GB",
    "sg:address":"Treetops, Pond Tail Drive",
    "sg:city":"Horsham",
    "sg:classifiers":[
        {
            "category":"Banks & Credit Unions",
            "subcategory":"Financial Services",
            "type":"Services"
        }
    ],
    "sg:phone":"+44 1403 274844",
    "sg:postcode":"RH12 5HY",
    "sg:province":"West Sussex",
    "sg:tags":[
        "adviser"
    ],
    "wof:name":"Sapphire Financial Management",
    "wof:placetype":"venue"
},
  "geometry": {"coordinates":[-0.3291069865,51.0651817322],"type":"Point"}
}