{
  "type": "Feature",
  "properties": {
    "addr:full":"25-29 Harvey Close, Crowther Washington Durham NE38 0AB",
    "addr:housenumber":"25-29",
    "addr:postcode":"ne38 0ab",
    "addr:street":"Harvey Close",
    "iso:country":"GB",
    "sg:address":"25-29 Harvey Close, Crowther",
    "sg:city":"Washington",
    "sg:classifiers":[
        {
            "category":"Wholesale",
            "subcategory":"Meat",
            "type":"Manufacturing & Wholesale Goods"
        }
    ],
    "sg:phone":"+44 191 416 4816",
    "sg:postcode":"NE38 0AB",
    "sg:province":"Durham",
    "sg:tags":[
        "product"
    ],
    "wof:name":"Superior Meat Processor",
    "wof:placetype":"venue"
},
  "geometry": {"coordinates":[-1.5528130531,54.9018440247],"type":"Point"}
}