{
  "type": "Feature",
  "properties": {
    "iso:country":"GB",
    "sg:address":"R A F, Linton On Ouse",
    "sg:city":"York",
    "sg:classifiers":[
        {
            "category":"Professional",
            "type":"Services"
        }
    ],
    "sg:phone":"+44 1347 848222",
    "sg:postcode":"YO30 2AJ",
    "sg:province":"North Yorkshire",
    "sg:tags":[
        "aircraft",
        "maintenance"
    ],
    "wof:name":"V T Aerospace Ltd.",
    "wof:placetype":"venue"
},
  "geometry": {"coordinates":[-1.248299,54.04055],"type":"Point"}
}