{
  "type": "Feature",
  "properties": {
    "iso:country":"GB",
    "sg:address":"20 Maple Rd",
    "sg:city":"Dartford",
    "sg:classifiers":[
        {
            "category":"Retail",
            "subcategory":"Laundry & Dry Cleaning",
            "type":"Services"
        }
    ],
    "sg:postcode":"DA1 2QZ",
    "sg:province":"Kent",
    "sg:tags":[
        "alteration"
    ],
    "wof:name":"Mancini,David,",
    "wof:placetype":"venue"
},
  "geometry": {"coordinates":[0.206445,51.434967],"type":"Point"}
}