{
  "type": "Feature",
  "properties": {
    "addr:full":"Turner Lane, Whiston Rotherham South Yorkshire S60 4HY",
    "addr:postcode":"s60 4hy",
    "addr:street":"Turner Lane",
    "iso:country":"GB",
    "sg:address":"Turner Lane, Whiston",
    "sg:city":"Rotherham",
    "sg:classifiers":[
        {
            "category":"Bars & Pubs",
            "type":"Food & Drink"
        }
    ],
    "sg:phone":"+44 1709 378200",
    "sg:postcode":"S60 4HY",
    "sg:province":"South Yorkshire",
    "sg:tags":[
        "pubs",
        "inn"
    ],
    "wof:name":"Punch Retail (Holdings) Ltd.",
    "wof:placetype":"venue"
},
  "geometry": {"coordinates":[-1.309684,53.407742],"type":"Point"}
}