{
  "type": "Feature",
  "properties": {
    "iso:country":"GB",
    "sg:address":"3 Kithurst Close, Southgate",
    "sg:city":"Crawley",
    "sg:classifiers":[
        {
            "category":"Manufacturing",
            "subcategory":"Buildings",
            "type":"Manufacturing & Wholesale Goods"
        }
    ],
    "sg:postcode":"RH11 8TD",
    "sg:province":"West Sussex",
    "sg:tags":[
        "system",
        "air conditioning"
    ],
    "wof:name":"B E Environmental",
    "wof:placetype":"venue"
},
  "geometry": {"coordinates":[-0.193808,51.107384],"type":"Point"}
}