{
  "type": "Feature",
  "properties": {
    "addr:full":"48 High Street Lincoln Lincolnshire LN5 8AS",
    "addr:housenumber":"48",
    "addr:postcode":"ln5 8as",
    "addr:street":"High Street",
    "iso:country":"GB",
    "sg:address":"48 High Street",
    "sg:city":"Lincoln",
    "sg:classifiers":[
        {
            "category":"Professional",
            "subcategory":"Art Services",
            "type":"Services"
        }
    ],
    "sg:phone":"+44 1522 546445",
    "sg:postcode":"LN5 8AS",
    "sg:province":"Lincolnshire",
    "sg:tags":[
        "photographer"
    ],
    "wof:name":"Olan Mills Photographic Studio",
    "wof:placetype":"venue"
},
  "geometry": {"coordinates":[-0.545909,53.21619],"type":"Point"}
}