{
  "type": "Feature",
  "properties": {
    "addr:full":"121-125 Shields Road, Byker Newcastle-upon-tyne Tyne and Wear NE6 1DN",
    "addr:housenumber":"121-125",
    "addr:postcode":"ne6 1dn",
    "addr:street":"Shields Road",
    "iso:country":"GB",
    "sg:address":"121-125 Shields Road, Byker",
    "sg:city":"Newcastle-upon-tyne",
    "sg:classifiers":[
        {
            "category":"Shopping",
            "subcategory":"Pharmacy",
            "type":"Retail Goods"
        }
    ],
    "sg:phone":"+44 191 265 6505",
    "sg:postcode":"NE6 1DN",
    "sg:province":"Tyne and Wear",
    "sg:tags":[
        "pharmacist",
        "chemist"
    ],
    "wof:name":"Boots the Chemist",
    "wof:placetype":"venue"
},
  "geometry": {"coordinates":[-1.581249,54.977257],"type":"Point"}
}