{
  "type": "Feature",
  "properties": {
    "addr:full":"Cleveland Street Darlington Durham DL1 2PB",
    "addr:postcode":"dl1 2pb",
    "addr:street":"Cleveland Street",
    "iso:country":"GB",
    "sg:address":"Cleveland Street",
    "sg:city":"Darlington",
    "sg:classifiers":[
        {
            "category":"Home & Garden",
            "subcategory":"Garden Supply",
            "type":"Retail Goods"
        }
    ],
    "sg:phone":"+44 1325 240999",
    "sg:postcode":"DL1 2PB",
    "sg:province":"Durham",
    "sg:tags":[
        "nursery",
        "centre"
    ],
    "wof:name":"G & B Packaging",
    "wof:placetype":"venue"
},
  "geometry": {"coordinates":[-1.543577,54.534855],"type":"Point"}
}