{
  "type": "Feature",
  "properties": {
    "iso:country":"GB",
    "sg:address":"2 The Oaze, Sunset Park, Whitslake",
    "sg:city":"Whitstable",
    "sg:classifiers":[
        {
            "category":"Professional",
            "subcategory":"Business Services",
            "type":"Services"
        }
    ],
    "sg:postcode":"CT5 4TQ",
    "sg:province":"Kent",
    "sg:tags":[
        "shop",
        "cleaning"
    ],
    "wof:name":"John Gammon Cleaning",
    "wof:placetype":"venue"
},
  "geometry": {"coordinates":[1.0264060497,51.362247467],"type":"Point"}
}