{
  "type": "Feature",
  "properties": {
    "addr:full":"57 The Burroughs London Greater London NW4 4AX",
    "addr:housenumber":"57",
    "addr:postcode":"nw4 4ax",
    "addr:street":"The Burroughs",
    "iso:country":"GB",
    "sg:address":"57 The Burroughs",
    "sg:city":"London",
    "sg:classifiers":[
        {
            "category":"Shopping",
            "subcategory":"Department Store",
            "type":"Retail Goods"
        }
    ],
    "sg:postcode":"NW4 4AX",
    "sg:province":"Greater London",
    "wof:name":"Gernings Mode Shop",
    "wof:placetype":"venue"
},
  "geometry": {"coordinates":[-0.230052,51.587132],"type":"Point"}
}