{
  "type": "Feature",
  "properties": {
    "addr:full":"20 Portsmouth Rd, Horndean Waterlooville Hampshire PO8 9JX",
    "addr:housenumber":"20",
    "addr:postcode":"po8 9jx",
    "addr:street":"Portsmouth Rd",
    "iso:country":"GB",
    "sg:address":"20 Portsmouth Rd, Horndean",
    "sg:city":"Waterlooville",
    "sg:classifiers":[
        {
            "category":"Autos & Motor Vehicles",
            "subcategory":"Automobile Sales",
            "type":"Retail Goods"
        }
    ],
    "sg:phone":"+44 23 9257 1002",
    "sg:postcode":"PO8 9JX",
    "sg:province":"Hampshire",
    "sg:tags":[
        "car"
    ],
    "wof:name":"The Company Car Co Agency",
    "wof:placetype":"venue"
},
  "geometry": {"coordinates":[-0.9975929856,50.9130401611],"type":"Point"}
}