{
  "type": "Feature",
  "properties": {
    "addr:full":"Oxford St Salford Greater Manchester M5 3RX",
    "addr:postcode":"m5 3rx",
    "addr:street":"Oxford St",
    "iso:country":"GB",
    "sg:address":"Oxford St",
    "sg:city":"Salford",
    "sg:classifiers":[
        {
            "category":"Community Center",
            "subcategory":"Youth",
            "type":"Public Place"
        }
    ],
    "sg:phone":"+44 161 872 3767",
    "sg:postcode":"M5 3RX",
    "sg:province":"Greater Manchester",
    "sg:tags":[
        "organisation",
        "centre"
    ],
    "wof:name":"Salford Lads Club",
    "wof:placetype":"venue"
},
  "geometry": {"coordinates":[-2.322769,53.496143],"type":"Point"}
}