{
  "type": "Feature",
  "properties": {
    "iso:country":"GB",
    "sg:address":"Nursery Road, Urmston",
    "sg:city":"Manchester",
    "sg:classifiers":[
        {
            "category":"Education",
            "subcategory":"School",
            "type":"Public Place"
        }
    ],
    "sg:phone":"+44 161 748 5844",
    "sg:postcode":"M41 7WW",
    "sg:province":"Cheshire",
    "sg:tags":[
        "local",
        "authority"
    ],
    "wof:name":"Woodhouse Primary School",
    "wof:placetype":"venue"
},
  "geometry": {"coordinates":[-2.368944,53.458046],"type":"Point"}
}