{
  "type": "Feature",
  "properties": {
    "addr:full":"34 Silverdale Road Eastbourne East Sussex BN20 7EU",
    "addr:housenumber":"34",
    "addr:postcode":"bn20 7eu",
    "addr:street":"Silverdale Road",
    "iso:country":"GB",
    "sg:address":"34 Silverdale Road",
    "sg:city":"Eastbourne",
    "sg:classifiers":[
        {
            "category":"Professional",
            "subcategory":"Detective & Security Services",
            "type":"Services"
        }
    ],
    "sg:phone":"+44 1323 417142",
    "sg:postcode":"BN20 7EU",
    "sg:province":"East Sussex",
    "sg:tags":[
        "alarm",
        "burglar",
        "system"
    ],
    "wof:name":"Lock Alarm & Safe Co. Ltd.",
    "wof:placetype":"venue"
},
  "geometry": {"coordinates":[0.273742,50.760231],"type":"Point"}
}