{
  "type": "Feature",
  "properties": {
    "iso:country":"GB",
    "sg:address":"Ullswater Rd",
    "sg:city":"Warrington",
    "sg:classifiers":[
        {
            "category":"Social Services",
            "subcategory":"Retirement Home",
            "type":"Services"
        }
    ],
    "sg:phone":"+44 1942 724651",
    "sg:postcode":"WA3 3JB",
    "sg:province":"Cheshire",
    "sg:tags":[
        "residential",
        "care"
    ],
    "wof:name":"Ullswater House",
    "wof:placetype":"venue"
},
  "geometry": {"coordinates":[-2.585214,53.479183],"type":"Point"}
}