{
  "type": "Feature",
  "properties": {
    "addr:full":"Gable House, 239 Regents Park Road London Greater London N3 3LF",
    "addr:housenumber":"239",
    "addr:postcode":"n3 3lf",
    "addr:street":"Regents Park Road",
    "iso:country":"GB",
    "sg:address":"Gable House, 239 Regents Park Road",
    "sg:city":"London",
    "sg:classifiers":[
        {
            "category":"Real Estate",
            "subcategory":"Real Estate Agent",
            "type":"Services"
        }
    ],
    "sg:postcode":"N3 3LF",
    "sg:province":"Greater London",
    "wof:name":"Harrington Lowndes Rentals Limited",
    "wof:placetype":"venue"
},
  "geometry": {"coordinates":[-0.198683,51.595985],"type":"Point"}
}