{
  "type": "Feature",
  "properties": {
    "iso:country":"GB",
    "sg:address":"65 Margery St",
    "sg:city":"London",
    "sg:classifiers":[
        {
            "category":"Health Services",
            "subcategory":"Nursing And Care Facility",
            "type":"Services"
        },
        {
            "category":"Social Services",
            "subcategory":"Retirement Home",
            "type":"Services"
        }
    ],
    "sg:phone":"+44 20 7837 4055",
    "sg:postcode":"WC1X 0JL",
    "sg:province":"Greater London",
    "sg:tags":[
        "residential"
    ],
    "wof:name":"Notting Hill Housing Trust",
    "wof:placetype":"venue"
},
  "geometry": {"coordinates":[-0.1110040024,51.5271263123],"type":"Point"}
}