{
  "type": "Feature",
  "properties": {
    "addr:full":"Unit 2, The Street, Ewhurst Cranleigh Surrey GU6 7QD",
    "addr:housenumber":"unit 2",
    "addr:postcode":"gu6 7qd",
    "addr:street":"The Street",
    "iso:country":"GB",
    "sg:address":"Unit 2, The Street, Ewhurst",
    "sg:city":"Cranleigh",
    "sg:classifiers":[
        {
            "category":"Professional",
            "type":"Services"
        }
    ],
    "sg:phone":"+44 1483 278446",
    "sg:postcode":"GU6 7QD",
    "sg:province":"Surrey",
    "sg:tags":[
        "interior",
        "furnishers",
        "designer"
    ],
    "wof:name":"Ziegler's Quality Interiors",
    "wof:placetype":"venue"
},
  "geometry": {"coordinates":[-0.4421940148,51.1554412842],"type":"Point"}
}