{
  "type": "Feature",
  "properties": {
    "addr:full":"Pawletts House, West Street Somerton Somerset TA11 7PS",
    "addr:postcode":"ta11 7ps",
    "addr:street":"West Street",
    "iso:country":"GB",
    "sg:address":"Pawletts House, West Street",
    "sg:city":"Somerton",
    "sg:classifiers":[
        {
            "category":"Professional",
            "subcategory":"Accounting & Tax Preparation",
            "type":"Services"
        }
    ],
    "sg:phone":"+44 1458 272060",
    "sg:postcode":"TA11 7PS",
    "sg:province":"Somerset",
    "sg:tags":[
        "accountant"
    ],
    "wof:name":"Bridges Holland",
    "wof:placetype":"venue"
},
  "geometry": {"coordinates":[-2.7295439243,51.0536384583],"type":"Point"}
}