{
  "type": "Feature",
  "properties": {
    "addr:full":"Jual Brooks, 62 Reva Syke Rd Bradford West Yorkshire BD14 6QZ",
    "addr:housenumber":"62",
    "addr:postcode":"bd14 6qz",
    "addr:street":"Brooks;Syke Rd",
    "iso:country":"GB",
    "sg:address":"Jual Brooks, 62 Reva Syke Rd",
    "sg:city":"Bradford",
    "sg:classifiers":[
        {
            "category":"Building & Trades",
            "subcategory":"Construction",
            "type":"Services"
        }
    ],
    "sg:postcode":"BD14 6QZ",
    "sg:province":"West Yorkshire",
    "sg:tags":[
        "builder"
    ],
    "wof:name":"Western,A & W A,",
    "wof:placetype":"venue"
},
  "geometry": {"coordinates":[-1.7583060265,53.7957382202],"type":"Point"}
}