{
  "type": "Feature",
  "properties": {
    "iso:country":"GB",
    "sg:address":"12 Hampton Road",
    "sg:city":"Worcester Park",
    "sg:classifiers":[
        {
            "category":"Building & Trades",
            "subcategory":"Landscaping Services",
            "type":"Services"
        }
    ],
    "sg:postcode":"KT4 8ET",
    "sg:province":"Surrey",
    "sg:tags":[
        "contractor",
        "drainage"
    ],
    "wof:name":"Get Carter Drainage",
    "wof:placetype":"venue"
},
  "geometry": {"coordinates":[-0.2398249954,51.3765220642],"type":"Point"}
}