{
  "type": "Feature",
  "properties": {
    "addr:full":"Cottonwood, Nanstallon Bodmin Cornwall PL30 5LQ",
    "addr:postcode":"pl30 5lq",
    "addr:street":"Bodmin",
    "iso:country":"GB",
    "sg:address":"Cottonwood, Nanstallon",
    "sg:city":"Bodmin",
    "sg:classifiers":[
        {
            "category":"Manufacturing",
            "subcategory":"Metals",
            "type":"Manufacturing & Wholesale Goods"
        }
    ],
    "sg:phone":"+44 1208 831293",
    "sg:postcode":"PL30 5LQ",
    "sg:province":"Cornwall",
    "sg:tags":[
        "ore"
    ],
    "wof:name":"South Western Mining & Tunnelling Ltd.",
    "wof:placetype":"venue"
},
  "geometry": {"coordinates":[-4.7637491226,50.4711723328],"type":"Point"}
}