{
  "type": "Feature",
  "properties": {
    "addr:full":"Woodeson House, Rodley Leeds West Yorkshire LS13 1HN",
    "addr:postcode":"ls13 1hn",
    "addr:street":"Rodley;West",
    "iso:country":"GB",
    "sg:address":"Woodeson House, Rodley",
    "sg:city":"Leeds",
    "sg:classifiers":[
        {
            "category":"Professional",
            "subcategory":"Engineering",
            "type":"Services"
        }
    ],
    "sg:phone":"+44 113 255 1944",
    "sg:postcode":"LS13 1HN",
    "sg:province":"West Yorkshire",
    "wof:name":"The Clarke Chapman Group Ltd.",
    "wof:placetype":"venue"
},
  "geometry": {"coordinates":[-1.6710469723,53.8254699707],"type":"Point"}
}