{
  "type": "Feature",
  "properties": {
    "addr:full":"27a Hays Mews London Greater London W1J 5NY",
    "addr:housenumber":"27a",
    "addr:postcode":"w1j 5ny",
    "addr:street":"Hays Mews",
    "iso:country":"GB",
    "sg:address":"27a Hays Mews",
    "sg:city":"London",
    "sg:classifiers":[
        {
            "category":"Restaurant",
            "type":"Food & Drink"
        }
    ],
    "sg:phone":"+44 20 7499 3331",
    "sg:postcode":"W1J 5NY",
    "sg:province":"Greater London",
    "wof:name":"Greenhouse Restaurant",
    "wof:placetype":"venue"
},
  "geometry": {"coordinates":[-0.1493790001,51.507686615],"type":"Point"}
}