{
  "type": "Feature",
  "properties": {
    "addr:full":"37 Willow Cres Leigh Lancashire WN7 5RN",
    "addr:housenumber":"37",
    "addr:postcode":"wn7 5rn",
    "addr:street":"Willow Cres Leigh",
    "iso:country":"GB",
    "sg:address":"37 Willow Cres",
    "sg:city":"Leigh",
    "sg:classifiers":[
        {
            "category":"Building & Trades",
            "subcategory":"Plumbing",
            "type":"Services"
        }
    ],
    "sg:phone":"+44 1942 602859",
    "sg:postcode":"WN7 5RN",
    "sg:province":"Lancashire",
    "sg:tags":[
        "heating"
    ],
    "wof:name":"Gas Rite",
    "wof:placetype":"venue"
},
  "geometry": {"coordinates":[-2.5217370987,53.5121307373],"type":"Point"}
}