{
  "type": "Feature",
  "properties": {
    "iso:country":"GB",
    "sg:address":"37 Clarks Village",
    "sg:city":"Street",
    "sg:classifiers":[
        {
            "category":"Home & Garden",
            "subcategory":"Garden Supply",
            "type":"Retail Goods"
        }
    ],
    "sg:postcode":"BA16 0BB",
    "sg:province":"Somerset",
    "sg:tags":[
        "ornament"
    ],
    "wof:name":"The Pot People",
    "wof:placetype":"venue"
},
  "geometry": {"coordinates":[-2.74872,51.127872],"type":"Point"}
}