{
  "type": "Feature",
  "properties": {
    "addr:full":"133-139 Church Road, Hadleigh Benfleet Essex SS7 4EN",
    "addr:housenumber":"133-139",
    "addr:postcode":"ss7 4en",
    "addr:street":"Church Road",
    "iso:country":"GB",
    "sg:address":"133-139 Church Road, Hadleigh",
    "sg:city":"Benfleet",
    "sg:classifiers":[
        {
            "category":"Utilities",
            "subcategory":"Refuse",
            "type":"Services"
        }
    ],
    "sg:phone":"+44 1621 740414",
    "sg:postcode":"SS7 4EN",
    "sg:province":"Essex",
    "sg:tags":[
        "skip",
        "hire"
    ],
    "wof:name":"F W J Walker & Sons (Metals) Ltd.",
    "wof:placetype":"venue"
},
  "geometry": {"coordinates":[0.546570003,51.5696296692],"type":"Point"}
}