{
  "type": "Feature",
  "properties": {
    "addr:full":"15 Berners Street London Greater London W1T 3DP",
    "addr:housenumber":"15",
    "addr:postcode":"w1t 3dp",
    "addr:street":"Berners Street",
    "iso:country":"GB",
    "sg:address":"15 Berners Street",
    "sg:city":"London",
    "sg:classifiers":[
        {
            "category":"Travel",
            "subcategory":"Travel Agent",
            "type":"Entertainment"
        }
    ],
    "sg:phone":"+44 20 7255 6555",
    "sg:postcode":"W1T 3DP",
    "sg:province":"Greater London",
    "wof:name":"Portman Travel Ltd.",
    "wof:placetype":"venue"
},
  "geometry": {"coordinates":[-0.1365360022,51.5172653198],"type":"Point"}
}