{
  "type": "Feature",
  "properties": {
    "addr:full":"2 Oak Cottage, Westmarsh Canterbury Kent CT3 2LS",
    "addr:housenumber":"2",
    "addr:postcode":"ct3 2ls",
    "addr:street":"Oak;Westmarsh",
    "iso:country":"GB",
    "sg:address":"2 Oak Cottage, Westmarsh",
    "sg:city":"Canterbury",
    "sg:classifiers":[
        {
            "category":"Real Estate",
            "subcategory":"Surveying",
            "type":"Services"
        }
    ],
    "sg:postcode":"CT3 2LS",
    "sg:province":"Kent",
    "sg:tags":[
        "surveyor",
        "valuer"
    ],
    "wof:name":"Stevenson,Peter,",
    "wof:placetype":"venue"
},
  "geometry": {"coordinates":[1.2658549547,51.3065872192],"type":"Point"}
}