{
  "type": "Feature",
  "properties": {
    "addr:full":"Newton Villa Liskeard Cornwall PL14 5JU",
    "addr:postcode":"pl14 5ju",
    "addr:street":"Newton;Liskeard",
    "iso:country":"GB",
    "sg:address":"Newton Villa",
    "sg:city":"Liskeard",
    "sg:classifiers":[
        {
            "category":"Home & Garden",
            "subcategory":"Building Materials",
            "type":"Retail Goods"
        }
    ],
    "sg:phone":"+44 1579 343788",
    "sg:postcode":"PL14 5JU",
    "sg:province":"Cornwall",
    "sg:tags":[
        "fencing"
    ],
    "wof:name":"Digory Truscott",
    "wof:placetype":"venue"
},
  "geometry": {"coordinates":[-4.4658341408,50.4537963867],"type":"Point"}
}