{
  "type": "Feature",
  "properties": {
    "addr:full":"21/25 Delacourt Road London Greater London SE3 8XA",
    "addr:housenumber":"21 / 25",
    "addr:postcode":"se3 8xa",
    "addr:street":"Delacourt Road",
    "iso:country":"GB",
    "sg:address":"21/25 Delacourt Road",
    "sg:city":"London",
    "sg:classifiers":[
        {
            "category":"Retail",
            "subcategory":"Auto Repair",
            "type":"Services"
        }
    ],
    "sg:phone":"+44 20 8858 2041",
    "sg:postcode":"SE3 8XA",
    "sg:province":"Greater London",
    "sg:tags":[
        "modification",
        "garage"
    ],
    "wof:name":"Delacourt Motors Ltd.",
    "wof:placetype":"venue"
},
  "geometry": {"coordinates":[0.024673,51.4754562378],"type":"Point"}
}