{
  "type": "Feature",
  "properties": {
    "addr:full":"Drapers Corner, 20 Church Street Calne Wiltshire SN11 0HS",
    "addr:housenumber":"20",
    "addr:postcode":"sn11 0hs",
    "addr:street":"Church Street",
    "iso:country":"GB",
    "sg:address":"Drapers Corner, 20 Church Street",
    "sg:city":"Calne",
    "sg:classifiers":[
        {
            "category":"Shopping",
            "subcategory":"Bicycles & Sporting Goods",
            "type":"Retail Goods"
        }
    ],
    "sg:postcode":"SN11 0HS",
    "sg:province":"Wiltshire",
    "sg:tags":[
        "cycle",
        "accessory"
    ],
    "wof:name":"Recycle of Calne",
    "wof:placetype":"venue"
},
  "geometry": {"coordinates":[-2.004912,51.437672],"type":"Point"}
}