{
  "type": "Feature",
  "properties": {
    "addr:full":"194 Albert Road Southsea Hampshire PO4 0JT",
    "addr:housenumber":"194",
    "addr:postcode":"po4 0jt",
    "addr:street":"Albert Road",
    "iso:country":"GB",
    "sg:address":"194 Albert Road",
    "sg:city":"Southsea",
    "sg:classifiers":[
        {
            "category":"Real Estate",
            "subcategory":"Real Estate Services",
            "type":"Services"
        },
        {
            "category":"Banks & Credit Unions",
            "subcategory":"Investment Brokerage",
            "type":"Services"
        },
        {
            "category":"Real Estate",
            "subcategory":"Real Estate Agent",
            "type":"Services"
        }
    ],
    "sg:phone":"+44 23 9282 3731",
    "sg:postcode":"PO4 0JT",
    "sg:province":"Hampshire",
    "sg:tags":[
        "property",
        "management"
    ],
    "sg:website":"http://www.new-era-agency.co.uk",
    "wof:name":"New Era Agency",
    "wof:placetype":"venue"
},
  "geometry": {"coordinates":[-1.073184967,50.78647995],"type":"Point"}
}