{
  "type": "Feature",
  "properties": {
    "addr:full":"Station Rd Wrexham Wrexham LL12 0HE",
    "addr:postcode":"ll12 0he",
    "addr:street":"Station Rd",
    "iso:country":"GB",
    "sg:address":"Station Rd",
    "sg:city":"Wrexham",
    "sg:classifiers":[
        {
            "category":"Health Services",
            "subcategory":"Doctor",
            "type":"Services"
        }
    ],
    "sg:phone":"+44 1244 570317",
    "sg:postcode":"LL12 0HE",
    "sg:province":"Wrexham",
    "sg:tags":[
        "practitioners"
    ],
    "wof:name":"Halpin, K G",
    "wof:placetype":"venue"
},
  "geometry": {"coordinates":[-2.9568190575,53.108039856],"type":"Point"}
}