{
  "type": "Feature",
  "properties": {
    "addr:full":"15 High St Droitwich Worcestershire WR9 8EJ",
    "addr:housenumber":"15",
    "addr:postcode":"wr9 8ej",
    "addr:street":"High St",
    "iso:country":"GB",
    "sg:address":"15 High St",
    "sg:city":"Droitwich",
    "sg:classifiers":[
        {
            "category":"Shopping",
            "subcategory":"Clothing, Apparel, & Fashions",
            "type":"Retail Goods"
        }
    ],
    "sg:phone":"+44 1905 770137",
    "sg:postcode":"WR9 8EJ",
    "sg:province":"Worcestershire",
    "sg:tags":[
        "ladieswear"
    ],
    "wof:name":"Firefly Ladies Fashion",
    "wof:placetype":"venue"
},
  "geometry": {"coordinates":[-2.1484360695,52.2686157227],"type":"Point"}
}