{
  "type": "Feature",
  "properties": {
    "addr:full":"Grove Road Tring Buckinghamshire HP23 5PD",
    "addr:postcode":"hp23 5pd",
    "addr:street":"Grove Road",
    "iso:country":"GB",
    "sg:address":"Grove Road",
    "sg:city":"Tring",
    "sg:classifiers":[
        {
            "category":"Education",
            "subcategory":"School",
            "type":"Public Place"
        }
    ],
    "sg:phone":"+44 1442 822056",
    "sg:postcode":"HP23 5PD",
    "sg:province":"Buckinghamshire",
    "sg:tags":[
        "local",
        "authority"
    ],
    "wof:name":"Grove Road Primary School",
    "wof:placetype":"venue"
},
  "geometry": {"coordinates":[-0.65041399,51.8024787903],"type":"Point"}
}