{
  "type": "Feature",
  "properties": {
    "addr:full":"Battersea Park Service Station, 15-25 Parkgate Road London Greater London SW11 4NP",
    "addr:housenumber":"15-25",
    "addr:postcode":"sw11 4np",
    "addr:street":"Battersea Park;Parkgate Road",
    "iso:country":"GB",
    "sg:address":"Battersea Park Service Station, 15-25 Parkgate Road",
    "sg:city":"London",
    "sg:classifiers":[
        {
            "category":"Autos & Motor Vehicles",
            "subcategory":"Fuel & Gas Station",
            "type":"Retail Goods"
        }
    ],
    "sg:phone":"+44 20 7924 7108",
    "sg:postcode":"SW11 4NP",
    "sg:province":"Greater London",
    "sg:tags":[
        "hr",
        "petrol"
    ],
    "wof:name":"Battersea Park Service Station",
    "wof:placetype":"venue"
},
  "geometry": {"coordinates":[-0.165961,51.479248],"type":"Point"}
}