{
  "type": "Feature",
  "properties": {
    "addr:full":"1 Queen Street Peterborough Cambridgeshire PE1 1PA",
    "addr:housenumber":"1",
    "addr:postcode":"pe1 1pa",
    "addr:street":"Queen Street",
    "iso:country":"GB",
    "sg:address":"1 Queen Street",
    "sg:city":"Peterborough",
    "sg:classifiers":[
        {
            "category":"Real Estate",
            "subcategory":"Real Estate Agent",
            "type":"Services"
        }
    ],
    "sg:phone":"+44 1733 558871",
    "sg:postcode":"PE1 1PA",
    "sg:province":"Cambridgeshire",
    "wof:name":"Bairstow Eves",
    "wof:placetype":"venue"
},
  "geometry": {"coordinates":[-0.244525,52.572803],"type":"Point"}
}