{
  "type": "Feature",
  "properties": {
    "addr:full":"Merville, Pilgrims Way, Detling Maidstone Kent ME14 3EX",
    "addr:postcode":"me14 3ex",
    "addr:street":"Pilgrims Way",
    "iso:country":"GB",
    "sg:address":"Merville, Pilgrims Way, Detling",
    "sg:city":"Maidstone",
    "sg:classifiers":[
        {
            "category":"Professional",
            "subcategory":"Engineering",
            "type":"Services"
        }
    ],
    "sg:phone":"+44 1622 739920",
    "sg:postcode":"ME14 3EX",
    "sg:province":"Kent",
    "sg:tags":[
        "gas",
        "engineer"
    ],
    "wof:name":"Wallace Gas Services",
    "wof:placetype":"venue"
},
  "geometry": {"coordinates":[0.5693740249,51.293384552],"type":"Point"}
}