{
  "type": "Feature",
  "properties": {
    "iso:country":"GB",
    "sg:address":"Derbyshire Business Development Centre, Beaufort Street",
    "sg:city":"Derby",
    "sg:classifiers":[
        {
            "category":"Shopping",
            "subcategory":"Clothing, Apparel, & Fashions",
            "type":"Retail Goods"
        }
    ],
    "sg:phone":"+44 1332 298988",
    "sg:postcode":"DE21 6AX",
    "sg:province":"Derbyshire",
    "sg:tags":[
        "workwear",
        "protective",
        "clothing"
    ],
    "wof:name":"Derby Unitex Ltd.",
    "wof:placetype":"venue"
},
  "geometry": {"coordinates":[-1.45579,52.92762],"type":"Point"}
}