{
  "type": "Feature",
  "properties": {
    "addr:full":"Fir Tree Yard, 68a Stockett Lane Maidstone Kent ME17 4PY",
    "addr:housenumber":"68a",
    "addr:postcode":"me17 4py",
    "addr:street":"Fir Tree Yard;Stockett Lane",
    "iso:country":"GB",
    "sg:address":"Fir Tree Yard, 68a Stockett Lane",
    "sg:city":"Maidstone",
    "sg:classifiers":[
        {
            "category":"Building & Trades",
            "subcategory":"Construction",
            "type":"Services"
        }
    ],
    "sg:phone":"+44 1622 745410",
    "sg:postcode":"ME17 4PY",
    "sg:province":"Kent",
    "sg:tags":[
        "builder"
    ],
    "wof:name":"Brattle & Bray Ltd.",
    "wof:placetype":"venue"
},
  "geometry": {"coordinates":[0.4969500005,51.2369308472],"type":"Point"}
}