{
  "type": "Feature",
  "properties": {
    "iso:country":"GB",
    "sg:address":"Prince Charles Avenue, Orsett",
    "sg:city":"Grays",
    "sg:classifiers":[
        {
            "category":"Community Center",
            "type":"Public Place"
        }
    ],
    "sg:phone":"+44 1375 891402",
    "sg:postcode":"RM16 3HS",
    "sg:province":"Essex",
    "sg:tags":[
        "conference",
        "room",
        "centre"
    ],
    "wof:name":"V S H Ltd.",
    "wof:placetype":"venue"
},
  "geometry": {"coordinates":[0.3667750061,51.5123214722],"type":"Point"}
}