{
  "type": "Feature",
  "properties": {
    "iso:country":"GB",
    "sg:address":"3 Palmerston Court, 2-8 Palmerston Rd",
    "sg:city":"Sutton",
    "sg:classifiers":[
        {
            "category":"Real Estate",
            "subcategory":"Architect",
            "type":"Services"
        }
    ],
    "sg:phone":"+44 20 8642 7100",
    "sg:postcode":"SM1 4QL",
    "sg:province":"Surrey",
    "sg:tags":[
        "architectural"
    ],
    "wof:name":"W P Design",
    "wof:placetype":"venue"
},
  "geometry": {"coordinates":[-0.197558,51.361191],"type":"Point"}
}