{
  "type": "Feature",
  "properties": {
    "iso:country":"GB",
    "sg:address":"Kingsway House",
    "sg:city":"Hove",
    "sg:classifiers":[
        {
            "category":"Wholesale",
            "subcategory":"Books, Periodicals, & Newspapers",
            "type":"Manufacturing & Wholesale Goods"
        }
    ],
    "sg:postcode":"BN3 2DL",
    "sg:province":"East Sussex",
    "sg:tags":[
        "publishing"
    ],
    "wof:name":"Gateway Publishing & Events Ltd.",
    "wof:placetype":"venue"
},
  "geometry": {"coordinates":[-0.180084005,50.8256149292],"type":"Point"}
}