{
  "type": "Feature",
  "properties": {
    "addr:full":"Presbytery, 59 The Avenue Tadworth Surrey KT20 5DB",
    "addr:housenumber":"59",
    "addr:postcode":"kt20 5db",
    "addr:street":"The Avenue",
    "iso:country":"GB",
    "sg:address":"Presbytery, 59 The Avenue",
    "sg:city":"Tadworth",
    "sg:classifiers":[
        {
            "category":"Place Of Worship",
            "type":"Public Place"
        }
    ],
    "sg:phone":"+44 1737 813102",
    "sg:postcode":"KT20 5DB",
    "sg:province":"Surrey",
    "wof:name":"St John The Evangelist Church",
    "wof:placetype":"venue"
},
  "geometry": {"coordinates":[-0.239394,51.291584],"type":"Point"}
}