{
  "type": "Feature",
  "properties": {
    "iso:country":"GB",
    "sg:address":"137 Fennycroft Rd",
    "sg:city":"Hemel Hempstead",
    "sg:classifiers":[
        {
            "category":"Building & Trades",
            "subcategory":"Plumbing",
            "type":"Services"
        }
    ],
    "sg:phone":"+44 1442 217327",
    "sg:postcode":"HP1 3NR",
    "sg:province":"Hertfordshire",
    "sg:tags":[
        "heating"
    ],
    "wof:name":"A Cox",
    "wof:placetype":"venue"
},
  "geometry": {"coordinates":[-0.493305,51.766598],"type":"Point"}
}