{
  "type": "Feature",
  "properties": {
    "addr:full":"High Street, Porlock Minehead Somerset TA24 8PT",
    "addr:postcode":"ta24 8pt",
    "addr:street":"High Street",
    "iso:country":"GB",
    "sg:address":"High Street, Porlock",
    "sg:city":"Minehead",
    "sg:classifiers":[
        {
            "category":"Personal",
            "subcategory":"Beauty Salon",
            "type":"Services"
        }
    ],
    "sg:postcode":"TA24 8PT",
    "sg:province":"Somerset",
    "sg:tags":[
        "unisex",
        "hairdresser"
    ],
    "wof:name":"Eastern Importers",
    "wof:placetype":"venue"
},
  "geometry": {"coordinates":[-3.5935790539,51.209236145],"type":"Point"}
}