{
  "type": "Feature",
  "properties": {
    "addr:full":"56 Dundee Road Dundee Angus DD5 1HY",
    "addr:housenumber":"56",
    "addr:postcode":"dd5 1hy",
    "addr:street":"Dundee Road",
    "iso:country":"GB",
    "sg:address":"56 Dundee Road",
    "sg:city":"Dundee",
    "sg:classifiers":[
        {
            "category":"Shopping",
            "subcategory":"News",
            "type":"Retail Goods"
        }
    ],
    "sg:phone":"+44 1382 778440",
    "sg:postcode":"DD5 1HY",
    "sg:province":"Angus",
    "sg:tags":[
        "newsagent"
    ],
    "wof:name":"Miller's Newsagents",
    "wof:placetype":"venue"
},
  "geometry": {"coordinates":[-2.888652,56.469414],"type":"Point"}
}