{
  "type": "Feature",
  "properties": {
    "addr:full":"67 Mayfield Close, Rose Grn Bognor Regis West Sussex PO21 3PS",
    "addr:housenumber":"67",
    "addr:postcode":"po21 3ps",
    "addr:street":"Mayfield Close Rose Grn",
    "iso:country":"GB",
    "sg:address":"67 Mayfield Close, Rose Grn",
    "sg:city":"Bognor Regis",
    "sg:classifiers":[
        {
            "category":"Shopping",
            "subcategory":"Computers & Home Electronics",
            "type":"Retail Goods"
        }
    ],
    "sg:postcode":"PO21 3PS",
    "sg:province":"West Sussex",
    "sg:tags":[
        "equipment",
        "radio"
    ],
    "wof:name":"Radio Services",
    "wof:placetype":"venue"
},
  "geometry": {"coordinates":[-0.7259420156,50.7841186523],"type":"Point"}
}