{
  "type": "Feature",
  "properties": {
    "iso:country":"GB",
    "sg:address":"20 Station Street",
    "sg:city":"Saltburn-by-the-sea",
    "sg:classifiers":[
        {
            "category":"Shopping",
            "subcategory":"Mobile Phones",
            "type":"Retail Goods"
        },
        {
            "category":"Communications",
            "type":"Services"
        }
    ],
    "sg:phone":"+44 1287 622211",
    "sg:postcode":"TS12 1AE",
    "sg:province":"North Yorkshire",
    "sg:tags":[
        "telecommunication"
    ],
    "wof:name":"Total Telecom (Northern) Ltd.",
    "wof:placetype":"venue"
},
  "geometry": {"coordinates":[-0.974002,54.582687],"type":"Point"}
}