{
  "type": "Feature",
  "properties": {
    "addr:full":"38 Merritt Road, Crofton Park London Greater London SE4 1DY",
    "addr:housenumber":"38",
    "addr:postcode":"se4 1dy",
    "addr:street":"Merritt Road",
    "iso:country":"GB",
    "sg:address":"38 Merritt Road, Crofton Park",
    "sg:city":"London",
    "sg:classifiers":[
        {
            "category":"Professional",
            "subcategory":"Management & Consulting",
            "type":"Services"
        }
    ],
    "sg:phone":"+44 20 8692 9783",
    "sg:postcode":"SE4 1DY",
    "sg:province":"Greater London",
    "sg:tags":[
        "consultant",
        "business"
    ],
    "wof:name":"Tonick Consultancy Services Ltd.",
    "wof:placetype":"venue"
},
  "geometry": {"coordinates":[-0.034652,51.455585],"type":"Point"}
}