{
  "type": "Feature",
  "properties": {
    "iso:country":"GB",
    "sg:address":"8 Aylestone Walk, Moston",
    "sg:city":"Manchester",
    "sg:classifiers":[
        {
            "category":"Professional",
            "subcategory":"Art Services",
            "type":"Services"
        }
    ],
    "sg:postcode":"M40 5NY",
    "sg:province":"Greater Manchester",
    "sg:tags":[
        "photographer"
    ],
    "wof:name":"Peter Sherwood Photography",
    "wof:placetype":"venue"
},
  "geometry": {"coordinates":[-2.191999,53.506351],"type":"Point"}
}