{
  "type": "Feature",
  "properties": {
    "iso:country":"GB",
    "sg:address":"Horseshoe Nurseries, White Elm Rd",
    "sg:city":"Chelmsford",
    "sg:classifiers":[
        {
            "category":"Education",
            "subcategory":"Music School",
            "type":"Public Place"
        }
    ],
    "sg:postcode":"CM3 4LR",
    "sg:province":"Essex",
    "sg:tags":[
        "conservatory"
    ],
    "wof:name":"The Conservatory Company",
    "wof:placetype":"venue"
},
  "geometry": {"coordinates":[0.59505,51.69603],"type":"Point"}
}