{
  "type": "Feature",
  "properties": {
    "addr:full":"67 Wide Bargate Boston Lincolnshire PE21 6SG",
    "addr:housenumber":"67",
    "addr:postcode":"pe21 6sg",
    "addr:street":"Wide Bargate",
    "iso:country":"GB",
    "sg:address":"67 Wide Bargate",
    "sg:city":"Boston",
    "sg:classifiers":[
        {
            "category":"Professional",
            "subcategory":"Employment Agencies",
            "type":"Services"
        }
    ],
    "sg:postcode":"PE21 6SG",
    "sg:province":"Lincolnshire",
    "sg:tags":[
        "consultant"
    ],
    "wof:name":"Worksearch",
    "wof:placetype":"venue"
},
  "geometry": {"coordinates":[-0.0193969999,52.9805183411],"type":"Point"}
}