{
  "type": "Feature",
  "properties": {
    "addr:full":"The Old Chapel, Housesteads Drive Chester Cheshire CH2 3DL",
    "addr:postcode":"ch2 3dl",
    "addr:street":"Housesteads Drive",
    "iso:country":"GB",
    "sg:address":"The Old Chapel, Housesteads Drive",
    "sg:city":"Chester",
    "sg:classifiers":[
        {
            "category":"Arena",
            "subcategory":"Sports Club",
            "type":"Entertainment"
        }
    ],
    "sg:phone":"+44 1244 351484",
    "sg:postcode":"CH2 3DL",
    "sg:province":"Cheshire",
    "wof:name":"Deva Judokwai Sports & Community Centre",
    "wof:placetype":"venue"
},
  "geometry": {"coordinates":[-2.87043,53.198071],"type":"Point"}
}