{
  "type": "Feature",
  "properties": {
    "iso:country":"GB",
    "sg:address":"Waterloo Avenue Service Station, Waterloo Avenue",
    "sg:city":"Leiston",
    "sg:classifiers":[
        {
            "category":"Autos & Motor Vehicles",
            "subcategory":"Fuel & Gas Station",
            "type":"Retail Goods"
        }
    ],
    "sg:phone":"+44 1728 830783",
    "sg:postcode":"IP16 4HN",
    "sg:province":"Suffolk",
    "sg:tags":[
        "petrol",
        "filling"
    ],
    "wof:name":"L B Shotter & Sons",
    "wof:placetype":"venue"
},
  "geometry": {"coordinates":[1.563695,52.208408],"type":"Point"}
}