{
  "type": "Feature",
  "properties": {
    "addr:full":"7 Market Street Malton North Yorkshire YO17 7LY",
    "addr:housenumber":"7",
    "addr:postcode":"yo17 7ly",
    "addr:street":"Market Street",
    "iso:country":"GB",
    "sg:address":"7 Market Street",
    "sg:city":"Malton",
    "sg:classifiers":[
        {
            "category":"Sports & Exercise",
            "subcategory":"Gym",
            "type":"Entertainment"
        }
    ],
    "sg:phone":"+44 1653 696485",
    "sg:postcode":"YO17 7LY",
    "sg:province":"North Yorkshire",
    "sg:tags":[
        "fitness",
        "health",
        "centre"
    ],
    "wof:name":"The Workhouse",
    "wof:placetype":"venue"
},
  "geometry": {"coordinates":[-0.7999140024,54.134601593],"type":"Point"}
}