{
  "type": "Feature",
  "properties": {
    "addr:full":"65 London Wall London Greater London EC2M 5TH",
    "addr:housenumber":"65",
    "addr:postcode":"ec2m 5th",
    "addr:street":"London Wall",
    "iso:country":"GB",
    "sg:address":"65 London Wall",
    "sg:city":"London",
    "sg:classifiers":[
        {
            "category":"Communications",
            "subcategory":"Newspaper",
            "type":"Services"
        }
    ],
    "sg:postcode":"EC2M 5TH",
    "sg:province":"Greater London",
    "sg:tags":[
        "magazine"
    ],
    "wof:name":"Libas International Ltd",
    "wof:placetype":"venue"
},
  "geometry": {"coordinates":[-0.0857530013,51.5167617798],"type":"Point"}
}