{
  "type": "Feature",
  "properties": {
    "iso:country":"GB",
    "sg:address":"6 Bank Street",
    "sg:city":"Newton Abbot",
    "sg:classifiers":[
        {
            "category":"Shopping",
            "subcategory":"Books",
            "type":"Retail Goods"
        }
    ],
    "sg:phone":"+44 1626 352610",
    "sg:postcode":"TQ12 2JW",
    "sg:province":"Devon",
    "sg:tags":[
        "bookseller"
    ],
    "wof:name":"Mitre Bookshop",
    "wof:placetype":"venue"
},
  "geometry": {"coordinates":[-3.612136,50.529762],"type":"Point"}
}