{
  "type": "Feature",
  "properties": {
    "iso:country":"GB",
    "sg:address":"61-79 Norwood High St",
    "sg:city":"London",
    "sg:classifiers":[
        {
            "category":"Manufacturing",
            "subcategory":"Building Materials",
            "type":"Manufacturing & Wholesale Goods"
        }
    ],
    "sg:phone":"+44 20 8670 0700",
    "sg:postcode":"SE27 9JS",
    "sg:province":"Greater London",
    "sg:tags":[
        "merchant",
        "builder"
    ],
    "wof:name":"Travis Perkins Plc",
    "wof:placetype":"venue"
},
  "geometry": {"coordinates":[-0.1018539965,51.4308242798],"type":"Point"}
}