{
  "type": "Feature",
  "properties": {
    "iso:country":"GB",
    "sg:address":"Unit D, Stafford Park 12",
    "sg:city":"Telford",
    "sg:classifiers":[
        {
            "category":"Professional",
            "subcategory":"Business Services",
            "type":"Services"
        }
    ],
    "sg:phone":"+44 1952 292520",
    "sg:postcode":"TF3 3BJ",
    "sg:province":"Shropshire",
    "sg:tags":[
        "distribution"
    ],
    "wof:name":"P & O Trans European Ltd",
    "wof:placetype":"venue"
},
  "geometry": {"coordinates":[-2.416149,52.672195],"type":"Point"}
}