{
  "type": "Feature",
  "properties": {
    "iso:country":"GB",
    "sg:address":"Kingsbridge Road",
    "sg:city":"Huddersfield",
    "sg:classifiers":[
        {
            "category":"Professional",
            "subcategory":"Art Services",
            "type":"Services"
        }
    ],
    "sg:phone":"+44 1484 547947",
    "sg:postcode":"HD1 3AX",
    "sg:province":"West Yorkshire",
    "sg:tags":[
        "framing"
    ],
    "wof:name":"A C Framing (Sales) Ltd.",
    "wof:placetype":"venue"
},
  "geometry": {"coordinates":[-1.779849,53.639641],"type":"Point"}
}