{
  "type": "Feature",
  "properties": {
    "addr:full":"Boulton Road Birmingham West Midlands B21 0RE",
    "addr:postcode":"b21 0re",
    "addr:street":"Boulton Road",
    "iso:country":"GB",
    "sg:address":"Boulton Road",
    "sg:city":"Birmingham",
    "sg:classifiers":[
        {
            "category":"Education",
            "subcategory":"School",
            "type":"Public Place"
        },
        {
            "category":"Government",
            "subcategory":"Office",
            "type":"Public Place"
        }
    ],
    "sg:phone":"+44 121 554 1497",
    "sg:postcode":"B21 0RE",
    "sg:province":"West Midlands",
    "sg:tags":[
        "local",
        "authority"
    ],
    "wof:name":"James Watt Infant School",
    "wof:placetype":"venue"
},
  "geometry": {"coordinates":[-1.937989,52.503056],"type":"Point"}
}