{
  "type": "Feature",
  "properties": {
    "addr:full":"Dickson Drive Irvine North Ayrshire KA12 9EW",
    "addr:postcode":"ka12 9ew",
    "addr:street":"Dickson Drive",
    "iso:country":"GB",
    "sg:address":"Dickson Drive",
    "sg:city":"Irvine",
    "sg:classifiers":[
        {
            "category":"Community Center",
            "type":"Public Place"
        },
        {
            "category":"Organizations",
            "subcategory":"Community Association",
            "type":"Services"
        }
    ],
    "sg:phone":"+44 1294 311279",
    "sg:postcode":"KA12 9EW",
    "sg:province":"North Ayrshire",
    "sg:tags":[
        "club",
        "social",
        "centre"
    ],
    "wof:name":"Redburn Community Centre",
    "wof:placetype":"venue"
},
  "geometry": {"coordinates":[-4.6686639786,55.6289749146],"type":"Point"}
}