{
  "type": "Feature",
  "properties": {
    "addr:full":"34 Friar Street Worcester Worcestershire WR1 2LZ",
    "addr:housenumber":"34",
    "addr:postcode":"wr1 2lz",
    "addr:street":"Friar Street",
    "iso:country":"GB",
    "sg:address":"34 Friar Street",
    "sg:city":"Worcester",
    "sg:classifiers":[
        {
            "category":"Restaurant",
            "type":"Food & Drink"
        }
    ],
    "sg:phone":"+44 1905 26929",
    "sg:postcode":"WR1 2LZ",
    "sg:province":"Worcestershire",
    "wof:name":"The Conservatory Cafe Bar",
    "wof:placetype":"venue"
},
  "geometry": {"coordinates":[-2.2190699577,52.1901397705],"type":"Point"}
}