{
  "type": "Feature",
  "properties": {
    "iso:country":"GB",
    "sg:address":"20-26 Wood Street",
    "sg:city":"Ashby-de-la-zouch",
    "sg:classifiers":[
        {
            "category":"Autos & Motor Vehicles",
            "subcategory":"Auto Supplies",
            "type":"Retail Goods"
        }
    ],
    "sg:phone":"+44 1530 417416",
    "sg:postcode":"LE65 1EG",
    "sg:province":"Derbyshire",
    "sg:tags":[
        "exhaust",
        "absorber",
        "shock"
    ],
    "wof:name":"Kwik-Fit",
    "wof:placetype":"venue"
},
  "geometry": {"coordinates":[-1.465446949,52.7489128113],"type":"Point"}
}