{
  "type": "Feature",
  "properties": {
    "addr:full":"57 Emsworth Rd Portsmouth Hampshire PO2 0BS",
    "addr:housenumber":"57",
    "addr:postcode":"hampshire po2 0bs",
    "addr:street":"Emsworth Rd",
    "iso:country":"GB",
    "sg:address":"57 Emsworth Rd",
    "sg:city":"Portsmouth",
    "sg:classifiers":[
        {
            "category":"Retail",
            "subcategory":"Auto Repair",
            "type":"Services"
        }
    ],
    "sg:phone":"+44 23 9265 2852",
    "sg:postcode":"PO2 0BS",
    "sg:province":"Hampshire",
    "sg:tags":[
        "modification",
        "garage"
    ],
    "wof:name":"Go Autos",
    "wof:placetype":"venue"
},
  "geometry": {"coordinates":[-1.077785,50.813931],"type":"Point"}
}