{
  "type": "Feature",
  "properties": {
    "addr:full":"Bagham Barn Ct, Canterbury Rd, Chilham Canterbury Kent CT4 8AJ",
    "addr:postcode":"ct4 8aj",
    "addr:street":"Barn Ct Canterbury Rd",
    "iso:country":"GB",
    "sg:address":"Bagham Barn Ct, Canterbury Rd, Chilham",
    "sg:city":"Canterbury",
    "sg:classifiers":[
        {
            "category":"Retail",
            "subcategory":"Auto Repair",
            "type":"Services"
        }
    ],
    "sg:postcode":"CT4 8AJ",
    "sg:province":"Kent",
    "sg:tags":[
        "garage"
    ],
    "wof:name":"Jeffery,D,",
    "wof:placetype":"venue"
},
  "geometry": {"coordinates":[0.963739,51.243881],"type":"Point"}
}