{
  "type": "Feature",
  "properties": {
    "iso:country":"GB",
    "sg:address":"Station Road",
    "sg:city":"Pulborough",
    "sg:classifiers":[
        {
            "category":"Fast Food",
            "type":"Food & Drink"
        },
        {
            "category":"Food & Beverages",
            "subcategory":"Meat & Fish",
            "type":"Retail Goods"
        }
    ],
    "sg:phone":"+44 1798 875353",
    "sg:postcode":"RH20 1AH",
    "sg:province":"West Sussex",
    "sg:tags":[
        "shop",
        "chip"
    ],
    "wof:name":"Station Fryer",
    "wof:placetype":"venue"
},
  "geometry": {"coordinates":[-0.514244,50.956959],"type":"Point"}
}