{
  "type": "Feature",
  "properties": {
    "iso:country":"GB",
    "sg:address":"27 Ramshill Road, Southcliffe",
    "sg:city":"Scarborough",
    "sg:classifiers":[
        {
            "category":"Food & Beverages",
            "subcategory":"Meat & Fish",
            "type":"Retail Goods"
        }
    ],
    "sg:phone":"+44 1723 360022",
    "sg:postcode":"YO11 2LW",
    "sg:province":"North Yorkshire",
    "sg:tags":[
        "butcher"
    ],
    "wof:name":"The Gibson Butchers",
    "wof:placetype":"venue"
},
  "geometry": {"coordinates":[-0.4029769897,54.2732315063],"type":"Point"}
}