{
  "type": "Feature",
  "properties": {
    "iso:country":"GB",
    "sg:address":"Unit 19 Chapel Way, Avon Valley Business Park",
    "sg:city":"Bristol",
    "sg:classifiers":[
        {
            "category":"Retail",
            "subcategory":"Auto Repair",
            "type":"Services"
        }
    ],
    "sg:phone":"+44 117 977 2132",
    "sg:postcode":"BS4 4EU",
    "sg:province":"City of Bristol",
    "sg:tags":[
        "modification",
        "garage"
    ],
    "wof:name":"Harris Autos",
    "wof:placetype":"venue"
},
  "geometry": {"coordinates":[-2.5463819504,51.4522438049],"type":"Point"}
}