{
  "type": "Feature",
  "properties": {
    "addr:full":"980 Oxford Road Reading Berkshire RG30 6TW",
    "addr:housenumber":"980",
    "addr:postcode":"rg30 6tw",
    "addr:street":"Oxford Road",
    "iso:country":"GB",
    "sg:address":"980 Oxford Road",
    "sg:city":"Reading",
    "sg:classifiers":[
        {
            "category":"Food & Beverages",
            "subcategory":"Supermarket",
            "type":"Retail Goods"
        }
    ],
    "sg:phone":"+44 118 942 2444",
    "sg:postcode":"RG30 6TW",
    "sg:province":"Berkshire",
    "wof:name":"Waitrose Supermarkets",
    "wof:placetype":"venue"
},
  "geometry": {"coordinates":[-1.0195690393,51.4654006958],"type":"Point"}
}