{
  "type": "Feature",
  "properties": {
    "addr:full":"Nutgrove Road St Helens Cheshire WA9 5JR",
    "addr:postcode":"wa9 5jr",
    "addr:street":"Nutgrove Road",
    "iso:country":"GB",
    "sg:address":"Nutgrove Road",
    "sg:city":"St Helens",
    "sg:classifiers":[
        {
            "category":"Social Services",
            "subcategory":"Retirement Home",
            "type":"Services"
        }
    ],
    "sg:phone":"+44 151 426 4114",
    "sg:postcode":"WA9 5JR",
    "sg:province":"Cheshire",
    "sg:tags":[
        "rest"
    ],
    "wof:name":"Brown Edge House",
    "wof:placetype":"venue"
},
  "geometry": {"coordinates":[-2.7595870495,53.4332084656],"type":"Point"}
}