{
  "type": "Feature",
  "properties": {
    "iso:country":"GB",
    "sg:address":"22 Little Russell Street",
    "sg:city":"London",
    "sg:classifiers":[
        {
            "category":"Travel",
            "subcategory":"Travel Agent",
            "type":"Entertainment"
        }
    ],
    "sg:phone":"+44 20 7242 0440",
    "sg:postcode":"WC1A 2HL",
    "sg:province":"Greater London",
    "wof:name":"The Travel Centre (Potters Bar) Ltd.",
    "wof:placetype":"venue"
},
  "geometry": {"coordinates":[-0.1249589995,51.518157959],"type":"Point"}
}