{
  "type": "Feature",
  "properties": {
    "addr:full":"Chichester House, High Street, Ditchling Hassocks East Sussex BN6 8SY",
    "addr:postcode":"bn6 8sy",
    "addr:street":"High Street",
    "iso:country":"GB",
    "sg:address":"Chichester House, High Street, Ditchling",
    "sg:city":"Hassocks",
    "sg:classifiers":[
        {
            "category":"Building & Trades",
            "subcategory":"Construction",
            "type":"Services"
        }
    ],
    "sg:postcode":"BN6 8SY",
    "sg:province":"East Sussex",
    "sg:tags":[
        "builder"
    ],
    "wof:name":"Crighton Building Contractors Ltd",
    "wof:placetype":"venue"
},
  "geometry": {"coordinates":[-0.1402689964,50.9239959717],"type":"Point"}
}