{
  "type": "Feature",
  "properties": {
    "addr:full":"Tweentown Cheddar Somerset BS27 3JE",
    "addr:postcode":"bs27 3je",
    "addr:street":"Tweentown Cheddar",
    "iso:country":"GB",
    "sg:address":"Tweentown",
    "sg:city":"Cheddar",
    "sg:classifiers":[
        {
            "category":"Retail",
            "subcategory":"Auto Repair",
            "type":"Services"
        }
    ],
    "sg:phone":"+44 1934 742955",
    "sg:postcode":"BS27 3JE",
    "sg:province":"Somerset",
    "sg:tags":[
        "modification",
        "garage"
    ],
    "wof:name":"Cheddar Motors Ltd.",
    "wof:placetype":"venue"
},
  "geometry": {"coordinates":[-2.780824,51.280384],"type":"Point"}
}