{
  "type": "Feature",
  "properties": {
    "addr:full":"1a Melbourne St Coalville Leicestershire LE67 3QU",
    "addr:housenumber":"1a",
    "addr:postcode":"le67 3qu",
    "addr:street":"Melbourne St",
    "iso:country":"GB",
    "sg:address":"1a Melbourne St",
    "sg:city":"Coalville",
    "sg:classifiers":[
        {
            "category":"Building & Trades",
            "subcategory":"Cleaning & Sanitation",
            "type":"Services"
        }
    ],
    "sg:phone":"+44 1530 836060",
    "sg:postcode":"LE67 3QU",
    "sg:province":"Leicestershire",
    "sg:tags":[
        "commercial"
    ],
    "wof:name":"Miracle Clean",
    "wof:placetype":"venue"
},
  "geometry": {"coordinates":[-1.371984,52.722481],"type":"Point"}
}