{
  "type": "Feature",
  "properties": {
    "addr:full":"50-52 Station Hill Reading Berkshire RG1 1NF",
    "addr:housenumber":"50-52",
    "addr:postcode":"rg1 1nf",
    "addr:street":"Station Hill",
    "iso:country":"GB",
    "sg:address":"50-52 Station Hill",
    "sg:city":"Reading",
    "sg:classifiers":[
        {
            "category":"Professional",
            "subcategory":"Printing & Photocopies",
            "type":"Services"
        }
    ],
    "sg:phone":"+44 118 950 3100",
    "sg:postcode":"RG1 1NF",
    "sg:province":"Berkshire",
    "sg:tags":[
        "printer"
    ],
    "wof:name":"Impress Print & Design",
    "wof:placetype":"venue"
},
  "geometry": {"coordinates":[-0.9731910229,51.4584541321],"type":"Point"}
}