{
  "type": "Feature",
  "properties": {
    "iso:country":"GB",
    "sg:address":"57 Howden Hall Road",
    "sg:city":"Edinburgh",
    "sg:classifiers":[
        {
            "category":"Health Services",
            "subcategory":"Doctor",
            "type":"Services"
        }
    ],
    "sg:phone":"+44 131 664 2377",
    "sg:postcode":"EH16 6PL",
    "sg:province":"City of Edinburgh",
    "sg:tags":[
        "practitioners"
    ],
    "wof:name":"Howdenhall Surgery",
    "wof:placetype":"venue"
},
  "geometry": {"coordinates":[-3.1642699242,55.9017486572],"type":"Point"}
}