{
  "type": "Feature",
  "properties": {
    "addr:full":"Evelyn House, 62 Oxford St West End Hampshire W1N 9LF",
    "addr:housenumber":"62",
    "addr:postcode":"w1n 9lf",
    "addr:street":"Oxford St",
    "iso:country":"GB",
    "sg:address":"Evelyn House, 62 Oxford St",
    "sg:city":"West End",
    "sg:classifiers":[
        {
            "category":"Communications",
            "type":"Services"
        }
    ],
    "sg:phone":"+44 20 7631 0777",
    "sg:postcode":"W1N 9LF",
    "sg:province":"Hampshire",
    "sg:tags":[
        "audio-visual"
    ],
    "wof:name":"Blades Group Services",
    "wof:placetype":"venue"
},
  "geometry": {"coordinates":[-0.1663939953,51.5156593323],"type":"Point"}
}