{
  "type": "Feature",
  "properties": {
    "addr:full":"131 Bushmead Rd Luton Bedfordshire LU2 7YT",
    "addr:housenumber":"131",
    "addr:postcode":"lu2 7yt",
    "addr:street":"Bushmead Rd",
    "iso:country":"GB",
    "sg:address":"131 Bushmead Rd",
    "sg:city":"Luton",
    "sg:classifiers":[
        {
            "category":"Health Services",
            "subcategory":"Doctor",
            "type":"Services"
        },
        {
            "category":"Health Services",
            "subcategory":"Clinic",
            "type":"Services"
        }
    ],
    "sg:phone":"+44 1582 484883",
    "sg:postcode":"LU2 7YT",
    "sg:province":"Bedfordshire",
    "sg:tags":[
        "nh"
    ],
    "wof:name":"Bushmead Medical Centre",
    "wof:placetype":"venue"
},
  "geometry": {"coordinates":[-0.4139100015,51.9066047668],"type":"Point"}
}