{
  "type": "Feature",
  "properties": {
    "addr:full":"24 Nith Pla Dumfries Dumfries and Galloway DG1 2PN",
    "addr:housenumber":"24",
    "addr:postcode":"dg1 2pn",
    "addr:street":"Nith Pla",
    "iso:country":"GB",
    "sg:address":"24 Nith Pla",
    "sg:city":"Dumfries",
    "sg:classifiers":[
        {
            "category":"Real Estate",
            "subcategory":"Real Estate Agent",
            "type":"Services"
        },
        {
            "category":"Organizations",
            "subcategory":"Community Association",
            "type":"Services"
        }
    ],
    "sg:phone":"+44 1387 255133",
    "sg:postcode":"DG1 2PN",
    "sg:province":"Dumfries and Galloway",
    "sg:tags":[
        "society",
        "housing"
    ],
    "wof:name":"Home Housing Association",
    "wof:placetype":"venue"
},
  "geometry": {"coordinates":[-3.609516,55.066647],"type":"Point"}
}