{
  "type": "Feature",
  "properties": {
    "iso:country":"GB",
    "sg:address":"2 Post Office Avenue",
    "sg:city":"Inverness",
    "sg:classifiers":[
        {
            "category":"Restaurant",
            "type":"Food & Drink"
        }
    ],
    "sg:phone":"+44 1463 237190",
    "sg:postcode":"IV1 1DN",
    "sg:province":"Highland",
    "sg:tags":[
        "indian"
    ],
    "wof:name":"Rajah International (Inverness) Ltd.",
    "wof:placetype":"venue"
},
  "geometry": {"coordinates":[-4.226892,57.479301],"type":"Point"}
}