{
  "type": "Feature",
  "properties": {
    "addr:full":"Millburn Cottage, Millburn St Aberdeen Aberdeen City AB11 5SS",
    "addr:postcode":"ab11 5ss",
    "addr:street":"Millburn St",
    "iso:country":"GB",
    "sg:address":"Millburn Cottage, Millburn St",
    "sg:city":"Aberdeen",
    "sg:classifiers":[
        {
            "category":"Retail",
            "subcategory":"Veterinary Services",
            "type":"Services"
        }
    ],
    "sg:phone":"+44 1224 588770",
    "sg:postcode":"AB11 5SS",
    "sg:province":"Aberdeen City",
    "sg:tags":[
        "surgeon"
    ],
    "wof:name":"Millburn Cottage Veterinary Practice",
    "wof:placetype":"venue"
},
  "geometry": {"coordinates":[-2.0915300846,57.1464500427],"type":"Point"}
}