{
  "type": "Feature",
  "properties": {
    "addr:full":"Unit D2 West Point Industrial Estate, Penarth Road Cardiff Cardiff CF11 8JQ",
    "addr:housenumber":"d2;estate",
    "addr:postcode":"cf11 8jq",
    "addr:street":"West;Industrial;Penarth Road",
    "iso:country":"GB",
    "sg:address":"Unit D2 West Point Industrial Estate, Penarth Road",
    "sg:city":"Cardiff",
    "sg:classifiers":[
        {
            "category":"Shopping",
            "type":"Retail Goods"
        }
    ],
    "sg:phone":"+44 29 2070 6200",
    "sg:postcode":"CF11 8JQ",
    "sg:province":"Cardiff",
    "sg:tags":[
        "part",
        "accessory"
    ],
    "wof:name":"Peter Boshier-Jones",
    "wof:placetype":"venue"
},
  "geometry": {"coordinates":[-3.19694,51.454971],"type":"Point"}
}