{
  "type": "Feature",
  "properties": {
    "iso:country":"GB",
    "sg:address":"Compound 14 Hallamway, Old Mill Lane Industrial Estate, Mansfield Woodhouse",
    "sg:city":"Mansfield",
    "sg:classifiers":[
        {
            "category":"Building & Trades",
            "subcategory":"Construction",
            "type":"Services"
        }
    ],
    "sg:phone":"+44 1623 623865",
    "sg:postcode":"NG19 9AL",
    "sg:province":"Derbyshire",
    "sg:tags":[
        "platform",
        "work",
        "scaffolding"
    ],
    "wof:name":"North Nottingham Scaffolding Ltd.",
    "wof:placetype":"venue"
},
  "geometry": {"coordinates":[-1.1834390163,53.1652069092],"type":"Point"}
}