{
  "type": "Feature",
  "properties": {
    "iso:country":"GB",
    "sg:address":"348 Abbey St",
    "sg:city":"Derby",
    "sg:classifiers":[
        {
            "category":"Personal",
            "subcategory":"Beauty Salon",
            "type":"Services"
        }
    ],
    "sg:phone":"+44 1332 746015",
    "sg:postcode":"DE22 3SZ",
    "sg:province":"Derbyshire",
    "sg:tags":[
        "unisex",
        "hairdresser"
    ],
    "wof:name":"Unique",
    "wof:placetype":"venue"
},
  "geometry": {"coordinates":[-1.483542,52.913834],"type":"Point"}
}