{
  "type": "Feature",
  "properties": {
    "addr:full":"Swaffham Road, Ashill Thetford Norfolk IP25 7BT",
    "addr:postcode":"ip25 7bt",
    "addr:street":"Swaffham Road",
    "iso:country":"GB",
    "sg:address":"Swaffham Road, Ashill",
    "sg:city":"Thetford",
    "sg:classifiers":[
        {
            "category":"Professional",
            "subcategory":"Engineering",
            "type":"Services"
        },
        {
            "category":"Retail",
            "subcategory":"Auto Repair",
            "type":"Services"
        }
    ],
    "sg:phone":"+44 1760 440628",
    "sg:postcode":"IP25 7BT",
    "sg:province":"Norfolk",
    "sg:tags":[
        "modification",
        "garage",
        "precision",
        "engineer"
    ],
    "wof:name":"Ashill Precision Engineering Co. Ltd.",
    "wof:placetype":"venue"
},
  "geometry": {"coordinates":[0.780673027,52.6025276184],"type":"Point"}
}