{
  "type": "Feature",
  "properties": {
    "addr:full":"322 Harrow Road Wembley Greater London HA9 6LL",
    "addr:housenumber":"322",
    "addr:postcode":"ha9 6ll",
    "addr:street":"Harrow Road",
    "iso:country":"GB",
    "sg:address":"322 Harrow Road",
    "sg:city":"Wembley",
    "sg:classifiers":[
        {
            "category":"Food & Beverages",
            "subcategory":"Liquor & Beverages",
            "type":"Retail Goods"
        }
    ],
    "sg:phone":"+44 20 8902 4600",
    "sg:postcode":"HA9 6LL",
    "sg:province":"Greater London",
    "sg:tags":[
        "beer",
        "wine",
        "spirit",
        "wines"
    ],
    "wof:name":"Pat's Off Licence",
    "wof:placetype":"venue"
},
  "geometry": {"coordinates":[-0.285539,51.553143],"type":"Point"}
}