{
  "type": "Feature",
  "properties": {
    "iso:country":"GB",
    "sg:address":"297 Cricklewood Broadway",
    "sg:city":"London",
    "sg:classifiers":[
        {
            "category":"Wholesale",
            "subcategory":"Office Equipment",
            "type":"Manufacturing & Wholesale Goods"
        },
        {
            "category":"Banks & Credit Unions",
            "subcategory":"Bureau De Change",
            "type":"Services"
        }
    ],
    "sg:phone":"+44 20 8450 7207",
    "sg:postcode":"NW2 6NX",
    "sg:province":"Greater London",
    "sg:tags":[
        "epos",
        "register",
        "cash",
        "accessory"
    ],
    "wof:name":"Cavendish Cash Registers Ltd",
    "wof:placetype":"venue"
},
  "geometry": {"coordinates":[-0.2189819962,51.5595359802],"type":"Point"}
}