{
  "type": "Feature",
  "properties": {
    "addr:full":"Unit 1 Hobbs Court, 2 Jacobs Street London Greater London SE1 2BG",
    "addr:housenumber":"unit 1;2",
    "addr:postcode":"se1 2bg",
    "addr:street":"Hobbs;Jacobs Street",
    "iso:country":"GB",
    "sg:address":"Unit 1 Hobbs Court, 2 Jacobs Street",
    "sg:city":"London",
    "sg:classifiers":[
        {
            "category":"Real Estate",
            "subcategory":"Architect",
            "type":"Services"
        }
    ],
    "sg:phone":"+44 20 7394 8850",
    "sg:postcode":"SE1 2BG",
    "sg:province":"Greater London",
    "sg:tags":[
        "architectural"
    ],
    "wof:name":"Poperinge Ltd.",
    "wof:placetype":"venue"
},
  "geometry": {"coordinates":[-0.070581,51.5009],"type":"Point"}
}