{
  "type": "Feature",
  "properties": {
    "addr:full":"31 Eastside, Kirkintilloch Glasgow East Dunbartonshire G66 1QA",
    "addr:housenumber":"31",
    "addr:postcode":"g66 1qa",
    "addr:street":"Eastside Kirkintilloch",
    "iso:country":"GB",
    "sg:address":"31 Eastside, Kirkintilloch",
    "sg:city":"Glasgow",
    "sg:classifiers":[
        {
            "category":"Shopping",
            "subcategory":"News",
            "type":"Retail Goods"
        }
    ],
    "sg:postcode":"G66 1QA",
    "sg:province":"East Dunbartonshire",
    "sg:tags":[
        "newsagent"
    ],
    "wof:name":"Mr News",
    "wof:placetype":"venue"
},
  "geometry": {"coordinates":[-4.1534910202,55.9421730042],"type":"Point"}
}