{
  "type": "Feature",
  "properties": {
    "addr:full":"51 Tenby Street North Birmingham West Midlands B1 3EG",
    "addr:housenumber":"51",
    "addr:postcode":"b1 3eg",
    "addr:street":"Tenby Street North",
    "iso:country":"GB",
    "sg:address":"51 Tenby Street North",
    "sg:city":"Birmingham",
    "sg:classifiers":[
        {
            "category":"Professional",
            "subcategory":"Printing & Photocopies",
            "type":"Services"
        }
    ],
    "sg:phone":"+44 121 236 5752",
    "sg:postcode":"B1 3EG",
    "sg:province":"West Midlands",
    "sg:tags":[
        "emblem",
        "wholesale",
        "badge"
    ],
    "wof:name":"Gladman & Norman Ltd.",
    "wof:placetype":"venue"
},
  "geometry": {"coordinates":[-1.9135140181,52.4863891602],"type":"Point"}
}