{
  "type": "Feature",
  "properties": {
    "addr:full":"1a Penfold Road Worthing West Sussex BN14 8PH",
    "addr:housenumber":"1a",
    "addr:postcode":"bn14 8ph",
    "addr:street":"Penfold Road",
    "iso:country":"GB",
    "sg:address":"1a Penfold Road",
    "sg:city":"Worthing",
    "sg:classifiers":[
        {
            "category":"Retail",
            "subcategory":"Repair Shop",
            "type":"Services"
        }
    ],
    "sg:postcode":"BN14 8PH",
    "sg:province":"West Sussex",
    "sg:tags":[
        "upholsterer"
    ],
    "wof:name":"Elliotts",
    "wof:placetype":"venue"
},
  "geometry": {"coordinates":[-0.366269,50.827694],"type":"Point"}
}