{
  "type": "Feature",
  "properties": {
    "addr:full":"Newton Square, Bampton Tiverton Devon EX16 9NE",
    "addr:postcode":"ex16 9ne",
    "addr:street":"Newton Square",
    "iso:country":"GB",
    "sg:address":"Newton Square, Bampton",
    "sg:city":"Tiverton",
    "sg:classifiers":[
        {
            "category":"Shopping",
            "subcategory":"Department Store",
            "type":"Retail Goods"
        }
    ],
    "sg:postcode":"EX16 9NE",
    "sg:province":"Devon",
    "wof:name":"Brian Seward",
    "wof:placetype":"venue"
},
  "geometry": {"coordinates":[-3.487424,50.990505],"type":"Point"}
}