{
  "type": "Feature",
  "properties": {
    "iso:country":"GB",
    "sg:address":"Unit 2c Station Road Indust Est, Hospital Rd",
    "sg:city":"Haddington",
    "sg:classifiers":[
        {
            "category":"Wholesale",
            "subcategory":"Fruits & Vegetables",
            "type":"Manufacturing & Wholesale Goods"
        }
    ],
    "sg:phone":"+44 1620 822873",
    "sg:postcode":"EH41 3PE",
    "sg:province":"East Lothian",
    "wof:name":"Miller",
    "wof:placetype":"venue"
},
  "geometry": {"coordinates":[-2.788459,55.955833],"type":"Point"}
}