{
  "type": "Feature",
  "properties": {
    "iso:country":"GB",
    "sg:address":"121 Hawkward Rd, Sible Hedingham",
    "sg:city":"Halstead",
    "sg:classifiers":[
        {
            "category":"Professional",
            "subcategory":"Business Services",
            "type":"Services"
        }
    ],
    "sg:phone":"+44 1787 462365",
    "sg:postcode":"CO9 3JX",
    "sg:province":"Essex",
    "sg:tags":[
        "distribution"
    ],
    "wof:name":"A.d Calver Light Haulage",
    "wof:placetype":"venue"
},
  "geometry": {"coordinates":[0.6358249784,51.9439964294],"type":"Point"}
}