{
  "type": "Feature",
  "properties": {
    "iso:country":"GB",
    "sg:address":"49 Queen St",
    "sg:city":"Salford",
    "sg:classifiers":[
        {
            "category":"Retail",
            "subcategory":"Auto Repair",
            "type":"Services"
        }
    ],
    "sg:phone":"+44 161 832 3650",
    "sg:postcode":"M3 7DQ",
    "sg:province":"Greater Manchester",
    "sg:tags":[
        "body",
        "car"
    ],
    "wof:name":"A & C Motor Bodies",
    "wof:placetype":"venue"
},
  "geometry": {"coordinates":[-2.2524189949,53.4867706299],"type":"Point"}
}