{
  "type": "Feature",
  "properties": {
    "iso:country":"GB",
    "sg:address":"Unit 5 Laundry Lane",
    "sg:city":"Cambridge",
    "sg:classifiers":[
        {
            "category":"Home & Garden",
            "subcategory":"Carpets & Floor Coverings",
            "type":"Retail Goods"
        }
    ],
    "sg:phone":"+44 1223 516026",
    "sg:postcode":"CB1 8DH",
    "sg:province":"Cambridgeshire",
    "sg:tags":[
        "textile",
        "floorcoverings"
    ],
    "wof:name":"M W Curley Ltd.",
    "wof:placetype":"venue"
},
  "geometry": {"coordinates":[0.157615,52.186836],"type":"Point"}
}