{
  "type": "Feature",
  "properties": {
    "addr:full":"55 Tower St Edinburgh City of Edinburgh EH6 7BN",
    "addr:housenumber":"55",
    "addr:postcode":"eh6 7bn",
    "addr:street":"Tower St Edinburgh",
    "iso:country":"GB",
    "sg:address":"55 Tower St",
    "sg:city":"Edinburgh",
    "sg:classifiers":[
        {
            "category":"Manufacturing",
            "subcategory":"Metals",
            "type":"Manufacturing & Wholesale Goods"
        }
    ],
    "sg:phone":"+44 131 555 1655",
    "sg:postcode":"EH6 7BN",
    "sg:province":"City of Edinburgh",
    "sg:tags":[
        "fab",
        "foundry"
    ],
    "wof:name":"Alchemy 3 D",
    "wof:placetype":"venue"
},
  "geometry": {"coordinates":[-3.1641139984,55.9774932861],"type":"Point"}
}