{
  "type": "Feature",
  "properties": {
    "addr:full":"Kings Road, Sunninghill Ascot Berkshire SL5 0AE",
    "addr:postcode":"sl5 0ae",
    "addr:street":"Kings Road",
    "iso:country":"GB",
    "sg:address":"Kings Road, Sunninghill",
    "sg:city":"Ascot",
    "sg:classifiers":[
        {
            "category":"Health Services",
            "subcategory":"Health Practitioner",
            "type":"Services"
        }
    ],
    "sg:phone":"+44 1628 624544",
    "sg:postcode":"SL5 0AE",
    "sg:province":"Berkshire",
    "sg:tags":[
        "osteopath"
    ],
    "wof:name":"Robin J Lansman",
    "wof:placetype":"venue"
},
  "geometry": {"coordinates":[-0.6527100205,51.4007225037],"type":"Point"}
}