{
  "type": "Feature",
  "properties": {
    "addr:full":"Unti 12 Cobham Way, Gatwick Rd Crawley Surrey RH10 2RX",
    "addr:housenumber":"12",
    "addr:postcode":"rh10 2rx",
    "addr:street":"Unti;Cobham Way Gatwick Rd",
    "iso:country":"GB",
    "sg:address":"Unti 12 Cobham Way, Gatwick Rd",
    "sg:city":"Crawley",
    "sg:classifiers":[
        {
            "category":"Autos & Motor Vehicles",
            "subcategory":"Auto Supplies",
            "type":"Retail Goods"
        }
    ],
    "sg:phone":"+44 1737 823329",
    "sg:postcode":"RH10 2RX",
    "sg:province":"Surrey",
    "sg:tags":[
        "component"
    ],
    "wof:name":"Brown Brothers",
    "wof:placetype":"venue"
},
  "geometry": {"coordinates":[-0.184753,51.118458],"type":"Point"}
}