{
  "type": "Feature",
  "properties": {
    "addr:full":"Dunfermline Business Centre, Izatt Avenue Dunfermline Fife KY11 3BZ",
    "addr:postcode":"ky11 3bz",
    "addr:street":"Avenue Dunfermline",
    "iso:country":"GB",
    "sg:address":"Dunfermline Business Centre, Izatt Avenue",
    "sg:city":"Dunfermline",
    "sg:classifiers":[
        {
            "category":"Professional",
            "subcategory":"Computer Services",
            "type":"Services"
        }
    ],
    "sg:postcode":"KY11 3BZ",
    "sg:province":"Fife",
    "sg:tags":[
        "system",
        "software"
    ],
    "wof:name":"Drummohr Technology Ltd.",
    "wof:placetype":"venue"
},
  "geometry": {"coordinates":[-3.473369,56.03577],"type":"Point"}
}