{
  "type": "Feature",
  "properties": {
    "addr:full":"Unit 4 Wellington Centre Aldershot Hampshire GU11 1DB",
    "addr:housenumber":"unit 4",
    "addr:postcode":"gu11 1db",
    "iso:country":"GB",
    "sg:address":"Unit 4 Wellington Centre",
    "sg:city":"Aldershot",
    "sg:classifiers":[
        {
            "category":"Professional",
            "subcategory":"Computer Services",
            "type":"Services"
        }
    ],
    "sg:phone":"+44 1252 311002",
    "sg:postcode":"GU11 1DB",
    "sg:province":"Hampshire",
    "sg:tags":[
        "system",
        "software"
    ],
    "wof:name":"Software Plus",
    "wof:placetype":"venue"
},
  "geometry": {"coordinates":[-0.7654989958,51.2485160828],"type":"Point"}
}