{
  "type": "Feature",
  "properties": {
    "addr:full":"12 Sefton Rd Epsom Surrey KT19 9HQ",
    "addr:housenumber":"12",
    "addr:postcode":"kt19 9hq",
    "addr:street":"Sefton Rd",
    "iso:country":"GB",
    "sg:address":"12 Sefton Rd",
    "sg:city":"Epsom",
    "sg:classifiers":[
        {
            "category":"Arts & Performance",
            "subcategory":"Music",
            "type":"Entertainment"
        }
    ],
    "sg:phone":"+44 1372 748334",
    "sg:postcode":"KT19 9HQ",
    "sg:province":"Surrey",
    "sg:tags":[
        "mobile",
        "disco"
    ],
    "wof:name":"Martini Discotheques",
    "wof:placetype":"venue"
},
  "geometry": {"coordinates":[-0.2641780078,51.3469314575],"type":"Point"}
}