{
  "type": "Feature",
  "properties": {
    "addr:full":"5 Trevelyan Terrace, High Street Bangor Gwynedd LL57 1AX",
    "addr:housenumber":"5",
    "addr:postcode":"ll57 1ax",
    "addr:street":"Trevelyan Terrace High Street",
    "iso:country":"GB",
    "sg:address":"5 Trevelyan Terrace, High Street",
    "sg:city":"Bangor",
    "sg:classifiers":[
        {
            "category":"Building & Trades",
            "subcategory":"Construction",
            "type":"Services"
        }
    ],
    "sg:phone":"+44 1248 371126",
    "sg:postcode":"LL57 1AX",
    "sg:province":"Gwynedd",
    "sg:tags":[
        "decorator",
        "painter"
    ],
    "wof:name":"D J Hughes Painter & Decorator",
    "wof:placetype":"venue"
},
  "geometry": {"coordinates":[-4.129403,53.225582],"type":"Point"}
}