{
  "type": "Feature",
  "properties": {
    "iso:country":"GB",
    "sg:address":"Premier Ho, Tennyson Dr",
    "sg:city":"Basildon",
    "sg:classifiers":[
        {
            "category":"Shopping",
            "subcategory":"Party Supplies",
            "type":"Retail Goods"
        }
    ],
    "sg:phone":"+44 1268 558002",
    "sg:postcode":"SS13 3BT",
    "sg:province":"Essex",
    "sg:tags":[
        "marquees",
        "floor",
        "tent"
    ],
    "wof:name":"M & B Marquees",
    "wof:placetype":"venue"
},
  "geometry": {"coordinates":[0.5027400255,51.5638809204],"type":"Point"}
}