{
  "type": "Feature",
  "properties": {
    "addr:full":"12 Lapwing Road, Kidsgrove Stoke-on-trent Cheshire ST7 4XP",
    "addr:housenumber":"12",
    "addr:postcode":"st7 4xp",
    "addr:street":"Lapwing Road",
    "iso:country":"GB",
    "sg:address":"12 Lapwing Road, Kidsgrove",
    "sg:city":"Stoke-on-trent",
    "sg:classifiers":[
        {
            "category":"Professional",
            "subcategory":"Detective & Security Services",
            "type":"Services"
        }
    ],
    "sg:postcode":"ST7 4XP",
    "sg:province":"Cheshire",
    "sg:tags":[
        "alarm",
        "burglar",
        "system"
    ],
    "wof:name":"South Cheshire Alarms & Electrical",
    "wof:placetype":"venue"
},
  "geometry": {"coordinates":[-2.2034380436,53.0855445862],"type":"Point"}
}