{
  "type": "Feature",
  "properties": {
    "addr:full":"Victoria Mills, Albert Street Huddersfield West Yorkshire HD1 3PG",
    "addr:postcode":"hd1 3pg",
    "addr:street":"Victoria;Albert Street",
    "iso:country":"GB",
    "sg:address":"Victoria Mills, Albert Street",
    "sg:city":"Huddersfield",
    "sg:classifiers":[
        {
            "category":"Retail",
            "subcategory":"Auto Repair",
            "type":"Services"
        }
    ],
    "sg:postcode":"HD1 3PG",
    "sg:province":"West Yorkshire",
    "sg:tags":[
        "modification",
        "garage"
    ],
    "wof:name":"S Greenwood & Sons",
    "wof:placetype":"venue"
},
  "geometry": {"coordinates":[-1.782684,53.646954],"type":"Point"}
}