{
  "type": "Feature",
  "properties": {
    "addr:full":"Moulton Park Business Centre, Redhouse Rd Northampton Northamptonshire NN3 6AQ",
    "addr:postcode":"nn3 6aq",
    "addr:street":"Redhouse Rd",
    "iso:country":"GB",
    "sg:address":"Moulton Park Business Centre, Redhouse Rd",
    "sg:city":"Northampton",
    "sg:classifiers":[
        {
            "category":"Professional",
            "subcategory":"Computer Services",
            "type":"Services"
        }
    ],
    "sg:phone":"+44 1604 497624",
    "sg:postcode":"NN3 6AQ",
    "sg:province":"Northamptonshire",
    "sg:tags":[
        "system",
        "software"
    ],
    "wof:name":"Baum Hart & Partners",
    "wof:placetype":"venue"
},
  "geometry": {"coordinates":[-0.8724489808,52.2776107788],"type":"Point"}
}