{
  "type": "Feature",
  "properties": {
    "iso:country":"GB",
    "sg:address":"59 High Street, Glynneath",
    "sg:city":"Neath",
    "sg:classifiers":[
        {
            "category":"Real Estate",
            "subcategory":"Surveying",
            "type":"Services"
        },
        {
            "category":"Real Estate",
            "subcategory":"Architect",
            "type":"Services"
        }
    ],
    "sg:phone":"+44 1639 720309",
    "sg:postcode":"SA11 5DA",
    "sg:province":"Neath Port Talbot",
    "sg:tags":[
        "surveyor",
        "valuer"
    ],
    "wof:name":"Terry Gardiner & Co",
    "wof:placetype":"venue"
},
  "geometry": {"coordinates":[-3.62091,51.746483],"type":"Point"}
}