{
  "type": "Feature",
  "properties": {
    "addr:full":"399 Stamfordham Rd Newcastle-upon-tyne Tyne and Wear NE5 5HA",
    "addr:housenumber":"399",
    "addr:postcode":"ne5 5ha",
    "addr:street":"Stamfordham Rd",
    "iso:country":"GB",
    "sg:address":"399 Stamfordham Rd",
    "sg:city":"Newcastle-upon-tyne",
    "sg:classifiers":[
        {
            "category":"Fast Food",
            "type":"Food & Drink"
        }
    ],
    "sg:postcode":"NE5 5HA",
    "sg:province":"Tyne and Wear",
    "sg:tags":[
        "away",
        "take"
    ],
    "wof:name":"Gibson,Sarah,",
    "wof:placetype":"venue"
},
  "geometry": {"coordinates":[-1.689694047,54.9986152649],"type":"Point"}
}