{
  "type": "Feature",
  "properties": {
    "iso:country":"GB",
    "sg:address":"2 Biddestone Road",
    "sg:city":"London",
    "sg:classifiers":[
        {
            "category":"Health Services",
            "subcategory":"Dentist",
            "type":"Services"
        }
    ],
    "sg:phone":"+44 20 7607 1557",
    "sg:postcode":"N7 9RA",
    "sg:province":"Greater London",
    "wof:name":"P Kylahsum B D S",
    "wof:placetype":"venue"
},
  "geometry": {"coordinates":[-0.117671,51.555283],"type":"Point"}
}