{
  "type": "Feature",
  "properties": {
    "iso:country":"GB",
    "sg:address":"75 Haverstock Hill",
    "sg:city":"London",
    "sg:classifiers":[
        {
            "category":"Travel",
            "subcategory":"Hotels & Motels",
            "type":"Entertainment"
        }
    ],
    "sg:postcode":"NW3 4SL",
    "sg:province":"Greater London",
    "wof:name":"Dargaz Limited",
    "wof:placetype":"venue"
},
  "geometry": {"coordinates":[-0.157628,51.546379],"type":"Point"}
}