{
  "type": "Feature",
  "properties": {
    "iso:country":"GB",
    "sg:address":"1a Bedford Place",
    "sg:city":"Southampton",
    "sg:classifiers":[
        {
            "category":"Fast Food",
            "type":"Food & Drink"
        }
    ],
    "sg:phone":"+44 23 8033 1816",
    "sg:postcode":"SO15 2BY",
    "sg:province":"Hampshire",
    "sg:tags":[
        "away",
        "take"
    ],
    "wof:name":"Larbi's",
    "wof:placetype":"venue"
},
  "geometry": {"coordinates":[-1.4057370424,50.9112625122],"type":"Point"}
}