{
  "type": "Feature",
  "properties": {
    "addr:full":"66 North St Stamford Cambridgeshire PE9 2YN",
    "addr:housenumber":"66",
    "addr:postcode":"pe9 2yn",
    "addr:street":"North St",
    "iso:country":"GB",
    "sg:address":"66 North St",
    "sg:city":"Stamford",
    "sg:classifiers":[
        {
            "category":"Fast Food",
            "type":"Food & Drink"
        }
    ],
    "sg:postcode":"PE9 2YN",
    "sg:province":"Cambridgeshire",
    "sg:tags":[
        "away",
        "take"
    ],
    "wof:name":"Kims Chinese Take Away",
    "wof:placetype":"venue"
},
  "geometry": {"coordinates":[-0.4834989905,52.6530151367],"type":"Point"}
}