{
  "type": "Feature",
  "properties": {
    "addr:full":"High St, Crofton Wakefield West Yorkshire WF4 1NG",
    "addr:postcode":"wf4 1ng",
    "addr:street":"High St",
    "iso:country":"GB",
    "sg:address":"High St, Crofton",
    "sg:city":"Wakefield",
    "sg:classifiers":[
        {
            "category":"Education",
            "subcategory":"Library",
            "type":"Public Place"
        }
    ],
    "sg:phone":"+44 1924 303960",
    "sg:postcode":"WF4 1NG",
    "sg:province":"West Yorkshire",
    "sg:tags":[
        "book"
    ],
    "wof:name":"Crofton Library",
    "wof:placetype":"venue"
},
  "geometry": {"coordinates":[-1.4370290041,53.664981842],"type":"Point"}
}