{
  "type": "Feature",
  "properties": {
    "addr:full":"Beckside, Longtown Carlisle Cumbria CA6 5NQ",
    "addr:postcode":"ca6 5nq",
    "addr:street":"Longtown",
    "iso:country":"GB",
    "sg:address":"Beckside, Longtown",
    "sg:city":"Carlisle",
    "sg:classifiers":[
        {
            "category":"Professional",
            "subcategory":"Engineering",
            "type":"Services"
        }
    ],
    "sg:phone":"+44 1228 791130",
    "sg:postcode":"CA6 5NQ",
    "sg:province":"Cumbria",
    "sg:tags":[
        "contractor",
        "electrical",
        "engineer"
    ],
    "wof:name":"David Taylor Electrical",
    "wof:placetype":"venue"
},
  "geometry": {"coordinates":[-2.969456,55.007263],"type":"Point"}
}