{
  "type": "Feature",
  "properties": {
    "addr:full":"50 The Copse, Bourne Lane, Woodlands Southampton Hampshire SO40 7GU",
    "addr:housenumber":"50",
    "addr:postcode":"so40 7gu",
    "addr:street":"The Copse Bourne Lane",
    "iso:country":"GB",
    "sg:address":"50 The Copse, Bourne Lane, Woodlands",
    "sg:city":"Southampton",
    "sg:classifiers":[
        {
            "category":"Manufacturing",
            "subcategory":"Buildings",
            "type":"Manufacturing & Wholesale Goods"
        }
    ],
    "sg:phone":"+44 23 8081 2880",
    "sg:postcode":"SO40 7GU",
    "sg:province":"Hampshire",
    "sg:tags":[
        "mobile",
        "home"
    ],
    "wof:name":"General Estates Co. Ltd.",
    "wof:placetype":"venue"
},
  "geometry": {"coordinates":[-1.5423389673,50.9040603638],"type":"Point"}
}