{
  "type": "Feature",
  "properties": {
    "addr:full":"144 Homerton High Street London Greater London E9 6JA",
    "addr:housenumber":"144",
    "addr:postcode":"e9 6ja",
    "addr:street":"Homerton High Street",
    "iso:country":"GB",
    "sg:address":"144 Homerton High Street",
    "sg:city":"London",
    "sg:classifiers":[
        {
            "category":"Retail",
            "subcategory":"Auto Repair",
            "type":"Services"
        }
    ],
    "sg:phone":"+44 20 8533 3701",
    "sg:postcode":"E9 6JA",
    "sg:province":"Greater London",
    "sg:tags":[
        "modification",
        "garage"
    ],
    "wof:name":"Autocheck M O T Centre",
    "wof:placetype":"venue"
},
  "geometry": {"coordinates":[-0.041192,51.548843],"type":"Point"}
}