{
  "type": "Feature",
  "properties": {
    "iso:country":"GB",
    "sg:address":"Unit Ho, Po Box 25",
    "sg:city":"Liverpool",
    "sg:classifiers":[
        {
            "category":"Professional",
            "subcategory":"Credit Reporting & Collection",
            "type":"Services"
        }
    ],
    "sg:phone":"+44 151 280 9955",
    "sg:postcode":"L24 9WS",
    "sg:province":"Merseyside",
    "sg:tags":[
        "collecting",
        "agency"
    ],
    "wof:name":"Direct Financial Recovery",
    "wof:placetype":"venue"
},
  "geometry": {"coordinates":[-2.8510100842,53.353679657],"type":"Point"}
}