{
  "type": "Feature",
  "properties": {
    "addr:full":"448-454 High Road London Greater London N17 9JN",
    "addr:housenumber":"448-454",
    "addr:postcode":"n17 9jn",
    "addr:street":"High Road",
    "iso:country":"GB",
    "sg:address":"448-454 High Road",
    "sg:city":"London",
    "sg:classifiers":[
        {
            "category":"Banks & Credit Unions",
            "subcategory":"Bank",
            "type":"Services"
        }
    ],
    "sg:phone":"+44 845 740 4404",
    "sg:postcode":"N17 9JN",
    "sg:province":"Greater London",
    "sg:tags":[
        "financial",
        "institution"
    ],
    "wof:name":"HSBC Bank plc",
    "wof:placetype":"venue"
},
  "geometry": {"coordinates":[-0.0695730001,51.5924110413],"type":"Point"}
}