{
  "type": "Feature",
  "properties": {
    "iso:country":"GB",
    "sg:address":"Maxwell Building",
    "sg:city":"Salford",
    "sg:classifiers":[
        {
            "category":"Education",
            "subcategory":"University",
            "type":"Public Place"
        }
    ],
    "sg:phone":"+44 161 743 1727",
    "sg:postcode":"M5 4WT",
    "sg:province":"Greater Manchester",
    "sg:tags":[
        "higher"
    ],
    "wof:name":"Campus University of Salford",
    "wof:placetype":"venue"
},
  "geometry": {"coordinates":[-2.2711799145,53.4847488403],"type":"Point"}
}