{
  "type": "Feature",
  "properties": {
    "addr:full":"Barton Square Manchester Greater Manchester M2 7HA",
    "addr:postcode":"m2 7ha",
    "addr:street":"Barton Square",
    "iso:country":"GB",
    "sg:address":"Barton Square",
    "sg:city":"Manchester",
    "sg:classifiers":[
        {
            "category":"Shopping",
            "subcategory":"Books",
            "type":"Retail Goods"
        }
    ],
    "sg:phone":"+44 161 832 8530",
    "sg:postcode":"M2 7HA",
    "sg:province":"Greater Manchester",
    "sg:tags":[
        "bookseller"
    ],
    "wof:name":"Sports Pages",
    "wof:placetype":"venue"
},
  "geometry": {"coordinates":[-2.24564,53.48283],"type":"Point"}
}