{
  "type": "Feature",
  "properties": {
    "iso:country":"GB",
    "sg:address":"St Johns Park, Blackheath",
    "sg:city":"London",
    "sg:classifiers":[
        {
            "category":"Travel",
            "subcategory":"Hotels & Motels",
            "type":"Entertainment"
        }
    ],
    "sg:phone":"+44 20 8853 4051",
    "sg:postcode":"SE3 7TD",
    "sg:province":"Greater London",
    "wof:name":"Vanbrugh Hotel",
    "wof:placetype":"venue"
},
  "geometry": {"coordinates":[0.01492,51.4754295349],"type":"Point"}
}