{
  "type": "Feature",
  "properties": {
    "addr:full":"Ben Knowle, Worth, Wookey Wells Somerset BA5 1LW",
    "addr:housenumber":"wookey",
    "addr:postcode":"ba5 1lw",
    "addr:street":"Ben Knowle Worth",
    "iso:country":"GB",
    "sg:address":"Ben Knowle, Worth, Wookey",
    "sg:city":"Wells",
    "sg:classifiers":[
        {
            "category":"Health Services",
            "subcategory":"Health Practitioner",
            "type":"Services"
        }
    ],
    "sg:phone":"+44 1749 675352",
    "sg:postcode":"BA5 1LW",
    "sg:province":"Somerset",
    "sg:tags":[
        "herbalist"
    ],
    "wof:name":"Kristin A Jeffs",
    "wof:placetype":"venue"
},
  "geometry": {"coordinates":[-2.6912670135,51.2068901062],"type":"Point"}
}