{
  "type": "Feature",
  "properties": {
    "addr:full":"Low Audlands, Gatebeck Kendal Cumbria LA8 0HU",
    "addr:postcode":"la8 0hu",
    "addr:street":"Gatebeck",
    "iso:country":"GB",
    "sg:address":"Low Audlands, Gatebeck",
    "sg:city":"Kendal",
    "sg:classifiers":[
        {
            "category":"Farming",
            "subcategory":"Farm",
            "type":"Manufacturing & Wholesale Goods"
        }
    ],
    "sg:phone":"+44 15395 67283",
    "sg:postcode":"LA8 0HU",
    "sg:province":"Cumbria",
    "sg:tags":[
        "mixed",
        "crop"
    ],
    "wof:name":"R T GIBSON & SON",
    "wof:placetype":"venue"
},
  "geometry": {"coordinates":[-2.693634,54.265919],"type":"Point"}
}