{
  "type": "Feature",
  "properties": {
    "addr:full":"5/6 Dukes Ct, Bognor Rd Chichester West Sussex PO19 2FX",
    "addr:housenumber":"5 / 6",
    "addr:postcode":"po19 2fx",
    "addr:street":"Dukes Ct Bognor Rd",
    "iso:country":"GB",
    "sg:address":"5/6 Dukes Ct, Bognor Rd",
    "sg:city":"Chichester",
    "sg:classifiers":[
        {
            "category":"Utilities",
            "type":"Services"
        }
    ],
    "sg:postcode":"PO19 2FX",
    "sg:province":"West Sussex",
    "sg:tags":[
        "internet"
    ],
    "wof:name":"Internet Direct Marketing Services Ltd",
    "wof:placetype":"venue"
},
  "geometry": {"coordinates":[-0.7754290104,50.8361663818],"type":"Point"}
}