{
  "type": "Feature",
  "properties": {
    "addr:full":"308-310 Slade Lane, Levenshulme Manchester Greater Manchester M19 2BY",
    "addr:housenumber":"308-310",
    "addr:postcode":"m19 2by",
    "addr:street":"Slade Lane",
    "iso:country":"GB",
    "sg:address":"308-310 Slade Lane, Levenshulme",
    "sg:city":"Manchester",
    "sg:classifiers":[
        {
            "category":"Professional",
            "subcategory":"Engineering",
            "type":"Services"
        }
    ],
    "sg:phone":"+44 161 248 4090",
    "sg:postcode":"M19 2BY",
    "sg:province":"Greater Manchester",
    "sg:tags":[
        "contractor",
        "electrical",
        "engineer"
    ],
    "wof:name":"M & B Systems (Power Instrumentation) Ltd.",
    "wof:placetype":"venue"
},
  "geometry": {"coordinates":[-2.199723959,53.4443702698],"type":"Point"}
}