{
  "type": "Feature",
  "properties": {
    "addr:full":"Invicta Works, Elliott Road Bromley Kent BR2 9NT",
    "addr:postcode":"br2 9nt",
    "addr:street":"Elliott Road",
    "iso:country":"GB",
    "sg:address":"Invicta Works, Elliott Road",
    "sg:city":"Bromley",
    "sg:classifiers":[
        {
            "category":"Communications",
            "type":"Services"
        }
    ],
    "sg:phone":"+44 20 8460 7299",
    "sg:postcode":"BR2 9NT",
    "sg:province":"Kent",
    "sg:tags":[
        "system",
        "music",
        "public",
        "address"
    ],
    "wof:name":"Michael Stevens & Partners Ltd.",
    "wof:placetype":"venue"
},
  "geometry": {"coordinates":[0.0352399983,51.3950614929],"type":"Point"}
}