{
  "type": "Feature",
  "properties": {
    "addr:full":"Queens Road Baptist Church, Queens Rd Coventry West Midlands CV1 3DE",
    "addr:postcode":"cv1 3de",
    "addr:street":"Queens;Queens Rd",
    "iso:country":"GB",
    "sg:address":"Queens Road Baptist Church, Queens Rd",
    "sg:city":"Coventry",
    "sg:classifiers":[
        {
            "category":"Social Services",
            "subcategory":"Adult Care",
            "type":"Services"
        }
    ],
    "sg:phone":"+44 24 7622 9988",
    "sg:postcode":"CV1 3DE",
    "sg:province":"West Midlands",
    "sg:tags":[
        "day",
        "centre"
    ],
    "wof:name":"Queens Road Day Centre",
    "wof:placetype":"venue"
},
  "geometry": {"coordinates":[-1.519914,52.404625],"type":"Point"}
}