{
  "type": "Feature",
  "properties": {
    "addr:full":"Maidstone Community Support Centre, Marsham St Maidstone Kent ME14 1HH",
    "addr:postcode":"me14 1hh",
    "addr:street":"Marsham St",
    "iso:country":"GB",
    "sg:address":"Maidstone Community Support Centre, Marsham St",
    "sg:city":"Maidstone",
    "sg:classifiers":[
        {
            "category":"Professional",
            "subcategory":"Lawyer & Legal Services",
            "type":"Services"
        }
    ],
    "sg:phone":"+44 1622 751327",
    "sg:postcode":"ME14 1HH",
    "sg:province":"Kent",
    "sg:tags":[
        "advice",
        "counselling"
    ],
    "wof:name":"Younger People With Dementia",
    "wof:placetype":"venue"
},
  "geometry": {"coordinates":[0.5250849724,51.2737998962],"type":"Point"}
}