{
  "type": "Feature",
  "properties": {
    "addr:full":"Unit 2 Tranters Yd, Whitehorse St Baldock Bedfordshire SG7 6QF",
    "addr:housenumber":"unit 2",
    "addr:postcode":"sg7 6qf",
    "addr:street":"Tranters Yd Whitehorse St",
    "iso:country":"GB",
    "sg:address":"Unit 2 Tranters Yd, Whitehorse St",
    "sg:city":"Baldock",
    "sg:classifiers":[
        {
            "category":"Home & Garden",
            "subcategory":"Furniture",
            "type":"Retail Goods"
        }
    ],
    "sg:postcode":"SG7 6QF",
    "sg:province":"Bedfordshire",
    "wof:name":"Piggott,Andrew,",
    "wof:placetype":"venue"
},
  "geometry": {"coordinates":[-0.188411,51.989967],"type":"Point"}
}