{
  "type": "Feature",
  "properties": {
    "iso:country":"GB",
    "sg:address":"459 Oldfield Lane North",
    "sg:city":"Greenford",
    "sg:classifiers":[
        {
            "category":"Retail",
            "subcategory":"Veterinary Services",
            "type":"Services"
        }
    ],
    "sg:phone":"+44 20 8422 5103",
    "sg:postcode":"UB6 0EU",
    "sg:province":"Greater London",
    "sg:tags":[
        "surgeon"
    ],
    "wof:name":"Alcombe Veterinary Practice Ltd.",
    "wof:placetype":"venue"
},
  "geometry": {"coordinates":[-0.344193,51.549328],"type":"Point"}
}