{
  "type": "Feature",
  "properties": {
    "iso:country":"GB",
    "sg:address":"15 Station Road, Erdington",
    "sg:city":"Birmingham",
    "sg:classifiers":[
        {
            "category":"Fast Food",
            "type":"Food & Drink"
        }
    ],
    "sg:phone":"+44 121 350 6382",
    "sg:postcode":"B23 6UB",
    "sg:province":"West Midlands",
    "sg:tags":[
        "away",
        "take"
    ],
    "wof:name":"Balti Gardens",
    "wof:placetype":"venue"
},
  "geometry": {"coordinates":[-1.837643,52.527534],"type":"Point"}
}