{
  "type": "Feature",
  "properties": {
    "addr:full":"238a Chellaston Road, Shelton Lock Derby Derbyshire DE24 9EF",
    "addr:housenumber":"238a",
    "addr:postcode":"de24 9ef",
    "addr:street":"Chellaston Road",
    "iso:country":"GB",
    "sg:address":"238a Chellaston Road, Shelton Lock",
    "sg:city":"Derby",
    "sg:classifiers":[
        {
            "category":"Cinema",
            "subcategory":"Movie Rental",
            "type":"Entertainment"
        }
    ],
    "sg:phone":"+44 1332 690000",
    "sg:postcode":"DE24 9EF",
    "sg:province":"Derbyshire",
    "sg:tags":[
        "video",
        "library"
    ],
    "wof:name":"U-Save Videos",
    "wof:placetype":"venue"
},
  "geometry": {"coordinates":[-1.445643,52.879368],"type":"Point"}
}