{
  "type": "Feature",
  "properties": {
    "iso:country":"GB",
    "sg:address":"484 Wimborne Rd",
    "sg:city":"Bournemouth",
    "sg:classifiers":[
        {
            "category":"Professional",
            "subcategory":"Engineering",
            "type":"Services"
        }
    ],
    "sg:phone":"+44 1202 537711",
    "sg:postcode":"BH9 2EY",
    "sg:province":"Dorset",
    "sg:tags":[
        "contractor",
        "electrical",
        "engineer"
    ],
    "wof:name":"Harveys Electrical",
    "wof:placetype":"venue"
},
  "geometry": {"coordinates":[-1.878797,50.743992],"type":"Point"}
}