{
  "type": "Feature",
  "properties": {
    "iso:country":"GB",
    "sg:address":"Highfield House, Foxt Road, Foxt",
    "sg:city":"Stoke-on-trent",
    "sg:classifiers":[
        {
            "category":"Communications",
            "type":"Services"
        }
    ],
    "sg:postcode":"ST10 2HJ",
    "sg:province":"Staffordshire",
    "sg:tags":[
        "system",
        "music",
        "public",
        "address"
    ],
    "wof:name":"D & B Electrics",
    "wof:placetype":"venue"
},
  "geometry": {"coordinates":[-1.950104,53.033615],"type":"Point"}
}