{
  "type": "Feature",
  "properties": {
    "addr:full":"1583 Great Western Road Glasgow Glasgow City G13 1LS",
    "addr:housenumber":"1583",
    "addr:postcode":"g13 1ls",
    "addr:street":"Great Western Road",
    "iso:country":"GB",
    "sg:address":"1583 Great Western Road",
    "sg:city":"Glasgow",
    "sg:classifiers":[
        {
            "category":"Personal",
            "subcategory":"Beauty Salon",
            "type":"Services"
        }
    ],
    "sg:phone":"+44 141 959 4608",
    "sg:postcode":"G13 1LS",
    "sg:province":"Glasgow City",
    "sg:tags":[
        "lady",
        "hairdresser"
    ],
    "wof:name":"Kensington Hair Studio",
    "wof:placetype":"venue"
},
  "geometry": {"coordinates":[-4.3237419128,55.8893623352],"type":"Point"}
}