{
  "type": "Feature",
  "properties": {
    "iso:country":"GB",
    "sg:address":"5 Avocet Way, Diplocks Way",
    "sg:city":"Hailsham",
    "sg:classifiers":[
        {
            "category":"Retail",
            "subcategory":"Auto Repair",
            "type":"Services"
        }
    ],
    "sg:phone":"+44 1323 846632",
    "sg:postcode":"BN27 3JF",
    "sg:province":"East Sussex",
    "sg:tags":[
        "body",
        "car"
    ],
    "wof:name":"Hailsham Auto Body Repairs",
    "wof:placetype":"venue"
},
  "geometry": {"coordinates":[0.247975,50.863796],"type":"Point"}
}