{
  "type": "Feature",
  "properties": {
    "addr:full":"59 Acorn Tree, Thornaby Stockton-on-tees Durham TS17 8LJ",
    "addr:housenumber":"59",
    "addr:postcode":"ts17 8lj",
    "addr:street":"Acorn Tree Thornaby",
    "iso:country":"GB",
    "sg:address":"59 Acorn Tree, Thornaby",
    "sg:city":"Stockton-on-tees",
    "sg:classifiers":[
        {
            "category":"Personal",
            "subcategory":"Beauty Salon",
            "type":"Services"
        }
    ],
    "sg:phone":"+44 1642 760985",
    "sg:postcode":"TS17 8LJ",
    "sg:province":"Durham",
    "sg:tags":[
        "unisex",
        "hairdresser"
    ],
    "wof:name":"The Hair Boutique",
    "wof:placetype":"venue"
},
  "geometry": {"coordinates":[-1.29885,54.54565],"type":"Point"}
}