{
  "type": "Feature",
  "properties": {
    "iso:country":"GB",
    "sg:address":"91-92 High Street, Clydach",
    "sg:city":"Swansea",
    "sg:classifiers":[
        {
            "category":"Manufacturing",
            "subcategory":"Signs",
            "type":"Manufacturing & Wholesale Goods"
        }
    ],
    "sg:phone":"+44 1792 842374",
    "sg:postcode":"SA6 5LN",
    "sg:province":"Swansea",
    "sg:tags":[
        "nameplate"
    ],
    "wof:name":"Valley Engraving Ltd.",
    "wof:placetype":"venue"
},
  "geometry": {"coordinates":[-3.89174,51.696014],"type":"Point"}
}