{
  "type": "Feature",
  "properties": {
    "iso:country":"GB",
    "sg:address":"7 Farm Mews, Farm Road",
    "sg:city":"Hove",
    "sg:classifiers":[
        {
            "category":"Professional",
            "subcategory":"Art Services",
            "type":"Services"
        }
    ],
    "sg:phone":"+44 1273 207470",
    "sg:postcode":"BN3 1GH",
    "sg:province":"East Sussex",
    "sg:tags":[
        "picture",
        "restoration",
        "cleaning"
    ],
    "wof:name":"Artists & Restorers Studios",
    "wof:placetype":"venue"
},
  "geometry": {"coordinates":[-0.159229,50.826244],"type":"Point"}
}