{
  "type": "Feature",
  "properties": {
    "iso:country":"GB",
    "sg:address":"59 Clifden Road, Worminghall",
    "sg:city":"Aylesbury",
    "sg:classifiers":[
        {
            "category":"Organizations",
            "subcategory":"Community Association",
            "type":"Services"
        }
    ],
    "sg:postcode":"HP18 9JR",
    "sg:province":"Buckinghamshire",
    "sg:tags":[
        "relation",
        "public"
    ],
    "wof:name":"John Dooley Associates",
    "wof:placetype":"venue"
},
  "geometry": {"coordinates":[-1.0742230415,51.7693595886],"type":"Point"}
}