{
  "type": "Feature",
  "properties": {
    "addr:full":"Melbourne Street, Morley Leeds West Yorkshire LS27 8BG",
    "addr:postcode":"ls27 8bg",
    "addr:street":"Melbourne Street",
    "iso:country":"GB",
    "sg:address":"Melbourne Street, Morley",
    "sg:city":"Leeds",
    "sg:classifiers":[
        {
            "category":"Retail",
            "subcategory":"Auto Repair",
            "type":"Services"
        }
    ],
    "sg:phone":"+44 113 252 9518",
    "sg:postcode":"LS27 8BG",
    "sg:province":"West Yorkshire",
    "sg:tags":[
        "modification",
        "garage",
        "related"
    ],
    "wof:name":"D R Lawton",
    "wof:placetype":"venue"
},
  "geometry": {"coordinates":[-1.536079,53.801708],"type":"Point"}
}