{
  "type": "Feature",
  "properties": {
    "addr:full":"Telford Gdn(s) Wolverhampton Staffordshire WV3 7LE",
    "addr:postcode":"wv3 7le",
    "addr:street":"Gdn S",
    "iso:country":"GB",
    "sg:address":"Telford Gdn(s)",
    "sg:city":"Wolverhampton",
    "sg:classifiers":[
        {
            "category":"Education",
            "subcategory":"School",
            "type":"Public Place"
        },
        {
            "category":"Government",
            "subcategory":"Office",
            "type":"Public Place"
        }
    ],
    "sg:phone":"+44 1902 556368",
    "sg:postcode":"WV3 7LE",
    "sg:province":"Staffordshire",
    "sg:tags":[
        "local",
        "authority"
    ],
    "wof:name":"St Michael's R C Primary School",
    "wof:placetype":"venue"
},
  "geometry": {"coordinates":[-2.169121,52.572353],"type":"Point"}
}