{
  "type": "Feature",
  "properties": {
    "addr:full":"275 Rectory Road Grays Essex RM17 5SW",
    "addr:housenumber":"275",
    "addr:postcode":"rm17 5sw",
    "addr:street":"Rectory Road",
    "iso:country":"GB",
    "sg:address":"275 Rectory Road",
    "sg:city":"Grays",
    "sg:classifiers":[
        {
            "category":"Home & Garden",
            "subcategory":"Home Furnishings",
            "type":"Retail Goods"
        }
    ],
    "sg:phone":"+44 1375 376001",
    "sg:postcode":"RM17 5SW",
    "sg:province":"Essex",
    "sg:tags":[
        "furnishers",
        "planner",
        "kitchen"
    ],
    "wof:name":"Thames Fitted Furniture",
    "wof:placetype":"venue"
},
  "geometry": {"coordinates":[0.34062,51.487862],"type":"Point"}
}