{
  "type": "Feature",
  "properties": {
    "iso:country":"GB",
    "sg:address":"Ebbw Vale Leisure Centre",
    "sg:city":"Ebbw Vale",
    "sg:classifiers":[
        {
            "category":"Health Services",
            "subcategory":"Clinic",
            "type":"Services"
        },
        {
            "category":"Food & Beverages",
            "subcategory":"Specialty",
            "type":"Retail Goods"
        }
    ],
    "sg:phone":"+44 1495 352143",
    "sg:postcode":"NP23 5XB",
    "sg:province":"Blaenau Gwent",
    "sg:tags":[
        "sport",
        "injury",
        "retailer"
    ],
    "wof:name":"HUGH DANIELS",
    "wof:placetype":"venue"
},
  "geometry": {"coordinates":[-3.211336,51.795582],"type":"Point"}
}