{
  "type": "Feature",
  "properties": {
    "iso:country":"GB",
    "sg:address":"1 Woodland Court, Ashridge Road",
    "sg:city":"Bristol",
    "sg:classifiers":[
        {
            "category":"Building & Trades",
            "subcategory":"Construction",
            "type":"Services"
        }
    ],
    "sg:phone":"+44 121 476 4151",
    "sg:postcode":"BS32 4JQ",
    "sg:province":"Gloucestershire",
    "sg:tags":[
        "builder"
    ],
    "wof:name":"Maxim Homes Ltd.",
    "wof:placetype":"venue"
},
  "geometry": {"coordinates":[-2.545937,51.556488],"type":"Point"}
}