{
  "type": "Feature",
  "properties": {
    "iso:country":"GB",
    "sg:address":"61-71 Collier St",
    "sg:city":"Islington",
    "sg:classifiers":[
        {
            "category":"Professional",
            "subcategory":"Art Services",
            "type":"Services"
        }
    ],
    "sg:phone":"+44 20 7833 2375",
    "sg:postcode":"N1 9BE",
    "sg:province":"Greater London",
    "sg:tags":[
        "graphic",
        "designer"
    ],
    "wof:name":"Studio 3 Quarters",
    "wof:placetype":"venue"
},
  "geometry": {"coordinates":[-0.1185289994,51.5320930481],"type":"Point"}
}