{
  "type": "Feature",
  "properties": {
    "addr:full":"Walton House, 63 South End Croydon Surrey CR0 1BF",
    "addr:housenumber":"63",
    "addr:postcode":"cr0 1bf",
    "addr:street":"South End",
    "iso:country":"GB",
    "sg:address":"Walton House, 63 South End",
    "sg:city":"Croydon",
    "sg:classifiers":[
        {
            "category":"Insurance",
            "subcategory":"Insurance Agent",
            "type":"Services"
        }
    ],
    "sg:phone":"+44 20 8688 4000",
    "sg:postcode":"CR0 1BF",
    "sg:province":"Surrey",
    "sg:tags":[
        "broker"
    ],
    "wof:name":"Francis Townsend Group Ltd.",
    "wof:placetype":"venue"
},
  "geometry": {"coordinates":[-0.0988290012,51.3653755188],"type":"Point"}
}