{
  "type": "Feature",
  "properties": {
    "addr:full":"36 St James's Close, Bishopdown Salisbury Wiltshire SP1 3FB",
    "addr:housenumber":"36",
    "addr:postcode":"sp1 3fb",
    "addr:street":"St James'S Close",
    "iso:country":"GB",
    "sg:address":"36 St James's Close, Bishopdown",
    "sg:city":"Salisbury",
    "sg:classifiers":[
        {
            "category":"Building & Trades",
            "subcategory":"Construction",
            "type":"Services"
        }
    ],
    "sg:phone":"+44 1722 328130",
    "sg:postcode":"SP1 3FB",
    "sg:province":"Wiltshire",
    "sg:tags":[
        "decorator",
        "painter"
    ],
    "wof:name":"Hallmark Services",
    "wof:placetype":"venue"
},
  "geometry": {"coordinates":[-1.865486,51.078217],"type":"Point"}
}