{
  "type": "Feature",
  "properties": {
    "iso:country":"GB",
    "sg:address":"535 City Road",
    "sg:city":"Sheffield",
    "sg:classifiers":[
        {
            "category":"Social Services",
            "subcategory":"Adult Care",
            "type":"Services"
        }
    ],
    "sg:phone":"+44 114 264 4411",
    "sg:postcode":"S2 1GF",
    "sg:province":"South Yorkshire",
    "sg:tags":[
        "day",
        "centre"
    ],
    "wof:name":"Mental Health Day Centre",
    "wof:placetype":"venue"
},
  "geometry": {"coordinates":[-1.4375009537,53.3664360046],"type":"Point"}
}