{
  "type": "Feature",
  "properties": {
    "iso:country":"GB",
    "sg:address":"17 Manstone Avenue",
    "sg:city":"Sidmouth",
    "sg:classifiers":[
        {
            "category":"Professional",
            "subcategory":"Detective & Security Services",
            "type":"Services"
        }
    ],
    "sg:phone":"+44 1395 577941",
    "sg:postcode":"EX10 9YJ",
    "sg:province":"Devon",
    "wof:name":"Andrew S O'connor",
    "wof:placetype":"venue"
},
  "geometry": {"coordinates":[-3.239576,50.695305],"type":"Point"}
}