{
  "type": "Feature",
  "properties": {
    "addr:full":"Town Hall Building, High St Northallerton North Yorkshire DL7 8NX",
    "addr:postcode":"dl7 8nx",
    "addr:street":"High St",
    "iso:country":"GB",
    "sg:address":"Town Hall Building, High St",
    "sg:city":"Northallerton",
    "sg:classifiers":[
        {
            "category":"Community Center",
            "subcategory":"Youth",
            "type":"Public Place"
        }
    ],
    "sg:phone":"+44 1609 777495",
    "sg:postcode":"DL7 8NX",
    "sg:province":"North Yorkshire",
    "sg:tags":[
        "organisation",
        "centre"
    ],
    "wof:name":"Northallerton Youth Centre",
    "wof:placetype":"venue"
},
  "geometry": {"coordinates":[-1.43708,54.340839],"type":"Point"}
}