{
  "type": "Feature",
  "properties": {
    "iso:country":"GB",
    "sg:address":"Brookmarsh Industrial Estate, Norman Road, Greenwich",
    "sg:city":"London",
    "sg:classifiers":[
        {
            "category":"Retail",
            "subcategory":"Auto Repair",
            "type":"Services"
        }
    ],
    "sg:phone":"+44 20 8858 1186",
    "sg:postcode":"SE10 9QE",
    "sg:province":"Greater London",
    "sg:tags":[
        "body",
        "car"
    ],
    "wof:name":"R & T Coachworks Ltd.",
    "wof:placetype":"venue"
},
  "geometry": {"coordinates":[-0.01802,51.478809],"type":"Point"}
}