{
  "type": "Feature",
  "properties": {
    "iso:country":"GB",
    "sg:address":"St Peters Way",
    "sg:city":"Northampton",
    "sg:classifiers":[
        {
            "category":"Restaurant",
            "type":"Food & Drink"
        }
    ],
    "sg:phone":"+44 1604 621282",
    "sg:postcode":"NN1 1SY",
    "sg:province":"Northamptonshire",
    "wof:name":"Hanrahans Bar & Restaurant",
    "wof:placetype":"venue"
},
  "geometry": {"coordinates":[-0.898858,52.23402],"type":"Point"}
}