{
  "type": "Feature",
  "properties": {
    "addr:full":"Ashdale Rd York East Riding of Yorkshire YO6 5DE",
    "addr:postcode":"yo6 5de",
    "addr:street":"Ashdale Rd",
    "iso:country":"GB",
    "sg:address":"Ashdale Rd",
    "sg:city":"York",
    "sg:classifiers":[
        {
            "category":"Travel",
            "subcategory":"Hotels & Motels",
            "type":"Entertainment"
        }
    ],
    "sg:phone":"+44 1439 770172",
    "sg:postcode":"YO6 5DE",
    "sg:province":"East Riding of Yorkshire",
    "sg:tags":[
        "house",
        "guest"
    ],
    "wof:name":"Westway Cottage Bed & Breakfast",
    "wof:placetype":"venue"
},
  "geometry": {"coordinates":[-1.0550240278,54.2461891174],"type":"Point"}
}