{
  "type": "Feature",
  "properties": {
    "iso:country":"GB",
    "sg:address":"7 Jocelyn Close, Pulham Market",
    "sg:city":"Diss",
    "sg:classifiers":[
        {
            "category":"Military Area",
            "subcategory":"Air Force Base",
            "type":"Public Place"
        }
    ],
    "sg:postcode":"IP21 4BE",
    "sg:province":"Norfolk",
    "sg:tags":[
        "taxi",
        "hire",
        "private"
    ],
    "wof:name":"Barry Quantrill",
    "wof:placetype":"venue"
},
  "geometry": {"coordinates":[1.2252399921,52.434928894],"type":"Point"}
}