{
  "type": "Feature",
  "properties": {
    "addr:full":"Daisy House, Haven Rd, The Hythe Colchester Essex CO2 8HT",
    "addr:postcode":"co2 8ht",
    "addr:street":"Haven Rd",
    "iso:country":"GB",
    "sg:address":"Daisy House, Haven Rd, The Hythe",
    "sg:city":"Colchester",
    "sg:classifiers":[
        {
            "category":"Utilities",
            "subcategory":"Refuse",
            "type":"Services"
        }
    ],
    "sg:phone":"+44 1206 871111",
    "sg:postcode":"CO2 8HT",
    "sg:province":"Essex",
    "sg:tags":[
        "disposal",
        "waste",
        "retail"
    ],
    "wof:name":"Onyx Total Waste Management",
    "wof:placetype":"venue"
},
  "geometry": {"coordinates":[0.927023,51.879295],"type":"Point"}
}