{
  "type": "Feature",
  "properties": {
    "addr:full":"41 Highfield Road Bourne End Berkshire SL8 5BE",
    "addr:housenumber":"41",
    "addr:postcode":"sl8 5be",
    "addr:street":"Highfield Road Bourne",
    "iso:country":"GB",
    "sg:address":"41 Highfield Road",
    "sg:city":"Bourne End",
    "sg:classifiers":[
        {
            "category":"Professional",
            "subcategory":"Engineering",
            "type":"Services"
        }
    ],
    "sg:phone":"+44 1753 621676",
    "sg:postcode":"SL8 5BE",
    "sg:province":"Berkshire",
    "sg:tags":[
        "contractor",
        "electrical",
        "engineer"
    ],
    "wof:name":"Powerline Ltd.",
    "wof:placetype":"venue"
},
  "geometry": {"coordinates":[-0.707828,51.580238],"type":"Point"}
}