{
  "type": "Feature",
  "properties": {
    "addr:full":"110 Upper Commercial Street Batley West Yorkshire WF17 5DP",
    "addr:housenumber":"110",
    "addr:postcode":"wf17 5dp",
    "addr:street":"Upper Commercial Street",
    "iso:country":"GB",
    "sg:address":"110 Upper Commercial Street",
    "sg:city":"Batley",
    "sg:classifiers":[
        {
            "category":"Professional",
            "type":"Services"
        }
    ],
    "sg:postcode":"WF17 5DP",
    "sg:province":"West Yorkshire",
    "sg:tags":[
        "interior",
        "furnishers",
        "designer"
    ],
    "wof:name":"Joan Reid",
    "wof:placetype":"venue"
},
  "geometry": {"coordinates":[-1.6370990276,53.7150650024],"type":"Point"}
}