{
  "type": "Feature",
  "properties": {
    "addr:full":"48 Beech Road Chinnor Buckinghamshire OX39 4RD",
    "addr:housenumber":"48",
    "addr:postcode":"ox39 4rd",
    "addr:street":"Beech Road",
    "iso:country":"GB",
    "sg:address":"48 Beech Road",
    "sg:city":"Chinnor",
    "sg:classifiers":[
        {
            "category":"Building & Trades",
            "subcategory":"Construction",
            "type":"Services"
        }
    ],
    "sg:phone":"+44 1844 351025",
    "sg:postcode":"OX39 4RD",
    "sg:province":"Buckinghamshire",
    "sg:tags":[
        "builder"
    ],
    "wof:name":"Royale Building Services",
    "wof:placetype":"venue"
},
  "geometry": {"coordinates":[-0.915013,51.701523],"type":"Point"}
}