{
  "type": "Feature",
  "properties": {
    "iso:country":"GB",
    "sg:address":"15 High Street",
    "sg:city":"Westerham",
    "sg:classifiers":[
        {
            "category":"Insurance",
            "subcategory":"Insurance Agent",
            "type":"Services"
        }
    ],
    "sg:phone":"+44 1959 564274",
    "sg:postcode":"TN16 1RA",
    "sg:province":"Kent",
    "sg:tags":[
        "broker"
    ],
    "wof:name":"Hammond Frey Marrington Ltd.",
    "wof:placetype":"venue"
},
  "geometry": {"coordinates":[0.069341,51.266487],"type":"Point"}
}