{
  "type": "Feature",
  "properties": {
    "iso:country":"GB",
    "sg:address":"44 Main Street, Woodhouse Eaves",
    "sg:city":"Loughborough",
    "sg:classifiers":[
        {
            "category":"Shopping",
            "subcategory":"News",
            "type":"Retail Goods"
        }
    ],
    "sg:phone":"+44 1509 890321",
    "sg:postcode":"LE12 8RZ",
    "sg:province":"Leicestershire",
    "sg:tags":[
        "newsagent"
    ],
    "wof:name":"Woodhouse News",
    "wof:placetype":"venue"
},
  "geometry": {"coordinates":[-1.189478,52.713161],"type":"Point"}
}