{
  "type": "Feature",
  "properties": {
    "iso:country":"GB",
    "sg:address":"4 Baring Crescent",
    "sg:city":"Exeter",
    "sg:classifiers":[
        {
            "category":"Real Estate",
            "subcategory":"Surveying",
            "type":"Services"
        }
    ],
    "sg:phone":"+44 1392 425960",
    "sg:postcode":"EX1 1TL",
    "sg:province":"Devon",
    "sg:tags":[
        "surveyor",
        "quantity"
    ],
    "wof:name":"E C Harris & Partners",
    "wof:placetype":"venue"
},
  "geometry": {"coordinates":[-3.514832,50.722839],"type":"Point"}
}