{
  "type": "Feature",
  "properties": {
    "addr:full":"71 The Ridings, Ockbrook Derby Derbyshire DE72 3SF",
    "addr:housenumber":"71",
    "addr:postcode":"de72 3sf",
    "addr:street":"The Ridings",
    "iso:country":"GB",
    "sg:address":"71 The Ridings, Ockbrook",
    "sg:city":"Derby",
    "sg:classifiers":[
        {
            "category":"Professional",
            "subcategory":"Engineering",
            "type":"Services"
        },
        {
            "category":"Building & Trades",
            "subcategory":"Construction",
            "type":"Services"
        }
    ],
    "sg:phone":"+44 1332 674276",
    "sg:postcode":"DE72 3SF",
    "sg:province":"Derbyshire",
    "sg:tags":[
        "installers",
        "gas",
        "engineer"
    ],
    "wof:name":"Ockbrook Gas Services",
    "wof:placetype":"venue"
},
  "geometry": {"coordinates":[-1.37211,52.919765],"type":"Point"}
}