{
  "type": "Feature",
  "properties": {
    "iso:country":"GB",
    "sg:address":"3a Kelvedon Street",
    "sg:city":"Newport",
    "sg:classifiers":[
        {
            "category":"Wholesale",
            "subcategory":"Construction Materials",
            "type":"Manufacturing & Wholesale Goods"
        }
    ],
    "sg:postcode":"NP19 0DW",
    "sg:province":"Newport",
    "sg:tags":[
        "supplier",
        "double",
        "glazing"
    ],
    "wof:name":"Kolor Cymreig Ltd.",
    "wof:placetype":"venue"
},
  "geometry": {"coordinates":[-2.978125,51.584572],"type":"Point"}
}