{
  "type": "Feature",
  "properties": {
    "iso:country":"GB",
    "sg:address":"191a Stanstead Rd, Forest Hill",
    "sg:city":"Forest Hill",
    "sg:classifiers":[
        {
            "category":"Shopping",
            "subcategory":"Hobbies, Toys, & Games",
            "type":"Retail Goods"
        }
    ],
    "sg:phone":"+44 20 8291 9123",
    "sg:postcode":"SE23 1HP",
    "sg:province":"Greater London",
    "sg:tags":[
        "house",
        "dolls'",
        "doll"
    ],
    "wof:name":"Apple Bee Doll Making Studio & Supplies",
    "wof:placetype":"venue"
},
  "geometry": {"coordinates":[-0.043715,51.44212],"type":"Point"}
}