{
  "type": "Feature",
  "properties": {
    "addr:full":"21 Market Place Wantage Berkshire OX12 8AE",
    "addr:housenumber":"21",
    "addr:postcode":"ox12 8ae",
    "addr:street":"Market Place",
    "iso:country":"GB",
    "sg:address":"21 Market Place",
    "sg:city":"Wantage",
    "sg:classifiers":[
        {
            "category":"Shopping",
            "subcategory":"Clothing, Apparel, & Fashions",
            "type":"Retail Goods"
        }
    ],
    "sg:phone":"+44 1235 770099",
    "sg:postcode":"OX12 8AE",
    "sg:province":"Berkshire",
    "sg:tags":[
        "menswear"
    ],
    "wof:name":"Badgers Ltd.",
    "wof:placetype":"venue"
},
  "geometry": {"coordinates":[-1.4274770021,51.5886192322],"type":"Point"}
}