{
  "type": "Feature",
  "properties": {
    "addr:full":"17 Bank Wood Close, Newbold Chesterfield Derbyshire S41 8XQ",
    "addr:housenumber":"17",
    "addr:postcode":"s41 8xq",
    "addr:street":"Bank Wood Close",
    "iso:country":"GB",
    "sg:address":"17 Bank Wood Close, Newbold",
    "sg:city":"Chesterfield",
    "sg:classifiers":[
        {
            "category":"Retail",
            "subcategory":"Repair Shop",
            "type":"Services"
        }
    ],
    "sg:phone":"+44 1246 200371",
    "sg:postcode":"S41 8XQ",
    "sg:province":"Derbyshire",
    "sg:tags":[
        "radio",
        "television",
        "video"
    ],
    "wof:name":"Ian Low Tv Video & Satellite Repairs",
    "wof:placetype":"venue"
},
  "geometry": {"coordinates":[-1.463976,53.254612],"type":"Point"}
}