{
  "type": "Feature",
  "properties": {
    "addr:full":"3 The Glebe Saffron Walden Essex CB11 4BQ",
    "addr:housenumber":"3",
    "addr:postcode":"cb11 4bq",
    "addr:street":"The Glebe",
    "iso:country":"GB",
    "sg:address":"3 The Glebe",
    "sg:city":"Saffron Walden",
    "sg:classifiers":[
        {
            "category":"Professional",
            "subcategory":"Computer Services",
            "type":"Services"
        }
    ],
    "sg:phone":"+44 1799 520888",
    "sg:postcode":"CB11 4BQ",
    "sg:province":"Essex",
    "sg:tags":[
        "consultant"
    ],
    "wof:name":"Abbey IT Consultants",
    "wof:placetype":"venue"
},
  "geometry": {"coordinates":[0.2476789951,52.0112037659],"type":"Point"}
}