{
  "type": "Feature",
  "properties": {
    "addr:full":"The Cross Watchet Somerset TA23 0AG",
    "addr:postcode":"ta23 0ag",
    "addr:street":"Cross",
    "iso:country":"GB",
    "sg:address":"The Cross",
    "sg:city":"Watchet",
    "sg:classifiers":[
        {
            "category":"Military Area",
            "subcategory":"Air Force Base",
            "type":"Public Place"
        }
    ],
    "sg:phone":"+44 1984 631973",
    "sg:postcode":"TA23 0AG",
    "sg:province":"Somerset",
    "sg:tags":[
        "taxi",
        "hire",
        "private"
    ],
    "wof:name":"Cliff's Cabs",
    "wof:placetype":"venue"
},
  "geometry": {"coordinates":[-3.330244,51.180626],"type":"Point"}
}