{
  "type": "Feature",
  "properties": {
    "addr:full":"39a Station Street Cockermouth Cumbria CA13 9QW",
    "addr:housenumber":"39a",
    "addr:postcode":"ca13 9qw",
    "addr:street":"Station Street",
    "iso:country":"GB",
    "sg:address":"39a Station Street",
    "sg:city":"Cockermouth",
    "sg:classifiers":[
        {
            "category":"Shopping",
            "subcategory":"Pets & Pet Supplies",
            "type":"Retail Goods"
        }
    ],
    "sg:phone":"+44 1900 829700",
    "sg:postcode":"CA13 9QW",
    "sg:province":"Cumbria",
    "wof:name":"M & K Pet Supplies",
    "wof:placetype":"venue"
},
  "geometry": {"coordinates":[-3.364006,54.662487],"type":"Point"}
}