{
  "type": "Feature",
  "properties": {
    "iso:country":"GB",
    "sg:address":"Unit 1G, Cibyn Industrial Estate",
    "sg:city":"Caernarfon",
    "sg:classifiers":[
        {
            "category":"Home & Garden",
            "subcategory":"Home Furnishings",
            "type":"Retail Goods"
        },
        {
            "category":"Home & Garden",
            "subcategory":"Furniture",
            "type":"Retail Goods"
        }
    ],
    "sg:phone":"+44 1286 677994",
    "sg:postcode":"LL55 2BD",
    "sg:province":"Gwynedd",
    "sg:tags":[
        "pine"
    ],
    "wof:name":"Reflections in Pine",
    "wof:placetype":"venue"
},
  "geometry": {"coordinates":[-4.2528247833,53.1405830383],"type":"Point"}
}