{
  "type": "Feature",
  "properties": {
    "iso:country":"GB",
    "sg:address":"7 Briwere Road",
    "sg:city":"Torquay",
    "sg:classifiers":[
        {
            "category":"Real Estate",
            "subcategory":"Architect",
            "type":"Services"
        }
    ],
    "sg:postcode":"TQ1 4DU",
    "sg:province":"Devon",
    "sg:tags":[
        "architectural"
    ],
    "wof:name":"Ian Newton Architectural Design",
    "wof:placetype":"venue"
},
  "geometry": {"coordinates":[-3.5471730232,50.4773674011],"type":"Point"}
}