{
  "type": "Feature",
  "properties": {
    "addr:full":"Littleton Mills, Winford Bristol Somerset BS40 8HJ",
    "addr:postcode":"bs40 8hj",
    "iso:country":"GB",
    "sg:address":"Littleton Mills, Winford",
    "sg:city":"Bristol",
    "sg:classifiers":[
        {
            "category":"Manufacturing",
            "subcategory":"Metals",
            "type":"Manufacturing & Wholesale Goods"
        }
    ],
    "sg:postcode":"BS40 8HJ",
    "sg:province":"Somerset",
    "sg:tags":[
        "steel",
        "fabricator",
        "erectors"
    ],
    "wof:name":"Valley Structures Ltd",
    "wof:placetype":"venue"
},
  "geometry": {"coordinates":[-2.6620140076,51.3826217651],"type":"Point"}
}