{
  "type": "Feature",
  "properties": {
    "addr:full":"56 Eaton Crescent Swansea Neath Port Talbot SA1 4QN",
    "addr:housenumber":"56",
    "addr:postcode":"sa1 4qn",
    "addr:street":"Eaton Crescent",
    "iso:country":"GB",
    "sg:address":"56 Eaton Crescent",
    "sg:city":"Swansea",
    "sg:classifiers":[
        {
            "category":"Health Services",
            "subcategory":"Nursing And Care Facility",
            "type":"Services"
        }
    ],
    "sg:phone":"+44 1792 463813",
    "sg:postcode":"SA1 4QN",
    "sg:province":"Neath Port Talbot",
    "sg:tags":[
        "home"
    ],
    "wof:name":"Morris House",
    "wof:placetype":"venue"
},
  "geometry": {"coordinates":[-3.9662950039,51.6165657043],"type":"Point"}
}