{
  "type": "Feature",
  "properties": {
    "iso:country":"GB",
    "sg:address":"11 Hill Street",
    "sg:city":"Southport",
    "sg:classifiers":[
        {
            "category":"Professional",
            "subcategory":"Testing Lab",
            "type":"Services"
        }
    ],
    "sg:phone":"+44 1704 500311",
    "sg:postcode":"PR9 0NW",
    "sg:province":"Lancashire",
    "sg:tags":[
        "pregnancy"
    ],
    "wof:name":"Life Pregnancy Care Service",
    "wof:placetype":"venue"
},
  "geometry": {"coordinates":[-3.000938,53.649536],"type":"Point"}
}