{
  "type": "Feature",
  "properties": {
    "iso:country":"GB",
    "sg:address":"Llys-eira, Birklands Lane",
    "sg:city":"St Albans",
    "sg:classifiers":[
        {
            "category":"Professional",
            "subcategory":"Lawyer & Legal Services",
            "type":"Services"
        }
    ],
    "sg:phone":"+44 1727 823186",
    "sg:postcode":"AL1 1EQ",
    "sg:province":"Hertfordshire",
    "sg:tags":[
        "solicitor"
    ],
    "wof:name":"G Pazzi-Axworthy",
    "wof:placetype":"venue"
},
  "geometry": {"coordinates":[-0.308774,51.732014],"type":"Point"}
}