{
  "type": "Feature",
  "properties": {
    "addr:full":"2 Summerfield Village Centre, Dean Row Road Wilmslow Cheshire SK9 2TA",
    "addr:housenumber":"2",
    "addr:postcode":"sk9 2ta",
    "addr:street":"Summerfield Village Centre Dean Row Road",
    "iso:country":"GB",
    "sg:address":"2 Summerfield Village Centre, Dean Row Road",
    "sg:city":"Wilmslow",
    "sg:classifiers":[
        {
            "category":"Shopping",
            "subcategory":"Pharmacy",
            "type":"Retail Goods"
        }
    ],
    "sg:phone":"+44 1625 523414",
    "sg:postcode":"SK9 2TA",
    "sg:province":"Cheshire",
    "sg:tags":[
        "pharmacist",
        "chemist"
    ],
    "wof:name":"Numark Pharmacy",
    "wof:placetype":"venue"
},
  "geometry": {"coordinates":[-2.227897,53.326797],"type":"Point"}
}