{
  "type": "Feature",
  "properties": {
    "iso:country":"GB",
    "sg:address":"141 Hillcrest",
    "sg:city":"Weybridge",
    "sg:classifiers":[
        {
            "category":"Personal",
            "type":"Services"
        }
    ],
    "sg:phone":"+44 1932 840377",
    "sg:postcode":"KT13 8AS",
    "sg:province":"Surrey",
    "sg:tags":[
        "dressmaker"
    ],
    "wof:name":"Couture Dressmaking & Alterations",
    "wof:placetype":"venue"
},
  "geometry": {"coordinates":[-0.454953,51.370647],"type":"Point"}
}