{
  "type": "Feature",
  "properties": {
    "addr:full":"Kingsbrook Lodge, Shaftesbury Road, Mere Warminster Somerset BA12 6BJ",
    "addr:postcode":"ba12 6bj",
    "addr:street":"Shaftesbury Road",
    "iso:country":"GB",
    "sg:address":"Kingsbrook Lodge, Shaftesbury Road, Mere",
    "sg:city":"Warminster",
    "sg:classifiers":[
        {
            "category":"Professional",
            "subcategory":"Management & Consulting",
            "type":"Services"
        }
    ],
    "sg:phone":"+44 1747 861800",
    "sg:postcode":"BA12 6BJ",
    "sg:province":"Somerset",
    "sg:tags":[
        "consultant",
        "training"
    ],
    "wof:name":"Dynamic Relations Ltd.",
    "wof:placetype":"venue"
},
  "geometry": {"coordinates":[-2.270170927,51.090511322],"type":"Point"}
}