{
  "type": "Feature",
  "properties": {
    "iso:country":"GB",
    "sg:address":"6 Alexander Drive, Bridge Of Allan",
    "sg:city":"Stirling",
    "sg:classifiers":[
        {
            "category":"Manufacturing",
            "subcategory":"Tools & Machinery",
            "type":"Manufacturing & Wholesale Goods"
        }
    ],
    "sg:phone":"+44 1786 832223",
    "sg:postcode":"FK9 4QB",
    "sg:province":"Clackmannanshire",
    "wof:name":"B G S Quality Systems Ltd.",
    "wof:placetype":"venue"
},
  "geometry": {"coordinates":[-3.94539,56.158005],"type":"Point"}
}