{
  "type": "Feature",
  "properties": {
    "iso:country":"GB",
    "sg:address":"Kinetic Centre, Theobald Street",
    "sg:city":"Borehamwood",
    "sg:classifiers":[
        {
            "category":"Professional",
            "subcategory":"Detective & Security Services",
            "type":"Services"
        }
    ],
    "sg:phone":"+44 20 8386 3617",
    "sg:postcode":"WD6 4SE",
    "sg:province":"Hertfordshire",
    "sg:tags":[
        "equipment"
    ],
    "wof:name":"Security Defence Technologies Ltd.",
    "wof:placetype":"venue"
},
  "geometry": {"coordinates":[-0.275754,51.655819],"type":"Point"}
}