{
  "type": "Feature",
  "properties": {
    "addr:full":"6 Kingsland Rd, London Greater London E2 8DA",
    "addr:housenumber":"6",
    "addr:postcode":"e2 8da",
    "addr:street":"Kingsland Rd",
    "iso:country":"GB",
    "sg:address":"6 Kingsland Rd,",
    "sg:city":"London",
    "sg:classifiers":[
        {
            "category":"Shopping",
            "subcategory":"Shoes",
            "type":"Retail Goods"
        }
    ],
    "sg:postcode":"E2 8DA",
    "sg:province":"Greater London",
    "sg:tags":[
        "shop"
    ],
    "wof:name":"Beeline Champers Footwear",
    "wof:placetype":"venue"
},
  "geometry": {"coordinates":[-0.0778570026,51.5273590088],"type":"Point"}
}