{
  "type": "Feature",
  "properties": {
    "addr:full":"Bank House Cannock Staffordshire WS11 3DW",
    "addr:postcode":"ws11 3dw",
    "iso:country":"GB",
    "sg:address":"Bank House",
    "sg:city":"Cannock",
    "sg:classifiers":[
        {
            "category":"Banks & Credit Unions",
            "subcategory":"Financial Services",
            "type":"Services"
        }
    ],
    "sg:phone":"+44 845 120 0100",
    "sg:postcode":"WS11 3DW",
    "sg:province":"Staffordshire",
    "sg:tags":[
        "building",
        "society"
    ],
    "wof:name":"Yorkshire Building Society",
    "wof:placetype":"venue"
},
  "geometry": {"coordinates":[-2.004649,52.67577],"type":"Point"}
}