{
  "type": "Feature",
  "properties": {
    "iso:country":"GB",
    "sg:address":"18 Oriel Drive, Fordhouses",
    "sg:city":"Wolverhampton",
    "sg:classifiers":[
        {
            "category":"Building & Trades",
            "subcategory":"Construction",
            "type":"Services"
        }
    ],
    "sg:postcode":"WV10 6LJ",
    "sg:province":"Staffordshire",
    "sg:tags":[
        "builder"
    ],
    "wof:name":"Timothy R Hazlewood",
    "wof:placetype":"venue"
},
  "geometry": {"coordinates":[-2.1241390705,52.6277084351],"type":"Point"}
}