{
  "type": "Feature",
  "properties": {
    "addr:full":"Rutland, Taylors Meanygate, Tarleaton Preston Lancashire PR4 6XB",
    "addr:postcode":"pr4 6xb",
    "addr:street":"Meanygate;Preston",
    "iso:country":"GB",
    "sg:address":"Rutland, Taylors Meanygate, Tarleaton",
    "sg:city":"Preston",
    "sg:classifiers":[
        {
            "category":"Farming",
            "subcategory":"Livestock Farm",
            "type":"Manufacturing & Wholesale Goods"
        }
    ],
    "sg:phone":"+44 1772 812647",
    "sg:postcode":"PR4 6XB",
    "sg:province":"Lancashire",
    "sg:tags":[
        "others"
    ],
    "wof:name":"Wright,Len,",
    "wof:placetype":"venue"
},
  "geometry": {"coordinates":[-2.881779,53.691959],"type":"Point"}
}