{
  "type": "Feature",
  "properties": {
    "addr:full":"2 Barkley Crescent Gravesend Kent DA12 2AD",
    "addr:housenumber":"2",
    "addr:postcode":"da12 2ad",
    "addr:street":"Barkley Crescent",
    "iso:country":"GB",
    "sg:address":"2 Barkley Crescent",
    "sg:city":"Gravesend",
    "sg:classifiers":[
        {
            "category":"Government",
            "subcategory":"Office",
            "type":"Public Place"
        }
    ],
    "sg:phone":"+44 1474 320805",
    "sg:postcode":"DA12 2AD",
    "sg:province":"Kent",
    "sg:tags":[
        "chamber",
        "commerce"
    ],
    "wof:name":"The Gravesham Chamber of Trade & Industry Ltd.",
    "wof:placetype":"venue"
},
  "geometry": {"coordinates":[0.37277,51.441833],"type":"Point"}
}