{
  "type": "Feature",
  "properties": {
    "addr:full":"53 Staple Hall Road, Bletchley Milton Keynes Buckinghamshire MK1 1BQ",
    "addr:housenumber":"53",
    "addr:postcode":"mk1 1bq",
    "addr:street":"Staple Hall Road",
    "iso:country":"GB",
    "sg:address":"53 Staple Hall Road, Bletchley",
    "sg:city":"Milton Keynes",
    "sg:classifiers":[
        {
            "category":"Building & Trades",
            "subcategory":"Cleaning & Sanitation",
            "type":"Services"
        }
    ],
    "sg:phone":"+44 1908 375228",
    "sg:postcode":"MK1 1BQ",
    "sg:province":"Buckinghamshire",
    "sg:tags":[
        "cleaner",
        "window"
    ],
    "wof:name":"R & S Cleaning Services",
    "wof:placetype":"venue"
},
  "geometry": {"coordinates":[-0.7182840109,52.0021934509],"type":"Point"}
}