{
  "type": "Feature",
  "properties": {
    "iso:country":"GB",
    "sg:address":"6 Town Square",
    "sg:city":"Erith",
    "sg:classifiers":[
        {
            "category":"Wholesale",
            "subcategory":"Fruits & Vegetables",
            "type":"Manufacturing & Wholesale Goods"
        }
    ],
    "sg:phone":"+44 1634 818075",
    "sg:postcode":"DA8 1RE",
    "sg:province":"Kent",
    "wof:name":"Harlesden Marketing Ltd.",
    "wof:placetype":"venue"
},
  "geometry": {"coordinates":[0.179447,51.480309],"type":"Point"}
}