{
  "type": "Feature",
  "properties": {
    "iso:country":"GB",
    "sg:address":"23c Dundas Street",
    "sg:city":"Edinburgh",
    "sg:classifiers":[
        {
            "category":"Shopping",
            "subcategory":"Antiques",
            "type":"Retail Goods"
        }
    ],
    "sg:postcode":"EH3 6QQ",
    "sg:province":"City of Edinburgh",
    "wof:name":"Adam Antiques Ltd.",
    "wof:placetype":"venue"
},
  "geometry": {"coordinates":[-3.1989440918,55.95703125],"type":"Point"}
}