{
  "type": "Feature",
  "properties": {
    "iso:country":"GB",
    "sg:address":"Unit 2 H Longhill Indust Est, Ullswater Rd",
    "sg:city":"Hartlepool",
    "sg:classifiers":[
        {
            "category":"Manufacturing",
            "subcategory":"Signs",
            "type":"Manufacturing & Wholesale Goods"
        }
    ],
    "sg:phone":"+44 1429 420009",
    "sg:postcode":"TS25 1UE",
    "sg:province":"Durham",
    "sg:tags":[
        "writer"
    ],
    "wof:name":"Wood Signs",
    "wof:placetype":"venue"
},
  "geometry": {"coordinates":[-1.2066,54.673111],"type":"Point"}
}