{
  "type": "Feature",
  "properties": {
    "iso:country":"GB",
    "sg:address":"100 Brondesbury Park",
    "sg:city":"London",
    "sg:classifiers":[
        {
            "category":"Real Estate",
            "subcategory":"Real Estate Services",
            "type":"Services"
        },
        {
            "category":"Professional",
            "subcategory":"Business Services",
            "type":"Services"
        }
    ],
    "sg:phone":"+44 20 8459 0015",
    "sg:postcode":"NW2 5JR",
    "sg:province":"Greater London",
    "sg:tags":[
        "building",
        "holding"
    ],
    "wof:name":"Park 100 Ltd.",
    "wof:placetype":"venue"
},
  "geometry": {"coordinates":[-0.225284,51.545704],"type":"Point"}
}