{
  "type": "Feature",
  "properties": {
    "iso:country":"GB",
    "sg:address":"33 High Street, Wick",
    "sg:city":"Bristol",
    "sg:classifiers":[
        {
            "category":"Personal",
            "subcategory":"Beauty Salon",
            "type":"Services"
        }
    ],
    "sg:phone":"+44 117 937 2725",
    "sg:postcode":"BS30 5QJ",
    "sg:province":"Gloucestershire",
    "sg:tags":[
        "unisex",
        "hairdresser"
    ],
    "wof:name":"Virgos",
    "wof:placetype":"venue"
},
  "geometry": {"coordinates":[-2.427626,51.452915],"type":"Point"}
}