{
  "type": "Feature",
  "properties": {
    "addr:full":"31 Marsh Parade Newcastle Staffordshire ST5 1BT",
    "addr:housenumber":"31",
    "addr:postcode":"st5 1bt",
    "addr:street":"Marsh Parade",
    "iso:country":"GB",
    "sg:address":"31 Marsh Parade",
    "sg:city":"Newcastle",
    "sg:classifiers":[
        {
            "category":"Banks & Credit Unions",
            "subcategory":"Financial Services",
            "type":"Services"
        }
    ],
    "sg:phone":"+44 1782 557800",
    "sg:postcode":"ST5 1BT",
    "sg:province":"Staffordshire",
    "sg:tags":[
        "consultant",
        "pension"
    ],
    "wof:name":"Richard Jacobs Pension & Trustee Services Ltd.",
    "wof:placetype":"venue"
},
  "geometry": {"coordinates":[-2.218900919,53.0111312866],"type":"Point"}
}