{
  "type": "Feature",
  "properties": {
    "iso:country":"GB",
    "sg:address":"The Green, Weathersfield",
    "sg:city":"Braintree",
    "sg:classifiers":[
        {
            "category":"Restaurant",
            "type":"Food & Drink"
        }
    ],
    "sg:phone":"+44 1371 850723",
    "sg:postcode":"CM7 4BS",
    "sg:province":"Essex",
    "wof:name":"W J  & M D R Dicken",
    "wof:placetype":"venue"
},
  "geometry": {"coordinates":[0.50193,51.937389],"type":"Point"}
}