{
  "type": "Feature",
  "properties": {
    "iso:country":"GB",
    "sg:address":"41 Westcombe Avenue",
    "sg:city":"Croydon",
    "sg:classifiers":[
        {
            "category":"Building & Trades",
            "subcategory":"Construction",
            "type":"Services"
        }
    ],
    "sg:phone":"+44 20 8689 7787",
    "sg:postcode":"CR0 3DE",
    "sg:province":"Surrey",
    "sg:tags":[
        "builder"
    ],
    "wof:name":"J R Builders",
    "wof:placetype":"venue"
},
  "geometry": {"coordinates":[-0.125021,51.385849],"type":"Point"}
}