{
  "type": "Feature",
  "properties": {
    "iso:country":"GB",
    "sg:address":"Unit 3 Ashmores Trading Estate, Tipton Road",
    "sg:city":"Dudley",
    "sg:classifiers":[
        {
            "category":"Wholesale",
            "subcategory":"Scrap",
            "type":"Manufacturing & Wholesale Goods"
        }
    ],
    "sg:phone":"+44 1384 252212",
    "sg:postcode":"DY1 4SA",
    "sg:province":"West Midlands",
    "sg:tags":[
        "breaker",
        "dismantlers"
    ],
    "wof:name":"T & B Diesel Services",
    "wof:placetype":"venue"
},
  "geometry": {"coordinates":[-2.0724999905,52.5183982849],"type":"Point"}
}