{
  "type": "Feature",
  "properties": {
    "addr:full":"86 Glasgow Rd Paisley Renfrewshire PA1 3NU",
    "addr:housenumber":"86",
    "addr:postcode":"pa1 3nu",
    "addr:street":"Glasgow Rd",
    "iso:country":"GB",
    "sg:address":"86 Glasgow Rd",
    "sg:city":"Paisley",
    "sg:classifiers":[
        {
            "category":"Bars & Pubs",
            "type":"Food & Drink"
        }
    ],
    "sg:phone":"+44 141 889 0911",
    "sg:postcode":"PA1 3NU",
    "sg:province":"Renfrewshire",
    "sg:tags":[
        "pubs",
        "inn"
    ],
    "wof:name":"Harvies Showbar",
    "wof:placetype":"venue"
},
  "geometry": {"coordinates":[-4.4049129486,55.8466911316],"type":"Point"}
}