{
  "type": "Feature",
  "properties": {
    "addr:full":"Cliffe Garage, Preston Pk, Yarm Rd Stockton-on-tees Durham TS18 3RH",
    "addr:postcode":"ts18 3rh",
    "addr:street":"Preston;Yarm Rd",
    "iso:country":"GB",
    "sg:address":"Cliffe Garage, Preston Pk, Yarm Rd",
    "sg:city":"Stockton-on-tees",
    "sg:classifiers":[
        {
            "category":"Retail",
            "subcategory":"Car Wash",
            "type":"Services"
        },
        {
            "category":"Retail",
            "subcategory":"Auto Repair",
            "type":"Services"
        }
    ],
    "sg:phone":"+44 1642 618109",
    "sg:postcode":"TS18 3RH",
    "sg:province":"Durham",
    "sg:tags":[
        "modification",
        "garage",
        "polishing",
        "washing"
    ],
    "wof:name":"Cliffe Garage",
    "wof:placetype":"venue"
},
  "geometry": {"coordinates":[-1.33963,54.534752],"type":"Point"}
}