{
  "type": "Feature",
  "properties": {
    "iso:country":"GB",
    "sg:address":"2 Glen View",
    "sg:city":"Gravesend",
    "sg:classifiers":[
        {
            "category":"Social Services",
            "subcategory":"Child Care",
            "type":"Services"
        }
    ],
    "sg:phone":"+44 1474 568017",
    "sg:postcode":"DA12 1LP",
    "sg:province":"Kent",
    "sg:tags":[
        "children's",
        "home"
    ],
    "wof:name":"St. Marys Childrens Homes",
    "wof:placetype":"venue"
},
  "geometry": {"coordinates":[0.37305,51.433338],"type":"Point"}
}