{
  "type": "Feature",
  "properties": {
    "iso:country":"GB",
    "sg:address":"Shallowbridge Farm, St Breward",
    "sg:city":"Bodmin",
    "sg:classifiers":[
        {
            "category":"Farming",
            "subcategory":"Livestock Farm",
            "type":"Manufacturing & Wholesale Goods"
        }
    ],
    "sg:phone":"+44 1208 850361",
    "sg:postcode":"PL30 4PN",
    "sg:province":"Cornwall",
    "sg:tags":[
        "others"
    ],
    "wof:name":"Mary J Harper",
    "wof:placetype":"venue"
},
  "geometry": {"coordinates":[-4.67204,50.57761],"type":"Point"}
}