{
  "type": "Feature",
  "properties": {
    "iso:country":"GB",
    "sg:address":"West Park, Bridgerule",
    "sg:city":"Holsworthy",
    "sg:classifiers":[
        {
            "category":"Manufacturing",
            "subcategory":"Glass & Minerals",
            "type":"Manufacturing & Wholesale Goods"
        }
    ],
    "sg:phone":"+44 1288 381447",
    "sg:postcode":"EX22 7EX",
    "sg:province":"Cornwall",
    "sg:tags":[
        "stained",
        "designer"
    ],
    "wof:name":"Hearn Dave & Sporne Chris",
    "wof:placetype":"venue"
},
  "geometry": {"coordinates":[-4.455791,50.799919],"type":"Point"}
}