{
  "type": "Feature",
  "properties": {
    "addr:full":"14 Portland Square Carlisle Cumbria CA1 1PY",
    "addr:housenumber":"14",
    "addr:postcode":"ca1 1py",
    "addr:street":"Portland Square",
    "iso:country":"GB",
    "sg:address":"14 Portland Square",
    "sg:city":"Carlisle",
    "sg:classifiers":[
        {
            "category":"Professional",
            "subcategory":"Lawyer & Legal Services",
            "type":"Services"
        }
    ],
    "sg:phone":"+44 1228 603075",
    "sg:postcode":"CA1 1PY",
    "sg:province":"Cumbria",
    "sg:tags":[
        "advice",
        "counselling"
    ],
    "wof:name":"Gay & Bisexual Mens Health Project",
    "wof:placetype":"venue"
},
  "geometry": {"coordinates":[-2.928133,54.892509],"type":"Point"}
}