{
  "type": "Feature",
  "properties": {
    "addr:full":"259d Coggleshall Road Braintree Essex CM7 9EF",
    "addr:housenumber":"259d",
    "addr:postcode":"cm7 9ef",
    "addr:street":"Coggleshall Road",
    "iso:country":"GB",
    "sg:address":"259d Coggleshall Road",
    "sg:city":"Braintree",
    "sg:classifiers":[
        {
            "category":"Shopping",
            "subcategory":"Computers & Home Electronics",
            "type":"Retail Goods"
        }
    ],
    "sg:phone":"+44 1376 341313",
    "sg:postcode":"CM7 9EF",
    "sg:province":"Essex",
    "sg:tags":[
        "equipment",
        "radio"
    ],
    "wof:name":"Samair Systems Ltd.",
    "wof:placetype":"venue"
},
  "geometry": {"coordinates":[0.5532420278,51.8777580261],"type":"Point"}
}