{
  "type": "Feature",
  "properties": {
    "iso:country":"GB",
    "sg:address":"7 Lescudjack Terrace",
    "sg:city":"Penzance",
    "sg:classifiers":[
        {
            "category":"Retail",
            "subcategory":"Repair Shop",
            "type":"Services"
        }
    ],
    "sg:phone":"+44 1736 368917",
    "sg:postcode":"TR18 3AE",
    "sg:province":"Cornwall",
    "sg:tags":[
        "clocks",
        "watch"
    ],
    "wof:name":"R A Vercesi",
    "wof:placetype":"venue"
},
  "geometry": {"coordinates":[-5.53429,50.123817],"type":"Point"}
}