{
  "type": "Feature",
  "properties": {
    "addr:full":"Unit 2a, 175 Salhouse Rd, Caston Industrial Est Norwich Norfolk NR7 9AQ",
    "addr:housenumber":"unit 2a 175",
    "addr:postcode":"nr7 9aq",
    "addr:street":"Salhouse Rd",
    "iso:country":"GB",
    "sg:address":"Unit 2a, 175 Salhouse Rd, Caston Industrial Est",
    "sg:city":"Norwich",
    "sg:classifiers":[
        {
            "category":"Autos & Motor Vehicles",
            "subcategory":"Automobile Sales",
            "type":"Retail Goods"
        }
    ],
    "sg:postcode":"NR7 9AQ",
    "sg:province":"Norfolk",
    "sg:tags":[
        "car"
    ],
    "wof:name":"Harper,Brian A,",
    "wof:placetype":"venue"
},
  "geometry": {"coordinates":[1.3362139463,52.6486625671],"type":"Point"}
}