{
  "type": "Feature",
  "properties": {
    "addr:full":"91-93 High Street Lockerbie Dumfries and Galloway DG11 2DA",
    "addr:housenumber":"91-93",
    "addr:postcode":"dg11 2da",
    "addr:street":"High Street",
    "iso:country":"GB",
    "sg:address":"91-93 High Street",
    "sg:city":"Lockerbie",
    "sg:classifiers":[
        {
            "category":"Cafe",
            "type":"Food & Drink"
        }
    ],
    "sg:phone":"+44 1576 202379",
    "sg:postcode":"DG11 2DA",
    "sg:province":"Dumfries and Galloway",
    "sg:tags":[
        "tea",
        "room"
    ],
    "wof:name":"Cafe 91",
    "wof:placetype":"venue"
},
  "geometry": {"coordinates":[-3.3561220169,55.1205329895],"type":"Point"}
}