{
  "type": "Feature",
  "properties": {
    "iso:country":"GB",
    "sg:address":"888 Foleshill Road",
    "sg:city":"Coventry",
    "sg:classifiers":[
        {
            "category":"Manufacturing",
            "subcategory":"Lumber",
            "type":"Manufacturing & Wholesale Goods"
        }
    ],
    "sg:postcode":"CV6 6GS",
    "sg:province":"Warwickshire",
    "sg:tags":[
        "importer",
        "merchants",
        "agent",
        "timber"
    ],
    "wof:name":"Bates Timber Merchants Ltd.",
    "wof:placetype":"venue"
},
  "geometry": {"coordinates":[-1.491011,52.440254],"type":"Point"}
}