{
  "type": "Feature",
  "properties": {
    "addr:full":"12 William Street Edinburgh City of Edinburgh EH3 7NH",
    "addr:housenumber":"12",
    "addr:postcode":"eh3 7nh",
    "addr:street":"William Street",
    "iso:country":"GB",
    "sg:address":"12 William Street",
    "sg:city":"Edinburgh",
    "sg:classifiers":[
        {
            "category":"Shopping",
            "subcategory":"Clothing, Apparel, & Fashions",
            "type":"Retail Goods"
        }
    ],
    "sg:phone":"+44 131 226 3303",
    "sg:postcode":"EH3 7NH",
    "sg:province":"City of Edinburgh",
    "sg:tags":[
        "shop"
    ],
    "wof:name":"The Extra Inch Ltd.",
    "wof:placetype":"venue"
},
  "geometry": {"coordinates":[-3.2117650509,55.9494514465],"type":"Point"}
}