{
  "type": "Feature",
  "properties": {
    "addr:full":"Holly Road, Little Dawley Telford Shropshire TF4 3HB",
    "addr:postcode":"tf4 3hb",
    "addr:street":"Holly Road",
    "iso:country":"GB",
    "sg:address":"Holly Road, Little Dawley",
    "sg:city":"Telford",
    "sg:classifiers":[
        {
            "category":"Bars & Pubs",
            "type":"Food & Drink"
        }
    ],
    "sg:phone":"+44 1952 592294",
    "sg:postcode":"TF4 3HB",
    "sg:province":"Shropshire",
    "sg:tags":[
        "pubs",
        "inn"
    ],
    "wof:name":"Greenalls Management Ltd.",
    "wof:placetype":"venue"
},
  "geometry": {"coordinates":[-2.4678330421,52.6526870728],"type":"Point"}
}