{
  "type": "Feature",
  "properties": {
    "addr:full":"Old Bakery, Riverside Clo Southampton Hampshire SO40 2LW",
    "addr:postcode":"hampshire so40 2lw",
    "addr:street":"Old",
    "iso:country":"GB",
    "sg:address":"Old Bakery, Riverside Clo",
    "sg:city":"Southampton",
    "sg:classifiers":[
        {
            "category":"Building & Trades",
            "subcategory":"Construction",
            "type":"Services"
        }
    ],
    "sg:phone":"+44 23 8081 3916",
    "sg:postcode":"SO40 2LW",
    "sg:province":"Hampshire",
    "sg:tags":[
        "builder"
    ],
    "wof:name":"G J Peace & Co",
    "wof:placetype":"venue"
},
  "geometry": {"coordinates":[-1.5591,50.913231],"type":"Point"}
}