{
  "type": "Feature",
  "properties": {
    "iso:country":"GB",
    "sg:address":"196 Main Street, Cambuslang",
    "sg:city":"Glasgow",
    "sg:classifiers":[
        {
            "category":"Fast Food",
            "type":"Food & Drink"
        }
    ],
    "sg:phone":"+44 141 641 1990",
    "sg:postcode":"G72 7EN",
    "sg:province":"South Lanarkshire",
    "sg:tags":[
        "away",
        "take"
    ],
    "wof:name":"Taj Palace",
    "wof:placetype":"venue"
},
  "geometry": {"coordinates":[-4.168389,55.819035],"type":"Point"}
}