{
  "type": "Feature",
  "properties": {
    "iso:country":"GB",
    "sg:address":"2 Clarence Pl",
    "sg:city":"London",
    "sg:classifiers":[
        {
            "category":"Food & Beverages",
            "subcategory":"Specialty",
            "type":"Retail Goods"
        }
    ],
    "sg:phone":"+44 20 8986 3963",
    "sg:postcode":"E5 8HN",
    "sg:province":"Greater London",
    "sg:tags":[
        "product",
        "health"
    ],
    "wof:name":"Herbalife",
    "wof:placetype":"venue"
},
  "geometry": {"coordinates":[-0.0551870018,51.5516395569],"type":"Point"}
}