{
  "type": "Feature",
  "properties": {
    "addr:full":"Pikestone Court, Portsmouth Drive Chorley Lancashire PR6 0TX",
    "addr:postcode":"pr6 0tx",
    "addr:street":"Portsmouth Drive",
    "iso:country":"GB",
    "sg:address":"Pikestone Court, Portsmouth Drive",
    "sg:city":"Chorley",
    "sg:classifiers":[
        {
            "category":"Organizations",
            "subcategory":"Community Association",
            "type":"Services"
        }
    ],
    "sg:phone":"+44 1257 266056",
    "sg:postcode":"PR6 0TX",
    "sg:province":"Lancashire",
    "sg:tags":[
        "co-operatives",
        "society",
        "housing",
        "trust"
    ],
    "wof:name":"Anchor Trust",
    "wof:placetype":"venue"
},
  "geometry": {"coordinates":[-2.6154079437,53.6527633667],"type":"Point"}
}