{
  "type": "Feature",
  "properties": {
    "addr:full":"Unit 4 Cotteswold Dairy Estate, Northway Lane Tewkesbury Gloucestershire GL20 8JE",
    "addr:housenumber":"unit 4",
    "addr:postcode":"gl20 8je",
    "addr:street":"Northway Lane",
    "iso:country":"GB",
    "sg:address":"Unit 4 Cotteswold Dairy Estate, Northway Lane",
    "sg:city":"Tewkesbury",
    "sg:classifiers":[
        {
            "category":"Retail",
            "subcategory":"Auto Repair",
            "type":"Services"
        }
    ],
    "sg:phone":"+44 1684 295091",
    "sg:postcode":"GL20 8JE",
    "sg:province":"Gloucestershire",
    "sg:tags":[
        "body",
        "car"
    ],
    "wof:name":"Tom Brown & Son",
    "wof:placetype":"venue"
},
  "geometry": {"coordinates":[-2.1038041115,51.9978027344],"type":"Point"}
}