{
  "type": "Feature",
  "properties": {
    "addr:full":"1-3 Chiswick Terrace, Acton Lane London Greater London W4 5LY",
    "addr:housenumber":"1-3",
    "addr:postcode":"w4 5ly",
    "addr:street":"Chiswick Terrace Acton Lane",
    "iso:country":"GB",
    "sg:address":"1-3 Chiswick Terrace, Acton Lane",
    "sg:city":"London",
    "sg:classifiers":[
        {
            "category":"Home & Garden",
            "subcategory":"Carpets & Floor Coverings",
            "type":"Retail Goods"
        }
    ],
    "sg:postcode":"W4 5LY",
    "sg:province":"Greater London",
    "sg:tags":[
        "carpets",
        "rug",
        "matting"
    ],
    "wof:name":"L & B Carpets Ltd.",
    "wof:placetype":"venue"
},
  "geometry": {"coordinates":[-0.2667599916,51.4931297302],"type":"Point"}
}