{
  "type": "Feature",
  "properties": {
    "iso:country":"GB",
    "sg:address":"Funtington",
    "sg:city":"Chichester",
    "sg:classifiers":[
        {
            "category":"Shopping",
            "subcategory":"Department Store",
            "type":"Retail Goods"
        },
        {
            "category":"Food & Beverages",
            "subcategory":"Groceries & Convenience Stores",
            "type":"Retail Goods"
        }
    ],
    "sg:phone":"+44 1243 575245",
    "sg:postcode":"PO18 9LJ",
    "sg:province":"West Sussex",
    "wof:name":"Country Fayre",
    "wof:placetype":"venue"
},
  "geometry": {"coordinates":[-0.86415,50.868462],"type":"Point"}
}