{
  "type": "Feature",
  "properties": {
    "iso:country":"GB",
    "sg:address":"Block 9 Caponacre Indslt Est",
    "sg:city":"Cumnock",
    "sg:classifiers":[
        {
            "category":"Freight",
            "type":"Transportation"
        }
    ],
    "sg:postcode":"KA18 1SH",
    "sg:province":"East Ayrshire",
    "sg:tags":[
        "haulage",
        "road"
    ],
    "wof:name":"Baird,John,Transport Ltd",
    "wof:placetype":"venue"
},
  "geometry": {"coordinates":[-4.264099,55.453255],"type":"Point"}
}