{
  "type": "Feature",
  "properties": {
    "iso:country":"GB",
    "sg:address":"85 Chamberlayne Road",
    "sg:city":"London",
    "sg:classifiers":[
        {
            "category":"Health Services",
            "subcategory":"Health Practitioner",
            "type":"Services"
        },
        {
            "category":"Shopping",
            "subcategory":"Pharmacy",
            "type":"Retail Goods"
        }
    ],
    "sg:phone":"+44 20 8964 2421",
    "sg:postcode":"NW10 3ND",
    "sg:province":"Greater London",
    "sg:tags":[
        "medicine",
        "medical",
        "therapy",
        "treatment",
        "alternative"
    ],
    "wof:name":"Chinese Health Care Centre",
    "wof:placetype":"venue"
},
  "geometry": {"coordinates":[-0.218941,51.534206],"type":"Point"}
}