{
  "type": "Feature",
  "properties": {
    "addr:full":"12 South Street Chichester West Sussex PO19 1EH",
    "addr:housenumber":"12",
    "addr:postcode":"po19 1eh",
    "addr:street":"South Street",
    "iso:country":"GB",
    "sg:address":"12 South Street",
    "sg:city":"Chichester",
    "sg:classifiers":[
        {
            "category":"Shopping",
            "subcategory":"Comic Books",
            "type":"Retail Goods"
        }
    ],
    "sg:phone":"+44 1243 538313",
    "sg:postcode":"PO19 1EH",
    "sg:province":"West Sussex",
    "sg:tags":[
        "jeweller",
        "sale",
        "jewellery"
    ],
    "sg:website":"http://www.timothyroe.co.uk",
    "wof:name":"Timothy Roe Fine Jewellery Ltd",
    "wof:placetype":"venue"
},
  "geometry": {"coordinates":[-0.779437,50.835888],"type":"Point"}
}