{
  "type": "Feature",
  "properties": {
    "addr:full":"533 Kings Road London Greater London SW10 0TZ",
    "addr:housenumber":"533",
    "addr:postcode":"sw10 0tz",
    "addr:street":"Kings Road",
    "iso:country":"GB",
    "sg:address":"533 Kings Road",
    "sg:city":"London",
    "sg:classifiers":[
        {
            "category":"Bars & Pubs",
            "subcategory":"Nightclub",
            "type":"Food & Drink"
        }
    ],
    "sg:phone":"+44 20 7376 5555",
    "sg:postcode":"SW10 0TZ",
    "sg:province":"Greater London",
    "sg:tags":[
        "club",
        "night",
        "activity"
    ],
    "wof:name":"Crazy Larry'S",
    "wof:placetype":"venue"
},
  "geometry": {"coordinates":[-0.185447,51.48027],"type":"Point"}
}