{
  "type": "Feature",
  "properties": {
    "iso:country":"GB",
    "sg:address":"Froggatt Ct, Bredbury Parkway, Bredbury",
    "sg:city":"Stockport",
    "sg:classifiers":[
        {
            "category":"Professional",
            "subcategory":"Engineering",
            "type":"Services"
        }
    ],
    "sg:postcode":"SK6 2SN",
    "sg:province":"Cheshire",
    "wof:name":"Blade Engineering Ltd",
    "wof:placetype":"venue"
},
  "geometry": {"coordinates":[-2.122762,53.42065],"type":"Point"}
}