{
  "type": "Feature",
  "properties": {
    "addr:full":"High Bow, Bow Carlisle Cumbria CA5 6EN",
    "addr:postcode":"ca5 6en",
    "iso:country":"GB",
    "sg:address":"High Bow, Bow",
    "sg:city":"Carlisle",
    "sg:classifiers":[
        {
            "category":"Farming",
            "subcategory":"Livestock Farm",
            "type":"Manufacturing & Wholesale Goods"
        }
    ],
    "sg:phone":"+44 1228 576243",
    "sg:postcode":"CA5 6EN",
    "sg:province":"Cumbria",
    "sg:tags":[
        "others"
    ],
    "wof:name":"J M & I Holliday",
    "wof:placetype":"venue"
},
  "geometry": {"coordinates":[-3.0386400223,54.8949890137],"type":"Point"}
}