{
  "type": "Feature",
  "properties": {
    "iso:country":"GB",
    "sg:address":"Dover Rd",
    "sg:city":"Dover",
    "sg:classifiers":[
        {
            "category":"Autos & Motor Vehicles",
            "subcategory":"Fuel & Gas Station",
            "type":"Retail Goods"
        }
    ],
    "sg:phone":"+44 1304 225640",
    "sg:postcode":"CT15 5EH",
    "sg:province":"Kent",
    "sg:tags":[
        "hr",
        "petrol"
    ],
    "wof:name":"Elf Service Station",
    "wof:placetype":"venue"
},
  "geometry": {"coordinates":[1.318732,51.148945],"type":"Point"}
}