{
  "type": "Feature",
  "properties": {
    "iso:country":"GB",
    "sg:address":"58 Battersea Park Road",
    "sg:city":"London",
    "sg:classifiers":[
        {
            "category":"Building & Trades",
            "subcategory":"Cleaning & Sanitation",
            "type":"Services"
        }
    ],
    "sg:postcode":"SW11 4JP",
    "sg:province":"Greater London",
    "sg:tags":[
        "commercial"
    ],
    "wof:name":"Julius Rutherford & Co. Ltd.",
    "wof:placetype":"venue"
},
  "geometry": {"coordinates":[-0.151404,51.475433],"type":"Point"}
}