{
  "type": "Feature",
  "properties": {
    "iso:country":"GB",
    "sg:address":"13 Winiford Road",
    "sg:city":"London",
    "sg:classifiers":[
        {
            "category":"Building & Trades",
            "subcategory":"Landscaping Services",
            "type":"Services"
        }
    ],
    "sg:postcode":"SW19 3AS",
    "sg:province":"Greater London",
    "sg:tags":[
        "design",
        "garden"
    ],
    "wof:name":"Neil Wormald",
    "wof:placetype":"venue"
},
  "geometry": {"coordinates":[-0.199158,51.413979],"type":"Point"}
}