{
  "type": "Feature",
  "properties": {
    "iso:country":"GB",
    "sg:address":"Anglian Rd",
    "sg:city":"Walsall",
    "sg:classifiers":[
        {
            "category":"Freight",
            "type":"Transportation"
        }
    ],
    "sg:phone":"+44 1922 454411",
    "sg:postcode":"WS9 8ET",
    "sg:province":"Staffordshire",
    "sg:tags":[
        "haulage",
        "road"
    ],
    "wof:name":"S Jones Transport Group",
    "wof:placetype":"venue"
},
  "geometry": {"coordinates":[-1.943928,52.603603],"type":"Point"}
}