{
  "type": "Feature",
  "properties": {
    "iso:country":"GB",
    "sg:address":"Acton Park Nurseries, Acton Park",
    "sg:city":"Wrexham",
    "sg:classifiers":[
        {
            "category":"Government",
            "subcategory":"Office",
            "type":"Public Place"
        }
    ],
    "sg:phone":"+44 1978 351591",
    "sg:postcode":"LL11 2SN",
    "sg:province":"Wrexham",
    "sg:tags":[
        "local"
    ],
    "wof:name":"Wrexham County Borough Council",
    "wof:placetype":"venue"
},
  "geometry": {"coordinates":[-2.992646,53.060043],"type":"Point"}
}