{
  "type": "Feature",
  "properties": {
    "addr:full":"Rectory, Church Walk Sudbury Essex CO10 9DL",
    "addr:postcode":"co10 9dl",
    "addr:street":"Church Walk",
    "iso:country":"GB",
    "sg:address":"Rectory, Church Walk",
    "sg:city":"Sudbury",
    "sg:classifiers":[
        {
            "category":"Place Of Worship",
            "type":"Public Place"
        }
    ],
    "sg:phone":"+44 1787 310845",
    "sg:postcode":"CO10 9DL",
    "sg:province":"Essex",
    "wof:name":"Holy Trinity Long Melford Church",
    "wof:placetype":"venue"
},
  "geometry": {"coordinates":[0.7343900204,52.0386047363],"type":"Point"}
}