{
  "type": "Feature",
  "properties": {
    "addr:full":"The Warehouse, Coverdale Rd Paignton Devon TQ3 3HQ",
    "addr:postcode":"tq3 3hq",
    "addr:street":"Coverdale Rd",
    "iso:country":"GB",
    "sg:address":"The Warehouse, Coverdale Rd",
    "sg:city":"Paignton",
    "sg:classifiers":[
        {
            "category":"Manufacturing",
            "subcategory":"Petroleum Products",
            "type":"Manufacturing & Wholesale Goods"
        }
    ],
    "sg:phone":"+44 1803 664300",
    "sg:postcode":"TQ3 3HQ",
    "sg:province":"Devon",
    "sg:tags":[
        "double",
        "glazing"
    ],
    "wof:name":"Sekura Windows",
    "wof:placetype":"venue"
},
  "geometry": {"coordinates":[-3.5676140785,50.4385681152],"type":"Point"}
}