{
  "type": "Feature",
  "properties": {
    "iso:country":"GB",
    "sg:address":"Lower Keys",
    "sg:city":"Evesham",
    "sg:classifiers":[
        {
            "category":"Travel",
            "subcategory":"Hotels & Motels",
            "type":"Entertainment"
        }
    ],
    "sg:phone":"+44 1386 442417",
    "sg:postcode":"WR11 3AB",
    "sg:province":"Gloucestershire",
    "sg:tags":[
        "self",
        "catering"
    ],
    "wof:name":"Weir Meadow Touring & Holiday Park",
    "wof:placetype":"venue"
},
  "geometry": {"coordinates":[-1.9398390055,52.0917205811],"type":"Point"}
}