{
  "type": "Feature",
  "properties": {
    "iso:country":"GB",
    "sg:address":"15 Market Place",
    "sg:city":"Uttoxeter",
    "sg:classifiers":[
        {
            "category":"Health Services",
            "subcategory":"Optometrist",
            "type":"Services"
        }
    ],
    "sg:phone":"+44 1889 567474",
    "sg:postcode":"ST14 8HY",
    "sg:province":"Derbyshire",
    "sg:tags":[
        "optician"
    ],
    "wof:name":"Peter Bowers",
    "wof:placetype":"venue"
},
  "geometry": {"coordinates":[-1.863302,52.898159],"type":"Point"}
}