{
  "type": "Feature",
  "properties": {
    "addr:full":"193 High Street Egham Surrey TW20 9ED",
    "addr:housenumber":"193",
    "addr:postcode":"tw20 9ed",
    "addr:street":"High Street",
    "iso:country":"GB",
    "sg:address":"193 High Street",
    "sg:city":"Egham",
    "sg:classifiers":[
        {
            "category":"Building & Trades",
            "subcategory":"Equipment Rental",
            "type":"Services"
        }
    ],
    "sg:phone":"+44 1784 433984",
    "sg:postcode":"TW20 9ED",
    "sg:province":"Surrey",
    "sg:tags":[
        "hire",
        "tool",
        "centre"
    ],
    "wof:name":"Thames Valley Tool Hire Ltd.",
    "wof:placetype":"venue"
},
  "geometry": {"coordinates":[-0.5447340012,51.4326400757],"type":"Point"}
}