{
  "type": "Feature",
  "properties": {
    "addr:full":"107 Lower Marsh Southwark Greater London SE1 7AB",
    "addr:housenumber":"107",
    "addr:postcode":"se1 7ab",
    "addr:street":"Lower Marsh",
    "iso:country":"GB",
    "sg:address":"107 Lower Marsh",
    "sg:city":"Southwark",
    "sg:classifiers":[
        {
            "category":"Restaurant",
            "type":"Food & Drink"
        }
    ],
    "sg:phone":"+44 20 7928 7647",
    "sg:postcode":"SE1 7AB",
    "sg:province":"Greater London",
    "wof:name":"Starburger",
    "wof:placetype":"venue"
},
  "geometry": {"coordinates":[-0.1124569997,51.501121521],"type":"Point"}
}