{
  "type": "Feature",
  "properties": {
    "addr:full":"5c Town Hall Street Blackburn Lancashire BB2 1AG",
    "addr:housenumber":"5c",
    "addr:postcode":"bb2 1ag",
    "addr:street":"Town Hall Street",
    "iso:country":"GB",
    "sg:address":"5c Town Hall Street",
    "sg:city":"Blackburn",
    "sg:classifiers":[
        {
            "category":"Shopping",
            "subcategory":"Department Store",
            "type":"Retail Goods"
        }
    ],
    "sg:phone":"+44 1254 698694",
    "sg:postcode":"BB2 1AG",
    "sg:province":"Lancashire",
    "wof:name":"Janet Wilkinson",
    "wof:placetype":"venue"
},
  "geometry": {"coordinates":[-2.4854230881,53.7498054504],"type":"Point"}
}