{
  "type": "Feature",
  "properties": {
    "iso:country":"GB",
    "sg:address":"14 Barkfield Avenue, Formby",
    "sg:city":"Liverpool",
    "sg:classifiers":[
        {
            "category":"Retail",
            "subcategory":"Storage",
            "type":"Services"
        }
    ],
    "sg:postcode":"L37 3JH",
    "sg:province":"Lancashire",
    "sg:tags":[
        "household",
        "removal"
    ],
    "wof:name":"Formby Removals",
    "wof:placetype":"venue"
},
  "geometry": {"coordinates":[-3.0709528923,53.5594329834],"type":"Point"}
}