{
  "type": "Feature",
  "properties": {
    "iso:country":"GB",
    "sg:address":"Affleck Gdns",
    "sg:city":"Dundee",
    "sg:classifiers":[
        {
            "category":"Professional",
            "subcategory":"Printing & Photocopies",
            "type":"Services"
        }
    ],
    "sg:phone":"+44 1382 370329",
    "sg:postcode":"DD5 3QQ",
    "sg:province":"Angus",
    "sg:tags":[
        "printer"
    ],
    "wof:name":"Niche Printers",
    "wof:placetype":"venue"
},
  "geometry": {"coordinates":[-2.8148241043,56.5392150879],"type":"Point"}
}