{
  "type": "Feature",
  "properties": {
    "iso:country":"GB",
    "sg:address":"50 Alexandra Road",
    "sg:city":"Worthing",
    "sg:classifiers":[
        {
            "category":"Travel",
            "subcategory":"Hotels & Motels",
            "type":"Entertainment"
        }
    ],
    "sg:postcode":"BN11 2DU",
    "sg:province":"West Sussex",
    "sg:tags":[
        "house",
        "guest"
    ],
    "wof:name":"Edelweiss Guest House",
    "wof:placetype":"venue"
},
  "geometry": {"coordinates":[-0.3562430143,50.8144989014],"type":"Point"}
}