{
  "type": "Feature",
  "properties": {
    "iso:country":"GB",
    "sg:address":"41 Hartington Avenue, Carlton",
    "sg:city":"Nottingham",
    "sg:classifiers":[
        {
            "category":"Building & Trades",
            "subcategory":"Cleaning & Sanitation",
            "type":"Services"
        }
    ],
    "sg:phone":"+44 115 952 1711",
    "sg:postcode":"NG4 3NR",
    "sg:province":"Nottinghamshire",
    "sg:tags":[
        "commercial"
    ],
    "wof:name":"Office & Home Maintenance Services",
    "wof:placetype":"venue"
},
  "geometry": {"coordinates":[-1.0941660404,52.9754676819],"type":"Point"}
}