{
  "type": "Feature",
  "properties": {
    "addr:full":"Rear Of, 57 Churchfield Road Peterborough Cambridgeshire PE4 6HE",
    "addr:housenumber":"rear of 57",
    "addr:postcode":"pe4 6he",
    "addr:street":"Churchfield Road",
    "iso:country":"GB",
    "sg:address":"Rear Of, 57 Churchfield Road",
    "sg:city":"Peterborough",
    "sg:classifiers":[
        {
            "category":"Food & Beverages",
            "subcategory":"Meat & Fish",
            "type":"Retail Goods"
        }
    ],
    "sg:postcode":"PE4 6HE",
    "sg:province":"Cambridgeshire",
    "sg:tags":[
        "chip"
    ],
    "wof:name":"Orchard Fish Shop",
    "wof:placetype":"venue"
},
  "geometry": {"coordinates":[-0.2634899914,52.602809906],"type":"Point"}
}