{
  "type": "Feature",
  "properties": {
    "iso:country":"GB",
    "sg:address":"24 St Helens Way, Ben Rhydding",
    "sg:city":"Ilkley",
    "sg:classifiers":[
        {
            "category":"Professional",
            "subcategory":"Management & Consulting",
            "type":"Services"
        }
    ],
    "sg:postcode":"LS29 8NP",
    "sg:province":"North Yorkshire",
    "sg:tags":[
        "consultant",
        "business"
    ],
    "wof:name":"Gabe,Peter,",
    "wof:placetype":"venue"
},
  "geometry": {"coordinates":[-1.80776,53.925652],"type":"Point"}
}