{
  "type": "Feature",
  "properties": {
    "addr:full":"23 Chipponds Drive St. Austell Cornwall PL25 5DE",
    "addr:housenumber":"23",
    "addr:postcode":"pl25 5de",
    "addr:street":"Chipponds Drive",
    "iso:country":"GB",
    "sg:address":"23 Chipponds Drive",
    "sg:city":"St. Austell",
    "sg:classifiers":[
        {
            "category":"Home & Garden",
            "subcategory":"Building Materials",
            "type":"Retail Goods"
        }
    ],
    "sg:phone":"+44 1726 76900",
    "sg:postcode":"PL25 5DE",
    "sg:province":"Cornwall",
    "sg:tags":[
        "insulation",
        "installers"
    ],
    "wof:name":"M & K Plastering Systems",
    "wof:placetype":"venue"
},
  "geometry": {"coordinates":[-4.8085598946,50.3367576599],"type":"Point"}
}