{
  "type": "Feature",
  "properties": {
    "addr:full":"40 Littlebrook Gardens, Cheshunt Waltham Cross Essex EN8 8QQ",
    "addr:housenumber":"40",
    "addr:postcode":"en8 8qq",
    "addr:street":"Littlebrook Gardens;Waltham Cross",
    "iso:country":"GB",
    "sg:address":"40 Littlebrook Gardens, Cheshunt",
    "sg:city":"Waltham Cross",
    "sg:classifiers":[
        {
            "category":"Building & Trades",
            "subcategory":"Construction",
            "type":"Services"
        }
    ],
    "sg:phone":"+44 1992 428234",
    "sg:postcode":"EN8 8QQ",
    "sg:province":"Essex",
    "sg:tags":[
        "builder"
    ],
    "wof:name":"Northstate Contracts Ltd.",
    "wof:placetype":"venue"
},
  "geometry": {"coordinates":[-0.0401719995,51.7018966675],"type":"Point"}
}