{
  "type": "Feature",
  "properties": {
    "iso:country":"GB",
    "sg:address":"Eagle Centre Market, Eagle Centre",
    "sg:city":"Derby",
    "sg:classifiers":[
        {
            "category":"Professional",
            "subcategory":"Art Services",
            "type":"Services"
        }
    ],
    "sg:phone":"+44 1332 368598",
    "sg:postcode":"DE1 2AZ",
    "sg:province":"Derbyshire",
    "sg:tags":[
        "picture",
        "restoration",
        "framing"
    ],
    "wof:name":"Names & Frames",
    "wof:placetype":"venue"
},
  "geometry": {"coordinates":[-1.483684,52.925171],"type":"Point"}
}