{
  "type": "Feature",
  "properties": {
    "iso:country":"GB",
    "sg:address":"7 George Street",
    "sg:city":"Oxford",
    "sg:classifiers":[
        {
            "category":"Bars & Pubs",
            "type":"Food & Drink"
        }
    ],
    "sg:phone":"+44 1865 793380",
    "sg:postcode":"OX1 2AT",
    "sg:province":"Oxfordshire",
    "sg:tags":[
        "pubs",
        "inn"
    ],
    "wof:name":"The Grapes",
    "wof:placetype":"venue"
},
  "geometry": {"coordinates":[-1.2589739561,51.7538833618],"type":"Point"}
}