{
  "type": "Feature",
  "properties": {
    "addr:full":"Christchurch Ho, 1-7 The Embankment Wellingborough Northamptonshire NN8 1LD",
    "addr:housenumber":"1-7",
    "addr:postcode":"nn8 1ld",
    "addr:street":"The Embankment",
    "iso:country":"GB",
    "sg:address":"Christchurch Ho, 1-7 The Embankment",
    "sg:city":"Wellingborough",
    "sg:classifiers":[
        {
            "category":"Government",
            "subcategory":"Office",
            "type":"Public Place"
        }
    ],
    "sg:phone":"+44 1933 225731",
    "sg:postcode":"NN8 1LD",
    "sg:province":"Northamptonshire",
    "sg:tags":[
        "central"
    ],
    "wof:name":"H M Inspector Of Taxes",
    "wof:placetype":"venue"
},
  "geometry": {"coordinates":[-0.696296,52.302422],"type":"Point"}
}