{
  "type": "Feature",
  "properties": {
    "addr:full":"Derbyshire House, Sherwin St Derby Derbyshire DE22 1GP",
    "addr:postcode":"de22 1gp",
    "addr:street":"Sherwin St",
    "iso:country":"GB",
    "sg:address":"Derbyshire House, Sherwin St",
    "sg:city":"Derby",
    "sg:classifiers":[
        {
            "category":"Organizations",
            "subcategory":"Non-profit Organization",
            "type":"Services"
        }
    ],
    "sg:phone":"+44 1332 384232",
    "sg:postcode":"DE22 1GP",
    "sg:province":"Derbyshire",
    "sg:tags":[
        "organisation",
        "voluntary",
        "charity"
    ],
    "wof:name":"NFWI Area Base",
    "wof:placetype":"venue"
},
  "geometry": {"coordinates":[-1.4938540459,52.9348564148],"type":"Point"}
}