{
  "type": "Feature",
  "properties": {
    "iso:country":"GB",
    "sg:address":"Station Street, Abersychan",
    "sg:city":"Pontypool",
    "sg:classifiers":[
        {
            "category":"Bars & Pubs",
            "type":"Food & Drink"
        }
    ],
    "sg:phone":"+44 1495 772152",
    "sg:postcode":"NP4 8PH",
    "sg:province":"Monmouthshire",
    "sg:tags":[
        "pubs",
        "inn"
    ],
    "wof:name":"Buck Inn",
    "wof:placetype":"venue"
},
  "geometry": {"coordinates":[-3.058544,51.724365],"type":"Point"}
}