{
  "type": "Feature",
  "properties": {
    "addr:full":"38 Woodcroft Road Wylam Northumberland NE41 8DH",
    "addr:housenumber":"38",
    "addr:postcode":"ne41 8dh",
    "addr:street":"Woodcroft Road",
    "iso:country":"GB",
    "sg:address":"38 Woodcroft Road",
    "sg:city":"Wylam",
    "sg:classifiers":[
        {
            "category":"Building & Trades",
            "subcategory":"Landscaping Services",
            "type":"Services"
        }
    ],
    "sg:phone":"+44 1661 836471",
    "sg:postcode":"NE41 8DH",
    "sg:province":"Northumberland",
    "sg:tags":[
        "forestry",
        "surgeon",
        "tree"
    ],
    "wof:name":"Simon Brough",
    "wof:placetype":"venue"
},
  "geometry": {"coordinates":[-1.8241130114,54.9752120972],"type":"Point"}
}