{
  "type": "Feature",
  "properties": {
    "iso:country":"GB",
    "sg:address":"33 Mulgrave Road",
    "sg:city":"Sutton",
    "sg:classifiers":[
        {
            "category":"Health Services",
            "subcategory":"Dentist",
            "type":"Services"
        }
    ],
    "sg:phone":"+44 20 8715 1107",
    "sg:postcode":"SM2 6LJ",
    "sg:province":"Surrey",
    "wof:name":"Laurence G Phelps",
    "wof:placetype":"venue"
},
  "geometry": {"coordinates":[-0.195739,51.358036],"type":"Point"}
}