{
  "type": "Feature",
  "properties": {
    "iso:country":"GB",
    "sg:address":"William Street",
    "sg:city":"Barrow-in-furness",
    "sg:classifiers":[
        {
            "category":"Bars & Pubs",
            "type":"Food & Drink"
        },
        {
            "category":"Community Center",
            "subcategory":"Social",
            "type":"Public Place"
        }
    ],
    "sg:phone":"+44 1229 828447",
    "sg:postcode":"LA14 1JZ",
    "sg:province":"Cumbria",
    "sg:tags":[
        "pubs",
        "house",
        "inn",
        "activity"
    ],
    "wof:name":"Cross Keys Hotel",
    "wof:placetype":"venue"
},
  "geometry": {"coordinates":[-3.2279639244,54.11328125],"type":"Point"}
}