{
  "type": "Feature",
  "properties": {
    "addr:full":"Oakendene Indust Est, Bolney Rd Horsham West Sussex RH13 8AZ",
    "addr:postcode":"rh13 8az",
    "addr:street":"Bolney Rd",
    "iso:country":"GB",
    "sg:address":"Oakendene Indust Est, Bolney Rd",
    "sg:city":"Horsham",
    "sg:classifiers":[
        {
            "category":"Shopping",
            "subcategory":"Clothing, Apparel, & Fashions",
            "type":"Retail Goods"
        }
    ],
    "sg:phone":"+44 1403 865376",
    "sg:postcode":"RH13 8AZ",
    "sg:province":"West Sussex",
    "sg:tags":[
        "wear",
        "leisure"
    ],
    "wof:name":"Plain Lazy",
    "wof:placetype":"venue"
},
  "geometry": {"coordinates":[-0.2553,50.991692],"type":"Point"}
}