{
  "type": "Feature",
  "properties": {
    "addr:full":"Blenheim Camp, Newmarket Road Bury St Edmunds Suffolk IP33 3SW",
    "addr:postcode":"ip33 3sw",
    "addr:street":"Newmarket Road",
    "iso:country":"GB",
    "sg:address":"Blenheim Camp, Newmarket Road",
    "sg:city":"Bury St Edmunds",
    "sg:classifiers":[
        {
            "category":"Organizations",
            "subcategory":"Community Association",
            "type":"Services"
        },
        {
            "category":"Organizations",
            "subcategory":"Membership Organization",
            "type":"Services"
        }
    ],
    "sg:postcode":"IP33 3SW",
    "sg:province":"Suffolk",
    "sg:tags":[
        "club",
        "social"
    ],
    "wof:name":"The Royal Anglian Association Club",
    "wof:placetype":"venue"
},
  "geometry": {"coordinates":[0.70932,52.249905],"type":"Point"}
}