{
  "type": "Feature",
  "properties": {
    "iso:country":"GB",
    "sg:address":"5-9 Bridge Street",
    "sg:city":"Bonnybridge",
    "sg:classifiers":[
        {
            "category":"Professional",
            "subcategory":"Accounting & Tax Preparation",
            "type":"Services"
        }
    ],
    "sg:phone":"+44 1324 812169",
    "sg:postcode":"FK4 1AD",
    "sg:province":"Falkirk",
    "sg:tags":[
        "accountant"
    ],
    "wof:name":"Dickson Middleton & Co",
    "wof:placetype":"venue"
},
  "geometry": {"coordinates":[-3.886884,56.000778],"type":"Point"}
}