{
  "type": "Feature",
  "properties": {
    "addr:full":"24 Springmeadow, Charlesworth Glossop Derbyshire SK13 5HP",
    "addr:housenumber":"24",
    "addr:postcode":"sk13 5hp",
    "addr:street":"Springmeadow Charlesworth",
    "iso:country":"GB",
    "sg:address":"24 Springmeadow, Charlesworth",
    "sg:city":"Glossop",
    "sg:classifiers":[
        {
            "category":"Professional",
            "subcategory":"Management & Consulting",
            "type":"Services"
        }
    ],
    "sg:phone":"+44 1457 867027",
    "sg:postcode":"SK13 5HP",
    "sg:province":"Derbyshire",
    "sg:tags":[
        "consultant",
        "business"
    ],
    "wof:name":"Geoff Roberts Associates Ltd.",
    "wof:placetype":"venue"
},
  "geometry": {"coordinates":[-1.991179,53.435108],"type":"Point"}
}