{
  "type": "Feature",
  "properties": {
    "addr:full":"55 Times Square, High St Sutton Surrey SM1 1LF",
    "addr:housenumber":"55",
    "addr:postcode":"sm1 1lf",
    "addr:street":"Times;High St",
    "iso:country":"GB",
    "sg:address":"55 Times Square, High St",
    "sg:city":"Sutton",
    "sg:classifiers":[
        {
            "category":"Shopping",
            "subcategory":"Gifts & Souvenirs",
            "type":"Retail Goods"
        }
    ],
    "sg:phone":"+44 20 8288 0818",
    "sg:postcode":"SM1 1LF",
    "sg:province":"Surrey",
    "sg:tags":[
        "shop"
    ],
    "wof:name":"Memory Lane",
    "wof:placetype":"venue"
},
  "geometry": {"coordinates":[-0.192759,51.362785],"type":"Point"}
}