{
  "type": "Feature",
  "properties": {
    "iso:country":"GB",
    "sg:address":"Minafon, Beddgelert",
    "sg:city":"Caernarfon",
    "sg:classifiers":[
        {
            "category":"Shopping",
            "subcategory":"Department Store",
            "type":"Retail Goods"
        },
        {
            "category":"Transit Center",
            "subcategory":"Freight",
            "type":"Transportation"
        },
        {
            "category":"Shopping",
            "subcategory":"Crafts & Fabrics",
            "type":"Retail Goods"
        }
    ],
    "sg:phone":"+44 1766 890586",
    "sg:postcode":"LL55 4NB",
    "sg:province":"Gwynedd",
    "sg:tags":[
        "shop",
        "outlet",
        "centre"
    ],
    "wof:name":"Beddgelert Woodcraft",
    "wof:placetype":"venue"
},
  "geometry": {"coordinates":[-4.1007938385,53.0123100281],"type":"Point"}
}