{
  "type": "Feature",
  "properties": {
    "addr:full":"17 Newbury St Wantage Berkshire OX12 8BU",
    "addr:housenumber":"17",
    "addr:postcode":"ox12 8bu",
    "addr:street":"Newbury St",
    "iso:country":"GB",
    "sg:address":"17 Newbury St",
    "sg:city":"Wantage",
    "sg:classifiers":[
        {
            "category":"Organizations",
            "subcategory":"Non-profit Organization",
            "type":"Services"
        }
    ],
    "sg:phone":"+44 1235 760422",
    "sg:postcode":"OX12 8BU",
    "sg:province":"Berkshire",
    "sg:tags":[
        "organisation",
        "voluntary",
        "charity"
    ],
    "wof:name":"Save The Children Charity Shop",
    "wof:placetype":"venue"
},
  "geometry": {"coordinates":[-1.4258359671,51.587726593],"type":"Point"}
}