{
  "type": "Feature",
  "properties": {
    "iso:country":"GB",
    "sg:address":"250 High Street",
    "sg:city":"Guildford",
    "sg:classifiers":[
        {
            "category":"Organizations",
            "subcategory":"Membership Organization",
            "type":"Services"
        }
    ],
    "sg:postcode":"GU1 3JG",
    "sg:province":"Surrey",
    "sg:tags":[
        "club"
    ],
    "wof:name":"1ST Sherydon Management Company Limited(",
    "wof:placetype":"venue"
},
  "geometry": {"coordinates":[-0.567585,51.237164],"type":"Point"}
}