{
  "type": "Feature",
  "properties": {
    "addr:full":"Chapel View, Caldbeck Wigton Cumbria CA7 8EB",
    "addr:postcode":"ca7 8eb",
    "addr:street":"Chapel",
    "iso:country":"GB",
    "sg:address":"Chapel View, Caldbeck",
    "sg:city":"Wigton",
    "sg:classifiers":[
        {
            "category":"Bus Charters",
            "type":"Transportation"
        }
    ],
    "sg:phone":"+44 16974 78237",
    "sg:postcode":"CA7 8EB",
    "sg:province":"Cumbria",
    "sg:tags":[
        "hire",
        "coach"
    ],
    "wof:name":"Tysons of Cumbria",
    "wof:placetype":"venue"
},
  "geometry": {"coordinates":[-3.0522398949,54.7492179871],"type":"Point"}
}