{
  "type": "Feature",
  "properties": {
    "addr:full":"Business College, Vicarage Farm Road Peterborough Cambridgeshire PE1 5TP",
    "addr:postcode":"pe1 5tp",
    "addr:street":"Farm Road",
    "iso:country":"GB",
    "sg:address":"Business College, Vicarage Farm Road",
    "sg:city":"Peterborough",
    "sg:classifiers":[
        {
            "category":"Education",
            "subcategory":"Special Training",
            "type":"Public Place"
        }
    ],
    "sg:phone":"+44 1733 312120",
    "sg:postcode":"PE1 5TP",
    "sg:province":"Cambridgeshire",
    "sg:tags":[
        "product",
        "centre"
    ],
    "wof:name":"Peterborough Itec Ltd.",
    "wof:placetype":"venue"
},
  "geometry": {"coordinates":[-0.2144200057,52.578540802],"type":"Point"}
}