{
  "type": "Feature",
  "properties": {
    "addr:full":"Patchway Health & Fitness Centre, 38-42 Bradley Road Bristol Gloucestershire BS34 5LB",
    "addr:housenumber":"38-42",
    "addr:postcode":"bs34 5lb",
    "addr:street":"Bradley Road",
    "iso:country":"GB",
    "sg:address":"Patchway Health & Fitness Centre, 38-42 Bradley Road",
    "sg:city":"Bristol",
    "sg:classifiers":[
        {
            "category":"Health Services",
            "subcategory":"Doctor",
            "type":"Services"
        }
    ],
    "sg:phone":"+44 117 969 2040",
    "sg:postcode":"BS34 5LB",
    "sg:province":"Gloucestershire",
    "sg:tags":[
        "practitioners"
    ],
    "wof:name":"Dr Rahman's Surgery",
    "wof:placetype":"venue"
},
  "geometry": {"coordinates":[-2.58083,51.536308],"type":"Point"}
}