{
  "type": "Feature",
  "properties": {
    "iso:country":"GB",
    "sg:address":"Temple Farm, Temple Hill, Wolvey",
    "sg:city":"Hinckley",
    "sg:classifiers":[
        {
            "category":"Retail",
            "subcategory":"Auto Repair",
            "type":"Services"
        }
    ],
    "sg:postcode":"LE10 3HY",
    "sg:province":"Leicestershire",
    "sg:tags":[
        "body",
        "car"
    ],
    "wof:name":"Wheeler & Davis",
    "wof:placetype":"venue"
},
  "geometry": {"coordinates":[-1.369322,52.485638],"type":"Point"}
}