{
  "type": "Feature",
  "properties": {
    "addr:full":"99a Hamilton Road Felixstowe Suffolk IP11 7BL",
    "addr:housenumber":"99a",
    "addr:postcode":"ip11 7bl",
    "addr:street":"Hamilton Road",
    "iso:country":"GB",
    "sg:address":"99a Hamilton Road",
    "sg:city":"Felixstowe",
    "sg:classifiers":[
        {
            "category":"Food & Beverages",
            "subcategory":"Fruits & Vegetables",
            "type":"Retail Goods"
        }
    ],
    "sg:phone":"+44 1394 285863",
    "sg:postcode":"IP11 7BL",
    "sg:province":"Suffolk",
    "sg:tags":[
        "greengrocer"
    ],
    "wof:name":"Four Seasons",
    "wof:placetype":"venue"
},
  "geometry": {"coordinates":[1.351645,51.963917],"type":"Point"}
}