{
  "type": "Feature",
  "properties": {
    "iso:country":"GB",
    "sg:address":"8 Bersham Lane, Badgers Dene",
    "sg:city":"Grays",
    "sg:classifiers":[
        {
            "category":"Home & Garden",
            "subcategory":"Home Furnishings",
            "type":"Retail Goods"
        }
    ],
    "sg:phone":"+44 1375 399993",
    "sg:postcode":"RM17 5EN",
    "sg:province":"Essex",
    "sg:tags":[
        "homefurnishings"
    ],
    "wof:name":"Ajs Polishing",
    "wof:placetype":"venue"
},
  "geometry": {"coordinates":[0.317015,51.483521],"type":"Point"}
}