{
  "type": "Feature",
  "properties": {
    "addr:full":"57 London Rd Brandon Norfolk IP27 0EL",
    "addr:housenumber":"57",
    "addr:postcode":"ip27 0el",
    "addr:street":"London Rd",
    "iso:country":"GB",
    "sg:address":"57 London Rd",
    "sg:city":"Brandon",
    "sg:classifiers":[
        {
            "category":"Building & Trades",
            "subcategory":"Plumbing",
            "type":"Services"
        }
    ],
    "sg:phone":"+44 1842 815574",
    "sg:postcode":"IP27 0EL",
    "sg:province":"Norfolk",
    "sg:tags":[
        "heating"
    ],
    "wof:name":"Simon Wells Plumbing Heating & Drainage",
    "wof:placetype":"venue"
},
  "geometry": {"coordinates":[0.6209489703,52.4464492798],"type":"Point"}
}