{
  "type": "Feature",
  "properties": {
    "addr:full":"6th Floor, 20 St Dunstans Hill London Greater London EC3R 8HY",
    "addr:housenumber":"6th floor 20",
    "addr:postcode":"ec3r 8hy",
    "addr:street":"St Dunstans Hill",
    "iso:country":"GB",
    "sg:address":"6th Floor, 20 St Dunstans Hill",
    "sg:city":"London",
    "sg:classifiers":[
        {
            "category":"Professional",
            "subcategory":"Detective & Security Services",
            "type":"Services"
        }
    ],
    "sg:phone":"+44 20 7621 9298",
    "sg:postcode":"EC3R 8HY",
    "sg:province":"Greater London",
    "wof:name":"Kim Eng Securities (London) Ltd.",
    "wof:placetype":"venue"
},
  "geometry": {"coordinates":[-0.0823339969,51.5092964172],"type":"Point"}
}