{
  "type": "Feature",
  "properties": {
    "addr:full":"14 Station Road Blackpool Lancashire FY4 1BE",
    "addr:housenumber":"14",
    "addr:postcode":"fy4 1be",
    "addr:street":"Station Road",
    "iso:country":"GB",
    "sg:address":"14 Station Road",
    "sg:city":"Blackpool",
    "sg:classifiers":[
        {
            "category":"Travel",
            "subcategory":"Hotels & Motels",
            "type":"Entertainment"
        }
    ],
    "sg:postcode":"FY4 1BE",
    "sg:province":"Lancashire",
    "wof:name":"Westfield Hotel",
    "wof:placetype":"venue"
},
  "geometry": {"coordinates":[-3.054825,53.795616],"type":"Point"}
}