{
  "type": "Feature",
  "properties": {
    "addr:full":"Elms Farm Bures Essex CO8 5BA",
    "addr:postcode":"co8 5ba",
    "iso:country":"GB",
    "sg:address":"Elms Farm",
    "sg:city":"Bures",
    "sg:classifiers":[
        {
            "category":"Wholesale",
            "subcategory":"Machinery & Supplies",
            "type":"Manufacturing & Wholesale Goods"
        }
    ],
    "sg:phone":"+44 1787 227730",
    "sg:postcode":"CO8 5BA",
    "sg:province":"Essex",
    "wof:name":"Elms Farm Workshop",
    "wof:placetype":"venue"
},
  "geometry": {"coordinates":[0.7706599832,51.9718017578],"type":"Point"}
}