{
  "type": "Feature",
  "properties": {
    "addr:full":"36 Greensfield Business Cnt, Mulgrave Terr Gateshead Tyne and Wear NE8 1PQ",
    "addr:housenumber":"36",
    "addr:postcode":"ne8 1pq",
    "addr:street":"Greensfield Business Cnt;Terr",
    "iso:country":"GB",
    "sg:address":"36 Greensfield Business Cnt, Mulgrave Terr",
    "sg:city":"Gateshead",
    "sg:classifiers":[
        {
            "category":"Home & Garden",
            "subcategory":"Kitchen Supply",
            "type":"Retail Goods"
        }
    ],
    "sg:postcode":"NE8 1PQ",
    "sg:province":"Tyne and Wear",
    "sg:tags":[
        "measuring",
        "scale"
    ],
    "wof:name":"S M K Balance Services",
    "wof:placetype":"venue"
},
  "geometry": {"coordinates":[-1.60703,54.962971],"type":"Point"}
}