{
  "type": "Feature",
  "properties": {
    "addr:full":"83 Uxbridge Road London Greater London W7 3ST",
    "addr:housenumber":"83",
    "addr:postcode":"w7 3st",
    "addr:street":"Uxbridge Road",
    "iso:country":"GB",
    "sg:address":"83 Uxbridge Road",
    "sg:city":"London",
    "sg:classifiers":[
        {
            "category":"Shopping",
            "subcategory":"Gifts & Souvenirs",
            "type":"Retail Goods"
        }
    ],
    "sg:postcode":"W7 3ST",
    "sg:province":"Greater London",
    "sg:tags":[
        "watch",
        "clock"
    ],
    "wof:name":"Time Kraft International",
    "wof:placetype":"venue"
},
  "geometry": {"coordinates":[-0.334963,51.508907],"type":"Point"}
}