{
  "type": "Feature",
  "properties": {
    "iso:country":"GB",
    "sg:address":"12 St Marys Glebe, Edlesborough",
    "sg:city":"Dunstable",
    "sg:classifiers":[
        {
            "category":"Professional",
            "subcategory":"Engineering",
            "type":"Services"
        }
    ],
    "sg:postcode":"LU6 2RB",
    "sg:province":"Bedfordshire",
    "wof:name":"M D Pearson",
    "wof:placetype":"venue"
},
  "geometry": {"coordinates":[-0.5907239914,51.8614883423],"type":"Point"}
}