{
  "type": "Feature",
  "properties": {
    "iso:country":"GB",
    "sg:address":"7-8 Imperial Studios, Imperial Rd",
    "sg:city":"Fulham",
    "sg:classifiers":[
        {
            "category":"Organizations",
            "subcategory":"Membership Organization",
            "type":"Services"
        }
    ],
    "sg:phone":"+44 20 7736 4555",
    "sg:postcode":"SW6 2AG",
    "sg:province":"Greater London",
    "sg:tags":[
        "club"
    ],
    "wof:name":"Sports Bar Development The Co",
    "wof:placetype":"venue"
},
  "geometry": {"coordinates":[-0.190114,51.476425],"type":"Point"}
}