{
  "type": "Feature",
  "properties": {
    "addr:full":"The Butts Alston Cumbria CA9 3JU",
    "addr:postcode":"ca9 3ju",
    "addr:street":"The Butts",
    "iso:country":"GB",
    "sg:address":"The Butts",
    "sg:city":"Alston",
    "sg:classifiers":[
        {
            "category":"Manufacturing",
            "subcategory":"Wood Products",
            "type":"Manufacturing & Wholesale Goods"
        }
    ],
    "sg:phone":"+44 1434 382934",
    "sg:postcode":"CA9 3JU",
    "sg:province":"Cumbria",
    "sg:tags":[
        "maker",
        "cabinet"
    ],
    "wof:name":"Pinehaven",
    "wof:placetype":"venue"
},
  "geometry": {"coordinates":[-2.438751936,54.8123817444],"type":"Point"}
}