{
  "type": "Feature",
  "properties": {
    "addr:full":"Station Road, Rickmansworth Watford Hertfordshire WD18 7FR",
    "addr:postcode":"wd18 7fr",
    "addr:street":"Station Road",
    "iso:country":"GB",
    "sg:address":"Station Road, Rickmansworth",
    "sg:city":"Watford",
    "sg:classifiers":[
        {
            "category":"Building & Trades",
            "subcategory":"Equipment Rental",
            "type":"Services"
        },
        {
            "category":"Building & Trades",
            "subcategory":"Construction",
            "type":"Services"
        }
    ],
    "sg:phone":"+44 1923 239928",
    "sg:postcode":"WD18 7FR",
    "sg:province":"Hertfordshire",
    "sg:tags":[
        "builder",
        "plant",
        "machinery"
    ],
    "wof:name":"Sixemor Roofing & Construction Ltd.",
    "wof:placetype":"venue"
},
  "geometry": {"coordinates":[-0.406211,51.657387],"type":"Point"}
}