{
  "type": "Feature",
  "properties": {
    "addr:full":"British Rail Goods Yard, Wood Street London Greater London E17 3NA",
    "addr:postcode":"e17 3na",
    "addr:street":"Yard Wood Street",
    "iso:country":"GB",
    "sg:address":"British Rail Goods Yard, Wood Street",
    "sg:city":"London",
    "sg:classifiers":[
        {
            "category":"Utilities",
            "subcategory":"Refuse",
            "type":"Services"
        }
    ],
    "sg:postcode":"E17 3NA",
    "sg:province":"Greater London",
    "sg:tags":[
        "skip",
        "hire"
    ],
    "wof:name":"M & K Skip Hire",
    "wof:placetype":"venue"
},
  "geometry": {"coordinates":[-0.00108,51.584381],"type":"Point"}
}