{
  "type": "Feature",
  "properties": {
    "addr:full":"80 London Road East Grinstead East Sussex RH19 1EP",
    "addr:housenumber":"80",
    "addr:postcode":"rh19 1ep",
    "addr:street":"London Road",
    "iso:country":"GB",
    "sg:address":"80 London Road",
    "sg:city":"East Grinstead",
    "sg:classifiers":[
        {
            "category":"Personal",
            "subcategory":"Beauty Salon",
            "type":"Services"
        },
        {
            "category":"Personal",
            "subcategory":"Barber",
            "type":"Services"
        }
    ],
    "sg:phone":"+44 1342 300082",
    "sg:postcode":"RH19 1EP",
    "sg:province":"East Sussex",
    "sg:tags":[
        "unisex",
        "hairdresser"
    ],
    "wof:name":"Success Hair Co",
    "wof:placetype":"venue"
},
  "geometry": {"coordinates":[-0.009903,51.126072],"type":"Point"}
}