{
  "type": "Feature",
  "properties": {
    "addr:full":"96 High Street, Acton London Greater London W3 6QX",
    "addr:housenumber":"96",
    "addr:postcode":"w3 6qx",
    "addr:street":"High Street",
    "iso:country":"GB",
    "sg:address":"96 High Street, Acton",
    "sg:city":"London",
    "sg:classifiers":[
        {
            "category":"Shopping",
            "subcategory":"News",
            "type":"Retail Goods"
        }
    ],
    "sg:phone":"+44 20 8993 8742",
    "sg:postcode":"W3 6QX",
    "sg:province":"Greater London",
    "sg:tags":[
        "newsagent"
    ],
    "wof:name":"Konti News",
    "wof:placetype":"venue"
},
  "geometry": {"coordinates":[-0.26859501,51.5068626404],"type":"Point"}
}