{
  "type": "Feature",
  "properties": {
    "addr:full":"11 Old Square London Greater London WC2A 3TS",
    "addr:housenumber":"11",
    "addr:postcode":"wc2a 3ts",
    "addr:street":"Old Square",
    "iso:country":"GB",
    "sg:address":"11 Old Square",
    "sg:city":"London",
    "sg:classifiers":[
        {
            "category":"Professional",
            "subcategory":"Lawyer & Legal Services",
            "type":"Services"
        }
    ],
    "sg:phone":"+44 20 7430 0341",
    "sg:postcode":"WC2A 3TS",
    "sg:province":"Greater London",
    "sg:tags":[
        "barrister"
    ],
    "wof:name":"Elizabeth Ovey",
    "wof:placetype":"venue"
},
  "geometry": {"coordinates":[-0.1132,51.51696],"type":"Point"}
}