{
  "type": "Feature",
  "properties": {
    "iso:country":"GB",
    "sg:address":"10 Cedar Crescent, Thornton",
    "sg:city":"Kirkcaldy",
    "sg:classifiers":[
        {
            "category":"Building & Trades",
            "subcategory":"Construction",
            "type":"Services"
        }
    ],
    "sg:phone":"+44 1592 774260",
    "sg:postcode":"KY1 4BE",
    "sg:province":"Fife",
    "sg:tags":[
        "builder"
    ],
    "wof:name":"A P Ritchie",
    "wof:placetype":"venue"
},
  "geometry": {"coordinates":[-3.1500940323,56.164100647],"type":"Point"}
}