{
  "type": "Feature",
  "properties": {
    "addr:full":"36 Brook Hill Rotherham South Yorkshire S61 2PY",
    "addr:housenumber":"36",
    "addr:postcode":"s61 2py",
    "addr:street":"Brook",
    "iso:country":"GB",
    "sg:address":"36 Brook Hill",
    "sg:city":"Rotherham",
    "sg:classifiers":[
        {
            "category":"Food & Beverages",
            "subcategory":"Meat & Fish",
            "type":"Retail Goods"
        }
    ],
    "sg:postcode":"S61 2PY",
    "sg:province":"South Yorkshire",
    "sg:tags":[
        "butcher"
    ],
    "wof:name":"E A Swift & Sons",
    "wof:placetype":"venue"
},
  "geometry": {"coordinates":[-1.436153,53.459572],"type":"Point"}
}