{
  "type": "Feature",
  "properties": {
    "addr:full":"29 Hospital Fields Road, Fulford Industrial Estate York North Yorkshire YO10 4FZ",
    "addr:housenumber":"29;estate",
    "addr:postcode":"yo10 4fz",
    "addr:street":"Hospital Fields Road;Industrial;York",
    "iso:country":"GB",
    "sg:address":"29 Hospital Fields Road, Fulford Industrial Estate",
    "sg:city":"York",
    "sg:classifiers":[
        {
            "category":"Manufacturing",
            "subcategory":"Metals",
            "type":"Manufacturing & Wholesale Goods"
        }
    ],
    "sg:phone":"+44 1904 636021",
    "sg:postcode":"YO10 4FZ",
    "sg:province":"North Yorkshire",
    "sg:tags":[
        "steel",
        "fabricator",
        "erectors"
    ],
    "wof:name":"M Brittain (York) Ltd.",
    "wof:placetype":"venue"
},
  "geometry": {"coordinates":[-1.0780889988,53.9450759888],"type":"Point"}
}