{
  "type": "Feature",
  "properties": {
    "addr:full":"135 Chineway Gardens Ottery St Mary Devon EX11 1JL",
    "addr:housenumber":"135",
    "addr:postcode":"ex11 1jl",
    "addr:street":"Chineway Gardens",
    "iso:country":"GB",
    "sg:address":"135 Chineway Gardens",
    "sg:city":"Ottery St Mary",
    "sg:classifiers":[
        {
            "category":"Professional",
            "subcategory":"Art Services",
            "type":"Services"
        },
        {
            "category":"Building & Trades",
            "subcategory":"Construction",
            "type":"Services"
        }
    ],
    "sg:phone":"+44 1404 813924",
    "sg:postcode":"EX11 1JL",
    "sg:province":"Devon",
    "sg:tags":[
        "decorator",
        "painter"
    ],
    "wof:name":"PAUL STEPHEN MARTIN",
    "wof:placetype":"venue"
},
  "geometry": {"coordinates":[-3.267132,50.750286],"type":"Point"}
}