{
  "type": "Feature",
  "properties": {
    "addr:full":"Cameron Square Fort William Highland PH33 6AJ",
    "addr:postcode":"ph33 6aj",
    "addr:street":"Cameron Square",
    "iso:country":"GB",
    "sg:address":"Cameron Square",
    "sg:city":"Fort William",
    "sg:classifiers":[
        {
            "category":"Cinema",
            "subcategory":"Movie Theater",
            "type":"Entertainment"
        }
    ],
    "sg:phone":"+44 1397 705095",
    "sg:postcode":"PH33 6AJ",
    "sg:province":"Highland",
    "wof:name":"Studio Cinema",
    "wof:placetype":"venue"
},
  "geometry": {"coordinates":[-5.110896,56.817833],"type":"Point"}
}