{
  "type": "Feature",
  "properties": {
    "addr:full":"Ivory Gate House 41 Dover Street London Greater London W1S 4NS",
    "addr:housenumber":"41",
    "addr:postcode":"w1s 4ns",
    "addr:street":"Ivory Gate;Dover Street",
    "iso:country":"GB",
    "sg:address":"Ivory Gate House 41 Dover Street",
    "sg:city":"London",
    "sg:classifiers":[
        {
            "category":"Banks & Credit Unions",
            "subcategory":"Financial Services",
            "type":"Services"
        }
    ],
    "sg:phone":"+44 20 7355 2093",
    "sg:postcode":"W1S 4NS",
    "sg:province":"Greater London",
    "sg:tags":[
        "consultant"
    ],
    "wof:name":"Hufkens Asset Management & Co. Ltd.",
    "wof:placetype":"venue"
},
  "geometry": {"coordinates":[-0.1422020048,51.5083198547],"type":"Point"}
}