{
  "type": "Feature",
  "properties": {
    "addr:full":"Fewston Post Office, Fewston Harrogate North Yorkshire HG3 1SU",
    "addr:postcode":"hg3 1su",
    "addr:street":"Fewston",
    "iso:country":"GB",
    "sg:address":"Fewston Post Office, Fewston",
    "sg:city":"Harrogate",
    "sg:classifiers":[
        {
            "category":"Bus Charters",
            "type":"Transportation"
        }
    ],
    "sg:phone":"+44 1943 880228",
    "sg:postcode":"HG3 1SU",
    "sg:province":"North Yorkshire",
    "sg:tags":[
        "hire",
        "coach"
    ],
    "wof:name":"Beecroft Coaches",
    "wof:placetype":"venue"
},
  "geometry": {"coordinates":[-1.7054309845,53.983215332],"type":"Point"}
}