{
  "type": "Feature",
  "properties": {
    "addr:full":"3 Bethany Chapel, Tregynon Newtown Powys SY16 3EP",
    "addr:housenumber":"3",
    "addr:postcode":"sy16 3ep",
    "addr:street":"Bethany Chapel",
    "iso:country":"GB",
    "sg:address":"3 Bethany Chapel, Tregynon",
    "sg:city":"Newtown",
    "sg:classifiers":[
        {
            "category":"Professional",
            "subcategory":"Management & Consulting",
            "type":"Services"
        }
    ],
    "sg:phone":"+44 1686 650654",
    "sg:postcode":"SY16 3EP",
    "sg:province":"Powys",
    "sg:tags":[
        "environmental",
        "consultant"
    ],
    "wof:name":"Bethany Training Services",
    "wof:placetype":"venue"
},
  "geometry": {"coordinates":[-3.3329489231,52.5782661438],"type":"Point"}
}