{
  "type": "Feature",
  "properties": {
    "iso:country":"GB",
    "sg:address":"Station Lane",
    "sg:city":"Chester Le Street",
    "sg:classifiers":[
        {
            "category":"Utilities",
            "subcategory":"Natural Gas",
            "type":"Services"
        }
    ],
    "sg:phone":"+44 191 411 1246",
    "sg:postcode":"DH3 1DH",
    "sg:province":"Durham",
    "sg:tags":[
        "supplier"
    ],
    "wof:name":"Messer Drinks Dispense Gas",
    "wof:placetype":"venue"
},
  "geometry": {"coordinates":[-1.578502059,54.8963279724],"type":"Point"}
}