{
  "type": "Feature",
  "properties": {
    "iso:country":"GB",
    "sg:address":"Shaw House, Two Woods Lane",
    "sg:city":"Brierley Hill",
    "sg:classifiers":[
        {
            "category":"Professional",
            "subcategory":"Art Services",
            "type":"Services"
        }
    ],
    "sg:phone":"+44 1384 76375",
    "sg:postcode":"DY5 1TA",
    "sg:province":"West Midlands",
    "sg:tags":[
        "photographer"
    ],
    "wof:name":"Jason Walters",
    "wof:placetype":"venue"
},
  "geometry": {"coordinates":[-2.109609,52.476116],"type":"Point"}
}