{
  "type": "Feature",
  "properties": {
    "addr:full":"7a Ilsham Road Torquay Devon TQ1 2JG",
    "addr:housenumber":"7a",
    "addr:postcode":"tq1 2jg",
    "addr:street":"Ilsham Road",
    "iso:country":"GB",
    "sg:address":"7a Ilsham Road",
    "sg:city":"Torquay",
    "sg:classifiers":[
        {
            "category":"Professional",
            "subcategory":"Accounting & Tax Preparation",
            "type":"Services"
        }
    ],
    "sg:phone":"+44 1803 297591",
    "sg:postcode":"TQ1 2JG",
    "sg:province":"Devon",
    "sg:tags":[
        "accountant"
    ],
    "wof:name":"Durtnall & Rowden",
    "wof:placetype":"venue"
},
  "geometry": {"coordinates":[-3.5070109367,50.4666900635],"type":"Point"}
}