{
  "type": "Feature",
  "properties": {
    "addr:full":"340 London Road Westcliff-on-sea Essex SS0 7JJ",
    "addr:housenumber":"340",
    "addr:postcode":"ss0 7jj",
    "addr:street":"London Road",
    "iso:country":"GB",
    "sg:address":"340 London Road",
    "sg:city":"Westcliff-on-sea",
    "sg:classifiers":[
        {
            "category":"Health Services",
            "subcategory":"Dentist",
            "type":"Services"
        }
    ],
    "sg:phone":"+44 1702 347633",
    "sg:postcode":"SS0 7JJ",
    "sg:province":"Essex",
    "wof:name":"N G Fraser & Associates",
    "wof:placetype":"venue"
},
  "geometry": {"coordinates":[0.696714,51.541519],"type":"Point"}
}