{
  "type": "Feature",
  "properties": {
    "iso:country":"GB",
    "sg:address":"135 Sandyford Rd",
    "sg:city":"Newcastle-upon-tyne",
    "sg:classifiers":[
        {
            "category":"Professional",
            "subcategory":"Advertising",
            "type":"Services"
        }
    ],
    "sg:postcode":"NE2 1QR",
    "sg:province":"Tyne and Wear",
    "sg:tags":[
        "agency"
    ],
    "wof:name":"Caradoc-Davies,Richard,",
    "wof:placetype":"venue"
},
  "geometry": {"coordinates":[-1.603183,54.981255],"type":"Point"}
}