{
  "type": "Feature",
  "properties": {
    "addr:full":"Brighton St, Seacombe Wallasey Wallasey Merseyside CH44 8DT",
    "addr:postcode":"ch44 8dt",
    "addr:street":"Brighton St",
    "iso:country":"GB",
    "sg:address":"Brighton St, Seacombe Wallasey",
    "sg:city":"Wallasey",
    "sg:classifiers":[
        {
            "category":"Bars & Pubs",
            "type":"Food & Drink"
        }
    ],
    "sg:phone":"+44 151 639 3680",
    "sg:postcode":"CH44 8DT",
    "sg:province":"Merseyside",
    "sg:tags":[
        "pubs",
        "inn"
    ],
    "wof:name":"Brighton Hotel",
    "wof:placetype":"venue"
},
  "geometry": {"coordinates":[-3.0262289047,53.4179763794],"type":"Point"}
}