{
  "type": "Feature",
  "properties": {
    "addr:full":"Manaton Close, Matford Business Park Exeter Devon EX2 8PF",
    "addr:postcode":"ex2 8pf",
    "addr:street":"Manaton Close Matford Business Park",
    "iso:country":"GB",
    "sg:address":"Manaton Close, Matford Business Park",
    "sg:city":"Exeter",
    "sg:classifiers":[
        {
            "category":"Autos & Motor Vehicles",
            "subcategory":"Automobile Sales",
            "type":"Retail Goods"
        }
    ],
    "sg:phone":"+44 1392 255300",
    "sg:postcode":"EX2 8PF",
    "sg:province":"Devon",
    "sg:tags":[
        "car"
    ],
    "wof:name":"Matford Landrover",
    "wof:placetype":"venue"
},
  "geometry": {"coordinates":[-3.524668932,50.6979598999],"type":"Point"}
}