{
  "type": "Feature",
  "properties": {
    "addr:full":"St Johns House St Johns Square Wolverhampton West Midlands WV2 4BH",
    "addr:postcode":"wv2 4bh",
    "addr:street":"St Johns Square",
    "iso:country":"GB",
    "sg:address":"St Johns House St Johns Square",
    "sg:city":"Wolverhampton",
    "sg:classifiers":[
        {
            "category":"Manufacturing",
            "subcategory":"Tools & Machinery",
            "type":"Manufacturing & Wholesale Goods"
        }
    ],
    "sg:phone":"+44 1202 292333",
    "sg:postcode":"WV2 4BH",
    "sg:province":"West Midlands",
    "sg:tags":[
        "society",
        "friendly"
    ],
    "wof:name":"Liverpool Victoria Friendly Society",
    "wof:placetype":"venue"
},
  "geometry": {"coordinates":[-2.128318,52.580898],"type":"Point"}
}