{
  "type": "Feature",
  "properties": {
    "addr:full":"Wheatsheaf Way Exeter Devon EX2 8RQ",
    "addr:postcode":"ex2 8rq",
    "addr:street":"Wheatsheaf Way",
    "iso:country":"GB",
    "sg:address":"Wheatsheaf Way",
    "sg:city":"Exeter",
    "sg:classifiers":[
        {
            "category":"Education",
            "subcategory":"School",
            "type":"Public Place"
        }
    ],
    "sg:phone":"+44 1392 254291",
    "sg:postcode":"EX2 8RQ",
    "sg:province":"Devon",
    "sg:tags":[
        "local",
        "authority"
    ],
    "wof:name":"Alphington Combined School",
    "wof:placetype":"venue"
},
  "geometry": {"coordinates":[-3.539364,50.70089],"type":"Point"}
}