{
  "type": "Feature",
  "properties": {
    "addr:full":"Po Box 1832 Buckingham Buckinghamshire MK18 1NZ",
    "addr:housenumber":"po",
    "addr:postcode":"mk18 1nz",
    "addr:street":"Box 1832",
    "iso:country":"GB",
    "sg:address":"Po Box 1832",
    "sg:city":"Buckingham",
    "sg:classifiers":[
        {
            "category":"Professional",
            "subcategory":"Lawyer & Legal Services",
            "type":"Services"
        }
    ],
    "sg:phone":"+44 1296 711500",
    "sg:postcode":"MK18 1NZ",
    "sg:province":"Buckinghamshire",
    "wof:name":"Independent Advocates",
    "wof:placetype":"venue"
},
  "geometry": {"coordinates":[-0.984599,52.001789],"type":"Point"}
}