{
  "type": "Feature",
  "properties": {
    "iso:country":"GB",
    "sg:address":"East Waterside, Upton-upon-severn",
    "sg:city":"Worcester",
    "sg:classifiers":[
        {
            "category":"Autos & Motor Vehicles",
            "subcategory":"Boat Sales",
            "type":"Retail Goods"
        }
    ],
    "sg:phone":"+44 1684 594540",
    "sg:postcode":"WR8 0PB",
    "sg:province":"Gloucestershire",
    "sg:tags":[
        "repair",
        "builder"
    ],
    "wof:name":"Marine Performance Parts & Service",
    "wof:placetype":"venue"
},
  "geometry": {"coordinates":[-2.218359,52.0634],"type":"Point"}
}