{
  "type": "Feature",
  "properties": {
    "addr:full":"Lucton House, 8 Long Wood Birmingham West Midlands B30 1HT",
    "addr:housenumber":"8",
    "addr:postcode":"b30 1ht",
    "addr:street":"Long Wood",
    "iso:country":"GB",
    "sg:address":"Lucton House, 8 Long Wood",
    "sg:city":"Birmingham",
    "sg:classifiers":[
        {
            "category":"Organizations",
            "subcategory":"Community Association",
            "type":"Services"
        }
    ],
    "sg:phone":"+44 121 451 3451",
    "sg:postcode":"B30 1HT",
    "sg:province":"West Midlands",
    "sg:tags":[
        "society",
        "housing"
    ],
    "wof:name":"Servite Houses",
    "wof:placetype":"venue"
},
  "geometry": {"coordinates":[-1.9390779734,52.4216995239],"type":"Point"}
}