{
  "type": "Feature",
  "properties": {
    "addr:full":"West Huntingtower Perth Perth and Kinross PH1 3NR",
    "addr:postcode":"ph1 3nr",
    "addr:street":"West Huntingtower",
    "iso:country":"GB",
    "sg:address":"West Huntingtower",
    "sg:city":"Perth",
    "sg:classifiers":[
        {
            "category":"Retail",
            "subcategory":"Veterinary Services",
            "type":"Services"
        }
    ],
    "sg:phone":"+44 1738 583083",
    "sg:postcode":"PH1 3NR",
    "sg:province":"Perth and Kinross",
    "sg:tags":[
        "surgeon",
        "activity"
    ],
    "wof:name":"Tower Veterinary Hospital",
    "wof:placetype":"venue"
},
  "geometry": {"coordinates":[-3.470555,56.450073],"type":"Point"}
}