{
  "type": "Feature",
  "properties": {
    "addr:full":"Southlands Care Home, 98 North Parade, Matlock Bath Matlock Derbyshire DE4 3NS",
    "addr:housenumber":"98",
    "addr:postcode":"de4 3ns",
    "addr:street":"North Parade",
    "iso:country":"GB",
    "sg:address":"Southlands Care Home, 98 North Parade, Matlock Bath",
    "sg:city":"Matlock",
    "sg:classifiers":[
        {
            "category":"Health Services",
            "subcategory":"Nursing And Care Facility",
            "type":"Services"
        },
        {
            "category":"Social Services",
            "subcategory":"Retirement Home",
            "type":"Services"
        }
    ],
    "sg:phone":"+44 1629 583129",
    "sg:postcode":"DE4 3NS",
    "sg:province":"Derbyshire",
    "sg:tags":[
        "residential"
    ],
    "wof:name":"Southlands Care Home",
    "wof:placetype":"venue"
},
  "geometry": {"coordinates":[-1.562195,53.121567],"type":"Point"}
}