{
  "type": "Feature",
  "properties": {
    "addr:full":"57 Bounces Road London Greater London N9 8JE",
    "addr:housenumber":"57",
    "addr:postcode":"n9 8je",
    "addr:street":"Bounces Road",
    "iso:country":"GB",
    "sg:address":"57 Bounces Road",
    "sg:city":"London",
    "sg:classifiers":[
        {
            "category":"Fast Food",
            "type":"Food & Drink"
        }
    ],
    "sg:phone":"+44 20 8807 3663",
    "sg:postcode":"N9 8JE",
    "sg:province":"Greater London",
    "sg:tags":[
        "away",
        "take"
    ],
    "wof:name":"Happy Garden",
    "wof:placetype":"venue"
},
  "geometry": {"coordinates":[-0.0521869995,51.6284599304],"type":"Point"}
}