{
  "type": "Feature",
  "properties": {
    "iso:country":"GB",
    "sg:address":"179 Smorrall Lane",
    "sg:city":"Bedworth",
    "sg:classifiers":[
        {
            "category":"Arena",
            "subcategory":"Sports Club",
            "type":"Entertainment"
        }
    ],
    "sg:phone":"+44 24 7636 0442",
    "sg:postcode":"CV12 0JP",
    "sg:province":"Warwickshire",
    "wof:name":"Newdigate Colliery & District Sports & Social Club",
    "wof:placetype":"venue"
},
  "geometry": {"coordinates":[-1.497949,52.473991],"type":"Point"}
}