{
  "type": "Feature",
  "properties": {
    "iso:country":"GB",
    "sg:address":"55 High Street",
    "sg:city":"Maldon",
    "sg:classifiers":[
        {
            "category":"Shopping",
            "subcategory":"Shoes",
            "type":"Retail Goods"
        }
    ],
    "sg:phone":"+44 1621 858192",
    "sg:postcode":"CM9 7PF",
    "sg:province":"Essex",
    "wof:name":"Essex Shoe Repairs Ltd.",
    "wof:placetype":"venue"
},
  "geometry": {"coordinates":[0.6778659821,51.731338501],"type":"Point"}
}