{
  "type": "Feature",
  "properties": {
    "addr:full":"24 Boxley Rd Chatham Kent ME5 9LF",
    "addr:housenumber":"24",
    "addr:postcode":"me5 9lf",
    "addr:street":"Boxley Rd",
    "iso:country":"GB",
    "sg:address":"24 Boxley Rd",
    "sg:city":"Chatham",
    "sg:classifiers":[
        {
            "category":"Home & Garden",
            "subcategory":"Building Materials",
            "type":"Retail Goods"
        }
    ],
    "sg:phone":"+44 1634 862155",
    "sg:postcode":"ME5 9LF",
    "sg:province":"Kent",
    "sg:tags":[
        "ironwork",
        "diy",
        "wrought"
    ],
    "wof:name":"D F G Owen",
    "wof:placetype":"venue"
},
  "geometry": {"coordinates":[0.528501,51.337856],"type":"Point"}
}