{
  "type": "Feature",
  "properties": {
    "iso:country":"GB",
    "sg:address":"5a Trinity St",
    "sg:city":"St Leonards On Sea",
    "sg:classifiers":[
        {
            "category":"Professional",
            "subcategory":"Lawyer & Legal Services",
            "type":"Services"
        }
    ],
    "sg:phone":"+44 1424 441548",
    "sg:postcode":"TN37 6LB",
    "sg:province":"East Sussex",
    "sg:tags":[
        "advice",
        "counselling"
    ],
    "wof:name":"Five A Day Programme",
    "wof:placetype":"venue"
},
  "geometry": {"coordinates":[0.55997,50.856499],"type":"Point"}
}