{
  "type": "Feature",
  "properties": {
    "addr:full":"Bromley Garage, Poplar Lane, Winnersh Wokingham Berkshire RG41 5JR",
    "addr:postcode":"rg41 5jr",
    "addr:street":"Poplar Lane",
    "iso:country":"GB",
    "sg:address":"Bromley Garage, Poplar Lane, Winnersh",
    "sg:city":"Wokingham",
    "sg:classifiers":[
        {
            "category":"Retail",
            "subcategory":"Auto Repair",
            "type":"Services"
        }
    ],
    "sg:phone":"+44 118 978 7525",
    "sg:postcode":"RG41 5JR",
    "sg:province":"Berkshire",
    "sg:tags":[
        "modification",
        "garage",
        "related"
    ],
    "wof:name":"BROMLEY GARAGE SERVICES LTD",
    "wof:placetype":"venue"
},
  "geometry": {"coordinates":[-0.8806459904,51.4302406311],"type":"Point"}
}