{
  "type": "Feature",
  "properties": {
    "iso:country":"GB",
    "sg:address":"109 Doncaster Road, Goldthorpe",
    "sg:city":"Rotherham",
    "sg:classifiers":[
        {
            "category":"Building & Trades",
            "subcategory":"Construction",
            "type":"Services"
        }
    ],
    "sg:phone":"+44 1709 881762",
    "sg:postcode":"S63 9HY",
    "sg:province":"South Yorkshire",
    "sg:tags":[
        "window",
        "replacement"
    ],
    "wof:name":"Climaseal",
    "wof:placetype":"venue"
},
  "geometry": {"coordinates":[-1.299249,53.535],"type":"Point"}
}