{
  "type": "Feature",
  "properties": {
    "iso:country":"GB",
    "sg:address":"17 Javelin Rd",
    "sg:city":"Norwich",
    "sg:classifiers":[
        {
            "category":"Food & Beverages",
            "subcategory":"Bakery",
            "type":"Retail Goods"
        }
    ],
    "sg:postcode":"NR6 6HP",
    "sg:province":"Norfolk",
    "sg:tags":[
        "confectionery"
    ],
    "wof:name":"Jolly Baker Norwich (The)",
    "wof:placetype":"venue"
},
  "geometry": {"coordinates":[1.2881599665,52.6706542969],"type":"Point"}
}