{
  "type": "Feature",
  "properties": {
    "addr:full":"69 King Street London Greater London W6 9HW",
    "addr:housenumber":"69",
    "addr:postcode":"w6 9hw",
    "addr:street":"King Street",
    "iso:country":"GB",
    "sg:address":"69 King Street",
    "sg:city":"London",
    "sg:classifiers":[
        {
            "category":"Professional",
            "subcategory":"Employment Agencies",
            "type":"Services"
        }
    ],
    "sg:phone":"+44 20 8748 9733",
    "sg:postcode":"W6 9HW",
    "sg:province":"Greater London",
    "sg:tags":[
        "consultant",
        "recruitment"
    ],
    "sg:website":"http://www.reed.co.uk",
    "wof:name":"Reed Employment Ltd",
    "wof:placetype":"venue"
},
  "geometry": {"coordinates":[-0.2278359979,51.4925003052],"type":"Point"}
}