{
  "type": "Feature",
  "properties": {
    "addr:full":"Britannia Works, Folds Road Bolton Lancashire BL1 2SE",
    "addr:postcode":"bl1 2se",
    "addr:street":"Folds Road",
    "iso:country":"GB",
    "sg:address":"Britannia Works, Folds Road",
    "sg:city":"Bolton",
    "sg:classifiers":[
        {
            "category":"Professional",
            "subcategory":"Engineering",
            "type":"Services"
        }
    ],
    "sg:phone":"+44 1204 382121",
    "sg:postcode":"BL1 2SE",
    "sg:province":"Lancashire",
    "sg:tags":[
        "engineer"
    ],
    "wof:name":"Webster Drives Ltd",
    "wof:placetype":"venue"
},
  "geometry": {"coordinates":[-2.426594,53.578289],"type":"Point"}
}