{
  "type": "Feature",
  "properties": {
    "addr:full":"Nizels Lane, Hildenborough Tonbridge Kent TN11 8NX",
    "addr:postcode":"tn11 8nx",
    "addr:street":"Nizels Lane",
    "iso:country":"GB",
    "sg:address":"Nizels Lane, Hildenborough",
    "sg:city":"Tonbridge",
    "sg:classifiers":[
        {
            "category":"Shopping",
            "subcategory":"Baby Store",
            "type":"Retail Goods"
        }
    ],
    "sg:postcode":"TN11 8NX",
    "sg:province":"Kent",
    "sg:tags":[
        "nursery",
        "accessory"
    ],
    "wof:name":"Nippers",
    "wof:placetype":"venue"
},
  "geometry": {"coordinates":[0.221242,51.219353],"type":"Point"}
}