{
  "type": "Feature",
  "properties": {
    "addr:full":"22a Topsfield Parade, Tottenham Lane Hornsey Greater London N8 8PP",
    "addr:housenumber":"22a",
    "addr:postcode":"n8 8pp",
    "addr:street":"Topsfield Parade Tottenham Lane",
    "iso:country":"GB",
    "sg:address":"22a Topsfield Parade, Tottenham Lane",
    "sg:city":"Hornsey",
    "sg:classifiers":[
        {
            "category":"Arts & Performance",
            "subcategory":"Arts Center",
            "type":"Entertainment"
        }
    ],
    "sg:phone":"+44 20 8374 4531",
    "sg:postcode":"N8 8PP",
    "sg:province":"Greater London",
    "sg:tags":[
        "centre"
    ],
    "wof:name":"Expressive Arts",
    "wof:placetype":"venue"
},
  "geometry": {"coordinates":[-0.12289,51.58057],"type":"Point"}
}