{
  "type": "Feature",
  "properties": {
    "iso:country":"GB",
    "sg:address":"57 Macduff Street",
    "sg:city":"Glasgow",
    "sg:classifiers":[
        {
            "category":"Social Services",
            "type":"Services"
        }
    ],
    "sg:phone":"+44 141 554 7401",
    "sg:postcode":"G31 4PJ",
    "sg:province":"Glasgow City",
    "wof:name":"Cuthelton Lilybank Neighbourhood Initiative",
    "wof:placetype":"venue"
},
  "geometry": {"coordinates":[-4.1951379776,55.8473625183],"type":"Point"}
}