{
  "type": "Feature",
  "properties": {
    "iso:country":"GB",
    "sg:address":"P O Box 308",
    "sg:city":"Orpington",
    "sg:classifiers":[
        {
            "category":"Communications",
            "subcategory":"Television Station",
            "type":"Services"
        }
    ],
    "sg:postcode":"BR5 1TB",
    "sg:province":"Kent",
    "sg:tags":[
        "equipment",
        "telephone"
    ],
    "wof:name":"Candlestick & Bakelite",
    "wof:placetype":"venue"
},
  "geometry": {"coordinates":[0.08488,51.38694],"type":"Point"}
}