{
  "type": "Feature",
  "properties": {
    "addr:full":"137 Gloucester Road North Bristol City of Bristol BS12 7PY",
    "addr:housenumber":"137",
    "addr:postcode":"bs12 7py",
    "addr:street":"Gloucester Road North",
    "iso:country":"GB",
    "sg:address":"137 Gloucester Road North",
    "sg:city":"Bristol",
    "sg:classifiers":[
        {
            "category":"Autos & Motor Vehicles",
            "subcategory":"Auto Supplies",
            "type":"Retail Goods"
        }
    ],
    "sg:phone":"+44 117 979 3777",
    "sg:postcode":"BS12 7PY",
    "sg:province":"City of Bristol",
    "sg:tags":[
        "part",
        "motorcycle",
        "accessory"
    ],
    "wof:name":"H R S Motorcycles & Accessories",
    "wof:placetype":"venue"
},
  "geometry": {"coordinates":[-2.5776190758,51.5044822693],"type":"Point"}
}