{
  "type": "Feature",
  "properties": {
    "iso:country":"GB",
    "sg:address":"Albert Road",
    "sg:city":"Retford",
    "sg:classifiers":[
        {
            "category":"Real Estate",
            "subcategory":"Real Estate Agent",
            "type":"Services"
        }
    ],
    "sg:phone":"+44 800 328 1678",
    "sg:postcode":"DN22 6JD",
    "sg:province":"Nottinghamshire",
    "wof:name":"Spencer Estates",
    "wof:placetype":"venue"
},
  "geometry": {"coordinates":[-0.940834,53.318539],"type":"Point"}
}