{
  "type": "Feature",
  "properties": {
    "addr:full":"Upper Bloomfield Rd Bath Somerset BA2 2RY",
    "addr:postcode":"ba2 2ry",
    "addr:street":"Upper Bloomfield Rd",
    "iso:country":"GB",
    "sg:address":"Upper Bloomfield Rd",
    "sg:city":"Bath",
    "sg:classifiers":[
        {
            "category":"Food & Beverages",
            "subcategory":"Supermarket",
            "type":"Retail Goods"
        }
    ],
    "sg:phone":"+44 1225 837869",
    "sg:postcode":"BA2 2RY",
    "sg:province":"Somerset",
    "wof:name":"CRS Ltd",
    "wof:placetype":"venue"
},
  "geometry": {"coordinates":[-2.3792560101,51.3597297668],"type":"Point"}
}