{
  "type": "Feature",
  "properties": {
    "addr:full":"27 St Kilda Road London Greater London W13 9DF",
    "addr:housenumber":"27",
    "addr:postcode":"w13 9df",
    "addr:street":"St Kilda Road",
    "iso:country":"GB",
    "sg:address":"27 St Kilda Road",
    "sg:city":"London",
    "sg:classifiers":[
        {
            "category":"Health Services",
            "subcategory":"Health Practitioner",
            "type":"Services"
        }
    ],
    "sg:phone":"+44 20 8579 5209",
    "sg:postcode":"W13 9DF",
    "sg:province":"Greater London",
    "sg:tags":[
        "technique",
        "alexander"
    ],
    "wof:name":"Geoffrey & Elisabeth Higginson",
    "wof:placetype":"venue"
},
  "geometry": {"coordinates":[-0.3251259923,51.5070762634],"type":"Point"}
}