{
  "type": "Feature",
  "properties": {
    "addr:full":"Unit 9 Temple Buildings, Temple Road Leicester Leicestershire LE5 4JG",
    "addr:housenumber":"unit 9 temple",
    "addr:postcode":"le5 4jg",
    "addr:street":"Buildings Temple Road",
    "iso:country":"GB",
    "sg:address":"Unit 9 Temple Buildings, Temple Road",
    "sg:city":"Leicester",
    "sg:classifiers":[
        {
            "category":"Shopping",
            "subcategory":"Clothing, Apparel, & Fashions",
            "type":"Retail Goods"
        }
    ],
    "sg:phone":"+44 116 273 4064",
    "sg:postcode":"LE5 4JG",
    "sg:province":"Leicestershire",
    "sg:tags":[
        "wear",
        "leisure"
    ],
    "wof:name":"Phoenix Leisurewear",
    "wof:placetype":"venue"
},
  "geometry": {"coordinates":[-1.0935440063,52.6331367493],"type":"Point"}
}