{
  "type": "Feature",
  "properties": {
    "addr:full":"19 Taylors Crescent Cranleigh Surrey GU6 7EL",
    "addr:housenumber":"19",
    "addr:postcode":"gu6 7el",
    "addr:street":"Taylors Crescent",
    "iso:country":"GB",
    "sg:address":"19 Taylors Crescent",
    "sg:city":"Cranleigh",
    "sg:classifiers":[
        {
            "category":"Building & Trades",
            "subcategory":"Cleaning & Sanitation",
            "type":"Services"
        }
    ],
    "sg:phone":"+44 1483 268617",
    "sg:postcode":"GU6 7EL",
    "sg:province":"Surrey",
    "sg:tags":[
        "cleaner",
        "window"
    ],
    "wof:name":"L R Cocks",
    "wof:placetype":"venue"
},
  "geometry": {"coordinates":[-0.47501,51.144634],"type":"Point"}
}