{
  "type": "Feature",
  "properties": {
    "iso:country":"GB",
    "sg:address":"16 Highland Rd",
    "sg:city":"Purley",
    "sg:classifiers":[
        {
            "category":"Building & Trades",
            "subcategory":"Cleaning & Sanitation",
            "type":"Services"
        }
    ],
    "sg:phone":"+44 20 8660 7559",
    "sg:postcode":"CR8 2HS",
    "sg:province":"Surrey",
    "sg:tags":[
        "facility"
    ],
    "wof:name":"The Facilities Consultancy",
    "wof:placetype":"venue"
},
  "geometry": {"coordinates":[-0.1151970029,51.3249282837],"type":"Point"}
}