{
  "type": "Feature",
  "properties": {
    "addr:full":"152 Station Rd, Surfleet Spalding Lincolnshire PE11 4DG",
    "addr:housenumber":"152",
    "addr:postcode":"pe11 4dg",
    "addr:street":"Station Rd",
    "iso:country":"GB",
    "sg:address":"152 Station Rd, Surfleet",
    "sg:city":"Spalding",
    "sg:classifiers":[
        {
            "category":"Shopping",
            "subcategory":"Department Store",
            "type":"Retail Goods"
        }
    ],
    "sg:phone":"+44 1775 680401",
    "sg:postcode":"PE11 4DG",
    "sg:province":"Lincolnshire",
    "wof:name":"Glenside Stores",
    "wof:placetype":"venue"
},
  "geometry": {"coordinates":[-0.123779,52.842209],"type":"Point"}
}