{
  "type": "Feature",
  "properties": {
    "iso:country":"GB",
    "sg:address":"1 Holmstall Parade, Burnt Oak Broadway",
    "sg:city":"Edgware",
    "sg:classifiers":[
        {
            "category":"Shopping",
            "subcategory":"News",
            "type":"Retail Goods"
        }
    ],
    "sg:phone":"+44 20 8205 7293",
    "sg:postcode":"HA8 5HX",
    "sg:province":"Greater London",
    "sg:tags":[
        "newsagent"
    ],
    "wof:name":"Lemington Newsagent",
    "wof:placetype":"venue"
},
  "geometry": {"coordinates":[-0.263269,51.597031],"type":"Point"}
}