{
  "type": "Feature",
  "properties": {
    "iso:country":"GB",
    "sg:address":"9 Richmond Pl",
    "sg:city":"Ilkley",
    "sg:classifiers":[
        {
            "category":"Health Services",
            "subcategory":"Health Practitioner",
            "type":"Services"
        }
    ],
    "sg:phone":"+44 1943 603170",
    "sg:postcode":"LS29 8TJ",
    "sg:province":"North Yorkshire",
    "sg:tags":[
        "hypnotherapists"
    ],
    "wof:name":"J D Morgan",
    "wof:placetype":"venue"
},
  "geometry": {"coordinates":[-1.8163249493,53.9227142334],"type":"Point"}
}