{
  "type": "Feature",
  "properties": {
    "addr:full":"Allviews, School Road, Rayne Braintree Essex CM77 6SS",
    "addr:postcode":"cm77 6ss",
    "addr:street":"School Road",
    "iso:country":"GB",
    "sg:address":"Allviews, School Road, Rayne",
    "sg:city":"Braintree",
    "sg:classifiers":[
        {
            "category":"Bus Charters",
            "type":"Transportation"
        }
    ],
    "sg:phone":"+44 1376 321817",
    "sg:postcode":"CM77 6SS",
    "sg:province":"Essex",
    "sg:tags":[
        "hire",
        "coach"
    ],
    "wof:name":"European Studies",
    "wof:placetype":"venue"
},
  "geometry": {"coordinates":[0.510394,51.875538],"type":"Point"}
}