{
  "type": "Feature",
  "properties": {
    "addr:full":"31 Courthill Avenue, Cathcart Glasgow East Renfrewshire G44 5AA",
    "addr:housenumber":"31",
    "addr:postcode":"g44 5aa",
    "addr:street":"Courthill Avenue",
    "iso:country":"GB",
    "sg:address":"31 Courthill Avenue, Cathcart",
    "sg:city":"Glasgow",
    "sg:classifiers":[
        {
            "category":"Building & Trades",
            "subcategory":"Plumbing",
            "type":"Services"
        }
    ],
    "sg:phone":"+44 141 637 3642",
    "sg:postcode":"G44 5AA",
    "sg:province":"East Renfrewshire",
    "sg:tags":[
        "heating"
    ],
    "wof:name":"McCann Plumbing & Heating Services",
    "wof:placetype":"venue"
},
  "geometry": {"coordinates":[-4.2552838326,55.8157310486],"type":"Point"}
}