{
  "type": "Feature",
  "properties": {
    "iso:country":"GB",
    "sg:address":"10 Plymouth Road",
    "sg:city":"Sale",
    "sg:classifiers":[
        {
            "category":"Personal",
            "subcategory":"Beauty Salon",
            "type":"Services"
        }
    ],
    "sg:phone":"+44 161 973 8789",
    "sg:postcode":"M33 5JD",
    "sg:province":"Cheshire",
    "sg:tags":[
        "unisex",
        "hairdresser"
    ],
    "wof:name":"Janice McNamara",
    "wof:placetype":"venue"
},
  "geometry": {"coordinates":[-2.3519079685,53.4271888733],"type":"Point"}
}