{
  "type": "Feature",
  "properties": {
    "iso:country":"GB",
    "sg:address":"22 Victoria Street",
    "sg:city":"Burnham-on-sea",
    "sg:classifiers":[
        {
            "category":"Home & Garden",
            "subcategory":"Home Furnishings",
            "type":"Retail Goods"
        }
    ],
    "sg:phone":"+44 1278 780094",
    "sg:postcode":"TA8 1AN",
    "sg:province":"Somerset",
    "sg:tags":[
        "awning",
        "canopy",
        "blinds"
    ],
    "wof:name":"B C L Windowblinds Ltd.",
    "wof:placetype":"venue"
},
  "geometry": {"coordinates":[-2.997807,51.238308],"type":"Point"}
}