{
  "type": "Feature",
  "properties": {
    "addr:full":"42 St Giles Oxford Oxfordshire OX1 3LW",
    "addr:housenumber":"42",
    "addr:postcode":"ox1 3lw",
    "addr:street":"St Giles",
    "iso:country":"GB",
    "sg:address":"42 St Giles",
    "sg:city":"Oxford",
    "sg:classifiers":[
        {
            "category":"Organizations",
            "subcategory":"Religious Organization",
            "type":"Services"
        }
    ],
    "sg:phone":"+44 1865 310323",
    "sg:postcode":"OX1 3LW",
    "sg:province":"Oxfordshire",
    "sg:tags":[
        "organisation",
        "place",
        "worship"
    ],
    "wof:name":"Quaker Centre",
    "wof:placetype":"venue"
},
  "geometry": {"coordinates":[-1.260525,51.757755],"type":"Point"}
}