{
  "type": "Feature",
  "properties": {
    "iso:country":"GB",
    "sg:address":"Bridge Road",
    "sg:city":"Ashford",
    "sg:classifiers":[
        {
            "category":"Autos & Motor Vehicles",
            "subcategory":"Automobile Sales",
            "type":"Retail Goods"
        },
        {
            "category":"Retail",
            "subcategory":"Driving School",
            "type":"Services"
        }
    ],
    "sg:phone":"+44 1303 812727",
    "sg:postcode":"TN25 6QQ",
    "sg:province":"Kent",
    "sg:tags":[
        "car"
    ],
    "wof:name":"John Childs (Garage) Ltd.",
    "wof:placetype":"venue"
},
  "geometry": {"coordinates":[0.97109,51.125549],"type":"Point"}
}