{
  "type": "Feature",
  "properties": {
    "iso:country":"GB",
    "sg:address":"7 Neale St",
    "sg:city":"Ipswich",
    "sg:classifiers":[
        {
            "category":"Real Estate",
            "subcategory":"Real Estate Agent",
            "type":"Services"
        }
    ],
    "sg:phone":"+44 1473 890088",
    "sg:postcode":"IP1 3JB",
    "sg:province":"Suffolk",
    "wof:name":"Bradshaw Estate Agents",
    "wof:placetype":"venue"
},
  "geometry": {"coordinates":[1.155336,52.059708],"type":"Point"}
}