{
  "type": "Feature",
  "properties": {
    "addr:full":"16 Lower Street Kettering Northamptonshire NN16 8DY",
    "addr:housenumber":"16",
    "addr:postcode":"nn16 8dy",
    "addr:street":"Lower Street",
    "iso:country":"GB",
    "sg:address":"16 Lower Street",
    "sg:city":"Kettering",
    "sg:classifiers":[
        {
            "category":"Restaurant",
            "type":"Food & Drink"
        }
    ],
    "sg:postcode":"NN16 8DY",
    "sg:province":"Northamptonshire",
    "wof:name":"Mr Chips",
    "wof:placetype":"venue"
},
  "geometry": {"coordinates":[-0.728918016,52.4006233215],"type":"Point"}
}