{
  "type": "Feature",
  "properties": {
    "addr:full":"59 Darkes Lane Potters Bar Greater London EN6 1BJ",
    "addr:housenumber":"59",
    "addr:postcode":"en6 1bj",
    "addr:street":"Darkes Lane",
    "iso:country":"GB",
    "sg:address":"59 Darkes Lane",
    "sg:city":"Potters Bar",
    "sg:classifiers":[
        {
            "category":"Banks & Credit Unions",
            "subcategory":"Bank",
            "type":"Services"
        },
        {
            "category":"Banks & Credit Unions",
            "subcategory":"Financial Services",
            "type":"Services"
        }
    ],
    "sg:phone":"+44 1707 658128",
    "sg:postcode":"EN6 1BJ",
    "sg:province":"Greater London",
    "sg:tags":[
        "building",
        "society"
    ],
    "wof:name":"Bristol & West Plc",
    "wof:placetype":"venue"
},
  "geometry": {"coordinates":[-0.1909549981,51.697933197],"type":"Point"}
}