{
  "type": "Feature",
  "properties": {
    "iso:country":"GB",
    "sg:address":"20 Henrietta St",
    "sg:city":"Birmingham",
    "sg:classifiers":[
        {
            "category":"Professional",
            "subcategory":"Business Services",
            "type":"Services"
        }
    ],
    "sg:phone":"+44 121 200 1144",
    "sg:postcode":"B19 3PS",
    "sg:province":"West Midlands",
    "sg:tags":[
        "import",
        "export",
        "agent"
    ],
    "wof:name":"Palino International Import & Export Ltd",
    "wof:placetype":"venue"
},
  "geometry": {"coordinates":[-1.9011160135,52.4875259399],"type":"Point"}
}