{
  "type": "Feature",
  "properties": {
    "addr:full":"26 High Street Knaresborough North Yorkshire HG5 0EQ",
    "addr:housenumber":"26",
    "addr:postcode":"hg5 0eq",
    "addr:street":"High Street",
    "iso:country":"GB",
    "sg:address":"26 High Street",
    "sg:city":"Knaresborough",
    "sg:classifiers":[
        {
            "category":"Recreation",
            "subcategory":"Amusement Park",
            "type":"Entertainment"
        }
    ],
    "sg:postcode":"HG5 0EQ",
    "sg:province":"North Yorkshire",
    "sg:tags":[
        "arcade"
    ],
    "wof:name":"J F Noble",
    "wof:placetype":"venue"
},
  "geometry": {"coordinates":[-1.465662,54.008003],"type":"Point"}
}