{
  "type": "Feature",
  "properties": {
    "addr:full":"14 Waddesdon Close Luton Bedfordshire LU2 9RJ",
    "addr:housenumber":"14",
    "addr:postcode":"lu2 9rj",
    "addr:street":"Waddesdon Close",
    "iso:country":"GB",
    "sg:address":"14 Waddesdon Close",
    "sg:city":"Luton",
    "sg:classifiers":[
        {
            "category":"Shopping",
            "subcategory":"Antiques",
            "type":"Retail Goods"
        },
        {
            "category":"Shopping",
            "subcategory":"Used Merchandise",
            "type":"Retail Goods"
        }
    ],
    "sg:phone":"+44 1582 415656",
    "sg:postcode":"LU2 9RJ",
    "sg:province":"Bedfordshire",
    "sg:tags":[
        "shop",
        "second-hand"
    ],
    "wof:name":"Abbey Antiques",
    "wof:placetype":"venue"
},
  "geometry": {"coordinates":[-0.378698,51.892719],"type":"Point"}
}