{
  "type": "Feature",
  "properties": {
    "addr:full":"3 The Calvert Centre, Woodmancott Winchester Hampshire SO21 3BN",
    "addr:housenumber":"3",
    "addr:postcode":"so21 3bn",
    "addr:street":"The",
    "iso:country":"GB",
    "sg:address":"3 The Calvert Centre, Woodmancott",
    "sg:city":"Winchester",
    "sg:classifiers":[
        {
            "category":"Retail",
            "subcategory":"Auto Repair",
            "type":"Services"
        }
    ],
    "sg:phone":"+44 1256 397150",
    "sg:postcode":"SO21 3BN",
    "sg:province":"Hampshire",
    "sg:tags":[
        "modification",
        "garage"
    ],
    "wof:name":"Keylink Systems Ltd.",
    "wof:placetype":"venue"
},
  "geometry": {"coordinates":[-1.194886,51.178879],"type":"Point"}
}