{
  "type": "Feature",
  "properties": {
    "iso:country":"GB",
    "sg:address":"6 Industrial Estate, Station Road",
    "sg:city":"Attleborough",
    "sg:classifiers":[
        {
            "category":"Shopping",
            "subcategory":"Pets & Pet Supplies",
            "type":"Retail Goods"
        },
        {
            "category":"Shopping",
            "type":"Retail Goods"
        }
    ],
    "sg:phone":"+44 1953 455186",
    "sg:postcode":"NR17 2NP",
    "sg:province":"Norfolk",
    "sg:tags":[
        "food",
        "merchant"
    ],
    "wof:name":"Taylors Petfoods",
    "wof:placetype":"venue"
},
  "geometry": {"coordinates":[1.0144350529,52.5190544128],"type":"Point"}
}