{
  "type": "Feature",
  "properties": {
    "addr:full":"Combley Lodge Newport Isle of Wight PO30 2NY",
    "addr:postcode":"po30 2ny",
    "addr:street":"Newport",
    "iso:country":"GB",
    "sg:address":"Combley Lodge",
    "sg:city":"Newport",
    "sg:classifiers":[
        {
            "category":"Building & Trades",
            "subcategory":"Construction",
            "type":"Services"
        }
    ],
    "sg:phone":"+44 1983 526048",
    "sg:postcode":"PO30 2NY",
    "sg:province":"Isle of Wight",
    "sg:tags":[
        "builder"
    ],
    "wof:name":"G O Barnes",
    "wof:placetype":"venue"
},
  "geometry": {"coordinates":[-1.2807689905,50.7007293701],"type":"Point"}
}