{
  "type": "Feature",
  "properties": {
    "addr:full":"107 Latimer Road Eastbourne East Sussex BN22 7ET",
    "addr:housenumber":"107",
    "addr:postcode":"bn22 7et",
    "addr:street":"Latimer Road",
    "iso:country":"GB",
    "sg:address":"107 Latimer Road",
    "sg:city":"Eastbourne",
    "sg:classifiers":[
        {
            "category":"Utilities",
            "subcategory":"Cable",
            "type":"Services"
        }
    ],
    "sg:postcode":"BN22 7ET",
    "sg:province":"East Sussex",
    "sg:tags":[
        "rope",
        "hawser"
    ],
    "wof:name":"Rigging Projects",
    "wof:placetype":"venue"
},
  "geometry": {"coordinates":[0.300496,50.777668],"type":"Point"}
}