{
  "type": "Feature",
  "properties": {
    "addr:full":"Griffiths Drive, Ashmore Park Wolverhampton Staffordshire WV11 2LH",
    "addr:postcode":"wv11 2lh",
    "addr:street":"Griffiths Drive;Park",
    "iso:country":"GB",
    "sg:address":"Griffiths Drive, Ashmore Park",
    "sg:city":"Wolverhampton",
    "sg:classifiers":[
        {
            "category":"Community Center",
            "type":"Public Place"
        }
    ],
    "sg:phone":"+44 1902 731707",
    "sg:postcode":"WV11 2LH",
    "sg:province":"Staffordshire",
    "sg:tags":[
        "centre"
    ],
    "wof:name":"Corpus Christi Social Centre Ltd.",
    "wof:placetype":"venue"
},
  "geometry": {"coordinates":[-2.058109,52.619808],"type":"Point"}
}