{
  "type": "Feature",
  "properties": {
    "addr:full":"C/o 49 Forest Place Walsall Staffordshire WS3 1SY",
    "addr:housenumber":"49",
    "addr:postcode":"ws3 1sy",
    "addr:street":"C / O;Forest Place",
    "iso:country":"GB",
    "sg:address":"C/o 49 Forest Place",
    "sg:city":"Walsall",
    "sg:classifiers":[
        {
            "category":"Organizations",
            "subcategory":"Political Organization",
            "type":"Services"
        }
    ],
    "sg:phone":"+44 1922 646357",
    "sg:postcode":"WS3 1SY",
    "sg:province":"Staffordshire",
    "sg:tags":[
        "party"
    ],
    "wof:name":"Democratic Labour Party",
    "wof:placetype":"venue"
},
  "geometry": {"coordinates":[-1.98483,52.602551],"type":"Point"}
}