{
  "type": "Feature",
  "properties": {
    "iso:country":"GB",
    "sg:address":"Upr Aughton Rd, Birkdale",
    "sg:city":"Southport",
    "sg:classifiers":[
        {
            "category":"Professional",
            "subcategory":"Accounting & Tax Preparation",
            "type":"Services"
        }
    ],
    "sg:postcode":"PR8 5NA",
    "sg:province":"Lancashire",
    "sg:tags":[
        "accountant"
    ],
    "wof:name":"Collins,Michael,",
    "wof:placetype":"venue"
},
  "geometry": {"coordinates":[-3.009814024,53.6371841431],"type":"Point"}
}