{
  "type": "Feature",
  "properties": {
    "iso:country":"GB",
    "sg:address":"12 Springfield Rd, Sharples, Dunscar",
    "sg:city":"Bolton",
    "sg:classifiers":[
        {
            "category":"Retail",
            "subcategory":"Veterinary Services",
            "type":"Services"
        }
    ],
    "sg:postcode":"BL1 7LQ",
    "sg:province":"Lancashire",
    "sg:tags":[
        "surgeon"
    ],
    "wof:name":"Barton,T B,",
    "wof:placetype":"venue"
},
  "geometry": {"coordinates":[-2.436165,53.613033],"type":"Point"}
}