{
  "type": "Feature",
  "properties": {
    "addr:full":"251 Munster Road London Greater London SW6 6BS",
    "addr:housenumber":"251",
    "addr:postcode":"sw6 6bs",
    "addr:street":"Munster Road",
    "iso:country":"GB",
    "sg:address":"251 Munster Road",
    "sg:city":"London",
    "sg:classifiers":[
        {
            "category":"Taxi",
            "type":"Transportation"
        }
    ],
    "sg:phone":"+44 20 7381 4999",
    "sg:postcode":"SW6 6BS",
    "sg:province":"Greater London",
    "sg:tags":[
        "mini",
        "cab"
    ],
    "wof:name":"A Top Cars",
    "wof:placetype":"venue"
},
  "geometry": {"coordinates":[-0.2128710002,51.480922699],"type":"Point"}
}