{
  "type": "Feature",
  "properties": {
    "addr:full":"32 High St Steyning West Sussex BN44 3YE",
    "addr:housenumber":"32",
    "addr:postcode":"bn44 3ye",
    "addr:street":"High St",
    "iso:country":"GB",
    "sg:address":"32 High St",
    "sg:city":"Steyning",
    "sg:classifiers":[
        {
            "category":"Shopping",
            "subcategory":"Gifts & Souvenirs",
            "type":"Retail Goods"
        }
    ],
    "sg:postcode":"BN44 3YE",
    "sg:province":"West Sussex",
    "sg:tags":[
        "shop"
    ],
    "wof:name":"Miracles",
    "wof:placetype":"venue"
},
  "geometry": {"coordinates":[-0.3282710016,50.887966156],"type":"Point"}
}