{
  "type": "Feature",
  "properties": {
    "iso:country":"GB",
    "sg:address":"The Old Court House, Roman Square",
    "sg:city":"Sittingbourne",
    "sg:classifiers":[
        {
            "category":"Insurance",
            "subcategory":"Insurance Agent",
            "type":"Services"
        }
    ],
    "sg:phone":"+44 1795 422990",
    "sg:postcode":"ME10 4BJ",
    "sg:province":"Kent",
    "wof:name":"Acorn Insurance Group",
    "wof:placetype":"venue"
},
  "geometry": {"coordinates":[0.73791,51.34082],"type":"Point"}
}