{
  "type": "Feature",
  "properties": {
    "iso:country":"GB",
    "sg:address":"30 Sand Road, Kewstoke",
    "sg:city":"Weston-super-mare",
    "sg:classifiers":[
        {
            "category":"Health Services",
            "subcategory":"Health Practitioner",
            "type":"Services"
        }
    ],
    "sg:postcode":"BS22 9UH",
    "sg:province":"Somerset",
    "sg:tags":[
        "hypnotherapists"
    ],
    "wof:name":"Elizabeth McIntyre",
    "wof:placetype":"venue"
},
  "geometry": {"coordinates":[-2.958048,51.376331],"type":"Point"}
}