{
  "type": "Feature",
  "properties": {
    "addr:full":"11 Anglesea Rd Woolwich Greater London SE18 6EG",
    "addr:housenumber":"11",
    "addr:postcode":"se18 6eg",
    "addr:street":"Anglesea Rd",
    "iso:country":"GB",
    "sg:address":"11 Anglesea Rd",
    "sg:city":"Woolwich",
    "sg:classifiers":[
        {
            "category":"Professional",
            "subcategory":"Detective & Security Services",
            "type":"Services"
        }
    ],
    "sg:phone":"+44 20 8855 5777",
    "sg:postcode":"SE18 6EG",
    "sg:province":"Greater London",
    "wof:name":"Horn Security Services",
    "wof:placetype":"venue"
},
  "geometry": {"coordinates":[0.0677179992,51.4886512756],"type":"Point"}
}