{
  "type": "Feature",
  "properties": {
    "iso:country":"GB",
    "sg:address":"21 Park Road",
    "sg:city":"Bingley",
    "sg:classifiers":[
        {
            "category":"Home & Garden",
            "subcategory":"Hardware",
            "type":"Retail Goods"
        }
    ],
    "sg:phone":"+44 1274 779001",
    "sg:postcode":"BD16 4BQ",
    "sg:province":"West Yorkshire",
    "sg:tags":[
        "device",
        "fixing",
        "fastener"
    ],
    "wof:name":"Phoenix Fixings Ltd",
    "wof:placetype":"venue"
},
  "geometry": {"coordinates":[-1.836453,53.850292],"type":"Point"}
}