{
  "type": "Feature",
  "properties": {
    "addr:full":"13 Fitzroy Place Glasgow Glasgow City G3 7RW",
    "addr:housenumber":"13",
    "addr:postcode":"g3 7rw",
    "addr:street":"Fitzroy Place",
    "iso:country":"GB",
    "sg:address":"13 Fitzroy Place",
    "sg:city":"Glasgow",
    "sg:classifiers":[
        {
            "category":"Professional",
            "subcategory":"Accounting & Tax Preparation",
            "type":"Services"
        }
    ],
    "sg:phone":"+44 141 248 4020",
    "sg:postcode":"G3 7RW",
    "sg:province":"Glasgow City",
    "sg:tags":[
        "accountant",
        "activity"
    ],
    "wof:name":"R A Scott Wheelan & Co",
    "wof:placetype":"venue"
},
  "geometry": {"coordinates":[-4.280479,55.86581],"type":"Point"}
}