{
  "type": "Feature",
  "properties": {
    "addr:full":"167 Cambridge Road St Helens Merseyside WA10 4HA",
    "addr:housenumber":"167",
    "addr:postcode":"wa10 4ha",
    "addr:street":"Cambridge Road",
    "iso:country":"GB",
    "sg:address":"167 Cambridge Road",
    "sg:city":"St Helens",
    "sg:classifiers":[
        {
            "category":"Shopping",
            "subcategory":"Discount & Variety Stores",
            "type":"Retail Goods"
        }
    ],
    "sg:phone":"+44 1744 605905",
    "sg:postcode":"WA10 4HA",
    "sg:province":"Merseyside",
    "sg:tags":[
        "centre"
    ],
    "wof:name":"Come & Save",
    "wof:placetype":"venue"
},
  "geometry": {"coordinates":[-2.75272,53.453228],"type":"Point"}
}