{
  "type": "Feature",
  "properties": {
    "addr:full":"8 The Strand, Shaldon Teignmouth Devon TQ14 0DL",
    "addr:housenumber":"8",
    "addr:postcode":"tq14 0dl",
    "addr:street":"The Strand",
    "iso:country":"GB",
    "sg:address":"8 The Strand, Shaldon",
    "sg:city":"Teignmouth",
    "sg:classifiers":[
        {
            "category":"Shopping",
            "subcategory":"Clothing, Apparel, & Fashions",
            "type":"Retail Goods"
        }
    ],
    "sg:phone":"+44 1626 872431",
    "sg:postcode":"TQ14 0DL",
    "sg:province":"Devon",
    "sg:tags":[
        "shop"
    ],
    "wof:name":"D E & D Sanders",
    "wof:placetype":"venue"
},
  "geometry": {"coordinates":[-3.518684,50.540852],"type":"Point"}
}