{
  "type": "Feature",
  "properties": {
    "iso:country":"GB",
    "sg:address":"78 High St",
    "sg:city":"Pwllheli",
    "sg:classifiers":[
        {
            "category":"Restaurant",
            "type":"Food & Drink"
        }
    ],
    "sg:phone":"+44 1758 701881",
    "sg:postcode":"LL53 5RR",
    "sg:province":"Gwynedd",
    "wof:name":"Peckish",
    "wof:placetype":"venue"
},
  "geometry": {"coordinates":[-4.416299,52.889931],"type":"Point"}
}