{
  "type": "Feature",
  "properties": {
    "addr:full":"Clyde Cotts, 15 Upper Church Road St Leonards-on-sea East Sussex TN37 7AS",
    "addr:housenumber":"15",
    "addr:postcode":"leonards-on-sea;tn37 7as",
    "addr:street":"Cotts;Upper Church Road St",
    "iso:country":"GB",
    "sg:address":"Clyde Cotts, 15 Upper Church Road",
    "sg:city":"St Leonards-on-sea",
    "sg:classifiers":[
        {
            "category":"Building & Trades",
            "subcategory":"Construction",
            "type":"Services"
        }
    ],
    "sg:phone":"+44 1424 751478",
    "sg:postcode":"TN37 7AS",
    "sg:province":"East Sussex",
    "sg:tags":[
        "builder"
    ],
    "wof:name":"R Wild (Hastings) Ltd.",
    "wof:placetype":"venue"
},
  "geometry": {"coordinates":[0.55391,50.878658],"type":"Point"}
}