{
  "type": "Feature",
  "properties": {
    "addr:full":"6 Brantfell Garage, Kendal Road, Bowness On Windermere Windermere Cumbria LA23 3FB",
    "addr:housenumber":"6",
    "addr:postcode":"la23 3fb",
    "addr:street":"Kendal Road",
    "iso:country":"GB",
    "sg:address":"6 Brantfell Garage, Kendal Road, Bowness On Windermere",
    "sg:city":"Windermere",
    "sg:classifiers":[
        {
            "category":"Retail",
            "subcategory":"Auto Rental",
            "type":"Services"
        }
    ],
    "sg:phone":"+44 15394 45910",
    "sg:postcode":"LA23 3FB",
    "sg:province":"Cumbria",
    "sg:tags":[
        "car"
    ],
    "wof:name":"Avis Rent A Car Ltd.",
    "wof:placetype":"venue"
},
  "geometry": {"coordinates":[-2.922436,54.362869],"type":"Point"}
}