{
  "type": "Feature",
  "properties": {
    "iso:country":"GB",
    "sg:address":"3 Wynford Rd",
    "sg:city":"Poole",
    "sg:classifiers":[
        {
            "category":"Building & Trades",
            "subcategory":"Construction",
            "type":"Services"
        }
    ],
    "sg:postcode":"BH14 8PG",
    "sg:province":"Dorset",
    "sg:tags":[
        "builder"
    ],
    "wof:name":"Southdown Developments",
    "wof:placetype":"venue"
},
  "geometry": {"coordinates":[-1.941576,50.722954],"type":"Point"}
}