{
  "type": "Feature",
  "properties": {
    "addr:full":"Unit 20, Roman Way, Coleshill Birmingham Warwickshire B46 1HQ",
    "addr:housenumber":"unit 20",
    "addr:postcode":"b46 1hq",
    "addr:street":"Roman Way",
    "iso:country":"GB",
    "sg:address":"Unit 20, Roman Way, Coleshill",
    "sg:city":"Birmingham",
    "sg:classifiers":[
        {
            "category":"Retail",
            "subcategory":"Auto Rental",
            "type":"Services"
        },
        {
            "category":"Retail",
            "subcategory":"Auto Repair",
            "type":"Services"
        }
    ],
    "sg:phone":"+44 1675 466000",
    "sg:postcode":"B46 1HQ",
    "sg:province":"Warwickshire",
    "sg:tags":[
        "body",
        "car"
    ],
    "wof:name":"Hallmarque Assistance Ltd.",
    "wof:placetype":"venue"
},
  "geometry": {"coordinates":[-1.709439,52.511021],"type":"Point"}
}