{
  "type": "Feature",
  "properties": {
    "iso:country":"GB",
    "sg:address":"Cecil Lodge, Falmouth Avenue",
    "sg:city":"Newmarket",
    "sg:classifiers":[
        {
            "category":"Organizations",
            "subcategory":"Professional Association",
            "type":"Services"
        }
    ],
    "sg:phone":"+44 1638 664538",
    "sg:postcode":"CB8 0NB",
    "sg:province":"Cambridgeshire",
    "sg:tags":[
        "union",
        "trade"
    ],
    "wof:name":"The National Union of Teachers",
    "wof:placetype":"venue"
},
  "geometry": {"coordinates":[0.399165988,52.2498168945],"type":"Point"}
}