{
  "type": "Feature",
  "properties": {
    "iso:country":"GB",
    "sg:address":"123 High Street",
    "sg:city":"Inverurie",
    "sg:classifiers":[
        {
            "category":"Personal",
            "subcategory":"Beauty Salon",
            "type":"Services"
        }
    ],
    "sg:phone":"+44 1467 624420",
    "sg:postcode":"AB51 3QJ",
    "sg:province":"Aberdeenshire",
    "wof:name":"Peaches & Cream",
    "wof:placetype":"venue"
},
  "geometry": {"coordinates":[-2.3709928989,57.2779502869],"type":"Point"}
}