{
  "type": "Feature",
  "properties": {
    "addr:full":"21 Martlesham Walk Manchester Greater Manchester M4 1LY",
    "addr:housenumber":"21",
    "addr:postcode":"m4 1ly",
    "addr:street":"Martlesham Walk",
    "iso:country":"GB",
    "sg:address":"21 Martlesham Walk",
    "sg:city":"Manchester",
    "sg:classifiers":[
        {
            "category":"Professional",
            "subcategory":"Credit Reporting & Collection",
            "type":"Services"
        }
    ],
    "sg:phone":"+44 161 835 3816",
    "sg:postcode":"M4 1LY",
    "sg:province":"Greater Manchester",
    "sg:tags":[
        "collecting",
        "agency"
    ],
    "wof:name":"Palleon Ltd.",
    "wof:placetype":"venue"
},
  "geometry": {"coordinates":[-2.2353589535,53.4848136902],"type":"Point"}
}