{
  "type": "Feature",
  "properties": {
    "iso:country":"GB",
    "sg:address":"245 High Street",
    "sg:city":"Burntisland",
    "sg:classifiers":[
        {
            "category":"Shopping",
            "subcategory":"Baby Store",
            "type":"Retail Goods"
        }
    ],
    "sg:postcode":"KY3 9AQ",
    "sg:province":"Fife",
    "sg:tags":[
        "babywear",
        "childrens"
    ],
    "wof:name":"Babyworld",
    "wof:placetype":"venue"
},
  "geometry": {"coordinates":[-3.231529,56.05986],"type":"Point"}
}