{
  "type": "Feature",
  "properties": {
    "iso:country":"GB",
    "sg:address":"Halsbury House, 35 Chancery Lane",
    "sg:city":"London",
    "sg:classifiers":[
        {
            "category":"Wholesale",
            "subcategory":"Books, Periodicals, & Newspapers",
            "type":"Manufacturing & Wholesale Goods"
        }
    ],
    "sg:phone":"+44 20 7400 2500",
    "sg:postcode":"WC2A 1EL",
    "sg:province":"Greater London",
    "sg:tags":[
        "publishing"
    ],
    "wof:name":"Butterworths Ltd.",
    "wof:placetype":"venue"
},
  "geometry": {"coordinates":[-0.1111489981,51.5141906738],"type":"Point"}
}