{
  "type": "Feature",
  "properties": {
    "addr:full":"60 London Rd East Grinstead East Sussex RH19 1AB",
    "addr:housenumber":"60",
    "addr:postcode":"rh19 1ab",
    "addr:street":"London Rd",
    "iso:country":"GB",
    "sg:address":"60 London Rd",
    "sg:city":"East Grinstead",
    "sg:classifiers":[
        {
            "category":"Travel",
            "subcategory":"Travel Agent",
            "type":"Entertainment"
        }
    ],
    "sg:postcode":"RH19 1AB",
    "sg:province":"East Sussex",
    "wof:name":"Personal Service Travel Ltd",
    "wof:placetype":"venue"
},
  "geometry": {"coordinates":[-0.0092099998,51.1255493164],"type":"Point"}
}