{
  "type": "Feature",
  "properties": {
    "iso:country":"GB",
    "sg:address":"3 Sutton Parade, Alfirston Road",
    "sg:city":"Seaford",
    "sg:classifiers":[
        {
            "category":"Farming",
            "subcategory":"Fish & Marine Products",
            "type":"Manufacturing & Wholesale Goods"
        },
        {
            "category":"Food & Beverages",
            "subcategory":"Meat & Fish",
            "type":"Retail Goods"
        }
    ],
    "sg:postcode":"BN25 3PX",
    "sg:province":"East Sussex",
    "sg:tags":[
        "fishmonger",
        "butcher"
    ],
    "wof:name":"M D Clarke & Sons",
    "wof:placetype":"venue"
},
  "geometry": {"coordinates":[0.11077,50.774776],"type":"Point"}
}