{
  "type": "Feature",
  "properties": {
    "iso:country":"GB",
    "sg:address":"Wilsden Road",
    "sg:city":"Bingley",
    "sg:classifiers":[
        {
            "category":"Home & Garden",
            "subcategory":"Garden Supply",
            "type":"Retail Goods"
        }
    ],
    "sg:phone":"+44 1535 274653",
    "sg:postcode":"BD16 1BL",
    "sg:province":"West Yorkshire",
    "sg:tags":[
        "nursery",
        "centre"
    ],
    "wof:name":"Stephen H Smith Garden & Leisure",
    "wof:placetype":"venue"
},
  "geometry": {"coordinates":[-1.870814,53.841259],"type":"Point"}
}