{
  "type": "Feature",
  "properties": {
    "addr:full":"41-43 Thomas Street Llanelli Carmarthenshire SA15 3JE",
    "addr:housenumber":"41-43",
    "addr:postcode":"sa15 3je",
    "addr:street":"Thomas Street",
    "iso:country":"GB",
    "sg:address":"41-43 Thomas Street",
    "sg:city":"Llanelli",
    "sg:classifiers":[
        {
            "category":"Shopping",
            "subcategory":"Florist",
            "type":"Retail Goods"
        }
    ],
    "sg:postcode":"SA15 3JE",
    "sg:province":"Carmarthenshire",
    "wof:name":"The Flower Pot",
    "wof:placetype":"venue"
},
  "geometry": {"coordinates":[-4.1611089706,51.6848487854],"type":"Point"}
}