{
  "type": "Feature",
  "properties": {
    "iso:country":"GB",
    "sg:address":"Unit 2, Botley Lane",
    "sg:city":"Chesham",
    "sg:classifiers":[
        {
            "category":"Building & Trades",
            "subcategory":"Construction",
            "type":"Services"
        }
    ],
    "sg:phone":"+44 1494 785689",
    "sg:postcode":"HP5 1XS",
    "sg:province":"Buckinghamshire",
    "sg:tags":[
        "builder"
    ],
    "wof:name":"Tuskar Construction Services Ltd",
    "wof:placetype":"venue"
},
  "geometry": {"coordinates":[-0.579094,51.710682],"type":"Point"}
}