{
  "type": "Feature",
  "properties": {
    "iso:country":"GB",
    "sg:address":"P O Box 35",
    "sg:city":"Newmarket",
    "sg:classifiers":[
        {
            "category":"Professional",
            "subcategory":"Computer Services",
            "type":"Services"
        }
    ],
    "sg:phone":"+44 1638 664055",
    "sg:postcode":"CB8 8ZA",
    "sg:province":"Cambridgeshire",
    "sg:tags":[
        "security",
        "retail"
    ],
    "wof:name":"Accses Computer Security",
    "wof:placetype":"venue"
},
  "geometry": {"coordinates":[0.5159,52.211559],"type":"Point"}
}