{
  "type": "Feature",
  "properties": {
    "iso:country":"GB",
    "sg:address":"82 Berkley St Eynesbury, St. Neots",
    "sg:city":"Huntingdon",
    "sg:classifiers":[
        {
            "category":"Professional",
            "subcategory":"Printing & Photocopies",
            "type":"Services"
        }
    ],
    "sg:phone":"+44 1480 381167",
    "sg:postcode":"PE19 2NF",
    "sg:province":"Bedfordshire",
    "sg:tags":[
        "trophy",
        "medal"
    ],
    "wof:name":"Jan Nagel Rosettes",
    "wof:placetype":"venue"
},
  "geometry": {"coordinates":[-0.2678200006,52.2240333557],"type":"Point"}
}