{
  "type": "Feature",
  "properties": {
    "iso:country":"GB",
    "sg:address":"80a High Street, Stoney Stratford",
    "sg:city":"Milton Keynes",
    "sg:classifiers":[
        {
            "category":"Professional",
            "subcategory":"Accounting & Tax Preparation",
            "type":"Services"
        }
    ],
    "sg:phone":"+44 1908 569000",
    "sg:postcode":"MK11 1AH",
    "sg:province":"Buckinghamshire",
    "sg:tags":[
        "accountant",
        "activity"
    ],
    "wof:name":"Fisher Morris Garrad",
    "wof:placetype":"venue"
},
  "geometry": {"coordinates":[-0.8542559743,52.0578079224],"type":"Point"}
}