{
  "type": "Feature",
  "properties": {
    "iso:country":"GB",
    "sg:address":"Unit 6, The Old Forge, Peterchurch",
    "sg:city":"Hereford",
    "sg:classifiers":[
        {
            "category":"Shopping",
            "subcategory":"Hobbies, Toys, & Games",
            "type":"Retail Goods"
        }
    ],
    "sg:phone":"+44 1981 550145",
    "sg:postcode":"HR2 0SD",
    "sg:province":"Herefordshire",
    "sg:tags":[
        "gunsmith"
    ],
    "wof:name":"John Slough Of London",
    "wof:placetype":"venue"
},
  "geometry": {"coordinates":[-2.9590930939,52.0460662842],"type":"Point"}
}