{
  "type": "Feature",
  "properties": {
    "addr:full":"29 Throgmorton Rd Yateley Hampshire GU46 6FA",
    "addr:housenumber":"29",
    "addr:postcode":"gu46 6fa",
    "addr:street":"Throgmorton Rd",
    "iso:country":"GB",
    "sg:address":"29 Throgmorton Rd",
    "sg:city":"Yateley",
    "sg:classifiers":[
        {
            "category":"Professional",
            "subcategory":"Employment Agencies",
            "type":"Services"
        }
    ],
    "sg:phone":"+44 1252 673707",
    "sg:postcode":"GU46 6FA",
    "sg:province":"Hampshire",
    "sg:tags":[
        "consultant"
    ],
    "wof:name":"Ski Personnel",
    "wof:placetype":"venue"
},
  "geometry": {"coordinates":[-0.8460559845,51.3366775513],"type":"Point"}
}