{
  "type": "Feature",
  "properties": {
    "addr:full":"9 Genoa Avenue London Greater London SW15 6DY",
    "addr:housenumber":"9",
    "addr:postcode":"sw15 6dy",
    "addr:street":"Genoa Avenue",
    "iso:country":"GB",
    "sg:address":"9 Genoa Avenue",
    "sg:city":"London",
    "sg:classifiers":[
        {
            "category":"Organizations",
            "subcategory":"Membership Organization",
            "type":"Services"
        }
    ],
    "sg:phone":"+44 1252 724438",
    "sg:postcode":"SW15 6DY",
    "sg:province":"Greater London",
    "sg:tags":[
        "club"
    ],
    "wof:name":"Almeida Management Ltd.",
    "wof:placetype":"venue"
},
  "geometry": {"coordinates":[-0.225952,51.458385],"type":"Point"}
}