{
  "type": "Feature",
  "properties": {
    "addr:full":"15 Forrest Street, Blantyre Glasgow South Lanarkshire G72 0JP",
    "addr:housenumber":"15",
    "addr:postcode":"g72 0jp",
    "addr:street":"Forrest Street",
    "iso:country":"GB",
    "sg:address":"15 Forrest Street, Blantyre",
    "sg:city":"Glasgow",
    "sg:classifiers":[
        {
            "category":"Home & Garden",
            "subcategory":"Building Materials",
            "type":"Retail Goods"
        }
    ],
    "sg:phone":"+44 1698 327718",
    "sg:postcode":"G72 0JP",
    "sg:province":"South Lanarkshire",
    "sg:tags":[
        "insulation",
        "installers"
    ],
    "wof:name":"Blantyre Insulation Services Ltd.",
    "wof:placetype":"venue"
},
  "geometry": {"coordinates":[-4.0928077698,55.7846603394],"type":"Point"}
}