{
  "type": "Feature",
  "properties": {
    "iso:country":"GB",
    "sg:address":"Abbey Meadows",
    "sg:city":"Leicester",
    "sg:classifiers":[
        {
            "category":"Professional",
            "subcategory":"Engineering",
            "type":"Services"
        }
    ],
    "sg:postcode":"LE4 5DF",
    "sg:province":"Leicestershire",
    "sg:tags":[
        "precision",
        "engineer"
    ],
    "wof:name":"Micronaid Slip Gauges Ltd.",
    "wof:placetype":"venue"
},
  "geometry": {"coordinates":[-1.132553,52.651508],"type":"Point"}
}