{
  "type": "Feature",
  "properties": {
    "addr:full":"2 Margerison Rd Ilkley North Yorkshire LS29 8QU",
    "addr:housenumber":"2",
    "addr:postcode":"ls29 8qu",
    "addr:street":"Margerison Rd",
    "iso:country":"GB",
    "sg:address":"2 Margerison Rd",
    "sg:city":"Ilkley",
    "sg:classifiers":[
        {
            "category":"Professional",
            "subcategory":"Management & Consulting",
            "type":"Services"
        }
    ],
    "sg:postcode":"LS29 8QU",
    "sg:province":"North Yorkshire",
    "sg:tags":[
        "consultant",
        "business"
    ],
    "wof:name":"Moorlands Associates",
    "wof:placetype":"venue"
},
  "geometry": {"coordinates":[-1.800661,53.92445],"type":"Point"}
}