{
  "type": "Feature",
  "properties": {
    "addr:full":"Caepistyll Street Swansea Neath Port Talbot SA1 2BE",
    "addr:postcode":"sa1 2be",
    "addr:street":"Caepistyll Street",
    "iso:country":"GB",
    "sg:address":"Caepistyll Street",
    "sg:city":"Swansea",
    "sg:classifiers":[
        {
            "category":"Education",
            "subcategory":"School",
            "type":"Public Place"
        }
    ],
    "sg:phone":"+44 1792 653609",
    "sg:postcode":"SA1 2BE",
    "sg:province":"Neath Port Talbot",
    "sg:tags":[
        "local",
        "authority"
    ],
    "wof:name":"St Joseph's Junior School",
    "wof:placetype":"venue"
},
  "geometry": {"coordinates":[-3.940928936,51.6231536865],"type":"Point"}
}