{
  "type": "Feature",
  "properties": {
    "addr:full":"Boundary House, Haveringland Rd, Felthorpe Norwich Norfolk NR10 4BZ",
    "addr:postcode":"nr10 4bz",
    "addr:street":"Haveringland Rd;Norwich",
    "iso:country":"GB",
    "sg:address":"Boundary House, Haveringland Rd, Felthorpe",
    "sg:city":"Norwich",
    "sg:classifiers":[
        {
            "category":"Health Services",
            "subcategory":"Nursing And Care Facility",
            "type":"Services"
        }
    ],
    "sg:phone":"+44 1603 754715",
    "sg:postcode":"NR10 4BZ",
    "sg:province":"Norfolk",
    "sg:tags":[
        "home"
    ],
    "wof:name":"Learning Disabilities",
    "wof:placetype":"venue"
},
  "geometry": {"coordinates":[1.2068099976,52.7269897461],"type":"Point"}
}