{
  "type": "Feature",
  "properties": {
    "addr:full":"3 Hutton Road, Shenfield Brentwood Essex CM15 8LA",
    "addr:housenumber":"3",
    "addr:postcode":"cm15 8la",
    "addr:street":"Hutton Road",
    "iso:country":"GB",
    "sg:address":"3 Hutton Road, Shenfield",
    "sg:city":"Brentwood",
    "sg:classifiers":[
        {
            "category":"Real Estate",
            "subcategory":"Developer",
            "type":"Services"
        }
    ],
    "sg:phone":"+44 1277 218768",
    "sg:postcode":"CM15 8LA",
    "sg:province":"Essex",
    "sg:tags":[
        "property"
    ],
    "wof:name":"Wentworth Developments Ltd.",
    "wof:placetype":"venue"
},
  "geometry": {"coordinates":[0.321998,51.629482],"type":"Point"}
}