{
  "type": "Feature",
  "properties": {
    "iso:country":"GB",
    "sg:address":"166-170 Bishopsgate",
    "sg:city":"London",
    "sg:classifiers":[
        {
            "category":"Bars & Pubs",
            "subcategory":"Wine Bar",
            "type":"Food & Drink"
        }
    ],
    "sg:phone":"+44 20 7247 8992",
    "sg:postcode":"EC2M 4LX",
    "sg:province":"Greater London",
    "wof:name":"Chapters Wine Bar",
    "wof:placetype":"venue"
},
  "geometry": {"coordinates":[-0.080388,51.517323],"type":"Point"}
}