{
  "type": "Feature",
  "properties": {
    "addr:full":"76-78 High St Guildford Surrey GU1 3HE",
    "addr:housenumber":"76-78",
    "addr:postcode":"gu1 3he",
    "addr:street":"High St",
    "iso:country":"GB",
    "sg:address":"76-78 High St",
    "sg:city":"Guildford",
    "sg:classifiers":[
        {
            "category":"Shopping",
            "subcategory":"Clothing, Apparel, & Fashions",
            "type":"Retail Goods"
        }
    ],
    "sg:phone":"+44 1483 568133",
    "sg:postcode":"GU1 3HE",
    "sg:province":"Surrey",
    "sg:tags":[
        "shop"
    ],
    "wof:name":"Kaliko Clothing Co",
    "wof:placetype":"venue"
},
  "geometry": {"coordinates":[-0.573566,51.235363],"type":"Point"}
}