{
  "type": "Feature",
  "properties": {
    "addr:full":"The Old Railway Station, Halton Aylesbury Buckinghamshire HP22 5NP",
    "addr:postcode":"hp22 5np",
    "iso:country":"GB",
    "sg:address":"The Old Railway Station, Halton",
    "sg:city":"Aylesbury",
    "sg:classifiers":[
        {
            "category":"Shopping",
            "subcategory":"Clothing, Apparel, & Fashions",
            "type":"Retail Goods"
        }
    ],
    "sg:phone":"+44 1296 625753",
    "sg:postcode":"HP22 5NP",
    "sg:province":"Buckinghamshire",
    "sg:tags":[
        "staff",
        "wear",
        "uniform"
    ],
    "wof:name":"E C Snaith & Son Ltd.",
    "wof:placetype":"venue"
},
  "geometry": {"coordinates":[-0.7348229885,51.7823448181],"type":"Point"}
}