{
  "type": "Feature",
  "properties": {
    "iso:country":"GB",
    "sg:address":"Taxi Way, Hillend Industrial Estate",
    "sg:city":"Dunfermline",
    "sg:classifiers":[
        {
            "category":"Government",
            "subcategory":"Department Of Motor Vehicles",
            "type":"Public Place"
        }
    ],
    "sg:phone":"+44 1383 823625",
    "sg:postcode":"KY11 9ES",
    "sg:province":"Fife",
    "sg:tags":[
        "commercial"
    ],
    "wof:name":"Heil-Europe Ltd.",
    "wof:placetype":"venue"
},
  "geometry": {"coordinates":[-3.347174,56.042625],"type":"Point"}
}