{
  "type": "Feature",
  "properties": {
    "addr:full":"19 High Street Hawick Cumbria TD9 9BD",
    "addr:housenumber":"19",
    "addr:postcode":"td9 9bd",
    "addr:street":"High Street",
    "iso:country":"GB",
    "sg:address":"19 High Street",
    "sg:city":"Hawick",
    "sg:classifiers":[
        {
            "category":"Social Services",
            "subcategory":"Adult Care",
            "type":"Services"
        }
    ],
    "sg:phone":"+44 1450 377924",
    "sg:postcode":"TD9 9BD",
    "sg:province":"Cumbria",
    "sg:tags":[
        "housing",
        "sheltered"
    ],
    "wof:name":"Streets Ahead (Borders)",
    "wof:placetype":"venue"
},
  "geometry": {"coordinates":[-2.787651,55.422298],"type":"Point"}
}