{
  "type": "Feature",
  "properties": {
    "addr:full":"107 Digby Avenue Nottingham Nottinghamshire NG3 6DT",
    "addr:housenumber":"107",
    "addr:postcode":"ng3 6dt",
    "addr:street":"Digby Avenue",
    "iso:country":"GB",
    "sg:address":"107 Digby Avenue",
    "sg:city":"Nottingham",
    "sg:classifiers":[
        {
            "category":"Building & Trades",
            "subcategory":"Plumbing",
            "type":"Services"
        }
    ],
    "sg:postcode":"NG3 6DT",
    "sg:province":"Nottinghamshire",
    "sg:tags":[
        "heating"
    ],
    "wof:name":"Roy Newbold",
    "wof:placetype":"venue"
},
  "geometry": {"coordinates":[-1.101536,52.9809],"type":"Point"}
}