{
  "type": "Feature",
  "properties": {
    "iso:country":"GB",
    "sg:address":"1 Lower Street",
    "sg:city":"Stansted",
    "sg:classifiers":[
        {
            "category":"Shopping",
            "subcategory":"Pharmacy",
            "type":"Retail Goods"
        }
    ],
    "sg:phone":"+44 1279 812278",
    "sg:postcode":"CM24 8LN",
    "sg:province":"Essex",
    "sg:tags":[
        "pharmacist",
        "chemist"
    ],
    "wof:name":"Moss Chemist",
    "wof:placetype":"venue"
},
  "geometry": {"coordinates":[0.1994799972,51.9022331238],"type":"Point"}
}