{
  "type": "Feature",
  "properties": {
    "addr:full":"957 Fulham Road London Greater London SW6 5HY",
    "addr:housenumber":"957",
    "addr:postcode":"sw6 5hy",
    "addr:street":"Fulham Road",
    "iso:country":"GB",
    "sg:address":"957 Fulham Road",
    "sg:city":"London",
    "sg:classifiers":[
        {
            "category":"Shopping",
            "type":"Retail Goods"
        }
    ],
    "sg:phone":"+44 20 7736 4763",
    "sg:postcode":"SW6 5HY",
    "sg:province":"Greater London",
    "sg:tags":[
        "part",
        "accessory"
    ],
    "wof:name":"Lively Motorparts Ltd.",
    "wof:placetype":"venue"
},
  "geometry": {"coordinates":[-0.2107219994,51.4717750549],"type":"Point"}
}