{
  "type": "Feature",
  "properties": {
    "addr:full":"Simark, High Street, Chieveley Newbury Berkshire RG20 8TE",
    "addr:postcode":"rg20 8te",
    "addr:street":"High Street",
    "iso:country":"GB",
    "sg:address":"Simark, High Street, Chieveley",
    "sg:city":"Newbury",
    "sg:classifiers":[
        {
            "category":"Retail",
            "subcategory":"Driving School",
            "type":"Services"
        }
    ],
    "sg:phone":"+44 1635 248041",
    "sg:postcode":"RG20 8TE",
    "sg:province":"Berkshire",
    "wof:name":"Chieveley School Of Motoring",
    "wof:placetype":"venue"
},
  "geometry": {"coordinates":[-1.3166630268,51.4626464844],"type":"Point"}
}