{
  "type": "Feature",
  "properties": {
    "addr:full":"Rotterdam Road, Sutton Fields Industrial Estate Hull East Riding of Yorkshire HU7 0XD",
    "addr:postcode":"hu7 0xd",
    "addr:street":"Rotterdam Road;Fields Industrial Estate",
    "iso:country":"GB",
    "sg:address":"Rotterdam Road, Sutton Fields Industrial Estate",
    "sg:city":"Hull",
    "sg:classifiers":[
        {
            "category":"Building & Trades",
            "subcategory":"Plumbing",
            "type":"Services"
        }
    ],
    "sg:phone":"+44 1482 834900",
    "sg:postcode":"HU7 0XD",
    "sg:province":"East Riding of Yorkshire",
    "sg:tags":[
        "heating"
    ],
    "wof:name":"Neville Tucker Heating Ltd.",
    "wof:placetype":"venue"
},
  "geometry": {"coordinates":[-0.3290640116,53.7742576599],"type":"Point"}
}