{
  "type": "Feature",
  "properties": {
    "iso:country":"GB",
    "sg:address":"17-27 The Exchange",
    "sg:city":"Leicester",
    "sg:classifiers":[
        {
            "category":"Food & Beverages",
            "subcategory":"Supermarket",
            "type":"Retail Goods"
        }
    ],
    "sg:phone":"+44 116 278 3359",
    "sg:postcode":"LE2 9BA",
    "sg:province":"Leicestershire",
    "wof:name":"Midland Co-Operative Society",
    "wof:placetype":"venue"
},
  "geometry": {"coordinates":[-1.144784,52.591518],"type":"Point"}
}