{
  "type": "Feature",
  "properties": {
    "iso:country":"GB",
    "sg:address":"64 Kingsway",
    "sg:city":"Leeds",
    "sg:classifiers":[
        {
            "category":"Shopping",
            "subcategory":"News",
            "type":"Retail Goods"
        }
    ],
    "sg:phone":"+44 113 286 2846",
    "sg:postcode":"LS25 1DQ",
    "sg:province":"North Yorkshire",
    "sg:tags":[
        "newsagent"
    ],
    "wof:name":"S & S Sanghera",
    "wof:placetype":"venue"
},
  "geometry": {"coordinates":[-1.399972,53.79044],"type":"Point"}
}