{
  "type": "Feature",
  "properties": {
    "iso:country":"GB",
    "sg:address":"20 Leicester Road",
    "sg:city":"Wigston",
    "sg:classifiers":[
        {
            "category":"Shopping",
            "subcategory":"Discount & Variety Stores",
            "type":"Retail Goods"
        }
    ],
    "sg:phone":"+44 116 281 2524",
    "sg:postcode":"LE18 1DR",
    "sg:province":"Leicestershire",
    "sg:tags":[
        "centre"
    ],
    "wof:name":"Bestsellers",
    "wof:placetype":"venue"
},
  "geometry": {"coordinates":[-1.1066060066,52.5860786438],"type":"Point"}
}