{
  "type": "Feature",
  "properties": {
    "iso:country":"GB",
    "sg:address":"Drimvargie Rd",
    "sg:city":"Oban",
    "sg:classifiers":[
        {
            "category":"Freight",
            "type":"Transportation"
        }
    ],
    "sg:phone":"+44 1631 563389",
    "sg:postcode":"PA34 4AJ",
    "sg:province":"Argyll and Bute",
    "sg:tags":[
        "haulage",
        "road"
    ],
    "wof:name":"Blueband Motors Ltd",
    "wof:placetype":"venue"
},
  "geometry": {"coordinates":[-5.469119,56.407982],"type":"Point"}
}