{
  "type": "Feature",
  "properties": {
    "addr:full":"Unitd, Metcalf Drive, Altham Industrial Estate Accrington Lancashire BB5 5TU",
    "addr:postcode":"bb5 5tu",
    "addr:street":"Metcalf Drive;Industrial Estate",
    "iso:country":"GB",
    "sg:address":"Unitd, Metcalf Drive, Altham Industrial Estate",
    "sg:city":"Accrington",
    "sg:classifiers":[
        {
            "category":"Shopping",
            "subcategory":"Beauty & Cosmetics",
            "type":"Retail Goods"
        }
    ],
    "sg:phone":"+44 1282 683100",
    "sg:postcode":"BB5 5TU",
    "sg:province":"Lancashire",
    "sg:tags":[
        "equipment",
        "hairdressing",
        "hairdresser",
        "supply"
    ],
    "wof:name":"Sabre Europe Ltd.",
    "wof:placetype":"venue"
},
  "geometry": {"coordinates":[-2.3510799408,53.7896728516],"type":"Point"}
}