{
  "type": "Feature",
  "properties": {
    "addr:full":"6 Regent Street, Eccles Manchester Greater Manchester M30 0AP",
    "addr:housenumber":"6",
    "addr:postcode":"m30 0ap",
    "addr:street":"Regent Street",
    "iso:country":"GB",
    "sg:address":"6 Regent Street, Eccles",
    "sg:city":"Manchester",
    "sg:classifiers":[
        {
            "category":"Health Services",
            "subcategory":"Dentist",
            "type":"Services"
        }
    ],
    "sg:phone":"+44 161 707 2866",
    "sg:postcode":"M30 0AP",
    "sg:province":"Greater Manchester",
    "sg:tags":[
        "technician",
        "dental"
    ],
    "wof:name":"Malcolm Fuller",
    "wof:placetype":"venue"
},
  "geometry": {"coordinates":[-2.344437,53.482872],"type":"Point"}
}