{
  "type": "Feature",
  "properties": {
    "addr:full":"M G I Ho, 3 Monson Rd Tunbridge Wells Kent TN1 1LS",
    "addr:housenumber":"3",
    "addr:postcode":"tn1 1ls",
    "addr:street":"M;Monson Rd",
    "iso:country":"GB",
    "sg:address":"M G I Ho, 3 Monson Rd",
    "sg:city":"Tunbridge Wells",
    "sg:classifiers":[
        {
            "category":"Food & Beverages",
            "subcategory":"Liquor & Beverages",
            "type":"Retail Goods"
        }
    ],
    "sg:phone":"+44 1892 544003",
    "sg:postcode":"TN1 1LS",
    "sg:province":"Kent",
    "sg:tags":[
        "beer",
        "spirit",
        "wines"
    ],
    "wof:name":"Laurence Hayward & Partners",
    "wof:placetype":"venue"
},
  "geometry": {"coordinates":[0.2635500133,51.1333732605],"type":"Point"}
}