{
  "type": "Feature",
  "properties": {
    "iso:country":"GB",
    "sg:address":"Polkirt Hill",
    "sg:city":"St Austell",
    "sg:classifiers":[
        {
            "category":"Travel",
            "subcategory":"Hotels & Motels",
            "type":"Entertainment"
        }
    ],
    "sg:phone":"+44 1726 843249",
    "sg:postcode":"PL26 6UR",
    "sg:province":"Cornwall",
    "wof:name":"Harbour Lights Hotel The",
    "wof:placetype":"venue"
},
  "geometry": {"coordinates":[-4.793856,50.248661],"type":"Point"}
}