{
  "type": "Feature",
  "properties": {
    "iso:country":"GB",
    "sg:address":"54 Bridge Street",
    "sg:city":"Berwick-upon-tweed",
    "sg:classifiers":[
        {
            "category":"Food & Beverages",
            "subcategory":"Specialty",
            "type":"Retail Goods"
        }
    ],
    "sg:postcode":"TD15 1AQ",
    "sg:province":"Northumberland",
    "sg:tags":[
        "organic"
    ],
    "wof:name":"The Green Shop",
    "wof:placetype":"venue"
},
  "geometry": {"coordinates":[-2.004755,55.768627],"type":"Point"}
}