{
  "type": "Feature",
  "properties": {
    "addr:full":"Gilbrook Basin, Beaufort Rd Birkenhead Merseyside L41 1HE",
    "addr:postcode":"l41 1he",
    "addr:street":"Gilbrook;Beaufort Rd",
    "iso:country":"GB",
    "sg:address":"Gilbrook Basin, Beaufort Rd",
    "sg:city":"Birkenhead",
    "sg:classifiers":[
        {
            "category":"Home & Garden",
            "subcategory":"Garden Supply",
            "type":"Retail Goods"
        }
    ],
    "sg:phone":"+44 151 652 2574",
    "sg:postcode":"L41 1HE",
    "sg:province":"Merseyside",
    "sg:tags":[
        "sand",
        "gravel"
    ],
    "wof:name":"Mersey Sand Suppliers",
    "wof:placetype":"venue"
},
  "geometry": {"coordinates":[-3.0254900455,53.3925590515],"type":"Point"}
}