{
  "type": "Feature",
  "properties": {
    "iso:country":"GB",
    "sg:address":"Seamer Rd",
    "sg:city":"Scarborough",
    "sg:classifiers":[
        {
            "category":"Autos & Motor Vehicles",
            "subcategory":"Automobile Sales",
            "type":"Retail Goods"
        }
    ],
    "sg:phone":"+44 1723 501501",
    "sg:postcode":"YO12 4DH",
    "sg:province":"North Yorkshire",
    "sg:tags":[
        "car"
    ],
    "wof:name":"Polar Ford Sarborough",
    "wof:placetype":"venue"
},
  "geometry": {"coordinates":[-0.416144,54.275265],"type":"Point"}
}