{
  "type": "Feature",
  "properties": {
    "iso:country":"GB",
    "sg:address":"13 Whalley Avenue",
    "sg:city":"Sale",
    "sg:classifiers":[
        {
            "category":"Shopping",
            "subcategory":"Clothing, Apparel, & Fashions",
            "type":"Retail Goods"
        },
        {
            "category":"Manufacturing",
            "subcategory":"Paper Products",
            "type":"Manufacturing & Wholesale Goods"
        }
    ],
    "sg:phone":"+44 161 905 1869",
    "sg:postcode":"M33 2BP",
    "sg:province":"Cheshire",
    "sg:tags":[
        "clothing",
        "fabric",
        "manufacturer"
    ],
    "wof:name":"H D K Industries Ltd",
    "wof:placetype":"venue"
},
  "geometry": {"coordinates":[-2.310115,53.425312],"type":"Point"}
}