{
  "type": "Feature",
  "properties": {
    "iso:country":"GB",
    "sg:address":"18 High Street",
    "sg:city":"Newtown",
    "sg:classifiers":[
        {
            "category":"Shopping",
            "subcategory":"Luggage & Leather Goods",
            "type":"Retail Goods"
        }
    ],
    "sg:phone":"+44 1686 626665",
    "sg:postcode":"SY16 2NP",
    "sg:province":"Powys",
    "sg:tags":[
        "shop",
        "leathergoods"
    ],
    "wof:name":"Alaven Leathershop",
    "wof:placetype":"venue"
},
  "geometry": {"coordinates":[-3.316275,52.514771],"type":"Point"}
}