{
  "type": "Feature",
  "properties": {
    "addr:full":"405 Edgeware Road London Greater London W2 1BT",
    "addr:housenumber":"405",
    "addr:postcode":"w2 1bt",
    "addr:street":"Edgeware Road",
    "iso:country":"GB",
    "sg:address":"405 Edgeware Road",
    "sg:city":"London",
    "sg:classifiers":[
        {
            "category":"Food & Beverages",
            "subcategory":"Liquor & Beverages",
            "type":"Retail Goods"
        }
    ],
    "sg:postcode":"W2 1BT",
    "sg:province":"Greater London",
    "sg:tags":[
        "beer",
        "spirit",
        "wines"
    ],
    "wof:name":"Hanzel Wines",
    "wof:placetype":"venue"
},
  "geometry": {"coordinates":[-0.1748020053,51.5232429504],"type":"Point"}
}