{
  "type": "Feature",
  "properties": {
    "iso:country":"GB",
    "sg:address":"241 Ammerdown Terrace, Radstock",
    "sg:city":"Bath",
    "sg:classifiers":[
        {
            "category":"Professional",
            "subcategory":"Art Services",
            "type":"Services"
        }
    ],
    "sg:postcode":"BA3 5UG",
    "sg:province":"Somerset",
    "sg:tags":[
        "carver",
        "sculptor"
    ],
    "wof:name":"L M Dickenson Woodcarving & Sculpture",
    "wof:placetype":"venue"
},
  "geometry": {"coordinates":[-2.408921,51.279984],"type":"Point"}
}