{
  "type": "Feature",
  "properties": {
    "addr:full":"26 Kingsmead Farnborough Hampshire GU14 7SL",
    "addr:housenumber":"26",
    "addr:postcode":"gu14 7sl",
    "iso:country":"GB",
    "sg:address":"26 Kingsmead",
    "sg:city":"Farnborough",
    "sg:classifiers":[
        {
            "category":"Shopping",
            "subcategory":"Jewelry",
            "type":"Retail Goods"
        },
        {
            "category":"Shopping",
            "subcategory":"Comic Books",
            "type":"Retail Goods"
        }
    ],
    "sg:phone":"+44 1252 513165",
    "sg:postcode":"GU14 7SL",
    "sg:province":"Hampshire",
    "sg:tags":[
        "jeweller",
        "sale",
        "jewellery"
    ],
    "wof:name":"F Hinds Ltd",
    "wof:placetype":"venue"
},
  "geometry": {"coordinates":[-0.7539889812,51.2919235229],"type":"Point"}
}