{
  "type": "Feature",
  "properties": {
    "addr:full":"23 Broad Street Lyme Regis Devon DT7 3QE",
    "addr:housenumber":"23",
    "addr:postcode":"dt7 3qe",
    "addr:street":"Broad Street",
    "iso:country":"GB",
    "sg:address":"23 Broad Street",
    "sg:city":"Lyme Regis",
    "sg:classifiers":[
        {
            "category":"Shopping",
            "subcategory":"Thrift Store",
            "type":"Retail Goods"
        }
    ],
    "sg:phone":"+44 1297 445557",
    "sg:postcode":"DT7 3QE",
    "sg:province":"Devon",
    "sg:tags":[
        "shop",
        "charity"
    ],
    "wof:name":"Joseph Weld & Trimar Hospice Trust",
    "wof:placetype":"venue"
},
  "geometry": {"coordinates":[-2.935433,50.724819],"type":"Point"}
}