{
  "type": "Feature",
  "properties": {
    "addr:full":"Woodlee Newbridge City of Edinburgh EH28 8QR",
    "addr:postcode":"eh28 8qr",
    "iso:country":"GB",
    "sg:address":"Woodlee",
    "sg:city":"Newbridge",
    "sg:classifiers":[
        {
            "category":"Retail",
            "subcategory":"Auto Repair",
            "type":"Services"
        }
    ],
    "sg:phone":"+44 131 333 2725",
    "sg:postcode":"EH28 8QR",
    "sg:province":"City of Edinburgh",
    "sg:tags":[
        "bodybuilder",
        "repairer"
    ],
    "wof:name":"William Bain",
    "wof:placetype":"venue"
},
  "geometry": {"coordinates":[-3.409335,55.940845],"type":"Point"}
}