{
  "type": "Feature",
  "properties": {
    "iso:country":"GB",
    "sg:address":"63 Marylebone High Street",
    "sg:city":"London",
    "sg:classifiers":[
        {
            "category":"Health Services",
            "subcategory":"Dentist",
            "type":"Services"
        }
    ],
    "sg:phone":"+44 20 7935 0430",
    "sg:postcode":"W1U 5JD",
    "sg:province":"Greater London",
    "sg:tags":[
        "technician",
        "dental"
    ],
    "wof:name":"Terfus",
    "wof:placetype":"venue"
},
  "geometry": {"coordinates":[-0.15164,51.522141],"type":"Point"}
}