{
  "type": "Feature",
  "properties": {
    "iso:country":"GB",
    "sg:address":"Chichester College Of Technology, Avenue-de-chartres",
    "sg:city":"Chichester",
    "sg:classifiers":[
        {
            "category":"Shopping",
            "subcategory":"Books",
            "type":"Retail Goods"
        }
    ],
    "sg:phone":"+44 1243 780231",
    "sg:postcode":"PO19 1SB",
    "sg:province":"West Sussex",
    "sg:tags":[
        "bookseller"
    ],
    "wof:name":"Hammicks Bookshop",
    "wof:placetype":"venue"
},
  "geometry": {"coordinates":[-0.775429,50.836166],"type":"Point"}
}