{
  "type": "Feature",
  "properties": {
    "addr:full":"576 Old Chester Rd Birkenhead Merseyside CH42 4PF",
    "addr:housenumber":"576",
    "addr:postcode":"ch42 4pf",
    "addr:street":"Old Chester Rd",
    "iso:country":"GB",
    "sg:address":"576 Old Chester Rd",
    "sg:city":"Birkenhead",
    "sg:classifiers":[
        {
            "category":"Retail",
            "subcategory":"Laundry & Dry Cleaning",
            "type":"Services"
        }
    ],
    "sg:postcode":"CH42 4PF",
    "sg:province":"Merseyside",
    "sg:tags":[
        "alteration"
    ],
    "wof:name":"Kelson,Carol,",
    "wof:placetype":"venue"
},
  "geometry": {"coordinates":[-3.014194,53.366589],"type":"Point"}
}