{
  "type": "Feature",
  "properties": {
    "addr:full":"4 The Grove, Podsbrook Chesterfield Derbyshire S43 3JY",
    "addr:housenumber":"4",
    "addr:postcode":"s43 3jy",
    "addr:street":"The Grove Podsbrook",
    "iso:country":"GB",
    "sg:address":"4 The Grove, Podsbrook",
    "sg:city":"Chesterfield",
    "sg:classifiers":[
        {
            "category":"Government",
            "subcategory":"Post Office",
            "type":"Public Place"
        }
    ],
    "sg:postcode":"S43 3JY",
    "sg:province":"Derbyshire",
    "wof:name":"Dawson,R,",
    "wof:placetype":"venue"
},
  "geometry": {"coordinates":[-1.337242,53.258766],"type":"Point"}
}