{
  "type": "Feature",
  "properties": {
    "iso:country":"GB",
    "sg:address":"Woolfin Farm, Morchard Rd",
    "sg:city":"Crediton",
    "sg:classifiers":[
        {
            "category":"Farming",
            "subcategory":"Farm",
            "type":"Manufacturing & Wholesale Goods"
        }
    ],
    "sg:phone":"+44 1363 84379",
    "sg:postcode":"EX17 5LQ",
    "sg:province":"Devon",
    "sg:tags":[
        "mixed",
        "crop"
    ],
    "wof:name":"P.L Baskerville",
    "wof:placetype":"venue"
},
  "geometry": {"coordinates":[-3.661404,50.790836],"type":"Point"}
}