{
  "type": "Feature",
  "properties": {
    "addr:full":"2-4 Cornfield Road Eastbourne East Sussex BN21 4PJ",
    "addr:housenumber":"2-4",
    "addr:postcode":"bn21 4pj",
    "addr:street":"Cornfield Road",
    "iso:country":"GB",
    "sg:address":"2-4 Cornfield Road",
    "sg:city":"Eastbourne",
    "sg:classifiers":[
        {
            "category":"Travel",
            "subcategory":"Travel Agent",
            "type":"Entertainment"
        }
    ],
    "sg:phone":"+44 1323 720355",
    "sg:postcode":"BN21 4PJ",
    "sg:province":"East Sussex",
    "wof:name":"Going Places Leisure Travel",
    "wof:placetype":"venue"
},
  "geometry": {"coordinates":[0.283815,50.768337],"type":"Point"}
}