{
  "type": "Feature",
  "properties": {
    "addr:full":"Midland Storage, Cat & Fiddle Lane, West Hallam Derby Derbyshire DE7 6HE",
    "addr:postcode":"de7 6he",
    "addr:street":"Lane",
    "iso:country":"GB",
    "sg:address":"Midland Storage, Cat & Fiddle Lane, West Hallam",
    "sg:city":"Derby",
    "sg:classifiers":[
        {
            "category":"Freight",
            "type":"Transportation"
        }
    ],
    "sg:postcode":"DE7 6HE",
    "sg:province":"Derbyshire",
    "sg:tags":[
        "forwarders"
    ],
    "wof:name":"North Star Cargo Services Ltd.",
    "wof:placetype":"venue"
},
  "geometry": {"coordinates":[-1.3616700172,52.9611701965],"type":"Point"}
}