{
  "type": "Feature",
  "properties": {
    "addr:full":"81 Bradwell Rd, Loughton Milton Keynes Buckinghamshire MK5 8BS",
    "addr:housenumber":"81",
    "addr:postcode":"mk5 8bs",
    "addr:street":"Bradwell Rd",
    "iso:country":"GB",
    "sg:address":"81 Bradwell Rd, Loughton",
    "sg:city":"Milton Keynes",
    "sg:classifiers":[
        {
            "category":"Building & Trades",
            "subcategory":"Construction",
            "type":"Services"
        }
    ],
    "sg:phone":"+44 1908 392690",
    "sg:postcode":"MK5 8BS",
    "sg:province":"Buckinghamshire",
    "sg:tags":[
        "builder"
    ],
    "wof:name":"Wren Builders",
    "wof:placetype":"venue"
},
  "geometry": {"coordinates":[-0.7834370136,52.0325508118],"type":"Point"}
}