{
  "type": "Feature",
  "properties": {
    "addr:full":"Unit 7 Victoria Industrial Estate, Victoria Road West Hebburn Tyne and Wear NE31 1UB",
    "addr:housenumber":"unit 7;estate",
    "addr:postcode":"ne31 1ub",
    "addr:street":"Victoria Industrial;Victoria Road West",
    "iso:country":"GB",
    "sg:address":"Unit 7 Victoria Industrial Estate, Victoria Road West",
    "sg:city":"Hebburn",
    "sg:classifiers":[
        {
            "category":"Autos & Motor Vehicles",
            "subcategory":"Boat Sales",
            "type":"Retail Goods"
        }
    ],
    "sg:phone":"+44 191 483 4836",
    "sg:postcode":"NE31 1UB",
    "sg:province":"Tyne and Wear",
    "sg:tags":[
        "repair",
        "builder"
    ],
    "wof:name":"McNulty Boats Ltd.",
    "wof:placetype":"venue"
},
  "geometry": {"coordinates":[-1.526224,54.962078],"type":"Point"}
}