{
  "type": "Feature",
  "properties": {
    "addr:full":"124 Melbury Avenue Poole Dorset BH12 4EW",
    "addr:housenumber":"124",
    "addr:postcode":"bh12 4ew",
    "addr:street":"Melbury Avenue",
    "iso:country":"GB",
    "sg:address":"124 Melbury Avenue",
    "sg:city":"Poole",
    "sg:classifiers":[
        {
            "category":"Taxi",
            "type":"Transportation"
        }
    ],
    "sg:phone":"+44 1202 267961",
    "sg:postcode":"BH12 4EW",
    "sg:province":"Dorset",
    "sg:tags":[
        "mini",
        "cab"
    ],
    "wof:name":"Hillside Cars Poole",
    "wof:placetype":"venue"
},
  "geometry": {"coordinates":[-1.922706008,50.7398452759],"type":"Point"}
}