{
  "type": "Feature",
  "properties": {
    "addr:full":"Kings Pass, Thames St Kingston Upon Thames Greater London KT1 1PG",
    "addr:postcode":"kt1 1pg",
    "addr:street":"Kings Pass Thames St",
    "iso:country":"GB",
    "sg:address":"Kings Pass, Thames St",
    "sg:city":"Kingston Upon Thames",
    "sg:classifiers":[
        {
            "category":"Bars & Pubs",
            "type":"Food & Drink"
        }
    ],
    "sg:phone":"+44 20 8546 4495",
    "sg:postcode":"KT1 1PG",
    "sg:province":"Greater London",
    "sg:tags":[
        "pubs",
        "inn"
    ],
    "wof:name":"The Gazebo",
    "wof:placetype":"venue"
},
  "geometry": {"coordinates":[-0.306309998,51.409488678],"type":"Point"}
}