{
  "type": "Feature",
  "properties": {
    "addr:full":"Jubilee Hall Road Farnborough Hampshire GU14 7NN",
    "addr:postcode":"gu14 7nn",
    "addr:street":"Hall Road",
    "iso:country":"GB",
    "sg:address":"Jubilee Hall Road",
    "sg:city":"Farnborough",
    "sg:classifiers":[
        {
            "category":"Retail",
            "subcategory":"Auto Repair",
            "type":"Services"
        }
    ],
    "sg:phone":"+44 1252 546178",
    "sg:postcode":"GU14 7NN",
    "sg:province":"Hampshire",
    "sg:tags":[
        "modification",
        "garage"
    ],
    "wof:name":"Kwik-Fit 2003 Ltd.",
    "wof:placetype":"venue"
},
  "geometry": {"coordinates":[-0.7529140115,51.2964744568],"type":"Point"}
}