{
  "type": "Feature",
  "properties": {
    "addr:full":"14 Norham Close, Wideopen Newcastle-upon-tyne Northumberland NE13 7HS",
    "addr:housenumber":"14",
    "addr:postcode":"ne13 7hs",
    "addr:street":"Norham Close",
    "iso:country":"GB",
    "sg:address":"14 Norham Close, Wideopen",
    "sg:city":"Newcastle-upon-tyne",
    "sg:classifiers":[
        {
            "category":"Retail",
            "subcategory":"Driving School",
            "type":"Services"
        }
    ],
    "sg:postcode":"NE13 7HS",
    "sg:province":"Northumberland",
    "wof:name":"Castle Ward",
    "wof:placetype":"venue"
},
  "geometry": {"coordinates":[-1.638543,55.043144],"type":"Point"}
}