{
  "type": "Feature",
  "properties": {
    "addr:full":"Bank House, Highwoods Square, Highwoods Colchester Essex CO4 9SW",
    "addr:postcode":"co4 9sw",
    "addr:street":"Highwoods Square Highwoods Colchester",
    "iso:country":"GB",
    "sg:address":"Bank House, Highwoods Square, Highwoods",
    "sg:city":"Colchester",
    "sg:classifiers":[
        {
            "category":"Real Estate",
            "subcategory":"Architect",
            "type":"Services"
        }
    ],
    "sg:phone":"+44 1206 853891",
    "sg:postcode":"CO4 9SW",
    "sg:province":"Essex",
    "sg:tags":[
        "architectural"
    ],
    "wof:name":"Pjb Chartered Architects Ltd.",
    "wof:placetype":"venue"
},
  "geometry": {"coordinates":[0.9266189933,51.9143867493],"type":"Point"}
}