{
  "type": "Feature",
  "properties": {
    "addr:full":"Devenish House, London Road Ascot Berkshire SL5 9RZ",
    "addr:postcode":"sl5 9rz",
    "addr:street":"London Road",
    "iso:country":"GB",
    "sg:address":"Devenish House, London Road",
    "sg:city":"Ascot",
    "sg:classifiers":[
        {
            "category":"Building & Trades",
            "subcategory":"Construction",
            "type":"Services"
        }
    ],
    "sg:postcode":"SL5 9RZ",
    "sg:province":"Berkshire",
    "sg:tags":[
        "contractor"
    ],
    "wof:name":"Kam Construction",
    "wof:placetype":"venue"
},
  "geometry": {"coordinates":[-0.638239,51.388504],"type":"Point"}
}