{
  "type": "Feature",
  "properties": {
    "addr:full":"6 Fenn Street, Winston Stowmarket Suffolk IP14 6LD",
    "addr:housenumber":"6",
    "addr:postcode":"ip14 6ld",
    "addr:street":"Fenn Street",
    "iso:country":"GB",
    "sg:address":"6 Fenn Street, Winston",
    "sg:city":"Stowmarket",
    "sg:classifiers":[
        {
            "category":"Building & Trades",
            "subcategory":"Construction",
            "type":"Services"
        }
    ],
    "sg:phone":"+44 1728 628588",
    "sg:postcode":"IP14 6LD",
    "sg:province":"Suffolk",
    "sg:tags":[
        "conservation",
        "builder",
        "craft",
        "thatching"
    ],
    "wof:name":"Martin J Edmonds",
    "wof:placetype":"venue"
},
  "geometry": {"coordinates":[1.1927700043,52.2095184326],"type":"Point"}
}