{
  "type": "Feature",
  "properties": {
    "addr:full":"Unit 3 Beddington Cross, 136-138 Beddington Farm R Croydon Surrey CR0 4XH",
    "addr:housenumber":"unit 3",
    "addr:postcode":"136-138;cr0 4xh",
    "addr:street":"Beddington Cross;Beddington Farm R",
    "iso:country":"GB",
    "sg:address":"Unit 3 Beddington Cross, 136-138 Beddington Farm R",
    "sg:city":"Croydon",
    "sg:classifiers":[
        {
            "category":"Building & Trades",
            "subcategory":"Construction",
            "type":"Services"
        },
        {
            "category":"Building & Trades",
            "subcategory":"Electrical",
            "type":"Services"
        }
    ],
    "sg:phone":"+44 20 8665 8500",
    "sg:postcode":"CR0 4XH",
    "sg:province":"Surrey",
    "sg:tags":[
        "consultant",
        "lighting",
        "design"
    ],
    "wof:name":"Fourth Phase (London) Ltd.",
    "wof:placetype":"venue"
},
  "geometry": {"coordinates":[-0.125764,51.367664],"type":"Point"}
}