{
  "type": "Feature",
  "properties": {
    "addr:full":"76 Main Street, Garforth Leeds North Yorkshire LS25 1AA",
    "addr:housenumber":"76",
    "addr:postcode":"ls25 1aa",
    "addr:street":"Main Street",
    "iso:country":"GB",
    "sg:address":"76 Main Street, Garforth",
    "sg:city":"Leeds",
    "sg:classifiers":[
        {
            "category":"Home & Garden",
            "subcategory":"Hardware",
            "type":"Retail Goods"
        }
    ],
    "sg:phone":"+44 113 286 0211",
    "sg:postcode":"LS25 1AA",
    "sg:province":"North Yorkshire",
    "sg:tags":[
        "retailer",
        "diy"
    ],
    "wof:name":"Pease of Garforth",
    "wof:placetype":"venue"
},
  "geometry": {"coordinates":[-1.3882889748,53.7952423096],"type":"Point"}
}