{
  "type": "Feature",
  "properties": {
    "addr:full":"Hillside Farm, Combeinteignhead Newton Abbot Devon TQ12 4RG",
    "addr:postcode":"tq12 4rg",
    "iso:country":"GB",
    "sg:address":"Hillside Farm, Combeinteignhead",
    "sg:city":"Newton Abbot",
    "sg:classifiers":[
        {
            "category":"Farming",
            "subcategory":"Livestock Farm",
            "type":"Manufacturing & Wholesale Goods"
        }
    ],
    "sg:phone":"+44 1626 873272",
    "sg:postcode":"TQ12 4RG",
    "sg:province":"Devon",
    "sg:tags":[
        "others"
    ],
    "wof:name":"C G Chudley",
    "wof:placetype":"venue"
},
  "geometry": {"coordinates":[-3.5510509014,50.5345077515],"type":"Point"}
}