{
  "type": "Feature",
  "properties": {
    "addr:full":"22 Parkwood Street, Thwaites Keighley West Yorkshire BD21 4NG",
    "addr:housenumber":"22",
    "addr:postcode":"bd21 4ng",
    "addr:street":"Parkwood Street",
    "iso:country":"GB",
    "sg:address":"22 Parkwood Street, Thwaites",
    "sg:city":"Keighley",
    "sg:classifiers":[
        {
            "category":"Bars & Pubs",
            "type":"Food & Drink"
        },
        {
            "category":"Community Center",
            "subcategory":"Social",
            "type":"Public Place"
        }
    ],
    "sg:phone":"+44 1535 608684",
    "sg:postcode":"BD21 4NG",
    "sg:province":"West Yorkshire",
    "sg:tags":[
        "pubs",
        "house",
        "inn",
        "activity"
    ],
    "wof:name":"Shoulder of Mutton",
    "wof:placetype":"venue"
},
  "geometry": {"coordinates":[-1.903828,53.863796],"type":"Point"}
}