{
  "type": "Feature",
  "properties": {
    "iso:country":"GB",
    "sg:address":"161 Foxglove Road",
    "sg:city":"Sheffield",
    "sg:classifiers":[
        {
            "category":"Retail",
            "subcategory":"Driving School",
            "type":"Services"
        }
    ],
    "sg:phone":"+44 114 243 4721",
    "sg:postcode":"S5 6FP",
    "sg:province":"South Yorkshire",
    "wof:name":"MIKE SHEEDY",
    "wof:placetype":"venue"
},
  "geometry": {"coordinates":[-1.441813,53.419743],"type":"Point"}
}