{
  "type": "Feature",
  "properties": {
    "iso:country":"GB",
    "sg:address":"24 Wellith Lane",
    "sg:city":"Rochdale",
    "sg:classifiers":[
        {
            "category":"Personal",
            "subcategory":"Barber",
            "type":"Services"
        }
    ],
    "sg:postcode":"OL11 1BB",
    "sg:province":"Lancashire",
    "sg:tags":[
        "men's",
        "hairdresser"
    ],
    "wof:name":"Tony's Haircuttery",
    "wof:placetype":"venue"
},
  "geometry": {"coordinates":[-2.148862,53.605774],"type":"Point"}
}