{
  "type": "Feature",
  "properties": {
    "iso:country":"GB",
    "sg:address":"Church Road, Tonteg",
    "sg:city":"Pontypridd",
    "sg:classifiers":[
        {
            "category":"Health Services",
            "subcategory":"Nursing And Care Facility",
            "type":"Services"
        }
    ],
    "sg:phone":"+44 1443 207915",
    "sg:postcode":"CF38 1HE",
    "sg:province":"Rhondda, Cynon, Taff",
    "sg:tags":[
        "home"
    ],
    "wof:name":"Olcote House",
    "wof:placetype":"venue"
},
  "geometry": {"coordinates":[-3.307702,51.571564],"type":"Point"}
}