{
  "type": "Feature",
  "properties": {
    "iso:country":"GB",
    "sg:address":"41 - 43 Cricklewood Bdwy",
    "sg:city":"London",
    "sg:classifiers":[
        {
            "category":"Food & Beverages",
            "subcategory":"Supermarket",
            "type":"Retail Goods"
        }
    ],
    "sg:phone":"+44 20 8452 2789",
    "sg:postcode":"NW2 3JX",
    "sg:province":"Greater London",
    "wof:name":"Modern Food Store",
    "wof:placetype":"venue"
},
  "geometry": {"coordinates":[-0.211595,51.553444],"type":"Point"}
}