{
  "type": "Feature",
  "properties": {
    "addr:full":"Unit 4 St Johns Business Centre Chesterfield Derbyshire S41 8TB",
    "addr:housenumber":"unit 4;business centre",
    "addr:postcode":"s41 8tb",
    "addr:street":"St Johns",
    "iso:country":"GB",
    "sg:address":"Unit 4 St Johns Business Centre",
    "sg:city":"Chesterfield",
    "sg:classifiers":[
        {
            "category":"Organizations",
            "subcategory":"Labor Organization",
            "type":"Services"
        }
    ],
    "sg:postcode":"S41 8TB",
    "sg:province":"Derbyshire",
    "sg:tags":[
        "equipment",
        "paging",
        "system"
    ],
    "wof:name":"Clofield Ltd.",
    "wof:placetype":"venue"
},
  "geometry": {"coordinates":[-1.436309,53.258755],"type":"Point"}
}