{
  "type": "Feature",
  "properties": {
    "addr:full":"138 Kings Road Kingston-upon-thames Greater London KT2 5HU",
    "addr:housenumber":"138",
    "addr:postcode":"kt2 5hu",
    "addr:street":"Kings Road",
    "iso:country":"GB",
    "sg:address":"138 Kings Road",
    "sg:city":"Kingston-upon-thames",
    "sg:classifiers":[
        {
            "category":"Building & Trades",
            "subcategory":"Landscaping Services",
            "type":"Services"
        }
    ],
    "sg:postcode":"KT2 5HU",
    "sg:province":"Greater London",
    "sg:tags":[
        "horticultural",
        "consultant"
    ],
    "wof:name":"Greenfingers Recyling Ltd.",
    "wof:placetype":"venue"
},
  "geometry": {"coordinates":[-0.295314014,51.4188156128],"type":"Point"}
}