{
  "type": "Feature",
  "properties": {
    "addr:full":"12 Station Row Sittingbourne Kent ME9 9EA",
    "addr:housenumber":"12",
    "addr:postcode":"me9 9ea",
    "addr:street":"Station Row",
    "iso:country":"GB",
    "sg:address":"12 Station Row",
    "sg:city":"Sittingbourne",
    "sg:classifiers":[
        {
            "category":"Building & Trades",
            "subcategory":"Construction",
            "type":"Services"
        }
    ],
    "sg:phone":"+44 1795 522469",
    "sg:postcode":"ME9 9EA",
    "sg:province":"Kent",
    "sg:tags":[
        "roofing"
    ],
    "wof:name":"J Bell-Reeves",
    "wof:placetype":"venue"
},
  "geometry": {"coordinates":[0.8026080132,51.3278808594],"type":"Point"}
}