{
  "type": "Feature",
  "properties": {
    "addr:full":"Office, Hilperton Rd Trowbridge Wiltshire BA14 7JG",
    "addr:postcode":"ba14 7jg",
    "addr:street":"Hilperton Rd",
    "iso:country":"GB",
    "sg:address":"Office, Hilperton Rd",
    "sg:city":"Trowbridge",
    "sg:classifiers":[
        {
            "category":"Social Services",
            "subcategory":"Retirement Home",
            "type":"Services"
        }
    ],
    "sg:phone":"+44 1225 752018",
    "sg:postcode":"BA14 7JG",
    "sg:province":"Wiltshire",
    "sg:tags":[
        "residential",
        "care"
    ],
    "wof:name":"Paddocks Old Peoples Home The",
    "wof:placetype":"venue"
},
  "geometry": {"coordinates":[-2.208374,51.315342],"type":"Point"}
}