{
  "type": "Feature",
  "properties": {
    "iso:country":"GB",
    "sg:address":"87 London Road, Marks Tey",
    "sg:city":"Colchester",
    "sg:classifiers":[
        {
            "category":"Food & Beverages",
            "subcategory":"Meat & Fish",
            "type":"Retail Goods"
        }
    ],
    "sg:postcode":"CO6 1EB",
    "sg:province":"Essex",
    "sg:tags":[
        "butcher"
    ],
    "wof:name":"A Willshier & Son",
    "wof:placetype":"venue"
},
  "geometry": {"coordinates":[0.799616,51.880341],"type":"Point"}
}