{
  "type": "Feature",
  "properties": {
    "addr:full":"6 Athenaeum Road London Greater London N20 9AE",
    "addr:housenumber":"6",
    "addr:postcode":"n20 9ae",
    "addr:street":"Athenaeum Road",
    "iso:country":"GB",
    "sg:address":"6 Athenaeum Road",
    "sg:city":"London",
    "sg:classifiers":[
        {
            "category":"Community Center",
            "type":"Public Place"
        }
    ],
    "sg:phone":"+44 20 8445 3557",
    "sg:postcode":"N20 9AE",
    "sg:province":"Greater London",
    "sg:tags":[
        "centre"
    ],
    "wof:name":"St. Mary Magdalen S Community Centre",
    "wof:placetype":"venue"
},
  "geometry": {"coordinates":[-0.173385,51.631397],"type":"Point"}
}