{
  "type": "Feature",
  "properties": {
    "addr:full":"36 Booth Street Ashton Under Lyne Greater Manchester OL6 7LB",
    "addr:housenumber":"36",
    "addr:postcode":"ol6 7lb",
    "addr:street":"Booth Street;Under Lyne",
    "iso:country":"GB",
    "sg:address":"36 Booth Street",
    "sg:city":"Ashton Under Lyne",
    "sg:classifiers":[
        {
            "category":"Professional",
            "subcategory":"Business Services",
            "type":"Services"
        }
    ],
    "sg:phone":"+44 161 343 2260",
    "sg:postcode":"OL6 7LB",
    "sg:province":"Greater Manchester",
    "sg:tags":[
        "import",
        "export",
        "agent"
    ],
    "wof:name":"Living Jewel Aquarium & Aviaries",
    "wof:placetype":"venue"
},
  "geometry": {"coordinates":[-2.0959041119,53.4874763489],"type":"Point"}
}