{
  "type": "Feature",
  "properties": {
    "addr:full":"Goodmayes Hospital, Barley Lane Ilford Essex IG3 8YB",
    "addr:postcode":"ig3 8yb",
    "addr:street":"Barley Lane",
    "iso:country":"GB",
    "sg:address":"Goodmayes Hospital, Barley Lane",
    "sg:city":"Ilford",
    "sg:classifiers":[
        {
            "category":"Health Services",
            "subcategory":"Hospital",
            "type":"Services"
        }
    ],
    "sg:phone":"+44 20 8983 8000",
    "sg:postcode":"IG3 8YB",
    "sg:province":"Essex",
    "wof:name":"North East London Mental Health Nhs Trust",
    "wof:placetype":"venue"
},
  "geometry": {"coordinates":[0.1091559976,51.5657997131],"type":"Point"}
}