{
  "type": "Feature",
  "properties": {
    "addr:full":"Unit 35c Vale Business Park, Llandow Cowbridge The Vale of Glamorgan CF71 7PF",
    "addr:housenumber":"unit 35c",
    "addr:postcode":"cf71 7pf",
    "addr:street":"Vale Business Park;Vale",
    "iso:country":"GB",
    "sg:address":"Unit 35c Vale Business Park, Llandow",
    "sg:city":"Cowbridge",
    "sg:classifiers":[
        {
            "category":"Home & Garden",
            "subcategory":"Carpets & Floor Coverings",
            "type":"Retail Goods"
        }
    ],
    "sg:phone":"+44 1446 774028",
    "sg:postcode":"CF71 7PF",
    "sg:province":"The Vale of Glamorgan",
    "sg:tags":[
        "rubber",
        "plastic"
    ],
    "wof:name":"A Littlejohn Ltd.",
    "wof:placetype":"venue"
},
  "geometry": {"coordinates":[-3.4991500378,51.4403686523],"type":"Point"}
}