{
  "type": "Feature",
  "properties": {
    "iso:country":"GB",
    "sg:address":"The Hollies, College Lane",
    "sg:city":"Tarporley",
    "sg:classifiers":[
        {
            "category":"Professional",
            "subcategory":"Printing & Photocopies",
            "type":"Services"
        }
    ],
    "sg:phone":"+44 1829 260420",
    "sg:postcode":"CW6 9PQ",
    "sg:province":"Cheshire",
    "sg:tags":[
        "printer"
    ],
    "wof:name":"Rubell Print Ltd.",
    "wof:placetype":"venue"
},
  "geometry": {"coordinates":[-2.605924,53.163754],"type":"Point"}
}