{
  "type": "Feature",
  "properties": {
    "addr:full":"26a Northenden Road Sale Cheshire M33 3BR",
    "addr:housenumber":"26a",
    "addr:postcode":"m33 3br",
    "addr:street":"Northenden Road",
    "iso:country":"GB",
    "sg:address":"26a Northenden Road",
    "sg:city":"Sale",
    "sg:classifiers":[
        {
            "category":"Professional",
            "subcategory":"Accounting & Tax Preparation",
            "type":"Services"
        }
    ],
    "sg:phone":"+44 161 969 7070",
    "sg:postcode":"M33 3BR",
    "sg:province":"Cheshire",
    "sg:tags":[
        "accountant"
    ],
    "wof:name":"Webb & Davis",
    "wof:placetype":"venue"
},
  "geometry": {"coordinates":[-2.316533,53.423794],"type":"Point"}
}