{
  "type": "Feature",
  "properties": {
    "iso:country":"GB",
    "sg:address":"Manchester Rd",
    "sg:city":"London",
    "sg:classifiers":[
        {
            "category":"Cafe",
            "type":"Food & Drink"
        }
    ],
    "sg:postcode":"E14 3BE",
    "sg:province":"Greater London",
    "sg:tags":[
        "tea",
        "room"
    ],
    "wof:name":"Ricco Cafes",
    "wof:placetype":"venue"
},
  "geometry": {"coordinates":[-0.009509,51.4983711243],"type":"Point"}
}