{
  "type": "Feature",
  "properties": {
    "addr:full":"Limes Farm, Main Road, Ratcliffe Culey Atherstone Leicestershire CV9 3PD",
    "addr:postcode":"cv9 3pd",
    "addr:street":"Main Road",
    "iso:country":"GB",
    "sg:address":"Limes Farm, Main Road, Ratcliffe Culey",
    "sg:city":"Atherstone",
    "sg:classifiers":[
        {
            "category":"Farming",
            "subcategory":"Livestock Farm",
            "type":"Manufacturing & Wholesale Goods"
        },
        {
            "category":"Farming",
            "subcategory":"Farm",
            "type":"Manufacturing & Wholesale Goods"
        }
    ],
    "sg:phone":"+44 1827 720123",
    "sg:postcode":"CV9 3PD",
    "sg:province":"Leicestershire",
    "sg:tags":[
        "mixed",
        "others"
    ],
    "wof:name":"Peter Garland",
    "wof:placetype":"venue"
},
  "geometry": {"coordinates":[-1.519489,52.592979],"type":"Point"}
}