{
  "type": "Feature",
  "properties": {
    "addr:full":"74a Chelford Road Macclesfield Cheshire SK10 3LQ",
    "addr:housenumber":"74a",
    "addr:postcode":"sk10 3lq",
    "addr:street":"Chelford Road",
    "iso:country":"GB",
    "sg:address":"74a Chelford Road",
    "sg:city":"Macclesfield",
    "sg:classifiers":[
        {
            "category":"Professional",
            "subcategory":"Art Services",
            "type":"Services"
        }
    ],
    "sg:phone":"+44 1625 425349",
    "sg:postcode":"SK10 3LQ",
    "sg:province":"Cheshire",
    "sg:tags":[
        "picture",
        "framing"
    ],
    "wof:name":"Frame Art",
    "wof:placetype":"venue"
},
  "geometry": {"coordinates":[-2.16176,53.259289],"type":"Point"}
}