{
  "type": "Feature",
  "properties": {
    "addr:full":"16 Imeary Street South Shields Tyne and Wear NE33 4EG",
    "addr:housenumber":"16",
    "addr:postcode":"ne33 4eg",
    "addr:street":"Imeary Street",
    "iso:country":"GB",
    "sg:address":"16 Imeary Street",
    "sg:city":"South Shields",
    "sg:classifiers":[
        {
            "category":"Personal",
            "subcategory":"Beauty Salon",
            "type":"Services"
        },
        {
            "category":"Personal",
            "subcategory":"Barber",
            "type":"Services"
        }
    ],
    "sg:phone":"+44 191 454 5282",
    "sg:postcode":"NE33 4EG",
    "sg:province":"Tyne and Wear",
    "sg:tags":[
        "unisex",
        "hairdresser"
    ],
    "wof:name":"Headstart",
    "wof:placetype":"venue"
},
  "geometry": {"coordinates":[-1.4242110252,54.9871520996],"type":"Point"}
}