{
  "type": "Feature",
  "properties": {
    "addr:full":"29 Fleet Road Farnborough Hampshire GU14 9RB",
    "addr:housenumber":"29",
    "addr:postcode":"gu14 9rb",
    "addr:street":"Fleet Road",
    "iso:country":"GB",
    "sg:address":"29 Fleet Road",
    "sg:city":"Farnborough",
    "sg:classifiers":[
        {
            "category":"Home & Garden",
            "subcategory":"Home Furnishings",
            "type":"Retail Goods"
        },
        {
            "category":"Building & Trades",
            "subcategory":"Construction",
            "type":"Services"
        }
    ],
    "sg:phone":"+44 1252 373840",
    "sg:postcode":"GU14 9RB",
    "sg:province":"Hampshire",
    "sg:tags":[
        "furnishers",
        "planner",
        "joiner",
        "carpenter",
        "kitchen"
    ],
    "wof:name":"A J Interiors",
    "wof:placetype":"venue"
},
  "geometry": {"coordinates":[-0.780208,51.295414],"type":"Point"}
}