{
  "type": "Feature",
  "properties": {
    "iso:country":"GB",
    "sg:address":"4 Montana Road, Kesgrave",
    "sg:city":"Ipswich",
    "sg:classifiers":[
        {
            "category":"Personal",
            "subcategory":"Beauty Salon",
            "type":"Services"
        }
    ],
    "sg:phone":"+44 1473 623357",
    "sg:postcode":"IP5 7ER",
    "sg:province":"Suffolk",
    "sg:tags":[
        "unisex",
        "hairdresser"
    ],
    "wof:name":"House of Hair",
    "wof:placetype":"venue"
},
  "geometry": {"coordinates":[1.240530014,52.0664482117],"type":"Point"}
}