{
  "type": "Feature",
  "properties": {
    "addr:full":"64 Aviemore Drive, Fearnhead Warrington Cheshire WA2 0TH",
    "addr:housenumber":"64",
    "addr:postcode":"wa2 0th",
    "addr:street":"Aviemore Drive",
    "iso:country":"GB",
    "sg:address":"64 Aviemore Drive, Fearnhead",
    "sg:city":"Warrington",
    "sg:classifiers":[
        {
            "category":"Professional",
            "subcategory":"Management & Consulting",
            "type":"Services"
        }
    ],
    "sg:phone":"+44 1925 483835",
    "sg:postcode":"WA2 0TH",
    "sg:province":"Cheshire",
    "sg:tags":[
        "consultant",
        "business"
    ],
    "wof:name":"Ince Consulting (Warrington) Ltd",
    "wof:placetype":"venue"
},
  "geometry": {"coordinates":[-2.5547270775,53.4156036377],"type":"Point"}
}