{
  "type": "Feature",
  "properties": {
    "addr:full":"330b Southern Row Ladbroke Grove Greater London W10 5AE",
    "addr:housenumber":"330b",
    "addr:postcode":"w10 5ae",
    "addr:street":"Southern Row",
    "iso:country":"GB",
    "sg:address":"330b Southern Row",
    "sg:city":"Ladbroke Grove",
    "sg:classifiers":[
        {
            "category":"Retail",
            "subcategory":"Auto Repair",
            "type":"Services"
        }
    ],
    "sg:phone":"+44 20 8969 0959",
    "sg:postcode":"W10 5AE",
    "sg:province":"Greater London",
    "sg:tags":[
        "modification",
        "garage"
    ],
    "wof:name":"O'Connells",
    "wof:placetype":"venue"
},
  "geometry": {"coordinates":[-0.2131800056,51.5247497559],"type":"Point"}
}