{
  "type": "Feature",
  "properties": {
    "addr:full":"13 Fair Street Cambridge Cambridgeshire CB1 1HA",
    "addr:housenumber":"13",
    "addr:postcode":"cb1 1ha",
    "addr:street":"Fair Street",
    "iso:country":"GB",
    "sg:address":"13 Fair Street",
    "sg:city":"Cambridge",
    "sg:classifiers":[
        {
            "category":"Professional",
            "subcategory":"Art Services",
            "type":"Services"
        }
    ],
    "sg:postcode":"CB1 1HA",
    "sg:province":"Cambridgeshire",
    "sg:tags":[
        "framing"
    ],
    "wof:name":"Nobby & I",
    "wof:placetype":"venue"
},
  "geometry": {"coordinates":[0.129362,52.207573],"type":"Point"}
}