{
  "type": "Feature",
  "properties": {
    "iso:country":"GB",
    "sg:address":"37 Harwill App, Churwell, Morley",
    "sg:city":"Leeds",
    "sg:classifiers":[
        {
            "category":"Farming",
            "subcategory":"Farm",
            "type":"Manufacturing & Wholesale Goods"
        }
    ],
    "sg:phone":"+44 113 252 2307",
    "sg:postcode":"LS27 7QW",
    "sg:province":"West Yorkshire",
    "sg:tags":[
        "agricultural"
    ],
    "wof:name":"Johnstones Pressure Washers",
    "wof:placetype":"venue"
},
  "geometry": {"coordinates":[-1.586605,53.759583],"type":"Point"}
}