{
  "type": "Feature",
  "properties": {
    "addr:full":"91 Canterbury Rd Croydon Surrey CR0 3HH",
    "addr:housenumber":"91",
    "addr:postcode":"cr0 3hh",
    "addr:street":"Canterbury Rd",
    "iso:country":"GB",
    "sg:address":"91 Canterbury Rd",
    "sg:city":"Croydon",
    "sg:classifiers":[
        {
            "category":"Retail",
            "subcategory":"Auto Repair",
            "type":"Services"
        }
    ],
    "sg:phone":"+44 20 8684 2291",
    "sg:postcode":"CR0 3HH",
    "sg:province":"Surrey",
    "sg:tags":[
        "body",
        "car"
    ],
    "wof:name":"Hyundai (Croydon)",
    "wof:placetype":"venue"
},
  "geometry": {"coordinates":[-0.116403,51.385456],"type":"Point"}
}