{
  "type": "Feature",
  "properties": {
    "iso:country":"GB",
    "sg:address":"Boon Hill Road, Bignall End",
    "sg:city":"Stoke-on-trent",
    "sg:classifiers":[
        {
            "category":"Arena",
            "subcategory":"Sports Club",
            "type":"Entertainment"
        }
    ],
    "sg:phone":"+44 1782 720514",
    "sg:postcode":"ST7 8LA",
    "sg:province":"Cheshire",
    "wof:name":"Bignall End Cricket Club",
    "wof:placetype":"venue"
},
  "geometry": {"coordinates":[-2.285524,53.053299],"type":"Point"}
}