{
  "type": "Feature",
  "properties": {
    "iso:country":"GB",
    "sg:address":"7a Ashley Road",
    "sg:city":"Epsom",
    "sg:classifiers":[
        {
            "category":"Professional",
            "subcategory":"Lawyer & Legal Services",
            "type":"Services"
        }
    ],
    "sg:phone":"+44 1372 729533",
    "sg:postcode":"KT18 5AQ",
    "sg:province":"Surrey",
    "sg:tags":[
        "solicitor"
    ],
    "wof:name":"Teresa Evans Solicitor",
    "wof:placetype":"venue"
},
  "geometry": {"coordinates":[-0.2666510046,51.3325767517],"type":"Point"}
}