{
  "type": "Feature",
  "properties": {
    "iso:country":"GB",
    "sg:address":"8 Station Road",
    "sg:city":"Gillingham",
    "sg:classifiers":[
        {
            "category":"Shopping",
            "type":"Retail Goods"
        }
    ],
    "sg:phone":"+44 1634 374676",
    "sg:postcode":"ME8 7PH",
    "sg:province":"Kent",
    "sg:tags":[
        "part",
        "accessory"
    ],
    "wof:name":"Amrit Wholesale Supplies",
    "wof:placetype":"venue"
},
  "geometry": {"coordinates":[0.6088240147,51.3634223938],"type":"Point"}
}