{
  "type": "Feature",
  "properties": {
    "iso:country":"GB",
    "sg:address":"Inglewhite Road",
    "sg:city":"Preston",
    "sg:classifiers":[
        {
            "category":"Retail",
            "subcategory":"Auto Repair",
            "type":"Services"
        }
    ],
    "sg:postcode":"PR3 2DB",
    "sg:province":"Lancashire",
    "sg:tags":[
        "modification",
        "garage"
    ],
    "wof:name":"Belmont Garage",
    "wof:placetype":"venue"
},
  "geometry": {"coordinates":[-2.682599,53.852634],"type":"Point"}
}