{
  "type": "Feature",
  "properties": {
    "addr:full":"64 Blackwatch Road Coventry Warwickshire CV6 3GT",
    "addr:housenumber":"64",
    "addr:postcode":"cv6 3gt",
    "addr:street":"Blackwatch Road",
    "iso:country":"GB",
    "sg:address":"64 Blackwatch Road",
    "sg:city":"Coventry",
    "sg:classifiers":[
        {
            "category":"Education",
            "subcategory":"University",
            "type":"Public Place"
        }
    ],
    "sg:phone":"+44 24 7659 9247",
    "sg:postcode":"CV6 3GT",
    "sg:province":"Warwickshire",
    "sg:tags":[
        "higher"
    ],
    "wof:name":"G D Gilbert",
    "wof:placetype":"venue"
},
  "geometry": {"coordinates":[-1.512685,52.432312],"type":"Point"}
}