{
  "type": "Feature",
  "properties": {
    "addr:full":"4 Dewhirst Rd Rochdale Lancashire OL12 0AG",
    "addr:housenumber":"4",
    "addr:postcode":"ol12 0ag",
    "addr:street":"Dewhirst Rd",
    "iso:country":"GB",
    "sg:address":"4 Dewhirst Rd",
    "sg:city":"Rochdale",
    "sg:classifiers":[
        {
            "category":"Food & Beverages",
            "subcategory":"Liquor & Beverages",
            "type":"Retail Goods"
        }
    ],
    "sg:postcode":"OL12 0AG",
    "sg:province":"Lancashire",
    "sg:tags":[
        "beer",
        "spirit",
        "wines"
    ],
    "wof:name":"Syke Off-Licence",
    "wof:placetype":"venue"
},
  "geometry": {"coordinates":[-2.151711,53.629669],"type":"Point"}
}