{
  "type": "Feature",
  "properties": {
    "addr:full":"3 Weston La Totnes Devon TQ9 5UN",
    "addr:housenumber":"3",
    "addr:postcode":"tq9 5un",
    "addr:street":"Weston La Totnes",
    "iso:country":"GB",
    "sg:address":"3 Weston La",
    "sg:city":"Totnes",
    "sg:classifiers":[
        {
            "category":"Professional",
            "type":"Services"
        }
    ],
    "sg:phone":"+44 1803 867591",
    "sg:postcode":"TQ9 5UN",
    "sg:province":"Devon",
    "sg:tags":[
        "reflexologists"
    ],
    "wof:name":"Vaughan Janet",
    "wof:placetype":"venue"
},
  "geometry": {"coordinates":[-3.6742780209,50.427696228],"type":"Point"}
}