{
  "type": "Feature",
  "properties": {
    "iso:country":"GB",
    "sg:address":"St Davids Way, Bermuda Park Industrial Estate",
    "sg:city":"Nuneaton",
    "sg:classifiers":[
        {
            "category":"Fast Food",
            "type":"Food & Drink"
        }
    ],
    "sg:postcode":"CV10 7SD",
    "sg:province":"Leicestershire",
    "sg:tags":[
        "away",
        "take"
    ],
    "wof:name":"McDonald's Restaurants",
    "wof:placetype":"venue"
},
  "geometry": {"coordinates":[-1.474476,52.49847],"type":"Point"}
}