{
  "type": "Feature",
  "properties": {
    "iso:country":"GB",
    "sg:address":"The Gemini Building, Houghton Hall Park, Houghton Regis",
    "sg:city":"Dunstable",
    "sg:classifiers":[
        {
            "category":"Shopping",
            "subcategory":"Computers & Home Electronics",
            "type":"Retail Goods"
        },
        {
            "category":"Professional",
            "subcategory":"Computer Services",
            "type":"Services"
        }
    ],
    "sg:phone":"+44 1582 868621",
    "sg:postcode":"LU5 5GB",
    "sg:province":"Bedfordshire",
    "sg:tags":[
        "software",
        "sales",
        "system"
    ],
    "wof:name":"Gemini Consultants Ltd",
    "wof:placetype":"venue"
},
  "geometry": {"coordinates":[-0.515774,51.905121],"type":"Point"}
}