{
  "type": "Feature",
  "properties": {
    "iso:country":"GB",
    "sg:address":"58 High Street, Sawston",
    "sg:city":"Cambridge",
    "sg:classifiers":[
        {
            "category":"Food & Beverages",
            "subcategory":"Meat & Fish",
            "type":"Retail Goods"
        }
    ],
    "sg:phone":"+44 1223 833223",
    "sg:postcode":"CB2 4BG",
    "sg:province":"Cambridgeshire",
    "sg:tags":[
        "butcher"
    ],
    "wof:name":"B Searle",
    "wof:placetype":"venue"
},
  "geometry": {"coordinates":[0.169621,52.122128],"type":"Point"}
}