{
  "type": "Feature",
  "properties": {
    "addr:full":"31 Freemasons Road London Greater London E16 3AR",
    "addr:housenumber":"31",
    "addr:postcode":"e16 3ar",
    "addr:street":"Freemasons Road",
    "iso:country":"GB",
    "sg:address":"31 Freemasons Road",
    "sg:city":"London",
    "sg:classifiers":[
        {
            "category":"Food & Beverages",
            "subcategory":"Fruits & Vegetables",
            "type":"Retail Goods"
        }
    ],
    "sg:phone":"+44 20 7476 1174",
    "sg:postcode":"E16 3AR",
    "sg:province":"Greater London",
    "sg:tags":[
        "greengrocer"
    ],
    "wof:name":"Ladlow Fruiterers",
    "wof:placetype":"venue"
},
  "geometry": {"coordinates":[0.025452,51.511059],"type":"Point"}
}