{
  "type": "Feature",
  "properties": {
    "addr:full":"Fairview Farm, Little Reedness Goole East Riding of Yorkshire DN14 8HQ",
    "addr:housenumber":"little reedness",
    "addr:postcode":"dn14 8hq",
    "iso:country":"GB",
    "sg:address":"Fairview Farm, Little Reedness",
    "sg:city":"Goole",
    "sg:classifiers":[
        {
            "category":"Building & Trades",
            "subcategory":"Construction",
            "type":"Services"
        }
    ],
    "sg:phone":"+44 1405 704475",
    "sg:postcode":"DN14 8HQ",
    "sg:province":"East Riding of Yorkshire",
    "sg:tags":[
        "builder"
    ],
    "wof:name":"D T Walker Building Contractors",
    "wof:placetype":"venue"
},
  "geometry": {"coordinates":[-0.780705,53.695141],"type":"Point"}
}