{
  "type": "Feature",
  "properties": {
    "addr:full":"Unit 1032, Whitgift Centre Croydon Surrey CR0 1UU",
    "addr:housenumber":"unit 1032",
    "addr:postcode":"cr0 1uu",
    "addr:street":"Whitgift Centre",
    "iso:country":"GB",
    "sg:address":"Unit 1032, Whitgift Centre",
    "sg:city":"Croydon",
    "sg:classifiers":[
        {
            "category":"Shopping",
            "subcategory":"Gifts & Souvenirs",
            "type":"Retail Goods"
        }
    ],
    "sg:phone":"+44 20 8680 3428",
    "sg:postcode":"CR0 1UU",
    "sg:province":"Surrey",
    "sg:tags":[
        "shop"
    ],
    "wof:name":"Burning Desires",
    "wof:placetype":"venue"
},
  "geometry": {"coordinates":[-0.097916998,51.3748893738],"type":"Point"}
}