{
  "type": "Feature",
  "properties": {
    "addr:full":"Tower Street Dudley West Midlands DY1 1NA",
    "addr:postcode":"dy1 1na",
    "addr:street":"Tower Street",
    "iso:country":"GB",
    "sg:address":"Tower Street",
    "sg:city":"Dudley",
    "sg:classifiers":[
        {
            "category":"Government",
            "subcategory":"Fire Station",
            "type":"Public Place"
        }
    ],
    "sg:phone":"+44 1384 253611",
    "sg:postcode":"DY1 1NA",
    "sg:province":"West Midlands",
    "wof:name":"West Midlands Fire Service",
    "wof:placetype":"venue"
},
  "geometry": {"coordinates":[-2.081834,52.512653],"type":"Point"}
}