{
  "type": "Feature",
  "properties": {
    "addr:full":"328 Kilburn High Road London Greater London NW6 2QN",
    "addr:housenumber":"328",
    "addr:postcode":"nw6 2qn",
    "addr:street":"Kilburn High Road",
    "iso:country":"GB",
    "sg:address":"328 Kilburn High Road",
    "sg:city":"London",
    "sg:classifiers":[
        {
            "category":"Personal",
            "subcategory":"Beauty Salon",
            "type":"Services"
        }
    ],
    "sg:phone":"+44 20 7328 0226",
    "sg:postcode":"NW6 2QN",
    "sg:province":"Greater London",
    "sg:tags":[
        "unisex",
        "hairdresser"
    ],
    "wof:name":"Roger & Francis",
    "wof:placetype":"venue"
},
  "geometry": {"coordinates":[-0.2017460018,51.545337677],"type":"Point"}
}