{
  "type": "Feature",
  "properties": {
    "iso:country":"GB",
    "sg:address":"Wessington Quay Ind Est, Crown Rd, Low Southwick",
    "sg:city":"Sunderland",
    "sg:classifiers":[
        {
            "category":"Government",
            "subcategory":"Department Of Motor Vehicles",
            "type":"Public Place"
        }
    ],
    "sg:phone":"+44 191 548 5577",
    "sg:postcode":"SR5 2BS",
    "sg:province":"Tyne and Wear",
    "sg:tags":[
        "inspection"
    ],
    "wof:name":"Riverside MOT Centre",
    "wof:placetype":"venue"
},
  "geometry": {"coordinates":[-1.406784,54.918163],"type":"Point"}
}