{
  "type": "Feature",
  "properties": {
    "addr:full":"Warrens Cottage, Bridge St Fareham Hampshire PO17 5JF",
    "addr:postcode":"po17 5jf",
    "addr:street":"Bridge St",
    "iso:country":"GB",
    "sg:address":"Warrens Cottage, Bridge St",
    "sg:city":"Fareham",
    "sg:classifiers":[
        {
            "category":"Professional",
            "subcategory":"Computer Services",
            "type":"Services"
        }
    ],
    "sg:phone":"+44 1329 835818",
    "sg:postcode":"PO17 5JF",
    "sg:province":"Hampshire",
    "sg:tags":[
        "consultant"
    ],
    "wof:name":"Information Systems Solutions",
    "wof:placetype":"venue"
},
  "geometry": {"coordinates":[-1.18549,50.900139],"type":"Point"}
}