{
  "type": "Feature",
  "properties": {
    "addr:full":"Mid Fleenas, Little Milln Nairn Highland IV12 5QL",
    "addr:postcode":"iv12 5ql",
    "iso:country":"GB",
    "sg:address":"Mid Fleenas, Little Milln",
    "sg:city":"Nairn",
    "sg:classifiers":[
        {
            "category":"Farming",
            "subcategory":"Livestock Farm",
            "type":"Manufacturing & Wholesale Goods"
        }
    ],
    "sg:phone":"+44 1667 452009",
    "sg:postcode":"IV12 5QL",
    "sg:province":"Highland",
    "sg:tags":[
        "others"
    ],
    "wof:name":"Macarthur Bros",
    "wof:placetype":"venue"
},
  "geometry": {"coordinates":[-3.8767089844,57.5832138062],"type":"Point"}
}