{
  "type": "Feature",
  "properties": {
    "addr:full":"10 Quorn Way, Binley Coventry Warwickshire CV3 2JU",
    "addr:housenumber":"10",
    "addr:postcode":"cv3 2ju",
    "addr:street":"Quorn Way",
    "iso:country":"GB",
    "sg:address":"10 Quorn Way, Binley",
    "sg:city":"Coventry",
    "sg:classifiers":[
        {
            "category":"Shopping",
            "subcategory":"Pharmacy",
            "type":"Retail Goods"
        }
    ],
    "sg:phone":"+44 24 7645 9909",
    "sg:postcode":"CV3 2JU",
    "sg:province":"Warwickshire",
    "sg:tags":[
        "pharmacist",
        "dispensing",
        "chemist"
    ],
    "wof:name":"Moss Pharmacy",
    "wof:placetype":"venue"
},
  "geometry": {"coordinates":[-1.4559860229,52.394203186],"type":"Point"}
}