{
  "type": "Feature",
  "properties": {
    "iso:country":"GB",
    "sg:address":"Dyfodwg Street",
    "sg:city":"Treorchy",
    "sg:classifiers":[
        {
            "category":"Arts & Performance",
            "subcategory":"Arts Center",
            "type":"Entertainment"
        },
        {
            "category":"Communications",
            "subcategory":"Film & Video Production",
            "type":"Services"
        }
    ],
    "sg:phone":"+44 1443 776090",
    "sg:postcode":"CF42 6NL",
    "sg:province":"Rhondda, Cynon, Taff",
    "sg:tags":[
        "centre",
        "illustrator",
        "artist"
    ],
    "wof:name":"Rhondda Cynon Taff Community Arts",
    "wof:placetype":"venue"
},
  "geometry": {"coordinates":[-3.508937,51.659237],"type":"Point"}
}