{
  "type": "Feature",
  "properties": {
    "iso:country":"GB",
    "sg:address":"30-31 Oldbury Place",
    "sg:city":"London",
    "sg:classifiers":[
        {
            "category":"Professional",
            "subcategory":"Detective & Security Services",
            "type":"Services"
        }
    ],
    "sg:phone":"+44 20 7935 7147",
    "sg:postcode":"W1U 5PR",
    "sg:province":"Greater London",
    "sg:tags":[
        "alarm",
        "burglar",
        "system",
        "locksmith"
    ],
    "wof:name":"Bramah Security Centres Ltd.",
    "wof:placetype":"venue"
},
  "geometry": {"coordinates":[-0.152433,51.521626],"type":"Point"}
}