{
  "type": "Feature",
  "properties": {
    "iso:country":"GB",
    "sg:address":"12 St Georges Road",
    "sg:city":"Harrogate",
    "sg:classifiers":[
        {
            "category":"Building & Trades",
            "subcategory":"Landscaping Services",
            "type":"Services"
        },
        {
            "category":"Social Services",
            "subcategory":"Adult Care",
            "type":"Services"
        }
    ],
    "sg:postcode":"HG2 9BS",
    "sg:province":"North Yorkshire",
    "sg:tags":[
        "gardening",
        "domestic",
        "cleaning"
    ],
    "wof:name":"A 1 Patio & Drive Pressure Cleaning Services",
    "wof:placetype":"venue"
},
  "geometry": {"coordinates":[-1.5394370556,53.9808998108],"type":"Point"}
}