{
  "type": "Feature",
  "properties": {
    "addr:full":"259 London Road Leicester Leicestershire LE2 3BE",
    "addr:housenumber":"259",
    "addr:postcode":"le2 3be",
    "addr:street":"London Road",
    "iso:country":"GB",
    "sg:address":"259 London Road",
    "sg:city":"Leicester",
    "sg:classifiers":[
        {
            "category":"Government",
            "subcategory":"Office",
            "type":"Public Place"
        }
    ],
    "sg:phone":"+44 116 221 0013",
    "sg:postcode":"LE2 3BE",
    "sg:province":"Leicestershire",
    "sg:tags":[
        "education",
        "agency",
        "authority"
    ],
    "sg:website":"http://www.m-a.org.uk",
    "wof:name":"The Mathematical Association",
    "wof:placetype":"venue"
},
  "geometry": {"coordinates":[-1.1100809574,52.6183280945],"type":"Point"}
}