{
  "type": "Feature",
  "properties": {
    "addr:full":"Brogdale Farmhouse, Brogdale Road Faversham Kent ME13 8XY",
    "addr:postcode":"me13 8xy",
    "addr:street":"Brogdale Road",
    "iso:country":"GB",
    "sg:address":"Brogdale Farmhouse, Brogdale Road",
    "sg:city":"Faversham",
    "sg:classifiers":[
        {
            "category":"Building & Trades",
            "subcategory":"Plumbing",
            "type":"Services"
        }
    ],
    "sg:phone":"+44 1795 535267",
    "sg:postcode":"ME13 8XY",
    "sg:province":"Kent",
    "sg:tags":[
        "central",
        "installation",
        "system",
        "servicing",
        "heating"
    ],
    "wof:name":"Richard Tovey",
    "wof:placetype":"venue"
},
  "geometry": {"coordinates":[0.88344,51.309605],"type":"Point"}
}