{
  "type": "Feature",
  "properties": {
    "addr:full":"5 Azalea Ho, Carrington Clo Redhill Surrey RH1 1BY",
    "addr:housenumber":"5",
    "addr:postcode":"rh1 1by",
    "addr:street":"Azalea Ho;Clo Redhill",
    "iso:country":"GB",
    "sg:address":"5 Azalea Ho, Carrington Clo",
    "sg:city":"Redhill",
    "sg:classifiers":[
        {
            "category":"Wholesale",
            "subcategory":"Scrap",
            "type":"Manufacturing & Wholesale Goods"
        }
    ],
    "sg:phone":"+44 1737 769956",
    "sg:postcode":"RH1 1BY",
    "sg:province":"Surrey",
    "sg:tags":[
        "breaker",
        "dismantlers"
    ],
    "wof:name":"Lee's Autos",
    "wof:placetype":"venue"
},
  "geometry": {"coordinates":[-0.168879,51.238178],"type":"Point"}
}