{
  "type": "Feature",
  "properties": {
    "addr:full":"11 Holly Avenue, Ryton Village Ryton Tyne and Wear NE40 3PP",
    "addr:housenumber":"11",
    "addr:postcode":"ne40 3pp",
    "addr:street":"Holly Avenue Ryton Village",
    "iso:country":"GB",
    "sg:address":"11 Holly Avenue, Ryton Village",
    "sg:city":"Ryton",
    "sg:classifiers":[
        {
            "category":"Organizations",
            "subcategory":"Non-profit Organization",
            "type":"Services"
        }
    ],
    "sg:phone":"+44 191 413 7282",
    "sg:postcode":"NE40 3PP",
    "sg:province":"Tyne and Wear",
    "sg:tags":[
        "alarm",
        "system"
    ],
    "wof:name":"Expert Alarms & Electricals",
    "wof:placetype":"venue"
},
  "geometry": {"coordinates":[-1.762946,54.974995],"type":"Point"}
}