{
  "type": "Feature",
  "properties": {
    "addr:full":"29 Old Port Lane, Bromborough Wirral Cheshire CH62 3RA",
    "addr:housenumber":"29",
    "addr:postcode":"ch62 3ra",
    "addr:street":"Old Port Lane",
    "iso:country":"GB",
    "sg:address":"29 Old Port Lane, Bromborough",
    "sg:city":"Wirral",
    "sg:classifiers":[
        {
            "category":"Fast Food",
            "type":"Food & Drink"
        }
    ],
    "sg:phone":"+44 151 334 6944",
    "sg:postcode":"CH62 3RA",
    "sg:province":"Cheshire",
    "sg:tags":[
        "away",
        "take"
    ],
    "wof:name":"Holmlea",
    "wof:placetype":"venue"
},
  "geometry": {"coordinates":[-2.9819800854,53.3358001709],"type":"Point"}
}