{
  "type": "Feature",
  "properties": {
    "iso:country":"GB",
    "sg:address":"Whitehall Pl",
    "sg:city":"Westminster",
    "sg:classifiers":[
        {
            "category":"Government",
            "subcategory":"Office",
            "type":"Public Place"
        }
    ],
    "sg:phone":"+44 20 7270 8080",
    "sg:postcode":"SW1A 2HH",
    "sg:province":"Greater London",
    "sg:tags":[
        "central"
    ],
    "wof:name":"Ministry Of Agriculture Fisheries & Food",
    "wof:placetype":"venue"
},
  "geometry": {"coordinates":[-0.1237360016,51.5063896179],"type":"Point"}
}