{
  "type": "Feature",
  "properties": {
    "addr:full":"The Plaza Centre, 600 Southchurch Rd Southend-on-sea Essex SS1 2PU",
    "addr:housenumber":"600",
    "addr:postcode":"ss1 2pu",
    "addr:street":"Southchurch Rd",
    "iso:country":"GB",
    "sg:address":"The Plaza Centre, 600 Southchurch Rd",
    "sg:city":"Southend-on-sea",
    "sg:classifiers":[
        {
            "category":"Professional",
            "subcategory":"Business Services",
            "type":"Services"
        }
    ],
    "sg:postcode":"SS1 2PU",
    "sg:province":"Essex",
    "sg:tags":[
        "import",
        "export",
        "agent"
    ],
    "wof:name":"Exousia International Ministries",
    "wof:placetype":"venue"
},
  "geometry": {"coordinates":[0.7051600218,51.5403862],"type":"Point"}
}