{
  "type": "Feature",
  "properties": {
    "iso:country":"GB",
    "sg:address":"6 Comrie Rd, Stepps",
    "sg:city":"Glasgow",
    "sg:classifiers":[
        {
            "category":"Shopping",
            "subcategory":"Stationery & Office Supplies",
            "type":"Retail Goods"
        }
    ],
    "sg:postcode":"G33 6LF",
    "sg:province":"Glasgow City",
    "wof:name":"Hewitt,J,",
    "wof:placetype":"venue"
},
  "geometry": {"coordinates":[-4.1579141617,55.8871307373],"type":"Point"}
}