{
  "type": "Feature",
  "properties": {
    "addr:full":"Units 4-5 Wigan Lancashire WN5 9DN",
    "addr:housenumber":"units 4-5",
    "addr:postcode":"wn5 9dn",
    "iso:country":"GB",
    "sg:address":"Units 4-5",
    "sg:city":"Wigan",
    "sg:classifiers":[
        {
            "category":"Wholesale",
            "subcategory":"Auto Parts",
            "type":"Manufacturing & Wholesale Goods"
        }
    ],
    "sg:phone":"+44 1942 496183",
    "sg:postcode":"WN5 9DN",
    "sg:province":"Lancashire",
    "sg:tags":[
        "wholesaler",
        "tyre"
    ],
    "wof:name":"Bandvulc Holdings Ltd.",
    "wof:placetype":"venue"
},
  "geometry": {"coordinates":[-2.666599,53.53627],"type":"Point"}
}