{
  "type": "Feature",
  "properties": {
    "iso:country":"GB",
    "sg:address":"De Lane Warr Road",
    "sg:city":"East Grinstead",
    "sg:classifiers":[
        {
            "category":"Retail",
            "subcategory":"Driving School",
            "type":"Services"
        }
    ],
    "sg:postcode":"RH19 3BS",
    "sg:province":"East Sussex",
    "sg:tags":[
        "instruction",
        "cycling",
        "motor"
    ],
    "wof:name":"British Motorcyclist Federation",
    "wof:placetype":"venue"
},
  "geometry": {"coordinates":[-0.0068390002,51.1267089844],"type":"Point"}
}