{
  "type": "Feature",
  "properties": {
    "addr:full":"Station Road Joinery Works, Maud Peterhead Aberdeenshire AB42 5LY",
    "addr:housenumber":"works",
    "addr:postcode":"ab42 5ly",
    "addr:street":"Station Road;Maud",
    "iso:country":"GB",
    "sg:address":"Station Road Joinery Works, Maud",
    "sg:city":"Peterhead",
    "sg:classifiers":[
        {
            "category":"Building & Trades",
            "subcategory":"Construction",
            "type":"Services"
        }
    ],
    "sg:phone":"+44 1771 613505",
    "sg:postcode":"AB42 5LY",
    "sg:province":"Aberdeenshire",
    "sg:tags":[
        "joinery"
    ],
    "wof:name":"Freddie Simpson",
    "wof:placetype":"venue"
},
  "geometry": {"coordinates":[-2.0038590431,57.5251808167],"type":"Point"}
}