{
  "type": "Feature",
  "properties": {
    "iso:country":"GB",
    "sg:address":"778 Christchurch Road",
    "sg:city":"Bournemouth",
    "sg:classifiers":[
        {
            "category":"Food & Beverages",
            "subcategory":"Bakery",
            "type":"Retail Goods"
        }
    ],
    "sg:phone":"+44 1202 301968",
    "sg:postcode":"BH7 6DB",
    "sg:province":"Dorset",
    "sg:tags":[
        "baker"
    ],
    "wof:name":"Boscombe Manor Bakery",
    "wof:placetype":"venue"
},
  "geometry": {"coordinates":[-1.8315550089,50.7287635803],"type":"Point"}
}