{
  "type": "Feature",
  "properties": {
    "iso:country":"GB",
    "sg:address":"58 Wyle Cop",
    "sg:city":"Shrewsbury",
    "sg:classifiers":[
        {
            "category":"Shopping",
            "subcategory":"Crafts & Fabrics",
            "type":"Retail Goods"
        }
    ],
    "sg:phone":"+44 1743 343902",
    "sg:postcode":"SY1 1XJ",
    "sg:province":"Shropshire",
    "sg:tags":[
        "machine",
        "sewing",
        "knitting"
    ],
    "wof:name":"Sewing Machine Centre",
    "wof:placetype":"venue"
},
  "geometry": {"coordinates":[-2.75045,52.706181],"type":"Point"}
}