{
  "type": "Feature",
  "properties": {
    "iso:country":"GB",
    "sg:address":"Spencer Rise",
    "sg:city":"London",
    "sg:classifiers":[
        {
            "category":"Health Services",
            "subcategory":"Health Practitioner",
            "type":"Services"
        }
    ],
    "sg:postcode":"NW5 1AR",
    "sg:province":"Greater London",
    "sg:tags":[
        "psychotherapist"
    ],
    "wof:name":"The Elms Therapists",
    "wof:placetype":"venue"
},
  "geometry": {"coordinates":[-0.1413290054,51.5583152771],"type":"Point"}
}