{
  "type": "Feature",
  "properties": {
    "addr:full":"100 Caldrum Street Dundee Dundee City DD3 7HD",
    "addr:housenumber":"100",
    "addr:postcode":"dd3 7hd",
    "addr:street":"Caldrum Street",
    "iso:country":"GB",
    "sg:address":"100 Caldrum Street",
    "sg:city":"Dundee",
    "sg:classifiers":[
        {
            "category":"Military Area",
            "subcategory":"Air Force Base",
            "type":"Public Place"
        }
    ],
    "sg:phone":"+44 1382 535666",
    "sg:postcode":"DD3 7HD",
    "sg:province":"Dundee City",
    "sg:tags":[
        "taxi",
        "hire",
        "private"
    ],
    "wof:name":"Monifieth Cabs",
    "wof:placetype":"venue"
},
  "geometry": {"coordinates":[-2.9738099575,56.4708213806],"type":"Point"}
}