{
  "type": "Feature",
  "properties": {
    "addr:full":"75 Wrose Rd Shipley West Yorkshire BD18 1HX",
    "addr:housenumber":"75",
    "addr:postcode":"bd18 1hx",
    "addr:street":"Wrose Rd",
    "iso:country":"GB",
    "sg:address":"75 Wrose Rd",
    "sg:city":"Shipley",
    "sg:classifiers":[
        {
            "category":"Food & Beverages",
            "subcategory":"Supermarket",
            "type":"Retail Goods"
        }
    ],
    "sg:phone":"+44 1274 591414",
    "sg:postcode":"BD18 1HX",
    "sg:province":"West Yorkshire",
    "wof:name":"Food Fairs",
    "wof:placetype":"venue"
},
  "geometry": {"coordinates":[-1.756212,53.828663],"type":"Point"}
}