{
  "type": "Feature",
  "properties": {
    "iso:country":"GB",
    "sg:address":"9 Ramsden St",
    "sg:city":"Huddersfield",
    "sg:classifiers":[
        {
            "category":"Banks & Credit Unions",
            "subcategory":"Financial Services",
            "type":"Services"
        }
    ],
    "sg:phone":"+44 1484 546517",
    "sg:postcode":"HD1 2SX",
    "sg:province":"West Yorkshire",
    "sg:tags":[
        "building",
        "society"
    ],
    "wof:name":"Alliance & Leicester plc",
    "wof:placetype":"venue"
},
  "geometry": {"coordinates":[-1.782538,53.644444],"type":"Point"}
}