{
  "type": "Feature",
  "properties": {
    "addr:full":"7 Kings Park Road Bournemouth Dorset BH7 7AE",
    "addr:housenumber":"7",
    "addr:postcode":"bh7 7ae",
    "addr:street":"Kings Park Road",
    "iso:country":"GB",
    "sg:address":"7 Kings Park Road",
    "sg:city":"Bournemouth",
    "sg:classifiers":[
        {
            "category":"Building & Trades",
            "subcategory":"Construction",
            "type":"Services"
        }
    ],
    "sg:postcode":"BH7 7AE",
    "sg:province":"Dorset",
    "sg:tags":[
        "decorator",
        "painter"
    ],
    "wof:name":"F W Anderson",
    "wof:placetype":"venue"
},
  "geometry": {"coordinates":[-1.842895,50.734348],"type":"Point"}
}