{
  "type": "Feature",
  "properties": {
    "addr:full":"Meir Health Centre, Saracen Way Stoke On Trent Staffordshire ST3 7DS",
    "addr:postcode":"st3 7ds",
    "addr:street":"Saracen Way",
    "iso:country":"GB",
    "sg:address":"Meir Health Centre, Saracen Way",
    "sg:city":"Stoke On Trent",
    "sg:classifiers":[
        {
            "category":"Health Services",
            "subcategory":"Doctor",
            "type":"Services"
        }
    ],
    "sg:phone":"+44 1782 324024",
    "sg:postcode":"ST3 7DS",
    "sg:province":"Staffordshire",
    "sg:tags":[
        "practitioners"
    ],
    "wof:name":"Ganapathy, D H",
    "wof:placetype":"venue"
},
  "geometry": {"coordinates":[-2.10466,52.976639],"type":"Point"}
}