{
  "type": "Feature",
  "properties": {
    "addr:full":"28 Annetyard Drive Skelmorlie North Ayrshire PA17 5BN",
    "addr:housenumber":"28",
    "addr:postcode":"pa17 5bn",
    "addr:street":"Annetyard Drive",
    "iso:country":"GB",
    "sg:address":"28 Annetyard Drive",
    "sg:city":"Skelmorlie",
    "sg:classifiers":[
        {
            "category":"Retail",
            "subcategory":"Event Space",
            "type":"Services"
        }
    ],
    "sg:phone":"+44 1475 522322",
    "sg:postcode":"PA17 5BN",
    "sg:province":"North Ayrshire",
    "sg:tags":[
        "pipeline"
    ],
    "wof:name":"Pipeline Pigging Consultants",
    "wof:placetype":"venue"
},
  "geometry": {"coordinates":[-4.883338,55.864464],"type":"Point"}
}