{
  "type": "Feature",
  "properties": {
    "addr:full":"Scourie, Sacriston Lane, Witton Gilbert Durham Durham DH7 6QU",
    "addr:postcode":"dh7 6qu",
    "addr:street":"Sacriston Lane",
    "iso:country":"GB",
    "sg:address":"Scourie, Sacriston Lane, Witton Gilbert",
    "sg:city":"Durham",
    "sg:classifiers":[
        {
            "category":"Shopping",
            "subcategory":"News",
            "type":"Retail Goods"
        }
    ],
    "sg:phone":"+44 191 371 2863",
    "sg:postcode":"DH7 6QU",
    "sg:province":"Durham",
    "sg:tags":[
        "newsagent"
    ],
    "wof:name":"Martin the Newsagent",
    "wof:placetype":"venue"
},
  "geometry": {"coordinates":[-1.6343990564,54.8087806702],"type":"Point"}
}