{
  "type": "Feature",
  "properties": {
    "iso:country":"GB",
    "sg:address":"50 Kingston Road",
    "sg:city":"London",
    "sg:classifiers":[
        {
            "category":"Autos & Motor Vehicles",
            "subcategory":"Automobile Sales",
            "type":"Retail Goods"
        }
    ],
    "sg:phone":"+44 20 8540 5590",
    "sg:postcode":"SW19 1JZ",
    "sg:province":"Greater London",
    "sg:tags":[
        "car"
    ],
    "wof:name":"Whites Audi Centre",
    "wof:placetype":"venue"
},
  "geometry": {"coordinates":[-0.1952610016,51.4153175354],"type":"Point"}
}