{
  "type": "Feature",
  "properties": {
    "addr:full":"125 Glasgow Road Hamilton South Lanarkshire ML3 0QG",
    "addr:housenumber":"125",
    "addr:postcode":"ml3 0qg",
    "addr:street":"Glasgow Road",
    "iso:country":"GB",
    "sg:address":"125 Glasgow Road",
    "sg:city":"Hamilton",
    "sg:classifiers":[
        {
            "category":"Food & Beverages",
            "subcategory":"Meat & Fish",
            "type":"Retail Goods"
        },
        {
            "category":"Food & Beverages",
            "subcategory":"Groceries & Convenience Stores",
            "type":"Retail Goods"
        }
    ],
    "sg:phone":"+44 1698 284277",
    "sg:postcode":"ML3 0QG",
    "sg:province":"South Lanarkshire",
    "sg:tags":[
        "shop",
        "chip"
    ],
    "wof:name":"Marini's Fish & Chicken Bar",
    "wof:placetype":"venue"
},
  "geometry": {"coordinates":[-4.073103,55.783627],"type":"Point"}
}