{
  "type": "Feature",
  "properties": {
    "addr:full":"1 Pemberton Row, Fetter La London Greater London EC4A 3ET",
    "addr:housenumber":"1",
    "addr:postcode":"ec4a 3et",
    "addr:street":"Pemberton Row Fetter La",
    "iso:country":"GB",
    "sg:address":"1 Pemberton Row, Fetter La",
    "sg:city":"London",
    "sg:classifiers":[
        {
            "category":"Real Estate",
            "subcategory":"Surveying",
            "type":"Services"
        }
    ],
    "sg:postcode":"EC4A 3ET",
    "sg:province":"Greater London",
    "sg:tags":[
        "building",
        "surveyor"
    ],
    "wof:name":"Spectrum D C M Ltd",
    "wof:placetype":"venue"
},
  "geometry": {"coordinates":[-0.1085639969,51.5150718689],"type":"Point"}
}