{
  "type": "Feature",
  "properties": {
    "addr:full":"12 Ravensworth Close, Pendas Fields Leeds West Yorkshire LS15 8UU",
    "addr:housenumber":"12",
    "addr:postcode":"ls15 8uu",
    "addr:street":"Ravensworth Close",
    "iso:country":"GB",
    "sg:address":"12 Ravensworth Close, Pendas Fields",
    "sg:city":"Leeds",
    "sg:classifiers":[
        {
            "category":"Professional",
            "subcategory":"Secretarial Services",
            "type":"Services"
        }
    ],
    "sg:phone":"+44 113 260 1024",
    "sg:postcode":"LS15 8UU",
    "sg:province":"West Yorkshire",
    "wof:name":"Call Cale",
    "wof:placetype":"venue"
},
  "geometry": {"coordinates":[-1.4305399656,53.8111763],"type":"Point"}
}