{
  "type": "Feature",
  "properties": {
    "iso:country":"GB",
    "sg:address":"Middleton Road",
    "sg:city":"Ilkley",
    "sg:classifiers":[
        {
            "category":"Autos & Motor Vehicles",
            "subcategory":"Automobile Sales",
            "type":"Retail Goods"
        }
    ],
    "sg:phone":"+44 1943 608733",
    "sg:postcode":"LS29 9EX",
    "sg:province":"North Yorkshire",
    "sg:tags":[
        "car"
    ],
    "wof:name":"Andrew Green Exclusive Cars",
    "wof:placetype":"venue"
},
  "geometry": {"coordinates":[-1.829389,53.927891],"type":"Point"}
}