{
  "type": "Feature",
  "properties": {
    "iso:country":"GB",
    "sg:address":"Dayr-house, Prospect Rd",
    "sg:city":"Bath",
    "sg:classifiers":[
        {
            "category":"Real Estate",
            "subcategory":"Architect",
            "type":"Services"
        }
    ],
    "sg:phone":"+44 1225 447114",
    "sg:postcode":"BA2 6AY",
    "sg:province":"Somerset",
    "wof:name":"Hadfield Associates",
    "wof:placetype":"venue"
},
  "geometry": {"coordinates":[-2.340164,51.3727],"type":"Point"}
}