{
  "type": "Feature",
  "properties": {
    "iso:country":"GB",
    "sg:address":"3-5 Lister Road, Hillington Industrial Estate",
    "sg:city":"Glasgow",
    "sg:classifiers":[
        {
            "category":"Manufacturing",
            "subcategory":"Electronics",
            "type":"Manufacturing & Wholesale Goods"
        },
        {
            "category":"Home & Garden",
            "subcategory":"Carpets & Floor Coverings",
            "type":"Retail Goods"
        }
    ],
    "sg:phone":"+44 141 882 8858",
    "sg:postcode":"G52 4BH",
    "sg:province":"Glasgow City",
    "sg:tags":[
        "control",
        "scale",
        "-",
        "component",
        "electronic",
        "manufacturer"
    ],
    "wof:name":"Force Measurement Systems Ltd",
    "wof:placetype":"venue"
},
  "geometry": {"coordinates":[-4.365018,55.857815],"type":"Point"}
}