{
  "type": "Feature",
  "properties": {
    "iso:country":"GB",
    "sg:address":"375 Ashley Road, Parkstone",
    "sg:city":"Poole",
    "sg:classifiers":[
        {
            "category":"Home & Garden",
            "subcategory":"Carpets & Floor Coverings",
            "type":"Retail Goods"
        }
    ],
    "sg:phone":"+44 1202 730176",
    "sg:postcode":"BH14 0AS",
    "sg:province":"Dorset",
    "sg:tags":[
        "carpets",
        "retailer",
        "rug",
        "matting"
    ],
    "wof:name":"Contakt Carpets Ltd.",
    "wof:placetype":"venue"
},
  "geometry": {"coordinates":[-1.941871,50.728928],"type":"Point"}
}