{
  "type": "Feature",
  "properties": {
    "addr:full":"15 East Terrace, Hesleden Hartlepool Durham TS27 4PR",
    "addr:housenumber":"15",
    "addr:postcode":"ts27 4pr",
    "addr:street":"East Terrace",
    "iso:country":"GB",
    "sg:address":"15 East Terrace, Hesleden",
    "sg:city":"Hartlepool",
    "sg:classifiers":[
        {
            "category":"Communications",
            "type":"Services"
        }
    ],
    "sg:postcode":"TS27 4PR",
    "sg:province":"Durham",
    "sg:tags":[
        "tv",
        "video",
        "radio"
    ],
    "wof:name":"20-20 Vision",
    "wof:placetype":"venue"
},
  "geometry": {"coordinates":[-1.3142310381,54.7353515625],"type":"Point"}
}