{
  "type": "Feature",
  "properties": {
    "addr:full":"105 Risbygate St Bury St Edmunds Suffolk IP33 3AA",
    "addr:housenumber":"105",
    "addr:postcode":"ip33 3aa",
    "addr:street":"Risbygate St",
    "iso:country":"GB",
    "sg:address":"105 Risbygate St",
    "sg:city":"Bury St Edmunds",
    "sg:classifiers":[
        {
            "category":"Professional",
            "subcategory":"Employment Agencies",
            "type":"Services"
        }
    ],
    "sg:phone":"+44 1284 766722",
    "sg:postcode":"IP33 3AA",
    "sg:province":"Suffolk",
    "sg:tags":[
        "consultant"
    ],
    "wof:name":"Driver Hire Nationwide",
    "wof:placetype":"venue"
},
  "geometry": {"coordinates":[0.7105559707,52.2471656799],"type":"Point"}
}