{
  "type": "Feature",
  "properties": {
    "iso:country":"GB",
    "sg:address":"Cobby Castle Lane, Bishopton",
    "sg:city":"Stockton-on-tees",
    "sg:classifiers":[
        {
            "category":"Education",
            "subcategory":"School",
            "type":"Public Place"
        },
        {
            "category":"Government",
            "subcategory":"Office",
            "type":"Public Place"
        }
    ],
    "sg:phone":"+44 1740 630339",
    "sg:postcode":"TS21 1HD",
    "sg:province":"Durham",
    "sg:tags":[
        "local",
        "authority"
    ],
    "wof:name":"Bishopton Redmarshall Primary School",
    "wof:placetype":"venue"
},
  "geometry": {"coordinates":[-1.435183,54.589146],"type":"Point"}
}