{
  "type": "Feature",
  "properties": {
    "addr:full":"112 Fitzjohns Avenue London Greater London NW3 6NT",
    "addr:housenumber":"112",
    "addr:postcode":"nw3 6nt",
    "addr:street":"Fitzjohns Avenue",
    "iso:country":"GB",
    "sg:address":"112 Fitzjohns Avenue",
    "sg:city":"London",
    "sg:classifiers":[
        {
            "category":"Banks & Credit Unions",
            "subcategory":"Financial Services",
            "type":"Services"
        }
    ],
    "sg:phone":"+44 20 7431 2925",
    "sg:postcode":"NW3 6NT",
    "sg:province":"Greater London",
    "sg:tags":[
        "consultant"
    ],
    "wof:name":"Centaur Asset Management (U K) Ltd.",
    "wof:placetype":"venue"
},
  "geometry": {"coordinates":[-0.177612,51.554768],"type":"Point"}
}