{
  "type": "Feature",
  "properties": {
    "addr:full":"2a Dyers Close, West Buckland Wellington Devon TA21 9JU",
    "addr:housenumber":"2a",
    "addr:postcode":"ta21 9ju",
    "addr:street":"Dyers Close",
    "iso:country":"GB",
    "sg:address":"2a Dyers Close, West Buckland",
    "sg:city":"Wellington",
    "sg:classifiers":[
        {
            "category":"Shopping",
            "subcategory":"Department Store",
            "type":"Retail Goods"
        },
        {
            "category":"Food & Beverages",
            "subcategory":"Groceries & Convenience Stores",
            "type":"Retail Goods"
        }
    ],
    "sg:phone":"+44 1823 667997",
    "sg:postcode":"TA21 9JU",
    "sg:province":"Devon",
    "wof:name":"West Buckland Post Office",
    "wof:placetype":"venue"
},
  "geometry": {"coordinates":[-3.1763410568,50.9776077271],"type":"Point"}
}