{
  "type": "Feature",
  "properties": {
    "iso:country":"GB",
    "sg:address":"57 High St, Wombwell",
    "sg:city":"Barnsley",
    "sg:classifiers":[
        {
            "category":"Restaurant",
            "type":"Food & Drink"
        }
    ],
    "sg:postcode":"S73 8HS",
    "sg:province":"South Yorkshire",
    "sg:tags":[
        "italian"
    ],
    "wof:name":"Davies,J,",
    "wof:placetype":"venue"
},
  "geometry": {"coordinates":[-1.399751,53.523026],"type":"Point"}
}