{
  "type": "Feature",
  "properties": {
    "iso:country":"GB",
    "sg:address":"17 Glamis Gardens, Dalgety Bay",
    "sg:city":"Dunfermline",
    "sg:classifiers":[
        {
            "category":"Professional",
            "subcategory":"Management & Consulting",
            "type":"Services"
        }
    ],
    "sg:phone":"+44 1383 823018",
    "sg:postcode":"KY11 9TD",
    "sg:province":"Fife",
    "sg:tags":[
        "consultant",
        "business"
    ],
    "wof:name":"Icaem Insight Ltd",
    "wof:placetype":"venue"
},
  "geometry": {"coordinates":[-3.351814,56.032909],"type":"Point"}
}