{
  "type": "Feature",
  "properties": {
    "iso:country":"GB",
    "sg:address":"Scarnell Road",
    "sg:city":"Norwich",
    "sg:classifiers":[
        {
            "category":"Education",
            "subcategory":"School",
            "type":"Public Place"
        }
    ],
    "sg:phone":"+44 1603 454569",
    "sg:postcode":"NR5 8HT",
    "sg:province":"Norfolk",
    "sg:tags":[
        "local",
        "authority"
    ],
    "wof:name":"NORFOLK COUNTY COUNCIL",
    "wof:placetype":"venue"
},
  "geometry": {"coordinates":[1.242454,52.630779],"type":"Point"}
}