{
  "type": "Feature",
  "properties": {
    "addr:full":"The Gaunts House, Denmark St Bristol City of Bristol BS1 5SD",
    "addr:postcode":"bs1 5sd",
    "addr:street":"Denmark St",
    "iso:country":"GB",
    "sg:address":"The Gaunts House, Denmark St",
    "sg:city":"Bristol",
    "sg:classifiers":[
        {
            "category":"Professional",
            "subcategory":"Accounting & Tax Preparation",
            "type":"Services"
        }
    ],
    "sg:phone":"+44 117 930 2100",
    "sg:postcode":"BS1 5SD",
    "sg:province":"City of Bristol",
    "sg:tags":[
        "consultant"
    ],
    "wof:name":"Inland Revenue",
    "wof:placetype":"venue"
},
  "geometry": {"coordinates":[-2.5995941162,51.453338623],"type":"Point"}
}