{
  "type": "Feature",
  "properties": {
    "addr:full":"12 Hampden Square London Greater London N14 5JR",
    "addr:housenumber":"12",
    "addr:postcode":"n14 5jr",
    "addr:street":"Hampden Square",
    "iso:country":"GB",
    "sg:address":"12 Hampden Square",
    "sg:city":"London",
    "sg:classifiers":[
        {
            "category":"Government",
            "subcategory":"Post Office",
            "type":"Public Place"
        },
        {
            "category":"Food & Beverages",
            "subcategory":"Groceries & Convenience Stores",
            "type":"Retail Goods"
        }
    ],
    "sg:phone":"+44 20 8361 8899",
    "sg:postcode":"N14 5JR",
    "sg:province":"Greater London",
    "wof:name":"Hampden Square Modified Post Office",
    "wof:placetype":"venue"
},
  "geometry": {"coordinates":[-0.142877996,51.6315536499],"type":"Point"}
}