{
  "type": "Feature",
  "properties": {
    "addr:full":"43 Hill Avenue Amersham Buckinghamshire HP6 5BX",
    "addr:housenumber":"43",
    "addr:postcode":"hp6 5bx",
    "addr:street":"Hill Avenue Amersham",
    "iso:country":"GB",
    "sg:address":"43 Hill Avenue",
    "sg:city":"Amersham",
    "sg:classifiers":[
        {
            "category":"Professional",
            "subcategory":"Computer Services",
            "type":"Services"
        }
    ],
    "sg:phone":"+44 1797 253673",
    "sg:postcode":"HP6 5BX",
    "sg:province":"Buckinghamshire",
    "sg:tags":[
        "development",
        "system",
        "software"
    ],
    "wof:name":"Woodbury Associates Ltd",
    "wof:placetype":"venue"
},
  "geometry": {"coordinates":[-0.607391,51.675972],"type":"Point"}
}