{
  "type": "Feature",
  "properties": {
    "addr:full":"183 Benhill Rd Sutton Surrey SM1 3SB",
    "addr:housenumber":"183",
    "addr:postcode":"sm1 3sb",
    "addr:street":"Benhill Rd",
    "iso:country":"GB",
    "sg:address":"183 Benhill Rd",
    "sg:city":"Sutton",
    "sg:classifiers":[
        {
            "category":"Building & Trades",
            "subcategory":"Construction",
            "type":"Services"
        }
    ],
    "sg:phone":"+44 20 8644 5058",
    "sg:postcode":"SM1 3SB",
    "sg:province":"Surrey",
    "sg:tags":[
        "builder"
    ],
    "wof:name":"Burns Scaffolding",
    "wof:placetype":"venue"
},
  "geometry": {"coordinates":[-0.184791,51.372379],"type":"Point"}
}