{
  "type": "Feature",
  "properties": {
    "addr:full":"3/4 Manaton Court, Manaton Close, Matford Business Park Exeter Devon EX2 8PF",
    "addr:housenumber":"3 / 4",
    "addr:postcode":"ex2 8pf",
    "addr:street":"Manaton Court Manaton Close Matford Business Park",
    "iso:country":"GB",
    "sg:address":"3/4 Manaton Court, Manaton Close, Matford Business Park",
    "sg:city":"Exeter",
    "sg:classifiers":[
        {
            "category":"Professional",
            "subcategory":"Computer Services",
            "type":"Services"
        }
    ],
    "sg:phone":"+44 1392 426473",
    "sg:postcode":"EX2 8PF",
    "sg:province":"Devon",
    "sg:tags":[
        "system",
        "software"
    ],
    "wof:name":"A M Micro",
    "wof:placetype":"venue"
},
  "geometry": {"coordinates":[-3.524668932,50.6979598999],"type":"Point"}
}