{
  "type": "Feature",
  "properties": {
    "addr:full":"22 The Parade Wallsend Tyne and Wear NE28 9RW",
    "addr:housenumber":"22",
    "addr:postcode":"ne28 9rw",
    "addr:street":"The Parade",
    "iso:country":"GB",
    "sg:address":"22 The Parade",
    "sg:city":"Wallsend",
    "sg:classifiers":[
        {
            "category":"Health Services",
            "subcategory":"Dentist",
            "type":"Services"
        }
    ],
    "sg:phone":"+44 191 295 4554",
    "sg:postcode":"NE28 9RW",
    "sg:province":"Tyne and Wear",
    "wof:name":"Shirley Downs",
    "wof:placetype":"venue"
},
  "geometry": {"coordinates":[-1.5332239866,54.9912796021],"type":"Point"}
}