{
  "type": "Feature",
  "properties": {
    "iso:country":"GB",
    "sg:address":"61 Market St, Eckington",
    "sg:city":"Sheffield",
    "sg:classifiers":[
        {
            "category":"Insurance",
            "subcategory":"Insurance Agent",
            "type":"Services"
        }
    ],
    "sg:postcode":"S21 4JG",
    "sg:province":"Derbyshire",
    "sg:tags":[
        "broker"
    ],
    "wof:name":"Hamnett Hart & Owens",
    "wof:placetype":"venue"
},
  "geometry": {"coordinates":[-1.356682,53.308979],"type":"Point"}
}