{
  "type": "Feature",
  "properties": {
    "addr:full":"59 Lawfield Avenue West Kilbride North Ayrshire KA23 9DH",
    "addr:housenumber":"59",
    "addr:postcode":"ka23 9dh",
    "addr:street":"Lawfield Avenue",
    "iso:country":"GB",
    "sg:address":"59 Lawfield Avenue",
    "sg:city":"West Kilbride",
    "sg:classifiers":[
        {
            "category":"Retail",
            "subcategory":"Repair Shop",
            "type":"Services"
        }
    ],
    "sg:postcode":"KA23 9DH",
    "sg:province":"North Ayrshire",
    "sg:tags":[
        "radio",
        "television",
        "video"
    ],
    "wof:name":"R C L Electronics",
    "wof:placetype":"venue"
},
  "geometry": {"coordinates":[-4.8478908539,55.6902732849],"type":"Point"}
}