{
  "type": "Feature",
  "properties": {
    "addr:full":"St Michaels, The Warren Leatherhead Surrey KT24 5RH",
    "addr:housenumber":"the",
    "addr:postcode":"kt24 5rh",
    "iso:country":"GB",
    "sg:address":"St Michaels, The Warren",
    "sg:city":"Leatherhead",
    "sg:classifiers":[
        {
            "category":"Professional",
            "subcategory":"Accounting & Tax Preparation",
            "type":"Services"
        }
    ],
    "sg:phone":"+44 1483 284000",
    "sg:postcode":"KT24 5RH",
    "sg:province":"Surrey",
    "sg:tags":[
        "accountant"
    ],
    "wof:name":"Bessler Hendrie",
    "wof:placetype":"venue"
},
  "geometry": {"coordinates":[-0.42855,51.258411],"type":"Point"}
}