{
  "type": "Feature",
  "properties": {
    "addr:full":"117 Cadzow Street Hamilton South Lanarkshire ML3 6JA",
    "addr:housenumber":"117",
    "addr:postcode":"ml3 6ja",
    "addr:street":"Cadzow Street",
    "iso:country":"GB",
    "sg:address":"117 Cadzow Street",
    "sg:city":"Hamilton",
    "sg:classifiers":[
        {
            "category":"Shopping",
            "subcategory":"Clothing, Apparel, & Fashions",
            "type":"Retail Goods"
        }
    ],
    "sg:postcode":"ML3 6JA",
    "sg:province":"South Lanarkshire",
    "sg:tags":[
        "leather",
        "garment"
    ],
    "wof:name":"Highland Sport Leisure Ltd",
    "wof:placetype":"venue"
},
  "geometry": {"coordinates":[-4.0365138054,55.7767868042],"type":"Point"}
}