{
  "type": "Feature",
  "properties": {
    "addr:full":"8 The Links, Queens Sq Corby Northamptonshire NN17 1PD",
    "addr:housenumber":"8",
    "addr:postcode":"nn17 1pd",
    "addr:street":"The",
    "iso:country":"GB",
    "sg:address":"8 The Links, Queens Sq",
    "sg:city":"Corby",
    "sg:classifiers":[
        {
            "category":"Food & Beverages",
            "subcategory":"Supermarket",
            "type":"Retail Goods"
        }
    ],
    "sg:phone":"+44 1536 202646",
    "sg:postcode":"NN17 1PD",
    "sg:province":"Northamptonshire",
    "wof:name":"Solo",
    "wof:placetype":"venue"
},
  "geometry": {"coordinates":[-0.7026000023,52.4859771729],"type":"Point"}
}