{
  "type": "Feature",
  "properties": {
    "addr:full":"28 Ford Road South Folkestone Kent CT20 1HJ",
    "addr:housenumber":"28",
    "addr:postcode":"ct20 1hj",
    "addr:street":"Ford Road South",
    "iso:country":"GB",
    "sg:address":"28 Ford Road South",
    "sg:city":"Folkestone",
    "sg:classifiers":[
        {
            "category":"Building & Trades",
            "subcategory":"Plumbing",
            "type":"Services"
        }
    ],
    "sg:phone":"+44 1303 256594",
    "sg:postcode":"CT20 1HJ",
    "sg:province":"Kent",
    "sg:tags":[
        "merchant",
        "plumbers'"
    ],
    "wof:name":"Dunn's Plumbing & Heating Supplies",
    "wof:placetype":"venue"
},
  "geometry": {"coordinates":[1.1798950434,51.082321167],"type":"Point"}
}