{
  "type": "Feature",
  "properties": {
    "iso:country":"GB",
    "sg:address":"8 Dunton Street",
    "sg:city":"Wigston",
    "sg:classifiers":[
        {
            "category":"Shopping",
            "subcategory":"Bicycles & Sporting Goods",
            "type":"Retail Goods"
        },
        {
            "category":"Recreation",
            "subcategory":"Fishing",
            "type":"Entertainment"
        }
    ],
    "sg:phone":"+44 116 278 2440",
    "sg:postcode":"LE18 4PU",
    "sg:province":"Leicestershire",
    "sg:tags":[
        "equipment",
        "angling"
    ],
    "wof:name":"All Seasons Angling Centre",
    "wof:placetype":"venue"
},
  "geometry": {"coordinates":[-1.1327739954,52.5793838501],"type":"Point"}
}