{
  "type": "Feature",
  "properties": {
    "iso:country":"GB",
    "sg:address":"Greystone Park, Moffat Road",
    "sg:city":"Dumfries",
    "sg:classifiers":[
        {
            "category":"Building & Trades",
            "subcategory":"Landscaping Services",
            "type":"Services"
        }
    ],
    "sg:phone":"+44 1387 272440",
    "sg:postcode":"DG1 1NP",
    "sg:province":"Dumfries and Galloway",
    "sg:tags":[
        "forestry",
        "tree"
    ],
    "wof:name":"Forestry Commission",
    "wof:placetype":"venue"
},
  "geometry": {"coordinates":[-3.600194,55.076759],"type":"Point"}
}