{
  "type": "Feature",
  "properties": {
    "iso:country":"GB",
    "sg:address":"37a High Street, Staveley",
    "sg:city":"Chesterfield",
    "sg:classifiers":[
        {
            "category":"Manufacturing",
            "subcategory":"Tools & Machinery",
            "type":"Manufacturing & Wholesale Goods"
        },
        {
            "category":"Insurance",
            "subcategory":"Insurance Agent",
            "type":"Services"
        }
    ],
    "sg:phone":"+44 1246 472449",
    "sg:postcode":"S43 3UU",
    "sg:province":"Derbyshire",
    "sg:tags":[
        "society",
        "friendly"
    ],
    "wof:name":"Staveley Insurance Services",
    "wof:placetype":"venue"
},
  "geometry": {"coordinates":[-1.3527729511,53.2683448792],"type":"Point"}
}