{
  "type": "Feature",
  "properties": {
    "addr:full":"Thorpe Rd Chertsey Surrey KT16 8PH",
    "addr:postcode":"kt16 8ph",
    "addr:street":"Thorpe Rd",
    "iso:country":"GB",
    "sg:address":"Thorpe Rd",
    "sg:city":"Chertsey",
    "sg:classifiers":[
        {
            "category":"Recreation",
            "subcategory":"Water Park",
            "type":"Entertainment"
        }
    ],
    "sg:phone":"+44 1932 561171",
    "sg:postcode":"KT16 8PH",
    "sg:province":"Surrey",
    "sg:tags":[
        "sport"
    ],
    "wof:name":"John Battleday Water Ski School",
    "wof:placetype":"venue"
},
  "geometry": {"coordinates":[-0.520692,51.398731],"type":"Point"}
}