{
  "type": "Feature",
  "properties": {
    "addr:full":"Shielhill Road, Northmuir Kirriemuir Angus DD8 4PN",
    "addr:postcode":"dd8 4pn",
    "addr:street":"Shielhill Road",
    "iso:country":"GB",
    "sg:address":"Shielhill Road, Northmuir",
    "sg:city":"Kirriemuir",
    "sg:classifiers":[
        {
            "category":"Bars & Pubs",
            "type":"Food & Drink"
        },
        {
            "category":"Community Center",
            "subcategory":"Social",
            "type":"Public Place"
        }
    ],
    "sg:phone":"+44 1575 573917",
    "sg:postcode":"DD8 4PN",
    "sg:province":"Angus",
    "sg:tags":[
        "pubs",
        "house",
        "inn",
        "activity"
    ],
    "wof:name":"Woodville Inn",
    "wof:placetype":"venue"
},
  "geometry": {"coordinates":[-2.9983489513,56.67552948],"type":"Point"}
}