{
  "type": "Feature",
  "properties": {
    "iso:country":"GB",
    "sg:address":"North Heath Industrial Estate, North Heath Lane",
    "sg:city":"Horsham",
    "sg:classifiers":[
        {
            "category":"Retail",
            "subcategory":"Auto Repair",
            "type":"Services"
        }
    ],
    "sg:phone":"+44 1403 255035",
    "sg:postcode":"RH12 5QE",
    "sg:province":"West Sussex",
    "sg:tags":[
        "modification",
        "garage"
    ],
    "wof:name":"North Heath Motors Horsham",
    "wof:placetype":"venue"
},
  "geometry": {"coordinates":[-0.329107,51.065182],"type":"Point"}
}