{
  "type": "Feature",
  "properties": {
    "addr:full":"24a Barbourne Road Worcester Worcestershire WR1 1HT",
    "addr:housenumber":"24a",
    "addr:postcode":"wr1 1ht",
    "addr:street":"Barbourne Road",
    "iso:country":"GB",
    "sg:address":"24a Barbourne Road",
    "sg:city":"Worcester",
    "sg:classifiers":[
        {
            "category":"Personal",
            "subcategory":"Beauty Salon",
            "type":"Services"
        }
    ],
    "sg:postcode":"WR1 1HT",
    "sg:province":"Worcestershire",
    "sg:tags":[
        "unisex",
        "hairdresser"
    ],
    "wof:name":"Kreme of the Krop",
    "wof:placetype":"venue"
},
  "geometry": {"coordinates":[-2.2254900932,52.2020111084],"type":"Point"}
}