{
  "type": "Feature",
  "properties": {
    "addr:full":"678 Bolton Road, Pendlebury, Swinton Manchester Greater Manchester M27 8FH",
    "addr:housenumber":"678",
    "addr:postcode":"m27 8fh",
    "addr:street":"Bolton Road",
    "iso:country":"GB",
    "sg:address":"678 Bolton Road, Pendlebury, Swinton",
    "sg:city":"Manchester",
    "sg:classifiers":[
        {
            "category":"Fast Food",
            "type":"Food & Drink"
        }
    ],
    "sg:phone":"+44 161 728 4707",
    "sg:postcode":"M27 8FH",
    "sg:province":"Greater Manchester",
    "sg:tags":[
        "delivery"
    ],
    "wof:name":"Liptes",
    "wof:placetype":"venue"
},
  "geometry": {"coordinates":[-2.3325250149,53.5185585022],"type":"Point"}
}