{
  "type": "Feature",
  "properties": {
    "addr:full":"Denton Street Carlisle Cumbria CA2 5HB",
    "addr:postcode":"ca2 5hb",
    "addr:street":"Denton Street",
    "iso:country":"GB",
    "sg:address":"Denton Street",
    "sg:city":"Carlisle",
    "sg:classifiers":[
        {
            "category":"Bars & Pubs",
            "type":"Food & Drink"
        }
    ],
    "sg:phone":"+44 1228 529311",
    "sg:postcode":"CA2 5HB",
    "sg:province":"Cumbria",
    "sg:tags":[
        "pubs",
        "inn"
    ],
    "wof:name":"Prince of Wales",
    "wof:placetype":"venue"
},
  "geometry": {"coordinates":[-2.939514,54.88826],"type":"Point"}
}