{
  "type": "Feature",
  "properties": {
    "addr:full":"Unit 14, Hetton Lyons Industrial Estate, Hetton Le Hole Houghton-le-spring Durham DH5 0RH",
    "addr:housenumber":"unit;hetton",
    "addr:postcode":"dh5 0rh",
    "addr:street":"Lyons Industrial",
    "iso:country":"GB",
    "sg:address":"Unit 14, Hetton Lyons Industrial Estate, Hetton Le Hole",
    "sg:city":"Houghton-le-spring",
    "sg:classifiers":[
        {
            "category":"Building & Trades",
            "subcategory":"Plumbing",
            "type":"Services"
        }
    ],
    "sg:phone":"+44 191 526 8106",
    "sg:postcode":"DH5 0RH",
    "sg:province":"Durham",
    "sg:tags":[
        "heating"
    ],
    "wof:name":"Sunter Ltd.",
    "wof:placetype":"venue"
},
  "geometry": {"coordinates":[-1.4686470032,54.8388786316],"type":"Point"}
}