{
  "type": "Feature",
  "properties": {
    "addr:full":"Kensington Road Thornton-cleveleys Lancashire FY5 1ER",
    "addr:postcode":"fy5 1er",
    "addr:street":"Kensington Road",
    "iso:country":"GB",
    "sg:address":"Kensington Road",
    "sg:city":"Thornton-cleveleys",
    "sg:classifiers":[
        {
            "category":"Community Center",
            "type":"Public Place"
        },
        {
            "category":"Government",
            "subcategory":"Office",
            "type":"Public Place"
        }
    ],
    "sg:phone":"+44 1253 863369",
    "sg:postcode":"FY5 1ER",
    "sg:province":"Lancashire",
    "sg:tags":[
        "agency",
        "education",
        "authority",
        "centre"
    ],
    "wof:name":"Frank Townsend Community Centre",
    "wof:placetype":"venue"
},
  "geometry": {"coordinates":[-3.0442390442,53.880191803],"type":"Point"}
}