{
  "type": "Feature",
  "properties": {
    "addr:full":"Shielhill Farm, Inverkip Greenock Inverclyde PA16 9NB",
    "addr:postcode":"pa16 9nb",
    "addr:street":"Inverkip Greenock",
    "iso:country":"GB",
    "sg:address":"Shielhill Farm, Inverkip",
    "sg:city":"Greenock",
    "sg:classifiers":[
        {
            "category":"Farming",
            "subcategory":"Livestock Farm",
            "type":"Manufacturing & Wholesale Goods"
        }
    ],
    "sg:phone":"+44 1475 521223",
    "sg:postcode":"PA16 9NB",
    "sg:province":"Inverclyde",
    "sg:tags":[
        "others"
    ],
    "wof:name":"A McIntyre",
    "wof:placetype":"venue"
},
  "geometry": {"coordinates":[-4.8158202171,55.9093894958],"type":"Point"}
}