{
  "type": "Feature",
  "properties": {
    "addr:full":"Anmer Cottage, Methwold Road Thetford Norfolk IP26 5LN",
    "addr:housenumber":"anmer",
    "addr:postcode":"ip26 5ln",
    "addr:street":"Methwold Road",
    "iso:country":"GB",
    "sg:address":"Anmer Cottage, Methwold Road",
    "sg:city":"Thetford",
    "sg:classifiers":[
        {
            "category":"Retail",
            "subcategory":"Funeral Services",
            "type":"Services"
        }
    ],
    "sg:postcode":"IP26 5LN",
    "sg:province":"Norfolk",
    "sg:tags":[
        "cemetery",
        "crematorium"
    ],
    "wof:name":"Northwold & Brandon Funeral Services",
    "wof:placetype":"venue"
},
  "geometry": {"coordinates":[0.5796599984,52.541519165],"type":"Point"}
}