{
  "type": "Feature",
  "properties": {
    "iso:country":"GB",
    "sg:address":"112 South Street",
    "sg:city":"Braintree",
    "sg:classifiers":[
        {
            "category":"Insurance",
            "subcategory":"Insurance Agent",
            "type":"Services"
        }
    ],
    "sg:phone":"+44 1376 326262",
    "sg:postcode":"CM7 3QQ",
    "sg:province":"Essex",
    "wof:name":"Quartile Ltd.",
    "wof:placetype":"venue"
},
  "geometry": {"coordinates":[0.555364,51.876495],"type":"Point"}
}