{
  "type": "Feature",
  "properties": {
    "iso:country":"GB",
    "sg:address":"Units 13-15 Gun Wharf Business Centre, Old Ford Rd",
    "sg:city":"Bow",
    "sg:classifiers":[
        {
            "category":"Food & Beverages",
            "subcategory":"Bakery",
            "type":"Retail Goods"
        }
    ],
    "sg:phone":"+44 20 8980 4456",
    "sg:postcode":"E3 5QB",
    "sg:province":"Greater London",
    "sg:tags":[
        "confectionery"
    ],
    "wof:name":"Bow Bakeries (Wholesale) Ltd",
    "wof:placetype":"venue"
},
  "geometry": {"coordinates":[-0.03934,51.53384],"type":"Point"}
}