{
  "type": "Feature",
  "properties": {
    "iso:country":"GB",
    "sg:address":"400 Sauchiehall St",
    "sg:city":"Glasgow",
    "sg:classifiers":[
        {
            "category":"Professional",
            "type":"Services"
        }
    ],
    "sg:postcode":"G2 3JD",
    "sg:province":"Glasgow City",
    "sg:tags":[
        "interior",
        "furnishers",
        "designer"
    ],
    "wof:name":"Skopos Design",
    "wof:placetype":"venue"
},
  "geometry": {"coordinates":[-4.265943,55.865837],"type":"Point"}
}