{
  "type": "Feature",
  "properties": {
    "iso:country":"GB",
    "sg:address":"Lyndale Court, London Rd",
    "sg:city":"Grays",
    "sg:classifiers":[
        {
            "category":"Education",
            "subcategory":"Special Training",
            "type":"Public Place"
        }
    ],
    "sg:phone":"+44 1708 861339",
    "sg:postcode":"RM20 3BJ",
    "sg:province":"Essex",
    "sg:tags":[
        "product",
        "centre"
    ],
    "wof:name":"RTA Adr",
    "wof:placetype":"venue"
},
  "geometry": {"coordinates":[0.3224849999,51.4783210754],"type":"Point"}
}