{
  "type": "Feature",
  "properties": {
    "addr:full":"Tesco Stores Ltd, Transit Way Plymouth Devon PL5 3TW",
    "addr:postcode":"pl5 3tw",
    "addr:street":"Transit Way",
    "iso:country":"GB",
    "sg:address":"Tesco Stores Ltd, Transit Way",
    "sg:city":"Plymouth",
    "sg:classifiers":[
        {
            "category":"Health Services",
            "subcategory":"Optometrist",
            "type":"Services"
        }
    ],
    "sg:phone":"+44 1752 795215",
    "sg:postcode":"PL5 3TW",
    "sg:province":"Devon",
    "sg:tags":[
        "optician"
    ],
    "wof:name":"Co-Op Eyecare",
    "wof:placetype":"venue"
},
  "geometry": {"coordinates":[-4.1513900757,50.4113616943],"type":"Point"}
}