{
  "type": "Feature",
  "properties": {
    "iso:country":"GB",
    "sg:address":"Rokesly Avenue",
    "sg:city":"London",
    "sg:classifiers":[
        {
            "category":"Education",
            "subcategory":"School",
            "type":"Public Place"
        }
    ],
    "sg:phone":"+44 20 8348 0290",
    "sg:postcode":"N8 8NH",
    "sg:province":"Greater London",
    "sg:tags":[
        "local",
        "authority"
    ],
    "wof:name":"Rokesly Junior School",
    "wof:placetype":"venue"
},
  "geometry": {"coordinates":[-0.121636,51.584114],"type":"Point"}
}