{
  "type": "Feature",
  "properties": {
    "iso:country":"GB",
    "sg:address":"53a Queen Street",
    "sg:city":"Louth",
    "sg:classifiers":[
        {
            "category":"Parking",
            "type":"Transportation"
        }
    ],
    "sg:phone":"+44 1507 602774",
    "sg:postcode":"LN11 9BJ",
    "sg:province":"Lincolnshire",
    "sg:tags":[
        "car",
        "valet"
    ],
    "wof:name":"Louth Car Valeting Service",
    "wof:placetype":"venue"
},
  "geometry": {"coordinates":[-0.001492,53.366756],"type":"Point"}
}