{
  "type": "Feature",
  "properties": {
    "iso:country":"GB",
    "sg:address":"21 Lockbridge Way, Milnsbridge",
    "sg:city":"Huddersfield",
    "sg:classifiers":[
        {
            "category":"Professional",
            "subcategory":"Engineering",
            "type":"Services"
        }
    ],
    "sg:postcode":"HD3 4NQ",
    "sg:province":"West Yorkshire",
    "sg:tags":[
        "contractor",
        "electrical",
        "engineer"
    ],
    "wof:name":"Vision Ariels",
    "wof:placetype":"venue"
},
  "geometry": {"coordinates":[-1.821269,53.63908],"type":"Point"}
}