{
  "type": "Feature",
  "properties": {
    "addr:full":"No 1 Wharf Bridge Street, Clay Cross Chesterfield Derbyshire S45 9NU",
    "addr:postcode":"s45 9nu",
    "addr:street":"Wharf Bridge Street",
    "iso:country":"GB",
    "sg:address":"No 1 Wharf Bridge Street, Clay Cross",
    "sg:city":"Chesterfield",
    "sg:classifiers":[
        {
            "category":"Utilities",
            "subcategory":"Fuel Oil & Lpg",
            "type":"Services"
        }
    ],
    "sg:phone":"+44 1246 863519",
    "sg:postcode":"S45 9NU",
    "sg:province":"Derbyshire",
    "sg:tags":[
        "coal",
        "smokeless"
    ],
    "wof:name":"Sorrells Fuels",
    "wof:placetype":"venue"
},
  "geometry": {"coordinates":[-1.415717,53.165791],"type":"Point"}
}