{
  "type": "Feature",
  "properties": {
    "addr:full":"71-73 Balby Road Doncaster South Yorkshire DN4 0RE",
    "addr:housenumber":"71-73",
    "addr:postcode":"dn4 0re",
    "addr:street":"Balby Road",
    "iso:country":"GB",
    "sg:address":"71-73 Balby Road",
    "sg:city":"Doncaster",
    "sg:classifiers":[
        {
            "category":"Shopping",
            "subcategory":"Books",
            "type":"Retail Goods"
        }
    ],
    "sg:phone":"+44 1302 738800",
    "sg:postcode":"DN4 0RE",
    "sg:province":"South Yorkshire",
    "wof:name":"The Food & Beverage Review Ltd.",
    "wof:placetype":"venue"
},
  "geometry": {"coordinates":[-1.145682,53.509666],"type":"Point"}
}