{
  "type": "Feature",
  "properties": {
    "addr:full":"61 Little Common Road Bexhill-on-sea East Sussex TN39 4HU",
    "addr:housenumber":"61",
    "addr:postcode":"tn39 4hu",
    "addr:street":"Little Common Road",
    "iso:country":"GB",
    "sg:address":"61 Little Common Road",
    "sg:city":"Bexhill-on-sea",
    "sg:classifiers":[
        {
            "category":"Health Services",
            "subcategory":"Podiatrist",
            "type":"Services"
        }
    ],
    "sg:phone":"+44 1424 731138",
    "sg:postcode":"TN39 4HU",
    "sg:province":"East Sussex",
    "sg:tags":[
        "podiatrists",
        "chiropodist"
    ],
    "wof:name":"J H Charles Chiropodist",
    "wof:placetype":"venue"
},
  "geometry": {"coordinates":[0.4612579942,50.8458862305],"type":"Point"}
}