{
  "type": "Feature",
  "properties": {
    "addr:full":"28 Hangleton Road Hove East Sussex BN3 7GE",
    "addr:housenumber":"28",
    "addr:postcode":"bn3 7ge",
    "addr:street":"Hangleton Road",
    "iso:country":"GB",
    "sg:address":"28 Hangleton Road",
    "sg:city":"Hove",
    "sg:classifiers":[
        {
            "category":"Building & Trades",
            "subcategory":"Construction",
            "type":"Services"
        }
    ],
    "sg:postcode":"BN3 7GE",
    "sg:province":"East Sussex",
    "sg:tags":[
        "ceiling",
        "contractor"
    ],
    "wof:name":"R A & S A Jackson",
    "wof:placetype":"venue"
},
  "geometry": {"coordinates":[-0.2037889957,50.8396759033],"type":"Point"}
}