{
  "type": "Feature",
  "properties": {
    "addr:full":"473 Stratford Road, Shirley Solihull West Midlands B90 4AD",
    "addr:housenumber":"473",
    "addr:postcode":"b90 4ad",
    "addr:street":"Stratford Road",
    "iso:country":"GB",
    "sg:address":"473 Stratford Road, Shirley",
    "sg:city":"Solihull",
    "sg:classifiers":[
        {
            "category":"Shopping",
            "subcategory":"Stationery & Office Supplies",
            "type":"Retail Goods"
        },
        {
            "category":"Professional",
            "subcategory":"Printing & Photocopies",
            "type":"Services"
        },
        {
            "category":"Professional",
            "subcategory":"Computer Services",
            "type":"Services"
        }
    ],
    "sg:phone":"+44 870 464 6131",
    "sg:postcode":"B90 4AD",
    "sg:province":"West Midlands",
    "sg:tags":[
        "printer",
        "system",
        "software"
    ],
    "wof:name":"Etrinsic Plc",
    "wof:placetype":"venue"
},
  "geometry": {"coordinates":[-1.821631,52.402466],"type":"Point"}
}