{
  "type": "Feature",
  "properties": {
    "addr:full":"325 Boxley Road Maidstone Kent ME14 2HN",
    "addr:housenumber":"325",
    "addr:postcode":"me14 2hn",
    "addr:street":"Boxley Road",
    "iso:country":"GB",
    "sg:address":"325 Boxley Road",
    "sg:city":"Maidstone",
    "sg:classifiers":[
        {
            "category":"Food & Beverages",
            "subcategory":"Meat & Fish",
            "type":"Retail Goods"
        }
    ],
    "sg:postcode":"ME14 2HN",
    "sg:province":"Kent",
    "sg:tags":[
        "chip"
    ],
    "wof:name":"Cornfords",
    "wof:placetype":"venue"
},
  "geometry": {"coordinates":[0.5359879732,51.2884101868],"type":"Point"}
}