{
  "type": "Feature",
  "properties": {
    "addr:full":"Stacey Yard, 5 Fielding Road, Cheshunt Waltham Cross Essex EN8 9TL",
    "addr:housenumber":"5",
    "addr:postcode":"en8 9tl",
    "addr:street":"Stacey;Fielding Road",
    "iso:country":"GB",
    "sg:address":"Stacey Yard, 5 Fielding Road, Cheshunt",
    "sg:city":"Waltham Cross",
    "sg:classifiers":[
        {
            "category":"Retail",
            "subcategory":"Auto Repair",
            "type":"Services"
        }
    ],
    "sg:phone":"+44 1992 640338",
    "sg:postcode":"EN8 9TL",
    "sg:province":"Essex",
    "sg:tags":[
        "modification",
        "garage"
    ],
    "wof:name":"Flamstead End Auto Services",
    "wof:placetype":"venue"
},
  "geometry": {"coordinates":[-0.033814,51.69051],"type":"Point"}
}