{
  "type": "Feature",
  "properties": {
    "iso:country":"GB",
    "sg:address":"3 Sheridan Centre, Mount Row",
    "sg:city":"Stafford",
    "sg:classifiers":[
        {
            "category":"Shopping",
            "subcategory":"Gifts & Souvenirs",
            "type":"Retail Goods"
        }
    ],
    "sg:postcode":"ST16 2AD",
    "sg:province":"Staffordshire",
    "sg:tags":[
        "poster",
        "card"
    ],
    "wof:name":"Campbell,Pamela Joan,",
    "wof:placetype":"venue"
},
  "geometry": {"coordinates":[-2.121768,52.803959],"type":"Point"}
}