{
  "type": "Feature",
  "properties": {
    "iso:country":"GB",
    "sg:address":"Stroudwood, Upham",
    "sg:city":"Southampton",
    "sg:classifiers":[
        {
            "category":"Farming",
            "subcategory":"Dairy Farm",
            "type":"Manufacturing & Wholesale Goods"
        }
    ],
    "sg:phone":"+44 1489 860184",
    "sg:postcode":"SO32 1HG",
    "sg:province":"Hampshire",
    "wof:name":"R J & M Hill",
    "wof:placetype":"venue"
},
  "geometry": {"coordinates":[-1.234751,50.982391],"type":"Point"}
}