{
  "type": "Feature",
  "properties": {
    "addr:full":"20 Heather Gardens Newbury Berkshire RG14 7RG",
    "addr:housenumber":"20",
    "addr:postcode":"rg14 7rg",
    "addr:street":"Heather Gardens",
    "iso:country":"GB",
    "sg:address":"20 Heather Gardens",
    "sg:city":"Newbury",
    "sg:classifiers":[
        {
            "category":"Banks & Credit Unions",
            "subcategory":"Financial Services",
            "type":"Services"
        }
    ],
    "sg:phone":"+44 1635 524403",
    "sg:postcode":"RG14 7RG",
    "sg:province":"Berkshire",
    "sg:tags":[
        "adviser"
    ],
    "wof:name":"Meridan Park Associates Ltd.",
    "wof:placetype":"venue"
},
  "geometry": {"coordinates":[-1.3337379694,51.383769989],"type":"Point"}
}