{
  "type": "Feature",
  "properties": {
    "iso:country":"GB",
    "sg:address":"43 Newmarket St",
    "sg:city":"Norwich",
    "sg:classifiers":[
        {
            "category":"Personal",
            "subcategory":"Beauty Salon",
            "type":"Services"
        }
    ],
    "sg:phone":"+44 1603 610992",
    "sg:postcode":"NR2 2DP",
    "sg:province":"Norfolk",
    "sg:tags":[
        "unisex",
        "hairdresser"
    ],
    "wof:name":"Hairflair",
    "wof:placetype":"venue"
},
  "geometry": {"coordinates":[1.282234,52.622093],"type":"Point"}
}