{
  "type": "Feature",
  "properties": {
    "iso:country":"GB",
    "sg:address":"Herrieffs, Ham Road, Liddington",
    "sg:city":"Swindon",
    "sg:classifiers":[
        {
            "category":"Building & Trades",
            "subcategory":"Construction",
            "type":"Services"
        }
    ],
    "sg:phone":"+44 1793 790384",
    "sg:postcode":"SN4 0HH",
    "sg:province":"Wiltshire",
    "sg:tags":[
        "decorator",
        "painter"
    ],
    "wof:name":"Walter John Crayford",
    "wof:placetype":"venue"
},
  "geometry": {"coordinates":[-1.704659,51.530834],"type":"Point"}
}