{
  "type": "Feature",
  "properties": {
    "addr:full":"1 Ardross Terrace Inverness Highland IV3 5NQ",
    "addr:housenumber":"1",
    "addr:postcode":"iv3 5nq",
    "addr:street":"Ardross Terrace",
    "iso:country":"GB",
    "sg:address":"1 Ardross Terrace",
    "sg:city":"Inverness",
    "sg:classifiers":[
        {
            "category":"Travel",
            "subcategory":"Hotels & Motels",
            "type":"Entertainment"
        }
    ],
    "sg:phone":"+44 1463 232878",
    "sg:postcode":"IV3 5NQ",
    "sg:province":"Highland",
    "wof:name":"Macdonald House Hotel",
    "wof:placetype":"venue"
},
  "geometry": {"coordinates":[-4.228958,57.475346],"type":"Point"}
}