{
  "type": "Feature",
  "properties": {
    "iso:country":"GB",
    "sg:address":"26 The Marlowes Centre, Marlowes",
    "sg:city":"Hemel Hempstead",
    "sg:classifiers":[
        {
            "category":"Shopping",
            "subcategory":"Shoes",
            "type":"Retail Goods"
        }
    ],
    "sg:phone":"+44 1442 233251",
    "sg:postcode":"HP1 1DX",
    "sg:province":"Hertfordshire",
    "sg:tags":[
        "shop",
        "retailer",
        "footwear"
    ],
    "sg:website":"http://www.shoezone.co.uk",
    "wof:name":"Shoe Zone",
    "wof:placetype":"venue"
},
  "geometry": {"coordinates":[-0.4750840068,51.7490005493],"type":"Point"}
}