{
  "type": "Feature",
  "properties": {
    "iso:country":"GB",
    "sg:address":"Norfolk Ho, Exchange St",
    "sg:city":"Norwich",
    "sg:classifiers":[
        {
            "category":"Banks & Credit Unions",
            "subcategory":"Bank",
            "type":"Services"
        }
    ],
    "sg:postcode":"NR2 1DD",
    "sg:province":"Norfolk",
    "wof:name":"National Westminster Bank Plc",
    "wof:placetype":"venue"
},
  "geometry": {"coordinates":[1.29338,52.630112],"type":"Point"}
}