{
  "type": "Feature",
  "properties": {
    "iso:country":"GB",
    "sg:address":"Roman Road",
    "sg:city":"Taunton",
    "sg:classifiers":[
        {
            "category":"Bars & Pubs",
            "type":"Food & Drink"
        }
    ],
    "sg:phone":"+44 1823 337424",
    "sg:postcode":"TA1 2BL",
    "sg:province":"Somerset",
    "sg:tags":[
        "pubs",
        "inn"
    ],
    "wof:name":"Oxford Inn",
    "wof:placetype":"venue"
},
  "geometry": {"coordinates":[-3.076114,51.020271],"type":"Point"}
}