{
  "type": "Feature",
  "properties": {
    "addr:full":"23 Vespasian Road, Roman Way Andover Hampshire SP10 5JP",
    "addr:housenumber":"23",
    "addr:postcode":"sp10 5jp",
    "addr:street":"Vespasian Road Roman Way",
    "iso:country":"GB",
    "sg:address":"23 Vespasian Road, Roman Way",
    "sg:city":"Andover",
    "sg:classifiers":[
        {
            "category":"Building & Trades",
            "subcategory":"Construction",
            "type":"Services"
        }
    ],
    "sg:postcode":"SP10 5JP",
    "sg:province":"Hampshire",
    "sg:tags":[
        "joiner",
        "carpenter"
    ],
    "wof:name":"Bill Ivey Carpentry Contractor",
    "wof:placetype":"venue"
},
  "geometry": {"coordinates":[-1.477719,51.224979],"type":"Point"}
}