{
  "type": "Feature",
  "properties": {
    "iso:country":"GB",
    "sg:address":"10 Downing St",
    "sg:city":"Smethwick",
    "sg:classifiers":[
        {
            "category":"Wholesale",
            "subcategory":"Construction Materials",
            "type":"Manufacturing & Wholesale Goods"
        }
    ],
    "sg:phone":"+44 121 558 2421",
    "sg:postcode":"B66 2PA",
    "sg:province":"West Midlands",
    "sg:tags":[
        "coating",
        "powder"
    ],
    "wof:name":"Burnsall Ltd",
    "wof:placetype":"venue"
},
  "geometry": {"coordinates":[-1.959449,52.500912],"type":"Point"}
}