{
  "type": "Feature",
  "properties": {
    "iso:country":"GB",
    "sg:address":"38a St Lukes Road, Old Windsor",
    "sg:city":"Windsor",
    "sg:classifiers":[
        {
            "category":"Professional",
            "subcategory":"Business Services",
            "type":"Services"
        }
    ],
    "sg:phone":"+44 1753 862535",
    "sg:postcode":"SL4 2QQ",
    "sg:province":"Berkshire",
    "sg:tags":[
        "bookmaker"
    ],
    "wof:name":"Taylors Racing Service Ltd.",
    "wof:placetype":"venue"
},
  "geometry": {"coordinates":[-0.585839,51.462482],"type":"Point"}
}