{
  "type": "Feature",
  "properties": {
    "iso:country":"GB",
    "sg:address":"55-56 Fore Street",
    "sg:city":"Trowbridge",
    "sg:classifiers":[
        {
            "category":"Education",
            "subcategory":"College",
            "type":"Public Place"
        }
    ],
    "sg:phone":"+44 1225 753586",
    "sg:postcode":"BA14 8ET",
    "sg:province":"Wiltshire",
    "sg:tags":[
        "school"
    ],
    "wof:name":"Scholars",
    "wof:placetype":"venue"
},
  "geometry": {"coordinates":[-2.208007,51.321209],"type":"Point"}
}