{
  "type": "Feature",
  "properties": {
    "iso:country":"GB",
    "sg:address":"Unit 34 28 Old Brompton Road, South Kensington",
    "sg:city":"London",
    "sg:classifiers":[
        {
            "category":"Banks & Credit Unions",
            "subcategory":"Investment Brokerage",
            "type":"Services"
        }
    ],
    "sg:postcode":"SW7 3SS",
    "sg:province":"Greater London",
    "sg:tags":[
        "fund",
        "raising"
    ],
    "wof:name":"Pegasus Promotion Ag Ltd",
    "wof:placetype":"venue"
},
  "geometry": {"coordinates":[-0.175388,51.493641],"type":"Point"}
}