{
  "type": "Feature",
  "properties": {
    "addr:full":"50 Lincoln St, Tipshelf Belper Derbyshire DE56 2JH",
    "addr:housenumber":"50",
    "addr:postcode":"de56 2jh",
    "addr:street":"Lincoln St",
    "iso:country":"GB",
    "sg:address":"50 Lincoln St, Tipshelf",
    "sg:city":"Belper",
    "sg:classifiers":[
        {
            "category":"Building & Trades",
            "subcategory":"Equipment Rental",
            "type":"Services"
        }
    ],
    "sg:phone":"+44 1773 874466",
    "sg:postcode":"DE56 2JH",
    "sg:province":"Derbyshire",
    "sg:tags":[
        "plant",
        "machinery"
    ],
    "wof:name":"I S Rowe",
    "wof:placetype":"venue"
},
  "geometry": {"coordinates":[-1.475982,53.02861],"type":"Point"}
}