{
  "type": "Feature",
  "properties": {
    "addr:full":"Argyle, Springfield Park Durham Durham DH1 4LS",
    "addr:postcode":"dh1 4ls",
    "addr:street":"Park",
    "iso:country":"GB",
    "sg:address":"Argyle, Springfield Park",
    "sg:city":"Durham",
    "sg:classifiers":[
        {
            "category":"Professional",
            "type":"Services"
        }
    ],
    "sg:postcode":"DH1 4LS",
    "sg:province":"Durham",
    "sg:tags":[
        "entertainer"
    ],
    "wof:name":"Hospital Entertainment",
    "wof:placetype":"venue"
},
  "geometry": {"coordinates":[-1.593117,54.783989],"type":"Point"}
}