{
  "type": "Feature",
  "properties": {
    "addr:full":"Bryn Maen Blaenau Ffestiniog Gwynedd LL41 4HN",
    "addr:postcode":"ll41 4hn",
    "iso:country":"GB",
    "sg:address":"Bryn Maen",
    "sg:city":"Blaenau Ffestiniog",
    "sg:classifiers":[
        {
            "category":"Transit Center",
            "subcategory":"Freight",
            "type":"Transportation"
        }
    ],
    "sg:phone":"+44 1766 590665",
    "sg:postcode":"LL41 4HN",
    "sg:province":"Gwynedd",
    "sg:tags":[
        "shop",
        "craft",
        "centre"
    ],
    "wof:name":"Moksha Crafts",
    "wof:placetype":"venue"
},
  "geometry": {"coordinates":[-3.931559,52.961349],"type":"Point"}
}