{
  "type": "Feature",
  "properties": {
    "addr:full":"Main Rd Keighley North Yorkshire BD20 5SP",
    "addr:postcode":"bd20 5sp",
    "addr:street":"Main Rd",
    "iso:country":"GB",
    "sg:address":"Main Rd",
    "sg:city":"Keighley",
    "sg:classifiers":[
        {
            "category":"Bars & Pubs",
            "type":"Food & Drink"
        }
    ],
    "sg:phone":"+44 1274 550931",
    "sg:postcode":"BD20 5SP",
    "sg:province":"North Yorkshire",
    "sg:tags":[
        "pubs",
        "inn"
    ],
    "wof:name":"Busfield Arms",
    "wof:placetype":"venue"
},
  "geometry": {"coordinates":[-1.8497949839,53.8747825623],"type":"Point"}
}