{
  "type": "Feature",
  "properties": {
    "addr:full":"Reams Cotts, Mill Lane, Worth Deal Kent CT14 0DU",
    "addr:postcode":"ct14 0du",
    "addr:street":"Mill Lane;Deal",
    "iso:country":"GB",
    "sg:address":"Reams Cotts, Mill Lane, Worth",
    "sg:city":"Deal",
    "sg:classifiers":[
        {
            "category":"Building & Trades",
            "subcategory":"Landscaping Services",
            "type":"Services"
        }
    ],
    "sg:phone":"+44 1304 613920",
    "sg:postcode":"CT14 0DU",
    "sg:province":"Kent",
    "sg:tags":[
        "consultant"
    ],
    "wof:name":"Visionmonth Ltd.",
    "wof:placetype":"venue"
},
  "geometry": {"coordinates":[1.3472839594,51.2563552856],"type":"Point"}
}