{
  "type": "Feature",
  "properties": {
    "addr:full":"127-129 Queensway, Bletchley Milton Keynes Buckinghamshire MK2 2DH",
    "addr:housenumber":"127-129",
    "addr:postcode":"mk2 2dh",
    "addr:street":"Queensway",
    "iso:country":"GB",
    "sg:address":"127-129 Queensway, Bletchley",
    "sg:city":"Milton Keynes",
    "sg:classifiers":[
        {
            "category":"Shopping",
            "subcategory":"Pharmacy",
            "type":"Retail Goods"
        }
    ],
    "sg:phone":"+44 1908 373674",
    "sg:postcode":"MK2 2DH",
    "sg:province":"Buckinghamshire",
    "sg:tags":[
        "pharmacist",
        "chemist"
    ],
    "wof:name":"Lloyds Chemist",
    "wof:placetype":"venue"
},
  "geometry": {"coordinates":[-0.728739,51.995106],"type":"Point"}
}