{
  "type": "Feature",
  "properties": {
    "iso:country":"GB",
    "sg:address":"Whickham Highway",
    "sg:city":"Gateshead",
    "sg:classifiers":[
        {
            "category":"Health Services",
            "subcategory":"Hospital",
            "type":"Services"
        }
    ],
    "sg:phone":"+44 191 402 6474",
    "sg:postcode":"NE11 9QT",
    "sg:province":"Tyne and Wear",
    "wof:name":"Gateshead Health Nhs Trust",
    "wof:placetype":"venue"
},
  "geometry": {"coordinates":[-1.65946,54.946411],"type":"Point"}
}