{
  "type": "Feature",
  "properties": {
    "iso:country":"GB",
    "sg:address":"2 High Street, Tettenhall",
    "sg:city":"Wolverhampton",
    "sg:classifiers":[
        {
            "category":"Shopping",
            "subcategory":"Optician",
            "type":"Retail Goods"
        }
    ],
    "sg:phone":"+44 1902 758811",
    "sg:postcode":"WV6 8QT",
    "sg:province":"Shropshire",
    "wof:name":"Lewis Elton Ltd.",
    "wof:placetype":"venue"
},
  "geometry": {"coordinates":[-2.168076992,52.5983695984],"type":"Point"}
}