{
  "type": "Feature",
  "properties": {
    "addr:full":"280 Barking Road, East Ham London Greater London E6 3BA",
    "addr:housenumber":"280",
    "addr:postcode":"e6 3ba",
    "addr:street":"Barking Road",
    "iso:country":"GB",
    "sg:address":"280 Barking Road, East Ham",
    "sg:city":"London",
    "sg:classifiers":[
        {
            "category":"Shopping",
            "subcategory":"Shoes",
            "type":"Retail Goods"
        }
    ],
    "sg:phone":"+44 20 8552 2026",
    "sg:postcode":"E6 3BA",
    "sg:province":"Greater London",
    "sg:tags":[
        "shop"
    ],
    "wof:name":"Buckle & Sons Ltd.",
    "wof:placetype":"venue"
},
  "geometry": {"coordinates":[0.051142,51.532352],"type":"Point"}
}