{
  "type": "Feature",
  "properties": {
    "addr:full":"1 Fore St Cullompton Devon EX15 1JW",
    "addr:housenumber":"1",
    "addr:postcode":"ex15 1jw",
    "addr:street":"Fore St",
    "iso:country":"GB",
    "sg:address":"1 Fore St",
    "sg:city":"Cullompton",
    "sg:classifiers":[
        {
            "category":"Travel",
            "subcategory":"Travel Agent",
            "type":"Entertainment"
        }
    ],
    "sg:phone":"+44 1884 33006",
    "sg:postcode":"EX15 1JW",
    "sg:province":"Devon",
    "wof:name":"Bowles International Travel Agency",
    "wof:placetype":"venue"
},
  "geometry": {"coordinates":[-3.3927719593,50.8573112488],"type":"Point"}
}