{
  "type": "Feature",
  "properties": {
    "addr:full":"Hawthorn Farm House, Marden Devizes Wiltshire SN10 3RQ",
    "addr:postcode":"sn10 3rq",
    "iso:country":"GB",
    "sg:address":"Hawthorn Farm House, Marden",
    "sg:city":"Devizes",
    "sg:classifiers":[
        {
            "category":"Professional",
            "type":"Services"
        }
    ],
    "sg:postcode":"SN10 3RQ",
    "sg:province":"Wiltshire",
    "sg:tags":[
        "interior",
        "furnishers",
        "designer"
    ],
    "wof:name":"Anne Cater Designs",
    "wof:placetype":"venue"
},
  "geometry": {"coordinates":[-1.8810310364,51.3153877258],"type":"Point"}
}