{
  "type": "Feature",
  "properties": {
    "iso:country":"GB",
    "sg:address":"9 Langwood Close, Eaton Socon",
    "sg:city":"St Neots",
    "sg:classifiers":[
        {
            "category":"Professional",
            "subcategory":"Advertising",
            "type":"Services"
        }
    ],
    "sg:postcode":"PE19 7QN",
    "sg:province":"Bedfordshire",
    "wof:name":"Long Associates",
    "wof:placetype":"venue"
},
  "geometry": {"coordinates":[-0.2869699895,52.2326889038],"type":"Point"}
}