{
  "type": "Feature",
  "properties": {
    "iso:country":"GB",
    "sg:address":"Unit 5 Ham Lane Farm, Ham Lane",
    "sg:city":"Haywards Heath",
    "sg:classifiers":[
        {
            "category":"Building & Trades",
            "subcategory":"Construction",
            "type":"Services"
        }
    ],
    "sg:postcode":"RH17 7PR",
    "sg:province":"East Sussex",
    "sg:tags":[
        "excavation",
        "groundwork",
        "contractor"
    ],
    "wof:name":"Shifters",
    "wof:placetype":"venue"
},
  "geometry": {"coordinates":[-0.056943,50.991543],"type":"Point"}
}