{
  "type": "Feature",
  "properties": {
    "addr:full":"43 Mitchell St Clerkenwell Greater London EC1V 3QD",
    "addr:housenumber":"43",
    "addr:postcode":"ec1v 3qd",
    "addr:street":"Mitchell St",
    "iso:country":"GB",
    "sg:address":"43 Mitchell St",
    "sg:city":"Clerkenwell",
    "sg:classifiers":[
        {
            "category":"Professional",
            "subcategory":"Art Services",
            "type":"Services"
        }
    ],
    "sg:phone":"+44 20 7250 1146",
    "sg:postcode":"EC1V 3QD",
    "sg:province":"Greater London",
    "sg:tags":[
        "framing"
    ],
    "wof:name":"Tony Guest",
    "wof:placetype":"venue"
},
  "geometry": {"coordinates":[-0.094569,51.52544],"type":"Point"}
}