{
  "type": "Feature",
  "properties": {
    "iso:country":"GB",
    "sg:address":"Brunel Way, Durranhill Industrial Estate",
    "sg:city":"Carlisle",
    "sg:classifiers":[
        {
            "category":"Retail",
            "subcategory":"Auto Repair",
            "type":"Services"
        }
    ],
    "sg:phone":"+44 1228 402256",
    "sg:postcode":"CA1 3NQ",
    "sg:province":"Cumbria",
    "sg:tags":[
        "modification",
        "garage"
    ],
    "wof:name":"Westmorland Garage",
    "wof:placetype":"venue"
},
  "geometry": {"coordinates":[-2.9100630283,54.8835372925],"type":"Point"}
}