{
  "type": "Feature",
  "properties": {
    "iso:country":"GB",
    "sg:address":"Yeomans Lane, Newtown",
    "sg:city":"Newbury",
    "sg:classifiers":[
        {
            "category":"Manufacturing",
            "subcategory":"Petroleum Products",
            "type":"Manufacturing & Wholesale Goods"
        }
    ],
    "sg:phone":"+44 1635 278630",
    "sg:postcode":"RG20 9BL",
    "sg:province":"Berkshire",
    "sg:tags":[
        "double",
        "glazing"
    ],
    "wof:name":"Castle Windows (Newbury) Ltd.",
    "wof:placetype":"venue"
},
  "geometry": {"coordinates":[-1.3230290413,51.3584365845],"type":"Point"}
}