{
  "type": "Feature",
  "properties": {
    "addr:full":"Harriot Drive, Heathcote Industrial Estate Warwick Warwickshire CV34 6TJ",
    "addr:postcode":"cv34 6tj",
    "addr:street":"Harriot Drive;Industrial Estate",
    "iso:country":"GB",
    "sg:address":"Harriot Drive, Heathcote Industrial Estate",
    "sg:city":"Warwick",
    "sg:classifiers":[
        {
            "category":"Manufacturing",
            "subcategory":"Lumber",
            "type":"Manufacturing & Wholesale Goods"
        }
    ],
    "sg:phone":"+44 1926 883876",
    "sg:postcode":"CV34 6TJ",
    "sg:province":"Warwickshire",
    "sg:tags":[
        "importer",
        "merchants",
        "agent",
        "timber"
    ],
    "wof:name":"The Spa & Warwick Timber Co. Ltd.",
    "wof:placetype":"venue"
},
  "geometry": {"coordinates":[-1.550471,52.272274],"type":"Point"}
}