{
  "type": "Feature",
  "properties": {
    "addr:full":"116 Lustrells Vale, Saltdean Brighton East Sussex BN2 8FB",
    "addr:housenumber":"116",
    "addr:postcode":"bn2 8fb",
    "addr:street":"Lustrells Vale Saltdean",
    "iso:country":"GB",
    "sg:address":"116 Lustrells Vale, Saltdean",
    "sg:city":"Brighton",
    "sg:classifiers":[
        {
            "category":"Professional",
            "subcategory":"Accounting & Tax Preparation",
            "type":"Services"
        }
    ],
    "sg:phone":"+44 1273 502788",
    "sg:postcode":"BN2 8FB",
    "sg:province":"East Sussex",
    "sg:tags":[
        "accountant"
    ],
    "wof:name":"David Abercrombie & Richard Gibb",
    "wof:placetype":"venue"
},
  "geometry": {"coordinates":[-0.0366000012,50.8096466064],"type":"Point"}
}