{
  "type": "Feature",
  "properties": {
    "iso:country":"GB",
    "sg:address":"194 Tulse Hill",
    "sg:city":"Brixton",
    "sg:classifiers":[
        {
            "category":"Professional",
            "subcategory":"Management & Consulting",
            "type":"Services"
        }
    ],
    "sg:phone":"+44 20 8671 5104",
    "sg:postcode":"SW2 3BU",
    "sg:province":"Greater London",
    "sg:tags":[
        "music"
    ],
    "wof:name":"Mega Volume Management Ltd",
    "wof:placetype":"venue"
},
  "geometry": {"coordinates":[-0.107103,51.441078],"type":"Point"}
}