{
  "type": "Feature",
  "properties": {
    "addr:full":"17 Capetown Square Sunderland Tyne and Wear SR5 3LZ",
    "addr:housenumber":"17",
    "addr:postcode":"sr5 3lz",
    "addr:street":"Capetown Square",
    "iso:country":"GB",
    "sg:address":"17 Capetown Square",
    "sg:city":"Sunderland",
    "sg:classifiers":[
        {
            "category":"Social Services",
            "subcategory":"Adult Care",
            "type":"Services"
        }
    ],
    "sg:phone":"+44 191 548 1965",
    "sg:postcode":"SR5 3LZ",
    "sg:province":"Tyne and Wear",
    "sg:tags":[
        "housing",
        "sheltered"
    ],
    "wof:name":"Capetown Square Sheltered Housing",
    "wof:placetype":"venue"
},
  "geometry": {"coordinates":[-1.459234,54.923351],"type":"Point"}
}