{
  "type": "Feature",
  "properties": {
    "addr:full":"47 Cressex Enterprise Centre, Lincoln Road High Wycombe Buckinghamshire HP12 3RL",
    "addr:housenumber":"47",
    "addr:postcode":"hp12 3rl",
    "addr:street":"Cressex;Lincoln Road",
    "iso:country":"GB",
    "sg:address":"47 Cressex Enterprise Centre, Lincoln Road",
    "sg:city":"High Wycombe",
    "sg:classifiers":[
        {
            "category":"Professional",
            "subcategory":"Computer Services",
            "type":"Services"
        }
    ],
    "sg:phone":"+44 1494 614630",
    "sg:postcode":"HP12 3RL",
    "sg:province":"Buckinghamshire",
    "sg:tags":[
        "consultant"
    ],
    "wof:name":"Aldebaran Systems Ltd.",
    "wof:placetype":"venue"
},
  "geometry": {"coordinates":[-0.77107,51.625961],"type":"Point"}
}