{
  "type": "Feature",
  "properties": {
    "iso:country":"GB",
    "sg:address":"West London Synagogue, 33 Seymour Pl",
    "sg:city":"West End",
    "sg:classifiers":[
        {
            "category":"Education",
            "subcategory":"Dance Studio",
            "type":"Public Place"
        }
    ],
    "sg:phone":"+44 20 7289 1869",
    "sg:postcode":"W1H 6AT",
    "sg:province":"Greater London",
    "sg:tags":[
        "school",
        "dancing"
    ],
    "wof:name":"Susan Zalcman School Of Dancing",
    "wof:placetype":"venue"
},
  "geometry": {"coordinates":[-0.1547300071,51.5154685974],"type":"Point"}
}