{
  "type": "Feature",
  "properties": {
    "addr:full":"4 St Clements Close, Lower Early Reading Berkshire RG6 4BT",
    "addr:housenumber":"4",
    "addr:postcode":"rg6 4bt",
    "addr:street":"St Clements Close",
    "iso:country":"GB",
    "sg:address":"4 St Clements Close, Lower Early",
    "sg:city":"Reading",
    "sg:classifiers":[
        {
            "category":"Building & Trades",
            "subcategory":"Plumbing",
            "type":"Services"
        }
    ],
    "sg:postcode":"RG6 4BT",
    "sg:province":"Berkshire",
    "sg:tags":[
        "heating"
    ],
    "wof:name":"P Edgington",
    "wof:placetype":"venue"
},
  "geometry": {"coordinates":[-0.9203870296,51.4268341064],"type":"Point"}
}