{
  "type": "Feature",
  "properties": {
    "iso:country":"GB",
    "sg:address":"2 Herbert Street",
    "sg:city":"Swansea",
    "sg:classifiers":[
        {
            "category":"Shopping",
            "subcategory":"Clothing, Apparel, & Fashions",
            "type":"Retail Goods"
        }
    ],
    "sg:phone":"+44 1792 863133",
    "sg:postcode":"SA8 4EB",
    "sg:province":"Neath Port Talbot",
    "sg:tags":[
        "shop"
    ],
    "wof:name":"Joyce Thomas",
    "wof:placetype":"venue"
},
  "geometry": {"coordinates":[-3.8531720638,51.7203025818],"type":"Point"}
}