{
  "type": "Feature",
  "properties": {
    "addr:full":"517 Katherine Road London Greater London E7 8DR",
    "addr:housenumber":"517",
    "addr:postcode":"e7 8dr",
    "addr:street":"Katherine Road",
    "iso:country":"GB",
    "sg:address":"517 Katherine Road",
    "sg:city":"London",
    "sg:classifiers":[
        {
            "category":"Retail",
            "subcategory":"Driving School",
            "type":"Services"
        }
    ],
    "sg:phone":"+44 20 8551 4072",
    "sg:postcode":"E7 8DR",
    "sg:province":"Greater London",
    "wof:name":"Forest School of Motoring",
    "wof:placetype":"venue"
},
  "geometry": {"coordinates":[0.036235,51.545948],"type":"Point"}
}