{
  "type": "Feature",
  "properties": {
    "addr:full":"47 Shoreditch High St Whitechapel Greater London E1 6JN",
    "addr:housenumber":"47",
    "addr:postcode":"e1 6jn",
    "addr:street":"Shoreditch High St",
    "iso:country":"GB",
    "sg:address":"47 Shoreditch High St",
    "sg:city":"Whitechapel",
    "sg:classifiers":[
        {
            "category":"Professional",
            "subcategory":"Printing & Photocopies",
            "type":"Services"
        }
    ],
    "sg:phone":"+44 20 7729 2011",
    "sg:postcode":"E1 6JN",
    "sg:province":"Greater London",
    "sg:tags":[
        "printer"
    ],
    "wof:name":"Murographics Ltd",
    "wof:placetype":"venue"
},
  "geometry": {"coordinates":[-0.078519,51.521488],"type":"Point"}
}