{
  "type": "Feature",
  "properties": {
    "addr:full":"The Old Fisheries Forres Moray IV36 0YJ",
    "addr:postcode":"iv36 0yj",
    "iso:country":"GB",
    "sg:address":"The Old Fisheries",
    "sg:city":"Forres",
    "sg:classifiers":[
        {
            "category":"Recreation",
            "subcategory":"Water Park",
            "type":"Entertainment"
        }
    ],
    "sg:phone":"+44 1309 690239",
    "sg:postcode":"IV36 0YJ",
    "sg:province":"Moray",
    "sg:tags":[
        "sport"
    ],
    "wof:name":"Moray Water Sports",
    "wof:placetype":"venue"
},
  "geometry": {"coordinates":[-3.6304500103,57.6073989868],"type":"Point"}
}