{
  "type": "Feature",
  "properties": {
    "iso:country":"GB",
    "sg:address":"7 Ida Street",
    "sg:city":"London",
    "sg:classifiers":[
        {
            "category":"Travel",
            "subcategory":"Hotels & Motels",
            "type":"Entertainment"
        }
    ],
    "sg:phone":"+44 20 7537 7796",
    "sg:postcode":"E14 6LT",
    "sg:province":"Greater London",
    "wof:name":"George Iv Regency Rooms",
    "wof:placetype":"venue"
},
  "geometry": {"coordinates":[-0.011319,51.511978],"type":"Point"}
}