{
  "type": "Feature",
  "properties": {
    "addr:full":"Willenhall Rd Wolverhampton West Midlands WV1 2HN",
    "addr:postcode":"wv1 2hn",
    "addr:street":"Willenhall Rd",
    "iso:country":"GB",
    "sg:address":"Willenhall Rd",
    "sg:city":"Wolverhampton",
    "sg:classifiers":[
        {
            "category":"Professional",
            "subcategory":"Printing & Photocopies",
            "type":"Services"
        }
    ],
    "sg:phone":"+44 1902 453030",
    "sg:postcode":"WV1 2HN",
    "sg:province":"West Midlands",
    "sg:tags":[
        "wooden",
        "seal"
    ],
    "wof:name":"D L I Brindley Ltd",
    "wof:placetype":"venue"
},
  "geometry": {"coordinates":[-2.104524,52.583401],"type":"Point"}
}