{
  "type": "Feature",
  "properties": {
    "iso:country":"GB",
    "sg:address":"Stafford Road, Weston",
    "sg:city":"Stafford",
    "sg:classifiers":[
        {
            "category":"Bars & Pubs",
            "type":"Food & Drink"
        }
    ],
    "sg:phone":"+44 1889 270286",
    "sg:postcode":"ST18 0HT",
    "sg:province":"Staffordshire",
    "sg:tags":[
        "pubs",
        "inn"
    ],
    "wof:name":"Saracens Head",
    "wof:placetype":"venue"
},
  "geometry": {"coordinates":[-2.035719,52.841549],"type":"Point"}
}