{
  "type": "Feature",
  "properties": {
    "addr:full":"Ground Floor, Austin Ho, 43 Poole Rd, Westbourne Bournemouth Dorset BH4 9DN",
    "addr:housenumber":"43",
    "addr:postcode":"bh4 9dn",
    "addr:street":"Poole Rd",
    "iso:country":"GB",
    "sg:address":"Ground Floor, Austin Ho, 43 Poole Rd, Westbourne",
    "sg:city":"Bournemouth",
    "sg:classifiers":[
        {
            "category":"Social Services",
            "type":"Services"
        }
    ],
    "sg:postcode":"BH4 9DN",
    "sg:province":"Dorset",
    "sg:tags":[
        "disability"
    ],
    "wof:name":"Loader,J,& Co Ltd",
    "wof:placetype":"venue"
},
  "geometry": {"coordinates":[-1.90105,50.722549],"type":"Point"}
}