{
  "type": "Feature",
  "properties": {
    "iso:country":"GB",
    "sg:address":"Unit 1 Mayflower Way",
    "sg:city":"Littlehampton",
    "sg:classifiers":[
        {
            "category":"Home & Garden",
            "subcategory":"Home Furnishings",
            "type":"Retail Goods"
        }
    ],
    "sg:phone":"+44 1903 503883",
    "sg:postcode":"BN16 4AY",
    "sg:province":"West Sussex",
    "sg:tags":[
        "blind",
        "curtain",
        "fitting"
    ],
    "wof:name":"Ferrar Furnishings",
    "wof:placetype":"venue"
},
  "geometry": {"coordinates":[-0.4779790044,50.8192749023],"type":"Point"}
}