{
  "type": "Feature",
  "properties": {
    "addr:full":"Redfants Manor Farm, Shalford Braintree Essex CM7 5HU",
    "addr:postcode":"cm7 5hu",
    "iso:country":"GB",
    "sg:address":"Redfants Manor Farm, Shalford",
    "sg:city":"Braintree",
    "sg:classifiers":[
        {
            "category":"Building & Trades",
            "subcategory":"Landscaping Services",
            "type":"Services"
        }
    ],
    "sg:phone":"+44 1371 850595",
    "sg:postcode":"CM7 5HU",
    "sg:province":"Essex",
    "sg:tags":[
        "landscape",
        "contractor"
    ],
    "wof:name":"Peter J Hull",
    "wof:placetype":"venue"
},
  "geometry": {"coordinates":[0.5017449856,51.9362983704],"type":"Point"}
}