{
  "type": "Feature",
  "properties": {
    "addr:full":"18 Pier Street Ventnor Isle of Wight PO38 1ST",
    "addr:housenumber":"18",
    "addr:postcode":"po38 1st",
    "addr:street":"Pier Street",
    "iso:country":"GB",
    "sg:address":"18 Pier Street",
    "sg:city":"Ventnor",
    "sg:classifiers":[
        {
            "category":"Bars & Pubs",
            "type":"Food & Drink"
        }
    ],
    "sg:phone":"+44 1983 856164",
    "sg:postcode":"PO38 1ST",
    "sg:province":"Isle of Wight",
    "sg:tags":[
        "pubs",
        "house",
        "inn",
        "public",
        "activity"
    ],
    "wof:name":"Rose Inn",
    "wof:placetype":"venue"
},
  "geometry": {"coordinates":[-1.2054380178,50.5945091248],"type":"Point"}
}