{
  "type": "Feature",
  "properties": {
    "addr:full":"Holmstead Manor, Staplefield Rd Haywards Heath East Sussex RH17 5JF",
    "addr:postcode":"rh17 5jf",
    "addr:street":"Staplefield Rd",
    "iso:country":"GB",
    "sg:address":"Holmstead Manor, Staplefield Rd",
    "sg:city":"Haywards Heath",
    "sg:classifiers":[
        {
            "category":"Organizations",
            "subcategory":"Religious Organization",
            "type":"Services"
        }
    ],
    "sg:phone":"+44 1444 440229",
    "sg:postcode":"RH17 5JF",
    "sg:province":"East Sussex",
    "sg:tags":[
        "organisation",
        "place",
        "worship"
    ],
    "wof:name":"Youth With A Mission",
    "wof:placetype":"venue"
},
  "geometry": {"coordinates":[-0.171389997,51.0233612061],"type":"Point"}
}