{
  "type": "Feature",
  "properties": {
    "addr:full":"8 Fowlds St Kilmarnock East Ayrshire KA1 1EG",
    "addr:housenumber":"8",
    "addr:postcode":"ka1 1eg",
    "addr:street":"Fowlds St",
    "iso:country":"GB",
    "sg:address":"8 Fowlds St",
    "sg:city":"Kilmarnock",
    "sg:classifiers":[
        {
            "category":"Cafe",
            "type":"Food & Drink"
        }
    ],
    "sg:postcode":"KA1 1EG",
    "sg:province":"East Ayrshire",
    "sg:tags":[
        "tea",
        "room"
    ],
    "wof:name":"Chimes Coffee Shop",
    "wof:placetype":"venue"
},
  "geometry": {"coordinates":[-4.496711,55.606892],"type":"Point"}
}