{
  "type": "Feature",
  "properties": {
    "addr:full":"Manor Farm, Watlington Rd King's Lynn Norfolk PE33 0EJ",
    "addr:postcode":"pe33 0ej",
    "addr:street":"Manor;Watlington Rd",
    "iso:country":"GB",
    "sg:address":"Manor Farm, Watlington Rd",
    "sg:city":"King's Lynn",
    "sg:classifiers":[
        {
            "category":"Banks & Credit Unions",
            "subcategory":"Investment Brokerage",
            "type":"Services"
        }
    ],
    "sg:phone":"+44 1553 810463",
    "sg:postcode":"PE33 0EJ",
    "sg:province":"Norfolk",
    "sg:tags":[
        "contractor"
    ],
    "wof:name":"Coates Bros",
    "wof:placetype":"venue"
},
  "geometry": {"coordinates":[0.3915,52.65786],"type":"Point"}
}