{
  "type": "Feature",
  "properties": {
    "addr:full":"Shrewsbury Road, Hadnall Shrewsbury Shropshire SY4 4AN",
    "addr:postcode":"sy4 4an",
    "addr:street":"Shrewsbury Road",
    "iso:country":"GB",
    "sg:address":"Shrewsbury Road, Hadnall",
    "sg:city":"Shrewsbury",
    "sg:classifiers":[
        {
            "category":"Professional",
            "type":"Services"
        }
    ],
    "sg:postcode":"SY4 4AN",
    "sg:province":"Shropshire",
    "sg:tags":[
        "repair",
        "tech",
        "maintenance"
    ],
    "wof:name":"Midwest Microsystems",
    "wof:placetype":"venue"
},
  "geometry": {"coordinates":[-2.709194,52.776546],"type":"Point"}
}