{
  "type": "Feature",
  "properties": {
    "addr:full":"231 Wood La Shepherd's Bush Greater London W12 0HL",
    "addr:housenumber":"231",
    "addr:postcode":"w12 0hl",
    "addr:street":"Wood La Shepherd'S",
    "iso:country":"GB",
    "sg:address":"231 Wood La",
    "sg:city":"Shepherd's Bush",
    "sg:classifiers":[
        {
            "category":"Shopping",
            "subcategory":"Florist",
            "type":"Retail Goods"
        }
    ],
    "sg:phone":"+44 20 8740 6464",
    "sg:postcode":"W12 0HL",
    "sg:province":"Greater London",
    "wof:name":"Exotic Tropical Flowers & Plants",
    "wof:placetype":"venue"
},
  "geometry": {"coordinates":[-0.2269430012,51.5161628723],"type":"Point"}
}