{
  "type": "Feature",
  "properties": {
    "addr:full":"Room 2002 Terminal 1, London Heathrow Airport Hounslow Greater London TW6 1NJ",
    "addr:housenumber":"2002;1;heathrow",
    "addr:postcode":"tw6 1nj",
    "addr:street":"Terminal;Airport",
    "iso:country":"GB",
    "sg:address":"Room 2002 Terminal 1, London Heathrow Airport",
    "sg:city":"Hounslow",
    "sg:classifiers":[
        {
            "category":"Airline",
            "type":"Transportation"
        }
    ],
    "sg:phone":"+44 20 8897 0695",
    "sg:postcode":"TW6 1NJ",
    "sg:province":"Greater London",
    "wof:name":"El Al (Cargo) Israel Airlines",
    "wof:placetype":"venue"
},
  "geometry": {"coordinates":[-0.4529339969,51.472454071],"type":"Point"}
}