{
  "type": "Feature",
  "properties": {
    "addr:full":"7 Goodramgate York North Yorkshire YO1 2LJ",
    "addr:housenumber":"7",
    "addr:postcode":"yo1 2lj",
    "addr:street":"Goodramgate",
    "iso:country":"GB",
    "sg:address":"7 Goodramgate",
    "sg:city":"York",
    "sg:classifiers":[
        {
            "category":"Shopping",
            "subcategory":"Thrift Store",
            "type":"Retail Goods"
        }
    ],
    "sg:postcode":"YO1 2LJ",
    "sg:province":"North Yorkshire",
    "sg:tags":[
        "shop",
        "charity"
    ],
    "wof:name":"Oxfam Charity Shop",
    "wof:placetype":"venue"
},
  "geometry": {"coordinates":[-1.078184,53.962776],"type":"Point"}
}