{
  "type": "Feature",
  "properties": {
    "iso:country":"GB",
    "sg:address":"135 Union Street",
    "sg:city":"Larkhall",
    "sg:classifiers":[
        {
            "category":"Utilities",
            "subcategory":"Electric",
            "type":"Services"
        }
    ],
    "sg:phone":"+44 1698 883220",
    "sg:postcode":"ML9 1DX",
    "sg:province":"South Lanarkshire",
    "sg:tags":[
        "electricity"
    ],
    "wof:name":"Scottish Power",
    "wof:placetype":"venue"
},
  "geometry": {"coordinates":[-3.9726979733,55.738319397],"type":"Point"}
}