{
  "type": "Feature",
  "properties": {
    "addr:full":"1 Victoria Parade, 331 Sandycombe Road Richmond Greater London TW9 3NB",
    "addr:housenumber":"1;331",
    "addr:postcode":"tw9 3nb",
    "addr:street":"Victoria Parade;Sandycombe Road",
    "iso:country":"GB",
    "sg:address":"1 Victoria Parade, 331 Sandycombe Road",
    "sg:city":"Richmond",
    "sg:classifiers":[
        {
            "category":"Real Estate",
            "subcategory":"Developer",
            "type":"Services"
        }
    ],
    "sg:postcode":"TW9 3NB",
    "sg:province":"Greater London",
    "sg:tags":[
        "calligrapher"
    ],
    "wof:name":"David Cherry",
    "wof:placetype":"venue"
},
  "geometry": {"coordinates":[-0.3027839959,51.462348938],"type":"Point"}
}