{
  "type": "Feature",
  "properties": {
    "addr:full":"2 Woodlands Avenue Kirkcudbright Dumfries and Galloway DG6 4BP",
    "addr:housenumber":"2",
    "addr:postcode":"dg6 4bp",
    "addr:street":"Woodlands Avenue",
    "iso:country":"GB",
    "sg:address":"2 Woodlands Avenue",
    "sg:city":"Kirkcudbright",
    "sg:classifiers":[
        {
            "category":"Freight",
            "type":"Transportation"
        }
    ],
    "sg:postcode":"DG6 4BP",
    "sg:province":"Dumfries and Galloway",
    "sg:tags":[
        "haulage",
        "road"
    ],
    "wof:name":"John Twiname",
    "wof:placetype":"venue"
},
  "geometry": {"coordinates":[-4.047436,54.834251],"type":"Point"}
}