{
  "type": "Feature",
  "properties": {
    "addr:full":"3 Meadow Way Verwood Dorset BH31 6EP",
    "addr:housenumber":"3",
    "addr:postcode":"bh31 6ep",
    "addr:street":"Meadow Way",
    "iso:country":"GB",
    "sg:address":"3 Meadow Way",
    "sg:city":"Verwood",
    "sg:classifiers":[
        {
            "category":"Building & Trades",
            "subcategory":"Plumbing",
            "type":"Services"
        }
    ],
    "sg:phone":"+44 1202 827739",
    "sg:postcode":"BH31 6EP",
    "sg:province":"Dorset",
    "sg:tags":[
        "central",
        "heating"
    ],
    "wof:name":"Malcolm F Reading",
    "wof:placetype":"venue"
},
  "geometry": {"coordinates":[-1.867632,50.871387],"type":"Point"}
}