{
  "type": "Feature",
  "properties": {
    "addr:full":"99a Stambridge Road Rochford Essex SS4 1DY",
    "addr:housenumber":"99a",
    "addr:postcode":"ss4 1dy",
    "addr:street":"Stambridge Road",
    "iso:country":"GB",
    "sg:address":"99a Stambridge Road",
    "sg:city":"Rochford",
    "sg:classifiers":[
        {
            "category":"Social Services",
            "subcategory":"Retirement Home",
            "type":"Services"
        }
    ],
    "sg:phone":"+44 1702 542256",
    "sg:postcode":"SS4 1DY",
    "sg:province":"Essex",
    "sg:tags":[
        "residential",
        "care"
    ],
    "wof:name":"John Grooms Housing Association",
    "wof:placetype":"venue"
},
  "geometry": {"coordinates":[0.716384,51.585697],"type":"Point"}
}