{
  "type": "Feature",
  "properties": {
    "addr:full":"21-22 West Wiltshire Craft Centr, E West Wilts Trading Westbury Wiltshire BA13 4HU",
    "addr:housenumber":"21-22",
    "addr:postcode":"ba13 4hu",
    "addr:street":"West;West",
    "iso:country":"GB",
    "sg:address":"21-22 West Wiltshire Craft Centr, E West Wilts Trading",
    "sg:city":"Westbury",
    "sg:classifiers":[
        {
            "category":"Retail",
            "subcategory":"Repair Shop",
            "type":"Services"
        }
    ],
    "sg:phone":"+44 1373 864202",
    "sg:postcode":"BA13 4HU",
    "sg:province":"Wiltshire",
    "sg:tags":[
        "television",
        "good",
        "video",
        "servicing",
        "maintenance",
        "radio"
    ],
    "wof:name":"Service All Electronics",
    "wof:placetype":"venue"
},
  "geometry": {"coordinates":[-2.2068190575,51.2730064392],"type":"Point"}
}