{
  "type": "Feature",
  "properties": {
    "addr:full":"Unit D, Sunshine Industrial Estate, Churchill Road Cheltenham Gloucestershire GL53 7EG",
    "addr:housenumber":"unit d",
    "addr:postcode":"gl53 7eg",
    "addr:street":"Sunshine Industrial Estate Churchill Road",
    "iso:country":"GB",
    "sg:address":"Unit D, Sunshine Industrial Estate, Churchill Road",
    "sg:city":"Cheltenham",
    "sg:classifiers":[
        {
            "category":"Building & Trades",
            "subcategory":"Construction",
            "type":"Services"
        }
    ],
    "sg:phone":"+44 1242 583700",
    "sg:postcode":"GL53 7EG",
    "sg:province":"Gloucestershire",
    "sg:tags":[
        "builder"
    ],
    "wof:name":"Cape Construction Ltd.",
    "wof:placetype":"venue"
},
  "geometry": {"coordinates":[-2.073980093,51.8848190308],"type":"Point"}
}