{
  "type": "Feature",
  "properties": {
    "iso:country":"GB",
    "sg:address":"Brickhouse Farm, Lancaster Road, Pilling",
    "sg:city":"Preston",
    "sg:classifiers":[
        {
            "category":"Farming",
            "subcategory":"Dairy Farm",
            "type":"Manufacturing & Wholesale Goods"
        },
        {
            "category":"Farming",
            "subcategory":"Livestock Farm",
            "type":"Manufacturing & Wholesale Goods"
        }
    ],
    "sg:phone":"+44 1253 790486",
    "sg:postcode":"PR3 6AU",
    "sg:province":"Lancashire",
    "sg:tags":[
        "others",
        "farmer"
    ],
    "wof:name":"S Kellet & Sons",
    "wof:placetype":"venue"
},
  "geometry": {"coordinates":[-2.910156,53.930977],"type":"Point"}
}