{
  "type": "Feature",
  "properties": {
    "iso:country":"GB",
    "sg:address":"Unit 2 Mill Lane Mews",
    "sg:city":"Ashby-de-la-zouch",
    "sg:classifiers":[
        {
            "category":"Shopping",
            "subcategory":"Hobbies, Toys, & Games",
            "type":"Retail Goods"
        }
    ],
    "sg:phone":"+44 1530 412983",
    "sg:postcode":"LE65 1HP",
    "sg:province":"Derbyshire",
    "sg:tags":[
        "computer"
    ],
    "wof:name":"Infinite Colours Ltd.",
    "wof:placetype":"venue"
},
  "geometry": {"coordinates":[-1.4710739851,52.7478141785],"type":"Point"}
}