{
  "type": "Feature",
  "properties": {
    "iso:country":"GB",
    "sg:address":"24 High Street, Earls Barton",
    "sg:city":"Northampton",
    "sg:classifiers":[
        {
            "category":"Building & Trades",
            "subcategory":"Plumbing",
            "type":"Services"
        }
    ],
    "sg:phone":"+44 1604 811469",
    "sg:postcode":"NN6 0JG",
    "sg:province":"Northamptonshire",
    "sg:tags":[
        "heating"
    ],
    "wof:name":"K Tipler Plumbing",
    "wof:placetype":"venue"
},
  "geometry": {"coordinates":[-0.7520890236,52.2655830383],"type":"Point"}
}