{
  "type": "Feature",
  "properties": {
    "addr:full":"32 Garth Road, Ty Coch Cwmbran Monmouthshire NP44 7AB",
    "addr:housenumber":"32",
    "addr:postcode":"np44 7ab",
    "addr:street":"Garth Road Ty Coch",
    "iso:country":"GB",
    "sg:address":"32 Garth Road, Ty Coch",
    "sg:city":"Cwmbran",
    "sg:classifiers":[
        {
            "category":"Health Services",
            "subcategory":"Health Practitioner",
            "type":"Services"
        }
    ],
    "sg:postcode":"NP44 7AB",
    "sg:province":"Monmouthshire",
    "sg:tags":[
        "osteopath"
    ],
    "wof:name":"Vivian Pugh",
    "wof:placetype":"venue"
},
  "geometry": {"coordinates":[-3.0281379223,51.63904953],"type":"Point"}
}