{
  "type": "Feature",
  "properties": {
    "iso:country":"GB",
    "sg:address":"12 Esplanade",
    "sg:city":"Whitby",
    "sg:classifiers":[
        {
            "category":"Travel",
            "subcategory":"Hotels & Motels",
            "type":"Entertainment"
        }
    ],
    "sg:postcode":"YO21 3HH",
    "sg:province":"North Yorkshire",
    "wof:name":"The Alexandra Hotel",
    "wof:placetype":"venue"
},
  "geometry": {"coordinates":[-0.6178920269,54.4901275635],"type":"Point"}
}