{
  "type": "Feature",
  "properties": {
    "addr:full":"5 Church Walk Shopping Centre, Walker Newcastle-upon-tyne Tyne and Wear NE6 3DP",
    "addr:housenumber":"5",
    "addr:postcode":"ne6 3dp",
    "addr:street":"Church Walk Shopping;Walker",
    "iso:country":"GB",
    "sg:address":"5 Church Walk Shopping Centre, Walker",
    "sg:city":"Newcastle-upon-tyne",
    "sg:classifiers":[
        {
            "category":"Shopping",
            "subcategory":"Florist",
            "type":"Retail Goods"
        }
    ],
    "sg:phone":"+44 191 262 6962",
    "sg:postcode":"NE6 3DP",
    "sg:province":"Tyne and Wear",
    "wof:name":"John Walton",
    "wof:placetype":"venue"
},
  "geometry": {"coordinates":[-1.5452840328,54.9734954834],"type":"Point"}
}