{
  "type": "Feature",
  "properties": {
    "addr:full":"49 Kingston Road Poole Dorset BH15 2LR",
    "addr:housenumber":"49",
    "addr:postcode":"bh15 2lr",
    "addr:street":"Kingston Road",
    "iso:country":"GB",
    "sg:address":"49 Kingston Road",
    "sg:city":"Poole",
    "sg:classifiers":[
        {
            "category":"Shopping",
            "subcategory":"Computers & Home Electronics",
            "type":"Retail Goods"
        }
    ],
    "sg:postcode":"BH15 2LR",
    "sg:province":"Dorset",
    "sg:tags":[
        "equipment",
        "radio"
    ],
    "wof:name":"Poole Logic",
    "wof:placetype":"venue"
},
  "geometry": {"coordinates":[-1.9749610424,50.7237739563],"type":"Point"}
}