{
  "type": "Feature",
  "properties": {
    "addr:full":"The Wheelhouse, Bonds Mill Stonehouse Gloucestershire GL10 3RF",
    "addr:postcode":"gl10 3rf",
    "addr:street":"Mill;Gloucestershire",
    "iso:country":"GB",
    "sg:address":"The Wheelhouse, Bonds Mill",
    "sg:city":"Stonehouse",
    "sg:classifiers":[
        {
            "category":"Professional",
            "subcategory":"Computer Services",
            "type":"Services"
        }
    ],
    "sg:phone":"+44 1453 791909",
    "sg:postcode":"GL10 3RF",
    "sg:province":"Gloucestershire",
    "sg:tags":[
        "consultant",
        "system",
        "software"
    ],
    "wof:name":"Jatech Ltd.",
    "wof:placetype":"venue"
},
  "geometry": {"coordinates":[-2.282234,51.745705],"type":"Point"}
}