{
  "type": "Feature",
  "properties": {
    "iso:country":"GB",
    "sg:address":", Oakhanger",
    "sg:city":"Bordon",
    "sg:classifiers":[
        {
            "category":"Bars & Pubs",
            "type":"Food & Drink"
        }
    ],
    "sg:phone":"+44 1420 472232",
    "sg:postcode":"GU35 9JQ",
    "sg:province":"Hampshire",
    "sg:tags":[
        "pubs",
        "inn",
        "-",
        "restaurant"
    ],
    "wof:name":"Red Lion",
    "wof:placetype":"venue"
},
  "geometry": {"coordinates":[-0.865114,51.108856],"type":"Point"}
}