{
  "type": "Feature",
  "properties": {
    "iso:country":"GB",
    "sg:address":"381 Penistone Road",
    "sg:city":"Sheffield",
    "sg:classifiers":[
        {
            "category":"Home & Garden",
            "subcategory":"Kitchen Supply",
            "type":"Retail Goods"
        }
    ],
    "sg:phone":"+44 114 233 1266",
    "sg:postcode":"S6 2FL",
    "sg:province":"South Yorkshire",
    "sg:tags":[
        "equipment",
        "catering"
    ],
    "sg:website":"http://www.stay-cool.net",
    "wof:name":"Overdale of Sheffield",
    "wof:placetype":"venue"
},
  "geometry": {"coordinates":[-1.4880919456,53.3977279663],"type":"Point"}
}