{
  "type": "Feature",
  "properties": {
    "addr:full":"59 High St Bradford West Yorkshire BD13 2AD",
    "addr:housenumber":"59",
    "addr:postcode":"bd13 2ad",
    "addr:street":"High St",
    "iso:country":"GB",
    "sg:address":"59 High St",
    "sg:city":"Bradford",
    "sg:classifiers":[
        {
            "category":"Cafe",
            "type":"Food & Drink"
        }
    ],
    "sg:phone":"+44 1274 882361",
    "sg:postcode":"BD13 2AD",
    "sg:province":"West Yorkshire",
    "sg:tags":[
        "tea",
        "room"
    ],
    "wof:name":"Dexters Cafe",
    "wof:placetype":"venue"
},
  "geometry": {"coordinates":[-1.846624,53.768112],"type":"Point"}
}