{
  "type": "Feature",
  "properties": {
    "addr:full":"Devon House, Paris Street Exeter Devon EX1 2JR",
    "addr:postcode":"ex1 2jr",
    "addr:street":"Paris Street",
    "iso:country":"GB",
    "sg:address":"Devon House, Paris Street",
    "sg:city":"Exeter",
    "sg:classifiers":[
        {
            "category":"Sports & Exercise",
            "subcategory":"Gym",
            "type":"Entertainment"
        }
    ],
    "sg:phone":"+44 1392 433656",
    "sg:postcode":"EX1 2JR",
    "sg:province":"Devon",
    "sg:tags":[
        "fitness",
        "health",
        "centre"
    ],
    "wof:name":"Sweat & Stretch Fitness Centre",
    "wof:placetype":"venue"
},
  "geometry": {"coordinates":[-3.523654,50.725151],"type":"Point"}
}