{
  "type": "Feature",
  "properties": {
    "addr:full":"83 High Street Chatham Kent ME4 4EE",
    "addr:housenumber":"83",
    "addr:postcode":"me4 4ee",
    "addr:street":"High Street",
    "iso:country":"GB",
    "sg:address":"83 High Street",
    "sg:city":"Chatham",
    "sg:classifiers":[
        {
            "category":"Insurance",
            "subcategory":"Insurance Agent",
            "type":"Services"
        }
    ],
    "sg:phone":"+44 1634 363600",
    "sg:postcode":"ME4 4EE",
    "sg:province":"Kent",
    "wof:name":"Royal London Mutual Insurance Society (The)",
    "wof:placetype":"venue"
},
  "geometry": {"coordinates":[0.520504,51.383732],"type":"Point"}
}