{
  "type": "Feature",
  "properties": {
    "iso:country":"GB",
    "sg:address":"133 Central St",
    "sg:city":"Clerkenwell",
    "sg:classifiers":[
        {
            "category":"Fast Food",
            "type":"Food & Drink"
        }
    ],
    "sg:phone":"+44 20 7250 1467",
    "sg:postcode":"EC1V 8AP",
    "sg:province":"Greater London",
    "sg:tags":[
        "away",
        "take"
    ],
    "wof:name":"Groppi",
    "wof:placetype":"venue"
},
  "geometry": {"coordinates":[-0.096999,51.527225],"type":"Point"}
}