{
  "type": "Feature",
  "properties": {
    "addr:full":"Lodge Farm, Shelton Huntingdon Bedfordshire PE28 0NR",
    "addr:postcode":"pe28 0nr",
    "addr:street":"Lodge",
    "iso:country":"GB",
    "sg:address":"Lodge Farm, Shelton",
    "sg:city":"Huntingdon",
    "sg:classifiers":[
        {
            "category":"Farming",
            "subcategory":"Livestock Farm",
            "type":"Manufacturing & Wholesale Goods"
        }
    ],
    "sg:postcode":"PE28 0NR",
    "sg:province":"Bedfordshire",
    "sg:tags":[
        "others"
    ],
    "wof:name":"K Rowlatt",
    "wof:placetype":"venue"
},
  "geometry": {"coordinates":[-0.4828799963,52.3095588684],"type":"Point"}
}