{
  "type": "Feature",
  "properties": {
    "addr:full":"8 Rutland Street Leicester Leicestershire LE1 1RA",
    "addr:housenumber":"8",
    "addr:postcode":"le1 1ra",
    "addr:street":"Rutland Street",
    "iso:country":"GB",
    "sg:address":"8 Rutland Street",
    "sg:city":"Leicester",
    "sg:classifiers":[
        {
            "category":"Professional",
            "subcategory":"Management & Consulting",
            "type":"Services"
        }
    ],
    "sg:phone":"+44 116 251 1661",
    "sg:postcode":"LE1 1RA",
    "sg:province":"Leicestershire",
    "sg:tags":[
        "consultant",
        "business"
    ],
    "wof:name":"S Five L Ltd.",
    "wof:placetype":"venue"
},
  "geometry": {"coordinates":[-1.1430380344,52.6128616333],"type":"Point"}
}