{
  "type": "Feature",
  "properties": {
    "addr:full":"Newport Road Crymych Pembrokeshire SA41 3RN",
    "addr:postcode":"sa41 3rn",
    "addr:street":"Newport Road",
    "iso:country":"GB",
    "sg:address":"Newport Road",
    "sg:city":"Crymych",
    "sg:classifiers":[
        {
            "category":"Autos & Motor Vehicles",
            "subcategory":"Auto Supplies",
            "type":"Retail Goods"
        }
    ],
    "sg:phone":"+44 1239 831464",
    "sg:postcode":"SA41 3RN",
    "sg:province":"Pembrokeshire",
    "sg:tags":[
        "tyre"
    ],
    "wof:name":"Crymych Exhaust & Tyre Centre",
    "wof:placetype":"venue"
},
  "geometry": {"coordinates":[-4.6484541893,51.9712409973],"type":"Point"}
}