{
  "type": "Feature",
  "properties": {
    "iso:country":"GB",
    "sg:address":"2nd Floor, Somerset House, Somerset Road",
    "sg:city":"Teddington",
    "sg:classifiers":[
        {
            "category":"Government",
            "subcategory":"Post Office",
            "type":"Public Place"
        }
    ],
    "sg:phone":"+44 20 8977 4522",
    "sg:postcode":"TW11 8RT",
    "sg:province":"Greater London",
    "sg:tags":[
        "messenger",
        "courier"
    ],
    "wof:name":"Concord Couriers Ltd.",
    "wof:placetype":"venue"
},
  "geometry": {"coordinates":[-0.338464,51.430256],"type":"Point"}
}