{
  "type": "Feature",
  "properties": {
    "addr:full":"12 Ash Rd Crewe Cheshire CW1 4DH",
    "addr:housenumber":"12",
    "addr:postcode":"cw1 4dh",
    "addr:street":"Ash Rd",
    "iso:country":"GB",
    "sg:address":"12 Ash Rd",
    "sg:city":"Crewe",
    "sg:classifiers":[
        {
            "category":"Freight",
            "type":"Transportation"
        }
    ],
    "sg:postcode":"CW1 4DH",
    "sg:province":"Cheshire",
    "sg:tags":[
        "haulage",
        "road"
    ],
    "wof:name":"Perocevic,Cemo,",
    "wof:placetype":"venue"
},
  "geometry": {"coordinates":[-2.4349400997,53.1082344055],"type":"Point"}
}