{
  "type": "Feature",
  "properties": {
    "addr:full":"10 St Annes Road West Lytham St Annes Lancashire FY8 1RF",
    "addr:housenumber":"10",
    "addr:postcode":"fy8 1rf",
    "addr:street":"St Annes Road West;St",
    "iso:country":"GB",
    "sg:address":"10 St Annes Road West",
    "sg:city":"Lytham St Annes",
    "sg:classifiers":[
        {
            "category":"Personal",
            "subcategory":"Beauty Salon",
            "type":"Services"
        }
    ],
    "sg:phone":"+44 1253 640066",
    "sg:postcode":"FY8 1RF",
    "sg:province":"Lancashire",
    "sg:tags":[
        "unisex",
        "hairdresser"
    ],
    "wof:name":"Hair in the Square",
    "wof:placetype":"venue"
},
  "geometry": {"coordinates":[-3.0322020054,53.750869751],"type":"Point"}
}