{
  "type": "Feature",
  "properties": {
    "addr:full":"Albion Lodge, Hanley Swan Worcester Gloucestershire WR8 0DN",
    "addr:postcode":"wr8 0dn",
    "addr:street":"Hanley Swan",
    "iso:country":"GB",
    "sg:address":"Albion Lodge, Hanley Swan",
    "sg:city":"Worcester",
    "sg:classifiers":[
        {
            "category":"Social Services",
            "subcategory":"Retirement Home",
            "type":"Services"
        }
    ],
    "sg:phone":"+44 1684 310626",
    "sg:postcode":"WR8 0DN",
    "sg:province":"Gloucestershire",
    "sg:tags":[
        "rest"
    ],
    "wof:name":"Albion Lodge Retirement Home",
    "wof:placetype":"venue"
},
  "geometry": {"coordinates":[-2.273579,52.083912],"type":"Point"}
}