{
  "type": "Feature",
  "properties": {
    "addr:full":"75 Clarence St Lancaster Lancashire LA1 3BB",
    "addr:housenumber":"75",
    "addr:postcode":"la1 3bb",
    "addr:street":"Clarence St",
    "iso:country":"GB",
    "sg:address":"75 Clarence St",
    "sg:city":"Lancaster",
    "sg:classifiers":[
        {
            "category":"Building & Trades",
            "subcategory":"Construction",
            "type":"Services"
        }
    ],
    "sg:phone":"+44 1524 60249",
    "sg:postcode":"LA1 3BB",
    "sg:province":"Lancashire",
    "sg:tags":[
        "builder"
    ],
    "wof:name":"MacBate Builders",
    "wof:placetype":"venue"
},
  "geometry": {"coordinates":[-2.7896559238,54.0436134338],"type":"Point"}
}