{
  "type": "Feature",
  "properties": {
    "iso:country":"GB",
    "sg:address":"98 Lauchope St",
    "sg:city":"Airdrie",
    "sg:classifiers":[
        {
            "category":"Bars & Pubs",
            "type":"Food & Drink"
        }
    ],
    "sg:phone":"+44 1236 762476",
    "sg:postcode":"ML6 8SW",
    "sg:province":"North Lanarkshire",
    "sg:tags":[
        "pubs",
        "inn"
    ],
    "wof:name":"Railway Inn",
    "wof:placetype":"venue"
},
  "geometry": {"coordinates":[-3.948809,55.844048],"type":"Point"}
}