{
  "type": "Feature",
  "properties": {
    "addr:full":"37 Hunter Crescent Troon South Ayrshire KA10 7AH",
    "addr:housenumber":"37",
    "addr:postcode":"ka10 7ah",
    "addr:street":"Hunter Crescent",
    "iso:country":"GB",
    "sg:address":"37 Hunter Crescent",
    "sg:city":"Troon",
    "sg:classifiers":[
        {
            "category":"Shopping",
            "subcategory":"Books",
            "type":"Retail Goods"
        }
    ],
    "sg:postcode":"KA10 7AH",
    "sg:province":"South Ayrshire",
    "sg:tags":[
        "second-hand"
    ],
    "wof:name":"W Buntain",
    "wof:placetype":"venue"
},
  "geometry": {"coordinates":[-4.63096,55.544254],"type":"Point"}
}