{
  "type": "Feature",
  "properties": {
    "addr:full":"1 The Exchange London Greater London NW4 3RJ",
    "addr:housenumber":"1",
    "addr:postcode":"nw4 3rj",
    "addr:street":"The",
    "iso:country":"GB",
    "sg:address":"1 The Exchange",
    "sg:city":"London",
    "sg:classifiers":[
        {
            "category":"Utilities",
            "subcategory":"Natural Gas",
            "type":"Services"
        }
    ],
    "sg:postcode":"NW4 3RJ",
    "sg:province":"Greater London",
    "sg:tags":[
        "supplier"
    ],
    "wof:name":"Bell Gas",
    "wof:placetype":"venue"
},
  "geometry": {"coordinates":[-0.2262399942,51.5801010132],"type":"Point"}
}