{
  "type": "Feature",
  "properties": {
    "iso:country":"GB",
    "sg:address":"2 Front Street, Sacriston",
    "sg:city":"Durham",
    "sg:classifiers":[
        {
            "category":"Food & Beverages",
            "subcategory":"Meat & Fish",
            "type":"Retail Goods"
        }
    ],
    "sg:phone":"+44 191 371 0775",
    "sg:postcode":"DH7 6LE",
    "sg:province":"Durham",
    "sg:tags":[
        "butcher"
    ],
    "wof:name":"L Hunt & Son",
    "wof:placetype":"venue"
},
  "geometry": {"coordinates":[-1.6264430285,54.8174057007],"type":"Point"}
}