{
  "type": "Feature",
  "properties": {
    "iso:country":"GB",
    "sg:address":"Felstead Road",
    "sg:city":"Epsom",
    "sg:classifiers":[
        {
            "category":"Retail",
            "subcategory":"Auto Repair",
            "type":"Services"
        }
    ],
    "sg:phone":"+44 1372 728500",
    "sg:postcode":"KT19 9AS",
    "sg:province":"Surrey",
    "sg:tags":[
        "modification",
        "garage"
    ],
    "wof:name":"Allam Motor Services Ltd.",
    "wof:placetype":"venue"
},
  "geometry": {"coordinates":[-0.264054,51.34259],"type":"Point"}
}