{
  "type": "Feature",
  "properties": {
    "iso:country":"GB",
    "sg:address":"School Clinic, Back Headroomgate Road",
    "sg:city":"Lytham St Annes",
    "sg:classifiers":[
        {
            "category":"Health Services",
            "subcategory":"Clinic",
            "type":"Services"
        }
    ],
    "sg:phone":"+44 1253 726844",
    "sg:postcode":"FY8 3ED",
    "sg:province":"Lancashire",
    "sg:tags":[
        "nh"
    ],
    "wof:name":"St Annes Clinic",
    "wof:placetype":"venue"
},
  "geometry": {"coordinates":[-3.0022139549,53.7499389648],"type":"Point"}
}