{
  "type": "Feature",
  "properties": {
    "addr:full":"Colemans Farm, Shaftesbury Road, East Knoyle Salisbury Wiltshire SP3 6AT",
    "addr:postcode":"sp3 6at",
    "addr:street":"Shaftesbury Road East",
    "iso:country":"GB",
    "sg:address":"Colemans Farm, Shaftesbury Road, East Knoyle",
    "sg:city":"Salisbury",
    "sg:classifiers":[
        {
            "category":"Farming",
            "subcategory":"Livestock Farm",
            "type":"Manufacturing & Wholesale Goods"
        }
    ],
    "sg:phone":"+44 1747 830300",
    "sg:postcode":"SP3 6AT",
    "sg:province":"Wiltshire",
    "sg:tags":[
        "others"
    ],
    "wof:name":"M S Green",
    "wof:placetype":"venue"
},
  "geometry": {"coordinates":[-2.167996,51.077801],"type":"Point"}
}