{
  "type": "Feature",
  "properties": {
    "addr:full":"The Surgery Exeter Devon EX6 6JA",
    "addr:postcode":"ex6 6ja",
    "iso:country":"GB",
    "sg:address":"The Surgery",
    "sg:city":"Exeter",
    "sg:classifiers":[
        {
            "category":"Health Services",
            "subcategory":"Doctor",
            "type":"Services"
        }
    ],
    "sg:phone":"+44 1647 24272",
    "sg:postcode":"EX6 6JA",
    "sg:province":"Devon",
    "sg:tags":[
        "practitioners"
    ],
    "wof:name":"Dudbridge, S B",
    "wof:placetype":"venue"
},
  "geometry": {"coordinates":[-3.74233,50.724812],"type":"Point"}
}