{
  "type": "Feature",
  "properties": {
    "iso:country":"GB",
    "sg:address":"264 The Broadway",
    "sg:city":"London",
    "sg:classifiers":[
        {
            "category":"Restaurant",
            "type":"Food & Drink"
        }
    ],
    "sg:phone":"+44 20 8542 5007",
    "sg:postcode":"SW19 1SB",
    "sg:province":"Greater London",
    "wof:name":"Mai's Kitchen",
    "wof:placetype":"venue"
},
  "geometry": {"coordinates":[-0.194769,51.419636],"type":"Point"}
}