{
  "type": "Feature",
  "properties": {
    "addr:full":"Main Street, Bishampton Pershore Worcestershire WR10 2NL",
    "addr:postcode":"wr10 2nl",
    "addr:street":"Main Street",
    "iso:country":"GB",
    "sg:address":"Main Street, Bishampton",
    "sg:city":"Pershore",
    "sg:classifiers":[
        {
            "category":"Building & Trades",
            "subcategory":"Plumbing",
            "type":"Services"
        }
    ],
    "sg:phone":"+44 1386 462448",
    "sg:postcode":"WR10 2NL",
    "sg:province":"Worcestershire",
    "sg:tags":[
        "heating"
    ],
    "wof:name":"Huxlely & Parry",
    "wof:placetype":"venue"
},
  "geometry": {"coordinates":[-2.0171310902,52.161441803],"type":"Point"}
}