{
  "type": "Feature",
  "properties": {
    "iso:country":"GB",
    "sg:address":"North Moor Road, Walkeringham",
    "sg:city":"Doncaster",
    "sg:classifiers":[
        {
            "category":"Government",
            "subcategory":"Post Office",
            "type":"Public Place"
        }
    ],
    "sg:phone":"+44 1427 890431",
    "sg:postcode":"DN10 4LW",
    "sg:province":"Lincolnshire",
    "wof:name":"Walkeringham Post Office",
    "wof:placetype":"venue"
},
  "geometry": {"coordinates":[-0.840679,53.422688],"type":"Point"}
}