{
  "type": "Feature",
  "properties": {
    "addr:full":"Aldor Hilldyke, Fishtoft Boston Lincolnshire PE22 0RL",
    "addr:postcode":"pe22 0rl",
    "iso:country":"GB",
    "sg:address":"Aldor Hilldyke, Fishtoft",
    "sg:city":"Boston",
    "sg:classifiers":[
        {
            "category":"Farming",
            "subcategory":"Farm",
            "type":"Manufacturing & Wholesale Goods"
        }
    ],
    "sg:postcode":"PE22 0RL",
    "sg:province":"Lincolnshire",
    "sg:tags":[
        "mixed",
        "crop"
    ],
    "wof:name":"A F Robinson",
    "wof:placetype":"venue"
},
  "geometry": {"coordinates":[-0.0026,53.004799],"type":"Point"}
}