{
  "type": "Feature",
  "properties": {
    "iso:country":"GB",
    "sg:address":"Kingshead Clo, Castlefields",
    "sg:city":"Runcorn",
    "sg:classifiers":[
        {
            "category":"Community Center",
            "subcategory":"Youth",
            "type":"Public Place"
        },
        {
            "category":"Government",
            "subcategory":"Office",
            "type":"Public Place"
        }
    ],
    "sg:phone":"+44 1928 564569",
    "sg:postcode":"WA7 2JQ",
    "sg:province":"Cheshire",
    "sg:tags":[
        "organisation",
        "local",
        "centre"
    ],
    "wof:name":"Cheshire County Council",
    "wof:placetype":"venue"
},
  "geometry": {"coordinates":[-2.695296,53.3405],"type":"Point"}
}