{
  "type": "Feature",
  "properties": {
    "iso:country":"GB",
    "sg:address":"48 Fw-sm Unit 5170 Block 290, Raf Lakenheath",
    "sg:city":"Brandon",
    "sg:classifiers":[
        {
            "category":"Government",
            "subcategory":"Office",
            "type":"Public Place"
        }
    ],
    "sg:postcode":"IP27 9PN",
    "sg:province":"Norfolk",
    "sg:tags":[
        "armed",
        "reserve"
    ],
    "wof:name":"United States Airforce",
    "wof:placetype":"venue"
},
  "geometry": {"coordinates":[0.626205,52.442741],"type":"Point"}
}