{
  "type": "Feature",
  "properties": {
    "addr:full":"9 Buie Close, Sparcells Swindon Wiltshire SN5 5FX",
    "addr:housenumber":"9",
    "addr:postcode":"sn5 5fx",
    "addr:street":"Buie Close",
    "iso:country":"GB",
    "sg:address":"9 Buie Close, Sparcells",
    "sg:city":"Swindon",
    "sg:classifiers":[
        {
            "category":"Manufacturing",
            "subcategory":"Wood Products",
            "type":"Manufacturing & Wholesale Goods"
        }
    ],
    "sg:phone":"+44 1793 873870",
    "sg:postcode":"SN5 5FX",
    "sg:province":"Wiltshire",
    "sg:tags":[
        "packaging",
        "crate",
        "pallets"
    ],
    "wof:name":"Acacia Supplies Ltd.",
    "wof:placetype":"venue"
},
  "geometry": {"coordinates":[-1.8292490244,51.5802764893],"type":"Point"}
}