{
  "type": "Feature",
  "properties": {
    "addr:full":"123 Church Road Teddington Greater London TW11 8QH",
    "addr:housenumber":"123",
    "addr:postcode":"tw11 8qh",
    "addr:street":"Church Road",
    "iso:country":"GB",
    "sg:address":"123 Church Road",
    "sg:city":"Teddington",
    "sg:classifiers":[
        {
            "category":"Building & Trades",
            "subcategory":"Construction",
            "type":"Services"
        }
    ],
    "sg:postcode":"TW11 8QH",
    "sg:province":"Greater London",
    "sg:tags":[
        "joiner",
        "carpenter"
    ],
    "wof:name":"P J Conneely",
    "wof:placetype":"venue"
},
  "geometry": {"coordinates":[-0.3399089873,51.430355072],"type":"Point"}
}