{
  "type": "Feature",
  "properties": {
    "addr:full":"45 Woodside Rd New Malden Surrey KT3 3AW",
    "addr:housenumber":"45",
    "addr:postcode":"kt3 3aw",
    "addr:street":"Woodside Rd",
    "iso:country":"GB",
    "sg:address":"45 Woodside Rd",
    "sg:city":"New Malden",
    "sg:classifiers":[
        {
            "category":"Professional",
            "subcategory":"Art Services",
            "type":"Services"
        }
    ],
    "sg:phone":"+44 20 8942 8090",
    "sg:postcode":"KT3 3AW",
    "sg:province":"Surrey",
    "sg:tags":[
        "photographer"
    ],
    "wof:name":"Gerald Cooper Photography",
    "wof:placetype":"venue"
},
  "geometry": {"coordinates":[-0.262771,51.408524],"type":"Point"}
}