{
  "type": "Feature",
  "properties": {
    "iso:country":"GB",
    "sg:address":"Llanrumney Avenue, Llanrumney",
    "sg:city":"Cardiff",
    "sg:classifiers":[
        {
            "category":"Health Services",
            "subcategory":"Clinic",
            "type":"Services"
        }
    ],
    "sg:phone":"+44 29 2077 0146",
    "sg:postcode":"CF3 9DP",
    "sg:province":"Caerphilly",
    "sg:tags":[
        "private"
    ],
    "wof:name":"Llanrumney Clinic",
    "wof:placetype":"venue"
},
  "geometry": {"coordinates":[-3.1234,51.521488],"type":"Point"}
}