{
  "type": "Feature",
  "properties": {
    "iso:country":"GB",
    "sg:address":"Henlow Mills, New Town",
    "sg:city":"Henlow",
    "sg:classifiers":[
        {
            "category":"Food & Beverages",
            "subcategory":"Supermarket",
            "type":"Retail Goods"
        }
    ],
    "sg:phone":"+44 1462 816188",
    "sg:postcode":"SG16 6AJ",
    "sg:province":"Bedfordshire",
    "sg:tags":[
        "frozen"
    ],
    "wof:name":"John Hare & Corporation Ltd.",
    "wof:placetype":"venue"
},
  "geometry": {"coordinates":[-0.285839,52.030876],"type":"Point"}
}