{
  "type": "Feature",
  "properties": {
    "addr:full":"New Icknield Way Letchworth Hertfordshire SG6 1EP",
    "addr:postcode":"sg6 1ep",
    "addr:street":"Icknield Way",
    "iso:country":"GB",
    "sg:address":"New Icknield Way",
    "sg:city":"Letchworth",
    "sg:classifiers":[
        {
            "category":"Shopping",
            "subcategory":"Stationery & Office Supplies",
            "type":"Retail Goods"
        }
    ],
    "sg:phone":"+44 1462 686137",
    "sg:postcode":"SG6 1EP",
    "sg:province":"Hertfordshire",
    "sg:tags":[
        "packaging",
        "material"
    ],
    "wof:name":"Church End Ltd.",
    "wof:placetype":"venue"
},
  "geometry": {"coordinates":[-0.210668,51.985821],"type":"Point"}
}