{
  "type": "Feature",
  "properties": {
    "addr:full":"18 Carew Road Eastbourne East Sussex BN21 2JD",
    "addr:housenumber":"18",
    "addr:postcode":"bn21 2jd",
    "addr:street":"Carew Road",
    "iso:country":"GB",
    "sg:address":"18 Carew Road",
    "sg:city":"Eastbourne",
    "sg:classifiers":[
        {
            "category":"Social Services",
            "subcategory":"Retirement Home",
            "type":"Services"
        }
    ],
    "sg:postcode":"BN21 2JD",
    "sg:province":"East Sussex",
    "sg:tags":[
        "residential",
        "care"
    ],
    "wof:name":"Highland House Rest Home",
    "wof:placetype":"venue"
},
  "geometry": {"coordinates":[0.279471,50.775967],"type":"Point"}
}