{
  "type": "Feature",
  "properties": {
    "iso:country":"GB",
    "sg:address":"P O Box 1056",
    "sg:city":"Ascot",
    "sg:classifiers":[
        {
            "category":"Building & Trades",
            "subcategory":"Construction",
            "type":"Services"
        }
    ],
    "sg:phone":"+44 1892 537731",
    "sg:postcode":"SL5 7BW",
    "sg:province":"Berkshire",
    "sg:tags":[
        "dry",
        "lining",
        "plasterers",
        "screeders"
    ],
    "wof:name":"J R Ward & Son",
    "wof:placetype":"venue"
},
  "geometry": {"coordinates":[-0.665919,51.41185],"type":"Point"}
}