{
  "type": "Feature",
  "properties": {
    "addr:full":"Avenue Rd Hartlepool Durham TS24 8BB",
    "addr:postcode":"ts24 8bb",
    "addr:street":"Avenue Rd",
    "iso:country":"GB",
    "sg:address":"Avenue Rd",
    "sg:city":"Hartlepool",
    "sg:classifiers":[
        {
            "category":"Government",
            "subcategory":"Police Station",
            "type":"Public Place"
        }
    ],
    "sg:phone":"+44 1429 221151",
    "sg:postcode":"TS24 8BB",
    "sg:province":"Durham",
    "sg:tags":[
        "support"
    ],
    "wof:name":"Hartlepool Police Office",
    "wof:placetype":"venue"
},
  "geometry": {"coordinates":[-1.215217948,54.6874313354],"type":"Point"}
}