{
  "type": "Feature",
  "properties": {
    "addr:full":"195 Brompton Road London Greater London SW3 1NE",
    "addr:housenumber":"195",
    "addr:postcode":"sw3 1ne",
    "addr:street":"Brompton Road",
    "iso:country":"GB",
    "sg:address":"195 Brompton Road",
    "sg:city":"London",
    "sg:classifiers":[
        {
            "category":"Transit Center",
            "subcategory":"Passenger",
            "type":"Transportation"
        }
    ],
    "sg:phone":"+44 20 7629 0070",
    "sg:postcode":"SW3 1NE",
    "sg:province":"Greater London",
    "sg:tags":[
        "ship",
        "broker"
    ],
    "wof:name":"Marine Capital Advisors",
    "wof:placetype":"venue"
},
  "geometry": {"coordinates":[-0.162029,51.500778],"type":"Point"}
}