{
  "type": "Feature",
  "properties": {
    "addr:full":"77 North Street Guildford Surrey GU1 4AL",
    "addr:housenumber":"77",
    "addr:postcode":"gu1 4al",
    "addr:street":"North Street",
    "iso:country":"GB",
    "sg:address":"77 North Street",
    "sg:city":"Guildford",
    "sg:classifiers":[
        {
            "category":"Education",
            "subcategory":"Library",
            "type":"Public Place"
        },
        {
            "category":"Government",
            "subcategory":"Office",
            "type":"Public Place"
        }
    ],
    "sg:phone":"+44 1483 534120",
    "sg:postcode":"GU1 4AL",
    "sg:province":"Surrey",
    "sg:tags":[
        "book",
        "local"
    ],
    "wof:name":"Guildford Library",
    "wof:placetype":"venue"
},
  "geometry": {"coordinates":[-0.571902,51.236881],"type":"Point"}
}