{
  "type": "Feature",
  "properties": {
    "addr:full":"12a Regent Street Teignmouth Devon TQ14 8SJ",
    "addr:housenumber":"12a",
    "addr:postcode":"tq14 8sj",
    "addr:street":"Regent Street",
    "iso:country":"GB",
    "sg:address":"12a Regent Street",
    "sg:city":"Teignmouth",
    "sg:classifiers":[
        {
            "category":"Professional",
            "subcategory":"Printing & Photocopies",
            "type":"Services"
        }
    ],
    "sg:postcode":"TQ14 8SJ",
    "sg:province":"Devon",
    "sg:tags":[
        "duplicating",
        "copying"
    ],
    "wof:name":"Copy Fax Typing Service Ltd",
    "wof:placetype":"venue"
},
  "geometry": {"coordinates":[-3.4935889244,50.5468864441],"type":"Point"}
}