{
  "type": "Feature",
  "properties": {
    "addr:full":"34 Froment Way, Milton Cambridge Cambridgeshire CB4 6DT",
    "addr:housenumber":"34",
    "addr:postcode":"cb4 6dt",
    "addr:street":"Froment Way",
    "iso:country":"GB",
    "sg:address":"34 Froment Way, Milton",
    "sg:city":"Cambridge",
    "sg:classifiers":[
        {
            "category":"Professional",
            "type":"Services"
        }
    ],
    "sg:phone":"+44 1223 860366",
    "sg:postcode":"CB4 6DT",
    "sg:province":"Cambridgeshire",
    "sg:tags":[
        "entertainer"
    ],
    "wof:name":"Just Puppets",
    "wof:placetype":"venue"
},
  "geometry": {"coordinates":[0.156391,52.245823],"type":"Point"}
}