{
  "type": "Feature",
  "properties": {
    "iso:country":"GB",
    "sg:address":"Berrymoor Rd",
    "sg:city":"Wellingborough",
    "sg:classifiers":[
        {
            "category":"Place Of Worship",
            "type":"Public Place"
        }
    ],
    "sg:phone":"+44 1933 222692",
    "sg:postcode":"NN8 2HU",
    "sg:province":"Northamptonshire",
    "wof:name":"St Andrews Church",
    "wof:placetype":"venue"
},
  "geometry": {"coordinates":[-0.702619,52.290871],"type":"Point"}
}