{
  "type": "Feature",
  "properties": {
    "addr:full":"Unit 4 Park Parade Industrial Estate, Welbeck St South Ashton-under-lyne Greater Manchester OL6 7PP",
    "addr:housenumber":"unit 4;estate",
    "addr:postcode":"ol6 7pp",
    "addr:street":"Park Parade Industrial;St",
    "iso:country":"GB",
    "sg:address":"Unit 4 Park Parade Industrial Estate, Welbeck St South",
    "sg:city":"Ashton-under-lyne",
    "sg:classifiers":[
        {
            "category":"Wholesale",
            "subcategory":"Machinery & Supplies",
            "type":"Manufacturing & Wholesale Goods"
        }
    ],
    "sg:phone":"+44 161 308 2624",
    "sg:postcode":"OL6 7PP",
    "sg:province":"Greater Manchester",
    "sg:tags":[
        "-",
        "sale",
        "hydraulic",
        "accessory",
        "equipment",
        "pump"
    ],
    "wof:name":"Euro Hydraulics Ltd.",
    "wof:placetype":"venue"
},
  "geometry": {"coordinates":[-2.088242054,53.489238739],"type":"Point"}
}