{
  "type": "Feature",
  "properties": {
    "iso:country":"GB",
    "sg:address":"193 Brighton Rd",
    "sg:city":"South Croydon",
    "sg:classifiers":[
        {
            "category":"Building & Trades",
            "subcategory":"Landscaping Services",
            "type":"Services"
        }
    ],
    "sg:phone":"+44 20 8680 8832",
    "sg:postcode":"CR2 6EG",
    "sg:province":"Surrey",
    "sg:tags":[
        "landscape",
        "contractor"
    ],
    "wof:name":"Greenscapes",
    "wof:placetype":"venue"
},
  "geometry": {"coordinates":[-0.097534,51.356083],"type":"Point"}
}