{
  "type": "Feature",
  "properties": {
    "addr:full":"6 Pringle Ct, Garstang Preston Lancashire PR3 1LN",
    "addr:housenumber":"6",
    "addr:postcode":"pr3 1ln",
    "addr:street":"Pringle Ct",
    "iso:country":"GB",
    "sg:address":"6 Pringle Ct, Garstang",
    "sg:city":"Preston",
    "sg:classifiers":[
        {
            "category":"Home & Garden",
            "subcategory":"Household Appliances",
            "type":"Retail Goods"
        }
    ],
    "sg:postcode":"PR3 1LN",
    "sg:province":"Lancashire",
    "sg:tags":[
        "domestic",
        "centre"
    ],
    "wof:name":"Garstang Domestics",
    "wof:placetype":"venue"
},
  "geometry": {"coordinates":[-2.7737839222,53.9073066711],"type":"Point"}
}