{
  "type": "Feature",
  "properties": {
    "iso:country":"GB",
    "sg:address":"1st Floor, Victoria House, Victoria Terrace",
    "sg:city":"Newport",
    "sg:classifiers":[
        {
            "category":"Home & Garden",
            "subcategory":"Carpets & Floor Coverings",
            "type":"Retail Goods"
        }
    ],
    "sg:phone":"+44 1495 243428",
    "sg:postcode":"NP11 4ET",
    "sg:province":"Blaenau Gwent",
    "sg:tags":[
        "carpets",
        "retailer",
        "rug",
        "matting"
    ],
    "wof:name":"Mike Brimfield Discount Carpets Ltd",
    "wof:placetype":"venue"
},
  "geometry": {"coordinates":[-3.144428,51.665329],"type":"Point"}
}