{
  "type": "Feature",
  "properties": {
    "addr:full":"Barnes Hill Birmingham West Midlands B29 5TY",
    "addr:postcode":"b29 5ty",
    "addr:street":"Barnes Hill",
    "iso:country":"GB",
    "sg:address":"Barnes Hill",
    "sg:city":"Birmingham",
    "sg:classifiers":[
        {
            "category":"Home & Garden",
            "subcategory":"Hardware",
            "type":"Retail Goods"
        }
    ],
    "sg:phone":"+44 121 427 1214",
    "sg:postcode":"B29 5TY",
    "sg:province":"West Midlands",
    "sg:tags":[
        "shop",
        "retailer",
        "diy"
    ],
    "wof:name":"Cash D I Y Supplies",
    "wof:placetype":"venue"
},
  "geometry": {"coordinates":[-1.9783719778,52.442741394],"type":"Point"}
}