{
  "type": "Feature",
  "properties": {
    "addr:full":"9 Petworth Road Haslemere Hampshire GU27 2JB",
    "addr:housenumber":"9",
    "addr:postcode":"gu27 2jb",
    "addr:street":"Petworth Road",
    "iso:country":"GB",
    "sg:address":"9 Petworth Road",
    "sg:city":"Haslemere",
    "sg:classifiers":[
        {
            "category":"Building & Trades",
            "subcategory":"Construction",
            "type":"Services"
        }
    ],
    "sg:phone":"+44 1428 658999",
    "sg:postcode":"GU27 2JB",
    "sg:province":"Hampshire",
    "sg:tags":[
        "builder"
    ],
    "wof:name":"Geometra Building Management Ltd.",
    "wof:placetype":"venue"
},
  "geometry": {"coordinates":[-0.7092549801,51.0871772766],"type":"Point"}
}