{
  "type": "Feature",
  "properties": {
    "addr:full":"Cattlegate Road Enfield Greater London EN2 9DP",
    "addr:postcode":"en2 9dp",
    "addr:street":"Cattlegate Road",
    "iso:country":"GB",
    "sg:address":"Cattlegate Road",
    "sg:city":"Enfield",
    "sg:classifiers":[
        {
            "category":"Home & Garden",
            "subcategory":"Garden Supply",
            "type":"Retail Goods"
        }
    ],
    "sg:phone":"+44 20 8363 1383",
    "sg:postcode":"EN2 9DP",
    "sg:province":"Greater London",
    "sg:tags":[
        "nursery",
        "centre"
    ],
    "wof:name":"Thompson's of Lindale Nursery",
    "wof:placetype":"venue"
},
  "geometry": {"coordinates":[-0.107449,51.683926],"type":"Point"}
}