{
  "type": "Feature",
  "properties": {
    "addr:full":"Windsor Rd Staines Berkshire TW19 5ER",
    "addr:postcode":"tw19 5er",
    "addr:street":"Windsor Rd",
    "iso:country":"GB",
    "sg:address":"Windsor Rd",
    "sg:city":"Staines",
    "sg:classifiers":[
        {
            "category":"Place Of Worship",
            "type":"Public Place"
        }
    ],
    "sg:phone":"+44 1784 483556",
    "sg:postcode":"TW19 5ER",
    "sg:province":"Berkshire",
    "wof:name":"St Andrews Church",
    "wof:placetype":"venue"
},
  "geometry": {"coordinates":[-0.567478,51.44817],"type":"Point"}
}