{
  "type": "Feature",
  "properties": {
    "addr:full":"Eastry Lodge High Church Wynd Yarm North Yorkshire TS15 9BQ",
    "addr:postcode":"ts15 9bq",
    "addr:street":"High;Wynd",
    "iso:country":"GB",
    "sg:address":"Eastry Lodge High Church Wynd",
    "sg:city":"Yarm",
    "sg:classifiers":[
        {
            "category":"Real Estate",
            "subcategory":"Architect",
            "type":"Services"
        }
    ],
    "sg:postcode":"TS15 9BQ",
    "sg:province":"North Yorkshire",
    "wof:name":"Stockstruc Ltd.",
    "wof:placetype":"venue"
},
  "geometry": {"coordinates":[-1.3541439772,54.5086364746],"type":"Point"}
}