{
  "type": "Feature",
  "properties": {
    "iso:country":"GB",
    "sg:address":"1 St Clements Court",
    "sg:city":"London",
    "sg:classifiers":[
        {
            "category":"Arts & Performance",
            "subcategory":"Theater",
            "type":"Entertainment"
        }
    ],
    "sg:postcode":"EC4N 7HB",
    "sg:province":"Greater London",
    "sg:tags":[
        "theatre"
    ],
    "wof:name":"Michael Voysey Theatrical Agents",
    "wof:placetype":"venue"
},
  "geometry": {"coordinates":[-0.0867500007,51.5115203857],"type":"Point"}
}