{
  "type": "Feature",
  "properties": {
    "addr:full":"5 Mill Paddock, Letcombe Regis Wantage Berkshire OX12 9JE",
    "addr:housenumber":"5",
    "addr:postcode":"ox12 9je",
    "addr:street":"Mill Paddock",
    "iso:country":"GB",
    "sg:address":"5 Mill Paddock, Letcombe Regis",
    "sg:city":"Wantage",
    "sg:classifiers":[
        {
            "category":"Coffee & Tea",
            "type":"Food & Drink"
        }
    ],
    "sg:phone":"+44 1235 764145",
    "sg:postcode":"OX12 9JE",
    "sg:province":"Berkshire",
    "sg:tags":[
        "machine",
        "supplier"
    ],
    "wof:name":"Bewley's Coffee Man",
    "wof:placetype":"venue"
},
  "geometry": {"coordinates":[-1.4279940128,51.5897026062],"type":"Point"}
}