{
  "type": "Feature",
  "properties": {
    "addr:full":"Unit L, Broad Lane Industrial Estate, Cottenham Cambridge Cambridgeshire CB4 8SW",
    "addr:postcode":"cb4 8sw",
    "addr:street":"Broad Lane Industrial Estate",
    "iso:country":"GB",
    "sg:address":"Unit L, Broad Lane Industrial Estate, Cottenham",
    "sg:city":"Cambridge",
    "sg:classifiers":[
        {
            "category":"Shopping",
            "subcategory":"Stationery & Office Supplies",
            "type":"Retail Goods"
        }
    ],
    "sg:phone":"+44 1954 208011",
    "sg:postcode":"CB4 8SW",
    "sg:province":"Cambridgeshire",
    "sg:tags":[
        "envelope"
    ],
    "wof:name":"East Anglia Trade Press Ltd.",
    "wof:placetype":"venue"
},
  "geometry": {"coordinates":[0.126215,52.286472],"type":"Point"}
}