{
  "type": "Feature",
  "properties": {
    "iso:country":"GB",
    "sg:address":"Unit 21, Bristol Craft Centre, 6 Leonard Lane",
    "sg:city":"Bristol",
    "sg:classifiers":[
        {
            "category":"Professional",
            "subcategory":"Art Services",
            "type":"Services"
        }
    ],
    "sg:phone":"+44 117 945 1951",
    "sg:postcode":"BS1 1EA",
    "sg:province":"City of Bristol",
    "sg:tags":[
        "technical",
        "illustrator",
        "commercial"
    ],
    "wof:name":"Adrian Barclay Illustration",
    "wof:placetype":"venue"
},
  "geometry": {"coordinates":[-2.59551,51.454781],"type":"Point"}
}