{
  "type": "Feature",
  "properties": {
    "iso:country":"GB",
    "sg:address":"Meadlake Place, Thorpe Lea Road",
    "sg:city":"Egham",
    "sg:classifiers":[
        {
            "category":"Professional",
            "subcategory":"Computer Services",
            "type":"Services"
        }
    ],
    "sg:phone":"+44 1784 470555",
    "sg:postcode":"TW20 8HE",
    "sg:province":"Surrey",
    "sg:tags":[
        "system",
        "software"
    ],
    "wof:name":"3 D Labs Ltd.",
    "wof:placetype":"venue"
},
  "geometry": {"coordinates":[-0.536077,51.406357],"type":"Point"}
}