{
  "type": "Feature",
  "properties": {
    "addr:full":"16 High Street Yarm North Yorkshire TS15 9AE",
    "addr:housenumber":"16",
    "addr:postcode":"ts15 9ae",
    "addr:street":"High Street",
    "iso:country":"GB",
    "sg:address":"16 High Street",
    "sg:city":"Yarm",
    "sg:classifiers":[
        {
            "category":"Shopping",
            "subcategory":"Clothing, Apparel, & Fashions",
            "type":"Retail Goods"
        }
    ],
    "sg:phone":"+44 1642 780868",
    "sg:postcode":"TS15 9AE",
    "sg:province":"North Yorkshire",
    "sg:tags":[
        "menswear"
    ],
    "wof:name":"J McNeil",
    "wof:placetype":"venue"
},
  "geometry": {"coordinates":[-1.353867054,54.5081787109],"type":"Point"}
}