{
  "type": "Feature",
  "properties": {
    "iso:country":"GB",
    "sg:address":"102 New St",
    "sg:city":"Birmingham",
    "sg:classifiers":[
        {
            "category":"Restaurant",
            "type":"Food & Drink"
        }
    ],
    "sg:phone":"+44 121 643 1548",
    "sg:postcode":"B2 4HS",
    "sg:province":"West Midlands",
    "sg:tags":[
        "italian"
    ],
    "wof:name":"Bella Pasta",
    "wof:placetype":"venue"
},
  "geometry": {"coordinates":[-1.9012240171,52.4792709351],"type":"Point"}
}