{
  "type": "Feature",
  "properties": {
    "iso:country":"GB",
    "sg:address":"37 Market Street, Whittlesey",
    "sg:city":"Peterborough",
    "sg:classifiers":[
        {
            "category":"Home & Garden",
            "subcategory":"Home Furnishings",
            "type":"Retail Goods"
        },
        {
            "category":"Building & Trades",
            "subcategory":"Construction",
            "type":"Services"
        }
    ],
    "sg:phone":"+44 1733 202220",
    "sg:postcode":"PE7 1BA",
    "sg:province":"Cambridgeshire",
    "sg:tags":[
        "mantelpiece",
        "fireplace"
    ],
    "wof:name":"Aspect Fires Ltd",
    "wof:placetype":"venue"
},
  "geometry": {"coordinates":[-0.1305480003,52.5566520691],"type":"Point"}
}