{
  "type": "Feature",
  "properties": {
    "addr:full":"185 Fleet Road Fleet Hampshire GU51 3BL",
    "addr:housenumber":"185",
    "addr:postcode":"gu51 3bl",
    "addr:street":"Fleet Road",
    "iso:country":"GB",
    "sg:address":"185 Fleet Road",
    "sg:city":"Fleet",
    "sg:classifiers":[
        {
            "category":"Travel",
            "subcategory":"Travel Agent",
            "type":"Entertainment"
        }
    ],
    "sg:phone":"+44 1252 815210",
    "sg:postcode":"GU51 3BL",
    "sg:province":"Hampshire",
    "wof:name":"Lunn Poly",
    "wof:placetype":"venue"
},
  "geometry": {"coordinates":[-0.8375689983,51.2850112915],"type":"Point"}
}