{
  "type": "Feature",
  "properties": {
    "iso:country":"GB",
    "sg:address":"The Caines, Thorpe Marriott",
    "sg:city":"Norwich",
    "sg:classifiers":[
        {
            "category":"Building & Trades",
            "subcategory":"Construction",
            "type":"Services"
        }
    ],
    "sg:phone":"+44 1603 262126",
    "sg:postcode":"NR8 6FU",
    "sg:province":"Norfolk",
    "sg:tags":[
        "builder"
    ],
    "wof:name":"Beazer Homes Colchester Ltd",
    "wof:placetype":"venue"
},
  "geometry": {"coordinates":[1.196809,52.689739],"type":"Point"}
}