{
  "type": "Feature",
  "properties": {
    "addr:full":"391 Hertford Rd Enfield Greater London EN3 5PP",
    "addr:housenumber":"391",
    "addr:postcode":"en3 5pp",
    "addr:street":"Hertford Rd",
    "iso:country":"GB",
    "sg:address":"391 Hertford Rd",
    "sg:city":"Enfield",
    "sg:classifiers":[
        {
            "category":"Manufacturing",
            "subcategory":"Furniture",
            "type":"Manufacturing & Wholesale Goods"
        }
    ],
    "sg:phone":"+44 20 8804 4466",
    "sg:postcode":"EN3 5PP",
    "sg:province":"Greater London",
    "sg:tags":[
        "mnfr",
        "garden",
        "patio"
    ],
    "wof:name":"Potstop",
    "wof:placetype":"venue"
},
  "geometry": {"coordinates":[-0.044766,51.66367],"type":"Point"}
}