{
  "type": "Feature",
  "properties": {
    "iso:country":"GB",
    "sg:address":"54 High Street",
    "sg:city":"Godstone",
    "sg:classifiers":[
        {
            "category":"Manufacturing",
            "subcategory":"Petroleum Products",
            "type":"Manufacturing & Wholesale Goods"
        },
        {
            "category":"Building & Trades",
            "subcategory":"Construction",
            "type":"Services"
        }
    ],
    "sg:postcode":"RH9 8LW",
    "sg:province":"Surrey",
    "sg:tags":[
        "double",
        "glazier",
        "glazing"
    ],
    "wof:name":"Tandridge Window Co",
    "wof:placetype":"venue"
},
  "geometry": {"coordinates":[-0.067239,51.250687],"type":"Point"}
}