{
  "type": "Feature",
  "properties": {
    "iso:country":"GB",
    "sg:address":"16 Willowdale Centre",
    "sg:city":"Wickford",
    "sg:classifiers":[
        {
            "category":"Shopping",
            "subcategory":"Pharmacy",
            "type":"Retail Goods"
        }
    ],
    "sg:phone":"+44 1268 761911",
    "sg:postcode":"SS12 0RA",
    "sg:province":"Essex",
    "sg:tags":[
        "pharmacist",
        "chemist"
    ],
    "wof:name":"Boots the Chemist",
    "wof:placetype":"venue"
},
  "geometry": {"coordinates":[0.5142400265,51.6087608337],"type":"Point"}
}