{
  "type": "Feature",
  "properties": {
    "iso:country":"GB",
    "sg:address":"Church Cottage, Tredington",
    "sg:city":"Tewkesbury",
    "sg:classifiers":[
        {
            "category":"Home & Garden",
            "subcategory":"Household Appliances",
            "type":"Retail Goods"
        }
    ],
    "sg:phone":"+44 1684 295717",
    "sg:postcode":"GL20 7BS",
    "sg:province":"Gloucestershire",
    "sg:tags":[
        "repairs",
        "electrical",
        "domestic",
        "servicing"
    ],
    "wof:name":"Robert P Cudmore",
    "wof:placetype":"venue"
},
  "geometry": {"coordinates":[-2.144484,51.965504],"type":"Point"}
}