{
  "type": "Feature",
  "properties": {
    "iso:country":"GB",
    "sg:address":"Within B.p Oil Ltd, Hamble Lane, Hamble",
    "sg:city":"Southampton",
    "sg:classifiers":[
        {
            "category":"Utilities",
            "subcategory":"Fuel Oil & Lpg",
            "type":"Services"
        }
    ],
    "sg:phone":"+44 1329 280364",
    "sg:postcode":"SO31 4NR",
    "sg:province":"Hampshire",
    "wof:name":"Charringtons",
    "wof:placetype":"venue"
},
  "geometry": {"coordinates":[-1.32331,50.856911],"type":"Point"}
}