{
  "type": "Feature",
  "properties": {
    "addr:full":"11-13 Kings Rd, Wombwell Barnsley South Yorkshire S73 0DW",
    "addr:housenumber":"11-13",
    "addr:postcode":"s73 0dw",
    "addr:street":"Kings Rd;Yorkshire",
    "iso:country":"GB",
    "sg:address":"11-13 Kings Rd, Wombwell",
    "sg:city":"Barnsley",
    "sg:classifiers":[
        {
            "category":"Shopping",
            "subcategory":"News",
            "type":"Retail Goods"
        }
    ],
    "sg:phone":"+44 1226 753153",
    "sg:postcode":"S73 0DW",
    "sg:province":"South Yorkshire",
    "sg:tags":[
        "newsagent"
    ],
    "wof:name":"J & A News",
    "wof:placetype":"venue"
},
  "geometry": {"coordinates":[-1.3977520466,53.5203437805],"type":"Point"}
}