{
  "type": "Feature",
  "properties": {
    "addr:full":"23 Lotland St Inverness Highland IV1 1ST",
    "addr:housenumber":"23",
    "addr:postcode":"iv1 1st",
    "addr:street":"Lotland St",
    "iso:country":"GB",
    "sg:address":"23 Lotland St",
    "sg:city":"Inverness",
    "sg:classifiers":[
        {
            "category":"Education",
            "subcategory":"Special Training",
            "type":"Public Place"
        }
    ],
    "sg:phone":"+44 1463 712215",
    "sg:postcode":"IV1 1ST",
    "sg:province":"Highland",
    "sg:tags":[
        "product",
        "centre"
    ],
    "wof:name":"Community Industry",
    "wof:placetype":"venue"
},
  "geometry": {"coordinates":[-4.226934,57.488148],"type":"Point"}
}