{
  "type": "Feature",
  "properties": {
    "iso:country":"GB",
    "sg:address":"The Half Croft, Syston",
    "sg:city":"Leicester",
    "sg:classifiers":[
        {
            "category":"Building & Trades",
            "subcategory":"Electrical",
            "type":"Services"
        }
    ],
    "sg:phone":"+44 116 260 8011",
    "sg:postcode":"LE7 1LD",
    "sg:province":"Leicestershire",
    "sg:tags":[
        "heating"
    ],
    "wof:name":"Rohde Shoes (U K) Ltd.",
    "wof:placetype":"venue"
},
  "geometry": {"coordinates":[-1.08294,52.701496],"type":"Point"}
}