{
  "type": "Feature",
  "properties": {
    "addr:full":"16 Lyon Rd Walton-on-thames Surrey KT12 3PU",
    "addr:housenumber":"16",
    "addr:postcode":"kt12 3pu",
    "addr:street":"Lyon Rd",
    "iso:country":"GB",
    "sg:address":"16 Lyon Rd",
    "sg:city":"Walton-on-thames",
    "sg:classifiers":[
        {
            "category":"Retail",
            "subcategory":"Repair Shop",
            "type":"Services"
        }
    ],
    "sg:postcode":"KT12 3PU",
    "sg:province":"Surrey",
    "sg:tags":[
        "upholsterer"
    ],
    "wof:name":"Trevean,Anthony,",
    "wof:placetype":"venue"
},
  "geometry": {"coordinates":[-0.386778,51.379002],"type":"Point"}
}