{
  "type": "Feature",
  "properties": {
    "addr:full":"Unit 1 Craven Street West Byfleet Surrey KT14 7JL",
    "addr:housenumber":"unit 1",
    "addr:postcode":"kt14 7jl",
    "addr:street":"Craven Street",
    "iso:country":"GB",
    "sg:address":"Unit 1 Craven Street",
    "sg:city":"West Byfleet",
    "sg:classifiers":[
        {
            "category":"Manufacturing",
            "subcategory":"Glass & Minerals",
            "type":"Manufacturing & Wholesale Goods"
        }
    ],
    "sg:phone":"+44 1932 332301",
    "sg:postcode":"KT14 7JL",
    "sg:province":"Surrey",
    "sg:tags":[
        "product"
    ],
    "wof:name":"Heraeus Materials Ltd.",
    "wof:placetype":"venue"
},
  "geometry": {"coordinates":[-0.472594,51.33794],"type":"Point"}
}