{
  "type": "Feature",
  "properties": {
    "iso:country":"GB",
    "sg:address":"6 The Manor House, St Margarets Grn",
    "sg:city":"Ipswich",
    "sg:classifiers":[
        {
            "category":"Education",
            "subcategory":"Special Training",
            "type":"Public Place"
        }
    ],
    "sg:phone":"+44 1473 225295",
    "sg:postcode":"IP4 2BS",
    "sg:province":"Suffolk",
    "sg:tags":[
        "product",
        "centre"
    ],
    "wof:name":"Hotel & Catering Training Co",
    "wof:placetype":"venue"
},
  "geometry": {"coordinates":[1.158836,52.058666],"type":"Point"}
}