{
  "type": "Feature",
  "properties": {
    "addr:full":"10 Bruce Street Dunfermline Fife KY12 7AG",
    "addr:housenumber":"10",
    "addr:postcode":"ky12 7ag",
    "addr:street":"Bruce Street",
    "iso:country":"GB",
    "sg:address":"10 Bruce Street",
    "sg:city":"Dunfermline",
    "sg:classifiers":[
        {
            "category":"Insurance",
            "subcategory":"Insurance Agent",
            "type":"Services"
        },
        {
            "category":"Banks & Credit Unions",
            "subcategory":"Financial Services",
            "type":"Services"
        }
    ],
    "sg:phone":"+44 1383 620072",
    "sg:postcode":"KY12 7AG",
    "sg:province":"Fife",
    "sg:tags":[
        "consultant",
        "broker"
    ],
    "wof:name":"Insuresafe",
    "wof:placetype":"venue"
},
  "geometry": {"coordinates":[-3.463689,56.071529],"type":"Point"}
}