{
  "type": "Feature",
  "properties": {
    "addr:full":"23 Coventry Street Stourbridge Staffordshire DY8 1EP",
    "addr:housenumber":"23",
    "addr:postcode":"dy8 1ep",
    "addr:street":"Coventry Street",
    "iso:country":"GB",
    "sg:address":"23 Coventry Street",
    "sg:city":"Stourbridge",
    "sg:classifiers":[
        {
            "category":"Organizations",
            "subcategory":"Non-profit Organization",
            "type":"Services"
        }
    ],
    "sg:phone":"+44 1384 379992",
    "sg:postcode":"DY8 1EP",
    "sg:province":"Staffordshire",
    "sg:tags":[
        "organisation",
        "voluntary",
        "charity"
    ],
    "wof:name":"The What? Centre Ltd.",
    "wof:placetype":"venue"
},
  "geometry": {"coordinates":[-2.147246,52.457855],"type":"Point"}
}