{
  "type": "Feature",
  "properties": {
    "addr:full":"126 Nottingham Road, Eastwood Nottingham Derbyshire NG16 3GD",
    "addr:housenumber":"126",
    "addr:postcode":"ng16 3gd",
    "addr:street":"Nottingham Road",
    "iso:country":"GB",
    "sg:address":"126 Nottingham Road, Eastwood",
    "sg:city":"Nottingham",
    "sg:classifiers":[
        {
            "category":"Shopping",
            "subcategory":"Clothing, Apparel, & Fashions",
            "type":"Retail Goods"
        }
    ],
    "sg:phone":"+44 1773 760090",
    "sg:postcode":"NG16 3GD",
    "sg:province":"Derbyshire",
    "sg:tags":[
        "shop"
    ],
    "wof:name":"Jazz Gigs",
    "wof:placetype":"venue"
},
  "geometry": {"coordinates":[-1.302345,53.017216],"type":"Point"}
}