{
  "type": "Feature",
  "properties": {
    "addr:full":"130 Hyndford Rd Lanark South Lanarkshire ML11 9AU",
    "addr:housenumber":"130",
    "addr:postcode":"ml11 9au",
    "addr:street":"Hyndford Rd",
    "iso:country":"GB",
    "sg:address":"130 Hyndford Rd",
    "sg:city":"Lanark",
    "sg:classifiers":[
        {
            "category":"Food & Beverages",
            "subcategory":"Liquor & Beverages",
            "type":"Retail Goods"
        }
    ],
    "sg:phone":"+44 1555 662277",
    "sg:postcode":"ML11 9AU",
    "sg:province":"South Lanarkshire",
    "sg:tags":[
        "beer",
        "spirit",
        "wines"
    ],
    "wof:name":"Gavin Liddell",
    "wof:placetype":"venue"
},
  "geometry": {"coordinates":[-3.7644109726,55.6695785522],"type":"Point"}
}