{
  "type": "Feature",
  "properties": {
    "iso:country":"GB",
    "sg:address":"The Old Police Station, Golden Hill",
    "sg:city":"Preston",
    "sg:classifiers":[
        {
            "category":"Professional",
            "subcategory":"Computer Services",
            "type":"Services"
        }
    ],
    "sg:postcode":"PR25 3NN",
    "sg:province":"Lancashire",
    "sg:tags":[
        "system",
        "software"
    ],
    "wof:name":"Chemtec Systems Ltd.",
    "wof:placetype":"venue"
},
  "geometry": {"coordinates":[-2.6879599094,53.6983108521],"type":"Point"}
}