{
  "type": "Feature",
  "properties": {
    "addr:full":"2 Clockhouse Paddock Horsham Rd, Capel Dorking Surrey RH5 5JJ",
    "addr:housenumber":"2",
    "addr:postcode":"rh5 5jj",
    "addr:street":"Clockhouse Paddock Horsham Rd",
    "iso:country":"GB",
    "sg:address":"2 Clockhouse Paddock Horsham Rd, Capel",
    "sg:city":"Dorking",
    "sg:classifiers":[
        {
            "category":"Shopping",
            "subcategory":"Florist",
            "type":"Retail Goods"
        }
    ],
    "sg:postcode":"RH5 5JJ",
    "sg:province":"Surrey",
    "wof:name":"Flowers by Caroline",
    "wof:placetype":"venue"
},
  "geometry": {"coordinates":[-0.3231390119,51.1498146057],"type":"Point"}
}