{
  "type": "Feature",
  "properties": {
    "addr:full":"Gavinton Street, Muirend Glasgow East Renfrewshire G44 3EF",
    "addr:postcode":"g44 3ef",
    "addr:street":"Gavinton Street",
    "iso:country":"GB",
    "sg:address":"Gavinton Street, Muirend",
    "sg:city":"Glasgow",
    "sg:classifiers":[
        {
            "category":"Social Services",
            "subcategory":"Adult Care",
            "type":"Services"
        },
        {
            "category":"Social Services",
            "subcategory":"Retirement Home",
            "type":"Services"
        }
    ],
    "sg:phone":"+44 141 637 9956",
    "sg:postcode":"G44 3EF",
    "sg:province":"East Renfrewshire",
    "sg:tags":[
        "housing",
        "sheltered",
        "accommodation"
    ],
    "wof:name":"Gavinton Street Sheltered Housing",
    "wof:placetype":"venue"
},
  "geometry": {"coordinates":[-4.2698640823,55.811706543],"type":"Point"}
}