{
  "type": "Feature",
  "properties": {
    "iso:country":"GB",
    "sg:address":"Belstone House, Eastern Wood Road, Langage Industrial Estate",
    "sg:city":"Plymouth",
    "sg:classifiers":[
        {
            "category":"Shopping",
            "subcategory":"Gifts & Souvenirs",
            "type":"Retail Goods"
        }
    ],
    "sg:phone":"+44 1752 345130",
    "sg:postcode":"PL7 5ET",
    "sg:province":"Devon",
    "sg:tags":[
        "ducting"
    ],
    "wof:name":"Air Duct Systems (S W) Ltd.",
    "wof:placetype":"venue"
},
  "geometry": {"coordinates":[-4.015759,50.386227],"type":"Point"}
}