{
  "type": "Feature",
  "properties": {
    "addr:full":"Troon Marina, Harbour Rd Troon South Ayrshire KA10 6DJ",
    "addr:postcode":"ka10 6dj",
    "addr:street":"Marina Harbour Rd",
    "iso:country":"GB",
    "sg:address":"Troon Marina, Harbour Rd",
    "sg:city":"Troon",
    "sg:classifiers":[
        {
            "category":"Autos & Motor Vehicles",
            "subcategory":"Boat Sales",
            "type":"Retail Goods"
        }
    ],
    "sg:phone":"+44 1292 319196",
    "sg:postcode":"KA10 6DJ",
    "sg:province":"South Ayrshire",
    "sg:tags":[
        "repair",
        "builder"
    ],
    "wof:name":"Rinker Direct",
    "wof:placetype":"venue"
},
  "geometry": {"coordinates":[-4.6537041664,55.5463142395],"type":"Point"}
}