{
  "type": "Feature",
  "properties": {
    "iso:country":"GB",
    "sg:address":"17 The Birches",
    "sg:city":"Leeds",
    "sg:classifiers":[
        {
            "category":"Organizations",
            "subcategory":"Non-profit Organization",
            "type":"Services"
        }
    ],
    "sg:phone":"+44 113 267 4518",
    "sg:postcode":"LS16 9DP",
    "sg:province":"West Yorkshire",
    "sg:tags":[
        "organisation",
        "voluntary",
        "charity"
    ],
    "wof:name":"Beauty Without Cruelty Charity",
    "wof:placetype":"venue"
},
  "geometry": {"coordinates":[-1.606019,53.877945],"type":"Point"}
}