{
  "type": "Feature",
  "properties": {
    "addr:full":"216 Westmill Rd Hitchin Bedfordshire SG5 2SP",
    "addr:housenumber":"216",
    "addr:postcode":"sg5 2sp",
    "addr:street":"Westmill Rd",
    "iso:country":"GB",
    "sg:address":"216 Westmill Rd",
    "sg:city":"Hitchin",
    "sg:classifiers":[
        {
            "category":"Recreation",
            "subcategory":"Dog Park",
            "type":"Entertainment"
        }
    ],
    "sg:phone":"+44 1462 457433",
    "sg:postcode":"SG5 2SP",
    "sg:province":"Bedfordshire",
    "wof:name":"Janice's Dog Grooming",
    "wof:placetype":"venue"
},
  "geometry": {"coordinates":[-0.293166995,51.9615020752],"type":"Point"}
}