{
  "type": "Feature",
  "properties": {
    "addr:full":"48 South St Ilkeston Derbyshire DE7 5QJ",
    "addr:housenumber":"48",
    "addr:postcode":"de7 5qj",
    "addr:street":"South St",
    "iso:country":"GB",
    "sg:address":"48 South St",
    "sg:city":"Ilkeston",
    "sg:classifiers":[
        {
            "category":"Banks & Credit Unions",
            "subcategory":"Financial Services",
            "type":"Services"
        }
    ],
    "sg:phone":"+44 115 932 2355",
    "sg:postcode":"DE7 5QJ",
    "sg:province":"Derbyshire",
    "sg:tags":[
        "adviser"
    ],
    "wof:name":"Williams Life Pensions Mortgage & Insurance Services",
    "wof:placetype":"venue"
},
  "geometry": {"coordinates":[-1.3091490269,52.9688034058],"type":"Point"}
}