{
  "type": "Feature",
  "properties": {
    "addr:full":"60a Cartlett Haverfordwest Pembrokeshire SA61 2LH",
    "addr:housenumber":"60a",
    "addr:postcode":"sa61 2lh",
    "addr:street":"Cartlett;Pembrokeshire",
    "iso:country":"GB",
    "sg:address":"60a Cartlett",
    "sg:city":"Haverfordwest",
    "sg:classifiers":[
        {
            "category":"Home & Garden",
            "subcategory":"Household Appliances",
            "type":"Retail Goods"
        }
    ],
    "sg:phone":"+44 1437 767711",
    "sg:postcode":"SA61 2LH",
    "sg:province":"Pembrokeshire",
    "sg:tags":[
        "cleaner",
        "vacuum"
    ],
    "wof:name":"South Wales Home Care Ltd",
    "wof:placetype":"venue"
},
  "geometry": {"coordinates":[-4.959441,51.803436],"type":"Point"}
}