{
  "type": "Feature",
  "properties": {
    "iso:country":"GB",
    "sg:address":"11 Lindridge Close",
    "sg:city":"Newton Abbot",
    "sg:classifiers":[
        {
            "category":"Building & Trades",
            "subcategory":"Plumbing",
            "type":"Services"
        }
    ],
    "sg:postcode":"TQ12 3NW",
    "sg:province":"Devon",
    "sg:tags":[
        "heating"
    ],
    "wof:name":"Bowden,Michael G,",
    "wof:placetype":"venue"
},
  "geometry": {"coordinates":[-3.597148,50.560108],"type":"Point"}
}