{
  "type": "Feature",
  "properties": {
    "iso:country":"GB",
    "sg:address":"21 Sandown Lane",
    "sg:city":"Liverpool",
    "sg:classifiers":[
        {
            "category":"Shopping",
            "subcategory":"Discount & Variety Stores",
            "type":"Retail Goods"
        }
    ],
    "sg:postcode":"L15 8HY",
    "sg:province":"Merseyside",
    "sg:tags":[
        "cleaning",
        "supply"
    ],
    "wof:name":"Hutpine Ltd.",
    "wof:placetype":"venue"
},
  "geometry": {"coordinates":[-2.921808,53.400448],"type":"Point"}
}