{
  "type": "Feature",
  "properties": {
    "iso:country":"GB",
    "sg:address":"Salisbury Street",
    "sg:city":"Leek",
    "sg:classifiers":[
        {
            "category":"Community Center",
            "subcategory":"Youth",
            "type":"Public Place"
        }
    ],
    "sg:phone":"+44 1538 383877",
    "sg:postcode":"ST13 5EE",
    "sg:province":"Staffordshire",
    "sg:tags":[
        "organisation",
        "centre"
    ],
    "wof:name":"Milwood Hall Youth & Community Centre",
    "wof:placetype":"venue"
},
  "geometry": {"coordinates":[-2.0289340019,53.1063766479],"type":"Point"}
}