{
  "type": "Feature",
  "properties": {
    "iso:country":"GB",
    "sg:address":"Constituency Of Carrick, Cumnock And Doon Valley, Skerrington House,  Glasnock,",
    "sg:city":"Ayr",
    "sg:classifiers":[
        {
            "category":"Government",
            "subcategory":"Office",
            "type":"Public Place"
        }
    ],
    "sg:phone":"+44 1290 422990",
    "sg:postcode":"KA18 3BU",
    "sg:province":"East Ayrshire",
    "sg:tags":[
        "mp",
        "meps"
    ],
    "wof:name":"George Foulkes MP (Lab)",
    "wof:placetype":"venue"
},
  "geometry": {"coordinates":[-4.2517199516,55.4389381409],"type":"Point"}
}