{
  "type": "Feature",
  "properties": {
    "addr:full":"59 Duchy Road Harrogate North Yorkshire HG1 2HE",
    "addr:housenumber":"59",
    "addr:postcode":"hg1 2he",
    "addr:street":"Duchy Road",
    "iso:country":"GB",
    "sg:address":"59 Duchy Road",
    "sg:city":"Harrogate",
    "sg:classifiers":[
        {
            "category":"Health Services",
            "subcategory":"Nursing And Care Facility",
            "type":"Services"
        }
    ],
    "sg:phone":"+44 1423 567872",
    "sg:postcode":"HG1 2HE",
    "sg:province":"North Yorkshire",
    "sg:tags":[
        "home"
    ],
    "wof:name":"Duchy House",
    "wof:placetype":"venue"
},
  "geometry": {"coordinates":[-1.565071,53.991631],"type":"Point"}
}