{
  "type": "Feature",
  "properties": {
    "iso:country":"GB",
    "sg:address":"Ty Mair, Menai Av",
    "sg:city":"Bangor",
    "sg:classifiers":[
        {
            "category":"Organizations",
            "subcategory":"Religious Organization",
            "type":"Services"
        }
    ],
    "sg:phone":"+44 1248 353670",
    "sg:postcode":"LL57 2HH",
    "sg:province":"Gwynedd",
    "sg:tags":[
        "organisation"
    ],
    "wof:name":"Sisters of Mercy",
    "wof:placetype":"venue"
},
  "geometry": {"coordinates":[-4.1260638237,53.2295951843],"type":"Point"}
}