{
  "type": "Feature",
  "properties": {
    "iso:country":"GB",
    "sg:address":"11 Riddings Close",
    "sg:city":"Bewdley",
    "sg:classifiers":[
        {
            "category":"Building & Trades",
            "subcategory":"Plumbing",
            "type":"Services"
        }
    ],
    "sg:phone":"+44 1299 402473",
    "sg:postcode":"DY12 1EN",
    "sg:province":"Shropshire",
    "sg:tags":[
        "heating"
    ],
    "wof:name":"C E Owen",
    "wof:placetype":"venue"
},
  "geometry": {"coordinates":[-2.3057088852,52.3840255737],"type":"Point"}
}