{
  "type": "Feature",
  "properties": {
    "iso:country":"GB",
    "sg:address":"The Water Front, 7-8 Westbridge Close",
    "sg:city":"Leicester",
    "sg:classifiers":[
        {
            "category":"Professional",
            "subcategory":"Employment Agencies",
            "type":"Services"
        }
    ],
    "sg:phone":"+44 116 299 4040",
    "sg:postcode":"LE3 5LW",
    "sg:province":"Leicestershire",
    "sg:tags":[
        "consultant"
    ],
    "wof:name":"P H D S Ltd.",
    "wof:placetype":"venue"
},
  "geometry": {"coordinates":[-1.143329978,52.6326217651],"type":"Point"}
}