{
  "type": "Feature",
  "properties": {
    "addr:full":"Unit 3, Rhosddu Industrial Estate, Old Rhosrobin Wrexham Wrexham LL11 4YL",
    "addr:housenumber":"unit 3",
    "addr:postcode":"ll11 4yl",
    "addr:street":"Rhosddu Industrial Estate Old Rhosrobin",
    "iso:country":"GB",
    "sg:address":"Unit 3, Rhosddu Industrial Estate, Old Rhosrobin",
    "sg:city":"Wrexham",
    "sg:classifiers":[
        {
            "category":"Retail",
            "subcategory":"Auto Repair",
            "type":"Services"
        }
    ],
    "sg:phone":"+44 1978 350512",
    "sg:postcode":"LL11 4YL",
    "sg:province":"Wrexham",
    "sg:tags":[
        "body",
        "garage",
        "modification",
        "car"
    ],
    "wof:name":"Wrexham Auto Kraft",
    "wof:placetype":"venue"
},
  "geometry": {"coordinates":[-3.0026988983,53.0706214905],"type":"Point"}
}