{
  "type": "Feature",
  "properties": {
    "iso:country":"GB",
    "sg:address":"Swanton Morley, East Dereham",
    "sg:city":"Dereham",
    "sg:classifiers":[
        {
            "category":"Health Services",
            "subcategory":"Nursing And Care Facility",
            "type":"Services"
        }
    ],
    "sg:phone":"+44 1362 637598",
    "sg:postcode":"NR20 4LT",
    "sg:province":"Norfolk",
    "sg:tags":[
        "home"
    ],
    "wof:name":"Lincoln House Nursing Home",
    "wof:placetype":"venue"
},
  "geometry": {"coordinates":[0.97885,52.702148],"type":"Point"}
}