{
  "type": "Feature",
  "properties": {
    "addr:full":"Lodge Farm, East Street, Fritwell Bicester Buckinghamshire OX27 7QF",
    "addr:postcode":"ox27 7qf",
    "addr:street":"Lodge;East Street",
    "iso:country":"GB",
    "sg:address":"Lodge Farm, East Street, Fritwell",
    "sg:city":"Bicester",
    "sg:classifiers":[
        {
            "category":"Farming",
            "subcategory":"Livestock Farm",
            "type":"Manufacturing & Wholesale Goods"
        }
    ],
    "sg:phone":"+44 1869 345214",
    "sg:postcode":"OX27 7QF",
    "sg:province":"Buckinghamshire",
    "sg:tags":[
        "others"
    ],
    "wof:name":"J Baker & Sons",
    "wof:placetype":"venue"
},
  "geometry": {"coordinates":[-1.231937,51.959255],"type":"Point"}
}