{
  "type": "Feature",
  "properties": {
    "addr:full":"31b Stubbington Green Fareham Hampshire PO14 2LE",
    "addr:housenumber":"31b",
    "addr:postcode":"po14 2le",
    "addr:street":"Stubbington Green",
    "iso:country":"GB",
    "sg:address":"31b Stubbington Green",
    "sg:city":"Fareham",
    "sg:classifiers":[
        {
            "category":"Personal",
            "subcategory":"Beauty Salon",
            "type":"Services"
        }
    ],
    "sg:phone":"+44 1329 667641",
    "sg:postcode":"PO14 2LE",
    "sg:province":"Hampshire",
    "sg:tags":[
        "unisex",
        "hairdresser"
    ],
    "wof:name":"Kutrz",
    "wof:placetype":"venue"
},
  "geometry": {"coordinates":[-1.2133510113,50.8260955811],"type":"Point"}
}