{
  "type": "Feature",
  "properties": {
    "addr:full":"55 Exley Road Keighley West Yorkshire BD21 1LT",
    "addr:housenumber":"55",
    "addr:postcode":"bd21 1lt",
    "addr:street":"Exley Road",
    "iso:country":"GB",
    "sg:address":"55 Exley Road",
    "sg:city":"Keighley",
    "sg:classifiers":[
        {
            "category":"Building & Trades",
            "subcategory":"Construction",
            "type":"Services"
        }
    ],
    "sg:phone":"+44 1535 662061",
    "sg:postcode":"BD21 1LT",
    "sg:province":"West Yorkshire",
    "sg:tags":[
        "builder"
    ],
    "wof:name":"TIMOTHY HIRD & SON (BUILDERS & CONTRACTORS) LTD",
    "wof:placetype":"venue"
},
  "geometry": {"coordinates":[-1.9242620468,53.8576850891],"type":"Point"}
}