{
  "type": "Feature",
  "properties": {
    "addr:full":"Rockwell Emi Home, Corbet Close Bristol City of Bristol BS11 0TA",
    "addr:postcode":"bs11 0ta",
    "addr:street":"Corbet Close",
    "iso:country":"GB",
    "sg:address":"Rockwell Emi Home, Corbet Close",
    "sg:city":"Bristol",
    "sg:classifiers":[
        {
            "category":"Organizations",
            "subcategory":"Non-profit Organization",
            "type":"Services"
        }
    ],
    "sg:phone":"+44 117 923 5773",
    "sg:postcode":"BS11 0TA",
    "sg:province":"City of Bristol",
    "sg:tags":[
        "organisation",
        "voluntary",
        "charity"
    ],
    "wof:name":"Willows Day Centre",
    "wof:placetype":"venue"
},
  "geometry": {"coordinates":[-2.650516,51.501755],"type":"Point"}
}