{
  "type": "Feature",
  "properties": {
    "addr:full":"21 Calais Road Burton-on-trent Derbyshire DE13 0UJ",
    "addr:postcode":"de13 0uj",
    "addr:street":"Calais Road",
    "iso:country":"GB",
    "sg:address":"21 Calais Road",
    "sg:city":"Burton-on-trent",
    "sg:classifiers":[
        {
            "category":"Shopping",
            "subcategory":"News",
            "type":"Retail Goods"
        }
    ],
    "sg:phone":"+44 1283 544178",
    "sg:postcode":"DE13 0UJ",
    "sg:province":"Derbyshire",
    "sg:tags":[
        "newsagent"
    ],
    "wof:name":"B & G News",
    "wof:placetype":"venue"
},
  "geometry": {"coordinates":[-1.6516859531,52.8183097839],"type":"Point"}
}