{
  "type": "Feature",
  "properties": {
    "iso:country":"GB",
    "sg:address":"Borough Offices Angel Hill",
    "sg:city":"Bury St Edmunds",
    "sg:classifiers":[
        {
            "category":"Community Center",
            "type":"Public Place"
        }
    ],
    "sg:phone":"+44 1284 757065",
    "sg:postcode":"IP33 1XB",
    "sg:province":"Suffolk",
    "sg:tags":[
        "conference",
        "room",
        "centre"
    ],
    "wof:name":"St Edmundsbury Halls",
    "wof:placetype":"venue"
},
  "geometry": {"coordinates":[0.70932,52.249905],"type":"Point"}
}