{
  "type": "Feature",
  "properties": {
    "addr:full":"36/4 Murrayburn Park, Murrayburn Park Edinburgh City of Edinburgh EH14 2PT",
    "addr:housenumber":"36 / 4",
    "addr:postcode":"eh14 2pt",
    "addr:street":"Murrayburn Park Murrayburn Park Edinburgh",
    "iso:country":"GB",
    "sg:address":"36/4 Murrayburn Park, Murrayburn Park",
    "sg:city":"Edinburgh",
    "sg:classifiers":[
        {
            "category":"Building & Trades",
            "subcategory":"Plumbing",
            "type":"Services"
        }
    ],
    "sg:phone":"+44 131 453 3170",
    "sg:postcode":"EH14 2PT",
    "sg:province":"City of Edinburgh",
    "sg:tags":[
        "heating"
    ],
    "wof:name":"K J S Plumbing & Building",
    "wof:placetype":"venue"
},
  "geometry": {"coordinates":[-3.2820589542,55.919380188],"type":"Point"}
}