{
  "type": "Feature",
  "properties": {
    "addr:full":"54 Cramhurst La Godalming Surrey GU8 5QZ",
    "addr:housenumber":"54",
    "addr:postcode":"gu8 5qz",
    "addr:street":"Cramhurst La Godalming",
    "iso:country":"GB",
    "sg:address":"54 Cramhurst La",
    "sg:city":"Godalming",
    "sg:classifiers":[
        {
            "category":"Professional",
            "subcategory":"Accounting & Tax Preparation",
            "type":"Services"
        }
    ],
    "sg:postcode":"GU8 5QZ",
    "sg:province":"Surrey",
    "sg:tags":[
        "accountant"
    ],
    "wof:name":"Berry,Carolyne S,",
    "wof:placetype":"venue"
},
  "geometry": {"coordinates":[-0.656768024,51.1588973999],"type":"Point"}
}