{
  "type": "Feature",
  "properties": {
    "iso:country":"GB",
    "sg:address":"The Docks",
    "sg:city":"Milford Haven",
    "sg:classifiers":[
        {
            "category":"Professional",
            "subcategory":"Engineering",
            "type":"Services"
        },
        {
            "category":"Building & Trades",
            "subcategory":"Electrical",
            "type":"Services"
        }
    ],
    "sg:phone":"+44 1646 692125",
    "sg:postcode":"SA73 3AF",
    "sg:province":"Pembrokeshire",
    "sg:tags":[
        "engineer",
        "electrician",
        "contractor"
    ],
    "wof:name":"Norrard Electrics",
    "wof:placetype":"venue"
},
  "geometry": {"coordinates":[-5.0270438194,51.7168083191],"type":"Point"}
}