{
  "type": "Feature",
  "properties": {
    "iso:country":"GB",
    "sg:address":"197 Manford Way",
    "sg:city":"Chigwell",
    "sg:classifiers":[
        {
            "category":"Food & Beverages",
            "subcategory":"Bakery",
            "type":"Retail Goods"
        }
    ],
    "sg:phone":"+44 20 8500 2166",
    "sg:postcode":"IG7 4DJ",
    "sg:province":"Essex",
    "sg:tags":[
        "baker"
    ],
    "wof:name":"Greggs",
    "wof:placetype":"venue"
},
  "geometry": {"coordinates":[0.1068,51.608364],"type":"Point"}
}