{
  "type": "Feature",
  "properties": {
    "iso:country":"GB",
    "sg:address":"Woodthorpe House, Mansfield Road",
    "sg:city":"Nottingham",
    "sg:classifiers":[
        {
            "category":"Education",
            "subcategory":"Dance Studio",
            "type":"Public Place"
        }
    ],
    "sg:postcode":"NG5 3FN",
    "sg:province":"Nottinghamshire",
    "sg:tags":[
        "school",
        "dancing"
    ],
    "wof:name":"Gregory School of Dancing",
    "wof:placetype":"venue"
},
  "geometry": {"coordinates":[-1.139457,52.993134],"type":"Point"}
}