{
  "type": "Feature",
  "properties": {
    "iso:country":"GB",
    "sg:address":"433 Park Road, Hockley",
    "sg:city":"Birmingham",
    "sg:classifiers":[
        {
            "category":"Professional",
            "subcategory":"Engineering",
            "type":"Services"
        }
    ],
    "sg:phone":"+44 121 551 1184",
    "sg:postcode":"B18 5TE",
    "sg:province":"West Midlands",
    "sg:tags":[
        "contractor",
        "electrical",
        "engineer"
    ],
    "wof:name":"Osborn Electrical Ltd.",
    "wof:placetype":"venue"
},
  "geometry": {"coordinates":[-1.9292440414,52.4983558655],"type":"Point"}
}