{
  "type": "Feature",
  "properties": {
    "iso:country":"GB",
    "sg:address":"9 Whitton Place, Seaton Delaval",
    "sg:city":"Whitley Bay",
    "sg:classifiers":[
        {
            "category":"Building & Trades",
            "subcategory":"Construction",
            "type":"Services"
        }
    ],
    "sg:phone":"+44 191 257 2747",
    "sg:postcode":"NE25 0BJ",
    "sg:province":"Northumberland",
    "sg:tags":[
        "tiling",
        "contractor"
    ],
    "wof:name":"Premier Tiling",
    "wof:placetype":"venue"
},
  "geometry": {"coordinates":[-1.517441988,55.0707206726],"type":"Point"}
}