{
  "type": "Feature",
  "properties": {
    "addr:full":"Lane End, Urban Road, Kirkby-in-ashfield Nottingham Nottinghamshire NG17 8AP",
    "addr:postcode":"ng17 8ap",
    "addr:street":"Urban Road",
    "iso:country":"GB",
    "sg:address":"Lane End, Urban Road, Kirkby-in-ashfield",
    "sg:city":"Nottingham",
    "sg:classifiers":[
        {
            "category":"Utilities",
            "subcategory":"Recycling",
            "type":"Services"
        }
    ],
    "sg:phone":"+44 1623 721006",
    "sg:postcode":"NG17 8AP",
    "sg:province":"Nottinghamshire",
    "sg:tags":[
        "centre"
    ],
    "wof:name":"Wheelie Bank Systems",
    "wof:placetype":"venue"
},
  "geometry": {"coordinates":[-1.2533479929,53.0995445251],"type":"Point"}
}