{
  "type": "Feature",
  "properties": {
    "iso:country":"GB",
    "sg:address":"39 Hamilton Street",
    "sg:city":"Saltcoats",
    "sg:classifiers":[
        {
            "category":"Fast Food",
            "type":"Food & Drink"
        }
    ],
    "sg:phone":"+44 1294 462100",
    "sg:postcode":"KA21 5DT",
    "sg:province":"North Ayrshire",
    "sg:tags":[
        "away",
        "meal",
        "outlet",
        "take"
    ],
    "wof:name":"Lunch Box",
    "wof:placetype":"venue"
},
  "geometry": {"coordinates":[-4.790599823,55.634803772],"type":"Point"}
}