{
  "type": "Feature",
  "properties": {
    "addr:full":"3 Addington Road, Woodford Kettering Northamptonshire NN14 4ES",
    "addr:housenumber":"3",
    "addr:postcode":"nn14 4es",
    "addr:street":"Addington Road",
    "iso:country":"GB",
    "sg:address":"3 Addington Road, Woodford",
    "sg:city":"Kettering",
    "sg:classifiers":[
        {
            "category":"Building & Trades",
            "subcategory":"Construction",
            "type":"Services"
        }
    ],
    "sg:phone":"+44 1832 734376",
    "sg:postcode":"NN14 4ES",
    "sg:province":"Northamptonshire",
    "sg:tags":[
        "builder"
    ],
    "wof:name":"A J Brown",
    "wof:placetype":"venue"
},
  "geometry": {"coordinates":[-0.58071,52.381443],"type":"Point"}
}