{
  "type": "Feature",
  "properties": {
    "addr:full":"Grapevine Hotel, Sheep St Cheltenham Gloucestershire GL54 1AU",
    "addr:postcode":"gl54 1au",
    "addr:street":"Sheep St",
    "iso:country":"GB",
    "sg:address":"Grapevine Hotel, Sheep St",
    "sg:city":"Cheltenham",
    "sg:classifiers":[
        {
            "category":"Travel",
            "subcategory":"Hotels & Motels",
            "type":"Entertainment"
        }
    ],
    "sg:phone":"+44 1451 830344",
    "sg:postcode":"GL54 1AU",
    "sg:province":"Gloucestershire",
    "wof:name":"Best Western Hotels",
    "wof:placetype":"venue"
},
  "geometry": {"coordinates":[-1.7212300301,51.9288711548],"type":"Point"}
}