{
  "type": "Feature",
  "properties": {
    "iso:country":"GB",
    "sg:address":"Five Birches, Nairdwood La",
    "sg:city":"Great Missenden",
    "sg:classifiers":[
        {
            "category":"Professional",
            "subcategory":"Management & Consulting",
            "type":"Services"
        }
    ],
    "sg:phone":"+44 1494 890854",
    "sg:postcode":"HP16 0QQ",
    "sg:province":"Buckinghamshire",
    "sg:tags":[
        "consultant",
        "business"
    ],
    "wof:name":"Morton Hodson Management Consultants",
    "wof:placetype":"venue"
},
  "geometry": {"coordinates":[-0.709043,51.704067],"type":"Point"}
}