{
  "type": "Feature",
  "properties": {
    "addr:full":"35 Linford Close Wigston Leicestershire LE18 3PZ",
    "addr:housenumber":"35",
    "addr:postcode":"le18 3pz",
    "addr:street":"Linford Close",
    "iso:country":"GB",
    "sg:address":"35 Linford Close",
    "sg:city":"Wigston",
    "sg:classifiers":[
        {
            "category":"Real Estate",
            "subcategory":"Real Estate Services",
            "type":"Services"
        },
        {
            "category":"Building & Trades",
            "subcategory":"Construction",
            "type":"Services"
        }
    ],
    "sg:phone":"+44 116 288 1293",
    "sg:postcode":"LE18 3PZ",
    "sg:province":"Leicestershire",
    "sg:tags":[
        "dry",
        "lining",
        "plasterers",
        "screeders"
    ],
    "wof:name":"Frederick M Linehan",
    "wof:placetype":"venue"
},
  "geometry": {"coordinates":[-1.097337,52.58519],"type":"Point"}
}