{
  "type": "Feature",
  "properties": {
    "addr:full":"20 Morgan St Pontypridd Caerphilly CF37 2DS",
    "addr:housenumber":"20",
    "addr:postcode":"cf37 2ds",
    "addr:street":"Morgan St",
    "iso:country":"GB",
    "sg:address":"20 Morgan St",
    "sg:city":"Pontypridd",
    "sg:classifiers":[
        {
            "category":"Health Services",
            "subcategory":"Dentist",
            "type":"Services"
        }
    ],
    "sg:phone":"+44 1443 403747",
    "sg:postcode":"CF37 2DS",
    "sg:province":"Caerphilly",
    "wof:name":"S A Hargreaves",
    "wof:placetype":"venue"
},
  "geometry": {"coordinates":[-3.3393189907,51.6060523987],"type":"Point"}
}