{
  "type": "Feature",
  "properties": {
    "iso:country":"GB",
    "sg:address":"46-47 Upper Berkeley Street",
    "sg:city":"London",
    "sg:classifiers":[
        {
            "category":"Professional",
            "subcategory":"Business Services",
            "type":"Services"
        }
    ],
    "sg:phone":"+44 20 7723 7977",
    "sg:postcode":"W1H 5QW",
    "sg:province":"Greater London",
    "sg:tags":[
        "import",
        "export",
        "agent"
    ],
    "wof:name":"Dubal Services Ltd.",
    "wof:placetype":"venue"
},
  "geometry": {"coordinates":[-0.161689,51.515079],"type":"Point"}
}