{
  "type": "Feature",
  "properties": {
    "addr:full":"233 Greenford Rd Greenford Greater London UB6 8QZ",
    "addr:housenumber":"233",
    "addr:postcode":"ub6 8qz",
    "addr:street":"Greenford Rd",
    "iso:country":"GB",
    "sg:address":"233 Greenford Rd",
    "sg:city":"Greenford",
    "sg:classifiers":[
        {
            "category":"Health Services",
            "subcategory":"Dentist",
            "type":"Services"
        }
    ],
    "sg:phone":"+44 20 8575 8030",
    "sg:postcode":"UB6 8QZ",
    "sg:province":"Greater London",
    "wof:name":"Ghalley S.S. & Associates",
    "wof:placetype":"venue"
},
  "geometry": {"coordinates":[-0.3519000113,51.5288085938],"type":"Point"}
}