{
  "type": "Feature",
  "properties": {
    "iso:country":"GB",
    "sg:address":"The Fireplace, 9 Lower St James St",
    "sg:city":"Newport",
    "sg:classifiers":[
        {
            "category":"Home & Garden",
            "subcategory":"Furniture",
            "type":"Retail Goods"
        }
    ],
    "sg:phone":"+44 1983 529763",
    "sg:postcode":"PO30 5HE",
    "sg:province":"Isle of Wight",
    "wof:name":"Vectis Kitchens",
    "wof:placetype":"venue"
},
  "geometry": {"coordinates":[-1.295939,50.7001],"type":"Point"}
}