{
  "type": "Feature",
  "properties": {
    "addr:full":"9 Bannockburn Road Stirling Falkirk FK7 0BP",
    "addr:housenumber":"9",
    "addr:postcode":"fk7 0bp",
    "addr:street":"Bannockburn Road",
    "iso:country":"GB",
    "sg:address":"9 Bannockburn Road",
    "sg:city":"Stirling",
    "sg:classifiers":[
        {
            "category":"Fast Food",
            "type":"Food & Drink"
        }
    ],
    "sg:phone":"+44 1786 473756",
    "sg:postcode":"FK7 0BP",
    "sg:province":"Falkirk",
    "sg:tags":[
        "away",
        "take"
    ],
    "wof:name":"New Hong Gai Takeaway",
    "wof:placetype":"venue"
},
  "geometry": {"coordinates":[-3.936674118,56.1003646851],"type":"Point"}
}