{
  "type": "Feature",
  "properties": {
    "addr:full":"30 Gardiner Street Prestwick South Ayrshire KA9 1JY",
    "addr:housenumber":"30",
    "addr:postcode":"ka9 1jy",
    "addr:street":"Gardiner Street",
    "iso:country":"GB",
    "sg:address":"30 Gardiner Street",
    "sg:city":"Prestwick",
    "sg:classifiers":[
        {
            "category":"Shopping",
            "subcategory":"Antiques",
            "type":"Retail Goods"
        }
    ],
    "sg:postcode":"KA9 1JY",
    "sg:province":"South Ayrshire",
    "wof:name":"Michael Manacini Furniture",
    "wof:placetype":"venue"
},
  "geometry": {"coordinates":[-4.609111,55.498745],"type":"Point"}
}