{
  "type": "Feature",
  "properties": {
    "iso:country":"GB",
    "sg:address":"Forth Avenue",
    "sg:city":"Kirkcaldy",
    "sg:classifiers":[
        {
            "category":"Autos & Motor Vehicles",
            "subcategory":"Auto Supplies",
            "type":"Retail Goods"
        }
    ],
    "sg:phone":"+44 1592 266171",
    "sg:postcode":"KY2 5QN",
    "sg:province":"Fife",
    "sg:tags":[
        "component"
    ],
    "wof:name":"Partco Ltd.",
    "wof:placetype":"venue"
},
  "geometry": {"coordinates":[-3.166924,56.114868],"type":"Point"}
}