{
  "type": "Feature",
  "properties": {
    "addr:full":"11 School Lane, Brinscall Chorley Lancashire PR6 8QS",
    "addr:housenumber":"11",
    "addr:postcode":"pr6 8qs",
    "addr:street":"School Lane",
    "iso:country":"GB",
    "sg:address":"11 School Lane, Brinscall",
    "sg:city":"Chorley",
    "sg:classifiers":[
        {
            "category":"Building & Trades",
            "subcategory":"Construction",
            "type":"Services"
        }
    ],
    "sg:phone":"+44 1254 830259",
    "sg:postcode":"PR6 8QS",
    "sg:province":"Lancashire",
    "sg:tags":[
        "decorator",
        "painter"
    ],
    "wof:name":"Clive Hull",
    "wof:placetype":"venue"
},
  "geometry": {"coordinates":[-2.5651800632,53.6877708435],"type":"Point"}
}