{
  "type": "Feature",
  "properties": {
    "addr:full":"Pine Tree Farm, Castle Lane, Wookey Wells Somerset BA5 1NN",
    "addr:postcode":"ba5 1nn",
    "addr:street":"Pine;Castle Lane",
    "iso:country":"GB",
    "sg:address":"Pine Tree Farm, Castle Lane, Wookey",
    "sg:city":"Wells",
    "sg:classifiers":[
        {
            "category":"Farming",
            "subcategory":"Livestock Farm",
            "type":"Manufacturing & Wholesale Goods"
        },
        {
            "category":"Farming",
            "subcategory":"Farm",
            "type":"Manufacturing & Wholesale Goods"
        }
    ],
    "sg:phone":"+44 1749 675247",
    "sg:postcode":"BA5 1NN",
    "sg:province":"Somerset",
    "sg:tags":[
        "mixed",
        "crop",
        "others"
    ],
    "wof:name":"R H & B D STOTT",
    "wof:placetype":"venue"
},
  "geometry": {"coordinates":[-2.6912670135,51.2068901062],"type":"Point"}
}