{
  "type": "Feature",
  "properties": {
    "iso:country":"GB",
    "sg:address":"Unit 13 Burton Enterprise Park, Hawkins Lane",
    "sg:city":"Burton-on-trent",
    "sg:classifiers":[
        {
            "category":"Professional",
            "subcategory":"Engineering",
            "type":"Services"
        }
    ],
    "sg:phone":"+44 1283 510213",
    "sg:postcode":"DE14 1QG",
    "sg:province":"Derbyshire",
    "wof:name":"Tipper Engineering",
    "wof:placetype":"venue"
},
  "geometry": {"coordinates":[-1.627324,52.816456],"type":"Point"}
}