{
  "type": "Feature",
  "properties": {
    "addr:full":"Quartzite Quarry, Cromhall Wotton-under-edge Gloucestershire GL12 8AB",
    "addr:postcode":"gl12 8ab",
    "addr:street":"Quartzite Quarry",
    "iso:country":"GB",
    "sg:address":"Quartzite Quarry, Cromhall",
    "sg:city":"Wotton-under-edge",
    "sg:classifiers":[
        {
            "category":"Manufacturing",
            "subcategory":"Glass & Minerals",
            "type":"Manufacturing & Wholesale Goods"
        }
    ],
    "sg:phone":"+44 1454 294513",
    "sg:postcode":"GL12 8AB",
    "sg:province":"Gloucestershire",
    "sg:tags":[
        "chalk",
        "stone",
        "slate"
    ],
    "wof:name":"R M C Roadstone Western",
    "wof:placetype":"venue"
},
  "geometry": {"coordinates":[-2.4440569878,51.6057929993],"type":"Point"}
}