{
  "type": "Feature",
  "properties": {
    "addr:full":"29-31 Fordbridge Road Ashford Greater London TW15 2TB",
    "addr:housenumber":"29-31",
    "addr:postcode":"tw15 2tb",
    "addr:street":"Fordbridge Road",
    "iso:country":"GB",
    "sg:address":"29-31 Fordbridge Road",
    "sg:city":"Ashford",
    "sg:classifiers":[
        {
            "category":"Social Services",
            "subcategory":"Retirement Home",
            "type":"Services"
        }
    ],
    "sg:phone":"+44 1784 253839",
    "sg:postcode":"TW15 2TB",
    "sg:province":"Greater London",
    "sg:tags":[
        "residential",
        "care"
    ],
    "wof:name":"HARPER HOTEL",
    "wof:placetype":"venue"
},
  "geometry": {"coordinates":[-0.464183,51.430611],"type":"Point"}
}