{
  "type": "Feature",
  "properties": {
    "addr:full":"205 Goldhawk Road, Shepherds Bush London Greater London W12 8EP",
    "addr:housenumber":"205",
    "addr:postcode":"w12 8ep",
    "addr:street":"Goldhawk Road",
    "iso:country":"GB",
    "sg:address":"205 Goldhawk Road, Shepherds Bush",
    "sg:city":"London",
    "sg:classifiers":[
        {
            "category":"Organizations",
            "subcategory":"Membership Organization",
            "type":"Services"
        }
    ],
    "sg:phone":"+44 20 8743 1624",
    "sg:postcode":"W12 8EP",
    "sg:province":"Greater London",
    "sg:tags":[
        "club"
    ],
    "wof:name":"Hyde & District Credit Union Ltd.",
    "wof:placetype":"venue"
},
  "geometry": {"coordinates":[-0.235650003,51.5002250671],"type":"Point"}
}