{
  "type": "Feature",
  "properties": {
    "iso:country":"GB",
    "sg:address":"88 Yarmouth Crescent",
    "sg:city":"London",
    "sg:classifiers":[
        {
            "category":"Retail",
            "subcategory":"Photofinishing",
            "type":"Services"
        },
        {
            "category":"Professional",
            "subcategory":"Art Services",
            "type":"Services"
        }
    ],
    "sg:phone":"+44 20 8801 9660",
    "sg:postcode":"N17 9PQ",
    "sg:province":"Greater London",
    "sg:tags":[
        "photographer",
        "photographic",
        "processor"
    ],
    "wof:name":"Seymour Colour",
    "wof:placetype":"venue"
},
  "geometry": {"coordinates":[-0.0591010004,51.5837020874],"type":"Point"}
}