{
  "type": "Feature",
  "properties": {
    "iso:country":"GB",
    "sg:address":"19 Hayfield Rd",
    "sg:city":"Minehead",
    "sg:classifiers":[
        {
            "category":"Taxi",
            "type":"Transportation"
        }
    ],
    "sg:phone":"+44 1643 703771",
    "sg:postcode":"TA24 6AB",
    "sg:province":"Somerset",
    "sg:tags":[
        "mini",
        "cab"
    ],
    "wof:name":"Alcombes Taxi",
    "wof:placetype":"venue"
},
  "geometry": {"coordinates":[-3.467862,51.199978],"type":"Point"}
}