{
  "type": "Feature",
  "properties": {
    "addr:full":"124 Cathcart Street Greenock Inverclyde PA15 1BB",
    "addr:housenumber":"124",
    "addr:postcode":"pa15 1bb",
    "addr:street":"Cathcart Street Greenock",
    "iso:country":"GB",
    "sg:address":"124 Cathcart Street",
    "sg:city":"Greenock",
    "sg:classifiers":[
        {
            "category":"Shopping",
            "subcategory":"Department Store",
            "type":"Retail Goods"
        },
        {
            "category":"Home & Garden",
            "subcategory":"Carpets & Floor Coverings",
            "type":"Retail Goods"
        }
    ],
    "sg:postcode":"PA15 1BB",
    "sg:province":"Inverclyde",
    "sg:tags":[
        "retailer",
        "rug"
    ],
    "wof:name":"Carpet World",
    "wof:placetype":"venue"
},
  "geometry": {"coordinates":[-4.7549028397,55.9470863342],"type":"Point"}
}