{
  "type": "Feature",
  "properties": {
    "iso:country":"GB",
    "sg:address":"111 Lodge La",
    "sg:city":"Liverpool",
    "sg:classifiers":[
        {
            "category":"Food & Beverages",
            "subcategory":"Meat & Fish",
            "type":"Retail Goods"
        }
    ],
    "sg:phone":"+44 151 733 7494",
    "sg:postcode":"L8 0QF",
    "sg:province":"Merseyside",
    "sg:tags":[
        "chip"
    ],
    "wof:name":"W T Man",
    "wof:placetype":"venue"
},
  "geometry": {"coordinates":[-2.9492709637,53.3941383362],"type":"Point"}
}