{
  "type": "Feature",
  "properties": {
    "addr:full":"Charles Street, Treherbert Treorchy Rhondda, Cynon, Taff CF42 5HF",
    "addr:postcode":"cf42 5hf",
    "addr:street":"Charles Street;Cynon Taff",
    "iso:country":"GB",
    "sg:address":"Charles Street, Treherbert",
    "sg:city":"Treorchy",
    "sg:classifiers":[
        {
            "category":"Education",
            "subcategory":"School",
            "type":"Public Place"
        }
    ],
    "sg:phone":"+44 1443 773540",
    "sg:postcode":"CF42 5HF",
    "sg:province":"Rhondda, Cynon, Taff",
    "sg:tags":[
        "local",
        "authority"
    ],
    "wof:name":"Penyrenglyn Infants School",
    "wof:placetype":"venue"
},
  "geometry": {"coordinates":[-3.5353739262,51.674243927],"type":"Point"}
}