{
  "type": "Feature",
  "properties": {
    "addr:full":"Ripley Road, Ambergate Belper Derbyshire DE56 2EP",
    "addr:postcode":"de56 2ep",
    "addr:street":"Ripley Road Ambergate",
    "iso:country":"GB",
    "sg:address":"Ripley Road, Ambergate",
    "sg:city":"Belper",
    "sg:classifiers":[
        {
            "category":"Freight",
            "type":"Transportation"
        }
    ],
    "sg:phone":"+44 1773 852382",
    "sg:postcode":"DE56 2EP",
    "sg:province":"Derbyshire",
    "sg:tags":[
        "haulage",
        "road"
    ],
    "wof:name":"Stanley Leonard Dean",
    "wof:placetype":"venue"
},
  "geometry": {"coordinates":[-1.4814300537,53.0598869324],"type":"Point"}
}