{
  "type": "Feature",
  "properties": {
    "addr:full":"4 Hartley Drive, Aldridge Walsall Staffordshire WS9 0RY",
    "addr:housenumber":"4",
    "addr:postcode":"ws9 0ry",
    "addr:street":"Hartley Drive",
    "iso:country":"GB",
    "sg:address":"4 Hartley Drive, Aldridge",
    "sg:city":"Walsall",
    "sg:classifiers":[
        {
            "category":"Personal",
            "type":"Services"
        }
    ],
    "sg:postcode":"WS9 0RY",
    "sg:province":"Staffordshire",
    "sg:tags":[
        "dressmaker"
    ],
    "wof:name":"Mellissa Jackson",
    "wof:placetype":"venue"
},
  "geometry": {"coordinates":[-1.9150539637,52.5958938599],"type":"Point"}
}