{
  "type": "Feature",
  "properties": {
    "addr:full":"Avalon Road Orpington Kent BR6 9BE",
    "addr:postcode":"br6 9be",
    "addr:street":"Avalon Road",
    "iso:country":"GB",
    "sg:address":"Avalon Road",
    "sg:city":"Orpington",
    "sg:classifiers":[
        {
            "category":"Social Services",
            "subcategory":"Retirement Home",
            "type":"Services"
        },
        {
            "category":"Government",
            "subcategory":"Office",
            "type":"Public Place"
        }
    ],
    "sg:phone":"+44 1689 833881",
    "sg:postcode":"BR6 9BE",
    "sg:province":"Kent",
    "sg:tags":[
        "residential",
        "central",
        "care"
    ],
    "wof:name":"Manorfields Residential Home",
    "wof:placetype":"venue"
},
  "geometry": {"coordinates":[0.1102650017,51.3719863892],"type":"Point"}
}