{
  "type": "Feature",
  "properties": {
    "iso:country":"GB",
    "sg:address":"Birk Avenue, Kendray",
    "sg:city":"Barnsley",
    "sg:classifiers":[
        {
            "category":"Bars & Pubs",
            "type":"Food & Drink"
        }
    ],
    "sg:phone":"+44 1226 297850",
    "sg:postcode":"S70 3AH",
    "sg:province":"South Yorkshire",
    "sg:tags":[
        "pubs",
        "inn"
    ],
    "wof:name":"The Kendray",
    "wof:placetype":"venue"
},
  "geometry": {"coordinates":[-1.455324,53.543381],"type":"Point"}
}