{
  "type": "Feature",
  "properties": {
    "addr:full":"Ibex House, 42-47 Minories London Greater London EC3N 1DY",
    "addr:housenumber":"42-47",
    "addr:postcode":"ec3n 1dy",
    "addr:street":"Minories",
    "iso:country":"GB",
    "sg:address":"Ibex House, 42-47 Minories",
    "sg:city":"London",
    "sg:classifiers":[
        {
            "category":"Professional",
            "subcategory":"Computer Services",
            "type":"Services"
        }
    ],
    "sg:phone":"+44 20 7680 0650",
    "sg:postcode":"EC3N 1DY",
    "sg:province":"Greater London",
    "sg:tags":[
        "system",
        "software"
    ],
    "wof:name":"Eclipse Computing Plc",
    "wof:placetype":"venue"
},
  "geometry": {"coordinates":[-0.0753540024,51.5119132996],"type":"Point"}
}