{
  "type": "Feature",
  "properties": {
    "addr:full":"30 Magdalene Street Cambridge Cambridgeshire CB3 0AF",
    "addr:housenumber":"30",
    "addr:postcode":"cb3 0af",
    "addr:street":"Magdalene Street",
    "iso:country":"GB",
    "sg:address":"30 Magdalene Street",
    "sg:city":"Cambridge",
    "sg:classifiers":[
        {
            "category":"Bars & Pubs",
            "type":"Food & Drink"
        }
    ],
    "sg:phone":"+44 1223 355068",
    "sg:postcode":"CB3 0AF",
    "sg:province":"Cambridgeshire",
    "sg:tags":[
        "pubs",
        "inn"
    ],
    "wof:name":"Pickerel Inn",
    "wof:placetype":"venue"
},
  "geometry": {"coordinates":[0.117193,52.209236],"type":"Point"}
}