{
  "type": "Feature",
  "properties": {
    "iso:country":"GB",
    "sg:address":"3a Trevethick Street",
    "sg:city":"Cardiff",
    "sg:classifiers":[
        {
            "category":"Building & Trades",
            "subcategory":"Cleaning & Sanitation",
            "type":"Services"
        }
    ],
    "sg:phone":"+44 29 2023 9544",
    "sg:postcode":"CF11 6EB",
    "sg:province":"Cardiff",
    "sg:tags":[
        "dry",
        "control",
        "damp",
        "rot"
    ],
    "wof:name":"Capital Damp-Proofing Ltd.",
    "wof:placetype":"venue"
},
  "geometry": {"coordinates":[-3.1943891048,51.4784240723],"type":"Point"}
}