{
  "type": "Feature",
  "properties": {
    "iso:country":"GB",
    "sg:address":"83 Herne Road",
    "sg:city":"Watford",
    "sg:classifiers":[
        {
            "category":"Professional",
            "subcategory":"Engineering",
            "type":"Services"
        }
    ],
    "sg:postcode":"WD23 3LP",
    "sg:province":"Hertfordshire",
    "sg:tags":[
        "contractor",
        "electrical",
        "engineer"
    ],
    "wof:name":"Steve Smith",
    "wof:placetype":"venue"
},
  "geometry": {"coordinates":[-0.3630689979,51.6443405151],"type":"Point"}
}