{
  "type": "Feature",
  "properties": {
    "iso:country":"GB",
    "sg:address":"23 Buxton Rd",
    "sg:city":"Thornton Heath",
    "sg:classifiers":[
        {
            "category":"Professional",
            "subcategory":"Lawyer & Legal Services",
            "type":"Services"
        }
    ],
    "sg:phone":"+44 20 8239 7033",
    "sg:postcode":"CR7 7HJ",
    "sg:province":"Surrey",
    "wof:name":"Immigration Consultants Services",
    "wof:placetype":"venue"
},
  "geometry": {"coordinates":[-0.108798,51.391899],"type":"Point"}
}