{
  "type": "Feature",
  "properties": {
    "iso:country":"GB",
    "sg:address":"Bulldog Works, Boars Tye Road, Silver End",
    "sg:city":"Witham",
    "sg:classifiers":[
        {
            "category":"Manufacturing",
            "subcategory":"Lumber",
            "type":"Manufacturing & Wholesale Goods"
        }
    ],
    "sg:phone":"+44 1376 584902",
    "sg:postcode":"CM8 3QE",
    "sg:province":"Essex",
    "sg:tags":[
        "importer",
        "merchants",
        "agent",
        "timber"
    ],
    "wof:name":"Nordic Timber",
    "wof:placetype":"venue"
},
  "geometry": {"coordinates":[0.625004,51.846443],"type":"Point"}
}