{
  "type": "Feature",
  "properties": {
    "iso:country":"GB",
    "sg:address":"2 St Georges Avenue",
    "sg:city":"Thornton-cleveleys",
    "sg:classifiers":[
        {
            "category":"Taxi",
            "type":"Transportation"
        },
        {
            "category":"Military Area",
            "subcategory":"Air Force Base",
            "type":"Public Place"
        }
    ],
    "sg:phone":"+44 1253 863558",
    "sg:postcode":"FY5 3NH",
    "sg:province":"Lancashire",
    "sg:tags":[
        "mini",
        "hire",
        "private",
        "cab"
    ],
    "wof:name":"Thornton Cabs",
    "wof:placetype":"venue"
},
  "geometry": {"coordinates":[-3.0386340618,53.87657547],"type":"Point"}
}