{
  "type": "Feature",
  "properties": {
    "addr:full":"16-18 London Road, Hazel Gro Stockport Cheshire SK7 4AH",
    "addr:housenumber":"16-18",
    "addr:postcode":"sk7 4ah",
    "addr:street":"London Road",
    "iso:country":"GB",
    "sg:address":"16-18 London Road, Hazel Gro",
    "sg:city":"Stockport",
    "sg:classifiers":[
        {
            "category":"Professional",
            "subcategory":"Art Services",
            "type":"Services"
        }
    ],
    "sg:phone":"+44 161 487 2362",
    "sg:postcode":"SK7 4AH",
    "sg:province":"Cheshire",
    "sg:tags":[
        "graphic",
        "designer"
    ],
    "wof:name":"Imago Design Studio",
    "wof:placetype":"venue"
},
  "geometry": {"coordinates":[-2.127103,53.384163],"type":"Point"}
}