{
  "type": "Feature",
  "properties": {
    "addr:full":"13 Riverside Studios, Amethyst Rd, Newcastle Business Pk Newcastle-upon-tyne Tyne and Wear NE4 7YL",
    "addr:housenumber":"13",
    "addr:postcode":"ne4 7yl",
    "addr:street":"Amethyst Rd Newcastle Business Pk Newcastle-Upon-Tyne",
    "iso:country":"GB",
    "sg:address":"13 Riverside Studios, Amethyst Rd, Newcastle Business Pk",
    "sg:city":"Newcastle-upon-tyne",
    "sg:classifiers":[
        {
            "category":"Shopping",
            "subcategory":"Mobile Phones",
            "type":"Retail Goods"
        }
    ],
    "sg:postcode":"NE4 7YL",
    "sg:province":"Tyne and Wear",
    "wof:name":"National Communications",
    "wof:placetype":"venue"
},
  "geometry": {"coordinates":[-1.64472,54.96133],"type":"Point"}
}