{
  "type": "Feature",
  "properties": {
    "addr:full":"Lower Halstead, Halstead Lane, Thurstonland Huddersfield West Yorkshire HD4 6XT",
    "addr:postcode":"hd4 6xt",
    "addr:street":"Lower Halstead Halstead Lane Thurstonland",
    "iso:country":"GB",
    "sg:address":"Lower Halstead, Halstead Lane, Thurstonland",
    "sg:city":"Huddersfield",
    "sg:classifiers":[
        {
            "category":"Farming",
            "subcategory":"Livestock Farm",
            "type":"Manufacturing & Wholesale Goods"
        },
        {
            "category":"Building & Trades",
            "subcategory":"Construction",
            "type":"Services"
        }
    ],
    "sg:phone":"+44 1484 661941",
    "sg:postcode":"HD4 6XT",
    "sg:province":"West Yorkshire",
    "sg:tags":[
        "others",
        "contractor"
    ],
    "wof:name":"Kenneth Hall (Builder) Ltd",
    "wof:placetype":"venue"
},
  "geometry": {"coordinates":[-1.749458,53.591061],"type":"Point"}
}