{
  "type": "Feature",
  "properties": {
    "addr:full":"Unit 1, Watch Close Coventry West Midlands CV1 3LN",
    "addr:housenumber":"unit 1",
    "addr:postcode":"cv1 3ln",
    "addr:street":"Watch Close",
    "iso:country":"GB",
    "sg:address":"Unit 1, Watch Close",
    "sg:city":"Coventry",
    "sg:classifiers":[
        {
            "category":"Communications",
            "type":"Services"
        }
    ],
    "sg:phone":"+44 24 7652 5656",
    "sg:postcode":"CV1 3LN",
    "sg:province":"West Midlands",
    "sg:tags":[
        "broadcasting"
    ],
    "wof:name":"Kix 96 Ltd.",
    "wof:placetype":"venue"
},
  "geometry": {"coordinates":[-1.5182679892,52.4086761475],"type":"Point"}
}