{
  "type": "Feature",
  "properties": {
    "iso:country":"GB",
    "sg:address":"53 Greasley Street",
    "sg:city":"Nottingham",
    "sg:classifiers":[
        {
            "category":"Fast Food",
            "type":"Food & Drink"
        }
    ],
    "sg:postcode":"NG6 8NG",
    "sg:province":"Nottinghamshire",
    "sg:tags":[
        "away",
        "take"
    ],
    "wof:name":"Grub Up",
    "wof:placetype":"venue"
},
  "geometry": {"coordinates":[-1.201173,52.999908],"type":"Point"}
}