{
  "type": "Feature",
  "properties": {
    "iso:country":"GB",
    "sg:address":"Unit 3a, Guildford Road Industrial Estate",
    "sg:city":"Hayle",
    "sg:classifiers":[
        {
            "category":"Professional",
            "subcategory":"Engineering",
            "type":"Services"
        }
    ],
    "sg:phone":"+44 1736 755010",
    "sg:postcode":"TR27 4QZ",
    "sg:province":"Cornwall",
    "wof:name":"Symons Agricultural Services Ltd.",
    "wof:placetype":"venue"
},
  "geometry": {"coordinates":[-5.400079,50.194763],"type":"Point"}
}