{
  "type": "Feature",
  "properties": {
    "addr:full":"4 Littlehesth La Berkhamsted Bedfordshire HP4 2RS",
    "addr:housenumber":"4",
    "addr:postcode":"hp4 2rs",
    "addr:street":"Littlehesth La Berkhamsted",
    "iso:country":"GB",
    "sg:address":"4 Littlehesth La",
    "sg:city":"Berkhamsted",
    "sg:classifiers":[
        {
            "category":"Professional",
            "subcategory":"Management & Consulting",
            "type":"Services"
        },
        {
            "category":"Professional",
            "subcategory":"Art Services",
            "type":"Services"
        }
    ],
    "sg:postcode":"HP4 2RS",
    "sg:province":"Bedfordshire",
    "sg:tags":[
        "consultant",
        "design",
        "marketing"
    ],
    "wof:name":"European Marketing Ltd",
    "wof:placetype":"venue"
},
  "geometry": {"coordinates":[-0.564559,51.760414],"type":"Point"}
}