{
  "type": "Feature",
  "properties": {
    "iso:country":"GB",
    "sg:address":"40 St Botolphs St",
    "sg:city":"Colchester",
    "sg:classifiers":[
        {
            "category":"Restaurant",
            "type":"Food & Drink"
        }
    ],
    "sg:phone":"+44 1206 578791",
    "sg:postcode":"CO2 7EA",
    "sg:province":"Essex",
    "sg:tags":[
        "indian"
    ],
    "wof:name":"Polash Indian Cuisine",
    "wof:placetype":"venue"
},
  "geometry": {"coordinates":[0.90363,51.887466],"type":"Point"}
}