{
  "type": "Feature",
  "properties": {
    "addr:full":"16b Hockerill St Bishop's Stortford Essex CM23 2DW",
    "addr:housenumber":"16b",
    "addr:postcode":"cm23 2dw",
    "addr:street":"Hockerill St",
    "iso:country":"GB",
    "sg:address":"16b Hockerill St",
    "sg:city":"Bishop's Stortford",
    "sg:classifiers":[
        {
            "category":"Health Services",
            "subcategory":"Health Practitioner",
            "type":"Services"
        }
    ],
    "sg:phone":"+44 1279 466099",
    "sg:postcode":"CM23 2DW",
    "sg:province":"Essex",
    "sg:tags":[
        "psychotherapist"
    ],
    "wof:name":"Stort Counselling & Psychotherapy Service",
    "wof:placetype":"venue"
},
  "geometry": {"coordinates":[0.1645530015,51.8697814941],"type":"Point"}
}