{
  "type": "Feature",
  "properties": {
    "iso:country":"GB",
    "sg:address":"7 Newham Crescent, Marton In Cleveland",
    "sg:city":"Middlesbrough",
    "sg:classifiers":[
        {
            "category":"Arena",
            "subcategory":"Sports Club",
            "type":"Entertainment"
        }
    ],
    "sg:phone":"+44 1642 321720",
    "sg:postcode":"TS7 8EY",
    "sg:province":"North Yorkshire",
    "wof:name":"The British Cycling Federation",
    "wof:placetype":"venue"
},
  "geometry": {"coordinates":[-1.202574,54.530643],"type":"Point"}
}