{
  "type": "Feature",
  "properties": {
    "iso:country":"GB",
    "sg:address":"Rear Of, 15 Lostock Road",
    "sg:city":"Manchester",
    "sg:classifiers":[
        {
            "category":"Autos & Motor Vehicles",
            "subcategory":"Automobile Sales",
            "type":"Retail Goods"
        }
    ],
    "sg:phone":"+44 161 748 8648",
    "sg:postcode":"M41 0SU",
    "sg:province":"Cheshire",
    "sg:tags":[
        "car",
        "used",
        "commercial"
    ],
    "wof:name":"D W Motors",
    "wof:placetype":"venue"
},
  "geometry": {"coordinates":[-2.3562600613,53.4580497742],"type":"Point"}
}