{
  "type": "Feature",
  "properties": {
    "iso:country":"GB",
    "sg:address":"28 Whiteley Avenue, Follaton",
    "sg:city":"Totnes",
    "sg:classifiers":[
        {
            "category":"Bus Charters",
            "type":"Transportation"
        }
    ],
    "sg:postcode":"TQ9 5FQ",
    "sg:province":"Devon",
    "sg:tags":[
        "hire",
        "coach"
    ],
    "wof:name":"Dartington & Totnes Omnibus Co",
    "wof:placetype":"venue"
},
  "geometry": {"coordinates":[-3.710655,50.434486],"type":"Point"}
}