{
  "type": "Feature",
  "properties": {
    "addr:full":"Railway Road, Adlington Chorley Lancashire PR6 9RG",
    "addr:postcode":"pr6 9rg",
    "addr:street":"Railway Road",
    "iso:country":"GB",
    "sg:address":"Railway Road, Adlington",
    "sg:city":"Chorley",
    "sg:classifiers":[
        {
            "category":"Travel",
            "subcategory":"Hotels & Motels",
            "type":"Entertainment"
        }
    ],
    "sg:phone":"+44 1257 480398",
    "sg:postcode":"PR6 9RG",
    "sg:province":"Lancashire",
    "wof:name":"Gladmar Hotel",
    "wof:placetype":"venue"
},
  "geometry": {"coordinates":[-2.6000640392,53.6155967712],"type":"Point"}
}