{
  "type": "Feature",
  "properties": {
    "addr:full":"Glasheen, 38 Welcomes Rd Kenley Surrey CR8 5HD",
    "addr:housenumber":"38",
    "addr:postcode":"cr8 5hd",
    "addr:street":"Glasheen;Welcomes Rd",
    "iso:country":"GB",
    "sg:address":"Glasheen, 38 Welcomes Rd",
    "sg:city":"Kenley",
    "sg:classifiers":[
        {
            "category":"Health Services",
            "subcategory":"Clinic",
            "type":"Services"
        }
    ],
    "sg:phone":"+44 20 8660 0200",
    "sg:postcode":"CR8 5HD",
    "sg:province":"Surrey",
    "sg:tags":[
        "aromatherapy"
    ],
    "wof:name":"Burton Mrs Jenin",
    "wof:placetype":"venue"
},
  "geometry": {"coordinates":[-0.0995149985,51.3227996826],"type":"Point"}
}