{
  "type": "Feature",
  "properties": {
    "addr:full":"Wakefield Road, Kinsley Pontefract West Yorkshire WF9 5JF",
    "addr:postcode":"wf9 5jf",
    "addr:street":"Wakefield Road;Pontefract West",
    "iso:country":"GB",
    "sg:address":"Wakefield Road, Kinsley",
    "sg:city":"Pontefract",
    "sg:classifiers":[
        {
            "category":"Organizations",
            "subcategory":"Membership Organization",
            "type":"Services"
        }
    ],
    "sg:phone":"+44 1977 610429",
    "sg:postcode":"WF9 5JF",
    "sg:province":"West Yorkshire",
    "sg:tags":[
        "club",
        "social"
    ],
    "wof:name":"The Royal British Legion",
    "wof:placetype":"venue"
},
  "geometry": {"coordinates":[-1.378049016,53.6350097656],"type":"Point"}
}