{
  "type": "Feature",
  "properties": {
    "iso:country":"GB",
    "sg:address":"Unit 5 Mitchelstone Drive, Mitchelson Industrial Estate",
    "sg:city":"Kirkcaldy",
    "sg:classifiers":[
        {
            "category":"Professional",
            "subcategory":"Engineering",
            "type":"Services"
        }
    ],
    "sg:phone":"+44 1592 650660",
    "sg:postcode":"KY1 3NA",
    "sg:province":"Fife",
    "sg:tags":[
        "precision",
        "engineer"
    ],
    "wof:name":"G S W  Mitchelston Ltd.",
    "wof:placetype":"venue"
},
  "geometry": {"coordinates":[-3.1385838985,56.1349449158],"type":"Point"}
}