{
  "type": "Feature",
  "properties": {
    "addr:full":"16 Tabernacle Road, Hanham Bristol City of Bristol BS15 8DU",
    "addr:housenumber":"16",
    "addr:postcode":"bs15 8du",
    "addr:street":"Tabernacle Road",
    "iso:country":"GB",
    "sg:address":"16 Tabernacle Road, Hanham",
    "sg:city":"Bristol",
    "sg:classifiers":[
        {
            "category":"Professional",
            "subcategory":"Engineering",
            "type":"Services"
        }
    ],
    "sg:phone":"+44 117 967 7676",
    "sg:postcode":"BS15 8DU",
    "sg:province":"City of Bristol",
    "sg:tags":[
        "contractor",
        "electrical",
        "engineer"
    ],
    "wof:name":"D Grant T W",
    "wof:placetype":"venue"
},
  "geometry": {"coordinates":[-2.518387,51.45068],"type":"Point"}
}