{
  "type": "Feature",
  "properties": {
    "addr:full":"27 Green Lanes Palmers Green Greater London N13 4TN",
    "addr:housenumber":"27",
    "addr:postcode":"n13 4tn",
    "addr:street":"Green Lanes",
    "iso:country":"GB",
    "sg:address":"27 Green Lanes",
    "sg:city":"Palmers Green",
    "sg:classifiers":[
        {
            "category":"Home & Garden",
            "subcategory":"Building Materials",
            "type":"Retail Goods"
        }
    ],
    "sg:phone":"+44 20 8365 8822",
    "sg:postcode":"N13 4TN",
    "sg:province":"Greater London",
    "sg:tags":[
        "door",
        "domestic"
    ],
    "wof:name":"Doorland",
    "wof:placetype":"venue"
},
  "geometry": {"coordinates":[-0.109579,51.61203],"type":"Point"}
}