{
  "type": "Feature",
  "properties": {
    "addr:full":"3 Temple Gardens, Temple London Greater London EC4Y 9AU",
    "addr:housenumber":"3",
    "addr:postcode":"ec4y 9au",
    "addr:street":"Temple Gardens",
    "iso:country":"GB",
    "sg:address":"3 Temple Gardens, Temple",
    "sg:city":"London",
    "sg:classifiers":[
        {
            "category":"Professional",
            "subcategory":"Lawyer & Legal Services",
            "type":"Services"
        }
    ],
    "sg:phone":"+44 20 7353 0832",
    "sg:postcode":"EC4Y 9AU",
    "sg:province":"Greater London",
    "sg:tags":[
        "barrister"
    ],
    "wof:name":"Berenice Grant",
    "wof:placetype":"venue"
},
  "geometry": {"coordinates":[-0.111221,51.51326],"type":"Point"}
}