{
  "type": "Feature",
  "properties": {
    "addr:full":"1 Dry St Basildon Essex SS16 5NG",
    "addr:housenumber":"1",
    "addr:postcode":"ss16 5ng",
    "addr:street":"Dry St",
    "iso:country":"GB",
    "sg:address":"1 Dry St",
    "sg:city":"Basildon",
    "sg:classifiers":[
        {
            "category":"Place Of Worship",
            "type":"Public Place"
        }
    ],
    "sg:phone":"+44 1268 520133",
    "sg:postcode":"SS16 5NG",
    "sg:province":"Essex",
    "wof:name":"Dry Street Memorial Church",
    "wof:placetype":"venue"
},
  "geometry": {"coordinates":[0.45618999,51.5577545166],"type":"Point"}
}