{
  "type": "Feature",
  "properties": {
    "addr:full":"20 Queensway Sudbury Essex CO10 0HG",
    "addr:housenumber":"20",
    "addr:postcode":"co10 0hg",
    "addr:street":"Queensway",
    "iso:country":"GB",
    "sg:address":"20 Queensway",
    "sg:city":"Sudbury",
    "sg:classifiers":[
        {
            "category":"Building & Trades",
            "subcategory":"Construction",
            "type":"Services"
        }
    ],
    "sg:phone":"+44 1787 372770",
    "sg:postcode":"CO10 0HG",
    "sg:province":"Essex",
    "sg:tags":[
        "builder"
    ],
    "wof:name":"Leonard John Mills",
    "wof:placetype":"venue"
},
  "geometry": {"coordinates":[0.751274,52.02948],"type":"Point"}
}