{
  "type": "Feature",
  "properties": {
    "iso:country":"GB",
    "sg:address":"Ermin Street, Baydon",
    "sg:city":"Marlborough",
    "sg:classifiers":[
        {
            "category":"Education",
            "subcategory":"School",
            "type":"Public Place"
        },
        {
            "category":"Government",
            "subcategory":"Office",
            "type":"Public Place"
        }
    ],
    "sg:phone":"+44 1672 540554",
    "sg:postcode":"SN8 2JJ",
    "sg:province":"Berkshire",
    "sg:tags":[
        "local",
        "authority"
    ],
    "wof:name":"Baydon St Nicholas C Of E Aided School",
    "wof:placetype":"venue"
},
  "geometry": {"coordinates":[-1.5963890553,51.5002861023],"type":"Point"}
}