{
  "type": "Feature",
  "properties": {
    "iso:country":"GB",
    "sg:address":"117-118 Western Rd",
    "sg:city":"Hove",
    "sg:classifiers":[
        {
            "category":"Professional",
            "subcategory":"Business Services",
            "type":"Services"
        }
    ],
    "sg:phone":"+44 1273 205317",
    "sg:postcode":"BN3 1DB",
    "sg:province":"East Sussex",
    "wof:name":"The Virtual Office",
    "wof:placetype":"venue"
},
  "geometry": {"coordinates":[-0.1572850049,50.8255195618],"type":"Point"}
}