{
  "type": "Feature",
  "properties": {
    "addr:full":"174 Roker Avenue Sunderland Tyne and Wear SR6 0HQ",
    "addr:housenumber":"174",
    "addr:postcode":"sr6 0hq",
    "addr:street":"Roker Avenue",
    "iso:country":"GB",
    "sg:address":"174 Roker Avenue",
    "sg:city":"Sunderland",
    "sg:classifiers":[
        {
            "category":"Shopping",
            "subcategory":"News",
            "type":"Retail Goods"
        }
    ],
    "sg:postcode":"SR6 0HQ",
    "sg:province":"Tyne and Wear",
    "sg:tags":[
        "newsagent"
    ],
    "wof:name":"Ben Littlewood",
    "wof:placetype":"venue"
},
  "geometry": {"coordinates":[-1.3770819902,54.9159355164],"type":"Point"}
}