{
  "type": "Feature",
  "properties": {
    "addr:full":"Westfield, Holbeach St Johns Spalding Cambridgeshire PE12 8RD",
    "addr:postcode":"pe12 8rd",
    "addr:street":"Holbeach St;Spalding",
    "iso:country":"GB",
    "sg:address":"Westfield, Holbeach St Johns",
    "sg:city":"Spalding",
    "sg:classifiers":[
        {
            "category":"Farming",
            "subcategory":"Livestock Farm",
            "type":"Manufacturing & Wholesale Goods"
        }
    ],
    "sg:phone":"+44 1406 540336",
    "sg:postcode":"PE12 8RD",
    "sg:province":"Cambridgeshire",
    "sg:tags":[
        "others"
    ],
    "wof:name":"J D Mawby & Sons Ltd.",
    "wof:placetype":"venue"
},
  "geometry": {"coordinates":[-0.00226,52.7538490295],"type":"Point"}
}