{
  "type": "Feature",
  "properties": {
    "addr:full":"Hatters Lane High Wycombe Buckinghamshire HP13 7LY",
    "addr:postcode":"hp13 7ly",
    "addr:street":"Hatters Lane",
    "iso:country":"GB",
    "sg:address":"Hatters Lane",
    "sg:city":"High Wycombe",
    "sg:classifiers":[
        {
            "category":"Bars & Pubs",
            "type":"Food & Drink"
        },
        {
            "category":"Community Center",
            "subcategory":"Social",
            "type":"Public Place"
        }
    ],
    "sg:phone":"+44 1494 442776",
    "sg:postcode":"HP13 7LY",
    "sg:province":"Buckinghamshire",
    "sg:tags":[
        "pubs",
        "house",
        "inn",
        "activity"
    ],
    "wof:name":"The Golden Fleece",
    "wof:placetype":"venue"
},
  "geometry": {"coordinates":[-0.723739028,51.6352157593],"type":"Point"}
}