{
  "type": "Feature",
  "properties": {
    "addr:full":"11 Longfellow Road, Burntwood Walsall Staffordshire WS7 8EY",
    "addr:housenumber":"11",
    "addr:postcode":"ws7 8ey",
    "addr:street":"Longfellow Road",
    "iso:country":"GB",
    "sg:address":"11 Longfellow Road, Burntwood",
    "sg:city":"Walsall",
    "sg:classifiers":[
        {
            "category":"Health Services",
            "subcategory":"Doctor",
            "type":"Services"
        }
    ],
    "sg:phone":"+44 1543 674503",
    "sg:postcode":"WS7 8EY",
    "sg:province":"Staffordshire",
    "sg:tags":[
        "practitioners"
    ],
    "wof:name":"M S Ahmad",
    "wof:placetype":"venue"
},
  "geometry": {"coordinates":[-1.926844,52.690281],"type":"Point"}
}