{
  "type": "Feature",
  "properties": {
    "addr:full":"4b Parchmore Road Thornton Heath Surrey CR7 8LU",
    "addr:housenumber":"4b",
    "addr:postcode":"cr7 8lu",
    "addr:street":"Parchmore Road",
    "iso:country":"GB",
    "sg:address":"4b Parchmore Road",
    "sg:city":"Thornton Heath",
    "sg:classifiers":[
        {
            "category":"Shopping",
            "type":"Retail Goods"
        }
    ],
    "sg:postcode":"CR7 8LU",
    "sg:province":"Surrey",
    "sg:tags":[
        "shop",
        "new age"
    ],
    "wof:name":"Rainbow Moon",
    "wof:placetype":"venue"
},
  "geometry": {"coordinates":[-0.0989670008,51.3997421265],"type":"Point"}
}