{
  "type": "Feature",
  "properties": {
    "addr:full":"Little Common Lane Rotherham South Yorkshire S60 1QR",
    "addr:postcode":"s60 1qr",
    "addr:street":"Little Common Lane",
    "iso:country":"GB",
    "sg:address":"Little Common Lane",
    "sg:city":"Rotherham",
    "sg:classifiers":[
        {
            "category":"Education",
            "subcategory":"School",
            "type":"Public Place"
        },
        {
            "category":"Government",
            "subcategory":"Office",
            "type":"Public Place"
        }
    ],
    "sg:phone":"+44 1709 740288",
    "sg:postcode":"S60 1QR",
    "sg:province":"South Yorkshire",
    "sg:tags":[
        "local",
        "authority"
    ],
    "wof:name":"Old Hall Comprehensive School",
    "wof:placetype":"venue"
},
  "geometry": {"coordinates":[-1.3010890484,53.4063224792],"type":"Point"}
}