{
  "type": "Feature",
  "properties": {
    "addr:full":"1281 Bristol Rd South Birmingham West Midlands B31 2SP",
    "addr:housenumber":"1281",
    "addr:postcode":"b31 2sp",
    "addr:street":"Bristol Rd",
    "iso:country":"GB",
    "sg:address":"1281 Bristol Rd South",
    "sg:city":"Birmingham",
    "sg:classifiers":[
        {
            "category":"Food & Beverages",
            "subcategory":"Fruits & Vegetables",
            "type":"Retail Goods"
        }
    ],
    "sg:postcode":"B31 2SP",
    "sg:province":"West Midlands",
    "sg:tags":[
        "greengrocer"
    ],
    "wof:name":"Powell,Susan,",
    "wof:placetype":"venue"
},
  "geometry": {"coordinates":[-1.982691,52.401676],"type":"Point"}
}