{
  "type": "Feature",
  "properties": {
    "iso:country":"GB",
    "sg:address":"Unit 15 Stapleton House, 110 Clifton Street",
    "sg:city":"London",
    "sg:classifiers":[
        {
            "category":"Communications",
            "subcategory":"Newspaper",
            "type":"Services"
        }
    ],
    "sg:phone":"+44 20 7729 6644",
    "sg:postcode":"EC2A 4HD",
    "sg:province":"Greater London",
    "sg:tags":[
        "magazine"
    ],
    "wof:name":"Mitre House Publishing Ltd.",
    "wof:placetype":"venue"
},
  "geometry": {"coordinates":[-0.082807,51.523567],"type":"Point"}
}