{
  "type": "Feature",
  "properties": {
    "iso:country":"GB",
    "sg:address":"Unit 7, Owling Ourt Nd St, Bowling Back Lane",
    "sg:city":"Bradford",
    "sg:classifiers":[
        {
            "category":"Professional",
            "subcategory":"Engineering",
            "type":"Services"
        }
    ],
    "sg:phone":"+44 1274 730340",
    "sg:postcode":"BD4 8TT",
    "sg:province":"West Yorkshire",
    "wof:name":"Parker Engineering & Transmissions",
    "wof:placetype":"venue"
},
  "geometry": {"coordinates":[-1.72509,53.787281],"type":"Point"}
}