{
  "type": "Feature",
  "properties": {
    "addr:full":"257 Liverpool Road, Penwortham Preston Lancashire PR1 0NA",
    "addr:housenumber":"257",
    "addr:postcode":"pr1 0na",
    "addr:street":"Liverpool Road",
    "iso:country":"GB",
    "sg:address":"257 Liverpool Road, Penwortham",
    "sg:city":"Preston",
    "sg:classifiers":[
        {
            "category":"Professional",
            "subcategory":"Accounting & Tax Preparation",
            "type":"Services"
        }
    ],
    "sg:postcode":"PR1 0NA",
    "sg:province":"Lancashire",
    "sg:tags":[
        "consultant"
    ],
    "wof:name":"Havenham Tax Services",
    "wof:placetype":"venue"
},
  "geometry": {"coordinates":[-2.746662,53.741947],"type":"Point"}
}