{
  "type": "Feature",
  "properties": {
    "addr:full":"7b Randolph Place Edinburgh City of Edinburgh EH3 7TE",
    "addr:housenumber":"7b",
    "addr:postcode":"eh3 7te",
    "addr:street":"Randolph Place Edinburgh",
    "iso:country":"GB",
    "sg:address":"7b Randolph Place",
    "sg:city":"Edinburgh",
    "sg:classifiers":[
        {
            "category":"Bars & Pubs",
            "type":"Food & Drink"
        }
    ],
    "sg:phone":"+44 131 539 8100",
    "sg:postcode":"EH3 7TE",
    "sg:province":"City of Edinburgh",
    "sg:tags":[
        "pubs",
        "inn"
    ],
    "wof:name":"Roy & Alan West & Co.",
    "wof:placetype":"venue"
},
  "geometry": {"coordinates":[-3.210224,55.952171],"type":"Point"}
}