{
  "type": "Feature",
  "properties": {
    "addr:full":"Greenfield Llandovery Carmarthenshire SA20 0YP",
    "addr:postcode":"sa20 0yp",
    "iso:country":"GB",
    "sg:address":"Greenfield",
    "sg:city":"Llandovery",
    "sg:classifiers":[
        {
            "category":"Building & Trades",
            "subcategory":"Landscaping Services",
            "type":"Services"
        }
    ],
    "sg:phone":"+44 1550 720419",
    "sg:postcode":"SA20 0YP",
    "sg:province":"Carmarthenshire",
    "sg:tags":[
        "forestry",
        "tree"
    ],
    "wof:name":"C T & J M Moore",
    "wof:placetype":"venue"
},
  "geometry": {"coordinates":[-3.7893269062,52.0079956055],"type":"Point"}
}