{
  "type": "Feature",
  "properties": {
    "addr:full":"Medtia House, Brunswick Street Oldham Lancashire OL1 1BU",
    "addr:postcode":"ol1 1bu",
    "addr:street":"Brunswick Street",
    "iso:country":"GB",
    "sg:address":"Medtia House, Brunswick Street",
    "sg:city":"Oldham",
    "sg:classifiers":[
        {
            "category":"Organizations",
            "subcategory":"Community Association",
            "type":"Services"
        }
    ],
    "sg:phone":"+44 161 620 2992",
    "sg:postcode":"OL1 1BU",
    "sg:province":"Lancashire",
    "sg:tags":[
        "society",
        "housing"
    ],
    "wof:name":"Aksa Housing Association Ltd.",
    "wof:placetype":"venue"
},
  "geometry": {"coordinates":[-2.115019,53.539566],"type":"Point"}
}