{
  "type": "Feature",
  "properties": {
    "addr:full":"Bell Close, Newnham Industrial Estate, Plympton Plymouth Devon PL7 4JH",
    "addr:postcode":"pl7 4jh",
    "addr:street":"Bell Close;Industrial Estate",
    "iso:country":"GB",
    "sg:address":"Bell Close, Newnham Industrial Estate, Plympton",
    "sg:city":"Plymouth",
    "sg:classifiers":[
        {
            "category":"Manufacturing",
            "subcategory":"Rubber & Plastics",
            "type":"Manufacturing & Wholesale Goods"
        }
    ],
    "sg:phone":"+44 1752 340029",
    "sg:postcode":"PL7 4JH",
    "sg:province":"Devon",
    "sg:tags":[
        "supplier",
        "stockist"
    ],
    "wof:name":"Canusa Systems Ltd.",
    "wof:placetype":"venue"
},
  "geometry": {"coordinates":[-4.0436348915,50.3950538635],"type":"Point"}
}