{
  "type": "Feature",
  "properties": {
    "addr:full":"509a West Derby Rd Liverpool Merseyside L6 4BW",
    "addr:housenumber":"509a",
    "addr:postcode":"l6 4bw",
    "addr:street":"West Derby Rd",
    "iso:country":"GB",
    "sg:address":"509a West Derby Rd",
    "sg:city":"Liverpool",
    "sg:classifiers":[
        {
            "category":"Professional",
            "type":"Services"
        }
    ],
    "sg:phone":"+44 151 233 1413",
    "sg:postcode":"L6 4BW",
    "sg:province":"Merseyside",
    "sg:tags":[
        "caterer"
    ],
    "wof:name":"Kayandis Kitchen",
    "wof:placetype":"venue"
},
  "geometry": {"coordinates":[-2.935526,53.424129],"type":"Point"}
}