{
  "type": "Feature",
  "properties": {
    "iso:country":"GB",
    "sg:address":"Mill Lane, South Elmsall",
    "sg:city":"Pontefract",
    "sg:classifiers":[
        {
            "category":"Organizations",
            "subcategory":"Membership Organization",
            "type":"Services"
        }
    ],
    "sg:phone":"+44 1977 648953",
    "sg:postcode":"WF9 2DS",
    "sg:province":"West Yorkshire",
    "sg:tags":[
        "club"
    ],
    "wof:name":"Rutherford Inns Ltd.",
    "wof:placetype":"venue"
},
  "geometry": {"coordinates":[-1.281007,53.598312],"type":"Point"}
}