{
  "type": "Feature",
  "properties": {
    "addr:full":"Main Road, West Kingsdown Sevenoaks Kent TN15 6EU",
    "addr:postcode":"tn15 6eu",
    "addr:street":"Main Road West",
    "iso:country":"GB",
    "sg:address":"Main Road, West Kingsdown",
    "sg:city":"Sevenoaks",
    "sg:classifiers":[
        {
            "category":"Shopping",
            "type":"Retail Goods"
        }
    ],
    "sg:phone":"+44 1474 853258",
    "sg:postcode":"TN15 6EU",
    "sg:province":"Kent",
    "sg:tags":[
        "part",
        "accessory"
    ],
    "wof:name":"Formula One Brands Hatch Ltd.",
    "wof:placetype":"venue"
},
  "geometry": {"coordinates":[0.25206,51.352001],"type":"Point"}
}