{
  "type": "Feature",
  "properties": {
    "addr:full":"291 Alcester Road South Birmingham West Midlands B14 6EB",
    "addr:housenumber":"291",
    "addr:postcode":"b14 6eb",
    "addr:street":"Alcester Road South",
    "iso:country":"GB",
    "sg:address":"291 Alcester Road South",
    "sg:city":"Birmingham",
    "sg:classifiers":[
        {
            "category":"Autos & Motor Vehicles",
            "subcategory":"Recreational Vehicle Sales",
            "type":"Retail Goods"
        }
    ],
    "sg:postcode":"B14 6EB",
    "sg:province":"West Midlands",
    "sg:tags":[
        "caravans",
        "motorhomes",
        "trailer"
    ],
    "wof:name":"Florida Motor Caravan Conversions",
    "wof:placetype":"venue"
},
  "geometry": {"coordinates":[-1.891475,52.42078],"type":"Point"}
}