{
  "type": "Feature",
  "properties": {
    "addr:full":"17 Green St Cambridge Cambridgeshire CB2 3JU",
    "addr:housenumber":"17",
    "addr:postcode":"cb2 3ju",
    "addr:street":"Green St",
    "iso:country":"GB",
    "sg:address":"17 Green St",
    "sg:city":"Cambridge",
    "sg:classifiers":[
        {
            "category":"Shopping",
            "subcategory":"Crafts & Fabrics",
            "type":"Retail Goods"
        }
    ],
    "sg:phone":"+44 1223 351610",
    "sg:postcode":"CB2 3JU",
    "sg:province":"Cambridgeshire",
    "sg:tags":[
        "material",
        "art"
    ],
    "wof:name":"Stencil Store",
    "wof:placetype":"venue"
},
  "geometry": {"coordinates":[0.1187589988,52.2066802979],"type":"Point"}
}