{
  "type": "Feature",
  "properties": {
    "addr:full":"229a Hyde End Road, Spencers Wood Reading Berkshire RG7 1BU",
    "addr:housenumber":"229a",
    "addr:postcode":"rg7 1bu",
    "addr:street":"Hyde End Road Spencers Wood",
    "iso:country":"GB",
    "sg:address":"229a Hyde End Road, Spencers Wood",
    "sg:city":"Reading",
    "sg:classifiers":[
        {
            "category":"Professional",
            "subcategory":"Engineering",
            "type":"Services"
        }
    ],
    "sg:phone":"+44 118 988 2292",
    "sg:postcode":"RG7 1BU",
    "sg:province":"Berkshire",
    "sg:tags":[
        "civil",
        "engineer"
    ],
    "wof:name":"County Contractors (U K) Ltd.",
    "wof:placetype":"venue"
},
  "geometry": {"coordinates":[-0.962181,51.393181],"type":"Point"}
}