{
  "type": "Feature",
  "properties": {
    "iso:country":"GB",
    "sg:address":"112-114 North Street, Bedminster",
    "sg:city":"Bristol",
    "sg:classifiers":[
        {
            "category":"Building & Trades",
            "subcategory":"Construction",
            "type":"Services"
        }
    ],
    "sg:phone":"+44 117 963 2637",
    "sg:postcode":"BS3 1HF",
    "sg:province":"City of Bristol",
    "sg:tags":[
        "glazier"
    ],
    "wof:name":"Petrie Glazing",
    "wof:placetype":"venue"
},
  "geometry": {"coordinates":[-2.607162,51.440216],"type":"Point"}
}