{
  "type": "Feature",
  "properties": {
    "addr:full":"48 Chapel Street Southport Lancashire PR8 1BZ",
    "addr:housenumber":"48",
    "addr:postcode":"pr8 1bz",
    "addr:street":"Chapel Street",
    "iso:country":"GB",
    "sg:address":"48 Chapel Street",
    "sg:city":"Southport",
    "sg:classifiers":[
        {
            "category":"Shopping",
            "subcategory":"Shoes",
            "type":"Retail Goods"
        }
    ],
    "sg:phone":"+44 1704 530542",
    "sg:postcode":"PR8 1BZ",
    "sg:province":"Lancashire",
    "sg:tags":[
        "shop",
        "retailer",
        "footwear"
    ],
    "sg:website":"http://www.clarks.co.uk",
    "wof:name":"Clarks Shoes Ltd",
    "wof:placetype":"venue"
},
  "geometry": {"coordinates":[-3.003741,53.647152],"type":"Point"}
}