{
  "type": "Feature",
  "properties": {
    "iso:country":"GB",
    "sg:address":"17 Blossom Street",
    "sg:city":"London",
    "sg:classifiers":[
        {
            "category":"Professional",
            "subcategory":"Accounting & Tax Preparation",
            "type":"Services"
        }
    ],
    "sg:postcode":"E1 6PL",
    "sg:province":"Greater London",
    "sg:tags":[
        "accountant"
    ],
    "wof:name":"Austins",
    "wof:placetype":"venue"
},
  "geometry": {"coordinates":[-0.0779159963,51.5211486816],"type":"Point"}
}