{
  "type": "Feature",
  "properties": {
    "iso:country":"GB",
    "sg:address":"145 Chester Road, Greenbank",
    "sg:city":"Northwich",
    "sg:classifiers":[
        {
            "category":"Freight",
            "type":"Transportation"
        }
    ],
    "sg:phone":"+44 1606 782968",
    "sg:postcode":"CW8 4AD",
    "sg:province":"Cheshire",
    "sg:tags":[
        "haulage",
        "road"
    ],
    "wof:name":"Grays Transport",
    "wof:placetype":"venue"
},
  "geometry": {"coordinates":[-2.529056,53.253925],"type":"Point"}
}