{
  "type": "Feature",
  "properties": {
    "addr:full":"7 Raleigh Road, Stoke Coventry Warwickshire CV2 4AA",
    "addr:housenumber":"7",
    "addr:postcode":"cv2 4aa",
    "addr:street":"Raleigh Road",
    "iso:country":"GB",
    "sg:address":"7 Raleigh Road, Stoke",
    "sg:city":"Coventry",
    "sg:classifiers":[
        {
            "category":"Building & Trades",
            "subcategory":"Construction",
            "type":"Services"
        }
    ],
    "sg:postcode":"CV2 4AA",
    "sg:province":"Warwickshire",
    "sg:tags":[
        "decorator",
        "painter"
    ],
    "wof:name":"Jane Harrison Painting & Decorating Services",
    "wof:placetype":"venue"
},
  "geometry": {"coordinates":[-1.474069,52.407333],"type":"Point"}
}