{
  "type": "Feature",
  "properties": {
    "addr:full":"28 Kennard Clo Glastonbury Somerset BA6 8ET",
    "addr:housenumber":"28",
    "addr:postcode":"ba6 8et",
    "addr:street":"Kennard Clo",
    "iso:country":"GB",
    "sg:address":"28 Kennard Clo",
    "sg:city":"Glastonbury",
    "sg:classifiers":[
        {
            "category":"Professional",
            "type":"Services"
        }
    ],
    "sg:phone":"+44 1458 835418",
    "sg:postcode":"BA6 8ET",
    "sg:province":"Somerset",
    "sg:tags":[
        "entertainer"
    ],
    "wof:name":"Williamson Puppets",
    "wof:placetype":"venue"
},
  "geometry": {"coordinates":[-2.708773,51.142441],"type":"Point"}
}