{
  "type": "Feature",
  "properties": {
    "iso:country":"GB",
    "sg:address":"Dickinson Street",
    "sg:city":"Oldham",
    "sg:classifiers":[
        {
            "category":"Autos & Motor Vehicles",
            "subcategory":"Auto Supplies",
            "type":"Retail Goods"
        }
    ],
    "sg:phone":"+44 161 652 3129",
    "sg:postcode":"OL4 1HD",
    "sg:province":"Lancashire",
    "sg:tags":[
        "component"
    ],
    "wof:name":"Brown Bros",
    "wof:placetype":"venue"
},
  "geometry": {"coordinates":[-2.0949890614,53.5437164307],"type":"Point"}
}