{
  "type": "Feature",
  "properties": {
    "iso:country":"GB",
    "sg:address":"Chipperfield Home Center, Tower Hill, Chipperfield",
    "sg:city":"King's Langley",
    "sg:classifiers":[
        {
            "category":"Home & Garden",
            "subcategory":"Home Furnishings",
            "type":"Retail Goods"
        }
    ],
    "sg:phone":"+44 1442 832981",
    "sg:postcode":"WD4 9LH",
    "sg:province":"Hertfordshire",
    "sg:tags":[
        "awning",
        "canopy",
        "blinds"
    ],
    "wof:name":"Window Dressings",
    "wof:placetype":"venue"
},
  "geometry": {"coordinates":[-0.50536,51.713032],"type":"Point"}
}