{
  "type": "Feature",
  "properties": {
    "addr:full":"171 Junction Road London Greater London N19 5PZ",
    "addr:housenumber":"171",
    "addr:postcode":"n19 5pz",
    "addr:street":"Junction Road",
    "iso:country":"GB",
    "sg:address":"171 Junction Road",
    "sg:city":"London",
    "sg:classifiers":[
        {
            "category":"Manufacturing",
            "subcategory":"Furniture",
            "type":"Manufacturing & Wholesale Goods"
        }
    ],
    "sg:phone":"+44 20 7272 1613",
    "sg:postcode":"N19 5PZ",
    "sg:province":"Greater London",
    "sg:tags":[
        "designer",
        "design"
    ],
    "wof:name":"Lime Design",
    "wof:placetype":"venue"
},
  "geometry": {"coordinates":[-0.1370929927,51.560546875],"type":"Point"}
}