{
  "type": "Feature",
  "properties": {
    "addr:full":"1 Florence Place, Newlyn Penzance Cornwall TR18 5PT",
    "addr:housenumber":"1",
    "addr:postcode":"tr18 5pt",
    "addr:street":"Florence Place",
    "iso:country":"GB",
    "sg:address":"1 Florence Place, Newlyn",
    "sg:city":"Penzance",
    "sg:classifiers":[
        {
            "category":"Ice Cream",
            "type":"Food & Drink"
        }
    ],
    "sg:postcode":"TR18 5PT",
    "sg:province":"Cornwall",
    "sg:tags":[
        "shop",
        "mobile",
        "parlour"
    ],
    "wof:name":"G M Webb",
    "wof:placetype":"venue"
},
  "geometry": {"coordinates":[-5.549429,50.106915],"type":"Point"}
}