{
  "type": "Feature",
  "properties": {
    "addr:full":"Barrow Ho, Fife St Sheffield South Yorkshire S9 1NN",
    "addr:postcode":"s9 1nn",
    "addr:street":"St",
    "iso:country":"GB",
    "sg:address":"Barrow Ho, Fife St",
    "sg:city":"Sheffield",
    "sg:classifiers":[
        {
            "category":"Food & Beverages",
            "subcategory":"Meat & Fish",
            "type":"Retail Goods"
        }
    ],
    "sg:postcode":"S9 1NN",
    "sg:province":"South Yorkshire",
    "sg:tags":[
        "butcher"
    ],
    "wof:name":"Wigglesworth,Peter,",
    "wof:placetype":"venue"
},
  "geometry": {"coordinates":[-1.4172040224,53.4219551086],"type":"Point"}
}