{
  "type": "Feature",
  "properties": {
    "iso:country":"GB",
    "sg:address":"Unit 8a Steps Indstl Pk, Magdale, Honley",
    "sg:city":"Holmfirth",
    "sg:classifiers":[
        {
            "category":"Bus Charters",
            "type":"Transportation"
        }
    ],
    "sg:postcode":"HD9 6RA",
    "sg:province":"South Yorkshire",
    "sg:tags":[
        "coach"
    ],
    "wof:name":"Stothart,Paul,",
    "wof:placetype":"venue"
},
  "geometry": {"coordinates":[-1.786623,53.601898],"type":"Point"}
}