{
  "type": "Feature",
  "properties": {
    "iso:country":"GB",
    "sg:address":"41 Victoria Road",
    "sg:city":"Southampton",
    "sg:classifiers":[
        {
            "category":"Shopping",
            "subcategory":"Thrift Store",
            "type":"Retail Goods"
        }
    ],
    "sg:postcode":"SO19 9DY",
    "sg:province":"Hampshire",
    "sg:tags":[
        "shop",
        "charity"
    ],
    "wof:name":"C R Y Charity Shop",
    "wof:placetype":"venue"
},
  "geometry": {"coordinates":[-1.379902,50.896667],"type":"Point"}
}