{
  "type": "Feature",
  "properties": {
    "iso:country":"GB",
    "sg:address":"The Angles, Southend Rd, Great Wakering",
    "sg:city":"Southend On Sea",
    "sg:classifiers":[
        {
            "category":"Building & Trades",
            "subcategory":"Construction",
            "type":"Services"
        }
    ],
    "sg:phone":"+44 1702 219384",
    "sg:postcode":"SS3 0PF",
    "sg:province":"Essex",
    "sg:tags":[
        "builder"
    ],
    "wof:name":"H.F Cook & Son",
    "wof:placetype":"venue"
},
  "geometry": {"coordinates":[0.799884975,51.5531959534],"type":"Point"}
}