{
  "type": "Feature",
  "properties": {
    "addr:full":"Carr St Ashton Under Lyne Greater Manchester OL6 8ES",
    "addr:postcode":"ol6 8es",
    "addr:street":"Carr St;Under Lyne",
    "iso:country":"GB",
    "sg:address":"Carr St",
    "sg:city":"Ashton Under Lyne",
    "sg:classifiers":[
        {
            "category":"Organizations",
            "subcategory":"Membership Organization",
            "type":"Services"
        }
    ],
    "sg:phone":"+44 161 330 7549",
    "sg:postcode":"OL6 8ES",
    "sg:province":"Greater Manchester",
    "sg:tags":[
        "club"
    ],
    "wof:name":"Ashton Bridge Club",
    "wof:placetype":"venue"
},
  "geometry": {"coordinates":[-2.079424,53.499657],"type":"Point"}
}