{
  "type": "Feature",
  "properties": {
    "iso:country":"GB",
    "sg:address":"5-11 Desford Road",
    "sg:city":"Leicester",
    "sg:classifiers":[
        {
            "category":"Retail",
            "subcategory":"Auto Repair",
            "type":"Services"
        }
    ],
    "sg:postcode":"LE9 9LG",
    "sg:province":"Leicestershire",
    "sg:tags":[
        "modification",
        "garage"
    ],
    "wof:name":"Verdon Garage",
    "wof:placetype":"venue"
},
  "geometry": {"coordinates":[-1.3335770369,52.6305122375],"type":"Point"}
}