{
  "type": "Feature",
  "properties": {
    "addr:full":"1b Finkle Court Finkle Street, Thorne Doncaster East Riding of Yorkshire DN8 5TW",
    "addr:housenumber":"1b",
    "addr:postcode":"dn8 5tw",
    "addr:street":"Finkle Court Finkle Street;Riding",
    "iso:country":"GB",
    "sg:address":"1b Finkle Court Finkle Street, Thorne",
    "sg:city":"Doncaster",
    "sg:classifiers":[
        {
            "category":"Building & Trades",
            "subcategory":"Cleaning & Sanitation",
            "type":"Services"
        }
    ],
    "sg:postcode":"DN8 5TW",
    "sg:province":"East Riding of Yorkshire",
    "sg:tags":[
        "asbestos",
        "removal"
    ],
    "wof:name":"Environmental Contamination Services Ltd.",
    "wof:placetype":"venue"
},
  "geometry": {"coordinates":[-0.9628440142,53.6110534668],"type":"Point"}
}