{
  "type": "Feature",
  "properties": {
    "addr:full":"Beck Farm, Trunch Hill, Denton Harleston Norfolk IP20 0AE",
    "addr:postcode":"ip20 0ae",
    "addr:street":"Trunch Hill",
    "iso:country":"GB",
    "sg:address":"Beck Farm, Trunch Hill, Denton",
    "sg:city":"Harleston",
    "sg:classifiers":[
        {
            "category":"Professional",
            "subcategory":"Printing & Photocopies",
            "type":"Services"
        }
    ],
    "sg:postcode":"IP20 0AE",
    "sg:province":"Norfolk",
    "sg:tags":[
        "trophy"
    ],
    "wof:name":"Hillview Rosettes",
    "wof:placetype":"venue"
},
  "geometry": {"coordinates":[1.35297,52.445759],"type":"Point"}
}