{
  "type": "Feature",
  "properties": {
    "addr:full":"Barlby Rd Ladbroke Grove Greater London W10 6BH",
    "addr:postcode":"w10 6bh",
    "addr:street":"Barlby Rd",
    "iso:country":"GB",
    "sg:address":"Barlby Rd",
    "sg:city":"Ladbroke Grove",
    "sg:classifiers":[
        {
            "category":"Government",
            "subcategory":"Office",
            "type":"Public Place"
        }
    ],
    "sg:phone":"+44 20 8964 2684",
    "sg:postcode":"W10 6BH",
    "sg:province":"Greater London",
    "sg:tags":[
        "education",
        "agency",
        "authority"
    ],
    "wof:name":"The Making Place",
    "wof:placetype":"venue"
},
  "geometry": {"coordinates":[-0.2173040062,51.5237312317],"type":"Point"}
}