{
  "type": "Feature",
  "properties": {
    "addr:full":"Farm Road Maidenhead Berkshire SL6 5JB",
    "addr:postcode":"sl6 5jb",
    "addr:street":"Farm Road",
    "iso:country":"GB",
    "sg:address":"Farm Road",
    "sg:city":"Maidenhead",
    "sg:classifiers":[
        {
            "category":"Education",
            "subcategory":"School",
            "type":"Public Place"
        }
    ],
    "sg:phone":"+44 1628 625068",
    "sg:postcode":"SL6 5JB",
    "sg:province":"Berkshire",
    "sg:tags":[
        "local",
        "authority"
    ],
    "wof:name":"Newlands Girls School",
    "wof:placetype":"venue"
},
  "geometry": {"coordinates":[-0.7612689734,51.5250434875],"type":"Point"}
}