{
  "type": "Feature",
  "properties": {
    "iso:country":"GB",
    "sg:address":"28-32 Greenwood Street",
    "sg:city":"Altrincham",
    "sg:classifiers":[
        {
            "category":"Social Services",
            "subcategory":"Child Care",
            "type":"Services"
        }
    ],
    "sg:phone":"+44 161 928 0225",
    "sg:postcode":"WA14 1RZ",
    "sg:province":"Cheshire",
    "sg:tags":[
        "agency",
        "nanny"
    ],
    "wof:name":"Network 0 to 5",
    "wof:placetype":"venue"
},
  "geometry": {"coordinates":[-2.352319,53.386528],"type":"Point"}
}