{
  "type": "Feature",
  "properties": {
    "iso:country":"GB",
    "sg:address":"Crabtree Ho, Crabtree Hill, Collingham",
    "sg:city":"Wetherby",
    "sg:classifiers":[
        {
            "category":"Building & Trades",
            "subcategory":"Electrical",
            "type":"Services"
        }
    ],
    "sg:postcode":"LS22 5AD",
    "sg:province":"North Yorkshire",
    "sg:tags":[
        "lighting"
    ],
    "wof:name":"Hickling,Michael,",
    "wof:placetype":"venue"
},
  "geometry": {"coordinates":[-1.414314,53.90572],"type":"Point"}
}