{
  "type": "Feature",
  "properties": {
    "addr:full":"Twickenham Road Birmingham West Midlands B44 0NS",
    "addr:postcode":"b44 0ns",
    "addr:street":"Twickenham Road",
    "iso:country":"GB",
    "sg:address":"Twickenham Road",
    "sg:city":"Birmingham",
    "sg:classifiers":[
        {
            "category":"Professional",
            "type":"Services"
        }
    ],
    "sg:phone":"+44 121 321 1990",
    "sg:postcode":"B44 0NS",
    "sg:province":"West Midlands",
    "sg:tags":[
        "entertainer"
    ],
    "wof:name":"Razzle Dazzle Entertainments",
    "wof:placetype":"venue"
},
  "geometry": {"coordinates":[-1.8643039465,52.5437583923],"type":"Point"}
}