{
  "type": "Feature",
  "properties": {
    "iso:country":"GB",
    "sg:address":"Ryefield Road",
    "sg:city":"Ross-on-wye",
    "sg:classifiers":[
        {
            "category":"Travel",
            "subcategory":"Hotels & Motels",
            "type":"Entertainment"
        }
    ],
    "sg:phone":"+44 1989 563880",
    "sg:postcode":"HR9 5LS",
    "sg:province":"Gloucestershire",
    "sg:tags":[
        "house",
        "guest"
    ],
    "wof:name":"Sunnymount Hotel",
    "wof:placetype":"venue"
},
  "geometry": {"coordinates":[-2.574733,51.91552],"type":"Point"}
}