{
  "type": "Feature",
  "properties": {
    "addr:full":"Unit 91 Upr Level, The Exchange Ilford Essex IG1 1AT",
    "addr:housenumber":"unit 91 upr level",
    "addr:postcode":"ig1 1at",
    "addr:street":"The Exchange",
    "iso:country":"GB",
    "sg:address":"Unit 91 Upr Level, The Exchange",
    "sg:city":"Ilford",
    "sg:classifiers":[
        {
            "category":"Shopping",
            "subcategory":"Clothing, Apparel, & Fashions",
            "type":"Retail Goods"
        }
    ],
    "sg:postcode":"IG1 1AT",
    "sg:province":"Essex",
    "sg:tags":[
        "menswear"
    ],
    "wof:name":"Khan,A R,",
    "wof:placetype":"venue"
},
  "geometry": {"coordinates":[0.0671150014,51.5637512207],"type":"Point"}
}