{
  "type": "Feature",
  "properties": {
    "iso:country":"GB",
    "sg:address":"7-25 New Hall Street",
    "sg:city":"Stoke-on-trent",
    "sg:classifiers":[
        {
            "category":"Home & Garden",
            "subcategory":"Carpets & Floor Coverings",
            "type":"Retail Goods"
        }
    ],
    "sg:phone":"+44 1782 273534",
    "sg:postcode":"ST1 5HQ",
    "sg:province":"Staffordshire",
    "sg:tags":[
        "carpets",
        "rug",
        "matting"
    ],
    "wof:name":"C A Furnishing Ltd.",
    "wof:placetype":"venue"
},
  "geometry": {"coordinates":[-2.1779620647,53.0270462036],"type":"Point"}
}