{
  "type": "Feature",
  "properties": {
    "addr:full":"460-462 Greenford Rd Greenford Greater London UB6 8SQ",
    "addr:housenumber":"460-462",
    "addr:postcode":"ub6 8sq",
    "addr:street":"Greenford Rd",
    "iso:country":"GB",
    "sg:address":"460-462 Greenford Rd",
    "sg:city":"Greenford",
    "sg:classifiers":[
        {
            "category":"Cinema",
            "subcategory":"Movie Rental",
            "type":"Entertainment"
        }
    ],
    "sg:phone":"+44 20 8575 7420",
    "sg:postcode":"UB6 8SQ",
    "sg:province":"Greater London",
    "sg:tags":[
        "video",
        "library"
    ],
    "wof:name":"Variety Video",
    "wof:placetype":"venue"
},
  "geometry": {"coordinates":[-0.3518260121,51.5281829834],"type":"Point"}
}