{
  "type": "Feature",
  "properties": {
    "iso:country":"GB",
    "sg:address":"44 Shelgate Rd",
    "sg:city":"Battersea",
    "sg:classifiers":[
        {
            "category":"Professional",
            "type":"Services"
        }
    ],
    "sg:phone":"+44 20 7223 5456",
    "sg:postcode":"SW11 1BG",
    "sg:province":"Greater London",
    "sg:tags":[
        "entertainer"
    ],
    "wof:name":"Opera Interludes & Musical Interludes",
    "wof:placetype":"venue"
},
  "geometry": {"coordinates":[-0.1650930047,51.459312439],"type":"Point"}
}