{
  "type": "Feature",
  "properties": {
    "addr:full":"Selby Rd Leeds West Yorkshire LS15 7NP",
    "addr:postcode":"ls15 7np",
    "addr:street":"Selby Rd",
    "iso:country":"GB",
    "sg:address":"Selby Rd",
    "sg:city":"Leeds",
    "sg:classifiers":[
        {
            "category":"Place Of Worship",
            "type":"Public Place"
        }
    ],
    "sg:phone":"+44 113 264 7000",
    "sg:postcode":"LS15 7NP",
    "sg:province":"West Yorkshire",
    "wof:name":"St. Wilfrid's Church",
    "wof:placetype":"venue"
},
  "geometry": {"coordinates":[-1.479819,53.799187],"type":"Point"}
}