{
  "type": "Feature",
  "properties": {
    "iso:country":"GB",
    "sg:address":"11 Malmesbury Rd",
    "sg:city":"Coventry",
    "sg:classifiers":[
        {
            "category":"Personal",
            "type":"Services"
        }
    ],
    "sg:postcode":"CV6 2HX",
    "sg:province":"Warwickshire",
    "sg:tags":[
        "wedding"
    ],
    "wof:name":"Abbey Bridal Gowns",
    "wof:placetype":"venue"
},
  "geometry": {"coordinates":[-1.525273,52.442982],"type":"Point"}
}