{
  "type": "Feature",
  "properties": {
    "iso:country":"GB",
    "sg:address":"1 Sheaf Street",
    "sg:city":"Daventry",
    "sg:classifiers":[
        {
            "category":"Professional",
            "subcategory":"Lawyer & Legal Services",
            "type":"Services"
        }
    ],
    "sg:phone":"+44 1327 301201",
    "sg:postcode":"NN11 4AA",
    "sg:province":"Northamptonshire",
    "sg:tags":[
        "solicitor"
    ],
    "wof:name":"Jonathan Hatton",
    "wof:placetype":"venue"
},
  "geometry": {"coordinates":[-1.16276896,52.2560005188],"type":"Point"}
}