{
  "type": "Feature",
  "properties": {
    "addr:full":"Chaucer Indstl Est, Dittons Rd Polegate East Sussex BN26 6JF",
    "addr:postcode":"bn26 6jf",
    "addr:street":"Dittons Rd",
    "iso:country":"GB",
    "sg:address":"Chaucer Indstl Est, Dittons Rd",
    "sg:city":"Polegate",
    "sg:classifiers":[
        {
            "category":"Shopping",
            "subcategory":"Antiques",
            "type":"Retail Goods"
        }
    ],
    "sg:postcode":"BN26 6JF",
    "sg:province":"East Sussex",
    "wof:name":"Gearing,Ray,",
    "wof:placetype":"venue"
},
  "geometry": {"coordinates":[0.244123,50.821339],"type":"Point"}
}