{
  "type": "Feature",
  "properties": {
    "iso:country":"GB",
    "sg:address":"1-3 The Broadway, London Road",
    "sg:city":"Southend-on-sea",
    "sg:classifiers":[
        {
            "category":"Banks & Credit Unions",
            "subcategory":"Bank",
            "type":"Services"
        }
    ],
    "sg:phone":"+44 845 740 4404",
    "sg:postcode":"SS1 3HJ",
    "sg:province":"Essex",
    "wof:name":"Hsbc Bank Plc",
    "wof:placetype":"venue"
},
  "geometry": {"coordinates":[0.75754,51.530396],"type":"Point"}
}