{
  "type": "Feature",
  "properties": {
    "addr:full":"108 Derby Road, Sandiacre Nottingham Derbyshire NG10 5HU",
    "addr:housenumber":"108",
    "addr:postcode":"ng10 5hu",
    "addr:street":"Derby Road",
    "iso:country":"GB",
    "sg:address":"108 Derby Road, Sandiacre",
    "sg:city":"Nottingham",
    "sg:classifiers":[
        {
            "category":"Personal",
            "subcategory":"Beauty Salon",
            "type":"Services"
        }
    ],
    "sg:phone":"+44 115 939 2136",
    "sg:postcode":"NG10 5HU",
    "sg:province":"Derbyshire",
    "sg:tags":[
        "unisex",
        "hairdresser"
    ],
    "wof:name":"Style House",
    "wof:placetype":"venue"
},
  "geometry": {"coordinates":[-1.294119,52.922142],"type":"Point"}
}