{
  "type": "Feature",
  "properties": {
    "iso:country":"GB",
    "sg:address":"P O Box 81",
    "sg:city":"Lincoln",
    "sg:classifiers":[
        {
            "category":"Communications",
            "subcategory":"Newspaper",
            "type":"Services"
        }
    ],
    "sg:phone":"+44 1522 527127",
    "sg:postcode":"LN1 1HD",
    "sg:province":"Lincolnshire",
    "sg:tags":[
        "magazine"
    ],
    "wof:name":"County Life Ltd.",
    "wof:placetype":"venue"
},
  "geometry": {"coordinates":[-0.55994,53.240921],"type":"Point"}
}