{
  "type": "Feature",
  "properties": {
    "addr:full":"36 Cherry Tree Av Dover Kent CT16 2NL",
    "addr:housenumber":"36",
    "addr:postcode":"ct16 2nl",
    "addr:street":"Cherry Tree Av Dover",
    "iso:country":"GB",
    "sg:address":"36 Cherry Tree Av",
    "sg:city":"Dover",
    "sg:classifiers":[
        {
            "category":"Food & Beverages",
            "subcategory":"Liquor & Beverages",
            "type":"Retail Goods"
        }
    ],
    "sg:phone":"+44 1304 210032",
    "sg:postcode":"CT16 2NL",
    "sg:province":"Kent",
    "sg:tags":[
        "beer",
        "spirit",
        "wines"
    ],
    "wof:name":"Unwins Wine Merchants",
    "wof:placetype":"venue"
},
  "geometry": {"coordinates":[1.301282,51.135925],"type":"Point"}
}