{
  "type": "Feature",
  "properties": {
    "addr:full":"43 Sangley Road, Catford London Greater London SE6 2DT",
    "addr:housenumber":"43",
    "addr:postcode":"se6 2dt",
    "addr:street":"Sangley Road",
    "iso:country":"GB",
    "sg:address":"43 Sangley Road, Catford",
    "sg:city":"London",
    "sg:classifiers":[
        {
            "category":"Professional",
            "subcategory":"Printing & Photocopies",
            "type":"Services"
        }
    ],
    "sg:phone":"+44 20 8697 8387",
    "sg:postcode":"SE6 2DT",
    "sg:province":"Greater London",
    "sg:tags":[
        "printer"
    ],
    "wof:name":"David Jasper Printing",
    "wof:placetype":"venue"
},
  "geometry": {"coordinates":[-0.02009,51.444027],"type":"Point"}
}