{
  "type": "Feature",
  "properties": {
    "addr:full":"Studio 6, Steeple House, Percy St Coventry West Midlands CV1 3BY",
    "addr:housenumber":"6",
    "addr:postcode":"cv1 3by",
    "addr:street":"Percy St",
    "iso:country":"GB",
    "sg:address":"Studio 6, Steeple House, Percy St",
    "sg:city":"Coventry",
    "sg:classifiers":[
        {
            "category":"Professional",
            "subcategory":"Employment Agencies",
            "type":"Services"
        }
    ],
    "sg:phone":"+44 24 7655 2772",
    "sg:postcode":"CV1 3BY",
    "sg:province":"West Midlands",
    "sg:tags":[
        "modelling"
    ],
    "wof:name":"Aesthetics",
    "wof:placetype":"venue"
},
  "geometry": {"coordinates":[-1.5077680349,52.4069862366],"type":"Point"}
}