{
  "type": "Feature",
  "properties": {
    "addr:full":"149 Hoxton St London Greater London N1 6PJ",
    "addr:housenumber":"149",
    "addr:postcode":"n1 6pj",
    "addr:street":"Hoxton St",
    "iso:country":"GB",
    "sg:address":"149 Hoxton St",
    "sg:city":"London",
    "sg:classifiers":[
        {
            "category":"Food & Beverages",
            "subcategory":"Meat & Fish",
            "type":"Retail Goods"
        }
    ],
    "sg:postcode":"N1 6PJ",
    "sg:province":"Greater London",
    "sg:tags":[
        "butcher"
    ],
    "wof:name":"Bond,Raymond,",
    "wof:placetype":"venue"
},
  "geometry": {"coordinates":[-0.0802529976,51.5310935974],"type":"Point"}
}