{
  "type": "Feature",
  "properties": {
    "addr:full":"42 Beechburn Crescent, Huyton Liverpool Merseyside L36 4JZ",
    "addr:housenumber":"42",
    "addr:postcode":"l36 4jz",
    "addr:street":"Beechburn Crescent",
    "iso:country":"GB",
    "sg:address":"42 Beechburn Crescent, Huyton",
    "sg:city":"Liverpool",
    "sg:classifiers":[
        {
            "category":"Building & Trades",
            "subcategory":"Construction",
            "type":"Services"
        }
    ],
    "sg:postcode":"L36 4JZ",
    "sg:province":"Merseyside",
    "sg:tags":[
        "builder"
    ],
    "wof:name":"A G Davies",
    "wof:placetype":"venue"
},
  "geometry": {"coordinates":[-2.8630459309,53.4131317139],"type":"Point"}
}