{
  "type": "Feature",
  "properties": {
    "addr:full":"Kingsford Farm, Peters Marland Torrington Devon EX38 8QH",
    "addr:housenumber":"peters",
    "addr:postcode":"ex38 8qh",
    "addr:street":"Kingsford",
    "iso:country":"GB",
    "sg:address":"Kingsford Farm, Peters Marland",
    "sg:city":"Torrington",
    "sg:classifiers":[
        {
            "category":"Farming",
            "subcategory":"Livestock Farm",
            "type":"Manufacturing & Wholesale Goods"
        },
        {
            "category":"Farming",
            "subcategory":"Farm",
            "type":"Manufacturing & Wholesale Goods"
        }
    ],
    "sg:phone":"+44 1805 601329",
    "sg:postcode":"EX38 8QH",
    "sg:province":"Devon",
    "sg:tags":[
        "mixed",
        "crop",
        "others"
    ],
    "wof:name":"M G Budd & Son",
    "wof:placetype":"venue"
},
  "geometry": {"coordinates":[-4.1422548294,50.9531517029],"type":"Point"}
}