{
  "type": "Feature",
  "properties": {
    "iso:country":"GB",
    "sg:address":"25 Sloan Street, Catrine",
    "sg:city":"Mauchline",
    "sg:classifiers":[
        {
            "category":"Freight",
            "type":"Transportation"
        }
    ],
    "sg:postcode":"KA5 6PR",
    "sg:province":"East Ayrshire",
    "sg:tags":[
        "haulage",
        "road"
    ],
    "wof:name":"Martin McLatchie & Son",
    "wof:placetype":"venue"
},
  "geometry": {"coordinates":[-4.328385,55.499874],"type":"Point"}
}