{
  "type": "Feature",
  "properties": {
    "addr:full":"8 Itchen Close Petersfield Hampshire GU31 4NH",
    "addr:housenumber":"8",
    "addr:postcode":"gu31 4nh",
    "addr:street":"Itchen Close",
    "iso:country":"GB",
    "sg:address":"8 Itchen Close",
    "sg:city":"Petersfield",
    "sg:classifiers":[
        {
            "category":"Building & Trades",
            "subcategory":"Construction",
            "type":"Services"
        }
    ],
    "sg:phone":"+44 1730 260087",
    "sg:postcode":"GU31 4NH",
    "sg:province":"Hampshire",
    "sg:tags":[
        "bricklaying"
    ],
    "wof:name":"D.M Construction",
    "wof:placetype":"venue"
},
  "geometry": {"coordinates":[-0.944773972,50.997959137],"type":"Point"}
}