{
  "type": "Feature",
  "properties": {
    "addr:full":"Cornwall House Clinic, Sandy La Newcastle Staffordshire ST5 0LZ",
    "addr:postcode":"st5 0lz",
    "addr:street":"Sandy La Newcastle",
    "iso:country":"GB",
    "sg:address":"Cornwall House Clinic, Sandy La",
    "sg:city":"Newcastle",
    "sg:classifiers":[
        {
            "category":"Health Services",
            "subcategory":"Doctor",
            "type":"Services"
        }
    ],
    "sg:phone":"+44 1782 714600",
    "sg:postcode":"ST5 0LZ",
    "sg:province":"Staffordshire",
    "sg:tags":[
        "surgeon"
    ],
    "wof:name":"W G Coddington",
    "wof:placetype":"venue"
},
  "geometry": {"coordinates":[-2.228601,53.008801],"type":"Point"}
}