{
  "type": "Feature",
  "properties": {
    "addr:full":"1 Seaford Street Kilmarnock East Ayrshire KA1 2BZ",
    "addr:housenumber":"1",
    "addr:postcode":"ka1 2bz",
    "addr:street":"Seaford Street",
    "iso:country":"GB",
    "sg:address":"1 Seaford Street",
    "sg:city":"Kilmarnock",
    "sg:classifiers":[
        {
            "category":"Real Estate",
            "subcategory":"Architect",
            "type":"Services"
        }
    ],
    "sg:phone":"+44 1563 524040",
    "sg:postcode":"KA1 2BZ",
    "sg:province":"East Ayrshire",
    "wof:name":"D MCCALL",
    "wof:placetype":"venue"
},
  "geometry": {"coordinates":[-4.5030789375,55.6075553894],"type":"Point"}
}