{
  "type": "Feature",
  "properties": {
    "addr:full":"Factory 4, Downing St Smethwick West Midlands B66 2PA",
    "addr:housenumber":"4",
    "addr:postcode":"b66 2pa",
    "addr:street":"Downing St",
    "iso:country":"GB",
    "sg:address":"Factory 4, Downing St",
    "sg:city":"Smethwick",
    "sg:classifiers":[
        {
            "category":"Professional",
            "subcategory":"Engineering",
            "type":"Services"
        }
    ],
    "sg:phone":"+44 121 558 2649",
    "sg:postcode":"B66 2PA",
    "sg:province":"West Midlands",
    "wof:name":"Powercast Ltd",
    "wof:placetype":"venue"
},
  "geometry": {"coordinates":[-1.971184,52.495926],"type":"Point"}
}