{
  "type": "Feature",
  "properties": {
    "addr:full":"8 Hadfield Walk Mansfield Nottinghamshire NG18 3QT",
    "addr:housenumber":"8",
    "addr:postcode":"ng18 3qt",
    "addr:street":"Hadfield Walk",
    "iso:country":"GB",
    "sg:address":"8 Hadfield Walk",
    "sg:city":"Mansfield",
    "sg:classifiers":[
        {
            "category":"Arts & Performance",
            "subcategory":"Music",
            "type":"Entertainment"
        }
    ],
    "sg:phone":"+44 1623 643310",
    "sg:postcode":"NG18 3QT",
    "sg:province":"Nottinghamshire",
    "sg:tags":[
        "mobile",
        "disco"
    ],
    "wof:name":"Star Wars Mobile Roadshow",
    "wof:placetype":"venue"
},
  "geometry": {"coordinates":[-1.152501,53.142185],"type":"Point"}
}