{
  "type": "Feature",
  "properties": {
    "iso:country":"GB",
    "sg:address":"36 Park Avenue",
    "sg:city":"Barking",
    "sg:classifiers":[
        {
            "category":"Arts & Performance",
            "subcategory":"Music",
            "type":"Entertainment"
        }
    ],
    "sg:phone":"+44 20 8594 1320",
    "sg:postcode":"IG11 8QU",
    "sg:province":"Essex",
    "sg:tags":[
        "mobile",
        "disco"
    ],
    "wof:name":"Stargazer Discos & Equipment Hire",
    "wof:placetype":"venue"
},
  "geometry": {"coordinates":[0.08376,51.542606],"type":"Point"}
}