{
  "type": "Feature",
  "properties": {
    "iso:country":"GB",
    "sg:address":"8 Bethel Street",
    "sg:city":"Brighouse",
    "sg:classifiers":[
        {
            "category":"Health Services",
            "subcategory":"Clinic",
            "type":"Services"
        }
    ],
    "sg:postcode":"HD6 1JN",
    "sg:province":"West Yorkshire",
    "sg:tags":[
        "aromatherapy"
    ],
    "wof:name":"Eric Parkinson",
    "wof:placetype":"venue"
},
  "geometry": {"coordinates":[-1.780404,53.701149],"type":"Point"}
}