{
  "type": "Feature",
  "properties": {
    "iso:country":"GB",
    "sg:address":"4 Tritton Ave, Beddington",
    "sg:city":"Croydon",
    "sg:classifiers":[
        {
            "category":"Building & Trades",
            "subcategory":"Plumbing",
            "type":"Services"
        }
    ],
    "sg:postcode":"CR0 4SS",
    "sg:province":"Surrey",
    "sg:tags":[
        "heating"
    ],
    "wof:name":"Plough Mechanical Services",
    "wof:placetype":"venue"
},
  "geometry": {"coordinates":[-0.129547,51.368717],"type":"Point"}
}