{
  "type": "Feature",
  "properties": {
    "addr:full":"24 Windam Drive, Barnby Dun Doncaster South Yorkshire DN3 1BL",
    "addr:housenumber":"24",
    "addr:postcode":"dn3 1bl",
    "addr:street":"Windam Drive",
    "iso:country":"GB",
    "sg:address":"24 Windam Drive, Barnby Dun",
    "sg:city":"Doncaster",
    "sg:classifiers":[
        {
            "category":"Place Of Worship",
            "type":"Public Place"
        }
    ],
    "sg:postcode":"DN3 1BL",
    "sg:province":"South Yorkshire",
    "wof:name":"The House of Prayer Ministries",
    "wof:placetype":"venue"
},
  "geometry": {"coordinates":[-1.0696519613,53.581237793],"type":"Point"}
}