{
  "type": "Feature",
  "properties": {
    "addr:full":"10 Clarkson Road Wednesbury West Midlands WS10 9AY",
    "addr:housenumber":"10",
    "addr:postcode":"ws10 9ay",
    "addr:street":"Clarkson Road",
    "iso:country":"GB",
    "sg:address":"10 Clarkson Road",
    "sg:city":"Wednesbury",
    "sg:classifiers":[
        {
            "category":"Social Services",
            "subcategory":"Retirement Home",
            "type":"Services"
        }
    ],
    "sg:phone":"+44 121 505 7775",
    "sg:postcode":"WS10 9AY",
    "sg:province":"West Midlands",
    "sg:tags":[
        "residential",
        "care"
    ],
    "wof:name":"Kelvedon House",
    "wof:placetype":"venue"
},
  "geometry": {"coordinates":[-2.0112149715,52.557434082],"type":"Point"}
}