{
  "type": "Feature",
  "properties": {
    "addr:full":"Ascot Motor Works, Winkfield Road Ascot Berkshire SL5 7EX",
    "addr:postcode":"sl5 7ex",
    "addr:street":"Winkfield Road",
    "iso:country":"GB",
    "sg:address":"Ascot Motor Works, Winkfield Road",
    "sg:city":"Ascot",
    "sg:classifiers":[
        {
            "category":"Food & Beverages",
            "subcategory":"Supermarket",
            "type":"Retail Goods"
        },
        {
            "category":"Retail",
            "subcategory":"Auto Repair",
            "type":"Services"
        }
    ],
    "sg:phone":"+44 1344 620324",
    "sg:postcode":"SL5 7EX",
    "sg:province":"Berkshire",
    "sg:tags":[
        "modification",
        "garage"
    ],
    "wof:name":"H May (Ascot) Ltd.",
    "wof:placetype":"venue"
},
  "geometry": {"coordinates":[-0.6737939715,51.4106750488],"type":"Point"}
}