{
  "type": "Feature",
  "properties": {
    "addr:full":"Ty Draw, Gwytherin Abergele Conwy LL22 8UY",
    "addr:postcode":"ll22 8uy",
    "addr:street":"Ty;Gwytherin",
    "iso:country":"GB",
    "sg:address":"Ty Draw, Gwytherin",
    "sg:city":"Abergele",
    "sg:classifiers":[
        {
            "category":"Farming",
            "subcategory":"Livestock Farm",
            "type":"Manufacturing & Wholesale Goods"
        }
    ],
    "sg:postcode":"LL22 8UY",
    "sg:province":"Conwy",
    "sg:tags":[
        "others"
    ],
    "wof:name":"Gareth Pierce Williams",
    "wof:placetype":"venue"
},
  "geometry": {"coordinates":[-3.681191,53.139381],"type":"Point"}
}