{
  "type": "Feature",
  "properties": {
    "iso:country":"GB",
    "sg:address":"2 Ling Cotts, Ousby",
    "sg:city":"Penrith",
    "sg:classifiers":[
        {
            "category":"Farming",
            "subcategory":"Poultry Farm",
            "type":"Manufacturing & Wholesale Goods"
        }
    ],
    "sg:phone":"+44 1768 881130",
    "sg:postcode":"CA10 1PS",
    "sg:province":"Cumbria",
    "sg:tags":[
        "game"
    ],
    "wof:name":"Frank Bird",
    "wof:placetype":"venue"
},
  "geometry": {"coordinates":[-2.5926849842,54.7084884644],"type":"Point"}
}