{
  "type": "Feature",
  "properties": {
    "addr:full":"White Rose Shopping Centre Leeds West Yorkshire LS11 8LL",
    "addr:postcode":"ls11 8ll",
    "addr:street":"West",
    "iso:country":"GB",
    "sg:address":"White Rose Shopping Centre",
    "sg:city":"Leeds",
    "sg:classifiers":[
        {
            "category":"Shopping",
            "subcategory":"Clothing, Apparel, & Fashions",
            "type":"Retail Goods"
        }
    ],
    "sg:phone":"+44 113 271 4270",
    "sg:postcode":"LS11 8LL",
    "sg:province":"West Yorkshire",
    "sg:tags":[
        "menswear"
    ],
    "wof:name":"Style Union",
    "wof:placetype":"venue"
},
  "geometry": {"coordinates":[-1.572584,53.761459],"type":"Point"}
}