{
  "type": "Feature",
  "properties": {
    "iso:country":"GB",
    "sg:address":"136 Crockhamwell Rd, Woodley",
    "sg:city":"Reading",
    "sg:classifiers":[
        {
            "category":"Shopping",
            "subcategory":"Thrift Store",
            "type":"Retail Goods"
        }
    ],
    "sg:phone":"+44 118 944 2009",
    "sg:postcode":"RG5 3JH",
    "sg:province":"Berkshire",
    "sg:tags":[
        "shop",
        "charity"
    ],
    "wof:name":"British Red Cross Shop",
    "wof:placetype":"venue"
},
  "geometry": {"coordinates":[-0.90606,51.45079],"type":"Point"}
}