{
  "type": "Feature",
  "properties": {
    "addr:full":"Unit 1-3 Great Russell Ct, Fieldhead Nusiness Centre Bradford West Yorkshire BD7 1JZ",
    "addr:housenumber":"unit 1-3",
    "addr:postcode":"yorkshire bd7 1jz",
    "addr:street":"Great Russell Ct Fieldhead Nusiness",
    "iso:country":"GB",
    "sg:address":"Unit 1-3 Great Russell Ct, Fieldhead Nusiness Centre",
    "sg:city":"Bradford",
    "sg:classifiers":[
        {
            "category":"Manufacturing",
            "subcategory":"Tools & Machinery",
            "type":"Manufacturing & Wholesale Goods"
        },
        {
            "category":"Manufacturing",
            "subcategory":"Motor Vehicles & Parts",
            "type":"Manufacturing & Wholesale Goods"
        }
    ],
    "sg:phone":"+44 1274 393321",
    "sg:postcode":"BD7 1JZ",
    "sg:province":"West Yorkshire",
    "sg:tags":[
        "bearing",
        "stockist"
    ],
    "sg:website":"http://www.bsl.co.uk",
    "wof:name":"BSL Ltd",
    "wof:placetype":"venue"
},
  "geometry": {"coordinates":[-1.771316,53.794365],"type":"Point"}
}