{
  "type": "Feature",
  "properties": {
    "addr:full":"84 High St Merthyr Tydfil Merthyr Tydfil CF47 8UG",
    "addr:housenumber":"84",
    "addr:postcode":"cf47 8ug",
    "addr:street":"High St",
    "iso:country":"GB",
    "sg:address":"84 High St",
    "sg:city":"Merthyr Tydfil",
    "sg:classifiers":[
        {
            "category":"Professional",
            "subcategory":"Detective & Security Services",
            "type":"Services"
        }
    ],
    "sg:phone":"+44 1685 374240",
    "sg:postcode":"CF47 8UG",
    "sg:province":"Merthyr Tydfil",
    "sg:tags":[
        "alarm",
        "burglar",
        "system"
    ],
    "wof:name":"Sentry Alarms",
    "wof:placetype":"venue"
},
  "geometry": {"coordinates":[-3.377679,51.748219],"type":"Point"}
}