{
  "type": "Feature",
  "properties": {
    "addr:full":"1 Church Road Felixstowe Suffolk IP11 9NF",
    "addr:housenumber":"1",
    "addr:postcode":"ip11 9nf",
    "addr:street":"Church Road",
    "iso:country":"GB",
    "sg:address":"1 Church Road",
    "sg:city":"Felixstowe",
    "sg:classifiers":[
        {
            "category":"Building & Trades",
            "subcategory":"Construction",
            "type":"Services"
        }
    ],
    "sg:phone":"+44 1394 278254",
    "sg:postcode":"IP11 9NF",
    "sg:province":"Suffolk",
    "sg:tags":[
        "builder"
    ],
    "wof:name":"Peter G Mayes",
    "wof:placetype":"venue"
},
  "geometry": {"coordinates":[1.368182,51.969181],"type":"Point"}
}