{
  "type": "Feature",
  "properties": {
    "addr:full":"Queens Rd Bexhill On Sea East Sussex TN39 3JE",
    "addr:postcode":"tn39 3je",
    "addr:street":"Queens Rd",
    "iso:country":"GB",
    "sg:address":"Queens Rd",
    "sg:city":"Bexhill On Sea",
    "sg:classifiers":[
        {
            "category":"Insurance",
            "subcategory":"Insurance Agent",
            "type":"Services"
        }
    ],
    "sg:phone":"+44 1424 213001",
    "sg:postcode":"TN39 3JE",
    "sg:province":"East Sussex",
    "wof:name":"AC Insurance Services",
    "wof:placetype":"venue"
},
  "geometry": {"coordinates":[0.46986,50.83865],"type":"Point"}
}