{
  "type": "Feature",
  "properties": {
    "iso:country":"GB",
    "sg:address":"100 Tanfields New Church Farm",
    "sg:city":"Skelmersdale",
    "sg:classifiers":[
        {
            "category":"Retail",
            "subcategory":"Storage",
            "type":"Services"
        }
    ],
    "sg:postcode":"WN8 8NR",
    "sg:province":"Lancashire",
    "sg:tags":[
        "household",
        "removal"
    ],
    "wof:name":"Central Skelmersdale Removals",
    "wof:placetype":"venue"
},
  "geometry": {"coordinates":[-2.7884199619,53.5519447327],"type":"Point"}
}