{
  "type": "Feature",
  "properties": {
    "iso:country":"GB",
    "sg:address":"Linden Ho Steeles La",
    "sg:city":"Gravesend",
    "sg:classifiers":[
        {
            "category":"Education",
            "subcategory":"School",
            "type":"Public Place"
        }
    ],
    "sg:phone":"+44 1474 812443",
    "sg:postcode":"DA13 0QD",
    "sg:province":"Kent",
    "sg:tags":[
        "private",
        "tuition"
    ],
    "wof:name":"Begin Bridge",
    "wof:placetype":"venue"
},
  "geometry": {"coordinates":[0.3543800116,51.358341217],"type":"Point"}
}