{
  "type": "Feature",
  "properties": {
    "iso:country":"GB",
    "sg:address":"Melton House, 65-67 Clarendon Road",
    "sg:city":"Watford",
    "sg:classifiers":[
        {
            "category":"Train Station",
            "subcategory":"Rail",
            "type":"Transportation"
        }
    ],
    "sg:phone":"+44 1923 207321",
    "sg:postcode":"WD17 1XY",
    "sg:province":"Hertfordshire",
    "sg:tags":[
        "railway"
    ],
    "wof:name":"Network Rail Ltd.",
    "wof:placetype":"venue"
},
  "geometry": {"coordinates":[-0.3969990015,51.661781311],"type":"Point"}
}