{
  "type": "Feature",
  "properties": {
    "addr:full":"99-101 Thistle Lane Leeds West Yorkshire LS10 4JD",
    "addr:housenumber":"99-101",
    "addr:postcode":"ls10 4jd",
    "addr:street":"Thistle Lane",
    "iso:country":"GB",
    "sg:address":"99-101 Thistle Lane",
    "sg:city":"Leeds",
    "sg:classifiers":[
        {
            "category":"Government",
            "subcategory":"Post Office",
            "type":"Public Place"
        }
    ],
    "sg:phone":"+44 113 270 1979",
    "sg:postcode":"LS10 4JD",
    "sg:province":"West Yorkshire",
    "wof:name":"Throstle Lane Post Office",
    "wof:placetype":"venue"
},
  "geometry": {"coordinates":[-1.550003,53.741634],"type":"Point"}
}