{
  "type": "Feature",
  "properties": {
    "addr:full":"142 Cambridge Road Southport Lancashire PR9 9RZ",
    "addr:housenumber":"142",
    "addr:postcode":"pr9 9rz",
    "addr:street":"Cambridge Road",
    "iso:country":"GB",
    "sg:address":"142 Cambridge Road",
    "sg:city":"Southport",
    "sg:classifiers":[
        {
            "category":"Manufacturing",
            "subcategory":"Wood Products",
            "type":"Manufacturing & Wholesale Goods"
        }
    ],
    "sg:phone":"+44 1704 233133",
    "sg:postcode":"PR9 9RZ",
    "sg:province":"Lancashire",
    "sg:tags":[
        "maker",
        "cabinet"
    ],
    "wof:name":"The Real Kitchen Co",
    "wof:placetype":"venue"
},
  "geometry": {"coordinates":[-2.9767351151,53.6600112915],"type":"Point"}
}