{
  "type": "Feature",
  "properties": {
    "addr:full":"42 Spencer Clo Swindon Wiltshire SN5 6NG",
    "addr:housenumber":"42;clo",
    "addr:postcode":"sn5 6ng",
    "addr:street":"Spencer",
    "iso:country":"GB",
    "sg:address":"42 Spencer Clo",
    "sg:city":"Swindon",
    "sg:classifiers":[
        {
            "category":"Professional",
            "subcategory":"Testing Lab",
            "type":"Services"
        }
    ],
    "sg:phone":"+44 1793 877332",
    "sg:postcode":"SN5 6NG",
    "sg:province":"Wiltshire",
    "sg:tags":[
        "inspection",
        "calibration"
    ],
    "wof:name":"M M C",
    "wof:placetype":"venue"
},
  "geometry": {"coordinates":[-1.8435549736,51.5641326904],"type":"Point"}
}