{
  "type": "Feature",
  "properties": {
    "addr:full":"Wallbutton Rd Brockley Greater London SE4 2NY",
    "addr:postcode":"se4 2ny",
    "addr:street":"Wallbutton Rd",
    "iso:country":"GB",
    "sg:address":"Wallbutton Rd",
    "sg:city":"Brockley",
    "sg:classifiers":[
        {
            "category":"Education",
            "subcategory":"School",
            "type":"Public Place"
        }
    ],
    "sg:phone":"+44 20 7732 2122",
    "sg:postcode":"SE4 2NY",
    "sg:province":"Greater London",
    "sg:tags":[
        "local",
        "authority"
    ],
    "wof:name":"Hatcham Wood Secondary School",
    "wof:placetype":"venue"
},
  "geometry": {"coordinates":[-0.0354689993,51.4620513916],"type":"Point"}
}