{
  "type": "Feature",
  "properties": {
    "iso:country":"GB",
    "sg:address":"17 Highland Ridge",
    "sg:city":"Halesowen",
    "sg:classifiers":[
        {
            "category":"Home & Garden",
            "subcategory":"Kitchen Supply",
            "type":"Retail Goods"
        }
    ],
    "sg:phone":"+44 121 422 2628",
    "sg:postcode":"B62 8PH",
    "sg:province":"West Midlands",
    "sg:tags":[
        "equipment",
        "catering"
    ],
    "wof:name":"C K L Equipment",
    "wof:placetype":"venue"
},
  "geometry": {"coordinates":[-2.025365,52.457516],"type":"Point"}
}