{
  "type": "Feature",
  "properties": {
    "iso:country":"GB",
    "sg:address":"2 Grove Road",
    "sg:city":"Harpenden",
    "sg:classifiers":[
        {
            "category":"Restaurant",
            "type":"Food & Drink"
        }
    ],
    "sg:postcode":"AL5 1PX",
    "sg:province":"Hertfordshire",
    "sg:tags":[
        "indian"
    ],
    "wof:name":"New Bilash",
    "wof:placetype":"venue"
},
  "geometry": {"coordinates":[-0.342329,51.807076],"type":"Point"}
}