{
  "type": "Feature",
  "properties": {
    "iso:country":"GB",
    "sg:address":"Chanctondown, Horsham Road",
    "sg:city":"Steyning",
    "sg:classifiers":[
        {
            "category":"Farming",
            "subcategory":"Poultry Farm",
            "type":"Manufacturing & Wholesale Goods"
        }
    ],
    "sg:phone":"+44 1903 813346",
    "sg:postcode":"BN44 3AA",
    "sg:province":"West Sussex",
    "sg:tags":[
        "game"
    ],
    "wof:name":"R & C Knight",
    "wof:placetype":"venue"
},
  "geometry": {"coordinates":[-0.3177250028,50.8827972412],"type":"Point"}
}