{
  "type": "Feature",
  "properties": {
    "addr:full":"41 St Helier Avenue Morden Surrey SM4 6HY",
    "addr:housenumber":"41",
    "addr:postcode":"sm4 6hy",
    "addr:street":"St Helier Avenue",
    "iso:country":"GB",
    "sg:address":"41 St Helier Avenue",
    "sg:city":"Morden",
    "sg:classifiers":[
        {
            "category":"Health Services",
            "subcategory":"Dentist",
            "type":"Services"
        }
    ],
    "sg:phone":"+44 20 8648 9711",
    "sg:postcode":"SM4 6HY",
    "sg:province":"Surrey",
    "wof:name":"M Z Sheikh",
    "wof:placetype":"venue"
},
  "geometry": {"coordinates":[-0.186596,51.397808],"type":"Point"}
}