{
  "type": "Feature",
  "properties": {
    "addr:full":"6 Brookfield Cotts, The Strand, Lympstone Exmouth Devon EX8 5ES",
    "addr:housenumber":"6;cotts",
    "addr:postcode":"ex8 5es",
    "addr:street":"Brookfield;The Strand",
    "iso:country":"GB",
    "sg:address":"6 Brookfield Cotts, The Strand, Lympstone",
    "sg:city":"Exmouth",
    "sg:classifiers":[
        {
            "category":"Shopping",
            "subcategory":"News",
            "type":"Retail Goods"
        }
    ],
    "sg:phone":"+44 1395 265364",
    "sg:postcode":"EX8 5ES",
    "sg:province":"Devon",
    "sg:tags":[
        "newsagent"
    ],
    "wof:name":"Lympstone News",
    "wof:placetype":"venue"
},
  "geometry": {"coordinates":[-3.417639,50.649639],"type":"Point"}
}