{
  "type": "Feature",
  "properties": {
    "addr:full":"10 London Road, Thatcham Newbury Berkshire RG14 1JX",
    "addr:housenumber":"10",
    "addr:postcode":"rg14 1jx",
    "addr:street":"London Road",
    "iso:country":"GB",
    "sg:address":"10 London Road, Thatcham",
    "sg:city":"Newbury",
    "sg:classifiers":[
        {
            "category":"Retail",
            "subcategory":"Veterinary Services",
            "type":"Services"
        }
    ],
    "sg:phone":"+44 1635 868382",
    "sg:postcode":"RG14 1JX",
    "sg:province":"Berkshire",
    "sg:tags":[
        "surgeon"
    ],
    "wof:name":"O'Gorman Slater & Main",
    "wof:placetype":"venue"
},
  "geometry": {"coordinates":[-1.324003,51.405598],"type":"Point"}
}