{
  "type": "Feature",
  "properties": {
    "addr:full":"High Road Buckhurst Hill Essex IG9 5HU",
    "addr:postcode":"ig9 5hu",
    "addr:street":"High Road",
    "iso:country":"GB",
    "sg:address":"High Road",
    "sg:city":"Buckhurst Hill",
    "sg:classifiers":[
        {
            "category":"Parking",
            "type":"Transportation"
        }
    ],
    "sg:postcode":"IG9 5HU",
    "sg:province":"Essex",
    "sg:tags":[
        "car",
        "valet"
    ],
    "wof:name":"Buckhurst Hill Car Wash",
    "wof:placetype":"venue"
},
  "geometry": {"coordinates":[0.0373400003,51.6328849792],"type":"Point"}
}