{
  "type": "Feature",
  "properties": {
    "iso:country":"GB",
    "sg:address":"Prospect Farm, West Kirby Road",
    "sg:city":"Wirral",
    "sg:classifiers":[
        {
            "category":"Retail",
            "subcategory":"Laundry & Dry Cleaning",
            "type":"Services"
        },
        {
            "category":"Retail",
            "subcategory":"Repair Shop",
            "type":"Services"
        }
    ],
    "sg:phone":"+44 151 677 1800",
    "sg:postcode":"CH46 5NH",
    "sg:province":"Merseyside",
    "sg:tags":[
        "clothing",
        "alteration"
    ],
    "wof:name":"Perfect Stitch Workshop",
    "wof:placetype":"venue"
},
  "geometry": {"coordinates":[-3.123532,53.38937],"type":"Point"}
}