{
  "type": "Feature",
  "properties": {
    "addr:full":"9-11 Old Market Pl Warrington Cheshire WA1 1QB",
    "addr:housenumber":"9-11",
    "addr:postcode":"wa1 1qb",
    "addr:street":"Old Market Pl",
    "iso:country":"GB",
    "sg:address":"9-11 Old Market Pl",
    "sg:city":"Warrington",
    "sg:classifiers":[
        {
            "category":"Shopping",
            "subcategory":"Shoes",
            "type":"Retail Goods"
        }
    ],
    "sg:phone":"+44 1925 635529",
    "sg:postcode":"WA1 1QB",
    "sg:province":"Cheshire",
    "sg:tags":[
        "shop"
    ],
    "wof:name":"Saxone",
    "wof:placetype":"venue"
},
  "geometry": {"coordinates":[-2.5943639278,53.3899002075],"type":"Point"}
}