{
  "type": "Feature",
  "properties": {
    "iso:country":"GB",
    "sg:address":"Snarehill Farm, Euston Road, Snarehill",
    "sg:city":"Thetford",
    "sg:classifiers":[
        {
            "category":"Farming",
            "subcategory":"Poultry Farm",
            "type":"Manufacturing & Wholesale Goods"
        }
    ],
    "sg:phone":"+44 1842 764850",
    "sg:postcode":"IP24 2QD",
    "sg:province":"Norfolk",
    "sg:tags":[
        "game",
        "farmer"
    ],
    "wof:name":"Crown Chicken Ltd",
    "wof:placetype":"venue"
},
  "geometry": {"coordinates":[0.7859719992,52.376285553],"type":"Point"}
}