{
  "type": "Feature",
  "properties": {
    "addr:full":"Lainstone Ho, Guildford Rd Woking Surrey GU22 7UP",
    "addr:postcode":"gu22 7up",
    "addr:street":"Guildford Rd",
    "iso:country":"GB",
    "sg:address":"Lainstone Ho, Guildford Rd",
    "sg:city":"Woking",
    "sg:classifiers":[
        {
            "category":"Arts & Performance",
            "subcategory":"Music",
            "type":"Entertainment"
        }
    ],
    "sg:phone":"+44 1483 767933",
    "sg:postcode":"GU22 7UP",
    "sg:province":"Surrey",
    "sg:tags":[
        "mobile",
        "disco"
    ],
    "wof:name":"Uptown Downtown Roadshow",
    "wof:placetype":"venue"
},
  "geometry": {"coordinates":[-0.56429,51.309059],"type":"Point"}
}