{
  "type": "Feature",
  "properties": {
    "iso:country":"GB",
    "sg:address":"11 Cumberland Road",
    "sg:city":"West Bromwich",
    "sg:classifiers":[
        {
            "category":"Education",
            "subcategory":"University",
            "type":"Public Place"
        }
    ],
    "sg:phone":"+44 121 588 3849",
    "sg:postcode":"B71 1HP",
    "sg:province":"West Midlands",
    "sg:tags":[
        "higher"
    ],
    "wof:name":"Alan Rogers",
    "wof:placetype":"venue"
},
  "geometry": {"coordinates":[-1.9911060333,52.5348320007],"type":"Point"}
}