{
  "type": "Feature",
  "properties": {
    "iso:country":"GB",
    "sg:address":"Unit 4a Woodthorpe Avenue Industrial Es, T, Woodthorpe Avenue",
    "sg:city":"Boston",
    "sg:classifiers":[
        {
            "category":"Manufacturing",
            "subcategory":"Lumber",
            "type":"Manufacturing & Wholesale Goods"
        }
    ],
    "sg:postcode":"PE21 0NR",
    "sg:province":"Lincolnshire",
    "sg:tags":[
        "importer",
        "merchants",
        "agent",
        "timber"
    ],
    "wof:name":"T & T Timber",
    "wof:placetype":"venue"
},
  "geometry": {"coordinates":[-0.003269,52.975712],"type":"Point"}
}