{
  "type": "Feature",
  "properties": {
    "addr:full":"121-127 London Road Kingston-upon-thames Greater London KT2 6NH",
    "addr:housenumber":"121-127",
    "addr:postcode":"kt2 6nh",
    "addr:street":"London Road",
    "iso:country":"GB",
    "sg:address":"121-127 London Road",
    "sg:city":"Kingston-upon-thames",
    "sg:classifiers":[
        {
            "category":"Professional",
            "subcategory":"Testing Lab",
            "type":"Services"
        }
    ],
    "sg:phone":"+44 20 8549 3222",
    "sg:postcode":"KT2 6NH",
    "sg:province":"Greater London",
    "sg:tags":[
        "mot"
    ],
    "wof:name":"Fulfords of Kingston",
    "wof:placetype":"venue"
},
  "geometry": {"coordinates":[-0.294164,51.410717],"type":"Point"}
}