{
  "type": "Feature",
  "properties": {
    "iso:country":"GB",
    "sg:address":"33 Syddal Road, Bramhall",
    "sg:city":"Stockport",
    "sg:classifiers":[
        {
            "category":"Education",
            "subcategory":"School",
            "type":"Public Place"
        }
    ],
    "sg:phone":"+44 161 439 1751",
    "sg:postcode":"SK7 1AB",
    "sg:province":"Cheshire",
    "sg:tags":[
        "independent",
        "preparatory"
    ],
    "wof:name":"Syddal Park School Ltd.",
    "wof:placetype":"venue"
},
  "geometry": {"coordinates":[-2.1692700386,53.3559875488],"type":"Point"}
}