{
  "type": "Feature",
  "properties": {
    "iso:country":"GB",
    "sg:address":"8c Brampton Road",
    "sg:city":"Huntingdon",
    "sg:classifiers":[
        {
            "category":"Health Services",
            "subcategory":"Podiatrist",
            "type":"Services"
        }
    ],
    "sg:phone":"+44 1480 453592",
    "sg:postcode":"PE29 3BQ",
    "sg:province":"Cambridgeshire",
    "sg:tags":[
        "podiatrists",
        "chiropodist"
    ],
    "wof:name":"John Mcmullan",
    "wof:placetype":"venue"
},
  "geometry": {"coordinates":[-0.190538,52.330078],"type":"Point"}
}