{
  "type": "Feature",
  "properties": {
    "addr:full":"Unit 2, Burdwell Works, New Mill Road Huddersfield South Yorkshire HD9 7AZ",
    "addr:housenumber":"unit 2",
    "addr:postcode":"hd9 7az",
    "addr:street":"New Mill Road",
    "iso:country":"GB",
    "sg:address":"Unit 2, Burdwell Works, New Mill Road",
    "sg:city":"Huddersfield",
    "sg:classifiers":[
        {
            "category":"Home & Garden",
            "subcategory":"Building Materials",
            "type":"Retail Goods"
        }
    ],
    "sg:phone":"+44 1484 666400",
    "sg:postcode":"HD9 7AZ",
    "sg:province":"South Yorkshire",
    "sg:tags":[
        "roofing",
        "product",
        "related"
    ],
    "wof:name":"Greys Artstone Ltd",
    "wof:placetype":"venue"
},
  "geometry": {"coordinates":[-1.7559429407,53.5761222839],"type":"Point"}
}