{
  "type": "Feature",
  "properties": {
    "addr:full":"35 Denmark Hill London Greater London SE5 8RS",
    "addr:housenumber":"35",
    "addr:postcode":"se5 8rs",
    "addr:street":"Denmark Hill",
    "iso:country":"GB",
    "sg:address":"35 Denmark Hill",
    "sg:city":"London",
    "sg:classifiers":[
        {
            "category":"Bars & Pubs",
            "type":"Food & Drink"
        }
    ],
    "sg:phone":"+44 20 7703 4756",
    "sg:postcode":"SE5 8RS",
    "sg:province":"Greater London",
    "sg:tags":[
        "pubs",
        "inn"
    ],
    "wof:name":"The Joiners Arms",
    "wof:placetype":"venue"
},
  "geometry": {"coordinates":[-0.093021,51.472355],"type":"Point"}
}