{
  "type": "Feature",
  "properties": {
    "iso:country":"GB",
    "sg:address":"Beacon House, Willow Walk",
    "sg:city":"Skelmersdale",
    "sg:classifiers":[
        {
            "category":"Shopping",
            "subcategory":"Pharmacy",
            "type":"Retail Goods"
        }
    ],
    "sg:phone":"+44 870 514 3733",
    "sg:postcode":"WN8 6UR",
    "sg:province":"Lancashire",
    "sg:tags":[
        "medicine",
        "therapy"
    ],
    "wof:name":"Transcendental Meditation Centre",
    "wof:placetype":"venue"
},
  "geometry": {"coordinates":[-2.7763640881,53.5647926331],"type":"Point"}
}