{
  "type": "Feature",
  "properties": {
    "addr:full":"97a Main Street, Beeford Driffield East Riding of Yorkshire YO25 8AY",
    "addr:housenumber":"97a",
    "addr:postcode":"yo25 8ay",
    "addr:street":"Main Street",
    "iso:country":"GB",
    "sg:address":"97a Main Street, Beeford",
    "sg:city":"Driffield",
    "sg:classifiers":[
        {
            "category":"Retail",
            "subcategory":"Veterinary Services",
            "type":"Services"
        }
    ],
    "sg:phone":"+44 1262 488175",
    "sg:postcode":"YO25 8AY",
    "sg:province":"East Riding of Yorkshire",
    "sg:tags":[
        "surgeon"
    ],
    "wof:name":"Salus Q P Ltd.",
    "wof:placetype":"venue"
},
  "geometry": {"coordinates":[-0.296199,53.970352],"type":"Point"}
}