{
  "type": "Feature",
  "properties": {
    "iso:country":"GB",
    "sg:address":"19 The Square",
    "sg:city":"Beaminster",
    "sg:classifiers":[
        {
            "category":"Food & Beverages",
            "subcategory":"Meat & Fish",
            "type":"Retail Goods"
        }
    ],
    "sg:phone":"+44 1308 862253",
    "sg:postcode":"DT8 3AU",
    "sg:province":"Dorset",
    "sg:tags":[
        "butcher"
    ],
    "wof:name":"Frampton & Sons of Beaminster",
    "wof:placetype":"venue"
},
  "geometry": {"coordinates":[-2.7388939857,50.8090057373],"type":"Point"}
}