{
  "type": "Feature",
  "properties": {
    "iso:country":"GB",
    "sg:address":"208 Webheath, Palmeston Road",
    "sg:city":"London",
    "sg:classifiers":[
        {
            "category":"Social Services",
            "subcategory":"Adult Care",
            "type":"Services"
        }
    ],
    "sg:phone":"+44 20 7624 8811",
    "sg:postcode":"NW6 2JU",
    "sg:province":"Greater London",
    "sg:tags":[
        "day",
        "centre"
    ],
    "wof:name":"Kingsgate Rescource Centre",
    "wof:placetype":"venue"
},
  "geometry": {"coordinates":[-0.19824,51.545429],"type":"Point"}
}