{
  "type": "Feature",
  "properties": {
    "addr:full":"Lloyd Ho, 400a Third Av Manchester Cheshire M17 1BL",
    "addr:housenumber":"400a",
    "addr:postcode":"m17 1bl",
    "addr:street":"Third Av Manchester",
    "iso:country":"GB",
    "sg:address":"Lloyd Ho, 400a Third Av",
    "sg:city":"Manchester",
    "sg:classifiers":[
        {
            "category":"Professional",
            "subcategory":"Detective & Security Services",
            "type":"Services"
        }
    ],
    "sg:phone":"+44 161 872 4434",
    "sg:postcode":"M17 1BL",
    "sg:province":"Cheshire",
    "sg:tags":[
        "alarm",
        "burglar",
        "system"
    ],
    "wof:name":"Masco Security Systems",
    "wof:placetype":"venue"
},
  "geometry": {"coordinates":[-2.2488100529,53.4796218872],"type":"Point"}
}