{
  "type": "Feature",
  "properties": {
    "addr:full":"270 Brixton Road London Greater London SW9 6AQ",
    "addr:housenumber":"270",
    "addr:postcode":"sw9 6aq",
    "addr:street":"Brixton Road",
    "iso:country":"GB",
    "sg:address":"270 Brixton Road",
    "sg:city":"London",
    "sg:classifiers":[
        {
            "category":"Military Area",
            "subcategory":"Air Force Base",
            "type":"Public Place"
        }
    ],
    "sg:phone":"+44 20 7733 2164",
    "sg:postcode":"SW9 6AQ",
    "sg:province":"Greater London",
    "sg:tags":[
        "taxi",
        "hire",
        "private"
    ],
    "wof:name":"Brixton Mini Cabs",
    "wof:placetype":"venue"
},
  "geometry": {"coordinates":[-0.1127590016,51.4709014893],"type":"Point"}
}