{
  "type": "Feature",
  "properties": {
    "addr:full":"1 The Plain, Thornbury Bristol Gloucestershire BS35 2AG",
    "addr:housenumber":"1",
    "addr:postcode":"bs35 2ag",
    "addr:street":"The Plain",
    "iso:country":"GB",
    "sg:address":"1 The Plain, Thornbury",
    "sg:city":"Bristol",
    "sg:classifiers":[
        {
            "category":"Building & Trades",
            "subcategory":"Landscaping Services",
            "type":"Services"
        }
    ],
    "sg:phone":"+44 1454 413212",
    "sg:postcode":"BS35 2AG",
    "sg:province":"Gloucestershire",
    "sg:tags":[
        "landscape",
        "contractor"
    ],
    "wof:name":"T & J Owen",
    "wof:placetype":"venue"
},
  "geometry": {"coordinates":[-2.5257461071,51.6091499329],"type":"Point"}
}