{
  "type": "Feature",
  "properties": {
    "iso:country":"GB",
    "sg:address":"Silverwood, Congleton Road",
    "sg:city":"Alderley Edge",
    "sg:classifiers":[
        {
            "category":"Real Estate",
            "subcategory":"Architect",
            "type":"Services"
        }
    ],
    "sg:phone":"+44 1625 590701",
    "sg:postcode":"SK9 7AL",
    "sg:province":"Cheshire",
    "wof:name":"Hogbens",
    "wof:placetype":"venue"
},
  "geometry": {"coordinates":[-2.2363340855,53.3028068542],"type":"Point"}
}