{
  "type": "Feature",
  "properties": {
    "addr:full":"64 Grasmere Macclesfield Cheshire SK11 8PL",
    "addr:housenumber":"64",
    "addr:postcode":"sk11 8pl",
    "addr:street":"Grasmere",
    "iso:country":"GB",
    "sg:address":"64 Grasmere",
    "sg:city":"Macclesfield",
    "sg:classifiers":[
        {
            "category":"Professional",
            "subcategory":"Accounting & Tax Preparation",
            "type":"Services"
        }
    ],
    "sg:phone":"+44 1625 420818",
    "sg:postcode":"SK11 8PL",
    "sg:province":"Cheshire",
    "sg:tags":[
        "accountant"
    ],
    "wof:name":"J Watson & Co",
    "wof:placetype":"venue"
},
  "geometry": {"coordinates":[-2.1524000168,53.2513885498],"type":"Point"}
}