{
  "type": "Feature",
  "properties": {
    "addr:full":"Bristol Road, Hardwicke Gloucester Gloucestershire GL2 4QY",
    "addr:postcode":"gl2 4qy",
    "addr:street":"Bristol Road",
    "iso:country":"GB",
    "sg:address":"Bristol Road, Hardwicke",
    "sg:city":"Gloucester",
    "sg:classifiers":[
        {
            "category":"Bars & Pubs",
            "type":"Food & Drink"
        }
    ],
    "sg:phone":"+44 1452 720028",
    "sg:postcode":"GL2 4QY",
    "sg:province":"Gloucestershire",
    "sg:tags":[
        "pubs",
        "inn"
    ],
    "wof:name":"Morning Star",
    "wof:placetype":"venue"
},
  "geometry": {"coordinates":[-2.291809,51.805439],"type":"Point"}
}