{
  "type": "Feature",
  "properties": {
    "iso:country":"GB",
    "sg:address":"11 Mill La, Earley",
    "sg:city":"Reading",
    "sg:classifiers":[
        {
            "category":"Banks & Credit Unions",
            "subcategory":"Financial Services",
            "type":"Services"
        }
    ],
    "sg:postcode":"RG6 7JF",
    "sg:province":"Berkshire",
    "sg:tags":[
        "adviser"
    ],
    "wof:name":"Financial Solutions Partnership (The)",
    "wof:placetype":"venue"
},
  "geometry": {"coordinates":[-0.9070919752,51.4376792908],"type":"Point"}
}