{
  "type": "Feature",
  "properties": {
    "iso:country":"GB",
    "sg:address":"365 Holburn St",
    "sg:city":"Aberdeen",
    "sg:classifiers":[
        {
            "category":"Personal",
            "subcategory":"Beauty Salon",
            "type":"Services"
        }
    ],
    "sg:phone":"+44 1224 593431",
    "sg:postcode":"AB10 7FQ",
    "sg:province":"Aberdeen City",
    "sg:tags":[
        "unisex",
        "hairdresser"
    ],
    "wof:name":"D'Style",
    "wof:placetype":"venue"
},
  "geometry": {"coordinates":[-2.117149,57.130032],"type":"Point"}
}