{
  "type": "Feature",
  "properties": {
    "addr:full":"Great Pulteney Street Bath Somerset BA2 4DN",
    "addr:postcode":"ba2 4dn",
    "addr:street":"Great Pulteney Street",
    "iso:country":"GB",
    "sg:address":"Great Pulteney Street",
    "sg:city":"Bath",
    "sg:classifiers":[
        {
            "category":"Travel",
            "subcategory":"Hotels & Motels",
            "type":"Entertainment"
        }
    ],
    "sg:phone":"+44 1225 787960",
    "sg:postcode":"BA2 4DN",
    "sg:province":"Somerset",
    "wof:name":"Dukes Hotel",
    "wof:placetype":"venue"
},
  "geometry": {"coordinates":[-2.3518989086,51.3853492737],"type":"Point"}
}