{
  "type": "Feature",
  "properties": {
    "addr:full":"110 Temple Chambers, Temple Avenue London Greater London EC4Y 0DT",
    "addr:housenumber":"110",
    "addr:postcode":"ec4y 0dt",
    "addr:street":"Temple Chambers Temple Avenue",
    "iso:country":"GB",
    "sg:address":"110 Temple Chambers, Temple Avenue",
    "sg:city":"London",
    "sg:classifiers":[
        {
            "category":"Communications",
            "subcategory":"Newspaper",
            "type":"Services"
        }
    ],
    "sg:phone":"+44 20 7353 8442",
    "sg:postcode":"EC4Y 0DT",
    "sg:province":"Greater London",
    "sg:tags":[
        "magazine"
    ],
    "wof:name":"Express & Star",
    "wof:placetype":"venue"
},
  "geometry": {"coordinates":[-0.107969,51.512539],"type":"Point"}
}