{
  "type": "Feature",
  "properties": {
    "addr:full":"Sturminster Road, Stockwood Bristol City of Bristol BS14 8EJ",
    "addr:postcode":"bs14 8ej",
    "addr:street":"Sturminster Road",
    "iso:country":"GB",
    "sg:address":"Sturminster Road, Stockwood",
    "sg:city":"Bristol",
    "sg:classifiers":[
        {
            "category":"Government",
            "subcategory":"Post Office",
            "type":"Public Place"
        }
    ],
    "sg:phone":"+44 1275 832389",
    "sg:postcode":"BS14 8EJ",
    "sg:province":"City of Bristol",
    "wof:name":"Sturminster Road Post Office",
    "wof:placetype":"venue"
},
  "geometry": {"coordinates":[-2.5408289433,51.41173172],"type":"Point"}
}