{
  "type": "Feature",
  "properties": {
    "addr:full":"19 Falstaffst Shrewsbury Shropshire SY1 2QN",
    "addr:housenumber":"19",
    "addr:postcode":"sy1 2qn",
    "addr:street":"Falstaffst",
    "iso:country":"GB",
    "sg:address":"19 Falstaffst",
    "sg:city":"Shrewsbury",
    "sg:classifiers":[
        {
            "category":"Arena",
            "subcategory":"Sports Club",
            "type":"Entertainment"
        }
    ],
    "sg:postcode":"SY1 2QN",
    "sg:province":"Shropshire",
    "wof:name":"Greenfields & District Bowling Club Ltd",
    "wof:placetype":"venue"
},
  "geometry": {"coordinates":[-2.748201,52.720211],"type":"Point"}
}