{
  "type": "Feature",
  "properties": {
    "addr:full":"58 Charlotte Road London Greater London EC2A 3QG",
    "addr:housenumber":"58",
    "addr:postcode":"ec2a 3qg",
    "addr:street":"Charlotte Road",
    "iso:country":"GB",
    "sg:address":"58 Charlotte Road",
    "sg:city":"London",
    "sg:classifiers":[
        {
            "category":"Professional",
            "subcategory":"Art Services",
            "type":"Services"
        }
    ],
    "sg:phone":"+44 20 7613 3130",
    "sg:postcode":"EC2A 3QG",
    "sg:province":"Greater London",
    "sg:tags":[
        "graphic",
        "designer"
    ],
    "wof:name":"Taylor McKenzie Design Consultants Ltd.",
    "wof:placetype":"venue"
},
  "geometry": {"coordinates":[-0.080982,51.525928],"type":"Point"}
}