{
  "type": "Feature",
  "properties": {
    "addr:full":"65 Chapel Market London Greater London N1 9ER",
    "addr:housenumber":"65",
    "addr:postcode":"n1 9er",
    "addr:street":"Chapel Market",
    "iso:country":"GB",
    "sg:address":"65 Chapel Market",
    "sg:city":"London",
    "sg:classifiers":[
        {
            "category":"Fast Food",
            "type":"Food & Drink"
        }
    ],
    "sg:phone":"+44 20 7833 8924",
    "sg:postcode":"N1 9ER",
    "sg:province":"Greater London",
    "sg:tags":[
        "away",
        "take"
    ],
    "wof:name":"McDonalds Restaurants Ltd.",
    "wof:placetype":"venue"
},
  "geometry": {"coordinates":[-0.1084429994,51.5333976746],"type":"Point"}
}