{
  "type": "Feature",
  "properties": {
    "addr:full":"56 Church Road, Crystal Palace London Greater London SE19 2EZ",
    "addr:housenumber":"56",
    "addr:postcode":"se19 2ez",
    "addr:street":"Church Road",
    "iso:country":"GB",
    "sg:address":"56 Church Road, Crystal Palace",
    "sg:city":"London",
    "sg:classifiers":[
        {
            "category":"Professional",
            "subcategory":"Accounting & Tax Preparation",
            "type":"Services"
        }
    ],
    "sg:phone":"+44 20 8771 7000",
    "sg:postcode":"SE19 2EZ",
    "sg:province":"Greater London",
    "sg:tags":[
        "accountant"
    ],
    "wof:name":"Coker Isa & Co",
    "wof:placetype":"venue"
},
  "geometry": {"coordinates":[-0.0803169981,51.4178237915],"type":"Point"}
}