{
  "type": "Feature",
  "properties": {
    "addr:full":"21 Laindon Centre Basildon Essex SS15 5TE",
    "addr:housenumber":"21",
    "addr:postcode":"ss15 5te",
    "addr:street":"Laindon Centre",
    "iso:country":"GB",
    "sg:address":"21 Laindon Centre",
    "sg:city":"Basildon",
    "sg:classifiers":[
        {
            "category":"Personal",
            "subcategory":"Beauty Salon",
            "type":"Services"
        }
    ],
    "sg:phone":"+44 1268 543059",
    "sg:postcode":"SS15 5TE",
    "sg:province":"Essex",
    "sg:tags":[
        "unisex",
        "hairdresser"
    ],
    "wof:name":"Headquarters",
    "wof:placetype":"venue"
},
  "geometry": {"coordinates":[0.4375860095,51.5682945251],"type":"Point"}
}