{
  "type": "Feature",
  "properties": {
    "iso:country":"GB",
    "sg:address":"Butlers Garage, 38 Breck Rd",
    "sg:city":"Wallasey",
    "sg:classifiers":[
        {
            "category":"Utilities",
            "subcategory":"Refuse",
            "type":"Services"
        }
    ],
    "sg:phone":"+44 151 638 5130",
    "sg:postcode":"L44 3BD",
    "sg:province":"Merseyside",
    "sg:tags":[
        "skip",
        "hire"
    ],
    "wof:name":"Butlers Skip Hire",
    "wof:placetype":"venue"
},
  "geometry": {"coordinates":[-3.04994,53.41959],"type":"Point"}
}