{
  "type": "Feature",
  "properties": {
    "addr:full":"Yard D North Street Trading Est Brierley Hill West Midlands DY5 3QF",
    "addr:postcode":"dy5 3qf",
    "addr:street":"Yard;North Street;Hill",
    "iso:country":"GB",
    "sg:address":"Yard D North Street Trading Est",
    "sg:city":"Brierley Hill",
    "sg:classifiers":[
        {
            "category":"Wholesale",
            "subcategory":"Scrap",
            "type":"Manufacturing & Wholesale Goods"
        }
    ],
    "sg:phone":"+44 1384 262343",
    "sg:postcode":"DY5 3QF",
    "sg:province":"West Midlands",
    "sg:tags":[
        "breaker",
        "dismantlers"
    ],
    "wof:name":"T Wrecks",
    "wof:placetype":"venue"
},
  "geometry": {"coordinates":[-2.128347,52.479427],"type":"Point"}
}