{
  "type": "Feature",
  "properties": {
    "addr:full":"Bar Lane Industrial Park, Bar Lane Nottingham Nottinghamshire NG6 0JA",
    "addr:postcode":"ng6 0ja",
    "addr:street":"Bar Lane Industrial Park Bar Lane",
    "iso:country":"GB",
    "sg:address":"Bar Lane Industrial Park, Bar Lane",
    "sg:city":"Nottingham",
    "sg:classifiers":[
        {
            "category":"Building & Trades",
            "subcategory":"Landscaping Services",
            "type":"Services"
        }
    ],
    "sg:phone":"+44 115 970 5909",
    "sg:postcode":"NG6 0JA",
    "sg:province":"Nottinghamshire",
    "sg:tags":[
        "landscape",
        "contractor"
    ],
    "wof:name":"Horizon Landscapes Ltd",
    "wof:placetype":"venue"
},
  "geometry": {"coordinates":[-1.188729,52.978905],"type":"Point"}
}