{
  "type": "Feature",
  "properties": {
    "addr:full":"The Quadrant Huntingdon Cambridgeshire PE17 4PE",
    "addr:postcode":"pe17 4pe",
    "addr:street":"Huntingdon",
    "iso:country":"GB",
    "sg:address":"The Quadrant",
    "sg:city":"Huntingdon",
    "sg:classifiers":[
        {
            "category":"Autos & Motor Vehicles",
            "subcategory":"Automobile Sales",
            "type":"Retail Goods"
        }
    ],
    "sg:phone":"+44 1480 469555",
    "sg:postcode":"PE17 4PE",
    "sg:province":"Cambridgeshire",
    "sg:tags":[
        "commercial"
    ],
    "wof:name":"Fran Cars",
    "wof:placetype":"venue"
},
  "geometry": {"coordinates":[-0.1893000007,52.3351402283],"type":"Point"}
}