{
  "type": "Feature",
  "properties": {
    "addr:full":"The Old Granary, Bishop Thornton Harrogate North Yorkshire HG3 3JX",
    "addr:postcode":"hg3 3jx",
    "addr:street":"Bishop",
    "iso:country":"GB",
    "sg:address":"The Old Granary, Bishop Thornton",
    "sg:city":"Harrogate",
    "sg:classifiers":[
        {
            "category":"Building & Trades",
            "subcategory":"Construction",
            "type":"Services"
        }
    ],
    "sg:postcode":"HG3 3JX",
    "sg:province":"North Yorkshire",
    "sg:tags":[
        "builder"
    ],
    "wof:name":"Alan J Everitt",
    "wof:placetype":"venue"
},
  "geometry": {"coordinates":[-1.6005049944,54.0648117065],"type":"Point"}
}