{
  "type": "Feature",
  "properties": {
    "addr:full":"184 Lightbowne Road Manchester Greater Manchester M40 5EE",
    "addr:housenumber":"184",
    "addr:postcode":"m40 5ee",
    "addr:street":"Lightbowne Road",
    "iso:country":"GB",
    "sg:address":"184 Lightbowne Road",
    "sg:city":"Manchester",
    "sg:classifiers":[
        {
            "category":"Government",
            "subcategory":"Office",
            "type":"Public Place"
        },
        {
            "category":"Organizations",
            "subcategory":"Non-profit Organization",
            "type":"Services"
        }
    ],
    "sg:phone":"+44 161 684 9660",
    "sg:postcode":"M40 5EE",
    "sg:province":"Greater Manchester",
    "sg:tags":[
        "organisation",
        "community",
        "project",
        "charitable",
        "gov",
        "charity"
    ],
    "wof:name":"Lightbowne Young Families Project",
    "wof:placetype":"venue"
},
  "geometry": {"coordinates":[-2.192199,53.508095],"type":"Point"}
}