{
  "type": "Feature",
  "properties": {
    "iso:country":"GB",
    "sg:address":"26 Keirby Walk",
    "sg:city":"Burnley",
    "sg:classifiers":[
        {
            "category":"Shopping",
            "subcategory":"Clothing, Apparel, & Fashions",
            "type":"Retail Goods"
        }
    ],
    "sg:phone":"+44 1282 435081",
    "sg:postcode":"BB11 2DE",
    "sg:province":"Lancashire",
    "sg:tags":[
        "shop"
    ],
    "wof:name":"Looking Good (Clothing) Ltd.",
    "wof:placetype":"venue"
},
  "geometry": {"coordinates":[-2.239647,53.789768],"type":"Point"}
}