{
  "type": "Feature",
  "properties": {
    "iso:country":"GB",
    "sg:address":"2 The Trinity Centre, Park Farm Industrial Estate",
    "sg:city":"Wellingborough",
    "sg:classifiers":[
        {
            "category":"Building & Trades",
            "subcategory":"Construction",
            "type":"Services"
        }
    ],
    "sg:postcode":"NN8 6ZB",
    "sg:province":"Northamptonshire",
    "sg:tags":[
        "ceiling",
        "contractor"
    ],
    "wof:name":"Anchor Ceilings Ltd.",
    "wof:placetype":"venue"
},
  "geometry": {"coordinates":[-0.696296,52.302422],"type":"Point"}
}