{
  "type": "Feature",
  "properties": {
    "addr:full":"32 Cardiff Rd Dinas Powys The Vale of Glamorgan CF64 4JS",
    "addr:housenumber":"32",
    "addr:postcode":"cf64 4js",
    "addr:street":"Cardiff Rd;Vale",
    "iso:country":"GB",
    "sg:address":"32 Cardiff Rd",
    "sg:city":"Dinas Powys",
    "sg:classifiers":[
        {
            "category":"Retail",
            "subcategory":"Auto Repair",
            "type":"Services"
        }
    ],
    "sg:postcode":"CF64 4JS",
    "sg:province":"The Vale of Glamorgan",
    "sg:tags":[
        "body",
        "car"
    ],
    "wof:name":"Power,Brian,",
    "wof:placetype":"venue"
},
  "geometry": {"coordinates":[-3.214654,51.43401],"type":"Point"}
}