{
  "type": "Feature",
  "properties": {
    "iso:country":"GB",
    "sg:address":"7 Castle Street",
    "sg:city":"Christchurch",
    "sg:classifiers":[
        {
            "category":"Real Estate",
            "subcategory":"Real Estate Agent",
            "type":"Services"
        }
    ],
    "sg:phone":"+44 1202 474202",
    "sg:postcode":"BH23 1DP",
    "sg:province":"Dorset",
    "wof:name":"Slades Estate Agents",
    "wof:placetype":"venue"
},
  "geometry": {"coordinates":[-1.7755240202,50.7336654663],"type":"Point"}
}