{
  "type": "Feature",
  "properties": {
    "iso:country":"GB",
    "sg:address":"Brynffynon House, Trelewis",
    "sg:city":"Treharris",
    "sg:classifiers":[
        {
            "category":"Professional",
            "subcategory":"Detective & Security Services",
            "type":"Services"
        }
    ],
    "sg:phone":"+44 1443 410806",
    "sg:postcode":"CF46 6BL",
    "sg:province":"Caerphilly",
    "wof:name":"Tasma Security",
    "wof:placetype":"venue"
},
  "geometry": {"coordinates":[-3.298256,51.67009],"type":"Point"}
}