{
  "type": "Feature",
  "properties": {
    "addr:full":"10c Thornton Lodge Rd Huddersfield West Yorkshire HD1 3JQ",
    "addr:housenumber":"10c",
    "addr:postcode":"hd1 3jq",
    "addr:street":"Thornton Lodge Rd",
    "iso:country":"GB",
    "sg:address":"10c Thornton Lodge Rd",
    "sg:city":"Huddersfield",
    "sg:classifiers":[
        {
            "category":"Professional",
            "subcategory":"Accounting & Tax Preparation",
            "type":"Services"
        }
    ],
    "sg:phone":"+44 1484 422115",
    "sg:postcode":"HD1 3JQ",
    "sg:province":"West Yorkshire",
    "sg:tags":[
        "accountant"
    ],
    "wof:name":"Azim & Co Accountants",
    "wof:placetype":"venue"
},
  "geometry": {"coordinates":[-1.7977499962,53.6397972107],"type":"Point"}
}