{
  "type": "Feature",
  "properties": {
    "iso:country":"GB",
    "sg:address":"2 Hillside",
    "sg:city":"Barnstaple",
    "sg:classifiers":[
        {
            "category":"Parking",
            "type":"Transportation"
        },
        {
            "category":"Retail",
            "subcategory":"Car Wash",
            "type":"Services"
        }
    ],
    "sg:phone":"+44 1271 375730",
    "sg:postcode":"EX31 2JG",
    "sg:province":"Devon",
    "sg:tags":[
        "valet"
    ],
    "wof:name":"NICK HAWKINS",
    "wof:placetype":"venue"
},
  "geometry": {"coordinates":[-4.085629,51.07214],"type":"Point"}
}