{
  "type": "Feature",
  "properties": {
    "addr:full":"Kinkedale Road Middlesbrough North Yorkshire TS6 7RU",
    "addr:postcode":"ts6 7ru",
    "addr:street":"Kinkedale Road",
    "iso:country":"GB",
    "sg:address":"Kinkedale Road",
    "sg:city":"Middlesbrough",
    "sg:classifiers":[
        {
            "category":"Shopping",
            "subcategory":"Bicycles & Sporting Goods",
            "type":"Retail Goods"
        },
        {
            "category":"Manufacturing",
            "subcategory":"Watercraft",
            "type":"Manufacturing & Wholesale Goods"
        }
    ],
    "sg:phone":"+44 1642 468665",
    "sg:postcode":"TS6 7RU",
    "sg:province":"North Yorkshire",
    "sg:tags":[
        "boatbuilder",
        "equipment",
        "marine",
        "supply"
    ],
    "wof:name":"TEES FOYBOAT MARINE",
    "wof:placetype":"venue"
},
  "geometry": {"coordinates":[-1.14408,54.594669],"type":"Point"}
}