{
  "type": "Feature",
  "properties": {
    "addr:full":"Ormside Close, Hindley Industrial Estate, Hindley Grn Wigan Lancashire WN2 4HR",
    "addr:postcode":"wn2 4hr",
    "addr:street":"Ormside Close;Industrial Estate Hindley Grn",
    "iso:country":"GB",
    "sg:address":"Ormside Close, Hindley Industrial Estate, Hindley Grn",
    "sg:city":"Wigan",
    "sg:classifiers":[
        {
            "category":"Shopping",
            "type":"Retail Goods"
        }
    ],
    "sg:phone":"+44 1942 257112",
    "sg:postcode":"WN2 4HR",
    "sg:province":"Lancashire",
    "sg:tags":[
        "equipment",
        "clothing",
        "safety"
    ],
    "wof:name":"Nelsa Ltd.",
    "wof:placetype":"venue"
},
  "geometry": {"coordinates":[-2.5443658829,53.5274887085],"type":"Point"}
}