{
  "type": "Feature",
  "properties": {
    "iso:country":"GB",
    "sg:address":"4 Birchgrove Stores, Llanmartin",
    "sg:city":"Newport",
    "sg:classifiers":[
        {
            "category":"Food & Beverages",
            "subcategory":"Meat & Fish",
            "type":"Retail Goods"
        }
    ],
    "sg:postcode":"NP18 2JA",
    "sg:province":"Monmouthshire",
    "sg:tags":[
        "butcher"
    ],
    "wof:name":"Rice,P M,& Sons",
    "wof:placetype":"venue"
},
  "geometry": {"coordinates":[-2.882259,51.60257],"type":"Point"}
}