{
  "type": "Feature",
  "properties": {
    "addr:full":"1 Spital Road Maldon Essex CM9 6DT",
    "addr:housenumber":"1",
    "addr:postcode":"cm9 6dt",
    "addr:street":"Spital Road",
    "iso:country":"GB",
    "sg:address":"1 Spital Road",
    "sg:city":"Maldon",
    "sg:classifiers":[
        {
            "category":"Autos & Motor Vehicles",
            "subcategory":"Automobile Sales",
            "type":"Retail Goods"
        }
    ],
    "sg:phone":"+44 1621 852345",
    "sg:postcode":"CM9 6DT",
    "sg:province":"Essex",
    "sg:tags":[
        "car"
    ],
    "wof:name":"Dover Court Motor Co",
    "wof:placetype":"venue"
},
  "geometry": {"coordinates":[0.67459,51.730919],"type":"Point"}
}