{
  "type": "Feature",
  "properties": {
    "addr:full":"Foulmeed Farm, Sandwich Road Deal Kent CT14 0AS",
    "addr:postcode":"ct14 0as",
    "addr:street":"Sandwich Road Deal",
    "iso:country":"GB",
    "sg:address":"Foulmeed Farm, Sandwich Road",
    "sg:city":"Deal",
    "sg:classifiers":[
        {
            "category":"Retail",
            "subcategory":"Auto Repair",
            "type":"Services"
        }
    ],
    "sg:phone":"+44 1304 617640",
    "sg:postcode":"CT14 0AS",
    "sg:province":"Kent",
    "sg:tags":[
        "modification",
        "garage",
        "related"
    ],
    "wof:name":"Craker Bros",
    "wof:placetype":"venue"
},
  "geometry": {"coordinates":[1.403235,51.223129],"type":"Point"}
}