{
  "type": "Feature",
  "properties": {
    "addr:full":"3 Ashley Ct, High St West Drayton Greater London UB7 7DN",
    "addr:housenumber":"3",
    "addr:postcode":"ub7 7dn",
    "addr:street":"Ashley Ct High St",
    "iso:country":"GB",
    "sg:address":"3 Ashley Ct, High St",
    "sg:city":"West Drayton",
    "sg:classifiers":[
        {
            "category":"Freight",
            "type":"Transportation"
        }
    ],
    "sg:postcode":"UB7 7DN",
    "sg:province":"Greater London",
    "sg:tags":[
        "forwarders"
    ],
    "wof:name":"Cargo Network (Heathrow) Ltd",
    "wof:placetype":"venue"
},
  "geometry": {"coordinates":[-0.4739899933,51.5091171265],"type":"Point"}
}