{
  "type": "Feature",
  "properties": {
    "addr:full":"Flat 1 102 Upper High St Epsom Surrey KT17 4RQ",
    "addr:housenumber":"102",
    "addr:postcode":"kt17 4rq",
    "addr:street":"Upper High St",
    "iso:country":"GB",
    "sg:address":"Flat 1 102 Upper High St",
    "sg:city":"Epsom",
    "sg:classifiers":[
        {
            "category":"Building & Trades",
            "subcategory":"Equipment Rental",
            "type":"Services"
        }
    ],
    "sg:phone":"+44 20 8395 0943",
    "sg:postcode":"KT17 4RQ",
    "sg:province":"Surrey",
    "sg:tags":[
        "hire",
        "centre"
    ],
    "wof:name":"Creative Plant Services",
    "wof:placetype":"venue"
},
  "geometry": {"coordinates":[-0.25802,51.33477],"type":"Point"}
}