{
  "type": "Feature",
  "properties": {
    "addr:full":"Lambswick Lindridge Tenbury Wells Herefordshire WR15 8JQ",
    "addr:housenumber":"lindridge",
    "addr:postcode":"wr15 8jq",
    "iso:country":"GB",
    "sg:address":"Lambswick Lindridge",
    "sg:city":"Tenbury Wells",
    "sg:classifiers":[
        {
            "category":"Farming",
            "subcategory":"Livestock Farm",
            "type":"Manufacturing & Wholesale Goods"
        }
    ],
    "sg:phone":"+44 1584 881264",
    "sg:postcode":"WR15 8JQ",
    "sg:province":"Herefordshire",
    "sg:tags":[
        "others"
    ],
    "wof:name":"Cooper,W J,(Claywood) Ltd",
    "wof:placetype":"venue"
},
  "geometry": {"coordinates":[-2.594178915,52.3125839233],"type":"Point"}
}