{
  "type": "Feature",
  "properties": {
    "addr:full":"Po Box 15 Waterlooville Hampshire PO7 6BQ",
    "addr:housenumber":"po box 15",
    "addr:postcode":"po7 6bq",
    "iso:country":"GB",
    "sg:address":"Po Box 15",
    "sg:city":"Waterlooville",
    "sg:classifiers":[
        {
            "category":"Shopping",
            "subcategory":"Books",
            "type":"Retail Goods"
        }
    ],
    "sg:postcode":"PO7 6BQ",
    "sg:province":"Hampshire",
    "sg:tags":[
        "bookseller"
    ],
    "wof:name":"Pet Marketing Services",
    "wof:placetype":"venue"
},
  "geometry": {"coordinates":[-1.0614490509,50.8994903564],"type":"Point"}
}