{
  "type": "Feature",
  "properties": {
    "iso:country":"GB",
    "sg:address":"144 Milton Road",
    "sg:city":"Cambridge",
    "sg:classifiers":[
        {
            "category":"Real Estate",
            "subcategory":"Architect",
            "type":"Services"
        }
    ],
    "sg:phone":"+44 1223 576370",
    "sg:postcode":"CB4 1LE",
    "sg:province":"Cambridgeshire",
    "wof:name":"Rowland Carmichael Architects",
    "wof:placetype":"venue"
},
  "geometry": {"coordinates":[0.1301759928,52.2181167603],"type":"Point"}
}