{
  "type": "Feature",
  "properties": {
    "iso:country":"GB",
    "sg:address":"Unit 27 Bramshall Industrial Estate, Stone Road",
    "sg:city":"Uttoxeter",
    "sg:classifiers":[
        {
            "category":"Freight",
            "type":"Transportation"
        }
    ],
    "sg:postcode":"ST14 8SH",
    "sg:province":"Derbyshire",
    "sg:tags":[
        "haulage",
        "road"
    ],
    "wof:name":"Doug Punchard & Sons",
    "wof:placetype":"venue"
},
  "geometry": {"coordinates":[-1.924539,52.895695],"type":"Point"}
}