{
  "type": "Feature",
  "properties": {
    "addr:full":"2nd Floor London Greater London W14 8NS",
    "addr:housenumber":"2nd floor",
    "addr:postcode":"w14 8ns",
    "iso:country":"GB",
    "sg:address":"2nd Floor",
    "sg:city":"London",
    "sg:classifiers":[
        {
            "category":"Professional",
            "subcategory":"Advertising",
            "type":"Services"
        }
    ],
    "sg:phone":"+44 20 7348 5870",
    "sg:postcode":"W14 8NS",
    "sg:province":"Greater London",
    "sg:tags":[
        "agency"
    ],
    "wof:name":"Red C",
    "wof:placetype":"venue"
},
  "geometry": {"coordinates":[-0.2055490017,51.4981193542],"type":"Point"}
}