{
  "type": "Feature",
  "properties": {
    "addr:full":"90 Turney Rd Dulwich Greater London SE21 7JH",
    "addr:housenumber":"90",
    "addr:postcode":"se21 7jh",
    "addr:street":"Turney Rd",
    "iso:country":"GB",
    "sg:address":"90 Turney Rd",
    "sg:city":"Dulwich",
    "sg:classifiers":[
        {
            "category":"Health Services",
            "subcategory":"Medical Lab",
            "type":"Services"
        }
    ],
    "sg:phone":"+44 20 7733 2413",
    "sg:postcode":"SE21 7JH",
    "sg:province":"Greater London",
    "sg:tags":[
        "disposal",
        "waste"
    ],
    "wof:name":"Clinicontrol Ltd",
    "wof:placetype":"venue"
},
  "geometry": {"coordinates":[-0.095364,51.446671],"type":"Point"}
}