{
  "type": "Feature",
  "properties": {
    "addr:full":"2 The Bull Pit Bradford-on-avon Wiltshire BA15 1NB",
    "addr:housenumber":"2",
    "addr:postcode":"ba15 1nb",
    "addr:street":"The;Bradford-On-Avon",
    "iso:country":"GB",
    "sg:address":"2 The Bull Pit",
    "sg:city":"Bradford-on-avon",
    "sg:classifiers":[
        {
            "category":"Retail",
            "subcategory":"Funeral Services",
            "type":"Services"
        }
    ],
    "sg:phone":"+44 1225 863208",
    "sg:postcode":"BA15 1NB",
    "sg:province":"Wiltshire",
    "sg:tags":[
        "director"
    ],
    "sg:website":"http://www.csbowyer.com",
    "wof:name":"C S Bowyer Ltd.",
    "wof:placetype":"venue"
},
  "geometry": {"coordinates":[-2.2517769337,51.3483581543],"type":"Point"}
}