{
  "type": "Feature",
  "properties": {
    "addr:full":"34 Ashgrove Road Aberdeen Aberdeen City AB25 3AD",
    "addr:housenumber":"34",
    "addr:postcode":"ab25 3ad",
    "addr:street":"Ashgrove Road",
    "iso:country":"GB",
    "sg:address":"34 Ashgrove Road",
    "sg:city":"Aberdeen",
    "sg:classifiers":[
        {
            "category":"Travel",
            "subcategory":"Hotels & Motels",
            "type":"Entertainment"
        }
    ],
    "sg:phone":"+44 1224 484861",
    "sg:postcode":"AB25 3AD",
    "sg:province":"Aberdeen City",
    "sg:tags":[
        "house",
        "guest"
    ],
    "wof:name":"Ashgrove Guest House",
    "wof:placetype":"venue"
},
  "geometry": {"coordinates":[-2.117132,57.159786],"type":"Point"}
}