{
  "type": "Feature",
  "properties": {
    "addr:full":"57 Summerhill Road London Greater London N15 4HR",
    "addr:housenumber":"57",
    "addr:postcode":"n15 4hr",
    "addr:street":"Summerhill Road",
    "iso:country":"GB",
    "sg:address":"57 Summerhill Road",
    "sg:city":"London",
    "sg:classifiers":[
        {
            "category":"Social Services",
            "subcategory":"Adult Care",
            "type":"Services"
        },
        {
            "category":"Social Services",
            "subcategory":"Retirement Home",
            "type":"Services"
        }
    ],
    "sg:phone":"+44 20 8802 4451",
    "sg:postcode":"N15 4HR",
    "sg:province":"Greater London",
    "sg:tags":[
        "housing",
        "sheltered",
        "accommodation"
    ],
    "wof:name":"Sheltered Housing",
    "wof:placetype":"venue"
},
  "geometry": {"coordinates":[-0.08294,51.586754],"type":"Point"}
}