{
  "type": "Feature",
  "properties": {
    "addr:full":"17 High Street, Kemnay Inverurie Aberdeenshire AB51 5NB",
    "addr:housenumber":"17",
    "addr:postcode":"ab51 5nb",
    "addr:street":"High Street",
    "iso:country":"GB",
    "sg:address":"17 High Street, Kemnay",
    "sg:city":"Inverurie",
    "sg:classifiers":[
        {
            "category":"Health Services",
            "subcategory":"Clinic",
            "type":"Services"
        },
        {
            "category":"Shopping",
            "subcategory":"Pharmacy",
            "type":"Retail Goods"
        }
    ],
    "sg:phone":"+44 1467 642205",
    "sg:postcode":"AB51 5NB",
    "sg:province":"Aberdeenshire",
    "sg:tags":[
        "nh",
        "dispensing",
        "chemist"
    ],
    "wof:name":"Kemnay Pharmacy",
    "wof:placetype":"venue"
},
  "geometry": {"coordinates":[-2.4453039169,57.2344894409],"type":"Point"}
}