{
  "type": "Feature",
  "properties": {
    "iso:country":"GB",
    "sg:address":"Wellhouse Mills, Main Street, Wilsden",
    "sg:city":"Bradford",
    "sg:classifiers":[
        {
            "category":"Retail",
            "subcategory":"Auto Repair",
            "type":"Services"
        }
    ],
    "sg:phone":"+44 1535 275254",
    "sg:postcode":"BD15 0JW",
    "sg:province":"West Yorkshire",
    "sg:tags":[
        "modification",
        "car",
        "classic"
    ],
    "wof:name":"Roy Sharp",
    "wof:placetype":"venue"
},
  "geometry": {"coordinates":[-1.8602889776,53.8230133057],"type":"Point"}
}