{
  "type": "Feature",
  "properties": {
    "iso:country":"GB",
    "sg:address":"George St",
    "sg:city":"Manchester",
    "sg:classifiers":[
        {
            "category":"Place Of Worship",
            "type":"Public Place"
        }
    ],
    "sg:phone":"+44 161 865 4648",
    "sg:postcode":"M41 9BA",
    "sg:province":"Cheshire",
    "wof:name":"Urmston Methodist Church",
    "wof:placetype":"venue"
},
  "geometry": {"coordinates":[-2.343934,53.446884],"type":"Point"}
}