{
  "type": "Feature",
  "properties": {
    "addr:full":"2 Brookside Newhaven East Sussex BN9 9AX",
    "addr:housenumber":"2",
    "addr:postcode":"bn9 9ax",
    "addr:street":"Brookside Newhaven",
    "iso:country":"GB",
    "sg:address":"2 Brookside",
    "sg:city":"Newhaven",
    "sg:classifiers":[
        {
            "category":"Building & Trades",
            "subcategory":"Landscaping Services",
            "type":"Services"
        }
    ],
    "sg:phone":"+44 1273 512025",
    "sg:postcode":"BN9 9AX",
    "sg:province":"East Sussex",
    "sg:tags":[
        "gardening"
    ],
    "wof:name":"Landscape Services",
    "wof:placetype":"venue"
},
  "geometry": {"coordinates":[0.036648,50.807789],"type":"Point"}
}