{
  "type": "Feature",
  "properties": {
    "iso:country":"GB",
    "sg:address":"Gledhow, Radford Road",
    "sg:city":"Crawley",
    "sg:classifiers":[
        {
            "category":"Personal",
            "type":"Services"
        }
    ],
    "sg:postcode":"RH10 3NW",
    "sg:province":"Surrey",
    "sg:tags":[
        "wedding"
    ],
    "wof:name":"Gatwick Studios",
    "wof:placetype":"venue"
},
  "geometry": {"coordinates":[-0.154689,51.14201],"type":"Point"}
}