{
  "type": "Feature",
  "properties": {
    "addr:full":"Brook Moor, Wembley Road, North Somercotes Louth Lincolnshire LN11 7NP",
    "addr:postcode":"ln11 7np",
    "addr:street":"Brook Moor Wembley Road;Louth",
    "iso:country":"GB",
    "sg:address":"Brook Moor, Wembley Road, North Somercotes",
    "sg:city":"Louth",
    "sg:classifiers":[
        {
            "category":"Farming",
            "subcategory":"Livestock Farm",
            "type":"Manufacturing & Wholesale Goods"
        }
    ],
    "sg:phone":"+44 1507 358374",
    "sg:postcode":"LN11 7NP",
    "sg:province":"Lincolnshire",
    "sg:tags":[
        "others"
    ],
    "wof:name":"Brooks Bros",
    "wof:placetype":"venue"
},
  "geometry": {"coordinates":[0.132652998,53.446395874],"type":"Point"}
}