{
  "type": "Feature",
  "properties": {
    "addr:full":"7 Brook Crt, Brook Street, Bishops Waltham Southampton Hampshire SO32 1AX",
    "addr:housenumber":"7",
    "addr:postcode":"so32 1ax",
    "addr:street":"Brook Crt Brook Street",
    "iso:country":"GB",
    "sg:address":"7 Brook Crt, Brook Street, Bishops Waltham",
    "sg:city":"Southampton",
    "sg:classifiers":[
        {
            "category":"Travel",
            "subcategory":"Travel Agent",
            "type":"Entertainment"
        }
    ],
    "sg:phone":"+44 1489 896428",
    "sg:postcode":"SO32 1AX",
    "sg:province":"Hampshire",
    "wof:name":"R E Bath Travel Service Ltd.",
    "wof:placetype":"venue"
},
  "geometry": {"coordinates":[-1.2120419741,50.9547996521],"type":"Point"}
}