{
  "type": "Feature",
  "properties": {
    "iso:country":"GB",
    "sg:address":"29 St James Street",
    "sg:city":"South Petherton",
    "sg:classifiers":[
        {
            "category":"Personal",
            "subcategory":"Beauty Salon",
            "type":"Services"
        }
    ],
    "sg:phone":"+44 1460 242054",
    "sg:postcode":"TA13 5BN",
    "sg:province":"Somerset",
    "sg:tags":[
        "unisex",
        "hairdresser"
    ],
    "wof:name":"Lockets Unisex",
    "wof:placetype":"venue"
},
  "geometry": {"coordinates":[-2.809847,50.949791],"type":"Point"}
}