{
  "type": "Feature",
  "properties": {
    "iso:country":"GB",
    "sg:address":"Jagger Grn",
    "sg:city":"Halifax",
    "sg:classifiers":[
        {
            "category":"Professional",
            "subcategory":"Art Services",
            "type":"Services"
        }
    ],
    "sg:phone":"+44 1422 374272",
    "sg:postcode":"HX4 9DE",
    "sg:province":"West Yorkshire",
    "sg:tags":[
        "glass",
        "engraver"
    ],
    "wof:name":"Beverley Smith",
    "wof:placetype":"venue"
},
  "geometry": {"coordinates":[-1.8623039722,53.669631958],"type":"Point"}
}