{
  "type": "Feature",
  "properties": {
    "addr:full":"Shadsworth Road Blackburn Lancashire BB1 2HR",
    "addr:postcode":"bb1 2hr",
    "addr:street":"Shadsworth Road",
    "iso:country":"GB",
    "sg:address":"Shadsworth Road",
    "sg:city":"Blackburn",
    "sg:classifiers":[
        {
            "category":"Bars & Pubs",
            "type":"Food & Drink"
        }
    ],
    "sg:postcode":"BB1 2HR",
    "sg:province":"Lancashire",
    "sg:tags":[
        "pubs",
        "inn"
    ],
    "wof:name":"Cascades",
    "wof:placetype":"venue"
},
  "geometry": {"coordinates":[-2.4450740814,53.746257782],"type":"Point"}
}