{
  "type": "Feature",
  "properties": {
    "iso:country":"GB",
    "sg:address":"First Floor, 1 Silverwell Lane",
    "sg:city":"Bolton",
    "sg:classifiers":[
        {
            "category":"Health Services",
            "subcategory":"Nursing And Care Facility",
            "type":"Services"
        },
        {
            "category":"Organizations",
            "subcategory":"Community Association",
            "type":"Services"
        }
    ],
    "sg:phone":"+44 1204 368500",
    "sg:postcode":"BL1 1QN",
    "sg:province":"Lancashire",
    "sg:tags":[
        "society",
        "housing",
        "home"
    ],
    "wof:name":"Moorside Housing Association Ltd.",
    "wof:placetype":"venue"
},
  "geometry": {"coordinates":[-2.42543,53.577465],"type":"Point"}
}