{
  "type": "Feature",
  "properties": {
    "addr:full":"17 The Knapp Calne Wiltshire SN11 8NR",
    "addr:housenumber":"17",
    "addr:postcode":"sn11 8nr",
    "addr:street":"The Knapp",
    "iso:country":"GB",
    "sg:address":"17 The Knapp",
    "sg:city":"Calne",
    "sg:classifiers":[
        {
            "category":"Building & Trades",
            "subcategory":"Construction",
            "type":"Services"
        }
    ],
    "sg:postcode":"SN11 8NR",
    "sg:province":"Wiltshire",
    "sg:tags":[
        "roofing",
        "contracting"
    ],
    "wof:name":"J & A ROOFING",
    "wof:placetype":"venue"
},
  "geometry": {"coordinates":[-1.9986419678,51.4393005371],"type":"Point"}
}