{
  "type": "Feature",
  "properties": {
    "iso:country":"GB",
    "sg:address":"32 Eastbank Street",
    "sg:city":"Southport",
    "sg:classifiers":[
        {
            "category":"Food & Beverages",
            "subcategory":"Meat & Fish",
            "type":"Retail Goods"
        }
    ],
    "sg:phone":"+44 1704 531789",
    "sg:postcode":"PR8 1ET",
    "sg:province":"Lancashire",
    "sg:tags":[
        "chip"
    ],
    "wof:name":"Fleetwood Fish & Chips",
    "wof:placetype":"venue"
},
  "geometry": {"coordinates":[-3.0051579475,53.6454772949],"type":"Point"}
}