{
  "type": "Feature",
  "properties": {
    "iso:country":"GB",
    "sg:address":"229-235 Argyle St",
    "sg:city":"Glasgow",
    "sg:classifiers":[
        {
            "category":"Shopping",
            "subcategory":"Clothing, Apparel, & Fashions",
            "type":"Retail Goods"
        }
    ],
    "sg:phone":"+44 141 226 9992",
    "sg:postcode":"G2 8DL",
    "sg:province":"Glasgow City",
    "sg:tags":[
        "shop"
    ],
    "wof:name":"Storm",
    "wof:placetype":"venue"
},
  "geometry": {"coordinates":[-4.261239,55.858688],"type":"Point"}
}