{
  "type": "Feature",
  "properties": {
    "addr:full":"8 Alfredsway Industrial Estate, Alfreds Way Barking Essex IG11 0AS",
    "addr:housenumber":"8",
    "addr:postcode":"ig11 0as",
    "addr:street":"Alfredsway Industrial Estate Alfreds Way",
    "iso:country":"GB",
    "sg:address":"8 Alfredsway Industrial Estate, Alfreds Way",
    "sg:city":"Barking",
    "sg:classifiers":[
        {
            "category":"Home & Garden",
            "subcategory":"Home Furnishings",
            "type":"Retail Goods"
        },
        {
            "category":"Home & Garden",
            "subcategory":"Hardware",
            "type":"Retail Goods"
        }
    ],
    "sg:phone":"+44 20 8591 2570",
    "sg:postcode":"IG11 0AS",
    "sg:province":"Essex",
    "sg:tags":[
        "merchant",
        "paint",
        "diy",
        "decorators'"
    ],
    "wof:name":"Dulux Decorators Centre",
    "wof:placetype":"venue"
},
  "geometry": {"coordinates":[0.081115,51.539101],"type":"Point"}
}