{
  "type": "Feature",
  "properties": {
    "iso:country":"GB",
    "sg:address":"92 Kings Highway",
    "sg:city":"Woolwich",
    "sg:classifiers":[
        {
            "category":"Cafe",
            "type":"Food & Drink"
        }
    ],
    "sg:phone":"+44 20 8854 4806",
    "sg:postcode":"SE18 2BG",
    "sg:province":"Greater London",
    "sg:tags":[
        "tea",
        "room"
    ],
    "wof:name":"Highway Cafe",
    "wof:placetype":"venue"
},
  "geometry": {"coordinates":[0.1030659974,51.4788360596],"type":"Point"}
}