{
  "type": "Feature",
  "properties": {
    "iso:country":"GB",
    "sg:address":"Atrium Court",
    "sg:city":"Bracknell",
    "sg:classifiers":[
        {
            "category":"Professional",
            "subcategory":"Computer Services",
            "type":"Services"
        }
    ],
    "sg:phone":"+44 870 300 6525",
    "sg:postcode":"RG12 1BW",
    "sg:province":"Berkshire",
    "sg:tags":[
        "system",
        "software"
    ],
    "wof:name":"Netstore (U K) Ltd.",
    "wof:placetype":"venue"
},
  "geometry": {"coordinates":[-0.75089,51.416248],"type":"Point"}
}