{
  "type": "Feature",
  "properties": {
    "addr:full":"12 Broad Street Stamford Cambridgeshire PE9 1PG",
    "addr:housenumber":"12",
    "addr:postcode":"pe9 1pg",
    "addr:street":"Broad Street",
    "iso:country":"GB",
    "sg:address":"12 Broad Street",
    "sg:city":"Stamford",
    "sg:classifiers":[
        {
            "category":"Professional",
            "subcategory":"Employment Agencies",
            "type":"Services"
        }
    ],
    "sg:postcode":"PE9 1PG",
    "sg:province":"Cambridgeshire",
    "sg:tags":[
        "career",
        "guidance"
    ],
    "wof:name":"Lincolnshire Careers & Guidance Services",
    "wof:placetype":"venue"
},
  "geometry": {"coordinates":[-0.478064,52.653549],"type":"Point"}
}