{
  "type": "Feature",
  "properties": {
    "iso:country":"GB",
    "sg:address":"Avenue Road, Hurst Grn",
    "sg:city":"Clitheroe",
    "sg:classifiers":[
        {
            "category":"Organizations",
            "subcategory":"Community Association",
            "type":"Services"
        },
        {
            "category":"Organizations",
            "subcategory":"Membership Organization",
            "type":"Services"
        }
    ],
    "sg:phone":"+44 1254 826400",
    "sg:postcode":"BB7 9QB",
    "sg:province":"Lancashire",
    "sg:tags":[
        "club",
        "social"
    ],
    "wof:name":"St.Peter's Guild Club",
    "wof:placetype":"venue"
},
  "geometry": {"coordinates":[-2.481339,53.839169],"type":"Point"}
}