{
  "type": "Feature",
  "properties": {
    "addr:full":"Middlewood House, Linton Wood Lane York North Yorkshire YO30 2BE",
    "addr:postcode":"yo30 2be",
    "addr:street":"Linton Wood Lane",
    "iso:country":"GB",
    "sg:address":"Middlewood House, Linton Wood Lane",
    "sg:city":"York",
    "sg:classifiers":[
        {
            "category":"Professional",
            "subcategory":"Art Services",
            "type":"Services"
        }
    ],
    "sg:phone":"+44 1347 848787",
    "sg:postcode":"YO30 2BE",
    "sg:province":"North Yorkshire",
    "sg:tags":[
        "photographer"
    ],
    "wof:name":"Chris Mason Photography",
    "wof:placetype":"venue"
},
  "geometry": {"coordinates":[-1.234384,54.041309],"type":"Point"}
}