{
  "type": "Feature",
  "properties": {
    "addr:full":"Carolyn House, Dingwall Rd Croydon Surrey CR0 9XF",
    "addr:postcode":"cr0 9xf",
    "addr:street":"Dingwall Rd",
    "iso:country":"GB",
    "sg:address":"Carolyn House, Dingwall Rd",
    "sg:city":"Croydon",
    "sg:classifiers":[
        {
            "category":"Professional",
            "subcategory":"Accounting & Tax Preparation",
            "type":"Services"
        }
    ],
    "sg:phone":"+44 20 8681 5666",
    "sg:postcode":"CR0 9XF",
    "sg:province":"Surrey",
    "sg:tags":[
        "payroll"
    ],
    "wof:name":"Rebus Group plc",
    "wof:placetype":"venue"
},
  "geometry": {"coordinates":[-0.0958089978,51.3778038025],"type":"Point"}
}