{
  "type": "Feature",
  "properties": {
    "iso:country":"GB",
    "sg:address":"59 Shelley Av",
    "sg:city":"Manor Park",
    "sg:classifiers":[
        {
            "category":"Health Services",
            "subcategory":"Doctor",
            "type":"Services"
        }
    ],
    "sg:phone":"+44 20 8472 9332",
    "sg:postcode":"E12 6PX",
    "sg:province":"Greater London",
    "sg:tags":[
        "practitioners"
    ],
    "wof:name":"Desai, J D",
    "wof:placetype":"venue"
},
  "geometry": {"coordinates":[0.050296,51.543381],"type":"Point"}
}