{
  "type": "Feature",
  "properties": {
    "iso:country":"GB",
    "sg:address":"1 Station Parade, Green Street, Upton Park",
    "sg:city":"London",
    "sg:classifiers":[
        {
            "category":"Transit Center",
            "subcategory":"Freight",
            "type":"Transportation"
        },
        {
            "category":"Shopping",
            "subcategory":"Computers & Home Electronics",
            "type":"Retail Goods"
        }
    ],
    "sg:phone":"+44 20 8472 4575",
    "sg:postcode":"E13 9AT",
    "sg:province":"Greater London",
    "sg:tags":[
        "hi-fi",
        "fi",
        "hi",
        "centre"
    ],
    "sg:website":"http://www.2rays.com",
    "wof:name":"2 Rays Enterprises",
    "wof:placetype":"venue"
},
  "geometry": {"coordinates":[0.03549,51.535469],"type":"Point"}
}