{
  "type": "Feature",
  "properties": {
    "iso:country":"GB",
    "sg:address":"Denston Hall Estate, Denston",
    "sg:city":"Newmarket",
    "sg:classifiers":[
        {
            "category":"Farming",
            "subcategory":"Farm",
            "type":"Manufacturing & Wholesale Goods"
        }
    ],
    "sg:postcode":"CB8 8PW",
    "sg:province":"Cambridgeshire",
    "sg:tags":[
        "mixed",
        "crop"
    ],
    "wof:name":"R F Macaire",
    "wof:placetype":"venue"
},
  "geometry": {"coordinates":[0.57454,52.145916],"type":"Point"}
}