{
  "type": "Feature",
  "properties": {
    "iso:country":"GB",
    "sg:address":"3 Midfield Parade, Mayplace Road East",
    "sg:city":"Bexleyheath",
    "sg:classifiers":[
        {
            "category":"Shopping",
            "subcategory":"News",
            "type":"Retail Goods"
        }
    ],
    "sg:phone":"+44 1322 521061",
    "sg:postcode":"DA7 6NA",
    "sg:province":"Kent",
    "sg:tags":[
        "newsagent"
    ],
    "wof:name":"Barnehurst One Stop",
    "wof:placetype":"venue"
},
  "geometry": {"coordinates":[0.1534489989,51.4590263367],"type":"Point"}
}