{
  "type": "Feature",
  "properties": {
    "addr:full":"48 Derwen Rd, Pontardawe Swansea Neath Port Talbot SA8 3AU",
    "addr:housenumber":"48",
    "addr:postcode":"sa8 3au",
    "addr:street":"Derwen Rd",
    "iso:country":"GB",
    "sg:address":"48 Derwen Rd, Pontardawe",
    "sg:city":"Swansea",
    "sg:classifiers":[
        {
            "category":"Professional",
            "subcategory":"Engineering",
            "type":"Services"
        }
    ],
    "sg:phone":"+44 1792 863355",
    "sg:postcode":"SA8 3AU",
    "sg:province":"Neath Port Talbot",
    "sg:tags":[
        "consulting",
        "engineer"
    ],
    "wof:name":"Construction Management Services",
    "wof:placetype":"venue"
},
  "geometry": {"coordinates":[-3.854427,51.710869],"type":"Point"}
}