{
  "type": "Feature",
  "properties": {
    "iso:country":"GB",
    "sg:address":"104 Garratt Lane",
    "sg:city":"London",
    "sg:classifiers":[
        {
            "category":"Bars & Pubs",
            "type":"Food & Drink"
        }
    ],
    "sg:phone":"+44 20 8874 4099",
    "sg:postcode":"SW18 4DJ",
    "sg:province":"Greater London",
    "sg:tags":[
        "pubs",
        "inn"
    ],
    "wof:name":"Old Sergeant",
    "wof:placetype":"venue"
},
  "geometry": {"coordinates":[-0.190449,51.451267],"type":"Point"}
}