{
  "type": "Feature",
  "properties": {
    "addr:full":", Limington Yeovil Dorset BA22 8ER",
    "addr:postcode":"ba22 8er",
    "addr:street":"Dorset",
    "iso:country":"GB",
    "sg:address":", Limington",
    "sg:city":"Yeovil",
    "sg:classifiers":[
        {
            "category":"Transit Center",
            "subcategory":"Passenger",
            "type":"Transportation"
        },
        {
            "category":"Retail",
            "subcategory":"Pet Boarding",
            "type":"Services"
        }
    ],
    "sg:phone":"+44 1935 840392",
    "sg:postcode":"BA22 8ER",
    "sg:province":"Dorset",
    "sg:tags":[
        "kennel",
        "catteries"
    ],
    "wof:name":"Moonwinds Quarantine & Boarding Kennels",
    "wof:placetype":"venue"
},
  "geometry": {"coordinates":[-2.6549079418,50.9960289001],"type":"Point"}
}