{
  "type": "Feature",
  "properties": {
    "addr:full":"14 Mill Hill Road Cowes Isle of Wight PO31 7EA",
    "addr:housenumber":"14",
    "addr:postcode":"po31 7ea",
    "addr:street":"Mill Hill Road",
    "iso:country":"GB",
    "sg:address":"14 Mill Hill Road",
    "sg:city":"Cowes",
    "sg:classifiers":[
        {
            "category":"Retail",
            "subcategory":"Repair Shop",
            "type":"Services"
        }
    ],
    "sg:phone":"+44 1983 291422",
    "sg:postcode":"PO31 7EA",
    "sg:province":"Isle of Wight",
    "sg:tags":[
        "upholsterer"
    ],
    "wof:name":"Island Upholstery",
    "wof:placetype":"venue"
},
  "geometry": {"coordinates":[-1.296792984,50.7589683533],"type":"Point"}
}