{
  "type": "Feature",
  "properties": {
    "addr:full":"1 East Parade York North Yorkshire YO31 7WJ",
    "addr:housenumber":"1",
    "addr:postcode":"yo31 7wj",
    "addr:street":"East Parade",
    "iso:country":"GB",
    "sg:address":"1 East Parade",
    "sg:city":"York",
    "sg:classifiers":[
        {
            "category":"Insurance",
            "subcategory":"Insurance Agent",
            "type":"Services"
        },
        {
            "category":"Banks & Credit Unions",
            "subcategory":"Financial Services",
            "type":"Services"
        }
    ],
    "sg:postcode":"YO31 7WJ",
    "sg:province":"North Yorkshire",
    "sg:tags":[
        "adviser",
        "broker"
    ],
    "wof:name":"BOLAN DALE (FINANCIAL SERVICES) LTD",
    "wof:placetype":"venue"
},
  "geometry": {"coordinates":[-1.0666110516,53.9651908875],"type":"Point"}
}