{
  "type": "Feature",
  "properties": {
    "iso:country":"GB",
    "sg:address":"Brompton Lane",
    "sg:city":"Rochester",
    "sg:classifiers":[
        {
            "category":"Place Of Worship",
            "type":"Public Place"
        }
    ],
    "sg:phone":"+44 1634 718718",
    "sg:postcode":"ME2 3BQ",
    "sg:province":"Kent",
    "wof:name":"Strrod Gospel Mission Church",
    "wof:placetype":"venue"
},
  "geometry": {"coordinates":[0.4926050007,51.3997001648],"type":"Point"}
}