{
  "type": "Feature",
  "properties": {
    "iso:country":"GB",
    "sg:address":"50a Stramongate",
    "sg:city":"Kendal",
    "sg:classifiers":[
        {
            "category":"Home & Garden",
            "subcategory":"Home Furnishings",
            "type":"Retail Goods"
        }
    ],
    "sg:phone":"+44 1539 731936",
    "sg:postcode":"LA9 4BD",
    "sg:province":"Cumbria",
    "sg:tags":[
        "furnishers",
        "planner",
        "kitchen"
    ],
    "wof:name":"Christians of Kendal",
    "wof:placetype":"venue"
},
  "geometry": {"coordinates":[-2.743741,54.328911],"type":"Point"}
}