{
  "type": "Feature",
  "properties": {
    "iso:country":"GB",
    "sg:address":"18 The Wynd, Cumbernauld",
    "sg:city":"Glasgow",
    "sg:classifiers":[
        {
            "category":"Farming",
            "subcategory":"Nursery",
            "type":"Manufacturing & Wholesale Goods"
        }
    ],
    "sg:postcode":"G67 2SU",
    "sg:province":"Falkirk",
    "sg:tags":[
        "creche"
    ],
    "wof:name":"Craigard Nursery",
    "wof:placetype":"venue"
},
  "geometry": {"coordinates":[-3.97496,55.963192],"type":"Point"}
}