{
  "type": "Feature",
  "properties": {
    "iso:country":"GB",
    "sg:address":"200 Derby Road",
    "sg:city":"Chesterfield",
    "sg:classifiers":[
        {
            "category":"Place Of Worship",
            "type":"Public Place"
        }
    ],
    "sg:phone":"+44 1246 273753",
    "sg:postcode":"S40 2EP",
    "sg:province":"Derbyshire",
    "wof:name":"Church of the Holy Family",
    "wof:placetype":"venue"
},
  "geometry": {"coordinates":[-1.4263709784,53.2242126465],"type":"Point"}
}