{
  "type": "Feature",
  "properties": {
    "addr:full":"21 Harts Hill Close, Hillingdon Uxbridge Greater London UB10 9LH",
    "addr:housenumber":"21",
    "addr:postcode":"ub10 9lh",
    "addr:street":"Harts Hill Close",
    "iso:country":"GB",
    "sg:address":"21 Harts Hill Close, Hillingdon",
    "sg:city":"Uxbridge",
    "sg:classifiers":[
        {
            "category":"Professional",
            "subcategory":"Accounting & Tax Preparation",
            "type":"Services"
        }
    ],
    "sg:postcode":"UB10 9LH",
    "sg:province":"Greater London",
    "sg:tags":[
        "consultant",
        "accountant"
    ],
    "wof:name":"Alan W Hooper Fcaatii",
    "wof:placetype":"venue"
},
  "geometry": {"coordinates":[-0.4507189989,51.5494689941],"type":"Point"}
}