{
  "type": "Feature",
  "properties": {
    "iso:country":"GB",
    "sg:address":"Acornfield Road, Knowsley Industrial Park",
    "sg:city":"Liverpool",
    "sg:classifiers":[
        {
            "category":"Taxi",
            "type":"Transportation"
        }
    ],
    "sg:postcode":"L33 7UG",
    "sg:province":"Lancashire",
    "sg:tags":[
        "mini",
        "cab"
    ],
    "wof:name":"Kable Kabs",
    "wof:placetype":"venue"
},
  "geometry": {"coordinates":[-2.850859,53.479881],"type":"Point"}
}