{
  "type": "Feature",
  "properties": {
    "addr:full":"32 Broad Street Fraserburgh Aberdeenshire AB43 5AH",
    "addr:housenumber":"32",
    "addr:postcode":"ab43 5ah",
    "addr:street":"Broad Street",
    "iso:country":"GB",
    "sg:address":"32 Broad Street",
    "sg:city":"Fraserburgh",
    "sg:classifiers":[
        {
            "category":"Shopping",
            "subcategory":"Department Store",
            "type":"Retail Goods"
        }
    ],
    "sg:phone":"+44 1346 517511",
    "sg:postcode":"AB43 5AH",
    "sg:province":"Aberdeenshire",
    "wof:name":"Christies 99p Stores",
    "wof:placetype":"venue"
},
  "geometry": {"coordinates":[-2.005165,57.692802],"type":"Point"}
}