{
  "type": "Feature",
  "properties": {
    "iso:country":"GB",
    "sg:address":"27 Park Road",
    "sg:city":"Shipley",
    "sg:classifiers":[
        {
            "category":"Professional",
            "subcategory":"Detective & Security Services",
            "type":"Services"
        }
    ],
    "sg:phone":"+44 1274 587465",
    "sg:postcode":"BD18 2JU",
    "sg:province":"West Yorkshire",
    "sg:tags":[
        "locksmith"
    ],
    "wof:name":"Yorkshire Lock & Safe Co.",
    "wof:placetype":"venue"
},
  "geometry": {"coordinates":[-1.766788,53.832184],"type":"Point"}
}