{
  "type": "Feature",
  "properties": {
    "iso:country":"GB",
    "sg:address":"75b Ampthill Road",
    "sg:city":"Shefford",
    "sg:classifiers":[
        {
            "category":"Building & Trades",
            "subcategory":"Construction",
            "type":"Services"
        }
    ],
    "sg:postcode":"SG17 5AZ",
    "sg:province":"Bedfordshire",
    "sg:tags":[
        "joiner",
        "carpenter"
    ],
    "wof:name":"Anthony J Albone",
    "wof:placetype":"venue"
},
  "geometry": {"coordinates":[-0.3431020081,52.0368309021],"type":"Point"}
}