{
  "type": "Feature",
  "properties": {
    "iso:country":"GB",
    "sg:address":"Unit 418, Oakshott Place",
    "sg:city":"Preston",
    "sg:classifiers":[
        {
            "category":"Wholesale",
            "subcategory":"Chemicals & Plastics",
            "type":"Manufacturing & Wholesale Goods"
        }
    ],
    "sg:postcode":"PR5 8AT",
    "sg:province":"Lancashire",
    "sg:tags":[
        "product",
        "allied"
    ],
    "wof:name":"Marabou Ltd.",
    "wof:placetype":"venue"
},
  "geometry": {"coordinates":[-2.636815,53.722282],"type":"Point"}
}