{
  "type": "Feature",
  "properties": {
    "iso:country":"GB",
    "sg:address":"47 Nelson Street",
    "sg:city":"Carlisle",
    "sg:classifiers":[
        {
            "category":"Health Services",
            "subcategory":"Nursing And Care Facility",
            "type":"Services"
        },
        {
            "category":"Organizations",
            "subcategory":"Community Association",
            "type":"Services"
        }
    ],
    "sg:phone":"+44 1228 633600",
    "sg:postcode":"CA2 5NE",
    "sg:province":"Cumbria",
    "sg:tags":[
        "co-operatives",
        "society",
        "housing",
        "trust",
        "home"
    ],
    "wof:name":"Impact Housing Association Ltd.",
    "wof:placetype":"venue"
},
  "geometry": {"coordinates":[-2.943802,54.887787],"type":"Point"}
}