{
  "type": "Feature",
  "properties": {
    "addr:full":"West Ho, West St Chipping Norton Gloucestershire OX7 6YQ",
    "addr:postcode":"ox7 6yq",
    "addr:street":"West;West St",
    "iso:country":"GB",
    "sg:address":"West Ho, West St",
    "sg:city":"Chipping Norton",
    "sg:classifiers":[
        {
            "category":"Building & Trades",
            "subcategory":"Construction",
            "type":"Services"
        }
    ],
    "sg:phone":"+44 1608 658059",
    "sg:postcode":"OX7 6YQ",
    "sg:province":"Gloucestershire",
    "sg:tags":[
        "contractor"
    ],
    "wof:name":"Crompton Construction Ltd",
    "wof:placetype":"venue"
},
  "geometry": {"coordinates":[-1.545912981,51.9404067993],"type":"Point"}
}