{
  "type": "Feature",
  "properties": {
    "iso:country":"GB",
    "sg:address":"Ford House, Nantgarw Road",
    "sg:city":"Caerphilly",
    "sg:classifiers":[
        {
            "category":"Autos & Motor Vehicles",
            "subcategory":"Automobile Sales",
            "type":"Retail Goods"
        }
    ],
    "sg:postcode":"CF83 1BW",
    "sg:province":"Caerphilly",
    "sg:tags":[
        "car"
    ],
    "wof:name":"Caerphilly Motor Co",
    "wof:placetype":"venue"
},
  "geometry": {"coordinates":[-3.223979,51.57774],"type":"Point"}
}