{
  "type": "Feature",
  "properties": {
    "addr:full":"Dental Surgery, 8 Brock St Lancaster Lancashire LA1 1UU",
    "addr:housenumber":"8",
    "addr:postcode":"la1 1uu",
    "addr:street":"Brock St",
    "iso:country":"GB",
    "sg:address":"Dental Surgery, 8 Brock St",
    "sg:city":"Lancaster",
    "sg:classifiers":[
        {
            "category":"Health Services",
            "subcategory":"Dentist",
            "type":"Services"
        }
    ],
    "sg:phone":"+44 1524 37324",
    "sg:postcode":"LA1 1UU",
    "sg:province":"Lancashire",
    "wof:name":"Ian Wild B.D.S",
    "wof:placetype":"venue"
},
  "geometry": {"coordinates":[-2.7990291119,54.0445365906],"type":"Point"}
}