{
  "type": "Feature",
  "properties": {
    "addr:full":"Woodlands County First School, Winding Way Salisbury Wiltshire SP2 9DY",
    "addr:postcode":"sp2 9dy",
    "addr:street":"Winding Way",
    "iso:country":"GB",
    "sg:address":"Woodlands County First School, Winding Way",
    "sg:city":"Salisbury",
    "sg:classifiers":[
        {
            "category":"Education",
            "subcategory":"Preschool",
            "type":"Public Place"
        }
    ],
    "sg:phone":"+44 1722 337549",
    "sg:postcode":"SP2 9DY",
    "sg:province":"Wiltshire",
    "sg:tags":[
        "pre-school",
        "playgroups"
    ],
    "wof:name":"Tree Tops Playgroup",
    "wof:placetype":"venue"
},
  "geometry": {"coordinates":[-1.8002840281,51.0695381165],"type":"Point"}
}