{
  "type": "Feature",
  "properties": {
    "addr:full":"26-28 High St Cleethorpes Lincolnshire DN35 8JN",
    "addr:housenumber":"26-28",
    "addr:postcode":"dn35 8jn",
    "addr:street":"High St",
    "iso:country":"GB",
    "sg:address":"26-28 High St",
    "sg:city":"Cleethorpes",
    "sg:classifiers":[
        {
            "category":"Bars & Pubs",
            "type":"Food & Drink"
        }
    ],
    "sg:phone":"+44 181 426 4486",
    "sg:postcode":"DN35 8JN",
    "sg:province":"Lincolnshire",
    "sg:tags":[
        "pubs",
        "inn"
    ],
    "wof:name":"Baton Rouge The",
    "wof:placetype":"venue"
},
  "geometry": {"coordinates":[-0.0313040018,53.5608062744],"type":"Point"}
}