{
  "type": "Feature",
  "properties": {
    "addr:full":"52 Whitewaits Harlow Essex CM20 3LN",
    "addr:housenumber":"52",
    "addr:postcode":"cm20 3ln",
    "addr:street":"Whitewaits",
    "iso:country":"GB",
    "sg:address":"52 Whitewaits",
    "sg:city":"Harlow",
    "sg:classifiers":[
        {
            "category":"Building & Trades",
            "subcategory":"Cleaning & Sanitation",
            "type":"Services"
        }
    ],
    "sg:phone":"+44 1279 422335",
    "sg:postcode":"CM20 3LN",
    "sg:province":"Essex",
    "sg:tags":[
        "commercial"
    ],
    "wof:name":"K & S Cleaning",
    "wof:placetype":"venue"
},
  "geometry": {"coordinates":[0.1071520001,51.7701301575],"type":"Point"}
}