{
  "type": "Feature",
  "properties": {
    "iso:country":"GB",
    "sg:address":"10 New St",
    "sg:city":"Worcester",
    "sg:classifiers":[
        {
            "category":"Professional",
            "subcategory":"Art Services",
            "type":"Services"
        }
    ],
    "sg:phone":"+44 1905 611196",
    "sg:postcode":"WR1 2DN",
    "sg:province":"Worcestershire",
    "sg:tags":[
        "picture",
        "restoration"
    ],
    "wof:name":"TGJ Framing",
    "wof:placetype":"venue"
},
  "geometry": {"coordinates":[-2.218516,52.191429],"type":"Point"}
}