{
  "type": "Feature",
  "properties": {
    "iso:country":"GB",
    "sg:address":"Davies Mews",
    "sg:city":"London",
    "sg:classifiers":[
        {
            "category":"Shopping",
            "subcategory":"Antiques",
            "type":"Retail Goods"
        }
    ],
    "sg:postcode":"W1K 5LP",
    "sg:province":"Greater London",
    "wof:name":"Cloudheath Ltd",
    "wof:placetype":"venue"
},
  "geometry": {"coordinates":[-0.147994,51.513161],"type":"Point"}
}