{
  "type": "Feature",
  "properties": {
    "addr:full":"32-34 Kings Road Harrogate North Yorkshire HG1 5JW",
    "addr:housenumber":"32-34",
    "addr:postcode":"hg1 5jw",
    "addr:street":"Kings Road",
    "iso:country":"GB",
    "sg:address":"32-34 Kings Road",
    "sg:city":"Harrogate",
    "sg:classifiers":[
        {
            "category":"Professional",
            "subcategory":"Printing & Photocopies",
            "type":"Services"
        }
    ],
    "sg:phone":"+44 1423 530362",
    "sg:postcode":"HG1 5JW",
    "sg:province":"North Yorkshire",
    "sg:tags":[
        "printer"
    ],
    "wof:name":"Elanders (U K) Ltd.",
    "wof:placetype":"venue"
},
  "geometry": {"coordinates":[-1.5418679714,53.9958152771],"type":"Point"}
}