{
  "type": "Feature",
  "properties": {
    "addr:full":"2200 Parkway, Kettering Parkway Kettering Northamptonshire NN15 6XR",
    "addr:housenumber":"2200",
    "addr:postcode":"nn15 6xr",
    "addr:street":"Parkway Kettering Parkway",
    "iso:country":"GB",
    "sg:address":"2200 Parkway, Kettering Parkway",
    "sg:city":"Kettering",
    "sg:classifiers":[
        {
            "category":"Shopping",
            "subcategory":"Clothing, Apparel, & Fashions",
            "type":"Retail Goods"
        }
    ],
    "sg:phone":"+44 1536 312177",
    "sg:postcode":"NN15 6XR",
    "sg:province":"Northamptonshire",
    "sg:tags":[
        "clothing",
        "fabric"
    ],
    "wof:name":"House Of Sand Ltd",
    "wof:placetype":"venue"
},
  "geometry": {"coordinates":[-0.7092990279,52.3754081726],"type":"Point"}
}