{
  "type": "Feature",
  "properties": {
    "addr:full":"Strid Cottage, Bolton Abbey Skipton Lancashire BD23 6AN",
    "addr:postcode":"bd23 6an",
    "addr:street":"Bolton Abbey",
    "iso:country":"GB",
    "sg:address":"Strid Cottage, Bolton Abbey",
    "sg:city":"Skipton",
    "sg:classifiers":[
        {
            "category":"Education",
            "subcategory":"School",
            "type":"Public Place"
        }
    ],
    "sg:phone":"+44 1756 710452",
    "sg:postcode":"BD23 6AN",
    "sg:province":"Lancashire",
    "sg:tags":[
        "independent",
        "preparatory"
    ],
    "wof:name":"Wharfedale Montessori School & Training College",
    "wof:placetype":"venue"
},
  "geometry": {"coordinates":[-1.891229,53.981838],"type":"Point"}
}