{
  "type": "Feature",
  "properties": {
    "addr:full":"15 Old Marston Rd, Marston Oxford Oxfordshire OX3 0JR",
    "addr:housenumber":"15",
    "addr:postcode":"ox3 0jr",
    "addr:street":"Old Marston Rd",
    "iso:country":"GB",
    "sg:address":"15 Old Marston Rd, Marston",
    "sg:city":"Oxford",
    "sg:classifiers":[
        {
            "category":"Food & Beverages",
            "subcategory":"Supermarket",
            "type":"Retail Goods"
        }
    ],
    "sg:phone":"+44 1865 242672",
    "sg:postcode":"OX3 0JR",
    "sg:province":"Oxfordshire",
    "wof:name":"Oxford Swindon & Gloucester Co-Operative Society Ltd",
    "wof:placetype":"venue"
},
  "geometry": {"coordinates":[-1.234738946,51.7660751343],"type":"Point"}
}