{
  "type": "Feature",
  "properties": {
    "addr:full":"3 Kensington High Street London Greater London W8 5ED",
    "addr:housenumber":"3",
    "addr:postcode":"w8 5ed",
    "addr:street":"Kensington High Street",
    "iso:country":"GB",
    "sg:address":"3 Kensington High Street",
    "sg:city":"London",
    "sg:classifiers":[
        {
            "category":"Personal",
            "subcategory":"Beauty Salon",
            "type":"Services"
        }
    ],
    "sg:phone":"+44 20 7938 3888",
    "sg:postcode":"W8 5ED",
    "sg:province":"Greater London",
    "sg:tags":[
        "unisex",
        "hairdresser"
    ],
    "wof:name":"Shemale Hair & Beauty Salon",
    "wof:placetype":"venue"
},
  "geometry": {"coordinates":[-0.1902599931,51.5022010803],"type":"Point"}
}