{
  "type": "Feature",
  "properties": {
    "iso:country":"GB",
    "sg:address":"Pentre Rd, St Clears",
    "sg:city":"Carmarthen",
    "sg:classifiers":[
        {
            "category":"Arena",
            "subcategory":"Sports Club",
            "type":"Entertainment"
        }
    ],
    "sg:postcode":"SA33 4AA",
    "sg:province":"Carmarthenshire",
    "wof:name":"St. Clears Rugby Club",
    "wof:placetype":"venue"
},
  "geometry": {"coordinates":[-4.496358,51.819958],"type":"Point"}
}