{
  "type": "Feature",
  "properties": {
    "addr:full":"East Hanningfield Rd Chelmsford Essex CM2 7TP",
    "addr:postcode":"cm2 7tp",
    "addr:street":"East Hanningfield Rd",
    "iso:country":"GB",
    "sg:address":"East Hanningfield Rd",
    "sg:city":"Chelmsford",
    "sg:classifiers":[
        {
            "category":"Social Services",
            "subcategory":"Job Training",
            "type":"Services"
        }
    ],
    "sg:phone":"+44 1245 478634",
    "sg:postcode":"CM2 7TP",
    "sg:province":"Essex",
    "sg:tags":[
        "engineering",
        "marine"
    ],
    "wof:name":"C P Systems (Southampton) Ltd",
    "wof:placetype":"venue"
},
  "geometry": {"coordinates":[0.541455,51.69751],"type":"Point"}
}