{
  "type": "Feature",
  "properties": {
    "addr:full":"Legion House, 838 Uxbridge Road Hayes Greater London UB4 0RP",
    "addr:housenumber":"838",
    "addr:postcode":"ub4 0rp",
    "addr:street":"Uxbridge Road",
    "iso:country":"GB",
    "sg:address":"Legion House, 838 Uxbridge Road",
    "sg:city":"Hayes",
    "sg:classifiers":[
        {
            "category":"Shopping",
            "subcategory":"News",
            "type":"Retail Goods"
        }
    ],
    "sg:phone":"+44 20 8848 3701",
    "sg:postcode":"UB4 0RP",
    "sg:province":"Greater London",
    "sg:tags":[
        "newsagent"
    ],
    "wof:name":"Kenneth Balfour Ltd.",
    "wof:placetype":"venue"
},
  "geometry": {"coordinates":[-0.415369,51.520592],"type":"Point"}
}