{
  "type": "Feature",
  "properties": {
    "iso:country":"GB",
    "sg:address":"Flat 3 Brick Lane, High Street",
    "sg:city":"Henfield",
    "sg:classifiers":[
        {
            "category":"Home & Garden",
            "subcategory":"Hardware",
            "type":"Retail Goods"
        }
    ],
    "sg:phone":"+44 1273 492388",
    "sg:postcode":"BN5 9DB",
    "sg:province":"West Sussex",
    "wof:name":"Hamfelds Ltd.",
    "wof:placetype":"venue"
},
  "geometry": {"coordinates":[-0.272289,50.931419],"type":"Point"}
}