{
  "type": "Feature",
  "properties": {
    "addr:full":"1 Hunters Mead Badminton Gloucestershire GL9 1BL",
    "addr:housenumber":"1",
    "addr:postcode":"gl9 1bl",
    "addr:street":"Hunters Mead",
    "iso:country":"GB",
    "sg:address":"1 Hunters Mead",
    "sg:city":"Badminton",
    "sg:classifiers":[
        {
            "category":"Professional",
            "subcategory":"Management & Consulting",
            "type":"Services"
        }
    ],
    "sg:phone":"+44 1454 238388",
    "sg:postcode":"GL9 1BL",
    "sg:province":"Gloucestershire",
    "sg:tags":[
        "consultant",
        "business"
    ],
    "wof:name":"Genesis",
    "wof:placetype":"venue"
},
  "geometry": {"coordinates":[-2.318641901,51.5807266235],"type":"Point"}
}