{
  "type": "Feature",
  "properties": {
    "iso:country":"GB",
    "sg:address":"70 Webster Gardens, Ealing",
    "sg:city":"London",
    "sg:classifiers":[
        {
            "category":"Freight",
            "type":"Transportation"
        }
    ],
    "sg:phone":"+44 20 8567 4456",
    "sg:postcode":"W5 5NH",
    "sg:province":"Greater London",
    "sg:tags":[
        "forwarders"
    ],
    "wof:name":"M I S Shipping Ltd.",
    "wof:placetype":"venue"
},
  "geometry": {"coordinates":[-0.303288,51.508915],"type":"Point"}
}