{
  "type": "Feature",
  "properties": {
    "addr:full":"Cabus Nook Lane, Winmarleigh, Garstang Preston Lancashire PR3 1AA",
    "addr:postcode":"garstang;pr3 1aa",
    "addr:street":"Nook Lane",
    "iso:country":"GB",
    "sg:address":"Cabus Nook Lane, Winmarleigh, Garstang",
    "sg:city":"Preston",
    "sg:classifiers":[
        {
            "category":"Recreation",
            "subcategory":"Campground",
            "type":"Entertainment"
        }
    ],
    "sg:phone":"+44 1995 606200",
    "sg:postcode":"PR3 1AA",
    "sg:province":"Lancashire",
    "sg:tags":[
        "caravan",
        "park"
    ],
    "wof:name":"Smithy Caravan Park",
    "wof:placetype":"venue"
},
  "geometry": {"coordinates":[-2.7804000378,53.924041748],"type":"Point"}
}