{
  "type": "Feature",
  "properties": {
    "iso:country":"GB",
    "sg:address":"50 High Street",
    "sg:city":"Heathfield",
    "sg:classifiers":[
        {
            "category":"Health Services",
            "subcategory":"Optometrist",
            "type":"Services"
        }
    ],
    "sg:postcode":"TN21 8JB",
    "sg:province":"East Sussex",
    "sg:tags":[
        "optician"
    ],
    "wof:name":"Robert Pople Opticians",
    "wof:placetype":"venue"
},
  "geometry": {"coordinates":[0.250111,50.971329],"type":"Point"}
}