{
  "type": "Feature",
  "properties": {
    "iso:country":"GB",
    "sg:address":"Acton Street",
    "sg:city":"Nottingham",
    "sg:classifiers":[
        {
            "category":"Professional",
            "subcategory":"Printing & Photocopies",
            "type":"Services"
        }
    ],
    "sg:phone":"+44 115 972 4941",
    "sg:postcode":"NG10 1FT",
    "sg:province":"Derbyshire",
    "sg:tags":[
        "embroiderer"
    ],
    "wof:name":"Long Eaton Embroiderers",
    "wof:placetype":"venue"
},
  "geometry": {"coordinates":[-1.266649,52.890209],"type":"Point"}
}