{
  "type": "Feature",
  "properties": {
    "iso:country":"GB",
    "sg:address":"Parc-y-bore, Puncheston",
    "sg:city":"Haverfordwest",
    "sg:classifiers":[
        {
            "category":"Farming",
            "subcategory":"Livestock Farm",
            "type":"Manufacturing & Wholesale Goods"
        }
    ],
    "sg:postcode":"SA62 5RW",
    "sg:province":"Pembrokeshire",
    "sg:tags":[
        "others"
    ],
    "wof:name":"Dylan M & K Lewis",
    "wof:placetype":"venue"
},
  "geometry": {"coordinates":[-4.899444,51.930275],"type":"Point"}
}