{
  "type": "Feature",
  "properties": {
    "iso:country":"GB",
    "sg:address":"35 Minshull New Road",
    "sg:city":"Crewe",
    "sg:classifiers":[
        {
            "category":"Food & Beverages",
            "subcategory":"Meat & Fish",
            "type":"Retail Goods"
        }
    ],
    "sg:phone":"+44 1270 505560",
    "sg:postcode":"CW1 3PE",
    "sg:province":"Cheshire",
    "sg:tags":[
        "chip"
    ],
    "wof:name":"Fishy Business",
    "wof:placetype":"venue"
},
  "geometry": {"coordinates":[-2.4673728943,53.1029167175],"type":"Point"}
}