{
  "type": "Feature",
  "properties": {
    "addr:full":"Hutton Moor Farm, Hutton Conyers Ripon North Yorkshire HG4 5LZ",
    "addr:postcode":"hg4 5lz",
    "addr:street":"Hutton Moor Farm Hutton",
    "iso:country":"GB",
    "sg:address":"Hutton Moor Farm, Hutton Conyers",
    "sg:city":"Ripon",
    "sg:classifiers":[
        {
            "category":"Farming",
            "subcategory":"Livestock Farm",
            "type":"Manufacturing & Wholesale Goods"
        }
    ],
    "sg:phone":"+44 1765 640525",
    "sg:postcode":"HG4 5LZ",
    "sg:province":"North Yorkshire",
    "sg:tags":[
        "others"
    ],
    "wof:name":"R A Wise & Sons",
    "wof:placetype":"venue"
},
  "geometry": {"coordinates":[-1.5147240162,54.1440353394],"type":"Point"}
}