{
  "type": "Feature",
  "properties": {
    "iso:country":"GB",
    "sg:address":"195 Normanton Rd",
    "sg:city":"Derby",
    "sg:classifiers":[
        {
            "category":"Real Estate",
            "subcategory":"Real Estate Operator",
            "type":"Services"
        }
    ],
    "sg:phone":"+44 1332 743774",
    "sg:postcode":"DE23 6US",
    "sg:province":"Derbyshire",
    "sg:tags":[
        "letting",
        "agent"
    ],
    "wof:name":"Derby Commercials",
    "wof:placetype":"venue"
},
  "geometry": {"coordinates":[-1.476518,52.912392],"type":"Point"}
}