{
  "type": "Feature",
  "properties": {
    "addr:full":"64-68 Camden High Street, Camden London Greater London NW1 0LT",
    "addr:housenumber":"64-68",
    "addr:postcode":"nw1 0lt",
    "addr:street":"Camden High Street",
    "iso:country":"GB",
    "sg:address":"64-68 Camden High Street, Camden",
    "sg:city":"London",
    "sg:classifiers":[
        {
            "category":"Communications",
            "type":"Services"
        }
    ],
    "sg:phone":"+44 20 7419 6355",
    "sg:postcode":"NW1 0LT",
    "sg:province":"Greater London",
    "sg:tags":[
        "audio-visual"
    ],
    "wof:name":"Renaissance Productions Ltd.",
    "wof:placetype":"venue"
},
  "geometry": {"coordinates":[-0.137392,51.537956],"type":"Point"}
}