{
  "type": "Feature",
  "properties": {
    "addr:full":"Willis House, Flowers Hill, Brislington Bristol City of Bristol BS4 5JJ",
    "addr:postcode":"bs4 5jj",
    "addr:street":"Flowers Hill",
    "iso:country":"GB",
    "sg:address":"Willis House, Flowers Hill, Brislington",
    "sg:city":"Bristol",
    "sg:classifiers":[
        {
            "category":"Home & Garden",
            "subcategory":"Hardware",
            "type":"Retail Goods"
        }
    ],
    "sg:phone":"+44 117 971 1451",
    "sg:postcode":"BS4 5JJ",
    "sg:province":"City of Bristol",
    "sg:tags":[
        "compressor",
        "air"
    ],
    "wof:name":"Garafit Services Ltd.",
    "wof:placetype":"venue"
},
  "geometry": {"coordinates":[-2.5425701141,51.4296226501],"type":"Point"}
}