{
  "type": "Feature",
  "properties": {
    "iso:country":"GB",
    "sg:address":"Lansbury Avenue",
    "sg:city":"Chesterfield",
    "sg:classifiers":[
        {
            "category":"Social Services",
            "subcategory":"Adult Care",
            "type":"Services"
        }
    ],
    "sg:phone":"+44 1246 472749",
    "sg:postcode":"S43 3AQ",
    "sg:province":"Derbyshire",
    "sg:tags":[
        "housing",
        "sheltered"
    ],
    "wof:name":"Lansbury Avenue Sheltered Housing",
    "wof:placetype":"venue"
},
  "geometry": {"coordinates":[-1.324489,53.276009],"type":"Point"}
}