{
  "type": "Feature",
  "properties": {
    "addr:full":"Unit 4, Heol-ty-gwyn Industrial Estate Maesteg Bridgend CF34 0BQ",
    "addr:housenumber":"unit 4",
    "addr:postcode":"cf34 0bq",
    "addr:street":"Heol-Ty-Gwyn Industrial Estate",
    "iso:country":"GB",
    "sg:address":"Unit 4, Heol-ty-gwyn Industrial Estate",
    "sg:city":"Maesteg",
    "sg:classifiers":[
        {
            "category":"Recreation",
            "subcategory":"Dog Park",
            "type":"Entertainment"
        }
    ],
    "sg:phone":"+44 1656 736333",
    "sg:postcode":"CF34 0BQ",
    "sg:province":"Bridgend",
    "wof:name":"The Doghouse Groomers",
    "wof:placetype":"venue"
},
  "geometry": {"coordinates":[-3.665857,51.614807],"type":"Point"}
}