{
  "type": "Feature",
  "properties": {
    "addr:full":"Unit D Arena Business Centre, Ashfield Road London Greater London N4 1NY",
    "addr:housenumber":"unit d",
    "addr:postcode":"n4 1ny",
    "addr:street":"Arena Business Centre Ashfield Road",
    "iso:country":"GB",
    "sg:address":"Unit D Arena Business Centre, Ashfield Road",
    "sg:city":"London",
    "sg:classifiers":[
        {
            "category":"Shopping",
            "subcategory":"Stationery & Office Supplies",
            "type":"Retail Goods"
        }
    ],
    "sg:phone":"+44 20 8880 2211",
    "sg:postcode":"N4 1NY",
    "sg:province":"Greater London",
    "sg:tags":[
        "equipment",
        "furniture"
    ],
    "wof:name":"Kayline 2000 Ltd.",
    "wof:placetype":"venue"
},
  "geometry": {"coordinates":[-0.09069,51.57819],"type":"Point"}
}