{
  "type": "Feature",
  "properties": {
    "iso:country":"GB",
    "sg:address":"Montague Road, Hanwell",
    "sg:city":"London",
    "sg:classifiers":[
        {
            "category":"Manufacturing",
            "subcategory":"Metals",
            "type":"Manufacturing & Wholesale Goods"
        }
    ],
    "sg:phone":"+44 20 8884 0239",
    "sg:postcode":"W7 3UR",
    "sg:province":"Greater London",
    "sg:tags":[
        "work",
        "sheet"
    ],
    "wof:name":"Boldvale Engineering Ltd.",
    "wof:placetype":"venue"
},
  "geometry": {"coordinates":[-0.334424,51.506676],"type":"Point"}
}