{
  "type": "Feature",
  "properties": {
    "iso:country":"GB",
    "sg:address":"Dairy House Farm, Bristol Road",
    "sg:city":"Wells",
    "sg:classifiers":[
        {
            "category":"Home & Garden",
            "subcategory":"Garden Supply",
            "type":"Retail Goods"
        },
        {
            "category":"Farming",
            "subcategory":"Farm",
            "type":"Manufacturing & Wholesale Goods"
        }
    ],
    "sg:phone":"+44 1749 673503",
    "sg:postcode":"BA5 3AA",
    "sg:province":"Somerset",
    "sg:tags":[
        "mixed",
        "bulb",
        "crop",
        "grower"
    ],
    "wof:name":"George R A Mullins",
    "wof:placetype":"venue"
},
  "geometry": {"coordinates":[-2.646985054,51.2216682434],"type":"Point"}
}