{
  "type": "Feature",
  "properties": {
    "addr:full":"Common Lane, Corley Moor Coventry Warwickshire CV7 8AQ",
    "addr:postcode":"cv7 8aq",
    "addr:street":"Common Lane",
    "iso:country":"GB",
    "sg:address":"Common Lane, Corley Moor",
    "sg:city":"Coventry",
    "sg:classifiers":[
        {
            "category":"Bars & Pubs",
            "type":"Food & Drink"
        }
    ],
    "sg:phone":"+44 1676 540241",
    "sg:postcode":"CV7 8AQ",
    "sg:province":"Warwickshire",
    "sg:tags":[
        "pubs",
        "inn"
    ],
    "wof:name":"The Bull & Butcher",
    "wof:placetype":"venue"
},
  "geometry": {"coordinates":[-1.558937,52.464916],"type":"Point"}
}