{
  "type": "Feature",
  "properties": {
    "addr:full":"8 Cotton Lane Preston Lancashire PR2 1JR",
    "addr:housenumber":"8",
    "addr:postcode":"pr2 1jr",
    "addr:street":"Cotton Lane",
    "iso:country":"GB",
    "sg:address":"8 Cotton Lane",
    "sg:city":"Preston",
    "sg:classifiers":[
        {
            "category":"Building & Trades",
            "subcategory":"Construction",
            "type":"Services"
        }
    ],
    "sg:postcode":"PR2 1JR",
    "sg:province":"Lancashire",
    "sg:tags":[
        "builder"
    ],
    "wof:name":"Jack Smith (Builders) Ltd.",
    "wof:placetype":"venue"
},
  "geometry": {"coordinates":[-2.772727,53.764423],"type":"Point"}
}