{
  "type": "Feature",
  "properties": {
    "iso:country":"GB",
    "sg:address":"Unit 11 Lady Ann Mills, Lady Ann Road",
    "sg:city":"Batley",
    "sg:classifiers":[
        {
            "category":"Manufacturing",
            "subcategory":"Furniture",
            "type":"Manufacturing & Wholesale Goods"
        }
    ],
    "sg:phone":"+44 1924 445333",
    "sg:postcode":"WF17 0PS",
    "sg:province":"West Yorkshire",
    "sg:tags":[
        "mnfr",
        "upholsterer"
    ],
    "wof:name":"Ashleigh Designs",
    "wof:placetype":"venue"
},
  "geometry": {"coordinates":[-1.654499,53.726421],"type":"Point"}
}