{
  "type": "Feature",
  "properties": {
    "addr:full":"9 Ascot Park Estate, Lenton Street, Sandiacre Nottingham Derbyshire NG10 5DL",
    "addr:housenumber":"9",
    "addr:postcode":"ng10 5dl",
    "addr:street":"Ascot Park Estate Lenton Street",
    "iso:country":"GB",
    "sg:address":"9 Ascot Park Estate, Lenton Street, Sandiacre",
    "sg:city":"Nottingham",
    "sg:classifiers":[
        {
            "category":"Manufacturing",
            "subcategory":"Rubber & Plastics",
            "type":"Manufacturing & Wholesale Goods"
        }
    ],
    "sg:phone":"+44 115 939 0716",
    "sg:postcode":"NG10 5DL",
    "sg:province":"Derbyshire",
    "sg:tags":[
        "injection",
        "moulding"
    ],
    "sg:website":"http://www.hpm.com",
    "wof:name":"H P M Ltd",
    "wof:placetype":"venue"
},
  "geometry": {"coordinates":[-1.285829,52.928791],"type":"Point"}
}