{
  "type": "Feature",
  "properties": {
    "addr:full":"2a Elliott Road Birmingham West Midlands B29 6LA",
    "addr:housenumber":"2a",
    "addr:postcode":"b29 6la",
    "addr:street":"Elliott Road",
    "iso:country":"GB",
    "sg:address":"2a Elliott Road",
    "sg:city":"Birmingham",
    "sg:classifiers":[
        {
            "category":"Cafe",
            "type":"Food & Drink"
        }
    ],
    "sg:postcode":"B29 6LA",
    "sg:province":"West Midlands",
    "sg:tags":[
        "tea",
        "room"
    ],
    "wof:name":"Ivy's Cafe",
    "wof:placetype":"venue"
},
  "geometry": {"coordinates":[-1.9381150007,52.4404602051],"type":"Point"}
}