{
  "type": "Feature",
  "properties": {
    "iso:country":"GB",
    "sg:address":"4 South Road",
    "sg:city":"Watchet",
    "sg:classifiers":[
        {
            "category":"Insurance",
            "subcategory":"Insurance Agent",
            "type":"Services"
        }
    ],
    "sg:postcode":"TA23 0DA",
    "sg:province":"Somerset",
    "sg:tags":[
        "broker"
    ],
    "wof:name":"Town & Country Insurance",
    "wof:placetype":"venue"
},
  "geometry": {"coordinates":[-3.3287250996,51.1801528931],"type":"Point"}
}