{
  "type": "Feature",
  "properties": {
    "addr:full":"1 Wainscott Road, Wainscott Rochester Kent ME2 4LA",
    "addr:housenumber":"1",
    "addr:postcode":"me2 4la",
    "addr:street":"Wainscott Road",
    "iso:country":"GB",
    "sg:address":"1 Wainscott Road, Wainscott",
    "sg:city":"Rochester",
    "sg:classifiers":[
        {
            "category":"Food & Beverages",
            "subcategory":"Meat & Fish",
            "type":"Retail Goods"
        },
        {
            "category":"Food & Beverages",
            "subcategory":"Groceries & Convenience Stores",
            "type":"Retail Goods"
        }
    ],
    "sg:phone":"+44 1634 717587",
    "sg:postcode":"ME2 4LA",
    "sg:province":"Kent",
    "sg:tags":[
        "shop",
        "chip"
    ],
    "wof:name":"Golden Fish Bar",
    "wof:placetype":"venue"
},
  "geometry": {"coordinates":[0.5129899979,51.4125289917],"type":"Point"}
}