{
  "type": "Feature",
  "properties": {
    "addr:full":"80 Harley St West End Hampshire W1N 1AE",
    "addr:housenumber":"80",
    "addr:postcode":"w1n 1ae",
    "addr:street":"Harley St",
    "iso:country":"GB",
    "sg:address":"80 Harley St",
    "sg:city":"West End",
    "sg:classifiers":[
        {
            "category":"Health Services",
            "subcategory":"Doctor",
            "type":"Services"
        }
    ],
    "sg:phone":"+44 20 7580 3664",
    "sg:postcode":"W1N 1AE",
    "sg:province":"Hampshire",
    "sg:tags":[
        "practitioners"
    ],
    "wof:name":"Shah, N S",
    "wof:placetype":"venue"
},
  "geometry": {"coordinates":[-0.147277,51.520214],"type":"Point"}
}