{
  "type": "Feature",
  "properties": {
    "addr:full":"Unit 3 North Berwick East Lothian EH39 5NB",
    "addr:housenumber":"unit 3",
    "addr:postcode":"eh39 5nb",
    "addr:street":"North Berwick",
    "iso:country":"GB",
    "sg:address":"Unit 3",
    "sg:city":"North Berwick",
    "sg:classifiers":[
        {
            "category":"Professional",
            "subcategory":"Printing & Photocopies",
            "type":"Services"
        }
    ],
    "sg:phone":"+44 1620 892767",
    "sg:postcode":"EH39 5NB",
    "sg:province":"East Lothian",
    "sg:tags":[
        "printer"
    ],
    "wof:name":"Tantallon Press Ltd.",
    "wof:placetype":"venue"
},
  "geometry": {"coordinates":[-2.7170538902,56.058555603],"type":"Point"}
}