{
  "type": "Feature",
  "properties": {
    "addr:full":"Main Street, Greenodd Ulverston Cumbria LA12 7QZ",
    "addr:postcode":"la12 7qz",
    "addr:street":"Main Street",
    "iso:country":"GB",
    "sg:address":"Main Street, Greenodd",
    "sg:city":"Ulverston",
    "sg:classifiers":[
        {
            "category":"Food & Beverages",
            "subcategory":"Bakery",
            "type":"Retail Goods"
        }
    ],
    "sg:phone":"+44 1229 861265",
    "sg:postcode":"LA12 7QZ",
    "sg:province":"Cumbria",
    "sg:tags":[
        "baker"
    ],
    "wof:name":"Judith & Beverly Law Law",
    "wof:placetype":"venue"
},
  "geometry": {"coordinates":[-3.0923540592,54.1967315674],"type":"Point"}
}