{
  "type": "Feature",
  "properties": {
    "iso:country":"GB",
    "sg:address":"Instrument Works, Edward Road",
    "sg:city":"Coulsdon",
    "sg:classifiers":[
        {
            "category":"Health Services",
            "subcategory":"Hospital",
            "type":"Services"
        },
        {
            "category":"Professional",
            "subcategory":"Management & Consulting",
            "type":"Services"
        }
    ],
    "sg:phone":"+44 20 8668 2131",
    "sg:postcode":"CR5 2XA",
    "sg:province":"Surrey",
    "sg:tags":[
        "surgical",
        "holding",
        "activity"
    ],
    "wof:name":"ALFRED COX (HOLDINGS) LTD",
    "wof:placetype":"venue"
},
  "geometry": {"coordinates":[-0.139179,51.318924],"type":"Point"}
}