{
  "type": "Feature",
  "properties": {
    "addr:full":"36-37 Featherstone St Clerkenwell Greater London EC1Y 8QZ",
    "addr:housenumber":"36-37",
    "addr:postcode":"ec1y 8qz",
    "addr:street":"Featherstone St",
    "iso:country":"GB",
    "sg:address":"36-37 Featherstone St",
    "sg:city":"Clerkenwell",
    "sg:classifiers":[
        {
            "category":"Real Estate",
            "subcategory":"Architect",
            "type":"Services"
        }
    ],
    "sg:phone":"+44 20 7251 0783",
    "sg:postcode":"EC1Y 8QZ",
    "sg:province":"Greater London",
    "wof:name":"Paul Hyett Architects",
    "wof:placetype":"venue"
},
  "geometry": {"coordinates":[-0.088195,51.524746],"type":"Point"}
}