{
  "type": "Feature",
  "properties": {
    "addr:full":"41 Portway Frome Somerset BA11 1QS",
    "addr:housenumber":"41",
    "addr:postcode":"ba11 1qs",
    "addr:street":"Portway",
    "iso:country":"GB",
    "sg:address":"41 Portway",
    "sg:city":"Frome",
    "sg:classifiers":[
        {
            "category":"Health Services",
            "subcategory":"Dentist",
            "type":"Services"
        }
    ],
    "sg:postcode":"BA11 1QS",
    "sg:province":"Somerset",
    "wof:name":"Portway Dental Practice",
    "wof:placetype":"venue"
},
  "geometry": {"coordinates":[-2.3143839836,51.2276573181],"type":"Point"}
}