{
  "type": "Feature",
  "properties": {
    "addr:full":"Unit 42 Monument Industrial Park, Chalgro Oxford Oxfordshire OX44 7RW",
    "addr:housenumber":"unit 42",
    "addr:postcode":"ox44 7rw",
    "addr:street":"Monument Industrial Park",
    "iso:country":"GB",
    "sg:address":"Unit 42 Monument Industrial Park, Chalgro",
    "sg:city":"Oxford",
    "sg:classifiers":[
        {
            "category":"Wholesale",
            "subcategory":"Machinery & Supplies",
            "type":"Manufacturing & Wholesale Goods"
        }
    ],
    "sg:phone":"+44 1865 891466",
    "sg:postcode":"OX44 7RW",
    "sg:province":"Oxfordshire",
    "sg:tags":[
        "bottling",
        "related",
        "equipment"
    ],
    "wof:name":"Cap Coder Ltd",
    "wof:placetype":"venue"
},
  "geometry": {"coordinates":[-1.0649600029,51.6698188782],"type":"Point"}
}