{
  "type": "Feature",
  "properties": {
    "addr:full":"Room 39 Atlantic House, London Gatwick Airport Gatwick Surrey RH6 0PU",
    "addr:housenumber":"39",
    "addr:postcode":"rh6 0pu",
    "addr:street":"Airport Gatwick",
    "iso:country":"GB",
    "sg:address":"Room 39 Atlantic House, London Gatwick Airport",
    "sg:city":"Gatwick",
    "sg:classifiers":[
        {
            "category":"Professional",
            "type":"Services"
        }
    ],
    "sg:phone":"+44 1293 544333",
    "sg:postcode":"RH6 0PU",
    "sg:province":"Surrey",
    "sg:tags":[
        "aircraft",
        "maintenance"
    ],
    "wof:name":"Koninklijke Luchtvaart Maatschappij N V",
    "wof:placetype":"venue"
},
  "geometry": {"coordinates":[-0.1771389991,51.1666946411],"type":"Point"}
}