{
  "type": "Feature",
  "properties": {
    "iso:country":"GB",
    "sg:address":"Old Coach Rd, Bilborough",
    "sg:city":"Nottingham",
    "sg:classifiers":[
        {
            "category":"Personal",
            "type":"Services"
        }
    ],
    "sg:postcode":"NG8 5BY",
    "sg:province":"Nottinghamshire",
    "sg:tags":[
        "delivery"
    ],
    "wof:name":"Smith,Stephen,",
    "wof:placetype":"venue"
},
  "geometry": {"coordinates":[-1.1827499866,52.9705505371],"type":"Point"}
}