{
  "type": "Feature",
  "properties": {
    "iso:country":"GB",
    "sg:address":"Siemens House, Oldbury",
    "sg:city":"Bracknell",
    "sg:classifiers":[
        {
            "category":"Professional",
            "subcategory":"Computer Services",
            "type":"Services"
        }
    ],
    "sg:phone":"+44 1344 396000",
    "sg:postcode":"RG12 8FZ",
    "sg:province":"Berkshire",
    "sg:tags":[
        "consultant"
    ],
    "wof:name":"Siemens Plc",
    "wof:placetype":"venue"
},
  "geometry": {"coordinates":[-0.76737,51.412308],"type":"Point"}
}