{
  "type": "Feature",
  "properties": {
    "addr:full":"84-85 Crystal Peaks Shopping Centre, Eckington Way Sheffield Derbyshire S19 6PQ",
    "addr:housenumber":"84-85",
    "addr:postcode":"s19 6pq",
    "addr:street":"Crystal Peaks Shopping;Eckington Way",
    "iso:country":"GB",
    "sg:address":"84-85 Crystal Peaks Shopping Centre, Eckington Way",
    "sg:city":"Sheffield",
    "sg:classifiers":[
        {
            "category":"Shopping",
            "subcategory":"Pets & Pet Supplies",
            "type":"Retail Goods"
        }
    ],
    "sg:phone":"+44 114 251 0897",
    "sg:postcode":"S19 6PQ",
    "sg:province":"Derbyshire",
    "sg:tags":[
        "food"
    ],
    "wof:name":"Peak Pet Foods",
    "wof:placetype":"venue"
},
  "geometry": {"coordinates":[-1.464544,53.38311],"type":"Point"}
}