{
  "type": "Feature",
  "properties": {
    "iso:country":"GB",
    "sg:address":"Unit 26 Freightliner Road, Brighton Street Industrial Estat",
    "sg:city":"Hull",
    "sg:classifiers":[
        {
            "category":"Food & Beverages",
            "subcategory":"Bakery",
            "type":"Retail Goods"
        },
        {
            "category":"Food & Beverages",
            "subcategory":"Supermarket",
            "type":"Retail Goods"
        }
    ],
    "sg:phone":"+44 1482 588088",
    "sg:postcode":"HU3 4UN",
    "sg:province":"East Riding of Yorkshire",
    "sg:tags":[
        "frozen",
        "confectionery"
    ],
    "wof:name":"Chaucer Foods Ltd.",
    "wof:placetype":"venue"
},
  "geometry": {"coordinates":[-0.3794029951,53.7302627563],"type":"Point"}
}