{
  "type": "Feature",
  "properties": {
    "addr:full":"Main Street, Grove Wantage Berkshire OX12 7JT",
    "addr:postcode":"ox12 7jt",
    "addr:street":"Main Street Grove",
    "iso:country":"GB",
    "sg:address":"Main Street, Grove",
    "sg:city":"Wantage",
    "sg:classifiers":[
        {
            "category":"Bars & Pubs",
            "type":"Food & Drink"
        },
        {
            "category":"Community Center",
            "subcategory":"Social",
            "type":"Public Place"
        }
    ],
    "sg:phone":"+44 1235 763860",
    "sg:postcode":"OX12 7JT",
    "sg:province":"Berkshire",
    "sg:tags":[
        "pubs",
        "house",
        "inn",
        "activity"
    ],
    "wof:name":"The Bell",
    "wof:placetype":"venue"
},
  "geometry": {"coordinates":[-1.4236390591,51.5917472839],"type":"Point"}
}