{
  "type": "Feature",
  "properties": {
    "addr:full":"Unit A, The Enterprise Centre Beckenham Kent BR3 1LH",
    "addr:housenumber":"unit a the enterprise centre",
    "addr:postcode":"br3 1lh",
    "iso:country":"GB",
    "sg:address":"Unit A, The Enterprise Centre",
    "sg:city":"Beckenham",
    "sg:classifiers":[
        {
            "category":"Retail",
            "subcategory":"Repair Shop",
            "type":"Services"
        }
    ],
    "sg:postcode":"BR3 1LH",
    "sg:province":"Kent",
    "sg:tags":[
        "maintenance"
    ],
    "wof:name":"Southern Construction Ltd.",
    "wof:placetype":"venue"
},
  "geometry": {"coordinates":[-0.0278350003,51.4071617126],"type":"Point"}
}