{
  "type": "Feature",
  "properties": {
    "addr:full":"32 Croft Holm Moreton-in-marsh Gloucestershire GL56 0JH",
    "addr:housenumber":"32",
    "addr:postcode":"gl56 0jh",
    "addr:street":"Croft Holm",
    "iso:country":"GB",
    "sg:address":"32 Croft Holm",
    "sg:city":"Moreton-in-marsh",
    "sg:classifiers":[
        {
            "category":"Cafe",
            "type":"Food & Drink"
        }
    ],
    "sg:phone":"+44 1608 651881",
    "sg:postcode":"GL56 0JH",
    "sg:province":"Gloucestershire",
    "sg:tags":[
        "tea",
        "room"
    ],
    "wof:name":"Cafe Dijon",
    "wof:placetype":"venue"
},
  "geometry": {"coordinates":[-1.695832,51.987793],"type":"Point"}
}