{
  "type": "Feature",
  "properties": {
    "iso:country":"GB",
    "sg:address":"102 Reads Avenue",
    "sg:city":"Blackpool",
    "sg:classifiers":[
        {
            "category":"Travel",
            "subcategory":"Hotels & Motels",
            "type":"Entertainment"
        }
    ],
    "sg:phone":"+44 1253 751293",
    "sg:postcode":"FY1 4JJ",
    "sg:province":"Lancashire",
    "wof:name":"Presidente Hotel",
    "wof:placetype":"venue"
},
  "geometry": {"coordinates":[-3.042204,53.814465],"type":"Point"}
}