{
  "type": "Feature",
  "properties": {
    "iso:country":"GB",
    "sg:address":"Care Of Army & Navy Stores, 64 High Street",
    "sg:city":"Bromley",
    "sg:classifiers":[
        {
            "category":"Shopping",
            "subcategory":"Clothing, Apparel, & Fashions",
            "type":"Retail Goods"
        }
    ],
    "sg:phone":"+44 20 8466 5137",
    "sg:postcode":"BR1 1EN",
    "sg:province":"Kent",
    "sg:tags":[
        "shop"
    ],
    "wof:name":"Jaeger Ladieswear",
    "wof:placetype":"venue"
},
  "geometry": {"coordinates":[0.01536,51.402],"type":"Point"}
}