{
  "type": "Feature",
  "properties": {
    "iso:country":"GB",
    "sg:address":"20 Lower High Street",
    "sg:city":"Stourbridge",
    "sg:classifiers":[
        {
            "category":"Utilities",
            "subcategory":"Natural Gas",
            "type":"Services"
        }
    ],
    "sg:phone":"+44 1384 372246",
    "sg:postcode":"DY8 1TA",
    "sg:province":"Staffordshire",
    "sg:tags":[
        "supplier"
    ],
    "wof:name":"Gasway (Stourbridge) Ltd.",
    "wof:placetype":"venue"
},
  "geometry": {"coordinates":[-2.149803,52.459587],"type":"Point"}
}