{
  "type": "Feature",
  "properties": {
    "addr:full":"Essex Ho, 9-11 Mildmay Rd Romford Essex RM7 7DA",
    "addr:housenumber":"9-11",
    "addr:postcode":"rm7 7da",
    "addr:street":"Mildmay Rd",
    "iso:country":"GB",
    "sg:address":"Essex Ho, 9-11 Mildmay Rd",
    "sg:city":"Romford",
    "sg:classifiers":[
        {
            "category":"Building & Trades",
            "subcategory":"Cleaning & Sanitation",
            "type":"Services"
        }
    ],
    "sg:postcode":"RM7 7DA",
    "sg:province":"Essex",
    "sg:tags":[
        "commercial"
    ],
    "wof:name":"B S W Contracts Ltd",
    "wof:placetype":"venue"
},
  "geometry": {"coordinates":[0.171299994,51.5778884888],"type":"Point"}
}