{
  "type": "Feature",
  "properties": {
    "iso:country":"GB",
    "sg:address":"Gadlas, Dudleston Heath",
    "sg:city":"Ellesmere",
    "sg:classifiers":[
        {
            "category":"Professional",
            "subcategory":"Detective & Security Services",
            "type":"Services"
        }
    ],
    "sg:phone":"+44 1691 690545",
    "sg:postcode":"SY12 9DY",
    "sg:province":"Shropshire",
    "wof:name":"Castle Security Services",
    "wof:placetype":"venue"
},
  "geometry": {"coordinates":[-2.9737188816,52.9377441406],"type":"Point"}
}