{
  "type": "Feature",
  "properties": {
    "addr:full":"Thorpe Lodge, Yarmouth Rd Norwich Norfolk NR7 0DU",
    "addr:postcode":"nr7 0du",
    "addr:street":"Yarmouth Rd",
    "iso:country":"GB",
    "sg:address":"Thorpe Lodge, Yarmouth Rd",
    "sg:city":"Norwich",
    "sg:classifiers":[
        {
            "category":"Professional",
            "subcategory":"Computer Services",
            "type":"Services"
        }
    ],
    "sg:phone":"+44 1603 700758",
    "sg:postcode":"NR7 0DU",
    "sg:province":"Norfolk",
    "sg:tags":[
        "consultant"
    ],
    "wof:name":"CFM",
    "wof:placetype":"venue"
},
  "geometry": {"coordinates":[1.3301930428,52.6265335083],"type":"Point"}
}