{
  "type": "Feature",
  "properties": {
    "addr:full":"East Moors Industrial Estate Cardiff Cardiff CF24 5JR",
    "addr:postcode":"cf24 5jr",
    "addr:street":"East Moors Industrial Estate",
    "iso:country":"GB",
    "sg:address":"East Moors Industrial Estate",
    "sg:city":"Cardiff",
    "sg:classifiers":[
        {
            "category":"Manufacturing",
            "subcategory":"Metals",
            "type":"Manufacturing & Wholesale Goods"
        }
    ],
    "sg:postcode":"CF24 5JR",
    "sg:province":"Cardiff",
    "sg:tags":[
        "merchant"
    ],
    "wof:name":"Project Hardware Ltd.",
    "wof:placetype":"venue"
},
  "geometry": {"coordinates":[-3.1467890739,51.4750328064],"type":"Point"}
}