{
  "type": "Feature",
  "properties": {
    "iso:country":"GB",
    "sg:address":"31 Hillside Road, Ackworth",
    "sg:city":"Pontefract",
    "sg:classifiers":[
        {
            "category":"Building & Trades",
            "subcategory":"Construction",
            "type":"Services"
        }
    ],
    "sg:postcode":"WF7 7NJ",
    "sg:province":"West Yorkshire",
    "sg:tags":[
        "builder"
    ],
    "wof:name":"D G Construction & Maintenance",
    "wof:placetype":"venue"
},
  "geometry": {"coordinates":[-1.335199,53.643543],"type":"Point"}
}