{
  "type": "Feature",
  "properties": {
    "iso:country":"GB",
    "sg:address":"Beechenhurst, 145 Menlove Avenue",
    "sg:city":"Liverpool",
    "sg:classifiers":[
        {
            "category":"Education",
            "subcategory":"School",
            "type":"Public Place"
        }
    ],
    "sg:phone":"+44 151 722 3279",
    "sg:postcode":"L18 3EE",
    "sg:province":"Merseyside",
    "sg:tags":[
        "independent",
        "preparatory"
    ],
    "wof:name":"Mary E Blake Ltd.",
    "wof:placetype":"venue"
},
  "geometry": {"coordinates":[-2.9784810543,53.4097747803],"type":"Point"}
}