{
  "type": "Feature",
  "properties": {
    "iso:country":"GB",
    "sg:address":"Old Service Station, Hucknell Rd, Bulwell",
    "sg:city":"Nottingham",
    "sg:classifiers":[
        {
            "category":"Retail",
            "subcategory":"Auto Repair",
            "type":"Services"
        }
    ],
    "sg:phone":"+44 115 927 8465",
    "sg:postcode":"NG5 1BN",
    "sg:province":"Nottinghamshire",
    "sg:tags":[
        "modification",
        "garage"
    ],
    "wof:name":"Nottingham Restoration Services",
    "wof:placetype":"venue"
},
  "geometry": {"coordinates":[-1.15681,52.97456],"type":"Point"}
}