{
  "type": "Feature",
  "properties": {
    "iso:country":"GB",
    "sg:address":"118 Lammas Street",
    "sg:city":"Carmarthen",
    "sg:classifiers":[
        {
            "category":"Shopping",
            "subcategory":"Clothing, Apparel, & Fashions",
            "type":"Retail Goods"
        }
    ],
    "sg:phone":"+44 1267 220123",
    "sg:postcode":"SA31 3AE",
    "sg:province":"Carmarthenshire",
    "sg:tags":[
        "shop"
    ],
    "wof:name":"Peacocks Stores",
    "wof:placetype":"venue"
},
  "geometry": {"coordinates":[-4.30969,51.856377],"type":"Point"}
}