{
  "type": "Feature",
  "properties": {
    "addr:full":"Raikes Road Thornton-cleveleys Lancashire FY5 5LS",
    "addr:postcode":"fy5 5ls",
    "addr:street":"Raikes Road",
    "iso:country":"GB",
    "sg:address":"Raikes Road",
    "sg:city":"Thornton-cleveleys",
    "sg:classifiers":[
        {
            "category":"Sports & Exercise",
            "subcategory":"Stables",
            "type":"Entertainment"
        }
    ],
    "sg:phone":"+44 1253 820235",
    "sg:postcode":"FY5 5LS",
    "sg:province":"Lancashire",
    "sg:tags":[
        "education",
        "equestrian"
    ],
    "wof:name":"Thornton Equestrian Centre",
    "wof:placetype":"venue"
},
  "geometry": {"coordinates":[-2.987757,53.872124],"type":"Point"}
}