{
  "type": "Feature",
  "properties": {
    "addr:full":"442 Hoe St London Greater London E17 9AH",
    "addr:housenumber":"442",
    "addr:postcode":"e17 9ah",
    "addr:street":"Hoe St",
    "iso:country":"GB",
    "sg:address":"442 Hoe St",
    "sg:city":"London",
    "sg:classifiers":[
        {
            "category":"Retail",
            "subcategory":"Laundry & Dry Cleaning",
            "type":"Services"
        }
    ],
    "sg:postcode":"E17 9AH",
    "sg:province":"Greater London",
    "sg:tags":[
        "alteration"
    ],
    "wof:name":"Star Tailors & Dry Cleaners",
    "wof:placetype":"venue"
},
  "geometry": {"coordinates":[-0.015134,51.576118],"type":"Point"}
}