{
  "type": "Feature",
  "properties": {
    "addr:full":"Belgravia House, Well St, Cefn Mawr Wrexham Wrexham LL14 3AE",
    "addr:postcode":"ll14 3ae",
    "addr:street":"Well St;Mawr",
    "iso:country":"GB",
    "sg:address":"Belgravia House, Well St, Cefn Mawr",
    "sg:city":"Wrexham",
    "sg:classifiers":[
        {
            "category":"Professional",
            "subcategory":"Business Services",
            "type":"Services"
        }
    ],
    "sg:phone":"+44 1978 823850",
    "sg:postcode":"LL14 3AE",
    "sg:province":"Wrexham",
    "sg:tags":[
        "bookmaker"
    ],
    "wof:name":"S.C Jones",
    "wof:placetype":"venue"
},
  "geometry": {"coordinates":[-3.0725340843,52.97315979],"type":"Point"}
}