{
  "type": "Feature",
  "properties": {
    "iso:country":"GB",
    "sg:address":"77 Ramsay Avenue, Farnworth",
    "sg:city":"Bolton",
    "sg:classifiers":[
        {
            "category":"Building & Trades",
            "subcategory":"Construction",
            "type":"Services"
        }
    ],
    "sg:phone":"+44 1204 795949",
    "sg:postcode":"BL4 9RA",
    "sg:province":"Lancashire",
    "sg:tags":[
        "surfacing",
        "road"
    ],
    "wof:name":"Ramsay Contractors",
    "wof:placetype":"venue"
},
  "geometry": {"coordinates":[-2.4163229465,53.5448532104],"type":"Point"}
}