{
  "type": "Feature",
  "properties": {
    "addr:full":"104 Wood Street London Greater London E17 3HX",
    "addr:housenumber":"104",
    "addr:postcode":"e17 3hx",
    "addr:street":"Wood Street",
    "iso:country":"GB",
    "sg:address":"104 Wood Street",
    "sg:city":"London",
    "sg:classifiers":[
        {
            "category":"Shopping",
            "subcategory":"Shoes",
            "type":"Retail Goods"
        }
    ],
    "sg:phone":"+44 20 8520 7868",
    "sg:postcode":"E17 3HX",
    "sg:province":"Greater London",
    "sg:tags":[
        "shop"
    ],
    "wof:name":"Agombar's",
    "wof:placetype":"venue"
},
  "geometry": {"coordinates":[-0.004405,51.588474],"type":"Point"}
}