{
  "type": "Feature",
  "properties": {
    "iso:country":"GB",
    "sg:address":"15 Moseley Avenue, Latchford",
    "sg:city":"Warrington",
    "sg:classifiers":[
        {
            "category":"Building & Trades",
            "subcategory":"Construction",
            "type":"Services"
        }
    ],
    "sg:phone":"+44 1925 634559",
    "sg:postcode":"WA4 1NX",
    "sg:province":"Cheshire",
    "sg:tags":[
        "roofing"
    ],
    "wof:name":"John Baker",
    "wof:placetype":"venue"
},
  "geometry": {"coordinates":[-2.551435,53.38308],"type":"Point"}
}