{
  "type": "Feature",
  "properties": {
    "addr:full":"44 Mere St Diss Norfolk IP22 4AG",
    "addr:housenumber":"44",
    "addr:postcode":"ip22 4ag",
    "addr:street":"Mere St",
    "iso:country":"GB",
    "sg:address":"44 Mere St",
    "sg:city":"Diss",
    "sg:classifiers":[
        {
            "category":"Food & Beverages",
            "subcategory":"Meat & Fish",
            "type":"Retail Goods"
        }
    ],
    "sg:postcode":"IP22 4AG",
    "sg:province":"Norfolk",
    "sg:tags":[
        "butcher"
    ],
    "wof:name":"M & M Butchers",
    "wof:placetype":"venue"
},
  "geometry": {"coordinates":[1.108789,52.375263],"type":"Point"}
}