{
  "type": "Feature",
  "properties": {
    "addr:full":"Stanella Cottage, Newtown Road, Awbridge Romsey Hampshire SO51 0GG",
    "addr:postcode":"so51 0gg",
    "addr:street":"Newtown Road",
    "iso:country":"GB",
    "sg:address":"Stanella Cottage, Newtown Road, Awbridge",
    "sg:city":"Romsey",
    "sg:classifiers":[
        {
            "category":"Building & Trades",
            "subcategory":"Construction",
            "type":"Services"
        }
    ],
    "sg:phone":"+44 1794 340035",
    "sg:postcode":"SO51 0GG",
    "sg:province":"Hampshire",
    "sg:tags":[
        "decorator",
        "painter"
    ],
    "wof:name":"Whitelock Michael S Painters & Decorators",
    "wof:placetype":"venue"
},
  "geometry": {"coordinates":[-1.530253,51.013233],"type":"Point"}
}