{
  "type": "Feature",
  "properties": {
    "iso:country":"GB",
    "sg:address":"46 Princes Avenue, Eastham",
    "sg:city":"Wirral",
    "sg:classifiers":[
        {
            "category":"Building & Trades",
            "subcategory":"Construction",
            "type":"Services"
        }
    ],
    "sg:phone":"+44 151 327 6338",
    "sg:postcode":"CH62 8BJ",
    "sg:province":"Cheshire",
    "sg:tags":[
        "builder"
    ],
    "wof:name":"Peter Rayner",
    "wof:placetype":"venue"
},
  "geometry": {"coordinates":[-2.976335,53.319893],"type":"Point"}
}