{
  "type": "Feature",
  "properties": {
    "addr:full":"Llandudno Market Hall, Bodhyfryd Road Llandudno Conwy LL30 2DT",
    "addr:postcode":"ll30 2dt",
    "addr:street":"Bodhyfryd Road",
    "iso:country":"GB",
    "sg:address":"Llandudno Market Hall, Bodhyfryd Road",
    "sg:city":"Llandudno",
    "sg:classifiers":[
        {
            "category":"Shopping",
            "subcategory":"Antiques",
            "type":"Retail Goods"
        }
    ],
    "sg:postcode":"LL30 2DT",
    "sg:province":"Conwy",
    "wof:name":"B Jones",
    "wof:placetype":"venue"
},
  "geometry": {"coordinates":[-3.8187639713,53.3224334717],"type":"Point"}
}