{
  "type": "Feature",
  "properties": {
    "addr:full":"Unit 8 Milburngate Centre Durham Durham DH1 5TA",
    "addr:housenumber":"unit 8",
    "addr:postcode":"dh1 5ta",
    "addr:street":"Milburngate Centre",
    "iso:country":"GB",
    "sg:address":"Unit 8 Milburngate Centre",
    "sg:city":"Durham",
    "sg:classifiers":[
        {
            "category":"Shopping",
            "subcategory":"Clothing, Apparel, & Fashions",
            "type":"Retail Goods"
        }
    ],
    "sg:phone":"+44 191 386 0588",
    "sg:postcode":"DH1 5TA",
    "sg:province":"Durham",
    "sg:tags":[
        "menswear"
    ],
    "wof:name":"Miss Selfridges",
    "wof:placetype":"venue"
},
  "geometry": {"coordinates":[-1.574608,54.777534],"type":"Point"}
}