{
  "type": "Feature",
  "properties": {
    "iso:country":"GB",
    "sg:address":"18a Upper Bannister Street",
    "sg:city":"Southampton",
    "sg:classifiers":[
        {
            "category":"Autos & Motor Vehicles",
            "subcategory":"Boat Sales",
            "type":"Retail Goods"
        }
    ],
    "sg:phone":"+44 23 8021 1007",
    "sg:postcode":"SO15 2EF",
    "sg:province":"Hampshire",
    "sg:tags":[
        "balloon"
    ],
    "wof:name":"Celebrations - the Party People Ltd.",
    "wof:placetype":"venue"
},
  "geometry": {"coordinates":[-1.4056400061,50.913028717],"type":"Point"}
}