{
  "type": "Feature",
  "properties": {
    "addr:full":"28 Love Lane Pinner Greater London HA5 3EX",
    "addr:housenumber":"28",
    "addr:postcode":"ha5 3ex",
    "addr:street":"Love Lane",
    "iso:country":"GB",
    "sg:address":"28 Love Lane",
    "sg:city":"Pinner",
    "sg:classifiers":[
        {
            "category":"Place Of Worship",
            "type":"Public Place"
        },
        {
            "category":"Organizations",
            "subcategory":"Non-profit Organization",
            "type":"Services"
        }
    ],
    "sg:phone":"+44 20 8866 0098",
    "sg:postcode":"HA5 3EX",
    "sg:province":"Greater London",
    "sg:tags":[
        "charitable",
        "organisation",
        "charity"
    ],
    "wof:name":"ST LUKE'S R C CHURCH",
    "wof:placetype":"venue"
},
  "geometry": {"coordinates":[-0.382762,51.595837],"type":"Point"}
}