{
  "type": "Feature",
  "properties": {
    "addr:full":"418 Halifax Road Rochdale Lancashire OL16 2RQ",
    "addr:housenumber":"418",
    "addr:postcode":"ol16 2rq",
    "addr:street":"Halifax Road",
    "iso:country":"GB",
    "sg:address":"418 Halifax Road",
    "sg:city":"Rochdale",
    "sg:classifiers":[
        {
            "category":"Personal",
            "subcategory":"Beauty Salon",
            "type":"Services"
        }
    ],
    "sg:phone":"+44 1706 645806",
    "sg:postcode":"OL16 2RQ",
    "sg:province":"Lancashire",
    "sg:tags":[
        "unisex",
        "hairdresser"
    ],
    "wof:name":"Hair Fx",
    "wof:placetype":"venue"
},
  "geometry": {"coordinates":[-2.1312580109,53.6345252991],"type":"Point"}
}