{
  "type": "Feature",
  "properties": {
    "addr:full":"53 Wolveleigh Terrace Newcastle-upon-tyne Tyne and Wear NE3 1UP",
    "addr:housenumber":"53",
    "addr:postcode":"ne3 1up",
    "addr:street":"Wolveleigh Terrace",
    "iso:country":"GB",
    "sg:address":"53 Wolveleigh Terrace",
    "sg:city":"Newcastle-upon-tyne",
    "sg:classifiers":[
        {
            "category":"Health Services",
            "subcategory":"Health Practitioner",
            "type":"Services"
        }
    ],
    "sg:postcode":"NE3 1UP",
    "sg:province":"Tyne and Wear",
    "sg:tags":[
        "physiotherapist"
    ],
    "wof:name":"E Dias",
    "wof:placetype":"venue"
},
  "geometry": {"coordinates":[-1.614637,55.009174],"type":"Point"}
}