{
  "type": "Feature",
  "properties": {
    "iso:country":"GB",
    "sg:address":"Unit 5 Kerfoot Business Park, Kerfoot St",
    "sg:city":"Warrington",
    "sg:classifiers":[
        {
            "category":"Building & Trades",
            "subcategory":"Construction",
            "type":"Services"
        }
    ],
    "sg:phone":"+44 1925 638553",
    "sg:postcode":"WA2 8NX",
    "sg:province":"Cheshire",
    "sg:tags":[
        "roofing"
    ],
    "wof:name":"Rooftec Roofing Supplies Ltd",
    "wof:placetype":"venue"
},
  "geometry": {"coordinates":[-2.589254,53.393826],"type":"Point"}
}