{
  "type": "Feature",
  "properties": {
    "addr:full":"Princess Road Seaham Durham SR7 7QT",
    "addr:postcode":"sr7 7qt",
    "addr:street":"Princess Road",
    "iso:country":"GB",
    "sg:address":"Princess Road",
    "sg:city":"Seaham",
    "sg:classifiers":[
        {
            "category":"Military Area",
            "subcategory":"Air Force Base",
            "type":"Public Place"
        }
    ],
    "sg:phone":"+44 191 581 4775",
    "sg:postcode":"SR7 7QT",
    "sg:province":"Durham",
    "sg:tags":[
        "taxi",
        "hire",
        "private"
    ],
    "wof:name":"Danny's Taxis",
    "wof:placetype":"venue"
},
  "geometry": {"coordinates":[-1.3412040472,54.8360366821],"type":"Point"}
}