{
  "type": "Feature",
  "properties": {
    "addr:full":"Amor Hall, Washbrook Ipswich Suffolk IP8 3HX",
    "addr:postcode":"ip8 3hx",
    "iso:country":"GB",
    "sg:address":"Amor Hall, Washbrook",
    "sg:city":"Ipswich",
    "sg:classifiers":[
        {
            "category":"Real Estate",
            "subcategory":"Developer",
            "type":"Services"
        }
    ],
    "sg:postcode":"IP8 3HX",
    "sg:province":"Suffolk",
    "sg:tags":[
        "property"
    ],
    "wof:name":"East Court Industries",
    "wof:placetype":"venue"
},
  "geometry": {"coordinates":[1.0875,52.037563],"type":"Point"}
}