{
  "type": "Feature",
  "properties": {
    "addr:full":"Tankerfield, The Promenade Carnforth Cumbria LA5 0HA",
    "addr:postcode":"la5 0ha",
    "addr:street":"The Promenade",
    "iso:country":"GB",
    "sg:address":"Tankerfield, The Promenade",
    "sg:city":"Carnforth",
    "sg:classifiers":[
        {
            "category":"Shopping",
            "type":"Retail Goods"
        }
    ],
    "sg:postcode":"LA5 0HA",
    "sg:province":"Cumbria",
    "sg:tags":[
        "merchant"
    ],
    "wof:name":"David Baldwin",
    "wof:placetype":"venue"
},
  "geometry": {"coordinates":[-2.7680590153,54.1284790039],"type":"Point"}
}