{
  "type": "Feature",
  "properties": {
    "addr:full":"Well Lane, Whiston Rotherham South Yorkshire S60 4HX",
    "addr:postcode":"s60 4hx",
    "addr:street":"Well Lane",
    "iso:country":"GB",
    "sg:address":"Well Lane, Whiston",
    "sg:city":"Rotherham",
    "sg:classifiers":[
        {
            "category":"Government",
            "subcategory":"City Hall",
            "type":"Public Place"
        }
    ],
    "sg:phone":"+44 1709 378774",
    "sg:postcode":"S60 4HX",
    "sg:province":"South Yorkshire",
    "wof:name":"Whiston Parish Hall",
    "wof:placetype":"venue"
},
  "geometry": {"coordinates":[-1.309684,53.407742],"type":"Point"}
}