{
  "type": "Feature",
  "properties": {
    "addr:full":"266 West Green Rd Seven Sisters Greater London N15 3QR",
    "addr:housenumber":"266",
    "addr:postcode":"n15 3qr",
    "addr:street":"West Green Rd",
    "iso:country":"GB",
    "sg:address":"266 West Green Rd",
    "sg:city":"Seven Sisters",
    "sg:classifiers":[
        {
            "category":"Shopping",
            "subcategory":"Baby Store",
            "type":"Retail Goods"
        }
    ],
    "sg:phone":"+44 20 8888 6035",
    "sg:postcode":"N15 3QR",
    "sg:province":"Greater London",
    "sg:tags":[
        "babywear",
        "childrens"
    ],
    "wof:name":"Magda Childrens Wear",
    "wof:placetype":"venue"
},
  "geometry": {"coordinates":[-0.08946,51.58643],"type":"Point"}
}