{
  "type": "Feature",
  "properties": {
    "iso:country":"GB",
    "sg:address":"Unit 8d, Haltwhistle Ind Est",
    "sg:city":"Haltwhistle",
    "sg:classifiers":[
        {
            "category":"Building & Trades",
            "subcategory":"Cleaning & Sanitation",
            "type":"Services"
        }
    ],
    "sg:phone":"+44 1434 322877",
    "sg:postcode":"NE49 9HA",
    "sg:province":"Northumberland",
    "sg:tags":[
        "steam"
    ],
    "wof:name":"I.P.W",
    "wof:placetype":"venue"
},
  "geometry": {"coordinates":[-2.464497,54.968594],"type":"Point"}
}