{
  "type": "Feature",
  "properties": {
    "iso:country":"GB",
    "sg:address":"Hale Bank 40 Bridgeman Terrace",
    "sg:city":"Wigan",
    "sg:classifiers":[
        {
            "category":"Retail",
            "subcategory":"Storage",
            "type":"Services"
        }
    ],
    "sg:postcode":"WN1 1TT",
    "sg:province":"Lancashire",
    "sg:tags":[
        "household",
        "removal"
    ],
    "wof:name":"Megatrade Ltd",
    "wof:placetype":"venue"
},
  "geometry": {"coordinates":[-2.6335320473,53.5441551208],"type":"Point"}
}