{
  "type": "Feature",
  "properties": {
    "addr:full":"Hackford Road, Wicklewood Wymondham Norfolk NR18 9QJ",
    "addr:postcode":"nr18 9qj",
    "addr:street":"Hackford Road",
    "iso:country":"GB",
    "sg:address":"Hackford Road, Wicklewood",
    "sg:city":"Wymondham",
    "sg:classifiers":[
        {
            "category":"Education",
            "subcategory":"School",
            "type":"Public Place"
        }
    ],
    "sg:phone":"+44 1953 602333",
    "sg:postcode":"NR18 9QJ",
    "sg:province":"Norfolk",
    "sg:tags":[
        "college"
    ],
    "wof:name":"Wicklewood Primary School",
    "wof:placetype":"venue"
},
  "geometry": {"coordinates":[1.0524439812,52.5803337097],"type":"Point"}
}