{
  "type": "Feature",
  "properties": {
    "iso:country":"GB",
    "sg:address":"32 Poplar Gro, Forest Town",
    "sg:city":"Mansfield",
    "sg:classifiers":[
        {
            "category":"Freight",
            "type":"Transportation"
        }
    ],
    "sg:phone":"+44 1623 624356",
    "sg:postcode":"NG19 0HN",
    "sg:province":"Derbyshire",
    "sg:tags":[
        "haulage",
        "road"
    ],
    "wof:name":"Roy Bedford",
    "wof:placetype":"venue"
},
  "geometry": {"coordinates":[-1.148097,53.154411],"type":"Point"}
}