{
  "type": "Feature",
  "properties": {
    "addr:full":"41 Winifred Road, Skewen Neath Neath Port Talbot SA10 6HW",
    "addr:housenumber":"41",
    "addr:postcode":"sa10 6hw",
    "addr:street":"Winifred Road",
    "iso:country":"GB",
    "sg:address":"41 Winifred Road, Skewen",
    "sg:city":"Neath",
    "sg:classifiers":[
        {
            "category":"Building & Trades",
            "subcategory":"Construction",
            "type":"Services"
        }
    ],
    "sg:phone":"+44 1792 813596",
    "sg:postcode":"SA10 6HW",
    "sg:province":"Neath Port Talbot",
    "sg:tags":[
        "supplier",
        "installers",
        "cladding"
    ],
    "wof:name":"Melding Stone Craft",
    "wof:placetype":"venue"
},
  "geometry": {"coordinates":[-3.849269,51.659996],"type":"Point"}
}