{
  "type": "Feature",
  "properties": {
    "addr:full":"Unit 33, Westcott Venture Park Aylesbury Buckinghamshire HP18 0NP",
    "addr:housenumber":"unit 33",
    "addr:postcode":"hp18 0np",
    "addr:street":"Venture Park",
    "iso:country":"GB",
    "sg:address":"Unit 33, Westcott Venture Park",
    "sg:city":"Aylesbury",
    "sg:classifiers":[
        {
            "category":"Retail",
            "subcategory":"Auto Repair",
            "type":"Services"
        }
    ],
    "sg:phone":"+44 1296 770858",
    "sg:postcode":"HP18 0NP",
    "sg:province":"Buckinghamshire",
    "sg:tags":[
        "body",
        "car",
        "specialist",
        "customizing"
    ],
    "wof:name":"Bucks Mini Centre",
    "wof:placetype":"venue"
},
  "geometry": {"coordinates":[-0.97273,51.840069],"type":"Point"}
}