{
  "type": "Feature",
  "properties": {
    "iso:country":"GB",
    "sg:address":"65 Warmwell, East Knighton",
    "sg:city":"Dorchester",
    "sg:classifiers":[
        {
            "category":"Food & Beverages",
            "subcategory":"Farmers Market",
            "type":"Retail Goods"
        }
    ],
    "sg:phone":"+44 1305 852901",
    "sg:postcode":"DT2 8LL",
    "sg:province":"Dorset",
    "sg:tags":[
        "gardener"
    ],
    "wof:name":"E A & E Sinnick",
    "wof:placetype":"venue"
},
  "geometry": {"coordinates":[-2.321779,50.696331],"type":"Point"}
}