{
  "type": "Feature",
  "properties": {
    "iso:country":"GB",
    "sg:address":"2 Hankinson Way, Salford Shopping Centre",
    "sg:city":"Salford",
    "sg:classifiers":[
        {
            "category":"Insurance",
            "subcategory":"Insurance Agent",
            "type":"Services"
        }
    ],
    "sg:postcode":"M6 5JA",
    "sg:province":"Greater Manchester",
    "wof:name":"Swinton",
    "wof:placetype":"venue"
},
  "geometry": {"coordinates":[-2.2860980034,53.4897270203],"type":"Point"}
}