{
  "type": "Feature",
  "properties": {
    "iso:country":"GB",
    "sg:address":"High Street",
    "sg:city":"Abbots Langley",
    "sg:classifiers":[
        {
            "category":"Education",
            "subcategory":"Library",
            "type":"Public Place"
        },
        {
            "category":"Government",
            "subcategory":"Office",
            "type":"Public Place"
        }
    ],
    "sg:phone":"+44 1923 471333",
    "sg:postcode":"WD5 0AP",
    "sg:province":"Hertfordshire",
    "sg:tags":[
        "book",
        "local"
    ],
    "wof:name":"Abbots Langley Library",
    "wof:placetype":"venue"
},
  "geometry": {"coordinates":[-0.415717,51.709038],"type":"Point"}
}