{
  "type": "Feature",
  "properties": {
    "addr:full":"Rap House, Harrison Street Burnley Lancashire BB10 2HP",
    "addr:postcode":"bb10 2hp",
    "addr:street":"Harrison Street",
    "iso:country":"GB",
    "sg:address":"Rap House, Harrison Street",
    "sg:city":"Burnley",
    "sg:classifiers":[
        {
            "category":"Shopping",
            "type":"Retail Goods"
        }
    ],
    "sg:phone":"+44 1282 410600",
    "sg:postcode":"BB10 2HP",
    "sg:province":"Lancashire",
    "sg:tags":[
        "equipment",
        "clothing",
        "safety"
    ],
    "wof:name":"Panda Gardening Products",
    "wof:placetype":"venue"
},
  "geometry": {"coordinates":[-2.199944,53.811275],"type":"Point"}
}