{
  "type": "Feature",
  "properties": {
    "iso:country":"GB",
    "sg:address":"91 Leytonstone Rd",
    "sg:city":"Stratford",
    "sg:classifiers":[
        {
            "category":"Cafe",
            "type":"Food & Drink"
        }
    ],
    "sg:phone":"+44 20 8257 1494",
    "sg:postcode":"E15 1JA",
    "sg:province":"Greater London",
    "sg:tags":[
        "tea",
        "room"
    ],
    "wof:name":"The Cosy Cafe",
    "wof:placetype":"venue"
},
  "geometry": {"coordinates":[0.00559,51.547642],"type":"Point"}
}