{
  "type": "Feature",
  "properties": {
    "iso:country":"GB",
    "sg:address":"Penley",
    "sg:city":"Wrexham",
    "sg:classifiers":[
        {
            "category":"Shopping",
            "subcategory":"Department Store",
            "type":"Retail Goods"
        }
    ],
    "sg:postcode":"LL13 0LG",
    "sg:province":"Wrexham",
    "wof:name":"Penley Post Office an General Store",
    "wof:placetype":"venue"
},
  "geometry": {"coordinates":[-2.95589,52.958771],"type":"Point"}
}