{
  "type": "Feature",
  "properties": {
    "iso:country":"GB",
    "sg:address":"13 Rowlands Rd",
    "sg:city":"Worthing",
    "sg:classifiers":[
        {
            "category":"Shopping",
            "subcategory":"Pharmacy",
            "type":"Retail Goods"
        }
    ],
    "sg:postcode":"BN11 3JJ",
    "sg:province":"West Sussex",
    "sg:tags":[
        "pharmacist",
        "store",
        "drug",
        "chemist"
    ],
    "wof:name":"Salter,Alan,",
    "wof:placetype":"venue"
},
  "geometry": {"coordinates":[-0.379151,50.809727],"type":"Point"}
}