{
  "type": "Feature",
  "properties": {
    "addr:full":"10a Newport Business Station Middlesbrough North Yorkshire TS1 5EA",
    "addr:housenumber":"10a",
    "addr:postcode":"ts1 5ea",
    "addr:street":"Newport Business Station",
    "iso:country":"GB",
    "sg:address":"10a Newport Business Station",
    "sg:city":"Middlesbrough",
    "sg:classifiers":[
        {
            "category":"Professional",
            "subcategory":"Detective & Security Services",
            "type":"Services"
        }
    ],
    "sg:phone":"+44 1642 230940",
    "sg:postcode":"TS1 5EA",
    "sg:province":"North Yorkshire",
    "sg:tags":[
        "locksmith"
    ],
    "wof:name":"Stephen Appleyard Locksmith",
    "wof:placetype":"venue"
},
  "geometry": {"coordinates":[-1.252209,54.57531],"type":"Point"}
}