{
  "type": "Feature",
  "properties": {
    "iso:country":"GB",
    "sg:address":"5 Breinton Road",
    "sg:city":"Hereford",
    "sg:classifiers":[
        {
            "category":"Real Estate",
            "subcategory":"Real Estate Agent",
            "type":"Services"
        }
    ],
    "sg:postcode":"HR4 0JU",
    "sg:province":"Herefordshire",
    "wof:name":"Jane E Lilwall",
    "wof:placetype":"venue"
},
  "geometry": {"coordinates":[-2.727273941,52.0536193848],"type":"Point"}
}