{
  "type": "Feature",
  "properties": {
    "addr:full":"29 Oxford Hill Witney Oxfordshire OX28 3JU",
    "addr:housenumber":"29",
    "addr:postcode":"ox28 3ju",
    "addr:street":"Oxford Hill",
    "iso:country":"GB",
    "sg:address":"29 Oxford Hill",
    "sg:city":"Witney",
    "sg:classifiers":[
        {
            "category":"Travel",
            "subcategory":"Hotels & Motels",
            "type":"Entertainment"
        }
    ],
    "sg:postcode":"OX28 3JU",
    "sg:province":"Oxfordshire",
    "sg:tags":[
        "house",
        "guest"
    ],
    "wof:name":"Crofters Guest House",
    "wof:placetype":"venue"
},
  "geometry": {"coordinates":[-1.4700499773,51.786315918],"type":"Point"}
}