{
  "type": "Feature",
  "properties": {
    "iso:country":"GB",
    "sg:address":"Arc",
    "sg:city":"Accrington",
    "sg:classifiers":[
        {
            "category":"Shopping",
            "subcategory":"Discount & Variety Stores",
            "type":"Retail Goods"
        }
    ],
    "sg:postcode":"BB5 2EL",
    "sg:province":"Lancashire",
    "sg:tags":[
        "centre"
    ],
    "wof:name":"Bootleggers",
    "wof:placetype":"venue"
},
  "geometry": {"coordinates":[-2.3485989571,53.7430496216],"type":"Point"}
}