{
  "type": "Feature",
  "properties": {
    "iso:country":"GB",
    "sg:address":"19 Don Road",
    "sg:city":"Sheffield",
    "sg:classifiers":[
        {
            "category":"Manufacturing",
            "subcategory":"Metals",
            "type":"Manufacturing & Wholesale Goods"
        }
    ],
    "sg:phone":"+44 114 221 2020",
    "sg:postcode":"S9 2UD",
    "sg:province":"South Yorkshire",
    "sg:tags":[
        "steel",
        "stockholder"
    ],
    "sg:website":"http://www.ghcook.com",
    "wof:name":"George H Cook & Co Ltd",
    "wof:placetype":"venue"
},
  "geometry": {"coordinates":[-1.4327039719,53.3994064331],"type":"Point"}
}