{
  "type": "Feature",
  "properties": {
    "iso:country":"GB",
    "sg:address":"Beaufort Road",
    "sg:city":"Ebbw Vale",
    "sg:classifiers":[
        {
            "category":"Education",
            "subcategory":"School",
            "type":"Public Place"
        }
    ],
    "sg:phone":"+44 1495 302589",
    "sg:postcode":"NP23 5NJ",
    "sg:province":"Blaenau Gwent",
    "sg:tags":[
        "local",
        "authority"
    ],
    "wof:name":"Gwent County Council",
    "wof:placetype":"venue"
},
  "geometry": {"coordinates":[-3.207253933,51.7872543335],"type":"Point"}
}