{
  "type": "Feature",
  "properties": {
    "iso:country":"GB",
    "sg:address":"King St",
    "sg:city":"Oldham",
    "sg:classifiers":[
        {
            "category":"Recreation",
            "type":"Entertainment"
        }
    ],
    "sg:phone":"+44 161 621 0445",
    "sg:postcode":"OL8 1EU",
    "sg:province":"Lancashire",
    "sg:tags":[
        "snooker",
        "billiards",
        "pool"
    ],
    "wof:name":"Riley's American Pool & Snooker Club",
    "wof:placetype":"venue"
},
  "geometry": {"coordinates":[-2.117009,53.540005],"type":"Point"}
}