{
  "type": "Feature",
  "properties": {
    "addr:full":"259 East La, North Wembley Wembley Greater London HA0 3NN",
    "addr:housenumber":"259",
    "addr:postcode":"ha0 3nn",
    "addr:street":"East La North",
    "iso:country":"GB",
    "sg:address":"259 East La, North Wembley",
    "sg:city":"Wembley",
    "sg:classifiers":[
        {
            "category":"Freight",
            "type":"Transportation"
        }
    ],
    "sg:postcode":"HA0 3NN",
    "sg:province":"Greater London",
    "sg:tags":[
        "haulage",
        "road"
    ],
    "wof:name":"Tompkins,W G,& Sons",
    "wof:placetype":"venue"
},
  "geometry": {"coordinates":[-0.309175998,51.5623703003],"type":"Point"}
}