{
  "type": "Feature",
  "properties": {
    "iso:country":"GB",
    "sg:address":"The E P I Centre, Mansfield Road, Blidworth",
    "sg:city":"Mansfield",
    "sg:classifiers":[
        {
            "category":"Professional",
            "subcategory":"Printing & Photocopies",
            "type":"Services"
        }
    ],
    "sg:phone":"+44 1623 490114",
    "sg:postcode":"NG21 0LR",
    "sg:province":"Nottinghamshire",
    "sg:tags":[
        "emblem",
        "wholesale",
        "badge"
    ],
    "wof:name":"Mirical Emblems Ltd.",
    "wof:placetype":"venue"
},
  "geometry": {"coordinates":[-1.1174639463,53.0990791321],"type":"Point"}
}