{
  "type": "Feature",
  "properties": {
    "iso:country":"GB",
    "sg:address":"103 South Street",
    "sg:city":"Perth",
    "sg:classifiers":[
        {
            "category":"Bars & Pubs",
            "type":"Food & Drink"
        }
    ],
    "sg:phone":"+44 1738 637479",
    "sg:postcode":"PH2 8PA",
    "sg:province":"Perth and Kinross",
    "sg:tags":[
        "pubs",
        "inn"
    ],
    "wof:name":"Scaramouche",
    "wof:placetype":"venue"
},
  "geometry": {"coordinates":[-3.430969,56.395435],"type":"Point"}
}