{
  "type": "Feature",
  "properties": {
    "iso:country":"GB",
    "sg:address":"Uxbridge Square",
    "sg:city":"Menai Bridge",
    "sg:classifiers":[
        {
            "category":"Personal",
            "subcategory":"Beauty Salon",
            "type":"Services"
        },
        {
            "category":"Personal",
            "subcategory":"Barber",
            "type":"Services"
        }
    ],
    "sg:phone":"+44 1248 712871",
    "sg:postcode":"LL59 5AT",
    "sg:province":"Isle of Anglesey",
    "sg:tags":[
        "unisex",
        "men's",
        "hairdresser"
    ],
    "wof:name":"The Barbers Shop",
    "wof:placetype":"venue"
},
  "geometry": {"coordinates":[-4.1630687714,53.2259635925],"type":"Point"}
}