{
  "type": "Feature",
  "properties": {
    "addr:full":"Unit 6, Lovett Road, Hampton Lovett Industrial Estate Droitwich Worcestershire WR9 0QG",
    "addr:housenumber":"unit 6",
    "addr:postcode":"wr9 0qg",
    "addr:street":"Lovett Road;Industrial Estate",
    "iso:country":"GB",
    "sg:address":"Unit 6, Lovett Road, Hampton Lovett Industrial Estate",
    "sg:city":"Droitwich",
    "sg:classifiers":[
        {
            "category":"Manufacturing",
            "subcategory":"Wood Products",
            "type":"Manufacturing & Wholesale Goods"
        }
    ],
    "sg:phone":"+44 1905 794703",
    "sg:postcode":"WR9 0QG",
    "sg:province":"Worcestershire",
    "sg:tags":[
        "packaging",
        "crate",
        "pallets"
    ],
    "wof:name":"Leedan Packaging Ltd.",
    "wof:placetype":"venue"
},
  "geometry": {"coordinates":[-2.167675972,52.2846183777],"type":"Point"}
}