{
  "type": "Feature",
  "properties": {
    "addr:full":"17 Garrick Way Ipswich Suffolk IP1 6NF",
    "addr:housenumber":"17",
    "addr:postcode":"ip1 6nf",
    "addr:street":"Garrick Way",
    "iso:country":"GB",
    "sg:address":"17 Garrick Way",
    "sg:city":"Ipswich",
    "sg:classifiers":[
        {
            "category":"Building & Trades",
            "subcategory":"Cleaning & Sanitation",
            "type":"Services"
        }
    ],
    "sg:phone":"+44 1473 749007",
    "sg:postcode":"IP1 6NF",
    "sg:province":"Suffolk",
    "sg:tags":[
        "commercial"
    ],
    "wof:name":"Mapleleaf Cleaners",
    "wof:placetype":"venue"
},
  "geometry": {"coordinates":[1.137952,52.080025],"type":"Point"}
}