{
  "type": "Feature",
  "properties": {
    "addr:full":"12 Crediton Hill, West Hampstead London Greater London NW6 1HP",
    "addr:housenumber":"12",
    "addr:postcode":"nw6 1hp",
    "addr:street":"Crediton Hill",
    "iso:country":"GB",
    "sg:address":"12 Crediton Hill, West Hampstead",
    "sg:city":"London",
    "sg:classifiers":[
        {
            "category":"Building & Trades",
            "subcategory":"Construction",
            "type":"Services"
        }
    ],
    "sg:phone":"+44 20 7431 1614",
    "sg:postcode":"NW6 1HP",
    "sg:province":"Greater London",
    "sg:tags":[
        "management"
    ],
    "wof:name":"Niceport Ltd.",
    "wof:placetype":"venue"
},
  "geometry": {"coordinates":[-0.219209,51.536358],"type":"Point"}
}