{
  "type": "Feature",
  "properties": {
    "addr:full":"146a Lea Bridge Rd, Hackney London Greater London E5 9RF",
    "addr:housenumber":"146a",
    "addr:postcode":"e5 9rf",
    "addr:street":"Lea Bridge Rd",
    "iso:country":"GB",
    "sg:address":"146a Lea Bridge Rd, Hackney",
    "sg:city":"London",
    "sg:classifiers":[
        {
            "category":"Home & Garden",
            "subcategory":"Furniture",
            "type":"Retail Goods"
        }
    ],
    "sg:postcode":"E5 9RF",
    "sg:province":"Greater London",
    "wof:name":"Collins,Bertie",
    "wof:placetype":"venue"
},
  "geometry": {"coordinates":[-0.04598,51.561947],"type":"Point"}
}