{
  "type": "Feature",
  "properties": {
    "iso:country":"GB",
    "sg:address":"3 Fairfax Clo",
    "sg:city":"Ashby-de-la-zouch",
    "sg:classifiers":[
        {
            "category":"Shopping",
            "subcategory":"Catalog Store",
            "type":"Retail Goods"
        }
    ],
    "sg:postcode":"LE65 1LZ",
    "sg:province":"Derbyshire",
    "sg:tags":[
        "mail",
        "order"
    ],
    "wof:name":"Mann,Janet,",
    "wof:placetype":"venue"
},
  "geometry": {"coordinates":[-1.458656,52.751228],"type":"Point"}
}