{
  "type": "Feature",
  "properties": {
    "addr:full":"156 Lawrence Road Liverpool Merseyside L15 3HA",
    "addr:housenumber":"156",
    "addr:postcode":"l15 3ha",
    "addr:street":"Lawrence Road",
    "iso:country":"GB",
    "sg:address":"156 Lawrence Road",
    "sg:city":"Liverpool",
    "sg:classifiers":[
        {
            "category":"Building & Trades",
            "subcategory":"Construction",
            "type":"Services"
        }
    ],
    "sg:phone":"+44 151 708 9624",
    "sg:postcode":"L15 3HA",
    "sg:province":"Merseyside",
    "sg:tags":[
        "decorator",
        "painter"
    ],
    "wof:name":"les Forshaw",
    "wof:placetype":"venue"
},
  "geometry": {"coordinates":[-2.9297859669,53.3955421448],"type":"Point"}
}