{
  "type": "Feature",
  "properties": {
    "addr:full":"4 Wilford Lane, West Bridgford Nottingham Nottinghamshire NG2 7QX",
    "addr:housenumber":"4",
    "addr:postcode":"ng2 7qx",
    "addr:street":"Wilford Lane",
    "iso:country":"GB",
    "sg:address":"4 Wilford Lane, West Bridgford",
    "sg:city":"Nottingham",
    "sg:classifiers":[
        {
            "category":"Manufacturing",
            "subcategory":"Textiles",
            "type":"Manufacturing & Wholesale Goods"
        },
        {
            "category":"Government",
            "subcategory":"Office",
            "type":"Public Place"
        }
    ],
    "sg:phone":"+44 115 981 8618",
    "sg:postcode":"NG2 7QX",
    "sg:province":"Nottinghamshire",
    "sg:tags":[
        "knitwear",
        "local"
    ],
    "wof:name":"West Bridgford Machine Co. Ltd.",
    "wof:placetype":"venue"
},
  "geometry": {"coordinates":[-1.137437,52.932648],"type":"Point"}
}