{
  "type": "Feature",
  "properties": {
    "addr:full":"Grundisburgh Road Woodbridge Suffolk IP12 4HG",
    "addr:postcode":"ip12 4hg",
    "addr:street":"Grundisburgh Road",
    "iso:country":"GB",
    "sg:address":"Grundisburgh Road",
    "sg:city":"Woodbridge",
    "sg:classifiers":[
        {
            "category":"Retail",
            "subcategory":"Repair Shop",
            "type":"Services"
        }
    ],
    "sg:phone":"+44 1394 383838",
    "sg:postcode":"IP12 4HG",
    "sg:province":"Suffolk",
    "sg:tags":[
        "maintenance"
    ],
    "wof:name":"Banyard & Houchell Ltd.",
    "wof:placetype":"venue"
},
  "geometry": {"coordinates":[1.30359,52.096455],"type":"Point"}
}