{
  "type": "Feature",
  "properties": {
    "iso:country":"GB",
    "sg:address":"2 St Marys Pass",
    "sg:city":"Cambridge",
    "sg:classifiers":[
        {
            "category":"Professional",
            "subcategory":"Computer Services",
            "type":"Services"
        }
    ],
    "sg:phone":"+44 1223 303267",
    "sg:postcode":"CB2 3PQ",
    "sg:province":"Cambridgeshire",
    "sg:tags":[
        "system",
        "software"
    ],
    "wof:name":"Multimedia Village Ltd",
    "wof:placetype":"venue"
},
  "geometry": {"coordinates":[0.1182449982,52.2075462341],"type":"Point"}
}