{
  "type": "Feature",
  "properties": {
    "addr:full":"104 Regent Street Shanklin Isle of Wight PO37 7AP",
    "addr:housenumber":"104",
    "addr:postcode":"po37 7ap",
    "addr:street":"Regent Street",
    "iso:country":"GB",
    "sg:address":"104 Regent Street",
    "sg:city":"Shanklin",
    "sg:classifiers":[
        {
            "category":"Cinema",
            "subcategory":"Movie Rental",
            "type":"Entertainment"
        }
    ],
    "sg:phone":"+44 1983 863905",
    "sg:postcode":"PO37 7AP",
    "sg:province":"Isle of Wight",
    "sg:tags":[
        "video",
        "library"
    ],
    "wof:name":"Blockbuster Video Express",
    "wof:placetype":"venue"
},
  "geometry": {"coordinates":[-1.17913,50.632881],"type":"Point"}
}