{
  "type": "Feature",
  "properties": {
    "addr:full":"61 Market Place, Shaw Oldham Lancashire OL2 8NN",
    "addr:housenumber":"61",
    "addr:postcode":"ol2 8nn",
    "addr:street":"Market Place",
    "iso:country":"GB",
    "sg:address":"61 Market Place, Shaw",
    "sg:city":"Oldham",
    "sg:classifiers":[
        {
            "category":"Home & Garden",
            "subcategory":"Home Furnishings",
            "type":"Retail Goods"
        }
    ],
    "sg:phone":"+44 1706 299522",
    "sg:postcode":"OL2 8NN",
    "sg:province":"Lancashire",
    "sg:tags":[
        "beds",
        "bedding",
        "blanket"
    ],
    "wof:name":"Sleeptight Beds",
    "wof:placetype":"venue"
},
  "geometry": {"coordinates":[-2.094029,53.57579],"type":"Point"}
}