{
  "type": "Feature",
  "properties": {
    "addr:full":"60 The Mall, Ealing London Greater London W5 3TA",
    "addr:housenumber":"60",
    "addr:postcode":"w5 3ta",
    "addr:street":"The Mall",
    "iso:country":"GB",
    "sg:address":"60 The Mall, Ealing",
    "sg:city":"London",
    "sg:classifiers":[
        {
            "category":"Professional",
            "subcategory":"Detective & Security Services",
            "type":"Services"
        }
    ],
    "sg:postcode":"W5 3TA",
    "sg:province":"Greater London",
    "wof:name":"International Total Services Ltd",
    "wof:placetype":"venue"
},
  "geometry": {"coordinates":[-0.300414,51.513927],"type":"Point"}
}