{
  "type": "Feature",
  "properties": {
    "iso:country":"GB",
    "sg:address":"Po Box 6227, Shepshed",
    "sg:city":"Loughborough",
    "sg:classifiers":[
        {
            "category":"Home & Garden",
            "subcategory":"Household Appliances",
            "type":"Retail Goods"
        }
    ],
    "sg:phone":"+44 1509 506179",
    "sg:postcode":"LE12 9WH",
    "sg:province":"Leicestershire",
    "sg:tags":[
        "electrical"
    ],
    "wof:name":"Mode",
    "wof:placetype":"venue"
},
  "geometry": {"coordinates":[-1.3354599476,52.7827987671],"type":"Point"}
}