{
  "type": "Feature",
  "properties": {
    "iso:country":"GB",
    "sg:address":"43 Baker Street",
    "sg:city":"Weston-super-mare",
    "sg:classifiers":[
        {
            "category":"Government",
            "subcategory":"Post Office",
            "type":"Public Place"
        }
    ],
    "sg:phone":"+44 1934 623938",
    "sg:postcode":"BS23 3AF",
    "sg:province":"Somerset",
    "wof:name":"Baker Street Post Office",
    "wof:placetype":"venue"
},
  "geometry": {"coordinates":[-2.971596,51.349121],"type":"Point"}
}