{
  "type": "Feature",
  "properties": {
    "iso:country":"GB",
    "sg:address":"650 Eglinton Street, Eglington",
    "sg:city":"Glasgow",
    "sg:classifiers":[
        {
            "category":"Organizations",
            "subcategory":"Labor Organization",
            "type":"Services"
        }
    ],
    "sg:phone":"+44 141 429 4444",
    "sg:postcode":"G5 9RP",
    "sg:province":"Glasgow City",
    "sg:tags":[
        "woodworking",
        "machinery"
    ],
    "wof:name":"The Saw Centre Ltd.",
    "wof:placetype":"venue"
},
  "geometry": {"coordinates":[-4.261979,55.844551],"type":"Point"}
}