{
  "type": "Feature",
  "properties": {
    "iso:country":"GB",
    "sg:address":"15 Church Road",
    "sg:city":"Newport",
    "sg:classifiers":[
        {
            "category":"Social Services",
            "subcategory":"Retirement Home",
            "type":"Services"
        }
    ],
    "sg:phone":"+44 1633 251600",
    "sg:postcode":"NP19 7EJ",
    "sg:province":"Newport",
    "sg:tags":[
        "care"
    ],
    "wof:name":"Summerhill Community Care Ltd.",
    "wof:placetype":"venue"
},
  "geometry": {"coordinates":[-2.9851169586,51.5924797058],"type":"Point"}
}