{
  "type": "Feature",
  "properties": {
    "addr:full":"1-3 Cherry Row Leeds West Yorkshire LS9 7LY",
    "addr:housenumber":"1-3",
    "addr:postcode":"ls9 7ly",
    "addr:street":"Cherry Row",
    "iso:country":"GB",
    "sg:address":"1-3 Cherry Row",
    "sg:city":"Leeds",
    "sg:classifiers":[
        {
            "category":"Banks & Credit Unions",
            "subcategory":"Bureau De Change",
            "type":"Services"
        },
        {
            "category":"Food & Beverages",
            "subcategory":"Groceries & Convenience Stores",
            "type":"Retail Goods"
        }
    ],
    "sg:phone":"+44 113 245 9800",
    "sg:postcode":"LS9 7LY",
    "sg:province":"West Yorkshire",
    "sg:tags":[
        "beer",
        "spirit",
        "wine"
    ],
    "sg:website":"http://www.bargainbooze.co.uk",
    "wof:name":"Bargain Booze",
    "wof:placetype":"venue"
},
  "geometry": {"coordinates":[-1.528389,53.805439],"type":"Point"}
}