{
  "type": "Feature",
  "properties": {
    "addr:full":"The Vicarage Carmarthen Carmarthenshire SA33 6TU",
    "addr:postcode":"sa33 6tu",
    "iso:country":"GB",
    "sg:address":"The Vicarage",
    "sg:city":"Carmarthen",
    "sg:classifiers":[
        {
            "category":"Place Of Worship",
            "type":"Public Place"
        }
    ],
    "sg:phone":"+44 1267 281605",
    "sg:postcode":"SA33 6TU",
    "sg:province":"Carmarthenshire",
    "wof:name":"St Micheal's Church Newchurch",
    "wof:placetype":"venue"
},
  "geometry": {"coordinates":[-4.37261,51.921249],"type":"Point"}
}