{
  "type": "Feature",
  "properties": {
    "iso:country":"GB",
    "sg:address":"72a Park La, Netherton",
    "sg:city":"Bootle",
    "sg:classifiers":[
        {
            "category":"Personal",
            "subcategory":"Beauty Salon",
            "type":"Services"
        }
    ],
    "sg:postcode":"L30 1RN",
    "sg:province":"Merseyside",
    "sg:tags":[
        "unisex",
        "hairdresser"
    ],
    "wof:name":"Cutting Gallery (The)",
    "wof:placetype":"venue"
},
  "geometry": {"coordinates":[-2.96272,53.477562],"type":"Point"}
}