{
  "type": "Feature",
  "properties": {
    "addr:full":"Flat 3, 12 Egremont Street Ely Cambridgeshire CB6 1AE",
    "addr:housenumber":"12",
    "addr:postcode":"cb6 1ae",
    "addr:street":"Egremont Street",
    "iso:country":"GB",
    "sg:address":"Flat 3, 12 Egremont Street",
    "sg:city":"Ely",
    "sg:classifiers":[
        {
            "category":"Shopping",
            "subcategory":"Pharmacy",
            "type":"Retail Goods"
        }
    ],
    "sg:postcode":"CB6 1AE",
    "sg:province":"Cambridgeshire",
    "sg:tags":[
        "medicine",
        "therapy"
    ],
    "wof:name":"Pauline Sillett",
    "wof:placetype":"venue"
},
  "geometry": {"coordinates":[0.2616600096,52.4018516541],"type":"Point"}
}