{
  "type": "Feature",
  "properties": {
    "addr:full":"Odhams Wharf, Topsham Exeter Devon EX3 0PD",
    "addr:postcode":"ex3 0pd",
    "iso:country":"GB",
    "sg:address":"Odhams Wharf, Topsham",
    "sg:city":"Exeter",
    "sg:classifiers":[
        {
            "category":"Autos & Motor Vehicles",
            "subcategory":"Boat Sales",
            "type":"Retail Goods"
        }
    ],
    "sg:phone":"+44 1392 873680",
    "sg:postcode":"EX3 0PD",
    "sg:province":"Devon",
    "sg:tags":[
        "repair",
        "builder"
    ],
    "wof:name":"Tremlett (Boat Sales) Ltd.",
    "wof:placetype":"venue"
},
  "geometry": {"coordinates":[-3.450055,50.683174],"type":"Point"}
}