{
  "type": "Feature",
  "properties": {
    "addr:full":"86 Watling Street Rd Preston Lancashire PR2 8BP",
    "addr:housenumber":"86",
    "addr:postcode":"pr2 8bp",
    "addr:street":"Watling Street Rd",
    "iso:country":"GB",
    "sg:address":"86 Watling Street Rd",
    "sg:city":"Preston",
    "sg:classifiers":[
        {
            "category":"Health Services",
            "subcategory":"Health Practitioner",
            "type":"Services"
        }
    ],
    "sg:phone":"+44 1772 715693",
    "sg:postcode":"PR2 8BP",
    "sg:province":"Lancashire",
    "sg:tags":[
        "physiotherapist"
    ],
    "wof:name":"Beniston Mrs J",
    "wof:placetype":"venue"
},
  "geometry": {"coordinates":[-2.693696022,53.7788734436],"type":"Point"}
}