{
  "type": "Feature",
  "properties": {
    "addr:full":"Unit 50, 90 Lots Road London Greater London SW10 0QD",
    "addr:housenumber":"unit;90",
    "addr:postcode":"sw10 0qd",
    "addr:street":"Lots Road",
    "iso:country":"GB",
    "sg:address":"Unit 50, 90 Lots Road",
    "sg:city":"London",
    "sg:classifiers":[
        {
            "category":"Real Estate",
            "subcategory":"Real Estate Agent",
            "type":"Services"
        }
    ],
    "sg:phone":"+44 20 7351 3600",
    "sg:postcode":"SW10 0QD",
    "sg:province":"Greater London",
    "wof:name":"Philip Rea Ltd.",
    "wof:placetype":"venue"
},
  "geometry": {"coordinates":[-0.181035,51.478642],"type":"Point"}
}