{
  "type": "Feature",
  "properties": {
    "iso:country":"GB",
    "sg:address":"The Quadrangle, Imperial Square",
    "sg:city":"Cheltenham",
    "sg:classifiers":[
        {
            "category":"Banks & Credit Unions",
            "subcategory":"Financial Services",
            "type":"Services"
        }
    ],
    "sg:phone":"+44 1242 582648",
    "sg:postcode":"GL50 1PZ",
    "sg:province":"Gloucestershire",
    "sg:tags":[
        "building",
        "society"
    ],
    "wof:name":"Stroud & Swindon Building Society",
    "wof:placetype":"venue"
},
  "geometry": {"coordinates":[-2.0784590244,51.8980484009],"type":"Point"}
}