{
  "type": "Feature",
  "properties": {
    "addr:full":"15 Long Lane London Greater London N3 2PR",
    "addr:housenumber":"15",
    "addr:postcode":"n3 2pr",
    "addr:street":"Long Lane",
    "iso:country":"GB",
    "sg:address":"15 Long Lane",
    "sg:city":"London",
    "sg:classifiers":[
        {
            "category":"Shopping",
            "subcategory":"Antiques",
            "type":"Retail Goods"
        }
    ],
    "sg:phone":"+44 20 8343 0084",
    "sg:postcode":"N3 2PR",
    "sg:province":"Greater London",
    "wof:name":"Clifford Antiques",
    "wof:placetype":"venue"
},
  "geometry": {"coordinates":[-0.1880819947,51.6044502258],"type":"Point"}
}