{
  "type": "Feature",
  "properties": {
    "addr:full":"6 Banc Pendre Kidwelly Carmarthenshire SA17 4TA",
    "addr:housenumber":"6",
    "addr:postcode":"sa17 4ta",
    "addr:street":"Banc Pendre",
    "iso:country":"GB",
    "sg:address":"6 Banc Pendre",
    "sg:city":"Kidwelly",
    "sg:classifiers":[
        {
            "category":"Manufacturing",
            "subcategory":"Tools & Machinery",
            "type":"Manufacturing & Wholesale Goods"
        }
    ],
    "sg:postcode":"SA17 4TA",
    "sg:province":"Carmarthenshire",
    "sg:tags":[
        "society",
        "friendly"
    ],
    "wof:name":"Dyfed Credit Ltd",
    "wof:placetype":"venue"
},
  "geometry": {"coordinates":[-4.305484,51.734463],"type":"Point"}
}