{
  "type": "Feature",
  "properties": {
    "addr:full":"20 Alloa Road, Goodmayes Ilford Essex IG3 9SP",
    "addr:housenumber":"20",
    "addr:postcode":"ig3 9sp",
    "addr:street":"Alloa Road",
    "iso:country":"GB",
    "sg:address":"20 Alloa Road, Goodmayes",
    "sg:city":"Ilford",
    "sg:classifiers":[
        {
            "category":"Education",
            "subcategory":"Dance Studio",
            "type":"Public Place"
        }
    ],
    "sg:postcode":"IG3 9SP",
    "sg:province":"Essex",
    "sg:tags":[
        "school",
        "dancing"
    ],
    "wof:name":"Doreen Win-Kree School of Dancing",
    "wof:placetype":"venue"
},
  "geometry": {"coordinates":[0.1118199974,51.5618896484],"type":"Point"}
}