{
  "type": "Feature",
  "properties": {
    "iso:country":"GB",
    "sg:address":"16 Heathgate",
    "sg:city":"Witham",
    "sg:classifiers":[
        {
            "category":"Building & Trades",
            "subcategory":"Plumbing",
            "type":"Services"
        }
    ],
    "sg:postcode":"CM8 3NZ",
    "sg:province":"Essex",
    "sg:tags":[
        "heating"
    ],
    "wof:name":"Iszard Heating & Plumbing",
    "wof:placetype":"venue"
},
  "geometry": {"coordinates":[0.666161,51.781311],"type":"Point"}
}