{
  "type": "Feature",
  "properties": {
    "addr:full":"12 Wartling Dr, Little Common Bexhill-on-sea East Sussex TN39 4QN",
    "addr:housenumber":"12",
    "addr:postcode":"bexhill-on-sea;tn39 4qn",
    "addr:street":"Wartling Dr",
    "iso:country":"GB",
    "sg:address":"12 Wartling Dr, Little Common",
    "sg:city":"Bexhill-on-sea",
    "sg:classifiers":[
        {
            "category":"Building & Trades",
            "subcategory":"Construction",
            "type":"Services"
        }
    ],
    "sg:postcode":"TN39 4QN",
    "sg:province":"East Sussex",
    "sg:tags":[
        "glazier"
    ],
    "wof:name":"Chapman,John W,",
    "wof:placetype":"venue"
},
  "geometry": {"coordinates":[0.410204,50.846703],"type":"Point"}
}