{
  "type": "Feature",
  "properties": {
    "iso:country":"GB",
    "sg:address":"18 St Mary-at-hill",
    "sg:city":"London",
    "sg:classifiers":[
        {
            "category":"Professional",
            "subcategory":"Business Services",
            "type":"Services"
        }
    ],
    "sg:phone":"+44 20 7283 2373",
    "sg:postcode":"EC3R 8EE",
    "sg:province":"Greater London",
    "sg:tags":[
        "holding",
        "trade"
    ],
    "wof:name":"Minories Holdings Ltd.",
    "wof:placetype":"venue"
},
  "geometry": {"coordinates":[-0.0838200003,51.5096702576],"type":"Point"}
}