{
  "type": "Feature",
  "properties": {
    "iso:country":"GB",
    "sg:address":"31 Victoria Rd",
    "sg:city":"Bridlington",
    "sg:classifiers":[
        {
            "category":"Travel",
            "subcategory":"Hotels & Motels",
            "type":"Entertainment"
        }
    ],
    "sg:phone":"+44 1262 675511",
    "sg:postcode":"YO15 2AT",
    "sg:province":"East Riding of Yorkshire",
    "sg:tags":[
        "house",
        "guest"
    ],
    "wof:name":"Fernlea Guest House",
    "wof:placetype":"venue"
},
  "geometry": {"coordinates":[-0.187399,54.08749],"type":"Point"}
}