{
  "type": "Feature",
  "properties": {
    "iso:country":"GB",
    "sg:address":"12 Denbigh Street",
    "sg:city":"Llanrwst",
    "sg:classifiers":[
        {
            "category":"Bars & Pubs",
            "type":"Food & Drink"
        },
        {
            "category":"Community Center",
            "subcategory":"Social",
            "type":"Public Place"
        }
    ],
    "sg:phone":"+44 1492 640496",
    "sg:postcode":"LL26 0LL",
    "sg:province":"Conwy",
    "sg:tags":[
        "pubs",
        "house",
        "inn",
        "activity"
    ],
    "wof:name":"Red Lion Hotel",
    "wof:placetype":"venue"
},
  "geometry": {"coordinates":[-3.796854,53.139015],"type":"Point"}
}