{
  "type": "Feature",
  "properties": {
    "addr:full":"5 Holt Ct Heneage St West Aston Business Birmingham West Midlands B7 4AX",
    "addr:housenumber":"5",
    "addr:postcode":"b7 4ax",
    "addr:street":"Holt Ct Heneage St West Aston",
    "iso:country":"GB",
    "sg:address":"5 Holt Ct Heneage St West Aston Business",
    "sg:city":"Birmingham",
    "sg:classifiers":[
        {
            "category":"Professional",
            "subcategory":"Engineering",
            "type":"Services"
        }
    ],
    "sg:phone":"+44 121 606 1200",
    "sg:postcode":"B7 4AX",
    "sg:province":"West Midlands",
    "sg:tags":[
        "electronic",
        "engineer"
    ],
    "wof:name":"Sagem S A",
    "wof:placetype":"venue"
},
  "geometry": {"coordinates":[-1.884165,52.485771],"type":"Point"}
}