{
  "type": "Feature",
  "properties": {
    "addr:full":"Kiran Virdee Medical Centre, Sultan Road Lordswood Chatham Kent ME5 8TJ",
    "addr:postcode":"me5 8tj",
    "addr:street":"Sultan Road Lordswood",
    "iso:country":"GB",
    "sg:address":"Kiran Virdee Medical Centre, Sultan Road Lordswood",
    "sg:city":"Chatham",
    "sg:classifiers":[
        {
            "category":"Health Services",
            "subcategory":"Doctor",
            "type":"Services"
        },
        {
            "category":"Health Services",
            "subcategory":"Clinic",
            "type":"Services"
        }
    ],
    "sg:phone":"+44 1634 669221",
    "sg:postcode":"ME5 8TJ",
    "sg:province":"Kent",
    "sg:tags":[
        "nh",
        "practitioners"
    ],
    "wof:name":"Kiran Virdee",
    "wof:placetype":"venue"
},
  "geometry": {"coordinates":[0.5454900265,51.3337402344],"type":"Point"}
}