{
  "type": "Feature",
  "properties": {
    "iso:country":"GB",
    "sg:address":"2 Mill Lane, Peasmarsh",
    "sg:city":"Guildford",
    "sg:classifiers":[
        {
            "category":"Home & Garden",
            "subcategory":"Building Materials",
            "type":"Retail Goods"
        }
    ],
    "sg:phone":"+44 1483 458382",
    "sg:postcode":"GU3 1NB",
    "sg:province":"Surrey",
    "sg:tags":[
        "gate",
        "door",
        "barrier"
    ],
    "wof:name":"Door Entry Services",
    "wof:placetype":"venue"
},
  "geometry": {"coordinates":[-0.583267,51.207062],"type":"Point"}
}