{
  "type": "Feature",
  "properties": {
    "iso:country":"GB",
    "sg:address":"8 Lawn St",
    "sg:city":"Paisley",
    "sg:classifiers":[
        {
            "category":"Bars & Pubs",
            "type":"Food & Drink"
        }
    ],
    "sg:postcode":"PA1 1HA",
    "sg:province":"Renfrewshire",
    "sg:tags":[
        "pubs",
        "inn"
    ],
    "wof:name":"Abbey Bar (The)",
    "wof:placetype":"venue"
},
  "geometry": {"coordinates":[-4.419643,55.846447],"type":"Point"}
}