{
  "type": "Feature",
  "properties": {
    "addr:full":"3 Abingdon Place, Banwell Rd, Combe Down Bath Somerset BA2 2UH",
    "addr:housenumber":"3",
    "addr:postcode":"ba2 2uh",
    "addr:street":"Abingdon Place Banwell Rd",
    "iso:country":"GB",
    "sg:address":"3 Abingdon Place, Banwell Rd, Combe Down",
    "sg:city":"Bath",
    "sg:classifiers":[
        {
            "category":"Building & Trades",
            "subcategory":"Construction",
            "type":"Services"
        }
    ],
    "sg:phone":"+44 1225 836088",
    "sg:postcode":"BA2 2UH",
    "sg:province":"Somerset",
    "sg:tags":[
        "installers",
        "gas"
    ],
    "wof:name":"A.G Oldall",
    "wof:placetype":"venue"
},
  "geometry": {"coordinates":[-2.379496,51.355698],"type":"Point"}
}