{
  "type": "Feature",
  "properties": {
    "iso:country":"GB",
    "sg:address":"Wellington House, Wellington Rd",
    "sg:city":"Wokingham",
    "sg:classifiers":[
        {
            "category":"Organizations",
            "subcategory":"Non-profit Organization",
            "type":"Services"
        }
    ],
    "sg:phone":"+44 118 978 9656",
    "sg:postcode":"RG40 2AG",
    "sg:province":"Berkshire",
    "sg:tags":[
        "organisation",
        "voluntary",
        "charity"
    ],
    "wof:name":"Wokinghan Community Services",
    "wof:placetype":"venue"
},
  "geometry": {"coordinates":[-0.842057,51.410534],"type":"Point"}
}