{
  "type": "Feature",
  "properties": {
    "addr:full":"Penybont Llandrindod Wells Powys LD1 5UA",
    "addr:postcode":"ld1 5ua",
    "addr:street":"Llandrindod Wells",
    "iso:country":"GB",
    "sg:address":"Penybont",
    "sg:city":"Llandrindod Wells",
    "sg:classifiers":[
        {
            "category":"Retail",
            "subcategory":"Auto Repair",
            "type":"Services"
        }
    ],
    "sg:phone":"+44 1597 851770",
    "sg:postcode":"LD1 5UA",
    "sg:province":"Powys",
    "sg:tags":[
        "modification",
        "garage"
    ],
    "wof:name":"Penybont Services",
    "wof:placetype":"venue"
},
  "geometry": {"coordinates":[-3.29729,52.267941],"type":"Point"}
}