{
  "type": "Feature",
  "properties": {
    "iso:country":"GB",
    "sg:address":"95 Stanley Road",
    "sg:city":"Hornchurch",
    "sg:classifiers":[
        {
            "category":"Professional",
            "subcategory":"Computer Services",
            "type":"Services"
        }
    ],
    "sg:phone":"+44 7831 557555",
    "sg:postcode":"RM12 4JP",
    "sg:province":"Essex",
    "sg:tags":[
        "system",
        "software"
    ],
    "wof:name":"Database Engineering (U K) Ltd.",
    "wof:placetype":"venue"
},
  "geometry": {"coordinates":[0.213951,51.558704],"type":"Point"}
}