{
  "type": "Feature",
  "properties": {
    "addr:full":"493 Saffron Lane Leicester Leicestershire LE2 6UG",
    "addr:housenumber":"493",
    "addr:postcode":"le2 6ug",
    "addr:street":"Saffron Lane",
    "iso:country":"GB",
    "sg:address":"493 Saffron Lane",
    "sg:city":"Leicester",
    "sg:classifiers":[
        {
            "category":"Shopping",
            "subcategory":"News",
            "type":"Retail Goods"
        }
    ],
    "sg:phone":"+44 116 224 2304",
    "sg:postcode":"LE2 6UG",
    "sg:province":"Leicestershire",
    "sg:tags":[
        "newsagent"
    ],
    "wof:name":"S K S News",
    "wof:placetype":"venue"
},
  "geometry": {"coordinates":[-1.1399040222,52.6024246216],"type":"Point"}
}