{
  "type": "Feature",
  "properties": {
    "addr:full":"89 Wandsworth Bridge Road London Greater London SW6 2TD",
    "addr:housenumber":"89",
    "addr:postcode":"sw6 2td",
    "addr:street":"Wandsworth Bridge Road",
    "iso:country":"GB",
    "sg:address":"89 Wandsworth Bridge Road",
    "sg:city":"London",
    "sg:classifiers":[
        {
            "category":"Real Estate",
            "subcategory":"Architect",
            "type":"Services"
        }
    ],
    "sg:phone":"+44 20 7610 6006",
    "sg:postcode":"SW6 2TD",
    "sg:province":"Greater London",
    "wof:name":"Simon Smith & Michael Brooke Architcets",
    "wof:placetype":"venue"
},
  "geometry": {"coordinates":[-0.191792,51.473915],"type":"Point"}
}