{
  "type": "Feature",
  "properties": {
    "iso:country":"GB",
    "sg:address":"6b Mains Drive",
    "sg:city":"Erskine",
    "sg:classifiers":[
        {
            "category":"Shopping",
            "subcategory":"News",
            "type":"Retail Goods"
        }
    ],
    "sg:phone":"+44 141 561 0015",
    "sg:postcode":"PA8 7JQ",
    "sg:province":"Renfrewshire",
    "sg:tags":[
        "newsagent"
    ],
    "wof:name":"A A Superstores",
    "wof:placetype":"venue"
},
  "geometry": {"coordinates":[-4.443821,55.900143],"type":"Point"}
}