{
  "type": "Feature",
  "properties": {
    "iso:country":"GB",
    "sg:address":"54 Stanley Road, Garndiffaith",
    "sg:city":"Pontypool",
    "sg:classifiers":[
        {
            "category":"Personal",
            "subcategory":"Beauty Salon",
            "type":"Services"
        },
        {
            "category":"Personal",
            "subcategory":"Barber",
            "type":"Services"
        }
    ],
    "sg:phone":"+44 1495 774748",
    "sg:postcode":"NP4 7LH",
    "sg:province":"Monmouthshire",
    "sg:tags":[
        "unisex",
        "hairdresser"
    ],
    "wof:name":"The Head Gardener",
    "wof:placetype":"venue"
},
  "geometry": {"coordinates":[-3.065359,51.734039],"type":"Point"}
}