{
  "type": "Feature",
  "properties": {
    "iso:country":"GB",
    "sg:address":"72 Foleshill Road",
    "sg:city":"Coventry",
    "sg:classifiers":[
        {
            "category":"Retail",
            "subcategory":"Auto Repair",
            "type":"Services"
        }
    ],
    "sg:phone":"+44 24 7655 3000",
    "sg:postcode":"CV1 4JJ",
    "sg:province":"West Midlands",
    "sg:tags":[
        "modification",
        "garage",
        "related"
    ],
    "wof:name":"Nw Autocentres Ltd.",
    "wof:placetype":"venue"
},
  "geometry": {"coordinates":[-1.508293,52.417221],"type":"Point"}
}