{
  "type": "Feature",
  "properties": {
    "iso:country":"GB",
    "sg:address":"Berkeley Buildings, Great Ormes Road",
    "sg:city":"Llandudno",
    "sg:classifiers":[
        {
            "category":"Personal",
            "subcategory":"Beauty Salon",
            "type":"Services"
        }
    ],
    "sg:postcode":"LL30 2BW",
    "sg:province":"Conwy",
    "sg:tags":[
        "unisex",
        "hairdresser"
    ],
    "wof:name":"The Hair Box",
    "wof:placetype":"venue"
},
  "geometry": {"coordinates":[-3.818764,53.322433],"type":"Point"}
}