{
  "type": "Feature",
  "properties": {
    "addr:full":"98 Savile Rd Dewsbury West Yorkshire WF12 9LP",
    "addr:housenumber":"98",
    "addr:postcode":"wf12 9lp",
    "addr:street":"Savile Rd",
    "iso:country":"GB",
    "sg:address":"98 Savile Rd",
    "sg:city":"Dewsbury",
    "sg:classifiers":[
        {
            "category":"Home & Garden",
            "subcategory":"Furniture",
            "type":"Retail Goods"
        }
    ],
    "sg:phone":"+44 1924 461450",
    "sg:postcode":"WF12 9LP",
    "sg:province":"West Yorkshire",
    "wof:name":"Dad R Furniture Bargain Centre",
    "wof:placetype":"venue"
},
  "geometry": {"coordinates":[-1.6321099997,53.6841125488],"type":"Point"}
}