{
  "type": "Feature",
  "properties": {
    "addr:full":"190 High Street, Lye Stourbridge West Midlands DY9 8LH",
    "addr:housenumber":"190",
    "addr:postcode":"dy9 8lh",
    "addr:street":"High Street",
    "iso:country":"GB",
    "sg:address":"190 High Street, Lye",
    "sg:city":"Stourbridge",
    "sg:classifiers":[
        {
            "category":"Retail",
            "subcategory":"Repair Shop",
            "type":"Services"
        },
        {
            "category":"Shopping",
            "subcategory":"Used Merchandise",
            "type":"Retail Goods"
        }
    ],
    "sg:postcode":"DY9 8LH",
    "sg:province":"West Midlands",
    "sg:tags":[
        "sale",
        "second-hand"
    ],
    "wof:name":"T J'S DISCOUNT CENTRE",
    "wof:placetype":"venue"
},
  "geometry": {"coordinates":[-2.115266,52.457542],"type":"Point"}
}