{
  "type": "Feature",
  "properties": {
    "addr:full":"110 Honeybourne Rd Halesowen West Midlands B63 3HD",
    "addr:housenumber":"110",
    "addr:postcode":"b63 3hd",
    "addr:street":"Honeybourne Rd",
    "iso:country":"GB",
    "sg:address":"110 Honeybourne Rd",
    "sg:city":"Halesowen",
    "sg:classifiers":[
        {
            "category":"Professional",
            "subcategory":"Secretarial Services",
            "type":"Services"
        }
    ],
    "sg:phone":"+44 121 550 0312",
    "sg:postcode":"B63 3HD",
    "sg:province":"West Midlands",
    "wof:name":"Hannaford Business Services",
    "wof:placetype":"venue"
},
  "geometry": {"coordinates":[-2.043049,52.447853],"type":"Point"}
}