{
  "type": "Feature",
  "properties": {
    "addr:full":"8a Front Street, Acomb York North Yorkshire YO24 3BZ",
    "addr:housenumber":"8a",
    "addr:postcode":"yo24 3bz",
    "addr:street":"Front Street",
    "iso:country":"GB",
    "sg:address":"8a Front Street, Acomb",
    "sg:city":"York",
    "sg:classifiers":[
        {
            "category":"Professional",
            "subcategory":"Accounting & Tax Preparation",
            "type":"Services"
        }
    ],
    "sg:phone":"+44 1904 792226",
    "sg:postcode":"YO24 3BZ",
    "sg:province":"North Yorkshire",
    "sg:tags":[
        "accountant"
    ],
    "wof:name":"A J Brown",
    "wof:placetype":"venue"
},
  "geometry": {"coordinates":[-1.126385,53.954708],"type":"Point"}
}