{
  "type": "Feature",
  "properties": {
    "addr:full":"127 High Street South Rushden Bedfordshire NN10 0RB",
    "addr:housenumber":"127",
    "addr:postcode":"nn10 0rb",
    "addr:street":"High Street South",
    "iso:country":"GB",
    "sg:address":"127 High Street South",
    "sg:city":"Rushden",
    "sg:classifiers":[
        {
            "category":"Bars & Pubs",
            "type":"Food & Drink"
        }
    ],
    "sg:phone":"+44 1933 312235",
    "sg:postcode":"NN10 0RB",
    "sg:province":"Bedfordshire",
    "sg:tags":[
        "pubs",
        "inn"
    ],
    "wof:name":"The Compasses",
    "wof:placetype":"venue"
},
  "geometry": {"coordinates":[-0.592626,52.285137],"type":"Point"}
}