{
  "type": "Feature",
  "properties": {
    "addr:full":"31 Drakes Road Amersham Buckinghamshire HP7 9ED",
    "addr:housenumber":"31",
    "addr:postcode":"hp7 9ed",
    "addr:street":"Drakes Road",
    "iso:country":"GB",
    "sg:address":"31 Drakes Road",
    "sg:city":"Amersham",
    "sg:classifiers":[
        {
            "category":"Taxi",
            "type":"Transportation"
        },
        {
            "category":"Military Area",
            "subcategory":"Air Force Base",
            "type":"Public Place"
        }
    ],
    "sg:phone":"+44 1494 724165",
    "sg:postcode":"HP7 9ED",
    "sg:province":"Buckinghamshire",
    "sg:tags":[
        "mini",
        "hire",
        "private",
        "cab"
    ],
    "wof:name":"Jordans Taxis",
    "wof:placetype":"venue"
},
  "geometry": {"coordinates":[-0.597853,51.668583],"type":"Point"}
}