{
  "type": "Feature",
  "properties": {
    "addr:full":"Matlock Lido, Imperial Road Matlock Derbyshire DE4 3NL",
    "addr:postcode":"de4 3nl",
    "addr:street":"Imperial Road",
    "iso:country":"GB",
    "sg:address":"Matlock Lido, Imperial Road",
    "sg:city":"Matlock",
    "sg:classifiers":[
        {
            "category":"Government",
            "subcategory":"Office",
            "type":"Public Place"
        }
    ],
    "sg:phone":"+44 1629 582843",
    "sg:postcode":"DE4 3NL",
    "sg:province":"Derbyshire",
    "sg:tags":[
        "local"
    ],
    "wof:name":"Derbyshire Dales District Council",
    "wof:placetype":"venue"
},
  "geometry": {"coordinates":[-1.5482740402,53.1356163025],"type":"Point"}
}