{
  "type": "Feature",
  "properties": {
    "addr:full":"124 Rickmansworth Road Watford Hertfordshire WD18 7JW",
    "addr:housenumber":"124",
    "addr:postcode":"wd18 7jw",
    "addr:street":"Rickmansworth Road",
    "iso:country":"GB",
    "sg:address":"124 Rickmansworth Road",
    "sg:city":"Watford",
    "sg:classifiers":[
        {
            "category":"Communications",
            "subcategory":"Newspaper",
            "type":"Services"
        }
    ],
    "sg:phone":"+44 1923 242211",
    "sg:postcode":"WD18 7JW",
    "sg:province":"Hertfordshire",
    "sg:tags":[
        "magazine"
    ],
    "wof:name":"Observer Newspapers",
    "wof:placetype":"venue"
},
  "geometry": {"coordinates":[-0.4196090102,51.6535072327],"type":"Point"}
}