{
  "type": "Feature",
  "properties": {
    "addr:full":"2 The Old Dairy, North Street Melton Mowbray Leicestershire LE13 1NL",
    "addr:housenumber":"2",
    "addr:postcode":"le13 1nl",
    "addr:street":"The Old;North Street",
    "iso:country":"GB",
    "sg:address":"2 The Old Dairy, North Street",
    "sg:city":"Melton Mowbray",
    "sg:classifiers":[
        {
            "category":"Professional",
            "subcategory":"Engineering",
            "type":"Services"
        }
    ],
    "sg:phone":"+44 116 234 8000",
    "sg:postcode":"LE13 1NL",
    "sg:province":"Leicestershire",
    "sg:tags":[
        "consulting",
        "engineer"
    ],
    "wof:name":"Cassells Group Ltd.",
    "wof:placetype":"venue"
},
  "geometry": {"coordinates":[-0.8895549774,52.7658691406],"type":"Point"}
}