{
  "type": "Feature",
  "properties": {
    "addr:full":"Echo House, Pennywell Indust Est Sunderland Tyne and Wear SR4 9ER",
    "addr:postcode":"sr4 9er",
    "addr:street":"Pennywell Indust Est",
    "iso:country":"GB",
    "sg:address":"Echo House, Pennywell Indust Est",
    "sg:city":"Sunderland",
    "sg:classifiers":[
        {
            "category":"Shopping",
            "subcategory":"Books",
            "type":"Retail Goods"
        }
    ],
    "sg:phone":"+44 191 534 4916",
    "sg:postcode":"SR4 9ER",
    "sg:province":"Tyne and Wear",
    "wof:name":"North East Jobs",
    "wof:placetype":"venue"
},
  "geometry": {"coordinates":[-1.4547100067,54.8932113647],"type":"Point"}
}