{
  "type": "Feature",
  "properties": {
    "addr:full":"Immingham Dock Immingham Lincolnshire DN40 2LY",
    "addr:postcode":"dn40 2ly",
    "iso:country":"GB",
    "sg:address":"Immingham Dock",
    "sg:city":"Immingham",
    "sg:classifiers":[
        {
            "category":"Harbor",
            "type":"Transportation"
        }
    ],
    "sg:phone":"+44 1469 572015",
    "sg:postcode":"DN40 2LY",
    "sg:province":"Lincolnshire",
    "sg:tags":[
        "dock",
        "ports",
        "harbour"
    ],
    "wof:name":"Pilots Lobby",
    "wof:placetype":"venue"
},
  "geometry": {"coordinates":[-0.2289270014,53.633731842],"type":"Point"}
}