{
  "type": "Feature",
  "properties": {
    "addr:full":"8 Hinckley Road, Walsgrave On Sowe Coventry Warwickshire CV2 2EX",
    "addr:housenumber":"8",
    "addr:postcode":"cv2 2ex",
    "addr:street":"Hinckley Road",
    "iso:country":"GB",
    "sg:address":"8 Hinckley Road, Walsgrave On Sowe",
    "sg:city":"Coventry",
    "sg:classifiers":[
        {
            "category":"Building & Trades",
            "subcategory":"Plumbing",
            "type":"Services"
        }
    ],
    "sg:phone":"+44 24 7661 4762",
    "sg:postcode":"CV2 2EX",
    "sg:province":"Warwickshire",
    "sg:tags":[
        "heating"
    ],
    "wof:name":"Central Boilercare",
    "wof:placetype":"venue"
},
  "geometry": {"coordinates":[-1.4434349537,52.4252853394],"type":"Point"}
}