{
  "type": "Feature",
  "properties": {
    "iso:country":"GB",
    "sg:address":"38 Rydding Sq",
    "sg:city":"West Bromwich",
    "sg:classifiers":[
        {
            "category":"Building & Trades",
            "subcategory":"Construction",
            "type":"Services"
        }
    ],
    "sg:phone":"+44 121 556 8627",
    "sg:postcode":"B71 2AB",
    "sg:province":"West Midlands",
    "sg:tags":[
        "decorator",
        "painter"
    ],
    "wof:name":"Piper-Richards",
    "wof:placetype":"venue"
},
  "geometry": {"coordinates":[-2.00775,52.539951],"type":"Point"}
}