{
  "type": "Feature",
  "properties": {
    "addr:full":"10 Aintree Drive Leamington Spa Warwickshire CV32 7TU",
    "addr:housenumber":"10",
    "addr:postcode":"cv32 7tu",
    "addr:street":"Aintree Drive",
    "iso:country":"GB",
    "sg:address":"10 Aintree Drive",
    "sg:city":"Leamington Spa",
    "sg:classifiers":[
        {
            "category":"Military Area",
            "subcategory":"Air Force Base",
            "type":"Public Place"
        }
    ],
    "sg:phone":"+44 1926 888862",
    "sg:postcode":"CV32 7TU",
    "sg:province":"Warwickshire",
    "sg:tags":[
        "taxi",
        "hire",
        "private"
    ],
    "wof:name":"Rai Taxis",
    "wof:placetype":"venue"
},
  "geometry": {"coordinates":[-1.514463,52.303783],"type":"Point"}
}