{
  "type": "Feature",
  "properties": {
    "addr:full":"135-139 Bradshawgate Bolton Lancashire BL2 1BJ",
    "addr:housenumber":"135-139",
    "addr:postcode":"bl2 1bj",
    "addr:street":"Bradshawgate Bolton",
    "iso:country":"GB",
    "sg:address":"135-139 Bradshawgate",
    "sg:city":"Bolton",
    "sg:classifiers":[
        {
            "category":"Home & Garden",
            "subcategory":"Furniture",
            "type":"Retail Goods"
        }
    ],
    "sg:phone":"+44 1204 398177",
    "sg:postcode":"BL2 1BJ",
    "sg:province":"Lancashire",
    "wof:name":"C S Lounge Suites",
    "wof:placetype":"venue"
},
  "geometry": {"coordinates":[-2.4250779152,53.57604599],"type":"Point"}
}