{
  "type": "Feature",
  "properties": {
    "iso:country":"GB",
    "sg:address":"14 Rectory Road",
    "sg:city":"Nottingham",
    "sg:classifiers":[
        {
            "category":"Professional",
            "subcategory":"Engineering",
            "type":"Services"
        }
    ],
    "sg:postcode":"NG2 6BG",
    "sg:province":"Nottinghamshire",
    "sg:tags":[
        "contractor",
        "electrical",
        "engineer"
    ],
    "wof:name":"Rapiersystem Ltd.",
    "wof:placetype":"venue"
},
  "geometry": {"coordinates":[-1.1309239864,52.9294166565],"type":"Point"}
}