{
  "type": "Feature",
  "properties": {
    "iso:country":"GB",
    "sg:address":"East Park Drive",
    "sg:city":"Blackpool",
    "sg:classifiers":[
        {
            "category":"Social Services",
            "subcategory":"Adult Care",
            "type":"Services"
        },
        {
            "category":"Landmark",
            "subcategory":"Tourist Attraction",
            "type":"Public Place"
        }
    ],
    "sg:phone":"+44 1253 763827",
    "sg:postcode":"FY3 9RB",
    "sg:province":"Lancashire",
    "sg:tags":[
        "model",
        "interest",
        "village"
    ],
    "wof:name":"Home Blackpool Model Village & Gardens",
    "wof:placetype":"venue"
},
  "geometry": {"coordinates":[-3.020994,53.810436],"type":"Point"}
}