{
  "type": "Feature",
  "properties": {
    "iso:country":"GB",
    "sg:address":"Choudhary House, 24 Dark Lane, Ardwick",
    "sg:city":"Manchester",
    "sg:classifiers":[
        {
            "category":"Shopping",
            "subcategory":"Clothing, Apparel, & Fashions",
            "type":"Retail Goods"
        }
    ],
    "sg:phone":"+44 161 274 3456",
    "sg:postcode":"M12 6FA",
    "sg:province":"Greater Manchester",
    "sg:tags":[
        "clothing",
        "fabric"
    ],
    "wof:name":"Choudhary Trading Co. Ltd.",
    "wof:placetype":"venue"
},
  "geometry": {"coordinates":[-2.219192028,53.4751358032],"type":"Point"}
}