{
  "type": "Feature",
  "properties": {
    "iso:country":"GB",
    "sg:address":"10 Cedar Square",
    "sg:city":"Blackpool",
    "sg:classifiers":[
        {
            "category":"Real Estate",
            "subcategory":"Surveying",
            "type":"Services"
        },
        {
            "category":"Real Estate",
            "subcategory":"Real Estate Agent",
            "type":"Services"
        }
    ],
    "sg:phone":"+44 1253 295599",
    "sg:postcode":"FY1 1BP",
    "sg:province":"Lancashire",
    "sg:tags":[
        "surveyor",
        "valuer"
    ],
    "wof:name":"NOBLETT WALKER",
    "wof:placetype":"venue"
},
  "geometry": {"coordinates":[-3.0503408909,53.818447113],"type":"Point"}
}