{
  "type": "Feature",
  "properties": {
    "addr:full":"32 Frederick Street Sunderland Tyne and Wear SR1 1LN",
    "addr:housenumber":"32",
    "addr:postcode":"sr1 1ln",
    "addr:street":"Frederick Street",
    "iso:country":"GB",
    "sg:address":"32 Frederick Street",
    "sg:city":"Sunderland",
    "sg:classifiers":[
        {
            "category":"Professional",
            "subcategory":"Employment Agencies",
            "type":"Services"
        }
    ],
    "sg:phone":"+44 191 510 0788",
    "sg:postcode":"SR1 1LN",
    "sg:province":"Tyne and Wear",
    "sg:tags":[
        "consultant"
    ],
    "wof:name":"Flagstaff Services",
    "wof:placetype":"venue"
},
  "geometry": {"coordinates":[-1.3787549734,54.9047088623],"type":"Point"}
}