{
  "type": "Feature",
  "properties": {
    "iso:country":"GB",
    "sg:address":"82 Leytonstone Road",
    "sg:city":"London",
    "sg:classifiers":[
        {
            "category":"Bars & Pubs",
            "type":"Food & Drink"
        },
        {
            "category":"Professional",
            "subcategory":"Management & Consulting",
            "type":"Services"
        }
    ],
    "sg:phone":"+44 20 8522 7131",
    "sg:postcode":"E15 1SQ",
    "sg:province":"Greater London",
    "sg:tags":[
        "pubs",
        "inn",
        "holding",
        "activity"
    ],
    "wof:name":"GALA HOLDINGS LTD",
    "wof:placetype":"venue"
},
  "geometry": {"coordinates":[0.005241,51.549652],"type":"Point"}
}