{
  "type": "Feature",
  "properties": {
    "addr:full":"37 Old Street Clevedon Somerset BS21 6DA",
    "addr:housenumber":"37",
    "addr:postcode":"bs21 6da",
    "addr:street":"Old Street",
    "iso:country":"GB",
    "sg:address":"37 Old Street",
    "sg:city":"Clevedon",
    "sg:classifiers":[
        {
            "category":"Organizations",
            "subcategory":"Non-profit Organization",
            "type":"Services"
        }
    ],
    "sg:phone":"+44 1275 341587",
    "sg:postcode":"BS21 6DA",
    "sg:province":"Somerset",
    "sg:tags":[
        "organisation",
        "voluntary",
        "charity"
    ],
    "wof:name":"The Salvation Army",
    "wof:placetype":"venue"
},
  "geometry": {"coordinates":[-2.8498499393,51.4366149902],"type":"Point"}
}