{
  "type": "Feature",
  "properties": {
    "iso:country":"GB",
    "sg:address":"8 Market Hall",
    "sg:city":"Doncaster",
    "sg:classifiers":[
        {
            "category":"Food & Beverages",
            "subcategory":"Meat & Fish",
            "type":"Retail Goods"
        }
    ],
    "sg:phone":"+44 1302 326229",
    "sg:postcode":"DN1 1NG",
    "sg:province":"South Yorkshire",
    "sg:tags":[
        "butcher"
    ],
    "wof:name":"T J Plane",
    "wof:placetype":"venue"
},
  "geometry": {"coordinates":[-1.133433,53.524899],"type":"Point"}
}