{
  "type": "Feature",
  "properties": {
    "addr:full":"Rock Road Spennymoor Durham DL16 7DA",
    "addr:postcode":"dl16 7da",
    "addr:street":"Rock Road",
    "iso:country":"GB",
    "sg:address":"Rock Road",
    "sg:city":"Spennymoor",
    "sg:classifiers":[
        {
            "category":"Education",
            "subcategory":"School",
            "type":"Public Place"
        },
        {
            "category":"Government",
            "subcategory":"Office",
            "type":"Public Place"
        }
    ],
    "sg:phone":"+44 1388 814523",
    "sg:postcode":"DL16 7DA",
    "sg:province":"Durham",
    "sg:tags":[
        "local",
        "authority"
    ],
    "wof:name":"Durham County Council",
    "wof:placetype":"venue"
},
  "geometry": {"coordinates":[-1.6123189926,54.6917686462],"type":"Point"}
}