{
  "type": "Feature",
  "properties": {
    "addr:full":"Sale Masonic Hall, Tatton Road Manchester Cheshire M33 1EE",
    "addr:postcode":"m33 1ee",
    "addr:street":"Tatton Road",
    "iso:country":"GB",
    "sg:address":"Sale Masonic Hall, Tatton Road",
    "sg:city":"Manchester",
    "sg:classifiers":[
        {
            "category":"Professional",
            "type":"Services"
        }
    ],
    "sg:postcode":"M33 1EE",
    "sg:province":"Cheshire",
    "sg:tags":[
        "caterer"
    ],
    "wof:name":"Martin Coughlan Catering Services",
    "wof:placetype":"venue"
},
  "geometry": {"coordinates":[-2.2488090992,53.4796218872],"type":"Point"}
}