{
  "type": "Feature",
  "properties": {
    "iso:country":"GB",
    "sg:address":"23 Elmfield Rd, New Rossington",
    "sg:city":"Doncaster",
    "sg:classifiers":[
        {
            "category":"Retail",
            "subcategory":"Funeral Services",
            "type":"Services"
        }
    ],
    "sg:phone":"+44 1302 863266",
    "sg:postcode":"DN11 0BS",
    "sg:province":"South Yorkshire",
    "sg:tags":[
        "mnfr",
        "monumental",
        "mason"
    ],
    "wof:name":"Zengold",
    "wof:placetype":"venue"
},
  "geometry": {"coordinates":[-1.0670449734,53.4715690613],"type":"Point"}
}