{
  "type": "Feature",
  "properties": {
    "iso:country":"GB",
    "sg:address":"5 Victoria Avenue",
    "sg:city":"Hastings",
    "sg:classifiers":[
        {
            "category":"Retail",
            "subcategory":"Veterinary Services",
            "type":"Services"
        }
    ],
    "sg:phone":"+44 1424 438685",
    "sg:postcode":"TN35 5BY",
    "sg:province":"East Sussex",
    "sg:tags":[
        "surgeon"
    ],
    "wof:name":"Paul R Cooper",
    "wof:placetype":"venue"
},
  "geometry": {"coordinates":[0.6085479856,50.8731155396],"type":"Point"}
}