{
  "type": "Feature",
  "properties": {
    "iso:country":"GB",
    "sg:address":"Unit 8 Mersey Road Indust Est, Mersey Road North",
    "sg:city":"Manchester",
    "sg:classifiers":[
        {
            "category":"Manufacturing",
            "subcategory":"Paper Products",
            "type":"Manufacturing & Wholesale Goods"
        }
    ],
    "sg:phone":"+44 161 681 3522",
    "sg:postcode":"M35 9LU",
    "sg:province":"Lancashire",
    "sg:tags":[
        "cardboard"
    ],
    "wof:name":"Slitmaster Ltd",
    "wof:placetype":"venue"
},
  "geometry": {"coordinates":[-2.143859,53.515079],"type":"Point"}
}