{
  "type": "Feature",
  "properties": {
    "iso:country":"GB",
    "sg:address":"64 Dale Street",
    "sg:city":"Liverpool",
    "sg:classifiers":[
        {
            "category":"Professional",
            "subcategory":"Art Services",
            "type":"Services"
        }
    ],
    "sg:phone":"+44 151 236 3996",
    "sg:postcode":"L2 5ST",
    "sg:province":"Merseyside",
    "sg:tags":[
        "photographer"
    ],
    "wof:name":"Philip Ainsworth",
    "wof:placetype":"venue"
},
  "geometry": {"coordinates":[-2.98763,53.40834],"type":"Point"}
}