{
  "type": "Feature",
  "properties": {
    "addr:full":"1 Buccleuch Street Innerleithen Scottish Borders EH44 6LA",
    "addr:housenumber":"1",
    "addr:postcode":"eh44 6la",
    "addr:street":"Buccleuch Street",
    "iso:country":"GB",
    "sg:address":"1 Buccleuch Street",
    "sg:city":"Innerleithen",
    "sg:classifiers":[
        {
            "category":"Education",
            "subcategory":"Library",
            "type":"Public Place"
        },
        {
            "category":"Government",
            "subcategory":"Office",
            "type":"Public Place"
        }
    ],
    "sg:phone":"+44 1896 830789",
    "sg:postcode":"EH44 6LA",
    "sg:province":"Scottish Borders",
    "sg:tags":[
        "book",
        "local"
    ],
    "wof:name":"Innerleithen Library Open Day",
    "wof:placetype":"venue"
},
  "geometry": {"coordinates":[-3.0599570274,55.6198921204],"type":"Point"}
}