{
  "type": "Feature",
  "properties": {
    "addr:full":"5 Kings North Road, Flixton Manchester Cheshire M41 8SL",
    "addr:housenumber":"5",
    "addr:postcode":"m41 8sl",
    "addr:street":"Kings North Road",
    "iso:country":"GB",
    "sg:address":"5 Kings North Road, Flixton",
    "sg:city":"Manchester",
    "sg:classifiers":[
        {
            "category":"Building & Trades",
            "subcategory":"Plumbing",
            "type":"Services"
        }
    ],
    "sg:postcode":"M41 8SL",
    "sg:province":"Cheshire",
    "sg:tags":[
        "central",
        "heating"
    ],
    "wof:name":"Heatech",
    "wof:placetype":"venue"
},
  "geometry": {"coordinates":[-2.392604,53.455799],"type":"Point"}
}