{
  "type": "Feature",
  "properties": {
    "addr:full":"7 Station Parade, Cherry Tree Rise Buckhurst Hill Essex IG9 6EU",
    "addr:housenumber":"7",
    "addr:postcode":"ig9 6eu",
    "addr:street":"Station Parade Cherry Tree Rise",
    "iso:country":"GB",
    "sg:address":"7 Station Parade, Cherry Tree Rise",
    "sg:city":"Buckhurst Hill",
    "sg:classifiers":[
        {
            "category":"Personal",
            "subcategory":"Barber",
            "type":"Services"
        }
    ],
    "sg:phone":"+44 20 8504 3416",
    "sg:postcode":"IG9 6EU",
    "sg:province":"Essex",
    "sg:tags":[
        "unisex",
        "men's",
        "hairdresser"
    ],
    "wof:name":"T J's Hair Club",
    "wof:placetype":"venue"
},
  "geometry": {"coordinates":[0.0456690006,51.6168937683],"type":"Point"}
}