{
  "type": "Feature",
  "properties": {
    "addr:full":"Alder Crescent Luton Bedfordshire LU3 1TG",
    "addr:postcode":"lu3 1tg",
    "addr:street":"Alder Crescent",
    "iso:country":"GB",
    "sg:address":"Alder Crescent",
    "sg:city":"Luton",
    "sg:classifiers":[
        {
            "category":"Communications",
            "type":"Services"
        }
    ],
    "sg:phone":"+44 1582 404167",
    "sg:postcode":"LU3 1TG",
    "sg:province":"Bedfordshire",
    "sg:tags":[
        "telecommunication"
    ],
    "wof:name":"G R M Ltd.",
    "wof:placetype":"venue"
},
  "geometry": {"coordinates":[-0.441832,51.899456],"type":"Point"}
}