{
  "type": "Feature",
  "properties": {
    "addr:full":"Tudor House, Tudor Industrial Estate Dukinfield Greater Manchester SK16 4RN",
    "addr:postcode":"sk16 4rn",
    "addr:street":"Tudor Industrial Estate",
    "iso:country":"GB",
    "sg:address":"Tudor House, Tudor Industrial Estate",
    "sg:city":"Dukinfield",
    "sg:classifiers":[
        {
            "category":"Professional",
            "type":"Services"
        },
        {
            "category":"Banks & Credit Unions",
            "subcategory":"Bank",
            "type":"Services"
        }
    ],
    "sg:phone":"+44 161 330 6521",
    "sg:postcode":"SK16 4RN",
    "sg:province":"Greater Manchester",
    "sg:tags":[
        "services",
        "belt",
        "conveyor"
    ],
    "wof:name":"Transelastic Ltd.",
    "wof:placetype":"venue"
},
  "geometry": {"coordinates":[-2.1028389931,53.4698066711],"type":"Point"}
}