{
  "type": "Feature",
  "properties": {
    "addr:full":"Doctors Surgery 59 Queen Ediths Way Cambridge Cambridgeshire CB1 8PJ",
    "addr:housenumber":"59",
    "addr:postcode":"cb1 8pj",
    "addr:street":"Queen Ediths Way",
    "iso:country":"GB",
    "sg:address":"Doctors Surgery 59 Queen Ediths Way",
    "sg:city":"Cambridge",
    "sg:classifiers":[
        {
            "category":"Health Services",
            "subcategory":"Doctor",
            "type":"Services"
        }
    ],
    "sg:postcode":"CB1 8PJ",
    "sg:province":"Cambridgeshire",
    "sg:tags":[
        "practitioners"
    ],
    "wof:name":"Pavis,H,",
    "wof:placetype":"venue"
},
  "geometry": {"coordinates":[0.1525699943,52.1796607971],"type":"Point"}
}