{
  "type": "Feature",
  "properties": {
    "addr:full":"Milestone House Indstl Est Penrith Cumbria CA11 9NQ",
    "addr:postcode":"ca11 9nq",
    "addr:street":"Indstl Est",
    "iso:country":"GB",
    "sg:address":"Milestone House Indstl Est",
    "sg:city":"Penrith",
    "sg:classifiers":[
        {
            "category":"Building & Trades",
            "subcategory":"Construction",
            "type":"Services"
        }
    ],
    "sg:phone":"+44 1768 864977",
    "sg:postcode":"CA11 9NQ",
    "sg:province":"Cumbria",
    "sg:tags":[
        "resurfacing",
        "laying",
        "floor"
    ],
    "wof:name":"Quattro Contracting Ltd",
    "wof:placetype":"venue"
},
  "geometry": {"coordinates":[-2.7574689388,54.6643028259],"type":"Point"}
}