{
  "type": "Feature",
  "properties": {
    "iso:country":"GB",
    "sg:address":"19 Pasture Lane, Padgate",
    "sg:city":"Warrington",
    "sg:classifiers":[
        {
            "category":"Building & Trades",
            "subcategory":"Construction",
            "type":"Services"
        }
    ],
    "sg:phone":"+44 1925 812619",
    "sg:postcode":"WA2 0PY",
    "sg:province":"Cheshire",
    "sg:tags":[
        "decorator",
        "painter"
    ],
    "wof:name":"A & G Maclean",
    "wof:placetype":"venue"
},
  "geometry": {"coordinates":[-2.5473968983,53.4087905884],"type":"Point"}
}