{
  "type": "Feature",
  "properties": {
    "addr:full":"8 Bill Todd Way, Taverham Norwich Norfolk NR8 6GF",
    "addr:housenumber":"8",
    "addr:postcode":"nr8 6gf",
    "addr:street":"Bill Todd Way;Norwich Norfolk",
    "iso:country":"GB",
    "sg:address":"8 Bill Todd Way, Taverham",
    "sg:city":"Norwich",
    "sg:classifiers":[
        {
            "category":"Real Estate",
            "subcategory":"Developer",
            "type":"Services"
        },
        {
            "category":"Building & Trades",
            "subcategory":"Construction",
            "type":"Services"
        }
    ],
    "sg:phone":"+44 1603 861275",
    "sg:postcode":"NR8 6GF",
    "sg:province":"Norfolk",
    "sg:tags":[
        "residential",
        "builder",
        "property"
    ],
    "wof:name":"BOVIS HOMES LTD",
    "wof:placetype":"venue"
},
  "geometry": {"coordinates":[1.2012829781,52.6887931824],"type":"Point"}
}