{
  "type": "Feature",
  "properties": {
    "addr:full":"4 West Avenue St Albans Hertfordshire AL2 3HF",
    "addr:housenumber":"4",
    "addr:postcode":"al2 3hf",
    "addr:street":"West Avenue",
    "iso:country":"GB",
    "sg:address":"4 West Avenue",
    "sg:city":"St Albans",
    "sg:classifiers":[
        {
            "category":"Building & Trades",
            "subcategory":"Construction",
            "type":"Services"
        }
    ],
    "sg:phone":"+44 1727 854978",
    "sg:postcode":"AL2 3HF",
    "sg:province":"Hertfordshire",
    "sg:tags":[
        "builder"
    ],
    "wof:name":"C Whitehouse Developments",
    "wof:placetype":"venue"
},
  "geometry": {"coordinates":[-0.356514,51.73156],"type":"Point"}
}