{
  "type": "Feature",
  "properties": {
    "addr:full":"Mulberry House, Sandy Lane Bristol City of Bristol BS8 3SQ",
    "addr:postcode":"bs8 3sq",
    "addr:street":"Sandy Lane",
    "iso:country":"GB",
    "sg:address":"Mulberry House, Sandy Lane",
    "sg:city":"Bristol",
    "sg:classifiers":[
        {
            "category":"Communications",
            "subcategory":"Film & Video Production",
            "type":"Services"
        },
        {
            "category":"Professional",
            "subcategory":"Art Services",
            "type":"Services"
        }
    ],
    "sg:postcode":"BS8 3SQ",
    "sg:province":"City of Bristol",
    "sg:tags":[
        "photographer",
        "illustrator",
        "artist"
    ],
    "wof:name":"2D Illustration Agency",
    "wof:placetype":"venue"
},
  "geometry": {"coordinates":[-2.6945409775,51.4589385986],"type":"Point"}
}