{
  "type": "Feature",
  "properties": {
    "addr:full":"46 Kingwell Road Barnet Hertfordshire EN4 0HY",
    "addr:housenumber":"46",
    "addr:postcode":"en4 0hy",
    "addr:street":"Kingwell Road",
    "iso:country":"GB",
    "sg:address":"46 Kingwell Road",
    "sg:city":"Barnet",
    "sg:classifiers":[
        {
            "category":"Professional",
            "subcategory":"Management & Consulting",
            "type":"Services"
        }
    ],
    "sg:phone":"+44 20 8440 5590",
    "sg:postcode":"EN4 0HY",
    "sg:province":"Hertfordshire",
    "sg:tags":[
        "consultant",
        "business"
    ],
    "wof:name":"Hadley Consultancy",
    "wof:placetype":"venue"
},
  "geometry": {"coordinates":[-0.1641680002,51.670085907],"type":"Point"}
}