{
  "type": "Feature",
  "properties": {
    "iso:country":"GB",
    "sg:address":"The Garage, Greenbridge Lane",
    "sg:city":"Liverpool",
    "sg:classifiers":[
        {
            "category":"Retail",
            "subcategory":"Auto Repair",
            "type":"Services"
        }
    ],
    "sg:postcode":"L26 6LE",
    "sg:province":"Merseyside",
    "sg:tags":[
        "modification",
        "garage"
    ],
    "wof:name":"W H Tuer",
    "wof:placetype":"venue"
},
  "geometry": {"coordinates":[-2.8222899437,53.3678016663],"type":"Point"}
}