{
  "type": "Feature",
  "properties": {
    "addr:full":"Charingthay House, Sylvan Road Exeter Devon EX4 6ET",
    "addr:postcode":"ex4 6et",
    "addr:street":"Sylvan Road",
    "iso:country":"GB",
    "sg:address":"Charingthay House, Sylvan Road",
    "sg:city":"Exeter",
    "sg:classifiers":[
        {
            "category":"Building & Trades",
            "subcategory":"Construction",
            "type":"Services"
        }
    ],
    "sg:postcode":"EX4 6ET",
    "sg:province":"Devon",
    "sg:tags":[
        "builder"
    ],
    "wof:name":"L J Last Ltd.",
    "wof:placetype":"venue"
},
  "geometry": {"coordinates":[-3.5201730728,50.7384300232],"type":"Point"}
}