{
  "type": "Feature",
  "properties": {
    "addr:full":"40 Stratford Road, Honeybourne Evesham Gloucestershire WR11 7PP",
    "addr:housenumber":"40",
    "addr:postcode":"wr11 7pp",
    "addr:street":"Stratford Road",
    "iso:country":"GB",
    "sg:address":"40 Stratford Road, Honeybourne",
    "sg:city":"Evesham",
    "sg:classifiers":[
        {
            "category":"Shopping",
            "subcategory":"Department Store",
            "type":"Retail Goods"
        }
    ],
    "sg:phone":"+44 1386 830315",
    "sg:postcode":"WR11 7PP",
    "sg:province":"Gloucestershire",
    "wof:name":"Spar",
    "wof:placetype":"venue"
},
  "geometry": {"coordinates":[-1.8270299435,52.0962944031],"type":"Point"}
}