{
  "type": "Feature",
  "properties": {
    "addr:full":"23 Notting Hill Gate London Greater London W11 3JQ",
    "addr:housenumber":"23",
    "addr:postcode":"w11 3jq",
    "addr:street":"Notting Hill Gate",
    "iso:country":"GB",
    "sg:address":"23 Notting Hill Gate",
    "sg:city":"London",
    "sg:classifiers":[
        {
            "category":"Personal",
            "subcategory":"Beauty Salon",
            "type":"Services"
        },
        {
            "category":"Personal",
            "subcategory":"Barber",
            "type":"Services"
        }
    ],
    "sg:phone":"+44 20 7727 5517",
    "sg:postcode":"W11 3JQ",
    "sg:province":"Greater London",
    "sg:tags":[
        "unisex",
        "hairdresser"
    ],
    "wof:name":"Homy'S Unisex Hair Salon",
    "wof:placetype":"venue"
},
  "geometry": {"coordinates":[-0.194666,51.509285],"type":"Point"}
}