{
  "type": "Feature",
  "properties": {
    "addr:full":"Red House Farm, Station Road, Onneley Crewe Cheshire CW3 9QQ",
    "addr:postcode":"cw3 9qq",
    "addr:street":"Station Road",
    "iso:country":"GB",
    "sg:address":"Red House Farm, Station Road, Onneley",
    "sg:city":"Crewe",
    "sg:classifiers":[
        {
            "category":"Farming",
            "subcategory":"Livestock Farm",
            "type":"Manufacturing & Wholesale Goods"
        }
    ],
    "sg:postcode":"CW3 9QQ",
    "sg:province":"Cheshire",
    "sg:tags":[
        "others"
    ],
    "wof:name":"P R & L K Salmon",
    "wof:placetype":"venue"
},
  "geometry": {"coordinates":[-2.373396,52.98394],"type":"Point"}
}