{
  "type": "Feature",
  "properties": {
    "iso:country":"GB",
    "sg:address":"12 Strand Av",
    "sg:city":"Wigan",
    "sg:classifiers":[
        {
            "category":"Building & Trades",
            "subcategory":"Construction",
            "type":"Services"
        }
    ],
    "sg:phone":"+44 1942 728459",
    "sg:postcode":"WN4 8LE",
    "sg:province":"Lancashire",
    "sg:tags":[
        "decorator",
        "painter"
    ],
    "wof:name":"W M Cook",
    "wof:placetype":"venue"
},
  "geometry": {"coordinates":[-2.638844,53.492451],"type":"Point"}
}