{
  "type": "Feature",
  "properties": {
    "addr:full":"532 Goldington Rd Bedford Bedfordshire MK41 0DX",
    "addr:housenumber":"532",
    "addr:postcode":"mk41 0dx",
    "addr:street":"Goldington Rd",
    "iso:country":"GB",
    "sg:address":"532 Goldington Rd",
    "sg:city":"Bedford",
    "sg:classifiers":[
        {
            "category":"Home & Garden",
            "subcategory":"Furniture",
            "type":"Retail Goods"
        }
    ],
    "sg:phone":"+44 1234 355581",
    "sg:postcode":"MK41 0DX",
    "sg:province":"Bedfordshire",
    "wof:name":"Hatters Furniture Group",
    "wof:placetype":"venue"
},
  "geometry": {"coordinates":[-0.419968009,52.1449928284],"type":"Point"}
}