{
  "type": "Feature",
  "properties": {
    "addr:full":"65 Garmen Road, Tottenham London Greater London N17 0UX",
    "addr:housenumber":"65",
    "addr:postcode":"n17 0ux",
    "addr:street":"Garmen Road",
    "iso:country":"GB",
    "sg:address":"65 Garmen Road, Tottenham",
    "sg:city":"London",
    "sg:classifiers":[
        {
            "category":"Retail",
            "subcategory":"Auto Repair",
            "type":"Services"
        }
    ],
    "sg:phone":"+44 20 8885 2277",
    "sg:postcode":"N17 0UX",
    "sg:province":"Greater London",
    "sg:tags":[
        "body",
        "car"
    ],
    "wof:name":"Spraytech",
    "wof:placetype":"venue"
},
  "geometry": {"coordinates":[-0.050806,51.604828],"type":"Point"}
}