{
  "type": "Feature",
  "properties": {
    "addr:full":"Queensmead Road, Loudwater High Wycombe Buckinghamshire HP10 9XA",
    "addr:postcode":"hp10 9xa",
    "addr:street":"Queensmead Road",
    "iso:country":"GB",
    "sg:address":"Queensmead Road, Loudwater",
    "sg:city":"High Wycombe",
    "sg:classifiers":[
        {
            "category":"Health Services",
            "subcategory":"Doctor",
            "type":"Services"
        }
    ],
    "sg:phone":"+44 1494 445150",
    "sg:postcode":"HP10 9XA",
    "sg:province":"Buckinghamshire",
    "sg:tags":[
        "practitioners"
    ],
    "wof:name":"Loudwater Surgery",
    "wof:placetype":"venue"
},
  "geometry": {"coordinates":[-0.6980680227,51.6085548401],"type":"Point"}
}