{
  "type": "Feature",
  "properties": {
    "addr:full":"C/o Parker Cavendish, 28 Church Road Stanmore Greater London HA7 4XR",
    "addr:housenumber":"/ o;28",
    "addr:postcode":"ha7 4xr",
    "addr:street":"C;Cavendish;Church Road",
    "iso:country":"GB",
    "sg:address":"C/o Parker Cavendish, 28 Church Road",
    "sg:city":"Stanmore",
    "sg:classifiers":[
        {
            "category":"Professional",
            "subcategory":"Engineering",
            "type":"Services"
        }
    ],
    "sg:postcode":"HA7 4XR",
    "sg:province":"Greater London",
    "sg:tags":[
        "contractor",
        "electrical",
        "engineer"
    ],
    "wof:name":"Protech Trading Ltd",
    "wof:placetype":"venue"
},
  "geometry": {"coordinates":[-0.3104090095,51.6175460815],"type":"Point"}
}