{
  "type": "Feature",
  "properties": {
    "addr:full":"North View Ruardean Gloucestershire GL17 9US",
    "addr:postcode":"gl17 9us",
    "addr:street":"North",
    "iso:country":"GB",
    "sg:address":"North View",
    "sg:city":"Ruardean",
    "sg:classifiers":[
        {
            "category":"Government",
            "subcategory":"Post Office",
            "type":"Public Place"
        }
    ],
    "sg:phone":"+44 1594 542449",
    "sg:postcode":"GL17 9US",
    "sg:province":"Gloucestershire",
    "wof:name":"Ruardean Sub Post Office",
    "wof:placetype":"venue"
},
  "geometry": {"coordinates":[-2.548074007,51.8567886353],"type":"Point"}
}