{
  "type": "Feature",
  "properties": {
    "addr:full":"43 Marshalls Way St Albans Hertfordshire AL4 8HZ",
    "addr:housenumber":"43",
    "addr:postcode":"al4 8hz",
    "addr:street":"Marshalls Way",
    "iso:country":"GB",
    "sg:address":"43 Marshalls Way",
    "sg:city":"St Albans",
    "sg:classifiers":[
        {
            "category":"Professional",
            "subcategory":"Art Services",
            "type":"Services"
        }
    ],
    "sg:phone":"+44 1582 765021",
    "sg:postcode":"AL4 8HZ",
    "sg:province":"Hertfordshire",
    "sg:tags":[
        "photographer"
    ],
    "wof:name":"Arif Gardner Photography",
    "wof:placetype":"venue"
},
  "geometry": {"coordinates":[-0.3177300096,51.8197212219],"type":"Point"}
}