{
  "type": "Feature",
  "properties": {
    "addr:full":"80 Park Road Wallsend Tyne and Wear NE28 6QY",
    "addr:housenumber":"80",
    "addr:postcode":"ne28 6qy",
    "addr:street":"Park Road",
    "iso:country":"GB",
    "sg:address":"80 Park Road",
    "sg:city":"Wallsend",
    "sg:classifiers":[
        {
            "category":"Shopping",
            "subcategory":"Used Merchandise",
            "type":"Retail Goods"
        }
    ],
    "sg:phone":"+44 191 263 3444",
    "sg:postcode":"NE28 6QY",
    "sg:province":"Tyne and Wear",
    "sg:tags":[
        "shop",
        "second-hand"
    ],
    "wof:name":"The Sale Shop",
    "wof:placetype":"venue"
},
  "geometry": {"coordinates":[-1.5307220221,54.9912948608],"type":"Point"}
}