{
  "type": "Feature",
  "properties": {
    "addr:full":"3 Tile Cross Trading Estate, Tile Cross Road Birmingham West Midlands B33 0NW",
    "addr:housenumber":"3",
    "addr:postcode":"b33 0nw",
    "addr:street":"Tile Cross Trading Estate Tile Cross Road",
    "iso:country":"GB",
    "sg:address":"3 Tile Cross Trading Estate, Tile Cross Road",
    "sg:city":"Birmingham",
    "sg:classifiers":[
        {
            "category":"Wholesale",
            "subcategory":"Machinery & Supplies",
            "type":"Manufacturing & Wholesale Goods"
        },
        {
            "category":"Home & Garden",
            "subcategory":"Hardware",
            "type":"Retail Goods"
        }
    ],
    "sg:phone":"+44 121 779 6856",
    "sg:postcode":"B33 0NW",
    "sg:province":"West Midlands",
    "sg:tags":[
        "fixing",
        "-",
        "sale",
        "hydraulic",
        "accessory",
        "equipment",
        "bolt",
        "nuts"
    ],
    "wof:name":"Hydrajaws Ltd",
    "wof:placetype":"venue"
},
  "geometry": {"coordinates":[-1.764914,52.473034],"type":"Point"}
}