{
  "type": "Feature",
  "properties": {
    "addr:full":"12 Brackley Road Buckingham Buckinghamshire MK18 1JD",
    "addr:housenumber":"12",
    "addr:postcode":"mk18 1jd",
    "addr:street":"Brackley Road",
    "iso:country":"GB",
    "sg:address":"12 Brackley Road",
    "sg:city":"Buckingham",
    "sg:classifiers":[
        {
            "category":"Health Services",
            "subcategory":"Chiropractor",
            "type":"Services"
        }
    ],
    "sg:phone":"+44 1280 816623",
    "sg:postcode":"MK18 1JD",
    "sg:province":"Buckinghamshire",
    "wof:name":"Buckingham Chiropractic Clinic",
    "wof:placetype":"venue"
},
  "geometry": {"coordinates":[-1.0042330027,52.0032958984],"type":"Point"}
}