{
  "type": "Feature",
  "properties": {
    "addr:full":"34 Barford Dr Chester Le Street Durham DH2 3HR",
    "addr:housenumber":"34",
    "addr:postcode":"dh2 3hr",
    "addr:street":"Barford Dr;Le Street",
    "iso:country":"GB",
    "sg:address":"34 Barford Dr",
    "sg:city":"Chester Le Street",
    "sg:classifiers":[
        {
            "category":"Building & Trades",
            "subcategory":"Construction",
            "type":"Services"
        }
    ],
    "sg:phone":"+44 191 388 7313",
    "sg:postcode":"DH2 3HR",
    "sg:province":"Durham",
    "sg:tags":[
        "contractor",
        "paving",
        "driveway"
    ],
    "wof:name":"Creative Paving",
    "wof:placetype":"venue"
},
  "geometry": {"coordinates":[-1.591375,54.845715],"type":"Point"}
}