{
  "type": "Feature",
  "properties": {
    "iso:country":"GB",
    "sg:address":"13 Crammavill Street",
    "sg:city":"Grays",
    "sg:classifiers":[
        {
            "category":"Shopping",
            "subcategory":"Pets & Pet Supplies",
            "type":"Retail Goods"
        }
    ],
    "sg:phone":"+44 1375 385509",
    "sg:postcode":"RM16 2AP",
    "sg:province":"Essex",
    "wof:name":"Crammavill Pets",
    "wof:placetype":"venue"
},
  "geometry": {"coordinates":[0.3297399879,51.4977645874],"type":"Point"}
}