{
  "type": "Feature",
  "properties": {
    "addr:full":"Wessex House, 40 Station Road Westbury Wiltshire BA13 3JN",
    "addr:housenumber":"40",
    "addr:postcode":"ba13 3jn",
    "addr:street":"Station Road",
    "iso:country":"GB",
    "sg:address":"Wessex House, 40 Station Road",
    "sg:city":"Westbury",
    "sg:classifiers":[
        {
            "category":"Professional",
            "subcategory":"Computer Services",
            "type":"Services"
        }
    ],
    "sg:phone":"+44 1732 765440",
    "sg:postcode":"BA13 3JN",
    "sg:province":"Wiltshire",
    "sg:tags":[
        "development",
        "system",
        "software"
    ],
    "wof:name":"Software Developments (Digital Direct) Ltd.",
    "wof:placetype":"venue"
},
  "geometry": {"coordinates":[-2.1893229485,51.2625427246],"type":"Point"}
}