{
  "type": "Feature",
  "properties": {
    "addr:full":"Ninewells Hospital Dundee Dundee City DD1 9SY",
    "addr:postcode":"dd1 9sy",
    "iso:country":"GB",
    "sg:address":"Ninewells Hospital",
    "sg:city":"Dundee",
    "sg:classifiers":[
        {
            "category":"Shopping",
            "subcategory":"Books",
            "type":"Retail Goods"
        },
        {
            "category":"Shopping",
            "subcategory":"News",
            "type":"Retail Goods"
        }
    ],
    "sg:phone":"+44 1382 566551",
    "sg:postcode":"DD1 9SY",
    "sg:province":"Dundee City",
    "sg:tags":[
        "bookseller",
        "newsagent"
    ],
    "wof:name":"Blackwell University Bookshop",
    "wof:placetype":"venue"
},
  "geometry": {"coordinates":[-2.967609,56.461376],"type":"Point"}
}