{
  "type": "Feature",
  "properties": {
    "iso:country":"GB",
    "sg:address":"22 Stanborough Rd",
    "sg:city":"Welwyn Garden City",
    "sg:classifiers":[
        {
            "category":"Professional",
            "subcategory":"Management & Consulting",
            "type":"Services"
        }
    ],
    "sg:phone":"+44 1707 395044",
    "sg:postcode":"AL8 6XD",
    "sg:province":"Hertfordshire",
    "sg:tags":[
        "marketing",
        "consultant"
    ],
    "wof:name":"Dotcom",
    "wof:placetype":"venue"
},
  "geometry": {"coordinates":[-0.2131800056,51.7924194336],"type":"Point"}
}