{
  "type": "Feature",
  "properties": {
    "addr:full":"Lechmere, Copthall Avenue, Hawkhurst Cranbrook East Sussex TN18 4LR",
    "addr:postcode":"tn18 4lr",
    "addr:street":"Copthall Avenue",
    "iso:country":"GB",
    "sg:address":"Lechmere, Copthall Avenue, Hawkhurst",
    "sg:city":"Cranbrook",
    "sg:classifiers":[
        {
            "category":"Professional",
            "subcategory":"Engineering",
            "type":"Services"
        }
    ],
    "sg:postcode":"TN18 4LR",
    "sg:province":"East Sussex",
    "sg:tags":[
        "contractor",
        "electrical",
        "engineer"
    ],
    "wof:name":"Wizcom Ltd",
    "wof:placetype":"venue"
},
  "geometry": {"coordinates":[0.510175,51.047626],"type":"Point"}
}