{
  "type": "Feature",
  "properties": {
    "addr:full":"37 Thomas Street Holyhead Isle of Anglesey LL65 1RR",
    "addr:housenumber":"37",
    "addr:postcode":"ll65 1rr",
    "addr:street":"Thomas Street",
    "iso:country":"GB",
    "sg:address":"37 Thomas Street",
    "sg:city":"Holyhead",
    "sg:classifiers":[
        {
            "category":"Military Area",
            "subcategory":"Air Force Base",
            "type":"Public Place"
        }
    ],
    "sg:phone":"+44 1407 764046",
    "sg:postcode":"LL65 1RR",
    "sg:province":"Isle of Anglesey",
    "sg:tags":[
        "taxi",
        "hire",
        "private"
    ],
    "wof:name":"Star Taxi",
    "wof:placetype":"venue"
},
  "geometry": {"coordinates":[-4.6354207993,53.3104171753],"type":"Point"}
}