{
  "type": "Feature",
  "properties": {
    "iso:country":"GB",
    "sg:address":"19 Turners Hill, Cheshunt",
    "sg:city":"Waltham Cross",
    "sg:classifiers":[
        {
            "category":"Manufacturing",
            "subcategory":"Tools & Machinery",
            "type":"Manufacturing & Wholesale Goods"
        }
    ],
    "sg:phone":"+44 1992 629364",
    "sg:postcode":"EN8 8NJ",
    "sg:province":"Essex",
    "sg:tags":[
        "society",
        "friendly"
    ],
    "wof:name":"Crossbrook Insurance",
    "wof:placetype":"venue"
},
  "geometry": {"coordinates":[-0.034483,51.699947],"type":"Point"}
}