{
  "type": "Feature",
  "properties": {
    "addr:full":"Unit 1, Grove Rd, Northfleet Gravesend Kent DA11 9AX",
    "addr:housenumber":"unit 1",
    "addr:postcode":"da11 9ax",
    "addr:street":"Grove Rd",
    "iso:country":"GB",
    "sg:address":"Unit 1, Grove Rd, Northfleet",
    "sg:city":"Gravesend",
    "sg:classifiers":[
        {
            "category":"Wholesale",
            "subcategory":"Construction Materials",
            "type":"Manufacturing & Wholesale Goods"
        }
    ],
    "sg:phone":"+44 1474 326666",
    "sg:postcode":"DA11 9AX",
    "sg:province":"Kent",
    "sg:tags":[
        "lift"
    ],
    "wof:name":"Cls Lifting Services",
    "wof:placetype":"venue"
},
  "geometry": {"coordinates":[0.324836,51.449921],"type":"Point"}
}