{
  "type": "Feature",
  "properties": {
    "addr:full":"19a The Carfax Horsham West Sussex RH12 1EB",
    "addr:housenumber":"19a",
    "addr:postcode":"rh12 1eb",
    "addr:street":"The Carfax",
    "iso:country":"GB",
    "sg:address":"19a The Carfax",
    "sg:city":"Horsham",
    "sg:classifiers":[
        {
            "category":"Personal",
            "subcategory":"Beauty Salon",
            "type":"Services"
        }
    ],
    "sg:phone":"+44 1403 241341",
    "sg:postcode":"RH12 1EB",
    "sg:province":"West Sussex",
    "sg:tags":[
        "unisex",
        "hairdresser"
    ],
    "wof:name":"The Hair & Beauty Studio",
    "wof:placetype":"venue"
},
  "geometry": {"coordinates":[-0.32772699,51.0631790161],"type":"Point"}
}