{
  "type": "Feature",
  "properties": {
    "iso:country":"GB",
    "sg:address":"59 Southdown Road",
    "sg:city":"Harpenden",
    "sg:classifiers":[
        {
            "category":"Bars & Pubs",
            "type":"Food & Drink"
        }
    ],
    "sg:phone":"+44 1582 766745",
    "sg:postcode":"AL5 1PQ",
    "sg:province":"Hertfordshire",
    "sg:tags":[
        "pubs",
        "inn"
    ],
    "wof:name":"The Skew Bridge",
    "wof:placetype":"venue"
},
  "geometry": {"coordinates":[-0.348246,51.808666],"type":"Point"}
}