{
  "type": "Feature",
  "properties": {
    "iso:country":"GB",
    "sg:address":"45 Murray Road",
    "sg:city":"Workington",
    "sg:classifiers":[
        {
            "category":"Shopping",
            "subcategory":"Stationery & Office Supplies",
            "type":"Retail Goods"
        }
    ],
    "sg:phone":"+44 1900 871427",
    "sg:postcode":"CA14 2AB",
    "sg:province":"Cumbria",
    "wof:name":"Stationery Box Ltd.",
    "wof:placetype":"venue"
},
  "geometry": {"coordinates":[-3.54613,54.644192],"type":"Point"}
}