{
  "type": "Feature",
  "properties": {
    "iso:country":"GB",
    "sg:address":"272 Alcester Road South",
    "sg:city":"Birmingham",
    "sg:classifiers":[
        {
            "category":"Shopping",
            "subcategory":"Pharmacy",
            "type":"Retail Goods"
        }
    ],
    "sg:phone":"+44 121 444 6234",
    "sg:postcode":"B14 6EN",
    "sg:province":"West Midlands",
    "sg:tags":[
        "pharmacist",
        "chemist"
    ],
    "wof:name":"Asker's Chemists",
    "wof:placetype":"venue"
},
  "geometry": {"coordinates":[-1.892109,52.421711],"type":"Point"}
}