{
  "type": "Feature",
  "properties": {
    "addr:full":"P O Box 76 Chipping Norton Gloucestershire OX7 6FS",
    "addr:housenumber":"box 76",
    "addr:postcode":"ox7 6fs",
    "addr:street":"P O",
    "iso:country":"GB",
    "sg:address":"P O Box 76",
    "sg:city":"Chipping Norton",
    "sg:classifiers":[
        {
            "category":"Shopping",
            "subcategory":"Clothing, Apparel, & Fashions",
            "type":"Retail Goods"
        }
    ],
    "sg:phone":"+44 1993 832085",
    "sg:postcode":"OX7 6FS",
    "sg:province":"Gloucestershire",
    "sg:tags":[
        "wear",
        "leisure"
    ],
    "wof:name":"Kooltog",
    "wof:placetype":"venue"
},
  "geometry": {"coordinates":[-1.545912981,51.9404067993],"type":"Point"}
}