{
  "type": "Feature",
  "properties": {
    "iso:country":"GB",
    "sg:address":"18 Crown Hill, Church St",
    "sg:city":"Croydon",
    "sg:classifiers":[
        {
            "category":"Bars & Pubs",
            "subcategory":"Nightclub",
            "type":"Food & Drink"
        }
    ],
    "sg:phone":"+44 20 8688 9990",
    "sg:postcode":"CR0 1RZ",
    "sg:province":"Surrey",
    "sg:tags":[
        "club",
        "night"
    ],
    "wof:name":"Colosseum Bar & Nightclub",
    "wof:placetype":"venue"
},
  "geometry": {"coordinates":[-0.100717,51.373653],"type":"Point"}
}