{
  "type": "Feature",
  "properties": {
    "iso:country":"GB",
    "sg:address":"43 Breton Side",
    "sg:city":"Plymouth",
    "sg:classifiers":[
        {
            "category":"Shopping",
            "subcategory":"Clothing, Apparel, & Fashions",
            "type":"Retail Goods"
        }
    ],
    "sg:phone":"+44 1752 216510",
    "sg:postcode":"PL4 0BB",
    "sg:province":"Devon",
    "sg:tags":[
        "dresswear"
    ],
    "wof:name":"The Frock Exchange",
    "wof:placetype":"venue"
},
  "geometry": {"coordinates":[-4.134448,50.370842],"type":"Point"}
}