{
  "type": "Feature",
  "properties": {
    "addr:full":"Duncrieve Rd, Glenfarg Perth Perth and Kinross PH2 9PA",
    "addr:postcode":"ph2 9pa",
    "addr:street":"Duncrieve Rd",
    "iso:country":"GB",
    "sg:address":"Duncrieve Rd, Glenfarg",
    "sg:city":"Perth",
    "sg:classifiers":[
        {
            "category":"Retail",
            "subcategory":"Repair Shop",
            "type":"Services"
        },
        {
            "category":"Building & Trades",
            "subcategory":"Construction",
            "type":"Services"
        }
    ],
    "sg:postcode":"PH2 9PA",
    "sg:province":"Perth and Kinross",
    "sg:tags":[
        "builder",
        "upholsterer"
    ],
    "wof:name":"Milne,Scott A,",
    "wof:placetype":"venue"
},
  "geometry": {"coordinates":[-3.398643,56.278355],"type":"Point"}
}