{
  "type": "Feature",
  "properties": {
    "addr:full":"51 New Heston Road Hounslow Greater London TW5 0LW",
    "addr:housenumber":"51",
    "addr:postcode":"tw5 0lw",
    "addr:street":"New Heston Road",
    "iso:country":"GB",
    "sg:address":"51 New Heston Road",
    "sg:city":"Hounslow",
    "sg:classifiers":[
        {
            "category":"Social Services",
            "type":"Services"
        },
        {
            "category":"Social Services",
            "subcategory":"Child Care",
            "type":"Services"
        }
    ],
    "sg:phone":"+44 20 8570 6585",
    "sg:postcode":"TW5 0LW",
    "sg:province":"Greater London",
    "sg:tags":[
        "day",
        "centre"
    ],
    "wof:name":"Heston Work Centre",
    "wof:placetype":"venue"
},
  "geometry": {"coordinates":[-0.374689,51.48547],"type":"Point"}
}