{
  "type": "Feature",
  "properties": {
    "addr:full":"Suite 110 Park House Watford Hertfordshire WD18 8PH",
    "addr:housenumber":"suite 110",
    "addr:postcode":"wd18 8ph",
    "addr:street":"Park House",
    "iso:country":"GB",
    "sg:address":"Suite 110 Park House",
    "sg:city":"Watford",
    "sg:classifiers":[
        {
            "category":"Building & Trades",
            "subcategory":"Plumbing",
            "type":"Services"
        }
    ],
    "sg:phone":"+44 1442 217941",
    "sg:postcode":"WD18 8PH",
    "sg:province":"Hertfordshire",
    "sg:tags":[
        "central",
        "heating"
    ],
    "wof:name":"Bayliss K J Plumbing & Heating & Gas Installation",
    "wof:placetype":"venue"
},
  "geometry": {"coordinates":[-0.430398,51.645023],"type":"Point"}
}