{
  "type": "Feature",
  "properties": {
    "addr:full":"6 Kersland Street Glasgow Glasgow City G12 8BL",
    "addr:housenumber":"6",
    "addr:postcode":"g12 8bl",
    "addr:street":"Kersland Street",
    "iso:country":"GB",
    "sg:address":"6 Kersland Street",
    "sg:city":"Glasgow",
    "sg:classifiers":[
        {
            "category":"Fast Food",
            "type":"Food & Drink"
        }
    ],
    "sg:phone":"+44 141 400 1960",
    "sg:postcode":"G12 8BL",
    "sg:province":"Glasgow City",
    "sg:tags":[
        "away",
        "take"
    ],
    "wof:name":"Over The Rainbow",
    "wof:placetype":"venue"
},
  "geometry": {"coordinates":[-4.2887940407,55.8771743774],"type":"Point"}
}