{
  "type": "Feature",
  "properties": {
    "iso:country":"GB",
    "sg:address":"Meadowfield Avenue",
    "sg:city":"Middlesbrough",
    "sg:classifiers":[
        {
            "category":"Fast Food",
            "type":"Food & Drink"
        }
    ],
    "sg:postcode":"TS4 2UW",
    "sg:province":"North Yorkshire",
    "sg:tags":[
        "away",
        "take"
    ],
    "wof:name":"Meadowfield Road Fishshop",
    "wof:placetype":"venue"
},
  "geometry": {"coordinates":[-1.23252,54.555965],"type":"Point"}
}