{
  "type": "Feature",
  "properties": {
    "iso:country":"GB",
    "sg:address":"Rear",
    "sg:city":"Blackpool",
    "sg:classifiers":[
        {
            "category":"Home & Garden",
            "subcategory":"Home Furnishings",
            "type":"Retail Goods"
        }
    ],
    "sg:postcode":"FY1 6EB",
    "sg:province":"Lancashire",
    "sg:tags":[
        "awning",
        "canopy",
        "blinds"
    ],
    "wof:name":"Orion Blinds",
    "wof:placetype":"venue"
},
  "geometry": {"coordinates":[-3.0507180691,53.8091011047],"type":"Point"}
}