{
  "type": "Feature",
  "properties": {
    "iso:country":"GB",
    "sg:address":"Calder House, Jockey Field",
    "sg:city":"Haverfordwest",
    "sg:classifiers":[
        {
            "category":"Shopping",
            "subcategory":"Computers & Home Electronics",
            "type":"Retail Goods"
        }
    ],
    "sg:phone":"+44 1437 766630",
    "sg:postcode":"SA61 2PN",
    "sg:province":"Pembrokeshire",
    "sg:tags":[
        "consumables"
    ],
    "wof:name":"Calder Computer Supplies",
    "wof:placetype":"venue"
},
  "geometry": {"coordinates":[-4.965922,51.807388],"type":"Point"}
}