{
  "type": "Feature",
  "properties": {
    "addr:full":"76a Albert Rd Colne Lancashire BB8 0AG",
    "addr:housenumber":"76a",
    "addr:postcode":"bb8 0ag",
    "addr:street":"Albert Rd",
    "iso:country":"GB",
    "sg:address":"76a Albert Rd",
    "sg:city":"Colne",
    "sg:classifiers":[
        {
            "category":"Shopping",
            "subcategory":"Stationery & Office Supplies",
            "type":"Retail Goods"
        }
    ],
    "sg:phone":"+44 1282 864625",
    "sg:postcode":"BB8 0AG",
    "sg:province":"Lancashire",
    "sg:tags":[
        "item",
        "promotional"
    ],
    "wof:name":"Text Styles Ltd",
    "wof:placetype":"venue"
},
  "geometry": {"coordinates":[-2.1782119274,53.8554496765],"type":"Point"}
}