{
  "type": "Feature",
  "properties": {
    "iso:country":"GB",
    "sg:address":"3 Lindley Road",
    "sg:city":"London",
    "sg:classifiers":[
        {
            "category":"Professional",
            "subcategory":"Computer Services",
            "type":"Services"
        }
    ],
    "sg:postcode":"E10 6QT",
    "sg:province":"Greater London",
    "sg:tags":[
        "system",
        "software"
    ],
    "wof:name":"Interlagos Technology Ltd",
    "wof:placetype":"venue"
},
  "geometry": {"coordinates":[-0.009205,51.563419],"type":"Point"}
}