{
  "type": "Feature",
  "properties": {
    "iso:country":"GB",
    "sg:address":"158 Overbrook",
    "sg:city":"Swindon",
    "sg:classifiers":[
        {
            "category":"Professional",
            "subcategory":"Accounting & Tax Preparation",
            "type":"Services"
        }
    ],
    "sg:postcode":"SN3 6AY",
    "sg:province":"Wiltshire",
    "sg:tags":[
        "accountant"
    ],
    "wof:name":"Martin Buck Business Services",
    "wof:placetype":"venue"
},
  "geometry": {"coordinates":[-1.741945982,51.5509796143],"type":"Point"}
}