{
  "type": "Feature",
  "properties": {
    "addr:full":"6 Clarendon Road Canvey Island Essex SS8 8DR",
    "addr:housenumber":"6",
    "addr:postcode":"ss8 8dr",
    "addr:street":"Clarendon Road",
    "iso:country":"GB",
    "sg:address":"6 Clarendon Road",
    "sg:city":"Canvey Island",
    "sg:classifiers":[
        {
            "category":"Utilities",
            "subcategory":"Refuse",
            "type":"Services"
        }
    ],
    "sg:phone":"+44 1268 511435",
    "sg:postcode":"SS8 8DR",
    "sg:province":"Essex",
    "sg:tags":[
        "disposal",
        "waste"
    ],
    "wof:name":"Canvey Skip Hire",
    "wof:placetype":"venue"
},
  "geometry": {"coordinates":[0.598713,51.525208],"type":"Point"}
}