{
  "type": "Feature",
  "properties": {
    "addr:full":"2 Blackthorn Lane, Burn Bridge Harrogate North Yorkshire HG3 1NZ",
    "addr:housenumber":"2",
    "addr:postcode":"hg3 1nz",
    "addr:street":"Blackthorn Lane Burn Bridge",
    "iso:country":"GB",
    "sg:address":"2 Blackthorn Lane, Burn Bridge",
    "sg:city":"Harrogate",
    "sg:classifiers":[
        {
            "category":"Professional",
            "subcategory":"Management & Consulting",
            "type":"Services"
        }
    ],
    "sg:phone":"+44 1423 873112",
    "sg:postcode":"HG3 1NZ",
    "sg:province":"North Yorkshire",
    "sg:tags":[
        "project"
    ],
    "wof:name":"C.M.A Project Services",
    "wof:placetype":"venue"
},
  "geometry": {"coordinates":[-1.548265,53.961674],"type":"Point"}
}