{
  "type": "Feature",
  "properties": {
    "iso:country":"GB",
    "sg:address":"35 St Martins Court",
    "sg:city":"London",
    "sg:classifiers":[
        {
            "category":"Shopping",
            "subcategory":"Comic Books",
            "type":"Retail Goods"
        }
    ],
    "sg:phone":"+44 20 7240 0795",
    "sg:postcode":"WC2N 4AL",
    "sg:province":"Greater London",
    "sg:tags":[
        "jeweller"
    ],
    "wof:name":"Pearl Cross Ltd.",
    "wof:placetype":"venue"
},
  "geometry": {"coordinates":[-0.12786,51.511021],"type":"Point"}
}