{
  "type": "Feature",
  "properties": {
    "addr:full":"Unit A227 Riverside, Business Centre, Haldane Place Wandsworth Greater London SW18 4UQ",
    "addr:postcode":"sw18 4uq",
    "addr:street":"Haldane Place",
    "iso:country":"GB",
    "sg:address":"Unit A227 Riverside, Business Centre, Haldane Place",
    "sg:city":"Wandsworth",
    "sg:classifiers":[
        {
            "category":"Manufacturing",
            "subcategory":"Textiles",
            "type":"Manufacturing & Wholesale Goods"
        }
    ],
    "sg:phone":"+44 20 8870 4161",
    "sg:postcode":"SW18 4UQ",
    "sg:province":"Greater London",
    "sg:tags":[
        "made-up"
    ],
    "wof:name":"Sarah Millet Design",
    "wof:placetype":"venue"
},
  "geometry": {"coordinates":[-0.1944790035,51.4568710327],"type":"Point"}
}