{
  "type": "Feature",
  "properties": {
    "iso:country":"GB",
    "sg:address":"Unit 12, Newhall Street",
    "sg:city":"Willenhall",
    "sg:classifiers":[
        {
            "category":"Cafe",
            "type":"Food & Drink"
        }
    ],
    "sg:phone":"+44 1902 607236",
    "sg:postcode":"WV13 1LQ",
    "sg:province":"West Midlands",
    "sg:tags":[
        "tea",
        "room"
    ],
    "wof:name":"Corner Cafe",
    "wof:placetype":"venue"
},
  "geometry": {"coordinates":[-2.052249,52.587421],"type":"Point"}
}