{
  "type": "Feature",
  "properties": {
    "addr:full":"18 St Georges Square Stamford Cambridgeshire PE9 2BN",
    "addr:housenumber":"18",
    "addr:postcode":"pe9 2bn",
    "addr:street":"St Georges Square",
    "iso:country":"GB",
    "sg:address":"18 St Georges Square",
    "sg:city":"Stamford",
    "sg:classifiers":[
        {
            "category":"Professional",
            "subcategory":"Management & Consulting",
            "type":"Services"
        }
    ],
    "sg:phone":"+44 1780 766787",
    "sg:postcode":"PE9 2BN",
    "sg:province":"Cambridgeshire",
    "sg:tags":[
        "consultant",
        "promotion",
        "direct",
        "sale"
    ],
    "wof:name":"Liquid Products Ltd.",
    "wof:placetype":"venue"
},
  "geometry": {"coordinates":[-0.4761570096,52.6515960693],"type":"Point"}
}