{
  "type": "Feature",
  "properties": {
    "addr:full":"252 High Street Orpington Kent BR6 0LZ",
    "addr:housenumber":"252",
    "addr:postcode":"br6 0lz",
    "addr:street":"High Street",
    "iso:country":"GB",
    "sg:address":"252 High Street",
    "sg:city":"Orpington",
    "sg:classifiers":[
        {
            "category":"Travel",
            "subcategory":"Travel Agent",
            "type":"Entertainment"
        }
    ],
    "sg:phone":"+44 1689 832532",
    "sg:postcode":"BR6 0LZ",
    "sg:province":"Kent",
    "wof:name":"Transit Management Ltd.",
    "wof:placetype":"venue"
},
  "geometry": {"coordinates":[0.099214,51.375912],"type":"Point"}
}