{
  "type": "Feature",
  "properties": {
    "iso:country":"GB",
    "sg:address":"Ridge End Farm, Pinfold Lane, Fixby",
    "sg:city":"Huddersfield",
    "sg:classifiers":[
        {
            "category":"Farming",
            "subcategory":"Dairy Farm",
            "type":"Manufacturing & Wholesale Goods"
        }
    ],
    "sg:phone":"+44 1422 372958",
    "sg:postcode":"HD2 2EN",
    "sg:province":"West Yorkshire",
    "sg:tags":[
        "farmer"
    ],
    "wof:name":"B & R A BOTTOMLEY",
    "wof:placetype":"venue"
},
  "geometry": {"coordinates":[-1.7881439924,53.678768158],"type":"Point"}
}