{
  "type": "Feature",
  "properties": {
    "iso:country":"GB",
    "sg:address":"Stotfield Road",
    "sg:city":"Lossiemouth",
    "sg:classifiers":[
        {
            "category":"Social Services",
            "subcategory":"Retirement Home",
            "type":"Services"
        }
    ],
    "sg:phone":"+44 1343 814067",
    "sg:postcode":"IV31 6QR",
    "sg:province":"Moray",
    "sg:tags":[
        "residential",
        "care"
    ],
    "wof:name":"Whinneybank Residential Home",
    "wof:placetype":"venue"
},
  "geometry": {"coordinates":[-3.3011190891,57.7181282043],"type":"Point"}
}