{
  "type": "Feature",
  "properties": {
    "addr:full":"122 Horbury Road Wakefield West Yorkshire WF2 8BQ",
    "addr:housenumber":"122",
    "addr:postcode":"wf2 8bq",
    "addr:street":"Horbury Road",
    "iso:country":"GB",
    "sg:address":"122 Horbury Road",
    "sg:city":"Wakefield",
    "sg:classifiers":[
        {
            "category":"Fast Food",
            "type":"Food & Drink"
        },
        {
            "category":"Recreation",
            "subcategory":"Fishing",
            "type":"Entertainment"
        }
    ],
    "sg:phone":"+44 1924 369410",
    "sg:postcode":"WF2 8BQ",
    "sg:province":"West Yorkshire",
    "sg:tags":[
        "shop",
        "fish",
        "angling",
        "chip"
    ],
    "wof:name":"Cross Lane Fisheries",
    "wof:placetype":"venue"
},
  "geometry": {"coordinates":[-1.517764,53.675976],"type":"Point"}
}