{
  "type": "Feature",
  "properties": {
    "addr:full":"162 Long Road Canvey Island Essex SS8 0JP",
    "addr:housenumber":"162",
    "addr:postcode":"ss8 0jp",
    "addr:street":"Long Road",
    "iso:country":"GB",
    "sg:address":"162 Long Road",
    "sg:city":"Canvey Island",
    "sg:classifiers":[
        {
            "category":"Food & Beverages",
            "subcategory":"Meat & Fish",
            "type":"Retail Goods"
        }
    ],
    "sg:phone":"+44 1268 684315",
    "sg:postcode":"SS8 0JP",
    "sg:province":"Essex",
    "sg:tags":[
        "chip"
    ],
    "wof:name":"Louis Fish Bar",
    "wof:placetype":"venue"
},
  "geometry": {"coordinates":[0.5820440054,51.5202865601],"type":"Point"}
}