{
  "type": "Feature",
  "properties": {
    "addr:full":"Unit B3 The Courtyard, Lonesome Lane Reigate Surrey RH2 7QT",
    "addr:postcode":"rh2 7qt",
    "addr:street":"The Courtyard Lonesome Lane",
    "iso:country":"GB",
    "sg:address":"Unit B3 The Courtyard, Lonesome Lane",
    "sg:city":"Reigate",
    "sg:classifiers":[
        {
            "category":"Manufacturing",
            "subcategory":"Signs",
            "type":"Manufacturing & Wholesale Goods"
        }
    ],
    "sg:phone":"+44 1737 246969",
    "sg:postcode":"RH2 7QT",
    "sg:province":"Surrey",
    "sg:tags":[
        "nameplate"
    ],
    "wof:name":"Signs & Safety Ltd.",
    "wof:placetype":"venue"
},
  "geometry": {"coordinates":[-0.2047789991,51.2357444763],"type":"Point"}
}