{
  "type": "Feature",
  "properties": {
    "addr:full":"61 Rigbourne Hill Beccles Norfolk NR34 9JQ",
    "addr:housenumber":"61",
    "addr:postcode":"nr34 9jq",
    "addr:street":"Rigbourne Hill",
    "iso:country":"GB",
    "sg:address":"61 Rigbourne Hill",
    "sg:city":"Beccles",
    "sg:classifiers":[
        {
            "category":"Place Of Worship",
            "type":"Public Place"
        },
        {
            "category":"Organizations",
            "subcategory":"Non-profit Organization",
            "type":"Services"
        }
    ],
    "sg:phone":"+44 1502 716370",
    "sg:postcode":"NR34 9JQ",
    "sg:province":"Norfolk",
    "sg:tags":[
        "charitable",
        "organisation",
        "charity"
    ],
    "wof:name":"ST LUKES CHURCH CENTRE",
    "wof:placetype":"venue"
},
  "geometry": {"coordinates":[1.574518,52.449062],"type":"Point"}
}