{
  "type": "Feature",
  "properties": {
    "iso:country":"GB",
    "sg:address":"Lower Meyrick Street",
    "sg:city":"Pembroke Dock",
    "sg:classifiers":[
        {
            "category":"Food & Beverages",
            "subcategory":"Fruits & Vegetables",
            "type":"Retail Goods"
        }
    ],
    "sg:phone":"+44 1646 621259",
    "sg:postcode":"SA72 6WF",
    "sg:province":"Pembrokeshire",
    "sg:tags":[
        "greengrocer"
    ],
    "wof:name":"K M  Stratford",
    "wof:placetype":"venue"
},
  "geometry": {"coordinates":[-4.942424,51.691856],"type":"Point"}
}