{
  "type": "Feature",
  "properties": {
    "addr:full":"Unit 10, Windsor Park, Windsor Avenue Wimbledon Greater London SW19 2RR",
    "addr:housenumber":"unit 10",
    "addr:postcode":"sw19 2rr",
    "addr:street":"Park Windsor Avenue",
    "iso:country":"GB",
    "sg:address":"Unit 10, Windsor Park, Windsor Avenue",
    "sg:city":"Wimbledon",
    "sg:classifiers":[
        {
            "category":"Manufacturing",
            "subcategory":"Wood Products",
            "type":"Manufacturing & Wholesale Goods"
        }
    ],
    "sg:phone":"+44 20 8544 9999",
    "sg:postcode":"SW19 2RR",
    "sg:province":"Greater London",
    "sg:tags":[
        "mnfrs",
        "window",
        "film"
    ],
    "wof:name":"Unique Film Co",
    "wof:placetype":"venue"
},
  "geometry": {"coordinates":[-0.207024,51.420998],"type":"Point"}
}