{
  "type": "Feature",
  "properties": {
    "iso:country":"GB",
    "sg:address":"12 Flitcroft St",
    "sg:city":"London",
    "sg:classifiers":[
        {
            "category":"Real Estate",
            "subcategory":"Real Estate Agent",
            "type":"Services"
        }
    ],
    "sg:postcode":"WC2H 8DJ",
    "sg:province":"Greater London",
    "wof:name":"Whyke Properties Ltd",
    "wof:placetype":"venue"
},
  "geometry": {"coordinates":[-0.12952,51.514751],"type":"Point"}
}