{
  "type": "Feature",
  "properties": {
    "addr:full":"95 Louth Road Grimsby Lincolnshire DN33 2JH",
    "addr:housenumber":"95",
    "addr:postcode":"dn33 2jh",
    "addr:street":"Louth Road",
    "iso:country":"GB",
    "sg:address":"95 Louth Road",
    "sg:city":"Grimsby",
    "sg:classifiers":[
        {
            "category":"Education",
            "subcategory":"School",
            "type":"Public Place"
        }
    ],
    "sg:postcode":"DN33 2JH",
    "sg:province":"Lincolnshire",
    "sg:tags":[
        "private",
        "tuition"
    ],
    "wof:name":"Science & Mathematics Tuition Centre (The)",
    "wof:placetype":"venue"
},
  "geometry": {"coordinates":[-0.088068001,53.5344467163],"type":"Point"}
}