{
  "type": "Feature",
  "properties": {
    "iso:country":"GB",
    "sg:address":"91 Main Street, Hockwold",
    "sg:city":"Thetford",
    "sg:classifiers":[
        {
            "category":"Personal",
            "subcategory":"Beauty Salon",
            "type":"Services"
        },
        {
            "category":"Personal",
            "subcategory":"Barber",
            "type":"Services"
        }
    ],
    "sg:phone":"+44 1842 828253",
    "sg:postcode":"IP26 4LN",
    "sg:province":"Norfolk",
    "sg:tags":[
        "unisex",
        "hairdresser"
    ],
    "wof:name":"Mane Streak",
    "wof:placetype":"venue"
},
  "geometry": {"coordinates":[0.5474600196,52.4637145996],"type":"Point"}
}