{
  "type": "Feature",
  "properties": {
    "iso:country":"GB",
    "sg:address":"Bennetwood Farm, Southridge, Streatley",
    "sg:city":"Reading",
    "sg:classifiers":[
        {
            "category":"Banks & Credit Unions",
            "subcategory":"Investment Brokerage",
            "type":"Services"
        }
    ],
    "sg:phone":"+44 1491 872377",
    "sg:postcode":"RG8 9ST",
    "sg:province":"Berkshire",
    "sg:tags":[
        "contractor"
    ],
    "wof:name":"Chris Webber Contracting",
    "wof:placetype":"venue"
},
  "geometry": {"coordinates":[-1.148915,51.523052],"type":"Point"}
}