{
  "type": "Feature",
  "properties": {
    "addr:full":"75 Southfields Drive Leicester Leicestershire LE2 6QT",
    "addr:housenumber":"75",
    "addr:postcode":"le2 6qt",
    "addr:street":"Southfields Drive",
    "iso:country":"GB",
    "sg:address":"75 Southfields Drive",
    "sg:city":"Leicester",
    "sg:classifiers":[
        {
            "category":"Shopping",
            "subcategory":"Used Merchandise",
            "type":"Retail Goods"
        }
    ],
    "sg:phone":"+44 116 244 0889",
    "sg:postcode":"LE2 6QT",
    "sg:province":"Leicestershire",
    "sg:tags":[
        "furniture"
    ],
    "wof:name":"T J Mart",
    "wof:placetype":"venue"
},
  "geometry": {"coordinates":[-1.1332859993,52.5970306396],"type":"Point"}
}