{
  "type": "Feature",
  "properties": {
    "addr:full":"22 Victoria Street Paignton Devon TQ4 5DN",
    "addr:housenumber":"22",
    "addr:postcode":"tq4 5dn",
    "addr:street":"Victoria Street",
    "iso:country":"GB",
    "sg:address":"22 Victoria Street",
    "sg:city":"Paignton",
    "sg:classifiers":[
        {
            "category":"Shopping",
            "subcategory":"Gifts & Souvenirs",
            "type":"Retail Goods"
        }
    ],
    "sg:phone":"+44 1803 526094",
    "sg:postcode":"TQ4 5DN",
    "sg:province":"Devon",
    "sg:tags":[
        "shop"
    ],
    "wof:name":"Bastins Ltd.",
    "wof:placetype":"venue"
},
  "geometry": {"coordinates":[-3.566477,50.435513],"type":"Point"}
}