{
  "type": "Feature",
  "properties": {
    "iso:country":"GB",
    "sg:address":"6 Cedar Road",
    "sg:city":"Newport",
    "sg:classifiers":[
        {
            "category":"Personal",
            "type":"Services"
        }
    ],
    "sg:postcode":"NP19 0BA",
    "sg:province":"Newport",
    "sg:tags":[
        "dating",
        "friendship",
        "agency"
    ],
    "wof:name":"In Touch Uk",
    "wof:placetype":"venue"
},
  "geometry": {"coordinates":[-2.987371,51.590313],"type":"Point"}
}