{
  "type": "Feature",
  "properties": {
    "addr:full":"41 Cecil Street Carlisle Cumbria CA1 1NS",
    "addr:housenumber":"41",
    "addr:postcode":"ca1 1ns",
    "addr:street":"Cecil Street",
    "iso:country":"GB",
    "sg:address":"41 Cecil Street",
    "sg:city":"Carlisle",
    "sg:classifiers":[
        {
            "category":"Professional",
            "subcategory":"Art Services",
            "type":"Services"
        }
    ],
    "sg:phone":"+44 1228 533344",
    "sg:postcode":"CA1 1NS",
    "sg:province":"Cumbria",
    "sg:tags":[
        "photographer"
    ],
    "wof:name":"Studio North",
    "wof:placetype":"venue"
},
  "geometry": {"coordinates":[-2.9292600155,54.8920402527],"type":"Point"}
}