{
  "type": "Feature",
  "properties": {
    "addr:full":"Unit 8 Lower Mantel Close, Bridge Street Industrial Estate, Bridge Street Chesterfield Derbyshire S45 9NU",
    "addr:housenumber":"unit 8;estate",
    "addr:postcode":"s45 9nu",
    "addr:street":"Lower Mantel Close Bridge Street Industrial;Bridge Street",
    "iso:country":"GB",
    "sg:address":"Unit 8 Lower Mantel Close, Bridge Street Industrial Estate, Bridge Street",
    "sg:city":"Chesterfield",
    "sg:classifiers":[
        {
            "category":"Retail",
            "subcategory":"Auto Repair",
            "type":"Services"
        }
    ],
    "sg:postcode":"S45 9NU",
    "sg:province":"Derbyshire",
    "sg:tags":[
        "modification",
        "garage"
    ],
    "wof:name":"les Andrews",
    "wof:placetype":"venue"
},
  "geometry": {"coordinates":[-1.41169,53.169071],"type":"Point"}
}