{
  "type": "Feature",
  "properties": {
    "addr:full":"P O Box 85 Aylesbury Buckinghamshire HP20 2RL",
    "addr:housenumber":"box 85",
    "addr:postcode":"hp20 2rl",
    "addr:street":"P O",
    "iso:country":"GB",
    "sg:address":"P O Box 85",
    "sg:city":"Aylesbury",
    "sg:classifiers":[
        {
            "category":"Professional",
            "subcategory":"Lawyer & Legal Services",
            "type":"Services"
        }
    ],
    "sg:phone":"+44 1296 436827",
    "sg:postcode":"HP20 2RL",
    "sg:province":"Buckinghamshire",
    "sg:tags":[
        "advice",
        "counselling"
    ],
    "wof:name":"Womens Aid",
    "wof:placetype":"venue"
},
  "geometry": {"coordinates":[-0.810219,51.825901],"type":"Point"}
}