{
  "type": "Feature",
  "properties": {
    "iso:country":"GB",
    "sg:address":"21 High Street, Saltford",
    "sg:city":"Bristol",
    "sg:classifiers":[
        {
            "category":"Manufacturing",
            "subcategory":"Paper Products",
            "type":"Manufacturing & Wholesale Goods"
        }
    ],
    "sg:phone":"+44 1225 874366",
    "sg:postcode":"BS31 3ED",
    "sg:province":"City of Bristol",
    "sg:tags":[
        "cardboard"
    ],
    "wof:name":"Stewart Dagger",
    "wof:placetype":"venue"
},
  "geometry": {"coordinates":[-2.45517,51.404472],"type":"Point"}
}