{
  "type": "Feature",
  "properties": {
    "addr:full":"24 Otley Rd, Charlestown Baildon Shipley West Yorkshire BD17 7JN",
    "addr:housenumber":"24",
    "addr:postcode":"bd17 7jn",
    "addr:street":"Otley Rd",
    "iso:country":"GB",
    "sg:address":"24 Otley Rd, Charlestown Baildon",
    "sg:city":"Shipley",
    "sg:classifiers":[
        {
            "category":"Bars & Pubs",
            "type":"Food & Drink"
        },
        {
            "category":"Community Center",
            "subcategory":"Social",
            "type":"Public Place"
        }
    ],
    "sg:phone":"+44 1274 586530",
    "sg:postcode":"BD17 7JN",
    "sg:province":"West Yorkshire",
    "sg:tags":[
        "pubs",
        "house",
        "inn",
        "activity"
    ],
    "wof:name":"New Inn",
    "wof:placetype":"venue"
},
  "geometry": {"coordinates":[-1.7679200172,53.8406295776],"type":"Point"}
}