{
  "type": "Feature",
  "properties": {
    "addr:full":"Cross Hands Industrial Estate, Cross Hands Llanelli Carmarthenshire SA14 6RE",
    "addr:postcode":"sa14 6re",
    "addr:street":"Cross;Industrial Estate;Hands Llanelli",
    "iso:country":"GB",
    "sg:address":"Cross Hands Industrial Estate, Cross Hands",
    "sg:city":"Llanelli",
    "sg:classifiers":[
        {
            "category":"Retail",
            "subcategory":"Auto Repair",
            "type":"Services"
        }
    ],
    "sg:phone":"+44 1269 845043",
    "sg:postcode":"SA14 6RE",
    "sg:province":"Carmarthenshire",
    "sg:tags":[
        "caravan",
        "servicing"
    ],
    "wof:name":"John Stott",
    "wof:placetype":"venue"
},
  "geometry": {"coordinates":[-4.0850901604,51.7961578369],"type":"Point"}
}