{
  "type": "Feature",
  "properties": {
    "addr:full":"Unit 20 Brooklands Road, Carcroft Common, Carcroft Doncaster North Yorkshire DN6 7BA",
    "addr:housenumber":"unit 20",
    "addr:postcode":"dn6 7ba",
    "addr:street":"Brooklands Road Carcroft Common",
    "iso:country":"GB",
    "sg:address":"Unit 20 Brooklands Road, Carcroft Common, Carcroft",
    "sg:city":"Doncaster",
    "sg:classifiers":[
        {
            "category":"Manufacturing",
            "subcategory":"Signs",
            "type":"Manufacturing & Wholesale Goods"
        }
    ],
    "sg:phone":"+44 1302 728177",
    "sg:postcode":"DN6 7BA",
    "sg:province":"North Yorkshire",
    "sg:tags":[
        "writer"
    ],
    "wof:name":"Write Sign",
    "wof:placetype":"venue"
},
  "geometry": {"coordinates":[-1.1777590513,53.5777015686],"type":"Point"}
}