{
  "type": "Feature",
  "properties": {
    "addr:full":"955 Harrow Road Wembley Greater London HA0 2SA",
    "addr:housenumber":"955",
    "addr:postcode":"ha0 2sa",
    "addr:street":"Harrow Road",
    "iso:country":"GB",
    "sg:address":"955 Harrow Road",
    "sg:city":"Wembley",
    "sg:classifiers":[
        {
            "category":"Travel",
            "subcategory":"Hotels & Motels",
            "type":"Entertainment"
        }
    ],
    "sg:postcode":"HA0 2SA",
    "sg:province":"Greater London",
    "wof:name":"Sudbury Hotel",
    "wof:placetype":"venue"
},
  "geometry": {"coordinates":[-0.3276219964,51.5591926575],"type":"Point"}
}