{
  "type": "Feature",
  "properties": {
    "addr:full":"P O Box 78 Oxted Surrey RH8 0FH",
    "addr:housenumber":"box 78",
    "addr:postcode":"rh8 0fh",
    "addr:street":"P O;Oxted",
    "iso:country":"GB",
    "sg:address":"P O Box 78",
    "sg:city":"Oxted",
    "sg:classifiers":[
        {
            "category":"Professional",
            "subcategory":"Management & Consulting",
            "type":"Services"
        }
    ],
    "sg:phone":"+44 1883 722695",
    "sg:postcode":"RH8 0FH",
    "sg:province":"Surrey",
    "sg:tags":[
        "consultant",
        "business"
    ],
    "wof:name":"I M C G",
    "wof:placetype":"venue"
},
  "geometry": {"coordinates":[0.0098700002,51.2552108765],"type":"Point"}
}