{
  "type": "Feature",
  "properties": {
    "addr:full":"56 Eyehorne Street, Hollingbourne Maidstone Kent ME17 1TS",
    "addr:housenumber":"56",
    "addr:postcode":"me17 1ts",
    "addr:street":"Eyehorne Street",
    "iso:country":"GB",
    "sg:address":"56 Eyehorne Street, Hollingbourne",
    "sg:city":"Maidstone",
    "sg:classifiers":[
        {
            "category":"Bars & Pubs",
            "type":"Food & Drink"
        },
        {
            "category":"Community Center",
            "subcategory":"Social",
            "type":"Public Place"
        }
    ],
    "sg:phone":"+44 1622 880220",
    "sg:postcode":"ME17 1TS",
    "sg:province":"Kent",
    "sg:tags":[
        "pubs",
        "house",
        "inn",
        "activity"
    ],
    "wof:name":"The Sugar Loaves",
    "wof:placetype":"venue"
},
  "geometry": {"coordinates":[0.627644,51.26136],"type":"Point"}
}