{
  "type": "Feature",
  "properties": {
    "addr:full":"No.29 The Parade Swindon Wiltshire SN1 1BB",
    "addr:housenumber":"no.29",
    "addr:postcode":"sn1 1bb",
    "addr:street":"The Parade",
    "iso:country":"GB",
    "sg:address":"No.29 The Parade",
    "sg:city":"Swindon",
    "sg:classifiers":[
        {
            "category":"Shopping",
            "subcategory":"Department Store",
            "type":"Retail Goods"
        }
    ],
    "sg:postcode":"SN1 1BB",
    "sg:province":"Wiltshire",
    "wof:name":"Richard Popham Ltd",
    "wof:placetype":"venue"
},
  "geometry": {"coordinates":[-1.784979,51.563229],"type":"Point"}
}