{
  "type": "Feature",
  "properties": {
    "addr:full":"51 Alexandra Parade Dunoon Argyll and Bute PA23 8AF",
    "addr:housenumber":"51",
    "addr:postcode":"pa23 8af",
    "addr:street":"Alexandra Parade",
    "iso:country":"GB",
    "sg:address":"51 Alexandra Parade",
    "sg:city":"Dunoon",
    "sg:classifiers":[
        {
            "category":"Travel",
            "subcategory":"Hotels & Motels",
            "type":"Entertainment"
        }
    ],
    "sg:postcode":"PA23 8AF",
    "sg:province":"Argyll and Bute",
    "sg:tags":[
        "house",
        "guest"
    ],
    "wof:name":"The Cedars Hotel",
    "wof:placetype":"venue"
},
  "geometry": {"coordinates":[-4.922727108,55.9519577026],"type":"Point"}
}