{
  "type": "Feature",
  "properties": {
    "addr:full":"Enterprise House, Foleshill Enterprise Park Coventry Warwickshire CV6 5NX",
    "addr:postcode":"cv6 5nx",
    "addr:street":"Enterprise Park",
    "iso:country":"GB",
    "sg:address":"Enterprise House, Foleshill Enterprise Park",
    "sg:city":"Coventry",
    "sg:classifiers":[
        {
            "category":"Communications",
            "type":"Services"
        }
    ],
    "sg:phone":"+44 24 7666 7337",
    "sg:postcode":"CV6 5NX",
    "sg:province":"Warwickshire",
    "sg:tags":[
        "data",
        "network"
    ],
    "wof:name":"Edge Designs Ltd.",
    "wof:placetype":"venue"
},
  "geometry": {"coordinates":[-1.50311,52.424671],"type":"Point"}
}