{
  "type": "Feature",
  "properties": {
    "iso:country":"GB",
    "sg:address":"22-24 Coleridge Drive, Enderby",
    "sg:city":"Leicester",
    "sg:classifiers":[
        {
            "category":"Organizations",
            "subcategory":"Community Association",
            "type":"Services"
        },
        {
            "category":"Organizations",
            "subcategory":"Membership Organization",
            "type":"Services"
        }
    ],
    "sg:phone":"+44 116 286 4897",
    "sg:postcode":"LE19 4QF",
    "sg:province":"Leicestershire",
    "sg:tags":[
        "club",
        "social"
    ],
    "wof:name":"Enderby & District Social Club Ltd.",
    "wof:placetype":"venue"
},
  "geometry": {"coordinates":[-1.2064640522,52.5886383057],"type":"Point"}
}