{
  "type": "Feature",
  "properties": {
    "iso:country":"GB",
    "sg:address":"Units 8 -9, Lyon Close Woburn Road Industria",
    "sg:city":"Bedford",
    "sg:classifiers":[
        {
            "category":"Manufacturing",
            "subcategory":"Rubber & Plastics",
            "type":"Manufacturing & Wholesale Goods"
        },
        {
            "category":"Wholesale",
            "subcategory":"Electrical",
            "type":"Manufacturing & Wholesale Goods"
        }
    ],
    "sg:phone":"+44 1234 843737",
    "sg:postcode":"MK42 7SB",
    "sg:province":"Bedfordshire",
    "sg:tags":[
        "equipment",
        "product",
        "foam",
        "refrigeration"
    ],
    "wof:name":"Foam Conversion (U K) Ltd.",
    "wof:placetype":"venue"
},
  "geometry": {"coordinates":[-0.49208,52.10976],"type":"Point"}
}