{
  "type": "Feature",
  "properties": {
    "iso:country":"GB",
    "sg:address":"Ivy Mills, Mill Lane",
    "sg:city":"Bradford",
    "sg:classifiers":[
        {
            "category":"Shopping",
            "type":"Retail Goods"
        }
    ],
    "sg:postcode":"BD5 0HF",
    "sg:province":"West Yorkshire",
    "sg:tags":[
        "product",
        "disposable"
    ],
    "wof:name":"Yorkshire Rose Paper Convertors",
    "wof:placetype":"venue"
},
  "geometry": {"coordinates":[-1.74866,53.786179],"type":"Point"}
}