{
  "type": "Feature",
  "properties": {
    "addr:full":"Albert Road Rushden Bedfordshire NN10 0BU",
    "addr:postcode":"nn10 0bu",
    "addr:street":"Albert Road",
    "iso:country":"GB",
    "sg:address":"Albert Road",
    "sg:city":"Rushden",
    "sg:classifiers":[
        {
            "category":"Farming",
            "subcategory":"Dairy Farm",
            "type":"Manufacturing & Wholesale Goods"
        },
        {
            "category":"Food & Beverages",
            "subcategory":"Groceries & Convenience Stores",
            "type":"Retail Goods"
        }
    ],
    "sg:postcode":"NN10 0BU",
    "sg:province":"Bedfordshire",
    "wof:name":"Abbott's Dairy",
    "wof:placetype":"venue"
},
  "geometry": {"coordinates":[-0.5939210057,52.2932662964],"type":"Point"}
}