{
  "type": "Feature",
  "properties": {
    "iso:country":"GB",
    "sg:address":"17 Milton Rd",
    "sg:city":"Swindon",
    "sg:classifiers":[
        {
            "category":"Organizations",
            "subcategory":"Membership Organization",
            "type":"Services"
        }
    ],
    "sg:phone":"+44 1793 536316",
    "sg:postcode":"SN1 5JE",
    "sg:province":"Wiltshire",
    "sg:tags":[
        "club"
    ],
    "wof:name":"Polish Club",
    "wof:placetype":"venue"
},
  "geometry": {"coordinates":[-1.7896089554,51.5602455139],"type":"Point"}
}