{
  "type": "Feature",
  "properties": {
    "addr:full":"12 Howard Street Rotherham South Yorkshire S60 1QU",
    "addr:housenumber":"12",
    "addr:postcode":"s60 1qu",
    "addr:street":"Howard Street",
    "iso:country":"GB",
    "sg:address":"12 Howard Street",
    "sg:city":"Rotherham",
    "sg:classifiers":[
        {
            "category":"Shopping",
            "subcategory":"Pharmacy",
            "type":"Retail Goods"
        }
    ],
    "sg:phone":"+44 1709 820343",
    "sg:postcode":"S60 1QU",
    "sg:province":"South Yorkshire",
    "sg:tags":[
        "store",
        "drug"
    ],
    "wof:name":"Superdrug Stores Pharmacy",
    "wof:placetype":"venue"
},
  "geometry": {"coordinates":[-1.3544800282,53.4319229126],"type":"Point"}
}