{
  "type": "Feature",
  "properties": {
    "iso:country":"GB",
    "sg:address":"26 Castle Arcade Balcony",
    "sg:city":"Cardiff",
    "sg:classifiers":[
        {
            "category":"Communications",
            "subcategory":"Newspaper",
            "type":"Services"
        },
        {
            "category":"Wholesale",
            "subcategory":"Books, Periodicals, & Newspapers",
            "type":"Manufacturing & Wholesale Goods"
        }
    ],
    "sg:phone":"+44 29 2066 5161",
    "sg:postcode":"CF10 1BY",
    "sg:province":"Cardiff",
    "sg:tags":[
        "publisher",
        "magazine"
    ],
    "wof:name":"Jazz Newspapers Ltd",
    "wof:placetype":"venue"
},
  "geometry": {"coordinates":[-3.180717,51.481022],"type":"Point"}
}