{
  "type": "Feature",
  "properties": {
    "addr:full":"Pine Court, Ripley Road Knaresborough North Yorkshire HG5 9BU",
    "addr:postcode":"hg5 9bu",
    "addr:street":"Pine Court Ripley Road",
    "iso:country":"GB",
    "sg:address":"Pine Court, Ripley Road",
    "sg:city":"Knaresborough",
    "sg:classifiers":[
        {
            "category":"Health Services",
            "subcategory":"Nursing And Care Facility",
            "type":"Services"
        }
    ],
    "sg:phone":"+44 1423 866677",
    "sg:postcode":"HG5 9BU",
    "sg:province":"North Yorkshire",
    "sg:tags":[
        "home"
    ],
    "wof:name":"Insight Homes Ltd.",
    "wof:placetype":"venue"
},
  "geometry": {"coordinates":[-1.492609,54.020287],"type":"Point"}
}