{
  "type": "Feature",
  "properties": {
    "addr:full":"The Harriot, Harriots Lane Ashtead Surrey KT21 2QH",
    "addr:postcode":"kt21 2qh",
    "addr:street":"Harriots Lane",
    "iso:country":"GB",
    "sg:address":"The Harriot, Harriots Lane",
    "sg:city":"Ashtead",
    "sg:classifiers":[
        {
            "category":"Professional",
            "subcategory":"Engineering",
            "type":"Services"
        }
    ],
    "sg:phone":"+44 1372 279515",
    "sg:postcode":"KT21 2QH",
    "sg:province":"Surrey",
    "sg:tags":[
        "contractor",
        "electrical",
        "engineer"
    ],
    "wof:name":"Acre Installations",
    "wof:placetype":"venue"
},
  "geometry": {"coordinates":[-0.300947994,51.3088989258],"type":"Point"}
}