{
  "type": "Feature",
  "properties": {
    "addr:full":"50 James St Louth Lincolnshire LN11 0JW",
    "addr:housenumber":"50",
    "addr:postcode":"ln11 0jw",
    "addr:street":"James St Louth",
    "iso:country":"GB",
    "sg:address":"50 James St",
    "sg:city":"Louth",
    "sg:classifiers":[
        {
            "category":"Building & Trades",
            "subcategory":"Construction",
            "type":"Services"
        }
    ],
    "sg:phone":"+44 1507 602466",
    "sg:postcode":"LN11 0JW",
    "sg:province":"Lincolnshire",
    "sg:tags":[
        "joinery"
    ],
    "wof:name":"Brown,M R,",
    "wof:placetype":"venue"
},
  "geometry": {"coordinates":[-0.000295,53.369022],"type":"Point"}
}