{
  "type": "Feature",
  "properties": {
    "iso:country":"GB",
    "sg:address":"243 Byres Rd",
    "sg:city":"Glasgow",
    "sg:classifiers":[
        {
            "category":"Shopping",
            "subcategory":"Shoes",
            "type":"Retail Goods"
        }
    ],
    "sg:postcode":"G12 8UB",
    "sg:province":"Glasgow City",
    "sg:tags":[
        "shop"
    ],
    "wof:name":"Stead & Simpson Ltd",
    "wof:placetype":"venue"
},
  "geometry": {"coordinates":[-4.293922,55.875301],"type":"Point"}
}