{
  "type": "Feature",
  "properties": {
    "addr:full":"64 West Gro Walton On Thames Surrey KT12 5PB",
    "addr:housenumber":"64",
    "addr:postcode":"kt12 5pb",
    "addr:street":"West Gro",
    "iso:country":"GB",
    "sg:address":"64 West Gro",
    "sg:city":"Walton On Thames",
    "sg:classifiers":[
        {
            "category":"Building & Trades",
            "subcategory":"Landscaping Services",
            "type":"Services"
        }
    ],
    "sg:phone":"+44 1932 241812",
    "sg:postcode":"KT12 5PB",
    "sg:province":"Surrey",
    "sg:tags":[
        "forestry",
        "tree"
    ],
    "wof:name":"Raymond Fairhead",
    "wof:placetype":"venue"
},
  "geometry": {"coordinates":[-0.409637,51.371979],"type":"Point"}
}