{
  "type": "Feature",
  "properties": {
    "addr:full":"London Road Bedford Bedfordshire MK42 0NX",
    "addr:postcode":"mk42 0nx",
    "addr:street":"London Road",
    "iso:country":"GB",
    "sg:address":"London Road",
    "sg:city":"Bedford",
    "sg:classifiers":[
        {
            "category":"Autos & Motor Vehicles",
            "subcategory":"Fuel & Gas Station",
            "type":"Retail Goods"
        }
    ],
    "sg:phone":"+44 1234 345190",
    "sg:postcode":"MK42 0NX",
    "sg:province":"Bedfordshire",
    "sg:tags":[
        "hr",
        "petrol"
    ],
    "wof:name":"Southgate Service Station",
    "wof:placetype":"venue"
},
  "geometry": {"coordinates":[-0.461554,52.127777],"type":"Point"}
}