{
  "type": "Feature",
  "properties": {
    "iso:country":"GB",
    "sg:address":"Gutter Farm, Winkhill",
    "sg:city":"Leek",
    "sg:classifiers":[
        {
            "category":"Farming",
            "subcategory":"Livestock Farm",
            "type":"Manufacturing & Wholesale Goods"
        }
    ],
    "sg:phone":"+44 1538 308280",
    "sg:postcode":"ST13 7QT",
    "sg:province":"Staffordshire",
    "sg:tags":[
        "others"
    ],
    "wof:name":"Top Gutter Farm",
    "wof:placetype":"venue"
},
  "geometry": {"coordinates":[-1.9089250565,53.058177948],"type":"Point"}
}