{
  "type": "Feature",
  "properties": {
    "addr:full":"Broad St Birmingham West Midlands B1 2DY",
    "addr:postcode":"b1 2dy",
    "addr:street":"Broad St",
    "iso:country":"GB",
    "sg:address":"Broad St",
    "sg:city":"Birmingham",
    "sg:classifiers":[
        {
            "category":"Bars & Pubs",
            "type":"Food & Drink"
        }
    ],
    "sg:phone":"+44 121 643 0444",
    "sg:postcode":"B1 2DY",
    "sg:province":"West Midlands",
    "sg:tags":[
        "pubs",
        "inn"
    ],
    "wof:name":"Edwards",
    "wof:placetype":"venue"
},
  "geometry": {"coordinates":[-1.9120739698,52.4768753052],"type":"Point"}
}