{
  "type": "Feature",
  "properties": {
    "addr:full":"72 Commercial St Newport East Riding of Yorkshire NP1 6BA",
    "addr:housenumber":"72",
    "addr:postcode":"np1 6ba",
    "addr:street":"Commercial St",
    "iso:country":"GB",
    "sg:address":"72 Commercial St",
    "sg:city":"Newport",
    "sg:classifiers":[
        {
            "category":"Health Services",
            "subcategory":"Dentist",
            "type":"Services"
        }
    ],
    "sg:phone":"+44 1633 601411",
    "sg:postcode":"NP1 6BA",
    "sg:province":"East Riding of Yorkshire",
    "sg:tags":[
        "technician",
        "dental"
    ],
    "wof:name":"Risca Dental Laboratory",
    "wof:placetype":"venue"
},
  "geometry": {"coordinates":[-2.9930789471,51.5838737488],"type":"Point"}
}