{
  "type": "Feature",
  "properties": {
    "iso:country":"GB",
    "sg:address":"260 The Glades Shopping Centre",
    "sg:city":"Bromley",
    "sg:classifiers":[
        {
            "category":"Banks & Credit Unions",
            "subcategory":"Bank",
            "type":"Services"
        }
    ],
    "sg:phone":"+44 20 8460 0048",
    "sg:postcode":"BR1 1DN",
    "sg:province":"Kent",
    "wof:name":"Abbey National Plc",
    "wof:placetype":"venue"
},
  "geometry": {"coordinates":[0.014928,51.405701],"type":"Point"}
}