{
  "type": "Feature",
  "properties": {
    "addr:full":"Unit 2, Dabble Duck Industrial Estate Shildon Durham DL4 2RA",
    "addr:housenumber":"unit 2",
    "addr:postcode":"dl4 2ra",
    "addr:street":"Dabble Duck Industrial",
    "iso:country":"GB",
    "sg:address":"Unit 2, Dabble Duck Industrial Estate",
    "sg:city":"Shildon",
    "sg:classifiers":[
        {
            "category":"Professional",
            "type":"Services"
        },
        {
            "category":"Autos & Motor Vehicles",
            "subcategory":"Auto Supplies",
            "type":"Retail Goods"
        }
    ],
    "sg:phone":"+44 1388 774411",
    "sg:postcode":"DL4 2RA",
    "sg:province":"Durham",
    "sg:tags":[
        "control",
        "sales",
        "electric",
        "servicing",
        "system"
    ],
    "wof:name":"Clark Components Co. Ltd.",
    "wof:placetype":"venue"
},
  "geometry": {"coordinates":[-1.651709,54.628571],"type":"Point"}
}