{
  "type": "Feature",
  "properties": {
    "iso:country":"GB",
    "sg:address":"156 Hawton Rd",
    "sg:city":"Newark",
    "sg:classifiers":[
        {
            "category":"Cinema",
            "subcategory":"Movie Rental",
            "type":"Entertainment"
        }
    ],
    "sg:phone":"+44 1636 676809",
    "sg:postcode":"NG24 4QQ",
    "sg:province":"Nottinghamshire",
    "sg:tags":[
        "video",
        "library"
    ],
    "wof:name":"Trends Video Centre",
    "wof:placetype":"venue"
},
  "geometry": {"coordinates":[-0.824267,53.061363],"type":"Point"}
}