{
  "type": "Feature",
  "properties": {
    "addr:full":"290 Woodgrange Dr Southend On Sea Essex SS1 2XR",
    "addr:housenumber":"290",
    "addr:postcode":"ss1 2xr",
    "addr:street":"Woodgrange Dr",
    "iso:country":"GB",
    "sg:address":"290 Woodgrange Dr",
    "sg:city":"Southend On Sea",
    "sg:classifiers":[
        {
            "category":"Shopping",
            "subcategory":"Party Supplies",
            "type":"Retail Goods"
        }
    ],
    "sg:phone":"+44 1702 465253",
    "sg:postcode":"SS1 2XR",
    "sg:province":"Essex",
    "sg:tags":[
        "inflatables",
        "bouncy",
        "castle"
    ],
    "wof:name":"Fergus Fun Factory",
    "wof:placetype":"venue"
},
  "geometry": {"coordinates":[0.736747,51.53569],"type":"Point"}
}