{
  "type": "Feature",
  "properties": {
    "iso:country":"GB",
    "sg:address":"Nellington Court, Fremlin Close",
    "sg:city":"Tunbridge Wells",
    "sg:classifiers":[
        {
            "category":"Health Services",
            "subcategory":"Nursing And Care Facility",
            "type":"Services"
        }
    ],
    "sg:phone":"+44 1892 542763",
    "sg:postcode":"TN4 8SZ",
    "sg:province":"Kent",
    "sg:tags":[
        "home"
    ],
    "wof:name":"Humanist Housing Association",
    "wof:placetype":"venue"
},
  "geometry": {"coordinates":[0.224679,51.137302],"type":"Point"}
}