{
  "type": "Feature",
  "properties": {
    "addr:full":"26 Norwich Rd, Thelveton Diss Norfolk IP21 4NG",
    "addr:housenumber":"26",
    "addr:postcode":"ip21 4ng",
    "addr:street":"Norwich Rd",
    "iso:country":"GB",
    "sg:address":"26 Norwich Rd, Thelveton",
    "sg:city":"Diss",
    "sg:classifiers":[
        {
            "category":"Building & Trades",
            "subcategory":"Construction",
            "type":"Services"
        }
    ],
    "sg:phone":"+44 1379 741070",
    "sg:postcode":"IP21 4NG",
    "sg:province":"Norfolk",
    "sg:tags":[
        "joiner",
        "carpenter"
    ],
    "wof:name":"P.R West",
    "wof:placetype":"venue"
},
  "geometry": {"coordinates":[1.177008,52.386475],"type":"Point"}
}