{
  "type": "Feature",
  "properties": {
    "addr:full":"61 Marston Road Stafford Staffordshire ST16 3BX",
    "addr:housenumber":"61",
    "addr:postcode":"st16 3bx",
    "addr:street":"Marston Road",
    "iso:country":"GB",
    "sg:address":"61 Marston Road",
    "sg:city":"Stafford",
    "sg:classifiers":[
        {
            "category":"Banks & Credit Unions",
            "subcategory":"Financial Services",
            "type":"Services"
        }
    ],
    "sg:postcode":"ST16 3BX",
    "sg:province":"Staffordshire",
    "sg:tags":[
        "adviser"
    ],
    "wof:name":"Fortune Financial Services",
    "wof:placetype":"venue"
},
  "geometry": {"coordinates":[-2.118724,52.817917],"type":"Point"}
}