{
  "type": "Feature",
  "properties": {
    "iso:country":"GB",
    "sg:address":"1 Ashfield Rd, Shotton",
    "sg:city":"Deeside",
    "sg:classifiers":[
        {
            "category":"Arts & Performance",
            "subcategory":"Music",
            "type":"Entertainment"
        }
    ],
    "sg:phone":"+44 1244 821067",
    "sg:postcode":"CH5 1AQ",
    "sg:province":"Flintshire",
    "sg:tags":[
        "mobile",
        "disco"
    ],
    "wof:name":"Cascade Disco",
    "wof:placetype":"venue"
},
  "geometry": {"coordinates":[-3.0355019569,53.2126502991],"type":"Point"}
}