{
  "type": "Feature",
  "properties": {
    "iso:country":"GB",
    "sg:address":"14 Premier House, Waterloo Terrace",
    "sg:city":"London",
    "sg:classifiers":[
        {
            "category":"Shopping",
            "subcategory":"Photographic Equipment",
            "type":"Retail Goods"
        }
    ],
    "sg:postcode":"N1 1TG",
    "sg:province":"Greater London",
    "wof:name":"Martin Evening",
    "wof:placetype":"venue"
},
  "geometry": {"coordinates":[-0.1032499969,51.5405731201],"type":"Point"}
}