{
  "type": "Feature",
  "properties": {
    "addr:full":"Lower Level, The Bargate Centre Southampton Hampshire SO14 2YD",
    "addr:housenumber":"lower level",
    "addr:postcode":"so14 2yd",
    "addr:street":"The Bargate Centre",
    "iso:country":"GB",
    "sg:address":"Lower Level, The Bargate Centre",
    "sg:city":"Southampton",
    "sg:classifiers":[
        {
            "category":"Utilities",
            "type":"Services"
        }
    ],
    "sg:phone":"+44 23 8023 3548",
    "sg:postcode":"SO14 2YD",
    "sg:province":"Hampshire",
    "sg:tags":[
        "internet"
    ],
    "wof:name":"Internet Exchange",
    "wof:placetype":"venue"
},
  "geometry": {"coordinates":[-1.4028999805,50.9024085999],"type":"Point"}
}