{
  "type": "Feature",
  "properties": {
    "addr:full":"103 Grosvenor Place Margate Kent CT9 1UX",
    "addr:housenumber":"103",
    "addr:postcode":"ct9 1ux",
    "addr:street":"Grosvenor Place Margate",
    "iso:country":"GB",
    "sg:address":"103 Grosvenor Place",
    "sg:city":"Margate",
    "sg:classifiers":[
        {
            "category":"Utilities",
            "subcategory":"Telephone",
            "type":"Services"
        }
    ],
    "sg:phone":"+44 1843 232777",
    "sg:postcode":"CT9 1UX",
    "sg:province":"Kent",
    "sg:tags":[
        "telecommunication"
    ],
    "wof:name":"Kent Telephones",
    "wof:placetype":"venue"
},
  "geometry": {"coordinates":[1.381261,51.383682],"type":"Point"}
}