{
  "type": "Feature",
  "properties": {
    "addr:full":"111 Strathmore Drive Stirling Clackmannanshire FK9 5DT",
    "addr:housenumber":"111",
    "addr:postcode":"fk9 5dt",
    "addr:street":"Strathmore Drive",
    "iso:country":"GB",
    "sg:address":"111 Strathmore Drive",
    "sg:city":"Stirling",
    "sg:classifiers":[
        {
            "category":"Building & Trades",
            "subcategory":"Construction",
            "type":"Services"
        }
    ],
    "sg:phone":"+44 1786 465348",
    "sg:postcode":"FK9 5DT",
    "sg:province":"Clackmannanshire",
    "sg:tags":[
        "joinery",
        "decorator",
        "painter",
        "carpentry"
    ],
    "wof:name":"Doug Marshall",
    "wof:placetype":"venue"
},
  "geometry": {"coordinates":[-3.9237589836,56.1383895874],"type":"Point"}
}