{
  "type": "Feature",
  "properties": {
    "addr:full":"Bordley Green Farm, Hetton Skipton Lancashire BD23 6NE",
    "addr:housenumber":"hetton skipton",
    "addr:postcode":"bd23 6ne",
    "iso:country":"GB",
    "sg:address":"Bordley Green Farm, Hetton",
    "sg:city":"Skipton",
    "sg:classifiers":[
        {
            "category":"Farming",
            "subcategory":"Livestock Farm",
            "type":"Manufacturing & Wholesale Goods"
        }
    ],
    "sg:phone":"+44 1729 830350",
    "sg:postcode":"BD23 6NE",
    "sg:province":"Lancashire",
    "sg:tags":[
        "others"
    ],
    "wof:name":"J S Stephenson",
    "wof:placetype":"venue"
},
  "geometry": {"coordinates":[-2.090883,54.080284],"type":"Point"}
}