{
  "type": "Feature",
  "properties": {
    "iso:country":"GB",
    "sg:address":"Unit 5c Roundwood Industrial Estate",
    "sg:city":"Ossett",
    "sg:classifiers":[
        {
            "category":"Professional",
            "subcategory":"Engineering",
            "type":"Services"
        },
        {
            "category":"Building & Trades",
            "subcategory":"Electrical",
            "type":"Services"
        }
    ],
    "sg:phone":"+44 1924 269999",
    "sg:postcode":"WF5 9SQ",
    "sg:province":"West Yorkshire",
    "sg:tags":[
        "engineer",
        "electrician",
        "contractor"
    ],
    "wof:name":"Key Electrical Contractors & Storefitters",
    "wof:placetype":"venue"
},
  "geometry": {"coordinates":[-1.548518,53.679585],"type":"Point"}
}