{
  "type": "Feature",
  "properties": {
    "addr:full":"5 Baltic Pl Bristol Somerset BS20 0EJ",
    "addr:housenumber":"5",
    "addr:postcode":"bs20 0ej",
    "addr:street":"Baltic Pl",
    "iso:country":"GB",
    "sg:address":"5 Baltic Pl",
    "sg:city":"Bristol",
    "sg:classifiers":[
        {
            "category":"Health Services",
            "subcategory":"Dentist",
            "type":"Services"
        }
    ],
    "sg:phone":"+44 1275 373497",
    "sg:postcode":"BS20 0EJ",
    "sg:province":"Somerset",
    "wof:name":"A P Pritchard",
    "wof:placetype":"venue"
},
  "geometry": {"coordinates":[-2.684424,51.478855],"type":"Point"}
}