{
  "type": "Feature",
  "properties": {
    "iso:country":"GB",
    "sg:address":"84 Cotmore Close",
    "sg:city":"Thame",
    "sg:classifiers":[
        {
            "category":"Retail",
            "subcategory":"Driving School",
            "type":"Services"
        }
    ],
    "sg:phone":"+44 1844 261505",
    "sg:postcode":"OX9 3NE",
    "sg:province":"Buckinghamshire",
    "wof:name":"Berkeley School of Motoring",
    "wof:placetype":"venue"
},
  "geometry": {"coordinates":[-0.964689,51.74221],"type":"Point"}
}