{
  "type": "Feature",
  "properties": {
    "iso:country":"GB",
    "sg:address":"Sterling Court, Leyland Business Park, Centurion Way, Farington",
    "sg:city":"Preston",
    "sg:classifiers":[
        {
            "category":"Professional",
            "subcategory":"Printing & Photocopies",
            "type":"Services"
        },
        {
            "category":"Professional",
            "subcategory":"Computer Services",
            "type":"Services"
        }
    ],
    "sg:phone":"+44 1772 622322",
    "sg:postcode":"PR25 3GR",
    "sg:province":"Lancashire",
    "sg:tags":[
        "software",
        "printer",
        "system",
        "supply"
    ],
    "wof:name":"Townsend Print Services Ltd",
    "wof:placetype":"venue"
},
  "geometry": {"coordinates":[-2.647199,53.785809],"type":"Point"}
}