{
  "type": "Feature",
  "properties": {
    "addr:full":"89 Barrack Lane, Aldwick Bognor Regis West Sussex PO21 4DX",
    "addr:housenumber":"89",
    "addr:postcode":"po21 4dx",
    "addr:street":"Barrack Lane",
    "iso:country":"GB",
    "sg:address":"89 Barrack Lane, Aldwick",
    "sg:city":"Bognor Regis",
    "sg:classifiers":[
        {
            "category":"Building & Trades",
            "subcategory":"Plumbing",
            "type":"Services"
        }
    ],
    "sg:phone":"+44 1243 268875",
    "sg:postcode":"PO21 4DX",
    "sg:province":"West Sussex",
    "sg:tags":[
        "central",
        "heating"
    ],
    "wof:name":"Aqua Plumbing & Heating",
    "wof:placetype":"venue"
},
  "geometry": {"coordinates":[-0.7169299722,50.7775001526],"type":"Point"}
}