{
  "type": "Feature",
  "properties": {
    "iso:country":"GB",
    "sg:address":"14 Clifford Street",
    "sg:city":"York",
    "sg:classifiers":[
        {
            "category":"Food & Beverages",
            "subcategory":"Bakery",
            "type":"Retail Goods"
        }
    ],
    "sg:phone":"+44 1904 646361",
    "sg:postcode":"YO1 9RD",
    "sg:province":"North Yorkshire",
    "sg:tags":[
        "pizza"
    ],
    "wof:name":"Pizza Hut",
    "wof:placetype":"venue"
},
  "geometry": {"coordinates":[-1.0817660093,53.9567070007],"type":"Point"}
}