{
  "type": "Feature",
  "properties": {
    "addr:full":"455 Blackburn Road Bolton Lancashire BL1 8NN",
    "addr:housenumber":"455",
    "addr:postcode":"bl1 8nn",
    "addr:street":"Blackburn Road",
    "iso:country":"GB",
    "sg:address":"455 Blackburn Road",
    "sg:city":"Bolton",
    "sg:classifiers":[
        {
            "category":"Bars & Pubs",
            "type":"Food & Drink"
        }
    ],
    "sg:phone":"+44 1204 301557",
    "sg:postcode":"BL1 8NN",
    "sg:province":"Lancashire",
    "sg:tags":[
        "pubs",
        "inn"
    ],
    "wof:name":"The Lamb Hotel",
    "wof:placetype":"venue"
},
  "geometry": {"coordinates":[-2.433032,53.598541],"type":"Point"}
}