{
  "type": "Feature",
  "properties": {
    "addr:full":"Unit 12, Garonor Way, Portbury Bristol Somerset BS20 7XE",
    "addr:housenumber":"unit 12",
    "addr:postcode":"bs20 7xe",
    "addr:street":"Garonor Way",
    "iso:country":"GB",
    "sg:address":"Unit 12, Garonor Way, Portbury",
    "sg:city":"Bristol",
    "sg:classifiers":[
        {
            "category":"Food & Beverages",
            "subcategory":"Candy",
            "type":"Retail Goods"
        }
    ],
    "sg:phone":"+44 1275 374850",
    "sg:postcode":"BS20 7XE",
    "sg:province":"Somerset",
    "sg:tags":[
        "confectionery"
    ],
    "wof:name":"Manor Bakeries",
    "wof:placetype":"venue"
},
  "geometry": {"coordinates":[-2.7116100788,51.4840698242],"type":"Point"}
}