{
  "type": "Feature",
  "properties": {
    "iso:country":"GB",
    "sg:address":"57 Bankhouse Rd",
    "sg:city":"Nelson",
    "sg:classifiers":[
        {
            "category":"Shopping",
            "subcategory":"Department Store",
            "type":"Retail Goods"
        }
    ],
    "sg:postcode":"BB9 7QN",
    "sg:province":"Lancashire",
    "wof:name":"Boothman,M,",
    "wof:placetype":"venue"
},
  "geometry": {"coordinates":[-2.210563,53.84],"type":"Point"}
}