{
  "type": "Feature",
  "properties": {
    "iso:country":"GB",
    "sg:address":"75 St Marys Way",
    "sg:city":"Nottingham",
    "sg:classifiers":[
        {
            "category":"Building & Trades",
            "subcategory":"Plumbing",
            "type":"Services"
        }
    ],
    "sg:postcode":"NG15 7DL",
    "sg:province":"Nottinghamshire",
    "sg:tags":[
        "central",
        "heating"
    ],
    "wof:name":"Colin R Moore",
    "wof:placetype":"venue"
},
  "geometry": {"coordinates":[-1.2060699463,53.0430221558],"type":"Point"}
}