{
  "type": "Feature",
  "properties": {
    "addr:full":"4 Ravine Terrace, Roker Sunderland Tyne and Wear SR6 9LZ",
    "addr:housenumber":"4",
    "addr:postcode":"sr6 9lz",
    "addr:street":"Ravine Terrace",
    "iso:country":"GB",
    "sg:address":"4 Ravine Terrace, Roker",
    "sg:city":"Sunderland",
    "sg:classifiers":[
        {
            "category":"Sports & Exercise",
            "subcategory":"Swimming Pool",
            "type":"Entertainment"
        }
    ],
    "sg:phone":"+44 191 567 8423",
    "sg:postcode":"SR6 9LZ",
    "sg:province":"Tyne and Wear",
    "sg:tags":[
        "diver"
    ],
    "wof:name":"Divesafe",
    "wof:placetype":"venue"
},
  "geometry": {"coordinates":[-1.3668940067,54.9249763489],"type":"Point"}
}