{
  "type": "Feature",
  "properties": {
    "addr:full":"Howard Rd, Strensall York North Yorkshire YO32 5SS",
    "addr:postcode":"yo32 5ss",
    "addr:street":"Howard Rd",
    "iso:country":"GB",
    "sg:address":"Howard Rd, Strensall",
    "sg:city":"York",
    "sg:classifiers":[
        {
            "category":"Professional",
            "subcategory":"Engineering",
            "type":"Services"
        }
    ],
    "sg:phone":"+44 1904 490800",
    "sg:postcode":"YO32 5SS",
    "sg:province":"North Yorkshire",
    "sg:tags":[
        "electrical",
        "engineer"
    ],
    "wof:name":"Daubney",
    "wof:placetype":"venue"
},
  "geometry": {"coordinates":[-1.0384520292,54.0359573364],"type":"Point"}
}