{
  "type": "Feature",
  "properties": {
    "iso:country":"GB",
    "sg:address":"Unit 6 Belasis Ct, Greenwood Rd",
    "sg:city":"Billingham",
    "sg:classifiers":[
        {
            "category":"Professional",
            "subcategory":"Engineering",
            "type":"Services"
        }
    ],
    "sg:phone":"+44 1642 567100",
    "sg:postcode":"TS23 4AZ",
    "sg:province":"Durham",
    "sg:tags":[
        "contractor",
        "electrical",
        "engineer"
    ],
    "wof:name":"R & H (UK) Ltd",
    "wof:placetype":"venue"
},
  "geometry": {"coordinates":[-1.2693749666,54.6026000977],"type":"Point"}
}