{
  "type": "Feature",
  "properties": {
    "iso:country":"GB",
    "sg:address":"Heltwate, Bretton",
    "sg:city":"Peterborough",
    "sg:classifiers":[
        {
            "category":"Shopping",
            "subcategory":"Department Store",
            "type":"Retail Goods"
        }
    ],
    "sg:phone":"+44 1733 267966",
    "sg:postcode":"PE3 8RE",
    "sg:province":"Cambridgeshire",
    "wof:name":"Heltwate Stores",
    "wof:placetype":"venue"
},
  "geometry": {"coordinates":[-0.288839,52.6008],"type":"Point"}
}