{
  "type": "Feature",
  "properties": {
    "iso:country":"GB",
    "sg:address":"9 Winterbottom Gro, Mottram",
    "sg:city":"Hyde",
    "sg:classifiers":[
        {
            "category":"Organizations",
            "subcategory":"Membership Organization",
            "type":"Services"
        }
    ],
    "sg:postcode":"SK14 6QL",
    "sg:province":"Cheshire",
    "sg:tags":[
        "club"
    ],
    "wof:name":"Manchester City Council",
    "wof:placetype":"venue"
},
  "geometry": {"coordinates":[-2.0225100517,53.4501914978],"type":"Point"}
}