{
  "type": "Feature",
  "properties": {
    "addr:full":"Walker Street, Middleton Manchester Greater Manchester M24 4QF",
    "addr:postcode":"m24 4qf",
    "addr:street":"Walker Street",
    "iso:country":"GB",
    "sg:address":"Walker Street, Middleton",
    "sg:city":"Manchester",
    "sg:classifiers":[
        {
            "category":"Health Services",
            "subcategory":"Nursing And Care Facility",
            "type":"Services"
        }
    ],
    "sg:phone":"+44 161 655 4223",
    "sg:postcode":"M24 4QF",
    "sg:province":"Greater Manchester",
    "sg:tags":[
        "home"
    ],
    "wof:name":"Little Heaton",
    "wof:placetype":"venue"
},
  "geometry": {"coordinates":[-2.2265241146,53.5439605713],"type":"Point"}
}