{
  "type": "Feature",
  "properties": {
    "addr:full":"Unit 7 Centre Court, Vine Lane Halesowen West Midlands B63 3EB",
    "addr:housenumber":"unit 7",
    "addr:postcode":"b63 3eb",
    "addr:street":"Centre Court Vine Lane",
    "iso:country":"GB",
    "sg:address":"Unit 7 Centre Court, Vine Lane",
    "sg:city":"Halesowen",
    "sg:classifiers":[
        {
            "category":"Professional",
            "subcategory":"Accounting & Tax Preparation",
            "type":"Services"
        }
    ],
    "sg:phone":"+44 121 550 2232",
    "sg:postcode":"B63 3EB",
    "sg:province":"West Midlands",
    "sg:tags":[
        "accountant"
    ],
    "wof:name":"Robert Pritchard & Co",
    "wof:placetype":"venue"
},
  "geometry": {"coordinates":[-2.0458590984,52.4483451843],"type":"Point"}
}