{
  "type": "Feature",
  "properties": {
    "addr:full":"479 Central Drive Blackpool Lancashire FY1 6LB",
    "addr:housenumber":"479",
    "addr:postcode":"fy1 6lb",
    "addr:street":"Central Drive",
    "iso:country":"GB",
    "sg:address":"479 Central Drive",
    "sg:city":"Blackpool",
    "sg:classifiers":[
        {
            "category":"Travel",
            "subcategory":"Hotels & Motels",
            "type":"Entertainment"
        }
    ],
    "sg:phone":"+44 1253 345870",
    "sg:postcode":"FY1 6LB",
    "sg:province":"Lancashire",
    "wof:name":"The Knightsbridge Hotel",
    "wof:placetype":"venue"
},
  "geometry": {"coordinates":[-3.043463,53.799576],"type":"Point"}
}