{
  "type": "Feature",
  "properties": {
    "addr:full":"6 Hazelwood Cottages, Knowle La Cranleigh Surrey GU6 8JP",
    "addr:housenumber":"6",
    "addr:postcode":"gu6 8jp",
    "addr:street":"Hazelwood Cottages",
    "iso:country":"GB",
    "sg:address":"6 Hazelwood Cottages, Knowle La",
    "sg:city":"Cranleigh",
    "sg:classifiers":[
        {
            "category":"Shopping",
            "subcategory":"Thrift Store",
            "type":"Retail Goods"
        }
    ],
    "sg:phone":"+44 1483 274855",
    "sg:postcode":"GU6 8JP",
    "sg:province":"Surrey",
    "sg:tags":[
        "shop",
        "charity"
    ],
    "wof:name":"Imperial Cancer Research Fund",
    "wof:placetype":"venue"
},
  "geometry": {"coordinates":[-0.482998997,51.1415405273],"type":"Point"}
}