{
  "type": "Feature",
  "properties": {
    "addr:full":"Pharmacy, Caldy Valley Rd Chester Cheshire CH3 5QJ",
    "addr:postcode":"ch3 5qj",
    "addr:street":"Caldy Valley Rd",
    "iso:country":"GB",
    "sg:address":"Pharmacy, Caldy Valley Rd",
    "sg:city":"Chester",
    "sg:classifiers":[
        {
            "category":"Shopping",
            "subcategory":"Pharmacy",
            "type":"Retail Goods"
        }
    ],
    "sg:phone":"+44 1244 348518",
    "sg:postcode":"CH3 5QJ",
    "sg:province":"Cheshire",
    "sg:tags":[
        "pharmacist",
        "chemist"
    ],
    "wof:name":"J Sainsbury PLC",
    "wof:placetype":"venue"
},
  "geometry": {"coordinates":[-2.8546190262,53.1877288818],"type":"Point"}
}