{
  "type": "Feature",
  "properties": {
    "addr:full":"Captia House, Broadford Business Park Guildford Surrey GU4 8EP",
    "addr:postcode":"gu4 8ep",
    "addr:street":"Broadford Business Park",
    "iso:country":"GB",
    "sg:address":"Captia House, Broadford Business Park",
    "sg:city":"Guildford",
    "sg:classifiers":[
        {
            "category":"Professional",
            "subcategory":"Computer Services",
            "type":"Services"
        }
    ],
    "sg:postcode":"GU4 8EP",
    "sg:province":"Surrey",
    "sg:tags":[
        "bureau",
        "facility"
    ],
    "wof:name":"C C C Network Systems Group Ltd.",
    "wof:placetype":"venue"
},
  "geometry": {"coordinates":[-0.572318,51.210953],"type":"Point"}
}