{
  "type": "Feature",
  "properties": {
    "addr:full":"Sumner Street Blackburn Lancashire BB2 2LD",
    "addr:postcode":"bb2 2ld",
    "addr:street":"Sumner Street",
    "iso:country":"GB",
    "sg:address":"Sumner Street",
    "sg:city":"Blackburn",
    "sg:classifiers":[
        {
            "category":"Professional",
            "subcategory":"Business Services",
            "type":"Services"
        },
        {
            "category":"Shopping",
            "type":"Retail Goods"
        }
    ],
    "sg:phone":"+44 1254 672155",
    "sg:postcode":"BB2 2LD",
    "sg:province":"Lancashire",
    "sg:tags":[
        "merchant",
        "agricultural"
    ],
    "wof:name":"J Berry",
    "wof:placetype":"venue"
},
  "geometry": {"coordinates":[-2.4879739285,53.7425956726],"type":"Point"}
}