{
  "type": "Feature",
  "properties": {
    "iso:country":"GB",
    "sg:address":"30 Falkland Road",
    "sg:city":"Sheffield",
    "sg:classifiers":[
        {
            "category":"Real Estate",
            "subcategory":"Architect",
            "type":"Services"
        }
    ],
    "sg:postcode":"S11 7PN",
    "sg:province":"Derbyshire",
    "wof:name":"Alick Mason Associates",
    "wof:placetype":"venue"
},
  "geometry": {"coordinates":[-1.514248,53.357891],"type":"Point"}
}