{
  "type": "Feature",
  "properties": {
    "addr:full":"48 Newbury Lane Oldbury West Midlands B69 1HF",
    "addr:housenumber":"48",
    "addr:postcode":"b69 1hf",
    "addr:street":"Newbury Lane",
    "iso:country":"GB",
    "sg:address":"48 Newbury Lane",
    "sg:city":"Oldbury",
    "sg:classifiers":[
        {
            "category":"Organizations",
            "subcategory":"Community Association",
            "type":"Services"
        },
        {
            "category":"Organizations",
            "subcategory":"Membership Organization",
            "type":"Services"
        }
    ],
    "sg:phone":"+44 121 552 4450",
    "sg:postcode":"B69 1HF",
    "sg:province":"West Midlands",
    "sg:tags":[
        "club",
        "social"
    ],
    "wof:name":"NEWBURY LANE SPORTS & SOCIAL CLUB",
    "wof:placetype":"venue"
},
  "geometry": {"coordinates":[-2.0294790268,52.4980392456],"type":"Point"}
}