{
  "type": "Feature",
  "properties": {
    "iso:country":"GB",
    "sg:address":"Unit 5, Lon Parcwr Indstl Est",
    "sg:city":"Ruthin",
    "sg:classifiers":[
        {
            "category":"Sports & Exercise",
            "subcategory":"Sports Center",
            "type":"Entertainment"
        }
    ],
    "sg:postcode":"LL15 1NJ",
    "sg:province":"Denbighshire",
    "sg:tags":[
        "shop",
        "good"
    ],
    "wof:name":"Outdoor Leisure Supplies Ltd",
    "wof:placetype":"venue"
},
  "geometry": {"coordinates":[-3.310729,53.119884],"type":"Point"}
}