{
  "type": "Feature",
  "properties": {
    "iso:country":"GB",
    "sg:address":"96 Ravenhead Road",
    "sg:city":"St Helens",
    "sg:classifiers":[
        {
            "category":"Sports & Exercise",
            "subcategory":"Race Track",
            "type":"Entertainment"
        }
    ],
    "sg:phone":"+44 1744 612361",
    "sg:postcode":"WA10 3LR",
    "sg:province":"Merseyside",
    "sg:tags":[
        "motor"
    ],
    "wof:name":"Magnum Motor Sport",
    "wof:placetype":"venue"
},
  "geometry": {"coordinates":[-2.7530140877,53.4426574707],"type":"Point"}
}