{
  "type": "Feature",
  "properties": {
    "addr:full":"47 Queensway Tiverton Devon EX16 6HX",
    "addr:housenumber":"47",
    "addr:postcode":"ex16 6hx",
    "addr:street":"Queensway",
    "iso:country":"GB",
    "sg:address":"47 Queensway",
    "sg:city":"Tiverton",
    "sg:classifiers":[
        {
            "category":"Travel",
            "subcategory":"Travel Agent",
            "type":"Entertainment"
        }
    ],
    "sg:phone":"+44 1884 259545",
    "sg:postcode":"EX16 6HX",
    "sg:province":"Devon",
    "wof:name":"Reach For The Sky",
    "wof:placetype":"venue"
},
  "geometry": {"coordinates":[-3.470999,50.910423],"type":"Point"}
}