{
  "type": "Feature",
  "properties": {
    "iso:country":"GB",
    "sg:address":"I Phoenix Court, Wakefield Road",
    "sg:city":"Brighouse",
    "sg:classifiers":[
        {
            "category":"Home & Garden",
            "subcategory":"Household Appliances",
            "type":"Retail Goods"
        }
    ],
    "sg:phone":"+44 1484 401953",
    "sg:postcode":"HD6 1PF",
    "sg:province":"West Yorkshire",
    "sg:tags":[
        "gas"
    ],
    "wof:name":"David Hart",
    "wof:placetype":"venue"
},
  "geometry": {"coordinates":[-1.774817,53.702133],"type":"Point"}
}