{
  "type": "Feature",
  "properties": {
    "addr:full":"10 Village Farm Rd, Village Farm Indust Est Bridgend Bridgend CF33 6BL",
    "addr:housenumber":"10",
    "addr:postcode":"cf33 6bl",
    "addr:street":"Village Farm Rd;Indust",
    "iso:country":"GB",
    "sg:address":"10 Village Farm Rd, Village Farm Indust Est",
    "sg:city":"Bridgend",
    "sg:classifiers":[
        {
            "category":"Organizations",
            "subcategory":"Non-profit Organization",
            "type":"Services"
        }
    ],
    "sg:phone":"+44 1656 743781",
    "sg:postcode":"CF33 6BL",
    "sg:province":"Bridgend",
    "sg:tags":[
        "organisation",
        "voluntary",
        "charity"
    ],
    "wof:name":"St Vincent De Paul Society",
    "wof:placetype":"venue"
},
  "geometry": {"coordinates":[-3.6749680042,51.5242195129],"type":"Point"}
}