{
  "type": "Feature",
  "properties": {
    "addr:full":"56 New Street Ashford Kent TN24 8TT",
    "addr:housenumber":"56",
    "addr:postcode":"tn24 8tt",
    "addr:street":"New Street",
    "iso:country":"GB",
    "sg:address":"56 New Street",
    "sg:city":"Ashford",
    "sg:classifiers":[
        {
            "category":"Bars & Pubs",
            "type":"Food & Drink"
        }
    ],
    "sg:phone":"+44 1233 629932",
    "sg:postcode":"TN24 8TT",
    "sg:province":"Kent",
    "sg:tags":[
        "pubs",
        "inn"
    ],
    "wof:name":"The British Volunteers",
    "wof:placetype":"venue"
},
  "geometry": {"coordinates":[0.8681,51.150959],"type":"Point"}
}