{
  "type": "Feature",
  "properties": {
    "iso:country":"GB",
    "sg:address":"Ramsgate Road",
    "sg:city":"Margate",
    "sg:classifiers":[
        {
            "category":"Bars & Pubs",
            "type":"Food & Drink"
        }
    ],
    "sg:phone":"+44 1843 220663",
    "sg:postcode":"CT9 4EU",
    "sg:province":"Kent",
    "sg:tags":[
        "pubs",
        "inn"
    ],
    "wof:name":"The Orb Inn",
    "wof:placetype":"venue"
},
  "geometry": {"coordinates":[1.383768,51.378002],"type":"Point"}
}