{
  "type": "Feature",
  "properties": {
    "iso:country":"GB",
    "sg:address":"39-41 Town Street, Marple Bridge",
    "sg:city":"Stockport",
    "sg:classifiers":[
        {
            "category":"Personal",
            "subcategory":"Beauty Salon",
            "type":"Services"
        },
        {
            "category":"Personal",
            "subcategory":"Barber",
            "type":"Services"
        }
    ],
    "sg:phone":"+44 161 426 0106",
    "sg:postcode":"SK6 5AA",
    "sg:province":"Cheshire",
    "sg:tags":[
        "unisex",
        "hairdresser"
    ],
    "wof:name":"Sherlocks",
    "wof:placetype":"venue"
},
  "geometry": {"coordinates":[-2.053729,53.400291],"type":"Point"}
}