{
  "type": "Feature",
  "properties": {
    "addr:full":"Unit J Marsdens Building, Mailin Road, Mailin Bridge Sheffield South Yorkshire S6 5FG",
    "addr:postcode":"s6 5fg",
    "addr:street":"Mailin Road Mailin Bridge",
    "iso:country":"GB",
    "sg:address":"Unit J Marsdens Building, Mailin Road, Mailin Bridge",
    "sg:city":"Sheffield",
    "sg:classifiers":[
        {
            "category":"Retail",
            "subcategory":"Auto Repair",
            "type":"Services"
        }
    ],
    "sg:postcode":"S6 5FG",
    "sg:province":"South Yorkshire",
    "sg:tags":[
        "modification",
        "garage"
    ],
    "wof:name":"S G Motors",
    "wof:placetype":"venue"
},
  "geometry": {"coordinates":[-1.51429,53.39867],"type":"Point"}
}