{
  "type": "Feature",
  "properties": {
    "addr:full":"The Forge, Norton Heath Ingatestone Essex CM4 0LJ",
    "addr:postcode":"cm4 0lj",
    "addr:street":"Norton Heath",
    "iso:country":"GB",
    "sg:address":"The Forge, Norton Heath",
    "sg:city":"Ingatestone",
    "sg:classifiers":[
        {
            "category":"Building & Trades",
            "subcategory":"Equipment Rental",
            "type":"Services"
        }
    ],
    "sg:phone":"+44 1277 821631",
    "sg:postcode":"CM4 0LJ",
    "sg:province":"Essex",
    "sg:tags":[
        "plant",
        "machinery"
    ],
    "wof:name":"J Matthews Plant Hire Ltd.",
    "wof:placetype":"venue"
},
  "geometry": {"coordinates":[0.383585,51.669922],"type":"Point"}
}