{
  "type": "Feature",
  "properties": {
    "addr:full":"Leisure House, Poplar Tree Lane, Road Common, Southwick Trowbridge Wiltshire BA14 9NB",
    "addr:postcode":"ba14 9nb",
    "addr:street":"Poplar Tree Lane Road Common Southwick",
    "iso:country":"GB",
    "sg:address":"Leisure House, Poplar Tree Lane, Road Common, Southwick",
    "sg:city":"Trowbridge",
    "sg:classifiers":[
        {
            "category":"Autos & Motor Vehicles",
            "subcategory":"Automobile Sales",
            "type":"Retail Goods"
        }
    ],
    "sg:phone":"+44 1373 831200",
    "sg:postcode":"BA14 9NB",
    "sg:province":"Wiltshire",
    "sg:tags":[
        "commercial"
    ],
    "wof:name":"Land Leisure UK",
    "wof:placetype":"venue"
},
  "geometry": {"coordinates":[-2.256912,51.291145],"type":"Point"}
}