{
  "type": "Feature",
  "properties": {
    "iso:country":"GB",
    "sg:address":"34a & B Kensington Church Street",
    "sg:city":"London",
    "sg:classifiers":[
        {
            "category":"Home & Garden",
            "subcategory":"Hardware",
            "type":"Retail Goods"
        }
    ],
    "sg:phone":"+44 20 7937 5033",
    "sg:postcode":"W8 4HA",
    "sg:province":"Greater London",
    "sg:tags":[
        "retailer",
        "lighting"
    ],
    "wof:name":"Ann's",
    "wof:placetype":"venue"
},
  "geometry": {"coordinates":[-0.19181,51.503941],"type":"Point"}
}