{
  "type": "Feature",
  "properties": {
    "addr:full":"1 Crown Bank Sandbach Cheshire CW11 0EW",
    "addr:housenumber":"1",
    "addr:postcode":"cw11 0ew",
    "addr:street":"Crown Bank",
    "iso:country":"GB",
    "sg:address":"1 Crown Bank",
    "sg:city":"Sandbach",
    "sg:classifiers":[
        {
            "category":"Building & Trades",
            "subcategory":"Construction",
            "type":"Services"
        }
    ],
    "sg:phone":"+44 1270 766799",
    "sg:postcode":"CW11 0EW",
    "sg:province":"Cheshire",
    "sg:tags":[
        "builder"
    ],
    "wof:name":"Beazer Partnerships Homes",
    "wof:placetype":"venue"
},
  "geometry": {"coordinates":[-2.3612349033,53.1441307068],"type":"Point"}
}