{
  "type": "Feature",
  "properties": {
    "addr:full":"4 Castle, New Cumnock Cumnock East Ayrshire KA18 4AH",
    "addr:housenumber":"4",
    "addr:postcode":"ka18 4ah",
    "addr:street":"Castle New;Cumnock East",
    "iso:country":"GB",
    "sg:address":"4 Castle, New Cumnock",
    "sg:city":"Cumnock",
    "sg:classifiers":[
        {
            "category":"Education",
            "subcategory":"School",
            "type":"Public Place"
        },
        {
            "category":"Government",
            "subcategory":"Office",
            "type":"Public Place"
        }
    ],
    "sg:phone":"+44 1290 338423",
    "sg:postcode":"KA18 4AH",
    "sg:province":"East Ayrshire",
    "sg:tags":[
        "local",
        "authority"
    ],
    "wof:name":"Castle Primary School",
    "wof:placetype":"venue"
},
  "geometry": {"coordinates":[-4.1845731735,55.3946647644],"type":"Point"}
}