{
  "type": "Feature",
  "properties": {
    "addr:full":"316-318 Petre Street Sheffield South Yorkshire S4 8LU",
    "addr:postcode":"316-318;s4 8lu",
    "addr:street":"Petre Street",
    "iso:country":"GB",
    "sg:address":"316-318 Petre Street",
    "sg:city":"Sheffield",
    "sg:classifiers":[
        {
            "category":"Building & Trades",
            "subcategory":"Plumbing",
            "type":"Services"
        },
        {
            "category":"Retail",
            "subcategory":"Storage",
            "type":"Services"
        }
    ],
    "sg:phone":"+44 114 261 1183",
    "sg:postcode":"S4 8LU",
    "sg:province":"South Yorkshire",
    "sg:tags":[
        "household",
        "industrial",
        "business",
        "removal"
    ],
    "wof:name":"Specialised Movers",
    "wof:placetype":"venue"
},
  "geometry": {"coordinates":[-1.4417970181,53.40366745],"type":"Point"}
}