{
  "type": "Feature",
  "properties": {
    "iso:country":"GB",
    "sg:address":"36 Wide Bargate",
    "sg:city":"Boston",
    "sg:classifiers":[
        {
            "category":"Shopping",
            "subcategory":"Department Store",
            "type":"Retail Goods"
        }
    ],
    "sg:phone":"+44 1205 311355",
    "sg:postcode":"PE21 6RX",
    "sg:province":"Lincolnshire",
    "wof:name":"Coney's (Tailors) Ltd.",
    "wof:placetype":"venue"
},
  "geometry": {"coordinates":[-0.020861,52.980602],"type":"Point"}
}