{
  "type": "Feature",
  "properties": {
    "iso:country":"GB",
    "sg:address":"17 West End Road",
    "sg:city":"Morecambe",
    "sg:classifiers":[
        {
            "category":"Social Services",
            "subcategory":"Retirement Home",
            "type":"Services"
        },
        {
            "category":"Government",
            "subcategory":"Office",
            "type":"Public Place"
        }
    ],
    "sg:phone":"+44 1524 418420",
    "sg:postcode":"LA4 4DJ",
    "sg:province":"Lancashire",
    "sg:tags":[
        "residential",
        "central",
        "care"
    ],
    "wof:name":"Holywell Home for the Mentally Handicapped",
    "wof:placetype":"venue"
},
  "geometry": {"coordinates":[-2.8777160645,54.0671920776],"type":"Point"}
}