{
  "type": "Feature",
  "properties": {
    "iso:country":"GB",
    "sg:address":"121 Lee Road",
    "sg:city":"London",
    "sg:classifiers":[
        {
            "category":"Food & Beverages",
            "subcategory":"Meat & Fish",
            "type":"Retail Goods"
        }
    ],
    "sg:phone":"+44 20 8318 2116",
    "sg:postcode":"SE3 9DS",
    "sg:province":"Greater London",
    "sg:tags":[
        "seafood"
    ],
    "wof:name":"Villa Moura",
    "wof:placetype":"venue"
},
  "geometry": {"coordinates":[0.010917,51.457863],"type":"Point"}
}