{
  "type": "Feature",
  "properties": {
    "addr:full":"83 Westlaw Place Glenrothes Fife KY6 2RZ",
    "addr:housenumber":"83",
    "addr:postcode":"ky6 2rz",
    "addr:street":"Westlaw Place",
    "iso:country":"GB",
    "sg:address":"83 Westlaw Place",
    "sg:city":"Glenrothes",
    "sg:classifiers":[
        {
            "category":"Shopping",
            "subcategory":"Catalog Store",
            "type":"Retail Goods"
        }
    ],
    "sg:phone":"+44 1592 772827",
    "sg:postcode":"KY6 2RZ",
    "sg:province":"Fife",
    "sg:tags":[
        "mail",
        "order"
    ],
    "wof:name":"Morses",
    "wof:placetype":"venue"
},
  "geometry": {"coordinates":[-3.202153,56.181911],"type":"Point"}
}