{
  "type": "Feature",
  "properties": {
    "addr:full":"Bellamour Way, Colton Rugeley Staffordshire WS15 3LN",
    "addr:postcode":"ws15 3ln",
    "addr:street":"Bellamour Way",
    "iso:country":"GB",
    "sg:address":"Bellamour Way, Colton",
    "sg:city":"Rugeley",
    "sg:classifiers":[
        {
            "category":"Bars & Pubs",
            "type":"Food & Drink"
        }
    ],
    "sg:phone":"+44 1889 586769",
    "sg:postcode":"WS15 3LN",
    "sg:province":"Staffordshire",
    "sg:tags":[
        "pubs",
        "inn"
    ],
    "wof:name":"Avebury Inns Ltd.",
    "wof:placetype":"venue"
},
  "geometry": {"coordinates":[-1.937324,52.78326],"type":"Point"}
}