{
  "type": "Feature",
  "properties": {
    "iso:country":"GB",
    "sg:address":"Betts Hall Bath St",
    "sg:city":"Rugby",
    "sg:classifiers":[
        {
            "category":"Shopping",
            "subcategory":"Thrift Store",
            "type":"Retail Goods"
        }
    ],
    "sg:postcode":"CV21 3JD",
    "sg:province":"Warwickshire",
    "sg:tags":[
        "shop",
        "charity"
    ],
    "wof:name":"Racks Charity Shop",
    "wof:placetype":"venue"
},
  "geometry": {"coordinates":[-1.2538700104,52.3752403259],"type":"Point"}
}