{
  "type": "Feature",
  "properties": {
    "addr:full":"Main Road, Stretton Chesterfield Derbyshire DE55 6EW",
    "addr:postcode":"de55 6ew",
    "addr:street":"Main Road",
    "iso:country":"GB",
    "sg:address":"Main Road, Stretton",
    "sg:city":"Chesterfield",
    "sg:classifiers":[
        {
            "category":"Autos & Motor Vehicles",
            "subcategory":"Automobile Sales",
            "type":"Retail Goods"
        }
    ],
    "sg:phone":"+44 1246 862891",
    "sg:postcode":"DE55 6EW",
    "sg:province":"Derbyshire",
    "sg:tags":[
        "car",
        "used"
    ],
    "wof:name":"Highfield Garage",
    "wof:placetype":"venue"
},
  "geometry": {"coordinates":[-1.4144550562,53.1462211609],"type":"Point"}
}