{
  "type": "Feature",
  "properties": {
    "addr:full":"The Barns, Clare Hall Sudbury Essex CO10 8PJ",
    "addr:postcode":"co10 8pj",
    "addr:street":"Sudbury",
    "iso:country":"GB",
    "sg:address":"The Barns, Clare Hall",
    "sg:city":"Sudbury",
    "sg:classifiers":[
        {
            "category":"Professional",
            "type":"Services"
        }
    ],
    "sg:phone":"+44 1787 278808",
    "sg:postcode":"CO10 8PJ",
    "sg:province":"Essex",
    "sg:tags":[
        "interior",
        "furnishers",
        "designer"
    ],
    "wof:name":"Country House Interiors",
    "wof:placetype":"venue"
},
  "geometry": {"coordinates":[0.581251,52.080494],"type":"Point"}
}