{
  "type": "Feature",
  "properties": {
    "iso:country":"GB",
    "sg:address":"2 Tresham Rd",
    "sg:city":"Peterborough",
    "sg:classifiers":[
        {
            "category":"Manufacturing",
            "subcategory":"Toys & Sporting Goods",
            "type":"Manufacturing & Wholesale Goods"
        },
        {
            "category":"Shopping",
            "subcategory":"Hobbies, Toys, & Games",
            "type":"Retail Goods"
        }
    ],
    "sg:phone":"+44 1733 371170",
    "sg:postcode":"PE2 6SG",
    "sg:province":"Cambridgeshire",
    "sg:tags":[
        "product",
        "games",
        "manufacturer"
    ],
    "wof:name":"Robin House",
    "wof:placetype":"venue"
},
  "geometry": {"coordinates":[-0.309086,52.543545],"type":"Point"}
}