{
  "type": "Feature",
  "properties": {
    "iso:country":"GB",
    "sg:address":"Woodlands Rd",
    "sg:city":"Gillingham",
    "sg:classifiers":[
        {
            "category":"Sports & Exercise",
            "subcategory":"Golf",
            "type":"Entertainment"
        }
    ],
    "sg:phone":"+44 1634 855862",
    "sg:postcode":"ME7 2BX",
    "sg:province":"Kent",
    "sg:tags":[
        "equipment"
    ],
    "wof:name":"The Professionals Shop",
    "wof:placetype":"venue"
},
  "geometry": {"coordinates":[0.568997,51.3853],"type":"Point"}
}