{
  "type": "Feature",
  "properties": {
    "addr:full":"3 Wykeham Way, Haddenham Aylesbury Buckinghamshire HP17 8BL",
    "addr:housenumber":"3",
    "addr:postcode":"hp17 8bl",
    "addr:street":"Wykeham Way",
    "iso:country":"GB",
    "sg:address":"3 Wykeham Way, Haddenham",
    "sg:city":"Aylesbury",
    "sg:classifiers":[
        {
            "category":"Building & Trades",
            "subcategory":"Construction",
            "type":"Services"
        }
    ],
    "sg:phone":"+44 1844 290855",
    "sg:postcode":"HP17 8BL",
    "sg:province":"Buckinghamshire",
    "sg:tags":[
        "joinery",
        "joiner",
        "carpenter",
        "carpentry"
    ],
    "wof:name":"Ray Waller",
    "wof:placetype":"venue"
},
  "geometry": {"coordinates":[-0.9353740215,51.7711906433],"type":"Point"}
}