{
  "type": "Feature",
  "properties": {
    "addr:full":"Lower Cockhill Barn, Hothersall Lane Preston Lancashire PR3 2XB",
    "addr:postcode":"pr3 2xb",
    "addr:street":"Hothersall Lane",
    "iso:country":"GB",
    "sg:address":"Lower Cockhill Barn, Hothersall Lane",
    "sg:city":"Preston",
    "sg:classifiers":[
        {
            "category":"Building & Trades",
            "subcategory":"Construction",
            "type":"Services"
        }
    ],
    "sg:phone":"+44 1772 783121",
    "sg:postcode":"PR3 2XB",
    "sg:province":"Lancashire",
    "sg:tags":[
        "builder"
    ],
    "wof:name":"J G Dewhurst Building Conctractors",
    "wof:placetype":"venue"
},
  "geometry": {"coordinates":[-2.5753700733,53.8177185059],"type":"Point"}
}