{
  "type": "Feature",
  "properties": {
    "addr:full":"Monkton Avenue Weston-super-mare Somerset BS24 9DA",
    "addr:postcode":"bs24 9da",
    "addr:street":"Monkton Avenue",
    "iso:country":"GB",
    "sg:address":"Monkton Avenue",
    "sg:city":"Weston-super-mare",
    "sg:classifiers":[
        {
            "category":"Shopping",
            "subcategory":"Pharmacy",
            "type":"Retail Goods"
        }
    ],
    "sg:phone":"+44 1934 813720",
    "sg:postcode":"BS24 9DA",
    "sg:province":"Somerset",
    "sg:tags":[
        "pharmacist",
        "chemist"
    ],
    "wof:name":"Broadway Pharmacy",
    "wof:placetype":"venue"
},
  "geometry": {"coordinates":[-2.9562289715,51.3238716125],"type":"Point"}
}