{
  "type": "Feature",
  "properties": {
    "iso:country":"GB",
    "sg:address":"14 Coniston Road, Redbridge",
    "sg:city":"Southampton",
    "sg:classifiers":[
        {
            "category":"Building & Trades",
            "subcategory":"Construction",
            "type":"Services"
        }
    ],
    "sg:phone":"+44 23 8086 5550",
    "sg:postcode":"SO16 9BT",
    "sg:province":"Hampshire",
    "sg:tags":[
        "roofing",
        "contracting"
    ],
    "wof:name":"David Osman General Builder",
    "wof:placetype":"venue"
},
  "geometry": {"coordinates":[-1.4710780382,50.9237976074],"type":"Point"}
}