{
  "type": "Feature",
  "properties": {
    "addr:full":"602a Bromford Lane, Washwood Heath Birmingham West Midlands B8 2EN",
    "addr:housenumber":"602a",
    "addr:postcode":"b8 2en",
    "addr:street":"Bromford Lane",
    "iso:country":"GB",
    "sg:address":"602a Bromford Lane, Washwood Heath",
    "sg:city":"Birmingham",
    "sg:classifiers":[
        {
            "category":"Autos & Motor Vehicles",
            "subcategory":"Fuel & Gas Station",
            "type":"Retail Goods"
        }
    ],
    "sg:postcode":"B8 2EN",
    "sg:province":"West Midlands",
    "sg:tags":[
        "petrol",
        "filling"
    ],
    "wof:name":"Bromford Lane Service Centre",
    "wof:placetype":"venue"
},
  "geometry": {"coordinates":[-1.819167,52.495018],"type":"Point"}
}