{
  "type": "Feature",
  "properties": {
    "iso:country":"GB",
    "sg:address":"20 Kelmscott Rd",
    "sg:city":"Birmingham",
    "sg:classifiers":[
        {
            "category":"Health Services",
            "subcategory":"Doctor",
            "type":"Services"
        }
    ],
    "sg:phone":"+44 121 426 2354",
    "sg:postcode":"B17 8QN",
    "sg:province":"West Midlands",
    "sg:tags":[
        "practitioners"
    ],
    "wof:name":"Cooke, H B J",
    "wof:placetype":"venue"
},
  "geometry": {"coordinates":[-1.964819,52.467075],"type":"Point"}
}