{
  "type": "Feature",
  "properties": {
    "iso:country":"GB",
    "sg:address":"The Friary",
    "sg:city":"Lichfield",
    "sg:classifiers":[
        {
            "category":"Retail",
            "subcategory":"Storage",
            "type":"Services"
        }
    ],
    "sg:postcode":"WS13 6QE",
    "sg:province":"Staffordshire",
    "sg:tags":[
        "household",
        "removal"
    ],
    "wof:name":"Admiral Removals & Storage",
    "wof:placetype":"venue"
},
  "geometry": {"coordinates":[-1.831813,52.680695],"type":"Point"}
}