{
  "type": "Feature",
  "properties": {
    "addr:full":"York Bungalow, Lt Wakering Hall Lane, Great Wakering Southend-on-sea Essex SS3 0HG",
    "addr:postcode":"ss3 0hg",
    "addr:street":"Lt;Hall Lane",
    "iso:country":"GB",
    "sg:address":"York Bungalow, Lt Wakering Hall Lane, Great Wakering",
    "sg:city":"Southend-on-sea",
    "sg:classifiers":[
        {
            "category":"Freight",
            "type":"Transportation"
        }
    ],
    "sg:phone":"+44 1702 219497",
    "sg:postcode":"SS3 0HG",
    "sg:province":"Essex",
    "sg:tags":[
        "haulage",
        "road"
    ],
    "wof:name":"E & K Ellis Ltd.",
    "wof:placetype":"venue"
},
  "geometry": {"coordinates":[0.799885,51.553196],"type":"Point"}
}