{
  "type": "Feature",
  "properties": {
    "iso:country":"GB",
    "sg:address":"East Community Centre, Moor Terrace",
    "sg:city":"Sunderland",
    "sg:classifiers":[
        {
            "category":"Organizations",
            "subcategory":"Non-profit Organization",
            "type":"Services"
        }
    ],
    "sg:phone":"+44 191 565 5648",
    "sg:postcode":"SR1 2JH",
    "sg:province":"Tyne and Wear",
    "sg:tags":[
        "organisation",
        "voluntary",
        "charity"
    ],
    "wof:name":"Old Peoples Project",
    "wof:placetype":"venue"
},
  "geometry": {"coordinates":[-1.3862899542,54.9022903442],"type":"Point"}
}