{
  "type": "Feature",
  "properties": {
    "iso:country":"GB",
    "sg:address":"40 St. Matthews St",
    "sg:city":"Ipswich",
    "sg:classifiers":[
        {
            "category":"Shopping",
            "subcategory":"Thrift Store",
            "type":"Retail Goods"
        }
    ],
    "sg:phone":"+44 1473 225473",
    "sg:postcode":"IP1 3EP",
    "sg:province":"Suffolk",
    "sg:tags":[
        "shop",
        "charity"
    ],
    "wof:name":"SCOPE Charity Shops",
    "wof:placetype":"venue"
},
  "geometry": {"coordinates":[1.1477470398,52.0599784851],"type":"Point"}
}