{
  "type": "Feature",
  "properties": {
    "iso:country":"GB",
    "sg:address":"The Larches, Canal Hill",
    "sg:city":"Tiverton",
    "sg:classifiers":[
        {
            "category":"Social Services",
            "subcategory":"Adult Care",
            "type":"Services"
        },
        {
            "category":"Social Services",
            "subcategory":"Retirement Home",
            "type":"Services"
        }
    ],
    "sg:phone":"+44 1884 258701",
    "sg:postcode":"EX16 4JD",
    "sg:province":"Devon",
    "sg:tags":[
        "provider"
    ],
    "wof:name":"Community Careline Services",
    "wof:placetype":"venue"
},
  "geometry": {"coordinates":[-3.478969,50.902901],"type":"Point"}
}