{
  "type": "Feature",
  "properties": {
    "addr:full":"P O Box 2795 London Greater London NW10 9AY",
    "addr:housenumber":"p o;2795",
    "addr:postcode":"nw10 9ay",
    "iso:country":"GB",
    "sg:address":"P O Box 2795",
    "sg:city":"London",
    "sg:classifiers":[
        {
            "category":"Professional",
            "type":"Services"
        }
    ],
    "sg:postcode":"NW10 9AY",
    "sg:province":"Greater London",
    "sg:tags":[
        "entertainer"
    ],
    "wof:name":"Carroll,Mick,",
    "wof:placetype":"venue"
},
  "geometry": {"coordinates":[-0.2499600053,51.5444908142],"type":"Point"}
}