{
  "type": "Feature",
  "properties": {
    "iso:country":"GB",
    "sg:address":"Room 217 The Town Hall, Chapel Road",
    "sg:city":"Worthing",
    "sg:classifiers":[
        {
            "category":"Organizations",
            "subcategory":"Non-profit Organization",
            "type":"Services"
        }
    ],
    "sg:phone":"+44 1903 210959",
    "sg:postcode":"BN11 1HA",
    "sg:province":"West Sussex",
    "sg:tags":[
        "organisation",
        "voluntary",
        "charity"
    ],
    "wof:name":"The Worthing & District Victim Support Scheme",
    "wof:placetype":"venue"
},
  "geometry": {"coordinates":[-0.3754239976,50.8136253357],"type":"Point"}
}