{
  "type": "Feature",
  "properties": {
    "addr:full":"5-9 Chancery Walk Burnley Lancashire BB11 1PZ",
    "addr:housenumber":"5-9",
    "addr:postcode":"bb11 1pz",
    "addr:street":"Chancery Walk",
    "iso:country":"GB",
    "sg:address":"5-9 Chancery Walk",
    "sg:city":"Burnley",
    "sg:classifiers":[
        {
            "category":"Travel",
            "subcategory":"Travel Agent",
            "type":"Entertainment"
        }
    ],
    "sg:phone":"+44 1282 453711",
    "sg:postcode":"BB11 1PZ",
    "sg:province":"Lancashire",
    "wof:name":"Going Places Leisure Travel",
    "wof:placetype":"venue"
},
  "geometry": {"coordinates":[-2.2438089848,53.7880096436],"type":"Point"}
}