{
  "type": "Feature",
  "properties": {
    "addr:full":"223 High St Glasgow Glasgow City G1 1PP",
    "addr:housenumber":"223",
    "addr:postcode":"g1 1pp",
    "addr:street":"High St",
    "iso:country":"GB",
    "sg:address":"223 High St",
    "sg:city":"Glasgow",
    "sg:classifiers":[
        {
            "category":"Cafe",
            "type":"Food & Drink"
        }
    ],
    "sg:phone":"+44 141 552 9177",
    "sg:postcode":"G1 1PP",
    "sg:province":"Glasgow City",
    "sg:tags":[
        "tea",
        "room"
    ],
    "wof:name":"The High Street Cross Cafes",
    "wof:placetype":"venue"
},
  "geometry": {"coordinates":[-4.2402420044,55.8602256775],"type":"Point"}
}