{
  "type": "Feature",
  "properties": {
    "iso:country":"GB",
    "sg:address":"155 Kilburn High Road",
    "sg:city":"London",
    "sg:classifiers":[
        {
            "category":"Bars & Pubs",
            "type":"Food & Drink"
        }
    ],
    "sg:phone":"+44 20 7644 9961",
    "sg:postcode":"NW6 7HU",
    "sg:province":"Greater London",
    "sg:tags":[
        "pubs",
        "inn"
    ],
    "wof:name":"Goose & Granite",
    "wof:placetype":"venue"
},
  "geometry": {"coordinates":[-0.196149,51.54018],"type":"Point"}
}