{
  "type": "Feature",
  "properties": {
    "iso:country":"GB",
    "sg:address":"Fulhams, Kyre",
    "sg:city":"Tenbury Wells",
    "sg:classifiers":[
        {
            "category":"Social Services",
            "subcategory":"Retirement Home",
            "type":"Services"
        }
    ],
    "sg:postcode":"WR15 8RN",
    "sg:province":"Herefordshire",
    "sg:tags":[
        "residential",
        "care"
    ],
    "wof:name":"The Fulhams Residential Home",
    "wof:placetype":"venue"
},
  "geometry": {"coordinates":[-2.594179,52.312584],"type":"Point"}
}