{
  "type": "Feature",
  "properties": {
    "iso:country":"GB",
    "sg:address":"2 Smiths Yard, Great Staughton",
    "sg:city":"Huntingdon",
    "sg:classifiers":[
        {
            "category":"Professional",
            "subcategory":"Advertising",
            "type":"Services"
        }
    ],
    "sg:phone":"+44 1480 860112",
    "sg:postcode":"PE19 4DE",
    "sg:province":"Bedfordshire",
    "sg:tags":[
        "mail",
        "direct"
    ],
    "wof:name":"Mailing Solutions",
    "wof:placetype":"venue"
},
  "geometry": {"coordinates":[-0.34338,52.268021],"type":"Point"}
}