{
  "type": "Feature",
  "properties": {
    "addr:full":"Waters Green Garage, Waters Grn Macclesfield Cheshire SK11 6JX",
    "addr:postcode":"sk11 6jx",
    "addr:street":"Waters;Grn",
    "iso:country":"GB",
    "sg:address":"Waters Green Garage, Waters Grn",
    "sg:city":"Macclesfield",
    "sg:classifiers":[
        {
            "category":"Retail",
            "subcategory":"Auto Repair",
            "type":"Services"
        }
    ],
    "sg:postcode":"SK11 6JX",
    "sg:province":"Cheshire",
    "sg:tags":[
        "modification",
        "garage"
    ],
    "wof:name":"Sovereign Motors",
    "wof:placetype":"venue"
},
  "geometry": {"coordinates":[-2.1230809689,53.259979248],"type":"Point"}
}