{
  "type": "Feature",
  "properties": {
    "addr:full":"17 Beech Street Harrogate North Yorkshire HG2 7PL",
    "addr:housenumber":"17",
    "addr:postcode":"hg2 7pl",
    "addr:street":"Beech Street",
    "iso:country":"GB",
    "sg:address":"17 Beech Street",
    "sg:city":"Harrogate",
    "sg:classifiers":[
        {
            "category":"Building & Trades",
            "subcategory":"Construction",
            "type":"Services"
        }
    ],
    "sg:postcode":"HG2 7PL",
    "sg:province":"North Yorkshire",
    "sg:tags":[
        "roofing"
    ],
    "wof:name":"I & P Henderson",
    "wof:placetype":"venue"
},
  "geometry": {"coordinates":[-1.5020200014,53.9968795776],"type":"Point"}
}