{
  "type": "Feature",
  "properties": {
    "iso:country":"GB",
    "sg:address":"349 Promenade",
    "sg:city":"Blackpool",
    "sg:classifiers":[
        {
            "category":"Travel",
            "subcategory":"Hotels & Motels",
            "type":"Entertainment"
        },
        {
            "category":"Coffee & Tea",
            "type":"Food & Drink"
        }
    ],
    "sg:phone":"+44 1253 346114",
    "sg:postcode":"FY1 6BJ",
    "sg:province":"Lancashire",
    "sg:tags":[
        "merchant"
    ],
    "wof:name":"The Brookfield Hotel",
    "wof:placetype":"venue"
},
  "geometry": {"coordinates":[-3.055277,53.801781],"type":"Point"}
}