{
  "type": "Feature",
  "properties": {
    "addr:full":"38 Victoria Rd Scarborough North Yorkshire YO11 1SD",
    "addr:housenumber":"38",
    "addr:postcode":"yo11 1sd",
    "addr:street":"Victoria Rd",
    "iso:country":"GB",
    "sg:address":"38 Victoria Rd",
    "sg:city":"Scarborough",
    "sg:classifiers":[
        {
            "category":"Shopping",
            "subcategory":"Bicycles & Sporting Goods",
            "type":"Retail Goods"
        }
    ],
    "sg:phone":"+44 1723 368777",
    "sg:postcode":"YO11 1SD",
    "sg:province":"North Yorkshire",
    "sg:tags":[
        "equipment",
        "camping"
    ],
    "wof:name":"Leisureways",
    "wof:placetype":"venue"
},
  "geometry": {"coordinates":[-0.408959,54.278439],"type":"Point"}
}