{
  "type": "Feature",
  "properties": {
    "addr:full":"7a Kings Road Southsea Hampshire PO5 4DJ",
    "addr:housenumber":"7a",
    "addr:postcode":"po5 4dj",
    "addr:street":"Kings Road",
    "iso:country":"GB",
    "sg:address":"7a Kings Road",
    "sg:city":"Southsea",
    "sg:classifiers":[
        {
            "category":"Professional",
            "subcategory":"Employment Agencies",
            "type":"Services"
        }
    ],
    "sg:phone":"+44 23 9287 6600",
    "sg:postcode":"PO5 4DJ",
    "sg:province":"Hampshire",
    "sg:tags":[
        "consultant"
    ],
    "wof:name":"Job Zone Ltd.",
    "wof:placetype":"venue"
},
  "geometry": {"coordinates":[-1.094678998,50.7912483215],"type":"Point"}
}