{
  "type": "Feature",
  "properties": {
    "addr:full":"15 Whitland Rd Carshalton Surrey SM5 1QX",
    "addr:housenumber":"15",
    "addr:postcode":"sm5 1qx",
    "addr:street":"Whitland Rd",
    "iso:country":"GB",
    "sg:address":"15 Whitland Rd",
    "sg:city":"Carshalton",
    "sg:classifiers":[
        {
            "category":"Building & Trades",
            "subcategory":"Pest Control",
            "type":"Services"
        }
    ],
    "sg:phone":"+44 20 8644 8640",
    "sg:postcode":"SM5 1QX",
    "sg:province":"Surrey",
    "sg:tags":[
        "vermin"
    ],
    "wof:name":"AA Surrey Pest Control",
    "wof:placetype":"venue"
},
  "geometry": {"coordinates":[-0.177835,51.379192],"type":"Point"}
}