{
  "type": "Feature",
  "properties": {
    "addr:full":"77 Bounces Road London Greater London N9 8LD",
    "addr:housenumber":"77",
    "addr:postcode":"n9 8ld",
    "addr:street":"Bounces Road",
    "iso:country":"GB",
    "sg:address":"77 Bounces Road",
    "sg:city":"London",
    "sg:classifiers":[
        {
            "category":"Restaurant",
            "type":"Food & Drink"
        }
    ],
    "sg:postcode":"N9 8LD",
    "sg:province":"Greater London",
    "wof:name":"Olympic Flame",
    "wof:placetype":"venue"
},
  "geometry": {"coordinates":[-0.051827,51.628349],"type":"Point"}
}