{
  "type": "Feature",
  "properties": {
    "iso:country":"GB",
    "sg:address":"Greystones, Sandy Lane",
    "sg:city":"York",
    "sg:classifiers":[
        {
            "category":"Building & Trades",
            "subcategory":"Landscaping Services",
            "type":"Services"
        },
        {
            "category":"Utilities",
            "subcategory":"Fuel Oil & Lpg",
            "type":"Services"
        }
    ],
    "sg:postcode":"YO32 9UT",
    "sg:province":"North Yorkshire",
    "sg:tags":[
        "pond",
        "coal",
        "smokeless",
        "aquarium"
    ],
    "wof:name":"John Drury & Son",
    "wof:placetype":"venue"
},
  "geometry": {"coordinates":[-0.9884899855,54.0034103394],"type":"Point"}
}