{
  "type": "Feature",
  "properties": {
    "iso:country":"GB",
    "sg:address":"Unit 3 & 4 Meat Market, Upper Hollingdean Road",
    "sg:city":"Brighton",
    "sg:classifiers":[
        {
            "category":"Wholesale",
            "subcategory":"Meat",
            "type":"Manufacturing & Wholesale Goods"
        }
    ],
    "sg:phone":"+44 1273 561003",
    "sg:postcode":"BN1 7GW",
    "sg:province":"East Sussex",
    "sg:tags":[
        "-"
    ],
    "wof:name":"Weddel Swift Distribution Ltd.",
    "wof:placetype":"venue"
},
  "geometry": {"coordinates":[-0.1310500056,50.838760376],"type":"Point"}
}