{
  "type": "Feature",
  "properties": {
    "addr:full":"3a Canberra House St Albans Hertfordshire AL1 1LE",
    "addr:housenumber":"3a",
    "addr:postcode":"al1 1le",
    "addr:street":"House",
    "iso:country":"GB",
    "sg:address":"3a Canberra House",
    "sg:city":"St Albans",
    "sg:classifiers":[
        {
            "category":"Professional",
            "subcategory":"Computer Services",
            "type":"Services"
        }
    ],
    "sg:postcode":"AL1 1LE",
    "sg:province":"Hertfordshire",
    "sg:tags":[
        "system",
        "software"
    ],
    "wof:name":"Esoft (U K) Ltd.",
    "wof:placetype":"venue"
},
  "geometry": {"coordinates":[-0.3372299969,51.7504615784],"type":"Point"}
}