{
  "type": "Feature",
  "properties": {
    "addr:full":"4 York St Accrington Lancashire BB5 4LA",
    "addr:housenumber":"4",
    "addr:postcode":"bb5 4la",
    "addr:street":"York St",
    "iso:country":"GB",
    "sg:address":"4 York St",
    "sg:city":"Accrington",
    "sg:classifiers":[
        {
            "category":"Building & Trades",
            "subcategory":"Construction",
            "type":"Services"
        }
    ],
    "sg:phone":"+44 1254 382442",
    "sg:postcode":"BB5 4LA",
    "sg:province":"Lancashire",
    "sg:tags":[
        "joiner",
        "carpenter"
    ],
    "wof:name":"J Woods",
    "wof:placetype":"venue"
},
  "geometry": {"coordinates":[-2.3900198936,53.7552375793],"type":"Point"}
}