{
  "type": "Feature",
  "properties": {
    "iso:country":"GB",
    "sg:address":"Lime Tree Farm House, Chilton",
    "sg:city":"Didcot",
    "sg:classifiers":[
        {
            "category":"Professional",
            "subcategory":"Management & Consulting",
            "type":"Services"
        }
    ],
    "sg:phone":"+44 1235 831926",
    "sg:postcode":"OX11 0SW",
    "sg:province":"Oxfordshire",
    "sg:tags":[
        "consultant",
        "business"
    ],
    "wof:name":"Garrett Consultants Ltd.",
    "wof:placetype":"venue"
},
  "geometry": {"coordinates":[-1.292361,51.572792],"type":"Point"}
}