{
  "type": "Feature",
  "properties": {
    "addr:full":"Woodborough C Of E School Pewsey Wiltshire SN9 5PL",
    "addr:postcode":"sn9 5pl",
    "iso:country":"GB",
    "sg:address":"Woodborough C Of E School",
    "sg:city":"Pewsey",
    "sg:classifiers":[
        {
            "category":"Government",
            "subcategory":"Office",
            "type":"Public Place"
        }
    ],
    "sg:phone":"+44 1672 851305",
    "sg:postcode":"SN9 5PL",
    "sg:province":"Wiltshire",
    "sg:tags":[
        "local"
    ],
    "wof:name":"Wiltshire County Council",
    "wof:placetype":"venue"
},
  "geometry": {"coordinates":[-1.7623189688,51.3402862549],"type":"Point"}
}