{
  "type": "Feature",
  "properties": {
    "addr:full":"York Place Dental Practice, 37 Upperby Rd Carlisle Cumbria CA2 4HZ",
    "addr:housenumber":"37",
    "addr:postcode":"ca2 4hz",
    "addr:street":"York;Upperby Rd",
    "iso:country":"GB",
    "sg:address":"York Place Dental Practice, 37 Upperby Rd",
    "sg:city":"Carlisle",
    "sg:classifiers":[
        {
            "category":"Health Services",
            "subcategory":"Dentist",
            "type":"Services"
        }
    ],
    "sg:phone":"+44 1228 533431",
    "sg:postcode":"CA2 4HZ",
    "sg:province":"Cumbria",
    "wof:name":"R Hellen",
    "wof:placetype":"venue"
},
  "geometry": {"coordinates":[-2.9252700806,54.8779182434],"type":"Point"}
}