{
  "type": "Feature",
  "properties": {
    "addr:full":"10 Bellingham Lane Rayleigh Essex SS6 7ED",
    "addr:housenumber":"10",
    "addr:postcode":"ss6 7ed",
    "addr:street":"Bellingham Lane",
    "iso:country":"GB",
    "sg:address":"10 Bellingham Lane",
    "sg:city":"Rayleigh",
    "sg:classifiers":[
        {
            "category":"Manufacturing",
            "subcategory":"Tools & Machinery",
            "type":"Manufacturing & Wholesale Goods"
        }
    ],
    "sg:phone":"+44 1268 770375",
    "sg:postcode":"SS6 7ED",
    "sg:province":"Essex",
    "sg:tags":[
        "society",
        "friendly"
    ],
    "wof:name":"Fourways Insurance Services",
    "wof:placetype":"venue"
},
  "geometry": {"coordinates":[0.606818974,51.5875358582],"type":"Point"}
}