{
  "type": "Feature",
  "properties": {
    "addr:full":"Dorleys, Dorleys Corner Saxmundham Suffolk IP17 2QZ",
    "addr:postcode":"ip17 2qz",
    "iso:country":"GB",
    "sg:address":"Dorleys, Dorleys Corner",
    "sg:city":"Saxmundham",
    "sg:classifiers":[
        {
            "category":"Professional",
            "subcategory":"Accounting & Tax Preparation",
            "type":"Services"
        }
    ],
    "sg:postcode":"IP17 2QZ",
    "sg:province":"Suffolk",
    "sg:tags":[
        "consultant"
    ],
    "wof:name":"Tax Watchdog Ltd.",
    "wof:placetype":"venue"
},
  "geometry": {"coordinates":[1.489533,52.216713],"type":"Point"}
}