{
  "type": "Feature",
  "properties": {
    "iso:country":"GB",
    "sg:address":"Frog's Abbey Lane, Manea Road, Wimblington",
    "sg:city":"March",
    "sg:classifiers":[
        {
            "category":"Shopping",
            "type":"Retail Goods"
        }
    ],
    "sg:phone":"+44 1354 740942",
    "sg:postcode":"PE15 0PD",
    "sg:province":"Cambridgeshire",
    "sg:tags":[
        "equipment",
        "clothing",
        "safety"
    ],
    "wof:name":"Jerry H Smith Industrial Equipment",
    "wof:placetype":"venue"
},
  "geometry": {"coordinates":[0.09103,52.509991],"type":"Point"}
}