{
  "type": "Feature",
  "properties": {
    "iso:country":"GB",
    "sg:address":"53a Brewer St",
    "sg:city":"London",
    "sg:classifiers":[
        {
            "category":"Communications",
            "subcategory":"Film & Video Production",
            "type":"Services"
        }
    ],
    "sg:phone":"+44 20 7287 1188",
    "sg:postcode":"W1F 9UD",
    "sg:province":"Greater London",
    "sg:tags":[
        "tv",
        "studio"
    ],
    "wof:name":"Nolan Boulter Films Ltd",
    "wof:placetype":"venue"
},
  "geometry": {"coordinates":[-0.135176003,51.5115623474],"type":"Point"}
}