{
  "type": "Feature",
  "properties": {
    "addr:full":"Inner Circle London Greater London NW1 4NR",
    "addr:postcode":"nw1 4nr",
    "addr:street":"Inner Circle",
    "iso:country":"GB",
    "sg:address":"Inner Circle",
    "sg:city":"London",
    "sg:classifiers":[
        {
            "category":"Arts & Performance",
            "subcategory":"Theater",
            "type":"Entertainment"
        }
    ],
    "sg:postcode":"NW1 4NR",
    "sg:province":"Greater London",
    "sg:tags":[
        "hall",
        "theatre",
        "concert"
    ],
    "wof:name":"Open Air Theatre",
    "wof:placetype":"venue"
},
  "geometry": {"coordinates":[-0.155098,51.526505],"type":"Point"}
}