{
  "type": "Feature",
  "properties": {
    "addr:full":"39a Leicester Rd Wigston Leicestershire LE18 1NR",
    "addr:housenumber":"39a",
    "addr:postcode":"le18 1nr",
    "addr:street":"Leicester Rd",
    "iso:country":"GB",
    "sg:address":"39a Leicester Rd",
    "sg:city":"Wigston",
    "sg:classifiers":[
        {
            "category":"Personal",
            "subcategory":"Beauty Salon",
            "type":"Services"
        }
    ],
    "sg:phone":"+44 116 288 7433",
    "sg:postcode":"LE18 1NR",
    "sg:province":"Leicestershire",
    "wof:name":"Marshalls Sun & Beauty",
    "wof:placetype":"venue"
},
  "geometry": {"coordinates":[-1.105582,52.587086],"type":"Point"}
}