{
  "type": "Feature",
  "properties": {
    "iso:country":"GB",
    "sg:address":"Marine Activity Centre, North Dock",
    "sg:city":"Sunderland",
    "sg:classifiers":[
        {
            "category":"Shopping",
            "subcategory":"News",
            "type":"Retail Goods"
        }
    ],
    "sg:postcode":"SR6 0PW",
    "sg:province":"Tyne and Wear",
    "sg:tags":[
        "newsagent"
    ],
    "wof:name":"Marine News",
    "wof:placetype":"venue"
},
  "geometry": {"coordinates":[-1.3674299717,54.9199981689],"type":"Point"}
}