{
  "type": "Feature",
  "properties": {
    "iso:country":"GB",
    "sg:address":"205 Littlemoor Road",
    "sg:city":"Weymouth",
    "sg:classifiers":[
        {
            "category":"Health Services",
            "subcategory":"Health Practitioner",
            "type":"Services"
        },
        {
            "category":"Health Services",
            "subcategory":"Podiatrist",
            "type":"Services"
        }
    ],
    "sg:phone":"+44 1305 833800",
    "sg:postcode":"DT3 6AF",
    "sg:province":"Dorset",
    "sg:tags":[
        "osteopath",
        "chiropodist"
    ],
    "wof:name":"MICHAEL TALBOT",
    "wof:placetype":"venue"
},
  "geometry": {"coordinates":[-2.4504289627,50.6467628479],"type":"Point"}
}