{
  "type": "Feature",
  "properties": {
    "addr:full":"Prosen Road Kirriemuir Angus DD8 5AT",
    "addr:postcode":"dd8 5at",
    "addr:street":"Prosen Road",
    "iso:country":"GB",
    "sg:address":"Prosen Road",
    "sg:city":"Kirriemuir",
    "sg:classifiers":[
        {
            "category":"Government",
            "subcategory":"Office",
            "type":"Public Place"
        },
        {
            "category":"Community Center",
            "type":"Public Place"
        },
        {
            "category":"Arena",
            "subcategory":"Sports Club",
            "type":"Entertainment"
        }
    ],
    "sg:phone":"+44 1575 574849",
    "sg:postcode":"DD8 5AT",
    "sg:province":"Angus",
    "sg:tags":[
        "recreation",
        "local",
        "leisure",
        "centre"
    ],
    "wof:name":"Webster's High School Sports Centre",
    "wof:placetype":"venue"
},
  "geometry": {"coordinates":[-3.009831,56.671432],"type":"Point"}
}