{
  "type": "Feature",
  "properties": {
    "addr:full":"11 Monks Rise Welwyn Garden City Hertfordshire AL8 7NF",
    "addr:housenumber":"11",
    "addr:postcode":"al8 7nf",
    "addr:street":"Monks Rise",
    "iso:country":"GB",
    "sg:address":"11 Monks Rise",
    "sg:city":"Welwyn Garden City",
    "sg:classifiers":[
        {
            "category":"Shopping",
            "subcategory":"Computers & Home Electronics",
            "type":"Retail Goods"
        },
        {
            "category":"Professional",
            "subcategory":"Computer Services",
            "type":"Services"
        }
    ],
    "sg:phone":"+44 1707 394242",
    "sg:postcode":"AL8 7NF",
    "sg:province":"Hertfordshire",
    "sg:tags":[
        "software",
        "sales",
        "system"
    ],
    "wof:name":"Finestra Ltd.",
    "wof:placetype":"venue"
},
  "geometry": {"coordinates":[-0.2061430067,51.8192024231],"type":"Point"}
}