{
  "type": "Feature",
  "properties": {
    "addr:full":"8 Stratheden Parade, Blackheath London Greater London SE3 7SX",
    "addr:housenumber":"8",
    "addr:postcode":"se3 7sx",
    "addr:street":"Stratheden Parade",
    "iso:country":"GB",
    "sg:address":"8 Stratheden Parade, Blackheath",
    "sg:city":"London",
    "sg:classifiers":[
        {
            "category":"Travel",
            "subcategory":"Travel Agent",
            "type":"Entertainment"
        }
    ],
    "sg:phone":"+44 20 8858 1016",
    "sg:postcode":"SE3 7SX",
    "sg:province":"Greater London",
    "wof:name":"Wellers Travel Services",
    "wof:placetype":"venue"
},
  "geometry": {"coordinates":[0.0185560007,51.4764633179],"type":"Point"}
}