{
  "type": "Feature",
  "properties": {
    "iso:country":"GB",
    "sg:address":"10 Highcliffe Avenue, Fixby",
    "sg:city":"Huddersfield",
    "sg:classifiers":[
        {
            "category":"Government",
            "subcategory":"Fire Station",
            "type":"Public Place"
        }
    ],
    "sg:phone":"+44 1484 548156",
    "sg:postcode":"HD2 2NS",
    "sg:province":"West Yorkshire",
    "sg:tags":[
        "security"
    ],
    "wof:name":"J B Fire Protection",
    "wof:placetype":"venue"
},
  "geometry": {"coordinates":[-1.792221,53.666801],"type":"Point"}
}