{
  "type": "Feature",
  "properties": {
    "iso:country":"GB",
    "sg:address":"1a Chaloner Street",
    "sg:city":"Guisborough",
    "sg:classifiers":[
        {
            "category":"Professional",
            "subcategory":"Accounting & Tax Preparation",
            "type":"Services"
        }
    ],
    "sg:postcode":"TS14 6QD",
    "sg:province":"North Yorkshire",
    "sg:tags":[
        "accountant"
    ],
    "wof:name":"Michael Gale & Co.",
    "wof:placetype":"venue"
},
  "geometry": {"coordinates":[-1.052664,54.53548],"type":"Point"}
}