{
  "type": "Feature",
  "properties": {
    "iso:country":"GB",
    "sg:address":"8 Main Road, Cherhill",
    "sg:city":"Calne",
    "sg:classifiers":[
        {
            "category":"Wholesale",
            "subcategory":"Electrical",
            "type":"Manufacturing & Wholesale Goods"
        }
    ],
    "sg:phone":"+44 1249 817579",
    "sg:postcode":"SN11 8UX",
    "sg:province":"Wiltshire",
    "sg:tags":[
        "equipment",
        "refrigeration"
    ],
    "wof:name":"Western Air",
    "wof:placetype":"venue"
},
  "geometry": {"coordinates":[-1.952616,51.428757],"type":"Point"}
}