{
  "type": "Feature",
  "properties": {
    "addr:full":"204 Earl's Court Road London Greater London SW5 9QF",
    "addr:housenumber":"204",
    "addr:postcode":"sw5 9qf",
    "addr:street":"Earl'S Court Road",
    "iso:country":"GB",
    "sg:address":"204 Earl's Court Road",
    "sg:city":"London",
    "sg:classifiers":[
        {
            "category":"Restaurant",
            "type":"Food & Drink"
        }
    ],
    "sg:phone":"+44 20 7259 2544",
    "sg:postcode":"SW5 9QF",
    "sg:province":"Greater London",
    "wof:name":"Nando's Chickenland Ltd.",
    "wof:placetype":"venue"
},
  "geometry": {"coordinates":[-0.1938199997,51.4925689697],"type":"Point"}
}