{
  "type": "Feature",
  "properties": {
    "addr:full":"Hamstall Hall Farm, Hamstall Ridware Rugeley Staffordshire WS15 3RS",
    "addr:housenumber":"hamstall;ridware",
    "addr:postcode":"ws15 3rs",
    "addr:street":"Hall",
    "iso:country":"GB",
    "sg:address":"Hamstall Hall Farm, Hamstall Ridware",
    "sg:city":"Rugeley",
    "sg:classifiers":[
        {
            "category":"Farming",
            "subcategory":"Farm",
            "type":"Manufacturing & Wholesale Goods"
        }
    ],
    "sg:postcode":"WS15 3RS",
    "sg:province":"Staffordshire",
    "sg:tags":[
        "mixed",
        "crop"
    ],
    "wof:name":"Bostock Farms Ltd.",
    "wof:placetype":"venue"
},
  "geometry": {"coordinates":[-1.8425689936,52.768737793],"type":"Point"}
}