{
  "type": "Feature",
  "properties": {
    "iso:country":"GB",
    "sg:address":"22 Bridge Street",
    "sg:city":"Bishops Stortford",
    "sg:classifiers":[
        {
            "category":"Professional",
            "subcategory":"Printing & Photocopies",
            "type":"Services"
        }
    ],
    "sg:phone":"+44 1279 461500",
    "sg:postcode":"CM23 2JY",
    "sg:province":"Essex",
    "sg:tags":[
        "printer"
    ],
    "wof:name":"Prontaprint",
    "wof:placetype":"venue"
},
  "geometry": {"coordinates":[0.1609829962,51.8710708618],"type":"Point"}
}