{
  "type": "Feature",
  "properties": {
    "iso:country":"GB",
    "sg:address":"39 Westmeads Rd",
    "sg:city":"Whitstable",
    "sg:classifiers":[
        {
            "category":"Professional",
            "subcategory":"Accounting & Tax Preparation",
            "type":"Services"
        }
    ],
    "sg:phone":"+44 1227 262338",
    "sg:postcode":"CT5 1LW",
    "sg:province":"Kent",
    "sg:tags":[
        "accountant"
    ],
    "wof:name":"Clare Hammocks",
    "wof:placetype":"venue"
},
  "geometry": {"coordinates":[1.032055974,51.360584259],"type":"Point"}
}