{
  "type": "Feature",
  "properties": {
    "addr:full":"2 The Parade, Valley Drive Gravesend Kent DA12 5RT",
    "addr:housenumber":"2",
    "addr:postcode":"da12 5rt",
    "addr:street":"The Parade Valley Drive",
    "iso:country":"GB",
    "sg:address":"2 The Parade, Valley Drive",
    "sg:city":"Gravesend",
    "sg:classifiers":[
        {
            "category":"Shopping",
            "subcategory":"News",
            "type":"Retail Goods"
        },
        {
            "category":"Government",
            "subcategory":"Post Office",
            "type":"Public Place"
        }
    ],
    "sg:phone":"+44 1474 566696",
    "sg:postcode":"DA12 5RT",
    "sg:province":"Kent",
    "sg:tags":[
        "newsagent"
    ],
    "wof:name":"Valley Drive Sub Post Office",
    "wof:placetype":"venue"
},
  "geometry": {"coordinates":[0.380335,51.41087],"type":"Point"}
}