{
  "type": "Feature",
  "properties": {
    "iso:country":"GB",
    "sg:address":"Care Of Smallwood House, Church Grn West",
    "sg:city":"Redditch",
    "sg:classifiers":[
        {
            "category":"Health Services",
            "subcategory":"Hospital",
            "type":"Services"
        }
    ],
    "sg:phone":"+44 1527 488621",
    "sg:postcode":"B97 4BD",
    "sg:province":"Warwickshire",
    "wof:name":"Rowan Day Hospital",
    "wof:placetype":"venue"
},
  "geometry": {"coordinates":[-1.941267,52.30727],"type":"Point"}
}