{
  "type": "Feature",
  "properties": {
    "addr:full":"Blakes Oak Farm Abingdon Oxfordshire OX14 2JD",
    "addr:postcode":"ox14 2jd",
    "addr:street":"Blakes Oak Farm",
    "iso:country":"GB",
    "sg:address":"Blakes Oak Farm",
    "sg:city":"Abingdon",
    "sg:classifiers":[
        {
            "category":"Home & Garden",
            "subcategory":"Garden Supply",
            "type":"Retail Goods"
        }
    ],
    "sg:phone":"+44 1865 735522",
    "sg:postcode":"OX14 2JD",
    "sg:province":"Oxfordshire",
    "sg:tags":[
        "turfing"
    ],
    "wof:name":"White Horse Turf Ltd.",
    "wof:placetype":"venue"
},
  "geometry": {"coordinates":[-1.285489,51.673325],"type":"Point"}
}