{
  "type": "Feature",
  "properties": {
    "addr:full":"46 Oakhill Road Rickmansworth Hertfordshire WD3 9RF",
    "addr:housenumber":"46",
    "addr:postcode":"wd3 9rf",
    "addr:street":"Oakhill Road",
    "iso:country":"GB",
    "sg:address":"46 Oakhill Road",
    "sg:city":"Rickmansworth",
    "sg:classifiers":[
        {
            "category":"Retail",
            "subcategory":"Auto Repair",
            "type":"Services"
        }
    ],
    "sg:phone":"+44 1923 720581",
    "sg:postcode":"WD3 9RF",
    "sg:province":"Hertfordshire",
    "sg:tags":[
        "modification",
        "garage"
    ],
    "wof:name":"Roger Page",
    "wof:placetype":"venue"
},
  "geometry": {"coordinates":[-0.5140950084,51.6242523193],"type":"Point"}
}