{
  "type": "Feature",
  "properties": {
    "iso:country":"GB",
    "sg:address":"Newton Road",
    "sg:city":"Carnoustie",
    "sg:classifiers":[
        {
            "category":"Government",
            "subcategory":"Office",
            "type":"Public Place"
        },
        {
            "category":"Recreation",
            "subcategory":"Campground",
            "type":"Entertainment"
        }
    ],
    "sg:phone":"+44 1241 854430",
    "sg:postcode":"DD7 6HQ",
    "sg:province":"Angus",
    "sg:tags":[
        "park",
        "caravan",
        "local"
    ],
    "wof:name":"Woodlands Caravan Park",
    "wof:placetype":"venue"
},
  "geometry": {"coordinates":[-2.7110989094,56.5087547302],"type":"Point"}
}