{
  "type": "Feature",
  "properties": {
    "addr:full":"1 Landsberg, Litchfield Road Industrial Estate Tamworth Staffordshire B79 7XB",
    "addr:housenumber":"1",
    "addr:postcode":"b79 7xb",
    "addr:street":"Landsberg Litchfield Road Industrial Estate",
    "iso:country":"GB",
    "sg:address":"1 Landsberg, Litchfield Road Industrial Estate",
    "sg:city":"Tamworth",
    "sg:classifiers":[
        {
            "category":"Wholesale",
            "subcategory":"Vending Machines",
            "type":"Manufacturing & Wholesale Goods"
        }
    ],
    "sg:phone":"+44 1827 55501",
    "sg:postcode":"B79 7XB",
    "sg:province":"Staffordshire",
    "sg:tags":[
        "sale"
    ],
    "wof:name":"Provend Services",
    "wof:placetype":"venue"
},
  "geometry": {"coordinates":[-1.6876840591,52.6340942383],"type":"Point"}
}