{
  "type": "Feature",
  "properties": {
    "iso:country":"GB",
    "sg:address":"Charnwood Rd",
    "sg:city":"Loughborough",
    "sg:classifiers":[
        {
            "category":"Community Center",
            "type":"Public Place"
        }
    ],
    "sg:phone":"+44 1509 505072",
    "sg:postcode":"LE12 9QE",
    "sg:province":"Leicestershire",
    "sg:tags":[
        "centre"
    ],
    "wof:name":"Shepshed",
    "wof:placetype":"venue"
},
  "geometry": {"coordinates":[-1.2913479805,52.7708358765],"type":"Point"}
}