{
  "type": "Feature",
  "properties": {
    "iso:country":"GB",
    "sg:address":"Townhead, Cupar Rd",
    "sg:city":"Leven",
    "sg:classifiers":[
        {
            "category":"Professional",
            "subcategory":"Engineering",
            "type":"Services"
        }
    ],
    "sg:phone":"+44 1333 351798",
    "sg:postcode":"KY8 5LR",
    "sg:province":"Fife",
    "sg:tags":[
        "contractor",
        "electrical",
        "engineer"
    ],
    "wof:name":"C & C Electrical",
    "wof:placetype":"venue"
},
  "geometry": {"coordinates":[-2.998787,56.194401],"type":"Point"}
}