{
  "type": "Feature",
  "properties": {
    "addr:full":"1 Craig View Harrogate North Yorkshire HG2 9LU",
    "addr:housenumber":"1",
    "addr:postcode":"hg2 9lu",
    "addr:street":"Craig View",
    "iso:country":"GB",
    "sg:address":"1 Craig View",
    "sg:city":"Harrogate",
    "sg:classifiers":[
        {
            "category":"Professional",
            "subcategory":"Engineering",
            "type":"Services"
        },
        {
            "category":"Professional",
            "subcategory":"Detective & Security Services",
            "type":"Services"
        }
    ],
    "sg:postcode":"HG2 9LU",
    "sg:province":"North Yorkshire",
    "sg:tags":[
        "burglar",
        "alarm",
        "system",
        "contractor",
        "electrical",
        "engineer"
    ],
    "wof:name":"Ashville Electrical & Security Systems",
    "wof:placetype":"venue"
},
  "geometry": {"coordinates":[-1.557172,53.973759],"type":"Point"}
}