{
  "type": "Feature",
  "properties": {
    "addr:full":"Equity Chambers Poole Dorset BH15 1DX",
    "addr:postcode":"bh15 1dx",
    "iso:country":"GB",
    "sg:address":"Equity Chambers",
    "sg:city":"Poole",
    "sg:classifiers":[
        {
            "category":"Professional",
            "subcategory":"Detective & Security Services",
            "type":"Services"
        }
    ],
    "sg:postcode":"BH15 1DX",
    "sg:province":"Dorset",
    "sg:tags":[
        "agency"
    ],
    "wof:name":"Bridge Investigations",
    "wof:placetype":"venue"
},
  "geometry": {"coordinates":[-1.9867390394,50.7144851685],"type":"Point"}
}