{
  "type": "Feature",
  "properties": {
    "iso:country":"GB",
    "sg:address":"30 Rockingham Drive, Perton",
    "sg:city":"Wolverhampton",
    "sg:classifiers":[
        {
            "category":"Professional",
            "subcategory":"Engineering",
            "type":"Services"
        }
    ],
    "sg:postcode":"WV6 7SJ",
    "sg:province":"Shropshire",
    "wof:name":"P S Nicholas Associates Ltd",
    "wof:placetype":"venue"
},
  "geometry": {"coordinates":[-2.197913,52.59148],"type":"Point"}
}