{
  "type": "Feature",
  "properties": {
    "iso:country":"GB",
    "sg:address":"Unit 20 Vulcan Business Centre",
    "sg:city":"Croydon",
    "sg:classifiers":[
        {
            "category":"Professional",
            "subcategory":"Management & Consulting",
            "type":"Services"
        },
        {
            "category":"Government",
            "subcategory":"Fire Station",
            "type":"Public Place"
        }
    ],
    "sg:phone":"+44 1689 844477",
    "sg:postcode":"CR0 9UG",
    "sg:province":"Surrey",
    "sg:tags":[
        "consultant",
        "protection",
        "engineer"
    ],
    "wof:name":"P S Applications Ltd.",
    "wof:placetype":"venue"
},
  "geometry": {"coordinates":[-0.1211239994,51.3774986267],"type":"Point"}
}