{
  "type": "Feature",
  "properties": {
    "addr:full":"98 High Street West Wickham Kent BR4 0NF",
    "addr:housenumber":"98",
    "addr:postcode":"br4 0nf",
    "addr:street":"High Street",
    "iso:country":"GB",
    "sg:address":"98 High Street",
    "sg:city":"West Wickham",
    "sg:classifiers":[
        {
            "category":"Building & Trades",
            "subcategory":"Landscaping Services",
            "type":"Services"
        }
    ],
    "sg:postcode":"BR4 0NF",
    "sg:province":"Kent",
    "sg:tags":[
        "pond",
        "aquarium"
    ],
    "wof:name":"West Wickham Aquarium",
    "wof:placetype":"venue"
},
  "geometry": {"coordinates":[-0.0190719999,51.3767700195],"type":"Point"}
}