{
  "type": "Feature",
  "properties": {
    "addr:full":"8 Grosvenor Street Blackpool Lancashire FY1 3DX",
    "addr:housenumber":"8",
    "addr:postcode":"fy1 3dx",
    "addr:street":"Grosvenor Street",
    "iso:country":"GB",
    "sg:address":"8 Grosvenor Street",
    "sg:city":"Blackpool",
    "sg:classifiers":[
        {
            "category":"Travel",
            "subcategory":"Hotels & Motels",
            "type":"Entertainment"
        }
    ],
    "sg:postcode":"FY1 3DX",
    "sg:province":"Lancashire",
    "sg:tags":[
        "house",
        "guest"
    ],
    "wof:name":"Sharose",
    "wof:placetype":"venue"
},
  "geometry": {"coordinates":[-3.045443058,53.8188438416],"type":"Point"}
}