{
  "type": "Feature",
  "properties": {
    "iso:country":"GB",
    "sg:address":"90 Forest Rd",
    "sg:city":"Frome",
    "sg:classifiers":[
        {
            "category":"Food & Beverages",
            "subcategory":"Groceries & Convenience Stores",
            "type":"Retail Goods"
        }
    ],
    "sg:phone":"+44 1373 465787",
    "sg:postcode":"BA11 2TU",
    "sg:province":"Somerset",
    "wof:name":"T & S Stores",
    "wof:placetype":"venue"
},
  "geometry": {"coordinates":[-2.305557,51.240768],"type":"Point"}
}