{
  "type": "Feature",
  "properties": {
    "addr:full":"Old Station Yard, Off Trafalgar Street Burnley Lancashire BB11 1RA",
    "addr:postcode":"bb11 1ra",
    "addr:street":"Old Station;Off Trafalgar Street",
    "iso:country":"GB",
    "sg:address":"Old Station Yard, Off Trafalgar Street",
    "sg:city":"Burnley",
    "sg:classifiers":[
        {
            "category":"Autos & Motor Vehicles",
            "subcategory":"Automobile Sales",
            "type":"Retail Goods"
        }
    ],
    "sg:phone":"+44 1282 450704",
    "sg:postcode":"BB11 1RA",
    "sg:province":"Lancashire",
    "sg:tags":[
        "car"
    ],
    "wof:name":"Keith Abbott",
    "wof:placetype":"venue"
},
  "geometry": {"coordinates":[-2.2438089848,53.7880096436],"type":"Point"}
}