{
  "type": "Feature",
  "properties": {
    "iso:country":"GB",
    "sg:address":"White Lion House, Church Street, Bishops Lydeard",
    "sg:city":"Taunton",
    "sg:classifiers":[
        {
            "category":"Food & Beverages",
            "subcategory":"Fruits & Vegetables",
            "type":"Retail Goods"
        }
    ],
    "sg:phone":"+44 1823 433973",
    "sg:postcode":"TA4 3AT",
    "sg:province":"Devon",
    "sg:tags":[
        "greengrocer"
    ],
    "wof:name":"The Fruit & Flower Basket",
    "wof:placetype":"venue"
},
  "geometry": {"coordinates":[-3.255958,51.047794],"type":"Point"}
}