{
  "type": "Feature",
  "properties": {
    "iso:country":"GB",
    "sg:address":"The Bungalow, Bull Haw Farm",
    "sg:city":"Barnsley",
    "sg:classifiers":[
        {
            "category":"Farming",
            "subcategory":"Livestock Farm",
            "type":"Manufacturing & Wholesale Goods"
        }
    ],
    "sg:phone":"+44 1226 790631",
    "sg:postcode":"S75 4NJ",
    "sg:province":"South Yorkshire",
    "sg:tags":[
        "others"
    ],
    "wof:name":"Thomas Penrose",
    "wof:placetype":"venue"
},
  "geometry": {"coordinates":[-1.57881,53.543091],"type":"Point"}
}