{
  "type": "Feature",
  "properties": {
    "iso:country":"GB",
    "sg:address":"Unit 9 Bolton Market Hall",
    "sg:city":"Bolton",
    "sg:classifiers":[
        {
            "category":"Home & Garden",
            "subcategory":"Kitchen Supply",
            "type":"Retail Goods"
        }
    ],
    "sg:phone":"+44 1204 522922",
    "sg:postcode":"BL1 2AR",
    "sg:province":"Lancashire",
    "sg:tags":[
        "glassware",
        "china"
    ],
    "wof:name":"Joseph Bailey & Son (Bolton) Ltd.",
    "wof:placetype":"venue"
},
  "geometry": {"coordinates":[-2.430254,53.580528],"type":"Point"}
}