{
  "type": "Feature",
  "properties": {
    "addr:full":"5 Swan Court, East Street Andover Hampshire SP10 1EZ",
    "addr:housenumber":"5",
    "addr:postcode":"sp10 1ez",
    "addr:street":"Swan Court East Street",
    "iso:country":"GB",
    "sg:address":"5 Swan Court, East Street",
    "sg:city":"Andover",
    "sg:classifiers":[
        {
            "category":"Real Estate",
            "subcategory":"Real Estate Agent",
            "type":"Services"
        }
    ],
    "sg:phone":"+44 1264 336990",
    "sg:postcode":"SP10 1EZ",
    "sg:province":"Hampshire",
    "wof:name":"Evans & Partridge",
    "wof:placetype":"venue"
},
  "geometry": {"coordinates":[-1.4767789841,51.2064933777],"type":"Point"}
}