{
  "type": "Feature",
  "properties": {
    "iso:country":"GB",
    "sg:address":"45 Edna Road",
    "sg:city":"London",
    "sg:classifiers":[
        {
            "category":"Professional",
            "subcategory":"Accounting & Tax Preparation",
            "type":"Services"
        }
    ],
    "sg:phone":"+44 20 8542 5232",
    "sg:postcode":"SW20 8BS",
    "sg:province":"Greater London",
    "sg:tags":[
        "accountant"
    ],
    "wof:name":"Martin Equipment Ltd",
    "wof:placetype":"venue"
},
  "geometry": {"coordinates":[-0.223749,51.408867],"type":"Point"}
}