{
  "type": "Feature",
  "properties": {
    "addr:full":"21 Crewe Road Sandbach Cheshire CW11 4NE",
    "addr:housenumber":"21",
    "addr:postcode":"cw11 4ne",
    "addr:street":"Crewe Road",
    "iso:country":"GB",
    "sg:address":"21 Crewe Road",
    "sg:city":"Sandbach",
    "sg:classifiers":[
        {
            "category":"Shopping",
            "subcategory":"Mobile Phones",
            "type":"Retail Goods"
        }
    ],
    "sg:phone":"+44 1270 761227",
    "sg:postcode":"CW11 4NE",
    "sg:province":"Cheshire",
    "wof:name":"The Phone Inn",
    "wof:placetype":"venue"
},
  "geometry": {"coordinates":[-2.3695249557,53.1420326233],"type":"Point"}
}