{
  "type": "Feature",
  "properties": {
    "iso:country":"GB",
    "sg:address":"Green Vale, Withleigh",
    "sg:city":"Tiverton",
    "sg:classifiers":[
        {
            "category":"Retail",
            "subcategory":"Auto Repair",
            "type":"Services"
        }
    ],
    "sg:postcode":"EX16 8JH",
    "sg:province":"Devon",
    "sg:tags":[
        "body",
        "car"
    ],
    "wof:name":"Jackson,D,",
    "wof:placetype":"venue"
},
  "geometry": {"coordinates":[-3.544087,50.902725],"type":"Point"}
}