{
  "type": "Feature",
  "properties": {
    "addr:full":"13a Goswell Hill Windsor Berkshire SL4 1RH",
    "addr:housenumber":"13a",
    "addr:postcode":"sl4 1rh",
    "addr:street":"Goswell Hill",
    "iso:country":"GB",
    "sg:address":"13a Goswell Hill",
    "sg:city":"Windsor",
    "sg:classifiers":[
        {
            "category":"Professional",
            "subcategory":"Management & Consulting",
            "type":"Services"
        },
        {
            "category":"Arena",
            "subcategory":"Sports Club",
            "type":"Entertainment"
        }
    ],
    "sg:phone":"+44 1753 866400",
    "sg:postcode":"SL4 1RH",
    "sg:province":"Berkshire",
    "sg:tags":[
        "consultant",
        "specialist"
    ],
    "wof:name":"SHARMI & JOSEPH BEAUTY & PARAMEDIC CENTRE",
    "wof:placetype":"venue"
},
  "geometry": {"coordinates":[-0.610707,51.482849],"type":"Point"}
}