{
  "type": "Feature",
  "properties": {
    "iso:country":"GB",
    "sg:address":"2 Clayton Parade, Turners Hill, Cheshunt",
    "sg:city":"Waltham Cross",
    "sg:classifiers":[
        {
            "category":"Professional",
            "type":"Services"
        }
    ],
    "sg:postcode":"EN8 8NQ",
    "sg:province":"Essex",
    "sg:tags":[
        "interior",
        "furnishers",
        "designer"
    ],
    "wof:name":"Hepworths Interiors",
    "wof:placetype":"venue"
},
  "geometry": {"coordinates":[-0.034519,51.701355],"type":"Point"}
}