{
  "type": "Feature",
  "properties": {
    "iso:country":"GB",
    "sg:address":"Unit 10 Button Mills Lower Mills, Bridgend",
    "sg:city":"Stonehouse",
    "sg:classifiers":[
        {
            "category":"Farming",
            "subcategory":"Farm",
            "type":"Manufacturing & Wholesale Goods"
        }
    ],
    "sg:phone":"+44 1453 791344",
    "sg:postcode":"GL10 2BB",
    "sg:province":"Gloucestershire",
    "sg:tags":[
        "agricultural"
    ],
    "wof:name":"C Hall",
    "wof:placetype":"venue"
},
  "geometry": {"coordinates":[-2.2822339535,51.7457046509],"type":"Point"}
}