{
  "type": "Feature",
  "properties": {
    "addr:full":"26 Ermine Close Hounslow Greater London TW4 7PW",
    "addr:housenumber":"26",
    "addr:postcode":"tw4 7pw",
    "addr:street":"Ermine Close",
    "iso:country":"GB",
    "sg:address":"26 Ermine Close",
    "sg:city":"Hounslow",
    "sg:classifiers":[
        {
            "category":"Retail",
            "subcategory":"Auto Repair",
            "type":"Services"
        }
    ],
    "sg:phone":"+44 20 8572 7163",
    "sg:postcode":"TW4 7PW",
    "sg:province":"Greater London",
    "sg:tags":[
        "car",
        "upholsterer"
    ],
    "wof:name":"Arry's Valeting",
    "wof:placetype":"venue"
},
  "geometry": {"coordinates":[-0.397841,51.47253],"type":"Point"}
}