{
  "type": "Feature",
  "properties": {
    "iso:country":"GB",
    "sg:address":"Unit 2a The Carr Office, Richmond House, White Rose Way",
    "sg:city":"Doncaster",
    "sg:classifiers":[
        {
            "category":"Professional",
            "subcategory":"Management & Consulting",
            "type":"Services"
        }
    ],
    "sg:postcode":"DN4 5JH",
    "sg:province":"South Yorkshire",
    "sg:tags":[
        "marketing",
        "consultant"
    ],
    "wof:name":"Media-Byte Marketing Ltd",
    "wof:placetype":"venue"
},
  "geometry": {"coordinates":[-1.1149890423,53.501209259],"type":"Point"}
}