{
  "type": "Feature",
  "properties": {
    "addr:full":"Hackness Rd Scarborough North Yorkshire YO12 5RY",
    "addr:postcode":"yo12 5ry",
    "addr:street":"Hackness Rd",
    "iso:country":"GB",
    "sg:address":"Hackness Rd",
    "sg:city":"Scarborough",
    "sg:classifiers":[
        {
            "category":"Bars & Pubs",
            "type":"Food & Drink"
        }
    ],
    "sg:phone":"+44 1723 372834",
    "sg:postcode":"YO12 5RY",
    "sg:province":"North Yorkshire",
    "sg:tags":[
        "pubs",
        "inn"
    ],
    "wof:name":"Punch Leisure Ltd",
    "wof:placetype":"venue"
},
  "geometry": {"coordinates":[-0.442589,54.296543],"type":"Point"}
}