{
  "type": "Feature",
  "properties": {
    "addr:full":"16 Stort Mill Harlow Essex CM20 2SN",
    "addr:housenumber":"16",
    "addr:postcode":"cm20 2sn",
    "addr:street":"Stort Mill",
    "iso:country":"GB",
    "sg:address":"16 Stort Mill",
    "sg:city":"Harlow",
    "sg:classifiers":[
        {
            "category":"Food & Beverages",
            "subcategory":"Bakery",
            "type":"Retail Goods"
        }
    ],
    "sg:phone":"+44 1279 423332",
    "sg:postcode":"CM20 2SN",
    "sg:province":"Essex",
    "sg:tags":[
        "baker"
    ],
    "wof:name":"Andersons Bakeries",
    "wof:placetype":"venue"
},
  "geometry": {"coordinates":[0.128241,51.79298],"type":"Point"}
}