{
  "type": "Feature",
  "properties": {
    "addr:full":"65 Old Christchurch Rd Bournemouth Dorset BH1 1EW",
    "addr:housenumber":"65",
    "addr:postcode":"bh1 1ew",
    "addr:street":"Old Christchurch Rd",
    "iso:country":"GB",
    "sg:address":"65 Old Christchurch Rd",
    "sg:city":"Bournemouth",
    "sg:classifiers":[
        {
            "category":"Travel",
            "subcategory":"Travel Agent",
            "type":"Entertainment"
        }
    ],
    "sg:phone":"+44 1202 638700",
    "sg:postcode":"BH1 1EW",
    "sg:province":"Dorset",
    "wof:name":"Going Places",
    "wof:placetype":"venue"
},
  "geometry": {"coordinates":[-1.8766889572,50.7211151123],"type":"Point"}
}