{
  "type": "Feature",
  "properties": {
    "iso:country":"GB",
    "sg:address":"Water Street Garage, Water Street",
    "sg:city":"Deal",
    "sg:classifiers":[
        {
            "category":"Professional",
            "subcategory":"Engineering",
            "type":"Services"
        },
        {
            "category":"Autos & Motor Vehicles",
            "subcategory":"Auto Supplies",
            "type":"Retail Goods"
        },
        {
            "category":"Retail",
            "subcategory":"Auto Repair",
            "type":"Services"
        }
    ],
    "sg:phone":"+44 1304 380255",
    "sg:postcode":"CT14 6DJ",
    "sg:province":"Kent",
    "sg:tags":[
        "contractor",
        "garage",
        "electrical",
        "tyre",
        "modification",
        "engineer"
    ],
    "wof:name":"M & D Tyres",
    "wof:placetype":"venue"
},
  "geometry": {"coordinates":[1.4016580582,51.2283592224],"type":"Point"}
}