{
  "type": "Feature",
  "properties": {
    "iso:country":"GB",
    "sg:address":"Gelligaer Quarry, Gelligaer Common",
    "sg:city":"Treharris",
    "sg:classifiers":[
        {
            "category":"Manufacturing",
            "subcategory":"Glass & Minerals",
            "type":"Manufacturing & Wholesale Goods"
        }
    ],
    "sg:phone":"+44 1443 410886",
    "sg:postcode":"CF46 6TA",
    "sg:province":"Caerphilly",
    "sg:tags":[
        "chalk",
        "stone",
        "slate"
    ],
    "wof:name":"Pioneer Aggregates (Uk)",
    "wof:placetype":"venue"
},
  "geometry": {"coordinates":[-3.3064699173,51.6648864746],"type":"Point"}
}