{
  "type": "Feature",
  "properties": {
    "addr:full":"418 Preston Old Road Blackburn Lancashire BB2 5LP",
    "addr:housenumber":"418",
    "addr:postcode":"bb2 5lp",
    "addr:street":"Preston Old Road",
    "iso:country":"GB",
    "sg:address":"418 Preston Old Road",
    "sg:city":"Blackburn",
    "sg:classifiers":[
        {
            "category":"Government",
            "subcategory":"Post Office",
            "type":"Public Place"
        }
    ],
    "sg:phone":"+44 1254 201085",
    "sg:postcode":"BB2 5LP",
    "sg:province":"Lancashire",
    "wof:name":"Cherry Tree Post Office",
    "wof:placetype":"venue"
},
  "geometry": {"coordinates":[-2.5205209255,53.73279953],"type":"Point"}
}