{
  "type": "Feature",
  "properties": {
    "addr:full":"7 Gillygate Pontefract North Yorkshire WF8 1PH",
    "addr:housenumber":"7",
    "addr:postcode":"wf8 1ph",
    "addr:street":"Gillygate Pontefract",
    "iso:country":"GB",
    "sg:address":"7 Gillygate",
    "sg:city":"Pontefract",
    "sg:classifiers":[
        {
            "category":"Personal",
            "subcategory":"Beauty Salon",
            "type":"Services"
        }
    ],
    "sg:phone":"+44 1977 708888",
    "sg:postcode":"WF8 1PH",
    "sg:province":"North Yorkshire",
    "sg:tags":[
        "unisex",
        "hairdresser"
    ],
    "wof:name":"Salon 7",
    "wof:placetype":"venue"
},
  "geometry": {"coordinates":[-1.3098080158,53.691822052],"type":"Point"}
}