{
  "type": "Feature",
  "properties": {
    "addr:full":"10 Langridge Drive East Grinstead East Sussex RH19 4SX",
    "addr:housenumber":"10",
    "addr:postcode":"rh19 4sx",
    "addr:street":"Langridge Drive",
    "iso:country":"GB",
    "sg:address":"10 Langridge Drive",
    "sg:city":"East Grinstead",
    "sg:classifiers":[
        {
            "category":"Home & Garden",
            "subcategory":"Home Furnishings",
            "type":"Retail Goods"
        },
        {
            "category":"Building & Trades",
            "subcategory":"Construction",
            "type":"Services"
        }
    ],
    "sg:phone":"+44 1342 327585",
    "sg:postcode":"RH19 4SX",
    "sg:province":"East Sussex",
    "sg:tags":[
        "bedroom",
        "installers",
        "planner",
        "kitchen",
        "furnishers"
    ],
    "wof:name":"J A Gaunt & M A Palmer",
    "wof:placetype":"venue"
},
  "geometry": {"coordinates":[-0.0139779998,51.1231536865],"type":"Point"}
}