{
  "type": "Feature",
  "properties": {
    "addr:full":"Jeray House, Unit 16,st. Georges Ind. Est., White Lion Road Amersham Buckinghamshire HP7 9JQ",
    "addr:housenumber":"unit 16",
    "addr:postcode":"hp7 9jq",
    "addr:street":"Est.;Lion Road",
    "iso:country":"GB",
    "sg:address":"Jeray House, Unit 16,st. Georges Ind. Est., White Lion Road",
    "sg:city":"Amersham",
    "sg:classifiers":[
        {
            "category":"Home & Garden",
            "subcategory":"Kitchen Supply",
            "type":"Retail Goods"
        }
    ],
    "sg:phone":"+44 1494 766566",
    "sg:postcode":"HP7 9JQ",
    "sg:province":"Buckinghamshire",
    "sg:tags":[
        "bar",
        "accessory"
    ],
    "wof:name":"Original Products Ltd/ Jeray Sales Ltd.",
    "wof:placetype":"venue"
},
  "geometry": {"coordinates":[-0.58602,51.671711],"type":"Point"}
}