{
  "type": "Feature",
  "properties": {
    "addr:full":"14 Queen St Wells Somerset BA5 2DP",
    "addr:housenumber":"14",
    "addr:postcode":"ba5 2dp",
    "addr:street":"Queen St",
    "iso:country":"GB",
    "sg:address":"14 Queen St",
    "sg:city":"Wells",
    "sg:classifiers":[
        {
            "category":"Deli",
            "type":"Food & Drink"
        },
        {
            "category":"Food & Beverages",
            "subcategory":"Meat & Fish",
            "type":"Retail Goods"
        }
    ],
    "sg:phone":"+44 1749 679803",
    "sg:postcode":"BA5 2DP",
    "sg:province":"Somerset",
    "sg:tags":[
        "delicatessen",
        "butcher"
    ],
    "wof:name":"Laurel Bank Dairy Co Ltd",
    "wof:placetype":"venue"
},
  "geometry": {"coordinates":[-2.6488289833,51.2074661255],"type":"Point"}
}