{
  "type": "Feature",
  "properties": {
    "addr:full":"532 Doncaster Road Barnsley South Yorkshire S71 5AQ",
    "addr:housenumber":"532",
    "addr:postcode":"s71 5aq",
    "addr:street":"Doncaster Road;Yorkshire",
    "iso:country":"GB",
    "sg:address":"532 Doncaster Road",
    "sg:city":"Barnsley",
    "sg:classifiers":[
        {
            "category":"Shopping",
            "subcategory":"News",
            "type":"Retail Goods"
        }
    ],
    "sg:phone":"+44 1226 213966",
    "sg:postcode":"S71 5AQ",
    "sg:province":"South Yorkshire",
    "sg:tags":[
        "newsagent"
    ],
    "wof:name":"G & J Humpleby",
    "wof:placetype":"venue"
},
  "geometry": {"coordinates":[-1.418548,53.546093],"type":"Point"}
}