{
  "type": "Feature",
  "properties": {
    "addr:full":"Inverebrie Farm Ellon Aberdeenshire AB41 8PX",
    "addr:postcode":"ab41 8px",
    "iso:country":"GB",
    "sg:address":"Inverebrie Farm",
    "sg:city":"Ellon",
    "sg:classifiers":[
        {
            "category":"Banks & Credit Unions",
            "subcategory":"Financial Services",
            "type":"Services"
        }
    ],
    "sg:phone":"+44 1358 761444",
    "sg:postcode":"AB41 8PX",
    "sg:province":"Aberdeenshire",
    "sg:tags":[
        "consultant"
    ],
    "wof:name":"Agricultural Finance Bureau Ltd.",
    "wof:placetype":"venue"
},
  "geometry": {"coordinates":[-2.072814,57.364136],"type":"Point"}
}