{
  "type": "Feature",
  "properties": {
    "iso:country":"GB",
    "sg:address":"Dunkeswell Aerodrome, Dunkeswell",
    "sg:city":"Honiton",
    "sg:classifiers":[
        {
            "category":"Education",
            "subcategory":"Special Training",
            "type":"Public Place"
        }
    ],
    "sg:phone":"+44 1404 891643",
    "sg:postcode":"EX14 4RA",
    "sg:province":"Devon",
    "sg:tags":[
        "school",
        "flying"
    ],
    "wof:name":"Devon School of Flying Ltd.",
    "wof:placetype":"venue"
},
  "geometry": {"coordinates":[-3.2225089073,50.8633232117],"type":"Point"}
}