{
  "type": "Feature",
  "properties": {
    "addr:full":"Unit 3, Witheridge Place Ilfracombe Devon EX34 9RA",
    "addr:housenumber":"unit 3",
    "addr:postcode":"ex34 9ra",
    "addr:street":"Witheridge Place",
    "iso:country":"GB",
    "sg:address":"Unit 3, Witheridge Place",
    "sg:city":"Ilfracombe",
    "sg:classifiers":[
        {
            "category":"Professional",
            "subcategory":"Engineering",
            "type":"Services"
        }
    ],
    "sg:phone":"+44 1271 867702",
    "sg:postcode":"EX34 9RA",
    "sg:province":"Devon",
    "sg:tags":[
        "precision",
        "engineer"
    ],
    "wof:name":"Hele Bay Precision Engineering Co",
    "wof:placetype":"venue"
},
  "geometry": {"coordinates":[-4.0999641418,51.2069244385],"type":"Point"}
}