{
  "type": "Feature",
  "properties": {
    "addr:full":"Wansee, Galltyfoel Caernarfon Gwynedd LL55 3EG",
    "addr:postcode":"ll55 3eg",
    "iso:country":"GB",
    "sg:address":"Wansee, Galltyfoel",
    "sg:city":"Caernarfon",
    "sg:classifiers":[
        {
            "category":"Government",
            "subcategory":"Post Office",
            "type":"Public Place"
        }
    ],
    "sg:phone":"+44 1286 870240",
    "sg:postcode":"LL55 3EG",
    "sg:province":"Gwynedd",
    "sg:tags":[
        "organisation",
        "soc",
        "research"
    ],
    "wof:name":"M Foley",
    "wof:placetype":"venue"
},
  "geometry": {"coordinates":[-4.1118440628,53.1412162781],"type":"Point"}
}