{
  "type": "Feature",
  "properties": {
    "iso:country":"GB",
    "sg:address":"Millbay Docks",
    "sg:city":"Plymouth",
    "sg:classifiers":[
        {
            "category":"Freight",
            "type":"Transportation"
        }
    ],
    "sg:phone":"+44 1752 665154",
    "sg:postcode":"PL1 3SA",
    "sg:province":"Devon",
    "sg:tags":[
        "overseas",
        "forwarders",
        "shipping",
        "removal"
    ],
    "wof:name":"BELLAMY & CO (PLYMOUTH) LTD",
    "wof:placetype":"venue"
},
  "geometry": {"coordinates":[-4.1519341469,50.3678359985],"type":"Point"}
}