{
  "type": "Feature",
  "properties": {
    "iso:country":"GB",
    "sg:address":"B1-b2 Unit, Empress Park",
    "sg:city":"Southampton",
    "sg:classifiers":[
        {
            "category":"Wholesale",
            "subcategory":"Machinery & Supplies",
            "type":"Manufacturing & Wholesale Goods"
        },
        {
            "category":"Arts & Performance",
            "subcategory":"Theater",
            "type":"Entertainment"
        }
    ],
    "sg:phone":"+44 23 8021 1000",
    "sg:postcode":"SO14 0JX",
    "sg:province":"Hampshire",
    "sg:tags":[
        "theatrical",
        "presentation"
    ],
    "wof:name":"HANDMADE PRODUCTIONS LTD",
    "wof:placetype":"venue"
},
  "geometry": {"coordinates":[-1.3923200369,50.9180107117],"type":"Point"}
}