{
  "type": "Feature",
  "properties": {
    "iso:country":"GB",
    "sg:address":"64 Larches Lane, Ashton",
    "sg:city":"Preston",
    "sg:classifiers":[
        {
            "category":"Place Of Worship",
            "type":"Public Place"
        }
    ],
    "sg:postcode":"PR2 1PP",
    "sg:province":"Lancashire",
    "wof:name":"Our Lady & St. Bernard S R C Church",
    "wof:placetype":"venue"
},
  "geometry": {"coordinates":[-2.757628,53.764614],"type":"Point"}
}