{
  "type": "Feature",
  "properties": {
    "addr:full":"Llanbradach Service Station, Wingfield Terr Caerphilly Caerphilly CF83 3NT",
    "addr:postcode":"cf83 3nt",
    "addr:street":"Terr",
    "iso:country":"GB",
    "sg:address":"Llanbradach Service Station, Wingfield Terr",
    "sg:city":"Caerphilly",
    "sg:classifiers":[
        {
            "category":"Retail",
            "subcategory":"Auto Repair",
            "type":"Services"
        }
    ],
    "sg:phone":"+44 29 2088 8808",
    "sg:postcode":"CF83 3NT",
    "sg:province":"Caerphilly",
    "sg:tags":[
        "modification",
        "garage"
    ],
    "wof:name":"K & T Autos",
    "wof:placetype":"venue"
},
  "geometry": {"coordinates":[-3.2177278996,51.576587677],"type":"Point"}
}