{
  "type": "Feature",
  "properties": {
    "addr:full":"15 Spring Gro, Farncombe Godalming Surrey GU7 3SS",
    "addr:housenumber":"15",
    "addr:postcode":"gu7 3ss",
    "addr:street":"Spring Gro Farncombe Godalming",
    "iso:country":"GB",
    "sg:address":"15 Spring Gro, Farncombe",
    "sg:city":"Godalming",
    "sg:classifiers":[
        {
            "category":"Building & Trades",
            "subcategory":"Construction",
            "type":"Services"
        }
    ],
    "sg:postcode":"GU7 3SS",
    "sg:province":"Surrey",
    "sg:tags":[
        "roofing"
    ],
    "wof:name":"John Milton Brickwork",
    "wof:placetype":"venue"
},
  "geometry": {"coordinates":[-0.608808,51.202309],"type":"Point"}
}