{
  "type": "Feature",
  "properties": {
    "iso:country":"GB",
    "sg:address":"6-8 Drayton Park, Islington",
    "sg:city":"London",
    "sg:classifiers":[
        {
            "category":"Shopping",
            "type":"Retail Goods"
        }
    ],
    "sg:postcode":"N5 1NU",
    "sg:province":"Greater London",
    "sg:tags":[
        "part",
        "accessory"
    ],
    "wof:name":"Pearlcastle Ltd.",
    "wof:placetype":"venue"
},
  "geometry": {"coordinates":[-0.1090760008,51.5506134033],"type":"Point"}
}