{
  "type": "Feature",
  "properties": {
    "addr:full":"6-8 Drayton Park, Islington London Greater London N5 1NU",
    "addr:housenumber":"6-8",
    "addr:postcode":"n5 1nu",
    "addr:street":"Drayton Park",
    "iso:country":"GB",
    "sg:address":"6-8 Drayton Park, Islington",
    "sg:city":"London",
    "sg:classifiers":[
        {
            "category":"Shopping",
            "type":"Retail Goods"
        }
    ],
    "sg:postcode":"N5 1NU",
    "sg:province":"Greater London",
    "sg:tags":[
        "part",
        "accessory"
    ],
    "wof:name":"Pearlcastle Ltd.",
    "wof:placetype":"venue"
},
  "geometry": {"coordinates":[-0.1090760008,51.5506134033],"type":"Point"}
}