{
  "type": "Feature",
  "properties": {
    "iso:country":"GB",
    "sg:address":"337 Ruislip Rd",
    "sg:city":"Northolt",
    "sg:classifiers":[
        {
            "category":"Health Services",
            "subcategory":"Doctor",
            "type":"Services"
        }
    ],
    "sg:phone":"+44 20 8578 1537",
    "sg:postcode":"UB5 6AS",
    "sg:province":"Greater London",
    "sg:tags":[
        "practitioners"
    ],
    "wof:name":"Joshi, B V",
    "wof:placetype":"venue"
},
  "geometry": {"coordinates":[-0.3730579913,51.5326194763],"type":"Point"}
}