{
  "type": "Feature",
  "properties": {
    "iso:country":"GB",
    "sg:address":"Cupernham Lane",
    "sg:city":"Romsey",
    "sg:classifiers":[
        {
            "category":"Farming",
            "subcategory":"Nursery",
            "type":"Manufacturing & Wholesale Goods"
        }
    ],
    "sg:phone":"+44 1794 523686",
    "sg:postcode":"SO51 7LF",
    "sg:province":"Hampshire",
    "sg:tags":[
        "creche"
    ],
    "wof:name":"Abbotswood Day Nursery",
    "wof:placetype":"venue"
},
  "geometry": {"coordinates":[-1.4848940372,51.0040550232],"type":"Point"}
}