{
  "type": "Feature",
  "properties": {
    "iso:country":"GB",
    "sg:address":"39 Woolwich Road",
    "sg:city":"London",
    "sg:classifiers":[
        {
            "category":"Retail",
            "subcategory":"Funeral Services",
            "type":"Services"
        }
    ],
    "sg:phone":"+44 20 8858 2966",
    "sg:postcode":"SE10 0RA",
    "sg:province":"Greater London",
    "sg:tags":[
        "director"
    ],
    "wof:name":"Francis Chappell & Sons",
    "wof:placetype":"venue"
},
  "geometry": {"coordinates":[0.0082670003,51.486328125],"type":"Point"}
}