{
  "type": "Feature",
  "properties": {
    "addr:full":"122 Flemming Crescent Leigh On Sea Essex SS9 4HT",
    "addr:housenumber":"122",
    "addr:postcode":"ss9 4ht",
    "addr:street":"Flemming Crescent",
    "iso:country":"GB",
    "sg:address":"122 Flemming Crescent",
    "sg:city":"Leigh On Sea",
    "sg:classifiers":[
        {
            "category":"Freight",
            "type":"Transportation"
        }
    ],
    "sg:phone":"+44 1702 719919",
    "sg:postcode":"SS9 4HT",
    "sg:province":"Essex",
    "sg:tags":[
        "haulage",
        "road"
    ],
    "wof:name":"BATES HAULAGE",
    "wof:placetype":"venue"
},
  "geometry": {"coordinates":[0.649522,51.555794],"type":"Point"}
}