{
  "type": "Feature",
  "properties": {
    "iso:country":"GB",
    "sg:address":"23 The Venn",
    "sg:city":"Shaftesbury",
    "sg:classifiers":[
        {
            "category":"Retail",
            "subcategory":"Repair Shop",
            "type":"Services"
        }
    ],
    "sg:phone":"+44 1747 853683",
    "sg:postcode":"SP7 8EB",
    "sg:province":"Dorset",
    "sg:tags":[
        "maintenance"
    ],
    "wof:name":"Fraser Eade the Handyman",
    "wof:placetype":"venue"
},
  "geometry": {"coordinates":[-2.189091,51.010075],"type":"Point"}
}