{
  "type": "Feature",
  "properties": {
    "addr:full":"160-163 Friar Street Reading Berkshire RG1 1JR",
    "addr:housenumber":"160-163",
    "addr:postcode":"rg1 1jr",
    "addr:street":"Friar Street",
    "iso:country":"GB",
    "sg:address":"160-163 Friar Street",
    "sg:city":"Reading",
    "sg:classifiers":[
        {
            "category":"Government",
            "subcategory":"Court House",
            "type":"Public Place"
        }
    ],
    "sg:phone":"+44 118 959 9833",
    "sg:postcode":"RG1 1JR",
    "sg:province":"Berkshire",
    "wof:name":"The Home Office",
    "wof:placetype":"venue"
},
  "geometry": {"coordinates":[-0.970954,51.456566],"type":"Point"}
}