{
  "type": "Feature",
  "properties": {
    "addr:full":"Scar Farm, Whitewood Lane, Tilston Malpas Cheshire SY14 7DL",
    "addr:postcode":"sy14 7dl",
    "addr:street":"Scar;Whitewood Lane",
    "iso:country":"GB",
    "sg:address":"Scar Farm, Whitewood Lane, Tilston",
    "sg:city":"Malpas",
    "sg:classifiers":[
        {
            "category":"Farming",
            "subcategory":"Dairy Farm",
            "type":"Manufacturing & Wholesale Goods"
        }
    ],
    "sg:postcode":"SY14 7DL",
    "sg:province":"Cheshire",
    "wof:name":"Philip G Evans",
    "wof:placetype":"venue"
},
  "geometry": {"coordinates":[-2.8073289394,53.0566711426],"type":"Point"}
}