{
  "type": "Feature",
  "properties": {
    "iso:country":"GB",
    "sg:address":"Eastfield Road",
    "sg:city":"Grimsby",
    "sg:classifiers":[
        {
            "category":"Autos & Motor Vehicles",
            "subcategory":"Auto Supplies",
            "type":"Retail Goods"
        }
    ],
    "sg:phone":"+44 1469 572422",
    "sg:postcode":"DN40 3DH",
    "sg:province":"Lincolnshire",
    "sg:tags":[
        "towing",
        "eqpt",
        "trailer"
    ],
    "wof:name":"Crane Fruehauf",
    "wof:placetype":"venue"
},
  "geometry": {"coordinates":[-0.255424,53.635429],"type":"Point"}
}