{
  "type": "Feature",
  "properties": {
    "addr:full":"508 High Rd Woodford Green Essex IG8 0PN",
    "addr:housenumber":"508",
    "addr:postcode":"ig8 0pn",
    "addr:street":"High Rd",
    "iso:country":"GB",
    "sg:address":"508 High Rd",
    "sg:city":"Woodford Green",
    "sg:classifiers":[
        {
            "category":"Professional",
            "type":"Services"
        }
    ],
    "sg:phone":"+44 20 8559 2950",
    "sg:postcode":"IG8 0PN",
    "sg:province":"Essex",
    "sg:tags":[
        "shopfitters"
    ],
    "wof:name":"European Eagle Contracts Ltd",
    "wof:placetype":"venue"
},
  "geometry": {"coordinates":[0.025808,51.616512],"type":"Point"}
}