{
  "type": "Feature",
  "properties": {
    "iso:country":"GB",
    "sg:address":"Stratton Mill, Stratton",
    "sg:city":"Dorchester",
    "sg:classifiers":[
        {
            "category":"Farming",
            "subcategory":"Dairy Farm",
            "type":"Manufacturing & Wholesale Goods"
        }
    ],
    "sg:phone":"+44 1305 264214",
    "sg:postcode":"DT2 9TY",
    "sg:province":"Dorset",
    "wof:name":"Wrackleford Farms Ltd.",
    "wof:placetype":"venue"
},
  "geometry": {"coordinates":[-2.496254,50.743633],"type":"Point"}
}