{
  "type": "Feature",
  "properties": {
    "addr:full":"1 Sefton Avenue, Lipson Vale Plymouth Devon PL4 7HB",
    "addr:housenumber":"1",
    "addr:postcode":"pl4 7hb",
    "addr:street":"Sefton Avenue Lipson Vale",
    "iso:country":"GB",
    "sg:address":"1 Sefton Avenue, Lipson Vale",
    "sg:city":"Plymouth",
    "sg:classifiers":[
        {
            "category":"Personal",
            "subcategory":"Beauty Salon",
            "type":"Services"
        }
    ],
    "sg:postcode":"PL4 7HB",
    "sg:province":"Devon",
    "sg:tags":[
        "unisex",
        "hairdresser"
    ],
    "wof:name":"Ultra Images",
    "wof:placetype":"venue"
},
  "geometry": {"coordinates":[-4.120523,50.380756],"type":"Point"}
}