{
  "type": "Feature",
  "properties": {
    "addr:full":"12 Grasmere Avenue, Green Lane Coventry Warwickshire CV3 6AY",
    "addr:housenumber":"12",
    "addr:postcode":"cv3 6ay",
    "addr:street":"Grasmere Avenue Green Lane",
    "iso:country":"GB",
    "sg:address":"12 Grasmere Avenue, Green Lane",
    "sg:city":"Coventry",
    "sg:classifiers":[
        {
            "category":"Professional",
            "subcategory":"Engineering",
            "type":"Services"
        }
    ],
    "sg:phone":"+44 24 7641 7296",
    "sg:postcode":"CV3 6AY",
    "sg:province":"Warwickshire",
    "sg:tags":[
        "contractor",
        "electrical",
        "engineer"
    ],
    "wof:name":"T Spence Electrical",
    "wof:placetype":"venue"
},
  "geometry": {"coordinates":[-1.5313719511,52.3858032227],"type":"Point"}
}