{
  "type": "Feature",
  "properties": {
    "addr:full":"Speke Boulevard, Speke Liverpool Merseyside L24 9PN",
    "addr:postcode":"l24 9pn",
    "addr:street":"Speke Boulevard",
    "iso:country":"GB",
    "sg:address":"Speke Boulevard, Speke",
    "sg:city":"Liverpool",
    "sg:classifiers":[
        {
            "category":"Arena",
            "subcategory":"Sports Club",
            "type":"Entertainment"
        }
    ],
    "sg:phone":"+44 151 486 2811",
    "sg:postcode":"L24 9PN",
    "sg:province":"Merseyside",
    "wof:name":"METAL BOX ONIAN SPORTS & SOCIAL CLUB",
    "wof:placetype":"venue"
},
  "geometry": {"coordinates":[-2.8501338959,53.3485107422],"type":"Point"}
}