{
  "type": "Feature",
  "properties": {
    "iso:country":"GB",
    "sg:address":"150 East India Dock Road",
    "sg:city":"London",
    "sg:classifiers":[
        {
            "category":"Bars & Pubs",
            "type":"Food & Drink"
        }
    ],
    "sg:phone":"+44 20 7515 7215",
    "sg:postcode":"E14 0BP",
    "sg:province":"Greater London",
    "sg:tags":[
        "pubs",
        "inn"
    ],
    "wof:name":"The Manor Arms",
    "wof:placetype":"venue"
},
  "geometry": {"coordinates":[-0.0152519997,51.5112266541],"type":"Point"}
}