{
  "type": "Feature",
  "properties": {
    "iso:country":"GB",
    "sg:address":"Thornleigh",
    "sg:city":"Gainsborough",
    "sg:classifiers":[
        {
            "category":"Home & Garden",
            "subcategory":"Furniture",
            "type":"Retail Goods"
        }
    ],
    "sg:phone":"+44 1427 838259",
    "sg:postcode":"DN21 5PT",
    "sg:province":"Lincolnshire",
    "wof:name":"Thornleigh Pine",
    "wof:placetype":"venue"
},
  "geometry": {"coordinates":[-0.772768,53.395695],"type":"Point"}
}