{
  "type": "Feature",
  "properties": {
    "addr:full":"Barrow Hill Farm, Ramsdean Petersfield Hampshire GU32 1RW",
    "addr:postcode":"gu32 1rw",
    "addr:street":"Ramsdean Petersfield",
    "iso:country":"GB",
    "sg:address":"Barrow Hill Farm, Ramsdean",
    "sg:city":"Petersfield",
    "sg:classifiers":[
        {
            "category":"Farming",
            "subcategory":"Dairy Farm",
            "type":"Manufacturing & Wholesale Goods"
        }
    ],
    "sg:phone":"+44 1730 823461",
    "sg:postcode":"GU32 1RW",
    "sg:province":"Hampshire",
    "wof:name":"Dairy Unit",
    "wof:placetype":"venue"
},
  "geometry": {"coordinates":[-0.9963499904,50.9962768555],"type":"Point"}
}