{
  "type": "Feature",
  "properties": {
    "addr:full":"6 Headingley Gardens Nottingham Nottinghamshire NG8 5AX",
    "addr:housenumber":"6",
    "addr:postcode":"ng8 5ax",
    "addr:street":"Headingley Gardens",
    "iso:country":"GB",
    "sg:address":"6 Headingley Gardens",
    "sg:city":"Nottingham",
    "sg:classifiers":[
        {
            "category":"Building & Trades",
            "subcategory":"Construction",
            "type":"Services"
        }
    ],
    "sg:phone":"+44 115 929 9221",
    "sg:postcode":"NG8 5AX",
    "sg:province":"Nottinghamshire",
    "sg:tags":[
        "decorator",
        "painter"
    ],
    "wof:name":"Allen Decorators",
    "wof:placetype":"venue"
},
  "geometry": {"coordinates":[-1.188011,52.968277],"type":"Point"}
}