{
  "type": "Feature",
  "properties": {
    "iso:country":"GB",
    "sg:address":"13 Priory Lanes, Northgate",
    "sg:city":"Chichester",
    "sg:classifiers":[
        {
            "category":"Home & Garden",
            "subcategory":"Kitchen Supply",
            "type":"Retail Goods"
        }
    ],
    "sg:phone":"+44 1243 773121",
    "sg:postcode":"PO19 1AR",
    "sg:province":"West Sussex",
    "sg:tags":[
        "table"
    ],
    "wof:name":"Catercraft Cook Shops Ltd.",
    "wof:placetype":"venue"
},
  "geometry": {"coordinates":[-0.776676,50.838219],"type":"Point"}
}