{
  "type": "Feature",
  "properties": {
    "iso:country":"GB",
    "sg:address":"37 Old Kempshott Lane, Worting",
    "sg:city":"Basingstoke",
    "sg:classifiers":[
        {
            "category":"Wholesale",
            "subcategory":"Scrap",
            "type":"Manufacturing & Wholesale Goods"
        }
    ],
    "sg:phone":"+44 1256 328612",
    "sg:postcode":"RG22 5ET",
    "sg:province":"Hampshire",
    "sg:tags":[
        "waste",
        "metal"
    ],
    "wof:name":"Re-Use",
    "wof:placetype":"venue"
},
  "geometry": {"coordinates":[-1.136312,51.259285],"type":"Point"}
}