{
  "type": "Feature",
  "properties": {
    "addr:full":"Grove Rd Wantage Berkshire OX12 7BU",
    "addr:postcode":"ox12 7bu",
    "addr:street":"Grove Rd",
    "iso:country":"GB",
    "sg:address":"Grove Rd",
    "sg:city":"Wantage",
    "sg:classifiers":[
        {
            "category":"Freight",
            "type":"Transportation"
        }
    ],
    "sg:phone":"+44 1235 769764",
    "sg:postcode":"OX12 7BU",
    "sg:province":"Berkshire",
    "sg:tags":[
        "haulage",
        "road"
    ],
    "wof:name":"B O C Baker (Transport) Ltd",
    "wof:placetype":"venue"
},
  "geometry": {"coordinates":[-1.423141,51.593349],"type":"Point"}
}