{
  "type": "Feature",
  "properties": {
    "iso:country":"GB",
    "sg:address":"Derriford Road",
    "sg:city":"Plymouth",
    "sg:classifiers":[
        {
            "category":"Government",
            "subcategory":"Office",
            "type":"Public Place"
        }
    ],
    "sg:phone":"+44 1752 769663",
    "sg:postcode":"PL6 8BH",
    "sg:province":"Devon",
    "sg:tags":[
        "education",
        "agency",
        "authority"
    ],
    "wof:name":"Plymouth City Council",
    "wof:placetype":"venue"
},
  "geometry": {"coordinates":[-4.108934,50.418251],"type":"Point"}
}