{
  "type": "Feature",
  "properties": {
    "addr:full":"Elmsmere Court, Blackhills Lane Swansea Swansea SA2 7JN",
    "addr:postcode":"sa2 7jn",
    "addr:street":"Elmsmere Court Blackhills Lane",
    "iso:country":"GB",
    "sg:address":"Elmsmere Court, Blackhills Lane",
    "sg:city":"Swansea",
    "sg:classifiers":[
        {
            "category":"Building & Trades",
            "subcategory":"Landscaping Services",
            "type":"Services"
        }
    ],
    "sg:postcode":"SA2 7JN",
    "sg:province":"Swansea",
    "sg:tags":[
        "landscape",
        "contractor"
    ],
    "wof:name":"Astute Landscapes",
    "wof:placetype":"venue"
},
  "geometry": {"coordinates":[-4.055391,51.602604],"type":"Point"}
}