{
  "type": "Feature",
  "properties": {
    "iso:country":"GB",
    "sg:address":"59 Blackwell Road",
    "sg:city":"King's Langley",
    "sg:classifiers":[
        {
            "category":"Professional",
            "subcategory":"Employment Agencies",
            "type":"Services"
        }
    ],
    "sg:postcode":"WD4 8NE",
    "sg:province":"Hertfordshire",
    "sg:tags":[
        "pair",
        "au"
    ],
    "wof:name":"The Home From Home Au-Pair Agency",
    "wof:placetype":"venue"
},
  "geometry": {"coordinates":[-0.4460180104,51.7121925354],"type":"Point"}
}