{
  "type": "Feature",
  "properties": {
    "iso:country":"GB",
    "sg:address":"12A Eccleston Street Westminster",
    "sg:city":"London",
    "sg:classifiers":[
        {
            "category":"Professional",
            "subcategory":"Computer Services",
            "type":"Services"
        }
    ],
    "sg:postcode":"SW1W 9LT",
    "sg:tags":[
        "kramaley",
        "social-games",
        "facebook-games"
    ],
    "sg:website":"http://www.kramaley.com",
    "wof:name":"Kramaley Games",
    "wof:placetype":"venue"
},
  "geometry": {"coordinates":[-0.1479318,51.4944999],"type":"Point"}
}