{
  "type": "Feature",
  "properties": {
    "iso:country":"GB",
    "sg:address":"833 Bradshaw Road, Turton",
    "sg:city":"Bolton",
    "sg:classifiers":[
        {
            "category":"Building & Trades",
            "subcategory":"Construction",
            "type":"Services"
        }
    ],
    "sg:phone":"+44 1204 853267",
    "sg:postcode":"BL7 0HR",
    "sg:province":"Lancashire",
    "sg:tags":[
        "decorator",
        "painter"
    ],
    "wof:name":"Gordon Markland",
    "wof:placetype":"venue"
},
  "geometry": {"coordinates":[-2.3986389637,53.6379508972],"type":"Point"}
}