{
  "type": "Feature",
  "properties": {
    "addr:full":"70 St Albans Rd Watford Hertfordshire WD1 1RP",
    "addr:housenumber":"70",
    "addr:postcode":"wd1 1rp",
    "addr:street":"St Albans Rd",
    "iso:country":"GB",
    "sg:address":"70 St Albans Rd",
    "sg:city":"Watford",
    "sg:classifiers":[
        {
            "category":"Banks & Credit Unions",
            "subcategory":"Financial Services",
            "type":"Services"
        }
    ],
    "sg:phone":"+44 1923 233244",
    "sg:postcode":"WD1 1RP",
    "sg:province":"Hertfordshire",
    "sg:tags":[
        "claim",
        "assessor"
    ],
    "wof:name":"Turnamms Assessors",
    "wof:placetype":"venue"
},
  "geometry": {"coordinates":[-0.4001410007,51.6628417969],"type":"Point"}
}