{
  "type": "Feature",
  "properties": {
    "addr:full":"3 Market Street, Penkridge Stafford Shropshire ST19 5DH",
    "addr:housenumber":"3",
    "addr:postcode":"st19 5dh",
    "addr:street":"Market Street",
    "iso:country":"GB",
    "sg:address":"3 Market Street, Penkridge",
    "sg:city":"Stafford",
    "sg:classifiers":[
        {
            "category":"Shopping",
            "subcategory":"Gifts & Souvenirs",
            "type":"Retail Goods"
        }
    ],
    "sg:phone":"+44 1785 714115",
    "sg:postcode":"ST19 5DH",
    "sg:province":"Shropshire",
    "sg:tags":[
        "shop"
    ],
    "wof:name":"Giftique",
    "wof:placetype":"venue"
},
  "geometry": {"coordinates":[-2.11634,52.722607],"type":"Point"}
}