{
  "type": "Feature",
  "properties": {
    "addr:full":"119 High St Staines Berkshire TW18 4PD",
    "addr:housenumber":"119",
    "addr:postcode":"tw18 4pd",
    "addr:street":"High St",
    "iso:country":"GB",
    "sg:address":"119 High St",
    "sg:city":"Staines",
    "sg:classifiers":[
        {
            "category":"Farming",
            "subcategory":"Fish & Marine Products",
            "type":"Manufacturing & Wholesale Goods"
        }
    ],
    "sg:phone":"+44 1784 452278",
    "sg:postcode":"TW18 4PD",
    "sg:province":"Berkshire",
    "sg:tags":[
        "fishmonger"
    ],
    "wof:name":"Bridge Fisheries",
    "wof:placetype":"venue"
},
  "geometry": {"coordinates":[-0.5086680055,51.434967041],"type":"Point"}
}