{
  "type": "Feature",
  "properties": {
    "addr:full":"Harbour Point, Rye Harbour Rye East Sussex TN31 7TU",
    "addr:postcode":"tn31 7tu",
    "iso:country":"GB",
    "sg:address":"Harbour Point, Rye Harbour",
    "sg:city":"Rye",
    "sg:classifiers":[
        {
            "category":"Utilities",
            "subcategory":"Natural Gas",
            "type":"Services"
        }
    ],
    "sg:phone":"+44 1797 225797",
    "sg:postcode":"TN31 7TU",
    "sg:province":"East Sussex",
    "sg:tags":[
        "weather"
    ],
    "wof:name":"Weathernews U K  Ltd.",
    "wof:placetype":"venue"
},
  "geometry": {"coordinates":[0.7617750168,50.9381065369],"type":"Point"}
}