{
  "type": "Feature",
  "properties": {
    "iso:country":"GB",
    "sg:address":"244 Commercial Way",
    "sg:city":"London",
    "sg:classifiers":[
        {
            "category":"Autos & Motor Vehicles",
            "subcategory":"Auto Supplies",
            "type":"Retail Goods"
        }
    ],
    "sg:postcode":"SE15 1PU",
    "sg:province":"Greater London",
    "sg:tags":[
        "rubber",
        "tyre"
    ],
    "wof:name":"Brogden,D,",
    "wof:placetype":"venue"
},
  "geometry": {"coordinates":[-0.06438,51.478821],"type":"Point"}
}