{
  "type": "Feature",
  "properties": {
    "addr:full":"The Woodlands, Malthouse La Shipston-on-stour Warwickshire CV36 5JL",
    "addr:postcode":"cv36 5jl",
    "iso:country":"GB",
    "sg:address":"The Woodlands, Malthouse La",
    "sg:city":"Shipston-on-stour",
    "sg:classifiers":[
        {
            "category":"Manufacturing",
            "subcategory":"Wood Products",
            "type":"Manufacturing & Wholesale Goods"
        },
        {
            "category":"Building & Trades",
            "subcategory":"Construction",
            "type":"Services"
        }
    ],
    "sg:postcode":"CV36 5JL",
    "sg:province":"Warwickshire",
    "sg:tags":[
        "joinery",
        "sawmill",
        "shaving"
    ],
    "wof:name":"Caswell,Richard,",
    "wof:placetype":"venue"
},
  "geometry": {"coordinates":[-1.5686240196,52.0284729004],"type":"Point"}
}