{
  "type": "Feature",
  "properties": {
    "addr:full":"36 Red Hill Gro Birmingham West Midlands B38 9RZ",
    "addr:housenumber":"36",
    "addr:postcode":"b38 9rz",
    "addr:street":"Red Hill Gro",
    "iso:country":"GB",
    "sg:address":"36 Red Hill Gro",
    "sg:city":"Birmingham",
    "sg:classifiers":[
        {
            "category":"Building & Trades",
            "subcategory":"Construction",
            "type":"Services"
        }
    ],
    "sg:phone":"+44 121 458 6315",
    "sg:postcode":"B38 9RZ",
    "sg:province":"West Midlands",
    "sg:tags":[
        "roofing"
    ],
    "wof:name":"Hughes Felt Roofing",
    "wof:placetype":"venue"
},
  "geometry": {"coordinates":[-1.934894,52.391857],"type":"Point"}
}