{
  "type": "Feature",
  "properties": {
    "addr:full":"Alexandra Rd Liverpool Merseyside L22 1RJ",
    "addr:postcode":"l22 1rj",
    "addr:street":"Alexandra Rd",
    "iso:country":"GB",
    "sg:address":"Alexandra Rd",
    "sg:city":"Liverpool",
    "sg:classifiers":[
        {
            "category":"Building & Trades",
            "subcategory":"Construction",
            "type":"Services"
        }
    ],
    "sg:phone":"+44 151 495 1234",
    "sg:postcode":"L22 1RJ",
    "sg:province":"Merseyside",
    "sg:tags":[
        "roofing"
    ],
    "wof:name":"A & A Kirby Roofing",
    "wof:placetype":"venue"
},
  "geometry": {"coordinates":[-3.02272892,53.4716453552],"type":"Point"}
}