{
  "type": "Feature",
  "properties": {
    "iso:country":"GB",
    "sg:address":"48 Brown Street",
    "sg:city":"Dundee",
    "sg:classifiers":[
        {
            "category":"Wholesale",
            "subcategory":"Scrap",
            "type":"Manufacturing & Wholesale Goods"
        }
    ],
    "sg:phone":"+44 1382 322734",
    "sg:postcode":"DD1 5DT",
    "sg:province":"Dundee City",
    "sg:tags":[
        "waste",
        "metal"
    ],
    "wof:name":"Alex Thomson & Sons (Verdant)",
    "wof:placetype":"venue"
},
  "geometry": {"coordinates":[-2.980943,56.462921],"type":"Point"}
}