{
  "type": "Feature",
  "properties": {
    "addr:full":"Unit 8, Atlas Mews Hackney Greater London E8 2NE",
    "addr:housenumber":"unit 8",
    "addr:postcode":"e8 2ne",
    "addr:street":"Atlas Mews",
    "iso:country":"GB",
    "sg:address":"Unit 8, Atlas Mews",
    "sg:city":"Hackney",
    "sg:classifiers":[
        {
            "category":"Professional",
            "subcategory":"Business Services",
            "type":"Services"
        }
    ],
    "sg:phone":"+44 20 7254 9884",
    "sg:postcode":"E8 2NE",
    "sg:province":"Greater London",
    "sg:tags":[
        "distributor",
        "film"
    ],
    "wof:name":"Gideon Koppel",
    "wof:placetype":"venue"
},
  "geometry": {"coordinates":[-0.070913,51.5467],"type":"Point"}
}