{
  "type": "Feature",
  "properties": {
    "addr:full":"24 Swan Street, Kingsclere Newbury Berkshire RG20 5PJ",
    "addr:housenumber":"24",
    "addr:postcode":"rg20 5pj",
    "addr:street":"Swan Street",
    "iso:country":"GB",
    "sg:address":"24 Swan Street, Kingsclere",
    "sg:city":"Newbury",
    "sg:classifiers":[
        {
            "category":"Education",
            "subcategory":"Dance Studio",
            "type":"Public Place"
        }
    ],
    "sg:phone":"+44 1635 299797",
    "sg:postcode":"RG20 5PJ",
    "sg:province":"Berkshire",
    "sg:tags":[
        "school",
        "dancing"
    ],
    "wof:name":"J L D School Of Dancing",
    "wof:placetype":"venue"
},
  "geometry": {"coordinates":[-1.24877,51.323399],"type":"Point"}
}