{
  "type": "Feature",
  "properties": {
    "addr:full":"14b Naseby Rd, Birmingham West Midlands B8 3HE",
    "addr:housenumber":"14b",
    "addr:postcode":"b8 3he",
    "addr:street":"Naseby Rd",
    "iso:country":"GB",
    "sg:address":"14b Naseby Rd,",
    "sg:city":"Birmingham",
    "sg:classifiers":[
        {
            "category":"Building & Trades",
            "subcategory":"Construction",
            "type":"Services"
        }
    ],
    "sg:postcode":"B8 3HE",
    "sg:province":"West Midlands",
    "sg:tags":[
        "joiner",
        "carpenter"
    ],
    "wof:name":"Azzad,Mohamed,",
    "wof:placetype":"venue"
},
  "geometry": {"coordinates":[-1.8454020023,52.4884109497],"type":"Point"}
}