{
  "type": "Feature",
  "properties": {
    "addr:full":"Church House Wakefield West Yorkshire WF1 1LP",
    "addr:postcode":"wf1 1lp",
    "addr:street":"West",
    "iso:country":"GB",
    "sg:address":"Church House",
    "sg:city":"Wakefield",
    "sg:classifiers":[
        {
            "category":"Organizations",
            "subcategory":"Religious Organization",
            "type":"Services"
        }
    ],
    "sg:phone":"+44 1924 371802",
    "sg:postcode":"WF1 1LP",
    "sg:province":"West Yorkshire",
    "sg:tags":[
        "organisation"
    ],
    "wof:name":"The Wakefield Diocesan Council of Education Ltd.",
    "wof:placetype":"venue"
},
  "geometry": {"coordinates":[-1.499019,53.68111],"type":"Point"}
}