{
  "type": "Feature",
  "properties": {
    "addr:full":"King Street Burton-on-trent Derbyshire DE14 3AG",
    "addr:postcode":"de14 3ag",
    "addr:street":"King Street",
    "iso:country":"GB",
    "sg:address":"King Street",
    "sg:city":"Burton-on-trent",
    "sg:classifiers":[
        {
            "category":"Health Services",
            "subcategory":"Doctor",
            "type":"Services"
        },
        {
            "category":"Health Services",
            "subcategory":"Clinic",
            "type":"Services"
        }
    ],
    "sg:postcode":"DE14 3AG",
    "sg:province":"Derbyshire",
    "sg:tags":[
        "nh",
        "practitioners"
    ],
    "wof:name":"The Surgery",
    "wof:placetype":"venue"
},
  "geometry": {"coordinates":[-1.6392790079,52.7972488403],"type":"Point"}
}