{
  "type": "Feature",
  "properties": {
    "iso:country":"GB",
    "sg:address":"1 Stoneleigh Rd",
    "sg:city":"Ilford",
    "sg:classifiers":[
        {
            "category":"Place Of Worship",
            "type":"Public Place"
        }
    ],
    "sg:phone":"+44 20 8550 4540",
    "sg:postcode":"IG5 0JB",
    "sg:province":"Essex",
    "wof:name":"St John Vianney R C Church",
    "wof:placetype":"venue"
},
  "geometry": {"coordinates":[0.0541950017,51.5867462158],"type":"Point"}
}