{
  "type": "Feature",
  "properties": {
    "addr:full":"19 Codrington Court London Greater London SE16 5FS",
    "addr:housenumber":"19",
    "addr:postcode":"se16 5fs",
    "addr:street":"Codrington Court",
    "iso:country":"GB",
    "sg:address":"19 Codrington Court",
    "sg:city":"London",
    "sg:classifiers":[
        {
            "category":"Professional",
            "subcategory":"Management & Consulting",
            "type":"Services"
        }
    ],
    "sg:phone":"+44 20 7394 8411",
    "sg:postcode":"SE16 5FS",
    "sg:province":"Greater London",
    "sg:tags":[
        "consultant",
        "training"
    ],
    "wof:name":"Spectrum Training & Development Ltd.",
    "wof:placetype":"venue"
},
  "geometry": {"coordinates":[-0.0400520004,51.4479179382],"type":"Point"}
}