{
  "type": "Feature",
  "properties": {
    "iso:country":"GB",
    "sg:address":"Pink Bank Lane, Longsight",
    "sg:city":"Manchester",
    "sg:classifiers":[
        {
            "category":"Professional",
            "subcategory":"Engineering",
            "type":"Services"
        }
    ],
    "sg:phone":"+44 161 231 1241",
    "sg:postcode":"M12 5GH",
    "sg:province":"Greater Manchester",
    "wof:name":"E V Leonard & Co. (Handling Devices) Ltd.",
    "wof:placetype":"venue"
},
  "geometry": {"coordinates":[-2.191729,53.45948],"type":"Point"}
}