{
  "type": "Feature",
  "properties": {
    "addr:full":"102 Ockford Road Godalming Surrey GU7 1RG",
    "addr:housenumber":"102",
    "addr:postcode":"gu7 1rg",
    "addr:street":"Ockford Road",
    "iso:country":"GB",
    "sg:address":"102 Ockford Road",
    "sg:city":"Godalming",
    "sg:classifiers":[
        {
            "category":"Building & Trades",
            "subcategory":"Construction",
            "type":"Services"
        }
    ],
    "sg:phone":"+44 1483 424959",
    "sg:postcode":"GU7 1RG",
    "sg:province":"Surrey",
    "sg:tags":[
        "builder"
    ],
    "wof:name":"Cordery Build Ltd.",
    "wof:placetype":"venue"
},
  "geometry": {"coordinates":[-0.6218839884,51.1818313599],"type":"Point"}
}