{
  "type": "Feature",
  "properties": {
    "addr:full":"12 Cow Pasture Road Ilkley North Yorkshire LS29 8SR",
    "addr:housenumber":"12",
    "addr:postcode":"ls29 8sr",
    "addr:street":"Cow Pasture Road",
    "iso:country":"GB",
    "sg:address":"12 Cow Pasture Road",
    "sg:city":"Ilkley",
    "sg:classifiers":[
        {
            "category":"Personal",
            "subcategory":"Beauty Salon",
            "type":"Services"
        },
        {
            "category":"Personal",
            "subcategory":"Barber",
            "type":"Services"
        }
    ],
    "sg:phone":"+44 1943 432009",
    "sg:postcode":"LS29 8SR",
    "sg:province":"North Yorkshire",
    "sg:tags":[
        "unisex",
        "hairdresser"
    ],
    "wof:name":"The Hairshop",
    "wof:placetype":"venue"
},
  "geometry": {"coordinates":[-1.819736,53.924072],"type":"Point"}
}