{
  "type": "Feature",
  "properties": {
    "addr:full":"Nunnington Court, Nunnington Hereford Herefordshire HR1 3NJ",
    "addr:postcode":"hr1 3nj",
    "addr:street":"Nunnington",
    "iso:country":"GB",
    "sg:address":"Nunnington Court, Nunnington",
    "sg:city":"Hereford",
    "sg:classifiers":[
        {
            "category":"Farming",
            "subcategory":"Livestock Farm",
            "type":"Manufacturing & Wholesale Goods"
        }
    ],
    "sg:phone":"+44 1432 850248",
    "sg:postcode":"HR1 3NJ",
    "sg:province":"Herefordshire",
    "sg:tags":[
        "others"
    ],
    "wof:name":"B L Williams & Son",
    "wof:placetype":"venue"
},
  "geometry": {"coordinates":[-2.65757,52.085442],"type":"Point"}
}