{
  "type": "Feature",
  "properties": {
    "addr:full":"Unit 7 Main Street, Cleland Motherwell North Lanarkshire ML1 5QW",
    "addr:housenumber":"unit 7",
    "addr:postcode":"ml1 5qw",
    "addr:street":"Main Street",
    "iso:country":"GB",
    "sg:address":"Unit 7 Main Street, Cleland",
    "sg:city":"Motherwell",
    "sg:classifiers":[
        {
            "category":"Food & Beverages",
            "subcategory":"Fruits & Vegetables",
            "type":"Retail Goods"
        }
    ],
    "sg:phone":"+44 1698 860368",
    "sg:postcode":"ML1 5QW",
    "sg:province":"North Lanarkshire",
    "sg:tags":[
        "greengrocer"
    ],
    "wof:name":"Fruit Corner",
    "wof:placetype":"venue"
},
  "geometry": {"coordinates":[-3.913539,55.803085],"type":"Point"}
}