{
  "type": "Feature",
  "properties": {
    "iso:country":"GB",
    "sg:address":"140 Higher Road, Urmston",
    "sg:city":"Manchester",
    "sg:classifiers":[
        {
            "category":"Professional",
            "subcategory":"Engineering",
            "type":"Services"
        },
        {
            "category":"Building & Trades",
            "subcategory":"Construction",
            "type":"Services"
        }
    ],
    "sg:phone":"+44 161 747 7077",
    "sg:postcode":"M41 9AZ",
    "sg:province":"Cheshire",
    "sg:tags":[
        "fork",
        "lift",
        "truck"
    ],
    "wof:name":"Kin Ltd.",
    "wof:placetype":"venue"
},
  "geometry": {"coordinates":[-2.344861,53.448448],"type":"Point"}
}