{
  "type": "Feature",
  "properties": {
    "addr:full":"John Kirk House, 25 Pearl Close Beckton London Greater London E6 5QY",
    "addr:housenumber":"25",
    "addr:postcode":"e6 5qy",
    "addr:street":"Pearl Close",
    "iso:country":"GB",
    "sg:address":"John Kirk House, 25 Pearl Close Beckton",
    "sg:city":"London",
    "sg:classifiers":[
        {
            "category":"Health Services",
            "subcategory":"Nursing And Care Facility",
            "type":"Services"
        },
        {
            "category":"Social Services",
            "subcategory":"Retirement Home",
            "type":"Services"
        }
    ],
    "sg:phone":"+44 20 7511 6636",
    "sg:postcode":"E6 5QY",
    "sg:province":"Greater London",
    "sg:tags":[
        "residential"
    ],
    "wof:name":"Shaftesbury Housing",
    "wof:placetype":"venue"
},
  "geometry": {"coordinates":[0.060655,51.512913],"type":"Point"}
}