{
  "type": "Feature",
  "properties": {
    "addr:full":"82 Temple Avenue Dagenham Essex RM8 1LS",
    "addr:housenumber":"82",
    "addr:postcode":"rm8 1ls",
    "addr:street":"Temple Avenue",
    "iso:country":"GB",
    "sg:address":"82 Temple Avenue",
    "sg:city":"Dagenham",
    "sg:classifiers":[
        {
            "category":"Shopping",
            "subcategory":"Musical Instruments",
            "type":"Retail Goods"
        }
    ],
    "sg:postcode":"RM8 1LS",
    "sg:province":"Essex",
    "wof:name":"R M Marquis",
    "wof:placetype":"venue"
},
  "geometry": {"coordinates":[0.14993,51.564354],"type":"Point"}
}