{
  "type": "Feature",
  "properties": {
    "addr:full":"Pear Tree Cottage, Nomansland Tiverton Devon EX16 8NN",
    "addr:postcode":"ex16 8nn",
    "addr:street":"Nomansland",
    "iso:country":"GB",
    "sg:address":"Pear Tree Cottage, Nomansland",
    "sg:city":"Tiverton",
    "sg:classifiers":[
        {
            "category":"Building & Trades",
            "subcategory":"Construction",
            "type":"Services"
        }
    ],
    "sg:phone":"+44 1884 860534",
    "sg:postcode":"EX16 8NN",
    "sg:province":"Devon",
    "sg:tags":[
        "demolition",
        "contractor"
    ],
    "wof:name":"H J Dismantling",
    "wof:placetype":"venue"
},
  "geometry": {"coordinates":[-3.652964,50.912041],"type":"Point"}
}