{
  "type": "Feature",
  "properties": {
    "iso:country":"GB",
    "sg:address":"96 London Road, Southborough",
    "sg:city":"Tunbridge Wells",
    "sg:classifiers":[
        {
            "category":"Cafe",
            "type":"Food & Drink"
        }
    ],
    "sg:phone":"+44 1892 546819",
    "sg:postcode":"TN4 0PW",
    "sg:province":"Kent",
    "sg:tags":[
        "tea",
        "snack",
        "bar",
        "room"
    ],
    "wof:name":"The Lunch Box",
    "wof:placetype":"venue"
},
  "geometry": {"coordinates":[0.259848,51.156036],"type":"Point"}
}