{
  "type": "Feature",
  "properties": {
    "iso:country":"GB",
    "sg:address":"32 Gaen St",
    "sg:city":"Abertillery",
    "sg:classifiers":[
        {
            "category":"Building & Trades",
            "subcategory":"Construction",
            "type":"Services"
        }
    ],
    "sg:phone":"+44 1495 212707",
    "sg:postcode":"NP3 1PT",
    "sg:province":"Blaenau Gwent",
    "sg:tags":[
        "roofing"
    ],
    "wof:name":"Sureseal",
    "wof:placetype":"venue"
},
  "geometry": {"coordinates":[-3.136823,51.735912],"type":"Point"}
}