{
  "type": "Feature",
  "properties": {
    "iso:country":"GB",
    "sg:address":"2a Bracken Road",
    "sg:city":"Maidenhead",
    "sg:classifiers":[
        {
            "category":"Professional",
            "subcategory":"Computer Services",
            "type":"Services"
        }
    ],
    "sg:postcode":"SL6 3EF",
    "sg:tags":[
        "photo-sharing-community",
        "digital-photography-blogs",
        "photoblog",
        "online-photo-sharing",
        "digital-photography",
        "photo-gallery"
    ],
    "sg:website":"http://www.pixyblog.com",
    "wof:name":"Pixy Ltd",
    "wof:placetype":"venue"
},
  "geometry": {"coordinates":[-0.742987,51.508466],"type":"Point"}
}