{
  "type": "Feature",
  "properties": {
    "iso:country":"GB",
    "sg:address":"35 Exeforde Avenue",
    "sg:city":"Ashford",
    "sg:classifiers":[
        {
            "category":"Organizations",
            "subcategory":"Membership Organization",
            "type":"Services"
        }
    ],
    "sg:postcode":"TW15 2EF",
    "sg:province":"Greater London",
    "sg:tags":[
        "club"
    ],
    "wof:name":"Hounslow & District Aquarists Society",
    "wof:placetype":"venue"
},
  "geometry": {"coordinates":[-0.4579730034,51.4334487915],"type":"Point"}
}