{
  "type": "Feature",
  "properties": {
    "addr:full":"1 Elderwood Drive Bristol Gloucestershire BS30 9YA",
    "addr:housenumber":"1",
    "addr:postcode":"bs30 9ya",
    "addr:street":"Elderwood Drive",
    "iso:country":"GB",
    "sg:address":"1 Elderwood Drive",
    "sg:city":"Bristol",
    "sg:classifiers":[
        {
            "category":"Building & Trades",
            "subcategory":"Plumbing",
            "type":"Services"
        }
    ],
    "sg:postcode":"BS30 9YA",
    "sg:province":"Gloucestershire",
    "sg:tags":[
        "heating"
    ],
    "wof:name":"S B Butterfield",
    "wof:placetype":"venue"
},
  "geometry": {"coordinates":[-2.486806,51.440033],"type":"Point"}
}