{
  "type": "Feature",
  "properties": {
    "iso:country":"GB",
    "sg:address":"253 New Road Side, Horsforth",
    "sg:city":"Leeds",
    "sg:classifiers":[
        {
            "category":"Travel",
            "subcategory":"Travel Agent",
            "type":"Entertainment"
        }
    ],
    "sg:phone":"+44 113 259 0266",
    "sg:postcode":"LS18 4DR",
    "sg:province":"West Yorkshire",
    "wof:name":"Co. Travel Ltd.",
    "wof:placetype":"venue"
},
  "geometry": {"coordinates":[-1.639522,53.834335],"type":"Point"}
}