{
  "type": "Feature",
  "properties": {
    "iso:country":"GB",
    "sg:address":"39 Bedford Square",
    "sg:city":"London",
    "sg:classifiers":[
        {
            "category":"Real Estate",
            "subcategory":"Real Estate Operator",
            "type":"Services"
        }
    ],
    "sg:phone":"+44 20 7631 2002",
    "sg:postcode":"WC1B 3EG",
    "sg:province":"Greater London",
    "sg:tags":[
        "letting",
        "agent"
    ],
    "wof:name":"Central London Apartments Ltd.",
    "wof:placetype":"venue"
},
  "geometry": {"coordinates":[-0.128742,51.518242],"type":"Point"}
}