{
  "type": "Feature",
  "properties": {
    "iso:country":"GB",
    "sg:address":"17 Mkt Sq",
    "sg:city":"London",
    "sg:classifiers":[
        {
            "category":"Food & Beverages",
            "subcategory":"Fruits & Vegetables",
            "type":"Retail Goods"
        }
    ],
    "sg:postcode":"E14 6AQ",
    "sg:province":"Greater London",
    "sg:tags":[
        "greengrocer"
    ],
    "wof:name":"Dave's Greengrocers",
    "wof:placetype":"venue"
},
  "geometry": {"coordinates":[-0.0150499996,51.5121612549],"type":"Point"}
}