{
  "type": "Feature",
  "properties": {
    "addr:full":"58 Station Road, Sandiacre Nottingham Derbyshire NG10 5AS",
    "addr:housenumber":"58",
    "addr:postcode":"ng10 5as",
    "addr:street":"Station Road",
    "iso:country":"GB",
    "sg:address":"58 Station Road, Sandiacre",
    "sg:city":"Nottingham",
    "sg:classifiers":[
        {
            "category":"Banks & Credit Unions",
            "subcategory":"Financial Services",
            "type":"Services"
        }
    ],
    "sg:phone":"+44 115 939 6969",
    "sg:postcode":"NG10 5AS",
    "sg:province":"Derbyshire",
    "sg:tags":[
        "adviser"
    ],
    "wof:name":"Flinders Gosrani Partnership",
    "wof:placetype":"venue"
},
  "geometry": {"coordinates":[-1.284598,52.922619],"type":"Point"}
}