{
  "type": "Feature",
  "properties": {
    "iso:country":"GB",
    "sg:address":"45 Cobham Road, Ferndown Industrial Estate",
    "sg:city":"Wimborne",
    "sg:classifiers":[
        {
            "category":"Professional",
            "subcategory":"Engineering",
            "type":"Services"
        }
    ],
    "sg:postcode":"BH21 7QZ",
    "sg:province":"Dorset",
    "wof:name":"Be Realisations Ltd.",
    "wof:placetype":"venue"
},
  "geometry": {"coordinates":[-1.91521,50.812847],"type":"Point"}
}