{
  "type": "Feature",
  "properties": {
    "iso:country":"GB",
    "sg:address":"119 Main Street, Horsley Woodho",
    "sg:city":"Ilkeston",
    "sg:classifiers":[
        {
            "category":"Recreation",
            "type":"Entertainment"
        }
    ],
    "sg:phone":"+44 1332 781420",
    "sg:postcode":"DE7 6AX",
    "sg:province":"Derbyshire",
    "sg:tags":[
        "outdoor",
        "pursuit"
    ],
    "wof:name":"Derwent Activities",
    "wof:placetype":"venue"
},
  "geometry": {"coordinates":[-1.394818,52.993423],"type":"Point"}
}