{
  "type": "Feature",
  "properties": {
    "iso:country":"GB",
    "sg:address":"The Depot, Crook Street",
    "sg:city":"Bolton",
    "sg:classifiers":[
        {
            "category":"Arena",
            "subcategory":"Sports Club",
            "type":"Entertainment"
        }
    ],
    "sg:phone":"+44 1204 393637",
    "sg:postcode":"BL3 6AS",
    "sg:province":"Lancashire",
    "wof:name":"G M T Sports & Social Club",
    "wof:placetype":"venue"
},
  "geometry": {"coordinates":[-2.42672,53.573502],"type":"Point"}
}