{
  "type": "Feature",
  "properties": {
    "iso:country":"GB",
    "sg:address":"Royal Albert Memorial Museum, Queen Street",
    "sg:city":"Exeter",
    "sg:classifiers":[
        {
            "category":"Museum",
            "subcategory":"Art Museum",
            "type":"Entertainment"
        }
    ],
    "sg:phone":"+44 1392 265858",
    "sg:postcode":"EX4 3RX",
    "sg:province":"Devon",
    "sg:tags":[
        "gallery"
    ],
    "wof:name":"Exeter City Museums & Art Gallery",
    "wof:placetype":"venue"
},
  "geometry": {"coordinates":[-3.53226,50.72493],"type":"Point"}
}