{
  "type": "Feature",
  "properties": {
    "addr:full":"29-31 Rose Street Aberdeen Aberdeen City AB10 1UB",
    "addr:housenumber":"29-31",
    "addr:postcode":"ab10 1ub",
    "addr:street":"Rose Street",
    "iso:country":"GB",
    "sg:address":"29-31 Rose Street",
    "sg:city":"Aberdeen",
    "sg:classifiers":[
        {
            "category":"Shopping",
            "subcategory":"Department Store",
            "type":"Retail Goods"
        },
        {
            "category":"Shopping",
            "subcategory":"Bicycles & Sporting Goods",
            "type":"Retail Goods"
        },
        {
            "category":"Sports & Exercise",
            "subcategory":"Sports Center",
            "type":"Entertainment"
        }
    ],
    "sg:phone":"+44 1224 620100",
    "sg:postcode":"AB10 1UB",
    "sg:province":"Aberdeen City",
    "sg:tags":[
        "shop",
        "sale"
    ],
    "wof:name":"Thistle Sports",
    "wof:placetype":"venue"
},
  "geometry": {"coordinates":[-2.111518,57.144135],"type":"Point"}
}