{
  "type": "Feature",
  "properties": {
    "addr:full":"Hornsey, Collingwood Business Centre London Greater London N19 4PJ",
    "addr:postcode":"n19 4pj",
    "iso:country":"GB",
    "sg:address":"Hornsey, Collingwood Business Centre",
    "sg:city":"London",
    "sg:classifiers":[
        {
            "category":"Government",
            "subcategory":"Office",
            "type":"Public Place"
        }
    ],
    "sg:phone":"+44 20 7561 7800",
    "sg:postcode":"N19 4PJ",
    "sg:province":"Greater London",
    "sg:tags":[
        "inland",
        "revenue"
    ],
    "wof:name":"Inland Revenue",
    "wof:placetype":"venue"
},
  "geometry": {"coordinates":[-0.1238500029,51.5597114563],"type":"Point"}
}