{
  "type": "Feature",
  "properties": {
    "addr:full":"Derwent Business Centre, Clarke St Derby Derbyshire DE1 2BU",
    "addr:postcode":"de1 2bu",
    "addr:street":"Clarke St",
    "iso:country":"GB",
    "sg:address":"Derwent Business Centre, Clarke St",
    "sg:city":"Derby",
    "sg:classifiers":[
        {
            "category":"Professional",
            "subcategory":"Management & Consulting",
            "type":"Services"
        }
    ],
    "sg:postcode":"DE1 2BU",
    "sg:province":"Derbyshire",
    "sg:tags":[
        "marketing",
        "consultant"
    ],
    "wof:name":"Business Developement Associates",
    "wof:placetype":"venue"
},
  "geometry": {"coordinates":[-1.4688489437,52.928150177],"type":"Point"}
}