{
  "type": "Feature",
  "properties": {
    "addr:full":"Units 14, 16 & 17 Solent Trading Estate, Shamblehurst Lane South Southampton Hampshire SO30 2FQ",
    "addr:housenumber":"units;16 & 17",
    "addr:postcode":"so30 2fq",
    "addr:street":"Trading;Shamblehurst Lane South",
    "iso:country":"GB",
    "sg:address":"Units 14, 16 & 17 Solent Trading Estate, Shamblehurst Lane South",
    "sg:city":"Southampton",
    "sg:classifiers":[
        {
            "category":"Retail",
            "subcategory":"Repair Shop",
            "type":"Services"
        },
        {
            "category":"Home & Garden",
            "subcategory":"Kitchen Supply",
            "type":"Retail Goods"
        }
    ],
    "sg:phone":"+44 1489 789494",
    "sg:postcode":"SO30 2FQ",
    "sg:province":"Hampshire",
    "sg:tags":[
        "equipment",
        "catering"
    ],
    "wof:name":"H C E Ltd.",
    "wof:placetype":"venue"
},
  "geometry": {"coordinates":[-1.331328,50.913353],"type":"Point"}
}