{
  "type": "Feature",
  "properties": {
    "addr:full":"Main Rd, Kesgrave Ipswich Suffolk IP5 1AG",
    "addr:postcode":"ip5 1ag",
    "addr:street":"Main Rd",
    "iso:country":"GB",
    "sg:address":"Main Rd, Kesgrave",
    "sg:city":"Ipswich",
    "sg:classifiers":[
        {
            "category":"Autos & Motor Vehicles",
            "subcategory":"Fuel & Gas Station",
            "type":"Retail Goods"
        }
    ],
    "sg:phone":"+44 1473 622016",
    "sg:postcode":"IP5 1AG",
    "sg:province":"Suffolk",
    "sg:tags":[
        "petrol",
        "filling"
    ],
    "wof:name":"Kesgrave Autopoint",
    "wof:placetype":"venue"
},
  "geometry": {"coordinates":[1.2324999571,52.065826416],"type":"Point"}
}