{
  "type": "Feature",
  "properties": {
    "addr:full":"122 Kensington Church St Kensington Greater London W8 4BH",
    "addr:housenumber":"122",
    "addr:postcode":"w8 4bh",
    "addr:street":"Kensington Church St",
    "iso:country":"GB",
    "sg:address":"122 Kensington Church St",
    "sg:city":"Kensington",
    "sg:classifiers":[
        {
            "category":"Food & Beverages",
            "subcategory":"Bakery",
            "type":"Retail Goods"
        }
    ],
    "sg:phone":"+44 20 7229 2190",
    "sg:postcode":"W8 4BH",
    "sg:province":"Greater London",
    "sg:tags":[
        "baker"
    ],
    "wof:name":"Clarke'S Shop",
    "wof:placetype":"venue"
},
  "geometry": {"coordinates":[-0.194459,51.506931],"type":"Point"}
}