{
  "type": "Feature",
  "properties": {
    "addr:full":"33 High Street, Yeadon Leeds West Yorkshire LS19 7SP",
    "addr:housenumber":"33",
    "addr:postcode":"ls19 7sp",
    "addr:street":"High Street",
    "iso:country":"GB",
    "sg:address":"33 High Street, Yeadon",
    "sg:city":"Leeds",
    "sg:classifiers":[
        {
            "category":"Shopping",
            "subcategory":"Gifts & Souvenirs",
            "type":"Retail Goods"
        }
    ],
    "sg:phone":"+44 113 250 1214",
    "sg:postcode":"LS19 7SP",
    "sg:province":"West Yorkshire",
    "sg:tags":[
        "poster",
        "card"
    ],
    "wof:name":"Box of Cards",
    "wof:placetype":"venue"
},
  "geometry": {"coordinates":[-1.683445,53.866295],"type":"Point"}
}