{
  "type": "Feature",
  "properties": {
    "addr:full":"Care Of Royal Berkshire Hospital, Maternity Unit, Craven Road Reading Berkshire RG1 5AN",
    "addr:housenumber":"unit",
    "addr:postcode":"rg1 5an",
    "addr:street":"Craven Road",
    "iso:country":"GB",
    "sg:address":"Care Of Royal Berkshire Hospital, Maternity Unit, Craven Road",
    "sg:city":"Reading",
    "sg:classifiers":[
        {
            "category":"Shopping",
            "subcategory":"Baby Store",
            "type":"Retail Goods"
        }
    ],
    "sg:phone":"+44 118 975 3681",
    "sg:postcode":"RG1 5AN",
    "sg:province":"Berkshire",
    "sg:tags":[
        "nursery",
        "accessory"
    ],
    "wof:name":"Babycare",
    "wof:placetype":"venue"
},
  "geometry": {"coordinates":[-0.9630089998,51.4535217285],"type":"Point"}
}