{
  "type": "Feature",
  "properties": {
    "iso:country":"GB",
    "sg:address":"1 Avenue Parade, The Avenue",
    "sg:city":"Sunbury-on-thames",
    "sg:classifiers":[
        {
            "category":"Personal",
            "subcategory":"Beauty Salon",
            "type":"Services"
        }
    ],
    "sg:phone":"+44 1932 786444",
    "sg:postcode":"TW16 5HS",
    "sg:province":"Surrey",
    "sg:tags":[
        "unisex",
        "hairdresser"
    ],
    "wof:name":"A M Studios",
    "wof:placetype":"venue"
},
  "geometry": {"coordinates":[-0.40621,51.406425],"type":"Point"}
}