{
  "type": "Feature",
  "properties": {
    "addr:full":"Unit 7, The Textile Centre, Hindringham Rd Walsingham Norfolk NR22 6DR",
    "addr:housenumber":"unit 7",
    "addr:postcode":"nr22 6dr",
    "addr:street":"The;Hindringham Rd",
    "iso:country":"GB",
    "sg:address":"Unit 7, The Textile Centre, Hindringham Rd",
    "sg:city":"Walsingham",
    "sg:classifiers":[
        {
            "category":"Manufacturing",
            "subcategory":"Textiles",
            "type":"Manufacturing & Wholesale Goods"
        },
        {
            "category":"Home & Garden",
            "subcategory":"Carpets & Floor Coverings",
            "type":"Retail Goods"
        }
    ],
    "sg:phone":"+44 1328 820961",
    "sg:postcode":"NR22 6DR",
    "sg:province":"Norfolk",
    "sg:tags":[
        "merchant",
        "design",
        "oriental",
        "rug",
        "agent"
    ],
    "wof:name":"Murray Carpets",
    "wof:placetype":"venue"
},
  "geometry": {"coordinates":[0.886179,52.901119],"type":"Point"}
}