{
  "type": "Feature",
  "properties": {
    "addr:full":"South Street Crewe Cheshire CW2 6HL",
    "addr:postcode":"cw2 6hl",
    "addr:street":"South Street",
    "iso:country":"GB",
    "sg:address":"South Street",
    "sg:city":"Crewe",
    "sg:classifiers":[
        {
            "category":"Organizations",
            "subcategory":"Membership Organization",
            "type":"Services"
        }
    ],
    "sg:phone":"+44 1270 258165",
    "sg:postcode":"CW2 6HL",
    "sg:province":"Cheshire",
    "sg:tags":[
        "club"
    ],
    "wof:name":"South Street Snooker & Social Club",
    "wof:placetype":"venue"
},
  "geometry": {"coordinates":[-2.4377400875,53.0880699158],"type":"Point"}
}