{
  "type": "Feature",
  "properties": {
    "iso:country":"GB",
    "sg:address":"100 Hartfield Road",
    "sg:city":"Forest Row",
    "sg:classifiers":[
        {
            "category":"Place Of Worship",
            "subcategory":"Synagogue",
            "type":"Public Place"
        },
        {
            "category":"Building & Trades",
            "subcategory":"Construction",
            "type":"Services"
        }
    ],
    "sg:phone":"+44 7966 494783",
    "sg:postcode":"RH18 5LY",
    "sg:province":"East Sussex",
    "sg:tags":[
        "property",
        "joiner",
        "converter",
        "loft",
        "carpenter"
    ],
    "wof:name":"Space Unlimited",
    "wof:placetype":"venue"
},
  "geometry": {"coordinates":[0.05285,51.093956],"type":"Point"}
}