{
  "type": "Feature",
  "properties": {
    "iso:country":"GB",
    "sg:address":"23 Stapleton Avenue, Greasby",
    "sg:city":"Wirral",
    "sg:classifiers":[
        {
            "category":"Home & Garden",
            "subcategory":"Home Furnishings",
            "type":"Retail Goods"
        }
    ],
    "sg:postcode":"CH49 2QT",
    "sg:province":"Merseyside",
    "sg:tags":[
        "awning",
        "canopy",
        "blinds"
    ],
    "wof:name":"The Carolina Blind Co.",
    "wof:placetype":"venue"
},
  "geometry": {"coordinates":[-3.120067,53.379833],"type":"Point"}
}