{
  "type": "Feature",
  "properties": {
    "addr:full":"61 Castle Street Luton Bedfordshire LU1 3AG",
    "addr:housenumber":"61",
    "addr:postcode":"lu1 3ag",
    "addr:street":"Castle Street",
    "iso:country":"GB",
    "sg:address":"61 Castle Street",
    "sg:city":"Luton",
    "sg:classifiers":[
        {
            "category":"Personal",
            "subcategory":"Beauty Salon",
            "type":"Services"
        }
    ],
    "sg:phone":"+44 1582 721674",
    "sg:postcode":"LU1 3AG",
    "sg:province":"Bedfordshire",
    "sg:tags":[
        "ladies",
        "lady",
        "hairdresser"
    ],
    "wof:name":"Wendy'S",
    "wof:placetype":"venue"
},
  "geometry": {"coordinates":[-0.4156970084,51.8754272461],"type":"Point"}
}