{
  "type": "Feature",
  "properties": {
    "addr:full":"4 Wolfhanger Cottages Alresford Hampshire SO24 0JJ",
    "addr:housenumber":"4",
    "addr:postcode":"so24 0jj",
    "addr:street":"Wolfhanger Cottages",
    "iso:country":"GB",
    "sg:address":"4 Wolfhanger Cottages",
    "sg:city":"Alresford",
    "sg:classifiers":[
        {
            "category":"Retail",
            "subcategory":"Auto Repair",
            "type":"Services"
        }
    ],
    "sg:phone":"+44 1962 771126",
    "sg:postcode":"SO24 0JJ",
    "sg:province":"Hampshire",
    "sg:tags":[
        "body",
        "car"
    ],
    "wof:name":"Dentsaway",
    "wof:placetype":"venue"
},
  "geometry": {"coordinates":[-1.09402,51.052719],"type":"Point"}
}