{
  "type": "Feature",
  "properties": {
    "addr:full":"Unit 3 Murrills Trading Estate, Portchester Fareham Hampshire PO16 9RD",
    "addr:housenumber":"unit 3",
    "addr:postcode":"po16 9rd",
    "addr:street":"Trading Estate",
    "iso:country":"GB",
    "sg:address":"Unit 3 Murrills Trading Estate, Portchester",
    "sg:city":"Fareham",
    "sg:classifiers":[
        {
            "category":"Wholesale",
            "subcategory":"Electrical",
            "type":"Manufacturing & Wholesale Goods"
        },
        {
            "category":"Shopping",
            "subcategory":"Computers & Home Electronics",
            "type":"Retail Goods"
        }
    ],
    "sg:phone":"+44 23 9237 7875",
    "sg:postcode":"PO16 9RD",
    "sg:province":"Hampshire",
    "sg:tags":[
        "wholesaler"
    ],
    "wof:name":"Medlock Electric Ltd.",
    "wof:placetype":"venue"
},
  "geometry": {"coordinates":[-1.130738,50.846088],"type":"Point"}
}