{
  "type": "Feature",
  "properties": {
    "iso:country":"GB",
    "sg:address":"Unit 23 Brittania Way, Boley Park Industrial Estate",
    "sg:city":"Lichfield",
    "sg:classifiers":[
        {
            "category":"Professional",
            "subcategory":"Art Services",
            "type":"Services"
        }
    ],
    "sg:phone":"+44 1543 263327",
    "sg:postcode":"WS14 9UY",
    "sg:province":"Staffordshire",
    "sg:tags":[
        "decorating",
        "painting"
    ],
    "wof:name":"Bob Holden Enterprises Ltd.",
    "wof:placetype":"venue"
},
  "geometry": {"coordinates":[-1.8019720316,52.68542099],"type":"Point"}
}