{
  "type": "Feature",
  "properties": {
    "addr:full":"4 Monks Close, South Harrow Harrow Greater London HA2 0RD",
    "addr:housenumber":"4",
    "addr:postcode":"ha2 0rd",
    "addr:street":"Monks Close",
    "iso:country":"GB",
    "sg:address":"4 Monks Close, South Harrow",
    "sg:city":"Harrow",
    "sg:classifiers":[
        {
            "category":"Building & Trades",
            "subcategory":"Landscaping Services",
            "type":"Services"
        }
    ],
    "sg:phone":"+44 20 8422 3426",
    "sg:postcode":"HA2 0RD",
    "sg:province":"Greater London",
    "sg:tags":[
        "landscape",
        "contractor"
    ],
    "wof:name":"A & M Landscapes",
    "wof:placetype":"venue"
},
  "geometry": {"coordinates":[-0.36349,51.567944],"type":"Point"}
}