{
  "type": "Feature",
  "properties": {
    "addr:full":"79 Park Lane, Netherton Bootle Merseyside L30 1QB",
    "addr:housenumber":"79",
    "addr:postcode":"l30 1qb",
    "addr:street":"Park Lane",
    "iso:country":"GB",
    "sg:address":"79 Park Lane, Netherton",
    "sg:city":"Bootle",
    "sg:classifiers":[
        {
            "category":"Food & Beverages",
            "subcategory":"Candy",
            "type":"Retail Goods"
        },
        {
            "category":"Food & Beverages",
            "subcategory":"Bakery",
            "type":"Retail Goods"
        }
    ],
    "sg:phone":"+44 151 286 8419",
    "sg:postcode":"L30 1QB",
    "sg:province":"Merseyside",
    "sg:tags":[
        "shop",
        "confectioner",
        "baker"
    ],
    "wof:name":"Sayers Confectioners Ltd.",
    "wof:placetype":"venue"
},
  "geometry": {"coordinates":[-2.9642779827,53.4784736633],"type":"Point"}
}