{
  "type": "Feature",
  "properties": {
    "addr:full":"The Street, South Stoke Reading Berkshire RG8 0JS",
    "addr:postcode":"rg8 0js",
    "addr:street":"The Street South",
    "iso:country":"GB",
    "sg:address":"The Street, South Stoke",
    "sg:city":"Reading",
    "sg:classifiers":[
        {
            "category":"Education",
            "subcategory":"School",
            "type":"Public Place"
        }
    ],
    "sg:phone":"+44 1491 872948",
    "sg:postcode":"RG8 0JS",
    "sg:province":"Berkshire",
    "sg:tags":[
        "local",
        "authority"
    ],
    "wof:name":"South Stoke County Primary School",
    "wof:placetype":"venue"
},
  "geometry": {"coordinates":[-1.1380170584,51.5475502014],"type":"Point"}
}