{
  "type": "Feature",
  "properties": {
    "iso:country":"GB",
    "sg:address":"20 Goldhawk Road",
    "sg:city":"London",
    "sg:classifiers":[
        {
            "category":"Professional",
            "subcategory":"Detective & Security Services",
            "type":"Services"
        },
        {
            "category":"Building & Trades",
            "subcategory":"Locksmith",
            "type":"Services"
        }
    ],
    "sg:phone":"+44 20 8746 1347",
    "sg:postcode":"W12 8DH",
    "sg:province":"Greater London",
    "wof:name":"G Franchi & Sons",
    "wof:placetype":"venue"
},
  "geometry": {"coordinates":[-0.224811,51.502884],"type":"Point"}
}