{
  "type": "Feature",
  "properties": {
    "iso:country":"GB",
    "sg:address":"Rear 60 Addelade Street",
    "sg:city":"Fleetwood",
    "sg:classifiers":[
        {
            "category":"Building & Trades",
            "subcategory":"Construction",
            "type":"Services"
        }
    ],
    "sg:phone":"+44 1253 773217",
    "sg:postcode":"FY7 6EE",
    "sg:province":"Lancashire",
    "sg:tags":[
        "builder"
    ],
    "wof:name":"Wilson A & Nephew Joinery & Building Contractors",
    "wof:placetype":"venue"
},
  "geometry": {"coordinates":[-3.0118880272,53.9245185852],"type":"Point"}
}