{
  "type": "Feature",
  "properties": {
    "addr:full":"Horkesley Park, Park Road Colchester Essex CO6 4JR",
    "addr:postcode":"co6 4jr",
    "addr:street":"Park Road Colchester",
    "iso:country":"GB",
    "sg:address":"Horkesley Park, Park Road",
    "sg:city":"Colchester",
    "sg:classifiers":[
        {
            "category":"Education",
            "subcategory":"School",
            "type":"Public Place"
        }
    ],
    "sg:postcode":"CO6 4JR",
    "sg:province":"Essex",
    "sg:tags":[
        "independent",
        "preparatory"
    ],
    "wof:name":"Littlegarth School (Dedham) Ltd.",
    "wof:placetype":"venue"
},
  "geometry": {"coordinates":[0.86765,51.967377],"type":"Point"}
}