{
  "type": "Feature",
  "properties": {
    "addr:full":"Bunkers Hill West, Orton Road Carlisle Cumbria CA2 6RA",
    "addr:postcode":"ca2 6ra",
    "addr:street":"Hill;Orton Road",
    "iso:country":"GB",
    "sg:address":"Bunkers Hill West, Orton Road",
    "sg:city":"Carlisle",
    "sg:classifiers":[
        {
            "category":"Professional",
            "subcategory":"Management & Consulting",
            "type":"Services"
        }
    ],
    "sg:postcode":"CA2 6RA",
    "sg:province":"Cumbria",
    "sg:tags":[
        "consultant",
        "business"
    ],
    "wof:name":"Executive Search Plus Europe Ltd.",
    "wof:placetype":"venue"
},
  "geometry": {"coordinates":[-2.98687,54.882912],"type":"Point"}
}