{
  "type": "Feature",
  "properties": {
    "iso:country":"GB",
    "sg:address":"Unit 2 Chestnut Ho, Moorgreen Industrial Park",
    "sg:city":"Nottingham",
    "sg:classifiers":[
        {
            "category":"Shopping",
            "subcategory":"Clothing, Apparel, & Fashions",
            "type":"Retail Goods"
        }
    ],
    "sg:phone":"+44 1773 535926",
    "sg:postcode":"NG16 3PX",
    "sg:province":"Derbyshire",
    "sg:tags":[
        "clothing"
    ],
    "wof:name":"Faab Clothing",
    "wof:placetype":"venue"
},
  "geometry": {"coordinates":[-1.2909990549,53.0260696411],"type":"Point"}
}