{
  "type": "Feature",
  "properties": {
    "addr:full":"347a Wakefield Road, Denby Dale Huddersfield South Yorkshire HD8 8RT",
    "addr:housenumber":"347a",
    "addr:postcode":"hd8 8rt",
    "addr:street":"Wakefield Road",
    "iso:country":"GB",
    "sg:address":"347a Wakefield Road, Denby Dale",
    "sg:city":"Huddersfield",
    "sg:classifiers":[
        {
            "category":"Shopping",
            "type":"Retail Goods"
        }
    ],
    "sg:phone":"+44 1484 866906",
    "sg:postcode":"HD8 8RT",
    "sg:province":"South Yorkshire",
    "sg:tags":[
        "part",
        "accessory"
    ],
    "wof:name":"Motapart",
    "wof:placetype":"venue"
},
  "geometry": {"coordinates":[-1.6567729712,53.572681427],"type":"Point"}
}