{
  "type": "Feature",
  "properties": {
    "addr:full":"21 High St Epsom Surrey KT19 8DD",
    "addr:housenumber":"21",
    "addr:postcode":"kt19 8dd",
    "addr:street":"High St",
    "iso:country":"GB",
    "sg:address":"21 High St",
    "sg:city":"Epsom",
    "sg:classifiers":[
        {
            "category":"Shopping",
            "subcategory":"Gifts & Souvenirs",
            "type":"Retail Goods"
        }
    ],
    "sg:phone":"+44 1372 722113",
    "sg:postcode":"KT19 8DD",
    "sg:province":"Surrey",
    "sg:tags":[
        "poster",
        "card"
    ],
    "wof:name":"With Love",
    "wof:placetype":"venue"
},
  "geometry": {"coordinates":[-0.2651309967,51.3337936401],"type":"Point"}
}