{
  "type": "Feature",
  "properties": {
    "addr:full":"16 Church St Crook Durham DL15 9BG",
    "addr:housenumber":"16",
    "addr:postcode":"dl15 9bg",
    "addr:street":"Church St",
    "iso:country":"GB",
    "sg:address":"16 Church St",
    "sg:city":"Crook",
    "sg:classifiers":[
        {
            "category":"Home & Garden",
            "subcategory":"Household Appliances",
            "type":"Retail Goods"
        }
    ],
    "sg:postcode":"DL15 9BG",
    "sg:province":"Durham",
    "sg:tags":[
        "electrical",
        "domestic"
    ],
    "wof:name":"Northern Electric Plc",
    "wof:placetype":"venue"
},
  "geometry": {"coordinates":[-1.744636,54.714844],"type":"Point"}
}