{
  "type": "Feature",
  "properties": {
    "addr:full":"Unit 4 Glasgow Glasgow City G20 0BT",
    "addr:housenumber":"unit 4",
    "addr:postcode":"g20 0bt",
    "iso:country":"GB",
    "sg:address":"Unit 4",
    "sg:city":"Glasgow",
    "sg:classifiers":[
        {
            "category":"Professional",
            "subcategory":"Lawyer & Legal Services",
            "type":"Services"
        }
    ],
    "sg:phone":"+44 141 945 5533",
    "sg:postcode":"G20 0BT",
    "sg:province":"Glasgow City",
    "sg:tags":[
        "solicitor"
    ],
    "wof:name":"Campbell D Joss",
    "wof:placetype":"venue"
},
  "geometry": {"coordinates":[-4.300069809,55.8971405029],"type":"Point"}
}