{
  "type": "Feature",
  "properties": {
    "addr:full":"19 Skelton Industrial Estate, Skelton-in-clevelandskelton Saltburn-by-the-sea North Yorkshire TS12 2LQ",
    "addr:housenumber":"19",
    "addr:postcode":"ts12 2lq",
    "addr:street":"Skelton Industrial",
    "iso:country":"GB",
    "sg:address":"19 Skelton Industrial Estate, Skelton-in-clevelandskelton",
    "sg:city":"Saltburn-by-the-sea",
    "sg:classifiers":[
        {
            "category":"Manufacturing",
            "subcategory":"Metals",
            "type":"Manufacturing & Wholesale Goods"
        }
    ],
    "sg:phone":"+44 1287 654550",
    "sg:postcode":"TS12 2LQ",
    "sg:province":"North Yorkshire",
    "sg:tags":[
        "steel",
        "fabricator",
        "erectors"
    ],
    "wof:name":"Skelton Engineering Co.",
    "wof:placetype":"venue"
},
  "geometry": {"coordinates":[-0.9414799809,54.5661201477],"type":"Point"}
}