{
  "type": "Feature",
  "properties": {
    "iso:country":"GB",
    "sg:address":"15 Henderson Avenue",
    "sg:city":"Scunthorpe",
    "sg:classifiers":[
        {
            "category":"Food & Beverages",
            "subcategory":"Meat & Fish",
            "type":"Retail Goods"
        }
    ],
    "sg:postcode":"DN15 7RL",
    "sg:province":"Lincolnshire",
    "sg:tags":[
        "chip"
    ],
    "wof:name":"Paynes Fish & Chips",
    "wof:placetype":"venue"
},
  "geometry": {"coordinates":[-0.661584,53.59222],"type":"Point"}
}