{
  "type": "Feature",
  "properties": {
    "addr:full":"15 Percy St Liverpool Merseyside L8 7LT",
    "addr:housenumber":"15",
    "addr:postcode":"l8 7lt",
    "addr:street":"Percy St",
    "iso:country":"GB",
    "sg:address":"15 Percy St",
    "sg:city":"Liverpool",
    "sg:classifiers":[
        {
            "category":"Wholesale",
            "subcategory":"Books, Periodicals, & Newspapers",
            "type":"Manufacturing & Wholesale Goods"
        }
    ],
    "sg:phone":"+44 151 709 7803",
    "sg:postcode":"L8 7LT",
    "sg:province":"Merseyside",
    "sg:tags":[
        "publishing"
    ],
    "wof:name":"Hooton Aircraft",
    "wof:placetype":"venue"
},
  "geometry": {"coordinates":[-2.969367981,53.3972587585],"type":"Point"}
}