{
  "type": "Feature",
  "properties": {
    "iso:country":"GB",
    "sg:address":"16 Stoneyford Road",
    "sg:city":"Sutton-in-ashfield",
    "sg:classifiers":[
        {
            "category":"Personal",
            "subcategory":"Beauty Salon",
            "type":"Services"
        }
    ],
    "sg:postcode":"NG17 4DB",
    "sg:province":"Nottinghamshire",
    "sg:tags":[
        "lady",
        "hairdresser"
    ],
    "wof:name":"Yvonnes Ladies & Childrens Hairdressers",
    "wof:placetype":"venue"
},
  "geometry": {"coordinates":[-1.257825,53.131695],"type":"Point"}
}