{
  "type": "Feature",
  "properties": {
    "addr:full":"Fradley Aerodrome Lichfield Staffordshire WS14 9HQ",
    "addr:postcode":"ws14 9hq",
    "addr:street":"Staffordshire",
    "iso:country":"GB",
    "sg:address":"Fradley Aerodrome",
    "sg:city":"Lichfield",
    "sg:classifiers":[
        {
            "category":"Utilities",
            "subcategory":"Mobile Phone",
            "type":"Services"
        }
    ],
    "sg:phone":"+44 1543 256911",
    "sg:postcode":"WS14 9HQ",
    "sg:province":"Staffordshire",
    "sg:tags":[
        "mnfr",
        "good",
        "electrical"
    ],
    "wof:name":"B90 Hanger Re-manufacturing",
    "wof:placetype":"venue"
},
  "geometry": {"coordinates":[-1.7986119986,52.6732292175],"type":"Point"}
}