{
  "type": "Feature",
  "properties": {
    "iso:country":"GB",
    "sg:address":"Market Square",
    "sg:city":"Sandy",
    "sg:classifiers":[
        {
            "category":"Food & Beverages",
            "subcategory":"Supermarket",
            "type":"Retail Goods"
        }
    ],
    "sg:phone":"+44 1767 691688",
    "sg:postcode":"SG19 1JA",
    "sg:province":"Bedfordshire",
    "wof:name":"Budgens Stores",
    "wof:placetype":"venue"
},
  "geometry": {"coordinates":[-0.2875620127,52.129234314],"type":"Point"}
}