{
  "type": "Feature",
  "properties": {
    "iso:country":"GB",
    "sg:address":"29 Royal Quays Factory Outlets",
    "sg:city":"North Shields",
    "sg:classifiers":[
        {
            "category":"Shopping",
            "subcategory":"Clothing, Apparel, & Fashions",
            "type":"Retail Goods"
        }
    ],
    "sg:postcode":"NE29 6DW",
    "sg:province":"Tyne and Wear",
    "sg:tags":[
        "ladieswear"
    ],
    "wof:name":"The Chainstore Outlet",
    "wof:placetype":"venue"
},
  "geometry": {"coordinates":[-1.4641339779,54.9957046509],"type":"Point"}
}