{
  "type": "Feature",
  "properties": {
    "iso:country":"GB",
    "sg:address":"Unit 4 Wootham Road, Industrial Estate",
    "sg:city":"Abingdon",
    "sg:classifiers":[
        {
            "category":"Professional",
            "subcategory":"Engineering",
            "type":"Services"
        },
        {
            "category":"Retail",
            "subcategory":"Auto Repair",
            "type":"Services"
        }
    ],
    "sg:phone":"+44 1235 532551",
    "sg:postcode":"OX14 1LD",
    "sg:province":"Oxfordshire",
    "sg:tags":[
        "modification",
        "garage",
        "ge",
        "engineer",
        "mechanical"
    ],
    "wof:name":"Ken McIntyre",
    "wof:placetype":"venue"
},
  "geometry": {"coordinates":[-1.2854889631,51.673324585],"type":"Point"}
}