{
  "type": "Feature",
  "properties": {
    "addr:full":"37 South St Arbroath Angus DD11 3AB",
    "addr:housenumber":"37",
    "addr:postcode":"dd11 3ab",
    "addr:street":"South St",
    "iso:country":"GB",
    "sg:address":"37 South St",
    "sg:city":"Arbroath",
    "sg:classifiers":[
        {
            "category":"Government",
            "subcategory":"Post Office",
            "type":"Public Place"
        }
    ],
    "sg:phone":"+44 1361 882292",
    "sg:postcode":"DD11 3AB",
    "sg:province":"Angus",
    "wof:name":"Royal Mail Delivery Office",
    "wof:placetype":"venue"
},
  "geometry": {"coordinates":[-2.6156010628,56.5707473755],"type":"Point"}
}