{
  "type": "Feature",
  "properties": {
    "addr:full":"Waterloo Wharf, West Quay Road Poole Dorset BH15 1HX",
    "addr:postcode":"bh15 1hx",
    "addr:street":"Waterloo;West Quay Road",
    "iso:country":"GB",
    "sg:address":"Waterloo Wharf, West Quay Road",
    "sg:city":"Poole",
    "sg:classifiers":[
        {
            "category":"Real Estate",
            "subcategory":"Architect",
            "type":"Services"
        }
    ],
    "sg:phone":"+44 1202 667668",
    "sg:postcode":"BH15 1HX",
    "sg:province":"Dorset",
    "wof:name":"Triton Marine",
    "wof:placetype":"venue"
},
  "geometry": {"coordinates":[-1.9867390394,50.7144851685],"type":"Point"}
}