{
  "type": "Feature",
  "properties": {
    "addr:full":"8 Filmer Road London Greater London SW6 7BW",
    "addr:housenumber":"8",
    "addr:postcode":"sw6 7bw",
    "addr:street":"Filmer Road",
    "iso:country":"GB",
    "sg:address":"8 Filmer Road",
    "sg:city":"London",
    "sg:classifiers":[
        {
            "category":"Building & Trades",
            "subcategory":"Construction",
            "type":"Services"
        }
    ],
    "sg:phone":"+44 20 7385 7069",
    "sg:postcode":"SW6 7BW",
    "sg:province":"Greater London",
    "sg:tags":[
        "roofing"
    ],
    "wof:name":"P P M Specialist Works Ltd.",
    "wof:placetype":"venue"
},
  "geometry": {"coordinates":[-0.207627,51.480183],"type":"Point"}
}