{
  "type": "Feature",
  "properties": {
    "addr:full":"Lady Lea Rd, Horsley Woodhouse Derby Derbyshire DE215LL",
    "addr:postcode":"de215ll",
    "addr:street":"Lady Lea Rd",
    "iso:country":"GB",
    "sg:address":"Lady Lea Rd, Horsley Woodhouse",
    "sg:city":"Derby",
    "sg:classifiers":[
        {
            "category":"Manufacturing",
            "subcategory":"Rubber & Plastics",
            "type":"Manufacturing & Wholesale Goods"
        }
    ],
    "sg:postcode":"DE215LL",
    "sg:province":"Derbyshire",
    "sg:tags":[
        "product"
    ],
    "wof:name":"Bowfield Window Systems",
    "wof:placetype":"venue"
},
  "geometry": {"coordinates":[-1.4393390417,52.9962615967],"type":"Point"}
}