{
  "type": "Feature",
  "properties": {
    "iso:country":"GB",
    "sg:address":"25 Station Road",
    "sg:city":"Corsham",
    "sg:classifiers":[
        {
            "category":"Utilities",
            "subcategory":"Telephone",
            "type":"Services"
        },
        {
            "category":"Communications",
            "type":"Services"
        }
    ],
    "sg:phone":"+44 1249 714041",
    "sg:postcode":"SN13 9EY",
    "sg:province":"Wiltshire",
    "sg:tags":[
        "telecommunication",
        "network"
    ],
    "wof:name":"Roland Colegate Ltd",
    "wof:placetype":"venue"
},
  "geometry": {"coordinates":[-2.1856820583,51.4278030396],"type":"Point"}
}