{
  "type": "Feature",
  "properties": {
    "addr:full":"Rockmount Chester Cheshire CH2 1AA",
    "addr:postcode":"ch2 1aa",
    "iso:country":"GB",
    "sg:address":"Rockmount",
    "sg:city":"Chester",
    "sg:classifiers":[
        {
            "category":"Shopping",
            "subcategory":"Pharmacy",
            "type":"Retail Goods"
        }
    ],
    "sg:postcode":"CH2 1AA",
    "sg:province":"Cheshire",
    "sg:tags":[
        "medicine",
        "therapy"
    ],
    "wof:name":"Indigo Health Consultancy",
    "wof:placetype":"venue"
},
  "geometry": {"coordinates":[-2.889089,53.216476],"type":"Point"}
}