{
  "type": "Feature",
  "properties": {
    "addr:full":"Foundry Works, River Street Bacup Lancashire OL13 9QX",
    "addr:postcode":"ol13 9qx",
    "addr:street":"River Street",
    "iso:country":"GB",
    "sg:address":"Foundry Works, River Street",
    "sg:city":"Bacup",
    "sg:classifiers":[
        {
            "category":"Professional",
            "subcategory":"Engineering",
            "type":"Services"
        }
    ],
    "sg:phone":"+44 1706 879829",
    "sg:postcode":"OL13 9QX",
    "sg:province":"Lancashire",
    "sg:tags":[
        "engineer",
        "mechanical"
    ],
    "wof:name":"N & T J Winfield",
    "wof:placetype":"venue"
},
  "geometry": {"coordinates":[-2.201104,53.702717],"type":"Point"}
}