{
  "type": "Feature",
  "properties": {
    "addr:full":"11 Coverdale, Heelands Milton Keynes Buckinghamshire MK13 7LZ",
    "addr:housenumber":"11",
    "addr:postcode":"mk13 7lz",
    "addr:street":"Coverdale Heelands",
    "iso:country":"GB",
    "sg:address":"11 Coverdale, Heelands",
    "sg:city":"Milton Keynes",
    "sg:classifiers":[
        {
            "category":"Professional",
            "subcategory":"Accounting & Tax Preparation",
            "type":"Services"
        }
    ],
    "sg:phone":"+44 1908 225585",
    "sg:postcode":"MK13 7LZ",
    "sg:province":"Buckinghamshire",
    "sg:tags":[
        "accountant"
    ],
    "wof:name":"The Beck Partnership",
    "wof:placetype":"venue"
},
  "geometry": {"coordinates":[-0.77488,52.056442],"type":"Point"}
}