{
  "type": "Feature",
  "properties": {
    "iso:country":"GB",
    "sg:address":"Pollington",
    "sg:city":"Goole",
    "sg:classifiers":[
        {
            "category":"Marine",
            "type":"Transportation"
        }
    ],
    "sg:phone":"+44 1405 861918",
    "sg:postcode":"DN14 0DY",
    "sg:province":"East Riding of Yorkshire",
    "sg:tags":[
        "inland",
        "waterway",
        "river"
    ],
    "wof:name":"Pollington Lock",
    "wof:placetype":"venue"
},
  "geometry": {"coordinates":[-1.072647,53.670296],"type":"Point"}
}