{
  "type": "Feature",
  "properties": {
    "addr:full":"The Old Fire Station Penryn Cornwall TR10 8JH",
    "addr:postcode":"tr10 8jh",
    "iso:country":"GB",
    "sg:address":"The Old Fire Station",
    "sg:city":"Penryn",
    "sg:classifiers":[
        {
            "category":"Real Estate",
            "subcategory":"Architect",
            "type":"Services"
        }
    ],
    "sg:postcode":"TR10 8JH",
    "sg:province":"Cornwall",
    "wof:name":"Stanley Partnership",
    "wof:placetype":"venue"
},
  "geometry": {"coordinates":[-5.1048088074,50.1685752869],"type":"Point"}
}