{
  "type": "Feature",
  "properties": {
    "addr:full":"Glenthorne Ho, 5-17 Hammersmith Gro Hammersmith Greater London W6 0LG",
    "addr:housenumber":"5-17",
    "addr:postcode":"w6 0lg",
    "addr:street":"Glenthorne;Hammersmith Gro",
    "iso:country":"GB",
    "sg:address":"Glenthorne Ho, 5-17 Hammersmith Gro",
    "sg:city":"Hammersmith",
    "sg:classifiers":[
        {
            "category":"Organizations",
            "subcategory":"Religious Organization",
            "type":"Services"
        }
    ],
    "sg:phone":"+44 20 8748 7576",
    "sg:postcode":"W6 0LG",
    "sg:province":"Greater London",
    "sg:tags":[
        "organisation"
    ],
    "wof:name":"His People Christian Ministries",
    "wof:placetype":"venue"
},
  "geometry": {"coordinates":[-0.22942,51.496151],"type":"Point"}
}