{
  "type": "Feature",
  "properties": {
    "iso:country":"GB",
    "sg:address":"Oakley House, Stank Lane",
    "sg:city":"Bishops Castle",
    "sg:classifiers":[
        {
            "category":"Building & Trades",
            "subcategory":"Construction",
            "type":"Services"
        }
    ],
    "sg:postcode":"SY9 5EY",
    "sg:province":"Shropshire",
    "sg:tags":[
        "joiner",
        "carpenter"
    ],
    "wof:name":"S R & P S Middleton",
    "wof:placetype":"venue"
},
  "geometry": {"coordinates":[-2.98068,52.481106],"type":"Point"}
}