{
  "type": "Feature",
  "properties": {
    "addr:full":"Central Buildings, High Street Wolverhampton Shropshire WV5 9DN",
    "addr:postcode":"wv5 9dn",
    "addr:street":"Central;High Street",
    "iso:country":"GB",
    "sg:address":"Central Buildings, High Street",
    "sg:city":"Wolverhampton",
    "sg:classifiers":[
        {
            "category":"Home & Garden",
            "subcategory":"Home Furnishings",
            "type":"Retail Goods"
        }
    ],
    "sg:postcode":"WV5 9DN",
    "sg:province":"Shropshire",
    "sg:tags":[
        "furnishers",
        "planner",
        "kitchen"
    ],
    "wof:name":"Copperfield Interiors",
    "wof:placetype":"venue"
},
  "geometry": {"coordinates":[-2.18276,52.536129],"type":"Point"}
}