{
  "type": "Feature",
  "properties": {
    "iso:country":"GB",
    "sg:address":"Court Cocking",
    "sg:city":"St Ives",
    "sg:classifiers":[
        {
            "category":"Travel",
            "subcategory":"Hotels & Motels",
            "type":"Entertainment"
        }
    ],
    "sg:phone":"+44 1736 795525",
    "sg:postcode":"TR26 1HQ",
    "sg:province":"Cornwall",
    "sg:tags":[
        "house",
        "guest"
    ],
    "wof:name":"Harbour Lights Guest House",
    "wof:placetype":"venue"
},
  "geometry": {"coordinates":[-5.48018,50.214039],"type":"Point"}
}