{
  "type": "Feature",
  "properties": {
    "addr:full":"216 Buckingham Road Hampton Greater London TW12 3JX",
    "addr:housenumber":"216",
    "addr:postcode":"tw12 3jx",
    "addr:street":"Buckingham Road",
    "iso:country":"GB",
    "sg:address":"216 Buckingham Road",
    "sg:city":"Hampton",
    "sg:classifiers":[
        {
            "category":"Professional",
            "subcategory":"Management & Consulting",
            "type":"Services"
        }
    ],
    "sg:phone":"+44 20 8979 6568",
    "sg:postcode":"TW12 3JX",
    "sg:province":"Greater London",
    "sg:tags":[
        "consultant",
        "geophysical",
        "geological"
    ],
    "wof:name":"Pais Geophysical Software Ltd.",
    "wof:placetype":"venue"
},
  "geometry": {"coordinates":[-0.381762,51.43198],"type":"Point"}
}