{
  "type": "Feature",
  "properties": {
    "iso:country":"GB",
    "sg:address":"Muirhead Farm",
    "sg:city":"Lockerbie",
    "sg:classifiers":[
        {
            "category":"Farming",
            "subcategory":"Livestock Farm",
            "type":"Manufacturing & Wholesale Goods"
        }
    ],
    "sg:phone":"+44 1576 202586",
    "sg:postcode":"DG11 1LL",
    "sg:province":"Dumfries and Galloway",
    "sg:tags":[
        "others"
    ],
    "wof:name":"T H J Rae & Partners",
    "wof:placetype":"venue"
},
  "geometry": {"coordinates":[-3.420439,55.12104],"type":"Point"}
}