{
  "type": "Feature",
  "properties": {
    "addr:full":"5 First Avenue Halstead Essex CO9 2EX",
    "addr:housenumber":"5",
    "addr:postcode":"co9 2ex",
    "addr:street":"First Avenue",
    "iso:country":"GB",
    "sg:address":"5 First Avenue",
    "sg:city":"Halstead",
    "sg:classifiers":[
        {
            "category":"Food & Beverages",
            "subcategory":"Bakery",
            "type":"Retail Goods"
        }
    ],
    "sg:phone":"+44 1787 472048",
    "sg:postcode":"CO9 2EX",
    "sg:province":"Essex",
    "sg:tags":[
        "baker"
    ],
    "wof:name":"Castle Bakery",
    "wof:placetype":"venue"
},
  "geometry": {"coordinates":[0.656971,51.939053],"type":"Point"}
}