{
  "type": "Feature",
  "properties": {
    "addr:full":"Fiveoaks Lane Chigwell Essex IG7 4QP",
    "addr:postcode":"ig7 4qp",
    "addr:street":"Fiveoaks Lane",
    "iso:country":"GB",
    "sg:address":"Fiveoaks Lane",
    "sg:city":"Chigwell",
    "sg:classifiers":[
        {
            "category":"Train Station",
            "subcategory":"Rail",
            "type":"Transportation"
        }
    ],
    "sg:postcode":"IG7 4QP",
    "sg:province":"Essex",
    "sg:tags":[
        "caravan"
    ],
    "wof:name":"Mr C Walker",
    "wof:placetype":"venue"
},
  "geometry": {"coordinates":[0.075095,51.618946],"type":"Point"}
}