{
  "type": "Feature",
  "properties": {
    "iso:country":"GB",
    "sg:address":"105 Westborough Road",
    "sg:city":"Westcliff-on-sea",
    "sg:classifiers":[
        {
            "category":"Professional",
            "subcategory":"Computer Services",
            "type":"Services"
        }
    ],
    "sg:phone":"+44 1702 436381",
    "sg:postcode":"SS0 9JQ",
    "sg:province":"Essex",
    "sg:tags":[
        "system",
        "software"
    ],
    "wof:name":"P C Tec",
    "wof:placetype":"venue"
},
  "geometry": {"coordinates":[0.694137,51.546497],"type":"Point"}
}