{
  "type": "Feature",
  "properties": {
    "iso:country":"GB",
    "sg:address":"Opendale Road, Burnham",
    "sg:city":"Slough",
    "sg:classifiers":[
        {
            "category":"Education",
            "subcategory":"School",
            "type":"Public Place"
        },
        {
            "category":"Government",
            "subcategory":"Office",
            "type":"Public Place"
        }
    ],
    "sg:phone":"+44 1628 662107",
    "sg:postcode":"SL1 7LZ",
    "sg:province":"Berkshire",
    "sg:tags":[
        "local",
        "authority"
    ],
    "wof:name":"Burnham Upper School",
    "wof:placetype":"venue"
},
  "geometry": {"coordinates":[-0.662177,51.527859],"type":"Point"}
}