{
  "type": "Feature",
  "properties": {
    "iso:country":"GB",
    "sg:address":"1 Paper Mews, High Street",
    "sg:city":"Dorking",
    "sg:classifiers":[
        {
            "category":"Professional",
            "subcategory":"Accounting & Tax Preparation",
            "type":"Services"
        }
    ],
    "sg:postcode":"RH4 2TU",
    "sg:province":"Surrey",
    "sg:tags":[
        "accountant"
    ],
    "wof:name":"Ellis Atkins",
    "wof:placetype":"venue"
},
  "geometry": {"coordinates":[-0.3288139999,51.233341217],"type":"Point"}
}