{
  "type": "Feature",
  "properties": {
    "addr:full":"London Bridge Station, Railway App London Greater London SE1 9SP",
    "addr:postcode":"se1 9sp",
    "addr:street":"London Bridge",
    "iso:country":"GB",
    "sg:address":"London Bridge Station, Railway App",
    "sg:city":"London",
    "sg:classifiers":[
        {
            "category":"Food & Beverages",
            "subcategory":"Groceries & Convenience Stores",
            "type":"Retail Goods"
        }
    ],
    "sg:phone":"+44 20 7357 9900",
    "sg:postcode":"SE1 9SP",
    "sg:province":"Greater London",
    "wof:name":"Belleview Ltd.",
    "wof:placetype":"venue"
},
  "geometry": {"coordinates":[-0.08598,51.50462],"type":"Point"}
}