{
  "type": "Feature",
  "properties": {
    "addr:full":"Unit 12 Avenue Close Birmingham West Midlands B7 4NU",
    "addr:housenumber":"unit 12",
    "addr:postcode":"b7 4nu",
    "addr:street":"Avenue Close",
    "iso:country":"GB",
    "sg:address":"Unit 12 Avenue Close",
    "sg:city":"Birmingham",
    "sg:classifiers":[
        {
            "category":"Communications",
            "subcategory":"Newspaper",
            "type":"Services"
        }
    ],
    "sg:phone":"+44 121 683 2662",
    "sg:postcode":"B7 4NU",
    "sg:province":"West Midlands",
    "sg:tags":[
        "magazine"
    ],
    "wof:name":"Bike Trader",
    "wof:placetype":"venue"
},
  "geometry": {"coordinates":[-1.8796490431,52.4951324463],"type":"Point"}
}