{
  "type": "Feature",
  "properties": {
    "addr:full":"Unit 8 Alpha Centre Alpha Road Aldershot Hampshire GU12 4RG",
    "addr:housenumber":"unit 8",
    "addr:postcode":"gu12 4rg",
    "addr:street":"Alpha;Alpha Road",
    "iso:country":"GB",
    "sg:address":"Unit 8 Alpha Centre Alpha Road",
    "sg:city":"Aldershot",
    "sg:classifiers":[
        {
            "category":"Wholesale",
            "subcategory":"Construction Materials",
            "type":"Manufacturing & Wholesale Goods"
        }
    ],
    "sg:phone":"+44 1252 322233",
    "sg:postcode":"GU12 4RG",
    "sg:province":"Hampshire",
    "sg:tags":[
        "lift"
    ],
    "wof:name":"Farleygreene Ltd.",
    "wof:placetype":"venue"
},
  "geometry": {"coordinates":[-0.73986,51.246498],"type":"Point"}
}