{
  "type": "Feature",
  "properties": {
    "iso:country":"GB",
    "sg:address":"Cheyneys Farmhouse, Ower",
    "sg:city":"Romsey",
    "sg:classifiers":[
        {
            "category":"Autos & Motor Vehicles",
            "subcategory":"Motorcycle Sales",
            "type":"Retail Goods"
        }
    ],
    "sg:postcode":"SO51 6AF",
    "sg:province":"Hampshire",
    "sg:tags":[
        "chauffeur",
        "driven",
        "car"
    ],
    "wof:name":"Forest Edge Cars",
    "wof:placetype":"venue"
},
  "geometry": {"coordinates":[-1.5387040377,50.9466209412],"type":"Point"}
}