{
  "type": "Feature",
  "properties": {
    "iso:country":"GB",
    "sg:address":"Regent St",
    "sg:city":"Blyth",
    "sg:classifiers":[
        {
            "category":"Sports & Exercise",
            "subcategory":"Gym",
            "type":"Entertainment"
        }
    ],
    "sg:postcode":"NE24 1LL",
    "sg:province":"Northumberland",
    "sg:tags":[
        "fitness",
        "health",
        "centre"
    ],
    "wof:name":"Foster,Alan J,",
    "wof:placetype":"venue"
},
  "geometry": {"coordinates":[-1.514094,55.13216],"type":"Point"}
}