{
  "type": "Feature",
  "properties": {
    "addr:full":"30 Butts Road Alton Hampshire GU34 1NB",
    "addr:housenumber":"30",
    "addr:postcode":"gu34 1nb",
    "addr:street":"Butts Road",
    "iso:country":"GB",
    "sg:address":"30 Butts Road",
    "sg:city":"Alton",
    "sg:classifiers":[
        {
            "category":"Professional",
            "subcategory":"Business Services",
            "type":"Services"
        }
    ],
    "sg:postcode":"GU34 1NB",
    "sg:province":"Hampshire",
    "sg:tags":[
        "tile",
        "stockist"
    ],
    "wof:name":"Cathlean Ann Tiles",
    "wof:placetype":"venue"
},
  "geometry": {"coordinates":[-0.981472,51.144588],"type":"Point"}
}