{
  "type": "Feature",
  "properties": {
    "addr:full":"Enterprise Centre, Salop Road Welshpool Shropshire SY21 7RE",
    "addr:postcode":"sy21 7re",
    "addr:street":"Salop Road",
    "iso:country":"GB",
    "sg:address":"Enterprise Centre, Salop Road",
    "sg:city":"Welshpool",
    "sg:classifiers":[
        {
            "category":"Communications",
            "subcategory":"Newspaper",
            "type":"Services"
        }
    ],
    "sg:phone":"+44 1938 555929",
    "sg:postcode":"SY21 7RE",
    "sg:province":"Shropshire",
    "sg:tags":[
        "magazine"
    ],
    "wof:name":"Powys Talking Newspaper",
    "wof:placetype":"venue"
},
  "geometry": {"coordinates":[-3.1452031136,52.661190033],"type":"Point"}
}