{
  "type": "Feature",
  "properties": {
    "iso:country":"GB",
    "sg:address":"Cairnhill Of Melrose, Gamrie",
    "sg:city":"Banff",
    "sg:classifiers":[
        {
            "category":"Farming",
            "subcategory":"Livestock Farm",
            "type":"Manufacturing & Wholesale Goods"
        }
    ],
    "sg:phone":"+44 1343 540504",
    "sg:postcode":"AB45 3SA",
    "sg:province":"Aberdeenshire",
    "sg:tags":[
        "others"
    ],
    "wof:name":"Moray Pigs Ltd",
    "wof:placetype":"venue"
},
  "geometry": {"coordinates":[-2.412667,57.662766],"type":"Point"}
}