{
  "type": "Feature",
  "properties": {
    "iso:country":"GB",
    "sg:address":"67 Camburn St",
    "sg:city":"Glasgow",
    "sg:classifiers":[
        {
            "category":"Wholesale",
            "subcategory":"Non-durable Goods",
            "type":"Manufacturing & Wholesale Goods"
        }
    ],
    "sg:phone":"+44 141 778 1445",
    "sg:postcode":"G32 6AX",
    "sg:province":"Glasgow City",
    "sg:tags":[
        "animal",
        "by-product"
    ],
    "wof:name":"David Stewart (Glasgow) Ltd",
    "wof:placetype":"venue"
},
  "geometry": {"coordinates":[-4.17605,55.854179],"type":"Point"}
}