{
  "type": "Feature",
  "properties": {
    "addr:full":"Mill Farm, Main Road, North Tuddenham Dereham Norfolk NR20 3DJ",
    "addr:postcode":"nr20 3dj",
    "addr:street":"Main Road North;Dereham",
    "iso:country":"GB",
    "sg:address":"Mill Farm, Main Road, North Tuddenham",
    "sg:city":"Dereham",
    "sg:classifiers":[
        {
            "category":"Home & Garden",
            "subcategory":"Garden Supply",
            "type":"Retail Goods"
        },
        {
            "category":"Farming",
            "subcategory":"Farm",
            "type":"Manufacturing & Wholesale Goods"
        }
    ],
    "sg:postcode":"NR20 3DJ",
    "sg:province":"Norfolk",
    "sg:tags":[
        "mixed",
        "bulb",
        "crop",
        "grower"
    ],
    "wof:name":"Malcolm E Fayers",
    "wof:placetype":"venue"
},
  "geometry": {"coordinates":[1.016303,52.687038],"type":"Point"}
}