{
  "type": "Feature",
  "properties": {
    "iso:country":"GB",
    "sg:address":"15 Ploughmans Clo",
    "sg:city":"Camden",
    "sg:classifiers":[
        {
            "category":"Health Services",
            "subcategory":"Health Practitioner",
            "type":"Services"
        }
    ],
    "sg:phone":"+44 20 7388 6990",
    "sg:postcode":"NW1 0XH",
    "sg:province":"Greater London",
    "sg:tags":[
        "psychologist"
    ],
    "wof:name":"A R Arthur",
    "wof:placetype":"venue"
},
  "geometry": {"coordinates":[-0.1328150034,51.5391960144],"type":"Point"}
}