{
  "type": "Feature",
  "properties": {
    "addr:full":"Buskin Farm, Exbourne Okehampton Devon EX20 3RL",
    "addr:postcode":"ex20 3rl",
    "iso:country":"GB",
    "sg:address":"Buskin Farm, Exbourne",
    "sg:city":"Okehampton",
    "sg:classifiers":[
        {
            "category":"Farming",
            "subcategory":"Livestock Farm",
            "type":"Manufacturing & Wholesale Goods"
        }
    ],
    "sg:postcode":"EX20 3RL",
    "sg:province":"Devon",
    "sg:tags":[
        "others"
    ],
    "wof:name":"D C & H O Letheren",
    "wof:placetype":"venue"
},
  "geometry": {"coordinates":[-3.9854340553,50.7999763489],"type":"Point"}
}