{
  "type": "Feature",
  "properties": {
    "addr:full":"22 London Road Chipping Norton Gloucestershire OX7 5AX",
    "addr:housenumber":"22",
    "addr:postcode":"ox7 5ax",
    "addr:street":"London Road",
    "iso:country":"GB",
    "sg:address":"22 London Road",
    "sg:city":"Chipping Norton",
    "sg:classifiers":[
        {
            "category":"Organizations",
            "subcategory":"Community Association",
            "type":"Services"
        }
    ],
    "sg:phone":"+44 1608 645756",
    "sg:postcode":"OX7 5AX",
    "sg:province":"Gloucestershire",
    "sg:tags":[
        "relation",
        "public"
    ],
    "wof:name":"Lincoln Beasley P R  & Marketing Ltd.",
    "wof:placetype":"venue"
},
  "geometry": {"coordinates":[-1.5413089991,51.9439086914],"type":"Point"}
}