{
  "type": "Feature",
  "properties": {
    "addr:full":"61 Priory Way Mirfield West Yorkshire WF14 9EB",
    "addr:housenumber":"61",
    "addr:postcode":"wf14 9eb",
    "addr:street":"Priory Way",
    "iso:country":"GB",
    "sg:address":"61 Priory Way",
    "sg:city":"Mirfield",
    "sg:classifiers":[
        {
            "category":"Professional",
            "subcategory":"Accounting & Tax Preparation",
            "type":"Services"
        }
    ],
    "sg:phone":"+44 1924 491611",
    "sg:postcode":"WF14 9EB",
    "sg:province":"West Yorkshire",
    "sg:tags":[
        "accountant"
    ],
    "wof:name":"Priory Accounting Services Ltd.",
    "wof:placetype":"venue"
},
  "geometry": {"coordinates":[-1.7065249681,53.6832427979],"type":"Point"}
}