{
  "type": "Feature",
  "properties": {
    "addr:full":"Wimblebury Road Cannock Staffordshire WS12 5EP",
    "addr:postcode":"ws12 5ep",
    "addr:street":"Wimblebury Road",
    "iso:country":"GB",
    "sg:address":"Wimblebury Road",
    "sg:city":"Cannock",
    "sg:classifiers":[
        {
            "category":"Education",
            "subcategory":"School",
            "type":"Public Place"
        }
    ],
    "sg:phone":"+44 1543 279370",
    "sg:postcode":"WS12 5EP",
    "sg:province":"Staffordshire",
    "sg:tags":[
        "local",
        "authority"
    ],
    "wof:name":"Heath Hayes Primary School",
    "wof:placetype":"venue"
},
  "geometry": {"coordinates":[-1.9772490263,52.6994361877],"type":"Point"}
}