{
  "type": "Feature",
  "properties": {
    "addr:full":"8 Binns Close Coventry Warwickshire CV4 9TB",
    "addr:housenumber":"8",
    "addr:postcode":"cv4 9tb",
    "addr:street":"Binns Close",
    "iso:country":"GB",
    "sg:address":"8 Binns Close",
    "sg:city":"Coventry",
    "sg:classifiers":[
        {
            "category":"Manufacturing",
            "subcategory":"Wood Products",
            "type":"Manufacturing & Wholesale Goods"
        }
    ],
    "sg:phone":"+44 24 7647 0074",
    "sg:postcode":"CV4 9TB",
    "sg:province":"Warwickshire",
    "sg:tags":[
        "packaging",
        "crate",
        "pallets"
    ],
    "wof:name":"Propack Automation Machinery Ltd.",
    "wof:placetype":"venue"
},
  "geometry": {"coordinates":[-1.5816869736,52.3972206116],"type":"Point"}
}