{
  "type": "Feature",
  "properties": {
    "addr:full":"Clayton Fold Farm, Oakmere Avenue, Withnell Chorley Lancashire PR6 8AX",
    "addr:postcode":"pr6 8ax",
    "addr:street":"Clayton Fold;Oakmere Avenue",
    "iso:country":"GB",
    "sg:address":"Clayton Fold Farm, Oakmere Avenue, Withnell",
    "sg:city":"Chorley",
    "sg:classifiers":[
        {
            "category":"Farming",
            "subcategory":"Livestock Farm",
            "type":"Manufacturing & Wholesale Goods"
        }
    ],
    "sg:phone":"+44 1254 830349",
    "sg:postcode":"PR6 8AX",
    "sg:province":"Lancashire",
    "sg:tags":[
        "others"
    ],
    "wof:name":"H Berry",
    "wof:placetype":"venue"
},
  "geometry": {"coordinates":[-2.5568039417,53.6921348572],"type":"Point"}
}