{
  "type": "Feature",
  "properties": {
    "addr:full":"8 Clarendon Drive London Greater London SW15 1AA",
    "addr:housenumber":"8",
    "addr:postcode":"sw15 1aa",
    "addr:street":"Clarendon Drive",
    "iso:country":"GB",
    "sg:address":"8 Clarendon Drive",
    "sg:city":"London",
    "sg:classifiers":[
        {
            "category":"Manufacturing",
            "subcategory":"Electronics",
            "type":"Manufacturing & Wholesale Goods"
        }
    ],
    "sg:postcode":"SW15 1AA",
    "sg:province":"Greater London",
    "sg:tags":[
        "control",
        "component",
        "-",
        "electronic"
    ],
    "wof:name":"Crouzet Appliance Controls",
    "wof:placetype":"venue"
},
  "geometry": {"coordinates":[-0.22229,51.464016],"type":"Point"}
}