{
  "type": "Feature",
  "properties": {
    "iso:country":"GB",
    "sg:address":"Windsor Estate, New Road",
    "sg:city":"Sheerness",
    "sg:classifiers":[
        {
            "category":"Home & Garden",
            "subcategory":"Home Furnishings",
            "type":"Retail Goods"
        },
        {
            "category":"Home & Garden",
            "subcategory":"Furniture",
            "type":"Retail Goods"
        }
    ],
    "sg:phone":"+44 1795 660426",
    "sg:postcode":"ME12 1NB",
    "sg:province":"Kent",
    "sg:tags":[
        "furnishers",
        "planner",
        "kitchen"
    ],
    "wof:name":"Windsor Fitted Furniture",
    "wof:placetype":"venue"
},
  "geometry": {"coordinates":[0.764665,51.43885],"type":"Point"}
}