{
  "type": "Feature",
  "properties": {
    "addr:full":"Muldron Quarry, Fauldhouse Bathgate North Lanarkshire EH47 9AD",
    "addr:postcode":"eh47 9ad",
    "addr:street":"Muldron;Fauldhouse Bathgate",
    "iso:country":"GB",
    "sg:address":"Muldron Quarry, Fauldhouse",
    "sg:city":"Bathgate",
    "sg:classifiers":[
        {
            "category":"Utilities",
            "subcategory":"Refuse",
            "type":"Services"
        }
    ],
    "sg:phone":"+44 1501 771185",
    "sg:postcode":"EH47 9AD",
    "sg:province":"North Lanarkshire",
    "sg:tags":[
        "disposal",
        "waste"
    ],
    "wof:name":"Levenseat Landfill",
    "wof:placetype":"venue"
},
  "geometry": {"coordinates":[-3.7066040039,55.8278808594],"type":"Point"}
}