{
  "type": "Feature",
  "properties": {
    "addr:full":"5 Enterprise Close, Warsash Southampton Hampshire SO31 9BD",
    "addr:housenumber":"5",
    "addr:postcode":"so31 9bd",
    "addr:street":"Enterprise Close",
    "iso:country":"GB",
    "sg:address":"5 Enterprise Close, Warsash",
    "sg:city":"Southampton",
    "sg:classifiers":[
        {
            "category":"Manufacturing",
            "subcategory":"Petroleum Products",
            "type":"Manufacturing & Wholesale Goods"
        }
    ],
    "sg:phone":"+44 1489 583227",
    "sg:postcode":"SO31 9BD",
    "sg:province":"Hampshire",
    "sg:tags":[
        "double",
        "glazing"
    ],
    "wof:name":"Bunny Graham Replacement Window & Door Services",
    "wof:placetype":"venue"
},
  "geometry": {"coordinates":[-1.2890189886,50.8539237976],"type":"Point"}
}