{
  "type": "Feature",
  "properties": {
    "iso:country":"GB",
    "sg:address":"Station Rd",
    "sg:city":"Littlehampton",
    "sg:classifiers":[
        {
            "category":"Organizations",
            "subcategory":"Non-profit Organization",
            "type":"Services"
        }
    ],
    "sg:phone":"+44 1903 850184",
    "sg:postcode":"BN16 4HY",
    "sg:province":"West Sussex",
    "sg:tags":[
        "organisation",
        "voluntary",
        "charity"
    ],
    "wof:name":"Arthritis Research Campaign",
    "wof:placetype":"venue"
},
  "geometry": {"coordinates":[-0.484564,50.828548],"type":"Point"}
}