{
  "type": "Feature",
  "properties": {
    "iso:country":"GB",
    "sg:address":"2 Gisburn St",
    "sg:city":"Colne",
    "sg:classifiers":[
        {
            "category":"Shopping",
            "subcategory":"News",
            "type":"Retail Goods"
        }
    ],
    "sg:phone":"+44 1282 812044",
    "sg:postcode":"BB8 7ER",
    "sg:province":"Lancashire",
    "sg:tags":[
        "newsagent"
    ],
    "wof:name":"M & S Gelgard",
    "wof:placetype":"venue"
},
  "geometry": {"coordinates":[-2.19008708,53.919631958],"type":"Point"}
}