{
  "type": "Feature",
  "properties": {
    "iso:country":"GB",
    "sg:address":"Dinham Rd",
    "sg:city":"Exeter",
    "sg:classifiers":[
        {
            "category":"Place Of Worship",
            "type":"Public Place"
        }
    ],
    "sg:phone":"+44 1392 254396",
    "sg:postcode":"EX4 4EE",
    "sg:province":"Devon",
    "wof:name":"St Michael & All Angels C Of E Church",
    "wof:placetype":"venue"
},
  "geometry": {"coordinates":[-3.536849,50.724266],"type":"Point"}
}