{
  "type": "Feature",
  "properties": {
    "iso:country":"GB",
    "sg:address":"Whatley Avenue",
    "sg:city":"London",
    "sg:classifiers":[
        {
            "category":"Education",
            "subcategory":"University",
            "type":"Public Place"
        },
        {
            "category":"Government",
            "subcategory":"Office",
            "type":"Public Place"
        }
    ],
    "sg:phone":"+44 20 8543 9292",
    "sg:postcode":"SW20 9NS",
    "sg:province":"Greater London",
    "sg:tags":[
        "local",
        "adult"
    ],
    "wof:name":"Merton Adult College",
    "wof:placetype":"venue"
},
  "geometry": {"coordinates":[-0.2128559947,51.4073181152],"type":"Point"}
}