{
  "type": "Feature",
  "properties": {
    "addr:full":"Scottish Life House Northampton Northamptonshire NN1 2QZ",
    "addr:postcode":"nn1 2qz",
    "iso:country":"GB",
    "sg:address":"Scottish Life House",
    "sg:city":"Northampton",
    "sg:classifiers":[
        {
            "category":"Professional",
            "subcategory":"Management & Consulting",
            "type":"Services"
        },
        {
            "category":"Professional",
            "subcategory":"Engineering",
            "type":"Services"
        }
    ],
    "sg:phone":"+44 1604 233360",
    "sg:postcode":"NN1 2QZ",
    "sg:province":"Northamptonshire",
    "sg:tags":[
        "consultant",
        "business",
        "engineer"
    ],
    "wof:name":"Logistics Support Analysts Ltd.",
    "wof:placetype":"venue"
},
  "geometry": {"coordinates":[-0.903703,52.242229],"type":"Point"}
}