{
  "type": "Feature",
  "properties": {
    "addr:full":"49 Oakwood Avenue London Greater London N14 6QH",
    "addr:housenumber":"49",
    "addr:postcode":"n14 6qh",
    "addr:street":"Oakwood Avenue",
    "iso:country":"GB",
    "sg:address":"49 Oakwood Avenue",
    "sg:city":"London",
    "sg:classifiers":[
        {
            "category":"Building & Trades",
            "subcategory":"Construction",
            "type":"Services"
        }
    ],
    "sg:phone":"+44 20 8882 9685",
    "sg:postcode":"N14 6QH",
    "sg:province":"Greater London",
    "sg:tags":[
        "builder"
    ],
    "wof:name":"V M G Construction Ltd.",
    "wof:placetype":"venue"
},
  "geometry": {"coordinates":[-0.124211,51.637295],"type":"Point"}
}