{
  "type": "Feature",
  "properties": {
    "addr:full":"12 Pendrell Rd London Greater London SE4 2PB",
    "addr:housenumber":"12",
    "addr:postcode":"se4 2pb",
    "addr:street":"Pendrell Rd",
    "iso:country":"GB",
    "sg:address":"12 Pendrell Rd",
    "sg:city":"London",
    "sg:classifiers":[
        {
            "category":"Building & Trades",
            "subcategory":"Plumbing",
            "type":"Services"
        }
    ],
    "sg:postcode":"SE4 2PB",
    "sg:province":"Greater London",
    "sg:tags":[
        "central",
        "heating"
    ],
    "wof:name":"Moodie,N,",
    "wof:placetype":"venue"
},
  "geometry": {"coordinates":[-0.0427680016,51.4665603638],"type":"Point"}
}