{
  "type": "Feature",
  "properties": {
    "iso:country":"GB",
    "sg:address":"27 Mid Rd",
    "sg:city":"Biggar",
    "sg:classifiers":[
        {
            "category":"Farming",
            "subcategory":"Dairy Farm",
            "type":"Manufacturing & Wholesale Goods"
        }
    ],
    "sg:phone":"+44 1899 221601",
    "sg:postcode":"ML12 6AW",
    "sg:province":"Dumfries and Galloway",
    "sg:tags":[
        "farmer"
    ],
    "wof:name":"Hugh M Jackson",
    "wof:placetype":"venue"
},
  "geometry": {"coordinates":[-3.513251,55.626572],"type":"Point"}
}