{
  "type": "Feature",
  "properties": {
    "addr:full":"Widford Lodge School, Widford Chelmsford Essex CM2 9AN",
    "addr:postcode":"cm2 9an",
    "iso:country":"GB",
    "sg:address":"Widford Lodge School, Widford",
    "sg:city":"Chelmsford",
    "sg:classifiers":[
        {
            "category":"Education",
            "subcategory":"School",
            "type":"Public Place"
        }
    ],
    "sg:phone":"+44 1245 352581",
    "sg:postcode":"CM2 9AN",
    "sg:province":"Essex",
    "sg:tags":[
        "independent",
        "preparatory"
    ],
    "wof:name":"Widford Lodge School Ltd.",
    "wof:placetype":"venue"
},
  "geometry": {"coordinates":[0.458281,51.720329],"type":"Point"}
}