{
  "type": "Feature",
  "properties": {
    "addr:full":"127-128 Newport Provision Market, Dock Street Newport East Riding of Yorkshire NP9 1DE",
    "addr:housenumber":"127-128",
    "addr:postcode":"np9 1de",
    "addr:street":"Newport;Dock Street",
    "iso:country":"GB",
    "sg:address":"127-128 Newport Provision Market, Dock Street",
    "sg:city":"Newport",
    "sg:classifiers":[
        {
            "category":"Food & Beverages",
            "subcategory":"Meat & Fish",
            "type":"Retail Goods"
        }
    ],
    "sg:phone":"+44 1633 262641",
    "sg:postcode":"NP9 1DE",
    "sg:province":"East Riding of Yorkshire",
    "sg:tags":[
        "butcher"
    ],
    "wof:name":"D R Wyatt",
    "wof:placetype":"venue"
},
  "geometry": {"coordinates":[-2.9953889847,51.5892944336],"type":"Point"}
}