{
  "type": "Feature",
  "properties": {
    "addr:full":"883-885 Finchley Road, Golders Grn London Greater London NW11 8RR",
    "addr:housenumber":"883-885",
    "addr:postcode":"nw11 8rr",
    "addr:street":"Finchley Road Golders Grn",
    "iso:country":"GB",
    "sg:address":"883-885 Finchley Road, Golders Grn",
    "sg:city":"London",
    "sg:classifiers":[
        {
            "category":"Banks & Credit Unions",
            "subcategory":"Bank",
            "type":"Services"
        }
    ],
    "sg:phone":"+44 20 8218 6000",
    "sg:postcode":"NW11 8RR",
    "sg:province":"Greater London",
    "wof:name":"Barclays Bank Plc",
    "wof:placetype":"venue"
},
  "geometry": {"coordinates":[-0.1955730021,51.5713119507],"type":"Point"}
}