{
  "type": "Feature",
  "properties": {
    "addr:full":"Unit 1-2 Building 2, Sandwich Industrial Estate Sandwich Kent CT13 9LY",
    "addr:housenumber":"unit",
    "addr:postcode":"ct13 9ly",
    "addr:street":"Building;Sandwich Industrial",
    "iso:country":"GB",
    "sg:address":"Unit 1-2 Building 2, Sandwich Industrial Estate",
    "sg:city":"Sandwich",
    "sg:classifiers":[
        {
            "category":"Social Services",
            "subcategory":"Child Care",
            "type":"Services"
        }
    ],
    "sg:phone":"+44 1304 620971",
    "sg:postcode":"CT13 9LY",
    "sg:province":"Kent",
    "sg:tags":[
        "children's",
        "home"
    ],
    "wof:name":"Lynstead Childrens Services",
    "wof:placetype":"venue"
},
  "geometry": {"coordinates":[1.3423039913,51.2761688232],"type":"Point"}
}