{
  "type": "Feature",
  "properties": {
    "iso:country":"GB",
    "sg:address":"Grange Brook, Rags Lane, Cheshunt",
    "sg:city":"Waltham Cross",
    "sg:classifiers":[
        {
            "category":"Autos & Motor Vehicles",
            "subcategory":"Automobile Sales",
            "type":"Retail Goods"
        }
    ],
    "sg:phone":"+44 1707 875508",
    "sg:postcode":"EN7 6TD",
    "sg:province":"Greater London",
    "sg:tags":[
        "commercial"
    ],
    "wof:name":"Hertfordshire Commercial Vehicles",
    "wof:placetype":"venue"
},
  "geometry": {"coordinates":[-0.0744400024,51.715171814],"type":"Point"}
}