{
  "type": "Feature",
  "properties": {
    "iso:country":"GB",
    "sg:address":"13 Hurst Rd",
    "sg:city":"Farnborough",
    "sg:classifiers":[
        {
            "category":"Building & Trades",
            "subcategory":"Plumbing",
            "type":"Services"
        }
    ],
    "sg:phone":"+44 1252 515291",
    "sg:postcode":"GU14 8HE",
    "sg:province":"Hampshire",
    "sg:tags":[
        "heating"
    ],
    "wof:name":"Auto Plumbing",
    "wof:placetype":"venue"
},
  "geometry": {"coordinates":[-0.758968,51.312111],"type":"Point"}
}