{
  "type": "Feature",
  "properties": {
    "iso:country":"GB",
    "sg:address":"The Surgery, Ferrindonald, Teangue",
    "sg:city":"Isle Of Skye",
    "sg:classifiers":[
        {
            "category":"Health Services",
            "subcategory":"Doctor",
            "type":"Services"
        }
    ],
    "sg:phone":"+44 1471 844283",
    "sg:postcode":"IV44 8RF",
    "sg:province":"Highland",
    "sg:tags":[
        "practitioners"
    ],
    "wof:name":"Venters",
    "wof:placetype":"venue"
},
  "geometry": {"coordinates":[-5.86816,57.096741],"type":"Point"}
}