{
  "type": "Feature",
  "properties": {
    "iso:country":"GB",
    "sg:address":"Whimpwell Green",
    "sg:city":"Norwich",
    "sg:classifiers":[
        {
            "category":"Shopping",
            "subcategory":"Department Store",
            "type":"Retail Goods"
        }
    ],
    "sg:postcode":"NR12 0AJ",
    "sg:province":"Norfolk",
    "wof:name":"Lower Happisburgh Post Office",
    "wof:placetype":"venue"
},
  "geometry": {"coordinates":[1.5332030058,52.8189964294],"type":"Point"}
}