{
  "type": "Feature",
  "properties": {
    "iso:country":"GB",
    "sg:address":"Trafalgular House, Navigation Rd",
    "sg:city":"Altrincham",
    "sg:classifiers":[
        {
            "category":"Shopping",
            "subcategory":"Computers & Home Electronics",
            "type":"Retail Goods"
        }
    ],
    "sg:phone":"+44 161 941 2727",
    "sg:postcode":"WA14 1NF",
    "sg:province":"Cheshire",
    "wof:name":"Epicor Systems",
    "wof:placetype":"venue"
},
  "geometry": {"coordinates":[-2.351409,53.397594],"type":"Point"}
}