{
  "type": "Feature",
  "properties": {
    "addr:full":"11 Woods Terr, Murton Colliery Seaham Durham SR7 9AD",
    "addr:housenumber":"11",
    "addr:postcode":"sr7 9ad",
    "addr:street":"Woods Terr",
    "iso:country":"GB",
    "sg:address":"11 Woods Terr, Murton Colliery",
    "sg:city":"Seaham",
    "sg:classifiers":[
        {
            "category":"Food & Beverages",
            "subcategory":"Meat & Fish",
            "type":"Retail Goods"
        }
    ],
    "sg:postcode":"SR7 9AD",
    "sg:province":"Durham",
    "sg:tags":[
        "butcher"
    ],
    "wof:name":"Dewhurst Butchers Ltd",
    "wof:placetype":"venue"
},
  "geometry": {"coordinates":[-1.3838729858,54.8169975281],"type":"Point"}
}