{
  "type": "Feature",
  "properties": {
    "iso:country":"GB",
    "sg:address":"Panescentre, 292 Vauxhall Bridge Road",
    "sg:city":"London",
    "sg:classifiers":[
        {
            "category":"Communications",
            "subcategory":"News Services",
            "type":"Services"
        }
    ],
    "sg:phone":"+44 20 7963 7000",
    "sg:postcode":"SW1V 1AE",
    "sg:province":"Greater London",
    "sg:tags":[
        "photo",
        "agency"
    ],
    "wof:name":"The Press Association Ltd.",
    "wof:placetype":"venue"
},
  "geometry": {"coordinates":[-0.14139,51.49509],"type":"Point"}
}