{
  "type": "Feature",
  "properties": {
    "addr:full":"Malltraeth Bodorgan Isle of Anglesey LL62 5BA",
    "addr:postcode":"ll62 5ba",
    "addr:street":"Bodorgan",
    "iso:country":"GB",
    "sg:address":"Malltraeth",
    "sg:city":"Bodorgan",
    "sg:classifiers":[
        {
            "category":"Recreation",
            "subcategory":"Campground",
            "type":"Entertainment"
        }
    ],
    "sg:postcode":"LL62 5BA",
    "sg:province":"Isle of Anglesey",
    "sg:tags":[
        "site",
        "camping"
    ],
    "wof:name":"Pen-y-Bont Farm Touring & Camp Site",
    "wof:placetype":"venue"
},
  "geometry": {"coordinates":[-4.4229488373,53.1828117371],"type":"Point"}
}