{
  "type": "Feature",
  "properties": {
    "iso:country":"GB",
    "sg:address":"43 Sandon Road, Cresswell",
    "sg:city":"Stoke-on-trent",
    "sg:classifiers":[
        {
            "category":"Banks & Credit Unions",
            "subcategory":"Financial Services",
            "type":"Services"
        }
    ],
    "sg:postcode":"ST11 9RB",
    "sg:province":"Staffordshire",
    "sg:tags":[
        "consultant"
    ],
    "wof:name":"Hanroe Finance",
    "wof:placetype":"venue"
},
  "geometry": {"coordinates":[-2.039405,52.950142],"type":"Point"}
}