{
  "type": "Feature",
  "properties": {
    "iso:country":"GB",
    "sg:address":"2-3 Gateway Arcade, 355 Upper Street",
    "sg:city":"London",
    "sg:classifiers":[
        {
            "category":"Shopping",
            "subcategory":"Antiques",
            "type":"Retail Goods"
        }
    ],
    "sg:phone":"+44 20 7359 6839",
    "sg:postcode":"N1 0PG",
    "sg:province":"Greater London",
    "wof:name":"Hart & Rosenberg",
    "wof:placetype":"venue"
},
  "geometry": {"coordinates":[-0.10449,51.5345],"type":"Point"}
}