{
  "type": "Feature",
  "properties": {
    "addr:full":"Old Town Jail, 14/18 London Road Sevenoaks Kent TN13 1AJ",
    "addr:housenumber":"14 / 18",
    "addr:postcode":"tn13 1aj",
    "addr:street":"London Road",
    "iso:country":"GB",
    "sg:address":"Old Town Jail, 14/18 London Road",
    "sg:city":"Sevenoaks",
    "sg:classifiers":[
        {
            "category":"Shopping",
            "subcategory":"Books",
            "type":"Retail Goods"
        }
    ],
    "sg:phone":"+44 1732 463356",
    "sg:postcode":"TN13 1AJ",
    "sg:province":"Kent",
    "wof:name":"Fordwise Ltd.",
    "wof:placetype":"venue"
},
  "geometry": {"coordinates":[0.1929389983,51.270198822],"type":"Point"}
}