{
  "type": "Feature",
  "properties": {
    "addr:full":"Clare House Worton Hall Industri, Al Estate Isleworth Greater London TW7 6ER",
    "addr:postcode":"tw7 6er",
    "addr:street":"Industri Al Estate",
    "iso:country":"GB",
    "sg:address":"Clare House Worton Hall Industri, Al Estate",
    "sg:city":"Isleworth",
    "sg:classifiers":[
        {
            "category":"Banks & Credit Unions",
            "subcategory":"Financial Services",
            "type":"Services"
        }
    ],
    "sg:phone":"+44 20 8560 1111",
    "sg:postcode":"TW7 6ER",
    "sg:province":"Greater London",
    "sg:tags":[
        "adviser"
    ],
    "wof:name":"Peter Hobbs (Life & Pensions) Ltd.",
    "wof:placetype":"venue"
},
  "geometry": {"coordinates":[-0.3382329941,51.4739151001],"type":"Point"}
}