{
  "type": "Feature",
  "properties": {
    "addr:full":"Pavilion, Ironmills Rd Dalkeith City of Edinburgh EH22 1JN",
    "addr:postcode":"eh22 1jn",
    "addr:street":"Ironmills Rd",
    "iso:country":"GB",
    "sg:address":"Pavilion, Ironmills Rd",
    "sg:city":"Dalkeith",
    "sg:classifiers":[
        {
            "category":"Arena",
            "subcategory":"Stadium",
            "type":"Entertainment"
        },
        {
            "category":"Arena",
            "subcategory":"Sports Club",
            "type":"Entertainment"
        }
    ],
    "sg:phone":"+44 131 654 1213",
    "sg:postcode":"EH22 1JN",
    "sg:province":"City of Edinburgh",
    "sg:tags":[
        "ground"
    ],
    "wof:name":"Ironmills Park",
    "wof:placetype":"venue"
},
  "geometry": {"coordinates":[-3.0686130524,55.8928794861],"type":"Point"}
}