{
  "type": "Feature",
  "properties": {
    "iso:country":"GB",
    "sg:address":"Whitehall Road",
    "sg:city":"Bristol",
    "sg:classifiers":[
        {
            "category":"Bars & Pubs",
            "type":"Food & Drink"
        }
    ],
    "sg:phone":"+44 117 951 7082",
    "sg:postcode":"BS5 7BH",
    "sg:province":"City of Bristol",
    "sg:tags":[
        "pubs",
        "inn"
    ],
    "wof:name":"Inntrepreneur Pub Co.",
    "wof:placetype":"venue"
},
  "geometry": {"coordinates":[-2.5509159565,51.4641799927],"type":"Point"}
}