{
  "type": "Feature",
  "properties": {
    "iso:country":"GB",
    "sg:address":"32 Straight Rd",
    "sg:city":"Romford",
    "sg:classifiers":[
        {
            "category":"Building & Trades",
            "subcategory":"Construction",
            "type":"Services"
        }
    ],
    "sg:postcode":"RM3 8AA",
    "sg:province":"Essex",
    "sg:tags":[
        "roofing"
    ],
    "wof:name":"Smith,Geoffrey Colin,",
    "wof:placetype":"venue"
},
  "geometry": {"coordinates":[0.213206,51.594303],"type":"Point"}
}