{
  "type": "Feature",
  "properties": {
    "iso:country":"GB",
    "sg:address":"3 South Street, Portslade",
    "sg:city":"Brighton",
    "sg:classifiers":[
        {
            "category":"Food & Beverages",
            "subcategory":"Meat & Fish",
            "type":"Retail Goods"
        }
    ],
    "sg:postcode":"BN41 2LE",
    "sg:province":"East Sussex",
    "sg:tags":[
        "chip"
    ],
    "wof:name":"Rainbow Fish Bar",
    "wof:placetype":"venue"
},
  "geometry": {"coordinates":[-0.218314,50.842243],"type":"Point"}
}