{
  "type": "Feature",
  "properties": {
    "addr:full":"Glenthorne Avenue Yeovil Somerset BA21 4PG",
    "addr:postcode":"ba21 4pg",
    "addr:street":"Glenthorne Avenue",
    "iso:country":"GB",
    "sg:address":"Glenthorne Avenue",
    "sg:city":"Yeovil",
    "sg:classifiers":[
        {
            "category":"Education",
            "subcategory":"School",
            "type":"Public Place"
        },
        {
            "category":"Government",
            "subcategory":"Office",
            "type":"Public Place"
        }
    ],
    "sg:phone":"+44 1935 474477",
    "sg:postcode":"BA21 4PG",
    "sg:province":"Somerset",
    "sg:tags":[
        "local",
        "authority"
    ],
    "wof:name":"Milford Junior School",
    "wof:placetype":"venue"
},
  "geometry": {"coordinates":[-2.626819,50.955013],"type":"Point"}
}