{
  "type": "Feature",
  "properties": {
    "iso:country":"GB",
    "sg:address":"New St, Biddulph Moor",
    "sg:city":"Stoke-on-trent",
    "sg:classifiers":[
        {
            "category":"Farming",
            "subcategory":"Dairy Farm",
            "type":"Manufacturing & Wholesale Goods"
        }
    ],
    "sg:postcode":"ST8 7NW",
    "sg:province":"Staffordshire",
    "wof:name":"Bailey,Douglas,",
    "wof:placetype":"venue"
},
  "geometry": {"coordinates":[-2.141274,53.120323],"type":"Point"}
}