{
  "type": "Feature",
  "properties": {
    "addr:full":"Scatterty Banff Aberdeenshire AB45 3PA",
    "addr:postcode":"ab45 3pa",
    "iso:country":"GB",
    "sg:address":"Scatterty",
    "sg:city":"Banff",
    "sg:classifiers":[
        {
            "category":"Farming",
            "subcategory":"Farm",
            "type":"Manufacturing & Wholesale Goods"
        }
    ],
    "sg:phone":"+44 1261 821665",
    "sg:postcode":"AB45 3PA",
    "sg:province":"Aberdeenshire",
    "sg:tags":[
        "mixed",
        "crop"
    ],
    "wof:name":"Alexander Urquhart",
    "wof:placetype":"venue"
},
  "geometry": {"coordinates":[-2.4760389328,57.6374092102],"type":"Point"}
}