{
  "type": "Feature",
  "properties": {
    "addr:full":"513 Etruria Rd Stoke On Trent Staffordshire ST4 6HT",
    "addr:housenumber":"513",
    "addr:postcode":"st4 6ht",
    "addr:street":"Etruria Rd",
    "iso:country":"GB",
    "sg:address":"513 Etruria Rd",
    "sg:city":"Stoke On Trent",
    "sg:classifiers":[
        {
            "category":"Health Services",
            "subcategory":"Chiropractor",
            "type":"Services"
        }
    ],
    "sg:phone":"+44 1782 627133",
    "sg:postcode":"ST4 6HT",
    "sg:province":"Staffordshire",
    "wof:name":"Basford Chiropractic Clinic",
    "wof:placetype":"venue"
},
  "geometry": {"coordinates":[-2.209624,53.016361],"type":"Point"}
}