{
  "type": "Feature",
  "properties": {
    "addr:full":"Church Street, Micheldever Winchester Hampshire SO21 3DB",
    "addr:postcode":"so21 3db",
    "addr:street":"Church Street",
    "iso:country":"GB",
    "sg:address":"Church Street, Micheldever",
    "sg:city":"Winchester",
    "sg:classifiers":[
        {
            "category":"Education",
            "subcategory":"School",
            "type":"Public Place"
        }
    ],
    "sg:phone":"+44 1962 774213",
    "sg:postcode":"SO21 3DB",
    "sg:province":"Hampshire",
    "sg:tags":[
        "local",
        "authority"
    ],
    "wof:name":"Micheldever C of E Primary School",
    "wof:placetype":"venue"
},
  "geometry": {"coordinates":[-1.2605600357,51.1786842346],"type":"Point"}
}