{
  "type": "Feature",
  "properties": {
    "addr:full":"3a Cuxton Road, Strood Rochester Kent ME2 2BT",
    "addr:housenumber":"3a",
    "addr:postcode":"me2 2bt",
    "addr:street":"Cuxton Road",
    "iso:country":"GB",
    "sg:address":"3a Cuxton Road, Strood",
    "sg:city":"Rochester",
    "sg:classifiers":[
        {
            "category":"Home & Garden",
            "subcategory":"Household Appliances",
            "type":"Retail Goods"
        }
    ],
    "sg:postcode":"ME2 2BT",
    "sg:province":"Kent",
    "sg:tags":[
        "domestic",
        "centre"
    ],
    "wof:name":"Recycled Appliances",
    "wof:placetype":"venue"
},
  "geometry": {"coordinates":[0.4912930131,51.3955841064],"type":"Point"}
}