{
  "type": "Feature",
  "properties": {
    "iso:country":"GB",
    "sg:address":"36 Castle Street",
    "sg:city":"Hertford",
    "sg:classifiers":[
        {
            "category":"Professional",
            "subcategory":"Management & Consulting",
            "type":"Services"
        }
    ],
    "sg:phone":"+44 1992 503512",
    "sg:postcode":"SG14 1HH",
    "sg:province":"Hertfordshire",
    "sg:tags":[
        "consultant",
        "business"
    ],
    "wof:name":"Stort Valley Enterprise Agency",
    "wof:placetype":"venue"
},
  "geometry": {"coordinates":[-0.079096,51.794849],"type":"Point"}
}