{
  "type": "Feature",
  "properties": {
    "iso:country":"GB",
    "sg:address":"Silver Ho, 32 Silver St",
    "sg:city":"Doncaster",
    "sg:classifiers":[
        {
            "category":"Government",
            "subcategory":"Office",
            "type":"Public Place"
        }
    ],
    "sg:phone":"+44 1302 368165",
    "sg:postcode":"DN1 1HR",
    "sg:province":"South Yorkshire",
    "sg:tags":[
        "central"
    ],
    "wof:name":"H M Inspectorate Of Mines Health & Safety Executive",
    "wof:placetype":"venue"
},
  "geometry": {"coordinates":[-1.130565,53.524391],"type":"Point"}
}