{
  "type": "Feature",
  "properties": {
    "iso:country":"GB",
    "sg:address":"41-43 Boltro Road",
    "sg:city":"Haywards Heath",
    "sg:classifiers":[
        {
            "category":"Health Services",
            "subcategory":"Health Practitioner",
            "type":"Services"
        }
    ],
    "sg:phone":"+44 1444 413743",
    "sg:postcode":"RH16 1BJ",
    "sg:province":"East Sussex",
    "sg:tags":[
        "physiotherapist"
    ],
    "wof:name":"Oathall Physiotherapy Clinic",
    "wof:placetype":"venue"
},
  "geometry": {"coordinates":[-0.107601,51.001713],"type":"Point"}
}