{
  "type": "Feature",
  "properties": {
    "addr:full":"77 St John Street Bridgwater Somerset TA6 5HX",
    "addr:housenumber":"77",
    "addr:postcode":"ta6 5hx",
    "addr:street":"St John Street",
    "iso:country":"GB",
    "sg:address":"77 St John Street",
    "sg:city":"Bridgwater",
    "sg:classifiers":[
        {
            "category":"Shopping",
            "subcategory":"News",
            "type":"Retail Goods"
        }
    ],
    "sg:phone":"+44 1278 453921",
    "sg:postcode":"TA6 5HX",
    "sg:province":"Somerset",
    "sg:tags":[
        "newsagent"
    ],
    "wof:name":"Scoops",
    "wof:placetype":"venue"
},
  "geometry": {"coordinates":[-2.9942319393,51.1281776428],"type":"Point"}
}