{
  "type": "Feature",
  "properties": {
    "addr:full":"86 Barrowby Road Grantham Lincolnshire NG31 8AF",
    "addr:housenumber":"86",
    "addr:postcode":"ng31 8af",
    "addr:street":"Barrowby Road",
    "iso:country":"GB",
    "sg:address":"86 Barrowby Road",
    "sg:city":"Grantham",
    "sg:classifiers":[
        {
            "category":"Organizations",
            "subcategory":"Non-profit Organization",
            "type":"Services"
        }
    ],
    "sg:phone":"+44 1476 591010",
    "sg:postcode":"NG31 8AF",
    "sg:province":"Lincolnshire",
    "sg:tags":[
        "organisation",
        "voluntary",
        "charity"
    ],
    "wof:name":"Gifts Hospice Services",
    "wof:placetype":"venue"
},
  "geometry": {"coordinates":[-0.650733,52.916767],"type":"Point"}
}