{
  "type": "Feature",
  "properties": {
    "addr:full":"75 Feltham Road Ashford Greater London TW15 1DB",
    "addr:housenumber":"75",
    "addr:postcode":"tw15 1db",
    "addr:street":"Feltham Road",
    "iso:country":"GB",
    "sg:address":"75 Feltham Road",
    "sg:city":"Ashford",
    "sg:classifiers":[
        {
            "category":"Shopping",
            "subcategory":"News",
            "type":"Retail Goods"
        }
    ],
    "sg:phone":"+44 1784 254431",
    "sg:postcode":"TW15 1DB",
    "sg:province":"Greater London",
    "sg:tags":[
        "newsagent"
    ],
    "wof:name":"The Corner Shop",
    "wof:placetype":"venue"
},
  "geometry": {"coordinates":[-0.451756,51.432697],"type":"Point"}
}