{
  "type": "Feature",
  "properties": {
    "addr:full":"24a Park Street Bath Bath and North East Somerset BA1 2TF",
    "addr:housenumber":"24a",
    "addr:postcode":"ba1 2tf",
    "addr:street":"Park Street",
    "iso:country":"GB",
    "sg:address":"24a Park Street",
    "sg:city":"Bath",
    "sg:classifiers":[
        {
            "category":"Professional",
            "subcategory":"Engineering",
            "type":"Services"
        }
    ],
    "sg:phone":"+44 1225 423819",
    "sg:postcode":"BA1 2TF",
    "sg:province":"Bath and North East Somerset",
    "sg:tags":[
        "engineer",
        "mechanical"
    ],
    "wof:name":"NICK FRASER TECHNICAL SERVICES LTD",
    "wof:placetype":"venue"
},
  "geometry": {"coordinates":[-2.367837,51.390938],"type":"Point"}
}