{
  "type": "Feature",
  "properties": {
    "iso:country":"GB",
    "sg:address":"16 Ridgmount Street",
    "sg:city":"Bedford",
    "sg:classifiers":[
        {
            "category":"Retail",
            "subcategory":"Photofinishing",
            "type":"Services"
        },
        {
            "category":"Professional",
            "subcategory":"Art Services",
            "type":"Services"
        }
    ],
    "sg:phone":"+44 1234 340152",
    "sg:postcode":"MK42 9HR",
    "sg:province":"Bedfordshire",
    "sg:tags":[
        "photographer",
        "photographic",
        "processor"
    ],
    "wof:name":"R & R Galletta",
    "wof:placetype":"venue"
},
  "geometry": {"coordinates":[-0.469925,52.126225],"type":"Point"}
}