{
  "type": "Feature",
  "properties": {
    "addr:full":"56 Exning Road Newmarket Cambridgeshire CB8 7JG",
    "addr:housenumber":"56",
    "addr:postcode":"cb8 7jg",
    "addr:street":"Exning Road",
    "iso:country":"GB",
    "sg:address":"56 Exning Road",
    "sg:city":"Newmarket",
    "sg:classifiers":[
        {
            "category":"Health Services",
            "subcategory":"Hospital",
            "type":"Services"
        },
        {
            "category":"Professional",
            "subcategory":"Computer Services",
            "type":"Services"
        }
    ],
    "sg:phone":"+44 1638 564000",
    "sg:postcode":"CB8 7JG",
    "sg:province":"Cambridgeshire",
    "sg:tags":[
        "system",
        "software"
    ],
    "wof:name":"Newmarket Hospital",
    "wof:placetype":"venue"
},
  "geometry": {"coordinates":[0.38552,52.258129],"type":"Point"}
}