{
  "type": "Feature",
  "properties": {
    "iso:country":"GB",
    "sg:address":"9 High Street",
    "sg:city":"Luton",
    "sg:classifiers":[
        {
            "category":"Shopping",
            "subcategory":"News",
            "type":"Retail Goods"
        }
    ],
    "sg:phone":"+44 1582 571774",
    "sg:postcode":"LU4 9JU",
    "sg:province":"Bedfordshire",
    "sg:tags":[
        "newsagent"
    ],
    "wof:name":"Leagrave Newsagent",
    "wof:placetype":"venue"
},
  "geometry": {"coordinates":[-0.463647,51.902618],"type":"Point"}
}