{
  "type": "Feature",
  "properties": {
    "addr:full":"64 Bath Rd Swindon Wiltshire SN1 4AY",
    "addr:housenumber":"64",
    "addr:postcode":"sn1 4ay",
    "addr:street":"Bath Rd",
    "iso:country":"GB",
    "sg:address":"64 Bath Rd",
    "sg:city":"Swindon",
    "sg:classifiers":[
        {
            "category":"Health Services",
            "subcategory":"Nursing And Care Facility",
            "type":"Services"
        }
    ],
    "sg:phone":"+44 1793 618137",
    "sg:postcode":"SN1 4AY",
    "sg:province":"Wiltshire",
    "sg:tags":[
        "home"
    ],
    "wof:name":"Mary Court",
    "wof:placetype":"venue"
},
  "geometry": {"coordinates":[-1.783275,51.552628],"type":"Point"}
}