{
  "type": "Feature",
  "properties": {
    "iso:country":"GB",
    "sg:address":"4 Tarleton Avenue",
    "sg:city":"Woodhall Spa",
    "sg:classifiers":[
        {
            "category":"Military Area",
            "subcategory":"Air Force Base",
            "type":"Public Place"
        }
    ],
    "sg:phone":"+44 1526 352178",
    "sg:postcode":"LN10 6SE",
    "sg:province":"Lincolnshire",
    "sg:tags":[
        "taxi",
        "hire",
        "private"
    ],
    "wof:name":"Spa Taxi Service",
    "wof:placetype":"venue"
},
  "geometry": {"coordinates":[-0.2057940066,53.1534194946],"type":"Point"}
}