{
  "type": "Feature",
  "properties": {
    "iso:country":"GB",
    "sg:address":"9 Orwell Furlong",
    "sg:city":"Cambridge",
    "sg:classifiers":[
        {
            "category":"Professional",
            "subcategory":"Art Services",
            "type":"Services"
        }
    ],
    "sg:postcode":"CB4 0WY",
    "sg:province":"Cambridgeshire",
    "sg:tags":[
        "graphic",
        "designer"
    ],
    "wof:name":"Cardinal Graphics",
    "wof:placetype":"venue"
},
  "geometry": {"coordinates":[0.15146,52.23138],"type":"Point"}
}