{
  "type": "Feature",
  "properties": {
    "iso:country":"GB",
    "sg:address":"Church Street",
    "sg:city":"Bingley",
    "sg:classifiers":[
        {
            "category":"Government",
            "subcategory":"Office",
            "type":"Public Place"
        }
    ],
    "sg:phone":"+44 1274 564977",
    "sg:postcode":"BD16 2PP",
    "sg:province":"West Yorkshire",
    "sg:tags":[
        "local"
    ],
    "wof:name":"Holy Trinity C of E First School",
    "wof:placetype":"venue"
},
  "geometry": {"coordinates":[-1.831659,53.846432],"type":"Point"}
}