{
  "type": "Feature",
  "properties": {
    "iso:country":"GB",
    "sg:address":"29-31 Surrey Street",
    "sg:city":"Sheffield",
    "sg:classifiers":[
        {
            "category":"Shopping",
            "subcategory":"Comic Books",
            "type":"Retail Goods"
        }
    ],
    "sg:phone":"+44 114 273 7644",
    "sg:postcode":"S1 2LG",
    "sg:province":"South Yorkshire",
    "sg:tags":[
        "jeweller"
    ],
    "wof:name":"Leslie Cass (Jewellers) Ltd.",
    "wof:placetype":"venue"
},
  "geometry": {"coordinates":[-1.469753027,53.3808784485],"type":"Point"}
}