{
  "type": "Feature",
  "properties": {
    "iso:country":"GB",
    "sg:address":"7 Warwick Road",
    "sg:city":"Carlisle",
    "sg:classifiers":[
        {
            "category":"Shopping",
            "subcategory":"Pharmacy",
            "type":"Retail Goods"
        }
    ],
    "sg:phone":"+44 1228 525228",
    "sg:postcode":"CA1 1DH",
    "sg:province":"Cumbria",
    "sg:tags":[
        "medicine",
        "therapy"
    ],
    "wof:name":"The Health Food Centre",
    "wof:placetype":"venue"
},
  "geometry": {"coordinates":[-2.932389,54.892727],"type":"Point"}
}