{
  "type": "Feature",
  "properties": {
    "addr:full":"33 Mkt Sq Bicester Oxfordshire OX26 6AG",
    "addr:housenumber":"33",
    "addr:postcode":"ox26 6ag",
    "addr:street":"Mkt Sq",
    "iso:country":"GB",
    "sg:address":"33 Mkt Sq",
    "sg:city":"Bicester",
    "sg:classifiers":[
        {
            "category":"Banks & Credit Unions",
            "subcategory":"Financial Services",
            "type":"Services"
        }
    ],
    "sg:postcode":"OX26 6AG",
    "sg:province":"Oxfordshire",
    "sg:tags":[
        "building",
        "society"
    ],
    "wof:name":"Nationwide Building Society",
    "wof:placetype":"venue"
},
  "geometry": {"coordinates":[-1.1510740519,51.8965530396],"type":"Point"}
}