{
  "type": "Feature",
  "properties": {
    "addr:full":"Digswell Place Stables, Digswell Hill Welwyn Garden City Hertfordshire AL8 7SU",
    "addr:postcode":"al8 7su",
    "addr:street":"Digswell Place;Digswell Hill",
    "iso:country":"GB",
    "sg:address":"Digswell Place Stables, Digswell Hill",
    "sg:city":"Welwyn Garden City",
    "sg:classifiers":[
        {
            "category":"Sports & Exercise",
            "subcategory":"Stables",
            "type":"Entertainment"
        }
    ],
    "sg:phone":"+44 1707 332159",
    "sg:postcode":"AL8 7SU",
    "sg:province":"Hertfordshire",
    "sg:tags":[
        "education",
        "equestrian"
    ],
    "wof:name":"Digswell Place R D A Group",
    "wof:placetype":"venue"
},
  "geometry": {"coordinates":[-0.21987,51.813541],"type":"Point"}
}