{
  "type": "Feature",
  "properties": {
    "iso:country":"GB",
    "sg:address":"91 High St",
    "sg:city":"Forres",
    "sg:classifiers":[
        {
            "category":"Communications",
            "type":"Services"
        }
    ],
    "sg:postcode":"IV36 1AA",
    "sg:province":"Moray",
    "sg:tags":[
        "telecommunication"
    ],
    "wof:name":"Scottish Property Network",
    "wof:placetype":"venue"
},
  "geometry": {"coordinates":[-3.6134929657,57.6100616455],"type":"Point"}
}