{
  "type": "Feature",
  "properties": {
    "addr:full":"Unit 35 Marsh Way Fariview Indus, T Estate Rainham Essex RM13 8RH",
    "addr:housenumber":"unit 35",
    "addr:postcode":"rm13 8rh",
    "addr:street":"Marsh Way Fariview Indus T Estate",
    "iso:country":"GB",
    "sg:address":"Unit 35 Marsh Way Fariview Indus, T Estate",
    "sg:city":"Rainham",
    "sg:classifiers":[
        {
            "category":"Professional",
            "subcategory":"Engineering",
            "type":"Services"
        }
    ],
    "sg:phone":"+44 1708 556513",
    "sg:postcode":"RM13 8RH",
    "sg:province":"Essex",
    "sg:tags":[
        "civil",
        "engineer"
    ],
    "wof:name":"Eve Claydon Ltd.",
    "wof:placetype":"venue"
},
  "geometry": {"coordinates":[0.1725450009,51.5110282898],"type":"Point"}
}