{
  "type": "Feature",
  "properties": {
    "addr:full":"2 West End Villas Spilsby Lincolnshire PE23 5ED",
    "addr:housenumber":"2",
    "addr:postcode":"pe23 5ed",
    "addr:street":"West End Villas",
    "iso:country":"GB",
    "sg:address":"2 West End Villas",
    "sg:city":"Spilsby",
    "sg:classifiers":[
        {
            "category":"Education",
            "subcategory":"Library",
            "type":"Public Place"
        }
    ],
    "sg:phone":"+44 1790 752386",
    "sg:postcode":"PE23 5ED",
    "sg:province":"Lincolnshire",
    "sg:tags":[
        "book"
    ],
    "wof:name":"Spilsby Library",
    "wof:placetype":"venue"
},
  "geometry": {"coordinates":[0.0924189985,53.1744804382],"type":"Point"}
}