{
  "type": "Feature",
  "properties": {
    "iso:country":"GB",
    "sg:address":"40 Westmuir Street",
    "sg:city":"Glasgow",
    "sg:classifiers":[
        {
            "category":"Shopping",
            "subcategory":"Department Store",
            "type":"Retail Goods"
        }
    ],
    "sg:phone":"+44 141 556 3618",
    "sg:postcode":"G31 5BH",
    "sg:province":"Glasgow City",
    "wof:name":"Betterbuys",
    "wof:placetype":"venue"
},
  "geometry": {"coordinates":[-4.195219,55.851559],"type":"Point"}
}