{
  "type": "Feature",
  "properties": {
    "iso:country":"GB",
    "sg:address":"Unit 6 Beaufort St Business Ctr, Beaufort Street",
    "sg:city":"Derby",
    "sg:classifiers":[
        {
            "category":"Professional",
            "subcategory":"Computer Services",
            "type":"Services"
        }
    ],
    "sg:phone":"+44 1332 204461",
    "sg:postcode":"DE21 6AX",
    "sg:province":"Derbyshire",
    "sg:tags":[
        "system",
        "software"
    ],
    "wof:name":"Distributed Network Systems Ltd.",
    "wof:placetype":"venue"
},
  "geometry": {"coordinates":[-1.457391,52.934895],"type":"Point"}
}