{
  "type": "Feature",
  "properties": {
    "iso:country":"GB",
    "sg:address":"32 Old Wood Chase, Southwood",
    "sg:city":"Farnborough",
    "sg:classifiers":[
        {
            "category":"Home & Garden",
            "subcategory":"Household Appliances",
            "type":"Retail Goods"
        },
        {
            "category":"Retail",
            "subcategory":"Repair Shop",
            "type":"Services"
        }
    ],
    "sg:phone":"+44 1252 519319",
    "sg:postcode":"GU14 0QS",
    "sg:province":"Hampshire",
    "sg:tags":[
        "machine",
        "electrical",
        "washing"
    ],
    "wof:name":"A G W Domestic Services",
    "wof:placetype":"venue"
},
  "geometry": {"coordinates":[-0.7960749865,51.2916221619],"type":"Point"}
}