{
  "type": "Feature",
  "properties": {
    "addr:full":"Finchampstead Rd Wokingham Berkshire RG40 3HD",
    "addr:postcode":"rg40 3hd",
    "addr:street":"Finchampstead Rd",
    "iso:country":"GB",
    "sg:address":"Finchampstead Rd",
    "sg:city":"Wokingham",
    "sg:classifiers":[
        {
            "category":"Education",
            "subcategory":"School",
            "type":"Public Place"
        }
    ],
    "sg:phone":"+44 118 978 5151",
    "sg:postcode":"RG40 3HD",
    "sg:province":"Berkshire",
    "sg:tags":[
        "college"
    ],
    "wof:name":"White House Preparatory School",
    "wof:placetype":"venue"
},
  "geometry": {"coordinates":[-0.8561589718,51.3768844604],"type":"Point"}
}