{
  "type": "Feature",
  "properties": {
    "addr:full":"Timbers Farm, Nuffield Henley-on-thames Berkshire RG9 5SY",
    "addr:postcode":"rg9 5sy",
    "iso:country":"GB",
    "sg:address":"Timbers Farm, Nuffield",
    "sg:city":"Henley-on-thames",
    "sg:classifiers":[
        {
            "category":"Manufacturing",
            "subcategory":"Wood Products",
            "type":"Manufacturing & Wholesale Goods"
        }
    ],
    "sg:phone":"+44 1491 642233",
    "sg:postcode":"RG9 5SY",
    "sg:province":"Berkshire",
    "sg:tags":[
        "maker",
        "cabinet"
    ],
    "wof:name":"M Leighfield",
    "wof:placetype":"venue"
},
  "geometry": {"coordinates":[-1.034349,51.579739],"type":"Point"}
}