{
  "type": "Feature",
  "properties": {
    "iso:country":"GB",
    "sg:address":"Canda, Hampole Balk Lane",
    "sg:city":"Doncaster",
    "sg:classifiers":[
        {
            "category":"Bus Charters",
            "type":"Transportation"
        }
    ],
    "sg:phone":"+44 1302 722227",
    "sg:postcode":"DN6 8LF",
    "sg:province":"North Yorkshire",
    "sg:tags":[
        "hire",
        "coach"
    ],
    "wof:name":"Travelgreen Ltd.",
    "wof:placetype":"venue"
},
  "geometry": {"coordinates":[-1.208666,53.588203],"type":"Point"}
}