{
  "type": "Feature",
  "properties": {
    "addr:full":"Dunstable Road Newport Newport NP19 9LU",
    "addr:postcode":"np19 9lu",
    "addr:street":"Dunstable Road",
    "iso:country":"GB",
    "sg:address":"Dunstable Road",
    "sg:city":"Newport",
    "sg:classifiers":[
        {
            "category":"Education",
            "subcategory":"School",
            "type":"Public Place"
        }
    ],
    "sg:phone":"+44 1633 272308",
    "sg:postcode":"NP19 9LU",
    "sg:province":"Newport",
    "sg:tags":[
        "local",
        "authority"
    ],
    "wof:name":"Ringland Junior School",
    "wof:placetype":"venue"
},
  "geometry": {"coordinates":[-2.937775,51.590759],"type":"Point"}
}