{
  "type": "Feature",
  "properties": {
    "iso:country":"GB",
    "sg:address":"7 Cotefield Drive",
    "sg:city":"Leighton Buzzard",
    "sg:classifiers":[
        {
            "category":"Home & Garden",
            "subcategory":"Carpets & Floor Coverings",
            "type":"Retail Goods"
        }
    ],
    "sg:postcode":"LU7 3DS",
    "sg:province":"Bedfordshire",
    "sg:tags":[
        "cleaner",
        "upholstery"
    ],
    "wof:name":"Wall to Wall",
    "wof:placetype":"venue"
},
  "geometry": {"coordinates":[-0.6563349962,51.9332618713],"type":"Point"}
}