{
  "type": "Feature",
  "properties": {
    "iso:country":"GB",
    "sg:address":"30 Eastgate St",
    "sg:city":"Stafford",
    "sg:classifiers":[
        {
            "category":"Real Estate",
            "subcategory":"Real Estate Agent",
            "type":"Services"
        }
    ],
    "sg:postcode":"ST16 2LZ",
    "sg:province":"Staffordshire",
    "wof:name":"P P S Property Services",
    "wof:placetype":"venue"
},
  "geometry": {"coordinates":[-2.113249,52.806549],"type":"Point"}
}