{
  "type": "Feature",
  "properties": {
    "addr:full":"34-36 High Street, Braunston Daventry Northamptonshire NN11 7HR",
    "addr:housenumber":"34-36",
    "addr:postcode":"nn11 7hr",
    "addr:street":"High Street",
    "iso:country":"GB",
    "sg:address":"34-36 High Street, Braunston",
    "sg:city":"Daventry",
    "sg:classifiers":[
        {
            "category":"Government",
            "subcategory":"Post Office",
            "type":"Public Place"
        }
    ],
    "sg:postcode":"NN11 7HR",
    "sg:province":"Northamptonshire",
    "wof:name":"Braunston Sub Post Office",
    "wof:placetype":"venue"
},
  "geometry": {"coordinates":[-1.207384,52.291759],"type":"Point"}
}