{
  "type": "Feature",
  "properties": {
    "addr:full":"Wessex House, Silchester Rd Tadley Berkshire RG26 3PX",
    "addr:postcode":"rg26 3px",
    "addr:street":"Silchester Rd",
    "iso:country":"GB",
    "sg:address":"Wessex House, Silchester Rd",
    "sg:city":"Tadley",
    "sg:classifiers":[
        {
            "category":"Professional",
            "subcategory":"Engineering",
            "type":"Services"
        }
    ],
    "sg:phone":"+44 118 981 3842",
    "sg:postcode":"RG26 3PX",
    "sg:province":"Berkshire",
    "wof:name":"Kayell Associates",
    "wof:placetype":"venue"
},
  "geometry": {"coordinates":[-1.131048,51.357998],"type":"Point"}
}