{
  "type": "Feature",
  "properties": {
    "addr:full":"39 Malmains Way Beckenham Kent BR3 6SB",
    "addr:housenumber":"39",
    "addr:postcode":"br3 6sb",
    "addr:street":"Malmains Way",
    "iso:country":"GB",
    "sg:address":"39 Malmains Way",
    "sg:city":"Beckenham",
    "sg:classifiers":[
        {
            "category":"Manufacturing",
            "subcategory":"Tools & Machinery",
            "type":"Manufacturing & Wholesale Goods"
        }
    ],
    "sg:phone":"+44 20 8402 3996",
    "sg:postcode":"BR3 6SB",
    "sg:province":"Kent",
    "sg:tags":[
        "society",
        "friendly"
    ],
    "wof:name":"L I G Commercial Insurance Specialists",
    "wof:placetype":"venue"
},
  "geometry": {"coordinates":[-0.009264,51.395779],"type":"Point"}
}