{
  "type": "Feature",
  "properties": {
    "iso:country":"GB",
    "sg:address":"Blackbird Road",
    "sg:city":"Leicester",
    "sg:classifiers":[
        {
            "category":"Bars & Pubs",
            "type":"Food & Drink"
        },
        {
            "category":"Health Services",
            "subcategory":"Dentist",
            "type":"Services"
        }
    ],
    "sg:phone":"+44 116 262 2678",
    "sg:postcode":"LE4 0FW",
    "sg:province":"Leicestershire",
    "sg:tags":[
        "pubs",
        "inn"
    ],
    "wof:name":"The Blackbird",
    "wof:placetype":"venue"
},
  "geometry": {"coordinates":[-1.1435830593,52.6507492065],"type":"Point"}
}