{
  "type": "Feature",
  "properties": {
    "addr:full":"202a Barnsley Road, Flockton Wakefield West Yorkshire WF4 4AB",
    "addr:housenumber":"202a",
    "addr:postcode":"wf4 4ab",
    "addr:street":"Barnsley Road;West",
    "iso:country":"GB",
    "sg:address":"202a Barnsley Road, Flockton",
    "sg:city":"Wakefield",
    "sg:classifiers":[
        {
            "category":"Shopping",
            "subcategory":"News",
            "type":"Retail Goods"
        }
    ],
    "sg:postcode":"WF4 4AB",
    "sg:province":"West Yorkshire",
    "sg:tags":[
        "newsagent"
    ],
    "wof:name":"Dorothy & Valerie Heaversedge",
    "wof:placetype":"venue"
},
  "geometry": {"coordinates":[-1.632919,53.631516],"type":"Point"}
}