{
  "type": "Feature",
  "properties": {
    "iso:country":"GB",
    "sg:address":"73 Belle Vue Road, Earl Shilton",
    "sg:city":"Leicester",
    "sg:classifiers":[
        {
            "category":"Shopping",
            "subcategory":"News",
            "type":"Retail Goods"
        }
    ],
    "sg:phone":"+44 1455 842235",
    "sg:postcode":"LE9 7PA",
    "sg:province":"Leicestershire",
    "sg:tags":[
        "newsagent"
    ],
    "wof:name":"Bellevue News",
    "wof:placetype":"venue"
},
  "geometry": {"coordinates":[-1.33213,52.572929],"type":"Point"}
}