{
  "type": "Feature",
  "properties": {
    "addr:full":"Thame Rd, Stadhampton Oxford Oxfordshire OX44 7TX",
    "addr:postcode":"ox44 7tx",
    "addr:street":"Thame Rd",
    "iso:country":"GB",
    "sg:address":"Thame Rd, Stadhampton",
    "sg:city":"Oxford",
    "sg:classifiers":[
        {
            "category":"Bars & Pubs",
            "type":"Food & Drink"
        },
        {
            "category":"Community Center",
            "subcategory":"Social",
            "type":"Public Place"
        }
    ],
    "sg:phone":"+44 1865 890381",
    "sg:postcode":"OX44 7TX",
    "sg:province":"Oxfordshire",
    "sg:tags":[
        "pubs",
        "house",
        "inn",
        "activity"
    ],
    "wof:name":"The Crown",
    "wof:placetype":"venue"
},
  "geometry": {"coordinates":[-1.1294039488,51.6830940247],"type":"Point"}
}