{
  "type": "Feature",
  "properties": {
    "iso:country":"GB",
    "sg:address":"Westbury Sub, Mendip Wells",
    "sg:city":"Wells",
    "sg:classifiers":[
        {
            "category":"Education",
            "subcategory":"School",
            "type":"Public Place"
        },
        {
            "category":"Government",
            "subcategory":"Office",
            "type":"Public Place"
        }
    ],
    "sg:phone":"+44 1749 870437",
    "sg:postcode":"BA5 1HL",
    "sg:province":"Somerset",
    "sg:tags":[
        "local",
        "authority"
    ],
    "wof:name":"St Lawrences Vc Primary School",
    "wof:placetype":"venue"
},
  "geometry": {"coordinates":[-2.6459538937,51.2113494873],"type":"Point"}
}