{
  "type": "Feature",
  "properties": {
    "addr:full":"74-78 Park Road, Whitchurch Cardiff Cardiff CF14 7BR",
    "addr:housenumber":"74-78",
    "addr:postcode":"cf14 7br",
    "addr:street":"Park Road",
    "iso:country":"GB",
    "sg:address":"74-78 Park Road, Whitchurch",
    "sg:city":"Cardiff",
    "sg:classifiers":[
        {
            "category":"Shopping",
            "subcategory":"Stationery & Office Supplies",
            "type":"Retail Goods"
        },
        {
            "category":"Communications",
            "subcategory":"Radio Station",
            "type":"Services"
        }
    ],
    "sg:phone":"+44 29 2052 9925",
    "sg:postcode":"CF14 7BR",
    "sg:province":"Cardiff",
    "sg:tags":[
        "item",
        "television",
        "production",
        "promotional"
    ],
    "wof:name":"J M Creative Ltd",
    "wof:placetype":"venue"
},
  "geometry": {"coordinates":[-3.22967,51.51894],"type":"Point"}
}