{
  "type": "Feature",
  "properties": {
    "iso:country":"GB",
    "sg:address":"2 Queensdale Road",
    "sg:city":"Liverpool",
    "sg:classifiers":[
        {
            "category":"Health Services",
            "subcategory":"Chiropractor",
            "type":"Services"
        }
    ],
    "sg:phone":"+44 151 733 5715",
    "sg:postcode":"L18 1LT",
    "sg:province":"Merseyside",
    "wof:name":"Allerton Chiropractic Clinic",
    "wof:placetype":"venue"
},
  "geometry": {"coordinates":[-2.913484,53.38723],"type":"Point"}
}