{
  "type": "Feature",
  "properties": {
    "addr:full":"81 Warwick Street Liverpool Merseyside L8 4TG",
    "addr:housenumber":"81",
    "addr:postcode":"l8 4tg",
    "addr:street":"Warwick Street",
    "iso:country":"GB",
    "sg:address":"81 Warwick Street",
    "sg:city":"Liverpool",
    "sg:classifiers":[
        {
            "category":"Personal",
            "subcategory":"Beauty Salon",
            "type":"Services"
        }
    ],
    "sg:phone":"+44 151 709 4867",
    "sg:postcode":"L8 4TG",
    "sg:province":"Merseyside",
    "sg:tags":[
        "unisex",
        "hairdresser"
    ],
    "wof:name":"What A Hair Design",
    "wof:placetype":"venue"
},
  "geometry": {"coordinates":[-2.973779,53.39027],"type":"Point"}
}