{
  "type": "Feature",
  "properties": {
    "addr:full":"95 Main Road, High Harrington Workington Cumbria CA14 4NQ",
    "addr:housenumber":"95",
    "addr:postcode":"ca14 4nq",
    "addr:street":"Main Road",
    "iso:country":"GB",
    "sg:address":"95 Main Road, High Harrington",
    "sg:city":"Workington",
    "sg:classifiers":[
        {
            "category":"Bars & Pubs",
            "type":"Food & Drink"
        }
    ],
    "sg:postcode":"CA14 4NQ",
    "sg:province":"Cumbria",
    "sg:tags":[
        "pubs",
        "inn"
    ],
    "wof:name":"Galloping Horse Inn",
    "wof:placetype":"venue"
},
  "geometry": {"coordinates":[-3.54617,54.614372],"type":"Point"}
}