{
  "type": "Feature",
  "properties": {
    "iso:country":"GB",
    "sg:address":"Banbury Road, Byfield",
    "sg:city":"Daventry",
    "sg:classifiers":[
        {
            "category":"Social Services",
            "subcategory":"Retirement Home",
            "type":"Services"
        }
    ],
    "sg:phone":"+44 1327 260234",
    "sg:postcode":"NN11 6UA",
    "sg:province":"Northamptonshire",
    "sg:tags":[
        "residential",
        "care"
    ],
    "wof:name":"Solden Hill House",
    "wof:placetype":"venue"
},
  "geometry": {"coordinates":[-1.245537,52.174984],"type":"Point"}
}