{
  "type": "Feature",
  "properties": {
    "iso:country":"GB",
    "sg:address":"50 Providence Place",
    "sg:city":"Brighton",
    "sg:classifiers":[
        {
            "category":"Shopping",
            "subcategory":"Clothing, Apparel, & Fashions",
            "type":"Retail Goods"
        }
    ],
    "sg:phone":"+44 1273 622056",
    "sg:postcode":"BN1 4GE",
    "sg:province":"East Sussex",
    "sg:tags":[
        "t-shirt"
    ],
    "wof:name":"Upfront Incorporated",
    "wof:placetype":"venue"
},
  "geometry": {"coordinates":[-0.136638999,50.8308486938],"type":"Point"}
}