{
  "type": "Feature",
  "properties": {
    "iso:country":"GB",
    "sg:address":"Brynog Home Farm, Felinfach",
    "sg:city":"Lampeter",
    "sg:classifiers":[
        {
            "category":"Farming",
            "subcategory":"Dairy Farm",
            "type":"Manufacturing & Wholesale Goods"
        }
    ],
    "sg:phone":"+44 1570 470340",
    "sg:postcode":"SA48 8AQ",
    "sg:province":"Carmarthenshire",
    "wof:name":"D T H Jones",
    "wof:placetype":"venue"
},
  "geometry": {"coordinates":[-4.151364,52.179935],"type":"Point"}
}