{
  "type": "Feature",
  "properties": {
    "iso:country":"GB",
    "sg:address":"9 Market Place",
    "sg:city":"Clitheroe",
    "sg:classifiers":[
        {
            "category":"Shopping",
            "subcategory":"Clothing, Apparel, & Fashions",
            "type":"Retail Goods"
        }
    ],
    "sg:phone":"+44 1200 422562",
    "sg:postcode":"BB7 2BZ",
    "sg:province":"Lancashire",
    "sg:tags":[
        "menswear"
    ],
    "wof:name":"Fred Read & Co. Ltd.",
    "wof:placetype":"venue"
},
  "geometry": {"coordinates":[-2.3910288811,53.8726768494],"type":"Point"}
}