{
  "type": "Feature",
  "properties": {
    "addr:full":"Blyth Harbour, Commision South Harbour Blyth Northumberland NE24 3PB",
    "addr:postcode":"ne24 3pb",
    "addr:street":"Blyth Harbour Commision",
    "iso:country":"GB",
    "sg:address":"Blyth Harbour, Commision South Harbour",
    "sg:city":"Blyth",
    "sg:classifiers":[
        {
            "category":"Professional",
            "subcategory":"Engineering",
            "type":"Services"
        }
    ],
    "sg:phone":"+44 1670 544400",
    "sg:postcode":"NE24 3PB",
    "sg:province":"Northumberland",
    "wof:name":"Blyth Marine Services",
    "wof:placetype":"venue"
},
  "geometry": {"coordinates":[-1.498729,55.124847],"type":"Point"}
}