{
  "type": "Feature",
  "properties": {
    "iso:country":"GB",
    "sg:address":"32 Braemar Avenue, Stretford",
    "sg:city":"Manchester",
    "sg:classifiers":[
        {
            "category":"Building & Trades",
            "subcategory":"Construction",
            "type":"Services"
        }
    ],
    "sg:phone":"+44 161 865 0453",
    "sg:postcode":"M32 9NA",
    "sg:province":"Cheshire",
    "sg:tags":[
        "builder"
    ],
    "wof:name":"K & A Builders",
    "wof:placetype":"venue"
},
  "geometry": {"coordinates":[-2.3274729252,53.44921875],"type":"Point"}
}