{
  "type": "Feature",
  "properties": {
    "addr:full":"Newton Road Sudbury Essex CO10 0PZ",
    "addr:postcode":"co10 0pz",
    "addr:street":"Newton Road",
    "iso:country":"GB",
    "sg:address":"Newton Road",
    "sg:city":"Sudbury",
    "sg:classifiers":[
        {
            "category":"Home & Garden",
            "subcategory":"Garden Supply",
            "type":"Retail Goods"
        }
    ],
    "sg:phone":"+44 1787 377062",
    "sg:postcode":"CO10 0PZ",
    "sg:province":"Essex",
    "sg:tags":[
        "nursery",
        "centre"
    ],
    "wof:name":"Chilton Quality Plants",
    "wof:placetype":"venue"
},
  "geometry": {"coordinates":[0.7533450127,52.0404243469],"type":"Point"}
}