{
  "type": "Feature",
  "properties": {
    "iso:country":"GB",
    "sg:address":"26a Long Street",
    "sg:city":"Thirsk",
    "sg:classifiers":[
        {
            "category":"Manufacturing",
            "subcategory":"Petroleum Products",
            "type":"Manufacturing & Wholesale Goods"
        },
        {
            "category":"Manufacturing",
            "subcategory":"Apparel",
            "type":"Manufacturing & Wholesale Goods"
        }
    ],
    "sg:phone":"+44 1845 524777",
    "sg:postcode":"YO7 1AP",
    "sg:province":"North Yorkshire",
    "sg:tags":[
        "double",
        "glazing",
        "shirt",
        "maker"
    ],
    "wof:name":"New Additions",
    "wof:placetype":"venue"
},
  "geometry": {"coordinates":[-1.337861,54.234753],"type":"Point"}
}