{
  "type": "Feature",
  "properties": {
    "iso:country":"GB",
    "sg:address":"Unit 5a Cottage Lane Industrial Estate, Broughton Astley",
    "sg:city":"Leicester",
    "sg:classifiers":[
        {
            "category":"Professional",
            "subcategory":"Printing & Photocopies",
            "type":"Services"
        }
    ],
    "sg:phone":"+44 1455 289235",
    "sg:postcode":"LE9 6TU",
    "sg:province":"Leicestershire",
    "sg:tags":[
        "printer"
    ],
    "wof:name":"Abbey Graphics Design & Print",
    "wof:placetype":"venue"
},
  "geometry": {"coordinates":[-1.198466,52.528671],"type":"Point"}
}