{
  "type": "Feature",
  "properties": {
    "iso:country":"GB",
    "sg:address":"13th Floor, 60 Charles Street",
    "sg:city":"Leicester",
    "sg:classifiers":[
        {
            "category":"Professional",
            "subcategory":"Lawyer & Legal Services",
            "type":"Services"
        }
    ],
    "sg:phone":"+44 116 253 9070",
    "sg:postcode":"LE1 1FB",
    "sg:province":"Leicestershire",
    "sg:tags":[
        "solicitor"
    ],
    "wof:name":"Cort & Co Solicitors",
    "wof:placetype":"venue"
},
  "geometry": {"coordinates":[-1.129728,52.635464],"type":"Point"}
}