{
  "type": "Feature",
  "properties": {
    "addr:full":"Bridge Road Worthing West Sussex BN14 7BU",
    "addr:postcode":"bn14 7bu",
    "addr:street":"Bridge Road",
    "iso:country":"GB",
    "sg:address":"Bridge Road",
    "sg:city":"Worthing",
    "sg:classifiers":[
        {
            "category":"Professional",
            "subcategory":"Testing Lab",
            "type":"Services"
        }
    ],
    "sg:postcode":"BN14 7BU",
    "sg:province":"West Sussex",
    "sg:tags":[
        "mot"
    ],
    "wof:name":"Central Auto Repair Services",
    "wof:placetype":"venue"
},
  "geometry": {"coordinates":[-0.3738690019,50.8193855286],"type":"Point"}
}