{
  "type": "Feature",
  "properties": {
    "iso:country":"GB",
    "sg:address":"Suite 9 Derwent View, Bracken Holme Business Park",
    "sg:city":"Selby",
    "sg:classifiers":[
        {
            "category":"Professional",
            "subcategory":"Computer Services",
            "type":"Services"
        }
    ],
    "sg:postcode":"YO8 6EL",
    "sg:province":"East Riding of Yorkshire",
    "sg:tags":[
        "system",
        "software"
    ],
    "wof:name":"Aaland Ltd.",
    "wof:placetype":"venue"
},
  "geometry": {"coordinates":[-0.9393839836,53.7624893188],"type":"Point"}
}