{
  "type": "Feature",
  "properties": {
    "iso:country":"GB",
    "sg:address":"Peddars Way, School Road, Rattlesden",
    "sg:city":"Bury St Edmunds",
    "sg:classifiers":[
        {
            "category":"Military Area",
            "subcategory":"Army Base",
            "type":"Public Place"
        },
        {
            "category":"Professional",
            "subcategory":"Business Services",
            "type":"Services"
        }
    ],
    "sg:phone":"+44 1449 737194",
    "sg:postcode":"IP30 0SE",
    "sg:province":"Suffolk",
    "sg:tags":[
        "transportation",
        "livestock",
        "transport"
    ],
    "wof:name":"Owen Farming Transport Ltd.",
    "wof:placetype":"venue"
},
  "geometry": {"coordinates":[0.8893899918,52.1936187744],"type":"Point"}
}