{
  "type": "Feature",
  "properties": {
    "iso:country":"GB",
    "sg:address":"Business Travel, Third Floor, Kimberley House",
    "sg:city":"Leeds",
    "sg:classifiers":[
        {
            "category":"Travel",
            "subcategory":"Travel Agent",
            "type":"Entertainment"
        }
    ],
    "sg:phone":"+44 113 244 2270",
    "sg:postcode":"LS3 1AD",
    "sg:province":"West Yorkshire",
    "wof:name":"Carlson Wagonlit Travel",
    "wof:placetype":"venue"
},
  "geometry": {"coordinates":[-1.55639,53.801472],"type":"Point"}
}