{
  "type": "Feature",
  "properties": {
    "addr:full":"6 The Square Lightwater Surrey GU18 5SS",
    "addr:housenumber":"6",
    "addr:postcode":"gu18 5ss",
    "addr:street":"The Square",
    "iso:country":"GB",
    "sg:address":"6 The Square",
    "sg:city":"Lightwater",
    "sg:classifiers":[
        {
            "category":"Manufacturing",
            "subcategory":"Tools & Machinery",
            "type":"Manufacturing & Wholesale Goods"
        }
    ],
    "sg:phone":"+44 1276 451533",
    "sg:postcode":"GU18 5SS",
    "sg:province":"Surrey",
    "sg:tags":[
        "society",
        "friendly"
    ],
    "wof:name":"Oldfield Insurance Consultants",
    "wof:placetype":"venue"
},
  "geometry": {"coordinates":[-0.664359,51.350834],"type":"Point"}
}