{
  "type": "Feature",
  "properties": {
    "iso:country":"GB",
    "sg:address":"140 Brox Road",
    "sg:city":"Chertsey",
    "sg:classifiers":[
        {
            "category":"Shopping",
            "subcategory":"Books",
            "type":"Retail Goods"
        }
    ],
    "sg:phone":"+44 1932 875210",
    "sg:postcode":"KT16 0LQ",
    "sg:province":"Surrey",
    "wof:name":"Regent Publishing Services",
    "wof:placetype":"venue"
},
  "geometry": {"coordinates":[-0.531446,51.365154],"type":"Point"}
}