{
  "type": "Feature",
  "properties": {
    "iso:country":"GB",
    "sg:address":"Carver Hey Farm, Moss Lane, Little Hoole",
    "sg:city":"Preston",
    "sg:classifiers":[
        {
            "category":"Building & Trades",
            "subcategory":"Construction",
            "type":"Services"
        }
    ],
    "sg:phone":"+44 1772 619199",
    "sg:postcode":"PR4 4SX",
    "sg:province":"Lancashire",
    "sg:tags":[
        "decorator",
        "painter"
    ],
    "wof:name":"A J Noblett Ltd",
    "wof:placetype":"venue"
},
  "geometry": {"coordinates":[-2.7772600651,53.7066192627],"type":"Point"}
}