{
  "type": "Feature",
  "properties": {
    "iso:country":"GB",
    "sg:address":"Hill Top House, Main Street, Burley-in-wharfdale",
    "sg:city":"Ilkley",
    "sg:classifiers":[
        {
            "category":"Real Estate",
            "subcategory":"Real Estate Agent",
            "type":"Services"
        }
    ],
    "sg:phone":"+44 1943 862859",
    "sg:postcode":"LS29 7JW",
    "sg:province":"North Yorkshire",
    "wof:name":"Brecks Property Co. Ltd.",
    "wof:placetype":"venue"
},
  "geometry": {"coordinates":[-1.753334,53.915257],"type":"Point"}
}