{
  "type": "Feature",
  "properties": {
    "iso:country":"GB",
    "sg:address":"46 Whitburn Street, Hightown",
    "sg:city":"Bridgnorth",
    "sg:classifiers":[
        {
            "category":"Professional",
            "subcategory":"Printing & Photocopies",
            "type":"Services"
        }
    ],
    "sg:phone":"+44 1746 761177",
    "sg:postcode":"WV16 4QT",
    "sg:province":"Shropshire",
    "sg:tags":[
        "embroiderer"
    ],
    "wof:name":"Stitches of Bridgnorth",
    "wof:placetype":"venue"
},
  "geometry": {"coordinates":[-2.423871,52.535526],"type":"Point"}
}