{
  "type": "Feature",
  "properties": {
    "addr:full":"207 Ardleigh Green Road Hornchurch Essex RM11 2SD",
    "addr:housenumber":"207",
    "addr:postcode":"rm11 2sd",
    "addr:street":"Ardleigh Green Road",
    "iso:country":"GB",
    "sg:address":"207 Ardleigh Green Road",
    "sg:city":"Hornchurch",
    "sg:classifiers":[
        {
            "category":"Professional",
            "subcategory":"Printing & Photocopies",
            "type":"Services"
        }
    ],
    "sg:phone":"+44 1708 451375",
    "sg:postcode":"RM11 2SD",
    "sg:province":"Essex",
    "sg:tags":[
        "printer"
    ],
    "wof:name":"G H R Jarvis & Co",
    "wof:placetype":"venue"
},
  "geometry": {"coordinates":[0.2203900069,51.5844192505],"type":"Point"}
}