{
  "type": "Feature",
  "properties": {
    "iso:country":"GB",
    "sg:address":"Union Road",
    "sg:city":"Nottingham",
    "sg:classifiers":[
        {
            "category":"Professional",
            "subcategory":"Printing & Photocopies",
            "type":"Services"
        }
    ],
    "sg:phone":"+44 115 950 7631",
    "sg:postcode":"NG3 1FU",
    "sg:province":"Nottinghamshire",
    "sg:tags":[
        "print",
        "finisher"
    ],
    "wof:name":"F F Allsopp & Co. Ltd.",
    "wof:placetype":"venue"
},
  "geometry": {"coordinates":[-1.1450229883,52.9582672119],"type":"Point"}
}