{
  "type": "Feature",
  "properties": {
    "iso:country":"GB",
    "sg:address":"44 Boston Road, Beaumont Leys",
    "sg:city":"Leicester",
    "sg:classifiers":[
        {
            "category":"Shopping",
            "subcategory":"Stationery & Office Supplies",
            "type":"Retail Goods"
        }
    ],
    "sg:phone":"+44 116 234 0102",
    "sg:postcode":"LE4 1AA",
    "sg:province":"Leicestershire",
    "sg:tags":[
        "envelope"
    ],
    "wof:name":"Dowling Envelopes Ltd.",
    "wof:placetype":"venue"
},
  "geometry": {"coordinates":[-1.1747000217,52.6656112671],"type":"Point"}
}