{
  "type": "Feature",
  "properties": {
    "addr:full":"3 Merchants Common, East Goscote Leicester Leicestershire LE7 8XH",
    "addr:housenumber":"3",
    "addr:postcode":"le7 8xh",
    "addr:street":"Merchants Common",
    "iso:country":"GB",
    "sg:address":"3 Merchants Common, East Goscote",
    "sg:city":"Leicester",
    "sg:classifiers":[
        {
            "category":"Shopping",
            "subcategory":"News",
            "type":"Retail Goods"
        }
    ],
    "sg:phone":"+44 116 269 7604",
    "sg:postcode":"LE7 8XH",
    "sg:province":"Leicestershire",
    "sg:tags":[
        "newsagent"
    ],
    "wof:name":"Forbuoys",
    "wof:placetype":"venue"
},
  "geometry": {"coordinates":[-1.0465099812,52.7157783508],"type":"Point"}
}