{
  "type": "Feature",
  "properties": {
    "iso:country":"GB",
    "sg:address":"71 Streatham Hill",
    "sg:city":"London",
    "sg:classifiers":[
        {
            "category":"Shopping",
            "subcategory":"Clothing, Apparel, & Fashions",
            "type":"Retail Goods"
        }
    ],
    "sg:phone":"+44 20 8674 8688",
    "sg:postcode":"SW2 4TX",
    "sg:province":"Greater London",
    "sg:tags":[
        "dresswear"
    ],
    "wof:name":"Classic Cuts (Hire) Ltd.",
    "wof:placetype":"venue"
},
  "geometry": {"coordinates":[-0.125789,51.439716],"type":"Point"}
}