{
  "type": "Feature",
  "properties": {
    "addr:full":"1 Llanyravon Square, Llanyravon Cwmbran Monmouthshire NP44 8HS",
    "addr:housenumber":"1",
    "addr:postcode":"np44 8hs",
    "addr:street":"Llanyravon Square Llanyravon",
    "iso:country":"GB",
    "sg:address":"1 Llanyravon Square, Llanyravon",
    "sg:city":"Cwmbran",
    "sg:classifiers":[
        {
            "category":"Shopping",
            "subcategory":"News",
            "type":"Retail Goods"
        }
    ],
    "sg:phone":"+44 1633 483729",
    "sg:postcode":"NP44 8HS",
    "sg:province":"Monmouthshire",
    "sg:tags":[
        "newsagent"
    ],
    "wof:name":"R & R Retail",
    "wof:placetype":"venue"
},
  "geometry": {"coordinates":[-3.007728,51.646103],"type":"Point"}
}