{
  "type": "Feature",
  "properties": {
    "addr:full":"East Leys Farm, Grindale Bridlington East Riding of Yorkshire YO16 4YB",
    "addr:postcode":"yo16 4yb",
    "addr:street":"East Leys",
    "iso:country":"GB",
    "sg:address":"East Leys Farm, Grindale",
    "sg:city":"Bridlington",
    "sg:classifiers":[
        {
            "category":"Farming",
            "subcategory":"Farm",
            "type":"Manufacturing & Wholesale Goods"
        }
    ],
    "sg:postcode":"YO16 4YB",
    "sg:province":"East Riding of Yorkshire",
    "sg:tags":[
        "mixed",
        "crop"
    ],
    "wof:name":"J Thompson Farm",
    "wof:placetype":"venue"
},
  "geometry": {"coordinates":[-0.2680400014,54.1248893738],"type":"Point"}
}