{
  "type": "Feature",
  "properties": {
    "iso:country":"GB",
    "sg:address":"38-40 Leigh Road",
    "sg:city":"Leigh-on-sea",
    "sg:classifiers":[
        {
            "category":"Health Services",
            "subcategory":"Doctor",
            "type":"Services"
        }
    ],
    "sg:phone":"+44 1702 475105",
    "sg:postcode":"SS9 1LF",
    "sg:province":"Essex",
    "sg:tags":[
        "practitioners"
    ],
    "wof:name":"Drs Sooriakumaran V & Santhakumar K",
    "wof:placetype":"venue"
},
  "geometry": {"coordinates":[0.670227,51.543461],"type":"Point"}
}