{
  "type": "Feature",
  "properties": {
    "addr:full":"Osteopathy Clinic, 31 Hammerton St Burnley Lancashire BB11 1LT",
    "addr:housenumber":"31",
    "addr:postcode":"bb11 1lt",
    "addr:street":"Hammerton St",
    "iso:country":"GB",
    "sg:address":"Osteopathy Clinic, 31 Hammerton St",
    "sg:city":"Burnley",
    "sg:classifiers":[
        {
            "category":"Health Services",
            "subcategory":"Health Practitioner",
            "type":"Services"
        }
    ],
    "sg:phone":"+44 1282 450850",
    "sg:postcode":"BB11 1LT",
    "sg:province":"Lancashire",
    "sg:tags":[
        "osteopath"
    ],
    "wof:name":"M Ratcliffe",
    "wof:placetype":"venue"
},
  "geometry": {"coordinates":[-2.2438089848,53.7880096436],"type":"Point"}
}