{
  "type": "Feature",
  "properties": {
    "addr:full":"3-5 Homestall, Buckingham Industrial Estate Buckingham Buckinghamshire MK18 1XJ",
    "addr:housenumber":"3-5",
    "addr:postcode":"mk18 1xj",
    "addr:street":"Homestall Buckingham Industrial Estate",
    "iso:country":"GB",
    "sg:address":"3-5 Homestall, Buckingham Industrial Estate",
    "sg:city":"Buckingham",
    "sg:classifiers":[
        {
            "category":"Parking",
            "type":"Transportation"
        }
    ],
    "sg:postcode":"MK18 1XJ",
    "sg:province":"Buckinghamshire",
    "sg:tags":[
        "car",
        "valet"
    ],
    "wof:name":"Executive Car Care Valeting Services",
    "wof:placetype":"venue"
},
  "geometry": {"coordinates":[-0.9864789844,52.0007514954],"type":"Point"}
}