{
  "type": "Feature",
  "properties": {
    "addr:full":"Unit 4 Gidleys Meadow Exeter Devon EX6 7QB",
    "addr:housenumber":"unit 4",
    "addr:postcode":"ex6 7qb",
    "addr:street":"Gidleys Meadow",
    "iso:country":"GB",
    "sg:address":"Unit 4 Gidleys Meadow",
    "sg:city":"Exeter",
    "sg:classifiers":[
        {
            "category":"Building & Trades",
            "subcategory":"Construction",
            "type":"Services"
        }
    ],
    "sg:phone":"+44 1647 252977",
    "sg:postcode":"EX6 7QB",
    "sg:province":"Devon",
    "sg:tags":[
        "builder"
    ],
    "wof:name":"Stephen Clarke",
    "wof:placetype":"venue"
},
  "geometry": {"coordinates":[-3.6445600986,50.6556510925],"type":"Point"}
}