{
  "type": "Feature",
  "properties": {
    "addr:full":"64-70 Dock Street Fleetwood Lancashire FY7 6JW",
    "addr:housenumber":"64-70",
    "addr:postcode":"fy7 6jw",
    "addr:street":"Dock Street",
    "iso:country":"GB",
    "sg:address":"64-70 Dock Street",
    "sg:city":"Fleetwood",
    "sg:classifiers":[
        {
            "category":"Retail",
            "subcategory":"Auto Repair",
            "type":"Services"
        }
    ],
    "sg:phone":"+44 1253 872180",
    "sg:postcode":"FY7 6JW",
    "sg:province":"Lancashire",
    "sg:tags":[
        "modification",
        "garage"
    ],
    "wof:name":"Fleetwood Tyre & Auto Centre",
    "wof:placetype":"venue"
},
  "geometry": {"coordinates":[-3.007089,53.922741],"type":"Point"}
}