{
  "type": "Feature",
  "properties": {
    "iso:country":"GB",
    "sg:address":"83 Gordon Road",
    "sg:city":"London",
    "sg:classifiers":[
        {
            "category":"Home & Garden",
            "subcategory":"Home Furnishings",
            "type":"Retail Goods"
        }
    ],
    "sg:phone":"+44 20 8991 2071",
    "sg:postcode":"W5 2AL",
    "sg:province":"Greater London",
    "sg:tags":[
        "racking",
        "shelving",
        "diy"
    ],
    "wof:name":"C F Design",
    "wof:placetype":"venue"
},
  "geometry": {"coordinates":[-0.313082,51.514565],"type":"Point"}
}