{
  "type": "Feature",
  "properties": {
    "iso:country":"GB",
    "sg:address":"Hardwick",
    "sg:city":"Abergavenny",
    "sg:classifiers":[
        {
            "category":"Bars & Pubs",
            "type":"Food & Drink"
        }
    ],
    "sg:phone":"+44 1873 854220",
    "sg:postcode":"NP7 9AA",
    "sg:province":"Herefordshire",
    "sg:tags":[
        "pubs",
        "inn"
    ],
    "wof:name":"Horse & Jockey Inn",
    "wof:placetype":"venue"
},
  "geometry": {"coordinates":[-3.0060489178,51.7961502075],"type":"Point"}
}