{
  "type": "Feature",
  "properties": {
    "iso:country":"GB",
    "sg:address":"7 Collipriest View, Ashley",
    "sg:city":"Tiverton",
    "sg:classifiers":[
        {
            "category":"Freight",
            "type":"Transportation"
        }
    ],
    "sg:phone":"+44 1884 256452",
    "sg:postcode":"EX16 5PR",
    "sg:province":"Devon",
    "sg:tags":[
        "haulage",
        "road"
    ],
    "wof:name":"Christopher Hellier Transport",
    "wof:placetype":"venue"
},
  "geometry": {"coordinates":[-3.4931490421,50.9050254822],"type":"Point"}
}