{
  "type": "Feature",
  "properties": {
    "iso:country":"GB",
    "sg:address":"2 Oak Park Rise",
    "sg:city":"Barnsley",
    "sg:classifiers":[
        {
            "category":"Building & Trades",
            "subcategory":"Construction",
            "type":"Services"
        }
    ],
    "sg:phone":"+44 1226 296343",
    "sg:postcode":"S70 4PB",
    "sg:province":"South Yorkshire",
    "sg:tags":[
        "roofing",
        "contracting"
    ],
    "wof:name":"A & S Fenton Roofing",
    "wof:placetype":"venue"
},
  "geometry": {"coordinates":[-1.470719,53.543716],"type":"Point"}
}