{
  "type": "Feature",
  "properties": {
    "addr:full":"Main Street Crianlarich Argyll and Bute FK20 8QN",
    "addr:postcode":"fk20 8qn",
    "addr:street":"Main Street",
    "iso:country":"GB",
    "sg:address":"Main Street",
    "sg:city":"Crianlarich",
    "sg:classifiers":[
        {
            "category":"Restaurant",
            "type":"Food & Drink"
        },
        {
            "category":"Community Center",
            "subcategory":"Social",
            "type":"Public Place"
        }
    ],
    "sg:phone":"+44 1838 300271",
    "sg:postcode":"FK20 8QN",
    "sg:province":"Argyll and Bute",
    "sg:tags":[
        "house",
        "activity"
    ],
    "wof:name":"The Rod & Reel",
    "wof:placetype":"venue"
},
  "geometry": {"coordinates":[-4.6189618111,56.3928947449],"type":"Point"}
}