{
  "type": "Feature",
  "properties": {
    "addr:full":"Maes Y Gwair, Maenygroes New Quay Ceredigion SA45 9RL",
    "addr:postcode":"sa45 9rl",
    "addr:street":"Maes Y Gwair Maenygroes",
    "iso:country":"GB",
    "sg:address":"Maes Y Gwair, Maenygroes",
    "sg:city":"New Quay",
    "sg:classifiers":[
        {
            "category":"Train Station",
            "subcategory":"Rail",
            "type":"Transportation"
        }
    ],
    "sg:postcode":"SA45 9RL",
    "sg:province":"Ceredigion",
    "sg:tags":[
        "caravan"
    ],
    "wof:name":"Dolphin Bay Carvans",
    "wof:placetype":"venue"
},
  "geometry": {"coordinates":[-4.3607897758,52.2136726379],"type":"Point"}
}