{
  "type": "Feature",
  "properties": {
    "iso:country":"GB",
    "sg:address":"45-46 Chandos Place",
    "sg:city":"London",
    "sg:classifiers":[
        {
            "category":"Shopping",
            "subcategory":"Pharmacy",
            "type":"Retail Goods"
        }
    ],
    "sg:phone":"+44 20 7836 5220",
    "sg:postcode":"WC2N 4HS",
    "sg:province":"Greater London",
    "sg:tags":[
        "medicine",
        "therapy"
    ],
    "wof:name":"Institute of Chinese Medicine",
    "wof:placetype":"venue"
},
  "geometry": {"coordinates":[-0.1258900017,51.5097198486],"type":"Point"}
}