{
  "type": "Feature",
  "properties": {
    "addr:full":"25 Bridge Street, Killamarsh Sheffield Derbyshire S21 1AH",
    "addr:housenumber":"25",
    "addr:postcode":"s21 1ah",
    "addr:street":"Bridge Street",
    "iso:country":"GB",
    "sg:address":"25 Bridge Street, Killamarsh",
    "sg:city":"Sheffield",
    "sg:classifiers":[
        {
            "category":"Home & Garden",
            "subcategory":"Carpets & Floor Coverings",
            "type":"Retail Goods"
        }
    ],
    "sg:phone":"+44 114 248 2634",
    "sg:postcode":"S21 1AH",
    "sg:province":"Derbyshire",
    "sg:tags":[
        "carpets",
        "retailer",
        "rug",
        "matting"
    ],
    "wof:name":"Killamarsh Carpets",
    "wof:placetype":"venue"
},
  "geometry": {"coordinates":[-1.317505,53.324524],"type":"Point"}
}