{
  "type": "Feature",
  "properties": {
    "addr:full":"St Johns House, Barrington Road Altrincham Cheshire WA14 1JY",
    "addr:postcode":"wa14 1jy",
    "addr:street":"Barrington Road",
    "iso:country":"GB",
    "sg:address":"St Johns House, Barrington Road",
    "sg:city":"Altrincham",
    "sg:classifiers":[
        {
            "category":"Professional",
            "subcategory":"Computer Services",
            "type":"Services"
        }
    ],
    "sg:phone":"+44 161 928 9334",
    "sg:postcode":"WA14 1JY",
    "sg:province":"Cheshire",
    "sg:tags":[
        "system",
        "software"
    ],
    "wof:name":"Computer Associates Plc",
    "wof:placetype":"venue"
},
  "geometry": {"coordinates":[-2.3515779972,53.3951377869],"type":"Point"}
}