{
  "type": "Feature",
  "properties": {
    "addr:full":"Furness House, Trafford Road Salford Greater Manchester M5 2XB",
    "addr:postcode":"m5 2xb",
    "addr:street":"Trafford Road",
    "iso:country":"GB",
    "sg:address":"Furness House, Trafford Road",
    "sg:city":"Salford",
    "sg:classifiers":[
        {
            "category":"Manufacturing",
            "subcategory":"Tools & Machinery",
            "type":"Manufacturing & Wholesale Goods"
        }
    ],
    "sg:phone":"+44 161 877 5797",
    "sg:postcode":"M5 2XB",
    "sg:province":"Greater Manchester",
    "sg:tags":[
        "society",
        "friendly"
    ],
    "wof:name":"Farley Taylor Moore",
    "wof:placetype":"venue"
},
  "geometry": {"coordinates":[-2.283781,53.467026],"type":"Point"}
}