{
  "type": "Feature",
  "properties": {
    "addr:full":"15 Green St Bath Bath and North East Somerset BA1 2JZ",
    "addr:housenumber":"15",
    "addr:postcode":"ba1 2jz",
    "addr:street":"Green St",
    "iso:country":"GB",
    "sg:address":"15 Green St",
    "sg:city":"Bath",
    "sg:classifiers":[
        {
            "category":"Shopping",
            "subcategory":"Clothing, Apparel, & Fashions",
            "type":"Retail Goods"
        }
    ],
    "sg:postcode":"BA1 2JZ",
    "sg:province":"Bath and North East Somerset",
    "sg:tags":[
        "shop"
    ],
    "wof:name":"Rowland Field Sports Ltd",
    "wof:placetype":"venue"
},
  "geometry": {"coordinates":[-2.360522,51.383263],"type":"Point"}
}