{
  "type": "Feature",
  "properties": {
    "iso:country":"GB",
    "sg:address":"6 Williams Avenue",
    "sg:city":"Exeter",
    "sg:classifiers":[
        {
            "category":"Building & Trades",
            "subcategory":"Construction",
            "type":"Services"
        }
    ],
    "sg:phone":"+44 1392 411851",
    "sg:postcode":"EX2 8BN",
    "sg:province":"Devon",
    "sg:tags":[
        "ventilation",
        "contractor"
    ],
    "wof:name":"West Country Damp Control",
    "wof:placetype":"venue"
},
  "geometry": {"coordinates":[-3.5349729061,50.7158546448],"type":"Point"}
}