{
  "type": "Feature",
  "properties": {
    "addr:full":"Fronwen Red Wharf Bay Pentraeth Isle of Anglesey LL75 8PZ",
    "addr:postcode":"ll75 8pz",
    "iso:country":"GB",
    "sg:address":"Fronwen Red Wharf Bay",
    "sg:city":"Pentraeth",
    "sg:classifiers":[
        {
            "category":"Building & Trades",
            "subcategory":"Equipment Rental",
            "type":"Services"
        }
    ],
    "sg:phone":"+44 1248 450544",
    "sg:postcode":"LL75 8PZ",
    "sg:province":"Isle of Anglesey",
    "sg:tags":[
        "plant",
        "machinery"
    ],
    "wof:name":"P Bennett",
    "wof:placetype":"venue"
},
  "geometry": {"coordinates":[-4.216624,53.282597],"type":"Point"}
}