{
  "type": "Feature",
  "properties": {
    "addr:full":"328e Kilburn High Road London Greater London NW6 2QN",
    "addr:housenumber":"328e",
    "addr:postcode":"nw6 2qn",
    "addr:street":"Kilburn High Road",
    "iso:country":"GB",
    "sg:address":"328e Kilburn High Road",
    "sg:city":"London",
    "sg:classifiers":[
        {
            "category":"Food & Beverages",
            "subcategory":"Bakery",
            "type":"Retail Goods"
        }
    ],
    "sg:phone":"+44 20 7625 7399",
    "sg:postcode":"NW6 2QN",
    "sg:province":"Greater London",
    "sg:tags":[
        "confectionery"
    ],
    "wof:name":"Irish Bakers & Patisserie",
    "wof:placetype":"venue"
},
  "geometry": {"coordinates":[-0.2017460018,51.545337677],"type":"Point"}
}