{
  "type": "Feature",
  "properties": {
    "addr:full":"Kingsbury Road, Curdworth Sutton Coldfield Warwickshire B76 9EE",
    "addr:postcode":"b76 9ee",
    "addr:street":"Kingsbury Road",
    "iso:country":"GB",
    "sg:address":"Kingsbury Road, Curdworth",
    "sg:city":"Sutton Coldfield",
    "sg:classifiers":[
        {
            "category":"Manufacturing",
            "subcategory":"Rubber & Plastics",
            "type":"Manufacturing & Wholesale Goods"
        }
    ],
    "sg:phone":"+44 1675 470382",
    "sg:postcode":"B76 9EE",
    "sg:province":"Warwickshire",
    "sg:tags":[
        "injection",
        "moulding"
    ],
    "wof:name":"Charlesworth & Son Ltd.",
    "wof:placetype":"venue"
},
  "geometry": {"coordinates":[-1.738229,52.534969],"type":"Point"}
}