{
  "type": "Feature",
  "properties": {
    "iso:country":"GB",
    "sg:address":"Unit 8, Weavers Court, Forest Mill",
    "sg:city":"Selkirk",
    "sg:classifiers":[
        {
            "category":"Manufacturing",
            "subcategory":"Rubber & Plastics",
            "type":"Manufacturing & Wholesale Goods"
        }
    ],
    "sg:phone":"+44 1750 21050",
    "sg:postcode":"TD7 5NY",
    "sg:province":"Scottish Borders",
    "sg:tags":[
        "injection",
        "moulding"
    ],
    "wof:name":"Cademuir Toolmaking Ltd",
    "wof:placetype":"venue"
},
  "geometry": {"coordinates":[-2.907738924,55.5322685242],"type":"Point"}
}