{
  "type": "Feature",
  "properties": {
    "addr:full":"The Courtyard Northwich Cheshire CW9 7LU",
    "addr:postcode":"cw9 7lu",
    "iso:country":"GB",
    "sg:address":"The Courtyard",
    "sg:city":"Northwich",
    "sg:classifiers":[
        {
            "category":"Military Area",
            "subcategory":"Air Force Base",
            "type":"Public Place"
        }
    ],
    "sg:phone":"+44 1606 42222",
    "sg:postcode":"CW9 7LU",
    "sg:province":"Cheshire",
    "sg:tags":[
        "taxi",
        "hire",
        "private"
    ],
    "wof:name":"Station Cars",
    "wof:placetype":"venue"
},
  "geometry": {"coordinates":[-2.594354,53.257515],"type":"Point"}
}