{
  "type": "Feature",
  "properties": {
    "addr:full":"Worth Corner, Turners Hill Crawley Surrey RH10 7SL",
    "addr:postcode":"rh10 7sl",
    "addr:street":"Turners Hill",
    "iso:country":"GB",
    "sg:address":"Worth Corner, Turners Hill",
    "sg:city":"Crawley",
    "sg:classifiers":[
        {
            "category":"Real Estate",
            "subcategory":"Surveying",
            "type":"Services"
        }
    ],
    "sg:phone":"+44 1293 881860",
    "sg:postcode":"RH10 7SL",
    "sg:province":"Surrey",
    "sg:tags":[
        "surveyor",
        "quantity"
    ],
    "wof:name":"Harrabin Consultancy",
    "wof:placetype":"venue"
},
  "geometry": {"coordinates":[-0.1558219939,51.1182403564],"type":"Point"}
}