{
  "type": "Feature",
  "properties": {
    "iso:country":"GB",
    "sg:address":"Liverpool Rd, Irlam",
    "sg:city":"Manchester",
    "sg:classifiers":[
        {
            "category":"Building & Trades",
            "subcategory":"Construction",
            "type":"Services"
        }
    ],
    "sg:phone":"+44 161 777 8765",
    "sg:postcode":"M44 6AJ",
    "sg:province":"Greater Manchester",
    "sg:tags":[
        "equipment"
    ],
    "wof:name":"Bryn Thomas Crane Hire",
    "wof:placetype":"venue"
},
  "geometry": {"coordinates":[-2.425654,53.43993],"type":"Point"}
}