{
  "type": "Feature",
  "properties": {
    "iso:country":"GB",
    "sg:address":"96 Corbylands Rd",
    "sg:city":"Sidcup",
    "sg:classifiers":[
        {
            "category":"Building & Trades",
            "subcategory":"Landscaping Services",
            "type":"Services"
        }
    ],
    "sg:phone":"+44 20 8309 9696",
    "sg:postcode":"DA15 8JQ",
    "sg:province":"Kent",
    "sg:tags":[
        "landscape",
        "contractor"
    ],
    "wof:name":"Natural Stone & Landscape Supplies",
    "wof:placetype":"venue"
},
  "geometry": {"coordinates":[0.0908029974,51.4427032471],"type":"Point"}
}