{
  "type": "Feature",
  "properties": {
    "addr:full":"51 Ratcliffe Terrace Edinburgh City of Edinburgh EH9 1SU",
    "addr:housenumber":"51",
    "addr:postcode":"eh9 1su",
    "addr:street":"Ratcliffe Terrace",
    "iso:country":"GB",
    "sg:address":"51 Ratcliffe Terrace",
    "sg:city":"Edinburgh",
    "sg:classifiers":[
        {
            "category":"Wholesale",
            "subcategory":"Office Equipment",
            "type":"Manufacturing & Wholesale Goods"
        },
        {
            "category":"Retail",
            "subcategory":"Storage",
            "type":"Services"
        }
    ],
    "sg:phone":"+44 131 667 0195",
    "sg:postcode":"EH9 1SU",
    "sg:province":"City of Edinburgh",
    "sg:tags":[
        "recording",
        "supplier",
        "furniture"
    ],
    "sg:website":"http://www.welgo.co.uk",
    "wof:name":"Welgo Office Equipment Ltd",
    "wof:placetype":"venue"
},
  "geometry": {"coordinates":[-3.1779010296,55.9338493347],"type":"Point"}
}