{
  "type": "Feature",
  "properties": {
    "addr:full":"36 King Street Twickenham Greater London TW1 3SN",
    "addr:housenumber":"36",
    "addr:postcode":"tw1 3sn",
    "addr:street":"King Street",
    "iso:country":"GB",
    "sg:address":"36 King Street",
    "sg:city":"Twickenham",
    "sg:classifiers":[
        {
            "category":"Food & Beverages",
            "subcategory":"Fruits & Vegetables",
            "type":"Retail Goods"
        }
    ],
    "sg:phone":"+44 20 8891 1900",
    "sg:postcode":"TW1 3SN",
    "sg:province":"Greater London",
    "sg:tags":[
        "greengrocer"
    ],
    "wof:name":"Cousins Of Twickenham",
    "wof:placetype":"venue"
},
  "geometry": {"coordinates":[-0.3290739954,51.4460029602],"type":"Point"}
}