{
  "type": "Feature",
  "properties": {
    "addr:full":"1 Commercial St, Trimdon Collery Trimdon Station Durham TS29 6AD",
    "addr:housenumber":"1",
    "addr:postcode":"ts29 6ad",
    "addr:street":"Commercial St;Station",
    "iso:country":"GB",
    "sg:address":"1 Commercial St, Trimdon Collery",
    "sg:city":"Trimdon Station",
    "sg:classifiers":[
        {
            "category":"Shopping",
            "subcategory":"News",
            "type":"Retail Goods"
        }
    ],
    "sg:phone":"+44 1429 880240",
    "sg:postcode":"TS29 6AD",
    "sg:province":"Durham",
    "sg:tags":[
        "newsagent"
    ],
    "wof:name":"Harpers Newsagents",
    "wof:placetype":"venue"
},
  "geometry": {"coordinates":[-1.4117310047,54.7180175781],"type":"Point"}
}