{
  "type": "Feature",
  "properties": {
    "addr:full":"Cross Lane, Marple Stockport Cheshire SK6 7PZ",
    "addr:postcode":"sk6 7pz",
    "addr:street":"Cross Lane",
    "iso:country":"GB",
    "sg:address":"Cross Lane, Marple",
    "sg:city":"Stockport",
    "sg:classifiers":[
        {
            "category":"Bars & Pubs",
            "type":"Food & Drink"
        },
        {
            "category":"Community Center",
            "subcategory":"Social",
            "type":"Public Place"
        }
    ],
    "sg:phone":"+44 161 427 3839",
    "sg:postcode":"SK6 7PZ",
    "sg:province":"Cheshire",
    "sg:tags":[
        "pubs",
        "house",
        "inn",
        "activity"
    ],
    "wof:name":"The Otters",
    "wof:placetype":"venue"
},
  "geometry": {"coordinates":[-2.0736479759,53.3931999207],"type":"Point"}
}