{
  "type": "Feature",
  "properties": {
    "iso:country":"GB",
    "sg:address":"1 Park Court, Riccall Road, Escrick",
    "sg:city":"York",
    "sg:classifiers":[
        {
            "category":"Real Estate",
            "subcategory":"Surveying",
            "type":"Services"
        }
    ],
    "sg:phone":"+44 1904 728995",
    "sg:postcode":"YO19 6ED",
    "sg:province":"North Yorkshire",
    "sg:tags":[
        "surveyor",
        "quantity"
    ],
    "wof:name":"Hambleton Risk Management Ltd.",
    "wof:placetype":"venue"
},
  "geometry": {"coordinates":[-1.044655,53.879566],"type":"Point"}
}