{
  "type": "Feature",
  "properties": {
    "addr:full":"19 Hollins Lane, Marple Stockport Cheshire SK6 6AW",
    "addr:housenumber":"19",
    "addr:postcode":"sk6 6aw",
    "addr:street":"Hollins Lane",
    "iso:country":"GB",
    "sg:address":"19 Hollins Lane, Marple",
    "sg:city":"Stockport",
    "sg:classifiers":[
        {
            "category":"Professional",
            "subcategory":"Accounting & Tax Preparation",
            "type":"Services"
        }
    ],
    "sg:phone":"+44 161 427 6265",
    "sg:postcode":"SK6 6AW",
    "sg:province":"Cheshire",
    "sg:tags":[
        "accountant"
    ],
    "wof:name":"Geoff Duckworth & Co",
    "wof:placetype":"venue"
},
  "geometry": {"coordinates":[-2.063755,53.395336],"type":"Point"}
}