{
  "type": "Feature",
  "properties": {
    "addr:full":"51 Great Portland Street London Greater London W1W 7LF",
    "addr:housenumber":"51",
    "addr:postcode":"w1w 7lf",
    "addr:street":"Great Portland Street",
    "iso:country":"GB",
    "sg:address":"51 Great Portland Street",
    "sg:city":"London",
    "sg:classifiers":[
        {
            "category":"Building & Trades",
            "subcategory":"Equipment Rental",
            "type":"Services"
        }
    ],
    "sg:postcode":"W1W 7LF",
    "sg:province":"Greater London",
    "sg:tags":[
        "supply"
    ],
    "wof:name":"Octopus Trading Co. Ltd.",
    "wof:placetype":"venue"
},
  "geometry": {"coordinates":[-0.141737,51.51741],"type":"Point"}
}