{
  "type": "Feature",
  "properties": {
    "iso:country":"GB",
    "sg:address":"Badgers Hay, Lodes Lane",
    "sg:city":"Taunton",
    "sg:classifiers":[
        {
            "category":"Health Services",
            "subcategory":"Health Practitioner",
            "type":"Services"
        }
    ],
    "sg:postcode":"TA2 8HU",
    "sg:province":"Somerset",
    "sg:tags":[
        "psychotherapist"
    ],
    "wof:name":"Jill Hopkins",
    "wof:placetype":"venue"
},
  "geometry": {"coordinates":[-3.11296,51.062222],"type":"Point"}
}