{
  "type": "Feature",
  "properties": {
    "iso:country":"GB",
    "sg:address":"Coldwell Street, Selling",
    "sg:city":"Gateshead",
    "sg:classifiers":[
        {
            "category":"Building & Trades",
            "subcategory":"Landscaping Services",
            "type":"Services"
        },
        {
            "category":"Shopping",
            "subcategory":"Pets & Pet Supplies",
            "type":"Retail Goods"
        }
    ],
    "sg:phone":"+44 191 469 0090",
    "sg:postcode":"NE10 9HH",
    "sg:province":"Tyne and Wear",
    "sg:tags":[
        "shop",
        "pond",
        "aquarium"
    ],
    "wof:name":"Emersons Pet Centre",
    "wof:placetype":"venue"
},
  "geometry": {"coordinates":[-1.571049,54.949104],"type":"Point"}
}