{
  "type": "Feature",
  "properties": {
    "addr:full":"32 Shorncliffe Road Folkestone Kent CT20 2NA",
    "addr:housenumber":"32",
    "addr:postcode":"ct20 2na",
    "addr:street":"Shorncliffe Road",
    "iso:country":"GB",
    "sg:address":"32 Shorncliffe Road",
    "sg:city":"Folkestone",
    "sg:classifiers":[
        {
            "category":"Health Services",
            "subcategory":"Dentist",
            "type":"Services"
        }
    ],
    "sg:phone":"+44 1303 253266",
    "sg:postcode":"CT20 2NA",
    "sg:province":"Kent",
    "wof:name":"J R W Smith",
    "wof:placetype":"venue"
},
  "geometry": {"coordinates":[1.165364027,51.0812149048],"type":"Point"}
}