{
  "type": "Feature",
  "properties": {
    "addr:full":"Collis House Milton Keynes Buckinghamshire MK15 0AA",
    "addr:postcode":"mk15 0aa",
    "iso:country":"GB",
    "sg:address":"Collis House",
    "sg:city":"Milton Keynes",
    "sg:classifiers":[
        {
            "category":"Organizations",
            "subcategory":"Non-profit Organization",
            "type":"Services"
        }
    ],
    "sg:postcode":"MK15 0AA",
    "sg:province":"Buckinghamshire",
    "sg:tags":[
        "organisation",
        "voluntary",
        "charity"
    ],
    "wof:name":"St.Francis Children's Society",
    "wof:placetype":"venue"
},
  "geometry": {"coordinates":[-0.7179790139,52.0430717468],"type":"Point"}
}