{
  "type": "Feature",
  "properties": {
    "addr:full":"30-38 Hammersmith Broadway London Greater London W6 7AB",
    "addr:housenumber":"30-38",
    "addr:postcode":"w6 7ab",
    "addr:street":"Hammersmith Broadway",
    "iso:country":"GB",
    "sg:address":"30-38 Hammersmith Broadway",
    "sg:city":"London",
    "sg:classifiers":[
        {
            "category":"Professional",
            "subcategory":"Lawyer & Legal Services",
            "type":"Services"
        }
    ],
    "sg:phone":"+44 20 8741 1482",
    "sg:postcode":"W6 7AB",
    "sg:province":"Greater London",
    "sg:tags":[
        "solicitor"
    ],
    "wof:name":"Farrell Matthews & Weir",
    "wof:placetype":"venue"
},
  "geometry": {"coordinates":[-0.2243379951,51.4933013916],"type":"Point"}
}