{
  "type": "Feature",
  "properties": {
    "iso:country":"GB",
    "sg:address":"27 Dean Ridge, Gowkhall",
    "sg:city":"Dunfermline",
    "sg:classifiers":[
        {
            "category":"Building & Trades",
            "subcategory":"Construction",
            "type":"Services"
        }
    ],
    "sg:postcode":"KY12 9PE",
    "sg:province":"Fife",
    "sg:tags":[
        "joiner",
        "carpenter"
    ],
    "wof:name":"Murray Thompson Joiner",
    "wof:placetype":"venue"
},
  "geometry": {"coordinates":[-3.5220310688,56.08436203],"type":"Point"}
}