{
  "type": "Feature",
  "properties": {
    "addr:full":"Gibbet Lane, Wereham King's Lynn Norfolk PE33 9AA",
    "addr:postcode":"pe33 9aa",
    "addr:street":"Gibbet Lane;Lynn",
    "iso:country":"GB",
    "sg:address":"Gibbet Lane, Wereham",
    "sg:city":"King's Lynn",
    "sg:classifiers":[
        {
            "category":"Building & Trades",
            "subcategory":"Landscaping Services",
            "type":"Services"
        }
    ],
    "sg:phone":"+44 1366 500979",
    "sg:postcode":"PE33 9AA",
    "sg:province":"Norfolk",
    "sg:tags":[
        "horticultural",
        "consultant"
    ],
    "wof:name":"Rudman Construction",
    "wof:placetype":"venue"
},
  "geometry": {"coordinates":[0.4925900102,52.5957717896],"type":"Point"}
}