{
  "type": "Feature",
  "properties": {
    "addr:full":"North Street Herne Bay Kent CT6 5HB",
    "addr:postcode":"ct6 5hb",
    "addr:street":"North Street",
    "iso:country":"GB",
    "sg:address":"North Street",
    "sg:city":"Herne Bay",
    "sg:classifiers":[
        {
            "category":"Bars & Pubs",
            "type":"Food & Drink"
        }
    ],
    "sg:phone":"+44 1227 375658",
    "sg:postcode":"CT6 5HB",
    "sg:province":"Kent",
    "sg:tags":[
        "pubs",
        "inn"
    ],
    "wof:name":"Rodney's Head",
    "wof:placetype":"venue"
},
  "geometry": {"coordinates":[1.131739974,51.3716888428],"type":"Point"}
}