{
  "type": "Feature",
  "properties": {
    "iso:country":"GB",
    "sg:address":"66 Boundary Road, Walthamstow",
    "sg:city":"London",
    "sg:classifiers":[
        {
            "category":"Freight",
            "type":"Transportation"
        }
    ],
    "sg:phone":"+44 20 8503 6833",
    "sg:postcode":"E17 8JU",
    "sg:province":"Greater London",
    "sg:tags":[
        "overseas",
        "shipping",
        "removal"
    ],
    "wof:name":"Mike Harrison Shipping",
    "wof:placetype":"venue"
},
  "geometry": {"coordinates":[-0.017968,51.57563],"type":"Point"}
}