{
  "type": "Feature",
  "properties": {
    "iso:country":"GB",
    "sg:address":"82-90 Queensland Road",
    "sg:city":"London",
    "sg:classifiers":[
        {
            "category":"Professional",
            "subcategory":"Printing & Photocopies",
            "type":"Services"
        }
    ],
    "sg:phone":"+44 20 7686 6111",
    "sg:postcode":"N7 7AS",
    "sg:province":"Greater London",
    "sg:tags":[
        "printer"
    ],
    "wof:name":"Lithosphere Ltd",
    "wof:placetype":"venue"
},
  "geometry": {"coordinates":[-0.108095,51.553314],"type":"Point"}
}