{
  "type": "Feature",
  "properties": {
    "addr:full":"49 Great George Street Leeds West Yorkshire LS1 3BB",
    "addr:housenumber":"49",
    "addr:postcode":"ls1 3bb",
    "addr:street":"Great George Street",
    "iso:country":"GB",
    "sg:address":"49 Great George Street",
    "sg:city":"Leeds",
    "sg:classifiers":[
        {
            "category":"Insurance",
            "subcategory":"Insurance Agent",
            "type":"Services"
        },
        {
            "category":"Professional",
            "subcategory":"Lawyer & Legal Services",
            "type":"Services"
        }
    ],
    "sg:phone":"+44 113 244 9737",
    "sg:postcode":"LS1 3BB",
    "sg:province":"West Yorkshire",
    "sg:tags":[
        "broker",
        "solicitor"
    ],
    "wof:name":"Lawrence Scoffield & Co. Ltd.",
    "wof:placetype":"venue"
},
  "geometry": {"coordinates":[-1.5486899614,53.8009185791],"type":"Point"}
}