{
  "type": "Feature",
  "properties": {
    "iso:country":"GB",
    "sg:address":"4c Cotgrave Shopping Centre, Cotgrave",
    "sg:city":"Nottingham",
    "sg:classifiers":[
        {
            "category":"Food & Beverages",
            "subcategory":"Bakery",
            "type":"Retail Goods"
        }
    ],
    "sg:phone":"+44 115 989 3733",
    "sg:postcode":"NG12 3JQ",
    "sg:province":"Nottinghamshire",
    "sg:tags":[
        "baker"
    ],
    "wof:name":"The Hot Bread Shop",
    "wof:placetype":"venue"
},
  "geometry": {"coordinates":[-1.0571290255,52.9066200256],"type":"Point"}
}