{
  "type": "Feature",
  "properties": {
    "iso:country":"GB",
    "sg:address":"12 Shaw Road",
    "sg:city":"Prestwick",
    "sg:classifiers":[
        {
            "category":"Fast Food",
            "type":"Food & Drink"
        }
    ],
    "sg:phone":"+44 1292 474025",
    "sg:postcode":"KA9 2LN",
    "sg:province":"South Ayrshire",
    "sg:tags":[
        "away",
        "meal",
        "outlet",
        "take"
    ],
    "wof:name":"Dragon City",
    "wof:placetype":"venue"
},
  "geometry": {"coordinates":[-4.5981822014,55.500919342],"type":"Point"}
}