{
  "type": "Feature",
  "properties": {
    "iso:country":"GB",
    "sg:address":"The Old Forge Park St, Lydd",
    "sg:city":"Romney Marsh",
    "sg:classifiers":[
        {
            "category":"Professional",
            "subcategory":"Printing & Photocopies",
            "type":"Services"
        }
    ],
    "sg:postcode":"TN29 9AY",
    "sg:province":"Kent",
    "sg:tags":[
        "printer"
    ],
    "wof:name":"Collins,Chris,",
    "wof:placetype":"venue"
},
  "geometry": {"coordinates":[0.9037529826,50.9503479004],"type":"Point"}
}