{
  "type": "Feature",
  "properties": {
    "addr:full":"87 Heap Bridge Bury Lancashire BL9 7HS",
    "addr:housenumber":"87",
    "addr:postcode":"bl9 7hs",
    "addr:street":"Heap Bridge",
    "iso:country":"GB",
    "sg:address":"87 Heap Bridge",
    "sg:city":"Bury",
    "sg:classifiers":[
        {
            "category":"Fast Food",
            "type":"Food & Drink"
        }
    ],
    "sg:phone":"+44 161 764 1665",
    "sg:postcode":"BL9 7HS",
    "sg:province":"Lancashire",
    "sg:tags":[
        "away",
        "take"
    ],
    "wof:name":"The Butty Stop",
    "wof:placetype":"venue"
},
  "geometry": {"coordinates":[-2.258119,53.588261],"type":"Point"}
}