{
  "type": "Feature",
  "properties": {
    "addr:full":"28 Aberafan Centre Port Talbot Neath Port Talbot SA13 1PB",
    "addr:housenumber":"28",
    "addr:postcode":"sa13 1pb",
    "addr:street":"Aberafan Centre Port Talbot",
    "iso:country":"GB",
    "sg:address":"28 Aberafan Centre",
    "sg:city":"Port Talbot",
    "sg:classifiers":[
        {
            "category":"Sports & Exercise",
            "subcategory":"Sports Center",
            "type":"Entertainment"
        }
    ],
    "sg:phone":"+44 1639 881347",
    "sg:postcode":"SA13 1PB",
    "sg:province":"Neath Port Talbot",
    "sg:tags":[
        "shop",
        "good"
    ],
    "wof:name":"Gwyn Richards Sports",
    "wof:placetype":"venue"
},
  "geometry": {"coordinates":[-3.78549,51.59676],"type":"Point"}
}