{
  "type": "Feature",
  "properties": {
    "addr:full":"Blackbrook Hill House, Tickow Lane Loughborough Leicestershire LE12 9EY",
    "addr:postcode":"le12 9ey",
    "addr:street":"Blackbrook;Tickow Lane",
    "iso:country":"GB",
    "sg:address":"Blackbrook Hill House, Tickow Lane",
    "sg:city":"Loughborough",
    "sg:classifiers":[
        {
            "category":"Retail",
            "subcategory":"Auto Repair",
            "type":"Services"
        },
        {
            "category":"Sports & Exercise",
            "subcategory":"Race Track",
            "type":"Entertainment"
        }
    ],
    "sg:phone":"+44 1509 506054",
    "sg:postcode":"LE12 9EY",
    "sg:province":"Leicestershire",
    "sg:tags":[
        "modification",
        "car",
        "motor",
        "classic"
    ],
    "wof:name":"Simon Hadfield Racecar Restorations",
    "wof:placetype":"venue"
},
  "geometry": {"coordinates":[-1.3134299517,52.7662773132],"type":"Point"}
}