{
  "type": "Feature",
  "properties": {
    "addr:full":"Units 1 & 2 Sherrard Wks, 1a Sherrard Rd London Greater London E7 8DN",
    "addr:housenumber":"units 1 & 2;1a",
    "addr:postcode":"e7 8dn",
    "addr:street":"Sherrard Wks;Sherrard Rd",
    "iso:country":"GB",
    "sg:address":"Units 1 & 2 Sherrard Wks, 1a Sherrard Rd",
    "sg:city":"London",
    "sg:classifiers":[
        {
            "category":"Shopping",
            "subcategory":"Clothing, Apparel, & Fashions",
            "type":"Retail Goods"
        }
    ],
    "sg:postcode":"E7 8DN",
    "sg:province":"Greater London",
    "sg:tags":[
        "clothing",
        "fabric"
    ],
    "wof:name":"Ylunis,Mohammed,",
    "wof:placetype":"venue"
},
  "geometry": {"coordinates":[0.032121,51.544601],"type":"Point"}
}