{
  "type": "Feature",
  "properties": {
    "addr:full":"100c Saughton Road North Edinburgh City of Edinburgh EH12 7JN",
    "addr:housenumber":"100c",
    "addr:postcode":"eh12 7jn",
    "addr:street":"Saughton Road North Edinburgh",
    "iso:country":"GB",
    "sg:address":"100c Saughton Road North",
    "sg:city":"Edinburgh",
    "sg:classifiers":[
        {
            "category":"Food & Beverages",
            "subcategory":"Meat & Fish",
            "type":"Retail Goods"
        }
    ],
    "sg:phone":"+44 131 316 4274",
    "sg:postcode":"EH12 7JN",
    "sg:province":"City of Edinburgh",
    "sg:tags":[
        "butcher"
    ],
    "wof:name":"Harry Simpson",
    "wof:placetype":"venue"
},
  "geometry": {"coordinates":[-3.279266,55.936169],"type":"Point"}
}