{
  "type": "Feature",
  "properties": {
    "iso:country":"GB",
    "sg:address":"Sheldon House, Sheep Street",
    "sg:city":"Shipston-on-stour",
    "sg:classifiers":[
        {
            "category":"Professional",
            "subcategory":"Art Services",
            "type":"Services"
        }
    ],
    "sg:phone":"+44 1608 661085",
    "sg:postcode":"CV36 4AH",
    "sg:province":"Warwickshire",
    "sg:tags":[
        "graphic",
        "designer"
    ],
    "wof:name":"Concept Graphic (Industrial & Graphic Design) Ltd.",
    "wof:placetype":"venue"
},
  "geometry": {"coordinates":[-1.624428,52.063568],"type":"Point"}
}