{
  "type": "Feature",
  "properties": {
    "iso:country":"GB",
    "sg:address":"South Road",
    "sg:city":"Hythe",
    "sg:classifiers":[
        {
            "category":"Government",
            "subcategory":"Office",
            "type":"Public Place"
        },
        {
            "category":"Sports & Exercise",
            "subcategory":"Swimming Pool",
            "type":"Entertainment"
        }
    ],
    "sg:phone":"+44 1303 269177",
    "sg:postcode":"CT21 6AR",
    "sg:province":"Kent",
    "sg:tags":[
        "operation",
        "local"
    ],
    "wof:name":"Hythe Pool",
    "wof:placetype":"venue"
},
  "geometry": {"coordinates":[1.08999,51.067444],"type":"Point"}
}