{
  "type": "Feature",
  "properties": {
    "addr:full":"28 King Street Huntly Aberdeenshire AB54 5DG",
    "addr:housenumber":"28",
    "addr:postcode":"ab54 5dg",
    "addr:street":"King Street",
    "iso:country":"GB",
    "sg:address":"28 King Street",
    "sg:city":"Huntly",
    "sg:classifiers":[
        {
            "category":"Farming",
            "subcategory":"Dairy Farm",
            "type":"Manufacturing & Wholesale Goods"
        },
        {
            "category":"Farming",
            "subcategory":"Livestock Farm",
            "type":"Manufacturing & Wholesale Goods"
        },
        {
            "category":"Farming",
            "subcategory":"Farm",
            "type":"Manufacturing & Wholesale Goods"
        }
    ],
    "sg:phone":"+44 1466 792284",
    "sg:postcode":"AB54 5DG",
    "sg:province":"Aberdeenshire",
    "sg:tags":[
        "breeder",
        "mixed",
        "crop",
        "others"
    ],
    "wof:name":"Grampian Pig Producers Ltd.",
    "wof:placetype":"venue"
},
  "geometry": {"coordinates":[-2.7911350727,57.4467163086],"type":"Point"}
}