{
  "type": "Feature",
  "properties": {
    "addr:full":"Furnace Lane, Lamberhurst Tunbridge Wells East Sussex TN3 8LJ",
    "addr:postcode":"tn3 8lj",
    "addr:street":"Furnace Lane",
    "iso:country":"GB",
    "sg:address":"Furnace Lane, Lamberhurst",
    "sg:city":"Tunbridge Wells",
    "sg:classifiers":[
        {
            "category":"Bars & Pubs",
            "type":"Food & Drink"
        }
    ],
    "sg:phone":"+44 1892 890279",
    "sg:postcode":"TN3 8LJ",
    "sg:province":"East Sussex",
    "sg:tags":[
        "pubs",
        "inn"
    ],
    "wof:name":"Elephants Head",
    "wof:placetype":"venue"
},
  "geometry": {"coordinates":[0.391085,51.099903],"type":"Point"}
}