{
  "type": "Feature",
  "properties": {
    "addr:full":"Unit 8, 343-453 Latimer Rd Ladbroke Grove Greater London W10 6RQ",
    "addr:housenumber":"unit 8",
    "addr:postcode":"343-453;w10 6rq",
    "addr:street":"Latimer Rd",
    "iso:country":"GB",
    "sg:address":"Unit 8, 343-453 Latimer Rd",
    "sg:city":"Ladbroke Grove",
    "sg:classifiers":[
        {
            "category":"Home & Garden",
            "subcategory":"Carpets & Floor Coverings",
            "type":"Retail Goods"
        }
    ],
    "sg:phone":"+44 20 8960 0000",
    "sg:postcode":"W10 6RQ",
    "sg:province":"Greater London",
    "sg:tags":[
        "cleaner",
        "upholstery"
    ],
    "wof:name":"The English Cleaning Company",
    "wof:placetype":"venue"
},
  "geometry": {"coordinates":[-0.2226479948,51.5158500671],"type":"Point"}
}