{
  "type": "Feature",
  "properties": {
    "addr:full":"6 Harbour Street Irvine North Ayrshire KA12 8PY",
    "addr:housenumber":"6",
    "addr:postcode":"ka12 8py",
    "addr:street":"Harbour Street",
    "iso:country":"GB",
    "sg:address":"6 Harbour Street",
    "sg:city":"Irvine",
    "sg:classifiers":[
        {
            "category":"Bars & Pubs",
            "type":"Food & Drink"
        },
        {
            "category":"Community Center",
            "subcategory":"Social",
            "type":"Public Place"
        }
    ],
    "sg:phone":"+44 1294 274657",
    "sg:postcode":"KA12 8PY",
    "sg:province":"North Ayrshire",
    "sg:tags":[
        "pubs",
        "house",
        "inn",
        "activity"
    ],
    "wof:name":"Harbour Lights",
    "wof:placetype":"venue"
},
  "geometry": {"coordinates":[-4.679486,55.609756],"type":"Point"}
}