{
  "type": "Feature",
  "properties": {
    "addr:full":"Unit 7 Crow Nest Industrial Estate, Barnoldswick Colne Lancashire BB8 6JA",
    "addr:housenumber":"unit 7;estate",
    "addr:postcode":"bb8 6ja",
    "addr:street":"Crow Nest Industrial;Colne",
    "iso:country":"GB",
    "sg:address":"Unit 7 Crow Nest Industrial Estate, Barnoldswick",
    "sg:city":"Colne",
    "sg:classifiers":[
        {
            "category":"Manufacturing",
            "subcategory":"Metals",
            "type":"Manufacturing & Wholesale Goods"
        }
    ],
    "sg:phone":"+44 1282 817333",
    "sg:postcode":"BB8 6JA",
    "sg:province":"Lancashire",
    "sg:tags":[
        "steel",
        "fabricator",
        "erectors"
    ],
    "wof:name":"Pendle Metal Craft",
    "wof:placetype":"venue"
},
  "geometry": {"coordinates":[-2.170365,53.856857],"type":"Point"}
}