{
  "type": "Feature",
  "properties": {
    "addr:full":"Sycamore St Newcastle Emlyn Carmarthenshire SA38 9AL",
    "addr:postcode":"sa38 9al",
    "addr:street":"Sycamore St",
    "iso:country":"GB",
    "sg:address":"Sycamore St",
    "sg:city":"Newcastle Emlyn",
    "sg:classifiers":[
        {
            "category":"Banks & Credit Unions",
            "subcategory":"Bank",
            "type":"Services"
        }
    ],
    "sg:phone":"+44 1239 710330",
    "sg:postcode":"SA38 9AL",
    "sg:province":"Carmarthenshire",
    "wof:name":"NatWest",
    "wof:placetype":"venue"
},
  "geometry": {"coordinates":[-4.4679679871,52.038318634],"type":"Point"}
}