{
  "type": "Feature",
  "properties": {
    "addr:full":"Minffordd Road, Caergeiliog Holyhead Isle of Anglesey LL65 3NA",
    "addr:postcode":"ll65 3na",
    "addr:street":"Minffordd Road Caergeiliog Holyhead",
    "iso:country":"GB",
    "sg:address":"Minffordd Road, Caergeiliog",
    "sg:city":"Holyhead",
    "sg:classifiers":[
        {
            "category":"Fast Food",
            "type":"Food & Drink"
        },
        {
            "category":"Food & Beverages",
            "subcategory":"Meat & Fish",
            "type":"Retail Goods"
        }
    ],
    "sg:phone":"+44 1407 741338",
    "sg:postcode":"LL65 3NA",
    "sg:province":"Isle of Anglesey",
    "sg:tags":[
        "chip",
        "away",
        "take"
    ],
    "wof:name":"H Wall",
    "wof:placetype":"venue"
},
  "geometry": {"coordinates":[-4.51695,53.268639],"type":"Point"}
}