{
  "type": "Feature",
  "properties": {
    "addr:full":"Sparks Marina Hayling Island Hampshire PO11 9SR",
    "addr:postcode":"po11 9sr",
    "iso:country":"GB",
    "sg:address":"Sparks Marina",
    "sg:city":"Hayling Island",
    "sg:classifiers":[
        {
            "category":"Autos & Motor Vehicles",
            "subcategory":"Boat Sales",
            "type":"Retail Goods"
        }
    ],
    "sg:phone":"+44 23 9246 6075",
    "sg:postcode":"PO11 9SR",
    "sg:province":"Hampshire",
    "sg:tags":[
        "yacht",
        "broker"
    ],
    "wof:name":"Opalmarine Ltd.",
    "wof:placetype":"venue"
},
  "geometry": {"coordinates":[-0.9776340127,50.8318405151],"type":"Point"}
}