{
  "type": "Feature",
  "properties": {
    "addr:full":"Speedwell Close, Chandlers Ford Industrial Estate Eastleigh Hampshire SO53 4BT",
    "addr:postcode":"so53 4bt",
    "addr:street":"Speedwell Close Chandlers Ford Industrial Estate",
    "iso:country":"GB",
    "sg:address":"Speedwell Close, Chandlers Ford Industrial Estate",
    "sg:city":"Eastleigh",
    "sg:classifiers":[
        {
            "category":"Cinema",
            "subcategory":"Movie Rental",
            "type":"Entertainment"
        }
    ],
    "sg:phone":"+44 23 8026 7428",
    "sg:postcode":"SO53 4BT",
    "sg:province":"Hampshire",
    "sg:tags":[
        "video",
        "library"
    ],
    "wof:name":"Video Solent (West) Ltd.",
    "wof:placetype":"venue"
},
  "geometry": {"coordinates":[-1.395442009,50.982219696],"type":"Point"}
}