{
  "type": "Feature",
  "properties": {
    "iso:country":"GB",
    "sg:address":"15 Stevenson Court, Craigshill",
    "sg:city":"Livingston",
    "sg:classifiers":[
        {
            "category":"Military Area",
            "subcategory":"Air Force Base",
            "type":"Public Place"
        }
    ],
    "sg:postcode":"EH54 5NW",
    "sg:province":"West Lothian",
    "sg:tags":[
        "taxi",
        "hire",
        "private"
    ],
    "wof:name":"Direct Airport Transfers",
    "wof:placetype":"venue"
},
  "geometry": {"coordinates":[-3.509834,55.886246],"type":"Point"}
}