{
  "type": "Feature",
  "properties": {
    "iso:country":"GB",
    "sg:address":"Southmead Surgery, Blackpond La",
    "sg:city":"Slough",
    "sg:classifiers":[
        {
            "category":"Health Services",
            "subcategory":"Doctor",
            "type":"Services"
        }
    ],
    "sg:phone":"+44 1753 643195",
    "sg:postcode":"SL2 3ER",
    "sg:province":"Berkshire",
    "sg:tags":[
        "practitioners"
    ],
    "wof:name":"Sally-Ann Hayward",
    "wof:placetype":"venue"
},
  "geometry": {"coordinates":[-0.61694,51.55249],"type":"Point"}
}