{
  "type": "Feature",
  "properties": {
    "iso:country":"GB",
    "sg:address":"82 Hall Lane, West Winch",
    "sg:city":"King's Lynn",
    "sg:classifiers":[
        {
            "category":"Building & Trades",
            "subcategory":"Plumbing",
            "type":"Services"
        }
    ],
    "sg:phone":"+44 1553 840859",
    "sg:postcode":"PE33 0QF",
    "sg:province":"Norfolk",
    "sg:tags":[
        "plumber",
        "heating"
    ],
    "wof:name":"LENNY TRACEY",
    "wof:placetype":"venue"
},
  "geometry": {"coordinates":[0.41056,52.708099],"type":"Point"}
}