{
  "type": "Feature",
  "properties": {
    "addr:full":"Mauds Yard, Southgate Wakefield West Yorkshire WF1 1BA",
    "addr:postcode":"wf1 1ba",
    "addr:street":"Southgate Wakefield West",
    "iso:country":"GB",
    "sg:address":"Mauds Yard, Southgate",
    "sg:city":"Wakefield",
    "sg:classifiers":[
        {
            "category":"Place Of Worship",
            "type":"Public Place"
        }
    ],
    "sg:phone":"+44 1977 600224",
    "sg:postcode":"WF1 1BA",
    "sg:province":"West Yorkshire",
    "wof:name":"The Salvation Army",
    "wof:placetype":"venue"
},
  "geometry": {"coordinates":[-1.50054,53.68108],"type":"Point"}
}