{
  "type": "Feature",
  "properties": {
    "iso:country":"GB",
    "sg:address":"White Chimneys, Mill Hill, Ashford Road",
    "sg:city":"Ashford",
    "sg:classifiers":[
        {
            "category":"Retail",
            "subcategory":"Repair Shop",
            "type":"Services"
        }
    ],
    "sg:postcode":"TN23 3EW",
    "sg:province":"Kent",
    "sg:tags":[
        "upholsterer"
    ],
    "wof:name":"Denis Hayer",
    "wof:placetype":"venue"
},
  "geometry": {"coordinates":[0.876037,51.146633],"type":"Point"}
}