{
  "type": "Feature",
  "properties": {
    "iso:country":"GB",
    "sg:address":"18 High Street, Alton",
    "sg:city":"Stoke-on-trent",
    "sg:classifiers":[
        {
            "category":"Professional",
            "subcategory":"Art Services",
            "type":"Services"
        }
    ],
    "sg:postcode":"ST10 4AQ",
    "sg:province":"Staffordshire",
    "sg:tags":[
        "picture",
        "restoration"
    ],
    "wof:name":"Alton Framing",
    "wof:placetype":"venue"
},
  "geometry": {"coordinates":[-1.891489,52.978096],"type":"Point"}
}