{
  "type": "Feature",
  "properties": {
    "addr:full":"19 Theatre Walk Derby Derbyshire DE1 2NG",
    "addr:housenumber":"19",
    "addr:postcode":"de1 2ng",
    "addr:street":"Theatre Walk",
    "iso:country":"GB",
    "sg:address":"19 Theatre Walk",
    "sg:city":"Derby",
    "sg:classifiers":[
        {
            "category":"Shopping",
            "subcategory":"Clothing, Apparel, & Fashions",
            "type":"Retail Goods"
        }
    ],
    "sg:postcode":"DE1 2NG",
    "sg:province":"Derbyshire",
    "sg:tags":[
        "ladieswear"
    ],
    "wof:name":"West One",
    "wof:placetype":"venue"
},
  "geometry": {"coordinates":[-1.4836839437,52.9251708984],"type":"Point"}
}