{
  "type": "Feature",
  "properties": {
    "addr:full":"Unit 9, Upper Barn Farm, Bicester Rd, Westcott Aylesbury Buckinghamshire HP18 0JX",
    "addr:housenumber":"unit 9",
    "addr:postcode":"hp18 0jx",
    "addr:street":"Upper Barn;Bicester Rd",
    "iso:country":"GB",
    "sg:address":"Unit 9, Upper Barn Farm, Bicester Rd, Westcott",
    "sg:city":"Aylesbury",
    "sg:classifiers":[
        {
            "category":"Autos & Motor Vehicles",
            "subcategory":"Automobile Sales",
            "type":"Retail Goods"
        }
    ],
    "sg:phone":"+44 1296 651893",
    "sg:postcode":"HP18 0JX",
    "sg:province":"Buckinghamshire",
    "sg:tags":[
        "car",
        "specialist",
        "sales",
        "classic"
    ],
    "wof:name":"The Horseless Carriage Company",
    "wof:placetype":"venue"
},
  "geometry": {"coordinates":[-0.957499,51.846924],"type":"Point"}
}