{
  "type": "Feature",
  "properties": {
    "addr:full":"Slaidburn Crescent Southport Lancashire PR9 9AL",
    "addr:postcode":"pr9 9al",
    "addr:street":"Slaidburn Crescent",
    "iso:country":"GB",
    "sg:address":"Slaidburn Crescent",
    "sg:city":"Southport",
    "sg:classifiers":[
        {
            "category":"Shopping",
            "subcategory":"Pharmacy",
            "type":"Retail Goods"
        }
    ],
    "sg:postcode":"PR9 9AL",
    "sg:province":"Lancashire",
    "sg:tags":[
        "pharmaceutical"
    ],
    "wof:name":"Bell Sons & Co. (Druggists) Ltd.",
    "wof:placetype":"venue"
},
  "geometry": {"coordinates":[-2.9614810944,53.6732635498],"type":"Point"}
}