{
  "type": "Feature",
  "properties": {
    "addr:full":"21 Sussex Croft Woodbridge Suffolk IP12 3TL",
    "addr:housenumber":"21",
    "addr:postcode":"ip12 3tl",
    "addr:street":"Sussex Croft",
    "iso:country":"GB",
    "sg:address":"21 Sussex Croft",
    "sg:city":"Woodbridge",
    "sg:classifiers":[
        {
            "category":"Social Services",
            "subcategory":"Child Care",
            "type":"Services"
        }
    ],
    "sg:phone":"+44 1394 460905",
    "sg:postcode":"IP12 3TL",
    "sg:province":"Suffolk",
    "sg:tags":[
        "agency",
        "nanny"
    ],
    "wof:name":"Au Pair Link",
    "wof:placetype":"venue"
},
  "geometry": {"coordinates":[1.385268,52.083939],"type":"Point"}
}