{
  "type": "Feature",
  "properties": {
    "iso:country":"GB",
    "sg:address":"Kipling Rd",
    "sg:city":"Chester",
    "sg:classifiers":[
        {
            "category":"Education",
            "subcategory":"School",
            "type":"Public Place"
        }
    ],
    "sg:phone":"+44 1244 390758",
    "sg:postcode":"CH1 5UU",
    "sg:province":"Cheshire",
    "sg:tags":[
        "local",
        "authority"
    ],
    "wof:name":"St. Theresa Primary School",
    "wof:placetype":"venue"
},
  "geometry": {"coordinates":[-2.916334,53.20916],"type":"Point"}
}