{
  "type": "Feature",
  "properties": {
    "iso:country":"GB",
    "sg:address":"36 Canterbury Street",
    "sg:city":"Gillingham",
    "sg:classifiers":[
        {
            "category":"Shopping",
            "subcategory":"Music",
            "type":"Retail Goods"
        }
    ],
    "sg:phone":"+44 1634 281750",
    "sg:postcode":"ME7 5TX",
    "sg:province":"Kent",
    "sg:tags":[
        "dvd",
        "record",
        "tape",
        "vinyl",
        "cd"
    ],
    "wof:name":"Medway Record Centre",
    "wof:placetype":"venue"
},
  "geometry": {"coordinates":[0.5447030067,51.3867607117],"type":"Point"}
}