{
  "type": "Feature",
  "properties": {
    "iso:country":"GB",
    "sg:address":"89 Union Street",
    "sg:city":"Larkhall",
    "sg:classifiers":[
        {
            "category":"Food & Beverages",
            "subcategory":"Fruits & Vegetables",
            "type":"Retail Goods"
        }
    ],
    "sg:phone":"+44 1698 882857",
    "sg:postcode":"ML9 1DZ",
    "sg:province":"South Lanarkshire",
    "sg:tags":[
        "greengrocer"
    ],
    "wof:name":"K & J McGuire",
    "wof:placetype":"venue"
},
  "geometry": {"coordinates":[-3.9735319614,55.7395706177],"type":"Point"}
}