{
  "type": "Feature",
  "properties": {
    "iso:country":"GB",
    "sg:address":"The Street, Coaley",
    "sg:city":"Dursley",
    "sg:classifiers":[
        {
            "category":"Education",
            "subcategory":"School",
            "type":"Public Place"
        }
    ],
    "sg:phone":"+44 1453 890358",
    "sg:postcode":"GL11 5EB",
    "sg:province":"Gloucestershire",
    "sg:tags":[
        "local",
        "authority"
    ],
    "wof:name":"Coaley C Of E Controlled Primary School",
    "wof:placetype":"venue"
},
  "geometry": {"coordinates":[-2.330017,51.710686],"type":"Point"}
}