{
  "type": "Feature",
  "properties": {
    "iso:country":"GB",
    "sg:address":"Works Customs Centre, The Airport, Newmarket Rd",
    "sg:city":"Cambridge",
    "sg:classifiers":[
        {
            "category":"Airline",
            "type":"Transportation"
        }
    ],
    "sg:postcode":"CB5 8RT",
    "sg:province":"Cambridgeshire",
    "sg:tags":[
        "aircraft",
        "charter"
    ],
    "wof:name":"Magnet Air Services Ltd",
    "wof:placetype":"venue"
},
  "geometry": {"coordinates":[0.1747249961,52.2108001709],"type":"Point"}
}