{
  "type": "Feature",
  "properties": {
    "addr:full":"23 Station Road, Chadwell Heath Romford Essex RM6 4BE",
    "addr:housenumber":"23",
    "addr:postcode":"rm6 4be",
    "addr:street":"Station Road",
    "iso:country":"GB",
    "sg:address":"23 Station Road, Chadwell Heath",
    "sg:city":"Romford",
    "sg:classifiers":[
        {
            "category":"Building & Trades",
            "subcategory":"Plumbing",
            "type":"Services"
        }
    ],
    "sg:phone":"+44 20 8599 2228",
    "sg:postcode":"RM6 4BE",
    "sg:province":"Essex",
    "sg:tags":[
        "merchant",
        "plumbers'"
    ],
    "wof:name":"Heathpace Ltd.",
    "wof:placetype":"venue"
},
  "geometry": {"coordinates":[0.130501,51.570061],"type":"Point"}
}