{
  "type": "Feature",
  "properties": {
    "addr:full":"Trenders Avenue Rayleigh Essex SS6 9RG",
    "addr:postcode":"ss6 9rg",
    "addr:street":"Avenue",
    "iso:country":"GB",
    "sg:address":"Trenders Avenue",
    "sg:city":"Rayleigh",
    "sg:classifiers":[
        {
            "category":"Wholesale",
            "subcategory":"Scrap",
            "type":"Manufacturing & Wholesale Goods"
        }
    ],
    "sg:phone":"+44 1268 780150",
    "sg:postcode":"SS6 9RG",
    "sg:province":"Essex",
    "sg:tags":[
        "salvage"
    ],
    "wof:name":"Searles Reclamation & Salvage",
    "wof:placetype":"venue"
},
  "geometry": {"coordinates":[0.598154,51.612602],"type":"Point"}
}