{
  "type": "Feature",
  "properties": {
    "iso:country":"GB",
    "sg:address":"Social Services, Ross On Wye Area, Berkeley Lodge",
    "sg:city":"Ross On Wye",
    "sg:classifiers":[
        {
            "category":"Government",
            "subcategory":"Office",
            "type":"Public Place"
        }
    ],
    "sg:phone":"+44 1989 567444",
    "sg:postcode":"HR9 7DA",
    "sg:province":"Gloucestershire",
    "sg:tags":[
        "local"
    ],
    "wof:name":"Worcestershire County Council",
    "wof:placetype":"venue"
},
  "geometry": {"coordinates":[-2.581733,51.916481],"type":"Point"}
}