{
  "type": "Feature",
  "properties": {
    "iso:country":"GB",
    "sg:address":"Croydon Road, Radford",
    "sg:city":"Nottingham",
    "sg:classifiers":[
        {
            "category":"Professional",
            "subcategory":"Printing & Photocopies",
            "type":"Services"
        }
    ],
    "sg:phone":"+44 115 924 9111",
    "sg:postcode":"NG7 3DS",
    "sg:province":"Nottinghamshire",
    "sg:tags":[
        "process",
        "screen",
        "printer"
    ],
    "wof:name":"Diagraph Advertising",
    "wof:placetype":"venue"
},
  "geometry": {"coordinates":[-1.178945,52.959232],"type":"Point"}
}