{
  "type": "Feature",
  "properties": {
    "addr:full":"29 Newborough Scarborough North Yorkshire YO11 1NA",
    "addr:housenumber":"29",
    "addr:postcode":"yo11 1na",
    "addr:street":"Newborough",
    "iso:country":"GB",
    "sg:address":"29 Newborough",
    "sg:city":"Scarborough",
    "sg:classifiers":[
        {
            "category":"Shopping",
            "subcategory":"Clothing, Apparel, & Fashions",
            "type":"Retail Goods"
        }
    ],
    "sg:phone":"+44 1723 352577",
    "sg:postcode":"YO11 1NA",
    "sg:province":"North Yorkshire",
    "sg:tags":[
        "shop"
    ],
    "wof:name":"Kings Stores",
    "wof:placetype":"venue"
},
  "geometry": {"coordinates":[-0.398453,54.282818],"type":"Point"}
}