{
  "type": "Feature",
  "properties": {
    "iso:country":"GB",
    "sg:address":"1 Bede Av, Burton Stone La",
    "sg:city":"York",
    "sg:classifiers":[
        {
            "category":"Personal",
            "type":"Services"
        }
    ],
    "sg:phone":"+44 1904 626964",
    "sg:postcode":"YO30 6ED",
    "sg:province":"North Yorkshire",
    "sg:tags":[
        "dressmaker"
    ],
    "wof:name":"Thelma",
    "wof:placetype":"venue"
},
  "geometry": {"coordinates":[-1.0867259502,53.9742698669],"type":"Point"}
}