{
  "type": "Feature",
  "properties": {
    "iso:country":"GB",
    "sg:address":"Becketts Wharf, Lower Teddington Rd",
    "sg:city":"Kingston Upon Thames",
    "sg:classifiers":[
        {
            "category":"Professional",
            "subcategory":"Computer Services",
            "type":"Services"
        }
    ],
    "sg:phone":"+44 20 8943 0027",
    "sg:postcode":"KT1 4ER",
    "sg:province":"Greater London",
    "sg:tags":[
        "system",
        "software"
    ],
    "wof:name":"S Q L Star People Ltd",
    "wof:placetype":"venue"
},
  "geometry": {"coordinates":[-0.3097690046,51.4135246277],"type":"Point"}
}