{
  "type": "Feature",
  "properties": {
    "iso:country":"GB",
    "sg:address":"50a Flamborough Road",
    "sg:city":"Bridlington",
    "sg:classifiers":[
        {
            "category":"Shopping",
            "subcategory":"Florist",
            "type":"Retail Goods"
        }
    ],
    "sg:phone":"+44 1262 400484",
    "sg:postcode":"YO15 2JQ",
    "sg:province":"East Riding of Yorkshire",
    "wof:name":"The Flower Shop",
    "wof:placetype":"venue"
},
  "geometry": {"coordinates":[-0.185698,54.090057],"type":"Point"}
}