{
  "type": "Feature",
  "properties": {
    "iso:country":"GB",
    "sg:address":"16 Tavistock St, Bletchley",
    "sg:city":"Milton Keynes",
    "sg:classifiers":[
        {
            "category":"Autos & Motor Vehicles",
            "subcategory":"Automobile Sales",
            "type":"Retail Goods"
        }
    ],
    "sg:phone":"+44 1908 375666",
    "sg:postcode":"MK2 2PF",
    "sg:province":"Buckinghamshire",
    "sg:tags":[
        "commercial"
    ],
    "wof:name":"Roots Works",
    "wof:placetype":"venue"
},
  "geometry": {"coordinates":[-0.7214649916,51.9994888306],"type":"Point"}
}