{
  "type": "Feature",
  "properties": {
    "iso:country":"GB",
    "sg:address":"Central Methodist Church, Oldergate",
    "sg:city":"Tamworth",
    "sg:classifiers":[
        {
            "category":"Organizations",
            "subcategory":"Non-profit Organization",
            "type":"Services"
        }
    ],
    "sg:phone":"+44 1827 310353",
    "sg:postcode":"B79 7BJ",
    "sg:province":"Staffordshire",
    "sg:tags":[
        "organisation",
        "voluntary",
        "charity"
    ],
    "wof:name":"South East Staffordshire Friendship Project",
    "wof:placetype":"venue"
},
  "geometry": {"coordinates":[-1.6876840591,52.6340942383],"type":"Point"}
}