{
  "type": "Feature",
  "properties": {
    "addr:full":"High St Steyning West Sussex BN44 3RE",
    "addr:postcode":"bn44 3re",
    "addr:street":"High St",
    "iso:country":"GB",
    "sg:address":"High St",
    "sg:city":"Steyning",
    "sg:classifiers":[
        {
            "category":"Bars & Pubs",
            "type":"Food & Drink"
        }
    ],
    "sg:postcode":"BN44 3RE",
    "sg:province":"West Sussex",
    "sg:tags":[
        "pubs",
        "inn"
    ],
    "wof:name":"Ord,Douglas,",
    "wof:placetype":"venue"
},
  "geometry": {"coordinates":[-0.3325639963,50.8909950256],"type":"Point"}
}