{
  "type": "Feature",
  "properties": {
    "iso:country":"GB",
    "sg:address":"P O Box 3151, West Bergholt",
    "sg:city":"Colchester",
    "sg:classifiers":[
        {
            "category":"Professional",
            "subcategory":"Computer Services",
            "type":"Services"
        }
    ],
    "sg:phone":"+44 1206 240120",
    "sg:postcode":"CO6 3JH",
    "sg:province":"Essex",
    "sg:tags":[
        "system",
        "software"
    ],
    "wof:name":"Delta Computer Training Ltd.",
    "wof:placetype":"venue"
},
  "geometry": {"coordinates":[0.8386,51.916451],"type":"Point"}
}