{
  "type": "Feature",
  "properties": {
    "addr:full":"55 Friends Av Waltham Cross Essex EN8 8LX",
    "addr:housenumber":"55",
    "addr:postcode":"en8 8lx",
    "addr:street":"Friends Av Waltham Cross",
    "iso:country":"GB",
    "sg:address":"55 Friends Av",
    "sg:city":"Waltham Cross",
    "sg:classifiers":[
        {
            "category":"Home & Garden",
            "subcategory":"Home Furnishings",
            "type":"Retail Goods"
        }
    ],
    "sg:phone":"+44 1992 629018",
    "sg:postcode":"EN8 8LX",
    "sg:province":"Essex",
    "sg:tags":[
        "awning",
        "canopy",
        "blinds"
    ],
    "wof:name":"A P Conservatory & Awning Specialists",
    "wof:placetype":"venue"
},
  "geometry": {"coordinates":[-0.037671,51.695709],"type":"Point"}
}