{
  "type": "Feature",
  "properties": {
    "addr:full":"Unit 2 Venlo Industrial Estate, Knowles Street Bradford West Yorkshire BD4 6HA",
    "addr:housenumber":"unit 2",
    "addr:postcode":"bd4 6ha",
    "addr:street":"Industrial Estate Knowles Street",
    "iso:country":"GB",
    "sg:address":"Unit 2 Venlo Industrial Estate, Knowles Street",
    "sg:city":"Bradford",
    "sg:classifiers":[
        {
            "category":"Professional",
            "subcategory":"Engineering",
            "type":"Services"
        }
    ],
    "sg:phone":"+44 1274 688870",
    "sg:postcode":"BD4 6HA",
    "sg:province":"West Yorkshire",
    "wof:name":"A E S Engineering Ltd.",
    "wof:placetype":"venue"
},
  "geometry": {"coordinates":[-1.724750042,53.7714691162],"type":"Point"}
}