{
  "type": "Feature",
  "properties": {
    "addr:full":"1012 Bradford Road, Birstall Batley West Yorkshire WF17 9JD",
    "addr:housenumber":"1012",
    "addr:postcode":"wf17 9jd",
    "addr:street":"Bradford Road",
    "iso:country":"GB",
    "sg:address":"1012 Bradford Road, Birstall",
    "sg:city":"Batley",
    "sg:classifiers":[
        {
            "category":"Professional",
            "subcategory":"Engineering",
            "type":"Services"
        }
    ],
    "sg:phone":"+44 1924 479613",
    "sg:postcode":"WF17 9JD",
    "sg:province":"West Yorkshire",
    "sg:tags":[
        "contractor",
        "electrical",
        "engineer"
    ],
    "wof:name":"Control & Development (Leeds) Ltd.",
    "wof:placetype":"venue"
},
  "geometry": {"coordinates":[-1.67055,53.733185],"type":"Point"}
}