{
  "type": "Feature",
  "properties": {
    "iso:country":"GB",
    "sg:address":"Riverside Place, The Bridge",
    "sg:city":"Taunton",
    "sg:classifiers":[
        {
            "category":"Shopping",
            "subcategory":"Clothing, Apparel, & Fashions",
            "type":"Retail Goods"
        }
    ],
    "sg:postcode":"TA1 4UG",
    "sg:province":"Somerset",
    "sg:tags":[
        "clothing",
        "fabric"
    ],
    "wof:name":"Chandni Chowk",
    "wof:placetype":"venue"
},
  "geometry": {"coordinates":[-3.110699,51.01049],"type":"Point"}
}