{
  "type": "Feature",
  "properties": {
    "iso:country":"GB",
    "sg:address":"30 St Clements Street",
    "sg:city":"Oxford",
    "sg:classifiers":[
        {
            "category":"Bars & Pubs",
            "type":"Food & Drink"
        },
        {
            "category":"Community Center",
            "subcategory":"Social",
            "type":"Public Place"
        }
    ],
    "sg:phone":"+44 1865 242660",
    "sg:postcode":"OX4 1AB",
    "sg:province":"Oxfordshire",
    "sg:tags":[
        "pubs",
        "house",
        "inn",
        "activity"
    ],
    "wof:name":"Angel & Greyhound",
    "wof:placetype":"venue"
},
  "geometry": {"coordinates":[-1.242691,51.750221],"type":"Point"}
}