{
  "type": "Feature",
  "properties": {
    "addr:full":"2 Lindsay Road Poole Dorset BH13 6AR",
    "addr:housenumber":"2",
    "addr:postcode":"bh13 6ar",
    "addr:street":"Lindsay Road",
    "iso:country":"GB",
    "sg:address":"2 Lindsay Road",
    "sg:city":"Poole",
    "sg:classifiers":[
        {
            "category":"Farming",
            "subcategory":"Nursery",
            "type":"Manufacturing & Wholesale Goods"
        },
        {
            "category":"Education",
            "subcategory":"Preschool",
            "type":"Public Place"
        }
    ],
    "sg:phone":"+44 1202 768769",
    "sg:postcode":"BH13 6AR",
    "sg:province":"Dorset",
    "sg:tags":[
        "school",
        "creche"
    ],
    "wof:name":"Puss 'N' Boots Day Nursery",
    "wof:placetype":"venue"
},
  "geometry": {"coordinates":[-1.922636,50.723808],"type":"Point"}
}