{
  "type": "Feature",
  "properties": {
    "iso:country":"GB",
    "sg:address":"3 Alder Drive, Hoghton",
    "sg:city":"Preston",
    "sg:classifiers":[
        {
            "category":"Fast Food",
            "type":"Food & Drink"
        }
    ],
    "sg:phone":"+44 1254 851400",
    "sg:postcode":"PR5 0AD",
    "sg:province":"Lancashire",
    "sg:tags":[
        "away",
        "meal",
        "outlet",
        "take"
    ],
    "wof:name":"Topoli Kebab & Pizza House",
    "wof:placetype":"venue"
},
  "geometry": {"coordinates":[-2.619925,53.73333],"type":"Point"}
}