{
  "type": "Feature",
  "properties": {
    "addr:full":"53b Kingston Hill Kingston-upon-thames Greater London KT2 7PS",
    "addr:housenumber":"53b",
    "addr:postcode":"kt2 7ps",
    "addr:street":"Kingston Hill Kingston-Upon-Thames",
    "iso:country":"GB",
    "sg:address":"53b Kingston Hill",
    "sg:city":"Kingston-upon-thames",
    "sg:classifiers":[
        {
            "category":"Professional",
            "subcategory":"Accounting & Tax Preparation",
            "type":"Services"
        }
    ],
    "sg:phone":"+44 20 8546 7773",
    "sg:postcode":"KT2 7PS",
    "sg:province":"Greater London",
    "sg:tags":[
        "accountant"
    ],
    "wof:name":"A Munir Sheikh & Co",
    "wof:placetype":"venue"
},
  "geometry": {"coordinates":[-0.284396,51.415916],"type":"Point"}
}