{
  "type": "Feature",
  "properties": {
    "addr:full":"Blackvein Industrial Estate, Cross Keys Newport Blaenau Gwent NP11 7PX",
    "addr:postcode":"np11 7px",
    "addr:street":"Estate",
    "iso:country":"GB",
    "sg:address":"Blackvein Industrial Estate, Cross Keys",
    "sg:city":"Newport",
    "sg:classifiers":[
        {
            "category":"Manufacturing",
            "subcategory":"Metals",
            "type":"Manufacturing & Wholesale Goods"
        }
    ],
    "sg:postcode":"NP11 7PX",
    "sg:province":"Blaenau Gwent",
    "sg:tags":[
        "steel",
        "stockholder"
    ],
    "wof:name":"Hall & Pickles",
    "wof:placetype":"venue"
},
  "geometry": {"coordinates":[-3.134394,51.618141],"type":"Point"}
}