{
  "type": "Feature",
  "properties": {
    "addr:full":"11 North Lane, Rustington Littlehampton West Sussex BN16 3PF",
    "addr:housenumber":"11",
    "addr:postcode":"bn16 3pf",
    "addr:street":"North Lane",
    "iso:country":"GB",
    "sg:address":"11 North Lane, Rustington",
    "sg:city":"Littlehampton",
    "sg:classifiers":[
        {
            "category":"Personal",
            "subcategory":"Beauty Salon",
            "type":"Services"
        }
    ],
    "sg:phone":"+44 1903 782756",
    "sg:postcode":"BN16 3PF",
    "sg:province":"West Sussex",
    "sg:tags":[
        "unisex",
        "hairdresser"
    ],
    "wof:name":"Lovely Hair",
    "wof:placetype":"venue"
},
  "geometry": {"coordinates":[-0.516356,50.813412],"type":"Point"}
}