{
  "type": "Feature",
  "properties": {
    "addr:full":"Green Road, Headington Oxford Oxfordshire OX3 8EU",
    "addr:postcode":"ox3 8eu",
    "addr:street":"Green Road",
    "iso:country":"GB",
    "sg:address":"Green Road, Headington",
    "sg:city":"Oxford",
    "sg:classifiers":[
        {
            "category":"Communications",
            "subcategory":"Television Station",
            "type":"Services"
        }
    ],
    "sg:phone":"+44 1865 767676",
    "sg:postcode":"OX3 8EU",
    "sg:province":"Oxfordshire",
    "sg:tags":[
        "audio-visual"
    ],
    "wof:name":"Unicol Engineering",
    "wof:placetype":"venue"
},
  "geometry": {"coordinates":[-1.1958099604,51.7606887817],"type":"Point"}
}