{
  "type": "Feature",
  "properties": {
    "iso:country":"GB",
    "sg:address":"4 Mount Crescent, Morriston",
    "sg:city":"Swansea",
    "sg:classifiers":[
        {
            "category":"Food & Beverages",
            "subcategory":"Supermarket",
            "type":"Retail Goods"
        }
    ],
    "sg:phone":"+44 1792 791381",
    "sg:postcode":"SA6 6BS",
    "sg:province":"Swansea",
    "wof:name":"Spar",
    "wof:placetype":"venue"
},
  "geometry": {"coordinates":[-3.938684,51.670383],"type":"Point"}
}