{
  "type": "Feature",
  "properties": {
    "iso:country":"GB",
    "sg:address":"1-2 Wallis Road, Skippers Lane Industrial Estate",
    "sg:city":"Middlesbrough",
    "sg:classifiers":[
        {
            "category":"Retail",
            "subcategory":"Auto Repair",
            "type":"Services"
        }
    ],
    "sg:postcode":"TS6 6JB",
    "sg:province":"North Yorkshire",
    "sg:tags":[
        "modification",
        "garage"
    ],
    "wof:name":"Auto Vehicle Services",
    "wof:placetype":"venue"
},
  "geometry": {"coordinates":[-1.183147,54.572044],"type":"Point"}
}