{
  "type": "Feature",
  "properties": {
    "iso:country":"GB",
    "sg:address":"30 Stafford St",
    "sg:city":"Edinburgh",
    "sg:classifiers":[
        {
            "category":"Real Estate",
            "subcategory":"Architect",
            "type":"Services"
        }
    ],
    "sg:postcode":"EH3 7BD",
    "sg:province":"City of Edinburgh",
    "wof:name":"Reilly,George,",
    "wof:placetype":"venue"
},
  "geometry": {"coordinates":[-3.212289,55.950207],"type":"Point"}
}