{
  "type": "Feature",
  "properties": {
    "iso:country":"GB",
    "sg:address":"74 Smith Lane",
    "sg:city":"Leigh",
    "sg:classifiers":[
        {
            "category":"Farming",
            "subcategory":"Nursery",
            "type":"Manufacturing & Wholesale Goods"
        }
    ],
    "sg:phone":"+44 1942 259870",
    "sg:postcode":"WN2 4XR",
    "sg:province":"Lancashire",
    "sg:tags":[
        "creche"
    ],
    "wof:name":"Kate's Kindergarten",
    "wof:placetype":"venue"
},
  "geometry": {"coordinates":[-2.520198,53.494438],"type":"Point"}
}