{
  "type": "Feature",
  "properties": {
    "addr:full":"West Rd, Shoeburyness Southend On Sea Essex SS3 9EF",
    "addr:postcode":"ss3 9ef",
    "addr:street":"West Rd;Southend;Sea",
    "iso:country":"GB",
    "sg:address":"West Rd, Shoeburyness",
    "sg:city":"Southend On Sea",
    "sg:classifiers":[
        {
            "category":"Place Of Worship",
            "type":"Public Place"
        }
    ],
    "sg:phone":"+44 1702 296425",
    "sg:postcode":"SS3 9EF",
    "sg:province":"Essex",
    "wof:name":"Shoebury Evangelical Church",
    "wof:placetype":"venue"
},
  "geometry": {"coordinates":[0.7796059847,51.5329246521],"type":"Point"}
}