{
  "type": "Feature",
  "properties": {
    "iso:country":"GB",
    "sg:address":"Elms Court, Torrs Park",
    "sg:city":"Ilfracombe",
    "sg:classifiers":[
        {
            "category":"Professional",
            "subcategory":"Printing & Photocopies",
            "type":"Services"
        }
    ],
    "sg:phone":"+44 1271 862557",
    "sg:postcode":"EX34 8BA",
    "sg:province":"Devon",
    "sg:tags":[
        "printer"
    ],
    "wof:name":"Arthur H Stockwell Ltd.",
    "wof:placetype":"venue"
},
  "geometry": {"coordinates":[-4.128042,51.208588],"type":"Point"}
}