{
  "type": "Feature",
  "properties": {
    "addr:full":"46 Bushell Road Poole Dorset BH15 3HE",
    "addr:housenumber":"46",
    "addr:postcode":"bh15 3he",
    "addr:street":"Bushell Road",
    "iso:country":"GB",
    "sg:address":"46 Bushell Road",
    "sg:city":"Poole",
    "sg:classifiers":[
        {
            "category":"Retail",
            "subcategory":"Repair Shop",
            "type":"Services"
        }
    ],
    "sg:postcode":"BH15 3HE",
    "sg:province":"Dorset",
    "sg:tags":[
        "radio",
        "television",
        "video"
    ],
    "wof:name":"J P T V",
    "wof:placetype":"venue"
},
  "geometry": {"coordinates":[-1.9848899841,50.7387886047],"type":"Point"}
}