{
  "type": "Feature",
  "properties": {
    "iso:country":"GB",
    "sg:address":"Warton Road",
    "sg:city":"Carnforth",
    "sg:classifiers":[
        {
            "category":"Shopping",
            "subcategory":"Crafts & Fabrics",
            "type":"Retail Goods"
        }
    ],
    "sg:phone":"+44 1524 732005",
    "sg:postcode":"LA5 9EU",
    "sg:province":"Cumbria",
    "sg:tags":[
        "merchant",
        "wool"
    ],
    "wof:name":"Scotish Wool Growers",
    "wof:placetype":"venue"
},
  "geometry": {"coordinates":[-2.771196,54.131489],"type":"Point"}
}