{
  "type": "Feature",
  "properties": {
    "addr:full":"13-15 Warner Street Stevenston North Ayrshire KA20 3LB",
    "addr:housenumber":"13-15",
    "addr:postcode":"ka20 3lb",
    "addr:street":"Warner Street",
    "iso:country":"GB",
    "sg:address":"13-15 Warner Street",
    "sg:city":"Stevenston",
    "sg:classifiers":[
        {
            "category":"Government",
            "subcategory":"Office",
            "type":"Public Place"
        }
    ],
    "sg:phone":"+44 1294 468434",
    "sg:postcode":"KA20 3LB",
    "sg:province":"North Ayrshire",
    "sg:tags":[
        "local"
    ],
    "wof:name":"Warner Street Children's Home",
    "wof:placetype":"venue"
},
  "geometry": {"coordinates":[-4.75081,55.633862],"type":"Point"}
}