{
  "type": "Feature",
  "properties": {
    "addr:full":"47 High Street, Great Gonerby Grantham Lincolnshire NG31 8JR",
    "addr:housenumber":"47",
    "addr:postcode":"ng31 8jr",
    "addr:street":"High Street",
    "iso:country":"GB",
    "sg:address":"47 High Street, Great Gonerby",
    "sg:city":"Grantham",
    "sg:classifiers":[
        {
            "category":"Bus Charters",
            "type":"Transportation"
        }
    ],
    "sg:phone":"+44 1476 563118",
    "sg:postcode":"NG31 8JR",
    "sg:province":"Lincolnshire",
    "sg:tags":[
        "hire",
        "coach"
    ],
    "wof:name":"W J Simmons (Coaches) Ltd.",
    "wof:placetype":"venue"
},
  "geometry": {"coordinates":[-0.667176,52.937119],"type":"Point"}
}