{
  "type": "Feature",
  "properties": {
    "iso:country":"GB",
    "sg:address":"New Rd",
    "sg:city":"Tredegar",
    "sg:classifiers":[
        {
            "category":"Professional",
            "subcategory":"Testing Lab",
            "type":"Services"
        }
    ],
    "sg:phone":"+44 1495 725980",
    "sg:postcode":"NP22 4BL",
    "sg:province":"Blaenau Gwent",
    "sg:tags":[
        "mot"
    ],
    "wof:name":"Morgans Car Sales",
    "wof:placetype":"venue"
},
  "geometry": {"coordinates":[-3.2184939384,51.7360649109],"type":"Point"}
}