{
  "type": "Feature",
  "properties": {
    "iso:country":"GB",
    "sg:address":"89 High Street, Hadleigh",
    "sg:city":"Ipswich",
    "sg:classifiers":[
        {
            "category":"Professional",
            "subcategory":"Accounting & Tax Preparation",
            "type":"Services"
        }
    ],
    "sg:phone":"+44 1473 822143",
    "sg:postcode":"IP7 5EA",
    "sg:province":"Suffolk",
    "sg:tags":[
        "consultant",
        "activity"
    ],
    "wof:name":"Walter Wright & Co",
    "wof:placetype":"venue"
},
  "geometry": {"coordinates":[0.9527829885,52.0448989868],"type":"Point"}
}