{
  "type": "Feature",
  "properties": {
    "iso:country":"GB",
    "sg:address":"Unit 1 Reardene, Cleeve Road",
    "sg:city":"Evesham",
    "sg:classifiers":[
        {
            "category":"Home & Garden",
            "subcategory":"Home Furnishings",
            "type":"Retail Goods"
        }
    ],
    "sg:postcode":"WR11 8JR",
    "sg:province":"Gloucestershire",
    "sg:tags":[
        "mantelpiece",
        "fireplace"
    ],
    "wof:name":"Alcester Fireplaces",
    "wof:placetype":"venue"
},
  "geometry": {"coordinates":[-1.943969,52.106392],"type":"Point"}
}