{
  "type": "Feature",
  "properties": {
    "addr:full":"Betony Road, Enigma Business Park Malvern Herefordshire WR14 1GB",
    "addr:postcode":"wr14 1gb",
    "addr:street":"Betony Road;Business Park",
    "iso:country":"GB",
    "sg:address":"Betony Road, Enigma Business Park",
    "sg:city":"Malvern",
    "sg:classifiers":[
        {
            "category":"Home & Garden",
            "subcategory":"Carpets & Floor Coverings",
            "type":"Retail Goods"
        }
    ],
    "sg:phone":"+44 1684 572880",
    "sg:postcode":"WR14 1GB",
    "sg:province":"Herefordshire",
    "sg:tags":[
        "rubber",
        "plastic"
    ],
    "wof:name":"Neale Plastics Ltd.",
    "wof:placetype":"venue"
},
  "geometry": {"coordinates":[-2.3022658825,52.1254234314],"type":"Point"}
}