{
  "type": "Feature",
  "properties": {
    "addr:full":"50 Baxter Gate Loughborough Leicestershire LE11 1TH",
    "addr:housenumber":"50",
    "addr:postcode":"le11 1th",
    "addr:street":"Baxter Gate",
    "iso:country":"GB",
    "sg:address":"50 Baxter Gate",
    "sg:city":"Loughborough",
    "sg:classifiers":[
        {
            "category":"Professional",
            "type":"Services"
        }
    ],
    "sg:phone":"+44 1509 260600",
    "sg:postcode":"LE11 1TH",
    "sg:province":"Leicestershire",
    "sg:tags":[
        "repair",
        "tech",
        "maintenance"
    ],
    "wof:name":"Miracle Micros",
    "wof:placetype":"venue"
},
  "geometry": {"coordinates":[-1.2035609484,52.772605896],"type":"Point"}
}