{
  "type": "Feature",
  "properties": {
    "addr:full":"19 Main Street, Barton Under Needwood Burton-on-trent Derbyshire DE13 8AA",
    "addr:housenumber":"19",
    "addr:postcode":"de13 8aa",
    "addr:street":"Main Street",
    "iso:country":"GB",
    "sg:address":"19 Main Street, Barton Under Needwood",
    "sg:city":"Burton-on-trent",
    "sg:classifiers":[
        {
            "category":"Professional",
            "subcategory":"Art Services",
            "type":"Services"
        }
    ],
    "sg:phone":"+44 1283 711711",
    "sg:postcode":"DE13 8AA",
    "sg:province":"Derbyshire",
    "sg:tags":[
        "graphic",
        "designer"
    ],
    "wof:name":"Norman Stuart Partnership",
    "wof:placetype":"venue"
},
  "geometry": {"coordinates":[-1.722254,52.764462],"type":"Point"}
}