{
  "type": "Feature",
  "properties": {
    "iso:country":"GB",
    "sg:address":"17 The Avenue",
    "sg:city":"Minehead",
    "sg:classifiers":[
        {
            "category":"Professional",
            "subcategory":"Employment Agencies",
            "type":"Services"
        }
    ],
    "sg:phone":"+44 1643 435800",
    "sg:postcode":"TA24 5XZ",
    "sg:province":"Somerset",
    "sg:tags":[
        "consultant"
    ],
    "wof:name":"Employment Service Jobcentre",
    "wof:placetype":"venue"
},
  "geometry": {"coordinates":[-3.475131,51.206444],"type":"Point"}
}