{
  "type": "Feature",
  "properties": {
    "addr:full":"14 Warminster Rd Westbury Wiltshire BA13 3PB",
    "addr:housenumber":"14",
    "addr:postcode":"ba13 3pb",
    "addr:street":"Warminster Rd",
    "iso:country":"GB",
    "sg:address":"14 Warminster Rd",
    "sg:city":"Westbury",
    "sg:classifiers":[
        {
            "category":"Professional",
            "subcategory":"Art Services",
            "type":"Services"
        }
    ],
    "sg:phone":"+44 1373 300045",
    "sg:postcode":"BA13 3PB",
    "sg:province":"Wiltshire",
    "sg:tags":[
        "picture",
        "restoration"
    ],
    "wof:name":"Westbury Fine Art & Framing",
    "wof:placetype":"venue"
},
  "geometry": {"coordinates":[-2.1835649014,51.2592086792],"type":"Point"}
}