{
  "type": "Feature",
  "properties": {
    "iso:country":"GB",
    "sg:address":"205 Woodgrange Drive",
    "sg:city":"Southend-on-sea",
    "sg:classifiers":[
        {
            "category":"Food & Beverages",
            "subcategory":"Bakery",
            "type":"Retail Goods"
        }
    ],
    "sg:phone":"+44 1702 463736",
    "sg:postcode":"SS1 2SG",
    "sg:province":"Essex",
    "sg:tags":[
        "baker"
    ],
    "wof:name":"Baldwins Bakeries Ltd.",
    "wof:placetype":"venue"
},
  "geometry": {"coordinates":[0.732787,51.535748],"type":"Point"}
}