{
  "type": "Feature",
  "properties": {
    "addr:full":"13 Briarwood Bristol City of Bristol BS9 3SS",
    "addr:housenumber":"13",
    "addr:postcode":"bs9 3ss",
    "addr:street":"Briarwood",
    "iso:country":"GB",
    "sg:address":"13 Briarwood",
    "sg:city":"Bristol",
    "sg:classifiers":[
        {
            "category":"Professional",
            "subcategory":"Accounting & Tax Preparation",
            "type":"Services"
        }
    ],
    "sg:postcode":"BS9 3SS",
    "sg:province":"City of Bristol",
    "sg:tags":[
        "accountant"
    ],
    "wof:name":"Peter S Whitfield",
    "wof:placetype":"venue"
},
  "geometry": {"coordinates":[-2.621913,51.487553],"type":"Point"}
}