{
  "type": "Feature",
  "properties": {
    "addr:full":"South Croft, Ovington Prudhoe Northumberland NE42 6EE",
    "addr:postcode":"ne42 6ee",
    "addr:street":"South Croft",
    "iso:country":"GB",
    "sg:address":"South Croft, Ovington",
    "sg:city":"Prudhoe",
    "sg:classifiers":[
        {
            "category":"Real Estate",
            "subcategory":"Surveying",
            "type":"Services"
        }
    ],
    "sg:phone":"+44 1661 832515",
    "sg:postcode":"NE42 6EE",
    "sg:province":"Northumberland",
    "sg:tags":[
        "surveyor",
        "valuer"
    ],
    "wof:name":"Michael D Coates",
    "wof:placetype":"venue"
},
  "geometry": {"coordinates":[-1.899347,54.96825],"type":"Point"}
}