{
  "type": "Feature",
  "properties": {
    "addr:full":"189 Balham High Road London Greater London SW12 9BA",
    "addr:housenumber":"189",
    "addr:postcode":"sw12 9ba",
    "addr:street":"Balham High",
    "iso:country":"GB",
    "sg:address":"189 Balham High Road",
    "sg:city":"London",
    "sg:classifiers":[
        {
            "category":"Cafe",
            "type":"Food & Drink"
        }
    ],
    "sg:phone":"+44 20 8675 4547",
    "sg:postcode":"SW12 9BA",
    "sg:province":"Greater London",
    "sg:tags":[
        "tea",
        "room"
    ],
    "wof:name":"Chris's Cafe",
    "wof:placetype":"venue"
},
  "geometry": {"coordinates":[-0.1541849971,51.4416351318],"type":"Point"}
}