{
  "type": "Feature",
  "properties": {
    "addr:full":"Unit 2 Aldbourne Road Coventry West Midlands CV1 4EQ",
    "addr:housenumber":"unit 2",
    "addr:postcode":"cv1 4eq",
    "addr:street":"Aldbourne Road",
    "iso:country":"GB",
    "sg:address":"Unit 2 Aldbourne Road",
    "sg:city":"Coventry",
    "sg:classifiers":[
        {
            "category":"Manufacturing",
            "subcategory":"Metals",
            "type":"Manufacturing & Wholesale Goods"
        },
        {
            "category":"Professional",
            "subcategory":"Engineering",
            "type":"Services"
        }
    ],
    "sg:phone":"+44 24 7663 0489",
    "sg:postcode":"CV1 4EQ",
    "sg:province":"West Midlands",
    "sg:tags":[
        "work",
        "sheet",
        "engineer"
    ],
    "wof:name":"Coventry Metal Design",
    "wof:placetype":"venue"
},
  "geometry": {"coordinates":[-1.5095289946,52.4188728333],"type":"Point"}
}