{
  "type": "Feature",
  "properties": {
    "iso:country":"GB",
    "sg:address":"81a Front St",
    "sg:city":"Prudhoe",
    "sg:classifiers":[
        {
            "category":"Education",
            "subcategory":"Special Training",
            "type":"Public Place"
        }
    ],
    "sg:phone":"+44 1661 835393",
    "sg:postcode":"NE42 5PU",
    "sg:province":"Northumberland",
    "sg:tags":[
        "product",
        "centre"
    ],
    "wof:name":"North East Chamber Of Commerce Jobwise (Tynedale)",
    "wof:placetype":"venue"
},
  "geometry": {"coordinates":[-1.85283,54.961235],"type":"Point"}
}