{
  "type": "Feature",
  "properties": {
    "iso:country":"GB",
    "sg:address":"107 Bear Road, Hamworth",
    "sg:city":"Feltham",
    "sg:classifiers":[
        {
            "category":"Shopping",
            "subcategory":"Pharmacy",
            "type":"Retail Goods"
        }
    ],
    "sg:phone":"+44 20 8898 0327",
    "sg:postcode":"TW13 6SA",
    "sg:province":"Greater London",
    "sg:tags":[
        "pharmacist",
        "chemist"
    ],
    "wof:name":"Moss Chemists",
    "wof:placetype":"venue"
},
  "geometry": {"coordinates":[-0.390207,51.430733],"type":"Point"}
}