{
  "type": "Feature",
  "properties": {
    "iso:country":"GB",
    "sg:address":"Oakham Crescent, Bulkington",
    "sg:city":"Nuneaton",
    "sg:classifiers":[
        {
            "category":"Government",
            "subcategory":"Office",
            "type":"Public Place"
        },
        {
            "category":"Social Services",
            "subcategory":"Adult Care",
            "type":"Services"
        },
        {
            "category":"Social Services",
            "subcategory":"Retirement Home",
            "type":"Services"
        }
    ],
    "sg:phone":"+44 24 7631 3614",
    "sg:postcode":"CV12 9JS",
    "sg:province":"Warwickshire",
    "sg:tags":[
        "housing",
        "local",
        "accommodation",
        "sheltered"
    ],
    "wof:name":"Oakham Crescent Sheltered Housing",
    "wof:placetype":"venue"
},
  "geometry": {"coordinates":[-1.416902,52.476826],"type":"Point"}
}