{
  "type": "Feature",
  "properties": {
    "addr:full":"70 Broadway, Urmston Manchester Cheshire M41 7WF",
    "addr:housenumber":"70",
    "addr:postcode":"m41 7wf",
    "addr:street":"Broadway",
    "iso:country":"GB",
    "sg:address":"70 Broadway, Urmston",
    "sg:city":"Manchester",
    "sg:classifiers":[
        {
            "category":"Freight",
            "type":"Transportation"
        },
        {
            "category":"Government",
            "subcategory":"Post Office",
            "type":"Public Place"
        }
    ],
    "sg:phone":"+44 161 746 7846",
    "sg:postcode":"M41 7WF",
    "sg:province":"Cheshire",
    "sg:tags":[
        "haulage",
        "messenger",
        "road",
        "courier",
        "transport"
    ],
    "wof:name":"Lifeline Courier Services",
    "wof:placetype":"venue"
},
  "geometry": {"coordinates":[-2.364148,53.460217],"type":"Point"}
}