{
  "type": "Feature",
  "properties": {
    "iso:country":"GB",
    "sg:address":"5 Staple Close, West Quantoxhead",
    "sg:city":"Taunton",
    "sg:classifiers":[
        {
            "category":"Professional",
            "subcategory":"Engineering",
            "type":"Services"
        },
        {
            "category":"Building & Trades",
            "subcategory":"Electrical",
            "type":"Services"
        }
    ],
    "sg:phone":"+44 1984 632690",
    "sg:postcode":"TA4 4DF",
    "sg:province":"Devon",
    "sg:tags":[
        "engineer",
        "electrician",
        "contractor"
    ],
    "wof:name":"Jago Electrical",
    "wof:placetype":"venue"
},
  "geometry": {"coordinates":[-3.2763619423,51.1678009033],"type":"Point"}
}