{
  "type": "Feature",
  "properties": {
    "addr:full":"6 Rectory Lane, Harrietsham Maidstone Kent ME17 1HP",
    "addr:housenumber":"6",
    "addr:postcode":"me17 1hp",
    "addr:street":"Rectory Lane",
    "iso:country":"GB",
    "sg:address":"6 Rectory Lane, Harrietsham",
    "sg:city":"Maidstone",
    "sg:classifiers":[
        {
            "category":"Education",
            "subcategory":"College",
            "type":"Public Place"
        }
    ],
    "sg:phone":"+44 1622 851447",
    "sg:postcode":"ME17 1HP",
    "sg:province":"Kent",
    "sg:tags":[
        "school"
    ],
    "wof:name":"School Shop (Mail Order) Ltd.",
    "wof:placetype":"venue"
},
  "geometry": {"coordinates":[0.6820819974,51.2416992188],"type":"Point"}
}