{
  "type": "Feature",
  "properties": {
    "iso:country":"GB",
    "sg:address":"8 Owl Lane, Shaw Cross",
    "sg:city":"Dewsbury",
    "sg:classifiers":[
        {
            "category":"Home & Garden",
            "subcategory":"Building Materials",
            "type":"Retail Goods"
        }
    ],
    "sg:phone":"+44 1924 463488",
    "sg:postcode":"WF12 7RQ",
    "sg:province":"West Yorkshire",
    "sg:tags":[
        "plaster",
        "ware",
        "plasterware"
    ],
    "wof:name":"Ossett Mouldings Fibrous Ltd",
    "wof:placetype":"venue"
},
  "geometry": {"coordinates":[-1.604019,53.703415],"type":"Point"}
}