{
  "type": "Feature",
  "properties": {
    "addr:full":"9 Railway Street Hertford Hertfordshire SG14 1BG",
    "addr:housenumber":"9",
    "addr:postcode":"sg14 1bg",
    "addr:street":"Railway Street",
    "iso:country":"GB",
    "sg:address":"9 Railway Street",
    "sg:city":"Hertford",
    "sg:classifiers":[
        {
            "category":"Cafe",
            "type":"Food & Drink"
        }
    ],
    "sg:phone":"+44 1992 589726",
    "sg:postcode":"SG14 1BG",
    "sg:province":"Hertfordshire",
    "sg:tags":[
        "tea",
        "snack",
        "bar",
        "room"
    ],
    "wof:name":"Barnies Grill",
    "wof:placetype":"venue"
},
  "geometry": {"coordinates":[-0.07674,51.79707],"type":"Point"}
}