{
  "type": "Feature",
  "properties": {
    "iso:country":"GB",
    "sg:address":"Unit 18 Garston Industrial Estate, Blackburne Street",
    "sg:city":"Liverpool",
    "sg:classifiers":[
        {
            "category":"Shopping",
            "subcategory":"Pets & Pet Supplies",
            "type":"Retail Goods"
        }
    ],
    "sg:phone":"+44 151 494 9050",
    "sg:postcode":"L19 8JB",
    "sg:province":"Merseyside",
    "sg:tags":[
        "food"
    ],
    "wof:name":"Companions Choice Products Ltd.",
    "wof:placetype":"venue"
},
  "geometry": {"coordinates":[-2.897359,53.345726],"type":"Point"}
}