{
  "type": "Feature",
  "properties": {
    "addr:full":"Tower Road South Bristol Gloucestershire BS30 8BT",
    "addr:postcode":"bs30 8bt",
    "addr:street":"Tower Road South",
    "iso:country":"GB",
    "sg:address":"Tower Road South",
    "sg:city":"Bristol",
    "sg:classifiers":[
        {
            "category":"Sports & Exercise",
            "subcategory":"Golf",
            "type":"Entertainment"
        }
    ],
    "sg:phone":"+44 117 967 5859",
    "sg:postcode":"BS30 8BT",
    "sg:province":"Gloucestershire",
    "sg:tags":[
        "club",
        "course"
    ],
    "wof:name":"Warmley Golf Course",
    "wof:placetype":"venue"
},
  "geometry": {"coordinates":[-2.477228,51.451778],"type":"Point"}
}