{
  "type": "Feature",
  "properties": {
    "iso:country":"GB",
    "sg:address":"70 Wimborne Rd",
    "sg:city":"Poole",
    "sg:classifiers":[
        {
            "category":"Health Services",
            "subcategory":"Health Practitioner",
            "type":"Services"
        }
    ],
    "sg:phone":"+44 1202 674956",
    "sg:postcode":"BH15 2BZ",
    "sg:province":"Dorset",
    "sg:tags":[
        "homoeopathic"
    ],
    "wof:name":"Ian Roberts BSc. C.Ed. LLSCH.",
    "wof:placetype":"venue"
},
  "geometry": {"coordinates":[-1.9784920216,50.7231216431],"type":"Point"}
}