{
  "type": "Feature",
  "properties": {
    "addr:full":"Marine Parade West Clacton-on-sea Essex CO15 1XB",
    "addr:postcode":"co15 1xb",
    "addr:street":"Marine Parade West",
    "iso:country":"GB",
    "sg:address":"Marine Parade West",
    "sg:city":"Clacton-on-sea",
    "sg:classifiers":[
        {
            "category":"Cafe",
            "type":"Food & Drink"
        },
        {
            "category":"Ice Cream",
            "type":"Food & Drink"
        }
    ],
    "sg:phone":"+44 1255 474852",
    "sg:postcode":"CO15 1XB",
    "sg:province":"Essex",
    "sg:tags":[
        "tea",
        "parlour",
        "room"
    ],
    "wof:name":"Greensward Cafe",
    "wof:placetype":"venue"
},
  "geometry": {"coordinates":[1.1536200047,51.7871856689],"type":"Point"}
}