{
  "type": "Feature",
  "properties": {
    "iso:country":"GB",
    "sg:address":"196 New Street, Biddulph Moor",
    "sg:city":"Stoke-on-trent",
    "sg:classifiers":[
        {
            "category":"Home & Garden",
            "subcategory":"Home Furnishings",
            "type":"Retail Goods"
        }
    ],
    "sg:phone":"+44 1782 514105",
    "sg:postcode":"ST8 7NW",
    "sg:province":"Staffordshire",
    "sg:tags":[
        "mantelpiece",
        "fireplace"
    ],
    "wof:name":"Ideas",
    "wof:placetype":"venue"
},
  "geometry": {"coordinates":[-2.15002,53.11425],"type":"Point"}
}