{
  "type": "Feature",
  "properties": {
    "iso:country":"GB",
    "sg:address":"3 Godrer Waen, Flint Mountain",
    "sg:city":"Flint",
    "sg:classifiers":[
        {
            "category":"Professional",
            "subcategory":"Engineering",
            "type":"Services"
        }
    ],
    "sg:postcode":"CH6 5UU",
    "sg:province":"Flintshire",
    "sg:tags":[
        "contractor",
        "electrical",
        "engineer"
    ],
    "wof:name":"Taylor-Jones Electrical Ltd.",
    "wof:placetype":"venue"
},
  "geometry": {"coordinates":[-3.135299,53.224121],"type":"Point"}
}