{
  "type": "Feature",
  "properties": {
    "iso:country":"GB",
    "sg:address":"21 Alexandra Road",
    "sg:city":"Sleaford",
    "sg:classifiers":[
        {
            "category":"Building & Trades",
            "subcategory":"Construction",
            "type":"Services"
        }
    ],
    "sg:postcode":"NG34 7QW",
    "sg:province":"Lincolnshire",
    "sg:tags":[
        "decorator",
        "painter"
    ],
    "wof:name":"A P Maintenance",
    "wof:placetype":"venue"
},
  "geometry": {"coordinates":[-0.41803,52.997395],"type":"Point"}
}