{
  "type": "Feature",
  "properties": {
    "iso:country":"GB",
    "sg:address":"65 Bond Street",
    "sg:city":"Macclesfield",
    "sg:classifiers":[
        {
            "category":"Shopping",
            "subcategory":"News",
            "type":"Retail Goods"
        },
        {
            "category":"Government",
            "subcategory":"Post Office",
            "type":"Public Place"
        }
    ],
    "sg:postcode":"SK11 6QR",
    "sg:province":"Cheshire",
    "sg:tags":[
        "newsagent"
    ],
    "wof:name":"Stewarts Bond Street Post Office",
    "wof:placetype":"venue"
},
  "geometry": {"coordinates":[-2.1322760582,53.2568588257],"type":"Point"}
}