{
  "type": "Feature",
  "properties": {
    "iso:country":"GB",
    "sg:address":"School Lane, Littlewick Green",
    "sg:city":"Maidenhead",
    "sg:classifiers":[
        {
            "category":"Education",
            "subcategory":"Preschool",
            "type":"Public Place"
        },
        {
            "category":"Education",
            "subcategory":"School",
            "type":"Public Place"
        }
    ],
    "sg:phone":"+44 1628 828258",
    "sg:postcode":"SL6 3QY",
    "sg:province":"Berkshire",
    "sg:tags":[
        "independent",
        "preparatory",
        "nursery"
    ],
    "wof:name":"Littlewick Green Montessori School",
    "wof:placetype":"venue"
},
  "geometry": {"coordinates":[-0.7911859751,51.5109977722],"type":"Point"}
}