{
  "type": "Feature",
  "properties": {
    "addr:full":"Manor Farm, Church Lane, Croydon Royston Bedfordshire SG8 0DX",
    "addr:postcode":"sg8 0dx",
    "addr:street":"Manor;Church Lane",
    "iso:country":"GB",
    "sg:address":"Manor Farm, Church Lane, Croydon",
    "sg:city":"Royston",
    "sg:classifiers":[
        {
            "category":"Farming",
            "subcategory":"Farm",
            "type":"Manufacturing & Wholesale Goods"
        }
    ],
    "sg:phone":"+44 1223 207203",
    "sg:postcode":"SG8 0DX",
    "sg:province":"Bedfordshire",
    "sg:tags":[
        "mixed",
        "crop"
    ],
    "wof:name":"D & A Sapsed",
    "wof:placetype":"venue"
},
  "geometry": {"coordinates":[-0.079094,52.128361],"type":"Point"}
}