{
  "type": "Feature",
  "properties": {
    "iso:country":"GB",
    "sg:address":"Unit 15 Heath Hill Industrial Estate, Dawley",
    "sg:city":"Telford",
    "sg:classifiers":[
        {
            "category":"Building & Trades",
            "subcategory":"Equipment Rental",
            "type":"Services"
        }
    ],
    "sg:phone":"+44 1952 504349",
    "sg:postcode":"TF4 2RH",
    "sg:province":"Shropshire",
    "sg:tags":[
        "hire",
        "centre"
    ],
    "wof:name":"Quanthire",
    "wof:placetype":"venue"
},
  "geometry": {"coordinates":[-2.472110033,52.6657447815],"type":"Point"}
}