{
  "type": "Feature",
  "properties": {
    "addr:full":"43a Redlaver Street, Grangetown Cardiff Cardiff CF11 7LZ",
    "addr:housenumber":"43a",
    "addr:postcode":"cf11 7lz",
    "addr:street":"Redlaver Street",
    "iso:country":"GB",
    "sg:address":"43a Redlaver Street, Grangetown",
    "sg:city":"Cardiff",
    "sg:classifiers":[
        {
            "category":"Building & Trades",
            "subcategory":"Construction",
            "type":"Services"
        }
    ],
    "sg:postcode":"CF11 7LZ",
    "sg:province":"Cardiff",
    "sg:tags":[
        "flooring"
    ],
    "wof:name":"P M Laws Flooring",
    "wof:placetype":"venue"
},
  "geometry": {"coordinates":[-3.185765028,51.4689254761],"type":"Point"}
}