{
  "type": "Feature",
  "properties": {
    "iso:country":"GB",
    "sg:address":"43 St Johns Road",
    "sg:city":"Hemel Hempstead",
    "sg:classifiers":[
        {
            "category":"Fast Food",
            "type":"Food & Drink"
        }
    ],
    "sg:phone":"+44 1442 250008",
    "sg:postcode":"HP1 1QQ",
    "sg:province":"Hertfordshire",
    "sg:tags":[
        "away",
        "meal",
        "outlet",
        "take"
    ],
    "wof:name":"Alinoor Tandoori",
    "wof:placetype":"venue"
},
  "geometry": {"coordinates":[-0.486717999,51.7462272644],"type":"Point"}
}