{
  "type": "Feature",
  "properties": {
    "addr:full":"Adelpha 1-11 John Adams St Holborn Greater London WC2N 6HT",
    "addr:housenumber":"1-11",
    "addr:postcode":"wc2n 6ht",
    "addr:street":"Adelpha;John Adams St",
    "iso:country":"GB",
    "sg:address":"Adelpha 1-11 John Adams St",
    "sg:city":"Holborn",
    "sg:classifiers":[
        {
            "category":"Organizations",
            "subcategory":"Non-profit Organization",
            "type":"Services"
        }
    ],
    "sg:phone":"+44 20 7712 2443",
    "sg:postcode":"WC2N 6HT",
    "sg:province":"Greater London",
    "sg:tags":[
        "organisation",
        "voluntary",
        "charity"
    ],
    "wof:name":"Womens National Commission The",
    "wof:placetype":"venue"
},
  "geometry": {"coordinates":[-0.1222200021,51.5090408325],"type":"Point"}
}