{
  "type": "Feature",
  "properties": {
    "addr:full":"12 Brindlery Road Hinckley Leicestershire LE10 3BY",
    "addr:housenumber":"12",
    "addr:postcode":"le10 3by",
    "addr:street":"Brindlery Road",
    "iso:country":"GB",
    "sg:address":"12 Brindlery Road",
    "sg:city":"Hinckley",
    "sg:classifiers":[
        {
            "category":"Wholesale",
            "subcategory":"Scrap",
            "type":"Manufacturing & Wholesale Goods"
        }
    ],
    "sg:phone":"+44 1455 637393",
    "sg:postcode":"LE10 3BY",
    "sg:province":"Leicestershire",
    "sg:tags":[
        "waste",
        "metal"
    ],
    "wof:name":"B & R White",
    "wof:placetype":"venue"
},
  "geometry": {"coordinates":[-1.4035,52.540138],"type":"Point"}
}