{
  "type": "Feature",
  "properties": {
    "iso:country":"GB",
    "sg:address":"99 Berwick Street",
    "sg:city":"London",
    "sg:classifiers":[
        {
            "category":"Shopping",
            "subcategory":"Used Merchandise",
            "type":"Retail Goods"
        }
    ],
    "sg:postcode":"W1F 0QD",
    "sg:province":"Greater London",
    "sg:tags":[
        "shop",
        "second-hand"
    ],
    "wof:name":"Andy's Household Goods",
    "wof:placetype":"venue"
},
  "geometry": {"coordinates":[-0.134545,51.512871],"type":"Point"}
}