{
  "type": "Feature",
  "properties": {
    "addr:full":"Tetnall Street Dudley West Midlands DY2 8SA",
    "addr:postcode":"dy2 8sa",
    "addr:street":"Tetnall Street",
    "iso:country":"GB",
    "sg:address":"Tetnall Street",
    "sg:city":"Dudley",
    "sg:classifiers":[
        {
            "category":"Home & Garden",
            "subcategory":"Home Furnishings",
            "type":"Retail Goods"
        }
    ],
    "sg:phone":"+44 1384 255523",
    "sg:postcode":"DY2 8SA",
    "sg:province":"West Midlands",
    "sg:tags":[
        "awning",
        "canopy",
        "blinds"
    ],
    "wof:name":"Cresta (Blinds) Ltd.",
    "wof:placetype":"venue"
},
  "geometry": {"coordinates":[-2.0809469223,52.5063362122],"type":"Point"}
}