{
  "type": "Feature",
  "properties": {
    "addr:full":"Salisbury Lodge Berkeley Gloucestershire GL13 9QJ",
    "addr:postcode":"gl13 9qj",
    "iso:country":"GB",
    "sg:address":"Salisbury Lodge",
    "sg:city":"Berkeley",
    "sg:classifiers":[
        {
            "category":"Professional",
            "subcategory":"Art Services",
            "type":"Services"
        }
    ],
    "sg:phone":"+44 1453 511086",
    "sg:postcode":"GL13 9QJ",
    "sg:province":"Gloucestershire",
    "sg:tags":[
        "graphic",
        "designer"
    ],
    "wof:name":"Digital Designs",
    "wof:placetype":"venue"
},
  "geometry": {"coordinates":[-2.4595689774,51.6931877136],"type":"Point"}
}