{
  "type": "Feature",
  "properties": {
    "iso:country":"GB",
    "sg:address":"Foel Farm",
    "sg:city":"Newcastle Emlyn",
    "sg:classifiers":[
        {
            "category":"Farming",
            "subcategory":"Farm",
            "type":"Manufacturing & Wholesale Goods"
        }
    ],
    "sg:phone":"+44 1239 710970",
    "sg:postcode":"SA38 9RH",
    "sg:province":"Carmarthenshire",
    "sg:tags":[
        "mixed",
        "crop"
    ],
    "wof:name":"S C Benner",
    "wof:placetype":"venue"
},
  "geometry": {"coordinates":[-4.467984,52.035919],"type":"Point"}
}